package burp;

import java.math.BigInteger;

class Zs4v extends ClassLoader {
  static Object ZB;
  
  static String Za;
  
  private static final String[] a;
  
  private static final String[] b;
  
  static void Zc(Object[] paramArrayOfObject, Object paramObject) throws Throwable {}
  
  static void Zg(Object paramObject) {
    Zlqy.ZZ = a(2574, -29210);
    Zlqy.ZP = new BigInteger(a(2573, -32444));
    boolean bool = Zt2e.ZN();
    try {
      try {
        if (Zm6g.ZG.charAt(Math.abs(((BigInteger)Zm6g.ZO).intValue() % 32)) > Zluk.ZW.charAt(Math.abs(((BigInteger)Zeyd.Zl).intValue() % 32))) {
          try {
            Zx0t.ZH(Class.forName(a(2569, -20917)));
            if (!bool)
              Zlo5.Zy(Class.forName(a(2568, 7389))); 
          } catch (Throwable throwable) {
            throw a(null);
          } 
          return;
        } 
      } catch (Throwable throwable) {
        throw a(null);
      } 
      Zlo5.Zy(Class.forName(a(2568, 7389)));
    } catch (Throwable throwable) {}
  }
  
  static boolean Zo(Object[] paramArrayOfObject, Object paramObject) throws Throwable {
    // Byte code:
    //   0: invokestatic ZK : ()Z
    //   3: istore_2
    //   4: getstatic burp/Zr_w.ZK : Ljava/lang/Object;
    //   7: checkcast java/math/BigInteger
    //   10: invokevirtual toByteArray : ()[B
    //   13: astore_3
    //   14: bipush #32
    //   16: newarray int
    //   18: dup
    //   19: iconst_0
    //   20: ldc 943331329
    //   22: iastore
    //   23: dup
    //   24: iconst_1
    //   25: ldc 170788368
    //   27: iastore
    //   28: dup
    //   29: iconst_2
    //   30: ldc 1008414755
    //   32: iastore
    //   33: dup
    //   34: iconst_3
    //   35: ldc 187049985
    //   37: iastore
    //   38: dup
    //   39: iconst_4
    //   40: ldc 1010368540
    //   42: iastore
    //   43: dup
    //   44: iconst_5
    //   45: ldc 220604441
    //   47: iastore
    //   48: dup
    //   49: bipush #6
    //   51: ldc 940377620
    //   53: iastore
    //   54: dup
    //   55: bipush #7
    //   57: ldc 255209728
    //   59: iastore
    //   60: dup
    //   61: bipush #8
    //   63: ldc 689771012
    //   65: iastore
    //   66: dup
    //   67: bipush #9
    //   69: ldc 221709344
    //   71: iastore
    //   72: dup
    //   73: bipush #10
    //   75: ldc 957157408
    //   77: iastore
    //   78: dup
    //   79: bipush #11
    //   81: ldc 892536332
    //   83: iastore
    //   84: dup
    //   85: bipush #12
    //   87: ldc 722417666
    //   89: iastore
    //   90: dup
    //   91: bipush #13
    //   93: ldc 1026621720
    //   95: iastore
    //   96: dup
    //   97: bipush #14
    //   99: ldc 655302664
    //   101: iastore
    //   102: dup
    //   103: bipush #15
    //   105: ldc 890966315
    //   107: iastore
    //   108: dup
    //   109: bipush #16
    //   111: ldc 187632156
    //   113: iastore
    //   114: dup
    //   115: bipush #17
    //   117: ldc 874189824
    //   119: iastore
    //   120: dup
    //   121: bipush #18
    //   123: ldc 254150144
    //   125: iastore
    //   126: dup
    //   127: bipush #19
    //   129: ldc 924386310
    //   131: iastore
    //   132: dup
    //   133: bipush #20
    //   135: ldc 121057538
    //   137: iastore
    //   138: dup
    //   139: bipush #21
    //   141: ldc 840500228
    //   143: iastore
    //   144: dup
    //   145: bipush #22
    //   147: ldc 389160971
    //   149: iastore
    //   150: dup
    //   151: bipush #23
    //   153: ldc 907870729
    //   155: iastore
    //   156: dup
    //   157: bipush #24
    //   159: ldc 389426184
    //   161: iastore
    //   162: dup
    //   163: bipush #25
    //   165: ldc 973875457
    //   167: iastore
    //   168: dup
    //   169: bipush #26
    //   171: ldc 372376604
    //   173: iastore
    //   174: dup
    //   175: bipush #27
    //   177: ldc 707731490
    //   179: iastore
    //   180: dup
    //   181: bipush #28
    //   183: ldc 1043334948
    //   185: iastore
    //   186: dup
    //   187: bipush #29
    //   189: ldc 439222784
    //   191: iastore
    //   192: dup
    //   193: bipush #30
    //   195: ldc 876216579
    //   197: iastore
    //   198: dup
    //   199: bipush #31
    //   201: ldc 455999525
    //   203: iastore
    //   204: astore #5
    //   206: bipush #8
    //   208: aload_3
    //   209: arraylength
    //   210: bipush #8
    //   212: irem
    //   213: isub
    //   214: istore #6
    //   216: aload_3
    //   217: arraylength
    //   218: iload #6
    //   220: iadd
    //   221: newarray byte
    //   223: astore #7
    //   225: iconst_0
    //   226: istore #8
    //   228: iload #8
    //   230: aload_3
    //   231: arraylength
    //   232: if_icmpge -> 251
    //   235: aload #7
    //   237: iload #8
    //   239: aload_3
    //   240: iload #8
    //   242: baload
    //   243: bastore
    //   244: iinc #8, 1
    //   247: iload_2
    //   248: ifeq -> 228
    //   251: aload_3
    //   252: arraylength
    //   253: istore #8
    //   255: iload #8
    //   257: aload #7
    //   259: arraylength
    //   260: if_icmpge -> 278
    //   263: aload #7
    //   265: iload #8
    //   267: iload #6
    //   269: i2b
    //   270: bastore
    //   271: iinc #8, 1
    //   274: iload_2
    //   275: ifeq -> 255
    //   278: aload #7
    //   280: astore_3
    //   281: bipush #64
    //   283: newarray int
    //   285: dup
    //   286: iconst_0
    //   287: ldc 16843776
    //   289: iastore
    //   290: dup
    //   291: iconst_1
    //   292: iconst_0
    //   293: iastore
    //   294: dup
    //   295: iconst_2
    //   296: ldc 65536
    //   298: iastore
    //   299: dup
    //   300: iconst_3
    //   301: ldc 16843780
    //   303: iastore
    //   304: dup
    //   305: iconst_4
    //   306: ldc 16842756
    //   308: iastore
    //   309: dup
    //   310: iconst_5
    //   311: ldc 66564
    //   313: iastore
    //   314: dup
    //   315: bipush #6
    //   317: iconst_4
    //   318: iastore
    //   319: dup
    //   320: bipush #7
    //   322: ldc 65536
    //   324: iastore
    //   325: dup
    //   326: bipush #8
    //   328: sipush #1024
    //   331: iastore
    //   332: dup
    //   333: bipush #9
    //   335: ldc 16843776
    //   337: iastore
    //   338: dup
    //   339: bipush #10
    //   341: ldc 16843780
    //   343: iastore
    //   344: dup
    //   345: bipush #11
    //   347: sipush #1024
    //   350: iastore
    //   351: dup
    //   352: bipush #12
    //   354: ldc 16778244
    //   356: iastore
    //   357: dup
    //   358: bipush #13
    //   360: ldc 16842756
    //   362: iastore
    //   363: dup
    //   364: bipush #14
    //   366: ldc 16777216
    //   368: iastore
    //   369: dup
    //   370: bipush #15
    //   372: iconst_4
    //   373: iastore
    //   374: dup
    //   375: bipush #16
    //   377: sipush #1028
    //   380: iastore
    //   381: dup
    //   382: bipush #17
    //   384: ldc 16778240
    //   386: iastore
    //   387: dup
    //   388: bipush #18
    //   390: ldc 16778240
    //   392: iastore
    //   393: dup
    //   394: bipush #19
    //   396: ldc 66560
    //   398: iastore
    //   399: dup
    //   400: bipush #20
    //   402: ldc 66560
    //   404: iastore
    //   405: dup
    //   406: bipush #21
    //   408: ldc 16842752
    //   410: iastore
    //   411: dup
    //   412: bipush #22
    //   414: ldc 16842752
    //   416: iastore
    //   417: dup
    //   418: bipush #23
    //   420: ldc 16778244
    //   422: iastore
    //   423: dup
    //   424: bipush #24
    //   426: ldc 65540
    //   428: iastore
    //   429: dup
    //   430: bipush #25
    //   432: ldc 16777220
    //   434: iastore
    //   435: dup
    //   436: bipush #26
    //   438: ldc 16777220
    //   440: iastore
    //   441: dup
    //   442: bipush #27
    //   444: ldc 65540
    //   446: iastore
    //   447: dup
    //   448: bipush #28
    //   450: iconst_0
    //   451: iastore
    //   452: dup
    //   453: bipush #29
    //   455: sipush #1028
    //   458: iastore
    //   459: dup
    //   460: bipush #30
    //   462: ldc 66564
    //   464: iastore
    //   465: dup
    //   466: bipush #31
    //   468: ldc 16777216
    //   470: iastore
    //   471: dup
    //   472: bipush #32
    //   474: ldc 65536
    //   476: iastore
    //   477: dup
    //   478: bipush #33
    //   480: ldc 16843780
    //   482: iastore
    //   483: dup
    //   484: bipush #34
    //   486: iconst_4
    //   487: iastore
    //   488: dup
    //   489: bipush #35
    //   491: ldc 16842752
    //   493: iastore
    //   494: dup
    //   495: bipush #36
    //   497: ldc 16843776
    //   499: iastore
    //   500: dup
    //   501: bipush #37
    //   503: ldc 16777216
    //   505: iastore
    //   506: dup
    //   507: bipush #38
    //   509: ldc 16777216
    //   511: iastore
    //   512: dup
    //   513: bipush #39
    //   515: sipush #1024
    //   518: iastore
    //   519: dup
    //   520: bipush #40
    //   522: ldc 16842756
    //   524: iastore
    //   525: dup
    //   526: bipush #41
    //   528: ldc 65536
    //   530: iastore
    //   531: dup
    //   532: bipush #42
    //   534: ldc 66560
    //   536: iastore
    //   537: dup
    //   538: bipush #43
    //   540: ldc 16777220
    //   542: iastore
    //   543: dup
    //   544: bipush #44
    //   546: sipush #1024
    //   549: iastore
    //   550: dup
    //   551: bipush #45
    //   553: iconst_4
    //   554: iastore
    //   555: dup
    //   556: bipush #46
    //   558: ldc 16778244
    //   560: iastore
    //   561: dup
    //   562: bipush #47
    //   564: ldc 66564
    //   566: iastore
    //   567: dup
    //   568: bipush #48
    //   570: ldc 16843780
    //   572: iastore
    //   573: dup
    //   574: bipush #49
    //   576: ldc 65540
    //   578: iastore
    //   579: dup
    //   580: bipush #50
    //   582: ldc 16842752
    //   584: iastore
    //   585: dup
    //   586: bipush #51
    //   588: ldc 16778244
    //   590: iastore
    //   591: dup
    //   592: bipush #52
    //   594: ldc 16777220
    //   596: iastore
    //   597: dup
    //   598: bipush #53
    //   600: sipush #1028
    //   603: iastore
    //   604: dup
    //   605: bipush #54
    //   607: ldc 66564
    //   609: iastore
    //   610: dup
    //   611: bipush #55
    //   613: ldc 16843776
    //   615: iastore
    //   616: dup
    //   617: bipush #56
    //   619: sipush #1028
    //   622: iastore
    //   623: dup
    //   624: bipush #57
    //   626: ldc 16778240
    //   628: iastore
    //   629: dup
    //   630: bipush #58
    //   632: ldc 16778240
    //   634: iastore
    //   635: dup
    //   636: bipush #59
    //   638: iconst_0
    //   639: iastore
    //   640: dup
    //   641: bipush #60
    //   643: ldc 65540
    //   645: iastore
    //   646: dup
    //   647: bipush #61
    //   649: ldc 66560
    //   651: iastore
    //   652: dup
    //   653: bipush #62
    //   655: iconst_0
    //   656: iastore
    //   657: dup
    //   658: bipush #63
    //   660: ldc 16842756
    //   662: iastore
    //   663: astore #8
    //   665: bipush #64
    //   667: newarray int
    //   669: dup
    //   670: iconst_0
    //   671: ldc -2146402272
    //   673: iastore
    //   674: dup
    //   675: iconst_1
    //   676: ldc -2147450880
    //   678: iastore
    //   679: dup
    //   680: iconst_2
    //   681: ldc 32768
    //   683: iastore
    //   684: dup
    //   685: iconst_3
    //   686: ldc 1081376
    //   688: iastore
    //   689: dup
    //   690: iconst_4
    //   691: ldc 1048576
    //   693: iastore
    //   694: dup
    //   695: iconst_5
    //   696: bipush #32
    //   698: iastore
    //   699: dup
    //   700: bipush #6
    //   702: ldc -2146435040
    //   704: iastore
    //   705: dup
    //   706: bipush #7
    //   708: ldc -2147450848
    //   710: iastore
    //   711: dup
    //   712: bipush #8
    //   714: ldc -2147483616
    //   716: iastore
    //   717: dup
    //   718: bipush #9
    //   720: ldc -2146402272
    //   722: iastore
    //   723: dup
    //   724: bipush #10
    //   726: ldc -2146402304
    //   728: iastore
    //   729: dup
    //   730: bipush #11
    //   732: ldc -2147483648
    //   734: iastore
    //   735: dup
    //   736: bipush #12
    //   738: ldc -2147450880
    //   740: iastore
    //   741: dup
    //   742: bipush #13
    //   744: ldc 1048576
    //   746: iastore
    //   747: dup
    //   748: bipush #14
    //   750: bipush #32
    //   752: iastore
    //   753: dup
    //   754: bipush #15
    //   756: ldc -2146435040
    //   758: iastore
    //   759: dup
    //   760: bipush #16
    //   762: ldc 1081344
    //   764: iastore
    //   765: dup
    //   766: bipush #17
    //   768: ldc 1048608
    //   770: iastore
    //   771: dup
    //   772: bipush #18
    //   774: ldc -2147450848
    //   776: iastore
    //   777: dup
    //   778: bipush #19
    //   780: iconst_0
    //   781: iastore
    //   782: dup
    //   783: bipush #20
    //   785: ldc -2147483648
    //   787: iastore
    //   788: dup
    //   789: bipush #21
    //   791: ldc 32768
    //   793: iastore
    //   794: dup
    //   795: bipush #22
    //   797: ldc 1081376
    //   799: iastore
    //   800: dup
    //   801: bipush #23
    //   803: ldc -2146435072
    //   805: iastore
    //   806: dup
    //   807: bipush #24
    //   809: ldc 1048608
    //   811: iastore
    //   812: dup
    //   813: bipush #25
    //   815: ldc -2147483616
    //   817: iastore
    //   818: dup
    //   819: bipush #26
    //   821: iconst_0
    //   822: iastore
    //   823: dup
    //   824: bipush #27
    //   826: ldc 1081344
    //   828: iastore
    //   829: dup
    //   830: bipush #28
    //   832: ldc 32800
    //   834: iastore
    //   835: dup
    //   836: bipush #29
    //   838: ldc -2146402304
    //   840: iastore
    //   841: dup
    //   842: bipush #30
    //   844: ldc -2146435072
    //   846: iastore
    //   847: dup
    //   848: bipush #31
    //   850: ldc 32800
    //   852: iastore
    //   853: dup
    //   854: bipush #32
    //   856: iconst_0
    //   857: iastore
    //   858: dup
    //   859: bipush #33
    //   861: ldc 1081376
    //   863: iastore
    //   864: dup
    //   865: bipush #34
    //   867: ldc -2146435040
    //   869: iastore
    //   870: dup
    //   871: bipush #35
    //   873: ldc 1048576
    //   875: iastore
    //   876: dup
    //   877: bipush #36
    //   879: ldc -2147450848
    //   881: iastore
    //   882: dup
    //   883: bipush #37
    //   885: ldc -2146435072
    //   887: iastore
    //   888: dup
    //   889: bipush #38
    //   891: ldc -2146402304
    //   893: iastore
    //   894: dup
    //   895: bipush #39
    //   897: ldc 32768
    //   899: iastore
    //   900: dup
    //   901: bipush #40
    //   903: ldc -2146435072
    //   905: iastore
    //   906: dup
    //   907: bipush #41
    //   909: ldc -2147450880
    //   911: iastore
    //   912: dup
    //   913: bipush #42
    //   915: bipush #32
    //   917: iastore
    //   918: dup
    //   919: bipush #43
    //   921: ldc -2146402272
    //   923: iastore
    //   924: dup
    //   925: bipush #44
    //   927: ldc 1081376
    //   929: iastore
    //   930: dup
    //   931: bipush #45
    //   933: bipush #32
    //   935: iastore
    //   936: dup
    //   937: bipush #46
    //   939: ldc 32768
    //   941: iastore
    //   942: dup
    //   943: bipush #47
    //   945: ldc -2147483648
    //   947: iastore
    //   948: dup
    //   949: bipush #48
    //   951: ldc 32800
    //   953: iastore
    //   954: dup
    //   955: bipush #49
    //   957: ldc -2146402304
    //   959: iastore
    //   960: dup
    //   961: bipush #50
    //   963: ldc 1048576
    //   965: iastore
    //   966: dup
    //   967: bipush #51
    //   969: ldc -2147483616
    //   971: iastore
    //   972: dup
    //   973: bipush #52
    //   975: ldc 1048608
    //   977: iastore
    //   978: dup
    //   979: bipush #53
    //   981: ldc -2147450848
    //   983: iastore
    //   984: dup
    //   985: bipush #54
    //   987: ldc -2147483616
    //   989: iastore
    //   990: dup
    //   991: bipush #55
    //   993: ldc 1048608
    //   995: iastore
    //   996: dup
    //   997: bipush #56
    //   999: ldc 1081344
    //   1001: iastore
    //   1002: dup
    //   1003: bipush #57
    //   1005: iconst_0
    //   1006: iastore
    //   1007: dup
    //   1008: bipush #58
    //   1010: ldc -2147450880
    //   1012: iastore
    //   1013: dup
    //   1014: bipush #59
    //   1016: ldc 32800
    //   1018: iastore
    //   1019: dup
    //   1020: bipush #60
    //   1022: ldc -2147483648
    //   1024: iastore
    //   1025: dup
    //   1026: bipush #61
    //   1028: ldc -2146435040
    //   1030: iastore
    //   1031: dup
    //   1032: bipush #62
    //   1034: ldc -2146402272
    //   1036: iastore
    //   1037: dup
    //   1038: bipush #63
    //   1040: ldc 1081344
    //   1042: iastore
    //   1043: astore #9
    //   1045: bipush #64
    //   1047: newarray int
    //   1049: dup
    //   1050: iconst_0
    //   1051: sipush #520
    //   1054: iastore
    //   1055: dup
    //   1056: iconst_1
    //   1057: ldc 134349312
    //   1059: iastore
    //   1060: dup
    //   1061: iconst_2
    //   1062: iconst_0
    //   1063: iastore
    //   1064: dup
    //   1065: iconst_3
    //   1066: ldc 134348808
    //   1068: iastore
    //   1069: dup
    //   1070: iconst_4
    //   1071: ldc 134218240
    //   1073: iastore
    //   1074: dup
    //   1075: iconst_5
    //   1076: iconst_0
    //   1077: iastore
    //   1078: dup
    //   1079: bipush #6
    //   1081: ldc 131592
    //   1083: iastore
    //   1084: dup
    //   1085: bipush #7
    //   1087: ldc 134218240
    //   1089: iastore
    //   1090: dup
    //   1091: bipush #8
    //   1093: ldc 131080
    //   1095: iastore
    //   1096: dup
    //   1097: bipush #9
    //   1099: ldc 134217736
    //   1101: iastore
    //   1102: dup
    //   1103: bipush #10
    //   1105: ldc 134217736
    //   1107: iastore
    //   1108: dup
    //   1109: bipush #11
    //   1111: ldc 131072
    //   1113: iastore
    //   1114: dup
    //   1115: bipush #12
    //   1117: ldc 134349320
    //   1119: iastore
    //   1120: dup
    //   1121: bipush #13
    //   1123: ldc 131080
    //   1125: iastore
    //   1126: dup
    //   1127: bipush #14
    //   1129: ldc 134348800
    //   1131: iastore
    //   1132: dup
    //   1133: bipush #15
    //   1135: sipush #520
    //   1138: iastore
    //   1139: dup
    //   1140: bipush #16
    //   1142: ldc 134217728
    //   1144: iastore
    //   1145: dup
    //   1146: bipush #17
    //   1148: bipush #8
    //   1150: iastore
    //   1151: dup
    //   1152: bipush #18
    //   1154: ldc 134349312
    //   1156: iastore
    //   1157: dup
    //   1158: bipush #19
    //   1160: sipush #512
    //   1163: iastore
    //   1164: dup
    //   1165: bipush #20
    //   1167: ldc 131584
    //   1169: iastore
    //   1170: dup
    //   1171: bipush #21
    //   1173: ldc 134348800
    //   1175: iastore
    //   1176: dup
    //   1177: bipush #22
    //   1179: ldc 134348808
    //   1181: iastore
    //   1182: dup
    //   1183: bipush #23
    //   1185: ldc 131592
    //   1187: iastore
    //   1188: dup
    //   1189: bipush #24
    //   1191: ldc 134218248
    //   1193: iastore
    //   1194: dup
    //   1195: bipush #25
    //   1197: ldc 131584
    //   1199: iastore
    //   1200: dup
    //   1201: bipush #26
    //   1203: ldc 131072
    //   1205: iastore
    //   1206: dup
    //   1207: bipush #27
    //   1209: ldc 134218248
    //   1211: iastore
    //   1212: dup
    //   1213: bipush #28
    //   1215: bipush #8
    //   1217: iastore
    //   1218: dup
    //   1219: bipush #29
    //   1221: ldc 134349320
    //   1223: iastore
    //   1224: dup
    //   1225: bipush #30
    //   1227: sipush #512
    //   1230: iastore
    //   1231: dup
    //   1232: bipush #31
    //   1234: ldc 134217728
    //   1236: iastore
    //   1237: dup
    //   1238: bipush #32
    //   1240: ldc 134349312
    //   1242: iastore
    //   1243: dup
    //   1244: bipush #33
    //   1246: ldc 134217728
    //   1248: iastore
    //   1249: dup
    //   1250: bipush #34
    //   1252: ldc 131080
    //   1254: iastore
    //   1255: dup
    //   1256: bipush #35
    //   1258: sipush #520
    //   1261: iastore
    //   1262: dup
    //   1263: bipush #36
    //   1265: ldc 131072
    //   1267: iastore
    //   1268: dup
    //   1269: bipush #37
    //   1271: ldc 134349312
    //   1273: iastore
    //   1274: dup
    //   1275: bipush #38
    //   1277: ldc 134218240
    //   1279: iastore
    //   1280: dup
    //   1281: bipush #39
    //   1283: iconst_0
    //   1284: iastore
    //   1285: dup
    //   1286: bipush #40
    //   1288: sipush #512
    //   1291: iastore
    //   1292: dup
    //   1293: bipush #41
    //   1295: ldc 131080
    //   1297: iastore
    //   1298: dup
    //   1299: bipush #42
    //   1301: ldc 134349320
    //   1303: iastore
    //   1304: dup
    //   1305: bipush #43
    //   1307: ldc 134218240
    //   1309: iastore
    //   1310: dup
    //   1311: bipush #44
    //   1313: ldc 134217736
    //   1315: iastore
    //   1316: dup
    //   1317: bipush #45
    //   1319: sipush #512
    //   1322: iastore
    //   1323: dup
    //   1324: bipush #46
    //   1326: iconst_0
    //   1327: iastore
    //   1328: dup
    //   1329: bipush #47
    //   1331: ldc 134348808
    //   1333: iastore
    //   1334: dup
    //   1335: bipush #48
    //   1337: ldc 134218248
    //   1339: iastore
    //   1340: dup
    //   1341: bipush #49
    //   1343: ldc 131072
    //   1345: iastore
    //   1346: dup
    //   1347: bipush #50
    //   1349: ldc 134217728
    //   1351: iastore
    //   1352: dup
    //   1353: bipush #51
    //   1355: ldc 134349320
    //   1357: iastore
    //   1358: dup
    //   1359: bipush #52
    //   1361: bipush #8
    //   1363: iastore
    //   1364: dup
    //   1365: bipush #53
    //   1367: ldc 131592
    //   1369: iastore
    //   1370: dup
    //   1371: bipush #54
    //   1373: ldc 131584
    //   1375: iastore
    //   1376: dup
    //   1377: bipush #55
    //   1379: ldc 134217736
    //   1381: iastore
    //   1382: dup
    //   1383: bipush #56
    //   1385: ldc 134348800
    //   1387: iastore
    //   1388: dup
    //   1389: bipush #57
    //   1391: ldc 134218248
    //   1393: iastore
    //   1394: dup
    //   1395: bipush #58
    //   1397: sipush #520
    //   1400: iastore
    //   1401: dup
    //   1402: bipush #59
    //   1404: ldc 134348800
    //   1406: iastore
    //   1407: dup
    //   1408: bipush #60
    //   1410: ldc 131592
    //   1412: iastore
    //   1413: dup
    //   1414: bipush #61
    //   1416: bipush #8
    //   1418: iastore
    //   1419: dup
    //   1420: bipush #62
    //   1422: ldc 134348808
    //   1424: iastore
    //   1425: dup
    //   1426: bipush #63
    //   1428: ldc 131584
    //   1430: iastore
    //   1431: astore #10
    //   1433: bipush #64
    //   1435: newarray int
    //   1437: dup
    //   1438: iconst_0
    //   1439: ldc 8396801
    //   1441: iastore
    //   1442: dup
    //   1443: iconst_1
    //   1444: sipush #8321
    //   1447: iastore
    //   1448: dup
    //   1449: iconst_2
    //   1450: sipush #8321
    //   1453: iastore
    //   1454: dup
    //   1455: iconst_3
    //   1456: sipush #128
    //   1459: iastore
    //   1460: dup
    //   1461: iconst_4
    //   1462: ldc 8396928
    //   1464: iastore
    //   1465: dup
    //   1466: iconst_5
    //   1467: ldc 8388737
    //   1469: iastore
    //   1470: dup
    //   1471: bipush #6
    //   1473: ldc 8388609
    //   1475: iastore
    //   1476: dup
    //   1477: bipush #7
    //   1479: sipush #8193
    //   1482: iastore
    //   1483: dup
    //   1484: bipush #8
    //   1486: iconst_0
    //   1487: iastore
    //   1488: dup
    //   1489: bipush #9
    //   1491: ldc 8396800
    //   1493: iastore
    //   1494: dup
    //   1495: bipush #10
    //   1497: ldc 8396800
    //   1499: iastore
    //   1500: dup
    //   1501: bipush #11
    //   1503: ldc 8396929
    //   1505: iastore
    //   1506: dup
    //   1507: bipush #12
    //   1509: sipush #129
    //   1512: iastore
    //   1513: dup
    //   1514: bipush #13
    //   1516: iconst_0
    //   1517: iastore
    //   1518: dup
    //   1519: bipush #14
    //   1521: ldc 8388736
    //   1523: iastore
    //   1524: dup
    //   1525: bipush #15
    //   1527: ldc 8388609
    //   1529: iastore
    //   1530: dup
    //   1531: bipush #16
    //   1533: iconst_1
    //   1534: iastore
    //   1535: dup
    //   1536: bipush #17
    //   1538: sipush #8192
    //   1541: iastore
    //   1542: dup
    //   1543: bipush #18
    //   1545: ldc 8388608
    //   1547: iastore
    //   1548: dup
    //   1549: bipush #19
    //   1551: ldc 8396801
    //   1553: iastore
    //   1554: dup
    //   1555: bipush #20
    //   1557: sipush #128
    //   1560: iastore
    //   1561: dup
    //   1562: bipush #21
    //   1564: ldc 8388608
    //   1566: iastore
    //   1567: dup
    //   1568: bipush #22
    //   1570: sipush #8193
    //   1573: iastore
    //   1574: dup
    //   1575: bipush #23
    //   1577: sipush #8320
    //   1580: iastore
    //   1581: dup
    //   1582: bipush #24
    //   1584: ldc 8388737
    //   1586: iastore
    //   1587: dup
    //   1588: bipush #25
    //   1590: iconst_1
    //   1591: iastore
    //   1592: dup
    //   1593: bipush #26
    //   1595: sipush #8320
    //   1598: iastore
    //   1599: dup
    //   1600: bipush #27
    //   1602: ldc 8388736
    //   1604: iastore
    //   1605: dup
    //   1606: bipush #28
    //   1608: sipush #8192
    //   1611: iastore
    //   1612: dup
    //   1613: bipush #29
    //   1615: ldc 8396928
    //   1617: iastore
    //   1618: dup
    //   1619: bipush #30
    //   1621: ldc 8396929
    //   1623: iastore
    //   1624: dup
    //   1625: bipush #31
    //   1627: sipush #129
    //   1630: iastore
    //   1631: dup
    //   1632: bipush #32
    //   1634: ldc 8388736
    //   1636: iastore
    //   1637: dup
    //   1638: bipush #33
    //   1640: ldc 8388609
    //   1642: iastore
    //   1643: dup
    //   1644: bipush #34
    //   1646: ldc 8396800
    //   1648: iastore
    //   1649: dup
    //   1650: bipush #35
    //   1652: ldc 8396929
    //   1654: iastore
    //   1655: dup
    //   1656: bipush #36
    //   1658: sipush #129
    //   1661: iastore
    //   1662: dup
    //   1663: bipush #37
    //   1665: iconst_0
    //   1666: iastore
    //   1667: dup
    //   1668: bipush #38
    //   1670: iconst_0
    //   1671: iastore
    //   1672: dup
    //   1673: bipush #39
    //   1675: ldc 8396800
    //   1677: iastore
    //   1678: dup
    //   1679: bipush #40
    //   1681: sipush #8320
    //   1684: iastore
    //   1685: dup
    //   1686: bipush #41
    //   1688: ldc 8388736
    //   1690: iastore
    //   1691: dup
    //   1692: bipush #42
    //   1694: ldc 8388737
    //   1696: iastore
    //   1697: dup
    //   1698: bipush #43
    //   1700: iconst_1
    //   1701: iastore
    //   1702: dup
    //   1703: bipush #44
    //   1705: ldc 8396801
    //   1707: iastore
    //   1708: dup
    //   1709: bipush #45
    //   1711: sipush #8321
    //   1714: iastore
    //   1715: dup
    //   1716: bipush #46
    //   1718: sipush #8321
    //   1721: iastore
    //   1722: dup
    //   1723: bipush #47
    //   1725: sipush #128
    //   1728: iastore
    //   1729: dup
    //   1730: bipush #48
    //   1732: ldc 8396929
    //   1734: iastore
    //   1735: dup
    //   1736: bipush #49
    //   1738: sipush #129
    //   1741: iastore
    //   1742: dup
    //   1743: bipush #50
    //   1745: iconst_1
    //   1746: iastore
    //   1747: dup
    //   1748: bipush #51
    //   1750: sipush #8192
    //   1753: iastore
    //   1754: dup
    //   1755: bipush #52
    //   1757: ldc 8388609
    //   1759: iastore
    //   1760: dup
    //   1761: bipush #53
    //   1763: sipush #8193
    //   1766: iastore
    //   1767: dup
    //   1768: bipush #54
    //   1770: ldc 8396928
    //   1772: iastore
    //   1773: dup
    //   1774: bipush #55
    //   1776: ldc 8388737
    //   1778: iastore
    //   1779: dup
    //   1780: bipush #56
    //   1782: sipush #8193
    //   1785: iastore
    //   1786: dup
    //   1787: bipush #57
    //   1789: sipush #8320
    //   1792: iastore
    //   1793: dup
    //   1794: bipush #58
    //   1796: ldc 8388608
    //   1798: iastore
    //   1799: dup
    //   1800: bipush #59
    //   1802: ldc 8396801
    //   1804: iastore
    //   1805: dup
    //   1806: bipush #60
    //   1808: sipush #128
    //   1811: iastore
    //   1812: dup
    //   1813: bipush #61
    //   1815: ldc 8388608
    //   1817: iastore
    //   1818: dup
    //   1819: bipush #62
    //   1821: sipush #8192
    //   1824: iastore
    //   1825: dup
    //   1826: bipush #63
    //   1828: ldc 8396928
    //   1830: iastore
    //   1831: astore #11
    //   1833: bipush #64
    //   1835: newarray int
    //   1837: dup
    //   1838: iconst_0
    //   1839: sipush #256
    //   1842: iastore
    //   1843: dup
    //   1844: iconst_1
    //   1845: ldc 34078976
    //   1847: iastore
    //   1848: dup
    //   1849: iconst_2
    //   1850: ldc 34078720
    //   1852: iastore
    //   1853: dup
    //   1854: iconst_3
    //   1855: ldc 1107296512
    //   1857: iastore
    //   1858: dup
    //   1859: iconst_4
    //   1860: ldc 524288
    //   1862: iastore
    //   1863: dup
    //   1864: iconst_5
    //   1865: sipush #256
    //   1868: iastore
    //   1869: dup
    //   1870: bipush #6
    //   1872: ldc 1073741824
    //   1874: iastore
    //   1875: dup
    //   1876: bipush #7
    //   1878: ldc 34078720
    //   1880: iastore
    //   1881: dup
    //   1882: bipush #8
    //   1884: ldc 1074266368
    //   1886: iastore
    //   1887: dup
    //   1888: bipush #9
    //   1890: ldc 524288
    //   1892: iastore
    //   1893: dup
    //   1894: bipush #10
    //   1896: ldc 33554688
    //   1898: iastore
    //   1899: dup
    //   1900: bipush #11
    //   1902: ldc 1074266368
    //   1904: iastore
    //   1905: dup
    //   1906: bipush #12
    //   1908: ldc 1107296512
    //   1910: iastore
    //   1911: dup
    //   1912: bipush #13
    //   1914: ldc 1107820544
    //   1916: iastore
    //   1917: dup
    //   1918: bipush #14
    //   1920: ldc 524544
    //   1922: iastore
    //   1923: dup
    //   1924: bipush #15
    //   1926: ldc 1073741824
    //   1928: iastore
    //   1929: dup
    //   1930: bipush #16
    //   1932: ldc 33554432
    //   1934: iastore
    //   1935: dup
    //   1936: bipush #17
    //   1938: ldc 1074266112
    //   1940: iastore
    //   1941: dup
    //   1942: bipush #18
    //   1944: ldc 1074266112
    //   1946: iastore
    //   1947: dup
    //   1948: bipush #19
    //   1950: iconst_0
    //   1951: iastore
    //   1952: dup
    //   1953: bipush #20
    //   1955: ldc 1073742080
    //   1957: iastore
    //   1958: dup
    //   1959: bipush #21
    //   1961: ldc 1107820800
    //   1963: iastore
    //   1964: dup
    //   1965: bipush #22
    //   1967: ldc 1107820800
    //   1969: iastore
    //   1970: dup
    //   1971: bipush #23
    //   1973: ldc 33554688
    //   1975: iastore
    //   1976: dup
    //   1977: bipush #24
    //   1979: ldc 1107820544
    //   1981: iastore
    //   1982: dup
    //   1983: bipush #25
    //   1985: ldc 1073742080
    //   1987: iastore
    //   1988: dup
    //   1989: bipush #26
    //   1991: iconst_0
    //   1992: iastore
    //   1993: dup
    //   1994: bipush #27
    //   1996: ldc 1107296256
    //   1998: iastore
    //   1999: dup
    //   2000: bipush #28
    //   2002: ldc 34078976
    //   2004: iastore
    //   2005: dup
    //   2006: bipush #29
    //   2008: ldc 33554432
    //   2010: iastore
    //   2011: dup
    //   2012: bipush #30
    //   2014: ldc 1107296256
    //   2016: iastore
    //   2017: dup
    //   2018: bipush #31
    //   2020: ldc 524544
    //   2022: iastore
    //   2023: dup
    //   2024: bipush #32
    //   2026: ldc 524288
    //   2028: iastore
    //   2029: dup
    //   2030: bipush #33
    //   2032: ldc 1107296512
    //   2034: iastore
    //   2035: dup
    //   2036: bipush #34
    //   2038: sipush #256
    //   2041: iastore
    //   2042: dup
    //   2043: bipush #35
    //   2045: ldc 33554432
    //   2047: iastore
    //   2048: dup
    //   2049: bipush #36
    //   2051: ldc 1073741824
    //   2053: iastore
    //   2054: dup
    //   2055: bipush #37
    //   2057: ldc 34078720
    //   2059: iastore
    //   2060: dup
    //   2061: bipush #38
    //   2063: ldc 1107296512
    //   2065: iastore
    //   2066: dup
    //   2067: bipush #39
    //   2069: ldc 1074266368
    //   2071: iastore
    //   2072: dup
    //   2073: bipush #40
    //   2075: ldc 33554688
    //   2077: iastore
    //   2078: dup
    //   2079: bipush #41
    //   2081: ldc 1073741824
    //   2083: iastore
    //   2084: dup
    //   2085: bipush #42
    //   2087: ldc 1107820544
    //   2089: iastore
    //   2090: dup
    //   2091: bipush #43
    //   2093: ldc 34078976
    //   2095: iastore
    //   2096: dup
    //   2097: bipush #44
    //   2099: ldc 1074266368
    //   2101: iastore
    //   2102: dup
    //   2103: bipush #45
    //   2105: sipush #256
    //   2108: iastore
    //   2109: dup
    //   2110: bipush #46
    //   2112: ldc 33554432
    //   2114: iastore
    //   2115: dup
    //   2116: bipush #47
    //   2118: ldc 1107820544
    //   2120: iastore
    //   2121: dup
    //   2122: bipush #48
    //   2124: ldc 1107820800
    //   2126: iastore
    //   2127: dup
    //   2128: bipush #49
    //   2130: ldc 524544
    //   2132: iastore
    //   2133: dup
    //   2134: bipush #50
    //   2136: ldc 1107296256
    //   2138: iastore
    //   2139: dup
    //   2140: bipush #51
    //   2142: ldc 1107820800
    //   2144: iastore
    //   2145: dup
    //   2146: bipush #52
    //   2148: ldc 34078720
    //   2150: iastore
    //   2151: dup
    //   2152: bipush #53
    //   2154: iconst_0
    //   2155: iastore
    //   2156: dup
    //   2157: bipush #54
    //   2159: ldc 1074266112
    //   2161: iastore
    //   2162: dup
    //   2163: bipush #55
    //   2165: ldc 1107296256
    //   2167: iastore
    //   2168: dup
    //   2169: bipush #56
    //   2171: ldc 524544
    //   2173: iastore
    //   2174: dup
    //   2175: bipush #57
    //   2177: ldc 33554688
    //   2179: iastore
    //   2180: dup
    //   2181: bipush #58
    //   2183: ldc 1073742080
    //   2185: iastore
    //   2186: dup
    //   2187: bipush #59
    //   2189: ldc 524288
    //   2191: iastore
    //   2192: dup
    //   2193: bipush #60
    //   2195: iconst_0
    //   2196: iastore
    //   2197: dup
    //   2198: bipush #61
    //   2200: ldc 1074266112
    //   2202: iastore
    //   2203: dup
    //   2204: bipush #62
    //   2206: ldc 34078976
    //   2208: iastore
    //   2209: dup
    //   2210: bipush #63
    //   2212: ldc 1073742080
    //   2214: iastore
    //   2215: astore #12
    //   2217: bipush #64
    //   2219: newarray int
    //   2221: dup
    //   2222: iconst_0
    //   2223: ldc 536870928
    //   2225: iastore
    //   2226: dup
    //   2227: iconst_1
    //   2228: ldc 541065216
    //   2230: iastore
    //   2231: dup
    //   2232: iconst_2
    //   2233: sipush #16384
    //   2236: iastore
    //   2237: dup
    //   2238: iconst_3
    //   2239: ldc 541081616
    //   2241: iastore
    //   2242: dup
    //   2243: iconst_4
    //   2244: ldc 541065216
    //   2246: iastore
    //   2247: dup
    //   2248: iconst_5
    //   2249: bipush #16
    //   2251: iastore
    //   2252: dup
    //   2253: bipush #6
    //   2255: ldc 541081616
    //   2257: iastore
    //   2258: dup
    //   2259: bipush #7
    //   2261: ldc 4194304
    //   2263: iastore
    //   2264: dup
    //   2265: bipush #8
    //   2267: ldc 536887296
    //   2269: iastore
    //   2270: dup
    //   2271: bipush #9
    //   2273: ldc 4210704
    //   2275: iastore
    //   2276: dup
    //   2277: bipush #10
    //   2279: ldc 4194304
    //   2281: iastore
    //   2282: dup
    //   2283: bipush #11
    //   2285: ldc 536870928
    //   2287: iastore
    //   2288: dup
    //   2289: bipush #12
    //   2291: ldc 4194320
    //   2293: iastore
    //   2294: dup
    //   2295: bipush #13
    //   2297: ldc 536887296
    //   2299: iastore
    //   2300: dup
    //   2301: bipush #14
    //   2303: ldc 536870912
    //   2305: iastore
    //   2306: dup
    //   2307: bipush #15
    //   2309: sipush #16400
    //   2312: iastore
    //   2313: dup
    //   2314: bipush #16
    //   2316: iconst_0
    //   2317: iastore
    //   2318: dup
    //   2319: bipush #17
    //   2321: ldc 4194320
    //   2323: iastore
    //   2324: dup
    //   2325: bipush #18
    //   2327: ldc 536887312
    //   2329: iastore
    //   2330: dup
    //   2331: bipush #19
    //   2333: sipush #16384
    //   2336: iastore
    //   2337: dup
    //   2338: bipush #20
    //   2340: ldc 4210688
    //   2342: iastore
    //   2343: dup
    //   2344: bipush #21
    //   2346: ldc 536887312
    //   2348: iastore
    //   2349: dup
    //   2350: bipush #22
    //   2352: bipush #16
    //   2354: iastore
    //   2355: dup
    //   2356: bipush #23
    //   2358: ldc 541065232
    //   2360: iastore
    //   2361: dup
    //   2362: bipush #24
    //   2364: ldc 541065232
    //   2366: iastore
    //   2367: dup
    //   2368: bipush #25
    //   2370: iconst_0
    //   2371: iastore
    //   2372: dup
    //   2373: bipush #26
    //   2375: ldc 4210704
    //   2377: iastore
    //   2378: dup
    //   2379: bipush #27
    //   2381: ldc 541081600
    //   2383: iastore
    //   2384: dup
    //   2385: bipush #28
    //   2387: sipush #16400
    //   2390: iastore
    //   2391: dup
    //   2392: bipush #29
    //   2394: ldc 4210688
    //   2396: iastore
    //   2397: dup
    //   2398: bipush #30
    //   2400: ldc 541081600
    //   2402: iastore
    //   2403: dup
    //   2404: bipush #31
    //   2406: ldc 536870912
    //   2408: iastore
    //   2409: dup
    //   2410: bipush #32
    //   2412: ldc 536887296
    //   2414: iastore
    //   2415: dup
    //   2416: bipush #33
    //   2418: bipush #16
    //   2420: iastore
    //   2421: dup
    //   2422: bipush #34
    //   2424: ldc 541065232
    //   2426: iastore
    //   2427: dup
    //   2428: bipush #35
    //   2430: ldc 4210688
    //   2432: iastore
    //   2433: dup
    //   2434: bipush #36
    //   2436: ldc 541081616
    //   2438: iastore
    //   2439: dup
    //   2440: bipush #37
    //   2442: ldc 4194304
    //   2444: iastore
    //   2445: dup
    //   2446: bipush #38
    //   2448: sipush #16400
    //   2451: iastore
    //   2452: dup
    //   2453: bipush #39
    //   2455: ldc 536870928
    //   2457: iastore
    //   2458: dup
    //   2459: bipush #40
    //   2461: ldc 4194304
    //   2463: iastore
    //   2464: dup
    //   2465: bipush #41
    //   2467: ldc 536887296
    //   2469: iastore
    //   2470: dup
    //   2471: bipush #42
    //   2473: ldc 536870912
    //   2475: iastore
    //   2476: dup
    //   2477: bipush #43
    //   2479: sipush #16400
    //   2482: iastore
    //   2483: dup
    //   2484: bipush #44
    //   2486: ldc 536870928
    //   2488: iastore
    //   2489: dup
    //   2490: bipush #45
    //   2492: ldc 541081616
    //   2494: iastore
    //   2495: dup
    //   2496: bipush #46
    //   2498: ldc 4210688
    //   2500: iastore
    //   2501: dup
    //   2502: bipush #47
    //   2504: ldc 541065216
    //   2506: iastore
    //   2507: dup
    //   2508: bipush #48
    //   2510: ldc 4210704
    //   2512: iastore
    //   2513: dup
    //   2514: bipush #49
    //   2516: ldc 541081600
    //   2518: iastore
    //   2519: dup
    //   2520: bipush #50
    //   2522: iconst_0
    //   2523: iastore
    //   2524: dup
    //   2525: bipush #51
    //   2527: ldc 541065232
    //   2529: iastore
    //   2530: dup
    //   2531: bipush #52
    //   2533: bipush #16
    //   2535: iastore
    //   2536: dup
    //   2537: bipush #53
    //   2539: sipush #16384
    //   2542: iastore
    //   2543: dup
    //   2544: bipush #54
    //   2546: ldc 541065216
    //   2548: iastore
    //   2549: dup
    //   2550: bipush #55
    //   2552: ldc 4210704
    //   2554: iastore
    //   2555: dup
    //   2556: bipush #56
    //   2558: sipush #16384
    //   2561: iastore
    //   2562: dup
    //   2563: bipush #57
    //   2565: ldc 4194320
    //   2567: iastore
    //   2568: dup
    //   2569: bipush #58
    //   2571: ldc 536887312
    //   2573: iastore
    //   2574: dup
    //   2575: bipush #59
    //   2577: iconst_0
    //   2578: iastore
    //   2579: dup
    //   2580: bipush #60
    //   2582: ldc 541081600
    //   2584: iastore
    //   2585: dup
    //   2586: bipush #61
    //   2588: ldc 536870912
    //   2590: iastore
    //   2591: dup
    //   2592: bipush #62
    //   2594: ldc 4194320
    //   2596: iastore
    //   2597: dup
    //   2598: bipush #63
    //   2600: ldc 536887312
    //   2602: iastore
    //   2603: astore #13
    //   2605: bipush #64
    //   2607: newarray int
    //   2609: dup
    //   2610: iconst_0
    //   2611: ldc 2097152
    //   2613: iastore
    //   2614: dup
    //   2615: iconst_1
    //   2616: ldc 69206018
    //   2618: iastore
    //   2619: dup
    //   2620: iconst_2
    //   2621: ldc 67110914
    //   2623: iastore
    //   2624: dup
    //   2625: iconst_3
    //   2626: iconst_0
    //   2627: iastore
    //   2628: dup
    //   2629: iconst_4
    //   2630: sipush #2048
    //   2633: iastore
    //   2634: dup
    //   2635: iconst_5
    //   2636: ldc 67110914
    //   2638: iastore
    //   2639: dup
    //   2640: bipush #6
    //   2642: ldc 2099202
    //   2644: iastore
    //   2645: dup
    //   2646: bipush #7
    //   2648: ldc 69208064
    //   2650: iastore
    //   2651: dup
    //   2652: bipush #8
    //   2654: ldc 69208066
    //   2656: iastore
    //   2657: dup
    //   2658: bipush #9
    //   2660: ldc 2097152
    //   2662: iastore
    //   2663: dup
    //   2664: bipush #10
    //   2666: iconst_0
    //   2667: iastore
    //   2668: dup
    //   2669: bipush #11
    //   2671: ldc 67108866
    //   2673: iastore
    //   2674: dup
    //   2675: bipush #12
    //   2677: iconst_2
    //   2678: iastore
    //   2679: dup
    //   2680: bipush #13
    //   2682: ldc 67108864
    //   2684: iastore
    //   2685: dup
    //   2686: bipush #14
    //   2688: ldc 69206018
    //   2690: iastore
    //   2691: dup
    //   2692: bipush #15
    //   2694: sipush #2050
    //   2697: iastore
    //   2698: dup
    //   2699: bipush #16
    //   2701: ldc 67110912
    //   2703: iastore
    //   2704: dup
    //   2705: bipush #17
    //   2707: ldc 2099202
    //   2709: iastore
    //   2710: dup
    //   2711: bipush #18
    //   2713: ldc 2097154
    //   2715: iastore
    //   2716: dup
    //   2717: bipush #19
    //   2719: ldc 67110912
    //   2721: iastore
    //   2722: dup
    //   2723: bipush #20
    //   2725: ldc 67108866
    //   2727: iastore
    //   2728: dup
    //   2729: bipush #21
    //   2731: ldc 69206016
    //   2733: iastore
    //   2734: dup
    //   2735: bipush #22
    //   2737: ldc 69208064
    //   2739: iastore
    //   2740: dup
    //   2741: bipush #23
    //   2743: ldc 2097154
    //   2745: iastore
    //   2746: dup
    //   2747: bipush #24
    //   2749: ldc 69206016
    //   2751: iastore
    //   2752: dup
    //   2753: bipush #25
    //   2755: sipush #2048
    //   2758: iastore
    //   2759: dup
    //   2760: bipush #26
    //   2762: sipush #2050
    //   2765: iastore
    //   2766: dup
    //   2767: bipush #27
    //   2769: ldc 69208066
    //   2771: iastore
    //   2772: dup
    //   2773: bipush #28
    //   2775: ldc 2099200
    //   2777: iastore
    //   2778: dup
    //   2779: bipush #29
    //   2781: iconst_2
    //   2782: iastore
    //   2783: dup
    //   2784: bipush #30
    //   2786: ldc 67108864
    //   2788: iastore
    //   2789: dup
    //   2790: bipush #31
    //   2792: ldc 2099200
    //   2794: iastore
    //   2795: dup
    //   2796: bipush #32
    //   2798: ldc 67108864
    //   2800: iastore
    //   2801: dup
    //   2802: bipush #33
    //   2804: ldc 2099200
    //   2806: iastore
    //   2807: dup
    //   2808: bipush #34
    //   2810: ldc 2097152
    //   2812: iastore
    //   2813: dup
    //   2814: bipush #35
    //   2816: ldc 67110914
    //   2818: iastore
    //   2819: dup
    //   2820: bipush #36
    //   2822: ldc 67110914
    //   2824: iastore
    //   2825: dup
    //   2826: bipush #37
    //   2828: ldc 69206018
    //   2830: iastore
    //   2831: dup
    //   2832: bipush #38
    //   2834: ldc 69206018
    //   2836: iastore
    //   2837: dup
    //   2838: bipush #39
    //   2840: iconst_2
    //   2841: iastore
    //   2842: dup
    //   2843: bipush #40
    //   2845: ldc 2097154
    //   2847: iastore
    //   2848: dup
    //   2849: bipush #41
    //   2851: ldc 67108864
    //   2853: iastore
    //   2854: dup
    //   2855: bipush #42
    //   2857: ldc 67110912
    //   2859: iastore
    //   2860: dup
    //   2861: bipush #43
    //   2863: ldc 2097152
    //   2865: iastore
    //   2866: dup
    //   2867: bipush #44
    //   2869: ldc 69208064
    //   2871: iastore
    //   2872: dup
    //   2873: bipush #45
    //   2875: sipush #2050
    //   2878: iastore
    //   2879: dup
    //   2880: bipush #46
    //   2882: ldc 2099202
    //   2884: iastore
    //   2885: dup
    //   2886: bipush #47
    //   2888: ldc 69208064
    //   2890: iastore
    //   2891: dup
    //   2892: bipush #48
    //   2894: sipush #2050
    //   2897: iastore
    //   2898: dup
    //   2899: bipush #49
    //   2901: ldc 67108866
    //   2903: iastore
    //   2904: dup
    //   2905: bipush #50
    //   2907: ldc 69208066
    //   2909: iastore
    //   2910: dup
    //   2911: bipush #51
    //   2913: ldc 69206016
    //   2915: iastore
    //   2916: dup
    //   2917: bipush #52
    //   2919: ldc 2099200
    //   2921: iastore
    //   2922: dup
    //   2923: bipush #53
    //   2925: iconst_0
    //   2926: iastore
    //   2927: dup
    //   2928: bipush #54
    //   2930: iconst_2
    //   2931: iastore
    //   2932: dup
    //   2933: bipush #55
    //   2935: ldc 69208066
    //   2937: iastore
    //   2938: dup
    //   2939: bipush #56
    //   2941: iconst_0
    //   2942: iastore
    //   2943: dup
    //   2944: bipush #57
    //   2946: ldc 2099202
    //   2948: iastore
    //   2949: dup
    //   2950: bipush #58
    //   2952: ldc 69206016
    //   2954: iastore
    //   2955: dup
    //   2956: bipush #59
    //   2958: sipush #2048
    //   2961: iastore
    //   2962: dup
    //   2963: bipush #60
    //   2965: ldc 67108866
    //   2967: iastore
    //   2968: dup
    //   2969: bipush #61
    //   2971: ldc 67110912
    //   2973: iastore
    //   2974: dup
    //   2975: bipush #62
    //   2977: sipush #2048
    //   2980: iastore
    //   2981: dup
    //   2982: bipush #63
    //   2984: ldc 2097154
    //   2986: iastore
    //   2987: astore #14
    //   2989: bipush #64
    //   2991: newarray int
    //   2993: dup
    //   2994: iconst_0
    //   2995: ldc 268439616
    //   2997: iastore
    //   2998: dup
    //   2999: iconst_1
    //   3000: sipush #4096
    //   3003: iastore
    //   3004: dup
    //   3005: iconst_2
    //   3006: ldc 262144
    //   3008: iastore
    //   3009: dup
    //   3010: iconst_3
    //   3011: ldc 268701760
    //   3013: iastore
    //   3014: dup
    //   3015: iconst_4
    //   3016: ldc 268435456
    //   3018: iastore
    //   3019: dup
    //   3020: iconst_5
    //   3021: ldc 268439616
    //   3023: iastore
    //   3024: dup
    //   3025: bipush #6
    //   3027: bipush #64
    //   3029: iastore
    //   3030: dup
    //   3031: bipush #7
    //   3033: ldc 268435456
    //   3035: iastore
    //   3036: dup
    //   3037: bipush #8
    //   3039: ldc 262208
    //   3041: iastore
    //   3042: dup
    //   3043: bipush #9
    //   3045: ldc 268697600
    //   3047: iastore
    //   3048: dup
    //   3049: bipush #10
    //   3051: ldc 268701760
    //   3053: iastore
    //   3054: dup
    //   3055: bipush #11
    //   3057: ldc 266240
    //   3059: iastore
    //   3060: dup
    //   3061: bipush #12
    //   3063: ldc 268701696
    //   3065: iastore
    //   3066: dup
    //   3067: bipush #13
    //   3069: ldc 266304
    //   3071: iastore
    //   3072: dup
    //   3073: bipush #14
    //   3075: sipush #4096
    //   3078: iastore
    //   3079: dup
    //   3080: bipush #15
    //   3082: bipush #64
    //   3084: iastore
    //   3085: dup
    //   3086: bipush #16
    //   3088: ldc 268697600
    //   3090: iastore
    //   3091: dup
    //   3092: bipush #17
    //   3094: ldc 268435520
    //   3096: iastore
    //   3097: dup
    //   3098: bipush #18
    //   3100: ldc 268439552
    //   3102: iastore
    //   3103: dup
    //   3104: bipush #19
    //   3106: sipush #4160
    //   3109: iastore
    //   3110: dup
    //   3111: bipush #20
    //   3113: ldc 266240
    //   3115: iastore
    //   3116: dup
    //   3117: bipush #21
    //   3119: ldc 262208
    //   3121: iastore
    //   3122: dup
    //   3123: bipush #22
    //   3125: ldc 268697664
    //   3127: iastore
    //   3128: dup
    //   3129: bipush #23
    //   3131: ldc 268701696
    //   3133: iastore
    //   3134: dup
    //   3135: bipush #24
    //   3137: sipush #4160
    //   3140: iastore
    //   3141: dup
    //   3142: bipush #25
    //   3144: iconst_0
    //   3145: iastore
    //   3146: dup
    //   3147: bipush #26
    //   3149: iconst_0
    //   3150: iastore
    //   3151: dup
    //   3152: bipush #27
    //   3154: ldc 268697664
    //   3156: iastore
    //   3157: dup
    //   3158: bipush #28
    //   3160: ldc 268435520
    //   3162: iastore
    //   3163: dup
    //   3164: bipush #29
    //   3166: ldc 268439552
    //   3168: iastore
    //   3169: dup
    //   3170: bipush #30
    //   3172: ldc 266304
    //   3174: iastore
    //   3175: dup
    //   3176: bipush #31
    //   3178: ldc 262144
    //   3180: iastore
    //   3181: dup
    //   3182: bipush #32
    //   3184: ldc 266304
    //   3186: iastore
    //   3187: dup
    //   3188: bipush #33
    //   3190: ldc 262144
    //   3192: iastore
    //   3193: dup
    //   3194: bipush #34
    //   3196: ldc 268701696
    //   3198: iastore
    //   3199: dup
    //   3200: bipush #35
    //   3202: sipush #4096
    //   3205: iastore
    //   3206: dup
    //   3207: bipush #36
    //   3209: bipush #64
    //   3211: iastore
    //   3212: dup
    //   3213: bipush #37
    //   3215: ldc 268697664
    //   3217: iastore
    //   3218: dup
    //   3219: bipush #38
    //   3221: sipush #4096
    //   3224: iastore
    //   3225: dup
    //   3226: bipush #39
    //   3228: ldc 266304
    //   3230: iastore
    //   3231: dup
    //   3232: bipush #40
    //   3234: ldc 268439552
    //   3236: iastore
    //   3237: dup
    //   3238: bipush #41
    //   3240: bipush #64
    //   3242: iastore
    //   3243: dup
    //   3244: bipush #42
    //   3246: ldc 268435520
    //   3248: iastore
    //   3249: dup
    //   3250: bipush #43
    //   3252: ldc 268697600
    //   3254: iastore
    //   3255: dup
    //   3256: bipush #44
    //   3258: ldc 268697664
    //   3260: iastore
    //   3261: dup
    //   3262: bipush #45
    //   3264: ldc 268435456
    //   3266: iastore
    //   3267: dup
    //   3268: bipush #46
    //   3270: ldc 262144
    //   3272: iastore
    //   3273: dup
    //   3274: bipush #47
    //   3276: ldc 268439616
    //   3278: iastore
    //   3279: dup
    //   3280: bipush #48
    //   3282: iconst_0
    //   3283: iastore
    //   3284: dup
    //   3285: bipush #49
    //   3287: ldc 268701760
    //   3289: iastore
    //   3290: dup
    //   3291: bipush #50
    //   3293: ldc 262208
    //   3295: iastore
    //   3296: dup
    //   3297: bipush #51
    //   3299: ldc 268435520
    //   3301: iastore
    //   3302: dup
    //   3303: bipush #52
    //   3305: ldc 268697600
    //   3307: iastore
    //   3308: dup
    //   3309: bipush #53
    //   3311: ldc 268439552
    //   3313: iastore
    //   3314: dup
    //   3315: bipush #54
    //   3317: ldc 268439616
    //   3319: iastore
    //   3320: dup
    //   3321: bipush #55
    //   3323: iconst_0
    //   3324: iastore
    //   3325: dup
    //   3326: bipush #56
    //   3328: ldc 268701760
    //   3330: iastore
    //   3331: dup
    //   3332: bipush #57
    //   3334: ldc 266240
    //   3336: iastore
    //   3337: dup
    //   3338: bipush #58
    //   3340: ldc 266240
    //   3342: iastore
    //   3343: dup
    //   3344: bipush #59
    //   3346: sipush #4160
    //   3349: iastore
    //   3350: dup
    //   3351: bipush #60
    //   3353: sipush #4160
    //   3356: iastore
    //   3357: dup
    //   3358: bipush #61
    //   3360: ldc 262208
    //   3362: iastore
    //   3363: dup
    //   3364: bipush #62
    //   3366: ldc 268435456
    //   3368: iastore
    //   3369: dup
    //   3370: bipush #63
    //   3372: ldc 268701696
    //   3374: iastore
    //   3375: astore #15
    //   3377: aload_3
    //   3378: arraylength
    //   3379: istore #16
    //   3381: iconst_2
    //   3382: newarray int
    //   3384: astore #17
    //   3386: iload #16
    //   3388: newarray byte
    //   3390: astore #4
    //   3392: iload #16
    //   3394: bipush #8
    //   3396: idiv
    //   3397: istore #18
    //   3399: iconst_0
    //   3400: istore #19
    //   3402: iload #19
    //   3404: iload #18
    //   3406: if_icmpge -> 4320
    //   3409: iload #19
    //   3411: bipush #8
    //   3413: imul
    //   3414: istore #20
    //   3416: iconst_0
    //   3417: istore #21
    //   3419: iload #21
    //   3421: iconst_2
    //   3422: if_icmpge -> 3507
    //   3425: aload #17
    //   3427: iload #21
    //   3429: aload_3
    //   3430: iload #20
    //   3432: iload #21
    //   3434: iconst_4
    //   3435: imul
    //   3436: iadd
    //   3437: baload
    //   3438: sipush #255
    //   3441: iand
    //   3442: bipush #24
    //   3444: ishl
    //   3445: aload_3
    //   3446: iload #20
    //   3448: iload #21
    //   3450: iconst_4
    //   3451: imul
    //   3452: iadd
    //   3453: iconst_1
    //   3454: iadd
    //   3455: baload
    //   3456: sipush #255
    //   3459: iand
    //   3460: bipush #16
    //   3462: ishl
    //   3463: ior
    //   3464: aload_3
    //   3465: iload #20
    //   3467: iload #21
    //   3469: iconst_4
    //   3470: imul
    //   3471: iadd
    //   3472: iconst_2
    //   3473: iadd
    //   3474: baload
    //   3475: sipush #255
    //   3478: iand
    //   3479: bipush #8
    //   3481: ishl
    //   3482: ior
    //   3483: aload_3
    //   3484: iload #20
    //   3486: iload #21
    //   3488: iconst_4
    //   3489: imul
    //   3490: iadd
    //   3491: iconst_3
    //   3492: iadd
    //   3493: baload
    //   3494: sipush #255
    //   3497: iand
    //   3498: ior
    //   3499: iastore
    //   3500: iinc #21, 1
    //   3503: iload_2
    //   3504: ifeq -> 3419
    //   3507: iconst_0
    //   3508: istore #26
    //   3510: aload #17
    //   3512: iconst_0
    //   3513: iaload
    //   3514: istore #24
    //   3516: aload #17
    //   3518: iconst_1
    //   3519: iaload
    //   3520: istore #23
    //   3522: iload #24
    //   3524: iconst_4
    //   3525: iushr
    //   3526: iload #23
    //   3528: ixor
    //   3529: ldc 252645135
    //   3531: iand
    //   3532: istore #22
    //   3534: iload #23
    //   3536: iload #22
    //   3538: ixor
    //   3539: istore #23
    //   3541: iload #24
    //   3543: iload #22
    //   3545: iconst_4
    //   3546: ishl
    //   3547: ixor
    //   3548: istore #24
    //   3550: iload #24
    //   3552: bipush #16
    //   3554: iushr
    //   3555: iload #23
    //   3557: ixor
    //   3558: ldc 65535
    //   3560: iand
    //   3561: istore #22
    //   3563: iload #23
    //   3565: iload #22
    //   3567: ixor
    //   3568: istore #23
    //   3570: iload #24
    //   3572: iload #22
    //   3574: bipush #16
    //   3576: ishl
    //   3577: ixor
    //   3578: istore #24
    //   3580: iload #23
    //   3582: iconst_2
    //   3583: iushr
    //   3584: iload #24
    //   3586: ixor
    //   3587: ldc 858993459
    //   3589: iand
    //   3590: istore #22
    //   3592: iload #24
    //   3594: iload #22
    //   3596: ixor
    //   3597: istore #24
    //   3599: iload #23
    //   3601: iload #22
    //   3603: iconst_2
    //   3604: ishl
    //   3605: ixor
    //   3606: istore #23
    //   3608: iload #23
    //   3610: bipush #8
    //   3612: iushr
    //   3613: iload #24
    //   3615: ixor
    //   3616: ldc 16711935
    //   3618: iand
    //   3619: istore #22
    //   3621: iload #24
    //   3623: iload #22
    //   3625: ixor
    //   3626: istore #24
    //   3628: iload #23
    //   3630: iload #22
    //   3632: bipush #8
    //   3634: ishl
    //   3635: ixor
    //   3636: istore #23
    //   3638: iload #23
    //   3640: iconst_1
    //   3641: ishl
    //   3642: iload #23
    //   3644: bipush #31
    //   3646: iushr
    //   3647: iconst_1
    //   3648: iand
    //   3649: ior
    //   3650: istore #23
    //   3652: iload #24
    //   3654: iload #23
    //   3656: ixor
    //   3657: ldc -1431655766
    //   3659: iand
    //   3660: istore #22
    //   3662: iload #24
    //   3664: iload #22
    //   3666: ixor
    //   3667: istore #24
    //   3669: iload #23
    //   3671: iload #22
    //   3673: ixor
    //   3674: istore #23
    //   3676: iload #24
    //   3678: iconst_1
    //   3679: ishl
    //   3680: iload #24
    //   3682: bipush #31
    //   3684: iushr
    //   3685: iconst_1
    //   3686: iand
    //   3687: ior
    //   3688: istore #24
    //   3690: iconst_0
    //   3691: istore #25
    //   3693: iload #25
    //   3695: bipush #8
    //   3697: if_icmpge -> 4035
    //   3700: iload #23
    //   3702: bipush #28
    //   3704: ishl
    //   3705: iload #23
    //   3707: iconst_4
    //   3708: iushr
    //   3709: ior
    //   3710: istore #22
    //   3712: iload #22
    //   3714: aload #5
    //   3716: iload #26
    //   3718: iinc #26, 1
    //   3721: iaload
    //   3722: ixor
    //   3723: istore #22
    //   3725: aload #14
    //   3727: iload #22
    //   3729: bipush #63
    //   3731: iand
    //   3732: iaload
    //   3733: istore #21
    //   3735: iload #21
    //   3737: aload #12
    //   3739: iload #22
    //   3741: bipush #8
    //   3743: iushr
    //   3744: bipush #63
    //   3746: iand
    //   3747: iaload
    //   3748: ior
    //   3749: istore #21
    //   3751: iload #21
    //   3753: aload #10
    //   3755: iload #22
    //   3757: bipush #16
    //   3759: iushr
    //   3760: bipush #63
    //   3762: iand
    //   3763: iaload
    //   3764: ior
    //   3765: istore #21
    //   3767: iload #21
    //   3769: aload #8
    //   3771: iload #22
    //   3773: bipush #24
    //   3775: iushr
    //   3776: bipush #63
    //   3778: iand
    //   3779: iaload
    //   3780: ior
    //   3781: istore #21
    //   3783: iload #23
    //   3785: aload #5
    //   3787: iload #26
    //   3789: iinc #26, 1
    //   3792: iaload
    //   3793: ixor
    //   3794: istore #22
    //   3796: iload #21
    //   3798: aload #15
    //   3800: iload #22
    //   3802: bipush #63
    //   3804: iand
    //   3805: iaload
    //   3806: ior
    //   3807: istore #21
    //   3809: iload #21
    //   3811: aload #13
    //   3813: iload #22
    //   3815: bipush #8
    //   3817: iushr
    //   3818: bipush #63
    //   3820: iand
    //   3821: iaload
    //   3822: ior
    //   3823: istore #21
    //   3825: iload #21
    //   3827: aload #11
    //   3829: iload #22
    //   3831: bipush #16
    //   3833: iushr
    //   3834: bipush #63
    //   3836: iand
    //   3837: iaload
    //   3838: ior
    //   3839: istore #21
    //   3841: iload #21
    //   3843: aload #9
    //   3845: iload #22
    //   3847: bipush #24
    //   3849: iushr
    //   3850: bipush #63
    //   3852: iand
    //   3853: iaload
    //   3854: ior
    //   3855: istore #21
    //   3857: iload #24
    //   3859: iload #21
    //   3861: ixor
    //   3862: istore #24
    //   3864: iload #24
    //   3866: bipush #28
    //   3868: ishl
    //   3869: iload #24
    //   3871: iconst_4
    //   3872: iushr
    //   3873: ior
    //   3874: istore #22
    //   3876: iload #22
    //   3878: aload #5
    //   3880: iload #26
    //   3882: iinc #26, 1
    //   3885: iaload
    //   3886: ixor
    //   3887: istore #22
    //   3889: aload #14
    //   3891: iload #22
    //   3893: bipush #63
    //   3895: iand
    //   3896: iaload
    //   3897: istore #21
    //   3899: iload #21
    //   3901: aload #12
    //   3903: iload #22
    //   3905: bipush #8
    //   3907: iushr
    //   3908: bipush #63
    //   3910: iand
    //   3911: iaload
    //   3912: ior
    //   3913: istore #21
    //   3915: iload #21
    //   3917: aload #10
    //   3919: iload #22
    //   3921: bipush #16
    //   3923: iushr
    //   3924: bipush #63
    //   3926: iand
    //   3927: iaload
    //   3928: ior
    //   3929: istore #21
    //   3931: iload #21
    //   3933: aload #8
    //   3935: iload #22
    //   3937: bipush #24
    //   3939: iushr
    //   3940: bipush #63
    //   3942: iand
    //   3943: iaload
    //   3944: ior
    //   3945: istore #21
    //   3947: iload #24
    //   3949: aload #5
    //   3951: iload #26
    //   3953: iinc #26, 1
    //   3956: iaload
    //   3957: ixor
    //   3958: istore #22
    //   3960: iload #21
    //   3962: aload #15
    //   3964: iload #22
    //   3966: bipush #63
    //   3968: iand
    //   3969: iaload
    //   3970: ior
    //   3971: istore #21
    //   3973: iload #21
    //   3975: aload #13
    //   3977: iload #22
    //   3979: bipush #8
    //   3981: iushr
    //   3982: bipush #63
    //   3984: iand
    //   3985: iaload
    //   3986: ior
    //   3987: istore #21
    //   3989: iload #21
    //   3991: aload #11
    //   3993: iload #22
    //   3995: bipush #16
    //   3997: iushr
    //   3998: bipush #63
    //   4000: iand
    //   4001: iaload
    //   4002: ior
    //   4003: istore #21
    //   4005: iload #21
    //   4007: aload #9
    //   4009: iload #22
    //   4011: bipush #24
    //   4013: iushr
    //   4014: bipush #63
    //   4016: iand
    //   4017: iaload
    //   4018: ior
    //   4019: istore #21
    //   4021: iload #23
    //   4023: iload #21
    //   4025: ixor
    //   4026: istore #23
    //   4028: iinc #25, 1
    //   4031: iload_2
    //   4032: ifeq -> 3693
    //   4035: iload #23
    //   4037: bipush #31
    //   4039: ishl
    //   4040: iload #23
    //   4042: iconst_1
    //   4043: iushr
    //   4044: ior
    //   4045: istore #23
    //   4047: iload #24
    //   4049: iload #23
    //   4051: ixor
    //   4052: ldc -1431655766
    //   4054: iand
    //   4055: istore #22
    //   4057: iload #24
    //   4059: iload #22
    //   4061: ixor
    //   4062: istore #24
    //   4064: iload #23
    //   4066: iload #22
    //   4068: ixor
    //   4069: istore #23
    //   4071: iload #24
    //   4073: bipush #31
    //   4075: ishl
    //   4076: iload #24
    //   4078: iconst_1
    //   4079: iushr
    //   4080: ior
    //   4081: istore #24
    //   4083: iload #24
    //   4085: bipush #8
    //   4087: iushr
    //   4088: iload #23
    //   4090: ixor
    //   4091: ldc 16711935
    //   4093: iand
    //   4094: istore #22
    //   4096: iload #23
    //   4098: iload #22
    //   4100: ixor
    //   4101: istore #23
    //   4103: iload #24
    //   4105: iload #22
    //   4107: bipush #8
    //   4109: ishl
    //   4110: ixor
    //   4111: istore #24
    //   4113: iload #24
    //   4115: iconst_2
    //   4116: iushr
    //   4117: iload #23
    //   4119: ixor
    //   4120: ldc 858993459
    //   4122: iand
    //   4123: istore #22
    //   4125: iload #23
    //   4127: iload #22
    //   4129: ixor
    //   4130: istore #23
    //   4132: iload #24
    //   4134: iload #22
    //   4136: iconst_2
    //   4137: ishl
    //   4138: ixor
    //   4139: istore #24
    //   4141: iload #23
    //   4143: bipush #16
    //   4145: iushr
    //   4146: iload #24
    //   4148: ixor
    //   4149: ldc 65535
    //   4151: iand
    //   4152: istore #22
    //   4154: iload #24
    //   4156: iload #22
    //   4158: ixor
    //   4159: istore #24
    //   4161: iload #23
    //   4163: iload #22
    //   4165: bipush #16
    //   4167: ishl
    //   4168: ixor
    //   4169: istore #23
    //   4171: iload #23
    //   4173: iconst_4
    //   4174: iushr
    //   4175: iload #24
    //   4177: ixor
    //   4178: ldc 252645135
    //   4180: iand
    //   4181: istore #22
    //   4183: iload #24
    //   4185: iload #22
    //   4187: ixor
    //   4188: istore #24
    //   4190: iload #23
    //   4192: iload #22
    //   4194: iconst_4
    //   4195: ishl
    //   4196: ixor
    //   4197: istore #23
    //   4199: aload #17
    //   4201: iconst_0
    //   4202: iload #23
    //   4204: iastore
    //   4205: aload #17
    //   4207: iconst_1
    //   4208: iload #24
    //   4210: iastore
    //   4211: iload #19
    //   4213: bipush #8
    //   4215: imul
    //   4216: istore #27
    //   4218: iconst_0
    //   4219: istore #28
    //   4221: iload #28
    //   4223: iconst_2
    //   4224: if_icmpge -> 4313
    //   4227: aload #4
    //   4229: iload #27
    //   4231: iload #28
    //   4233: iconst_4
    //   4234: imul
    //   4235: iadd
    //   4236: aload #17
    //   4238: iload #28
    //   4240: iaload
    //   4241: bipush #24
    //   4243: iushr
    //   4244: i2b
    //   4245: bastore
    //   4246: aload #4
    //   4248: iload #27
    //   4250: iload #28
    //   4252: iconst_4
    //   4253: imul
    //   4254: iadd
    //   4255: iconst_1
    //   4256: iadd
    //   4257: aload #17
    //   4259: iload #28
    //   4261: iaload
    //   4262: bipush #16
    //   4264: iushr
    //   4265: i2b
    //   4266: bastore
    //   4267: aload #4
    //   4269: iload #27
    //   4271: iload #28
    //   4273: iconst_4
    //   4274: imul
    //   4275: iadd
    //   4276: iconst_2
    //   4277: iadd
    //   4278: aload #17
    //   4280: iload #28
    //   4282: iaload
    //   4283: bipush #8
    //   4285: iushr
    //   4286: i2b
    //   4287: bastore
    //   4288: aload #4
    //   4290: iload #27
    //   4292: iload #28
    //   4294: iconst_4
    //   4295: imul
    //   4296: iadd
    //   4297: iconst_3
    //   4298: iadd
    //   4299: aload #17
    //   4301: iload #28
    //   4303: iaload
    //   4304: i2b
    //   4305: bastore
    //   4306: iinc #28, 1
    //   4309: iload_2
    //   4310: ifeq -> 4221
    //   4313: iinc #19, 1
    //   4316: iload_2
    //   4317: ifeq -> 3402
    //   4320: new java/math/BigInteger
    //   4323: dup
    //   4324: aload #4
    //   4326: invokespecial <init> : ([B)V
    //   4329: invokevirtual abs : ()Ljava/math/BigInteger;
    //   4332: putstatic burp/Zgk1.ZD : Ljava/lang/Object;
    //   4335: getstatic burp/Zrdo.ZK : Ljava/lang/Object;
    //   4338: checkcast java/math/BigInteger
    //   4341: invokevirtual toByteArray : ()[B
    //   4344: astore_3
    //   4345: iconst_0
    //   4346: istore #5
    //   4348: iconst_0
    //   4349: istore #6
    //   4351: iload #6
    //   4353: aload_3
    //   4354: arraylength
    //   4355: if_icmpge -> 4500
    //   4358: aload_3
    //   4359: iload #6
    //   4361: baload
    //   4362: istore #7
    //   4364: iload #7
    //   4366: bipush #48
    //   4368: if_icmplt -> 4385
    //   4371: iload #7
    //   4373: bipush #57
    //   4375: if_icmple -> 4483
    //   4378: goto -> 4385
    //   4381: invokestatic a : (Ljava/lang/Throwable;)Ljava/lang/Throwable;
    //   4384: athrow
    //   4385: iload #7
    //   4387: bipush #65
    //   4389: if_icmplt -> 4413
    //   4392: goto -> 4399
    //   4395: invokestatic a : (Ljava/lang/Throwable;)Ljava/lang/Throwable;
    //   4398: athrow
    //   4399: iload #7
    //   4401: bipush #90
    //   4403: if_icmple -> 4483
    //   4406: goto -> 4413
    //   4409: invokestatic a : (Ljava/lang/Throwable;)Ljava/lang/Throwable;
    //   4412: athrow
    //   4413: iload #7
    //   4415: bipush #97
    //   4417: if_icmplt -> 4441
    //   4420: goto -> 4427
    //   4423: invokestatic a : (Ljava/lang/Throwable;)Ljava/lang/Throwable;
    //   4426: athrow
    //   4427: iload #7
    //   4429: bipush #122
    //   4431: if_icmple -> 4483
    //   4434: goto -> 4441
    //   4437: invokestatic a : (Ljava/lang/Throwable;)Ljava/lang/Throwable;
    //   4440: athrow
    //   4441: iload #7
    //   4443: bipush #43
    //   4445: if_icmpeq -> 4483
    //   4448: goto -> 4455
    //   4451: invokestatic a : (Ljava/lang/Throwable;)Ljava/lang/Throwable;
    //   4454: athrow
    //   4455: iload #7
    //   4457: bipush #47
    //   4459: if_icmpeq -> 4483
    //   4462: goto -> 4469
    //   4465: invokestatic a : (Ljava/lang/Throwable;)Ljava/lang/Throwable;
    //   4468: athrow
    //   4469: iload #7
    //   4471: bipush #61
    //   4473: if_icmpne -> 4493
    //   4476: goto -> 4483
    //   4479: invokestatic a : (Ljava/lang/Throwable;)Ljava/lang/Throwable;
    //   4482: athrow
    //   4483: iinc #5, 1
    //   4486: goto -> 4493
    //   4489: invokestatic a : (Ljava/lang/Throwable;)Ljava/lang/Throwable;
    //   4492: athrow
    //   4493: iinc #6, 1
    //   4496: iload_2
    //   4497: ifeq -> 4351
    //   4500: iload #5
    //   4502: newarray byte
    //   4504: astore #6
    //   4506: iconst_0
    //   4507: istore #7
    //   4509: iconst_0
    //   4510: istore #8
    //   4512: iload #8
    //   4514: aload_3
    //   4515: arraylength
    //   4516: if_icmpge -> 4668
    //   4519: aload_3
    //   4520: iload #8
    //   4522: baload
    //   4523: istore #9
    //   4525: iload #9
    //   4527: bipush #48
    //   4529: if_icmplt -> 4546
    //   4532: iload #9
    //   4534: bipush #57
    //   4536: if_icmple -> 4644
    //   4539: goto -> 4546
    //   4542: invokestatic a : (Ljava/lang/Throwable;)Ljava/lang/Throwable;
    //   4545: athrow
    //   4546: iload #9
    //   4548: bipush #65
    //   4550: if_icmplt -> 4574
    //   4553: goto -> 4560
    //   4556: invokestatic a : (Ljava/lang/Throwable;)Ljava/lang/Throwable;
    //   4559: athrow
    //   4560: iload #9
    //   4562: bipush #90
    //   4564: if_icmple -> 4644
    //   4567: goto -> 4574
    //   4570: invokestatic a : (Ljava/lang/Throwable;)Ljava/lang/Throwable;
    //   4573: athrow
    //   4574: iload #9
    //   4576: bipush #97
    //   4578: if_icmplt -> 4602
    //   4581: goto -> 4588
    //   4584: invokestatic a : (Ljava/lang/Throwable;)Ljava/lang/Throwable;
    //   4587: athrow
    //   4588: iload #9
    //   4590: bipush #122
    //   4592: if_icmple -> 4644
    //   4595: goto -> 4602
    //   4598: invokestatic a : (Ljava/lang/Throwable;)Ljava/lang/Throwable;
    //   4601: athrow
    //   4602: iload #9
    //   4604: bipush #43
    //   4606: if_icmpeq -> 4644
    //   4609: goto -> 4616
    //   4612: invokestatic a : (Ljava/lang/Throwable;)Ljava/lang/Throwable;
    //   4615: athrow
    //   4616: iload #9
    //   4618: bipush #47
    //   4620: if_icmpeq -> 4644
    //   4623: goto -> 4630
    //   4626: invokestatic a : (Ljava/lang/Throwable;)Ljava/lang/Throwable;
    //   4629: athrow
    //   4630: iload #9
    //   4632: bipush #61
    //   4634: if_icmpne -> 4661
    //   4637: goto -> 4644
    //   4640: invokestatic a : (Ljava/lang/Throwable;)Ljava/lang/Throwable;
    //   4643: athrow
    //   4644: aload #6
    //   4646: iload #7
    //   4648: iload #9
    //   4650: bastore
    //   4651: iinc #7, 1
    //   4654: goto -> 4661
    //   4657: invokestatic a : (Ljava/lang/Throwable;)Ljava/lang/Throwable;
    //   4660: athrow
    //   4661: iinc #8, 1
    //   4664: iload_2
    //   4665: ifeq -> 4512
    //   4668: aload #6
    //   4670: astore #4
    //   4672: aload #4
    //   4674: astore_3
    //   4675: aload_3
    //   4676: arraylength
    //   4677: istore #5
    //   4679: aload_3
    //   4680: iload #5
    //   4682: iconst_1
    //   4683: isub
    //   4684: baload
    //   4685: bipush #61
    //   4687: if_icmpne -> 4697
    //   4690: iinc #5, -1
    //   4693: iload_2
    //   4694: ifeq -> 4679
    //   4697: iload #5
    //   4699: aload_3
    //   4700: arraylength
    //   4701: iconst_4
    //   4702: idiv
    //   4703: isub
    //   4704: newarray byte
    //   4706: astore #6
    //   4708: iconst_0
    //   4709: istore #7
    //   4711: iload #7
    //   4713: aload_3
    //   4714: arraylength
    //   4715: if_icmpge -> 4977
    //   4718: aload_3
    //   4719: iload #7
    //   4721: baload
    //   4722: bipush #61
    //   4724: if_icmpne -> 4743
    //   4727: aload_3
    //   4728: iload #7
    //   4730: iconst_0
    //   4731: bastore
    //   4732: iload_2
    //   4733: ifeq -> 4970
    //   4736: goto -> 4743
    //   4739: invokestatic a : (Ljava/lang/Throwable;)Ljava/lang/Throwable;
    //   4742: athrow
    //   4743: aload_3
    //   4744: iload #7
    //   4746: baload
    //   4747: bipush #47
    //   4749: if_icmpne -> 4776
    //   4752: goto -> 4759
    //   4755: invokestatic a : (Ljava/lang/Throwable;)Ljava/lang/Throwable;
    //   4758: athrow
    //   4759: aload_3
    //   4760: iload #7
    //   4762: bipush #63
    //   4764: bastore
    //   4765: iload_2
    //   4766: ifeq -> 4970
    //   4769: goto -> 4776
    //   4772: invokestatic a : (Ljava/lang/Throwable;)Ljava/lang/Throwable;
    //   4775: athrow
    //   4776: aload_3
    //   4777: iload #7
    //   4779: baload
    //   4780: bipush #43
    //   4782: if_icmpne -> 4809
    //   4785: goto -> 4792
    //   4788: invokestatic a : (Ljava/lang/Throwable;)Ljava/lang/Throwable;
    //   4791: athrow
    //   4792: aload_3
    //   4793: iload #7
    //   4795: bipush #62
    //   4797: bastore
    //   4798: iload_2
    //   4799: ifeq -> 4970
    //   4802: goto -> 4809
    //   4805: invokestatic a : (Ljava/lang/Throwable;)Ljava/lang/Throwable;
    //   4808: athrow
    //   4809: aload_3
    //   4810: iload #7
    //   4812: baload
    //   4813: bipush #48
    //   4815: if_icmplt -> 4864
    //   4818: goto -> 4825
    //   4821: invokestatic a : (Ljava/lang/Throwable;)Ljava/lang/Throwable;
    //   4824: athrow
    //   4825: aload_3
    //   4826: iload #7
    //   4828: baload
    //   4829: bipush #57
    //   4831: if_icmpgt -> 4864
    //   4834: goto -> 4841
    //   4837: invokestatic a : (Ljava/lang/Throwable;)Ljava/lang/Throwable;
    //   4840: athrow
    //   4841: aload_3
    //   4842: iload #7
    //   4844: aload_3
    //   4845: iload #7
    //   4847: baload
    //   4848: bipush #-4
    //   4850: isub
    //   4851: i2b
    //   4852: bastore
    //   4853: iload_2
    //   4854: ifeq -> 4970
    //   4857: goto -> 4864
    //   4860: invokestatic a : (Ljava/lang/Throwable;)Ljava/lang/Throwable;
    //   4863: athrow
    //   4864: aload_3
    //   4865: iload #7
    //   4867: baload
    //   4868: bipush #97
    //   4870: if_icmplt -> 4919
    //   4873: goto -> 4880
    //   4876: invokestatic a : (Ljava/lang/Throwable;)Ljava/lang/Throwable;
    //   4879: athrow
    //   4880: aload_3
    //   4881: iload #7
    //   4883: baload
    //   4884: bipush #122
    //   4886: if_icmpgt -> 4919
    //   4889: goto -> 4896
    //   4892: invokestatic a : (Ljava/lang/Throwable;)Ljava/lang/Throwable;
    //   4895: athrow
    //   4896: aload_3
    //   4897: iload #7
    //   4899: aload_3
    //   4900: iload #7
    //   4902: baload
    //   4903: bipush #71
    //   4905: isub
    //   4906: i2b
    //   4907: bastore
    //   4908: iload_2
    //   4909: ifeq -> 4970
    //   4912: goto -> 4919
    //   4915: invokestatic a : (Ljava/lang/Throwable;)Ljava/lang/Throwable;
    //   4918: athrow
    //   4919: aload_3
    //   4920: iload #7
    //   4922: baload
    //   4923: bipush #65
    //   4925: if_icmplt -> 4970
    //   4928: goto -> 4935
    //   4931: invokestatic a : (Ljava/lang/Throwable;)Ljava/lang/Throwable;
    //   4934: athrow
    //   4935: aload_3
    //   4936: iload #7
    //   4938: baload
    //   4939: bipush #90
    //   4941: if_icmpgt -> 4970
    //   4944: goto -> 4951
    //   4947: invokestatic a : (Ljava/lang/Throwable;)Ljava/lang/Throwable;
    //   4950: athrow
    //   4951: aload_3
    //   4952: iload #7
    //   4954: aload_3
    //   4955: iload #7
    //   4957: baload
    //   4958: bipush #65
    //   4960: isub
    //   4961: i2b
    //   4962: bastore
    //   4963: goto -> 4970
    //   4966: invokestatic a : (Ljava/lang/Throwable;)Ljava/lang/Throwable;
    //   4969: athrow
    //   4970: iinc #7, 1
    //   4973: iload_2
    //   4974: ifeq -> 4711
    //   4977: iconst_0
    //   4978: istore #7
    //   4980: iconst_0
    //   4981: istore #8
    //   4983: iload #8
    //   4985: aload #6
    //   4987: arraylength
    //   4988: iconst_2
    //   4989: isub
    //   4990: if_icmpge -> 5093
    //   4993: aload #6
    //   4995: iload #8
    //   4997: aload_3
    //   4998: iload #7
    //   5000: baload
    //   5001: iconst_2
    //   5002: ishl
    //   5003: sipush #255
    //   5006: iand
    //   5007: aload_3
    //   5008: iload #7
    //   5010: iconst_1
    //   5011: iadd
    //   5012: baload
    //   5013: iconst_4
    //   5014: iushr
    //   5015: iconst_3
    //   5016: iand
    //   5017: ior
    //   5018: i2b
    //   5019: bastore
    //   5020: aload #6
    //   5022: iload #8
    //   5024: iconst_1
    //   5025: iadd
    //   5026: aload_3
    //   5027: iload #7
    //   5029: iconst_1
    //   5030: iadd
    //   5031: baload
    //   5032: iconst_4
    //   5033: ishl
    //   5034: sipush #255
    //   5037: iand
    //   5038: aload_3
    //   5039: iload #7
    //   5041: iconst_2
    //   5042: iadd
    //   5043: baload
    //   5044: iconst_2
    //   5045: iushr
    //   5046: bipush #15
    //   5048: iand
    //   5049: ior
    //   5050: i2b
    //   5051: bastore
    //   5052: aload #6
    //   5054: iload #8
    //   5056: iconst_2
    //   5057: iadd
    //   5058: aload_3
    //   5059: iload #7
    //   5061: iconst_2
    //   5062: iadd
    //   5063: baload
    //   5064: bipush #6
    //   5066: ishl
    //   5067: sipush #255
    //   5070: iand
    //   5071: aload_3
    //   5072: iload #7
    //   5074: iconst_3
    //   5075: iadd
    //   5076: baload
    //   5077: bipush #63
    //   5079: iand
    //   5080: ior
    //   5081: i2b
    //   5082: bastore
    //   5083: iinc #7, 4
    //   5086: iinc #8, 3
    //   5089: iload_2
    //   5090: ifeq -> 4983
    //   5093: iload #8
    //   5095: aload #6
    //   5097: arraylength
    //   5098: if_icmpge -> 5135
    //   5101: aload #6
    //   5103: iload #8
    //   5105: aload_3
    //   5106: iload #7
    //   5108: baload
    //   5109: iconst_2
    //   5110: ishl
    //   5111: sipush #255
    //   5114: iand
    //   5115: aload_3
    //   5116: iload #7
    //   5118: iconst_1
    //   5119: iadd
    //   5120: baload
    //   5121: iconst_4
    //   5122: iushr
    //   5123: iconst_3
    //   5124: iand
    //   5125: ior
    //   5126: i2b
    //   5127: bastore
    //   5128: goto -> 5135
    //   5131: invokestatic a : (Ljava/lang/Throwable;)Ljava/lang/Throwable;
    //   5134: athrow
    //   5135: iinc #8, 1
    //   5138: iload #8
    //   5140: aload #6
    //   5142: arraylength
    //   5143: if_icmpge -> 5183
    //   5146: aload #6
    //   5148: iload #8
    //   5150: aload_3
    //   5151: iload #7
    //   5153: iconst_1
    //   5154: iadd
    //   5155: baload
    //   5156: iconst_4
    //   5157: ishl
    //   5158: sipush #255
    //   5161: iand
    //   5162: aload_3
    //   5163: iload #7
    //   5165: iconst_2
    //   5166: iadd
    //   5167: baload
    //   5168: iconst_2
    //   5169: iushr
    //   5170: bipush #15
    //   5172: iand
    //   5173: ior
    //   5174: i2b
    //   5175: bastore
    //   5176: goto -> 5183
    //   5179: invokestatic a : (Ljava/lang/Throwable;)Ljava/lang/Throwable;
    //   5182: athrow
    //   5183: aload #6
    //   5185: astore #4
    //   5187: new java/math/BigInteger
    //   5190: dup
    //   5191: aload #4
    //   5193: invokespecial <init> : ([B)V
    //   5196: invokevirtual abs : ()Ljava/math/BigInteger;
    //   5199: putstatic burp/Ze6t.Zu : Ljava/lang/Object;
    //   5202: getstatic burp/Zxti.ZJ : Ljava/lang/Object;
    //   5205: checkcast java/math/BigInteger
    //   5208: invokevirtual toByteArray : ()[B
    //   5211: astore_3
    //   5212: bipush #64
    //   5214: newarray byte
    //   5216: dup
    //   5217: iconst_0
    //   5218: bipush #-128
    //   5220: bastore
    //   5221: dup
    //   5222: iconst_1
    //   5223: iconst_0
    //   5224: bastore
    //   5225: dup
    //   5226: iconst_2
    //   5227: iconst_0
    //   5228: bastore
    //   5229: dup
    //   5230: iconst_3
    //   5231: iconst_0
    //   5232: bastore
    //   5233: dup
    //   5234: iconst_4
    //   5235: iconst_0
    //   5236: bastore
    //   5237: dup
    //   5238: iconst_5
    //   5239: iconst_0
    //   5240: bastore
    //   5241: dup
    //   5242: bipush #6
    //   5244: iconst_0
    //   5245: bastore
    //   5246: dup
    //   5247: bipush #7
    //   5249: iconst_0
    //   5250: bastore
    //   5251: dup
    //   5252: bipush #8
    //   5254: iconst_0
    //   5255: bastore
    //   5256: dup
    //   5257: bipush #9
    //   5259: iconst_0
    //   5260: bastore
    //   5261: dup
    //   5262: bipush #10
    //   5264: iconst_0
    //   5265: bastore
    //   5266: dup
    //   5267: bipush #11
    //   5269: iconst_0
    //   5270: bastore
    //   5271: dup
    //   5272: bipush #12
    //   5274: iconst_0
    //   5275: bastore
    //   5276: dup
    //   5277: bipush #13
    //   5279: iconst_0
    //   5280: bastore
    //   5281: dup
    //   5282: bipush #14
    //   5284: iconst_0
    //   5285: bastore
    //   5286: dup
    //   5287: bipush #15
    //   5289: iconst_0
    //   5290: bastore
    //   5291: dup
    //   5292: bipush #16
    //   5294: iconst_0
    //   5295: bastore
    //   5296: dup
    //   5297: bipush #17
    //   5299: iconst_0
    //   5300: bastore
    //   5301: dup
    //   5302: bipush #18
    //   5304: iconst_0
    //   5305: bastore
    //   5306: dup
    //   5307: bipush #19
    //   5309: iconst_0
    //   5310: bastore
    //   5311: dup
    //   5312: bipush #20
    //   5314: iconst_0
    //   5315: bastore
    //   5316: dup
    //   5317: bipush #21
    //   5319: iconst_0
    //   5320: bastore
    //   5321: dup
    //   5322: bipush #22
    //   5324: iconst_0
    //   5325: bastore
    //   5326: dup
    //   5327: bipush #23
    //   5329: iconst_0
    //   5330: bastore
    //   5331: dup
    //   5332: bipush #24
    //   5334: iconst_0
    //   5335: bastore
    //   5336: dup
    //   5337: bipush #25
    //   5339: iconst_0
    //   5340: bastore
    //   5341: dup
    //   5342: bipush #26
    //   5344: iconst_0
    //   5345: bastore
    //   5346: dup
    //   5347: bipush #27
    //   5349: iconst_0
    //   5350: bastore
    //   5351: dup
    //   5352: bipush #28
    //   5354: iconst_0
    //   5355: bastore
    //   5356: dup
    //   5357: bipush #29
    //   5359: iconst_0
    //   5360: bastore
    //   5361: dup
    //   5362: bipush #30
    //   5364: iconst_0
    //   5365: bastore
    //   5366: dup
    //   5367: bipush #31
    //   5369: iconst_0
    //   5370: bastore
    //   5371: dup
    //   5372: bipush #32
    //   5374: iconst_0
    //   5375: bastore
    //   5376: dup
    //   5377: bipush #33
    //   5379: iconst_0
    //   5380: bastore
    //   5381: dup
    //   5382: bipush #34
    //   5384: iconst_0
    //   5385: bastore
    //   5386: dup
    //   5387: bipush #35
    //   5389: iconst_0
    //   5390: bastore
    //   5391: dup
    //   5392: bipush #36
    //   5394: iconst_0
    //   5395: bastore
    //   5396: dup
    //   5397: bipush #37
    //   5399: iconst_0
    //   5400: bastore
    //   5401: dup
    //   5402: bipush #38
    //   5404: iconst_0
    //   5405: bastore
    //   5406: dup
    //   5407: bipush #39
    //   5409: iconst_0
    //   5410: bastore
    //   5411: dup
    //   5412: bipush #40
    //   5414: iconst_0
    //   5415: bastore
    //   5416: dup
    //   5417: bipush #41
    //   5419: iconst_0
    //   5420: bastore
    //   5421: dup
    //   5422: bipush #42
    //   5424: iconst_0
    //   5425: bastore
    //   5426: dup
    //   5427: bipush #43
    //   5429: iconst_0
    //   5430: bastore
    //   5431: dup
    //   5432: bipush #44
    //   5434: iconst_0
    //   5435: bastore
    //   5436: dup
    //   5437: bipush #45
    //   5439: iconst_0
    //   5440: bastore
    //   5441: dup
    //   5442: bipush #46
    //   5444: iconst_0
    //   5445: bastore
    //   5446: dup
    //   5447: bipush #47
    //   5449: iconst_0
    //   5450: bastore
    //   5451: dup
    //   5452: bipush #48
    //   5454: iconst_0
    //   5455: bastore
    //   5456: dup
    //   5457: bipush #49
    //   5459: iconst_0
    //   5460: bastore
    //   5461: dup
    //   5462: bipush #50
    //   5464: iconst_0
    //   5465: bastore
    //   5466: dup
    //   5467: bipush #51
    //   5469: iconst_0
    //   5470: bastore
    //   5471: dup
    //   5472: bipush #52
    //   5474: iconst_0
    //   5475: bastore
    //   5476: dup
    //   5477: bipush #53
    //   5479: iconst_0
    //   5480: bastore
    //   5481: dup
    //   5482: bipush #54
    //   5484: iconst_0
    //   5485: bastore
    //   5486: dup
    //   5487: bipush #55
    //   5489: iconst_0
    //   5490: bastore
    //   5491: dup
    //   5492: bipush #56
    //   5494: iconst_0
    //   5495: bastore
    //   5496: dup
    //   5497: bipush #57
    //   5499: iconst_0
    //   5500: bastore
    //   5501: dup
    //   5502: bipush #58
    //   5504: iconst_0
    //   5505: bastore
    //   5506: dup
    //   5507: bipush #59
    //   5509: iconst_0
    //   5510: bastore
    //   5511: dup
    //   5512: bipush #60
    //   5514: iconst_0
    //   5515: bastore
    //   5516: dup
    //   5517: bipush #61
    //   5519: iconst_0
    //   5520: bastore
    //   5521: dup
    //   5522: bipush #62
    //   5524: iconst_0
    //   5525: bastore
    //   5526: dup
    //   5527: bipush #63
    //   5529: iconst_0
    //   5530: bastore
    //   5531: astore #5
    //   5533: bipush #64
    //   5535: newarray int
    //   5537: dup
    //   5538: iconst_0
    //   5539: ldc 1116352408
    //   5541: iastore
    //   5542: dup
    //   5543: iconst_1
    //   5544: ldc 1899447441
    //   5546: iastore
    //   5547: dup
    //   5548: iconst_2
    //   5549: ldc -1245643825
    //   5551: iastore
    //   5552: dup
    //   5553: iconst_3
    //   5554: ldc -373957723
    //   5556: iastore
    //   5557: dup
    //   5558: iconst_4
    //   5559: ldc 961987163
    //   5561: iastore
    //   5562: dup
    //   5563: iconst_5
    //   5564: ldc 1508970993
    //   5566: iastore
    //   5567: dup
    //   5568: bipush #6
    //   5570: ldc -1841331548
    //   5572: iastore
    //   5573: dup
    //   5574: bipush #7
    //   5576: ldc -1424204075
    //   5578: iastore
    //   5579: dup
    //   5580: bipush #8
    //   5582: ldc -670586216
    //   5584: iastore
    //   5585: dup
    //   5586: bipush #9
    //   5588: ldc 310598401
    //   5590: iastore
    //   5591: dup
    //   5592: bipush #10
    //   5594: ldc 607225278
    //   5596: iastore
    //   5597: dup
    //   5598: bipush #11
    //   5600: ldc 1426881987
    //   5602: iastore
    //   5603: dup
    //   5604: bipush #12
    //   5606: ldc 1925078388
    //   5608: iastore
    //   5609: dup
    //   5610: bipush #13
    //   5612: ldc -2132889090
    //   5614: iastore
    //   5615: dup
    //   5616: bipush #14
    //   5618: ldc -1680079193
    //   5620: iastore
    //   5621: dup
    //   5622: bipush #15
    //   5624: ldc -1046744716
    //   5626: iastore
    //   5627: dup
    //   5628: bipush #16
    //   5630: ldc -459576895
    //   5632: iastore
    //   5633: dup
    //   5634: bipush #17
    //   5636: ldc -272742522
    //   5638: iastore
    //   5639: dup
    //   5640: bipush #18
    //   5642: ldc 264347078
    //   5644: iastore
    //   5645: dup
    //   5646: bipush #19
    //   5648: ldc 604807628
    //   5650: iastore
    //   5651: dup
    //   5652: bipush #20
    //   5654: ldc 770255983
    //   5656: iastore
    //   5657: dup
    //   5658: bipush #21
    //   5660: ldc 1249150122
    //   5662: iastore
    //   5663: dup
    //   5664: bipush #22
    //   5666: ldc 1555081692
    //   5668: iastore
    //   5669: dup
    //   5670: bipush #23
    //   5672: ldc 1996064986
    //   5674: iastore
    //   5675: dup
    //   5676: bipush #24
    //   5678: ldc -1740746414
    //   5680: iastore
    //   5681: dup
    //   5682: bipush #25
    //   5684: ldc -1473132947
    //   5686: iastore
    //   5687: dup
    //   5688: bipush #26
    //   5690: ldc -1341970488
    //   5692: iastore
    //   5693: dup
    //   5694: bipush #27
    //   5696: ldc -1084653625
    //   5698: iastore
    //   5699: dup
    //   5700: bipush #28
    //   5702: ldc -958395405
    //   5704: iastore
    //   5705: dup
    //   5706: bipush #29
    //   5708: ldc -710438585
    //   5710: iastore
    //   5711: dup
    //   5712: bipush #30
    //   5714: ldc 113926993
    //   5716: iastore
    //   5717: dup
    //   5718: bipush #31
    //   5720: ldc 338241895
    //   5722: iastore
    //   5723: dup
    //   5724: bipush #32
    //   5726: ldc 666307205
    //   5728: iastore
    //   5729: dup
    //   5730: bipush #33
    //   5732: ldc 773529912
    //   5734: iastore
    //   5735: dup
    //   5736: bipush #34
    //   5738: ldc 1294757372
    //   5740: iastore
    //   5741: dup
    //   5742: bipush #35
    //   5744: ldc 1396182291
    //   5746: iastore
    //   5747: dup
    //   5748: bipush #36
    //   5750: ldc 1695183700
    //   5752: iastore
    //   5753: dup
    //   5754: bipush #37
    //   5756: ldc 1986661051
    //   5758: iastore
    //   5759: dup
    //   5760: bipush #38
    //   5762: ldc -2117940946
    //   5764: iastore
    //   5765: dup
    //   5766: bipush #39
    //   5768: ldc -1838011259
    //   5770: iastore
    //   5771: dup
    //   5772: bipush #40
    //   5774: ldc -1564481375
    //   5776: iastore
    //   5777: dup
    //   5778: bipush #41
    //   5780: ldc -1474664885
    //   5782: iastore
    //   5783: dup
    //   5784: bipush #42
    //   5786: ldc -1035236496
    //   5788: iastore
    //   5789: dup
    //   5790: bipush #43
    //   5792: ldc -949202525
    //   5794: iastore
    //   5795: dup
    //   5796: bipush #44
    //   5798: ldc -778901479
    //   5800: iastore
    //   5801: dup
    //   5802: bipush #45
    //   5804: ldc -694614492
    //   5806: iastore
    //   5807: dup
    //   5808: bipush #46
    //   5810: ldc -200395387
    //   5812: iastore
    //   5813: dup
    //   5814: bipush #47
    //   5816: ldc 275423344
    //   5818: iastore
    //   5819: dup
    //   5820: bipush #48
    //   5822: ldc 430227734
    //   5824: iastore
    //   5825: dup
    //   5826: bipush #49
    //   5828: ldc 506948616
    //   5830: iastore
    //   5831: dup
    //   5832: bipush #50
    //   5834: ldc 659060556
    //   5836: iastore
    //   5837: dup
    //   5838: bipush #51
    //   5840: ldc 883997877
    //   5842: iastore
    //   5843: dup
    //   5844: bipush #52
    //   5846: ldc 958139571
    //   5848: iastore
    //   5849: dup
    //   5850: bipush #53
    //   5852: ldc 1322822218
    //   5854: iastore
    //   5855: dup
    //   5856: bipush #54
    //   5858: ldc 1537002063
    //   5860: iastore
    //   5861: dup
    //   5862: bipush #55
    //   5864: ldc 1747873779
    //   5866: iastore
    //   5867: dup
    //   5868: bipush #56
    //   5870: ldc 1955562222
    //   5872: iastore
    //   5873: dup
    //   5874: bipush #57
    //   5876: ldc 2024104815
    //   5878: iastore
    //   5879: dup
    //   5880: bipush #58
    //   5882: ldc -2067236844
    //   5884: iastore
    //   5885: dup
    //   5886: bipush #59
    //   5888: ldc -1933114872
    //   5890: iastore
    //   5891: dup
    //   5892: bipush #60
    //   5894: ldc -1866530822
    //   5896: iastore
    //   5897: dup
    //   5898: bipush #61
    //   5900: ldc -1538233109
    //   5902: iastore
    //   5903: dup
    //   5904: bipush #62
    //   5906: ldc -1090935817
    //   5908: iastore
    //   5909: dup
    //   5910: bipush #63
    //   5912: ldc -965641998
    //   5914: iastore
    //   5915: astore #6
    //   5917: iconst_2
    //   5918: newarray int
    //   5920: dup
    //   5921: iconst_0
    //   5922: iconst_0
    //   5923: iastore
    //   5924: dup
    //   5925: iconst_1
    //   5926: iconst_0
    //   5927: iastore
    //   5928: astore #7
    //   5930: bipush #8
    //   5932: newarray int
    //   5934: dup
    //   5935: iconst_0
    //   5936: ldc 1779033703
    //   5938: iastore
    //   5939: dup
    //   5940: iconst_1
    //   5941: ldc -1150833019
    //   5943: iastore
    //   5944: dup
    //   5945: iconst_2
    //   5946: ldc 1013904242
    //   5948: iastore
    //   5949: dup
    //   5950: iconst_3
    //   5951: ldc -1521486534
    //   5953: iastore
    //   5954: dup
    //   5955: iconst_4
    //   5956: ldc 1359893119
    //   5958: iastore
    //   5959: dup
    //   5960: iconst_5
    //   5961: ldc -1694144372
    //   5963: iastore
    //   5964: dup
    //   5965: bipush #6
    //   5967: ldc 528734635
    //   5969: iastore
    //   5970: dup
    //   5971: bipush #7
    //   5973: ldc 1541459225
    //   5975: iastore
    //   5976: astore #8
    //   5978: bipush #64
    //   5980: newarray byte
    //   5982: astore #9
    //   5984: bipush #64
    //   5986: newarray byte
    //   5988: astore #10
    //   5990: aload_3
    //   5991: arraylength
    //   5992: istore #11
    //   5994: aload #7
    //   5996: iconst_0
    //   5997: iaload
    //   5998: bipush #63
    //   6000: iand
    //   6001: istore #12
    //   6003: aload #7
    //   6005: iconst_0
    //   6006: dup2
    //   6007: iaload
    //   6008: iload #11
    //   6010: iadd
    //   6011: iastore
    //   6012: aload #7
    //   6014: iconst_0
    //   6015: dup2
    //   6016: iaload
    //   6017: iconst_m1
    //   6018: iand
    //   6019: iastore
    //   6020: aload #7
    //   6022: iconst_0
    //   6023: iaload
    //   6024: iload #11
    //   6026: if_icmpge -> 6044
    //   6029: aload #7
    //   6031: iconst_1
    //   6032: dup2
    //   6033: iaload
    //   6034: iconst_1
    //   6035: iadd
    //   6036: iastore
    //   6037: goto -> 6044
    //   6040: invokestatic a : (Ljava/lang/Throwable;)Ljava/lang/Throwable;
    //   6043: athrow
    //   6044: iconst_0
    //   6045: istore #13
    //   6047: iload #11
    //   6049: bipush #64
    //   6051: if_icmplt -> 6660
    //   6054: iconst_0
    //   6055: istore #14
    //   6057: iload #14
    //   6059: bipush #64
    //   6061: if_icmpge -> 6083
    //   6064: aload #10
    //   6066: iload #14
    //   6068: aload_3
    //   6069: iload #13
    //   6071: iload #14
    //   6073: iadd
    //   6074: baload
    //   6075: bastore
    //   6076: iinc #14, 1
    //   6079: iload_2
    //   6080: ifeq -> 6057
    //   6083: bipush #64
    //   6085: newarray int
    //   6087: astore #14
    //   6089: bipush #8
    //   6091: newarray int
    //   6093: astore #15
    //   6095: iconst_0
    //   6096: istore #16
    //   6098: iload #16
    //   6100: bipush #8
    //   6102: if_icmpge -> 6122
    //   6105: aload #15
    //   6107: iload #16
    //   6109: aload #8
    //   6111: iload #16
    //   6113: iaload
    //   6114: iastore
    //   6115: iinc #16, 1
    //   6118: iload_2
    //   6119: ifeq -> 6098
    //   6122: iconst_0
    //   6123: istore #16
    //   6125: iload #16
    //   6127: bipush #64
    //   6129: if_icmpge -> 6620
    //   6132: iload #16
    //   6134: bipush #16
    //   6136: if_icmpge -> 6217
    //   6139: aload #14
    //   6141: iload #16
    //   6143: aload #10
    //   6145: iconst_4
    //   6146: iload #16
    //   6148: imul
    //   6149: baload
    //   6150: sipush #255
    //   6153: iand
    //   6154: bipush #24
    //   6156: ishl
    //   6157: aload #10
    //   6159: iconst_4
    //   6160: iload #16
    //   6162: imul
    //   6163: iconst_1
    //   6164: iadd
    //   6165: baload
    //   6166: sipush #255
    //   6169: iand
    //   6170: bipush #16
    //   6172: ishl
    //   6173: ior
    //   6174: aload #10
    //   6176: iconst_4
    //   6177: iload #16
    //   6179: imul
    //   6180: iconst_2
    //   6181: iadd
    //   6182: baload
    //   6183: sipush #255
    //   6186: iand
    //   6187: bipush #8
    //   6189: ishl
    //   6190: ior
    //   6191: aload #10
    //   6193: iconst_4
    //   6194: iload #16
    //   6196: imul
    //   6197: iconst_3
    //   6198: iadd
    //   6199: baload
    //   6200: sipush #255
    //   6203: iand
    //   6204: ior
    //   6205: iastore
    //   6206: iload_2
    //   6207: ifeq -> 6360
    //   6210: goto -> 6217
    //   6213: invokestatic a : (Ljava/lang/Throwable;)Ljava/lang/Throwable;
    //   6216: athrow
    //   6217: aload #14
    //   6219: iload #16
    //   6221: aload #14
    //   6223: iload #16
    //   6225: iconst_2
    //   6226: isub
    //   6227: iaload
    //   6228: bipush #17
    //   6230: iushr
    //   6231: aload #14
    //   6233: iload #16
    //   6235: iconst_2
    //   6236: isub
    //   6237: iaload
    //   6238: bipush #15
    //   6240: ishl
    //   6241: ior
    //   6242: aload #14
    //   6244: iload #16
    //   6246: iconst_2
    //   6247: isub
    //   6248: iaload
    //   6249: bipush #19
    //   6251: iushr
    //   6252: aload #14
    //   6254: iload #16
    //   6256: iconst_2
    //   6257: isub
    //   6258: iaload
    //   6259: bipush #13
    //   6261: ishl
    //   6262: ior
    //   6263: ixor
    //   6264: aload #14
    //   6266: iload #16
    //   6268: iconst_2
    //   6269: isub
    //   6270: iaload
    //   6271: bipush #10
    //   6273: iushr
    //   6274: ixor
    //   6275: aload #14
    //   6277: iload #16
    //   6279: bipush #7
    //   6281: isub
    //   6282: iaload
    //   6283: iadd
    //   6284: aload #14
    //   6286: iload #16
    //   6288: bipush #15
    //   6290: isub
    //   6291: iaload
    //   6292: bipush #7
    //   6294: iushr
    //   6295: aload #14
    //   6297: iload #16
    //   6299: bipush #15
    //   6301: isub
    //   6302: iaload
    //   6303: bipush #25
    //   6305: ishl
    //   6306: ior
    //   6307: aload #14
    //   6309: iload #16
    //   6311: bipush #15
    //   6313: isub
    //   6314: iaload
    //   6315: bipush #18
    //   6317: iushr
    //   6318: aload #14
    //   6320: iload #16
    //   6322: bipush #15
    //   6324: isub
    //   6325: iaload
    //   6326: bipush #14
    //   6328: ishl
    //   6329: ior
    //   6330: ixor
    //   6331: aload #14
    //   6333: iload #16
    //   6335: bipush #15
    //   6337: isub
    //   6338: iaload
    //   6339: iconst_3
    //   6340: iushr
    //   6341: ixor
    //   6342: iadd
    //   6343: aload #14
    //   6345: iload #16
    //   6347: bipush #16
    //   6349: isub
    //   6350: iaload
    //   6351: iadd
    //   6352: iastore
    //   6353: goto -> 6360
    //   6356: invokestatic a : (Ljava/lang/Throwable;)Ljava/lang/Throwable;
    //   6359: athrow
    //   6360: aload #15
    //   6362: bipush #7
    //   6364: iaload
    //   6365: aload #15
    //   6367: iconst_4
    //   6368: iaload
    //   6369: bipush #6
    //   6371: iushr
    //   6372: aload #15
    //   6374: iconst_4
    //   6375: iaload
    //   6376: bipush #26
    //   6378: ishl
    //   6379: ior
    //   6380: aload #15
    //   6382: iconst_4
    //   6383: iaload
    //   6384: bipush #11
    //   6386: iushr
    //   6387: aload #15
    //   6389: iconst_4
    //   6390: iaload
    //   6391: bipush #21
    //   6393: ishl
    //   6394: ior
    //   6395: ixor
    //   6396: aload #15
    //   6398: iconst_4
    //   6399: iaload
    //   6400: bipush #25
    //   6402: iushr
    //   6403: aload #15
    //   6405: iconst_4
    //   6406: iaload
    //   6407: bipush #7
    //   6409: ishl
    //   6410: ior
    //   6411: ixor
    //   6412: iadd
    //   6413: aload #15
    //   6415: bipush #6
    //   6417: iaload
    //   6418: aload #15
    //   6420: iconst_4
    //   6421: iaload
    //   6422: aload #15
    //   6424: iconst_5
    //   6425: iaload
    //   6426: aload #15
    //   6428: bipush #6
    //   6430: iaload
    //   6431: ixor
    //   6432: iand
    //   6433: ixor
    //   6434: iadd
    //   6435: aload #6
    //   6437: iload #16
    //   6439: iaload
    //   6440: iadd
    //   6441: aload #14
    //   6443: iload #16
    //   6445: iaload
    //   6446: iadd
    //   6447: istore #17
    //   6449: aload #15
    //   6451: iconst_0
    //   6452: iaload
    //   6453: iconst_2
    //   6454: iushr
    //   6455: aload #15
    //   6457: iconst_0
    //   6458: iaload
    //   6459: bipush #30
    //   6461: ishl
    //   6462: ior
    //   6463: aload #15
    //   6465: iconst_0
    //   6466: iaload
    //   6467: bipush #13
    //   6469: iushr
    //   6470: aload #15
    //   6472: iconst_0
    //   6473: iaload
    //   6474: bipush #19
    //   6476: ishl
    //   6477: ior
    //   6478: ixor
    //   6479: aload #15
    //   6481: iconst_0
    //   6482: iaload
    //   6483: bipush #22
    //   6485: iushr
    //   6486: aload #15
    //   6488: iconst_0
    //   6489: iaload
    //   6490: bipush #10
    //   6492: ishl
    //   6493: ior
    //   6494: ixor
    //   6495: aload #15
    //   6497: iconst_0
    //   6498: iaload
    //   6499: aload #15
    //   6501: iconst_1
    //   6502: iaload
    //   6503: iand
    //   6504: aload #15
    //   6506: iconst_2
    //   6507: iaload
    //   6508: aload #15
    //   6510: iconst_0
    //   6511: iaload
    //   6512: aload #15
    //   6514: iconst_1
    //   6515: iaload
    //   6516: ior
    //   6517: iand
    //   6518: ior
    //   6519: iadd
    //   6520: istore #18
    //   6522: aload #15
    //   6524: iconst_3
    //   6525: dup2
    //   6526: iaload
    //   6527: iload #17
    //   6529: iadd
    //   6530: iastore
    //   6531: aload #15
    //   6533: bipush #7
    //   6535: iload #17
    //   6537: iload #18
    //   6539: iadd
    //   6540: iastore
    //   6541: aload #15
    //   6543: bipush #7
    //   6545: iaload
    //   6546: istore #17
    //   6548: aload #15
    //   6550: bipush #7
    //   6552: aload #15
    //   6554: bipush #6
    //   6556: iaload
    //   6557: iastore
    //   6558: aload #15
    //   6560: bipush #6
    //   6562: aload #15
    //   6564: iconst_5
    //   6565: iaload
    //   6566: iastore
    //   6567: aload #15
    //   6569: iconst_5
    //   6570: aload #15
    //   6572: iconst_4
    //   6573: iaload
    //   6574: iastore
    //   6575: aload #15
    //   6577: iconst_4
    //   6578: aload #15
    //   6580: iconst_3
    //   6581: iaload
    //   6582: iastore
    //   6583: aload #15
    //   6585: iconst_3
    //   6586: aload #15
    //   6588: iconst_2
    //   6589: iaload
    //   6590: iastore
    //   6591: aload #15
    //   6593: iconst_2
    //   6594: aload #15
    //   6596: iconst_1
    //   6597: iaload
    //   6598: iastore
    //   6599: aload #15
    //   6601: iconst_1
    //   6602: aload #15
    //   6604: iconst_0
    //   6605: iaload
    //   6606: iastore
    //   6607: aload #15
    //   6609: iconst_0
    //   6610: iload #17
    //   6612: iastore
    //   6613: iinc #16, 1
    //   6616: iload_2
    //   6617: ifeq -> 6125
    //   6620: iconst_0
    //   6621: istore #16
    //   6623: iload #16
    //   6625: bipush #8
    //   6627: if_icmpge -> 6650
    //   6630: aload #8
    //   6632: iload #16
    //   6634: dup2
    //   6635: iaload
    //   6636: aload #15
    //   6638: iload #16
    //   6640: iaload
    //   6641: iadd
    //   6642: iastore
    //   6643: iinc #16, 1
    //   6646: iload_2
    //   6647: ifeq -> 6623
    //   6650: iinc #13, 64
    //   6653: iinc #11, -64
    //   6656: iload_2
    //   6657: ifeq -> 6047
    //   6660: iload #11
    //   6662: ifle -> 6697
    //   6665: iconst_0
    //   6666: istore #14
    //   6668: iload #14
    //   6670: iload #11
    //   6672: if_icmpge -> 6697
    //   6675: aload #9
    //   6677: iload #12
    //   6679: iload #14
    //   6681: iadd
    //   6682: aload_3
    //   6683: iload #13
    //   6685: iload #14
    //   6687: iadd
    //   6688: baload
    //   6689: bastore
    //   6690: iinc #14, 1
    //   6693: iload_2
    //   6694: ifeq -> 6668
    //   6697: aload #7
    //   6699: iconst_0
    //   6700: iaload
    //   6701: bipush #29
    //   6703: iushr
    //   6704: aload #7
    //   6706: iconst_1
    //   6707: iaload
    //   6708: iconst_3
    //   6709: ishl
    //   6710: ior
    //   6711: istore #14
    //   6713: aload #7
    //   6715: iconst_0
    //   6716: iaload
    //   6717: iconst_3
    //   6718: ishl
    //   6719: istore #15
    //   6721: aload #7
    //   6723: iconst_0
    //   6724: iaload
    //   6725: bipush #63
    //   6727: iand
    //   6728: istore #16
    //   6730: iload #16
    //   6732: bipush #56
    //   6734: if_icmpge -> 6749
    //   6737: bipush #56
    //   6739: iload #16
    //   6741: isub
    //   6742: goto -> 6754
    //   6745: invokestatic a : (Ljava/lang/Throwable;)Ljava/lang/Throwable;
    //   6748: athrow
    //   6749: bipush #120
    //   6751: iload #16
    //   6753: isub
    //   6754: istore #17
    //   6756: aload #7
    //   6758: iconst_0
    //   6759: iaload
    //   6760: bipush #63
    //   6762: iand
    //   6763: istore #12
    //   6765: bipush #64
    //   6767: iload #12
    //   6769: isub
    //   6770: istore #18
    //   6772: aload #7
    //   6774: iconst_0
    //   6775: dup2
    //   6776: iaload
    //   6777: iload #17
    //   6779: iadd
    //   6780: iastore
    //   6781: aload #7
    //   6783: iconst_0
    //   6784: dup2
    //   6785: iaload
    //   6786: iconst_m1
    //   6787: iand
    //   6788: iastore
    //   6789: aload #7
    //   6791: iconst_0
    //   6792: iaload
    //   6793: iload #17
    //   6795: if_icmpge -> 6813
    //   6798: aload #7
    //   6800: iconst_1
    //   6801: dup2
    //   6802: iaload
    //   6803: iconst_1
    //   6804: iadd
    //   6805: iastore
    //   6806: goto -> 6813
    //   6809: invokestatic a : (Ljava/lang/Throwable;)Ljava/lang/Throwable;
    //   6812: athrow
    //   6813: iconst_0
    //   6814: istore #13
    //   6816: iload #12
    //   6818: ifle -> 7449
    //   6821: iload #17
    //   6823: iload #18
    //   6825: if_icmplt -> 7449
    //   6828: goto -> 6835
    //   6831: invokestatic a : (Ljava/lang/Throwable;)Ljava/lang/Throwable;
    //   6834: athrow
    //   6835: iconst_0
    //   6836: istore #19
    //   6838: iload #19
    //   6840: iload #18
    //   6842: if_icmpge -> 6865
    //   6845: aload #9
    //   6847: iload #12
    //   6849: iload #19
    //   6851: iadd
    //   6852: aload #5
    //   6854: iload #19
    //   6856: baload
    //   6857: bastore
    //   6858: iinc #19, 1
    //   6861: iload_2
    //   6862: ifeq -> 6838
    //   6865: bipush #64
    //   6867: newarray int
    //   6869: astore #19
    //   6871: bipush #8
    //   6873: newarray int
    //   6875: astore #20
    //   6877: iconst_0
    //   6878: istore #21
    //   6880: iload #21
    //   6882: bipush #8
    //   6884: if_icmpge -> 6904
    //   6887: aload #20
    //   6889: iload #21
    //   6891: aload #8
    //   6893: iload #21
    //   6895: iaload
    //   6896: iastore
    //   6897: iinc #21, 1
    //   6900: iload_2
    //   6901: ifeq -> 6880
    //   6904: iconst_0
    //   6905: istore #21
    //   6907: iload #21
    //   6909: bipush #64
    //   6911: if_icmpge -> 7402
    //   6914: iload #21
    //   6916: bipush #16
    //   6918: if_icmpge -> 6999
    //   6921: aload #19
    //   6923: iload #21
    //   6925: aload #9
    //   6927: iconst_4
    //   6928: iload #21
    //   6930: imul
    //   6931: baload
    //   6932: sipush #255
    //   6935: iand
    //   6936: bipush #24
    //   6938: ishl
    //   6939: aload #9
    //   6941: iconst_4
    //   6942: iload #21
    //   6944: imul
    //   6945: iconst_1
    //   6946: iadd
    //   6947: baload
    //   6948: sipush #255
    //   6951: iand
    //   6952: bipush #16
    //   6954: ishl
    //   6955: ior
    //   6956: aload #9
    //   6958: iconst_4
    //   6959: iload #21
    //   6961: imul
    //   6962: iconst_2
    //   6963: iadd
    //   6964: baload
    //   6965: sipush #255
    //   6968: iand
    //   6969: bipush #8
    //   6971: ishl
    //   6972: ior
    //   6973: aload #9
    //   6975: iconst_4
    //   6976: iload #21
    //   6978: imul
    //   6979: iconst_3
    //   6980: iadd
    //   6981: baload
    //   6982: sipush #255
    //   6985: iand
    //   6986: ior
    //   6987: iastore
    //   6988: iload_2
    //   6989: ifeq -> 7142
    //   6992: goto -> 6999
    //   6995: invokestatic a : (Ljava/lang/Throwable;)Ljava/lang/Throwable;
    //   6998: athrow
    //   6999: aload #19
    //   7001: iload #21
    //   7003: aload #19
    //   7005: iload #21
    //   7007: iconst_2
    //   7008: isub
    //   7009: iaload
    //   7010: bipush #17
    //   7012: iushr
    //   7013: aload #19
    //   7015: iload #21
    //   7017: iconst_2
    //   7018: isub
    //   7019: iaload
    //   7020: bipush #15
    //   7022: ishl
    //   7023: ior
    //   7024: aload #19
    //   7026: iload #21
    //   7028: iconst_2
    //   7029: isub
    //   7030: iaload
    //   7031: bipush #19
    //   7033: iushr
    //   7034: aload #19
    //   7036: iload #21
    //   7038: iconst_2
    //   7039: isub
    //   7040: iaload
    //   7041: bipush #13
    //   7043: ishl
    //   7044: ior
    //   7045: ixor
    //   7046: aload #19
    //   7048: iload #21
    //   7050: iconst_2
    //   7051: isub
    //   7052: iaload
    //   7053: bipush #10
    //   7055: iushr
    //   7056: ixor
    //   7057: aload #19
    //   7059: iload #21
    //   7061: bipush #7
    //   7063: isub
    //   7064: iaload
    //   7065: iadd
    //   7066: aload #19
    //   7068: iload #21
    //   7070: bipush #15
    //   7072: isub
    //   7073: iaload
    //   7074: bipush #7
    //   7076: iushr
    //   7077: aload #19
    //   7079: iload #21
    //   7081: bipush #15
    //   7083: isub
    //   7084: iaload
    //   7085: bipush #25
    //   7087: ishl
    //   7088: ior
    //   7089: aload #19
    //   7091: iload #21
    //   7093: bipush #15
    //   7095: isub
    //   7096: iaload
    //   7097: bipush #18
    //   7099: iushr
    //   7100: aload #19
    //   7102: iload #21
    //   7104: bipush #15
    //   7106: isub
    //   7107: iaload
    //   7108: bipush #14
    //   7110: ishl
    //   7111: ior
    //   7112: ixor
    //   7113: aload #19
    //   7115: iload #21
    //   7117: bipush #15
    //   7119: isub
    //   7120: iaload
    //   7121: iconst_3
    //   7122: iushr
    //   7123: ixor
    //   7124: iadd
    //   7125: aload #19
    //   7127: iload #21
    //   7129: bipush #16
    //   7131: isub
    //   7132: iaload
    //   7133: iadd
    //   7134: iastore
    //   7135: goto -> 7142
    //   7138: invokestatic a : (Ljava/lang/Throwable;)Ljava/lang/Throwable;
    //   7141: athrow
    //   7142: aload #20
    //   7144: bipush #7
    //   7146: iaload
    //   7147: aload #20
    //   7149: iconst_4
    //   7150: iaload
    //   7151: bipush #6
    //   7153: iushr
    //   7154: aload #20
    //   7156: iconst_4
    //   7157: iaload
    //   7158: bipush #26
    //   7160: ishl
    //   7161: ior
    //   7162: aload #20
    //   7164: iconst_4
    //   7165: iaload
    //   7166: bipush #11
    //   7168: iushr
    //   7169: aload #20
    //   7171: iconst_4
    //   7172: iaload
    //   7173: bipush #21
    //   7175: ishl
    //   7176: ior
    //   7177: ixor
    //   7178: aload #20
    //   7180: iconst_4
    //   7181: iaload
    //   7182: bipush #25
    //   7184: iushr
    //   7185: aload #20
    //   7187: iconst_4
    //   7188: iaload
    //   7189: bipush #7
    //   7191: ishl
    //   7192: ior
    //   7193: ixor
    //   7194: iadd
    //   7195: aload #20
    //   7197: bipush #6
    //   7199: iaload
    //   7200: aload #20
    //   7202: iconst_4
    //   7203: iaload
    //   7204: aload #20
    //   7206: iconst_5
    //   7207: iaload
    //   7208: aload #20
    //   7210: bipush #6
    //   7212: iaload
    //   7213: ixor
    //   7214: iand
    //   7215: ixor
    //   7216: iadd
    //   7217: aload #6
    //   7219: iload #21
    //   7221: iaload
    //   7222: iadd
    //   7223: aload #19
    //   7225: iload #21
    //   7227: iaload
    //   7228: iadd
    //   7229: istore #22
    //   7231: aload #20
    //   7233: iconst_0
    //   7234: iaload
    //   7235: iconst_2
    //   7236: iushr
    //   7237: aload #20
    //   7239: iconst_0
    //   7240: iaload
    //   7241: bipush #30
    //   7243: ishl
    //   7244: ior
    //   7245: aload #20
    //   7247: iconst_0
    //   7248: iaload
    //   7249: bipush #13
    //   7251: iushr
    //   7252: aload #20
    //   7254: iconst_0
    //   7255: iaload
    //   7256: bipush #19
    //   7258: ishl
    //   7259: ior
    //   7260: ixor
    //   7261: aload #20
    //   7263: iconst_0
    //   7264: iaload
    //   7265: bipush #22
    //   7267: iushr
    //   7268: aload #20
    //   7270: iconst_0
    //   7271: iaload
    //   7272: bipush #10
    //   7274: ishl
    //   7275: ior
    //   7276: ixor
    //   7277: aload #20
    //   7279: iconst_0
    //   7280: iaload
    //   7281: aload #20
    //   7283: iconst_1
    //   7284: iaload
    //   7285: iand
    //   7286: aload #20
    //   7288: iconst_2
    //   7289: iaload
    //   7290: aload #20
    //   7292: iconst_0
    //   7293: iaload
    //   7294: aload #20
    //   7296: iconst_1
    //   7297: iaload
    //   7298: ior
    //   7299: iand
    //   7300: ior
    //   7301: iadd
    //   7302: istore #23
    //   7304: aload #20
    //   7306: iconst_3
    //   7307: dup2
    //   7308: iaload
    //   7309: iload #22
    //   7311: iadd
    //   7312: iastore
    //   7313: aload #20
    //   7315: bipush #7
    //   7317: iload #22
    //   7319: iload #23
    //   7321: iadd
    //   7322: iastore
    //   7323: aload #20
    //   7325: bipush #7
    //   7327: iaload
    //   7328: istore #22
    //   7330: aload #20
    //   7332: bipush #7
    //   7334: aload #20
    //   7336: bipush #6
    //   7338: iaload
    //   7339: iastore
    //   7340: aload #20
    //   7342: bipush #6
    //   7344: aload #20
    //   7346: iconst_5
    //   7347: iaload
    //   7348: iastore
    //   7349: aload #20
    //   7351: iconst_5
    //   7352: aload #20
    //   7354: iconst_4
    //   7355: iaload
    //   7356: iastore
    //   7357: aload #20
    //   7359: iconst_4
    //   7360: aload #20
    //   7362: iconst_3
    //   7363: iaload
    //   7364: iastore
    //   7365: aload #20
    //   7367: iconst_3
    //   7368: aload #20
    //   7370: iconst_2
    //   7371: iaload
    //   7372: iastore
    //   7373: aload #20
    //   7375: iconst_2
    //   7376: aload #20
    //   7378: iconst_1
    //   7379: iaload
    //   7380: iastore
    //   7381: aload #20
    //   7383: iconst_1
    //   7384: aload #20
    //   7386: iconst_0
    //   7387: iaload
    //   7388: iastore
    //   7389: aload #20
    //   7391: iconst_0
    //   7392: iload #22
    //   7394: iastore
    //   7395: iinc #21, 1
    //   7398: iload_2
    //   7399: ifeq -> 6907
    //   7402: iconst_0
    //   7403: istore #21
    //   7405: iload #21
    //   7407: bipush #8
    //   7409: if_icmpge -> 7432
    //   7412: aload #8
    //   7414: iload #21
    //   7416: dup2
    //   7417: iaload
    //   7418: aload #20
    //   7420: iload #21
    //   7422: iaload
    //   7423: iadd
    //   7424: iastore
    //   7425: iinc #21, 1
    //   7428: iload_2
    //   7429: ifeq -> 7405
    //   7432: iload #13
    //   7434: iload #18
    //   7436: iadd
    //   7437: istore #13
    //   7439: iload #17
    //   7441: iload #18
    //   7443: isub
    //   7444: istore #17
    //   7446: iconst_0
    //   7447: istore #12
    //   7449: iload #17
    //   7451: bipush #64
    //   7453: if_icmplt -> 8063
    //   7456: iconst_0
    //   7457: istore #19
    //   7459: iload #19
    //   7461: bipush #64
    //   7463: if_icmpge -> 7486
    //   7466: aload #10
    //   7468: iload #19
    //   7470: aload #5
    //   7472: iload #13
    //   7474: iload #19
    //   7476: iadd
    //   7477: baload
    //   7478: bastore
    //   7479: iinc #19, 1
    //   7482: iload_2
    //   7483: ifeq -> 7459
    //   7486: bipush #64
    //   7488: newarray int
    //   7490: astore #19
    //   7492: bipush #8
    //   7494: newarray int
    //   7496: astore #20
    //   7498: iconst_0
    //   7499: istore #21
    //   7501: iload #21
    //   7503: bipush #8
    //   7505: if_icmpge -> 7525
    //   7508: aload #20
    //   7510: iload #21
    //   7512: aload #8
    //   7514: iload #21
    //   7516: iaload
    //   7517: iastore
    //   7518: iinc #21, 1
    //   7521: iload_2
    //   7522: ifeq -> 7501
    //   7525: iconst_0
    //   7526: istore #21
    //   7528: iload #21
    //   7530: bipush #64
    //   7532: if_icmpge -> 8023
    //   7535: iload #21
    //   7537: bipush #16
    //   7539: if_icmpge -> 7620
    //   7542: aload #19
    //   7544: iload #21
    //   7546: aload #10
    //   7548: iconst_4
    //   7549: iload #21
    //   7551: imul
    //   7552: baload
    //   7553: sipush #255
    //   7556: iand
    //   7557: bipush #24
    //   7559: ishl
    //   7560: aload #10
    //   7562: iconst_4
    //   7563: iload #21
    //   7565: imul
    //   7566: iconst_1
    //   7567: iadd
    //   7568: baload
    //   7569: sipush #255
    //   7572: iand
    //   7573: bipush #16
    //   7575: ishl
    //   7576: ior
    //   7577: aload #10
    //   7579: iconst_4
    //   7580: iload #21
    //   7582: imul
    //   7583: iconst_2
    //   7584: iadd
    //   7585: baload
    //   7586: sipush #255
    //   7589: iand
    //   7590: bipush #8
    //   7592: ishl
    //   7593: ior
    //   7594: aload #10
    //   7596: iconst_4
    //   7597: iload #21
    //   7599: imul
    //   7600: iconst_3
    //   7601: iadd
    //   7602: baload
    //   7603: sipush #255
    //   7606: iand
    //   7607: ior
    //   7608: iastore
    //   7609: iload_2
    //   7610: ifeq -> 7763
    //   7613: goto -> 7620
    //   7616: invokestatic a : (Ljava/lang/Throwable;)Ljava/lang/Throwable;
    //   7619: athrow
    //   7620: aload #19
    //   7622: iload #21
    //   7624: aload #19
    //   7626: iload #21
    //   7628: iconst_2
    //   7629: isub
    //   7630: iaload
    //   7631: bipush #17
    //   7633: iushr
    //   7634: aload #19
    //   7636: iload #21
    //   7638: iconst_2
    //   7639: isub
    //   7640: iaload
    //   7641: bipush #15
    //   7643: ishl
    //   7644: ior
    //   7645: aload #19
    //   7647: iload #21
    //   7649: iconst_2
    //   7650: isub
    //   7651: iaload
    //   7652: bipush #19
    //   7654: iushr
    //   7655: aload #19
    //   7657: iload #21
    //   7659: iconst_2
    //   7660: isub
    //   7661: iaload
    //   7662: bipush #13
    //   7664: ishl
    //   7665: ior
    //   7666: ixor
    //   7667: aload #19
    //   7669: iload #21
    //   7671: iconst_2
    //   7672: isub
    //   7673: iaload
    //   7674: bipush #10
    //   7676: iushr
    //   7677: ixor
    //   7678: aload #19
    //   7680: iload #21
    //   7682: bipush #7
    //   7684: isub
    //   7685: iaload
    //   7686: iadd
    //   7687: aload #19
    //   7689: iload #21
    //   7691: bipush #15
    //   7693: isub
    //   7694: iaload
    //   7695: bipush #7
    //   7697: iushr
    //   7698: aload #19
    //   7700: iload #21
    //   7702: bipush #15
    //   7704: isub
    //   7705: iaload
    //   7706: bipush #25
    //   7708: ishl
    //   7709: ior
    //   7710: aload #19
    //   7712: iload #21
    //   7714: bipush #15
    //   7716: isub
    //   7717: iaload
    //   7718: bipush #18
    //   7720: iushr
    //   7721: aload #19
    //   7723: iload #21
    //   7725: bipush #15
    //   7727: isub
    //   7728: iaload
    //   7729: bipush #14
    //   7731: ishl
    //   7732: ior
    //   7733: ixor
    //   7734: aload #19
    //   7736: iload #21
    //   7738: bipush #15
    //   7740: isub
    //   7741: iaload
    //   7742: iconst_3
    //   7743: iushr
    //   7744: ixor
    //   7745: iadd
    //   7746: aload #19
    //   7748: iload #21
    //   7750: bipush #16
    //   7752: isub
    //   7753: iaload
    //   7754: iadd
    //   7755: iastore
    //   7756: goto -> 7763
    //   7759: invokestatic a : (Ljava/lang/Throwable;)Ljava/lang/Throwable;
    //   7762: athrow
    //   7763: aload #20
    //   7765: bipush #7
    //   7767: iaload
    //   7768: aload #20
    //   7770: iconst_4
    //   7771: iaload
    //   7772: bipush #6
    //   7774: iushr
    //   7775: aload #20
    //   7777: iconst_4
    //   7778: iaload
    //   7779: bipush #26
    //   7781: ishl
    //   7782: ior
    //   7783: aload #20
    //   7785: iconst_4
    //   7786: iaload
    //   7787: bipush #11
    //   7789: iushr
    //   7790: aload #20
    //   7792: iconst_4
    //   7793: iaload
    //   7794: bipush #21
    //   7796: ishl
    //   7797: ior
    //   7798: ixor
    //   7799: aload #20
    //   7801: iconst_4
    //   7802: iaload
    //   7803: bipush #25
    //   7805: iushr
    //   7806: aload #20
    //   7808: iconst_4
    //   7809: iaload
    //   7810: bipush #7
    //   7812: ishl
    //   7813: ior
    //   7814: ixor
    //   7815: iadd
    //   7816: aload #20
    //   7818: bipush #6
    //   7820: iaload
    //   7821: aload #20
    //   7823: iconst_4
    //   7824: iaload
    //   7825: aload #20
    //   7827: iconst_5
    //   7828: iaload
    //   7829: aload #20
    //   7831: bipush #6
    //   7833: iaload
    //   7834: ixor
    //   7835: iand
    //   7836: ixor
    //   7837: iadd
    //   7838: aload #6
    //   7840: iload #21
    //   7842: iaload
    //   7843: iadd
    //   7844: aload #19
    //   7846: iload #21
    //   7848: iaload
    //   7849: iadd
    //   7850: istore #22
    //   7852: aload #20
    //   7854: iconst_0
    //   7855: iaload
    //   7856: iconst_2
    //   7857: iushr
    //   7858: aload #20
    //   7860: iconst_0
    //   7861: iaload
    //   7862: bipush #30
    //   7864: ishl
    //   7865: ior
    //   7866: aload #20
    //   7868: iconst_0
    //   7869: iaload
    //   7870: bipush #13
    //   7872: iushr
    //   7873: aload #20
    //   7875: iconst_0
    //   7876: iaload
    //   7877: bipush #19
    //   7879: ishl
    //   7880: ior
    //   7881: ixor
    //   7882: aload #20
    //   7884: iconst_0
    //   7885: iaload
    //   7886: bipush #22
    //   7888: iushr
    //   7889: aload #20
    //   7891: iconst_0
    //   7892: iaload
    //   7893: bipush #10
    //   7895: ishl
    //   7896: ior
    //   7897: ixor
    //   7898: aload #20
    //   7900: iconst_0
    //   7901: iaload
    //   7902: aload #20
    //   7904: iconst_1
    //   7905: iaload
    //   7906: iand
    //   7907: aload #20
    //   7909: iconst_2
    //   7910: iaload
    //   7911: aload #20
    //   7913: iconst_0
    //   7914: iaload
    //   7915: aload #20
    //   7917: iconst_1
    //   7918: iaload
    //   7919: ior
    //   7920: iand
    //   7921: ior
    //   7922: iadd
    //   7923: istore #23
    //   7925: aload #20
    //   7927: iconst_3
    //   7928: dup2
    //   7929: iaload
    //   7930: iload #22
    //   7932: iadd
    //   7933: iastore
    //   7934: aload #20
    //   7936: bipush #7
    //   7938: iload #22
    //   7940: iload #23
    //   7942: iadd
    //   7943: iastore
    //   7944: aload #20
    //   7946: bipush #7
    //   7948: iaload
    //   7949: istore #22
    //   7951: aload #20
    //   7953: bipush #7
    //   7955: aload #20
    //   7957: bipush #6
    //   7959: iaload
    //   7960: iastore
    //   7961: aload #20
    //   7963: bipush #6
    //   7965: aload #20
    //   7967: iconst_5
    //   7968: iaload
    //   7969: iastore
    //   7970: aload #20
    //   7972: iconst_5
    //   7973: aload #20
    //   7975: iconst_4
    //   7976: iaload
    //   7977: iastore
    //   7978: aload #20
    //   7980: iconst_4
    //   7981: aload #20
    //   7983: iconst_3
    //   7984: iaload
    //   7985: iastore
    //   7986: aload #20
    //   7988: iconst_3
    //   7989: aload #20
    //   7991: iconst_2
    //   7992: iaload
    //   7993: iastore
    //   7994: aload #20
    //   7996: iconst_2
    //   7997: aload #20
    //   7999: iconst_1
    //   8000: iaload
    //   8001: iastore
    //   8002: aload #20
    //   8004: iconst_1
    //   8005: aload #20
    //   8007: iconst_0
    //   8008: iaload
    //   8009: iastore
    //   8010: aload #20
    //   8012: iconst_0
    //   8013: iload #22
    //   8015: iastore
    //   8016: iinc #21, 1
    //   8019: iload_2
    //   8020: ifeq -> 7528
    //   8023: iconst_0
    //   8024: istore #21
    //   8026: iload #21
    //   8028: bipush #8
    //   8030: if_icmpge -> 8053
    //   8033: aload #8
    //   8035: iload #21
    //   8037: dup2
    //   8038: iaload
    //   8039: aload #20
    //   8041: iload #21
    //   8043: iaload
    //   8044: iadd
    //   8045: iastore
    //   8046: iinc #21, 1
    //   8049: iload_2
    //   8050: ifeq -> 8026
    //   8053: iinc #13, 64
    //   8056: iinc #17, -64
    //   8059: iload_2
    //   8060: ifeq -> 7449
    //   8063: iload #17
    //   8065: ifle -> 8101
    //   8068: iconst_0
    //   8069: istore #19
    //   8071: iload #19
    //   8073: iload #17
    //   8075: if_icmpge -> 8101
    //   8078: aload #9
    //   8080: iload #12
    //   8082: iload #19
    //   8084: iadd
    //   8085: aload #5
    //   8087: iload #13
    //   8089: iload #19
    //   8091: iadd
    //   8092: baload
    //   8093: bastore
    //   8094: iinc #19, 1
    //   8097: iload_2
    //   8098: ifeq -> 8071
    //   8101: bipush #8
    //   8103: newarray byte
    //   8105: astore #19
    //   8107: aload #19
    //   8109: iconst_0
    //   8110: iload #14
    //   8112: bipush #24
    //   8114: iushr
    //   8115: i2b
    //   8116: bastore
    //   8117: aload #19
    //   8119: iconst_1
    //   8120: iload #14
    //   8122: bipush #16
    //   8124: iushr
    //   8125: i2b
    //   8126: bastore
    //   8127: aload #19
    //   8129: iconst_2
    //   8130: iload #14
    //   8132: bipush #8
    //   8134: iushr
    //   8135: i2b
    //   8136: bastore
    //   8137: aload #19
    //   8139: iconst_3
    //   8140: iload #14
    //   8142: i2b
    //   8143: bastore
    //   8144: aload #19
    //   8146: iconst_4
    //   8147: iload #15
    //   8149: bipush #24
    //   8151: iushr
    //   8152: i2b
    //   8153: bastore
    //   8154: aload #19
    //   8156: iconst_5
    //   8157: iload #15
    //   8159: bipush #16
    //   8161: iushr
    //   8162: i2b
    //   8163: bastore
    //   8164: aload #19
    //   8166: bipush #6
    //   8168: iload #15
    //   8170: bipush #8
    //   8172: iushr
    //   8173: i2b
    //   8174: bastore
    //   8175: aload #19
    //   8177: bipush #7
    //   8179: iload #15
    //   8181: i2b
    //   8182: bastore
    //   8183: bipush #8
    //   8185: istore #11
    //   8187: aload #7
    //   8189: iconst_0
    //   8190: iaload
    //   8191: bipush #63
    //   8193: iand
    //   8194: istore #12
    //   8196: bipush #64
    //   8198: iload #12
    //   8200: isub
    //   8201: istore #18
    //   8203: aload #7
    //   8205: iconst_0
    //   8206: dup2
    //   8207: iaload
    //   8208: iload #11
    //   8210: iadd
    //   8211: iastore
    //   8212: aload #7
    //   8214: iconst_0
    //   8215: dup2
    //   8216: iaload
    //   8217: iconst_m1
    //   8218: iand
    //   8219: iastore
    //   8220: aload #7
    //   8222: iconst_0
    //   8223: iaload
    //   8224: iload #11
    //   8226: if_icmpge -> 8244
    //   8229: aload #7
    //   8231: iconst_1
    //   8232: dup2
    //   8233: iaload
    //   8234: iconst_1
    //   8235: iadd
    //   8236: iastore
    //   8237: goto -> 8244
    //   8240: invokestatic a : (Ljava/lang/Throwable;)Ljava/lang/Throwable;
    //   8243: athrow
    //   8244: iload #12
    //   8246: ifle -> 8860
    //   8249: iload #11
    //   8251: iload #18
    //   8253: if_icmplt -> 8860
    //   8256: goto -> 8263
    //   8259: invokestatic a : (Ljava/lang/Throwable;)Ljava/lang/Throwable;
    //   8262: athrow
    //   8263: iconst_0
    //   8264: istore #20
    //   8266: iload #20
    //   8268: iload #18
    //   8270: if_icmpge -> 8293
    //   8273: aload #9
    //   8275: iload #12
    //   8277: iload #20
    //   8279: iadd
    //   8280: aload #19
    //   8282: iload #20
    //   8284: baload
    //   8285: bastore
    //   8286: iinc #20, 1
    //   8289: iload_2
    //   8290: ifeq -> 8266
    //   8293: bipush #64
    //   8295: newarray int
    //   8297: astore #20
    //   8299: bipush #8
    //   8301: newarray int
    //   8303: astore #21
    //   8305: iconst_0
    //   8306: istore #22
    //   8308: iload #22
    //   8310: bipush #8
    //   8312: if_icmpge -> 8332
    //   8315: aload #21
    //   8317: iload #22
    //   8319: aload #8
    //   8321: iload #22
    //   8323: iaload
    //   8324: iastore
    //   8325: iinc #22, 1
    //   8328: iload_2
    //   8329: ifeq -> 8308
    //   8332: iconst_0
    //   8333: istore #22
    //   8335: iload #22
    //   8337: bipush #64
    //   8339: if_icmpge -> 8830
    //   8342: iload #22
    //   8344: bipush #16
    //   8346: if_icmpge -> 8427
    //   8349: aload #20
    //   8351: iload #22
    //   8353: aload #9
    //   8355: iconst_4
    //   8356: iload #22
    //   8358: imul
    //   8359: baload
    //   8360: sipush #255
    //   8363: iand
    //   8364: bipush #24
    //   8366: ishl
    //   8367: aload #9
    //   8369: iconst_4
    //   8370: iload #22
    //   8372: imul
    //   8373: iconst_1
    //   8374: iadd
    //   8375: baload
    //   8376: sipush #255
    //   8379: iand
    //   8380: bipush #16
    //   8382: ishl
    //   8383: ior
    //   8384: aload #9
    //   8386: iconst_4
    //   8387: iload #22
    //   8389: imul
    //   8390: iconst_2
    //   8391: iadd
    //   8392: baload
    //   8393: sipush #255
    //   8396: iand
    //   8397: bipush #8
    //   8399: ishl
    //   8400: ior
    //   8401: aload #9
    //   8403: iconst_4
    //   8404: iload #22
    //   8406: imul
    //   8407: iconst_3
    //   8408: iadd
    //   8409: baload
    //   8410: sipush #255
    //   8413: iand
    //   8414: ior
    //   8415: iastore
    //   8416: iload_2
    //   8417: ifeq -> 8570
    //   8420: goto -> 8427
    //   8423: invokestatic a : (Ljava/lang/Throwable;)Ljava/lang/Throwable;
    //   8426: athrow
    //   8427: aload #20
    //   8429: iload #22
    //   8431: aload #20
    //   8433: iload #22
    //   8435: iconst_2
    //   8436: isub
    //   8437: iaload
    //   8438: bipush #17
    //   8440: iushr
    //   8441: aload #20
    //   8443: iload #22
    //   8445: iconst_2
    //   8446: isub
    //   8447: iaload
    //   8448: bipush #15
    //   8450: ishl
    //   8451: ior
    //   8452: aload #20
    //   8454: iload #22
    //   8456: iconst_2
    //   8457: isub
    //   8458: iaload
    //   8459: bipush #19
    //   8461: iushr
    //   8462: aload #20
    //   8464: iload #22
    //   8466: iconst_2
    //   8467: isub
    //   8468: iaload
    //   8469: bipush #13
    //   8471: ishl
    //   8472: ior
    //   8473: ixor
    //   8474: aload #20
    //   8476: iload #22
    //   8478: iconst_2
    //   8479: isub
    //   8480: iaload
    //   8481: bipush #10
    //   8483: iushr
    //   8484: ixor
    //   8485: aload #20
    //   8487: iload #22
    //   8489: bipush #7
    //   8491: isub
    //   8492: iaload
    //   8493: iadd
    //   8494: aload #20
    //   8496: iload #22
    //   8498: bipush #15
    //   8500: isub
    //   8501: iaload
    //   8502: bipush #7
    //   8504: iushr
    //   8505: aload #20
    //   8507: iload #22
    //   8509: bipush #15
    //   8511: isub
    //   8512: iaload
    //   8513: bipush #25
    //   8515: ishl
    //   8516: ior
    //   8517: aload #20
    //   8519: iload #22
    //   8521: bipush #15
    //   8523: isub
    //   8524: iaload
    //   8525: bipush #18
    //   8527: iushr
    //   8528: aload #20
    //   8530: iload #22
    //   8532: bipush #15
    //   8534: isub
    //   8535: iaload
    //   8536: bipush #14
    //   8538: ishl
    //   8539: ior
    //   8540: ixor
    //   8541: aload #20
    //   8543: iload #22
    //   8545: bipush #15
    //   8547: isub
    //   8548: iaload
    //   8549: iconst_3
    //   8550: iushr
    //   8551: ixor
    //   8552: iadd
    //   8553: aload #20
    //   8555: iload #22
    //   8557: bipush #16
    //   8559: isub
    //   8560: iaload
    //   8561: iadd
    //   8562: iastore
    //   8563: goto -> 8570
    //   8566: invokestatic a : (Ljava/lang/Throwable;)Ljava/lang/Throwable;
    //   8569: athrow
    //   8570: aload #21
    //   8572: bipush #7
    //   8574: iaload
    //   8575: aload #21
    //   8577: iconst_4
    //   8578: iaload
    //   8579: bipush #6
    //   8581: iushr
    //   8582: aload #21
    //   8584: iconst_4
    //   8585: iaload
    //   8586: bipush #26
    //   8588: ishl
    //   8589: ior
    //   8590: aload #21
    //   8592: iconst_4
    //   8593: iaload
    //   8594: bipush #11
    //   8596: iushr
    //   8597: aload #21
    //   8599: iconst_4
    //   8600: iaload
    //   8601: bipush #21
    //   8603: ishl
    //   8604: ior
    //   8605: ixor
    //   8606: aload #21
    //   8608: iconst_4
    //   8609: iaload
    //   8610: bipush #25
    //   8612: iushr
    //   8613: aload #21
    //   8615: iconst_4
    //   8616: iaload
    //   8617: bipush #7
    //   8619: ishl
    //   8620: ior
    //   8621: ixor
    //   8622: iadd
    //   8623: aload #21
    //   8625: bipush #6
    //   8627: iaload
    //   8628: aload #21
    //   8630: iconst_4
    //   8631: iaload
    //   8632: aload #21
    //   8634: iconst_5
    //   8635: iaload
    //   8636: aload #21
    //   8638: bipush #6
    //   8640: iaload
    //   8641: ixor
    //   8642: iand
    //   8643: ixor
    //   8644: iadd
    //   8645: aload #6
    //   8647: iload #22
    //   8649: iaload
    //   8650: iadd
    //   8651: aload #20
    //   8653: iload #22
    //   8655: iaload
    //   8656: iadd
    //   8657: istore #23
    //   8659: aload #21
    //   8661: iconst_0
    //   8662: iaload
    //   8663: iconst_2
    //   8664: iushr
    //   8665: aload #21
    //   8667: iconst_0
    //   8668: iaload
    //   8669: bipush #30
    //   8671: ishl
    //   8672: ior
    //   8673: aload #21
    //   8675: iconst_0
    //   8676: iaload
    //   8677: bipush #13
    //   8679: iushr
    //   8680: aload #21
    //   8682: iconst_0
    //   8683: iaload
    //   8684: bipush #19
    //   8686: ishl
    //   8687: ior
    //   8688: ixor
    //   8689: aload #21
    //   8691: iconst_0
    //   8692: iaload
    //   8693: bipush #22
    //   8695: iushr
    //   8696: aload #21
    //   8698: iconst_0
    //   8699: iaload
    //   8700: bipush #10
    //   8702: ishl
    //   8703: ior
    //   8704: ixor
    //   8705: aload #21
    //   8707: iconst_0
    //   8708: iaload
    //   8709: aload #21
    //   8711: iconst_1
    //   8712: iaload
    //   8713: iand
    //   8714: aload #21
    //   8716: iconst_2
    //   8717: iaload
    //   8718: aload #21
    //   8720: iconst_0
    //   8721: iaload
    //   8722: aload #21
    //   8724: iconst_1
    //   8725: iaload
    //   8726: ior
    //   8727: iand
    //   8728: ior
    //   8729: iadd
    //   8730: istore #24
    //   8732: aload #21
    //   8734: iconst_3
    //   8735: dup2
    //   8736: iaload
    //   8737: iload #23
    //   8739: iadd
    //   8740: iastore
    //   8741: aload #21
    //   8743: bipush #7
    //   8745: iload #23
    //   8747: iload #24
    //   8749: iadd
    //   8750: iastore
    //   8751: aload #21
    //   8753: bipush #7
    //   8755: iaload
    //   8756: istore #23
    //   8758: aload #21
    //   8760: bipush #7
    //   8762: aload #21
    //   8764: bipush #6
    //   8766: iaload
    //   8767: iastore
    //   8768: aload #21
    //   8770: bipush #6
    //   8772: aload #21
    //   8774: iconst_5
    //   8775: iaload
    //   8776: iastore
    //   8777: aload #21
    //   8779: iconst_5
    //   8780: aload #21
    //   8782: iconst_4
    //   8783: iaload
    //   8784: iastore
    //   8785: aload #21
    //   8787: iconst_4
    //   8788: aload #21
    //   8790: iconst_3
    //   8791: iaload
    //   8792: iastore
    //   8793: aload #21
    //   8795: iconst_3
    //   8796: aload #21
    //   8798: iconst_2
    //   8799: iaload
    //   8800: iastore
    //   8801: aload #21
    //   8803: iconst_2
    //   8804: aload #21
    //   8806: iconst_1
    //   8807: iaload
    //   8808: iastore
    //   8809: aload #21
    //   8811: iconst_1
    //   8812: aload #21
    //   8814: iconst_0
    //   8815: iaload
    //   8816: iastore
    //   8817: aload #21
    //   8819: iconst_0
    //   8820: iload #23
    //   8822: iastore
    //   8823: iinc #22, 1
    //   8826: iload_2
    //   8827: ifeq -> 8335
    //   8830: iconst_0
    //   8831: istore #22
    //   8833: iload #22
    //   8835: bipush #8
    //   8837: if_icmpge -> 8860
    //   8840: aload #8
    //   8842: iload #22
    //   8844: dup2
    //   8845: iaload
    //   8846: aload #21
    //   8848: iload #22
    //   8850: iaload
    //   8851: iadd
    //   8852: iastore
    //   8853: iinc #22, 1
    //   8856: iload_2
    //   8857: ifeq -> 8833
    //   8860: bipush #32
    //   8862: newarray byte
    //   8864: astore #4
    //   8866: sipush #2564
    //   8869: aload #4
    //   8871: iconst_0
    //   8872: aload #8
    //   8874: iconst_0
    //   8875: iaload
    //   8876: bipush #24
    //   8878: iushr
    //   8879: i2b
    //   8880: bastore
    //   8881: sipush #-505
    //   8884: aload #4
    //   8886: iconst_1
    //   8887: aload #8
    //   8889: iconst_0
    //   8890: iaload
    //   8891: bipush #16
    //   8893: iushr
    //   8894: i2b
    //   8895: bastore
    //   8896: aload #4
    //   8898: iconst_2
    //   8899: aload #8
    //   8901: iconst_0
    //   8902: iaload
    //   8903: bipush #8
    //   8905: iushr
    //   8906: i2b
    //   8907: bastore
    //   8908: aload #4
    //   8910: iconst_3
    //   8911: aload #8
    //   8913: iconst_0
    //   8914: iaload
    //   8915: i2b
    //   8916: bastore
    //   8917: aload #4
    //   8919: iconst_4
    //   8920: aload #8
    //   8922: iconst_1
    //   8923: iaload
    //   8924: bipush #24
    //   8926: iushr
    //   8927: i2b
    //   8928: bastore
    //   8929: aload #4
    //   8931: iconst_5
    //   8932: aload #8
    //   8934: iconst_1
    //   8935: iaload
    //   8936: bipush #16
    //   8938: iushr
    //   8939: i2b
    //   8940: bastore
    //   8941: aload #4
    //   8943: bipush #6
    //   8945: aload #8
    //   8947: iconst_1
    //   8948: iaload
    //   8949: bipush #8
    //   8951: iushr
    //   8952: i2b
    //   8953: bastore
    //   8954: aload #4
    //   8956: bipush #7
    //   8958: aload #8
    //   8960: iconst_1
    //   8961: iaload
    //   8962: i2b
    //   8963: bastore
    //   8964: aload #4
    //   8966: bipush #8
    //   8968: aload #8
    //   8970: iconst_2
    //   8971: iaload
    //   8972: bipush #24
    //   8974: iushr
    //   8975: i2b
    //   8976: bastore
    //   8977: aload #4
    //   8979: bipush #9
    //   8981: aload #8
    //   8983: iconst_2
    //   8984: iaload
    //   8985: bipush #16
    //   8987: iushr
    //   8988: i2b
    //   8989: bastore
    //   8990: aload #4
    //   8992: bipush #10
    //   8994: aload #8
    //   8996: iconst_2
    //   8997: iaload
    //   8998: bipush #8
    //   9000: iushr
    //   9001: i2b
    //   9002: bastore
    //   9003: aload #4
    //   9005: bipush #11
    //   9007: aload #8
    //   9009: iconst_2
    //   9010: iaload
    //   9011: i2b
    //   9012: bastore
    //   9013: aload #4
    //   9015: bipush #12
    //   9017: aload #8
    //   9019: iconst_3
    //   9020: iaload
    //   9021: bipush #24
    //   9023: iushr
    //   9024: i2b
    //   9025: bastore
    //   9026: aload #4
    //   9028: bipush #13
    //   9030: aload #8
    //   9032: iconst_3
    //   9033: iaload
    //   9034: bipush #16
    //   9036: iushr
    //   9037: i2b
    //   9038: bastore
    //   9039: aload #4
    //   9041: bipush #14
    //   9043: aload #8
    //   9045: iconst_3
    //   9046: iaload
    //   9047: bipush #8
    //   9049: iushr
    //   9050: i2b
    //   9051: bastore
    //   9052: aload #4
    //   9054: bipush #15
    //   9056: aload #8
    //   9058: iconst_3
    //   9059: iaload
    //   9060: i2b
    //   9061: bastore
    //   9062: aload #4
    //   9064: bipush #16
    //   9066: aload #8
    //   9068: iconst_4
    //   9069: iaload
    //   9070: bipush #24
    //   9072: iushr
    //   9073: i2b
    //   9074: bastore
    //   9075: aload #4
    //   9077: bipush #17
    //   9079: aload #8
    //   9081: iconst_4
    //   9082: iaload
    //   9083: bipush #16
    //   9085: iushr
    //   9086: i2b
    //   9087: bastore
    //   9088: aload #4
    //   9090: bipush #18
    //   9092: aload #8
    //   9094: iconst_4
    //   9095: iaload
    //   9096: bipush #8
    //   9098: iushr
    //   9099: i2b
    //   9100: bastore
    //   9101: aload #4
    //   9103: bipush #19
    //   9105: aload #8
    //   9107: iconst_4
    //   9108: iaload
    //   9109: i2b
    //   9110: bastore
    //   9111: aload #4
    //   9113: bipush #20
    //   9115: aload #8
    //   9117: iconst_5
    //   9118: iaload
    //   9119: bipush #24
    //   9121: iushr
    //   9122: i2b
    //   9123: bastore
    //   9124: aload #4
    //   9126: bipush #21
    //   9128: aload #8
    //   9130: iconst_5
    //   9131: iaload
    //   9132: bipush #16
    //   9134: iushr
    //   9135: i2b
    //   9136: bastore
    //   9137: aload #4
    //   9139: bipush #22
    //   9141: aload #8
    //   9143: iconst_5
    //   9144: iaload
    //   9145: bipush #8
    //   9147: iushr
    //   9148: i2b
    //   9149: bastore
    //   9150: aload #4
    //   9152: bipush #23
    //   9154: aload #8
    //   9156: iconst_5
    //   9157: iaload
    //   9158: i2b
    //   9159: bastore
    //   9160: aload #4
    //   9162: bipush #24
    //   9164: aload #8
    //   9166: bipush #6
    //   9168: iaload
    //   9169: bipush #24
    //   9171: iushr
    //   9172: i2b
    //   9173: bastore
    //   9174: aload #4
    //   9176: bipush #25
    //   9178: aload #8
    //   9180: bipush #6
    //   9182: iaload
    //   9183: bipush #16
    //   9185: iushr
    //   9186: i2b
    //   9187: bastore
    //   9188: aload #4
    //   9190: bipush #26
    //   9192: aload #8
    //   9194: bipush #6
    //   9196: iaload
    //   9197: bipush #8
    //   9199: iushr
    //   9200: i2b
    //   9201: bastore
    //   9202: aload #4
    //   9204: bipush #27
    //   9206: aload #8
    //   9208: bipush #6
    //   9210: iaload
    //   9211: i2b
    //   9212: bastore
    //   9213: aload #4
    //   9215: bipush #28
    //   9217: aload #8
    //   9219: bipush #7
    //   9221: iaload
    //   9222: bipush #24
    //   9224: iushr
    //   9225: i2b
    //   9226: bastore
    //   9227: aload #4
    //   9229: bipush #29
    //   9231: aload #8
    //   9233: bipush #7
    //   9235: iaload
    //   9236: bipush #16
    //   9238: iushr
    //   9239: i2b
    //   9240: bastore
    //   9241: aload #4
    //   9243: bipush #30
    //   9245: aload #8
    //   9247: bipush #7
    //   9249: iaload
    //   9250: bipush #8
    //   9252: iushr
    //   9253: i2b
    //   9254: bastore
    //   9255: aload #4
    //   9257: bipush #31
    //   9259: aload #8
    //   9261: bipush #7
    //   9263: iaload
    //   9264: i2b
    //   9265: bastore
    //   9266: new java/math/BigInteger
    //   9269: dup
    //   9270: aload #4
    //   9272: invokespecial <init> : ([B)V
    //   9275: invokevirtual abs : ()Ljava/math/BigInteger;
    //   9278: putstatic burp/Zgz2.Zs : Ljava/lang/Object;
    //   9281: invokestatic a : (II)Ljava/lang/String;
    //   9284: iconst_1
    //   9285: ldc burp/Zxyq
    //   9287: invokevirtual getClassLoader : ()Ljava/lang/ClassLoader;
    //   9290: invokestatic forName : (Ljava/lang/String;ZLjava/lang/ClassLoader;)Ljava/lang/Class;
    //   9293: invokevirtual getDeclaredFields : ()[Ljava/lang/reflect/Field;
    //   9296: astore_3
    //   9297: aload_3
    //   9298: arraylength
    //   9299: istore #4
    //   9301: iconst_0
    //   9302: istore #5
    //   9304: iload #5
    //   9306: iload #4
    //   9308: if_icmpge -> 9445
    //   9311: aload_3
    //   9312: iload #5
    //   9314: aaload
    //   9315: astore #6
    //   9317: aload #6
    //   9319: invokevirtual getModifiers : ()I
    //   9322: invokestatic isStatic : (I)Z
    //   9325: ifne -> 9335
    //   9328: goto -> 9438
    //   9331: invokestatic a : (Ljava/lang/Throwable;)Ljava/lang/Throwable;
    //   9334: athrow
    //   9335: aload #6
    //   9337: invokevirtual getType : ()Ljava/lang/Class;
    //   9340: astore #7
    //   9342: aload #7
    //   9344: ifnull -> 9425
    //   9347: aload #7
    //   9349: invokevirtual isPrimitive : ()Z
    //   9352: ifne -> 9425
    //   9355: goto -> 9362
    //   9358: invokestatic a : (Ljava/lang/Throwable;)Ljava/lang/Throwable;
    //   9361: athrow
    //   9362: aload #7
    //   9364: invokevirtual getPackage : ()Ljava/lang/Package;
    //   9367: ifnull -> 9425
    //   9370: goto -> 9377
    //   9373: invokestatic a : (Ljava/lang/Throwable;)Ljava/lang/Throwable;
    //   9376: athrow
    //   9377: aload #7
    //   9379: invokevirtual getPackage : ()Ljava/lang/Package;
    //   9382: invokevirtual getName : ()Ljava/lang/String;
    //   9385: ifnull -> 9425
    //   9388: goto -> 9395
    //   9391: invokestatic a : (Ljava/lang/Throwable;)Ljava/lang/Throwable;
    //   9394: athrow
    //   9395: aload #7
    //   9397: invokevirtual getPackage : ()Ljava/lang/Package;
    //   9400: invokevirtual getName : ()Ljava/lang/String;
    //   9403: sipush #2571
    //   9406: sipush #3020
    //   9409: invokestatic a : (II)Ljava/lang/String;
    //   9412: invokevirtual startsWith : (Ljava/lang/String;)Z
    //   9415: ifne -> 9425
    //   9418: goto -> 9425
    //   9421: invokestatic a : (Ljava/lang/Throwable;)Ljava/lang/Throwable;
    //   9424: athrow
    //   9425: aload #6
    //   9427: iconst_1
    //   9428: invokevirtual setAccessible : (Z)V
    //   9431: aload #6
    //   9433: aconst_null
    //   9434: invokevirtual get : (Ljava/lang/Object;)Ljava/lang/Object;
    //   9437: pop
    //   9438: iinc #5, 1
    //   9441: iload_2
    //   9442: ifeq -> 9304
    //   9445: sipush #2570
    //   9448: sipush #32163
    //   9451: invokestatic a : (II)Ljava/lang/String;
    //   9454: invokestatic forName : (Ljava/lang/String;)Ljava/lang/Class;
    //   9457: invokevirtual getDeclaredMethods : ()[Ljava/lang/reflect/Method;
    //   9460: astore_3
    //   9461: aload_3
    //   9462: arraylength
    //   9463: istore #4
    //   9465: iconst_0
    //   9466: istore #5
    //   9468: iload #5
    //   9470: iload #4
    //   9472: if_icmpge -> 9604
    //   9475: aload_3
    //   9476: iload #5
    //   9478: aaload
    //   9479: astore #6
    //   9481: aload #6
    //   9483: invokevirtual getParameterTypes : ()[Ljava/lang/Class;
    //   9486: pop
    //   9487: aload #6
    //   9489: invokevirtual getModifiers : ()I
    //   9492: invokestatic isStatic : (I)Z
    //   9495: ifeq -> 9590
    //   9498: aload #6
    //   9500: invokevirtual getParameterTypes : ()[Ljava/lang/Class;
    //   9503: arraylength
    //   9504: iconst_2
    //   9505: if_icmpne -> 9590
    //   9508: goto -> 9515
    //   9511: invokestatic a : (Ljava/lang/Throwable;)Ljava/lang/Throwable;
    //   9514: athrow
    //   9515: aload #6
    //   9517: invokevirtual getReturnType : ()Ljava/lang/Class;
    //   9520: getstatic java/lang/Void.TYPE : Ljava/lang/Class;
    //   9523: invokevirtual equals : (Ljava/lang/Object;)Z
    //   9526: ifeq -> 9590
    //   9529: goto -> 9536
    //   9532: invokestatic a : (Ljava/lang/Throwable;)Ljava/lang/Throwable;
    //   9535: athrow
    //   9536: aload #6
    //   9538: iconst_1
    //   9539: invokevirtual setAccessible : (Z)V
    //   9542: aload #6
    //   9544: aconst_null
    //   9545: iconst_2
    //   9546: anewarray java/lang/Object
    //   9549: dup
    //   9550: iconst_0
    //   9551: aload_0
    //   9552: aastore
    //   9553: dup
    //   9554: iconst_1
    //   9555: aload_1
    //   9556: ifnonnull -> 9574
    //   9559: goto -> 9566
    //   9562: invokestatic a : (Ljava/lang/Throwable;)Ljava/lang/Throwable;
    //   9565: athrow
    //   9566: aload_1
    //   9567: goto -> 9581
    //   9570: invokestatic a : (Ljava/lang/Throwable;)Ljava/lang/Throwable;
    //   9573: athrow
    //   9574: aload_1
    //   9575: checkcast [B
    //   9578: invokevirtual clone : ()Ljava/lang/Object;
    //   9581: aastore
    //   9582: invokevirtual invoke : (Ljava/lang/Object;[Ljava/lang/Object;)Ljava/lang/Object;
    //   9585: pop
    //   9586: iload_2
    //   9587: ifeq -> 9604
    //   9590: iinc #5, 1
    //   9593: iload_2
    //   9594: ifeq -> 9468
    //   9597: goto -> 9604
    //   9600: invokestatic a : (Ljava/lang/Throwable;)Ljava/lang/Throwable;
    //   9603: athrow
    //   9604: getstatic burp/Zxz_.Zb : Ljava/lang/String;
    //   9607: getstatic burp/Zsn6.Zo : Ljava/lang/Object;
    //   9610: checkcast java/math/BigInteger
    //   9613: invokevirtual intValue : ()I
    //   9616: bipush #32
    //   9618: irem
    //   9619: invokestatic abs : (I)I
    //   9622: invokevirtual charAt : (I)C
    //   9625: getstatic burp/Zm6g.ZG : Ljava/lang/String;
    //   9628: getstatic burp/Zzi3.ZJ : Ljava/lang/Object;
    //   9631: checkcast java/math/BigInteger
    //   9634: invokevirtual intValue : ()I
    //   9637: bipush #32
    //   9639: irem
    //   9640: invokestatic abs : (I)I
    //   9643: invokevirtual charAt : (I)C
    //   9646: if_icmpgt -> 9753
    //   9649: getstatic burp/Zstq.ZL : Ljava/lang/String;
    //   9652: getstatic burp/Zgk1.ZD : Ljava/lang/Object;
    //   9655: checkcast java/math/BigInteger
    //   9658: invokevirtual intValue : ()I
    //   9661: bipush #32
    //   9663: irem
    //   9664: invokestatic abs : (I)I
    //   9667: invokevirtual charAt : (I)C
    //   9670: getstatic burp/Zlqy.ZZ : Ljava/lang/String;
    //   9673: getstatic burp/Zmjw.ZD : Ljava/lang/Object;
    //   9676: checkcast java/math/BigInteger
    //   9679: invokevirtual intValue : ()I
    //   9682: bipush #32
    //   9684: irem
    //   9685: invokestatic abs : (I)I
    //   9688: invokevirtual charAt : (I)C
    //   9691: if_icmple -> 9753
    //   9694: goto -> 9701
    //   9697: invokestatic a : (Ljava/lang/Throwable;)Ljava/lang/Throwable;
    //   9700: athrow
    //   9701: getstatic burp/Zk52.ZL : Ljava/lang/String;
    //   9704: getstatic burp/Zmpv.ZI : Ljava/lang/Object;
    //   9707: checkcast java/math/BigInteger
    //   9710: invokevirtual intValue : ()I
    //   9713: bipush #32
    //   9715: irem
    //   9716: invokestatic abs : (I)I
    //   9719: invokevirtual charAt : (I)C
    //   9722: getstatic burp/Zeyd.Zr : Ljava/lang/String;
    //   9725: getstatic burp/Zgx6.Zo : Ljava/lang/Object;
    //   9728: checkcast java/math/BigInteger
    //   9731: invokevirtual intValue : ()I
    //   9734: bipush #32
    //   9736: irem
    //   9737: invokestatic abs : (I)I
    //   9740: invokevirtual charAt : (I)C
    //   9743: if_icmple -> 9761
    //   9746: goto -> 9753
    //   9749: invokestatic a : (Ljava/lang/Throwable;)Ljava/lang/Throwable;
    //   9752: athrow
    //   9753: iconst_1
    //   9754: goto -> 9762
    //   9757: invokestatic a : (Ljava/lang/Throwable;)Ljava/lang/Throwable;
    //   9760: athrow
    //   9761: iconst_0
    //   9762: ireturn
    //   9763: astore_3
    //   9764: new java/lang/Exception
    //   9767: dup
    //   9768: aload_3
    //   9769: invokevirtual getMessage : ()Ljava/lang/String;
    //   9772: invokespecial <init> : (Ljava/lang/String;)V
    //   9775: athrow
    // Exception table:
    //   from	to	target	type
    //   4	9762	9763	java/lang/Throwable
    //   4364	4378	4381	java/lang/Throwable
    //   4371	4392	4395	java/lang/Throwable
    //   4385	4406	4409	java/lang/Throwable
    //   4399	4420	4423	java/lang/Throwable
    //   4413	4434	4437	java/lang/Throwable
    //   4427	4448	4451	java/lang/Throwable
    //   4441	4462	4465	java/lang/Throwable
    //   4455	4476	4479	java/lang/Throwable
    //   4469	4486	4489	java/lang/Throwable
    //   4525	4539	4542	java/lang/Throwable
    //   4532	4553	4556	java/lang/Throwable
    //   4546	4567	4570	java/lang/Throwable
    //   4560	4581	4584	java/lang/Throwable
    //   4574	4595	4598	java/lang/Throwable
    //   4588	4609	4612	java/lang/Throwable
    //   4602	4623	4626	java/lang/Throwable
    //   4616	4637	4640	java/lang/Throwable
    //   4630	4654	4657	java/lang/Throwable
    //   4718	4736	4739	java/lang/Throwable
    //   4727	4752	4755	java/lang/Throwable
    //   4743	4769	4772	java/lang/Throwable
    //   4759	4785	4788	java/lang/Throwable
    //   4776	4802	4805	java/lang/Throwable
    //   4792	4818	4821	java/lang/Throwable
    //   4809	4834	4837	java/lang/Throwable
    //   4825	4857	4860	java/lang/Throwable
    //   4841	4873	4876	java/lang/Throwable
    //   4864	4889	4892	java/lang/Throwable
    //   4880	4912	4915	java/lang/Throwable
    //   4896	4928	4931	java/lang/Throwable
    //   4919	4944	4947	java/lang/Throwable
    //   4935	4963	4966	java/lang/Throwable
    //   5093	5128	5131	java/lang/Throwable
    //   5135	5176	5179	java/lang/Throwable
    //   6003	6037	6040	java/lang/Throwable
    //   6132	6210	6213	java/lang/Throwable
    //   6139	6353	6356	java/lang/Throwable
    //   6730	6745	6745	java/lang/Throwable
    //   6772	6806	6809	java/lang/Throwable
    //   6816	6828	6831	java/lang/Throwable
    //   6914	6992	6995	java/lang/Throwable
    //   6921	7135	7138	java/lang/Throwable
    //   7535	7613	7616	java/lang/Throwable
    //   7542	7756	7759	java/lang/Throwable
    //   8203	8237	8240	java/lang/Throwable
    //   8244	8256	8259	java/lang/Throwable
    //   8342	8420	8423	java/lang/Throwable
    //   8349	8563	8566	java/lang/Throwable
    //   9317	9331	9331	java/lang/Throwable
    //   9342	9355	9358	java/lang/Throwable
    //   9347	9370	9373	java/lang/Throwable
    //   9362	9388	9391	java/lang/Throwable
    //   9377	9418	9421	java/lang/Throwable
    //   9481	9508	9511	java/lang/Throwable
    //   9498	9529	9532	java/lang/Throwable
    //   9515	9559	9562	java/lang/Throwable
    //   9536	9570	9570	java/lang/Throwable
    //   9581	9597	9600	java/lang/Throwable
    //   9604	9694	9697	java/lang/Throwable
    //   9649	9746	9749	java/lang/Throwable
    //   9701	9757	9757	java/lang/Throwable
  }
  
  static {
    // Byte code:
    //   0: bipush #9
    //   2: anewarray java/lang/String
    //   5: astore #5
    //   7: iconst_0
    //   8: istore_3
    //   9: ldc '9=u}+jA0w'3pc-kXMn_F1\\tjH\\bJq*\\b>z__K;6~WB~yeOmj>9er^ m]W,2ib@;,my%# hsMTD,\\f.>MIZ['<(>2X|j/@<}l}Q\\tS\{\\t94.\\t^;\\r'
    //   11: dup
    //   12: astore_2
    //   13: invokevirtual length : ()I
    //   16: istore #4
    //   18: bipush #32
    //   20: istore_1
    //   21: iconst_m1
    //   22: istore_0
    //   23: bipush #86
    //   25: iinc #0, 1
    //   28: aload_2
    //   29: iload_0
    //   30: dup
    //   31: iload_1
    //   32: iadd
    //   33: invokevirtual substring : (II)Ljava/lang/String;
    //   36: iconst_m1
    //   37: goto -> 142
    //   40: aload #5
    //   42: swap
    //   43: iload_3
    //   44: iinc #3, 1
    //   47: swap
    //   48: aastore
    //   49: iload_0
    //   50: iload_1
    //   51: iadd
    //   52: dup
    //   53: istore_0
    //   54: iload #4
    //   56: if_icmpge -> 68
    //   59: aload_2
    //   60: iload_0
    //   61: invokevirtual charAt : (I)C
    //   64: istore_1
    //   65: goto -> 23
    //   68: ldc 'nC{\\tC/I9d'
    //   70: dup
    //   71: astore_2
    //   72: invokevirtual length : ()I
    //   75: istore #4
    //   77: iconst_4
    //   78: istore_1
    //   79: iconst_m1
    //   80: istore_0
    //   81: bipush #41
    //   83: iinc #0, 1
    //   86: aload_2
    //   87: iload_0
    //   88: dup
    //   89: iload_1
    //   90: iadd
    //   91: invokevirtual substring : (II)Ljava/lang/String;
    //   94: iconst_0
    //   95: goto -> 142
    //   98: aload #5
    //   100: swap
    //   101: iload_3
    //   102: iinc #3, 1
    //   105: swap
    //   106: aastore
    //   107: iload_0
    //   108: iload_1
    //   109: iadd
    //   110: dup
    //   111: istore_0
    //   112: iload #4
    //   114: if_icmpge -> 126
    //   117: aload_2
    //   118: iload_0
    //   119: invokevirtual charAt : (I)C
    //   122: istore_1
    //   123: goto -> 81
    //   126: aload #5
    //   128: putstatic burp/Zs4v.a : [Ljava/lang/String;
    //   131: bipush #9
    //   133: anewarray java/lang/String
    //   136: putstatic burp/Zs4v.b : [Ljava/lang/String;
    //   139: goto -> 300
    //   142: dup_x2
    //   143: pop
    //   144: invokevirtual toCharArray : ()[C
    //   147: dup_x1
    //   148: arraylength
    //   149: dup_x2
    //   150: pop
    //   151: iconst_0
    //   152: istore #6
    //   154: dup2_x1
    //   155: pop2
    //   156: dup_x2
    //   157: iconst_1
    //   158: if_icmpgt -> 260
    //   161: dup2
    //   162: swap
    //   163: iload #6
    //   165: dup2_x1
    //   166: caload
    //   167: swap
    //   168: iload #6
    //   170: bipush #7
    //   172: irem
    //   173: tableswitch default -> 242, 0 -> 212, 1 -> 217, 2 -> 222, 3 -> 227, 4 -> 232, 5 -> 237
    //   212: bipush #127
    //   214: goto -> 244
    //   217: bipush #29
    //   219: goto -> 244
    //   222: bipush #49
    //   224: goto -> 244
    //   227: bipush #100
    //   229: goto -> 244
    //   232: bipush #81
    //   234: goto -> 244
    //   237: bipush #93
    //   239: goto -> 244
    //   242: bipush #49
    //   244: ixor
    //   245: ixor
    //   246: i2c
    //   247: castore
    //   248: iinc #6, 1
    //   251: dup
    //   252: ifne -> 260
    //   255: dup2
    //   256: dup_x1
    //   257: goto -> 165
    //   260: dup2_x1
    //   261: pop2
    //   262: dup_x2
    //   263: iload #6
    //   265: if_icmpgt -> 161
    //   268: pop
    //   269: new java/lang/String
    //   272: dup_x1
    //   273: swap
    //   274: invokespecial <init> : ([C)V
    //   277: invokevirtual intern : ()Ljava/lang/String;
    //   280: swap
    //   281: pop
    //   282: swap
    //   283: tableswitch default -> 40, 0 -> 98
    //   300: new java/math/BigInteger
    //   303: dup
    //   304: sipush #2575
    //   307: sipush #-10323
    //   310: invokestatic a : (II)Ljava/lang/String;
    //   313: invokespecial <init> : (Ljava/lang/String;)V
    //   316: putstatic burp/Zs4v.ZB : Ljava/lang/Object;
    //   319: sipush #2572
    //   322: sipush #27887
    //   325: invokestatic a : (II)Ljava/lang/String;
    //   328: putstatic burp/Zs4v.Za : Ljava/lang/String;
    //   331: return
  }
  
  private static Throwable a(Throwable paramThrowable) {
    return paramThrowable;
  }
  
  private static String a(int paramInt1, int paramInt2) {
    int i = (paramInt1 ^ 0xA0C) & 0xFFFF;
    if (b[i] == null) {
      char[] arrayOfChar = a[i].toCharArray();
      switch (arrayOfChar[0] & 0xFF) {
        case 0:
        
        case 1:
        
        case 2:
        
        case 3:
        
        case 4:
        
        case 5:
        
        case 6:
        
        case 7:
        
        case 8:
        
        case 9:
        
        case 10:
        
        case 11:
        
        case 12:
        
        case 13:
        
        case 14:
        
        case 15:
        
        case 16:
        
        case 17:
        
        case 18:
        
        case 19:
        
        case 20:
        
        case 21:
        
        case 22:
        
        case 23:
        
        case 24:
        
        case 25:
        
        case 26:
        
        case 27:
        
        case 28:
        
        case 29:
        
        case 30:
        
        case 31:
        
        case 32:
        
        case 33:
        
        case 34:
        
        case 35:
        
        case 36:
        
        case 37:
        
        case 38:
        
        case 39:
        
        case 40:
        
        case 41:
        
        case 42:
        
        case 43:
        
        case 44:
        
        case 45:
        
        case 46:
        
        case 47:
        
        case 48:
        
        case 49:
        
        case 50:
        
        case 51:
        
        case 52:
        
        case 53:
        
        case 54:
        
        case 55:
        
        case 56:
        
        case 57:
        
        case 58:
        
        case 59:
        
        case 60:
        
        case 61:
        
        case 62:
        
        case 63:
        
        case 64:
        
        case 65:
        
        case 66:
        
        case 67:
        
        case 68:
        
        case 69:
        
        case 70:
        
        case 71:
        
        case 72:
        
        case 73:
        
        case 74:
        
        case 75:
        
        case 76:
        
        case 77:
        
        case 78:
        
        case 79:
        
        case 80:
        
        case 81:
        
        case 82:
        
        case 83:
        
        case 84:
        
        case 85:
        
        case 86:
        
        case 87:
        
        case 88:
        
        case 89:
        
        case 90:
        
        case 91:
        
        case 92:
        
        case 93:
        
        case 94:
        
        case 95:
        
        case 96:
        
        case 97:
        
        case 98:
        
        case 99:
        
        case 100:
        
        case 101:
        
        case 102:
        
        case 103:
        
        case 104:
        
        case 105:
        
        case 106:
        
        case 107:
        
        case 108:
        
        case 109:
        
        case 110:
        
        case 111:
        
        case 112:
        
        case 113:
        
        case 114:
        
        case 115:
        
        case 116:
        
        case 117:
        
        case 118:
        
        case 119:
        
        case 120:
        
        case 121:
        
        case 122:
        
        case 123:
        
        case 124:
        
        case 125:
        
        case 126:
        
        case 127:
        
        case 128:
        
        case 129:
        
        case 130:
        
        case 131:
        
        case 132:
        
        case 133:
        
        case 134:
        
        case 135:
        
        case 136:
        
        case 137:
        
        case 138:
        
        case 139:
        
        case 140:
        
        case 141:
        
        case 142:
        
        case 143:
        
        case 144:
        
        case 145:
        
        case 146:
        
        case 147:
        
        case 148:
        
        case 149:
        
        case 150:
        
        case 151:
        
        case 152:
        
        case 153:
        
        case 154:
        
        case 155:
        
        case 156:
        
        case 157:
        
        case 158:
        
        case 159:
        
        case 160:
        
        case 161:
        
        case 162:
        
        case 163:
        
        case 164:
        
        case 165:
        
        case 166:
        
        case 167:
        
        case 168:
        
        case 169:
        
        case 170:
        
        case 171:
        
        case 172:
        
        case 173:
        
        case 174:
        
        case 175:
        
        case 176:
        
        case 177:
        
        case 178:
        
        case 179:
        
        case 180:
        
        case 181:
        
        case 182:
        
        case 183:
        
        case 184:
        
        case 185:
        
        case 186:
        
        case 187:
        
        case 188:
        
        case 189:
        
        case 190:
        
        case 191:
        
        case 192:
        
        case 193:
        
        case 194:
        
        case 195:
        
        case 196:
        
        case 197:
        
        case 198:
        
        case 199:
        
        case 200:
        
        case 201:
        
        case 202:
        
        case 203:
        
        case 204:
        
        case 205:
        
        case 206:
        
        case 207:
        
        case 208:
        
        case 209:
        
        case 210:
        
        case 211:
        
        case 212:
        
        case 213:
        
        case 214:
        
        case 215:
        
        case 216:
        
        case 217:
        
        case 218:
        
        case 219:
        
        case 220:
        
        case 221:
        
        case 222:
        
        case 223:
        
        case 224:
        
        case 225:
        
        case 226:
        
        case 227:
        
        case 228:
        
        case 229:
        
        case 230:
        
        case 231:
        
        case 232:
        
        case 233:
        
        case 234:
        
        case 235:
        
        case 236:
        
        case 237:
        
        case 238:
        
        case 239:
        
        case 240:
        
        case 241:
        
        case 242:
        
        case 243:
        
        case 244:
        
        case 245:
        
        case 246:
        
        case 247:
        
        case 248:
        
        case 249:
        
        case 250:
        
        case 251:
        
        case 252:
        
        case 253:
        
        case 254:
        
        default:
          break;
      } 
      byte b1 = 5;
      int j = (paramInt2 & 0xFF) - b1;
      if (j < 0)
        j += 256; 
      int k = ((paramInt2 & 0xFFFF) >>> 8) - b1;
      if (k < 0)
        k += 256; 
      for (byte b2 = 0; b2 < arrayOfChar.length; b2++) {
        int m = b2 % 2;
        if (m == 0) {
          arrayOfChar[b2] = (char)(arrayOfChar[b2] ^ j);
          j = ((j >>> 3 | j << 5) ^ arrayOfChar[b2]) & 0xFF;
        } else {
          arrayOfChar[b2] = (char)(arrayOfChar[b2] ^ k);
          k = ((k >>> 3 | k << 5) ^ arrayOfChar[b2]) & 0xFF;
        } 
      } 
      b[i] = (new String(arrayOfChar)).intern();
    } 
    return b[i];
  }
}


/* Location:              C:\Program Files\BurpSuitePro\burpsuite_pro.jar!\burp\Zs4v.class
 * Java compiler version: 21 (65.0)
 * JD-Core Version:       1.1.3
 */