package burp;

abstract class Zs4x implements Zmky {
  private boolean ZP;
  
  private boolean ZY;
  
  public void ZI(Ztu8 paramZtu8) {
    // Byte code:
    //   0: invokestatic ZG : ()[Ljava/lang/String;
    //   3: astore_2
    //   4: aload_0
    //   5: getfield ZP : Z
    //   8: ifeq -> 27
    //   11: aload_1
    //   12: invokestatic ZD : (Lburp/Ztu8;)Z
    //   15: ifeq -> 105
    //   18: aload_0
    //   19: iconst_0
    //   20: putfield ZP : Z
    //   23: aload_2
    //   24: ifnull -> 105
    //   27: aload_0
    //   28: getfield ZY : Z
    //   31: ifeq -> 50
    //   34: aload_1
    //   35: invokestatic ZN : (Lburp/Ztu8;)Z
    //   38: ifeq -> 105
    //   41: aload_0
    //   42: iconst_0
    //   43: putfield ZY : Z
    //   46: aload_2
    //   47: ifnull -> 105
    //   50: aload_1
    //   51: invokestatic ZS : (Lburp/Ztu8;)Z
    //   54: ifeq -> 77
    //   57: aload_1
    //   58: invokeinterface Zlv : ()Ljava/lang/String;
    //   63: astore_3
    //   64: aload_3
    //   65: ifnull -> 73
    //   68: aload_0
    //   69: aload_3
    //   70: invokevirtual ZM : (Ljava/lang/String;)V
    //   73: aload_2
    //   74: ifnull -> 105
    //   77: aload_1
    //   78: invokestatic ZH : (Lburp/Ztu8;)Z
    //   81: ifeq -> 93
    //   84: aload_0
    //   85: iconst_1
    //   86: putfield ZP : Z
    //   89: aload_2
    //   90: ifnull -> 105
    //   93: aload_1
    //   94: invokestatic ZL : (Lburp/Ztu8;)Z
    //   97: ifeq -> 105
    //   100: aload_0
    //   101: iconst_1
    //   102: putfield ZY : Z
    //   105: return
  }
  
  abstract void ZM(String paramString);
}


/* Location:              C:\Program Files\BurpSuitePro\burpsuite_pro.jar!\burp\Zs4x.class
 * Java compiler version: 21 (65.0)
 * JD-Core Version:       1.1.3
 */