package burp;

import java.math.BigInteger;

class Zs5y extends ClassLoader {
  static Object Zd;
  
  static String ZO;
  
  private static final String[] a;
  
  private static final String[] b;
  
  static void ZX(Object[] paramArrayOfObject, Object paramObject) throws Throwable {}
  
  static void ZX(Object paramObject) {
    Ztq2.Zt = a(6024, 21252);
    Ztq2.Zj = new BigInteger(a(6030, -21758));
    boolean bool = Zt2e.ZN();
    try {
      try {
        if (Ze25.Zp.charAt(Math.abs(((BigInteger)Zm7v.ZP).intValue() % 32)) > Zbjx.ZA.charAt(Math.abs(((BigInteger)Zmli.Zh).intValue() % 32))) {
          try {
            Ztdd.Zc(Class.forName(a(6028, -27697)));
            if (!bool)
              Zscf.ZV(Class.forName(a(6029, -12413))); 
          } catch (Throwable throwable) {
            throw a(null);
          } 
          return;
        } 
      } catch (Throwable throwable) {
        throw a(null);
      } 
      Zscf.ZV(Class.forName(a(6029, -12413)));
    } catch (Throwable throwable) {}
  }
  
  static boolean ZZ(Object[] paramArrayOfObject, Object paramObject) throws Throwable {
    // Byte code:
    //   0: invokestatic ZK : ()Z
    //   3: istore_2
    //   4: getstatic burp/Zzr8.ZC : Ljava/lang/Object;
    //   7: checkcast java/math/BigInteger
    //   10: invokevirtual toByteArray : ()[B
    //   13: astore_3
    //   14: aload_3
    //   15: arraylength
    //   16: bipush #8
    //   18: iadd
    //   19: bipush #6
    //   21: ishr
    //   22: iconst_1
    //   23: iadd
    //   24: bipush #16
    //   26: imul
    //   27: newarray int
    //   29: astore #5
    //   31: iconst_0
    //   32: istore #6
    //   34: iload #6
    //   36: aload_3
    //   37: arraylength
    //   38: if_icmpge -> 81
    //   41: aload_3
    //   42: iload #6
    //   44: baload
    //   45: sipush #255
    //   48: iand
    //   49: istore #7
    //   51: aload #5
    //   53: iload #6
    //   55: iconst_2
    //   56: ishr
    //   57: dup2
    //   58: iaload
    //   59: iload #7
    //   61: bipush #24
    //   63: iload #6
    //   65: iconst_4
    //   66: irem
    //   67: bipush #8
    //   69: imul
    //   70: isub
    //   71: ishl
    //   72: ior
    //   73: iastore
    //   74: iinc #6, 1
    //   77: iload_2
    //   78: ifeq -> 34
    //   81: aload #5
    //   83: iload #6
    //   85: iconst_2
    //   86: ishr
    //   87: dup2
    //   88: iaload
    //   89: sipush #128
    //   92: bipush #24
    //   94: iload #6
    //   96: iconst_4
    //   97: irem
    //   98: bipush #8
    //   100: imul
    //   101: isub
    //   102: ishl
    //   103: ior
    //   104: iastore
    //   105: aload #5
    //   107: aload #5
    //   109: arraylength
    //   110: iconst_1
    //   111: isub
    //   112: aload_3
    //   113: arraylength
    //   114: bipush #8
    //   116: imul
    //   117: iastore
    //   118: bipush #80
    //   120: newarray int
    //   122: astore #7
    //   124: ldc 1732584193
    //   126: istore #8
    //   128: ldc -271733879
    //   130: istore #9
    //   132: ldc -1732584194
    //   134: istore #10
    //   136: ldc 271733878
    //   138: istore #11
    //   140: ldc -1009589776
    //   142: istore #12
    //   144: iconst_0
    //   145: istore #6
    //   147: iload #6
    //   149: aload #5
    //   151: arraylength
    //   152: if_icmpge -> 474
    //   155: iload #8
    //   157: istore #13
    //   159: iload #9
    //   161: istore #14
    //   163: iload #10
    //   165: istore #15
    //   167: iload #11
    //   169: istore #16
    //   171: iload #12
    //   173: istore #17
    //   175: iconst_0
    //   176: istore #18
    //   178: iload #18
    //   180: bipush #80
    //   182: if_icmpge -> 432
    //   185: iload #18
    //   187: bipush #16
    //   189: if_icmpge -> 216
    //   192: aload #7
    //   194: iload #18
    //   196: aload #5
    //   198: iload #6
    //   200: iload #18
    //   202: iadd
    //   203: iaload
    //   204: iastore
    //   205: iload_2
    //   206: ifeq -> 271
    //   209: goto -> 216
    //   212: invokestatic a : (Ljava/lang/Throwable;)Ljava/lang/Throwable;
    //   215: athrow
    //   216: aload #7
    //   218: iload #18
    //   220: iconst_3
    //   221: isub
    //   222: iaload
    //   223: aload #7
    //   225: iload #18
    //   227: bipush #8
    //   229: isub
    //   230: iaload
    //   231: ixor
    //   232: aload #7
    //   234: iload #18
    //   236: bipush #14
    //   238: isub
    //   239: iaload
    //   240: ixor
    //   241: aload #7
    //   243: iload #18
    //   245: bipush #16
    //   247: isub
    //   248: iaload
    //   249: ixor
    //   250: istore #19
    //   252: iload #19
    //   254: iconst_1
    //   255: ishl
    //   256: iload #19
    //   258: bipush #31
    //   260: iushr
    //   261: ior
    //   262: istore #20
    //   264: aload #7
    //   266: iload #18
    //   268: iload #20
    //   270: iastore
    //   271: iload #8
    //   273: iconst_5
    //   274: ishl
    //   275: iload #8
    //   277: bipush #27
    //   279: iushr
    //   280: ior
    //   281: istore #19
    //   283: iload #19
    //   285: iload #12
    //   287: iadd
    //   288: aload #7
    //   290: iload #18
    //   292: iaload
    //   293: iadd
    //   294: iload #18
    //   296: bipush #20
    //   298: if_icmpge -> 324
    //   301: ldc 1518500249
    //   303: iload #9
    //   305: iload #10
    //   307: iand
    //   308: iload #9
    //   310: iconst_m1
    //   311: ixor
    //   312: iload #11
    //   314: iand
    //   315: ior
    //   316: iadd
    //   317: goto -> 394
    //   320: invokestatic a : (Ljava/lang/Throwable;)Ljava/lang/Throwable;
    //   323: athrow
    //   324: iload #18
    //   326: bipush #40
    //   328: if_icmpge -> 349
    //   331: ldc 1859775393
    //   333: iload #9
    //   335: iload #10
    //   337: ixor
    //   338: iload #11
    //   340: ixor
    //   341: iadd
    //   342: goto -> 394
    //   345: invokestatic a : (Ljava/lang/Throwable;)Ljava/lang/Throwable;
    //   348: athrow
    //   349: iload #18
    //   351: bipush #60
    //   353: if_icmpge -> 383
    //   356: ldc -1894007588
    //   358: iload #9
    //   360: iload #10
    //   362: iand
    //   363: iload #9
    //   365: iload #11
    //   367: iand
    //   368: ior
    //   369: iload #10
    //   371: iload #11
    //   373: iand
    //   374: ior
    //   375: iadd
    //   376: goto -> 394
    //   379: invokestatic a : (Ljava/lang/Throwable;)Ljava/lang/Throwable;
    //   382: athrow
    //   383: ldc -899497514
    //   385: iload #9
    //   387: iload #10
    //   389: ixor
    //   390: iload #11
    //   392: ixor
    //   393: iadd
    //   394: iadd
    //   395: istore #20
    //   397: iload #11
    //   399: istore #12
    //   401: iload #10
    //   403: istore #11
    //   405: iload #9
    //   407: bipush #30
    //   409: ishl
    //   410: iload #9
    //   412: iconst_2
    //   413: iushr
    //   414: ior
    //   415: istore #10
    //   417: iload #8
    //   419: istore #9
    //   421: iload #20
    //   423: istore #8
    //   425: iinc #18, 1
    //   428: iload_2
    //   429: ifeq -> 178
    //   432: iload #8
    //   434: iload #13
    //   436: iadd
    //   437: istore #8
    //   439: iload #9
    //   441: iload #14
    //   443: iadd
    //   444: istore #9
    //   446: iload #10
    //   448: iload #15
    //   450: iadd
    //   451: istore #10
    //   453: iload #11
    //   455: iload #16
    //   457: iadd
    //   458: istore #11
    //   460: iload #12
    //   462: iload #17
    //   464: iadd
    //   465: istore #12
    //   467: iinc #6, 16
    //   470: iload_2
    //   471: ifeq -> 147
    //   474: iconst_5
    //   475: newarray int
    //   477: dup
    //   478: iconst_0
    //   479: iload #8
    //   481: iastore
    //   482: dup
    //   483: iconst_1
    //   484: iload #9
    //   486: iastore
    //   487: dup
    //   488: iconst_2
    //   489: iload #10
    //   491: iastore
    //   492: dup
    //   493: iconst_3
    //   494: iload #11
    //   496: iastore
    //   497: dup
    //   498: iconst_4
    //   499: iload #12
    //   501: iastore
    //   502: astore #13
    //   504: bipush #20
    //   506: newarray byte
    //   508: astore #14
    //   510: iconst_0
    //   511: istore #15
    //   513: iload #15
    //   515: bipush #20
    //   517: if_icmpge -> 558
    //   520: aload #13
    //   522: iload #15
    //   524: iconst_4
    //   525: idiv
    //   526: iaload
    //   527: istore #16
    //   529: iconst_3
    //   530: iload #15
    //   532: iconst_4
    //   533: irem
    //   534: isub
    //   535: bipush #8
    //   537: imul
    //   538: istore #17
    //   540: aload #14
    //   542: iload #15
    //   544: iload #16
    //   546: iload #17
    //   548: iushr
    //   549: i2b
    //   550: bastore
    //   551: iinc #15, 1
    //   554: iload_2
    //   555: ifeq -> 513
    //   558: aload #14
    //   560: astore #4
    //   562: new java/math/BigInteger
    //   565: dup
    //   566: aload #4
    //   568: invokespecial <init> : ([B)V
    //   571: invokevirtual abs : ()Ljava/math/BigInteger;
    //   574: putstatic burp/Zbsz.ZP : Ljava/lang/Object;
    //   577: getstatic burp/Ztdl.Zw : Ljava/lang/Object;
    //   580: checkcast java/math/BigInteger
    //   583: invokevirtual toByteArray : ()[B
    //   586: astore_3
    //   587: bipush #64
    //   589: newarray byte
    //   591: dup
    //   592: iconst_0
    //   593: bipush #-128
    //   595: bastore
    //   596: dup
    //   597: iconst_1
    //   598: iconst_0
    //   599: bastore
    //   600: dup
    //   601: iconst_2
    //   602: iconst_0
    //   603: bastore
    //   604: dup
    //   605: iconst_3
    //   606: iconst_0
    //   607: bastore
    //   608: dup
    //   609: iconst_4
    //   610: iconst_0
    //   611: bastore
    //   612: dup
    //   613: iconst_5
    //   614: iconst_0
    //   615: bastore
    //   616: dup
    //   617: bipush #6
    //   619: iconst_0
    //   620: bastore
    //   621: dup
    //   622: bipush #7
    //   624: iconst_0
    //   625: bastore
    //   626: dup
    //   627: bipush #8
    //   629: iconst_0
    //   630: bastore
    //   631: dup
    //   632: bipush #9
    //   634: iconst_0
    //   635: bastore
    //   636: dup
    //   637: bipush #10
    //   639: iconst_0
    //   640: bastore
    //   641: dup
    //   642: bipush #11
    //   644: iconst_0
    //   645: bastore
    //   646: dup
    //   647: bipush #12
    //   649: iconst_0
    //   650: bastore
    //   651: dup
    //   652: bipush #13
    //   654: iconst_0
    //   655: bastore
    //   656: dup
    //   657: bipush #14
    //   659: iconst_0
    //   660: bastore
    //   661: dup
    //   662: bipush #15
    //   664: iconst_0
    //   665: bastore
    //   666: dup
    //   667: bipush #16
    //   669: iconst_0
    //   670: bastore
    //   671: dup
    //   672: bipush #17
    //   674: iconst_0
    //   675: bastore
    //   676: dup
    //   677: bipush #18
    //   679: iconst_0
    //   680: bastore
    //   681: dup
    //   682: bipush #19
    //   684: iconst_0
    //   685: bastore
    //   686: dup
    //   687: bipush #20
    //   689: iconst_0
    //   690: bastore
    //   691: dup
    //   692: bipush #21
    //   694: iconst_0
    //   695: bastore
    //   696: dup
    //   697: bipush #22
    //   699: iconst_0
    //   700: bastore
    //   701: dup
    //   702: bipush #23
    //   704: iconst_0
    //   705: bastore
    //   706: dup
    //   707: bipush #24
    //   709: iconst_0
    //   710: bastore
    //   711: dup
    //   712: bipush #25
    //   714: iconst_0
    //   715: bastore
    //   716: dup
    //   717: bipush #26
    //   719: iconst_0
    //   720: bastore
    //   721: dup
    //   722: bipush #27
    //   724: iconst_0
    //   725: bastore
    //   726: dup
    //   727: bipush #28
    //   729: iconst_0
    //   730: bastore
    //   731: dup
    //   732: bipush #29
    //   734: iconst_0
    //   735: bastore
    //   736: dup
    //   737: bipush #30
    //   739: iconst_0
    //   740: bastore
    //   741: dup
    //   742: bipush #31
    //   744: iconst_0
    //   745: bastore
    //   746: dup
    //   747: bipush #32
    //   749: iconst_0
    //   750: bastore
    //   751: dup
    //   752: bipush #33
    //   754: iconst_0
    //   755: bastore
    //   756: dup
    //   757: bipush #34
    //   759: iconst_0
    //   760: bastore
    //   761: dup
    //   762: bipush #35
    //   764: iconst_0
    //   765: bastore
    //   766: dup
    //   767: bipush #36
    //   769: iconst_0
    //   770: bastore
    //   771: dup
    //   772: bipush #37
    //   774: iconst_0
    //   775: bastore
    //   776: dup
    //   777: bipush #38
    //   779: iconst_0
    //   780: bastore
    //   781: dup
    //   782: bipush #39
    //   784: iconst_0
    //   785: bastore
    //   786: dup
    //   787: bipush #40
    //   789: iconst_0
    //   790: bastore
    //   791: dup
    //   792: bipush #41
    //   794: iconst_0
    //   795: bastore
    //   796: dup
    //   797: bipush #42
    //   799: iconst_0
    //   800: bastore
    //   801: dup
    //   802: bipush #43
    //   804: iconst_0
    //   805: bastore
    //   806: dup
    //   807: bipush #44
    //   809: iconst_0
    //   810: bastore
    //   811: dup
    //   812: bipush #45
    //   814: iconst_0
    //   815: bastore
    //   816: dup
    //   817: bipush #46
    //   819: iconst_0
    //   820: bastore
    //   821: dup
    //   822: bipush #47
    //   824: iconst_0
    //   825: bastore
    //   826: dup
    //   827: bipush #48
    //   829: iconst_0
    //   830: bastore
    //   831: dup
    //   832: bipush #49
    //   834: iconst_0
    //   835: bastore
    //   836: dup
    //   837: bipush #50
    //   839: iconst_0
    //   840: bastore
    //   841: dup
    //   842: bipush #51
    //   844: iconst_0
    //   845: bastore
    //   846: dup
    //   847: bipush #52
    //   849: iconst_0
    //   850: bastore
    //   851: dup
    //   852: bipush #53
    //   854: iconst_0
    //   855: bastore
    //   856: dup
    //   857: bipush #54
    //   859: iconst_0
    //   860: bastore
    //   861: dup
    //   862: bipush #55
    //   864: iconst_0
    //   865: bastore
    //   866: dup
    //   867: bipush #56
    //   869: iconst_0
    //   870: bastore
    //   871: dup
    //   872: bipush #57
    //   874: iconst_0
    //   875: bastore
    //   876: dup
    //   877: bipush #58
    //   879: iconst_0
    //   880: bastore
    //   881: dup
    //   882: bipush #59
    //   884: iconst_0
    //   885: bastore
    //   886: dup
    //   887: bipush #60
    //   889: iconst_0
    //   890: bastore
    //   891: dup
    //   892: bipush #61
    //   894: iconst_0
    //   895: bastore
    //   896: dup
    //   897: bipush #62
    //   899: iconst_0
    //   900: bastore
    //   901: dup
    //   902: bipush #63
    //   904: iconst_0
    //   905: bastore
    //   906: astore #5
    //   908: bipush #64
    //   910: newarray int
    //   912: dup
    //   913: iconst_0
    //   914: ldc 1116352408
    //   916: iastore
    //   917: dup
    //   918: iconst_1
    //   919: ldc 1899447441
    //   921: iastore
    //   922: dup
    //   923: iconst_2
    //   924: ldc -1245643825
    //   926: iastore
    //   927: dup
    //   928: iconst_3
    //   929: ldc -373957723
    //   931: iastore
    //   932: dup
    //   933: iconst_4
    //   934: ldc 961987163
    //   936: iastore
    //   937: dup
    //   938: iconst_5
    //   939: ldc 1508970993
    //   941: iastore
    //   942: dup
    //   943: bipush #6
    //   945: ldc -1841331548
    //   947: iastore
    //   948: dup
    //   949: bipush #7
    //   951: ldc -1424204075
    //   953: iastore
    //   954: dup
    //   955: bipush #8
    //   957: ldc -670586216
    //   959: iastore
    //   960: dup
    //   961: bipush #9
    //   963: ldc 310598401
    //   965: iastore
    //   966: dup
    //   967: bipush #10
    //   969: ldc 607225278
    //   971: iastore
    //   972: dup
    //   973: bipush #11
    //   975: ldc 1426881987
    //   977: iastore
    //   978: dup
    //   979: bipush #12
    //   981: ldc 1925078388
    //   983: iastore
    //   984: dup
    //   985: bipush #13
    //   987: ldc -2132889090
    //   989: iastore
    //   990: dup
    //   991: bipush #14
    //   993: ldc -1680079193
    //   995: iastore
    //   996: dup
    //   997: bipush #15
    //   999: ldc -1046744716
    //   1001: iastore
    //   1002: dup
    //   1003: bipush #16
    //   1005: ldc -459576895
    //   1007: iastore
    //   1008: dup
    //   1009: bipush #17
    //   1011: ldc -272742522
    //   1013: iastore
    //   1014: dup
    //   1015: bipush #18
    //   1017: ldc 264347078
    //   1019: iastore
    //   1020: dup
    //   1021: bipush #19
    //   1023: ldc 604807628
    //   1025: iastore
    //   1026: dup
    //   1027: bipush #20
    //   1029: ldc 770255983
    //   1031: iastore
    //   1032: dup
    //   1033: bipush #21
    //   1035: ldc 1249150122
    //   1037: iastore
    //   1038: dup
    //   1039: bipush #22
    //   1041: ldc 1555081692
    //   1043: iastore
    //   1044: dup
    //   1045: bipush #23
    //   1047: ldc 1996064986
    //   1049: iastore
    //   1050: dup
    //   1051: bipush #24
    //   1053: ldc -1740746414
    //   1055: iastore
    //   1056: dup
    //   1057: bipush #25
    //   1059: ldc -1473132947
    //   1061: iastore
    //   1062: dup
    //   1063: bipush #26
    //   1065: ldc -1341970488
    //   1067: iastore
    //   1068: dup
    //   1069: bipush #27
    //   1071: ldc -1084653625
    //   1073: iastore
    //   1074: dup
    //   1075: bipush #28
    //   1077: ldc -958395405
    //   1079: iastore
    //   1080: dup
    //   1081: bipush #29
    //   1083: ldc -710438585
    //   1085: iastore
    //   1086: dup
    //   1087: bipush #30
    //   1089: ldc 113926993
    //   1091: iastore
    //   1092: dup
    //   1093: bipush #31
    //   1095: ldc 338241895
    //   1097: iastore
    //   1098: dup
    //   1099: bipush #32
    //   1101: ldc 666307205
    //   1103: iastore
    //   1104: dup
    //   1105: bipush #33
    //   1107: ldc 773529912
    //   1109: iastore
    //   1110: dup
    //   1111: bipush #34
    //   1113: ldc 1294757372
    //   1115: iastore
    //   1116: dup
    //   1117: bipush #35
    //   1119: ldc 1396182291
    //   1121: iastore
    //   1122: dup
    //   1123: bipush #36
    //   1125: ldc 1695183700
    //   1127: iastore
    //   1128: dup
    //   1129: bipush #37
    //   1131: ldc 1986661051
    //   1133: iastore
    //   1134: dup
    //   1135: bipush #38
    //   1137: ldc -2117940946
    //   1139: iastore
    //   1140: dup
    //   1141: bipush #39
    //   1143: ldc -1838011259
    //   1145: iastore
    //   1146: dup
    //   1147: bipush #40
    //   1149: ldc -1564481375
    //   1151: iastore
    //   1152: dup
    //   1153: bipush #41
    //   1155: ldc -1474664885
    //   1157: iastore
    //   1158: dup
    //   1159: bipush #42
    //   1161: ldc -1035236496
    //   1163: iastore
    //   1164: dup
    //   1165: bipush #43
    //   1167: ldc -949202525
    //   1169: iastore
    //   1170: dup
    //   1171: bipush #44
    //   1173: ldc -778901479
    //   1175: iastore
    //   1176: dup
    //   1177: bipush #45
    //   1179: ldc -694614492
    //   1181: iastore
    //   1182: dup
    //   1183: bipush #46
    //   1185: ldc -200395387
    //   1187: iastore
    //   1188: dup
    //   1189: bipush #47
    //   1191: ldc 275423344
    //   1193: iastore
    //   1194: dup
    //   1195: bipush #48
    //   1197: ldc 430227734
    //   1199: iastore
    //   1200: dup
    //   1201: bipush #49
    //   1203: ldc 506948616
    //   1205: iastore
    //   1206: dup
    //   1207: bipush #50
    //   1209: ldc 659060556
    //   1211: iastore
    //   1212: dup
    //   1213: bipush #51
    //   1215: ldc 883997877
    //   1217: iastore
    //   1218: dup
    //   1219: bipush #52
    //   1221: ldc 958139571
    //   1223: iastore
    //   1224: dup
    //   1225: bipush #53
    //   1227: ldc 1322822218
    //   1229: iastore
    //   1230: dup
    //   1231: bipush #54
    //   1233: ldc 1537002063
    //   1235: iastore
    //   1236: dup
    //   1237: bipush #55
    //   1239: ldc 1747873779
    //   1241: iastore
    //   1242: dup
    //   1243: bipush #56
    //   1245: ldc 1955562222
    //   1247: iastore
    //   1248: dup
    //   1249: bipush #57
    //   1251: ldc 2024104815
    //   1253: iastore
    //   1254: dup
    //   1255: bipush #58
    //   1257: ldc -2067236844
    //   1259: iastore
    //   1260: dup
    //   1261: bipush #59
    //   1263: ldc -1933114872
    //   1265: iastore
    //   1266: dup
    //   1267: bipush #60
    //   1269: ldc -1866530822
    //   1271: iastore
    //   1272: dup
    //   1273: bipush #61
    //   1275: ldc -1538233109
    //   1277: iastore
    //   1278: dup
    //   1279: bipush #62
    //   1281: ldc -1090935817
    //   1283: iastore
    //   1284: dup
    //   1285: bipush #63
    //   1287: ldc -965641998
    //   1289: iastore
    //   1290: astore #6
    //   1292: iconst_2
    //   1293: newarray int
    //   1295: dup
    //   1296: iconst_0
    //   1297: iconst_0
    //   1298: iastore
    //   1299: dup
    //   1300: iconst_1
    //   1301: iconst_0
    //   1302: iastore
    //   1303: astore #7
    //   1305: bipush #8
    //   1307: newarray int
    //   1309: dup
    //   1310: iconst_0
    //   1311: ldc 1779033703
    //   1313: iastore
    //   1314: dup
    //   1315: iconst_1
    //   1316: ldc -1150833019
    //   1318: iastore
    //   1319: dup
    //   1320: iconst_2
    //   1321: ldc 1013904242
    //   1323: iastore
    //   1324: dup
    //   1325: iconst_3
    //   1326: ldc -1521486534
    //   1328: iastore
    //   1329: dup
    //   1330: iconst_4
    //   1331: ldc 1359893119
    //   1333: iastore
    //   1334: dup
    //   1335: iconst_5
    //   1336: ldc -1694144372
    //   1338: iastore
    //   1339: dup
    //   1340: bipush #6
    //   1342: ldc 528734635
    //   1344: iastore
    //   1345: dup
    //   1346: bipush #7
    //   1348: ldc 1541459225
    //   1350: iastore
    //   1351: astore #8
    //   1353: bipush #64
    //   1355: newarray byte
    //   1357: astore #9
    //   1359: bipush #64
    //   1361: newarray byte
    //   1363: astore #10
    //   1365: aload_3
    //   1366: arraylength
    //   1367: istore #11
    //   1369: aload #7
    //   1371: iconst_0
    //   1372: iaload
    //   1373: bipush #63
    //   1375: iand
    //   1376: istore #12
    //   1378: aload #7
    //   1380: iconst_0
    //   1381: dup2
    //   1382: iaload
    //   1383: iload #11
    //   1385: iadd
    //   1386: iastore
    //   1387: aload #7
    //   1389: iconst_0
    //   1390: dup2
    //   1391: iaload
    //   1392: iconst_m1
    //   1393: iand
    //   1394: iastore
    //   1395: aload #7
    //   1397: iconst_0
    //   1398: iaload
    //   1399: iload #11
    //   1401: if_icmpge -> 1419
    //   1404: aload #7
    //   1406: iconst_1
    //   1407: dup2
    //   1408: iaload
    //   1409: iconst_1
    //   1410: iadd
    //   1411: iastore
    //   1412: goto -> 1419
    //   1415: invokestatic a : (Ljava/lang/Throwable;)Ljava/lang/Throwable;
    //   1418: athrow
    //   1419: iconst_0
    //   1420: istore #13
    //   1422: iload #11
    //   1424: bipush #64
    //   1426: if_icmplt -> 2035
    //   1429: iconst_0
    //   1430: istore #14
    //   1432: iload #14
    //   1434: bipush #64
    //   1436: if_icmpge -> 1458
    //   1439: aload #10
    //   1441: iload #14
    //   1443: aload_3
    //   1444: iload #13
    //   1446: iload #14
    //   1448: iadd
    //   1449: baload
    //   1450: bastore
    //   1451: iinc #14, 1
    //   1454: iload_2
    //   1455: ifeq -> 1432
    //   1458: bipush #64
    //   1460: newarray int
    //   1462: astore #14
    //   1464: bipush #8
    //   1466: newarray int
    //   1468: astore #15
    //   1470: iconst_0
    //   1471: istore #16
    //   1473: iload #16
    //   1475: bipush #8
    //   1477: if_icmpge -> 1497
    //   1480: aload #15
    //   1482: iload #16
    //   1484: aload #8
    //   1486: iload #16
    //   1488: iaload
    //   1489: iastore
    //   1490: iinc #16, 1
    //   1493: iload_2
    //   1494: ifeq -> 1473
    //   1497: iconst_0
    //   1498: istore #16
    //   1500: iload #16
    //   1502: bipush #64
    //   1504: if_icmpge -> 1995
    //   1507: iload #16
    //   1509: bipush #16
    //   1511: if_icmpge -> 1592
    //   1514: aload #14
    //   1516: iload #16
    //   1518: aload #10
    //   1520: iconst_4
    //   1521: iload #16
    //   1523: imul
    //   1524: baload
    //   1525: sipush #255
    //   1528: iand
    //   1529: bipush #24
    //   1531: ishl
    //   1532: aload #10
    //   1534: iconst_4
    //   1535: iload #16
    //   1537: imul
    //   1538: iconst_1
    //   1539: iadd
    //   1540: baload
    //   1541: sipush #255
    //   1544: iand
    //   1545: bipush #16
    //   1547: ishl
    //   1548: ior
    //   1549: aload #10
    //   1551: iconst_4
    //   1552: iload #16
    //   1554: imul
    //   1555: iconst_2
    //   1556: iadd
    //   1557: baload
    //   1558: sipush #255
    //   1561: iand
    //   1562: bipush #8
    //   1564: ishl
    //   1565: ior
    //   1566: aload #10
    //   1568: iconst_4
    //   1569: iload #16
    //   1571: imul
    //   1572: iconst_3
    //   1573: iadd
    //   1574: baload
    //   1575: sipush #255
    //   1578: iand
    //   1579: ior
    //   1580: iastore
    //   1581: iload_2
    //   1582: ifeq -> 1735
    //   1585: goto -> 1592
    //   1588: invokestatic a : (Ljava/lang/Throwable;)Ljava/lang/Throwable;
    //   1591: athrow
    //   1592: aload #14
    //   1594: iload #16
    //   1596: aload #14
    //   1598: iload #16
    //   1600: iconst_2
    //   1601: isub
    //   1602: iaload
    //   1603: bipush #17
    //   1605: iushr
    //   1606: aload #14
    //   1608: iload #16
    //   1610: iconst_2
    //   1611: isub
    //   1612: iaload
    //   1613: bipush #15
    //   1615: ishl
    //   1616: ior
    //   1617: aload #14
    //   1619: iload #16
    //   1621: iconst_2
    //   1622: isub
    //   1623: iaload
    //   1624: bipush #19
    //   1626: iushr
    //   1627: aload #14
    //   1629: iload #16
    //   1631: iconst_2
    //   1632: isub
    //   1633: iaload
    //   1634: bipush #13
    //   1636: ishl
    //   1637: ior
    //   1638: ixor
    //   1639: aload #14
    //   1641: iload #16
    //   1643: iconst_2
    //   1644: isub
    //   1645: iaload
    //   1646: bipush #10
    //   1648: iushr
    //   1649: ixor
    //   1650: aload #14
    //   1652: iload #16
    //   1654: bipush #7
    //   1656: isub
    //   1657: iaload
    //   1658: iadd
    //   1659: aload #14
    //   1661: iload #16
    //   1663: bipush #15
    //   1665: isub
    //   1666: iaload
    //   1667: bipush #7
    //   1669: iushr
    //   1670: aload #14
    //   1672: iload #16
    //   1674: bipush #15
    //   1676: isub
    //   1677: iaload
    //   1678: bipush #25
    //   1680: ishl
    //   1681: ior
    //   1682: aload #14
    //   1684: iload #16
    //   1686: bipush #15
    //   1688: isub
    //   1689: iaload
    //   1690: bipush #18
    //   1692: iushr
    //   1693: aload #14
    //   1695: iload #16
    //   1697: bipush #15
    //   1699: isub
    //   1700: iaload
    //   1701: bipush #14
    //   1703: ishl
    //   1704: ior
    //   1705: ixor
    //   1706: aload #14
    //   1708: iload #16
    //   1710: bipush #15
    //   1712: isub
    //   1713: iaload
    //   1714: iconst_3
    //   1715: iushr
    //   1716: ixor
    //   1717: iadd
    //   1718: aload #14
    //   1720: iload #16
    //   1722: bipush #16
    //   1724: isub
    //   1725: iaload
    //   1726: iadd
    //   1727: iastore
    //   1728: goto -> 1735
    //   1731: invokestatic a : (Ljava/lang/Throwable;)Ljava/lang/Throwable;
    //   1734: athrow
    //   1735: aload #15
    //   1737: bipush #7
    //   1739: iaload
    //   1740: aload #15
    //   1742: iconst_4
    //   1743: iaload
    //   1744: bipush #6
    //   1746: iushr
    //   1747: aload #15
    //   1749: iconst_4
    //   1750: iaload
    //   1751: bipush #26
    //   1753: ishl
    //   1754: ior
    //   1755: aload #15
    //   1757: iconst_4
    //   1758: iaload
    //   1759: bipush #11
    //   1761: iushr
    //   1762: aload #15
    //   1764: iconst_4
    //   1765: iaload
    //   1766: bipush #21
    //   1768: ishl
    //   1769: ior
    //   1770: ixor
    //   1771: aload #15
    //   1773: iconst_4
    //   1774: iaload
    //   1775: bipush #25
    //   1777: iushr
    //   1778: aload #15
    //   1780: iconst_4
    //   1781: iaload
    //   1782: bipush #7
    //   1784: ishl
    //   1785: ior
    //   1786: ixor
    //   1787: iadd
    //   1788: aload #15
    //   1790: bipush #6
    //   1792: iaload
    //   1793: aload #15
    //   1795: iconst_4
    //   1796: iaload
    //   1797: aload #15
    //   1799: iconst_5
    //   1800: iaload
    //   1801: aload #15
    //   1803: bipush #6
    //   1805: iaload
    //   1806: ixor
    //   1807: iand
    //   1808: ixor
    //   1809: iadd
    //   1810: aload #6
    //   1812: iload #16
    //   1814: iaload
    //   1815: iadd
    //   1816: aload #14
    //   1818: iload #16
    //   1820: iaload
    //   1821: iadd
    //   1822: istore #17
    //   1824: aload #15
    //   1826: iconst_0
    //   1827: iaload
    //   1828: iconst_2
    //   1829: iushr
    //   1830: aload #15
    //   1832: iconst_0
    //   1833: iaload
    //   1834: bipush #30
    //   1836: ishl
    //   1837: ior
    //   1838: aload #15
    //   1840: iconst_0
    //   1841: iaload
    //   1842: bipush #13
    //   1844: iushr
    //   1845: aload #15
    //   1847: iconst_0
    //   1848: iaload
    //   1849: bipush #19
    //   1851: ishl
    //   1852: ior
    //   1853: ixor
    //   1854: aload #15
    //   1856: iconst_0
    //   1857: iaload
    //   1858: bipush #22
    //   1860: iushr
    //   1861: aload #15
    //   1863: iconst_0
    //   1864: iaload
    //   1865: bipush #10
    //   1867: ishl
    //   1868: ior
    //   1869: ixor
    //   1870: aload #15
    //   1872: iconst_0
    //   1873: iaload
    //   1874: aload #15
    //   1876: iconst_1
    //   1877: iaload
    //   1878: iand
    //   1879: aload #15
    //   1881: iconst_2
    //   1882: iaload
    //   1883: aload #15
    //   1885: iconst_0
    //   1886: iaload
    //   1887: aload #15
    //   1889: iconst_1
    //   1890: iaload
    //   1891: ior
    //   1892: iand
    //   1893: ior
    //   1894: iadd
    //   1895: istore #18
    //   1897: aload #15
    //   1899: iconst_3
    //   1900: dup2
    //   1901: iaload
    //   1902: iload #17
    //   1904: iadd
    //   1905: iastore
    //   1906: aload #15
    //   1908: bipush #7
    //   1910: iload #17
    //   1912: iload #18
    //   1914: iadd
    //   1915: iastore
    //   1916: aload #15
    //   1918: bipush #7
    //   1920: iaload
    //   1921: istore #17
    //   1923: aload #15
    //   1925: bipush #7
    //   1927: aload #15
    //   1929: bipush #6
    //   1931: iaload
    //   1932: iastore
    //   1933: aload #15
    //   1935: bipush #6
    //   1937: aload #15
    //   1939: iconst_5
    //   1940: iaload
    //   1941: iastore
    //   1942: aload #15
    //   1944: iconst_5
    //   1945: aload #15
    //   1947: iconst_4
    //   1948: iaload
    //   1949: iastore
    //   1950: aload #15
    //   1952: iconst_4
    //   1953: aload #15
    //   1955: iconst_3
    //   1956: iaload
    //   1957: iastore
    //   1958: aload #15
    //   1960: iconst_3
    //   1961: aload #15
    //   1963: iconst_2
    //   1964: iaload
    //   1965: iastore
    //   1966: aload #15
    //   1968: iconst_2
    //   1969: aload #15
    //   1971: iconst_1
    //   1972: iaload
    //   1973: iastore
    //   1974: aload #15
    //   1976: iconst_1
    //   1977: aload #15
    //   1979: iconst_0
    //   1980: iaload
    //   1981: iastore
    //   1982: aload #15
    //   1984: iconst_0
    //   1985: iload #17
    //   1987: iastore
    //   1988: iinc #16, 1
    //   1991: iload_2
    //   1992: ifeq -> 1500
    //   1995: iconst_0
    //   1996: istore #16
    //   1998: iload #16
    //   2000: bipush #8
    //   2002: if_icmpge -> 2025
    //   2005: aload #8
    //   2007: iload #16
    //   2009: dup2
    //   2010: iaload
    //   2011: aload #15
    //   2013: iload #16
    //   2015: iaload
    //   2016: iadd
    //   2017: iastore
    //   2018: iinc #16, 1
    //   2021: iload_2
    //   2022: ifeq -> 1998
    //   2025: iinc #13, 64
    //   2028: iinc #11, -64
    //   2031: iload_2
    //   2032: ifeq -> 1422
    //   2035: iload #11
    //   2037: ifle -> 2072
    //   2040: iconst_0
    //   2041: istore #14
    //   2043: iload #14
    //   2045: iload #11
    //   2047: if_icmpge -> 2072
    //   2050: aload #9
    //   2052: iload #12
    //   2054: iload #14
    //   2056: iadd
    //   2057: aload_3
    //   2058: iload #13
    //   2060: iload #14
    //   2062: iadd
    //   2063: baload
    //   2064: bastore
    //   2065: iinc #14, 1
    //   2068: iload_2
    //   2069: ifeq -> 2043
    //   2072: aload #7
    //   2074: iconst_0
    //   2075: iaload
    //   2076: bipush #29
    //   2078: iushr
    //   2079: aload #7
    //   2081: iconst_1
    //   2082: iaload
    //   2083: iconst_3
    //   2084: ishl
    //   2085: ior
    //   2086: istore #14
    //   2088: aload #7
    //   2090: iconst_0
    //   2091: iaload
    //   2092: iconst_3
    //   2093: ishl
    //   2094: istore #15
    //   2096: aload #7
    //   2098: iconst_0
    //   2099: iaload
    //   2100: bipush #63
    //   2102: iand
    //   2103: istore #16
    //   2105: iload #16
    //   2107: bipush #56
    //   2109: if_icmpge -> 2124
    //   2112: bipush #56
    //   2114: iload #16
    //   2116: isub
    //   2117: goto -> 2129
    //   2120: invokestatic a : (Ljava/lang/Throwable;)Ljava/lang/Throwable;
    //   2123: athrow
    //   2124: bipush #120
    //   2126: iload #16
    //   2128: isub
    //   2129: istore #17
    //   2131: aload #7
    //   2133: iconst_0
    //   2134: iaload
    //   2135: bipush #63
    //   2137: iand
    //   2138: istore #12
    //   2140: bipush #64
    //   2142: iload #12
    //   2144: isub
    //   2145: istore #18
    //   2147: aload #7
    //   2149: iconst_0
    //   2150: dup2
    //   2151: iaload
    //   2152: iload #17
    //   2154: iadd
    //   2155: iastore
    //   2156: aload #7
    //   2158: iconst_0
    //   2159: dup2
    //   2160: iaload
    //   2161: iconst_m1
    //   2162: iand
    //   2163: iastore
    //   2164: aload #7
    //   2166: iconst_0
    //   2167: iaload
    //   2168: iload #17
    //   2170: if_icmpge -> 2188
    //   2173: aload #7
    //   2175: iconst_1
    //   2176: dup2
    //   2177: iaload
    //   2178: iconst_1
    //   2179: iadd
    //   2180: iastore
    //   2181: goto -> 2188
    //   2184: invokestatic a : (Ljava/lang/Throwable;)Ljava/lang/Throwable;
    //   2187: athrow
    //   2188: iconst_0
    //   2189: istore #13
    //   2191: iload #12
    //   2193: ifle -> 2824
    //   2196: iload #17
    //   2198: iload #18
    //   2200: if_icmplt -> 2824
    //   2203: goto -> 2210
    //   2206: invokestatic a : (Ljava/lang/Throwable;)Ljava/lang/Throwable;
    //   2209: athrow
    //   2210: iconst_0
    //   2211: istore #19
    //   2213: iload #19
    //   2215: iload #18
    //   2217: if_icmpge -> 2240
    //   2220: aload #9
    //   2222: iload #12
    //   2224: iload #19
    //   2226: iadd
    //   2227: aload #5
    //   2229: iload #19
    //   2231: baload
    //   2232: bastore
    //   2233: iinc #19, 1
    //   2236: iload_2
    //   2237: ifeq -> 2213
    //   2240: bipush #64
    //   2242: newarray int
    //   2244: astore #19
    //   2246: bipush #8
    //   2248: newarray int
    //   2250: astore #20
    //   2252: iconst_0
    //   2253: istore #21
    //   2255: iload #21
    //   2257: bipush #8
    //   2259: if_icmpge -> 2279
    //   2262: aload #20
    //   2264: iload #21
    //   2266: aload #8
    //   2268: iload #21
    //   2270: iaload
    //   2271: iastore
    //   2272: iinc #21, 1
    //   2275: iload_2
    //   2276: ifeq -> 2255
    //   2279: iconst_0
    //   2280: istore #21
    //   2282: iload #21
    //   2284: bipush #64
    //   2286: if_icmpge -> 2777
    //   2289: iload #21
    //   2291: bipush #16
    //   2293: if_icmpge -> 2374
    //   2296: aload #19
    //   2298: iload #21
    //   2300: aload #9
    //   2302: iconst_4
    //   2303: iload #21
    //   2305: imul
    //   2306: baload
    //   2307: sipush #255
    //   2310: iand
    //   2311: bipush #24
    //   2313: ishl
    //   2314: aload #9
    //   2316: iconst_4
    //   2317: iload #21
    //   2319: imul
    //   2320: iconst_1
    //   2321: iadd
    //   2322: baload
    //   2323: sipush #255
    //   2326: iand
    //   2327: bipush #16
    //   2329: ishl
    //   2330: ior
    //   2331: aload #9
    //   2333: iconst_4
    //   2334: iload #21
    //   2336: imul
    //   2337: iconst_2
    //   2338: iadd
    //   2339: baload
    //   2340: sipush #255
    //   2343: iand
    //   2344: bipush #8
    //   2346: ishl
    //   2347: ior
    //   2348: aload #9
    //   2350: iconst_4
    //   2351: iload #21
    //   2353: imul
    //   2354: iconst_3
    //   2355: iadd
    //   2356: baload
    //   2357: sipush #255
    //   2360: iand
    //   2361: ior
    //   2362: iastore
    //   2363: iload_2
    //   2364: ifeq -> 2517
    //   2367: goto -> 2374
    //   2370: invokestatic a : (Ljava/lang/Throwable;)Ljava/lang/Throwable;
    //   2373: athrow
    //   2374: aload #19
    //   2376: iload #21
    //   2378: aload #19
    //   2380: iload #21
    //   2382: iconst_2
    //   2383: isub
    //   2384: iaload
    //   2385: bipush #17
    //   2387: iushr
    //   2388: aload #19
    //   2390: iload #21
    //   2392: iconst_2
    //   2393: isub
    //   2394: iaload
    //   2395: bipush #15
    //   2397: ishl
    //   2398: ior
    //   2399: aload #19
    //   2401: iload #21
    //   2403: iconst_2
    //   2404: isub
    //   2405: iaload
    //   2406: bipush #19
    //   2408: iushr
    //   2409: aload #19
    //   2411: iload #21
    //   2413: iconst_2
    //   2414: isub
    //   2415: iaload
    //   2416: bipush #13
    //   2418: ishl
    //   2419: ior
    //   2420: ixor
    //   2421: aload #19
    //   2423: iload #21
    //   2425: iconst_2
    //   2426: isub
    //   2427: iaload
    //   2428: bipush #10
    //   2430: iushr
    //   2431: ixor
    //   2432: aload #19
    //   2434: iload #21
    //   2436: bipush #7
    //   2438: isub
    //   2439: iaload
    //   2440: iadd
    //   2441: aload #19
    //   2443: iload #21
    //   2445: bipush #15
    //   2447: isub
    //   2448: iaload
    //   2449: bipush #7
    //   2451: iushr
    //   2452: aload #19
    //   2454: iload #21
    //   2456: bipush #15
    //   2458: isub
    //   2459: iaload
    //   2460: bipush #25
    //   2462: ishl
    //   2463: ior
    //   2464: aload #19
    //   2466: iload #21
    //   2468: bipush #15
    //   2470: isub
    //   2471: iaload
    //   2472: bipush #18
    //   2474: iushr
    //   2475: aload #19
    //   2477: iload #21
    //   2479: bipush #15
    //   2481: isub
    //   2482: iaload
    //   2483: bipush #14
    //   2485: ishl
    //   2486: ior
    //   2487: ixor
    //   2488: aload #19
    //   2490: iload #21
    //   2492: bipush #15
    //   2494: isub
    //   2495: iaload
    //   2496: iconst_3
    //   2497: iushr
    //   2498: ixor
    //   2499: iadd
    //   2500: aload #19
    //   2502: iload #21
    //   2504: bipush #16
    //   2506: isub
    //   2507: iaload
    //   2508: iadd
    //   2509: iastore
    //   2510: goto -> 2517
    //   2513: invokestatic a : (Ljava/lang/Throwable;)Ljava/lang/Throwable;
    //   2516: athrow
    //   2517: aload #20
    //   2519: bipush #7
    //   2521: iaload
    //   2522: aload #20
    //   2524: iconst_4
    //   2525: iaload
    //   2526: bipush #6
    //   2528: iushr
    //   2529: aload #20
    //   2531: iconst_4
    //   2532: iaload
    //   2533: bipush #26
    //   2535: ishl
    //   2536: ior
    //   2537: aload #20
    //   2539: iconst_4
    //   2540: iaload
    //   2541: bipush #11
    //   2543: iushr
    //   2544: aload #20
    //   2546: iconst_4
    //   2547: iaload
    //   2548: bipush #21
    //   2550: ishl
    //   2551: ior
    //   2552: ixor
    //   2553: aload #20
    //   2555: iconst_4
    //   2556: iaload
    //   2557: bipush #25
    //   2559: iushr
    //   2560: aload #20
    //   2562: iconst_4
    //   2563: iaload
    //   2564: bipush #7
    //   2566: ishl
    //   2567: ior
    //   2568: ixor
    //   2569: iadd
    //   2570: aload #20
    //   2572: bipush #6
    //   2574: iaload
    //   2575: aload #20
    //   2577: iconst_4
    //   2578: iaload
    //   2579: aload #20
    //   2581: iconst_5
    //   2582: iaload
    //   2583: aload #20
    //   2585: bipush #6
    //   2587: iaload
    //   2588: ixor
    //   2589: iand
    //   2590: ixor
    //   2591: iadd
    //   2592: aload #6
    //   2594: iload #21
    //   2596: iaload
    //   2597: iadd
    //   2598: aload #19
    //   2600: iload #21
    //   2602: iaload
    //   2603: iadd
    //   2604: istore #22
    //   2606: aload #20
    //   2608: iconst_0
    //   2609: iaload
    //   2610: iconst_2
    //   2611: iushr
    //   2612: aload #20
    //   2614: iconst_0
    //   2615: iaload
    //   2616: bipush #30
    //   2618: ishl
    //   2619: ior
    //   2620: aload #20
    //   2622: iconst_0
    //   2623: iaload
    //   2624: bipush #13
    //   2626: iushr
    //   2627: aload #20
    //   2629: iconst_0
    //   2630: iaload
    //   2631: bipush #19
    //   2633: ishl
    //   2634: ior
    //   2635: ixor
    //   2636: aload #20
    //   2638: iconst_0
    //   2639: iaload
    //   2640: bipush #22
    //   2642: iushr
    //   2643: aload #20
    //   2645: iconst_0
    //   2646: iaload
    //   2647: bipush #10
    //   2649: ishl
    //   2650: ior
    //   2651: ixor
    //   2652: aload #20
    //   2654: iconst_0
    //   2655: iaload
    //   2656: aload #20
    //   2658: iconst_1
    //   2659: iaload
    //   2660: iand
    //   2661: aload #20
    //   2663: iconst_2
    //   2664: iaload
    //   2665: aload #20
    //   2667: iconst_0
    //   2668: iaload
    //   2669: aload #20
    //   2671: iconst_1
    //   2672: iaload
    //   2673: ior
    //   2674: iand
    //   2675: ior
    //   2676: iadd
    //   2677: istore #23
    //   2679: aload #20
    //   2681: iconst_3
    //   2682: dup2
    //   2683: iaload
    //   2684: iload #22
    //   2686: iadd
    //   2687: iastore
    //   2688: aload #20
    //   2690: bipush #7
    //   2692: iload #22
    //   2694: iload #23
    //   2696: iadd
    //   2697: iastore
    //   2698: aload #20
    //   2700: bipush #7
    //   2702: iaload
    //   2703: istore #22
    //   2705: aload #20
    //   2707: bipush #7
    //   2709: aload #20
    //   2711: bipush #6
    //   2713: iaload
    //   2714: iastore
    //   2715: aload #20
    //   2717: bipush #6
    //   2719: aload #20
    //   2721: iconst_5
    //   2722: iaload
    //   2723: iastore
    //   2724: aload #20
    //   2726: iconst_5
    //   2727: aload #20
    //   2729: iconst_4
    //   2730: iaload
    //   2731: iastore
    //   2732: aload #20
    //   2734: iconst_4
    //   2735: aload #20
    //   2737: iconst_3
    //   2738: iaload
    //   2739: iastore
    //   2740: aload #20
    //   2742: iconst_3
    //   2743: aload #20
    //   2745: iconst_2
    //   2746: iaload
    //   2747: iastore
    //   2748: aload #20
    //   2750: iconst_2
    //   2751: aload #20
    //   2753: iconst_1
    //   2754: iaload
    //   2755: iastore
    //   2756: aload #20
    //   2758: iconst_1
    //   2759: aload #20
    //   2761: iconst_0
    //   2762: iaload
    //   2763: iastore
    //   2764: aload #20
    //   2766: iconst_0
    //   2767: iload #22
    //   2769: iastore
    //   2770: iinc #21, 1
    //   2773: iload_2
    //   2774: ifeq -> 2282
    //   2777: iconst_0
    //   2778: istore #21
    //   2780: iload #21
    //   2782: bipush #8
    //   2784: if_icmpge -> 2807
    //   2787: aload #8
    //   2789: iload #21
    //   2791: dup2
    //   2792: iaload
    //   2793: aload #20
    //   2795: iload #21
    //   2797: iaload
    //   2798: iadd
    //   2799: iastore
    //   2800: iinc #21, 1
    //   2803: iload_2
    //   2804: ifeq -> 2780
    //   2807: iload #13
    //   2809: iload #18
    //   2811: iadd
    //   2812: istore #13
    //   2814: iload #17
    //   2816: iload #18
    //   2818: isub
    //   2819: istore #17
    //   2821: iconst_0
    //   2822: istore #12
    //   2824: iload #17
    //   2826: bipush #64
    //   2828: if_icmplt -> 3438
    //   2831: iconst_0
    //   2832: istore #19
    //   2834: iload #19
    //   2836: bipush #64
    //   2838: if_icmpge -> 2861
    //   2841: aload #10
    //   2843: iload #19
    //   2845: aload #5
    //   2847: iload #13
    //   2849: iload #19
    //   2851: iadd
    //   2852: baload
    //   2853: bastore
    //   2854: iinc #19, 1
    //   2857: iload_2
    //   2858: ifeq -> 2834
    //   2861: bipush #64
    //   2863: newarray int
    //   2865: astore #19
    //   2867: bipush #8
    //   2869: newarray int
    //   2871: astore #20
    //   2873: iconst_0
    //   2874: istore #21
    //   2876: iload #21
    //   2878: bipush #8
    //   2880: if_icmpge -> 2900
    //   2883: aload #20
    //   2885: iload #21
    //   2887: aload #8
    //   2889: iload #21
    //   2891: iaload
    //   2892: iastore
    //   2893: iinc #21, 1
    //   2896: iload_2
    //   2897: ifeq -> 2876
    //   2900: iconst_0
    //   2901: istore #21
    //   2903: iload #21
    //   2905: bipush #64
    //   2907: if_icmpge -> 3398
    //   2910: iload #21
    //   2912: bipush #16
    //   2914: if_icmpge -> 2995
    //   2917: aload #19
    //   2919: iload #21
    //   2921: aload #10
    //   2923: iconst_4
    //   2924: iload #21
    //   2926: imul
    //   2927: baload
    //   2928: sipush #255
    //   2931: iand
    //   2932: bipush #24
    //   2934: ishl
    //   2935: aload #10
    //   2937: iconst_4
    //   2938: iload #21
    //   2940: imul
    //   2941: iconst_1
    //   2942: iadd
    //   2943: baload
    //   2944: sipush #255
    //   2947: iand
    //   2948: bipush #16
    //   2950: ishl
    //   2951: ior
    //   2952: aload #10
    //   2954: iconst_4
    //   2955: iload #21
    //   2957: imul
    //   2958: iconst_2
    //   2959: iadd
    //   2960: baload
    //   2961: sipush #255
    //   2964: iand
    //   2965: bipush #8
    //   2967: ishl
    //   2968: ior
    //   2969: aload #10
    //   2971: iconst_4
    //   2972: iload #21
    //   2974: imul
    //   2975: iconst_3
    //   2976: iadd
    //   2977: baload
    //   2978: sipush #255
    //   2981: iand
    //   2982: ior
    //   2983: iastore
    //   2984: iload_2
    //   2985: ifeq -> 3138
    //   2988: goto -> 2995
    //   2991: invokestatic a : (Ljava/lang/Throwable;)Ljava/lang/Throwable;
    //   2994: athrow
    //   2995: aload #19
    //   2997: iload #21
    //   2999: aload #19
    //   3001: iload #21
    //   3003: iconst_2
    //   3004: isub
    //   3005: iaload
    //   3006: bipush #17
    //   3008: iushr
    //   3009: aload #19
    //   3011: iload #21
    //   3013: iconst_2
    //   3014: isub
    //   3015: iaload
    //   3016: bipush #15
    //   3018: ishl
    //   3019: ior
    //   3020: aload #19
    //   3022: iload #21
    //   3024: iconst_2
    //   3025: isub
    //   3026: iaload
    //   3027: bipush #19
    //   3029: iushr
    //   3030: aload #19
    //   3032: iload #21
    //   3034: iconst_2
    //   3035: isub
    //   3036: iaload
    //   3037: bipush #13
    //   3039: ishl
    //   3040: ior
    //   3041: ixor
    //   3042: aload #19
    //   3044: iload #21
    //   3046: iconst_2
    //   3047: isub
    //   3048: iaload
    //   3049: bipush #10
    //   3051: iushr
    //   3052: ixor
    //   3053: aload #19
    //   3055: iload #21
    //   3057: bipush #7
    //   3059: isub
    //   3060: iaload
    //   3061: iadd
    //   3062: aload #19
    //   3064: iload #21
    //   3066: bipush #15
    //   3068: isub
    //   3069: iaload
    //   3070: bipush #7
    //   3072: iushr
    //   3073: aload #19
    //   3075: iload #21
    //   3077: bipush #15
    //   3079: isub
    //   3080: iaload
    //   3081: bipush #25
    //   3083: ishl
    //   3084: ior
    //   3085: aload #19
    //   3087: iload #21
    //   3089: bipush #15
    //   3091: isub
    //   3092: iaload
    //   3093: bipush #18
    //   3095: iushr
    //   3096: aload #19
    //   3098: iload #21
    //   3100: bipush #15
    //   3102: isub
    //   3103: iaload
    //   3104: bipush #14
    //   3106: ishl
    //   3107: ior
    //   3108: ixor
    //   3109: aload #19
    //   3111: iload #21
    //   3113: bipush #15
    //   3115: isub
    //   3116: iaload
    //   3117: iconst_3
    //   3118: iushr
    //   3119: ixor
    //   3120: iadd
    //   3121: aload #19
    //   3123: iload #21
    //   3125: bipush #16
    //   3127: isub
    //   3128: iaload
    //   3129: iadd
    //   3130: iastore
    //   3131: goto -> 3138
    //   3134: invokestatic a : (Ljava/lang/Throwable;)Ljava/lang/Throwable;
    //   3137: athrow
    //   3138: aload #20
    //   3140: bipush #7
    //   3142: iaload
    //   3143: aload #20
    //   3145: iconst_4
    //   3146: iaload
    //   3147: bipush #6
    //   3149: iushr
    //   3150: aload #20
    //   3152: iconst_4
    //   3153: iaload
    //   3154: bipush #26
    //   3156: ishl
    //   3157: ior
    //   3158: aload #20
    //   3160: iconst_4
    //   3161: iaload
    //   3162: bipush #11
    //   3164: iushr
    //   3165: aload #20
    //   3167: iconst_4
    //   3168: iaload
    //   3169: bipush #21
    //   3171: ishl
    //   3172: ior
    //   3173: ixor
    //   3174: aload #20
    //   3176: iconst_4
    //   3177: iaload
    //   3178: bipush #25
    //   3180: iushr
    //   3181: aload #20
    //   3183: iconst_4
    //   3184: iaload
    //   3185: bipush #7
    //   3187: ishl
    //   3188: ior
    //   3189: ixor
    //   3190: iadd
    //   3191: aload #20
    //   3193: bipush #6
    //   3195: iaload
    //   3196: aload #20
    //   3198: iconst_4
    //   3199: iaload
    //   3200: aload #20
    //   3202: iconst_5
    //   3203: iaload
    //   3204: aload #20
    //   3206: bipush #6
    //   3208: iaload
    //   3209: ixor
    //   3210: iand
    //   3211: ixor
    //   3212: iadd
    //   3213: aload #6
    //   3215: iload #21
    //   3217: iaload
    //   3218: iadd
    //   3219: aload #19
    //   3221: iload #21
    //   3223: iaload
    //   3224: iadd
    //   3225: istore #22
    //   3227: aload #20
    //   3229: iconst_0
    //   3230: iaload
    //   3231: iconst_2
    //   3232: iushr
    //   3233: aload #20
    //   3235: iconst_0
    //   3236: iaload
    //   3237: bipush #30
    //   3239: ishl
    //   3240: ior
    //   3241: aload #20
    //   3243: iconst_0
    //   3244: iaload
    //   3245: bipush #13
    //   3247: iushr
    //   3248: aload #20
    //   3250: iconst_0
    //   3251: iaload
    //   3252: bipush #19
    //   3254: ishl
    //   3255: ior
    //   3256: ixor
    //   3257: aload #20
    //   3259: iconst_0
    //   3260: iaload
    //   3261: bipush #22
    //   3263: iushr
    //   3264: aload #20
    //   3266: iconst_0
    //   3267: iaload
    //   3268: bipush #10
    //   3270: ishl
    //   3271: ior
    //   3272: ixor
    //   3273: aload #20
    //   3275: iconst_0
    //   3276: iaload
    //   3277: aload #20
    //   3279: iconst_1
    //   3280: iaload
    //   3281: iand
    //   3282: aload #20
    //   3284: iconst_2
    //   3285: iaload
    //   3286: aload #20
    //   3288: iconst_0
    //   3289: iaload
    //   3290: aload #20
    //   3292: iconst_1
    //   3293: iaload
    //   3294: ior
    //   3295: iand
    //   3296: ior
    //   3297: iadd
    //   3298: istore #23
    //   3300: aload #20
    //   3302: iconst_3
    //   3303: dup2
    //   3304: iaload
    //   3305: iload #22
    //   3307: iadd
    //   3308: iastore
    //   3309: aload #20
    //   3311: bipush #7
    //   3313: iload #22
    //   3315: iload #23
    //   3317: iadd
    //   3318: iastore
    //   3319: aload #20
    //   3321: bipush #7
    //   3323: iaload
    //   3324: istore #22
    //   3326: aload #20
    //   3328: bipush #7
    //   3330: aload #20
    //   3332: bipush #6
    //   3334: iaload
    //   3335: iastore
    //   3336: aload #20
    //   3338: bipush #6
    //   3340: aload #20
    //   3342: iconst_5
    //   3343: iaload
    //   3344: iastore
    //   3345: aload #20
    //   3347: iconst_5
    //   3348: aload #20
    //   3350: iconst_4
    //   3351: iaload
    //   3352: iastore
    //   3353: aload #20
    //   3355: iconst_4
    //   3356: aload #20
    //   3358: iconst_3
    //   3359: iaload
    //   3360: iastore
    //   3361: aload #20
    //   3363: iconst_3
    //   3364: aload #20
    //   3366: iconst_2
    //   3367: iaload
    //   3368: iastore
    //   3369: aload #20
    //   3371: iconst_2
    //   3372: aload #20
    //   3374: iconst_1
    //   3375: iaload
    //   3376: iastore
    //   3377: aload #20
    //   3379: iconst_1
    //   3380: aload #20
    //   3382: iconst_0
    //   3383: iaload
    //   3384: iastore
    //   3385: aload #20
    //   3387: iconst_0
    //   3388: iload #22
    //   3390: iastore
    //   3391: iinc #21, 1
    //   3394: iload_2
    //   3395: ifeq -> 2903
    //   3398: iconst_0
    //   3399: istore #21
    //   3401: iload #21
    //   3403: bipush #8
    //   3405: if_icmpge -> 3428
    //   3408: aload #8
    //   3410: iload #21
    //   3412: dup2
    //   3413: iaload
    //   3414: aload #20
    //   3416: iload #21
    //   3418: iaload
    //   3419: iadd
    //   3420: iastore
    //   3421: iinc #21, 1
    //   3424: iload_2
    //   3425: ifeq -> 3401
    //   3428: iinc #13, 64
    //   3431: iinc #17, -64
    //   3434: iload_2
    //   3435: ifeq -> 2824
    //   3438: iload #17
    //   3440: ifle -> 3476
    //   3443: iconst_0
    //   3444: istore #19
    //   3446: iload #19
    //   3448: iload #17
    //   3450: if_icmpge -> 3476
    //   3453: aload #9
    //   3455: iload #12
    //   3457: iload #19
    //   3459: iadd
    //   3460: aload #5
    //   3462: iload #13
    //   3464: iload #19
    //   3466: iadd
    //   3467: baload
    //   3468: bastore
    //   3469: iinc #19, 1
    //   3472: iload_2
    //   3473: ifeq -> 3446
    //   3476: bipush #8
    //   3478: newarray byte
    //   3480: astore #19
    //   3482: aload #19
    //   3484: iconst_0
    //   3485: iload #14
    //   3487: bipush #24
    //   3489: iushr
    //   3490: i2b
    //   3491: bastore
    //   3492: aload #19
    //   3494: iconst_1
    //   3495: iload #14
    //   3497: bipush #16
    //   3499: iushr
    //   3500: i2b
    //   3501: bastore
    //   3502: aload #19
    //   3504: iconst_2
    //   3505: iload #14
    //   3507: bipush #8
    //   3509: iushr
    //   3510: i2b
    //   3511: bastore
    //   3512: aload #19
    //   3514: iconst_3
    //   3515: iload #14
    //   3517: i2b
    //   3518: bastore
    //   3519: aload #19
    //   3521: iconst_4
    //   3522: iload #15
    //   3524: bipush #24
    //   3526: iushr
    //   3527: i2b
    //   3528: bastore
    //   3529: aload #19
    //   3531: iconst_5
    //   3532: iload #15
    //   3534: bipush #16
    //   3536: iushr
    //   3537: i2b
    //   3538: bastore
    //   3539: aload #19
    //   3541: bipush #6
    //   3543: iload #15
    //   3545: bipush #8
    //   3547: iushr
    //   3548: i2b
    //   3549: bastore
    //   3550: aload #19
    //   3552: bipush #7
    //   3554: iload #15
    //   3556: i2b
    //   3557: bastore
    //   3558: bipush #8
    //   3560: istore #11
    //   3562: aload #7
    //   3564: iconst_0
    //   3565: iaload
    //   3566: bipush #63
    //   3568: iand
    //   3569: istore #12
    //   3571: bipush #64
    //   3573: iload #12
    //   3575: isub
    //   3576: istore #18
    //   3578: aload #7
    //   3580: iconst_0
    //   3581: dup2
    //   3582: iaload
    //   3583: iload #11
    //   3585: iadd
    //   3586: iastore
    //   3587: aload #7
    //   3589: iconst_0
    //   3590: dup2
    //   3591: iaload
    //   3592: iconst_m1
    //   3593: iand
    //   3594: iastore
    //   3595: aload #7
    //   3597: iconst_0
    //   3598: iaload
    //   3599: iload #11
    //   3601: if_icmpge -> 3619
    //   3604: aload #7
    //   3606: iconst_1
    //   3607: dup2
    //   3608: iaload
    //   3609: iconst_1
    //   3610: iadd
    //   3611: iastore
    //   3612: goto -> 3619
    //   3615: invokestatic a : (Ljava/lang/Throwable;)Ljava/lang/Throwable;
    //   3618: athrow
    //   3619: iload #12
    //   3621: ifle -> 4235
    //   3624: iload #11
    //   3626: iload #18
    //   3628: if_icmplt -> 4235
    //   3631: goto -> 3638
    //   3634: invokestatic a : (Ljava/lang/Throwable;)Ljava/lang/Throwable;
    //   3637: athrow
    //   3638: iconst_0
    //   3639: istore #20
    //   3641: iload #20
    //   3643: iload #18
    //   3645: if_icmpge -> 3668
    //   3648: aload #9
    //   3650: iload #12
    //   3652: iload #20
    //   3654: iadd
    //   3655: aload #19
    //   3657: iload #20
    //   3659: baload
    //   3660: bastore
    //   3661: iinc #20, 1
    //   3664: iload_2
    //   3665: ifeq -> 3641
    //   3668: bipush #64
    //   3670: newarray int
    //   3672: astore #20
    //   3674: bipush #8
    //   3676: newarray int
    //   3678: astore #21
    //   3680: iconst_0
    //   3681: istore #22
    //   3683: iload #22
    //   3685: bipush #8
    //   3687: if_icmpge -> 3707
    //   3690: aload #21
    //   3692: iload #22
    //   3694: aload #8
    //   3696: iload #22
    //   3698: iaload
    //   3699: iastore
    //   3700: iinc #22, 1
    //   3703: iload_2
    //   3704: ifeq -> 3683
    //   3707: iconst_0
    //   3708: istore #22
    //   3710: iload #22
    //   3712: bipush #64
    //   3714: if_icmpge -> 4205
    //   3717: iload #22
    //   3719: bipush #16
    //   3721: if_icmpge -> 3802
    //   3724: aload #20
    //   3726: iload #22
    //   3728: aload #9
    //   3730: iconst_4
    //   3731: iload #22
    //   3733: imul
    //   3734: baload
    //   3735: sipush #255
    //   3738: iand
    //   3739: bipush #24
    //   3741: ishl
    //   3742: aload #9
    //   3744: iconst_4
    //   3745: iload #22
    //   3747: imul
    //   3748: iconst_1
    //   3749: iadd
    //   3750: baload
    //   3751: sipush #255
    //   3754: iand
    //   3755: bipush #16
    //   3757: ishl
    //   3758: ior
    //   3759: aload #9
    //   3761: iconst_4
    //   3762: iload #22
    //   3764: imul
    //   3765: iconst_2
    //   3766: iadd
    //   3767: baload
    //   3768: sipush #255
    //   3771: iand
    //   3772: bipush #8
    //   3774: ishl
    //   3775: ior
    //   3776: aload #9
    //   3778: iconst_4
    //   3779: iload #22
    //   3781: imul
    //   3782: iconst_3
    //   3783: iadd
    //   3784: baload
    //   3785: sipush #255
    //   3788: iand
    //   3789: ior
    //   3790: iastore
    //   3791: iload_2
    //   3792: ifeq -> 3945
    //   3795: goto -> 3802
    //   3798: invokestatic a : (Ljava/lang/Throwable;)Ljava/lang/Throwable;
    //   3801: athrow
    //   3802: aload #20
    //   3804: iload #22
    //   3806: aload #20
    //   3808: iload #22
    //   3810: iconst_2
    //   3811: isub
    //   3812: iaload
    //   3813: bipush #17
    //   3815: iushr
    //   3816: aload #20
    //   3818: iload #22
    //   3820: iconst_2
    //   3821: isub
    //   3822: iaload
    //   3823: bipush #15
    //   3825: ishl
    //   3826: ior
    //   3827: aload #20
    //   3829: iload #22
    //   3831: iconst_2
    //   3832: isub
    //   3833: iaload
    //   3834: bipush #19
    //   3836: iushr
    //   3837: aload #20
    //   3839: iload #22
    //   3841: iconst_2
    //   3842: isub
    //   3843: iaload
    //   3844: bipush #13
    //   3846: ishl
    //   3847: ior
    //   3848: ixor
    //   3849: aload #20
    //   3851: iload #22
    //   3853: iconst_2
    //   3854: isub
    //   3855: iaload
    //   3856: bipush #10
    //   3858: iushr
    //   3859: ixor
    //   3860: aload #20
    //   3862: iload #22
    //   3864: bipush #7
    //   3866: isub
    //   3867: iaload
    //   3868: iadd
    //   3869: aload #20
    //   3871: iload #22
    //   3873: bipush #15
    //   3875: isub
    //   3876: iaload
    //   3877: bipush #7
    //   3879: iushr
    //   3880: aload #20
    //   3882: iload #22
    //   3884: bipush #15
    //   3886: isub
    //   3887: iaload
    //   3888: bipush #25
    //   3890: ishl
    //   3891: ior
    //   3892: aload #20
    //   3894: iload #22
    //   3896: bipush #15
    //   3898: isub
    //   3899: iaload
    //   3900: bipush #18
    //   3902: iushr
    //   3903: aload #20
    //   3905: iload #22
    //   3907: bipush #15
    //   3909: isub
    //   3910: iaload
    //   3911: bipush #14
    //   3913: ishl
    //   3914: ior
    //   3915: ixor
    //   3916: aload #20
    //   3918: iload #22
    //   3920: bipush #15
    //   3922: isub
    //   3923: iaload
    //   3924: iconst_3
    //   3925: iushr
    //   3926: ixor
    //   3927: iadd
    //   3928: aload #20
    //   3930: iload #22
    //   3932: bipush #16
    //   3934: isub
    //   3935: iaload
    //   3936: iadd
    //   3937: iastore
    //   3938: goto -> 3945
    //   3941: invokestatic a : (Ljava/lang/Throwable;)Ljava/lang/Throwable;
    //   3944: athrow
    //   3945: aload #21
    //   3947: bipush #7
    //   3949: iaload
    //   3950: aload #21
    //   3952: iconst_4
    //   3953: iaload
    //   3954: bipush #6
    //   3956: iushr
    //   3957: aload #21
    //   3959: iconst_4
    //   3960: iaload
    //   3961: bipush #26
    //   3963: ishl
    //   3964: ior
    //   3965: aload #21
    //   3967: iconst_4
    //   3968: iaload
    //   3969: bipush #11
    //   3971: iushr
    //   3972: aload #21
    //   3974: iconst_4
    //   3975: iaload
    //   3976: bipush #21
    //   3978: ishl
    //   3979: ior
    //   3980: ixor
    //   3981: aload #21
    //   3983: iconst_4
    //   3984: iaload
    //   3985: bipush #25
    //   3987: iushr
    //   3988: aload #21
    //   3990: iconst_4
    //   3991: iaload
    //   3992: bipush #7
    //   3994: ishl
    //   3995: ior
    //   3996: ixor
    //   3997: iadd
    //   3998: aload #21
    //   4000: bipush #6
    //   4002: iaload
    //   4003: aload #21
    //   4005: iconst_4
    //   4006: iaload
    //   4007: aload #21
    //   4009: iconst_5
    //   4010: iaload
    //   4011: aload #21
    //   4013: bipush #6
    //   4015: iaload
    //   4016: ixor
    //   4017: iand
    //   4018: ixor
    //   4019: iadd
    //   4020: aload #6
    //   4022: iload #22
    //   4024: iaload
    //   4025: iadd
    //   4026: aload #20
    //   4028: iload #22
    //   4030: iaload
    //   4031: iadd
    //   4032: istore #23
    //   4034: aload #21
    //   4036: iconst_0
    //   4037: iaload
    //   4038: iconst_2
    //   4039: iushr
    //   4040: aload #21
    //   4042: iconst_0
    //   4043: iaload
    //   4044: bipush #30
    //   4046: ishl
    //   4047: ior
    //   4048: aload #21
    //   4050: iconst_0
    //   4051: iaload
    //   4052: bipush #13
    //   4054: iushr
    //   4055: aload #21
    //   4057: iconst_0
    //   4058: iaload
    //   4059: bipush #19
    //   4061: ishl
    //   4062: ior
    //   4063: ixor
    //   4064: aload #21
    //   4066: iconst_0
    //   4067: iaload
    //   4068: bipush #22
    //   4070: iushr
    //   4071: aload #21
    //   4073: iconst_0
    //   4074: iaload
    //   4075: bipush #10
    //   4077: ishl
    //   4078: ior
    //   4079: ixor
    //   4080: aload #21
    //   4082: iconst_0
    //   4083: iaload
    //   4084: aload #21
    //   4086: iconst_1
    //   4087: iaload
    //   4088: iand
    //   4089: aload #21
    //   4091: iconst_2
    //   4092: iaload
    //   4093: aload #21
    //   4095: iconst_0
    //   4096: iaload
    //   4097: aload #21
    //   4099: iconst_1
    //   4100: iaload
    //   4101: ior
    //   4102: iand
    //   4103: ior
    //   4104: iadd
    //   4105: istore #24
    //   4107: aload #21
    //   4109: iconst_3
    //   4110: dup2
    //   4111: iaload
    //   4112: iload #23
    //   4114: iadd
    //   4115: iastore
    //   4116: aload #21
    //   4118: bipush #7
    //   4120: iload #23
    //   4122: iload #24
    //   4124: iadd
    //   4125: iastore
    //   4126: aload #21
    //   4128: bipush #7
    //   4130: iaload
    //   4131: istore #23
    //   4133: aload #21
    //   4135: bipush #7
    //   4137: aload #21
    //   4139: bipush #6
    //   4141: iaload
    //   4142: iastore
    //   4143: aload #21
    //   4145: bipush #6
    //   4147: aload #21
    //   4149: iconst_5
    //   4150: iaload
    //   4151: iastore
    //   4152: aload #21
    //   4154: iconst_5
    //   4155: aload #21
    //   4157: iconst_4
    //   4158: iaload
    //   4159: iastore
    //   4160: aload #21
    //   4162: iconst_4
    //   4163: aload #21
    //   4165: iconst_3
    //   4166: iaload
    //   4167: iastore
    //   4168: aload #21
    //   4170: iconst_3
    //   4171: aload #21
    //   4173: iconst_2
    //   4174: iaload
    //   4175: iastore
    //   4176: aload #21
    //   4178: iconst_2
    //   4179: aload #21
    //   4181: iconst_1
    //   4182: iaload
    //   4183: iastore
    //   4184: aload #21
    //   4186: iconst_1
    //   4187: aload #21
    //   4189: iconst_0
    //   4190: iaload
    //   4191: iastore
    //   4192: aload #21
    //   4194: iconst_0
    //   4195: iload #23
    //   4197: iastore
    //   4198: iinc #22, 1
    //   4201: iload_2
    //   4202: ifeq -> 3710
    //   4205: iconst_0
    //   4206: istore #22
    //   4208: iload #22
    //   4210: bipush #8
    //   4212: if_icmpge -> 4235
    //   4215: aload #8
    //   4217: iload #22
    //   4219: dup2
    //   4220: iaload
    //   4221: aload #21
    //   4223: iload #22
    //   4225: iaload
    //   4226: iadd
    //   4227: iastore
    //   4228: iinc #22, 1
    //   4231: iload_2
    //   4232: ifeq -> 4208
    //   4235: bipush #32
    //   4237: newarray byte
    //   4239: astore #4
    //   4241: sipush #6031
    //   4244: aload #4
    //   4246: iconst_0
    //   4247: aload #8
    //   4249: iconst_0
    //   4250: iaload
    //   4251: bipush #24
    //   4253: iushr
    //   4254: i2b
    //   4255: bastore
    //   4256: sipush #-26268
    //   4259: aload #4
    //   4261: iconst_1
    //   4262: aload #8
    //   4264: iconst_0
    //   4265: iaload
    //   4266: bipush #16
    //   4268: iushr
    //   4269: i2b
    //   4270: bastore
    //   4271: aload #4
    //   4273: iconst_2
    //   4274: aload #8
    //   4276: iconst_0
    //   4277: iaload
    //   4278: bipush #8
    //   4280: iushr
    //   4281: i2b
    //   4282: bastore
    //   4283: aload #4
    //   4285: iconst_3
    //   4286: aload #8
    //   4288: iconst_0
    //   4289: iaload
    //   4290: i2b
    //   4291: bastore
    //   4292: aload #4
    //   4294: iconst_4
    //   4295: aload #8
    //   4297: iconst_1
    //   4298: iaload
    //   4299: bipush #24
    //   4301: iushr
    //   4302: i2b
    //   4303: bastore
    //   4304: aload #4
    //   4306: iconst_5
    //   4307: aload #8
    //   4309: iconst_1
    //   4310: iaload
    //   4311: bipush #16
    //   4313: iushr
    //   4314: i2b
    //   4315: bastore
    //   4316: aload #4
    //   4318: bipush #6
    //   4320: aload #8
    //   4322: iconst_1
    //   4323: iaload
    //   4324: bipush #8
    //   4326: iushr
    //   4327: i2b
    //   4328: bastore
    //   4329: aload #4
    //   4331: bipush #7
    //   4333: aload #8
    //   4335: iconst_1
    //   4336: iaload
    //   4337: i2b
    //   4338: bastore
    //   4339: aload #4
    //   4341: bipush #8
    //   4343: aload #8
    //   4345: iconst_2
    //   4346: iaload
    //   4347: bipush #24
    //   4349: iushr
    //   4350: i2b
    //   4351: bastore
    //   4352: aload #4
    //   4354: bipush #9
    //   4356: aload #8
    //   4358: iconst_2
    //   4359: iaload
    //   4360: bipush #16
    //   4362: iushr
    //   4363: i2b
    //   4364: bastore
    //   4365: aload #4
    //   4367: bipush #10
    //   4369: aload #8
    //   4371: iconst_2
    //   4372: iaload
    //   4373: bipush #8
    //   4375: iushr
    //   4376: i2b
    //   4377: bastore
    //   4378: aload #4
    //   4380: bipush #11
    //   4382: aload #8
    //   4384: iconst_2
    //   4385: iaload
    //   4386: i2b
    //   4387: bastore
    //   4388: aload #4
    //   4390: bipush #12
    //   4392: aload #8
    //   4394: iconst_3
    //   4395: iaload
    //   4396: bipush #24
    //   4398: iushr
    //   4399: i2b
    //   4400: bastore
    //   4401: aload #4
    //   4403: bipush #13
    //   4405: aload #8
    //   4407: iconst_3
    //   4408: iaload
    //   4409: bipush #16
    //   4411: iushr
    //   4412: i2b
    //   4413: bastore
    //   4414: aload #4
    //   4416: bipush #14
    //   4418: aload #8
    //   4420: iconst_3
    //   4421: iaload
    //   4422: bipush #8
    //   4424: iushr
    //   4425: i2b
    //   4426: bastore
    //   4427: aload #4
    //   4429: bipush #15
    //   4431: aload #8
    //   4433: iconst_3
    //   4434: iaload
    //   4435: i2b
    //   4436: bastore
    //   4437: aload #4
    //   4439: bipush #16
    //   4441: aload #8
    //   4443: iconst_4
    //   4444: iaload
    //   4445: bipush #24
    //   4447: iushr
    //   4448: i2b
    //   4449: bastore
    //   4450: aload #4
    //   4452: bipush #17
    //   4454: aload #8
    //   4456: iconst_4
    //   4457: iaload
    //   4458: bipush #16
    //   4460: iushr
    //   4461: i2b
    //   4462: bastore
    //   4463: aload #4
    //   4465: bipush #18
    //   4467: aload #8
    //   4469: iconst_4
    //   4470: iaload
    //   4471: bipush #8
    //   4473: iushr
    //   4474: i2b
    //   4475: bastore
    //   4476: aload #4
    //   4478: bipush #19
    //   4480: aload #8
    //   4482: iconst_4
    //   4483: iaload
    //   4484: i2b
    //   4485: bastore
    //   4486: aload #4
    //   4488: bipush #20
    //   4490: aload #8
    //   4492: iconst_5
    //   4493: iaload
    //   4494: bipush #24
    //   4496: iushr
    //   4497: i2b
    //   4498: bastore
    //   4499: aload #4
    //   4501: bipush #21
    //   4503: aload #8
    //   4505: iconst_5
    //   4506: iaload
    //   4507: bipush #16
    //   4509: iushr
    //   4510: i2b
    //   4511: bastore
    //   4512: aload #4
    //   4514: bipush #22
    //   4516: aload #8
    //   4518: iconst_5
    //   4519: iaload
    //   4520: bipush #8
    //   4522: iushr
    //   4523: i2b
    //   4524: bastore
    //   4525: aload #4
    //   4527: bipush #23
    //   4529: aload #8
    //   4531: iconst_5
    //   4532: iaload
    //   4533: i2b
    //   4534: bastore
    //   4535: aload #4
    //   4537: bipush #24
    //   4539: aload #8
    //   4541: bipush #6
    //   4543: iaload
    //   4544: bipush #24
    //   4546: iushr
    //   4547: i2b
    //   4548: bastore
    //   4549: aload #4
    //   4551: bipush #25
    //   4553: aload #8
    //   4555: bipush #6
    //   4557: iaload
    //   4558: bipush #16
    //   4560: iushr
    //   4561: i2b
    //   4562: bastore
    //   4563: aload #4
    //   4565: bipush #26
    //   4567: aload #8
    //   4569: bipush #6
    //   4571: iaload
    //   4572: bipush #8
    //   4574: iushr
    //   4575: i2b
    //   4576: bastore
    //   4577: aload #4
    //   4579: bipush #27
    //   4581: aload #8
    //   4583: bipush #6
    //   4585: iaload
    //   4586: i2b
    //   4587: bastore
    //   4588: aload #4
    //   4590: bipush #28
    //   4592: aload #8
    //   4594: bipush #7
    //   4596: iaload
    //   4597: bipush #24
    //   4599: iushr
    //   4600: i2b
    //   4601: bastore
    //   4602: aload #4
    //   4604: bipush #29
    //   4606: aload #8
    //   4608: bipush #7
    //   4610: iaload
    //   4611: bipush #16
    //   4613: iushr
    //   4614: i2b
    //   4615: bastore
    //   4616: aload #4
    //   4618: bipush #30
    //   4620: aload #8
    //   4622: bipush #7
    //   4624: iaload
    //   4625: bipush #8
    //   4627: iushr
    //   4628: i2b
    //   4629: bastore
    //   4630: aload #4
    //   4632: bipush #31
    //   4634: aload #8
    //   4636: bipush #7
    //   4638: iaload
    //   4639: i2b
    //   4640: bastore
    //   4641: new java/math/BigInteger
    //   4644: dup
    //   4645: aload #4
    //   4647: invokespecial <init> : ([B)V
    //   4650: invokevirtual abs : ()Ljava/math/BigInteger;
    //   4653: putstatic burp/Zrqi.Zb : Ljava/lang/Object;
    //   4656: invokestatic a : (II)Ljava/lang/String;
    //   4659: iconst_1
    //   4660: ldc burp/Zegw
    //   4662: invokevirtual getClassLoader : ()Ljava/lang/ClassLoader;
    //   4665: invokestatic forName : (Ljava/lang/String;ZLjava/lang/ClassLoader;)Ljava/lang/Class;
    //   4668: invokevirtual getDeclaredFields : ()[Ljava/lang/reflect/Field;
    //   4671: astore_3
    //   4672: aload_3
    //   4673: arraylength
    //   4674: istore #4
    //   4676: iconst_0
    //   4677: istore #5
    //   4679: iload #5
    //   4681: iload #4
    //   4683: if_icmpge -> 4820
    //   4686: aload_3
    //   4687: iload #5
    //   4689: aaload
    //   4690: astore #6
    //   4692: aload #6
    //   4694: invokevirtual getModifiers : ()I
    //   4697: invokestatic isStatic : (I)Z
    //   4700: ifne -> 4710
    //   4703: goto -> 4813
    //   4706: invokestatic a : (Ljava/lang/Throwable;)Ljava/lang/Throwable;
    //   4709: athrow
    //   4710: aload #6
    //   4712: invokevirtual getType : ()Ljava/lang/Class;
    //   4715: astore #7
    //   4717: aload #7
    //   4719: ifnull -> 4800
    //   4722: aload #7
    //   4724: invokevirtual isPrimitive : ()Z
    //   4727: ifne -> 4800
    //   4730: goto -> 4737
    //   4733: invokestatic a : (Ljava/lang/Throwable;)Ljava/lang/Throwable;
    //   4736: athrow
    //   4737: aload #7
    //   4739: invokevirtual getPackage : ()Ljava/lang/Package;
    //   4742: ifnull -> 4800
    //   4745: goto -> 4752
    //   4748: invokestatic a : (Ljava/lang/Throwable;)Ljava/lang/Throwable;
    //   4751: athrow
    //   4752: aload #7
    //   4754: invokevirtual getPackage : ()Ljava/lang/Package;
    //   4757: invokevirtual getName : ()Ljava/lang/String;
    //   4760: ifnull -> 4800
    //   4763: goto -> 4770
    //   4766: invokestatic a : (Ljava/lang/Throwable;)Ljava/lang/Throwable;
    //   4769: athrow
    //   4770: aload #7
    //   4772: invokevirtual getPackage : ()Ljava/lang/Package;
    //   4775: invokevirtual getName : ()Ljava/lang/String;
    //   4778: sipush #6025
    //   4781: sipush #28727
    //   4784: invokestatic a : (II)Ljava/lang/String;
    //   4787: invokevirtual startsWith : (Ljava/lang/String;)Z
    //   4790: ifne -> 4800
    //   4793: goto -> 4800
    //   4796: invokestatic a : (Ljava/lang/Throwable;)Ljava/lang/Throwable;
    //   4799: athrow
    //   4800: aload #6
    //   4802: iconst_1
    //   4803: invokevirtual setAccessible : (Z)V
    //   4806: aload #6
    //   4808: aconst_null
    //   4809: invokevirtual get : (Ljava/lang/Object;)Ljava/lang/Object;
    //   4812: pop
    //   4813: iinc #5, 1
    //   4816: iload_2
    //   4817: ifeq -> 4679
    //   4820: sipush #6026
    //   4823: sipush #3881
    //   4826: invokestatic a : (II)Ljava/lang/String;
    //   4829: invokestatic forName : (Ljava/lang/String;)Ljava/lang/Class;
    //   4832: invokevirtual getDeclaredMethods : ()[Ljava/lang/reflect/Method;
    //   4835: astore_3
    //   4836: aload_3
    //   4837: arraylength
    //   4838: istore #4
    //   4840: iconst_0
    //   4841: istore #5
    //   4843: iload #5
    //   4845: iload #4
    //   4847: if_icmpge -> 4979
    //   4850: aload_3
    //   4851: iload #5
    //   4853: aaload
    //   4854: astore #6
    //   4856: aload #6
    //   4858: invokevirtual getParameterTypes : ()[Ljava/lang/Class;
    //   4861: pop
    //   4862: aload #6
    //   4864: invokevirtual getModifiers : ()I
    //   4867: invokestatic isStatic : (I)Z
    //   4870: ifeq -> 4965
    //   4873: aload #6
    //   4875: invokevirtual getParameterTypes : ()[Ljava/lang/Class;
    //   4878: arraylength
    //   4879: iconst_2
    //   4880: if_icmpne -> 4965
    //   4883: goto -> 4890
    //   4886: invokestatic a : (Ljava/lang/Throwable;)Ljava/lang/Throwable;
    //   4889: athrow
    //   4890: aload #6
    //   4892: invokevirtual getReturnType : ()Ljava/lang/Class;
    //   4895: getstatic java/lang/Void.TYPE : Ljava/lang/Class;
    //   4898: invokevirtual equals : (Ljava/lang/Object;)Z
    //   4901: ifeq -> 4965
    //   4904: goto -> 4911
    //   4907: invokestatic a : (Ljava/lang/Throwable;)Ljava/lang/Throwable;
    //   4910: athrow
    //   4911: aload #6
    //   4913: iconst_1
    //   4914: invokevirtual setAccessible : (Z)V
    //   4917: aload #6
    //   4919: aconst_null
    //   4920: iconst_2
    //   4921: anewarray java/lang/Object
    //   4924: dup
    //   4925: iconst_0
    //   4926: aload_0
    //   4927: aastore
    //   4928: dup
    //   4929: iconst_1
    //   4930: aload_1
    //   4931: ifnonnull -> 4949
    //   4934: goto -> 4941
    //   4937: invokestatic a : (Ljava/lang/Throwable;)Ljava/lang/Throwable;
    //   4940: athrow
    //   4941: aload_1
    //   4942: goto -> 4956
    //   4945: invokestatic a : (Ljava/lang/Throwable;)Ljava/lang/Throwable;
    //   4948: athrow
    //   4949: aload_1
    //   4950: checkcast [B
    //   4953: invokevirtual clone : ()Ljava/lang/Object;
    //   4956: aastore
    //   4957: invokevirtual invoke : (Ljava/lang/Object;[Ljava/lang/Object;)Ljava/lang/Object;
    //   4960: pop
    //   4961: iload_2
    //   4962: ifeq -> 4979
    //   4965: iinc #5, 1
    //   4968: iload_2
    //   4969: ifeq -> 4843
    //   4972: goto -> 4979
    //   4975: invokestatic a : (Ljava/lang/Throwable;)Ljava/lang/Throwable;
    //   4978: athrow
    //   4979: getstatic burp/Zeig.Zg : Ljava/lang/String;
    //   4982: getstatic burp/Zes.Zx : Ljava/lang/Object;
    //   4985: checkcast java/math/BigInteger
    //   4988: invokevirtual intValue : ()I
    //   4991: bipush #32
    //   4993: irem
    //   4994: invokestatic abs : (I)I
    //   4997: invokevirtual charAt : (I)C
    //   5000: getstatic burp/Zrww.ZV : Ljava/lang/String;
    //   5003: getstatic burp/Zegw.ZW : Ljava/lang/Object;
    //   5006: checkcast java/math/BigInteger
    //   5009: invokevirtual intValue : ()I
    //   5012: bipush #32
    //   5014: irem
    //   5015: invokestatic abs : (I)I
    //   5018: invokevirtual charAt : (I)C
    //   5021: if_icmpgt -> 5136
    //   5024: getstatic burp/Zkjj.ZT : Ljava/lang/String;
    //   5027: getstatic burp/Zebe.Zw : Ljava/lang/Object;
    //   5030: checkcast java/math/BigInteger
    //   5033: invokevirtual intValue : ()I
    //   5036: bipush #32
    //   5038: irem
    //   5039: invokestatic abs : (I)I
    //   5042: invokevirtual charAt : (I)C
    //   5045: getstatic burp/Zk9q.Zk : Ljava/lang/String;
    //   5048: getstatic burp/Zxd1.Zc : Ljava/lang/Object;
    //   5051: checkcast java/math/BigInteger
    //   5054: invokevirtual intValue : ()I
    //   5057: bipush #32
    //   5059: irem
    //   5060: invokestatic abs : (I)I
    //   5063: invokevirtual charAt : (I)C
    //   5066: if_icmple -> 5136
    //   5069: goto -> 5076
    //   5072: invokestatic a : (Ljava/lang/Throwable;)Ljava/lang/Throwable;
    //   5075: athrow
    //   5076: getstatic burp/Zkf6.ZO : Ljava/lang/String;
    //   5079: getstatic burp/Zgu4.Zs : Ljava/lang/Object;
    //   5082: checkcast java/math/BigInteger
    //   5085: invokevirtual intValue : ()I
    //   5088: bipush #32
    //   5090: irem
    //   5091: invokestatic abs : (I)I
    //   5094: invokevirtual charAt : (I)C
    //   5097: getstatic burp/Zg4z.Zm : Ljava/lang/String;
    //   5100: getstatic burp/Zxn9.ZN : Ljava/lang/Object;
    //   5103: checkcast java/math/BigInteger
    //   5106: invokevirtual intValue : ()I
    //   5109: bipush #32
    //   5111: irem
    //   5112: invokestatic abs : (I)I
    //   5115: invokevirtual charAt : (I)C
    //   5118: if_icmpgt -> 5136
    //   5121: goto -> 5128
    //   5124: invokestatic a : (Ljava/lang/Throwable;)Ljava/lang/Throwable;
    //   5127: athrow
    //   5128: iconst_1
    //   5129: goto -> 5137
    //   5132: invokestatic a : (Ljava/lang/Throwable;)Ljava/lang/Throwable;
    //   5135: athrow
    //   5136: iconst_0
    //   5137: ireturn
    //   5138: astore_3
    //   5139: new java/lang/Exception
    //   5142: dup
    //   5143: aload_3
    //   5144: invokevirtual getMessage : ()Ljava/lang/String;
    //   5147: invokespecial <init> : (Ljava/lang/String;)V
    //   5150: athrow
    // Exception table:
    //   from	to	target	type
    //   4	5137	5138	java/lang/Throwable
    //   185	209	212	java/lang/Throwable
    //   283	320	320	java/lang/Throwable
    //   324	345	345	java/lang/Throwable
    //   349	379	379	java/lang/Throwable
    //   1378	1412	1415	java/lang/Throwable
    //   1507	1585	1588	java/lang/Throwable
    //   1514	1728	1731	java/lang/Throwable
    //   2105	2120	2120	java/lang/Throwable
    //   2147	2181	2184	java/lang/Throwable
    //   2191	2203	2206	java/lang/Throwable
    //   2289	2367	2370	java/lang/Throwable
    //   2296	2510	2513	java/lang/Throwable
    //   2910	2988	2991	java/lang/Throwable
    //   2917	3131	3134	java/lang/Throwable
    //   3578	3612	3615	java/lang/Throwable
    //   3619	3631	3634	java/lang/Throwable
    //   3717	3795	3798	java/lang/Throwable
    //   3724	3938	3941	java/lang/Throwable
    //   4692	4706	4706	java/lang/Throwable
    //   4717	4730	4733	java/lang/Throwable
    //   4722	4745	4748	java/lang/Throwable
    //   4737	4763	4766	java/lang/Throwable
    //   4752	4793	4796	java/lang/Throwable
    //   4856	4883	4886	java/lang/Throwable
    //   4873	4904	4907	java/lang/Throwable
    //   4890	4934	4937	java/lang/Throwable
    //   4911	4945	4945	java/lang/Throwable
    //   4956	4972	4975	java/lang/Throwable
    //   4979	5069	5072	java/lang/Throwable
    //   5024	5121	5124	java/lang/Throwable
    //   5076	5132	5132	java/lang/Throwable
  }
  
  static {
    // Byte code:
    //   0: bipush #8
    //   2: anewarray java/lang/String
    //   5: astore #5
    //   7: iconst_0
    //   8: istore_3
    //   9: ldc 'xSt\\t0_M7\\t7sO{\:Svm*D<5aD2"BP8v>Z2E \\t <B T5?:`cErB,LzF?'
    //   11: dup
    //   12: astore_2
    //   13: invokevirtual length : ()I
    //   16: istore #4
    //   18: bipush #8
    //   20: istore_1
    //   21: iconst_m1
    //   22: istore_0
    //   23: bipush #124
    //   25: iinc #0, 1
    //   28: aload_2
    //   29: iload_0
    //   30: dup
    //   31: iload_1
    //   32: iadd
    //   33: invokevirtual substring : (II)Ljava/lang/String;
    //   36: iconst_m1
    //   37: goto -> 143
    //   40: aload #5
    //   42: swap
    //   43: iload_3
    //   44: iinc #3, 1
    //   47: swap
    //   48: aastore
    //   49: iload_0
    //   50: iload_1
    //   51: iadd
    //   52: dup
    //   53: istore_0
    //   54: iload #4
    //   56: if_icmpge -> 68
    //   59: aload_2
    //   60: iload_0
    //   61: invokevirtual charAt : (I)C
    //   64: istore_1
    //   65: goto -> 23
    //   68: ldc 'Sgz 1h!yVzANyZ(\\r'
    //   70: dup
    //   71: astore_2
    //   72: invokevirtual length : ()I
    //   75: istore #4
    //   77: bipush #9
    //   79: istore_1
    //   80: iconst_m1
    //   81: istore_0
    //   82: bipush #51
    //   84: iinc #0, 1
    //   87: aload_2
    //   88: iload_0
    //   89: dup
    //   90: iload_1
    //   91: iadd
    //   92: invokevirtual substring : (II)Ljava/lang/String;
    //   95: iconst_0
    //   96: goto -> 143
    //   99: aload #5
    //   101: swap
    //   102: iload_3
    //   103: iinc #3, 1
    //   106: swap
    //   107: aastore
    //   108: iload_0
    //   109: iload_1
    //   110: iadd
    //   111: dup
    //   112: istore_0
    //   113: iload #4
    //   115: if_icmpge -> 127
    //   118: aload_2
    //   119: iload_0
    //   120: invokevirtual charAt : (I)C
    //   123: istore_1
    //   124: goto -> 82
    //   127: aload #5
    //   129: putstatic burp/Zs5y.a : [Ljava/lang/String;
    //   132: bipush #8
    //   134: anewarray java/lang/String
    //   137: putstatic burp/Zs5y.b : [Ljava/lang/String;
    //   140: goto -> 300
    //   143: dup_x2
    //   144: pop
    //   145: invokevirtual toCharArray : ()[C
    //   148: dup_x1
    //   149: arraylength
    //   150: dup_x2
    //   151: pop
    //   152: iconst_0
    //   153: istore #6
    //   155: dup2_x1
    //   156: pop2
    //   157: dup_x2
    //   158: iconst_1
    //   159: if_icmpgt -> 260
    //   162: dup2
    //   163: swap
    //   164: iload #6
    //   166: dup2_x1
    //   167: caload
    //   168: swap
    //   169: iload #6
    //   171: bipush #7
    //   173: irem
    //   174: tableswitch default -> 242, 0 -> 212, 1 -> 217, 2 -> 222, 3 -> 227, 4 -> 232, 5 -> 237
    //   212: bipush #126
    //   214: goto -> 244
    //   217: bipush #67
    //   219: goto -> 244
    //   222: bipush #57
    //   224: goto -> 244
    //   227: bipush #108
    //   229: goto -> 244
    //   232: bipush #49
    //   234: goto -> 244
    //   237: bipush #68
    //   239: goto -> 244
    //   242: bipush #62
    //   244: ixor
    //   245: ixor
    //   246: i2c
    //   247: castore
    //   248: iinc #6, 1
    //   251: dup
    //   252: ifne -> 260
    //   255: dup2
    //   256: dup_x1
    //   257: goto -> 166
    //   260: dup2_x1
    //   261: pop2
    //   262: dup_x2
    //   263: iload #6
    //   265: if_icmpgt -> 162
    //   268: pop
    //   269: new java/lang/String
    //   272: dup_x1
    //   273: swap
    //   274: invokespecial <init> : ([C)V
    //   277: invokevirtual intern : ()Ljava/lang/String;
    //   280: swap
    //   281: pop
    //   282: swap
    //   283: tableswitch default -> 40, 0 -> 99
    //   300: new java/math/BigInteger
    //   303: dup
    //   304: bipush #32
    //   306: newarray byte
    //   308: dup
    //   309: iconst_0
    //   310: bipush #122
    //   312: bastore
    //   313: dup
    //   314: iconst_1
    //   315: bipush #72
    //   317: bastore
    //   318: dup
    //   319: iconst_2
    //   320: bipush #27
    //   322: bastore
    //   323: dup
    //   324: iconst_3
    //   325: bipush #13
    //   327: bastore
    //   328: dup
    //   329: iconst_4
    //   330: bipush #127
    //   332: bastore
    //   333: dup
    //   334: iconst_5
    //   335: bipush #14
    //   337: bastore
    //   338: dup
    //   339: bipush #6
    //   341: bipush #44
    //   343: bastore
    //   344: dup
    //   345: bipush #7
    //   347: bipush #95
    //   349: bastore
    //   350: dup
    //   351: bipush #8
    //   353: bipush #-10
    //   355: bastore
    //   356: dup
    //   357: bipush #9
    //   359: bipush #-104
    //   361: bastore
    //   362: dup
    //   363: bipush #10
    //   365: bipush #-54
    //   367: bastore
    //   368: dup
    //   369: bipush #11
    //   371: bipush #78
    //   373: bastore
    //   374: dup
    //   375: bipush #12
    //   377: bipush #89
    //   379: bastore
    //   380: dup
    //   381: bipush #13
    //   383: bipush #15
    //   385: bastore
    //   386: dup
    //   387: bipush #14
    //   389: bipush #-86
    //   391: bastore
    //   392: dup
    //   393: bipush #15
    //   395: bipush #125
    //   397: bastore
    //   398: dup
    //   399: bipush #16
    //   401: bipush #-56
    //   403: bastore
    //   404: dup
    //   405: bipush #17
    //   407: bipush #54
    //   409: bastore
    //   410: dup
    //   411: bipush #18
    //   413: bipush #-12
    //   415: bastore
    //   416: dup
    //   417: bipush #19
    //   419: bipush #-102
    //   421: bastore
    //   422: dup
    //   423: bipush #20
    //   425: bipush #-92
    //   427: bastore
    //   428: dup
    //   429: bipush #21
    //   431: bipush #87
    //   433: bastore
    //   434: dup
    //   435: bipush #22
    //   437: bipush #-79
    //   439: bastore
    //   440: dup
    //   441: bipush #23
    //   443: bipush #86
    //   445: bastore
    //   446: dup
    //   447: bipush #24
    //   449: bipush #7
    //   451: bastore
    //   452: dup
    //   453: bipush #25
    //   455: bipush #-90
    //   457: bastore
    //   458: dup
    //   459: bipush #26
    //   461: bipush #-70
    //   463: bastore
    //   464: dup
    //   465: bipush #27
    //   467: bipush #-47
    //   469: bastore
    //   470: dup
    //   471: bipush #28
    //   473: bipush #96
    //   475: bastore
    //   476: dup
    //   477: bipush #29
    //   479: bipush #122
    //   481: bastore
    //   482: dup
    //   483: bipush #30
    //   485: bipush #-48
    //   487: bastore
    //   488: dup
    //   489: bipush #31
    //   491: bipush #-15
    //   493: bastore
    //   494: invokespecial <init> : ([B)V
    //   497: putstatic burp/Zs5y.Zd : Ljava/lang/Object;
    //   500: sipush #6027
    //   503: sipush #5046
    //   506: invokestatic a : (II)Ljava/lang/String;
    //   509: putstatic burp/Zs5y.ZO : Ljava/lang/String;
    //   512: return
  }
  
  private static Throwable a(Throwable paramThrowable) {
    return paramThrowable;
  }
  
  private static String a(int paramInt1, int paramInt2) {
    int i = (paramInt1 ^ 0x178C) & 0xFFFF;
    if (b[i] == null) {
      char[] arrayOfChar = a[i].toCharArray();
      switch (arrayOfChar[0] & 0xFF) {
        case 0:
        
        case 1:
        
        case 2:
        
        case 3:
        
        case 4:
        
        case 5:
        
        case 6:
        
        case 7:
        
        case 8:
        
        case 9:
        
        case 10:
        
        case 11:
        
        case 12:
        
        case 13:
        
        case 14:
        
        case 15:
        
        case 16:
        
        case 17:
        
        case 18:
        
        case 19:
        
        case 20:
        
        case 21:
        
        case 22:
        
        case 23:
        
        case 24:
        
        case 25:
        
        case 26:
        
        case 27:
        
        case 28:
        
        case 29:
        
        case 30:
        
        case 31:
        
        case 32:
        
        case 33:
        
        case 34:
        
        case 35:
        
        case 36:
        
        case 37:
        
        case 38:
        
        case 39:
        
        case 40:
        
        case 41:
        
        case 42:
        
        case 43:
        
        case 44:
        
        case 45:
        
        case 46:
        
        case 47:
        
        case 48:
        
        case 49:
        
        case 50:
        
        case 51:
        
        case 52:
        
        case 53:
        
        case 54:
        
        case 55:
        
        case 56:
        
        case 57:
        
        case 58:
        
        case 59:
        
        case 60:
        
        case 61:
        
        case 62:
        
        case 63:
        
        case 64:
        
        case 65:
        
        case 66:
        
        case 67:
        
        case 68:
        
        case 69:
        
        case 70:
        
        case 71:
        
        case 72:
        
        case 73:
        
        case 74:
        
        case 75:
        
        case 76:
        
        case 77:
        
        case 78:
        
        case 79:
        
        case 80:
        
        case 81:
        
        case 82:
        
        case 83:
        
        case 84:
        
        case 85:
        
        case 86:
        
        case 87:
        
        case 88:
        
        case 89:
        
        case 90:
        
        case 91:
        
        case 92:
        
        case 93:
        
        case 94:
        
        case 95:
        
        case 96:
        
        case 97:
        
        case 98:
        
        case 99:
        
        case 100:
        
        case 101:
        
        case 102:
        
        case 103:
        
        case 104:
        
        case 105:
        
        case 106:
        
        case 107:
        
        case 108:
        
        case 109:
        
        case 110:
        
        case 111:
        
        case 112:
        
        case 113:
        
        case 114:
        
        case 115:
        
        case 116:
        
        case 117:
        
        case 118:
        
        case 119:
        
        case 120:
        
        case 121:
        
        case 122:
        
        case 123:
        
        case 124:
        
        case 125:
        
        case 126:
        
        case 127:
        
        case 128:
        
        case 129:
        
        case 130:
        
        case 131:
        
        case 132:
        
        case 133:
        
        case 134:
        
        case 135:
        
        case 136:
        
        case 137:
        
        case 138:
        
        case 139:
        
        case 140:
        
        case 141:
        
        case 142:
        
        case 143:
        
        case 144:
        
        case 145:
        
        case 146:
        
        case 147:
        
        case 148:
        
        case 149:
        
        case 150:
        
        case 151:
        
        case 152:
        
        case 153:
        
        case 154:
        
        case 155:
        
        case 156:
        
        case 157:
        
        case 158:
        
        case 159:
        
        case 160:
        
        case 161:
        
        case 162:
        
        case 163:
        
        case 164:
        
        case 165:
        
        case 166:
        
        case 167:
        
        case 168:
        
        case 169:
        
        case 170:
        
        case 171:
        
        case 172:
        
        case 173:
        
        case 174:
        
        case 175:
        
        case 176:
        
        case 177:
        
        case 178:
        
        case 179:
        
        case 180:
        
        case 181:
        
        case 182:
        
        case 183:
        
        case 184:
        
        case 185:
        
        case 186:
        
        case 187:
        
        case 188:
        
        case 189:
        
        case 190:
        
        case 191:
        
        case 192:
        
        case 193:
        
        case 194:
        
        case 195:
        
        case 196:
        
        case 197:
        
        case 198:
        
        case 199:
        
        case 200:
        
        case 201:
        
        case 202:
        
        case 203:
        
        case 204:
        
        case 205:
        
        case 206:
        
        case 207:
        
        case 208:
        
        case 209:
        
        case 210:
        
        case 211:
        
        case 212:
        
        case 213:
        
        case 214:
        
        case 215:
        
        case 216:
        
        case 217:
        
        case 218:
        
        case 219:
        
        case 220:
        
        case 221:
        
        case 222:
        
        case 223:
        
        case 224:
        
        case 225:
        
        case 226:
        
        case 227:
        
        case 228:
        
        case 229:
        
        case 230:
        
        case 231:
        
        case 232:
        
        case 233:
        
        case 234:
        
        case 235:
        
        case 236:
        
        case 237:
        
        case 238:
        
        case 239:
        
        case 240:
        
        case 241:
        
        case 242:
        
        case 243:
        
        case 244:
        
        case 245:
        
        case 246:
        
        case 247:
        
        case 248:
        
        case 249:
        
        case 250:
        
        case 251:
        
        case 252:
        
        case 253:
        
        case 254:
        
        default:
          break;
      } 
      byte b1 = 33;
      int j = (paramInt2 & 0xFF) - b1;
      if (j < 0)
        j += 256; 
      int k = ((paramInt2 & 0xFFFF) >>> 8) - b1;
      if (k < 0)
        k += 256; 
      for (byte b2 = 0; b2 < arrayOfChar.length; b2++) {
        int m = b2 % 2;
        if (m == 0) {
          arrayOfChar[b2] = (char)(arrayOfChar[b2] ^ j);
          j = ((j >>> 3 | j << 5) ^ arrayOfChar[b2]) & 0xFF;
        } else {
          arrayOfChar[b2] = (char)(arrayOfChar[b2] ^ k);
          k = ((k >>> 3 | k << 5) ^ arrayOfChar[b2]) & 0xFF;
        } 
      } 
      b[i] = (new String(arrayOfChar)).intern();
    } 
    return b[i];
  }
}


/* Location:              C:\Program Files\BurpSuitePro\burpsuite_pro.jar!\burp\Zs5y.class
 * Java compiler version: 21 (65.0)
 * JD-Core Version:       1.1.3
 */