package burp;

import java.math.BigInteger;

class Zs6g extends ClassLoader {
  static Object Zq;
  
  static String ZU;
  
  private static final String[] a;
  
  private static final String[] b;
  
  static void Zl(Object[] paramArrayOfObject, Object paramObject) throws Throwable {}
  
  static boolean ZD(Object[] paramArrayOfObject, Object paramObject) throws Throwable {
    // Byte code:
    //   0: invokestatic ZK : ()Z
    //   3: istore_2
    //   4: getstatic burp/Zxtn.ZY : Ljava/lang/Object;
    //   7: checkcast java/math/BigInteger
    //   10: invokevirtual toByteArray : ()[B
    //   13: astore_3
    //   14: aload_3
    //   15: arraylength
    //   16: bipush #8
    //   18: iadd
    //   19: bipush #6
    //   21: ishr
    //   22: iconst_1
    //   23: iadd
    //   24: bipush #16
    //   26: imul
    //   27: newarray int
    //   29: astore #5
    //   31: iconst_0
    //   32: istore #6
    //   34: iload #6
    //   36: aload_3
    //   37: arraylength
    //   38: if_icmpge -> 81
    //   41: aload_3
    //   42: iload #6
    //   44: baload
    //   45: sipush #255
    //   48: iand
    //   49: istore #7
    //   51: aload #5
    //   53: iload #6
    //   55: iconst_2
    //   56: ishr
    //   57: dup2
    //   58: iaload
    //   59: iload #7
    //   61: bipush #24
    //   63: iload #6
    //   65: iconst_4
    //   66: irem
    //   67: bipush #8
    //   69: imul
    //   70: isub
    //   71: ishl
    //   72: ior
    //   73: iastore
    //   74: iinc #6, 1
    //   77: iload_2
    //   78: ifeq -> 34
    //   81: aload #5
    //   83: iload #6
    //   85: iconst_2
    //   86: ishr
    //   87: dup2
    //   88: iaload
    //   89: sipush #128
    //   92: bipush #24
    //   94: iload #6
    //   96: iconst_4
    //   97: irem
    //   98: bipush #8
    //   100: imul
    //   101: isub
    //   102: ishl
    //   103: ior
    //   104: iastore
    //   105: aload #5
    //   107: aload #5
    //   109: arraylength
    //   110: iconst_1
    //   111: isub
    //   112: aload_3
    //   113: arraylength
    //   114: bipush #8
    //   116: imul
    //   117: iastore
    //   118: bipush #80
    //   120: newarray int
    //   122: astore #7
    //   124: ldc 1732584193
    //   126: istore #8
    //   128: ldc -271733879
    //   130: istore #9
    //   132: ldc -1732584194
    //   134: istore #10
    //   136: ldc 271733878
    //   138: istore #11
    //   140: ldc -1009589776
    //   142: istore #12
    //   144: iconst_0
    //   145: istore #6
    //   147: iload #6
    //   149: aload #5
    //   151: arraylength
    //   152: if_icmpge -> 474
    //   155: iload #8
    //   157: istore #13
    //   159: iload #9
    //   161: istore #14
    //   163: iload #10
    //   165: istore #15
    //   167: iload #11
    //   169: istore #16
    //   171: iload #12
    //   173: istore #17
    //   175: iconst_0
    //   176: istore #18
    //   178: iload #18
    //   180: bipush #80
    //   182: if_icmpge -> 432
    //   185: iload #18
    //   187: bipush #16
    //   189: if_icmpge -> 216
    //   192: aload #7
    //   194: iload #18
    //   196: aload #5
    //   198: iload #6
    //   200: iload #18
    //   202: iadd
    //   203: iaload
    //   204: iastore
    //   205: iload_2
    //   206: ifeq -> 271
    //   209: goto -> 216
    //   212: invokestatic a : (Ljava/lang/Throwable;)Ljava/lang/Throwable;
    //   215: athrow
    //   216: aload #7
    //   218: iload #18
    //   220: iconst_3
    //   221: isub
    //   222: iaload
    //   223: aload #7
    //   225: iload #18
    //   227: bipush #8
    //   229: isub
    //   230: iaload
    //   231: ixor
    //   232: aload #7
    //   234: iload #18
    //   236: bipush #14
    //   238: isub
    //   239: iaload
    //   240: ixor
    //   241: aload #7
    //   243: iload #18
    //   245: bipush #16
    //   247: isub
    //   248: iaload
    //   249: ixor
    //   250: istore #19
    //   252: iload #19
    //   254: iconst_1
    //   255: ishl
    //   256: iload #19
    //   258: bipush #31
    //   260: iushr
    //   261: ior
    //   262: istore #20
    //   264: aload #7
    //   266: iload #18
    //   268: iload #20
    //   270: iastore
    //   271: iload #8
    //   273: iconst_5
    //   274: ishl
    //   275: iload #8
    //   277: bipush #27
    //   279: iushr
    //   280: ior
    //   281: istore #19
    //   283: iload #19
    //   285: iload #12
    //   287: iadd
    //   288: aload #7
    //   290: iload #18
    //   292: iaload
    //   293: iadd
    //   294: iload #18
    //   296: bipush #20
    //   298: if_icmpge -> 324
    //   301: ldc 1518500249
    //   303: iload #9
    //   305: iload #10
    //   307: iand
    //   308: iload #9
    //   310: iconst_m1
    //   311: ixor
    //   312: iload #11
    //   314: iand
    //   315: ior
    //   316: iadd
    //   317: goto -> 394
    //   320: invokestatic a : (Ljava/lang/Throwable;)Ljava/lang/Throwable;
    //   323: athrow
    //   324: iload #18
    //   326: bipush #40
    //   328: if_icmpge -> 349
    //   331: ldc 1859775393
    //   333: iload #9
    //   335: iload #10
    //   337: ixor
    //   338: iload #11
    //   340: ixor
    //   341: iadd
    //   342: goto -> 394
    //   345: invokestatic a : (Ljava/lang/Throwable;)Ljava/lang/Throwable;
    //   348: athrow
    //   349: iload #18
    //   351: bipush #60
    //   353: if_icmpge -> 383
    //   356: ldc -1894007588
    //   358: iload #9
    //   360: iload #10
    //   362: iand
    //   363: iload #9
    //   365: iload #11
    //   367: iand
    //   368: ior
    //   369: iload #10
    //   371: iload #11
    //   373: iand
    //   374: ior
    //   375: iadd
    //   376: goto -> 394
    //   379: invokestatic a : (Ljava/lang/Throwable;)Ljava/lang/Throwable;
    //   382: athrow
    //   383: ldc -899497514
    //   385: iload #9
    //   387: iload #10
    //   389: ixor
    //   390: iload #11
    //   392: ixor
    //   393: iadd
    //   394: iadd
    //   395: istore #20
    //   397: iload #11
    //   399: istore #12
    //   401: iload #10
    //   403: istore #11
    //   405: iload #9
    //   407: bipush #30
    //   409: ishl
    //   410: iload #9
    //   412: iconst_2
    //   413: iushr
    //   414: ior
    //   415: istore #10
    //   417: iload #8
    //   419: istore #9
    //   421: iload #20
    //   423: istore #8
    //   425: iinc #18, 1
    //   428: iload_2
    //   429: ifeq -> 178
    //   432: iload #8
    //   434: iload #13
    //   436: iadd
    //   437: istore #8
    //   439: iload #9
    //   441: iload #14
    //   443: iadd
    //   444: istore #9
    //   446: iload #10
    //   448: iload #15
    //   450: iadd
    //   451: istore #10
    //   453: iload #11
    //   455: iload #16
    //   457: iadd
    //   458: istore #11
    //   460: iload #12
    //   462: iload #17
    //   464: iadd
    //   465: istore #12
    //   467: iinc #6, 16
    //   470: iload_2
    //   471: ifeq -> 147
    //   474: iconst_5
    //   475: newarray int
    //   477: dup
    //   478: iconst_0
    //   479: iload #8
    //   481: iastore
    //   482: dup
    //   483: iconst_1
    //   484: iload #9
    //   486: iastore
    //   487: dup
    //   488: iconst_2
    //   489: iload #10
    //   491: iastore
    //   492: dup
    //   493: iconst_3
    //   494: iload #11
    //   496: iastore
    //   497: dup
    //   498: iconst_4
    //   499: iload #12
    //   501: iastore
    //   502: astore #13
    //   504: bipush #20
    //   506: newarray byte
    //   508: astore #14
    //   510: iconst_0
    //   511: istore #15
    //   513: iload #15
    //   515: bipush #20
    //   517: if_icmpge -> 558
    //   520: aload #13
    //   522: iload #15
    //   524: iconst_4
    //   525: idiv
    //   526: iaload
    //   527: istore #16
    //   529: iconst_3
    //   530: iload #15
    //   532: iconst_4
    //   533: irem
    //   534: isub
    //   535: bipush #8
    //   537: imul
    //   538: istore #17
    //   540: aload #14
    //   542: iload #15
    //   544: iload #16
    //   546: iload #17
    //   548: iushr
    //   549: i2b
    //   550: bastore
    //   551: iinc #15, 1
    //   554: iload_2
    //   555: ifeq -> 513
    //   558: aload #14
    //   560: astore #4
    //   562: new java/math/BigInteger
    //   565: dup
    //   566: aload #4
    //   568: invokespecial <init> : ([B)V
    //   571: invokevirtual abs : ()Ljava/math/BigInteger;
    //   574: putstatic burp/Zkku.Zz : Ljava/lang/Object;
    //   577: getstatic burp/Zx58.ZE : Ljava/lang/Object;
    //   580: checkcast java/math/BigInteger
    //   583: getstatic burp/Zs4v.ZB : Ljava/lang/Object;
    //   586: checkcast java/math/BigInteger
    //   589: invokevirtual subtract : (Ljava/math/BigInteger;)Ljava/math/BigInteger;
    //   592: putstatic burp/Ztev.Zr : Ljava/lang/Object;
    //   595: new java/lang/StringBuilder
    //   598: dup
    //   599: invokespecial <init> : ()V
    //   602: astore_3
    //   603: iconst_0
    //   604: istore #4
    //   606: iload #4
    //   608: bipush #32
    //   610: if_icmpge -> 1943
    //   613: iload #4
    //   615: tableswitch default -> 1936, 0 -> 756, 1 -> 793, 2 -> 830, 3 -> 867, 4 -> 904, 5 -> 941, 6 -> 978, 7 -> 1015, 8 -> 1052, 9 -> 1089, 10 -> 1126, 11 -> 1163, 12 -> 1200, 13 -> 1237, 14 -> 1274, 15 -> 1311, 16 -> 1348, 17 -> 1385, 18 -> 1422, 19 -> 1459, 20 -> 1496, 21 -> 1533, 22 -> 1570, 23 -> 1607, 24 -> 1644, 25 -> 1681, 26 -> 1718, 27 -> 1755, 28 -> 1792, 29 -> 1829, 30 -> 1866, 31 -> 1903
    //   756: aload_3
    //   757: getstatic burp/Ze3d.ZL : Ljava/lang/String;
    //   760: getstatic burp/Zlbd.ZU : Ljava/lang/Object;
    //   763: checkcast java/math/BigInteger
    //   766: invokevirtual intValue : ()I
    //   769: bipush #32
    //   771: irem
    //   772: invokestatic abs : (I)I
    //   775: invokevirtual charAt : (I)C
    //   778: invokevirtual append : (C)Ljava/lang/StringBuilder;
    //   781: pop
    //   782: iload_2
    //   783: ifeq -> 1936
    //   786: goto -> 793
    //   789: invokestatic a : (Ljava/lang/Throwable;)Ljava/lang/Throwable;
    //   792: athrow
    //   793: aload_3
    //   794: getstatic burp/Zrp3.Zf : Ljava/lang/String;
    //   797: getstatic burp/Zzmc.Zg : Ljava/lang/Object;
    //   800: checkcast java/math/BigInteger
    //   803: invokevirtual intValue : ()I
    //   806: bipush #32
    //   808: irem
    //   809: invokestatic abs : (I)I
    //   812: invokevirtual charAt : (I)C
    //   815: invokevirtual append : (C)Ljava/lang/StringBuilder;
    //   818: pop
    //   819: iload_2
    //   820: ifeq -> 1936
    //   823: goto -> 830
    //   826: invokestatic a : (Ljava/lang/Throwable;)Ljava/lang/Throwable;
    //   829: athrow
    //   830: aload_3
    //   831: getstatic burp/Zmz.Zp : Ljava/lang/String;
    //   834: getstatic burp/Zezq.Zu : Ljava/lang/Object;
    //   837: checkcast java/math/BigInteger
    //   840: invokevirtual intValue : ()I
    //   843: bipush #32
    //   845: irem
    //   846: invokestatic abs : (I)I
    //   849: invokevirtual charAt : (I)C
    //   852: invokevirtual append : (C)Ljava/lang/StringBuilder;
    //   855: pop
    //   856: iload_2
    //   857: ifeq -> 1936
    //   860: goto -> 867
    //   863: invokestatic a : (Ljava/lang/Throwable;)Ljava/lang/Throwable;
    //   866: athrow
    //   867: aload_3
    //   868: getstatic burp/Zt4g.Zj : Ljava/lang/String;
    //   871: getstatic burp/Zter.Zc : Ljava/lang/Object;
    //   874: checkcast java/math/BigInteger
    //   877: invokevirtual intValue : ()I
    //   880: bipush #32
    //   882: irem
    //   883: invokestatic abs : (I)I
    //   886: invokevirtual charAt : (I)C
    //   889: invokevirtual append : (C)Ljava/lang/StringBuilder;
    //   892: pop
    //   893: iload_2
    //   894: ifeq -> 1936
    //   897: goto -> 904
    //   900: invokestatic a : (Ljava/lang/Throwable;)Ljava/lang/Throwable;
    //   903: athrow
    //   904: aload_3
    //   905: getstatic burp/Zrcu.Zb : Ljava/lang/String;
    //   908: getstatic burp/Zxfu.ZA : Ljava/lang/Object;
    //   911: checkcast java/math/BigInteger
    //   914: invokevirtual intValue : ()I
    //   917: bipush #32
    //   919: irem
    //   920: invokestatic abs : (I)I
    //   923: invokevirtual charAt : (I)C
    //   926: invokevirtual append : (C)Ljava/lang/StringBuilder;
    //   929: pop
    //   930: iload_2
    //   931: ifeq -> 1936
    //   934: goto -> 941
    //   937: invokestatic a : (Ljava/lang/Throwable;)Ljava/lang/Throwable;
    //   940: athrow
    //   941: aload_3
    //   942: getstatic burp/Zrhu.ZJ : Ljava/lang/String;
    //   945: getstatic burp/Zmfw.ZS : Ljava/lang/Object;
    //   948: checkcast java/math/BigInteger
    //   951: invokevirtual intValue : ()I
    //   954: bipush #32
    //   956: irem
    //   957: invokestatic abs : (I)I
    //   960: invokevirtual charAt : (I)C
    //   963: invokevirtual append : (C)Ljava/lang/StringBuilder;
    //   966: pop
    //   967: iload_2
    //   968: ifeq -> 1936
    //   971: goto -> 978
    //   974: invokestatic a : (Ljava/lang/Throwable;)Ljava/lang/Throwable;
    //   977: athrow
    //   978: aload_3
    //   979: getstatic burp/Zbzc.ZL : Ljava/lang/String;
    //   982: getstatic burp/Zzri.ZG : Ljava/lang/Object;
    //   985: checkcast java/math/BigInteger
    //   988: invokevirtual intValue : ()I
    //   991: bipush #32
    //   993: irem
    //   994: invokestatic abs : (I)I
    //   997: invokevirtual charAt : (I)C
    //   1000: invokevirtual append : (C)Ljava/lang/StringBuilder;
    //   1003: pop
    //   1004: iload_2
    //   1005: ifeq -> 1936
    //   1008: goto -> 1015
    //   1011: invokestatic a : (Ljava/lang/Throwable;)Ljava/lang/Throwable;
    //   1014: athrow
    //   1015: aload_3
    //   1016: getstatic burp/Zm8i.Z_ : Ljava/lang/String;
    //   1019: getstatic burp/Zzok.ZY : Ljava/lang/Object;
    //   1022: checkcast java/math/BigInteger
    //   1025: invokevirtual intValue : ()I
    //   1028: bipush #32
    //   1030: irem
    //   1031: invokestatic abs : (I)I
    //   1034: invokevirtual charAt : (I)C
    //   1037: invokevirtual append : (C)Ljava/lang/StringBuilder;
    //   1040: pop
    //   1041: iload_2
    //   1042: ifeq -> 1936
    //   1045: goto -> 1052
    //   1048: invokestatic a : (Ljava/lang/Throwable;)Ljava/lang/Throwable;
    //   1051: athrow
    //   1052: aload_3
    //   1053: getstatic burp/Zlo0.ZD : Ljava/lang/String;
    //   1056: getstatic burp/Zx_s.ZX : Ljava/lang/Object;
    //   1059: checkcast java/math/BigInteger
    //   1062: invokevirtual intValue : ()I
    //   1065: bipush #32
    //   1067: irem
    //   1068: invokestatic abs : (I)I
    //   1071: invokevirtual charAt : (I)C
    //   1074: invokevirtual append : (C)Ljava/lang/StringBuilder;
    //   1077: pop
    //   1078: iload_2
    //   1079: ifeq -> 1936
    //   1082: goto -> 1089
    //   1085: invokestatic a : (Ljava/lang/Throwable;)Ljava/lang/Throwable;
    //   1088: athrow
    //   1089: aload_3
    //   1090: getstatic burp/Zzh1.Zn : Ljava/lang/String;
    //   1093: getstatic burp/Zgii.ZD : Ljava/lang/Object;
    //   1096: checkcast java/math/BigInteger
    //   1099: invokevirtual intValue : ()I
    //   1102: bipush #32
    //   1104: irem
    //   1105: invokestatic abs : (I)I
    //   1108: invokevirtual charAt : (I)C
    //   1111: invokevirtual append : (C)Ljava/lang/StringBuilder;
    //   1114: pop
    //   1115: iload_2
    //   1116: ifeq -> 1936
    //   1119: goto -> 1126
    //   1122: invokestatic a : (Ljava/lang/Throwable;)Ljava/lang/Throwable;
    //   1125: athrow
    //   1126: aload_3
    //   1127: getstatic burp/Zg7p.ZA : Ljava/lang/String;
    //   1130: getstatic burp/Ze5t.Zc : Ljava/lang/Object;
    //   1133: checkcast java/math/BigInteger
    //   1136: invokevirtual intValue : ()I
    //   1139: bipush #32
    //   1141: irem
    //   1142: invokestatic abs : (I)I
    //   1145: invokevirtual charAt : (I)C
    //   1148: invokevirtual append : (C)Ljava/lang/StringBuilder;
    //   1151: pop
    //   1152: iload_2
    //   1153: ifeq -> 1936
    //   1156: goto -> 1163
    //   1159: invokestatic a : (Ljava/lang/Throwable;)Ljava/lang/Throwable;
    //   1162: athrow
    //   1163: aload_3
    //   1164: getstatic burp/Zl88.Zd : Ljava/lang/String;
    //   1167: getstatic burp/Zzb2.ZW : Ljava/lang/Object;
    //   1170: checkcast java/math/BigInteger
    //   1173: invokevirtual intValue : ()I
    //   1176: bipush #32
    //   1178: irem
    //   1179: invokestatic abs : (I)I
    //   1182: invokevirtual charAt : (I)C
    //   1185: invokevirtual append : (C)Ljava/lang/StringBuilder;
    //   1188: pop
    //   1189: iload_2
    //   1190: ifeq -> 1936
    //   1193: goto -> 1200
    //   1196: invokestatic a : (Ljava/lang/Throwable;)Ljava/lang/Throwable;
    //   1199: athrow
    //   1200: aload_3
    //   1201: getstatic burp/Zzc7.ZN : Ljava/lang/String;
    //   1204: getstatic burp/Zlo5.Zf : Ljava/lang/Object;
    //   1207: checkcast java/math/BigInteger
    //   1210: invokevirtual intValue : ()I
    //   1213: bipush #32
    //   1215: irem
    //   1216: invokestatic abs : (I)I
    //   1219: invokevirtual charAt : (I)C
    //   1222: invokevirtual append : (C)Ljava/lang/StringBuilder;
    //   1225: pop
    //   1226: iload_2
    //   1227: ifeq -> 1936
    //   1230: goto -> 1237
    //   1233: invokestatic a : (Ljava/lang/Throwable;)Ljava/lang/Throwable;
    //   1236: athrow
    //   1237: aload_3
    //   1238: getstatic burp/Zxzp.ZH : Ljava/lang/String;
    //   1241: getstatic burp/Zrqd.Zi : Ljava/lang/Object;
    //   1244: checkcast java/math/BigInteger
    //   1247: invokevirtual intValue : ()I
    //   1250: bipush #32
    //   1252: irem
    //   1253: invokestatic abs : (I)I
    //   1256: invokevirtual charAt : (I)C
    //   1259: invokevirtual append : (C)Ljava/lang/StringBuilder;
    //   1262: pop
    //   1263: iload_2
    //   1264: ifeq -> 1936
    //   1267: goto -> 1274
    //   1270: invokestatic a : (Ljava/lang/Throwable;)Ljava/lang/Throwable;
    //   1273: athrow
    //   1274: aload_3
    //   1275: getstatic burp/Zti7.Zc : Ljava/lang/String;
    //   1278: getstatic burp/Zry9.Zw : Ljava/lang/Object;
    //   1281: checkcast java/math/BigInteger
    //   1284: invokevirtual intValue : ()I
    //   1287: bipush #32
    //   1289: irem
    //   1290: invokestatic abs : (I)I
    //   1293: invokevirtual charAt : (I)C
    //   1296: invokevirtual append : (C)Ljava/lang/StringBuilder;
    //   1299: pop
    //   1300: iload_2
    //   1301: ifeq -> 1936
    //   1304: goto -> 1311
    //   1307: invokestatic a : (Ljava/lang/Throwable;)Ljava/lang/Throwable;
    //   1310: athrow
    //   1311: aload_3
    //   1312: getstatic burp/Zsow.Zh : Ljava/lang/String;
    //   1315: getstatic burp/Zegk.ZR : Ljava/lang/Object;
    //   1318: checkcast java/math/BigInteger
    //   1321: invokevirtual intValue : ()I
    //   1324: bipush #32
    //   1326: irem
    //   1327: invokestatic abs : (I)I
    //   1330: invokevirtual charAt : (I)C
    //   1333: invokevirtual append : (C)Ljava/lang/StringBuilder;
    //   1336: pop
    //   1337: iload_2
    //   1338: ifeq -> 1936
    //   1341: goto -> 1348
    //   1344: invokestatic a : (Ljava/lang/Throwable;)Ljava/lang/Throwable;
    //   1347: athrow
    //   1348: aload_3
    //   1349: getstatic burp/Zko9.Zf : Ljava/lang/String;
    //   1352: getstatic burp/Zmuj.ZH : Ljava/lang/Object;
    //   1355: checkcast java/math/BigInteger
    //   1358: invokevirtual intValue : ()I
    //   1361: bipush #32
    //   1363: irem
    //   1364: invokestatic abs : (I)I
    //   1367: invokevirtual charAt : (I)C
    //   1370: invokevirtual append : (C)Ljava/lang/StringBuilder;
    //   1373: pop
    //   1374: iload_2
    //   1375: ifeq -> 1936
    //   1378: goto -> 1385
    //   1381: invokestatic a : (Ljava/lang/Throwable;)Ljava/lang/Throwable;
    //   1384: athrow
    //   1385: aload_3
    //   1386: getstatic burp/Zl_9.ZP : Ljava/lang/String;
    //   1389: getstatic burp/Ztkh.Zh : Ljava/lang/Object;
    //   1392: checkcast java/math/BigInteger
    //   1395: invokevirtual intValue : ()I
    //   1398: bipush #32
    //   1400: irem
    //   1401: invokestatic abs : (I)I
    //   1404: invokevirtual charAt : (I)C
    //   1407: invokevirtual append : (C)Ljava/lang/StringBuilder;
    //   1410: pop
    //   1411: iload_2
    //   1412: ifeq -> 1936
    //   1415: goto -> 1422
    //   1418: invokestatic a : (Ljava/lang/Throwable;)Ljava/lang/Throwable;
    //   1421: athrow
    //   1422: aload_3
    //   1423: getstatic burp/Zsgj.ZN : Ljava/lang/String;
    //   1426: getstatic burp/Zlx5.Zp : Ljava/lang/Object;
    //   1429: checkcast java/math/BigInteger
    //   1432: invokevirtual intValue : ()I
    //   1435: bipush #32
    //   1437: irem
    //   1438: invokestatic abs : (I)I
    //   1441: invokevirtual charAt : (I)C
    //   1444: invokevirtual append : (C)Ljava/lang/StringBuilder;
    //   1447: pop
    //   1448: iload_2
    //   1449: ifeq -> 1936
    //   1452: goto -> 1459
    //   1455: invokestatic a : (Ljava/lang/Throwable;)Ljava/lang/Throwable;
    //   1458: athrow
    //   1459: aload_3
    //   1460: getstatic burp/Zlbd.Zq : Ljava/lang/String;
    //   1463: getstatic burp/Zrkc.ZI : Ljava/lang/Object;
    //   1466: checkcast java/math/BigInteger
    //   1469: invokevirtual intValue : ()I
    //   1472: bipush #32
    //   1474: irem
    //   1475: invokestatic abs : (I)I
    //   1478: invokevirtual charAt : (I)C
    //   1481: invokevirtual append : (C)Ljava/lang/StringBuilder;
    //   1484: pop
    //   1485: iload_2
    //   1486: ifeq -> 1936
    //   1489: goto -> 1496
    //   1492: invokestatic a : (Ljava/lang/Throwable;)Ljava/lang/Throwable;
    //   1495: athrow
    //   1496: aload_3
    //   1497: getstatic burp/Zrhp.ZQ : Ljava/lang/String;
    //   1500: getstatic burp/Zzri.ZG : Ljava/lang/Object;
    //   1503: checkcast java/math/BigInteger
    //   1506: invokevirtual intValue : ()I
    //   1509: bipush #32
    //   1511: irem
    //   1512: invokestatic abs : (I)I
    //   1515: invokevirtual charAt : (I)C
    //   1518: invokevirtual append : (C)Ljava/lang/StringBuilder;
    //   1521: pop
    //   1522: iload_2
    //   1523: ifeq -> 1936
    //   1526: goto -> 1533
    //   1529: invokestatic a : (Ljava/lang/Throwable;)Ljava/lang/Throwable;
    //   1532: athrow
    //   1533: aload_3
    //   1534: getstatic burp/Zzri.ZL : Ljava/lang/String;
    //   1537: getstatic burp/Zlhu.ZJ : Ljava/lang/Object;
    //   1540: checkcast java/math/BigInteger
    //   1543: invokevirtual intValue : ()I
    //   1546: bipush #32
    //   1548: irem
    //   1549: invokestatic abs : (I)I
    //   1552: invokevirtual charAt : (I)C
    //   1555: invokevirtual append : (C)Ljava/lang/StringBuilder;
    //   1558: pop
    //   1559: iload_2
    //   1560: ifeq -> 1936
    //   1563: goto -> 1570
    //   1566: invokestatic a : (Ljava/lang/Throwable;)Ljava/lang/Throwable;
    //   1569: athrow
    //   1570: aload_3
    //   1571: getstatic burp/Zrw7.Zo : Ljava/lang/String;
    //   1574: getstatic burp/Zrjg.ZG : Ljava/lang/Object;
    //   1577: checkcast java/math/BigInteger
    //   1580: invokevirtual intValue : ()I
    //   1583: bipush #32
    //   1585: irem
    //   1586: invokestatic abs : (I)I
    //   1589: invokevirtual charAt : (I)C
    //   1592: invokevirtual append : (C)Ljava/lang/StringBuilder;
    //   1595: pop
    //   1596: iload_2
    //   1597: ifeq -> 1936
    //   1600: goto -> 1607
    //   1603: invokestatic a : (Ljava/lang/Throwable;)Ljava/lang/Throwable;
    //   1606: athrow
    //   1607: aload_3
    //   1608: getstatic burp/Ze_0.Zi : Ljava/lang/String;
    //   1611: getstatic burp/Zke7.Zj : Ljava/lang/Object;
    //   1614: checkcast java/math/BigInteger
    //   1617: invokevirtual intValue : ()I
    //   1620: bipush #32
    //   1622: irem
    //   1623: invokestatic abs : (I)I
    //   1626: invokevirtual charAt : (I)C
    //   1629: invokevirtual append : (C)Ljava/lang/StringBuilder;
    //   1632: pop
    //   1633: iload_2
    //   1634: ifeq -> 1936
    //   1637: goto -> 1644
    //   1640: invokestatic a : (Ljava/lang/Throwable;)Ljava/lang/Throwable;
    //   1643: athrow
    //   1644: aload_3
    //   1645: getstatic burp/Zeud.Za : Ljava/lang/String;
    //   1648: getstatic burp/Ztjh.ZU : Ljava/lang/Object;
    //   1651: checkcast java/math/BigInteger
    //   1654: invokevirtual intValue : ()I
    //   1657: bipush #32
    //   1659: irem
    //   1660: invokestatic abs : (I)I
    //   1663: invokevirtual charAt : (I)C
    //   1666: invokevirtual append : (C)Ljava/lang/StringBuilder;
    //   1669: pop
    //   1670: iload_2
    //   1671: ifeq -> 1936
    //   1674: goto -> 1681
    //   1677: invokestatic a : (Ljava/lang/Throwable;)Ljava/lang/Throwable;
    //   1680: athrow
    //   1681: aload_3
    //   1682: getstatic burp/Zkdq.ZZ : Ljava/lang/String;
    //   1685: getstatic burp/Zgu4.Zs : Ljava/lang/Object;
    //   1688: checkcast java/math/BigInteger
    //   1691: invokevirtual intValue : ()I
    //   1694: bipush #32
    //   1696: irem
    //   1697: invokestatic abs : (I)I
    //   1700: invokevirtual charAt : (I)C
    //   1703: invokevirtual append : (C)Ljava/lang/StringBuilder;
    //   1706: pop
    //   1707: iload_2
    //   1708: ifeq -> 1936
    //   1711: goto -> 1718
    //   1714: invokestatic a : (Ljava/lang/Throwable;)Ljava/lang/Throwable;
    //   1717: athrow
    //   1718: aload_3
    //   1719: getstatic burp/Zk7f.ZA : Ljava/lang/String;
    //   1722: getstatic burp/Zlqy.ZP : Ljava/lang/Object;
    //   1725: checkcast java/math/BigInteger
    //   1728: invokevirtual intValue : ()I
    //   1731: bipush #32
    //   1733: irem
    //   1734: invokestatic abs : (I)I
    //   1737: invokevirtual charAt : (I)C
    //   1740: invokevirtual append : (C)Ljava/lang/StringBuilder;
    //   1743: pop
    //   1744: iload_2
    //   1745: ifeq -> 1936
    //   1748: goto -> 1755
    //   1751: invokestatic a : (Ljava/lang/Throwable;)Ljava/lang/Throwable;
    //   1754: athrow
    //   1755: aload_3
    //   1756: getstatic burp/Zs59.Zc : Ljava/lang/String;
    //   1759: getstatic burp/Zttj.ZF : Ljava/lang/Object;
    //   1762: checkcast java/math/BigInteger
    //   1765: invokevirtual intValue : ()I
    //   1768: bipush #32
    //   1770: irem
    //   1771: invokestatic abs : (I)I
    //   1774: invokevirtual charAt : (I)C
    //   1777: invokevirtual append : (C)Ljava/lang/StringBuilder;
    //   1780: pop
    //   1781: iload_2
    //   1782: ifeq -> 1936
    //   1785: goto -> 1792
    //   1788: invokestatic a : (Ljava/lang/Throwable;)Ljava/lang/Throwable;
    //   1791: athrow
    //   1792: aload_3
    //   1793: getstatic burp/Zzr.Zp : Ljava/lang/String;
    //   1796: getstatic burp/Zzuh.ZV : Ljava/lang/Object;
    //   1799: checkcast java/math/BigInteger
    //   1802: invokevirtual intValue : ()I
    //   1805: bipush #32
    //   1807: irem
    //   1808: invokestatic abs : (I)I
    //   1811: invokevirtual charAt : (I)C
    //   1814: invokevirtual append : (C)Ljava/lang/StringBuilder;
    //   1817: pop
    //   1818: iload_2
    //   1819: ifeq -> 1936
    //   1822: goto -> 1829
    //   1825: invokestatic a : (Ljava/lang/Throwable;)Ljava/lang/Throwable;
    //   1828: athrow
    //   1829: aload_3
    //   1830: getstatic burp/Zxdy.Zm : Ljava/lang/String;
    //   1833: getstatic burp/Zb2s.Ze : Ljava/lang/Object;
    //   1836: checkcast java/math/BigInteger
    //   1839: invokevirtual intValue : ()I
    //   1842: bipush #32
    //   1844: irem
    //   1845: invokestatic abs : (I)I
    //   1848: invokevirtual charAt : (I)C
    //   1851: invokevirtual append : (C)Ljava/lang/StringBuilder;
    //   1854: pop
    //   1855: iload_2
    //   1856: ifeq -> 1936
    //   1859: goto -> 1866
    //   1862: invokestatic a : (Ljava/lang/Throwable;)Ljava/lang/Throwable;
    //   1865: athrow
    //   1866: aload_3
    //   1867: getstatic burp/Ze5f.Zt : Ljava/lang/String;
    //   1870: getstatic burp/Zlpj.Zc : Ljava/lang/Object;
    //   1873: checkcast java/math/BigInteger
    //   1876: invokevirtual intValue : ()I
    //   1879: bipush #32
    //   1881: irem
    //   1882: invokestatic abs : (I)I
    //   1885: invokevirtual charAt : (I)C
    //   1888: invokevirtual append : (C)Ljava/lang/StringBuilder;
    //   1891: pop
    //   1892: iload_2
    //   1893: ifeq -> 1936
    //   1896: goto -> 1903
    //   1899: invokestatic a : (Ljava/lang/Throwable;)Ljava/lang/Throwable;
    //   1902: athrow
    //   1903: aload_3
    //   1904: getstatic burp/Ze0z.ZU : Ljava/lang/String;
    //   1907: getstatic burp/Zm3x.ZM : Ljava/lang/Object;
    //   1910: checkcast java/math/BigInteger
    //   1913: invokevirtual intValue : ()I
    //   1916: bipush #32
    //   1918: irem
    //   1919: invokestatic abs : (I)I
    //   1922: invokevirtual charAt : (I)C
    //   1925: invokevirtual append : (C)Ljava/lang/StringBuilder;
    //   1928: pop
    //   1929: goto -> 1936
    //   1932: invokestatic a : (Ljava/lang/Throwable;)Ljava/lang/Throwable;
    //   1935: athrow
    //   1936: iinc #4, 1
    //   1939: iload_2
    //   1940: ifeq -> 606
    //   1943: aload_3
    //   1944: invokevirtual toString : ()Ljava/lang/String;
    //   1947: putstatic burp/Zgw_.ZH : Ljava/lang/String;
    //   1950: sipush #14002
    //   1953: sipush #-28744
    //   1956: invokestatic a : (II)Ljava/lang/String;
    //   1959: iconst_1
    //   1960: ldc burp/Zso7
    //   1962: invokevirtual getClassLoader : ()Ljava/lang/ClassLoader;
    //   1965: invokestatic forName : (Ljava/lang/String;ZLjava/lang/ClassLoader;)Ljava/lang/Class;
    //   1968: invokevirtual getDeclaredFields : ()[Ljava/lang/reflect/Field;
    //   1971: astore #4
    //   1973: aload #4
    //   1975: arraylength
    //   1976: istore #5
    //   1978: iconst_0
    //   1979: istore #6
    //   1981: iload #6
    //   1983: iload #5
    //   1985: if_icmpge -> 2123
    //   1988: aload #4
    //   1990: iload #6
    //   1992: aaload
    //   1993: astore #7
    //   1995: aload #7
    //   1997: invokevirtual getModifiers : ()I
    //   2000: invokestatic isStatic : (I)Z
    //   2003: ifne -> 2013
    //   2006: goto -> 2116
    //   2009: invokestatic a : (Ljava/lang/Throwable;)Ljava/lang/Throwable;
    //   2012: athrow
    //   2013: aload #7
    //   2015: invokevirtual getType : ()Ljava/lang/Class;
    //   2018: astore #8
    //   2020: aload #8
    //   2022: ifnull -> 2103
    //   2025: aload #8
    //   2027: invokevirtual isPrimitive : ()Z
    //   2030: ifne -> 2103
    //   2033: goto -> 2040
    //   2036: invokestatic a : (Ljava/lang/Throwable;)Ljava/lang/Throwable;
    //   2039: athrow
    //   2040: aload #8
    //   2042: invokevirtual getPackage : ()Ljava/lang/Package;
    //   2045: ifnull -> 2103
    //   2048: goto -> 2055
    //   2051: invokestatic a : (Ljava/lang/Throwable;)Ljava/lang/Throwable;
    //   2054: athrow
    //   2055: aload #8
    //   2057: invokevirtual getPackage : ()Ljava/lang/Package;
    //   2060: invokevirtual getName : ()Ljava/lang/String;
    //   2063: ifnull -> 2103
    //   2066: goto -> 2073
    //   2069: invokestatic a : (Ljava/lang/Throwable;)Ljava/lang/Throwable;
    //   2072: athrow
    //   2073: aload #8
    //   2075: invokevirtual getPackage : ()Ljava/lang/Package;
    //   2078: invokevirtual getName : ()Ljava/lang/String;
    //   2081: sipush #14003
    //   2084: sipush #9758
    //   2087: invokestatic a : (II)Ljava/lang/String;
    //   2090: invokevirtual startsWith : (Ljava/lang/String;)Z
    //   2093: ifne -> 2103
    //   2096: goto -> 2103
    //   2099: invokestatic a : (Ljava/lang/Throwable;)Ljava/lang/Throwable;
    //   2102: athrow
    //   2103: aload #7
    //   2105: iconst_1
    //   2106: invokevirtual setAccessible : (Z)V
    //   2109: aload #7
    //   2111: aconst_null
    //   2112: invokevirtual get : (Ljava/lang/Object;)Ljava/lang/Object;
    //   2115: pop
    //   2116: iinc #6, 1
    //   2119: iload_2
    //   2120: ifeq -> 1981
    //   2123: sipush #14004
    //   2126: sipush #13692
    //   2129: invokestatic a : (II)Ljava/lang/String;
    //   2132: invokestatic forName : (Ljava/lang/String;)Ljava/lang/Class;
    //   2135: invokevirtual getDeclaredMethods : ()[Ljava/lang/reflect/Method;
    //   2138: astore #4
    //   2140: aload #4
    //   2142: arraylength
    //   2143: istore #5
    //   2145: iconst_0
    //   2146: istore #6
    //   2148: iload #6
    //   2150: iload #5
    //   2152: if_icmpge -> 2282
    //   2155: aload #4
    //   2157: iload #6
    //   2159: aaload
    //   2160: astore #7
    //   2162: aload #7
    //   2164: invokevirtual getParameterTypes : ()[Ljava/lang/Class;
    //   2167: pop
    //   2168: aload #7
    //   2170: invokevirtual getModifiers : ()I
    //   2173: invokestatic isStatic : (I)Z
    //   2176: ifeq -> 2268
    //   2179: aload #7
    //   2181: invokevirtual getParameterTypes : ()[Ljava/lang/Class;
    //   2184: arraylength
    //   2185: iconst_2
    //   2186: if_icmpne -> 2268
    //   2189: goto -> 2196
    //   2192: invokestatic a : (Ljava/lang/Throwable;)Ljava/lang/Throwable;
    //   2195: athrow
    //   2196: aload #7
    //   2198: invokevirtual getReturnType : ()Ljava/lang/Class;
    //   2201: getstatic java/lang/Boolean.TYPE : Ljava/lang/Class;
    //   2204: if_acmpne -> 2268
    //   2207: goto -> 2214
    //   2210: invokestatic a : (Ljava/lang/Throwable;)Ljava/lang/Throwable;
    //   2213: athrow
    //   2214: aload #7
    //   2216: iconst_1
    //   2217: invokevirtual setAccessible : (Z)V
    //   2220: aload #7
    //   2222: aconst_null
    //   2223: iconst_2
    //   2224: anewarray java/lang/Object
    //   2227: dup
    //   2228: iconst_0
    //   2229: aload_0
    //   2230: aastore
    //   2231: dup
    //   2232: iconst_1
    //   2233: aload_1
    //   2234: ifnonnull -> 2252
    //   2237: goto -> 2244
    //   2240: invokestatic a : (Ljava/lang/Throwable;)Ljava/lang/Throwable;
    //   2243: athrow
    //   2244: aload_1
    //   2245: goto -> 2259
    //   2248: invokestatic a : (Ljava/lang/Throwable;)Ljava/lang/Throwable;
    //   2251: athrow
    //   2252: aload_1
    //   2253: checkcast [B
    //   2256: invokevirtual clone : ()Ljava/lang/Object;
    //   2259: aastore
    //   2260: invokevirtual invoke : (Ljava/lang/Object;[Ljava/lang/Object;)Ljava/lang/Object;
    //   2263: pop
    //   2264: iload_2
    //   2265: ifeq -> 2282
    //   2268: iinc #6, 1
    //   2271: iload_2
    //   2272: ifeq -> 2148
    //   2275: goto -> 2282
    //   2278: invokestatic a : (Ljava/lang/Throwable;)Ljava/lang/Throwable;
    //   2281: athrow
    //   2282: sipush #14010
    //   2285: sipush #13838
    //   2288: invokestatic a : (II)Ljava/lang/String;
    //   2291: iconst_1
    //   2292: ldc burp/Zttj
    //   2294: invokevirtual getClassLoader : ()Ljava/lang/ClassLoader;
    //   2297: invokestatic forName : (Ljava/lang/String;ZLjava/lang/ClassLoader;)Ljava/lang/Class;
    //   2300: invokevirtual getDeclaredFields : ()[Ljava/lang/reflect/Field;
    //   2303: astore #4
    //   2305: aload #4
    //   2307: arraylength
    //   2308: istore #5
    //   2310: iconst_0
    //   2311: istore #6
    //   2313: iload #6
    //   2315: iload #5
    //   2317: if_icmpge -> 2455
    //   2320: aload #4
    //   2322: iload #6
    //   2324: aaload
    //   2325: astore #7
    //   2327: aload #7
    //   2329: invokevirtual getModifiers : ()I
    //   2332: invokestatic isStatic : (I)Z
    //   2335: ifne -> 2345
    //   2338: goto -> 2448
    //   2341: invokestatic a : (Ljava/lang/Throwable;)Ljava/lang/Throwable;
    //   2344: athrow
    //   2345: aload #7
    //   2347: invokevirtual getType : ()Ljava/lang/Class;
    //   2350: astore #8
    //   2352: aload #8
    //   2354: ifnull -> 2435
    //   2357: aload #8
    //   2359: invokevirtual isPrimitive : ()Z
    //   2362: ifne -> 2435
    //   2365: goto -> 2372
    //   2368: invokestatic a : (Ljava/lang/Throwable;)Ljava/lang/Throwable;
    //   2371: athrow
    //   2372: aload #8
    //   2374: invokevirtual getPackage : ()Ljava/lang/Package;
    //   2377: ifnull -> 2435
    //   2380: goto -> 2387
    //   2383: invokestatic a : (Ljava/lang/Throwable;)Ljava/lang/Throwable;
    //   2386: athrow
    //   2387: aload #8
    //   2389: invokevirtual getPackage : ()Ljava/lang/Package;
    //   2392: invokevirtual getName : ()Ljava/lang/String;
    //   2395: ifnull -> 2435
    //   2398: goto -> 2405
    //   2401: invokestatic a : (Ljava/lang/Throwable;)Ljava/lang/Throwable;
    //   2404: athrow
    //   2405: aload #8
    //   2407: invokevirtual getPackage : ()Ljava/lang/Package;
    //   2410: invokevirtual getName : ()Ljava/lang/String;
    //   2413: sipush #14011
    //   2416: sipush #4629
    //   2419: invokestatic a : (II)Ljava/lang/String;
    //   2422: invokevirtual startsWith : (Ljava/lang/String;)Z
    //   2425: ifne -> 2435
    //   2428: goto -> 2435
    //   2431: invokestatic a : (Ljava/lang/Throwable;)Ljava/lang/Throwable;
    //   2434: athrow
    //   2435: aload #7
    //   2437: iconst_1
    //   2438: invokevirtual setAccessible : (Z)V
    //   2441: aload #7
    //   2443: aconst_null
    //   2444: invokevirtual get : (Ljava/lang/Object;)Ljava/lang/Object;
    //   2447: pop
    //   2448: iinc #6, 1
    //   2451: iload_2
    //   2452: ifeq -> 2313
    //   2455: sipush #13993
    //   2458: bipush #-42
    //   2460: invokestatic a : (II)Ljava/lang/String;
    //   2463: invokestatic forName : (Ljava/lang/String;)Ljava/lang/Class;
    //   2466: invokevirtual getDeclaredMethods : ()[Ljava/lang/reflect/Method;
    //   2469: astore #4
    //   2471: aload #4
    //   2473: arraylength
    //   2474: istore #5
    //   2476: iconst_0
    //   2477: istore #6
    //   2479: iload #6
    //   2481: iload #5
    //   2483: if_icmpge -> 2616
    //   2486: aload #4
    //   2488: iload #6
    //   2490: aaload
    //   2491: astore #7
    //   2493: aload #7
    //   2495: invokevirtual getParameterTypes : ()[Ljava/lang/Class;
    //   2498: pop
    //   2499: aload #7
    //   2501: invokevirtual getModifiers : ()I
    //   2504: invokestatic isStatic : (I)Z
    //   2507: ifeq -> 2602
    //   2510: aload #7
    //   2512: invokevirtual getParameterTypes : ()[Ljava/lang/Class;
    //   2515: arraylength
    //   2516: iconst_2
    //   2517: if_icmpne -> 2602
    //   2520: goto -> 2527
    //   2523: invokestatic a : (Ljava/lang/Throwable;)Ljava/lang/Throwable;
    //   2526: athrow
    //   2527: aload #7
    //   2529: invokevirtual getReturnType : ()Ljava/lang/Class;
    //   2532: getstatic java/lang/Void.TYPE : Ljava/lang/Class;
    //   2535: invokevirtual equals : (Ljava/lang/Object;)Z
    //   2538: ifeq -> 2602
    //   2541: goto -> 2548
    //   2544: invokestatic a : (Ljava/lang/Throwable;)Ljava/lang/Throwable;
    //   2547: athrow
    //   2548: aload #7
    //   2550: iconst_1
    //   2551: invokevirtual setAccessible : (Z)V
    //   2554: aload #7
    //   2556: aconst_null
    //   2557: iconst_2
    //   2558: anewarray java/lang/Object
    //   2561: dup
    //   2562: iconst_0
    //   2563: aload_0
    //   2564: aastore
    //   2565: dup
    //   2566: iconst_1
    //   2567: aload_1
    //   2568: ifnonnull -> 2586
    //   2571: goto -> 2578
    //   2574: invokestatic a : (Ljava/lang/Throwable;)Ljava/lang/Throwable;
    //   2577: athrow
    //   2578: aload_1
    //   2579: goto -> 2593
    //   2582: invokestatic a : (Ljava/lang/Throwable;)Ljava/lang/Throwable;
    //   2585: athrow
    //   2586: aload_1
    //   2587: checkcast [B
    //   2590: invokevirtual clone : ()Ljava/lang/Object;
    //   2593: aastore
    //   2594: invokevirtual invoke : (Ljava/lang/Object;[Ljava/lang/Object;)Ljava/lang/Object;
    //   2597: pop
    //   2598: iload_2
    //   2599: ifeq -> 2616
    //   2602: iinc #6, 1
    //   2605: iload_2
    //   2606: ifeq -> 2479
    //   2609: goto -> 2616
    //   2612: invokestatic a : (Ljava/lang/Throwable;)Ljava/lang/Throwable;
    //   2615: athrow
    //   2616: iconst_0
    //   2617: istore #4
    //   2619: getstatic burp/Ztte.ZD : Ljava/lang/String;
    //   2622: getstatic burp/Zei_.Za : Ljava/lang/Object;
    //   2625: checkcast java/math/BigInteger
    //   2628: invokevirtual intValue : ()I
    //   2631: bipush #32
    //   2633: irem
    //   2634: invokestatic abs : (I)I
    //   2637: invokevirtual charAt : (I)C
    //   2640: getstatic burp/Zl_9.ZP : Ljava/lang/String;
    //   2643: getstatic burp/Zs_.Zs : Ljava/lang/Object;
    //   2646: checkcast java/math/BigInteger
    //   2649: invokevirtual intValue : ()I
    //   2652: bipush #32
    //   2654: irem
    //   2655: invokestatic abs : (I)I
    //   2658: invokevirtual charAt : (I)C
    //   2661: if_icmpgt -> 3006
    //   2664: sipush #13990
    //   2667: sipush #29846
    //   2670: invokestatic a : (II)Ljava/lang/String;
    //   2673: iconst_1
    //   2674: ldc burp/Zl3l
    //   2676: invokevirtual getClassLoader : ()Ljava/lang/ClassLoader;
    //   2679: invokestatic forName : (Ljava/lang/String;ZLjava/lang/ClassLoader;)Ljava/lang/Class;
    //   2682: invokevirtual getDeclaredFields : ()[Ljava/lang/reflect/Field;
    //   2685: astore #5
    //   2687: aload #5
    //   2689: arraylength
    //   2690: istore #6
    //   2692: iconst_0
    //   2693: istore #7
    //   2695: iload #7
    //   2697: iload #6
    //   2699: if_icmpge -> 2837
    //   2702: aload #5
    //   2704: iload #7
    //   2706: aaload
    //   2707: astore #8
    //   2709: aload #8
    //   2711: invokevirtual getModifiers : ()I
    //   2714: invokestatic isStatic : (I)Z
    //   2717: ifne -> 2727
    //   2720: goto -> 2830
    //   2723: invokestatic a : (Ljava/lang/Throwable;)Ljava/lang/Throwable;
    //   2726: athrow
    //   2727: aload #8
    //   2729: invokevirtual getType : ()Ljava/lang/Class;
    //   2732: astore #9
    //   2734: aload #9
    //   2736: ifnull -> 2817
    //   2739: aload #9
    //   2741: invokevirtual isPrimitive : ()Z
    //   2744: ifne -> 2817
    //   2747: goto -> 2754
    //   2750: invokestatic a : (Ljava/lang/Throwable;)Ljava/lang/Throwable;
    //   2753: athrow
    //   2754: aload #9
    //   2756: invokevirtual getPackage : ()Ljava/lang/Package;
    //   2759: ifnull -> 2817
    //   2762: goto -> 2769
    //   2765: invokestatic a : (Ljava/lang/Throwable;)Ljava/lang/Throwable;
    //   2768: athrow
    //   2769: aload #9
    //   2771: invokevirtual getPackage : ()Ljava/lang/Package;
    //   2774: invokevirtual getName : ()Ljava/lang/String;
    //   2777: ifnull -> 2817
    //   2780: goto -> 2787
    //   2783: invokestatic a : (Ljava/lang/Throwable;)Ljava/lang/Throwable;
    //   2786: athrow
    //   2787: aload #9
    //   2789: invokevirtual getPackage : ()Ljava/lang/Package;
    //   2792: invokevirtual getName : ()Ljava/lang/String;
    //   2795: sipush #14011
    //   2798: sipush #4629
    //   2801: invokestatic a : (II)Ljava/lang/String;
    //   2804: invokevirtual startsWith : (Ljava/lang/String;)Z
    //   2807: ifne -> 2817
    //   2810: goto -> 2817
    //   2813: invokestatic a : (Ljava/lang/Throwable;)Ljava/lang/Throwable;
    //   2816: athrow
    //   2817: aload #8
    //   2819: iconst_1
    //   2820: invokevirtual setAccessible : (Z)V
    //   2823: aload #8
    //   2825: aconst_null
    //   2826: invokevirtual get : (Ljava/lang/Object;)Ljava/lang/Object;
    //   2829: pop
    //   2830: iinc #7, 1
    //   2833: iload_2
    //   2834: ifeq -> 2695
    //   2837: sipush #13990
    //   2840: sipush #29846
    //   2843: invokestatic a : (II)Ljava/lang/String;
    //   2846: invokestatic forName : (Ljava/lang/String;)Ljava/lang/Class;
    //   2849: invokevirtual getDeclaredMethods : ()[Ljava/lang/reflect/Method;
    //   2852: astore #5
    //   2854: aload #5
    //   2856: arraylength
    //   2857: istore #6
    //   2859: iconst_0
    //   2860: istore #7
    //   2862: iload #7
    //   2864: iload #6
    //   2866: if_icmpge -> 3003
    //   2869: aload #5
    //   2871: iload #7
    //   2873: aaload
    //   2874: astore #8
    //   2876: aload #8
    //   2878: invokevirtual getParameterTypes : ()[Ljava/lang/Class;
    //   2881: pop
    //   2882: aload #8
    //   2884: invokevirtual getModifiers : ()I
    //   2887: invokestatic isStatic : (I)Z
    //   2890: ifeq -> 2989
    //   2893: aload #8
    //   2895: invokevirtual getParameterTypes : ()[Ljava/lang/Class;
    //   2898: arraylength
    //   2899: iconst_2
    //   2900: if_icmpne -> 2989
    //   2903: goto -> 2910
    //   2906: invokestatic a : (Ljava/lang/Throwable;)Ljava/lang/Throwable;
    //   2909: athrow
    //   2910: aload #8
    //   2912: invokevirtual getReturnType : ()Ljava/lang/Class;
    //   2915: getstatic java/lang/Boolean.TYPE : Ljava/lang/Class;
    //   2918: if_acmpne -> 2989
    //   2921: goto -> 2928
    //   2924: invokestatic a : (Ljava/lang/Throwable;)Ljava/lang/Throwable;
    //   2927: athrow
    //   2928: aload #8
    //   2930: iconst_1
    //   2931: invokevirtual setAccessible : (Z)V
    //   2934: aload #8
    //   2936: aconst_null
    //   2937: iconst_2
    //   2938: anewarray java/lang/Object
    //   2941: dup
    //   2942: iconst_0
    //   2943: aload_0
    //   2944: aastore
    //   2945: dup
    //   2946: iconst_1
    //   2947: aload_1
    //   2948: ifnonnull -> 2966
    //   2951: goto -> 2958
    //   2954: invokestatic a : (Ljava/lang/Throwable;)Ljava/lang/Throwable;
    //   2957: athrow
    //   2958: aload_1
    //   2959: goto -> 2973
    //   2962: invokestatic a : (Ljava/lang/Throwable;)Ljava/lang/Throwable;
    //   2965: athrow
    //   2966: aload_1
    //   2967: checkcast [B
    //   2970: invokevirtual clone : ()Ljava/lang/Object;
    //   2973: aastore
    //   2974: invokevirtual invoke : (Ljava/lang/Object;[Ljava/lang/Object;)Ljava/lang/Object;
    //   2977: checkcast java/lang/Boolean
    //   2980: invokevirtual booleanValue : ()Z
    //   2983: istore #4
    //   2985: iload_2
    //   2986: ifeq -> 3003
    //   2989: iinc #7, 1
    //   2992: iload_2
    //   2993: ifeq -> 2862
    //   2996: goto -> 3003
    //   2999: invokestatic a : (Ljava/lang/Throwable;)Ljava/lang/Throwable;
    //   3002: athrow
    //   3003: goto -> 3345
    //   3006: sipush #13991
    //   3009: sipush #-4641
    //   3012: invokestatic a : (II)Ljava/lang/String;
    //   3015: iconst_1
    //   3016: ldc burp/Zezn
    //   3018: invokevirtual getClassLoader : ()Ljava/lang/ClassLoader;
    //   3021: invokestatic forName : (Ljava/lang/String;ZLjava/lang/ClassLoader;)Ljava/lang/Class;
    //   3024: invokevirtual getDeclaredFields : ()[Ljava/lang/reflect/Field;
    //   3027: astore #5
    //   3029: aload #5
    //   3031: arraylength
    //   3032: istore #6
    //   3034: iconst_0
    //   3035: istore #7
    //   3037: iload #7
    //   3039: iload #6
    //   3041: if_icmpge -> 3179
    //   3044: aload #5
    //   3046: iload #7
    //   3048: aaload
    //   3049: astore #8
    //   3051: aload #8
    //   3053: invokevirtual getModifiers : ()I
    //   3056: invokestatic isStatic : (I)Z
    //   3059: ifne -> 3069
    //   3062: goto -> 3172
    //   3065: invokestatic a : (Ljava/lang/Throwable;)Ljava/lang/Throwable;
    //   3068: athrow
    //   3069: aload #8
    //   3071: invokevirtual getType : ()Ljava/lang/Class;
    //   3074: astore #9
    //   3076: aload #9
    //   3078: ifnull -> 3159
    //   3081: aload #9
    //   3083: invokevirtual isPrimitive : ()Z
    //   3086: ifne -> 3159
    //   3089: goto -> 3096
    //   3092: invokestatic a : (Ljava/lang/Throwable;)Ljava/lang/Throwable;
    //   3095: athrow
    //   3096: aload #9
    //   3098: invokevirtual getPackage : ()Ljava/lang/Package;
    //   3101: ifnull -> 3159
    //   3104: goto -> 3111
    //   3107: invokestatic a : (Ljava/lang/Throwable;)Ljava/lang/Throwable;
    //   3110: athrow
    //   3111: aload #9
    //   3113: invokevirtual getPackage : ()Ljava/lang/Package;
    //   3116: invokevirtual getName : ()Ljava/lang/String;
    //   3119: ifnull -> 3159
    //   3122: goto -> 3129
    //   3125: invokestatic a : (Ljava/lang/Throwable;)Ljava/lang/Throwable;
    //   3128: athrow
    //   3129: aload #9
    //   3131: invokevirtual getPackage : ()Ljava/lang/Package;
    //   3134: invokevirtual getName : ()Ljava/lang/String;
    //   3137: sipush #14011
    //   3140: sipush #4629
    //   3143: invokestatic a : (II)Ljava/lang/String;
    //   3146: invokevirtual startsWith : (Ljava/lang/String;)Z
    //   3149: ifne -> 3159
    //   3152: goto -> 3159
    //   3155: invokestatic a : (Ljava/lang/Throwable;)Ljava/lang/Throwable;
    //   3158: athrow
    //   3159: aload #8
    //   3161: iconst_1
    //   3162: invokevirtual setAccessible : (Z)V
    //   3165: aload #8
    //   3167: aconst_null
    //   3168: invokevirtual get : (Ljava/lang/Object;)Ljava/lang/Object;
    //   3171: pop
    //   3172: iinc #7, 1
    //   3175: iload_2
    //   3176: ifeq -> 3037
    //   3179: sipush #14015
    //   3182: sipush #25021
    //   3185: invokestatic a : (II)Ljava/lang/String;
    //   3188: invokestatic forName : (Ljava/lang/String;)Ljava/lang/Class;
    //   3191: invokevirtual getDeclaredMethods : ()[Ljava/lang/reflect/Method;
    //   3194: astore #5
    //   3196: aload #5
    //   3198: arraylength
    //   3199: istore #6
    //   3201: iconst_0
    //   3202: istore #7
    //   3204: iload #7
    //   3206: iload #6
    //   3208: if_icmpge -> 3345
    //   3211: aload #5
    //   3213: iload #7
    //   3215: aaload
    //   3216: astore #8
    //   3218: aload #8
    //   3220: invokevirtual getParameterTypes : ()[Ljava/lang/Class;
    //   3223: pop
    //   3224: aload #8
    //   3226: invokevirtual getModifiers : ()I
    //   3229: invokestatic isStatic : (I)Z
    //   3232: ifeq -> 3331
    //   3235: aload #8
    //   3237: invokevirtual getParameterTypes : ()[Ljava/lang/Class;
    //   3240: arraylength
    //   3241: iconst_2
    //   3242: if_icmpne -> 3331
    //   3245: goto -> 3252
    //   3248: invokestatic a : (Ljava/lang/Throwable;)Ljava/lang/Throwable;
    //   3251: athrow
    //   3252: aload #8
    //   3254: invokevirtual getReturnType : ()Ljava/lang/Class;
    //   3257: getstatic java/lang/Boolean.TYPE : Ljava/lang/Class;
    //   3260: if_acmpne -> 3331
    //   3263: goto -> 3270
    //   3266: invokestatic a : (Ljava/lang/Throwable;)Ljava/lang/Throwable;
    //   3269: athrow
    //   3270: aload #8
    //   3272: iconst_1
    //   3273: invokevirtual setAccessible : (Z)V
    //   3276: aload #8
    //   3278: aconst_null
    //   3279: iconst_2
    //   3280: anewarray java/lang/Object
    //   3283: dup
    //   3284: iconst_0
    //   3285: aload_0
    //   3286: aastore
    //   3287: dup
    //   3288: iconst_1
    //   3289: aload_1
    //   3290: ifnonnull -> 3308
    //   3293: goto -> 3300
    //   3296: invokestatic a : (Ljava/lang/Throwable;)Ljava/lang/Throwable;
    //   3299: athrow
    //   3300: aload_1
    //   3301: goto -> 3315
    //   3304: invokestatic a : (Ljava/lang/Throwable;)Ljava/lang/Throwable;
    //   3307: athrow
    //   3308: aload_1
    //   3309: checkcast [B
    //   3312: invokevirtual clone : ()Ljava/lang/Object;
    //   3315: aastore
    //   3316: invokevirtual invoke : (Ljava/lang/Object;[Ljava/lang/Object;)Ljava/lang/Object;
    //   3319: checkcast java/lang/Boolean
    //   3322: invokevirtual booleanValue : ()Z
    //   3325: istore #4
    //   3327: iload_2
    //   3328: ifeq -> 3345
    //   3331: iinc #7, 1
    //   3334: iload_2
    //   3335: ifeq -> 3204
    //   3338: goto -> 3345
    //   3341: invokestatic a : (Ljava/lang/Throwable;)Ljava/lang/Throwable;
    //   3344: athrow
    //   3345: iload #4
    //   3347: ifeq -> 3353
    //   3350: iload #4
    //   3352: ireturn
    //   3353: getstatic burp/Zmt6.Zx : Ljava/lang/String;
    //   3356: getstatic burp/Zr8g.ZF : Ljava/lang/Object;
    //   3359: checkcast java/math/BigInteger
    //   3362: invokevirtual intValue : ()I
    //   3365: bipush #32
    //   3367: irem
    //   3368: invokestatic abs : (I)I
    //   3371: invokevirtual charAt : (I)C
    //   3374: getstatic burp/Zxoa.Z_ : Ljava/lang/String;
    //   3377: getstatic burp/Zr_k.Zx : Ljava/lang/Object;
    //   3380: checkcast java/math/BigInteger
    //   3383: invokevirtual intValue : ()I
    //   3386: bipush #32
    //   3388: irem
    //   3389: invokestatic abs : (I)I
    //   3392: invokevirtual charAt : (I)C
    //   3395: if_icmple -> 3741
    //   3398: sipush #14001
    //   3401: sipush #25223
    //   3404: invokestatic a : (II)Ljava/lang/String;
    //   3407: iconst_1
    //   3408: ldc burp/Zgq_
    //   3410: invokevirtual getClassLoader : ()Ljava/lang/ClassLoader;
    //   3413: invokestatic forName : (Ljava/lang/String;ZLjava/lang/ClassLoader;)Ljava/lang/Class;
    //   3416: invokevirtual getDeclaredFields : ()[Ljava/lang/reflect/Field;
    //   3419: astore #5
    //   3421: aload #5
    //   3423: arraylength
    //   3424: istore #6
    //   3426: iconst_0
    //   3427: istore #7
    //   3429: iload #7
    //   3431: iload #6
    //   3433: if_icmpge -> 3571
    //   3436: aload #5
    //   3438: iload #7
    //   3440: aaload
    //   3441: astore #8
    //   3443: aload #8
    //   3445: invokevirtual getModifiers : ()I
    //   3448: invokestatic isStatic : (I)Z
    //   3451: ifne -> 3461
    //   3454: goto -> 3564
    //   3457: invokestatic a : (Ljava/lang/Throwable;)Ljava/lang/Throwable;
    //   3460: athrow
    //   3461: aload #8
    //   3463: invokevirtual getType : ()Ljava/lang/Class;
    //   3466: astore #9
    //   3468: aload #9
    //   3470: ifnull -> 3551
    //   3473: aload #9
    //   3475: invokevirtual isPrimitive : ()Z
    //   3478: ifne -> 3551
    //   3481: goto -> 3488
    //   3484: invokestatic a : (Ljava/lang/Throwable;)Ljava/lang/Throwable;
    //   3487: athrow
    //   3488: aload #9
    //   3490: invokevirtual getPackage : ()Ljava/lang/Package;
    //   3493: ifnull -> 3551
    //   3496: goto -> 3503
    //   3499: invokestatic a : (Ljava/lang/Throwable;)Ljava/lang/Throwable;
    //   3502: athrow
    //   3503: aload #9
    //   3505: invokevirtual getPackage : ()Ljava/lang/Package;
    //   3508: invokevirtual getName : ()Ljava/lang/String;
    //   3511: ifnull -> 3551
    //   3514: goto -> 3521
    //   3517: invokestatic a : (Ljava/lang/Throwable;)Ljava/lang/Throwable;
    //   3520: athrow
    //   3521: aload #9
    //   3523: invokevirtual getPackage : ()Ljava/lang/Package;
    //   3526: invokevirtual getName : ()Ljava/lang/String;
    //   3529: sipush #14011
    //   3532: sipush #4629
    //   3535: invokestatic a : (II)Ljava/lang/String;
    //   3538: invokevirtual startsWith : (Ljava/lang/String;)Z
    //   3541: ifne -> 3551
    //   3544: goto -> 3551
    //   3547: invokestatic a : (Ljava/lang/Throwable;)Ljava/lang/Throwable;
    //   3550: athrow
    //   3551: aload #8
    //   3553: iconst_1
    //   3554: invokevirtual setAccessible : (Z)V
    //   3557: aload #8
    //   3559: aconst_null
    //   3560: invokevirtual get : (Ljava/lang/Object;)Ljava/lang/Object;
    //   3563: pop
    //   3564: iinc #7, 1
    //   3567: iload_2
    //   3568: ifeq -> 3429
    //   3571: sipush #14000
    //   3574: sipush #21544
    //   3577: invokestatic a : (II)Ljava/lang/String;
    //   3580: invokestatic forName : (Ljava/lang/String;)Ljava/lang/Class;
    //   3583: invokevirtual getDeclaredMethods : ()[Ljava/lang/reflect/Method;
    //   3586: astore #5
    //   3588: aload #5
    //   3590: arraylength
    //   3591: istore #6
    //   3593: iconst_0
    //   3594: istore #7
    //   3596: iload #7
    //   3598: iload #6
    //   3600: if_icmpge -> 3737
    //   3603: aload #5
    //   3605: iload #7
    //   3607: aaload
    //   3608: astore #8
    //   3610: aload #8
    //   3612: invokevirtual getParameterTypes : ()[Ljava/lang/Class;
    //   3615: pop
    //   3616: aload #8
    //   3618: invokevirtual getModifiers : ()I
    //   3621: invokestatic isStatic : (I)Z
    //   3624: ifeq -> 3723
    //   3627: aload #8
    //   3629: invokevirtual getParameterTypes : ()[Ljava/lang/Class;
    //   3632: arraylength
    //   3633: iconst_2
    //   3634: if_icmpne -> 3723
    //   3637: goto -> 3644
    //   3640: invokestatic a : (Ljava/lang/Throwable;)Ljava/lang/Throwable;
    //   3643: athrow
    //   3644: aload #8
    //   3646: invokevirtual getReturnType : ()Ljava/lang/Class;
    //   3649: getstatic java/lang/Boolean.TYPE : Ljava/lang/Class;
    //   3652: if_acmpne -> 3723
    //   3655: goto -> 3662
    //   3658: invokestatic a : (Ljava/lang/Throwable;)Ljava/lang/Throwable;
    //   3661: athrow
    //   3662: aload #8
    //   3664: iconst_1
    //   3665: invokevirtual setAccessible : (Z)V
    //   3668: aload #8
    //   3670: aconst_null
    //   3671: iconst_2
    //   3672: anewarray java/lang/Object
    //   3675: dup
    //   3676: iconst_0
    //   3677: aload_0
    //   3678: aastore
    //   3679: dup
    //   3680: iconst_1
    //   3681: aload_1
    //   3682: ifnonnull -> 3700
    //   3685: goto -> 3692
    //   3688: invokestatic a : (Ljava/lang/Throwable;)Ljava/lang/Throwable;
    //   3691: athrow
    //   3692: aload_1
    //   3693: goto -> 3707
    //   3696: invokestatic a : (Ljava/lang/Throwable;)Ljava/lang/Throwable;
    //   3699: athrow
    //   3700: aload_1
    //   3701: checkcast [B
    //   3704: invokevirtual clone : ()Ljava/lang/Object;
    //   3707: aastore
    //   3708: invokevirtual invoke : (Ljava/lang/Object;[Ljava/lang/Object;)Ljava/lang/Object;
    //   3711: checkcast java/lang/Boolean
    //   3714: invokevirtual booleanValue : ()Z
    //   3717: istore #4
    //   3719: iload_2
    //   3720: ifeq -> 3737
    //   3723: iinc #7, 1
    //   3726: iload_2
    //   3727: ifeq -> 3596
    //   3730: goto -> 3737
    //   3733: invokestatic a : (Ljava/lang/Throwable;)Ljava/lang/Throwable;
    //   3736: athrow
    //   3737: iload_2
    //   3738: ifeq -> 4080
    //   3741: sipush #14012
    //   3744: sipush #-6791
    //   3747: invokestatic a : (II)Ljava/lang/String;
    //   3750: iconst_1
    //   3751: ldc burp/Zb9k
    //   3753: invokevirtual getClassLoader : ()Ljava/lang/ClassLoader;
    //   3756: invokestatic forName : (Ljava/lang/String;ZLjava/lang/ClassLoader;)Ljava/lang/Class;
    //   3759: invokevirtual getDeclaredFields : ()[Ljava/lang/reflect/Field;
    //   3762: astore #5
    //   3764: aload #5
    //   3766: arraylength
    //   3767: istore #6
    //   3769: iconst_0
    //   3770: istore #7
    //   3772: iload #7
    //   3774: iload #6
    //   3776: if_icmpge -> 3914
    //   3779: aload #5
    //   3781: iload #7
    //   3783: aaload
    //   3784: astore #8
    //   3786: aload #8
    //   3788: invokevirtual getModifiers : ()I
    //   3791: invokestatic isStatic : (I)Z
    //   3794: ifne -> 3804
    //   3797: goto -> 3907
    //   3800: invokestatic a : (Ljava/lang/Throwable;)Ljava/lang/Throwable;
    //   3803: athrow
    //   3804: aload #8
    //   3806: invokevirtual getType : ()Ljava/lang/Class;
    //   3809: astore #9
    //   3811: aload #9
    //   3813: ifnull -> 3894
    //   3816: aload #9
    //   3818: invokevirtual isPrimitive : ()Z
    //   3821: ifne -> 3894
    //   3824: goto -> 3831
    //   3827: invokestatic a : (Ljava/lang/Throwable;)Ljava/lang/Throwable;
    //   3830: athrow
    //   3831: aload #9
    //   3833: invokevirtual getPackage : ()Ljava/lang/Package;
    //   3836: ifnull -> 3894
    //   3839: goto -> 3846
    //   3842: invokestatic a : (Ljava/lang/Throwable;)Ljava/lang/Throwable;
    //   3845: athrow
    //   3846: aload #9
    //   3848: invokevirtual getPackage : ()Ljava/lang/Package;
    //   3851: invokevirtual getName : ()Ljava/lang/String;
    //   3854: ifnull -> 3894
    //   3857: goto -> 3864
    //   3860: invokestatic a : (Ljava/lang/Throwable;)Ljava/lang/Throwable;
    //   3863: athrow
    //   3864: aload #9
    //   3866: invokevirtual getPackage : ()Ljava/lang/Package;
    //   3869: invokevirtual getName : ()Ljava/lang/String;
    //   3872: sipush #14011
    //   3875: sipush #4629
    //   3878: invokestatic a : (II)Ljava/lang/String;
    //   3881: invokevirtual startsWith : (Ljava/lang/String;)Z
    //   3884: ifne -> 3894
    //   3887: goto -> 3894
    //   3890: invokestatic a : (Ljava/lang/Throwable;)Ljava/lang/Throwable;
    //   3893: athrow
    //   3894: aload #8
    //   3896: iconst_1
    //   3897: invokevirtual setAccessible : (Z)V
    //   3900: aload #8
    //   3902: aconst_null
    //   3903: invokevirtual get : (Ljava/lang/Object;)Ljava/lang/Object;
    //   3906: pop
    //   3907: iinc #7, 1
    //   3910: iload_2
    //   3911: ifeq -> 3772
    //   3914: sipush #14007
    //   3917: sipush #22187
    //   3920: invokestatic a : (II)Ljava/lang/String;
    //   3923: invokestatic forName : (Ljava/lang/String;)Ljava/lang/Class;
    //   3926: invokevirtual getDeclaredMethods : ()[Ljava/lang/reflect/Method;
    //   3929: astore #5
    //   3931: aload #5
    //   3933: arraylength
    //   3934: istore #6
    //   3936: iconst_0
    //   3937: istore #7
    //   3939: iload #7
    //   3941: iload #6
    //   3943: if_icmpge -> 4080
    //   3946: aload #5
    //   3948: iload #7
    //   3950: aaload
    //   3951: astore #8
    //   3953: aload #8
    //   3955: invokevirtual getParameterTypes : ()[Ljava/lang/Class;
    //   3958: pop
    //   3959: aload #8
    //   3961: invokevirtual getModifiers : ()I
    //   3964: invokestatic isStatic : (I)Z
    //   3967: ifeq -> 4066
    //   3970: aload #8
    //   3972: invokevirtual getParameterTypes : ()[Ljava/lang/Class;
    //   3975: arraylength
    //   3976: iconst_2
    //   3977: if_icmpne -> 4066
    //   3980: goto -> 3987
    //   3983: invokestatic a : (Ljava/lang/Throwable;)Ljava/lang/Throwable;
    //   3986: athrow
    //   3987: aload #8
    //   3989: invokevirtual getReturnType : ()Ljava/lang/Class;
    //   3992: getstatic java/lang/Boolean.TYPE : Ljava/lang/Class;
    //   3995: if_acmpne -> 4066
    //   3998: goto -> 4005
    //   4001: invokestatic a : (Ljava/lang/Throwable;)Ljava/lang/Throwable;
    //   4004: athrow
    //   4005: aload #8
    //   4007: iconst_1
    //   4008: invokevirtual setAccessible : (Z)V
    //   4011: aload #8
    //   4013: aconst_null
    //   4014: iconst_2
    //   4015: anewarray java/lang/Object
    //   4018: dup
    //   4019: iconst_0
    //   4020: aload_0
    //   4021: aastore
    //   4022: dup
    //   4023: iconst_1
    //   4024: aload_1
    //   4025: ifnonnull -> 4043
    //   4028: goto -> 4035
    //   4031: invokestatic a : (Ljava/lang/Throwable;)Ljava/lang/Throwable;
    //   4034: athrow
    //   4035: aload_1
    //   4036: goto -> 4050
    //   4039: invokestatic a : (Ljava/lang/Throwable;)Ljava/lang/Throwable;
    //   4042: athrow
    //   4043: aload_1
    //   4044: checkcast [B
    //   4047: invokevirtual clone : ()Ljava/lang/Object;
    //   4050: aastore
    //   4051: invokevirtual invoke : (Ljava/lang/Object;[Ljava/lang/Object;)Ljava/lang/Object;
    //   4054: checkcast java/lang/Boolean
    //   4057: invokevirtual booleanValue : ()Z
    //   4060: istore #4
    //   4062: iload_2
    //   4063: ifeq -> 4080
    //   4066: iinc #7, 1
    //   4069: iload_2
    //   4070: ifeq -> 3939
    //   4073: goto -> 4080
    //   4076: invokestatic a : (Ljava/lang/Throwable;)Ljava/lang/Throwable;
    //   4079: athrow
    //   4080: iload #4
    //   4082: ifeq -> 4088
    //   4085: iload #4
    //   4087: ireturn
    //   4088: getstatic burp/Zb9k.Za : Ljava/lang/String;
    //   4091: getstatic burp/Zewo.ZZ : Ljava/lang/Object;
    //   4094: checkcast java/math/BigInteger
    //   4097: invokevirtual intValue : ()I
    //   4100: bipush #32
    //   4102: irem
    //   4103: invokestatic abs : (I)I
    //   4106: invokevirtual charAt : (I)C
    //   4109: getstatic burp/Zly0.ZE : Ljava/lang/String;
    //   4112: getstatic burp/Zeyt.ZR : Ljava/lang/Object;
    //   4115: checkcast java/math/BigInteger
    //   4118: invokevirtual intValue : ()I
    //   4121: bipush #32
    //   4123: irem
    //   4124: invokestatic abs : (I)I
    //   4127: invokevirtual charAt : (I)C
    //   4130: if_icmpgt -> 4476
    //   4133: sipush #13996
    //   4136: sipush #-14719
    //   4139: invokestatic a : (II)Ljava/lang/String;
    //   4142: iconst_1
    //   4143: ldc burp/Zeju
    //   4145: invokevirtual getClassLoader : ()Ljava/lang/ClassLoader;
    //   4148: invokestatic forName : (Ljava/lang/String;ZLjava/lang/ClassLoader;)Ljava/lang/Class;
    //   4151: invokevirtual getDeclaredFields : ()[Ljava/lang/reflect/Field;
    //   4154: astore #5
    //   4156: aload #5
    //   4158: arraylength
    //   4159: istore #6
    //   4161: iconst_0
    //   4162: istore #7
    //   4164: iload #7
    //   4166: iload #6
    //   4168: if_icmpge -> 4306
    //   4171: aload #5
    //   4173: iload #7
    //   4175: aaload
    //   4176: astore #8
    //   4178: aload #8
    //   4180: invokevirtual getModifiers : ()I
    //   4183: invokestatic isStatic : (I)Z
    //   4186: ifne -> 4196
    //   4189: goto -> 4299
    //   4192: invokestatic a : (Ljava/lang/Throwable;)Ljava/lang/Throwable;
    //   4195: athrow
    //   4196: aload #8
    //   4198: invokevirtual getType : ()Ljava/lang/Class;
    //   4201: astore #9
    //   4203: aload #9
    //   4205: ifnull -> 4286
    //   4208: aload #9
    //   4210: invokevirtual isPrimitive : ()Z
    //   4213: ifne -> 4286
    //   4216: goto -> 4223
    //   4219: invokestatic a : (Ljava/lang/Throwable;)Ljava/lang/Throwable;
    //   4222: athrow
    //   4223: aload #9
    //   4225: invokevirtual getPackage : ()Ljava/lang/Package;
    //   4228: ifnull -> 4286
    //   4231: goto -> 4238
    //   4234: invokestatic a : (Ljava/lang/Throwable;)Ljava/lang/Throwable;
    //   4237: athrow
    //   4238: aload #9
    //   4240: invokevirtual getPackage : ()Ljava/lang/Package;
    //   4243: invokevirtual getName : ()Ljava/lang/String;
    //   4246: ifnull -> 4286
    //   4249: goto -> 4256
    //   4252: invokestatic a : (Ljava/lang/Throwable;)Ljava/lang/Throwable;
    //   4255: athrow
    //   4256: aload #9
    //   4258: invokevirtual getPackage : ()Ljava/lang/Package;
    //   4261: invokevirtual getName : ()Ljava/lang/String;
    //   4264: sipush #14011
    //   4267: sipush #4629
    //   4270: invokestatic a : (II)Ljava/lang/String;
    //   4273: invokevirtual startsWith : (Ljava/lang/String;)Z
    //   4276: ifne -> 4286
    //   4279: goto -> 4286
    //   4282: invokestatic a : (Ljava/lang/Throwable;)Ljava/lang/Throwable;
    //   4285: athrow
    //   4286: aload #8
    //   4288: iconst_1
    //   4289: invokevirtual setAccessible : (Z)V
    //   4292: aload #8
    //   4294: aconst_null
    //   4295: invokevirtual get : (Ljava/lang/Object;)Ljava/lang/Object;
    //   4298: pop
    //   4299: iinc #7, 1
    //   4302: iload_2
    //   4303: ifeq -> 4164
    //   4306: sipush #14006
    //   4309: sipush #15682
    //   4312: invokestatic a : (II)Ljava/lang/String;
    //   4315: invokestatic forName : (Ljava/lang/String;)Ljava/lang/Class;
    //   4318: invokevirtual getDeclaredMethods : ()[Ljava/lang/reflect/Method;
    //   4321: astore #5
    //   4323: aload #5
    //   4325: arraylength
    //   4326: istore #6
    //   4328: iconst_0
    //   4329: istore #7
    //   4331: iload #7
    //   4333: iload #6
    //   4335: if_icmpge -> 4472
    //   4338: aload #5
    //   4340: iload #7
    //   4342: aaload
    //   4343: astore #8
    //   4345: aload #8
    //   4347: invokevirtual getParameterTypes : ()[Ljava/lang/Class;
    //   4350: pop
    //   4351: aload #8
    //   4353: invokevirtual getModifiers : ()I
    //   4356: invokestatic isStatic : (I)Z
    //   4359: ifeq -> 4458
    //   4362: aload #8
    //   4364: invokevirtual getParameterTypes : ()[Ljava/lang/Class;
    //   4367: arraylength
    //   4368: iconst_2
    //   4369: if_icmpne -> 4458
    //   4372: goto -> 4379
    //   4375: invokestatic a : (Ljava/lang/Throwable;)Ljava/lang/Throwable;
    //   4378: athrow
    //   4379: aload #8
    //   4381: invokevirtual getReturnType : ()Ljava/lang/Class;
    //   4384: getstatic java/lang/Boolean.TYPE : Ljava/lang/Class;
    //   4387: if_acmpne -> 4458
    //   4390: goto -> 4397
    //   4393: invokestatic a : (Ljava/lang/Throwable;)Ljava/lang/Throwable;
    //   4396: athrow
    //   4397: aload #8
    //   4399: iconst_1
    //   4400: invokevirtual setAccessible : (Z)V
    //   4403: aload #8
    //   4405: aconst_null
    //   4406: iconst_2
    //   4407: anewarray java/lang/Object
    //   4410: dup
    //   4411: iconst_0
    //   4412: aload_0
    //   4413: aastore
    //   4414: dup
    //   4415: iconst_1
    //   4416: aload_1
    //   4417: ifnonnull -> 4435
    //   4420: goto -> 4427
    //   4423: invokestatic a : (Ljava/lang/Throwable;)Ljava/lang/Throwable;
    //   4426: athrow
    //   4427: aload_1
    //   4428: goto -> 4442
    //   4431: invokestatic a : (Ljava/lang/Throwable;)Ljava/lang/Throwable;
    //   4434: athrow
    //   4435: aload_1
    //   4436: checkcast [B
    //   4439: invokevirtual clone : ()Ljava/lang/Object;
    //   4442: aastore
    //   4443: invokevirtual invoke : (Ljava/lang/Object;[Ljava/lang/Object;)Ljava/lang/Object;
    //   4446: checkcast java/lang/Boolean
    //   4449: invokevirtual booleanValue : ()Z
    //   4452: istore #4
    //   4454: iload_2
    //   4455: ifeq -> 4472
    //   4458: iinc #7, 1
    //   4461: iload_2
    //   4462: ifeq -> 4331
    //   4465: goto -> 4472
    //   4468: invokestatic a : (Ljava/lang/Throwable;)Ljava/lang/Throwable;
    //   4471: athrow
    //   4472: iload_2
    //   4473: ifeq -> 4815
    //   4476: sipush #13998
    //   4479: sipush #-6337
    //   4482: invokestatic a : (II)Ljava/lang/String;
    //   4485: iconst_1
    //   4486: ldc burp/Zgwh
    //   4488: invokevirtual getClassLoader : ()Ljava/lang/ClassLoader;
    //   4491: invokestatic forName : (Ljava/lang/String;ZLjava/lang/ClassLoader;)Ljava/lang/Class;
    //   4494: invokevirtual getDeclaredFields : ()[Ljava/lang/reflect/Field;
    //   4497: astore #5
    //   4499: aload #5
    //   4501: arraylength
    //   4502: istore #6
    //   4504: iconst_0
    //   4505: istore #7
    //   4507: iload #7
    //   4509: iload #6
    //   4511: if_icmpge -> 4649
    //   4514: aload #5
    //   4516: iload #7
    //   4518: aaload
    //   4519: astore #8
    //   4521: aload #8
    //   4523: invokevirtual getModifiers : ()I
    //   4526: invokestatic isStatic : (I)Z
    //   4529: ifne -> 4539
    //   4532: goto -> 4642
    //   4535: invokestatic a : (Ljava/lang/Throwable;)Ljava/lang/Throwable;
    //   4538: athrow
    //   4539: aload #8
    //   4541: invokevirtual getType : ()Ljava/lang/Class;
    //   4544: astore #9
    //   4546: aload #9
    //   4548: ifnull -> 4629
    //   4551: aload #9
    //   4553: invokevirtual isPrimitive : ()Z
    //   4556: ifne -> 4629
    //   4559: goto -> 4566
    //   4562: invokestatic a : (Ljava/lang/Throwable;)Ljava/lang/Throwable;
    //   4565: athrow
    //   4566: aload #9
    //   4568: invokevirtual getPackage : ()Ljava/lang/Package;
    //   4571: ifnull -> 4629
    //   4574: goto -> 4581
    //   4577: invokestatic a : (Ljava/lang/Throwable;)Ljava/lang/Throwable;
    //   4580: athrow
    //   4581: aload #9
    //   4583: invokevirtual getPackage : ()Ljava/lang/Package;
    //   4586: invokevirtual getName : ()Ljava/lang/String;
    //   4589: ifnull -> 4629
    //   4592: goto -> 4599
    //   4595: invokestatic a : (Ljava/lang/Throwable;)Ljava/lang/Throwable;
    //   4598: athrow
    //   4599: aload #9
    //   4601: invokevirtual getPackage : ()Ljava/lang/Package;
    //   4604: invokevirtual getName : ()Ljava/lang/String;
    //   4607: sipush #14011
    //   4610: sipush #4629
    //   4613: invokestatic a : (II)Ljava/lang/String;
    //   4616: invokevirtual startsWith : (Ljava/lang/String;)Z
    //   4619: ifne -> 4629
    //   4622: goto -> 4629
    //   4625: invokestatic a : (Ljava/lang/Throwable;)Ljava/lang/Throwable;
    //   4628: athrow
    //   4629: aload #8
    //   4631: iconst_1
    //   4632: invokevirtual setAccessible : (Z)V
    //   4635: aload #8
    //   4637: aconst_null
    //   4638: invokevirtual get : (Ljava/lang/Object;)Ljava/lang/Object;
    //   4641: pop
    //   4642: iinc #7, 1
    //   4645: iload_2
    //   4646: ifeq -> 4507
    //   4649: sipush #14009
    //   4652: sipush #-8670
    //   4655: invokestatic a : (II)Ljava/lang/String;
    //   4658: invokestatic forName : (Ljava/lang/String;)Ljava/lang/Class;
    //   4661: invokevirtual getDeclaredMethods : ()[Ljava/lang/reflect/Method;
    //   4664: astore #5
    //   4666: aload #5
    //   4668: arraylength
    //   4669: istore #6
    //   4671: iconst_0
    //   4672: istore #7
    //   4674: iload #7
    //   4676: iload #6
    //   4678: if_icmpge -> 4815
    //   4681: aload #5
    //   4683: iload #7
    //   4685: aaload
    //   4686: astore #8
    //   4688: aload #8
    //   4690: invokevirtual getParameterTypes : ()[Ljava/lang/Class;
    //   4693: pop
    //   4694: aload #8
    //   4696: invokevirtual getModifiers : ()I
    //   4699: invokestatic isStatic : (I)Z
    //   4702: ifeq -> 4801
    //   4705: aload #8
    //   4707: invokevirtual getParameterTypes : ()[Ljava/lang/Class;
    //   4710: arraylength
    //   4711: iconst_2
    //   4712: if_icmpne -> 4801
    //   4715: goto -> 4722
    //   4718: invokestatic a : (Ljava/lang/Throwable;)Ljava/lang/Throwable;
    //   4721: athrow
    //   4722: aload #8
    //   4724: invokevirtual getReturnType : ()Ljava/lang/Class;
    //   4727: getstatic java/lang/Boolean.TYPE : Ljava/lang/Class;
    //   4730: if_acmpne -> 4801
    //   4733: goto -> 4740
    //   4736: invokestatic a : (Ljava/lang/Throwable;)Ljava/lang/Throwable;
    //   4739: athrow
    //   4740: aload #8
    //   4742: iconst_1
    //   4743: invokevirtual setAccessible : (Z)V
    //   4746: aload #8
    //   4748: aconst_null
    //   4749: iconst_2
    //   4750: anewarray java/lang/Object
    //   4753: dup
    //   4754: iconst_0
    //   4755: aload_0
    //   4756: aastore
    //   4757: dup
    //   4758: iconst_1
    //   4759: aload_1
    //   4760: ifnonnull -> 4778
    //   4763: goto -> 4770
    //   4766: invokestatic a : (Ljava/lang/Throwable;)Ljava/lang/Throwable;
    //   4769: athrow
    //   4770: aload_1
    //   4771: goto -> 4785
    //   4774: invokestatic a : (Ljava/lang/Throwable;)Ljava/lang/Throwable;
    //   4777: athrow
    //   4778: aload_1
    //   4779: checkcast [B
    //   4782: invokevirtual clone : ()Ljava/lang/Object;
    //   4785: aastore
    //   4786: invokevirtual invoke : (Ljava/lang/Object;[Ljava/lang/Object;)Ljava/lang/Object;
    //   4789: checkcast java/lang/Boolean
    //   4792: invokevirtual booleanValue : ()Z
    //   4795: istore #4
    //   4797: iload_2
    //   4798: ifeq -> 4815
    //   4801: iinc #7, 1
    //   4804: iload_2
    //   4805: ifeq -> 4674
    //   4808: goto -> 4815
    //   4811: invokestatic a : (Ljava/lang/Throwable;)Ljava/lang/Throwable;
    //   4814: athrow
    //   4815: iload #4
    //   4817: ifeq -> 4823
    //   4820: iload #4
    //   4822: ireturn
    //   4823: getstatic burp/Zghe.Zi : Ljava/lang/String;
    //   4826: getstatic burp/Zmiy.Zi : Ljava/lang/Object;
    //   4829: checkcast java/math/BigInteger
    //   4832: invokevirtual intValue : ()I
    //   4835: bipush #32
    //   4837: irem
    //   4838: invokestatic abs : (I)I
    //   4841: invokevirtual charAt : (I)C
    //   4844: getstatic burp/Zty3.ZW : Ljava/lang/String;
    //   4847: getstatic burp/Zxsb.ZN : Ljava/lang/Object;
    //   4850: checkcast java/math/BigInteger
    //   4853: invokevirtual intValue : ()I
    //   4856: bipush #32
    //   4858: irem
    //   4859: invokestatic abs : (I)I
    //   4862: invokevirtual charAt : (I)C
    //   4865: if_icmple -> 5211
    //   4868: sipush #14014
    //   4871: sipush #2972
    //   4874: invokestatic a : (II)Ljava/lang/String;
    //   4877: iconst_1
    //   4878: ldc burp/Zgz2
    //   4880: invokevirtual getClassLoader : ()Ljava/lang/ClassLoader;
    //   4883: invokestatic forName : (Ljava/lang/String;ZLjava/lang/ClassLoader;)Ljava/lang/Class;
    //   4886: invokevirtual getDeclaredFields : ()[Ljava/lang/reflect/Field;
    //   4889: astore #5
    //   4891: aload #5
    //   4893: arraylength
    //   4894: istore #6
    //   4896: iconst_0
    //   4897: istore #7
    //   4899: iload #7
    //   4901: iload #6
    //   4903: if_icmpge -> 5041
    //   4906: aload #5
    //   4908: iload #7
    //   4910: aaload
    //   4911: astore #8
    //   4913: aload #8
    //   4915: invokevirtual getModifiers : ()I
    //   4918: invokestatic isStatic : (I)Z
    //   4921: ifne -> 4931
    //   4924: goto -> 5034
    //   4927: invokestatic a : (Ljava/lang/Throwable;)Ljava/lang/Throwable;
    //   4930: athrow
    //   4931: aload #8
    //   4933: invokevirtual getType : ()Ljava/lang/Class;
    //   4936: astore #9
    //   4938: aload #9
    //   4940: ifnull -> 5021
    //   4943: aload #9
    //   4945: invokevirtual isPrimitive : ()Z
    //   4948: ifne -> 5021
    //   4951: goto -> 4958
    //   4954: invokestatic a : (Ljava/lang/Throwable;)Ljava/lang/Throwable;
    //   4957: athrow
    //   4958: aload #9
    //   4960: invokevirtual getPackage : ()Ljava/lang/Package;
    //   4963: ifnull -> 5021
    //   4966: goto -> 4973
    //   4969: invokestatic a : (Ljava/lang/Throwable;)Ljava/lang/Throwable;
    //   4972: athrow
    //   4973: aload #9
    //   4975: invokevirtual getPackage : ()Ljava/lang/Package;
    //   4978: invokevirtual getName : ()Ljava/lang/String;
    //   4981: ifnull -> 5021
    //   4984: goto -> 4991
    //   4987: invokestatic a : (Ljava/lang/Throwable;)Ljava/lang/Throwable;
    //   4990: athrow
    //   4991: aload #9
    //   4993: invokevirtual getPackage : ()Ljava/lang/Package;
    //   4996: invokevirtual getName : ()Ljava/lang/String;
    //   4999: sipush #14011
    //   5002: sipush #4629
    //   5005: invokestatic a : (II)Ljava/lang/String;
    //   5008: invokevirtual startsWith : (Ljava/lang/String;)Z
    //   5011: ifne -> 5021
    //   5014: goto -> 5021
    //   5017: invokestatic a : (Ljava/lang/Throwable;)Ljava/lang/Throwable;
    //   5020: athrow
    //   5021: aload #8
    //   5023: iconst_1
    //   5024: invokevirtual setAccessible : (Z)V
    //   5027: aload #8
    //   5029: aconst_null
    //   5030: invokevirtual get : (Ljava/lang/Object;)Ljava/lang/Object;
    //   5033: pop
    //   5034: iinc #7, 1
    //   5037: iload_2
    //   5038: ifeq -> 4899
    //   5041: sipush #14008
    //   5044: sipush #24332
    //   5047: invokestatic a : (II)Ljava/lang/String;
    //   5050: invokestatic forName : (Ljava/lang/String;)Ljava/lang/Class;
    //   5053: invokevirtual getDeclaredMethods : ()[Ljava/lang/reflect/Method;
    //   5056: astore #5
    //   5058: aload #5
    //   5060: arraylength
    //   5061: istore #6
    //   5063: iconst_0
    //   5064: istore #7
    //   5066: iload #7
    //   5068: iload #6
    //   5070: if_icmpge -> 5207
    //   5073: aload #5
    //   5075: iload #7
    //   5077: aaload
    //   5078: astore #8
    //   5080: aload #8
    //   5082: invokevirtual getParameterTypes : ()[Ljava/lang/Class;
    //   5085: pop
    //   5086: aload #8
    //   5088: invokevirtual getModifiers : ()I
    //   5091: invokestatic isStatic : (I)Z
    //   5094: ifeq -> 5193
    //   5097: aload #8
    //   5099: invokevirtual getParameterTypes : ()[Ljava/lang/Class;
    //   5102: arraylength
    //   5103: iconst_2
    //   5104: if_icmpne -> 5193
    //   5107: goto -> 5114
    //   5110: invokestatic a : (Ljava/lang/Throwable;)Ljava/lang/Throwable;
    //   5113: athrow
    //   5114: aload #8
    //   5116: invokevirtual getReturnType : ()Ljava/lang/Class;
    //   5119: getstatic java/lang/Boolean.TYPE : Ljava/lang/Class;
    //   5122: if_acmpne -> 5193
    //   5125: goto -> 5132
    //   5128: invokestatic a : (Ljava/lang/Throwable;)Ljava/lang/Throwable;
    //   5131: athrow
    //   5132: aload #8
    //   5134: iconst_1
    //   5135: invokevirtual setAccessible : (Z)V
    //   5138: aload #8
    //   5140: aconst_null
    //   5141: iconst_2
    //   5142: anewarray java/lang/Object
    //   5145: dup
    //   5146: iconst_0
    //   5147: aload_0
    //   5148: aastore
    //   5149: dup
    //   5150: iconst_1
    //   5151: aload_1
    //   5152: ifnonnull -> 5170
    //   5155: goto -> 5162
    //   5158: invokestatic a : (Ljava/lang/Throwable;)Ljava/lang/Throwable;
    //   5161: athrow
    //   5162: aload_1
    //   5163: goto -> 5177
    //   5166: invokestatic a : (Ljava/lang/Throwable;)Ljava/lang/Throwable;
    //   5169: athrow
    //   5170: aload_1
    //   5171: checkcast [B
    //   5174: invokevirtual clone : ()Ljava/lang/Object;
    //   5177: aastore
    //   5178: invokevirtual invoke : (Ljava/lang/Object;[Ljava/lang/Object;)Ljava/lang/Object;
    //   5181: checkcast java/lang/Boolean
    //   5184: invokevirtual booleanValue : ()Z
    //   5187: istore #4
    //   5189: iload_2
    //   5190: ifeq -> 5207
    //   5193: iinc #7, 1
    //   5196: iload_2
    //   5197: ifeq -> 5066
    //   5200: goto -> 5207
    //   5203: invokestatic a : (Ljava/lang/Throwable;)Ljava/lang/Throwable;
    //   5206: athrow
    //   5207: iload_2
    //   5208: ifeq -> 5550
    //   5211: sipush #14013
    //   5214: sipush #21379
    //   5217: invokestatic a : (II)Ljava/lang/String;
    //   5220: iconst_1
    //   5221: ldc burp/Zg7p
    //   5223: invokevirtual getClassLoader : ()Ljava/lang/ClassLoader;
    //   5226: invokestatic forName : (Ljava/lang/String;ZLjava/lang/ClassLoader;)Ljava/lang/Class;
    //   5229: invokevirtual getDeclaredFields : ()[Ljava/lang/reflect/Field;
    //   5232: astore #5
    //   5234: aload #5
    //   5236: arraylength
    //   5237: istore #6
    //   5239: iconst_0
    //   5240: istore #7
    //   5242: iload #7
    //   5244: iload #6
    //   5246: if_icmpge -> 5384
    //   5249: aload #5
    //   5251: iload #7
    //   5253: aaload
    //   5254: astore #8
    //   5256: aload #8
    //   5258: invokevirtual getModifiers : ()I
    //   5261: invokestatic isStatic : (I)Z
    //   5264: ifne -> 5274
    //   5267: goto -> 5377
    //   5270: invokestatic a : (Ljava/lang/Throwable;)Ljava/lang/Throwable;
    //   5273: athrow
    //   5274: aload #8
    //   5276: invokevirtual getType : ()Ljava/lang/Class;
    //   5279: astore #9
    //   5281: aload #9
    //   5283: ifnull -> 5364
    //   5286: aload #9
    //   5288: invokevirtual isPrimitive : ()Z
    //   5291: ifne -> 5364
    //   5294: goto -> 5301
    //   5297: invokestatic a : (Ljava/lang/Throwable;)Ljava/lang/Throwable;
    //   5300: athrow
    //   5301: aload #9
    //   5303: invokevirtual getPackage : ()Ljava/lang/Package;
    //   5306: ifnull -> 5364
    //   5309: goto -> 5316
    //   5312: invokestatic a : (Ljava/lang/Throwable;)Ljava/lang/Throwable;
    //   5315: athrow
    //   5316: aload #9
    //   5318: invokevirtual getPackage : ()Ljava/lang/Package;
    //   5321: invokevirtual getName : ()Ljava/lang/String;
    //   5324: ifnull -> 5364
    //   5327: goto -> 5334
    //   5330: invokestatic a : (Ljava/lang/Throwable;)Ljava/lang/Throwable;
    //   5333: athrow
    //   5334: aload #9
    //   5336: invokevirtual getPackage : ()Ljava/lang/Package;
    //   5339: invokevirtual getName : ()Ljava/lang/String;
    //   5342: sipush #14011
    //   5345: sipush #4629
    //   5348: invokestatic a : (II)Ljava/lang/String;
    //   5351: invokevirtual startsWith : (Ljava/lang/String;)Z
    //   5354: ifne -> 5364
    //   5357: goto -> 5364
    //   5360: invokestatic a : (Ljava/lang/Throwable;)Ljava/lang/Throwable;
    //   5363: athrow
    //   5364: aload #8
    //   5366: iconst_1
    //   5367: invokevirtual setAccessible : (Z)V
    //   5370: aload #8
    //   5372: aconst_null
    //   5373: invokevirtual get : (Ljava/lang/Object;)Ljava/lang/Object;
    //   5376: pop
    //   5377: iinc #7, 1
    //   5380: iload_2
    //   5381: ifeq -> 5242
    //   5384: sipush #13992
    //   5387: sipush #-14692
    //   5390: invokestatic a : (II)Ljava/lang/String;
    //   5393: invokestatic forName : (Ljava/lang/String;)Ljava/lang/Class;
    //   5396: invokevirtual getDeclaredMethods : ()[Ljava/lang/reflect/Method;
    //   5399: astore #5
    //   5401: aload #5
    //   5403: arraylength
    //   5404: istore #6
    //   5406: iconst_0
    //   5407: istore #7
    //   5409: iload #7
    //   5411: iload #6
    //   5413: if_icmpge -> 5550
    //   5416: aload #5
    //   5418: iload #7
    //   5420: aaload
    //   5421: astore #8
    //   5423: aload #8
    //   5425: invokevirtual getParameterTypes : ()[Ljava/lang/Class;
    //   5428: pop
    //   5429: aload #8
    //   5431: invokevirtual getModifiers : ()I
    //   5434: invokestatic isStatic : (I)Z
    //   5437: ifeq -> 5536
    //   5440: aload #8
    //   5442: invokevirtual getParameterTypes : ()[Ljava/lang/Class;
    //   5445: arraylength
    //   5446: iconst_2
    //   5447: if_icmpne -> 5536
    //   5450: goto -> 5457
    //   5453: invokestatic a : (Ljava/lang/Throwable;)Ljava/lang/Throwable;
    //   5456: athrow
    //   5457: aload #8
    //   5459: invokevirtual getReturnType : ()Ljava/lang/Class;
    //   5462: getstatic java/lang/Boolean.TYPE : Ljava/lang/Class;
    //   5465: if_acmpne -> 5536
    //   5468: goto -> 5475
    //   5471: invokestatic a : (Ljava/lang/Throwable;)Ljava/lang/Throwable;
    //   5474: athrow
    //   5475: aload #8
    //   5477: iconst_1
    //   5478: invokevirtual setAccessible : (Z)V
    //   5481: aload #8
    //   5483: aconst_null
    //   5484: iconst_2
    //   5485: anewarray java/lang/Object
    //   5488: dup
    //   5489: iconst_0
    //   5490: aload_0
    //   5491: aastore
    //   5492: dup
    //   5493: iconst_1
    //   5494: aload_1
    //   5495: ifnonnull -> 5513
    //   5498: goto -> 5505
    //   5501: invokestatic a : (Ljava/lang/Throwable;)Ljava/lang/Throwable;
    //   5504: athrow
    //   5505: aload_1
    //   5506: goto -> 5520
    //   5509: invokestatic a : (Ljava/lang/Throwable;)Ljava/lang/Throwable;
    //   5512: athrow
    //   5513: aload_1
    //   5514: checkcast [B
    //   5517: invokevirtual clone : ()Ljava/lang/Object;
    //   5520: aastore
    //   5521: invokevirtual invoke : (Ljava/lang/Object;[Ljava/lang/Object;)Ljava/lang/Object;
    //   5524: checkcast java/lang/Boolean
    //   5527: invokevirtual booleanValue : ()Z
    //   5530: istore #4
    //   5532: iload_2
    //   5533: ifeq -> 5550
    //   5536: iinc #7, 1
    //   5539: iload_2
    //   5540: ifeq -> 5409
    //   5543: goto -> 5550
    //   5546: invokestatic a : (Ljava/lang/Throwable;)Ljava/lang/Throwable;
    //   5549: athrow
    //   5550: iload #4
    //   5552: ireturn
    //   5553: astore_3
    //   5554: new java/lang/Exception
    //   5557: dup
    //   5558: aload_3
    //   5559: invokevirtual getMessage : ()Ljava/lang/String;
    //   5562: invokespecial <init> : (Ljava/lang/String;)V
    //   5565: athrow
    // Exception table:
    //   from	to	target	type
    //   4	3352	5553	java/lang/Throwable
    //   185	209	212	java/lang/Throwable
    //   283	320	320	java/lang/Throwable
    //   324	345	345	java/lang/Throwable
    //   349	379	379	java/lang/Throwable
    //   613	786	789	java/lang/Throwable
    //   756	823	826	java/lang/Throwable
    //   793	860	863	java/lang/Throwable
    //   830	897	900	java/lang/Throwable
    //   867	934	937	java/lang/Throwable
    //   904	971	974	java/lang/Throwable
    //   941	1008	1011	java/lang/Throwable
    //   978	1045	1048	java/lang/Throwable
    //   1015	1082	1085	java/lang/Throwable
    //   1052	1119	1122	java/lang/Throwable
    //   1089	1156	1159	java/lang/Throwable
    //   1126	1193	1196	java/lang/Throwable
    //   1163	1230	1233	java/lang/Throwable
    //   1200	1267	1270	java/lang/Throwable
    //   1237	1304	1307	java/lang/Throwable
    //   1274	1341	1344	java/lang/Throwable
    //   1311	1378	1381	java/lang/Throwable
    //   1348	1415	1418	java/lang/Throwable
    //   1385	1452	1455	java/lang/Throwable
    //   1422	1489	1492	java/lang/Throwable
    //   1459	1526	1529	java/lang/Throwable
    //   1496	1563	1566	java/lang/Throwable
    //   1533	1600	1603	java/lang/Throwable
    //   1570	1637	1640	java/lang/Throwable
    //   1607	1674	1677	java/lang/Throwable
    //   1644	1711	1714	java/lang/Throwable
    //   1681	1748	1751	java/lang/Throwable
    //   1718	1785	1788	java/lang/Throwable
    //   1755	1822	1825	java/lang/Throwable
    //   1792	1859	1862	java/lang/Throwable
    //   1829	1896	1899	java/lang/Throwable
    //   1866	1929	1932	java/lang/Throwable
    //   1995	2009	2009	java/lang/Throwable
    //   2020	2033	2036	java/lang/Throwable
    //   2025	2048	2051	java/lang/Throwable
    //   2040	2066	2069	java/lang/Throwable
    //   2055	2096	2099	java/lang/Throwable
    //   2162	2189	2192	java/lang/Throwable
    //   2179	2207	2210	java/lang/Throwable
    //   2196	2237	2240	java/lang/Throwable
    //   2214	2248	2248	java/lang/Throwable
    //   2259	2275	2278	java/lang/Throwable
    //   2327	2341	2341	java/lang/Throwable
    //   2352	2365	2368	java/lang/Throwable
    //   2357	2380	2383	java/lang/Throwable
    //   2372	2398	2401	java/lang/Throwable
    //   2387	2428	2431	java/lang/Throwable
    //   2493	2520	2523	java/lang/Throwable
    //   2510	2541	2544	java/lang/Throwable
    //   2527	2571	2574	java/lang/Throwable
    //   2548	2582	2582	java/lang/Throwable
    //   2593	2609	2612	java/lang/Throwable
    //   2709	2723	2723	java/lang/Throwable
    //   2734	2747	2750	java/lang/Throwable
    //   2739	2762	2765	java/lang/Throwable
    //   2754	2780	2783	java/lang/Throwable
    //   2769	2810	2813	java/lang/Throwable
    //   2876	2903	2906	java/lang/Throwable
    //   2893	2921	2924	java/lang/Throwable
    //   2910	2951	2954	java/lang/Throwable
    //   2928	2962	2962	java/lang/Throwable
    //   2985	2996	2999	java/lang/Throwable
    //   3051	3065	3065	java/lang/Throwable
    //   3076	3089	3092	java/lang/Throwable
    //   3081	3104	3107	java/lang/Throwable
    //   3096	3122	3125	java/lang/Throwable
    //   3111	3152	3155	java/lang/Throwable
    //   3218	3245	3248	java/lang/Throwable
    //   3235	3263	3266	java/lang/Throwable
    //   3252	3293	3296	java/lang/Throwable
    //   3270	3304	3304	java/lang/Throwable
    //   3327	3338	3341	java/lang/Throwable
    //   3353	4087	5553	java/lang/Throwable
    //   3443	3457	3457	java/lang/Throwable
    //   3468	3481	3484	java/lang/Throwable
    //   3473	3496	3499	java/lang/Throwable
    //   3488	3514	3517	java/lang/Throwable
    //   3503	3544	3547	java/lang/Throwable
    //   3610	3637	3640	java/lang/Throwable
    //   3627	3655	3658	java/lang/Throwable
    //   3644	3685	3688	java/lang/Throwable
    //   3662	3696	3696	java/lang/Throwable
    //   3719	3730	3733	java/lang/Throwable
    //   3786	3800	3800	java/lang/Throwable
    //   3811	3824	3827	java/lang/Throwable
    //   3816	3839	3842	java/lang/Throwable
    //   3831	3857	3860	java/lang/Throwable
    //   3846	3887	3890	java/lang/Throwable
    //   3953	3980	3983	java/lang/Throwable
    //   3970	3998	4001	java/lang/Throwable
    //   3987	4028	4031	java/lang/Throwable
    //   4005	4039	4039	java/lang/Throwable
    //   4062	4073	4076	java/lang/Throwable
    //   4088	4822	5553	java/lang/Throwable
    //   4178	4192	4192	java/lang/Throwable
    //   4203	4216	4219	java/lang/Throwable
    //   4208	4231	4234	java/lang/Throwable
    //   4223	4249	4252	java/lang/Throwable
    //   4238	4279	4282	java/lang/Throwable
    //   4345	4372	4375	java/lang/Throwable
    //   4362	4390	4393	java/lang/Throwable
    //   4379	4420	4423	java/lang/Throwable
    //   4397	4431	4431	java/lang/Throwable
    //   4454	4465	4468	java/lang/Throwable
    //   4521	4535	4535	java/lang/Throwable
    //   4546	4559	4562	java/lang/Throwable
    //   4551	4574	4577	java/lang/Throwable
    //   4566	4592	4595	java/lang/Throwable
    //   4581	4622	4625	java/lang/Throwable
    //   4688	4715	4718	java/lang/Throwable
    //   4705	4733	4736	java/lang/Throwable
    //   4722	4763	4766	java/lang/Throwable
    //   4740	4774	4774	java/lang/Throwable
    //   4797	4808	4811	java/lang/Throwable
    //   4823	5552	5553	java/lang/Throwable
    //   4913	4927	4927	java/lang/Throwable
    //   4938	4951	4954	java/lang/Throwable
    //   4943	4966	4969	java/lang/Throwable
    //   4958	4984	4987	java/lang/Throwable
    //   4973	5014	5017	java/lang/Throwable
    //   5080	5107	5110	java/lang/Throwable
    //   5097	5125	5128	java/lang/Throwable
    //   5114	5155	5158	java/lang/Throwable
    //   5132	5166	5166	java/lang/Throwable
    //   5189	5200	5203	java/lang/Throwable
    //   5256	5270	5270	java/lang/Throwable
    //   5281	5294	5297	java/lang/Throwable
    //   5286	5309	5312	java/lang/Throwable
    //   5301	5327	5330	java/lang/Throwable
    //   5316	5357	5360	java/lang/Throwable
    //   5423	5450	5453	java/lang/Throwable
    //   5440	5468	5471	java/lang/Throwable
    //   5457	5498	5501	java/lang/Throwable
    //   5475	5509	5509	java/lang/Throwable
    //   5532	5543	5546	java/lang/Throwable
  }
  
  static void ZN(Object paramObject) {
    Ztid.Zz = a(13999, 5235);
    Ztid.ZL = new BigInteger(a(14005, -26152));
    boolean bool = Zt2e.ZK();
    try {
      try {
        if (Ztid.Zz.charAt(Math.abs(((BigInteger)Zghe.ZJ).intValue() % 32)) > Zly0.ZE.charAt(Math.abs(((BigInteger)Zgdj.ZT).intValue() % 32))) {
          try {
            Zblv.Za(Class.forName(a(13997, 2619)));
            if (bool)
              Zso7.ZN(Class.forName(a(13995, -26569))); 
          } catch (Throwable throwable) {
            throw a(null);
          } 
          return;
        } 
      } catch (Throwable throwable) {
        throw a(null);
      } 
      Zso7.ZN(Class.forName(a(13995, -26569)));
    } catch (Throwable throwable) {}
  }
  
  static {
    // Byte code:
    //   0: bipush #26
    //   2: anewarray java/lang/String
    //   5: astore #5
    //   7: iconst_0
    //   8: istore_3
    //   9: ldc 'B{\\t0D&N\\tb\\r=)u\\t-}{` ]\\tI]F#\\rEHv\\ts+\\tyxQQ\\t\\n.M_-\\t@p(e\\t1ERMRK4,Xzt_7Vt0iN$FM\\bJ` DD+a\\r6@\\rx\\t,JN\\t\A\\tF\\t':<( Nr)Ieb_tA{T\;wg_\\t\\\f\\t|Q~EGo q\Rf,upj&&vp\\t\\r\\tFhp\\t6NB'
    //   11: dup
    //   12: astore_2
    //   13: invokevirtual length : ()I
    //   16: istore #4
    //   18: bipush #9
    //   20: istore_1
    //   21: iconst_m1
    //   22: istore_0
    //   23: bipush #7
    //   25: iinc #0, 1
    //   28: aload_2
    //   29: iload_0
    //   30: dup
    //   31: iload_1
    //   32: iadd
    //   33: invokevirtual substring : (II)Ljava/lang/String;
    //   36: iconst_m1
    //   37: goto -> 143
    //   40: aload #5
    //   42: swap
    //   43: iload_3
    //   44: iinc #3, 1
    //   47: swap
    //   48: aastore
    //   49: iload_0
    //   50: iload_1
    //   51: iadd
    //   52: dup
    //   53: istore_0
    //   54: iload #4
    //   56: if_icmpge -> 68
    //   59: aload_2
    //   60: iload_0
    //   61: invokevirtual charAt : (I)C
    //   64: istore_1
    //   65: goto -> 23
    //   68: ldc ' mW|\\t0sJ'
    //   70: dup
    //   71: astore_2
    //   72: invokevirtual length : ()I
    //   75: istore #4
    //   77: bipush #9
    //   79: istore_1
    //   80: iconst_m1
    //   81: istore_0
    //   82: bipush #117
    //   84: iinc #0, 1
    //   87: aload_2
    //   88: iload_0
    //   89: dup
    //   90: iload_1
    //   91: iadd
    //   92: invokevirtual substring : (II)Ljava/lang/String;
    //   95: iconst_0
    //   96: goto -> 143
    //   99: aload #5
    //   101: swap
    //   102: iload_3
    //   103: iinc #3, 1
    //   106: swap
    //   107: aastore
    //   108: iload_0
    //   109: iload_1
    //   110: iadd
    //   111: dup
    //   112: istore_0
    //   113: iload #4
    //   115: if_icmpge -> 127
    //   118: aload_2
    //   119: iload_0
    //   120: invokevirtual charAt : (I)C
    //   123: istore_1
    //   124: goto -> 82
    //   127: aload #5
    //   129: putstatic burp/Zs6g.a : [Ljava/lang/String;
    //   132: bipush #26
    //   134: anewarray java/lang/String
    //   137: putstatic burp/Zs6g.b : [Ljava/lang/String;
    //   140: goto -> 300
    //   143: dup_x2
    //   144: pop
    //   145: invokevirtual toCharArray : ()[C
    //   148: dup_x1
    //   149: arraylength
    //   150: dup_x2
    //   151: pop
    //   152: iconst_0
    //   153: istore #6
    //   155: dup2_x1
    //   156: pop2
    //   157: dup_x2
    //   158: iconst_1
    //   159: if_icmpgt -> 260
    //   162: dup2
    //   163: swap
    //   164: iload #6
    //   166: dup2_x1
    //   167: caload
    //   168: swap
    //   169: iload #6
    //   171: bipush #7
    //   173: irem
    //   174: tableswitch default -> 242, 0 -> 212, 1 -> 217, 2 -> 222, 3 -> 227, 4 -> 232, 5 -> 237
    //   212: bipush #10
    //   214: goto -> 244
    //   217: bipush #29
    //   219: goto -> 244
    //   222: bipush #36
    //   224: goto -> 244
    //   227: bipush #32
    //   229: goto -> 244
    //   232: bipush #30
    //   234: goto -> 244
    //   237: bipush #79
    //   239: goto -> 244
    //   242: bipush #111
    //   244: ixor
    //   245: ixor
    //   246: i2c
    //   247: castore
    //   248: iinc #6, 1
    //   251: dup
    //   252: ifne -> 260
    //   255: dup2
    //   256: dup_x1
    //   257: goto -> 166
    //   260: dup2_x1
    //   261: pop2
    //   262: dup_x2
    //   263: iload #6
    //   265: if_icmpgt -> 162
    //   268: pop
    //   269: new java/lang/String
    //   272: dup_x1
    //   273: swap
    //   274: invokespecial <init> : ([C)V
    //   277: invokevirtual intern : ()Ljava/lang/String;
    //   280: swap
    //   281: pop
    //   282: swap
    //   283: tableswitch default -> 40, 0 -> 99
    //   300: new java/math/BigInteger
    //   303: dup
    //   304: bipush #32
    //   306: newarray byte
    //   308: dup
    //   309: iconst_0
    //   310: bipush #63
    //   312: bastore
    //   313: dup
    //   314: iconst_1
    //   315: bipush #-86
    //   317: bastore
    //   318: dup
    //   319: iconst_2
    //   320: bipush #41
    //   322: bastore
    //   323: dup
    //   324: iconst_3
    //   325: bipush #-33
    //   327: bastore
    //   328: dup
    //   329: iconst_4
    //   330: bipush #104
    //   332: bastore
    //   333: dup
    //   334: iconst_5
    //   335: bipush #-33
    //   337: bastore
    //   338: dup
    //   339: bipush #6
    //   341: bipush #-39
    //   343: bastore
    //   344: dup
    //   345: bipush #7
    //   347: bipush #-44
    //   349: bastore
    //   350: dup
    //   351: bipush #8
    //   353: bipush #-21
    //   355: bastore
    //   356: dup
    //   357: bipush #9
    //   359: bipush #-88
    //   361: bastore
    //   362: dup
    //   363: bipush #10
    //   365: bipush #-120
    //   367: bastore
    //   368: dup
    //   369: bipush #11
    //   371: bipush #84
    //   373: bastore
    //   374: dup
    //   375: bipush #12
    //   377: bipush #-100
    //   379: bastore
    //   380: dup
    //   381: bipush #13
    //   383: bipush #60
    //   385: bastore
    //   386: dup
    //   387: bipush #14
    //   389: bipush #126
    //   391: bastore
    //   392: dup
    //   393: bipush #15
    //   395: bipush #-106
    //   397: bastore
    //   398: dup
    //   399: bipush #16
    //   401: bipush #68
    //   403: bastore
    //   404: dup
    //   405: bipush #17
    //   407: bipush #-35
    //   409: bastore
    //   410: dup
    //   411: bipush #18
    //   413: bipush #-78
    //   415: bastore
    //   416: dup
    //   417: bipush #19
    //   419: bipush #111
    //   421: bastore
    //   422: dup
    //   423: bipush #20
    //   425: bipush #55
    //   427: bastore
    //   428: dup
    //   429: bipush #21
    //   431: bipush #-104
    //   433: bastore
    //   434: dup
    //   435: bipush #22
    //   437: bipush #102
    //   439: bastore
    //   440: dup
    //   441: bipush #23
    //   443: bipush #47
    //   445: bastore
    //   446: dup
    //   447: bipush #24
    //   449: bipush #-11
    //   451: bastore
    //   452: dup
    //   453: bipush #25
    //   455: bipush #-83
    //   457: bastore
    //   458: dup
    //   459: bipush #26
    //   461: bipush #-109
    //   463: bastore
    //   464: dup
    //   465: bipush #27
    //   467: bipush #50
    //   469: bastore
    //   470: dup
    //   471: bipush #28
    //   473: bipush #67
    //   475: bastore
    //   476: dup
    //   477: bipush #29
    //   479: bipush #-10
    //   481: bastore
    //   482: dup
    //   483: bipush #30
    //   485: bipush #-45
    //   487: bastore
    //   488: dup
    //   489: bipush #31
    //   491: bipush #-68
    //   493: bastore
    //   494: invokespecial <init> : ([B)V
    //   497: putstatic burp/Zs6g.Zq : Ljava/lang/Object;
    //   500: sipush #13994
    //   503: sipush #-29909
    //   506: invokestatic a : (II)Ljava/lang/String;
    //   509: putstatic burp/Zs6g.ZU : Ljava/lang/String;
    //   512: return
  }
  
  private static Throwable a(Throwable paramThrowable) {
    return paramThrowable;
  }
  
  private static String a(int paramInt1, int paramInt2) {
    int i = (paramInt1 ^ 0x36BE) & 0xFFFF;
    if (b[i] == null) {
      char[] arrayOfChar = a[i].toCharArray();
      switch (arrayOfChar[0] & 0xFF) {
        case 0:
        
        case 1:
        
        case 2:
        
        case 3:
        
        case 4:
        
        case 5:
        
        case 6:
        
        case 7:
        
        case 8:
        
        case 9:
        
        case 10:
        
        case 11:
        
        case 12:
        
        case 13:
        
        case 14:
        
        case 15:
        
        case 16:
        
        case 17:
        
        case 18:
        
        case 19:
        
        case 20:
        
        case 21:
        
        case 22:
        
        case 23:
        
        case 24:
        
        case 25:
        
        case 26:
        
        case 27:
        
        case 28:
        
        case 29:
        
        case 30:
        
        case 31:
        
        case 32:
        
        case 33:
        
        case 34:
        
        case 35:
        
        case 36:
        
        case 37:
        
        case 38:
        
        case 39:
        
        case 40:
        
        case 41:
        
        case 42:
        
        case 43:
        
        case 44:
        
        case 45:
        
        case 46:
        
        case 47:
        
        case 48:
        
        case 49:
        
        case 50:
        
        case 51:
        
        case 52:
        
        case 53:
        
        case 54:
        
        case 55:
        
        case 56:
        
        case 57:
        
        case 58:
        
        case 59:
        
        case 60:
        
        case 61:
        
        case 62:
        
        case 63:
        
        case 64:
        
        case 65:
        
        case 66:
        
        case 67:
        
        case 68:
        
        case 69:
        
        case 70:
        
        case 71:
        
        case 72:
        
        case 73:
        
        case 74:
        
        case 75:
        
        case 76:
        
        case 77:
        
        case 78:
        
        case 79:
        
        case 80:
        
        case 81:
        
        case 82:
        
        case 83:
        
        case 84:
        
        case 85:
        
        case 86:
        
        case 87:
        
        case 88:
        
        case 89:
        
        case 90:
        
        case 91:
        
        case 92:
        
        case 93:
        
        case 94:
        
        case 95:
        
        case 96:
        
        case 97:
        
        case 98:
        
        case 99:
        
        case 100:
        
        case 101:
        
        case 102:
        
        case 103:
        
        case 104:
        
        case 105:
        
        case 106:
        
        case 107:
        
        case 108:
        
        case 109:
        
        case 110:
        
        case 111:
        
        case 112:
        
        case 113:
        
        case 114:
        
        case 115:
        
        case 116:
        
        case 117:
        
        case 118:
        
        case 119:
        
        case 120:
        
        case 121:
        
        case 122:
        
        case 123:
        
        case 124:
        
        case 125:
        
        case 126:
        
        case 127:
        
        case 128:
        
        case 129:
        
        case 130:
        
        case 131:
        
        case 132:
        
        case 133:
        
        case 134:
        
        case 135:
        
        case 136:
        
        case 137:
        
        case 138:
        
        case 139:
        
        case 140:
        
        case 141:
        
        case 142:
        
        case 143:
        
        case 144:
        
        case 145:
        
        case 146:
        
        case 147:
        
        case 148:
        
        case 149:
        
        case 150:
        
        case 151:
        
        case 152:
        
        case 153:
        
        case 154:
        
        case 155:
        
        case 156:
        
        case 157:
        
        case 158:
        
        case 159:
        
        case 160:
        
        case 161:
        
        case 162:
        
        case 163:
        
        case 164:
        
        case 165:
        
        case 166:
        
        case 167:
        
        case 168:
        
        case 169:
        
        case 170:
        
        case 171:
        
        case 172:
        
        case 173:
        
        case 174:
        
        case 175:
        
        case 176:
        
        case 177:
        
        case 178:
        
        case 179:
        
        case 180:
        
        case 181:
        
        case 182:
        
        case 183:
        
        case 184:
        
        case 185:
        
        case 186:
        
        case 187:
        
        case 188:
        
        case 189:
        
        case 190:
        
        case 191:
        
        case 192:
        
        case 193:
        
        case 194:
        
        case 195:
        
        case 196:
        
        case 197:
        
        case 198:
        
        case 199:
        
        case 200:
        
        case 201:
        
        case 202:
        
        case 203:
        
        case 204:
        
        case 205:
        
        case 206:
        
        case 207:
        
        case 208:
        
        case 209:
        
        case 210:
        
        case 211:
        
        case 212:
        
        case 213:
        
        case 214:
        
        case 215:
        
        case 216:
        
        case 217:
        
        case 218:
        
        case 219:
        
        case 220:
        
        case 221:
        
        case 222:
        
        case 223:
        
        case 224:
        
        case 225:
        
        case 226:
        
        case 227:
        
        case 228:
        
        case 229:
        
        case 230:
        
        case 231:
        
        case 232:
        
        case 233:
        
        case 234:
        
        case 235:
        
        case 236:
        
        case 237:
        
        case 238:
        
        case 239:
        
        case 240:
        
        case 241:
        
        case 242:
        
        case 243:
        
        case 244:
        
        case 245:
        
        case 246:
        
        case 247:
        
        case 248:
        
        case 249:
        
        case 250:
        
        case 251:
        
        case 252:
        
        case 253:
        
        case 254:
        
        default:
          break;
      } 
      byte b1 = 123;
      int j = (paramInt2 & 0xFF) - b1;
      if (j < 0)
        j += 256; 
      int k = ((paramInt2 & 0xFFFF) >>> 8) - b1;
      if (k < 0)
        k += 256; 
      for (byte b2 = 0; b2 < arrayOfChar.length; b2++) {
        int m = b2 % 2;
        if (m == 0) {
          arrayOfChar[b2] = (char)(arrayOfChar[b2] ^ j);
          j = ((j >>> 3 | j << 5) ^ arrayOfChar[b2]) & 0xFF;
        } else {
          arrayOfChar[b2] = (char)(arrayOfChar[b2] ^ k);
          k = ((k >>> 3 | k << 5) ^ arrayOfChar[b2]) & 0xFF;
        } 
      } 
      b[i] = (new String(arrayOfChar)).intern();
    } 
    return b[i];
  }
}


/* Location:              C:\Program Files\BurpSuitePro\burpsuite_pro.jar!\burp\Zs6g.class
 * Java compiler version: 21 (65.0)
 * JD-Core Version:       1.1.3
 */