package burp;

import java.math.BigInteger;

class Zs75 extends ClassLoader {
  static String Zn;
  
  static Object Zo;
  
  private static final String[] a;
  
  private static final String[] b;
  
  static void Zw(Object[] paramArrayOfObject, Object paramObject) throws Throwable {}
  
  static void ZC(Object paramObject) {
    Zbzk.ZS = a(-1880, -15710);
    Zbzk.ZI = new BigInteger(a(-1883, -8888));
    boolean bool = Zt2e.ZK();
    try {
      try {
        if (Zs4z.Zs.charAt(Math.abs(((BigInteger)Zlhy.ZN).intValue() % 32)) > Zef0.ZR.charAt(Math.abs(((BigInteger)Zza8.Zh).intValue() % 32))) {
          try {
            Zs34.ZT(Class.forName(a(-1881, 8199)));
            if (bool)
              Zmj8.ZE(Class.forName(a(-1873, 25774))); 
          } catch (Throwable throwable) {
            throw a(null);
          } 
          return;
        } 
      } catch (Throwable throwable) {
        throw a(null);
      } 
      Zmj8.ZE(Class.forName(a(-1873, 25774)));
    } catch (Throwable throwable) {}
  }
  
  static boolean ZG(Object[] paramArrayOfObject, Object paramObject) throws Throwable {
    // Byte code:
    //   0: invokestatic ZN : ()Z
    //   3: istore_2
    //   4: ldc2_w 8682522807148012
    //   7: invokestatic currentTimeMillis : ()J
    //   10: lxor
    //   11: lstore #4
    //   13: lload #4
    //   15: ldc2_w 25214903917
    //   18: lmul
    //   19: ldc2_w 11
    //   22: ladd
    //   23: ldc2_w 281474976710655
    //   26: land
    //   27: lstore #4
    //   29: lload #4
    //   31: bipush #32
    //   33: lshl
    //   34: lstore #6
    //   36: lload #4
    //   38: ldc2_w 25214903917
    //   41: lmul
    //   42: ldc2_w 11
    //   45: ladd
    //   46: ldc2_w 281474976710655
    //   49: land
    //   50: lstore #4
    //   52: lload #6
    //   54: lload #4
    //   56: ladd
    //   57: lstore #6
    //   59: bipush #16
    //   61: newarray byte
    //   63: dup
    //   64: iconst_0
    //   65: bipush #48
    //   67: bastore
    //   68: dup
    //   69: iconst_1
    //   70: bipush #49
    //   72: bastore
    //   73: dup
    //   74: iconst_2
    //   75: bipush #50
    //   77: bastore
    //   78: dup
    //   79: iconst_3
    //   80: bipush #51
    //   82: bastore
    //   83: dup
    //   84: iconst_4
    //   85: bipush #52
    //   87: bastore
    //   88: dup
    //   89: iconst_5
    //   90: bipush #53
    //   92: bastore
    //   93: dup
    //   94: bipush #6
    //   96: bipush #54
    //   98: bastore
    //   99: dup
    //   100: bipush #7
    //   102: bipush #55
    //   104: bastore
    //   105: dup
    //   106: bipush #8
    //   108: bipush #56
    //   110: bastore
    //   111: dup
    //   112: bipush #9
    //   114: bipush #57
    //   116: bastore
    //   117: dup
    //   118: bipush #10
    //   120: bipush #97
    //   122: bastore
    //   123: dup
    //   124: bipush #11
    //   126: bipush #98
    //   128: bastore
    //   129: dup
    //   130: bipush #12
    //   132: bipush #99
    //   134: bastore
    //   135: dup
    //   136: bipush #13
    //   138: bipush #100
    //   140: bastore
    //   141: dup
    //   142: bipush #14
    //   144: bipush #101
    //   146: bastore
    //   147: dup
    //   148: bipush #15
    //   150: bipush #102
    //   152: bastore
    //   153: astore #8
    //   155: bipush #64
    //   157: newarray byte
    //   159: astore #9
    //   161: bipush #64
    //   163: istore #10
    //   165: bipush #16
    //   167: istore #11
    //   169: iload #11
    //   171: iconst_1
    //   172: isub
    //   173: i2l
    //   174: lstore #12
    //   176: aload #9
    //   178: iinc #10, -1
    //   181: iload #10
    //   183: aload #8
    //   185: lload #6
    //   187: lload #12
    //   189: land
    //   190: l2i
    //   191: baload
    //   192: bastore
    //   193: lload #6
    //   195: iconst_4
    //   196: lushr
    //   197: lstore #6
    //   199: lload #6
    //   201: lconst_0
    //   202: lcmp
    //   203: ifne -> 176
    //   206: bipush #64
    //   208: iload #10
    //   210: isub
    //   211: newarray byte
    //   213: astore_3
    //   214: iconst_0
    //   215: istore #14
    //   217: iload #14
    //   219: aload_3
    //   220: arraylength
    //   221: if_icmpge -> 243
    //   224: aload_3
    //   225: iload #14
    //   227: aload #9
    //   229: iload #10
    //   231: iload #14
    //   233: iadd
    //   234: baload
    //   235: bastore
    //   236: iinc #14, 1
    //   239: iload_2
    //   240: ifne -> 217
    //   243: aload_3
    //   244: arraylength
    //   245: bipush #10
    //   247: if_icmplt -> 13
    //   250: new java/io/ByteArrayOutputStream
    //   253: dup
    //   254: invokespecial <init> : ()V
    //   257: astore_3
    //   258: getstatic burp/Zqp.ZX : Ljava/lang/String;
    //   261: astore #4
    //   263: iconst_0
    //   264: istore #5
    //   266: iload #5
    //   268: aload #4
    //   270: invokevirtual length : ()I
    //   273: if_icmpge -> 303
    //   276: aload_3
    //   277: aload #4
    //   279: iload #5
    //   281: iload #5
    //   283: iconst_2
    //   284: iadd
    //   285: invokevirtual substring : (II)Ljava/lang/String;
    //   288: bipush #16
    //   290: invokestatic parseInt : (Ljava/lang/String;I)I
    //   293: invokevirtual write : (I)V
    //   296: iinc #5, 2
    //   299: iload_2
    //   300: ifne -> 266
    //   303: aload_3
    //   304: invokevirtual toByteArray : ()[B
    //   307: astore #5
    //   309: getstatic burp/Zzo5.Zf : Ljava/lang/Object;
    //   312: checkcast java/math/BigInteger
    //   315: invokevirtual toByteArray : ()[B
    //   318: astore #6
    //   320: sipush #256
    //   323: newarray byte
    //   325: astore #8
    //   327: sipush #256
    //   330: newarray int
    //   332: astore #9
    //   334: sipush #256
    //   337: newarray int
    //   339: astore #10
    //   341: sipush #256
    //   344: newarray int
    //   346: astore #11
    //   348: sipush #256
    //   351: newarray int
    //   353: astore #12
    //   355: bipush #10
    //   357: newarray int
    //   359: astore #13
    //   361: sipush #283
    //   364: istore #14
    //   366: iconst_0
    //   367: istore #16
    //   369: iload #16
    //   371: sipush #256
    //   374: if_icmpge -> 608
    //   377: sipush #-1888
    //   380: sipush #7703
    //   383: invokestatic a : (II)Ljava/lang/String;
    //   386: iload #16
    //   388: iconst_1
    //   389: iushr
    //   390: invokevirtual charAt : (I)C
    //   393: istore #25
    //   395: iload #16
    //   397: iconst_1
    //   398: iand
    //   399: ifne -> 414
    //   402: iload #25
    //   404: bipush #8
    //   406: iushr
    //   407: goto -> 416
    //   410: invokestatic a : (Ljava/lang/Throwable;)Ljava/lang/Throwable;
    //   413: athrow
    //   414: iload #25
    //   416: i2b
    //   417: sipush #255
    //   420: iand
    //   421: istore #15
    //   423: iload #16
    //   425: iconst_1
    //   426: ishl
    //   427: istore #17
    //   429: iload #17
    //   431: sipush #256
    //   434: if_icmplt -> 444
    //   437: iload #17
    //   439: iload #14
    //   441: ixor
    //   442: istore #17
    //   444: iload #17
    //   446: iconst_1
    //   447: ishl
    //   448: istore #18
    //   450: iload #18
    //   452: sipush #256
    //   455: if_icmplt -> 465
    //   458: iload #18
    //   460: iload #14
    //   462: ixor
    //   463: istore #18
    //   465: iload #18
    //   467: iconst_1
    //   468: ishl
    //   469: istore #19
    //   471: iload #19
    //   473: sipush #256
    //   476: if_icmplt -> 486
    //   479: iload #19
    //   481: iload #14
    //   483: ixor
    //   484: istore #19
    //   486: iload #19
    //   488: iload #16
    //   490: ixor
    //   491: istore #20
    //   493: iload #20
    //   495: iload #17
    //   497: ixor
    //   498: istore #21
    //   500: iload #20
    //   502: iload #18
    //   504: ixor
    //   505: istore #22
    //   507: iload #19
    //   509: iload #18
    //   511: ixor
    //   512: iload #17
    //   514: ixor
    //   515: istore #23
    //   517: aload #8
    //   519: iload #16
    //   521: iload #15
    //   523: i2b
    //   524: bastore
    //   525: aload #9
    //   527: iload #15
    //   529: iload #23
    //   531: bipush #24
    //   533: ishl
    //   534: iload #20
    //   536: bipush #16
    //   538: ishl
    //   539: ior
    //   540: iload #22
    //   542: bipush #8
    //   544: ishl
    //   545: ior
    //   546: iload #21
    //   548: ior
    //   549: dup
    //   550: istore #24
    //   552: iastore
    //   553: aload #10
    //   555: iload #15
    //   557: iload #24
    //   559: bipush #8
    //   561: iushr
    //   562: iload #24
    //   564: bipush #24
    //   566: ishl
    //   567: ior
    //   568: iastore
    //   569: aload #11
    //   571: iload #15
    //   573: iload #24
    //   575: bipush #16
    //   577: iushr
    //   578: iload #24
    //   580: bipush #16
    //   582: ishl
    //   583: ior
    //   584: iastore
    //   585: aload #12
    //   587: iload #15
    //   589: iload #24
    //   591: bipush #24
    //   593: iushr
    //   594: iload #24
    //   596: bipush #8
    //   598: ishl
    //   599: ior
    //   600: iastore
    //   601: iinc #16, 1
    //   604: iload_2
    //   605: ifne -> 369
    //   608: iconst_1
    //   609: istore #25
    //   611: aload #13
    //   613: iconst_0
    //   614: iload #25
    //   616: bipush #24
    //   618: ishl
    //   619: iastore
    //   620: iconst_1
    //   621: istore #26
    //   623: iload #26
    //   625: bipush #10
    //   627: if_icmpge -> 668
    //   630: iload #25
    //   632: iconst_1
    //   633: ishl
    //   634: istore #25
    //   636: iload #25
    //   638: sipush #256
    //   641: if_icmplt -> 651
    //   644: iload #25
    //   646: iload #14
    //   648: ixor
    //   649: istore #25
    //   651: aload #13
    //   653: iload #26
    //   655: iload #25
    //   657: bipush #24
    //   659: ishl
    //   660: iastore
    //   661: iinc #26, 1
    //   664: iload_2
    //   665: ifne -> 623
    //   668: iconst_4
    //   669: istore #26
    //   671: iload #26
    //   673: bipush #6
    //   675: iadd
    //   676: istore #27
    //   678: iconst_4
    //   679: iload #27
    //   681: iconst_1
    //   682: iadd
    //   683: imul
    //   684: istore #28
    //   686: iload #28
    //   688: newarray int
    //   690: astore #29
    //   692: iload #28
    //   694: newarray int
    //   696: astore #30
    //   698: iconst_0
    //   699: istore #25
    //   701: iconst_0
    //   702: istore #32
    //   704: iconst_0
    //   705: istore #33
    //   707: iload #32
    //   709: iload #26
    //   711: if_icmpge -> 779
    //   714: aload #29
    //   716: iload #32
    //   718: aload #5
    //   720: iload #33
    //   722: baload
    //   723: bipush #24
    //   725: ishl
    //   726: aload #5
    //   728: iload #33
    //   730: iconst_1
    //   731: iadd
    //   732: baload
    //   733: sipush #255
    //   736: iand
    //   737: bipush #16
    //   739: ishl
    //   740: ior
    //   741: aload #5
    //   743: iload #33
    //   745: iconst_2
    //   746: iadd
    //   747: baload
    //   748: sipush #255
    //   751: iand
    //   752: bipush #8
    //   754: ishl
    //   755: ior
    //   756: aload #5
    //   758: iload #33
    //   760: iconst_3
    //   761: iadd
    //   762: baload
    //   763: sipush #255
    //   766: iand
    //   767: ior
    //   768: iastore
    //   769: iinc #32, 1
    //   772: iinc #33, 4
    //   775: iload_2
    //   776: ifne -> 707
    //   779: iload #26
    //   781: istore #32
    //   783: iconst_0
    //   784: istore #33
    //   786: iload #32
    //   788: iload #28
    //   790: if_icmpge -> 917
    //   793: aload #29
    //   795: iload #32
    //   797: iconst_1
    //   798: isub
    //   799: iaload
    //   800: istore #31
    //   802: iload #33
    //   804: ifne -> 891
    //   807: iload #26
    //   809: istore #33
    //   811: aload #8
    //   813: iload #31
    //   815: bipush #16
    //   817: iushr
    //   818: sipush #255
    //   821: iand
    //   822: baload
    //   823: bipush #24
    //   825: ishl
    //   826: aload #8
    //   828: iload #31
    //   830: bipush #8
    //   832: iushr
    //   833: sipush #255
    //   836: iand
    //   837: baload
    //   838: sipush #255
    //   841: iand
    //   842: bipush #16
    //   844: ishl
    //   845: ior
    //   846: aload #8
    //   848: iload #31
    //   850: sipush #255
    //   853: iand
    //   854: baload
    //   855: sipush #255
    //   858: iand
    //   859: bipush #8
    //   861: ishl
    //   862: ior
    //   863: aload #8
    //   865: iload #31
    //   867: bipush #24
    //   869: iushr
    //   870: baload
    //   871: sipush #255
    //   874: iand
    //   875: ior
    //   876: istore #31
    //   878: iload #31
    //   880: aload #13
    //   882: iload #25
    //   884: iinc #25, 1
    //   887: iaload
    //   888: ixor
    //   889: istore #31
    //   891: aload #29
    //   893: iload #32
    //   895: aload #29
    //   897: iload #32
    //   899: iload #26
    //   901: isub
    //   902: iaload
    //   903: iload #31
    //   905: ixor
    //   906: iastore
    //   907: iinc #32, 1
    //   910: iinc #33, -1
    //   913: iload_2
    //   914: ifne -> 786
    //   917: iconst_0
    //   918: istore #32
    //   920: iconst_4
    //   921: iload #27
    //   923: imul
    //   924: istore #33
    //   926: aload #30
    //   928: iload #32
    //   930: aload #29
    //   932: iload #33
    //   934: iaload
    //   935: iastore
    //   936: aload #30
    //   938: iload #32
    //   940: iconst_1
    //   941: iadd
    //   942: aload #29
    //   944: iload #33
    //   946: iconst_1
    //   947: iadd
    //   948: iaload
    //   949: iastore
    //   950: aload #30
    //   952: iload #32
    //   954: iconst_2
    //   955: iadd
    //   956: aload #29
    //   958: iload #33
    //   960: iconst_2
    //   961: iadd
    //   962: iaload
    //   963: iastore
    //   964: aload #30
    //   966: iload #32
    //   968: iconst_3
    //   969: iadd
    //   970: aload #29
    //   972: iload #33
    //   974: iconst_3
    //   975: iadd
    //   976: iaload
    //   977: iastore
    //   978: iinc #32, 4
    //   981: iinc #33, -4
    //   984: iconst_1
    //   985: istore #35
    //   987: iload #35
    //   989: iload #27
    //   991: if_icmpge -> 1355
    //   994: aload #29
    //   996: iload #33
    //   998: iaload
    //   999: istore #34
    //   1001: aload #30
    //   1003: iload #32
    //   1005: aload #9
    //   1007: aload #8
    //   1009: iload #34
    //   1011: bipush #24
    //   1013: iushr
    //   1014: baload
    //   1015: sipush #255
    //   1018: iand
    //   1019: iaload
    //   1020: aload #10
    //   1022: aload #8
    //   1024: iload #34
    //   1026: bipush #16
    //   1028: iushr
    //   1029: sipush #255
    //   1032: iand
    //   1033: baload
    //   1034: sipush #255
    //   1037: iand
    //   1038: iaload
    //   1039: ixor
    //   1040: aload #11
    //   1042: aload #8
    //   1044: iload #34
    //   1046: bipush #8
    //   1048: iushr
    //   1049: sipush #255
    //   1052: iand
    //   1053: baload
    //   1054: sipush #255
    //   1057: iand
    //   1058: iaload
    //   1059: ixor
    //   1060: aload #12
    //   1062: aload #8
    //   1064: iload #34
    //   1066: sipush #255
    //   1069: iand
    //   1070: baload
    //   1071: sipush #255
    //   1074: iand
    //   1075: iaload
    //   1076: ixor
    //   1077: iastore
    //   1078: aload #29
    //   1080: iload #33
    //   1082: iconst_1
    //   1083: iadd
    //   1084: iaload
    //   1085: istore #34
    //   1087: aload #30
    //   1089: iload #32
    //   1091: iconst_1
    //   1092: iadd
    //   1093: aload #9
    //   1095: aload #8
    //   1097: iload #34
    //   1099: bipush #24
    //   1101: iushr
    //   1102: baload
    //   1103: sipush #255
    //   1106: iand
    //   1107: iaload
    //   1108: aload #10
    //   1110: aload #8
    //   1112: iload #34
    //   1114: bipush #16
    //   1116: iushr
    //   1117: sipush #255
    //   1120: iand
    //   1121: baload
    //   1122: sipush #255
    //   1125: iand
    //   1126: iaload
    //   1127: ixor
    //   1128: aload #11
    //   1130: aload #8
    //   1132: iload #34
    //   1134: bipush #8
    //   1136: iushr
    //   1137: sipush #255
    //   1140: iand
    //   1141: baload
    //   1142: sipush #255
    //   1145: iand
    //   1146: iaload
    //   1147: ixor
    //   1148: aload #12
    //   1150: aload #8
    //   1152: iload #34
    //   1154: sipush #255
    //   1157: iand
    //   1158: baload
    //   1159: sipush #255
    //   1162: iand
    //   1163: iaload
    //   1164: ixor
    //   1165: iastore
    //   1166: aload #29
    //   1168: iload #33
    //   1170: iconst_2
    //   1171: iadd
    //   1172: iaload
    //   1173: istore #34
    //   1175: aload #30
    //   1177: iload #32
    //   1179: iconst_2
    //   1180: iadd
    //   1181: aload #9
    //   1183: aload #8
    //   1185: iload #34
    //   1187: bipush #24
    //   1189: iushr
    //   1190: baload
    //   1191: sipush #255
    //   1194: iand
    //   1195: iaload
    //   1196: aload #10
    //   1198: aload #8
    //   1200: iload #34
    //   1202: bipush #16
    //   1204: iushr
    //   1205: sipush #255
    //   1208: iand
    //   1209: baload
    //   1210: sipush #255
    //   1213: iand
    //   1214: iaload
    //   1215: ixor
    //   1216: aload #11
    //   1218: aload #8
    //   1220: iload #34
    //   1222: bipush #8
    //   1224: iushr
    //   1225: sipush #255
    //   1228: iand
    //   1229: baload
    //   1230: sipush #255
    //   1233: iand
    //   1234: iaload
    //   1235: ixor
    //   1236: aload #12
    //   1238: aload #8
    //   1240: iload #34
    //   1242: sipush #255
    //   1245: iand
    //   1246: baload
    //   1247: sipush #255
    //   1250: iand
    //   1251: iaload
    //   1252: ixor
    //   1253: iastore
    //   1254: aload #29
    //   1256: iload #33
    //   1258: iconst_3
    //   1259: iadd
    //   1260: iaload
    //   1261: istore #34
    //   1263: aload #30
    //   1265: iload #32
    //   1267: iconst_3
    //   1268: iadd
    //   1269: aload #9
    //   1271: aload #8
    //   1273: iload #34
    //   1275: bipush #24
    //   1277: iushr
    //   1278: baload
    //   1279: sipush #255
    //   1282: iand
    //   1283: iaload
    //   1284: aload #10
    //   1286: aload #8
    //   1288: iload #34
    //   1290: bipush #16
    //   1292: iushr
    //   1293: sipush #255
    //   1296: iand
    //   1297: baload
    //   1298: sipush #255
    //   1301: iand
    //   1302: iaload
    //   1303: ixor
    //   1304: aload #11
    //   1306: aload #8
    //   1308: iload #34
    //   1310: bipush #8
    //   1312: iushr
    //   1313: sipush #255
    //   1316: iand
    //   1317: baload
    //   1318: sipush #255
    //   1321: iand
    //   1322: iaload
    //   1323: ixor
    //   1324: aload #12
    //   1326: aload #8
    //   1328: iload #34
    //   1330: sipush #255
    //   1333: iand
    //   1334: baload
    //   1335: sipush #255
    //   1338: iand
    //   1339: iaload
    //   1340: ixor
    //   1341: iastore
    //   1342: iinc #32, 4
    //   1345: iinc #33, -4
    //   1348: iinc #35, 1
    //   1351: iload_2
    //   1352: ifne -> 987
    //   1355: aload #30
    //   1357: iload #32
    //   1359: aload #29
    //   1361: iload #33
    //   1363: iaload
    //   1364: iastore
    //   1365: aload #30
    //   1367: iload #32
    //   1369: iconst_1
    //   1370: iadd
    //   1371: aload #29
    //   1373: iload #33
    //   1375: iconst_1
    //   1376: iadd
    //   1377: iaload
    //   1378: iastore
    //   1379: aload #30
    //   1381: iload #32
    //   1383: iconst_2
    //   1384: iadd
    //   1385: aload #29
    //   1387: iload #33
    //   1389: iconst_2
    //   1390: iadd
    //   1391: iaload
    //   1392: iastore
    //   1393: aload #30
    //   1395: iload #32
    //   1397: iconst_3
    //   1398: iadd
    //   1399: aload #29
    //   1401: iload #33
    //   1403: iconst_3
    //   1404: iadd
    //   1405: iaload
    //   1406: iastore
    //   1407: iconst_0
    //   1408: newarray byte
    //   1410: astore #35
    //   1412: aload #6
    //   1414: arraylength
    //   1415: bipush #16
    //   1417: irem
    //   1418: ifeq -> 1442
    //   1421: new java/lang/Exception
    //   1424: dup
    //   1425: sipush #-1886
    //   1428: sipush #-6257
    //   1431: invokestatic a : (II)Ljava/lang/String;
    //   1434: invokespecial <init> : (Ljava/lang/String;)V
    //   1437: athrow
    //   1438: invokestatic a : (Ljava/lang/Throwable;)Ljava/lang/Throwable;
    //   1441: athrow
    //   1442: bipush #10
    //   1444: istore #36
    //   1446: sipush #-1878
    //   1449: sipush #256
    //   1452: newarray byte
    //   1454: astore #37
    //   1456: sipush #5839
    //   1459: sipush #256
    //   1462: newarray int
    //   1464: astore #38
    //   1466: sipush #256
    //   1469: newarray int
    //   1471: astore #39
    //   1473: sipush #256
    //   1476: newarray int
    //   1478: astore #40
    //   1480: sipush #256
    //   1483: newarray int
    //   1485: astore #41
    //   1487: sipush #283
    //   1490: istore #14
    //   1492: invokestatic a : (II)Ljava/lang/String;
    //   1495: astore #42
    //   1497: iconst_0
    //   1498: istore #16
    //   1500: iload #16
    //   1502: sipush #256
    //   1505: if_icmpge -> 1732
    //   1508: aload #42
    //   1510: iload #16
    //   1512: iconst_1
    //   1513: iushr
    //   1514: invokevirtual charAt : (I)C
    //   1517: istore #43
    //   1519: iload #16
    //   1521: iconst_1
    //   1522: iand
    //   1523: ifne -> 1538
    //   1526: iload #43
    //   1528: bipush #8
    //   1530: iushr
    //   1531: goto -> 1540
    //   1534: invokestatic a : (Ljava/lang/Throwable;)Ljava/lang/Throwable;
    //   1537: athrow
    //   1538: iload #43
    //   1540: i2b
    //   1541: sipush #255
    //   1544: iand
    //   1545: istore #15
    //   1547: iload #16
    //   1549: iconst_1
    //   1550: ishl
    //   1551: istore #17
    //   1553: iload #17
    //   1555: sipush #256
    //   1558: if_icmplt -> 1568
    //   1561: iload #17
    //   1563: iload #14
    //   1565: ixor
    //   1566: istore #17
    //   1568: iload #17
    //   1570: iconst_1
    //   1571: ishl
    //   1572: istore #18
    //   1574: iload #18
    //   1576: sipush #256
    //   1579: if_icmplt -> 1589
    //   1582: iload #18
    //   1584: iload #14
    //   1586: ixor
    //   1587: istore #18
    //   1589: iload #18
    //   1591: iconst_1
    //   1592: ishl
    //   1593: istore #19
    //   1595: iload #19
    //   1597: sipush #256
    //   1600: if_icmplt -> 1610
    //   1603: iload #19
    //   1605: iload #14
    //   1607: ixor
    //   1608: istore #19
    //   1610: iload #19
    //   1612: iload #16
    //   1614: ixor
    //   1615: istore #20
    //   1617: iload #20
    //   1619: iload #17
    //   1621: ixor
    //   1622: istore #21
    //   1624: iload #20
    //   1626: iload #18
    //   1628: ixor
    //   1629: istore #22
    //   1631: iload #19
    //   1633: iload #18
    //   1635: ixor
    //   1636: iload #17
    //   1638: ixor
    //   1639: istore #23
    //   1641: aload #37
    //   1643: iload #15
    //   1645: iload #16
    //   1647: i2b
    //   1648: bastore
    //   1649: aload #38
    //   1651: iload #15
    //   1653: iload #23
    //   1655: bipush #24
    //   1657: ishl
    //   1658: iload #20
    //   1660: bipush #16
    //   1662: ishl
    //   1663: ior
    //   1664: iload #22
    //   1666: bipush #8
    //   1668: ishl
    //   1669: ior
    //   1670: iload #21
    //   1672: ior
    //   1673: dup
    //   1674: istore #24
    //   1676: iastore
    //   1677: aload #39
    //   1679: iload #15
    //   1681: iload #24
    //   1683: bipush #8
    //   1685: iushr
    //   1686: iload #24
    //   1688: bipush #24
    //   1690: ishl
    //   1691: ior
    //   1692: iastore
    //   1693: aload #40
    //   1695: iload #15
    //   1697: iload #24
    //   1699: bipush #16
    //   1701: iushr
    //   1702: iload #24
    //   1704: bipush #16
    //   1706: ishl
    //   1707: ior
    //   1708: iastore
    //   1709: aload #41
    //   1711: iload #15
    //   1713: iload #24
    //   1715: bipush #24
    //   1717: iushr
    //   1718: iload #24
    //   1720: bipush #8
    //   1722: ishl
    //   1723: ior
    //   1724: iastore
    //   1725: iinc #16, 1
    //   1728: iload_2
    //   1729: ifne -> 1500
    //   1732: aload #6
    //   1734: arraylength
    //   1735: newarray byte
    //   1737: astore #43
    //   1739: iconst_0
    //   1740: istore #44
    //   1742: iload #44
    //   1744: aload #6
    //   1746: arraylength
    //   1747: bipush #16
    //   1749: idiv
    //   1750: if_icmpge -> 2664
    //   1753: bipush #16
    //   1755: newarray byte
    //   1757: astore #45
    //   1759: bipush #16
    //   1761: newarray byte
    //   1763: astore #46
    //   1765: iconst_0
    //   1766: istore #47
    //   1768: iload #47
    //   1770: bipush #16
    //   1772: if_icmpge -> 1798
    //   1775: aload #45
    //   1777: iload #47
    //   1779: aload #6
    //   1781: iload #47
    //   1783: iload #44
    //   1785: bipush #16
    //   1787: imul
    //   1788: iadd
    //   1789: baload
    //   1790: bastore
    //   1791: iinc #47, 1
    //   1794: iload_2
    //   1795: ifne -> 1768
    //   1798: iconst_0
    //   1799: istore #47
    //   1801: aload #45
    //   1803: iconst_0
    //   1804: baload
    //   1805: bipush #24
    //   1807: ishl
    //   1808: aload #45
    //   1810: iconst_1
    //   1811: baload
    //   1812: sipush #255
    //   1815: iand
    //   1816: bipush #16
    //   1818: ishl
    //   1819: ior
    //   1820: aload #45
    //   1822: iconst_2
    //   1823: baload
    //   1824: sipush #255
    //   1827: iand
    //   1828: bipush #8
    //   1830: ishl
    //   1831: ior
    //   1832: aload #45
    //   1834: iconst_3
    //   1835: baload
    //   1836: sipush #255
    //   1839: iand
    //   1840: ior
    //   1841: aload #30
    //   1843: iconst_0
    //   1844: iaload
    //   1845: ixor
    //   1846: istore #49
    //   1848: aload #45
    //   1850: iconst_4
    //   1851: baload
    //   1852: bipush #24
    //   1854: ishl
    //   1855: aload #45
    //   1857: iconst_5
    //   1858: baload
    //   1859: sipush #255
    //   1862: iand
    //   1863: bipush #16
    //   1865: ishl
    //   1866: ior
    //   1867: aload #45
    //   1869: bipush #6
    //   1871: baload
    //   1872: sipush #255
    //   1875: iand
    //   1876: bipush #8
    //   1878: ishl
    //   1879: ior
    //   1880: aload #45
    //   1882: bipush #7
    //   1884: baload
    //   1885: sipush #255
    //   1888: iand
    //   1889: ior
    //   1890: aload #30
    //   1892: iconst_1
    //   1893: iaload
    //   1894: ixor
    //   1895: istore #50
    //   1897: aload #45
    //   1899: bipush #8
    //   1901: baload
    //   1902: bipush #24
    //   1904: ishl
    //   1905: aload #45
    //   1907: bipush #9
    //   1909: baload
    //   1910: sipush #255
    //   1913: iand
    //   1914: bipush #16
    //   1916: ishl
    //   1917: ior
    //   1918: aload #45
    //   1920: bipush #10
    //   1922: baload
    //   1923: sipush #255
    //   1926: iand
    //   1927: bipush #8
    //   1929: ishl
    //   1930: ior
    //   1931: aload #45
    //   1933: bipush #11
    //   1935: baload
    //   1936: sipush #255
    //   1939: iand
    //   1940: ior
    //   1941: aload #30
    //   1943: iconst_2
    //   1944: iaload
    //   1945: ixor
    //   1946: istore #51
    //   1948: aload #45
    //   1950: bipush #12
    //   1952: baload
    //   1953: bipush #24
    //   1955: ishl
    //   1956: aload #45
    //   1958: bipush #13
    //   1960: baload
    //   1961: sipush #255
    //   1964: iand
    //   1965: bipush #16
    //   1967: ishl
    //   1968: ior
    //   1969: aload #45
    //   1971: bipush #14
    //   1973: baload
    //   1974: sipush #255
    //   1977: iand
    //   1978: bipush #8
    //   1980: ishl
    //   1981: ior
    //   1982: aload #45
    //   1984: bipush #15
    //   1986: baload
    //   1987: sipush #255
    //   1990: iand
    //   1991: ior
    //   1992: aload #30
    //   1994: iconst_3
    //   1995: iaload
    //   1996: ixor
    //   1997: istore #52
    //   1999: iconst_1
    //   2000: istore #53
    //   2002: iload #53
    //   2004: iload #36
    //   2006: if_icmpge -> 2249
    //   2009: iinc #47, 4
    //   2012: aload #38
    //   2014: iload #49
    //   2016: bipush #24
    //   2018: iushr
    //   2019: iaload
    //   2020: aload #39
    //   2022: iload #52
    //   2024: bipush #16
    //   2026: iushr
    //   2027: sipush #255
    //   2030: iand
    //   2031: iaload
    //   2032: ixor
    //   2033: aload #40
    //   2035: iload #51
    //   2037: bipush #8
    //   2039: iushr
    //   2040: sipush #255
    //   2043: iand
    //   2044: iaload
    //   2045: ixor
    //   2046: aload #41
    //   2048: iload #50
    //   2050: sipush #255
    //   2053: iand
    //   2054: iaload
    //   2055: ixor
    //   2056: aload #30
    //   2058: iload #47
    //   2060: iaload
    //   2061: ixor
    //   2062: istore #54
    //   2064: aload #38
    //   2066: iload #50
    //   2068: bipush #24
    //   2070: iushr
    //   2071: iaload
    //   2072: aload #39
    //   2074: iload #49
    //   2076: bipush #16
    //   2078: iushr
    //   2079: sipush #255
    //   2082: iand
    //   2083: iaload
    //   2084: ixor
    //   2085: aload #40
    //   2087: iload #52
    //   2089: bipush #8
    //   2091: iushr
    //   2092: sipush #255
    //   2095: iand
    //   2096: iaload
    //   2097: ixor
    //   2098: aload #41
    //   2100: iload #51
    //   2102: sipush #255
    //   2105: iand
    //   2106: iaload
    //   2107: ixor
    //   2108: aload #30
    //   2110: iload #47
    //   2112: iconst_1
    //   2113: iadd
    //   2114: iaload
    //   2115: ixor
    //   2116: istore #55
    //   2118: aload #38
    //   2120: iload #51
    //   2122: bipush #24
    //   2124: iushr
    //   2125: iaload
    //   2126: aload #39
    //   2128: iload #50
    //   2130: bipush #16
    //   2132: iushr
    //   2133: sipush #255
    //   2136: iand
    //   2137: iaload
    //   2138: ixor
    //   2139: aload #40
    //   2141: iload #49
    //   2143: bipush #8
    //   2145: iushr
    //   2146: sipush #255
    //   2149: iand
    //   2150: iaload
    //   2151: ixor
    //   2152: aload #41
    //   2154: iload #52
    //   2156: sipush #255
    //   2159: iand
    //   2160: iaload
    //   2161: ixor
    //   2162: aload #30
    //   2164: iload #47
    //   2166: iconst_2
    //   2167: iadd
    //   2168: iaload
    //   2169: ixor
    //   2170: istore #56
    //   2172: aload #38
    //   2174: iload #52
    //   2176: bipush #24
    //   2178: iushr
    //   2179: iaload
    //   2180: aload #39
    //   2182: iload #51
    //   2184: bipush #16
    //   2186: iushr
    //   2187: sipush #255
    //   2190: iand
    //   2191: iaload
    //   2192: ixor
    //   2193: aload #40
    //   2195: iload #50
    //   2197: bipush #8
    //   2199: iushr
    //   2200: sipush #255
    //   2203: iand
    //   2204: iaload
    //   2205: ixor
    //   2206: aload #41
    //   2208: iload #49
    //   2210: sipush #255
    //   2213: iand
    //   2214: iaload
    //   2215: ixor
    //   2216: aload #30
    //   2218: iload #47
    //   2220: iconst_3
    //   2221: iadd
    //   2222: iaload
    //   2223: ixor
    //   2224: istore #57
    //   2226: iload #54
    //   2228: istore #49
    //   2230: iload #55
    //   2232: istore #50
    //   2234: iload #56
    //   2236: istore #51
    //   2238: iload #57
    //   2240: istore #52
    //   2242: iinc #53, 1
    //   2245: iload_2
    //   2246: ifne -> 2002
    //   2249: iinc #47, 4
    //   2252: aload #30
    //   2254: iload #47
    //   2256: iaload
    //   2257: istore #48
    //   2259: aload #46
    //   2261: iconst_0
    //   2262: aload #37
    //   2264: iload #49
    //   2266: bipush #24
    //   2268: iushr
    //   2269: baload
    //   2270: iload #48
    //   2272: bipush #24
    //   2274: iushr
    //   2275: ixor
    //   2276: i2b
    //   2277: bastore
    //   2278: aload #46
    //   2280: iconst_1
    //   2281: aload #37
    //   2283: iload #52
    //   2285: bipush #16
    //   2287: iushr
    //   2288: sipush #255
    //   2291: iand
    //   2292: baload
    //   2293: iload #48
    //   2295: bipush #16
    //   2297: iushr
    //   2298: ixor
    //   2299: i2b
    //   2300: bastore
    //   2301: aload #46
    //   2303: iconst_2
    //   2304: aload #37
    //   2306: iload #51
    //   2308: bipush #8
    //   2310: iushr
    //   2311: sipush #255
    //   2314: iand
    //   2315: baload
    //   2316: iload #48
    //   2318: bipush #8
    //   2320: iushr
    //   2321: ixor
    //   2322: i2b
    //   2323: bastore
    //   2324: aload #46
    //   2326: iconst_3
    //   2327: aload #37
    //   2329: iload #50
    //   2331: sipush #255
    //   2334: iand
    //   2335: baload
    //   2336: iload #48
    //   2338: ixor
    //   2339: i2b
    //   2340: bastore
    //   2341: aload #30
    //   2343: iload #47
    //   2345: iconst_1
    //   2346: iadd
    //   2347: iaload
    //   2348: istore #48
    //   2350: aload #46
    //   2352: iconst_4
    //   2353: aload #37
    //   2355: iload #50
    //   2357: bipush #24
    //   2359: iushr
    //   2360: baload
    //   2361: iload #48
    //   2363: bipush #24
    //   2365: iushr
    //   2366: ixor
    //   2367: i2b
    //   2368: bastore
    //   2369: aload #46
    //   2371: iconst_5
    //   2372: aload #37
    //   2374: iload #49
    //   2376: bipush #16
    //   2378: iushr
    //   2379: sipush #255
    //   2382: iand
    //   2383: baload
    //   2384: iload #48
    //   2386: bipush #16
    //   2388: iushr
    //   2389: ixor
    //   2390: i2b
    //   2391: bastore
    //   2392: aload #46
    //   2394: bipush #6
    //   2396: aload #37
    //   2398: iload #52
    //   2400: bipush #8
    //   2402: iushr
    //   2403: sipush #255
    //   2406: iand
    //   2407: baload
    //   2408: iload #48
    //   2410: bipush #8
    //   2412: iushr
    //   2413: ixor
    //   2414: i2b
    //   2415: bastore
    //   2416: aload #46
    //   2418: bipush #7
    //   2420: aload #37
    //   2422: iload #51
    //   2424: sipush #255
    //   2427: iand
    //   2428: baload
    //   2429: iload #48
    //   2431: ixor
    //   2432: i2b
    //   2433: bastore
    //   2434: aload #30
    //   2436: iload #47
    //   2438: iconst_2
    //   2439: iadd
    //   2440: iaload
    //   2441: istore #48
    //   2443: aload #46
    //   2445: bipush #8
    //   2447: aload #37
    //   2449: iload #51
    //   2451: bipush #24
    //   2453: iushr
    //   2454: baload
    //   2455: iload #48
    //   2457: bipush #24
    //   2459: iushr
    //   2460: ixor
    //   2461: i2b
    //   2462: bastore
    //   2463: aload #46
    //   2465: bipush #9
    //   2467: aload #37
    //   2469: iload #50
    //   2471: bipush #16
    //   2473: iushr
    //   2474: sipush #255
    //   2477: iand
    //   2478: baload
    //   2479: iload #48
    //   2481: bipush #16
    //   2483: iushr
    //   2484: ixor
    //   2485: i2b
    //   2486: bastore
    //   2487: aload #46
    //   2489: bipush #10
    //   2491: aload #37
    //   2493: iload #49
    //   2495: bipush #8
    //   2497: iushr
    //   2498: sipush #255
    //   2501: iand
    //   2502: baload
    //   2503: iload #48
    //   2505: bipush #8
    //   2507: iushr
    //   2508: ixor
    //   2509: i2b
    //   2510: bastore
    //   2511: aload #46
    //   2513: bipush #11
    //   2515: aload #37
    //   2517: iload #52
    //   2519: sipush #255
    //   2522: iand
    //   2523: baload
    //   2524: iload #48
    //   2526: ixor
    //   2527: i2b
    //   2528: bastore
    //   2529: aload #30
    //   2531: iload #47
    //   2533: iconst_3
    //   2534: iadd
    //   2535: iaload
    //   2536: istore #48
    //   2538: aload #46
    //   2540: bipush #12
    //   2542: aload #37
    //   2544: iload #52
    //   2546: bipush #24
    //   2548: iushr
    //   2549: baload
    //   2550: iload #48
    //   2552: bipush #24
    //   2554: iushr
    //   2555: ixor
    //   2556: i2b
    //   2557: bastore
    //   2558: aload #46
    //   2560: bipush #13
    //   2562: aload #37
    //   2564: iload #51
    //   2566: bipush #16
    //   2568: iushr
    //   2569: sipush #255
    //   2572: iand
    //   2573: baload
    //   2574: iload #48
    //   2576: bipush #16
    //   2578: iushr
    //   2579: ixor
    //   2580: i2b
    //   2581: bastore
    //   2582: aload #46
    //   2584: bipush #14
    //   2586: aload #37
    //   2588: iload #50
    //   2590: bipush #8
    //   2592: iushr
    //   2593: sipush #255
    //   2596: iand
    //   2597: baload
    //   2598: iload #48
    //   2600: bipush #8
    //   2602: iushr
    //   2603: ixor
    //   2604: i2b
    //   2605: bastore
    //   2606: aload #46
    //   2608: bipush #15
    //   2610: aload #37
    //   2612: iload #49
    //   2614: sipush #255
    //   2617: iand
    //   2618: baload
    //   2619: iload #48
    //   2621: ixor
    //   2622: i2b
    //   2623: bastore
    //   2624: iconst_0
    //   2625: istore #53
    //   2627: iload #53
    //   2629: bipush #16
    //   2631: if_icmpge -> 2657
    //   2634: aload #43
    //   2636: iload #53
    //   2638: iload #44
    //   2640: bipush #16
    //   2642: imul
    //   2643: iadd
    //   2644: aload #46
    //   2646: iload #53
    //   2648: baload
    //   2649: bastore
    //   2650: iinc #53, 1
    //   2653: iload_2
    //   2654: ifne -> 2627
    //   2657: iinc #44, 1
    //   2660: iload_2
    //   2661: ifne -> 1742
    //   2664: aload #43
    //   2666: arraylength
    //   2667: ifle -> 2748
    //   2670: aload #43
    //   2672: aload #43
    //   2674: arraylength
    //   2675: iconst_1
    //   2676: isub
    //   2677: baload
    //   2678: istore #44
    //   2680: iload #44
    //   2682: bipush #16
    //   2684: if_icmple -> 2695
    //   2687: aload #43
    //   2689: astore #35
    //   2691: iload_2
    //   2692: ifne -> 2748
    //   2695: aload #43
    //   2697: arraylength
    //   2698: iload #44
    //   2700: isub
    //   2701: newarray byte
    //   2703: astore #35
    //   2705: iconst_0
    //   2706: istore #45
    //   2708: iload #45
    //   2710: aload #35
    //   2712: arraylength
    //   2713: if_icmpge -> 2748
    //   2716: iload #45
    //   2718: aload #43
    //   2720: arraylength
    //   2721: if_icmpge -> 2748
    //   2724: aload #35
    //   2726: iload #45
    //   2728: aload #43
    //   2730: iload #45
    //   2732: baload
    //   2733: bastore
    //   2734: iinc #45, 1
    //   2737: iload_2
    //   2738: ifne -> 2708
    //   2741: goto -> 2748
    //   2744: invokestatic a : (Ljava/lang/Throwable;)Ljava/lang/Throwable;
    //   2747: athrow
    //   2748: aload #35
    //   2750: astore #7
    //   2752: new java/math/BigInteger
    //   2755: dup
    //   2756: aload #7
    //   2758: invokespecial <init> : ([B)V
    //   2761: invokevirtual abs : ()Ljava/math/BigInteger;
    //   2764: putstatic burp/Zbzk.ZI : Ljava/lang/Object;
    //   2767: new java/lang/StringBuilder
    //   2770: dup
    //   2771: invokespecial <init> : ()V
    //   2774: astore_3
    //   2775: iconst_0
    //   2776: istore #4
    //   2778: iload #4
    //   2780: bipush #32
    //   2782: if_icmpge -> 4115
    //   2785: iload #4
    //   2787: tableswitch default -> 4108, 0 -> 2928, 1 -> 2965, 2 -> 3002, 3 -> 3039, 4 -> 3076, 5 -> 3113, 6 -> 3150, 7 -> 3187, 8 -> 3224, 9 -> 3261, 10 -> 3298, 11 -> 3335, 12 -> 3372, 13 -> 3409, 14 -> 3446, 15 -> 3483, 16 -> 3520, 17 -> 3557, 18 -> 3594, 19 -> 3631, 20 -> 3668, 21 -> 3705, 22 -> 3742, 23 -> 3779, 24 -> 3816, 25 -> 3853, 26 -> 3890, 27 -> 3927, 28 -> 3964, 29 -> 4001, 30 -> 4038, 31 -> 4075
    //   2928: aload_3
    //   2929: getstatic burp/Zg6f.Zf : Ljava/lang/String;
    //   2932: getstatic burp/Zeqg.Zm : Ljava/lang/Object;
    //   2935: checkcast java/math/BigInteger
    //   2938: invokevirtual intValue : ()I
    //   2941: bipush #32
    //   2943: irem
    //   2944: invokestatic abs : (I)I
    //   2947: invokevirtual charAt : (I)C
    //   2950: invokevirtual append : (C)Ljava/lang/StringBuilder;
    //   2953: pop
    //   2954: iload_2
    //   2955: ifne -> 4108
    //   2958: goto -> 2965
    //   2961: invokestatic a : (Ljava/lang/Throwable;)Ljava/lang/Throwable;
    //   2964: athrow
    //   2965: aload_3
    //   2966: getstatic burp/Zrof.ZE : Ljava/lang/String;
    //   2969: getstatic burp/Zlhy.ZN : Ljava/lang/Object;
    //   2972: checkcast java/math/BigInteger
    //   2975: invokevirtual intValue : ()I
    //   2978: bipush #32
    //   2980: irem
    //   2981: invokestatic abs : (I)I
    //   2984: invokevirtual charAt : (I)C
    //   2987: invokevirtual append : (C)Ljava/lang/StringBuilder;
    //   2990: pop
    //   2991: iload_2
    //   2992: ifne -> 4108
    //   2995: goto -> 3002
    //   2998: invokestatic a : (Ljava/lang/Throwable;)Ljava/lang/Throwable;
    //   3001: athrow
    //   3002: aload_3
    //   3003: getstatic burp/Zg_5.ZG : Ljava/lang/String;
    //   3006: getstatic burp/Zb8y.ZI : Ljava/lang/Object;
    //   3009: checkcast java/math/BigInteger
    //   3012: invokevirtual intValue : ()I
    //   3015: bipush #32
    //   3017: irem
    //   3018: invokestatic abs : (I)I
    //   3021: invokevirtual charAt : (I)C
    //   3024: invokevirtual append : (C)Ljava/lang/StringBuilder;
    //   3027: pop
    //   3028: iload_2
    //   3029: ifne -> 4108
    //   3032: goto -> 3039
    //   3035: invokestatic a : (Ljava/lang/Throwable;)Ljava/lang/Throwable;
    //   3038: athrow
    //   3039: aload_3
    //   3040: getstatic burp/Zix.Zp : Ljava/lang/String;
    //   3043: getstatic burp/Zs83.ZT : Ljava/lang/Object;
    //   3046: checkcast java/math/BigInteger
    //   3049: invokevirtual intValue : ()I
    //   3052: bipush #32
    //   3054: irem
    //   3055: invokestatic abs : (I)I
    //   3058: invokevirtual charAt : (I)C
    //   3061: invokevirtual append : (C)Ljava/lang/StringBuilder;
    //   3064: pop
    //   3065: iload_2
    //   3066: ifne -> 4108
    //   3069: goto -> 3076
    //   3072: invokestatic a : (Ljava/lang/Throwable;)Ljava/lang/Throwable;
    //   3075: athrow
    //   3076: aload_3
    //   3077: getstatic burp/Zlrm.Zt : Ljava/lang/String;
    //   3080: getstatic burp/Zlhy.ZN : Ljava/lang/Object;
    //   3083: checkcast java/math/BigInteger
    //   3086: invokevirtual intValue : ()I
    //   3089: bipush #32
    //   3091: irem
    //   3092: invokestatic abs : (I)I
    //   3095: invokevirtual charAt : (I)C
    //   3098: invokevirtual append : (C)Ljava/lang/StringBuilder;
    //   3101: pop
    //   3102: iload_2
    //   3103: ifne -> 4108
    //   3106: goto -> 3113
    //   3109: invokestatic a : (Ljava/lang/Throwable;)Ljava/lang/Throwable;
    //   3112: athrow
    //   3113: aload_3
    //   3114: getstatic burp/Zram.Ze : Ljava/lang/String;
    //   3117: getstatic burp/Ztcv.ZY : Ljava/lang/Object;
    //   3120: checkcast java/math/BigInteger
    //   3123: invokevirtual intValue : ()I
    //   3126: bipush #32
    //   3128: irem
    //   3129: invokestatic abs : (I)I
    //   3132: invokevirtual charAt : (I)C
    //   3135: invokevirtual append : (C)Ljava/lang/StringBuilder;
    //   3138: pop
    //   3139: iload_2
    //   3140: ifne -> 4108
    //   3143: goto -> 3150
    //   3146: invokestatic a : (Ljava/lang/Throwable;)Ljava/lang/Throwable;
    //   3149: athrow
    //   3150: aload_3
    //   3151: getstatic burp/Ztfh.ZU : Ljava/lang/String;
    //   3154: getstatic burp/Zs_3.ZZ : Ljava/lang/Object;
    //   3157: checkcast java/math/BigInteger
    //   3160: invokevirtual intValue : ()I
    //   3163: bipush #32
    //   3165: irem
    //   3166: invokestatic abs : (I)I
    //   3169: invokevirtual charAt : (I)C
    //   3172: invokevirtual append : (C)Ljava/lang/StringBuilder;
    //   3175: pop
    //   3176: iload_2
    //   3177: ifne -> 4108
    //   3180: goto -> 3187
    //   3183: invokestatic a : (Ljava/lang/Throwable;)Ljava/lang/Throwable;
    //   3186: athrow
    //   3187: aload_3
    //   3188: getstatic burp/Zera.Zn : Ljava/lang/String;
    //   3191: getstatic burp/Zg4d.Zm : Ljava/lang/Object;
    //   3194: checkcast java/math/BigInteger
    //   3197: invokevirtual intValue : ()I
    //   3200: bipush #32
    //   3202: irem
    //   3203: invokestatic abs : (I)I
    //   3206: invokevirtual charAt : (I)C
    //   3209: invokevirtual append : (C)Ljava/lang/StringBuilder;
    //   3212: pop
    //   3213: iload_2
    //   3214: ifne -> 4108
    //   3217: goto -> 3224
    //   3220: invokestatic a : (Ljava/lang/Throwable;)Ljava/lang/Throwable;
    //   3223: athrow
    //   3224: aload_3
    //   3225: getstatic burp/Ze69.ZA : Ljava/lang/String;
    //   3228: getstatic burp/Zlck.Zr : Ljava/lang/Object;
    //   3231: checkcast java/math/BigInteger
    //   3234: invokevirtual intValue : ()I
    //   3237: bipush #32
    //   3239: irem
    //   3240: invokestatic abs : (I)I
    //   3243: invokevirtual charAt : (I)C
    //   3246: invokevirtual append : (C)Ljava/lang/StringBuilder;
    //   3249: pop
    //   3250: iload_2
    //   3251: ifne -> 4108
    //   3254: goto -> 3261
    //   3257: invokestatic a : (Ljava/lang/Throwable;)Ljava/lang/Throwable;
    //   3260: athrow
    //   3261: aload_3
    //   3262: getstatic burp/Zest.Zd : Ljava/lang/String;
    //   3265: getstatic burp/Zstb.ZC : Ljava/lang/Object;
    //   3268: checkcast java/math/BigInteger
    //   3271: invokevirtual intValue : ()I
    //   3274: bipush #32
    //   3276: irem
    //   3277: invokestatic abs : (I)I
    //   3280: invokevirtual charAt : (I)C
    //   3283: invokevirtual append : (C)Ljava/lang/StringBuilder;
    //   3286: pop
    //   3287: iload_2
    //   3288: ifne -> 4108
    //   3291: goto -> 3298
    //   3294: invokestatic a : (Ljava/lang/Throwable;)Ljava/lang/Throwable;
    //   3297: athrow
    //   3298: aload_3
    //   3299: getstatic burp/Ztdd.ZA : Ljava/lang/String;
    //   3302: getstatic burp/Zzc_.Zi : Ljava/lang/Object;
    //   3305: checkcast java/math/BigInteger
    //   3308: invokevirtual intValue : ()I
    //   3311: bipush #32
    //   3313: irem
    //   3314: invokestatic abs : (I)I
    //   3317: invokevirtual charAt : (I)C
    //   3320: invokevirtual append : (C)Ljava/lang/StringBuilder;
    //   3323: pop
    //   3324: iload_2
    //   3325: ifne -> 4108
    //   3328: goto -> 3335
    //   3331: invokestatic a : (Ljava/lang/Throwable;)Ljava/lang/Throwable;
    //   3334: athrow
    //   3335: aload_3
    //   3336: getstatic burp/Zlh8.ZY : Ljava/lang/String;
    //   3339: getstatic burp/Zzc_.Zi : Ljava/lang/Object;
    //   3342: checkcast java/math/BigInteger
    //   3345: invokevirtual intValue : ()I
    //   3348: bipush #32
    //   3350: irem
    //   3351: invokestatic abs : (I)I
    //   3354: invokevirtual charAt : (I)C
    //   3357: invokevirtual append : (C)Ljava/lang/StringBuilder;
    //   3360: pop
    //   3361: iload_2
    //   3362: ifne -> 4108
    //   3365: goto -> 3372
    //   3368: invokestatic a : (Ljava/lang/Throwable;)Ljava/lang/Throwable;
    //   3371: athrow
    //   3372: aload_3
    //   3373: getstatic burp/Zztk.Zf : Ljava/lang/String;
    //   3376: getstatic burp/Zex.ZO : Ljava/lang/Object;
    //   3379: checkcast java/math/BigInteger
    //   3382: invokevirtual intValue : ()I
    //   3385: bipush #32
    //   3387: irem
    //   3388: invokestatic abs : (I)I
    //   3391: invokevirtual charAt : (I)C
    //   3394: invokevirtual append : (C)Ljava/lang/StringBuilder;
    //   3397: pop
    //   3398: iload_2
    //   3399: ifne -> 4108
    //   3402: goto -> 3409
    //   3405: invokestatic a : (Ljava/lang/Throwable;)Ljava/lang/Throwable;
    //   3408: athrow
    //   3409: aload_3
    //   3410: getstatic burp/Zmyg.ZE : Ljava/lang/String;
    //   3413: getstatic burp/Zsj5.Zv : Ljava/lang/Object;
    //   3416: checkcast java/math/BigInteger
    //   3419: invokevirtual intValue : ()I
    //   3422: bipush #32
    //   3424: irem
    //   3425: invokestatic abs : (I)I
    //   3428: invokevirtual charAt : (I)C
    //   3431: invokevirtual append : (C)Ljava/lang/StringBuilder;
    //   3434: pop
    //   3435: iload_2
    //   3436: ifne -> 4108
    //   3439: goto -> 3446
    //   3442: invokestatic a : (Ljava/lang/Throwable;)Ljava/lang/Throwable;
    //   3445: athrow
    //   3446: aload_3
    //   3447: getstatic burp/Zg4k.ZB : Ljava/lang/String;
    //   3450: getstatic burp/Zsj5.Zv : Ljava/lang/Object;
    //   3453: checkcast java/math/BigInteger
    //   3456: invokevirtual intValue : ()I
    //   3459: bipush #32
    //   3461: irem
    //   3462: invokestatic abs : (I)I
    //   3465: invokevirtual charAt : (I)C
    //   3468: invokevirtual append : (C)Ljava/lang/StringBuilder;
    //   3471: pop
    //   3472: iload_2
    //   3473: ifne -> 4108
    //   3476: goto -> 3483
    //   3479: invokestatic a : (Ljava/lang/Throwable;)Ljava/lang/Throwable;
    //   3482: athrow
    //   3483: aload_3
    //   3484: getstatic burp/Zxn5.ZI : Ljava/lang/String;
    //   3487: getstatic burp/Zmyg.Zj : Ljava/lang/Object;
    //   3490: checkcast java/math/BigInteger
    //   3493: invokevirtual intValue : ()I
    //   3496: bipush #32
    //   3498: irem
    //   3499: invokestatic abs : (I)I
    //   3502: invokevirtual charAt : (I)C
    //   3505: invokevirtual append : (C)Ljava/lang/StringBuilder;
    //   3508: pop
    //   3509: iload_2
    //   3510: ifne -> 4108
    //   3513: goto -> 3520
    //   3516: invokestatic a : (Ljava/lang/Throwable;)Ljava/lang/Throwable;
    //   3519: athrow
    //   3520: aload_3
    //   3521: getstatic burp/Zm8w.ZL : Ljava/lang/String;
    //   3524: getstatic burp/Zztk.Za : Ljava/lang/Object;
    //   3527: checkcast java/math/BigInteger
    //   3530: invokevirtual intValue : ()I
    //   3533: bipush #32
    //   3535: irem
    //   3536: invokestatic abs : (I)I
    //   3539: invokevirtual charAt : (I)C
    //   3542: invokevirtual append : (C)Ljava/lang/StringBuilder;
    //   3545: pop
    //   3546: iload_2
    //   3547: ifne -> 4108
    //   3550: goto -> 3557
    //   3553: invokestatic a : (Ljava/lang/Throwable;)Ljava/lang/Throwable;
    //   3556: athrow
    //   3557: aload_3
    //   3558: getstatic burp/Zz0w.ZO : Ljava/lang/String;
    //   3561: getstatic burp/Zmr7.ZO : Ljava/lang/Object;
    //   3564: checkcast java/math/BigInteger
    //   3567: invokevirtual intValue : ()I
    //   3570: bipush #32
    //   3572: irem
    //   3573: invokestatic abs : (I)I
    //   3576: invokevirtual charAt : (I)C
    //   3579: invokevirtual append : (C)Ljava/lang/StringBuilder;
    //   3582: pop
    //   3583: iload_2
    //   3584: ifne -> 4108
    //   3587: goto -> 3594
    //   3590: invokestatic a : (Ljava/lang/Throwable;)Ljava/lang/Throwable;
    //   3593: athrow
    //   3594: aload_3
    //   3595: getstatic burp/Zrtv.ZA : Ljava/lang/String;
    //   3598: getstatic burp/Zz0w.ZF : Ljava/lang/Object;
    //   3601: checkcast java/math/BigInteger
    //   3604: invokevirtual intValue : ()I
    //   3607: bipush #32
    //   3609: irem
    //   3610: invokestatic abs : (I)I
    //   3613: invokevirtual charAt : (I)C
    //   3616: invokevirtual append : (C)Ljava/lang/StringBuilder;
    //   3619: pop
    //   3620: iload_2
    //   3621: ifne -> 4108
    //   3624: goto -> 3631
    //   3627: invokestatic a : (Ljava/lang/Throwable;)Ljava/lang/Throwable;
    //   3630: athrow
    //   3631: aload_3
    //   3632: getstatic burp/Zevr.Zk : Ljava/lang/String;
    //   3635: getstatic burp/Ztkh.Zh : Ljava/lang/Object;
    //   3638: checkcast java/math/BigInteger
    //   3641: invokevirtual intValue : ()I
    //   3644: bipush #32
    //   3646: irem
    //   3647: invokestatic abs : (I)I
    //   3650: invokevirtual charAt : (I)C
    //   3653: invokevirtual append : (C)Ljava/lang/StringBuilder;
    //   3656: pop
    //   3657: iload_2
    //   3658: ifne -> 4108
    //   3661: goto -> 3668
    //   3664: invokestatic a : (Ljava/lang/Throwable;)Ljava/lang/Throwable;
    //   3667: athrow
    //   3668: aload_3
    //   3669: getstatic burp/Ze8i.ZM : Ljava/lang/String;
    //   3672: getstatic burp/Zt3f.Zp : Ljava/lang/Object;
    //   3675: checkcast java/math/BigInteger
    //   3678: invokevirtual intValue : ()I
    //   3681: bipush #32
    //   3683: irem
    //   3684: invokestatic abs : (I)I
    //   3687: invokevirtual charAt : (I)C
    //   3690: invokevirtual append : (C)Ljava/lang/StringBuilder;
    //   3693: pop
    //   3694: iload_2
    //   3695: ifne -> 4108
    //   3698: goto -> 3705
    //   3701: invokestatic a : (Ljava/lang/Throwable;)Ljava/lang/Throwable;
    //   3704: athrow
    //   3705: aload_3
    //   3706: getstatic burp/Zs_v.Zn : Ljava/lang/String;
    //   3709: getstatic burp/Zmx6.ZJ : Ljava/lang/Object;
    //   3712: checkcast java/math/BigInteger
    //   3715: invokevirtual intValue : ()I
    //   3718: bipush #32
    //   3720: irem
    //   3721: invokestatic abs : (I)I
    //   3724: invokevirtual charAt : (I)C
    //   3727: invokevirtual append : (C)Ljava/lang/StringBuilder;
    //   3730: pop
    //   3731: iload_2
    //   3732: ifne -> 4108
    //   3735: goto -> 3742
    //   3738: invokestatic a : (Ljava/lang/Throwable;)Ljava/lang/Throwable;
    //   3741: athrow
    //   3742: aload_3
    //   3743: getstatic burp/Zrcy.Zq : Ljava/lang/String;
    //   3746: getstatic burp/Zm52.ZR : Ljava/lang/Object;
    //   3749: checkcast java/math/BigInteger
    //   3752: invokevirtual intValue : ()I
    //   3755: bipush #32
    //   3757: irem
    //   3758: invokestatic abs : (I)I
    //   3761: invokevirtual charAt : (I)C
    //   3764: invokevirtual append : (C)Ljava/lang/StringBuilder;
    //   3767: pop
    //   3768: iload_2
    //   3769: ifne -> 4108
    //   3772: goto -> 3779
    //   3775: invokestatic a : (Ljava/lang/Throwable;)Ljava/lang/Throwable;
    //   3778: athrow
    //   3779: aload_3
    //   3780: getstatic burp/Zzox.ZB : Ljava/lang/String;
    //   3783: getstatic burp/Zefo.ZW : Ljava/lang/Object;
    //   3786: checkcast java/math/BigInteger
    //   3789: invokevirtual intValue : ()I
    //   3792: bipush #32
    //   3794: irem
    //   3795: invokestatic abs : (I)I
    //   3798: invokevirtual charAt : (I)C
    //   3801: invokevirtual append : (C)Ljava/lang/StringBuilder;
    //   3804: pop
    //   3805: iload_2
    //   3806: ifne -> 4108
    //   3809: goto -> 3816
    //   3812: invokestatic a : (Ljava/lang/Throwable;)Ljava/lang/Throwable;
    //   3815: athrow
    //   3816: aload_3
    //   3817: getstatic burp/Zlrm.Zt : Ljava/lang/String;
    //   3820: getstatic burp/Ztcv.ZY : Ljava/lang/Object;
    //   3823: checkcast java/math/BigInteger
    //   3826: invokevirtual intValue : ()I
    //   3829: bipush #32
    //   3831: irem
    //   3832: invokestatic abs : (I)I
    //   3835: invokevirtual charAt : (I)C
    //   3838: invokevirtual append : (C)Ljava/lang/StringBuilder;
    //   3841: pop
    //   3842: iload_2
    //   3843: ifne -> 4108
    //   3846: goto -> 3853
    //   3849: invokestatic a : (Ljava/lang/Throwable;)Ljava/lang/Throwable;
    //   3852: athrow
    //   3853: aload_3
    //   3854: getstatic burp/Ztfh.ZU : Ljava/lang/String;
    //   3857: getstatic burp/Zs83.ZT : Ljava/lang/Object;
    //   3860: checkcast java/math/BigInteger
    //   3863: invokevirtual intValue : ()I
    //   3866: bipush #32
    //   3868: irem
    //   3869: invokestatic abs : (I)I
    //   3872: invokevirtual charAt : (I)C
    //   3875: invokevirtual append : (C)Ljava/lang/StringBuilder;
    //   3878: pop
    //   3879: iload_2
    //   3880: ifne -> 4108
    //   3883: goto -> 3890
    //   3886: invokestatic a : (Ljava/lang/Throwable;)Ljava/lang/Throwable;
    //   3889: athrow
    //   3890: aload_3
    //   3891: getstatic burp/Zt5j.ZR : Ljava/lang/String;
    //   3894: getstatic burp/Zmj8.Zz : Ljava/lang/Object;
    //   3897: checkcast java/math/BigInteger
    //   3900: invokevirtual intValue : ()I
    //   3903: bipush #32
    //   3905: irem
    //   3906: invokestatic abs : (I)I
    //   3909: invokevirtual charAt : (I)C
    //   3912: invokevirtual append : (C)Ljava/lang/StringBuilder;
    //   3915: pop
    //   3916: iload_2
    //   3917: ifne -> 4108
    //   3920: goto -> 3927
    //   3923: invokestatic a : (Ljava/lang/Throwable;)Ljava/lang/Throwable;
    //   3926: athrow
    //   3927: aload_3
    //   3928: getstatic burp/Zkt7.ZM : Ljava/lang/String;
    //   3931: getstatic burp/Zzo5.Zf : Ljava/lang/Object;
    //   3934: checkcast java/math/BigInteger
    //   3937: invokevirtual intValue : ()I
    //   3940: bipush #32
    //   3942: irem
    //   3943: invokestatic abs : (I)I
    //   3946: invokevirtual charAt : (I)C
    //   3949: invokevirtual append : (C)Ljava/lang/StringBuilder;
    //   3952: pop
    //   3953: iload_2
    //   3954: ifne -> 4108
    //   3957: goto -> 3964
    //   3960: invokestatic a : (Ljava/lang/Throwable;)Ljava/lang/Throwable;
    //   3963: athrow
    //   3964: aload_3
    //   3965: getstatic burp/Zlx5.ZP : Ljava/lang/String;
    //   3968: getstatic burp/Zltz.Zg : Ljava/lang/Object;
    //   3971: checkcast java/math/BigInteger
    //   3974: invokevirtual intValue : ()I
    //   3977: bipush #32
    //   3979: irem
    //   3980: invokestatic abs : (I)I
    //   3983: invokevirtual charAt : (I)C
    //   3986: invokevirtual append : (C)Ljava/lang/StringBuilder;
    //   3989: pop
    //   3990: iload_2
    //   3991: ifne -> 4108
    //   3994: goto -> 4001
    //   3997: invokestatic a : (Ljava/lang/Throwable;)Ljava/lang/Throwable;
    //   4000: athrow
    //   4001: aload_3
    //   4002: getstatic burp/Zlr.ZO : Ljava/lang/String;
    //   4005: getstatic burp/Zk7f.Za : Ljava/lang/Object;
    //   4008: checkcast java/math/BigInteger
    //   4011: invokevirtual intValue : ()I
    //   4014: bipush #32
    //   4016: irem
    //   4017: invokestatic abs : (I)I
    //   4020: invokevirtual charAt : (I)C
    //   4023: invokevirtual append : (C)Ljava/lang/StringBuilder;
    //   4026: pop
    //   4027: iload_2
    //   4028: ifne -> 4108
    //   4031: goto -> 4038
    //   4034: invokestatic a : (Ljava/lang/Throwable;)Ljava/lang/Throwable;
    //   4037: athrow
    //   4038: aload_3
    //   4039: getstatic burp/Zkt7.ZM : Ljava/lang/String;
    //   4042: getstatic burp/Zrof.ZB : Ljava/lang/Object;
    //   4045: checkcast java/math/BigInteger
    //   4048: invokevirtual intValue : ()I
    //   4051: bipush #32
    //   4053: irem
    //   4054: invokestatic abs : (I)I
    //   4057: invokevirtual charAt : (I)C
    //   4060: invokevirtual append : (C)Ljava/lang/StringBuilder;
    //   4063: pop
    //   4064: iload_2
    //   4065: ifne -> 4108
    //   4068: goto -> 4075
    //   4071: invokestatic a : (Ljava/lang/Throwable;)Ljava/lang/Throwable;
    //   4074: athrow
    //   4075: aload_3
    //   4076: getstatic burp/Zeuc.Zp : Ljava/lang/String;
    //   4079: getstatic burp/Zm4i.Zr : Ljava/lang/Object;
    //   4082: checkcast java/math/BigInteger
    //   4085: invokevirtual intValue : ()I
    //   4088: bipush #32
    //   4090: irem
    //   4091: invokestatic abs : (I)I
    //   4094: invokevirtual charAt : (I)C
    //   4097: invokevirtual append : (C)Ljava/lang/StringBuilder;
    //   4100: pop
    //   4101: goto -> 4108
    //   4104: invokestatic a : (Ljava/lang/Throwable;)Ljava/lang/Throwable;
    //   4107: athrow
    //   4108: iinc #4, 1
    //   4111: iload_2
    //   4112: ifne -> 2778
    //   4115: aload_3
    //   4116: invokevirtual toString : ()Ljava/lang/String;
    //   4119: putstatic burp/Ze5t.ZX : Ljava/lang/String;
    //   4122: sipush #-1877
    //   4125: sipush #11551
    //   4128: invokestatic a : (II)Ljava/lang/String;
    //   4131: iconst_1
    //   4132: ldc burp/Zb8v
    //   4134: invokevirtual getClassLoader : ()Ljava/lang/ClassLoader;
    //   4137: invokestatic forName : (Ljava/lang/String;ZLjava/lang/ClassLoader;)Ljava/lang/Class;
    //   4140: invokevirtual getDeclaredFields : ()[Ljava/lang/reflect/Field;
    //   4143: astore #4
    //   4145: aload #4
    //   4147: arraylength
    //   4148: istore #5
    //   4150: iconst_0
    //   4151: istore #6
    //   4153: iload #6
    //   4155: iload #5
    //   4157: if_icmpge -> 4295
    //   4160: aload #4
    //   4162: iload #6
    //   4164: aaload
    //   4165: astore #7
    //   4167: aload #7
    //   4169: invokevirtual getModifiers : ()I
    //   4172: invokestatic isStatic : (I)Z
    //   4175: ifne -> 4185
    //   4178: goto -> 4288
    //   4181: invokestatic a : (Ljava/lang/Throwable;)Ljava/lang/Throwable;
    //   4184: athrow
    //   4185: aload #7
    //   4187: invokevirtual getType : ()Ljava/lang/Class;
    //   4190: astore #8
    //   4192: aload #8
    //   4194: ifnull -> 4275
    //   4197: aload #8
    //   4199: invokevirtual isPrimitive : ()Z
    //   4202: ifne -> 4275
    //   4205: goto -> 4212
    //   4208: invokestatic a : (Ljava/lang/Throwable;)Ljava/lang/Throwable;
    //   4211: athrow
    //   4212: aload #8
    //   4214: invokevirtual getPackage : ()Ljava/lang/Package;
    //   4217: ifnull -> 4275
    //   4220: goto -> 4227
    //   4223: invokestatic a : (Ljava/lang/Throwable;)Ljava/lang/Throwable;
    //   4226: athrow
    //   4227: aload #8
    //   4229: invokevirtual getPackage : ()Ljava/lang/Package;
    //   4232: invokevirtual getName : ()Ljava/lang/String;
    //   4235: ifnull -> 4275
    //   4238: goto -> 4245
    //   4241: invokestatic a : (Ljava/lang/Throwable;)Ljava/lang/Throwable;
    //   4244: athrow
    //   4245: aload #8
    //   4247: invokevirtual getPackage : ()Ljava/lang/Package;
    //   4250: invokevirtual getName : ()Ljava/lang/String;
    //   4253: sipush #-1887
    //   4256: sipush #18179
    //   4259: invokestatic a : (II)Ljava/lang/String;
    //   4262: invokevirtual startsWith : (Ljava/lang/String;)Z
    //   4265: ifne -> 4275
    //   4268: goto -> 4275
    //   4271: invokestatic a : (Ljava/lang/Throwable;)Ljava/lang/Throwable;
    //   4274: athrow
    //   4275: aload #7
    //   4277: iconst_1
    //   4278: invokevirtual setAccessible : (Z)V
    //   4281: aload #7
    //   4283: aconst_null
    //   4284: invokevirtual get : (Ljava/lang/Object;)Ljava/lang/Object;
    //   4287: pop
    //   4288: iinc #6, 1
    //   4291: iload_2
    //   4292: ifne -> 4153
    //   4295: sipush #-1885
    //   4298: sipush #-29695
    //   4301: invokestatic a : (II)Ljava/lang/String;
    //   4304: invokestatic forName : (Ljava/lang/String;)Ljava/lang/Class;
    //   4307: invokevirtual getDeclaredMethods : ()[Ljava/lang/reflect/Method;
    //   4310: astore #4
    //   4312: aload #4
    //   4314: arraylength
    //   4315: istore #5
    //   4317: iconst_0
    //   4318: istore #6
    //   4320: iload #6
    //   4322: iload #5
    //   4324: if_icmpge -> 4457
    //   4327: aload #4
    //   4329: iload #6
    //   4331: aaload
    //   4332: astore #7
    //   4334: aload #7
    //   4336: invokevirtual getParameterTypes : ()[Ljava/lang/Class;
    //   4339: pop
    //   4340: aload #7
    //   4342: invokevirtual getModifiers : ()I
    //   4345: invokestatic isStatic : (I)Z
    //   4348: ifeq -> 4443
    //   4351: aload #7
    //   4353: invokevirtual getParameterTypes : ()[Ljava/lang/Class;
    //   4356: arraylength
    //   4357: iconst_2
    //   4358: if_icmpne -> 4443
    //   4361: goto -> 4368
    //   4364: invokestatic a : (Ljava/lang/Throwable;)Ljava/lang/Throwable;
    //   4367: athrow
    //   4368: aload #7
    //   4370: invokevirtual getReturnType : ()Ljava/lang/Class;
    //   4373: getstatic java/lang/Void.TYPE : Ljava/lang/Class;
    //   4376: invokevirtual equals : (Ljava/lang/Object;)Z
    //   4379: ifeq -> 4443
    //   4382: goto -> 4389
    //   4385: invokestatic a : (Ljava/lang/Throwable;)Ljava/lang/Throwable;
    //   4388: athrow
    //   4389: aload #7
    //   4391: iconst_1
    //   4392: invokevirtual setAccessible : (Z)V
    //   4395: aload #7
    //   4397: aconst_null
    //   4398: iconst_2
    //   4399: anewarray java/lang/Object
    //   4402: dup
    //   4403: iconst_0
    //   4404: aload_0
    //   4405: aastore
    //   4406: dup
    //   4407: iconst_1
    //   4408: aload_1
    //   4409: ifnonnull -> 4427
    //   4412: goto -> 4419
    //   4415: invokestatic a : (Ljava/lang/Throwable;)Ljava/lang/Throwable;
    //   4418: athrow
    //   4419: aload_1
    //   4420: goto -> 4434
    //   4423: invokestatic a : (Ljava/lang/Throwable;)Ljava/lang/Throwable;
    //   4426: athrow
    //   4427: aload_1
    //   4428: checkcast [B
    //   4431: invokevirtual clone : ()Ljava/lang/Object;
    //   4434: aastore
    //   4435: invokevirtual invoke : (Ljava/lang/Object;[Ljava/lang/Object;)Ljava/lang/Object;
    //   4438: pop
    //   4439: iload_2
    //   4440: ifne -> 4457
    //   4443: iinc #6, 1
    //   4446: iload_2
    //   4447: ifne -> 4320
    //   4450: goto -> 4457
    //   4453: invokestatic a : (Ljava/lang/Throwable;)Ljava/lang/Throwable;
    //   4456: athrow
    //   4457: getstatic burp/Zza8.Zh : Ljava/lang/Object;
    //   4460: checkcast java/math/BigInteger
    //   4463: invokevirtual intValue : ()I
    //   4466: i2l
    //   4467: invokestatic currentTimeMillis : ()J
    //   4470: ladd
    //   4471: getstatic burp/Zt0t.ZL : Ljava/lang/Object;
    //   4474: checkcast java/math/BigInteger
    //   4477: invokevirtual intValue : ()I
    //   4480: i2l
    //   4481: lcmp
    //   4482: ifge -> 4820
    //   4485: sipush #-1874
    //   4488: sipush #14697
    //   4491: invokestatic a : (II)Ljava/lang/String;
    //   4494: iconst_1
    //   4495: ldc burp/Zmlu
    //   4497: invokevirtual getClassLoader : ()Ljava/lang/ClassLoader;
    //   4500: invokestatic forName : (Ljava/lang/String;ZLjava/lang/ClassLoader;)Ljava/lang/Class;
    //   4503: invokevirtual getDeclaredFields : ()[Ljava/lang/reflect/Field;
    //   4506: astore #4
    //   4508: aload #4
    //   4510: arraylength
    //   4511: istore #5
    //   4513: iconst_0
    //   4514: istore #6
    //   4516: iload #6
    //   4518: iload #5
    //   4520: if_icmpge -> 4658
    //   4523: aload #4
    //   4525: iload #6
    //   4527: aaload
    //   4528: astore #7
    //   4530: aload #7
    //   4532: invokevirtual getModifiers : ()I
    //   4535: invokestatic isStatic : (I)Z
    //   4538: ifne -> 4548
    //   4541: goto -> 4651
    //   4544: invokestatic a : (Ljava/lang/Throwable;)Ljava/lang/Throwable;
    //   4547: athrow
    //   4548: aload #7
    //   4550: invokevirtual getType : ()Ljava/lang/Class;
    //   4553: astore #8
    //   4555: aload #8
    //   4557: ifnull -> 4638
    //   4560: aload #8
    //   4562: invokevirtual isPrimitive : ()Z
    //   4565: ifne -> 4638
    //   4568: goto -> 4575
    //   4571: invokestatic a : (Ljava/lang/Throwable;)Ljava/lang/Throwable;
    //   4574: athrow
    //   4575: aload #8
    //   4577: invokevirtual getPackage : ()Ljava/lang/Package;
    //   4580: ifnull -> 4638
    //   4583: goto -> 4590
    //   4586: invokestatic a : (Ljava/lang/Throwable;)Ljava/lang/Throwable;
    //   4589: athrow
    //   4590: aload #8
    //   4592: invokevirtual getPackage : ()Ljava/lang/Package;
    //   4595: invokevirtual getName : ()Ljava/lang/String;
    //   4598: ifnull -> 4638
    //   4601: goto -> 4608
    //   4604: invokestatic a : (Ljava/lang/Throwable;)Ljava/lang/Throwable;
    //   4607: athrow
    //   4608: aload #8
    //   4610: invokevirtual getPackage : ()Ljava/lang/Package;
    //   4613: invokevirtual getName : ()Ljava/lang/String;
    //   4616: sipush #-1879
    //   4619: sipush #-1585
    //   4622: invokestatic a : (II)Ljava/lang/String;
    //   4625: invokevirtual startsWith : (Ljava/lang/String;)Z
    //   4628: ifne -> 4638
    //   4631: goto -> 4638
    //   4634: invokestatic a : (Ljava/lang/Throwable;)Ljava/lang/Throwable;
    //   4637: athrow
    //   4638: aload #7
    //   4640: iconst_1
    //   4641: invokevirtual setAccessible : (Z)V
    //   4644: aload #7
    //   4646: aconst_null
    //   4647: invokevirtual get : (Ljava/lang/Object;)Ljava/lang/Object;
    //   4650: pop
    //   4651: iinc #6, 1
    //   4654: iload_2
    //   4655: ifne -> 4516
    //   4658: sipush #-1884
    //   4661: sipush #-13243
    //   4664: invokestatic a : (II)Ljava/lang/String;
    //   4667: invokestatic forName : (Ljava/lang/String;)Ljava/lang/Class;
    //   4670: invokevirtual getDeclaredMethods : ()[Ljava/lang/reflect/Method;
    //   4673: astore #4
    //   4675: aload #4
    //   4677: arraylength
    //   4678: istore #5
    //   4680: iconst_0
    //   4681: istore #6
    //   4683: iload #6
    //   4685: iload #5
    //   4687: if_icmpge -> 4820
    //   4690: aload #4
    //   4692: iload #6
    //   4694: aaload
    //   4695: astore #7
    //   4697: aload #7
    //   4699: invokevirtual getParameterTypes : ()[Ljava/lang/Class;
    //   4702: pop
    //   4703: aload #7
    //   4705: invokevirtual getModifiers : ()I
    //   4708: invokestatic isStatic : (I)Z
    //   4711: ifeq -> 4806
    //   4714: aload #7
    //   4716: invokevirtual getParameterTypes : ()[Ljava/lang/Class;
    //   4719: arraylength
    //   4720: iconst_2
    //   4721: if_icmpne -> 4806
    //   4724: goto -> 4731
    //   4727: invokestatic a : (Ljava/lang/Throwable;)Ljava/lang/Throwable;
    //   4730: athrow
    //   4731: aload #7
    //   4733: invokevirtual getReturnType : ()Ljava/lang/Class;
    //   4736: getstatic java/lang/Void.TYPE : Ljava/lang/Class;
    //   4739: invokevirtual equals : (Ljava/lang/Object;)Z
    //   4742: ifeq -> 4806
    //   4745: goto -> 4752
    //   4748: invokestatic a : (Ljava/lang/Throwable;)Ljava/lang/Throwable;
    //   4751: athrow
    //   4752: aload #7
    //   4754: iconst_1
    //   4755: invokevirtual setAccessible : (Z)V
    //   4758: aload #7
    //   4760: aconst_null
    //   4761: iconst_2
    //   4762: anewarray java/lang/Object
    //   4765: dup
    //   4766: iconst_0
    //   4767: aload_0
    //   4768: aastore
    //   4769: dup
    //   4770: iconst_1
    //   4771: aload_1
    //   4772: ifnonnull -> 4790
    //   4775: goto -> 4782
    //   4778: invokestatic a : (Ljava/lang/Throwable;)Ljava/lang/Throwable;
    //   4781: athrow
    //   4782: aload_1
    //   4783: goto -> 4797
    //   4786: invokestatic a : (Ljava/lang/Throwable;)Ljava/lang/Throwable;
    //   4789: athrow
    //   4790: aload_1
    //   4791: checkcast [B
    //   4794: invokevirtual clone : ()Ljava/lang/Object;
    //   4797: aastore
    //   4798: invokevirtual invoke : (Ljava/lang/Object;[Ljava/lang/Object;)Ljava/lang/Object;
    //   4801: pop
    //   4802: iload_2
    //   4803: ifne -> 4820
    //   4806: iinc #6, 1
    //   4809: iload_2
    //   4810: ifne -> 4683
    //   4813: goto -> 4820
    //   4816: invokestatic a : (Ljava/lang/Throwable;)Ljava/lang/Throwable;
    //   4819: athrow
    //   4820: getstatic burp/Zli5.Zt : Ljava/lang/Object;
    //   4823: checkcast java/math/BigInteger
    //   4826: invokevirtual toByteArray : ()[B
    //   4829: astore #4
    //   4831: bipush #32
    //   4833: newarray int
    //   4835: dup
    //   4836: iconst_0
    //   4837: ldc 943331329
    //   4839: iastore
    //   4840: dup
    //   4841: iconst_1
    //   4842: ldc 170788368
    //   4844: iastore
    //   4845: dup
    //   4846: iconst_2
    //   4847: ldc 1008414755
    //   4849: iastore
    //   4850: dup
    //   4851: iconst_3
    //   4852: ldc 187049985
    //   4854: iastore
    //   4855: dup
    //   4856: iconst_4
    //   4857: ldc 1010368540
    //   4859: iastore
    //   4860: dup
    //   4861: iconst_5
    //   4862: ldc 220604441
    //   4864: iastore
    //   4865: dup
    //   4866: bipush #6
    //   4868: ldc 940377620
    //   4870: iastore
    //   4871: dup
    //   4872: bipush #7
    //   4874: ldc 255209728
    //   4876: iastore
    //   4877: dup
    //   4878: bipush #8
    //   4880: ldc 689771012
    //   4882: iastore
    //   4883: dup
    //   4884: bipush #9
    //   4886: ldc 221709344
    //   4888: iastore
    //   4889: dup
    //   4890: bipush #10
    //   4892: ldc 957157408
    //   4894: iastore
    //   4895: dup
    //   4896: bipush #11
    //   4898: ldc 892536332
    //   4900: iastore
    //   4901: dup
    //   4902: bipush #12
    //   4904: ldc 722417666
    //   4906: iastore
    //   4907: dup
    //   4908: bipush #13
    //   4910: ldc 1026621720
    //   4912: iastore
    //   4913: dup
    //   4914: bipush #14
    //   4916: ldc 655302664
    //   4918: iastore
    //   4919: dup
    //   4920: bipush #15
    //   4922: ldc 890966315
    //   4924: iastore
    //   4925: dup
    //   4926: bipush #16
    //   4928: ldc 187632156
    //   4930: iastore
    //   4931: dup
    //   4932: bipush #17
    //   4934: ldc 874189824
    //   4936: iastore
    //   4937: dup
    //   4938: bipush #18
    //   4940: ldc 254150144
    //   4942: iastore
    //   4943: dup
    //   4944: bipush #19
    //   4946: ldc 924386310
    //   4948: iastore
    //   4949: dup
    //   4950: bipush #20
    //   4952: ldc 121057538
    //   4954: iastore
    //   4955: dup
    //   4956: bipush #21
    //   4958: ldc 840500228
    //   4960: iastore
    //   4961: dup
    //   4962: bipush #22
    //   4964: ldc 389160971
    //   4966: iastore
    //   4967: dup
    //   4968: bipush #23
    //   4970: ldc 907870729
    //   4972: iastore
    //   4973: dup
    //   4974: bipush #24
    //   4976: ldc 389426184
    //   4978: iastore
    //   4979: dup
    //   4980: bipush #25
    //   4982: ldc 973875457
    //   4984: iastore
    //   4985: dup
    //   4986: bipush #26
    //   4988: ldc 372376604
    //   4990: iastore
    //   4991: dup
    //   4992: bipush #27
    //   4994: ldc 707731490
    //   4996: iastore
    //   4997: dup
    //   4998: bipush #28
    //   5000: ldc 1043334948
    //   5002: iastore
    //   5003: dup
    //   5004: bipush #29
    //   5006: ldc 439222784
    //   5008: iastore
    //   5009: dup
    //   5010: bipush #30
    //   5012: ldc 876216579
    //   5014: iastore
    //   5015: dup
    //   5016: bipush #31
    //   5018: ldc 455999525
    //   5020: iastore
    //   5021: astore #6
    //   5023: bipush #8
    //   5025: aload #4
    //   5027: arraylength
    //   5028: bipush #8
    //   5030: irem
    //   5031: isub
    //   5032: istore #7
    //   5034: aload #4
    //   5036: arraylength
    //   5037: iload #7
    //   5039: iadd
    //   5040: newarray byte
    //   5042: astore #8
    //   5044: iconst_0
    //   5045: istore #9
    //   5047: iload #9
    //   5049: aload #4
    //   5051: arraylength
    //   5052: if_icmpge -> 5072
    //   5055: aload #8
    //   5057: iload #9
    //   5059: aload #4
    //   5061: iload #9
    //   5063: baload
    //   5064: bastore
    //   5065: iinc #9, 1
    //   5068: iload_2
    //   5069: ifne -> 5047
    //   5072: aload #4
    //   5074: arraylength
    //   5075: istore #9
    //   5077: iload #9
    //   5079: aload #8
    //   5081: arraylength
    //   5082: if_icmpge -> 5100
    //   5085: aload #8
    //   5087: iload #9
    //   5089: iload #7
    //   5091: i2b
    //   5092: bastore
    //   5093: iinc #9, 1
    //   5096: iload_2
    //   5097: ifne -> 5077
    //   5100: aload #8
    //   5102: astore #4
    //   5104: bipush #64
    //   5106: newarray int
    //   5108: dup
    //   5109: iconst_0
    //   5110: ldc 16843776
    //   5112: iastore
    //   5113: dup
    //   5114: iconst_1
    //   5115: iconst_0
    //   5116: iastore
    //   5117: dup
    //   5118: iconst_2
    //   5119: ldc 65536
    //   5121: iastore
    //   5122: dup
    //   5123: iconst_3
    //   5124: ldc 16843780
    //   5126: iastore
    //   5127: dup
    //   5128: iconst_4
    //   5129: ldc 16842756
    //   5131: iastore
    //   5132: dup
    //   5133: iconst_5
    //   5134: ldc 66564
    //   5136: iastore
    //   5137: dup
    //   5138: bipush #6
    //   5140: iconst_4
    //   5141: iastore
    //   5142: dup
    //   5143: bipush #7
    //   5145: ldc 65536
    //   5147: iastore
    //   5148: dup
    //   5149: bipush #8
    //   5151: sipush #1024
    //   5154: iastore
    //   5155: dup
    //   5156: bipush #9
    //   5158: ldc 16843776
    //   5160: iastore
    //   5161: dup
    //   5162: bipush #10
    //   5164: ldc 16843780
    //   5166: iastore
    //   5167: dup
    //   5168: bipush #11
    //   5170: sipush #1024
    //   5173: iastore
    //   5174: dup
    //   5175: bipush #12
    //   5177: ldc 16778244
    //   5179: iastore
    //   5180: dup
    //   5181: bipush #13
    //   5183: ldc 16842756
    //   5185: iastore
    //   5186: dup
    //   5187: bipush #14
    //   5189: ldc 16777216
    //   5191: iastore
    //   5192: dup
    //   5193: bipush #15
    //   5195: iconst_4
    //   5196: iastore
    //   5197: dup
    //   5198: bipush #16
    //   5200: sipush #1028
    //   5203: iastore
    //   5204: dup
    //   5205: bipush #17
    //   5207: ldc 16778240
    //   5209: iastore
    //   5210: dup
    //   5211: bipush #18
    //   5213: ldc 16778240
    //   5215: iastore
    //   5216: dup
    //   5217: bipush #19
    //   5219: ldc 66560
    //   5221: iastore
    //   5222: dup
    //   5223: bipush #20
    //   5225: ldc 66560
    //   5227: iastore
    //   5228: dup
    //   5229: bipush #21
    //   5231: ldc 16842752
    //   5233: iastore
    //   5234: dup
    //   5235: bipush #22
    //   5237: ldc 16842752
    //   5239: iastore
    //   5240: dup
    //   5241: bipush #23
    //   5243: ldc 16778244
    //   5245: iastore
    //   5246: dup
    //   5247: bipush #24
    //   5249: ldc 65540
    //   5251: iastore
    //   5252: dup
    //   5253: bipush #25
    //   5255: ldc 16777220
    //   5257: iastore
    //   5258: dup
    //   5259: bipush #26
    //   5261: ldc 16777220
    //   5263: iastore
    //   5264: dup
    //   5265: bipush #27
    //   5267: ldc 65540
    //   5269: iastore
    //   5270: dup
    //   5271: bipush #28
    //   5273: iconst_0
    //   5274: iastore
    //   5275: dup
    //   5276: bipush #29
    //   5278: sipush #1028
    //   5281: iastore
    //   5282: dup
    //   5283: bipush #30
    //   5285: ldc 66564
    //   5287: iastore
    //   5288: dup
    //   5289: bipush #31
    //   5291: ldc 16777216
    //   5293: iastore
    //   5294: dup
    //   5295: bipush #32
    //   5297: ldc 65536
    //   5299: iastore
    //   5300: dup
    //   5301: bipush #33
    //   5303: ldc 16843780
    //   5305: iastore
    //   5306: dup
    //   5307: bipush #34
    //   5309: iconst_4
    //   5310: iastore
    //   5311: dup
    //   5312: bipush #35
    //   5314: ldc 16842752
    //   5316: iastore
    //   5317: dup
    //   5318: bipush #36
    //   5320: ldc 16843776
    //   5322: iastore
    //   5323: dup
    //   5324: bipush #37
    //   5326: ldc 16777216
    //   5328: iastore
    //   5329: dup
    //   5330: bipush #38
    //   5332: ldc 16777216
    //   5334: iastore
    //   5335: dup
    //   5336: bipush #39
    //   5338: sipush #1024
    //   5341: iastore
    //   5342: dup
    //   5343: bipush #40
    //   5345: ldc 16842756
    //   5347: iastore
    //   5348: dup
    //   5349: bipush #41
    //   5351: ldc 65536
    //   5353: iastore
    //   5354: dup
    //   5355: bipush #42
    //   5357: ldc 66560
    //   5359: iastore
    //   5360: dup
    //   5361: bipush #43
    //   5363: ldc 16777220
    //   5365: iastore
    //   5366: dup
    //   5367: bipush #44
    //   5369: sipush #1024
    //   5372: iastore
    //   5373: dup
    //   5374: bipush #45
    //   5376: iconst_4
    //   5377: iastore
    //   5378: dup
    //   5379: bipush #46
    //   5381: ldc 16778244
    //   5383: iastore
    //   5384: dup
    //   5385: bipush #47
    //   5387: ldc 66564
    //   5389: iastore
    //   5390: dup
    //   5391: bipush #48
    //   5393: ldc 16843780
    //   5395: iastore
    //   5396: dup
    //   5397: bipush #49
    //   5399: ldc 65540
    //   5401: iastore
    //   5402: dup
    //   5403: bipush #50
    //   5405: ldc 16842752
    //   5407: iastore
    //   5408: dup
    //   5409: bipush #51
    //   5411: ldc 16778244
    //   5413: iastore
    //   5414: dup
    //   5415: bipush #52
    //   5417: ldc 16777220
    //   5419: iastore
    //   5420: dup
    //   5421: bipush #53
    //   5423: sipush #1028
    //   5426: iastore
    //   5427: dup
    //   5428: bipush #54
    //   5430: ldc 66564
    //   5432: iastore
    //   5433: dup
    //   5434: bipush #55
    //   5436: ldc 16843776
    //   5438: iastore
    //   5439: dup
    //   5440: bipush #56
    //   5442: sipush #1028
    //   5445: iastore
    //   5446: dup
    //   5447: bipush #57
    //   5449: ldc 16778240
    //   5451: iastore
    //   5452: dup
    //   5453: bipush #58
    //   5455: ldc 16778240
    //   5457: iastore
    //   5458: dup
    //   5459: bipush #59
    //   5461: iconst_0
    //   5462: iastore
    //   5463: dup
    //   5464: bipush #60
    //   5466: ldc 65540
    //   5468: iastore
    //   5469: dup
    //   5470: bipush #61
    //   5472: ldc 66560
    //   5474: iastore
    //   5475: dup
    //   5476: bipush #62
    //   5478: iconst_0
    //   5479: iastore
    //   5480: dup
    //   5481: bipush #63
    //   5483: ldc 16842756
    //   5485: iastore
    //   5486: astore #9
    //   5488: bipush #64
    //   5490: newarray int
    //   5492: dup
    //   5493: iconst_0
    //   5494: ldc -2146402272
    //   5496: iastore
    //   5497: dup
    //   5498: iconst_1
    //   5499: ldc -2147450880
    //   5501: iastore
    //   5502: dup
    //   5503: iconst_2
    //   5504: ldc 32768
    //   5506: iastore
    //   5507: dup
    //   5508: iconst_3
    //   5509: ldc 1081376
    //   5511: iastore
    //   5512: dup
    //   5513: iconst_4
    //   5514: ldc 1048576
    //   5516: iastore
    //   5517: dup
    //   5518: iconst_5
    //   5519: bipush #32
    //   5521: iastore
    //   5522: dup
    //   5523: bipush #6
    //   5525: ldc -2146435040
    //   5527: iastore
    //   5528: dup
    //   5529: bipush #7
    //   5531: ldc -2147450848
    //   5533: iastore
    //   5534: dup
    //   5535: bipush #8
    //   5537: ldc -2147483616
    //   5539: iastore
    //   5540: dup
    //   5541: bipush #9
    //   5543: ldc -2146402272
    //   5545: iastore
    //   5546: dup
    //   5547: bipush #10
    //   5549: ldc -2146402304
    //   5551: iastore
    //   5552: dup
    //   5553: bipush #11
    //   5555: ldc -2147483648
    //   5557: iastore
    //   5558: dup
    //   5559: bipush #12
    //   5561: ldc -2147450880
    //   5563: iastore
    //   5564: dup
    //   5565: bipush #13
    //   5567: ldc 1048576
    //   5569: iastore
    //   5570: dup
    //   5571: bipush #14
    //   5573: bipush #32
    //   5575: iastore
    //   5576: dup
    //   5577: bipush #15
    //   5579: ldc -2146435040
    //   5581: iastore
    //   5582: dup
    //   5583: bipush #16
    //   5585: ldc 1081344
    //   5587: iastore
    //   5588: dup
    //   5589: bipush #17
    //   5591: ldc 1048608
    //   5593: iastore
    //   5594: dup
    //   5595: bipush #18
    //   5597: ldc -2147450848
    //   5599: iastore
    //   5600: dup
    //   5601: bipush #19
    //   5603: iconst_0
    //   5604: iastore
    //   5605: dup
    //   5606: bipush #20
    //   5608: ldc -2147483648
    //   5610: iastore
    //   5611: dup
    //   5612: bipush #21
    //   5614: ldc 32768
    //   5616: iastore
    //   5617: dup
    //   5618: bipush #22
    //   5620: ldc 1081376
    //   5622: iastore
    //   5623: dup
    //   5624: bipush #23
    //   5626: ldc -2146435072
    //   5628: iastore
    //   5629: dup
    //   5630: bipush #24
    //   5632: ldc 1048608
    //   5634: iastore
    //   5635: dup
    //   5636: bipush #25
    //   5638: ldc -2147483616
    //   5640: iastore
    //   5641: dup
    //   5642: bipush #26
    //   5644: iconst_0
    //   5645: iastore
    //   5646: dup
    //   5647: bipush #27
    //   5649: ldc 1081344
    //   5651: iastore
    //   5652: dup
    //   5653: bipush #28
    //   5655: ldc 32800
    //   5657: iastore
    //   5658: dup
    //   5659: bipush #29
    //   5661: ldc -2146402304
    //   5663: iastore
    //   5664: dup
    //   5665: bipush #30
    //   5667: ldc -2146435072
    //   5669: iastore
    //   5670: dup
    //   5671: bipush #31
    //   5673: ldc 32800
    //   5675: iastore
    //   5676: dup
    //   5677: bipush #32
    //   5679: iconst_0
    //   5680: iastore
    //   5681: dup
    //   5682: bipush #33
    //   5684: ldc 1081376
    //   5686: iastore
    //   5687: dup
    //   5688: bipush #34
    //   5690: ldc -2146435040
    //   5692: iastore
    //   5693: dup
    //   5694: bipush #35
    //   5696: ldc 1048576
    //   5698: iastore
    //   5699: dup
    //   5700: bipush #36
    //   5702: ldc -2147450848
    //   5704: iastore
    //   5705: dup
    //   5706: bipush #37
    //   5708: ldc -2146435072
    //   5710: iastore
    //   5711: dup
    //   5712: bipush #38
    //   5714: ldc -2146402304
    //   5716: iastore
    //   5717: dup
    //   5718: bipush #39
    //   5720: ldc 32768
    //   5722: iastore
    //   5723: dup
    //   5724: bipush #40
    //   5726: ldc -2146435072
    //   5728: iastore
    //   5729: dup
    //   5730: bipush #41
    //   5732: ldc -2147450880
    //   5734: iastore
    //   5735: dup
    //   5736: bipush #42
    //   5738: bipush #32
    //   5740: iastore
    //   5741: dup
    //   5742: bipush #43
    //   5744: ldc -2146402272
    //   5746: iastore
    //   5747: dup
    //   5748: bipush #44
    //   5750: ldc 1081376
    //   5752: iastore
    //   5753: dup
    //   5754: bipush #45
    //   5756: bipush #32
    //   5758: iastore
    //   5759: dup
    //   5760: bipush #46
    //   5762: ldc 32768
    //   5764: iastore
    //   5765: dup
    //   5766: bipush #47
    //   5768: ldc -2147483648
    //   5770: iastore
    //   5771: dup
    //   5772: bipush #48
    //   5774: ldc 32800
    //   5776: iastore
    //   5777: dup
    //   5778: bipush #49
    //   5780: ldc -2146402304
    //   5782: iastore
    //   5783: dup
    //   5784: bipush #50
    //   5786: ldc 1048576
    //   5788: iastore
    //   5789: dup
    //   5790: bipush #51
    //   5792: ldc -2147483616
    //   5794: iastore
    //   5795: dup
    //   5796: bipush #52
    //   5798: ldc 1048608
    //   5800: iastore
    //   5801: dup
    //   5802: bipush #53
    //   5804: ldc -2147450848
    //   5806: iastore
    //   5807: dup
    //   5808: bipush #54
    //   5810: ldc -2147483616
    //   5812: iastore
    //   5813: dup
    //   5814: bipush #55
    //   5816: ldc 1048608
    //   5818: iastore
    //   5819: dup
    //   5820: bipush #56
    //   5822: ldc 1081344
    //   5824: iastore
    //   5825: dup
    //   5826: bipush #57
    //   5828: iconst_0
    //   5829: iastore
    //   5830: dup
    //   5831: bipush #58
    //   5833: ldc -2147450880
    //   5835: iastore
    //   5836: dup
    //   5837: bipush #59
    //   5839: ldc 32800
    //   5841: iastore
    //   5842: dup
    //   5843: bipush #60
    //   5845: ldc -2147483648
    //   5847: iastore
    //   5848: dup
    //   5849: bipush #61
    //   5851: ldc -2146435040
    //   5853: iastore
    //   5854: dup
    //   5855: bipush #62
    //   5857: ldc -2146402272
    //   5859: iastore
    //   5860: dup
    //   5861: bipush #63
    //   5863: ldc 1081344
    //   5865: iastore
    //   5866: astore #10
    //   5868: bipush #64
    //   5870: newarray int
    //   5872: dup
    //   5873: iconst_0
    //   5874: sipush #520
    //   5877: iastore
    //   5878: dup
    //   5879: iconst_1
    //   5880: ldc 134349312
    //   5882: iastore
    //   5883: dup
    //   5884: iconst_2
    //   5885: iconst_0
    //   5886: iastore
    //   5887: dup
    //   5888: iconst_3
    //   5889: ldc 134348808
    //   5891: iastore
    //   5892: dup
    //   5893: iconst_4
    //   5894: ldc 134218240
    //   5896: iastore
    //   5897: dup
    //   5898: iconst_5
    //   5899: iconst_0
    //   5900: iastore
    //   5901: dup
    //   5902: bipush #6
    //   5904: ldc 131592
    //   5906: iastore
    //   5907: dup
    //   5908: bipush #7
    //   5910: ldc 134218240
    //   5912: iastore
    //   5913: dup
    //   5914: bipush #8
    //   5916: ldc 131080
    //   5918: iastore
    //   5919: dup
    //   5920: bipush #9
    //   5922: ldc 134217736
    //   5924: iastore
    //   5925: dup
    //   5926: bipush #10
    //   5928: ldc 134217736
    //   5930: iastore
    //   5931: dup
    //   5932: bipush #11
    //   5934: ldc 131072
    //   5936: iastore
    //   5937: dup
    //   5938: bipush #12
    //   5940: ldc 134349320
    //   5942: iastore
    //   5943: dup
    //   5944: bipush #13
    //   5946: ldc 131080
    //   5948: iastore
    //   5949: dup
    //   5950: bipush #14
    //   5952: ldc 134348800
    //   5954: iastore
    //   5955: dup
    //   5956: bipush #15
    //   5958: sipush #520
    //   5961: iastore
    //   5962: dup
    //   5963: bipush #16
    //   5965: ldc 134217728
    //   5967: iastore
    //   5968: dup
    //   5969: bipush #17
    //   5971: bipush #8
    //   5973: iastore
    //   5974: dup
    //   5975: bipush #18
    //   5977: ldc 134349312
    //   5979: iastore
    //   5980: dup
    //   5981: bipush #19
    //   5983: sipush #512
    //   5986: iastore
    //   5987: dup
    //   5988: bipush #20
    //   5990: ldc 131584
    //   5992: iastore
    //   5993: dup
    //   5994: bipush #21
    //   5996: ldc 134348800
    //   5998: iastore
    //   5999: dup
    //   6000: bipush #22
    //   6002: ldc 134348808
    //   6004: iastore
    //   6005: dup
    //   6006: bipush #23
    //   6008: ldc 131592
    //   6010: iastore
    //   6011: dup
    //   6012: bipush #24
    //   6014: ldc 134218248
    //   6016: iastore
    //   6017: dup
    //   6018: bipush #25
    //   6020: ldc 131584
    //   6022: iastore
    //   6023: dup
    //   6024: bipush #26
    //   6026: ldc 131072
    //   6028: iastore
    //   6029: dup
    //   6030: bipush #27
    //   6032: ldc 134218248
    //   6034: iastore
    //   6035: dup
    //   6036: bipush #28
    //   6038: bipush #8
    //   6040: iastore
    //   6041: dup
    //   6042: bipush #29
    //   6044: ldc 134349320
    //   6046: iastore
    //   6047: dup
    //   6048: bipush #30
    //   6050: sipush #512
    //   6053: iastore
    //   6054: dup
    //   6055: bipush #31
    //   6057: ldc 134217728
    //   6059: iastore
    //   6060: dup
    //   6061: bipush #32
    //   6063: ldc 134349312
    //   6065: iastore
    //   6066: dup
    //   6067: bipush #33
    //   6069: ldc 134217728
    //   6071: iastore
    //   6072: dup
    //   6073: bipush #34
    //   6075: ldc 131080
    //   6077: iastore
    //   6078: dup
    //   6079: bipush #35
    //   6081: sipush #520
    //   6084: iastore
    //   6085: dup
    //   6086: bipush #36
    //   6088: ldc 131072
    //   6090: iastore
    //   6091: dup
    //   6092: bipush #37
    //   6094: ldc 134349312
    //   6096: iastore
    //   6097: dup
    //   6098: bipush #38
    //   6100: ldc 134218240
    //   6102: iastore
    //   6103: dup
    //   6104: bipush #39
    //   6106: iconst_0
    //   6107: iastore
    //   6108: dup
    //   6109: bipush #40
    //   6111: sipush #512
    //   6114: iastore
    //   6115: dup
    //   6116: bipush #41
    //   6118: ldc 131080
    //   6120: iastore
    //   6121: dup
    //   6122: bipush #42
    //   6124: ldc 134349320
    //   6126: iastore
    //   6127: dup
    //   6128: bipush #43
    //   6130: ldc 134218240
    //   6132: iastore
    //   6133: dup
    //   6134: bipush #44
    //   6136: ldc 134217736
    //   6138: iastore
    //   6139: dup
    //   6140: bipush #45
    //   6142: sipush #512
    //   6145: iastore
    //   6146: dup
    //   6147: bipush #46
    //   6149: iconst_0
    //   6150: iastore
    //   6151: dup
    //   6152: bipush #47
    //   6154: ldc 134348808
    //   6156: iastore
    //   6157: dup
    //   6158: bipush #48
    //   6160: ldc 134218248
    //   6162: iastore
    //   6163: dup
    //   6164: bipush #49
    //   6166: ldc 131072
    //   6168: iastore
    //   6169: dup
    //   6170: bipush #50
    //   6172: ldc 134217728
    //   6174: iastore
    //   6175: dup
    //   6176: bipush #51
    //   6178: ldc 134349320
    //   6180: iastore
    //   6181: dup
    //   6182: bipush #52
    //   6184: bipush #8
    //   6186: iastore
    //   6187: dup
    //   6188: bipush #53
    //   6190: ldc 131592
    //   6192: iastore
    //   6193: dup
    //   6194: bipush #54
    //   6196: ldc 131584
    //   6198: iastore
    //   6199: dup
    //   6200: bipush #55
    //   6202: ldc 134217736
    //   6204: iastore
    //   6205: dup
    //   6206: bipush #56
    //   6208: ldc 134348800
    //   6210: iastore
    //   6211: dup
    //   6212: bipush #57
    //   6214: ldc 134218248
    //   6216: iastore
    //   6217: dup
    //   6218: bipush #58
    //   6220: sipush #520
    //   6223: iastore
    //   6224: dup
    //   6225: bipush #59
    //   6227: ldc 134348800
    //   6229: iastore
    //   6230: dup
    //   6231: bipush #60
    //   6233: ldc 131592
    //   6235: iastore
    //   6236: dup
    //   6237: bipush #61
    //   6239: bipush #8
    //   6241: iastore
    //   6242: dup
    //   6243: bipush #62
    //   6245: ldc 134348808
    //   6247: iastore
    //   6248: dup
    //   6249: bipush #63
    //   6251: ldc 131584
    //   6253: iastore
    //   6254: astore #11
    //   6256: bipush #64
    //   6258: newarray int
    //   6260: dup
    //   6261: iconst_0
    //   6262: ldc 8396801
    //   6264: iastore
    //   6265: dup
    //   6266: iconst_1
    //   6267: sipush #8321
    //   6270: iastore
    //   6271: dup
    //   6272: iconst_2
    //   6273: sipush #8321
    //   6276: iastore
    //   6277: dup
    //   6278: iconst_3
    //   6279: sipush #128
    //   6282: iastore
    //   6283: dup
    //   6284: iconst_4
    //   6285: ldc 8396928
    //   6287: iastore
    //   6288: dup
    //   6289: iconst_5
    //   6290: ldc 8388737
    //   6292: iastore
    //   6293: dup
    //   6294: bipush #6
    //   6296: ldc 8388609
    //   6298: iastore
    //   6299: dup
    //   6300: bipush #7
    //   6302: sipush #8193
    //   6305: iastore
    //   6306: dup
    //   6307: bipush #8
    //   6309: iconst_0
    //   6310: iastore
    //   6311: dup
    //   6312: bipush #9
    //   6314: ldc 8396800
    //   6316: iastore
    //   6317: dup
    //   6318: bipush #10
    //   6320: ldc 8396800
    //   6322: iastore
    //   6323: dup
    //   6324: bipush #11
    //   6326: ldc 8396929
    //   6328: iastore
    //   6329: dup
    //   6330: bipush #12
    //   6332: sipush #129
    //   6335: iastore
    //   6336: dup
    //   6337: bipush #13
    //   6339: iconst_0
    //   6340: iastore
    //   6341: dup
    //   6342: bipush #14
    //   6344: ldc 8388736
    //   6346: iastore
    //   6347: dup
    //   6348: bipush #15
    //   6350: ldc 8388609
    //   6352: iastore
    //   6353: dup
    //   6354: bipush #16
    //   6356: iconst_1
    //   6357: iastore
    //   6358: dup
    //   6359: bipush #17
    //   6361: sipush #8192
    //   6364: iastore
    //   6365: dup
    //   6366: bipush #18
    //   6368: ldc 8388608
    //   6370: iastore
    //   6371: dup
    //   6372: bipush #19
    //   6374: ldc 8396801
    //   6376: iastore
    //   6377: dup
    //   6378: bipush #20
    //   6380: sipush #128
    //   6383: iastore
    //   6384: dup
    //   6385: bipush #21
    //   6387: ldc 8388608
    //   6389: iastore
    //   6390: dup
    //   6391: bipush #22
    //   6393: sipush #8193
    //   6396: iastore
    //   6397: dup
    //   6398: bipush #23
    //   6400: sipush #8320
    //   6403: iastore
    //   6404: dup
    //   6405: bipush #24
    //   6407: ldc 8388737
    //   6409: iastore
    //   6410: dup
    //   6411: bipush #25
    //   6413: iconst_1
    //   6414: iastore
    //   6415: dup
    //   6416: bipush #26
    //   6418: sipush #8320
    //   6421: iastore
    //   6422: dup
    //   6423: bipush #27
    //   6425: ldc 8388736
    //   6427: iastore
    //   6428: dup
    //   6429: bipush #28
    //   6431: sipush #8192
    //   6434: iastore
    //   6435: dup
    //   6436: bipush #29
    //   6438: ldc 8396928
    //   6440: iastore
    //   6441: dup
    //   6442: bipush #30
    //   6444: ldc 8396929
    //   6446: iastore
    //   6447: dup
    //   6448: bipush #31
    //   6450: sipush #129
    //   6453: iastore
    //   6454: dup
    //   6455: bipush #32
    //   6457: ldc 8388736
    //   6459: iastore
    //   6460: dup
    //   6461: bipush #33
    //   6463: ldc 8388609
    //   6465: iastore
    //   6466: dup
    //   6467: bipush #34
    //   6469: ldc 8396800
    //   6471: iastore
    //   6472: dup
    //   6473: bipush #35
    //   6475: ldc 8396929
    //   6477: iastore
    //   6478: dup
    //   6479: bipush #36
    //   6481: sipush #129
    //   6484: iastore
    //   6485: dup
    //   6486: bipush #37
    //   6488: iconst_0
    //   6489: iastore
    //   6490: dup
    //   6491: bipush #38
    //   6493: iconst_0
    //   6494: iastore
    //   6495: dup
    //   6496: bipush #39
    //   6498: ldc 8396800
    //   6500: iastore
    //   6501: dup
    //   6502: bipush #40
    //   6504: sipush #8320
    //   6507: iastore
    //   6508: dup
    //   6509: bipush #41
    //   6511: ldc 8388736
    //   6513: iastore
    //   6514: dup
    //   6515: bipush #42
    //   6517: ldc 8388737
    //   6519: iastore
    //   6520: dup
    //   6521: bipush #43
    //   6523: iconst_1
    //   6524: iastore
    //   6525: dup
    //   6526: bipush #44
    //   6528: ldc 8396801
    //   6530: iastore
    //   6531: dup
    //   6532: bipush #45
    //   6534: sipush #8321
    //   6537: iastore
    //   6538: dup
    //   6539: bipush #46
    //   6541: sipush #8321
    //   6544: iastore
    //   6545: dup
    //   6546: bipush #47
    //   6548: sipush #128
    //   6551: iastore
    //   6552: dup
    //   6553: bipush #48
    //   6555: ldc 8396929
    //   6557: iastore
    //   6558: dup
    //   6559: bipush #49
    //   6561: sipush #129
    //   6564: iastore
    //   6565: dup
    //   6566: bipush #50
    //   6568: iconst_1
    //   6569: iastore
    //   6570: dup
    //   6571: bipush #51
    //   6573: sipush #8192
    //   6576: iastore
    //   6577: dup
    //   6578: bipush #52
    //   6580: ldc 8388609
    //   6582: iastore
    //   6583: dup
    //   6584: bipush #53
    //   6586: sipush #8193
    //   6589: iastore
    //   6590: dup
    //   6591: bipush #54
    //   6593: ldc 8396928
    //   6595: iastore
    //   6596: dup
    //   6597: bipush #55
    //   6599: ldc 8388737
    //   6601: iastore
    //   6602: dup
    //   6603: bipush #56
    //   6605: sipush #8193
    //   6608: iastore
    //   6609: dup
    //   6610: bipush #57
    //   6612: sipush #8320
    //   6615: iastore
    //   6616: dup
    //   6617: bipush #58
    //   6619: ldc 8388608
    //   6621: iastore
    //   6622: dup
    //   6623: bipush #59
    //   6625: ldc 8396801
    //   6627: iastore
    //   6628: dup
    //   6629: bipush #60
    //   6631: sipush #128
    //   6634: iastore
    //   6635: dup
    //   6636: bipush #61
    //   6638: ldc 8388608
    //   6640: iastore
    //   6641: dup
    //   6642: bipush #62
    //   6644: sipush #8192
    //   6647: iastore
    //   6648: dup
    //   6649: bipush #63
    //   6651: ldc 8396928
    //   6653: iastore
    //   6654: astore #12
    //   6656: bipush #64
    //   6658: newarray int
    //   6660: dup
    //   6661: iconst_0
    //   6662: sipush #256
    //   6665: iastore
    //   6666: dup
    //   6667: iconst_1
    //   6668: ldc 34078976
    //   6670: iastore
    //   6671: dup
    //   6672: iconst_2
    //   6673: ldc 34078720
    //   6675: iastore
    //   6676: dup
    //   6677: iconst_3
    //   6678: ldc 1107296512
    //   6680: iastore
    //   6681: dup
    //   6682: iconst_4
    //   6683: ldc 524288
    //   6685: iastore
    //   6686: dup
    //   6687: iconst_5
    //   6688: sipush #256
    //   6691: iastore
    //   6692: dup
    //   6693: bipush #6
    //   6695: ldc 1073741824
    //   6697: iastore
    //   6698: dup
    //   6699: bipush #7
    //   6701: ldc 34078720
    //   6703: iastore
    //   6704: dup
    //   6705: bipush #8
    //   6707: ldc 1074266368
    //   6709: iastore
    //   6710: dup
    //   6711: bipush #9
    //   6713: ldc 524288
    //   6715: iastore
    //   6716: dup
    //   6717: bipush #10
    //   6719: ldc 33554688
    //   6721: iastore
    //   6722: dup
    //   6723: bipush #11
    //   6725: ldc 1074266368
    //   6727: iastore
    //   6728: dup
    //   6729: bipush #12
    //   6731: ldc 1107296512
    //   6733: iastore
    //   6734: dup
    //   6735: bipush #13
    //   6737: ldc 1107820544
    //   6739: iastore
    //   6740: dup
    //   6741: bipush #14
    //   6743: ldc 524544
    //   6745: iastore
    //   6746: dup
    //   6747: bipush #15
    //   6749: ldc 1073741824
    //   6751: iastore
    //   6752: dup
    //   6753: bipush #16
    //   6755: ldc 33554432
    //   6757: iastore
    //   6758: dup
    //   6759: bipush #17
    //   6761: ldc 1074266112
    //   6763: iastore
    //   6764: dup
    //   6765: bipush #18
    //   6767: ldc 1074266112
    //   6769: iastore
    //   6770: dup
    //   6771: bipush #19
    //   6773: iconst_0
    //   6774: iastore
    //   6775: dup
    //   6776: bipush #20
    //   6778: ldc 1073742080
    //   6780: iastore
    //   6781: dup
    //   6782: bipush #21
    //   6784: ldc 1107820800
    //   6786: iastore
    //   6787: dup
    //   6788: bipush #22
    //   6790: ldc 1107820800
    //   6792: iastore
    //   6793: dup
    //   6794: bipush #23
    //   6796: ldc 33554688
    //   6798: iastore
    //   6799: dup
    //   6800: bipush #24
    //   6802: ldc 1107820544
    //   6804: iastore
    //   6805: dup
    //   6806: bipush #25
    //   6808: ldc 1073742080
    //   6810: iastore
    //   6811: dup
    //   6812: bipush #26
    //   6814: iconst_0
    //   6815: iastore
    //   6816: dup
    //   6817: bipush #27
    //   6819: ldc 1107296256
    //   6821: iastore
    //   6822: dup
    //   6823: bipush #28
    //   6825: ldc 34078976
    //   6827: iastore
    //   6828: dup
    //   6829: bipush #29
    //   6831: ldc 33554432
    //   6833: iastore
    //   6834: dup
    //   6835: bipush #30
    //   6837: ldc 1107296256
    //   6839: iastore
    //   6840: dup
    //   6841: bipush #31
    //   6843: ldc 524544
    //   6845: iastore
    //   6846: dup
    //   6847: bipush #32
    //   6849: ldc 524288
    //   6851: iastore
    //   6852: dup
    //   6853: bipush #33
    //   6855: ldc 1107296512
    //   6857: iastore
    //   6858: dup
    //   6859: bipush #34
    //   6861: sipush #256
    //   6864: iastore
    //   6865: dup
    //   6866: bipush #35
    //   6868: ldc 33554432
    //   6870: iastore
    //   6871: dup
    //   6872: bipush #36
    //   6874: ldc 1073741824
    //   6876: iastore
    //   6877: dup
    //   6878: bipush #37
    //   6880: ldc 34078720
    //   6882: iastore
    //   6883: dup
    //   6884: bipush #38
    //   6886: ldc 1107296512
    //   6888: iastore
    //   6889: dup
    //   6890: bipush #39
    //   6892: ldc 1074266368
    //   6894: iastore
    //   6895: dup
    //   6896: bipush #40
    //   6898: ldc 33554688
    //   6900: iastore
    //   6901: dup
    //   6902: bipush #41
    //   6904: ldc 1073741824
    //   6906: iastore
    //   6907: dup
    //   6908: bipush #42
    //   6910: ldc 1107820544
    //   6912: iastore
    //   6913: dup
    //   6914: bipush #43
    //   6916: ldc 34078976
    //   6918: iastore
    //   6919: dup
    //   6920: bipush #44
    //   6922: ldc 1074266368
    //   6924: iastore
    //   6925: dup
    //   6926: bipush #45
    //   6928: sipush #256
    //   6931: iastore
    //   6932: dup
    //   6933: bipush #46
    //   6935: ldc 33554432
    //   6937: iastore
    //   6938: dup
    //   6939: bipush #47
    //   6941: ldc 1107820544
    //   6943: iastore
    //   6944: dup
    //   6945: bipush #48
    //   6947: ldc 1107820800
    //   6949: iastore
    //   6950: dup
    //   6951: bipush #49
    //   6953: ldc 524544
    //   6955: iastore
    //   6956: dup
    //   6957: bipush #50
    //   6959: ldc 1107296256
    //   6961: iastore
    //   6962: dup
    //   6963: bipush #51
    //   6965: ldc 1107820800
    //   6967: iastore
    //   6968: dup
    //   6969: bipush #52
    //   6971: ldc 34078720
    //   6973: iastore
    //   6974: dup
    //   6975: bipush #53
    //   6977: iconst_0
    //   6978: iastore
    //   6979: dup
    //   6980: bipush #54
    //   6982: ldc 1074266112
    //   6984: iastore
    //   6985: dup
    //   6986: bipush #55
    //   6988: ldc 1107296256
    //   6990: iastore
    //   6991: dup
    //   6992: bipush #56
    //   6994: ldc 524544
    //   6996: iastore
    //   6997: dup
    //   6998: bipush #57
    //   7000: ldc 33554688
    //   7002: iastore
    //   7003: dup
    //   7004: bipush #58
    //   7006: ldc 1073742080
    //   7008: iastore
    //   7009: dup
    //   7010: bipush #59
    //   7012: ldc 524288
    //   7014: iastore
    //   7015: dup
    //   7016: bipush #60
    //   7018: iconst_0
    //   7019: iastore
    //   7020: dup
    //   7021: bipush #61
    //   7023: ldc 1074266112
    //   7025: iastore
    //   7026: dup
    //   7027: bipush #62
    //   7029: ldc 34078976
    //   7031: iastore
    //   7032: dup
    //   7033: bipush #63
    //   7035: ldc 1073742080
    //   7037: iastore
    //   7038: astore #13
    //   7040: bipush #64
    //   7042: newarray int
    //   7044: dup
    //   7045: iconst_0
    //   7046: ldc 536870928
    //   7048: iastore
    //   7049: dup
    //   7050: iconst_1
    //   7051: ldc 541065216
    //   7053: iastore
    //   7054: dup
    //   7055: iconst_2
    //   7056: sipush #16384
    //   7059: iastore
    //   7060: dup
    //   7061: iconst_3
    //   7062: ldc 541081616
    //   7064: iastore
    //   7065: dup
    //   7066: iconst_4
    //   7067: ldc 541065216
    //   7069: iastore
    //   7070: dup
    //   7071: iconst_5
    //   7072: bipush #16
    //   7074: iastore
    //   7075: dup
    //   7076: bipush #6
    //   7078: ldc 541081616
    //   7080: iastore
    //   7081: dup
    //   7082: bipush #7
    //   7084: ldc 4194304
    //   7086: iastore
    //   7087: dup
    //   7088: bipush #8
    //   7090: ldc 536887296
    //   7092: iastore
    //   7093: dup
    //   7094: bipush #9
    //   7096: ldc 4210704
    //   7098: iastore
    //   7099: dup
    //   7100: bipush #10
    //   7102: ldc 4194304
    //   7104: iastore
    //   7105: dup
    //   7106: bipush #11
    //   7108: ldc 536870928
    //   7110: iastore
    //   7111: dup
    //   7112: bipush #12
    //   7114: ldc 4194320
    //   7116: iastore
    //   7117: dup
    //   7118: bipush #13
    //   7120: ldc 536887296
    //   7122: iastore
    //   7123: dup
    //   7124: bipush #14
    //   7126: ldc 536870912
    //   7128: iastore
    //   7129: dup
    //   7130: bipush #15
    //   7132: sipush #16400
    //   7135: iastore
    //   7136: dup
    //   7137: bipush #16
    //   7139: iconst_0
    //   7140: iastore
    //   7141: dup
    //   7142: bipush #17
    //   7144: ldc 4194320
    //   7146: iastore
    //   7147: dup
    //   7148: bipush #18
    //   7150: ldc 536887312
    //   7152: iastore
    //   7153: dup
    //   7154: bipush #19
    //   7156: sipush #16384
    //   7159: iastore
    //   7160: dup
    //   7161: bipush #20
    //   7163: ldc 4210688
    //   7165: iastore
    //   7166: dup
    //   7167: bipush #21
    //   7169: ldc 536887312
    //   7171: iastore
    //   7172: dup
    //   7173: bipush #22
    //   7175: bipush #16
    //   7177: iastore
    //   7178: dup
    //   7179: bipush #23
    //   7181: ldc 541065232
    //   7183: iastore
    //   7184: dup
    //   7185: bipush #24
    //   7187: ldc 541065232
    //   7189: iastore
    //   7190: dup
    //   7191: bipush #25
    //   7193: iconst_0
    //   7194: iastore
    //   7195: dup
    //   7196: bipush #26
    //   7198: ldc 4210704
    //   7200: iastore
    //   7201: dup
    //   7202: bipush #27
    //   7204: ldc 541081600
    //   7206: iastore
    //   7207: dup
    //   7208: bipush #28
    //   7210: sipush #16400
    //   7213: iastore
    //   7214: dup
    //   7215: bipush #29
    //   7217: ldc 4210688
    //   7219: iastore
    //   7220: dup
    //   7221: bipush #30
    //   7223: ldc 541081600
    //   7225: iastore
    //   7226: dup
    //   7227: bipush #31
    //   7229: ldc 536870912
    //   7231: iastore
    //   7232: dup
    //   7233: bipush #32
    //   7235: ldc 536887296
    //   7237: iastore
    //   7238: dup
    //   7239: bipush #33
    //   7241: bipush #16
    //   7243: iastore
    //   7244: dup
    //   7245: bipush #34
    //   7247: ldc 541065232
    //   7249: iastore
    //   7250: dup
    //   7251: bipush #35
    //   7253: ldc 4210688
    //   7255: iastore
    //   7256: dup
    //   7257: bipush #36
    //   7259: ldc 541081616
    //   7261: iastore
    //   7262: dup
    //   7263: bipush #37
    //   7265: ldc 4194304
    //   7267: iastore
    //   7268: dup
    //   7269: bipush #38
    //   7271: sipush #16400
    //   7274: iastore
    //   7275: dup
    //   7276: bipush #39
    //   7278: ldc 536870928
    //   7280: iastore
    //   7281: dup
    //   7282: bipush #40
    //   7284: ldc 4194304
    //   7286: iastore
    //   7287: dup
    //   7288: bipush #41
    //   7290: ldc 536887296
    //   7292: iastore
    //   7293: dup
    //   7294: bipush #42
    //   7296: ldc 536870912
    //   7298: iastore
    //   7299: dup
    //   7300: bipush #43
    //   7302: sipush #16400
    //   7305: iastore
    //   7306: dup
    //   7307: bipush #44
    //   7309: ldc 536870928
    //   7311: iastore
    //   7312: dup
    //   7313: bipush #45
    //   7315: ldc 541081616
    //   7317: iastore
    //   7318: dup
    //   7319: bipush #46
    //   7321: ldc 4210688
    //   7323: iastore
    //   7324: dup
    //   7325: bipush #47
    //   7327: ldc 541065216
    //   7329: iastore
    //   7330: dup
    //   7331: bipush #48
    //   7333: ldc 4210704
    //   7335: iastore
    //   7336: dup
    //   7337: bipush #49
    //   7339: ldc 541081600
    //   7341: iastore
    //   7342: dup
    //   7343: bipush #50
    //   7345: iconst_0
    //   7346: iastore
    //   7347: dup
    //   7348: bipush #51
    //   7350: ldc 541065232
    //   7352: iastore
    //   7353: dup
    //   7354: bipush #52
    //   7356: bipush #16
    //   7358: iastore
    //   7359: dup
    //   7360: bipush #53
    //   7362: sipush #16384
    //   7365: iastore
    //   7366: dup
    //   7367: bipush #54
    //   7369: ldc 541065216
    //   7371: iastore
    //   7372: dup
    //   7373: bipush #55
    //   7375: ldc 4210704
    //   7377: iastore
    //   7378: dup
    //   7379: bipush #56
    //   7381: sipush #16384
    //   7384: iastore
    //   7385: dup
    //   7386: bipush #57
    //   7388: ldc 4194320
    //   7390: iastore
    //   7391: dup
    //   7392: bipush #58
    //   7394: ldc 536887312
    //   7396: iastore
    //   7397: dup
    //   7398: bipush #59
    //   7400: iconst_0
    //   7401: iastore
    //   7402: dup
    //   7403: bipush #60
    //   7405: ldc 541081600
    //   7407: iastore
    //   7408: dup
    //   7409: bipush #61
    //   7411: ldc 536870912
    //   7413: iastore
    //   7414: dup
    //   7415: bipush #62
    //   7417: ldc 4194320
    //   7419: iastore
    //   7420: dup
    //   7421: bipush #63
    //   7423: ldc 536887312
    //   7425: iastore
    //   7426: astore #14
    //   7428: bipush #64
    //   7430: newarray int
    //   7432: dup
    //   7433: iconst_0
    //   7434: ldc 2097152
    //   7436: iastore
    //   7437: dup
    //   7438: iconst_1
    //   7439: ldc 69206018
    //   7441: iastore
    //   7442: dup
    //   7443: iconst_2
    //   7444: ldc 67110914
    //   7446: iastore
    //   7447: dup
    //   7448: iconst_3
    //   7449: iconst_0
    //   7450: iastore
    //   7451: dup
    //   7452: iconst_4
    //   7453: sipush #2048
    //   7456: iastore
    //   7457: dup
    //   7458: iconst_5
    //   7459: ldc 67110914
    //   7461: iastore
    //   7462: dup
    //   7463: bipush #6
    //   7465: ldc 2099202
    //   7467: iastore
    //   7468: dup
    //   7469: bipush #7
    //   7471: ldc 69208064
    //   7473: iastore
    //   7474: dup
    //   7475: bipush #8
    //   7477: ldc 69208066
    //   7479: iastore
    //   7480: dup
    //   7481: bipush #9
    //   7483: ldc 2097152
    //   7485: iastore
    //   7486: dup
    //   7487: bipush #10
    //   7489: iconst_0
    //   7490: iastore
    //   7491: dup
    //   7492: bipush #11
    //   7494: ldc 67108866
    //   7496: iastore
    //   7497: dup
    //   7498: bipush #12
    //   7500: iconst_2
    //   7501: iastore
    //   7502: dup
    //   7503: bipush #13
    //   7505: ldc 67108864
    //   7507: iastore
    //   7508: dup
    //   7509: bipush #14
    //   7511: ldc 69206018
    //   7513: iastore
    //   7514: dup
    //   7515: bipush #15
    //   7517: sipush #2050
    //   7520: iastore
    //   7521: dup
    //   7522: bipush #16
    //   7524: ldc 67110912
    //   7526: iastore
    //   7527: dup
    //   7528: bipush #17
    //   7530: ldc 2099202
    //   7532: iastore
    //   7533: dup
    //   7534: bipush #18
    //   7536: ldc 2097154
    //   7538: iastore
    //   7539: dup
    //   7540: bipush #19
    //   7542: ldc 67110912
    //   7544: iastore
    //   7545: dup
    //   7546: bipush #20
    //   7548: ldc 67108866
    //   7550: iastore
    //   7551: dup
    //   7552: bipush #21
    //   7554: ldc 69206016
    //   7556: iastore
    //   7557: dup
    //   7558: bipush #22
    //   7560: ldc 69208064
    //   7562: iastore
    //   7563: dup
    //   7564: bipush #23
    //   7566: ldc 2097154
    //   7568: iastore
    //   7569: dup
    //   7570: bipush #24
    //   7572: ldc 69206016
    //   7574: iastore
    //   7575: dup
    //   7576: bipush #25
    //   7578: sipush #2048
    //   7581: iastore
    //   7582: dup
    //   7583: bipush #26
    //   7585: sipush #2050
    //   7588: iastore
    //   7589: dup
    //   7590: bipush #27
    //   7592: ldc 69208066
    //   7594: iastore
    //   7595: dup
    //   7596: bipush #28
    //   7598: ldc 2099200
    //   7600: iastore
    //   7601: dup
    //   7602: bipush #29
    //   7604: iconst_2
    //   7605: iastore
    //   7606: dup
    //   7607: bipush #30
    //   7609: ldc 67108864
    //   7611: iastore
    //   7612: dup
    //   7613: bipush #31
    //   7615: ldc 2099200
    //   7617: iastore
    //   7618: dup
    //   7619: bipush #32
    //   7621: ldc 67108864
    //   7623: iastore
    //   7624: dup
    //   7625: bipush #33
    //   7627: ldc 2099200
    //   7629: iastore
    //   7630: dup
    //   7631: bipush #34
    //   7633: ldc 2097152
    //   7635: iastore
    //   7636: dup
    //   7637: bipush #35
    //   7639: ldc 67110914
    //   7641: iastore
    //   7642: dup
    //   7643: bipush #36
    //   7645: ldc 67110914
    //   7647: iastore
    //   7648: dup
    //   7649: bipush #37
    //   7651: ldc 69206018
    //   7653: iastore
    //   7654: dup
    //   7655: bipush #38
    //   7657: ldc 69206018
    //   7659: iastore
    //   7660: dup
    //   7661: bipush #39
    //   7663: iconst_2
    //   7664: iastore
    //   7665: dup
    //   7666: bipush #40
    //   7668: ldc 2097154
    //   7670: iastore
    //   7671: dup
    //   7672: bipush #41
    //   7674: ldc 67108864
    //   7676: iastore
    //   7677: dup
    //   7678: bipush #42
    //   7680: ldc 67110912
    //   7682: iastore
    //   7683: dup
    //   7684: bipush #43
    //   7686: ldc 2097152
    //   7688: iastore
    //   7689: dup
    //   7690: bipush #44
    //   7692: ldc 69208064
    //   7694: iastore
    //   7695: dup
    //   7696: bipush #45
    //   7698: sipush #2050
    //   7701: iastore
    //   7702: dup
    //   7703: bipush #46
    //   7705: ldc 2099202
    //   7707: iastore
    //   7708: dup
    //   7709: bipush #47
    //   7711: ldc 69208064
    //   7713: iastore
    //   7714: dup
    //   7715: bipush #48
    //   7717: sipush #2050
    //   7720: iastore
    //   7721: dup
    //   7722: bipush #49
    //   7724: ldc 67108866
    //   7726: iastore
    //   7727: dup
    //   7728: bipush #50
    //   7730: ldc 69208066
    //   7732: iastore
    //   7733: dup
    //   7734: bipush #51
    //   7736: ldc 69206016
    //   7738: iastore
    //   7739: dup
    //   7740: bipush #52
    //   7742: ldc 2099200
    //   7744: iastore
    //   7745: dup
    //   7746: bipush #53
    //   7748: iconst_0
    //   7749: iastore
    //   7750: dup
    //   7751: bipush #54
    //   7753: iconst_2
    //   7754: iastore
    //   7755: dup
    //   7756: bipush #55
    //   7758: ldc 69208066
    //   7760: iastore
    //   7761: dup
    //   7762: bipush #56
    //   7764: iconst_0
    //   7765: iastore
    //   7766: dup
    //   7767: bipush #57
    //   7769: ldc 2099202
    //   7771: iastore
    //   7772: dup
    //   7773: bipush #58
    //   7775: ldc 69206016
    //   7777: iastore
    //   7778: dup
    //   7779: bipush #59
    //   7781: sipush #2048
    //   7784: iastore
    //   7785: dup
    //   7786: bipush #60
    //   7788: ldc 67108866
    //   7790: iastore
    //   7791: dup
    //   7792: bipush #61
    //   7794: ldc 67110912
    //   7796: iastore
    //   7797: dup
    //   7798: bipush #62
    //   7800: sipush #2048
    //   7803: iastore
    //   7804: dup
    //   7805: bipush #63
    //   7807: ldc 2097154
    //   7809: iastore
    //   7810: astore #15
    //   7812: bipush #64
    //   7814: newarray int
    //   7816: dup
    //   7817: iconst_0
    //   7818: ldc 268439616
    //   7820: iastore
    //   7821: dup
    //   7822: iconst_1
    //   7823: sipush #4096
    //   7826: iastore
    //   7827: dup
    //   7828: iconst_2
    //   7829: ldc 262144
    //   7831: iastore
    //   7832: dup
    //   7833: iconst_3
    //   7834: ldc 268701760
    //   7836: iastore
    //   7837: dup
    //   7838: iconst_4
    //   7839: ldc 268435456
    //   7841: iastore
    //   7842: dup
    //   7843: iconst_5
    //   7844: ldc 268439616
    //   7846: iastore
    //   7847: dup
    //   7848: bipush #6
    //   7850: bipush #64
    //   7852: iastore
    //   7853: dup
    //   7854: bipush #7
    //   7856: ldc 268435456
    //   7858: iastore
    //   7859: dup
    //   7860: bipush #8
    //   7862: ldc 262208
    //   7864: iastore
    //   7865: dup
    //   7866: bipush #9
    //   7868: ldc 268697600
    //   7870: iastore
    //   7871: dup
    //   7872: bipush #10
    //   7874: ldc 268701760
    //   7876: iastore
    //   7877: dup
    //   7878: bipush #11
    //   7880: ldc 266240
    //   7882: iastore
    //   7883: dup
    //   7884: bipush #12
    //   7886: ldc 268701696
    //   7888: iastore
    //   7889: dup
    //   7890: bipush #13
    //   7892: ldc 266304
    //   7894: iastore
    //   7895: dup
    //   7896: bipush #14
    //   7898: sipush #4096
    //   7901: iastore
    //   7902: dup
    //   7903: bipush #15
    //   7905: bipush #64
    //   7907: iastore
    //   7908: dup
    //   7909: bipush #16
    //   7911: ldc 268697600
    //   7913: iastore
    //   7914: dup
    //   7915: bipush #17
    //   7917: ldc 268435520
    //   7919: iastore
    //   7920: dup
    //   7921: bipush #18
    //   7923: ldc 268439552
    //   7925: iastore
    //   7926: dup
    //   7927: bipush #19
    //   7929: sipush #4160
    //   7932: iastore
    //   7933: dup
    //   7934: bipush #20
    //   7936: ldc 266240
    //   7938: iastore
    //   7939: dup
    //   7940: bipush #21
    //   7942: ldc 262208
    //   7944: iastore
    //   7945: dup
    //   7946: bipush #22
    //   7948: ldc 268697664
    //   7950: iastore
    //   7951: dup
    //   7952: bipush #23
    //   7954: ldc 268701696
    //   7956: iastore
    //   7957: dup
    //   7958: bipush #24
    //   7960: sipush #4160
    //   7963: iastore
    //   7964: dup
    //   7965: bipush #25
    //   7967: iconst_0
    //   7968: iastore
    //   7969: dup
    //   7970: bipush #26
    //   7972: iconst_0
    //   7973: iastore
    //   7974: dup
    //   7975: bipush #27
    //   7977: ldc 268697664
    //   7979: iastore
    //   7980: dup
    //   7981: bipush #28
    //   7983: ldc 268435520
    //   7985: iastore
    //   7986: dup
    //   7987: bipush #29
    //   7989: ldc 268439552
    //   7991: iastore
    //   7992: dup
    //   7993: bipush #30
    //   7995: ldc 266304
    //   7997: iastore
    //   7998: dup
    //   7999: bipush #31
    //   8001: ldc 262144
    //   8003: iastore
    //   8004: dup
    //   8005: bipush #32
    //   8007: ldc 266304
    //   8009: iastore
    //   8010: dup
    //   8011: bipush #33
    //   8013: ldc 262144
    //   8015: iastore
    //   8016: dup
    //   8017: bipush #34
    //   8019: ldc 268701696
    //   8021: iastore
    //   8022: dup
    //   8023: bipush #35
    //   8025: sipush #4096
    //   8028: iastore
    //   8029: dup
    //   8030: bipush #36
    //   8032: bipush #64
    //   8034: iastore
    //   8035: dup
    //   8036: bipush #37
    //   8038: ldc 268697664
    //   8040: iastore
    //   8041: dup
    //   8042: bipush #38
    //   8044: sipush #4096
    //   8047: iastore
    //   8048: dup
    //   8049: bipush #39
    //   8051: ldc 266304
    //   8053: iastore
    //   8054: dup
    //   8055: bipush #40
    //   8057: ldc 268439552
    //   8059: iastore
    //   8060: dup
    //   8061: bipush #41
    //   8063: bipush #64
    //   8065: iastore
    //   8066: dup
    //   8067: bipush #42
    //   8069: ldc 268435520
    //   8071: iastore
    //   8072: dup
    //   8073: bipush #43
    //   8075: ldc 268697600
    //   8077: iastore
    //   8078: dup
    //   8079: bipush #44
    //   8081: ldc 268697664
    //   8083: iastore
    //   8084: dup
    //   8085: bipush #45
    //   8087: ldc 268435456
    //   8089: iastore
    //   8090: dup
    //   8091: bipush #46
    //   8093: ldc 262144
    //   8095: iastore
    //   8096: dup
    //   8097: bipush #47
    //   8099: ldc 268439616
    //   8101: iastore
    //   8102: dup
    //   8103: bipush #48
    //   8105: iconst_0
    //   8106: iastore
    //   8107: dup
    //   8108: bipush #49
    //   8110: ldc 268701760
    //   8112: iastore
    //   8113: dup
    //   8114: bipush #50
    //   8116: ldc 262208
    //   8118: iastore
    //   8119: dup
    //   8120: bipush #51
    //   8122: ldc 268435520
    //   8124: iastore
    //   8125: dup
    //   8126: bipush #52
    //   8128: ldc 268697600
    //   8130: iastore
    //   8131: dup
    //   8132: bipush #53
    //   8134: ldc 268439552
    //   8136: iastore
    //   8137: dup
    //   8138: bipush #54
    //   8140: ldc 268439616
    //   8142: iastore
    //   8143: dup
    //   8144: bipush #55
    //   8146: iconst_0
    //   8147: iastore
    //   8148: dup
    //   8149: bipush #56
    //   8151: ldc 268701760
    //   8153: iastore
    //   8154: dup
    //   8155: bipush #57
    //   8157: ldc 266240
    //   8159: iastore
    //   8160: dup
    //   8161: bipush #58
    //   8163: ldc 266240
    //   8165: iastore
    //   8166: dup
    //   8167: bipush #59
    //   8169: sipush #4160
    //   8172: iastore
    //   8173: dup
    //   8174: bipush #60
    //   8176: sipush #4160
    //   8179: iastore
    //   8180: dup
    //   8181: bipush #61
    //   8183: ldc 262208
    //   8185: iastore
    //   8186: dup
    //   8187: bipush #62
    //   8189: ldc 268435456
    //   8191: iastore
    //   8192: dup
    //   8193: bipush #63
    //   8195: ldc 268701696
    //   8197: iastore
    //   8198: astore #16
    //   8200: aload #4
    //   8202: arraylength
    //   8203: istore #17
    //   8205: iconst_2
    //   8206: newarray int
    //   8208: astore #18
    //   8210: iload #17
    //   8212: newarray byte
    //   8214: astore #5
    //   8216: iload #17
    //   8218: bipush #8
    //   8220: idiv
    //   8221: istore #19
    //   8223: iconst_0
    //   8224: istore #20
    //   8226: iload #20
    //   8228: iload #19
    //   8230: if_icmpge -> 9148
    //   8233: iload #20
    //   8235: bipush #8
    //   8237: imul
    //   8238: istore #21
    //   8240: iconst_0
    //   8241: istore #22
    //   8243: iload #22
    //   8245: iconst_2
    //   8246: if_icmpge -> 8335
    //   8249: aload #18
    //   8251: iload #22
    //   8253: aload #4
    //   8255: iload #21
    //   8257: iload #22
    //   8259: iconst_4
    //   8260: imul
    //   8261: iadd
    //   8262: baload
    //   8263: sipush #255
    //   8266: iand
    //   8267: bipush #24
    //   8269: ishl
    //   8270: aload #4
    //   8272: iload #21
    //   8274: iload #22
    //   8276: iconst_4
    //   8277: imul
    //   8278: iadd
    //   8279: iconst_1
    //   8280: iadd
    //   8281: baload
    //   8282: sipush #255
    //   8285: iand
    //   8286: bipush #16
    //   8288: ishl
    //   8289: ior
    //   8290: aload #4
    //   8292: iload #21
    //   8294: iload #22
    //   8296: iconst_4
    //   8297: imul
    //   8298: iadd
    //   8299: iconst_2
    //   8300: iadd
    //   8301: baload
    //   8302: sipush #255
    //   8305: iand
    //   8306: bipush #8
    //   8308: ishl
    //   8309: ior
    //   8310: aload #4
    //   8312: iload #21
    //   8314: iload #22
    //   8316: iconst_4
    //   8317: imul
    //   8318: iadd
    //   8319: iconst_3
    //   8320: iadd
    //   8321: baload
    //   8322: sipush #255
    //   8325: iand
    //   8326: ior
    //   8327: iastore
    //   8328: iinc #22, 1
    //   8331: iload_2
    //   8332: ifne -> 8243
    //   8335: iconst_0
    //   8336: istore #27
    //   8338: aload #18
    //   8340: iconst_0
    //   8341: iaload
    //   8342: istore #25
    //   8344: aload #18
    //   8346: iconst_1
    //   8347: iaload
    //   8348: istore #24
    //   8350: iload #25
    //   8352: iconst_4
    //   8353: iushr
    //   8354: iload #24
    //   8356: ixor
    //   8357: ldc 252645135
    //   8359: iand
    //   8360: istore #23
    //   8362: iload #24
    //   8364: iload #23
    //   8366: ixor
    //   8367: istore #24
    //   8369: iload #25
    //   8371: iload #23
    //   8373: iconst_4
    //   8374: ishl
    //   8375: ixor
    //   8376: istore #25
    //   8378: iload #25
    //   8380: bipush #16
    //   8382: iushr
    //   8383: iload #24
    //   8385: ixor
    //   8386: ldc 65535
    //   8388: iand
    //   8389: istore #23
    //   8391: iload #24
    //   8393: iload #23
    //   8395: ixor
    //   8396: istore #24
    //   8398: iload #25
    //   8400: iload #23
    //   8402: bipush #16
    //   8404: ishl
    //   8405: ixor
    //   8406: istore #25
    //   8408: iload #24
    //   8410: iconst_2
    //   8411: iushr
    //   8412: iload #25
    //   8414: ixor
    //   8415: ldc 858993459
    //   8417: iand
    //   8418: istore #23
    //   8420: iload #25
    //   8422: iload #23
    //   8424: ixor
    //   8425: istore #25
    //   8427: iload #24
    //   8429: iload #23
    //   8431: iconst_2
    //   8432: ishl
    //   8433: ixor
    //   8434: istore #24
    //   8436: iload #24
    //   8438: bipush #8
    //   8440: iushr
    //   8441: iload #25
    //   8443: ixor
    //   8444: ldc 16711935
    //   8446: iand
    //   8447: istore #23
    //   8449: iload #25
    //   8451: iload #23
    //   8453: ixor
    //   8454: istore #25
    //   8456: iload #24
    //   8458: iload #23
    //   8460: bipush #8
    //   8462: ishl
    //   8463: ixor
    //   8464: istore #24
    //   8466: iload #24
    //   8468: iconst_1
    //   8469: ishl
    //   8470: iload #24
    //   8472: bipush #31
    //   8474: iushr
    //   8475: iconst_1
    //   8476: iand
    //   8477: ior
    //   8478: istore #24
    //   8480: iload #25
    //   8482: iload #24
    //   8484: ixor
    //   8485: ldc -1431655766
    //   8487: iand
    //   8488: istore #23
    //   8490: iload #25
    //   8492: iload #23
    //   8494: ixor
    //   8495: istore #25
    //   8497: iload #24
    //   8499: iload #23
    //   8501: ixor
    //   8502: istore #24
    //   8504: iload #25
    //   8506: iconst_1
    //   8507: ishl
    //   8508: iload #25
    //   8510: bipush #31
    //   8512: iushr
    //   8513: iconst_1
    //   8514: iand
    //   8515: ior
    //   8516: istore #25
    //   8518: iconst_0
    //   8519: istore #26
    //   8521: iload #26
    //   8523: bipush #8
    //   8525: if_icmpge -> 8863
    //   8528: iload #24
    //   8530: bipush #28
    //   8532: ishl
    //   8533: iload #24
    //   8535: iconst_4
    //   8536: iushr
    //   8537: ior
    //   8538: istore #23
    //   8540: iload #23
    //   8542: aload #6
    //   8544: iload #27
    //   8546: iinc #27, 1
    //   8549: iaload
    //   8550: ixor
    //   8551: istore #23
    //   8553: aload #15
    //   8555: iload #23
    //   8557: bipush #63
    //   8559: iand
    //   8560: iaload
    //   8561: istore #22
    //   8563: iload #22
    //   8565: aload #13
    //   8567: iload #23
    //   8569: bipush #8
    //   8571: iushr
    //   8572: bipush #63
    //   8574: iand
    //   8575: iaload
    //   8576: ior
    //   8577: istore #22
    //   8579: iload #22
    //   8581: aload #11
    //   8583: iload #23
    //   8585: bipush #16
    //   8587: iushr
    //   8588: bipush #63
    //   8590: iand
    //   8591: iaload
    //   8592: ior
    //   8593: istore #22
    //   8595: iload #22
    //   8597: aload #9
    //   8599: iload #23
    //   8601: bipush #24
    //   8603: iushr
    //   8604: bipush #63
    //   8606: iand
    //   8607: iaload
    //   8608: ior
    //   8609: istore #22
    //   8611: iload #24
    //   8613: aload #6
    //   8615: iload #27
    //   8617: iinc #27, 1
    //   8620: iaload
    //   8621: ixor
    //   8622: istore #23
    //   8624: iload #22
    //   8626: aload #16
    //   8628: iload #23
    //   8630: bipush #63
    //   8632: iand
    //   8633: iaload
    //   8634: ior
    //   8635: istore #22
    //   8637: iload #22
    //   8639: aload #14
    //   8641: iload #23
    //   8643: bipush #8
    //   8645: iushr
    //   8646: bipush #63
    //   8648: iand
    //   8649: iaload
    //   8650: ior
    //   8651: istore #22
    //   8653: iload #22
    //   8655: aload #12
    //   8657: iload #23
    //   8659: bipush #16
    //   8661: iushr
    //   8662: bipush #63
    //   8664: iand
    //   8665: iaload
    //   8666: ior
    //   8667: istore #22
    //   8669: iload #22
    //   8671: aload #10
    //   8673: iload #23
    //   8675: bipush #24
    //   8677: iushr
    //   8678: bipush #63
    //   8680: iand
    //   8681: iaload
    //   8682: ior
    //   8683: istore #22
    //   8685: iload #25
    //   8687: iload #22
    //   8689: ixor
    //   8690: istore #25
    //   8692: iload #25
    //   8694: bipush #28
    //   8696: ishl
    //   8697: iload #25
    //   8699: iconst_4
    //   8700: iushr
    //   8701: ior
    //   8702: istore #23
    //   8704: iload #23
    //   8706: aload #6
    //   8708: iload #27
    //   8710: iinc #27, 1
    //   8713: iaload
    //   8714: ixor
    //   8715: istore #23
    //   8717: aload #15
    //   8719: iload #23
    //   8721: bipush #63
    //   8723: iand
    //   8724: iaload
    //   8725: istore #22
    //   8727: iload #22
    //   8729: aload #13
    //   8731: iload #23
    //   8733: bipush #8
    //   8735: iushr
    //   8736: bipush #63
    //   8738: iand
    //   8739: iaload
    //   8740: ior
    //   8741: istore #22
    //   8743: iload #22
    //   8745: aload #11
    //   8747: iload #23
    //   8749: bipush #16
    //   8751: iushr
    //   8752: bipush #63
    //   8754: iand
    //   8755: iaload
    //   8756: ior
    //   8757: istore #22
    //   8759: iload #22
    //   8761: aload #9
    //   8763: iload #23
    //   8765: bipush #24
    //   8767: iushr
    //   8768: bipush #63
    //   8770: iand
    //   8771: iaload
    //   8772: ior
    //   8773: istore #22
    //   8775: iload #25
    //   8777: aload #6
    //   8779: iload #27
    //   8781: iinc #27, 1
    //   8784: iaload
    //   8785: ixor
    //   8786: istore #23
    //   8788: iload #22
    //   8790: aload #16
    //   8792: iload #23
    //   8794: bipush #63
    //   8796: iand
    //   8797: iaload
    //   8798: ior
    //   8799: istore #22
    //   8801: iload #22
    //   8803: aload #14
    //   8805: iload #23
    //   8807: bipush #8
    //   8809: iushr
    //   8810: bipush #63
    //   8812: iand
    //   8813: iaload
    //   8814: ior
    //   8815: istore #22
    //   8817: iload #22
    //   8819: aload #12
    //   8821: iload #23
    //   8823: bipush #16
    //   8825: iushr
    //   8826: bipush #63
    //   8828: iand
    //   8829: iaload
    //   8830: ior
    //   8831: istore #22
    //   8833: iload #22
    //   8835: aload #10
    //   8837: iload #23
    //   8839: bipush #24
    //   8841: iushr
    //   8842: bipush #63
    //   8844: iand
    //   8845: iaload
    //   8846: ior
    //   8847: istore #22
    //   8849: iload #24
    //   8851: iload #22
    //   8853: ixor
    //   8854: istore #24
    //   8856: iinc #26, 1
    //   8859: iload_2
    //   8860: ifne -> 8521
    //   8863: iload #24
    //   8865: bipush #31
    //   8867: ishl
    //   8868: iload #24
    //   8870: iconst_1
    //   8871: iushr
    //   8872: ior
    //   8873: istore #24
    //   8875: iload #25
    //   8877: iload #24
    //   8879: ixor
    //   8880: ldc -1431655766
    //   8882: iand
    //   8883: istore #23
    //   8885: iload #25
    //   8887: iload #23
    //   8889: ixor
    //   8890: istore #25
    //   8892: iload #24
    //   8894: iload #23
    //   8896: ixor
    //   8897: istore #24
    //   8899: iload #25
    //   8901: bipush #31
    //   8903: ishl
    //   8904: iload #25
    //   8906: iconst_1
    //   8907: iushr
    //   8908: ior
    //   8909: istore #25
    //   8911: iload #25
    //   8913: bipush #8
    //   8915: iushr
    //   8916: iload #24
    //   8918: ixor
    //   8919: ldc 16711935
    //   8921: iand
    //   8922: istore #23
    //   8924: iload #24
    //   8926: iload #23
    //   8928: ixor
    //   8929: istore #24
    //   8931: iload #25
    //   8933: iload #23
    //   8935: bipush #8
    //   8937: ishl
    //   8938: ixor
    //   8939: istore #25
    //   8941: iload #25
    //   8943: iconst_2
    //   8944: iushr
    //   8945: iload #24
    //   8947: ixor
    //   8948: ldc 858993459
    //   8950: iand
    //   8951: istore #23
    //   8953: iload #24
    //   8955: iload #23
    //   8957: ixor
    //   8958: istore #24
    //   8960: iload #25
    //   8962: iload #23
    //   8964: iconst_2
    //   8965: ishl
    //   8966: ixor
    //   8967: istore #25
    //   8969: iload #24
    //   8971: bipush #16
    //   8973: iushr
    //   8974: iload #25
    //   8976: ixor
    //   8977: ldc 65535
    //   8979: iand
    //   8980: istore #23
    //   8982: iload #25
    //   8984: iload #23
    //   8986: ixor
    //   8987: istore #25
    //   8989: iload #24
    //   8991: iload #23
    //   8993: bipush #16
    //   8995: ishl
    //   8996: ixor
    //   8997: istore #24
    //   8999: iload #24
    //   9001: iconst_4
    //   9002: iushr
    //   9003: iload #25
    //   9005: ixor
    //   9006: ldc 252645135
    //   9008: iand
    //   9009: istore #23
    //   9011: iload #25
    //   9013: iload #23
    //   9015: ixor
    //   9016: istore #25
    //   9018: iload #24
    //   9020: iload #23
    //   9022: iconst_4
    //   9023: ishl
    //   9024: ixor
    //   9025: istore #24
    //   9027: aload #18
    //   9029: iconst_0
    //   9030: iload #24
    //   9032: iastore
    //   9033: aload #18
    //   9035: iconst_1
    //   9036: iload #25
    //   9038: iastore
    //   9039: iload #20
    //   9041: bipush #8
    //   9043: imul
    //   9044: istore #28
    //   9046: iconst_0
    //   9047: istore #29
    //   9049: iload #29
    //   9051: iconst_2
    //   9052: if_icmpge -> 9141
    //   9055: aload #5
    //   9057: iload #28
    //   9059: iload #29
    //   9061: iconst_4
    //   9062: imul
    //   9063: iadd
    //   9064: aload #18
    //   9066: iload #29
    //   9068: iaload
    //   9069: bipush #24
    //   9071: iushr
    //   9072: i2b
    //   9073: bastore
    //   9074: aload #5
    //   9076: iload #28
    //   9078: iload #29
    //   9080: iconst_4
    //   9081: imul
    //   9082: iadd
    //   9083: iconst_1
    //   9084: iadd
    //   9085: aload #18
    //   9087: iload #29
    //   9089: iaload
    //   9090: bipush #16
    //   9092: iushr
    //   9093: i2b
    //   9094: bastore
    //   9095: aload #5
    //   9097: iload #28
    //   9099: iload #29
    //   9101: iconst_4
    //   9102: imul
    //   9103: iadd
    //   9104: iconst_2
    //   9105: iadd
    //   9106: aload #18
    //   9108: iload #29
    //   9110: iaload
    //   9111: bipush #8
    //   9113: iushr
    //   9114: i2b
    //   9115: bastore
    //   9116: aload #5
    //   9118: iload #28
    //   9120: iload #29
    //   9122: iconst_4
    //   9123: imul
    //   9124: iadd
    //   9125: iconst_3
    //   9126: iadd
    //   9127: aload #18
    //   9129: iload #29
    //   9131: iaload
    //   9132: i2b
    //   9133: bastore
    //   9134: iinc #29, 1
    //   9137: iload_2
    //   9138: ifne -> 9049
    //   9141: iinc #20, 1
    //   9144: iload_2
    //   9145: ifne -> 8226
    //   9148: getstatic burp/Ze8m.Zx : Ljava/lang/String;
    //   9151: getstatic burp/Zsf7.Zg : Ljava/lang/Object;
    //   9154: checkcast java/math/BigInteger
    //   9157: invokevirtual intValue : ()I
    //   9160: bipush #32
    //   9162: irem
    //   9163: invokestatic abs : (I)I
    //   9166: invokevirtual charAt : (I)C
    //   9169: getstatic burp/Zlck.ZL : Ljava/lang/String;
    //   9172: getstatic burp/Zg4d.Zm : Ljava/lang/Object;
    //   9175: checkcast java/math/BigInteger
    //   9178: invokevirtual intValue : ()I
    //   9181: bipush #32
    //   9183: irem
    //   9184: invokestatic abs : (I)I
    //   9187: invokevirtual charAt : (I)C
    //   9190: if_icmple -> 9305
    //   9193: getstatic burp/Zlnm.ZL : Ljava/lang/String;
    //   9196: getstatic burp/Zeb7.ZJ : Ljava/lang/Object;
    //   9199: checkcast java/math/BigInteger
    //   9202: invokevirtual intValue : ()I
    //   9205: bipush #32
    //   9207: irem
    //   9208: invokestatic abs : (I)I
    //   9211: invokevirtual charAt : (I)C
    //   9214: getstatic burp/Zs8y.Zr : Ljava/lang/String;
    //   9217: getstatic burp/Zlck.Zr : Ljava/lang/Object;
    //   9220: checkcast java/math/BigInteger
    //   9223: invokevirtual intValue : ()I
    //   9226: bipush #32
    //   9228: irem
    //   9229: invokestatic abs : (I)I
    //   9232: invokevirtual charAt : (I)C
    //   9235: if_icmpgt -> 9305
    //   9238: goto -> 9245
    //   9241: invokestatic a : (Ljava/lang/Throwable;)Ljava/lang/Throwable;
    //   9244: athrow
    //   9245: getstatic burp/Ztlz.ZE : Ljava/lang/String;
    //   9248: getstatic burp/Zevr.ZG : Ljava/lang/Object;
    //   9251: checkcast java/math/BigInteger
    //   9254: invokevirtual intValue : ()I
    //   9257: bipush #32
    //   9259: irem
    //   9260: invokestatic abs : (I)I
    //   9263: invokevirtual charAt : (I)C
    //   9266: getstatic burp/Zxe.ZD : Ljava/lang/String;
    //   9269: getstatic burp/Zxo7.Zi : Ljava/lang/Object;
    //   9272: checkcast java/math/BigInteger
    //   9275: invokevirtual intValue : ()I
    //   9278: bipush #32
    //   9280: irem
    //   9281: invokestatic abs : (I)I
    //   9284: invokevirtual charAt : (I)C
    //   9287: if_icmpgt -> 9305
    //   9290: goto -> 9297
    //   9293: invokestatic a : (Ljava/lang/Throwable;)Ljava/lang/Throwable;
    //   9296: athrow
    //   9297: iconst_1
    //   9298: goto -> 9306
    //   9301: invokestatic a : (Ljava/lang/Throwable;)Ljava/lang/Throwable;
    //   9304: athrow
    //   9305: iconst_0
    //   9306: ireturn
    //   9307: astore_3
    //   9308: new java/lang/Exception
    //   9311: dup
    //   9312: aload_3
    //   9313: invokevirtual getMessage : ()Ljava/lang/String;
    //   9316: invokespecial <init> : (Ljava/lang/String;)V
    //   9319: athrow
    // Exception table:
    //   from	to	target	type
    //   4	9306	9307	java/lang/Throwable
    //   395	410	410	java/lang/Throwable
    //   1412	1438	1438	java/lang/Throwable
    //   1519	1534	1534	java/lang/Throwable
    //   2716	2741	2744	java/lang/Throwable
    //   2785	2958	2961	java/lang/Throwable
    //   2928	2995	2998	java/lang/Throwable
    //   2965	3032	3035	java/lang/Throwable
    //   3002	3069	3072	java/lang/Throwable
    //   3039	3106	3109	java/lang/Throwable
    //   3076	3143	3146	java/lang/Throwable
    //   3113	3180	3183	java/lang/Throwable
    //   3150	3217	3220	java/lang/Throwable
    //   3187	3254	3257	java/lang/Throwable
    //   3224	3291	3294	java/lang/Throwable
    //   3261	3328	3331	java/lang/Throwable
    //   3298	3365	3368	java/lang/Throwable
    //   3335	3402	3405	java/lang/Throwable
    //   3372	3439	3442	java/lang/Throwable
    //   3409	3476	3479	java/lang/Throwable
    //   3446	3513	3516	java/lang/Throwable
    //   3483	3550	3553	java/lang/Throwable
    //   3520	3587	3590	java/lang/Throwable
    //   3557	3624	3627	java/lang/Throwable
    //   3594	3661	3664	java/lang/Throwable
    //   3631	3698	3701	java/lang/Throwable
    //   3668	3735	3738	java/lang/Throwable
    //   3705	3772	3775	java/lang/Throwable
    //   3742	3809	3812	java/lang/Throwable
    //   3779	3846	3849	java/lang/Throwable
    //   3816	3883	3886	java/lang/Throwable
    //   3853	3920	3923	java/lang/Throwable
    //   3890	3957	3960	java/lang/Throwable
    //   3927	3994	3997	java/lang/Throwable
    //   3964	4031	4034	java/lang/Throwable
    //   4001	4068	4071	java/lang/Throwable
    //   4038	4101	4104	java/lang/Throwable
    //   4167	4181	4181	java/lang/Throwable
    //   4192	4205	4208	java/lang/Throwable
    //   4197	4220	4223	java/lang/Throwable
    //   4212	4238	4241	java/lang/Throwable
    //   4227	4268	4271	java/lang/Throwable
    //   4334	4361	4364	java/lang/Throwable
    //   4351	4382	4385	java/lang/Throwable
    //   4368	4412	4415	java/lang/Throwable
    //   4389	4423	4423	java/lang/Throwable
    //   4434	4450	4453	java/lang/Throwable
    //   4530	4544	4544	java/lang/Throwable
    //   4555	4568	4571	java/lang/Throwable
    //   4560	4583	4586	java/lang/Throwable
    //   4575	4601	4604	java/lang/Throwable
    //   4590	4631	4634	java/lang/Throwable
    //   4697	4724	4727	java/lang/Throwable
    //   4714	4745	4748	java/lang/Throwable
    //   4731	4775	4778	java/lang/Throwable
    //   4752	4786	4786	java/lang/Throwable
    //   4797	4813	4816	java/lang/Throwable
    //   9148	9238	9241	java/lang/Throwable
    //   9193	9290	9293	java/lang/Throwable
    //   9245	9301	9301	java/lang/Throwable
  }
  
  static {
    // Byte code:
    //   0: bipush #14
    //   2: anewarray java/lang/String
    //   5: astore #5
    //   7: iconst_0
    //   8: istore_3
    //   9: ldc '|heM+CLqae\\tHH[.??Qw 3b&[OZHd][dH*\\t0E&6\\tdkM8B7XD@0|\\t%Y63I0Q[uVt]_Y.oAq3{;/}SU~ap??\\tQAQ _O!3^FC#!zs'
    //   11: dup
    //   12: astore_2
    //   13: invokevirtual length : ()I
    //   16: istore #4
    //   18: bipush #19
    //   20: istore_1
    //   21: iconst_m1
    //   22: istore_0
    //   23: bipush #7
    //   25: iinc #0, 1
    //   28: aload_2
    //   29: iload_0
    //   30: dup
    //   31: iload_1
    //   32: iadd
    //   33: invokevirtual substring : (II)Ljava/lang/String;
    //   36: iconst_m1
    //   37: goto -> 143
    //   40: aload #5
    //   42: swap
    //   43: iload_3
    //   44: iinc #3, 1
    //   47: swap
    //   48: aastore
    //   49: iload_0
    //   50: iload_1
    //   51: iadd
    //   52: dup
    //   53: istore_0
    //   54: iload #4
    //   56: if_icmpge -> 68
    //   59: aload_2
    //   60: iload_0
    //   61: invokevirtual charAt : (I)C
    //   64: istore_1
    //   65: goto -> 23
    //   68: ldc 'G+\\tz6+W2'
    //   70: dup
    //   71: astore_2
    //   72: invokevirtual length : ()I
    //   75: istore #4
    //   77: bipush #9
    //   79: istore_1
    //   80: iconst_m1
    //   81: istore_0
    //   82: bipush #100
    //   84: iinc #0, 1
    //   87: aload_2
    //   88: iload_0
    //   89: dup
    //   90: iload_1
    //   91: iadd
    //   92: invokevirtual substring : (II)Ljava/lang/String;
    //   95: iconst_0
    //   96: goto -> 143
    //   99: aload #5
    //   101: swap
    //   102: iload_3
    //   103: iinc #3, 1
    //   106: swap
    //   107: aastore
    //   108: iload_0
    //   109: iload_1
    //   110: iadd
    //   111: dup
    //   112: istore_0
    //   113: iload #4
    //   115: if_icmpge -> 127
    //   118: aload_2
    //   119: iload_0
    //   120: invokevirtual charAt : (I)C
    //   123: istore_1
    //   124: goto -> 82
    //   127: aload #5
    //   129: putstatic burp/Zs75.a : [Ljava/lang/String;
    //   132: bipush #14
    //   134: anewarray java/lang/String
    //   137: putstatic burp/Zs75.b : [Ljava/lang/String;
    //   140: goto -> 300
    //   143: dup_x2
    //   144: pop
    //   145: invokevirtual toCharArray : ()[C
    //   148: dup_x1
    //   149: arraylength
    //   150: dup_x2
    //   151: pop
    //   152: iconst_0
    //   153: istore #6
    //   155: dup2_x1
    //   156: pop2
    //   157: dup_x2
    //   158: iconst_1
    //   159: if_icmpgt -> 260
    //   162: dup2
    //   163: swap
    //   164: iload #6
    //   166: dup2_x1
    //   167: caload
    //   168: swap
    //   169: iload #6
    //   171: bipush #7
    //   173: irem
    //   174: tableswitch default -> 242, 0 -> 212, 1 -> 217, 2 -> 222, 3 -> 227, 4 -> 232, 5 -> 237
    //   212: bipush #120
    //   214: goto -> 244
    //   217: bipush #83
    //   219: goto -> 244
    //   222: bipush #119
    //   224: goto -> 244
    //   227: bipush #103
    //   229: goto -> 244
    //   232: bipush #112
    //   234: goto -> 244
    //   237: bipush #125
    //   239: goto -> 244
    //   242: bipush #71
    //   244: ixor
    //   245: ixor
    //   246: i2c
    //   247: castore
    //   248: iinc #6, 1
    //   251: dup
    //   252: ifne -> 260
    //   255: dup2
    //   256: dup_x1
    //   257: goto -> 166
    //   260: dup2_x1
    //   261: pop2
    //   262: dup_x2
    //   263: iload #6
    //   265: if_icmpgt -> 162
    //   268: pop
    //   269: new java/lang/String
    //   272: dup_x1
    //   273: swap
    //   274: invokespecial <init> : ([C)V
    //   277: invokevirtual intern : ()Ljava/lang/String;
    //   280: swap
    //   281: pop
    //   282: swap
    //   283: tableswitch default -> 40, 0 -> 99
    //   300: sipush #-1882
    //   303: sipush #27561
    //   306: invokestatic a : (II)Ljava/lang/String;
    //   309: putstatic burp/Zs75.Zn : Ljava/lang/String;
    //   312: new java/math/BigInteger
    //   315: dup
    //   316: iconst_1
    //   317: bipush #32
    //   319: newarray byte
    //   321: dup
    //   322: iconst_0
    //   323: bipush #21
    //   325: bastore
    //   326: dup
    //   327: iconst_1
    //   328: bipush #-96
    //   330: bastore
    //   331: dup
    //   332: iconst_2
    //   333: bipush #8
    //   335: bastore
    //   336: dup
    //   337: iconst_3
    //   338: bipush #87
    //   340: bastore
    //   341: dup
    //   342: iconst_4
    //   343: bipush #110
    //   345: bastore
    //   346: dup
    //   347: iconst_5
    //   348: bipush #31
    //   350: bastore
    //   351: dup
    //   352: bipush #6
    //   354: bipush #46
    //   356: bastore
    //   357: dup
    //   358: bipush #7
    //   360: bipush #-94
    //   362: bastore
    //   363: dup
    //   364: bipush #8
    //   366: bipush #31
    //   368: bastore
    //   369: dup
    //   370: bipush #9
    //   372: bipush #-19
    //   374: bastore
    //   375: dup
    //   376: bipush #10
    //   378: bipush #-75
    //   380: bastore
    //   381: dup
    //   382: bipush #11
    //   384: bipush #-74
    //   386: bastore
    //   387: dup
    //   388: bipush #12
    //   390: bipush #110
    //   392: bastore
    //   393: dup
    //   394: bipush #13
    //   396: bipush #25
    //   398: bastore
    //   399: dup
    //   400: bipush #14
    //   402: bipush #-80
    //   404: bastore
    //   405: dup
    //   406: bipush #15
    //   408: bipush #-28
    //   410: bastore
    //   411: dup
    //   412: bipush #16
    //   414: bipush #31
    //   416: bastore
    //   417: dup
    //   418: bipush #17
    //   420: bipush #52
    //   422: bastore
    //   423: dup
    //   424: bipush #18
    //   426: bipush #-96
    //   428: bastore
    //   429: dup
    //   430: bipush #19
    //   432: bipush #-88
    //   434: bastore
    //   435: dup
    //   436: bipush #20
    //   438: bipush #93
    //   440: bastore
    //   441: dup
    //   442: bipush #21
    //   444: bipush #-29
    //   446: bastore
    //   447: dup
    //   448: bipush #22
    //   450: bipush #-81
    //   452: bastore
    //   453: dup
    //   454: bipush #23
    //   456: bipush #89
    //   458: bastore
    //   459: dup
    //   460: bipush #24
    //   462: bipush #12
    //   464: bastore
    //   465: dup
    //   466: bipush #25
    //   468: bipush #65
    //   470: bastore
    //   471: dup
    //   472: bipush #26
    //   474: bipush #52
    //   476: bastore
    //   477: dup
    //   478: bipush #27
    //   480: bipush #44
    //   482: bastore
    //   483: dup
    //   484: bipush #28
    //   486: bipush #34
    //   488: bastore
    //   489: dup
    //   490: bipush #29
    //   492: bipush #-88
    //   494: bastore
    //   495: dup
    //   496: bipush #30
    //   498: bipush #95
    //   500: bastore
    //   501: dup
    //   502: bipush #31
    //   504: bipush #55
    //   506: bastore
    //   507: invokespecial <init> : (I[B)V
    //   510: putstatic burp/Zs75.Zo : Ljava/lang/Object;
    //   513: return
  }
  
  private static Throwable a(Throwable paramThrowable) {
    return paramThrowable;
  }
  
  private static String a(int paramInt1, int paramInt2) {
    int i = (paramInt1 ^ 0xFFFFF8A2) & 0xFFFF;
    if (b[i] == null) {
      char[] arrayOfChar = a[i].toCharArray();
      switch (arrayOfChar[0] & 0xFF) {
        case 0:
        
        case 1:
        
        case 2:
        
        case 3:
        
        case 4:
        
        case 5:
        
        case 6:
        
        case 7:
        
        case 8:
        
        case 9:
        
        case 10:
        
        case 11:
        
        case 12:
        
        case 13:
        
        case 14:
        
        case 15:
        
        case 16:
        
        case 17:
        
        case 18:
        
        case 19:
        
        case 20:
        
        case 21:
        
        case 22:
        
        case 23:
        
        case 24:
        
        case 25:
        
        case 26:
        
        case 27:
        
        case 28:
        
        case 29:
        
        case 30:
        
        case 31:
        
        case 32:
        
        case 33:
        
        case 34:
        
        case 35:
        
        case 36:
        
        case 37:
        
        case 38:
        
        case 39:
        
        case 40:
        
        case 41:
        
        case 42:
        
        case 43:
        
        case 44:
        
        case 45:
        
        case 46:
        
        case 47:
        
        case 48:
        
        case 49:
        
        case 50:
        
        case 51:
        
        case 52:
        
        case 53:
        
        case 54:
        
        case 55:
        
        case 56:
        
        case 57:
        
        case 58:
        
        case 59:
        
        case 60:
        
        case 61:
        
        case 62:
        
        case 63:
        
        case 64:
        
        case 65:
        
        case 66:
        
        case 67:
        
        case 68:
        
        case 69:
        
        case 70:
        
        case 71:
        
        case 72:
        
        case 73:
        
        case 74:
        
        case 75:
        
        case 76:
        
        case 77:
        
        case 78:
        
        case 79:
        
        case 80:
        
        case 81:
        
        case 82:
        
        case 83:
        
        case 84:
        
        case 85:
        
        case 86:
        
        case 87:
        
        case 88:
        
        case 89:
        
        case 90:
        
        case 91:
        
        case 92:
        
        case 93:
        
        case 94:
        
        case 95:
        
        case 96:
        
        case 97:
        
        case 98:
        
        case 99:
        
        case 100:
        
        case 101:
        
        case 102:
        
        case 103:
        
        case 104:
        
        case 105:
        
        case 106:
        
        case 107:
        
        case 108:
        
        case 109:
        
        case 110:
        
        case 111:
        
        case 112:
        
        case 113:
        
        case 114:
        
        case 115:
        
        case 116:
        
        case 117:
        
        case 118:
        
        case 119:
        
        case 120:
        
        case 121:
        
        case 122:
        
        case 123:
        
        case 124:
        
        case 125:
        
        case 126:
        
        case 127:
        
        case 128:
        
        case 129:
        
        case 130:
        
        case 131:
        
        case 132:
        
        case 133:
        
        case 134:
        
        case 135:
        
        case 136:
        
        case 137:
        
        case 138:
        
        case 139:
        
        case 140:
        
        case 141:
        
        case 142:
        
        case 143:
        
        case 144:
        
        case 145:
        
        case 146:
        
        case 147:
        
        case 148:
        
        case 149:
        
        case 150:
        
        case 151:
        
        case 152:
        
        case 153:
        
        case 154:
        
        case 155:
        
        case 156:
        
        case 157:
        
        case 158:
        
        case 159:
        
        case 160:
        
        case 161:
        
        case 162:
        
        case 163:
        
        case 164:
        
        case 165:
        
        case 166:
        
        case 167:
        
        case 168:
        
        case 169:
        
        case 170:
        
        case 171:
        
        case 172:
        
        case 173:
        
        case 174:
        
        case 175:
        
        case 176:
        
        case 177:
        
        case 178:
        
        case 179:
        
        case 180:
        
        case 181:
        
        case 182:
        
        case 183:
        
        case 184:
        
        case 185:
        
        case 186:
        
        case 187:
        
        case 188:
        
        case 189:
        
        case 190:
        
        case 191:
        
        case 192:
        
        case 193:
        
        case 194:
        
        case 195:
        
        case 196:
        
        case 197:
        
        case 198:
        
        case 199:
        
        case 200:
        
        case 201:
        
        case 202:
        
        case 203:
        
        case 204:
        
        case 205:
        
        case 206:
        
        case 207:
        
        case 208:
        
        case 209:
        
        case 210:
        
        case 211:
        
        case 212:
        
        case 213:
        
        case 214:
        
        case 215:
        
        case 216:
        
        case 217:
        
        case 218:
        
        case 219:
        
        case 220:
        
        case 221:
        
        case 222:
        
        case 223:
        
        case 224:
        
        case 225:
        
        case 226:
        
        case 227:
        
        case 228:
        
        case 229:
        
        case 230:
        
        case 231:
        
        case 232:
        
        case 233:
        
        case 234:
        
        case 235:
        
        case 236:
        
        case 237:
        
        case 238:
        
        case 239:
        
        case 240:
        
        case 241:
        
        case 242:
        
        case 243:
        
        case 244:
        
        case 245:
        
        case 246:
        
        case 247:
        
        case 248:
        
        case 249:
        
        case 250:
        
        case 251:
        
        case 252:
        
        case 253:
        
        case 254:
        
        default:
          break;
      } 
      byte b1 = 20;
      int j = (paramInt2 & 0xFF) - b1;
      if (j < 0)
        j += 256; 
      int k = ((paramInt2 & 0xFFFF) >>> 8) - b1;
      if (k < 0)
        k += 256; 
      for (byte b2 = 0; b2 < arrayOfChar.length; b2++) {
        int m = b2 % 2;
        if (m == 0) {
          arrayOfChar[b2] = (char)(arrayOfChar[b2] ^ j);
          j = ((j >>> 3 | j << 5) ^ arrayOfChar[b2]) & 0xFF;
        } else {
          arrayOfChar[b2] = (char)(arrayOfChar[b2] ^ k);
          k = ((k >>> 3 | k << 5) ^ arrayOfChar[b2]) & 0xFF;
        } 
      } 
      b[i] = (new String(arrayOfChar)).intern();
    } 
    return b[i];
  }
}


/* Location:              C:\Program Files\BurpSuitePro\burpsuite_pro.jar!\burp\Zs75.class
 * Java compiler version: 21 (65.0)
 * JD-Core Version:       1.1.3
 */