package burp;

import java.math.BigInteger;

class Zs_v extends ClassLoader {
  static String Zn;
  
  static Object Zs;
  
  private static final String[] a;
  
  private static final String[] b;
  
  static void Zh(Object[] paramArrayOfObject, Object paramObject) throws Throwable {}
  
  static void ZA(Object paramObject) {
    Zb8y.Zn = a(-14363, -21260);
    Zb8y.ZI = new BigInteger(a(-14368, 17152));
    boolean bool = Zt2e.ZN();
    try {
      try {
        if (Zke7.Zl.charAt(Math.abs(((BigInteger)Zest.Zq).intValue() % 32)) <= Zkm0.ZL.charAt(Math.abs(((BigInteger)Ze8i.Zq).intValue() % 32))) {
          try {
            Zm3s.Zx(Class.forName(a(-14342, -1892)));
            if (!bool)
              Zlnm.ZC(Class.forName(a(-14354, 24160))); 
          } catch (Throwable throwable) {
            throw a(null);
          } 
          return;
        } 
      } catch (Throwable throwable) {
        throw a(null);
      } 
      Zlnm.ZC(Class.forName(a(-14354, 24160)));
    } catch (Throwable throwable) {}
  }
  
  static boolean ZP(Object[] paramArrayOfObject, Object paramObject) throws Throwable {
    // Byte code:
    //   0: invokestatic ZK : ()Z
    //   3: istore_2
    //   4: new java/lang/StringBuilder
    //   7: dup
    //   8: invokespecial <init> : ()V
    //   11: astore_3
    //   12: iconst_0
    //   13: istore #4
    //   15: iload #4
    //   17: bipush #32
    //   19: if_icmpge -> 1355
    //   22: iload #4
    //   24: tableswitch default -> 1348, 0 -> 168, 1 -> 205, 2 -> 242, 3 -> 279, 4 -> 316, 5 -> 353, 6 -> 390, 7 -> 427, 8 -> 464, 9 -> 501, 10 -> 538, 11 -> 575, 12 -> 612, 13 -> 649, 14 -> 686, 15 -> 723, 16 -> 760, 17 -> 797, 18 -> 834, 19 -> 871, 20 -> 908, 21 -> 945, 22 -> 982, 23 -> 1019, 24 -> 1056, 25 -> 1093, 26 -> 1130, 27 -> 1167, 28 -> 1204, 29 -> 1241, 30 -> 1278, 31 -> 1315
    //   168: aload_3
    //   169: getstatic burp/Zs75.Zn : Ljava/lang/String;
    //   172: getstatic burp/Zsxh.Zk : Ljava/lang/Object;
    //   175: checkcast java/math/BigInteger
    //   178: invokevirtual intValue : ()I
    //   181: bipush #32
    //   183: irem
    //   184: invokestatic abs : (I)I
    //   187: invokevirtual charAt : (I)C
    //   190: invokevirtual append : (C)Ljava/lang/StringBuilder;
    //   193: pop
    //   194: iload_2
    //   195: ifeq -> 1348
    //   198: goto -> 205
    //   201: invokestatic a : (Ljava/lang/Throwable;)Ljava/lang/Throwable;
    //   204: athrow
    //   205: aload_3
    //   206: getstatic burp/Zzc_.Zg : Ljava/lang/String;
    //   209: getstatic burp/Zzyr.Za : Ljava/lang/Object;
    //   212: checkcast java/math/BigInteger
    //   215: invokevirtual intValue : ()I
    //   218: bipush #32
    //   220: irem
    //   221: invokestatic abs : (I)I
    //   224: invokevirtual charAt : (I)C
    //   227: invokevirtual append : (C)Ljava/lang/StringBuilder;
    //   230: pop
    //   231: iload_2
    //   232: ifeq -> 1348
    //   235: goto -> 242
    //   238: invokestatic a : (Ljava/lang/Throwable;)Ljava/lang/Throwable;
    //   241: athrow
    //   242: aload_3
    //   243: getstatic burp/Zzmw.Zd : Ljava/lang/String;
    //   246: getstatic burp/Zt0t.ZL : Ljava/lang/Object;
    //   249: checkcast java/math/BigInteger
    //   252: invokevirtual intValue : ()I
    //   255: bipush #32
    //   257: irem
    //   258: invokestatic abs : (I)I
    //   261: invokevirtual charAt : (I)C
    //   264: invokevirtual append : (C)Ljava/lang/StringBuilder;
    //   267: pop
    //   268: iload_2
    //   269: ifeq -> 1348
    //   272: goto -> 279
    //   275: invokestatic a : (Ljava/lang/Throwable;)Ljava/lang/Throwable;
    //   278: athrow
    //   279: aload_3
    //   280: getstatic burp/Zmyg.ZE : Ljava/lang/String;
    //   283: getstatic burp/Ztcv.ZY : Ljava/lang/Object;
    //   286: checkcast java/math/BigInteger
    //   289: invokevirtual intValue : ()I
    //   292: bipush #32
    //   294: irem
    //   295: invokestatic abs : (I)I
    //   298: invokevirtual charAt : (I)C
    //   301: invokevirtual append : (C)Ljava/lang/StringBuilder;
    //   304: pop
    //   305: iload_2
    //   306: ifeq -> 1348
    //   309: goto -> 316
    //   312: invokestatic a : (Ljava/lang/Throwable;)Ljava/lang/Throwable;
    //   315: athrow
    //   316: aload_3
    //   317: getstatic burp/Zke7.Zl : Ljava/lang/String;
    //   320: getstatic burp/Zgqi.Zp : Ljava/lang/Object;
    //   323: checkcast java/math/BigInteger
    //   326: invokevirtual intValue : ()I
    //   329: bipush #32
    //   331: irem
    //   332: invokestatic abs : (I)I
    //   335: invokevirtual charAt : (I)C
    //   338: invokevirtual append : (C)Ljava/lang/StringBuilder;
    //   341: pop
    //   342: iload_2
    //   343: ifeq -> 1348
    //   346: goto -> 353
    //   349: invokestatic a : (Ljava/lang/Throwable;)Ljava/lang/Throwable;
    //   352: athrow
    //   353: aload_3
    //   354: getstatic burp/Zevr.Zk : Ljava/lang/String;
    //   357: getstatic burp/Zs_3.ZZ : Ljava/lang/Object;
    //   360: checkcast java/math/BigInteger
    //   363: invokevirtual intValue : ()I
    //   366: bipush #32
    //   368: irem
    //   369: invokestatic abs : (I)I
    //   372: invokevirtual charAt : (I)C
    //   375: invokevirtual append : (C)Ljava/lang/StringBuilder;
    //   378: pop
    //   379: iload_2
    //   380: ifeq -> 1348
    //   383: goto -> 390
    //   386: invokestatic a : (Ljava/lang/Throwable;)Ljava/lang/Throwable;
    //   389: athrow
    //   390: aload_3
    //   391: getstatic burp/Ze8m.Zx : Ljava/lang/String;
    //   394: getstatic burp/Zk7e.ZW : Ljava/lang/Object;
    //   397: checkcast java/math/BigInteger
    //   400: invokevirtual intValue : ()I
    //   403: bipush #32
    //   405: irem
    //   406: invokestatic abs : (I)I
    //   409: invokevirtual charAt : (I)C
    //   412: invokevirtual append : (C)Ljava/lang/StringBuilder;
    //   415: pop
    //   416: iload_2
    //   417: ifeq -> 1348
    //   420: goto -> 427
    //   423: invokestatic a : (Ljava/lang/Throwable;)Ljava/lang/Throwable;
    //   426: athrow
    //   427: aload_3
    //   428: getstatic burp/Zm6h.Za : Ljava/lang/String;
    //   431: getstatic burp/Zs8y.ZG : Ljava/lang/Object;
    //   434: checkcast java/math/BigInteger
    //   437: invokevirtual intValue : ()I
    //   440: bipush #32
    //   442: irem
    //   443: invokestatic abs : (I)I
    //   446: invokevirtual charAt : (I)C
    //   449: invokevirtual append : (C)Ljava/lang/StringBuilder;
    //   452: pop
    //   453: iload_2
    //   454: ifeq -> 1348
    //   457: goto -> 464
    //   460: invokestatic a : (Ljava/lang/Throwable;)Ljava/lang/Throwable;
    //   463: athrow
    //   464: aload_3
    //   465: getstatic burp/Ztdd.ZA : Ljava/lang/String;
    //   468: getstatic burp/Zltz.Zg : Ljava/lang/Object;
    //   471: checkcast java/math/BigInteger
    //   474: invokevirtual intValue : ()I
    //   477: bipush #32
    //   479: irem
    //   480: invokestatic abs : (I)I
    //   483: invokevirtual charAt : (I)C
    //   486: invokevirtual append : (C)Ljava/lang/StringBuilder;
    //   489: pop
    //   490: iload_2
    //   491: ifeq -> 1348
    //   494: goto -> 501
    //   497: invokestatic a : (Ljava/lang/Throwable;)Ljava/lang/Throwable;
    //   500: athrow
    //   501: aload_3
    //   502: getstatic burp/Ztye.ZR : Ljava/lang/String;
    //   505: getstatic burp/Zmyg.Zj : Ljava/lang/Object;
    //   508: checkcast java/math/BigInteger
    //   511: invokevirtual intValue : ()I
    //   514: bipush #32
    //   516: irem
    //   517: invokestatic abs : (I)I
    //   520: invokevirtual charAt : (I)C
    //   523: invokevirtual append : (C)Ljava/lang/StringBuilder;
    //   526: pop
    //   527: iload_2
    //   528: ifeq -> 1348
    //   531: goto -> 538
    //   534: invokestatic a : (Ljava/lang/Throwable;)Ljava/lang/Throwable;
    //   537: athrow
    //   538: aload_3
    //   539: getstatic burp/Zm6h.Za : Ljava/lang/String;
    //   542: getstatic burp/Zeb7.ZJ : Ljava/lang/Object;
    //   545: checkcast java/math/BigInteger
    //   548: invokevirtual intValue : ()I
    //   551: bipush #32
    //   553: irem
    //   554: invokestatic abs : (I)I
    //   557: invokevirtual charAt : (I)C
    //   560: invokevirtual append : (C)Ljava/lang/StringBuilder;
    //   563: pop
    //   564: iload_2
    //   565: ifeq -> 1348
    //   568: goto -> 575
    //   571: invokestatic a : (Ljava/lang/Throwable;)Ljava/lang/Throwable;
    //   574: athrow
    //   575: aload_3
    //   576: getstatic burp/Zlf0.ZS : Ljava/lang/String;
    //   579: getstatic burp/Zzr5.Za : Ljava/lang/Object;
    //   582: checkcast java/math/BigInteger
    //   585: invokevirtual intValue : ()I
    //   588: bipush #32
    //   590: irem
    //   591: invokestatic abs : (I)I
    //   594: invokevirtual charAt : (I)C
    //   597: invokevirtual append : (C)Ljava/lang/StringBuilder;
    //   600: pop
    //   601: iload_2
    //   602: ifeq -> 1348
    //   605: goto -> 612
    //   608: invokestatic a : (Ljava/lang/Throwable;)Ljava/lang/Throwable;
    //   611: athrow
    //   612: aload_3
    //   613: getstatic burp/Zmx6.ZG : Ljava/lang/String;
    //   616: getstatic burp/Zmr7.ZO : Ljava/lang/Object;
    //   619: checkcast java/math/BigInteger
    //   622: invokevirtual intValue : ()I
    //   625: bipush #32
    //   627: irem
    //   628: invokestatic abs : (I)I
    //   631: invokevirtual charAt : (I)C
    //   634: invokevirtual append : (C)Ljava/lang/StringBuilder;
    //   637: pop
    //   638: iload_2
    //   639: ifeq -> 1348
    //   642: goto -> 649
    //   645: invokestatic a : (Ljava/lang/Throwable;)Ljava/lang/Throwable;
    //   648: athrow
    //   649: aload_3
    //   650: getstatic burp/Zs34.Zq : Ljava/lang/String;
    //   653: getstatic burp/Zb.ZV : Ljava/lang/Object;
    //   656: checkcast java/math/BigInteger
    //   659: invokevirtual intValue : ()I
    //   662: bipush #32
    //   664: irem
    //   665: invokestatic abs : (I)I
    //   668: invokevirtual charAt : (I)C
    //   671: invokevirtual append : (C)Ljava/lang/StringBuilder;
    //   674: pop
    //   675: iload_2
    //   676: ifeq -> 1348
    //   679: goto -> 686
    //   682: invokestatic a : (Ljava/lang/Throwable;)Ljava/lang/Throwable;
    //   685: athrow
    //   686: aload_3
    //   687: getstatic burp/Zt0t.ZR : Ljava/lang/String;
    //   690: getstatic burp/Zk7e.ZW : Ljava/lang/Object;
    //   693: checkcast java/math/BigInteger
    //   696: invokevirtual intValue : ()I
    //   699: bipush #32
    //   701: irem
    //   702: invokestatic abs : (I)I
    //   705: invokevirtual charAt : (I)C
    //   708: invokevirtual append : (C)Ljava/lang/StringBuilder;
    //   711: pop
    //   712: iload_2
    //   713: ifeq -> 1348
    //   716: goto -> 723
    //   719: invokestatic a : (Ljava/lang/Throwable;)Ljava/lang/Throwable;
    //   722: athrow
    //   723: aload_3
    //   724: getstatic burp/Zmsn.ZD : Ljava/lang/String;
    //   727: getstatic burp/Zlr.ZK : Ljava/lang/Object;
    //   730: checkcast java/math/BigInteger
    //   733: invokevirtual intValue : ()I
    //   736: bipush #32
    //   738: irem
    //   739: invokestatic abs : (I)I
    //   742: invokevirtual charAt : (I)C
    //   745: invokevirtual append : (C)Ljava/lang/StringBuilder;
    //   748: pop
    //   749: iload_2
    //   750: ifeq -> 1348
    //   753: goto -> 760
    //   756: invokestatic a : (Ljava/lang/Throwable;)Ljava/lang/Throwable;
    //   759: athrow
    //   760: aload_3
    //   761: getstatic burp/Zlem.Zl : Ljava/lang/String;
    //   764: getstatic burp/Zz6t.ZA : Ljava/lang/Object;
    //   767: checkcast java/math/BigInteger
    //   770: invokevirtual intValue : ()I
    //   773: bipush #32
    //   775: irem
    //   776: invokestatic abs : (I)I
    //   779: invokevirtual charAt : (I)C
    //   782: invokevirtual append : (C)Ljava/lang/StringBuilder;
    //   785: pop
    //   786: iload_2
    //   787: ifeq -> 1348
    //   790: goto -> 797
    //   793: invokestatic a : (Ljava/lang/Throwable;)Ljava/lang/Throwable;
    //   796: athrow
    //   797: aload_3
    //   798: getstatic burp/Zrtc.Zl : Ljava/lang/String;
    //   801: getstatic burp/Zg4d.Zm : Ljava/lang/Object;
    //   804: checkcast java/math/BigInteger
    //   807: invokevirtual intValue : ()I
    //   810: bipush #32
    //   812: irem
    //   813: invokestatic abs : (I)I
    //   816: invokevirtual charAt : (I)C
    //   819: invokevirtual append : (C)Ljava/lang/StringBuilder;
    //   822: pop
    //   823: iload_2
    //   824: ifeq -> 1348
    //   827: goto -> 834
    //   830: invokestatic a : (Ljava/lang/Throwable;)Ljava/lang/Throwable;
    //   833: athrow
    //   834: aload_3
    //   835: getstatic burp/Zevr.Zk : Ljava/lang/String;
    //   838: getstatic burp/Zm3p.Zz : Ljava/lang/Object;
    //   841: checkcast java/math/BigInteger
    //   844: invokevirtual intValue : ()I
    //   847: bipush #32
    //   849: irem
    //   850: invokestatic abs : (I)I
    //   853: invokevirtual charAt : (I)C
    //   856: invokevirtual append : (C)Ljava/lang/StringBuilder;
    //   859: pop
    //   860: iload_2
    //   861: ifeq -> 1348
    //   864: goto -> 871
    //   867: invokestatic a : (Ljava/lang/Throwable;)Ljava/lang/Throwable;
    //   870: athrow
    //   871: aload_3
    //   872: getstatic burp/Zmsn.ZD : Ljava/lang/String;
    //   875: getstatic burp/Zrtv.Zg : Ljava/lang/Object;
    //   878: checkcast java/math/BigInteger
    //   881: invokevirtual intValue : ()I
    //   884: bipush #32
    //   886: irem
    //   887: invokestatic abs : (I)I
    //   890: invokevirtual charAt : (I)C
    //   893: invokevirtual append : (C)Ljava/lang/StringBuilder;
    //   896: pop
    //   897: iload_2
    //   898: ifeq -> 1348
    //   901: goto -> 908
    //   904: invokestatic a : (Ljava/lang/Throwable;)Ljava/lang/Throwable;
    //   907: athrow
    //   908: aload_3
    //   909: getstatic burp/Zmj8.ZL : Ljava/lang/String;
    //   912: getstatic burp/Ztlz.ZW : Ljava/lang/Object;
    //   915: checkcast java/math/BigInteger
    //   918: invokevirtual intValue : ()I
    //   921: bipush #32
    //   923: irem
    //   924: invokestatic abs : (I)I
    //   927: invokevirtual charAt : (I)C
    //   930: invokevirtual append : (C)Ljava/lang/StringBuilder;
    //   933: pop
    //   934: iload_2
    //   935: ifeq -> 1348
    //   938: goto -> 945
    //   941: invokestatic a : (Ljava/lang/Throwable;)Ljava/lang/Throwable;
    //   944: athrow
    //   945: aload_3
    //   946: getstatic burp/Ze82.Zx : Ljava/lang/String;
    //   949: getstatic burp/Zzox.Zq : Ljava/lang/Object;
    //   952: checkcast java/math/BigInteger
    //   955: invokevirtual intValue : ()I
    //   958: bipush #32
    //   960: irem
    //   961: invokestatic abs : (I)I
    //   964: invokevirtual charAt : (I)C
    //   967: invokevirtual append : (C)Ljava/lang/StringBuilder;
    //   970: pop
    //   971: iload_2
    //   972: ifeq -> 1348
    //   975: goto -> 982
    //   978: invokestatic a : (Ljava/lang/Throwable;)Ljava/lang/Throwable;
    //   981: athrow
    //   982: aload_3
    //   983: getstatic burp/Zm6h.Za : Ljava/lang/String;
    //   986: getstatic burp/Zix.ZO : Ljava/lang/Object;
    //   989: checkcast java/math/BigInteger
    //   992: invokevirtual intValue : ()I
    //   995: bipush #32
    //   997: irem
    //   998: invokestatic abs : (I)I
    //   1001: invokevirtual charAt : (I)C
    //   1004: invokevirtual append : (C)Ljava/lang/StringBuilder;
    //   1007: pop
    //   1008: iload_2
    //   1009: ifeq -> 1348
    //   1012: goto -> 1019
    //   1015: invokestatic a : (Ljava/lang/Throwable;)Ljava/lang/Throwable;
    //   1018: athrow
    //   1019: aload_3
    //   1020: getstatic burp/Zt9_.Zf : Ljava/lang/String;
    //   1023: getstatic burp/Zlr.ZK : Ljava/lang/Object;
    //   1026: checkcast java/math/BigInteger
    //   1029: invokevirtual intValue : ()I
    //   1032: bipush #32
    //   1034: irem
    //   1035: invokestatic abs : (I)I
    //   1038: invokevirtual charAt : (I)C
    //   1041: invokevirtual append : (C)Ljava/lang/StringBuilder;
    //   1044: pop
    //   1045: iload_2
    //   1046: ifeq -> 1348
    //   1049: goto -> 1056
    //   1052: invokestatic a : (Ljava/lang/Throwable;)Ljava/lang/Throwable;
    //   1055: athrow
    //   1056: aload_3
    //   1057: getstatic burp/Zmsn.ZD : Ljava/lang/String;
    //   1060: getstatic burp/Zera.Zy : Ljava/lang/Object;
    //   1063: checkcast java/math/BigInteger
    //   1066: invokevirtual intValue : ()I
    //   1069: bipush #32
    //   1071: irem
    //   1072: invokestatic abs : (I)I
    //   1075: invokevirtual charAt : (I)C
    //   1078: invokevirtual append : (C)Ljava/lang/StringBuilder;
    //   1081: pop
    //   1082: iload_2
    //   1083: ifeq -> 1348
    //   1086: goto -> 1093
    //   1089: invokestatic a : (Ljava/lang/Throwable;)Ljava/lang/Throwable;
    //   1092: athrow
    //   1093: aload_3
    //   1094: getstatic burp/Zs_v.Zn : Ljava/lang/String;
    //   1097: getstatic burp/Zx6d.ZU : Ljava/lang/Object;
    //   1100: checkcast java/math/BigInteger
    //   1103: invokevirtual intValue : ()I
    //   1106: bipush #32
    //   1108: irem
    //   1109: invokestatic abs : (I)I
    //   1112: invokevirtual charAt : (I)C
    //   1115: invokevirtual append : (C)Ljava/lang/StringBuilder;
    //   1118: pop
    //   1119: iload_2
    //   1120: ifeq -> 1348
    //   1123: goto -> 1130
    //   1126: invokestatic a : (Ljava/lang/Throwable;)Ljava/lang/Throwable;
    //   1129: athrow
    //   1130: aload_3
    //   1131: getstatic burp/Zsxo.ZW : Ljava/lang/String;
    //   1134: getstatic burp/Zxjv.ZY : Ljava/lang/Object;
    //   1137: checkcast java/math/BigInteger
    //   1140: invokevirtual intValue : ()I
    //   1143: bipush #32
    //   1145: irem
    //   1146: invokestatic abs : (I)I
    //   1149: invokevirtual charAt : (I)C
    //   1152: invokevirtual append : (C)Ljava/lang/StringBuilder;
    //   1155: pop
    //   1156: iload_2
    //   1157: ifeq -> 1348
    //   1160: goto -> 1167
    //   1163: invokestatic a : (Ljava/lang/Throwable;)Ljava/lang/Throwable;
    //   1166: athrow
    //   1167: aload_3
    //   1168: getstatic burp/Zs4z.Zs : Ljava/lang/String;
    //   1171: getstatic burp/Zeuc.Zd : Ljava/lang/Object;
    //   1174: checkcast java/math/BigInteger
    //   1177: invokevirtual intValue : ()I
    //   1180: bipush #32
    //   1182: irem
    //   1183: invokestatic abs : (I)I
    //   1186: invokevirtual charAt : (I)C
    //   1189: invokevirtual append : (C)Ljava/lang/StringBuilder;
    //   1192: pop
    //   1193: iload_2
    //   1194: ifeq -> 1348
    //   1197: goto -> 1204
    //   1200: invokestatic a : (Ljava/lang/Throwable;)Ljava/lang/Throwable;
    //   1203: athrow
    //   1204: aload_3
    //   1205: getstatic burp/Zvo3.Z_ : Ljava/lang/String;
    //   1208: getstatic burp/Zz2e.Zm : Ljava/lang/Object;
    //   1211: checkcast java/math/BigInteger
    //   1214: invokevirtual intValue : ()I
    //   1217: bipush #32
    //   1219: irem
    //   1220: invokestatic abs : (I)I
    //   1223: invokevirtual charAt : (I)C
    //   1226: invokevirtual append : (C)Ljava/lang/StringBuilder;
    //   1229: pop
    //   1230: iload_2
    //   1231: ifeq -> 1348
    //   1234: goto -> 1241
    //   1237: invokestatic a : (Ljava/lang/Throwable;)Ljava/lang/Throwable;
    //   1240: athrow
    //   1241: aload_3
    //   1242: getstatic burp/Zg4k.ZB : Ljava/lang/String;
    //   1245: getstatic burp/Zeqg.Zm : Ljava/lang/Object;
    //   1248: checkcast java/math/BigInteger
    //   1251: invokevirtual intValue : ()I
    //   1254: bipush #32
    //   1256: irem
    //   1257: invokestatic abs : (I)I
    //   1260: invokevirtual charAt : (I)C
    //   1263: invokevirtual append : (C)Ljava/lang/StringBuilder;
    //   1266: pop
    //   1267: iload_2
    //   1268: ifeq -> 1348
    //   1271: goto -> 1278
    //   1274: invokestatic a : (Ljava/lang/Throwable;)Ljava/lang/Throwable;
    //   1277: athrow
    //   1278: aload_3
    //   1279: getstatic burp/Zlck.ZL : Ljava/lang/String;
    //   1282: getstatic burp/Zkll.Zl : Ljava/lang/Object;
    //   1285: checkcast java/math/BigInteger
    //   1288: invokevirtual intValue : ()I
    //   1291: bipush #32
    //   1293: irem
    //   1294: invokestatic abs : (I)I
    //   1297: invokevirtual charAt : (I)C
    //   1300: invokevirtual append : (C)Ljava/lang/StringBuilder;
    //   1303: pop
    //   1304: iload_2
    //   1305: ifeq -> 1348
    //   1308: goto -> 1315
    //   1311: invokestatic a : (Ljava/lang/Throwable;)Ljava/lang/Throwable;
    //   1314: athrow
    //   1315: aload_3
    //   1316: getstatic burp/Ztfh.ZU : Ljava/lang/String;
    //   1319: getstatic burp/Zstb.ZC : Ljava/lang/Object;
    //   1322: checkcast java/math/BigInteger
    //   1325: invokevirtual intValue : ()I
    //   1328: bipush #32
    //   1330: irem
    //   1331: invokestatic abs : (I)I
    //   1334: invokevirtual charAt : (I)C
    //   1337: invokevirtual append : (C)Ljava/lang/StringBuilder;
    //   1340: pop
    //   1341: goto -> 1348
    //   1344: invokestatic a : (Ljava/lang/Throwable;)Ljava/lang/Throwable;
    //   1347: athrow
    //   1348: iinc #4, 1
    //   1351: iload_2
    //   1352: ifeq -> 15
    //   1355: aload_3
    //   1356: invokevirtual toString : ()Ljava/lang/String;
    //   1359: putstatic burp/Zrof.ZE : Ljava/lang/String;
    //   1362: sipush #-14353
    //   1365: getstatic burp/Zt9_.ZN : Ljava/lang/Object;
    //   1368: checkcast java/math/BigInteger
    //   1371: getstatic burp/Zevr.ZG : Ljava/lang/Object;
    //   1374: checkcast java/math/BigInteger
    //   1377: invokevirtual subtract : (Ljava/math/BigInteger;)Ljava/math/BigInteger;
    //   1380: putstatic burp/Ztye.ZK : Ljava/lang/Object;
    //   1383: sipush #-13707
    //   1386: getstatic burp/Zex.ZO : Ljava/lang/Object;
    //   1389: checkcast java/math/BigInteger
    //   1392: getstatic burp/Zmx6.ZJ : Ljava/lang/Object;
    //   1395: checkcast java/math/BigInteger
    //   1398: invokevirtual subtract : (Ljava/math/BigInteger;)Ljava/math/BigInteger;
    //   1401: putstatic burp/Zt98.Zz : Ljava/lang/Object;
    //   1404: invokestatic a : (II)Ljava/lang/String;
    //   1407: iconst_1
    //   1408: ldc burp/Zkup
    //   1410: invokevirtual getClassLoader : ()Ljava/lang/ClassLoader;
    //   1413: invokestatic forName : (Ljava/lang/String;ZLjava/lang/ClassLoader;)Ljava/lang/Class;
    //   1416: invokevirtual getDeclaredFields : ()[Ljava/lang/reflect/Field;
    //   1419: astore #4
    //   1421: aload #4
    //   1423: arraylength
    //   1424: istore #5
    //   1426: iconst_0
    //   1427: istore #6
    //   1429: iload #6
    //   1431: iload #5
    //   1433: if_icmpge -> 1571
    //   1436: aload #4
    //   1438: iload #6
    //   1440: aaload
    //   1441: astore #7
    //   1443: aload #7
    //   1445: invokevirtual getModifiers : ()I
    //   1448: invokestatic isStatic : (I)Z
    //   1451: ifne -> 1461
    //   1454: goto -> 1564
    //   1457: invokestatic a : (Ljava/lang/Throwable;)Ljava/lang/Throwable;
    //   1460: athrow
    //   1461: aload #7
    //   1463: invokevirtual getType : ()Ljava/lang/Class;
    //   1466: astore #8
    //   1468: aload #8
    //   1470: ifnull -> 1551
    //   1473: aload #8
    //   1475: invokevirtual isPrimitive : ()Z
    //   1478: ifne -> 1551
    //   1481: goto -> 1488
    //   1484: invokestatic a : (Ljava/lang/Throwable;)Ljava/lang/Throwable;
    //   1487: athrow
    //   1488: aload #8
    //   1490: invokevirtual getPackage : ()Ljava/lang/Package;
    //   1493: ifnull -> 1551
    //   1496: goto -> 1503
    //   1499: invokestatic a : (Ljava/lang/Throwable;)Ljava/lang/Throwable;
    //   1502: athrow
    //   1503: aload #8
    //   1505: invokevirtual getPackage : ()Ljava/lang/Package;
    //   1508: invokevirtual getName : ()Ljava/lang/String;
    //   1511: ifnull -> 1551
    //   1514: goto -> 1521
    //   1517: invokestatic a : (Ljava/lang/Throwable;)Ljava/lang/Throwable;
    //   1520: athrow
    //   1521: aload #8
    //   1523: invokevirtual getPackage : ()Ljava/lang/Package;
    //   1526: invokevirtual getName : ()Ljava/lang/String;
    //   1529: sipush #-14366
    //   1532: sipush #28514
    //   1535: invokestatic a : (II)Ljava/lang/String;
    //   1538: invokevirtual startsWith : (Ljava/lang/String;)Z
    //   1541: ifne -> 1551
    //   1544: goto -> 1551
    //   1547: invokestatic a : (Ljava/lang/Throwable;)Ljava/lang/Throwable;
    //   1550: athrow
    //   1551: aload #7
    //   1553: iconst_1
    //   1554: invokevirtual setAccessible : (Z)V
    //   1557: aload #7
    //   1559: aconst_null
    //   1560: invokevirtual get : (Ljava/lang/Object;)Ljava/lang/Object;
    //   1563: pop
    //   1564: iinc #6, 1
    //   1567: iload_2
    //   1568: ifeq -> 1429
    //   1571: sipush #-14341
    //   1574: sipush #-3235
    //   1577: invokestatic a : (II)Ljava/lang/String;
    //   1580: invokestatic forName : (Ljava/lang/String;)Ljava/lang/Class;
    //   1583: invokevirtual getDeclaredMethods : ()[Ljava/lang/reflect/Method;
    //   1586: astore #4
    //   1588: aload #4
    //   1590: arraylength
    //   1591: istore #5
    //   1593: iconst_0
    //   1594: istore #6
    //   1596: iload #6
    //   1598: iload #5
    //   1600: if_icmpge -> 1733
    //   1603: aload #4
    //   1605: iload #6
    //   1607: aaload
    //   1608: astore #7
    //   1610: aload #7
    //   1612: invokevirtual getParameterTypes : ()[Ljava/lang/Class;
    //   1615: pop
    //   1616: aload #7
    //   1618: invokevirtual getModifiers : ()I
    //   1621: invokestatic isStatic : (I)Z
    //   1624: ifeq -> 1719
    //   1627: aload #7
    //   1629: invokevirtual getParameterTypes : ()[Ljava/lang/Class;
    //   1632: arraylength
    //   1633: iconst_2
    //   1634: if_icmpne -> 1719
    //   1637: goto -> 1644
    //   1640: invokestatic a : (Ljava/lang/Throwable;)Ljava/lang/Throwable;
    //   1643: athrow
    //   1644: aload #7
    //   1646: invokevirtual getReturnType : ()Ljava/lang/Class;
    //   1649: getstatic java/lang/Void.TYPE : Ljava/lang/Class;
    //   1652: invokevirtual equals : (Ljava/lang/Object;)Z
    //   1655: ifeq -> 1719
    //   1658: goto -> 1665
    //   1661: invokestatic a : (Ljava/lang/Throwable;)Ljava/lang/Throwable;
    //   1664: athrow
    //   1665: aload #7
    //   1667: iconst_1
    //   1668: invokevirtual setAccessible : (Z)V
    //   1671: aload #7
    //   1673: aconst_null
    //   1674: iconst_2
    //   1675: anewarray java/lang/Object
    //   1678: dup
    //   1679: iconst_0
    //   1680: aload_0
    //   1681: aastore
    //   1682: dup
    //   1683: iconst_1
    //   1684: aload_1
    //   1685: ifnonnull -> 1703
    //   1688: goto -> 1695
    //   1691: invokestatic a : (Ljava/lang/Throwable;)Ljava/lang/Throwable;
    //   1694: athrow
    //   1695: aload_1
    //   1696: goto -> 1710
    //   1699: invokestatic a : (Ljava/lang/Throwable;)Ljava/lang/Throwable;
    //   1702: athrow
    //   1703: aload_1
    //   1704: checkcast [B
    //   1707: invokevirtual clone : ()Ljava/lang/Object;
    //   1710: aastore
    //   1711: invokevirtual invoke : (Ljava/lang/Object;[Ljava/lang/Object;)Ljava/lang/Object;
    //   1714: pop
    //   1715: iload_2
    //   1716: ifeq -> 1733
    //   1719: iinc #6, 1
    //   1722: iload_2
    //   1723: ifeq -> 1596
    //   1726: goto -> 1733
    //   1729: invokestatic a : (Ljava/lang/Throwable;)Ljava/lang/Throwable;
    //   1732: athrow
    //   1733: iconst_0
    //   1734: istore #4
    //   1736: getstatic burp/Zs00.Zv : Ljava/lang/String;
    //   1739: getstatic burp/Zkm0.ZI : Ljava/lang/Object;
    //   1742: checkcast java/math/BigInteger
    //   1745: invokevirtual intValue : ()I
    //   1748: bipush #32
    //   1750: irem
    //   1751: invokestatic abs : (I)I
    //   1754: invokevirtual charAt : (I)C
    //   1757: getstatic burp/Zlo5.ZJ : Ljava/lang/String;
    //   1760: getstatic burp/Zv8c.Zx : Ljava/lang/Object;
    //   1763: checkcast java/math/BigInteger
    //   1766: invokevirtual intValue : ()I
    //   1769: bipush #32
    //   1771: irem
    //   1772: invokestatic abs : (I)I
    //   1775: invokevirtual charAt : (I)C
    //   1778: if_icmpgt -> 2123
    //   1781: sipush #-14347
    //   1784: sipush #3768
    //   1787: invokestatic a : (II)Ljava/lang/String;
    //   1790: iconst_1
    //   1791: ldc burp/Zefn
    //   1793: invokevirtual getClassLoader : ()Ljava/lang/ClassLoader;
    //   1796: invokestatic forName : (Ljava/lang/String;ZLjava/lang/ClassLoader;)Ljava/lang/Class;
    //   1799: invokevirtual getDeclaredFields : ()[Ljava/lang/reflect/Field;
    //   1802: astore #5
    //   1804: aload #5
    //   1806: arraylength
    //   1807: istore #6
    //   1809: iconst_0
    //   1810: istore #7
    //   1812: iload #7
    //   1814: iload #6
    //   1816: if_icmpge -> 1954
    //   1819: aload #5
    //   1821: iload #7
    //   1823: aaload
    //   1824: astore #8
    //   1826: aload #8
    //   1828: invokevirtual getModifiers : ()I
    //   1831: invokestatic isStatic : (I)Z
    //   1834: ifne -> 1844
    //   1837: goto -> 1947
    //   1840: invokestatic a : (Ljava/lang/Throwable;)Ljava/lang/Throwable;
    //   1843: athrow
    //   1844: aload #8
    //   1846: invokevirtual getType : ()Ljava/lang/Class;
    //   1849: astore #9
    //   1851: aload #9
    //   1853: ifnull -> 1934
    //   1856: aload #9
    //   1858: invokevirtual isPrimitive : ()Z
    //   1861: ifne -> 1934
    //   1864: goto -> 1871
    //   1867: invokestatic a : (Ljava/lang/Throwable;)Ljava/lang/Throwable;
    //   1870: athrow
    //   1871: aload #9
    //   1873: invokevirtual getPackage : ()Ljava/lang/Package;
    //   1876: ifnull -> 1934
    //   1879: goto -> 1886
    //   1882: invokestatic a : (Ljava/lang/Throwable;)Ljava/lang/Throwable;
    //   1885: athrow
    //   1886: aload #9
    //   1888: invokevirtual getPackage : ()Ljava/lang/Package;
    //   1891: invokevirtual getName : ()Ljava/lang/String;
    //   1894: ifnull -> 1934
    //   1897: goto -> 1904
    //   1900: invokestatic a : (Ljava/lang/Throwable;)Ljava/lang/Throwable;
    //   1903: athrow
    //   1904: aload #9
    //   1906: invokevirtual getPackage : ()Ljava/lang/Package;
    //   1909: invokevirtual getName : ()Ljava/lang/String;
    //   1912: sipush #-14357
    //   1915: sipush #-23898
    //   1918: invokestatic a : (II)Ljava/lang/String;
    //   1921: invokevirtual startsWith : (Ljava/lang/String;)Z
    //   1924: ifne -> 1934
    //   1927: goto -> 1934
    //   1930: invokestatic a : (Ljava/lang/Throwable;)Ljava/lang/Throwable;
    //   1933: athrow
    //   1934: aload #8
    //   1936: iconst_1
    //   1937: invokevirtual setAccessible : (Z)V
    //   1940: aload #8
    //   1942: aconst_null
    //   1943: invokevirtual get : (Ljava/lang/Object;)Ljava/lang/Object;
    //   1946: pop
    //   1947: iinc #7, 1
    //   1950: iload_2
    //   1951: ifeq -> 1812
    //   1954: sipush #-14339
    //   1957: sipush #3767
    //   1960: invokestatic a : (II)Ljava/lang/String;
    //   1963: invokestatic forName : (Ljava/lang/String;)Ljava/lang/Class;
    //   1966: invokevirtual getDeclaredMethods : ()[Ljava/lang/reflect/Method;
    //   1969: astore #5
    //   1971: aload #5
    //   1973: arraylength
    //   1974: istore #6
    //   1976: iconst_0
    //   1977: istore #7
    //   1979: iload #7
    //   1981: iload #6
    //   1983: if_icmpge -> 2120
    //   1986: aload #5
    //   1988: iload #7
    //   1990: aaload
    //   1991: astore #8
    //   1993: aload #8
    //   1995: invokevirtual getParameterTypes : ()[Ljava/lang/Class;
    //   1998: pop
    //   1999: aload #8
    //   2001: invokevirtual getModifiers : ()I
    //   2004: invokestatic isStatic : (I)Z
    //   2007: ifeq -> 2106
    //   2010: aload #8
    //   2012: invokevirtual getParameterTypes : ()[Ljava/lang/Class;
    //   2015: arraylength
    //   2016: iconst_2
    //   2017: if_icmpne -> 2106
    //   2020: goto -> 2027
    //   2023: invokestatic a : (Ljava/lang/Throwable;)Ljava/lang/Throwable;
    //   2026: athrow
    //   2027: aload #8
    //   2029: invokevirtual getReturnType : ()Ljava/lang/Class;
    //   2032: getstatic java/lang/Boolean.TYPE : Ljava/lang/Class;
    //   2035: if_acmpne -> 2106
    //   2038: goto -> 2045
    //   2041: invokestatic a : (Ljava/lang/Throwable;)Ljava/lang/Throwable;
    //   2044: athrow
    //   2045: aload #8
    //   2047: iconst_1
    //   2048: invokevirtual setAccessible : (Z)V
    //   2051: aload #8
    //   2053: aconst_null
    //   2054: iconst_2
    //   2055: anewarray java/lang/Object
    //   2058: dup
    //   2059: iconst_0
    //   2060: aload_0
    //   2061: aastore
    //   2062: dup
    //   2063: iconst_1
    //   2064: aload_1
    //   2065: ifnonnull -> 2083
    //   2068: goto -> 2075
    //   2071: invokestatic a : (Ljava/lang/Throwable;)Ljava/lang/Throwable;
    //   2074: athrow
    //   2075: aload_1
    //   2076: goto -> 2090
    //   2079: invokestatic a : (Ljava/lang/Throwable;)Ljava/lang/Throwable;
    //   2082: athrow
    //   2083: aload_1
    //   2084: checkcast [B
    //   2087: invokevirtual clone : ()Ljava/lang/Object;
    //   2090: aastore
    //   2091: invokevirtual invoke : (Ljava/lang/Object;[Ljava/lang/Object;)Ljava/lang/Object;
    //   2094: checkcast java/lang/Boolean
    //   2097: invokevirtual booleanValue : ()Z
    //   2100: istore #4
    //   2102: iload_2
    //   2103: ifeq -> 2120
    //   2106: iinc #7, 1
    //   2109: iload_2
    //   2110: ifeq -> 1979
    //   2113: goto -> 2120
    //   2116: invokestatic a : (Ljava/lang/Throwable;)Ljava/lang/Throwable;
    //   2119: athrow
    //   2120: goto -> 2462
    //   2123: sipush #-14361
    //   2126: sipush #-22626
    //   2129: invokestatic a : (II)Ljava/lang/String;
    //   2132: iconst_1
    //   2133: ldc burp/Zlh2
    //   2135: invokevirtual getClassLoader : ()Ljava/lang/ClassLoader;
    //   2138: invokestatic forName : (Ljava/lang/String;ZLjava/lang/ClassLoader;)Ljava/lang/Class;
    //   2141: invokevirtual getDeclaredFields : ()[Ljava/lang/reflect/Field;
    //   2144: astore #5
    //   2146: aload #5
    //   2148: arraylength
    //   2149: istore #6
    //   2151: iconst_0
    //   2152: istore #7
    //   2154: iload #7
    //   2156: iload #6
    //   2158: if_icmpge -> 2296
    //   2161: aload #5
    //   2163: iload #7
    //   2165: aaload
    //   2166: astore #8
    //   2168: aload #8
    //   2170: invokevirtual getModifiers : ()I
    //   2173: invokestatic isStatic : (I)Z
    //   2176: ifne -> 2186
    //   2179: goto -> 2289
    //   2182: invokestatic a : (Ljava/lang/Throwable;)Ljava/lang/Throwable;
    //   2185: athrow
    //   2186: aload #8
    //   2188: invokevirtual getType : ()Ljava/lang/Class;
    //   2191: astore #9
    //   2193: aload #9
    //   2195: ifnull -> 2276
    //   2198: aload #9
    //   2200: invokevirtual isPrimitive : ()Z
    //   2203: ifne -> 2276
    //   2206: goto -> 2213
    //   2209: invokestatic a : (Ljava/lang/Throwable;)Ljava/lang/Throwable;
    //   2212: athrow
    //   2213: aload #9
    //   2215: invokevirtual getPackage : ()Ljava/lang/Package;
    //   2218: ifnull -> 2276
    //   2221: goto -> 2228
    //   2224: invokestatic a : (Ljava/lang/Throwable;)Ljava/lang/Throwable;
    //   2227: athrow
    //   2228: aload #9
    //   2230: invokevirtual getPackage : ()Ljava/lang/Package;
    //   2233: invokevirtual getName : ()Ljava/lang/String;
    //   2236: ifnull -> 2276
    //   2239: goto -> 2246
    //   2242: invokestatic a : (Ljava/lang/Throwable;)Ljava/lang/Throwable;
    //   2245: athrow
    //   2246: aload #9
    //   2248: invokevirtual getPackage : ()Ljava/lang/Package;
    //   2251: invokevirtual getName : ()Ljava/lang/String;
    //   2254: sipush #-14357
    //   2257: sipush #-23898
    //   2260: invokestatic a : (II)Ljava/lang/String;
    //   2263: invokevirtual startsWith : (Ljava/lang/String;)Z
    //   2266: ifne -> 2276
    //   2269: goto -> 2276
    //   2272: invokestatic a : (Ljava/lang/Throwable;)Ljava/lang/Throwable;
    //   2275: athrow
    //   2276: aload #8
    //   2278: iconst_1
    //   2279: invokevirtual setAccessible : (Z)V
    //   2282: aload #8
    //   2284: aconst_null
    //   2285: invokevirtual get : (Ljava/lang/Object;)Ljava/lang/Object;
    //   2288: pop
    //   2289: iinc #7, 1
    //   2292: iload_2
    //   2293: ifeq -> 2154
    //   2296: sipush #-14356
    //   2299: sipush #32132
    //   2302: invokestatic a : (II)Ljava/lang/String;
    //   2305: invokestatic forName : (Ljava/lang/String;)Ljava/lang/Class;
    //   2308: invokevirtual getDeclaredMethods : ()[Ljava/lang/reflect/Method;
    //   2311: astore #5
    //   2313: aload #5
    //   2315: arraylength
    //   2316: istore #6
    //   2318: iconst_0
    //   2319: istore #7
    //   2321: iload #7
    //   2323: iload #6
    //   2325: if_icmpge -> 2462
    //   2328: aload #5
    //   2330: iload #7
    //   2332: aaload
    //   2333: astore #8
    //   2335: aload #8
    //   2337: invokevirtual getParameterTypes : ()[Ljava/lang/Class;
    //   2340: pop
    //   2341: aload #8
    //   2343: invokevirtual getModifiers : ()I
    //   2346: invokestatic isStatic : (I)Z
    //   2349: ifeq -> 2448
    //   2352: aload #8
    //   2354: invokevirtual getParameterTypes : ()[Ljava/lang/Class;
    //   2357: arraylength
    //   2358: iconst_2
    //   2359: if_icmpne -> 2448
    //   2362: goto -> 2369
    //   2365: invokestatic a : (Ljava/lang/Throwable;)Ljava/lang/Throwable;
    //   2368: athrow
    //   2369: aload #8
    //   2371: invokevirtual getReturnType : ()Ljava/lang/Class;
    //   2374: getstatic java/lang/Boolean.TYPE : Ljava/lang/Class;
    //   2377: if_acmpne -> 2448
    //   2380: goto -> 2387
    //   2383: invokestatic a : (Ljava/lang/Throwable;)Ljava/lang/Throwable;
    //   2386: athrow
    //   2387: aload #8
    //   2389: iconst_1
    //   2390: invokevirtual setAccessible : (Z)V
    //   2393: aload #8
    //   2395: aconst_null
    //   2396: iconst_2
    //   2397: anewarray java/lang/Object
    //   2400: dup
    //   2401: iconst_0
    //   2402: aload_0
    //   2403: aastore
    //   2404: dup
    //   2405: iconst_1
    //   2406: aload_1
    //   2407: ifnonnull -> 2425
    //   2410: goto -> 2417
    //   2413: invokestatic a : (Ljava/lang/Throwable;)Ljava/lang/Throwable;
    //   2416: athrow
    //   2417: aload_1
    //   2418: goto -> 2432
    //   2421: invokestatic a : (Ljava/lang/Throwable;)Ljava/lang/Throwable;
    //   2424: athrow
    //   2425: aload_1
    //   2426: checkcast [B
    //   2429: invokevirtual clone : ()Ljava/lang/Object;
    //   2432: aastore
    //   2433: invokevirtual invoke : (Ljava/lang/Object;[Ljava/lang/Object;)Ljava/lang/Object;
    //   2436: checkcast java/lang/Boolean
    //   2439: invokevirtual booleanValue : ()Z
    //   2442: istore #4
    //   2444: iload_2
    //   2445: ifeq -> 2462
    //   2448: iinc #7, 1
    //   2451: iload_2
    //   2452: ifeq -> 2321
    //   2455: goto -> 2462
    //   2458: invokestatic a : (Ljava/lang/Throwable;)Ljava/lang/Throwable;
    //   2461: athrow
    //   2462: iload #4
    //   2464: ifeq -> 2470
    //   2467: iload #4
    //   2469: ireturn
    //   2470: getstatic burp/Zkjr.Zg : Ljava/lang/String;
    //   2473: getstatic burp/Ze54.Zx : Ljava/lang/Object;
    //   2476: checkcast java/math/BigInteger
    //   2479: invokevirtual intValue : ()I
    //   2482: bipush #32
    //   2484: irem
    //   2485: invokestatic abs : (I)I
    //   2488: invokevirtual charAt : (I)C
    //   2491: getstatic burp/Zk7f.ZA : Ljava/lang/String;
    //   2494: getstatic burp/Zke7.Zj : Ljava/lang/Object;
    //   2497: checkcast java/math/BigInteger
    //   2500: invokevirtual intValue : ()I
    //   2503: bipush #32
    //   2505: irem
    //   2506: invokestatic abs : (I)I
    //   2509: invokevirtual charAt : (I)C
    //   2512: if_icmpgt -> 2858
    //   2515: sipush #-14343
    //   2518: sipush #26540
    //   2521: invokestatic a : (II)Ljava/lang/String;
    //   2524: iconst_1
    //   2525: ldc burp/Ztvp
    //   2527: invokevirtual getClassLoader : ()Ljava/lang/ClassLoader;
    //   2530: invokestatic forName : (Ljava/lang/String;ZLjava/lang/ClassLoader;)Ljava/lang/Class;
    //   2533: invokevirtual getDeclaredFields : ()[Ljava/lang/reflect/Field;
    //   2536: astore #5
    //   2538: aload #5
    //   2540: arraylength
    //   2541: istore #6
    //   2543: iconst_0
    //   2544: istore #7
    //   2546: iload #7
    //   2548: iload #6
    //   2550: if_icmpge -> 2688
    //   2553: aload #5
    //   2555: iload #7
    //   2557: aaload
    //   2558: astore #8
    //   2560: aload #8
    //   2562: invokevirtual getModifiers : ()I
    //   2565: invokestatic isStatic : (I)Z
    //   2568: ifne -> 2578
    //   2571: goto -> 2681
    //   2574: invokestatic a : (Ljava/lang/Throwable;)Ljava/lang/Throwable;
    //   2577: athrow
    //   2578: aload #8
    //   2580: invokevirtual getType : ()Ljava/lang/Class;
    //   2583: astore #9
    //   2585: aload #9
    //   2587: ifnull -> 2668
    //   2590: aload #9
    //   2592: invokevirtual isPrimitive : ()Z
    //   2595: ifne -> 2668
    //   2598: goto -> 2605
    //   2601: invokestatic a : (Ljava/lang/Throwable;)Ljava/lang/Throwable;
    //   2604: athrow
    //   2605: aload #9
    //   2607: invokevirtual getPackage : ()Ljava/lang/Package;
    //   2610: ifnull -> 2668
    //   2613: goto -> 2620
    //   2616: invokestatic a : (Ljava/lang/Throwable;)Ljava/lang/Throwable;
    //   2619: athrow
    //   2620: aload #9
    //   2622: invokevirtual getPackage : ()Ljava/lang/Package;
    //   2625: invokevirtual getName : ()Ljava/lang/String;
    //   2628: ifnull -> 2668
    //   2631: goto -> 2638
    //   2634: invokestatic a : (Ljava/lang/Throwable;)Ljava/lang/Throwable;
    //   2637: athrow
    //   2638: aload #9
    //   2640: invokevirtual getPackage : ()Ljava/lang/Package;
    //   2643: invokevirtual getName : ()Ljava/lang/String;
    //   2646: sipush #-14357
    //   2649: sipush #-23898
    //   2652: invokestatic a : (II)Ljava/lang/String;
    //   2655: invokevirtual startsWith : (Ljava/lang/String;)Z
    //   2658: ifne -> 2668
    //   2661: goto -> 2668
    //   2664: invokestatic a : (Ljava/lang/Throwable;)Ljava/lang/Throwable;
    //   2667: athrow
    //   2668: aload #8
    //   2670: iconst_1
    //   2671: invokevirtual setAccessible : (Z)V
    //   2674: aload #8
    //   2676: aconst_null
    //   2677: invokevirtual get : (Ljava/lang/Object;)Ljava/lang/Object;
    //   2680: pop
    //   2681: iinc #7, 1
    //   2684: iload_2
    //   2685: ifeq -> 2546
    //   2688: sipush #-14349
    //   2691: sipush #-22692
    //   2694: invokestatic a : (II)Ljava/lang/String;
    //   2697: invokestatic forName : (Ljava/lang/String;)Ljava/lang/Class;
    //   2700: invokevirtual getDeclaredMethods : ()[Ljava/lang/reflect/Method;
    //   2703: astore #5
    //   2705: aload #5
    //   2707: arraylength
    //   2708: istore #6
    //   2710: iconst_0
    //   2711: istore #7
    //   2713: iload #7
    //   2715: iload #6
    //   2717: if_icmpge -> 2854
    //   2720: aload #5
    //   2722: iload #7
    //   2724: aaload
    //   2725: astore #8
    //   2727: aload #8
    //   2729: invokevirtual getParameterTypes : ()[Ljava/lang/Class;
    //   2732: pop
    //   2733: aload #8
    //   2735: invokevirtual getModifiers : ()I
    //   2738: invokestatic isStatic : (I)Z
    //   2741: ifeq -> 2840
    //   2744: aload #8
    //   2746: invokevirtual getParameterTypes : ()[Ljava/lang/Class;
    //   2749: arraylength
    //   2750: iconst_2
    //   2751: if_icmpne -> 2840
    //   2754: goto -> 2761
    //   2757: invokestatic a : (Ljava/lang/Throwable;)Ljava/lang/Throwable;
    //   2760: athrow
    //   2761: aload #8
    //   2763: invokevirtual getReturnType : ()Ljava/lang/Class;
    //   2766: getstatic java/lang/Boolean.TYPE : Ljava/lang/Class;
    //   2769: if_acmpne -> 2840
    //   2772: goto -> 2779
    //   2775: invokestatic a : (Ljava/lang/Throwable;)Ljava/lang/Throwable;
    //   2778: athrow
    //   2779: aload #8
    //   2781: iconst_1
    //   2782: invokevirtual setAccessible : (Z)V
    //   2785: aload #8
    //   2787: aconst_null
    //   2788: iconst_2
    //   2789: anewarray java/lang/Object
    //   2792: dup
    //   2793: iconst_0
    //   2794: aload_0
    //   2795: aastore
    //   2796: dup
    //   2797: iconst_1
    //   2798: aload_1
    //   2799: ifnonnull -> 2817
    //   2802: goto -> 2809
    //   2805: invokestatic a : (Ljava/lang/Throwable;)Ljava/lang/Throwable;
    //   2808: athrow
    //   2809: aload_1
    //   2810: goto -> 2824
    //   2813: invokestatic a : (Ljava/lang/Throwable;)Ljava/lang/Throwable;
    //   2816: athrow
    //   2817: aload_1
    //   2818: checkcast [B
    //   2821: invokevirtual clone : ()Ljava/lang/Object;
    //   2824: aastore
    //   2825: invokevirtual invoke : (Ljava/lang/Object;[Ljava/lang/Object;)Ljava/lang/Object;
    //   2828: checkcast java/lang/Boolean
    //   2831: invokevirtual booleanValue : ()Z
    //   2834: istore #4
    //   2836: iload_2
    //   2837: ifeq -> 2854
    //   2840: iinc #7, 1
    //   2843: iload_2
    //   2844: ifeq -> 2713
    //   2847: goto -> 2854
    //   2850: invokestatic a : (Ljava/lang/Throwable;)Ljava/lang/Throwable;
    //   2853: athrow
    //   2854: iload_2
    //   2855: ifeq -> 3197
    //   2858: sipush #-14362
    //   2861: sipush #31799
    //   2864: invokestatic a : (II)Ljava/lang/String;
    //   2867: iconst_1
    //   2868: ldc burp/Zljx
    //   2870: invokevirtual getClassLoader : ()Ljava/lang/ClassLoader;
    //   2873: invokestatic forName : (Ljava/lang/String;ZLjava/lang/ClassLoader;)Ljava/lang/Class;
    //   2876: invokevirtual getDeclaredFields : ()[Ljava/lang/reflect/Field;
    //   2879: astore #5
    //   2881: aload #5
    //   2883: arraylength
    //   2884: istore #6
    //   2886: iconst_0
    //   2887: istore #7
    //   2889: iload #7
    //   2891: iload #6
    //   2893: if_icmpge -> 3031
    //   2896: aload #5
    //   2898: iload #7
    //   2900: aaload
    //   2901: astore #8
    //   2903: aload #8
    //   2905: invokevirtual getModifiers : ()I
    //   2908: invokestatic isStatic : (I)Z
    //   2911: ifne -> 2921
    //   2914: goto -> 3024
    //   2917: invokestatic a : (Ljava/lang/Throwable;)Ljava/lang/Throwable;
    //   2920: athrow
    //   2921: aload #8
    //   2923: invokevirtual getType : ()Ljava/lang/Class;
    //   2926: astore #9
    //   2928: aload #9
    //   2930: ifnull -> 3011
    //   2933: aload #9
    //   2935: invokevirtual isPrimitive : ()Z
    //   2938: ifne -> 3011
    //   2941: goto -> 2948
    //   2944: invokestatic a : (Ljava/lang/Throwable;)Ljava/lang/Throwable;
    //   2947: athrow
    //   2948: aload #9
    //   2950: invokevirtual getPackage : ()Ljava/lang/Package;
    //   2953: ifnull -> 3011
    //   2956: goto -> 2963
    //   2959: invokestatic a : (Ljava/lang/Throwable;)Ljava/lang/Throwable;
    //   2962: athrow
    //   2963: aload #9
    //   2965: invokevirtual getPackage : ()Ljava/lang/Package;
    //   2968: invokevirtual getName : ()Ljava/lang/String;
    //   2971: ifnull -> 3011
    //   2974: goto -> 2981
    //   2977: invokestatic a : (Ljava/lang/Throwable;)Ljava/lang/Throwable;
    //   2980: athrow
    //   2981: aload #9
    //   2983: invokevirtual getPackage : ()Ljava/lang/Package;
    //   2986: invokevirtual getName : ()Ljava/lang/String;
    //   2989: sipush #-14357
    //   2992: sipush #-23898
    //   2995: invokestatic a : (II)Ljava/lang/String;
    //   2998: invokevirtual startsWith : (Ljava/lang/String;)Z
    //   3001: ifne -> 3011
    //   3004: goto -> 3011
    //   3007: invokestatic a : (Ljava/lang/Throwable;)Ljava/lang/Throwable;
    //   3010: athrow
    //   3011: aload #8
    //   3013: iconst_1
    //   3014: invokevirtual setAccessible : (Z)V
    //   3017: aload #8
    //   3019: aconst_null
    //   3020: invokevirtual get : (Ljava/lang/Object;)Ljava/lang/Object;
    //   3023: pop
    //   3024: iinc #7, 1
    //   3027: iload_2
    //   3028: ifeq -> 2889
    //   3031: sipush #-14337
    //   3034: sipush #-14837
    //   3037: invokestatic a : (II)Ljava/lang/String;
    //   3040: invokestatic forName : (Ljava/lang/String;)Ljava/lang/Class;
    //   3043: invokevirtual getDeclaredMethods : ()[Ljava/lang/reflect/Method;
    //   3046: astore #5
    //   3048: aload #5
    //   3050: arraylength
    //   3051: istore #6
    //   3053: iconst_0
    //   3054: istore #7
    //   3056: iload #7
    //   3058: iload #6
    //   3060: if_icmpge -> 3197
    //   3063: aload #5
    //   3065: iload #7
    //   3067: aaload
    //   3068: astore #8
    //   3070: aload #8
    //   3072: invokevirtual getParameterTypes : ()[Ljava/lang/Class;
    //   3075: pop
    //   3076: aload #8
    //   3078: invokevirtual getModifiers : ()I
    //   3081: invokestatic isStatic : (I)Z
    //   3084: ifeq -> 3183
    //   3087: aload #8
    //   3089: invokevirtual getParameterTypes : ()[Ljava/lang/Class;
    //   3092: arraylength
    //   3093: iconst_2
    //   3094: if_icmpne -> 3183
    //   3097: goto -> 3104
    //   3100: invokestatic a : (Ljava/lang/Throwable;)Ljava/lang/Throwable;
    //   3103: athrow
    //   3104: aload #8
    //   3106: invokevirtual getReturnType : ()Ljava/lang/Class;
    //   3109: getstatic java/lang/Boolean.TYPE : Ljava/lang/Class;
    //   3112: if_acmpne -> 3183
    //   3115: goto -> 3122
    //   3118: invokestatic a : (Ljava/lang/Throwable;)Ljava/lang/Throwable;
    //   3121: athrow
    //   3122: aload #8
    //   3124: iconst_1
    //   3125: invokevirtual setAccessible : (Z)V
    //   3128: aload #8
    //   3130: aconst_null
    //   3131: iconst_2
    //   3132: anewarray java/lang/Object
    //   3135: dup
    //   3136: iconst_0
    //   3137: aload_0
    //   3138: aastore
    //   3139: dup
    //   3140: iconst_1
    //   3141: aload_1
    //   3142: ifnonnull -> 3160
    //   3145: goto -> 3152
    //   3148: invokestatic a : (Ljava/lang/Throwable;)Ljava/lang/Throwable;
    //   3151: athrow
    //   3152: aload_1
    //   3153: goto -> 3167
    //   3156: invokestatic a : (Ljava/lang/Throwable;)Ljava/lang/Throwable;
    //   3159: athrow
    //   3160: aload_1
    //   3161: checkcast [B
    //   3164: invokevirtual clone : ()Ljava/lang/Object;
    //   3167: aastore
    //   3168: invokevirtual invoke : (Ljava/lang/Object;[Ljava/lang/Object;)Ljava/lang/Object;
    //   3171: checkcast java/lang/Boolean
    //   3174: invokevirtual booleanValue : ()Z
    //   3177: istore #4
    //   3179: iload_2
    //   3180: ifeq -> 3197
    //   3183: iinc #7, 1
    //   3186: iload_2
    //   3187: ifeq -> 3056
    //   3190: goto -> 3197
    //   3193: invokestatic a : (Ljava/lang/Throwable;)Ljava/lang/Throwable;
    //   3196: athrow
    //   3197: iload #4
    //   3199: ifeq -> 3205
    //   3202: iload #4
    //   3204: ireturn
    //   3205: getstatic burp/Zmhi.ZQ : Ljava/lang/String;
    //   3208: getstatic burp/Zzgh.ZV : Ljava/lang/Object;
    //   3211: checkcast java/math/BigInteger
    //   3214: invokevirtual intValue : ()I
    //   3217: bipush #32
    //   3219: irem
    //   3220: invokestatic abs : (I)I
    //   3223: invokevirtual charAt : (I)C
    //   3226: getstatic burp/Zz6t.Zx : Ljava/lang/String;
    //   3229: getstatic burp/Zbzk.ZI : Ljava/lang/Object;
    //   3232: checkcast java/math/BigInteger
    //   3235: invokevirtual intValue : ()I
    //   3238: bipush #32
    //   3240: irem
    //   3241: invokestatic abs : (I)I
    //   3244: invokevirtual charAt : (I)C
    //   3247: if_icmpgt -> 3593
    //   3250: sipush #-14350
    //   3253: sipush #-1924
    //   3256: invokestatic a : (II)Ljava/lang/String;
    //   3259: iconst_1
    //   3260: ldc burp/Zg0j
    //   3262: invokevirtual getClassLoader : ()Ljava/lang/ClassLoader;
    //   3265: invokestatic forName : (Ljava/lang/String;ZLjava/lang/ClassLoader;)Ljava/lang/Class;
    //   3268: invokevirtual getDeclaredFields : ()[Ljava/lang/reflect/Field;
    //   3271: astore #5
    //   3273: aload #5
    //   3275: arraylength
    //   3276: istore #6
    //   3278: iconst_0
    //   3279: istore #7
    //   3281: iload #7
    //   3283: iload #6
    //   3285: if_icmpge -> 3423
    //   3288: aload #5
    //   3290: iload #7
    //   3292: aaload
    //   3293: astore #8
    //   3295: aload #8
    //   3297: invokevirtual getModifiers : ()I
    //   3300: invokestatic isStatic : (I)Z
    //   3303: ifne -> 3313
    //   3306: goto -> 3416
    //   3309: invokestatic a : (Ljava/lang/Throwable;)Ljava/lang/Throwable;
    //   3312: athrow
    //   3313: aload #8
    //   3315: invokevirtual getType : ()Ljava/lang/Class;
    //   3318: astore #9
    //   3320: aload #9
    //   3322: ifnull -> 3403
    //   3325: aload #9
    //   3327: invokevirtual isPrimitive : ()Z
    //   3330: ifne -> 3403
    //   3333: goto -> 3340
    //   3336: invokestatic a : (Ljava/lang/Throwable;)Ljava/lang/Throwable;
    //   3339: athrow
    //   3340: aload #9
    //   3342: invokevirtual getPackage : ()Ljava/lang/Package;
    //   3345: ifnull -> 3403
    //   3348: goto -> 3355
    //   3351: invokestatic a : (Ljava/lang/Throwable;)Ljava/lang/Throwable;
    //   3354: athrow
    //   3355: aload #9
    //   3357: invokevirtual getPackage : ()Ljava/lang/Package;
    //   3360: invokevirtual getName : ()Ljava/lang/String;
    //   3363: ifnull -> 3403
    //   3366: goto -> 3373
    //   3369: invokestatic a : (Ljava/lang/Throwable;)Ljava/lang/Throwable;
    //   3372: athrow
    //   3373: aload #9
    //   3375: invokevirtual getPackage : ()Ljava/lang/Package;
    //   3378: invokevirtual getName : ()Ljava/lang/String;
    //   3381: sipush #-14357
    //   3384: sipush #-23898
    //   3387: invokestatic a : (II)Ljava/lang/String;
    //   3390: invokevirtual startsWith : (Ljava/lang/String;)Z
    //   3393: ifne -> 3403
    //   3396: goto -> 3403
    //   3399: invokestatic a : (Ljava/lang/Throwable;)Ljava/lang/Throwable;
    //   3402: athrow
    //   3403: aload #8
    //   3405: iconst_1
    //   3406: invokevirtual setAccessible : (Z)V
    //   3409: aload #8
    //   3411: aconst_null
    //   3412: invokevirtual get : (Ljava/lang/Object;)Ljava/lang/Object;
    //   3415: pop
    //   3416: iinc #7, 1
    //   3419: iload_2
    //   3420: ifeq -> 3281
    //   3423: sipush #-14352
    //   3426: sipush #15709
    //   3429: invokestatic a : (II)Ljava/lang/String;
    //   3432: invokestatic forName : (Ljava/lang/String;)Ljava/lang/Class;
    //   3435: invokevirtual getDeclaredMethods : ()[Ljava/lang/reflect/Method;
    //   3438: astore #5
    //   3440: aload #5
    //   3442: arraylength
    //   3443: istore #6
    //   3445: iconst_0
    //   3446: istore #7
    //   3448: iload #7
    //   3450: iload #6
    //   3452: if_icmpge -> 3589
    //   3455: aload #5
    //   3457: iload #7
    //   3459: aaload
    //   3460: astore #8
    //   3462: aload #8
    //   3464: invokevirtual getParameterTypes : ()[Ljava/lang/Class;
    //   3467: pop
    //   3468: aload #8
    //   3470: invokevirtual getModifiers : ()I
    //   3473: invokestatic isStatic : (I)Z
    //   3476: ifeq -> 3575
    //   3479: aload #8
    //   3481: invokevirtual getParameterTypes : ()[Ljava/lang/Class;
    //   3484: arraylength
    //   3485: iconst_2
    //   3486: if_icmpne -> 3575
    //   3489: goto -> 3496
    //   3492: invokestatic a : (Ljava/lang/Throwable;)Ljava/lang/Throwable;
    //   3495: athrow
    //   3496: aload #8
    //   3498: invokevirtual getReturnType : ()Ljava/lang/Class;
    //   3501: getstatic java/lang/Boolean.TYPE : Ljava/lang/Class;
    //   3504: if_acmpne -> 3575
    //   3507: goto -> 3514
    //   3510: invokestatic a : (Ljava/lang/Throwable;)Ljava/lang/Throwable;
    //   3513: athrow
    //   3514: aload #8
    //   3516: iconst_1
    //   3517: invokevirtual setAccessible : (Z)V
    //   3520: aload #8
    //   3522: aconst_null
    //   3523: iconst_2
    //   3524: anewarray java/lang/Object
    //   3527: dup
    //   3528: iconst_0
    //   3529: aload_0
    //   3530: aastore
    //   3531: dup
    //   3532: iconst_1
    //   3533: aload_1
    //   3534: ifnonnull -> 3552
    //   3537: goto -> 3544
    //   3540: invokestatic a : (Ljava/lang/Throwable;)Ljava/lang/Throwable;
    //   3543: athrow
    //   3544: aload_1
    //   3545: goto -> 3559
    //   3548: invokestatic a : (Ljava/lang/Throwable;)Ljava/lang/Throwable;
    //   3551: athrow
    //   3552: aload_1
    //   3553: checkcast [B
    //   3556: invokevirtual clone : ()Ljava/lang/Object;
    //   3559: aastore
    //   3560: invokevirtual invoke : (Ljava/lang/Object;[Ljava/lang/Object;)Ljava/lang/Object;
    //   3563: checkcast java/lang/Boolean
    //   3566: invokevirtual booleanValue : ()Z
    //   3569: istore #4
    //   3571: iload_2
    //   3572: ifeq -> 3589
    //   3575: iinc #7, 1
    //   3578: iload_2
    //   3579: ifeq -> 3448
    //   3582: goto -> 3589
    //   3585: invokestatic a : (Ljava/lang/Throwable;)Ljava/lang/Throwable;
    //   3588: athrow
    //   3589: iload_2
    //   3590: ifeq -> 3932
    //   3593: sipush #-14345
    //   3596: sipush #10628
    //   3599: invokestatic a : (II)Ljava/lang/String;
    //   3602: iconst_1
    //   3603: ldc burp/Zzh1
    //   3605: invokevirtual getClassLoader : ()Ljava/lang/ClassLoader;
    //   3608: invokestatic forName : (Ljava/lang/String;ZLjava/lang/ClassLoader;)Ljava/lang/Class;
    //   3611: invokevirtual getDeclaredFields : ()[Ljava/lang/reflect/Field;
    //   3614: astore #5
    //   3616: aload #5
    //   3618: arraylength
    //   3619: istore #6
    //   3621: iconst_0
    //   3622: istore #7
    //   3624: iload #7
    //   3626: iload #6
    //   3628: if_icmpge -> 3766
    //   3631: aload #5
    //   3633: iload #7
    //   3635: aaload
    //   3636: astore #8
    //   3638: aload #8
    //   3640: invokevirtual getModifiers : ()I
    //   3643: invokestatic isStatic : (I)Z
    //   3646: ifne -> 3656
    //   3649: goto -> 3759
    //   3652: invokestatic a : (Ljava/lang/Throwable;)Ljava/lang/Throwable;
    //   3655: athrow
    //   3656: aload #8
    //   3658: invokevirtual getType : ()Ljava/lang/Class;
    //   3661: astore #9
    //   3663: aload #9
    //   3665: ifnull -> 3746
    //   3668: aload #9
    //   3670: invokevirtual isPrimitive : ()Z
    //   3673: ifne -> 3746
    //   3676: goto -> 3683
    //   3679: invokestatic a : (Ljava/lang/Throwable;)Ljava/lang/Throwable;
    //   3682: athrow
    //   3683: aload #9
    //   3685: invokevirtual getPackage : ()Ljava/lang/Package;
    //   3688: ifnull -> 3746
    //   3691: goto -> 3698
    //   3694: invokestatic a : (Ljava/lang/Throwable;)Ljava/lang/Throwable;
    //   3697: athrow
    //   3698: aload #9
    //   3700: invokevirtual getPackage : ()Ljava/lang/Package;
    //   3703: invokevirtual getName : ()Ljava/lang/String;
    //   3706: ifnull -> 3746
    //   3709: goto -> 3716
    //   3712: invokestatic a : (Ljava/lang/Throwable;)Ljava/lang/Throwable;
    //   3715: athrow
    //   3716: aload #9
    //   3718: invokevirtual getPackage : ()Ljava/lang/Package;
    //   3721: invokevirtual getName : ()Ljava/lang/String;
    //   3724: sipush #-14357
    //   3727: sipush #-23898
    //   3730: invokestatic a : (II)Ljava/lang/String;
    //   3733: invokevirtual startsWith : (Ljava/lang/String;)Z
    //   3736: ifne -> 3746
    //   3739: goto -> 3746
    //   3742: invokestatic a : (Ljava/lang/Throwable;)Ljava/lang/Throwable;
    //   3745: athrow
    //   3746: aload #8
    //   3748: iconst_1
    //   3749: invokevirtual setAccessible : (Z)V
    //   3752: aload #8
    //   3754: aconst_null
    //   3755: invokevirtual get : (Ljava/lang/Object;)Ljava/lang/Object;
    //   3758: pop
    //   3759: iinc #7, 1
    //   3762: iload_2
    //   3763: ifeq -> 3624
    //   3766: sipush #-14355
    //   3769: sipush #-11096
    //   3772: invokestatic a : (II)Ljava/lang/String;
    //   3775: invokestatic forName : (Ljava/lang/String;)Ljava/lang/Class;
    //   3778: invokevirtual getDeclaredMethods : ()[Ljava/lang/reflect/Method;
    //   3781: astore #5
    //   3783: aload #5
    //   3785: arraylength
    //   3786: istore #6
    //   3788: iconst_0
    //   3789: istore #7
    //   3791: iload #7
    //   3793: iload #6
    //   3795: if_icmpge -> 3932
    //   3798: aload #5
    //   3800: iload #7
    //   3802: aaload
    //   3803: astore #8
    //   3805: aload #8
    //   3807: invokevirtual getParameterTypes : ()[Ljava/lang/Class;
    //   3810: pop
    //   3811: aload #8
    //   3813: invokevirtual getModifiers : ()I
    //   3816: invokestatic isStatic : (I)Z
    //   3819: ifeq -> 3918
    //   3822: aload #8
    //   3824: invokevirtual getParameterTypes : ()[Ljava/lang/Class;
    //   3827: arraylength
    //   3828: iconst_2
    //   3829: if_icmpne -> 3918
    //   3832: goto -> 3839
    //   3835: invokestatic a : (Ljava/lang/Throwable;)Ljava/lang/Throwable;
    //   3838: athrow
    //   3839: aload #8
    //   3841: invokevirtual getReturnType : ()Ljava/lang/Class;
    //   3844: getstatic java/lang/Boolean.TYPE : Ljava/lang/Class;
    //   3847: if_acmpne -> 3918
    //   3850: goto -> 3857
    //   3853: invokestatic a : (Ljava/lang/Throwable;)Ljava/lang/Throwable;
    //   3856: athrow
    //   3857: aload #8
    //   3859: iconst_1
    //   3860: invokevirtual setAccessible : (Z)V
    //   3863: aload #8
    //   3865: aconst_null
    //   3866: iconst_2
    //   3867: anewarray java/lang/Object
    //   3870: dup
    //   3871: iconst_0
    //   3872: aload_0
    //   3873: aastore
    //   3874: dup
    //   3875: iconst_1
    //   3876: aload_1
    //   3877: ifnonnull -> 3895
    //   3880: goto -> 3887
    //   3883: invokestatic a : (Ljava/lang/Throwable;)Ljava/lang/Throwable;
    //   3886: athrow
    //   3887: aload_1
    //   3888: goto -> 3902
    //   3891: invokestatic a : (Ljava/lang/Throwable;)Ljava/lang/Throwable;
    //   3894: athrow
    //   3895: aload_1
    //   3896: checkcast [B
    //   3899: invokevirtual clone : ()Ljava/lang/Object;
    //   3902: aastore
    //   3903: invokevirtual invoke : (Ljava/lang/Object;[Ljava/lang/Object;)Ljava/lang/Object;
    //   3906: checkcast java/lang/Boolean
    //   3909: invokevirtual booleanValue : ()Z
    //   3912: istore #4
    //   3914: iload_2
    //   3915: ifeq -> 3932
    //   3918: iinc #7, 1
    //   3921: iload_2
    //   3922: ifeq -> 3791
    //   3925: goto -> 3932
    //   3928: invokestatic a : (Ljava/lang/Throwable;)Ljava/lang/Throwable;
    //   3931: athrow
    //   3932: iload #4
    //   3934: ifeq -> 3940
    //   3937: iload #4
    //   3939: ireturn
    //   3940: getstatic burp/Ze64.ZM : Ljava/lang/String;
    //   3943: getstatic burp/Zef0.ZX : Ljava/lang/Object;
    //   3946: checkcast java/math/BigInteger
    //   3949: invokevirtual intValue : ()I
    //   3952: bipush #32
    //   3954: irem
    //   3955: invokestatic abs : (I)I
    //   3958: invokevirtual charAt : (I)C
    //   3961: getstatic burp/Zlck.ZL : Ljava/lang/String;
    //   3964: getstatic burp/Zli5.Zt : Ljava/lang/Object;
    //   3967: checkcast java/math/BigInteger
    //   3970: invokevirtual intValue : ()I
    //   3973: bipush #32
    //   3975: irem
    //   3976: invokestatic abs : (I)I
    //   3979: invokevirtual charAt : (I)C
    //   3982: if_icmple -> 4328
    //   3985: sipush #-14344
    //   3988: sipush #-22258
    //   3991: invokestatic a : (II)Ljava/lang/String;
    //   3994: iconst_1
    //   3995: ldc burp/Zelc
    //   3997: invokevirtual getClassLoader : ()Ljava/lang/ClassLoader;
    //   4000: invokestatic forName : (Ljava/lang/String;ZLjava/lang/ClassLoader;)Ljava/lang/Class;
    //   4003: invokevirtual getDeclaredFields : ()[Ljava/lang/reflect/Field;
    //   4006: astore #5
    //   4008: aload #5
    //   4010: arraylength
    //   4011: istore #6
    //   4013: iconst_0
    //   4014: istore #7
    //   4016: iload #7
    //   4018: iload #6
    //   4020: if_icmpge -> 4158
    //   4023: aload #5
    //   4025: iload #7
    //   4027: aaload
    //   4028: astore #8
    //   4030: aload #8
    //   4032: invokevirtual getModifiers : ()I
    //   4035: invokestatic isStatic : (I)Z
    //   4038: ifne -> 4048
    //   4041: goto -> 4151
    //   4044: invokestatic a : (Ljava/lang/Throwable;)Ljava/lang/Throwable;
    //   4047: athrow
    //   4048: aload #8
    //   4050: invokevirtual getType : ()Ljava/lang/Class;
    //   4053: astore #9
    //   4055: aload #9
    //   4057: ifnull -> 4138
    //   4060: aload #9
    //   4062: invokevirtual isPrimitive : ()Z
    //   4065: ifne -> 4138
    //   4068: goto -> 4075
    //   4071: invokestatic a : (Ljava/lang/Throwable;)Ljava/lang/Throwable;
    //   4074: athrow
    //   4075: aload #9
    //   4077: invokevirtual getPackage : ()Ljava/lang/Package;
    //   4080: ifnull -> 4138
    //   4083: goto -> 4090
    //   4086: invokestatic a : (Ljava/lang/Throwable;)Ljava/lang/Throwable;
    //   4089: athrow
    //   4090: aload #9
    //   4092: invokevirtual getPackage : ()Ljava/lang/Package;
    //   4095: invokevirtual getName : ()Ljava/lang/String;
    //   4098: ifnull -> 4138
    //   4101: goto -> 4108
    //   4104: invokestatic a : (Ljava/lang/Throwable;)Ljava/lang/Throwable;
    //   4107: athrow
    //   4108: aload #9
    //   4110: invokevirtual getPackage : ()Ljava/lang/Package;
    //   4113: invokevirtual getName : ()Ljava/lang/String;
    //   4116: sipush #-14357
    //   4119: sipush #-23898
    //   4122: invokestatic a : (II)Ljava/lang/String;
    //   4125: invokevirtual startsWith : (Ljava/lang/String;)Z
    //   4128: ifne -> 4138
    //   4131: goto -> 4138
    //   4134: invokestatic a : (Ljava/lang/Throwable;)Ljava/lang/Throwable;
    //   4137: athrow
    //   4138: aload #8
    //   4140: iconst_1
    //   4141: invokevirtual setAccessible : (Z)V
    //   4144: aload #8
    //   4146: aconst_null
    //   4147: invokevirtual get : (Ljava/lang/Object;)Ljava/lang/Object;
    //   4150: pop
    //   4151: iinc #7, 1
    //   4154: iload_2
    //   4155: ifeq -> 4016
    //   4158: sipush #-14364
    //   4161: sipush #28109
    //   4164: invokestatic a : (II)Ljava/lang/String;
    //   4167: invokestatic forName : (Ljava/lang/String;)Ljava/lang/Class;
    //   4170: invokevirtual getDeclaredMethods : ()[Ljava/lang/reflect/Method;
    //   4173: astore #5
    //   4175: aload #5
    //   4177: arraylength
    //   4178: istore #6
    //   4180: iconst_0
    //   4181: istore #7
    //   4183: iload #7
    //   4185: iload #6
    //   4187: if_icmpge -> 4324
    //   4190: aload #5
    //   4192: iload #7
    //   4194: aaload
    //   4195: astore #8
    //   4197: aload #8
    //   4199: invokevirtual getParameterTypes : ()[Ljava/lang/Class;
    //   4202: pop
    //   4203: aload #8
    //   4205: invokevirtual getModifiers : ()I
    //   4208: invokestatic isStatic : (I)Z
    //   4211: ifeq -> 4310
    //   4214: aload #8
    //   4216: invokevirtual getParameterTypes : ()[Ljava/lang/Class;
    //   4219: arraylength
    //   4220: iconst_2
    //   4221: if_icmpne -> 4310
    //   4224: goto -> 4231
    //   4227: invokestatic a : (Ljava/lang/Throwable;)Ljava/lang/Throwable;
    //   4230: athrow
    //   4231: aload #8
    //   4233: invokevirtual getReturnType : ()Ljava/lang/Class;
    //   4236: getstatic java/lang/Boolean.TYPE : Ljava/lang/Class;
    //   4239: if_acmpne -> 4310
    //   4242: goto -> 4249
    //   4245: invokestatic a : (Ljava/lang/Throwable;)Ljava/lang/Throwable;
    //   4248: athrow
    //   4249: aload #8
    //   4251: iconst_1
    //   4252: invokevirtual setAccessible : (Z)V
    //   4255: aload #8
    //   4257: aconst_null
    //   4258: iconst_2
    //   4259: anewarray java/lang/Object
    //   4262: dup
    //   4263: iconst_0
    //   4264: aload_0
    //   4265: aastore
    //   4266: dup
    //   4267: iconst_1
    //   4268: aload_1
    //   4269: ifnonnull -> 4287
    //   4272: goto -> 4279
    //   4275: invokestatic a : (Ljava/lang/Throwable;)Ljava/lang/Throwable;
    //   4278: athrow
    //   4279: aload_1
    //   4280: goto -> 4294
    //   4283: invokestatic a : (Ljava/lang/Throwable;)Ljava/lang/Throwable;
    //   4286: athrow
    //   4287: aload_1
    //   4288: checkcast [B
    //   4291: invokevirtual clone : ()Ljava/lang/Object;
    //   4294: aastore
    //   4295: invokevirtual invoke : (Ljava/lang/Object;[Ljava/lang/Object;)Ljava/lang/Object;
    //   4298: checkcast java/lang/Boolean
    //   4301: invokevirtual booleanValue : ()Z
    //   4304: istore #4
    //   4306: iload_2
    //   4307: ifeq -> 4324
    //   4310: iinc #7, 1
    //   4313: iload_2
    //   4314: ifeq -> 4183
    //   4317: goto -> 4324
    //   4320: invokestatic a : (Ljava/lang/Throwable;)Ljava/lang/Throwable;
    //   4323: athrow
    //   4324: iload_2
    //   4325: ifeq -> 4667
    //   4328: sipush #-14348
    //   4331: sipush #9756
    //   4334: invokestatic a : (II)Ljava/lang/String;
    //   4337: iconst_1
    //   4338: ldc burp/Zttq
    //   4340: invokevirtual getClassLoader : ()Ljava/lang/ClassLoader;
    //   4343: invokestatic forName : (Ljava/lang/String;ZLjava/lang/ClassLoader;)Ljava/lang/Class;
    //   4346: invokevirtual getDeclaredFields : ()[Ljava/lang/reflect/Field;
    //   4349: astore #5
    //   4351: aload #5
    //   4353: arraylength
    //   4354: istore #6
    //   4356: iconst_0
    //   4357: istore #7
    //   4359: iload #7
    //   4361: iload #6
    //   4363: if_icmpge -> 4501
    //   4366: aload #5
    //   4368: iload #7
    //   4370: aaload
    //   4371: astore #8
    //   4373: aload #8
    //   4375: invokevirtual getModifiers : ()I
    //   4378: invokestatic isStatic : (I)Z
    //   4381: ifne -> 4391
    //   4384: goto -> 4494
    //   4387: invokestatic a : (Ljava/lang/Throwable;)Ljava/lang/Throwable;
    //   4390: athrow
    //   4391: aload #8
    //   4393: invokevirtual getType : ()Ljava/lang/Class;
    //   4396: astore #9
    //   4398: aload #9
    //   4400: ifnull -> 4481
    //   4403: aload #9
    //   4405: invokevirtual isPrimitive : ()Z
    //   4408: ifne -> 4481
    //   4411: goto -> 4418
    //   4414: invokestatic a : (Ljava/lang/Throwable;)Ljava/lang/Throwable;
    //   4417: athrow
    //   4418: aload #9
    //   4420: invokevirtual getPackage : ()Ljava/lang/Package;
    //   4423: ifnull -> 4481
    //   4426: goto -> 4433
    //   4429: invokestatic a : (Ljava/lang/Throwable;)Ljava/lang/Throwable;
    //   4432: athrow
    //   4433: aload #9
    //   4435: invokevirtual getPackage : ()Ljava/lang/Package;
    //   4438: invokevirtual getName : ()Ljava/lang/String;
    //   4441: ifnull -> 4481
    //   4444: goto -> 4451
    //   4447: invokestatic a : (Ljava/lang/Throwable;)Ljava/lang/Throwable;
    //   4450: athrow
    //   4451: aload #9
    //   4453: invokevirtual getPackage : ()Ljava/lang/Package;
    //   4456: invokevirtual getName : ()Ljava/lang/String;
    //   4459: sipush #-14357
    //   4462: sipush #-23898
    //   4465: invokestatic a : (II)Ljava/lang/String;
    //   4468: invokevirtual startsWith : (Ljava/lang/String;)Z
    //   4471: ifne -> 4481
    //   4474: goto -> 4481
    //   4477: invokestatic a : (Ljava/lang/Throwable;)Ljava/lang/Throwable;
    //   4480: athrow
    //   4481: aload #8
    //   4483: iconst_1
    //   4484: invokevirtual setAccessible : (Z)V
    //   4487: aload #8
    //   4489: aconst_null
    //   4490: invokevirtual get : (Ljava/lang/Object;)Ljava/lang/Object;
    //   4493: pop
    //   4494: iinc #7, 1
    //   4497: iload_2
    //   4498: ifeq -> 4359
    //   4501: sipush #-14351
    //   4504: sipush #-27300
    //   4507: invokestatic a : (II)Ljava/lang/String;
    //   4510: invokestatic forName : (Ljava/lang/String;)Ljava/lang/Class;
    //   4513: invokevirtual getDeclaredMethods : ()[Ljava/lang/reflect/Method;
    //   4516: astore #5
    //   4518: aload #5
    //   4520: arraylength
    //   4521: istore #6
    //   4523: iconst_0
    //   4524: istore #7
    //   4526: iload #7
    //   4528: iload #6
    //   4530: if_icmpge -> 4667
    //   4533: aload #5
    //   4535: iload #7
    //   4537: aaload
    //   4538: astore #8
    //   4540: aload #8
    //   4542: invokevirtual getParameterTypes : ()[Ljava/lang/Class;
    //   4545: pop
    //   4546: aload #8
    //   4548: invokevirtual getModifiers : ()I
    //   4551: invokestatic isStatic : (I)Z
    //   4554: ifeq -> 4653
    //   4557: aload #8
    //   4559: invokevirtual getParameterTypes : ()[Ljava/lang/Class;
    //   4562: arraylength
    //   4563: iconst_2
    //   4564: if_icmpne -> 4653
    //   4567: goto -> 4574
    //   4570: invokestatic a : (Ljava/lang/Throwable;)Ljava/lang/Throwable;
    //   4573: athrow
    //   4574: aload #8
    //   4576: invokevirtual getReturnType : ()Ljava/lang/Class;
    //   4579: getstatic java/lang/Boolean.TYPE : Ljava/lang/Class;
    //   4582: if_acmpne -> 4653
    //   4585: goto -> 4592
    //   4588: invokestatic a : (Ljava/lang/Throwable;)Ljava/lang/Throwable;
    //   4591: athrow
    //   4592: aload #8
    //   4594: iconst_1
    //   4595: invokevirtual setAccessible : (Z)V
    //   4598: aload #8
    //   4600: aconst_null
    //   4601: iconst_2
    //   4602: anewarray java/lang/Object
    //   4605: dup
    //   4606: iconst_0
    //   4607: aload_0
    //   4608: aastore
    //   4609: dup
    //   4610: iconst_1
    //   4611: aload_1
    //   4612: ifnonnull -> 4630
    //   4615: goto -> 4622
    //   4618: invokestatic a : (Ljava/lang/Throwable;)Ljava/lang/Throwable;
    //   4621: athrow
    //   4622: aload_1
    //   4623: goto -> 4637
    //   4626: invokestatic a : (Ljava/lang/Throwable;)Ljava/lang/Throwable;
    //   4629: athrow
    //   4630: aload_1
    //   4631: checkcast [B
    //   4634: invokevirtual clone : ()Ljava/lang/Object;
    //   4637: aastore
    //   4638: invokevirtual invoke : (Ljava/lang/Object;[Ljava/lang/Object;)Ljava/lang/Object;
    //   4641: checkcast java/lang/Boolean
    //   4644: invokevirtual booleanValue : ()Z
    //   4647: istore #4
    //   4649: iload_2
    //   4650: ifeq -> 4667
    //   4653: iinc #7, 1
    //   4656: iload_2
    //   4657: ifeq -> 4526
    //   4660: goto -> 4667
    //   4663: invokestatic a : (Ljava/lang/Throwable;)Ljava/lang/Throwable;
    //   4666: athrow
    //   4667: iload #4
    //   4669: ifeq -> 4675
    //   4672: iload #4
    //   4674: ireturn
    //   4675: getstatic burp/Ztlz.ZE : Ljava/lang/String;
    //   4678: getstatic burp/Zlf0.ZC : Ljava/lang/Object;
    //   4681: checkcast java/math/BigInteger
    //   4684: invokevirtual intValue : ()I
    //   4687: bipush #32
    //   4689: irem
    //   4690: invokestatic abs : (I)I
    //   4693: invokevirtual charAt : (I)C
    //   4696: getstatic burp/Ztcv.Zl : Ljava/lang/String;
    //   4699: getstatic burp/Zr1z.Zi : Ljava/lang/Object;
    //   4702: checkcast java/math/BigInteger
    //   4705: invokevirtual intValue : ()I
    //   4708: bipush #32
    //   4710: irem
    //   4711: invokestatic abs : (I)I
    //   4714: invokevirtual charAt : (I)C
    //   4717: if_icmple -> 5063
    //   4720: sipush #-14338
    //   4723: sipush #-19588
    //   4726: invokestatic a : (II)Ljava/lang/String;
    //   4729: iconst_1
    //   4730: ldc burp/Zez0
    //   4732: invokevirtual getClassLoader : ()Ljava/lang/ClassLoader;
    //   4735: invokestatic forName : (Ljava/lang/String;ZLjava/lang/ClassLoader;)Ljava/lang/Class;
    //   4738: invokevirtual getDeclaredFields : ()[Ljava/lang/reflect/Field;
    //   4741: astore #5
    //   4743: aload #5
    //   4745: arraylength
    //   4746: istore #6
    //   4748: iconst_0
    //   4749: istore #7
    //   4751: iload #7
    //   4753: iload #6
    //   4755: if_icmpge -> 4893
    //   4758: aload #5
    //   4760: iload #7
    //   4762: aaload
    //   4763: astore #8
    //   4765: aload #8
    //   4767: invokevirtual getModifiers : ()I
    //   4770: invokestatic isStatic : (I)Z
    //   4773: ifne -> 4783
    //   4776: goto -> 4886
    //   4779: invokestatic a : (Ljava/lang/Throwable;)Ljava/lang/Throwable;
    //   4782: athrow
    //   4783: aload #8
    //   4785: invokevirtual getType : ()Ljava/lang/Class;
    //   4788: astore #9
    //   4790: aload #9
    //   4792: ifnull -> 4873
    //   4795: aload #9
    //   4797: invokevirtual isPrimitive : ()Z
    //   4800: ifne -> 4873
    //   4803: goto -> 4810
    //   4806: invokestatic a : (Ljava/lang/Throwable;)Ljava/lang/Throwable;
    //   4809: athrow
    //   4810: aload #9
    //   4812: invokevirtual getPackage : ()Ljava/lang/Package;
    //   4815: ifnull -> 4873
    //   4818: goto -> 4825
    //   4821: invokestatic a : (Ljava/lang/Throwable;)Ljava/lang/Throwable;
    //   4824: athrow
    //   4825: aload #9
    //   4827: invokevirtual getPackage : ()Ljava/lang/Package;
    //   4830: invokevirtual getName : ()Ljava/lang/String;
    //   4833: ifnull -> 4873
    //   4836: goto -> 4843
    //   4839: invokestatic a : (Ljava/lang/Throwable;)Ljava/lang/Throwable;
    //   4842: athrow
    //   4843: aload #9
    //   4845: invokevirtual getPackage : ()Ljava/lang/Package;
    //   4848: invokevirtual getName : ()Ljava/lang/String;
    //   4851: sipush #-14357
    //   4854: sipush #-23898
    //   4857: invokestatic a : (II)Ljava/lang/String;
    //   4860: invokevirtual startsWith : (Ljava/lang/String;)Z
    //   4863: ifne -> 4873
    //   4866: goto -> 4873
    //   4869: invokestatic a : (Ljava/lang/Throwable;)Ljava/lang/Throwable;
    //   4872: athrow
    //   4873: aload #8
    //   4875: iconst_1
    //   4876: invokevirtual setAccessible : (Z)V
    //   4879: aload #8
    //   4881: aconst_null
    //   4882: invokevirtual get : (Ljava/lang/Object;)Ljava/lang/Object;
    //   4885: pop
    //   4886: iinc #7, 1
    //   4889: iload_2
    //   4890: ifeq -> 4751
    //   4893: sipush #-14340
    //   4896: sipush #29758
    //   4899: invokestatic a : (II)Ljava/lang/String;
    //   4902: invokestatic forName : (Ljava/lang/String;)Ljava/lang/Class;
    //   4905: invokevirtual getDeclaredMethods : ()[Ljava/lang/reflect/Method;
    //   4908: astore #5
    //   4910: aload #5
    //   4912: arraylength
    //   4913: istore #6
    //   4915: iconst_0
    //   4916: istore #7
    //   4918: iload #7
    //   4920: iload #6
    //   4922: if_icmpge -> 5059
    //   4925: aload #5
    //   4927: iload #7
    //   4929: aaload
    //   4930: astore #8
    //   4932: aload #8
    //   4934: invokevirtual getParameterTypes : ()[Ljava/lang/Class;
    //   4937: pop
    //   4938: aload #8
    //   4940: invokevirtual getModifiers : ()I
    //   4943: invokestatic isStatic : (I)Z
    //   4946: ifeq -> 5045
    //   4949: aload #8
    //   4951: invokevirtual getParameterTypes : ()[Ljava/lang/Class;
    //   4954: arraylength
    //   4955: iconst_2
    //   4956: if_icmpne -> 5045
    //   4959: goto -> 4966
    //   4962: invokestatic a : (Ljava/lang/Throwable;)Ljava/lang/Throwable;
    //   4965: athrow
    //   4966: aload #8
    //   4968: invokevirtual getReturnType : ()Ljava/lang/Class;
    //   4971: getstatic java/lang/Boolean.TYPE : Ljava/lang/Class;
    //   4974: if_acmpne -> 5045
    //   4977: goto -> 4984
    //   4980: invokestatic a : (Ljava/lang/Throwable;)Ljava/lang/Throwable;
    //   4983: athrow
    //   4984: aload #8
    //   4986: iconst_1
    //   4987: invokevirtual setAccessible : (Z)V
    //   4990: aload #8
    //   4992: aconst_null
    //   4993: iconst_2
    //   4994: anewarray java/lang/Object
    //   4997: dup
    //   4998: iconst_0
    //   4999: aload_0
    //   5000: aastore
    //   5001: dup
    //   5002: iconst_1
    //   5003: aload_1
    //   5004: ifnonnull -> 5022
    //   5007: goto -> 5014
    //   5010: invokestatic a : (Ljava/lang/Throwable;)Ljava/lang/Throwable;
    //   5013: athrow
    //   5014: aload_1
    //   5015: goto -> 5029
    //   5018: invokestatic a : (Ljava/lang/Throwable;)Ljava/lang/Throwable;
    //   5021: athrow
    //   5022: aload_1
    //   5023: checkcast [B
    //   5026: invokevirtual clone : ()Ljava/lang/Object;
    //   5029: aastore
    //   5030: invokevirtual invoke : (Ljava/lang/Object;[Ljava/lang/Object;)Ljava/lang/Object;
    //   5033: checkcast java/lang/Boolean
    //   5036: invokevirtual booleanValue : ()Z
    //   5039: istore #4
    //   5041: iload_2
    //   5042: ifeq -> 5059
    //   5045: iinc #7, 1
    //   5048: iload_2
    //   5049: ifeq -> 4918
    //   5052: goto -> 5059
    //   5055: invokestatic a : (Ljava/lang/Throwable;)Ljava/lang/Throwable;
    //   5058: athrow
    //   5059: iload_2
    //   5060: ifeq -> 5402
    //   5063: sipush #-14365
    //   5066: sipush #-27750
    //   5069: invokestatic a : (II)Ljava/lang/String;
    //   5072: iconst_1
    //   5073: ldc burp/Zbo7
    //   5075: invokevirtual getClassLoader : ()Ljava/lang/ClassLoader;
    //   5078: invokestatic forName : (Ljava/lang/String;ZLjava/lang/ClassLoader;)Ljava/lang/Class;
    //   5081: invokevirtual getDeclaredFields : ()[Ljava/lang/reflect/Field;
    //   5084: astore #5
    //   5086: aload #5
    //   5088: arraylength
    //   5089: istore #6
    //   5091: iconst_0
    //   5092: istore #7
    //   5094: iload #7
    //   5096: iload #6
    //   5098: if_icmpge -> 5236
    //   5101: aload #5
    //   5103: iload #7
    //   5105: aaload
    //   5106: astore #8
    //   5108: aload #8
    //   5110: invokevirtual getModifiers : ()I
    //   5113: invokestatic isStatic : (I)Z
    //   5116: ifne -> 5126
    //   5119: goto -> 5229
    //   5122: invokestatic a : (Ljava/lang/Throwable;)Ljava/lang/Throwable;
    //   5125: athrow
    //   5126: aload #8
    //   5128: invokevirtual getType : ()Ljava/lang/Class;
    //   5131: astore #9
    //   5133: aload #9
    //   5135: ifnull -> 5216
    //   5138: aload #9
    //   5140: invokevirtual isPrimitive : ()Z
    //   5143: ifne -> 5216
    //   5146: goto -> 5153
    //   5149: invokestatic a : (Ljava/lang/Throwable;)Ljava/lang/Throwable;
    //   5152: athrow
    //   5153: aload #9
    //   5155: invokevirtual getPackage : ()Ljava/lang/Package;
    //   5158: ifnull -> 5216
    //   5161: goto -> 5168
    //   5164: invokestatic a : (Ljava/lang/Throwable;)Ljava/lang/Throwable;
    //   5167: athrow
    //   5168: aload #9
    //   5170: invokevirtual getPackage : ()Ljava/lang/Package;
    //   5173: invokevirtual getName : ()Ljava/lang/String;
    //   5176: ifnull -> 5216
    //   5179: goto -> 5186
    //   5182: invokestatic a : (Ljava/lang/Throwable;)Ljava/lang/Throwable;
    //   5185: athrow
    //   5186: aload #9
    //   5188: invokevirtual getPackage : ()Ljava/lang/Package;
    //   5191: invokevirtual getName : ()Ljava/lang/String;
    //   5194: sipush #-14357
    //   5197: sipush #-23898
    //   5200: invokestatic a : (II)Ljava/lang/String;
    //   5203: invokevirtual startsWith : (Ljava/lang/String;)Z
    //   5206: ifne -> 5216
    //   5209: goto -> 5216
    //   5212: invokestatic a : (Ljava/lang/Throwable;)Ljava/lang/Throwable;
    //   5215: athrow
    //   5216: aload #8
    //   5218: iconst_1
    //   5219: invokevirtual setAccessible : (Z)V
    //   5222: aload #8
    //   5224: aconst_null
    //   5225: invokevirtual get : (Ljava/lang/Object;)Ljava/lang/Object;
    //   5228: pop
    //   5229: iinc #7, 1
    //   5232: iload_2
    //   5233: ifeq -> 5094
    //   5236: sipush #-14367
    //   5239: sipush #-13158
    //   5242: invokestatic a : (II)Ljava/lang/String;
    //   5245: invokestatic forName : (Ljava/lang/String;)Ljava/lang/Class;
    //   5248: invokevirtual getDeclaredMethods : ()[Ljava/lang/reflect/Method;
    //   5251: astore #5
    //   5253: aload #5
    //   5255: arraylength
    //   5256: istore #6
    //   5258: iconst_0
    //   5259: istore #7
    //   5261: iload #7
    //   5263: iload #6
    //   5265: if_icmpge -> 5402
    //   5268: aload #5
    //   5270: iload #7
    //   5272: aaload
    //   5273: astore #8
    //   5275: aload #8
    //   5277: invokevirtual getParameterTypes : ()[Ljava/lang/Class;
    //   5280: pop
    //   5281: aload #8
    //   5283: invokevirtual getModifiers : ()I
    //   5286: invokestatic isStatic : (I)Z
    //   5289: ifeq -> 5388
    //   5292: aload #8
    //   5294: invokevirtual getParameterTypes : ()[Ljava/lang/Class;
    //   5297: arraylength
    //   5298: iconst_2
    //   5299: if_icmpne -> 5388
    //   5302: goto -> 5309
    //   5305: invokestatic a : (Ljava/lang/Throwable;)Ljava/lang/Throwable;
    //   5308: athrow
    //   5309: aload #8
    //   5311: invokevirtual getReturnType : ()Ljava/lang/Class;
    //   5314: getstatic java/lang/Boolean.TYPE : Ljava/lang/Class;
    //   5317: if_acmpne -> 5388
    //   5320: goto -> 5327
    //   5323: invokestatic a : (Ljava/lang/Throwable;)Ljava/lang/Throwable;
    //   5326: athrow
    //   5327: aload #8
    //   5329: iconst_1
    //   5330: invokevirtual setAccessible : (Z)V
    //   5333: aload #8
    //   5335: aconst_null
    //   5336: iconst_2
    //   5337: anewarray java/lang/Object
    //   5340: dup
    //   5341: iconst_0
    //   5342: aload_0
    //   5343: aastore
    //   5344: dup
    //   5345: iconst_1
    //   5346: aload_1
    //   5347: ifnonnull -> 5365
    //   5350: goto -> 5357
    //   5353: invokestatic a : (Ljava/lang/Throwable;)Ljava/lang/Throwable;
    //   5356: athrow
    //   5357: aload_1
    //   5358: goto -> 5372
    //   5361: invokestatic a : (Ljava/lang/Throwable;)Ljava/lang/Throwable;
    //   5364: athrow
    //   5365: aload_1
    //   5366: checkcast [B
    //   5369: invokevirtual clone : ()Ljava/lang/Object;
    //   5372: aastore
    //   5373: invokevirtual invoke : (Ljava/lang/Object;[Ljava/lang/Object;)Ljava/lang/Object;
    //   5376: checkcast java/lang/Boolean
    //   5379: invokevirtual booleanValue : ()Z
    //   5382: istore #4
    //   5384: iload_2
    //   5385: ifeq -> 5402
    //   5388: iinc #7, 1
    //   5391: iload_2
    //   5392: ifeq -> 5261
    //   5395: goto -> 5402
    //   5398: invokestatic a : (Ljava/lang/Throwable;)Ljava/lang/Throwable;
    //   5401: athrow
    //   5402: iload #4
    //   5404: ireturn
    //   5405: astore_3
    //   5406: new java/lang/Exception
    //   5409: dup
    //   5410: aload_3
    //   5411: invokevirtual getMessage : ()Ljava/lang/String;
    //   5414: invokespecial <init> : (Ljava/lang/String;)V
    //   5417: athrow
    // Exception table:
    //   from	to	target	type
    //   4	2469	5405	java/lang/Throwable
    //   22	198	201	java/lang/Throwable
    //   168	235	238	java/lang/Throwable
    //   205	272	275	java/lang/Throwable
    //   242	309	312	java/lang/Throwable
    //   279	346	349	java/lang/Throwable
    //   316	383	386	java/lang/Throwable
    //   353	420	423	java/lang/Throwable
    //   390	457	460	java/lang/Throwable
    //   427	494	497	java/lang/Throwable
    //   464	531	534	java/lang/Throwable
    //   501	568	571	java/lang/Throwable
    //   538	605	608	java/lang/Throwable
    //   575	642	645	java/lang/Throwable
    //   612	679	682	java/lang/Throwable
    //   649	716	719	java/lang/Throwable
    //   686	753	756	java/lang/Throwable
    //   723	790	793	java/lang/Throwable
    //   760	827	830	java/lang/Throwable
    //   797	864	867	java/lang/Throwable
    //   834	901	904	java/lang/Throwable
    //   871	938	941	java/lang/Throwable
    //   908	975	978	java/lang/Throwable
    //   945	1012	1015	java/lang/Throwable
    //   982	1049	1052	java/lang/Throwable
    //   1019	1086	1089	java/lang/Throwable
    //   1056	1123	1126	java/lang/Throwable
    //   1093	1160	1163	java/lang/Throwable
    //   1130	1197	1200	java/lang/Throwable
    //   1167	1234	1237	java/lang/Throwable
    //   1204	1271	1274	java/lang/Throwable
    //   1241	1308	1311	java/lang/Throwable
    //   1278	1341	1344	java/lang/Throwable
    //   1443	1457	1457	java/lang/Throwable
    //   1468	1481	1484	java/lang/Throwable
    //   1473	1496	1499	java/lang/Throwable
    //   1488	1514	1517	java/lang/Throwable
    //   1503	1544	1547	java/lang/Throwable
    //   1610	1637	1640	java/lang/Throwable
    //   1627	1658	1661	java/lang/Throwable
    //   1644	1688	1691	java/lang/Throwable
    //   1665	1699	1699	java/lang/Throwable
    //   1710	1726	1729	java/lang/Throwable
    //   1826	1840	1840	java/lang/Throwable
    //   1851	1864	1867	java/lang/Throwable
    //   1856	1879	1882	java/lang/Throwable
    //   1871	1897	1900	java/lang/Throwable
    //   1886	1927	1930	java/lang/Throwable
    //   1993	2020	2023	java/lang/Throwable
    //   2010	2038	2041	java/lang/Throwable
    //   2027	2068	2071	java/lang/Throwable
    //   2045	2079	2079	java/lang/Throwable
    //   2102	2113	2116	java/lang/Throwable
    //   2168	2182	2182	java/lang/Throwable
    //   2193	2206	2209	java/lang/Throwable
    //   2198	2221	2224	java/lang/Throwable
    //   2213	2239	2242	java/lang/Throwable
    //   2228	2269	2272	java/lang/Throwable
    //   2335	2362	2365	java/lang/Throwable
    //   2352	2380	2383	java/lang/Throwable
    //   2369	2410	2413	java/lang/Throwable
    //   2387	2421	2421	java/lang/Throwable
    //   2444	2455	2458	java/lang/Throwable
    //   2470	3204	5405	java/lang/Throwable
    //   2560	2574	2574	java/lang/Throwable
    //   2585	2598	2601	java/lang/Throwable
    //   2590	2613	2616	java/lang/Throwable
    //   2605	2631	2634	java/lang/Throwable
    //   2620	2661	2664	java/lang/Throwable
    //   2727	2754	2757	java/lang/Throwable
    //   2744	2772	2775	java/lang/Throwable
    //   2761	2802	2805	java/lang/Throwable
    //   2779	2813	2813	java/lang/Throwable
    //   2836	2847	2850	java/lang/Throwable
    //   2903	2917	2917	java/lang/Throwable
    //   2928	2941	2944	java/lang/Throwable
    //   2933	2956	2959	java/lang/Throwable
    //   2948	2974	2977	java/lang/Throwable
    //   2963	3004	3007	java/lang/Throwable
    //   3070	3097	3100	java/lang/Throwable
    //   3087	3115	3118	java/lang/Throwable
    //   3104	3145	3148	java/lang/Throwable
    //   3122	3156	3156	java/lang/Throwable
    //   3179	3190	3193	java/lang/Throwable
    //   3205	3939	5405	java/lang/Throwable
    //   3295	3309	3309	java/lang/Throwable
    //   3320	3333	3336	java/lang/Throwable
    //   3325	3348	3351	java/lang/Throwable
    //   3340	3366	3369	java/lang/Throwable
    //   3355	3396	3399	java/lang/Throwable
    //   3462	3489	3492	java/lang/Throwable
    //   3479	3507	3510	java/lang/Throwable
    //   3496	3537	3540	java/lang/Throwable
    //   3514	3548	3548	java/lang/Throwable
    //   3571	3582	3585	java/lang/Throwable
    //   3638	3652	3652	java/lang/Throwable
    //   3663	3676	3679	java/lang/Throwable
    //   3668	3691	3694	java/lang/Throwable
    //   3683	3709	3712	java/lang/Throwable
    //   3698	3739	3742	java/lang/Throwable
    //   3805	3832	3835	java/lang/Throwable
    //   3822	3850	3853	java/lang/Throwable
    //   3839	3880	3883	java/lang/Throwable
    //   3857	3891	3891	java/lang/Throwable
    //   3914	3925	3928	java/lang/Throwable
    //   3940	4674	5405	java/lang/Throwable
    //   4030	4044	4044	java/lang/Throwable
    //   4055	4068	4071	java/lang/Throwable
    //   4060	4083	4086	java/lang/Throwable
    //   4075	4101	4104	java/lang/Throwable
    //   4090	4131	4134	java/lang/Throwable
    //   4197	4224	4227	java/lang/Throwable
    //   4214	4242	4245	java/lang/Throwable
    //   4231	4272	4275	java/lang/Throwable
    //   4249	4283	4283	java/lang/Throwable
    //   4306	4317	4320	java/lang/Throwable
    //   4373	4387	4387	java/lang/Throwable
    //   4398	4411	4414	java/lang/Throwable
    //   4403	4426	4429	java/lang/Throwable
    //   4418	4444	4447	java/lang/Throwable
    //   4433	4474	4477	java/lang/Throwable
    //   4540	4567	4570	java/lang/Throwable
    //   4557	4585	4588	java/lang/Throwable
    //   4574	4615	4618	java/lang/Throwable
    //   4592	4626	4626	java/lang/Throwable
    //   4649	4660	4663	java/lang/Throwable
    //   4675	5404	5405	java/lang/Throwable
    //   4765	4779	4779	java/lang/Throwable
    //   4790	4803	4806	java/lang/Throwable
    //   4795	4818	4821	java/lang/Throwable
    //   4810	4836	4839	java/lang/Throwable
    //   4825	4866	4869	java/lang/Throwable
    //   4932	4959	4962	java/lang/Throwable
    //   4949	4977	4980	java/lang/Throwable
    //   4966	5007	5010	java/lang/Throwable
    //   4984	5018	5018	java/lang/Throwable
    //   5041	5052	5055	java/lang/Throwable
    //   5108	5122	5122	java/lang/Throwable
    //   5133	5146	5149	java/lang/Throwable
    //   5138	5161	5164	java/lang/Throwable
    //   5153	5179	5182	java/lang/Throwable
    //   5168	5209	5212	java/lang/Throwable
    //   5275	5302	5305	java/lang/Throwable
    //   5292	5320	5323	java/lang/Throwable
    //   5309	5350	5353	java/lang/Throwable
    //   5327	5361	5361	java/lang/Throwable
    //   5384	5395	5398	java/lang/Throwable
  }
  
  static {
    // Byte code:
    //   0: bipush #29
    //   2: anewarray java/lang/String
    //   5: astore #5
    //   7: iconst_0
    //   8: istore_3
    //   9: ldc '<f{B 1[*6W~09a>Ea4\\th5\\t]'\\t~\%K\\tY5G?+\\t8  <\\t=MfH@Nz\\t DA\\tA\\t b?\\temB!R!\\tKMHH@\\t#z\\ba45\\tj ]\\t\\r@Q"\\t6.\\f \\n|8;zP-\}a>.49>RPs\\t!;\\tZfU\\rK-(Kw\\t`s5MYN[rO[ 5z==hN\\n[;8j~{HJ'O?f2\\tL\\nHU\\t3y|\\t\\t^x7'
    //   11: dup
    //   12: astore_2
    //   13: invokevirtual length : ()I
    //   16: istore #4
    //   18: bipush #9
    //   20: istore_1
    //   21: iconst_m1
    //   22: istore_0
    //   23: bipush #106
    //   25: iinc #0, 1
    //   28: aload_2
    //   29: iload_0
    //   30: dup
    //   31: iload_1
    //   32: iadd
    //   33: invokevirtual substring : (II)Ljava/lang/String;
    //   36: iconst_m1
    //   37: goto -> 143
    //   40: aload #5
    //   42: swap
    //   43: iload_3
    //   44: iinc #3, 1
    //   47: swap
    //   48: aastore
    //   49: iload_0
    //   50: iload_1
    //   51: iadd
    //   52: dup
    //   53: istore_0
    //   54: iload #4
    //   56: if_icmpge -> 68
    //   59: aload_2
    //   60: iload_0
    //   61: invokevirtual charAt : (I)C
    //   64: istore_1
    //   65: goto -> 23
    //   68: ldc 'G+2Eo'
    //   70: dup
    //   71: astore_2
    //   72: invokevirtual length : ()I
    //   75: istore #4
    //   77: bipush #9
    //   79: istore_1
    //   80: iconst_m1
    //   81: istore_0
    //   82: bipush #94
    //   84: iinc #0, 1
    //   87: aload_2
    //   88: iload_0
    //   89: dup
    //   90: iload_1
    //   91: iadd
    //   92: invokevirtual substring : (II)Ljava/lang/String;
    //   95: iconst_0
    //   96: goto -> 143
    //   99: aload #5
    //   101: swap
    //   102: iload_3
    //   103: iinc #3, 1
    //   106: swap
    //   107: aastore
    //   108: iload_0
    //   109: iload_1
    //   110: iadd
    //   111: dup
    //   112: istore_0
    //   113: iload #4
    //   115: if_icmpge -> 127
    //   118: aload_2
    //   119: iload_0
    //   120: invokevirtual charAt : (I)C
    //   123: istore_1
    //   124: goto -> 82
    //   127: aload #5
    //   129: putstatic burp/Zs_v.a : [Ljava/lang/String;
    //   132: bipush #29
    //   134: anewarray java/lang/String
    //   137: putstatic burp/Zs_v.b : [Ljava/lang/String;
    //   140: goto -> 300
    //   143: dup_x2
    //   144: pop
    //   145: invokevirtual toCharArray : ()[C
    //   148: dup_x1
    //   149: arraylength
    //   150: dup_x2
    //   151: pop
    //   152: iconst_0
    //   153: istore #6
    //   155: dup2_x1
    //   156: pop2
    //   157: dup_x2
    //   158: iconst_1
    //   159: if_icmpgt -> 260
    //   162: dup2
    //   163: swap
    //   164: iload #6
    //   166: dup2_x1
    //   167: caload
    //   168: swap
    //   169: iload #6
    //   171: bipush #7
    //   173: irem
    //   174: tableswitch default -> 242, 0 -> 212, 1 -> 217, 2 -> 222, 3 -> 227, 4 -> 232, 5 -> 237
    //   212: bipush #19
    //   214: goto -> 244
    //   217: bipush #67
    //   219: goto -> 244
    //   222: bipush #7
    //   224: goto -> 244
    //   227: bipush #37
    //   229: goto -> 244
    //   232: bipush #52
    //   234: goto -> 244
    //   237: bipush #43
    //   239: goto -> 244
    //   242: bipush #127
    //   244: ixor
    //   245: ixor
    //   246: i2c
    //   247: castore
    //   248: iinc #6, 1
    //   251: dup
    //   252: ifne -> 260
    //   255: dup2
    //   256: dup_x1
    //   257: goto -> 166
    //   260: dup2_x1
    //   261: pop2
    //   262: dup_x2
    //   263: iload #6
    //   265: if_icmpgt -> 162
    //   268: pop
    //   269: new java/lang/String
    //   272: dup_x1
    //   273: swap
    //   274: invokespecial <init> : ([C)V
    //   277: invokevirtual intern : ()Ljava/lang/String;
    //   280: swap
    //   281: pop
    //   282: swap
    //   283: tableswitch default -> 40, 0 -> 99
    //   300: sipush #-14346
    //   303: sipush #4573
    //   306: invokestatic a : (II)Ljava/lang/String;
    //   309: putstatic burp/Zs_v.Zn : Ljava/lang/String;
    //   312: new java/math/BigInteger
    //   315: dup
    //   316: iconst_1
    //   317: bipush #32
    //   319: newarray byte
    //   321: dup
    //   322: iconst_0
    //   323: bipush #31
    //   325: bastore
    //   326: dup
    //   327: iconst_1
    //   328: bipush #59
    //   330: bastore
    //   331: dup
    //   332: iconst_2
    //   333: bipush #-38
    //   335: bastore
    //   336: dup
    //   337: iconst_3
    //   338: bipush #-111
    //   340: bastore
    //   341: dup
    //   342: iconst_4
    //   343: bipush #85
    //   345: bastore
    //   346: dup
    //   347: iconst_5
    //   348: bipush #26
    //   350: bastore
    //   351: dup
    //   352: bipush #6
    //   354: bipush #-22
    //   356: bastore
    //   357: dup
    //   358: bipush #7
    //   360: bipush #23
    //   362: bastore
    //   363: dup
    //   364: bipush #8
    //   366: bipush #-88
    //   368: bastore
    //   369: dup
    //   370: bipush #9
    //   372: bipush #-94
    //   374: bastore
    //   375: dup
    //   376: bipush #10
    //   378: iconst_5
    //   379: bastore
    //   380: dup
    //   381: bipush #11
    //   383: bipush #8
    //   385: bastore
    //   386: dup
    //   387: bipush #12
    //   389: bipush #71
    //   391: bastore
    //   392: dup
    //   393: bipush #13
    //   395: bipush #35
    //   397: bastore
    //   398: dup
    //   399: bipush #14
    //   401: bipush #-116
    //   403: bastore
    //   404: dup
    //   405: bipush #15
    //   407: bipush #-62
    //   409: bastore
    //   410: dup
    //   411: bipush #16
    //   413: bipush #85
    //   415: bastore
    //   416: dup
    //   417: bipush #17
    //   419: iconst_3
    //   420: bastore
    //   421: dup
    //   422: bipush #18
    //   424: bipush #-111
    //   426: bastore
    //   427: dup
    //   428: bipush #19
    //   430: bipush #-49
    //   432: bastore
    //   433: dup
    //   434: bipush #20
    //   436: bipush #-85
    //   438: bastore
    //   439: dup
    //   440: bipush #21
    //   442: bipush #-42
    //   444: bastore
    //   445: dup
    //   446: bipush #22
    //   448: bipush #-65
    //   450: bastore
    //   451: dup
    //   452: bipush #23
    //   454: bipush #117
    //   456: bastore
    //   457: dup
    //   458: bipush #24
    //   460: bipush #-70
    //   462: bastore
    //   463: dup
    //   464: bipush #25
    //   466: bipush #-28
    //   468: bastore
    //   469: dup
    //   470: bipush #26
    //   472: bipush #105
    //   474: bastore
    //   475: dup
    //   476: bipush #27
    //   478: bipush #-15
    //   480: bastore
    //   481: dup
    //   482: bipush #28
    //   484: bipush #-114
    //   486: bastore
    //   487: dup
    //   488: bipush #29
    //   490: iconst_0
    //   491: bastore
    //   492: dup
    //   493: bipush #30
    //   495: bipush #-104
    //   497: bastore
    //   498: dup
    //   499: bipush #31
    //   501: bipush #-34
    //   503: bastore
    //   504: invokespecial <init> : (I[B)V
    //   507: putstatic burp/Zs_v.Zs : Ljava/lang/Object;
    //   510: return
  }
  
  private static Throwable a(Throwable paramThrowable) {
    return paramThrowable;
  }
  
  private static String a(int paramInt1, int paramInt2) {
    int i = (paramInt1 ^ 0xFFFFC7F7) & 0xFFFF;
    if (b[i] == null) {
      char[] arrayOfChar = a[i].toCharArray();
      switch (arrayOfChar[0] & 0xFF) {
        case 0:
        
        case 1:
        
        case 2:
        
        case 3:
        
        case 4:
        
        case 5:
        
        case 6:
        
        case 7:
        
        case 8:
        
        case 9:
        
        case 10:
        
        case 11:
        
        case 12:
        
        case 13:
        
        case 14:
        
        case 15:
        
        case 16:
        
        case 17:
        
        case 18:
        
        case 19:
        
        case 20:
        
        case 21:
        
        case 22:
        
        case 23:
        
        case 24:
        
        case 25:
        
        case 26:
        
        case 27:
        
        case 28:
        
        case 29:
        
        case 30:
        
        case 31:
        
        case 32:
        
        case 33:
        
        case 34:
        
        case 35:
        
        case 36:
        
        case 37:
        
        case 38:
        
        case 39:
        
        case 40:
        
        case 41:
        
        case 42:
        
        case 43:
        
        case 44:
        
        case 45:
        
        case 46:
        
        case 47:
        
        case 48:
        
        case 49:
        
        case 50:
        
        case 51:
        
        case 52:
        
        case 53:
        
        case 54:
        
        case 55:
        
        case 56:
        
        case 57:
        
        case 58:
        
        case 59:
        
        case 60:
        
        case 61:
        
        case 62:
        
        case 63:
        
        case 64:
        
        case 65:
        
        case 66:
        
        case 67:
        
        case 68:
        
        case 69:
        
        case 70:
        
        case 71:
        
        case 72:
        
        case 73:
        
        case 74:
        
        case 75:
        
        case 76:
        
        case 77:
        
        case 78:
        
        case 79:
        
        case 80:
        
        case 81:
        
        case 82:
        
        case 83:
        
        case 84:
        
        case 85:
        
        case 86:
        
        case 87:
        
        case 88:
        
        case 89:
        
        case 90:
        
        case 91:
        
        case 92:
        
        case 93:
        
        case 94:
        
        case 95:
        
        case 96:
        
        case 97:
        
        case 98:
        
        case 99:
        
        case 100:
        
        case 101:
        
        case 102:
        
        case 103:
        
        case 104:
        
        case 105:
        
        case 106:
        
        case 107:
        
        case 108:
        
        case 109:
        
        case 110:
        
        case 111:
        
        case 112:
        
        case 113:
        
        case 114:
        
        case 115:
        
        case 116:
        
        case 117:
        
        case 118:
        
        case 119:
        
        case 120:
        
        case 121:
        
        case 122:
        
        case 123:
        
        case 124:
        
        case 125:
        
        case 126:
        
        case 127:
        
        case 128:
        
        case 129:
        
        case 130:
        
        case 131:
        
        case 132:
        
        case 133:
        
        case 134:
        
        case 135:
        
        case 136:
        
        case 137:
        
        case 138:
        
        case 139:
        
        case 140:
        
        case 141:
        
        case 142:
        
        case 143:
        
        case 144:
        
        case 145:
        
        case 146:
        
        case 147:
        
        case 148:
        
        case 149:
        
        case 150:
        
        case 151:
        
        case 152:
        
        case 153:
        
        case 154:
        
        case 155:
        
        case 156:
        
        case 157:
        
        case 158:
        
        case 159:
        
        case 160:
        
        case 161:
        
        case 162:
        
        case 163:
        
        case 164:
        
        case 165:
        
        case 166:
        
        case 167:
        
        case 168:
        
        case 169:
        
        case 170:
        
        case 171:
        
        case 172:
        
        case 173:
        
        case 174:
        
        case 175:
        
        case 176:
        
        case 177:
        
        case 178:
        
        case 179:
        
        case 180:
        
        case 181:
        
        case 182:
        
        case 183:
        
        case 184:
        
        case 185:
        
        case 186:
        
        case 187:
        
        case 188:
        
        case 189:
        
        case 190:
        
        case 191:
        
        case 192:
        
        case 193:
        
        case 194:
        
        case 195:
        
        case 196:
        
        case 197:
        
        case 198:
        
        case 199:
        
        case 200:
        
        case 201:
        
        case 202:
        
        case 203:
        
        case 204:
        
        case 205:
        
        case 206:
        
        case 207:
        
        case 208:
        
        case 209:
        
        case 210:
        
        case 211:
        
        case 212:
        
        case 213:
        
        case 214:
        
        case 215:
        
        case 216:
        
        case 217:
        
        case 218:
        
        case 219:
        
        case 220:
        
        case 221:
        
        case 222:
        
        case 223:
        
        case 224:
        
        case 225:
        
        case 226:
        
        case 227:
        
        case 228:
        
        case 229:
        
        case 230:
        
        case 231:
        
        case 232:
        
        case 233:
        
        case 234:
        
        case 235:
        
        case 236:
        
        case 237:
        
        case 238:
        
        case 239:
        
        case 240:
        
        case 241:
        
        case 242:
        
        case 243:
        
        case 244:
        
        case 245:
        
        case 246:
        
        case 247:
        
        case 248:
        
        case 249:
        
        case 250:
        
        case 251:
        
        case 252:
        
        case 253:
        
        case 254:
        
        default:
          break;
      } 
      byte b1 = 75;
      int j = (paramInt2 & 0xFF) - b1;
      if (j < 0)
        j += 256; 
      int k = ((paramInt2 & 0xFFFF) >>> 8) - b1;
      if (k < 0)
        k += 256; 
      for (byte b2 = 0; b2 < arrayOfChar.length; b2++) {
        int m = b2 % 2;
        if (m == 0) {
          arrayOfChar[b2] = (char)(arrayOfChar[b2] ^ j);
          j = ((j >>> 3 | j << 5) ^ arrayOfChar[b2]) & 0xFF;
        } else {
          arrayOfChar[b2] = (char)(arrayOfChar[b2] ^ k);
          k = ((k >>> 3 | k << 5) ^ arrayOfChar[b2]) & 0xFF;
        } 
      } 
      b[i] = (new String(arrayOfChar)).intern();
    } 
    return b[i];
  }
}


/* Location:              C:\Program Files\BurpSuitePro\burpsuite_pro.jar!\burp\Zs_v.class
 * Java compiler version: 21 (65.0)
 * JD-Core Version:       1.1.3
 */