package burp;

import java.math.BigInteger;

class Zsbd extends ClassLoader {
  static Object Zh;
  
  static String ZA;
  
  private static final String[] a;
  
  private static final String[] b;
  
  static void ZV(Object[] paramArrayOfObject, Object paramObject) throws Throwable {}
  
  static boolean ZL(Object[] paramArrayOfObject, Object paramObject) throws Throwable {
    // Byte code:
    //   0: invokestatic ZK : ()Z
    //   3: istore_2
    //   4: getstatic burp/Zkff.Zr : Ljava/lang/Object;
    //   7: checkcast java/math/BigInteger
    //   10: getstatic burp/Zsk4.Ze : Ljava/lang/Object;
    //   13: checkcast java/math/BigInteger
    //   16: invokevirtual subtract : (Ljava/math/BigInteger;)Ljava/math/BigInteger;
    //   19: putstatic burp/Zx_b.ZX : Ljava/lang/Object;
    //   22: new java/io/ByteArrayOutputStream
    //   25: dup
    //   26: invokespecial <init> : ()V
    //   29: astore_3
    //   30: getstatic burp/Zxof.Zs : Ljava/lang/String;
    //   33: astore #4
    //   35: iconst_0
    //   36: istore #5
    //   38: iload #5
    //   40: aload #4
    //   42: invokevirtual length : ()I
    //   45: if_icmpge -> 75
    //   48: aload_3
    //   49: aload #4
    //   51: iload #5
    //   53: iload #5
    //   55: iconst_2
    //   56: iadd
    //   57: invokevirtual substring : (II)Ljava/lang/String;
    //   60: bipush #16
    //   62: invokestatic parseInt : (Ljava/lang/String;I)I
    //   65: invokevirtual write : (I)V
    //   68: iinc #5, 2
    //   71: iload_2
    //   72: ifeq -> 38
    //   75: aload_3
    //   76: invokevirtual toByteArray : ()[B
    //   79: astore #5
    //   81: getstatic burp/Ztzw.Zk : Ljava/lang/Object;
    //   84: checkcast java/math/BigInteger
    //   87: invokevirtual toByteArray : ()[B
    //   90: astore #6
    //   92: sipush #256
    //   95: newarray byte
    //   97: astore #8
    //   99: sipush #256
    //   102: newarray int
    //   104: astore #9
    //   106: sipush #256
    //   109: newarray int
    //   111: astore #10
    //   113: sipush #256
    //   116: newarray int
    //   118: astore #11
    //   120: sipush #256
    //   123: newarray int
    //   125: astore #12
    //   127: bipush #10
    //   129: newarray int
    //   131: astore #13
    //   133: sipush #283
    //   136: istore #14
    //   138: iconst_0
    //   139: istore #16
    //   141: iload #16
    //   143: sipush #256
    //   146: if_icmpge -> 380
    //   149: sipush #-17771
    //   152: sipush #-24900
    //   155: invokestatic a : (II)Ljava/lang/String;
    //   158: iload #16
    //   160: iconst_1
    //   161: iushr
    //   162: invokevirtual charAt : (I)C
    //   165: istore #25
    //   167: iload #16
    //   169: iconst_1
    //   170: iand
    //   171: ifne -> 186
    //   174: iload #25
    //   176: bipush #8
    //   178: iushr
    //   179: goto -> 188
    //   182: invokestatic a : (Ljava/lang/Throwable;)Ljava/lang/Throwable;
    //   185: athrow
    //   186: iload #25
    //   188: i2b
    //   189: sipush #255
    //   192: iand
    //   193: istore #15
    //   195: iload #16
    //   197: iconst_1
    //   198: ishl
    //   199: istore #17
    //   201: iload #17
    //   203: sipush #256
    //   206: if_icmplt -> 216
    //   209: iload #17
    //   211: iload #14
    //   213: ixor
    //   214: istore #17
    //   216: iload #17
    //   218: iconst_1
    //   219: ishl
    //   220: istore #18
    //   222: iload #18
    //   224: sipush #256
    //   227: if_icmplt -> 237
    //   230: iload #18
    //   232: iload #14
    //   234: ixor
    //   235: istore #18
    //   237: iload #18
    //   239: iconst_1
    //   240: ishl
    //   241: istore #19
    //   243: iload #19
    //   245: sipush #256
    //   248: if_icmplt -> 258
    //   251: iload #19
    //   253: iload #14
    //   255: ixor
    //   256: istore #19
    //   258: iload #19
    //   260: iload #16
    //   262: ixor
    //   263: istore #20
    //   265: iload #20
    //   267: iload #17
    //   269: ixor
    //   270: istore #21
    //   272: iload #20
    //   274: iload #18
    //   276: ixor
    //   277: istore #22
    //   279: iload #19
    //   281: iload #18
    //   283: ixor
    //   284: iload #17
    //   286: ixor
    //   287: istore #23
    //   289: aload #8
    //   291: iload #16
    //   293: iload #15
    //   295: i2b
    //   296: bastore
    //   297: aload #9
    //   299: iload #15
    //   301: iload #23
    //   303: bipush #24
    //   305: ishl
    //   306: iload #20
    //   308: bipush #16
    //   310: ishl
    //   311: ior
    //   312: iload #22
    //   314: bipush #8
    //   316: ishl
    //   317: ior
    //   318: iload #21
    //   320: ior
    //   321: dup
    //   322: istore #24
    //   324: iastore
    //   325: aload #10
    //   327: iload #15
    //   329: iload #24
    //   331: bipush #8
    //   333: iushr
    //   334: iload #24
    //   336: bipush #24
    //   338: ishl
    //   339: ior
    //   340: iastore
    //   341: aload #11
    //   343: iload #15
    //   345: iload #24
    //   347: bipush #16
    //   349: iushr
    //   350: iload #24
    //   352: bipush #16
    //   354: ishl
    //   355: ior
    //   356: iastore
    //   357: aload #12
    //   359: iload #15
    //   361: iload #24
    //   363: bipush #24
    //   365: iushr
    //   366: iload #24
    //   368: bipush #8
    //   370: ishl
    //   371: ior
    //   372: iastore
    //   373: iinc #16, 1
    //   376: iload_2
    //   377: ifeq -> 141
    //   380: iconst_1
    //   381: istore #25
    //   383: aload #13
    //   385: iconst_0
    //   386: iload #25
    //   388: bipush #24
    //   390: ishl
    //   391: iastore
    //   392: iconst_1
    //   393: istore #26
    //   395: iload #26
    //   397: bipush #10
    //   399: if_icmpge -> 440
    //   402: iload #25
    //   404: iconst_1
    //   405: ishl
    //   406: istore #25
    //   408: iload #25
    //   410: sipush #256
    //   413: if_icmplt -> 423
    //   416: iload #25
    //   418: iload #14
    //   420: ixor
    //   421: istore #25
    //   423: aload #13
    //   425: iload #26
    //   427: iload #25
    //   429: bipush #24
    //   431: ishl
    //   432: iastore
    //   433: iinc #26, 1
    //   436: iload_2
    //   437: ifeq -> 395
    //   440: iconst_4
    //   441: istore #26
    //   443: iload #26
    //   445: bipush #6
    //   447: iadd
    //   448: istore #27
    //   450: iconst_4
    //   451: iload #27
    //   453: iconst_1
    //   454: iadd
    //   455: imul
    //   456: istore #28
    //   458: iload #28
    //   460: newarray int
    //   462: astore #29
    //   464: iload #28
    //   466: newarray int
    //   468: astore #30
    //   470: iconst_0
    //   471: istore #25
    //   473: iconst_0
    //   474: istore #32
    //   476: iconst_0
    //   477: istore #33
    //   479: iload #32
    //   481: iload #26
    //   483: if_icmpge -> 551
    //   486: aload #29
    //   488: iload #32
    //   490: aload #5
    //   492: iload #33
    //   494: baload
    //   495: bipush #24
    //   497: ishl
    //   498: aload #5
    //   500: iload #33
    //   502: iconst_1
    //   503: iadd
    //   504: baload
    //   505: sipush #255
    //   508: iand
    //   509: bipush #16
    //   511: ishl
    //   512: ior
    //   513: aload #5
    //   515: iload #33
    //   517: iconst_2
    //   518: iadd
    //   519: baload
    //   520: sipush #255
    //   523: iand
    //   524: bipush #8
    //   526: ishl
    //   527: ior
    //   528: aload #5
    //   530: iload #33
    //   532: iconst_3
    //   533: iadd
    //   534: baload
    //   535: sipush #255
    //   538: iand
    //   539: ior
    //   540: iastore
    //   541: iinc #32, 1
    //   544: iinc #33, 4
    //   547: iload_2
    //   548: ifeq -> 479
    //   551: iload #26
    //   553: istore #32
    //   555: iconst_0
    //   556: istore #33
    //   558: iload #32
    //   560: iload #28
    //   562: if_icmpge -> 689
    //   565: aload #29
    //   567: iload #32
    //   569: iconst_1
    //   570: isub
    //   571: iaload
    //   572: istore #31
    //   574: iload #33
    //   576: ifne -> 663
    //   579: iload #26
    //   581: istore #33
    //   583: aload #8
    //   585: iload #31
    //   587: bipush #16
    //   589: iushr
    //   590: sipush #255
    //   593: iand
    //   594: baload
    //   595: bipush #24
    //   597: ishl
    //   598: aload #8
    //   600: iload #31
    //   602: bipush #8
    //   604: iushr
    //   605: sipush #255
    //   608: iand
    //   609: baload
    //   610: sipush #255
    //   613: iand
    //   614: bipush #16
    //   616: ishl
    //   617: ior
    //   618: aload #8
    //   620: iload #31
    //   622: sipush #255
    //   625: iand
    //   626: baload
    //   627: sipush #255
    //   630: iand
    //   631: bipush #8
    //   633: ishl
    //   634: ior
    //   635: aload #8
    //   637: iload #31
    //   639: bipush #24
    //   641: iushr
    //   642: baload
    //   643: sipush #255
    //   646: iand
    //   647: ior
    //   648: istore #31
    //   650: iload #31
    //   652: aload #13
    //   654: iload #25
    //   656: iinc #25, 1
    //   659: iaload
    //   660: ixor
    //   661: istore #31
    //   663: aload #29
    //   665: iload #32
    //   667: aload #29
    //   669: iload #32
    //   671: iload #26
    //   673: isub
    //   674: iaload
    //   675: iload #31
    //   677: ixor
    //   678: iastore
    //   679: iinc #32, 1
    //   682: iinc #33, -1
    //   685: iload_2
    //   686: ifeq -> 558
    //   689: iconst_0
    //   690: istore #32
    //   692: iconst_4
    //   693: iload #27
    //   695: imul
    //   696: istore #33
    //   698: aload #30
    //   700: iload #32
    //   702: aload #29
    //   704: iload #33
    //   706: iaload
    //   707: iastore
    //   708: aload #30
    //   710: iload #32
    //   712: iconst_1
    //   713: iadd
    //   714: aload #29
    //   716: iload #33
    //   718: iconst_1
    //   719: iadd
    //   720: iaload
    //   721: iastore
    //   722: aload #30
    //   724: iload #32
    //   726: iconst_2
    //   727: iadd
    //   728: aload #29
    //   730: iload #33
    //   732: iconst_2
    //   733: iadd
    //   734: iaload
    //   735: iastore
    //   736: aload #30
    //   738: iload #32
    //   740: iconst_3
    //   741: iadd
    //   742: aload #29
    //   744: iload #33
    //   746: iconst_3
    //   747: iadd
    //   748: iaload
    //   749: iastore
    //   750: iinc #32, 4
    //   753: iinc #33, -4
    //   756: iconst_1
    //   757: istore #35
    //   759: iload #35
    //   761: iload #27
    //   763: if_icmpge -> 1127
    //   766: aload #29
    //   768: iload #33
    //   770: iaload
    //   771: istore #34
    //   773: aload #30
    //   775: iload #32
    //   777: aload #9
    //   779: aload #8
    //   781: iload #34
    //   783: bipush #24
    //   785: iushr
    //   786: baload
    //   787: sipush #255
    //   790: iand
    //   791: iaload
    //   792: aload #10
    //   794: aload #8
    //   796: iload #34
    //   798: bipush #16
    //   800: iushr
    //   801: sipush #255
    //   804: iand
    //   805: baload
    //   806: sipush #255
    //   809: iand
    //   810: iaload
    //   811: ixor
    //   812: aload #11
    //   814: aload #8
    //   816: iload #34
    //   818: bipush #8
    //   820: iushr
    //   821: sipush #255
    //   824: iand
    //   825: baload
    //   826: sipush #255
    //   829: iand
    //   830: iaload
    //   831: ixor
    //   832: aload #12
    //   834: aload #8
    //   836: iload #34
    //   838: sipush #255
    //   841: iand
    //   842: baload
    //   843: sipush #255
    //   846: iand
    //   847: iaload
    //   848: ixor
    //   849: iastore
    //   850: aload #29
    //   852: iload #33
    //   854: iconst_1
    //   855: iadd
    //   856: iaload
    //   857: istore #34
    //   859: aload #30
    //   861: iload #32
    //   863: iconst_1
    //   864: iadd
    //   865: aload #9
    //   867: aload #8
    //   869: iload #34
    //   871: bipush #24
    //   873: iushr
    //   874: baload
    //   875: sipush #255
    //   878: iand
    //   879: iaload
    //   880: aload #10
    //   882: aload #8
    //   884: iload #34
    //   886: bipush #16
    //   888: iushr
    //   889: sipush #255
    //   892: iand
    //   893: baload
    //   894: sipush #255
    //   897: iand
    //   898: iaload
    //   899: ixor
    //   900: aload #11
    //   902: aload #8
    //   904: iload #34
    //   906: bipush #8
    //   908: iushr
    //   909: sipush #255
    //   912: iand
    //   913: baload
    //   914: sipush #255
    //   917: iand
    //   918: iaload
    //   919: ixor
    //   920: aload #12
    //   922: aload #8
    //   924: iload #34
    //   926: sipush #255
    //   929: iand
    //   930: baload
    //   931: sipush #255
    //   934: iand
    //   935: iaload
    //   936: ixor
    //   937: iastore
    //   938: aload #29
    //   940: iload #33
    //   942: iconst_2
    //   943: iadd
    //   944: iaload
    //   945: istore #34
    //   947: aload #30
    //   949: iload #32
    //   951: iconst_2
    //   952: iadd
    //   953: aload #9
    //   955: aload #8
    //   957: iload #34
    //   959: bipush #24
    //   961: iushr
    //   962: baload
    //   963: sipush #255
    //   966: iand
    //   967: iaload
    //   968: aload #10
    //   970: aload #8
    //   972: iload #34
    //   974: bipush #16
    //   976: iushr
    //   977: sipush #255
    //   980: iand
    //   981: baload
    //   982: sipush #255
    //   985: iand
    //   986: iaload
    //   987: ixor
    //   988: aload #11
    //   990: aload #8
    //   992: iload #34
    //   994: bipush #8
    //   996: iushr
    //   997: sipush #255
    //   1000: iand
    //   1001: baload
    //   1002: sipush #255
    //   1005: iand
    //   1006: iaload
    //   1007: ixor
    //   1008: aload #12
    //   1010: aload #8
    //   1012: iload #34
    //   1014: sipush #255
    //   1017: iand
    //   1018: baload
    //   1019: sipush #255
    //   1022: iand
    //   1023: iaload
    //   1024: ixor
    //   1025: iastore
    //   1026: aload #29
    //   1028: iload #33
    //   1030: iconst_3
    //   1031: iadd
    //   1032: iaload
    //   1033: istore #34
    //   1035: aload #30
    //   1037: iload #32
    //   1039: iconst_3
    //   1040: iadd
    //   1041: aload #9
    //   1043: aload #8
    //   1045: iload #34
    //   1047: bipush #24
    //   1049: iushr
    //   1050: baload
    //   1051: sipush #255
    //   1054: iand
    //   1055: iaload
    //   1056: aload #10
    //   1058: aload #8
    //   1060: iload #34
    //   1062: bipush #16
    //   1064: iushr
    //   1065: sipush #255
    //   1068: iand
    //   1069: baload
    //   1070: sipush #255
    //   1073: iand
    //   1074: iaload
    //   1075: ixor
    //   1076: aload #11
    //   1078: aload #8
    //   1080: iload #34
    //   1082: bipush #8
    //   1084: iushr
    //   1085: sipush #255
    //   1088: iand
    //   1089: baload
    //   1090: sipush #255
    //   1093: iand
    //   1094: iaload
    //   1095: ixor
    //   1096: aload #12
    //   1098: aload #8
    //   1100: iload #34
    //   1102: sipush #255
    //   1105: iand
    //   1106: baload
    //   1107: sipush #255
    //   1110: iand
    //   1111: iaload
    //   1112: ixor
    //   1113: iastore
    //   1114: iinc #32, 4
    //   1117: iinc #33, -4
    //   1120: iinc #35, 1
    //   1123: iload_2
    //   1124: ifeq -> 759
    //   1127: aload #30
    //   1129: iload #32
    //   1131: aload #29
    //   1133: iload #33
    //   1135: iaload
    //   1136: iastore
    //   1137: aload #30
    //   1139: iload #32
    //   1141: iconst_1
    //   1142: iadd
    //   1143: aload #29
    //   1145: iload #33
    //   1147: iconst_1
    //   1148: iadd
    //   1149: iaload
    //   1150: iastore
    //   1151: aload #30
    //   1153: iload #32
    //   1155: iconst_2
    //   1156: iadd
    //   1157: aload #29
    //   1159: iload #33
    //   1161: iconst_2
    //   1162: iadd
    //   1163: iaload
    //   1164: iastore
    //   1165: aload #30
    //   1167: iload #32
    //   1169: iconst_3
    //   1170: iadd
    //   1171: aload #29
    //   1173: iload #33
    //   1175: iconst_3
    //   1176: iadd
    //   1177: iaload
    //   1178: iastore
    //   1179: iconst_0
    //   1180: newarray byte
    //   1182: astore #35
    //   1184: aload #6
    //   1186: arraylength
    //   1187: bipush #16
    //   1189: irem
    //   1190: ifeq -> 1214
    //   1193: new java/lang/Exception
    //   1196: dup
    //   1197: sipush #-17786
    //   1200: sipush #-7317
    //   1203: invokestatic a : (II)Ljava/lang/String;
    //   1206: invokespecial <init> : (Ljava/lang/String;)V
    //   1209: athrow
    //   1210: invokestatic a : (Ljava/lang/Throwable;)Ljava/lang/Throwable;
    //   1213: athrow
    //   1214: bipush #10
    //   1216: istore #36
    //   1218: sipush #-17787
    //   1221: sipush #256
    //   1224: newarray byte
    //   1226: astore #37
    //   1228: sipush #-18736
    //   1231: sipush #256
    //   1234: newarray int
    //   1236: astore #38
    //   1238: sipush #256
    //   1241: newarray int
    //   1243: astore #39
    //   1245: sipush #256
    //   1248: newarray int
    //   1250: astore #40
    //   1252: sipush #256
    //   1255: newarray int
    //   1257: astore #41
    //   1259: sipush #283
    //   1262: istore #14
    //   1264: invokestatic a : (II)Ljava/lang/String;
    //   1267: astore #42
    //   1269: iconst_0
    //   1270: istore #16
    //   1272: iload #16
    //   1274: sipush #256
    //   1277: if_icmpge -> 1504
    //   1280: aload #42
    //   1282: iload #16
    //   1284: iconst_1
    //   1285: iushr
    //   1286: invokevirtual charAt : (I)C
    //   1289: istore #43
    //   1291: iload #16
    //   1293: iconst_1
    //   1294: iand
    //   1295: ifne -> 1310
    //   1298: iload #43
    //   1300: bipush #8
    //   1302: iushr
    //   1303: goto -> 1312
    //   1306: invokestatic a : (Ljava/lang/Throwable;)Ljava/lang/Throwable;
    //   1309: athrow
    //   1310: iload #43
    //   1312: i2b
    //   1313: sipush #255
    //   1316: iand
    //   1317: istore #15
    //   1319: iload #16
    //   1321: iconst_1
    //   1322: ishl
    //   1323: istore #17
    //   1325: iload #17
    //   1327: sipush #256
    //   1330: if_icmplt -> 1340
    //   1333: iload #17
    //   1335: iload #14
    //   1337: ixor
    //   1338: istore #17
    //   1340: iload #17
    //   1342: iconst_1
    //   1343: ishl
    //   1344: istore #18
    //   1346: iload #18
    //   1348: sipush #256
    //   1351: if_icmplt -> 1361
    //   1354: iload #18
    //   1356: iload #14
    //   1358: ixor
    //   1359: istore #18
    //   1361: iload #18
    //   1363: iconst_1
    //   1364: ishl
    //   1365: istore #19
    //   1367: iload #19
    //   1369: sipush #256
    //   1372: if_icmplt -> 1382
    //   1375: iload #19
    //   1377: iload #14
    //   1379: ixor
    //   1380: istore #19
    //   1382: iload #19
    //   1384: iload #16
    //   1386: ixor
    //   1387: istore #20
    //   1389: iload #20
    //   1391: iload #17
    //   1393: ixor
    //   1394: istore #21
    //   1396: iload #20
    //   1398: iload #18
    //   1400: ixor
    //   1401: istore #22
    //   1403: iload #19
    //   1405: iload #18
    //   1407: ixor
    //   1408: iload #17
    //   1410: ixor
    //   1411: istore #23
    //   1413: aload #37
    //   1415: iload #15
    //   1417: iload #16
    //   1419: i2b
    //   1420: bastore
    //   1421: aload #38
    //   1423: iload #15
    //   1425: iload #23
    //   1427: bipush #24
    //   1429: ishl
    //   1430: iload #20
    //   1432: bipush #16
    //   1434: ishl
    //   1435: ior
    //   1436: iload #22
    //   1438: bipush #8
    //   1440: ishl
    //   1441: ior
    //   1442: iload #21
    //   1444: ior
    //   1445: dup
    //   1446: istore #24
    //   1448: iastore
    //   1449: aload #39
    //   1451: iload #15
    //   1453: iload #24
    //   1455: bipush #8
    //   1457: iushr
    //   1458: iload #24
    //   1460: bipush #24
    //   1462: ishl
    //   1463: ior
    //   1464: iastore
    //   1465: aload #40
    //   1467: iload #15
    //   1469: iload #24
    //   1471: bipush #16
    //   1473: iushr
    //   1474: iload #24
    //   1476: bipush #16
    //   1478: ishl
    //   1479: ior
    //   1480: iastore
    //   1481: aload #41
    //   1483: iload #15
    //   1485: iload #24
    //   1487: bipush #24
    //   1489: iushr
    //   1490: iload #24
    //   1492: bipush #8
    //   1494: ishl
    //   1495: ior
    //   1496: iastore
    //   1497: iinc #16, 1
    //   1500: iload_2
    //   1501: ifeq -> 1272
    //   1504: aload #6
    //   1506: arraylength
    //   1507: newarray byte
    //   1509: astore #43
    //   1511: iconst_0
    //   1512: istore #44
    //   1514: iload #44
    //   1516: aload #6
    //   1518: arraylength
    //   1519: bipush #16
    //   1521: idiv
    //   1522: if_icmpge -> 2436
    //   1525: bipush #16
    //   1527: newarray byte
    //   1529: astore #45
    //   1531: bipush #16
    //   1533: newarray byte
    //   1535: astore #46
    //   1537: iconst_0
    //   1538: istore #47
    //   1540: iload #47
    //   1542: bipush #16
    //   1544: if_icmpge -> 1570
    //   1547: aload #45
    //   1549: iload #47
    //   1551: aload #6
    //   1553: iload #47
    //   1555: iload #44
    //   1557: bipush #16
    //   1559: imul
    //   1560: iadd
    //   1561: baload
    //   1562: bastore
    //   1563: iinc #47, 1
    //   1566: iload_2
    //   1567: ifeq -> 1540
    //   1570: iconst_0
    //   1571: istore #47
    //   1573: aload #45
    //   1575: iconst_0
    //   1576: baload
    //   1577: bipush #24
    //   1579: ishl
    //   1580: aload #45
    //   1582: iconst_1
    //   1583: baload
    //   1584: sipush #255
    //   1587: iand
    //   1588: bipush #16
    //   1590: ishl
    //   1591: ior
    //   1592: aload #45
    //   1594: iconst_2
    //   1595: baload
    //   1596: sipush #255
    //   1599: iand
    //   1600: bipush #8
    //   1602: ishl
    //   1603: ior
    //   1604: aload #45
    //   1606: iconst_3
    //   1607: baload
    //   1608: sipush #255
    //   1611: iand
    //   1612: ior
    //   1613: aload #30
    //   1615: iconst_0
    //   1616: iaload
    //   1617: ixor
    //   1618: istore #49
    //   1620: aload #45
    //   1622: iconst_4
    //   1623: baload
    //   1624: bipush #24
    //   1626: ishl
    //   1627: aload #45
    //   1629: iconst_5
    //   1630: baload
    //   1631: sipush #255
    //   1634: iand
    //   1635: bipush #16
    //   1637: ishl
    //   1638: ior
    //   1639: aload #45
    //   1641: bipush #6
    //   1643: baload
    //   1644: sipush #255
    //   1647: iand
    //   1648: bipush #8
    //   1650: ishl
    //   1651: ior
    //   1652: aload #45
    //   1654: bipush #7
    //   1656: baload
    //   1657: sipush #255
    //   1660: iand
    //   1661: ior
    //   1662: aload #30
    //   1664: iconst_1
    //   1665: iaload
    //   1666: ixor
    //   1667: istore #50
    //   1669: aload #45
    //   1671: bipush #8
    //   1673: baload
    //   1674: bipush #24
    //   1676: ishl
    //   1677: aload #45
    //   1679: bipush #9
    //   1681: baload
    //   1682: sipush #255
    //   1685: iand
    //   1686: bipush #16
    //   1688: ishl
    //   1689: ior
    //   1690: aload #45
    //   1692: bipush #10
    //   1694: baload
    //   1695: sipush #255
    //   1698: iand
    //   1699: bipush #8
    //   1701: ishl
    //   1702: ior
    //   1703: aload #45
    //   1705: bipush #11
    //   1707: baload
    //   1708: sipush #255
    //   1711: iand
    //   1712: ior
    //   1713: aload #30
    //   1715: iconst_2
    //   1716: iaload
    //   1717: ixor
    //   1718: istore #51
    //   1720: aload #45
    //   1722: bipush #12
    //   1724: baload
    //   1725: bipush #24
    //   1727: ishl
    //   1728: aload #45
    //   1730: bipush #13
    //   1732: baload
    //   1733: sipush #255
    //   1736: iand
    //   1737: bipush #16
    //   1739: ishl
    //   1740: ior
    //   1741: aload #45
    //   1743: bipush #14
    //   1745: baload
    //   1746: sipush #255
    //   1749: iand
    //   1750: bipush #8
    //   1752: ishl
    //   1753: ior
    //   1754: aload #45
    //   1756: bipush #15
    //   1758: baload
    //   1759: sipush #255
    //   1762: iand
    //   1763: ior
    //   1764: aload #30
    //   1766: iconst_3
    //   1767: iaload
    //   1768: ixor
    //   1769: istore #52
    //   1771: iconst_1
    //   1772: istore #53
    //   1774: iload #53
    //   1776: iload #36
    //   1778: if_icmpge -> 2021
    //   1781: iinc #47, 4
    //   1784: aload #38
    //   1786: iload #49
    //   1788: bipush #24
    //   1790: iushr
    //   1791: iaload
    //   1792: aload #39
    //   1794: iload #52
    //   1796: bipush #16
    //   1798: iushr
    //   1799: sipush #255
    //   1802: iand
    //   1803: iaload
    //   1804: ixor
    //   1805: aload #40
    //   1807: iload #51
    //   1809: bipush #8
    //   1811: iushr
    //   1812: sipush #255
    //   1815: iand
    //   1816: iaload
    //   1817: ixor
    //   1818: aload #41
    //   1820: iload #50
    //   1822: sipush #255
    //   1825: iand
    //   1826: iaload
    //   1827: ixor
    //   1828: aload #30
    //   1830: iload #47
    //   1832: iaload
    //   1833: ixor
    //   1834: istore #54
    //   1836: aload #38
    //   1838: iload #50
    //   1840: bipush #24
    //   1842: iushr
    //   1843: iaload
    //   1844: aload #39
    //   1846: iload #49
    //   1848: bipush #16
    //   1850: iushr
    //   1851: sipush #255
    //   1854: iand
    //   1855: iaload
    //   1856: ixor
    //   1857: aload #40
    //   1859: iload #52
    //   1861: bipush #8
    //   1863: iushr
    //   1864: sipush #255
    //   1867: iand
    //   1868: iaload
    //   1869: ixor
    //   1870: aload #41
    //   1872: iload #51
    //   1874: sipush #255
    //   1877: iand
    //   1878: iaload
    //   1879: ixor
    //   1880: aload #30
    //   1882: iload #47
    //   1884: iconst_1
    //   1885: iadd
    //   1886: iaload
    //   1887: ixor
    //   1888: istore #55
    //   1890: aload #38
    //   1892: iload #51
    //   1894: bipush #24
    //   1896: iushr
    //   1897: iaload
    //   1898: aload #39
    //   1900: iload #50
    //   1902: bipush #16
    //   1904: iushr
    //   1905: sipush #255
    //   1908: iand
    //   1909: iaload
    //   1910: ixor
    //   1911: aload #40
    //   1913: iload #49
    //   1915: bipush #8
    //   1917: iushr
    //   1918: sipush #255
    //   1921: iand
    //   1922: iaload
    //   1923: ixor
    //   1924: aload #41
    //   1926: iload #52
    //   1928: sipush #255
    //   1931: iand
    //   1932: iaload
    //   1933: ixor
    //   1934: aload #30
    //   1936: iload #47
    //   1938: iconst_2
    //   1939: iadd
    //   1940: iaload
    //   1941: ixor
    //   1942: istore #56
    //   1944: aload #38
    //   1946: iload #52
    //   1948: bipush #24
    //   1950: iushr
    //   1951: iaload
    //   1952: aload #39
    //   1954: iload #51
    //   1956: bipush #16
    //   1958: iushr
    //   1959: sipush #255
    //   1962: iand
    //   1963: iaload
    //   1964: ixor
    //   1965: aload #40
    //   1967: iload #50
    //   1969: bipush #8
    //   1971: iushr
    //   1972: sipush #255
    //   1975: iand
    //   1976: iaload
    //   1977: ixor
    //   1978: aload #41
    //   1980: iload #49
    //   1982: sipush #255
    //   1985: iand
    //   1986: iaload
    //   1987: ixor
    //   1988: aload #30
    //   1990: iload #47
    //   1992: iconst_3
    //   1993: iadd
    //   1994: iaload
    //   1995: ixor
    //   1996: istore #57
    //   1998: iload #54
    //   2000: istore #49
    //   2002: iload #55
    //   2004: istore #50
    //   2006: iload #56
    //   2008: istore #51
    //   2010: iload #57
    //   2012: istore #52
    //   2014: iinc #53, 1
    //   2017: iload_2
    //   2018: ifeq -> 1774
    //   2021: iinc #47, 4
    //   2024: aload #30
    //   2026: iload #47
    //   2028: iaload
    //   2029: istore #48
    //   2031: aload #46
    //   2033: iconst_0
    //   2034: aload #37
    //   2036: iload #49
    //   2038: bipush #24
    //   2040: iushr
    //   2041: baload
    //   2042: iload #48
    //   2044: bipush #24
    //   2046: iushr
    //   2047: ixor
    //   2048: i2b
    //   2049: bastore
    //   2050: aload #46
    //   2052: iconst_1
    //   2053: aload #37
    //   2055: iload #52
    //   2057: bipush #16
    //   2059: iushr
    //   2060: sipush #255
    //   2063: iand
    //   2064: baload
    //   2065: iload #48
    //   2067: bipush #16
    //   2069: iushr
    //   2070: ixor
    //   2071: i2b
    //   2072: bastore
    //   2073: aload #46
    //   2075: iconst_2
    //   2076: aload #37
    //   2078: iload #51
    //   2080: bipush #8
    //   2082: iushr
    //   2083: sipush #255
    //   2086: iand
    //   2087: baload
    //   2088: iload #48
    //   2090: bipush #8
    //   2092: iushr
    //   2093: ixor
    //   2094: i2b
    //   2095: bastore
    //   2096: aload #46
    //   2098: iconst_3
    //   2099: aload #37
    //   2101: iload #50
    //   2103: sipush #255
    //   2106: iand
    //   2107: baload
    //   2108: iload #48
    //   2110: ixor
    //   2111: i2b
    //   2112: bastore
    //   2113: aload #30
    //   2115: iload #47
    //   2117: iconst_1
    //   2118: iadd
    //   2119: iaload
    //   2120: istore #48
    //   2122: aload #46
    //   2124: iconst_4
    //   2125: aload #37
    //   2127: iload #50
    //   2129: bipush #24
    //   2131: iushr
    //   2132: baload
    //   2133: iload #48
    //   2135: bipush #24
    //   2137: iushr
    //   2138: ixor
    //   2139: i2b
    //   2140: bastore
    //   2141: aload #46
    //   2143: iconst_5
    //   2144: aload #37
    //   2146: iload #49
    //   2148: bipush #16
    //   2150: iushr
    //   2151: sipush #255
    //   2154: iand
    //   2155: baload
    //   2156: iload #48
    //   2158: bipush #16
    //   2160: iushr
    //   2161: ixor
    //   2162: i2b
    //   2163: bastore
    //   2164: aload #46
    //   2166: bipush #6
    //   2168: aload #37
    //   2170: iload #52
    //   2172: bipush #8
    //   2174: iushr
    //   2175: sipush #255
    //   2178: iand
    //   2179: baload
    //   2180: iload #48
    //   2182: bipush #8
    //   2184: iushr
    //   2185: ixor
    //   2186: i2b
    //   2187: bastore
    //   2188: aload #46
    //   2190: bipush #7
    //   2192: aload #37
    //   2194: iload #51
    //   2196: sipush #255
    //   2199: iand
    //   2200: baload
    //   2201: iload #48
    //   2203: ixor
    //   2204: i2b
    //   2205: bastore
    //   2206: aload #30
    //   2208: iload #47
    //   2210: iconst_2
    //   2211: iadd
    //   2212: iaload
    //   2213: istore #48
    //   2215: aload #46
    //   2217: bipush #8
    //   2219: aload #37
    //   2221: iload #51
    //   2223: bipush #24
    //   2225: iushr
    //   2226: baload
    //   2227: iload #48
    //   2229: bipush #24
    //   2231: iushr
    //   2232: ixor
    //   2233: i2b
    //   2234: bastore
    //   2235: aload #46
    //   2237: bipush #9
    //   2239: aload #37
    //   2241: iload #50
    //   2243: bipush #16
    //   2245: iushr
    //   2246: sipush #255
    //   2249: iand
    //   2250: baload
    //   2251: iload #48
    //   2253: bipush #16
    //   2255: iushr
    //   2256: ixor
    //   2257: i2b
    //   2258: bastore
    //   2259: aload #46
    //   2261: bipush #10
    //   2263: aload #37
    //   2265: iload #49
    //   2267: bipush #8
    //   2269: iushr
    //   2270: sipush #255
    //   2273: iand
    //   2274: baload
    //   2275: iload #48
    //   2277: bipush #8
    //   2279: iushr
    //   2280: ixor
    //   2281: i2b
    //   2282: bastore
    //   2283: aload #46
    //   2285: bipush #11
    //   2287: aload #37
    //   2289: iload #52
    //   2291: sipush #255
    //   2294: iand
    //   2295: baload
    //   2296: iload #48
    //   2298: ixor
    //   2299: i2b
    //   2300: bastore
    //   2301: aload #30
    //   2303: iload #47
    //   2305: iconst_3
    //   2306: iadd
    //   2307: iaload
    //   2308: istore #48
    //   2310: aload #46
    //   2312: bipush #12
    //   2314: aload #37
    //   2316: iload #52
    //   2318: bipush #24
    //   2320: iushr
    //   2321: baload
    //   2322: iload #48
    //   2324: bipush #24
    //   2326: iushr
    //   2327: ixor
    //   2328: i2b
    //   2329: bastore
    //   2330: aload #46
    //   2332: bipush #13
    //   2334: aload #37
    //   2336: iload #51
    //   2338: bipush #16
    //   2340: iushr
    //   2341: sipush #255
    //   2344: iand
    //   2345: baload
    //   2346: iload #48
    //   2348: bipush #16
    //   2350: iushr
    //   2351: ixor
    //   2352: i2b
    //   2353: bastore
    //   2354: aload #46
    //   2356: bipush #14
    //   2358: aload #37
    //   2360: iload #50
    //   2362: bipush #8
    //   2364: iushr
    //   2365: sipush #255
    //   2368: iand
    //   2369: baload
    //   2370: iload #48
    //   2372: bipush #8
    //   2374: iushr
    //   2375: ixor
    //   2376: i2b
    //   2377: bastore
    //   2378: aload #46
    //   2380: bipush #15
    //   2382: aload #37
    //   2384: iload #49
    //   2386: sipush #255
    //   2389: iand
    //   2390: baload
    //   2391: iload #48
    //   2393: ixor
    //   2394: i2b
    //   2395: bastore
    //   2396: iconst_0
    //   2397: istore #53
    //   2399: iload #53
    //   2401: bipush #16
    //   2403: if_icmpge -> 2429
    //   2406: aload #43
    //   2408: iload #53
    //   2410: iload #44
    //   2412: bipush #16
    //   2414: imul
    //   2415: iadd
    //   2416: aload #46
    //   2418: iload #53
    //   2420: baload
    //   2421: bastore
    //   2422: iinc #53, 1
    //   2425: iload_2
    //   2426: ifeq -> 2399
    //   2429: iinc #44, 1
    //   2432: iload_2
    //   2433: ifeq -> 1514
    //   2436: aload #43
    //   2438: arraylength
    //   2439: ifle -> 2520
    //   2442: aload #43
    //   2444: aload #43
    //   2446: arraylength
    //   2447: iconst_1
    //   2448: isub
    //   2449: baload
    //   2450: istore #44
    //   2452: iload #44
    //   2454: bipush #16
    //   2456: if_icmple -> 2467
    //   2459: aload #43
    //   2461: astore #35
    //   2463: iload_2
    //   2464: ifeq -> 2520
    //   2467: aload #43
    //   2469: arraylength
    //   2470: iload #44
    //   2472: isub
    //   2473: newarray byte
    //   2475: astore #35
    //   2477: iconst_0
    //   2478: istore #45
    //   2480: iload #45
    //   2482: aload #35
    //   2484: arraylength
    //   2485: if_icmpge -> 2520
    //   2488: iload #45
    //   2490: aload #43
    //   2492: arraylength
    //   2493: if_icmpge -> 2520
    //   2496: aload #35
    //   2498: iload #45
    //   2500: aload #43
    //   2502: iload #45
    //   2504: baload
    //   2505: bastore
    //   2506: iinc #45, 1
    //   2509: iload_2
    //   2510: ifeq -> 2480
    //   2513: goto -> 2520
    //   2516: invokestatic a : (Ljava/lang/Throwable;)Ljava/lang/Throwable;
    //   2519: athrow
    //   2520: aload #35
    //   2522: astore #7
    //   2524: sipush #-17790
    //   2527: new java/math/BigInteger
    //   2530: dup
    //   2531: aload #7
    //   2533: invokespecial <init> : ([B)V
    //   2536: invokevirtual abs : ()Ljava/math/BigInteger;
    //   2539: putstatic burp/Zx_b.ZX : Ljava/lang/Object;
    //   2542: sipush #-12927
    //   2545: getstatic burp/Zcc.Zd : Ljava/lang/Object;
    //   2548: checkcast java/math/BigInteger
    //   2551: getstatic burp/Zex5.Zb : Ljava/lang/Object;
    //   2554: checkcast java/math/BigInteger
    //   2557: invokevirtual subtract : (Ljava/math/BigInteger;)Ljava/math/BigInteger;
    //   2560: putstatic burp/Zt7w.ZF : Ljava/lang/Object;
    //   2563: invokestatic a : (II)Ljava/lang/String;
    //   2566: iconst_1
    //   2567: ldc burp/Zxzv
    //   2569: invokevirtual getClassLoader : ()Ljava/lang/ClassLoader;
    //   2572: invokestatic forName : (Ljava/lang/String;ZLjava/lang/ClassLoader;)Ljava/lang/Class;
    //   2575: invokevirtual getDeclaredFields : ()[Ljava/lang/reflect/Field;
    //   2578: astore_3
    //   2579: aload_3
    //   2580: arraylength
    //   2581: istore #4
    //   2583: iconst_0
    //   2584: istore #5
    //   2586: iload #5
    //   2588: iload #4
    //   2590: if_icmpge -> 2727
    //   2593: aload_3
    //   2594: iload #5
    //   2596: aaload
    //   2597: astore #6
    //   2599: aload #6
    //   2601: invokevirtual getModifiers : ()I
    //   2604: invokestatic isStatic : (I)Z
    //   2607: ifne -> 2617
    //   2610: goto -> 2720
    //   2613: invokestatic a : (Ljava/lang/Throwable;)Ljava/lang/Throwable;
    //   2616: athrow
    //   2617: aload #6
    //   2619: invokevirtual getType : ()Ljava/lang/Class;
    //   2622: astore #7
    //   2624: aload #7
    //   2626: ifnull -> 2707
    //   2629: aload #7
    //   2631: invokevirtual isPrimitive : ()Z
    //   2634: ifne -> 2707
    //   2637: goto -> 2644
    //   2640: invokestatic a : (Ljava/lang/Throwable;)Ljava/lang/Throwable;
    //   2643: athrow
    //   2644: aload #7
    //   2646: invokevirtual getPackage : ()Ljava/lang/Package;
    //   2649: ifnull -> 2707
    //   2652: goto -> 2659
    //   2655: invokestatic a : (Ljava/lang/Throwable;)Ljava/lang/Throwable;
    //   2658: athrow
    //   2659: aload #7
    //   2661: invokevirtual getPackage : ()Ljava/lang/Package;
    //   2664: invokevirtual getName : ()Ljava/lang/String;
    //   2667: ifnull -> 2707
    //   2670: goto -> 2677
    //   2673: invokestatic a : (Ljava/lang/Throwable;)Ljava/lang/Throwable;
    //   2676: athrow
    //   2677: aload #7
    //   2679: invokevirtual getPackage : ()Ljava/lang/Package;
    //   2682: invokevirtual getName : ()Ljava/lang/String;
    //   2685: sipush #-17779
    //   2688: sipush #917
    //   2691: invokestatic a : (II)Ljava/lang/String;
    //   2694: invokevirtual startsWith : (Ljava/lang/String;)Z
    //   2697: ifne -> 2707
    //   2700: goto -> 2707
    //   2703: invokestatic a : (Ljava/lang/Throwable;)Ljava/lang/Throwable;
    //   2706: athrow
    //   2707: aload #6
    //   2709: iconst_1
    //   2710: invokevirtual setAccessible : (Z)V
    //   2713: aload #6
    //   2715: aconst_null
    //   2716: invokevirtual get : (Ljava/lang/Object;)Ljava/lang/Object;
    //   2719: pop
    //   2720: iinc #5, 1
    //   2723: iload_2
    //   2724: ifeq -> 2586
    //   2727: sipush #-17775
    //   2730: sipush #13269
    //   2733: invokestatic a : (II)Ljava/lang/String;
    //   2736: invokestatic forName : (Ljava/lang/String;)Ljava/lang/Class;
    //   2739: invokevirtual getDeclaredMethods : ()[Ljava/lang/reflect/Method;
    //   2742: astore_3
    //   2743: aload_3
    //   2744: arraylength
    //   2745: istore #4
    //   2747: iconst_0
    //   2748: istore #5
    //   2750: iload #5
    //   2752: iload #4
    //   2754: if_icmpge -> 2886
    //   2757: aload_3
    //   2758: iload #5
    //   2760: aaload
    //   2761: astore #6
    //   2763: aload #6
    //   2765: invokevirtual getParameterTypes : ()[Ljava/lang/Class;
    //   2768: pop
    //   2769: aload #6
    //   2771: invokevirtual getModifiers : ()I
    //   2774: invokestatic isStatic : (I)Z
    //   2777: ifeq -> 2872
    //   2780: aload #6
    //   2782: invokevirtual getParameterTypes : ()[Ljava/lang/Class;
    //   2785: arraylength
    //   2786: iconst_2
    //   2787: if_icmpne -> 2872
    //   2790: goto -> 2797
    //   2793: invokestatic a : (Ljava/lang/Throwable;)Ljava/lang/Throwable;
    //   2796: athrow
    //   2797: aload #6
    //   2799: invokevirtual getReturnType : ()Ljava/lang/Class;
    //   2802: getstatic java/lang/Void.TYPE : Ljava/lang/Class;
    //   2805: invokevirtual equals : (Ljava/lang/Object;)Z
    //   2808: ifeq -> 2872
    //   2811: goto -> 2818
    //   2814: invokestatic a : (Ljava/lang/Throwable;)Ljava/lang/Throwable;
    //   2817: athrow
    //   2818: aload #6
    //   2820: iconst_1
    //   2821: invokevirtual setAccessible : (Z)V
    //   2824: aload #6
    //   2826: aconst_null
    //   2827: iconst_2
    //   2828: anewarray java/lang/Object
    //   2831: dup
    //   2832: iconst_0
    //   2833: aload_0
    //   2834: aastore
    //   2835: dup
    //   2836: iconst_1
    //   2837: aload_1
    //   2838: ifnonnull -> 2856
    //   2841: goto -> 2848
    //   2844: invokestatic a : (Ljava/lang/Throwable;)Ljava/lang/Throwable;
    //   2847: athrow
    //   2848: aload_1
    //   2849: goto -> 2863
    //   2852: invokestatic a : (Ljava/lang/Throwable;)Ljava/lang/Throwable;
    //   2855: athrow
    //   2856: aload_1
    //   2857: checkcast [B
    //   2860: invokevirtual clone : ()Ljava/lang/Object;
    //   2863: aastore
    //   2864: invokevirtual invoke : (Ljava/lang/Object;[Ljava/lang/Object;)Ljava/lang/Object;
    //   2867: pop
    //   2868: iload_2
    //   2869: ifeq -> 2886
    //   2872: iinc #5, 1
    //   2875: iload_2
    //   2876: ifeq -> 2750
    //   2879: goto -> 2886
    //   2882: invokestatic a : (Ljava/lang/Throwable;)Ljava/lang/Throwable;
    //   2885: athrow
    //   2886: getstatic burp/Zgfm.ZV : Ljava/lang/Object;
    //   2889: checkcast java/math/BigInteger
    //   2892: invokevirtual toByteArray : ()[B
    //   2895: astore_3
    //   2896: bipush #64
    //   2898: newarray byte
    //   2900: dup
    //   2901: iconst_0
    //   2902: bipush #-128
    //   2904: bastore
    //   2905: dup
    //   2906: iconst_1
    //   2907: iconst_0
    //   2908: bastore
    //   2909: dup
    //   2910: iconst_2
    //   2911: iconst_0
    //   2912: bastore
    //   2913: dup
    //   2914: iconst_3
    //   2915: iconst_0
    //   2916: bastore
    //   2917: dup
    //   2918: iconst_4
    //   2919: iconst_0
    //   2920: bastore
    //   2921: dup
    //   2922: iconst_5
    //   2923: iconst_0
    //   2924: bastore
    //   2925: dup
    //   2926: bipush #6
    //   2928: iconst_0
    //   2929: bastore
    //   2930: dup
    //   2931: bipush #7
    //   2933: iconst_0
    //   2934: bastore
    //   2935: dup
    //   2936: bipush #8
    //   2938: iconst_0
    //   2939: bastore
    //   2940: dup
    //   2941: bipush #9
    //   2943: iconst_0
    //   2944: bastore
    //   2945: dup
    //   2946: bipush #10
    //   2948: iconst_0
    //   2949: bastore
    //   2950: dup
    //   2951: bipush #11
    //   2953: iconst_0
    //   2954: bastore
    //   2955: dup
    //   2956: bipush #12
    //   2958: iconst_0
    //   2959: bastore
    //   2960: dup
    //   2961: bipush #13
    //   2963: iconst_0
    //   2964: bastore
    //   2965: dup
    //   2966: bipush #14
    //   2968: iconst_0
    //   2969: bastore
    //   2970: dup
    //   2971: bipush #15
    //   2973: iconst_0
    //   2974: bastore
    //   2975: dup
    //   2976: bipush #16
    //   2978: iconst_0
    //   2979: bastore
    //   2980: dup
    //   2981: bipush #17
    //   2983: iconst_0
    //   2984: bastore
    //   2985: dup
    //   2986: bipush #18
    //   2988: iconst_0
    //   2989: bastore
    //   2990: dup
    //   2991: bipush #19
    //   2993: iconst_0
    //   2994: bastore
    //   2995: dup
    //   2996: bipush #20
    //   2998: iconst_0
    //   2999: bastore
    //   3000: dup
    //   3001: bipush #21
    //   3003: iconst_0
    //   3004: bastore
    //   3005: dup
    //   3006: bipush #22
    //   3008: iconst_0
    //   3009: bastore
    //   3010: dup
    //   3011: bipush #23
    //   3013: iconst_0
    //   3014: bastore
    //   3015: dup
    //   3016: bipush #24
    //   3018: iconst_0
    //   3019: bastore
    //   3020: dup
    //   3021: bipush #25
    //   3023: iconst_0
    //   3024: bastore
    //   3025: dup
    //   3026: bipush #26
    //   3028: iconst_0
    //   3029: bastore
    //   3030: dup
    //   3031: bipush #27
    //   3033: iconst_0
    //   3034: bastore
    //   3035: dup
    //   3036: bipush #28
    //   3038: iconst_0
    //   3039: bastore
    //   3040: dup
    //   3041: bipush #29
    //   3043: iconst_0
    //   3044: bastore
    //   3045: dup
    //   3046: bipush #30
    //   3048: iconst_0
    //   3049: bastore
    //   3050: dup
    //   3051: bipush #31
    //   3053: iconst_0
    //   3054: bastore
    //   3055: dup
    //   3056: bipush #32
    //   3058: iconst_0
    //   3059: bastore
    //   3060: dup
    //   3061: bipush #33
    //   3063: iconst_0
    //   3064: bastore
    //   3065: dup
    //   3066: bipush #34
    //   3068: iconst_0
    //   3069: bastore
    //   3070: dup
    //   3071: bipush #35
    //   3073: iconst_0
    //   3074: bastore
    //   3075: dup
    //   3076: bipush #36
    //   3078: iconst_0
    //   3079: bastore
    //   3080: dup
    //   3081: bipush #37
    //   3083: iconst_0
    //   3084: bastore
    //   3085: dup
    //   3086: bipush #38
    //   3088: iconst_0
    //   3089: bastore
    //   3090: dup
    //   3091: bipush #39
    //   3093: iconst_0
    //   3094: bastore
    //   3095: dup
    //   3096: bipush #40
    //   3098: iconst_0
    //   3099: bastore
    //   3100: dup
    //   3101: bipush #41
    //   3103: iconst_0
    //   3104: bastore
    //   3105: dup
    //   3106: bipush #42
    //   3108: iconst_0
    //   3109: bastore
    //   3110: dup
    //   3111: bipush #43
    //   3113: iconst_0
    //   3114: bastore
    //   3115: dup
    //   3116: bipush #44
    //   3118: iconst_0
    //   3119: bastore
    //   3120: dup
    //   3121: bipush #45
    //   3123: iconst_0
    //   3124: bastore
    //   3125: dup
    //   3126: bipush #46
    //   3128: iconst_0
    //   3129: bastore
    //   3130: dup
    //   3131: bipush #47
    //   3133: iconst_0
    //   3134: bastore
    //   3135: dup
    //   3136: bipush #48
    //   3138: iconst_0
    //   3139: bastore
    //   3140: dup
    //   3141: bipush #49
    //   3143: iconst_0
    //   3144: bastore
    //   3145: dup
    //   3146: bipush #50
    //   3148: iconst_0
    //   3149: bastore
    //   3150: dup
    //   3151: bipush #51
    //   3153: iconst_0
    //   3154: bastore
    //   3155: dup
    //   3156: bipush #52
    //   3158: iconst_0
    //   3159: bastore
    //   3160: dup
    //   3161: bipush #53
    //   3163: iconst_0
    //   3164: bastore
    //   3165: dup
    //   3166: bipush #54
    //   3168: iconst_0
    //   3169: bastore
    //   3170: dup
    //   3171: bipush #55
    //   3173: iconst_0
    //   3174: bastore
    //   3175: dup
    //   3176: bipush #56
    //   3178: iconst_0
    //   3179: bastore
    //   3180: dup
    //   3181: bipush #57
    //   3183: iconst_0
    //   3184: bastore
    //   3185: dup
    //   3186: bipush #58
    //   3188: iconst_0
    //   3189: bastore
    //   3190: dup
    //   3191: bipush #59
    //   3193: iconst_0
    //   3194: bastore
    //   3195: dup
    //   3196: bipush #60
    //   3198: iconst_0
    //   3199: bastore
    //   3200: dup
    //   3201: bipush #61
    //   3203: iconst_0
    //   3204: bastore
    //   3205: dup
    //   3206: bipush #62
    //   3208: iconst_0
    //   3209: bastore
    //   3210: dup
    //   3211: bipush #63
    //   3213: iconst_0
    //   3214: bastore
    //   3215: astore #5
    //   3217: bipush #64
    //   3219: newarray int
    //   3221: dup
    //   3222: iconst_0
    //   3223: ldc 1116352408
    //   3225: iastore
    //   3226: dup
    //   3227: iconst_1
    //   3228: ldc 1899447441
    //   3230: iastore
    //   3231: dup
    //   3232: iconst_2
    //   3233: ldc -1245643825
    //   3235: iastore
    //   3236: dup
    //   3237: iconst_3
    //   3238: ldc -373957723
    //   3240: iastore
    //   3241: dup
    //   3242: iconst_4
    //   3243: ldc 961987163
    //   3245: iastore
    //   3246: dup
    //   3247: iconst_5
    //   3248: ldc 1508970993
    //   3250: iastore
    //   3251: dup
    //   3252: bipush #6
    //   3254: ldc -1841331548
    //   3256: iastore
    //   3257: dup
    //   3258: bipush #7
    //   3260: ldc -1424204075
    //   3262: iastore
    //   3263: dup
    //   3264: bipush #8
    //   3266: ldc -670586216
    //   3268: iastore
    //   3269: dup
    //   3270: bipush #9
    //   3272: ldc 310598401
    //   3274: iastore
    //   3275: dup
    //   3276: bipush #10
    //   3278: ldc 607225278
    //   3280: iastore
    //   3281: dup
    //   3282: bipush #11
    //   3284: ldc 1426881987
    //   3286: iastore
    //   3287: dup
    //   3288: bipush #12
    //   3290: ldc 1925078388
    //   3292: iastore
    //   3293: dup
    //   3294: bipush #13
    //   3296: ldc -2132889090
    //   3298: iastore
    //   3299: dup
    //   3300: bipush #14
    //   3302: ldc -1680079193
    //   3304: iastore
    //   3305: dup
    //   3306: bipush #15
    //   3308: ldc -1046744716
    //   3310: iastore
    //   3311: dup
    //   3312: bipush #16
    //   3314: ldc -459576895
    //   3316: iastore
    //   3317: dup
    //   3318: bipush #17
    //   3320: ldc -272742522
    //   3322: iastore
    //   3323: dup
    //   3324: bipush #18
    //   3326: ldc 264347078
    //   3328: iastore
    //   3329: dup
    //   3330: bipush #19
    //   3332: ldc 604807628
    //   3334: iastore
    //   3335: dup
    //   3336: bipush #20
    //   3338: ldc 770255983
    //   3340: iastore
    //   3341: dup
    //   3342: bipush #21
    //   3344: ldc 1249150122
    //   3346: iastore
    //   3347: dup
    //   3348: bipush #22
    //   3350: ldc 1555081692
    //   3352: iastore
    //   3353: dup
    //   3354: bipush #23
    //   3356: ldc 1996064986
    //   3358: iastore
    //   3359: dup
    //   3360: bipush #24
    //   3362: ldc -1740746414
    //   3364: iastore
    //   3365: dup
    //   3366: bipush #25
    //   3368: ldc -1473132947
    //   3370: iastore
    //   3371: dup
    //   3372: bipush #26
    //   3374: ldc -1341970488
    //   3376: iastore
    //   3377: dup
    //   3378: bipush #27
    //   3380: ldc -1084653625
    //   3382: iastore
    //   3383: dup
    //   3384: bipush #28
    //   3386: ldc -958395405
    //   3388: iastore
    //   3389: dup
    //   3390: bipush #29
    //   3392: ldc -710438585
    //   3394: iastore
    //   3395: dup
    //   3396: bipush #30
    //   3398: ldc 113926993
    //   3400: iastore
    //   3401: dup
    //   3402: bipush #31
    //   3404: ldc 338241895
    //   3406: iastore
    //   3407: dup
    //   3408: bipush #32
    //   3410: ldc 666307205
    //   3412: iastore
    //   3413: dup
    //   3414: bipush #33
    //   3416: ldc 773529912
    //   3418: iastore
    //   3419: dup
    //   3420: bipush #34
    //   3422: ldc 1294757372
    //   3424: iastore
    //   3425: dup
    //   3426: bipush #35
    //   3428: ldc 1396182291
    //   3430: iastore
    //   3431: dup
    //   3432: bipush #36
    //   3434: ldc 1695183700
    //   3436: iastore
    //   3437: dup
    //   3438: bipush #37
    //   3440: ldc 1986661051
    //   3442: iastore
    //   3443: dup
    //   3444: bipush #38
    //   3446: ldc -2117940946
    //   3448: iastore
    //   3449: dup
    //   3450: bipush #39
    //   3452: ldc -1838011259
    //   3454: iastore
    //   3455: dup
    //   3456: bipush #40
    //   3458: ldc -1564481375
    //   3460: iastore
    //   3461: dup
    //   3462: bipush #41
    //   3464: ldc -1474664885
    //   3466: iastore
    //   3467: dup
    //   3468: bipush #42
    //   3470: ldc -1035236496
    //   3472: iastore
    //   3473: dup
    //   3474: bipush #43
    //   3476: ldc -949202525
    //   3478: iastore
    //   3479: dup
    //   3480: bipush #44
    //   3482: ldc -778901479
    //   3484: iastore
    //   3485: dup
    //   3486: bipush #45
    //   3488: ldc -694614492
    //   3490: iastore
    //   3491: dup
    //   3492: bipush #46
    //   3494: ldc -200395387
    //   3496: iastore
    //   3497: dup
    //   3498: bipush #47
    //   3500: ldc 275423344
    //   3502: iastore
    //   3503: dup
    //   3504: bipush #48
    //   3506: ldc 430227734
    //   3508: iastore
    //   3509: dup
    //   3510: bipush #49
    //   3512: ldc 506948616
    //   3514: iastore
    //   3515: dup
    //   3516: bipush #50
    //   3518: ldc 659060556
    //   3520: iastore
    //   3521: dup
    //   3522: bipush #51
    //   3524: ldc 883997877
    //   3526: iastore
    //   3527: dup
    //   3528: bipush #52
    //   3530: ldc 958139571
    //   3532: iastore
    //   3533: dup
    //   3534: bipush #53
    //   3536: ldc 1322822218
    //   3538: iastore
    //   3539: dup
    //   3540: bipush #54
    //   3542: ldc 1537002063
    //   3544: iastore
    //   3545: dup
    //   3546: bipush #55
    //   3548: ldc 1747873779
    //   3550: iastore
    //   3551: dup
    //   3552: bipush #56
    //   3554: ldc 1955562222
    //   3556: iastore
    //   3557: dup
    //   3558: bipush #57
    //   3560: ldc 2024104815
    //   3562: iastore
    //   3563: dup
    //   3564: bipush #58
    //   3566: ldc -2067236844
    //   3568: iastore
    //   3569: dup
    //   3570: bipush #59
    //   3572: ldc -1933114872
    //   3574: iastore
    //   3575: dup
    //   3576: bipush #60
    //   3578: ldc -1866530822
    //   3580: iastore
    //   3581: dup
    //   3582: bipush #61
    //   3584: ldc -1538233109
    //   3586: iastore
    //   3587: dup
    //   3588: bipush #62
    //   3590: ldc -1090935817
    //   3592: iastore
    //   3593: dup
    //   3594: bipush #63
    //   3596: ldc -965641998
    //   3598: iastore
    //   3599: astore #6
    //   3601: iconst_2
    //   3602: newarray int
    //   3604: dup
    //   3605: iconst_0
    //   3606: iconst_0
    //   3607: iastore
    //   3608: dup
    //   3609: iconst_1
    //   3610: iconst_0
    //   3611: iastore
    //   3612: astore #7
    //   3614: bipush #8
    //   3616: newarray int
    //   3618: dup
    //   3619: iconst_0
    //   3620: ldc 1779033703
    //   3622: iastore
    //   3623: dup
    //   3624: iconst_1
    //   3625: ldc -1150833019
    //   3627: iastore
    //   3628: dup
    //   3629: iconst_2
    //   3630: ldc 1013904242
    //   3632: iastore
    //   3633: dup
    //   3634: iconst_3
    //   3635: ldc -1521486534
    //   3637: iastore
    //   3638: dup
    //   3639: iconst_4
    //   3640: ldc 1359893119
    //   3642: iastore
    //   3643: dup
    //   3644: iconst_5
    //   3645: ldc -1694144372
    //   3647: iastore
    //   3648: dup
    //   3649: bipush #6
    //   3651: ldc 528734635
    //   3653: iastore
    //   3654: dup
    //   3655: bipush #7
    //   3657: ldc 1541459225
    //   3659: iastore
    //   3660: astore #8
    //   3662: bipush #64
    //   3664: newarray byte
    //   3666: astore #9
    //   3668: bipush #64
    //   3670: newarray byte
    //   3672: astore #10
    //   3674: aload_3
    //   3675: arraylength
    //   3676: istore #11
    //   3678: aload #7
    //   3680: iconst_0
    //   3681: iaload
    //   3682: bipush #63
    //   3684: iand
    //   3685: istore #12
    //   3687: aload #7
    //   3689: iconst_0
    //   3690: dup2
    //   3691: iaload
    //   3692: iload #11
    //   3694: iadd
    //   3695: iastore
    //   3696: aload #7
    //   3698: iconst_0
    //   3699: dup2
    //   3700: iaload
    //   3701: iconst_m1
    //   3702: iand
    //   3703: iastore
    //   3704: aload #7
    //   3706: iconst_0
    //   3707: iaload
    //   3708: iload #11
    //   3710: if_icmpge -> 3728
    //   3713: aload #7
    //   3715: iconst_1
    //   3716: dup2
    //   3717: iaload
    //   3718: iconst_1
    //   3719: iadd
    //   3720: iastore
    //   3721: goto -> 3728
    //   3724: invokestatic a : (Ljava/lang/Throwable;)Ljava/lang/Throwable;
    //   3727: athrow
    //   3728: iconst_0
    //   3729: istore #13
    //   3731: iload #11
    //   3733: bipush #64
    //   3735: if_icmplt -> 4344
    //   3738: iconst_0
    //   3739: istore #14
    //   3741: iload #14
    //   3743: bipush #64
    //   3745: if_icmpge -> 3767
    //   3748: aload #10
    //   3750: iload #14
    //   3752: aload_3
    //   3753: iload #13
    //   3755: iload #14
    //   3757: iadd
    //   3758: baload
    //   3759: bastore
    //   3760: iinc #14, 1
    //   3763: iload_2
    //   3764: ifeq -> 3741
    //   3767: bipush #64
    //   3769: newarray int
    //   3771: astore #14
    //   3773: bipush #8
    //   3775: newarray int
    //   3777: astore #15
    //   3779: iconst_0
    //   3780: istore #16
    //   3782: iload #16
    //   3784: bipush #8
    //   3786: if_icmpge -> 3806
    //   3789: aload #15
    //   3791: iload #16
    //   3793: aload #8
    //   3795: iload #16
    //   3797: iaload
    //   3798: iastore
    //   3799: iinc #16, 1
    //   3802: iload_2
    //   3803: ifeq -> 3782
    //   3806: iconst_0
    //   3807: istore #16
    //   3809: iload #16
    //   3811: bipush #64
    //   3813: if_icmpge -> 4304
    //   3816: iload #16
    //   3818: bipush #16
    //   3820: if_icmpge -> 3901
    //   3823: aload #14
    //   3825: iload #16
    //   3827: aload #10
    //   3829: iconst_4
    //   3830: iload #16
    //   3832: imul
    //   3833: baload
    //   3834: sipush #255
    //   3837: iand
    //   3838: bipush #24
    //   3840: ishl
    //   3841: aload #10
    //   3843: iconst_4
    //   3844: iload #16
    //   3846: imul
    //   3847: iconst_1
    //   3848: iadd
    //   3849: baload
    //   3850: sipush #255
    //   3853: iand
    //   3854: bipush #16
    //   3856: ishl
    //   3857: ior
    //   3858: aload #10
    //   3860: iconst_4
    //   3861: iload #16
    //   3863: imul
    //   3864: iconst_2
    //   3865: iadd
    //   3866: baload
    //   3867: sipush #255
    //   3870: iand
    //   3871: bipush #8
    //   3873: ishl
    //   3874: ior
    //   3875: aload #10
    //   3877: iconst_4
    //   3878: iload #16
    //   3880: imul
    //   3881: iconst_3
    //   3882: iadd
    //   3883: baload
    //   3884: sipush #255
    //   3887: iand
    //   3888: ior
    //   3889: iastore
    //   3890: iload_2
    //   3891: ifeq -> 4044
    //   3894: goto -> 3901
    //   3897: invokestatic a : (Ljava/lang/Throwable;)Ljava/lang/Throwable;
    //   3900: athrow
    //   3901: aload #14
    //   3903: iload #16
    //   3905: aload #14
    //   3907: iload #16
    //   3909: iconst_2
    //   3910: isub
    //   3911: iaload
    //   3912: bipush #17
    //   3914: iushr
    //   3915: aload #14
    //   3917: iload #16
    //   3919: iconst_2
    //   3920: isub
    //   3921: iaload
    //   3922: bipush #15
    //   3924: ishl
    //   3925: ior
    //   3926: aload #14
    //   3928: iload #16
    //   3930: iconst_2
    //   3931: isub
    //   3932: iaload
    //   3933: bipush #19
    //   3935: iushr
    //   3936: aload #14
    //   3938: iload #16
    //   3940: iconst_2
    //   3941: isub
    //   3942: iaload
    //   3943: bipush #13
    //   3945: ishl
    //   3946: ior
    //   3947: ixor
    //   3948: aload #14
    //   3950: iload #16
    //   3952: iconst_2
    //   3953: isub
    //   3954: iaload
    //   3955: bipush #10
    //   3957: iushr
    //   3958: ixor
    //   3959: aload #14
    //   3961: iload #16
    //   3963: bipush #7
    //   3965: isub
    //   3966: iaload
    //   3967: iadd
    //   3968: aload #14
    //   3970: iload #16
    //   3972: bipush #15
    //   3974: isub
    //   3975: iaload
    //   3976: bipush #7
    //   3978: iushr
    //   3979: aload #14
    //   3981: iload #16
    //   3983: bipush #15
    //   3985: isub
    //   3986: iaload
    //   3987: bipush #25
    //   3989: ishl
    //   3990: ior
    //   3991: aload #14
    //   3993: iload #16
    //   3995: bipush #15
    //   3997: isub
    //   3998: iaload
    //   3999: bipush #18
    //   4001: iushr
    //   4002: aload #14
    //   4004: iload #16
    //   4006: bipush #15
    //   4008: isub
    //   4009: iaload
    //   4010: bipush #14
    //   4012: ishl
    //   4013: ior
    //   4014: ixor
    //   4015: aload #14
    //   4017: iload #16
    //   4019: bipush #15
    //   4021: isub
    //   4022: iaload
    //   4023: iconst_3
    //   4024: iushr
    //   4025: ixor
    //   4026: iadd
    //   4027: aload #14
    //   4029: iload #16
    //   4031: bipush #16
    //   4033: isub
    //   4034: iaload
    //   4035: iadd
    //   4036: iastore
    //   4037: goto -> 4044
    //   4040: invokestatic a : (Ljava/lang/Throwable;)Ljava/lang/Throwable;
    //   4043: athrow
    //   4044: aload #15
    //   4046: bipush #7
    //   4048: iaload
    //   4049: aload #15
    //   4051: iconst_4
    //   4052: iaload
    //   4053: bipush #6
    //   4055: iushr
    //   4056: aload #15
    //   4058: iconst_4
    //   4059: iaload
    //   4060: bipush #26
    //   4062: ishl
    //   4063: ior
    //   4064: aload #15
    //   4066: iconst_4
    //   4067: iaload
    //   4068: bipush #11
    //   4070: iushr
    //   4071: aload #15
    //   4073: iconst_4
    //   4074: iaload
    //   4075: bipush #21
    //   4077: ishl
    //   4078: ior
    //   4079: ixor
    //   4080: aload #15
    //   4082: iconst_4
    //   4083: iaload
    //   4084: bipush #25
    //   4086: iushr
    //   4087: aload #15
    //   4089: iconst_4
    //   4090: iaload
    //   4091: bipush #7
    //   4093: ishl
    //   4094: ior
    //   4095: ixor
    //   4096: iadd
    //   4097: aload #15
    //   4099: bipush #6
    //   4101: iaload
    //   4102: aload #15
    //   4104: iconst_4
    //   4105: iaload
    //   4106: aload #15
    //   4108: iconst_5
    //   4109: iaload
    //   4110: aload #15
    //   4112: bipush #6
    //   4114: iaload
    //   4115: ixor
    //   4116: iand
    //   4117: ixor
    //   4118: iadd
    //   4119: aload #6
    //   4121: iload #16
    //   4123: iaload
    //   4124: iadd
    //   4125: aload #14
    //   4127: iload #16
    //   4129: iaload
    //   4130: iadd
    //   4131: istore #17
    //   4133: aload #15
    //   4135: iconst_0
    //   4136: iaload
    //   4137: iconst_2
    //   4138: iushr
    //   4139: aload #15
    //   4141: iconst_0
    //   4142: iaload
    //   4143: bipush #30
    //   4145: ishl
    //   4146: ior
    //   4147: aload #15
    //   4149: iconst_0
    //   4150: iaload
    //   4151: bipush #13
    //   4153: iushr
    //   4154: aload #15
    //   4156: iconst_0
    //   4157: iaload
    //   4158: bipush #19
    //   4160: ishl
    //   4161: ior
    //   4162: ixor
    //   4163: aload #15
    //   4165: iconst_0
    //   4166: iaload
    //   4167: bipush #22
    //   4169: iushr
    //   4170: aload #15
    //   4172: iconst_0
    //   4173: iaload
    //   4174: bipush #10
    //   4176: ishl
    //   4177: ior
    //   4178: ixor
    //   4179: aload #15
    //   4181: iconst_0
    //   4182: iaload
    //   4183: aload #15
    //   4185: iconst_1
    //   4186: iaload
    //   4187: iand
    //   4188: aload #15
    //   4190: iconst_2
    //   4191: iaload
    //   4192: aload #15
    //   4194: iconst_0
    //   4195: iaload
    //   4196: aload #15
    //   4198: iconst_1
    //   4199: iaload
    //   4200: ior
    //   4201: iand
    //   4202: ior
    //   4203: iadd
    //   4204: istore #18
    //   4206: aload #15
    //   4208: iconst_3
    //   4209: dup2
    //   4210: iaload
    //   4211: iload #17
    //   4213: iadd
    //   4214: iastore
    //   4215: aload #15
    //   4217: bipush #7
    //   4219: iload #17
    //   4221: iload #18
    //   4223: iadd
    //   4224: iastore
    //   4225: aload #15
    //   4227: bipush #7
    //   4229: iaload
    //   4230: istore #17
    //   4232: aload #15
    //   4234: bipush #7
    //   4236: aload #15
    //   4238: bipush #6
    //   4240: iaload
    //   4241: iastore
    //   4242: aload #15
    //   4244: bipush #6
    //   4246: aload #15
    //   4248: iconst_5
    //   4249: iaload
    //   4250: iastore
    //   4251: aload #15
    //   4253: iconst_5
    //   4254: aload #15
    //   4256: iconst_4
    //   4257: iaload
    //   4258: iastore
    //   4259: aload #15
    //   4261: iconst_4
    //   4262: aload #15
    //   4264: iconst_3
    //   4265: iaload
    //   4266: iastore
    //   4267: aload #15
    //   4269: iconst_3
    //   4270: aload #15
    //   4272: iconst_2
    //   4273: iaload
    //   4274: iastore
    //   4275: aload #15
    //   4277: iconst_2
    //   4278: aload #15
    //   4280: iconst_1
    //   4281: iaload
    //   4282: iastore
    //   4283: aload #15
    //   4285: iconst_1
    //   4286: aload #15
    //   4288: iconst_0
    //   4289: iaload
    //   4290: iastore
    //   4291: aload #15
    //   4293: iconst_0
    //   4294: iload #17
    //   4296: iastore
    //   4297: iinc #16, 1
    //   4300: iload_2
    //   4301: ifeq -> 3809
    //   4304: iconst_0
    //   4305: istore #16
    //   4307: iload #16
    //   4309: bipush #8
    //   4311: if_icmpge -> 4334
    //   4314: aload #8
    //   4316: iload #16
    //   4318: dup2
    //   4319: iaload
    //   4320: aload #15
    //   4322: iload #16
    //   4324: iaload
    //   4325: iadd
    //   4326: iastore
    //   4327: iinc #16, 1
    //   4330: iload_2
    //   4331: ifeq -> 4307
    //   4334: iinc #13, 64
    //   4337: iinc #11, -64
    //   4340: iload_2
    //   4341: ifeq -> 3731
    //   4344: iload #11
    //   4346: ifle -> 4381
    //   4349: iconst_0
    //   4350: istore #14
    //   4352: iload #14
    //   4354: iload #11
    //   4356: if_icmpge -> 4381
    //   4359: aload #9
    //   4361: iload #12
    //   4363: iload #14
    //   4365: iadd
    //   4366: aload_3
    //   4367: iload #13
    //   4369: iload #14
    //   4371: iadd
    //   4372: baload
    //   4373: bastore
    //   4374: iinc #14, 1
    //   4377: iload_2
    //   4378: ifeq -> 4352
    //   4381: aload #7
    //   4383: iconst_0
    //   4384: iaload
    //   4385: bipush #29
    //   4387: iushr
    //   4388: aload #7
    //   4390: iconst_1
    //   4391: iaload
    //   4392: iconst_3
    //   4393: ishl
    //   4394: ior
    //   4395: istore #14
    //   4397: aload #7
    //   4399: iconst_0
    //   4400: iaload
    //   4401: iconst_3
    //   4402: ishl
    //   4403: istore #15
    //   4405: aload #7
    //   4407: iconst_0
    //   4408: iaload
    //   4409: bipush #63
    //   4411: iand
    //   4412: istore #16
    //   4414: iload #16
    //   4416: bipush #56
    //   4418: if_icmpge -> 4433
    //   4421: bipush #56
    //   4423: iload #16
    //   4425: isub
    //   4426: goto -> 4438
    //   4429: invokestatic a : (Ljava/lang/Throwable;)Ljava/lang/Throwable;
    //   4432: athrow
    //   4433: bipush #120
    //   4435: iload #16
    //   4437: isub
    //   4438: istore #17
    //   4440: aload #7
    //   4442: iconst_0
    //   4443: iaload
    //   4444: bipush #63
    //   4446: iand
    //   4447: istore #12
    //   4449: bipush #64
    //   4451: iload #12
    //   4453: isub
    //   4454: istore #18
    //   4456: aload #7
    //   4458: iconst_0
    //   4459: dup2
    //   4460: iaload
    //   4461: iload #17
    //   4463: iadd
    //   4464: iastore
    //   4465: aload #7
    //   4467: iconst_0
    //   4468: dup2
    //   4469: iaload
    //   4470: iconst_m1
    //   4471: iand
    //   4472: iastore
    //   4473: aload #7
    //   4475: iconst_0
    //   4476: iaload
    //   4477: iload #17
    //   4479: if_icmpge -> 4497
    //   4482: aload #7
    //   4484: iconst_1
    //   4485: dup2
    //   4486: iaload
    //   4487: iconst_1
    //   4488: iadd
    //   4489: iastore
    //   4490: goto -> 4497
    //   4493: invokestatic a : (Ljava/lang/Throwable;)Ljava/lang/Throwable;
    //   4496: athrow
    //   4497: iconst_0
    //   4498: istore #13
    //   4500: iload #12
    //   4502: ifle -> 5133
    //   4505: iload #17
    //   4507: iload #18
    //   4509: if_icmplt -> 5133
    //   4512: goto -> 4519
    //   4515: invokestatic a : (Ljava/lang/Throwable;)Ljava/lang/Throwable;
    //   4518: athrow
    //   4519: iconst_0
    //   4520: istore #19
    //   4522: iload #19
    //   4524: iload #18
    //   4526: if_icmpge -> 4549
    //   4529: aload #9
    //   4531: iload #12
    //   4533: iload #19
    //   4535: iadd
    //   4536: aload #5
    //   4538: iload #19
    //   4540: baload
    //   4541: bastore
    //   4542: iinc #19, 1
    //   4545: iload_2
    //   4546: ifeq -> 4522
    //   4549: bipush #64
    //   4551: newarray int
    //   4553: astore #19
    //   4555: bipush #8
    //   4557: newarray int
    //   4559: astore #20
    //   4561: iconst_0
    //   4562: istore #21
    //   4564: iload #21
    //   4566: bipush #8
    //   4568: if_icmpge -> 4588
    //   4571: aload #20
    //   4573: iload #21
    //   4575: aload #8
    //   4577: iload #21
    //   4579: iaload
    //   4580: iastore
    //   4581: iinc #21, 1
    //   4584: iload_2
    //   4585: ifeq -> 4564
    //   4588: iconst_0
    //   4589: istore #21
    //   4591: iload #21
    //   4593: bipush #64
    //   4595: if_icmpge -> 5086
    //   4598: iload #21
    //   4600: bipush #16
    //   4602: if_icmpge -> 4683
    //   4605: aload #19
    //   4607: iload #21
    //   4609: aload #9
    //   4611: iconst_4
    //   4612: iload #21
    //   4614: imul
    //   4615: baload
    //   4616: sipush #255
    //   4619: iand
    //   4620: bipush #24
    //   4622: ishl
    //   4623: aload #9
    //   4625: iconst_4
    //   4626: iload #21
    //   4628: imul
    //   4629: iconst_1
    //   4630: iadd
    //   4631: baload
    //   4632: sipush #255
    //   4635: iand
    //   4636: bipush #16
    //   4638: ishl
    //   4639: ior
    //   4640: aload #9
    //   4642: iconst_4
    //   4643: iload #21
    //   4645: imul
    //   4646: iconst_2
    //   4647: iadd
    //   4648: baload
    //   4649: sipush #255
    //   4652: iand
    //   4653: bipush #8
    //   4655: ishl
    //   4656: ior
    //   4657: aload #9
    //   4659: iconst_4
    //   4660: iload #21
    //   4662: imul
    //   4663: iconst_3
    //   4664: iadd
    //   4665: baload
    //   4666: sipush #255
    //   4669: iand
    //   4670: ior
    //   4671: iastore
    //   4672: iload_2
    //   4673: ifeq -> 4826
    //   4676: goto -> 4683
    //   4679: invokestatic a : (Ljava/lang/Throwable;)Ljava/lang/Throwable;
    //   4682: athrow
    //   4683: aload #19
    //   4685: iload #21
    //   4687: aload #19
    //   4689: iload #21
    //   4691: iconst_2
    //   4692: isub
    //   4693: iaload
    //   4694: bipush #17
    //   4696: iushr
    //   4697: aload #19
    //   4699: iload #21
    //   4701: iconst_2
    //   4702: isub
    //   4703: iaload
    //   4704: bipush #15
    //   4706: ishl
    //   4707: ior
    //   4708: aload #19
    //   4710: iload #21
    //   4712: iconst_2
    //   4713: isub
    //   4714: iaload
    //   4715: bipush #19
    //   4717: iushr
    //   4718: aload #19
    //   4720: iload #21
    //   4722: iconst_2
    //   4723: isub
    //   4724: iaload
    //   4725: bipush #13
    //   4727: ishl
    //   4728: ior
    //   4729: ixor
    //   4730: aload #19
    //   4732: iload #21
    //   4734: iconst_2
    //   4735: isub
    //   4736: iaload
    //   4737: bipush #10
    //   4739: iushr
    //   4740: ixor
    //   4741: aload #19
    //   4743: iload #21
    //   4745: bipush #7
    //   4747: isub
    //   4748: iaload
    //   4749: iadd
    //   4750: aload #19
    //   4752: iload #21
    //   4754: bipush #15
    //   4756: isub
    //   4757: iaload
    //   4758: bipush #7
    //   4760: iushr
    //   4761: aload #19
    //   4763: iload #21
    //   4765: bipush #15
    //   4767: isub
    //   4768: iaload
    //   4769: bipush #25
    //   4771: ishl
    //   4772: ior
    //   4773: aload #19
    //   4775: iload #21
    //   4777: bipush #15
    //   4779: isub
    //   4780: iaload
    //   4781: bipush #18
    //   4783: iushr
    //   4784: aload #19
    //   4786: iload #21
    //   4788: bipush #15
    //   4790: isub
    //   4791: iaload
    //   4792: bipush #14
    //   4794: ishl
    //   4795: ior
    //   4796: ixor
    //   4797: aload #19
    //   4799: iload #21
    //   4801: bipush #15
    //   4803: isub
    //   4804: iaload
    //   4805: iconst_3
    //   4806: iushr
    //   4807: ixor
    //   4808: iadd
    //   4809: aload #19
    //   4811: iload #21
    //   4813: bipush #16
    //   4815: isub
    //   4816: iaload
    //   4817: iadd
    //   4818: iastore
    //   4819: goto -> 4826
    //   4822: invokestatic a : (Ljava/lang/Throwable;)Ljava/lang/Throwable;
    //   4825: athrow
    //   4826: aload #20
    //   4828: bipush #7
    //   4830: iaload
    //   4831: aload #20
    //   4833: iconst_4
    //   4834: iaload
    //   4835: bipush #6
    //   4837: iushr
    //   4838: aload #20
    //   4840: iconst_4
    //   4841: iaload
    //   4842: bipush #26
    //   4844: ishl
    //   4845: ior
    //   4846: aload #20
    //   4848: iconst_4
    //   4849: iaload
    //   4850: bipush #11
    //   4852: iushr
    //   4853: aload #20
    //   4855: iconst_4
    //   4856: iaload
    //   4857: bipush #21
    //   4859: ishl
    //   4860: ior
    //   4861: ixor
    //   4862: aload #20
    //   4864: iconst_4
    //   4865: iaload
    //   4866: bipush #25
    //   4868: iushr
    //   4869: aload #20
    //   4871: iconst_4
    //   4872: iaload
    //   4873: bipush #7
    //   4875: ishl
    //   4876: ior
    //   4877: ixor
    //   4878: iadd
    //   4879: aload #20
    //   4881: bipush #6
    //   4883: iaload
    //   4884: aload #20
    //   4886: iconst_4
    //   4887: iaload
    //   4888: aload #20
    //   4890: iconst_5
    //   4891: iaload
    //   4892: aload #20
    //   4894: bipush #6
    //   4896: iaload
    //   4897: ixor
    //   4898: iand
    //   4899: ixor
    //   4900: iadd
    //   4901: aload #6
    //   4903: iload #21
    //   4905: iaload
    //   4906: iadd
    //   4907: aload #19
    //   4909: iload #21
    //   4911: iaload
    //   4912: iadd
    //   4913: istore #22
    //   4915: aload #20
    //   4917: iconst_0
    //   4918: iaload
    //   4919: iconst_2
    //   4920: iushr
    //   4921: aload #20
    //   4923: iconst_0
    //   4924: iaload
    //   4925: bipush #30
    //   4927: ishl
    //   4928: ior
    //   4929: aload #20
    //   4931: iconst_0
    //   4932: iaload
    //   4933: bipush #13
    //   4935: iushr
    //   4936: aload #20
    //   4938: iconst_0
    //   4939: iaload
    //   4940: bipush #19
    //   4942: ishl
    //   4943: ior
    //   4944: ixor
    //   4945: aload #20
    //   4947: iconst_0
    //   4948: iaload
    //   4949: bipush #22
    //   4951: iushr
    //   4952: aload #20
    //   4954: iconst_0
    //   4955: iaload
    //   4956: bipush #10
    //   4958: ishl
    //   4959: ior
    //   4960: ixor
    //   4961: aload #20
    //   4963: iconst_0
    //   4964: iaload
    //   4965: aload #20
    //   4967: iconst_1
    //   4968: iaload
    //   4969: iand
    //   4970: aload #20
    //   4972: iconst_2
    //   4973: iaload
    //   4974: aload #20
    //   4976: iconst_0
    //   4977: iaload
    //   4978: aload #20
    //   4980: iconst_1
    //   4981: iaload
    //   4982: ior
    //   4983: iand
    //   4984: ior
    //   4985: iadd
    //   4986: istore #23
    //   4988: aload #20
    //   4990: iconst_3
    //   4991: dup2
    //   4992: iaload
    //   4993: iload #22
    //   4995: iadd
    //   4996: iastore
    //   4997: aload #20
    //   4999: bipush #7
    //   5001: iload #22
    //   5003: iload #23
    //   5005: iadd
    //   5006: iastore
    //   5007: aload #20
    //   5009: bipush #7
    //   5011: iaload
    //   5012: istore #22
    //   5014: aload #20
    //   5016: bipush #7
    //   5018: aload #20
    //   5020: bipush #6
    //   5022: iaload
    //   5023: iastore
    //   5024: aload #20
    //   5026: bipush #6
    //   5028: aload #20
    //   5030: iconst_5
    //   5031: iaload
    //   5032: iastore
    //   5033: aload #20
    //   5035: iconst_5
    //   5036: aload #20
    //   5038: iconst_4
    //   5039: iaload
    //   5040: iastore
    //   5041: aload #20
    //   5043: iconst_4
    //   5044: aload #20
    //   5046: iconst_3
    //   5047: iaload
    //   5048: iastore
    //   5049: aload #20
    //   5051: iconst_3
    //   5052: aload #20
    //   5054: iconst_2
    //   5055: iaload
    //   5056: iastore
    //   5057: aload #20
    //   5059: iconst_2
    //   5060: aload #20
    //   5062: iconst_1
    //   5063: iaload
    //   5064: iastore
    //   5065: aload #20
    //   5067: iconst_1
    //   5068: aload #20
    //   5070: iconst_0
    //   5071: iaload
    //   5072: iastore
    //   5073: aload #20
    //   5075: iconst_0
    //   5076: iload #22
    //   5078: iastore
    //   5079: iinc #21, 1
    //   5082: iload_2
    //   5083: ifeq -> 4591
    //   5086: iconst_0
    //   5087: istore #21
    //   5089: iload #21
    //   5091: bipush #8
    //   5093: if_icmpge -> 5116
    //   5096: aload #8
    //   5098: iload #21
    //   5100: dup2
    //   5101: iaload
    //   5102: aload #20
    //   5104: iload #21
    //   5106: iaload
    //   5107: iadd
    //   5108: iastore
    //   5109: iinc #21, 1
    //   5112: iload_2
    //   5113: ifeq -> 5089
    //   5116: iload #13
    //   5118: iload #18
    //   5120: iadd
    //   5121: istore #13
    //   5123: iload #17
    //   5125: iload #18
    //   5127: isub
    //   5128: istore #17
    //   5130: iconst_0
    //   5131: istore #12
    //   5133: iload #17
    //   5135: bipush #64
    //   5137: if_icmplt -> 5747
    //   5140: iconst_0
    //   5141: istore #19
    //   5143: iload #19
    //   5145: bipush #64
    //   5147: if_icmpge -> 5170
    //   5150: aload #10
    //   5152: iload #19
    //   5154: aload #5
    //   5156: iload #13
    //   5158: iload #19
    //   5160: iadd
    //   5161: baload
    //   5162: bastore
    //   5163: iinc #19, 1
    //   5166: iload_2
    //   5167: ifeq -> 5143
    //   5170: bipush #64
    //   5172: newarray int
    //   5174: astore #19
    //   5176: bipush #8
    //   5178: newarray int
    //   5180: astore #20
    //   5182: iconst_0
    //   5183: istore #21
    //   5185: iload #21
    //   5187: bipush #8
    //   5189: if_icmpge -> 5209
    //   5192: aload #20
    //   5194: iload #21
    //   5196: aload #8
    //   5198: iload #21
    //   5200: iaload
    //   5201: iastore
    //   5202: iinc #21, 1
    //   5205: iload_2
    //   5206: ifeq -> 5185
    //   5209: iconst_0
    //   5210: istore #21
    //   5212: iload #21
    //   5214: bipush #64
    //   5216: if_icmpge -> 5707
    //   5219: iload #21
    //   5221: bipush #16
    //   5223: if_icmpge -> 5304
    //   5226: aload #19
    //   5228: iload #21
    //   5230: aload #10
    //   5232: iconst_4
    //   5233: iload #21
    //   5235: imul
    //   5236: baload
    //   5237: sipush #255
    //   5240: iand
    //   5241: bipush #24
    //   5243: ishl
    //   5244: aload #10
    //   5246: iconst_4
    //   5247: iload #21
    //   5249: imul
    //   5250: iconst_1
    //   5251: iadd
    //   5252: baload
    //   5253: sipush #255
    //   5256: iand
    //   5257: bipush #16
    //   5259: ishl
    //   5260: ior
    //   5261: aload #10
    //   5263: iconst_4
    //   5264: iload #21
    //   5266: imul
    //   5267: iconst_2
    //   5268: iadd
    //   5269: baload
    //   5270: sipush #255
    //   5273: iand
    //   5274: bipush #8
    //   5276: ishl
    //   5277: ior
    //   5278: aload #10
    //   5280: iconst_4
    //   5281: iload #21
    //   5283: imul
    //   5284: iconst_3
    //   5285: iadd
    //   5286: baload
    //   5287: sipush #255
    //   5290: iand
    //   5291: ior
    //   5292: iastore
    //   5293: iload_2
    //   5294: ifeq -> 5447
    //   5297: goto -> 5304
    //   5300: invokestatic a : (Ljava/lang/Throwable;)Ljava/lang/Throwable;
    //   5303: athrow
    //   5304: aload #19
    //   5306: iload #21
    //   5308: aload #19
    //   5310: iload #21
    //   5312: iconst_2
    //   5313: isub
    //   5314: iaload
    //   5315: bipush #17
    //   5317: iushr
    //   5318: aload #19
    //   5320: iload #21
    //   5322: iconst_2
    //   5323: isub
    //   5324: iaload
    //   5325: bipush #15
    //   5327: ishl
    //   5328: ior
    //   5329: aload #19
    //   5331: iload #21
    //   5333: iconst_2
    //   5334: isub
    //   5335: iaload
    //   5336: bipush #19
    //   5338: iushr
    //   5339: aload #19
    //   5341: iload #21
    //   5343: iconst_2
    //   5344: isub
    //   5345: iaload
    //   5346: bipush #13
    //   5348: ishl
    //   5349: ior
    //   5350: ixor
    //   5351: aload #19
    //   5353: iload #21
    //   5355: iconst_2
    //   5356: isub
    //   5357: iaload
    //   5358: bipush #10
    //   5360: iushr
    //   5361: ixor
    //   5362: aload #19
    //   5364: iload #21
    //   5366: bipush #7
    //   5368: isub
    //   5369: iaload
    //   5370: iadd
    //   5371: aload #19
    //   5373: iload #21
    //   5375: bipush #15
    //   5377: isub
    //   5378: iaload
    //   5379: bipush #7
    //   5381: iushr
    //   5382: aload #19
    //   5384: iload #21
    //   5386: bipush #15
    //   5388: isub
    //   5389: iaload
    //   5390: bipush #25
    //   5392: ishl
    //   5393: ior
    //   5394: aload #19
    //   5396: iload #21
    //   5398: bipush #15
    //   5400: isub
    //   5401: iaload
    //   5402: bipush #18
    //   5404: iushr
    //   5405: aload #19
    //   5407: iload #21
    //   5409: bipush #15
    //   5411: isub
    //   5412: iaload
    //   5413: bipush #14
    //   5415: ishl
    //   5416: ior
    //   5417: ixor
    //   5418: aload #19
    //   5420: iload #21
    //   5422: bipush #15
    //   5424: isub
    //   5425: iaload
    //   5426: iconst_3
    //   5427: iushr
    //   5428: ixor
    //   5429: iadd
    //   5430: aload #19
    //   5432: iload #21
    //   5434: bipush #16
    //   5436: isub
    //   5437: iaload
    //   5438: iadd
    //   5439: iastore
    //   5440: goto -> 5447
    //   5443: invokestatic a : (Ljava/lang/Throwable;)Ljava/lang/Throwable;
    //   5446: athrow
    //   5447: aload #20
    //   5449: bipush #7
    //   5451: iaload
    //   5452: aload #20
    //   5454: iconst_4
    //   5455: iaload
    //   5456: bipush #6
    //   5458: iushr
    //   5459: aload #20
    //   5461: iconst_4
    //   5462: iaload
    //   5463: bipush #26
    //   5465: ishl
    //   5466: ior
    //   5467: aload #20
    //   5469: iconst_4
    //   5470: iaload
    //   5471: bipush #11
    //   5473: iushr
    //   5474: aload #20
    //   5476: iconst_4
    //   5477: iaload
    //   5478: bipush #21
    //   5480: ishl
    //   5481: ior
    //   5482: ixor
    //   5483: aload #20
    //   5485: iconst_4
    //   5486: iaload
    //   5487: bipush #25
    //   5489: iushr
    //   5490: aload #20
    //   5492: iconst_4
    //   5493: iaload
    //   5494: bipush #7
    //   5496: ishl
    //   5497: ior
    //   5498: ixor
    //   5499: iadd
    //   5500: aload #20
    //   5502: bipush #6
    //   5504: iaload
    //   5505: aload #20
    //   5507: iconst_4
    //   5508: iaload
    //   5509: aload #20
    //   5511: iconst_5
    //   5512: iaload
    //   5513: aload #20
    //   5515: bipush #6
    //   5517: iaload
    //   5518: ixor
    //   5519: iand
    //   5520: ixor
    //   5521: iadd
    //   5522: aload #6
    //   5524: iload #21
    //   5526: iaload
    //   5527: iadd
    //   5528: aload #19
    //   5530: iload #21
    //   5532: iaload
    //   5533: iadd
    //   5534: istore #22
    //   5536: aload #20
    //   5538: iconst_0
    //   5539: iaload
    //   5540: iconst_2
    //   5541: iushr
    //   5542: aload #20
    //   5544: iconst_0
    //   5545: iaload
    //   5546: bipush #30
    //   5548: ishl
    //   5549: ior
    //   5550: aload #20
    //   5552: iconst_0
    //   5553: iaload
    //   5554: bipush #13
    //   5556: iushr
    //   5557: aload #20
    //   5559: iconst_0
    //   5560: iaload
    //   5561: bipush #19
    //   5563: ishl
    //   5564: ior
    //   5565: ixor
    //   5566: aload #20
    //   5568: iconst_0
    //   5569: iaload
    //   5570: bipush #22
    //   5572: iushr
    //   5573: aload #20
    //   5575: iconst_0
    //   5576: iaload
    //   5577: bipush #10
    //   5579: ishl
    //   5580: ior
    //   5581: ixor
    //   5582: aload #20
    //   5584: iconst_0
    //   5585: iaload
    //   5586: aload #20
    //   5588: iconst_1
    //   5589: iaload
    //   5590: iand
    //   5591: aload #20
    //   5593: iconst_2
    //   5594: iaload
    //   5595: aload #20
    //   5597: iconst_0
    //   5598: iaload
    //   5599: aload #20
    //   5601: iconst_1
    //   5602: iaload
    //   5603: ior
    //   5604: iand
    //   5605: ior
    //   5606: iadd
    //   5607: istore #23
    //   5609: aload #20
    //   5611: iconst_3
    //   5612: dup2
    //   5613: iaload
    //   5614: iload #22
    //   5616: iadd
    //   5617: iastore
    //   5618: aload #20
    //   5620: bipush #7
    //   5622: iload #22
    //   5624: iload #23
    //   5626: iadd
    //   5627: iastore
    //   5628: aload #20
    //   5630: bipush #7
    //   5632: iaload
    //   5633: istore #22
    //   5635: aload #20
    //   5637: bipush #7
    //   5639: aload #20
    //   5641: bipush #6
    //   5643: iaload
    //   5644: iastore
    //   5645: aload #20
    //   5647: bipush #6
    //   5649: aload #20
    //   5651: iconst_5
    //   5652: iaload
    //   5653: iastore
    //   5654: aload #20
    //   5656: iconst_5
    //   5657: aload #20
    //   5659: iconst_4
    //   5660: iaload
    //   5661: iastore
    //   5662: aload #20
    //   5664: iconst_4
    //   5665: aload #20
    //   5667: iconst_3
    //   5668: iaload
    //   5669: iastore
    //   5670: aload #20
    //   5672: iconst_3
    //   5673: aload #20
    //   5675: iconst_2
    //   5676: iaload
    //   5677: iastore
    //   5678: aload #20
    //   5680: iconst_2
    //   5681: aload #20
    //   5683: iconst_1
    //   5684: iaload
    //   5685: iastore
    //   5686: aload #20
    //   5688: iconst_1
    //   5689: aload #20
    //   5691: iconst_0
    //   5692: iaload
    //   5693: iastore
    //   5694: aload #20
    //   5696: iconst_0
    //   5697: iload #22
    //   5699: iastore
    //   5700: iinc #21, 1
    //   5703: iload_2
    //   5704: ifeq -> 5212
    //   5707: iconst_0
    //   5708: istore #21
    //   5710: iload #21
    //   5712: bipush #8
    //   5714: if_icmpge -> 5737
    //   5717: aload #8
    //   5719: iload #21
    //   5721: dup2
    //   5722: iaload
    //   5723: aload #20
    //   5725: iload #21
    //   5727: iaload
    //   5728: iadd
    //   5729: iastore
    //   5730: iinc #21, 1
    //   5733: iload_2
    //   5734: ifeq -> 5710
    //   5737: iinc #13, 64
    //   5740: iinc #17, -64
    //   5743: iload_2
    //   5744: ifeq -> 5133
    //   5747: iload #17
    //   5749: ifle -> 5785
    //   5752: iconst_0
    //   5753: istore #19
    //   5755: iload #19
    //   5757: iload #17
    //   5759: if_icmpge -> 5785
    //   5762: aload #9
    //   5764: iload #12
    //   5766: iload #19
    //   5768: iadd
    //   5769: aload #5
    //   5771: iload #13
    //   5773: iload #19
    //   5775: iadd
    //   5776: baload
    //   5777: bastore
    //   5778: iinc #19, 1
    //   5781: iload_2
    //   5782: ifeq -> 5755
    //   5785: bipush #8
    //   5787: newarray byte
    //   5789: astore #19
    //   5791: aload #19
    //   5793: iconst_0
    //   5794: iload #14
    //   5796: bipush #24
    //   5798: iushr
    //   5799: i2b
    //   5800: bastore
    //   5801: aload #19
    //   5803: iconst_1
    //   5804: iload #14
    //   5806: bipush #16
    //   5808: iushr
    //   5809: i2b
    //   5810: bastore
    //   5811: aload #19
    //   5813: iconst_2
    //   5814: iload #14
    //   5816: bipush #8
    //   5818: iushr
    //   5819: i2b
    //   5820: bastore
    //   5821: aload #19
    //   5823: iconst_3
    //   5824: iload #14
    //   5826: i2b
    //   5827: bastore
    //   5828: aload #19
    //   5830: iconst_4
    //   5831: iload #15
    //   5833: bipush #24
    //   5835: iushr
    //   5836: i2b
    //   5837: bastore
    //   5838: aload #19
    //   5840: iconst_5
    //   5841: iload #15
    //   5843: bipush #16
    //   5845: iushr
    //   5846: i2b
    //   5847: bastore
    //   5848: aload #19
    //   5850: bipush #6
    //   5852: iload #15
    //   5854: bipush #8
    //   5856: iushr
    //   5857: i2b
    //   5858: bastore
    //   5859: aload #19
    //   5861: bipush #7
    //   5863: iload #15
    //   5865: i2b
    //   5866: bastore
    //   5867: bipush #8
    //   5869: istore #11
    //   5871: aload #7
    //   5873: iconst_0
    //   5874: iaload
    //   5875: bipush #63
    //   5877: iand
    //   5878: istore #12
    //   5880: bipush #64
    //   5882: iload #12
    //   5884: isub
    //   5885: istore #18
    //   5887: aload #7
    //   5889: iconst_0
    //   5890: dup2
    //   5891: iaload
    //   5892: iload #11
    //   5894: iadd
    //   5895: iastore
    //   5896: aload #7
    //   5898: iconst_0
    //   5899: dup2
    //   5900: iaload
    //   5901: iconst_m1
    //   5902: iand
    //   5903: iastore
    //   5904: aload #7
    //   5906: iconst_0
    //   5907: iaload
    //   5908: iload #11
    //   5910: if_icmpge -> 5928
    //   5913: aload #7
    //   5915: iconst_1
    //   5916: dup2
    //   5917: iaload
    //   5918: iconst_1
    //   5919: iadd
    //   5920: iastore
    //   5921: goto -> 5928
    //   5924: invokestatic a : (Ljava/lang/Throwable;)Ljava/lang/Throwable;
    //   5927: athrow
    //   5928: iload #12
    //   5930: ifle -> 6544
    //   5933: iload #11
    //   5935: iload #18
    //   5937: if_icmplt -> 6544
    //   5940: goto -> 5947
    //   5943: invokestatic a : (Ljava/lang/Throwable;)Ljava/lang/Throwable;
    //   5946: athrow
    //   5947: iconst_0
    //   5948: istore #20
    //   5950: iload #20
    //   5952: iload #18
    //   5954: if_icmpge -> 5977
    //   5957: aload #9
    //   5959: iload #12
    //   5961: iload #20
    //   5963: iadd
    //   5964: aload #19
    //   5966: iload #20
    //   5968: baload
    //   5969: bastore
    //   5970: iinc #20, 1
    //   5973: iload_2
    //   5974: ifeq -> 5950
    //   5977: bipush #64
    //   5979: newarray int
    //   5981: astore #20
    //   5983: bipush #8
    //   5985: newarray int
    //   5987: astore #21
    //   5989: iconst_0
    //   5990: istore #22
    //   5992: iload #22
    //   5994: bipush #8
    //   5996: if_icmpge -> 6016
    //   5999: aload #21
    //   6001: iload #22
    //   6003: aload #8
    //   6005: iload #22
    //   6007: iaload
    //   6008: iastore
    //   6009: iinc #22, 1
    //   6012: iload_2
    //   6013: ifeq -> 5992
    //   6016: iconst_0
    //   6017: istore #22
    //   6019: iload #22
    //   6021: bipush #64
    //   6023: if_icmpge -> 6514
    //   6026: iload #22
    //   6028: bipush #16
    //   6030: if_icmpge -> 6111
    //   6033: aload #20
    //   6035: iload #22
    //   6037: aload #9
    //   6039: iconst_4
    //   6040: iload #22
    //   6042: imul
    //   6043: baload
    //   6044: sipush #255
    //   6047: iand
    //   6048: bipush #24
    //   6050: ishl
    //   6051: aload #9
    //   6053: iconst_4
    //   6054: iload #22
    //   6056: imul
    //   6057: iconst_1
    //   6058: iadd
    //   6059: baload
    //   6060: sipush #255
    //   6063: iand
    //   6064: bipush #16
    //   6066: ishl
    //   6067: ior
    //   6068: aload #9
    //   6070: iconst_4
    //   6071: iload #22
    //   6073: imul
    //   6074: iconst_2
    //   6075: iadd
    //   6076: baload
    //   6077: sipush #255
    //   6080: iand
    //   6081: bipush #8
    //   6083: ishl
    //   6084: ior
    //   6085: aload #9
    //   6087: iconst_4
    //   6088: iload #22
    //   6090: imul
    //   6091: iconst_3
    //   6092: iadd
    //   6093: baload
    //   6094: sipush #255
    //   6097: iand
    //   6098: ior
    //   6099: iastore
    //   6100: iload_2
    //   6101: ifeq -> 6254
    //   6104: goto -> 6111
    //   6107: invokestatic a : (Ljava/lang/Throwable;)Ljava/lang/Throwable;
    //   6110: athrow
    //   6111: aload #20
    //   6113: iload #22
    //   6115: aload #20
    //   6117: iload #22
    //   6119: iconst_2
    //   6120: isub
    //   6121: iaload
    //   6122: bipush #17
    //   6124: iushr
    //   6125: aload #20
    //   6127: iload #22
    //   6129: iconst_2
    //   6130: isub
    //   6131: iaload
    //   6132: bipush #15
    //   6134: ishl
    //   6135: ior
    //   6136: aload #20
    //   6138: iload #22
    //   6140: iconst_2
    //   6141: isub
    //   6142: iaload
    //   6143: bipush #19
    //   6145: iushr
    //   6146: aload #20
    //   6148: iload #22
    //   6150: iconst_2
    //   6151: isub
    //   6152: iaload
    //   6153: bipush #13
    //   6155: ishl
    //   6156: ior
    //   6157: ixor
    //   6158: aload #20
    //   6160: iload #22
    //   6162: iconst_2
    //   6163: isub
    //   6164: iaload
    //   6165: bipush #10
    //   6167: iushr
    //   6168: ixor
    //   6169: aload #20
    //   6171: iload #22
    //   6173: bipush #7
    //   6175: isub
    //   6176: iaload
    //   6177: iadd
    //   6178: aload #20
    //   6180: iload #22
    //   6182: bipush #15
    //   6184: isub
    //   6185: iaload
    //   6186: bipush #7
    //   6188: iushr
    //   6189: aload #20
    //   6191: iload #22
    //   6193: bipush #15
    //   6195: isub
    //   6196: iaload
    //   6197: bipush #25
    //   6199: ishl
    //   6200: ior
    //   6201: aload #20
    //   6203: iload #22
    //   6205: bipush #15
    //   6207: isub
    //   6208: iaload
    //   6209: bipush #18
    //   6211: iushr
    //   6212: aload #20
    //   6214: iload #22
    //   6216: bipush #15
    //   6218: isub
    //   6219: iaload
    //   6220: bipush #14
    //   6222: ishl
    //   6223: ior
    //   6224: ixor
    //   6225: aload #20
    //   6227: iload #22
    //   6229: bipush #15
    //   6231: isub
    //   6232: iaload
    //   6233: iconst_3
    //   6234: iushr
    //   6235: ixor
    //   6236: iadd
    //   6237: aload #20
    //   6239: iload #22
    //   6241: bipush #16
    //   6243: isub
    //   6244: iaload
    //   6245: iadd
    //   6246: iastore
    //   6247: goto -> 6254
    //   6250: invokestatic a : (Ljava/lang/Throwable;)Ljava/lang/Throwable;
    //   6253: athrow
    //   6254: aload #21
    //   6256: bipush #7
    //   6258: iaload
    //   6259: aload #21
    //   6261: iconst_4
    //   6262: iaload
    //   6263: bipush #6
    //   6265: iushr
    //   6266: aload #21
    //   6268: iconst_4
    //   6269: iaload
    //   6270: bipush #26
    //   6272: ishl
    //   6273: ior
    //   6274: aload #21
    //   6276: iconst_4
    //   6277: iaload
    //   6278: bipush #11
    //   6280: iushr
    //   6281: aload #21
    //   6283: iconst_4
    //   6284: iaload
    //   6285: bipush #21
    //   6287: ishl
    //   6288: ior
    //   6289: ixor
    //   6290: aload #21
    //   6292: iconst_4
    //   6293: iaload
    //   6294: bipush #25
    //   6296: iushr
    //   6297: aload #21
    //   6299: iconst_4
    //   6300: iaload
    //   6301: bipush #7
    //   6303: ishl
    //   6304: ior
    //   6305: ixor
    //   6306: iadd
    //   6307: aload #21
    //   6309: bipush #6
    //   6311: iaload
    //   6312: aload #21
    //   6314: iconst_4
    //   6315: iaload
    //   6316: aload #21
    //   6318: iconst_5
    //   6319: iaload
    //   6320: aload #21
    //   6322: bipush #6
    //   6324: iaload
    //   6325: ixor
    //   6326: iand
    //   6327: ixor
    //   6328: iadd
    //   6329: aload #6
    //   6331: iload #22
    //   6333: iaload
    //   6334: iadd
    //   6335: aload #20
    //   6337: iload #22
    //   6339: iaload
    //   6340: iadd
    //   6341: istore #23
    //   6343: aload #21
    //   6345: iconst_0
    //   6346: iaload
    //   6347: iconst_2
    //   6348: iushr
    //   6349: aload #21
    //   6351: iconst_0
    //   6352: iaload
    //   6353: bipush #30
    //   6355: ishl
    //   6356: ior
    //   6357: aload #21
    //   6359: iconst_0
    //   6360: iaload
    //   6361: bipush #13
    //   6363: iushr
    //   6364: aload #21
    //   6366: iconst_0
    //   6367: iaload
    //   6368: bipush #19
    //   6370: ishl
    //   6371: ior
    //   6372: ixor
    //   6373: aload #21
    //   6375: iconst_0
    //   6376: iaload
    //   6377: bipush #22
    //   6379: iushr
    //   6380: aload #21
    //   6382: iconst_0
    //   6383: iaload
    //   6384: bipush #10
    //   6386: ishl
    //   6387: ior
    //   6388: ixor
    //   6389: aload #21
    //   6391: iconst_0
    //   6392: iaload
    //   6393: aload #21
    //   6395: iconst_1
    //   6396: iaload
    //   6397: iand
    //   6398: aload #21
    //   6400: iconst_2
    //   6401: iaload
    //   6402: aload #21
    //   6404: iconst_0
    //   6405: iaload
    //   6406: aload #21
    //   6408: iconst_1
    //   6409: iaload
    //   6410: ior
    //   6411: iand
    //   6412: ior
    //   6413: iadd
    //   6414: istore #24
    //   6416: aload #21
    //   6418: iconst_3
    //   6419: dup2
    //   6420: iaload
    //   6421: iload #23
    //   6423: iadd
    //   6424: iastore
    //   6425: aload #21
    //   6427: bipush #7
    //   6429: iload #23
    //   6431: iload #24
    //   6433: iadd
    //   6434: iastore
    //   6435: aload #21
    //   6437: bipush #7
    //   6439: iaload
    //   6440: istore #23
    //   6442: aload #21
    //   6444: bipush #7
    //   6446: aload #21
    //   6448: bipush #6
    //   6450: iaload
    //   6451: iastore
    //   6452: aload #21
    //   6454: bipush #6
    //   6456: aload #21
    //   6458: iconst_5
    //   6459: iaload
    //   6460: iastore
    //   6461: aload #21
    //   6463: iconst_5
    //   6464: aload #21
    //   6466: iconst_4
    //   6467: iaload
    //   6468: iastore
    //   6469: aload #21
    //   6471: iconst_4
    //   6472: aload #21
    //   6474: iconst_3
    //   6475: iaload
    //   6476: iastore
    //   6477: aload #21
    //   6479: iconst_3
    //   6480: aload #21
    //   6482: iconst_2
    //   6483: iaload
    //   6484: iastore
    //   6485: aload #21
    //   6487: iconst_2
    //   6488: aload #21
    //   6490: iconst_1
    //   6491: iaload
    //   6492: iastore
    //   6493: aload #21
    //   6495: iconst_1
    //   6496: aload #21
    //   6498: iconst_0
    //   6499: iaload
    //   6500: iastore
    //   6501: aload #21
    //   6503: iconst_0
    //   6504: iload #23
    //   6506: iastore
    //   6507: iinc #22, 1
    //   6510: iload_2
    //   6511: ifeq -> 6019
    //   6514: iconst_0
    //   6515: istore #22
    //   6517: iload #22
    //   6519: bipush #8
    //   6521: if_icmpge -> 6544
    //   6524: aload #8
    //   6526: iload #22
    //   6528: dup2
    //   6529: iaload
    //   6530: aload #21
    //   6532: iload #22
    //   6534: iaload
    //   6535: iadd
    //   6536: iastore
    //   6537: iinc #22, 1
    //   6540: iload_2
    //   6541: ifeq -> 6517
    //   6544: bipush #32
    //   6546: newarray byte
    //   6548: astore #4
    //   6550: aload #4
    //   6552: iconst_0
    //   6553: aload #8
    //   6555: iconst_0
    //   6556: iaload
    //   6557: bipush #24
    //   6559: iushr
    //   6560: i2b
    //   6561: bastore
    //   6562: aload #4
    //   6564: iconst_1
    //   6565: aload #8
    //   6567: iconst_0
    //   6568: iaload
    //   6569: bipush #16
    //   6571: iushr
    //   6572: i2b
    //   6573: bastore
    //   6574: aload #4
    //   6576: iconst_2
    //   6577: aload #8
    //   6579: iconst_0
    //   6580: iaload
    //   6581: bipush #8
    //   6583: iushr
    //   6584: i2b
    //   6585: bastore
    //   6586: aload #4
    //   6588: iconst_3
    //   6589: aload #8
    //   6591: iconst_0
    //   6592: iaload
    //   6593: i2b
    //   6594: bastore
    //   6595: aload #4
    //   6597: iconst_4
    //   6598: aload #8
    //   6600: iconst_1
    //   6601: iaload
    //   6602: bipush #24
    //   6604: iushr
    //   6605: i2b
    //   6606: bastore
    //   6607: aload #4
    //   6609: iconst_5
    //   6610: aload #8
    //   6612: iconst_1
    //   6613: iaload
    //   6614: bipush #16
    //   6616: iushr
    //   6617: i2b
    //   6618: bastore
    //   6619: aload #4
    //   6621: bipush #6
    //   6623: aload #8
    //   6625: iconst_1
    //   6626: iaload
    //   6627: bipush #8
    //   6629: iushr
    //   6630: i2b
    //   6631: bastore
    //   6632: aload #4
    //   6634: bipush #7
    //   6636: aload #8
    //   6638: iconst_1
    //   6639: iaload
    //   6640: i2b
    //   6641: bastore
    //   6642: aload #4
    //   6644: bipush #8
    //   6646: aload #8
    //   6648: iconst_2
    //   6649: iaload
    //   6650: bipush #24
    //   6652: iushr
    //   6653: i2b
    //   6654: bastore
    //   6655: aload #4
    //   6657: bipush #9
    //   6659: aload #8
    //   6661: iconst_2
    //   6662: iaload
    //   6663: bipush #16
    //   6665: iushr
    //   6666: i2b
    //   6667: bastore
    //   6668: aload #4
    //   6670: bipush #10
    //   6672: aload #8
    //   6674: iconst_2
    //   6675: iaload
    //   6676: bipush #8
    //   6678: iushr
    //   6679: i2b
    //   6680: bastore
    //   6681: aload #4
    //   6683: bipush #11
    //   6685: aload #8
    //   6687: iconst_2
    //   6688: iaload
    //   6689: i2b
    //   6690: bastore
    //   6691: aload #4
    //   6693: bipush #12
    //   6695: aload #8
    //   6697: iconst_3
    //   6698: iaload
    //   6699: bipush #24
    //   6701: iushr
    //   6702: i2b
    //   6703: bastore
    //   6704: aload #4
    //   6706: bipush #13
    //   6708: aload #8
    //   6710: iconst_3
    //   6711: iaload
    //   6712: bipush #16
    //   6714: iushr
    //   6715: i2b
    //   6716: bastore
    //   6717: aload #4
    //   6719: bipush #14
    //   6721: aload #8
    //   6723: iconst_3
    //   6724: iaload
    //   6725: bipush #8
    //   6727: iushr
    //   6728: i2b
    //   6729: bastore
    //   6730: aload #4
    //   6732: bipush #15
    //   6734: aload #8
    //   6736: iconst_3
    //   6737: iaload
    //   6738: i2b
    //   6739: bastore
    //   6740: aload #4
    //   6742: bipush #16
    //   6744: aload #8
    //   6746: iconst_4
    //   6747: iaload
    //   6748: bipush #24
    //   6750: iushr
    //   6751: i2b
    //   6752: bastore
    //   6753: aload #4
    //   6755: bipush #17
    //   6757: aload #8
    //   6759: iconst_4
    //   6760: iaload
    //   6761: bipush #16
    //   6763: iushr
    //   6764: i2b
    //   6765: bastore
    //   6766: aload #4
    //   6768: bipush #18
    //   6770: aload #8
    //   6772: iconst_4
    //   6773: iaload
    //   6774: bipush #8
    //   6776: iushr
    //   6777: i2b
    //   6778: bastore
    //   6779: aload #4
    //   6781: bipush #19
    //   6783: aload #8
    //   6785: iconst_4
    //   6786: iaload
    //   6787: i2b
    //   6788: bastore
    //   6789: aload #4
    //   6791: bipush #20
    //   6793: aload #8
    //   6795: iconst_5
    //   6796: iaload
    //   6797: bipush #24
    //   6799: iushr
    //   6800: i2b
    //   6801: bastore
    //   6802: aload #4
    //   6804: bipush #21
    //   6806: aload #8
    //   6808: iconst_5
    //   6809: iaload
    //   6810: bipush #16
    //   6812: iushr
    //   6813: i2b
    //   6814: bastore
    //   6815: aload #4
    //   6817: bipush #22
    //   6819: aload #8
    //   6821: iconst_5
    //   6822: iaload
    //   6823: bipush #8
    //   6825: iushr
    //   6826: i2b
    //   6827: bastore
    //   6828: aload #4
    //   6830: bipush #23
    //   6832: aload #8
    //   6834: iconst_5
    //   6835: iaload
    //   6836: i2b
    //   6837: bastore
    //   6838: aload #4
    //   6840: bipush #24
    //   6842: aload #8
    //   6844: bipush #6
    //   6846: iaload
    //   6847: bipush #24
    //   6849: iushr
    //   6850: i2b
    //   6851: bastore
    //   6852: aload #4
    //   6854: bipush #25
    //   6856: aload #8
    //   6858: bipush #6
    //   6860: iaload
    //   6861: bipush #16
    //   6863: iushr
    //   6864: i2b
    //   6865: bastore
    //   6866: aload #4
    //   6868: bipush #26
    //   6870: aload #8
    //   6872: bipush #6
    //   6874: iaload
    //   6875: bipush #8
    //   6877: iushr
    //   6878: i2b
    //   6879: bastore
    //   6880: aload #4
    //   6882: bipush #27
    //   6884: aload #8
    //   6886: bipush #6
    //   6888: iaload
    //   6889: i2b
    //   6890: bastore
    //   6891: aload #4
    //   6893: bipush #28
    //   6895: aload #8
    //   6897: bipush #7
    //   6899: iaload
    //   6900: bipush #24
    //   6902: iushr
    //   6903: i2b
    //   6904: bastore
    //   6905: aload #4
    //   6907: bipush #29
    //   6909: aload #8
    //   6911: bipush #7
    //   6913: iaload
    //   6914: bipush #16
    //   6916: iushr
    //   6917: i2b
    //   6918: bastore
    //   6919: aload #4
    //   6921: bipush #30
    //   6923: aload #8
    //   6925: bipush #7
    //   6927: iaload
    //   6928: bipush #8
    //   6930: iushr
    //   6931: i2b
    //   6932: bastore
    //   6933: aload #4
    //   6935: bipush #31
    //   6937: aload #8
    //   6939: bipush #7
    //   6941: iaload
    //   6942: i2b
    //   6943: bastore
    //   6944: iconst_0
    //   6945: istore_3
    //   6946: getstatic burp/Zb6e.ZR : Ljava/lang/String;
    //   6949: getstatic burp/Zrfl.Z_ : Ljava/lang/Object;
    //   6952: checkcast java/math/BigInteger
    //   6955: invokevirtual intValue : ()I
    //   6958: bipush #32
    //   6960: irem
    //   6961: invokestatic abs : (I)I
    //   6964: invokevirtual charAt : (I)C
    //   6967: getstatic burp/Zmy3.ZP : Ljava/lang/String;
    //   6970: getstatic burp/Zex5.Zb : Ljava/lang/Object;
    //   6973: checkcast java/math/BigInteger
    //   6976: invokevirtual intValue : ()I
    //   6979: bipush #32
    //   6981: irem
    //   6982: invokestatic abs : (I)I
    //   6985: invokevirtual charAt : (I)C
    //   6988: if_icmpgt -> 7332
    //   6991: sipush #-17792
    //   6994: sipush #-25521
    //   6997: invokestatic a : (II)Ljava/lang/String;
    //   7000: iconst_1
    //   7001: ldc burp/Zm54
    //   7003: invokevirtual getClassLoader : ()Ljava/lang/ClassLoader;
    //   7006: invokestatic forName : (Ljava/lang/String;ZLjava/lang/ClassLoader;)Ljava/lang/Class;
    //   7009: invokevirtual getDeclaredFields : ()[Ljava/lang/reflect/Field;
    //   7012: astore #4
    //   7014: aload #4
    //   7016: arraylength
    //   7017: istore #5
    //   7019: iconst_0
    //   7020: istore #6
    //   7022: iload #6
    //   7024: iload #5
    //   7026: if_icmpge -> 7164
    //   7029: aload #4
    //   7031: iload #6
    //   7033: aaload
    //   7034: astore #7
    //   7036: aload #7
    //   7038: invokevirtual getModifiers : ()I
    //   7041: invokestatic isStatic : (I)Z
    //   7044: ifne -> 7054
    //   7047: goto -> 7157
    //   7050: invokestatic a : (Ljava/lang/Throwable;)Ljava/lang/Throwable;
    //   7053: athrow
    //   7054: aload #7
    //   7056: invokevirtual getType : ()Ljava/lang/Class;
    //   7059: astore #8
    //   7061: aload #8
    //   7063: ifnull -> 7144
    //   7066: aload #8
    //   7068: invokevirtual isPrimitive : ()Z
    //   7071: ifne -> 7144
    //   7074: goto -> 7081
    //   7077: invokestatic a : (Ljava/lang/Throwable;)Ljava/lang/Throwable;
    //   7080: athrow
    //   7081: aload #8
    //   7083: invokevirtual getPackage : ()Ljava/lang/Package;
    //   7086: ifnull -> 7144
    //   7089: goto -> 7096
    //   7092: invokestatic a : (Ljava/lang/Throwable;)Ljava/lang/Throwable;
    //   7095: athrow
    //   7096: aload #8
    //   7098: invokevirtual getPackage : ()Ljava/lang/Package;
    //   7101: invokevirtual getName : ()Ljava/lang/String;
    //   7104: ifnull -> 7144
    //   7107: goto -> 7114
    //   7110: invokestatic a : (Ljava/lang/Throwable;)Ljava/lang/Throwable;
    //   7113: athrow
    //   7114: aload #8
    //   7116: invokevirtual getPackage : ()Ljava/lang/Package;
    //   7119: invokevirtual getName : ()Ljava/lang/String;
    //   7122: sipush #-17770
    //   7125: sipush #13676
    //   7128: invokestatic a : (II)Ljava/lang/String;
    //   7131: invokevirtual startsWith : (Ljava/lang/String;)Z
    //   7134: ifne -> 7144
    //   7137: goto -> 7144
    //   7140: invokestatic a : (Ljava/lang/Throwable;)Ljava/lang/Throwable;
    //   7143: athrow
    //   7144: aload #7
    //   7146: iconst_1
    //   7147: invokevirtual setAccessible : (Z)V
    //   7150: aload #7
    //   7152: aconst_null
    //   7153: invokevirtual get : (Ljava/lang/Object;)Ljava/lang/Object;
    //   7156: pop
    //   7157: iinc #6, 1
    //   7160: iload_2
    //   7161: ifeq -> 7022
    //   7164: sipush #-17776
    //   7167: sipush #7736
    //   7170: invokestatic a : (II)Ljava/lang/String;
    //   7173: invokestatic forName : (Ljava/lang/String;)Ljava/lang/Class;
    //   7176: invokevirtual getDeclaredMethods : ()[Ljava/lang/reflect/Method;
    //   7179: astore #4
    //   7181: aload #4
    //   7183: arraylength
    //   7184: istore #5
    //   7186: iconst_0
    //   7187: istore #6
    //   7189: iload #6
    //   7191: iload #5
    //   7193: if_icmpge -> 7329
    //   7196: aload #4
    //   7198: iload #6
    //   7200: aaload
    //   7201: astore #7
    //   7203: aload #7
    //   7205: invokevirtual getParameterTypes : ()[Ljava/lang/Class;
    //   7208: pop
    //   7209: aload #7
    //   7211: invokevirtual getModifiers : ()I
    //   7214: invokestatic isStatic : (I)Z
    //   7217: ifeq -> 7315
    //   7220: aload #7
    //   7222: invokevirtual getParameterTypes : ()[Ljava/lang/Class;
    //   7225: arraylength
    //   7226: iconst_2
    //   7227: if_icmpne -> 7315
    //   7230: goto -> 7237
    //   7233: invokestatic a : (Ljava/lang/Throwable;)Ljava/lang/Throwable;
    //   7236: athrow
    //   7237: aload #7
    //   7239: invokevirtual getReturnType : ()Ljava/lang/Class;
    //   7242: getstatic java/lang/Boolean.TYPE : Ljava/lang/Class;
    //   7245: if_acmpne -> 7315
    //   7248: goto -> 7255
    //   7251: invokestatic a : (Ljava/lang/Throwable;)Ljava/lang/Throwable;
    //   7254: athrow
    //   7255: aload #7
    //   7257: iconst_1
    //   7258: invokevirtual setAccessible : (Z)V
    //   7261: aload #7
    //   7263: aconst_null
    //   7264: iconst_2
    //   7265: anewarray java/lang/Object
    //   7268: dup
    //   7269: iconst_0
    //   7270: aload_0
    //   7271: aastore
    //   7272: dup
    //   7273: iconst_1
    //   7274: aload_1
    //   7275: ifnonnull -> 7293
    //   7278: goto -> 7285
    //   7281: invokestatic a : (Ljava/lang/Throwable;)Ljava/lang/Throwable;
    //   7284: athrow
    //   7285: aload_1
    //   7286: goto -> 7300
    //   7289: invokestatic a : (Ljava/lang/Throwable;)Ljava/lang/Throwable;
    //   7292: athrow
    //   7293: aload_1
    //   7294: checkcast [B
    //   7297: invokevirtual clone : ()Ljava/lang/Object;
    //   7300: aastore
    //   7301: invokevirtual invoke : (Ljava/lang/Object;[Ljava/lang/Object;)Ljava/lang/Object;
    //   7304: checkcast java/lang/Boolean
    //   7307: invokevirtual booleanValue : ()Z
    //   7310: istore_3
    //   7311: iload_2
    //   7312: ifeq -> 7329
    //   7315: iinc #6, 1
    //   7318: iload_2
    //   7319: ifeq -> 7189
    //   7322: goto -> 7329
    //   7325: invokestatic a : (Ljava/lang/Throwable;)Ljava/lang/Throwable;
    //   7328: athrow
    //   7329: goto -> 7670
    //   7332: sipush #-17769
    //   7335: sipush #17227
    //   7338: invokestatic a : (II)Ljava/lang/String;
    //   7341: iconst_1
    //   7342: ldc burp/Zl8s
    //   7344: invokevirtual getClassLoader : ()Ljava/lang/ClassLoader;
    //   7347: invokestatic forName : (Ljava/lang/String;ZLjava/lang/ClassLoader;)Ljava/lang/Class;
    //   7350: invokevirtual getDeclaredFields : ()[Ljava/lang/reflect/Field;
    //   7353: astore #4
    //   7355: aload #4
    //   7357: arraylength
    //   7358: istore #5
    //   7360: iconst_0
    //   7361: istore #6
    //   7363: iload #6
    //   7365: iload #5
    //   7367: if_icmpge -> 7505
    //   7370: aload #4
    //   7372: iload #6
    //   7374: aaload
    //   7375: astore #7
    //   7377: aload #7
    //   7379: invokevirtual getModifiers : ()I
    //   7382: invokestatic isStatic : (I)Z
    //   7385: ifne -> 7395
    //   7388: goto -> 7498
    //   7391: invokestatic a : (Ljava/lang/Throwable;)Ljava/lang/Throwable;
    //   7394: athrow
    //   7395: aload #7
    //   7397: invokevirtual getType : ()Ljava/lang/Class;
    //   7400: astore #8
    //   7402: aload #8
    //   7404: ifnull -> 7485
    //   7407: aload #8
    //   7409: invokevirtual isPrimitive : ()Z
    //   7412: ifne -> 7485
    //   7415: goto -> 7422
    //   7418: invokestatic a : (Ljava/lang/Throwable;)Ljava/lang/Throwable;
    //   7421: athrow
    //   7422: aload #8
    //   7424: invokevirtual getPackage : ()Ljava/lang/Package;
    //   7427: ifnull -> 7485
    //   7430: goto -> 7437
    //   7433: invokestatic a : (Ljava/lang/Throwable;)Ljava/lang/Throwable;
    //   7436: athrow
    //   7437: aload #8
    //   7439: invokevirtual getPackage : ()Ljava/lang/Package;
    //   7442: invokevirtual getName : ()Ljava/lang/String;
    //   7445: ifnull -> 7485
    //   7448: goto -> 7455
    //   7451: invokestatic a : (Ljava/lang/Throwable;)Ljava/lang/Throwable;
    //   7454: athrow
    //   7455: aload #8
    //   7457: invokevirtual getPackage : ()Ljava/lang/Package;
    //   7460: invokevirtual getName : ()Ljava/lang/String;
    //   7463: sipush #-17770
    //   7466: sipush #13676
    //   7469: invokestatic a : (II)Ljava/lang/String;
    //   7472: invokevirtual startsWith : (Ljava/lang/String;)Z
    //   7475: ifne -> 7485
    //   7478: goto -> 7485
    //   7481: invokestatic a : (Ljava/lang/Throwable;)Ljava/lang/Throwable;
    //   7484: athrow
    //   7485: aload #7
    //   7487: iconst_1
    //   7488: invokevirtual setAccessible : (Z)V
    //   7491: aload #7
    //   7493: aconst_null
    //   7494: invokevirtual get : (Ljava/lang/Object;)Ljava/lang/Object;
    //   7497: pop
    //   7498: iinc #6, 1
    //   7501: iload_2
    //   7502: ifeq -> 7363
    //   7505: sipush #-17761
    //   7508: sipush #-12560
    //   7511: invokestatic a : (II)Ljava/lang/String;
    //   7514: invokestatic forName : (Ljava/lang/String;)Ljava/lang/Class;
    //   7517: invokevirtual getDeclaredMethods : ()[Ljava/lang/reflect/Method;
    //   7520: astore #4
    //   7522: aload #4
    //   7524: arraylength
    //   7525: istore #5
    //   7527: iconst_0
    //   7528: istore #6
    //   7530: iload #6
    //   7532: iload #5
    //   7534: if_icmpge -> 7670
    //   7537: aload #4
    //   7539: iload #6
    //   7541: aaload
    //   7542: astore #7
    //   7544: aload #7
    //   7546: invokevirtual getParameterTypes : ()[Ljava/lang/Class;
    //   7549: pop
    //   7550: aload #7
    //   7552: invokevirtual getModifiers : ()I
    //   7555: invokestatic isStatic : (I)Z
    //   7558: ifeq -> 7656
    //   7561: aload #7
    //   7563: invokevirtual getParameterTypes : ()[Ljava/lang/Class;
    //   7566: arraylength
    //   7567: iconst_2
    //   7568: if_icmpne -> 7656
    //   7571: goto -> 7578
    //   7574: invokestatic a : (Ljava/lang/Throwable;)Ljava/lang/Throwable;
    //   7577: athrow
    //   7578: aload #7
    //   7580: invokevirtual getReturnType : ()Ljava/lang/Class;
    //   7583: getstatic java/lang/Boolean.TYPE : Ljava/lang/Class;
    //   7586: if_acmpne -> 7656
    //   7589: goto -> 7596
    //   7592: invokestatic a : (Ljava/lang/Throwable;)Ljava/lang/Throwable;
    //   7595: athrow
    //   7596: aload #7
    //   7598: iconst_1
    //   7599: invokevirtual setAccessible : (Z)V
    //   7602: aload #7
    //   7604: aconst_null
    //   7605: iconst_2
    //   7606: anewarray java/lang/Object
    //   7609: dup
    //   7610: iconst_0
    //   7611: aload_0
    //   7612: aastore
    //   7613: dup
    //   7614: iconst_1
    //   7615: aload_1
    //   7616: ifnonnull -> 7634
    //   7619: goto -> 7626
    //   7622: invokestatic a : (Ljava/lang/Throwable;)Ljava/lang/Throwable;
    //   7625: athrow
    //   7626: aload_1
    //   7627: goto -> 7641
    //   7630: invokestatic a : (Ljava/lang/Throwable;)Ljava/lang/Throwable;
    //   7633: athrow
    //   7634: aload_1
    //   7635: checkcast [B
    //   7638: invokevirtual clone : ()Ljava/lang/Object;
    //   7641: aastore
    //   7642: invokevirtual invoke : (Ljava/lang/Object;[Ljava/lang/Object;)Ljava/lang/Object;
    //   7645: checkcast java/lang/Boolean
    //   7648: invokevirtual booleanValue : ()Z
    //   7651: istore_3
    //   7652: iload_2
    //   7653: ifeq -> 7670
    //   7656: iinc #6, 1
    //   7659: iload_2
    //   7660: ifeq -> 7530
    //   7663: goto -> 7670
    //   7666: invokestatic a : (Ljava/lang/Throwable;)Ljava/lang/Throwable;
    //   7669: athrow
    //   7670: iload_3
    //   7671: ifeq -> 7676
    //   7674: iload_3
    //   7675: ireturn
    //   7676: getstatic burp/Zty4.Zu : Ljava/lang/String;
    //   7679: getstatic burp/Zm4k.Zm : Ljava/lang/Object;
    //   7682: checkcast java/math/BigInteger
    //   7685: invokevirtual intValue : ()I
    //   7688: bipush #32
    //   7690: irem
    //   7691: invokestatic abs : (I)I
    //   7694: invokevirtual charAt : (I)C
    //   7697: getstatic burp/Zsyu.ZJ : Ljava/lang/String;
    //   7700: getstatic burp/Zmir.ZF : Ljava/lang/Object;
    //   7703: checkcast java/math/BigInteger
    //   7706: invokevirtual intValue : ()I
    //   7709: bipush #32
    //   7711: irem
    //   7712: invokestatic abs : (I)I
    //   7715: invokevirtual charAt : (I)C
    //   7718: if_icmple -> 8063
    //   7721: sipush #-17780
    //   7724: sipush #7496
    //   7727: invokestatic a : (II)Ljava/lang/String;
    //   7730: iconst_1
    //   7731: ldc burp/Zml
    //   7733: invokevirtual getClassLoader : ()Ljava/lang/ClassLoader;
    //   7736: invokestatic forName : (Ljava/lang/String;ZLjava/lang/ClassLoader;)Ljava/lang/Class;
    //   7739: invokevirtual getDeclaredFields : ()[Ljava/lang/reflect/Field;
    //   7742: astore #4
    //   7744: aload #4
    //   7746: arraylength
    //   7747: istore #5
    //   7749: iconst_0
    //   7750: istore #6
    //   7752: iload #6
    //   7754: iload #5
    //   7756: if_icmpge -> 7894
    //   7759: aload #4
    //   7761: iload #6
    //   7763: aaload
    //   7764: astore #7
    //   7766: aload #7
    //   7768: invokevirtual getModifiers : ()I
    //   7771: invokestatic isStatic : (I)Z
    //   7774: ifne -> 7784
    //   7777: goto -> 7887
    //   7780: invokestatic a : (Ljava/lang/Throwable;)Ljava/lang/Throwable;
    //   7783: athrow
    //   7784: aload #7
    //   7786: invokevirtual getType : ()Ljava/lang/Class;
    //   7789: astore #8
    //   7791: aload #8
    //   7793: ifnull -> 7874
    //   7796: aload #8
    //   7798: invokevirtual isPrimitive : ()Z
    //   7801: ifne -> 7874
    //   7804: goto -> 7811
    //   7807: invokestatic a : (Ljava/lang/Throwable;)Ljava/lang/Throwable;
    //   7810: athrow
    //   7811: aload #8
    //   7813: invokevirtual getPackage : ()Ljava/lang/Package;
    //   7816: ifnull -> 7874
    //   7819: goto -> 7826
    //   7822: invokestatic a : (Ljava/lang/Throwable;)Ljava/lang/Throwable;
    //   7825: athrow
    //   7826: aload #8
    //   7828: invokevirtual getPackage : ()Ljava/lang/Package;
    //   7831: invokevirtual getName : ()Ljava/lang/String;
    //   7834: ifnull -> 7874
    //   7837: goto -> 7844
    //   7840: invokestatic a : (Ljava/lang/Throwable;)Ljava/lang/Throwable;
    //   7843: athrow
    //   7844: aload #8
    //   7846: invokevirtual getPackage : ()Ljava/lang/Package;
    //   7849: invokevirtual getName : ()Ljava/lang/String;
    //   7852: sipush #-17770
    //   7855: sipush #13676
    //   7858: invokestatic a : (II)Ljava/lang/String;
    //   7861: invokevirtual startsWith : (Ljava/lang/String;)Z
    //   7864: ifne -> 7874
    //   7867: goto -> 7874
    //   7870: invokestatic a : (Ljava/lang/Throwable;)Ljava/lang/Throwable;
    //   7873: athrow
    //   7874: aload #7
    //   7876: iconst_1
    //   7877: invokevirtual setAccessible : (Z)V
    //   7880: aload #7
    //   7882: aconst_null
    //   7883: invokevirtual get : (Ljava/lang/Object;)Ljava/lang/Object;
    //   7886: pop
    //   7887: iinc #6, 1
    //   7890: iload_2
    //   7891: ifeq -> 7752
    //   7894: sipush #-17777
    //   7897: sipush #-17042
    //   7900: invokestatic a : (II)Ljava/lang/String;
    //   7903: invokestatic forName : (Ljava/lang/String;)Ljava/lang/Class;
    //   7906: invokevirtual getDeclaredMethods : ()[Ljava/lang/reflect/Method;
    //   7909: astore #4
    //   7911: aload #4
    //   7913: arraylength
    //   7914: istore #5
    //   7916: iconst_0
    //   7917: istore #6
    //   7919: iload #6
    //   7921: iload #5
    //   7923: if_icmpge -> 8059
    //   7926: aload #4
    //   7928: iload #6
    //   7930: aaload
    //   7931: astore #7
    //   7933: aload #7
    //   7935: invokevirtual getParameterTypes : ()[Ljava/lang/Class;
    //   7938: pop
    //   7939: aload #7
    //   7941: invokevirtual getModifiers : ()I
    //   7944: invokestatic isStatic : (I)Z
    //   7947: ifeq -> 8045
    //   7950: aload #7
    //   7952: invokevirtual getParameterTypes : ()[Ljava/lang/Class;
    //   7955: arraylength
    //   7956: iconst_2
    //   7957: if_icmpne -> 8045
    //   7960: goto -> 7967
    //   7963: invokestatic a : (Ljava/lang/Throwable;)Ljava/lang/Throwable;
    //   7966: athrow
    //   7967: aload #7
    //   7969: invokevirtual getReturnType : ()Ljava/lang/Class;
    //   7972: getstatic java/lang/Boolean.TYPE : Ljava/lang/Class;
    //   7975: if_acmpne -> 8045
    //   7978: goto -> 7985
    //   7981: invokestatic a : (Ljava/lang/Throwable;)Ljava/lang/Throwable;
    //   7984: athrow
    //   7985: aload #7
    //   7987: iconst_1
    //   7988: invokevirtual setAccessible : (Z)V
    //   7991: aload #7
    //   7993: aconst_null
    //   7994: iconst_2
    //   7995: anewarray java/lang/Object
    //   7998: dup
    //   7999: iconst_0
    //   8000: aload_0
    //   8001: aastore
    //   8002: dup
    //   8003: iconst_1
    //   8004: aload_1
    //   8005: ifnonnull -> 8023
    //   8008: goto -> 8015
    //   8011: invokestatic a : (Ljava/lang/Throwable;)Ljava/lang/Throwable;
    //   8014: athrow
    //   8015: aload_1
    //   8016: goto -> 8030
    //   8019: invokestatic a : (Ljava/lang/Throwable;)Ljava/lang/Throwable;
    //   8022: athrow
    //   8023: aload_1
    //   8024: checkcast [B
    //   8027: invokevirtual clone : ()Ljava/lang/Object;
    //   8030: aastore
    //   8031: invokevirtual invoke : (Ljava/lang/Object;[Ljava/lang/Object;)Ljava/lang/Object;
    //   8034: checkcast java/lang/Boolean
    //   8037: invokevirtual booleanValue : ()Z
    //   8040: istore_3
    //   8041: iload_2
    //   8042: ifeq -> 8059
    //   8045: iinc #6, 1
    //   8048: iload_2
    //   8049: ifeq -> 7919
    //   8052: goto -> 8059
    //   8055: invokestatic a : (Ljava/lang/Throwable;)Ljava/lang/Throwable;
    //   8058: athrow
    //   8059: iload_2
    //   8060: ifeq -> 8401
    //   8063: sipush #-17763
    //   8066: sipush #-29705
    //   8069: invokestatic a : (II)Ljava/lang/String;
    //   8072: iconst_1
    //   8073: ldc burp/Zt5t
    //   8075: invokevirtual getClassLoader : ()Ljava/lang/ClassLoader;
    //   8078: invokestatic forName : (Ljava/lang/String;ZLjava/lang/ClassLoader;)Ljava/lang/Class;
    //   8081: invokevirtual getDeclaredFields : ()[Ljava/lang/reflect/Field;
    //   8084: astore #4
    //   8086: aload #4
    //   8088: arraylength
    //   8089: istore #5
    //   8091: iconst_0
    //   8092: istore #6
    //   8094: iload #6
    //   8096: iload #5
    //   8098: if_icmpge -> 8236
    //   8101: aload #4
    //   8103: iload #6
    //   8105: aaload
    //   8106: astore #7
    //   8108: aload #7
    //   8110: invokevirtual getModifiers : ()I
    //   8113: invokestatic isStatic : (I)Z
    //   8116: ifne -> 8126
    //   8119: goto -> 8229
    //   8122: invokestatic a : (Ljava/lang/Throwable;)Ljava/lang/Throwable;
    //   8125: athrow
    //   8126: aload #7
    //   8128: invokevirtual getType : ()Ljava/lang/Class;
    //   8131: astore #8
    //   8133: aload #8
    //   8135: ifnull -> 8216
    //   8138: aload #8
    //   8140: invokevirtual isPrimitive : ()Z
    //   8143: ifne -> 8216
    //   8146: goto -> 8153
    //   8149: invokestatic a : (Ljava/lang/Throwable;)Ljava/lang/Throwable;
    //   8152: athrow
    //   8153: aload #8
    //   8155: invokevirtual getPackage : ()Ljava/lang/Package;
    //   8158: ifnull -> 8216
    //   8161: goto -> 8168
    //   8164: invokestatic a : (Ljava/lang/Throwable;)Ljava/lang/Throwable;
    //   8167: athrow
    //   8168: aload #8
    //   8170: invokevirtual getPackage : ()Ljava/lang/Package;
    //   8173: invokevirtual getName : ()Ljava/lang/String;
    //   8176: ifnull -> 8216
    //   8179: goto -> 8186
    //   8182: invokestatic a : (Ljava/lang/Throwable;)Ljava/lang/Throwable;
    //   8185: athrow
    //   8186: aload #8
    //   8188: invokevirtual getPackage : ()Ljava/lang/Package;
    //   8191: invokevirtual getName : ()Ljava/lang/String;
    //   8194: sipush #-17770
    //   8197: sipush #13676
    //   8200: invokestatic a : (II)Ljava/lang/String;
    //   8203: invokevirtual startsWith : (Ljava/lang/String;)Z
    //   8206: ifne -> 8216
    //   8209: goto -> 8216
    //   8212: invokestatic a : (Ljava/lang/Throwable;)Ljava/lang/Throwable;
    //   8215: athrow
    //   8216: aload #7
    //   8218: iconst_1
    //   8219: invokevirtual setAccessible : (Z)V
    //   8222: aload #7
    //   8224: aconst_null
    //   8225: invokevirtual get : (Ljava/lang/Object;)Ljava/lang/Object;
    //   8228: pop
    //   8229: iinc #6, 1
    //   8232: iload_2
    //   8233: ifeq -> 8094
    //   8236: sipush #-17784
    //   8239: sipush #-23019
    //   8242: invokestatic a : (II)Ljava/lang/String;
    //   8245: invokestatic forName : (Ljava/lang/String;)Ljava/lang/Class;
    //   8248: invokevirtual getDeclaredMethods : ()[Ljava/lang/reflect/Method;
    //   8251: astore #4
    //   8253: aload #4
    //   8255: arraylength
    //   8256: istore #5
    //   8258: iconst_0
    //   8259: istore #6
    //   8261: iload #6
    //   8263: iload #5
    //   8265: if_icmpge -> 8401
    //   8268: aload #4
    //   8270: iload #6
    //   8272: aaload
    //   8273: astore #7
    //   8275: aload #7
    //   8277: invokevirtual getParameterTypes : ()[Ljava/lang/Class;
    //   8280: pop
    //   8281: aload #7
    //   8283: invokevirtual getModifiers : ()I
    //   8286: invokestatic isStatic : (I)Z
    //   8289: ifeq -> 8387
    //   8292: aload #7
    //   8294: invokevirtual getParameterTypes : ()[Ljava/lang/Class;
    //   8297: arraylength
    //   8298: iconst_2
    //   8299: if_icmpne -> 8387
    //   8302: goto -> 8309
    //   8305: invokestatic a : (Ljava/lang/Throwable;)Ljava/lang/Throwable;
    //   8308: athrow
    //   8309: aload #7
    //   8311: invokevirtual getReturnType : ()Ljava/lang/Class;
    //   8314: getstatic java/lang/Boolean.TYPE : Ljava/lang/Class;
    //   8317: if_acmpne -> 8387
    //   8320: goto -> 8327
    //   8323: invokestatic a : (Ljava/lang/Throwable;)Ljava/lang/Throwable;
    //   8326: athrow
    //   8327: aload #7
    //   8329: iconst_1
    //   8330: invokevirtual setAccessible : (Z)V
    //   8333: aload #7
    //   8335: aconst_null
    //   8336: iconst_2
    //   8337: anewarray java/lang/Object
    //   8340: dup
    //   8341: iconst_0
    //   8342: aload_0
    //   8343: aastore
    //   8344: dup
    //   8345: iconst_1
    //   8346: aload_1
    //   8347: ifnonnull -> 8365
    //   8350: goto -> 8357
    //   8353: invokestatic a : (Ljava/lang/Throwable;)Ljava/lang/Throwable;
    //   8356: athrow
    //   8357: aload_1
    //   8358: goto -> 8372
    //   8361: invokestatic a : (Ljava/lang/Throwable;)Ljava/lang/Throwable;
    //   8364: athrow
    //   8365: aload_1
    //   8366: checkcast [B
    //   8369: invokevirtual clone : ()Ljava/lang/Object;
    //   8372: aastore
    //   8373: invokevirtual invoke : (Ljava/lang/Object;[Ljava/lang/Object;)Ljava/lang/Object;
    //   8376: checkcast java/lang/Boolean
    //   8379: invokevirtual booleanValue : ()Z
    //   8382: istore_3
    //   8383: iload_2
    //   8384: ifeq -> 8401
    //   8387: iinc #6, 1
    //   8390: iload_2
    //   8391: ifeq -> 8261
    //   8394: goto -> 8401
    //   8397: invokestatic a : (Ljava/lang/Throwable;)Ljava/lang/Throwable;
    //   8400: athrow
    //   8401: iload_3
    //   8402: ifeq -> 8407
    //   8405: iload_3
    //   8406: ireturn
    //   8407: getstatic burp/Zlfi.Zg : Ljava/lang/String;
    //   8410: getstatic burp/Zb9m.ZK : Ljava/lang/Object;
    //   8413: checkcast java/math/BigInteger
    //   8416: invokevirtual intValue : ()I
    //   8419: bipush #32
    //   8421: irem
    //   8422: invokestatic abs : (I)I
    //   8425: invokevirtual charAt : (I)C
    //   8428: getstatic burp/Zsmn.Zo : Ljava/lang/String;
    //   8431: getstatic burp/Zlpu.ZE : Ljava/lang/Object;
    //   8434: checkcast java/math/BigInteger
    //   8437: invokevirtual intValue : ()I
    //   8440: bipush #32
    //   8442: irem
    //   8443: invokestatic abs : (I)I
    //   8446: invokevirtual charAt : (I)C
    //   8449: if_icmpgt -> 8794
    //   8452: sipush #-17774
    //   8455: sipush #-5278
    //   8458: invokestatic a : (II)Ljava/lang/String;
    //   8461: iconst_1
    //   8462: ldc burp/Zlwm
    //   8464: invokevirtual getClassLoader : ()Ljava/lang/ClassLoader;
    //   8467: invokestatic forName : (Ljava/lang/String;ZLjava/lang/ClassLoader;)Ljava/lang/Class;
    //   8470: invokevirtual getDeclaredFields : ()[Ljava/lang/reflect/Field;
    //   8473: astore #4
    //   8475: aload #4
    //   8477: arraylength
    //   8478: istore #5
    //   8480: iconst_0
    //   8481: istore #6
    //   8483: iload #6
    //   8485: iload #5
    //   8487: if_icmpge -> 8625
    //   8490: aload #4
    //   8492: iload #6
    //   8494: aaload
    //   8495: astore #7
    //   8497: aload #7
    //   8499: invokevirtual getModifiers : ()I
    //   8502: invokestatic isStatic : (I)Z
    //   8505: ifne -> 8515
    //   8508: goto -> 8618
    //   8511: invokestatic a : (Ljava/lang/Throwable;)Ljava/lang/Throwable;
    //   8514: athrow
    //   8515: aload #7
    //   8517: invokevirtual getType : ()Ljava/lang/Class;
    //   8520: astore #8
    //   8522: aload #8
    //   8524: ifnull -> 8605
    //   8527: aload #8
    //   8529: invokevirtual isPrimitive : ()Z
    //   8532: ifne -> 8605
    //   8535: goto -> 8542
    //   8538: invokestatic a : (Ljava/lang/Throwable;)Ljava/lang/Throwable;
    //   8541: athrow
    //   8542: aload #8
    //   8544: invokevirtual getPackage : ()Ljava/lang/Package;
    //   8547: ifnull -> 8605
    //   8550: goto -> 8557
    //   8553: invokestatic a : (Ljava/lang/Throwable;)Ljava/lang/Throwable;
    //   8556: athrow
    //   8557: aload #8
    //   8559: invokevirtual getPackage : ()Ljava/lang/Package;
    //   8562: invokevirtual getName : ()Ljava/lang/String;
    //   8565: ifnull -> 8605
    //   8568: goto -> 8575
    //   8571: invokestatic a : (Ljava/lang/Throwable;)Ljava/lang/Throwable;
    //   8574: athrow
    //   8575: aload #8
    //   8577: invokevirtual getPackage : ()Ljava/lang/Package;
    //   8580: invokevirtual getName : ()Ljava/lang/String;
    //   8583: sipush #-17770
    //   8586: sipush #13676
    //   8589: invokestatic a : (II)Ljava/lang/String;
    //   8592: invokevirtual startsWith : (Ljava/lang/String;)Z
    //   8595: ifne -> 8605
    //   8598: goto -> 8605
    //   8601: invokestatic a : (Ljava/lang/Throwable;)Ljava/lang/Throwable;
    //   8604: athrow
    //   8605: aload #7
    //   8607: iconst_1
    //   8608: invokevirtual setAccessible : (Z)V
    //   8611: aload #7
    //   8613: aconst_null
    //   8614: invokevirtual get : (Ljava/lang/Object;)Ljava/lang/Object;
    //   8617: pop
    //   8618: iinc #6, 1
    //   8621: iload_2
    //   8622: ifeq -> 8483
    //   8625: sipush #-17774
    //   8628: sipush #-5278
    //   8631: invokestatic a : (II)Ljava/lang/String;
    //   8634: invokestatic forName : (Ljava/lang/String;)Ljava/lang/Class;
    //   8637: invokevirtual getDeclaredMethods : ()[Ljava/lang/reflect/Method;
    //   8640: astore #4
    //   8642: aload #4
    //   8644: arraylength
    //   8645: istore #5
    //   8647: iconst_0
    //   8648: istore #6
    //   8650: iload #6
    //   8652: iload #5
    //   8654: if_icmpge -> 8790
    //   8657: aload #4
    //   8659: iload #6
    //   8661: aaload
    //   8662: astore #7
    //   8664: aload #7
    //   8666: invokevirtual getParameterTypes : ()[Ljava/lang/Class;
    //   8669: pop
    //   8670: aload #7
    //   8672: invokevirtual getModifiers : ()I
    //   8675: invokestatic isStatic : (I)Z
    //   8678: ifeq -> 8776
    //   8681: aload #7
    //   8683: invokevirtual getParameterTypes : ()[Ljava/lang/Class;
    //   8686: arraylength
    //   8687: iconst_2
    //   8688: if_icmpne -> 8776
    //   8691: goto -> 8698
    //   8694: invokestatic a : (Ljava/lang/Throwable;)Ljava/lang/Throwable;
    //   8697: athrow
    //   8698: aload #7
    //   8700: invokevirtual getReturnType : ()Ljava/lang/Class;
    //   8703: getstatic java/lang/Boolean.TYPE : Ljava/lang/Class;
    //   8706: if_acmpne -> 8776
    //   8709: goto -> 8716
    //   8712: invokestatic a : (Ljava/lang/Throwable;)Ljava/lang/Throwable;
    //   8715: athrow
    //   8716: aload #7
    //   8718: iconst_1
    //   8719: invokevirtual setAccessible : (Z)V
    //   8722: aload #7
    //   8724: aconst_null
    //   8725: iconst_2
    //   8726: anewarray java/lang/Object
    //   8729: dup
    //   8730: iconst_0
    //   8731: aload_0
    //   8732: aastore
    //   8733: dup
    //   8734: iconst_1
    //   8735: aload_1
    //   8736: ifnonnull -> 8754
    //   8739: goto -> 8746
    //   8742: invokestatic a : (Ljava/lang/Throwable;)Ljava/lang/Throwable;
    //   8745: athrow
    //   8746: aload_1
    //   8747: goto -> 8761
    //   8750: invokestatic a : (Ljava/lang/Throwable;)Ljava/lang/Throwable;
    //   8753: athrow
    //   8754: aload_1
    //   8755: checkcast [B
    //   8758: invokevirtual clone : ()Ljava/lang/Object;
    //   8761: aastore
    //   8762: invokevirtual invoke : (Ljava/lang/Object;[Ljava/lang/Object;)Ljava/lang/Object;
    //   8765: checkcast java/lang/Boolean
    //   8768: invokevirtual booleanValue : ()Z
    //   8771: istore_3
    //   8772: iload_2
    //   8773: ifeq -> 8790
    //   8776: iinc #6, 1
    //   8779: iload_2
    //   8780: ifeq -> 8650
    //   8783: goto -> 8790
    //   8786: invokestatic a : (Ljava/lang/Throwable;)Ljava/lang/Throwable;
    //   8789: athrow
    //   8790: iload_2
    //   8791: ifeq -> 9132
    //   8794: sipush #-17772
    //   8797: sipush #2778
    //   8800: invokestatic a : (II)Ljava/lang/String;
    //   8803: iconst_1
    //   8804: ldc burp/Zlsg
    //   8806: invokevirtual getClassLoader : ()Ljava/lang/ClassLoader;
    //   8809: invokestatic forName : (Ljava/lang/String;ZLjava/lang/ClassLoader;)Ljava/lang/Class;
    //   8812: invokevirtual getDeclaredFields : ()[Ljava/lang/reflect/Field;
    //   8815: astore #4
    //   8817: aload #4
    //   8819: arraylength
    //   8820: istore #5
    //   8822: iconst_0
    //   8823: istore #6
    //   8825: iload #6
    //   8827: iload #5
    //   8829: if_icmpge -> 8967
    //   8832: aload #4
    //   8834: iload #6
    //   8836: aaload
    //   8837: astore #7
    //   8839: aload #7
    //   8841: invokevirtual getModifiers : ()I
    //   8844: invokestatic isStatic : (I)Z
    //   8847: ifne -> 8857
    //   8850: goto -> 8960
    //   8853: invokestatic a : (Ljava/lang/Throwable;)Ljava/lang/Throwable;
    //   8856: athrow
    //   8857: aload #7
    //   8859: invokevirtual getType : ()Ljava/lang/Class;
    //   8862: astore #8
    //   8864: aload #8
    //   8866: ifnull -> 8947
    //   8869: aload #8
    //   8871: invokevirtual isPrimitive : ()Z
    //   8874: ifne -> 8947
    //   8877: goto -> 8884
    //   8880: invokestatic a : (Ljava/lang/Throwable;)Ljava/lang/Throwable;
    //   8883: athrow
    //   8884: aload #8
    //   8886: invokevirtual getPackage : ()Ljava/lang/Package;
    //   8889: ifnull -> 8947
    //   8892: goto -> 8899
    //   8895: invokestatic a : (Ljava/lang/Throwable;)Ljava/lang/Throwable;
    //   8898: athrow
    //   8899: aload #8
    //   8901: invokevirtual getPackage : ()Ljava/lang/Package;
    //   8904: invokevirtual getName : ()Ljava/lang/String;
    //   8907: ifnull -> 8947
    //   8910: goto -> 8917
    //   8913: invokestatic a : (Ljava/lang/Throwable;)Ljava/lang/Throwable;
    //   8916: athrow
    //   8917: aload #8
    //   8919: invokevirtual getPackage : ()Ljava/lang/Package;
    //   8922: invokevirtual getName : ()Ljava/lang/String;
    //   8925: sipush #-17770
    //   8928: sipush #13676
    //   8931: invokestatic a : (II)Ljava/lang/String;
    //   8934: invokevirtual startsWith : (Ljava/lang/String;)Z
    //   8937: ifne -> 8947
    //   8940: goto -> 8947
    //   8943: invokestatic a : (Ljava/lang/Throwable;)Ljava/lang/Throwable;
    //   8946: athrow
    //   8947: aload #7
    //   8949: iconst_1
    //   8950: invokevirtual setAccessible : (Z)V
    //   8953: aload #7
    //   8955: aconst_null
    //   8956: invokevirtual get : (Ljava/lang/Object;)Ljava/lang/Object;
    //   8959: pop
    //   8960: iinc #6, 1
    //   8963: iload_2
    //   8964: ifeq -> 8825
    //   8967: sipush #-17782
    //   8970: sipush #19680
    //   8973: invokestatic a : (II)Ljava/lang/String;
    //   8976: invokestatic forName : (Ljava/lang/String;)Ljava/lang/Class;
    //   8979: invokevirtual getDeclaredMethods : ()[Ljava/lang/reflect/Method;
    //   8982: astore #4
    //   8984: aload #4
    //   8986: arraylength
    //   8987: istore #5
    //   8989: iconst_0
    //   8990: istore #6
    //   8992: iload #6
    //   8994: iload #5
    //   8996: if_icmpge -> 9132
    //   8999: aload #4
    //   9001: iload #6
    //   9003: aaload
    //   9004: astore #7
    //   9006: aload #7
    //   9008: invokevirtual getParameterTypes : ()[Ljava/lang/Class;
    //   9011: pop
    //   9012: aload #7
    //   9014: invokevirtual getModifiers : ()I
    //   9017: invokestatic isStatic : (I)Z
    //   9020: ifeq -> 9118
    //   9023: aload #7
    //   9025: invokevirtual getParameterTypes : ()[Ljava/lang/Class;
    //   9028: arraylength
    //   9029: iconst_2
    //   9030: if_icmpne -> 9118
    //   9033: goto -> 9040
    //   9036: invokestatic a : (Ljava/lang/Throwable;)Ljava/lang/Throwable;
    //   9039: athrow
    //   9040: aload #7
    //   9042: invokevirtual getReturnType : ()Ljava/lang/Class;
    //   9045: getstatic java/lang/Boolean.TYPE : Ljava/lang/Class;
    //   9048: if_acmpne -> 9118
    //   9051: goto -> 9058
    //   9054: invokestatic a : (Ljava/lang/Throwable;)Ljava/lang/Throwable;
    //   9057: athrow
    //   9058: aload #7
    //   9060: iconst_1
    //   9061: invokevirtual setAccessible : (Z)V
    //   9064: aload #7
    //   9066: aconst_null
    //   9067: iconst_2
    //   9068: anewarray java/lang/Object
    //   9071: dup
    //   9072: iconst_0
    //   9073: aload_0
    //   9074: aastore
    //   9075: dup
    //   9076: iconst_1
    //   9077: aload_1
    //   9078: ifnonnull -> 9096
    //   9081: goto -> 9088
    //   9084: invokestatic a : (Ljava/lang/Throwable;)Ljava/lang/Throwable;
    //   9087: athrow
    //   9088: aload_1
    //   9089: goto -> 9103
    //   9092: invokestatic a : (Ljava/lang/Throwable;)Ljava/lang/Throwable;
    //   9095: athrow
    //   9096: aload_1
    //   9097: checkcast [B
    //   9100: invokevirtual clone : ()Ljava/lang/Object;
    //   9103: aastore
    //   9104: invokevirtual invoke : (Ljava/lang/Object;[Ljava/lang/Object;)Ljava/lang/Object;
    //   9107: checkcast java/lang/Boolean
    //   9110: invokevirtual booleanValue : ()Z
    //   9113: istore_3
    //   9114: iload_2
    //   9115: ifeq -> 9132
    //   9118: iinc #6, 1
    //   9121: iload_2
    //   9122: ifeq -> 8992
    //   9125: goto -> 9132
    //   9128: invokestatic a : (Ljava/lang/Throwable;)Ljava/lang/Throwable;
    //   9131: athrow
    //   9132: iload_3
    //   9133: ifeq -> 9138
    //   9136: iload_3
    //   9137: ireturn
    //   9138: getstatic burp/Zmsl.ZP : Ljava/lang/String;
    //   9141: getstatic burp/Zx_u.Zy : Ljava/lang/Object;
    //   9144: checkcast java/math/BigInteger
    //   9147: invokevirtual intValue : ()I
    //   9150: bipush #32
    //   9152: irem
    //   9153: invokestatic abs : (I)I
    //   9156: invokevirtual charAt : (I)C
    //   9159: getstatic burp/Zgco.Zh : Ljava/lang/String;
    //   9162: getstatic burp/Zxxd.Zn : Ljava/lang/Object;
    //   9165: checkcast java/math/BigInteger
    //   9168: invokevirtual intValue : ()I
    //   9171: bipush #32
    //   9173: irem
    //   9174: invokestatic abs : (I)I
    //   9177: invokevirtual charAt : (I)C
    //   9180: if_icmpgt -> 9525
    //   9183: sipush #-17789
    //   9186: sipush #-7404
    //   9189: invokestatic a : (II)Ljava/lang/String;
    //   9192: iconst_1
    //   9193: ldc burp/Zrpx
    //   9195: invokevirtual getClassLoader : ()Ljava/lang/ClassLoader;
    //   9198: invokestatic forName : (Ljava/lang/String;ZLjava/lang/ClassLoader;)Ljava/lang/Class;
    //   9201: invokevirtual getDeclaredFields : ()[Ljava/lang/reflect/Field;
    //   9204: astore #4
    //   9206: aload #4
    //   9208: arraylength
    //   9209: istore #5
    //   9211: iconst_0
    //   9212: istore #6
    //   9214: iload #6
    //   9216: iload #5
    //   9218: if_icmpge -> 9356
    //   9221: aload #4
    //   9223: iload #6
    //   9225: aaload
    //   9226: astore #7
    //   9228: aload #7
    //   9230: invokevirtual getModifiers : ()I
    //   9233: invokestatic isStatic : (I)Z
    //   9236: ifne -> 9246
    //   9239: goto -> 9349
    //   9242: invokestatic a : (Ljava/lang/Throwable;)Ljava/lang/Throwable;
    //   9245: athrow
    //   9246: aload #7
    //   9248: invokevirtual getType : ()Ljava/lang/Class;
    //   9251: astore #8
    //   9253: aload #8
    //   9255: ifnull -> 9336
    //   9258: aload #8
    //   9260: invokevirtual isPrimitive : ()Z
    //   9263: ifne -> 9336
    //   9266: goto -> 9273
    //   9269: invokestatic a : (Ljava/lang/Throwable;)Ljava/lang/Throwable;
    //   9272: athrow
    //   9273: aload #8
    //   9275: invokevirtual getPackage : ()Ljava/lang/Package;
    //   9278: ifnull -> 9336
    //   9281: goto -> 9288
    //   9284: invokestatic a : (Ljava/lang/Throwable;)Ljava/lang/Throwable;
    //   9287: athrow
    //   9288: aload #8
    //   9290: invokevirtual getPackage : ()Ljava/lang/Package;
    //   9293: invokevirtual getName : ()Ljava/lang/String;
    //   9296: ifnull -> 9336
    //   9299: goto -> 9306
    //   9302: invokestatic a : (Ljava/lang/Throwable;)Ljava/lang/Throwable;
    //   9305: athrow
    //   9306: aload #8
    //   9308: invokevirtual getPackage : ()Ljava/lang/Package;
    //   9311: invokevirtual getName : ()Ljava/lang/String;
    //   9314: sipush #-17770
    //   9317: sipush #13676
    //   9320: invokestatic a : (II)Ljava/lang/String;
    //   9323: invokevirtual startsWith : (Ljava/lang/String;)Z
    //   9326: ifne -> 9336
    //   9329: goto -> 9336
    //   9332: invokestatic a : (Ljava/lang/Throwable;)Ljava/lang/Throwable;
    //   9335: athrow
    //   9336: aload #7
    //   9338: iconst_1
    //   9339: invokevirtual setAccessible : (Z)V
    //   9342: aload #7
    //   9344: aconst_null
    //   9345: invokevirtual get : (Ljava/lang/Object;)Ljava/lang/Object;
    //   9348: pop
    //   9349: iinc #6, 1
    //   9352: iload_2
    //   9353: ifeq -> 9214
    //   9356: sipush #-17764
    //   9359: sipush #10579
    //   9362: invokestatic a : (II)Ljava/lang/String;
    //   9365: invokestatic forName : (Ljava/lang/String;)Ljava/lang/Class;
    //   9368: invokevirtual getDeclaredMethods : ()[Ljava/lang/reflect/Method;
    //   9371: astore #4
    //   9373: aload #4
    //   9375: arraylength
    //   9376: istore #5
    //   9378: iconst_0
    //   9379: istore #6
    //   9381: iload #6
    //   9383: iload #5
    //   9385: if_icmpge -> 9521
    //   9388: aload #4
    //   9390: iload #6
    //   9392: aaload
    //   9393: astore #7
    //   9395: aload #7
    //   9397: invokevirtual getParameterTypes : ()[Ljava/lang/Class;
    //   9400: pop
    //   9401: aload #7
    //   9403: invokevirtual getModifiers : ()I
    //   9406: invokestatic isStatic : (I)Z
    //   9409: ifeq -> 9507
    //   9412: aload #7
    //   9414: invokevirtual getParameterTypes : ()[Ljava/lang/Class;
    //   9417: arraylength
    //   9418: iconst_2
    //   9419: if_icmpne -> 9507
    //   9422: goto -> 9429
    //   9425: invokestatic a : (Ljava/lang/Throwable;)Ljava/lang/Throwable;
    //   9428: athrow
    //   9429: aload #7
    //   9431: invokevirtual getReturnType : ()Ljava/lang/Class;
    //   9434: getstatic java/lang/Boolean.TYPE : Ljava/lang/Class;
    //   9437: if_acmpne -> 9507
    //   9440: goto -> 9447
    //   9443: invokestatic a : (Ljava/lang/Throwable;)Ljava/lang/Throwable;
    //   9446: athrow
    //   9447: aload #7
    //   9449: iconst_1
    //   9450: invokevirtual setAccessible : (Z)V
    //   9453: aload #7
    //   9455: aconst_null
    //   9456: iconst_2
    //   9457: anewarray java/lang/Object
    //   9460: dup
    //   9461: iconst_0
    //   9462: aload_0
    //   9463: aastore
    //   9464: dup
    //   9465: iconst_1
    //   9466: aload_1
    //   9467: ifnonnull -> 9485
    //   9470: goto -> 9477
    //   9473: invokestatic a : (Ljava/lang/Throwable;)Ljava/lang/Throwable;
    //   9476: athrow
    //   9477: aload_1
    //   9478: goto -> 9492
    //   9481: invokestatic a : (Ljava/lang/Throwable;)Ljava/lang/Throwable;
    //   9484: athrow
    //   9485: aload_1
    //   9486: checkcast [B
    //   9489: invokevirtual clone : ()Ljava/lang/Object;
    //   9492: aastore
    //   9493: invokevirtual invoke : (Ljava/lang/Object;[Ljava/lang/Object;)Ljava/lang/Object;
    //   9496: checkcast java/lang/Boolean
    //   9499: invokevirtual booleanValue : ()Z
    //   9502: istore_3
    //   9503: iload_2
    //   9504: ifeq -> 9521
    //   9507: iinc #6, 1
    //   9510: iload_2
    //   9511: ifeq -> 9381
    //   9514: goto -> 9521
    //   9517: invokestatic a : (Ljava/lang/Throwable;)Ljava/lang/Throwable;
    //   9520: athrow
    //   9521: iload_2
    //   9522: ifeq -> 9863
    //   9525: sipush #-17778
    //   9528: sipush #31169
    //   9531: invokestatic a : (II)Ljava/lang/String;
    //   9534: iconst_1
    //   9535: ldc burp/Ze3j
    //   9537: invokevirtual getClassLoader : ()Ljava/lang/ClassLoader;
    //   9540: invokestatic forName : (Ljava/lang/String;ZLjava/lang/ClassLoader;)Ljava/lang/Class;
    //   9543: invokevirtual getDeclaredFields : ()[Ljava/lang/reflect/Field;
    //   9546: astore #4
    //   9548: aload #4
    //   9550: arraylength
    //   9551: istore #5
    //   9553: iconst_0
    //   9554: istore #6
    //   9556: iload #6
    //   9558: iload #5
    //   9560: if_icmpge -> 9698
    //   9563: aload #4
    //   9565: iload #6
    //   9567: aaload
    //   9568: astore #7
    //   9570: aload #7
    //   9572: invokevirtual getModifiers : ()I
    //   9575: invokestatic isStatic : (I)Z
    //   9578: ifne -> 9588
    //   9581: goto -> 9691
    //   9584: invokestatic a : (Ljava/lang/Throwable;)Ljava/lang/Throwable;
    //   9587: athrow
    //   9588: aload #7
    //   9590: invokevirtual getType : ()Ljava/lang/Class;
    //   9593: astore #8
    //   9595: aload #8
    //   9597: ifnull -> 9678
    //   9600: aload #8
    //   9602: invokevirtual isPrimitive : ()Z
    //   9605: ifne -> 9678
    //   9608: goto -> 9615
    //   9611: invokestatic a : (Ljava/lang/Throwable;)Ljava/lang/Throwable;
    //   9614: athrow
    //   9615: aload #8
    //   9617: invokevirtual getPackage : ()Ljava/lang/Package;
    //   9620: ifnull -> 9678
    //   9623: goto -> 9630
    //   9626: invokestatic a : (Ljava/lang/Throwable;)Ljava/lang/Throwable;
    //   9629: athrow
    //   9630: aload #8
    //   9632: invokevirtual getPackage : ()Ljava/lang/Package;
    //   9635: invokevirtual getName : ()Ljava/lang/String;
    //   9638: ifnull -> 9678
    //   9641: goto -> 9648
    //   9644: invokestatic a : (Ljava/lang/Throwable;)Ljava/lang/Throwable;
    //   9647: athrow
    //   9648: aload #8
    //   9650: invokevirtual getPackage : ()Ljava/lang/Package;
    //   9653: invokevirtual getName : ()Ljava/lang/String;
    //   9656: sipush #-17770
    //   9659: sipush #13676
    //   9662: invokestatic a : (II)Ljava/lang/String;
    //   9665: invokevirtual startsWith : (Ljava/lang/String;)Z
    //   9668: ifne -> 9678
    //   9671: goto -> 9678
    //   9674: invokestatic a : (Ljava/lang/Throwable;)Ljava/lang/Throwable;
    //   9677: athrow
    //   9678: aload #7
    //   9680: iconst_1
    //   9681: invokevirtual setAccessible : (Z)V
    //   9684: aload #7
    //   9686: aconst_null
    //   9687: invokevirtual get : (Ljava/lang/Object;)Ljava/lang/Object;
    //   9690: pop
    //   9691: iinc #6, 1
    //   9694: iload_2
    //   9695: ifeq -> 9556
    //   9698: sipush #-17773
    //   9701: sipush #17253
    //   9704: invokestatic a : (II)Ljava/lang/String;
    //   9707: invokestatic forName : (Ljava/lang/String;)Ljava/lang/Class;
    //   9710: invokevirtual getDeclaredMethods : ()[Ljava/lang/reflect/Method;
    //   9713: astore #4
    //   9715: aload #4
    //   9717: arraylength
    //   9718: istore #5
    //   9720: iconst_0
    //   9721: istore #6
    //   9723: iload #6
    //   9725: iload #5
    //   9727: if_icmpge -> 9863
    //   9730: aload #4
    //   9732: iload #6
    //   9734: aaload
    //   9735: astore #7
    //   9737: aload #7
    //   9739: invokevirtual getParameterTypes : ()[Ljava/lang/Class;
    //   9742: pop
    //   9743: aload #7
    //   9745: invokevirtual getModifiers : ()I
    //   9748: invokestatic isStatic : (I)Z
    //   9751: ifeq -> 9849
    //   9754: aload #7
    //   9756: invokevirtual getParameterTypes : ()[Ljava/lang/Class;
    //   9759: arraylength
    //   9760: iconst_2
    //   9761: if_icmpne -> 9849
    //   9764: goto -> 9771
    //   9767: invokestatic a : (Ljava/lang/Throwable;)Ljava/lang/Throwable;
    //   9770: athrow
    //   9771: aload #7
    //   9773: invokevirtual getReturnType : ()Ljava/lang/Class;
    //   9776: getstatic java/lang/Boolean.TYPE : Ljava/lang/Class;
    //   9779: if_acmpne -> 9849
    //   9782: goto -> 9789
    //   9785: invokestatic a : (Ljava/lang/Throwable;)Ljava/lang/Throwable;
    //   9788: athrow
    //   9789: aload #7
    //   9791: iconst_1
    //   9792: invokevirtual setAccessible : (Z)V
    //   9795: aload #7
    //   9797: aconst_null
    //   9798: iconst_2
    //   9799: anewarray java/lang/Object
    //   9802: dup
    //   9803: iconst_0
    //   9804: aload_0
    //   9805: aastore
    //   9806: dup
    //   9807: iconst_1
    //   9808: aload_1
    //   9809: ifnonnull -> 9827
    //   9812: goto -> 9819
    //   9815: invokestatic a : (Ljava/lang/Throwable;)Ljava/lang/Throwable;
    //   9818: athrow
    //   9819: aload_1
    //   9820: goto -> 9834
    //   9823: invokestatic a : (Ljava/lang/Throwable;)Ljava/lang/Throwable;
    //   9826: athrow
    //   9827: aload_1
    //   9828: checkcast [B
    //   9831: invokevirtual clone : ()Ljava/lang/Object;
    //   9834: aastore
    //   9835: invokevirtual invoke : (Ljava/lang/Object;[Ljava/lang/Object;)Ljava/lang/Object;
    //   9838: checkcast java/lang/Boolean
    //   9841: invokevirtual booleanValue : ()Z
    //   9844: istore_3
    //   9845: iload_2
    //   9846: ifeq -> 9863
    //   9849: iinc #6, 1
    //   9852: iload_2
    //   9853: ifeq -> 9723
    //   9856: goto -> 9863
    //   9859: invokestatic a : (Ljava/lang/Throwable;)Ljava/lang/Throwable;
    //   9862: athrow
    //   9863: iload_3
    //   9864: ireturn
    //   9865: astore_3
    //   9866: new java/lang/Exception
    //   9869: dup
    //   9870: aload_3
    //   9871: invokevirtual getMessage : ()Ljava/lang/String;
    //   9874: invokespecial <init> : (Ljava/lang/String;)V
    //   9877: athrow
    // Exception table:
    //   from	to	target	type
    //   4	7675	9865	java/lang/Throwable
    //   167	182	182	java/lang/Throwable
    //   1184	1210	1210	java/lang/Throwable
    //   1291	1306	1306	java/lang/Throwable
    //   2488	2513	2516	java/lang/Throwable
    //   2599	2613	2613	java/lang/Throwable
    //   2624	2637	2640	java/lang/Throwable
    //   2629	2652	2655	java/lang/Throwable
    //   2644	2670	2673	java/lang/Throwable
    //   2659	2700	2703	java/lang/Throwable
    //   2763	2790	2793	java/lang/Throwable
    //   2780	2811	2814	java/lang/Throwable
    //   2797	2841	2844	java/lang/Throwable
    //   2818	2852	2852	java/lang/Throwable
    //   2863	2879	2882	java/lang/Throwable
    //   3687	3721	3724	java/lang/Throwable
    //   3816	3894	3897	java/lang/Throwable
    //   3823	4037	4040	java/lang/Throwable
    //   4414	4429	4429	java/lang/Throwable
    //   4456	4490	4493	java/lang/Throwable
    //   4500	4512	4515	java/lang/Throwable
    //   4598	4676	4679	java/lang/Throwable
    //   4605	4819	4822	java/lang/Throwable
    //   5219	5297	5300	java/lang/Throwable
    //   5226	5440	5443	java/lang/Throwable
    //   5887	5921	5924	java/lang/Throwable
    //   5928	5940	5943	java/lang/Throwable
    //   6026	6104	6107	java/lang/Throwable
    //   6033	6247	6250	java/lang/Throwable
    //   7036	7050	7050	java/lang/Throwable
    //   7061	7074	7077	java/lang/Throwable
    //   7066	7089	7092	java/lang/Throwable
    //   7081	7107	7110	java/lang/Throwable
    //   7096	7137	7140	java/lang/Throwable
    //   7203	7230	7233	java/lang/Throwable
    //   7220	7248	7251	java/lang/Throwable
    //   7237	7278	7281	java/lang/Throwable
    //   7255	7289	7289	java/lang/Throwable
    //   7311	7322	7325	java/lang/Throwable
    //   7377	7391	7391	java/lang/Throwable
    //   7402	7415	7418	java/lang/Throwable
    //   7407	7430	7433	java/lang/Throwable
    //   7422	7448	7451	java/lang/Throwable
    //   7437	7478	7481	java/lang/Throwable
    //   7544	7571	7574	java/lang/Throwable
    //   7561	7589	7592	java/lang/Throwable
    //   7578	7619	7622	java/lang/Throwable
    //   7596	7630	7630	java/lang/Throwable
    //   7652	7663	7666	java/lang/Throwable
    //   7676	8406	9865	java/lang/Throwable
    //   7766	7780	7780	java/lang/Throwable
    //   7791	7804	7807	java/lang/Throwable
    //   7796	7819	7822	java/lang/Throwable
    //   7811	7837	7840	java/lang/Throwable
    //   7826	7867	7870	java/lang/Throwable
    //   7933	7960	7963	java/lang/Throwable
    //   7950	7978	7981	java/lang/Throwable
    //   7967	8008	8011	java/lang/Throwable
    //   7985	8019	8019	java/lang/Throwable
    //   8041	8052	8055	java/lang/Throwable
    //   8108	8122	8122	java/lang/Throwable
    //   8133	8146	8149	java/lang/Throwable
    //   8138	8161	8164	java/lang/Throwable
    //   8153	8179	8182	java/lang/Throwable
    //   8168	8209	8212	java/lang/Throwable
    //   8275	8302	8305	java/lang/Throwable
    //   8292	8320	8323	java/lang/Throwable
    //   8309	8350	8353	java/lang/Throwable
    //   8327	8361	8361	java/lang/Throwable
    //   8383	8394	8397	java/lang/Throwable
    //   8407	9137	9865	java/lang/Throwable
    //   8497	8511	8511	java/lang/Throwable
    //   8522	8535	8538	java/lang/Throwable
    //   8527	8550	8553	java/lang/Throwable
    //   8542	8568	8571	java/lang/Throwable
    //   8557	8598	8601	java/lang/Throwable
    //   8664	8691	8694	java/lang/Throwable
    //   8681	8709	8712	java/lang/Throwable
    //   8698	8739	8742	java/lang/Throwable
    //   8716	8750	8750	java/lang/Throwable
    //   8772	8783	8786	java/lang/Throwable
    //   8839	8853	8853	java/lang/Throwable
    //   8864	8877	8880	java/lang/Throwable
    //   8869	8892	8895	java/lang/Throwable
    //   8884	8910	8913	java/lang/Throwable
    //   8899	8940	8943	java/lang/Throwable
    //   9006	9033	9036	java/lang/Throwable
    //   9023	9051	9054	java/lang/Throwable
    //   9040	9081	9084	java/lang/Throwable
    //   9058	9092	9092	java/lang/Throwable
    //   9114	9125	9128	java/lang/Throwable
    //   9138	9864	9865	java/lang/Throwable
    //   9228	9242	9242	java/lang/Throwable
    //   9253	9266	9269	java/lang/Throwable
    //   9258	9281	9284	java/lang/Throwable
    //   9273	9299	9302	java/lang/Throwable
    //   9288	9329	9332	java/lang/Throwable
    //   9395	9422	9425	java/lang/Throwable
    //   9412	9440	9443	java/lang/Throwable
    //   9429	9470	9473	java/lang/Throwable
    //   9447	9481	9481	java/lang/Throwable
    //   9503	9514	9517	java/lang/Throwable
    //   9570	9584	9584	java/lang/Throwable
    //   9595	9608	9611	java/lang/Throwable
    //   9600	9623	9626	java/lang/Throwable
    //   9615	9641	9644	java/lang/Throwable
    //   9630	9671	9674	java/lang/Throwable
    //   9737	9764	9767	java/lang/Throwable
    //   9754	9782	9785	java/lang/Throwable
    //   9771	9812	9815	java/lang/Throwable
    //   9789	9823	9823	java/lang/Throwable
    //   9845	9856	9859	java/lang/Throwable
  }
  
  static void Zj(Object paramObject) {
    Zx_u.Z_ = a(-17791, 9294);
    Zx_u.Zy = new BigInteger(a(-17788, -12217));
    boolean bool = Zt2e.ZK();
    try {
      try {
        if (Zsx6.ZJ.charAt(Math.abs(((BigInteger)Ztzw.Zk).intValue() % 32)) > Zeoi.Zh.charAt(Math.abs(((BigInteger)Zm1l.Za).intValue() % 32))) {
          try {
            Zgr4.Zw(Class.forName(a(-17781, 22244)));
            if (bool)
              Zzoc.ZE(Class.forName(a(-17783, 16351))); 
          } catch (Throwable throwable) {
            throw a(null);
          } 
          return;
        } 
      } catch (Throwable throwable) {
        throw a(null);
      } 
      Zzoc.ZE(Class.forName(a(-17783, 16351)));
    } catch (Throwable throwable) {}
  }
  
  static {
    // Byte code:
    //   0: bipush #28
    //   2: anewarray java/lang/String
    //   5: astore #5
    //   7: iconst_0
    //   8: istore_3
    //   9: ldc 'w=7~Mg.grP'CL4KmTPmq3s`E \y$Q\r80p(\\f#2b'??Mao+IY;;6hxgnk_%yi.Vi6DM+zX9@~tBQ_a2\\r9z\\t\\n \\tR1NS) `p\)]%\\ )wX`\\t&n=\\t\\n*|\\t[]F\\tkR-1_<\\tlK--F,\\ta}\\t:=\\tQ|\\t%s\\r~Q\\tM??\\tc>?\\t<v\\tfE[\\thj*>\\tO=/\\t>n#@ ^ZK=_l-VCSZ1\\r`'
    //   11: dup
    //   12: astore_2
    //   13: invokevirtual length : ()I
    //   16: istore #4
    //   18: bipush #77
    //   20: istore_1
    //   21: iconst_m1
    //   22: istore_0
    //   23: bipush #112
    //   25: iinc #0, 1
    //   28: aload_2
    //   29: iload_0
    //   30: dup
    //   31: iload_1
    //   32: iadd
    //   33: invokevirtual substring : (II)Ljava/lang/String;
    //   36: iconst_m1
    //   37: goto -> 143
    //   40: aload #5
    //   42: swap
    //   43: iload_3
    //   44: iinc #3, 1
    //   47: swap
    //   48: aastore
    //   49: iload_0
    //   50: iload_1
    //   51: iadd
    //   52: dup
    //   53: istore_0
    //   54: iload #4
    //   56: if_icmpge -> 68
    //   59: aload_2
    //   60: iload_0
    //   61: invokevirtual charAt : (I)C
    //   64: istore_1
    //   65: goto -> 23
    //   68: ldc '6GD4\\tzO'
    //   70: dup
    //   71: astore_2
    //   72: invokevirtual length : ()I
    //   75: istore #4
    //   77: bipush #9
    //   79: istore_1
    //   80: iconst_m1
    //   81: istore_0
    //   82: bipush #37
    //   84: iinc #0, 1
    //   87: aload_2
    //   88: iload_0
    //   89: dup
    //   90: iload_1
    //   91: iadd
    //   92: invokevirtual substring : (II)Ljava/lang/String;
    //   95: iconst_0
    //   96: goto -> 143
    //   99: aload #5
    //   101: swap
    //   102: iload_3
    //   103: iinc #3, 1
    //   106: swap
    //   107: aastore
    //   108: iload_0
    //   109: iload_1
    //   110: iadd
    //   111: dup
    //   112: istore_0
    //   113: iload #4
    //   115: if_icmpge -> 127
    //   118: aload_2
    //   119: iload_0
    //   120: invokevirtual charAt : (I)C
    //   123: istore_1
    //   124: goto -> 82
    //   127: aload #5
    //   129: putstatic burp/Zsbd.a : [Ljava/lang/String;
    //   132: bipush #28
    //   134: anewarray java/lang/String
    //   137: putstatic burp/Zsbd.b : [Ljava/lang/String;
    //   140: goto -> 300
    //   143: dup_x2
    //   144: pop
    //   145: invokevirtual toCharArray : ()[C
    //   148: dup_x1
    //   149: arraylength
    //   150: dup_x2
    //   151: pop
    //   152: iconst_0
    //   153: istore #6
    //   155: dup2_x1
    //   156: pop2
    //   157: dup_x2
    //   158: iconst_1
    //   159: if_icmpgt -> 260
    //   162: dup2
    //   163: swap
    //   164: iload #6
    //   166: dup2_x1
    //   167: caload
    //   168: swap
    //   169: iload #6
    //   171: bipush #7
    //   173: irem
    //   174: tableswitch default -> 242, 0 -> 212, 1 -> 217, 2 -> 222, 3 -> 227, 4 -> 232, 5 -> 237
    //   212: bipush #53
    //   214: goto -> 244
    //   217: bipush #118
    //   219: goto -> 244
    //   222: bipush #66
    //   224: goto -> 244
    //   227: bipush #124
    //   229: goto -> 244
    //   232: bipush #96
    //   234: goto -> 244
    //   237: bipush #47
    //   239: goto -> 244
    //   242: bipush #31
    //   244: ixor
    //   245: ixor
    //   246: i2c
    //   247: castore
    //   248: iinc #6, 1
    //   251: dup
    //   252: ifne -> 260
    //   255: dup2
    //   256: dup_x1
    //   257: goto -> 166
    //   260: dup2_x1
    //   261: pop2
    //   262: dup_x2
    //   263: iload #6
    //   265: if_icmpgt -> 162
    //   268: pop
    //   269: new java/lang/String
    //   272: dup_x1
    //   273: swap
    //   274: invokespecial <init> : ([C)V
    //   277: invokevirtual intern : ()Ljava/lang/String;
    //   280: swap
    //   281: pop
    //   282: swap
    //   283: tableswitch default -> 40, 0 -> 99
    //   300: new java/math/BigInteger
    //   303: dup
    //   304: sipush #-17785
    //   307: sipush #-32698
    //   310: invokestatic a : (II)Ljava/lang/String;
    //   313: invokespecial <init> : (Ljava/lang/String;)V
    //   316: putstatic burp/Zsbd.Zh : Ljava/lang/Object;
    //   319: sipush #-17762
    //   322: sipush #-27513
    //   325: invokestatic a : (II)Ljava/lang/String;
    //   328: putstatic burp/Zsbd.ZA : Ljava/lang/String;
    //   331: return
  }
  
  private static Throwable a(Throwable paramThrowable) {
    return paramThrowable;
  }
  
  private static String a(int paramInt1, int paramInt2) {
    int i = (paramInt1 ^ 0xFFFFBA87) & 0xFFFF;
    if (b[i] == null) {
      char[] arrayOfChar = a[i].toCharArray();
      switch (arrayOfChar[0] & 0xFF) {
        case 0:
        
        case 1:
        
        case 2:
        
        case 3:
        
        case 4:
        
        case 5:
        
        case 6:
        
        case 7:
        
        case 8:
        
        case 9:
        
        case 10:
        
        case 11:
        
        case 12:
        
        case 13:
        
        case 14:
        
        case 15:
        
        case 16:
        
        case 17:
        
        case 18:
        
        case 19:
        
        case 20:
        
        case 21:
        
        case 22:
        
        case 23:
        
        case 24:
        
        case 25:
        
        case 26:
        
        case 27:
        
        case 28:
        
        case 29:
        
        case 30:
        
        case 31:
        
        case 32:
        
        case 33:
        
        case 34:
        
        case 35:
        
        case 36:
        
        case 37:
        
        case 38:
        
        case 39:
        
        case 40:
        
        case 41:
        
        case 42:
        
        case 43:
        
        case 44:
        
        case 45:
        
        case 46:
        
        case 47:
        
        case 48:
        
        case 49:
        
        case 50:
        
        case 51:
        
        case 52:
        
        case 53:
        
        case 54:
        
        case 55:
        
        case 56:
        
        case 57:
        
        case 58:
        
        case 59:
        
        case 60:
        
        case 61:
        
        case 62:
        
        case 63:
        
        case 64:
        
        case 65:
        
        case 66:
        
        case 67:
        
        case 68:
        
        case 69:
        
        case 70:
        
        case 71:
        
        case 72:
        
        case 73:
        
        case 74:
        
        case 75:
        
        case 76:
        
        case 77:
        
        case 78:
        
        case 79:
        
        case 80:
        
        case 81:
        
        case 82:
        
        case 83:
        
        case 84:
        
        case 85:
        
        case 86:
        
        case 87:
        
        case 88:
        
        case 89:
        
        case 90:
        
        case 91:
        
        case 92:
        
        case 93:
        
        case 94:
        
        case 95:
        
        case 96:
        
        case 97:
        
        case 98:
        
        case 99:
        
        case 100:
        
        case 101:
        
        case 102:
        
        case 103:
        
        case 104:
        
        case 105:
        
        case 106:
        
        case 107:
        
        case 108:
        
        case 109:
        
        case 110:
        
        case 111:
        
        case 112:
        
        case 113:
        
        case 114:
        
        case 115:
        
        case 116:
        
        case 117:
        
        case 118:
        
        case 119:
        
        case 120:
        
        case 121:
        
        case 122:
        
        case 123:
        
        case 124:
        
        case 125:
        
        case 126:
        
        case 127:
        
        case 128:
        
        case 129:
        
        case 130:
        
        case 131:
        
        case 132:
        
        case 133:
        
        case 134:
        
        case 135:
        
        case 136:
        
        case 137:
        
        case 138:
        
        case 139:
        
        case 140:
        
        case 141:
        
        case 142:
        
        case 143:
        
        case 144:
        
        case 145:
        
        case 146:
        
        case 147:
        
        case 148:
        
        case 149:
        
        case 150:
        
        case 151:
        
        case 152:
        
        case 153:
        
        case 154:
        
        case 155:
        
        case 156:
        
        case 157:
        
        case 158:
        
        case 159:
        
        case 160:
        
        case 161:
        
        case 162:
        
        case 163:
        
        case 164:
        
        case 165:
        
        case 166:
        
        case 167:
        
        case 168:
        
        case 169:
        
        case 170:
        
        case 171:
        
        case 172:
        
        case 173:
        
        case 174:
        
        case 175:
        
        case 176:
        
        case 177:
        
        case 178:
        
        case 179:
        
        case 180:
        
        case 181:
        
        case 182:
        
        case 183:
        
        case 184:
        
        case 185:
        
        case 186:
        
        case 187:
        
        case 188:
        
        case 189:
        
        case 190:
        
        case 191:
        
        case 192:
        
        case 193:
        
        case 194:
        
        case 195:
        
        case 196:
        
        case 197:
        
        case 198:
        
        case 199:
        
        case 200:
        
        case 201:
        
        case 202:
        
        case 203:
        
        case 204:
        
        case 205:
        
        case 206:
        
        case 207:
        
        case 208:
        
        case 209:
        
        case 210:
        
        case 211:
        
        case 212:
        
        case 213:
        
        case 214:
        
        case 215:
        
        case 216:
        
        case 217:
        
        case 218:
        
        case 219:
        
        case 220:
        
        case 221:
        
        case 222:
        
        case 223:
        
        case 224:
        
        case 225:
        
        case 226:
        
        case 227:
        
        case 228:
        
        case 229:
        
        case 230:
        
        case 231:
        
        case 232:
        
        case 233:
        
        case 234:
        
        case 235:
        
        case 236:
        
        case 237:
        
        case 238:
        
        case 239:
        
        case 240:
        
        case 241:
        
        case 242:
        
        case 243:
        
        case 244:
        
        case 245:
        
        case 246:
        
        case 247:
        
        case 248:
        
        case 249:
        
        case 250:
        
        case 251:
        
        case 252:
        
        case 253:
        
        case 254:
        
        default:
          break;
      } 
      byte b1 = 46;
      int j = (paramInt2 & 0xFF) - b1;
      if (j < 0)
        j += 256; 
      int k = ((paramInt2 & 0xFFFF) >>> 8) - b1;
      if (k < 0)
        k += 256; 
      for (byte b2 = 0; b2 < arrayOfChar.length; b2++) {
        int m = b2 % 2;
        if (m == 0) {
          arrayOfChar[b2] = (char)(arrayOfChar[b2] ^ j);
          j = ((j >>> 3 | j << 5) ^ arrayOfChar[b2]) & 0xFF;
        } else {
          arrayOfChar[b2] = (char)(arrayOfChar[b2] ^ k);
          k = ((k >>> 3 | k << 5) ^ arrayOfChar[b2]) & 0xFF;
        } 
      } 
      b[i] = (new String(arrayOfChar)).intern();
    } 
    return b[i];
  }
}


/* Location:              C:\Program Files\BurpSuitePro\burpsuite_pro.jar!\burp\Zsbd.class
 * Java compiler version: 21 (65.0)
 * JD-Core Version:       1.1.3
 */