package burp;

import java.math.BigInteger;

class Zsbo extends ClassLoader {
  static Object ZG;
  
  static String Zg;
  
  private static final String[] a;
  
  private static final String[] b;
  
  static void ZI(Object[] paramArrayOfObject, Object paramObject) throws Throwable {}
  
  static void Za(Object paramObject) {
    Zs8w.ZR = a(-20541, -20581);
    Zs8w.ZW = new BigInteger(a(-20531, 14457));
    boolean bool = Zt2e.ZK();
    try {
      try {
        if (Zsn4.ZZ.charAt(Math.abs(((BigInteger)Ze1k.ZD).intValue() % 32)) <= Zr36.Ze.charAt(Math.abs(((BigInteger)Zr1t.ZP).intValue() % 32))) {
          try {
            Zgjs.ZW(Class.forName(a(-20533, 23743)));
            if (bool)
              Zlwc.Zd(Class.forName(a(-20530, -52))); 
          } catch (Throwable throwable) {
            throw a(null);
          } 
          return;
        } 
      } catch (Throwable throwable) {
        throw a(null);
      } 
      Zlwc.Zd(Class.forName(a(-20530, -52)));
    } catch (Throwable throwable) {}
  }
  
  static boolean ZZ(Object[] paramArrayOfObject, Object paramObject) throws Throwable {
    // Byte code:
    //   0: invokestatic ZK : ()Z
    //   3: istore_2
    //   4: getstatic burp/Zmdi.Zw : Ljava/lang/Object;
    //   7: checkcast java/math/BigInteger
    //   10: invokevirtual toByteArray : ()[B
    //   13: astore_3
    //   14: bipush #32
    //   16: newarray int
    //   18: dup
    //   19: iconst_0
    //   20: ldc 876216579
    //   22: iastore
    //   23: dup
    //   24: iconst_1
    //   25: ldc 455999525
    //   27: iastore
    //   28: dup
    //   29: iconst_2
    //   30: ldc 1043334948
    //   32: iastore
    //   33: dup
    //   34: iconst_3
    //   35: ldc 439222784
    //   37: iastore
    //   38: dup
    //   39: iconst_4
    //   40: ldc 372376604
    //   42: iastore
    //   43: dup
    //   44: iconst_5
    //   45: ldc 707731490
    //   47: iastore
    //   48: dup
    //   49: bipush #6
    //   51: ldc 389426184
    //   53: iastore
    //   54: dup
    //   55: bipush #7
    //   57: ldc 973875457
    //   59: iastore
    //   60: dup
    //   61: bipush #8
    //   63: ldc 389160971
    //   65: iastore
    //   66: dup
    //   67: bipush #9
    //   69: ldc 907870729
    //   71: iastore
    //   72: dup
    //   73: bipush #10
    //   75: ldc 121057538
    //   77: iastore
    //   78: dup
    //   79: bipush #11
    //   81: ldc 840500228
    //   83: iastore
    //   84: dup
    //   85: bipush #12
    //   87: ldc 254150144
    //   89: iastore
    //   90: dup
    //   91: bipush #13
    //   93: ldc 924386310
    //   95: iastore
    //   96: dup
    //   97: bipush #14
    //   99: ldc 187632156
    //   101: iastore
    //   102: dup
    //   103: bipush #15
    //   105: ldc 874189824
    //   107: iastore
    //   108: dup
    //   109: bipush #16
    //   111: ldc 655302664
    //   113: iastore
    //   114: dup
    //   115: bipush #17
    //   117: ldc 890966315
    //   119: iastore
    //   120: dup
    //   121: bipush #18
    //   123: ldc 722417666
    //   125: iastore
    //   126: dup
    //   127: bipush #19
    //   129: ldc 1026621720
    //   131: iastore
    //   132: dup
    //   133: bipush #20
    //   135: ldc 957157408
    //   137: iastore
    //   138: dup
    //   139: bipush #21
    //   141: ldc 892536332
    //   143: iastore
    //   144: dup
    //   145: bipush #22
    //   147: ldc 689771012
    //   149: iastore
    //   150: dup
    //   151: bipush #23
    //   153: ldc 221709344
    //   155: iastore
    //   156: dup
    //   157: bipush #24
    //   159: ldc 940377620
    //   161: iastore
    //   162: dup
    //   163: bipush #25
    //   165: ldc 255209728
    //   167: iastore
    //   168: dup
    //   169: bipush #26
    //   171: ldc 1010368540
    //   173: iastore
    //   174: dup
    //   175: bipush #27
    //   177: ldc 220604441
    //   179: iastore
    //   180: dup
    //   181: bipush #28
    //   183: ldc 1008414755
    //   185: iastore
    //   186: dup
    //   187: bipush #29
    //   189: ldc 187049985
    //   191: iastore
    //   192: dup
    //   193: bipush #30
    //   195: ldc 943331329
    //   197: iastore
    //   198: dup
    //   199: bipush #31
    //   201: ldc 170788368
    //   203: iastore
    //   204: astore #5
    //   206: bipush #64
    //   208: newarray int
    //   210: dup
    //   211: iconst_0
    //   212: ldc 16843776
    //   214: iastore
    //   215: dup
    //   216: iconst_1
    //   217: iconst_0
    //   218: iastore
    //   219: dup
    //   220: iconst_2
    //   221: ldc 65536
    //   223: iastore
    //   224: dup
    //   225: iconst_3
    //   226: ldc 16843780
    //   228: iastore
    //   229: dup
    //   230: iconst_4
    //   231: ldc 16842756
    //   233: iastore
    //   234: dup
    //   235: iconst_5
    //   236: ldc 66564
    //   238: iastore
    //   239: dup
    //   240: bipush #6
    //   242: iconst_4
    //   243: iastore
    //   244: dup
    //   245: bipush #7
    //   247: ldc 65536
    //   249: iastore
    //   250: dup
    //   251: bipush #8
    //   253: sipush #1024
    //   256: iastore
    //   257: dup
    //   258: bipush #9
    //   260: ldc 16843776
    //   262: iastore
    //   263: dup
    //   264: bipush #10
    //   266: ldc 16843780
    //   268: iastore
    //   269: dup
    //   270: bipush #11
    //   272: sipush #1024
    //   275: iastore
    //   276: dup
    //   277: bipush #12
    //   279: ldc 16778244
    //   281: iastore
    //   282: dup
    //   283: bipush #13
    //   285: ldc 16842756
    //   287: iastore
    //   288: dup
    //   289: bipush #14
    //   291: ldc 16777216
    //   293: iastore
    //   294: dup
    //   295: bipush #15
    //   297: iconst_4
    //   298: iastore
    //   299: dup
    //   300: bipush #16
    //   302: sipush #1028
    //   305: iastore
    //   306: dup
    //   307: bipush #17
    //   309: ldc 16778240
    //   311: iastore
    //   312: dup
    //   313: bipush #18
    //   315: ldc 16778240
    //   317: iastore
    //   318: dup
    //   319: bipush #19
    //   321: ldc 66560
    //   323: iastore
    //   324: dup
    //   325: bipush #20
    //   327: ldc 66560
    //   329: iastore
    //   330: dup
    //   331: bipush #21
    //   333: ldc 16842752
    //   335: iastore
    //   336: dup
    //   337: bipush #22
    //   339: ldc 16842752
    //   341: iastore
    //   342: dup
    //   343: bipush #23
    //   345: ldc 16778244
    //   347: iastore
    //   348: dup
    //   349: bipush #24
    //   351: ldc 65540
    //   353: iastore
    //   354: dup
    //   355: bipush #25
    //   357: ldc 16777220
    //   359: iastore
    //   360: dup
    //   361: bipush #26
    //   363: ldc 16777220
    //   365: iastore
    //   366: dup
    //   367: bipush #27
    //   369: ldc 65540
    //   371: iastore
    //   372: dup
    //   373: bipush #28
    //   375: iconst_0
    //   376: iastore
    //   377: dup
    //   378: bipush #29
    //   380: sipush #1028
    //   383: iastore
    //   384: dup
    //   385: bipush #30
    //   387: ldc 66564
    //   389: iastore
    //   390: dup
    //   391: bipush #31
    //   393: ldc 16777216
    //   395: iastore
    //   396: dup
    //   397: bipush #32
    //   399: ldc 65536
    //   401: iastore
    //   402: dup
    //   403: bipush #33
    //   405: ldc 16843780
    //   407: iastore
    //   408: dup
    //   409: bipush #34
    //   411: iconst_4
    //   412: iastore
    //   413: dup
    //   414: bipush #35
    //   416: ldc 16842752
    //   418: iastore
    //   419: dup
    //   420: bipush #36
    //   422: ldc 16843776
    //   424: iastore
    //   425: dup
    //   426: bipush #37
    //   428: ldc 16777216
    //   430: iastore
    //   431: dup
    //   432: bipush #38
    //   434: ldc 16777216
    //   436: iastore
    //   437: dup
    //   438: bipush #39
    //   440: sipush #1024
    //   443: iastore
    //   444: dup
    //   445: bipush #40
    //   447: ldc 16842756
    //   449: iastore
    //   450: dup
    //   451: bipush #41
    //   453: ldc 65536
    //   455: iastore
    //   456: dup
    //   457: bipush #42
    //   459: ldc 66560
    //   461: iastore
    //   462: dup
    //   463: bipush #43
    //   465: ldc 16777220
    //   467: iastore
    //   468: dup
    //   469: bipush #44
    //   471: sipush #1024
    //   474: iastore
    //   475: dup
    //   476: bipush #45
    //   478: iconst_4
    //   479: iastore
    //   480: dup
    //   481: bipush #46
    //   483: ldc 16778244
    //   485: iastore
    //   486: dup
    //   487: bipush #47
    //   489: ldc 66564
    //   491: iastore
    //   492: dup
    //   493: bipush #48
    //   495: ldc 16843780
    //   497: iastore
    //   498: dup
    //   499: bipush #49
    //   501: ldc 65540
    //   503: iastore
    //   504: dup
    //   505: bipush #50
    //   507: ldc 16842752
    //   509: iastore
    //   510: dup
    //   511: bipush #51
    //   513: ldc 16778244
    //   515: iastore
    //   516: dup
    //   517: bipush #52
    //   519: ldc 16777220
    //   521: iastore
    //   522: dup
    //   523: bipush #53
    //   525: sipush #1028
    //   528: iastore
    //   529: dup
    //   530: bipush #54
    //   532: ldc 66564
    //   534: iastore
    //   535: dup
    //   536: bipush #55
    //   538: ldc 16843776
    //   540: iastore
    //   541: dup
    //   542: bipush #56
    //   544: sipush #1028
    //   547: iastore
    //   548: dup
    //   549: bipush #57
    //   551: ldc 16778240
    //   553: iastore
    //   554: dup
    //   555: bipush #58
    //   557: ldc 16778240
    //   559: iastore
    //   560: dup
    //   561: bipush #59
    //   563: iconst_0
    //   564: iastore
    //   565: dup
    //   566: bipush #60
    //   568: ldc 65540
    //   570: iastore
    //   571: dup
    //   572: bipush #61
    //   574: ldc 66560
    //   576: iastore
    //   577: dup
    //   578: bipush #62
    //   580: iconst_0
    //   581: iastore
    //   582: dup
    //   583: bipush #63
    //   585: ldc 16842756
    //   587: iastore
    //   588: astore #6
    //   590: bipush #64
    //   592: newarray int
    //   594: dup
    //   595: iconst_0
    //   596: ldc -2146402272
    //   598: iastore
    //   599: dup
    //   600: iconst_1
    //   601: ldc -2147450880
    //   603: iastore
    //   604: dup
    //   605: iconst_2
    //   606: ldc 32768
    //   608: iastore
    //   609: dup
    //   610: iconst_3
    //   611: ldc 1081376
    //   613: iastore
    //   614: dup
    //   615: iconst_4
    //   616: ldc 1048576
    //   618: iastore
    //   619: dup
    //   620: iconst_5
    //   621: bipush #32
    //   623: iastore
    //   624: dup
    //   625: bipush #6
    //   627: ldc -2146435040
    //   629: iastore
    //   630: dup
    //   631: bipush #7
    //   633: ldc -2147450848
    //   635: iastore
    //   636: dup
    //   637: bipush #8
    //   639: ldc -2147483616
    //   641: iastore
    //   642: dup
    //   643: bipush #9
    //   645: ldc -2146402272
    //   647: iastore
    //   648: dup
    //   649: bipush #10
    //   651: ldc -2146402304
    //   653: iastore
    //   654: dup
    //   655: bipush #11
    //   657: ldc -2147483648
    //   659: iastore
    //   660: dup
    //   661: bipush #12
    //   663: ldc -2147450880
    //   665: iastore
    //   666: dup
    //   667: bipush #13
    //   669: ldc 1048576
    //   671: iastore
    //   672: dup
    //   673: bipush #14
    //   675: bipush #32
    //   677: iastore
    //   678: dup
    //   679: bipush #15
    //   681: ldc -2146435040
    //   683: iastore
    //   684: dup
    //   685: bipush #16
    //   687: ldc 1081344
    //   689: iastore
    //   690: dup
    //   691: bipush #17
    //   693: ldc 1048608
    //   695: iastore
    //   696: dup
    //   697: bipush #18
    //   699: ldc -2147450848
    //   701: iastore
    //   702: dup
    //   703: bipush #19
    //   705: iconst_0
    //   706: iastore
    //   707: dup
    //   708: bipush #20
    //   710: ldc -2147483648
    //   712: iastore
    //   713: dup
    //   714: bipush #21
    //   716: ldc 32768
    //   718: iastore
    //   719: dup
    //   720: bipush #22
    //   722: ldc 1081376
    //   724: iastore
    //   725: dup
    //   726: bipush #23
    //   728: ldc -2146435072
    //   730: iastore
    //   731: dup
    //   732: bipush #24
    //   734: ldc 1048608
    //   736: iastore
    //   737: dup
    //   738: bipush #25
    //   740: ldc -2147483616
    //   742: iastore
    //   743: dup
    //   744: bipush #26
    //   746: iconst_0
    //   747: iastore
    //   748: dup
    //   749: bipush #27
    //   751: ldc 1081344
    //   753: iastore
    //   754: dup
    //   755: bipush #28
    //   757: ldc 32800
    //   759: iastore
    //   760: dup
    //   761: bipush #29
    //   763: ldc -2146402304
    //   765: iastore
    //   766: dup
    //   767: bipush #30
    //   769: ldc -2146435072
    //   771: iastore
    //   772: dup
    //   773: bipush #31
    //   775: ldc 32800
    //   777: iastore
    //   778: dup
    //   779: bipush #32
    //   781: iconst_0
    //   782: iastore
    //   783: dup
    //   784: bipush #33
    //   786: ldc 1081376
    //   788: iastore
    //   789: dup
    //   790: bipush #34
    //   792: ldc -2146435040
    //   794: iastore
    //   795: dup
    //   796: bipush #35
    //   798: ldc 1048576
    //   800: iastore
    //   801: dup
    //   802: bipush #36
    //   804: ldc -2147450848
    //   806: iastore
    //   807: dup
    //   808: bipush #37
    //   810: ldc -2146435072
    //   812: iastore
    //   813: dup
    //   814: bipush #38
    //   816: ldc -2146402304
    //   818: iastore
    //   819: dup
    //   820: bipush #39
    //   822: ldc 32768
    //   824: iastore
    //   825: dup
    //   826: bipush #40
    //   828: ldc -2146435072
    //   830: iastore
    //   831: dup
    //   832: bipush #41
    //   834: ldc -2147450880
    //   836: iastore
    //   837: dup
    //   838: bipush #42
    //   840: bipush #32
    //   842: iastore
    //   843: dup
    //   844: bipush #43
    //   846: ldc -2146402272
    //   848: iastore
    //   849: dup
    //   850: bipush #44
    //   852: ldc 1081376
    //   854: iastore
    //   855: dup
    //   856: bipush #45
    //   858: bipush #32
    //   860: iastore
    //   861: dup
    //   862: bipush #46
    //   864: ldc 32768
    //   866: iastore
    //   867: dup
    //   868: bipush #47
    //   870: ldc -2147483648
    //   872: iastore
    //   873: dup
    //   874: bipush #48
    //   876: ldc 32800
    //   878: iastore
    //   879: dup
    //   880: bipush #49
    //   882: ldc -2146402304
    //   884: iastore
    //   885: dup
    //   886: bipush #50
    //   888: ldc 1048576
    //   890: iastore
    //   891: dup
    //   892: bipush #51
    //   894: ldc -2147483616
    //   896: iastore
    //   897: dup
    //   898: bipush #52
    //   900: ldc 1048608
    //   902: iastore
    //   903: dup
    //   904: bipush #53
    //   906: ldc -2147450848
    //   908: iastore
    //   909: dup
    //   910: bipush #54
    //   912: ldc -2147483616
    //   914: iastore
    //   915: dup
    //   916: bipush #55
    //   918: ldc 1048608
    //   920: iastore
    //   921: dup
    //   922: bipush #56
    //   924: ldc 1081344
    //   926: iastore
    //   927: dup
    //   928: bipush #57
    //   930: iconst_0
    //   931: iastore
    //   932: dup
    //   933: bipush #58
    //   935: ldc -2147450880
    //   937: iastore
    //   938: dup
    //   939: bipush #59
    //   941: ldc 32800
    //   943: iastore
    //   944: dup
    //   945: bipush #60
    //   947: ldc -2147483648
    //   949: iastore
    //   950: dup
    //   951: bipush #61
    //   953: ldc -2146435040
    //   955: iastore
    //   956: dup
    //   957: bipush #62
    //   959: ldc -2146402272
    //   961: iastore
    //   962: dup
    //   963: bipush #63
    //   965: ldc 1081344
    //   967: iastore
    //   968: astore #7
    //   970: bipush #64
    //   972: newarray int
    //   974: dup
    //   975: iconst_0
    //   976: sipush #520
    //   979: iastore
    //   980: dup
    //   981: iconst_1
    //   982: ldc 134349312
    //   984: iastore
    //   985: dup
    //   986: iconst_2
    //   987: iconst_0
    //   988: iastore
    //   989: dup
    //   990: iconst_3
    //   991: ldc 134348808
    //   993: iastore
    //   994: dup
    //   995: iconst_4
    //   996: ldc 134218240
    //   998: iastore
    //   999: dup
    //   1000: iconst_5
    //   1001: iconst_0
    //   1002: iastore
    //   1003: dup
    //   1004: bipush #6
    //   1006: ldc 131592
    //   1008: iastore
    //   1009: dup
    //   1010: bipush #7
    //   1012: ldc 134218240
    //   1014: iastore
    //   1015: dup
    //   1016: bipush #8
    //   1018: ldc 131080
    //   1020: iastore
    //   1021: dup
    //   1022: bipush #9
    //   1024: ldc 134217736
    //   1026: iastore
    //   1027: dup
    //   1028: bipush #10
    //   1030: ldc 134217736
    //   1032: iastore
    //   1033: dup
    //   1034: bipush #11
    //   1036: ldc 131072
    //   1038: iastore
    //   1039: dup
    //   1040: bipush #12
    //   1042: ldc 134349320
    //   1044: iastore
    //   1045: dup
    //   1046: bipush #13
    //   1048: ldc 131080
    //   1050: iastore
    //   1051: dup
    //   1052: bipush #14
    //   1054: ldc 134348800
    //   1056: iastore
    //   1057: dup
    //   1058: bipush #15
    //   1060: sipush #520
    //   1063: iastore
    //   1064: dup
    //   1065: bipush #16
    //   1067: ldc 134217728
    //   1069: iastore
    //   1070: dup
    //   1071: bipush #17
    //   1073: bipush #8
    //   1075: iastore
    //   1076: dup
    //   1077: bipush #18
    //   1079: ldc 134349312
    //   1081: iastore
    //   1082: dup
    //   1083: bipush #19
    //   1085: sipush #512
    //   1088: iastore
    //   1089: dup
    //   1090: bipush #20
    //   1092: ldc 131584
    //   1094: iastore
    //   1095: dup
    //   1096: bipush #21
    //   1098: ldc 134348800
    //   1100: iastore
    //   1101: dup
    //   1102: bipush #22
    //   1104: ldc 134348808
    //   1106: iastore
    //   1107: dup
    //   1108: bipush #23
    //   1110: ldc 131592
    //   1112: iastore
    //   1113: dup
    //   1114: bipush #24
    //   1116: ldc 134218248
    //   1118: iastore
    //   1119: dup
    //   1120: bipush #25
    //   1122: ldc 131584
    //   1124: iastore
    //   1125: dup
    //   1126: bipush #26
    //   1128: ldc 131072
    //   1130: iastore
    //   1131: dup
    //   1132: bipush #27
    //   1134: ldc 134218248
    //   1136: iastore
    //   1137: dup
    //   1138: bipush #28
    //   1140: bipush #8
    //   1142: iastore
    //   1143: dup
    //   1144: bipush #29
    //   1146: ldc 134349320
    //   1148: iastore
    //   1149: dup
    //   1150: bipush #30
    //   1152: sipush #512
    //   1155: iastore
    //   1156: dup
    //   1157: bipush #31
    //   1159: ldc 134217728
    //   1161: iastore
    //   1162: dup
    //   1163: bipush #32
    //   1165: ldc 134349312
    //   1167: iastore
    //   1168: dup
    //   1169: bipush #33
    //   1171: ldc 134217728
    //   1173: iastore
    //   1174: dup
    //   1175: bipush #34
    //   1177: ldc 131080
    //   1179: iastore
    //   1180: dup
    //   1181: bipush #35
    //   1183: sipush #520
    //   1186: iastore
    //   1187: dup
    //   1188: bipush #36
    //   1190: ldc 131072
    //   1192: iastore
    //   1193: dup
    //   1194: bipush #37
    //   1196: ldc 134349312
    //   1198: iastore
    //   1199: dup
    //   1200: bipush #38
    //   1202: ldc 134218240
    //   1204: iastore
    //   1205: dup
    //   1206: bipush #39
    //   1208: iconst_0
    //   1209: iastore
    //   1210: dup
    //   1211: bipush #40
    //   1213: sipush #512
    //   1216: iastore
    //   1217: dup
    //   1218: bipush #41
    //   1220: ldc 131080
    //   1222: iastore
    //   1223: dup
    //   1224: bipush #42
    //   1226: ldc 134349320
    //   1228: iastore
    //   1229: dup
    //   1230: bipush #43
    //   1232: ldc 134218240
    //   1234: iastore
    //   1235: dup
    //   1236: bipush #44
    //   1238: ldc 134217736
    //   1240: iastore
    //   1241: dup
    //   1242: bipush #45
    //   1244: sipush #512
    //   1247: iastore
    //   1248: dup
    //   1249: bipush #46
    //   1251: iconst_0
    //   1252: iastore
    //   1253: dup
    //   1254: bipush #47
    //   1256: ldc 134348808
    //   1258: iastore
    //   1259: dup
    //   1260: bipush #48
    //   1262: ldc 134218248
    //   1264: iastore
    //   1265: dup
    //   1266: bipush #49
    //   1268: ldc 131072
    //   1270: iastore
    //   1271: dup
    //   1272: bipush #50
    //   1274: ldc 134217728
    //   1276: iastore
    //   1277: dup
    //   1278: bipush #51
    //   1280: ldc 134349320
    //   1282: iastore
    //   1283: dup
    //   1284: bipush #52
    //   1286: bipush #8
    //   1288: iastore
    //   1289: dup
    //   1290: bipush #53
    //   1292: ldc 131592
    //   1294: iastore
    //   1295: dup
    //   1296: bipush #54
    //   1298: ldc 131584
    //   1300: iastore
    //   1301: dup
    //   1302: bipush #55
    //   1304: ldc 134217736
    //   1306: iastore
    //   1307: dup
    //   1308: bipush #56
    //   1310: ldc 134348800
    //   1312: iastore
    //   1313: dup
    //   1314: bipush #57
    //   1316: ldc 134218248
    //   1318: iastore
    //   1319: dup
    //   1320: bipush #58
    //   1322: sipush #520
    //   1325: iastore
    //   1326: dup
    //   1327: bipush #59
    //   1329: ldc 134348800
    //   1331: iastore
    //   1332: dup
    //   1333: bipush #60
    //   1335: ldc 131592
    //   1337: iastore
    //   1338: dup
    //   1339: bipush #61
    //   1341: bipush #8
    //   1343: iastore
    //   1344: dup
    //   1345: bipush #62
    //   1347: ldc 134348808
    //   1349: iastore
    //   1350: dup
    //   1351: bipush #63
    //   1353: ldc 131584
    //   1355: iastore
    //   1356: astore #8
    //   1358: bipush #64
    //   1360: newarray int
    //   1362: dup
    //   1363: iconst_0
    //   1364: ldc 8396801
    //   1366: iastore
    //   1367: dup
    //   1368: iconst_1
    //   1369: sipush #8321
    //   1372: iastore
    //   1373: dup
    //   1374: iconst_2
    //   1375: sipush #8321
    //   1378: iastore
    //   1379: dup
    //   1380: iconst_3
    //   1381: sipush #128
    //   1384: iastore
    //   1385: dup
    //   1386: iconst_4
    //   1387: ldc 8396928
    //   1389: iastore
    //   1390: dup
    //   1391: iconst_5
    //   1392: ldc 8388737
    //   1394: iastore
    //   1395: dup
    //   1396: bipush #6
    //   1398: ldc 8388609
    //   1400: iastore
    //   1401: dup
    //   1402: bipush #7
    //   1404: sipush #8193
    //   1407: iastore
    //   1408: dup
    //   1409: bipush #8
    //   1411: iconst_0
    //   1412: iastore
    //   1413: dup
    //   1414: bipush #9
    //   1416: ldc 8396800
    //   1418: iastore
    //   1419: dup
    //   1420: bipush #10
    //   1422: ldc 8396800
    //   1424: iastore
    //   1425: dup
    //   1426: bipush #11
    //   1428: ldc 8396929
    //   1430: iastore
    //   1431: dup
    //   1432: bipush #12
    //   1434: sipush #129
    //   1437: iastore
    //   1438: dup
    //   1439: bipush #13
    //   1441: iconst_0
    //   1442: iastore
    //   1443: dup
    //   1444: bipush #14
    //   1446: ldc 8388736
    //   1448: iastore
    //   1449: dup
    //   1450: bipush #15
    //   1452: ldc 8388609
    //   1454: iastore
    //   1455: dup
    //   1456: bipush #16
    //   1458: iconst_1
    //   1459: iastore
    //   1460: dup
    //   1461: bipush #17
    //   1463: sipush #8192
    //   1466: iastore
    //   1467: dup
    //   1468: bipush #18
    //   1470: ldc 8388608
    //   1472: iastore
    //   1473: dup
    //   1474: bipush #19
    //   1476: ldc 8396801
    //   1478: iastore
    //   1479: dup
    //   1480: bipush #20
    //   1482: sipush #128
    //   1485: iastore
    //   1486: dup
    //   1487: bipush #21
    //   1489: ldc 8388608
    //   1491: iastore
    //   1492: dup
    //   1493: bipush #22
    //   1495: sipush #8193
    //   1498: iastore
    //   1499: dup
    //   1500: bipush #23
    //   1502: sipush #8320
    //   1505: iastore
    //   1506: dup
    //   1507: bipush #24
    //   1509: ldc 8388737
    //   1511: iastore
    //   1512: dup
    //   1513: bipush #25
    //   1515: iconst_1
    //   1516: iastore
    //   1517: dup
    //   1518: bipush #26
    //   1520: sipush #8320
    //   1523: iastore
    //   1524: dup
    //   1525: bipush #27
    //   1527: ldc 8388736
    //   1529: iastore
    //   1530: dup
    //   1531: bipush #28
    //   1533: sipush #8192
    //   1536: iastore
    //   1537: dup
    //   1538: bipush #29
    //   1540: ldc 8396928
    //   1542: iastore
    //   1543: dup
    //   1544: bipush #30
    //   1546: ldc 8396929
    //   1548: iastore
    //   1549: dup
    //   1550: bipush #31
    //   1552: sipush #129
    //   1555: iastore
    //   1556: dup
    //   1557: bipush #32
    //   1559: ldc 8388736
    //   1561: iastore
    //   1562: dup
    //   1563: bipush #33
    //   1565: ldc 8388609
    //   1567: iastore
    //   1568: dup
    //   1569: bipush #34
    //   1571: ldc 8396800
    //   1573: iastore
    //   1574: dup
    //   1575: bipush #35
    //   1577: ldc 8396929
    //   1579: iastore
    //   1580: dup
    //   1581: bipush #36
    //   1583: sipush #129
    //   1586: iastore
    //   1587: dup
    //   1588: bipush #37
    //   1590: iconst_0
    //   1591: iastore
    //   1592: dup
    //   1593: bipush #38
    //   1595: iconst_0
    //   1596: iastore
    //   1597: dup
    //   1598: bipush #39
    //   1600: ldc 8396800
    //   1602: iastore
    //   1603: dup
    //   1604: bipush #40
    //   1606: sipush #8320
    //   1609: iastore
    //   1610: dup
    //   1611: bipush #41
    //   1613: ldc 8388736
    //   1615: iastore
    //   1616: dup
    //   1617: bipush #42
    //   1619: ldc 8388737
    //   1621: iastore
    //   1622: dup
    //   1623: bipush #43
    //   1625: iconst_1
    //   1626: iastore
    //   1627: dup
    //   1628: bipush #44
    //   1630: ldc 8396801
    //   1632: iastore
    //   1633: dup
    //   1634: bipush #45
    //   1636: sipush #8321
    //   1639: iastore
    //   1640: dup
    //   1641: bipush #46
    //   1643: sipush #8321
    //   1646: iastore
    //   1647: dup
    //   1648: bipush #47
    //   1650: sipush #128
    //   1653: iastore
    //   1654: dup
    //   1655: bipush #48
    //   1657: ldc 8396929
    //   1659: iastore
    //   1660: dup
    //   1661: bipush #49
    //   1663: sipush #129
    //   1666: iastore
    //   1667: dup
    //   1668: bipush #50
    //   1670: iconst_1
    //   1671: iastore
    //   1672: dup
    //   1673: bipush #51
    //   1675: sipush #8192
    //   1678: iastore
    //   1679: dup
    //   1680: bipush #52
    //   1682: ldc 8388609
    //   1684: iastore
    //   1685: dup
    //   1686: bipush #53
    //   1688: sipush #8193
    //   1691: iastore
    //   1692: dup
    //   1693: bipush #54
    //   1695: ldc 8396928
    //   1697: iastore
    //   1698: dup
    //   1699: bipush #55
    //   1701: ldc 8388737
    //   1703: iastore
    //   1704: dup
    //   1705: bipush #56
    //   1707: sipush #8193
    //   1710: iastore
    //   1711: dup
    //   1712: bipush #57
    //   1714: sipush #8320
    //   1717: iastore
    //   1718: dup
    //   1719: bipush #58
    //   1721: ldc 8388608
    //   1723: iastore
    //   1724: dup
    //   1725: bipush #59
    //   1727: ldc 8396801
    //   1729: iastore
    //   1730: dup
    //   1731: bipush #60
    //   1733: sipush #128
    //   1736: iastore
    //   1737: dup
    //   1738: bipush #61
    //   1740: ldc 8388608
    //   1742: iastore
    //   1743: dup
    //   1744: bipush #62
    //   1746: sipush #8192
    //   1749: iastore
    //   1750: dup
    //   1751: bipush #63
    //   1753: ldc 8396928
    //   1755: iastore
    //   1756: astore #9
    //   1758: bipush #64
    //   1760: newarray int
    //   1762: dup
    //   1763: iconst_0
    //   1764: sipush #256
    //   1767: iastore
    //   1768: dup
    //   1769: iconst_1
    //   1770: ldc 34078976
    //   1772: iastore
    //   1773: dup
    //   1774: iconst_2
    //   1775: ldc 34078720
    //   1777: iastore
    //   1778: dup
    //   1779: iconst_3
    //   1780: ldc 1107296512
    //   1782: iastore
    //   1783: dup
    //   1784: iconst_4
    //   1785: ldc 524288
    //   1787: iastore
    //   1788: dup
    //   1789: iconst_5
    //   1790: sipush #256
    //   1793: iastore
    //   1794: dup
    //   1795: bipush #6
    //   1797: ldc 1073741824
    //   1799: iastore
    //   1800: dup
    //   1801: bipush #7
    //   1803: ldc 34078720
    //   1805: iastore
    //   1806: dup
    //   1807: bipush #8
    //   1809: ldc 1074266368
    //   1811: iastore
    //   1812: dup
    //   1813: bipush #9
    //   1815: ldc 524288
    //   1817: iastore
    //   1818: dup
    //   1819: bipush #10
    //   1821: ldc 33554688
    //   1823: iastore
    //   1824: dup
    //   1825: bipush #11
    //   1827: ldc 1074266368
    //   1829: iastore
    //   1830: dup
    //   1831: bipush #12
    //   1833: ldc 1107296512
    //   1835: iastore
    //   1836: dup
    //   1837: bipush #13
    //   1839: ldc 1107820544
    //   1841: iastore
    //   1842: dup
    //   1843: bipush #14
    //   1845: ldc 524544
    //   1847: iastore
    //   1848: dup
    //   1849: bipush #15
    //   1851: ldc 1073741824
    //   1853: iastore
    //   1854: dup
    //   1855: bipush #16
    //   1857: ldc 33554432
    //   1859: iastore
    //   1860: dup
    //   1861: bipush #17
    //   1863: ldc 1074266112
    //   1865: iastore
    //   1866: dup
    //   1867: bipush #18
    //   1869: ldc 1074266112
    //   1871: iastore
    //   1872: dup
    //   1873: bipush #19
    //   1875: iconst_0
    //   1876: iastore
    //   1877: dup
    //   1878: bipush #20
    //   1880: ldc 1073742080
    //   1882: iastore
    //   1883: dup
    //   1884: bipush #21
    //   1886: ldc 1107820800
    //   1888: iastore
    //   1889: dup
    //   1890: bipush #22
    //   1892: ldc 1107820800
    //   1894: iastore
    //   1895: dup
    //   1896: bipush #23
    //   1898: ldc 33554688
    //   1900: iastore
    //   1901: dup
    //   1902: bipush #24
    //   1904: ldc 1107820544
    //   1906: iastore
    //   1907: dup
    //   1908: bipush #25
    //   1910: ldc 1073742080
    //   1912: iastore
    //   1913: dup
    //   1914: bipush #26
    //   1916: iconst_0
    //   1917: iastore
    //   1918: dup
    //   1919: bipush #27
    //   1921: ldc 1107296256
    //   1923: iastore
    //   1924: dup
    //   1925: bipush #28
    //   1927: ldc 34078976
    //   1929: iastore
    //   1930: dup
    //   1931: bipush #29
    //   1933: ldc 33554432
    //   1935: iastore
    //   1936: dup
    //   1937: bipush #30
    //   1939: ldc 1107296256
    //   1941: iastore
    //   1942: dup
    //   1943: bipush #31
    //   1945: ldc 524544
    //   1947: iastore
    //   1948: dup
    //   1949: bipush #32
    //   1951: ldc 524288
    //   1953: iastore
    //   1954: dup
    //   1955: bipush #33
    //   1957: ldc 1107296512
    //   1959: iastore
    //   1960: dup
    //   1961: bipush #34
    //   1963: sipush #256
    //   1966: iastore
    //   1967: dup
    //   1968: bipush #35
    //   1970: ldc 33554432
    //   1972: iastore
    //   1973: dup
    //   1974: bipush #36
    //   1976: ldc 1073741824
    //   1978: iastore
    //   1979: dup
    //   1980: bipush #37
    //   1982: ldc 34078720
    //   1984: iastore
    //   1985: dup
    //   1986: bipush #38
    //   1988: ldc 1107296512
    //   1990: iastore
    //   1991: dup
    //   1992: bipush #39
    //   1994: ldc 1074266368
    //   1996: iastore
    //   1997: dup
    //   1998: bipush #40
    //   2000: ldc 33554688
    //   2002: iastore
    //   2003: dup
    //   2004: bipush #41
    //   2006: ldc 1073741824
    //   2008: iastore
    //   2009: dup
    //   2010: bipush #42
    //   2012: ldc 1107820544
    //   2014: iastore
    //   2015: dup
    //   2016: bipush #43
    //   2018: ldc 34078976
    //   2020: iastore
    //   2021: dup
    //   2022: bipush #44
    //   2024: ldc 1074266368
    //   2026: iastore
    //   2027: dup
    //   2028: bipush #45
    //   2030: sipush #256
    //   2033: iastore
    //   2034: dup
    //   2035: bipush #46
    //   2037: ldc 33554432
    //   2039: iastore
    //   2040: dup
    //   2041: bipush #47
    //   2043: ldc 1107820544
    //   2045: iastore
    //   2046: dup
    //   2047: bipush #48
    //   2049: ldc 1107820800
    //   2051: iastore
    //   2052: dup
    //   2053: bipush #49
    //   2055: ldc 524544
    //   2057: iastore
    //   2058: dup
    //   2059: bipush #50
    //   2061: ldc 1107296256
    //   2063: iastore
    //   2064: dup
    //   2065: bipush #51
    //   2067: ldc 1107820800
    //   2069: iastore
    //   2070: dup
    //   2071: bipush #52
    //   2073: ldc 34078720
    //   2075: iastore
    //   2076: dup
    //   2077: bipush #53
    //   2079: iconst_0
    //   2080: iastore
    //   2081: dup
    //   2082: bipush #54
    //   2084: ldc 1074266112
    //   2086: iastore
    //   2087: dup
    //   2088: bipush #55
    //   2090: ldc 1107296256
    //   2092: iastore
    //   2093: dup
    //   2094: bipush #56
    //   2096: ldc 524544
    //   2098: iastore
    //   2099: dup
    //   2100: bipush #57
    //   2102: ldc 33554688
    //   2104: iastore
    //   2105: dup
    //   2106: bipush #58
    //   2108: ldc 1073742080
    //   2110: iastore
    //   2111: dup
    //   2112: bipush #59
    //   2114: ldc 524288
    //   2116: iastore
    //   2117: dup
    //   2118: bipush #60
    //   2120: iconst_0
    //   2121: iastore
    //   2122: dup
    //   2123: bipush #61
    //   2125: ldc 1074266112
    //   2127: iastore
    //   2128: dup
    //   2129: bipush #62
    //   2131: ldc 34078976
    //   2133: iastore
    //   2134: dup
    //   2135: bipush #63
    //   2137: ldc 1073742080
    //   2139: iastore
    //   2140: astore #10
    //   2142: bipush #64
    //   2144: newarray int
    //   2146: dup
    //   2147: iconst_0
    //   2148: ldc 536870928
    //   2150: iastore
    //   2151: dup
    //   2152: iconst_1
    //   2153: ldc 541065216
    //   2155: iastore
    //   2156: dup
    //   2157: iconst_2
    //   2158: sipush #16384
    //   2161: iastore
    //   2162: dup
    //   2163: iconst_3
    //   2164: ldc 541081616
    //   2166: iastore
    //   2167: dup
    //   2168: iconst_4
    //   2169: ldc 541065216
    //   2171: iastore
    //   2172: dup
    //   2173: iconst_5
    //   2174: bipush #16
    //   2176: iastore
    //   2177: dup
    //   2178: bipush #6
    //   2180: ldc 541081616
    //   2182: iastore
    //   2183: dup
    //   2184: bipush #7
    //   2186: ldc 4194304
    //   2188: iastore
    //   2189: dup
    //   2190: bipush #8
    //   2192: ldc 536887296
    //   2194: iastore
    //   2195: dup
    //   2196: bipush #9
    //   2198: ldc 4210704
    //   2200: iastore
    //   2201: dup
    //   2202: bipush #10
    //   2204: ldc 4194304
    //   2206: iastore
    //   2207: dup
    //   2208: bipush #11
    //   2210: ldc 536870928
    //   2212: iastore
    //   2213: dup
    //   2214: bipush #12
    //   2216: ldc 4194320
    //   2218: iastore
    //   2219: dup
    //   2220: bipush #13
    //   2222: ldc 536887296
    //   2224: iastore
    //   2225: dup
    //   2226: bipush #14
    //   2228: ldc 536870912
    //   2230: iastore
    //   2231: dup
    //   2232: bipush #15
    //   2234: sipush #16400
    //   2237: iastore
    //   2238: dup
    //   2239: bipush #16
    //   2241: iconst_0
    //   2242: iastore
    //   2243: dup
    //   2244: bipush #17
    //   2246: ldc 4194320
    //   2248: iastore
    //   2249: dup
    //   2250: bipush #18
    //   2252: ldc 536887312
    //   2254: iastore
    //   2255: dup
    //   2256: bipush #19
    //   2258: sipush #16384
    //   2261: iastore
    //   2262: dup
    //   2263: bipush #20
    //   2265: ldc 4210688
    //   2267: iastore
    //   2268: dup
    //   2269: bipush #21
    //   2271: ldc 536887312
    //   2273: iastore
    //   2274: dup
    //   2275: bipush #22
    //   2277: bipush #16
    //   2279: iastore
    //   2280: dup
    //   2281: bipush #23
    //   2283: ldc 541065232
    //   2285: iastore
    //   2286: dup
    //   2287: bipush #24
    //   2289: ldc 541065232
    //   2291: iastore
    //   2292: dup
    //   2293: bipush #25
    //   2295: iconst_0
    //   2296: iastore
    //   2297: dup
    //   2298: bipush #26
    //   2300: ldc 4210704
    //   2302: iastore
    //   2303: dup
    //   2304: bipush #27
    //   2306: ldc 541081600
    //   2308: iastore
    //   2309: dup
    //   2310: bipush #28
    //   2312: sipush #16400
    //   2315: iastore
    //   2316: dup
    //   2317: bipush #29
    //   2319: ldc 4210688
    //   2321: iastore
    //   2322: dup
    //   2323: bipush #30
    //   2325: ldc 541081600
    //   2327: iastore
    //   2328: dup
    //   2329: bipush #31
    //   2331: ldc 536870912
    //   2333: iastore
    //   2334: dup
    //   2335: bipush #32
    //   2337: ldc 536887296
    //   2339: iastore
    //   2340: dup
    //   2341: bipush #33
    //   2343: bipush #16
    //   2345: iastore
    //   2346: dup
    //   2347: bipush #34
    //   2349: ldc 541065232
    //   2351: iastore
    //   2352: dup
    //   2353: bipush #35
    //   2355: ldc 4210688
    //   2357: iastore
    //   2358: dup
    //   2359: bipush #36
    //   2361: ldc 541081616
    //   2363: iastore
    //   2364: dup
    //   2365: bipush #37
    //   2367: ldc 4194304
    //   2369: iastore
    //   2370: dup
    //   2371: bipush #38
    //   2373: sipush #16400
    //   2376: iastore
    //   2377: dup
    //   2378: bipush #39
    //   2380: ldc 536870928
    //   2382: iastore
    //   2383: dup
    //   2384: bipush #40
    //   2386: ldc 4194304
    //   2388: iastore
    //   2389: dup
    //   2390: bipush #41
    //   2392: ldc 536887296
    //   2394: iastore
    //   2395: dup
    //   2396: bipush #42
    //   2398: ldc 536870912
    //   2400: iastore
    //   2401: dup
    //   2402: bipush #43
    //   2404: sipush #16400
    //   2407: iastore
    //   2408: dup
    //   2409: bipush #44
    //   2411: ldc 536870928
    //   2413: iastore
    //   2414: dup
    //   2415: bipush #45
    //   2417: ldc 541081616
    //   2419: iastore
    //   2420: dup
    //   2421: bipush #46
    //   2423: ldc 4210688
    //   2425: iastore
    //   2426: dup
    //   2427: bipush #47
    //   2429: ldc 541065216
    //   2431: iastore
    //   2432: dup
    //   2433: bipush #48
    //   2435: ldc 4210704
    //   2437: iastore
    //   2438: dup
    //   2439: bipush #49
    //   2441: ldc 541081600
    //   2443: iastore
    //   2444: dup
    //   2445: bipush #50
    //   2447: iconst_0
    //   2448: iastore
    //   2449: dup
    //   2450: bipush #51
    //   2452: ldc 541065232
    //   2454: iastore
    //   2455: dup
    //   2456: bipush #52
    //   2458: bipush #16
    //   2460: iastore
    //   2461: dup
    //   2462: bipush #53
    //   2464: sipush #16384
    //   2467: iastore
    //   2468: dup
    //   2469: bipush #54
    //   2471: ldc 541065216
    //   2473: iastore
    //   2474: dup
    //   2475: bipush #55
    //   2477: ldc 4210704
    //   2479: iastore
    //   2480: dup
    //   2481: bipush #56
    //   2483: sipush #16384
    //   2486: iastore
    //   2487: dup
    //   2488: bipush #57
    //   2490: ldc 4194320
    //   2492: iastore
    //   2493: dup
    //   2494: bipush #58
    //   2496: ldc 536887312
    //   2498: iastore
    //   2499: dup
    //   2500: bipush #59
    //   2502: iconst_0
    //   2503: iastore
    //   2504: dup
    //   2505: bipush #60
    //   2507: ldc 541081600
    //   2509: iastore
    //   2510: dup
    //   2511: bipush #61
    //   2513: ldc 536870912
    //   2515: iastore
    //   2516: dup
    //   2517: bipush #62
    //   2519: ldc 4194320
    //   2521: iastore
    //   2522: dup
    //   2523: bipush #63
    //   2525: ldc 536887312
    //   2527: iastore
    //   2528: astore #11
    //   2530: bipush #64
    //   2532: newarray int
    //   2534: dup
    //   2535: iconst_0
    //   2536: ldc 2097152
    //   2538: iastore
    //   2539: dup
    //   2540: iconst_1
    //   2541: ldc 69206018
    //   2543: iastore
    //   2544: dup
    //   2545: iconst_2
    //   2546: ldc 67110914
    //   2548: iastore
    //   2549: dup
    //   2550: iconst_3
    //   2551: iconst_0
    //   2552: iastore
    //   2553: dup
    //   2554: iconst_4
    //   2555: sipush #2048
    //   2558: iastore
    //   2559: dup
    //   2560: iconst_5
    //   2561: ldc 67110914
    //   2563: iastore
    //   2564: dup
    //   2565: bipush #6
    //   2567: ldc 2099202
    //   2569: iastore
    //   2570: dup
    //   2571: bipush #7
    //   2573: ldc 69208064
    //   2575: iastore
    //   2576: dup
    //   2577: bipush #8
    //   2579: ldc 69208066
    //   2581: iastore
    //   2582: dup
    //   2583: bipush #9
    //   2585: ldc 2097152
    //   2587: iastore
    //   2588: dup
    //   2589: bipush #10
    //   2591: iconst_0
    //   2592: iastore
    //   2593: dup
    //   2594: bipush #11
    //   2596: ldc 67108866
    //   2598: iastore
    //   2599: dup
    //   2600: bipush #12
    //   2602: iconst_2
    //   2603: iastore
    //   2604: dup
    //   2605: bipush #13
    //   2607: ldc 67108864
    //   2609: iastore
    //   2610: dup
    //   2611: bipush #14
    //   2613: ldc 69206018
    //   2615: iastore
    //   2616: dup
    //   2617: bipush #15
    //   2619: sipush #2050
    //   2622: iastore
    //   2623: dup
    //   2624: bipush #16
    //   2626: ldc 67110912
    //   2628: iastore
    //   2629: dup
    //   2630: bipush #17
    //   2632: ldc 2099202
    //   2634: iastore
    //   2635: dup
    //   2636: bipush #18
    //   2638: ldc 2097154
    //   2640: iastore
    //   2641: dup
    //   2642: bipush #19
    //   2644: ldc 67110912
    //   2646: iastore
    //   2647: dup
    //   2648: bipush #20
    //   2650: ldc 67108866
    //   2652: iastore
    //   2653: dup
    //   2654: bipush #21
    //   2656: ldc 69206016
    //   2658: iastore
    //   2659: dup
    //   2660: bipush #22
    //   2662: ldc 69208064
    //   2664: iastore
    //   2665: dup
    //   2666: bipush #23
    //   2668: ldc 2097154
    //   2670: iastore
    //   2671: dup
    //   2672: bipush #24
    //   2674: ldc 69206016
    //   2676: iastore
    //   2677: dup
    //   2678: bipush #25
    //   2680: sipush #2048
    //   2683: iastore
    //   2684: dup
    //   2685: bipush #26
    //   2687: sipush #2050
    //   2690: iastore
    //   2691: dup
    //   2692: bipush #27
    //   2694: ldc 69208066
    //   2696: iastore
    //   2697: dup
    //   2698: bipush #28
    //   2700: ldc 2099200
    //   2702: iastore
    //   2703: dup
    //   2704: bipush #29
    //   2706: iconst_2
    //   2707: iastore
    //   2708: dup
    //   2709: bipush #30
    //   2711: ldc 67108864
    //   2713: iastore
    //   2714: dup
    //   2715: bipush #31
    //   2717: ldc 2099200
    //   2719: iastore
    //   2720: dup
    //   2721: bipush #32
    //   2723: ldc 67108864
    //   2725: iastore
    //   2726: dup
    //   2727: bipush #33
    //   2729: ldc 2099200
    //   2731: iastore
    //   2732: dup
    //   2733: bipush #34
    //   2735: ldc 2097152
    //   2737: iastore
    //   2738: dup
    //   2739: bipush #35
    //   2741: ldc 67110914
    //   2743: iastore
    //   2744: dup
    //   2745: bipush #36
    //   2747: ldc 67110914
    //   2749: iastore
    //   2750: dup
    //   2751: bipush #37
    //   2753: ldc 69206018
    //   2755: iastore
    //   2756: dup
    //   2757: bipush #38
    //   2759: ldc 69206018
    //   2761: iastore
    //   2762: dup
    //   2763: bipush #39
    //   2765: iconst_2
    //   2766: iastore
    //   2767: dup
    //   2768: bipush #40
    //   2770: ldc 2097154
    //   2772: iastore
    //   2773: dup
    //   2774: bipush #41
    //   2776: ldc 67108864
    //   2778: iastore
    //   2779: dup
    //   2780: bipush #42
    //   2782: ldc 67110912
    //   2784: iastore
    //   2785: dup
    //   2786: bipush #43
    //   2788: ldc 2097152
    //   2790: iastore
    //   2791: dup
    //   2792: bipush #44
    //   2794: ldc 69208064
    //   2796: iastore
    //   2797: dup
    //   2798: bipush #45
    //   2800: sipush #2050
    //   2803: iastore
    //   2804: dup
    //   2805: bipush #46
    //   2807: ldc 2099202
    //   2809: iastore
    //   2810: dup
    //   2811: bipush #47
    //   2813: ldc 69208064
    //   2815: iastore
    //   2816: dup
    //   2817: bipush #48
    //   2819: sipush #2050
    //   2822: iastore
    //   2823: dup
    //   2824: bipush #49
    //   2826: ldc 67108866
    //   2828: iastore
    //   2829: dup
    //   2830: bipush #50
    //   2832: ldc 69208066
    //   2834: iastore
    //   2835: dup
    //   2836: bipush #51
    //   2838: ldc 69206016
    //   2840: iastore
    //   2841: dup
    //   2842: bipush #52
    //   2844: ldc 2099200
    //   2846: iastore
    //   2847: dup
    //   2848: bipush #53
    //   2850: iconst_0
    //   2851: iastore
    //   2852: dup
    //   2853: bipush #54
    //   2855: iconst_2
    //   2856: iastore
    //   2857: dup
    //   2858: bipush #55
    //   2860: ldc 69208066
    //   2862: iastore
    //   2863: dup
    //   2864: bipush #56
    //   2866: iconst_0
    //   2867: iastore
    //   2868: dup
    //   2869: bipush #57
    //   2871: ldc 2099202
    //   2873: iastore
    //   2874: dup
    //   2875: bipush #58
    //   2877: ldc 69206016
    //   2879: iastore
    //   2880: dup
    //   2881: bipush #59
    //   2883: sipush #2048
    //   2886: iastore
    //   2887: dup
    //   2888: bipush #60
    //   2890: ldc 67108866
    //   2892: iastore
    //   2893: dup
    //   2894: bipush #61
    //   2896: ldc 67110912
    //   2898: iastore
    //   2899: dup
    //   2900: bipush #62
    //   2902: sipush #2048
    //   2905: iastore
    //   2906: dup
    //   2907: bipush #63
    //   2909: ldc 2097154
    //   2911: iastore
    //   2912: astore #12
    //   2914: bipush #64
    //   2916: newarray int
    //   2918: dup
    //   2919: iconst_0
    //   2920: ldc 268439616
    //   2922: iastore
    //   2923: dup
    //   2924: iconst_1
    //   2925: sipush #4096
    //   2928: iastore
    //   2929: dup
    //   2930: iconst_2
    //   2931: ldc 262144
    //   2933: iastore
    //   2934: dup
    //   2935: iconst_3
    //   2936: ldc 268701760
    //   2938: iastore
    //   2939: dup
    //   2940: iconst_4
    //   2941: ldc 268435456
    //   2943: iastore
    //   2944: dup
    //   2945: iconst_5
    //   2946: ldc 268439616
    //   2948: iastore
    //   2949: dup
    //   2950: bipush #6
    //   2952: bipush #64
    //   2954: iastore
    //   2955: dup
    //   2956: bipush #7
    //   2958: ldc 268435456
    //   2960: iastore
    //   2961: dup
    //   2962: bipush #8
    //   2964: ldc 262208
    //   2966: iastore
    //   2967: dup
    //   2968: bipush #9
    //   2970: ldc 268697600
    //   2972: iastore
    //   2973: dup
    //   2974: bipush #10
    //   2976: ldc 268701760
    //   2978: iastore
    //   2979: dup
    //   2980: bipush #11
    //   2982: ldc 266240
    //   2984: iastore
    //   2985: dup
    //   2986: bipush #12
    //   2988: ldc 268701696
    //   2990: iastore
    //   2991: dup
    //   2992: bipush #13
    //   2994: ldc 266304
    //   2996: iastore
    //   2997: dup
    //   2998: bipush #14
    //   3000: sipush #4096
    //   3003: iastore
    //   3004: dup
    //   3005: bipush #15
    //   3007: bipush #64
    //   3009: iastore
    //   3010: dup
    //   3011: bipush #16
    //   3013: ldc 268697600
    //   3015: iastore
    //   3016: dup
    //   3017: bipush #17
    //   3019: ldc 268435520
    //   3021: iastore
    //   3022: dup
    //   3023: bipush #18
    //   3025: ldc 268439552
    //   3027: iastore
    //   3028: dup
    //   3029: bipush #19
    //   3031: sipush #4160
    //   3034: iastore
    //   3035: dup
    //   3036: bipush #20
    //   3038: ldc 266240
    //   3040: iastore
    //   3041: dup
    //   3042: bipush #21
    //   3044: ldc 262208
    //   3046: iastore
    //   3047: dup
    //   3048: bipush #22
    //   3050: ldc 268697664
    //   3052: iastore
    //   3053: dup
    //   3054: bipush #23
    //   3056: ldc 268701696
    //   3058: iastore
    //   3059: dup
    //   3060: bipush #24
    //   3062: sipush #4160
    //   3065: iastore
    //   3066: dup
    //   3067: bipush #25
    //   3069: iconst_0
    //   3070: iastore
    //   3071: dup
    //   3072: bipush #26
    //   3074: iconst_0
    //   3075: iastore
    //   3076: dup
    //   3077: bipush #27
    //   3079: ldc 268697664
    //   3081: iastore
    //   3082: dup
    //   3083: bipush #28
    //   3085: ldc 268435520
    //   3087: iastore
    //   3088: dup
    //   3089: bipush #29
    //   3091: ldc 268439552
    //   3093: iastore
    //   3094: dup
    //   3095: bipush #30
    //   3097: ldc 266304
    //   3099: iastore
    //   3100: dup
    //   3101: bipush #31
    //   3103: ldc 262144
    //   3105: iastore
    //   3106: dup
    //   3107: bipush #32
    //   3109: ldc 266304
    //   3111: iastore
    //   3112: dup
    //   3113: bipush #33
    //   3115: ldc 262144
    //   3117: iastore
    //   3118: dup
    //   3119: bipush #34
    //   3121: ldc 268701696
    //   3123: iastore
    //   3124: dup
    //   3125: bipush #35
    //   3127: sipush #4096
    //   3130: iastore
    //   3131: dup
    //   3132: bipush #36
    //   3134: bipush #64
    //   3136: iastore
    //   3137: dup
    //   3138: bipush #37
    //   3140: ldc 268697664
    //   3142: iastore
    //   3143: dup
    //   3144: bipush #38
    //   3146: sipush #4096
    //   3149: iastore
    //   3150: dup
    //   3151: bipush #39
    //   3153: ldc 266304
    //   3155: iastore
    //   3156: dup
    //   3157: bipush #40
    //   3159: ldc 268439552
    //   3161: iastore
    //   3162: dup
    //   3163: bipush #41
    //   3165: bipush #64
    //   3167: iastore
    //   3168: dup
    //   3169: bipush #42
    //   3171: ldc 268435520
    //   3173: iastore
    //   3174: dup
    //   3175: bipush #43
    //   3177: ldc 268697600
    //   3179: iastore
    //   3180: dup
    //   3181: bipush #44
    //   3183: ldc 268697664
    //   3185: iastore
    //   3186: dup
    //   3187: bipush #45
    //   3189: ldc 268435456
    //   3191: iastore
    //   3192: dup
    //   3193: bipush #46
    //   3195: ldc 262144
    //   3197: iastore
    //   3198: dup
    //   3199: bipush #47
    //   3201: ldc 268439616
    //   3203: iastore
    //   3204: dup
    //   3205: bipush #48
    //   3207: iconst_0
    //   3208: iastore
    //   3209: dup
    //   3210: bipush #49
    //   3212: ldc 268701760
    //   3214: iastore
    //   3215: dup
    //   3216: bipush #50
    //   3218: ldc 262208
    //   3220: iastore
    //   3221: dup
    //   3222: bipush #51
    //   3224: ldc 268435520
    //   3226: iastore
    //   3227: dup
    //   3228: bipush #52
    //   3230: ldc 268697600
    //   3232: iastore
    //   3233: dup
    //   3234: bipush #53
    //   3236: ldc 268439552
    //   3238: iastore
    //   3239: dup
    //   3240: bipush #54
    //   3242: ldc 268439616
    //   3244: iastore
    //   3245: dup
    //   3246: bipush #55
    //   3248: iconst_0
    //   3249: iastore
    //   3250: dup
    //   3251: bipush #56
    //   3253: ldc 268701760
    //   3255: iastore
    //   3256: dup
    //   3257: bipush #57
    //   3259: ldc 266240
    //   3261: iastore
    //   3262: dup
    //   3263: bipush #58
    //   3265: ldc 266240
    //   3267: iastore
    //   3268: dup
    //   3269: bipush #59
    //   3271: sipush #4160
    //   3274: iastore
    //   3275: dup
    //   3276: bipush #60
    //   3278: sipush #4160
    //   3281: iastore
    //   3282: dup
    //   3283: bipush #61
    //   3285: ldc 262208
    //   3287: iastore
    //   3288: dup
    //   3289: bipush #62
    //   3291: ldc 268435456
    //   3293: iastore
    //   3294: dup
    //   3295: bipush #63
    //   3297: ldc 268701696
    //   3299: iastore
    //   3300: astore #13
    //   3302: aload_3
    //   3303: arraylength
    //   3304: istore #14
    //   3306: iload #14
    //   3308: bipush #8
    //   3310: irem
    //   3311: ifeq -> 3335
    //   3314: new java/lang/Exception
    //   3317: dup
    //   3318: sipush #-20529
    //   3321: sipush #-25300
    //   3324: invokestatic a : (II)Ljava/lang/String;
    //   3327: invokespecial <init> : (Ljava/lang/String;)V
    //   3330: athrow
    //   3331: invokestatic a : (Ljava/lang/Throwable;)Ljava/lang/Throwable;
    //   3334: athrow
    //   3335: iconst_2
    //   3336: newarray int
    //   3338: astore #15
    //   3340: iload #14
    //   3342: newarray byte
    //   3344: astore #16
    //   3346: iload #14
    //   3348: bipush #8
    //   3350: idiv
    //   3351: istore #17
    //   3353: iconst_0
    //   3354: istore #18
    //   3356: iload #18
    //   3358: iload #17
    //   3360: if_icmpge -> 4274
    //   3363: iload #18
    //   3365: bipush #8
    //   3367: imul
    //   3368: istore #19
    //   3370: iconst_0
    //   3371: istore #20
    //   3373: iload #20
    //   3375: iconst_2
    //   3376: if_icmpge -> 3461
    //   3379: aload #15
    //   3381: iload #20
    //   3383: aload_3
    //   3384: iload #19
    //   3386: iload #20
    //   3388: iconst_4
    //   3389: imul
    //   3390: iadd
    //   3391: baload
    //   3392: sipush #255
    //   3395: iand
    //   3396: bipush #24
    //   3398: ishl
    //   3399: aload_3
    //   3400: iload #19
    //   3402: iload #20
    //   3404: iconst_4
    //   3405: imul
    //   3406: iadd
    //   3407: iconst_1
    //   3408: iadd
    //   3409: baload
    //   3410: sipush #255
    //   3413: iand
    //   3414: bipush #16
    //   3416: ishl
    //   3417: ior
    //   3418: aload_3
    //   3419: iload #19
    //   3421: iload #20
    //   3423: iconst_4
    //   3424: imul
    //   3425: iadd
    //   3426: iconst_2
    //   3427: iadd
    //   3428: baload
    //   3429: sipush #255
    //   3432: iand
    //   3433: bipush #8
    //   3435: ishl
    //   3436: ior
    //   3437: aload_3
    //   3438: iload #19
    //   3440: iload #20
    //   3442: iconst_4
    //   3443: imul
    //   3444: iadd
    //   3445: iconst_3
    //   3446: iadd
    //   3447: baload
    //   3448: sipush #255
    //   3451: iand
    //   3452: ior
    //   3453: iastore
    //   3454: iinc #20, 1
    //   3457: iload_2
    //   3458: ifeq -> 3373
    //   3461: iconst_0
    //   3462: istore #25
    //   3464: aload #15
    //   3466: iconst_0
    //   3467: iaload
    //   3468: istore #23
    //   3470: aload #15
    //   3472: iconst_1
    //   3473: iaload
    //   3474: istore #22
    //   3476: iload #23
    //   3478: iconst_4
    //   3479: iushr
    //   3480: iload #22
    //   3482: ixor
    //   3483: ldc 252645135
    //   3485: iand
    //   3486: istore #21
    //   3488: iload #22
    //   3490: iload #21
    //   3492: ixor
    //   3493: istore #22
    //   3495: iload #23
    //   3497: iload #21
    //   3499: iconst_4
    //   3500: ishl
    //   3501: ixor
    //   3502: istore #23
    //   3504: iload #23
    //   3506: bipush #16
    //   3508: iushr
    //   3509: iload #22
    //   3511: ixor
    //   3512: ldc 65535
    //   3514: iand
    //   3515: istore #21
    //   3517: iload #22
    //   3519: iload #21
    //   3521: ixor
    //   3522: istore #22
    //   3524: iload #23
    //   3526: iload #21
    //   3528: bipush #16
    //   3530: ishl
    //   3531: ixor
    //   3532: istore #23
    //   3534: iload #22
    //   3536: iconst_2
    //   3537: iushr
    //   3538: iload #23
    //   3540: ixor
    //   3541: ldc 858993459
    //   3543: iand
    //   3544: istore #21
    //   3546: iload #23
    //   3548: iload #21
    //   3550: ixor
    //   3551: istore #23
    //   3553: iload #22
    //   3555: iload #21
    //   3557: iconst_2
    //   3558: ishl
    //   3559: ixor
    //   3560: istore #22
    //   3562: iload #22
    //   3564: bipush #8
    //   3566: iushr
    //   3567: iload #23
    //   3569: ixor
    //   3570: ldc 16711935
    //   3572: iand
    //   3573: istore #21
    //   3575: iload #23
    //   3577: iload #21
    //   3579: ixor
    //   3580: istore #23
    //   3582: iload #22
    //   3584: iload #21
    //   3586: bipush #8
    //   3588: ishl
    //   3589: ixor
    //   3590: istore #22
    //   3592: iload #22
    //   3594: iconst_1
    //   3595: ishl
    //   3596: iload #22
    //   3598: bipush #31
    //   3600: iushr
    //   3601: iconst_1
    //   3602: iand
    //   3603: ior
    //   3604: istore #22
    //   3606: iload #23
    //   3608: iload #22
    //   3610: ixor
    //   3611: ldc -1431655766
    //   3613: iand
    //   3614: istore #21
    //   3616: iload #23
    //   3618: iload #21
    //   3620: ixor
    //   3621: istore #23
    //   3623: iload #22
    //   3625: iload #21
    //   3627: ixor
    //   3628: istore #22
    //   3630: iload #23
    //   3632: iconst_1
    //   3633: ishl
    //   3634: iload #23
    //   3636: bipush #31
    //   3638: iushr
    //   3639: iconst_1
    //   3640: iand
    //   3641: ior
    //   3642: istore #23
    //   3644: iconst_0
    //   3645: istore #24
    //   3647: iload #24
    //   3649: bipush #8
    //   3651: if_icmpge -> 3989
    //   3654: iload #22
    //   3656: bipush #28
    //   3658: ishl
    //   3659: iload #22
    //   3661: iconst_4
    //   3662: iushr
    //   3663: ior
    //   3664: istore #21
    //   3666: iload #21
    //   3668: aload #5
    //   3670: iload #25
    //   3672: iinc #25, 1
    //   3675: iaload
    //   3676: ixor
    //   3677: istore #21
    //   3679: aload #12
    //   3681: iload #21
    //   3683: bipush #63
    //   3685: iand
    //   3686: iaload
    //   3687: istore #20
    //   3689: iload #20
    //   3691: aload #10
    //   3693: iload #21
    //   3695: bipush #8
    //   3697: iushr
    //   3698: bipush #63
    //   3700: iand
    //   3701: iaload
    //   3702: ior
    //   3703: istore #20
    //   3705: iload #20
    //   3707: aload #8
    //   3709: iload #21
    //   3711: bipush #16
    //   3713: iushr
    //   3714: bipush #63
    //   3716: iand
    //   3717: iaload
    //   3718: ior
    //   3719: istore #20
    //   3721: iload #20
    //   3723: aload #6
    //   3725: iload #21
    //   3727: bipush #24
    //   3729: iushr
    //   3730: bipush #63
    //   3732: iand
    //   3733: iaload
    //   3734: ior
    //   3735: istore #20
    //   3737: iload #22
    //   3739: aload #5
    //   3741: iload #25
    //   3743: iinc #25, 1
    //   3746: iaload
    //   3747: ixor
    //   3748: istore #21
    //   3750: iload #20
    //   3752: aload #13
    //   3754: iload #21
    //   3756: bipush #63
    //   3758: iand
    //   3759: iaload
    //   3760: ior
    //   3761: istore #20
    //   3763: iload #20
    //   3765: aload #11
    //   3767: iload #21
    //   3769: bipush #8
    //   3771: iushr
    //   3772: bipush #63
    //   3774: iand
    //   3775: iaload
    //   3776: ior
    //   3777: istore #20
    //   3779: iload #20
    //   3781: aload #9
    //   3783: iload #21
    //   3785: bipush #16
    //   3787: iushr
    //   3788: bipush #63
    //   3790: iand
    //   3791: iaload
    //   3792: ior
    //   3793: istore #20
    //   3795: iload #20
    //   3797: aload #7
    //   3799: iload #21
    //   3801: bipush #24
    //   3803: iushr
    //   3804: bipush #63
    //   3806: iand
    //   3807: iaload
    //   3808: ior
    //   3809: istore #20
    //   3811: iload #23
    //   3813: iload #20
    //   3815: ixor
    //   3816: istore #23
    //   3818: iload #23
    //   3820: bipush #28
    //   3822: ishl
    //   3823: iload #23
    //   3825: iconst_4
    //   3826: iushr
    //   3827: ior
    //   3828: istore #21
    //   3830: iload #21
    //   3832: aload #5
    //   3834: iload #25
    //   3836: iinc #25, 1
    //   3839: iaload
    //   3840: ixor
    //   3841: istore #21
    //   3843: aload #12
    //   3845: iload #21
    //   3847: bipush #63
    //   3849: iand
    //   3850: iaload
    //   3851: istore #20
    //   3853: iload #20
    //   3855: aload #10
    //   3857: iload #21
    //   3859: bipush #8
    //   3861: iushr
    //   3862: bipush #63
    //   3864: iand
    //   3865: iaload
    //   3866: ior
    //   3867: istore #20
    //   3869: iload #20
    //   3871: aload #8
    //   3873: iload #21
    //   3875: bipush #16
    //   3877: iushr
    //   3878: bipush #63
    //   3880: iand
    //   3881: iaload
    //   3882: ior
    //   3883: istore #20
    //   3885: iload #20
    //   3887: aload #6
    //   3889: iload #21
    //   3891: bipush #24
    //   3893: iushr
    //   3894: bipush #63
    //   3896: iand
    //   3897: iaload
    //   3898: ior
    //   3899: istore #20
    //   3901: iload #23
    //   3903: aload #5
    //   3905: iload #25
    //   3907: iinc #25, 1
    //   3910: iaload
    //   3911: ixor
    //   3912: istore #21
    //   3914: iload #20
    //   3916: aload #13
    //   3918: iload #21
    //   3920: bipush #63
    //   3922: iand
    //   3923: iaload
    //   3924: ior
    //   3925: istore #20
    //   3927: iload #20
    //   3929: aload #11
    //   3931: iload #21
    //   3933: bipush #8
    //   3935: iushr
    //   3936: bipush #63
    //   3938: iand
    //   3939: iaload
    //   3940: ior
    //   3941: istore #20
    //   3943: iload #20
    //   3945: aload #9
    //   3947: iload #21
    //   3949: bipush #16
    //   3951: iushr
    //   3952: bipush #63
    //   3954: iand
    //   3955: iaload
    //   3956: ior
    //   3957: istore #20
    //   3959: iload #20
    //   3961: aload #7
    //   3963: iload #21
    //   3965: bipush #24
    //   3967: iushr
    //   3968: bipush #63
    //   3970: iand
    //   3971: iaload
    //   3972: ior
    //   3973: istore #20
    //   3975: iload #22
    //   3977: iload #20
    //   3979: ixor
    //   3980: istore #22
    //   3982: iinc #24, 1
    //   3985: iload_2
    //   3986: ifeq -> 3647
    //   3989: iload #22
    //   3991: bipush #31
    //   3993: ishl
    //   3994: iload #22
    //   3996: iconst_1
    //   3997: iushr
    //   3998: ior
    //   3999: istore #22
    //   4001: iload #23
    //   4003: iload #22
    //   4005: ixor
    //   4006: ldc -1431655766
    //   4008: iand
    //   4009: istore #21
    //   4011: iload #23
    //   4013: iload #21
    //   4015: ixor
    //   4016: istore #23
    //   4018: iload #22
    //   4020: iload #21
    //   4022: ixor
    //   4023: istore #22
    //   4025: iload #23
    //   4027: bipush #31
    //   4029: ishl
    //   4030: iload #23
    //   4032: iconst_1
    //   4033: iushr
    //   4034: ior
    //   4035: istore #23
    //   4037: iload #23
    //   4039: bipush #8
    //   4041: iushr
    //   4042: iload #22
    //   4044: ixor
    //   4045: ldc 16711935
    //   4047: iand
    //   4048: istore #21
    //   4050: iload #22
    //   4052: iload #21
    //   4054: ixor
    //   4055: istore #22
    //   4057: iload #23
    //   4059: iload #21
    //   4061: bipush #8
    //   4063: ishl
    //   4064: ixor
    //   4065: istore #23
    //   4067: iload #23
    //   4069: iconst_2
    //   4070: iushr
    //   4071: iload #22
    //   4073: ixor
    //   4074: ldc 858993459
    //   4076: iand
    //   4077: istore #21
    //   4079: iload #22
    //   4081: iload #21
    //   4083: ixor
    //   4084: istore #22
    //   4086: iload #23
    //   4088: iload #21
    //   4090: iconst_2
    //   4091: ishl
    //   4092: ixor
    //   4093: istore #23
    //   4095: iload #22
    //   4097: bipush #16
    //   4099: iushr
    //   4100: iload #23
    //   4102: ixor
    //   4103: ldc 65535
    //   4105: iand
    //   4106: istore #21
    //   4108: iload #23
    //   4110: iload #21
    //   4112: ixor
    //   4113: istore #23
    //   4115: iload #22
    //   4117: iload #21
    //   4119: bipush #16
    //   4121: ishl
    //   4122: ixor
    //   4123: istore #22
    //   4125: iload #22
    //   4127: iconst_4
    //   4128: iushr
    //   4129: iload #23
    //   4131: ixor
    //   4132: ldc 252645135
    //   4134: iand
    //   4135: istore #21
    //   4137: iload #23
    //   4139: iload #21
    //   4141: ixor
    //   4142: istore #23
    //   4144: iload #22
    //   4146: iload #21
    //   4148: iconst_4
    //   4149: ishl
    //   4150: ixor
    //   4151: istore #22
    //   4153: aload #15
    //   4155: iconst_0
    //   4156: iload #22
    //   4158: iastore
    //   4159: aload #15
    //   4161: iconst_1
    //   4162: iload #23
    //   4164: iastore
    //   4165: iload #18
    //   4167: bipush #8
    //   4169: imul
    //   4170: istore #26
    //   4172: iconst_0
    //   4173: istore #27
    //   4175: iload #27
    //   4177: iconst_2
    //   4178: if_icmpge -> 4267
    //   4181: aload #16
    //   4183: iload #26
    //   4185: iload #27
    //   4187: iconst_4
    //   4188: imul
    //   4189: iadd
    //   4190: aload #15
    //   4192: iload #27
    //   4194: iaload
    //   4195: bipush #24
    //   4197: iushr
    //   4198: i2b
    //   4199: bastore
    //   4200: aload #16
    //   4202: iload #26
    //   4204: iload #27
    //   4206: iconst_4
    //   4207: imul
    //   4208: iadd
    //   4209: iconst_1
    //   4210: iadd
    //   4211: aload #15
    //   4213: iload #27
    //   4215: iaload
    //   4216: bipush #16
    //   4218: iushr
    //   4219: i2b
    //   4220: bastore
    //   4221: aload #16
    //   4223: iload #26
    //   4225: iload #27
    //   4227: iconst_4
    //   4228: imul
    //   4229: iadd
    //   4230: iconst_2
    //   4231: iadd
    //   4232: aload #15
    //   4234: iload #27
    //   4236: iaload
    //   4237: bipush #8
    //   4239: iushr
    //   4240: i2b
    //   4241: bastore
    //   4242: aload #16
    //   4244: iload #26
    //   4246: iload #27
    //   4248: iconst_4
    //   4249: imul
    //   4250: iadd
    //   4251: iconst_3
    //   4252: iadd
    //   4253: aload #15
    //   4255: iload #27
    //   4257: iaload
    //   4258: i2b
    //   4259: bastore
    //   4260: iinc #27, 1
    //   4263: iload_2
    //   4264: ifeq -> 4175
    //   4267: iinc #18, 1
    //   4270: iload_2
    //   4271: ifeq -> 3356
    //   4274: aload #16
    //   4276: aload #16
    //   4278: arraylength
    //   4279: iconst_1
    //   4280: isub
    //   4281: baload
    //   4282: istore #18
    //   4284: aload #16
    //   4286: arraylength
    //   4287: iload #18
    //   4289: isub
    //   4290: newarray byte
    //   4292: astore #4
    //   4294: aload #16
    //   4296: arraylength
    //   4297: aload #4
    //   4299: arraylength
    //   4300: if_icmpge -> 4324
    //   4303: new java/lang/Exception
    //   4306: dup
    //   4307: sipush #-20542
    //   4310: sipush #-9604
    //   4313: invokestatic a : (II)Ljava/lang/String;
    //   4316: invokespecial <init> : (Ljava/lang/String;)V
    //   4319: athrow
    //   4320: invokestatic a : (Ljava/lang/Throwable;)Ljava/lang/Throwable;
    //   4323: athrow
    //   4324: iconst_0
    //   4325: istore #19
    //   4327: iload #19
    //   4329: aload #4
    //   4331: arraylength
    //   4332: if_icmpge -> 4352
    //   4335: aload #4
    //   4337: iload #19
    //   4339: aload #16
    //   4341: iload #19
    //   4343: baload
    //   4344: bastore
    //   4345: iinc #19, 1
    //   4348: iload_2
    //   4349: ifeq -> 4327
    //   4352: new java/math/BigInteger
    //   4355: dup
    //   4356: aload #4
    //   4358: invokespecial <init> : ([B)V
    //   4361: invokevirtual abs : ()Ljava/math/BigInteger;
    //   4364: putstatic burp/Zscz.ZN : Ljava/lang/Object;
    //   4367: new java/lang/StringBuilder
    //   4370: dup
    //   4371: invokespecial <init> : ()V
    //   4374: astore_3
    //   4375: iconst_0
    //   4376: istore #4
    //   4378: iload #4
    //   4380: bipush #32
    //   4382: if_icmpge -> 5715
    //   4385: iload #4
    //   4387: tableswitch default -> 5708, 0 -> 4528, 1 -> 4565, 2 -> 4602, 3 -> 4639, 4 -> 4676, 5 -> 4713, 6 -> 4750, 7 -> 4787, 8 -> 4824, 9 -> 4861, 10 -> 4898, 11 -> 4935, 12 -> 4972, 13 -> 5009, 14 -> 5046, 15 -> 5083, 16 -> 5120, 17 -> 5157, 18 -> 5194, 19 -> 5231, 20 -> 5268, 21 -> 5305, 22 -> 5342, 23 -> 5379, 24 -> 5416, 25 -> 5453, 26 -> 5490, 27 -> 5527, 28 -> 5564, 29 -> 5601, 30 -> 5638, 31 -> 5675
    //   4528: aload_3
    //   4529: getstatic burp/Zl_a.ZD : Ljava/lang/String;
    //   4532: getstatic burp/Zb2u.ZY : Ljava/lang/Object;
    //   4535: checkcast java/math/BigInteger
    //   4538: invokevirtual intValue : ()I
    //   4541: bipush #32
    //   4543: irem
    //   4544: invokestatic abs : (I)I
    //   4547: invokevirtual charAt : (I)C
    //   4550: invokevirtual append : (C)Ljava/lang/StringBuilder;
    //   4553: pop
    //   4554: iload_2
    //   4555: ifeq -> 5708
    //   4558: goto -> 4565
    //   4561: invokestatic a : (Ljava/lang/Throwable;)Ljava/lang/Throwable;
    //   4564: athrow
    //   4565: aload_3
    //   4566: getstatic burp/Zsn4.ZZ : Ljava/lang/String;
    //   4569: getstatic burp/Zegj.ZT : Ljava/lang/Object;
    //   4572: checkcast java/math/BigInteger
    //   4575: invokevirtual intValue : ()I
    //   4578: bipush #32
    //   4580: irem
    //   4581: invokestatic abs : (I)I
    //   4584: invokevirtual charAt : (I)C
    //   4587: invokevirtual append : (C)Ljava/lang/StringBuilder;
    //   4590: pop
    //   4591: iload_2
    //   4592: ifeq -> 5708
    //   4595: goto -> 4602
    //   4598: invokestatic a : (Ljava/lang/Throwable;)Ljava/lang/Throwable;
    //   4601: athrow
    //   4602: aload_3
    //   4603: getstatic burp/Zmf6.Zn : Ljava/lang/String;
    //   4606: getstatic burp/Zscf.ZG : Ljava/lang/Object;
    //   4609: checkcast java/math/BigInteger
    //   4612: invokevirtual intValue : ()I
    //   4615: bipush #32
    //   4617: irem
    //   4618: invokestatic abs : (I)I
    //   4621: invokevirtual charAt : (I)C
    //   4624: invokevirtual append : (C)Ljava/lang/StringBuilder;
    //   4627: pop
    //   4628: iload_2
    //   4629: ifeq -> 5708
    //   4632: goto -> 4639
    //   4635: invokestatic a : (Ljava/lang/Throwable;)Ljava/lang/Throwable;
    //   4638: athrow
    //   4639: aload_3
    //   4640: getstatic burp/Zgpx.Z_ : Ljava/lang/String;
    //   4643: getstatic burp/Zlc2.ZQ : Ljava/lang/Object;
    //   4646: checkcast java/math/BigInteger
    //   4649: invokevirtual intValue : ()I
    //   4652: bipush #32
    //   4654: irem
    //   4655: invokestatic abs : (I)I
    //   4658: invokevirtual charAt : (I)C
    //   4661: invokevirtual append : (C)Ljava/lang/StringBuilder;
    //   4664: pop
    //   4665: iload_2
    //   4666: ifeq -> 5708
    //   4669: goto -> 4676
    //   4672: invokestatic a : (Ljava/lang/Throwable;)Ljava/lang/Throwable;
    //   4675: athrow
    //   4676: aload_3
    //   4677: getstatic burp/Zz0f.ZW : Ljava/lang/String;
    //   4680: getstatic burp/Zrqe.ZX : Ljava/lang/Object;
    //   4683: checkcast java/math/BigInteger
    //   4686: invokevirtual intValue : ()I
    //   4689: bipush #32
    //   4691: irem
    //   4692: invokestatic abs : (I)I
    //   4695: invokevirtual charAt : (I)C
    //   4698: invokevirtual append : (C)Ljava/lang/StringBuilder;
    //   4701: pop
    //   4702: iload_2
    //   4703: ifeq -> 5708
    //   4706: goto -> 4713
    //   4709: invokestatic a : (Ljava/lang/Throwable;)Ljava/lang/Throwable;
    //   4712: athrow
    //   4713: aload_3
    //   4714: getstatic burp/Zg4z.Zm : Ljava/lang/String;
    //   4717: getstatic burp/Zzk_.Zx : Ljava/lang/Object;
    //   4720: checkcast java/math/BigInteger
    //   4723: invokevirtual intValue : ()I
    //   4726: bipush #32
    //   4728: irem
    //   4729: invokestatic abs : (I)I
    //   4732: invokevirtual charAt : (I)C
    //   4735: invokevirtual append : (C)Ljava/lang/StringBuilder;
    //   4738: pop
    //   4739: iload_2
    //   4740: ifeq -> 5708
    //   4743: goto -> 4750
    //   4746: invokestatic a : (Ljava/lang/Throwable;)Ljava/lang/Throwable;
    //   4749: athrow
    //   4750: aload_3
    //   4751: getstatic burp/Ztq4.Zb : Ljava/lang/String;
    //   4754: getstatic burp/Zg61.Zp : Ljava/lang/Object;
    //   4757: checkcast java/math/BigInteger
    //   4760: invokevirtual intValue : ()I
    //   4763: bipush #32
    //   4765: irem
    //   4766: invokestatic abs : (I)I
    //   4769: invokevirtual charAt : (I)C
    //   4772: invokevirtual append : (C)Ljava/lang/StringBuilder;
    //   4775: pop
    //   4776: iload_2
    //   4777: ifeq -> 5708
    //   4780: goto -> 4787
    //   4783: invokestatic a : (Ljava/lang/Throwable;)Ljava/lang/Throwable;
    //   4786: athrow
    //   4787: aload_3
    //   4788: getstatic burp/Zz0b.ZD : Ljava/lang/String;
    //   4791: getstatic burp/Zgrz.ZX : Ljava/lang/Object;
    //   4794: checkcast java/math/BigInteger
    //   4797: invokevirtual intValue : ()I
    //   4800: bipush #32
    //   4802: irem
    //   4803: invokestatic abs : (I)I
    //   4806: invokevirtual charAt : (I)C
    //   4809: invokevirtual append : (C)Ljava/lang/StringBuilder;
    //   4812: pop
    //   4813: iload_2
    //   4814: ifeq -> 5708
    //   4817: goto -> 4824
    //   4820: invokestatic a : (Ljava/lang/Throwable;)Ljava/lang/Throwable;
    //   4823: athrow
    //   4824: aload_3
    //   4825: getstatic burp/Zrqi.Zu : Ljava/lang/String;
    //   4828: getstatic burp/Zmpx.ZZ : Ljava/lang/Object;
    //   4831: checkcast java/math/BigInteger
    //   4834: invokevirtual intValue : ()I
    //   4837: bipush #32
    //   4839: irem
    //   4840: invokestatic abs : (I)I
    //   4843: invokevirtual charAt : (I)C
    //   4846: invokevirtual append : (C)Ljava/lang/StringBuilder;
    //   4849: pop
    //   4850: iload_2
    //   4851: ifeq -> 5708
    //   4854: goto -> 4861
    //   4857: invokestatic a : (Ljava/lang/Throwable;)Ljava/lang/Throwable;
    //   4860: athrow
    //   4861: aload_3
    //   4862: getstatic burp/Zlsg.Zs : Ljava/lang/String;
    //   4865: getstatic burp/Zs1k.Ze : Ljava/lang/Object;
    //   4868: checkcast java/math/BigInteger
    //   4871: invokevirtual intValue : ()I
    //   4874: bipush #32
    //   4876: irem
    //   4877: invokestatic abs : (I)I
    //   4880: invokevirtual charAt : (I)C
    //   4883: invokevirtual append : (C)Ljava/lang/StringBuilder;
    //   4886: pop
    //   4887: iload_2
    //   4888: ifeq -> 5708
    //   4891: goto -> 4898
    //   4894: invokestatic a : (Ljava/lang/Throwable;)Ljava/lang/Throwable;
    //   4897: athrow
    //   4898: aload_3
    //   4899: getstatic burp/Zk8f.ZV : Ljava/lang/String;
    //   4902: getstatic burp/Zeqx.Zh : Ljava/lang/Object;
    //   4905: checkcast java/math/BigInteger
    //   4908: invokevirtual intValue : ()I
    //   4911: bipush #32
    //   4913: irem
    //   4914: invokestatic abs : (I)I
    //   4917: invokevirtual charAt : (I)C
    //   4920: invokevirtual append : (C)Ljava/lang/StringBuilder;
    //   4923: pop
    //   4924: iload_2
    //   4925: ifeq -> 5708
    //   4928: goto -> 4935
    //   4931: invokestatic a : (Ljava/lang/Throwable;)Ljava/lang/Throwable;
    //   4934: athrow
    //   4935: aload_3
    //   4936: getstatic burp/Zrl5.ZG : Ljava/lang/String;
    //   4939: getstatic burp/Zzmc.Zg : Ljava/lang/Object;
    //   4942: checkcast java/math/BigInteger
    //   4945: invokevirtual intValue : ()I
    //   4948: bipush #32
    //   4950: irem
    //   4951: invokestatic abs : (I)I
    //   4954: invokevirtual charAt : (I)C
    //   4957: invokevirtual append : (C)Ljava/lang/StringBuilder;
    //   4960: pop
    //   4961: iload_2
    //   4962: ifeq -> 5708
    //   4965: goto -> 4972
    //   4968: invokestatic a : (Ljava/lang/Throwable;)Ljava/lang/Throwable;
    //   4971: athrow
    //   4972: aload_3
    //   4973: getstatic burp/Ze7e.Zc : Ljava/lang/String;
    //   4976: getstatic burp/Zma0.ZQ : Ljava/lang/Object;
    //   4979: checkcast java/math/BigInteger
    //   4982: invokevirtual intValue : ()I
    //   4985: bipush #32
    //   4987: irem
    //   4988: invokestatic abs : (I)I
    //   4991: invokevirtual charAt : (I)C
    //   4994: invokevirtual append : (C)Ljava/lang/StringBuilder;
    //   4997: pop
    //   4998: iload_2
    //   4999: ifeq -> 5708
    //   5002: goto -> 5009
    //   5005: invokestatic a : (Ljava/lang/Throwable;)Ljava/lang/Throwable;
    //   5008: athrow
    //   5009: aload_3
    //   5010: getstatic burp/Zek4.Zo : Ljava/lang/String;
    //   5013: getstatic burp/Zm83.Zl : Ljava/lang/Object;
    //   5016: checkcast java/math/BigInteger
    //   5019: invokevirtual intValue : ()I
    //   5022: bipush #32
    //   5024: irem
    //   5025: invokestatic abs : (I)I
    //   5028: invokevirtual charAt : (I)C
    //   5031: invokevirtual append : (C)Ljava/lang/StringBuilder;
    //   5034: pop
    //   5035: iload_2
    //   5036: ifeq -> 5708
    //   5039: goto -> 5046
    //   5042: invokestatic a : (Ljava/lang/Throwable;)Ljava/lang/Throwable;
    //   5045: athrow
    //   5046: aload_3
    //   5047: getstatic burp/Zssc.ZR : Ljava/lang/String;
    //   5050: getstatic burp/Zvh.Zb : Ljava/lang/Object;
    //   5053: checkcast java/math/BigInteger
    //   5056: invokevirtual intValue : ()I
    //   5059: bipush #32
    //   5061: irem
    //   5062: invokestatic abs : (I)I
    //   5065: invokevirtual charAt : (I)C
    //   5068: invokevirtual append : (C)Ljava/lang/StringBuilder;
    //   5071: pop
    //   5072: iload_2
    //   5073: ifeq -> 5708
    //   5076: goto -> 5083
    //   5079: invokestatic a : (Ljava/lang/Throwable;)Ljava/lang/Throwable;
    //   5082: athrow
    //   5083: aload_3
    //   5084: getstatic burp/Zz0y.ZM : Ljava/lang/String;
    //   5087: getstatic burp/Zllk.Zi : Ljava/lang/Object;
    //   5090: checkcast java/math/BigInteger
    //   5093: invokevirtual intValue : ()I
    //   5096: bipush #32
    //   5098: irem
    //   5099: invokestatic abs : (I)I
    //   5102: invokevirtual charAt : (I)C
    //   5105: invokevirtual append : (C)Ljava/lang/StringBuilder;
    //   5108: pop
    //   5109: iload_2
    //   5110: ifeq -> 5708
    //   5113: goto -> 5120
    //   5116: invokestatic a : (Ljava/lang/Throwable;)Ljava/lang/Throwable;
    //   5119: athrow
    //   5120: aload_3
    //   5121: getstatic burp/Zeub.ZT : Ljava/lang/String;
    //   5124: getstatic burp/Zt0m.Zt : Ljava/lang/Object;
    //   5127: checkcast java/math/BigInteger
    //   5130: invokevirtual intValue : ()I
    //   5133: bipush #32
    //   5135: irem
    //   5136: invokestatic abs : (I)I
    //   5139: invokevirtual charAt : (I)C
    //   5142: invokevirtual append : (C)Ljava/lang/StringBuilder;
    //   5145: pop
    //   5146: iload_2
    //   5147: ifeq -> 5708
    //   5150: goto -> 5157
    //   5153: invokestatic a : (Ljava/lang/Throwable;)Ljava/lang/Throwable;
    //   5156: athrow
    //   5157: aload_3
    //   5158: getstatic burp/Zeqx.Zu : Ljava/lang/String;
    //   5161: getstatic burp/Zkf6.ZS : Ljava/lang/Object;
    //   5164: checkcast java/math/BigInteger
    //   5167: invokevirtual intValue : ()I
    //   5170: bipush #32
    //   5172: irem
    //   5173: invokestatic abs : (I)I
    //   5176: invokevirtual charAt : (I)C
    //   5179: invokevirtual append : (C)Ljava/lang/StringBuilder;
    //   5182: pop
    //   5183: iload_2
    //   5184: ifeq -> 5708
    //   5187: goto -> 5194
    //   5190: invokestatic a : (Ljava/lang/Throwable;)Ljava/lang/Throwable;
    //   5193: athrow
    //   5194: aload_3
    //   5195: getstatic burp/Zrqi.Zu : Ljava/lang/String;
    //   5198: getstatic burp/Zr2q.ZS : Ljava/lang/Object;
    //   5201: checkcast java/math/BigInteger
    //   5204: invokevirtual intValue : ()I
    //   5207: bipush #32
    //   5209: irem
    //   5210: invokestatic abs : (I)I
    //   5213: invokevirtual charAt : (I)C
    //   5216: invokevirtual append : (C)Ljava/lang/StringBuilder;
    //   5219: pop
    //   5220: iload_2
    //   5221: ifeq -> 5708
    //   5224: goto -> 5231
    //   5227: invokestatic a : (Ljava/lang/Throwable;)Ljava/lang/Throwable;
    //   5230: athrow
    //   5231: aload_3
    //   5232: getstatic burp/Zgk9.Zf : Ljava/lang/String;
    //   5235: getstatic burp/Zz3b.Zu : Ljava/lang/Object;
    //   5238: checkcast java/math/BigInteger
    //   5241: invokevirtual intValue : ()I
    //   5244: bipush #32
    //   5246: irem
    //   5247: invokestatic abs : (I)I
    //   5250: invokevirtual charAt : (I)C
    //   5253: invokevirtual append : (C)Ljava/lang/StringBuilder;
    //   5256: pop
    //   5257: iload_2
    //   5258: ifeq -> 5708
    //   5261: goto -> 5268
    //   5264: invokestatic a : (Ljava/lang/Throwable;)Ljava/lang/Throwable;
    //   5267: athrow
    //   5268: aload_3
    //   5269: getstatic burp/Zmf2.ZK : Ljava/lang/String;
    //   5272: getstatic burp/Zlxr.Zz : Ljava/lang/Object;
    //   5275: checkcast java/math/BigInteger
    //   5278: invokevirtual intValue : ()I
    //   5281: bipush #32
    //   5283: irem
    //   5284: invokestatic abs : (I)I
    //   5287: invokevirtual charAt : (I)C
    //   5290: invokevirtual append : (C)Ljava/lang/StringBuilder;
    //   5293: pop
    //   5294: iload_2
    //   5295: ifeq -> 5708
    //   5298: goto -> 5305
    //   5301: invokestatic a : (Ljava/lang/Throwable;)Ljava/lang/Throwable;
    //   5304: athrow
    //   5305: aload_3
    //   5306: getstatic burp/Ze8j.ZU : Ljava/lang/String;
    //   5309: getstatic burp/Ze25.ZW : Ljava/lang/Object;
    //   5312: checkcast java/math/BigInteger
    //   5315: invokevirtual intValue : ()I
    //   5318: bipush #32
    //   5320: irem
    //   5321: invokestatic abs : (I)I
    //   5324: invokevirtual charAt : (I)C
    //   5327: invokevirtual append : (C)Ljava/lang/StringBuilder;
    //   5330: pop
    //   5331: iload_2
    //   5332: ifeq -> 5708
    //   5335: goto -> 5342
    //   5338: invokestatic a : (Ljava/lang/Throwable;)Ljava/lang/Throwable;
    //   5341: athrow
    //   5342: aload_3
    //   5343: getstatic burp/Ztzj.ZB : Ljava/lang/String;
    //   5346: getstatic burp/Zegv.ZL : Ljava/lang/Object;
    //   5349: checkcast java/math/BigInteger
    //   5352: invokevirtual intValue : ()I
    //   5355: bipush #32
    //   5357: irem
    //   5358: invokestatic abs : (I)I
    //   5361: invokevirtual charAt : (I)C
    //   5364: invokevirtual append : (C)Ljava/lang/StringBuilder;
    //   5367: pop
    //   5368: iload_2
    //   5369: ifeq -> 5708
    //   5372: goto -> 5379
    //   5375: invokestatic a : (Ljava/lang/Throwable;)Ljava/lang/Throwable;
    //   5378: athrow
    //   5379: aload_3
    //   5380: getstatic burp/Zkhf.Zb : Ljava/lang/String;
    //   5383: getstatic burp/Zos.ZB : Ljava/lang/Object;
    //   5386: checkcast java/math/BigInteger
    //   5389: invokevirtual intValue : ()I
    //   5392: bipush #32
    //   5394: irem
    //   5395: invokestatic abs : (I)I
    //   5398: invokevirtual charAt : (I)C
    //   5401: invokevirtual append : (C)Ljava/lang/StringBuilder;
    //   5404: pop
    //   5405: iload_2
    //   5406: ifeq -> 5708
    //   5409: goto -> 5416
    //   5412: invokestatic a : (Ljava/lang/Throwable;)Ljava/lang/Throwable;
    //   5415: athrow
    //   5416: aload_3
    //   5417: getstatic burp/Zlsg.Zs : Ljava/lang/String;
    //   5420: getstatic burp/Zesw.ZB : Ljava/lang/Object;
    //   5423: checkcast java/math/BigInteger
    //   5426: invokevirtual intValue : ()I
    //   5429: bipush #32
    //   5431: irem
    //   5432: invokestatic abs : (I)I
    //   5435: invokevirtual charAt : (I)C
    //   5438: invokevirtual append : (C)Ljava/lang/StringBuilder;
    //   5441: pop
    //   5442: iload_2
    //   5443: ifeq -> 5708
    //   5446: goto -> 5453
    //   5449: invokestatic a : (Ljava/lang/Throwable;)Ljava/lang/Throwable;
    //   5452: athrow
    //   5453: aload_3
    //   5454: getstatic burp/Zkhf.Zb : Ljava/lang/String;
    //   5457: getstatic burp/Zl_f.ZI : Ljava/lang/Object;
    //   5460: checkcast java/math/BigInteger
    //   5463: invokevirtual intValue : ()I
    //   5466: bipush #32
    //   5468: irem
    //   5469: invokestatic abs : (I)I
    //   5472: invokevirtual charAt : (I)C
    //   5475: invokevirtual append : (C)Ljava/lang/StringBuilder;
    //   5478: pop
    //   5479: iload_2
    //   5480: ifeq -> 5708
    //   5483: goto -> 5490
    //   5486: invokestatic a : (Ljava/lang/Throwable;)Ljava/lang/Throwable;
    //   5489: athrow
    //   5490: aload_3
    //   5491: getstatic burp/Zrm6.ZV : Ljava/lang/String;
    //   5494: getstatic burp/Zk8i.ZN : Ljava/lang/Object;
    //   5497: checkcast java/math/BigInteger
    //   5500: invokevirtual intValue : ()I
    //   5503: bipush #32
    //   5505: irem
    //   5506: invokestatic abs : (I)I
    //   5509: invokevirtual charAt : (I)C
    //   5512: invokevirtual append : (C)Ljava/lang/StringBuilder;
    //   5515: pop
    //   5516: iload_2
    //   5517: ifeq -> 5708
    //   5520: goto -> 5527
    //   5523: invokestatic a : (Ljava/lang/Throwable;)Ljava/lang/Throwable;
    //   5526: athrow
    //   5527: aload_3
    //   5528: getstatic burp/Zd9.Ze : Ljava/lang/String;
    //   5531: getstatic burp/Zrb6.ZQ : Ljava/lang/Object;
    //   5534: checkcast java/math/BigInteger
    //   5537: invokevirtual intValue : ()I
    //   5540: bipush #32
    //   5542: irem
    //   5543: invokestatic abs : (I)I
    //   5546: invokevirtual charAt : (I)C
    //   5549: invokevirtual append : (C)Ljava/lang/StringBuilder;
    //   5552: pop
    //   5553: iload_2
    //   5554: ifeq -> 5708
    //   5557: goto -> 5564
    //   5560: invokestatic a : (Ljava/lang/Throwable;)Ljava/lang/Throwable;
    //   5563: athrow
    //   5564: aload_3
    //   5565: getstatic burp/Zd9.Ze : Ljava/lang/String;
    //   5568: getstatic burp/Zmli.Zh : Ljava/lang/Object;
    //   5571: checkcast java/math/BigInteger
    //   5574: invokevirtual intValue : ()I
    //   5577: bipush #32
    //   5579: irem
    //   5580: invokestatic abs : (I)I
    //   5583: invokevirtual charAt : (I)C
    //   5586: invokevirtual append : (C)Ljava/lang/StringBuilder;
    //   5589: pop
    //   5590: iload_2
    //   5591: ifeq -> 5708
    //   5594: goto -> 5601
    //   5597: invokestatic a : (Ljava/lang/Throwable;)Ljava/lang/Throwable;
    //   5600: athrow
    //   5601: aload_3
    //   5602: getstatic burp/Zmz.Zp : Ljava/lang/String;
    //   5605: getstatic burp/Zrkw.ZV : Ljava/lang/Object;
    //   5608: checkcast java/math/BigInteger
    //   5611: invokevirtual intValue : ()I
    //   5614: bipush #32
    //   5616: irem
    //   5617: invokestatic abs : (I)I
    //   5620: invokevirtual charAt : (I)C
    //   5623: invokevirtual append : (C)Ljava/lang/StringBuilder;
    //   5626: pop
    //   5627: iload_2
    //   5628: ifeq -> 5708
    //   5631: goto -> 5638
    //   5634: invokestatic a : (Ljava/lang/Throwable;)Ljava/lang/Throwable;
    //   5637: athrow
    //   5638: aload_3
    //   5639: getstatic burp/Zt85.ZR : Ljava/lang/String;
    //   5642: getstatic burp/Zmll.ZU : Ljava/lang/Object;
    //   5645: checkcast java/math/BigInteger
    //   5648: invokevirtual intValue : ()I
    //   5651: bipush #32
    //   5653: irem
    //   5654: invokestatic abs : (I)I
    //   5657: invokevirtual charAt : (I)C
    //   5660: invokevirtual append : (C)Ljava/lang/StringBuilder;
    //   5663: pop
    //   5664: iload_2
    //   5665: ifeq -> 5708
    //   5668: goto -> 5675
    //   5671: invokestatic a : (Ljava/lang/Throwable;)Ljava/lang/Throwable;
    //   5674: athrow
    //   5675: aload_3
    //   5676: getstatic burp/Zxci.Zw : Ljava/lang/String;
    //   5679: getstatic burp/Zmt_.Zl : Ljava/lang/Object;
    //   5682: checkcast java/math/BigInteger
    //   5685: invokevirtual intValue : ()I
    //   5688: bipush #32
    //   5690: irem
    //   5691: invokestatic abs : (I)I
    //   5694: invokevirtual charAt : (I)C
    //   5697: invokevirtual append : (C)Ljava/lang/StringBuilder;
    //   5700: pop
    //   5701: goto -> 5708
    //   5704: invokestatic a : (Ljava/lang/Throwable;)Ljava/lang/Throwable;
    //   5707: athrow
    //   5708: iinc #4, 1
    //   5711: iload_2
    //   5712: ifeq -> 4378
    //   5715: aload_3
    //   5716: invokevirtual toString : ()Ljava/lang/String;
    //   5719: putstatic burp/Zs_m.Zt : Ljava/lang/String;
    //   5722: getstatic burp/Zek4.ZR : Ljava/lang/Object;
    //   5725: checkcast java/math/BigInteger
    //   5728: invokevirtual toByteArray : ()[B
    //   5731: astore #4
    //   5733: bipush #32
    //   5735: newarray int
    //   5737: dup
    //   5738: iconst_0
    //   5739: ldc 876216579
    //   5741: iastore
    //   5742: dup
    //   5743: iconst_1
    //   5744: ldc 455999525
    //   5746: iastore
    //   5747: dup
    //   5748: iconst_2
    //   5749: ldc 1043334948
    //   5751: iastore
    //   5752: dup
    //   5753: iconst_3
    //   5754: ldc 439222784
    //   5756: iastore
    //   5757: dup
    //   5758: iconst_4
    //   5759: ldc 372376604
    //   5761: iastore
    //   5762: dup
    //   5763: iconst_5
    //   5764: ldc 707731490
    //   5766: iastore
    //   5767: dup
    //   5768: bipush #6
    //   5770: ldc 389426184
    //   5772: iastore
    //   5773: dup
    //   5774: bipush #7
    //   5776: ldc 973875457
    //   5778: iastore
    //   5779: dup
    //   5780: bipush #8
    //   5782: ldc 389160971
    //   5784: iastore
    //   5785: dup
    //   5786: bipush #9
    //   5788: ldc 907870729
    //   5790: iastore
    //   5791: dup
    //   5792: bipush #10
    //   5794: ldc 121057538
    //   5796: iastore
    //   5797: dup
    //   5798: bipush #11
    //   5800: ldc 840500228
    //   5802: iastore
    //   5803: dup
    //   5804: bipush #12
    //   5806: ldc 254150144
    //   5808: iastore
    //   5809: dup
    //   5810: bipush #13
    //   5812: ldc 924386310
    //   5814: iastore
    //   5815: dup
    //   5816: bipush #14
    //   5818: ldc 187632156
    //   5820: iastore
    //   5821: dup
    //   5822: bipush #15
    //   5824: ldc 874189824
    //   5826: iastore
    //   5827: dup
    //   5828: bipush #16
    //   5830: ldc 655302664
    //   5832: iastore
    //   5833: dup
    //   5834: bipush #17
    //   5836: ldc 890966315
    //   5838: iastore
    //   5839: dup
    //   5840: bipush #18
    //   5842: ldc 722417666
    //   5844: iastore
    //   5845: dup
    //   5846: bipush #19
    //   5848: ldc 1026621720
    //   5850: iastore
    //   5851: dup
    //   5852: bipush #20
    //   5854: ldc 957157408
    //   5856: iastore
    //   5857: dup
    //   5858: bipush #21
    //   5860: ldc 892536332
    //   5862: iastore
    //   5863: dup
    //   5864: bipush #22
    //   5866: ldc 689771012
    //   5868: iastore
    //   5869: dup
    //   5870: bipush #23
    //   5872: ldc 221709344
    //   5874: iastore
    //   5875: dup
    //   5876: bipush #24
    //   5878: ldc 940377620
    //   5880: iastore
    //   5881: dup
    //   5882: bipush #25
    //   5884: ldc 255209728
    //   5886: iastore
    //   5887: dup
    //   5888: bipush #26
    //   5890: ldc 1010368540
    //   5892: iastore
    //   5893: dup
    //   5894: bipush #27
    //   5896: ldc 220604441
    //   5898: iastore
    //   5899: dup
    //   5900: bipush #28
    //   5902: ldc 1008414755
    //   5904: iastore
    //   5905: dup
    //   5906: bipush #29
    //   5908: ldc 187049985
    //   5910: iastore
    //   5911: dup
    //   5912: bipush #30
    //   5914: ldc 943331329
    //   5916: iastore
    //   5917: dup
    //   5918: bipush #31
    //   5920: ldc 170788368
    //   5922: iastore
    //   5923: astore #6
    //   5925: bipush #64
    //   5927: newarray int
    //   5929: dup
    //   5930: iconst_0
    //   5931: ldc 16843776
    //   5933: iastore
    //   5934: dup
    //   5935: iconst_1
    //   5936: iconst_0
    //   5937: iastore
    //   5938: dup
    //   5939: iconst_2
    //   5940: ldc 65536
    //   5942: iastore
    //   5943: dup
    //   5944: iconst_3
    //   5945: ldc 16843780
    //   5947: iastore
    //   5948: dup
    //   5949: iconst_4
    //   5950: ldc 16842756
    //   5952: iastore
    //   5953: dup
    //   5954: iconst_5
    //   5955: ldc 66564
    //   5957: iastore
    //   5958: dup
    //   5959: bipush #6
    //   5961: iconst_4
    //   5962: iastore
    //   5963: dup
    //   5964: bipush #7
    //   5966: ldc 65536
    //   5968: iastore
    //   5969: dup
    //   5970: bipush #8
    //   5972: sipush #1024
    //   5975: iastore
    //   5976: dup
    //   5977: bipush #9
    //   5979: ldc 16843776
    //   5981: iastore
    //   5982: dup
    //   5983: bipush #10
    //   5985: ldc 16843780
    //   5987: iastore
    //   5988: dup
    //   5989: bipush #11
    //   5991: sipush #1024
    //   5994: iastore
    //   5995: dup
    //   5996: bipush #12
    //   5998: ldc 16778244
    //   6000: iastore
    //   6001: dup
    //   6002: bipush #13
    //   6004: ldc 16842756
    //   6006: iastore
    //   6007: dup
    //   6008: bipush #14
    //   6010: ldc 16777216
    //   6012: iastore
    //   6013: dup
    //   6014: bipush #15
    //   6016: iconst_4
    //   6017: iastore
    //   6018: dup
    //   6019: bipush #16
    //   6021: sipush #1028
    //   6024: iastore
    //   6025: dup
    //   6026: bipush #17
    //   6028: ldc 16778240
    //   6030: iastore
    //   6031: dup
    //   6032: bipush #18
    //   6034: ldc 16778240
    //   6036: iastore
    //   6037: dup
    //   6038: bipush #19
    //   6040: ldc 66560
    //   6042: iastore
    //   6043: dup
    //   6044: bipush #20
    //   6046: ldc 66560
    //   6048: iastore
    //   6049: dup
    //   6050: bipush #21
    //   6052: ldc 16842752
    //   6054: iastore
    //   6055: dup
    //   6056: bipush #22
    //   6058: ldc 16842752
    //   6060: iastore
    //   6061: dup
    //   6062: bipush #23
    //   6064: ldc 16778244
    //   6066: iastore
    //   6067: dup
    //   6068: bipush #24
    //   6070: ldc 65540
    //   6072: iastore
    //   6073: dup
    //   6074: bipush #25
    //   6076: ldc 16777220
    //   6078: iastore
    //   6079: dup
    //   6080: bipush #26
    //   6082: ldc 16777220
    //   6084: iastore
    //   6085: dup
    //   6086: bipush #27
    //   6088: ldc 65540
    //   6090: iastore
    //   6091: dup
    //   6092: bipush #28
    //   6094: iconst_0
    //   6095: iastore
    //   6096: dup
    //   6097: bipush #29
    //   6099: sipush #1028
    //   6102: iastore
    //   6103: dup
    //   6104: bipush #30
    //   6106: ldc 66564
    //   6108: iastore
    //   6109: dup
    //   6110: bipush #31
    //   6112: ldc 16777216
    //   6114: iastore
    //   6115: dup
    //   6116: bipush #32
    //   6118: ldc 65536
    //   6120: iastore
    //   6121: dup
    //   6122: bipush #33
    //   6124: ldc 16843780
    //   6126: iastore
    //   6127: dup
    //   6128: bipush #34
    //   6130: iconst_4
    //   6131: iastore
    //   6132: dup
    //   6133: bipush #35
    //   6135: ldc 16842752
    //   6137: iastore
    //   6138: dup
    //   6139: bipush #36
    //   6141: ldc 16843776
    //   6143: iastore
    //   6144: dup
    //   6145: bipush #37
    //   6147: ldc 16777216
    //   6149: iastore
    //   6150: dup
    //   6151: bipush #38
    //   6153: ldc 16777216
    //   6155: iastore
    //   6156: dup
    //   6157: bipush #39
    //   6159: sipush #1024
    //   6162: iastore
    //   6163: dup
    //   6164: bipush #40
    //   6166: ldc 16842756
    //   6168: iastore
    //   6169: dup
    //   6170: bipush #41
    //   6172: ldc 65536
    //   6174: iastore
    //   6175: dup
    //   6176: bipush #42
    //   6178: ldc 66560
    //   6180: iastore
    //   6181: dup
    //   6182: bipush #43
    //   6184: ldc 16777220
    //   6186: iastore
    //   6187: dup
    //   6188: bipush #44
    //   6190: sipush #1024
    //   6193: iastore
    //   6194: dup
    //   6195: bipush #45
    //   6197: iconst_4
    //   6198: iastore
    //   6199: dup
    //   6200: bipush #46
    //   6202: ldc 16778244
    //   6204: iastore
    //   6205: dup
    //   6206: bipush #47
    //   6208: ldc 66564
    //   6210: iastore
    //   6211: dup
    //   6212: bipush #48
    //   6214: ldc 16843780
    //   6216: iastore
    //   6217: dup
    //   6218: bipush #49
    //   6220: ldc 65540
    //   6222: iastore
    //   6223: dup
    //   6224: bipush #50
    //   6226: ldc 16842752
    //   6228: iastore
    //   6229: dup
    //   6230: bipush #51
    //   6232: ldc 16778244
    //   6234: iastore
    //   6235: dup
    //   6236: bipush #52
    //   6238: ldc 16777220
    //   6240: iastore
    //   6241: dup
    //   6242: bipush #53
    //   6244: sipush #1028
    //   6247: iastore
    //   6248: dup
    //   6249: bipush #54
    //   6251: ldc 66564
    //   6253: iastore
    //   6254: dup
    //   6255: bipush #55
    //   6257: ldc 16843776
    //   6259: iastore
    //   6260: dup
    //   6261: bipush #56
    //   6263: sipush #1028
    //   6266: iastore
    //   6267: dup
    //   6268: bipush #57
    //   6270: ldc 16778240
    //   6272: iastore
    //   6273: dup
    //   6274: bipush #58
    //   6276: ldc 16778240
    //   6278: iastore
    //   6279: dup
    //   6280: bipush #59
    //   6282: iconst_0
    //   6283: iastore
    //   6284: dup
    //   6285: bipush #60
    //   6287: ldc 65540
    //   6289: iastore
    //   6290: dup
    //   6291: bipush #61
    //   6293: ldc 66560
    //   6295: iastore
    //   6296: dup
    //   6297: bipush #62
    //   6299: iconst_0
    //   6300: iastore
    //   6301: dup
    //   6302: bipush #63
    //   6304: ldc 16842756
    //   6306: iastore
    //   6307: astore #7
    //   6309: bipush #64
    //   6311: newarray int
    //   6313: dup
    //   6314: iconst_0
    //   6315: ldc -2146402272
    //   6317: iastore
    //   6318: dup
    //   6319: iconst_1
    //   6320: ldc -2147450880
    //   6322: iastore
    //   6323: dup
    //   6324: iconst_2
    //   6325: ldc 32768
    //   6327: iastore
    //   6328: dup
    //   6329: iconst_3
    //   6330: ldc 1081376
    //   6332: iastore
    //   6333: dup
    //   6334: iconst_4
    //   6335: ldc 1048576
    //   6337: iastore
    //   6338: dup
    //   6339: iconst_5
    //   6340: bipush #32
    //   6342: iastore
    //   6343: dup
    //   6344: bipush #6
    //   6346: ldc -2146435040
    //   6348: iastore
    //   6349: dup
    //   6350: bipush #7
    //   6352: ldc -2147450848
    //   6354: iastore
    //   6355: dup
    //   6356: bipush #8
    //   6358: ldc -2147483616
    //   6360: iastore
    //   6361: dup
    //   6362: bipush #9
    //   6364: ldc -2146402272
    //   6366: iastore
    //   6367: dup
    //   6368: bipush #10
    //   6370: ldc -2146402304
    //   6372: iastore
    //   6373: dup
    //   6374: bipush #11
    //   6376: ldc -2147483648
    //   6378: iastore
    //   6379: dup
    //   6380: bipush #12
    //   6382: ldc -2147450880
    //   6384: iastore
    //   6385: dup
    //   6386: bipush #13
    //   6388: ldc 1048576
    //   6390: iastore
    //   6391: dup
    //   6392: bipush #14
    //   6394: bipush #32
    //   6396: iastore
    //   6397: dup
    //   6398: bipush #15
    //   6400: ldc -2146435040
    //   6402: iastore
    //   6403: dup
    //   6404: bipush #16
    //   6406: ldc 1081344
    //   6408: iastore
    //   6409: dup
    //   6410: bipush #17
    //   6412: ldc 1048608
    //   6414: iastore
    //   6415: dup
    //   6416: bipush #18
    //   6418: ldc -2147450848
    //   6420: iastore
    //   6421: dup
    //   6422: bipush #19
    //   6424: iconst_0
    //   6425: iastore
    //   6426: dup
    //   6427: bipush #20
    //   6429: ldc -2147483648
    //   6431: iastore
    //   6432: dup
    //   6433: bipush #21
    //   6435: ldc 32768
    //   6437: iastore
    //   6438: dup
    //   6439: bipush #22
    //   6441: ldc 1081376
    //   6443: iastore
    //   6444: dup
    //   6445: bipush #23
    //   6447: ldc -2146435072
    //   6449: iastore
    //   6450: dup
    //   6451: bipush #24
    //   6453: ldc 1048608
    //   6455: iastore
    //   6456: dup
    //   6457: bipush #25
    //   6459: ldc -2147483616
    //   6461: iastore
    //   6462: dup
    //   6463: bipush #26
    //   6465: iconst_0
    //   6466: iastore
    //   6467: dup
    //   6468: bipush #27
    //   6470: ldc 1081344
    //   6472: iastore
    //   6473: dup
    //   6474: bipush #28
    //   6476: ldc 32800
    //   6478: iastore
    //   6479: dup
    //   6480: bipush #29
    //   6482: ldc -2146402304
    //   6484: iastore
    //   6485: dup
    //   6486: bipush #30
    //   6488: ldc -2146435072
    //   6490: iastore
    //   6491: dup
    //   6492: bipush #31
    //   6494: ldc 32800
    //   6496: iastore
    //   6497: dup
    //   6498: bipush #32
    //   6500: iconst_0
    //   6501: iastore
    //   6502: dup
    //   6503: bipush #33
    //   6505: ldc 1081376
    //   6507: iastore
    //   6508: dup
    //   6509: bipush #34
    //   6511: ldc -2146435040
    //   6513: iastore
    //   6514: dup
    //   6515: bipush #35
    //   6517: ldc 1048576
    //   6519: iastore
    //   6520: dup
    //   6521: bipush #36
    //   6523: ldc -2147450848
    //   6525: iastore
    //   6526: dup
    //   6527: bipush #37
    //   6529: ldc -2146435072
    //   6531: iastore
    //   6532: dup
    //   6533: bipush #38
    //   6535: ldc -2146402304
    //   6537: iastore
    //   6538: dup
    //   6539: bipush #39
    //   6541: ldc 32768
    //   6543: iastore
    //   6544: dup
    //   6545: bipush #40
    //   6547: ldc -2146435072
    //   6549: iastore
    //   6550: dup
    //   6551: bipush #41
    //   6553: ldc -2147450880
    //   6555: iastore
    //   6556: dup
    //   6557: bipush #42
    //   6559: bipush #32
    //   6561: iastore
    //   6562: dup
    //   6563: bipush #43
    //   6565: ldc -2146402272
    //   6567: iastore
    //   6568: dup
    //   6569: bipush #44
    //   6571: ldc 1081376
    //   6573: iastore
    //   6574: dup
    //   6575: bipush #45
    //   6577: bipush #32
    //   6579: iastore
    //   6580: dup
    //   6581: bipush #46
    //   6583: ldc 32768
    //   6585: iastore
    //   6586: dup
    //   6587: bipush #47
    //   6589: ldc -2147483648
    //   6591: iastore
    //   6592: dup
    //   6593: bipush #48
    //   6595: ldc 32800
    //   6597: iastore
    //   6598: dup
    //   6599: bipush #49
    //   6601: ldc -2146402304
    //   6603: iastore
    //   6604: dup
    //   6605: bipush #50
    //   6607: ldc 1048576
    //   6609: iastore
    //   6610: dup
    //   6611: bipush #51
    //   6613: ldc -2147483616
    //   6615: iastore
    //   6616: dup
    //   6617: bipush #52
    //   6619: ldc 1048608
    //   6621: iastore
    //   6622: dup
    //   6623: bipush #53
    //   6625: ldc -2147450848
    //   6627: iastore
    //   6628: dup
    //   6629: bipush #54
    //   6631: ldc -2147483616
    //   6633: iastore
    //   6634: dup
    //   6635: bipush #55
    //   6637: ldc 1048608
    //   6639: iastore
    //   6640: dup
    //   6641: bipush #56
    //   6643: ldc 1081344
    //   6645: iastore
    //   6646: dup
    //   6647: bipush #57
    //   6649: iconst_0
    //   6650: iastore
    //   6651: dup
    //   6652: bipush #58
    //   6654: ldc -2147450880
    //   6656: iastore
    //   6657: dup
    //   6658: bipush #59
    //   6660: ldc 32800
    //   6662: iastore
    //   6663: dup
    //   6664: bipush #60
    //   6666: ldc -2147483648
    //   6668: iastore
    //   6669: dup
    //   6670: bipush #61
    //   6672: ldc -2146435040
    //   6674: iastore
    //   6675: dup
    //   6676: bipush #62
    //   6678: ldc -2146402272
    //   6680: iastore
    //   6681: dup
    //   6682: bipush #63
    //   6684: ldc 1081344
    //   6686: iastore
    //   6687: astore #8
    //   6689: bipush #64
    //   6691: newarray int
    //   6693: dup
    //   6694: iconst_0
    //   6695: sipush #520
    //   6698: iastore
    //   6699: dup
    //   6700: iconst_1
    //   6701: ldc 134349312
    //   6703: iastore
    //   6704: dup
    //   6705: iconst_2
    //   6706: iconst_0
    //   6707: iastore
    //   6708: dup
    //   6709: iconst_3
    //   6710: ldc 134348808
    //   6712: iastore
    //   6713: dup
    //   6714: iconst_4
    //   6715: ldc 134218240
    //   6717: iastore
    //   6718: dup
    //   6719: iconst_5
    //   6720: iconst_0
    //   6721: iastore
    //   6722: dup
    //   6723: bipush #6
    //   6725: ldc 131592
    //   6727: iastore
    //   6728: dup
    //   6729: bipush #7
    //   6731: ldc 134218240
    //   6733: iastore
    //   6734: dup
    //   6735: bipush #8
    //   6737: ldc 131080
    //   6739: iastore
    //   6740: dup
    //   6741: bipush #9
    //   6743: ldc 134217736
    //   6745: iastore
    //   6746: dup
    //   6747: bipush #10
    //   6749: ldc 134217736
    //   6751: iastore
    //   6752: dup
    //   6753: bipush #11
    //   6755: ldc 131072
    //   6757: iastore
    //   6758: dup
    //   6759: bipush #12
    //   6761: ldc 134349320
    //   6763: iastore
    //   6764: dup
    //   6765: bipush #13
    //   6767: ldc 131080
    //   6769: iastore
    //   6770: dup
    //   6771: bipush #14
    //   6773: ldc 134348800
    //   6775: iastore
    //   6776: dup
    //   6777: bipush #15
    //   6779: sipush #520
    //   6782: iastore
    //   6783: dup
    //   6784: bipush #16
    //   6786: ldc 134217728
    //   6788: iastore
    //   6789: dup
    //   6790: bipush #17
    //   6792: bipush #8
    //   6794: iastore
    //   6795: dup
    //   6796: bipush #18
    //   6798: ldc 134349312
    //   6800: iastore
    //   6801: dup
    //   6802: bipush #19
    //   6804: sipush #512
    //   6807: iastore
    //   6808: dup
    //   6809: bipush #20
    //   6811: ldc 131584
    //   6813: iastore
    //   6814: dup
    //   6815: bipush #21
    //   6817: ldc 134348800
    //   6819: iastore
    //   6820: dup
    //   6821: bipush #22
    //   6823: ldc 134348808
    //   6825: iastore
    //   6826: dup
    //   6827: bipush #23
    //   6829: ldc 131592
    //   6831: iastore
    //   6832: dup
    //   6833: bipush #24
    //   6835: ldc 134218248
    //   6837: iastore
    //   6838: dup
    //   6839: bipush #25
    //   6841: ldc 131584
    //   6843: iastore
    //   6844: dup
    //   6845: bipush #26
    //   6847: ldc 131072
    //   6849: iastore
    //   6850: dup
    //   6851: bipush #27
    //   6853: ldc 134218248
    //   6855: iastore
    //   6856: dup
    //   6857: bipush #28
    //   6859: bipush #8
    //   6861: iastore
    //   6862: dup
    //   6863: bipush #29
    //   6865: ldc 134349320
    //   6867: iastore
    //   6868: dup
    //   6869: bipush #30
    //   6871: sipush #512
    //   6874: iastore
    //   6875: dup
    //   6876: bipush #31
    //   6878: ldc 134217728
    //   6880: iastore
    //   6881: dup
    //   6882: bipush #32
    //   6884: ldc 134349312
    //   6886: iastore
    //   6887: dup
    //   6888: bipush #33
    //   6890: ldc 134217728
    //   6892: iastore
    //   6893: dup
    //   6894: bipush #34
    //   6896: ldc 131080
    //   6898: iastore
    //   6899: dup
    //   6900: bipush #35
    //   6902: sipush #520
    //   6905: iastore
    //   6906: dup
    //   6907: bipush #36
    //   6909: ldc 131072
    //   6911: iastore
    //   6912: dup
    //   6913: bipush #37
    //   6915: ldc 134349312
    //   6917: iastore
    //   6918: dup
    //   6919: bipush #38
    //   6921: ldc 134218240
    //   6923: iastore
    //   6924: dup
    //   6925: bipush #39
    //   6927: iconst_0
    //   6928: iastore
    //   6929: dup
    //   6930: bipush #40
    //   6932: sipush #512
    //   6935: iastore
    //   6936: dup
    //   6937: bipush #41
    //   6939: ldc 131080
    //   6941: iastore
    //   6942: dup
    //   6943: bipush #42
    //   6945: ldc 134349320
    //   6947: iastore
    //   6948: dup
    //   6949: bipush #43
    //   6951: ldc 134218240
    //   6953: iastore
    //   6954: dup
    //   6955: bipush #44
    //   6957: ldc 134217736
    //   6959: iastore
    //   6960: dup
    //   6961: bipush #45
    //   6963: sipush #512
    //   6966: iastore
    //   6967: dup
    //   6968: bipush #46
    //   6970: iconst_0
    //   6971: iastore
    //   6972: dup
    //   6973: bipush #47
    //   6975: ldc 134348808
    //   6977: iastore
    //   6978: dup
    //   6979: bipush #48
    //   6981: ldc 134218248
    //   6983: iastore
    //   6984: dup
    //   6985: bipush #49
    //   6987: ldc 131072
    //   6989: iastore
    //   6990: dup
    //   6991: bipush #50
    //   6993: ldc 134217728
    //   6995: iastore
    //   6996: dup
    //   6997: bipush #51
    //   6999: ldc 134349320
    //   7001: iastore
    //   7002: dup
    //   7003: bipush #52
    //   7005: bipush #8
    //   7007: iastore
    //   7008: dup
    //   7009: bipush #53
    //   7011: ldc 131592
    //   7013: iastore
    //   7014: dup
    //   7015: bipush #54
    //   7017: ldc 131584
    //   7019: iastore
    //   7020: dup
    //   7021: bipush #55
    //   7023: ldc 134217736
    //   7025: iastore
    //   7026: dup
    //   7027: bipush #56
    //   7029: ldc 134348800
    //   7031: iastore
    //   7032: dup
    //   7033: bipush #57
    //   7035: ldc 134218248
    //   7037: iastore
    //   7038: dup
    //   7039: bipush #58
    //   7041: sipush #520
    //   7044: iastore
    //   7045: dup
    //   7046: bipush #59
    //   7048: ldc 134348800
    //   7050: iastore
    //   7051: dup
    //   7052: bipush #60
    //   7054: ldc 131592
    //   7056: iastore
    //   7057: dup
    //   7058: bipush #61
    //   7060: bipush #8
    //   7062: iastore
    //   7063: dup
    //   7064: bipush #62
    //   7066: ldc 134348808
    //   7068: iastore
    //   7069: dup
    //   7070: bipush #63
    //   7072: ldc 131584
    //   7074: iastore
    //   7075: astore #9
    //   7077: bipush #64
    //   7079: newarray int
    //   7081: dup
    //   7082: iconst_0
    //   7083: ldc 8396801
    //   7085: iastore
    //   7086: dup
    //   7087: iconst_1
    //   7088: sipush #8321
    //   7091: iastore
    //   7092: dup
    //   7093: iconst_2
    //   7094: sipush #8321
    //   7097: iastore
    //   7098: dup
    //   7099: iconst_3
    //   7100: sipush #128
    //   7103: iastore
    //   7104: dup
    //   7105: iconst_4
    //   7106: ldc 8396928
    //   7108: iastore
    //   7109: dup
    //   7110: iconst_5
    //   7111: ldc 8388737
    //   7113: iastore
    //   7114: dup
    //   7115: bipush #6
    //   7117: ldc 8388609
    //   7119: iastore
    //   7120: dup
    //   7121: bipush #7
    //   7123: sipush #8193
    //   7126: iastore
    //   7127: dup
    //   7128: bipush #8
    //   7130: iconst_0
    //   7131: iastore
    //   7132: dup
    //   7133: bipush #9
    //   7135: ldc 8396800
    //   7137: iastore
    //   7138: dup
    //   7139: bipush #10
    //   7141: ldc 8396800
    //   7143: iastore
    //   7144: dup
    //   7145: bipush #11
    //   7147: ldc 8396929
    //   7149: iastore
    //   7150: dup
    //   7151: bipush #12
    //   7153: sipush #129
    //   7156: iastore
    //   7157: dup
    //   7158: bipush #13
    //   7160: iconst_0
    //   7161: iastore
    //   7162: dup
    //   7163: bipush #14
    //   7165: ldc 8388736
    //   7167: iastore
    //   7168: dup
    //   7169: bipush #15
    //   7171: ldc 8388609
    //   7173: iastore
    //   7174: dup
    //   7175: bipush #16
    //   7177: iconst_1
    //   7178: iastore
    //   7179: dup
    //   7180: bipush #17
    //   7182: sipush #8192
    //   7185: iastore
    //   7186: dup
    //   7187: bipush #18
    //   7189: ldc 8388608
    //   7191: iastore
    //   7192: dup
    //   7193: bipush #19
    //   7195: ldc 8396801
    //   7197: iastore
    //   7198: dup
    //   7199: bipush #20
    //   7201: sipush #128
    //   7204: iastore
    //   7205: dup
    //   7206: bipush #21
    //   7208: ldc 8388608
    //   7210: iastore
    //   7211: dup
    //   7212: bipush #22
    //   7214: sipush #8193
    //   7217: iastore
    //   7218: dup
    //   7219: bipush #23
    //   7221: sipush #8320
    //   7224: iastore
    //   7225: dup
    //   7226: bipush #24
    //   7228: ldc 8388737
    //   7230: iastore
    //   7231: dup
    //   7232: bipush #25
    //   7234: iconst_1
    //   7235: iastore
    //   7236: dup
    //   7237: bipush #26
    //   7239: sipush #8320
    //   7242: iastore
    //   7243: dup
    //   7244: bipush #27
    //   7246: ldc 8388736
    //   7248: iastore
    //   7249: dup
    //   7250: bipush #28
    //   7252: sipush #8192
    //   7255: iastore
    //   7256: dup
    //   7257: bipush #29
    //   7259: ldc 8396928
    //   7261: iastore
    //   7262: dup
    //   7263: bipush #30
    //   7265: ldc 8396929
    //   7267: iastore
    //   7268: dup
    //   7269: bipush #31
    //   7271: sipush #129
    //   7274: iastore
    //   7275: dup
    //   7276: bipush #32
    //   7278: ldc 8388736
    //   7280: iastore
    //   7281: dup
    //   7282: bipush #33
    //   7284: ldc 8388609
    //   7286: iastore
    //   7287: dup
    //   7288: bipush #34
    //   7290: ldc 8396800
    //   7292: iastore
    //   7293: dup
    //   7294: bipush #35
    //   7296: ldc 8396929
    //   7298: iastore
    //   7299: dup
    //   7300: bipush #36
    //   7302: sipush #129
    //   7305: iastore
    //   7306: dup
    //   7307: bipush #37
    //   7309: iconst_0
    //   7310: iastore
    //   7311: dup
    //   7312: bipush #38
    //   7314: iconst_0
    //   7315: iastore
    //   7316: dup
    //   7317: bipush #39
    //   7319: ldc 8396800
    //   7321: iastore
    //   7322: dup
    //   7323: bipush #40
    //   7325: sipush #8320
    //   7328: iastore
    //   7329: dup
    //   7330: bipush #41
    //   7332: ldc 8388736
    //   7334: iastore
    //   7335: dup
    //   7336: bipush #42
    //   7338: ldc 8388737
    //   7340: iastore
    //   7341: dup
    //   7342: bipush #43
    //   7344: iconst_1
    //   7345: iastore
    //   7346: dup
    //   7347: bipush #44
    //   7349: ldc 8396801
    //   7351: iastore
    //   7352: dup
    //   7353: bipush #45
    //   7355: sipush #8321
    //   7358: iastore
    //   7359: dup
    //   7360: bipush #46
    //   7362: sipush #8321
    //   7365: iastore
    //   7366: dup
    //   7367: bipush #47
    //   7369: sipush #128
    //   7372: iastore
    //   7373: dup
    //   7374: bipush #48
    //   7376: ldc 8396929
    //   7378: iastore
    //   7379: dup
    //   7380: bipush #49
    //   7382: sipush #129
    //   7385: iastore
    //   7386: dup
    //   7387: bipush #50
    //   7389: iconst_1
    //   7390: iastore
    //   7391: dup
    //   7392: bipush #51
    //   7394: sipush #8192
    //   7397: iastore
    //   7398: dup
    //   7399: bipush #52
    //   7401: ldc 8388609
    //   7403: iastore
    //   7404: dup
    //   7405: bipush #53
    //   7407: sipush #8193
    //   7410: iastore
    //   7411: dup
    //   7412: bipush #54
    //   7414: ldc 8396928
    //   7416: iastore
    //   7417: dup
    //   7418: bipush #55
    //   7420: ldc 8388737
    //   7422: iastore
    //   7423: dup
    //   7424: bipush #56
    //   7426: sipush #8193
    //   7429: iastore
    //   7430: dup
    //   7431: bipush #57
    //   7433: sipush #8320
    //   7436: iastore
    //   7437: dup
    //   7438: bipush #58
    //   7440: ldc 8388608
    //   7442: iastore
    //   7443: dup
    //   7444: bipush #59
    //   7446: ldc 8396801
    //   7448: iastore
    //   7449: dup
    //   7450: bipush #60
    //   7452: sipush #128
    //   7455: iastore
    //   7456: dup
    //   7457: bipush #61
    //   7459: ldc 8388608
    //   7461: iastore
    //   7462: dup
    //   7463: bipush #62
    //   7465: sipush #8192
    //   7468: iastore
    //   7469: dup
    //   7470: bipush #63
    //   7472: ldc 8396928
    //   7474: iastore
    //   7475: astore #10
    //   7477: bipush #64
    //   7479: newarray int
    //   7481: dup
    //   7482: iconst_0
    //   7483: sipush #256
    //   7486: iastore
    //   7487: dup
    //   7488: iconst_1
    //   7489: ldc 34078976
    //   7491: iastore
    //   7492: dup
    //   7493: iconst_2
    //   7494: ldc 34078720
    //   7496: iastore
    //   7497: dup
    //   7498: iconst_3
    //   7499: ldc 1107296512
    //   7501: iastore
    //   7502: dup
    //   7503: iconst_4
    //   7504: ldc 524288
    //   7506: iastore
    //   7507: dup
    //   7508: iconst_5
    //   7509: sipush #256
    //   7512: iastore
    //   7513: dup
    //   7514: bipush #6
    //   7516: ldc 1073741824
    //   7518: iastore
    //   7519: dup
    //   7520: bipush #7
    //   7522: ldc 34078720
    //   7524: iastore
    //   7525: dup
    //   7526: bipush #8
    //   7528: ldc 1074266368
    //   7530: iastore
    //   7531: dup
    //   7532: bipush #9
    //   7534: ldc 524288
    //   7536: iastore
    //   7537: dup
    //   7538: bipush #10
    //   7540: ldc 33554688
    //   7542: iastore
    //   7543: dup
    //   7544: bipush #11
    //   7546: ldc 1074266368
    //   7548: iastore
    //   7549: dup
    //   7550: bipush #12
    //   7552: ldc 1107296512
    //   7554: iastore
    //   7555: dup
    //   7556: bipush #13
    //   7558: ldc 1107820544
    //   7560: iastore
    //   7561: dup
    //   7562: bipush #14
    //   7564: ldc 524544
    //   7566: iastore
    //   7567: dup
    //   7568: bipush #15
    //   7570: ldc 1073741824
    //   7572: iastore
    //   7573: dup
    //   7574: bipush #16
    //   7576: ldc 33554432
    //   7578: iastore
    //   7579: dup
    //   7580: bipush #17
    //   7582: ldc 1074266112
    //   7584: iastore
    //   7585: dup
    //   7586: bipush #18
    //   7588: ldc 1074266112
    //   7590: iastore
    //   7591: dup
    //   7592: bipush #19
    //   7594: iconst_0
    //   7595: iastore
    //   7596: dup
    //   7597: bipush #20
    //   7599: ldc 1073742080
    //   7601: iastore
    //   7602: dup
    //   7603: bipush #21
    //   7605: ldc 1107820800
    //   7607: iastore
    //   7608: dup
    //   7609: bipush #22
    //   7611: ldc 1107820800
    //   7613: iastore
    //   7614: dup
    //   7615: bipush #23
    //   7617: ldc 33554688
    //   7619: iastore
    //   7620: dup
    //   7621: bipush #24
    //   7623: ldc 1107820544
    //   7625: iastore
    //   7626: dup
    //   7627: bipush #25
    //   7629: ldc 1073742080
    //   7631: iastore
    //   7632: dup
    //   7633: bipush #26
    //   7635: iconst_0
    //   7636: iastore
    //   7637: dup
    //   7638: bipush #27
    //   7640: ldc 1107296256
    //   7642: iastore
    //   7643: dup
    //   7644: bipush #28
    //   7646: ldc 34078976
    //   7648: iastore
    //   7649: dup
    //   7650: bipush #29
    //   7652: ldc 33554432
    //   7654: iastore
    //   7655: dup
    //   7656: bipush #30
    //   7658: ldc 1107296256
    //   7660: iastore
    //   7661: dup
    //   7662: bipush #31
    //   7664: ldc 524544
    //   7666: iastore
    //   7667: dup
    //   7668: bipush #32
    //   7670: ldc 524288
    //   7672: iastore
    //   7673: dup
    //   7674: bipush #33
    //   7676: ldc 1107296512
    //   7678: iastore
    //   7679: dup
    //   7680: bipush #34
    //   7682: sipush #256
    //   7685: iastore
    //   7686: dup
    //   7687: bipush #35
    //   7689: ldc 33554432
    //   7691: iastore
    //   7692: dup
    //   7693: bipush #36
    //   7695: ldc 1073741824
    //   7697: iastore
    //   7698: dup
    //   7699: bipush #37
    //   7701: ldc 34078720
    //   7703: iastore
    //   7704: dup
    //   7705: bipush #38
    //   7707: ldc 1107296512
    //   7709: iastore
    //   7710: dup
    //   7711: bipush #39
    //   7713: ldc 1074266368
    //   7715: iastore
    //   7716: dup
    //   7717: bipush #40
    //   7719: ldc 33554688
    //   7721: iastore
    //   7722: dup
    //   7723: bipush #41
    //   7725: ldc 1073741824
    //   7727: iastore
    //   7728: dup
    //   7729: bipush #42
    //   7731: ldc 1107820544
    //   7733: iastore
    //   7734: dup
    //   7735: bipush #43
    //   7737: ldc 34078976
    //   7739: iastore
    //   7740: dup
    //   7741: bipush #44
    //   7743: ldc 1074266368
    //   7745: iastore
    //   7746: dup
    //   7747: bipush #45
    //   7749: sipush #256
    //   7752: iastore
    //   7753: dup
    //   7754: bipush #46
    //   7756: ldc 33554432
    //   7758: iastore
    //   7759: dup
    //   7760: bipush #47
    //   7762: ldc 1107820544
    //   7764: iastore
    //   7765: dup
    //   7766: bipush #48
    //   7768: ldc 1107820800
    //   7770: iastore
    //   7771: dup
    //   7772: bipush #49
    //   7774: ldc 524544
    //   7776: iastore
    //   7777: dup
    //   7778: bipush #50
    //   7780: ldc 1107296256
    //   7782: iastore
    //   7783: dup
    //   7784: bipush #51
    //   7786: ldc 1107820800
    //   7788: iastore
    //   7789: dup
    //   7790: bipush #52
    //   7792: ldc 34078720
    //   7794: iastore
    //   7795: dup
    //   7796: bipush #53
    //   7798: iconst_0
    //   7799: iastore
    //   7800: dup
    //   7801: bipush #54
    //   7803: ldc 1074266112
    //   7805: iastore
    //   7806: dup
    //   7807: bipush #55
    //   7809: ldc 1107296256
    //   7811: iastore
    //   7812: dup
    //   7813: bipush #56
    //   7815: ldc 524544
    //   7817: iastore
    //   7818: dup
    //   7819: bipush #57
    //   7821: ldc 33554688
    //   7823: iastore
    //   7824: dup
    //   7825: bipush #58
    //   7827: ldc 1073742080
    //   7829: iastore
    //   7830: dup
    //   7831: bipush #59
    //   7833: ldc 524288
    //   7835: iastore
    //   7836: dup
    //   7837: bipush #60
    //   7839: iconst_0
    //   7840: iastore
    //   7841: dup
    //   7842: bipush #61
    //   7844: ldc 1074266112
    //   7846: iastore
    //   7847: dup
    //   7848: bipush #62
    //   7850: ldc 34078976
    //   7852: iastore
    //   7853: dup
    //   7854: bipush #63
    //   7856: ldc 1073742080
    //   7858: iastore
    //   7859: astore #11
    //   7861: bipush #64
    //   7863: newarray int
    //   7865: dup
    //   7866: iconst_0
    //   7867: ldc 536870928
    //   7869: iastore
    //   7870: dup
    //   7871: iconst_1
    //   7872: ldc 541065216
    //   7874: iastore
    //   7875: dup
    //   7876: iconst_2
    //   7877: sipush #16384
    //   7880: iastore
    //   7881: dup
    //   7882: iconst_3
    //   7883: ldc 541081616
    //   7885: iastore
    //   7886: dup
    //   7887: iconst_4
    //   7888: ldc 541065216
    //   7890: iastore
    //   7891: dup
    //   7892: iconst_5
    //   7893: bipush #16
    //   7895: iastore
    //   7896: dup
    //   7897: bipush #6
    //   7899: ldc 541081616
    //   7901: iastore
    //   7902: dup
    //   7903: bipush #7
    //   7905: ldc 4194304
    //   7907: iastore
    //   7908: dup
    //   7909: bipush #8
    //   7911: ldc 536887296
    //   7913: iastore
    //   7914: dup
    //   7915: bipush #9
    //   7917: ldc 4210704
    //   7919: iastore
    //   7920: dup
    //   7921: bipush #10
    //   7923: ldc 4194304
    //   7925: iastore
    //   7926: dup
    //   7927: bipush #11
    //   7929: ldc 536870928
    //   7931: iastore
    //   7932: dup
    //   7933: bipush #12
    //   7935: ldc 4194320
    //   7937: iastore
    //   7938: dup
    //   7939: bipush #13
    //   7941: ldc 536887296
    //   7943: iastore
    //   7944: dup
    //   7945: bipush #14
    //   7947: ldc 536870912
    //   7949: iastore
    //   7950: dup
    //   7951: bipush #15
    //   7953: sipush #16400
    //   7956: iastore
    //   7957: dup
    //   7958: bipush #16
    //   7960: iconst_0
    //   7961: iastore
    //   7962: dup
    //   7963: bipush #17
    //   7965: ldc 4194320
    //   7967: iastore
    //   7968: dup
    //   7969: bipush #18
    //   7971: ldc 536887312
    //   7973: iastore
    //   7974: dup
    //   7975: bipush #19
    //   7977: sipush #16384
    //   7980: iastore
    //   7981: dup
    //   7982: bipush #20
    //   7984: ldc 4210688
    //   7986: iastore
    //   7987: dup
    //   7988: bipush #21
    //   7990: ldc 536887312
    //   7992: iastore
    //   7993: dup
    //   7994: bipush #22
    //   7996: bipush #16
    //   7998: iastore
    //   7999: dup
    //   8000: bipush #23
    //   8002: ldc 541065232
    //   8004: iastore
    //   8005: dup
    //   8006: bipush #24
    //   8008: ldc 541065232
    //   8010: iastore
    //   8011: dup
    //   8012: bipush #25
    //   8014: iconst_0
    //   8015: iastore
    //   8016: dup
    //   8017: bipush #26
    //   8019: ldc 4210704
    //   8021: iastore
    //   8022: dup
    //   8023: bipush #27
    //   8025: ldc 541081600
    //   8027: iastore
    //   8028: dup
    //   8029: bipush #28
    //   8031: sipush #16400
    //   8034: iastore
    //   8035: dup
    //   8036: bipush #29
    //   8038: ldc 4210688
    //   8040: iastore
    //   8041: dup
    //   8042: bipush #30
    //   8044: ldc 541081600
    //   8046: iastore
    //   8047: dup
    //   8048: bipush #31
    //   8050: ldc 536870912
    //   8052: iastore
    //   8053: dup
    //   8054: bipush #32
    //   8056: ldc 536887296
    //   8058: iastore
    //   8059: dup
    //   8060: bipush #33
    //   8062: bipush #16
    //   8064: iastore
    //   8065: dup
    //   8066: bipush #34
    //   8068: ldc 541065232
    //   8070: iastore
    //   8071: dup
    //   8072: bipush #35
    //   8074: ldc 4210688
    //   8076: iastore
    //   8077: dup
    //   8078: bipush #36
    //   8080: ldc 541081616
    //   8082: iastore
    //   8083: dup
    //   8084: bipush #37
    //   8086: ldc 4194304
    //   8088: iastore
    //   8089: dup
    //   8090: bipush #38
    //   8092: sipush #16400
    //   8095: iastore
    //   8096: dup
    //   8097: bipush #39
    //   8099: ldc 536870928
    //   8101: iastore
    //   8102: dup
    //   8103: bipush #40
    //   8105: ldc 4194304
    //   8107: iastore
    //   8108: dup
    //   8109: bipush #41
    //   8111: ldc 536887296
    //   8113: iastore
    //   8114: dup
    //   8115: bipush #42
    //   8117: ldc 536870912
    //   8119: iastore
    //   8120: dup
    //   8121: bipush #43
    //   8123: sipush #16400
    //   8126: iastore
    //   8127: dup
    //   8128: bipush #44
    //   8130: ldc 536870928
    //   8132: iastore
    //   8133: dup
    //   8134: bipush #45
    //   8136: ldc 541081616
    //   8138: iastore
    //   8139: dup
    //   8140: bipush #46
    //   8142: ldc 4210688
    //   8144: iastore
    //   8145: dup
    //   8146: bipush #47
    //   8148: ldc 541065216
    //   8150: iastore
    //   8151: dup
    //   8152: bipush #48
    //   8154: ldc 4210704
    //   8156: iastore
    //   8157: dup
    //   8158: bipush #49
    //   8160: ldc 541081600
    //   8162: iastore
    //   8163: dup
    //   8164: bipush #50
    //   8166: iconst_0
    //   8167: iastore
    //   8168: dup
    //   8169: bipush #51
    //   8171: ldc 541065232
    //   8173: iastore
    //   8174: dup
    //   8175: bipush #52
    //   8177: bipush #16
    //   8179: iastore
    //   8180: dup
    //   8181: bipush #53
    //   8183: sipush #16384
    //   8186: iastore
    //   8187: dup
    //   8188: bipush #54
    //   8190: ldc 541065216
    //   8192: iastore
    //   8193: dup
    //   8194: bipush #55
    //   8196: ldc 4210704
    //   8198: iastore
    //   8199: dup
    //   8200: bipush #56
    //   8202: sipush #16384
    //   8205: iastore
    //   8206: dup
    //   8207: bipush #57
    //   8209: ldc 4194320
    //   8211: iastore
    //   8212: dup
    //   8213: bipush #58
    //   8215: ldc 536887312
    //   8217: iastore
    //   8218: dup
    //   8219: bipush #59
    //   8221: iconst_0
    //   8222: iastore
    //   8223: dup
    //   8224: bipush #60
    //   8226: ldc 541081600
    //   8228: iastore
    //   8229: dup
    //   8230: bipush #61
    //   8232: ldc 536870912
    //   8234: iastore
    //   8235: dup
    //   8236: bipush #62
    //   8238: ldc 4194320
    //   8240: iastore
    //   8241: dup
    //   8242: bipush #63
    //   8244: ldc 536887312
    //   8246: iastore
    //   8247: astore #12
    //   8249: bipush #64
    //   8251: newarray int
    //   8253: dup
    //   8254: iconst_0
    //   8255: ldc 2097152
    //   8257: iastore
    //   8258: dup
    //   8259: iconst_1
    //   8260: ldc 69206018
    //   8262: iastore
    //   8263: dup
    //   8264: iconst_2
    //   8265: ldc 67110914
    //   8267: iastore
    //   8268: dup
    //   8269: iconst_3
    //   8270: iconst_0
    //   8271: iastore
    //   8272: dup
    //   8273: iconst_4
    //   8274: sipush #2048
    //   8277: iastore
    //   8278: dup
    //   8279: iconst_5
    //   8280: ldc 67110914
    //   8282: iastore
    //   8283: dup
    //   8284: bipush #6
    //   8286: ldc 2099202
    //   8288: iastore
    //   8289: dup
    //   8290: bipush #7
    //   8292: ldc 69208064
    //   8294: iastore
    //   8295: dup
    //   8296: bipush #8
    //   8298: ldc 69208066
    //   8300: iastore
    //   8301: dup
    //   8302: bipush #9
    //   8304: ldc 2097152
    //   8306: iastore
    //   8307: dup
    //   8308: bipush #10
    //   8310: iconst_0
    //   8311: iastore
    //   8312: dup
    //   8313: bipush #11
    //   8315: ldc 67108866
    //   8317: iastore
    //   8318: dup
    //   8319: bipush #12
    //   8321: iconst_2
    //   8322: iastore
    //   8323: dup
    //   8324: bipush #13
    //   8326: ldc 67108864
    //   8328: iastore
    //   8329: dup
    //   8330: bipush #14
    //   8332: ldc 69206018
    //   8334: iastore
    //   8335: dup
    //   8336: bipush #15
    //   8338: sipush #2050
    //   8341: iastore
    //   8342: dup
    //   8343: bipush #16
    //   8345: ldc 67110912
    //   8347: iastore
    //   8348: dup
    //   8349: bipush #17
    //   8351: ldc 2099202
    //   8353: iastore
    //   8354: dup
    //   8355: bipush #18
    //   8357: ldc 2097154
    //   8359: iastore
    //   8360: dup
    //   8361: bipush #19
    //   8363: ldc 67110912
    //   8365: iastore
    //   8366: dup
    //   8367: bipush #20
    //   8369: ldc 67108866
    //   8371: iastore
    //   8372: dup
    //   8373: bipush #21
    //   8375: ldc 69206016
    //   8377: iastore
    //   8378: dup
    //   8379: bipush #22
    //   8381: ldc 69208064
    //   8383: iastore
    //   8384: dup
    //   8385: bipush #23
    //   8387: ldc 2097154
    //   8389: iastore
    //   8390: dup
    //   8391: bipush #24
    //   8393: ldc 69206016
    //   8395: iastore
    //   8396: dup
    //   8397: bipush #25
    //   8399: sipush #2048
    //   8402: iastore
    //   8403: dup
    //   8404: bipush #26
    //   8406: sipush #2050
    //   8409: iastore
    //   8410: dup
    //   8411: bipush #27
    //   8413: ldc 69208066
    //   8415: iastore
    //   8416: dup
    //   8417: bipush #28
    //   8419: ldc 2099200
    //   8421: iastore
    //   8422: dup
    //   8423: bipush #29
    //   8425: iconst_2
    //   8426: iastore
    //   8427: dup
    //   8428: bipush #30
    //   8430: ldc 67108864
    //   8432: iastore
    //   8433: dup
    //   8434: bipush #31
    //   8436: ldc 2099200
    //   8438: iastore
    //   8439: dup
    //   8440: bipush #32
    //   8442: ldc 67108864
    //   8444: iastore
    //   8445: dup
    //   8446: bipush #33
    //   8448: ldc 2099200
    //   8450: iastore
    //   8451: dup
    //   8452: bipush #34
    //   8454: ldc 2097152
    //   8456: iastore
    //   8457: dup
    //   8458: bipush #35
    //   8460: ldc 67110914
    //   8462: iastore
    //   8463: dup
    //   8464: bipush #36
    //   8466: ldc 67110914
    //   8468: iastore
    //   8469: dup
    //   8470: bipush #37
    //   8472: ldc 69206018
    //   8474: iastore
    //   8475: dup
    //   8476: bipush #38
    //   8478: ldc 69206018
    //   8480: iastore
    //   8481: dup
    //   8482: bipush #39
    //   8484: iconst_2
    //   8485: iastore
    //   8486: dup
    //   8487: bipush #40
    //   8489: ldc 2097154
    //   8491: iastore
    //   8492: dup
    //   8493: bipush #41
    //   8495: ldc 67108864
    //   8497: iastore
    //   8498: dup
    //   8499: bipush #42
    //   8501: ldc 67110912
    //   8503: iastore
    //   8504: dup
    //   8505: bipush #43
    //   8507: ldc 2097152
    //   8509: iastore
    //   8510: dup
    //   8511: bipush #44
    //   8513: ldc 69208064
    //   8515: iastore
    //   8516: dup
    //   8517: bipush #45
    //   8519: sipush #2050
    //   8522: iastore
    //   8523: dup
    //   8524: bipush #46
    //   8526: ldc 2099202
    //   8528: iastore
    //   8529: dup
    //   8530: bipush #47
    //   8532: ldc 69208064
    //   8534: iastore
    //   8535: dup
    //   8536: bipush #48
    //   8538: sipush #2050
    //   8541: iastore
    //   8542: dup
    //   8543: bipush #49
    //   8545: ldc 67108866
    //   8547: iastore
    //   8548: dup
    //   8549: bipush #50
    //   8551: ldc 69208066
    //   8553: iastore
    //   8554: dup
    //   8555: bipush #51
    //   8557: ldc 69206016
    //   8559: iastore
    //   8560: dup
    //   8561: bipush #52
    //   8563: ldc 2099200
    //   8565: iastore
    //   8566: dup
    //   8567: bipush #53
    //   8569: iconst_0
    //   8570: iastore
    //   8571: dup
    //   8572: bipush #54
    //   8574: iconst_2
    //   8575: iastore
    //   8576: dup
    //   8577: bipush #55
    //   8579: ldc 69208066
    //   8581: iastore
    //   8582: dup
    //   8583: bipush #56
    //   8585: iconst_0
    //   8586: iastore
    //   8587: dup
    //   8588: bipush #57
    //   8590: ldc 2099202
    //   8592: iastore
    //   8593: dup
    //   8594: bipush #58
    //   8596: ldc 69206016
    //   8598: iastore
    //   8599: dup
    //   8600: bipush #59
    //   8602: sipush #2048
    //   8605: iastore
    //   8606: dup
    //   8607: bipush #60
    //   8609: ldc 67108866
    //   8611: iastore
    //   8612: dup
    //   8613: bipush #61
    //   8615: ldc 67110912
    //   8617: iastore
    //   8618: dup
    //   8619: bipush #62
    //   8621: sipush #2048
    //   8624: iastore
    //   8625: dup
    //   8626: bipush #63
    //   8628: ldc 2097154
    //   8630: iastore
    //   8631: astore #13
    //   8633: bipush #64
    //   8635: newarray int
    //   8637: dup
    //   8638: iconst_0
    //   8639: ldc 268439616
    //   8641: iastore
    //   8642: dup
    //   8643: iconst_1
    //   8644: sipush #4096
    //   8647: iastore
    //   8648: dup
    //   8649: iconst_2
    //   8650: ldc 262144
    //   8652: iastore
    //   8653: dup
    //   8654: iconst_3
    //   8655: ldc 268701760
    //   8657: iastore
    //   8658: dup
    //   8659: iconst_4
    //   8660: ldc 268435456
    //   8662: iastore
    //   8663: dup
    //   8664: iconst_5
    //   8665: ldc 268439616
    //   8667: iastore
    //   8668: dup
    //   8669: bipush #6
    //   8671: bipush #64
    //   8673: iastore
    //   8674: dup
    //   8675: bipush #7
    //   8677: ldc 268435456
    //   8679: iastore
    //   8680: dup
    //   8681: bipush #8
    //   8683: ldc 262208
    //   8685: iastore
    //   8686: dup
    //   8687: bipush #9
    //   8689: ldc 268697600
    //   8691: iastore
    //   8692: dup
    //   8693: bipush #10
    //   8695: ldc 268701760
    //   8697: iastore
    //   8698: dup
    //   8699: bipush #11
    //   8701: ldc 266240
    //   8703: iastore
    //   8704: dup
    //   8705: bipush #12
    //   8707: ldc 268701696
    //   8709: iastore
    //   8710: dup
    //   8711: bipush #13
    //   8713: ldc 266304
    //   8715: iastore
    //   8716: dup
    //   8717: bipush #14
    //   8719: sipush #4096
    //   8722: iastore
    //   8723: dup
    //   8724: bipush #15
    //   8726: bipush #64
    //   8728: iastore
    //   8729: dup
    //   8730: bipush #16
    //   8732: ldc 268697600
    //   8734: iastore
    //   8735: dup
    //   8736: bipush #17
    //   8738: ldc 268435520
    //   8740: iastore
    //   8741: dup
    //   8742: bipush #18
    //   8744: ldc 268439552
    //   8746: iastore
    //   8747: dup
    //   8748: bipush #19
    //   8750: sipush #4160
    //   8753: iastore
    //   8754: dup
    //   8755: bipush #20
    //   8757: ldc 266240
    //   8759: iastore
    //   8760: dup
    //   8761: bipush #21
    //   8763: ldc 262208
    //   8765: iastore
    //   8766: dup
    //   8767: bipush #22
    //   8769: ldc 268697664
    //   8771: iastore
    //   8772: dup
    //   8773: bipush #23
    //   8775: ldc 268701696
    //   8777: iastore
    //   8778: dup
    //   8779: bipush #24
    //   8781: sipush #4160
    //   8784: iastore
    //   8785: dup
    //   8786: bipush #25
    //   8788: iconst_0
    //   8789: iastore
    //   8790: dup
    //   8791: bipush #26
    //   8793: iconst_0
    //   8794: iastore
    //   8795: dup
    //   8796: bipush #27
    //   8798: ldc 268697664
    //   8800: iastore
    //   8801: dup
    //   8802: bipush #28
    //   8804: ldc 268435520
    //   8806: iastore
    //   8807: dup
    //   8808: bipush #29
    //   8810: ldc 268439552
    //   8812: iastore
    //   8813: dup
    //   8814: bipush #30
    //   8816: ldc 266304
    //   8818: iastore
    //   8819: dup
    //   8820: bipush #31
    //   8822: ldc 262144
    //   8824: iastore
    //   8825: dup
    //   8826: bipush #32
    //   8828: ldc 266304
    //   8830: iastore
    //   8831: dup
    //   8832: bipush #33
    //   8834: ldc 262144
    //   8836: iastore
    //   8837: dup
    //   8838: bipush #34
    //   8840: ldc 268701696
    //   8842: iastore
    //   8843: dup
    //   8844: bipush #35
    //   8846: sipush #4096
    //   8849: iastore
    //   8850: dup
    //   8851: bipush #36
    //   8853: bipush #64
    //   8855: iastore
    //   8856: dup
    //   8857: bipush #37
    //   8859: ldc 268697664
    //   8861: iastore
    //   8862: dup
    //   8863: bipush #38
    //   8865: sipush #4096
    //   8868: iastore
    //   8869: dup
    //   8870: bipush #39
    //   8872: ldc 266304
    //   8874: iastore
    //   8875: dup
    //   8876: bipush #40
    //   8878: ldc 268439552
    //   8880: iastore
    //   8881: dup
    //   8882: bipush #41
    //   8884: bipush #64
    //   8886: iastore
    //   8887: dup
    //   8888: bipush #42
    //   8890: ldc 268435520
    //   8892: iastore
    //   8893: dup
    //   8894: bipush #43
    //   8896: ldc 268697600
    //   8898: iastore
    //   8899: dup
    //   8900: bipush #44
    //   8902: ldc 268697664
    //   8904: iastore
    //   8905: dup
    //   8906: bipush #45
    //   8908: ldc 268435456
    //   8910: iastore
    //   8911: dup
    //   8912: bipush #46
    //   8914: ldc 262144
    //   8916: iastore
    //   8917: dup
    //   8918: bipush #47
    //   8920: ldc 268439616
    //   8922: iastore
    //   8923: dup
    //   8924: bipush #48
    //   8926: iconst_0
    //   8927: iastore
    //   8928: dup
    //   8929: bipush #49
    //   8931: ldc 268701760
    //   8933: iastore
    //   8934: dup
    //   8935: bipush #50
    //   8937: ldc 262208
    //   8939: iastore
    //   8940: dup
    //   8941: bipush #51
    //   8943: ldc 268435520
    //   8945: iastore
    //   8946: dup
    //   8947: bipush #52
    //   8949: ldc 268697600
    //   8951: iastore
    //   8952: dup
    //   8953: bipush #53
    //   8955: ldc 268439552
    //   8957: iastore
    //   8958: dup
    //   8959: bipush #54
    //   8961: ldc 268439616
    //   8963: iastore
    //   8964: dup
    //   8965: bipush #55
    //   8967: iconst_0
    //   8968: iastore
    //   8969: dup
    //   8970: bipush #56
    //   8972: ldc 268701760
    //   8974: iastore
    //   8975: dup
    //   8976: bipush #57
    //   8978: ldc 266240
    //   8980: iastore
    //   8981: dup
    //   8982: bipush #58
    //   8984: ldc 266240
    //   8986: iastore
    //   8987: dup
    //   8988: bipush #59
    //   8990: sipush #4160
    //   8993: iastore
    //   8994: dup
    //   8995: bipush #60
    //   8997: sipush #4160
    //   9000: iastore
    //   9001: dup
    //   9002: bipush #61
    //   9004: ldc 262208
    //   9006: iastore
    //   9007: dup
    //   9008: bipush #62
    //   9010: ldc 268435456
    //   9012: iastore
    //   9013: dup
    //   9014: bipush #63
    //   9016: ldc 268701696
    //   9018: iastore
    //   9019: astore #14
    //   9021: aload #4
    //   9023: arraylength
    //   9024: istore #15
    //   9026: iload #15
    //   9028: bipush #8
    //   9030: irem
    //   9031: ifeq -> 9055
    //   9034: new java/lang/Exception
    //   9037: dup
    //   9038: sipush #-20542
    //   9041: sipush #-9604
    //   9044: invokestatic a : (II)Ljava/lang/String;
    //   9047: invokespecial <init> : (Ljava/lang/String;)V
    //   9050: athrow
    //   9051: invokestatic a : (Ljava/lang/Throwable;)Ljava/lang/Throwable;
    //   9054: athrow
    //   9055: iconst_2
    //   9056: newarray int
    //   9058: astore #16
    //   9060: iload #15
    //   9062: newarray byte
    //   9064: astore #17
    //   9066: iload #15
    //   9068: bipush #8
    //   9070: idiv
    //   9071: istore #18
    //   9073: iconst_0
    //   9074: istore #19
    //   9076: iload #19
    //   9078: iload #18
    //   9080: if_icmpge -> 9998
    //   9083: iload #19
    //   9085: bipush #8
    //   9087: imul
    //   9088: istore #20
    //   9090: iconst_0
    //   9091: istore #21
    //   9093: iload #21
    //   9095: iconst_2
    //   9096: if_icmpge -> 9185
    //   9099: aload #16
    //   9101: iload #21
    //   9103: aload #4
    //   9105: iload #20
    //   9107: iload #21
    //   9109: iconst_4
    //   9110: imul
    //   9111: iadd
    //   9112: baload
    //   9113: sipush #255
    //   9116: iand
    //   9117: bipush #24
    //   9119: ishl
    //   9120: aload #4
    //   9122: iload #20
    //   9124: iload #21
    //   9126: iconst_4
    //   9127: imul
    //   9128: iadd
    //   9129: iconst_1
    //   9130: iadd
    //   9131: baload
    //   9132: sipush #255
    //   9135: iand
    //   9136: bipush #16
    //   9138: ishl
    //   9139: ior
    //   9140: aload #4
    //   9142: iload #20
    //   9144: iload #21
    //   9146: iconst_4
    //   9147: imul
    //   9148: iadd
    //   9149: iconst_2
    //   9150: iadd
    //   9151: baload
    //   9152: sipush #255
    //   9155: iand
    //   9156: bipush #8
    //   9158: ishl
    //   9159: ior
    //   9160: aload #4
    //   9162: iload #20
    //   9164: iload #21
    //   9166: iconst_4
    //   9167: imul
    //   9168: iadd
    //   9169: iconst_3
    //   9170: iadd
    //   9171: baload
    //   9172: sipush #255
    //   9175: iand
    //   9176: ior
    //   9177: iastore
    //   9178: iinc #21, 1
    //   9181: iload_2
    //   9182: ifeq -> 9093
    //   9185: iconst_0
    //   9186: istore #26
    //   9188: aload #16
    //   9190: iconst_0
    //   9191: iaload
    //   9192: istore #24
    //   9194: aload #16
    //   9196: iconst_1
    //   9197: iaload
    //   9198: istore #23
    //   9200: iload #24
    //   9202: iconst_4
    //   9203: iushr
    //   9204: iload #23
    //   9206: ixor
    //   9207: ldc 252645135
    //   9209: iand
    //   9210: istore #22
    //   9212: iload #23
    //   9214: iload #22
    //   9216: ixor
    //   9217: istore #23
    //   9219: iload #24
    //   9221: iload #22
    //   9223: iconst_4
    //   9224: ishl
    //   9225: ixor
    //   9226: istore #24
    //   9228: iload #24
    //   9230: bipush #16
    //   9232: iushr
    //   9233: iload #23
    //   9235: ixor
    //   9236: ldc 65535
    //   9238: iand
    //   9239: istore #22
    //   9241: iload #23
    //   9243: iload #22
    //   9245: ixor
    //   9246: istore #23
    //   9248: iload #24
    //   9250: iload #22
    //   9252: bipush #16
    //   9254: ishl
    //   9255: ixor
    //   9256: istore #24
    //   9258: iload #23
    //   9260: iconst_2
    //   9261: iushr
    //   9262: iload #24
    //   9264: ixor
    //   9265: ldc 858993459
    //   9267: iand
    //   9268: istore #22
    //   9270: iload #24
    //   9272: iload #22
    //   9274: ixor
    //   9275: istore #24
    //   9277: iload #23
    //   9279: iload #22
    //   9281: iconst_2
    //   9282: ishl
    //   9283: ixor
    //   9284: istore #23
    //   9286: iload #23
    //   9288: bipush #8
    //   9290: iushr
    //   9291: iload #24
    //   9293: ixor
    //   9294: ldc 16711935
    //   9296: iand
    //   9297: istore #22
    //   9299: iload #24
    //   9301: iload #22
    //   9303: ixor
    //   9304: istore #24
    //   9306: iload #23
    //   9308: iload #22
    //   9310: bipush #8
    //   9312: ishl
    //   9313: ixor
    //   9314: istore #23
    //   9316: iload #23
    //   9318: iconst_1
    //   9319: ishl
    //   9320: iload #23
    //   9322: bipush #31
    //   9324: iushr
    //   9325: iconst_1
    //   9326: iand
    //   9327: ior
    //   9328: istore #23
    //   9330: iload #24
    //   9332: iload #23
    //   9334: ixor
    //   9335: ldc -1431655766
    //   9337: iand
    //   9338: istore #22
    //   9340: iload #24
    //   9342: iload #22
    //   9344: ixor
    //   9345: istore #24
    //   9347: iload #23
    //   9349: iload #22
    //   9351: ixor
    //   9352: istore #23
    //   9354: iload #24
    //   9356: iconst_1
    //   9357: ishl
    //   9358: iload #24
    //   9360: bipush #31
    //   9362: iushr
    //   9363: iconst_1
    //   9364: iand
    //   9365: ior
    //   9366: istore #24
    //   9368: iconst_0
    //   9369: istore #25
    //   9371: iload #25
    //   9373: bipush #8
    //   9375: if_icmpge -> 9713
    //   9378: iload #23
    //   9380: bipush #28
    //   9382: ishl
    //   9383: iload #23
    //   9385: iconst_4
    //   9386: iushr
    //   9387: ior
    //   9388: istore #22
    //   9390: iload #22
    //   9392: aload #6
    //   9394: iload #26
    //   9396: iinc #26, 1
    //   9399: iaload
    //   9400: ixor
    //   9401: istore #22
    //   9403: aload #13
    //   9405: iload #22
    //   9407: bipush #63
    //   9409: iand
    //   9410: iaload
    //   9411: istore #21
    //   9413: iload #21
    //   9415: aload #11
    //   9417: iload #22
    //   9419: bipush #8
    //   9421: iushr
    //   9422: bipush #63
    //   9424: iand
    //   9425: iaload
    //   9426: ior
    //   9427: istore #21
    //   9429: iload #21
    //   9431: aload #9
    //   9433: iload #22
    //   9435: bipush #16
    //   9437: iushr
    //   9438: bipush #63
    //   9440: iand
    //   9441: iaload
    //   9442: ior
    //   9443: istore #21
    //   9445: iload #21
    //   9447: aload #7
    //   9449: iload #22
    //   9451: bipush #24
    //   9453: iushr
    //   9454: bipush #63
    //   9456: iand
    //   9457: iaload
    //   9458: ior
    //   9459: istore #21
    //   9461: iload #23
    //   9463: aload #6
    //   9465: iload #26
    //   9467: iinc #26, 1
    //   9470: iaload
    //   9471: ixor
    //   9472: istore #22
    //   9474: iload #21
    //   9476: aload #14
    //   9478: iload #22
    //   9480: bipush #63
    //   9482: iand
    //   9483: iaload
    //   9484: ior
    //   9485: istore #21
    //   9487: iload #21
    //   9489: aload #12
    //   9491: iload #22
    //   9493: bipush #8
    //   9495: iushr
    //   9496: bipush #63
    //   9498: iand
    //   9499: iaload
    //   9500: ior
    //   9501: istore #21
    //   9503: iload #21
    //   9505: aload #10
    //   9507: iload #22
    //   9509: bipush #16
    //   9511: iushr
    //   9512: bipush #63
    //   9514: iand
    //   9515: iaload
    //   9516: ior
    //   9517: istore #21
    //   9519: iload #21
    //   9521: aload #8
    //   9523: iload #22
    //   9525: bipush #24
    //   9527: iushr
    //   9528: bipush #63
    //   9530: iand
    //   9531: iaload
    //   9532: ior
    //   9533: istore #21
    //   9535: iload #24
    //   9537: iload #21
    //   9539: ixor
    //   9540: istore #24
    //   9542: iload #24
    //   9544: bipush #28
    //   9546: ishl
    //   9547: iload #24
    //   9549: iconst_4
    //   9550: iushr
    //   9551: ior
    //   9552: istore #22
    //   9554: iload #22
    //   9556: aload #6
    //   9558: iload #26
    //   9560: iinc #26, 1
    //   9563: iaload
    //   9564: ixor
    //   9565: istore #22
    //   9567: aload #13
    //   9569: iload #22
    //   9571: bipush #63
    //   9573: iand
    //   9574: iaload
    //   9575: istore #21
    //   9577: iload #21
    //   9579: aload #11
    //   9581: iload #22
    //   9583: bipush #8
    //   9585: iushr
    //   9586: bipush #63
    //   9588: iand
    //   9589: iaload
    //   9590: ior
    //   9591: istore #21
    //   9593: iload #21
    //   9595: aload #9
    //   9597: iload #22
    //   9599: bipush #16
    //   9601: iushr
    //   9602: bipush #63
    //   9604: iand
    //   9605: iaload
    //   9606: ior
    //   9607: istore #21
    //   9609: iload #21
    //   9611: aload #7
    //   9613: iload #22
    //   9615: bipush #24
    //   9617: iushr
    //   9618: bipush #63
    //   9620: iand
    //   9621: iaload
    //   9622: ior
    //   9623: istore #21
    //   9625: iload #24
    //   9627: aload #6
    //   9629: iload #26
    //   9631: iinc #26, 1
    //   9634: iaload
    //   9635: ixor
    //   9636: istore #22
    //   9638: iload #21
    //   9640: aload #14
    //   9642: iload #22
    //   9644: bipush #63
    //   9646: iand
    //   9647: iaload
    //   9648: ior
    //   9649: istore #21
    //   9651: iload #21
    //   9653: aload #12
    //   9655: iload #22
    //   9657: bipush #8
    //   9659: iushr
    //   9660: bipush #63
    //   9662: iand
    //   9663: iaload
    //   9664: ior
    //   9665: istore #21
    //   9667: iload #21
    //   9669: aload #10
    //   9671: iload #22
    //   9673: bipush #16
    //   9675: iushr
    //   9676: bipush #63
    //   9678: iand
    //   9679: iaload
    //   9680: ior
    //   9681: istore #21
    //   9683: iload #21
    //   9685: aload #8
    //   9687: iload #22
    //   9689: bipush #24
    //   9691: iushr
    //   9692: bipush #63
    //   9694: iand
    //   9695: iaload
    //   9696: ior
    //   9697: istore #21
    //   9699: iload #23
    //   9701: iload #21
    //   9703: ixor
    //   9704: istore #23
    //   9706: iinc #25, 1
    //   9709: iload_2
    //   9710: ifeq -> 9371
    //   9713: iload #23
    //   9715: bipush #31
    //   9717: ishl
    //   9718: iload #23
    //   9720: iconst_1
    //   9721: iushr
    //   9722: ior
    //   9723: istore #23
    //   9725: iload #24
    //   9727: iload #23
    //   9729: ixor
    //   9730: ldc -1431655766
    //   9732: iand
    //   9733: istore #22
    //   9735: iload #24
    //   9737: iload #22
    //   9739: ixor
    //   9740: istore #24
    //   9742: iload #23
    //   9744: iload #22
    //   9746: ixor
    //   9747: istore #23
    //   9749: iload #24
    //   9751: bipush #31
    //   9753: ishl
    //   9754: iload #24
    //   9756: iconst_1
    //   9757: iushr
    //   9758: ior
    //   9759: istore #24
    //   9761: iload #24
    //   9763: bipush #8
    //   9765: iushr
    //   9766: iload #23
    //   9768: ixor
    //   9769: ldc 16711935
    //   9771: iand
    //   9772: istore #22
    //   9774: iload #23
    //   9776: iload #22
    //   9778: ixor
    //   9779: istore #23
    //   9781: iload #24
    //   9783: iload #22
    //   9785: bipush #8
    //   9787: ishl
    //   9788: ixor
    //   9789: istore #24
    //   9791: iload #24
    //   9793: iconst_2
    //   9794: iushr
    //   9795: iload #23
    //   9797: ixor
    //   9798: ldc 858993459
    //   9800: iand
    //   9801: istore #22
    //   9803: iload #23
    //   9805: iload #22
    //   9807: ixor
    //   9808: istore #23
    //   9810: iload #24
    //   9812: iload #22
    //   9814: iconst_2
    //   9815: ishl
    //   9816: ixor
    //   9817: istore #24
    //   9819: iload #23
    //   9821: bipush #16
    //   9823: iushr
    //   9824: iload #24
    //   9826: ixor
    //   9827: ldc 65535
    //   9829: iand
    //   9830: istore #22
    //   9832: iload #24
    //   9834: iload #22
    //   9836: ixor
    //   9837: istore #24
    //   9839: iload #23
    //   9841: iload #22
    //   9843: bipush #16
    //   9845: ishl
    //   9846: ixor
    //   9847: istore #23
    //   9849: iload #23
    //   9851: iconst_4
    //   9852: iushr
    //   9853: iload #24
    //   9855: ixor
    //   9856: ldc 252645135
    //   9858: iand
    //   9859: istore #22
    //   9861: iload #24
    //   9863: iload #22
    //   9865: ixor
    //   9866: istore #24
    //   9868: iload #23
    //   9870: iload #22
    //   9872: iconst_4
    //   9873: ishl
    //   9874: ixor
    //   9875: istore #23
    //   9877: aload #16
    //   9879: iconst_0
    //   9880: iload #23
    //   9882: iastore
    //   9883: aload #16
    //   9885: iconst_1
    //   9886: iload #24
    //   9888: iastore
    //   9889: iload #19
    //   9891: bipush #8
    //   9893: imul
    //   9894: istore #27
    //   9896: iconst_0
    //   9897: istore #28
    //   9899: iload #28
    //   9901: iconst_2
    //   9902: if_icmpge -> 9991
    //   9905: aload #17
    //   9907: iload #27
    //   9909: iload #28
    //   9911: iconst_4
    //   9912: imul
    //   9913: iadd
    //   9914: aload #16
    //   9916: iload #28
    //   9918: iaload
    //   9919: bipush #24
    //   9921: iushr
    //   9922: i2b
    //   9923: bastore
    //   9924: aload #17
    //   9926: iload #27
    //   9928: iload #28
    //   9930: iconst_4
    //   9931: imul
    //   9932: iadd
    //   9933: iconst_1
    //   9934: iadd
    //   9935: aload #16
    //   9937: iload #28
    //   9939: iaload
    //   9940: bipush #16
    //   9942: iushr
    //   9943: i2b
    //   9944: bastore
    //   9945: aload #17
    //   9947: iload #27
    //   9949: iload #28
    //   9951: iconst_4
    //   9952: imul
    //   9953: iadd
    //   9954: iconst_2
    //   9955: iadd
    //   9956: aload #16
    //   9958: iload #28
    //   9960: iaload
    //   9961: bipush #8
    //   9963: iushr
    //   9964: i2b
    //   9965: bastore
    //   9966: aload #17
    //   9968: iload #27
    //   9970: iload #28
    //   9972: iconst_4
    //   9973: imul
    //   9974: iadd
    //   9975: iconst_3
    //   9976: iadd
    //   9977: aload #16
    //   9979: iload #28
    //   9981: iaload
    //   9982: i2b
    //   9983: bastore
    //   9984: iinc #28, 1
    //   9987: iload_2
    //   9988: ifeq -> 9899
    //   9991: iinc #19, 1
    //   9994: iload_2
    //   9995: ifeq -> 9076
    //   9998: aload #17
    //   10000: aload #17
    //   10002: arraylength
    //   10003: iconst_1
    //   10004: isub
    //   10005: baload
    //   10006: istore #19
    //   10008: aload #17
    //   10010: arraylength
    //   10011: iload #19
    //   10013: isub
    //   10014: newarray byte
    //   10016: astore #5
    //   10018: aload #17
    //   10020: arraylength
    //   10021: aload #5
    //   10023: arraylength
    //   10024: if_icmpge -> 10048
    //   10027: new java/lang/Exception
    //   10030: dup
    //   10031: sipush #-20542
    //   10034: sipush #-9604
    //   10037: invokestatic a : (II)Ljava/lang/String;
    //   10040: invokespecial <init> : (Ljava/lang/String;)V
    //   10043: athrow
    //   10044: invokestatic a : (Ljava/lang/Throwable;)Ljava/lang/Throwable;
    //   10047: athrow
    //   10048: iconst_0
    //   10049: istore #20
    //   10051: iload #20
    //   10053: aload #5
    //   10055: arraylength
    //   10056: if_icmpge -> 10076
    //   10059: aload #5
    //   10061: iload #20
    //   10063: aload #17
    //   10065: iload #20
    //   10067: baload
    //   10068: bastore
    //   10069: iinc #20, 1
    //   10072: iload_2
    //   10073: ifeq -> 10051
    //   10076: new java/math/BigInteger
    //   10079: dup
    //   10080: aload #5
    //   10082: invokespecial <init> : ([B)V
    //   10085: invokevirtual abs : ()Ljava/math/BigInteger;
    //   10088: putstatic burp/Zbze.ZM : Ljava/lang/Object;
    //   10091: sipush #-20535
    //   10094: sipush #-9848
    //   10097: invokestatic a : (II)Ljava/lang/String;
    //   10100: iconst_1
    //   10101: ldc burp/Ztip
    //   10103: invokevirtual getClassLoader : ()Ljava/lang/ClassLoader;
    //   10106: invokestatic forName : (Ljava/lang/String;ZLjava/lang/ClassLoader;)Ljava/lang/Class;
    //   10109: invokevirtual getDeclaredFields : ()[Ljava/lang/reflect/Field;
    //   10112: astore #4
    //   10114: aload #4
    //   10116: arraylength
    //   10117: istore #5
    //   10119: iconst_0
    //   10120: istore #6
    //   10122: iload #6
    //   10124: iload #5
    //   10126: if_icmpge -> 10264
    //   10129: aload #4
    //   10131: iload #6
    //   10133: aaload
    //   10134: astore #7
    //   10136: aload #7
    //   10138: invokevirtual getModifiers : ()I
    //   10141: invokestatic isStatic : (I)Z
    //   10144: ifne -> 10154
    //   10147: goto -> 10257
    //   10150: invokestatic a : (Ljava/lang/Throwable;)Ljava/lang/Throwable;
    //   10153: athrow
    //   10154: aload #7
    //   10156: invokevirtual getType : ()Ljava/lang/Class;
    //   10159: astore #8
    //   10161: aload #8
    //   10163: ifnull -> 10244
    //   10166: aload #8
    //   10168: invokevirtual isPrimitive : ()Z
    //   10171: ifne -> 10244
    //   10174: goto -> 10181
    //   10177: invokestatic a : (Ljava/lang/Throwable;)Ljava/lang/Throwable;
    //   10180: athrow
    //   10181: aload #8
    //   10183: invokevirtual getPackage : ()Ljava/lang/Package;
    //   10186: ifnull -> 10244
    //   10189: goto -> 10196
    //   10192: invokestatic a : (Ljava/lang/Throwable;)Ljava/lang/Throwable;
    //   10195: athrow
    //   10196: aload #8
    //   10198: invokevirtual getPackage : ()Ljava/lang/Package;
    //   10201: invokevirtual getName : ()Ljava/lang/String;
    //   10204: ifnull -> 10244
    //   10207: goto -> 10214
    //   10210: invokestatic a : (Ljava/lang/Throwable;)Ljava/lang/Throwable;
    //   10213: athrow
    //   10214: aload #8
    //   10216: invokevirtual getPackage : ()Ljava/lang/Package;
    //   10219: invokevirtual getName : ()Ljava/lang/String;
    //   10222: sipush #-20532
    //   10225: sipush #-29824
    //   10228: invokestatic a : (II)Ljava/lang/String;
    //   10231: invokevirtual startsWith : (Ljava/lang/String;)Z
    //   10234: ifne -> 10244
    //   10237: goto -> 10244
    //   10240: invokestatic a : (Ljava/lang/Throwable;)Ljava/lang/Throwable;
    //   10243: athrow
    //   10244: aload #7
    //   10246: iconst_1
    //   10247: invokevirtual setAccessible : (Z)V
    //   10250: aload #7
    //   10252: aconst_null
    //   10253: invokevirtual get : (Ljava/lang/Object;)Ljava/lang/Object;
    //   10256: pop
    //   10257: iinc #6, 1
    //   10260: iload_2
    //   10261: ifeq -> 10122
    //   10264: sipush #-20536
    //   10267: sipush #2423
    //   10270: invokestatic a : (II)Ljava/lang/String;
    //   10273: invokestatic forName : (Ljava/lang/String;)Ljava/lang/Class;
    //   10276: invokevirtual getDeclaredMethods : ()[Ljava/lang/reflect/Method;
    //   10279: astore #4
    //   10281: aload #4
    //   10283: arraylength
    //   10284: istore #5
    //   10286: iconst_0
    //   10287: istore #6
    //   10289: iload #6
    //   10291: iload #5
    //   10293: if_icmpge -> 10426
    //   10296: aload #4
    //   10298: iload #6
    //   10300: aaload
    //   10301: astore #7
    //   10303: aload #7
    //   10305: invokevirtual getParameterTypes : ()[Ljava/lang/Class;
    //   10308: pop
    //   10309: aload #7
    //   10311: invokevirtual getModifiers : ()I
    //   10314: invokestatic isStatic : (I)Z
    //   10317: ifeq -> 10412
    //   10320: aload #7
    //   10322: invokevirtual getParameterTypes : ()[Ljava/lang/Class;
    //   10325: arraylength
    //   10326: iconst_2
    //   10327: if_icmpne -> 10412
    //   10330: goto -> 10337
    //   10333: invokestatic a : (Ljava/lang/Throwable;)Ljava/lang/Throwable;
    //   10336: athrow
    //   10337: aload #7
    //   10339: invokevirtual getReturnType : ()Ljava/lang/Class;
    //   10342: getstatic java/lang/Void.TYPE : Ljava/lang/Class;
    //   10345: invokevirtual equals : (Ljava/lang/Object;)Z
    //   10348: ifeq -> 10412
    //   10351: goto -> 10358
    //   10354: invokestatic a : (Ljava/lang/Throwable;)Ljava/lang/Throwable;
    //   10357: athrow
    //   10358: aload #7
    //   10360: iconst_1
    //   10361: invokevirtual setAccessible : (Z)V
    //   10364: aload #7
    //   10366: aconst_null
    //   10367: iconst_2
    //   10368: anewarray java/lang/Object
    //   10371: dup
    //   10372: iconst_0
    //   10373: aload_0
    //   10374: aastore
    //   10375: dup
    //   10376: iconst_1
    //   10377: aload_1
    //   10378: ifnonnull -> 10396
    //   10381: goto -> 10388
    //   10384: invokestatic a : (Ljava/lang/Throwable;)Ljava/lang/Throwable;
    //   10387: athrow
    //   10388: aload_1
    //   10389: goto -> 10403
    //   10392: invokestatic a : (Ljava/lang/Throwable;)Ljava/lang/Throwable;
    //   10395: athrow
    //   10396: aload_1
    //   10397: checkcast [B
    //   10400: invokevirtual clone : ()Ljava/lang/Object;
    //   10403: aastore
    //   10404: invokevirtual invoke : (Ljava/lang/Object;[Ljava/lang/Object;)Ljava/lang/Object;
    //   10407: pop
    //   10408: iload_2
    //   10409: ifeq -> 10426
    //   10412: iinc #6, 1
    //   10415: iload_2
    //   10416: ifeq -> 10289
    //   10419: goto -> 10426
    //   10422: invokestatic a : (Ljava/lang/Throwable;)Ljava/lang/Throwable;
    //   10425: athrow
    //   10426: getstatic burp/Zz41.Zc : Ljava/lang/String;
    //   10429: getstatic burp/Zedq.Zy : Ljava/lang/Object;
    //   10432: checkcast java/math/BigInteger
    //   10435: invokevirtual intValue : ()I
    //   10438: bipush #32
    //   10440: irem
    //   10441: invokestatic abs : (I)I
    //   10444: invokevirtual charAt : (I)C
    //   10447: getstatic burp/Zr02.ZG : Ljava/lang/String;
    //   10450: getstatic burp/Zm_u.Zf : Ljava/lang/Object;
    //   10453: checkcast java/math/BigInteger
    //   10456: invokevirtual intValue : ()I
    //   10459: bipush #32
    //   10461: irem
    //   10462: invokestatic abs : (I)I
    //   10465: invokevirtual charAt : (I)C
    //   10468: if_icmpgt -> 10575
    //   10471: getstatic burp/Zmf2.ZK : Ljava/lang/String;
    //   10474: getstatic burp/Ztbn.ZA : Ljava/lang/Object;
    //   10477: checkcast java/math/BigInteger
    //   10480: invokevirtual intValue : ()I
    //   10483: bipush #32
    //   10485: irem
    //   10486: invokestatic abs : (I)I
    //   10489: invokevirtual charAt : (I)C
    //   10492: getstatic burp/Zg2u.Zy : Ljava/lang/String;
    //   10495: getstatic burp/Zrkd.ZO : Ljava/lang/Object;
    //   10498: checkcast java/math/BigInteger
    //   10501: invokevirtual intValue : ()I
    //   10504: bipush #32
    //   10506: irem
    //   10507: invokestatic abs : (I)I
    //   10510: invokevirtual charAt : (I)C
    //   10513: if_icmpgt -> 10575
    //   10516: goto -> 10523
    //   10519: invokestatic a : (Ljava/lang/Throwable;)Ljava/lang/Throwable;
    //   10522: athrow
    //   10523: getstatic burp/Zxd1.ZQ : Ljava/lang/String;
    //   10526: getstatic burp/Zl7b.ZK : Ljava/lang/Object;
    //   10529: checkcast java/math/BigInteger
    //   10532: invokevirtual intValue : ()I
    //   10535: bipush #32
    //   10537: irem
    //   10538: invokestatic abs : (I)I
    //   10541: invokevirtual charAt : (I)C
    //   10544: getstatic burp/Zlxw.ZC : Ljava/lang/String;
    //   10547: getstatic burp/Zql.Zt : Ljava/lang/Object;
    //   10550: checkcast java/math/BigInteger
    //   10553: invokevirtual intValue : ()I
    //   10556: bipush #32
    //   10558: irem
    //   10559: invokestatic abs : (I)I
    //   10562: invokevirtual charAt : (I)C
    //   10565: if_icmple -> 10583
    //   10568: goto -> 10575
    //   10571: invokestatic a : (Ljava/lang/Throwable;)Ljava/lang/Throwable;
    //   10574: athrow
    //   10575: iconst_1
    //   10576: goto -> 10584
    //   10579: invokestatic a : (Ljava/lang/Throwable;)Ljava/lang/Throwable;
    //   10582: athrow
    //   10583: iconst_0
    //   10584: ireturn
    //   10585: astore_3
    //   10586: new java/lang/Exception
    //   10589: dup
    //   10590: aload_3
    //   10591: invokevirtual getMessage : ()Ljava/lang/String;
    //   10594: invokespecial <init> : (Ljava/lang/String;)V
    //   10597: athrow
    // Exception table:
    //   from	to	target	type
    //   4	10584	10585	java/lang/Throwable
    //   3306	3331	3331	java/lang/Throwable
    //   4294	4320	4320	java/lang/Throwable
    //   4385	4558	4561	java/lang/Throwable
    //   4528	4595	4598	java/lang/Throwable
    //   4565	4632	4635	java/lang/Throwable
    //   4602	4669	4672	java/lang/Throwable
    //   4639	4706	4709	java/lang/Throwable
    //   4676	4743	4746	java/lang/Throwable
    //   4713	4780	4783	java/lang/Throwable
    //   4750	4817	4820	java/lang/Throwable
    //   4787	4854	4857	java/lang/Throwable
    //   4824	4891	4894	java/lang/Throwable
    //   4861	4928	4931	java/lang/Throwable
    //   4898	4965	4968	java/lang/Throwable
    //   4935	5002	5005	java/lang/Throwable
    //   4972	5039	5042	java/lang/Throwable
    //   5009	5076	5079	java/lang/Throwable
    //   5046	5113	5116	java/lang/Throwable
    //   5083	5150	5153	java/lang/Throwable
    //   5120	5187	5190	java/lang/Throwable
    //   5157	5224	5227	java/lang/Throwable
    //   5194	5261	5264	java/lang/Throwable
    //   5231	5298	5301	java/lang/Throwable
    //   5268	5335	5338	java/lang/Throwable
    //   5305	5372	5375	java/lang/Throwable
    //   5342	5409	5412	java/lang/Throwable
    //   5379	5446	5449	java/lang/Throwable
    //   5416	5483	5486	java/lang/Throwable
    //   5453	5520	5523	java/lang/Throwable
    //   5490	5557	5560	java/lang/Throwable
    //   5527	5594	5597	java/lang/Throwable
    //   5564	5631	5634	java/lang/Throwable
    //   5601	5668	5671	java/lang/Throwable
    //   5638	5701	5704	java/lang/Throwable
    //   9026	9051	9051	java/lang/Throwable
    //   10018	10044	10044	java/lang/Throwable
    //   10136	10150	10150	java/lang/Throwable
    //   10161	10174	10177	java/lang/Throwable
    //   10166	10189	10192	java/lang/Throwable
    //   10181	10207	10210	java/lang/Throwable
    //   10196	10237	10240	java/lang/Throwable
    //   10303	10330	10333	java/lang/Throwable
    //   10320	10351	10354	java/lang/Throwable
    //   10337	10381	10384	java/lang/Throwable
    //   10358	10392	10392	java/lang/Throwable
    //   10403	10419	10422	java/lang/Throwable
    //   10426	10516	10519	java/lang/Throwable
    //   10471	10568	10571	java/lang/Throwable
    //   10523	10579	10579	java/lang/Throwable
  }
  
  static {
    // Byte code:
    //   0: bipush #10
    //   2: anewarray java/lang/String
    //   5: astore #5
    //   7: iconst_0
    //   8: istore_3
    //   9: ldc '%1 ?B7\\r4t>R\\t9<\\t\\tu\\t\\r\\t.2rX[CSDysbMd}j@LtD5\\b_ \\ft91g2>\zd'_-ubLq]~RV^ \\fV'
    //   11: dup
    //   12: astore_2
    //   13: invokevirtual length : ()I
    //   16: istore #4
    //   18: bipush #32
    //   20: istore_1
    //   21: iconst_m1
    //   22: istore_0
    //   23: bipush #23
    //   25: iinc #0, 1
    //   28: aload_2
    //   29: iload_0
    //   30: dup
    //   31: iload_1
    //   32: iadd
    //   33: invokevirtual substring : (II)Ljava/lang/String;
    //   36: iconst_m1
    //   37: goto -> 143
    //   40: aload #5
    //   42: swap
    //   43: iload_3
    //   44: iinc #3, 1
    //   47: swap
    //   48: aastore
    //   49: iload_0
    //   50: iload_1
    //   51: iadd
    //   52: dup
    //   53: istore_0
    //   54: iload #4
    //   56: if_icmpge -> 68
    //   59: aload_2
    //   60: iload_0
    //   61: invokevirtual charAt : (I)C
    //   64: istore_1
    //   65: goto -> 23
    //   68: ldc '*oLfvo B2=@HR8s\\nwoz>It{~'
    //   70: dup
    //   71: astore_2
    //   72: invokevirtual length : ()I
    //   75: istore #4
    //   77: bipush #19
    //   79: istore_1
    //   80: iconst_m1
    //   81: istore_0
    //   82: bipush #25
    //   84: iinc #0, 1
    //   87: aload_2
    //   88: iload_0
    //   89: dup
    //   90: iload_1
    //   91: iadd
    //   92: invokevirtual substring : (II)Ljava/lang/String;
    //   95: iconst_0
    //   96: goto -> 143
    //   99: aload #5
    //   101: swap
    //   102: iload_3
    //   103: iinc #3, 1
    //   106: swap
    //   107: aastore
    //   108: iload_0
    //   109: iload_1
    //   110: iadd
    //   111: dup
    //   112: istore_0
    //   113: iload #4
    //   115: if_icmpge -> 127
    //   118: aload_2
    //   119: iload_0
    //   120: invokevirtual charAt : (I)C
    //   123: istore_1
    //   124: goto -> 82
    //   127: aload #5
    //   129: putstatic burp/Zsbo.a : [Ljava/lang/String;
    //   132: bipush #10
    //   134: anewarray java/lang/String
    //   137: putstatic burp/Zsbo.b : [Ljava/lang/String;
    //   140: goto -> 300
    //   143: dup_x2
    //   144: pop
    //   145: invokevirtual toCharArray : ()[C
    //   148: dup_x1
    //   149: arraylength
    //   150: dup_x2
    //   151: pop
    //   152: iconst_0
    //   153: istore #6
    //   155: dup2_x1
    //   156: pop2
    //   157: dup_x2
    //   158: iconst_1
    //   159: if_icmpgt -> 259
    //   162: dup2
    //   163: swap
    //   164: iload #6
    //   166: dup2_x1
    //   167: caload
    //   168: swap
    //   169: iload #6
    //   171: bipush #7
    //   173: irem
    //   174: tableswitch default -> 241, 0 -> 212, 1 -> 217, 2 -> 222, 3 -> 226, 4 -> 231, 5 -> 236
    //   212: bipush #57
    //   214: goto -> 243
    //   217: bipush #21
    //   219: goto -> 243
    //   222: iconst_1
    //   223: goto -> 243
    //   226: bipush #109
    //   228: goto -> 243
    //   231: bipush #104
    //   233: goto -> 243
    //   236: bipush #41
    //   238: goto -> 243
    //   241: bipush #76
    //   243: ixor
    //   244: ixor
    //   245: i2c
    //   246: castore
    //   247: iinc #6, 1
    //   250: dup
    //   251: ifne -> 259
    //   254: dup2
    //   255: dup_x1
    //   256: goto -> 166
    //   259: dup2_x1
    //   260: pop2
    //   261: dup_x2
    //   262: iload #6
    //   264: if_icmpgt -> 162
    //   267: pop
    //   268: new java/lang/String
    //   271: dup_x1
    //   272: swap
    //   273: invokespecial <init> : ([C)V
    //   276: invokevirtual intern : ()Ljava/lang/String;
    //   279: swap
    //   280: pop
    //   281: swap
    //   282: tableswitch default -> 40, 0 -> 99
    //   300: new java/math/BigInteger
    //   303: dup
    //   304: iconst_1
    //   305: bipush #32
    //   307: newarray byte
    //   309: dup
    //   310: iconst_0
    //   311: bipush #112
    //   313: bastore
    //   314: dup
    //   315: iconst_1
    //   316: bipush #-6
    //   318: bastore
    //   319: dup
    //   320: iconst_2
    //   321: bipush #-74
    //   323: bastore
    //   324: dup
    //   325: iconst_3
    //   326: bipush #-114
    //   328: bastore
    //   329: dup
    //   330: iconst_4
    //   331: bipush #-41
    //   333: bastore
    //   334: dup
    //   335: iconst_5
    //   336: bipush #119
    //   338: bastore
    //   339: dup
    //   340: bipush #6
    //   342: bipush #79
    //   344: bastore
    //   345: dup
    //   346: bipush #7
    //   348: bipush #-47
    //   350: bastore
    //   351: dup
    //   352: bipush #8
    //   354: iconst_5
    //   355: bastore
    //   356: dup
    //   357: bipush #9
    //   359: bipush #-24
    //   361: bastore
    //   362: dup
    //   363: bipush #10
    //   365: bipush #87
    //   367: bastore
    //   368: dup
    //   369: bipush #11
    //   371: bipush #-114
    //   373: bastore
    //   374: dup
    //   375: bipush #12
    //   377: bipush #106
    //   379: bastore
    //   380: dup
    //   381: bipush #13
    //   383: bipush #42
    //   385: bastore
    //   386: dup
    //   387: bipush #14
    //   389: bipush #83
    //   391: bastore
    //   392: dup
    //   393: bipush #15
    //   395: bipush #-121
    //   397: bastore
    //   398: dup
    //   399: bipush #16
    //   401: bipush #-36
    //   403: bastore
    //   404: dup
    //   405: bipush #17
    //   407: bipush #-119
    //   409: bastore
    //   410: dup
    //   411: bipush #18
    //   413: bipush #-33
    //   415: bastore
    //   416: dup
    //   417: bipush #19
    //   419: bipush #-82
    //   421: bastore
    //   422: dup
    //   423: bipush #20
    //   425: bipush #117
    //   427: bastore
    //   428: dup
    //   429: bipush #21
    //   431: bipush #-40
    //   433: bastore
    //   434: dup
    //   435: bipush #22
    //   437: bipush #-73
    //   439: bastore
    //   440: dup
    //   441: bipush #23
    //   443: bipush #7
    //   445: bastore
    //   446: dup
    //   447: bipush #24
    //   449: bipush #-77
    //   451: bastore
    //   452: dup
    //   453: bipush #25
    //   455: bipush #109
    //   457: bastore
    //   458: dup
    //   459: bipush #26
    //   461: bipush #117
    //   463: bastore
    //   464: dup
    //   465: bipush #27
    //   467: bipush #83
    //   469: bastore
    //   470: dup
    //   471: bipush #28
    //   473: bipush #-84
    //   475: bastore
    //   476: dup
    //   477: bipush #29
    //   479: bipush #51
    //   481: bastore
    //   482: dup
    //   483: bipush #30
    //   485: bipush #17
    //   487: bastore
    //   488: dup
    //   489: bipush #31
    //   491: bipush #-70
    //   493: bastore
    //   494: invokespecial <init> : (I[B)V
    //   497: putstatic burp/Zsbo.ZG : Ljava/lang/Object;
    //   500: sipush #-20534
    //   503: sipush #20487
    //   506: invokestatic a : (II)Ljava/lang/String;
    //   509: putstatic burp/Zsbo.Zg : Ljava/lang/String;
    //   512: return
  }
  
  private static Throwable a(Throwable paramThrowable) {
    return paramThrowable;
  }
  
  private static String a(int paramInt1, int paramInt2) {
    int i = (paramInt1 ^ 0xFFFFAFCA) & 0xFFFF;
    if (b[i] == null) {
      char[] arrayOfChar = a[i].toCharArray();
      switch (arrayOfChar[0] & 0xFF) {
        case 0:
        
        case 1:
        
        case 2:
        
        case 3:
        
        case 4:
        
        case 5:
        
        case 6:
        
        case 7:
        
        case 8:
        
        case 9:
        
        case 10:
        
        case 11:
        
        case 12:
        
        case 13:
        
        case 14:
        
        case 15:
        
        case 16:
        
        case 17:
        
        case 18:
        
        case 19:
        
        case 20:
        
        case 21:
        
        case 22:
        
        case 23:
        
        case 24:
        
        case 25:
        
        case 26:
        
        case 27:
        
        case 28:
        
        case 29:
        
        case 30:
        
        case 31:
        
        case 32:
        
        case 33:
        
        case 34:
        
        case 35:
        
        case 36:
        
        case 37:
        
        case 38:
        
        case 39:
        
        case 40:
        
        case 41:
        
        case 42:
        
        case 43:
        
        case 44:
        
        case 45:
        
        case 46:
        
        case 47:
        
        case 48:
        
        case 49:
        
        case 50:
        
        case 51:
        
        case 52:
        
        case 53:
        
        case 54:
        
        case 55:
        
        case 56:
        
        case 57:
        
        case 58:
        
        case 59:
        
        case 60:
        
        case 61:
        
        case 62:
        
        case 63:
        
        case 64:
        
        case 65:
        
        case 66:
        
        case 67:
        
        case 68:
        
        case 69:
        
        case 70:
        
        case 71:
        
        case 72:
        
        case 73:
        
        case 74:
        
        case 75:
        
        case 76:
        
        case 77:
        
        case 78:
        
        case 79:
        
        case 80:
        
        case 81:
        
        case 82:
        
        case 83:
        
        case 84:
        
        case 85:
        
        case 86:
        
        case 87:
        
        case 88:
        
        case 89:
        
        case 90:
        
        case 91:
        
        case 92:
        
        case 93:
        
        case 94:
        
        case 95:
        
        case 96:
        
        case 97:
        
        case 98:
        
        case 99:
        
        case 100:
        
        case 101:
        
        case 102:
        
        case 103:
        
        case 104:
        
        case 105:
        
        case 106:
        
        case 107:
        
        case 108:
        
        case 109:
        
        case 110:
        
        case 111:
        
        case 112:
        
        case 113:
        
        case 114:
        
        case 115:
        
        case 116:
        
        case 117:
        
        case 118:
        
        case 119:
        
        case 120:
        
        case 121:
        
        case 122:
        
        case 123:
        
        case 124:
        
        case 125:
        
        case 126:
        
        case 127:
        
        case 128:
        
        case 129:
        
        case 130:
        
        case 131:
        
        case 132:
        
        case 133:
        
        case 134:
        
        case 135:
        
        case 136:
        
        case 137:
        
        case 138:
        
        case 139:
        
        case 140:
        
        case 141:
        
        case 142:
        
        case 143:
        
        case 144:
        
        case 145:
        
        case 146:
        
        case 147:
        
        case 148:
        
        case 149:
        
        case 150:
        
        case 151:
        
        case 152:
        
        case 153:
        
        case 154:
        
        case 155:
        
        case 156:
        
        case 157:
        
        case 158:
        
        case 159:
        
        case 160:
        
        case 161:
        
        case 162:
        
        case 163:
        
        case 164:
        
        case 165:
        
        case 166:
        
        case 167:
        
        case 168:
        
        case 169:
        
        case 170:
        
        case 171:
        
        case 172:
        
        case 173:
        
        case 174:
        
        case 175:
        
        case 176:
        
        case 177:
        
        case 178:
        
        case 179:
        
        case 180:
        
        case 181:
        
        case 182:
        
        case 183:
        
        case 184:
        
        case 185:
        
        case 186:
        
        case 187:
        
        case 188:
        
        case 189:
        
        case 190:
        
        case 191:
        
        case 192:
        
        case 193:
        
        case 194:
        
        case 195:
        
        case 196:
        
        case 197:
        
        case 198:
        
        case 199:
        
        case 200:
        
        case 201:
        
        case 202:
        
        case 203:
        
        case 204:
        
        case 205:
        
        case 206:
        
        case 207:
        
        case 208:
        
        case 209:
        
        case 210:
        
        case 211:
        
        case 212:
        
        case 213:
        
        case 214:
        
        case 215:
        
        case 216:
        
        case 217:
        
        case 218:
        
        case 219:
        
        case 220:
        
        case 221:
        
        case 222:
        
        case 223:
        
        case 224:
        
        case 225:
        
        case 226:
        
        case 227:
        
        case 228:
        
        case 229:
        
        case 230:
        
        case 231:
        
        case 232:
        
        case 233:
        
        case 234:
        
        case 235:
        
        case 236:
        
        case 237:
        
        case 238:
        
        case 239:
        
        case 240:
        
        case 241:
        
        case 242:
        
        case 243:
        
        case 244:
        
        case 245:
        
        case 246:
        
        case 247:
        
        case 248:
        
        case 249:
        
        case 250:
        
        case 251:
        
        case 252:
        
        case 253:
        
        case 254:
        
        default:
          break;
      } 
      char c = '';
      int j = (paramInt2 & 0xFF) - c;
      if (j < 0)
        j += 256; 
      int k = ((paramInt2 & 0xFFFF) >>> 8) - c;
      if (k < 0)
        k += 256; 
      for (byte b = 0; b < arrayOfChar.length; b++) {
        int m = b % 2;
        if (m == 0) {
          arrayOfChar[b] = (char)(arrayOfChar[b] ^ j);
          j = ((j >>> 3 | j << 5) ^ arrayOfChar[b]) & 0xFF;
        } else {
          arrayOfChar[b] = (char)(arrayOfChar[b] ^ k);
          k = ((k >>> 3 | k << 5) ^ arrayOfChar[b]) & 0xFF;
        } 
      } 
      b[i] = (new String(arrayOfChar)).intern();
    } 
    return b[i];
  }
}


/* Location:              C:\Program Files\BurpSuitePro\burpsuite_pro.jar!\burp\Zsbo.class
 * Java compiler version: 21 (65.0)
 * JD-Core Version:       1.1.3
 */