package burp;

import java.util.List;

public class Zsd2 implements Zrsu {
  private final List<Zrsu> Zl;
  
  Zsd2(Zrsu... paramVarArgs) {
    this.Zl = Zb99.Zh(paramVarArgs);
  }
  
  public void ZL(Ze3n paramZe3n, Zlkb paramZlkb, Zb6q paramZb6q, Zz4_ paramZz4_) {
    // Byte code:
    //   0: aload_0
    //   1: getfield Zl : Ljava/util/List;
    //   4: aload_1
    //   5: aload_2
    //   6: aload_3
    //   7: aload #4
    //   9: <illegal opcode> accept : (Lburp/Ze3n;Lburp/Zlkb;Lburp/Zb6q;Lburp/Zz4_;)Ljava/util/function/Consumer;
    //   14: invokeinterface forEach : (Ljava/util/function/Consumer;)V
    //   19: return
  }
  
  private static void lambda$report$0(Ze3n paramZe3n, Zlkb paramZlkb, Zb6q paramZb6q, Zz4_ paramZz4_, Zrsu paramZrsu) {
    paramZrsu.ZL(paramZe3n, paramZlkb, paramZb6q, paramZz4_);
  }
}


/* Location:              C:\Program Files\BurpSuitePro\burpsuite_pro.jar!\burp\Zsd2.class
 * Java compiler version: 21 (65.0)
 * JD-Core Version:       1.1.3
 */