package burp;

import java.math.BigInteger;

class Zsde extends ClassLoader {
  static String Zi;
  
  static Object Zx;
  
  private static final String[] a;
  
  private static final String[] b;
  
  static boolean Zf(Object[] paramArrayOfObject, Object paramObject) throws Throwable {
    // Byte code:
    //   0: invokestatic ZK : ()Z
    //   3: istore_2
    //   4: ldc2_w 8682522807148012
    //   7: invokestatic currentTimeMillis : ()J
    //   10: lxor
    //   11: lstore #4
    //   13: lload #4
    //   15: ldc2_w 25214903917
    //   18: lmul
    //   19: ldc2_w 11
    //   22: ladd
    //   23: ldc2_w 281474976710655
    //   26: land
    //   27: lstore #4
    //   29: lload #4
    //   31: bipush #32
    //   33: lshl
    //   34: lstore #6
    //   36: lload #4
    //   38: ldc2_w 25214903917
    //   41: lmul
    //   42: ldc2_w 11
    //   45: ladd
    //   46: ldc2_w 281474976710655
    //   49: land
    //   50: lstore #4
    //   52: lload #6
    //   54: lload #4
    //   56: ladd
    //   57: lstore #6
    //   59: bipush #16
    //   61: newarray byte
    //   63: dup
    //   64: iconst_0
    //   65: bipush #48
    //   67: bastore
    //   68: dup
    //   69: iconst_1
    //   70: bipush #49
    //   72: bastore
    //   73: dup
    //   74: iconst_2
    //   75: bipush #50
    //   77: bastore
    //   78: dup
    //   79: iconst_3
    //   80: bipush #51
    //   82: bastore
    //   83: dup
    //   84: iconst_4
    //   85: bipush #52
    //   87: bastore
    //   88: dup
    //   89: iconst_5
    //   90: bipush #53
    //   92: bastore
    //   93: dup
    //   94: bipush #6
    //   96: bipush #54
    //   98: bastore
    //   99: dup
    //   100: bipush #7
    //   102: bipush #55
    //   104: bastore
    //   105: dup
    //   106: bipush #8
    //   108: bipush #56
    //   110: bastore
    //   111: dup
    //   112: bipush #9
    //   114: bipush #57
    //   116: bastore
    //   117: dup
    //   118: bipush #10
    //   120: bipush #97
    //   122: bastore
    //   123: dup
    //   124: bipush #11
    //   126: bipush #98
    //   128: bastore
    //   129: dup
    //   130: bipush #12
    //   132: bipush #99
    //   134: bastore
    //   135: dup
    //   136: bipush #13
    //   138: bipush #100
    //   140: bastore
    //   141: dup
    //   142: bipush #14
    //   144: bipush #101
    //   146: bastore
    //   147: dup
    //   148: bipush #15
    //   150: bipush #102
    //   152: bastore
    //   153: astore #8
    //   155: bipush #64
    //   157: newarray byte
    //   159: astore #9
    //   161: bipush #64
    //   163: istore #10
    //   165: bipush #16
    //   167: istore #11
    //   169: iload #11
    //   171: iconst_1
    //   172: isub
    //   173: i2l
    //   174: lstore #12
    //   176: aload #9
    //   178: iinc #10, -1
    //   181: iload #10
    //   183: aload #8
    //   185: lload #6
    //   187: lload #12
    //   189: land
    //   190: l2i
    //   191: baload
    //   192: bastore
    //   193: lload #6
    //   195: iconst_4
    //   196: lushr
    //   197: lstore #6
    //   199: lload #6
    //   201: lconst_0
    //   202: lcmp
    //   203: ifne -> 176
    //   206: bipush #64
    //   208: iload #10
    //   210: isub
    //   211: newarray byte
    //   213: astore_3
    //   214: iconst_0
    //   215: istore #14
    //   217: iload #14
    //   219: aload_3
    //   220: arraylength
    //   221: if_icmpge -> 243
    //   224: aload_3
    //   225: iload #14
    //   227: aload #9
    //   229: iload #10
    //   231: iload #14
    //   233: iadd
    //   234: baload
    //   235: bastore
    //   236: iinc #14, 1
    //   239: iload_2
    //   240: ifeq -> 217
    //   243: aload_3
    //   244: arraylength
    //   245: bipush #10
    //   247: if_icmplt -> 13
    //   250: new java/io/ByteArrayOutputStream
    //   253: dup
    //   254: invokespecial <init> : ()V
    //   257: astore_3
    //   258: getstatic burp/Zk9s.ZM : Ljava/lang/String;
    //   261: astore #4
    //   263: iconst_0
    //   264: istore #5
    //   266: iload #5
    //   268: aload #4
    //   270: invokevirtual length : ()I
    //   273: if_icmpge -> 303
    //   276: aload_3
    //   277: aload #4
    //   279: iload #5
    //   281: iload #5
    //   283: iconst_2
    //   284: iadd
    //   285: invokevirtual substring : (II)Ljava/lang/String;
    //   288: bipush #16
    //   290: invokestatic parseInt : (Ljava/lang/String;I)I
    //   293: invokevirtual write : (I)V
    //   296: iinc #5, 2
    //   299: iload_2
    //   300: ifeq -> 266
    //   303: aload_3
    //   304: invokevirtual toByteArray : ()[B
    //   307: astore #5
    //   309: getstatic burp/Zes_.ZJ : Ljava/lang/Object;
    //   312: checkcast java/math/BigInteger
    //   315: invokevirtual toByteArray : ()[B
    //   318: astore #6
    //   320: sipush #256
    //   323: newarray byte
    //   325: astore #8
    //   327: sipush #256
    //   330: newarray int
    //   332: astore #9
    //   334: sipush #256
    //   337: newarray int
    //   339: astore #10
    //   341: sipush #256
    //   344: newarray int
    //   346: astore #11
    //   348: sipush #256
    //   351: newarray int
    //   353: astore #12
    //   355: bipush #10
    //   357: newarray int
    //   359: astore #13
    //   361: sipush #283
    //   364: istore #14
    //   366: iconst_0
    //   367: istore #16
    //   369: iload #16
    //   371: sipush #256
    //   374: if_icmpge -> 608
    //   377: sipush #7839
    //   380: sipush #-10074
    //   383: invokestatic a : (II)Ljava/lang/String;
    //   386: iload #16
    //   388: iconst_1
    //   389: iushr
    //   390: invokevirtual charAt : (I)C
    //   393: istore #25
    //   395: iload #16
    //   397: iconst_1
    //   398: iand
    //   399: ifne -> 414
    //   402: iload #25
    //   404: bipush #8
    //   406: iushr
    //   407: goto -> 416
    //   410: invokestatic a : (Ljava/lang/Throwable;)Ljava/lang/Throwable;
    //   413: athrow
    //   414: iload #25
    //   416: i2b
    //   417: sipush #255
    //   420: iand
    //   421: istore #15
    //   423: iload #16
    //   425: iconst_1
    //   426: ishl
    //   427: istore #17
    //   429: iload #17
    //   431: sipush #256
    //   434: if_icmplt -> 444
    //   437: iload #17
    //   439: iload #14
    //   441: ixor
    //   442: istore #17
    //   444: iload #17
    //   446: iconst_1
    //   447: ishl
    //   448: istore #18
    //   450: iload #18
    //   452: sipush #256
    //   455: if_icmplt -> 465
    //   458: iload #18
    //   460: iload #14
    //   462: ixor
    //   463: istore #18
    //   465: iload #18
    //   467: iconst_1
    //   468: ishl
    //   469: istore #19
    //   471: iload #19
    //   473: sipush #256
    //   476: if_icmplt -> 486
    //   479: iload #19
    //   481: iload #14
    //   483: ixor
    //   484: istore #19
    //   486: iload #19
    //   488: iload #16
    //   490: ixor
    //   491: istore #20
    //   493: iload #20
    //   495: iload #17
    //   497: ixor
    //   498: istore #21
    //   500: iload #20
    //   502: iload #18
    //   504: ixor
    //   505: istore #22
    //   507: iload #19
    //   509: iload #18
    //   511: ixor
    //   512: iload #17
    //   514: ixor
    //   515: istore #23
    //   517: aload #8
    //   519: iload #16
    //   521: iload #15
    //   523: i2b
    //   524: bastore
    //   525: aload #9
    //   527: iload #15
    //   529: iload #23
    //   531: bipush #24
    //   533: ishl
    //   534: iload #20
    //   536: bipush #16
    //   538: ishl
    //   539: ior
    //   540: iload #22
    //   542: bipush #8
    //   544: ishl
    //   545: ior
    //   546: iload #21
    //   548: ior
    //   549: dup
    //   550: istore #24
    //   552: iastore
    //   553: aload #10
    //   555: iload #15
    //   557: iload #24
    //   559: bipush #8
    //   561: iushr
    //   562: iload #24
    //   564: bipush #24
    //   566: ishl
    //   567: ior
    //   568: iastore
    //   569: aload #11
    //   571: iload #15
    //   573: iload #24
    //   575: bipush #16
    //   577: iushr
    //   578: iload #24
    //   580: bipush #16
    //   582: ishl
    //   583: ior
    //   584: iastore
    //   585: aload #12
    //   587: iload #15
    //   589: iload #24
    //   591: bipush #24
    //   593: iushr
    //   594: iload #24
    //   596: bipush #8
    //   598: ishl
    //   599: ior
    //   600: iastore
    //   601: iinc #16, 1
    //   604: iload_2
    //   605: ifeq -> 369
    //   608: iconst_1
    //   609: istore #25
    //   611: aload #13
    //   613: iconst_0
    //   614: iload #25
    //   616: bipush #24
    //   618: ishl
    //   619: iastore
    //   620: iconst_1
    //   621: istore #26
    //   623: iload #26
    //   625: bipush #10
    //   627: if_icmpge -> 668
    //   630: iload #25
    //   632: iconst_1
    //   633: ishl
    //   634: istore #25
    //   636: iload #25
    //   638: sipush #256
    //   641: if_icmplt -> 651
    //   644: iload #25
    //   646: iload #14
    //   648: ixor
    //   649: istore #25
    //   651: aload #13
    //   653: iload #26
    //   655: iload #25
    //   657: bipush #24
    //   659: ishl
    //   660: iastore
    //   661: iinc #26, 1
    //   664: iload_2
    //   665: ifeq -> 623
    //   668: iconst_4
    //   669: istore #26
    //   671: iload #26
    //   673: bipush #6
    //   675: iadd
    //   676: istore #27
    //   678: iconst_4
    //   679: iload #27
    //   681: iconst_1
    //   682: iadd
    //   683: imul
    //   684: istore #28
    //   686: iload #28
    //   688: newarray int
    //   690: astore #29
    //   692: iload #28
    //   694: newarray int
    //   696: astore #30
    //   698: iconst_0
    //   699: istore #25
    //   701: iconst_0
    //   702: istore #32
    //   704: iconst_0
    //   705: istore #33
    //   707: iload #32
    //   709: iload #26
    //   711: if_icmpge -> 779
    //   714: aload #29
    //   716: iload #32
    //   718: aload #5
    //   720: iload #33
    //   722: baload
    //   723: bipush #24
    //   725: ishl
    //   726: aload #5
    //   728: iload #33
    //   730: iconst_1
    //   731: iadd
    //   732: baload
    //   733: sipush #255
    //   736: iand
    //   737: bipush #16
    //   739: ishl
    //   740: ior
    //   741: aload #5
    //   743: iload #33
    //   745: iconst_2
    //   746: iadd
    //   747: baload
    //   748: sipush #255
    //   751: iand
    //   752: bipush #8
    //   754: ishl
    //   755: ior
    //   756: aload #5
    //   758: iload #33
    //   760: iconst_3
    //   761: iadd
    //   762: baload
    //   763: sipush #255
    //   766: iand
    //   767: ior
    //   768: iastore
    //   769: iinc #32, 1
    //   772: iinc #33, 4
    //   775: iload_2
    //   776: ifeq -> 707
    //   779: iload #26
    //   781: istore #32
    //   783: iconst_0
    //   784: istore #33
    //   786: iload #32
    //   788: iload #28
    //   790: if_icmpge -> 917
    //   793: aload #29
    //   795: iload #32
    //   797: iconst_1
    //   798: isub
    //   799: iaload
    //   800: istore #31
    //   802: iload #33
    //   804: ifne -> 891
    //   807: iload #26
    //   809: istore #33
    //   811: aload #8
    //   813: iload #31
    //   815: bipush #16
    //   817: iushr
    //   818: sipush #255
    //   821: iand
    //   822: baload
    //   823: bipush #24
    //   825: ishl
    //   826: aload #8
    //   828: iload #31
    //   830: bipush #8
    //   832: iushr
    //   833: sipush #255
    //   836: iand
    //   837: baload
    //   838: sipush #255
    //   841: iand
    //   842: bipush #16
    //   844: ishl
    //   845: ior
    //   846: aload #8
    //   848: iload #31
    //   850: sipush #255
    //   853: iand
    //   854: baload
    //   855: sipush #255
    //   858: iand
    //   859: bipush #8
    //   861: ishl
    //   862: ior
    //   863: aload #8
    //   865: iload #31
    //   867: bipush #24
    //   869: iushr
    //   870: baload
    //   871: sipush #255
    //   874: iand
    //   875: ior
    //   876: istore #31
    //   878: iload #31
    //   880: aload #13
    //   882: iload #25
    //   884: iinc #25, 1
    //   887: iaload
    //   888: ixor
    //   889: istore #31
    //   891: aload #29
    //   893: iload #32
    //   895: aload #29
    //   897: iload #32
    //   899: iload #26
    //   901: isub
    //   902: iaload
    //   903: iload #31
    //   905: ixor
    //   906: iastore
    //   907: iinc #32, 1
    //   910: iinc #33, -1
    //   913: iload_2
    //   914: ifeq -> 786
    //   917: iconst_0
    //   918: istore #32
    //   920: iconst_4
    //   921: iload #27
    //   923: imul
    //   924: istore #33
    //   926: aload #30
    //   928: iload #32
    //   930: aload #29
    //   932: iload #33
    //   934: iaload
    //   935: iastore
    //   936: aload #30
    //   938: iload #32
    //   940: iconst_1
    //   941: iadd
    //   942: aload #29
    //   944: iload #33
    //   946: iconst_1
    //   947: iadd
    //   948: iaload
    //   949: iastore
    //   950: aload #30
    //   952: iload #32
    //   954: iconst_2
    //   955: iadd
    //   956: aload #29
    //   958: iload #33
    //   960: iconst_2
    //   961: iadd
    //   962: iaload
    //   963: iastore
    //   964: aload #30
    //   966: iload #32
    //   968: iconst_3
    //   969: iadd
    //   970: aload #29
    //   972: iload #33
    //   974: iconst_3
    //   975: iadd
    //   976: iaload
    //   977: iastore
    //   978: iinc #32, 4
    //   981: iinc #33, -4
    //   984: iconst_1
    //   985: istore #35
    //   987: iload #35
    //   989: iload #27
    //   991: if_icmpge -> 1355
    //   994: aload #29
    //   996: iload #33
    //   998: iaload
    //   999: istore #34
    //   1001: aload #30
    //   1003: iload #32
    //   1005: aload #9
    //   1007: aload #8
    //   1009: iload #34
    //   1011: bipush #24
    //   1013: iushr
    //   1014: baload
    //   1015: sipush #255
    //   1018: iand
    //   1019: iaload
    //   1020: aload #10
    //   1022: aload #8
    //   1024: iload #34
    //   1026: bipush #16
    //   1028: iushr
    //   1029: sipush #255
    //   1032: iand
    //   1033: baload
    //   1034: sipush #255
    //   1037: iand
    //   1038: iaload
    //   1039: ixor
    //   1040: aload #11
    //   1042: aload #8
    //   1044: iload #34
    //   1046: bipush #8
    //   1048: iushr
    //   1049: sipush #255
    //   1052: iand
    //   1053: baload
    //   1054: sipush #255
    //   1057: iand
    //   1058: iaload
    //   1059: ixor
    //   1060: aload #12
    //   1062: aload #8
    //   1064: iload #34
    //   1066: sipush #255
    //   1069: iand
    //   1070: baload
    //   1071: sipush #255
    //   1074: iand
    //   1075: iaload
    //   1076: ixor
    //   1077: iastore
    //   1078: aload #29
    //   1080: iload #33
    //   1082: iconst_1
    //   1083: iadd
    //   1084: iaload
    //   1085: istore #34
    //   1087: aload #30
    //   1089: iload #32
    //   1091: iconst_1
    //   1092: iadd
    //   1093: aload #9
    //   1095: aload #8
    //   1097: iload #34
    //   1099: bipush #24
    //   1101: iushr
    //   1102: baload
    //   1103: sipush #255
    //   1106: iand
    //   1107: iaload
    //   1108: aload #10
    //   1110: aload #8
    //   1112: iload #34
    //   1114: bipush #16
    //   1116: iushr
    //   1117: sipush #255
    //   1120: iand
    //   1121: baload
    //   1122: sipush #255
    //   1125: iand
    //   1126: iaload
    //   1127: ixor
    //   1128: aload #11
    //   1130: aload #8
    //   1132: iload #34
    //   1134: bipush #8
    //   1136: iushr
    //   1137: sipush #255
    //   1140: iand
    //   1141: baload
    //   1142: sipush #255
    //   1145: iand
    //   1146: iaload
    //   1147: ixor
    //   1148: aload #12
    //   1150: aload #8
    //   1152: iload #34
    //   1154: sipush #255
    //   1157: iand
    //   1158: baload
    //   1159: sipush #255
    //   1162: iand
    //   1163: iaload
    //   1164: ixor
    //   1165: iastore
    //   1166: aload #29
    //   1168: iload #33
    //   1170: iconst_2
    //   1171: iadd
    //   1172: iaload
    //   1173: istore #34
    //   1175: aload #30
    //   1177: iload #32
    //   1179: iconst_2
    //   1180: iadd
    //   1181: aload #9
    //   1183: aload #8
    //   1185: iload #34
    //   1187: bipush #24
    //   1189: iushr
    //   1190: baload
    //   1191: sipush #255
    //   1194: iand
    //   1195: iaload
    //   1196: aload #10
    //   1198: aload #8
    //   1200: iload #34
    //   1202: bipush #16
    //   1204: iushr
    //   1205: sipush #255
    //   1208: iand
    //   1209: baload
    //   1210: sipush #255
    //   1213: iand
    //   1214: iaload
    //   1215: ixor
    //   1216: aload #11
    //   1218: aload #8
    //   1220: iload #34
    //   1222: bipush #8
    //   1224: iushr
    //   1225: sipush #255
    //   1228: iand
    //   1229: baload
    //   1230: sipush #255
    //   1233: iand
    //   1234: iaload
    //   1235: ixor
    //   1236: aload #12
    //   1238: aload #8
    //   1240: iload #34
    //   1242: sipush #255
    //   1245: iand
    //   1246: baload
    //   1247: sipush #255
    //   1250: iand
    //   1251: iaload
    //   1252: ixor
    //   1253: iastore
    //   1254: aload #29
    //   1256: iload #33
    //   1258: iconst_3
    //   1259: iadd
    //   1260: iaload
    //   1261: istore #34
    //   1263: aload #30
    //   1265: iload #32
    //   1267: iconst_3
    //   1268: iadd
    //   1269: aload #9
    //   1271: aload #8
    //   1273: iload #34
    //   1275: bipush #24
    //   1277: iushr
    //   1278: baload
    //   1279: sipush #255
    //   1282: iand
    //   1283: iaload
    //   1284: aload #10
    //   1286: aload #8
    //   1288: iload #34
    //   1290: bipush #16
    //   1292: iushr
    //   1293: sipush #255
    //   1296: iand
    //   1297: baload
    //   1298: sipush #255
    //   1301: iand
    //   1302: iaload
    //   1303: ixor
    //   1304: aload #11
    //   1306: aload #8
    //   1308: iload #34
    //   1310: bipush #8
    //   1312: iushr
    //   1313: sipush #255
    //   1316: iand
    //   1317: baload
    //   1318: sipush #255
    //   1321: iand
    //   1322: iaload
    //   1323: ixor
    //   1324: aload #12
    //   1326: aload #8
    //   1328: iload #34
    //   1330: sipush #255
    //   1333: iand
    //   1334: baload
    //   1335: sipush #255
    //   1338: iand
    //   1339: iaload
    //   1340: ixor
    //   1341: iastore
    //   1342: iinc #32, 4
    //   1345: iinc #33, -4
    //   1348: iinc #35, 1
    //   1351: iload_2
    //   1352: ifeq -> 987
    //   1355: aload #30
    //   1357: iload #32
    //   1359: aload #29
    //   1361: iload #33
    //   1363: iaload
    //   1364: iastore
    //   1365: aload #30
    //   1367: iload #32
    //   1369: iconst_1
    //   1370: iadd
    //   1371: aload #29
    //   1373: iload #33
    //   1375: iconst_1
    //   1376: iadd
    //   1377: iaload
    //   1378: iastore
    //   1379: aload #30
    //   1381: iload #32
    //   1383: iconst_2
    //   1384: iadd
    //   1385: aload #29
    //   1387: iload #33
    //   1389: iconst_2
    //   1390: iadd
    //   1391: iaload
    //   1392: iastore
    //   1393: aload #30
    //   1395: iload #32
    //   1397: iconst_3
    //   1398: iadd
    //   1399: aload #29
    //   1401: iload #33
    //   1403: iconst_3
    //   1404: iadd
    //   1405: iaload
    //   1406: iastore
    //   1407: iconst_0
    //   1408: newarray byte
    //   1410: astore #35
    //   1412: aload #6
    //   1414: arraylength
    //   1415: bipush #16
    //   1417: irem
    //   1418: ifeq -> 1442
    //   1421: new java/lang/Exception
    //   1424: dup
    //   1425: sipush #7833
    //   1428: sipush #-3063
    //   1431: invokestatic a : (II)Ljava/lang/String;
    //   1434: invokespecial <init> : (Ljava/lang/String;)V
    //   1437: athrow
    //   1438: invokestatic a : (Ljava/lang/Throwable;)Ljava/lang/Throwable;
    //   1441: athrow
    //   1442: bipush #10
    //   1444: istore #36
    //   1446: sipush #7825
    //   1449: sipush #256
    //   1452: newarray byte
    //   1454: astore #37
    //   1456: sipush #12422
    //   1459: sipush #256
    //   1462: newarray int
    //   1464: astore #38
    //   1466: sipush #256
    //   1469: newarray int
    //   1471: astore #39
    //   1473: sipush #256
    //   1476: newarray int
    //   1478: astore #40
    //   1480: sipush #256
    //   1483: newarray int
    //   1485: astore #41
    //   1487: sipush #283
    //   1490: istore #14
    //   1492: invokestatic a : (II)Ljava/lang/String;
    //   1495: astore #42
    //   1497: iconst_0
    //   1498: istore #16
    //   1500: iload #16
    //   1502: sipush #256
    //   1505: if_icmpge -> 1732
    //   1508: aload #42
    //   1510: iload #16
    //   1512: iconst_1
    //   1513: iushr
    //   1514: invokevirtual charAt : (I)C
    //   1517: istore #43
    //   1519: iload #16
    //   1521: iconst_1
    //   1522: iand
    //   1523: ifne -> 1538
    //   1526: iload #43
    //   1528: bipush #8
    //   1530: iushr
    //   1531: goto -> 1540
    //   1534: invokestatic a : (Ljava/lang/Throwable;)Ljava/lang/Throwable;
    //   1537: athrow
    //   1538: iload #43
    //   1540: i2b
    //   1541: sipush #255
    //   1544: iand
    //   1545: istore #15
    //   1547: iload #16
    //   1549: iconst_1
    //   1550: ishl
    //   1551: istore #17
    //   1553: iload #17
    //   1555: sipush #256
    //   1558: if_icmplt -> 1568
    //   1561: iload #17
    //   1563: iload #14
    //   1565: ixor
    //   1566: istore #17
    //   1568: iload #17
    //   1570: iconst_1
    //   1571: ishl
    //   1572: istore #18
    //   1574: iload #18
    //   1576: sipush #256
    //   1579: if_icmplt -> 1589
    //   1582: iload #18
    //   1584: iload #14
    //   1586: ixor
    //   1587: istore #18
    //   1589: iload #18
    //   1591: iconst_1
    //   1592: ishl
    //   1593: istore #19
    //   1595: iload #19
    //   1597: sipush #256
    //   1600: if_icmplt -> 1610
    //   1603: iload #19
    //   1605: iload #14
    //   1607: ixor
    //   1608: istore #19
    //   1610: iload #19
    //   1612: iload #16
    //   1614: ixor
    //   1615: istore #20
    //   1617: iload #20
    //   1619: iload #17
    //   1621: ixor
    //   1622: istore #21
    //   1624: iload #20
    //   1626: iload #18
    //   1628: ixor
    //   1629: istore #22
    //   1631: iload #19
    //   1633: iload #18
    //   1635: ixor
    //   1636: iload #17
    //   1638: ixor
    //   1639: istore #23
    //   1641: aload #37
    //   1643: iload #15
    //   1645: iload #16
    //   1647: i2b
    //   1648: bastore
    //   1649: aload #38
    //   1651: iload #15
    //   1653: iload #23
    //   1655: bipush #24
    //   1657: ishl
    //   1658: iload #20
    //   1660: bipush #16
    //   1662: ishl
    //   1663: ior
    //   1664: iload #22
    //   1666: bipush #8
    //   1668: ishl
    //   1669: ior
    //   1670: iload #21
    //   1672: ior
    //   1673: dup
    //   1674: istore #24
    //   1676: iastore
    //   1677: aload #39
    //   1679: iload #15
    //   1681: iload #24
    //   1683: bipush #8
    //   1685: iushr
    //   1686: iload #24
    //   1688: bipush #24
    //   1690: ishl
    //   1691: ior
    //   1692: iastore
    //   1693: aload #40
    //   1695: iload #15
    //   1697: iload #24
    //   1699: bipush #16
    //   1701: iushr
    //   1702: iload #24
    //   1704: bipush #16
    //   1706: ishl
    //   1707: ior
    //   1708: iastore
    //   1709: aload #41
    //   1711: iload #15
    //   1713: iload #24
    //   1715: bipush #24
    //   1717: iushr
    //   1718: iload #24
    //   1720: bipush #8
    //   1722: ishl
    //   1723: ior
    //   1724: iastore
    //   1725: iinc #16, 1
    //   1728: iload_2
    //   1729: ifeq -> 1500
    //   1732: aload #6
    //   1734: arraylength
    //   1735: newarray byte
    //   1737: astore #43
    //   1739: iconst_0
    //   1740: istore #44
    //   1742: iload #44
    //   1744: aload #6
    //   1746: arraylength
    //   1747: bipush #16
    //   1749: idiv
    //   1750: if_icmpge -> 2664
    //   1753: bipush #16
    //   1755: newarray byte
    //   1757: astore #45
    //   1759: bipush #16
    //   1761: newarray byte
    //   1763: astore #46
    //   1765: iconst_0
    //   1766: istore #47
    //   1768: iload #47
    //   1770: bipush #16
    //   1772: if_icmpge -> 1798
    //   1775: aload #45
    //   1777: iload #47
    //   1779: aload #6
    //   1781: iload #47
    //   1783: iload #44
    //   1785: bipush #16
    //   1787: imul
    //   1788: iadd
    //   1789: baload
    //   1790: bastore
    //   1791: iinc #47, 1
    //   1794: iload_2
    //   1795: ifeq -> 1768
    //   1798: iconst_0
    //   1799: istore #47
    //   1801: aload #45
    //   1803: iconst_0
    //   1804: baload
    //   1805: bipush #24
    //   1807: ishl
    //   1808: aload #45
    //   1810: iconst_1
    //   1811: baload
    //   1812: sipush #255
    //   1815: iand
    //   1816: bipush #16
    //   1818: ishl
    //   1819: ior
    //   1820: aload #45
    //   1822: iconst_2
    //   1823: baload
    //   1824: sipush #255
    //   1827: iand
    //   1828: bipush #8
    //   1830: ishl
    //   1831: ior
    //   1832: aload #45
    //   1834: iconst_3
    //   1835: baload
    //   1836: sipush #255
    //   1839: iand
    //   1840: ior
    //   1841: aload #30
    //   1843: iconst_0
    //   1844: iaload
    //   1845: ixor
    //   1846: istore #49
    //   1848: aload #45
    //   1850: iconst_4
    //   1851: baload
    //   1852: bipush #24
    //   1854: ishl
    //   1855: aload #45
    //   1857: iconst_5
    //   1858: baload
    //   1859: sipush #255
    //   1862: iand
    //   1863: bipush #16
    //   1865: ishl
    //   1866: ior
    //   1867: aload #45
    //   1869: bipush #6
    //   1871: baload
    //   1872: sipush #255
    //   1875: iand
    //   1876: bipush #8
    //   1878: ishl
    //   1879: ior
    //   1880: aload #45
    //   1882: bipush #7
    //   1884: baload
    //   1885: sipush #255
    //   1888: iand
    //   1889: ior
    //   1890: aload #30
    //   1892: iconst_1
    //   1893: iaload
    //   1894: ixor
    //   1895: istore #50
    //   1897: aload #45
    //   1899: bipush #8
    //   1901: baload
    //   1902: bipush #24
    //   1904: ishl
    //   1905: aload #45
    //   1907: bipush #9
    //   1909: baload
    //   1910: sipush #255
    //   1913: iand
    //   1914: bipush #16
    //   1916: ishl
    //   1917: ior
    //   1918: aload #45
    //   1920: bipush #10
    //   1922: baload
    //   1923: sipush #255
    //   1926: iand
    //   1927: bipush #8
    //   1929: ishl
    //   1930: ior
    //   1931: aload #45
    //   1933: bipush #11
    //   1935: baload
    //   1936: sipush #255
    //   1939: iand
    //   1940: ior
    //   1941: aload #30
    //   1943: iconst_2
    //   1944: iaload
    //   1945: ixor
    //   1946: istore #51
    //   1948: aload #45
    //   1950: bipush #12
    //   1952: baload
    //   1953: bipush #24
    //   1955: ishl
    //   1956: aload #45
    //   1958: bipush #13
    //   1960: baload
    //   1961: sipush #255
    //   1964: iand
    //   1965: bipush #16
    //   1967: ishl
    //   1968: ior
    //   1969: aload #45
    //   1971: bipush #14
    //   1973: baload
    //   1974: sipush #255
    //   1977: iand
    //   1978: bipush #8
    //   1980: ishl
    //   1981: ior
    //   1982: aload #45
    //   1984: bipush #15
    //   1986: baload
    //   1987: sipush #255
    //   1990: iand
    //   1991: ior
    //   1992: aload #30
    //   1994: iconst_3
    //   1995: iaload
    //   1996: ixor
    //   1997: istore #52
    //   1999: iconst_1
    //   2000: istore #53
    //   2002: iload #53
    //   2004: iload #36
    //   2006: if_icmpge -> 2249
    //   2009: iinc #47, 4
    //   2012: aload #38
    //   2014: iload #49
    //   2016: bipush #24
    //   2018: iushr
    //   2019: iaload
    //   2020: aload #39
    //   2022: iload #52
    //   2024: bipush #16
    //   2026: iushr
    //   2027: sipush #255
    //   2030: iand
    //   2031: iaload
    //   2032: ixor
    //   2033: aload #40
    //   2035: iload #51
    //   2037: bipush #8
    //   2039: iushr
    //   2040: sipush #255
    //   2043: iand
    //   2044: iaload
    //   2045: ixor
    //   2046: aload #41
    //   2048: iload #50
    //   2050: sipush #255
    //   2053: iand
    //   2054: iaload
    //   2055: ixor
    //   2056: aload #30
    //   2058: iload #47
    //   2060: iaload
    //   2061: ixor
    //   2062: istore #54
    //   2064: aload #38
    //   2066: iload #50
    //   2068: bipush #24
    //   2070: iushr
    //   2071: iaload
    //   2072: aload #39
    //   2074: iload #49
    //   2076: bipush #16
    //   2078: iushr
    //   2079: sipush #255
    //   2082: iand
    //   2083: iaload
    //   2084: ixor
    //   2085: aload #40
    //   2087: iload #52
    //   2089: bipush #8
    //   2091: iushr
    //   2092: sipush #255
    //   2095: iand
    //   2096: iaload
    //   2097: ixor
    //   2098: aload #41
    //   2100: iload #51
    //   2102: sipush #255
    //   2105: iand
    //   2106: iaload
    //   2107: ixor
    //   2108: aload #30
    //   2110: iload #47
    //   2112: iconst_1
    //   2113: iadd
    //   2114: iaload
    //   2115: ixor
    //   2116: istore #55
    //   2118: aload #38
    //   2120: iload #51
    //   2122: bipush #24
    //   2124: iushr
    //   2125: iaload
    //   2126: aload #39
    //   2128: iload #50
    //   2130: bipush #16
    //   2132: iushr
    //   2133: sipush #255
    //   2136: iand
    //   2137: iaload
    //   2138: ixor
    //   2139: aload #40
    //   2141: iload #49
    //   2143: bipush #8
    //   2145: iushr
    //   2146: sipush #255
    //   2149: iand
    //   2150: iaload
    //   2151: ixor
    //   2152: aload #41
    //   2154: iload #52
    //   2156: sipush #255
    //   2159: iand
    //   2160: iaload
    //   2161: ixor
    //   2162: aload #30
    //   2164: iload #47
    //   2166: iconst_2
    //   2167: iadd
    //   2168: iaload
    //   2169: ixor
    //   2170: istore #56
    //   2172: aload #38
    //   2174: iload #52
    //   2176: bipush #24
    //   2178: iushr
    //   2179: iaload
    //   2180: aload #39
    //   2182: iload #51
    //   2184: bipush #16
    //   2186: iushr
    //   2187: sipush #255
    //   2190: iand
    //   2191: iaload
    //   2192: ixor
    //   2193: aload #40
    //   2195: iload #50
    //   2197: bipush #8
    //   2199: iushr
    //   2200: sipush #255
    //   2203: iand
    //   2204: iaload
    //   2205: ixor
    //   2206: aload #41
    //   2208: iload #49
    //   2210: sipush #255
    //   2213: iand
    //   2214: iaload
    //   2215: ixor
    //   2216: aload #30
    //   2218: iload #47
    //   2220: iconst_3
    //   2221: iadd
    //   2222: iaload
    //   2223: ixor
    //   2224: istore #57
    //   2226: iload #54
    //   2228: istore #49
    //   2230: iload #55
    //   2232: istore #50
    //   2234: iload #56
    //   2236: istore #51
    //   2238: iload #57
    //   2240: istore #52
    //   2242: iinc #53, 1
    //   2245: iload_2
    //   2246: ifeq -> 2002
    //   2249: iinc #47, 4
    //   2252: aload #30
    //   2254: iload #47
    //   2256: iaload
    //   2257: istore #48
    //   2259: aload #46
    //   2261: iconst_0
    //   2262: aload #37
    //   2264: iload #49
    //   2266: bipush #24
    //   2268: iushr
    //   2269: baload
    //   2270: iload #48
    //   2272: bipush #24
    //   2274: iushr
    //   2275: ixor
    //   2276: i2b
    //   2277: bastore
    //   2278: aload #46
    //   2280: iconst_1
    //   2281: aload #37
    //   2283: iload #52
    //   2285: bipush #16
    //   2287: iushr
    //   2288: sipush #255
    //   2291: iand
    //   2292: baload
    //   2293: iload #48
    //   2295: bipush #16
    //   2297: iushr
    //   2298: ixor
    //   2299: i2b
    //   2300: bastore
    //   2301: aload #46
    //   2303: iconst_2
    //   2304: aload #37
    //   2306: iload #51
    //   2308: bipush #8
    //   2310: iushr
    //   2311: sipush #255
    //   2314: iand
    //   2315: baload
    //   2316: iload #48
    //   2318: bipush #8
    //   2320: iushr
    //   2321: ixor
    //   2322: i2b
    //   2323: bastore
    //   2324: aload #46
    //   2326: iconst_3
    //   2327: aload #37
    //   2329: iload #50
    //   2331: sipush #255
    //   2334: iand
    //   2335: baload
    //   2336: iload #48
    //   2338: ixor
    //   2339: i2b
    //   2340: bastore
    //   2341: aload #30
    //   2343: iload #47
    //   2345: iconst_1
    //   2346: iadd
    //   2347: iaload
    //   2348: istore #48
    //   2350: aload #46
    //   2352: iconst_4
    //   2353: aload #37
    //   2355: iload #50
    //   2357: bipush #24
    //   2359: iushr
    //   2360: baload
    //   2361: iload #48
    //   2363: bipush #24
    //   2365: iushr
    //   2366: ixor
    //   2367: i2b
    //   2368: bastore
    //   2369: aload #46
    //   2371: iconst_5
    //   2372: aload #37
    //   2374: iload #49
    //   2376: bipush #16
    //   2378: iushr
    //   2379: sipush #255
    //   2382: iand
    //   2383: baload
    //   2384: iload #48
    //   2386: bipush #16
    //   2388: iushr
    //   2389: ixor
    //   2390: i2b
    //   2391: bastore
    //   2392: aload #46
    //   2394: bipush #6
    //   2396: aload #37
    //   2398: iload #52
    //   2400: bipush #8
    //   2402: iushr
    //   2403: sipush #255
    //   2406: iand
    //   2407: baload
    //   2408: iload #48
    //   2410: bipush #8
    //   2412: iushr
    //   2413: ixor
    //   2414: i2b
    //   2415: bastore
    //   2416: aload #46
    //   2418: bipush #7
    //   2420: aload #37
    //   2422: iload #51
    //   2424: sipush #255
    //   2427: iand
    //   2428: baload
    //   2429: iload #48
    //   2431: ixor
    //   2432: i2b
    //   2433: bastore
    //   2434: aload #30
    //   2436: iload #47
    //   2438: iconst_2
    //   2439: iadd
    //   2440: iaload
    //   2441: istore #48
    //   2443: aload #46
    //   2445: bipush #8
    //   2447: aload #37
    //   2449: iload #51
    //   2451: bipush #24
    //   2453: iushr
    //   2454: baload
    //   2455: iload #48
    //   2457: bipush #24
    //   2459: iushr
    //   2460: ixor
    //   2461: i2b
    //   2462: bastore
    //   2463: aload #46
    //   2465: bipush #9
    //   2467: aload #37
    //   2469: iload #50
    //   2471: bipush #16
    //   2473: iushr
    //   2474: sipush #255
    //   2477: iand
    //   2478: baload
    //   2479: iload #48
    //   2481: bipush #16
    //   2483: iushr
    //   2484: ixor
    //   2485: i2b
    //   2486: bastore
    //   2487: aload #46
    //   2489: bipush #10
    //   2491: aload #37
    //   2493: iload #49
    //   2495: bipush #8
    //   2497: iushr
    //   2498: sipush #255
    //   2501: iand
    //   2502: baload
    //   2503: iload #48
    //   2505: bipush #8
    //   2507: iushr
    //   2508: ixor
    //   2509: i2b
    //   2510: bastore
    //   2511: aload #46
    //   2513: bipush #11
    //   2515: aload #37
    //   2517: iload #52
    //   2519: sipush #255
    //   2522: iand
    //   2523: baload
    //   2524: iload #48
    //   2526: ixor
    //   2527: i2b
    //   2528: bastore
    //   2529: aload #30
    //   2531: iload #47
    //   2533: iconst_3
    //   2534: iadd
    //   2535: iaload
    //   2536: istore #48
    //   2538: aload #46
    //   2540: bipush #12
    //   2542: aload #37
    //   2544: iload #52
    //   2546: bipush #24
    //   2548: iushr
    //   2549: baload
    //   2550: iload #48
    //   2552: bipush #24
    //   2554: iushr
    //   2555: ixor
    //   2556: i2b
    //   2557: bastore
    //   2558: aload #46
    //   2560: bipush #13
    //   2562: aload #37
    //   2564: iload #51
    //   2566: bipush #16
    //   2568: iushr
    //   2569: sipush #255
    //   2572: iand
    //   2573: baload
    //   2574: iload #48
    //   2576: bipush #16
    //   2578: iushr
    //   2579: ixor
    //   2580: i2b
    //   2581: bastore
    //   2582: aload #46
    //   2584: bipush #14
    //   2586: aload #37
    //   2588: iload #50
    //   2590: bipush #8
    //   2592: iushr
    //   2593: sipush #255
    //   2596: iand
    //   2597: baload
    //   2598: iload #48
    //   2600: bipush #8
    //   2602: iushr
    //   2603: ixor
    //   2604: i2b
    //   2605: bastore
    //   2606: aload #46
    //   2608: bipush #15
    //   2610: aload #37
    //   2612: iload #49
    //   2614: sipush #255
    //   2617: iand
    //   2618: baload
    //   2619: iload #48
    //   2621: ixor
    //   2622: i2b
    //   2623: bastore
    //   2624: iconst_0
    //   2625: istore #53
    //   2627: iload #53
    //   2629: bipush #16
    //   2631: if_icmpge -> 2657
    //   2634: aload #43
    //   2636: iload #53
    //   2638: iload #44
    //   2640: bipush #16
    //   2642: imul
    //   2643: iadd
    //   2644: aload #46
    //   2646: iload #53
    //   2648: baload
    //   2649: bastore
    //   2650: iinc #53, 1
    //   2653: iload_2
    //   2654: ifeq -> 2627
    //   2657: iinc #44, 1
    //   2660: iload_2
    //   2661: ifeq -> 1742
    //   2664: aload #43
    //   2666: arraylength
    //   2667: ifle -> 2748
    //   2670: aload #43
    //   2672: aload #43
    //   2674: arraylength
    //   2675: iconst_1
    //   2676: isub
    //   2677: baload
    //   2678: istore #44
    //   2680: iload #44
    //   2682: bipush #16
    //   2684: if_icmple -> 2695
    //   2687: aload #43
    //   2689: astore #35
    //   2691: iload_2
    //   2692: ifeq -> 2748
    //   2695: aload #43
    //   2697: arraylength
    //   2698: iload #44
    //   2700: isub
    //   2701: newarray byte
    //   2703: astore #35
    //   2705: iconst_0
    //   2706: istore #45
    //   2708: iload #45
    //   2710: aload #35
    //   2712: arraylength
    //   2713: if_icmpge -> 2748
    //   2716: iload #45
    //   2718: aload #43
    //   2720: arraylength
    //   2721: if_icmpge -> 2748
    //   2724: aload #35
    //   2726: iload #45
    //   2728: aload #43
    //   2730: iload #45
    //   2732: baload
    //   2733: bastore
    //   2734: iinc #45, 1
    //   2737: iload_2
    //   2738: ifeq -> 2708
    //   2741: goto -> 2748
    //   2744: invokestatic a : (Ljava/lang/Throwable;)Ljava/lang/Throwable;
    //   2747: athrow
    //   2748: aload #35
    //   2750: astore #7
    //   2752: new java/math/BigInteger
    //   2755: dup
    //   2756: aload #7
    //   2758: invokespecial <init> : ([B)V
    //   2761: invokevirtual abs : ()Ljava/math/BigInteger;
    //   2764: putstatic burp/Zg_p.Zx : Ljava/lang/Object;
    //   2767: getstatic burp/Zr0g.Zj : Ljava/lang/Object;
    //   2770: checkcast java/math/BigInteger
    //   2773: invokevirtual toByteArray : ()[B
    //   2776: astore_3
    //   2777: iconst_0
    //   2778: istore #5
    //   2780: iconst_0
    //   2781: istore #6
    //   2783: iload #6
    //   2785: aload_3
    //   2786: arraylength
    //   2787: if_icmpge -> 2932
    //   2790: aload_3
    //   2791: iload #6
    //   2793: baload
    //   2794: istore #7
    //   2796: iload #7
    //   2798: bipush #48
    //   2800: if_icmplt -> 2817
    //   2803: iload #7
    //   2805: bipush #57
    //   2807: if_icmple -> 2915
    //   2810: goto -> 2817
    //   2813: invokestatic a : (Ljava/lang/Throwable;)Ljava/lang/Throwable;
    //   2816: athrow
    //   2817: iload #7
    //   2819: bipush #65
    //   2821: if_icmplt -> 2845
    //   2824: goto -> 2831
    //   2827: invokestatic a : (Ljava/lang/Throwable;)Ljava/lang/Throwable;
    //   2830: athrow
    //   2831: iload #7
    //   2833: bipush #90
    //   2835: if_icmple -> 2915
    //   2838: goto -> 2845
    //   2841: invokestatic a : (Ljava/lang/Throwable;)Ljava/lang/Throwable;
    //   2844: athrow
    //   2845: iload #7
    //   2847: bipush #97
    //   2849: if_icmplt -> 2873
    //   2852: goto -> 2859
    //   2855: invokestatic a : (Ljava/lang/Throwable;)Ljava/lang/Throwable;
    //   2858: athrow
    //   2859: iload #7
    //   2861: bipush #122
    //   2863: if_icmple -> 2915
    //   2866: goto -> 2873
    //   2869: invokestatic a : (Ljava/lang/Throwable;)Ljava/lang/Throwable;
    //   2872: athrow
    //   2873: iload #7
    //   2875: bipush #43
    //   2877: if_icmpeq -> 2915
    //   2880: goto -> 2887
    //   2883: invokestatic a : (Ljava/lang/Throwable;)Ljava/lang/Throwable;
    //   2886: athrow
    //   2887: iload #7
    //   2889: bipush #47
    //   2891: if_icmpeq -> 2915
    //   2894: goto -> 2901
    //   2897: invokestatic a : (Ljava/lang/Throwable;)Ljava/lang/Throwable;
    //   2900: athrow
    //   2901: iload #7
    //   2903: bipush #61
    //   2905: if_icmpne -> 2925
    //   2908: goto -> 2915
    //   2911: invokestatic a : (Ljava/lang/Throwable;)Ljava/lang/Throwable;
    //   2914: athrow
    //   2915: iinc #5, 1
    //   2918: goto -> 2925
    //   2921: invokestatic a : (Ljava/lang/Throwable;)Ljava/lang/Throwable;
    //   2924: athrow
    //   2925: iinc #6, 1
    //   2928: iload_2
    //   2929: ifeq -> 2783
    //   2932: iload #5
    //   2934: newarray byte
    //   2936: astore #6
    //   2938: iconst_0
    //   2939: istore #7
    //   2941: iconst_0
    //   2942: istore #8
    //   2944: iload #8
    //   2946: aload_3
    //   2947: arraylength
    //   2948: if_icmpge -> 3100
    //   2951: aload_3
    //   2952: iload #8
    //   2954: baload
    //   2955: istore #9
    //   2957: iload #9
    //   2959: bipush #48
    //   2961: if_icmplt -> 2978
    //   2964: iload #9
    //   2966: bipush #57
    //   2968: if_icmple -> 3076
    //   2971: goto -> 2978
    //   2974: invokestatic a : (Ljava/lang/Throwable;)Ljava/lang/Throwable;
    //   2977: athrow
    //   2978: iload #9
    //   2980: bipush #65
    //   2982: if_icmplt -> 3006
    //   2985: goto -> 2992
    //   2988: invokestatic a : (Ljava/lang/Throwable;)Ljava/lang/Throwable;
    //   2991: athrow
    //   2992: iload #9
    //   2994: bipush #90
    //   2996: if_icmple -> 3076
    //   2999: goto -> 3006
    //   3002: invokestatic a : (Ljava/lang/Throwable;)Ljava/lang/Throwable;
    //   3005: athrow
    //   3006: iload #9
    //   3008: bipush #97
    //   3010: if_icmplt -> 3034
    //   3013: goto -> 3020
    //   3016: invokestatic a : (Ljava/lang/Throwable;)Ljava/lang/Throwable;
    //   3019: athrow
    //   3020: iload #9
    //   3022: bipush #122
    //   3024: if_icmple -> 3076
    //   3027: goto -> 3034
    //   3030: invokestatic a : (Ljava/lang/Throwable;)Ljava/lang/Throwable;
    //   3033: athrow
    //   3034: iload #9
    //   3036: bipush #43
    //   3038: if_icmpeq -> 3076
    //   3041: goto -> 3048
    //   3044: invokestatic a : (Ljava/lang/Throwable;)Ljava/lang/Throwable;
    //   3047: athrow
    //   3048: iload #9
    //   3050: bipush #47
    //   3052: if_icmpeq -> 3076
    //   3055: goto -> 3062
    //   3058: invokestatic a : (Ljava/lang/Throwable;)Ljava/lang/Throwable;
    //   3061: athrow
    //   3062: iload #9
    //   3064: bipush #61
    //   3066: if_icmpne -> 3093
    //   3069: goto -> 3076
    //   3072: invokestatic a : (Ljava/lang/Throwable;)Ljava/lang/Throwable;
    //   3075: athrow
    //   3076: aload #6
    //   3078: iload #7
    //   3080: iload #9
    //   3082: bastore
    //   3083: iinc #7, 1
    //   3086: goto -> 3093
    //   3089: invokestatic a : (Ljava/lang/Throwable;)Ljava/lang/Throwable;
    //   3092: athrow
    //   3093: iinc #8, 1
    //   3096: iload_2
    //   3097: ifeq -> 2944
    //   3100: aload #6
    //   3102: astore #4
    //   3104: aload #4
    //   3106: astore_3
    //   3107: aload_3
    //   3108: arraylength
    //   3109: istore #5
    //   3111: aload_3
    //   3112: iload #5
    //   3114: iconst_1
    //   3115: isub
    //   3116: baload
    //   3117: bipush #61
    //   3119: if_icmpne -> 3129
    //   3122: iinc #5, -1
    //   3125: iload_2
    //   3126: ifeq -> 3111
    //   3129: iload #5
    //   3131: aload_3
    //   3132: arraylength
    //   3133: iconst_4
    //   3134: idiv
    //   3135: isub
    //   3136: newarray byte
    //   3138: astore #6
    //   3140: iconst_0
    //   3141: istore #7
    //   3143: iload #7
    //   3145: aload_3
    //   3146: arraylength
    //   3147: if_icmpge -> 3409
    //   3150: aload_3
    //   3151: iload #7
    //   3153: baload
    //   3154: bipush #61
    //   3156: if_icmpne -> 3175
    //   3159: aload_3
    //   3160: iload #7
    //   3162: iconst_0
    //   3163: bastore
    //   3164: iload_2
    //   3165: ifeq -> 3402
    //   3168: goto -> 3175
    //   3171: invokestatic a : (Ljava/lang/Throwable;)Ljava/lang/Throwable;
    //   3174: athrow
    //   3175: aload_3
    //   3176: iload #7
    //   3178: baload
    //   3179: bipush #47
    //   3181: if_icmpne -> 3208
    //   3184: goto -> 3191
    //   3187: invokestatic a : (Ljava/lang/Throwable;)Ljava/lang/Throwable;
    //   3190: athrow
    //   3191: aload_3
    //   3192: iload #7
    //   3194: bipush #63
    //   3196: bastore
    //   3197: iload_2
    //   3198: ifeq -> 3402
    //   3201: goto -> 3208
    //   3204: invokestatic a : (Ljava/lang/Throwable;)Ljava/lang/Throwable;
    //   3207: athrow
    //   3208: aload_3
    //   3209: iload #7
    //   3211: baload
    //   3212: bipush #43
    //   3214: if_icmpne -> 3241
    //   3217: goto -> 3224
    //   3220: invokestatic a : (Ljava/lang/Throwable;)Ljava/lang/Throwable;
    //   3223: athrow
    //   3224: aload_3
    //   3225: iload #7
    //   3227: bipush #62
    //   3229: bastore
    //   3230: iload_2
    //   3231: ifeq -> 3402
    //   3234: goto -> 3241
    //   3237: invokestatic a : (Ljava/lang/Throwable;)Ljava/lang/Throwable;
    //   3240: athrow
    //   3241: aload_3
    //   3242: iload #7
    //   3244: baload
    //   3245: bipush #48
    //   3247: if_icmplt -> 3296
    //   3250: goto -> 3257
    //   3253: invokestatic a : (Ljava/lang/Throwable;)Ljava/lang/Throwable;
    //   3256: athrow
    //   3257: aload_3
    //   3258: iload #7
    //   3260: baload
    //   3261: bipush #57
    //   3263: if_icmpgt -> 3296
    //   3266: goto -> 3273
    //   3269: invokestatic a : (Ljava/lang/Throwable;)Ljava/lang/Throwable;
    //   3272: athrow
    //   3273: aload_3
    //   3274: iload #7
    //   3276: aload_3
    //   3277: iload #7
    //   3279: baload
    //   3280: bipush #-4
    //   3282: isub
    //   3283: i2b
    //   3284: bastore
    //   3285: iload_2
    //   3286: ifeq -> 3402
    //   3289: goto -> 3296
    //   3292: invokestatic a : (Ljava/lang/Throwable;)Ljava/lang/Throwable;
    //   3295: athrow
    //   3296: aload_3
    //   3297: iload #7
    //   3299: baload
    //   3300: bipush #97
    //   3302: if_icmplt -> 3351
    //   3305: goto -> 3312
    //   3308: invokestatic a : (Ljava/lang/Throwable;)Ljava/lang/Throwable;
    //   3311: athrow
    //   3312: aload_3
    //   3313: iload #7
    //   3315: baload
    //   3316: bipush #122
    //   3318: if_icmpgt -> 3351
    //   3321: goto -> 3328
    //   3324: invokestatic a : (Ljava/lang/Throwable;)Ljava/lang/Throwable;
    //   3327: athrow
    //   3328: aload_3
    //   3329: iload #7
    //   3331: aload_3
    //   3332: iload #7
    //   3334: baload
    //   3335: bipush #71
    //   3337: isub
    //   3338: i2b
    //   3339: bastore
    //   3340: iload_2
    //   3341: ifeq -> 3402
    //   3344: goto -> 3351
    //   3347: invokestatic a : (Ljava/lang/Throwable;)Ljava/lang/Throwable;
    //   3350: athrow
    //   3351: aload_3
    //   3352: iload #7
    //   3354: baload
    //   3355: bipush #65
    //   3357: if_icmplt -> 3402
    //   3360: goto -> 3367
    //   3363: invokestatic a : (Ljava/lang/Throwable;)Ljava/lang/Throwable;
    //   3366: athrow
    //   3367: aload_3
    //   3368: iload #7
    //   3370: baload
    //   3371: bipush #90
    //   3373: if_icmpgt -> 3402
    //   3376: goto -> 3383
    //   3379: invokestatic a : (Ljava/lang/Throwable;)Ljava/lang/Throwable;
    //   3382: athrow
    //   3383: aload_3
    //   3384: iload #7
    //   3386: aload_3
    //   3387: iload #7
    //   3389: baload
    //   3390: bipush #65
    //   3392: isub
    //   3393: i2b
    //   3394: bastore
    //   3395: goto -> 3402
    //   3398: invokestatic a : (Ljava/lang/Throwable;)Ljava/lang/Throwable;
    //   3401: athrow
    //   3402: iinc #7, 1
    //   3405: iload_2
    //   3406: ifeq -> 3143
    //   3409: iconst_0
    //   3410: istore #7
    //   3412: iconst_0
    //   3413: istore #8
    //   3415: iload #8
    //   3417: aload #6
    //   3419: arraylength
    //   3420: iconst_2
    //   3421: isub
    //   3422: if_icmpge -> 3525
    //   3425: aload #6
    //   3427: iload #8
    //   3429: aload_3
    //   3430: iload #7
    //   3432: baload
    //   3433: iconst_2
    //   3434: ishl
    //   3435: sipush #255
    //   3438: iand
    //   3439: aload_3
    //   3440: iload #7
    //   3442: iconst_1
    //   3443: iadd
    //   3444: baload
    //   3445: iconst_4
    //   3446: iushr
    //   3447: iconst_3
    //   3448: iand
    //   3449: ior
    //   3450: i2b
    //   3451: bastore
    //   3452: aload #6
    //   3454: iload #8
    //   3456: iconst_1
    //   3457: iadd
    //   3458: aload_3
    //   3459: iload #7
    //   3461: iconst_1
    //   3462: iadd
    //   3463: baload
    //   3464: iconst_4
    //   3465: ishl
    //   3466: sipush #255
    //   3469: iand
    //   3470: aload_3
    //   3471: iload #7
    //   3473: iconst_2
    //   3474: iadd
    //   3475: baload
    //   3476: iconst_2
    //   3477: iushr
    //   3478: bipush #15
    //   3480: iand
    //   3481: ior
    //   3482: i2b
    //   3483: bastore
    //   3484: aload #6
    //   3486: iload #8
    //   3488: iconst_2
    //   3489: iadd
    //   3490: aload_3
    //   3491: iload #7
    //   3493: iconst_2
    //   3494: iadd
    //   3495: baload
    //   3496: bipush #6
    //   3498: ishl
    //   3499: sipush #255
    //   3502: iand
    //   3503: aload_3
    //   3504: iload #7
    //   3506: iconst_3
    //   3507: iadd
    //   3508: baload
    //   3509: bipush #63
    //   3511: iand
    //   3512: ior
    //   3513: i2b
    //   3514: bastore
    //   3515: iinc #7, 4
    //   3518: iinc #8, 3
    //   3521: iload_2
    //   3522: ifeq -> 3415
    //   3525: iload #8
    //   3527: aload #6
    //   3529: arraylength
    //   3530: if_icmpge -> 3567
    //   3533: aload #6
    //   3535: iload #8
    //   3537: aload_3
    //   3538: iload #7
    //   3540: baload
    //   3541: iconst_2
    //   3542: ishl
    //   3543: sipush #255
    //   3546: iand
    //   3547: aload_3
    //   3548: iload #7
    //   3550: iconst_1
    //   3551: iadd
    //   3552: baload
    //   3553: iconst_4
    //   3554: iushr
    //   3555: iconst_3
    //   3556: iand
    //   3557: ior
    //   3558: i2b
    //   3559: bastore
    //   3560: goto -> 3567
    //   3563: invokestatic a : (Ljava/lang/Throwable;)Ljava/lang/Throwable;
    //   3566: athrow
    //   3567: iinc #8, 1
    //   3570: iload #8
    //   3572: aload #6
    //   3574: arraylength
    //   3575: if_icmpge -> 3615
    //   3578: aload #6
    //   3580: iload #8
    //   3582: aload_3
    //   3583: iload #7
    //   3585: iconst_1
    //   3586: iadd
    //   3587: baload
    //   3588: iconst_4
    //   3589: ishl
    //   3590: sipush #255
    //   3593: iand
    //   3594: aload_3
    //   3595: iload #7
    //   3597: iconst_2
    //   3598: iadd
    //   3599: baload
    //   3600: iconst_2
    //   3601: iushr
    //   3602: bipush #15
    //   3604: iand
    //   3605: ior
    //   3606: i2b
    //   3607: bastore
    //   3608: goto -> 3615
    //   3611: invokestatic a : (Ljava/lang/Throwable;)Ljava/lang/Throwable;
    //   3614: athrow
    //   3615: aload #6
    //   3617: astore #4
    //   3619: sipush #7837
    //   3622: new java/math/BigInteger
    //   3625: dup
    //   3626: aload #4
    //   3628: invokespecial <init> : ([B)V
    //   3631: invokevirtual abs : ()Ljava/math/BigInteger;
    //   3634: putstatic burp/Zxo6.Zw : Ljava/lang/Object;
    //   3637: sipush #2171
    //   3640: invokestatic a : (II)Ljava/lang/String;
    //   3643: iconst_1
    //   3644: ldc burp/Zxl5
    //   3646: invokevirtual getClassLoader : ()Ljava/lang/ClassLoader;
    //   3649: invokestatic forName : (Ljava/lang/String;ZLjava/lang/ClassLoader;)Ljava/lang/Class;
    //   3652: invokevirtual getDeclaredFields : ()[Ljava/lang/reflect/Field;
    //   3655: astore_3
    //   3656: aload_3
    //   3657: arraylength
    //   3658: istore #4
    //   3660: iconst_0
    //   3661: istore #5
    //   3663: iload #5
    //   3665: iload #4
    //   3667: if_icmpge -> 3804
    //   3670: aload_3
    //   3671: iload #5
    //   3673: aaload
    //   3674: astore #6
    //   3676: aload #6
    //   3678: invokevirtual getModifiers : ()I
    //   3681: invokestatic isStatic : (I)Z
    //   3684: ifne -> 3694
    //   3687: goto -> 3797
    //   3690: invokestatic a : (Ljava/lang/Throwable;)Ljava/lang/Throwable;
    //   3693: athrow
    //   3694: aload #6
    //   3696: invokevirtual getType : ()Ljava/lang/Class;
    //   3699: astore #7
    //   3701: aload #7
    //   3703: ifnull -> 3784
    //   3706: aload #7
    //   3708: invokevirtual isPrimitive : ()Z
    //   3711: ifne -> 3784
    //   3714: goto -> 3721
    //   3717: invokestatic a : (Ljava/lang/Throwable;)Ljava/lang/Throwable;
    //   3720: athrow
    //   3721: aload #7
    //   3723: invokevirtual getPackage : ()Ljava/lang/Package;
    //   3726: ifnull -> 3784
    //   3729: goto -> 3736
    //   3732: invokestatic a : (Ljava/lang/Throwable;)Ljava/lang/Throwable;
    //   3735: athrow
    //   3736: aload #7
    //   3738: invokevirtual getPackage : ()Ljava/lang/Package;
    //   3741: invokevirtual getName : ()Ljava/lang/String;
    //   3744: ifnull -> 3784
    //   3747: goto -> 3754
    //   3750: invokestatic a : (Ljava/lang/Throwable;)Ljava/lang/Throwable;
    //   3753: athrow
    //   3754: aload #7
    //   3756: invokevirtual getPackage : ()Ljava/lang/Package;
    //   3759: invokevirtual getName : ()Ljava/lang/String;
    //   3762: sipush #7835
    //   3765: sipush #28647
    //   3768: invokestatic a : (II)Ljava/lang/String;
    //   3771: invokevirtual startsWith : (Ljava/lang/String;)Z
    //   3774: ifne -> 3784
    //   3777: goto -> 3784
    //   3780: invokestatic a : (Ljava/lang/Throwable;)Ljava/lang/Throwable;
    //   3783: athrow
    //   3784: aload #6
    //   3786: iconst_1
    //   3787: invokevirtual setAccessible : (Z)V
    //   3790: aload #6
    //   3792: aconst_null
    //   3793: invokevirtual get : (Ljava/lang/Object;)Ljava/lang/Object;
    //   3796: pop
    //   3797: iinc #5, 1
    //   3800: iload_2
    //   3801: ifeq -> 3663
    //   3804: sipush #7836
    //   3807: sipush #-1663
    //   3810: invokestatic a : (II)Ljava/lang/String;
    //   3813: invokestatic forName : (Ljava/lang/String;)Ljava/lang/Class;
    //   3816: invokevirtual getDeclaredMethods : ()[Ljava/lang/reflect/Method;
    //   3819: astore_3
    //   3820: aload_3
    //   3821: arraylength
    //   3822: istore #4
    //   3824: iconst_0
    //   3825: istore #5
    //   3827: iload #5
    //   3829: iload #4
    //   3831: if_icmpge -> 3963
    //   3834: aload_3
    //   3835: iload #5
    //   3837: aaload
    //   3838: astore #6
    //   3840: aload #6
    //   3842: invokevirtual getParameterTypes : ()[Ljava/lang/Class;
    //   3845: pop
    //   3846: aload #6
    //   3848: invokevirtual getModifiers : ()I
    //   3851: invokestatic isStatic : (I)Z
    //   3854: ifeq -> 3949
    //   3857: aload #6
    //   3859: invokevirtual getParameterTypes : ()[Ljava/lang/Class;
    //   3862: arraylength
    //   3863: iconst_2
    //   3864: if_icmpne -> 3949
    //   3867: goto -> 3874
    //   3870: invokestatic a : (Ljava/lang/Throwable;)Ljava/lang/Throwable;
    //   3873: athrow
    //   3874: aload #6
    //   3876: invokevirtual getReturnType : ()Ljava/lang/Class;
    //   3879: getstatic java/lang/Void.TYPE : Ljava/lang/Class;
    //   3882: invokevirtual equals : (Ljava/lang/Object;)Z
    //   3885: ifeq -> 3949
    //   3888: goto -> 3895
    //   3891: invokestatic a : (Ljava/lang/Throwable;)Ljava/lang/Throwable;
    //   3894: athrow
    //   3895: aload #6
    //   3897: iconst_1
    //   3898: invokevirtual setAccessible : (Z)V
    //   3901: aload #6
    //   3903: aconst_null
    //   3904: iconst_2
    //   3905: anewarray java/lang/Object
    //   3908: dup
    //   3909: iconst_0
    //   3910: aload_0
    //   3911: aastore
    //   3912: dup
    //   3913: iconst_1
    //   3914: aload_1
    //   3915: ifnonnull -> 3933
    //   3918: goto -> 3925
    //   3921: invokestatic a : (Ljava/lang/Throwable;)Ljava/lang/Throwable;
    //   3924: athrow
    //   3925: aload_1
    //   3926: goto -> 3940
    //   3929: invokestatic a : (Ljava/lang/Throwable;)Ljava/lang/Throwable;
    //   3932: athrow
    //   3933: aload_1
    //   3934: checkcast [B
    //   3937: invokevirtual clone : ()Ljava/lang/Object;
    //   3940: aastore
    //   3941: invokevirtual invoke : (Ljava/lang/Object;[Ljava/lang/Object;)Ljava/lang/Object;
    //   3944: pop
    //   3945: iload_2
    //   3946: ifeq -> 3963
    //   3949: iinc #5, 1
    //   3952: iload_2
    //   3953: ifeq -> 3827
    //   3956: goto -> 3963
    //   3959: invokestatic a : (Ljava/lang/Throwable;)Ljava/lang/Throwable;
    //   3962: athrow
    //   3963: getstatic burp/Zgw0.ZL : Ljava/lang/String;
    //   3966: getstatic burp/Zshq.ZK : Ljava/lang/Object;
    //   3969: checkcast java/math/BigInteger
    //   3972: invokevirtual intValue : ()I
    //   3975: bipush #32
    //   3977: irem
    //   3978: invokestatic abs : (I)I
    //   3981: invokevirtual charAt : (I)C
    //   3984: getstatic burp/Zr3q.ZM : Ljava/lang/String;
    //   3987: getstatic burp/Zrnu.Zs : Ljava/lang/Object;
    //   3990: checkcast java/math/BigInteger
    //   3993: invokevirtual intValue : ()I
    //   3996: bipush #32
    //   3998: irem
    //   3999: invokestatic abs : (I)I
    //   4002: invokevirtual charAt : (I)C
    //   4005: if_icmpgt -> 4120
    //   4008: getstatic burp/Zr0g.Zf : Ljava/lang/String;
    //   4011: getstatic burp/Zlos.Zk : Ljava/lang/Object;
    //   4014: checkcast java/math/BigInteger
    //   4017: invokevirtual intValue : ()I
    //   4020: bipush #32
    //   4022: irem
    //   4023: invokestatic abs : (I)I
    //   4026: invokevirtual charAt : (I)C
    //   4029: getstatic burp/Zr0g.Zf : Ljava/lang/String;
    //   4032: getstatic burp/Zer.Zk : Ljava/lang/Object;
    //   4035: checkcast java/math/BigInteger
    //   4038: invokevirtual intValue : ()I
    //   4041: bipush #32
    //   4043: irem
    //   4044: invokestatic abs : (I)I
    //   4047: invokevirtual charAt : (I)C
    //   4050: if_icmpgt -> 4120
    //   4053: goto -> 4060
    //   4056: invokestatic a : (Ljava/lang/Throwable;)Ljava/lang/Throwable;
    //   4059: athrow
    //   4060: getstatic burp/Zllw.Zg : Ljava/lang/String;
    //   4063: getstatic burp/Zsde.Zx : Ljava/lang/Object;
    //   4066: checkcast java/math/BigInteger
    //   4069: invokevirtual intValue : ()I
    //   4072: bipush #32
    //   4074: irem
    //   4075: invokestatic abs : (I)I
    //   4078: invokevirtual charAt : (I)C
    //   4081: getstatic burp/Zb2s.Zq : Ljava/lang/String;
    //   4084: getstatic burp/Ztbf.Zv : Ljava/lang/Object;
    //   4087: checkcast java/math/BigInteger
    //   4090: invokevirtual intValue : ()I
    //   4093: bipush #32
    //   4095: irem
    //   4096: invokestatic abs : (I)I
    //   4099: invokevirtual charAt : (I)C
    //   4102: if_icmple -> 4120
    //   4105: goto -> 4112
    //   4108: invokestatic a : (Ljava/lang/Throwable;)Ljava/lang/Throwable;
    //   4111: athrow
    //   4112: iconst_1
    //   4113: goto -> 4121
    //   4116: invokestatic a : (Ljava/lang/Throwable;)Ljava/lang/Throwable;
    //   4119: athrow
    //   4120: iconst_0
    //   4121: ireturn
    //   4122: astore_3
    //   4123: new java/lang/Exception
    //   4126: dup
    //   4127: aload_3
    //   4128: invokevirtual getMessage : ()Ljava/lang/String;
    //   4131: invokespecial <init> : (Ljava/lang/String;)V
    //   4134: athrow
    // Exception table:
    //   from	to	target	type
    //   4	4121	4122	java/lang/Throwable
    //   395	410	410	java/lang/Throwable
    //   1412	1438	1438	java/lang/Throwable
    //   1519	1534	1534	java/lang/Throwable
    //   2716	2741	2744	java/lang/Throwable
    //   2796	2810	2813	java/lang/Throwable
    //   2803	2824	2827	java/lang/Throwable
    //   2817	2838	2841	java/lang/Throwable
    //   2831	2852	2855	java/lang/Throwable
    //   2845	2866	2869	java/lang/Throwable
    //   2859	2880	2883	java/lang/Throwable
    //   2873	2894	2897	java/lang/Throwable
    //   2887	2908	2911	java/lang/Throwable
    //   2901	2918	2921	java/lang/Throwable
    //   2957	2971	2974	java/lang/Throwable
    //   2964	2985	2988	java/lang/Throwable
    //   2978	2999	3002	java/lang/Throwable
    //   2992	3013	3016	java/lang/Throwable
    //   3006	3027	3030	java/lang/Throwable
    //   3020	3041	3044	java/lang/Throwable
    //   3034	3055	3058	java/lang/Throwable
    //   3048	3069	3072	java/lang/Throwable
    //   3062	3086	3089	java/lang/Throwable
    //   3150	3168	3171	java/lang/Throwable
    //   3159	3184	3187	java/lang/Throwable
    //   3175	3201	3204	java/lang/Throwable
    //   3191	3217	3220	java/lang/Throwable
    //   3208	3234	3237	java/lang/Throwable
    //   3224	3250	3253	java/lang/Throwable
    //   3241	3266	3269	java/lang/Throwable
    //   3257	3289	3292	java/lang/Throwable
    //   3273	3305	3308	java/lang/Throwable
    //   3296	3321	3324	java/lang/Throwable
    //   3312	3344	3347	java/lang/Throwable
    //   3328	3360	3363	java/lang/Throwable
    //   3351	3376	3379	java/lang/Throwable
    //   3367	3395	3398	java/lang/Throwable
    //   3525	3560	3563	java/lang/Throwable
    //   3567	3608	3611	java/lang/Throwable
    //   3676	3690	3690	java/lang/Throwable
    //   3701	3714	3717	java/lang/Throwable
    //   3706	3729	3732	java/lang/Throwable
    //   3721	3747	3750	java/lang/Throwable
    //   3736	3777	3780	java/lang/Throwable
    //   3840	3867	3870	java/lang/Throwable
    //   3857	3888	3891	java/lang/Throwable
    //   3874	3918	3921	java/lang/Throwable
    //   3895	3929	3929	java/lang/Throwable
    //   3940	3956	3959	java/lang/Throwable
    //   3963	4053	4056	java/lang/Throwable
    //   4008	4105	4108	java/lang/Throwable
    //   4060	4116	4116	java/lang/Throwable
  }
  
  static void ZX(Object paramObject) {
    Zl2q.ZI = a(7834, -15654);
    Zl2q.Zg = new BigInteger(a(7824, 6932));
    boolean bool = Zt2e.ZK();
    try {
      try {
        if (Zlv6.Zt.charAt(Math.abs(((BigInteger)Zlhm.ZT).intValue() % 32)) > Zrbp.Ze.charAt(Math.abs(((BigInteger)Zgw0.ZM).intValue() % 32))) {
          try {
            Zx54.Zf(Class.forName(a(7832, 17575)));
            if (bool)
              Zlp8.Zs(Class.forName(a(7826, -26025))); 
          } catch (Throwable throwable) {
            throw a(null);
          } 
          return;
        } 
      } catch (Throwable throwable) {
        throw a(null);
      } 
      Zlp8.Zs(Class.forName(a(7826, -26025)));
    } catch (Throwable throwable) {}
  }
  
  static void ZD(Object[] paramArrayOfObject, Object paramObject) throws Throwable {}
  
  static {
    // Byte code:
    //   0: bipush #12
    //   2: anewarray java/lang/String
    //   5: astore #5
    //   7: iconst_0
    //   8: istore_3
    //   9: ldc '3:,NHg8\\tB)kzK 36_i Iu^?<FhM^t\\tOKqR_\\t.??M\NaK p8UDfR %&Op/kg[?\\b43Nd??L_%[|,G"lR&v+JV\\f`D'(3uV49'
    //   11: dup
    //   12: astore_2
    //   13: invokevirtual length : ()I
    //   16: istore #4
    //   18: bipush #19
    //   20: istore_1
    //   21: iconst_m1
    //   22: istore_0
    //   23: bipush #81
    //   25: iinc #0, 1
    //   28: aload_2
    //   29: iload_0
    //   30: dup
    //   31: iload_1
    //   32: iadd
    //   33: invokevirtual substring : (II)Ljava/lang/String;
    //   36: iconst_m1
    //   37: goto -> 143
    //   40: aload #5
    //   42: swap
    //   43: iload_3
    //   44: iinc #3, 1
    //   47: swap
    //   48: aastore
    //   49: iload_0
    //   50: iload_1
    //   51: iadd
    //   52: dup
    //   53: istore_0
    //   54: iload #4
    //   56: if_icmpge -> 68
    //   59: aload_2
    //   60: iload_0
    //   61: invokevirtual charAt : (I)C
    //   64: istore_1
    //   65: goto -> 23
    //   68: ldc 'S9bU}]"~$}\\t*yN'
    //   70: dup
    //   71: astore_2
    //   72: invokevirtual length : ()I
    //   75: istore #4
    //   77: bipush #32
    //   79: istore_1
    //   80: iconst_m1
    //   81: istore_0
    //   82: bipush #30
    //   84: iinc #0, 1
    //   87: aload_2
    //   88: iload_0
    //   89: dup
    //   90: iload_1
    //   91: iadd
    //   92: invokevirtual substring : (II)Ljava/lang/String;
    //   95: iconst_0
    //   96: goto -> 143
    //   99: aload #5
    //   101: swap
    //   102: iload_3
    //   103: iinc #3, 1
    //   106: swap
    //   107: aastore
    //   108: iload_0
    //   109: iload_1
    //   110: iadd
    //   111: dup
    //   112: istore_0
    //   113: iload #4
    //   115: if_icmpge -> 127
    //   118: aload_2
    //   119: iload_0
    //   120: invokevirtual charAt : (I)C
    //   123: istore_1
    //   124: goto -> 82
    //   127: aload #5
    //   129: putstatic burp/Zsde.a : [Ljava/lang/String;
    //   132: bipush #12
    //   134: anewarray java/lang/String
    //   137: putstatic burp/Zsde.b : [Ljava/lang/String;
    //   140: goto -> 300
    //   143: dup_x2
    //   144: pop
    //   145: invokevirtual toCharArray : ()[C
    //   148: dup_x1
    //   149: arraylength
    //   150: dup_x2
    //   151: pop
    //   152: iconst_0
    //   153: istore #6
    //   155: dup2_x1
    //   156: pop2
    //   157: dup_x2
    //   158: iconst_1
    //   159: if_icmpgt -> 259
    //   162: dup2
    //   163: swap
    //   164: iload #6
    //   166: dup2_x1
    //   167: caload
    //   168: swap
    //   169: iload #6
    //   171: bipush #7
    //   173: irem
    //   174: tableswitch default -> 241, 0 -> 212, 1 -> 217, 2 -> 221, 3 -> 226, 4 -> 231, 5 -> 236
    //   212: bipush #107
    //   214: goto -> 243
    //   217: iconst_3
    //   218: goto -> 243
    //   221: bipush #113
    //   223: goto -> 243
    //   226: bipush #40
    //   228: goto -> 243
    //   231: bipush #124
    //   233: goto -> 243
    //   236: bipush #43
    //   238: goto -> 243
    //   241: bipush #58
    //   243: ixor
    //   244: ixor
    //   245: i2c
    //   246: castore
    //   247: iinc #6, 1
    //   250: dup
    //   251: ifne -> 259
    //   254: dup2
    //   255: dup_x1
    //   256: goto -> 166
    //   259: dup2_x1
    //   260: pop2
    //   261: dup_x2
    //   262: iload #6
    //   264: if_icmpgt -> 162
    //   267: pop
    //   268: new java/lang/String
    //   271: dup_x1
    //   272: swap
    //   273: invokespecial <init> : ([C)V
    //   276: invokevirtual intern : ()Ljava/lang/String;
    //   279: swap
    //   280: pop
    //   281: swap
    //   282: tableswitch default -> 40, 0 -> 99
    //   300: sipush #7827
    //   303: sipush #8962
    //   306: invokestatic a : (II)Ljava/lang/String;
    //   309: putstatic burp/Zsde.Zi : Ljava/lang/String;
    //   312: new java/math/BigInteger
    //   315: dup
    //   316: sipush #7838
    //   319: sipush #-13316
    //   322: invokestatic a : (II)Ljava/lang/String;
    //   325: invokespecial <init> : (Ljava/lang/String;)V
    //   328: putstatic burp/Zsde.Zx : Ljava/lang/Object;
    //   331: return
  }
  
  private static Throwable a(Throwable paramThrowable) {
    return paramThrowable;
  }
  
  private static String a(int paramInt1, int paramInt2) {
    int i = (paramInt1 ^ 0x1E99) & 0xFFFF;
    if (b[i] == null) {
      char[] arrayOfChar = a[i].toCharArray();
      switch (arrayOfChar[0] & 0xFF) {
        case 0:
        
        case 1:
        
        case 2:
        
        case 3:
        
        case 4:
        
        case 5:
        
        case 6:
        
        case 7:
        
        case 8:
        
        case 9:
        
        case 10:
        
        case 11:
        
        case 12:
        
        case 13:
        
        case 14:
        
        case 15:
        
        case 16:
        
        case 17:
        
        case 18:
        
        case 19:
        
        case 20:
        
        case 21:
        
        case 22:
        
        case 23:
        
        case 24:
        
        case 25:
        
        case 26:
        
        case 27:
        
        case 28:
        
        case 29:
        
        case 30:
        
        case 31:
        
        case 32:
        
        case 33:
        
        case 34:
        
        case 35:
        
        case 36:
        
        case 37:
        
        case 38:
        
        case 39:
        
        case 40:
        
        case 41:
        
        case 42:
        
        case 43:
        
        case 44:
        
        case 45:
        
        case 46:
        
        case 47:
        
        case 48:
        
        case 49:
        
        case 50:
        
        case 51:
        
        case 52:
        
        case 53:
        
        case 54:
        
        case 55:
        
        case 56:
        
        case 57:
        
        case 58:
        
        case 59:
        
        case 60:
        
        case 61:
        
        case 62:
        
        case 63:
        
        case 64:
        
        case 65:
        
        case 66:
        
        case 67:
        
        case 68:
        
        case 69:
        
        case 70:
        
        case 71:
        
        case 72:
        
        case 73:
        
        case 74:
        
        case 75:
        
        case 76:
        
        case 77:
        
        case 78:
        
        case 79:
        
        case 80:
        
        case 81:
        
        case 82:
        
        case 83:
        
        case 84:
        
        case 85:
        
        case 86:
        
        case 87:
        
        case 88:
        
        case 89:
        
        case 90:
        
        case 91:
        
        case 92:
        
        case 93:
        
        case 94:
        
        case 95:
        
        case 96:
        
        case 97:
        
        case 98:
        
        case 99:
        
        case 100:
        
        case 101:
        
        case 102:
        
        case 103:
        
        case 104:
        
        case 105:
        
        case 106:
        
        case 107:
        
        case 108:
        
        case 109:
        
        case 110:
        
        case 111:
        
        case 112:
        
        case 113:
        
        case 114:
        
        case 115:
        
        case 116:
        
        case 117:
        
        case 118:
        
        case 119:
        
        case 120:
        
        case 121:
        
        case 122:
        
        case 123:
        
        case 124:
        
        case 125:
        
        case 126:
        
        case 127:
        
        case 128:
        
        case 129:
        
        case 130:
        
        case 131:
        
        case 132:
        
        case 133:
        
        case 134:
        
        case 135:
        
        case 136:
        
        case 137:
        
        case 138:
        
        case 139:
        
        case 140:
        
        case 141:
        
        case 142:
        
        case 143:
        
        case 144:
        
        case 145:
        
        case 146:
        
        case 147:
        
        case 148:
        
        case 149:
        
        case 150:
        
        case 151:
        
        case 152:
        
        case 153:
        
        case 154:
        
        case 155:
        
        case 156:
        
        case 157:
        
        case 158:
        
        case 159:
        
        case 160:
        
        case 161:
        
        case 162:
        
        case 163:
        
        case 164:
        
        case 165:
        
        case 166:
        
        case 167:
        
        case 168:
        
        case 169:
        
        case 170:
        
        case 171:
        
        case 172:
        
        case 173:
        
        case 174:
        
        case 175:
        
        case 176:
        
        case 177:
        
        case 178:
        
        case 179:
        
        case 180:
        
        case 181:
        
        case 182:
        
        case 183:
        
        case 184:
        
        case 185:
        
        case 186:
        
        case 187:
        
        case 188:
        
        case 189:
        
        case 190:
        
        case 191:
        
        case 192:
        
        case 193:
        
        case 194:
        
        case 195:
        
        case 196:
        
        case 197:
        
        case 198:
        
        case 199:
        
        case 200:
        
        case 201:
        
        case 202:
        
        case 203:
        
        case 204:
        
        case 205:
        
        case 206:
        
        case 207:
        
        case 208:
        
        case 209:
        
        case 210:
        
        case 211:
        
        case 212:
        
        case 213:
        
        case 214:
        
        case 215:
        
        case 216:
        
        case 217:
        
        case 218:
        
        case 219:
        
        case 220:
        
        case 221:
        
        case 222:
        
        case 223:
        
        case 224:
        
        case 225:
        
        case 226:
        
        case 227:
        
        case 228:
        
        case 229:
        
        case 230:
        
        case 231:
        
        case 232:
        
        case 233:
        
        case 234:
        
        case 235:
        
        case 236:
        
        case 237:
        
        case 238:
        
        case 239:
        
        case 240:
        
        case 241:
        
        case 242:
        
        case 243:
        
        case 244:
        
        case 245:
        
        case 246:
        
        case 247:
        
        case 248:
        
        case 249:
        
        case 250:
        
        case 251:
        
        case 252:
        
        case 253:
        
        case 254:
        
        default:
          break;
      } 
      byte b1 = 15;
      int j = (paramInt2 & 0xFF) - b1;
      if (j < 0)
        j += 256; 
      int k = ((paramInt2 & 0xFFFF) >>> 8) - b1;
      if (k < 0)
        k += 256; 
      for (byte b2 = 0; b2 < arrayOfChar.length; b2++) {
        int m = b2 % 2;
        if (m == 0) {
          arrayOfChar[b2] = (char)(arrayOfChar[b2] ^ j);
          j = ((j >>> 3 | j << 5) ^ arrayOfChar[b2]) & 0xFF;
        } else {
          arrayOfChar[b2] = (char)(arrayOfChar[b2] ^ k);
          k = ((k >>> 3 | k << 5) ^ arrayOfChar[b2]) & 0xFF;
        } 
      } 
      b[i] = (new String(arrayOfChar)).intern();
    } 
    return b[i];
  }
}


/* Location:              C:\Program Files\BurpSuitePro\burpsuite_pro.jar!\burp\Zsde.class
 * Java compiler version: 21 (65.0)
 * JD-Core Version:       1.1.3
 */