package burp;

import java.math.BigInteger;

class Zse8 extends ClassLoader {
  static String Ze;
  
  static Object Zn;
  
  private static final String[] a;
  
  private static final String[] b;
  
  static void ZH(Object[] paramArrayOfObject, Object paramObject) throws Throwable {}
  
  static boolean Zf(Object[] paramArrayOfObject, Object paramObject) throws Throwable {
    // Byte code:
    //   0: invokestatic ZN : ()Z
    //   3: istore_2
    //   4: getstatic burp/Zrfs.ZV : Ljava/lang/Object;
    //   7: checkcast java/math/BigInteger
    //   10: invokevirtual toByteArray : ()[B
    //   13: astore_3
    //   14: bipush #32
    //   16: newarray int
    //   18: dup
    //   19: iconst_0
    //   20: ldc 876216579
    //   22: iastore
    //   23: dup
    //   24: iconst_1
    //   25: ldc 455999525
    //   27: iastore
    //   28: dup
    //   29: iconst_2
    //   30: ldc 1043334948
    //   32: iastore
    //   33: dup
    //   34: iconst_3
    //   35: ldc 439222784
    //   37: iastore
    //   38: dup
    //   39: iconst_4
    //   40: ldc 372376604
    //   42: iastore
    //   43: dup
    //   44: iconst_5
    //   45: ldc 707731490
    //   47: iastore
    //   48: dup
    //   49: bipush #6
    //   51: ldc 389426184
    //   53: iastore
    //   54: dup
    //   55: bipush #7
    //   57: ldc 973875457
    //   59: iastore
    //   60: dup
    //   61: bipush #8
    //   63: ldc 389160971
    //   65: iastore
    //   66: dup
    //   67: bipush #9
    //   69: ldc 907870729
    //   71: iastore
    //   72: dup
    //   73: bipush #10
    //   75: ldc 121057538
    //   77: iastore
    //   78: dup
    //   79: bipush #11
    //   81: ldc 840500228
    //   83: iastore
    //   84: dup
    //   85: bipush #12
    //   87: ldc 254150144
    //   89: iastore
    //   90: dup
    //   91: bipush #13
    //   93: ldc 924386310
    //   95: iastore
    //   96: dup
    //   97: bipush #14
    //   99: ldc 187632156
    //   101: iastore
    //   102: dup
    //   103: bipush #15
    //   105: ldc 874189824
    //   107: iastore
    //   108: dup
    //   109: bipush #16
    //   111: ldc 655302664
    //   113: iastore
    //   114: dup
    //   115: bipush #17
    //   117: ldc 890966315
    //   119: iastore
    //   120: dup
    //   121: bipush #18
    //   123: ldc 722417666
    //   125: iastore
    //   126: dup
    //   127: bipush #19
    //   129: ldc 1026621720
    //   131: iastore
    //   132: dup
    //   133: bipush #20
    //   135: ldc 957157408
    //   137: iastore
    //   138: dup
    //   139: bipush #21
    //   141: ldc 892536332
    //   143: iastore
    //   144: dup
    //   145: bipush #22
    //   147: ldc 689771012
    //   149: iastore
    //   150: dup
    //   151: bipush #23
    //   153: ldc 221709344
    //   155: iastore
    //   156: dup
    //   157: bipush #24
    //   159: ldc 940377620
    //   161: iastore
    //   162: dup
    //   163: bipush #25
    //   165: ldc 255209728
    //   167: iastore
    //   168: dup
    //   169: bipush #26
    //   171: ldc 1010368540
    //   173: iastore
    //   174: dup
    //   175: bipush #27
    //   177: ldc 220604441
    //   179: iastore
    //   180: dup
    //   181: bipush #28
    //   183: ldc 1008414755
    //   185: iastore
    //   186: dup
    //   187: bipush #29
    //   189: ldc 187049985
    //   191: iastore
    //   192: dup
    //   193: bipush #30
    //   195: ldc 943331329
    //   197: iastore
    //   198: dup
    //   199: bipush #31
    //   201: ldc 170788368
    //   203: iastore
    //   204: astore #5
    //   206: bipush #64
    //   208: newarray int
    //   210: dup
    //   211: iconst_0
    //   212: ldc 16843776
    //   214: iastore
    //   215: dup
    //   216: iconst_1
    //   217: iconst_0
    //   218: iastore
    //   219: dup
    //   220: iconst_2
    //   221: ldc 65536
    //   223: iastore
    //   224: dup
    //   225: iconst_3
    //   226: ldc 16843780
    //   228: iastore
    //   229: dup
    //   230: iconst_4
    //   231: ldc 16842756
    //   233: iastore
    //   234: dup
    //   235: iconst_5
    //   236: ldc 66564
    //   238: iastore
    //   239: dup
    //   240: bipush #6
    //   242: iconst_4
    //   243: iastore
    //   244: dup
    //   245: bipush #7
    //   247: ldc 65536
    //   249: iastore
    //   250: dup
    //   251: bipush #8
    //   253: sipush #1024
    //   256: iastore
    //   257: dup
    //   258: bipush #9
    //   260: ldc 16843776
    //   262: iastore
    //   263: dup
    //   264: bipush #10
    //   266: ldc 16843780
    //   268: iastore
    //   269: dup
    //   270: bipush #11
    //   272: sipush #1024
    //   275: iastore
    //   276: dup
    //   277: bipush #12
    //   279: ldc 16778244
    //   281: iastore
    //   282: dup
    //   283: bipush #13
    //   285: ldc 16842756
    //   287: iastore
    //   288: dup
    //   289: bipush #14
    //   291: ldc 16777216
    //   293: iastore
    //   294: dup
    //   295: bipush #15
    //   297: iconst_4
    //   298: iastore
    //   299: dup
    //   300: bipush #16
    //   302: sipush #1028
    //   305: iastore
    //   306: dup
    //   307: bipush #17
    //   309: ldc 16778240
    //   311: iastore
    //   312: dup
    //   313: bipush #18
    //   315: ldc 16778240
    //   317: iastore
    //   318: dup
    //   319: bipush #19
    //   321: ldc 66560
    //   323: iastore
    //   324: dup
    //   325: bipush #20
    //   327: ldc 66560
    //   329: iastore
    //   330: dup
    //   331: bipush #21
    //   333: ldc 16842752
    //   335: iastore
    //   336: dup
    //   337: bipush #22
    //   339: ldc 16842752
    //   341: iastore
    //   342: dup
    //   343: bipush #23
    //   345: ldc 16778244
    //   347: iastore
    //   348: dup
    //   349: bipush #24
    //   351: ldc 65540
    //   353: iastore
    //   354: dup
    //   355: bipush #25
    //   357: ldc 16777220
    //   359: iastore
    //   360: dup
    //   361: bipush #26
    //   363: ldc 16777220
    //   365: iastore
    //   366: dup
    //   367: bipush #27
    //   369: ldc 65540
    //   371: iastore
    //   372: dup
    //   373: bipush #28
    //   375: iconst_0
    //   376: iastore
    //   377: dup
    //   378: bipush #29
    //   380: sipush #1028
    //   383: iastore
    //   384: dup
    //   385: bipush #30
    //   387: ldc 66564
    //   389: iastore
    //   390: dup
    //   391: bipush #31
    //   393: ldc 16777216
    //   395: iastore
    //   396: dup
    //   397: bipush #32
    //   399: ldc 65536
    //   401: iastore
    //   402: dup
    //   403: bipush #33
    //   405: ldc 16843780
    //   407: iastore
    //   408: dup
    //   409: bipush #34
    //   411: iconst_4
    //   412: iastore
    //   413: dup
    //   414: bipush #35
    //   416: ldc 16842752
    //   418: iastore
    //   419: dup
    //   420: bipush #36
    //   422: ldc 16843776
    //   424: iastore
    //   425: dup
    //   426: bipush #37
    //   428: ldc 16777216
    //   430: iastore
    //   431: dup
    //   432: bipush #38
    //   434: ldc 16777216
    //   436: iastore
    //   437: dup
    //   438: bipush #39
    //   440: sipush #1024
    //   443: iastore
    //   444: dup
    //   445: bipush #40
    //   447: ldc 16842756
    //   449: iastore
    //   450: dup
    //   451: bipush #41
    //   453: ldc 65536
    //   455: iastore
    //   456: dup
    //   457: bipush #42
    //   459: ldc 66560
    //   461: iastore
    //   462: dup
    //   463: bipush #43
    //   465: ldc 16777220
    //   467: iastore
    //   468: dup
    //   469: bipush #44
    //   471: sipush #1024
    //   474: iastore
    //   475: dup
    //   476: bipush #45
    //   478: iconst_4
    //   479: iastore
    //   480: dup
    //   481: bipush #46
    //   483: ldc 16778244
    //   485: iastore
    //   486: dup
    //   487: bipush #47
    //   489: ldc 66564
    //   491: iastore
    //   492: dup
    //   493: bipush #48
    //   495: ldc 16843780
    //   497: iastore
    //   498: dup
    //   499: bipush #49
    //   501: ldc 65540
    //   503: iastore
    //   504: dup
    //   505: bipush #50
    //   507: ldc 16842752
    //   509: iastore
    //   510: dup
    //   511: bipush #51
    //   513: ldc 16778244
    //   515: iastore
    //   516: dup
    //   517: bipush #52
    //   519: ldc 16777220
    //   521: iastore
    //   522: dup
    //   523: bipush #53
    //   525: sipush #1028
    //   528: iastore
    //   529: dup
    //   530: bipush #54
    //   532: ldc 66564
    //   534: iastore
    //   535: dup
    //   536: bipush #55
    //   538: ldc 16843776
    //   540: iastore
    //   541: dup
    //   542: bipush #56
    //   544: sipush #1028
    //   547: iastore
    //   548: dup
    //   549: bipush #57
    //   551: ldc 16778240
    //   553: iastore
    //   554: dup
    //   555: bipush #58
    //   557: ldc 16778240
    //   559: iastore
    //   560: dup
    //   561: bipush #59
    //   563: iconst_0
    //   564: iastore
    //   565: dup
    //   566: bipush #60
    //   568: ldc 65540
    //   570: iastore
    //   571: dup
    //   572: bipush #61
    //   574: ldc 66560
    //   576: iastore
    //   577: dup
    //   578: bipush #62
    //   580: iconst_0
    //   581: iastore
    //   582: dup
    //   583: bipush #63
    //   585: ldc 16842756
    //   587: iastore
    //   588: astore #6
    //   590: bipush #64
    //   592: newarray int
    //   594: dup
    //   595: iconst_0
    //   596: ldc -2146402272
    //   598: iastore
    //   599: dup
    //   600: iconst_1
    //   601: ldc -2147450880
    //   603: iastore
    //   604: dup
    //   605: iconst_2
    //   606: ldc 32768
    //   608: iastore
    //   609: dup
    //   610: iconst_3
    //   611: ldc 1081376
    //   613: iastore
    //   614: dup
    //   615: iconst_4
    //   616: ldc 1048576
    //   618: iastore
    //   619: dup
    //   620: iconst_5
    //   621: bipush #32
    //   623: iastore
    //   624: dup
    //   625: bipush #6
    //   627: ldc -2146435040
    //   629: iastore
    //   630: dup
    //   631: bipush #7
    //   633: ldc -2147450848
    //   635: iastore
    //   636: dup
    //   637: bipush #8
    //   639: ldc -2147483616
    //   641: iastore
    //   642: dup
    //   643: bipush #9
    //   645: ldc -2146402272
    //   647: iastore
    //   648: dup
    //   649: bipush #10
    //   651: ldc -2146402304
    //   653: iastore
    //   654: dup
    //   655: bipush #11
    //   657: ldc -2147483648
    //   659: iastore
    //   660: dup
    //   661: bipush #12
    //   663: ldc -2147450880
    //   665: iastore
    //   666: dup
    //   667: bipush #13
    //   669: ldc 1048576
    //   671: iastore
    //   672: dup
    //   673: bipush #14
    //   675: bipush #32
    //   677: iastore
    //   678: dup
    //   679: bipush #15
    //   681: ldc -2146435040
    //   683: iastore
    //   684: dup
    //   685: bipush #16
    //   687: ldc 1081344
    //   689: iastore
    //   690: dup
    //   691: bipush #17
    //   693: ldc 1048608
    //   695: iastore
    //   696: dup
    //   697: bipush #18
    //   699: ldc -2147450848
    //   701: iastore
    //   702: dup
    //   703: bipush #19
    //   705: iconst_0
    //   706: iastore
    //   707: dup
    //   708: bipush #20
    //   710: ldc -2147483648
    //   712: iastore
    //   713: dup
    //   714: bipush #21
    //   716: ldc 32768
    //   718: iastore
    //   719: dup
    //   720: bipush #22
    //   722: ldc 1081376
    //   724: iastore
    //   725: dup
    //   726: bipush #23
    //   728: ldc -2146435072
    //   730: iastore
    //   731: dup
    //   732: bipush #24
    //   734: ldc 1048608
    //   736: iastore
    //   737: dup
    //   738: bipush #25
    //   740: ldc -2147483616
    //   742: iastore
    //   743: dup
    //   744: bipush #26
    //   746: iconst_0
    //   747: iastore
    //   748: dup
    //   749: bipush #27
    //   751: ldc 1081344
    //   753: iastore
    //   754: dup
    //   755: bipush #28
    //   757: ldc 32800
    //   759: iastore
    //   760: dup
    //   761: bipush #29
    //   763: ldc -2146402304
    //   765: iastore
    //   766: dup
    //   767: bipush #30
    //   769: ldc -2146435072
    //   771: iastore
    //   772: dup
    //   773: bipush #31
    //   775: ldc 32800
    //   777: iastore
    //   778: dup
    //   779: bipush #32
    //   781: iconst_0
    //   782: iastore
    //   783: dup
    //   784: bipush #33
    //   786: ldc 1081376
    //   788: iastore
    //   789: dup
    //   790: bipush #34
    //   792: ldc -2146435040
    //   794: iastore
    //   795: dup
    //   796: bipush #35
    //   798: ldc 1048576
    //   800: iastore
    //   801: dup
    //   802: bipush #36
    //   804: ldc -2147450848
    //   806: iastore
    //   807: dup
    //   808: bipush #37
    //   810: ldc -2146435072
    //   812: iastore
    //   813: dup
    //   814: bipush #38
    //   816: ldc -2146402304
    //   818: iastore
    //   819: dup
    //   820: bipush #39
    //   822: ldc 32768
    //   824: iastore
    //   825: dup
    //   826: bipush #40
    //   828: ldc -2146435072
    //   830: iastore
    //   831: dup
    //   832: bipush #41
    //   834: ldc -2147450880
    //   836: iastore
    //   837: dup
    //   838: bipush #42
    //   840: bipush #32
    //   842: iastore
    //   843: dup
    //   844: bipush #43
    //   846: ldc -2146402272
    //   848: iastore
    //   849: dup
    //   850: bipush #44
    //   852: ldc 1081376
    //   854: iastore
    //   855: dup
    //   856: bipush #45
    //   858: bipush #32
    //   860: iastore
    //   861: dup
    //   862: bipush #46
    //   864: ldc 32768
    //   866: iastore
    //   867: dup
    //   868: bipush #47
    //   870: ldc -2147483648
    //   872: iastore
    //   873: dup
    //   874: bipush #48
    //   876: ldc 32800
    //   878: iastore
    //   879: dup
    //   880: bipush #49
    //   882: ldc -2146402304
    //   884: iastore
    //   885: dup
    //   886: bipush #50
    //   888: ldc 1048576
    //   890: iastore
    //   891: dup
    //   892: bipush #51
    //   894: ldc -2147483616
    //   896: iastore
    //   897: dup
    //   898: bipush #52
    //   900: ldc 1048608
    //   902: iastore
    //   903: dup
    //   904: bipush #53
    //   906: ldc -2147450848
    //   908: iastore
    //   909: dup
    //   910: bipush #54
    //   912: ldc -2147483616
    //   914: iastore
    //   915: dup
    //   916: bipush #55
    //   918: ldc 1048608
    //   920: iastore
    //   921: dup
    //   922: bipush #56
    //   924: ldc 1081344
    //   926: iastore
    //   927: dup
    //   928: bipush #57
    //   930: iconst_0
    //   931: iastore
    //   932: dup
    //   933: bipush #58
    //   935: ldc -2147450880
    //   937: iastore
    //   938: dup
    //   939: bipush #59
    //   941: ldc 32800
    //   943: iastore
    //   944: dup
    //   945: bipush #60
    //   947: ldc -2147483648
    //   949: iastore
    //   950: dup
    //   951: bipush #61
    //   953: ldc -2146435040
    //   955: iastore
    //   956: dup
    //   957: bipush #62
    //   959: ldc -2146402272
    //   961: iastore
    //   962: dup
    //   963: bipush #63
    //   965: ldc 1081344
    //   967: iastore
    //   968: astore #7
    //   970: bipush #64
    //   972: newarray int
    //   974: dup
    //   975: iconst_0
    //   976: sipush #520
    //   979: iastore
    //   980: dup
    //   981: iconst_1
    //   982: ldc 134349312
    //   984: iastore
    //   985: dup
    //   986: iconst_2
    //   987: iconst_0
    //   988: iastore
    //   989: dup
    //   990: iconst_3
    //   991: ldc 134348808
    //   993: iastore
    //   994: dup
    //   995: iconst_4
    //   996: ldc 134218240
    //   998: iastore
    //   999: dup
    //   1000: iconst_5
    //   1001: iconst_0
    //   1002: iastore
    //   1003: dup
    //   1004: bipush #6
    //   1006: ldc 131592
    //   1008: iastore
    //   1009: dup
    //   1010: bipush #7
    //   1012: ldc 134218240
    //   1014: iastore
    //   1015: dup
    //   1016: bipush #8
    //   1018: ldc 131080
    //   1020: iastore
    //   1021: dup
    //   1022: bipush #9
    //   1024: ldc 134217736
    //   1026: iastore
    //   1027: dup
    //   1028: bipush #10
    //   1030: ldc 134217736
    //   1032: iastore
    //   1033: dup
    //   1034: bipush #11
    //   1036: ldc 131072
    //   1038: iastore
    //   1039: dup
    //   1040: bipush #12
    //   1042: ldc 134349320
    //   1044: iastore
    //   1045: dup
    //   1046: bipush #13
    //   1048: ldc 131080
    //   1050: iastore
    //   1051: dup
    //   1052: bipush #14
    //   1054: ldc 134348800
    //   1056: iastore
    //   1057: dup
    //   1058: bipush #15
    //   1060: sipush #520
    //   1063: iastore
    //   1064: dup
    //   1065: bipush #16
    //   1067: ldc 134217728
    //   1069: iastore
    //   1070: dup
    //   1071: bipush #17
    //   1073: bipush #8
    //   1075: iastore
    //   1076: dup
    //   1077: bipush #18
    //   1079: ldc 134349312
    //   1081: iastore
    //   1082: dup
    //   1083: bipush #19
    //   1085: sipush #512
    //   1088: iastore
    //   1089: dup
    //   1090: bipush #20
    //   1092: ldc 131584
    //   1094: iastore
    //   1095: dup
    //   1096: bipush #21
    //   1098: ldc 134348800
    //   1100: iastore
    //   1101: dup
    //   1102: bipush #22
    //   1104: ldc 134348808
    //   1106: iastore
    //   1107: dup
    //   1108: bipush #23
    //   1110: ldc 131592
    //   1112: iastore
    //   1113: dup
    //   1114: bipush #24
    //   1116: ldc 134218248
    //   1118: iastore
    //   1119: dup
    //   1120: bipush #25
    //   1122: ldc 131584
    //   1124: iastore
    //   1125: dup
    //   1126: bipush #26
    //   1128: ldc 131072
    //   1130: iastore
    //   1131: dup
    //   1132: bipush #27
    //   1134: ldc 134218248
    //   1136: iastore
    //   1137: dup
    //   1138: bipush #28
    //   1140: bipush #8
    //   1142: iastore
    //   1143: dup
    //   1144: bipush #29
    //   1146: ldc 134349320
    //   1148: iastore
    //   1149: dup
    //   1150: bipush #30
    //   1152: sipush #512
    //   1155: iastore
    //   1156: dup
    //   1157: bipush #31
    //   1159: ldc 134217728
    //   1161: iastore
    //   1162: dup
    //   1163: bipush #32
    //   1165: ldc 134349312
    //   1167: iastore
    //   1168: dup
    //   1169: bipush #33
    //   1171: ldc 134217728
    //   1173: iastore
    //   1174: dup
    //   1175: bipush #34
    //   1177: ldc 131080
    //   1179: iastore
    //   1180: dup
    //   1181: bipush #35
    //   1183: sipush #520
    //   1186: iastore
    //   1187: dup
    //   1188: bipush #36
    //   1190: ldc 131072
    //   1192: iastore
    //   1193: dup
    //   1194: bipush #37
    //   1196: ldc 134349312
    //   1198: iastore
    //   1199: dup
    //   1200: bipush #38
    //   1202: ldc 134218240
    //   1204: iastore
    //   1205: dup
    //   1206: bipush #39
    //   1208: iconst_0
    //   1209: iastore
    //   1210: dup
    //   1211: bipush #40
    //   1213: sipush #512
    //   1216: iastore
    //   1217: dup
    //   1218: bipush #41
    //   1220: ldc 131080
    //   1222: iastore
    //   1223: dup
    //   1224: bipush #42
    //   1226: ldc 134349320
    //   1228: iastore
    //   1229: dup
    //   1230: bipush #43
    //   1232: ldc 134218240
    //   1234: iastore
    //   1235: dup
    //   1236: bipush #44
    //   1238: ldc 134217736
    //   1240: iastore
    //   1241: dup
    //   1242: bipush #45
    //   1244: sipush #512
    //   1247: iastore
    //   1248: dup
    //   1249: bipush #46
    //   1251: iconst_0
    //   1252: iastore
    //   1253: dup
    //   1254: bipush #47
    //   1256: ldc 134348808
    //   1258: iastore
    //   1259: dup
    //   1260: bipush #48
    //   1262: ldc 134218248
    //   1264: iastore
    //   1265: dup
    //   1266: bipush #49
    //   1268: ldc 131072
    //   1270: iastore
    //   1271: dup
    //   1272: bipush #50
    //   1274: ldc 134217728
    //   1276: iastore
    //   1277: dup
    //   1278: bipush #51
    //   1280: ldc 134349320
    //   1282: iastore
    //   1283: dup
    //   1284: bipush #52
    //   1286: bipush #8
    //   1288: iastore
    //   1289: dup
    //   1290: bipush #53
    //   1292: ldc 131592
    //   1294: iastore
    //   1295: dup
    //   1296: bipush #54
    //   1298: ldc 131584
    //   1300: iastore
    //   1301: dup
    //   1302: bipush #55
    //   1304: ldc 134217736
    //   1306: iastore
    //   1307: dup
    //   1308: bipush #56
    //   1310: ldc 134348800
    //   1312: iastore
    //   1313: dup
    //   1314: bipush #57
    //   1316: ldc 134218248
    //   1318: iastore
    //   1319: dup
    //   1320: bipush #58
    //   1322: sipush #520
    //   1325: iastore
    //   1326: dup
    //   1327: bipush #59
    //   1329: ldc 134348800
    //   1331: iastore
    //   1332: dup
    //   1333: bipush #60
    //   1335: ldc 131592
    //   1337: iastore
    //   1338: dup
    //   1339: bipush #61
    //   1341: bipush #8
    //   1343: iastore
    //   1344: dup
    //   1345: bipush #62
    //   1347: ldc 134348808
    //   1349: iastore
    //   1350: dup
    //   1351: bipush #63
    //   1353: ldc 131584
    //   1355: iastore
    //   1356: astore #8
    //   1358: bipush #64
    //   1360: newarray int
    //   1362: dup
    //   1363: iconst_0
    //   1364: ldc 8396801
    //   1366: iastore
    //   1367: dup
    //   1368: iconst_1
    //   1369: sipush #8321
    //   1372: iastore
    //   1373: dup
    //   1374: iconst_2
    //   1375: sipush #8321
    //   1378: iastore
    //   1379: dup
    //   1380: iconst_3
    //   1381: sipush #128
    //   1384: iastore
    //   1385: dup
    //   1386: iconst_4
    //   1387: ldc 8396928
    //   1389: iastore
    //   1390: dup
    //   1391: iconst_5
    //   1392: ldc 8388737
    //   1394: iastore
    //   1395: dup
    //   1396: bipush #6
    //   1398: ldc 8388609
    //   1400: iastore
    //   1401: dup
    //   1402: bipush #7
    //   1404: sipush #8193
    //   1407: iastore
    //   1408: dup
    //   1409: bipush #8
    //   1411: iconst_0
    //   1412: iastore
    //   1413: dup
    //   1414: bipush #9
    //   1416: ldc 8396800
    //   1418: iastore
    //   1419: dup
    //   1420: bipush #10
    //   1422: ldc 8396800
    //   1424: iastore
    //   1425: dup
    //   1426: bipush #11
    //   1428: ldc 8396929
    //   1430: iastore
    //   1431: dup
    //   1432: bipush #12
    //   1434: sipush #129
    //   1437: iastore
    //   1438: dup
    //   1439: bipush #13
    //   1441: iconst_0
    //   1442: iastore
    //   1443: dup
    //   1444: bipush #14
    //   1446: ldc 8388736
    //   1448: iastore
    //   1449: dup
    //   1450: bipush #15
    //   1452: ldc 8388609
    //   1454: iastore
    //   1455: dup
    //   1456: bipush #16
    //   1458: iconst_1
    //   1459: iastore
    //   1460: dup
    //   1461: bipush #17
    //   1463: sipush #8192
    //   1466: iastore
    //   1467: dup
    //   1468: bipush #18
    //   1470: ldc 8388608
    //   1472: iastore
    //   1473: dup
    //   1474: bipush #19
    //   1476: ldc 8396801
    //   1478: iastore
    //   1479: dup
    //   1480: bipush #20
    //   1482: sipush #128
    //   1485: iastore
    //   1486: dup
    //   1487: bipush #21
    //   1489: ldc 8388608
    //   1491: iastore
    //   1492: dup
    //   1493: bipush #22
    //   1495: sipush #8193
    //   1498: iastore
    //   1499: dup
    //   1500: bipush #23
    //   1502: sipush #8320
    //   1505: iastore
    //   1506: dup
    //   1507: bipush #24
    //   1509: ldc 8388737
    //   1511: iastore
    //   1512: dup
    //   1513: bipush #25
    //   1515: iconst_1
    //   1516: iastore
    //   1517: dup
    //   1518: bipush #26
    //   1520: sipush #8320
    //   1523: iastore
    //   1524: dup
    //   1525: bipush #27
    //   1527: ldc 8388736
    //   1529: iastore
    //   1530: dup
    //   1531: bipush #28
    //   1533: sipush #8192
    //   1536: iastore
    //   1537: dup
    //   1538: bipush #29
    //   1540: ldc 8396928
    //   1542: iastore
    //   1543: dup
    //   1544: bipush #30
    //   1546: ldc 8396929
    //   1548: iastore
    //   1549: dup
    //   1550: bipush #31
    //   1552: sipush #129
    //   1555: iastore
    //   1556: dup
    //   1557: bipush #32
    //   1559: ldc 8388736
    //   1561: iastore
    //   1562: dup
    //   1563: bipush #33
    //   1565: ldc 8388609
    //   1567: iastore
    //   1568: dup
    //   1569: bipush #34
    //   1571: ldc 8396800
    //   1573: iastore
    //   1574: dup
    //   1575: bipush #35
    //   1577: ldc 8396929
    //   1579: iastore
    //   1580: dup
    //   1581: bipush #36
    //   1583: sipush #129
    //   1586: iastore
    //   1587: dup
    //   1588: bipush #37
    //   1590: iconst_0
    //   1591: iastore
    //   1592: dup
    //   1593: bipush #38
    //   1595: iconst_0
    //   1596: iastore
    //   1597: dup
    //   1598: bipush #39
    //   1600: ldc 8396800
    //   1602: iastore
    //   1603: dup
    //   1604: bipush #40
    //   1606: sipush #8320
    //   1609: iastore
    //   1610: dup
    //   1611: bipush #41
    //   1613: ldc 8388736
    //   1615: iastore
    //   1616: dup
    //   1617: bipush #42
    //   1619: ldc 8388737
    //   1621: iastore
    //   1622: dup
    //   1623: bipush #43
    //   1625: iconst_1
    //   1626: iastore
    //   1627: dup
    //   1628: bipush #44
    //   1630: ldc 8396801
    //   1632: iastore
    //   1633: dup
    //   1634: bipush #45
    //   1636: sipush #8321
    //   1639: iastore
    //   1640: dup
    //   1641: bipush #46
    //   1643: sipush #8321
    //   1646: iastore
    //   1647: dup
    //   1648: bipush #47
    //   1650: sipush #128
    //   1653: iastore
    //   1654: dup
    //   1655: bipush #48
    //   1657: ldc 8396929
    //   1659: iastore
    //   1660: dup
    //   1661: bipush #49
    //   1663: sipush #129
    //   1666: iastore
    //   1667: dup
    //   1668: bipush #50
    //   1670: iconst_1
    //   1671: iastore
    //   1672: dup
    //   1673: bipush #51
    //   1675: sipush #8192
    //   1678: iastore
    //   1679: dup
    //   1680: bipush #52
    //   1682: ldc 8388609
    //   1684: iastore
    //   1685: dup
    //   1686: bipush #53
    //   1688: sipush #8193
    //   1691: iastore
    //   1692: dup
    //   1693: bipush #54
    //   1695: ldc 8396928
    //   1697: iastore
    //   1698: dup
    //   1699: bipush #55
    //   1701: ldc 8388737
    //   1703: iastore
    //   1704: dup
    //   1705: bipush #56
    //   1707: sipush #8193
    //   1710: iastore
    //   1711: dup
    //   1712: bipush #57
    //   1714: sipush #8320
    //   1717: iastore
    //   1718: dup
    //   1719: bipush #58
    //   1721: ldc 8388608
    //   1723: iastore
    //   1724: dup
    //   1725: bipush #59
    //   1727: ldc 8396801
    //   1729: iastore
    //   1730: dup
    //   1731: bipush #60
    //   1733: sipush #128
    //   1736: iastore
    //   1737: dup
    //   1738: bipush #61
    //   1740: ldc 8388608
    //   1742: iastore
    //   1743: dup
    //   1744: bipush #62
    //   1746: sipush #8192
    //   1749: iastore
    //   1750: dup
    //   1751: bipush #63
    //   1753: ldc 8396928
    //   1755: iastore
    //   1756: astore #9
    //   1758: bipush #64
    //   1760: newarray int
    //   1762: dup
    //   1763: iconst_0
    //   1764: sipush #256
    //   1767: iastore
    //   1768: dup
    //   1769: iconst_1
    //   1770: ldc 34078976
    //   1772: iastore
    //   1773: dup
    //   1774: iconst_2
    //   1775: ldc 34078720
    //   1777: iastore
    //   1778: dup
    //   1779: iconst_3
    //   1780: ldc 1107296512
    //   1782: iastore
    //   1783: dup
    //   1784: iconst_4
    //   1785: ldc 524288
    //   1787: iastore
    //   1788: dup
    //   1789: iconst_5
    //   1790: sipush #256
    //   1793: iastore
    //   1794: dup
    //   1795: bipush #6
    //   1797: ldc 1073741824
    //   1799: iastore
    //   1800: dup
    //   1801: bipush #7
    //   1803: ldc 34078720
    //   1805: iastore
    //   1806: dup
    //   1807: bipush #8
    //   1809: ldc 1074266368
    //   1811: iastore
    //   1812: dup
    //   1813: bipush #9
    //   1815: ldc 524288
    //   1817: iastore
    //   1818: dup
    //   1819: bipush #10
    //   1821: ldc 33554688
    //   1823: iastore
    //   1824: dup
    //   1825: bipush #11
    //   1827: ldc 1074266368
    //   1829: iastore
    //   1830: dup
    //   1831: bipush #12
    //   1833: ldc 1107296512
    //   1835: iastore
    //   1836: dup
    //   1837: bipush #13
    //   1839: ldc 1107820544
    //   1841: iastore
    //   1842: dup
    //   1843: bipush #14
    //   1845: ldc 524544
    //   1847: iastore
    //   1848: dup
    //   1849: bipush #15
    //   1851: ldc 1073741824
    //   1853: iastore
    //   1854: dup
    //   1855: bipush #16
    //   1857: ldc 33554432
    //   1859: iastore
    //   1860: dup
    //   1861: bipush #17
    //   1863: ldc 1074266112
    //   1865: iastore
    //   1866: dup
    //   1867: bipush #18
    //   1869: ldc 1074266112
    //   1871: iastore
    //   1872: dup
    //   1873: bipush #19
    //   1875: iconst_0
    //   1876: iastore
    //   1877: dup
    //   1878: bipush #20
    //   1880: ldc 1073742080
    //   1882: iastore
    //   1883: dup
    //   1884: bipush #21
    //   1886: ldc 1107820800
    //   1888: iastore
    //   1889: dup
    //   1890: bipush #22
    //   1892: ldc 1107820800
    //   1894: iastore
    //   1895: dup
    //   1896: bipush #23
    //   1898: ldc 33554688
    //   1900: iastore
    //   1901: dup
    //   1902: bipush #24
    //   1904: ldc 1107820544
    //   1906: iastore
    //   1907: dup
    //   1908: bipush #25
    //   1910: ldc 1073742080
    //   1912: iastore
    //   1913: dup
    //   1914: bipush #26
    //   1916: iconst_0
    //   1917: iastore
    //   1918: dup
    //   1919: bipush #27
    //   1921: ldc 1107296256
    //   1923: iastore
    //   1924: dup
    //   1925: bipush #28
    //   1927: ldc 34078976
    //   1929: iastore
    //   1930: dup
    //   1931: bipush #29
    //   1933: ldc 33554432
    //   1935: iastore
    //   1936: dup
    //   1937: bipush #30
    //   1939: ldc 1107296256
    //   1941: iastore
    //   1942: dup
    //   1943: bipush #31
    //   1945: ldc 524544
    //   1947: iastore
    //   1948: dup
    //   1949: bipush #32
    //   1951: ldc 524288
    //   1953: iastore
    //   1954: dup
    //   1955: bipush #33
    //   1957: ldc 1107296512
    //   1959: iastore
    //   1960: dup
    //   1961: bipush #34
    //   1963: sipush #256
    //   1966: iastore
    //   1967: dup
    //   1968: bipush #35
    //   1970: ldc 33554432
    //   1972: iastore
    //   1973: dup
    //   1974: bipush #36
    //   1976: ldc 1073741824
    //   1978: iastore
    //   1979: dup
    //   1980: bipush #37
    //   1982: ldc 34078720
    //   1984: iastore
    //   1985: dup
    //   1986: bipush #38
    //   1988: ldc 1107296512
    //   1990: iastore
    //   1991: dup
    //   1992: bipush #39
    //   1994: ldc 1074266368
    //   1996: iastore
    //   1997: dup
    //   1998: bipush #40
    //   2000: ldc 33554688
    //   2002: iastore
    //   2003: dup
    //   2004: bipush #41
    //   2006: ldc 1073741824
    //   2008: iastore
    //   2009: dup
    //   2010: bipush #42
    //   2012: ldc 1107820544
    //   2014: iastore
    //   2015: dup
    //   2016: bipush #43
    //   2018: ldc 34078976
    //   2020: iastore
    //   2021: dup
    //   2022: bipush #44
    //   2024: ldc 1074266368
    //   2026: iastore
    //   2027: dup
    //   2028: bipush #45
    //   2030: sipush #256
    //   2033: iastore
    //   2034: dup
    //   2035: bipush #46
    //   2037: ldc 33554432
    //   2039: iastore
    //   2040: dup
    //   2041: bipush #47
    //   2043: ldc 1107820544
    //   2045: iastore
    //   2046: dup
    //   2047: bipush #48
    //   2049: ldc 1107820800
    //   2051: iastore
    //   2052: dup
    //   2053: bipush #49
    //   2055: ldc 524544
    //   2057: iastore
    //   2058: dup
    //   2059: bipush #50
    //   2061: ldc 1107296256
    //   2063: iastore
    //   2064: dup
    //   2065: bipush #51
    //   2067: ldc 1107820800
    //   2069: iastore
    //   2070: dup
    //   2071: bipush #52
    //   2073: ldc 34078720
    //   2075: iastore
    //   2076: dup
    //   2077: bipush #53
    //   2079: iconst_0
    //   2080: iastore
    //   2081: dup
    //   2082: bipush #54
    //   2084: ldc 1074266112
    //   2086: iastore
    //   2087: dup
    //   2088: bipush #55
    //   2090: ldc 1107296256
    //   2092: iastore
    //   2093: dup
    //   2094: bipush #56
    //   2096: ldc 524544
    //   2098: iastore
    //   2099: dup
    //   2100: bipush #57
    //   2102: ldc 33554688
    //   2104: iastore
    //   2105: dup
    //   2106: bipush #58
    //   2108: ldc 1073742080
    //   2110: iastore
    //   2111: dup
    //   2112: bipush #59
    //   2114: ldc 524288
    //   2116: iastore
    //   2117: dup
    //   2118: bipush #60
    //   2120: iconst_0
    //   2121: iastore
    //   2122: dup
    //   2123: bipush #61
    //   2125: ldc 1074266112
    //   2127: iastore
    //   2128: dup
    //   2129: bipush #62
    //   2131: ldc 34078976
    //   2133: iastore
    //   2134: dup
    //   2135: bipush #63
    //   2137: ldc 1073742080
    //   2139: iastore
    //   2140: astore #10
    //   2142: bipush #64
    //   2144: newarray int
    //   2146: dup
    //   2147: iconst_0
    //   2148: ldc 536870928
    //   2150: iastore
    //   2151: dup
    //   2152: iconst_1
    //   2153: ldc 541065216
    //   2155: iastore
    //   2156: dup
    //   2157: iconst_2
    //   2158: sipush #16384
    //   2161: iastore
    //   2162: dup
    //   2163: iconst_3
    //   2164: ldc 541081616
    //   2166: iastore
    //   2167: dup
    //   2168: iconst_4
    //   2169: ldc 541065216
    //   2171: iastore
    //   2172: dup
    //   2173: iconst_5
    //   2174: bipush #16
    //   2176: iastore
    //   2177: dup
    //   2178: bipush #6
    //   2180: ldc 541081616
    //   2182: iastore
    //   2183: dup
    //   2184: bipush #7
    //   2186: ldc 4194304
    //   2188: iastore
    //   2189: dup
    //   2190: bipush #8
    //   2192: ldc 536887296
    //   2194: iastore
    //   2195: dup
    //   2196: bipush #9
    //   2198: ldc 4210704
    //   2200: iastore
    //   2201: dup
    //   2202: bipush #10
    //   2204: ldc 4194304
    //   2206: iastore
    //   2207: dup
    //   2208: bipush #11
    //   2210: ldc 536870928
    //   2212: iastore
    //   2213: dup
    //   2214: bipush #12
    //   2216: ldc 4194320
    //   2218: iastore
    //   2219: dup
    //   2220: bipush #13
    //   2222: ldc 536887296
    //   2224: iastore
    //   2225: dup
    //   2226: bipush #14
    //   2228: ldc 536870912
    //   2230: iastore
    //   2231: dup
    //   2232: bipush #15
    //   2234: sipush #16400
    //   2237: iastore
    //   2238: dup
    //   2239: bipush #16
    //   2241: iconst_0
    //   2242: iastore
    //   2243: dup
    //   2244: bipush #17
    //   2246: ldc 4194320
    //   2248: iastore
    //   2249: dup
    //   2250: bipush #18
    //   2252: ldc 536887312
    //   2254: iastore
    //   2255: dup
    //   2256: bipush #19
    //   2258: sipush #16384
    //   2261: iastore
    //   2262: dup
    //   2263: bipush #20
    //   2265: ldc 4210688
    //   2267: iastore
    //   2268: dup
    //   2269: bipush #21
    //   2271: ldc 536887312
    //   2273: iastore
    //   2274: dup
    //   2275: bipush #22
    //   2277: bipush #16
    //   2279: iastore
    //   2280: dup
    //   2281: bipush #23
    //   2283: ldc 541065232
    //   2285: iastore
    //   2286: dup
    //   2287: bipush #24
    //   2289: ldc 541065232
    //   2291: iastore
    //   2292: dup
    //   2293: bipush #25
    //   2295: iconst_0
    //   2296: iastore
    //   2297: dup
    //   2298: bipush #26
    //   2300: ldc 4210704
    //   2302: iastore
    //   2303: dup
    //   2304: bipush #27
    //   2306: ldc 541081600
    //   2308: iastore
    //   2309: dup
    //   2310: bipush #28
    //   2312: sipush #16400
    //   2315: iastore
    //   2316: dup
    //   2317: bipush #29
    //   2319: ldc 4210688
    //   2321: iastore
    //   2322: dup
    //   2323: bipush #30
    //   2325: ldc 541081600
    //   2327: iastore
    //   2328: dup
    //   2329: bipush #31
    //   2331: ldc 536870912
    //   2333: iastore
    //   2334: dup
    //   2335: bipush #32
    //   2337: ldc 536887296
    //   2339: iastore
    //   2340: dup
    //   2341: bipush #33
    //   2343: bipush #16
    //   2345: iastore
    //   2346: dup
    //   2347: bipush #34
    //   2349: ldc 541065232
    //   2351: iastore
    //   2352: dup
    //   2353: bipush #35
    //   2355: ldc 4210688
    //   2357: iastore
    //   2358: dup
    //   2359: bipush #36
    //   2361: ldc 541081616
    //   2363: iastore
    //   2364: dup
    //   2365: bipush #37
    //   2367: ldc 4194304
    //   2369: iastore
    //   2370: dup
    //   2371: bipush #38
    //   2373: sipush #16400
    //   2376: iastore
    //   2377: dup
    //   2378: bipush #39
    //   2380: ldc 536870928
    //   2382: iastore
    //   2383: dup
    //   2384: bipush #40
    //   2386: ldc 4194304
    //   2388: iastore
    //   2389: dup
    //   2390: bipush #41
    //   2392: ldc 536887296
    //   2394: iastore
    //   2395: dup
    //   2396: bipush #42
    //   2398: ldc 536870912
    //   2400: iastore
    //   2401: dup
    //   2402: bipush #43
    //   2404: sipush #16400
    //   2407: iastore
    //   2408: dup
    //   2409: bipush #44
    //   2411: ldc 536870928
    //   2413: iastore
    //   2414: dup
    //   2415: bipush #45
    //   2417: ldc 541081616
    //   2419: iastore
    //   2420: dup
    //   2421: bipush #46
    //   2423: ldc 4210688
    //   2425: iastore
    //   2426: dup
    //   2427: bipush #47
    //   2429: ldc 541065216
    //   2431: iastore
    //   2432: dup
    //   2433: bipush #48
    //   2435: ldc 4210704
    //   2437: iastore
    //   2438: dup
    //   2439: bipush #49
    //   2441: ldc 541081600
    //   2443: iastore
    //   2444: dup
    //   2445: bipush #50
    //   2447: iconst_0
    //   2448: iastore
    //   2449: dup
    //   2450: bipush #51
    //   2452: ldc 541065232
    //   2454: iastore
    //   2455: dup
    //   2456: bipush #52
    //   2458: bipush #16
    //   2460: iastore
    //   2461: dup
    //   2462: bipush #53
    //   2464: sipush #16384
    //   2467: iastore
    //   2468: dup
    //   2469: bipush #54
    //   2471: ldc 541065216
    //   2473: iastore
    //   2474: dup
    //   2475: bipush #55
    //   2477: ldc 4210704
    //   2479: iastore
    //   2480: dup
    //   2481: bipush #56
    //   2483: sipush #16384
    //   2486: iastore
    //   2487: dup
    //   2488: bipush #57
    //   2490: ldc 4194320
    //   2492: iastore
    //   2493: dup
    //   2494: bipush #58
    //   2496: ldc 536887312
    //   2498: iastore
    //   2499: dup
    //   2500: bipush #59
    //   2502: iconst_0
    //   2503: iastore
    //   2504: dup
    //   2505: bipush #60
    //   2507: ldc 541081600
    //   2509: iastore
    //   2510: dup
    //   2511: bipush #61
    //   2513: ldc 536870912
    //   2515: iastore
    //   2516: dup
    //   2517: bipush #62
    //   2519: ldc 4194320
    //   2521: iastore
    //   2522: dup
    //   2523: bipush #63
    //   2525: ldc 536887312
    //   2527: iastore
    //   2528: astore #11
    //   2530: bipush #64
    //   2532: newarray int
    //   2534: dup
    //   2535: iconst_0
    //   2536: ldc 2097152
    //   2538: iastore
    //   2539: dup
    //   2540: iconst_1
    //   2541: ldc 69206018
    //   2543: iastore
    //   2544: dup
    //   2545: iconst_2
    //   2546: ldc 67110914
    //   2548: iastore
    //   2549: dup
    //   2550: iconst_3
    //   2551: iconst_0
    //   2552: iastore
    //   2553: dup
    //   2554: iconst_4
    //   2555: sipush #2048
    //   2558: iastore
    //   2559: dup
    //   2560: iconst_5
    //   2561: ldc 67110914
    //   2563: iastore
    //   2564: dup
    //   2565: bipush #6
    //   2567: ldc 2099202
    //   2569: iastore
    //   2570: dup
    //   2571: bipush #7
    //   2573: ldc 69208064
    //   2575: iastore
    //   2576: dup
    //   2577: bipush #8
    //   2579: ldc 69208066
    //   2581: iastore
    //   2582: dup
    //   2583: bipush #9
    //   2585: ldc 2097152
    //   2587: iastore
    //   2588: dup
    //   2589: bipush #10
    //   2591: iconst_0
    //   2592: iastore
    //   2593: dup
    //   2594: bipush #11
    //   2596: ldc 67108866
    //   2598: iastore
    //   2599: dup
    //   2600: bipush #12
    //   2602: iconst_2
    //   2603: iastore
    //   2604: dup
    //   2605: bipush #13
    //   2607: ldc 67108864
    //   2609: iastore
    //   2610: dup
    //   2611: bipush #14
    //   2613: ldc 69206018
    //   2615: iastore
    //   2616: dup
    //   2617: bipush #15
    //   2619: sipush #2050
    //   2622: iastore
    //   2623: dup
    //   2624: bipush #16
    //   2626: ldc 67110912
    //   2628: iastore
    //   2629: dup
    //   2630: bipush #17
    //   2632: ldc 2099202
    //   2634: iastore
    //   2635: dup
    //   2636: bipush #18
    //   2638: ldc 2097154
    //   2640: iastore
    //   2641: dup
    //   2642: bipush #19
    //   2644: ldc 67110912
    //   2646: iastore
    //   2647: dup
    //   2648: bipush #20
    //   2650: ldc 67108866
    //   2652: iastore
    //   2653: dup
    //   2654: bipush #21
    //   2656: ldc 69206016
    //   2658: iastore
    //   2659: dup
    //   2660: bipush #22
    //   2662: ldc 69208064
    //   2664: iastore
    //   2665: dup
    //   2666: bipush #23
    //   2668: ldc 2097154
    //   2670: iastore
    //   2671: dup
    //   2672: bipush #24
    //   2674: ldc 69206016
    //   2676: iastore
    //   2677: dup
    //   2678: bipush #25
    //   2680: sipush #2048
    //   2683: iastore
    //   2684: dup
    //   2685: bipush #26
    //   2687: sipush #2050
    //   2690: iastore
    //   2691: dup
    //   2692: bipush #27
    //   2694: ldc 69208066
    //   2696: iastore
    //   2697: dup
    //   2698: bipush #28
    //   2700: ldc 2099200
    //   2702: iastore
    //   2703: dup
    //   2704: bipush #29
    //   2706: iconst_2
    //   2707: iastore
    //   2708: dup
    //   2709: bipush #30
    //   2711: ldc 67108864
    //   2713: iastore
    //   2714: dup
    //   2715: bipush #31
    //   2717: ldc 2099200
    //   2719: iastore
    //   2720: dup
    //   2721: bipush #32
    //   2723: ldc 67108864
    //   2725: iastore
    //   2726: dup
    //   2727: bipush #33
    //   2729: ldc 2099200
    //   2731: iastore
    //   2732: dup
    //   2733: bipush #34
    //   2735: ldc 2097152
    //   2737: iastore
    //   2738: dup
    //   2739: bipush #35
    //   2741: ldc 67110914
    //   2743: iastore
    //   2744: dup
    //   2745: bipush #36
    //   2747: ldc 67110914
    //   2749: iastore
    //   2750: dup
    //   2751: bipush #37
    //   2753: ldc 69206018
    //   2755: iastore
    //   2756: dup
    //   2757: bipush #38
    //   2759: ldc 69206018
    //   2761: iastore
    //   2762: dup
    //   2763: bipush #39
    //   2765: iconst_2
    //   2766: iastore
    //   2767: dup
    //   2768: bipush #40
    //   2770: ldc 2097154
    //   2772: iastore
    //   2773: dup
    //   2774: bipush #41
    //   2776: ldc 67108864
    //   2778: iastore
    //   2779: dup
    //   2780: bipush #42
    //   2782: ldc 67110912
    //   2784: iastore
    //   2785: dup
    //   2786: bipush #43
    //   2788: ldc 2097152
    //   2790: iastore
    //   2791: dup
    //   2792: bipush #44
    //   2794: ldc 69208064
    //   2796: iastore
    //   2797: dup
    //   2798: bipush #45
    //   2800: sipush #2050
    //   2803: iastore
    //   2804: dup
    //   2805: bipush #46
    //   2807: ldc 2099202
    //   2809: iastore
    //   2810: dup
    //   2811: bipush #47
    //   2813: ldc 69208064
    //   2815: iastore
    //   2816: dup
    //   2817: bipush #48
    //   2819: sipush #2050
    //   2822: iastore
    //   2823: dup
    //   2824: bipush #49
    //   2826: ldc 67108866
    //   2828: iastore
    //   2829: dup
    //   2830: bipush #50
    //   2832: ldc 69208066
    //   2834: iastore
    //   2835: dup
    //   2836: bipush #51
    //   2838: ldc 69206016
    //   2840: iastore
    //   2841: dup
    //   2842: bipush #52
    //   2844: ldc 2099200
    //   2846: iastore
    //   2847: dup
    //   2848: bipush #53
    //   2850: iconst_0
    //   2851: iastore
    //   2852: dup
    //   2853: bipush #54
    //   2855: iconst_2
    //   2856: iastore
    //   2857: dup
    //   2858: bipush #55
    //   2860: ldc 69208066
    //   2862: iastore
    //   2863: dup
    //   2864: bipush #56
    //   2866: iconst_0
    //   2867: iastore
    //   2868: dup
    //   2869: bipush #57
    //   2871: ldc 2099202
    //   2873: iastore
    //   2874: dup
    //   2875: bipush #58
    //   2877: ldc 69206016
    //   2879: iastore
    //   2880: dup
    //   2881: bipush #59
    //   2883: sipush #2048
    //   2886: iastore
    //   2887: dup
    //   2888: bipush #60
    //   2890: ldc 67108866
    //   2892: iastore
    //   2893: dup
    //   2894: bipush #61
    //   2896: ldc 67110912
    //   2898: iastore
    //   2899: dup
    //   2900: bipush #62
    //   2902: sipush #2048
    //   2905: iastore
    //   2906: dup
    //   2907: bipush #63
    //   2909: ldc 2097154
    //   2911: iastore
    //   2912: astore #12
    //   2914: bipush #64
    //   2916: newarray int
    //   2918: dup
    //   2919: iconst_0
    //   2920: ldc 268439616
    //   2922: iastore
    //   2923: dup
    //   2924: iconst_1
    //   2925: sipush #4096
    //   2928: iastore
    //   2929: dup
    //   2930: iconst_2
    //   2931: ldc 262144
    //   2933: iastore
    //   2934: dup
    //   2935: iconst_3
    //   2936: ldc 268701760
    //   2938: iastore
    //   2939: dup
    //   2940: iconst_4
    //   2941: ldc 268435456
    //   2943: iastore
    //   2944: dup
    //   2945: iconst_5
    //   2946: ldc 268439616
    //   2948: iastore
    //   2949: dup
    //   2950: bipush #6
    //   2952: bipush #64
    //   2954: iastore
    //   2955: dup
    //   2956: bipush #7
    //   2958: ldc 268435456
    //   2960: iastore
    //   2961: dup
    //   2962: bipush #8
    //   2964: ldc 262208
    //   2966: iastore
    //   2967: dup
    //   2968: bipush #9
    //   2970: ldc 268697600
    //   2972: iastore
    //   2973: dup
    //   2974: bipush #10
    //   2976: ldc 268701760
    //   2978: iastore
    //   2979: dup
    //   2980: bipush #11
    //   2982: ldc 266240
    //   2984: iastore
    //   2985: dup
    //   2986: bipush #12
    //   2988: ldc 268701696
    //   2990: iastore
    //   2991: dup
    //   2992: bipush #13
    //   2994: ldc 266304
    //   2996: iastore
    //   2997: dup
    //   2998: bipush #14
    //   3000: sipush #4096
    //   3003: iastore
    //   3004: dup
    //   3005: bipush #15
    //   3007: bipush #64
    //   3009: iastore
    //   3010: dup
    //   3011: bipush #16
    //   3013: ldc 268697600
    //   3015: iastore
    //   3016: dup
    //   3017: bipush #17
    //   3019: ldc 268435520
    //   3021: iastore
    //   3022: dup
    //   3023: bipush #18
    //   3025: ldc 268439552
    //   3027: iastore
    //   3028: dup
    //   3029: bipush #19
    //   3031: sipush #4160
    //   3034: iastore
    //   3035: dup
    //   3036: bipush #20
    //   3038: ldc 266240
    //   3040: iastore
    //   3041: dup
    //   3042: bipush #21
    //   3044: ldc 262208
    //   3046: iastore
    //   3047: dup
    //   3048: bipush #22
    //   3050: ldc 268697664
    //   3052: iastore
    //   3053: dup
    //   3054: bipush #23
    //   3056: ldc 268701696
    //   3058: iastore
    //   3059: dup
    //   3060: bipush #24
    //   3062: sipush #4160
    //   3065: iastore
    //   3066: dup
    //   3067: bipush #25
    //   3069: iconst_0
    //   3070: iastore
    //   3071: dup
    //   3072: bipush #26
    //   3074: iconst_0
    //   3075: iastore
    //   3076: dup
    //   3077: bipush #27
    //   3079: ldc 268697664
    //   3081: iastore
    //   3082: dup
    //   3083: bipush #28
    //   3085: ldc 268435520
    //   3087: iastore
    //   3088: dup
    //   3089: bipush #29
    //   3091: ldc 268439552
    //   3093: iastore
    //   3094: dup
    //   3095: bipush #30
    //   3097: ldc 266304
    //   3099: iastore
    //   3100: dup
    //   3101: bipush #31
    //   3103: ldc 262144
    //   3105: iastore
    //   3106: dup
    //   3107: bipush #32
    //   3109: ldc 266304
    //   3111: iastore
    //   3112: dup
    //   3113: bipush #33
    //   3115: ldc 262144
    //   3117: iastore
    //   3118: dup
    //   3119: bipush #34
    //   3121: ldc 268701696
    //   3123: iastore
    //   3124: dup
    //   3125: bipush #35
    //   3127: sipush #4096
    //   3130: iastore
    //   3131: dup
    //   3132: bipush #36
    //   3134: bipush #64
    //   3136: iastore
    //   3137: dup
    //   3138: bipush #37
    //   3140: ldc 268697664
    //   3142: iastore
    //   3143: dup
    //   3144: bipush #38
    //   3146: sipush #4096
    //   3149: iastore
    //   3150: dup
    //   3151: bipush #39
    //   3153: ldc 266304
    //   3155: iastore
    //   3156: dup
    //   3157: bipush #40
    //   3159: ldc 268439552
    //   3161: iastore
    //   3162: dup
    //   3163: bipush #41
    //   3165: bipush #64
    //   3167: iastore
    //   3168: dup
    //   3169: bipush #42
    //   3171: ldc 268435520
    //   3173: iastore
    //   3174: dup
    //   3175: bipush #43
    //   3177: ldc 268697600
    //   3179: iastore
    //   3180: dup
    //   3181: bipush #44
    //   3183: ldc 268697664
    //   3185: iastore
    //   3186: dup
    //   3187: bipush #45
    //   3189: ldc 268435456
    //   3191: iastore
    //   3192: dup
    //   3193: bipush #46
    //   3195: ldc 262144
    //   3197: iastore
    //   3198: dup
    //   3199: bipush #47
    //   3201: ldc 268439616
    //   3203: iastore
    //   3204: dup
    //   3205: bipush #48
    //   3207: iconst_0
    //   3208: iastore
    //   3209: dup
    //   3210: bipush #49
    //   3212: ldc 268701760
    //   3214: iastore
    //   3215: dup
    //   3216: bipush #50
    //   3218: ldc 262208
    //   3220: iastore
    //   3221: dup
    //   3222: bipush #51
    //   3224: ldc 268435520
    //   3226: iastore
    //   3227: dup
    //   3228: bipush #52
    //   3230: ldc 268697600
    //   3232: iastore
    //   3233: dup
    //   3234: bipush #53
    //   3236: ldc 268439552
    //   3238: iastore
    //   3239: dup
    //   3240: bipush #54
    //   3242: ldc 268439616
    //   3244: iastore
    //   3245: dup
    //   3246: bipush #55
    //   3248: iconst_0
    //   3249: iastore
    //   3250: dup
    //   3251: bipush #56
    //   3253: ldc 268701760
    //   3255: iastore
    //   3256: dup
    //   3257: bipush #57
    //   3259: ldc 266240
    //   3261: iastore
    //   3262: dup
    //   3263: bipush #58
    //   3265: ldc 266240
    //   3267: iastore
    //   3268: dup
    //   3269: bipush #59
    //   3271: sipush #4160
    //   3274: iastore
    //   3275: dup
    //   3276: bipush #60
    //   3278: sipush #4160
    //   3281: iastore
    //   3282: dup
    //   3283: bipush #61
    //   3285: ldc 262208
    //   3287: iastore
    //   3288: dup
    //   3289: bipush #62
    //   3291: ldc 268435456
    //   3293: iastore
    //   3294: dup
    //   3295: bipush #63
    //   3297: ldc 268701696
    //   3299: iastore
    //   3300: astore #13
    //   3302: aload_3
    //   3303: arraylength
    //   3304: istore #14
    //   3306: iload #14
    //   3308: bipush #8
    //   3310: irem
    //   3311: ifeq -> 3335
    //   3314: new java/lang/Exception
    //   3317: dup
    //   3318: sipush #17497
    //   3321: sipush #-7423
    //   3324: invokestatic a : (II)Ljava/lang/String;
    //   3327: invokespecial <init> : (Ljava/lang/String;)V
    //   3330: athrow
    //   3331: invokestatic a : (Ljava/lang/Throwable;)Ljava/lang/Throwable;
    //   3334: athrow
    //   3335: iconst_2
    //   3336: newarray int
    //   3338: astore #15
    //   3340: iload #14
    //   3342: newarray byte
    //   3344: astore #16
    //   3346: iload #14
    //   3348: bipush #8
    //   3350: idiv
    //   3351: istore #17
    //   3353: iconst_0
    //   3354: istore #18
    //   3356: iload #18
    //   3358: iload #17
    //   3360: if_icmpge -> 4274
    //   3363: iload #18
    //   3365: bipush #8
    //   3367: imul
    //   3368: istore #19
    //   3370: iconst_0
    //   3371: istore #20
    //   3373: iload #20
    //   3375: iconst_2
    //   3376: if_icmpge -> 3461
    //   3379: aload #15
    //   3381: iload #20
    //   3383: aload_3
    //   3384: iload #19
    //   3386: iload #20
    //   3388: iconst_4
    //   3389: imul
    //   3390: iadd
    //   3391: baload
    //   3392: sipush #255
    //   3395: iand
    //   3396: bipush #24
    //   3398: ishl
    //   3399: aload_3
    //   3400: iload #19
    //   3402: iload #20
    //   3404: iconst_4
    //   3405: imul
    //   3406: iadd
    //   3407: iconst_1
    //   3408: iadd
    //   3409: baload
    //   3410: sipush #255
    //   3413: iand
    //   3414: bipush #16
    //   3416: ishl
    //   3417: ior
    //   3418: aload_3
    //   3419: iload #19
    //   3421: iload #20
    //   3423: iconst_4
    //   3424: imul
    //   3425: iadd
    //   3426: iconst_2
    //   3427: iadd
    //   3428: baload
    //   3429: sipush #255
    //   3432: iand
    //   3433: bipush #8
    //   3435: ishl
    //   3436: ior
    //   3437: aload_3
    //   3438: iload #19
    //   3440: iload #20
    //   3442: iconst_4
    //   3443: imul
    //   3444: iadd
    //   3445: iconst_3
    //   3446: iadd
    //   3447: baload
    //   3448: sipush #255
    //   3451: iand
    //   3452: ior
    //   3453: iastore
    //   3454: iinc #20, 1
    //   3457: iload_2
    //   3458: ifne -> 3373
    //   3461: iconst_0
    //   3462: istore #25
    //   3464: aload #15
    //   3466: iconst_0
    //   3467: iaload
    //   3468: istore #23
    //   3470: aload #15
    //   3472: iconst_1
    //   3473: iaload
    //   3474: istore #22
    //   3476: iload #23
    //   3478: iconst_4
    //   3479: iushr
    //   3480: iload #22
    //   3482: ixor
    //   3483: ldc 252645135
    //   3485: iand
    //   3486: istore #21
    //   3488: iload #22
    //   3490: iload #21
    //   3492: ixor
    //   3493: istore #22
    //   3495: iload #23
    //   3497: iload #21
    //   3499: iconst_4
    //   3500: ishl
    //   3501: ixor
    //   3502: istore #23
    //   3504: iload #23
    //   3506: bipush #16
    //   3508: iushr
    //   3509: iload #22
    //   3511: ixor
    //   3512: ldc 65535
    //   3514: iand
    //   3515: istore #21
    //   3517: iload #22
    //   3519: iload #21
    //   3521: ixor
    //   3522: istore #22
    //   3524: iload #23
    //   3526: iload #21
    //   3528: bipush #16
    //   3530: ishl
    //   3531: ixor
    //   3532: istore #23
    //   3534: iload #22
    //   3536: iconst_2
    //   3537: iushr
    //   3538: iload #23
    //   3540: ixor
    //   3541: ldc 858993459
    //   3543: iand
    //   3544: istore #21
    //   3546: iload #23
    //   3548: iload #21
    //   3550: ixor
    //   3551: istore #23
    //   3553: iload #22
    //   3555: iload #21
    //   3557: iconst_2
    //   3558: ishl
    //   3559: ixor
    //   3560: istore #22
    //   3562: iload #22
    //   3564: bipush #8
    //   3566: iushr
    //   3567: iload #23
    //   3569: ixor
    //   3570: ldc 16711935
    //   3572: iand
    //   3573: istore #21
    //   3575: iload #23
    //   3577: iload #21
    //   3579: ixor
    //   3580: istore #23
    //   3582: iload #22
    //   3584: iload #21
    //   3586: bipush #8
    //   3588: ishl
    //   3589: ixor
    //   3590: istore #22
    //   3592: iload #22
    //   3594: iconst_1
    //   3595: ishl
    //   3596: iload #22
    //   3598: bipush #31
    //   3600: iushr
    //   3601: iconst_1
    //   3602: iand
    //   3603: ior
    //   3604: istore #22
    //   3606: iload #23
    //   3608: iload #22
    //   3610: ixor
    //   3611: ldc -1431655766
    //   3613: iand
    //   3614: istore #21
    //   3616: iload #23
    //   3618: iload #21
    //   3620: ixor
    //   3621: istore #23
    //   3623: iload #22
    //   3625: iload #21
    //   3627: ixor
    //   3628: istore #22
    //   3630: iload #23
    //   3632: iconst_1
    //   3633: ishl
    //   3634: iload #23
    //   3636: bipush #31
    //   3638: iushr
    //   3639: iconst_1
    //   3640: iand
    //   3641: ior
    //   3642: istore #23
    //   3644: iconst_0
    //   3645: istore #24
    //   3647: iload #24
    //   3649: bipush #8
    //   3651: if_icmpge -> 3989
    //   3654: iload #22
    //   3656: bipush #28
    //   3658: ishl
    //   3659: iload #22
    //   3661: iconst_4
    //   3662: iushr
    //   3663: ior
    //   3664: istore #21
    //   3666: iload #21
    //   3668: aload #5
    //   3670: iload #25
    //   3672: iinc #25, 1
    //   3675: iaload
    //   3676: ixor
    //   3677: istore #21
    //   3679: aload #12
    //   3681: iload #21
    //   3683: bipush #63
    //   3685: iand
    //   3686: iaload
    //   3687: istore #20
    //   3689: iload #20
    //   3691: aload #10
    //   3693: iload #21
    //   3695: bipush #8
    //   3697: iushr
    //   3698: bipush #63
    //   3700: iand
    //   3701: iaload
    //   3702: ior
    //   3703: istore #20
    //   3705: iload #20
    //   3707: aload #8
    //   3709: iload #21
    //   3711: bipush #16
    //   3713: iushr
    //   3714: bipush #63
    //   3716: iand
    //   3717: iaload
    //   3718: ior
    //   3719: istore #20
    //   3721: iload #20
    //   3723: aload #6
    //   3725: iload #21
    //   3727: bipush #24
    //   3729: iushr
    //   3730: bipush #63
    //   3732: iand
    //   3733: iaload
    //   3734: ior
    //   3735: istore #20
    //   3737: iload #22
    //   3739: aload #5
    //   3741: iload #25
    //   3743: iinc #25, 1
    //   3746: iaload
    //   3747: ixor
    //   3748: istore #21
    //   3750: iload #20
    //   3752: aload #13
    //   3754: iload #21
    //   3756: bipush #63
    //   3758: iand
    //   3759: iaload
    //   3760: ior
    //   3761: istore #20
    //   3763: iload #20
    //   3765: aload #11
    //   3767: iload #21
    //   3769: bipush #8
    //   3771: iushr
    //   3772: bipush #63
    //   3774: iand
    //   3775: iaload
    //   3776: ior
    //   3777: istore #20
    //   3779: iload #20
    //   3781: aload #9
    //   3783: iload #21
    //   3785: bipush #16
    //   3787: iushr
    //   3788: bipush #63
    //   3790: iand
    //   3791: iaload
    //   3792: ior
    //   3793: istore #20
    //   3795: iload #20
    //   3797: aload #7
    //   3799: iload #21
    //   3801: bipush #24
    //   3803: iushr
    //   3804: bipush #63
    //   3806: iand
    //   3807: iaload
    //   3808: ior
    //   3809: istore #20
    //   3811: iload #23
    //   3813: iload #20
    //   3815: ixor
    //   3816: istore #23
    //   3818: iload #23
    //   3820: bipush #28
    //   3822: ishl
    //   3823: iload #23
    //   3825: iconst_4
    //   3826: iushr
    //   3827: ior
    //   3828: istore #21
    //   3830: iload #21
    //   3832: aload #5
    //   3834: iload #25
    //   3836: iinc #25, 1
    //   3839: iaload
    //   3840: ixor
    //   3841: istore #21
    //   3843: aload #12
    //   3845: iload #21
    //   3847: bipush #63
    //   3849: iand
    //   3850: iaload
    //   3851: istore #20
    //   3853: iload #20
    //   3855: aload #10
    //   3857: iload #21
    //   3859: bipush #8
    //   3861: iushr
    //   3862: bipush #63
    //   3864: iand
    //   3865: iaload
    //   3866: ior
    //   3867: istore #20
    //   3869: iload #20
    //   3871: aload #8
    //   3873: iload #21
    //   3875: bipush #16
    //   3877: iushr
    //   3878: bipush #63
    //   3880: iand
    //   3881: iaload
    //   3882: ior
    //   3883: istore #20
    //   3885: iload #20
    //   3887: aload #6
    //   3889: iload #21
    //   3891: bipush #24
    //   3893: iushr
    //   3894: bipush #63
    //   3896: iand
    //   3897: iaload
    //   3898: ior
    //   3899: istore #20
    //   3901: iload #23
    //   3903: aload #5
    //   3905: iload #25
    //   3907: iinc #25, 1
    //   3910: iaload
    //   3911: ixor
    //   3912: istore #21
    //   3914: iload #20
    //   3916: aload #13
    //   3918: iload #21
    //   3920: bipush #63
    //   3922: iand
    //   3923: iaload
    //   3924: ior
    //   3925: istore #20
    //   3927: iload #20
    //   3929: aload #11
    //   3931: iload #21
    //   3933: bipush #8
    //   3935: iushr
    //   3936: bipush #63
    //   3938: iand
    //   3939: iaload
    //   3940: ior
    //   3941: istore #20
    //   3943: iload #20
    //   3945: aload #9
    //   3947: iload #21
    //   3949: bipush #16
    //   3951: iushr
    //   3952: bipush #63
    //   3954: iand
    //   3955: iaload
    //   3956: ior
    //   3957: istore #20
    //   3959: iload #20
    //   3961: aload #7
    //   3963: iload #21
    //   3965: bipush #24
    //   3967: iushr
    //   3968: bipush #63
    //   3970: iand
    //   3971: iaload
    //   3972: ior
    //   3973: istore #20
    //   3975: iload #22
    //   3977: iload #20
    //   3979: ixor
    //   3980: istore #22
    //   3982: iinc #24, 1
    //   3985: iload_2
    //   3986: ifne -> 3647
    //   3989: iload #22
    //   3991: bipush #31
    //   3993: ishl
    //   3994: iload #22
    //   3996: iconst_1
    //   3997: iushr
    //   3998: ior
    //   3999: istore #22
    //   4001: iload #23
    //   4003: iload #22
    //   4005: ixor
    //   4006: ldc -1431655766
    //   4008: iand
    //   4009: istore #21
    //   4011: iload #23
    //   4013: iload #21
    //   4015: ixor
    //   4016: istore #23
    //   4018: iload #22
    //   4020: iload #21
    //   4022: ixor
    //   4023: istore #22
    //   4025: iload #23
    //   4027: bipush #31
    //   4029: ishl
    //   4030: iload #23
    //   4032: iconst_1
    //   4033: iushr
    //   4034: ior
    //   4035: istore #23
    //   4037: iload #23
    //   4039: bipush #8
    //   4041: iushr
    //   4042: iload #22
    //   4044: ixor
    //   4045: ldc 16711935
    //   4047: iand
    //   4048: istore #21
    //   4050: iload #22
    //   4052: iload #21
    //   4054: ixor
    //   4055: istore #22
    //   4057: iload #23
    //   4059: iload #21
    //   4061: bipush #8
    //   4063: ishl
    //   4064: ixor
    //   4065: istore #23
    //   4067: iload #23
    //   4069: iconst_2
    //   4070: iushr
    //   4071: iload #22
    //   4073: ixor
    //   4074: ldc 858993459
    //   4076: iand
    //   4077: istore #21
    //   4079: iload #22
    //   4081: iload #21
    //   4083: ixor
    //   4084: istore #22
    //   4086: iload #23
    //   4088: iload #21
    //   4090: iconst_2
    //   4091: ishl
    //   4092: ixor
    //   4093: istore #23
    //   4095: iload #22
    //   4097: bipush #16
    //   4099: iushr
    //   4100: iload #23
    //   4102: ixor
    //   4103: ldc 65535
    //   4105: iand
    //   4106: istore #21
    //   4108: iload #23
    //   4110: iload #21
    //   4112: ixor
    //   4113: istore #23
    //   4115: iload #22
    //   4117: iload #21
    //   4119: bipush #16
    //   4121: ishl
    //   4122: ixor
    //   4123: istore #22
    //   4125: iload #22
    //   4127: iconst_4
    //   4128: iushr
    //   4129: iload #23
    //   4131: ixor
    //   4132: ldc 252645135
    //   4134: iand
    //   4135: istore #21
    //   4137: iload #23
    //   4139: iload #21
    //   4141: ixor
    //   4142: istore #23
    //   4144: iload #22
    //   4146: iload #21
    //   4148: iconst_4
    //   4149: ishl
    //   4150: ixor
    //   4151: istore #22
    //   4153: aload #15
    //   4155: iconst_0
    //   4156: iload #22
    //   4158: iastore
    //   4159: aload #15
    //   4161: iconst_1
    //   4162: iload #23
    //   4164: iastore
    //   4165: iload #18
    //   4167: bipush #8
    //   4169: imul
    //   4170: istore #26
    //   4172: iconst_0
    //   4173: istore #27
    //   4175: iload #27
    //   4177: iconst_2
    //   4178: if_icmpge -> 4267
    //   4181: aload #16
    //   4183: iload #26
    //   4185: iload #27
    //   4187: iconst_4
    //   4188: imul
    //   4189: iadd
    //   4190: aload #15
    //   4192: iload #27
    //   4194: iaload
    //   4195: bipush #24
    //   4197: iushr
    //   4198: i2b
    //   4199: bastore
    //   4200: aload #16
    //   4202: iload #26
    //   4204: iload #27
    //   4206: iconst_4
    //   4207: imul
    //   4208: iadd
    //   4209: iconst_1
    //   4210: iadd
    //   4211: aload #15
    //   4213: iload #27
    //   4215: iaload
    //   4216: bipush #16
    //   4218: iushr
    //   4219: i2b
    //   4220: bastore
    //   4221: aload #16
    //   4223: iload #26
    //   4225: iload #27
    //   4227: iconst_4
    //   4228: imul
    //   4229: iadd
    //   4230: iconst_2
    //   4231: iadd
    //   4232: aload #15
    //   4234: iload #27
    //   4236: iaload
    //   4237: bipush #8
    //   4239: iushr
    //   4240: i2b
    //   4241: bastore
    //   4242: aload #16
    //   4244: iload #26
    //   4246: iload #27
    //   4248: iconst_4
    //   4249: imul
    //   4250: iadd
    //   4251: iconst_3
    //   4252: iadd
    //   4253: aload #15
    //   4255: iload #27
    //   4257: iaload
    //   4258: i2b
    //   4259: bastore
    //   4260: iinc #27, 1
    //   4263: iload_2
    //   4264: ifne -> 4175
    //   4267: iinc #18, 1
    //   4270: iload_2
    //   4271: ifne -> 3356
    //   4274: aload #16
    //   4276: aload #16
    //   4278: arraylength
    //   4279: iconst_1
    //   4280: isub
    //   4281: baload
    //   4282: istore #18
    //   4284: aload #16
    //   4286: arraylength
    //   4287: iload #18
    //   4289: isub
    //   4290: newarray byte
    //   4292: astore #4
    //   4294: aload #16
    //   4296: arraylength
    //   4297: aload #4
    //   4299: arraylength
    //   4300: if_icmpge -> 4324
    //   4303: new java/lang/Exception
    //   4306: dup
    //   4307: sipush #17489
    //   4310: sipush #23582
    //   4313: invokestatic a : (II)Ljava/lang/String;
    //   4316: invokespecial <init> : (Ljava/lang/String;)V
    //   4319: athrow
    //   4320: invokestatic a : (Ljava/lang/Throwable;)Ljava/lang/Throwable;
    //   4323: athrow
    //   4324: iconst_0
    //   4325: istore #19
    //   4327: iload #19
    //   4329: aload #4
    //   4331: arraylength
    //   4332: if_icmpge -> 4352
    //   4335: aload #4
    //   4337: iload #19
    //   4339: aload #16
    //   4341: iload #19
    //   4343: baload
    //   4344: bastore
    //   4345: iinc #19, 1
    //   4348: iload_2
    //   4349: ifne -> 4327
    //   4352: new java/math/BigInteger
    //   4355: dup
    //   4356: aload #4
    //   4358: invokespecial <init> : ([B)V
    //   4361: invokevirtual abs : ()Ljava/math/BigInteger;
    //   4364: putstatic burp/Zxan.ZX : Ljava/lang/Object;
    //   4367: getstatic burp/Zmli.Zh : Ljava/lang/Object;
    //   4370: checkcast java/math/BigInteger
    //   4373: invokevirtual toByteArray : ()[B
    //   4376: astore_3
    //   4377: bipush #64
    //   4379: newarray byte
    //   4381: dup
    //   4382: iconst_0
    //   4383: bipush #-128
    //   4385: bastore
    //   4386: dup
    //   4387: iconst_1
    //   4388: iconst_0
    //   4389: bastore
    //   4390: dup
    //   4391: iconst_2
    //   4392: iconst_0
    //   4393: bastore
    //   4394: dup
    //   4395: iconst_3
    //   4396: iconst_0
    //   4397: bastore
    //   4398: dup
    //   4399: iconst_4
    //   4400: iconst_0
    //   4401: bastore
    //   4402: dup
    //   4403: iconst_5
    //   4404: iconst_0
    //   4405: bastore
    //   4406: dup
    //   4407: bipush #6
    //   4409: iconst_0
    //   4410: bastore
    //   4411: dup
    //   4412: bipush #7
    //   4414: iconst_0
    //   4415: bastore
    //   4416: dup
    //   4417: bipush #8
    //   4419: iconst_0
    //   4420: bastore
    //   4421: dup
    //   4422: bipush #9
    //   4424: iconst_0
    //   4425: bastore
    //   4426: dup
    //   4427: bipush #10
    //   4429: iconst_0
    //   4430: bastore
    //   4431: dup
    //   4432: bipush #11
    //   4434: iconst_0
    //   4435: bastore
    //   4436: dup
    //   4437: bipush #12
    //   4439: iconst_0
    //   4440: bastore
    //   4441: dup
    //   4442: bipush #13
    //   4444: iconst_0
    //   4445: bastore
    //   4446: dup
    //   4447: bipush #14
    //   4449: iconst_0
    //   4450: bastore
    //   4451: dup
    //   4452: bipush #15
    //   4454: iconst_0
    //   4455: bastore
    //   4456: dup
    //   4457: bipush #16
    //   4459: iconst_0
    //   4460: bastore
    //   4461: dup
    //   4462: bipush #17
    //   4464: iconst_0
    //   4465: bastore
    //   4466: dup
    //   4467: bipush #18
    //   4469: iconst_0
    //   4470: bastore
    //   4471: dup
    //   4472: bipush #19
    //   4474: iconst_0
    //   4475: bastore
    //   4476: dup
    //   4477: bipush #20
    //   4479: iconst_0
    //   4480: bastore
    //   4481: dup
    //   4482: bipush #21
    //   4484: iconst_0
    //   4485: bastore
    //   4486: dup
    //   4487: bipush #22
    //   4489: iconst_0
    //   4490: bastore
    //   4491: dup
    //   4492: bipush #23
    //   4494: iconst_0
    //   4495: bastore
    //   4496: dup
    //   4497: bipush #24
    //   4499: iconst_0
    //   4500: bastore
    //   4501: dup
    //   4502: bipush #25
    //   4504: iconst_0
    //   4505: bastore
    //   4506: dup
    //   4507: bipush #26
    //   4509: iconst_0
    //   4510: bastore
    //   4511: dup
    //   4512: bipush #27
    //   4514: iconst_0
    //   4515: bastore
    //   4516: dup
    //   4517: bipush #28
    //   4519: iconst_0
    //   4520: bastore
    //   4521: dup
    //   4522: bipush #29
    //   4524: iconst_0
    //   4525: bastore
    //   4526: dup
    //   4527: bipush #30
    //   4529: iconst_0
    //   4530: bastore
    //   4531: dup
    //   4532: bipush #31
    //   4534: iconst_0
    //   4535: bastore
    //   4536: dup
    //   4537: bipush #32
    //   4539: iconst_0
    //   4540: bastore
    //   4541: dup
    //   4542: bipush #33
    //   4544: iconst_0
    //   4545: bastore
    //   4546: dup
    //   4547: bipush #34
    //   4549: iconst_0
    //   4550: bastore
    //   4551: dup
    //   4552: bipush #35
    //   4554: iconst_0
    //   4555: bastore
    //   4556: dup
    //   4557: bipush #36
    //   4559: iconst_0
    //   4560: bastore
    //   4561: dup
    //   4562: bipush #37
    //   4564: iconst_0
    //   4565: bastore
    //   4566: dup
    //   4567: bipush #38
    //   4569: iconst_0
    //   4570: bastore
    //   4571: dup
    //   4572: bipush #39
    //   4574: iconst_0
    //   4575: bastore
    //   4576: dup
    //   4577: bipush #40
    //   4579: iconst_0
    //   4580: bastore
    //   4581: dup
    //   4582: bipush #41
    //   4584: iconst_0
    //   4585: bastore
    //   4586: dup
    //   4587: bipush #42
    //   4589: iconst_0
    //   4590: bastore
    //   4591: dup
    //   4592: bipush #43
    //   4594: iconst_0
    //   4595: bastore
    //   4596: dup
    //   4597: bipush #44
    //   4599: iconst_0
    //   4600: bastore
    //   4601: dup
    //   4602: bipush #45
    //   4604: iconst_0
    //   4605: bastore
    //   4606: dup
    //   4607: bipush #46
    //   4609: iconst_0
    //   4610: bastore
    //   4611: dup
    //   4612: bipush #47
    //   4614: iconst_0
    //   4615: bastore
    //   4616: dup
    //   4617: bipush #48
    //   4619: iconst_0
    //   4620: bastore
    //   4621: dup
    //   4622: bipush #49
    //   4624: iconst_0
    //   4625: bastore
    //   4626: dup
    //   4627: bipush #50
    //   4629: iconst_0
    //   4630: bastore
    //   4631: dup
    //   4632: bipush #51
    //   4634: iconst_0
    //   4635: bastore
    //   4636: dup
    //   4637: bipush #52
    //   4639: iconst_0
    //   4640: bastore
    //   4641: dup
    //   4642: bipush #53
    //   4644: iconst_0
    //   4645: bastore
    //   4646: dup
    //   4647: bipush #54
    //   4649: iconst_0
    //   4650: bastore
    //   4651: dup
    //   4652: bipush #55
    //   4654: iconst_0
    //   4655: bastore
    //   4656: dup
    //   4657: bipush #56
    //   4659: iconst_0
    //   4660: bastore
    //   4661: dup
    //   4662: bipush #57
    //   4664: iconst_0
    //   4665: bastore
    //   4666: dup
    //   4667: bipush #58
    //   4669: iconst_0
    //   4670: bastore
    //   4671: dup
    //   4672: bipush #59
    //   4674: iconst_0
    //   4675: bastore
    //   4676: dup
    //   4677: bipush #60
    //   4679: iconst_0
    //   4680: bastore
    //   4681: dup
    //   4682: bipush #61
    //   4684: iconst_0
    //   4685: bastore
    //   4686: dup
    //   4687: bipush #62
    //   4689: iconst_0
    //   4690: bastore
    //   4691: dup
    //   4692: bipush #63
    //   4694: iconst_0
    //   4695: bastore
    //   4696: astore #5
    //   4698: bipush #64
    //   4700: newarray int
    //   4702: dup
    //   4703: iconst_0
    //   4704: ldc 1116352408
    //   4706: iastore
    //   4707: dup
    //   4708: iconst_1
    //   4709: ldc 1899447441
    //   4711: iastore
    //   4712: dup
    //   4713: iconst_2
    //   4714: ldc -1245643825
    //   4716: iastore
    //   4717: dup
    //   4718: iconst_3
    //   4719: ldc -373957723
    //   4721: iastore
    //   4722: dup
    //   4723: iconst_4
    //   4724: ldc 961987163
    //   4726: iastore
    //   4727: dup
    //   4728: iconst_5
    //   4729: ldc 1508970993
    //   4731: iastore
    //   4732: dup
    //   4733: bipush #6
    //   4735: ldc -1841331548
    //   4737: iastore
    //   4738: dup
    //   4739: bipush #7
    //   4741: ldc -1424204075
    //   4743: iastore
    //   4744: dup
    //   4745: bipush #8
    //   4747: ldc -670586216
    //   4749: iastore
    //   4750: dup
    //   4751: bipush #9
    //   4753: ldc 310598401
    //   4755: iastore
    //   4756: dup
    //   4757: bipush #10
    //   4759: ldc 607225278
    //   4761: iastore
    //   4762: dup
    //   4763: bipush #11
    //   4765: ldc 1426881987
    //   4767: iastore
    //   4768: dup
    //   4769: bipush #12
    //   4771: ldc 1925078388
    //   4773: iastore
    //   4774: dup
    //   4775: bipush #13
    //   4777: ldc -2132889090
    //   4779: iastore
    //   4780: dup
    //   4781: bipush #14
    //   4783: ldc -1680079193
    //   4785: iastore
    //   4786: dup
    //   4787: bipush #15
    //   4789: ldc -1046744716
    //   4791: iastore
    //   4792: dup
    //   4793: bipush #16
    //   4795: ldc -459576895
    //   4797: iastore
    //   4798: dup
    //   4799: bipush #17
    //   4801: ldc -272742522
    //   4803: iastore
    //   4804: dup
    //   4805: bipush #18
    //   4807: ldc 264347078
    //   4809: iastore
    //   4810: dup
    //   4811: bipush #19
    //   4813: ldc 604807628
    //   4815: iastore
    //   4816: dup
    //   4817: bipush #20
    //   4819: ldc 770255983
    //   4821: iastore
    //   4822: dup
    //   4823: bipush #21
    //   4825: ldc 1249150122
    //   4827: iastore
    //   4828: dup
    //   4829: bipush #22
    //   4831: ldc 1555081692
    //   4833: iastore
    //   4834: dup
    //   4835: bipush #23
    //   4837: ldc 1996064986
    //   4839: iastore
    //   4840: dup
    //   4841: bipush #24
    //   4843: ldc -1740746414
    //   4845: iastore
    //   4846: dup
    //   4847: bipush #25
    //   4849: ldc -1473132947
    //   4851: iastore
    //   4852: dup
    //   4853: bipush #26
    //   4855: ldc -1341970488
    //   4857: iastore
    //   4858: dup
    //   4859: bipush #27
    //   4861: ldc -1084653625
    //   4863: iastore
    //   4864: dup
    //   4865: bipush #28
    //   4867: ldc -958395405
    //   4869: iastore
    //   4870: dup
    //   4871: bipush #29
    //   4873: ldc -710438585
    //   4875: iastore
    //   4876: dup
    //   4877: bipush #30
    //   4879: ldc 113926993
    //   4881: iastore
    //   4882: dup
    //   4883: bipush #31
    //   4885: ldc 338241895
    //   4887: iastore
    //   4888: dup
    //   4889: bipush #32
    //   4891: ldc 666307205
    //   4893: iastore
    //   4894: dup
    //   4895: bipush #33
    //   4897: ldc 773529912
    //   4899: iastore
    //   4900: dup
    //   4901: bipush #34
    //   4903: ldc 1294757372
    //   4905: iastore
    //   4906: dup
    //   4907: bipush #35
    //   4909: ldc 1396182291
    //   4911: iastore
    //   4912: dup
    //   4913: bipush #36
    //   4915: ldc 1695183700
    //   4917: iastore
    //   4918: dup
    //   4919: bipush #37
    //   4921: ldc 1986661051
    //   4923: iastore
    //   4924: dup
    //   4925: bipush #38
    //   4927: ldc -2117940946
    //   4929: iastore
    //   4930: dup
    //   4931: bipush #39
    //   4933: ldc -1838011259
    //   4935: iastore
    //   4936: dup
    //   4937: bipush #40
    //   4939: ldc -1564481375
    //   4941: iastore
    //   4942: dup
    //   4943: bipush #41
    //   4945: ldc -1474664885
    //   4947: iastore
    //   4948: dup
    //   4949: bipush #42
    //   4951: ldc -1035236496
    //   4953: iastore
    //   4954: dup
    //   4955: bipush #43
    //   4957: ldc -949202525
    //   4959: iastore
    //   4960: dup
    //   4961: bipush #44
    //   4963: ldc -778901479
    //   4965: iastore
    //   4966: dup
    //   4967: bipush #45
    //   4969: ldc -694614492
    //   4971: iastore
    //   4972: dup
    //   4973: bipush #46
    //   4975: ldc -200395387
    //   4977: iastore
    //   4978: dup
    //   4979: bipush #47
    //   4981: ldc 275423344
    //   4983: iastore
    //   4984: dup
    //   4985: bipush #48
    //   4987: ldc 430227734
    //   4989: iastore
    //   4990: dup
    //   4991: bipush #49
    //   4993: ldc 506948616
    //   4995: iastore
    //   4996: dup
    //   4997: bipush #50
    //   4999: ldc 659060556
    //   5001: iastore
    //   5002: dup
    //   5003: bipush #51
    //   5005: ldc 883997877
    //   5007: iastore
    //   5008: dup
    //   5009: bipush #52
    //   5011: ldc 958139571
    //   5013: iastore
    //   5014: dup
    //   5015: bipush #53
    //   5017: ldc 1322822218
    //   5019: iastore
    //   5020: dup
    //   5021: bipush #54
    //   5023: ldc 1537002063
    //   5025: iastore
    //   5026: dup
    //   5027: bipush #55
    //   5029: ldc 1747873779
    //   5031: iastore
    //   5032: dup
    //   5033: bipush #56
    //   5035: ldc 1955562222
    //   5037: iastore
    //   5038: dup
    //   5039: bipush #57
    //   5041: ldc 2024104815
    //   5043: iastore
    //   5044: dup
    //   5045: bipush #58
    //   5047: ldc -2067236844
    //   5049: iastore
    //   5050: dup
    //   5051: bipush #59
    //   5053: ldc -1933114872
    //   5055: iastore
    //   5056: dup
    //   5057: bipush #60
    //   5059: ldc -1866530822
    //   5061: iastore
    //   5062: dup
    //   5063: bipush #61
    //   5065: ldc -1538233109
    //   5067: iastore
    //   5068: dup
    //   5069: bipush #62
    //   5071: ldc -1090935817
    //   5073: iastore
    //   5074: dup
    //   5075: bipush #63
    //   5077: ldc -965641998
    //   5079: iastore
    //   5080: astore #6
    //   5082: iconst_2
    //   5083: newarray int
    //   5085: dup
    //   5086: iconst_0
    //   5087: iconst_0
    //   5088: iastore
    //   5089: dup
    //   5090: iconst_1
    //   5091: iconst_0
    //   5092: iastore
    //   5093: astore #7
    //   5095: bipush #8
    //   5097: newarray int
    //   5099: dup
    //   5100: iconst_0
    //   5101: ldc 1779033703
    //   5103: iastore
    //   5104: dup
    //   5105: iconst_1
    //   5106: ldc -1150833019
    //   5108: iastore
    //   5109: dup
    //   5110: iconst_2
    //   5111: ldc 1013904242
    //   5113: iastore
    //   5114: dup
    //   5115: iconst_3
    //   5116: ldc -1521486534
    //   5118: iastore
    //   5119: dup
    //   5120: iconst_4
    //   5121: ldc 1359893119
    //   5123: iastore
    //   5124: dup
    //   5125: iconst_5
    //   5126: ldc -1694144372
    //   5128: iastore
    //   5129: dup
    //   5130: bipush #6
    //   5132: ldc 528734635
    //   5134: iastore
    //   5135: dup
    //   5136: bipush #7
    //   5138: ldc 1541459225
    //   5140: iastore
    //   5141: astore #8
    //   5143: bipush #64
    //   5145: newarray byte
    //   5147: astore #9
    //   5149: bipush #64
    //   5151: newarray byte
    //   5153: astore #10
    //   5155: aload_3
    //   5156: arraylength
    //   5157: istore #11
    //   5159: aload #7
    //   5161: iconst_0
    //   5162: iaload
    //   5163: bipush #63
    //   5165: iand
    //   5166: istore #12
    //   5168: aload #7
    //   5170: iconst_0
    //   5171: dup2
    //   5172: iaload
    //   5173: iload #11
    //   5175: iadd
    //   5176: iastore
    //   5177: aload #7
    //   5179: iconst_0
    //   5180: dup2
    //   5181: iaload
    //   5182: iconst_m1
    //   5183: iand
    //   5184: iastore
    //   5185: aload #7
    //   5187: iconst_0
    //   5188: iaload
    //   5189: iload #11
    //   5191: if_icmpge -> 5209
    //   5194: aload #7
    //   5196: iconst_1
    //   5197: dup2
    //   5198: iaload
    //   5199: iconst_1
    //   5200: iadd
    //   5201: iastore
    //   5202: goto -> 5209
    //   5205: invokestatic a : (Ljava/lang/Throwable;)Ljava/lang/Throwable;
    //   5208: athrow
    //   5209: iconst_0
    //   5210: istore #13
    //   5212: iload #11
    //   5214: bipush #64
    //   5216: if_icmplt -> 5825
    //   5219: iconst_0
    //   5220: istore #14
    //   5222: iload #14
    //   5224: bipush #64
    //   5226: if_icmpge -> 5248
    //   5229: aload #10
    //   5231: iload #14
    //   5233: aload_3
    //   5234: iload #13
    //   5236: iload #14
    //   5238: iadd
    //   5239: baload
    //   5240: bastore
    //   5241: iinc #14, 1
    //   5244: iload_2
    //   5245: ifne -> 5222
    //   5248: bipush #64
    //   5250: newarray int
    //   5252: astore #14
    //   5254: bipush #8
    //   5256: newarray int
    //   5258: astore #15
    //   5260: iconst_0
    //   5261: istore #16
    //   5263: iload #16
    //   5265: bipush #8
    //   5267: if_icmpge -> 5287
    //   5270: aload #15
    //   5272: iload #16
    //   5274: aload #8
    //   5276: iload #16
    //   5278: iaload
    //   5279: iastore
    //   5280: iinc #16, 1
    //   5283: iload_2
    //   5284: ifne -> 5263
    //   5287: iconst_0
    //   5288: istore #16
    //   5290: iload #16
    //   5292: bipush #64
    //   5294: if_icmpge -> 5785
    //   5297: iload #16
    //   5299: bipush #16
    //   5301: if_icmpge -> 5382
    //   5304: aload #14
    //   5306: iload #16
    //   5308: aload #10
    //   5310: iconst_4
    //   5311: iload #16
    //   5313: imul
    //   5314: baload
    //   5315: sipush #255
    //   5318: iand
    //   5319: bipush #24
    //   5321: ishl
    //   5322: aload #10
    //   5324: iconst_4
    //   5325: iload #16
    //   5327: imul
    //   5328: iconst_1
    //   5329: iadd
    //   5330: baload
    //   5331: sipush #255
    //   5334: iand
    //   5335: bipush #16
    //   5337: ishl
    //   5338: ior
    //   5339: aload #10
    //   5341: iconst_4
    //   5342: iload #16
    //   5344: imul
    //   5345: iconst_2
    //   5346: iadd
    //   5347: baload
    //   5348: sipush #255
    //   5351: iand
    //   5352: bipush #8
    //   5354: ishl
    //   5355: ior
    //   5356: aload #10
    //   5358: iconst_4
    //   5359: iload #16
    //   5361: imul
    //   5362: iconst_3
    //   5363: iadd
    //   5364: baload
    //   5365: sipush #255
    //   5368: iand
    //   5369: ior
    //   5370: iastore
    //   5371: iload_2
    //   5372: ifne -> 5525
    //   5375: goto -> 5382
    //   5378: invokestatic a : (Ljava/lang/Throwable;)Ljava/lang/Throwable;
    //   5381: athrow
    //   5382: aload #14
    //   5384: iload #16
    //   5386: aload #14
    //   5388: iload #16
    //   5390: iconst_2
    //   5391: isub
    //   5392: iaload
    //   5393: bipush #17
    //   5395: iushr
    //   5396: aload #14
    //   5398: iload #16
    //   5400: iconst_2
    //   5401: isub
    //   5402: iaload
    //   5403: bipush #15
    //   5405: ishl
    //   5406: ior
    //   5407: aload #14
    //   5409: iload #16
    //   5411: iconst_2
    //   5412: isub
    //   5413: iaload
    //   5414: bipush #19
    //   5416: iushr
    //   5417: aload #14
    //   5419: iload #16
    //   5421: iconst_2
    //   5422: isub
    //   5423: iaload
    //   5424: bipush #13
    //   5426: ishl
    //   5427: ior
    //   5428: ixor
    //   5429: aload #14
    //   5431: iload #16
    //   5433: iconst_2
    //   5434: isub
    //   5435: iaload
    //   5436: bipush #10
    //   5438: iushr
    //   5439: ixor
    //   5440: aload #14
    //   5442: iload #16
    //   5444: bipush #7
    //   5446: isub
    //   5447: iaload
    //   5448: iadd
    //   5449: aload #14
    //   5451: iload #16
    //   5453: bipush #15
    //   5455: isub
    //   5456: iaload
    //   5457: bipush #7
    //   5459: iushr
    //   5460: aload #14
    //   5462: iload #16
    //   5464: bipush #15
    //   5466: isub
    //   5467: iaload
    //   5468: bipush #25
    //   5470: ishl
    //   5471: ior
    //   5472: aload #14
    //   5474: iload #16
    //   5476: bipush #15
    //   5478: isub
    //   5479: iaload
    //   5480: bipush #18
    //   5482: iushr
    //   5483: aload #14
    //   5485: iload #16
    //   5487: bipush #15
    //   5489: isub
    //   5490: iaload
    //   5491: bipush #14
    //   5493: ishl
    //   5494: ior
    //   5495: ixor
    //   5496: aload #14
    //   5498: iload #16
    //   5500: bipush #15
    //   5502: isub
    //   5503: iaload
    //   5504: iconst_3
    //   5505: iushr
    //   5506: ixor
    //   5507: iadd
    //   5508: aload #14
    //   5510: iload #16
    //   5512: bipush #16
    //   5514: isub
    //   5515: iaload
    //   5516: iadd
    //   5517: iastore
    //   5518: goto -> 5525
    //   5521: invokestatic a : (Ljava/lang/Throwable;)Ljava/lang/Throwable;
    //   5524: athrow
    //   5525: aload #15
    //   5527: bipush #7
    //   5529: iaload
    //   5530: aload #15
    //   5532: iconst_4
    //   5533: iaload
    //   5534: bipush #6
    //   5536: iushr
    //   5537: aload #15
    //   5539: iconst_4
    //   5540: iaload
    //   5541: bipush #26
    //   5543: ishl
    //   5544: ior
    //   5545: aload #15
    //   5547: iconst_4
    //   5548: iaload
    //   5549: bipush #11
    //   5551: iushr
    //   5552: aload #15
    //   5554: iconst_4
    //   5555: iaload
    //   5556: bipush #21
    //   5558: ishl
    //   5559: ior
    //   5560: ixor
    //   5561: aload #15
    //   5563: iconst_4
    //   5564: iaload
    //   5565: bipush #25
    //   5567: iushr
    //   5568: aload #15
    //   5570: iconst_4
    //   5571: iaload
    //   5572: bipush #7
    //   5574: ishl
    //   5575: ior
    //   5576: ixor
    //   5577: iadd
    //   5578: aload #15
    //   5580: bipush #6
    //   5582: iaload
    //   5583: aload #15
    //   5585: iconst_4
    //   5586: iaload
    //   5587: aload #15
    //   5589: iconst_5
    //   5590: iaload
    //   5591: aload #15
    //   5593: bipush #6
    //   5595: iaload
    //   5596: ixor
    //   5597: iand
    //   5598: ixor
    //   5599: iadd
    //   5600: aload #6
    //   5602: iload #16
    //   5604: iaload
    //   5605: iadd
    //   5606: aload #14
    //   5608: iload #16
    //   5610: iaload
    //   5611: iadd
    //   5612: istore #17
    //   5614: aload #15
    //   5616: iconst_0
    //   5617: iaload
    //   5618: iconst_2
    //   5619: iushr
    //   5620: aload #15
    //   5622: iconst_0
    //   5623: iaload
    //   5624: bipush #30
    //   5626: ishl
    //   5627: ior
    //   5628: aload #15
    //   5630: iconst_0
    //   5631: iaload
    //   5632: bipush #13
    //   5634: iushr
    //   5635: aload #15
    //   5637: iconst_0
    //   5638: iaload
    //   5639: bipush #19
    //   5641: ishl
    //   5642: ior
    //   5643: ixor
    //   5644: aload #15
    //   5646: iconst_0
    //   5647: iaload
    //   5648: bipush #22
    //   5650: iushr
    //   5651: aload #15
    //   5653: iconst_0
    //   5654: iaload
    //   5655: bipush #10
    //   5657: ishl
    //   5658: ior
    //   5659: ixor
    //   5660: aload #15
    //   5662: iconst_0
    //   5663: iaload
    //   5664: aload #15
    //   5666: iconst_1
    //   5667: iaload
    //   5668: iand
    //   5669: aload #15
    //   5671: iconst_2
    //   5672: iaload
    //   5673: aload #15
    //   5675: iconst_0
    //   5676: iaload
    //   5677: aload #15
    //   5679: iconst_1
    //   5680: iaload
    //   5681: ior
    //   5682: iand
    //   5683: ior
    //   5684: iadd
    //   5685: istore #18
    //   5687: aload #15
    //   5689: iconst_3
    //   5690: dup2
    //   5691: iaload
    //   5692: iload #17
    //   5694: iadd
    //   5695: iastore
    //   5696: aload #15
    //   5698: bipush #7
    //   5700: iload #17
    //   5702: iload #18
    //   5704: iadd
    //   5705: iastore
    //   5706: aload #15
    //   5708: bipush #7
    //   5710: iaload
    //   5711: istore #17
    //   5713: aload #15
    //   5715: bipush #7
    //   5717: aload #15
    //   5719: bipush #6
    //   5721: iaload
    //   5722: iastore
    //   5723: aload #15
    //   5725: bipush #6
    //   5727: aload #15
    //   5729: iconst_5
    //   5730: iaload
    //   5731: iastore
    //   5732: aload #15
    //   5734: iconst_5
    //   5735: aload #15
    //   5737: iconst_4
    //   5738: iaload
    //   5739: iastore
    //   5740: aload #15
    //   5742: iconst_4
    //   5743: aload #15
    //   5745: iconst_3
    //   5746: iaload
    //   5747: iastore
    //   5748: aload #15
    //   5750: iconst_3
    //   5751: aload #15
    //   5753: iconst_2
    //   5754: iaload
    //   5755: iastore
    //   5756: aload #15
    //   5758: iconst_2
    //   5759: aload #15
    //   5761: iconst_1
    //   5762: iaload
    //   5763: iastore
    //   5764: aload #15
    //   5766: iconst_1
    //   5767: aload #15
    //   5769: iconst_0
    //   5770: iaload
    //   5771: iastore
    //   5772: aload #15
    //   5774: iconst_0
    //   5775: iload #17
    //   5777: iastore
    //   5778: iinc #16, 1
    //   5781: iload_2
    //   5782: ifne -> 5290
    //   5785: iconst_0
    //   5786: istore #16
    //   5788: iload #16
    //   5790: bipush #8
    //   5792: if_icmpge -> 5815
    //   5795: aload #8
    //   5797: iload #16
    //   5799: dup2
    //   5800: iaload
    //   5801: aload #15
    //   5803: iload #16
    //   5805: iaload
    //   5806: iadd
    //   5807: iastore
    //   5808: iinc #16, 1
    //   5811: iload_2
    //   5812: ifne -> 5788
    //   5815: iinc #13, 64
    //   5818: iinc #11, -64
    //   5821: iload_2
    //   5822: ifne -> 5212
    //   5825: iload #11
    //   5827: ifle -> 5862
    //   5830: iconst_0
    //   5831: istore #14
    //   5833: iload #14
    //   5835: iload #11
    //   5837: if_icmpge -> 5862
    //   5840: aload #9
    //   5842: iload #12
    //   5844: iload #14
    //   5846: iadd
    //   5847: aload_3
    //   5848: iload #13
    //   5850: iload #14
    //   5852: iadd
    //   5853: baload
    //   5854: bastore
    //   5855: iinc #14, 1
    //   5858: iload_2
    //   5859: ifne -> 5833
    //   5862: aload #7
    //   5864: iconst_0
    //   5865: iaload
    //   5866: bipush #29
    //   5868: iushr
    //   5869: aload #7
    //   5871: iconst_1
    //   5872: iaload
    //   5873: iconst_3
    //   5874: ishl
    //   5875: ior
    //   5876: istore #14
    //   5878: aload #7
    //   5880: iconst_0
    //   5881: iaload
    //   5882: iconst_3
    //   5883: ishl
    //   5884: istore #15
    //   5886: aload #7
    //   5888: iconst_0
    //   5889: iaload
    //   5890: bipush #63
    //   5892: iand
    //   5893: istore #16
    //   5895: iload #16
    //   5897: bipush #56
    //   5899: if_icmpge -> 5914
    //   5902: bipush #56
    //   5904: iload #16
    //   5906: isub
    //   5907: goto -> 5919
    //   5910: invokestatic a : (Ljava/lang/Throwable;)Ljava/lang/Throwable;
    //   5913: athrow
    //   5914: bipush #120
    //   5916: iload #16
    //   5918: isub
    //   5919: istore #17
    //   5921: aload #7
    //   5923: iconst_0
    //   5924: iaload
    //   5925: bipush #63
    //   5927: iand
    //   5928: istore #12
    //   5930: bipush #64
    //   5932: iload #12
    //   5934: isub
    //   5935: istore #18
    //   5937: aload #7
    //   5939: iconst_0
    //   5940: dup2
    //   5941: iaload
    //   5942: iload #17
    //   5944: iadd
    //   5945: iastore
    //   5946: aload #7
    //   5948: iconst_0
    //   5949: dup2
    //   5950: iaload
    //   5951: iconst_m1
    //   5952: iand
    //   5953: iastore
    //   5954: aload #7
    //   5956: iconst_0
    //   5957: iaload
    //   5958: iload #17
    //   5960: if_icmpge -> 5978
    //   5963: aload #7
    //   5965: iconst_1
    //   5966: dup2
    //   5967: iaload
    //   5968: iconst_1
    //   5969: iadd
    //   5970: iastore
    //   5971: goto -> 5978
    //   5974: invokestatic a : (Ljava/lang/Throwable;)Ljava/lang/Throwable;
    //   5977: athrow
    //   5978: iconst_0
    //   5979: istore #13
    //   5981: iload #12
    //   5983: ifle -> 6614
    //   5986: iload #17
    //   5988: iload #18
    //   5990: if_icmplt -> 6614
    //   5993: goto -> 6000
    //   5996: invokestatic a : (Ljava/lang/Throwable;)Ljava/lang/Throwable;
    //   5999: athrow
    //   6000: iconst_0
    //   6001: istore #19
    //   6003: iload #19
    //   6005: iload #18
    //   6007: if_icmpge -> 6030
    //   6010: aload #9
    //   6012: iload #12
    //   6014: iload #19
    //   6016: iadd
    //   6017: aload #5
    //   6019: iload #19
    //   6021: baload
    //   6022: bastore
    //   6023: iinc #19, 1
    //   6026: iload_2
    //   6027: ifne -> 6003
    //   6030: bipush #64
    //   6032: newarray int
    //   6034: astore #19
    //   6036: bipush #8
    //   6038: newarray int
    //   6040: astore #20
    //   6042: iconst_0
    //   6043: istore #21
    //   6045: iload #21
    //   6047: bipush #8
    //   6049: if_icmpge -> 6069
    //   6052: aload #20
    //   6054: iload #21
    //   6056: aload #8
    //   6058: iload #21
    //   6060: iaload
    //   6061: iastore
    //   6062: iinc #21, 1
    //   6065: iload_2
    //   6066: ifne -> 6045
    //   6069: iconst_0
    //   6070: istore #21
    //   6072: iload #21
    //   6074: bipush #64
    //   6076: if_icmpge -> 6567
    //   6079: iload #21
    //   6081: bipush #16
    //   6083: if_icmpge -> 6164
    //   6086: aload #19
    //   6088: iload #21
    //   6090: aload #9
    //   6092: iconst_4
    //   6093: iload #21
    //   6095: imul
    //   6096: baload
    //   6097: sipush #255
    //   6100: iand
    //   6101: bipush #24
    //   6103: ishl
    //   6104: aload #9
    //   6106: iconst_4
    //   6107: iload #21
    //   6109: imul
    //   6110: iconst_1
    //   6111: iadd
    //   6112: baload
    //   6113: sipush #255
    //   6116: iand
    //   6117: bipush #16
    //   6119: ishl
    //   6120: ior
    //   6121: aload #9
    //   6123: iconst_4
    //   6124: iload #21
    //   6126: imul
    //   6127: iconst_2
    //   6128: iadd
    //   6129: baload
    //   6130: sipush #255
    //   6133: iand
    //   6134: bipush #8
    //   6136: ishl
    //   6137: ior
    //   6138: aload #9
    //   6140: iconst_4
    //   6141: iload #21
    //   6143: imul
    //   6144: iconst_3
    //   6145: iadd
    //   6146: baload
    //   6147: sipush #255
    //   6150: iand
    //   6151: ior
    //   6152: iastore
    //   6153: iload_2
    //   6154: ifne -> 6307
    //   6157: goto -> 6164
    //   6160: invokestatic a : (Ljava/lang/Throwable;)Ljava/lang/Throwable;
    //   6163: athrow
    //   6164: aload #19
    //   6166: iload #21
    //   6168: aload #19
    //   6170: iload #21
    //   6172: iconst_2
    //   6173: isub
    //   6174: iaload
    //   6175: bipush #17
    //   6177: iushr
    //   6178: aload #19
    //   6180: iload #21
    //   6182: iconst_2
    //   6183: isub
    //   6184: iaload
    //   6185: bipush #15
    //   6187: ishl
    //   6188: ior
    //   6189: aload #19
    //   6191: iload #21
    //   6193: iconst_2
    //   6194: isub
    //   6195: iaload
    //   6196: bipush #19
    //   6198: iushr
    //   6199: aload #19
    //   6201: iload #21
    //   6203: iconst_2
    //   6204: isub
    //   6205: iaload
    //   6206: bipush #13
    //   6208: ishl
    //   6209: ior
    //   6210: ixor
    //   6211: aload #19
    //   6213: iload #21
    //   6215: iconst_2
    //   6216: isub
    //   6217: iaload
    //   6218: bipush #10
    //   6220: iushr
    //   6221: ixor
    //   6222: aload #19
    //   6224: iload #21
    //   6226: bipush #7
    //   6228: isub
    //   6229: iaload
    //   6230: iadd
    //   6231: aload #19
    //   6233: iload #21
    //   6235: bipush #15
    //   6237: isub
    //   6238: iaload
    //   6239: bipush #7
    //   6241: iushr
    //   6242: aload #19
    //   6244: iload #21
    //   6246: bipush #15
    //   6248: isub
    //   6249: iaload
    //   6250: bipush #25
    //   6252: ishl
    //   6253: ior
    //   6254: aload #19
    //   6256: iload #21
    //   6258: bipush #15
    //   6260: isub
    //   6261: iaload
    //   6262: bipush #18
    //   6264: iushr
    //   6265: aload #19
    //   6267: iload #21
    //   6269: bipush #15
    //   6271: isub
    //   6272: iaload
    //   6273: bipush #14
    //   6275: ishl
    //   6276: ior
    //   6277: ixor
    //   6278: aload #19
    //   6280: iload #21
    //   6282: bipush #15
    //   6284: isub
    //   6285: iaload
    //   6286: iconst_3
    //   6287: iushr
    //   6288: ixor
    //   6289: iadd
    //   6290: aload #19
    //   6292: iload #21
    //   6294: bipush #16
    //   6296: isub
    //   6297: iaload
    //   6298: iadd
    //   6299: iastore
    //   6300: goto -> 6307
    //   6303: invokestatic a : (Ljava/lang/Throwable;)Ljava/lang/Throwable;
    //   6306: athrow
    //   6307: aload #20
    //   6309: bipush #7
    //   6311: iaload
    //   6312: aload #20
    //   6314: iconst_4
    //   6315: iaload
    //   6316: bipush #6
    //   6318: iushr
    //   6319: aload #20
    //   6321: iconst_4
    //   6322: iaload
    //   6323: bipush #26
    //   6325: ishl
    //   6326: ior
    //   6327: aload #20
    //   6329: iconst_4
    //   6330: iaload
    //   6331: bipush #11
    //   6333: iushr
    //   6334: aload #20
    //   6336: iconst_4
    //   6337: iaload
    //   6338: bipush #21
    //   6340: ishl
    //   6341: ior
    //   6342: ixor
    //   6343: aload #20
    //   6345: iconst_4
    //   6346: iaload
    //   6347: bipush #25
    //   6349: iushr
    //   6350: aload #20
    //   6352: iconst_4
    //   6353: iaload
    //   6354: bipush #7
    //   6356: ishl
    //   6357: ior
    //   6358: ixor
    //   6359: iadd
    //   6360: aload #20
    //   6362: bipush #6
    //   6364: iaload
    //   6365: aload #20
    //   6367: iconst_4
    //   6368: iaload
    //   6369: aload #20
    //   6371: iconst_5
    //   6372: iaload
    //   6373: aload #20
    //   6375: bipush #6
    //   6377: iaload
    //   6378: ixor
    //   6379: iand
    //   6380: ixor
    //   6381: iadd
    //   6382: aload #6
    //   6384: iload #21
    //   6386: iaload
    //   6387: iadd
    //   6388: aload #19
    //   6390: iload #21
    //   6392: iaload
    //   6393: iadd
    //   6394: istore #22
    //   6396: aload #20
    //   6398: iconst_0
    //   6399: iaload
    //   6400: iconst_2
    //   6401: iushr
    //   6402: aload #20
    //   6404: iconst_0
    //   6405: iaload
    //   6406: bipush #30
    //   6408: ishl
    //   6409: ior
    //   6410: aload #20
    //   6412: iconst_0
    //   6413: iaload
    //   6414: bipush #13
    //   6416: iushr
    //   6417: aload #20
    //   6419: iconst_0
    //   6420: iaload
    //   6421: bipush #19
    //   6423: ishl
    //   6424: ior
    //   6425: ixor
    //   6426: aload #20
    //   6428: iconst_0
    //   6429: iaload
    //   6430: bipush #22
    //   6432: iushr
    //   6433: aload #20
    //   6435: iconst_0
    //   6436: iaload
    //   6437: bipush #10
    //   6439: ishl
    //   6440: ior
    //   6441: ixor
    //   6442: aload #20
    //   6444: iconst_0
    //   6445: iaload
    //   6446: aload #20
    //   6448: iconst_1
    //   6449: iaload
    //   6450: iand
    //   6451: aload #20
    //   6453: iconst_2
    //   6454: iaload
    //   6455: aload #20
    //   6457: iconst_0
    //   6458: iaload
    //   6459: aload #20
    //   6461: iconst_1
    //   6462: iaload
    //   6463: ior
    //   6464: iand
    //   6465: ior
    //   6466: iadd
    //   6467: istore #23
    //   6469: aload #20
    //   6471: iconst_3
    //   6472: dup2
    //   6473: iaload
    //   6474: iload #22
    //   6476: iadd
    //   6477: iastore
    //   6478: aload #20
    //   6480: bipush #7
    //   6482: iload #22
    //   6484: iload #23
    //   6486: iadd
    //   6487: iastore
    //   6488: aload #20
    //   6490: bipush #7
    //   6492: iaload
    //   6493: istore #22
    //   6495: aload #20
    //   6497: bipush #7
    //   6499: aload #20
    //   6501: bipush #6
    //   6503: iaload
    //   6504: iastore
    //   6505: aload #20
    //   6507: bipush #6
    //   6509: aload #20
    //   6511: iconst_5
    //   6512: iaload
    //   6513: iastore
    //   6514: aload #20
    //   6516: iconst_5
    //   6517: aload #20
    //   6519: iconst_4
    //   6520: iaload
    //   6521: iastore
    //   6522: aload #20
    //   6524: iconst_4
    //   6525: aload #20
    //   6527: iconst_3
    //   6528: iaload
    //   6529: iastore
    //   6530: aload #20
    //   6532: iconst_3
    //   6533: aload #20
    //   6535: iconst_2
    //   6536: iaload
    //   6537: iastore
    //   6538: aload #20
    //   6540: iconst_2
    //   6541: aload #20
    //   6543: iconst_1
    //   6544: iaload
    //   6545: iastore
    //   6546: aload #20
    //   6548: iconst_1
    //   6549: aload #20
    //   6551: iconst_0
    //   6552: iaload
    //   6553: iastore
    //   6554: aload #20
    //   6556: iconst_0
    //   6557: iload #22
    //   6559: iastore
    //   6560: iinc #21, 1
    //   6563: iload_2
    //   6564: ifne -> 6072
    //   6567: iconst_0
    //   6568: istore #21
    //   6570: iload #21
    //   6572: bipush #8
    //   6574: if_icmpge -> 6597
    //   6577: aload #8
    //   6579: iload #21
    //   6581: dup2
    //   6582: iaload
    //   6583: aload #20
    //   6585: iload #21
    //   6587: iaload
    //   6588: iadd
    //   6589: iastore
    //   6590: iinc #21, 1
    //   6593: iload_2
    //   6594: ifne -> 6570
    //   6597: iload #13
    //   6599: iload #18
    //   6601: iadd
    //   6602: istore #13
    //   6604: iload #17
    //   6606: iload #18
    //   6608: isub
    //   6609: istore #17
    //   6611: iconst_0
    //   6612: istore #12
    //   6614: iload #17
    //   6616: bipush #64
    //   6618: if_icmplt -> 7228
    //   6621: iconst_0
    //   6622: istore #19
    //   6624: iload #19
    //   6626: bipush #64
    //   6628: if_icmpge -> 6651
    //   6631: aload #10
    //   6633: iload #19
    //   6635: aload #5
    //   6637: iload #13
    //   6639: iload #19
    //   6641: iadd
    //   6642: baload
    //   6643: bastore
    //   6644: iinc #19, 1
    //   6647: iload_2
    //   6648: ifne -> 6624
    //   6651: bipush #64
    //   6653: newarray int
    //   6655: astore #19
    //   6657: bipush #8
    //   6659: newarray int
    //   6661: astore #20
    //   6663: iconst_0
    //   6664: istore #21
    //   6666: iload #21
    //   6668: bipush #8
    //   6670: if_icmpge -> 6690
    //   6673: aload #20
    //   6675: iload #21
    //   6677: aload #8
    //   6679: iload #21
    //   6681: iaload
    //   6682: iastore
    //   6683: iinc #21, 1
    //   6686: iload_2
    //   6687: ifne -> 6666
    //   6690: iconst_0
    //   6691: istore #21
    //   6693: iload #21
    //   6695: bipush #64
    //   6697: if_icmpge -> 7188
    //   6700: iload #21
    //   6702: bipush #16
    //   6704: if_icmpge -> 6785
    //   6707: aload #19
    //   6709: iload #21
    //   6711: aload #10
    //   6713: iconst_4
    //   6714: iload #21
    //   6716: imul
    //   6717: baload
    //   6718: sipush #255
    //   6721: iand
    //   6722: bipush #24
    //   6724: ishl
    //   6725: aload #10
    //   6727: iconst_4
    //   6728: iload #21
    //   6730: imul
    //   6731: iconst_1
    //   6732: iadd
    //   6733: baload
    //   6734: sipush #255
    //   6737: iand
    //   6738: bipush #16
    //   6740: ishl
    //   6741: ior
    //   6742: aload #10
    //   6744: iconst_4
    //   6745: iload #21
    //   6747: imul
    //   6748: iconst_2
    //   6749: iadd
    //   6750: baload
    //   6751: sipush #255
    //   6754: iand
    //   6755: bipush #8
    //   6757: ishl
    //   6758: ior
    //   6759: aload #10
    //   6761: iconst_4
    //   6762: iload #21
    //   6764: imul
    //   6765: iconst_3
    //   6766: iadd
    //   6767: baload
    //   6768: sipush #255
    //   6771: iand
    //   6772: ior
    //   6773: iastore
    //   6774: iload_2
    //   6775: ifne -> 6928
    //   6778: goto -> 6785
    //   6781: invokestatic a : (Ljava/lang/Throwable;)Ljava/lang/Throwable;
    //   6784: athrow
    //   6785: aload #19
    //   6787: iload #21
    //   6789: aload #19
    //   6791: iload #21
    //   6793: iconst_2
    //   6794: isub
    //   6795: iaload
    //   6796: bipush #17
    //   6798: iushr
    //   6799: aload #19
    //   6801: iload #21
    //   6803: iconst_2
    //   6804: isub
    //   6805: iaload
    //   6806: bipush #15
    //   6808: ishl
    //   6809: ior
    //   6810: aload #19
    //   6812: iload #21
    //   6814: iconst_2
    //   6815: isub
    //   6816: iaload
    //   6817: bipush #19
    //   6819: iushr
    //   6820: aload #19
    //   6822: iload #21
    //   6824: iconst_2
    //   6825: isub
    //   6826: iaload
    //   6827: bipush #13
    //   6829: ishl
    //   6830: ior
    //   6831: ixor
    //   6832: aload #19
    //   6834: iload #21
    //   6836: iconst_2
    //   6837: isub
    //   6838: iaload
    //   6839: bipush #10
    //   6841: iushr
    //   6842: ixor
    //   6843: aload #19
    //   6845: iload #21
    //   6847: bipush #7
    //   6849: isub
    //   6850: iaload
    //   6851: iadd
    //   6852: aload #19
    //   6854: iload #21
    //   6856: bipush #15
    //   6858: isub
    //   6859: iaload
    //   6860: bipush #7
    //   6862: iushr
    //   6863: aload #19
    //   6865: iload #21
    //   6867: bipush #15
    //   6869: isub
    //   6870: iaload
    //   6871: bipush #25
    //   6873: ishl
    //   6874: ior
    //   6875: aload #19
    //   6877: iload #21
    //   6879: bipush #15
    //   6881: isub
    //   6882: iaload
    //   6883: bipush #18
    //   6885: iushr
    //   6886: aload #19
    //   6888: iload #21
    //   6890: bipush #15
    //   6892: isub
    //   6893: iaload
    //   6894: bipush #14
    //   6896: ishl
    //   6897: ior
    //   6898: ixor
    //   6899: aload #19
    //   6901: iload #21
    //   6903: bipush #15
    //   6905: isub
    //   6906: iaload
    //   6907: iconst_3
    //   6908: iushr
    //   6909: ixor
    //   6910: iadd
    //   6911: aload #19
    //   6913: iload #21
    //   6915: bipush #16
    //   6917: isub
    //   6918: iaload
    //   6919: iadd
    //   6920: iastore
    //   6921: goto -> 6928
    //   6924: invokestatic a : (Ljava/lang/Throwable;)Ljava/lang/Throwable;
    //   6927: athrow
    //   6928: aload #20
    //   6930: bipush #7
    //   6932: iaload
    //   6933: aload #20
    //   6935: iconst_4
    //   6936: iaload
    //   6937: bipush #6
    //   6939: iushr
    //   6940: aload #20
    //   6942: iconst_4
    //   6943: iaload
    //   6944: bipush #26
    //   6946: ishl
    //   6947: ior
    //   6948: aload #20
    //   6950: iconst_4
    //   6951: iaload
    //   6952: bipush #11
    //   6954: iushr
    //   6955: aload #20
    //   6957: iconst_4
    //   6958: iaload
    //   6959: bipush #21
    //   6961: ishl
    //   6962: ior
    //   6963: ixor
    //   6964: aload #20
    //   6966: iconst_4
    //   6967: iaload
    //   6968: bipush #25
    //   6970: iushr
    //   6971: aload #20
    //   6973: iconst_4
    //   6974: iaload
    //   6975: bipush #7
    //   6977: ishl
    //   6978: ior
    //   6979: ixor
    //   6980: iadd
    //   6981: aload #20
    //   6983: bipush #6
    //   6985: iaload
    //   6986: aload #20
    //   6988: iconst_4
    //   6989: iaload
    //   6990: aload #20
    //   6992: iconst_5
    //   6993: iaload
    //   6994: aload #20
    //   6996: bipush #6
    //   6998: iaload
    //   6999: ixor
    //   7000: iand
    //   7001: ixor
    //   7002: iadd
    //   7003: aload #6
    //   7005: iload #21
    //   7007: iaload
    //   7008: iadd
    //   7009: aload #19
    //   7011: iload #21
    //   7013: iaload
    //   7014: iadd
    //   7015: istore #22
    //   7017: aload #20
    //   7019: iconst_0
    //   7020: iaload
    //   7021: iconst_2
    //   7022: iushr
    //   7023: aload #20
    //   7025: iconst_0
    //   7026: iaload
    //   7027: bipush #30
    //   7029: ishl
    //   7030: ior
    //   7031: aload #20
    //   7033: iconst_0
    //   7034: iaload
    //   7035: bipush #13
    //   7037: iushr
    //   7038: aload #20
    //   7040: iconst_0
    //   7041: iaload
    //   7042: bipush #19
    //   7044: ishl
    //   7045: ior
    //   7046: ixor
    //   7047: aload #20
    //   7049: iconst_0
    //   7050: iaload
    //   7051: bipush #22
    //   7053: iushr
    //   7054: aload #20
    //   7056: iconst_0
    //   7057: iaload
    //   7058: bipush #10
    //   7060: ishl
    //   7061: ior
    //   7062: ixor
    //   7063: aload #20
    //   7065: iconst_0
    //   7066: iaload
    //   7067: aload #20
    //   7069: iconst_1
    //   7070: iaload
    //   7071: iand
    //   7072: aload #20
    //   7074: iconst_2
    //   7075: iaload
    //   7076: aload #20
    //   7078: iconst_0
    //   7079: iaload
    //   7080: aload #20
    //   7082: iconst_1
    //   7083: iaload
    //   7084: ior
    //   7085: iand
    //   7086: ior
    //   7087: iadd
    //   7088: istore #23
    //   7090: aload #20
    //   7092: iconst_3
    //   7093: dup2
    //   7094: iaload
    //   7095: iload #22
    //   7097: iadd
    //   7098: iastore
    //   7099: aload #20
    //   7101: bipush #7
    //   7103: iload #22
    //   7105: iload #23
    //   7107: iadd
    //   7108: iastore
    //   7109: aload #20
    //   7111: bipush #7
    //   7113: iaload
    //   7114: istore #22
    //   7116: aload #20
    //   7118: bipush #7
    //   7120: aload #20
    //   7122: bipush #6
    //   7124: iaload
    //   7125: iastore
    //   7126: aload #20
    //   7128: bipush #6
    //   7130: aload #20
    //   7132: iconst_5
    //   7133: iaload
    //   7134: iastore
    //   7135: aload #20
    //   7137: iconst_5
    //   7138: aload #20
    //   7140: iconst_4
    //   7141: iaload
    //   7142: iastore
    //   7143: aload #20
    //   7145: iconst_4
    //   7146: aload #20
    //   7148: iconst_3
    //   7149: iaload
    //   7150: iastore
    //   7151: aload #20
    //   7153: iconst_3
    //   7154: aload #20
    //   7156: iconst_2
    //   7157: iaload
    //   7158: iastore
    //   7159: aload #20
    //   7161: iconst_2
    //   7162: aload #20
    //   7164: iconst_1
    //   7165: iaload
    //   7166: iastore
    //   7167: aload #20
    //   7169: iconst_1
    //   7170: aload #20
    //   7172: iconst_0
    //   7173: iaload
    //   7174: iastore
    //   7175: aload #20
    //   7177: iconst_0
    //   7178: iload #22
    //   7180: iastore
    //   7181: iinc #21, 1
    //   7184: iload_2
    //   7185: ifne -> 6693
    //   7188: iconst_0
    //   7189: istore #21
    //   7191: iload #21
    //   7193: bipush #8
    //   7195: if_icmpge -> 7218
    //   7198: aload #8
    //   7200: iload #21
    //   7202: dup2
    //   7203: iaload
    //   7204: aload #20
    //   7206: iload #21
    //   7208: iaload
    //   7209: iadd
    //   7210: iastore
    //   7211: iinc #21, 1
    //   7214: iload_2
    //   7215: ifne -> 7191
    //   7218: iinc #13, 64
    //   7221: iinc #17, -64
    //   7224: iload_2
    //   7225: ifne -> 6614
    //   7228: iload #17
    //   7230: ifle -> 7266
    //   7233: iconst_0
    //   7234: istore #19
    //   7236: iload #19
    //   7238: iload #17
    //   7240: if_icmpge -> 7266
    //   7243: aload #9
    //   7245: iload #12
    //   7247: iload #19
    //   7249: iadd
    //   7250: aload #5
    //   7252: iload #13
    //   7254: iload #19
    //   7256: iadd
    //   7257: baload
    //   7258: bastore
    //   7259: iinc #19, 1
    //   7262: iload_2
    //   7263: ifne -> 7236
    //   7266: bipush #8
    //   7268: newarray byte
    //   7270: astore #19
    //   7272: aload #19
    //   7274: iconst_0
    //   7275: iload #14
    //   7277: bipush #24
    //   7279: iushr
    //   7280: i2b
    //   7281: bastore
    //   7282: aload #19
    //   7284: iconst_1
    //   7285: iload #14
    //   7287: bipush #16
    //   7289: iushr
    //   7290: i2b
    //   7291: bastore
    //   7292: aload #19
    //   7294: iconst_2
    //   7295: iload #14
    //   7297: bipush #8
    //   7299: iushr
    //   7300: i2b
    //   7301: bastore
    //   7302: aload #19
    //   7304: iconst_3
    //   7305: iload #14
    //   7307: i2b
    //   7308: bastore
    //   7309: aload #19
    //   7311: iconst_4
    //   7312: iload #15
    //   7314: bipush #24
    //   7316: iushr
    //   7317: i2b
    //   7318: bastore
    //   7319: aload #19
    //   7321: iconst_5
    //   7322: iload #15
    //   7324: bipush #16
    //   7326: iushr
    //   7327: i2b
    //   7328: bastore
    //   7329: aload #19
    //   7331: bipush #6
    //   7333: iload #15
    //   7335: bipush #8
    //   7337: iushr
    //   7338: i2b
    //   7339: bastore
    //   7340: aload #19
    //   7342: bipush #7
    //   7344: iload #15
    //   7346: i2b
    //   7347: bastore
    //   7348: bipush #8
    //   7350: istore #11
    //   7352: aload #7
    //   7354: iconst_0
    //   7355: iaload
    //   7356: bipush #63
    //   7358: iand
    //   7359: istore #12
    //   7361: bipush #64
    //   7363: iload #12
    //   7365: isub
    //   7366: istore #18
    //   7368: aload #7
    //   7370: iconst_0
    //   7371: dup2
    //   7372: iaload
    //   7373: iload #11
    //   7375: iadd
    //   7376: iastore
    //   7377: aload #7
    //   7379: iconst_0
    //   7380: dup2
    //   7381: iaload
    //   7382: iconst_m1
    //   7383: iand
    //   7384: iastore
    //   7385: aload #7
    //   7387: iconst_0
    //   7388: iaload
    //   7389: iload #11
    //   7391: if_icmpge -> 7409
    //   7394: aload #7
    //   7396: iconst_1
    //   7397: dup2
    //   7398: iaload
    //   7399: iconst_1
    //   7400: iadd
    //   7401: iastore
    //   7402: goto -> 7409
    //   7405: invokestatic a : (Ljava/lang/Throwable;)Ljava/lang/Throwable;
    //   7408: athrow
    //   7409: iload #12
    //   7411: ifle -> 8025
    //   7414: iload #11
    //   7416: iload #18
    //   7418: if_icmplt -> 8025
    //   7421: goto -> 7428
    //   7424: invokestatic a : (Ljava/lang/Throwable;)Ljava/lang/Throwable;
    //   7427: athrow
    //   7428: iconst_0
    //   7429: istore #20
    //   7431: iload #20
    //   7433: iload #18
    //   7435: if_icmpge -> 7458
    //   7438: aload #9
    //   7440: iload #12
    //   7442: iload #20
    //   7444: iadd
    //   7445: aload #19
    //   7447: iload #20
    //   7449: baload
    //   7450: bastore
    //   7451: iinc #20, 1
    //   7454: iload_2
    //   7455: ifne -> 7431
    //   7458: bipush #64
    //   7460: newarray int
    //   7462: astore #20
    //   7464: bipush #8
    //   7466: newarray int
    //   7468: astore #21
    //   7470: iconst_0
    //   7471: istore #22
    //   7473: iload #22
    //   7475: bipush #8
    //   7477: if_icmpge -> 7497
    //   7480: aload #21
    //   7482: iload #22
    //   7484: aload #8
    //   7486: iload #22
    //   7488: iaload
    //   7489: iastore
    //   7490: iinc #22, 1
    //   7493: iload_2
    //   7494: ifne -> 7473
    //   7497: iconst_0
    //   7498: istore #22
    //   7500: iload #22
    //   7502: bipush #64
    //   7504: if_icmpge -> 7995
    //   7507: iload #22
    //   7509: bipush #16
    //   7511: if_icmpge -> 7592
    //   7514: aload #20
    //   7516: iload #22
    //   7518: aload #9
    //   7520: iconst_4
    //   7521: iload #22
    //   7523: imul
    //   7524: baload
    //   7525: sipush #255
    //   7528: iand
    //   7529: bipush #24
    //   7531: ishl
    //   7532: aload #9
    //   7534: iconst_4
    //   7535: iload #22
    //   7537: imul
    //   7538: iconst_1
    //   7539: iadd
    //   7540: baload
    //   7541: sipush #255
    //   7544: iand
    //   7545: bipush #16
    //   7547: ishl
    //   7548: ior
    //   7549: aload #9
    //   7551: iconst_4
    //   7552: iload #22
    //   7554: imul
    //   7555: iconst_2
    //   7556: iadd
    //   7557: baload
    //   7558: sipush #255
    //   7561: iand
    //   7562: bipush #8
    //   7564: ishl
    //   7565: ior
    //   7566: aload #9
    //   7568: iconst_4
    //   7569: iload #22
    //   7571: imul
    //   7572: iconst_3
    //   7573: iadd
    //   7574: baload
    //   7575: sipush #255
    //   7578: iand
    //   7579: ior
    //   7580: iastore
    //   7581: iload_2
    //   7582: ifne -> 7735
    //   7585: goto -> 7592
    //   7588: invokestatic a : (Ljava/lang/Throwable;)Ljava/lang/Throwable;
    //   7591: athrow
    //   7592: aload #20
    //   7594: iload #22
    //   7596: aload #20
    //   7598: iload #22
    //   7600: iconst_2
    //   7601: isub
    //   7602: iaload
    //   7603: bipush #17
    //   7605: iushr
    //   7606: aload #20
    //   7608: iload #22
    //   7610: iconst_2
    //   7611: isub
    //   7612: iaload
    //   7613: bipush #15
    //   7615: ishl
    //   7616: ior
    //   7617: aload #20
    //   7619: iload #22
    //   7621: iconst_2
    //   7622: isub
    //   7623: iaload
    //   7624: bipush #19
    //   7626: iushr
    //   7627: aload #20
    //   7629: iload #22
    //   7631: iconst_2
    //   7632: isub
    //   7633: iaload
    //   7634: bipush #13
    //   7636: ishl
    //   7637: ior
    //   7638: ixor
    //   7639: aload #20
    //   7641: iload #22
    //   7643: iconst_2
    //   7644: isub
    //   7645: iaload
    //   7646: bipush #10
    //   7648: iushr
    //   7649: ixor
    //   7650: aload #20
    //   7652: iload #22
    //   7654: bipush #7
    //   7656: isub
    //   7657: iaload
    //   7658: iadd
    //   7659: aload #20
    //   7661: iload #22
    //   7663: bipush #15
    //   7665: isub
    //   7666: iaload
    //   7667: bipush #7
    //   7669: iushr
    //   7670: aload #20
    //   7672: iload #22
    //   7674: bipush #15
    //   7676: isub
    //   7677: iaload
    //   7678: bipush #25
    //   7680: ishl
    //   7681: ior
    //   7682: aload #20
    //   7684: iload #22
    //   7686: bipush #15
    //   7688: isub
    //   7689: iaload
    //   7690: bipush #18
    //   7692: iushr
    //   7693: aload #20
    //   7695: iload #22
    //   7697: bipush #15
    //   7699: isub
    //   7700: iaload
    //   7701: bipush #14
    //   7703: ishl
    //   7704: ior
    //   7705: ixor
    //   7706: aload #20
    //   7708: iload #22
    //   7710: bipush #15
    //   7712: isub
    //   7713: iaload
    //   7714: iconst_3
    //   7715: iushr
    //   7716: ixor
    //   7717: iadd
    //   7718: aload #20
    //   7720: iload #22
    //   7722: bipush #16
    //   7724: isub
    //   7725: iaload
    //   7726: iadd
    //   7727: iastore
    //   7728: goto -> 7735
    //   7731: invokestatic a : (Ljava/lang/Throwable;)Ljava/lang/Throwable;
    //   7734: athrow
    //   7735: aload #21
    //   7737: bipush #7
    //   7739: iaload
    //   7740: aload #21
    //   7742: iconst_4
    //   7743: iaload
    //   7744: bipush #6
    //   7746: iushr
    //   7747: aload #21
    //   7749: iconst_4
    //   7750: iaload
    //   7751: bipush #26
    //   7753: ishl
    //   7754: ior
    //   7755: aload #21
    //   7757: iconst_4
    //   7758: iaload
    //   7759: bipush #11
    //   7761: iushr
    //   7762: aload #21
    //   7764: iconst_4
    //   7765: iaload
    //   7766: bipush #21
    //   7768: ishl
    //   7769: ior
    //   7770: ixor
    //   7771: aload #21
    //   7773: iconst_4
    //   7774: iaload
    //   7775: bipush #25
    //   7777: iushr
    //   7778: aload #21
    //   7780: iconst_4
    //   7781: iaload
    //   7782: bipush #7
    //   7784: ishl
    //   7785: ior
    //   7786: ixor
    //   7787: iadd
    //   7788: aload #21
    //   7790: bipush #6
    //   7792: iaload
    //   7793: aload #21
    //   7795: iconst_4
    //   7796: iaload
    //   7797: aload #21
    //   7799: iconst_5
    //   7800: iaload
    //   7801: aload #21
    //   7803: bipush #6
    //   7805: iaload
    //   7806: ixor
    //   7807: iand
    //   7808: ixor
    //   7809: iadd
    //   7810: aload #6
    //   7812: iload #22
    //   7814: iaload
    //   7815: iadd
    //   7816: aload #20
    //   7818: iload #22
    //   7820: iaload
    //   7821: iadd
    //   7822: istore #23
    //   7824: aload #21
    //   7826: iconst_0
    //   7827: iaload
    //   7828: iconst_2
    //   7829: iushr
    //   7830: aload #21
    //   7832: iconst_0
    //   7833: iaload
    //   7834: bipush #30
    //   7836: ishl
    //   7837: ior
    //   7838: aload #21
    //   7840: iconst_0
    //   7841: iaload
    //   7842: bipush #13
    //   7844: iushr
    //   7845: aload #21
    //   7847: iconst_0
    //   7848: iaload
    //   7849: bipush #19
    //   7851: ishl
    //   7852: ior
    //   7853: ixor
    //   7854: aload #21
    //   7856: iconst_0
    //   7857: iaload
    //   7858: bipush #22
    //   7860: iushr
    //   7861: aload #21
    //   7863: iconst_0
    //   7864: iaload
    //   7865: bipush #10
    //   7867: ishl
    //   7868: ior
    //   7869: ixor
    //   7870: aload #21
    //   7872: iconst_0
    //   7873: iaload
    //   7874: aload #21
    //   7876: iconst_1
    //   7877: iaload
    //   7878: iand
    //   7879: aload #21
    //   7881: iconst_2
    //   7882: iaload
    //   7883: aload #21
    //   7885: iconst_0
    //   7886: iaload
    //   7887: aload #21
    //   7889: iconst_1
    //   7890: iaload
    //   7891: ior
    //   7892: iand
    //   7893: ior
    //   7894: iadd
    //   7895: istore #24
    //   7897: aload #21
    //   7899: iconst_3
    //   7900: dup2
    //   7901: iaload
    //   7902: iload #23
    //   7904: iadd
    //   7905: iastore
    //   7906: aload #21
    //   7908: bipush #7
    //   7910: iload #23
    //   7912: iload #24
    //   7914: iadd
    //   7915: iastore
    //   7916: aload #21
    //   7918: bipush #7
    //   7920: iaload
    //   7921: istore #23
    //   7923: aload #21
    //   7925: bipush #7
    //   7927: aload #21
    //   7929: bipush #6
    //   7931: iaload
    //   7932: iastore
    //   7933: aload #21
    //   7935: bipush #6
    //   7937: aload #21
    //   7939: iconst_5
    //   7940: iaload
    //   7941: iastore
    //   7942: aload #21
    //   7944: iconst_5
    //   7945: aload #21
    //   7947: iconst_4
    //   7948: iaload
    //   7949: iastore
    //   7950: aload #21
    //   7952: iconst_4
    //   7953: aload #21
    //   7955: iconst_3
    //   7956: iaload
    //   7957: iastore
    //   7958: aload #21
    //   7960: iconst_3
    //   7961: aload #21
    //   7963: iconst_2
    //   7964: iaload
    //   7965: iastore
    //   7966: aload #21
    //   7968: iconst_2
    //   7969: aload #21
    //   7971: iconst_1
    //   7972: iaload
    //   7973: iastore
    //   7974: aload #21
    //   7976: iconst_1
    //   7977: aload #21
    //   7979: iconst_0
    //   7980: iaload
    //   7981: iastore
    //   7982: aload #21
    //   7984: iconst_0
    //   7985: iload #23
    //   7987: iastore
    //   7988: iinc #22, 1
    //   7991: iload_2
    //   7992: ifne -> 7500
    //   7995: iconst_0
    //   7996: istore #22
    //   7998: iload #22
    //   8000: bipush #8
    //   8002: if_icmpge -> 8025
    //   8005: aload #8
    //   8007: iload #22
    //   8009: dup2
    //   8010: iaload
    //   8011: aload #21
    //   8013: iload #22
    //   8015: iaload
    //   8016: iadd
    //   8017: iastore
    //   8018: iinc #22, 1
    //   8021: iload_2
    //   8022: ifne -> 7998
    //   8025: bipush #32
    //   8027: newarray byte
    //   8029: astore #4
    //   8031: aload #4
    //   8033: iconst_0
    //   8034: aload #8
    //   8036: iconst_0
    //   8037: iaload
    //   8038: bipush #24
    //   8040: iushr
    //   8041: i2b
    //   8042: bastore
    //   8043: aload #4
    //   8045: iconst_1
    //   8046: aload #8
    //   8048: iconst_0
    //   8049: iaload
    //   8050: bipush #16
    //   8052: iushr
    //   8053: i2b
    //   8054: bastore
    //   8055: aload #4
    //   8057: iconst_2
    //   8058: aload #8
    //   8060: iconst_0
    //   8061: iaload
    //   8062: bipush #8
    //   8064: iushr
    //   8065: i2b
    //   8066: bastore
    //   8067: aload #4
    //   8069: iconst_3
    //   8070: aload #8
    //   8072: iconst_0
    //   8073: iaload
    //   8074: i2b
    //   8075: bastore
    //   8076: aload #4
    //   8078: iconst_4
    //   8079: aload #8
    //   8081: iconst_1
    //   8082: iaload
    //   8083: bipush #24
    //   8085: iushr
    //   8086: i2b
    //   8087: bastore
    //   8088: aload #4
    //   8090: iconst_5
    //   8091: aload #8
    //   8093: iconst_1
    //   8094: iaload
    //   8095: bipush #16
    //   8097: iushr
    //   8098: i2b
    //   8099: bastore
    //   8100: aload #4
    //   8102: bipush #6
    //   8104: aload #8
    //   8106: iconst_1
    //   8107: iaload
    //   8108: bipush #8
    //   8110: iushr
    //   8111: i2b
    //   8112: bastore
    //   8113: aload #4
    //   8115: bipush #7
    //   8117: aload #8
    //   8119: iconst_1
    //   8120: iaload
    //   8121: i2b
    //   8122: bastore
    //   8123: aload #4
    //   8125: bipush #8
    //   8127: aload #8
    //   8129: iconst_2
    //   8130: iaload
    //   8131: bipush #24
    //   8133: iushr
    //   8134: i2b
    //   8135: bastore
    //   8136: aload #4
    //   8138: bipush #9
    //   8140: aload #8
    //   8142: iconst_2
    //   8143: iaload
    //   8144: bipush #16
    //   8146: iushr
    //   8147: i2b
    //   8148: bastore
    //   8149: aload #4
    //   8151: bipush #10
    //   8153: aload #8
    //   8155: iconst_2
    //   8156: iaload
    //   8157: bipush #8
    //   8159: iushr
    //   8160: i2b
    //   8161: bastore
    //   8162: aload #4
    //   8164: bipush #11
    //   8166: aload #8
    //   8168: iconst_2
    //   8169: iaload
    //   8170: i2b
    //   8171: bastore
    //   8172: aload #4
    //   8174: bipush #12
    //   8176: aload #8
    //   8178: iconst_3
    //   8179: iaload
    //   8180: bipush #24
    //   8182: iushr
    //   8183: i2b
    //   8184: bastore
    //   8185: aload #4
    //   8187: bipush #13
    //   8189: aload #8
    //   8191: iconst_3
    //   8192: iaload
    //   8193: bipush #16
    //   8195: iushr
    //   8196: i2b
    //   8197: bastore
    //   8198: aload #4
    //   8200: bipush #14
    //   8202: aload #8
    //   8204: iconst_3
    //   8205: iaload
    //   8206: bipush #8
    //   8208: iushr
    //   8209: i2b
    //   8210: bastore
    //   8211: aload #4
    //   8213: bipush #15
    //   8215: aload #8
    //   8217: iconst_3
    //   8218: iaload
    //   8219: i2b
    //   8220: bastore
    //   8221: aload #4
    //   8223: bipush #16
    //   8225: aload #8
    //   8227: iconst_4
    //   8228: iaload
    //   8229: bipush #24
    //   8231: iushr
    //   8232: i2b
    //   8233: bastore
    //   8234: aload #4
    //   8236: bipush #17
    //   8238: aload #8
    //   8240: iconst_4
    //   8241: iaload
    //   8242: bipush #16
    //   8244: iushr
    //   8245: i2b
    //   8246: bastore
    //   8247: aload #4
    //   8249: bipush #18
    //   8251: aload #8
    //   8253: iconst_4
    //   8254: iaload
    //   8255: bipush #8
    //   8257: iushr
    //   8258: i2b
    //   8259: bastore
    //   8260: aload #4
    //   8262: bipush #19
    //   8264: aload #8
    //   8266: iconst_4
    //   8267: iaload
    //   8268: i2b
    //   8269: bastore
    //   8270: aload #4
    //   8272: bipush #20
    //   8274: aload #8
    //   8276: iconst_5
    //   8277: iaload
    //   8278: bipush #24
    //   8280: iushr
    //   8281: i2b
    //   8282: bastore
    //   8283: aload #4
    //   8285: bipush #21
    //   8287: aload #8
    //   8289: iconst_5
    //   8290: iaload
    //   8291: bipush #16
    //   8293: iushr
    //   8294: i2b
    //   8295: bastore
    //   8296: aload #4
    //   8298: bipush #22
    //   8300: aload #8
    //   8302: iconst_5
    //   8303: iaload
    //   8304: bipush #8
    //   8306: iushr
    //   8307: i2b
    //   8308: bastore
    //   8309: aload #4
    //   8311: bipush #23
    //   8313: aload #8
    //   8315: iconst_5
    //   8316: iaload
    //   8317: i2b
    //   8318: bastore
    //   8319: aload #4
    //   8321: bipush #24
    //   8323: aload #8
    //   8325: bipush #6
    //   8327: iaload
    //   8328: bipush #24
    //   8330: iushr
    //   8331: i2b
    //   8332: bastore
    //   8333: aload #4
    //   8335: bipush #25
    //   8337: aload #8
    //   8339: bipush #6
    //   8341: iaload
    //   8342: bipush #16
    //   8344: iushr
    //   8345: i2b
    //   8346: bastore
    //   8347: aload #4
    //   8349: bipush #26
    //   8351: aload #8
    //   8353: bipush #6
    //   8355: iaload
    //   8356: bipush #8
    //   8358: iushr
    //   8359: i2b
    //   8360: bastore
    //   8361: aload #4
    //   8363: bipush #27
    //   8365: aload #8
    //   8367: bipush #6
    //   8369: iaload
    //   8370: i2b
    //   8371: bastore
    //   8372: aload #4
    //   8374: bipush #28
    //   8376: aload #8
    //   8378: bipush #7
    //   8380: iaload
    //   8381: bipush #24
    //   8383: iushr
    //   8384: i2b
    //   8385: bastore
    //   8386: aload #4
    //   8388: bipush #29
    //   8390: aload #8
    //   8392: bipush #7
    //   8394: iaload
    //   8395: bipush #16
    //   8397: iushr
    //   8398: i2b
    //   8399: bastore
    //   8400: aload #4
    //   8402: bipush #30
    //   8404: aload #8
    //   8406: bipush #7
    //   8408: iaload
    //   8409: bipush #8
    //   8411: iushr
    //   8412: i2b
    //   8413: bastore
    //   8414: aload #4
    //   8416: bipush #31
    //   8418: aload #8
    //   8420: bipush #7
    //   8422: iaload
    //   8423: i2b
    //   8424: bastore
    //   8425: new java/math/BigInteger
    //   8428: dup
    //   8429: aload #4
    //   8431: invokespecial <init> : ([B)V
    //   8434: invokevirtual abs : ()Ljava/math/BigInteger;
    //   8437: putstatic burp/Zb3d.Zw : Ljava/lang/Object;
    //   8440: getstatic burp/Ze2w.ZA : Ljava/lang/Object;
    //   8443: checkcast java/math/BigInteger
    //   8446: invokevirtual toByteArray : ()[B
    //   8449: astore_3
    //   8450: aload_3
    //   8451: arraylength
    //   8452: bipush #8
    //   8454: iadd
    //   8455: bipush #6
    //   8457: ishr
    //   8458: iconst_1
    //   8459: iadd
    //   8460: bipush #16
    //   8462: imul
    //   8463: newarray int
    //   8465: astore #5
    //   8467: iconst_0
    //   8468: istore #6
    //   8470: iload #6
    //   8472: aload_3
    //   8473: arraylength
    //   8474: if_icmpge -> 8517
    //   8477: aload_3
    //   8478: iload #6
    //   8480: baload
    //   8481: sipush #255
    //   8484: iand
    //   8485: istore #7
    //   8487: aload #5
    //   8489: iload #6
    //   8491: iconst_2
    //   8492: ishr
    //   8493: dup2
    //   8494: iaload
    //   8495: iload #7
    //   8497: bipush #24
    //   8499: iload #6
    //   8501: iconst_4
    //   8502: irem
    //   8503: bipush #8
    //   8505: imul
    //   8506: isub
    //   8507: ishl
    //   8508: ior
    //   8509: iastore
    //   8510: iinc #6, 1
    //   8513: iload_2
    //   8514: ifne -> 8470
    //   8517: aload #5
    //   8519: iload #6
    //   8521: iconst_2
    //   8522: ishr
    //   8523: dup2
    //   8524: iaload
    //   8525: sipush #128
    //   8528: bipush #24
    //   8530: iload #6
    //   8532: iconst_4
    //   8533: irem
    //   8534: bipush #8
    //   8536: imul
    //   8537: isub
    //   8538: ishl
    //   8539: ior
    //   8540: iastore
    //   8541: aload #5
    //   8543: aload #5
    //   8545: arraylength
    //   8546: iconst_1
    //   8547: isub
    //   8548: aload_3
    //   8549: arraylength
    //   8550: bipush #8
    //   8552: imul
    //   8553: iastore
    //   8554: bipush #80
    //   8556: newarray int
    //   8558: astore #7
    //   8560: ldc 1732584193
    //   8562: istore #8
    //   8564: ldc -271733879
    //   8566: istore #9
    //   8568: ldc -1732584194
    //   8570: istore #10
    //   8572: ldc 271733878
    //   8574: istore #11
    //   8576: ldc -1009589776
    //   8578: istore #12
    //   8580: iconst_0
    //   8581: istore #6
    //   8583: iload #6
    //   8585: aload #5
    //   8587: arraylength
    //   8588: if_icmpge -> 8910
    //   8591: iload #8
    //   8593: istore #13
    //   8595: iload #9
    //   8597: istore #14
    //   8599: iload #10
    //   8601: istore #15
    //   8603: iload #11
    //   8605: istore #16
    //   8607: iload #12
    //   8609: istore #17
    //   8611: iconst_0
    //   8612: istore #18
    //   8614: iload #18
    //   8616: bipush #80
    //   8618: if_icmpge -> 8868
    //   8621: iload #18
    //   8623: bipush #16
    //   8625: if_icmpge -> 8652
    //   8628: aload #7
    //   8630: iload #18
    //   8632: aload #5
    //   8634: iload #6
    //   8636: iload #18
    //   8638: iadd
    //   8639: iaload
    //   8640: iastore
    //   8641: iload_2
    //   8642: ifne -> 8707
    //   8645: goto -> 8652
    //   8648: invokestatic a : (Ljava/lang/Throwable;)Ljava/lang/Throwable;
    //   8651: athrow
    //   8652: aload #7
    //   8654: iload #18
    //   8656: iconst_3
    //   8657: isub
    //   8658: iaload
    //   8659: aload #7
    //   8661: iload #18
    //   8663: bipush #8
    //   8665: isub
    //   8666: iaload
    //   8667: ixor
    //   8668: aload #7
    //   8670: iload #18
    //   8672: bipush #14
    //   8674: isub
    //   8675: iaload
    //   8676: ixor
    //   8677: aload #7
    //   8679: iload #18
    //   8681: bipush #16
    //   8683: isub
    //   8684: iaload
    //   8685: ixor
    //   8686: istore #19
    //   8688: iload #19
    //   8690: iconst_1
    //   8691: ishl
    //   8692: iload #19
    //   8694: bipush #31
    //   8696: iushr
    //   8697: ior
    //   8698: istore #20
    //   8700: aload #7
    //   8702: iload #18
    //   8704: iload #20
    //   8706: iastore
    //   8707: iload #8
    //   8709: iconst_5
    //   8710: ishl
    //   8711: iload #8
    //   8713: bipush #27
    //   8715: iushr
    //   8716: ior
    //   8717: istore #19
    //   8719: iload #19
    //   8721: iload #12
    //   8723: iadd
    //   8724: aload #7
    //   8726: iload #18
    //   8728: iaload
    //   8729: iadd
    //   8730: iload #18
    //   8732: bipush #20
    //   8734: if_icmpge -> 8760
    //   8737: ldc 1518500249
    //   8739: iload #9
    //   8741: iload #10
    //   8743: iand
    //   8744: iload #9
    //   8746: iconst_m1
    //   8747: ixor
    //   8748: iload #11
    //   8750: iand
    //   8751: ior
    //   8752: iadd
    //   8753: goto -> 8830
    //   8756: invokestatic a : (Ljava/lang/Throwable;)Ljava/lang/Throwable;
    //   8759: athrow
    //   8760: iload #18
    //   8762: bipush #40
    //   8764: if_icmpge -> 8785
    //   8767: ldc 1859775393
    //   8769: iload #9
    //   8771: iload #10
    //   8773: ixor
    //   8774: iload #11
    //   8776: ixor
    //   8777: iadd
    //   8778: goto -> 8830
    //   8781: invokestatic a : (Ljava/lang/Throwable;)Ljava/lang/Throwable;
    //   8784: athrow
    //   8785: iload #18
    //   8787: bipush #60
    //   8789: if_icmpge -> 8819
    //   8792: ldc -1894007588
    //   8794: iload #9
    //   8796: iload #10
    //   8798: iand
    //   8799: iload #9
    //   8801: iload #11
    //   8803: iand
    //   8804: ior
    //   8805: iload #10
    //   8807: iload #11
    //   8809: iand
    //   8810: ior
    //   8811: iadd
    //   8812: goto -> 8830
    //   8815: invokestatic a : (Ljava/lang/Throwable;)Ljava/lang/Throwable;
    //   8818: athrow
    //   8819: ldc -899497514
    //   8821: iload #9
    //   8823: iload #10
    //   8825: ixor
    //   8826: iload #11
    //   8828: ixor
    //   8829: iadd
    //   8830: iadd
    //   8831: istore #20
    //   8833: iload #11
    //   8835: istore #12
    //   8837: iload #10
    //   8839: istore #11
    //   8841: iload #9
    //   8843: bipush #30
    //   8845: ishl
    //   8846: iload #9
    //   8848: iconst_2
    //   8849: iushr
    //   8850: ior
    //   8851: istore #10
    //   8853: iload #8
    //   8855: istore #9
    //   8857: iload #20
    //   8859: istore #8
    //   8861: iinc #18, 1
    //   8864: iload_2
    //   8865: ifne -> 8614
    //   8868: iload #8
    //   8870: iload #13
    //   8872: iadd
    //   8873: istore #8
    //   8875: iload #9
    //   8877: iload #14
    //   8879: iadd
    //   8880: istore #9
    //   8882: iload #10
    //   8884: iload #15
    //   8886: iadd
    //   8887: istore #10
    //   8889: iload #11
    //   8891: iload #16
    //   8893: iadd
    //   8894: istore #11
    //   8896: iload #12
    //   8898: iload #17
    //   8900: iadd
    //   8901: istore #12
    //   8903: iinc #6, 16
    //   8906: iload_2
    //   8907: ifne -> 8583
    //   8910: iconst_5
    //   8911: newarray int
    //   8913: dup
    //   8914: iconst_0
    //   8915: iload #8
    //   8917: iastore
    //   8918: dup
    //   8919: iconst_1
    //   8920: iload #9
    //   8922: iastore
    //   8923: dup
    //   8924: iconst_2
    //   8925: iload #10
    //   8927: iastore
    //   8928: dup
    //   8929: iconst_3
    //   8930: iload #11
    //   8932: iastore
    //   8933: dup
    //   8934: iconst_4
    //   8935: iload #12
    //   8937: iastore
    //   8938: astore #13
    //   8940: bipush #20
    //   8942: newarray byte
    //   8944: astore #14
    //   8946: iconst_0
    //   8947: istore #15
    //   8949: iload #15
    //   8951: bipush #20
    //   8953: if_icmpge -> 8994
    //   8956: aload #13
    //   8958: iload #15
    //   8960: iconst_4
    //   8961: idiv
    //   8962: iaload
    //   8963: istore #16
    //   8965: iconst_3
    //   8966: iload #15
    //   8968: iconst_4
    //   8969: irem
    //   8970: isub
    //   8971: bipush #8
    //   8973: imul
    //   8974: istore #17
    //   8976: aload #14
    //   8978: iload #15
    //   8980: iload #16
    //   8982: iload #17
    //   8984: iushr
    //   8985: i2b
    //   8986: bastore
    //   8987: iinc #15, 1
    //   8990: iload_2
    //   8991: ifne -> 8949
    //   8994: aload #14
    //   8996: astore #4
    //   8998: sipush #17498
    //   9001: new java/math/BigInteger
    //   9004: dup
    //   9005: aload #4
    //   9007: invokespecial <init> : ([B)V
    //   9010: invokevirtual abs : ()Ljava/math/BigInteger;
    //   9013: putstatic burp/Zea.ZO : Ljava/lang/Object;
    //   9016: sipush #23491
    //   9019: invokestatic a : (II)Ljava/lang/String;
    //   9022: iconst_1
    //   9023: ldc burp/Zro5
    //   9025: invokevirtual getClassLoader : ()Ljava/lang/ClassLoader;
    //   9028: invokestatic forName : (Ljava/lang/String;ZLjava/lang/ClassLoader;)Ljava/lang/Class;
    //   9031: invokevirtual getDeclaredFields : ()[Ljava/lang/reflect/Field;
    //   9034: astore_3
    //   9035: aload_3
    //   9036: arraylength
    //   9037: istore #4
    //   9039: iconst_0
    //   9040: istore #5
    //   9042: iload #5
    //   9044: iload #4
    //   9046: if_icmpge -> 9183
    //   9049: aload_3
    //   9050: iload #5
    //   9052: aaload
    //   9053: astore #6
    //   9055: aload #6
    //   9057: invokevirtual getModifiers : ()I
    //   9060: invokestatic isStatic : (I)Z
    //   9063: ifne -> 9073
    //   9066: goto -> 9176
    //   9069: invokestatic a : (Ljava/lang/Throwable;)Ljava/lang/Throwable;
    //   9072: athrow
    //   9073: aload #6
    //   9075: invokevirtual getType : ()Ljava/lang/Class;
    //   9078: astore #7
    //   9080: aload #7
    //   9082: ifnull -> 9163
    //   9085: aload #7
    //   9087: invokevirtual isPrimitive : ()Z
    //   9090: ifne -> 9163
    //   9093: goto -> 9100
    //   9096: invokestatic a : (Ljava/lang/Throwable;)Ljava/lang/Throwable;
    //   9099: athrow
    //   9100: aload #7
    //   9102: invokevirtual getPackage : ()Ljava/lang/Package;
    //   9105: ifnull -> 9163
    //   9108: goto -> 9115
    //   9111: invokestatic a : (Ljava/lang/Throwable;)Ljava/lang/Throwable;
    //   9114: athrow
    //   9115: aload #7
    //   9117: invokevirtual getPackage : ()Ljava/lang/Package;
    //   9120: invokevirtual getName : ()Ljava/lang/String;
    //   9123: ifnull -> 9163
    //   9126: goto -> 9133
    //   9129: invokestatic a : (Ljava/lang/Throwable;)Ljava/lang/Throwable;
    //   9132: athrow
    //   9133: aload #7
    //   9135: invokevirtual getPackage : ()Ljava/lang/Package;
    //   9138: invokevirtual getName : ()Ljava/lang/String;
    //   9141: sipush #17491
    //   9144: sipush #9427
    //   9147: invokestatic a : (II)Ljava/lang/String;
    //   9150: invokevirtual startsWith : (Ljava/lang/String;)Z
    //   9153: ifne -> 9163
    //   9156: goto -> 9163
    //   9159: invokestatic a : (Ljava/lang/Throwable;)Ljava/lang/Throwable;
    //   9162: athrow
    //   9163: aload #6
    //   9165: iconst_1
    //   9166: invokevirtual setAccessible : (Z)V
    //   9169: aload #6
    //   9171: aconst_null
    //   9172: invokevirtual get : (Ljava/lang/Object;)Ljava/lang/Object;
    //   9175: pop
    //   9176: iinc #5, 1
    //   9179: iload_2
    //   9180: ifne -> 9042
    //   9183: sipush #17496
    //   9186: sipush #-28951
    //   9189: invokestatic a : (II)Ljava/lang/String;
    //   9192: invokestatic forName : (Ljava/lang/String;)Ljava/lang/Class;
    //   9195: invokevirtual getDeclaredMethods : ()[Ljava/lang/reflect/Method;
    //   9198: astore_3
    //   9199: aload_3
    //   9200: arraylength
    //   9201: istore #4
    //   9203: iconst_0
    //   9204: istore #5
    //   9206: iload #5
    //   9208: iload #4
    //   9210: if_icmpge -> 9342
    //   9213: aload_3
    //   9214: iload #5
    //   9216: aaload
    //   9217: astore #6
    //   9219: aload #6
    //   9221: invokevirtual getParameterTypes : ()[Ljava/lang/Class;
    //   9224: pop
    //   9225: aload #6
    //   9227: invokevirtual getModifiers : ()I
    //   9230: invokestatic isStatic : (I)Z
    //   9233: ifeq -> 9328
    //   9236: aload #6
    //   9238: invokevirtual getParameterTypes : ()[Ljava/lang/Class;
    //   9241: arraylength
    //   9242: iconst_2
    //   9243: if_icmpne -> 9328
    //   9246: goto -> 9253
    //   9249: invokestatic a : (Ljava/lang/Throwable;)Ljava/lang/Throwable;
    //   9252: athrow
    //   9253: aload #6
    //   9255: invokevirtual getReturnType : ()Ljava/lang/Class;
    //   9258: getstatic java/lang/Void.TYPE : Ljava/lang/Class;
    //   9261: invokevirtual equals : (Ljava/lang/Object;)Z
    //   9264: ifeq -> 9328
    //   9267: goto -> 9274
    //   9270: invokestatic a : (Ljava/lang/Throwable;)Ljava/lang/Throwable;
    //   9273: athrow
    //   9274: aload #6
    //   9276: iconst_1
    //   9277: invokevirtual setAccessible : (Z)V
    //   9280: aload #6
    //   9282: aconst_null
    //   9283: iconst_2
    //   9284: anewarray java/lang/Object
    //   9287: dup
    //   9288: iconst_0
    //   9289: aload_0
    //   9290: aastore
    //   9291: dup
    //   9292: iconst_1
    //   9293: aload_1
    //   9294: ifnonnull -> 9312
    //   9297: goto -> 9304
    //   9300: invokestatic a : (Ljava/lang/Throwable;)Ljava/lang/Throwable;
    //   9303: athrow
    //   9304: aload_1
    //   9305: goto -> 9319
    //   9308: invokestatic a : (Ljava/lang/Throwable;)Ljava/lang/Throwable;
    //   9311: athrow
    //   9312: aload_1
    //   9313: checkcast [B
    //   9316: invokevirtual clone : ()Ljava/lang/Object;
    //   9319: aastore
    //   9320: invokevirtual invoke : (Ljava/lang/Object;[Ljava/lang/Object;)Ljava/lang/Object;
    //   9323: pop
    //   9324: iload_2
    //   9325: ifne -> 9342
    //   9328: iinc #5, 1
    //   9331: iload_2
    //   9332: ifne -> 9206
    //   9335: goto -> 9342
    //   9338: invokestatic a : (Ljava/lang/Throwable;)Ljava/lang/Throwable;
    //   9341: athrow
    //   9342: getstatic burp/Ze7e.Z_ : Ljava/lang/Object;
    //   9345: checkcast java/math/BigInteger
    //   9348: invokevirtual toByteArray : ()[B
    //   9351: astore_3
    //   9352: new java/lang/StringBuilder
    //   9355: dup
    //   9356: invokespecial <init> : ()V
    //   9359: astore #5
    //   9361: aload #5
    //   9363: sipush #17495
    //   9366: sipush #-29483
    //   9369: invokestatic a : (II)Ljava/lang/String;
    //   9372: invokevirtual append : (Ljava/lang/String;)Ljava/lang/StringBuilder;
    //   9375: pop
    //   9376: aload_3
    //   9377: astore #6
    //   9379: aload #6
    //   9381: arraylength
    //   9382: istore #7
    //   9384: iconst_0
    //   9385: istore #8
    //   9387: iload #8
    //   9389: iload #7
    //   9391: if_icmpge -> 9417
    //   9394: aload #6
    //   9396: iload #8
    //   9398: baload
    //   9399: istore #9
    //   9401: aload #5
    //   9403: iload #9
    //   9405: i2c
    //   9406: invokevirtual append : (C)Ljava/lang/StringBuilder;
    //   9409: pop
    //   9410: iinc #8, 1
    //   9413: iload_2
    //   9414: ifne -> 9387
    //   9417: aload #5
    //   9419: sipush #17493
    //   9422: sipush #18117
    //   9425: invokestatic a : (II)Ljava/lang/String;
    //   9428: ldc ''
    //   9430: invokestatic getProperty : (Ljava/lang/String;Ljava/lang/String;)Ljava/lang/String;
    //   9433: invokevirtual toLowerCase : ()Ljava/lang/String;
    //   9436: invokevirtual append : (Ljava/lang/String;)Ljava/lang/StringBuilder;
    //   9439: pop
    //   9440: aload #5
    //   9442: sipush #17494
    //   9445: sipush #-21960
    //   9448: invokestatic a : (II)Ljava/lang/String;
    //   9451: ldc ''
    //   9453: invokestatic getProperty : (Ljava/lang/String;Ljava/lang/String;)Ljava/lang/String;
    //   9456: invokevirtual toLowerCase : ()Ljava/lang/String;
    //   9459: invokevirtual append : (Ljava/lang/String;)Ljava/lang/StringBuilder;
    //   9462: pop
    //   9463: aload #5
    //   9465: invokevirtual toString : ()Ljava/lang/String;
    //   9468: invokevirtual getBytes : ()[B
    //   9471: astore #4
    //   9473: aload #4
    //   9475: astore_3
    //   9476: aload_3
    //   9477: arraylength
    //   9478: bipush #8
    //   9480: iadd
    //   9481: bipush #6
    //   9483: ishr
    //   9484: iconst_1
    //   9485: iadd
    //   9486: bipush #16
    //   9488: imul
    //   9489: newarray int
    //   9491: astore #5
    //   9493: iconst_0
    //   9494: istore #6
    //   9496: iload #6
    //   9498: aload_3
    //   9499: arraylength
    //   9500: if_icmpge -> 9543
    //   9503: aload_3
    //   9504: iload #6
    //   9506: baload
    //   9507: sipush #255
    //   9510: iand
    //   9511: istore #7
    //   9513: aload #5
    //   9515: iload #6
    //   9517: iconst_2
    //   9518: ishr
    //   9519: dup2
    //   9520: iaload
    //   9521: iload #7
    //   9523: bipush #24
    //   9525: iload #6
    //   9527: iconst_4
    //   9528: irem
    //   9529: bipush #8
    //   9531: imul
    //   9532: isub
    //   9533: ishl
    //   9534: ior
    //   9535: iastore
    //   9536: iinc #6, 1
    //   9539: iload_2
    //   9540: ifne -> 9496
    //   9543: aload #5
    //   9545: iload #6
    //   9547: iconst_2
    //   9548: ishr
    //   9549: dup2
    //   9550: iaload
    //   9551: sipush #128
    //   9554: bipush #24
    //   9556: iload #6
    //   9558: iconst_4
    //   9559: irem
    //   9560: bipush #8
    //   9562: imul
    //   9563: isub
    //   9564: ishl
    //   9565: ior
    //   9566: iastore
    //   9567: aload #5
    //   9569: aload #5
    //   9571: arraylength
    //   9572: iconst_1
    //   9573: isub
    //   9574: aload_3
    //   9575: arraylength
    //   9576: bipush #8
    //   9578: imul
    //   9579: iastore
    //   9580: bipush #80
    //   9582: newarray int
    //   9584: astore #7
    //   9586: ldc 1732584193
    //   9588: istore #8
    //   9590: ldc -271733879
    //   9592: istore #9
    //   9594: ldc -1732584194
    //   9596: istore #10
    //   9598: ldc 271733878
    //   9600: istore #11
    //   9602: ldc -1009589776
    //   9604: istore #12
    //   9606: iconst_0
    //   9607: istore #6
    //   9609: iload #6
    //   9611: aload #5
    //   9613: arraylength
    //   9614: if_icmpge -> 9936
    //   9617: iload #8
    //   9619: istore #13
    //   9621: iload #9
    //   9623: istore #14
    //   9625: iload #10
    //   9627: istore #15
    //   9629: iload #11
    //   9631: istore #16
    //   9633: iload #12
    //   9635: istore #17
    //   9637: iconst_0
    //   9638: istore #18
    //   9640: iload #18
    //   9642: bipush #80
    //   9644: if_icmpge -> 9894
    //   9647: iload #18
    //   9649: bipush #16
    //   9651: if_icmpge -> 9678
    //   9654: aload #7
    //   9656: iload #18
    //   9658: aload #5
    //   9660: iload #6
    //   9662: iload #18
    //   9664: iadd
    //   9665: iaload
    //   9666: iastore
    //   9667: iload_2
    //   9668: ifne -> 9733
    //   9671: goto -> 9678
    //   9674: invokestatic a : (Ljava/lang/Throwable;)Ljava/lang/Throwable;
    //   9677: athrow
    //   9678: aload #7
    //   9680: iload #18
    //   9682: iconst_3
    //   9683: isub
    //   9684: iaload
    //   9685: aload #7
    //   9687: iload #18
    //   9689: bipush #8
    //   9691: isub
    //   9692: iaload
    //   9693: ixor
    //   9694: aload #7
    //   9696: iload #18
    //   9698: bipush #14
    //   9700: isub
    //   9701: iaload
    //   9702: ixor
    //   9703: aload #7
    //   9705: iload #18
    //   9707: bipush #16
    //   9709: isub
    //   9710: iaload
    //   9711: ixor
    //   9712: istore #19
    //   9714: iload #19
    //   9716: iconst_1
    //   9717: ishl
    //   9718: iload #19
    //   9720: bipush #31
    //   9722: iushr
    //   9723: ior
    //   9724: istore #20
    //   9726: aload #7
    //   9728: iload #18
    //   9730: iload #20
    //   9732: iastore
    //   9733: iload #8
    //   9735: iconst_5
    //   9736: ishl
    //   9737: iload #8
    //   9739: bipush #27
    //   9741: iushr
    //   9742: ior
    //   9743: istore #19
    //   9745: iload #19
    //   9747: iload #12
    //   9749: iadd
    //   9750: aload #7
    //   9752: iload #18
    //   9754: iaload
    //   9755: iadd
    //   9756: iload #18
    //   9758: bipush #20
    //   9760: if_icmpge -> 9786
    //   9763: ldc 1518500249
    //   9765: iload #9
    //   9767: iload #10
    //   9769: iand
    //   9770: iload #9
    //   9772: iconst_m1
    //   9773: ixor
    //   9774: iload #11
    //   9776: iand
    //   9777: ior
    //   9778: iadd
    //   9779: goto -> 9856
    //   9782: invokestatic a : (Ljava/lang/Throwable;)Ljava/lang/Throwable;
    //   9785: athrow
    //   9786: iload #18
    //   9788: bipush #40
    //   9790: if_icmpge -> 9811
    //   9793: ldc 1859775393
    //   9795: iload #9
    //   9797: iload #10
    //   9799: ixor
    //   9800: iload #11
    //   9802: ixor
    //   9803: iadd
    //   9804: goto -> 9856
    //   9807: invokestatic a : (Ljava/lang/Throwable;)Ljava/lang/Throwable;
    //   9810: athrow
    //   9811: iload #18
    //   9813: bipush #60
    //   9815: if_icmpge -> 9845
    //   9818: ldc -1894007588
    //   9820: iload #9
    //   9822: iload #10
    //   9824: iand
    //   9825: iload #9
    //   9827: iload #11
    //   9829: iand
    //   9830: ior
    //   9831: iload #10
    //   9833: iload #11
    //   9835: iand
    //   9836: ior
    //   9837: iadd
    //   9838: goto -> 9856
    //   9841: invokestatic a : (Ljava/lang/Throwable;)Ljava/lang/Throwable;
    //   9844: athrow
    //   9845: ldc -899497514
    //   9847: iload #9
    //   9849: iload #10
    //   9851: ixor
    //   9852: iload #11
    //   9854: ixor
    //   9855: iadd
    //   9856: iadd
    //   9857: istore #20
    //   9859: iload #11
    //   9861: istore #12
    //   9863: iload #10
    //   9865: istore #11
    //   9867: iload #9
    //   9869: bipush #30
    //   9871: ishl
    //   9872: iload #9
    //   9874: iconst_2
    //   9875: iushr
    //   9876: ior
    //   9877: istore #10
    //   9879: iload #8
    //   9881: istore #9
    //   9883: iload #20
    //   9885: istore #8
    //   9887: iinc #18, 1
    //   9890: iload_2
    //   9891: ifne -> 9640
    //   9894: iload #8
    //   9896: iload #13
    //   9898: iadd
    //   9899: istore #8
    //   9901: iload #9
    //   9903: iload #14
    //   9905: iadd
    //   9906: istore #9
    //   9908: iload #10
    //   9910: iload #15
    //   9912: iadd
    //   9913: istore #10
    //   9915: iload #11
    //   9917: iload #16
    //   9919: iadd
    //   9920: istore #11
    //   9922: iload #12
    //   9924: iload #17
    //   9926: iadd
    //   9927: istore #12
    //   9929: iinc #6, 16
    //   9932: iload_2
    //   9933: ifne -> 9609
    //   9936: iconst_5
    //   9937: newarray int
    //   9939: dup
    //   9940: iconst_0
    //   9941: iload #8
    //   9943: iastore
    //   9944: dup
    //   9945: iconst_1
    //   9946: iload #9
    //   9948: iastore
    //   9949: dup
    //   9950: iconst_2
    //   9951: iload #10
    //   9953: iastore
    //   9954: dup
    //   9955: iconst_3
    //   9956: iload #11
    //   9958: iastore
    //   9959: dup
    //   9960: iconst_4
    //   9961: iload #12
    //   9963: iastore
    //   9964: astore #13
    //   9966: bipush #20
    //   9968: newarray byte
    //   9970: astore #14
    //   9972: iconst_0
    //   9973: istore #15
    //   9975: iload #15
    //   9977: bipush #20
    //   9979: if_icmpge -> 10020
    //   9982: aload #13
    //   9984: iload #15
    //   9986: iconst_4
    //   9987: idiv
    //   9988: iaload
    //   9989: istore #16
    //   9991: iconst_3
    //   9992: iload #15
    //   9994: iconst_4
    //   9995: irem
    //   9996: isub
    //   9997: bipush #8
    //   9999: imul
    //   10000: istore #17
    //   10002: aload #14
    //   10004: iload #15
    //   10006: iload #16
    //   10008: iload #17
    //   10010: iushr
    //   10011: i2b
    //   10012: bastore
    //   10013: iinc #15, 1
    //   10016: iload_2
    //   10017: ifne -> 9975
    //   10020: aload #14
    //   10022: astore #4
    //   10024: getstatic burp/Zrp2.ZJ : Ljava/lang/String;
    //   10027: getstatic burp/Zxdy.ZZ : Ljava/lang/Object;
    //   10030: checkcast java/math/BigInteger
    //   10033: invokevirtual intValue : ()I
    //   10036: bipush #32
    //   10038: irem
    //   10039: invokestatic abs : (I)I
    //   10042: invokevirtual charAt : (I)C
    //   10045: getstatic burp/Zg7e.Zg : Ljava/lang/String;
    //   10048: getstatic burp/Zv8d.ZN : Ljava/lang/Object;
    //   10051: checkcast java/math/BigInteger
    //   10054: invokevirtual intValue : ()I
    //   10057: bipush #32
    //   10059: irem
    //   10060: invokestatic abs : (I)I
    //   10063: invokevirtual charAt : (I)C
    //   10066: if_icmple -> 10173
    //   10069: getstatic burp/Zsu2.Zq : Ljava/lang/String;
    //   10072: getstatic burp/Zbun.ZH : Ljava/lang/Object;
    //   10075: checkcast java/math/BigInteger
    //   10078: invokevirtual intValue : ()I
    //   10081: bipush #32
    //   10083: irem
    //   10084: invokestatic abs : (I)I
    //   10087: invokevirtual charAt : (I)C
    //   10090: getstatic burp/Ze8j.ZU : Ljava/lang/String;
    //   10093: getstatic burp/Zssc.Zr : Ljava/lang/Object;
    //   10096: checkcast java/math/BigInteger
    //   10099: invokevirtual intValue : ()I
    //   10102: bipush #32
    //   10104: irem
    //   10105: invokestatic abs : (I)I
    //   10108: invokevirtual charAt : (I)C
    //   10111: if_icmple -> 10173
    //   10114: goto -> 10121
    //   10117: invokestatic a : (Ljava/lang/Throwable;)Ljava/lang/Throwable;
    //   10120: athrow
    //   10121: getstatic burp/Zz0b.ZD : Ljava/lang/String;
    //   10124: getstatic burp/Zxp1.ZP : Ljava/lang/Object;
    //   10127: checkcast java/math/BigInteger
    //   10130: invokevirtual intValue : ()I
    //   10133: bipush #32
    //   10135: irem
    //   10136: invokestatic abs : (I)I
    //   10139: invokevirtual charAt : (I)C
    //   10142: getstatic burp/Zs0h.ZX : Ljava/lang/String;
    //   10145: getstatic burp/Ztlo.ZP : Ljava/lang/Object;
    //   10148: checkcast java/math/BigInteger
    //   10151: invokevirtual intValue : ()I
    //   10154: bipush #32
    //   10156: irem
    //   10157: invokestatic abs : (I)I
    //   10160: invokevirtual charAt : (I)C
    //   10163: if_icmpgt -> 10181
    //   10166: goto -> 10173
    //   10169: invokestatic a : (Ljava/lang/Throwable;)Ljava/lang/Throwable;
    //   10172: athrow
    //   10173: iconst_1
    //   10174: goto -> 10182
    //   10177: invokestatic a : (Ljava/lang/Throwable;)Ljava/lang/Throwable;
    //   10180: athrow
    //   10181: iconst_0
    //   10182: ireturn
    //   10183: astore_3
    //   10184: new java/lang/Exception
    //   10187: dup
    //   10188: aload_3
    //   10189: invokevirtual getMessage : ()Ljava/lang/String;
    //   10192: invokespecial <init> : (Ljava/lang/String;)V
    //   10195: athrow
    // Exception table:
    //   from	to	target	type
    //   4	10182	10183	java/lang/Throwable
    //   3306	3331	3331	java/lang/Throwable
    //   4294	4320	4320	java/lang/Throwable
    //   5168	5202	5205	java/lang/Throwable
    //   5297	5375	5378	java/lang/Throwable
    //   5304	5518	5521	java/lang/Throwable
    //   5895	5910	5910	java/lang/Throwable
    //   5937	5971	5974	java/lang/Throwable
    //   5981	5993	5996	java/lang/Throwable
    //   6079	6157	6160	java/lang/Throwable
    //   6086	6300	6303	java/lang/Throwable
    //   6700	6778	6781	java/lang/Throwable
    //   6707	6921	6924	java/lang/Throwable
    //   7368	7402	7405	java/lang/Throwable
    //   7409	7421	7424	java/lang/Throwable
    //   7507	7585	7588	java/lang/Throwable
    //   7514	7728	7731	java/lang/Throwable
    //   8621	8645	8648	java/lang/Throwable
    //   8719	8756	8756	java/lang/Throwable
    //   8760	8781	8781	java/lang/Throwable
    //   8785	8815	8815	java/lang/Throwable
    //   9055	9069	9069	java/lang/Throwable
    //   9080	9093	9096	java/lang/Throwable
    //   9085	9108	9111	java/lang/Throwable
    //   9100	9126	9129	java/lang/Throwable
    //   9115	9156	9159	java/lang/Throwable
    //   9219	9246	9249	java/lang/Throwable
    //   9236	9267	9270	java/lang/Throwable
    //   9253	9297	9300	java/lang/Throwable
    //   9274	9308	9308	java/lang/Throwable
    //   9319	9335	9338	java/lang/Throwable
    //   9647	9671	9674	java/lang/Throwable
    //   9745	9782	9782	java/lang/Throwable
    //   9786	9807	9807	java/lang/Throwable
    //   9811	9841	9841	java/lang/Throwable
    //   10024	10114	10117	java/lang/Throwable
    //   10069	10166	10169	java/lang/Throwable
    //   10121	10177	10177	java/lang/Throwable
  }
  
  static void ZW(Object paramObject) {
    Zb3l.Zz = a(17488, -25334);
    Zb3l.Zl = new BigInteger(a(17503, 31225));
    boolean bool = Zt2e.ZK();
    try {
      try {
        if (Zkf6.ZO.charAt(Math.abs(((BigInteger)Zepy.Ze).intValue() % 32)) > Zkjj.ZT.charAt(Math.abs(((BigInteger)Ztl6.ZQ).intValue() % 32))) {
          try {
            Zm3s.Zx(Class.forName(a(17490, -770)));
            if (bool)
              Zzi_.ZJ(Class.forName(a(17492, -13804))); 
          } catch (Throwable throwable) {
            throw a(null);
          } 
          return;
        } 
      } catch (Throwable throwable) {
        throw a(null);
      } 
      Zzi_.ZJ(Class.forName(a(17492, -13804)));
    } catch (Throwable throwable) {}
  }
  
  static {
    // Byte code:
    //   0: bipush #13
    //   2: anewarray java/lang/String
    //   5: astore #5
    //   7: iconst_0
    //   8: istore_3
    //   9: ldc 'e\\t #O#;@gju Ug4A\\bAM15/}Ecfh[ \\fFN~(iLpcx\\t`o\z$B\\t\\rNP  w<DzUh"[&8A\To\\tz\\t4^AJA!6B:'
    //   11: dup
    //   12: astore_2
    //   13: invokevirtual length : ()I
    //   16: istore #4
    //   18: iconst_4
    //   19: istore_1
    //   20: iconst_m1
    //   21: istore_0
    //   22: bipush #65
    //   24: iinc #0, 1
    //   27: aload_2
    //   28: iload_0
    //   29: dup
    //   30: iload_1
    //   31: iadd
    //   32: invokevirtual substring : (II)Ljava/lang/String;
    //   35: iconst_m1
    //   36: goto -> 142
    //   39: aload #5
    //   41: swap
    //   42: iload_3
    //   43: iinc #3, 1
    //   46: swap
    //   47: aastore
    //   48: iload_0
    //   49: iload_1
    //   50: iadd
    //   51: dup
    //   52: istore_0
    //   53: iload #4
    //   55: if_icmpge -> 67
    //   58: aload_2
    //   59: iload_0
    //   60: invokevirtual charAt : (I)C
    //   63: istore_1
    //   64: goto -> 22
    //   67: ldc 'S\\biM/N8xXQ{r%|^jNQ)7\\tDi=v.oO +*zl'
    //   69: dup
    //   70: astore_2
    //   71: invokevirtual length : ()I
    //   74: istore #4
    //   76: bipush #9
    //   78: istore_1
    //   79: iconst_m1
    //   80: istore_0
    //   81: bipush #71
    //   83: iinc #0, 1
    //   86: aload_2
    //   87: iload_0
    //   88: dup
    //   89: iload_1
    //   90: iadd
    //   91: invokevirtual substring : (II)Ljava/lang/String;
    //   94: iconst_0
    //   95: goto -> 142
    //   98: aload #5
    //   100: swap
    //   101: iload_3
    //   102: iinc #3, 1
    //   105: swap
    //   106: aastore
    //   107: iload_0
    //   108: iload_1
    //   109: iadd
    //   110: dup
    //   111: istore_0
    //   112: iload #4
    //   114: if_icmpge -> 126
    //   117: aload_2
    //   118: iload_0
    //   119: invokevirtual charAt : (I)C
    //   122: istore_1
    //   123: goto -> 81
    //   126: aload #5
    //   128: putstatic burp/Zse8.a : [Ljava/lang/String;
    //   131: bipush #13
    //   133: anewarray java/lang/String
    //   136: putstatic burp/Zse8.b : [Ljava/lang/String;
    //   139: goto -> 300
    //   142: dup_x2
    //   143: pop
    //   144: invokevirtual toCharArray : ()[C
    //   147: dup_x1
    //   148: arraylength
    //   149: dup_x2
    //   150: pop
    //   151: iconst_0
    //   152: istore #6
    //   154: dup2_x1
    //   155: pop2
    //   156: dup_x2
    //   157: iconst_1
    //   158: if_icmpgt -> 260
    //   161: dup2
    //   162: swap
    //   163: iload #6
    //   165: dup2_x1
    //   166: caload
    //   167: swap
    //   168: iload #6
    //   170: bipush #7
    //   172: irem
    //   173: tableswitch default -> 242, 0 -> 212, 1 -> 217, 2 -> 222, 3 -> 227, 4 -> 232, 5 -> 237
    //   212: bipush #48
    //   214: goto -> 244
    //   217: bipush #60
    //   219: goto -> 244
    //   222: bipush #72
    //   224: goto -> 244
    //   227: bipush #58
    //   229: goto -> 244
    //   232: bipush #85
    //   234: goto -> 244
    //   237: bipush #38
    //   239: goto -> 244
    //   242: bipush #102
    //   244: ixor
    //   245: ixor
    //   246: i2c
    //   247: castore
    //   248: iinc #6, 1
    //   251: dup
    //   252: ifne -> 260
    //   255: dup2
    //   256: dup_x1
    //   257: goto -> 165
    //   260: dup2_x1
    //   261: pop2
    //   262: dup_x2
    //   263: iload #6
    //   265: if_icmpgt -> 161
    //   268: pop
    //   269: new java/lang/String
    //   272: dup_x1
    //   273: swap
    //   274: invokespecial <init> : ([C)V
    //   277: invokevirtual intern : ()Ljava/lang/String;
    //   280: swap
    //   281: pop
    //   282: swap
    //   283: tableswitch default -> 39, 0 -> 98
    //   300: sipush #17499
    //   303: sipush #17467
    //   306: invokestatic a : (II)Ljava/lang/String;
    //   309: putstatic burp/Zse8.Ze : Ljava/lang/String;
    //   312: new java/math/BigInteger
    //   315: dup
    //   316: iconst_1
    //   317: bipush #32
    //   319: newarray byte
    //   321: dup
    //   322: iconst_0
    //   323: bipush #9
    //   325: bastore
    //   326: dup
    //   327: iconst_1
    //   328: bipush #25
    //   330: bastore
    //   331: dup
    //   332: iconst_2
    //   333: bipush #101
    //   335: bastore
    //   336: dup
    //   337: iconst_3
    //   338: bipush #-114
    //   340: bastore
    //   341: dup
    //   342: iconst_4
    //   343: bipush #23
    //   345: bastore
    //   346: dup
    //   347: iconst_5
    //   348: bipush #-30
    //   350: bastore
    //   351: dup
    //   352: bipush #6
    //   354: bipush #-25
    //   356: bastore
    //   357: dup
    //   358: bipush #7
    //   360: bipush #-49
    //   362: bastore
    //   363: dup
    //   364: bipush #8
    //   366: bipush #-86
    //   368: bastore
    //   369: dup
    //   370: bipush #9
    //   372: bipush #-32
    //   374: bastore
    //   375: dup
    //   376: bipush #10
    //   378: bipush #-38
    //   380: bastore
    //   381: dup
    //   382: bipush #11
    //   384: bipush #-83
    //   386: bastore
    //   387: dup
    //   388: bipush #12
    //   390: bipush #52
    //   392: bastore
    //   393: dup
    //   394: bipush #13
    //   396: bipush #9
    //   398: bastore
    //   399: dup
    //   400: bipush #14
    //   402: bipush #88
    //   404: bastore
    //   405: dup
    //   406: bipush #15
    //   408: bipush #45
    //   410: bastore
    //   411: dup
    //   412: bipush #16
    //   414: bipush #-87
    //   416: bastore
    //   417: dup
    //   418: bipush #17
    //   420: iconst_3
    //   421: bastore
    //   422: dup
    //   423: bipush #18
    //   425: bipush #38
    //   427: bastore
    //   428: dup
    //   429: bipush #19
    //   431: bipush #93
    //   433: bastore
    //   434: dup
    //   435: bipush #20
    //   437: bipush #109
    //   439: bastore
    //   440: dup
    //   441: bipush #21
    //   443: bipush #-32
    //   445: bastore
    //   446: dup
    //   447: bipush #22
    //   449: bipush #112
    //   451: bastore
    //   452: dup
    //   453: bipush #23
    //   455: bipush #-23
    //   457: bastore
    //   458: dup
    //   459: bipush #24
    //   461: bipush #51
    //   463: bastore
    //   464: dup
    //   465: bipush #25
    //   467: bipush #-91
    //   469: bastore
    //   470: dup
    //   471: bipush #26
    //   473: bipush #35
    //   475: bastore
    //   476: dup
    //   477: bipush #27
    //   479: bipush #-67
    //   481: bastore
    //   482: dup
    //   483: bipush #28
    //   485: bipush #-20
    //   487: bastore
    //   488: dup
    //   489: bipush #29
    //   491: bipush #-14
    //   493: bastore
    //   494: dup
    //   495: bipush #30
    //   497: bipush #-74
    //   499: bastore
    //   500: dup
    //   501: bipush #31
    //   503: bipush #-118
    //   505: bastore
    //   506: invokespecial <init> : (I[B)V
    //   509: putstatic burp/Zse8.Zn : Ljava/lang/Object;
    //   512: return
  }
  
  private static Throwable a(Throwable paramThrowable) {
    return paramThrowable;
  }
  
  private static String a(int paramInt1, int paramInt2) {
    int i = (paramInt1 ^ 0x4453) & 0xFFFF;
    if (b[i] == null) {
      char[] arrayOfChar = a[i].toCharArray();
      switch (arrayOfChar[0] & 0xFF) {
        case 0:
        
        case 1:
        
        case 2:
        
        case 3:
        
        case 4:
        
        case 5:
        
        case 6:
        
        case 7:
        
        case 8:
        
        case 9:
        
        case 10:
        
        case 11:
        
        case 12:
        
        case 13:
        
        case 14:
        
        case 15:
        
        case 16:
        
        case 17:
        
        case 18:
        
        case 19:
        
        case 20:
        
        case 21:
        
        case 22:
        
        case 23:
        
        case 24:
        
        case 25:
        
        case 26:
        
        case 27:
        
        case 28:
        
        case 29:
        
        case 30:
        
        case 31:
        
        case 32:
        
        case 33:
        
        case 34:
        
        case 35:
        
        case 36:
        
        case 37:
        
        case 38:
        
        case 39:
        
        case 40:
        
        case 41:
        
        case 42:
        
        case 43:
        
        case 44:
        
        case 45:
        
        case 46:
        
        case 47:
        
        case 48:
        
        case 49:
        
        case 50:
        
        case 51:
        
        case 52:
        
        case 53:
        
        case 54:
        
        case 55:
        
        case 56:
        
        case 57:
        
        case 58:
        
        case 59:
        
        case 60:
        
        case 61:
        
        case 62:
        
        case 63:
        
        case 64:
        
        case 65:
        
        case 66:
        
        case 67:
        
        case 68:
        
        case 69:
        
        case 70:
        
        case 71:
        
        case 72:
        
        case 73:
        
        case 74:
        
        case 75:
        
        case 76:
        
        case 77:
        
        case 78:
        
        case 79:
        
        case 80:
        
        case 81:
        
        case 82:
        
        case 83:
        
        case 84:
        
        case 85:
        
        case 86:
        
        case 87:
        
        case 88:
        
        case 89:
        
        case 90:
        
        case 91:
        
        case 92:
        
        case 93:
        
        case 94:
        
        case 95:
        
        case 96:
        
        case 97:
        
        case 98:
        
        case 99:
        
        case 100:
        
        case 101:
        
        case 102:
        
        case 103:
        
        case 104:
        
        case 105:
        
        case 106:
        
        case 107:
        
        case 108:
        
        case 109:
        
        case 110:
        
        case 111:
        
        case 112:
        
        case 113:
        
        case 114:
        
        case 115:
        
        case 116:
        
        case 117:
        
        case 118:
        
        case 119:
        
        case 120:
        
        case 121:
        
        case 122:
        
        case 123:
        
        case 124:
        
        case 125:
        
        case 126:
        
        case 127:
        
        case 128:
        
        case 129:
        
        case 130:
        
        case 131:
        
        case 132:
        
        case 133:
        
        case 134:
        
        case 135:
        
        case 136:
        
        case 137:
        
        case 138:
        
        case 139:
        
        case 140:
        
        case 141:
        
        case 142:
        
        case 143:
        
        case 144:
        
        case 145:
        
        case 146:
        
        case 147:
        
        case 148:
        
        case 149:
        
        case 150:
        
        case 151:
        
        case 152:
        
        case 153:
        
        case 154:
        
        case 155:
        
        case 156:
        
        case 157:
        
        case 158:
        
        case 159:
        
        case 160:
        
        case 161:
        
        case 162:
        
        case 163:
        
        case 164:
        
        case 165:
        
        case 166:
        
        case 167:
        
        case 168:
        
        case 169:
        
        case 170:
        
        case 171:
        
        case 172:
        
        case 173:
        
        case 174:
        
        case 175:
        
        case 176:
        
        case 177:
        
        case 178:
        
        case 179:
        
        case 180:
        
        case 181:
        
        case 182:
        
        case 183:
        
        case 184:
        
        case 185:
        
        case 186:
        
        case 187:
        
        case 188:
        
        case 189:
        
        case 190:
        
        case 191:
        
        case 192:
        
        case 193:
        
        case 194:
        
        case 195:
        
        case 196:
        
        case 197:
        
        case 198:
        
        case 199:
        
        case 200:
        
        case 201:
        
        case 202:
        
        case 203:
        
        case 204:
        
        case 205:
        
        case 206:
        
        case 207:
        
        case 208:
        
        case 209:
        
        case 210:
        
        case 211:
        
        case 212:
        
        case 213:
        
        case 214:
        
        case 215:
        
        case 216:
        
        case 217:
        
        case 218:
        
        case 219:
        
        case 220:
        
        case 221:
        
        case 222:
        
        case 223:
        
        case 224:
        
        case 225:
        
        case 226:
        
        case 227:
        
        case 228:
        
        case 229:
        
        case 230:
        
        case 231:
        
        case 232:
        
        case 233:
        
        case 234:
        
        case 235:
        
        case 236:
        
        case 237:
        
        case 238:
        
        case 239:
        
        case 240:
        
        case 241:
        
        case 242:
        
        case 243:
        
        case 244:
        
        case 245:
        
        case 246:
        
        case 247:
        
        case 248:
        
        case 249:
        
        case 250:
        
        case 251:
        
        case 252:
        
        case 253:
        
        case 254:
        
        default:
          break;
      } 
      char c = '';
      int j = (paramInt2 & 0xFF) - c;
      if (j < 0)
        j += 256; 
      int k = ((paramInt2 & 0xFFFF) >>> 8) - c;
      if (k < 0)
        k += 256; 
      for (byte b = 0; b < arrayOfChar.length; b++) {
        int m = b % 2;
        if (m == 0) {
          arrayOfChar[b] = (char)(arrayOfChar[b] ^ j);
          j = ((j >>> 3 | j << 5) ^ arrayOfChar[b]) & 0xFF;
        } else {
          arrayOfChar[b] = (char)(arrayOfChar[b] ^ k);
          k = ((k >>> 3 | k << 5) ^ arrayOfChar[b]) & 0xFF;
        } 
      } 
      b[i] = (new String(arrayOfChar)).intern();
    } 
    return b[i];
  }
}


/* Location:              C:\Program Files\BurpSuitePro\burpsuite_pro.jar!\burp\Zse8.class
 * Java compiler version: 21 (65.0)
 * JD-Core Version:       1.1.3
 */