package burp;

import java.math.BigInteger;

class Zsf4 extends ClassLoader {
  static Object Zr;
  
  static String ZA;
  
  private static final String[] a;
  
  private static final String[] b;
  
  static boolean Zq(Object[] paramArrayOfObject, Object paramObject) throws Throwable {
    // Byte code:
    //   0: invokestatic ZK : ()Z
    //   3: istore_2
    //   4: getstatic burp/Zmh0.Zt : Ljava/lang/Object;
    //   7: checkcast java/math/BigInteger
    //   10: invokevirtual toByteArray : ()[B
    //   13: astore_3
    //   14: iconst_0
    //   15: istore #5
    //   17: iconst_0
    //   18: istore #6
    //   20: iload #6
    //   22: aload_3
    //   23: arraylength
    //   24: if_icmpge -> 169
    //   27: aload_3
    //   28: iload #6
    //   30: baload
    //   31: istore #7
    //   33: iload #7
    //   35: bipush #48
    //   37: if_icmplt -> 54
    //   40: iload #7
    //   42: bipush #57
    //   44: if_icmple -> 152
    //   47: goto -> 54
    //   50: invokestatic a : (Ljava/lang/Throwable;)Ljava/lang/Throwable;
    //   53: athrow
    //   54: iload #7
    //   56: bipush #65
    //   58: if_icmplt -> 82
    //   61: goto -> 68
    //   64: invokestatic a : (Ljava/lang/Throwable;)Ljava/lang/Throwable;
    //   67: athrow
    //   68: iload #7
    //   70: bipush #90
    //   72: if_icmple -> 152
    //   75: goto -> 82
    //   78: invokestatic a : (Ljava/lang/Throwable;)Ljava/lang/Throwable;
    //   81: athrow
    //   82: iload #7
    //   84: bipush #97
    //   86: if_icmplt -> 110
    //   89: goto -> 96
    //   92: invokestatic a : (Ljava/lang/Throwable;)Ljava/lang/Throwable;
    //   95: athrow
    //   96: iload #7
    //   98: bipush #122
    //   100: if_icmple -> 152
    //   103: goto -> 110
    //   106: invokestatic a : (Ljava/lang/Throwable;)Ljava/lang/Throwable;
    //   109: athrow
    //   110: iload #7
    //   112: bipush #43
    //   114: if_icmpeq -> 152
    //   117: goto -> 124
    //   120: invokestatic a : (Ljava/lang/Throwable;)Ljava/lang/Throwable;
    //   123: athrow
    //   124: iload #7
    //   126: bipush #47
    //   128: if_icmpeq -> 152
    //   131: goto -> 138
    //   134: invokestatic a : (Ljava/lang/Throwable;)Ljava/lang/Throwable;
    //   137: athrow
    //   138: iload #7
    //   140: bipush #61
    //   142: if_icmpne -> 162
    //   145: goto -> 152
    //   148: invokestatic a : (Ljava/lang/Throwable;)Ljava/lang/Throwable;
    //   151: athrow
    //   152: iinc #5, 1
    //   155: goto -> 162
    //   158: invokestatic a : (Ljava/lang/Throwable;)Ljava/lang/Throwable;
    //   161: athrow
    //   162: iinc #6, 1
    //   165: iload_2
    //   166: ifeq -> 20
    //   169: iload #5
    //   171: newarray byte
    //   173: astore #6
    //   175: iconst_0
    //   176: istore #7
    //   178: iconst_0
    //   179: istore #8
    //   181: iload #8
    //   183: aload_3
    //   184: arraylength
    //   185: if_icmpge -> 337
    //   188: aload_3
    //   189: iload #8
    //   191: baload
    //   192: istore #9
    //   194: iload #9
    //   196: bipush #48
    //   198: if_icmplt -> 215
    //   201: iload #9
    //   203: bipush #57
    //   205: if_icmple -> 313
    //   208: goto -> 215
    //   211: invokestatic a : (Ljava/lang/Throwable;)Ljava/lang/Throwable;
    //   214: athrow
    //   215: iload #9
    //   217: bipush #65
    //   219: if_icmplt -> 243
    //   222: goto -> 229
    //   225: invokestatic a : (Ljava/lang/Throwable;)Ljava/lang/Throwable;
    //   228: athrow
    //   229: iload #9
    //   231: bipush #90
    //   233: if_icmple -> 313
    //   236: goto -> 243
    //   239: invokestatic a : (Ljava/lang/Throwable;)Ljava/lang/Throwable;
    //   242: athrow
    //   243: iload #9
    //   245: bipush #97
    //   247: if_icmplt -> 271
    //   250: goto -> 257
    //   253: invokestatic a : (Ljava/lang/Throwable;)Ljava/lang/Throwable;
    //   256: athrow
    //   257: iload #9
    //   259: bipush #122
    //   261: if_icmple -> 313
    //   264: goto -> 271
    //   267: invokestatic a : (Ljava/lang/Throwable;)Ljava/lang/Throwable;
    //   270: athrow
    //   271: iload #9
    //   273: bipush #43
    //   275: if_icmpeq -> 313
    //   278: goto -> 285
    //   281: invokestatic a : (Ljava/lang/Throwable;)Ljava/lang/Throwable;
    //   284: athrow
    //   285: iload #9
    //   287: bipush #47
    //   289: if_icmpeq -> 313
    //   292: goto -> 299
    //   295: invokestatic a : (Ljava/lang/Throwable;)Ljava/lang/Throwable;
    //   298: athrow
    //   299: iload #9
    //   301: bipush #61
    //   303: if_icmpne -> 330
    //   306: goto -> 313
    //   309: invokestatic a : (Ljava/lang/Throwable;)Ljava/lang/Throwable;
    //   312: athrow
    //   313: aload #6
    //   315: iload #7
    //   317: iload #9
    //   319: bastore
    //   320: iinc #7, 1
    //   323: goto -> 330
    //   326: invokestatic a : (Ljava/lang/Throwable;)Ljava/lang/Throwable;
    //   329: athrow
    //   330: iinc #8, 1
    //   333: iload_2
    //   334: ifeq -> 181
    //   337: aload #6
    //   339: astore #4
    //   341: aload #4
    //   343: astore_3
    //   344: aload_3
    //   345: arraylength
    //   346: istore #5
    //   348: aload_3
    //   349: iload #5
    //   351: iconst_1
    //   352: isub
    //   353: baload
    //   354: bipush #61
    //   356: if_icmpne -> 366
    //   359: iinc #5, -1
    //   362: iload_2
    //   363: ifeq -> 348
    //   366: iload #5
    //   368: aload_3
    //   369: arraylength
    //   370: iconst_4
    //   371: idiv
    //   372: isub
    //   373: newarray byte
    //   375: astore #6
    //   377: iconst_0
    //   378: istore #7
    //   380: iload #7
    //   382: aload_3
    //   383: arraylength
    //   384: if_icmpge -> 646
    //   387: aload_3
    //   388: iload #7
    //   390: baload
    //   391: bipush #61
    //   393: if_icmpne -> 412
    //   396: aload_3
    //   397: iload #7
    //   399: iconst_0
    //   400: bastore
    //   401: iload_2
    //   402: ifeq -> 639
    //   405: goto -> 412
    //   408: invokestatic a : (Ljava/lang/Throwable;)Ljava/lang/Throwable;
    //   411: athrow
    //   412: aload_3
    //   413: iload #7
    //   415: baload
    //   416: bipush #47
    //   418: if_icmpne -> 445
    //   421: goto -> 428
    //   424: invokestatic a : (Ljava/lang/Throwable;)Ljava/lang/Throwable;
    //   427: athrow
    //   428: aload_3
    //   429: iload #7
    //   431: bipush #63
    //   433: bastore
    //   434: iload_2
    //   435: ifeq -> 639
    //   438: goto -> 445
    //   441: invokestatic a : (Ljava/lang/Throwable;)Ljava/lang/Throwable;
    //   444: athrow
    //   445: aload_3
    //   446: iload #7
    //   448: baload
    //   449: bipush #43
    //   451: if_icmpne -> 478
    //   454: goto -> 461
    //   457: invokestatic a : (Ljava/lang/Throwable;)Ljava/lang/Throwable;
    //   460: athrow
    //   461: aload_3
    //   462: iload #7
    //   464: bipush #62
    //   466: bastore
    //   467: iload_2
    //   468: ifeq -> 639
    //   471: goto -> 478
    //   474: invokestatic a : (Ljava/lang/Throwable;)Ljava/lang/Throwable;
    //   477: athrow
    //   478: aload_3
    //   479: iload #7
    //   481: baload
    //   482: bipush #48
    //   484: if_icmplt -> 533
    //   487: goto -> 494
    //   490: invokestatic a : (Ljava/lang/Throwable;)Ljava/lang/Throwable;
    //   493: athrow
    //   494: aload_3
    //   495: iload #7
    //   497: baload
    //   498: bipush #57
    //   500: if_icmpgt -> 533
    //   503: goto -> 510
    //   506: invokestatic a : (Ljava/lang/Throwable;)Ljava/lang/Throwable;
    //   509: athrow
    //   510: aload_3
    //   511: iload #7
    //   513: aload_3
    //   514: iload #7
    //   516: baload
    //   517: bipush #-4
    //   519: isub
    //   520: i2b
    //   521: bastore
    //   522: iload_2
    //   523: ifeq -> 639
    //   526: goto -> 533
    //   529: invokestatic a : (Ljava/lang/Throwable;)Ljava/lang/Throwable;
    //   532: athrow
    //   533: aload_3
    //   534: iload #7
    //   536: baload
    //   537: bipush #97
    //   539: if_icmplt -> 588
    //   542: goto -> 549
    //   545: invokestatic a : (Ljava/lang/Throwable;)Ljava/lang/Throwable;
    //   548: athrow
    //   549: aload_3
    //   550: iload #7
    //   552: baload
    //   553: bipush #122
    //   555: if_icmpgt -> 588
    //   558: goto -> 565
    //   561: invokestatic a : (Ljava/lang/Throwable;)Ljava/lang/Throwable;
    //   564: athrow
    //   565: aload_3
    //   566: iload #7
    //   568: aload_3
    //   569: iload #7
    //   571: baload
    //   572: bipush #71
    //   574: isub
    //   575: i2b
    //   576: bastore
    //   577: iload_2
    //   578: ifeq -> 639
    //   581: goto -> 588
    //   584: invokestatic a : (Ljava/lang/Throwable;)Ljava/lang/Throwable;
    //   587: athrow
    //   588: aload_3
    //   589: iload #7
    //   591: baload
    //   592: bipush #65
    //   594: if_icmplt -> 639
    //   597: goto -> 604
    //   600: invokestatic a : (Ljava/lang/Throwable;)Ljava/lang/Throwable;
    //   603: athrow
    //   604: aload_3
    //   605: iload #7
    //   607: baload
    //   608: bipush #90
    //   610: if_icmpgt -> 639
    //   613: goto -> 620
    //   616: invokestatic a : (Ljava/lang/Throwable;)Ljava/lang/Throwable;
    //   619: athrow
    //   620: aload_3
    //   621: iload #7
    //   623: aload_3
    //   624: iload #7
    //   626: baload
    //   627: bipush #65
    //   629: isub
    //   630: i2b
    //   631: bastore
    //   632: goto -> 639
    //   635: invokestatic a : (Ljava/lang/Throwable;)Ljava/lang/Throwable;
    //   638: athrow
    //   639: iinc #7, 1
    //   642: iload_2
    //   643: ifeq -> 380
    //   646: iconst_0
    //   647: istore #7
    //   649: iconst_0
    //   650: istore #8
    //   652: iload #8
    //   654: aload #6
    //   656: arraylength
    //   657: iconst_2
    //   658: isub
    //   659: if_icmpge -> 762
    //   662: aload #6
    //   664: iload #8
    //   666: aload_3
    //   667: iload #7
    //   669: baload
    //   670: iconst_2
    //   671: ishl
    //   672: sipush #255
    //   675: iand
    //   676: aload_3
    //   677: iload #7
    //   679: iconst_1
    //   680: iadd
    //   681: baload
    //   682: iconst_4
    //   683: iushr
    //   684: iconst_3
    //   685: iand
    //   686: ior
    //   687: i2b
    //   688: bastore
    //   689: aload #6
    //   691: iload #8
    //   693: iconst_1
    //   694: iadd
    //   695: aload_3
    //   696: iload #7
    //   698: iconst_1
    //   699: iadd
    //   700: baload
    //   701: iconst_4
    //   702: ishl
    //   703: sipush #255
    //   706: iand
    //   707: aload_3
    //   708: iload #7
    //   710: iconst_2
    //   711: iadd
    //   712: baload
    //   713: iconst_2
    //   714: iushr
    //   715: bipush #15
    //   717: iand
    //   718: ior
    //   719: i2b
    //   720: bastore
    //   721: aload #6
    //   723: iload #8
    //   725: iconst_2
    //   726: iadd
    //   727: aload_3
    //   728: iload #7
    //   730: iconst_2
    //   731: iadd
    //   732: baload
    //   733: bipush #6
    //   735: ishl
    //   736: sipush #255
    //   739: iand
    //   740: aload_3
    //   741: iload #7
    //   743: iconst_3
    //   744: iadd
    //   745: baload
    //   746: bipush #63
    //   748: iand
    //   749: ior
    //   750: i2b
    //   751: bastore
    //   752: iinc #7, 4
    //   755: iinc #8, 3
    //   758: iload_2
    //   759: ifeq -> 652
    //   762: iload #8
    //   764: aload #6
    //   766: arraylength
    //   767: if_icmpge -> 804
    //   770: aload #6
    //   772: iload #8
    //   774: aload_3
    //   775: iload #7
    //   777: baload
    //   778: iconst_2
    //   779: ishl
    //   780: sipush #255
    //   783: iand
    //   784: aload_3
    //   785: iload #7
    //   787: iconst_1
    //   788: iadd
    //   789: baload
    //   790: iconst_4
    //   791: iushr
    //   792: iconst_3
    //   793: iand
    //   794: ior
    //   795: i2b
    //   796: bastore
    //   797: goto -> 804
    //   800: invokestatic a : (Ljava/lang/Throwable;)Ljava/lang/Throwable;
    //   803: athrow
    //   804: iinc #8, 1
    //   807: iload #8
    //   809: aload #6
    //   811: arraylength
    //   812: if_icmpge -> 852
    //   815: aload #6
    //   817: iload #8
    //   819: aload_3
    //   820: iload #7
    //   822: iconst_1
    //   823: iadd
    //   824: baload
    //   825: iconst_4
    //   826: ishl
    //   827: sipush #255
    //   830: iand
    //   831: aload_3
    //   832: iload #7
    //   834: iconst_2
    //   835: iadd
    //   836: baload
    //   837: iconst_2
    //   838: iushr
    //   839: bipush #15
    //   841: iand
    //   842: ior
    //   843: i2b
    //   844: bastore
    //   845: goto -> 852
    //   848: invokestatic a : (Ljava/lang/Throwable;)Ljava/lang/Throwable;
    //   851: athrow
    //   852: aload #6
    //   854: astore #4
    //   856: new java/math/BigInteger
    //   859: dup
    //   860: aload #4
    //   862: invokespecial <init> : ([B)V
    //   865: invokevirtual abs : ()Ljava/math/BigInteger;
    //   868: putstatic burp/Zg3m.ZK : Ljava/lang/Object;
    //   871: getstatic burp/Zbxa.ZS : Ljava/lang/Object;
    //   874: checkcast java/math/BigInteger
    //   877: invokevirtual toByteArray : ()[B
    //   880: astore_3
    //   881: iconst_0
    //   882: istore #5
    //   884: iconst_0
    //   885: istore #6
    //   887: iload #6
    //   889: aload_3
    //   890: arraylength
    //   891: if_icmpge -> 1036
    //   894: aload_3
    //   895: iload #6
    //   897: baload
    //   898: istore #7
    //   900: iload #7
    //   902: bipush #48
    //   904: if_icmplt -> 921
    //   907: iload #7
    //   909: bipush #57
    //   911: if_icmple -> 1019
    //   914: goto -> 921
    //   917: invokestatic a : (Ljava/lang/Throwable;)Ljava/lang/Throwable;
    //   920: athrow
    //   921: iload #7
    //   923: bipush #65
    //   925: if_icmplt -> 949
    //   928: goto -> 935
    //   931: invokestatic a : (Ljava/lang/Throwable;)Ljava/lang/Throwable;
    //   934: athrow
    //   935: iload #7
    //   937: bipush #90
    //   939: if_icmple -> 1019
    //   942: goto -> 949
    //   945: invokestatic a : (Ljava/lang/Throwable;)Ljava/lang/Throwable;
    //   948: athrow
    //   949: iload #7
    //   951: bipush #97
    //   953: if_icmplt -> 977
    //   956: goto -> 963
    //   959: invokestatic a : (Ljava/lang/Throwable;)Ljava/lang/Throwable;
    //   962: athrow
    //   963: iload #7
    //   965: bipush #122
    //   967: if_icmple -> 1019
    //   970: goto -> 977
    //   973: invokestatic a : (Ljava/lang/Throwable;)Ljava/lang/Throwable;
    //   976: athrow
    //   977: iload #7
    //   979: bipush #43
    //   981: if_icmpeq -> 1019
    //   984: goto -> 991
    //   987: invokestatic a : (Ljava/lang/Throwable;)Ljava/lang/Throwable;
    //   990: athrow
    //   991: iload #7
    //   993: bipush #47
    //   995: if_icmpeq -> 1019
    //   998: goto -> 1005
    //   1001: invokestatic a : (Ljava/lang/Throwable;)Ljava/lang/Throwable;
    //   1004: athrow
    //   1005: iload #7
    //   1007: bipush #61
    //   1009: if_icmpne -> 1029
    //   1012: goto -> 1019
    //   1015: invokestatic a : (Ljava/lang/Throwable;)Ljava/lang/Throwable;
    //   1018: athrow
    //   1019: iinc #5, 1
    //   1022: goto -> 1029
    //   1025: invokestatic a : (Ljava/lang/Throwable;)Ljava/lang/Throwable;
    //   1028: athrow
    //   1029: iinc #6, 1
    //   1032: iload_2
    //   1033: ifeq -> 887
    //   1036: iload #5
    //   1038: newarray byte
    //   1040: astore #6
    //   1042: iconst_0
    //   1043: istore #7
    //   1045: iconst_0
    //   1046: istore #8
    //   1048: iload #8
    //   1050: aload_3
    //   1051: arraylength
    //   1052: if_icmpge -> 1204
    //   1055: aload_3
    //   1056: iload #8
    //   1058: baload
    //   1059: istore #9
    //   1061: iload #9
    //   1063: bipush #48
    //   1065: if_icmplt -> 1082
    //   1068: iload #9
    //   1070: bipush #57
    //   1072: if_icmple -> 1180
    //   1075: goto -> 1082
    //   1078: invokestatic a : (Ljava/lang/Throwable;)Ljava/lang/Throwable;
    //   1081: athrow
    //   1082: iload #9
    //   1084: bipush #65
    //   1086: if_icmplt -> 1110
    //   1089: goto -> 1096
    //   1092: invokestatic a : (Ljava/lang/Throwable;)Ljava/lang/Throwable;
    //   1095: athrow
    //   1096: iload #9
    //   1098: bipush #90
    //   1100: if_icmple -> 1180
    //   1103: goto -> 1110
    //   1106: invokestatic a : (Ljava/lang/Throwable;)Ljava/lang/Throwable;
    //   1109: athrow
    //   1110: iload #9
    //   1112: bipush #97
    //   1114: if_icmplt -> 1138
    //   1117: goto -> 1124
    //   1120: invokestatic a : (Ljava/lang/Throwable;)Ljava/lang/Throwable;
    //   1123: athrow
    //   1124: iload #9
    //   1126: bipush #122
    //   1128: if_icmple -> 1180
    //   1131: goto -> 1138
    //   1134: invokestatic a : (Ljava/lang/Throwable;)Ljava/lang/Throwable;
    //   1137: athrow
    //   1138: iload #9
    //   1140: bipush #43
    //   1142: if_icmpeq -> 1180
    //   1145: goto -> 1152
    //   1148: invokestatic a : (Ljava/lang/Throwable;)Ljava/lang/Throwable;
    //   1151: athrow
    //   1152: iload #9
    //   1154: bipush #47
    //   1156: if_icmpeq -> 1180
    //   1159: goto -> 1166
    //   1162: invokestatic a : (Ljava/lang/Throwable;)Ljava/lang/Throwable;
    //   1165: athrow
    //   1166: iload #9
    //   1168: bipush #61
    //   1170: if_icmpne -> 1197
    //   1173: goto -> 1180
    //   1176: invokestatic a : (Ljava/lang/Throwable;)Ljava/lang/Throwable;
    //   1179: athrow
    //   1180: aload #6
    //   1182: iload #7
    //   1184: iload #9
    //   1186: bastore
    //   1187: iinc #7, 1
    //   1190: goto -> 1197
    //   1193: invokestatic a : (Ljava/lang/Throwable;)Ljava/lang/Throwable;
    //   1196: athrow
    //   1197: iinc #8, 1
    //   1200: iload_2
    //   1201: ifeq -> 1048
    //   1204: aload #6
    //   1206: astore #4
    //   1208: aload #4
    //   1210: astore_3
    //   1211: aload_3
    //   1212: arraylength
    //   1213: istore #5
    //   1215: aload_3
    //   1216: iload #5
    //   1218: iconst_1
    //   1219: isub
    //   1220: baload
    //   1221: bipush #61
    //   1223: if_icmpne -> 1233
    //   1226: iinc #5, -1
    //   1229: iload_2
    //   1230: ifeq -> 1215
    //   1233: iload #5
    //   1235: aload_3
    //   1236: arraylength
    //   1237: iconst_4
    //   1238: idiv
    //   1239: isub
    //   1240: newarray byte
    //   1242: astore #6
    //   1244: iconst_0
    //   1245: istore #7
    //   1247: iload #7
    //   1249: aload_3
    //   1250: arraylength
    //   1251: if_icmpge -> 1513
    //   1254: aload_3
    //   1255: iload #7
    //   1257: baload
    //   1258: bipush #61
    //   1260: if_icmpne -> 1279
    //   1263: aload_3
    //   1264: iload #7
    //   1266: iconst_0
    //   1267: bastore
    //   1268: iload_2
    //   1269: ifeq -> 1506
    //   1272: goto -> 1279
    //   1275: invokestatic a : (Ljava/lang/Throwable;)Ljava/lang/Throwable;
    //   1278: athrow
    //   1279: aload_3
    //   1280: iload #7
    //   1282: baload
    //   1283: bipush #47
    //   1285: if_icmpne -> 1312
    //   1288: goto -> 1295
    //   1291: invokestatic a : (Ljava/lang/Throwable;)Ljava/lang/Throwable;
    //   1294: athrow
    //   1295: aload_3
    //   1296: iload #7
    //   1298: bipush #63
    //   1300: bastore
    //   1301: iload_2
    //   1302: ifeq -> 1506
    //   1305: goto -> 1312
    //   1308: invokestatic a : (Ljava/lang/Throwable;)Ljava/lang/Throwable;
    //   1311: athrow
    //   1312: aload_3
    //   1313: iload #7
    //   1315: baload
    //   1316: bipush #43
    //   1318: if_icmpne -> 1345
    //   1321: goto -> 1328
    //   1324: invokestatic a : (Ljava/lang/Throwable;)Ljava/lang/Throwable;
    //   1327: athrow
    //   1328: aload_3
    //   1329: iload #7
    //   1331: bipush #62
    //   1333: bastore
    //   1334: iload_2
    //   1335: ifeq -> 1506
    //   1338: goto -> 1345
    //   1341: invokestatic a : (Ljava/lang/Throwable;)Ljava/lang/Throwable;
    //   1344: athrow
    //   1345: aload_3
    //   1346: iload #7
    //   1348: baload
    //   1349: bipush #48
    //   1351: if_icmplt -> 1400
    //   1354: goto -> 1361
    //   1357: invokestatic a : (Ljava/lang/Throwable;)Ljava/lang/Throwable;
    //   1360: athrow
    //   1361: aload_3
    //   1362: iload #7
    //   1364: baload
    //   1365: bipush #57
    //   1367: if_icmpgt -> 1400
    //   1370: goto -> 1377
    //   1373: invokestatic a : (Ljava/lang/Throwable;)Ljava/lang/Throwable;
    //   1376: athrow
    //   1377: aload_3
    //   1378: iload #7
    //   1380: aload_3
    //   1381: iload #7
    //   1383: baload
    //   1384: bipush #-4
    //   1386: isub
    //   1387: i2b
    //   1388: bastore
    //   1389: iload_2
    //   1390: ifeq -> 1506
    //   1393: goto -> 1400
    //   1396: invokestatic a : (Ljava/lang/Throwable;)Ljava/lang/Throwable;
    //   1399: athrow
    //   1400: aload_3
    //   1401: iload #7
    //   1403: baload
    //   1404: bipush #97
    //   1406: if_icmplt -> 1455
    //   1409: goto -> 1416
    //   1412: invokestatic a : (Ljava/lang/Throwable;)Ljava/lang/Throwable;
    //   1415: athrow
    //   1416: aload_3
    //   1417: iload #7
    //   1419: baload
    //   1420: bipush #122
    //   1422: if_icmpgt -> 1455
    //   1425: goto -> 1432
    //   1428: invokestatic a : (Ljava/lang/Throwable;)Ljava/lang/Throwable;
    //   1431: athrow
    //   1432: aload_3
    //   1433: iload #7
    //   1435: aload_3
    //   1436: iload #7
    //   1438: baload
    //   1439: bipush #71
    //   1441: isub
    //   1442: i2b
    //   1443: bastore
    //   1444: iload_2
    //   1445: ifeq -> 1506
    //   1448: goto -> 1455
    //   1451: invokestatic a : (Ljava/lang/Throwable;)Ljava/lang/Throwable;
    //   1454: athrow
    //   1455: aload_3
    //   1456: iload #7
    //   1458: baload
    //   1459: bipush #65
    //   1461: if_icmplt -> 1506
    //   1464: goto -> 1471
    //   1467: invokestatic a : (Ljava/lang/Throwable;)Ljava/lang/Throwable;
    //   1470: athrow
    //   1471: aload_3
    //   1472: iload #7
    //   1474: baload
    //   1475: bipush #90
    //   1477: if_icmpgt -> 1506
    //   1480: goto -> 1487
    //   1483: invokestatic a : (Ljava/lang/Throwable;)Ljava/lang/Throwable;
    //   1486: athrow
    //   1487: aload_3
    //   1488: iload #7
    //   1490: aload_3
    //   1491: iload #7
    //   1493: baload
    //   1494: bipush #65
    //   1496: isub
    //   1497: i2b
    //   1498: bastore
    //   1499: goto -> 1506
    //   1502: invokestatic a : (Ljava/lang/Throwable;)Ljava/lang/Throwable;
    //   1505: athrow
    //   1506: iinc #7, 1
    //   1509: iload_2
    //   1510: ifeq -> 1247
    //   1513: iconst_0
    //   1514: istore #7
    //   1516: iconst_0
    //   1517: istore #8
    //   1519: iload #8
    //   1521: aload #6
    //   1523: arraylength
    //   1524: iconst_2
    //   1525: isub
    //   1526: if_icmpge -> 1629
    //   1529: aload #6
    //   1531: iload #8
    //   1533: aload_3
    //   1534: iload #7
    //   1536: baload
    //   1537: iconst_2
    //   1538: ishl
    //   1539: sipush #255
    //   1542: iand
    //   1543: aload_3
    //   1544: iload #7
    //   1546: iconst_1
    //   1547: iadd
    //   1548: baload
    //   1549: iconst_4
    //   1550: iushr
    //   1551: iconst_3
    //   1552: iand
    //   1553: ior
    //   1554: i2b
    //   1555: bastore
    //   1556: aload #6
    //   1558: iload #8
    //   1560: iconst_1
    //   1561: iadd
    //   1562: aload_3
    //   1563: iload #7
    //   1565: iconst_1
    //   1566: iadd
    //   1567: baload
    //   1568: iconst_4
    //   1569: ishl
    //   1570: sipush #255
    //   1573: iand
    //   1574: aload_3
    //   1575: iload #7
    //   1577: iconst_2
    //   1578: iadd
    //   1579: baload
    //   1580: iconst_2
    //   1581: iushr
    //   1582: bipush #15
    //   1584: iand
    //   1585: ior
    //   1586: i2b
    //   1587: bastore
    //   1588: aload #6
    //   1590: iload #8
    //   1592: iconst_2
    //   1593: iadd
    //   1594: aload_3
    //   1595: iload #7
    //   1597: iconst_2
    //   1598: iadd
    //   1599: baload
    //   1600: bipush #6
    //   1602: ishl
    //   1603: sipush #255
    //   1606: iand
    //   1607: aload_3
    //   1608: iload #7
    //   1610: iconst_3
    //   1611: iadd
    //   1612: baload
    //   1613: bipush #63
    //   1615: iand
    //   1616: ior
    //   1617: i2b
    //   1618: bastore
    //   1619: iinc #7, 4
    //   1622: iinc #8, 3
    //   1625: iload_2
    //   1626: ifeq -> 1519
    //   1629: iload #8
    //   1631: aload #6
    //   1633: arraylength
    //   1634: if_icmpge -> 1671
    //   1637: aload #6
    //   1639: iload #8
    //   1641: aload_3
    //   1642: iload #7
    //   1644: baload
    //   1645: iconst_2
    //   1646: ishl
    //   1647: sipush #255
    //   1650: iand
    //   1651: aload_3
    //   1652: iload #7
    //   1654: iconst_1
    //   1655: iadd
    //   1656: baload
    //   1657: iconst_4
    //   1658: iushr
    //   1659: iconst_3
    //   1660: iand
    //   1661: ior
    //   1662: i2b
    //   1663: bastore
    //   1664: goto -> 1671
    //   1667: invokestatic a : (Ljava/lang/Throwable;)Ljava/lang/Throwable;
    //   1670: athrow
    //   1671: iinc #8, 1
    //   1674: iload #8
    //   1676: aload #6
    //   1678: arraylength
    //   1679: if_icmpge -> 1719
    //   1682: aload #6
    //   1684: iload #8
    //   1686: aload_3
    //   1687: iload #7
    //   1689: iconst_1
    //   1690: iadd
    //   1691: baload
    //   1692: iconst_4
    //   1693: ishl
    //   1694: sipush #255
    //   1697: iand
    //   1698: aload_3
    //   1699: iload #7
    //   1701: iconst_2
    //   1702: iadd
    //   1703: baload
    //   1704: iconst_2
    //   1705: iushr
    //   1706: bipush #15
    //   1708: iand
    //   1709: ior
    //   1710: i2b
    //   1711: bastore
    //   1712: goto -> 1719
    //   1715: invokestatic a : (Ljava/lang/Throwable;)Ljava/lang/Throwable;
    //   1718: athrow
    //   1719: aload #6
    //   1721: astore #4
    //   1723: new java/math/BigInteger
    //   1726: dup
    //   1727: aload #4
    //   1729: invokespecial <init> : ([B)V
    //   1732: invokevirtual abs : ()Ljava/math/BigInteger;
    //   1735: putstatic burp/Zeai.ZI : Ljava/lang/Object;
    //   1738: new java/lang/StringBuilder
    //   1741: dup
    //   1742: invokespecial <init> : ()V
    //   1745: astore_3
    //   1746: iconst_0
    //   1747: istore #4
    //   1749: iload #4
    //   1751: bipush #32
    //   1753: if_icmpge -> 3087
    //   1756: iload #4
    //   1758: tableswitch default -> 3080, 0 -> 1900, 1 -> 1937, 2 -> 1974, 3 -> 2011, 4 -> 2048, 5 -> 2085, 6 -> 2122, 7 -> 2159, 8 -> 2196, 9 -> 2233, 10 -> 2270, 11 -> 2307, 12 -> 2344, 13 -> 2381, 14 -> 2418, 15 -> 2455, 16 -> 2492, 17 -> 2529, 18 -> 2566, 19 -> 2603, 20 -> 2640, 21 -> 2677, 22 -> 2714, 23 -> 2751, 24 -> 2788, 25 -> 2825, 26 -> 2862, 27 -> 2899, 28 -> 2936, 29 -> 2973, 30 -> 3010, 31 -> 3047
    //   1900: aload_3
    //   1901: getstatic burp/Ze9.Zh : Ljava/lang/String;
    //   1904: getstatic burp/Zl1z.ZV : Ljava/lang/Object;
    //   1907: checkcast java/math/BigInteger
    //   1910: invokevirtual intValue : ()I
    //   1913: bipush #32
    //   1915: irem
    //   1916: invokestatic abs : (I)I
    //   1919: invokevirtual charAt : (I)C
    //   1922: invokevirtual append : (C)Ljava/lang/StringBuilder;
    //   1925: pop
    //   1926: iload_2
    //   1927: ifeq -> 3080
    //   1930: goto -> 1937
    //   1933: invokestatic a : (Ljava/lang/Throwable;)Ljava/lang/Throwable;
    //   1936: athrow
    //   1937: aload_3
    //   1938: getstatic burp/Zth8.ZN : Ljava/lang/String;
    //   1941: getstatic burp/Zzh9.Zv : Ljava/lang/Object;
    //   1944: checkcast java/math/BigInteger
    //   1947: invokevirtual intValue : ()I
    //   1950: bipush #32
    //   1952: irem
    //   1953: invokestatic abs : (I)I
    //   1956: invokevirtual charAt : (I)C
    //   1959: invokevirtual append : (C)Ljava/lang/StringBuilder;
    //   1962: pop
    //   1963: iload_2
    //   1964: ifeq -> 3080
    //   1967: goto -> 1974
    //   1970: invokestatic a : (Ljava/lang/Throwable;)Ljava/lang/Throwable;
    //   1973: athrow
    //   1974: aload_3
    //   1975: getstatic burp/Zewq.ZV : Ljava/lang/String;
    //   1978: getstatic burp/Zl6z.Zt : Ljava/lang/Object;
    //   1981: checkcast java/math/BigInteger
    //   1984: invokevirtual intValue : ()I
    //   1987: bipush #32
    //   1989: irem
    //   1990: invokestatic abs : (I)I
    //   1993: invokevirtual charAt : (I)C
    //   1996: invokevirtual append : (C)Ljava/lang/StringBuilder;
    //   1999: pop
    //   2000: iload_2
    //   2001: ifeq -> 3080
    //   2004: goto -> 2011
    //   2007: invokestatic a : (Ljava/lang/Throwable;)Ljava/lang/Throwable;
    //   2010: athrow
    //   2011: aload_3
    //   2012: getstatic burp/Zm5s.Z_ : Ljava/lang/String;
    //   2015: getstatic burp/Zre4.Zx : Ljava/lang/Object;
    //   2018: checkcast java/math/BigInteger
    //   2021: invokevirtual intValue : ()I
    //   2024: bipush #32
    //   2026: irem
    //   2027: invokestatic abs : (I)I
    //   2030: invokevirtual charAt : (I)C
    //   2033: invokevirtual append : (C)Ljava/lang/StringBuilder;
    //   2036: pop
    //   2037: iload_2
    //   2038: ifeq -> 3080
    //   2041: goto -> 2048
    //   2044: invokestatic a : (Ljava/lang/Throwable;)Ljava/lang/Throwable;
    //   2047: athrow
    //   2048: aload_3
    //   2049: getstatic burp/Zl6z.ZL : Ljava/lang/String;
    //   2052: getstatic burp/Zlzs.ZL : Ljava/lang/Object;
    //   2055: checkcast java/math/BigInteger
    //   2058: invokevirtual intValue : ()I
    //   2061: bipush #32
    //   2063: irem
    //   2064: invokestatic abs : (I)I
    //   2067: invokevirtual charAt : (I)C
    //   2070: invokevirtual append : (C)Ljava/lang/StringBuilder;
    //   2073: pop
    //   2074: iload_2
    //   2075: ifeq -> 3080
    //   2078: goto -> 2085
    //   2081: invokestatic a : (Ljava/lang/Throwable;)Ljava/lang/Throwable;
    //   2084: athrow
    //   2085: aload_3
    //   2086: getstatic burp/Zt5a.Zl : Ljava/lang/String;
    //   2089: getstatic burp/Zz8o.Zg : Ljava/lang/Object;
    //   2092: checkcast java/math/BigInteger
    //   2095: invokevirtual intValue : ()I
    //   2098: bipush #32
    //   2100: irem
    //   2101: invokestatic abs : (I)I
    //   2104: invokevirtual charAt : (I)C
    //   2107: invokevirtual append : (C)Ljava/lang/StringBuilder;
    //   2110: pop
    //   2111: iload_2
    //   2112: ifeq -> 3080
    //   2115: goto -> 2122
    //   2118: invokestatic a : (Ljava/lang/Throwable;)Ljava/lang/Throwable;
    //   2121: athrow
    //   2122: aload_3
    //   2123: getstatic burp/Zbxa.ZY : Ljava/lang/String;
    //   2126: getstatic burp/Zlhu.ZJ : Ljava/lang/Object;
    //   2129: checkcast java/math/BigInteger
    //   2132: invokevirtual intValue : ()I
    //   2135: bipush #32
    //   2137: irem
    //   2138: invokestatic abs : (I)I
    //   2141: invokevirtual charAt : (I)C
    //   2144: invokevirtual append : (C)Ljava/lang/StringBuilder;
    //   2147: pop
    //   2148: iload_2
    //   2149: ifeq -> 3080
    //   2152: goto -> 2159
    //   2155: invokestatic a : (Ljava/lang/Throwable;)Ljava/lang/Throwable;
    //   2158: athrow
    //   2159: aload_3
    //   2160: getstatic burp/Zbsc.Zp : Ljava/lang/String;
    //   2163: getstatic burp/Zrct.ZV : Ljava/lang/Object;
    //   2166: checkcast java/math/BigInteger
    //   2169: invokevirtual intValue : ()I
    //   2172: bipush #32
    //   2174: irem
    //   2175: invokestatic abs : (I)I
    //   2178: invokevirtual charAt : (I)C
    //   2181: invokevirtual append : (C)Ljava/lang/StringBuilder;
    //   2184: pop
    //   2185: iload_2
    //   2186: ifeq -> 3080
    //   2189: goto -> 2196
    //   2192: invokestatic a : (Ljava/lang/Throwable;)Ljava/lang/Throwable;
    //   2195: athrow
    //   2196: aload_3
    //   2197: getstatic burp/Zmly.Zi : Ljava/lang/String;
    //   2200: getstatic burp/Zrp3.Zd : Ljava/lang/Object;
    //   2203: checkcast java/math/BigInteger
    //   2206: invokevirtual intValue : ()I
    //   2209: bipush #32
    //   2211: irem
    //   2212: invokestatic abs : (I)I
    //   2215: invokevirtual charAt : (I)C
    //   2218: invokevirtual append : (C)Ljava/lang/StringBuilder;
    //   2221: pop
    //   2222: iload_2
    //   2223: ifeq -> 3080
    //   2226: goto -> 2233
    //   2229: invokestatic a : (Ljava/lang/Throwable;)Ljava/lang/Throwable;
    //   2232: athrow
    //   2233: aload_3
    //   2234: getstatic burp/Zzhu.ZT : Ljava/lang/String;
    //   2237: getstatic burp/Zth8.Zk : Ljava/lang/Object;
    //   2240: checkcast java/math/BigInteger
    //   2243: invokevirtual intValue : ()I
    //   2246: bipush #32
    //   2248: irem
    //   2249: invokestatic abs : (I)I
    //   2252: invokevirtual charAt : (I)C
    //   2255: invokevirtual append : (C)Ljava/lang/StringBuilder;
    //   2258: pop
    //   2259: iload_2
    //   2260: ifeq -> 3080
    //   2263: goto -> 2270
    //   2266: invokestatic a : (Ljava/lang/Throwable;)Ljava/lang/Throwable;
    //   2269: athrow
    //   2270: aload_3
    //   2271: getstatic burp/Zrp3.Zf : Ljava/lang/String;
    //   2274: getstatic burp/Zm5s.ZB : Ljava/lang/Object;
    //   2277: checkcast java/math/BigInteger
    //   2280: invokevirtual intValue : ()I
    //   2283: bipush #32
    //   2285: irem
    //   2286: invokestatic abs : (I)I
    //   2289: invokevirtual charAt : (I)C
    //   2292: invokevirtual append : (C)Ljava/lang/StringBuilder;
    //   2295: pop
    //   2296: iload_2
    //   2297: ifeq -> 3080
    //   2300: goto -> 2307
    //   2303: invokestatic a : (Ljava/lang/Throwable;)Ljava/lang/Throwable;
    //   2306: athrow
    //   2307: aload_3
    //   2308: getstatic burp/Zms1.ZZ : Ljava/lang/String;
    //   2311: getstatic burp/Zgs6.Za : Ljava/lang/Object;
    //   2314: checkcast java/math/BigInteger
    //   2317: invokevirtual intValue : ()I
    //   2320: bipush #32
    //   2322: irem
    //   2323: invokestatic abs : (I)I
    //   2326: invokevirtual charAt : (I)C
    //   2329: invokevirtual append : (C)Ljava/lang/StringBuilder;
    //   2332: pop
    //   2333: iload_2
    //   2334: ifeq -> 3080
    //   2337: goto -> 2344
    //   2340: invokestatic a : (Ljava/lang/Throwable;)Ljava/lang/Throwable;
    //   2343: athrow
    //   2344: aload_3
    //   2345: getstatic burp/Zmdm.Za : Ljava/lang/String;
    //   2348: getstatic burp/Zr9j.Zw : Ljava/lang/Object;
    //   2351: checkcast java/math/BigInteger
    //   2354: invokevirtual intValue : ()I
    //   2357: bipush #32
    //   2359: irem
    //   2360: invokestatic abs : (I)I
    //   2363: invokevirtual charAt : (I)C
    //   2366: invokevirtual append : (C)Ljava/lang/StringBuilder;
    //   2369: pop
    //   2370: iload_2
    //   2371: ifeq -> 3080
    //   2374: goto -> 2381
    //   2377: invokestatic a : (Ljava/lang/Throwable;)Ljava/lang/Throwable;
    //   2380: athrow
    //   2381: aload_3
    //   2382: getstatic burp/Zeju.ZR : Ljava/lang/String;
    //   2385: getstatic burp/Zm5s.ZB : Ljava/lang/Object;
    //   2388: checkcast java/math/BigInteger
    //   2391: invokevirtual intValue : ()I
    //   2394: bipush #32
    //   2396: irem
    //   2397: invokestatic abs : (I)I
    //   2400: invokevirtual charAt : (I)C
    //   2403: invokevirtual append : (C)Ljava/lang/StringBuilder;
    //   2406: pop
    //   2407: iload_2
    //   2408: ifeq -> 3080
    //   2411: goto -> 2418
    //   2414: invokestatic a : (Ljava/lang/Throwable;)Ljava/lang/Throwable;
    //   2417: athrow
    //   2418: aload_3
    //   2419: getstatic burp/Ze9.Zh : Ljava/lang/String;
    //   2422: getstatic burp/Zeju.Zk : Ljava/lang/Object;
    //   2425: checkcast java/math/BigInteger
    //   2428: invokevirtual intValue : ()I
    //   2431: bipush #32
    //   2433: irem
    //   2434: invokestatic abs : (I)I
    //   2437: invokevirtual charAt : (I)C
    //   2440: invokevirtual append : (C)Ljava/lang/StringBuilder;
    //   2443: pop
    //   2444: iload_2
    //   2445: ifeq -> 3080
    //   2448: goto -> 2455
    //   2451: invokestatic a : (Ljava/lang/Throwable;)Ljava/lang/Throwable;
    //   2454: athrow
    //   2455: aload_3
    //   2456: getstatic burp/Zmec.Zi : Ljava/lang/String;
    //   2459: getstatic burp/Zro_.ZP : Ljava/lang/Object;
    //   2462: checkcast java/math/BigInteger
    //   2465: invokevirtual intValue : ()I
    //   2468: bipush #32
    //   2470: irem
    //   2471: invokestatic abs : (I)I
    //   2474: invokevirtual charAt : (I)C
    //   2477: invokevirtual append : (C)Ljava/lang/StringBuilder;
    //   2480: pop
    //   2481: iload_2
    //   2482: ifeq -> 3080
    //   2485: goto -> 2492
    //   2488: invokestatic a : (Ljava/lang/Throwable;)Ljava/lang/Throwable;
    //   2491: athrow
    //   2492: aload_3
    //   2493: getstatic burp/Zej5.Zo : Ljava/lang/String;
    //   2496: getstatic burp/Zro_.ZP : Ljava/lang/Object;
    //   2499: checkcast java/math/BigInteger
    //   2502: invokevirtual intValue : ()I
    //   2505: bipush #32
    //   2507: irem
    //   2508: invokestatic abs : (I)I
    //   2511: invokevirtual charAt : (I)C
    //   2514: invokevirtual append : (C)Ljava/lang/StringBuilder;
    //   2517: pop
    //   2518: iload_2
    //   2519: ifeq -> 3080
    //   2522: goto -> 2529
    //   2525: invokestatic a : (Ljava/lang/Throwable;)Ljava/lang/Throwable;
    //   2528: athrow
    //   2529: aload_3
    //   2530: getstatic burp/Zm5s.Z_ : Ljava/lang/String;
    //   2533: getstatic burp/Zr9j.Zw : Ljava/lang/Object;
    //   2536: checkcast java/math/BigInteger
    //   2539: invokevirtual intValue : ()I
    //   2542: bipush #32
    //   2544: irem
    //   2545: invokestatic abs : (I)I
    //   2548: invokevirtual charAt : (I)C
    //   2551: invokevirtual append : (C)Ljava/lang/StringBuilder;
    //   2554: pop
    //   2555: iload_2
    //   2556: ifeq -> 3080
    //   2559: goto -> 2566
    //   2562: invokestatic a : (Ljava/lang/Throwable;)Ljava/lang/Throwable;
    //   2565: athrow
    //   2566: aload_3
    //   2567: getstatic burp/Zeai.ZA : Ljava/lang/String;
    //   2570: getstatic burp/Zxee.Zj : Ljava/lang/Object;
    //   2573: checkcast java/math/BigInteger
    //   2576: invokevirtual intValue : ()I
    //   2579: bipush #32
    //   2581: irem
    //   2582: invokestatic abs : (I)I
    //   2585: invokevirtual charAt : (I)C
    //   2588: invokevirtual append : (C)Ljava/lang/StringBuilder;
    //   2591: pop
    //   2592: iload_2
    //   2593: ifeq -> 3080
    //   2596: goto -> 2603
    //   2599: invokestatic a : (Ljava/lang/Throwable;)Ljava/lang/Throwable;
    //   2602: athrow
    //   2603: aload_3
    //   2604: getstatic burp/Zrh1.Zg : Ljava/lang/String;
    //   2607: getstatic burp/Zmec.ZY : Ljava/lang/Object;
    //   2610: checkcast java/math/BigInteger
    //   2613: invokevirtual intValue : ()I
    //   2616: bipush #32
    //   2618: irem
    //   2619: invokestatic abs : (I)I
    //   2622: invokevirtual charAt : (I)C
    //   2625: invokevirtual append : (C)Ljava/lang/StringBuilder;
    //   2628: pop
    //   2629: iload_2
    //   2630: ifeq -> 3080
    //   2633: goto -> 2640
    //   2636: invokestatic a : (Ljava/lang/Throwable;)Ljava/lang/Throwable;
    //   2639: athrow
    //   2640: aload_3
    //   2641: getstatic burp/Zl6z.ZL : Ljava/lang/String;
    //   2644: getstatic burp/Zrx5.ZE : Ljava/lang/Object;
    //   2647: checkcast java/math/BigInteger
    //   2650: invokevirtual intValue : ()I
    //   2653: bipush #32
    //   2655: irem
    //   2656: invokestatic abs : (I)I
    //   2659: invokevirtual charAt : (I)C
    //   2662: invokevirtual append : (C)Ljava/lang/StringBuilder;
    //   2665: pop
    //   2666: iload_2
    //   2667: ifeq -> 3080
    //   2670: goto -> 2677
    //   2673: invokestatic a : (Ljava/lang/Throwable;)Ljava/lang/Throwable;
    //   2676: athrow
    //   2677: aload_3
    //   2678: getstatic burp/Zrnw.Zg : Ljava/lang/String;
    //   2681: getstatic burp/Zr9j.Zw : Ljava/lang/Object;
    //   2684: checkcast java/math/BigInteger
    //   2687: invokevirtual intValue : ()I
    //   2690: bipush #32
    //   2692: irem
    //   2693: invokestatic abs : (I)I
    //   2696: invokevirtual charAt : (I)C
    //   2699: invokevirtual append : (C)Ljava/lang/StringBuilder;
    //   2702: pop
    //   2703: iload_2
    //   2704: ifeq -> 3080
    //   2707: goto -> 2714
    //   2710: invokestatic a : (Ljava/lang/Throwable;)Ljava/lang/Throwable;
    //   2713: athrow
    //   2714: aload_3
    //   2715: getstatic burp/Zzhu.ZT : Ljava/lang/String;
    //   2718: getstatic burp/Ztg3.Zg : Ljava/lang/Object;
    //   2721: checkcast java/math/BigInteger
    //   2724: invokevirtual intValue : ()I
    //   2727: bipush #32
    //   2729: irem
    //   2730: invokestatic abs : (I)I
    //   2733: invokevirtual charAt : (I)C
    //   2736: invokevirtual append : (C)Ljava/lang/StringBuilder;
    //   2739: pop
    //   2740: iload_2
    //   2741: ifeq -> 3080
    //   2744: goto -> 2751
    //   2747: invokestatic a : (Ljava/lang/Throwable;)Ljava/lang/Throwable;
    //   2750: athrow
    //   2751: aload_3
    //   2752: getstatic burp/Zms1.ZZ : Ljava/lang/String;
    //   2755: getstatic burp/Ztdg.ZE : Ljava/lang/Object;
    //   2758: checkcast java/math/BigInteger
    //   2761: invokevirtual intValue : ()I
    //   2764: bipush #32
    //   2766: irem
    //   2767: invokestatic abs : (I)I
    //   2770: invokevirtual charAt : (I)C
    //   2773: invokevirtual append : (C)Ljava/lang/StringBuilder;
    //   2776: pop
    //   2777: iload_2
    //   2778: ifeq -> 3080
    //   2781: goto -> 2788
    //   2784: invokestatic a : (Ljava/lang/Throwable;)Ljava/lang/Throwable;
    //   2787: athrow
    //   2788: aload_3
    //   2789: getstatic burp/Zmly.Zi : Ljava/lang/String;
    //   2792: getstatic burp/Zb8_.ZT : Ljava/lang/Object;
    //   2795: checkcast java/math/BigInteger
    //   2798: invokevirtual intValue : ()I
    //   2801: bipush #32
    //   2803: irem
    //   2804: invokestatic abs : (I)I
    //   2807: invokevirtual charAt : (I)C
    //   2810: invokevirtual append : (C)Ljava/lang/StringBuilder;
    //   2813: pop
    //   2814: iload_2
    //   2815: ifeq -> 3080
    //   2818: goto -> 2825
    //   2821: invokestatic a : (Ljava/lang/Throwable;)Ljava/lang/Throwable;
    //   2824: athrow
    //   2825: aload_3
    //   2826: getstatic burp/Zz5l.ZH : Ljava/lang/String;
    //   2829: getstatic burp/Zg5.Zs : Ljava/lang/Object;
    //   2832: checkcast java/math/BigInteger
    //   2835: invokevirtual intValue : ()I
    //   2838: bipush #32
    //   2840: irem
    //   2841: invokestatic abs : (I)I
    //   2844: invokevirtual charAt : (I)C
    //   2847: invokevirtual append : (C)Ljava/lang/StringBuilder;
    //   2850: pop
    //   2851: iload_2
    //   2852: ifeq -> 3080
    //   2855: goto -> 2862
    //   2858: invokestatic a : (Ljava/lang/Throwable;)Ljava/lang/Throwable;
    //   2861: athrow
    //   2862: aload_3
    //   2863: getstatic burp/Zgl2.Zw : Ljava/lang/String;
    //   2866: getstatic burp/Ze_e.Za : Ljava/lang/Object;
    //   2869: checkcast java/math/BigInteger
    //   2872: invokevirtual intValue : ()I
    //   2875: bipush #32
    //   2877: irem
    //   2878: invokestatic abs : (I)I
    //   2881: invokevirtual charAt : (I)C
    //   2884: invokevirtual append : (C)Ljava/lang/StringBuilder;
    //   2887: pop
    //   2888: iload_2
    //   2889: ifeq -> 3080
    //   2892: goto -> 2899
    //   2895: invokestatic a : (Ljava/lang/Throwable;)Ljava/lang/Throwable;
    //   2898: athrow
    //   2899: aload_3
    //   2900: getstatic burp/Zrx5.ZD : Ljava/lang/String;
    //   2903: getstatic burp/Zl1z.ZV : Ljava/lang/Object;
    //   2906: checkcast java/math/BigInteger
    //   2909: invokevirtual intValue : ()I
    //   2912: bipush #32
    //   2914: irem
    //   2915: invokestatic abs : (I)I
    //   2918: invokevirtual charAt : (I)C
    //   2921: invokevirtual append : (C)Ljava/lang/StringBuilder;
    //   2924: pop
    //   2925: iload_2
    //   2926: ifeq -> 3080
    //   2929: goto -> 2936
    //   2932: invokestatic a : (Ljava/lang/Throwable;)Ljava/lang/Throwable;
    //   2935: athrow
    //   2936: aload_3
    //   2937: getstatic burp/Zlwi.ZN : Ljava/lang/String;
    //   2940: getstatic burp/Zl15.Zn : Ljava/lang/Object;
    //   2943: checkcast java/math/BigInteger
    //   2946: invokevirtual intValue : ()I
    //   2949: bipush #32
    //   2951: irem
    //   2952: invokestatic abs : (I)I
    //   2955: invokevirtual charAt : (I)C
    //   2958: invokevirtual append : (C)Ljava/lang/StringBuilder;
    //   2961: pop
    //   2962: iload_2
    //   2963: ifeq -> 3080
    //   2966: goto -> 2973
    //   2969: invokestatic a : (Ljava/lang/Throwable;)Ljava/lang/Throwable;
    //   2972: athrow
    //   2973: aload_3
    //   2974: getstatic burp/Zbsc.Zp : Ljava/lang/String;
    //   2977: getstatic burp/Zeai.ZI : Ljava/lang/Object;
    //   2980: checkcast java/math/BigInteger
    //   2983: invokevirtual intValue : ()I
    //   2986: bipush #32
    //   2988: irem
    //   2989: invokestatic abs : (I)I
    //   2992: invokevirtual charAt : (I)C
    //   2995: invokevirtual append : (C)Ljava/lang/StringBuilder;
    //   2998: pop
    //   2999: iload_2
    //   3000: ifeq -> 3080
    //   3003: goto -> 3010
    //   3006: invokestatic a : (Ljava/lang/Throwable;)Ljava/lang/Throwable;
    //   3009: athrow
    //   3010: aload_3
    //   3011: getstatic burp/Zsf4.ZA : Ljava/lang/String;
    //   3014: getstatic burp/Zrx5.ZE : Ljava/lang/Object;
    //   3017: checkcast java/math/BigInteger
    //   3020: invokevirtual intValue : ()I
    //   3023: bipush #32
    //   3025: irem
    //   3026: invokestatic abs : (I)I
    //   3029: invokevirtual charAt : (I)C
    //   3032: invokevirtual append : (C)Ljava/lang/StringBuilder;
    //   3035: pop
    //   3036: iload_2
    //   3037: ifeq -> 3080
    //   3040: goto -> 3047
    //   3043: invokestatic a : (Ljava/lang/Throwable;)Ljava/lang/Throwable;
    //   3046: athrow
    //   3047: aload_3
    //   3048: getstatic burp/Zm5s.Z_ : Ljava/lang/String;
    //   3051: getstatic burp/Zeju.Zk : Ljava/lang/Object;
    //   3054: checkcast java/math/BigInteger
    //   3057: invokevirtual intValue : ()I
    //   3060: bipush #32
    //   3062: irem
    //   3063: invokestatic abs : (I)I
    //   3066: invokevirtual charAt : (I)C
    //   3069: invokevirtual append : (C)Ljava/lang/StringBuilder;
    //   3072: pop
    //   3073: goto -> 3080
    //   3076: invokestatic a : (Ljava/lang/Throwable;)Ljava/lang/Throwable;
    //   3079: athrow
    //   3080: iinc #4, 1
    //   3083: iload_2
    //   3084: ifeq -> 1749
    //   3087: aload_3
    //   3088: invokevirtual toString : ()Ljava/lang/String;
    //   3091: putstatic burp/Zl8s.Zn : Ljava/lang/String;
    //   3094: sipush #-26925
    //   3097: sipush #-3083
    //   3100: invokestatic a : (II)Ljava/lang/String;
    //   3103: iconst_1
    //   3104: ldc burp/Zs75
    //   3106: invokevirtual getClassLoader : ()Ljava/lang/ClassLoader;
    //   3109: invokestatic forName : (Ljava/lang/String;ZLjava/lang/ClassLoader;)Ljava/lang/Class;
    //   3112: invokevirtual getDeclaredFields : ()[Ljava/lang/reflect/Field;
    //   3115: astore #4
    //   3117: aload #4
    //   3119: arraylength
    //   3120: istore #5
    //   3122: iconst_0
    //   3123: istore #6
    //   3125: iload #6
    //   3127: iload #5
    //   3129: if_icmpge -> 3267
    //   3132: aload #4
    //   3134: iload #6
    //   3136: aaload
    //   3137: astore #7
    //   3139: aload #7
    //   3141: invokevirtual getModifiers : ()I
    //   3144: invokestatic isStatic : (I)Z
    //   3147: ifne -> 3157
    //   3150: goto -> 3260
    //   3153: invokestatic a : (Ljava/lang/Throwable;)Ljava/lang/Throwable;
    //   3156: athrow
    //   3157: aload #7
    //   3159: invokevirtual getType : ()Ljava/lang/Class;
    //   3162: astore #8
    //   3164: aload #8
    //   3166: ifnull -> 3247
    //   3169: aload #8
    //   3171: invokevirtual isPrimitive : ()Z
    //   3174: ifne -> 3247
    //   3177: goto -> 3184
    //   3180: invokestatic a : (Ljava/lang/Throwable;)Ljava/lang/Throwable;
    //   3183: athrow
    //   3184: aload #8
    //   3186: invokevirtual getPackage : ()Ljava/lang/Package;
    //   3189: ifnull -> 3247
    //   3192: goto -> 3199
    //   3195: invokestatic a : (Ljava/lang/Throwable;)Ljava/lang/Throwable;
    //   3198: athrow
    //   3199: aload #8
    //   3201: invokevirtual getPackage : ()Ljava/lang/Package;
    //   3204: invokevirtual getName : ()Ljava/lang/String;
    //   3207: ifnull -> 3247
    //   3210: goto -> 3217
    //   3213: invokestatic a : (Ljava/lang/Throwable;)Ljava/lang/Throwable;
    //   3216: athrow
    //   3217: aload #8
    //   3219: invokevirtual getPackage : ()Ljava/lang/Package;
    //   3222: invokevirtual getName : ()Ljava/lang/String;
    //   3225: sipush #-26927
    //   3228: sipush #397
    //   3231: invokestatic a : (II)Ljava/lang/String;
    //   3234: invokevirtual startsWith : (Ljava/lang/String;)Z
    //   3237: ifne -> 3247
    //   3240: goto -> 3247
    //   3243: invokestatic a : (Ljava/lang/Throwable;)Ljava/lang/Throwable;
    //   3246: athrow
    //   3247: aload #7
    //   3249: iconst_1
    //   3250: invokevirtual setAccessible : (Z)V
    //   3253: aload #7
    //   3255: aconst_null
    //   3256: invokevirtual get : (Ljava/lang/Object;)Ljava/lang/Object;
    //   3259: pop
    //   3260: iinc #6, 1
    //   3263: iload_2
    //   3264: ifeq -> 3125
    //   3267: sipush #-26923
    //   3270: sipush #-20154
    //   3273: invokestatic a : (II)Ljava/lang/String;
    //   3276: invokestatic forName : (Ljava/lang/String;)Ljava/lang/Class;
    //   3279: invokevirtual getDeclaredMethods : ()[Ljava/lang/reflect/Method;
    //   3282: astore #4
    //   3284: aload #4
    //   3286: arraylength
    //   3287: istore #5
    //   3289: iconst_0
    //   3290: istore #6
    //   3292: iload #6
    //   3294: iload #5
    //   3296: if_icmpge -> 3429
    //   3299: aload #4
    //   3301: iload #6
    //   3303: aaload
    //   3304: astore #7
    //   3306: aload #7
    //   3308: invokevirtual getParameterTypes : ()[Ljava/lang/Class;
    //   3311: pop
    //   3312: aload #7
    //   3314: invokevirtual getModifiers : ()I
    //   3317: invokestatic isStatic : (I)Z
    //   3320: ifeq -> 3415
    //   3323: aload #7
    //   3325: invokevirtual getParameterTypes : ()[Ljava/lang/Class;
    //   3328: arraylength
    //   3329: iconst_2
    //   3330: if_icmpne -> 3415
    //   3333: goto -> 3340
    //   3336: invokestatic a : (Ljava/lang/Throwable;)Ljava/lang/Throwable;
    //   3339: athrow
    //   3340: aload #7
    //   3342: invokevirtual getReturnType : ()Ljava/lang/Class;
    //   3345: getstatic java/lang/Void.TYPE : Ljava/lang/Class;
    //   3348: invokevirtual equals : (Ljava/lang/Object;)Z
    //   3351: ifeq -> 3415
    //   3354: goto -> 3361
    //   3357: invokestatic a : (Ljava/lang/Throwable;)Ljava/lang/Throwable;
    //   3360: athrow
    //   3361: aload #7
    //   3363: iconst_1
    //   3364: invokevirtual setAccessible : (Z)V
    //   3367: aload #7
    //   3369: aconst_null
    //   3370: iconst_2
    //   3371: anewarray java/lang/Object
    //   3374: dup
    //   3375: iconst_0
    //   3376: aload_0
    //   3377: aastore
    //   3378: dup
    //   3379: iconst_1
    //   3380: aload_1
    //   3381: ifnonnull -> 3399
    //   3384: goto -> 3391
    //   3387: invokestatic a : (Ljava/lang/Throwable;)Ljava/lang/Throwable;
    //   3390: athrow
    //   3391: aload_1
    //   3392: goto -> 3406
    //   3395: invokestatic a : (Ljava/lang/Throwable;)Ljava/lang/Throwable;
    //   3398: athrow
    //   3399: aload_1
    //   3400: checkcast [B
    //   3403: invokevirtual clone : ()Ljava/lang/Object;
    //   3406: aastore
    //   3407: invokevirtual invoke : (Ljava/lang/Object;[Ljava/lang/Object;)Ljava/lang/Object;
    //   3410: pop
    //   3411: iload_2
    //   3412: ifeq -> 3429
    //   3415: iinc #6, 1
    //   3418: iload_2
    //   3419: ifeq -> 3292
    //   3422: goto -> 3429
    //   3425: invokestatic a : (Ljava/lang/Throwable;)Ljava/lang/Throwable;
    //   3428: athrow
    //   3429: getstatic burp/Zevc.ZF : Ljava/lang/String;
    //   3432: getstatic burp/Zmfw.ZS : Ljava/lang/Object;
    //   3435: checkcast java/math/BigInteger
    //   3438: invokevirtual intValue : ()I
    //   3441: bipush #32
    //   3443: irem
    //   3444: invokestatic abs : (I)I
    //   3447: invokevirtual charAt : (I)C
    //   3450: getstatic burp/Zr8r.Zn : Ljava/lang/String;
    //   3453: getstatic burp/Zrt9.Zy : Ljava/lang/Object;
    //   3456: checkcast java/math/BigInteger
    //   3459: invokevirtual intValue : ()I
    //   3462: bipush #32
    //   3464: irem
    //   3465: invokestatic abs : (I)I
    //   3468: invokevirtual charAt : (I)C
    //   3471: if_icmpgt -> 3578
    //   3474: getstatic burp/Zlwi.ZN : Ljava/lang/String;
    //   3477: getstatic burp/Zrxf.ZS : Ljava/lang/Object;
    //   3480: checkcast java/math/BigInteger
    //   3483: invokevirtual intValue : ()I
    //   3486: bipush #32
    //   3488: irem
    //   3489: invokestatic abs : (I)I
    //   3492: invokevirtual charAt : (I)C
    //   3495: getstatic burp/Zg3m.Za : Ljava/lang/String;
    //   3498: getstatic burp/Zeju.Zk : Ljava/lang/Object;
    //   3501: checkcast java/math/BigInteger
    //   3504: invokevirtual intValue : ()I
    //   3507: bipush #32
    //   3509: irem
    //   3510: invokestatic abs : (I)I
    //   3513: invokevirtual charAt : (I)C
    //   3516: if_icmpgt -> 3578
    //   3519: goto -> 3526
    //   3522: invokestatic a : (Ljava/lang/Throwable;)Ljava/lang/Throwable;
    //   3525: athrow
    //   3526: getstatic burp/Zspk.ZA : Ljava/lang/String;
    //   3529: getstatic burp/Zmdm.ZZ : Ljava/lang/Object;
    //   3532: checkcast java/math/BigInteger
    //   3535: invokevirtual intValue : ()I
    //   3538: bipush #32
    //   3540: irem
    //   3541: invokestatic abs : (I)I
    //   3544: invokevirtual charAt : (I)C
    //   3547: getstatic burp/Zeju.ZR : Ljava/lang/String;
    //   3550: getstatic burp/Zrct.ZV : Ljava/lang/Object;
    //   3553: checkcast java/math/BigInteger
    //   3556: invokevirtual intValue : ()I
    //   3559: bipush #32
    //   3561: irem
    //   3562: invokestatic abs : (I)I
    //   3565: invokevirtual charAt : (I)C
    //   3568: if_icmpgt -> 3586
    //   3571: goto -> 3578
    //   3574: invokestatic a : (Ljava/lang/Throwable;)Ljava/lang/Throwable;
    //   3577: athrow
    //   3578: iconst_1
    //   3579: goto -> 3587
    //   3582: invokestatic a : (Ljava/lang/Throwable;)Ljava/lang/Throwable;
    //   3585: athrow
    //   3586: iconst_0
    //   3587: ireturn
    //   3588: astore_3
    //   3589: new java/lang/Exception
    //   3592: dup
    //   3593: aload_3
    //   3594: invokevirtual getMessage : ()Ljava/lang/String;
    //   3597: invokespecial <init> : (Ljava/lang/String;)V
    //   3600: athrow
    // Exception table:
    //   from	to	target	type
    //   4	3587	3588	java/lang/Throwable
    //   33	47	50	java/lang/Throwable
    //   40	61	64	java/lang/Throwable
    //   54	75	78	java/lang/Throwable
    //   68	89	92	java/lang/Throwable
    //   82	103	106	java/lang/Throwable
    //   96	117	120	java/lang/Throwable
    //   110	131	134	java/lang/Throwable
    //   124	145	148	java/lang/Throwable
    //   138	155	158	java/lang/Throwable
    //   194	208	211	java/lang/Throwable
    //   201	222	225	java/lang/Throwable
    //   215	236	239	java/lang/Throwable
    //   229	250	253	java/lang/Throwable
    //   243	264	267	java/lang/Throwable
    //   257	278	281	java/lang/Throwable
    //   271	292	295	java/lang/Throwable
    //   285	306	309	java/lang/Throwable
    //   299	323	326	java/lang/Throwable
    //   387	405	408	java/lang/Throwable
    //   396	421	424	java/lang/Throwable
    //   412	438	441	java/lang/Throwable
    //   428	454	457	java/lang/Throwable
    //   445	471	474	java/lang/Throwable
    //   461	487	490	java/lang/Throwable
    //   478	503	506	java/lang/Throwable
    //   494	526	529	java/lang/Throwable
    //   510	542	545	java/lang/Throwable
    //   533	558	561	java/lang/Throwable
    //   549	581	584	java/lang/Throwable
    //   565	597	600	java/lang/Throwable
    //   588	613	616	java/lang/Throwable
    //   604	632	635	java/lang/Throwable
    //   762	797	800	java/lang/Throwable
    //   804	845	848	java/lang/Throwable
    //   900	914	917	java/lang/Throwable
    //   907	928	931	java/lang/Throwable
    //   921	942	945	java/lang/Throwable
    //   935	956	959	java/lang/Throwable
    //   949	970	973	java/lang/Throwable
    //   963	984	987	java/lang/Throwable
    //   977	998	1001	java/lang/Throwable
    //   991	1012	1015	java/lang/Throwable
    //   1005	1022	1025	java/lang/Throwable
    //   1061	1075	1078	java/lang/Throwable
    //   1068	1089	1092	java/lang/Throwable
    //   1082	1103	1106	java/lang/Throwable
    //   1096	1117	1120	java/lang/Throwable
    //   1110	1131	1134	java/lang/Throwable
    //   1124	1145	1148	java/lang/Throwable
    //   1138	1159	1162	java/lang/Throwable
    //   1152	1173	1176	java/lang/Throwable
    //   1166	1190	1193	java/lang/Throwable
    //   1254	1272	1275	java/lang/Throwable
    //   1263	1288	1291	java/lang/Throwable
    //   1279	1305	1308	java/lang/Throwable
    //   1295	1321	1324	java/lang/Throwable
    //   1312	1338	1341	java/lang/Throwable
    //   1328	1354	1357	java/lang/Throwable
    //   1345	1370	1373	java/lang/Throwable
    //   1361	1393	1396	java/lang/Throwable
    //   1377	1409	1412	java/lang/Throwable
    //   1400	1425	1428	java/lang/Throwable
    //   1416	1448	1451	java/lang/Throwable
    //   1432	1464	1467	java/lang/Throwable
    //   1455	1480	1483	java/lang/Throwable
    //   1471	1499	1502	java/lang/Throwable
    //   1629	1664	1667	java/lang/Throwable
    //   1671	1712	1715	java/lang/Throwable
    //   1756	1930	1933	java/lang/Throwable
    //   1900	1967	1970	java/lang/Throwable
    //   1937	2004	2007	java/lang/Throwable
    //   1974	2041	2044	java/lang/Throwable
    //   2011	2078	2081	java/lang/Throwable
    //   2048	2115	2118	java/lang/Throwable
    //   2085	2152	2155	java/lang/Throwable
    //   2122	2189	2192	java/lang/Throwable
    //   2159	2226	2229	java/lang/Throwable
    //   2196	2263	2266	java/lang/Throwable
    //   2233	2300	2303	java/lang/Throwable
    //   2270	2337	2340	java/lang/Throwable
    //   2307	2374	2377	java/lang/Throwable
    //   2344	2411	2414	java/lang/Throwable
    //   2381	2448	2451	java/lang/Throwable
    //   2418	2485	2488	java/lang/Throwable
    //   2455	2522	2525	java/lang/Throwable
    //   2492	2559	2562	java/lang/Throwable
    //   2529	2596	2599	java/lang/Throwable
    //   2566	2633	2636	java/lang/Throwable
    //   2603	2670	2673	java/lang/Throwable
    //   2640	2707	2710	java/lang/Throwable
    //   2677	2744	2747	java/lang/Throwable
    //   2714	2781	2784	java/lang/Throwable
    //   2751	2818	2821	java/lang/Throwable
    //   2788	2855	2858	java/lang/Throwable
    //   2825	2892	2895	java/lang/Throwable
    //   2862	2929	2932	java/lang/Throwable
    //   2899	2966	2969	java/lang/Throwable
    //   2936	3003	3006	java/lang/Throwable
    //   2973	3040	3043	java/lang/Throwable
    //   3010	3073	3076	java/lang/Throwable
    //   3139	3153	3153	java/lang/Throwable
    //   3164	3177	3180	java/lang/Throwable
    //   3169	3192	3195	java/lang/Throwable
    //   3184	3210	3213	java/lang/Throwable
    //   3199	3240	3243	java/lang/Throwable
    //   3306	3333	3336	java/lang/Throwable
    //   3323	3354	3357	java/lang/Throwable
    //   3340	3384	3387	java/lang/Throwable
    //   3361	3395	3395	java/lang/Throwable
    //   3406	3422	3425	java/lang/Throwable
    //   3429	3519	3522	java/lang/Throwable
    //   3474	3571	3574	java/lang/Throwable
    //   3526	3582	3582	java/lang/Throwable
  }
  
  static void ZF(Object paramObject) {
    Zmh0.Zs = a(-26916, 17646);
    Zmh0.Zt = new BigInteger(a(-26928, 8504));
    boolean bool = Zt2e.ZN();
    try {
      try {
        if (Zg3m.Za.charAt(Math.abs(((BigInteger)Zrfh.ZJ).intValue() % 32)) <= Zmec.Zi.charAt(Math.abs(((BigInteger)Zenq.Zd).intValue() % 32))) {
          try {
            Zeqw.Zp(Class.forName(a(-26924, 28311)));
            if (!bool)
              Ze54.ZX(Class.forName(a(-26922, 15734))); 
          } catch (Throwable throwable) {
            throw a(null);
          } 
          return;
        } 
      } catch (Throwable throwable) {
        throw a(null);
      } 
      Ze54.ZX(Class.forName(a(-26922, 15734)));
    } catch (Throwable throwable) {}
  }
  
  static void ZI(Object[] paramArrayOfObject, Object paramObject) throws Throwable {}
  
  static {
    // Byte code:
    //   0: bipush #9
    //   2: anewarray java/lang/String
    //   5: astore #5
    //   7: iconst_0
    //   8: istore_3
    //   9: ldc '\\tQma\\t\\fU]%L+7,YAJJw=QWN$X&7e8KvU0pQ<$C\\nMK~`]mU4*Ppq/>p#\\t$O\\bV BNUe)}z} 2N_St\\bsx^sqa]T'
    //   11: dup
    //   12: astore_2
    //   13: invokevirtual length : ()I
    //   16: istore #4
    //   18: bipush #9
    //   20: istore_1
    //   21: iconst_m1
    //   22: istore_0
    //   23: bipush #105
    //   25: iinc #0, 1
    //   28: aload_2
    //   29: iload_0
    //   30: dup
    //   31: iload_1
    //   32: iadd
    //   33: invokevirtual substring : (II)Ljava/lang/String;
    //   36: iconst_m1
    //   37: goto -> 143
    //   40: aload #5
    //   42: swap
    //   43: iload_3
    //   44: iinc #3, 1
    //   47: swap
    //   48: aastore
    //   49: iload_0
    //   50: iload_1
    //   51: iadd
    //   52: dup
    //   53: istore_0
    //   54: iload #4
    //   56: if_icmpge -> 68
    //   59: aload_2
    //   60: iload_0
    //   61: invokevirtual charAt : (I)C
    //   64: istore_1
    //   65: goto -> 23
    //   68: ldc '`^\\b%o I\F4:^yvi8['
    //   70: dup
    //   71: astore_2
    //   72: invokevirtual length : ()I
    //   75: istore #4
    //   77: bipush #9
    //   79: istore_1
    //   80: iconst_m1
    //   81: istore_0
    //   82: bipush #54
    //   84: iinc #0, 1
    //   87: aload_2
    //   88: iload_0
    //   89: dup
    //   90: iload_1
    //   91: iadd
    //   92: invokevirtual substring : (II)Ljava/lang/String;
    //   95: iconst_0
    //   96: goto -> 143
    //   99: aload #5
    //   101: swap
    //   102: iload_3
    //   103: iinc #3, 1
    //   106: swap
    //   107: aastore
    //   108: iload_0
    //   109: iload_1
    //   110: iadd
    //   111: dup
    //   112: istore_0
    //   113: iload #4
    //   115: if_icmpge -> 127
    //   118: aload_2
    //   119: iload_0
    //   120: invokevirtual charAt : (I)C
    //   123: istore_1
    //   124: goto -> 82
    //   127: aload #5
    //   129: putstatic burp/Zsf4.a : [Ljava/lang/String;
    //   132: bipush #9
    //   134: anewarray java/lang/String
    //   137: putstatic burp/Zsf4.b : [Ljava/lang/String;
    //   140: goto -> 300
    //   143: dup_x2
    //   144: pop
    //   145: invokevirtual toCharArray : ()[C
    //   148: dup_x1
    //   149: arraylength
    //   150: dup_x2
    //   151: pop
    //   152: iconst_0
    //   153: istore #6
    //   155: dup2_x1
    //   156: pop2
    //   157: dup_x2
    //   158: iconst_1
    //   159: if_icmpgt -> 259
    //   162: dup2
    //   163: swap
    //   164: iload #6
    //   166: dup2_x1
    //   167: caload
    //   168: swap
    //   169: iload #6
    //   171: bipush #7
    //   173: irem
    //   174: tableswitch default -> 241, 0 -> 212, 1 -> 217, 2 -> 222, 3 -> 226, 4 -> 231, 5 -> 236
    //   212: bipush #109
    //   214: goto -> 243
    //   217: bipush #74
    //   219: goto -> 243
    //   222: iconst_5
    //   223: goto -> 243
    //   226: bipush #112
    //   228: goto -> 243
    //   231: bipush #102
    //   233: goto -> 243
    //   236: bipush #78
    //   238: goto -> 243
    //   241: bipush #104
    //   243: ixor
    //   244: ixor
    //   245: i2c
    //   246: castore
    //   247: iinc #6, 1
    //   250: dup
    //   251: ifne -> 259
    //   254: dup2
    //   255: dup_x1
    //   256: goto -> 166
    //   259: dup2_x1
    //   260: pop2
    //   261: dup_x2
    //   262: iload #6
    //   264: if_icmpgt -> 162
    //   267: pop
    //   268: new java/lang/String
    //   271: dup_x1
    //   272: swap
    //   273: invokespecial <init> : ([C)V
    //   276: invokevirtual intern : ()Ljava/lang/String;
    //   279: swap
    //   280: pop
    //   281: swap
    //   282: tableswitch default -> 40, 0 -> 99
    //   300: new java/math/BigInteger
    //   303: dup
    //   304: sipush #-26921
    //   307: sipush #2560
    //   310: invokestatic a : (II)Ljava/lang/String;
    //   313: invokespecial <init> : (Ljava/lang/String;)V
    //   316: putstatic burp/Zsf4.Zr : Ljava/lang/Object;
    //   319: sipush #-26926
    //   322: sipush #-15687
    //   325: invokestatic a : (II)Ljava/lang/String;
    //   328: putstatic burp/Zsf4.ZA : Ljava/lang/String;
    //   331: return
  }
  
  private static Throwable a(Throwable paramThrowable) {
    return paramThrowable;
  }
  
  private static String a(int paramInt1, int paramInt2) {
    int i = (paramInt1 ^ 0xFFFF96D4) & 0xFFFF;
    if (b[i] == null) {
      char[] arrayOfChar = a[i].toCharArray();
      switch (arrayOfChar[0] & 0xFF) {
        case 0:
        
        case 1:
        
        case 2:
        
        case 3:
        
        case 4:
        
        case 5:
        
        case 6:
        
        case 7:
        
        case 8:
        
        case 9:
        
        case 10:
        
        case 11:
        
        case 12:
        
        case 13:
        
        case 14:
        
        case 15:
        
        case 16:
        
        case 17:
        
        case 18:
        
        case 19:
        
        case 20:
        
        case 21:
        
        case 22:
        
        case 23:
        
        case 24:
        
        case 25:
        
        case 26:
        
        case 27:
        
        case 28:
        
        case 29:
        
        case 30:
        
        case 31:
        
        case 32:
        
        case 33:
        
        case 34:
        
        case 35:
        
        case 36:
        
        case 37:
        
        case 38:
        
        case 39:
        
        case 40:
        
        case 41:
        
        case 42:
        
        case 43:
        
        case 44:
        
        case 45:
        
        case 46:
        
        case 47:
        
        case 48:
        
        case 49:
        
        case 50:
        
        case 51:
        
        case 52:
        
        case 53:
        
        case 54:
        
        case 55:
        
        case 56:
        
        case 57:
        
        case 58:
        
        case 59:
        
        case 60:
        
        case 61:
        
        case 62:
        
        case 63:
        
        case 64:
        
        case 65:
        
        case 66:
        
        case 67:
        
        case 68:
        
        case 69:
        
        case 70:
        
        case 71:
        
        case 72:
        
        case 73:
        
        case 74:
        
        case 75:
        
        case 76:
        
        case 77:
        
        case 78:
        
        case 79:
        
        case 80:
        
        case 81:
        
        case 82:
        
        case 83:
        
        case 84:
        
        case 85:
        
        case 86:
        
        case 87:
        
        case 88:
        
        case 89:
        
        case 90:
        
        case 91:
        
        case 92:
        
        case 93:
        
        case 94:
        
        case 95:
        
        case 96:
        
        case 97:
        
        case 98:
        
        case 99:
        
        case 100:
        
        case 101:
        
        case 102:
        
        case 103:
        
        case 104:
        
        case 105:
        
        case 106:
        
        case 107:
        
        case 108:
        
        case 109:
        
        case 110:
        
        case 111:
        
        case 112:
        
        case 113:
        
        case 114:
        
        case 115:
        
        case 116:
        
        case 117:
        
        case 118:
        
        case 119:
        
        case 120:
        
        case 121:
        
        case 122:
        
        case 123:
        
        case 124:
        
        case 125:
        
        case 126:
        
        case 127:
        
        case 128:
        
        case 129:
        
        case 130:
        
        case 131:
        
        case 132:
        
        case 133:
        
        case 134:
        
        case 135:
        
        case 136:
        
        case 137:
        
        case 138:
        
        case 139:
        
        case 140:
        
        case 141:
        
        case 142:
        
        case 143:
        
        case 144:
        
        case 145:
        
        case 146:
        
        case 147:
        
        case 148:
        
        case 149:
        
        case 150:
        
        case 151:
        
        case 152:
        
        case 153:
        
        case 154:
        
        case 155:
        
        case 156:
        
        case 157:
        
        case 158:
        
        case 159:
        
        case 160:
        
        case 161:
        
        case 162:
        
        case 163:
        
        case 164:
        
        case 165:
        
        case 166:
        
        case 167:
        
        case 168:
        
        case 169:
        
        case 170:
        
        case 171:
        
        case 172:
        
        case 173:
        
        case 174:
        
        case 175:
        
        case 176:
        
        case 177:
        
        case 178:
        
        case 179:
        
        case 180:
        
        case 181:
        
        case 182:
        
        case 183:
        
        case 184:
        
        case 185:
        
        case 186:
        
        case 187:
        
        case 188:
        
        case 189:
        
        case 190:
        
        case 191:
        
        case 192:
        
        case 193:
        
        case 194:
        
        case 195:
        
        case 196:
        
        case 197:
        
        case 198:
        
        case 199:
        
        case 200:
        
        case 201:
        
        case 202:
        
        case 203:
        
        case 204:
        
        case 205:
        
        case 206:
        
        case 207:
        
        case 208:
        
        case 209:
        
        case 210:
        
        case 211:
        
        case 212:
        
        case 213:
        
        case 214:
        
        case 215:
        
        case 216:
        
        case 217:
        
        case 218:
        
        case 219:
        
        case 220:
        
        case 221:
        
        case 222:
        
        case 223:
        
        case 224:
        
        case 225:
        
        case 226:
        
        case 227:
        
        case 228:
        
        case 229:
        
        case 230:
        
        case 231:
        
        case 232:
        
        case 233:
        
        case 234:
        
        case 235:
        
        case 236:
        
        case 237:
        
        case 238:
        
        case 239:
        
        case 240:
        
        case 241:
        
        case 242:
        
        case 243:
        
        case 244:
        
        case 245:
        
        case 246:
        
        case 247:
        
        case 248:
        
        case 249:
        
        case 250:
        
        case 251:
        
        case 252:
        
        case 253:
        
        case 254:
        
        default:
          break;
      } 
      byte b1 = 40;
      int j = (paramInt2 & 0xFF) - b1;
      if (j < 0)
        j += 256; 
      int k = ((paramInt2 & 0xFFFF) >>> 8) - b1;
      if (k < 0)
        k += 256; 
      for (byte b2 = 0; b2 < arrayOfChar.length; b2++) {
        int m = b2 % 2;
        if (m == 0) {
          arrayOfChar[b2] = (char)(arrayOfChar[b2] ^ j);
          j = ((j >>> 3 | j << 5) ^ arrayOfChar[b2]) & 0xFF;
        } else {
          arrayOfChar[b2] = (char)(arrayOfChar[b2] ^ k);
          k = ((k >>> 3 | k << 5) ^ arrayOfChar[b2]) & 0xFF;
        } 
      } 
      b[i] = (new String(arrayOfChar)).intern();
    } 
    return b[i];
  }
}


/* Location:              C:\Program Files\BurpSuitePro\burpsuite_pro.jar!\burp\Zsf4.class
 * Java compiler version: 21 (65.0)
 * JD-Core Version:       1.1.3
 */