package burp;

import java.math.BigInteger;

class Zsgj extends ClassLoader {
  static Object ZK;
  
  static String ZN;
  
  private static final String[] a;
  
  private static final String[] b;
  
  static void Zd(Object[] paramArrayOfObject, Object paramObject) throws Throwable {}
  
  static void ZL(Object paramObject) {
    Zz0j.Zf = a(-30948, -5725);
    Zz0j.Zn = new BigInteger(a(-30951, -25121));
    boolean bool = Zt2e.ZN();
    try {
      try {
        if (Zkvr.Zm.charAt(Math.abs(((BigInteger)Zkul.Zb).intValue() % 32)) <= Zlno.ZM.charAt(Math.abs(((BigInteger)Zkul.Zb).intValue() % 32))) {
          try {
            Zead.ZW(Class.forName(a(-30952, -30139)));
            if (!bool)
              Ze3d.Zi(Class.forName(a(-30950, -15144))); 
          } catch (Throwable throwable) {
            throw a(null);
          } 
          return;
        } 
      } catch (Throwable throwable) {
        throw a(null);
      } 
      Ze3d.Zi(Class.forName(a(-30950, -15144)));
    } catch (Throwable throwable) {}
  }
  
  static boolean Zk(Object[] paramArrayOfObject, Object paramObject) throws Throwable {
    // Byte code:
    //   0: invokestatic ZK : ()Z
    //   3: istore_2
    //   4: sipush #-30949
    //   7: sipush #23696
    //   10: invokestatic a : (II)Ljava/lang/String;
    //   13: invokestatic forName : (Ljava/lang/String;)Ljava/lang/Class;
    //   16: invokestatic ZX : (Ljava/lang/Object;)V
    //   19: new java/lang/String
    //   22: dup
    //   23: aload_1
    //   24: checkcast [B
    //   27: invokespecial <init> : ([B)V
    //   30: putstatic burp/Zzip.Za : Ljava/lang/String;
    //   33: getstatic burp/Ztid.ZL : Ljava/lang/Object;
    //   36: checkcast java/math/BigInteger
    //   39: invokevirtual toByteArray : ()[B
    //   42: astore_3
    //   43: bipush #64
    //   45: newarray byte
    //   47: dup
    //   48: iconst_0
    //   49: bipush #-128
    //   51: bastore
    //   52: dup
    //   53: iconst_1
    //   54: iconst_0
    //   55: bastore
    //   56: dup
    //   57: iconst_2
    //   58: iconst_0
    //   59: bastore
    //   60: dup
    //   61: iconst_3
    //   62: iconst_0
    //   63: bastore
    //   64: dup
    //   65: iconst_4
    //   66: iconst_0
    //   67: bastore
    //   68: dup
    //   69: iconst_5
    //   70: iconst_0
    //   71: bastore
    //   72: dup
    //   73: bipush #6
    //   75: iconst_0
    //   76: bastore
    //   77: dup
    //   78: bipush #7
    //   80: iconst_0
    //   81: bastore
    //   82: dup
    //   83: bipush #8
    //   85: iconst_0
    //   86: bastore
    //   87: dup
    //   88: bipush #9
    //   90: iconst_0
    //   91: bastore
    //   92: dup
    //   93: bipush #10
    //   95: iconst_0
    //   96: bastore
    //   97: dup
    //   98: bipush #11
    //   100: iconst_0
    //   101: bastore
    //   102: dup
    //   103: bipush #12
    //   105: iconst_0
    //   106: bastore
    //   107: dup
    //   108: bipush #13
    //   110: iconst_0
    //   111: bastore
    //   112: dup
    //   113: bipush #14
    //   115: iconst_0
    //   116: bastore
    //   117: dup
    //   118: bipush #15
    //   120: iconst_0
    //   121: bastore
    //   122: dup
    //   123: bipush #16
    //   125: iconst_0
    //   126: bastore
    //   127: dup
    //   128: bipush #17
    //   130: iconst_0
    //   131: bastore
    //   132: dup
    //   133: bipush #18
    //   135: iconst_0
    //   136: bastore
    //   137: dup
    //   138: bipush #19
    //   140: iconst_0
    //   141: bastore
    //   142: dup
    //   143: bipush #20
    //   145: iconst_0
    //   146: bastore
    //   147: dup
    //   148: bipush #21
    //   150: iconst_0
    //   151: bastore
    //   152: dup
    //   153: bipush #22
    //   155: iconst_0
    //   156: bastore
    //   157: dup
    //   158: bipush #23
    //   160: iconst_0
    //   161: bastore
    //   162: dup
    //   163: bipush #24
    //   165: iconst_0
    //   166: bastore
    //   167: dup
    //   168: bipush #25
    //   170: iconst_0
    //   171: bastore
    //   172: dup
    //   173: bipush #26
    //   175: iconst_0
    //   176: bastore
    //   177: dup
    //   178: bipush #27
    //   180: iconst_0
    //   181: bastore
    //   182: dup
    //   183: bipush #28
    //   185: iconst_0
    //   186: bastore
    //   187: dup
    //   188: bipush #29
    //   190: iconst_0
    //   191: bastore
    //   192: dup
    //   193: bipush #30
    //   195: iconst_0
    //   196: bastore
    //   197: dup
    //   198: bipush #31
    //   200: iconst_0
    //   201: bastore
    //   202: dup
    //   203: bipush #32
    //   205: iconst_0
    //   206: bastore
    //   207: dup
    //   208: bipush #33
    //   210: iconst_0
    //   211: bastore
    //   212: dup
    //   213: bipush #34
    //   215: iconst_0
    //   216: bastore
    //   217: dup
    //   218: bipush #35
    //   220: iconst_0
    //   221: bastore
    //   222: dup
    //   223: bipush #36
    //   225: iconst_0
    //   226: bastore
    //   227: dup
    //   228: bipush #37
    //   230: iconst_0
    //   231: bastore
    //   232: dup
    //   233: bipush #38
    //   235: iconst_0
    //   236: bastore
    //   237: dup
    //   238: bipush #39
    //   240: iconst_0
    //   241: bastore
    //   242: dup
    //   243: bipush #40
    //   245: iconst_0
    //   246: bastore
    //   247: dup
    //   248: bipush #41
    //   250: iconst_0
    //   251: bastore
    //   252: dup
    //   253: bipush #42
    //   255: iconst_0
    //   256: bastore
    //   257: dup
    //   258: bipush #43
    //   260: iconst_0
    //   261: bastore
    //   262: dup
    //   263: bipush #44
    //   265: iconst_0
    //   266: bastore
    //   267: dup
    //   268: bipush #45
    //   270: iconst_0
    //   271: bastore
    //   272: dup
    //   273: bipush #46
    //   275: iconst_0
    //   276: bastore
    //   277: dup
    //   278: bipush #47
    //   280: iconst_0
    //   281: bastore
    //   282: dup
    //   283: bipush #48
    //   285: iconst_0
    //   286: bastore
    //   287: dup
    //   288: bipush #49
    //   290: iconst_0
    //   291: bastore
    //   292: dup
    //   293: bipush #50
    //   295: iconst_0
    //   296: bastore
    //   297: dup
    //   298: bipush #51
    //   300: iconst_0
    //   301: bastore
    //   302: dup
    //   303: bipush #52
    //   305: iconst_0
    //   306: bastore
    //   307: dup
    //   308: bipush #53
    //   310: iconst_0
    //   311: bastore
    //   312: dup
    //   313: bipush #54
    //   315: iconst_0
    //   316: bastore
    //   317: dup
    //   318: bipush #55
    //   320: iconst_0
    //   321: bastore
    //   322: dup
    //   323: bipush #56
    //   325: iconst_0
    //   326: bastore
    //   327: dup
    //   328: bipush #57
    //   330: iconst_0
    //   331: bastore
    //   332: dup
    //   333: bipush #58
    //   335: iconst_0
    //   336: bastore
    //   337: dup
    //   338: bipush #59
    //   340: iconst_0
    //   341: bastore
    //   342: dup
    //   343: bipush #60
    //   345: iconst_0
    //   346: bastore
    //   347: dup
    //   348: bipush #61
    //   350: iconst_0
    //   351: bastore
    //   352: dup
    //   353: bipush #62
    //   355: iconst_0
    //   356: bastore
    //   357: dup
    //   358: bipush #63
    //   360: iconst_0
    //   361: bastore
    //   362: astore #5
    //   364: bipush #64
    //   366: newarray int
    //   368: dup
    //   369: iconst_0
    //   370: ldc 1116352408
    //   372: iastore
    //   373: dup
    //   374: iconst_1
    //   375: ldc 1899447441
    //   377: iastore
    //   378: dup
    //   379: iconst_2
    //   380: ldc -1245643825
    //   382: iastore
    //   383: dup
    //   384: iconst_3
    //   385: ldc -373957723
    //   387: iastore
    //   388: dup
    //   389: iconst_4
    //   390: ldc 961987163
    //   392: iastore
    //   393: dup
    //   394: iconst_5
    //   395: ldc 1508970993
    //   397: iastore
    //   398: dup
    //   399: bipush #6
    //   401: ldc -1841331548
    //   403: iastore
    //   404: dup
    //   405: bipush #7
    //   407: ldc -1424204075
    //   409: iastore
    //   410: dup
    //   411: bipush #8
    //   413: ldc -670586216
    //   415: iastore
    //   416: dup
    //   417: bipush #9
    //   419: ldc 310598401
    //   421: iastore
    //   422: dup
    //   423: bipush #10
    //   425: ldc 607225278
    //   427: iastore
    //   428: dup
    //   429: bipush #11
    //   431: ldc 1426881987
    //   433: iastore
    //   434: dup
    //   435: bipush #12
    //   437: ldc 1925078388
    //   439: iastore
    //   440: dup
    //   441: bipush #13
    //   443: ldc -2132889090
    //   445: iastore
    //   446: dup
    //   447: bipush #14
    //   449: ldc -1680079193
    //   451: iastore
    //   452: dup
    //   453: bipush #15
    //   455: ldc -1046744716
    //   457: iastore
    //   458: dup
    //   459: bipush #16
    //   461: ldc -459576895
    //   463: iastore
    //   464: dup
    //   465: bipush #17
    //   467: ldc -272742522
    //   469: iastore
    //   470: dup
    //   471: bipush #18
    //   473: ldc 264347078
    //   475: iastore
    //   476: dup
    //   477: bipush #19
    //   479: ldc 604807628
    //   481: iastore
    //   482: dup
    //   483: bipush #20
    //   485: ldc 770255983
    //   487: iastore
    //   488: dup
    //   489: bipush #21
    //   491: ldc 1249150122
    //   493: iastore
    //   494: dup
    //   495: bipush #22
    //   497: ldc 1555081692
    //   499: iastore
    //   500: dup
    //   501: bipush #23
    //   503: ldc 1996064986
    //   505: iastore
    //   506: dup
    //   507: bipush #24
    //   509: ldc -1740746414
    //   511: iastore
    //   512: dup
    //   513: bipush #25
    //   515: ldc -1473132947
    //   517: iastore
    //   518: dup
    //   519: bipush #26
    //   521: ldc -1341970488
    //   523: iastore
    //   524: dup
    //   525: bipush #27
    //   527: ldc -1084653625
    //   529: iastore
    //   530: dup
    //   531: bipush #28
    //   533: ldc -958395405
    //   535: iastore
    //   536: dup
    //   537: bipush #29
    //   539: ldc -710438585
    //   541: iastore
    //   542: dup
    //   543: bipush #30
    //   545: ldc 113926993
    //   547: iastore
    //   548: dup
    //   549: bipush #31
    //   551: ldc 338241895
    //   553: iastore
    //   554: dup
    //   555: bipush #32
    //   557: ldc 666307205
    //   559: iastore
    //   560: dup
    //   561: bipush #33
    //   563: ldc 773529912
    //   565: iastore
    //   566: dup
    //   567: bipush #34
    //   569: ldc 1294757372
    //   571: iastore
    //   572: dup
    //   573: bipush #35
    //   575: ldc 1396182291
    //   577: iastore
    //   578: dup
    //   579: bipush #36
    //   581: ldc 1695183700
    //   583: iastore
    //   584: dup
    //   585: bipush #37
    //   587: ldc 1986661051
    //   589: iastore
    //   590: dup
    //   591: bipush #38
    //   593: ldc -2117940946
    //   595: iastore
    //   596: dup
    //   597: bipush #39
    //   599: ldc -1838011259
    //   601: iastore
    //   602: dup
    //   603: bipush #40
    //   605: ldc -1564481375
    //   607: iastore
    //   608: dup
    //   609: bipush #41
    //   611: ldc -1474664885
    //   613: iastore
    //   614: dup
    //   615: bipush #42
    //   617: ldc -1035236496
    //   619: iastore
    //   620: dup
    //   621: bipush #43
    //   623: ldc -949202525
    //   625: iastore
    //   626: dup
    //   627: bipush #44
    //   629: ldc -778901479
    //   631: iastore
    //   632: dup
    //   633: bipush #45
    //   635: ldc -694614492
    //   637: iastore
    //   638: dup
    //   639: bipush #46
    //   641: ldc -200395387
    //   643: iastore
    //   644: dup
    //   645: bipush #47
    //   647: ldc 275423344
    //   649: iastore
    //   650: dup
    //   651: bipush #48
    //   653: ldc 430227734
    //   655: iastore
    //   656: dup
    //   657: bipush #49
    //   659: ldc 506948616
    //   661: iastore
    //   662: dup
    //   663: bipush #50
    //   665: ldc 659060556
    //   667: iastore
    //   668: dup
    //   669: bipush #51
    //   671: ldc 883997877
    //   673: iastore
    //   674: dup
    //   675: bipush #52
    //   677: ldc 958139571
    //   679: iastore
    //   680: dup
    //   681: bipush #53
    //   683: ldc 1322822218
    //   685: iastore
    //   686: dup
    //   687: bipush #54
    //   689: ldc 1537002063
    //   691: iastore
    //   692: dup
    //   693: bipush #55
    //   695: ldc 1747873779
    //   697: iastore
    //   698: dup
    //   699: bipush #56
    //   701: ldc 1955562222
    //   703: iastore
    //   704: dup
    //   705: bipush #57
    //   707: ldc 2024104815
    //   709: iastore
    //   710: dup
    //   711: bipush #58
    //   713: ldc -2067236844
    //   715: iastore
    //   716: dup
    //   717: bipush #59
    //   719: ldc -1933114872
    //   721: iastore
    //   722: dup
    //   723: bipush #60
    //   725: ldc -1866530822
    //   727: iastore
    //   728: dup
    //   729: bipush #61
    //   731: ldc -1538233109
    //   733: iastore
    //   734: dup
    //   735: bipush #62
    //   737: ldc -1090935817
    //   739: iastore
    //   740: dup
    //   741: bipush #63
    //   743: ldc -965641998
    //   745: iastore
    //   746: astore #6
    //   748: iconst_2
    //   749: newarray int
    //   751: dup
    //   752: iconst_0
    //   753: iconst_0
    //   754: iastore
    //   755: dup
    //   756: iconst_1
    //   757: iconst_0
    //   758: iastore
    //   759: astore #7
    //   761: bipush #8
    //   763: newarray int
    //   765: dup
    //   766: iconst_0
    //   767: ldc 1779033703
    //   769: iastore
    //   770: dup
    //   771: iconst_1
    //   772: ldc -1150833019
    //   774: iastore
    //   775: dup
    //   776: iconst_2
    //   777: ldc 1013904242
    //   779: iastore
    //   780: dup
    //   781: iconst_3
    //   782: ldc -1521486534
    //   784: iastore
    //   785: dup
    //   786: iconst_4
    //   787: ldc 1359893119
    //   789: iastore
    //   790: dup
    //   791: iconst_5
    //   792: ldc -1694144372
    //   794: iastore
    //   795: dup
    //   796: bipush #6
    //   798: ldc 528734635
    //   800: iastore
    //   801: dup
    //   802: bipush #7
    //   804: ldc 1541459225
    //   806: iastore
    //   807: astore #8
    //   809: bipush #64
    //   811: newarray byte
    //   813: astore #9
    //   815: bipush #64
    //   817: newarray byte
    //   819: astore #10
    //   821: aload_3
    //   822: arraylength
    //   823: istore #11
    //   825: aload #7
    //   827: iconst_0
    //   828: iaload
    //   829: bipush #63
    //   831: iand
    //   832: istore #12
    //   834: aload #7
    //   836: iconst_0
    //   837: dup2
    //   838: iaload
    //   839: iload #11
    //   841: iadd
    //   842: iastore
    //   843: aload #7
    //   845: iconst_0
    //   846: dup2
    //   847: iaload
    //   848: iconst_m1
    //   849: iand
    //   850: iastore
    //   851: aload #7
    //   853: iconst_0
    //   854: iaload
    //   855: iload #11
    //   857: if_icmpge -> 875
    //   860: aload #7
    //   862: iconst_1
    //   863: dup2
    //   864: iaload
    //   865: iconst_1
    //   866: iadd
    //   867: iastore
    //   868: goto -> 875
    //   871: invokestatic a : (Ljava/lang/Throwable;)Ljava/lang/Throwable;
    //   874: athrow
    //   875: iconst_0
    //   876: istore #13
    //   878: iload #11
    //   880: bipush #64
    //   882: if_icmplt -> 1491
    //   885: iconst_0
    //   886: istore #14
    //   888: iload #14
    //   890: bipush #64
    //   892: if_icmpge -> 914
    //   895: aload #10
    //   897: iload #14
    //   899: aload_3
    //   900: iload #13
    //   902: iload #14
    //   904: iadd
    //   905: baload
    //   906: bastore
    //   907: iinc #14, 1
    //   910: iload_2
    //   911: ifeq -> 888
    //   914: bipush #64
    //   916: newarray int
    //   918: astore #14
    //   920: bipush #8
    //   922: newarray int
    //   924: astore #15
    //   926: iconst_0
    //   927: istore #16
    //   929: iload #16
    //   931: bipush #8
    //   933: if_icmpge -> 953
    //   936: aload #15
    //   938: iload #16
    //   940: aload #8
    //   942: iload #16
    //   944: iaload
    //   945: iastore
    //   946: iinc #16, 1
    //   949: iload_2
    //   950: ifeq -> 929
    //   953: iconst_0
    //   954: istore #16
    //   956: iload #16
    //   958: bipush #64
    //   960: if_icmpge -> 1451
    //   963: iload #16
    //   965: bipush #16
    //   967: if_icmpge -> 1048
    //   970: aload #14
    //   972: iload #16
    //   974: aload #10
    //   976: iconst_4
    //   977: iload #16
    //   979: imul
    //   980: baload
    //   981: sipush #255
    //   984: iand
    //   985: bipush #24
    //   987: ishl
    //   988: aload #10
    //   990: iconst_4
    //   991: iload #16
    //   993: imul
    //   994: iconst_1
    //   995: iadd
    //   996: baload
    //   997: sipush #255
    //   1000: iand
    //   1001: bipush #16
    //   1003: ishl
    //   1004: ior
    //   1005: aload #10
    //   1007: iconst_4
    //   1008: iload #16
    //   1010: imul
    //   1011: iconst_2
    //   1012: iadd
    //   1013: baload
    //   1014: sipush #255
    //   1017: iand
    //   1018: bipush #8
    //   1020: ishl
    //   1021: ior
    //   1022: aload #10
    //   1024: iconst_4
    //   1025: iload #16
    //   1027: imul
    //   1028: iconst_3
    //   1029: iadd
    //   1030: baload
    //   1031: sipush #255
    //   1034: iand
    //   1035: ior
    //   1036: iastore
    //   1037: iload_2
    //   1038: ifeq -> 1191
    //   1041: goto -> 1048
    //   1044: invokestatic a : (Ljava/lang/Throwable;)Ljava/lang/Throwable;
    //   1047: athrow
    //   1048: aload #14
    //   1050: iload #16
    //   1052: aload #14
    //   1054: iload #16
    //   1056: iconst_2
    //   1057: isub
    //   1058: iaload
    //   1059: bipush #17
    //   1061: iushr
    //   1062: aload #14
    //   1064: iload #16
    //   1066: iconst_2
    //   1067: isub
    //   1068: iaload
    //   1069: bipush #15
    //   1071: ishl
    //   1072: ior
    //   1073: aload #14
    //   1075: iload #16
    //   1077: iconst_2
    //   1078: isub
    //   1079: iaload
    //   1080: bipush #19
    //   1082: iushr
    //   1083: aload #14
    //   1085: iload #16
    //   1087: iconst_2
    //   1088: isub
    //   1089: iaload
    //   1090: bipush #13
    //   1092: ishl
    //   1093: ior
    //   1094: ixor
    //   1095: aload #14
    //   1097: iload #16
    //   1099: iconst_2
    //   1100: isub
    //   1101: iaload
    //   1102: bipush #10
    //   1104: iushr
    //   1105: ixor
    //   1106: aload #14
    //   1108: iload #16
    //   1110: bipush #7
    //   1112: isub
    //   1113: iaload
    //   1114: iadd
    //   1115: aload #14
    //   1117: iload #16
    //   1119: bipush #15
    //   1121: isub
    //   1122: iaload
    //   1123: bipush #7
    //   1125: iushr
    //   1126: aload #14
    //   1128: iload #16
    //   1130: bipush #15
    //   1132: isub
    //   1133: iaload
    //   1134: bipush #25
    //   1136: ishl
    //   1137: ior
    //   1138: aload #14
    //   1140: iload #16
    //   1142: bipush #15
    //   1144: isub
    //   1145: iaload
    //   1146: bipush #18
    //   1148: iushr
    //   1149: aload #14
    //   1151: iload #16
    //   1153: bipush #15
    //   1155: isub
    //   1156: iaload
    //   1157: bipush #14
    //   1159: ishl
    //   1160: ior
    //   1161: ixor
    //   1162: aload #14
    //   1164: iload #16
    //   1166: bipush #15
    //   1168: isub
    //   1169: iaload
    //   1170: iconst_3
    //   1171: iushr
    //   1172: ixor
    //   1173: iadd
    //   1174: aload #14
    //   1176: iload #16
    //   1178: bipush #16
    //   1180: isub
    //   1181: iaload
    //   1182: iadd
    //   1183: iastore
    //   1184: goto -> 1191
    //   1187: invokestatic a : (Ljava/lang/Throwable;)Ljava/lang/Throwable;
    //   1190: athrow
    //   1191: aload #15
    //   1193: bipush #7
    //   1195: iaload
    //   1196: aload #15
    //   1198: iconst_4
    //   1199: iaload
    //   1200: bipush #6
    //   1202: iushr
    //   1203: aload #15
    //   1205: iconst_4
    //   1206: iaload
    //   1207: bipush #26
    //   1209: ishl
    //   1210: ior
    //   1211: aload #15
    //   1213: iconst_4
    //   1214: iaload
    //   1215: bipush #11
    //   1217: iushr
    //   1218: aload #15
    //   1220: iconst_4
    //   1221: iaload
    //   1222: bipush #21
    //   1224: ishl
    //   1225: ior
    //   1226: ixor
    //   1227: aload #15
    //   1229: iconst_4
    //   1230: iaload
    //   1231: bipush #25
    //   1233: iushr
    //   1234: aload #15
    //   1236: iconst_4
    //   1237: iaload
    //   1238: bipush #7
    //   1240: ishl
    //   1241: ior
    //   1242: ixor
    //   1243: iadd
    //   1244: aload #15
    //   1246: bipush #6
    //   1248: iaload
    //   1249: aload #15
    //   1251: iconst_4
    //   1252: iaload
    //   1253: aload #15
    //   1255: iconst_5
    //   1256: iaload
    //   1257: aload #15
    //   1259: bipush #6
    //   1261: iaload
    //   1262: ixor
    //   1263: iand
    //   1264: ixor
    //   1265: iadd
    //   1266: aload #6
    //   1268: iload #16
    //   1270: iaload
    //   1271: iadd
    //   1272: aload #14
    //   1274: iload #16
    //   1276: iaload
    //   1277: iadd
    //   1278: istore #17
    //   1280: aload #15
    //   1282: iconst_0
    //   1283: iaload
    //   1284: iconst_2
    //   1285: iushr
    //   1286: aload #15
    //   1288: iconst_0
    //   1289: iaload
    //   1290: bipush #30
    //   1292: ishl
    //   1293: ior
    //   1294: aload #15
    //   1296: iconst_0
    //   1297: iaload
    //   1298: bipush #13
    //   1300: iushr
    //   1301: aload #15
    //   1303: iconst_0
    //   1304: iaload
    //   1305: bipush #19
    //   1307: ishl
    //   1308: ior
    //   1309: ixor
    //   1310: aload #15
    //   1312: iconst_0
    //   1313: iaload
    //   1314: bipush #22
    //   1316: iushr
    //   1317: aload #15
    //   1319: iconst_0
    //   1320: iaload
    //   1321: bipush #10
    //   1323: ishl
    //   1324: ior
    //   1325: ixor
    //   1326: aload #15
    //   1328: iconst_0
    //   1329: iaload
    //   1330: aload #15
    //   1332: iconst_1
    //   1333: iaload
    //   1334: iand
    //   1335: aload #15
    //   1337: iconst_2
    //   1338: iaload
    //   1339: aload #15
    //   1341: iconst_0
    //   1342: iaload
    //   1343: aload #15
    //   1345: iconst_1
    //   1346: iaload
    //   1347: ior
    //   1348: iand
    //   1349: ior
    //   1350: iadd
    //   1351: istore #18
    //   1353: aload #15
    //   1355: iconst_3
    //   1356: dup2
    //   1357: iaload
    //   1358: iload #17
    //   1360: iadd
    //   1361: iastore
    //   1362: aload #15
    //   1364: bipush #7
    //   1366: iload #17
    //   1368: iload #18
    //   1370: iadd
    //   1371: iastore
    //   1372: aload #15
    //   1374: bipush #7
    //   1376: iaload
    //   1377: istore #17
    //   1379: aload #15
    //   1381: bipush #7
    //   1383: aload #15
    //   1385: bipush #6
    //   1387: iaload
    //   1388: iastore
    //   1389: aload #15
    //   1391: bipush #6
    //   1393: aload #15
    //   1395: iconst_5
    //   1396: iaload
    //   1397: iastore
    //   1398: aload #15
    //   1400: iconst_5
    //   1401: aload #15
    //   1403: iconst_4
    //   1404: iaload
    //   1405: iastore
    //   1406: aload #15
    //   1408: iconst_4
    //   1409: aload #15
    //   1411: iconst_3
    //   1412: iaload
    //   1413: iastore
    //   1414: aload #15
    //   1416: iconst_3
    //   1417: aload #15
    //   1419: iconst_2
    //   1420: iaload
    //   1421: iastore
    //   1422: aload #15
    //   1424: iconst_2
    //   1425: aload #15
    //   1427: iconst_1
    //   1428: iaload
    //   1429: iastore
    //   1430: aload #15
    //   1432: iconst_1
    //   1433: aload #15
    //   1435: iconst_0
    //   1436: iaload
    //   1437: iastore
    //   1438: aload #15
    //   1440: iconst_0
    //   1441: iload #17
    //   1443: iastore
    //   1444: iinc #16, 1
    //   1447: iload_2
    //   1448: ifeq -> 956
    //   1451: iconst_0
    //   1452: istore #16
    //   1454: iload #16
    //   1456: bipush #8
    //   1458: if_icmpge -> 1481
    //   1461: aload #8
    //   1463: iload #16
    //   1465: dup2
    //   1466: iaload
    //   1467: aload #15
    //   1469: iload #16
    //   1471: iaload
    //   1472: iadd
    //   1473: iastore
    //   1474: iinc #16, 1
    //   1477: iload_2
    //   1478: ifeq -> 1454
    //   1481: iinc #13, 64
    //   1484: iinc #11, -64
    //   1487: iload_2
    //   1488: ifeq -> 878
    //   1491: iload #11
    //   1493: ifle -> 1528
    //   1496: iconst_0
    //   1497: istore #14
    //   1499: iload #14
    //   1501: iload #11
    //   1503: if_icmpge -> 1528
    //   1506: aload #9
    //   1508: iload #12
    //   1510: iload #14
    //   1512: iadd
    //   1513: aload_3
    //   1514: iload #13
    //   1516: iload #14
    //   1518: iadd
    //   1519: baload
    //   1520: bastore
    //   1521: iinc #14, 1
    //   1524: iload_2
    //   1525: ifeq -> 1499
    //   1528: aload #7
    //   1530: iconst_0
    //   1531: iaload
    //   1532: bipush #29
    //   1534: iushr
    //   1535: aload #7
    //   1537: iconst_1
    //   1538: iaload
    //   1539: iconst_3
    //   1540: ishl
    //   1541: ior
    //   1542: istore #14
    //   1544: aload #7
    //   1546: iconst_0
    //   1547: iaload
    //   1548: iconst_3
    //   1549: ishl
    //   1550: istore #15
    //   1552: aload #7
    //   1554: iconst_0
    //   1555: iaload
    //   1556: bipush #63
    //   1558: iand
    //   1559: istore #16
    //   1561: iload #16
    //   1563: bipush #56
    //   1565: if_icmpge -> 1580
    //   1568: bipush #56
    //   1570: iload #16
    //   1572: isub
    //   1573: goto -> 1585
    //   1576: invokestatic a : (Ljava/lang/Throwable;)Ljava/lang/Throwable;
    //   1579: athrow
    //   1580: bipush #120
    //   1582: iload #16
    //   1584: isub
    //   1585: istore #17
    //   1587: aload #7
    //   1589: iconst_0
    //   1590: iaload
    //   1591: bipush #63
    //   1593: iand
    //   1594: istore #12
    //   1596: bipush #64
    //   1598: iload #12
    //   1600: isub
    //   1601: istore #18
    //   1603: aload #7
    //   1605: iconst_0
    //   1606: dup2
    //   1607: iaload
    //   1608: iload #17
    //   1610: iadd
    //   1611: iastore
    //   1612: aload #7
    //   1614: iconst_0
    //   1615: dup2
    //   1616: iaload
    //   1617: iconst_m1
    //   1618: iand
    //   1619: iastore
    //   1620: aload #7
    //   1622: iconst_0
    //   1623: iaload
    //   1624: iload #17
    //   1626: if_icmpge -> 1644
    //   1629: aload #7
    //   1631: iconst_1
    //   1632: dup2
    //   1633: iaload
    //   1634: iconst_1
    //   1635: iadd
    //   1636: iastore
    //   1637: goto -> 1644
    //   1640: invokestatic a : (Ljava/lang/Throwable;)Ljava/lang/Throwable;
    //   1643: athrow
    //   1644: iconst_0
    //   1645: istore #13
    //   1647: iload #12
    //   1649: ifle -> 2280
    //   1652: iload #17
    //   1654: iload #18
    //   1656: if_icmplt -> 2280
    //   1659: goto -> 1666
    //   1662: invokestatic a : (Ljava/lang/Throwable;)Ljava/lang/Throwable;
    //   1665: athrow
    //   1666: iconst_0
    //   1667: istore #19
    //   1669: iload #19
    //   1671: iload #18
    //   1673: if_icmpge -> 1696
    //   1676: aload #9
    //   1678: iload #12
    //   1680: iload #19
    //   1682: iadd
    //   1683: aload #5
    //   1685: iload #19
    //   1687: baload
    //   1688: bastore
    //   1689: iinc #19, 1
    //   1692: iload_2
    //   1693: ifeq -> 1669
    //   1696: bipush #64
    //   1698: newarray int
    //   1700: astore #19
    //   1702: bipush #8
    //   1704: newarray int
    //   1706: astore #20
    //   1708: iconst_0
    //   1709: istore #21
    //   1711: iload #21
    //   1713: bipush #8
    //   1715: if_icmpge -> 1735
    //   1718: aload #20
    //   1720: iload #21
    //   1722: aload #8
    //   1724: iload #21
    //   1726: iaload
    //   1727: iastore
    //   1728: iinc #21, 1
    //   1731: iload_2
    //   1732: ifeq -> 1711
    //   1735: iconst_0
    //   1736: istore #21
    //   1738: iload #21
    //   1740: bipush #64
    //   1742: if_icmpge -> 2233
    //   1745: iload #21
    //   1747: bipush #16
    //   1749: if_icmpge -> 1830
    //   1752: aload #19
    //   1754: iload #21
    //   1756: aload #9
    //   1758: iconst_4
    //   1759: iload #21
    //   1761: imul
    //   1762: baload
    //   1763: sipush #255
    //   1766: iand
    //   1767: bipush #24
    //   1769: ishl
    //   1770: aload #9
    //   1772: iconst_4
    //   1773: iload #21
    //   1775: imul
    //   1776: iconst_1
    //   1777: iadd
    //   1778: baload
    //   1779: sipush #255
    //   1782: iand
    //   1783: bipush #16
    //   1785: ishl
    //   1786: ior
    //   1787: aload #9
    //   1789: iconst_4
    //   1790: iload #21
    //   1792: imul
    //   1793: iconst_2
    //   1794: iadd
    //   1795: baload
    //   1796: sipush #255
    //   1799: iand
    //   1800: bipush #8
    //   1802: ishl
    //   1803: ior
    //   1804: aload #9
    //   1806: iconst_4
    //   1807: iload #21
    //   1809: imul
    //   1810: iconst_3
    //   1811: iadd
    //   1812: baload
    //   1813: sipush #255
    //   1816: iand
    //   1817: ior
    //   1818: iastore
    //   1819: iload_2
    //   1820: ifeq -> 1973
    //   1823: goto -> 1830
    //   1826: invokestatic a : (Ljava/lang/Throwable;)Ljava/lang/Throwable;
    //   1829: athrow
    //   1830: aload #19
    //   1832: iload #21
    //   1834: aload #19
    //   1836: iload #21
    //   1838: iconst_2
    //   1839: isub
    //   1840: iaload
    //   1841: bipush #17
    //   1843: iushr
    //   1844: aload #19
    //   1846: iload #21
    //   1848: iconst_2
    //   1849: isub
    //   1850: iaload
    //   1851: bipush #15
    //   1853: ishl
    //   1854: ior
    //   1855: aload #19
    //   1857: iload #21
    //   1859: iconst_2
    //   1860: isub
    //   1861: iaload
    //   1862: bipush #19
    //   1864: iushr
    //   1865: aload #19
    //   1867: iload #21
    //   1869: iconst_2
    //   1870: isub
    //   1871: iaload
    //   1872: bipush #13
    //   1874: ishl
    //   1875: ior
    //   1876: ixor
    //   1877: aload #19
    //   1879: iload #21
    //   1881: iconst_2
    //   1882: isub
    //   1883: iaload
    //   1884: bipush #10
    //   1886: iushr
    //   1887: ixor
    //   1888: aload #19
    //   1890: iload #21
    //   1892: bipush #7
    //   1894: isub
    //   1895: iaload
    //   1896: iadd
    //   1897: aload #19
    //   1899: iload #21
    //   1901: bipush #15
    //   1903: isub
    //   1904: iaload
    //   1905: bipush #7
    //   1907: iushr
    //   1908: aload #19
    //   1910: iload #21
    //   1912: bipush #15
    //   1914: isub
    //   1915: iaload
    //   1916: bipush #25
    //   1918: ishl
    //   1919: ior
    //   1920: aload #19
    //   1922: iload #21
    //   1924: bipush #15
    //   1926: isub
    //   1927: iaload
    //   1928: bipush #18
    //   1930: iushr
    //   1931: aload #19
    //   1933: iload #21
    //   1935: bipush #15
    //   1937: isub
    //   1938: iaload
    //   1939: bipush #14
    //   1941: ishl
    //   1942: ior
    //   1943: ixor
    //   1944: aload #19
    //   1946: iload #21
    //   1948: bipush #15
    //   1950: isub
    //   1951: iaload
    //   1952: iconst_3
    //   1953: iushr
    //   1954: ixor
    //   1955: iadd
    //   1956: aload #19
    //   1958: iload #21
    //   1960: bipush #16
    //   1962: isub
    //   1963: iaload
    //   1964: iadd
    //   1965: iastore
    //   1966: goto -> 1973
    //   1969: invokestatic a : (Ljava/lang/Throwable;)Ljava/lang/Throwable;
    //   1972: athrow
    //   1973: aload #20
    //   1975: bipush #7
    //   1977: iaload
    //   1978: aload #20
    //   1980: iconst_4
    //   1981: iaload
    //   1982: bipush #6
    //   1984: iushr
    //   1985: aload #20
    //   1987: iconst_4
    //   1988: iaload
    //   1989: bipush #26
    //   1991: ishl
    //   1992: ior
    //   1993: aload #20
    //   1995: iconst_4
    //   1996: iaload
    //   1997: bipush #11
    //   1999: iushr
    //   2000: aload #20
    //   2002: iconst_4
    //   2003: iaload
    //   2004: bipush #21
    //   2006: ishl
    //   2007: ior
    //   2008: ixor
    //   2009: aload #20
    //   2011: iconst_4
    //   2012: iaload
    //   2013: bipush #25
    //   2015: iushr
    //   2016: aload #20
    //   2018: iconst_4
    //   2019: iaload
    //   2020: bipush #7
    //   2022: ishl
    //   2023: ior
    //   2024: ixor
    //   2025: iadd
    //   2026: aload #20
    //   2028: bipush #6
    //   2030: iaload
    //   2031: aload #20
    //   2033: iconst_4
    //   2034: iaload
    //   2035: aload #20
    //   2037: iconst_5
    //   2038: iaload
    //   2039: aload #20
    //   2041: bipush #6
    //   2043: iaload
    //   2044: ixor
    //   2045: iand
    //   2046: ixor
    //   2047: iadd
    //   2048: aload #6
    //   2050: iload #21
    //   2052: iaload
    //   2053: iadd
    //   2054: aload #19
    //   2056: iload #21
    //   2058: iaload
    //   2059: iadd
    //   2060: istore #22
    //   2062: aload #20
    //   2064: iconst_0
    //   2065: iaload
    //   2066: iconst_2
    //   2067: iushr
    //   2068: aload #20
    //   2070: iconst_0
    //   2071: iaload
    //   2072: bipush #30
    //   2074: ishl
    //   2075: ior
    //   2076: aload #20
    //   2078: iconst_0
    //   2079: iaload
    //   2080: bipush #13
    //   2082: iushr
    //   2083: aload #20
    //   2085: iconst_0
    //   2086: iaload
    //   2087: bipush #19
    //   2089: ishl
    //   2090: ior
    //   2091: ixor
    //   2092: aload #20
    //   2094: iconst_0
    //   2095: iaload
    //   2096: bipush #22
    //   2098: iushr
    //   2099: aload #20
    //   2101: iconst_0
    //   2102: iaload
    //   2103: bipush #10
    //   2105: ishl
    //   2106: ior
    //   2107: ixor
    //   2108: aload #20
    //   2110: iconst_0
    //   2111: iaload
    //   2112: aload #20
    //   2114: iconst_1
    //   2115: iaload
    //   2116: iand
    //   2117: aload #20
    //   2119: iconst_2
    //   2120: iaload
    //   2121: aload #20
    //   2123: iconst_0
    //   2124: iaload
    //   2125: aload #20
    //   2127: iconst_1
    //   2128: iaload
    //   2129: ior
    //   2130: iand
    //   2131: ior
    //   2132: iadd
    //   2133: istore #23
    //   2135: aload #20
    //   2137: iconst_3
    //   2138: dup2
    //   2139: iaload
    //   2140: iload #22
    //   2142: iadd
    //   2143: iastore
    //   2144: aload #20
    //   2146: bipush #7
    //   2148: iload #22
    //   2150: iload #23
    //   2152: iadd
    //   2153: iastore
    //   2154: aload #20
    //   2156: bipush #7
    //   2158: iaload
    //   2159: istore #22
    //   2161: aload #20
    //   2163: bipush #7
    //   2165: aload #20
    //   2167: bipush #6
    //   2169: iaload
    //   2170: iastore
    //   2171: aload #20
    //   2173: bipush #6
    //   2175: aload #20
    //   2177: iconst_5
    //   2178: iaload
    //   2179: iastore
    //   2180: aload #20
    //   2182: iconst_5
    //   2183: aload #20
    //   2185: iconst_4
    //   2186: iaload
    //   2187: iastore
    //   2188: aload #20
    //   2190: iconst_4
    //   2191: aload #20
    //   2193: iconst_3
    //   2194: iaload
    //   2195: iastore
    //   2196: aload #20
    //   2198: iconst_3
    //   2199: aload #20
    //   2201: iconst_2
    //   2202: iaload
    //   2203: iastore
    //   2204: aload #20
    //   2206: iconst_2
    //   2207: aload #20
    //   2209: iconst_1
    //   2210: iaload
    //   2211: iastore
    //   2212: aload #20
    //   2214: iconst_1
    //   2215: aload #20
    //   2217: iconst_0
    //   2218: iaload
    //   2219: iastore
    //   2220: aload #20
    //   2222: iconst_0
    //   2223: iload #22
    //   2225: iastore
    //   2226: iinc #21, 1
    //   2229: iload_2
    //   2230: ifeq -> 1738
    //   2233: iconst_0
    //   2234: istore #21
    //   2236: iload #21
    //   2238: bipush #8
    //   2240: if_icmpge -> 2263
    //   2243: aload #8
    //   2245: iload #21
    //   2247: dup2
    //   2248: iaload
    //   2249: aload #20
    //   2251: iload #21
    //   2253: iaload
    //   2254: iadd
    //   2255: iastore
    //   2256: iinc #21, 1
    //   2259: iload_2
    //   2260: ifeq -> 2236
    //   2263: iload #13
    //   2265: iload #18
    //   2267: iadd
    //   2268: istore #13
    //   2270: iload #17
    //   2272: iload #18
    //   2274: isub
    //   2275: istore #17
    //   2277: iconst_0
    //   2278: istore #12
    //   2280: iload #17
    //   2282: bipush #64
    //   2284: if_icmplt -> 2894
    //   2287: iconst_0
    //   2288: istore #19
    //   2290: iload #19
    //   2292: bipush #64
    //   2294: if_icmpge -> 2317
    //   2297: aload #10
    //   2299: iload #19
    //   2301: aload #5
    //   2303: iload #13
    //   2305: iload #19
    //   2307: iadd
    //   2308: baload
    //   2309: bastore
    //   2310: iinc #19, 1
    //   2313: iload_2
    //   2314: ifeq -> 2290
    //   2317: bipush #64
    //   2319: newarray int
    //   2321: astore #19
    //   2323: bipush #8
    //   2325: newarray int
    //   2327: astore #20
    //   2329: iconst_0
    //   2330: istore #21
    //   2332: iload #21
    //   2334: bipush #8
    //   2336: if_icmpge -> 2356
    //   2339: aload #20
    //   2341: iload #21
    //   2343: aload #8
    //   2345: iload #21
    //   2347: iaload
    //   2348: iastore
    //   2349: iinc #21, 1
    //   2352: iload_2
    //   2353: ifeq -> 2332
    //   2356: iconst_0
    //   2357: istore #21
    //   2359: iload #21
    //   2361: bipush #64
    //   2363: if_icmpge -> 2854
    //   2366: iload #21
    //   2368: bipush #16
    //   2370: if_icmpge -> 2451
    //   2373: aload #19
    //   2375: iload #21
    //   2377: aload #10
    //   2379: iconst_4
    //   2380: iload #21
    //   2382: imul
    //   2383: baload
    //   2384: sipush #255
    //   2387: iand
    //   2388: bipush #24
    //   2390: ishl
    //   2391: aload #10
    //   2393: iconst_4
    //   2394: iload #21
    //   2396: imul
    //   2397: iconst_1
    //   2398: iadd
    //   2399: baload
    //   2400: sipush #255
    //   2403: iand
    //   2404: bipush #16
    //   2406: ishl
    //   2407: ior
    //   2408: aload #10
    //   2410: iconst_4
    //   2411: iload #21
    //   2413: imul
    //   2414: iconst_2
    //   2415: iadd
    //   2416: baload
    //   2417: sipush #255
    //   2420: iand
    //   2421: bipush #8
    //   2423: ishl
    //   2424: ior
    //   2425: aload #10
    //   2427: iconst_4
    //   2428: iload #21
    //   2430: imul
    //   2431: iconst_3
    //   2432: iadd
    //   2433: baload
    //   2434: sipush #255
    //   2437: iand
    //   2438: ior
    //   2439: iastore
    //   2440: iload_2
    //   2441: ifeq -> 2594
    //   2444: goto -> 2451
    //   2447: invokestatic a : (Ljava/lang/Throwable;)Ljava/lang/Throwable;
    //   2450: athrow
    //   2451: aload #19
    //   2453: iload #21
    //   2455: aload #19
    //   2457: iload #21
    //   2459: iconst_2
    //   2460: isub
    //   2461: iaload
    //   2462: bipush #17
    //   2464: iushr
    //   2465: aload #19
    //   2467: iload #21
    //   2469: iconst_2
    //   2470: isub
    //   2471: iaload
    //   2472: bipush #15
    //   2474: ishl
    //   2475: ior
    //   2476: aload #19
    //   2478: iload #21
    //   2480: iconst_2
    //   2481: isub
    //   2482: iaload
    //   2483: bipush #19
    //   2485: iushr
    //   2486: aload #19
    //   2488: iload #21
    //   2490: iconst_2
    //   2491: isub
    //   2492: iaload
    //   2493: bipush #13
    //   2495: ishl
    //   2496: ior
    //   2497: ixor
    //   2498: aload #19
    //   2500: iload #21
    //   2502: iconst_2
    //   2503: isub
    //   2504: iaload
    //   2505: bipush #10
    //   2507: iushr
    //   2508: ixor
    //   2509: aload #19
    //   2511: iload #21
    //   2513: bipush #7
    //   2515: isub
    //   2516: iaload
    //   2517: iadd
    //   2518: aload #19
    //   2520: iload #21
    //   2522: bipush #15
    //   2524: isub
    //   2525: iaload
    //   2526: bipush #7
    //   2528: iushr
    //   2529: aload #19
    //   2531: iload #21
    //   2533: bipush #15
    //   2535: isub
    //   2536: iaload
    //   2537: bipush #25
    //   2539: ishl
    //   2540: ior
    //   2541: aload #19
    //   2543: iload #21
    //   2545: bipush #15
    //   2547: isub
    //   2548: iaload
    //   2549: bipush #18
    //   2551: iushr
    //   2552: aload #19
    //   2554: iload #21
    //   2556: bipush #15
    //   2558: isub
    //   2559: iaload
    //   2560: bipush #14
    //   2562: ishl
    //   2563: ior
    //   2564: ixor
    //   2565: aload #19
    //   2567: iload #21
    //   2569: bipush #15
    //   2571: isub
    //   2572: iaload
    //   2573: iconst_3
    //   2574: iushr
    //   2575: ixor
    //   2576: iadd
    //   2577: aload #19
    //   2579: iload #21
    //   2581: bipush #16
    //   2583: isub
    //   2584: iaload
    //   2585: iadd
    //   2586: iastore
    //   2587: goto -> 2594
    //   2590: invokestatic a : (Ljava/lang/Throwable;)Ljava/lang/Throwable;
    //   2593: athrow
    //   2594: aload #20
    //   2596: bipush #7
    //   2598: iaload
    //   2599: aload #20
    //   2601: iconst_4
    //   2602: iaload
    //   2603: bipush #6
    //   2605: iushr
    //   2606: aload #20
    //   2608: iconst_4
    //   2609: iaload
    //   2610: bipush #26
    //   2612: ishl
    //   2613: ior
    //   2614: aload #20
    //   2616: iconst_4
    //   2617: iaload
    //   2618: bipush #11
    //   2620: iushr
    //   2621: aload #20
    //   2623: iconst_4
    //   2624: iaload
    //   2625: bipush #21
    //   2627: ishl
    //   2628: ior
    //   2629: ixor
    //   2630: aload #20
    //   2632: iconst_4
    //   2633: iaload
    //   2634: bipush #25
    //   2636: iushr
    //   2637: aload #20
    //   2639: iconst_4
    //   2640: iaload
    //   2641: bipush #7
    //   2643: ishl
    //   2644: ior
    //   2645: ixor
    //   2646: iadd
    //   2647: aload #20
    //   2649: bipush #6
    //   2651: iaload
    //   2652: aload #20
    //   2654: iconst_4
    //   2655: iaload
    //   2656: aload #20
    //   2658: iconst_5
    //   2659: iaload
    //   2660: aload #20
    //   2662: bipush #6
    //   2664: iaload
    //   2665: ixor
    //   2666: iand
    //   2667: ixor
    //   2668: iadd
    //   2669: aload #6
    //   2671: iload #21
    //   2673: iaload
    //   2674: iadd
    //   2675: aload #19
    //   2677: iload #21
    //   2679: iaload
    //   2680: iadd
    //   2681: istore #22
    //   2683: aload #20
    //   2685: iconst_0
    //   2686: iaload
    //   2687: iconst_2
    //   2688: iushr
    //   2689: aload #20
    //   2691: iconst_0
    //   2692: iaload
    //   2693: bipush #30
    //   2695: ishl
    //   2696: ior
    //   2697: aload #20
    //   2699: iconst_0
    //   2700: iaload
    //   2701: bipush #13
    //   2703: iushr
    //   2704: aload #20
    //   2706: iconst_0
    //   2707: iaload
    //   2708: bipush #19
    //   2710: ishl
    //   2711: ior
    //   2712: ixor
    //   2713: aload #20
    //   2715: iconst_0
    //   2716: iaload
    //   2717: bipush #22
    //   2719: iushr
    //   2720: aload #20
    //   2722: iconst_0
    //   2723: iaload
    //   2724: bipush #10
    //   2726: ishl
    //   2727: ior
    //   2728: ixor
    //   2729: aload #20
    //   2731: iconst_0
    //   2732: iaload
    //   2733: aload #20
    //   2735: iconst_1
    //   2736: iaload
    //   2737: iand
    //   2738: aload #20
    //   2740: iconst_2
    //   2741: iaload
    //   2742: aload #20
    //   2744: iconst_0
    //   2745: iaload
    //   2746: aload #20
    //   2748: iconst_1
    //   2749: iaload
    //   2750: ior
    //   2751: iand
    //   2752: ior
    //   2753: iadd
    //   2754: istore #23
    //   2756: aload #20
    //   2758: iconst_3
    //   2759: dup2
    //   2760: iaload
    //   2761: iload #22
    //   2763: iadd
    //   2764: iastore
    //   2765: aload #20
    //   2767: bipush #7
    //   2769: iload #22
    //   2771: iload #23
    //   2773: iadd
    //   2774: iastore
    //   2775: aload #20
    //   2777: bipush #7
    //   2779: iaload
    //   2780: istore #22
    //   2782: aload #20
    //   2784: bipush #7
    //   2786: aload #20
    //   2788: bipush #6
    //   2790: iaload
    //   2791: iastore
    //   2792: aload #20
    //   2794: bipush #6
    //   2796: aload #20
    //   2798: iconst_5
    //   2799: iaload
    //   2800: iastore
    //   2801: aload #20
    //   2803: iconst_5
    //   2804: aload #20
    //   2806: iconst_4
    //   2807: iaload
    //   2808: iastore
    //   2809: aload #20
    //   2811: iconst_4
    //   2812: aload #20
    //   2814: iconst_3
    //   2815: iaload
    //   2816: iastore
    //   2817: aload #20
    //   2819: iconst_3
    //   2820: aload #20
    //   2822: iconst_2
    //   2823: iaload
    //   2824: iastore
    //   2825: aload #20
    //   2827: iconst_2
    //   2828: aload #20
    //   2830: iconst_1
    //   2831: iaload
    //   2832: iastore
    //   2833: aload #20
    //   2835: iconst_1
    //   2836: aload #20
    //   2838: iconst_0
    //   2839: iaload
    //   2840: iastore
    //   2841: aload #20
    //   2843: iconst_0
    //   2844: iload #22
    //   2846: iastore
    //   2847: iinc #21, 1
    //   2850: iload_2
    //   2851: ifeq -> 2359
    //   2854: iconst_0
    //   2855: istore #21
    //   2857: iload #21
    //   2859: bipush #8
    //   2861: if_icmpge -> 2884
    //   2864: aload #8
    //   2866: iload #21
    //   2868: dup2
    //   2869: iaload
    //   2870: aload #20
    //   2872: iload #21
    //   2874: iaload
    //   2875: iadd
    //   2876: iastore
    //   2877: iinc #21, 1
    //   2880: iload_2
    //   2881: ifeq -> 2857
    //   2884: iinc #13, 64
    //   2887: iinc #17, -64
    //   2890: iload_2
    //   2891: ifeq -> 2280
    //   2894: iload #17
    //   2896: ifle -> 2932
    //   2899: iconst_0
    //   2900: istore #19
    //   2902: iload #19
    //   2904: iload #17
    //   2906: if_icmpge -> 2932
    //   2909: aload #9
    //   2911: iload #12
    //   2913: iload #19
    //   2915: iadd
    //   2916: aload #5
    //   2918: iload #13
    //   2920: iload #19
    //   2922: iadd
    //   2923: baload
    //   2924: bastore
    //   2925: iinc #19, 1
    //   2928: iload_2
    //   2929: ifeq -> 2902
    //   2932: bipush #8
    //   2934: newarray byte
    //   2936: astore #19
    //   2938: aload #19
    //   2940: iconst_0
    //   2941: iload #14
    //   2943: bipush #24
    //   2945: iushr
    //   2946: i2b
    //   2947: bastore
    //   2948: aload #19
    //   2950: iconst_1
    //   2951: iload #14
    //   2953: bipush #16
    //   2955: iushr
    //   2956: i2b
    //   2957: bastore
    //   2958: aload #19
    //   2960: iconst_2
    //   2961: iload #14
    //   2963: bipush #8
    //   2965: iushr
    //   2966: i2b
    //   2967: bastore
    //   2968: aload #19
    //   2970: iconst_3
    //   2971: iload #14
    //   2973: i2b
    //   2974: bastore
    //   2975: aload #19
    //   2977: iconst_4
    //   2978: iload #15
    //   2980: bipush #24
    //   2982: iushr
    //   2983: i2b
    //   2984: bastore
    //   2985: aload #19
    //   2987: iconst_5
    //   2988: iload #15
    //   2990: bipush #16
    //   2992: iushr
    //   2993: i2b
    //   2994: bastore
    //   2995: aload #19
    //   2997: bipush #6
    //   2999: iload #15
    //   3001: bipush #8
    //   3003: iushr
    //   3004: i2b
    //   3005: bastore
    //   3006: aload #19
    //   3008: bipush #7
    //   3010: iload #15
    //   3012: i2b
    //   3013: bastore
    //   3014: bipush #8
    //   3016: istore #11
    //   3018: aload #7
    //   3020: iconst_0
    //   3021: iaload
    //   3022: bipush #63
    //   3024: iand
    //   3025: istore #12
    //   3027: bipush #64
    //   3029: iload #12
    //   3031: isub
    //   3032: istore #18
    //   3034: aload #7
    //   3036: iconst_0
    //   3037: dup2
    //   3038: iaload
    //   3039: iload #11
    //   3041: iadd
    //   3042: iastore
    //   3043: aload #7
    //   3045: iconst_0
    //   3046: dup2
    //   3047: iaload
    //   3048: iconst_m1
    //   3049: iand
    //   3050: iastore
    //   3051: aload #7
    //   3053: iconst_0
    //   3054: iaload
    //   3055: iload #11
    //   3057: if_icmpge -> 3075
    //   3060: aload #7
    //   3062: iconst_1
    //   3063: dup2
    //   3064: iaload
    //   3065: iconst_1
    //   3066: iadd
    //   3067: iastore
    //   3068: goto -> 3075
    //   3071: invokestatic a : (Ljava/lang/Throwable;)Ljava/lang/Throwable;
    //   3074: athrow
    //   3075: iload #12
    //   3077: ifle -> 3691
    //   3080: iload #11
    //   3082: iload #18
    //   3084: if_icmplt -> 3691
    //   3087: goto -> 3094
    //   3090: invokestatic a : (Ljava/lang/Throwable;)Ljava/lang/Throwable;
    //   3093: athrow
    //   3094: iconst_0
    //   3095: istore #20
    //   3097: iload #20
    //   3099: iload #18
    //   3101: if_icmpge -> 3124
    //   3104: aload #9
    //   3106: iload #12
    //   3108: iload #20
    //   3110: iadd
    //   3111: aload #19
    //   3113: iload #20
    //   3115: baload
    //   3116: bastore
    //   3117: iinc #20, 1
    //   3120: iload_2
    //   3121: ifeq -> 3097
    //   3124: bipush #64
    //   3126: newarray int
    //   3128: astore #20
    //   3130: bipush #8
    //   3132: newarray int
    //   3134: astore #21
    //   3136: iconst_0
    //   3137: istore #22
    //   3139: iload #22
    //   3141: bipush #8
    //   3143: if_icmpge -> 3163
    //   3146: aload #21
    //   3148: iload #22
    //   3150: aload #8
    //   3152: iload #22
    //   3154: iaload
    //   3155: iastore
    //   3156: iinc #22, 1
    //   3159: iload_2
    //   3160: ifeq -> 3139
    //   3163: iconst_0
    //   3164: istore #22
    //   3166: iload #22
    //   3168: bipush #64
    //   3170: if_icmpge -> 3661
    //   3173: iload #22
    //   3175: bipush #16
    //   3177: if_icmpge -> 3258
    //   3180: aload #20
    //   3182: iload #22
    //   3184: aload #9
    //   3186: iconst_4
    //   3187: iload #22
    //   3189: imul
    //   3190: baload
    //   3191: sipush #255
    //   3194: iand
    //   3195: bipush #24
    //   3197: ishl
    //   3198: aload #9
    //   3200: iconst_4
    //   3201: iload #22
    //   3203: imul
    //   3204: iconst_1
    //   3205: iadd
    //   3206: baload
    //   3207: sipush #255
    //   3210: iand
    //   3211: bipush #16
    //   3213: ishl
    //   3214: ior
    //   3215: aload #9
    //   3217: iconst_4
    //   3218: iload #22
    //   3220: imul
    //   3221: iconst_2
    //   3222: iadd
    //   3223: baload
    //   3224: sipush #255
    //   3227: iand
    //   3228: bipush #8
    //   3230: ishl
    //   3231: ior
    //   3232: aload #9
    //   3234: iconst_4
    //   3235: iload #22
    //   3237: imul
    //   3238: iconst_3
    //   3239: iadd
    //   3240: baload
    //   3241: sipush #255
    //   3244: iand
    //   3245: ior
    //   3246: iastore
    //   3247: iload_2
    //   3248: ifeq -> 3401
    //   3251: goto -> 3258
    //   3254: invokestatic a : (Ljava/lang/Throwable;)Ljava/lang/Throwable;
    //   3257: athrow
    //   3258: aload #20
    //   3260: iload #22
    //   3262: aload #20
    //   3264: iload #22
    //   3266: iconst_2
    //   3267: isub
    //   3268: iaload
    //   3269: bipush #17
    //   3271: iushr
    //   3272: aload #20
    //   3274: iload #22
    //   3276: iconst_2
    //   3277: isub
    //   3278: iaload
    //   3279: bipush #15
    //   3281: ishl
    //   3282: ior
    //   3283: aload #20
    //   3285: iload #22
    //   3287: iconst_2
    //   3288: isub
    //   3289: iaload
    //   3290: bipush #19
    //   3292: iushr
    //   3293: aload #20
    //   3295: iload #22
    //   3297: iconst_2
    //   3298: isub
    //   3299: iaload
    //   3300: bipush #13
    //   3302: ishl
    //   3303: ior
    //   3304: ixor
    //   3305: aload #20
    //   3307: iload #22
    //   3309: iconst_2
    //   3310: isub
    //   3311: iaload
    //   3312: bipush #10
    //   3314: iushr
    //   3315: ixor
    //   3316: aload #20
    //   3318: iload #22
    //   3320: bipush #7
    //   3322: isub
    //   3323: iaload
    //   3324: iadd
    //   3325: aload #20
    //   3327: iload #22
    //   3329: bipush #15
    //   3331: isub
    //   3332: iaload
    //   3333: bipush #7
    //   3335: iushr
    //   3336: aload #20
    //   3338: iload #22
    //   3340: bipush #15
    //   3342: isub
    //   3343: iaload
    //   3344: bipush #25
    //   3346: ishl
    //   3347: ior
    //   3348: aload #20
    //   3350: iload #22
    //   3352: bipush #15
    //   3354: isub
    //   3355: iaload
    //   3356: bipush #18
    //   3358: iushr
    //   3359: aload #20
    //   3361: iload #22
    //   3363: bipush #15
    //   3365: isub
    //   3366: iaload
    //   3367: bipush #14
    //   3369: ishl
    //   3370: ior
    //   3371: ixor
    //   3372: aload #20
    //   3374: iload #22
    //   3376: bipush #15
    //   3378: isub
    //   3379: iaload
    //   3380: iconst_3
    //   3381: iushr
    //   3382: ixor
    //   3383: iadd
    //   3384: aload #20
    //   3386: iload #22
    //   3388: bipush #16
    //   3390: isub
    //   3391: iaload
    //   3392: iadd
    //   3393: iastore
    //   3394: goto -> 3401
    //   3397: invokestatic a : (Ljava/lang/Throwable;)Ljava/lang/Throwable;
    //   3400: athrow
    //   3401: aload #21
    //   3403: bipush #7
    //   3405: iaload
    //   3406: aload #21
    //   3408: iconst_4
    //   3409: iaload
    //   3410: bipush #6
    //   3412: iushr
    //   3413: aload #21
    //   3415: iconst_4
    //   3416: iaload
    //   3417: bipush #26
    //   3419: ishl
    //   3420: ior
    //   3421: aload #21
    //   3423: iconst_4
    //   3424: iaload
    //   3425: bipush #11
    //   3427: iushr
    //   3428: aload #21
    //   3430: iconst_4
    //   3431: iaload
    //   3432: bipush #21
    //   3434: ishl
    //   3435: ior
    //   3436: ixor
    //   3437: aload #21
    //   3439: iconst_4
    //   3440: iaload
    //   3441: bipush #25
    //   3443: iushr
    //   3444: aload #21
    //   3446: iconst_4
    //   3447: iaload
    //   3448: bipush #7
    //   3450: ishl
    //   3451: ior
    //   3452: ixor
    //   3453: iadd
    //   3454: aload #21
    //   3456: bipush #6
    //   3458: iaload
    //   3459: aload #21
    //   3461: iconst_4
    //   3462: iaload
    //   3463: aload #21
    //   3465: iconst_5
    //   3466: iaload
    //   3467: aload #21
    //   3469: bipush #6
    //   3471: iaload
    //   3472: ixor
    //   3473: iand
    //   3474: ixor
    //   3475: iadd
    //   3476: aload #6
    //   3478: iload #22
    //   3480: iaload
    //   3481: iadd
    //   3482: aload #20
    //   3484: iload #22
    //   3486: iaload
    //   3487: iadd
    //   3488: istore #23
    //   3490: aload #21
    //   3492: iconst_0
    //   3493: iaload
    //   3494: iconst_2
    //   3495: iushr
    //   3496: aload #21
    //   3498: iconst_0
    //   3499: iaload
    //   3500: bipush #30
    //   3502: ishl
    //   3503: ior
    //   3504: aload #21
    //   3506: iconst_0
    //   3507: iaload
    //   3508: bipush #13
    //   3510: iushr
    //   3511: aload #21
    //   3513: iconst_0
    //   3514: iaload
    //   3515: bipush #19
    //   3517: ishl
    //   3518: ior
    //   3519: ixor
    //   3520: aload #21
    //   3522: iconst_0
    //   3523: iaload
    //   3524: bipush #22
    //   3526: iushr
    //   3527: aload #21
    //   3529: iconst_0
    //   3530: iaload
    //   3531: bipush #10
    //   3533: ishl
    //   3534: ior
    //   3535: ixor
    //   3536: aload #21
    //   3538: iconst_0
    //   3539: iaload
    //   3540: aload #21
    //   3542: iconst_1
    //   3543: iaload
    //   3544: iand
    //   3545: aload #21
    //   3547: iconst_2
    //   3548: iaload
    //   3549: aload #21
    //   3551: iconst_0
    //   3552: iaload
    //   3553: aload #21
    //   3555: iconst_1
    //   3556: iaload
    //   3557: ior
    //   3558: iand
    //   3559: ior
    //   3560: iadd
    //   3561: istore #24
    //   3563: aload #21
    //   3565: iconst_3
    //   3566: dup2
    //   3567: iaload
    //   3568: iload #23
    //   3570: iadd
    //   3571: iastore
    //   3572: aload #21
    //   3574: bipush #7
    //   3576: iload #23
    //   3578: iload #24
    //   3580: iadd
    //   3581: iastore
    //   3582: aload #21
    //   3584: bipush #7
    //   3586: iaload
    //   3587: istore #23
    //   3589: aload #21
    //   3591: bipush #7
    //   3593: aload #21
    //   3595: bipush #6
    //   3597: iaload
    //   3598: iastore
    //   3599: aload #21
    //   3601: bipush #6
    //   3603: aload #21
    //   3605: iconst_5
    //   3606: iaload
    //   3607: iastore
    //   3608: aload #21
    //   3610: iconst_5
    //   3611: aload #21
    //   3613: iconst_4
    //   3614: iaload
    //   3615: iastore
    //   3616: aload #21
    //   3618: iconst_4
    //   3619: aload #21
    //   3621: iconst_3
    //   3622: iaload
    //   3623: iastore
    //   3624: aload #21
    //   3626: iconst_3
    //   3627: aload #21
    //   3629: iconst_2
    //   3630: iaload
    //   3631: iastore
    //   3632: aload #21
    //   3634: iconst_2
    //   3635: aload #21
    //   3637: iconst_1
    //   3638: iaload
    //   3639: iastore
    //   3640: aload #21
    //   3642: iconst_1
    //   3643: aload #21
    //   3645: iconst_0
    //   3646: iaload
    //   3647: iastore
    //   3648: aload #21
    //   3650: iconst_0
    //   3651: iload #23
    //   3653: iastore
    //   3654: iinc #22, 1
    //   3657: iload_2
    //   3658: ifeq -> 3166
    //   3661: iconst_0
    //   3662: istore #22
    //   3664: iload #22
    //   3666: bipush #8
    //   3668: if_icmpge -> 3691
    //   3671: aload #8
    //   3673: iload #22
    //   3675: dup2
    //   3676: iaload
    //   3677: aload #21
    //   3679: iload #22
    //   3681: iaload
    //   3682: iadd
    //   3683: iastore
    //   3684: iinc #22, 1
    //   3687: iload_2
    //   3688: ifeq -> 3664
    //   3691: bipush #32
    //   3693: newarray byte
    //   3695: astore #4
    //   3697: aload #4
    //   3699: iconst_0
    //   3700: aload #8
    //   3702: iconst_0
    //   3703: iaload
    //   3704: bipush #24
    //   3706: iushr
    //   3707: i2b
    //   3708: bastore
    //   3709: aload #4
    //   3711: iconst_1
    //   3712: aload #8
    //   3714: iconst_0
    //   3715: iaload
    //   3716: bipush #16
    //   3718: iushr
    //   3719: i2b
    //   3720: bastore
    //   3721: aload #4
    //   3723: iconst_2
    //   3724: aload #8
    //   3726: iconst_0
    //   3727: iaload
    //   3728: bipush #8
    //   3730: iushr
    //   3731: i2b
    //   3732: bastore
    //   3733: aload #4
    //   3735: iconst_3
    //   3736: aload #8
    //   3738: iconst_0
    //   3739: iaload
    //   3740: i2b
    //   3741: bastore
    //   3742: aload #4
    //   3744: iconst_4
    //   3745: aload #8
    //   3747: iconst_1
    //   3748: iaload
    //   3749: bipush #24
    //   3751: iushr
    //   3752: i2b
    //   3753: bastore
    //   3754: aload #4
    //   3756: iconst_5
    //   3757: aload #8
    //   3759: iconst_1
    //   3760: iaload
    //   3761: bipush #16
    //   3763: iushr
    //   3764: i2b
    //   3765: bastore
    //   3766: aload #4
    //   3768: bipush #6
    //   3770: aload #8
    //   3772: iconst_1
    //   3773: iaload
    //   3774: bipush #8
    //   3776: iushr
    //   3777: i2b
    //   3778: bastore
    //   3779: aload #4
    //   3781: bipush #7
    //   3783: aload #8
    //   3785: iconst_1
    //   3786: iaload
    //   3787: i2b
    //   3788: bastore
    //   3789: aload #4
    //   3791: bipush #8
    //   3793: aload #8
    //   3795: iconst_2
    //   3796: iaload
    //   3797: bipush #24
    //   3799: iushr
    //   3800: i2b
    //   3801: bastore
    //   3802: aload #4
    //   3804: bipush #9
    //   3806: aload #8
    //   3808: iconst_2
    //   3809: iaload
    //   3810: bipush #16
    //   3812: iushr
    //   3813: i2b
    //   3814: bastore
    //   3815: aload #4
    //   3817: bipush #10
    //   3819: aload #8
    //   3821: iconst_2
    //   3822: iaload
    //   3823: bipush #8
    //   3825: iushr
    //   3826: i2b
    //   3827: bastore
    //   3828: aload #4
    //   3830: bipush #11
    //   3832: aload #8
    //   3834: iconst_2
    //   3835: iaload
    //   3836: i2b
    //   3837: bastore
    //   3838: aload #4
    //   3840: bipush #12
    //   3842: aload #8
    //   3844: iconst_3
    //   3845: iaload
    //   3846: bipush #24
    //   3848: iushr
    //   3849: i2b
    //   3850: bastore
    //   3851: aload #4
    //   3853: bipush #13
    //   3855: aload #8
    //   3857: iconst_3
    //   3858: iaload
    //   3859: bipush #16
    //   3861: iushr
    //   3862: i2b
    //   3863: bastore
    //   3864: aload #4
    //   3866: bipush #14
    //   3868: aload #8
    //   3870: iconst_3
    //   3871: iaload
    //   3872: bipush #8
    //   3874: iushr
    //   3875: i2b
    //   3876: bastore
    //   3877: aload #4
    //   3879: bipush #15
    //   3881: aload #8
    //   3883: iconst_3
    //   3884: iaload
    //   3885: i2b
    //   3886: bastore
    //   3887: aload #4
    //   3889: bipush #16
    //   3891: aload #8
    //   3893: iconst_4
    //   3894: iaload
    //   3895: bipush #24
    //   3897: iushr
    //   3898: i2b
    //   3899: bastore
    //   3900: aload #4
    //   3902: bipush #17
    //   3904: aload #8
    //   3906: iconst_4
    //   3907: iaload
    //   3908: bipush #16
    //   3910: iushr
    //   3911: i2b
    //   3912: bastore
    //   3913: aload #4
    //   3915: bipush #18
    //   3917: aload #8
    //   3919: iconst_4
    //   3920: iaload
    //   3921: bipush #8
    //   3923: iushr
    //   3924: i2b
    //   3925: bastore
    //   3926: aload #4
    //   3928: bipush #19
    //   3930: aload #8
    //   3932: iconst_4
    //   3933: iaload
    //   3934: i2b
    //   3935: bastore
    //   3936: aload #4
    //   3938: bipush #20
    //   3940: aload #8
    //   3942: iconst_5
    //   3943: iaload
    //   3944: bipush #24
    //   3946: iushr
    //   3947: i2b
    //   3948: bastore
    //   3949: aload #4
    //   3951: bipush #21
    //   3953: aload #8
    //   3955: iconst_5
    //   3956: iaload
    //   3957: bipush #16
    //   3959: iushr
    //   3960: i2b
    //   3961: bastore
    //   3962: aload #4
    //   3964: bipush #22
    //   3966: aload #8
    //   3968: iconst_5
    //   3969: iaload
    //   3970: bipush #8
    //   3972: iushr
    //   3973: i2b
    //   3974: bastore
    //   3975: aload #4
    //   3977: bipush #23
    //   3979: aload #8
    //   3981: iconst_5
    //   3982: iaload
    //   3983: i2b
    //   3984: bastore
    //   3985: aload #4
    //   3987: bipush #24
    //   3989: aload #8
    //   3991: bipush #6
    //   3993: iaload
    //   3994: bipush #24
    //   3996: iushr
    //   3997: i2b
    //   3998: bastore
    //   3999: aload #4
    //   4001: bipush #25
    //   4003: aload #8
    //   4005: bipush #6
    //   4007: iaload
    //   4008: bipush #16
    //   4010: iushr
    //   4011: i2b
    //   4012: bastore
    //   4013: aload #4
    //   4015: bipush #26
    //   4017: aload #8
    //   4019: bipush #6
    //   4021: iaload
    //   4022: bipush #8
    //   4024: iushr
    //   4025: i2b
    //   4026: bastore
    //   4027: aload #4
    //   4029: bipush #27
    //   4031: aload #8
    //   4033: bipush #6
    //   4035: iaload
    //   4036: i2b
    //   4037: bastore
    //   4038: aload #4
    //   4040: bipush #28
    //   4042: aload #8
    //   4044: bipush #7
    //   4046: iaload
    //   4047: bipush #24
    //   4049: iushr
    //   4050: i2b
    //   4051: bastore
    //   4052: aload #4
    //   4054: bipush #29
    //   4056: aload #8
    //   4058: bipush #7
    //   4060: iaload
    //   4061: bipush #16
    //   4063: iushr
    //   4064: i2b
    //   4065: bastore
    //   4066: aload #4
    //   4068: bipush #30
    //   4070: aload #8
    //   4072: bipush #7
    //   4074: iaload
    //   4075: bipush #8
    //   4077: iushr
    //   4078: i2b
    //   4079: bastore
    //   4080: aload #4
    //   4082: bipush #31
    //   4084: aload #8
    //   4086: bipush #7
    //   4088: iaload
    //   4089: i2b
    //   4090: bastore
    //   4091: new java/math/BigInteger
    //   4094: dup
    //   4095: aload #4
    //   4097: invokespecial <init> : ([B)V
    //   4100: invokevirtual abs : ()Ljava/math/BigInteger;
    //   4103: putstatic burp/Zko9.ZC : Ljava/lang/Object;
    //   4106: getstatic burp/Zz0j.Zn : Ljava/lang/Object;
    //   4109: checkcast java/math/BigInteger
    //   4112: invokevirtual toByteArray : ()[B
    //   4115: astore_3
    //   4116: bipush #32
    //   4118: newarray int
    //   4120: dup
    //   4121: iconst_0
    //   4122: ldc 943331329
    //   4124: iastore
    //   4125: dup
    //   4126: iconst_1
    //   4127: ldc 170788368
    //   4129: iastore
    //   4130: dup
    //   4131: iconst_2
    //   4132: ldc 1008414755
    //   4134: iastore
    //   4135: dup
    //   4136: iconst_3
    //   4137: ldc 187049985
    //   4139: iastore
    //   4140: dup
    //   4141: iconst_4
    //   4142: ldc 1010368540
    //   4144: iastore
    //   4145: dup
    //   4146: iconst_5
    //   4147: ldc 220604441
    //   4149: iastore
    //   4150: dup
    //   4151: bipush #6
    //   4153: ldc 940377620
    //   4155: iastore
    //   4156: dup
    //   4157: bipush #7
    //   4159: ldc 255209728
    //   4161: iastore
    //   4162: dup
    //   4163: bipush #8
    //   4165: ldc 689771012
    //   4167: iastore
    //   4168: dup
    //   4169: bipush #9
    //   4171: ldc 221709344
    //   4173: iastore
    //   4174: dup
    //   4175: bipush #10
    //   4177: ldc 957157408
    //   4179: iastore
    //   4180: dup
    //   4181: bipush #11
    //   4183: ldc 892536332
    //   4185: iastore
    //   4186: dup
    //   4187: bipush #12
    //   4189: ldc 722417666
    //   4191: iastore
    //   4192: dup
    //   4193: bipush #13
    //   4195: ldc 1026621720
    //   4197: iastore
    //   4198: dup
    //   4199: bipush #14
    //   4201: ldc 655302664
    //   4203: iastore
    //   4204: dup
    //   4205: bipush #15
    //   4207: ldc 890966315
    //   4209: iastore
    //   4210: dup
    //   4211: bipush #16
    //   4213: ldc 187632156
    //   4215: iastore
    //   4216: dup
    //   4217: bipush #17
    //   4219: ldc 874189824
    //   4221: iastore
    //   4222: dup
    //   4223: bipush #18
    //   4225: ldc 254150144
    //   4227: iastore
    //   4228: dup
    //   4229: bipush #19
    //   4231: ldc 924386310
    //   4233: iastore
    //   4234: dup
    //   4235: bipush #20
    //   4237: ldc 121057538
    //   4239: iastore
    //   4240: dup
    //   4241: bipush #21
    //   4243: ldc 840500228
    //   4245: iastore
    //   4246: dup
    //   4247: bipush #22
    //   4249: ldc 389160971
    //   4251: iastore
    //   4252: dup
    //   4253: bipush #23
    //   4255: ldc 907870729
    //   4257: iastore
    //   4258: dup
    //   4259: bipush #24
    //   4261: ldc 389426184
    //   4263: iastore
    //   4264: dup
    //   4265: bipush #25
    //   4267: ldc 973875457
    //   4269: iastore
    //   4270: dup
    //   4271: bipush #26
    //   4273: ldc 372376604
    //   4275: iastore
    //   4276: dup
    //   4277: bipush #27
    //   4279: ldc 707731490
    //   4281: iastore
    //   4282: dup
    //   4283: bipush #28
    //   4285: ldc 1043334948
    //   4287: iastore
    //   4288: dup
    //   4289: bipush #29
    //   4291: ldc 439222784
    //   4293: iastore
    //   4294: dup
    //   4295: bipush #30
    //   4297: ldc 876216579
    //   4299: iastore
    //   4300: dup
    //   4301: bipush #31
    //   4303: ldc 455999525
    //   4305: iastore
    //   4306: astore #5
    //   4308: bipush #8
    //   4310: aload_3
    //   4311: arraylength
    //   4312: bipush #8
    //   4314: irem
    //   4315: isub
    //   4316: istore #6
    //   4318: aload_3
    //   4319: arraylength
    //   4320: iload #6
    //   4322: iadd
    //   4323: newarray byte
    //   4325: astore #7
    //   4327: iconst_0
    //   4328: istore #8
    //   4330: iload #8
    //   4332: aload_3
    //   4333: arraylength
    //   4334: if_icmpge -> 4353
    //   4337: aload #7
    //   4339: iload #8
    //   4341: aload_3
    //   4342: iload #8
    //   4344: baload
    //   4345: bastore
    //   4346: iinc #8, 1
    //   4349: iload_2
    //   4350: ifeq -> 4330
    //   4353: aload_3
    //   4354: arraylength
    //   4355: istore #8
    //   4357: iload #8
    //   4359: aload #7
    //   4361: arraylength
    //   4362: if_icmpge -> 4380
    //   4365: aload #7
    //   4367: iload #8
    //   4369: iload #6
    //   4371: i2b
    //   4372: bastore
    //   4373: iinc #8, 1
    //   4376: iload_2
    //   4377: ifeq -> 4357
    //   4380: aload #7
    //   4382: astore_3
    //   4383: bipush #64
    //   4385: newarray int
    //   4387: dup
    //   4388: iconst_0
    //   4389: ldc 16843776
    //   4391: iastore
    //   4392: dup
    //   4393: iconst_1
    //   4394: iconst_0
    //   4395: iastore
    //   4396: dup
    //   4397: iconst_2
    //   4398: ldc 65536
    //   4400: iastore
    //   4401: dup
    //   4402: iconst_3
    //   4403: ldc 16843780
    //   4405: iastore
    //   4406: dup
    //   4407: iconst_4
    //   4408: ldc 16842756
    //   4410: iastore
    //   4411: dup
    //   4412: iconst_5
    //   4413: ldc 66564
    //   4415: iastore
    //   4416: dup
    //   4417: bipush #6
    //   4419: iconst_4
    //   4420: iastore
    //   4421: dup
    //   4422: bipush #7
    //   4424: ldc 65536
    //   4426: iastore
    //   4427: dup
    //   4428: bipush #8
    //   4430: sipush #1024
    //   4433: iastore
    //   4434: dup
    //   4435: bipush #9
    //   4437: ldc 16843776
    //   4439: iastore
    //   4440: dup
    //   4441: bipush #10
    //   4443: ldc 16843780
    //   4445: iastore
    //   4446: dup
    //   4447: bipush #11
    //   4449: sipush #1024
    //   4452: iastore
    //   4453: dup
    //   4454: bipush #12
    //   4456: ldc 16778244
    //   4458: iastore
    //   4459: dup
    //   4460: bipush #13
    //   4462: ldc 16842756
    //   4464: iastore
    //   4465: dup
    //   4466: bipush #14
    //   4468: ldc 16777216
    //   4470: iastore
    //   4471: dup
    //   4472: bipush #15
    //   4474: iconst_4
    //   4475: iastore
    //   4476: dup
    //   4477: bipush #16
    //   4479: sipush #1028
    //   4482: iastore
    //   4483: dup
    //   4484: bipush #17
    //   4486: ldc 16778240
    //   4488: iastore
    //   4489: dup
    //   4490: bipush #18
    //   4492: ldc 16778240
    //   4494: iastore
    //   4495: dup
    //   4496: bipush #19
    //   4498: ldc 66560
    //   4500: iastore
    //   4501: dup
    //   4502: bipush #20
    //   4504: ldc 66560
    //   4506: iastore
    //   4507: dup
    //   4508: bipush #21
    //   4510: ldc 16842752
    //   4512: iastore
    //   4513: dup
    //   4514: bipush #22
    //   4516: ldc 16842752
    //   4518: iastore
    //   4519: dup
    //   4520: bipush #23
    //   4522: ldc 16778244
    //   4524: iastore
    //   4525: dup
    //   4526: bipush #24
    //   4528: ldc 65540
    //   4530: iastore
    //   4531: dup
    //   4532: bipush #25
    //   4534: ldc 16777220
    //   4536: iastore
    //   4537: dup
    //   4538: bipush #26
    //   4540: ldc 16777220
    //   4542: iastore
    //   4543: dup
    //   4544: bipush #27
    //   4546: ldc 65540
    //   4548: iastore
    //   4549: dup
    //   4550: bipush #28
    //   4552: iconst_0
    //   4553: iastore
    //   4554: dup
    //   4555: bipush #29
    //   4557: sipush #1028
    //   4560: iastore
    //   4561: dup
    //   4562: bipush #30
    //   4564: ldc 66564
    //   4566: iastore
    //   4567: dup
    //   4568: bipush #31
    //   4570: ldc 16777216
    //   4572: iastore
    //   4573: dup
    //   4574: bipush #32
    //   4576: ldc 65536
    //   4578: iastore
    //   4579: dup
    //   4580: bipush #33
    //   4582: ldc 16843780
    //   4584: iastore
    //   4585: dup
    //   4586: bipush #34
    //   4588: iconst_4
    //   4589: iastore
    //   4590: dup
    //   4591: bipush #35
    //   4593: ldc 16842752
    //   4595: iastore
    //   4596: dup
    //   4597: bipush #36
    //   4599: ldc 16843776
    //   4601: iastore
    //   4602: dup
    //   4603: bipush #37
    //   4605: ldc 16777216
    //   4607: iastore
    //   4608: dup
    //   4609: bipush #38
    //   4611: ldc 16777216
    //   4613: iastore
    //   4614: dup
    //   4615: bipush #39
    //   4617: sipush #1024
    //   4620: iastore
    //   4621: dup
    //   4622: bipush #40
    //   4624: ldc 16842756
    //   4626: iastore
    //   4627: dup
    //   4628: bipush #41
    //   4630: ldc 65536
    //   4632: iastore
    //   4633: dup
    //   4634: bipush #42
    //   4636: ldc 66560
    //   4638: iastore
    //   4639: dup
    //   4640: bipush #43
    //   4642: ldc 16777220
    //   4644: iastore
    //   4645: dup
    //   4646: bipush #44
    //   4648: sipush #1024
    //   4651: iastore
    //   4652: dup
    //   4653: bipush #45
    //   4655: iconst_4
    //   4656: iastore
    //   4657: dup
    //   4658: bipush #46
    //   4660: ldc 16778244
    //   4662: iastore
    //   4663: dup
    //   4664: bipush #47
    //   4666: ldc 66564
    //   4668: iastore
    //   4669: dup
    //   4670: bipush #48
    //   4672: ldc 16843780
    //   4674: iastore
    //   4675: dup
    //   4676: bipush #49
    //   4678: ldc 65540
    //   4680: iastore
    //   4681: dup
    //   4682: bipush #50
    //   4684: ldc 16842752
    //   4686: iastore
    //   4687: dup
    //   4688: bipush #51
    //   4690: ldc 16778244
    //   4692: iastore
    //   4693: dup
    //   4694: bipush #52
    //   4696: ldc 16777220
    //   4698: iastore
    //   4699: dup
    //   4700: bipush #53
    //   4702: sipush #1028
    //   4705: iastore
    //   4706: dup
    //   4707: bipush #54
    //   4709: ldc 66564
    //   4711: iastore
    //   4712: dup
    //   4713: bipush #55
    //   4715: ldc 16843776
    //   4717: iastore
    //   4718: dup
    //   4719: bipush #56
    //   4721: sipush #1028
    //   4724: iastore
    //   4725: dup
    //   4726: bipush #57
    //   4728: ldc 16778240
    //   4730: iastore
    //   4731: dup
    //   4732: bipush #58
    //   4734: ldc 16778240
    //   4736: iastore
    //   4737: dup
    //   4738: bipush #59
    //   4740: iconst_0
    //   4741: iastore
    //   4742: dup
    //   4743: bipush #60
    //   4745: ldc 65540
    //   4747: iastore
    //   4748: dup
    //   4749: bipush #61
    //   4751: ldc 66560
    //   4753: iastore
    //   4754: dup
    //   4755: bipush #62
    //   4757: iconst_0
    //   4758: iastore
    //   4759: dup
    //   4760: bipush #63
    //   4762: ldc 16842756
    //   4764: iastore
    //   4765: astore #8
    //   4767: bipush #64
    //   4769: newarray int
    //   4771: dup
    //   4772: iconst_0
    //   4773: ldc -2146402272
    //   4775: iastore
    //   4776: dup
    //   4777: iconst_1
    //   4778: ldc -2147450880
    //   4780: iastore
    //   4781: dup
    //   4782: iconst_2
    //   4783: ldc 32768
    //   4785: iastore
    //   4786: dup
    //   4787: iconst_3
    //   4788: ldc 1081376
    //   4790: iastore
    //   4791: dup
    //   4792: iconst_4
    //   4793: ldc 1048576
    //   4795: iastore
    //   4796: dup
    //   4797: iconst_5
    //   4798: bipush #32
    //   4800: iastore
    //   4801: dup
    //   4802: bipush #6
    //   4804: ldc -2146435040
    //   4806: iastore
    //   4807: dup
    //   4808: bipush #7
    //   4810: ldc -2147450848
    //   4812: iastore
    //   4813: dup
    //   4814: bipush #8
    //   4816: ldc -2147483616
    //   4818: iastore
    //   4819: dup
    //   4820: bipush #9
    //   4822: ldc -2146402272
    //   4824: iastore
    //   4825: dup
    //   4826: bipush #10
    //   4828: ldc -2146402304
    //   4830: iastore
    //   4831: dup
    //   4832: bipush #11
    //   4834: ldc -2147483648
    //   4836: iastore
    //   4837: dup
    //   4838: bipush #12
    //   4840: ldc -2147450880
    //   4842: iastore
    //   4843: dup
    //   4844: bipush #13
    //   4846: ldc 1048576
    //   4848: iastore
    //   4849: dup
    //   4850: bipush #14
    //   4852: bipush #32
    //   4854: iastore
    //   4855: dup
    //   4856: bipush #15
    //   4858: ldc -2146435040
    //   4860: iastore
    //   4861: dup
    //   4862: bipush #16
    //   4864: ldc 1081344
    //   4866: iastore
    //   4867: dup
    //   4868: bipush #17
    //   4870: ldc 1048608
    //   4872: iastore
    //   4873: dup
    //   4874: bipush #18
    //   4876: ldc -2147450848
    //   4878: iastore
    //   4879: dup
    //   4880: bipush #19
    //   4882: iconst_0
    //   4883: iastore
    //   4884: dup
    //   4885: bipush #20
    //   4887: ldc -2147483648
    //   4889: iastore
    //   4890: dup
    //   4891: bipush #21
    //   4893: ldc 32768
    //   4895: iastore
    //   4896: dup
    //   4897: bipush #22
    //   4899: ldc 1081376
    //   4901: iastore
    //   4902: dup
    //   4903: bipush #23
    //   4905: ldc -2146435072
    //   4907: iastore
    //   4908: dup
    //   4909: bipush #24
    //   4911: ldc 1048608
    //   4913: iastore
    //   4914: dup
    //   4915: bipush #25
    //   4917: ldc -2147483616
    //   4919: iastore
    //   4920: dup
    //   4921: bipush #26
    //   4923: iconst_0
    //   4924: iastore
    //   4925: dup
    //   4926: bipush #27
    //   4928: ldc 1081344
    //   4930: iastore
    //   4931: dup
    //   4932: bipush #28
    //   4934: ldc 32800
    //   4936: iastore
    //   4937: dup
    //   4938: bipush #29
    //   4940: ldc -2146402304
    //   4942: iastore
    //   4943: dup
    //   4944: bipush #30
    //   4946: ldc -2146435072
    //   4948: iastore
    //   4949: dup
    //   4950: bipush #31
    //   4952: ldc 32800
    //   4954: iastore
    //   4955: dup
    //   4956: bipush #32
    //   4958: iconst_0
    //   4959: iastore
    //   4960: dup
    //   4961: bipush #33
    //   4963: ldc 1081376
    //   4965: iastore
    //   4966: dup
    //   4967: bipush #34
    //   4969: ldc -2146435040
    //   4971: iastore
    //   4972: dup
    //   4973: bipush #35
    //   4975: ldc 1048576
    //   4977: iastore
    //   4978: dup
    //   4979: bipush #36
    //   4981: ldc -2147450848
    //   4983: iastore
    //   4984: dup
    //   4985: bipush #37
    //   4987: ldc -2146435072
    //   4989: iastore
    //   4990: dup
    //   4991: bipush #38
    //   4993: ldc -2146402304
    //   4995: iastore
    //   4996: dup
    //   4997: bipush #39
    //   4999: ldc 32768
    //   5001: iastore
    //   5002: dup
    //   5003: bipush #40
    //   5005: ldc -2146435072
    //   5007: iastore
    //   5008: dup
    //   5009: bipush #41
    //   5011: ldc -2147450880
    //   5013: iastore
    //   5014: dup
    //   5015: bipush #42
    //   5017: bipush #32
    //   5019: iastore
    //   5020: dup
    //   5021: bipush #43
    //   5023: ldc -2146402272
    //   5025: iastore
    //   5026: dup
    //   5027: bipush #44
    //   5029: ldc 1081376
    //   5031: iastore
    //   5032: dup
    //   5033: bipush #45
    //   5035: bipush #32
    //   5037: iastore
    //   5038: dup
    //   5039: bipush #46
    //   5041: ldc 32768
    //   5043: iastore
    //   5044: dup
    //   5045: bipush #47
    //   5047: ldc -2147483648
    //   5049: iastore
    //   5050: dup
    //   5051: bipush #48
    //   5053: ldc 32800
    //   5055: iastore
    //   5056: dup
    //   5057: bipush #49
    //   5059: ldc -2146402304
    //   5061: iastore
    //   5062: dup
    //   5063: bipush #50
    //   5065: ldc 1048576
    //   5067: iastore
    //   5068: dup
    //   5069: bipush #51
    //   5071: ldc -2147483616
    //   5073: iastore
    //   5074: dup
    //   5075: bipush #52
    //   5077: ldc 1048608
    //   5079: iastore
    //   5080: dup
    //   5081: bipush #53
    //   5083: ldc -2147450848
    //   5085: iastore
    //   5086: dup
    //   5087: bipush #54
    //   5089: ldc -2147483616
    //   5091: iastore
    //   5092: dup
    //   5093: bipush #55
    //   5095: ldc 1048608
    //   5097: iastore
    //   5098: dup
    //   5099: bipush #56
    //   5101: ldc 1081344
    //   5103: iastore
    //   5104: dup
    //   5105: bipush #57
    //   5107: iconst_0
    //   5108: iastore
    //   5109: dup
    //   5110: bipush #58
    //   5112: ldc -2147450880
    //   5114: iastore
    //   5115: dup
    //   5116: bipush #59
    //   5118: ldc 32800
    //   5120: iastore
    //   5121: dup
    //   5122: bipush #60
    //   5124: ldc -2147483648
    //   5126: iastore
    //   5127: dup
    //   5128: bipush #61
    //   5130: ldc -2146435040
    //   5132: iastore
    //   5133: dup
    //   5134: bipush #62
    //   5136: ldc -2146402272
    //   5138: iastore
    //   5139: dup
    //   5140: bipush #63
    //   5142: ldc 1081344
    //   5144: iastore
    //   5145: astore #9
    //   5147: bipush #64
    //   5149: newarray int
    //   5151: dup
    //   5152: iconst_0
    //   5153: sipush #520
    //   5156: iastore
    //   5157: dup
    //   5158: iconst_1
    //   5159: ldc 134349312
    //   5161: iastore
    //   5162: dup
    //   5163: iconst_2
    //   5164: iconst_0
    //   5165: iastore
    //   5166: dup
    //   5167: iconst_3
    //   5168: ldc 134348808
    //   5170: iastore
    //   5171: dup
    //   5172: iconst_4
    //   5173: ldc 134218240
    //   5175: iastore
    //   5176: dup
    //   5177: iconst_5
    //   5178: iconst_0
    //   5179: iastore
    //   5180: dup
    //   5181: bipush #6
    //   5183: ldc 131592
    //   5185: iastore
    //   5186: dup
    //   5187: bipush #7
    //   5189: ldc 134218240
    //   5191: iastore
    //   5192: dup
    //   5193: bipush #8
    //   5195: ldc 131080
    //   5197: iastore
    //   5198: dup
    //   5199: bipush #9
    //   5201: ldc 134217736
    //   5203: iastore
    //   5204: dup
    //   5205: bipush #10
    //   5207: ldc 134217736
    //   5209: iastore
    //   5210: dup
    //   5211: bipush #11
    //   5213: ldc 131072
    //   5215: iastore
    //   5216: dup
    //   5217: bipush #12
    //   5219: ldc 134349320
    //   5221: iastore
    //   5222: dup
    //   5223: bipush #13
    //   5225: ldc 131080
    //   5227: iastore
    //   5228: dup
    //   5229: bipush #14
    //   5231: ldc 134348800
    //   5233: iastore
    //   5234: dup
    //   5235: bipush #15
    //   5237: sipush #520
    //   5240: iastore
    //   5241: dup
    //   5242: bipush #16
    //   5244: ldc 134217728
    //   5246: iastore
    //   5247: dup
    //   5248: bipush #17
    //   5250: bipush #8
    //   5252: iastore
    //   5253: dup
    //   5254: bipush #18
    //   5256: ldc 134349312
    //   5258: iastore
    //   5259: dup
    //   5260: bipush #19
    //   5262: sipush #512
    //   5265: iastore
    //   5266: dup
    //   5267: bipush #20
    //   5269: ldc 131584
    //   5271: iastore
    //   5272: dup
    //   5273: bipush #21
    //   5275: ldc 134348800
    //   5277: iastore
    //   5278: dup
    //   5279: bipush #22
    //   5281: ldc 134348808
    //   5283: iastore
    //   5284: dup
    //   5285: bipush #23
    //   5287: ldc 131592
    //   5289: iastore
    //   5290: dup
    //   5291: bipush #24
    //   5293: ldc 134218248
    //   5295: iastore
    //   5296: dup
    //   5297: bipush #25
    //   5299: ldc 131584
    //   5301: iastore
    //   5302: dup
    //   5303: bipush #26
    //   5305: ldc 131072
    //   5307: iastore
    //   5308: dup
    //   5309: bipush #27
    //   5311: ldc 134218248
    //   5313: iastore
    //   5314: dup
    //   5315: bipush #28
    //   5317: bipush #8
    //   5319: iastore
    //   5320: dup
    //   5321: bipush #29
    //   5323: ldc 134349320
    //   5325: iastore
    //   5326: dup
    //   5327: bipush #30
    //   5329: sipush #512
    //   5332: iastore
    //   5333: dup
    //   5334: bipush #31
    //   5336: ldc 134217728
    //   5338: iastore
    //   5339: dup
    //   5340: bipush #32
    //   5342: ldc 134349312
    //   5344: iastore
    //   5345: dup
    //   5346: bipush #33
    //   5348: ldc 134217728
    //   5350: iastore
    //   5351: dup
    //   5352: bipush #34
    //   5354: ldc 131080
    //   5356: iastore
    //   5357: dup
    //   5358: bipush #35
    //   5360: sipush #520
    //   5363: iastore
    //   5364: dup
    //   5365: bipush #36
    //   5367: ldc 131072
    //   5369: iastore
    //   5370: dup
    //   5371: bipush #37
    //   5373: ldc 134349312
    //   5375: iastore
    //   5376: dup
    //   5377: bipush #38
    //   5379: ldc 134218240
    //   5381: iastore
    //   5382: dup
    //   5383: bipush #39
    //   5385: iconst_0
    //   5386: iastore
    //   5387: dup
    //   5388: bipush #40
    //   5390: sipush #512
    //   5393: iastore
    //   5394: dup
    //   5395: bipush #41
    //   5397: ldc 131080
    //   5399: iastore
    //   5400: dup
    //   5401: bipush #42
    //   5403: ldc 134349320
    //   5405: iastore
    //   5406: dup
    //   5407: bipush #43
    //   5409: ldc 134218240
    //   5411: iastore
    //   5412: dup
    //   5413: bipush #44
    //   5415: ldc 134217736
    //   5417: iastore
    //   5418: dup
    //   5419: bipush #45
    //   5421: sipush #512
    //   5424: iastore
    //   5425: dup
    //   5426: bipush #46
    //   5428: iconst_0
    //   5429: iastore
    //   5430: dup
    //   5431: bipush #47
    //   5433: ldc 134348808
    //   5435: iastore
    //   5436: dup
    //   5437: bipush #48
    //   5439: ldc 134218248
    //   5441: iastore
    //   5442: dup
    //   5443: bipush #49
    //   5445: ldc 131072
    //   5447: iastore
    //   5448: dup
    //   5449: bipush #50
    //   5451: ldc 134217728
    //   5453: iastore
    //   5454: dup
    //   5455: bipush #51
    //   5457: ldc 134349320
    //   5459: iastore
    //   5460: dup
    //   5461: bipush #52
    //   5463: bipush #8
    //   5465: iastore
    //   5466: dup
    //   5467: bipush #53
    //   5469: ldc 131592
    //   5471: iastore
    //   5472: dup
    //   5473: bipush #54
    //   5475: ldc 131584
    //   5477: iastore
    //   5478: dup
    //   5479: bipush #55
    //   5481: ldc 134217736
    //   5483: iastore
    //   5484: dup
    //   5485: bipush #56
    //   5487: ldc 134348800
    //   5489: iastore
    //   5490: dup
    //   5491: bipush #57
    //   5493: ldc 134218248
    //   5495: iastore
    //   5496: dup
    //   5497: bipush #58
    //   5499: sipush #520
    //   5502: iastore
    //   5503: dup
    //   5504: bipush #59
    //   5506: ldc 134348800
    //   5508: iastore
    //   5509: dup
    //   5510: bipush #60
    //   5512: ldc 131592
    //   5514: iastore
    //   5515: dup
    //   5516: bipush #61
    //   5518: bipush #8
    //   5520: iastore
    //   5521: dup
    //   5522: bipush #62
    //   5524: ldc 134348808
    //   5526: iastore
    //   5527: dup
    //   5528: bipush #63
    //   5530: ldc 131584
    //   5532: iastore
    //   5533: astore #10
    //   5535: bipush #64
    //   5537: newarray int
    //   5539: dup
    //   5540: iconst_0
    //   5541: ldc 8396801
    //   5543: iastore
    //   5544: dup
    //   5545: iconst_1
    //   5546: sipush #8321
    //   5549: iastore
    //   5550: dup
    //   5551: iconst_2
    //   5552: sipush #8321
    //   5555: iastore
    //   5556: dup
    //   5557: iconst_3
    //   5558: sipush #128
    //   5561: iastore
    //   5562: dup
    //   5563: iconst_4
    //   5564: ldc 8396928
    //   5566: iastore
    //   5567: dup
    //   5568: iconst_5
    //   5569: ldc 8388737
    //   5571: iastore
    //   5572: dup
    //   5573: bipush #6
    //   5575: ldc 8388609
    //   5577: iastore
    //   5578: dup
    //   5579: bipush #7
    //   5581: sipush #8193
    //   5584: iastore
    //   5585: dup
    //   5586: bipush #8
    //   5588: iconst_0
    //   5589: iastore
    //   5590: dup
    //   5591: bipush #9
    //   5593: ldc 8396800
    //   5595: iastore
    //   5596: dup
    //   5597: bipush #10
    //   5599: ldc 8396800
    //   5601: iastore
    //   5602: dup
    //   5603: bipush #11
    //   5605: ldc 8396929
    //   5607: iastore
    //   5608: dup
    //   5609: bipush #12
    //   5611: sipush #129
    //   5614: iastore
    //   5615: dup
    //   5616: bipush #13
    //   5618: iconst_0
    //   5619: iastore
    //   5620: dup
    //   5621: bipush #14
    //   5623: ldc 8388736
    //   5625: iastore
    //   5626: dup
    //   5627: bipush #15
    //   5629: ldc 8388609
    //   5631: iastore
    //   5632: dup
    //   5633: bipush #16
    //   5635: iconst_1
    //   5636: iastore
    //   5637: dup
    //   5638: bipush #17
    //   5640: sipush #8192
    //   5643: iastore
    //   5644: dup
    //   5645: bipush #18
    //   5647: ldc 8388608
    //   5649: iastore
    //   5650: dup
    //   5651: bipush #19
    //   5653: ldc 8396801
    //   5655: iastore
    //   5656: dup
    //   5657: bipush #20
    //   5659: sipush #128
    //   5662: iastore
    //   5663: dup
    //   5664: bipush #21
    //   5666: ldc 8388608
    //   5668: iastore
    //   5669: dup
    //   5670: bipush #22
    //   5672: sipush #8193
    //   5675: iastore
    //   5676: dup
    //   5677: bipush #23
    //   5679: sipush #8320
    //   5682: iastore
    //   5683: dup
    //   5684: bipush #24
    //   5686: ldc 8388737
    //   5688: iastore
    //   5689: dup
    //   5690: bipush #25
    //   5692: iconst_1
    //   5693: iastore
    //   5694: dup
    //   5695: bipush #26
    //   5697: sipush #8320
    //   5700: iastore
    //   5701: dup
    //   5702: bipush #27
    //   5704: ldc 8388736
    //   5706: iastore
    //   5707: dup
    //   5708: bipush #28
    //   5710: sipush #8192
    //   5713: iastore
    //   5714: dup
    //   5715: bipush #29
    //   5717: ldc 8396928
    //   5719: iastore
    //   5720: dup
    //   5721: bipush #30
    //   5723: ldc 8396929
    //   5725: iastore
    //   5726: dup
    //   5727: bipush #31
    //   5729: sipush #129
    //   5732: iastore
    //   5733: dup
    //   5734: bipush #32
    //   5736: ldc 8388736
    //   5738: iastore
    //   5739: dup
    //   5740: bipush #33
    //   5742: ldc 8388609
    //   5744: iastore
    //   5745: dup
    //   5746: bipush #34
    //   5748: ldc 8396800
    //   5750: iastore
    //   5751: dup
    //   5752: bipush #35
    //   5754: ldc 8396929
    //   5756: iastore
    //   5757: dup
    //   5758: bipush #36
    //   5760: sipush #129
    //   5763: iastore
    //   5764: dup
    //   5765: bipush #37
    //   5767: iconst_0
    //   5768: iastore
    //   5769: dup
    //   5770: bipush #38
    //   5772: iconst_0
    //   5773: iastore
    //   5774: dup
    //   5775: bipush #39
    //   5777: ldc 8396800
    //   5779: iastore
    //   5780: dup
    //   5781: bipush #40
    //   5783: sipush #8320
    //   5786: iastore
    //   5787: dup
    //   5788: bipush #41
    //   5790: ldc 8388736
    //   5792: iastore
    //   5793: dup
    //   5794: bipush #42
    //   5796: ldc 8388737
    //   5798: iastore
    //   5799: dup
    //   5800: bipush #43
    //   5802: iconst_1
    //   5803: iastore
    //   5804: dup
    //   5805: bipush #44
    //   5807: ldc 8396801
    //   5809: iastore
    //   5810: dup
    //   5811: bipush #45
    //   5813: sipush #8321
    //   5816: iastore
    //   5817: dup
    //   5818: bipush #46
    //   5820: sipush #8321
    //   5823: iastore
    //   5824: dup
    //   5825: bipush #47
    //   5827: sipush #128
    //   5830: iastore
    //   5831: dup
    //   5832: bipush #48
    //   5834: ldc 8396929
    //   5836: iastore
    //   5837: dup
    //   5838: bipush #49
    //   5840: sipush #129
    //   5843: iastore
    //   5844: dup
    //   5845: bipush #50
    //   5847: iconst_1
    //   5848: iastore
    //   5849: dup
    //   5850: bipush #51
    //   5852: sipush #8192
    //   5855: iastore
    //   5856: dup
    //   5857: bipush #52
    //   5859: ldc 8388609
    //   5861: iastore
    //   5862: dup
    //   5863: bipush #53
    //   5865: sipush #8193
    //   5868: iastore
    //   5869: dup
    //   5870: bipush #54
    //   5872: ldc 8396928
    //   5874: iastore
    //   5875: dup
    //   5876: bipush #55
    //   5878: ldc 8388737
    //   5880: iastore
    //   5881: dup
    //   5882: bipush #56
    //   5884: sipush #8193
    //   5887: iastore
    //   5888: dup
    //   5889: bipush #57
    //   5891: sipush #8320
    //   5894: iastore
    //   5895: dup
    //   5896: bipush #58
    //   5898: ldc 8388608
    //   5900: iastore
    //   5901: dup
    //   5902: bipush #59
    //   5904: ldc 8396801
    //   5906: iastore
    //   5907: dup
    //   5908: bipush #60
    //   5910: sipush #128
    //   5913: iastore
    //   5914: dup
    //   5915: bipush #61
    //   5917: ldc 8388608
    //   5919: iastore
    //   5920: dup
    //   5921: bipush #62
    //   5923: sipush #8192
    //   5926: iastore
    //   5927: dup
    //   5928: bipush #63
    //   5930: ldc 8396928
    //   5932: iastore
    //   5933: astore #11
    //   5935: bipush #64
    //   5937: newarray int
    //   5939: dup
    //   5940: iconst_0
    //   5941: sipush #256
    //   5944: iastore
    //   5945: dup
    //   5946: iconst_1
    //   5947: ldc 34078976
    //   5949: iastore
    //   5950: dup
    //   5951: iconst_2
    //   5952: ldc 34078720
    //   5954: iastore
    //   5955: dup
    //   5956: iconst_3
    //   5957: ldc 1107296512
    //   5959: iastore
    //   5960: dup
    //   5961: iconst_4
    //   5962: ldc 524288
    //   5964: iastore
    //   5965: dup
    //   5966: iconst_5
    //   5967: sipush #256
    //   5970: iastore
    //   5971: dup
    //   5972: bipush #6
    //   5974: ldc 1073741824
    //   5976: iastore
    //   5977: dup
    //   5978: bipush #7
    //   5980: ldc 34078720
    //   5982: iastore
    //   5983: dup
    //   5984: bipush #8
    //   5986: ldc 1074266368
    //   5988: iastore
    //   5989: dup
    //   5990: bipush #9
    //   5992: ldc 524288
    //   5994: iastore
    //   5995: dup
    //   5996: bipush #10
    //   5998: ldc 33554688
    //   6000: iastore
    //   6001: dup
    //   6002: bipush #11
    //   6004: ldc 1074266368
    //   6006: iastore
    //   6007: dup
    //   6008: bipush #12
    //   6010: ldc 1107296512
    //   6012: iastore
    //   6013: dup
    //   6014: bipush #13
    //   6016: ldc 1107820544
    //   6018: iastore
    //   6019: dup
    //   6020: bipush #14
    //   6022: ldc 524544
    //   6024: iastore
    //   6025: dup
    //   6026: bipush #15
    //   6028: ldc 1073741824
    //   6030: iastore
    //   6031: dup
    //   6032: bipush #16
    //   6034: ldc 33554432
    //   6036: iastore
    //   6037: dup
    //   6038: bipush #17
    //   6040: ldc 1074266112
    //   6042: iastore
    //   6043: dup
    //   6044: bipush #18
    //   6046: ldc 1074266112
    //   6048: iastore
    //   6049: dup
    //   6050: bipush #19
    //   6052: iconst_0
    //   6053: iastore
    //   6054: dup
    //   6055: bipush #20
    //   6057: ldc 1073742080
    //   6059: iastore
    //   6060: dup
    //   6061: bipush #21
    //   6063: ldc 1107820800
    //   6065: iastore
    //   6066: dup
    //   6067: bipush #22
    //   6069: ldc 1107820800
    //   6071: iastore
    //   6072: dup
    //   6073: bipush #23
    //   6075: ldc 33554688
    //   6077: iastore
    //   6078: dup
    //   6079: bipush #24
    //   6081: ldc 1107820544
    //   6083: iastore
    //   6084: dup
    //   6085: bipush #25
    //   6087: ldc 1073742080
    //   6089: iastore
    //   6090: dup
    //   6091: bipush #26
    //   6093: iconst_0
    //   6094: iastore
    //   6095: dup
    //   6096: bipush #27
    //   6098: ldc 1107296256
    //   6100: iastore
    //   6101: dup
    //   6102: bipush #28
    //   6104: ldc 34078976
    //   6106: iastore
    //   6107: dup
    //   6108: bipush #29
    //   6110: ldc 33554432
    //   6112: iastore
    //   6113: dup
    //   6114: bipush #30
    //   6116: ldc 1107296256
    //   6118: iastore
    //   6119: dup
    //   6120: bipush #31
    //   6122: ldc 524544
    //   6124: iastore
    //   6125: dup
    //   6126: bipush #32
    //   6128: ldc 524288
    //   6130: iastore
    //   6131: dup
    //   6132: bipush #33
    //   6134: ldc 1107296512
    //   6136: iastore
    //   6137: dup
    //   6138: bipush #34
    //   6140: sipush #256
    //   6143: iastore
    //   6144: dup
    //   6145: bipush #35
    //   6147: ldc 33554432
    //   6149: iastore
    //   6150: dup
    //   6151: bipush #36
    //   6153: ldc 1073741824
    //   6155: iastore
    //   6156: dup
    //   6157: bipush #37
    //   6159: ldc 34078720
    //   6161: iastore
    //   6162: dup
    //   6163: bipush #38
    //   6165: ldc 1107296512
    //   6167: iastore
    //   6168: dup
    //   6169: bipush #39
    //   6171: ldc 1074266368
    //   6173: iastore
    //   6174: dup
    //   6175: bipush #40
    //   6177: ldc 33554688
    //   6179: iastore
    //   6180: dup
    //   6181: bipush #41
    //   6183: ldc 1073741824
    //   6185: iastore
    //   6186: dup
    //   6187: bipush #42
    //   6189: ldc 1107820544
    //   6191: iastore
    //   6192: dup
    //   6193: bipush #43
    //   6195: ldc 34078976
    //   6197: iastore
    //   6198: dup
    //   6199: bipush #44
    //   6201: ldc 1074266368
    //   6203: iastore
    //   6204: dup
    //   6205: bipush #45
    //   6207: sipush #256
    //   6210: iastore
    //   6211: dup
    //   6212: bipush #46
    //   6214: ldc 33554432
    //   6216: iastore
    //   6217: dup
    //   6218: bipush #47
    //   6220: ldc 1107820544
    //   6222: iastore
    //   6223: dup
    //   6224: bipush #48
    //   6226: ldc 1107820800
    //   6228: iastore
    //   6229: dup
    //   6230: bipush #49
    //   6232: ldc 524544
    //   6234: iastore
    //   6235: dup
    //   6236: bipush #50
    //   6238: ldc 1107296256
    //   6240: iastore
    //   6241: dup
    //   6242: bipush #51
    //   6244: ldc 1107820800
    //   6246: iastore
    //   6247: dup
    //   6248: bipush #52
    //   6250: ldc 34078720
    //   6252: iastore
    //   6253: dup
    //   6254: bipush #53
    //   6256: iconst_0
    //   6257: iastore
    //   6258: dup
    //   6259: bipush #54
    //   6261: ldc 1074266112
    //   6263: iastore
    //   6264: dup
    //   6265: bipush #55
    //   6267: ldc 1107296256
    //   6269: iastore
    //   6270: dup
    //   6271: bipush #56
    //   6273: ldc 524544
    //   6275: iastore
    //   6276: dup
    //   6277: bipush #57
    //   6279: ldc 33554688
    //   6281: iastore
    //   6282: dup
    //   6283: bipush #58
    //   6285: ldc 1073742080
    //   6287: iastore
    //   6288: dup
    //   6289: bipush #59
    //   6291: ldc 524288
    //   6293: iastore
    //   6294: dup
    //   6295: bipush #60
    //   6297: iconst_0
    //   6298: iastore
    //   6299: dup
    //   6300: bipush #61
    //   6302: ldc 1074266112
    //   6304: iastore
    //   6305: dup
    //   6306: bipush #62
    //   6308: ldc 34078976
    //   6310: iastore
    //   6311: dup
    //   6312: bipush #63
    //   6314: ldc 1073742080
    //   6316: iastore
    //   6317: astore #12
    //   6319: bipush #64
    //   6321: newarray int
    //   6323: dup
    //   6324: iconst_0
    //   6325: ldc 536870928
    //   6327: iastore
    //   6328: dup
    //   6329: iconst_1
    //   6330: ldc 541065216
    //   6332: iastore
    //   6333: dup
    //   6334: iconst_2
    //   6335: sipush #16384
    //   6338: iastore
    //   6339: dup
    //   6340: iconst_3
    //   6341: ldc 541081616
    //   6343: iastore
    //   6344: dup
    //   6345: iconst_4
    //   6346: ldc 541065216
    //   6348: iastore
    //   6349: dup
    //   6350: iconst_5
    //   6351: bipush #16
    //   6353: iastore
    //   6354: dup
    //   6355: bipush #6
    //   6357: ldc 541081616
    //   6359: iastore
    //   6360: dup
    //   6361: bipush #7
    //   6363: ldc 4194304
    //   6365: iastore
    //   6366: dup
    //   6367: bipush #8
    //   6369: ldc 536887296
    //   6371: iastore
    //   6372: dup
    //   6373: bipush #9
    //   6375: ldc 4210704
    //   6377: iastore
    //   6378: dup
    //   6379: bipush #10
    //   6381: ldc 4194304
    //   6383: iastore
    //   6384: dup
    //   6385: bipush #11
    //   6387: ldc 536870928
    //   6389: iastore
    //   6390: dup
    //   6391: bipush #12
    //   6393: ldc 4194320
    //   6395: iastore
    //   6396: dup
    //   6397: bipush #13
    //   6399: ldc 536887296
    //   6401: iastore
    //   6402: dup
    //   6403: bipush #14
    //   6405: ldc 536870912
    //   6407: iastore
    //   6408: dup
    //   6409: bipush #15
    //   6411: sipush #16400
    //   6414: iastore
    //   6415: dup
    //   6416: bipush #16
    //   6418: iconst_0
    //   6419: iastore
    //   6420: dup
    //   6421: bipush #17
    //   6423: ldc 4194320
    //   6425: iastore
    //   6426: dup
    //   6427: bipush #18
    //   6429: ldc 536887312
    //   6431: iastore
    //   6432: dup
    //   6433: bipush #19
    //   6435: sipush #16384
    //   6438: iastore
    //   6439: dup
    //   6440: bipush #20
    //   6442: ldc 4210688
    //   6444: iastore
    //   6445: dup
    //   6446: bipush #21
    //   6448: ldc 536887312
    //   6450: iastore
    //   6451: dup
    //   6452: bipush #22
    //   6454: bipush #16
    //   6456: iastore
    //   6457: dup
    //   6458: bipush #23
    //   6460: ldc 541065232
    //   6462: iastore
    //   6463: dup
    //   6464: bipush #24
    //   6466: ldc 541065232
    //   6468: iastore
    //   6469: dup
    //   6470: bipush #25
    //   6472: iconst_0
    //   6473: iastore
    //   6474: dup
    //   6475: bipush #26
    //   6477: ldc 4210704
    //   6479: iastore
    //   6480: dup
    //   6481: bipush #27
    //   6483: ldc 541081600
    //   6485: iastore
    //   6486: dup
    //   6487: bipush #28
    //   6489: sipush #16400
    //   6492: iastore
    //   6493: dup
    //   6494: bipush #29
    //   6496: ldc 4210688
    //   6498: iastore
    //   6499: dup
    //   6500: bipush #30
    //   6502: ldc 541081600
    //   6504: iastore
    //   6505: dup
    //   6506: bipush #31
    //   6508: ldc 536870912
    //   6510: iastore
    //   6511: dup
    //   6512: bipush #32
    //   6514: ldc 536887296
    //   6516: iastore
    //   6517: dup
    //   6518: bipush #33
    //   6520: bipush #16
    //   6522: iastore
    //   6523: dup
    //   6524: bipush #34
    //   6526: ldc 541065232
    //   6528: iastore
    //   6529: dup
    //   6530: bipush #35
    //   6532: ldc 4210688
    //   6534: iastore
    //   6535: dup
    //   6536: bipush #36
    //   6538: ldc 541081616
    //   6540: iastore
    //   6541: dup
    //   6542: bipush #37
    //   6544: ldc 4194304
    //   6546: iastore
    //   6547: dup
    //   6548: bipush #38
    //   6550: sipush #16400
    //   6553: iastore
    //   6554: dup
    //   6555: bipush #39
    //   6557: ldc 536870928
    //   6559: iastore
    //   6560: dup
    //   6561: bipush #40
    //   6563: ldc 4194304
    //   6565: iastore
    //   6566: dup
    //   6567: bipush #41
    //   6569: ldc 536887296
    //   6571: iastore
    //   6572: dup
    //   6573: bipush #42
    //   6575: ldc 536870912
    //   6577: iastore
    //   6578: dup
    //   6579: bipush #43
    //   6581: sipush #16400
    //   6584: iastore
    //   6585: dup
    //   6586: bipush #44
    //   6588: ldc 536870928
    //   6590: iastore
    //   6591: dup
    //   6592: bipush #45
    //   6594: ldc 541081616
    //   6596: iastore
    //   6597: dup
    //   6598: bipush #46
    //   6600: ldc 4210688
    //   6602: iastore
    //   6603: dup
    //   6604: bipush #47
    //   6606: ldc 541065216
    //   6608: iastore
    //   6609: dup
    //   6610: bipush #48
    //   6612: ldc 4210704
    //   6614: iastore
    //   6615: dup
    //   6616: bipush #49
    //   6618: ldc 541081600
    //   6620: iastore
    //   6621: dup
    //   6622: bipush #50
    //   6624: iconst_0
    //   6625: iastore
    //   6626: dup
    //   6627: bipush #51
    //   6629: ldc 541065232
    //   6631: iastore
    //   6632: dup
    //   6633: bipush #52
    //   6635: bipush #16
    //   6637: iastore
    //   6638: dup
    //   6639: bipush #53
    //   6641: sipush #16384
    //   6644: iastore
    //   6645: dup
    //   6646: bipush #54
    //   6648: ldc 541065216
    //   6650: iastore
    //   6651: dup
    //   6652: bipush #55
    //   6654: ldc 4210704
    //   6656: iastore
    //   6657: dup
    //   6658: bipush #56
    //   6660: sipush #16384
    //   6663: iastore
    //   6664: dup
    //   6665: bipush #57
    //   6667: ldc 4194320
    //   6669: iastore
    //   6670: dup
    //   6671: bipush #58
    //   6673: ldc 536887312
    //   6675: iastore
    //   6676: dup
    //   6677: bipush #59
    //   6679: iconst_0
    //   6680: iastore
    //   6681: dup
    //   6682: bipush #60
    //   6684: ldc 541081600
    //   6686: iastore
    //   6687: dup
    //   6688: bipush #61
    //   6690: ldc 536870912
    //   6692: iastore
    //   6693: dup
    //   6694: bipush #62
    //   6696: ldc 4194320
    //   6698: iastore
    //   6699: dup
    //   6700: bipush #63
    //   6702: ldc 536887312
    //   6704: iastore
    //   6705: astore #13
    //   6707: bipush #64
    //   6709: newarray int
    //   6711: dup
    //   6712: iconst_0
    //   6713: ldc 2097152
    //   6715: iastore
    //   6716: dup
    //   6717: iconst_1
    //   6718: ldc 69206018
    //   6720: iastore
    //   6721: dup
    //   6722: iconst_2
    //   6723: ldc 67110914
    //   6725: iastore
    //   6726: dup
    //   6727: iconst_3
    //   6728: iconst_0
    //   6729: iastore
    //   6730: dup
    //   6731: iconst_4
    //   6732: sipush #2048
    //   6735: iastore
    //   6736: dup
    //   6737: iconst_5
    //   6738: ldc 67110914
    //   6740: iastore
    //   6741: dup
    //   6742: bipush #6
    //   6744: ldc 2099202
    //   6746: iastore
    //   6747: dup
    //   6748: bipush #7
    //   6750: ldc 69208064
    //   6752: iastore
    //   6753: dup
    //   6754: bipush #8
    //   6756: ldc 69208066
    //   6758: iastore
    //   6759: dup
    //   6760: bipush #9
    //   6762: ldc 2097152
    //   6764: iastore
    //   6765: dup
    //   6766: bipush #10
    //   6768: iconst_0
    //   6769: iastore
    //   6770: dup
    //   6771: bipush #11
    //   6773: ldc 67108866
    //   6775: iastore
    //   6776: dup
    //   6777: bipush #12
    //   6779: iconst_2
    //   6780: iastore
    //   6781: dup
    //   6782: bipush #13
    //   6784: ldc 67108864
    //   6786: iastore
    //   6787: dup
    //   6788: bipush #14
    //   6790: ldc 69206018
    //   6792: iastore
    //   6793: dup
    //   6794: bipush #15
    //   6796: sipush #2050
    //   6799: iastore
    //   6800: dup
    //   6801: bipush #16
    //   6803: ldc 67110912
    //   6805: iastore
    //   6806: dup
    //   6807: bipush #17
    //   6809: ldc 2099202
    //   6811: iastore
    //   6812: dup
    //   6813: bipush #18
    //   6815: ldc 2097154
    //   6817: iastore
    //   6818: dup
    //   6819: bipush #19
    //   6821: ldc 67110912
    //   6823: iastore
    //   6824: dup
    //   6825: bipush #20
    //   6827: ldc 67108866
    //   6829: iastore
    //   6830: dup
    //   6831: bipush #21
    //   6833: ldc 69206016
    //   6835: iastore
    //   6836: dup
    //   6837: bipush #22
    //   6839: ldc 69208064
    //   6841: iastore
    //   6842: dup
    //   6843: bipush #23
    //   6845: ldc 2097154
    //   6847: iastore
    //   6848: dup
    //   6849: bipush #24
    //   6851: ldc 69206016
    //   6853: iastore
    //   6854: dup
    //   6855: bipush #25
    //   6857: sipush #2048
    //   6860: iastore
    //   6861: dup
    //   6862: bipush #26
    //   6864: sipush #2050
    //   6867: iastore
    //   6868: dup
    //   6869: bipush #27
    //   6871: ldc 69208066
    //   6873: iastore
    //   6874: dup
    //   6875: bipush #28
    //   6877: ldc 2099200
    //   6879: iastore
    //   6880: dup
    //   6881: bipush #29
    //   6883: iconst_2
    //   6884: iastore
    //   6885: dup
    //   6886: bipush #30
    //   6888: ldc 67108864
    //   6890: iastore
    //   6891: dup
    //   6892: bipush #31
    //   6894: ldc 2099200
    //   6896: iastore
    //   6897: dup
    //   6898: bipush #32
    //   6900: ldc 67108864
    //   6902: iastore
    //   6903: dup
    //   6904: bipush #33
    //   6906: ldc 2099200
    //   6908: iastore
    //   6909: dup
    //   6910: bipush #34
    //   6912: ldc 2097152
    //   6914: iastore
    //   6915: dup
    //   6916: bipush #35
    //   6918: ldc 67110914
    //   6920: iastore
    //   6921: dup
    //   6922: bipush #36
    //   6924: ldc 67110914
    //   6926: iastore
    //   6927: dup
    //   6928: bipush #37
    //   6930: ldc 69206018
    //   6932: iastore
    //   6933: dup
    //   6934: bipush #38
    //   6936: ldc 69206018
    //   6938: iastore
    //   6939: dup
    //   6940: bipush #39
    //   6942: iconst_2
    //   6943: iastore
    //   6944: dup
    //   6945: bipush #40
    //   6947: ldc 2097154
    //   6949: iastore
    //   6950: dup
    //   6951: bipush #41
    //   6953: ldc 67108864
    //   6955: iastore
    //   6956: dup
    //   6957: bipush #42
    //   6959: ldc 67110912
    //   6961: iastore
    //   6962: dup
    //   6963: bipush #43
    //   6965: ldc 2097152
    //   6967: iastore
    //   6968: dup
    //   6969: bipush #44
    //   6971: ldc 69208064
    //   6973: iastore
    //   6974: dup
    //   6975: bipush #45
    //   6977: sipush #2050
    //   6980: iastore
    //   6981: dup
    //   6982: bipush #46
    //   6984: ldc 2099202
    //   6986: iastore
    //   6987: dup
    //   6988: bipush #47
    //   6990: ldc 69208064
    //   6992: iastore
    //   6993: dup
    //   6994: bipush #48
    //   6996: sipush #2050
    //   6999: iastore
    //   7000: dup
    //   7001: bipush #49
    //   7003: ldc 67108866
    //   7005: iastore
    //   7006: dup
    //   7007: bipush #50
    //   7009: ldc 69208066
    //   7011: iastore
    //   7012: dup
    //   7013: bipush #51
    //   7015: ldc 69206016
    //   7017: iastore
    //   7018: dup
    //   7019: bipush #52
    //   7021: ldc 2099200
    //   7023: iastore
    //   7024: dup
    //   7025: bipush #53
    //   7027: iconst_0
    //   7028: iastore
    //   7029: dup
    //   7030: bipush #54
    //   7032: iconst_2
    //   7033: iastore
    //   7034: dup
    //   7035: bipush #55
    //   7037: ldc 69208066
    //   7039: iastore
    //   7040: dup
    //   7041: bipush #56
    //   7043: iconst_0
    //   7044: iastore
    //   7045: dup
    //   7046: bipush #57
    //   7048: ldc 2099202
    //   7050: iastore
    //   7051: dup
    //   7052: bipush #58
    //   7054: ldc 69206016
    //   7056: iastore
    //   7057: dup
    //   7058: bipush #59
    //   7060: sipush #2048
    //   7063: iastore
    //   7064: dup
    //   7065: bipush #60
    //   7067: ldc 67108866
    //   7069: iastore
    //   7070: dup
    //   7071: bipush #61
    //   7073: ldc 67110912
    //   7075: iastore
    //   7076: dup
    //   7077: bipush #62
    //   7079: sipush #2048
    //   7082: iastore
    //   7083: dup
    //   7084: bipush #63
    //   7086: ldc 2097154
    //   7088: iastore
    //   7089: astore #14
    //   7091: bipush #64
    //   7093: newarray int
    //   7095: dup
    //   7096: iconst_0
    //   7097: ldc 268439616
    //   7099: iastore
    //   7100: dup
    //   7101: iconst_1
    //   7102: sipush #4096
    //   7105: iastore
    //   7106: dup
    //   7107: iconst_2
    //   7108: ldc 262144
    //   7110: iastore
    //   7111: dup
    //   7112: iconst_3
    //   7113: ldc 268701760
    //   7115: iastore
    //   7116: dup
    //   7117: iconst_4
    //   7118: ldc 268435456
    //   7120: iastore
    //   7121: dup
    //   7122: iconst_5
    //   7123: ldc 268439616
    //   7125: iastore
    //   7126: dup
    //   7127: bipush #6
    //   7129: bipush #64
    //   7131: iastore
    //   7132: dup
    //   7133: bipush #7
    //   7135: ldc 268435456
    //   7137: iastore
    //   7138: dup
    //   7139: bipush #8
    //   7141: ldc 262208
    //   7143: iastore
    //   7144: dup
    //   7145: bipush #9
    //   7147: ldc 268697600
    //   7149: iastore
    //   7150: dup
    //   7151: bipush #10
    //   7153: ldc 268701760
    //   7155: iastore
    //   7156: dup
    //   7157: bipush #11
    //   7159: ldc 266240
    //   7161: iastore
    //   7162: dup
    //   7163: bipush #12
    //   7165: ldc 268701696
    //   7167: iastore
    //   7168: dup
    //   7169: bipush #13
    //   7171: ldc 266304
    //   7173: iastore
    //   7174: dup
    //   7175: bipush #14
    //   7177: sipush #4096
    //   7180: iastore
    //   7181: dup
    //   7182: bipush #15
    //   7184: bipush #64
    //   7186: iastore
    //   7187: dup
    //   7188: bipush #16
    //   7190: ldc 268697600
    //   7192: iastore
    //   7193: dup
    //   7194: bipush #17
    //   7196: ldc 268435520
    //   7198: iastore
    //   7199: dup
    //   7200: bipush #18
    //   7202: ldc 268439552
    //   7204: iastore
    //   7205: dup
    //   7206: bipush #19
    //   7208: sipush #4160
    //   7211: iastore
    //   7212: dup
    //   7213: bipush #20
    //   7215: ldc 266240
    //   7217: iastore
    //   7218: dup
    //   7219: bipush #21
    //   7221: ldc 262208
    //   7223: iastore
    //   7224: dup
    //   7225: bipush #22
    //   7227: ldc 268697664
    //   7229: iastore
    //   7230: dup
    //   7231: bipush #23
    //   7233: ldc 268701696
    //   7235: iastore
    //   7236: dup
    //   7237: bipush #24
    //   7239: sipush #4160
    //   7242: iastore
    //   7243: dup
    //   7244: bipush #25
    //   7246: iconst_0
    //   7247: iastore
    //   7248: dup
    //   7249: bipush #26
    //   7251: iconst_0
    //   7252: iastore
    //   7253: dup
    //   7254: bipush #27
    //   7256: ldc 268697664
    //   7258: iastore
    //   7259: dup
    //   7260: bipush #28
    //   7262: ldc 268435520
    //   7264: iastore
    //   7265: dup
    //   7266: bipush #29
    //   7268: ldc 268439552
    //   7270: iastore
    //   7271: dup
    //   7272: bipush #30
    //   7274: ldc 266304
    //   7276: iastore
    //   7277: dup
    //   7278: bipush #31
    //   7280: ldc 262144
    //   7282: iastore
    //   7283: dup
    //   7284: bipush #32
    //   7286: ldc 266304
    //   7288: iastore
    //   7289: dup
    //   7290: bipush #33
    //   7292: ldc 262144
    //   7294: iastore
    //   7295: dup
    //   7296: bipush #34
    //   7298: ldc 268701696
    //   7300: iastore
    //   7301: dup
    //   7302: bipush #35
    //   7304: sipush #4096
    //   7307: iastore
    //   7308: dup
    //   7309: bipush #36
    //   7311: bipush #64
    //   7313: iastore
    //   7314: dup
    //   7315: bipush #37
    //   7317: ldc 268697664
    //   7319: iastore
    //   7320: dup
    //   7321: bipush #38
    //   7323: sipush #4096
    //   7326: iastore
    //   7327: dup
    //   7328: bipush #39
    //   7330: ldc 266304
    //   7332: iastore
    //   7333: dup
    //   7334: bipush #40
    //   7336: ldc 268439552
    //   7338: iastore
    //   7339: dup
    //   7340: bipush #41
    //   7342: bipush #64
    //   7344: iastore
    //   7345: dup
    //   7346: bipush #42
    //   7348: ldc 268435520
    //   7350: iastore
    //   7351: dup
    //   7352: bipush #43
    //   7354: ldc 268697600
    //   7356: iastore
    //   7357: dup
    //   7358: bipush #44
    //   7360: ldc 268697664
    //   7362: iastore
    //   7363: dup
    //   7364: bipush #45
    //   7366: ldc 268435456
    //   7368: iastore
    //   7369: dup
    //   7370: bipush #46
    //   7372: ldc 262144
    //   7374: iastore
    //   7375: dup
    //   7376: bipush #47
    //   7378: ldc 268439616
    //   7380: iastore
    //   7381: dup
    //   7382: bipush #48
    //   7384: iconst_0
    //   7385: iastore
    //   7386: dup
    //   7387: bipush #49
    //   7389: ldc 268701760
    //   7391: iastore
    //   7392: dup
    //   7393: bipush #50
    //   7395: ldc 262208
    //   7397: iastore
    //   7398: dup
    //   7399: bipush #51
    //   7401: ldc 268435520
    //   7403: iastore
    //   7404: dup
    //   7405: bipush #52
    //   7407: ldc 268697600
    //   7409: iastore
    //   7410: dup
    //   7411: bipush #53
    //   7413: ldc 268439552
    //   7415: iastore
    //   7416: dup
    //   7417: bipush #54
    //   7419: ldc 268439616
    //   7421: iastore
    //   7422: dup
    //   7423: bipush #55
    //   7425: iconst_0
    //   7426: iastore
    //   7427: dup
    //   7428: bipush #56
    //   7430: ldc 268701760
    //   7432: iastore
    //   7433: dup
    //   7434: bipush #57
    //   7436: ldc 266240
    //   7438: iastore
    //   7439: dup
    //   7440: bipush #58
    //   7442: ldc 266240
    //   7444: iastore
    //   7445: dup
    //   7446: bipush #59
    //   7448: sipush #4160
    //   7451: iastore
    //   7452: dup
    //   7453: bipush #60
    //   7455: sipush #4160
    //   7458: iastore
    //   7459: dup
    //   7460: bipush #61
    //   7462: ldc 262208
    //   7464: iastore
    //   7465: dup
    //   7466: bipush #62
    //   7468: ldc 268435456
    //   7470: iastore
    //   7471: dup
    //   7472: bipush #63
    //   7474: ldc 268701696
    //   7476: iastore
    //   7477: astore #15
    //   7479: aload_3
    //   7480: arraylength
    //   7481: istore #16
    //   7483: iconst_2
    //   7484: newarray int
    //   7486: astore #17
    //   7488: iload #16
    //   7490: newarray byte
    //   7492: astore #4
    //   7494: iload #16
    //   7496: bipush #8
    //   7498: idiv
    //   7499: istore #18
    //   7501: iconst_0
    //   7502: istore #19
    //   7504: iload #19
    //   7506: iload #18
    //   7508: if_icmpge -> 8422
    //   7511: iload #19
    //   7513: bipush #8
    //   7515: imul
    //   7516: istore #20
    //   7518: iconst_0
    //   7519: istore #21
    //   7521: iload #21
    //   7523: iconst_2
    //   7524: if_icmpge -> 7609
    //   7527: aload #17
    //   7529: iload #21
    //   7531: aload_3
    //   7532: iload #20
    //   7534: iload #21
    //   7536: iconst_4
    //   7537: imul
    //   7538: iadd
    //   7539: baload
    //   7540: sipush #255
    //   7543: iand
    //   7544: bipush #24
    //   7546: ishl
    //   7547: aload_3
    //   7548: iload #20
    //   7550: iload #21
    //   7552: iconst_4
    //   7553: imul
    //   7554: iadd
    //   7555: iconst_1
    //   7556: iadd
    //   7557: baload
    //   7558: sipush #255
    //   7561: iand
    //   7562: bipush #16
    //   7564: ishl
    //   7565: ior
    //   7566: aload_3
    //   7567: iload #20
    //   7569: iload #21
    //   7571: iconst_4
    //   7572: imul
    //   7573: iadd
    //   7574: iconst_2
    //   7575: iadd
    //   7576: baload
    //   7577: sipush #255
    //   7580: iand
    //   7581: bipush #8
    //   7583: ishl
    //   7584: ior
    //   7585: aload_3
    //   7586: iload #20
    //   7588: iload #21
    //   7590: iconst_4
    //   7591: imul
    //   7592: iadd
    //   7593: iconst_3
    //   7594: iadd
    //   7595: baload
    //   7596: sipush #255
    //   7599: iand
    //   7600: ior
    //   7601: iastore
    //   7602: iinc #21, 1
    //   7605: iload_2
    //   7606: ifeq -> 7521
    //   7609: iconst_0
    //   7610: istore #26
    //   7612: aload #17
    //   7614: iconst_0
    //   7615: iaload
    //   7616: istore #24
    //   7618: aload #17
    //   7620: iconst_1
    //   7621: iaload
    //   7622: istore #23
    //   7624: iload #24
    //   7626: iconst_4
    //   7627: iushr
    //   7628: iload #23
    //   7630: ixor
    //   7631: ldc 252645135
    //   7633: iand
    //   7634: istore #22
    //   7636: iload #23
    //   7638: iload #22
    //   7640: ixor
    //   7641: istore #23
    //   7643: iload #24
    //   7645: iload #22
    //   7647: iconst_4
    //   7648: ishl
    //   7649: ixor
    //   7650: istore #24
    //   7652: iload #24
    //   7654: bipush #16
    //   7656: iushr
    //   7657: iload #23
    //   7659: ixor
    //   7660: ldc 65535
    //   7662: iand
    //   7663: istore #22
    //   7665: iload #23
    //   7667: iload #22
    //   7669: ixor
    //   7670: istore #23
    //   7672: iload #24
    //   7674: iload #22
    //   7676: bipush #16
    //   7678: ishl
    //   7679: ixor
    //   7680: istore #24
    //   7682: iload #23
    //   7684: iconst_2
    //   7685: iushr
    //   7686: iload #24
    //   7688: ixor
    //   7689: ldc 858993459
    //   7691: iand
    //   7692: istore #22
    //   7694: iload #24
    //   7696: iload #22
    //   7698: ixor
    //   7699: istore #24
    //   7701: iload #23
    //   7703: iload #22
    //   7705: iconst_2
    //   7706: ishl
    //   7707: ixor
    //   7708: istore #23
    //   7710: iload #23
    //   7712: bipush #8
    //   7714: iushr
    //   7715: iload #24
    //   7717: ixor
    //   7718: ldc 16711935
    //   7720: iand
    //   7721: istore #22
    //   7723: iload #24
    //   7725: iload #22
    //   7727: ixor
    //   7728: istore #24
    //   7730: iload #23
    //   7732: iload #22
    //   7734: bipush #8
    //   7736: ishl
    //   7737: ixor
    //   7738: istore #23
    //   7740: iload #23
    //   7742: iconst_1
    //   7743: ishl
    //   7744: iload #23
    //   7746: bipush #31
    //   7748: iushr
    //   7749: iconst_1
    //   7750: iand
    //   7751: ior
    //   7752: istore #23
    //   7754: iload #24
    //   7756: iload #23
    //   7758: ixor
    //   7759: ldc -1431655766
    //   7761: iand
    //   7762: istore #22
    //   7764: iload #24
    //   7766: iload #22
    //   7768: ixor
    //   7769: istore #24
    //   7771: iload #23
    //   7773: iload #22
    //   7775: ixor
    //   7776: istore #23
    //   7778: iload #24
    //   7780: iconst_1
    //   7781: ishl
    //   7782: iload #24
    //   7784: bipush #31
    //   7786: iushr
    //   7787: iconst_1
    //   7788: iand
    //   7789: ior
    //   7790: istore #24
    //   7792: iconst_0
    //   7793: istore #25
    //   7795: iload #25
    //   7797: bipush #8
    //   7799: if_icmpge -> 8137
    //   7802: iload #23
    //   7804: bipush #28
    //   7806: ishl
    //   7807: iload #23
    //   7809: iconst_4
    //   7810: iushr
    //   7811: ior
    //   7812: istore #22
    //   7814: iload #22
    //   7816: aload #5
    //   7818: iload #26
    //   7820: iinc #26, 1
    //   7823: iaload
    //   7824: ixor
    //   7825: istore #22
    //   7827: aload #14
    //   7829: iload #22
    //   7831: bipush #63
    //   7833: iand
    //   7834: iaload
    //   7835: istore #21
    //   7837: iload #21
    //   7839: aload #12
    //   7841: iload #22
    //   7843: bipush #8
    //   7845: iushr
    //   7846: bipush #63
    //   7848: iand
    //   7849: iaload
    //   7850: ior
    //   7851: istore #21
    //   7853: iload #21
    //   7855: aload #10
    //   7857: iload #22
    //   7859: bipush #16
    //   7861: iushr
    //   7862: bipush #63
    //   7864: iand
    //   7865: iaload
    //   7866: ior
    //   7867: istore #21
    //   7869: iload #21
    //   7871: aload #8
    //   7873: iload #22
    //   7875: bipush #24
    //   7877: iushr
    //   7878: bipush #63
    //   7880: iand
    //   7881: iaload
    //   7882: ior
    //   7883: istore #21
    //   7885: iload #23
    //   7887: aload #5
    //   7889: iload #26
    //   7891: iinc #26, 1
    //   7894: iaload
    //   7895: ixor
    //   7896: istore #22
    //   7898: iload #21
    //   7900: aload #15
    //   7902: iload #22
    //   7904: bipush #63
    //   7906: iand
    //   7907: iaload
    //   7908: ior
    //   7909: istore #21
    //   7911: iload #21
    //   7913: aload #13
    //   7915: iload #22
    //   7917: bipush #8
    //   7919: iushr
    //   7920: bipush #63
    //   7922: iand
    //   7923: iaload
    //   7924: ior
    //   7925: istore #21
    //   7927: iload #21
    //   7929: aload #11
    //   7931: iload #22
    //   7933: bipush #16
    //   7935: iushr
    //   7936: bipush #63
    //   7938: iand
    //   7939: iaload
    //   7940: ior
    //   7941: istore #21
    //   7943: iload #21
    //   7945: aload #9
    //   7947: iload #22
    //   7949: bipush #24
    //   7951: iushr
    //   7952: bipush #63
    //   7954: iand
    //   7955: iaload
    //   7956: ior
    //   7957: istore #21
    //   7959: iload #24
    //   7961: iload #21
    //   7963: ixor
    //   7964: istore #24
    //   7966: iload #24
    //   7968: bipush #28
    //   7970: ishl
    //   7971: iload #24
    //   7973: iconst_4
    //   7974: iushr
    //   7975: ior
    //   7976: istore #22
    //   7978: iload #22
    //   7980: aload #5
    //   7982: iload #26
    //   7984: iinc #26, 1
    //   7987: iaload
    //   7988: ixor
    //   7989: istore #22
    //   7991: aload #14
    //   7993: iload #22
    //   7995: bipush #63
    //   7997: iand
    //   7998: iaload
    //   7999: istore #21
    //   8001: iload #21
    //   8003: aload #12
    //   8005: iload #22
    //   8007: bipush #8
    //   8009: iushr
    //   8010: bipush #63
    //   8012: iand
    //   8013: iaload
    //   8014: ior
    //   8015: istore #21
    //   8017: iload #21
    //   8019: aload #10
    //   8021: iload #22
    //   8023: bipush #16
    //   8025: iushr
    //   8026: bipush #63
    //   8028: iand
    //   8029: iaload
    //   8030: ior
    //   8031: istore #21
    //   8033: iload #21
    //   8035: aload #8
    //   8037: iload #22
    //   8039: bipush #24
    //   8041: iushr
    //   8042: bipush #63
    //   8044: iand
    //   8045: iaload
    //   8046: ior
    //   8047: istore #21
    //   8049: iload #24
    //   8051: aload #5
    //   8053: iload #26
    //   8055: iinc #26, 1
    //   8058: iaload
    //   8059: ixor
    //   8060: istore #22
    //   8062: iload #21
    //   8064: aload #15
    //   8066: iload #22
    //   8068: bipush #63
    //   8070: iand
    //   8071: iaload
    //   8072: ior
    //   8073: istore #21
    //   8075: iload #21
    //   8077: aload #13
    //   8079: iload #22
    //   8081: bipush #8
    //   8083: iushr
    //   8084: bipush #63
    //   8086: iand
    //   8087: iaload
    //   8088: ior
    //   8089: istore #21
    //   8091: iload #21
    //   8093: aload #11
    //   8095: iload #22
    //   8097: bipush #16
    //   8099: iushr
    //   8100: bipush #63
    //   8102: iand
    //   8103: iaload
    //   8104: ior
    //   8105: istore #21
    //   8107: iload #21
    //   8109: aload #9
    //   8111: iload #22
    //   8113: bipush #24
    //   8115: iushr
    //   8116: bipush #63
    //   8118: iand
    //   8119: iaload
    //   8120: ior
    //   8121: istore #21
    //   8123: iload #23
    //   8125: iload #21
    //   8127: ixor
    //   8128: istore #23
    //   8130: iinc #25, 1
    //   8133: iload_2
    //   8134: ifeq -> 7795
    //   8137: iload #23
    //   8139: bipush #31
    //   8141: ishl
    //   8142: iload #23
    //   8144: iconst_1
    //   8145: iushr
    //   8146: ior
    //   8147: istore #23
    //   8149: iload #24
    //   8151: iload #23
    //   8153: ixor
    //   8154: ldc -1431655766
    //   8156: iand
    //   8157: istore #22
    //   8159: iload #24
    //   8161: iload #22
    //   8163: ixor
    //   8164: istore #24
    //   8166: iload #23
    //   8168: iload #22
    //   8170: ixor
    //   8171: istore #23
    //   8173: iload #24
    //   8175: bipush #31
    //   8177: ishl
    //   8178: iload #24
    //   8180: iconst_1
    //   8181: iushr
    //   8182: ior
    //   8183: istore #24
    //   8185: iload #24
    //   8187: bipush #8
    //   8189: iushr
    //   8190: iload #23
    //   8192: ixor
    //   8193: ldc 16711935
    //   8195: iand
    //   8196: istore #22
    //   8198: iload #23
    //   8200: iload #22
    //   8202: ixor
    //   8203: istore #23
    //   8205: iload #24
    //   8207: iload #22
    //   8209: bipush #8
    //   8211: ishl
    //   8212: ixor
    //   8213: istore #24
    //   8215: iload #24
    //   8217: iconst_2
    //   8218: iushr
    //   8219: iload #23
    //   8221: ixor
    //   8222: ldc 858993459
    //   8224: iand
    //   8225: istore #22
    //   8227: iload #23
    //   8229: iload #22
    //   8231: ixor
    //   8232: istore #23
    //   8234: iload #24
    //   8236: iload #22
    //   8238: iconst_2
    //   8239: ishl
    //   8240: ixor
    //   8241: istore #24
    //   8243: iload #23
    //   8245: bipush #16
    //   8247: iushr
    //   8248: iload #24
    //   8250: ixor
    //   8251: ldc 65535
    //   8253: iand
    //   8254: istore #22
    //   8256: iload #24
    //   8258: iload #22
    //   8260: ixor
    //   8261: istore #24
    //   8263: iload #23
    //   8265: iload #22
    //   8267: bipush #16
    //   8269: ishl
    //   8270: ixor
    //   8271: istore #23
    //   8273: iload #23
    //   8275: iconst_4
    //   8276: iushr
    //   8277: iload #24
    //   8279: ixor
    //   8280: ldc 252645135
    //   8282: iand
    //   8283: istore #22
    //   8285: iload #24
    //   8287: iload #22
    //   8289: ixor
    //   8290: istore #24
    //   8292: iload #23
    //   8294: iload #22
    //   8296: iconst_4
    //   8297: ishl
    //   8298: ixor
    //   8299: istore #23
    //   8301: aload #17
    //   8303: iconst_0
    //   8304: iload #23
    //   8306: iastore
    //   8307: aload #17
    //   8309: iconst_1
    //   8310: iload #24
    //   8312: iastore
    //   8313: iload #19
    //   8315: bipush #8
    //   8317: imul
    //   8318: istore #27
    //   8320: iconst_0
    //   8321: istore #28
    //   8323: iload #28
    //   8325: iconst_2
    //   8326: if_icmpge -> 8415
    //   8329: aload #4
    //   8331: iload #27
    //   8333: iload #28
    //   8335: iconst_4
    //   8336: imul
    //   8337: iadd
    //   8338: aload #17
    //   8340: iload #28
    //   8342: iaload
    //   8343: bipush #24
    //   8345: iushr
    //   8346: i2b
    //   8347: bastore
    //   8348: aload #4
    //   8350: iload #27
    //   8352: iload #28
    //   8354: iconst_4
    //   8355: imul
    //   8356: iadd
    //   8357: iconst_1
    //   8358: iadd
    //   8359: aload #17
    //   8361: iload #28
    //   8363: iaload
    //   8364: bipush #16
    //   8366: iushr
    //   8367: i2b
    //   8368: bastore
    //   8369: aload #4
    //   8371: iload #27
    //   8373: iload #28
    //   8375: iconst_4
    //   8376: imul
    //   8377: iadd
    //   8378: iconst_2
    //   8379: iadd
    //   8380: aload #17
    //   8382: iload #28
    //   8384: iaload
    //   8385: bipush #8
    //   8387: iushr
    //   8388: i2b
    //   8389: bastore
    //   8390: aload #4
    //   8392: iload #27
    //   8394: iload #28
    //   8396: iconst_4
    //   8397: imul
    //   8398: iadd
    //   8399: iconst_3
    //   8400: iadd
    //   8401: aload #17
    //   8403: iload #28
    //   8405: iaload
    //   8406: i2b
    //   8407: bastore
    //   8408: iinc #28, 1
    //   8411: iload_2
    //   8412: ifeq -> 8323
    //   8415: iinc #19, 1
    //   8418: iload_2
    //   8419: ifeq -> 7504
    //   8422: new java/math/BigInteger
    //   8425: dup
    //   8426: aload #4
    //   8428: invokespecial <init> : ([B)V
    //   8431: invokevirtual abs : ()Ljava/math/BigInteger;
    //   8434: putstatic burp/Zsej.ZT : Ljava/lang/Object;
    //   8437: new java/lang/StringBuilder
    //   8440: dup
    //   8441: invokespecial <init> : ()V
    //   8444: astore_3
    //   8445: iconst_0
    //   8446: istore #4
    //   8448: iload #4
    //   8450: bipush #32
    //   8452: if_icmpge -> 9787
    //   8455: iload #4
    //   8457: tableswitch default -> 9780, 0 -> 8600, 1 -> 8637, 2 -> 8674, 3 -> 8711, 4 -> 8748, 5 -> 8785, 6 -> 8822, 7 -> 8859, 8 -> 8896, 9 -> 8933, 10 -> 8970, 11 -> 9007, 12 -> 9044, 13 -> 9081, 14 -> 9118, 15 -> 9155, 16 -> 9192, 17 -> 9229, 18 -> 9266, 19 -> 9303, 20 -> 9340, 21 -> 9377, 22 -> 9414, 23 -> 9451, 24 -> 9488, 25 -> 9525, 26 -> 9562, 27 -> 9599, 28 -> 9636, 29 -> 9673, 30 -> 9710, 31 -> 9747
    //   8600: aload_3
    //   8601: getstatic burp/Zbzk.ZS : Ljava/lang/String;
    //   8604: getstatic burp/Zg99.ZZ : Ljava/lang/Object;
    //   8607: checkcast java/math/BigInteger
    //   8610: invokevirtual intValue : ()I
    //   8613: bipush #32
    //   8615: irem
    //   8616: invokestatic abs : (I)I
    //   8619: invokevirtual charAt : (I)C
    //   8622: invokevirtual append : (C)Ljava/lang/StringBuilder;
    //   8625: pop
    //   8626: iload_2
    //   8627: ifeq -> 9780
    //   8630: goto -> 8637
    //   8633: invokestatic a : (Ljava/lang/Throwable;)Ljava/lang/Throwable;
    //   8636: athrow
    //   8637: aload_3
    //   8638: getstatic burp/Zgqi.Zv : Ljava/lang/String;
    //   8641: getstatic burp/Ztgj.ZY : Ljava/lang/Object;
    //   8644: checkcast java/math/BigInteger
    //   8647: invokevirtual intValue : ()I
    //   8650: bipush #32
    //   8652: irem
    //   8653: invokestatic abs : (I)I
    //   8656: invokevirtual charAt : (I)C
    //   8659: invokevirtual append : (C)Ljava/lang/StringBuilder;
    //   8662: pop
    //   8663: iload_2
    //   8664: ifeq -> 9780
    //   8667: goto -> 8674
    //   8670: invokestatic a : (Ljava/lang/Throwable;)Ljava/lang/Throwable;
    //   8673: athrow
    //   8674: aload_3
    //   8675: getstatic burp/Zeh9.ZF : Ljava/lang/String;
    //   8678: getstatic burp/Zsf3.ZH : Ljava/lang/Object;
    //   8681: checkcast java/math/BigInteger
    //   8684: invokevirtual intValue : ()I
    //   8687: bipush #32
    //   8689: irem
    //   8690: invokestatic abs : (I)I
    //   8693: invokevirtual charAt : (I)C
    //   8696: invokevirtual append : (C)Ljava/lang/StringBuilder;
    //   8699: pop
    //   8700: iload_2
    //   8701: ifeq -> 9780
    //   8704: goto -> 8711
    //   8707: invokestatic a : (Ljava/lang/Throwable;)Ljava/lang/Throwable;
    //   8710: athrow
    //   8711: aload_3
    //   8712: getstatic burp/Zmy4.ZS : Ljava/lang/String;
    //   8715: getstatic burp/Zstf.ZA : Ljava/lang/Object;
    //   8718: checkcast java/math/BigInteger
    //   8721: invokevirtual intValue : ()I
    //   8724: bipush #32
    //   8726: irem
    //   8727: invokestatic abs : (I)I
    //   8730: invokevirtual charAt : (I)C
    //   8733: invokevirtual append : (C)Ljava/lang/StringBuilder;
    //   8736: pop
    //   8737: iload_2
    //   8738: ifeq -> 9780
    //   8741: goto -> 8748
    //   8744: invokestatic a : (Ljava/lang/Throwable;)Ljava/lang/Throwable;
    //   8747: athrow
    //   8748: aload_3
    //   8749: getstatic burp/Zxt5.ZM : Ljava/lang/String;
    //   8752: getstatic burp/Zlo5.Zf : Ljava/lang/Object;
    //   8755: checkcast java/math/BigInteger
    //   8758: invokevirtual intValue : ()I
    //   8761: bipush #32
    //   8763: irem
    //   8764: invokestatic abs : (I)I
    //   8767: invokevirtual charAt : (I)C
    //   8770: invokevirtual append : (C)Ljava/lang/StringBuilder;
    //   8773: pop
    //   8774: iload_2
    //   8775: ifeq -> 9780
    //   8778: goto -> 8785
    //   8781: invokestatic a : (Ljava/lang/Throwable;)Ljava/lang/Throwable;
    //   8784: athrow
    //   8785: aload_3
    //   8786: getstatic burp/Zs0b.ZT : Ljava/lang/String;
    //   8789: getstatic burp/Zg_y.ZR : Ljava/lang/Object;
    //   8792: checkcast java/math/BigInteger
    //   8795: invokevirtual intValue : ()I
    //   8798: bipush #32
    //   8800: irem
    //   8801: invokestatic abs : (I)I
    //   8804: invokevirtual charAt : (I)C
    //   8807: invokevirtual append : (C)Ljava/lang/StringBuilder;
    //   8810: pop
    //   8811: iload_2
    //   8812: ifeq -> 9780
    //   8815: goto -> 8822
    //   8818: invokestatic a : (Ljava/lang/Throwable;)Ljava/lang/Throwable;
    //   8821: athrow
    //   8822: aload_3
    //   8823: getstatic burp/Zezn.Ze : Ljava/lang/String;
    //   8826: getstatic burp/Zlv6.ZN : Ljava/lang/Object;
    //   8829: checkcast java/math/BigInteger
    //   8832: invokevirtual intValue : ()I
    //   8835: bipush #32
    //   8837: irem
    //   8838: invokestatic abs : (I)I
    //   8841: invokevirtual charAt : (I)C
    //   8844: invokevirtual append : (C)Ljava/lang/StringBuilder;
    //   8847: pop
    //   8848: iload_2
    //   8849: ifeq -> 9780
    //   8852: goto -> 8859
    //   8855: invokestatic a : (Ljava/lang/Throwable;)Ljava/lang/Throwable;
    //   8858: athrow
    //   8859: aload_3
    //   8860: getstatic burp/Zry9.ZW : Ljava/lang/String;
    //   8863: getstatic burp/Zebu.Zu : Ljava/lang/Object;
    //   8866: checkcast java/math/BigInteger
    //   8869: invokevirtual intValue : ()I
    //   8872: bipush #32
    //   8874: irem
    //   8875: invokestatic abs : (I)I
    //   8878: invokevirtual charAt : (I)C
    //   8881: invokevirtual append : (C)Ljava/lang/StringBuilder;
    //   8884: pop
    //   8885: iload_2
    //   8886: ifeq -> 9780
    //   8889: goto -> 8896
    //   8892: invokestatic a : (Ljava/lang/Throwable;)Ljava/lang/Throwable;
    //   8895: athrow
    //   8896: aload_3
    //   8897: getstatic burp/Zex.Zn : Ljava/lang/String;
    //   8900: getstatic burp/Zzrb.Zj : Ljava/lang/Object;
    //   8903: checkcast java/math/BigInteger
    //   8906: invokevirtual intValue : ()I
    //   8909: bipush #32
    //   8911: irem
    //   8912: invokestatic abs : (I)I
    //   8915: invokevirtual charAt : (I)C
    //   8918: invokevirtual append : (C)Ljava/lang/StringBuilder;
    //   8921: pop
    //   8922: iload_2
    //   8923: ifeq -> 9780
    //   8926: goto -> 8933
    //   8929: invokestatic a : (Ljava/lang/Throwable;)Ljava/lang/Throwable;
    //   8932: athrow
    //   8933: aload_3
    //   8934: getstatic burp/Zkf9.ZS : Ljava/lang/String;
    //   8937: getstatic burp/Ze54.Zx : Ljava/lang/Object;
    //   8940: checkcast java/math/BigInteger
    //   8943: invokevirtual intValue : ()I
    //   8946: bipush #32
    //   8948: irem
    //   8949: invokestatic abs : (I)I
    //   8952: invokevirtual charAt : (I)C
    //   8955: invokevirtual append : (C)Ljava/lang/StringBuilder;
    //   8958: pop
    //   8959: iload_2
    //   8960: ifeq -> 9780
    //   8963: goto -> 8970
    //   8966: invokestatic a : (Ljava/lang/Throwable;)Ljava/lang/Throwable;
    //   8969: athrow
    //   8970: aload_3
    //   8971: getstatic burp/Zgr4.Zi : Ljava/lang/String;
    //   8974: getstatic burp/Zm06.ZU : Ljava/lang/Object;
    //   8977: checkcast java/math/BigInteger
    //   8980: invokevirtual intValue : ()I
    //   8983: bipush #32
    //   8985: irem
    //   8986: invokestatic abs : (I)I
    //   8989: invokevirtual charAt : (I)C
    //   8992: invokevirtual append : (C)Ljava/lang/StringBuilder;
    //   8995: pop
    //   8996: iload_2
    //   8997: ifeq -> 9780
    //   9000: goto -> 9007
    //   9003: invokestatic a : (Ljava/lang/Throwable;)Ljava/lang/Throwable;
    //   9006: athrow
    //   9007: aload_3
    //   9008: getstatic burp/Zkk6.ZP : Ljava/lang/String;
    //   9011: getstatic burp/Zbo2.ZQ : Ljava/lang/Object;
    //   9014: checkcast java/math/BigInteger
    //   9017: invokevirtual intValue : ()I
    //   9020: bipush #32
    //   9022: irem
    //   9023: invokestatic abs : (I)I
    //   9026: invokevirtual charAt : (I)C
    //   9029: invokevirtual append : (C)Ljava/lang/StringBuilder;
    //   9032: pop
    //   9033: iload_2
    //   9034: ifeq -> 9780
    //   9037: goto -> 9044
    //   9040: invokestatic a : (Ljava/lang/Throwable;)Ljava/lang/Throwable;
    //   9043: athrow
    //   9044: aload_3
    //   9045: getstatic burp/Zsgj.ZN : Ljava/lang/String;
    //   9048: getstatic burp/Zec0.Zg : Ljava/lang/Object;
    //   9051: checkcast java/math/BigInteger
    //   9054: invokevirtual intValue : ()I
    //   9057: bipush #32
    //   9059: irem
    //   9060: invokestatic abs : (I)I
    //   9063: invokevirtual charAt : (I)C
    //   9066: invokevirtual append : (C)Ljava/lang/StringBuilder;
    //   9069: pop
    //   9070: iload_2
    //   9071: ifeq -> 9780
    //   9074: goto -> 9081
    //   9077: invokestatic a : (Ljava/lang/Throwable;)Ljava/lang/Throwable;
    //   9080: athrow
    //   9081: aload_3
    //   9082: getstatic burp/Zxx4.Zq : Ljava/lang/String;
    //   9085: getstatic burp/Zlv6.ZN : Ljava/lang/Object;
    //   9088: checkcast java/math/BigInteger
    //   9091: invokevirtual intValue : ()I
    //   9094: bipush #32
    //   9096: irem
    //   9097: invokestatic abs : (I)I
    //   9100: invokevirtual charAt : (I)C
    //   9103: invokevirtual append : (C)Ljava/lang/StringBuilder;
    //   9106: pop
    //   9107: iload_2
    //   9108: ifeq -> 9780
    //   9111: goto -> 9118
    //   9114: invokestatic a : (Ljava/lang/Throwable;)Ljava/lang/Throwable;
    //   9117: athrow
    //   9118: aload_3
    //   9119: getstatic burp/Ztid.Zz : Ljava/lang/String;
    //   9122: getstatic burp/Zxzj.ZO : Ljava/lang/Object;
    //   9125: checkcast java/math/BigInteger
    //   9128: invokevirtual intValue : ()I
    //   9131: bipush #32
    //   9133: irem
    //   9134: invokestatic abs : (I)I
    //   9137: invokevirtual charAt : (I)C
    //   9140: invokevirtual append : (C)Ljava/lang/StringBuilder;
    //   9143: pop
    //   9144: iload_2
    //   9145: ifeq -> 9780
    //   9148: goto -> 9155
    //   9151: invokestatic a : (Ljava/lang/Throwable;)Ljava/lang/Throwable;
    //   9154: athrow
    //   9155: aload_3
    //   9156: getstatic burp/Zmr7.Zo : Ljava/lang/String;
    //   9159: getstatic burp/Zzqj.Zq : Ljava/lang/Object;
    //   9162: checkcast java/math/BigInteger
    //   9165: invokevirtual intValue : ()I
    //   9168: bipush #32
    //   9170: irem
    //   9171: invokestatic abs : (I)I
    //   9174: invokevirtual charAt : (I)C
    //   9177: invokevirtual append : (C)Ljava/lang/StringBuilder;
    //   9180: pop
    //   9181: iload_2
    //   9182: ifeq -> 9780
    //   9185: goto -> 9192
    //   9188: invokestatic a : (Ljava/lang/Throwable;)Ljava/lang/Throwable;
    //   9191: athrow
    //   9192: aload_3
    //   9193: getstatic burp/Ztw4.Zb : Ljava/lang/String;
    //   9196: getstatic burp/Zelz.Z_ : Ljava/lang/Object;
    //   9199: checkcast java/math/BigInteger
    //   9202: invokevirtual intValue : ()I
    //   9205: bipush #32
    //   9207: irem
    //   9208: invokestatic abs : (I)I
    //   9211: invokevirtual charAt : (I)C
    //   9214: invokevirtual append : (C)Ljava/lang/StringBuilder;
    //   9217: pop
    //   9218: iload_2
    //   9219: ifeq -> 9780
    //   9222: goto -> 9229
    //   9225: invokestatic a : (Ljava/lang/Throwable;)Ljava/lang/Throwable;
    //   9228: athrow
    //   9229: aload_3
    //   9230: getstatic burp/Zmha.Zo : Ljava/lang/String;
    //   9233: getstatic burp/Zti7.Zw : Ljava/lang/Object;
    //   9236: checkcast java/math/BigInteger
    //   9239: invokevirtual intValue : ()I
    //   9242: bipush #32
    //   9244: irem
    //   9245: invokestatic abs : (I)I
    //   9248: invokevirtual charAt : (I)C
    //   9251: invokevirtual append : (C)Ljava/lang/StringBuilder;
    //   9254: pop
    //   9255: iload_2
    //   9256: ifeq -> 9780
    //   9259: goto -> 9266
    //   9262: invokestatic a : (Ljava/lang/Throwable;)Ljava/lang/Throwable;
    //   9265: athrow
    //   9266: aload_3
    //   9267: getstatic burp/Zkfz.Zs : Ljava/lang/String;
    //   9270: getstatic burp/Zbu.ZW : Ljava/lang/Object;
    //   9273: checkcast java/math/BigInteger
    //   9276: invokevirtual intValue : ()I
    //   9279: bipush #32
    //   9281: irem
    //   9282: invokestatic abs : (I)I
    //   9285: invokevirtual charAt : (I)C
    //   9288: invokevirtual append : (C)Ljava/lang/StringBuilder;
    //   9291: pop
    //   9292: iload_2
    //   9293: ifeq -> 9780
    //   9296: goto -> 9303
    //   9299: invokestatic a : (Ljava/lang/Throwable;)Ljava/lang/Throwable;
    //   9302: athrow
    //   9303: aload_3
    //   9304: getstatic burp/Zt5t.ZK : Ljava/lang/String;
    //   9307: getstatic burp/Zx0t.Zt : Ljava/lang/Object;
    //   9310: checkcast java/math/BigInteger
    //   9313: invokevirtual intValue : ()I
    //   9316: bipush #32
    //   9318: irem
    //   9319: invokestatic abs : (I)I
    //   9322: invokevirtual charAt : (I)C
    //   9325: invokevirtual append : (C)Ljava/lang/StringBuilder;
    //   9328: pop
    //   9329: iload_2
    //   9330: ifeq -> 9780
    //   9333: goto -> 9340
    //   9336: invokestatic a : (Ljava/lang/Throwable;)Ljava/lang/Throwable;
    //   9339: athrow
    //   9340: aload_3
    //   9341: getstatic burp/Ztdd.ZA : Ljava/lang/String;
    //   9344: getstatic burp/Zzi3.ZJ : Ljava/lang/Object;
    //   9347: checkcast java/math/BigInteger
    //   9350: invokevirtual intValue : ()I
    //   9353: bipush #32
    //   9355: irem
    //   9356: invokestatic abs : (I)I
    //   9359: invokevirtual charAt : (I)C
    //   9362: invokevirtual append : (C)Ljava/lang/StringBuilder;
    //   9365: pop
    //   9366: iload_2
    //   9367: ifeq -> 9780
    //   9370: goto -> 9377
    //   9373: invokestatic a : (Ljava/lang/Throwable;)Ljava/lang/Throwable;
    //   9376: athrow
    //   9377: aload_3
    //   9378: getstatic burp/Zmtr.Zd : Ljava/lang/String;
    //   9381: getstatic burp/Zb9d.Ze : Ljava/lang/Object;
    //   9384: checkcast java/math/BigInteger
    //   9387: invokevirtual intValue : ()I
    //   9390: bipush #32
    //   9392: irem
    //   9393: invokestatic abs : (I)I
    //   9396: invokevirtual charAt : (I)C
    //   9399: invokevirtual append : (C)Ljava/lang/StringBuilder;
    //   9402: pop
    //   9403: iload_2
    //   9404: ifeq -> 9780
    //   9407: goto -> 9414
    //   9410: invokestatic a : (Ljava/lang/Throwable;)Ljava/lang/Throwable;
    //   9413: athrow
    //   9414: aload_3
    //   9415: getstatic burp/Zb8x.Zp : Ljava/lang/String;
    //   9418: getstatic burp/Zg2z.ZU : Ljava/lang/Object;
    //   9421: checkcast java/math/BigInteger
    //   9424: invokevirtual intValue : ()I
    //   9427: bipush #32
    //   9429: irem
    //   9430: invokestatic abs : (I)I
    //   9433: invokevirtual charAt : (I)C
    //   9436: invokevirtual append : (C)Ljava/lang/StringBuilder;
    //   9439: pop
    //   9440: iload_2
    //   9441: ifeq -> 9780
    //   9444: goto -> 9451
    //   9447: invokestatic a : (Ljava/lang/Throwable;)Ljava/lang/Throwable;
    //   9450: athrow
    //   9451: aload_3
    //   9452: getstatic burp/Ze13.Zg : Ljava/lang/String;
    //   9455: getstatic burp/Zldx.ZM : Ljava/lang/Object;
    //   9458: checkcast java/math/BigInteger
    //   9461: invokevirtual intValue : ()I
    //   9464: bipush #32
    //   9466: irem
    //   9467: invokestatic abs : (I)I
    //   9470: invokevirtual charAt : (I)C
    //   9473: invokevirtual append : (C)Ljava/lang/StringBuilder;
    //   9476: pop
    //   9477: iload_2
    //   9478: ifeq -> 9780
    //   9481: goto -> 9488
    //   9484: invokestatic a : (Ljava/lang/Throwable;)Ljava/lang/Throwable;
    //   9487: athrow
    //   9488: aload_3
    //   9489: getstatic burp/Zb20.ZL : Ljava/lang/String;
    //   9492: getstatic burp/Zg8v.ZB : Ljava/lang/Object;
    //   9495: checkcast java/math/BigInteger
    //   9498: invokevirtual intValue : ()I
    //   9501: bipush #32
    //   9503: irem
    //   9504: invokestatic abs : (I)I
    //   9507: invokevirtual charAt : (I)C
    //   9510: invokevirtual append : (C)Ljava/lang/StringBuilder;
    //   9513: pop
    //   9514: iload_2
    //   9515: ifeq -> 9780
    //   9518: goto -> 9525
    //   9521: invokestatic a : (Ljava/lang/Throwable;)Ljava/lang/Throwable;
    //   9524: athrow
    //   9525: aload_3
    //   9526: getstatic burp/Zty4.Zu : Ljava/lang/String;
    //   9529: getstatic burp/Zscz.ZN : Ljava/lang/Object;
    //   9532: checkcast java/math/BigInteger
    //   9535: invokevirtual intValue : ()I
    //   9538: bipush #32
    //   9540: irem
    //   9541: invokestatic abs : (I)I
    //   9544: invokevirtual charAt : (I)C
    //   9547: invokevirtual append : (C)Ljava/lang/StringBuilder;
    //   9550: pop
    //   9551: iload_2
    //   9552: ifeq -> 9780
    //   9555: goto -> 9562
    //   9558: invokestatic a : (Ljava/lang/Throwable;)Ljava/lang/Throwable;
    //   9561: athrow
    //   9562: aload_3
    //   9563: getstatic burp/Zgia.Zh : Ljava/lang/String;
    //   9566: getstatic burp/Zls0.ZZ : Ljava/lang/Object;
    //   9569: checkcast java/math/BigInteger
    //   9572: invokevirtual intValue : ()I
    //   9575: bipush #32
    //   9577: irem
    //   9578: invokestatic abs : (I)I
    //   9581: invokevirtual charAt : (I)C
    //   9584: invokevirtual append : (C)Ljava/lang/StringBuilder;
    //   9587: pop
    //   9588: iload_2
    //   9589: ifeq -> 9780
    //   9592: goto -> 9599
    //   9595: invokestatic a : (Ljava/lang/Throwable;)Ljava/lang/Throwable;
    //   9598: athrow
    //   9599: aload_3
    //   9600: getstatic burp/Zl8y.ZY : Ljava/lang/String;
    //   9603: getstatic burp/Zlp7.ZM : Ljava/lang/Object;
    //   9606: checkcast java/math/BigInteger
    //   9609: invokevirtual intValue : ()I
    //   9612: bipush #32
    //   9614: irem
    //   9615: invokestatic abs : (I)I
    //   9618: invokevirtual charAt : (I)C
    //   9621: invokevirtual append : (C)Ljava/lang/StringBuilder;
    //   9624: pop
    //   9625: iload_2
    //   9626: ifeq -> 9780
    //   9629: goto -> 9636
    //   9632: invokestatic a : (Ljava/lang/Throwable;)Ljava/lang/Throwable;
    //   9635: athrow
    //   9636: aload_3
    //   9637: getstatic burp/Zewq.ZV : Ljava/lang/String;
    //   9640: getstatic burp/Zre4.Zx : Ljava/lang/Object;
    //   9643: checkcast java/math/BigInteger
    //   9646: invokevirtual intValue : ()I
    //   9649: bipush #32
    //   9651: irem
    //   9652: invokestatic abs : (I)I
    //   9655: invokevirtual charAt : (I)C
    //   9658: invokevirtual append : (C)Ljava/lang/StringBuilder;
    //   9661: pop
    //   9662: iload_2
    //   9663: ifeq -> 9780
    //   9666: goto -> 9673
    //   9669: invokestatic a : (Ljava/lang/Throwable;)Ljava/lang/Throwable;
    //   9672: athrow
    //   9673: aload_3
    //   9674: getstatic burp/Zli5.Zq : Ljava/lang/String;
    //   9677: getstatic burp/Ztfr.Zr : Ljava/lang/Object;
    //   9680: checkcast java/math/BigInteger
    //   9683: invokevirtual intValue : ()I
    //   9686: bipush #32
    //   9688: irem
    //   9689: invokestatic abs : (I)I
    //   9692: invokevirtual charAt : (I)C
    //   9695: invokevirtual append : (C)Ljava/lang/StringBuilder;
    //   9698: pop
    //   9699: iload_2
    //   9700: ifeq -> 9780
    //   9703: goto -> 9710
    //   9706: invokestatic a : (Ljava/lang/Throwable;)Ljava/lang/Throwable;
    //   9709: athrow
    //   9710: aload_3
    //   9711: getstatic burp/Zmzh.Zm : Ljava/lang/String;
    //   9714: getstatic burp/Ze54.Zx : Ljava/lang/Object;
    //   9717: checkcast java/math/BigInteger
    //   9720: invokevirtual intValue : ()I
    //   9723: bipush #32
    //   9725: irem
    //   9726: invokestatic abs : (I)I
    //   9729: invokevirtual charAt : (I)C
    //   9732: invokevirtual append : (C)Ljava/lang/StringBuilder;
    //   9735: pop
    //   9736: iload_2
    //   9737: ifeq -> 9780
    //   9740: goto -> 9747
    //   9743: invokestatic a : (Ljava/lang/Throwable;)Ljava/lang/Throwable;
    //   9746: athrow
    //   9747: aload_3
    //   9748: getstatic burp/Zmou.ZP : Ljava/lang/String;
    //   9751: getstatic burp/Zxtc.ZF : Ljava/lang/Object;
    //   9754: checkcast java/math/BigInteger
    //   9757: invokevirtual intValue : ()I
    //   9760: bipush #32
    //   9762: irem
    //   9763: invokestatic abs : (I)I
    //   9766: invokevirtual charAt : (I)C
    //   9769: invokevirtual append : (C)Ljava/lang/StringBuilder;
    //   9772: pop
    //   9773: goto -> 9780
    //   9776: invokestatic a : (Ljava/lang/Throwable;)Ljava/lang/Throwable;
    //   9779: athrow
    //   9780: iinc #4, 1
    //   9783: iload_2
    //   9784: ifeq -> 8448
    //   9787: aload_3
    //   9788: invokevirtual toString : ()Ljava/lang/String;
    //   9791: putstatic burp/Zk8g.ZH : Ljava/lang/String;
    //   9794: sipush #-30958
    //   9797: sipush #3234
    //   9800: invokestatic a : (II)Ljava/lang/String;
    //   9803: iconst_1
    //   9804: ldc burp/Zzky
    //   9806: invokevirtual getClassLoader : ()Ljava/lang/ClassLoader;
    //   9809: invokestatic forName : (Ljava/lang/String;ZLjava/lang/ClassLoader;)Ljava/lang/Class;
    //   9812: invokevirtual getDeclaredFields : ()[Ljava/lang/reflect/Field;
    //   9815: astore #4
    //   9817: aload #4
    //   9819: arraylength
    //   9820: istore #5
    //   9822: iconst_0
    //   9823: istore #6
    //   9825: iload #6
    //   9827: iload #5
    //   9829: if_icmpge -> 9967
    //   9832: aload #4
    //   9834: iload #6
    //   9836: aaload
    //   9837: astore #7
    //   9839: aload #7
    //   9841: invokevirtual getModifiers : ()I
    //   9844: invokestatic isStatic : (I)Z
    //   9847: ifne -> 9857
    //   9850: goto -> 9960
    //   9853: invokestatic a : (Ljava/lang/Throwable;)Ljava/lang/Throwable;
    //   9856: athrow
    //   9857: aload #7
    //   9859: invokevirtual getType : ()Ljava/lang/Class;
    //   9862: astore #8
    //   9864: aload #8
    //   9866: ifnull -> 9947
    //   9869: aload #8
    //   9871: invokevirtual isPrimitive : ()Z
    //   9874: ifne -> 9947
    //   9877: goto -> 9884
    //   9880: invokestatic a : (Ljava/lang/Throwable;)Ljava/lang/Throwable;
    //   9883: athrow
    //   9884: aload #8
    //   9886: invokevirtual getPackage : ()Ljava/lang/Package;
    //   9889: ifnull -> 9947
    //   9892: goto -> 9899
    //   9895: invokestatic a : (Ljava/lang/Throwable;)Ljava/lang/Throwable;
    //   9898: athrow
    //   9899: aload #8
    //   9901: invokevirtual getPackage : ()Ljava/lang/Package;
    //   9904: invokevirtual getName : ()Ljava/lang/String;
    //   9907: ifnull -> 9947
    //   9910: goto -> 9917
    //   9913: invokestatic a : (Ljava/lang/Throwable;)Ljava/lang/Throwable;
    //   9916: athrow
    //   9917: aload #8
    //   9919: invokevirtual getPackage : ()Ljava/lang/Package;
    //   9922: invokevirtual getName : ()Ljava/lang/String;
    //   9925: sipush #-30955
    //   9928: sipush #-20548
    //   9931: invokestatic a : (II)Ljava/lang/String;
    //   9934: invokevirtual startsWith : (Ljava/lang/String;)Z
    //   9937: ifne -> 9947
    //   9940: goto -> 9947
    //   9943: invokestatic a : (Ljava/lang/Throwable;)Ljava/lang/Throwable;
    //   9946: athrow
    //   9947: aload #7
    //   9949: iconst_1
    //   9950: invokevirtual setAccessible : (Z)V
    //   9953: aload #7
    //   9955: aconst_null
    //   9956: invokevirtual get : (Ljava/lang/Object;)Ljava/lang/Object;
    //   9959: pop
    //   9960: iinc #6, 1
    //   9963: iload_2
    //   9964: ifeq -> 9825
    //   9967: sipush #-30946
    //   9970: sipush #-12292
    //   9973: invokestatic a : (II)Ljava/lang/String;
    //   9976: invokestatic forName : (Ljava/lang/String;)Ljava/lang/Class;
    //   9979: invokevirtual getDeclaredMethods : ()[Ljava/lang/reflect/Method;
    //   9982: astore #4
    //   9984: aload #4
    //   9986: arraylength
    //   9987: istore #5
    //   9989: iconst_0
    //   9990: istore #6
    //   9992: iload #6
    //   9994: iload #5
    //   9996: if_icmpge -> 10108
    //   9999: aload #4
    //   10001: iload #6
    //   10003: aaload
    //   10004: astore #7
    //   10006: aload #7
    //   10008: invokevirtual getParameterTypes : ()[Ljava/lang/Class;
    //   10011: pop
    //   10012: aload #7
    //   10014: invokevirtual getModifiers : ()I
    //   10017: invokestatic isStatic : (I)Z
    //   10020: ifeq -> 10094
    //   10023: aload #7
    //   10025: invokevirtual getParameterTypes : ()[Ljava/lang/Class;
    //   10028: arraylength
    //   10029: iconst_2
    //   10030: if_icmpne -> 10094
    //   10033: goto -> 10040
    //   10036: invokestatic a : (Ljava/lang/Throwable;)Ljava/lang/Throwable;
    //   10039: athrow
    //   10040: aload #7
    //   10042: invokevirtual getReturnType : ()Ljava/lang/Class;
    //   10045: getstatic java/lang/Boolean.TYPE : Ljava/lang/Class;
    //   10048: if_acmpne -> 10094
    //   10051: goto -> 10058
    //   10054: invokestatic a : (Ljava/lang/Throwable;)Ljava/lang/Throwable;
    //   10057: athrow
    //   10058: aload #7
    //   10060: iconst_1
    //   10061: invokevirtual setAccessible : (Z)V
    //   10064: aload #7
    //   10066: aconst_null
    //   10067: iconst_2
    //   10068: anewarray java/lang/Object
    //   10071: dup
    //   10072: iconst_0
    //   10073: aload_0
    //   10074: aastore
    //   10075: dup
    //   10076: iconst_1
    //   10077: aload_1
    //   10078: aastore
    //   10079: invokevirtual invoke : (Ljava/lang/Object;[Ljava/lang/Object;)Ljava/lang/Object;
    //   10082: pop
    //   10083: iload_2
    //   10084: ifeq -> 10108
    //   10087: goto -> 10094
    //   10090: invokestatic a : (Ljava/lang/Throwable;)Ljava/lang/Throwable;
    //   10093: athrow
    //   10094: iinc #6, 1
    //   10097: iload_2
    //   10098: ifeq -> 9992
    //   10101: goto -> 10108
    //   10104: invokestatic a : (Ljava/lang/Throwable;)Ljava/lang/Throwable;
    //   10107: athrow
    //   10108: sipush #-30959
    //   10111: sipush #5274
    //   10114: invokestatic a : (II)Ljava/lang/String;
    //   10117: iconst_1
    //   10118: ldc burp/Zod
    //   10120: invokevirtual getClassLoader : ()Ljava/lang/ClassLoader;
    //   10123: invokestatic forName : (Ljava/lang/String;ZLjava/lang/ClassLoader;)Ljava/lang/Class;
    //   10126: invokevirtual getDeclaredFields : ()[Ljava/lang/reflect/Field;
    //   10129: astore #4
    //   10131: aload #4
    //   10133: arraylength
    //   10134: istore #5
    //   10136: iconst_0
    //   10137: istore #6
    //   10139: iload #6
    //   10141: iload #5
    //   10143: if_icmpge -> 10281
    //   10146: aload #4
    //   10148: iload #6
    //   10150: aaload
    //   10151: astore #7
    //   10153: aload #7
    //   10155: invokevirtual getModifiers : ()I
    //   10158: invokestatic isStatic : (I)Z
    //   10161: ifne -> 10171
    //   10164: goto -> 10274
    //   10167: invokestatic a : (Ljava/lang/Throwable;)Ljava/lang/Throwable;
    //   10170: athrow
    //   10171: aload #7
    //   10173: invokevirtual getType : ()Ljava/lang/Class;
    //   10176: astore #8
    //   10178: aload #8
    //   10180: ifnull -> 10261
    //   10183: aload #8
    //   10185: invokevirtual isPrimitive : ()Z
    //   10188: ifne -> 10261
    //   10191: goto -> 10198
    //   10194: invokestatic a : (Ljava/lang/Throwable;)Ljava/lang/Throwable;
    //   10197: athrow
    //   10198: aload #8
    //   10200: invokevirtual getPackage : ()Ljava/lang/Package;
    //   10203: ifnull -> 10261
    //   10206: goto -> 10213
    //   10209: invokestatic a : (Ljava/lang/Throwable;)Ljava/lang/Throwable;
    //   10212: athrow
    //   10213: aload #8
    //   10215: invokevirtual getPackage : ()Ljava/lang/Package;
    //   10218: invokevirtual getName : ()Ljava/lang/String;
    //   10221: ifnull -> 10261
    //   10224: goto -> 10231
    //   10227: invokestatic a : (Ljava/lang/Throwable;)Ljava/lang/Throwable;
    //   10230: athrow
    //   10231: aload #8
    //   10233: invokevirtual getPackage : ()Ljava/lang/Package;
    //   10236: invokevirtual getName : ()Ljava/lang/String;
    //   10239: sipush #-30947
    //   10242: sipush #3872
    //   10245: invokestatic a : (II)Ljava/lang/String;
    //   10248: invokevirtual startsWith : (Ljava/lang/String;)Z
    //   10251: ifne -> 10261
    //   10254: goto -> 10261
    //   10257: invokestatic a : (Ljava/lang/Throwable;)Ljava/lang/Throwable;
    //   10260: athrow
    //   10261: aload #7
    //   10263: iconst_1
    //   10264: invokevirtual setAccessible : (Z)V
    //   10267: aload #7
    //   10269: aconst_null
    //   10270: invokevirtual get : (Ljava/lang/Object;)Ljava/lang/Object;
    //   10273: pop
    //   10274: iinc #6, 1
    //   10277: iload_2
    //   10278: ifeq -> 10139
    //   10281: sipush #-30945
    //   10284: sipush #6844
    //   10287: invokestatic a : (II)Ljava/lang/String;
    //   10290: invokestatic forName : (Ljava/lang/String;)Ljava/lang/Class;
    //   10293: invokevirtual getDeclaredMethods : ()[Ljava/lang/reflect/Method;
    //   10296: astore #4
    //   10298: aload #4
    //   10300: arraylength
    //   10301: istore #5
    //   10303: iconst_0
    //   10304: istore #6
    //   10306: iload #6
    //   10308: iload #5
    //   10310: if_icmpge -> 10440
    //   10313: aload #4
    //   10315: iload #6
    //   10317: aaload
    //   10318: astore #7
    //   10320: aload #7
    //   10322: invokevirtual getParameterTypes : ()[Ljava/lang/Class;
    //   10325: pop
    //   10326: aload #7
    //   10328: invokevirtual getModifiers : ()I
    //   10331: invokestatic isStatic : (I)Z
    //   10334: ifeq -> 10426
    //   10337: aload #7
    //   10339: invokevirtual getParameterTypes : ()[Ljava/lang/Class;
    //   10342: arraylength
    //   10343: iconst_2
    //   10344: if_icmpne -> 10426
    //   10347: goto -> 10354
    //   10350: invokestatic a : (Ljava/lang/Throwable;)Ljava/lang/Throwable;
    //   10353: athrow
    //   10354: aload #7
    //   10356: invokevirtual getReturnType : ()Ljava/lang/Class;
    //   10359: getstatic java/lang/Boolean.TYPE : Ljava/lang/Class;
    //   10362: if_acmpne -> 10426
    //   10365: goto -> 10372
    //   10368: invokestatic a : (Ljava/lang/Throwable;)Ljava/lang/Throwable;
    //   10371: athrow
    //   10372: aload #7
    //   10374: iconst_1
    //   10375: invokevirtual setAccessible : (Z)V
    //   10378: aload #7
    //   10380: aconst_null
    //   10381: iconst_2
    //   10382: anewarray java/lang/Object
    //   10385: dup
    //   10386: iconst_0
    //   10387: aload_0
    //   10388: aastore
    //   10389: dup
    //   10390: iconst_1
    //   10391: aload_1
    //   10392: ifnonnull -> 10410
    //   10395: goto -> 10402
    //   10398: invokestatic a : (Ljava/lang/Throwable;)Ljava/lang/Throwable;
    //   10401: athrow
    //   10402: aload_1
    //   10403: goto -> 10417
    //   10406: invokestatic a : (Ljava/lang/Throwable;)Ljava/lang/Throwable;
    //   10409: athrow
    //   10410: aload_1
    //   10411: checkcast [B
    //   10414: invokevirtual clone : ()Ljava/lang/Object;
    //   10417: aastore
    //   10418: invokevirtual invoke : (Ljava/lang/Object;[Ljava/lang/Object;)Ljava/lang/Object;
    //   10421: pop
    //   10422: iload_2
    //   10423: ifeq -> 10440
    //   10426: iinc #6, 1
    //   10429: iload_2
    //   10430: ifeq -> 10306
    //   10433: goto -> 10440
    //   10436: invokestatic a : (Ljava/lang/Throwable;)Ljava/lang/Throwable;
    //   10439: athrow
    //   10440: sipush #-30960
    //   10443: sipush #-28113
    //   10446: invokestatic a : (II)Ljava/lang/String;
    //   10449: iconst_1
    //   10450: ldc burp/Zz20
    //   10452: invokevirtual getClassLoader : ()Ljava/lang/ClassLoader;
    //   10455: invokestatic forName : (Ljava/lang/String;ZLjava/lang/ClassLoader;)Ljava/lang/Class;
    //   10458: invokevirtual getDeclaredFields : ()[Ljava/lang/reflect/Field;
    //   10461: astore #4
    //   10463: aload #4
    //   10465: arraylength
    //   10466: istore #5
    //   10468: iconst_0
    //   10469: istore #6
    //   10471: iload #6
    //   10473: iload #5
    //   10475: if_icmpge -> 10613
    //   10478: aload #4
    //   10480: iload #6
    //   10482: aaload
    //   10483: astore #7
    //   10485: aload #7
    //   10487: invokevirtual getModifiers : ()I
    //   10490: invokestatic isStatic : (I)Z
    //   10493: ifne -> 10503
    //   10496: goto -> 10606
    //   10499: invokestatic a : (Ljava/lang/Throwable;)Ljava/lang/Throwable;
    //   10502: athrow
    //   10503: aload #7
    //   10505: invokevirtual getType : ()Ljava/lang/Class;
    //   10508: astore #8
    //   10510: aload #8
    //   10512: ifnull -> 10593
    //   10515: aload #8
    //   10517: invokevirtual isPrimitive : ()Z
    //   10520: ifne -> 10593
    //   10523: goto -> 10530
    //   10526: invokestatic a : (Ljava/lang/Throwable;)Ljava/lang/Throwable;
    //   10529: athrow
    //   10530: aload #8
    //   10532: invokevirtual getPackage : ()Ljava/lang/Package;
    //   10535: ifnull -> 10593
    //   10538: goto -> 10545
    //   10541: invokestatic a : (Ljava/lang/Throwable;)Ljava/lang/Throwable;
    //   10544: athrow
    //   10545: aload #8
    //   10547: invokevirtual getPackage : ()Ljava/lang/Package;
    //   10550: invokevirtual getName : ()Ljava/lang/String;
    //   10553: ifnull -> 10593
    //   10556: goto -> 10563
    //   10559: invokestatic a : (Ljava/lang/Throwable;)Ljava/lang/Throwable;
    //   10562: athrow
    //   10563: aload #8
    //   10565: invokevirtual getPackage : ()Ljava/lang/Package;
    //   10568: invokevirtual getName : ()Ljava/lang/String;
    //   10571: sipush #-30947
    //   10574: sipush #3872
    //   10577: invokestatic a : (II)Ljava/lang/String;
    //   10580: invokevirtual startsWith : (Ljava/lang/String;)Z
    //   10583: ifne -> 10593
    //   10586: goto -> 10593
    //   10589: invokestatic a : (Ljava/lang/Throwable;)Ljava/lang/Throwable;
    //   10592: athrow
    //   10593: aload #7
    //   10595: iconst_1
    //   10596: invokevirtual setAccessible : (Z)V
    //   10599: aload #7
    //   10601: aconst_null
    //   10602: invokevirtual get : (Ljava/lang/Object;)Ljava/lang/Object;
    //   10605: pop
    //   10606: iinc #6, 1
    //   10609: iload_2
    //   10610: ifeq -> 10471
    //   10613: sipush #-30957
    //   10616: sipush #-29919
    //   10619: invokestatic a : (II)Ljava/lang/String;
    //   10622: invokestatic forName : (Ljava/lang/String;)Ljava/lang/Class;
    //   10625: invokevirtual getDeclaredMethods : ()[Ljava/lang/reflect/Method;
    //   10628: astore #4
    //   10630: aload #4
    //   10632: arraylength
    //   10633: istore #5
    //   10635: iconst_0
    //   10636: istore #6
    //   10638: iload #6
    //   10640: iload #5
    //   10642: if_icmpge -> 10775
    //   10645: aload #4
    //   10647: iload #6
    //   10649: aaload
    //   10650: astore #7
    //   10652: aload #7
    //   10654: invokevirtual getParameterTypes : ()[Ljava/lang/Class;
    //   10657: pop
    //   10658: aload #7
    //   10660: invokevirtual getModifiers : ()I
    //   10663: invokestatic isStatic : (I)Z
    //   10666: ifeq -> 10761
    //   10669: aload #7
    //   10671: invokevirtual getParameterTypes : ()[Ljava/lang/Class;
    //   10674: arraylength
    //   10675: iconst_2
    //   10676: if_icmpne -> 10761
    //   10679: goto -> 10686
    //   10682: invokestatic a : (Ljava/lang/Throwable;)Ljava/lang/Throwable;
    //   10685: athrow
    //   10686: aload #7
    //   10688: invokevirtual getReturnType : ()Ljava/lang/Class;
    //   10691: getstatic java/lang/Void.TYPE : Ljava/lang/Class;
    //   10694: invokevirtual equals : (Ljava/lang/Object;)Z
    //   10697: ifeq -> 10761
    //   10700: goto -> 10707
    //   10703: invokestatic a : (Ljava/lang/Throwable;)Ljava/lang/Throwable;
    //   10706: athrow
    //   10707: aload #7
    //   10709: iconst_1
    //   10710: invokevirtual setAccessible : (Z)V
    //   10713: aload #7
    //   10715: aconst_null
    //   10716: iconst_2
    //   10717: anewarray java/lang/Object
    //   10720: dup
    //   10721: iconst_0
    //   10722: aload_0
    //   10723: aastore
    //   10724: dup
    //   10725: iconst_1
    //   10726: aload_1
    //   10727: ifnonnull -> 10745
    //   10730: goto -> 10737
    //   10733: invokestatic a : (Ljava/lang/Throwable;)Ljava/lang/Throwable;
    //   10736: athrow
    //   10737: aload_1
    //   10738: goto -> 10752
    //   10741: invokestatic a : (Ljava/lang/Throwable;)Ljava/lang/Throwable;
    //   10744: athrow
    //   10745: aload_1
    //   10746: checkcast [B
    //   10749: invokevirtual clone : ()Ljava/lang/Object;
    //   10752: aastore
    //   10753: invokevirtual invoke : (Ljava/lang/Object;[Ljava/lang/Object;)Ljava/lang/Object;
    //   10756: pop
    //   10757: iload_2
    //   10758: ifeq -> 10775
    //   10761: iinc #6, 1
    //   10764: iload_2
    //   10765: ifeq -> 10638
    //   10768: goto -> 10775
    //   10771: invokestatic a : (Ljava/lang/Throwable;)Ljava/lang/Throwable;
    //   10774: athrow
    //   10775: getstatic burp/Zzuh.ZX : Ljava/lang/String;
    //   10778: getstatic burp/Zx4k.ZE : Ljava/lang/Object;
    //   10781: checkcast java/math/BigInteger
    //   10784: invokevirtual intValue : ()I
    //   10787: bipush #32
    //   10789: irem
    //   10790: invokestatic abs : (I)I
    //   10793: invokevirtual charAt : (I)C
    //   10796: getstatic burp/Zejj.ZQ : Ljava/lang/String;
    //   10799: getstatic burp/Zm14.ZZ : Ljava/lang/Object;
    //   10802: checkcast java/math/BigInteger
    //   10805: invokevirtual intValue : ()I
    //   10808: bipush #32
    //   10810: irem
    //   10811: invokestatic abs : (I)I
    //   10814: invokevirtual charAt : (I)C
    //   10817: if_icmpgt -> 10924
    //   10820: getstatic burp/Zmou.ZP : Ljava/lang/String;
    //   10823: getstatic burp/Zkmx.Zu : Ljava/lang/Object;
    //   10826: checkcast java/math/BigInteger
    //   10829: invokevirtual intValue : ()I
    //   10832: bipush #32
    //   10834: irem
    //   10835: invokestatic abs : (I)I
    //   10838: invokevirtual charAt : (I)C
    //   10841: getstatic burp/Zgsy.Zv : Ljava/lang/String;
    //   10844: getstatic burp/Zehi.Zb : Ljava/lang/Object;
    //   10847: checkcast java/math/BigInteger
    //   10850: invokevirtual intValue : ()I
    //   10853: bipush #32
    //   10855: irem
    //   10856: invokestatic abs : (I)I
    //   10859: invokevirtual charAt : (I)C
    //   10862: if_icmple -> 10924
    //   10865: goto -> 10872
    //   10868: invokestatic a : (Ljava/lang/Throwable;)Ljava/lang/Throwable;
    //   10871: athrow
    //   10872: getstatic burp/Zrt9.Zc : Ljava/lang/String;
    //   10875: getstatic burp/Zs36.Zs : Ljava/lang/Object;
    //   10878: checkcast java/math/BigInteger
    //   10881: invokevirtual intValue : ()I
    //   10884: bipush #32
    //   10886: irem
    //   10887: invokestatic abs : (I)I
    //   10890: invokevirtual charAt : (I)C
    //   10893: getstatic burp/Zzr5.Zg : Ljava/lang/String;
    //   10896: getstatic burp/Zsn6.Zo : Ljava/lang/Object;
    //   10899: checkcast java/math/BigInteger
    //   10902: invokevirtual intValue : ()I
    //   10905: bipush #32
    //   10907: irem
    //   10908: invokestatic abs : (I)I
    //   10911: invokevirtual charAt : (I)C
    //   10914: if_icmple -> 10932
    //   10917: goto -> 10924
    //   10920: invokestatic a : (Ljava/lang/Throwable;)Ljava/lang/Throwable;
    //   10923: athrow
    //   10924: iconst_1
    //   10925: goto -> 10933
    //   10928: invokestatic a : (Ljava/lang/Throwable;)Ljava/lang/Throwable;
    //   10931: athrow
    //   10932: iconst_0
    //   10933: ireturn
    //   10934: astore_3
    //   10935: new java/lang/Exception
    //   10938: dup
    //   10939: aload_3
    //   10940: invokevirtual getMessage : ()Ljava/lang/String;
    //   10943: invokespecial <init> : (Ljava/lang/String;)V
    //   10946: athrow
    // Exception table:
    //   from	to	target	type
    //   4	10933	10934	java/lang/Throwable
    //   834	868	871	java/lang/Throwable
    //   963	1041	1044	java/lang/Throwable
    //   970	1184	1187	java/lang/Throwable
    //   1561	1576	1576	java/lang/Throwable
    //   1603	1637	1640	java/lang/Throwable
    //   1647	1659	1662	java/lang/Throwable
    //   1745	1823	1826	java/lang/Throwable
    //   1752	1966	1969	java/lang/Throwable
    //   2366	2444	2447	java/lang/Throwable
    //   2373	2587	2590	java/lang/Throwable
    //   3034	3068	3071	java/lang/Throwable
    //   3075	3087	3090	java/lang/Throwable
    //   3173	3251	3254	java/lang/Throwable
    //   3180	3394	3397	java/lang/Throwable
    //   8455	8630	8633	java/lang/Throwable
    //   8600	8667	8670	java/lang/Throwable
    //   8637	8704	8707	java/lang/Throwable
    //   8674	8741	8744	java/lang/Throwable
    //   8711	8778	8781	java/lang/Throwable
    //   8748	8815	8818	java/lang/Throwable
    //   8785	8852	8855	java/lang/Throwable
    //   8822	8889	8892	java/lang/Throwable
    //   8859	8926	8929	java/lang/Throwable
    //   8896	8963	8966	java/lang/Throwable
    //   8933	9000	9003	java/lang/Throwable
    //   8970	9037	9040	java/lang/Throwable
    //   9007	9074	9077	java/lang/Throwable
    //   9044	9111	9114	java/lang/Throwable
    //   9081	9148	9151	java/lang/Throwable
    //   9118	9185	9188	java/lang/Throwable
    //   9155	9222	9225	java/lang/Throwable
    //   9192	9259	9262	java/lang/Throwable
    //   9229	9296	9299	java/lang/Throwable
    //   9266	9333	9336	java/lang/Throwable
    //   9303	9370	9373	java/lang/Throwable
    //   9340	9407	9410	java/lang/Throwable
    //   9377	9444	9447	java/lang/Throwable
    //   9414	9481	9484	java/lang/Throwable
    //   9451	9518	9521	java/lang/Throwable
    //   9488	9555	9558	java/lang/Throwable
    //   9525	9592	9595	java/lang/Throwable
    //   9562	9629	9632	java/lang/Throwable
    //   9599	9666	9669	java/lang/Throwable
    //   9636	9703	9706	java/lang/Throwable
    //   9673	9740	9743	java/lang/Throwable
    //   9710	9773	9776	java/lang/Throwable
    //   9839	9853	9853	java/lang/Throwable
    //   9864	9877	9880	java/lang/Throwable
    //   9869	9892	9895	java/lang/Throwable
    //   9884	9910	9913	java/lang/Throwable
    //   9899	9940	9943	java/lang/Throwable
    //   10006	10033	10036	java/lang/Throwable
    //   10023	10051	10054	java/lang/Throwable
    //   10040	10087	10090	java/lang/Throwable
    //   10058	10101	10104	java/lang/Throwable
    //   10153	10167	10167	java/lang/Throwable
    //   10178	10191	10194	java/lang/Throwable
    //   10183	10206	10209	java/lang/Throwable
    //   10198	10224	10227	java/lang/Throwable
    //   10213	10254	10257	java/lang/Throwable
    //   10320	10347	10350	java/lang/Throwable
    //   10337	10365	10368	java/lang/Throwable
    //   10354	10395	10398	java/lang/Throwable
    //   10372	10406	10406	java/lang/Throwable
    //   10417	10433	10436	java/lang/Throwable
    //   10485	10499	10499	java/lang/Throwable
    //   10510	10523	10526	java/lang/Throwable
    //   10515	10538	10541	java/lang/Throwable
    //   10530	10556	10559	java/lang/Throwable
    //   10545	10586	10589	java/lang/Throwable
    //   10652	10679	10682	java/lang/Throwable
    //   10669	10700	10703	java/lang/Throwable
    //   10686	10730	10733	java/lang/Throwable
    //   10707	10741	10741	java/lang/Throwable
    //   10752	10768	10771	java/lang/Throwable
    //   10775	10865	10868	java/lang/Throwable
    //   10820	10917	10920	java/lang/Throwable
    //   10872	10928	10928	java/lang/Throwable
  }
  
  static {
    // Byte code:
    //   0: bipush #14
    //   2: anewarray java/lang/String
    //   5: astore #5
    //   7: iconst_0
    //   8: istore_3
    //   9: ldc ']\\tKoyR^lB$ihxRmH0@7;\\t\\b/YUpm2j>!V\\tAcn\\n9\\tFP\\tAjL RJ7CxBByo&uCm!Ok>\\tZ\\f0\\tQ3.K\\t'Wh\\f\\t;`\\tdl?#t\\t]E0&'
    //   11: dup
    //   12: astore_2
    //   13: invokevirtual length : ()I
    //   16: istore #4
    //   18: bipush #76
    //   20: istore_1
    //   21: iconst_m1
    //   22: istore_0
    //   23: bipush #111
    //   25: iinc #0, 1
    //   28: aload_2
    //   29: iload_0
    //   30: dup
    //   31: iload_1
    //   32: iadd
    //   33: invokevirtual substring : (II)Ljava/lang/String;
    //   36: iconst_m1
    //   37: goto -> 142
    //   40: aload #5
    //   42: swap
    //   43: iload_3
    //   44: iinc #3, 1
    //   47: swap
    //   48: aastore
    //   49: iload_0
    //   50: iload_1
    //   51: iadd
    //   52: dup
    //   53: istore_0
    //   54: iload #4
    //   56: if_icmpge -> 68
    //   59: aload_2
    //   60: iload_0
    //   61: invokevirtual charAt : (I)C
    //   64: istore_1
    //   65: goto -> 23
    //   68: ldc ' +D2rmHKKyc90xDR57x'
    //   70: dup
    //   71: astore_2
    //   72: invokevirtual length : ()I
    //   75: istore #4
    //   77: iconst_4
    //   78: istore_1
    //   79: iconst_m1
    //   80: istore_0
    //   81: bipush #105
    //   83: iinc #0, 1
    //   86: aload_2
    //   87: iload_0
    //   88: dup
    //   89: iload_1
    //   90: iadd
    //   91: invokevirtual substring : (II)Ljava/lang/String;
    //   94: iconst_0
    //   95: goto -> 142
    //   98: aload #5
    //   100: swap
    //   101: iload_3
    //   102: iinc #3, 1
    //   105: swap
    //   106: aastore
    //   107: iload_0
    //   108: iload_1
    //   109: iadd
    //   110: dup
    //   111: istore_0
    //   112: iload #4
    //   114: if_icmpge -> 126
    //   117: aload_2
    //   118: iload_0
    //   119: invokevirtual charAt : (I)C
    //   122: istore_1
    //   123: goto -> 81
    //   126: aload #5
    //   128: putstatic burp/Zsgj.a : [Ljava/lang/String;
    //   131: bipush #14
    //   133: anewarray java/lang/String
    //   136: putstatic burp/Zsgj.b : [Ljava/lang/String;
    //   139: goto -> 300
    //   142: dup_x2
    //   143: pop
    //   144: invokevirtual toCharArray : ()[C
    //   147: dup_x1
    //   148: arraylength
    //   149: dup_x2
    //   150: pop
    //   151: iconst_0
    //   152: istore #6
    //   154: dup2_x1
    //   155: pop2
    //   156: dup_x2
    //   157: iconst_1
    //   158: if_icmpgt -> 260
    //   161: dup2
    //   162: swap
    //   163: iload #6
    //   165: dup2_x1
    //   166: caload
    //   167: swap
    //   168: iload #6
    //   170: bipush #7
    //   172: irem
    //   173: tableswitch default -> 242, 0 -> 212, 1 -> 217, 2 -> 222, 3 -> 227, 4 -> 232, 5 -> 237
    //   212: bipush #112
    //   214: goto -> 244
    //   217: bipush #125
    //   219: goto -> 244
    //   222: bipush #32
    //   224: goto -> 244
    //   227: bipush #53
    //   229: goto -> 244
    //   232: bipush #12
    //   234: goto -> 244
    //   237: bipush #29
    //   239: goto -> 244
    //   242: bipush #14
    //   244: ixor
    //   245: ixor
    //   246: i2c
    //   247: castore
    //   248: iinc #6, 1
    //   251: dup
    //   252: ifne -> 260
    //   255: dup2
    //   256: dup_x1
    //   257: goto -> 165
    //   260: dup2_x1
    //   261: pop2
    //   262: dup_x2
    //   263: iload #6
    //   265: if_icmpgt -> 161
    //   268: pop
    //   269: new java/lang/String
    //   272: dup_x1
    //   273: swap
    //   274: invokespecial <init> : ([C)V
    //   277: invokevirtual intern : ()Ljava/lang/String;
    //   280: swap
    //   281: pop
    //   282: swap
    //   283: tableswitch default -> 40, 0 -> 98
    //   300: new java/math/BigInteger
    //   303: dup
    //   304: bipush #32
    //   306: newarray byte
    //   308: dup
    //   309: iconst_0
    //   310: bipush #83
    //   312: bastore
    //   313: dup
    //   314: iconst_1
    //   315: bipush #-111
    //   317: bastore
    //   318: dup
    //   319: iconst_2
    //   320: bipush #-68
    //   322: bastore
    //   323: dup
    //   324: iconst_3
    //   325: bipush #-35
    //   327: bastore
    //   328: dup
    //   329: iconst_4
    //   330: bipush #-76
    //   332: bastore
    //   333: dup
    //   334: iconst_5
    //   335: bipush #77
    //   337: bastore
    //   338: dup
    //   339: bipush #6
    //   341: bipush #77
    //   343: bastore
    //   344: dup
    //   345: bipush #7
    //   347: bipush #15
    //   349: bastore
    //   350: dup
    //   351: bipush #8
    //   353: bipush #12
    //   355: bastore
    //   356: dup
    //   357: bipush #9
    //   359: bipush #79
    //   361: bastore
    //   362: dup
    //   363: bipush #10
    //   365: bipush #117
    //   367: bastore
    //   368: dup
    //   369: bipush #11
    //   371: bipush #111
    //   373: bastore
    //   374: dup
    //   375: bipush #12
    //   377: bipush #-36
    //   379: bastore
    //   380: dup
    //   381: bipush #13
    //   383: bipush #55
    //   385: bastore
    //   386: dup
    //   387: bipush #14
    //   389: bipush #-107
    //   391: bastore
    //   392: dup
    //   393: bipush #15
    //   395: bipush #86
    //   397: bastore
    //   398: dup
    //   399: bipush #16
    //   401: bipush #53
    //   403: bastore
    //   404: dup
    //   405: bipush #17
    //   407: bipush #18
    //   409: bastore
    //   410: dup
    //   411: bipush #18
    //   413: bipush #61
    //   415: bastore
    //   416: dup
    //   417: bipush #19
    //   419: bipush #-52
    //   421: bastore
    //   422: dup
    //   423: bipush #20
    //   425: bipush #69
    //   427: bastore
    //   428: dup
    //   429: bipush #21
    //   431: bipush #77
    //   433: bastore
    //   434: dup
    //   435: bipush #22
    //   437: bipush #120
    //   439: bastore
    //   440: dup
    //   441: bipush #23
    //   443: bipush #35
    //   445: bastore
    //   446: dup
    //   447: bipush #24
    //   449: bipush #14
    //   451: bastore
    //   452: dup
    //   453: bipush #25
    //   455: bipush #-125
    //   457: bastore
    //   458: dup
    //   459: bipush #26
    //   461: bipush #-19
    //   463: bastore
    //   464: dup
    //   465: bipush #27
    //   467: bipush #113
    //   469: bastore
    //   470: dup
    //   471: bipush #28
    //   473: bipush #16
    //   475: bastore
    //   476: dup
    //   477: bipush #29
    //   479: bipush #-112
    //   481: bastore
    //   482: dup
    //   483: bipush #30
    //   485: bipush #-98
    //   487: bastore
    //   488: dup
    //   489: bipush #31
    //   491: bipush #105
    //   493: bastore
    //   494: invokespecial <init> : ([B)V
    //   497: putstatic burp/Zsgj.ZK : Ljava/lang/Object;
    //   500: sipush #-30956
    //   503: sipush #-8461
    //   506: invokestatic a : (II)Ljava/lang/String;
    //   509: putstatic burp/Zsgj.ZN : Ljava/lang/String;
    //   512: return
  }
  
  private static Throwable a(Throwable paramThrowable) {
    return paramThrowable;
  }
  
  private static String a(int paramInt1, int paramInt2) {
    int i = (paramInt1 ^ 0xFFFF8719) & 0xFFFF;
    if (b[i] == null) {
      char[] arrayOfChar = a[i].toCharArray();
      switch (arrayOfChar[0] & 0xFF) {
        case 0:
        
        case 1:
        
        case 2:
        
        case 3:
        
        case 4:
        
        case 5:
        
        case 6:
        
        case 7:
        
        case 8:
        
        case 9:
        
        case 10:
        
        case 11:
        
        case 12:
        
        case 13:
        
        case 14:
        
        case 15:
        
        case 16:
        
        case 17:
        
        case 18:
        
        case 19:
        
        case 20:
        
        case 21:
        
        case 22:
        
        case 23:
        
        case 24:
        
        case 25:
        
        case 26:
        
        case 27:
        
        case 28:
        
        case 29:
        
        case 30:
        
        case 31:
        
        case 32:
        
        case 33:
        
        case 34:
        
        case 35:
        
        case 36:
        
        case 37:
        
        case 38:
        
        case 39:
        
        case 40:
        
        case 41:
        
        case 42:
        
        case 43:
        
        case 44:
        
        case 45:
        
        case 46:
        
        case 47:
        
        case 48:
        
        case 49:
        
        case 50:
        
        case 51:
        
        case 52:
        
        case 53:
        
        case 54:
        
        case 55:
        
        case 56:
        
        case 57:
        
        case 58:
        
        case 59:
        
        case 60:
        
        case 61:
        
        case 62:
        
        case 63:
        
        case 64:
        
        case 65:
        
        case 66:
        
        case 67:
        
        case 68:
        
        case 69:
        
        case 70:
        
        case 71:
        
        case 72:
        
        case 73:
        
        case 74:
        
        case 75:
        
        case 76:
        
        case 77:
        
        case 78:
        
        case 79:
        
        case 80:
        
        case 81:
        
        case 82:
        
        case 83:
        
        case 84:
        
        case 85:
        
        case 86:
        
        case 87:
        
        case 88:
        
        case 89:
        
        case 90:
        
        case 91:
        
        case 92:
        
        case 93:
        
        case 94:
        
        case 95:
        
        case 96:
        
        case 97:
        
        case 98:
        
        case 99:
        
        case 100:
        
        case 101:
        
        case 102:
        
        case 103:
        
        case 104:
        
        case 105:
        
        case 106:
        
        case 107:
        
        case 108:
        
        case 109:
        
        case 110:
        
        case 111:
        
        case 112:
        
        case 113:
        
        case 114:
        
        case 115:
        
        case 116:
        
        case 117:
        
        case 118:
        
        case 119:
        
        case 120:
        
        case 121:
        
        case 122:
        
        case 123:
        
        case 124:
        
        case 125:
        
        case 126:
        
        case 127:
        
        case 128:
        
        case 129:
        
        case 130:
        
        case 131:
        
        case 132:
        
        case 133:
        
        case 134:
        
        case 135:
        
        case 136:
        
        case 137:
        
        case 138:
        
        case 139:
        
        case 140:
        
        case 141:
        
        case 142:
        
        case 143:
        
        case 144:
        
        case 145:
        
        case 146:
        
        case 147:
        
        case 148:
        
        case 149:
        
        case 150:
        
        case 151:
        
        case 152:
        
        case 153:
        
        case 154:
        
        case 155:
        
        case 156:
        
        case 157:
        
        case 158:
        
        case 159:
        
        case 160:
        
        case 161:
        
        case 162:
        
        case 163:
        
        case 164:
        
        case 165:
        
        case 166:
        
        case 167:
        
        case 168:
        
        case 169:
        
        case 170:
        
        case 171:
        
        case 172:
        
        case 173:
        
        case 174:
        
        case 175:
        
        case 176:
        
        case 177:
        
        case 178:
        
        case 179:
        
        case 180:
        
        case 181:
        
        case 182:
        
        case 183:
        
        case 184:
        
        case 185:
        
        case 186:
        
        case 187:
        
        case 188:
        
        case 189:
        
        case 190:
        
        case 191:
        
        case 192:
        
        case 193:
        
        case 194:
        
        case 195:
        
        case 196:
        
        case 197:
        
        case 198:
        
        case 199:
        
        case 200:
        
        case 201:
        
        case 202:
        
        case 203:
        
        case 204:
        
        case 205:
        
        case 206:
        
        case 207:
        
        case 208:
        
        case 209:
        
        case 210:
        
        case 211:
        
        case 212:
        
        case 213:
        
        case 214:
        
        case 215:
        
        case 216:
        
        case 217:
        
        case 218:
        
        case 219:
        
        case 220:
        
        case 221:
        
        case 222:
        
        case 223:
        
        case 224:
        
        case 225:
        
        case 226:
        
        case 227:
        
        case 228:
        
        case 229:
        
        case 230:
        
        case 231:
        
        case 232:
        
        case 233:
        
        case 234:
        
        case 235:
        
        case 236:
        
        case 237:
        
        case 238:
        
        case 239:
        
        case 240:
        
        case 241:
        
        case 242:
        
        case 243:
        
        case 244:
        
        case 245:
        
        case 246:
        
        case 247:
        
        case 248:
        
        case 249:
        
        case 250:
        
        case 251:
        
        case 252:
        
        case 253:
        
        case 254:
        
        default:
          break;
      } 
      byte b1 = 20;
      int j = (paramInt2 & 0xFF) - b1;
      if (j < 0)
        j += 256; 
      int k = ((paramInt2 & 0xFFFF) >>> 8) - b1;
      if (k < 0)
        k += 256; 
      for (byte b2 = 0; b2 < arrayOfChar.length; b2++) {
        int m = b2 % 2;
        if (m == 0) {
          arrayOfChar[b2] = (char)(arrayOfChar[b2] ^ j);
          j = ((j >>> 3 | j << 5) ^ arrayOfChar[b2]) & 0xFF;
        } else {
          arrayOfChar[b2] = (char)(arrayOfChar[b2] ^ k);
          k = ((k >>> 3 | k << 5) ^ arrayOfChar[b2]) & 0xFF;
        } 
      } 
      b[i] = (new String(arrayOfChar)).intern();
    } 
    return b[i];
  }
}


/* Location:              C:\Program Files\BurpSuitePro\burpsuite_pro.jar!\burp\Zsgj.class
 * Java compiler version: 21 (65.0)
 * JD-Core Version:       1.1.3
 */