package burp;

public class Zsjz {
  public static void Zn(Zll9 paramZll9, Zbdf paramZbdf1, Zbdf paramZbdf2, Zkl6 paramZkl6, Ze47 paramZe47) {
    // Byte code:
    //   0: invokestatic Zb : ()Ljava/lang/String;
    //   3: astore #5
    //   5: aload_0
    //   6: ifnonnull -> 32
    //   9: aload_1
    //   10: aconst_null
    //   11: getstatic burp/Zgu3.HTTP_REQUEST : Lburp/Zgu3;
    //   14: aconst_null
    //   15: invokevirtual ZL : (Lburp/Zstu;Lburp/Zgu3;Lburp/Zmgv;)V
    //   18: aload_2
    //   19: aconst_null
    //   20: getstatic burp/Zgu3.HTTP_RESPONSE : Lburp/Zgu3;
    //   23: aconst_null
    //   24: invokevirtual ZL : (Lburp/Zstu;Lburp/Zgu3;Lburp/Zmgv;)V
    //   27: aload #5
    //   29: ifnonnull -> 170
    //   32: aload_0
    //   33: invokeinterface Zo3 : ()Lburp/Zbr;
    //   38: astore #6
    //   40: aload_0
    //   41: invokeinterface Zoe : ()Lburp/Zgsq;
    //   46: astore #7
    //   48: aload_0
    //   49: invokeinterface ZoO : ()Lburp/Zstu;
    //   54: astore #8
    //   56: aload #6
    //   58: ifnonnull -> 111
    //   61: aload #4
    //   63: aload_0
    //   64: invokeinterface Zod : ()Lburp/Zmzk;
    //   69: invokevirtual Zw : (Lburp/Zmzk;)Lburp/Zkyt;
    //   72: astore #9
    //   74: aload_3
    //   75: invokeinterface Zs : ()Lburp/Zm6e;
    //   80: invokeinterface ZO : ()Lburp/Ztom;
    //   85: aload_0
    //   86: invokeinterface ZlL : ()Lburp/Zlit;
    //   91: invokevirtual Zf : (Lburp/Zlit;)Lburp/Ztom;
    //   94: invokevirtual Zr : ()Lburp/Zstu;
    //   97: aload #9
    //   99: invokestatic Zy : (Lburp/Zstu;Lburp/Zkyt;)Lburp/Zbr;
    //   102: astore #6
    //   104: aload #9
    //   106: invokestatic ZW : (Lburp/Zkyt;)Lburp/Zgsq;
    //   109: astore #7
    //   111: aload_1
    //   112: aload #6
    //   114: aload_0
    //   115: invokeinterface Zod : ()Lburp/Zmzk;
    //   120: aload_3
    //   121: invokeinterface ZH : ()Lburp/Zey9;
    //   126: invokevirtual ZP : (Lburp/Zmzk;Lburp/Zey9;)Lburp/Zefx;
    //   129: aload #7
    //   131: aload_0
    //   132: invokevirtual Zw : (Lburp/Zefx;Lburp/Zgsq;Lburp/Zmgv;)V
    //   135: aload_2
    //   136: aload #8
    //   138: getstatic burp/Zgu3.HTTP_RESPONSE : Lburp/Zgu3;
    //   141: aload_0
    //   142: invokevirtual ZL : (Lburp/Zstu;Lburp/Zgu3;Lburp/Zmgv;)V
    //   145: aload #8
    //   147: ifnull -> 170
    //   150: aload_0
    //   151: instanceof burp/Zxxe
    //   154: ifeq -> 170
    //   157: aload_2
    //   158: aload_0
    //   159: checkcast burp/Zxxe
    //   162: invokeinterface Zg : ()Ljava/util/List;
    //   167: invokevirtual ZX : (Ljava/util/List;)V
    //   170: return
  }
}


/* Location:              C:\Program Files\BurpSuitePro\burpsuite_pro.jar!\burp\Zsjz.class
 * Java compiler version: 21 (65.0)
 * JD-Core Version:       1.1.3
 */