package burp;

import java.math.BigInteger;

class Zsk2 extends ClassLoader {
  static Object ZD;
  
  static String ZE;
  
  private static final String[] a;
  
  private static final String[] b;
  
  static void Zo(Object[] paramArrayOfObject, Object paramObject) throws Throwable {}
  
  static void Zi(Object paramObject) {
    Zrxm.Zp = a(14357, -14780);
    Zrxm.ZL = new BigInteger(a(14352, 178));
    boolean bool = Zt2e.ZN();
    try {
      try {
        if (Zr9p.Za.charAt(Math.abs(((BigInteger)Ztap.ZK).intValue() % 32)) <= Zl22.ZL.charAt(Math.abs(((BigInteger)Zezq.Zu).intValue() % 32))) {
          try {
            Zt5a.Za(Class.forName(a(14356, -16982)));
            if (!bool)
              Zmcq.Zl(Class.forName(a(14366, -10330))); 
          } catch (Throwable throwable) {
            throw a(null);
          } 
          return;
        } 
      } catch (Throwable throwable) {
        throw a(null);
      } 
      Zmcq.Zl(Class.forName(a(14366, -10330)));
    } catch (Throwable throwable) {}
  }
  
  static boolean Zd(Object[] paramArrayOfObject, Object paramObject) throws Throwable {
    // Byte code:
    //   0: invokestatic ZN : ()Z
    //   3: istore_2
    //   4: getstatic burp/Zlg1.ZH : Ljava/lang/Object;
    //   7: checkcast java/math/BigInteger
    //   10: getstatic burp/Zxdh.ZD : Ljava/lang/Object;
    //   13: checkcast java/math/BigInteger
    //   16: invokevirtual subtract : (Ljava/math/BigInteger;)Ljava/math/BigInteger;
    //   19: putstatic burp/Zb29.ZM : Ljava/lang/Object;
    //   22: ldc2_w 8682522807148012
    //   25: invokestatic currentTimeMillis : ()J
    //   28: lxor
    //   29: lstore #4
    //   31: lload #4
    //   33: ldc2_w 25214903917
    //   36: lmul
    //   37: ldc2_w 11
    //   40: ladd
    //   41: ldc2_w 281474976710655
    //   44: land
    //   45: lstore #4
    //   47: lload #4
    //   49: bipush #32
    //   51: lshl
    //   52: lstore #6
    //   54: lload #4
    //   56: ldc2_w 25214903917
    //   59: lmul
    //   60: ldc2_w 11
    //   63: ladd
    //   64: ldc2_w 281474976710655
    //   67: land
    //   68: lstore #4
    //   70: lload #6
    //   72: lload #4
    //   74: ladd
    //   75: lstore #6
    //   77: bipush #16
    //   79: newarray byte
    //   81: dup
    //   82: iconst_0
    //   83: bipush #48
    //   85: bastore
    //   86: dup
    //   87: iconst_1
    //   88: bipush #49
    //   90: bastore
    //   91: dup
    //   92: iconst_2
    //   93: bipush #50
    //   95: bastore
    //   96: dup
    //   97: iconst_3
    //   98: bipush #51
    //   100: bastore
    //   101: dup
    //   102: iconst_4
    //   103: bipush #52
    //   105: bastore
    //   106: dup
    //   107: iconst_5
    //   108: bipush #53
    //   110: bastore
    //   111: dup
    //   112: bipush #6
    //   114: bipush #54
    //   116: bastore
    //   117: dup
    //   118: bipush #7
    //   120: bipush #55
    //   122: bastore
    //   123: dup
    //   124: bipush #8
    //   126: bipush #56
    //   128: bastore
    //   129: dup
    //   130: bipush #9
    //   132: bipush #57
    //   134: bastore
    //   135: dup
    //   136: bipush #10
    //   138: bipush #97
    //   140: bastore
    //   141: dup
    //   142: bipush #11
    //   144: bipush #98
    //   146: bastore
    //   147: dup
    //   148: bipush #12
    //   150: bipush #99
    //   152: bastore
    //   153: dup
    //   154: bipush #13
    //   156: bipush #100
    //   158: bastore
    //   159: dup
    //   160: bipush #14
    //   162: bipush #101
    //   164: bastore
    //   165: dup
    //   166: bipush #15
    //   168: bipush #102
    //   170: bastore
    //   171: astore #8
    //   173: bipush #64
    //   175: newarray byte
    //   177: astore #9
    //   179: bipush #64
    //   181: istore #10
    //   183: bipush #16
    //   185: istore #11
    //   187: iload #11
    //   189: iconst_1
    //   190: isub
    //   191: i2l
    //   192: lstore #12
    //   194: aload #9
    //   196: iinc #10, -1
    //   199: iload #10
    //   201: aload #8
    //   203: lload #6
    //   205: lload #12
    //   207: land
    //   208: l2i
    //   209: baload
    //   210: bastore
    //   211: lload #6
    //   213: iconst_4
    //   214: lushr
    //   215: lstore #6
    //   217: lload #6
    //   219: lconst_0
    //   220: lcmp
    //   221: ifne -> 194
    //   224: bipush #64
    //   226: iload #10
    //   228: isub
    //   229: newarray byte
    //   231: astore_3
    //   232: iconst_0
    //   233: istore #14
    //   235: iload #14
    //   237: aload_3
    //   238: arraylength
    //   239: if_icmpge -> 261
    //   242: aload_3
    //   243: iload #14
    //   245: aload #9
    //   247: iload #10
    //   249: iload #14
    //   251: iadd
    //   252: baload
    //   253: bastore
    //   254: iinc #14, 1
    //   257: iload_2
    //   258: ifne -> 235
    //   261: aload_3
    //   262: arraylength
    //   263: bipush #10
    //   265: if_icmplt -> 31
    //   268: getstatic burp/Zb_c.ZN : Ljava/lang/Object;
    //   271: checkcast java/math/BigInteger
    //   274: invokevirtual toByteArray : ()[B
    //   277: astore_3
    //   278: bipush #32
    //   280: newarray int
    //   282: dup
    //   283: iconst_0
    //   284: ldc 876216579
    //   286: iastore
    //   287: dup
    //   288: iconst_1
    //   289: ldc 455999525
    //   291: iastore
    //   292: dup
    //   293: iconst_2
    //   294: ldc 1043334948
    //   296: iastore
    //   297: dup
    //   298: iconst_3
    //   299: ldc 439222784
    //   301: iastore
    //   302: dup
    //   303: iconst_4
    //   304: ldc 372376604
    //   306: iastore
    //   307: dup
    //   308: iconst_5
    //   309: ldc 707731490
    //   311: iastore
    //   312: dup
    //   313: bipush #6
    //   315: ldc 389426184
    //   317: iastore
    //   318: dup
    //   319: bipush #7
    //   321: ldc 973875457
    //   323: iastore
    //   324: dup
    //   325: bipush #8
    //   327: ldc 389160971
    //   329: iastore
    //   330: dup
    //   331: bipush #9
    //   333: ldc 907870729
    //   335: iastore
    //   336: dup
    //   337: bipush #10
    //   339: ldc 121057538
    //   341: iastore
    //   342: dup
    //   343: bipush #11
    //   345: ldc 840500228
    //   347: iastore
    //   348: dup
    //   349: bipush #12
    //   351: ldc 254150144
    //   353: iastore
    //   354: dup
    //   355: bipush #13
    //   357: ldc 924386310
    //   359: iastore
    //   360: dup
    //   361: bipush #14
    //   363: ldc 187632156
    //   365: iastore
    //   366: dup
    //   367: bipush #15
    //   369: ldc 874189824
    //   371: iastore
    //   372: dup
    //   373: bipush #16
    //   375: ldc 655302664
    //   377: iastore
    //   378: dup
    //   379: bipush #17
    //   381: ldc 890966315
    //   383: iastore
    //   384: dup
    //   385: bipush #18
    //   387: ldc 722417666
    //   389: iastore
    //   390: dup
    //   391: bipush #19
    //   393: ldc 1026621720
    //   395: iastore
    //   396: dup
    //   397: bipush #20
    //   399: ldc 957157408
    //   401: iastore
    //   402: dup
    //   403: bipush #21
    //   405: ldc 892536332
    //   407: iastore
    //   408: dup
    //   409: bipush #22
    //   411: ldc 689771012
    //   413: iastore
    //   414: dup
    //   415: bipush #23
    //   417: ldc 221709344
    //   419: iastore
    //   420: dup
    //   421: bipush #24
    //   423: ldc 940377620
    //   425: iastore
    //   426: dup
    //   427: bipush #25
    //   429: ldc 255209728
    //   431: iastore
    //   432: dup
    //   433: bipush #26
    //   435: ldc 1010368540
    //   437: iastore
    //   438: dup
    //   439: bipush #27
    //   441: ldc 220604441
    //   443: iastore
    //   444: dup
    //   445: bipush #28
    //   447: ldc 1008414755
    //   449: iastore
    //   450: dup
    //   451: bipush #29
    //   453: ldc 187049985
    //   455: iastore
    //   456: dup
    //   457: bipush #30
    //   459: ldc 943331329
    //   461: iastore
    //   462: dup
    //   463: bipush #31
    //   465: ldc 170788368
    //   467: iastore
    //   468: astore #5
    //   470: bipush #64
    //   472: newarray int
    //   474: dup
    //   475: iconst_0
    //   476: ldc 16843776
    //   478: iastore
    //   479: dup
    //   480: iconst_1
    //   481: iconst_0
    //   482: iastore
    //   483: dup
    //   484: iconst_2
    //   485: ldc 65536
    //   487: iastore
    //   488: dup
    //   489: iconst_3
    //   490: ldc 16843780
    //   492: iastore
    //   493: dup
    //   494: iconst_4
    //   495: ldc 16842756
    //   497: iastore
    //   498: dup
    //   499: iconst_5
    //   500: ldc 66564
    //   502: iastore
    //   503: dup
    //   504: bipush #6
    //   506: iconst_4
    //   507: iastore
    //   508: dup
    //   509: bipush #7
    //   511: ldc 65536
    //   513: iastore
    //   514: dup
    //   515: bipush #8
    //   517: sipush #1024
    //   520: iastore
    //   521: dup
    //   522: bipush #9
    //   524: ldc 16843776
    //   526: iastore
    //   527: dup
    //   528: bipush #10
    //   530: ldc 16843780
    //   532: iastore
    //   533: dup
    //   534: bipush #11
    //   536: sipush #1024
    //   539: iastore
    //   540: dup
    //   541: bipush #12
    //   543: ldc 16778244
    //   545: iastore
    //   546: dup
    //   547: bipush #13
    //   549: ldc 16842756
    //   551: iastore
    //   552: dup
    //   553: bipush #14
    //   555: ldc 16777216
    //   557: iastore
    //   558: dup
    //   559: bipush #15
    //   561: iconst_4
    //   562: iastore
    //   563: dup
    //   564: bipush #16
    //   566: sipush #1028
    //   569: iastore
    //   570: dup
    //   571: bipush #17
    //   573: ldc 16778240
    //   575: iastore
    //   576: dup
    //   577: bipush #18
    //   579: ldc 16778240
    //   581: iastore
    //   582: dup
    //   583: bipush #19
    //   585: ldc 66560
    //   587: iastore
    //   588: dup
    //   589: bipush #20
    //   591: ldc 66560
    //   593: iastore
    //   594: dup
    //   595: bipush #21
    //   597: ldc 16842752
    //   599: iastore
    //   600: dup
    //   601: bipush #22
    //   603: ldc 16842752
    //   605: iastore
    //   606: dup
    //   607: bipush #23
    //   609: ldc 16778244
    //   611: iastore
    //   612: dup
    //   613: bipush #24
    //   615: ldc 65540
    //   617: iastore
    //   618: dup
    //   619: bipush #25
    //   621: ldc 16777220
    //   623: iastore
    //   624: dup
    //   625: bipush #26
    //   627: ldc 16777220
    //   629: iastore
    //   630: dup
    //   631: bipush #27
    //   633: ldc 65540
    //   635: iastore
    //   636: dup
    //   637: bipush #28
    //   639: iconst_0
    //   640: iastore
    //   641: dup
    //   642: bipush #29
    //   644: sipush #1028
    //   647: iastore
    //   648: dup
    //   649: bipush #30
    //   651: ldc 66564
    //   653: iastore
    //   654: dup
    //   655: bipush #31
    //   657: ldc 16777216
    //   659: iastore
    //   660: dup
    //   661: bipush #32
    //   663: ldc 65536
    //   665: iastore
    //   666: dup
    //   667: bipush #33
    //   669: ldc 16843780
    //   671: iastore
    //   672: dup
    //   673: bipush #34
    //   675: iconst_4
    //   676: iastore
    //   677: dup
    //   678: bipush #35
    //   680: ldc 16842752
    //   682: iastore
    //   683: dup
    //   684: bipush #36
    //   686: ldc 16843776
    //   688: iastore
    //   689: dup
    //   690: bipush #37
    //   692: ldc 16777216
    //   694: iastore
    //   695: dup
    //   696: bipush #38
    //   698: ldc 16777216
    //   700: iastore
    //   701: dup
    //   702: bipush #39
    //   704: sipush #1024
    //   707: iastore
    //   708: dup
    //   709: bipush #40
    //   711: ldc 16842756
    //   713: iastore
    //   714: dup
    //   715: bipush #41
    //   717: ldc 65536
    //   719: iastore
    //   720: dup
    //   721: bipush #42
    //   723: ldc 66560
    //   725: iastore
    //   726: dup
    //   727: bipush #43
    //   729: ldc 16777220
    //   731: iastore
    //   732: dup
    //   733: bipush #44
    //   735: sipush #1024
    //   738: iastore
    //   739: dup
    //   740: bipush #45
    //   742: iconst_4
    //   743: iastore
    //   744: dup
    //   745: bipush #46
    //   747: ldc 16778244
    //   749: iastore
    //   750: dup
    //   751: bipush #47
    //   753: ldc 66564
    //   755: iastore
    //   756: dup
    //   757: bipush #48
    //   759: ldc 16843780
    //   761: iastore
    //   762: dup
    //   763: bipush #49
    //   765: ldc 65540
    //   767: iastore
    //   768: dup
    //   769: bipush #50
    //   771: ldc 16842752
    //   773: iastore
    //   774: dup
    //   775: bipush #51
    //   777: ldc 16778244
    //   779: iastore
    //   780: dup
    //   781: bipush #52
    //   783: ldc 16777220
    //   785: iastore
    //   786: dup
    //   787: bipush #53
    //   789: sipush #1028
    //   792: iastore
    //   793: dup
    //   794: bipush #54
    //   796: ldc 66564
    //   798: iastore
    //   799: dup
    //   800: bipush #55
    //   802: ldc 16843776
    //   804: iastore
    //   805: dup
    //   806: bipush #56
    //   808: sipush #1028
    //   811: iastore
    //   812: dup
    //   813: bipush #57
    //   815: ldc 16778240
    //   817: iastore
    //   818: dup
    //   819: bipush #58
    //   821: ldc 16778240
    //   823: iastore
    //   824: dup
    //   825: bipush #59
    //   827: iconst_0
    //   828: iastore
    //   829: dup
    //   830: bipush #60
    //   832: ldc 65540
    //   834: iastore
    //   835: dup
    //   836: bipush #61
    //   838: ldc 66560
    //   840: iastore
    //   841: dup
    //   842: bipush #62
    //   844: iconst_0
    //   845: iastore
    //   846: dup
    //   847: bipush #63
    //   849: ldc 16842756
    //   851: iastore
    //   852: astore #6
    //   854: bipush #64
    //   856: newarray int
    //   858: dup
    //   859: iconst_0
    //   860: ldc -2146402272
    //   862: iastore
    //   863: dup
    //   864: iconst_1
    //   865: ldc -2147450880
    //   867: iastore
    //   868: dup
    //   869: iconst_2
    //   870: ldc 32768
    //   872: iastore
    //   873: dup
    //   874: iconst_3
    //   875: ldc 1081376
    //   877: iastore
    //   878: dup
    //   879: iconst_4
    //   880: ldc 1048576
    //   882: iastore
    //   883: dup
    //   884: iconst_5
    //   885: bipush #32
    //   887: iastore
    //   888: dup
    //   889: bipush #6
    //   891: ldc -2146435040
    //   893: iastore
    //   894: dup
    //   895: bipush #7
    //   897: ldc -2147450848
    //   899: iastore
    //   900: dup
    //   901: bipush #8
    //   903: ldc -2147483616
    //   905: iastore
    //   906: dup
    //   907: bipush #9
    //   909: ldc -2146402272
    //   911: iastore
    //   912: dup
    //   913: bipush #10
    //   915: ldc -2146402304
    //   917: iastore
    //   918: dup
    //   919: bipush #11
    //   921: ldc -2147483648
    //   923: iastore
    //   924: dup
    //   925: bipush #12
    //   927: ldc -2147450880
    //   929: iastore
    //   930: dup
    //   931: bipush #13
    //   933: ldc 1048576
    //   935: iastore
    //   936: dup
    //   937: bipush #14
    //   939: bipush #32
    //   941: iastore
    //   942: dup
    //   943: bipush #15
    //   945: ldc -2146435040
    //   947: iastore
    //   948: dup
    //   949: bipush #16
    //   951: ldc 1081344
    //   953: iastore
    //   954: dup
    //   955: bipush #17
    //   957: ldc 1048608
    //   959: iastore
    //   960: dup
    //   961: bipush #18
    //   963: ldc -2147450848
    //   965: iastore
    //   966: dup
    //   967: bipush #19
    //   969: iconst_0
    //   970: iastore
    //   971: dup
    //   972: bipush #20
    //   974: ldc -2147483648
    //   976: iastore
    //   977: dup
    //   978: bipush #21
    //   980: ldc 32768
    //   982: iastore
    //   983: dup
    //   984: bipush #22
    //   986: ldc 1081376
    //   988: iastore
    //   989: dup
    //   990: bipush #23
    //   992: ldc -2146435072
    //   994: iastore
    //   995: dup
    //   996: bipush #24
    //   998: ldc 1048608
    //   1000: iastore
    //   1001: dup
    //   1002: bipush #25
    //   1004: ldc -2147483616
    //   1006: iastore
    //   1007: dup
    //   1008: bipush #26
    //   1010: iconst_0
    //   1011: iastore
    //   1012: dup
    //   1013: bipush #27
    //   1015: ldc 1081344
    //   1017: iastore
    //   1018: dup
    //   1019: bipush #28
    //   1021: ldc 32800
    //   1023: iastore
    //   1024: dup
    //   1025: bipush #29
    //   1027: ldc -2146402304
    //   1029: iastore
    //   1030: dup
    //   1031: bipush #30
    //   1033: ldc -2146435072
    //   1035: iastore
    //   1036: dup
    //   1037: bipush #31
    //   1039: ldc 32800
    //   1041: iastore
    //   1042: dup
    //   1043: bipush #32
    //   1045: iconst_0
    //   1046: iastore
    //   1047: dup
    //   1048: bipush #33
    //   1050: ldc 1081376
    //   1052: iastore
    //   1053: dup
    //   1054: bipush #34
    //   1056: ldc -2146435040
    //   1058: iastore
    //   1059: dup
    //   1060: bipush #35
    //   1062: ldc 1048576
    //   1064: iastore
    //   1065: dup
    //   1066: bipush #36
    //   1068: ldc -2147450848
    //   1070: iastore
    //   1071: dup
    //   1072: bipush #37
    //   1074: ldc -2146435072
    //   1076: iastore
    //   1077: dup
    //   1078: bipush #38
    //   1080: ldc -2146402304
    //   1082: iastore
    //   1083: dup
    //   1084: bipush #39
    //   1086: ldc 32768
    //   1088: iastore
    //   1089: dup
    //   1090: bipush #40
    //   1092: ldc -2146435072
    //   1094: iastore
    //   1095: dup
    //   1096: bipush #41
    //   1098: ldc -2147450880
    //   1100: iastore
    //   1101: dup
    //   1102: bipush #42
    //   1104: bipush #32
    //   1106: iastore
    //   1107: dup
    //   1108: bipush #43
    //   1110: ldc -2146402272
    //   1112: iastore
    //   1113: dup
    //   1114: bipush #44
    //   1116: ldc 1081376
    //   1118: iastore
    //   1119: dup
    //   1120: bipush #45
    //   1122: bipush #32
    //   1124: iastore
    //   1125: dup
    //   1126: bipush #46
    //   1128: ldc 32768
    //   1130: iastore
    //   1131: dup
    //   1132: bipush #47
    //   1134: ldc -2147483648
    //   1136: iastore
    //   1137: dup
    //   1138: bipush #48
    //   1140: ldc 32800
    //   1142: iastore
    //   1143: dup
    //   1144: bipush #49
    //   1146: ldc -2146402304
    //   1148: iastore
    //   1149: dup
    //   1150: bipush #50
    //   1152: ldc 1048576
    //   1154: iastore
    //   1155: dup
    //   1156: bipush #51
    //   1158: ldc -2147483616
    //   1160: iastore
    //   1161: dup
    //   1162: bipush #52
    //   1164: ldc 1048608
    //   1166: iastore
    //   1167: dup
    //   1168: bipush #53
    //   1170: ldc -2147450848
    //   1172: iastore
    //   1173: dup
    //   1174: bipush #54
    //   1176: ldc -2147483616
    //   1178: iastore
    //   1179: dup
    //   1180: bipush #55
    //   1182: ldc 1048608
    //   1184: iastore
    //   1185: dup
    //   1186: bipush #56
    //   1188: ldc 1081344
    //   1190: iastore
    //   1191: dup
    //   1192: bipush #57
    //   1194: iconst_0
    //   1195: iastore
    //   1196: dup
    //   1197: bipush #58
    //   1199: ldc -2147450880
    //   1201: iastore
    //   1202: dup
    //   1203: bipush #59
    //   1205: ldc 32800
    //   1207: iastore
    //   1208: dup
    //   1209: bipush #60
    //   1211: ldc -2147483648
    //   1213: iastore
    //   1214: dup
    //   1215: bipush #61
    //   1217: ldc -2146435040
    //   1219: iastore
    //   1220: dup
    //   1221: bipush #62
    //   1223: ldc -2146402272
    //   1225: iastore
    //   1226: dup
    //   1227: bipush #63
    //   1229: ldc 1081344
    //   1231: iastore
    //   1232: astore #7
    //   1234: bipush #64
    //   1236: newarray int
    //   1238: dup
    //   1239: iconst_0
    //   1240: sipush #520
    //   1243: iastore
    //   1244: dup
    //   1245: iconst_1
    //   1246: ldc 134349312
    //   1248: iastore
    //   1249: dup
    //   1250: iconst_2
    //   1251: iconst_0
    //   1252: iastore
    //   1253: dup
    //   1254: iconst_3
    //   1255: ldc 134348808
    //   1257: iastore
    //   1258: dup
    //   1259: iconst_4
    //   1260: ldc 134218240
    //   1262: iastore
    //   1263: dup
    //   1264: iconst_5
    //   1265: iconst_0
    //   1266: iastore
    //   1267: dup
    //   1268: bipush #6
    //   1270: ldc 131592
    //   1272: iastore
    //   1273: dup
    //   1274: bipush #7
    //   1276: ldc 134218240
    //   1278: iastore
    //   1279: dup
    //   1280: bipush #8
    //   1282: ldc 131080
    //   1284: iastore
    //   1285: dup
    //   1286: bipush #9
    //   1288: ldc 134217736
    //   1290: iastore
    //   1291: dup
    //   1292: bipush #10
    //   1294: ldc 134217736
    //   1296: iastore
    //   1297: dup
    //   1298: bipush #11
    //   1300: ldc 131072
    //   1302: iastore
    //   1303: dup
    //   1304: bipush #12
    //   1306: ldc 134349320
    //   1308: iastore
    //   1309: dup
    //   1310: bipush #13
    //   1312: ldc 131080
    //   1314: iastore
    //   1315: dup
    //   1316: bipush #14
    //   1318: ldc 134348800
    //   1320: iastore
    //   1321: dup
    //   1322: bipush #15
    //   1324: sipush #520
    //   1327: iastore
    //   1328: dup
    //   1329: bipush #16
    //   1331: ldc 134217728
    //   1333: iastore
    //   1334: dup
    //   1335: bipush #17
    //   1337: bipush #8
    //   1339: iastore
    //   1340: dup
    //   1341: bipush #18
    //   1343: ldc 134349312
    //   1345: iastore
    //   1346: dup
    //   1347: bipush #19
    //   1349: sipush #512
    //   1352: iastore
    //   1353: dup
    //   1354: bipush #20
    //   1356: ldc 131584
    //   1358: iastore
    //   1359: dup
    //   1360: bipush #21
    //   1362: ldc 134348800
    //   1364: iastore
    //   1365: dup
    //   1366: bipush #22
    //   1368: ldc 134348808
    //   1370: iastore
    //   1371: dup
    //   1372: bipush #23
    //   1374: ldc 131592
    //   1376: iastore
    //   1377: dup
    //   1378: bipush #24
    //   1380: ldc 134218248
    //   1382: iastore
    //   1383: dup
    //   1384: bipush #25
    //   1386: ldc 131584
    //   1388: iastore
    //   1389: dup
    //   1390: bipush #26
    //   1392: ldc 131072
    //   1394: iastore
    //   1395: dup
    //   1396: bipush #27
    //   1398: ldc 134218248
    //   1400: iastore
    //   1401: dup
    //   1402: bipush #28
    //   1404: bipush #8
    //   1406: iastore
    //   1407: dup
    //   1408: bipush #29
    //   1410: ldc 134349320
    //   1412: iastore
    //   1413: dup
    //   1414: bipush #30
    //   1416: sipush #512
    //   1419: iastore
    //   1420: dup
    //   1421: bipush #31
    //   1423: ldc 134217728
    //   1425: iastore
    //   1426: dup
    //   1427: bipush #32
    //   1429: ldc 134349312
    //   1431: iastore
    //   1432: dup
    //   1433: bipush #33
    //   1435: ldc 134217728
    //   1437: iastore
    //   1438: dup
    //   1439: bipush #34
    //   1441: ldc 131080
    //   1443: iastore
    //   1444: dup
    //   1445: bipush #35
    //   1447: sipush #520
    //   1450: iastore
    //   1451: dup
    //   1452: bipush #36
    //   1454: ldc 131072
    //   1456: iastore
    //   1457: dup
    //   1458: bipush #37
    //   1460: ldc 134349312
    //   1462: iastore
    //   1463: dup
    //   1464: bipush #38
    //   1466: ldc 134218240
    //   1468: iastore
    //   1469: dup
    //   1470: bipush #39
    //   1472: iconst_0
    //   1473: iastore
    //   1474: dup
    //   1475: bipush #40
    //   1477: sipush #512
    //   1480: iastore
    //   1481: dup
    //   1482: bipush #41
    //   1484: ldc 131080
    //   1486: iastore
    //   1487: dup
    //   1488: bipush #42
    //   1490: ldc 134349320
    //   1492: iastore
    //   1493: dup
    //   1494: bipush #43
    //   1496: ldc 134218240
    //   1498: iastore
    //   1499: dup
    //   1500: bipush #44
    //   1502: ldc 134217736
    //   1504: iastore
    //   1505: dup
    //   1506: bipush #45
    //   1508: sipush #512
    //   1511: iastore
    //   1512: dup
    //   1513: bipush #46
    //   1515: iconst_0
    //   1516: iastore
    //   1517: dup
    //   1518: bipush #47
    //   1520: ldc 134348808
    //   1522: iastore
    //   1523: dup
    //   1524: bipush #48
    //   1526: ldc 134218248
    //   1528: iastore
    //   1529: dup
    //   1530: bipush #49
    //   1532: ldc 131072
    //   1534: iastore
    //   1535: dup
    //   1536: bipush #50
    //   1538: ldc 134217728
    //   1540: iastore
    //   1541: dup
    //   1542: bipush #51
    //   1544: ldc 134349320
    //   1546: iastore
    //   1547: dup
    //   1548: bipush #52
    //   1550: bipush #8
    //   1552: iastore
    //   1553: dup
    //   1554: bipush #53
    //   1556: ldc 131592
    //   1558: iastore
    //   1559: dup
    //   1560: bipush #54
    //   1562: ldc 131584
    //   1564: iastore
    //   1565: dup
    //   1566: bipush #55
    //   1568: ldc 134217736
    //   1570: iastore
    //   1571: dup
    //   1572: bipush #56
    //   1574: ldc 134348800
    //   1576: iastore
    //   1577: dup
    //   1578: bipush #57
    //   1580: ldc 134218248
    //   1582: iastore
    //   1583: dup
    //   1584: bipush #58
    //   1586: sipush #520
    //   1589: iastore
    //   1590: dup
    //   1591: bipush #59
    //   1593: ldc 134348800
    //   1595: iastore
    //   1596: dup
    //   1597: bipush #60
    //   1599: ldc 131592
    //   1601: iastore
    //   1602: dup
    //   1603: bipush #61
    //   1605: bipush #8
    //   1607: iastore
    //   1608: dup
    //   1609: bipush #62
    //   1611: ldc 134348808
    //   1613: iastore
    //   1614: dup
    //   1615: bipush #63
    //   1617: ldc 131584
    //   1619: iastore
    //   1620: astore #8
    //   1622: bipush #64
    //   1624: newarray int
    //   1626: dup
    //   1627: iconst_0
    //   1628: ldc 8396801
    //   1630: iastore
    //   1631: dup
    //   1632: iconst_1
    //   1633: sipush #8321
    //   1636: iastore
    //   1637: dup
    //   1638: iconst_2
    //   1639: sipush #8321
    //   1642: iastore
    //   1643: dup
    //   1644: iconst_3
    //   1645: sipush #128
    //   1648: iastore
    //   1649: dup
    //   1650: iconst_4
    //   1651: ldc 8396928
    //   1653: iastore
    //   1654: dup
    //   1655: iconst_5
    //   1656: ldc 8388737
    //   1658: iastore
    //   1659: dup
    //   1660: bipush #6
    //   1662: ldc 8388609
    //   1664: iastore
    //   1665: dup
    //   1666: bipush #7
    //   1668: sipush #8193
    //   1671: iastore
    //   1672: dup
    //   1673: bipush #8
    //   1675: iconst_0
    //   1676: iastore
    //   1677: dup
    //   1678: bipush #9
    //   1680: ldc 8396800
    //   1682: iastore
    //   1683: dup
    //   1684: bipush #10
    //   1686: ldc 8396800
    //   1688: iastore
    //   1689: dup
    //   1690: bipush #11
    //   1692: ldc 8396929
    //   1694: iastore
    //   1695: dup
    //   1696: bipush #12
    //   1698: sipush #129
    //   1701: iastore
    //   1702: dup
    //   1703: bipush #13
    //   1705: iconst_0
    //   1706: iastore
    //   1707: dup
    //   1708: bipush #14
    //   1710: ldc 8388736
    //   1712: iastore
    //   1713: dup
    //   1714: bipush #15
    //   1716: ldc 8388609
    //   1718: iastore
    //   1719: dup
    //   1720: bipush #16
    //   1722: iconst_1
    //   1723: iastore
    //   1724: dup
    //   1725: bipush #17
    //   1727: sipush #8192
    //   1730: iastore
    //   1731: dup
    //   1732: bipush #18
    //   1734: ldc 8388608
    //   1736: iastore
    //   1737: dup
    //   1738: bipush #19
    //   1740: ldc 8396801
    //   1742: iastore
    //   1743: dup
    //   1744: bipush #20
    //   1746: sipush #128
    //   1749: iastore
    //   1750: dup
    //   1751: bipush #21
    //   1753: ldc 8388608
    //   1755: iastore
    //   1756: dup
    //   1757: bipush #22
    //   1759: sipush #8193
    //   1762: iastore
    //   1763: dup
    //   1764: bipush #23
    //   1766: sipush #8320
    //   1769: iastore
    //   1770: dup
    //   1771: bipush #24
    //   1773: ldc 8388737
    //   1775: iastore
    //   1776: dup
    //   1777: bipush #25
    //   1779: iconst_1
    //   1780: iastore
    //   1781: dup
    //   1782: bipush #26
    //   1784: sipush #8320
    //   1787: iastore
    //   1788: dup
    //   1789: bipush #27
    //   1791: ldc 8388736
    //   1793: iastore
    //   1794: dup
    //   1795: bipush #28
    //   1797: sipush #8192
    //   1800: iastore
    //   1801: dup
    //   1802: bipush #29
    //   1804: ldc 8396928
    //   1806: iastore
    //   1807: dup
    //   1808: bipush #30
    //   1810: ldc 8396929
    //   1812: iastore
    //   1813: dup
    //   1814: bipush #31
    //   1816: sipush #129
    //   1819: iastore
    //   1820: dup
    //   1821: bipush #32
    //   1823: ldc 8388736
    //   1825: iastore
    //   1826: dup
    //   1827: bipush #33
    //   1829: ldc 8388609
    //   1831: iastore
    //   1832: dup
    //   1833: bipush #34
    //   1835: ldc 8396800
    //   1837: iastore
    //   1838: dup
    //   1839: bipush #35
    //   1841: ldc 8396929
    //   1843: iastore
    //   1844: dup
    //   1845: bipush #36
    //   1847: sipush #129
    //   1850: iastore
    //   1851: dup
    //   1852: bipush #37
    //   1854: iconst_0
    //   1855: iastore
    //   1856: dup
    //   1857: bipush #38
    //   1859: iconst_0
    //   1860: iastore
    //   1861: dup
    //   1862: bipush #39
    //   1864: ldc 8396800
    //   1866: iastore
    //   1867: dup
    //   1868: bipush #40
    //   1870: sipush #8320
    //   1873: iastore
    //   1874: dup
    //   1875: bipush #41
    //   1877: ldc 8388736
    //   1879: iastore
    //   1880: dup
    //   1881: bipush #42
    //   1883: ldc 8388737
    //   1885: iastore
    //   1886: dup
    //   1887: bipush #43
    //   1889: iconst_1
    //   1890: iastore
    //   1891: dup
    //   1892: bipush #44
    //   1894: ldc 8396801
    //   1896: iastore
    //   1897: dup
    //   1898: bipush #45
    //   1900: sipush #8321
    //   1903: iastore
    //   1904: dup
    //   1905: bipush #46
    //   1907: sipush #8321
    //   1910: iastore
    //   1911: dup
    //   1912: bipush #47
    //   1914: sipush #128
    //   1917: iastore
    //   1918: dup
    //   1919: bipush #48
    //   1921: ldc 8396929
    //   1923: iastore
    //   1924: dup
    //   1925: bipush #49
    //   1927: sipush #129
    //   1930: iastore
    //   1931: dup
    //   1932: bipush #50
    //   1934: iconst_1
    //   1935: iastore
    //   1936: dup
    //   1937: bipush #51
    //   1939: sipush #8192
    //   1942: iastore
    //   1943: dup
    //   1944: bipush #52
    //   1946: ldc 8388609
    //   1948: iastore
    //   1949: dup
    //   1950: bipush #53
    //   1952: sipush #8193
    //   1955: iastore
    //   1956: dup
    //   1957: bipush #54
    //   1959: ldc 8396928
    //   1961: iastore
    //   1962: dup
    //   1963: bipush #55
    //   1965: ldc 8388737
    //   1967: iastore
    //   1968: dup
    //   1969: bipush #56
    //   1971: sipush #8193
    //   1974: iastore
    //   1975: dup
    //   1976: bipush #57
    //   1978: sipush #8320
    //   1981: iastore
    //   1982: dup
    //   1983: bipush #58
    //   1985: ldc 8388608
    //   1987: iastore
    //   1988: dup
    //   1989: bipush #59
    //   1991: ldc 8396801
    //   1993: iastore
    //   1994: dup
    //   1995: bipush #60
    //   1997: sipush #128
    //   2000: iastore
    //   2001: dup
    //   2002: bipush #61
    //   2004: ldc 8388608
    //   2006: iastore
    //   2007: dup
    //   2008: bipush #62
    //   2010: sipush #8192
    //   2013: iastore
    //   2014: dup
    //   2015: bipush #63
    //   2017: ldc 8396928
    //   2019: iastore
    //   2020: astore #9
    //   2022: bipush #64
    //   2024: newarray int
    //   2026: dup
    //   2027: iconst_0
    //   2028: sipush #256
    //   2031: iastore
    //   2032: dup
    //   2033: iconst_1
    //   2034: ldc 34078976
    //   2036: iastore
    //   2037: dup
    //   2038: iconst_2
    //   2039: ldc 34078720
    //   2041: iastore
    //   2042: dup
    //   2043: iconst_3
    //   2044: ldc 1107296512
    //   2046: iastore
    //   2047: dup
    //   2048: iconst_4
    //   2049: ldc 524288
    //   2051: iastore
    //   2052: dup
    //   2053: iconst_5
    //   2054: sipush #256
    //   2057: iastore
    //   2058: dup
    //   2059: bipush #6
    //   2061: ldc 1073741824
    //   2063: iastore
    //   2064: dup
    //   2065: bipush #7
    //   2067: ldc 34078720
    //   2069: iastore
    //   2070: dup
    //   2071: bipush #8
    //   2073: ldc 1074266368
    //   2075: iastore
    //   2076: dup
    //   2077: bipush #9
    //   2079: ldc 524288
    //   2081: iastore
    //   2082: dup
    //   2083: bipush #10
    //   2085: ldc 33554688
    //   2087: iastore
    //   2088: dup
    //   2089: bipush #11
    //   2091: ldc 1074266368
    //   2093: iastore
    //   2094: dup
    //   2095: bipush #12
    //   2097: ldc 1107296512
    //   2099: iastore
    //   2100: dup
    //   2101: bipush #13
    //   2103: ldc 1107820544
    //   2105: iastore
    //   2106: dup
    //   2107: bipush #14
    //   2109: ldc 524544
    //   2111: iastore
    //   2112: dup
    //   2113: bipush #15
    //   2115: ldc 1073741824
    //   2117: iastore
    //   2118: dup
    //   2119: bipush #16
    //   2121: ldc 33554432
    //   2123: iastore
    //   2124: dup
    //   2125: bipush #17
    //   2127: ldc 1074266112
    //   2129: iastore
    //   2130: dup
    //   2131: bipush #18
    //   2133: ldc 1074266112
    //   2135: iastore
    //   2136: dup
    //   2137: bipush #19
    //   2139: iconst_0
    //   2140: iastore
    //   2141: dup
    //   2142: bipush #20
    //   2144: ldc 1073742080
    //   2146: iastore
    //   2147: dup
    //   2148: bipush #21
    //   2150: ldc 1107820800
    //   2152: iastore
    //   2153: dup
    //   2154: bipush #22
    //   2156: ldc 1107820800
    //   2158: iastore
    //   2159: dup
    //   2160: bipush #23
    //   2162: ldc 33554688
    //   2164: iastore
    //   2165: dup
    //   2166: bipush #24
    //   2168: ldc 1107820544
    //   2170: iastore
    //   2171: dup
    //   2172: bipush #25
    //   2174: ldc 1073742080
    //   2176: iastore
    //   2177: dup
    //   2178: bipush #26
    //   2180: iconst_0
    //   2181: iastore
    //   2182: dup
    //   2183: bipush #27
    //   2185: ldc 1107296256
    //   2187: iastore
    //   2188: dup
    //   2189: bipush #28
    //   2191: ldc 34078976
    //   2193: iastore
    //   2194: dup
    //   2195: bipush #29
    //   2197: ldc 33554432
    //   2199: iastore
    //   2200: dup
    //   2201: bipush #30
    //   2203: ldc 1107296256
    //   2205: iastore
    //   2206: dup
    //   2207: bipush #31
    //   2209: ldc 524544
    //   2211: iastore
    //   2212: dup
    //   2213: bipush #32
    //   2215: ldc 524288
    //   2217: iastore
    //   2218: dup
    //   2219: bipush #33
    //   2221: ldc 1107296512
    //   2223: iastore
    //   2224: dup
    //   2225: bipush #34
    //   2227: sipush #256
    //   2230: iastore
    //   2231: dup
    //   2232: bipush #35
    //   2234: ldc 33554432
    //   2236: iastore
    //   2237: dup
    //   2238: bipush #36
    //   2240: ldc 1073741824
    //   2242: iastore
    //   2243: dup
    //   2244: bipush #37
    //   2246: ldc 34078720
    //   2248: iastore
    //   2249: dup
    //   2250: bipush #38
    //   2252: ldc 1107296512
    //   2254: iastore
    //   2255: dup
    //   2256: bipush #39
    //   2258: ldc 1074266368
    //   2260: iastore
    //   2261: dup
    //   2262: bipush #40
    //   2264: ldc 33554688
    //   2266: iastore
    //   2267: dup
    //   2268: bipush #41
    //   2270: ldc 1073741824
    //   2272: iastore
    //   2273: dup
    //   2274: bipush #42
    //   2276: ldc 1107820544
    //   2278: iastore
    //   2279: dup
    //   2280: bipush #43
    //   2282: ldc 34078976
    //   2284: iastore
    //   2285: dup
    //   2286: bipush #44
    //   2288: ldc 1074266368
    //   2290: iastore
    //   2291: dup
    //   2292: bipush #45
    //   2294: sipush #256
    //   2297: iastore
    //   2298: dup
    //   2299: bipush #46
    //   2301: ldc 33554432
    //   2303: iastore
    //   2304: dup
    //   2305: bipush #47
    //   2307: ldc 1107820544
    //   2309: iastore
    //   2310: dup
    //   2311: bipush #48
    //   2313: ldc 1107820800
    //   2315: iastore
    //   2316: dup
    //   2317: bipush #49
    //   2319: ldc 524544
    //   2321: iastore
    //   2322: dup
    //   2323: bipush #50
    //   2325: ldc 1107296256
    //   2327: iastore
    //   2328: dup
    //   2329: bipush #51
    //   2331: ldc 1107820800
    //   2333: iastore
    //   2334: dup
    //   2335: bipush #52
    //   2337: ldc 34078720
    //   2339: iastore
    //   2340: dup
    //   2341: bipush #53
    //   2343: iconst_0
    //   2344: iastore
    //   2345: dup
    //   2346: bipush #54
    //   2348: ldc 1074266112
    //   2350: iastore
    //   2351: dup
    //   2352: bipush #55
    //   2354: ldc 1107296256
    //   2356: iastore
    //   2357: dup
    //   2358: bipush #56
    //   2360: ldc 524544
    //   2362: iastore
    //   2363: dup
    //   2364: bipush #57
    //   2366: ldc 33554688
    //   2368: iastore
    //   2369: dup
    //   2370: bipush #58
    //   2372: ldc 1073742080
    //   2374: iastore
    //   2375: dup
    //   2376: bipush #59
    //   2378: ldc 524288
    //   2380: iastore
    //   2381: dup
    //   2382: bipush #60
    //   2384: iconst_0
    //   2385: iastore
    //   2386: dup
    //   2387: bipush #61
    //   2389: ldc 1074266112
    //   2391: iastore
    //   2392: dup
    //   2393: bipush #62
    //   2395: ldc 34078976
    //   2397: iastore
    //   2398: dup
    //   2399: bipush #63
    //   2401: ldc 1073742080
    //   2403: iastore
    //   2404: astore #10
    //   2406: bipush #64
    //   2408: newarray int
    //   2410: dup
    //   2411: iconst_0
    //   2412: ldc 536870928
    //   2414: iastore
    //   2415: dup
    //   2416: iconst_1
    //   2417: ldc 541065216
    //   2419: iastore
    //   2420: dup
    //   2421: iconst_2
    //   2422: sipush #16384
    //   2425: iastore
    //   2426: dup
    //   2427: iconst_3
    //   2428: ldc 541081616
    //   2430: iastore
    //   2431: dup
    //   2432: iconst_4
    //   2433: ldc 541065216
    //   2435: iastore
    //   2436: dup
    //   2437: iconst_5
    //   2438: bipush #16
    //   2440: iastore
    //   2441: dup
    //   2442: bipush #6
    //   2444: ldc 541081616
    //   2446: iastore
    //   2447: dup
    //   2448: bipush #7
    //   2450: ldc 4194304
    //   2452: iastore
    //   2453: dup
    //   2454: bipush #8
    //   2456: ldc 536887296
    //   2458: iastore
    //   2459: dup
    //   2460: bipush #9
    //   2462: ldc 4210704
    //   2464: iastore
    //   2465: dup
    //   2466: bipush #10
    //   2468: ldc 4194304
    //   2470: iastore
    //   2471: dup
    //   2472: bipush #11
    //   2474: ldc 536870928
    //   2476: iastore
    //   2477: dup
    //   2478: bipush #12
    //   2480: ldc 4194320
    //   2482: iastore
    //   2483: dup
    //   2484: bipush #13
    //   2486: ldc 536887296
    //   2488: iastore
    //   2489: dup
    //   2490: bipush #14
    //   2492: ldc 536870912
    //   2494: iastore
    //   2495: dup
    //   2496: bipush #15
    //   2498: sipush #16400
    //   2501: iastore
    //   2502: dup
    //   2503: bipush #16
    //   2505: iconst_0
    //   2506: iastore
    //   2507: dup
    //   2508: bipush #17
    //   2510: ldc 4194320
    //   2512: iastore
    //   2513: dup
    //   2514: bipush #18
    //   2516: ldc 536887312
    //   2518: iastore
    //   2519: dup
    //   2520: bipush #19
    //   2522: sipush #16384
    //   2525: iastore
    //   2526: dup
    //   2527: bipush #20
    //   2529: ldc 4210688
    //   2531: iastore
    //   2532: dup
    //   2533: bipush #21
    //   2535: ldc 536887312
    //   2537: iastore
    //   2538: dup
    //   2539: bipush #22
    //   2541: bipush #16
    //   2543: iastore
    //   2544: dup
    //   2545: bipush #23
    //   2547: ldc 541065232
    //   2549: iastore
    //   2550: dup
    //   2551: bipush #24
    //   2553: ldc 541065232
    //   2555: iastore
    //   2556: dup
    //   2557: bipush #25
    //   2559: iconst_0
    //   2560: iastore
    //   2561: dup
    //   2562: bipush #26
    //   2564: ldc 4210704
    //   2566: iastore
    //   2567: dup
    //   2568: bipush #27
    //   2570: ldc 541081600
    //   2572: iastore
    //   2573: dup
    //   2574: bipush #28
    //   2576: sipush #16400
    //   2579: iastore
    //   2580: dup
    //   2581: bipush #29
    //   2583: ldc 4210688
    //   2585: iastore
    //   2586: dup
    //   2587: bipush #30
    //   2589: ldc 541081600
    //   2591: iastore
    //   2592: dup
    //   2593: bipush #31
    //   2595: ldc 536870912
    //   2597: iastore
    //   2598: dup
    //   2599: bipush #32
    //   2601: ldc 536887296
    //   2603: iastore
    //   2604: dup
    //   2605: bipush #33
    //   2607: bipush #16
    //   2609: iastore
    //   2610: dup
    //   2611: bipush #34
    //   2613: ldc 541065232
    //   2615: iastore
    //   2616: dup
    //   2617: bipush #35
    //   2619: ldc 4210688
    //   2621: iastore
    //   2622: dup
    //   2623: bipush #36
    //   2625: ldc 541081616
    //   2627: iastore
    //   2628: dup
    //   2629: bipush #37
    //   2631: ldc 4194304
    //   2633: iastore
    //   2634: dup
    //   2635: bipush #38
    //   2637: sipush #16400
    //   2640: iastore
    //   2641: dup
    //   2642: bipush #39
    //   2644: ldc 536870928
    //   2646: iastore
    //   2647: dup
    //   2648: bipush #40
    //   2650: ldc 4194304
    //   2652: iastore
    //   2653: dup
    //   2654: bipush #41
    //   2656: ldc 536887296
    //   2658: iastore
    //   2659: dup
    //   2660: bipush #42
    //   2662: ldc 536870912
    //   2664: iastore
    //   2665: dup
    //   2666: bipush #43
    //   2668: sipush #16400
    //   2671: iastore
    //   2672: dup
    //   2673: bipush #44
    //   2675: ldc 536870928
    //   2677: iastore
    //   2678: dup
    //   2679: bipush #45
    //   2681: ldc 541081616
    //   2683: iastore
    //   2684: dup
    //   2685: bipush #46
    //   2687: ldc 4210688
    //   2689: iastore
    //   2690: dup
    //   2691: bipush #47
    //   2693: ldc 541065216
    //   2695: iastore
    //   2696: dup
    //   2697: bipush #48
    //   2699: ldc 4210704
    //   2701: iastore
    //   2702: dup
    //   2703: bipush #49
    //   2705: ldc 541081600
    //   2707: iastore
    //   2708: dup
    //   2709: bipush #50
    //   2711: iconst_0
    //   2712: iastore
    //   2713: dup
    //   2714: bipush #51
    //   2716: ldc 541065232
    //   2718: iastore
    //   2719: dup
    //   2720: bipush #52
    //   2722: bipush #16
    //   2724: iastore
    //   2725: dup
    //   2726: bipush #53
    //   2728: sipush #16384
    //   2731: iastore
    //   2732: dup
    //   2733: bipush #54
    //   2735: ldc 541065216
    //   2737: iastore
    //   2738: dup
    //   2739: bipush #55
    //   2741: ldc 4210704
    //   2743: iastore
    //   2744: dup
    //   2745: bipush #56
    //   2747: sipush #16384
    //   2750: iastore
    //   2751: dup
    //   2752: bipush #57
    //   2754: ldc 4194320
    //   2756: iastore
    //   2757: dup
    //   2758: bipush #58
    //   2760: ldc 536887312
    //   2762: iastore
    //   2763: dup
    //   2764: bipush #59
    //   2766: iconst_0
    //   2767: iastore
    //   2768: dup
    //   2769: bipush #60
    //   2771: ldc 541081600
    //   2773: iastore
    //   2774: dup
    //   2775: bipush #61
    //   2777: ldc 536870912
    //   2779: iastore
    //   2780: dup
    //   2781: bipush #62
    //   2783: ldc 4194320
    //   2785: iastore
    //   2786: dup
    //   2787: bipush #63
    //   2789: ldc 536887312
    //   2791: iastore
    //   2792: astore #11
    //   2794: bipush #64
    //   2796: newarray int
    //   2798: dup
    //   2799: iconst_0
    //   2800: ldc 2097152
    //   2802: iastore
    //   2803: dup
    //   2804: iconst_1
    //   2805: ldc 69206018
    //   2807: iastore
    //   2808: dup
    //   2809: iconst_2
    //   2810: ldc 67110914
    //   2812: iastore
    //   2813: dup
    //   2814: iconst_3
    //   2815: iconst_0
    //   2816: iastore
    //   2817: dup
    //   2818: iconst_4
    //   2819: sipush #2048
    //   2822: iastore
    //   2823: dup
    //   2824: iconst_5
    //   2825: ldc 67110914
    //   2827: iastore
    //   2828: dup
    //   2829: bipush #6
    //   2831: ldc 2099202
    //   2833: iastore
    //   2834: dup
    //   2835: bipush #7
    //   2837: ldc 69208064
    //   2839: iastore
    //   2840: dup
    //   2841: bipush #8
    //   2843: ldc 69208066
    //   2845: iastore
    //   2846: dup
    //   2847: bipush #9
    //   2849: ldc 2097152
    //   2851: iastore
    //   2852: dup
    //   2853: bipush #10
    //   2855: iconst_0
    //   2856: iastore
    //   2857: dup
    //   2858: bipush #11
    //   2860: ldc 67108866
    //   2862: iastore
    //   2863: dup
    //   2864: bipush #12
    //   2866: iconst_2
    //   2867: iastore
    //   2868: dup
    //   2869: bipush #13
    //   2871: ldc 67108864
    //   2873: iastore
    //   2874: dup
    //   2875: bipush #14
    //   2877: ldc 69206018
    //   2879: iastore
    //   2880: dup
    //   2881: bipush #15
    //   2883: sipush #2050
    //   2886: iastore
    //   2887: dup
    //   2888: bipush #16
    //   2890: ldc 67110912
    //   2892: iastore
    //   2893: dup
    //   2894: bipush #17
    //   2896: ldc 2099202
    //   2898: iastore
    //   2899: dup
    //   2900: bipush #18
    //   2902: ldc 2097154
    //   2904: iastore
    //   2905: dup
    //   2906: bipush #19
    //   2908: ldc 67110912
    //   2910: iastore
    //   2911: dup
    //   2912: bipush #20
    //   2914: ldc 67108866
    //   2916: iastore
    //   2917: dup
    //   2918: bipush #21
    //   2920: ldc 69206016
    //   2922: iastore
    //   2923: dup
    //   2924: bipush #22
    //   2926: ldc 69208064
    //   2928: iastore
    //   2929: dup
    //   2930: bipush #23
    //   2932: ldc 2097154
    //   2934: iastore
    //   2935: dup
    //   2936: bipush #24
    //   2938: ldc 69206016
    //   2940: iastore
    //   2941: dup
    //   2942: bipush #25
    //   2944: sipush #2048
    //   2947: iastore
    //   2948: dup
    //   2949: bipush #26
    //   2951: sipush #2050
    //   2954: iastore
    //   2955: dup
    //   2956: bipush #27
    //   2958: ldc 69208066
    //   2960: iastore
    //   2961: dup
    //   2962: bipush #28
    //   2964: ldc 2099200
    //   2966: iastore
    //   2967: dup
    //   2968: bipush #29
    //   2970: iconst_2
    //   2971: iastore
    //   2972: dup
    //   2973: bipush #30
    //   2975: ldc 67108864
    //   2977: iastore
    //   2978: dup
    //   2979: bipush #31
    //   2981: ldc 2099200
    //   2983: iastore
    //   2984: dup
    //   2985: bipush #32
    //   2987: ldc 67108864
    //   2989: iastore
    //   2990: dup
    //   2991: bipush #33
    //   2993: ldc 2099200
    //   2995: iastore
    //   2996: dup
    //   2997: bipush #34
    //   2999: ldc 2097152
    //   3001: iastore
    //   3002: dup
    //   3003: bipush #35
    //   3005: ldc 67110914
    //   3007: iastore
    //   3008: dup
    //   3009: bipush #36
    //   3011: ldc 67110914
    //   3013: iastore
    //   3014: dup
    //   3015: bipush #37
    //   3017: ldc 69206018
    //   3019: iastore
    //   3020: dup
    //   3021: bipush #38
    //   3023: ldc 69206018
    //   3025: iastore
    //   3026: dup
    //   3027: bipush #39
    //   3029: iconst_2
    //   3030: iastore
    //   3031: dup
    //   3032: bipush #40
    //   3034: ldc 2097154
    //   3036: iastore
    //   3037: dup
    //   3038: bipush #41
    //   3040: ldc 67108864
    //   3042: iastore
    //   3043: dup
    //   3044: bipush #42
    //   3046: ldc 67110912
    //   3048: iastore
    //   3049: dup
    //   3050: bipush #43
    //   3052: ldc 2097152
    //   3054: iastore
    //   3055: dup
    //   3056: bipush #44
    //   3058: ldc 69208064
    //   3060: iastore
    //   3061: dup
    //   3062: bipush #45
    //   3064: sipush #2050
    //   3067: iastore
    //   3068: dup
    //   3069: bipush #46
    //   3071: ldc 2099202
    //   3073: iastore
    //   3074: dup
    //   3075: bipush #47
    //   3077: ldc 69208064
    //   3079: iastore
    //   3080: dup
    //   3081: bipush #48
    //   3083: sipush #2050
    //   3086: iastore
    //   3087: dup
    //   3088: bipush #49
    //   3090: ldc 67108866
    //   3092: iastore
    //   3093: dup
    //   3094: bipush #50
    //   3096: ldc 69208066
    //   3098: iastore
    //   3099: dup
    //   3100: bipush #51
    //   3102: ldc 69206016
    //   3104: iastore
    //   3105: dup
    //   3106: bipush #52
    //   3108: ldc 2099200
    //   3110: iastore
    //   3111: dup
    //   3112: bipush #53
    //   3114: iconst_0
    //   3115: iastore
    //   3116: dup
    //   3117: bipush #54
    //   3119: iconst_2
    //   3120: iastore
    //   3121: dup
    //   3122: bipush #55
    //   3124: ldc 69208066
    //   3126: iastore
    //   3127: dup
    //   3128: bipush #56
    //   3130: iconst_0
    //   3131: iastore
    //   3132: dup
    //   3133: bipush #57
    //   3135: ldc 2099202
    //   3137: iastore
    //   3138: dup
    //   3139: bipush #58
    //   3141: ldc 69206016
    //   3143: iastore
    //   3144: dup
    //   3145: bipush #59
    //   3147: sipush #2048
    //   3150: iastore
    //   3151: dup
    //   3152: bipush #60
    //   3154: ldc 67108866
    //   3156: iastore
    //   3157: dup
    //   3158: bipush #61
    //   3160: ldc 67110912
    //   3162: iastore
    //   3163: dup
    //   3164: bipush #62
    //   3166: sipush #2048
    //   3169: iastore
    //   3170: dup
    //   3171: bipush #63
    //   3173: ldc 2097154
    //   3175: iastore
    //   3176: astore #12
    //   3178: bipush #64
    //   3180: newarray int
    //   3182: dup
    //   3183: iconst_0
    //   3184: ldc 268439616
    //   3186: iastore
    //   3187: dup
    //   3188: iconst_1
    //   3189: sipush #4096
    //   3192: iastore
    //   3193: dup
    //   3194: iconst_2
    //   3195: ldc 262144
    //   3197: iastore
    //   3198: dup
    //   3199: iconst_3
    //   3200: ldc 268701760
    //   3202: iastore
    //   3203: dup
    //   3204: iconst_4
    //   3205: ldc 268435456
    //   3207: iastore
    //   3208: dup
    //   3209: iconst_5
    //   3210: ldc 268439616
    //   3212: iastore
    //   3213: dup
    //   3214: bipush #6
    //   3216: bipush #64
    //   3218: iastore
    //   3219: dup
    //   3220: bipush #7
    //   3222: ldc 268435456
    //   3224: iastore
    //   3225: dup
    //   3226: bipush #8
    //   3228: ldc 262208
    //   3230: iastore
    //   3231: dup
    //   3232: bipush #9
    //   3234: ldc 268697600
    //   3236: iastore
    //   3237: dup
    //   3238: bipush #10
    //   3240: ldc 268701760
    //   3242: iastore
    //   3243: dup
    //   3244: bipush #11
    //   3246: ldc 266240
    //   3248: iastore
    //   3249: dup
    //   3250: bipush #12
    //   3252: ldc 268701696
    //   3254: iastore
    //   3255: dup
    //   3256: bipush #13
    //   3258: ldc 266304
    //   3260: iastore
    //   3261: dup
    //   3262: bipush #14
    //   3264: sipush #4096
    //   3267: iastore
    //   3268: dup
    //   3269: bipush #15
    //   3271: bipush #64
    //   3273: iastore
    //   3274: dup
    //   3275: bipush #16
    //   3277: ldc 268697600
    //   3279: iastore
    //   3280: dup
    //   3281: bipush #17
    //   3283: ldc 268435520
    //   3285: iastore
    //   3286: dup
    //   3287: bipush #18
    //   3289: ldc 268439552
    //   3291: iastore
    //   3292: dup
    //   3293: bipush #19
    //   3295: sipush #4160
    //   3298: iastore
    //   3299: dup
    //   3300: bipush #20
    //   3302: ldc 266240
    //   3304: iastore
    //   3305: dup
    //   3306: bipush #21
    //   3308: ldc 262208
    //   3310: iastore
    //   3311: dup
    //   3312: bipush #22
    //   3314: ldc 268697664
    //   3316: iastore
    //   3317: dup
    //   3318: bipush #23
    //   3320: ldc 268701696
    //   3322: iastore
    //   3323: dup
    //   3324: bipush #24
    //   3326: sipush #4160
    //   3329: iastore
    //   3330: dup
    //   3331: bipush #25
    //   3333: iconst_0
    //   3334: iastore
    //   3335: dup
    //   3336: bipush #26
    //   3338: iconst_0
    //   3339: iastore
    //   3340: dup
    //   3341: bipush #27
    //   3343: ldc 268697664
    //   3345: iastore
    //   3346: dup
    //   3347: bipush #28
    //   3349: ldc 268435520
    //   3351: iastore
    //   3352: dup
    //   3353: bipush #29
    //   3355: ldc 268439552
    //   3357: iastore
    //   3358: dup
    //   3359: bipush #30
    //   3361: ldc 266304
    //   3363: iastore
    //   3364: dup
    //   3365: bipush #31
    //   3367: ldc 262144
    //   3369: iastore
    //   3370: dup
    //   3371: bipush #32
    //   3373: ldc 266304
    //   3375: iastore
    //   3376: dup
    //   3377: bipush #33
    //   3379: ldc 262144
    //   3381: iastore
    //   3382: dup
    //   3383: bipush #34
    //   3385: ldc 268701696
    //   3387: iastore
    //   3388: dup
    //   3389: bipush #35
    //   3391: sipush #4096
    //   3394: iastore
    //   3395: dup
    //   3396: bipush #36
    //   3398: bipush #64
    //   3400: iastore
    //   3401: dup
    //   3402: bipush #37
    //   3404: ldc 268697664
    //   3406: iastore
    //   3407: dup
    //   3408: bipush #38
    //   3410: sipush #4096
    //   3413: iastore
    //   3414: dup
    //   3415: bipush #39
    //   3417: ldc 266304
    //   3419: iastore
    //   3420: dup
    //   3421: bipush #40
    //   3423: ldc 268439552
    //   3425: iastore
    //   3426: dup
    //   3427: bipush #41
    //   3429: bipush #64
    //   3431: iastore
    //   3432: dup
    //   3433: bipush #42
    //   3435: ldc 268435520
    //   3437: iastore
    //   3438: dup
    //   3439: bipush #43
    //   3441: ldc 268697600
    //   3443: iastore
    //   3444: dup
    //   3445: bipush #44
    //   3447: ldc 268697664
    //   3449: iastore
    //   3450: dup
    //   3451: bipush #45
    //   3453: ldc 268435456
    //   3455: iastore
    //   3456: dup
    //   3457: bipush #46
    //   3459: ldc 262144
    //   3461: iastore
    //   3462: dup
    //   3463: bipush #47
    //   3465: ldc 268439616
    //   3467: iastore
    //   3468: dup
    //   3469: bipush #48
    //   3471: iconst_0
    //   3472: iastore
    //   3473: dup
    //   3474: bipush #49
    //   3476: ldc 268701760
    //   3478: iastore
    //   3479: dup
    //   3480: bipush #50
    //   3482: ldc 262208
    //   3484: iastore
    //   3485: dup
    //   3486: bipush #51
    //   3488: ldc 268435520
    //   3490: iastore
    //   3491: dup
    //   3492: bipush #52
    //   3494: ldc 268697600
    //   3496: iastore
    //   3497: dup
    //   3498: bipush #53
    //   3500: ldc 268439552
    //   3502: iastore
    //   3503: dup
    //   3504: bipush #54
    //   3506: ldc 268439616
    //   3508: iastore
    //   3509: dup
    //   3510: bipush #55
    //   3512: iconst_0
    //   3513: iastore
    //   3514: dup
    //   3515: bipush #56
    //   3517: ldc 268701760
    //   3519: iastore
    //   3520: dup
    //   3521: bipush #57
    //   3523: ldc 266240
    //   3525: iastore
    //   3526: dup
    //   3527: bipush #58
    //   3529: ldc 266240
    //   3531: iastore
    //   3532: dup
    //   3533: bipush #59
    //   3535: sipush #4160
    //   3538: iastore
    //   3539: dup
    //   3540: bipush #60
    //   3542: sipush #4160
    //   3545: iastore
    //   3546: dup
    //   3547: bipush #61
    //   3549: ldc 262208
    //   3551: iastore
    //   3552: dup
    //   3553: bipush #62
    //   3555: ldc 268435456
    //   3557: iastore
    //   3558: dup
    //   3559: bipush #63
    //   3561: ldc 268701696
    //   3563: iastore
    //   3564: astore #13
    //   3566: aload_3
    //   3567: arraylength
    //   3568: istore #14
    //   3570: iload #14
    //   3572: bipush #8
    //   3574: irem
    //   3575: ifeq -> 3599
    //   3578: new java/lang/Exception
    //   3581: dup
    //   3582: sipush #14367
    //   3585: sipush #5890
    //   3588: invokestatic a : (II)Ljava/lang/String;
    //   3591: invokespecial <init> : (Ljava/lang/String;)V
    //   3594: athrow
    //   3595: invokestatic a : (Ljava/lang/Throwable;)Ljava/lang/Throwable;
    //   3598: athrow
    //   3599: iconst_2
    //   3600: newarray int
    //   3602: astore #15
    //   3604: iload #14
    //   3606: newarray byte
    //   3608: astore #16
    //   3610: iload #14
    //   3612: bipush #8
    //   3614: idiv
    //   3615: istore #17
    //   3617: iconst_0
    //   3618: istore #18
    //   3620: iload #18
    //   3622: iload #17
    //   3624: if_icmpge -> 4538
    //   3627: iload #18
    //   3629: bipush #8
    //   3631: imul
    //   3632: istore #19
    //   3634: iconst_0
    //   3635: istore #20
    //   3637: iload #20
    //   3639: iconst_2
    //   3640: if_icmpge -> 3725
    //   3643: aload #15
    //   3645: iload #20
    //   3647: aload_3
    //   3648: iload #19
    //   3650: iload #20
    //   3652: iconst_4
    //   3653: imul
    //   3654: iadd
    //   3655: baload
    //   3656: sipush #255
    //   3659: iand
    //   3660: bipush #24
    //   3662: ishl
    //   3663: aload_3
    //   3664: iload #19
    //   3666: iload #20
    //   3668: iconst_4
    //   3669: imul
    //   3670: iadd
    //   3671: iconst_1
    //   3672: iadd
    //   3673: baload
    //   3674: sipush #255
    //   3677: iand
    //   3678: bipush #16
    //   3680: ishl
    //   3681: ior
    //   3682: aload_3
    //   3683: iload #19
    //   3685: iload #20
    //   3687: iconst_4
    //   3688: imul
    //   3689: iadd
    //   3690: iconst_2
    //   3691: iadd
    //   3692: baload
    //   3693: sipush #255
    //   3696: iand
    //   3697: bipush #8
    //   3699: ishl
    //   3700: ior
    //   3701: aload_3
    //   3702: iload #19
    //   3704: iload #20
    //   3706: iconst_4
    //   3707: imul
    //   3708: iadd
    //   3709: iconst_3
    //   3710: iadd
    //   3711: baload
    //   3712: sipush #255
    //   3715: iand
    //   3716: ior
    //   3717: iastore
    //   3718: iinc #20, 1
    //   3721: iload_2
    //   3722: ifne -> 3637
    //   3725: iconst_0
    //   3726: istore #25
    //   3728: aload #15
    //   3730: iconst_0
    //   3731: iaload
    //   3732: istore #23
    //   3734: aload #15
    //   3736: iconst_1
    //   3737: iaload
    //   3738: istore #22
    //   3740: iload #23
    //   3742: iconst_4
    //   3743: iushr
    //   3744: iload #22
    //   3746: ixor
    //   3747: ldc 252645135
    //   3749: iand
    //   3750: istore #21
    //   3752: iload #22
    //   3754: iload #21
    //   3756: ixor
    //   3757: istore #22
    //   3759: iload #23
    //   3761: iload #21
    //   3763: iconst_4
    //   3764: ishl
    //   3765: ixor
    //   3766: istore #23
    //   3768: iload #23
    //   3770: bipush #16
    //   3772: iushr
    //   3773: iload #22
    //   3775: ixor
    //   3776: ldc 65535
    //   3778: iand
    //   3779: istore #21
    //   3781: iload #22
    //   3783: iload #21
    //   3785: ixor
    //   3786: istore #22
    //   3788: iload #23
    //   3790: iload #21
    //   3792: bipush #16
    //   3794: ishl
    //   3795: ixor
    //   3796: istore #23
    //   3798: iload #22
    //   3800: iconst_2
    //   3801: iushr
    //   3802: iload #23
    //   3804: ixor
    //   3805: ldc 858993459
    //   3807: iand
    //   3808: istore #21
    //   3810: iload #23
    //   3812: iload #21
    //   3814: ixor
    //   3815: istore #23
    //   3817: iload #22
    //   3819: iload #21
    //   3821: iconst_2
    //   3822: ishl
    //   3823: ixor
    //   3824: istore #22
    //   3826: iload #22
    //   3828: bipush #8
    //   3830: iushr
    //   3831: iload #23
    //   3833: ixor
    //   3834: ldc 16711935
    //   3836: iand
    //   3837: istore #21
    //   3839: iload #23
    //   3841: iload #21
    //   3843: ixor
    //   3844: istore #23
    //   3846: iload #22
    //   3848: iload #21
    //   3850: bipush #8
    //   3852: ishl
    //   3853: ixor
    //   3854: istore #22
    //   3856: iload #22
    //   3858: iconst_1
    //   3859: ishl
    //   3860: iload #22
    //   3862: bipush #31
    //   3864: iushr
    //   3865: iconst_1
    //   3866: iand
    //   3867: ior
    //   3868: istore #22
    //   3870: iload #23
    //   3872: iload #22
    //   3874: ixor
    //   3875: ldc -1431655766
    //   3877: iand
    //   3878: istore #21
    //   3880: iload #23
    //   3882: iload #21
    //   3884: ixor
    //   3885: istore #23
    //   3887: iload #22
    //   3889: iload #21
    //   3891: ixor
    //   3892: istore #22
    //   3894: iload #23
    //   3896: iconst_1
    //   3897: ishl
    //   3898: iload #23
    //   3900: bipush #31
    //   3902: iushr
    //   3903: iconst_1
    //   3904: iand
    //   3905: ior
    //   3906: istore #23
    //   3908: iconst_0
    //   3909: istore #24
    //   3911: iload #24
    //   3913: bipush #8
    //   3915: if_icmpge -> 4253
    //   3918: iload #22
    //   3920: bipush #28
    //   3922: ishl
    //   3923: iload #22
    //   3925: iconst_4
    //   3926: iushr
    //   3927: ior
    //   3928: istore #21
    //   3930: iload #21
    //   3932: aload #5
    //   3934: iload #25
    //   3936: iinc #25, 1
    //   3939: iaload
    //   3940: ixor
    //   3941: istore #21
    //   3943: aload #12
    //   3945: iload #21
    //   3947: bipush #63
    //   3949: iand
    //   3950: iaload
    //   3951: istore #20
    //   3953: iload #20
    //   3955: aload #10
    //   3957: iload #21
    //   3959: bipush #8
    //   3961: iushr
    //   3962: bipush #63
    //   3964: iand
    //   3965: iaload
    //   3966: ior
    //   3967: istore #20
    //   3969: iload #20
    //   3971: aload #8
    //   3973: iload #21
    //   3975: bipush #16
    //   3977: iushr
    //   3978: bipush #63
    //   3980: iand
    //   3981: iaload
    //   3982: ior
    //   3983: istore #20
    //   3985: iload #20
    //   3987: aload #6
    //   3989: iload #21
    //   3991: bipush #24
    //   3993: iushr
    //   3994: bipush #63
    //   3996: iand
    //   3997: iaload
    //   3998: ior
    //   3999: istore #20
    //   4001: iload #22
    //   4003: aload #5
    //   4005: iload #25
    //   4007: iinc #25, 1
    //   4010: iaload
    //   4011: ixor
    //   4012: istore #21
    //   4014: iload #20
    //   4016: aload #13
    //   4018: iload #21
    //   4020: bipush #63
    //   4022: iand
    //   4023: iaload
    //   4024: ior
    //   4025: istore #20
    //   4027: iload #20
    //   4029: aload #11
    //   4031: iload #21
    //   4033: bipush #8
    //   4035: iushr
    //   4036: bipush #63
    //   4038: iand
    //   4039: iaload
    //   4040: ior
    //   4041: istore #20
    //   4043: iload #20
    //   4045: aload #9
    //   4047: iload #21
    //   4049: bipush #16
    //   4051: iushr
    //   4052: bipush #63
    //   4054: iand
    //   4055: iaload
    //   4056: ior
    //   4057: istore #20
    //   4059: iload #20
    //   4061: aload #7
    //   4063: iload #21
    //   4065: bipush #24
    //   4067: iushr
    //   4068: bipush #63
    //   4070: iand
    //   4071: iaload
    //   4072: ior
    //   4073: istore #20
    //   4075: iload #23
    //   4077: iload #20
    //   4079: ixor
    //   4080: istore #23
    //   4082: iload #23
    //   4084: bipush #28
    //   4086: ishl
    //   4087: iload #23
    //   4089: iconst_4
    //   4090: iushr
    //   4091: ior
    //   4092: istore #21
    //   4094: iload #21
    //   4096: aload #5
    //   4098: iload #25
    //   4100: iinc #25, 1
    //   4103: iaload
    //   4104: ixor
    //   4105: istore #21
    //   4107: aload #12
    //   4109: iload #21
    //   4111: bipush #63
    //   4113: iand
    //   4114: iaload
    //   4115: istore #20
    //   4117: iload #20
    //   4119: aload #10
    //   4121: iload #21
    //   4123: bipush #8
    //   4125: iushr
    //   4126: bipush #63
    //   4128: iand
    //   4129: iaload
    //   4130: ior
    //   4131: istore #20
    //   4133: iload #20
    //   4135: aload #8
    //   4137: iload #21
    //   4139: bipush #16
    //   4141: iushr
    //   4142: bipush #63
    //   4144: iand
    //   4145: iaload
    //   4146: ior
    //   4147: istore #20
    //   4149: iload #20
    //   4151: aload #6
    //   4153: iload #21
    //   4155: bipush #24
    //   4157: iushr
    //   4158: bipush #63
    //   4160: iand
    //   4161: iaload
    //   4162: ior
    //   4163: istore #20
    //   4165: iload #23
    //   4167: aload #5
    //   4169: iload #25
    //   4171: iinc #25, 1
    //   4174: iaload
    //   4175: ixor
    //   4176: istore #21
    //   4178: iload #20
    //   4180: aload #13
    //   4182: iload #21
    //   4184: bipush #63
    //   4186: iand
    //   4187: iaload
    //   4188: ior
    //   4189: istore #20
    //   4191: iload #20
    //   4193: aload #11
    //   4195: iload #21
    //   4197: bipush #8
    //   4199: iushr
    //   4200: bipush #63
    //   4202: iand
    //   4203: iaload
    //   4204: ior
    //   4205: istore #20
    //   4207: iload #20
    //   4209: aload #9
    //   4211: iload #21
    //   4213: bipush #16
    //   4215: iushr
    //   4216: bipush #63
    //   4218: iand
    //   4219: iaload
    //   4220: ior
    //   4221: istore #20
    //   4223: iload #20
    //   4225: aload #7
    //   4227: iload #21
    //   4229: bipush #24
    //   4231: iushr
    //   4232: bipush #63
    //   4234: iand
    //   4235: iaload
    //   4236: ior
    //   4237: istore #20
    //   4239: iload #22
    //   4241: iload #20
    //   4243: ixor
    //   4244: istore #22
    //   4246: iinc #24, 1
    //   4249: iload_2
    //   4250: ifne -> 3911
    //   4253: iload #22
    //   4255: bipush #31
    //   4257: ishl
    //   4258: iload #22
    //   4260: iconst_1
    //   4261: iushr
    //   4262: ior
    //   4263: istore #22
    //   4265: iload #23
    //   4267: iload #22
    //   4269: ixor
    //   4270: ldc -1431655766
    //   4272: iand
    //   4273: istore #21
    //   4275: iload #23
    //   4277: iload #21
    //   4279: ixor
    //   4280: istore #23
    //   4282: iload #22
    //   4284: iload #21
    //   4286: ixor
    //   4287: istore #22
    //   4289: iload #23
    //   4291: bipush #31
    //   4293: ishl
    //   4294: iload #23
    //   4296: iconst_1
    //   4297: iushr
    //   4298: ior
    //   4299: istore #23
    //   4301: iload #23
    //   4303: bipush #8
    //   4305: iushr
    //   4306: iload #22
    //   4308: ixor
    //   4309: ldc 16711935
    //   4311: iand
    //   4312: istore #21
    //   4314: iload #22
    //   4316: iload #21
    //   4318: ixor
    //   4319: istore #22
    //   4321: iload #23
    //   4323: iload #21
    //   4325: bipush #8
    //   4327: ishl
    //   4328: ixor
    //   4329: istore #23
    //   4331: iload #23
    //   4333: iconst_2
    //   4334: iushr
    //   4335: iload #22
    //   4337: ixor
    //   4338: ldc 858993459
    //   4340: iand
    //   4341: istore #21
    //   4343: iload #22
    //   4345: iload #21
    //   4347: ixor
    //   4348: istore #22
    //   4350: iload #23
    //   4352: iload #21
    //   4354: iconst_2
    //   4355: ishl
    //   4356: ixor
    //   4357: istore #23
    //   4359: iload #22
    //   4361: bipush #16
    //   4363: iushr
    //   4364: iload #23
    //   4366: ixor
    //   4367: ldc 65535
    //   4369: iand
    //   4370: istore #21
    //   4372: iload #23
    //   4374: iload #21
    //   4376: ixor
    //   4377: istore #23
    //   4379: iload #22
    //   4381: iload #21
    //   4383: bipush #16
    //   4385: ishl
    //   4386: ixor
    //   4387: istore #22
    //   4389: iload #22
    //   4391: iconst_4
    //   4392: iushr
    //   4393: iload #23
    //   4395: ixor
    //   4396: ldc 252645135
    //   4398: iand
    //   4399: istore #21
    //   4401: iload #23
    //   4403: iload #21
    //   4405: ixor
    //   4406: istore #23
    //   4408: iload #22
    //   4410: iload #21
    //   4412: iconst_4
    //   4413: ishl
    //   4414: ixor
    //   4415: istore #22
    //   4417: aload #15
    //   4419: iconst_0
    //   4420: iload #22
    //   4422: iastore
    //   4423: aload #15
    //   4425: iconst_1
    //   4426: iload #23
    //   4428: iastore
    //   4429: iload #18
    //   4431: bipush #8
    //   4433: imul
    //   4434: istore #26
    //   4436: iconst_0
    //   4437: istore #27
    //   4439: iload #27
    //   4441: iconst_2
    //   4442: if_icmpge -> 4531
    //   4445: aload #16
    //   4447: iload #26
    //   4449: iload #27
    //   4451: iconst_4
    //   4452: imul
    //   4453: iadd
    //   4454: aload #15
    //   4456: iload #27
    //   4458: iaload
    //   4459: bipush #24
    //   4461: iushr
    //   4462: i2b
    //   4463: bastore
    //   4464: aload #16
    //   4466: iload #26
    //   4468: iload #27
    //   4470: iconst_4
    //   4471: imul
    //   4472: iadd
    //   4473: iconst_1
    //   4474: iadd
    //   4475: aload #15
    //   4477: iload #27
    //   4479: iaload
    //   4480: bipush #16
    //   4482: iushr
    //   4483: i2b
    //   4484: bastore
    //   4485: aload #16
    //   4487: iload #26
    //   4489: iload #27
    //   4491: iconst_4
    //   4492: imul
    //   4493: iadd
    //   4494: iconst_2
    //   4495: iadd
    //   4496: aload #15
    //   4498: iload #27
    //   4500: iaload
    //   4501: bipush #8
    //   4503: iushr
    //   4504: i2b
    //   4505: bastore
    //   4506: aload #16
    //   4508: iload #26
    //   4510: iload #27
    //   4512: iconst_4
    //   4513: imul
    //   4514: iadd
    //   4515: iconst_3
    //   4516: iadd
    //   4517: aload #15
    //   4519: iload #27
    //   4521: iaload
    //   4522: i2b
    //   4523: bastore
    //   4524: iinc #27, 1
    //   4527: iload_2
    //   4528: ifne -> 4439
    //   4531: iinc #18, 1
    //   4534: iload_2
    //   4535: ifne -> 3620
    //   4538: aload #16
    //   4540: aload #16
    //   4542: arraylength
    //   4543: iconst_1
    //   4544: isub
    //   4545: baload
    //   4546: istore #18
    //   4548: aload #16
    //   4550: arraylength
    //   4551: iload #18
    //   4553: isub
    //   4554: newarray byte
    //   4556: astore #4
    //   4558: aload #16
    //   4560: arraylength
    //   4561: aload #4
    //   4563: arraylength
    //   4564: if_icmpge -> 4588
    //   4567: new java/lang/Exception
    //   4570: dup
    //   4571: sipush #14348
    //   4574: sipush #-12314
    //   4577: invokestatic a : (II)Ljava/lang/String;
    //   4580: invokespecial <init> : (Ljava/lang/String;)V
    //   4583: athrow
    //   4584: invokestatic a : (Ljava/lang/Throwable;)Ljava/lang/Throwable;
    //   4587: athrow
    //   4588: iconst_0
    //   4589: istore #19
    //   4591: iload #19
    //   4593: aload #4
    //   4595: arraylength
    //   4596: if_icmpge -> 4616
    //   4599: aload #4
    //   4601: iload #19
    //   4603: aload #16
    //   4605: iload #19
    //   4607: baload
    //   4608: bastore
    //   4609: iinc #19, 1
    //   4612: iload_2
    //   4613: ifne -> 4591
    //   4616: new java/math/BigInteger
    //   4619: dup
    //   4620: aload #4
    //   4622: invokespecial <init> : ([B)V
    //   4625: invokevirtual abs : ()Ljava/math/BigInteger;
    //   4628: putstatic burp/Zrj3.ZA : Ljava/lang/Object;
    //   4631: sipush #14358
    //   4634: sipush #7316
    //   4637: invokestatic a : (II)Ljava/lang/String;
    //   4640: iconst_1
    //   4641: ldc burp/Zxsb
    //   4643: invokevirtual getClassLoader : ()Ljava/lang/ClassLoader;
    //   4646: invokestatic forName : (Ljava/lang/String;ZLjava/lang/ClassLoader;)Ljava/lang/Class;
    //   4649: invokevirtual getDeclaredFields : ()[Ljava/lang/reflect/Field;
    //   4652: astore_3
    //   4653: aload_3
    //   4654: arraylength
    //   4655: istore #4
    //   4657: iconst_0
    //   4658: istore #5
    //   4660: iload #5
    //   4662: iload #4
    //   4664: if_icmpge -> 4801
    //   4667: aload_3
    //   4668: iload #5
    //   4670: aaload
    //   4671: astore #6
    //   4673: aload #6
    //   4675: invokevirtual getModifiers : ()I
    //   4678: invokestatic isStatic : (I)Z
    //   4681: ifne -> 4691
    //   4684: goto -> 4794
    //   4687: invokestatic a : (Ljava/lang/Throwable;)Ljava/lang/Throwable;
    //   4690: athrow
    //   4691: aload #6
    //   4693: invokevirtual getType : ()Ljava/lang/Class;
    //   4696: astore #7
    //   4698: aload #7
    //   4700: ifnull -> 4781
    //   4703: aload #7
    //   4705: invokevirtual isPrimitive : ()Z
    //   4708: ifne -> 4781
    //   4711: goto -> 4718
    //   4714: invokestatic a : (Ljava/lang/Throwable;)Ljava/lang/Throwable;
    //   4717: athrow
    //   4718: aload #7
    //   4720: invokevirtual getPackage : ()Ljava/lang/Package;
    //   4723: ifnull -> 4781
    //   4726: goto -> 4733
    //   4729: invokestatic a : (Ljava/lang/Throwable;)Ljava/lang/Throwable;
    //   4732: athrow
    //   4733: aload #7
    //   4735: invokevirtual getPackage : ()Ljava/lang/Package;
    //   4738: invokevirtual getName : ()Ljava/lang/String;
    //   4741: ifnull -> 4781
    //   4744: goto -> 4751
    //   4747: invokestatic a : (Ljava/lang/Throwable;)Ljava/lang/Throwable;
    //   4750: athrow
    //   4751: aload #7
    //   4753: invokevirtual getPackage : ()Ljava/lang/Package;
    //   4756: invokevirtual getName : ()Ljava/lang/String;
    //   4759: sipush #14346
    //   4762: sipush #-14885
    //   4765: invokestatic a : (II)Ljava/lang/String;
    //   4768: invokevirtual startsWith : (Ljava/lang/String;)Z
    //   4771: ifne -> 4781
    //   4774: goto -> 4781
    //   4777: invokestatic a : (Ljava/lang/Throwable;)Ljava/lang/Throwable;
    //   4780: athrow
    //   4781: aload #6
    //   4783: iconst_1
    //   4784: invokevirtual setAccessible : (Z)V
    //   4787: aload #6
    //   4789: aconst_null
    //   4790: invokevirtual get : (Ljava/lang/Object;)Ljava/lang/Object;
    //   4793: pop
    //   4794: iinc #5, 1
    //   4797: iload_2
    //   4798: ifne -> 4660
    //   4801: sipush #14336
    //   4804: sipush #13523
    //   4807: invokestatic a : (II)Ljava/lang/String;
    //   4810: invokestatic forName : (Ljava/lang/String;)Ljava/lang/Class;
    //   4813: invokevirtual getDeclaredMethods : ()[Ljava/lang/reflect/Method;
    //   4816: astore_3
    //   4817: aload_3
    //   4818: arraylength
    //   4819: istore #4
    //   4821: iconst_0
    //   4822: istore #5
    //   4824: iload #5
    //   4826: iload #4
    //   4828: if_icmpge -> 4960
    //   4831: aload_3
    //   4832: iload #5
    //   4834: aaload
    //   4835: astore #6
    //   4837: aload #6
    //   4839: invokevirtual getParameterTypes : ()[Ljava/lang/Class;
    //   4842: pop
    //   4843: aload #6
    //   4845: invokevirtual getModifiers : ()I
    //   4848: invokestatic isStatic : (I)Z
    //   4851: ifeq -> 4946
    //   4854: aload #6
    //   4856: invokevirtual getParameterTypes : ()[Ljava/lang/Class;
    //   4859: arraylength
    //   4860: iconst_2
    //   4861: if_icmpne -> 4946
    //   4864: goto -> 4871
    //   4867: invokestatic a : (Ljava/lang/Throwable;)Ljava/lang/Throwable;
    //   4870: athrow
    //   4871: aload #6
    //   4873: invokevirtual getReturnType : ()Ljava/lang/Class;
    //   4876: getstatic java/lang/Void.TYPE : Ljava/lang/Class;
    //   4879: invokevirtual equals : (Ljava/lang/Object;)Z
    //   4882: ifeq -> 4946
    //   4885: goto -> 4892
    //   4888: invokestatic a : (Ljava/lang/Throwable;)Ljava/lang/Throwable;
    //   4891: athrow
    //   4892: aload #6
    //   4894: iconst_1
    //   4895: invokevirtual setAccessible : (Z)V
    //   4898: aload #6
    //   4900: aconst_null
    //   4901: iconst_2
    //   4902: anewarray java/lang/Object
    //   4905: dup
    //   4906: iconst_0
    //   4907: aload_0
    //   4908: aastore
    //   4909: dup
    //   4910: iconst_1
    //   4911: aload_1
    //   4912: ifnonnull -> 4930
    //   4915: goto -> 4922
    //   4918: invokestatic a : (Ljava/lang/Throwable;)Ljava/lang/Throwable;
    //   4921: athrow
    //   4922: aload_1
    //   4923: goto -> 4937
    //   4926: invokestatic a : (Ljava/lang/Throwable;)Ljava/lang/Throwable;
    //   4929: athrow
    //   4930: aload_1
    //   4931: checkcast [B
    //   4934: invokevirtual clone : ()Ljava/lang/Object;
    //   4937: aastore
    //   4938: invokevirtual invoke : (Ljava/lang/Object;[Ljava/lang/Object;)Ljava/lang/Object;
    //   4941: pop
    //   4942: iload_2
    //   4943: ifne -> 4960
    //   4946: iinc #5, 1
    //   4949: iload_2
    //   4950: ifne -> 4824
    //   4953: goto -> 4960
    //   4956: invokestatic a : (Ljava/lang/Throwable;)Ljava/lang/Throwable;
    //   4959: athrow
    //   4960: iconst_0
    //   4961: istore_3
    //   4962: getstatic burp/Zetv.ZE : Ljava/lang/String;
    //   4965: getstatic burp/Zkcd.ZE : Ljava/lang/Object;
    //   4968: checkcast java/math/BigInteger
    //   4971: invokevirtual intValue : ()I
    //   4974: bipush #32
    //   4976: irem
    //   4977: invokestatic abs : (I)I
    //   4980: invokevirtual charAt : (I)C
    //   4983: getstatic burp/Ztmy.ZF : Ljava/lang/String;
    //   4986: getstatic burp/Zr0.ZX : Ljava/lang/Object;
    //   4989: checkcast java/math/BigInteger
    //   4992: invokevirtual intValue : ()I
    //   4995: bipush #32
    //   4997: irem
    //   4998: invokestatic abs : (I)I
    //   5001: invokevirtual charAt : (I)C
    //   5004: if_icmpgt -> 5348
    //   5007: sipush #14345
    //   5010: sipush #-29402
    //   5013: invokestatic a : (II)Ljava/lang/String;
    //   5016: iconst_1
    //   5017: ldc burp/Zkw
    //   5019: invokevirtual getClassLoader : ()Ljava/lang/ClassLoader;
    //   5022: invokestatic forName : (Ljava/lang/String;ZLjava/lang/ClassLoader;)Ljava/lang/Class;
    //   5025: invokevirtual getDeclaredFields : ()[Ljava/lang/reflect/Field;
    //   5028: astore #4
    //   5030: aload #4
    //   5032: arraylength
    //   5033: istore #5
    //   5035: iconst_0
    //   5036: istore #6
    //   5038: iload #6
    //   5040: iload #5
    //   5042: if_icmpge -> 5180
    //   5045: aload #4
    //   5047: iload #6
    //   5049: aaload
    //   5050: astore #7
    //   5052: aload #7
    //   5054: invokevirtual getModifiers : ()I
    //   5057: invokestatic isStatic : (I)Z
    //   5060: ifne -> 5070
    //   5063: goto -> 5173
    //   5066: invokestatic a : (Ljava/lang/Throwable;)Ljava/lang/Throwable;
    //   5069: athrow
    //   5070: aload #7
    //   5072: invokevirtual getType : ()Ljava/lang/Class;
    //   5075: astore #8
    //   5077: aload #8
    //   5079: ifnull -> 5160
    //   5082: aload #8
    //   5084: invokevirtual isPrimitive : ()Z
    //   5087: ifne -> 5160
    //   5090: goto -> 5097
    //   5093: invokestatic a : (Ljava/lang/Throwable;)Ljava/lang/Throwable;
    //   5096: athrow
    //   5097: aload #8
    //   5099: invokevirtual getPackage : ()Ljava/lang/Package;
    //   5102: ifnull -> 5160
    //   5105: goto -> 5112
    //   5108: invokestatic a : (Ljava/lang/Throwable;)Ljava/lang/Throwable;
    //   5111: athrow
    //   5112: aload #8
    //   5114: invokevirtual getPackage : ()Ljava/lang/Package;
    //   5117: invokevirtual getName : ()Ljava/lang/String;
    //   5120: ifnull -> 5160
    //   5123: goto -> 5130
    //   5126: invokestatic a : (Ljava/lang/Throwable;)Ljava/lang/Throwable;
    //   5129: athrow
    //   5130: aload #8
    //   5132: invokevirtual getPackage : ()Ljava/lang/Package;
    //   5135: invokevirtual getName : ()Ljava/lang/String;
    //   5138: sipush #14349
    //   5141: sipush #25053
    //   5144: invokestatic a : (II)Ljava/lang/String;
    //   5147: invokevirtual startsWith : (Ljava/lang/String;)Z
    //   5150: ifne -> 5160
    //   5153: goto -> 5160
    //   5156: invokestatic a : (Ljava/lang/Throwable;)Ljava/lang/Throwable;
    //   5159: athrow
    //   5160: aload #7
    //   5162: iconst_1
    //   5163: invokevirtual setAccessible : (Z)V
    //   5166: aload #7
    //   5168: aconst_null
    //   5169: invokevirtual get : (Ljava/lang/Object;)Ljava/lang/Object;
    //   5172: pop
    //   5173: iinc #6, 1
    //   5176: iload_2
    //   5177: ifne -> 5038
    //   5180: sipush #14350
    //   5183: sipush #-9461
    //   5186: invokestatic a : (II)Ljava/lang/String;
    //   5189: invokestatic forName : (Ljava/lang/String;)Ljava/lang/Class;
    //   5192: invokevirtual getDeclaredMethods : ()[Ljava/lang/reflect/Method;
    //   5195: astore #4
    //   5197: aload #4
    //   5199: arraylength
    //   5200: istore #5
    //   5202: iconst_0
    //   5203: istore #6
    //   5205: iload #6
    //   5207: iload #5
    //   5209: if_icmpge -> 5345
    //   5212: aload #4
    //   5214: iload #6
    //   5216: aaload
    //   5217: astore #7
    //   5219: aload #7
    //   5221: invokevirtual getParameterTypes : ()[Ljava/lang/Class;
    //   5224: pop
    //   5225: aload #7
    //   5227: invokevirtual getModifiers : ()I
    //   5230: invokestatic isStatic : (I)Z
    //   5233: ifeq -> 5331
    //   5236: aload #7
    //   5238: invokevirtual getParameterTypes : ()[Ljava/lang/Class;
    //   5241: arraylength
    //   5242: iconst_2
    //   5243: if_icmpne -> 5331
    //   5246: goto -> 5253
    //   5249: invokestatic a : (Ljava/lang/Throwable;)Ljava/lang/Throwable;
    //   5252: athrow
    //   5253: aload #7
    //   5255: invokevirtual getReturnType : ()Ljava/lang/Class;
    //   5258: getstatic java/lang/Boolean.TYPE : Ljava/lang/Class;
    //   5261: if_acmpne -> 5331
    //   5264: goto -> 5271
    //   5267: invokestatic a : (Ljava/lang/Throwable;)Ljava/lang/Throwable;
    //   5270: athrow
    //   5271: aload #7
    //   5273: iconst_1
    //   5274: invokevirtual setAccessible : (Z)V
    //   5277: aload #7
    //   5279: aconst_null
    //   5280: iconst_2
    //   5281: anewarray java/lang/Object
    //   5284: dup
    //   5285: iconst_0
    //   5286: aload_0
    //   5287: aastore
    //   5288: dup
    //   5289: iconst_1
    //   5290: aload_1
    //   5291: ifnonnull -> 5309
    //   5294: goto -> 5301
    //   5297: invokestatic a : (Ljava/lang/Throwable;)Ljava/lang/Throwable;
    //   5300: athrow
    //   5301: aload_1
    //   5302: goto -> 5316
    //   5305: invokestatic a : (Ljava/lang/Throwable;)Ljava/lang/Throwable;
    //   5308: athrow
    //   5309: aload_1
    //   5310: checkcast [B
    //   5313: invokevirtual clone : ()Ljava/lang/Object;
    //   5316: aastore
    //   5317: invokevirtual invoke : (Ljava/lang/Object;[Ljava/lang/Object;)Ljava/lang/Object;
    //   5320: checkcast java/lang/Boolean
    //   5323: invokevirtual booleanValue : ()Z
    //   5326: istore_3
    //   5327: iload_2
    //   5328: ifne -> 5345
    //   5331: iinc #6, 1
    //   5334: iload_2
    //   5335: ifne -> 5205
    //   5338: goto -> 5345
    //   5341: invokestatic a : (Ljava/lang/Throwable;)Ljava/lang/Throwable;
    //   5344: athrow
    //   5345: goto -> 5686
    //   5348: sipush #14343
    //   5351: sipush #-16307
    //   5354: invokestatic a : (II)Ljava/lang/String;
    //   5357: iconst_1
    //   5358: ldc burp/Zbxa
    //   5360: invokevirtual getClassLoader : ()Ljava/lang/ClassLoader;
    //   5363: invokestatic forName : (Ljava/lang/String;ZLjava/lang/ClassLoader;)Ljava/lang/Class;
    //   5366: invokevirtual getDeclaredFields : ()[Ljava/lang/reflect/Field;
    //   5369: astore #4
    //   5371: aload #4
    //   5373: arraylength
    //   5374: istore #5
    //   5376: iconst_0
    //   5377: istore #6
    //   5379: iload #6
    //   5381: iload #5
    //   5383: if_icmpge -> 5521
    //   5386: aload #4
    //   5388: iload #6
    //   5390: aaload
    //   5391: astore #7
    //   5393: aload #7
    //   5395: invokevirtual getModifiers : ()I
    //   5398: invokestatic isStatic : (I)Z
    //   5401: ifne -> 5411
    //   5404: goto -> 5514
    //   5407: invokestatic a : (Ljava/lang/Throwable;)Ljava/lang/Throwable;
    //   5410: athrow
    //   5411: aload #7
    //   5413: invokevirtual getType : ()Ljava/lang/Class;
    //   5416: astore #8
    //   5418: aload #8
    //   5420: ifnull -> 5501
    //   5423: aload #8
    //   5425: invokevirtual isPrimitive : ()Z
    //   5428: ifne -> 5501
    //   5431: goto -> 5438
    //   5434: invokestatic a : (Ljava/lang/Throwable;)Ljava/lang/Throwable;
    //   5437: athrow
    //   5438: aload #8
    //   5440: invokevirtual getPackage : ()Ljava/lang/Package;
    //   5443: ifnull -> 5501
    //   5446: goto -> 5453
    //   5449: invokestatic a : (Ljava/lang/Throwable;)Ljava/lang/Throwable;
    //   5452: athrow
    //   5453: aload #8
    //   5455: invokevirtual getPackage : ()Ljava/lang/Package;
    //   5458: invokevirtual getName : ()Ljava/lang/String;
    //   5461: ifnull -> 5501
    //   5464: goto -> 5471
    //   5467: invokestatic a : (Ljava/lang/Throwable;)Ljava/lang/Throwable;
    //   5470: athrow
    //   5471: aload #8
    //   5473: invokevirtual getPackage : ()Ljava/lang/Package;
    //   5476: invokevirtual getName : ()Ljava/lang/String;
    //   5479: sipush #14349
    //   5482: sipush #25053
    //   5485: invokestatic a : (II)Ljava/lang/String;
    //   5488: invokevirtual startsWith : (Ljava/lang/String;)Z
    //   5491: ifne -> 5501
    //   5494: goto -> 5501
    //   5497: invokestatic a : (Ljava/lang/Throwable;)Ljava/lang/Throwable;
    //   5500: athrow
    //   5501: aload #7
    //   5503: iconst_1
    //   5504: invokevirtual setAccessible : (Z)V
    //   5507: aload #7
    //   5509: aconst_null
    //   5510: invokevirtual get : (Ljava/lang/Object;)Ljava/lang/Object;
    //   5513: pop
    //   5514: iinc #6, 1
    //   5517: iload_2
    //   5518: ifne -> 5379
    //   5521: sipush #14354
    //   5524: sipush #-3733
    //   5527: invokestatic a : (II)Ljava/lang/String;
    //   5530: invokestatic forName : (Ljava/lang/String;)Ljava/lang/Class;
    //   5533: invokevirtual getDeclaredMethods : ()[Ljava/lang/reflect/Method;
    //   5536: astore #4
    //   5538: aload #4
    //   5540: arraylength
    //   5541: istore #5
    //   5543: iconst_0
    //   5544: istore #6
    //   5546: iload #6
    //   5548: iload #5
    //   5550: if_icmpge -> 5686
    //   5553: aload #4
    //   5555: iload #6
    //   5557: aaload
    //   5558: astore #7
    //   5560: aload #7
    //   5562: invokevirtual getParameterTypes : ()[Ljava/lang/Class;
    //   5565: pop
    //   5566: aload #7
    //   5568: invokevirtual getModifiers : ()I
    //   5571: invokestatic isStatic : (I)Z
    //   5574: ifeq -> 5672
    //   5577: aload #7
    //   5579: invokevirtual getParameterTypes : ()[Ljava/lang/Class;
    //   5582: arraylength
    //   5583: iconst_2
    //   5584: if_icmpne -> 5672
    //   5587: goto -> 5594
    //   5590: invokestatic a : (Ljava/lang/Throwable;)Ljava/lang/Throwable;
    //   5593: athrow
    //   5594: aload #7
    //   5596: invokevirtual getReturnType : ()Ljava/lang/Class;
    //   5599: getstatic java/lang/Boolean.TYPE : Ljava/lang/Class;
    //   5602: if_acmpne -> 5672
    //   5605: goto -> 5612
    //   5608: invokestatic a : (Ljava/lang/Throwable;)Ljava/lang/Throwable;
    //   5611: athrow
    //   5612: aload #7
    //   5614: iconst_1
    //   5615: invokevirtual setAccessible : (Z)V
    //   5618: aload #7
    //   5620: aconst_null
    //   5621: iconst_2
    //   5622: anewarray java/lang/Object
    //   5625: dup
    //   5626: iconst_0
    //   5627: aload_0
    //   5628: aastore
    //   5629: dup
    //   5630: iconst_1
    //   5631: aload_1
    //   5632: ifnonnull -> 5650
    //   5635: goto -> 5642
    //   5638: invokestatic a : (Ljava/lang/Throwable;)Ljava/lang/Throwable;
    //   5641: athrow
    //   5642: aload_1
    //   5643: goto -> 5657
    //   5646: invokestatic a : (Ljava/lang/Throwable;)Ljava/lang/Throwable;
    //   5649: athrow
    //   5650: aload_1
    //   5651: checkcast [B
    //   5654: invokevirtual clone : ()Ljava/lang/Object;
    //   5657: aastore
    //   5658: invokevirtual invoke : (Ljava/lang/Object;[Ljava/lang/Object;)Ljava/lang/Object;
    //   5661: checkcast java/lang/Boolean
    //   5664: invokevirtual booleanValue : ()Z
    //   5667: istore_3
    //   5668: iload_2
    //   5669: ifne -> 5686
    //   5672: iinc #6, 1
    //   5675: iload_2
    //   5676: ifne -> 5546
    //   5679: goto -> 5686
    //   5682: invokestatic a : (Ljava/lang/Throwable;)Ljava/lang/Throwable;
    //   5685: athrow
    //   5686: iload_3
    //   5687: ifeq -> 5692
    //   5690: iload_3
    //   5691: ireturn
    //   5692: getstatic burp/Zr9p.Za : Ljava/lang/String;
    //   5695: getstatic burp/Zxdh.ZD : Ljava/lang/Object;
    //   5698: checkcast java/math/BigInteger
    //   5701: invokevirtual intValue : ()I
    //   5704: bipush #32
    //   5706: irem
    //   5707: invokestatic abs : (I)I
    //   5710: invokevirtual charAt : (I)C
    //   5713: getstatic burp/Zgyk.ZB : Ljava/lang/String;
    //   5716: getstatic burp/Zsk2.ZD : Ljava/lang/Object;
    //   5719: checkcast java/math/BigInteger
    //   5722: invokevirtual intValue : ()I
    //   5725: bipush #32
    //   5727: irem
    //   5728: invokestatic abs : (I)I
    //   5731: invokevirtual charAt : (I)C
    //   5734: if_icmple -> 6079
    //   5737: sipush #14355
    //   5740: sipush #-20758
    //   5743: invokestatic a : (II)Ljava/lang/String;
    //   5746: iconst_1
    //   5747: ldc burp/Zt5b
    //   5749: invokevirtual getClassLoader : ()Ljava/lang/ClassLoader;
    //   5752: invokestatic forName : (Ljava/lang/String;ZLjava/lang/ClassLoader;)Ljava/lang/Class;
    //   5755: invokevirtual getDeclaredFields : ()[Ljava/lang/reflect/Field;
    //   5758: astore #4
    //   5760: aload #4
    //   5762: arraylength
    //   5763: istore #5
    //   5765: iconst_0
    //   5766: istore #6
    //   5768: iload #6
    //   5770: iload #5
    //   5772: if_icmpge -> 5910
    //   5775: aload #4
    //   5777: iload #6
    //   5779: aaload
    //   5780: astore #7
    //   5782: aload #7
    //   5784: invokevirtual getModifiers : ()I
    //   5787: invokestatic isStatic : (I)Z
    //   5790: ifne -> 5800
    //   5793: goto -> 5903
    //   5796: invokestatic a : (Ljava/lang/Throwable;)Ljava/lang/Throwable;
    //   5799: athrow
    //   5800: aload #7
    //   5802: invokevirtual getType : ()Ljava/lang/Class;
    //   5805: astore #8
    //   5807: aload #8
    //   5809: ifnull -> 5890
    //   5812: aload #8
    //   5814: invokevirtual isPrimitive : ()Z
    //   5817: ifne -> 5890
    //   5820: goto -> 5827
    //   5823: invokestatic a : (Ljava/lang/Throwable;)Ljava/lang/Throwable;
    //   5826: athrow
    //   5827: aload #8
    //   5829: invokevirtual getPackage : ()Ljava/lang/Package;
    //   5832: ifnull -> 5890
    //   5835: goto -> 5842
    //   5838: invokestatic a : (Ljava/lang/Throwable;)Ljava/lang/Throwable;
    //   5841: athrow
    //   5842: aload #8
    //   5844: invokevirtual getPackage : ()Ljava/lang/Package;
    //   5847: invokevirtual getName : ()Ljava/lang/String;
    //   5850: ifnull -> 5890
    //   5853: goto -> 5860
    //   5856: invokestatic a : (Ljava/lang/Throwable;)Ljava/lang/Throwable;
    //   5859: athrow
    //   5860: aload #8
    //   5862: invokevirtual getPackage : ()Ljava/lang/Package;
    //   5865: invokevirtual getName : ()Ljava/lang/String;
    //   5868: sipush #14349
    //   5871: sipush #25053
    //   5874: invokestatic a : (II)Ljava/lang/String;
    //   5877: invokevirtual startsWith : (Ljava/lang/String;)Z
    //   5880: ifne -> 5890
    //   5883: goto -> 5890
    //   5886: invokestatic a : (Ljava/lang/Throwable;)Ljava/lang/Throwable;
    //   5889: athrow
    //   5890: aload #7
    //   5892: iconst_1
    //   5893: invokevirtual setAccessible : (Z)V
    //   5896: aload #7
    //   5898: aconst_null
    //   5899: invokevirtual get : (Ljava/lang/Object;)Ljava/lang/Object;
    //   5902: pop
    //   5903: iinc #6, 1
    //   5906: iload_2
    //   5907: ifne -> 5768
    //   5910: sipush #14337
    //   5913: sipush #23771
    //   5916: invokestatic a : (II)Ljava/lang/String;
    //   5919: invokestatic forName : (Ljava/lang/String;)Ljava/lang/Class;
    //   5922: invokevirtual getDeclaredMethods : ()[Ljava/lang/reflect/Method;
    //   5925: astore #4
    //   5927: aload #4
    //   5929: arraylength
    //   5930: istore #5
    //   5932: iconst_0
    //   5933: istore #6
    //   5935: iload #6
    //   5937: iload #5
    //   5939: if_icmpge -> 6075
    //   5942: aload #4
    //   5944: iload #6
    //   5946: aaload
    //   5947: astore #7
    //   5949: aload #7
    //   5951: invokevirtual getParameterTypes : ()[Ljava/lang/Class;
    //   5954: pop
    //   5955: aload #7
    //   5957: invokevirtual getModifiers : ()I
    //   5960: invokestatic isStatic : (I)Z
    //   5963: ifeq -> 6061
    //   5966: aload #7
    //   5968: invokevirtual getParameterTypes : ()[Ljava/lang/Class;
    //   5971: arraylength
    //   5972: iconst_2
    //   5973: if_icmpne -> 6061
    //   5976: goto -> 5983
    //   5979: invokestatic a : (Ljava/lang/Throwable;)Ljava/lang/Throwable;
    //   5982: athrow
    //   5983: aload #7
    //   5985: invokevirtual getReturnType : ()Ljava/lang/Class;
    //   5988: getstatic java/lang/Boolean.TYPE : Ljava/lang/Class;
    //   5991: if_acmpne -> 6061
    //   5994: goto -> 6001
    //   5997: invokestatic a : (Ljava/lang/Throwable;)Ljava/lang/Throwable;
    //   6000: athrow
    //   6001: aload #7
    //   6003: iconst_1
    //   6004: invokevirtual setAccessible : (Z)V
    //   6007: aload #7
    //   6009: aconst_null
    //   6010: iconst_2
    //   6011: anewarray java/lang/Object
    //   6014: dup
    //   6015: iconst_0
    //   6016: aload_0
    //   6017: aastore
    //   6018: dup
    //   6019: iconst_1
    //   6020: aload_1
    //   6021: ifnonnull -> 6039
    //   6024: goto -> 6031
    //   6027: invokestatic a : (Ljava/lang/Throwable;)Ljava/lang/Throwable;
    //   6030: athrow
    //   6031: aload_1
    //   6032: goto -> 6046
    //   6035: invokestatic a : (Ljava/lang/Throwable;)Ljava/lang/Throwable;
    //   6038: athrow
    //   6039: aload_1
    //   6040: checkcast [B
    //   6043: invokevirtual clone : ()Ljava/lang/Object;
    //   6046: aastore
    //   6047: invokevirtual invoke : (Ljava/lang/Object;[Ljava/lang/Object;)Ljava/lang/Object;
    //   6050: checkcast java/lang/Boolean
    //   6053: invokevirtual booleanValue : ()Z
    //   6056: istore_3
    //   6057: iload_2
    //   6058: ifne -> 6075
    //   6061: iinc #6, 1
    //   6064: iload_2
    //   6065: ifne -> 5935
    //   6068: goto -> 6075
    //   6071: invokestatic a : (Ljava/lang/Throwable;)Ljava/lang/Throwable;
    //   6074: athrow
    //   6075: iload_2
    //   6076: ifne -> 6417
    //   6079: sipush #14338
    //   6082: sipush #-17494
    //   6085: invokestatic a : (II)Ljava/lang/String;
    //   6088: iconst_1
    //   6089: ldc burp/Zgl4
    //   6091: invokevirtual getClassLoader : ()Ljava/lang/ClassLoader;
    //   6094: invokestatic forName : (Ljava/lang/String;ZLjava/lang/ClassLoader;)Ljava/lang/Class;
    //   6097: invokevirtual getDeclaredFields : ()[Ljava/lang/reflect/Field;
    //   6100: astore #4
    //   6102: aload #4
    //   6104: arraylength
    //   6105: istore #5
    //   6107: iconst_0
    //   6108: istore #6
    //   6110: iload #6
    //   6112: iload #5
    //   6114: if_icmpge -> 6252
    //   6117: aload #4
    //   6119: iload #6
    //   6121: aaload
    //   6122: astore #7
    //   6124: aload #7
    //   6126: invokevirtual getModifiers : ()I
    //   6129: invokestatic isStatic : (I)Z
    //   6132: ifne -> 6142
    //   6135: goto -> 6245
    //   6138: invokestatic a : (Ljava/lang/Throwable;)Ljava/lang/Throwable;
    //   6141: athrow
    //   6142: aload #7
    //   6144: invokevirtual getType : ()Ljava/lang/Class;
    //   6147: astore #8
    //   6149: aload #8
    //   6151: ifnull -> 6232
    //   6154: aload #8
    //   6156: invokevirtual isPrimitive : ()Z
    //   6159: ifne -> 6232
    //   6162: goto -> 6169
    //   6165: invokestatic a : (Ljava/lang/Throwable;)Ljava/lang/Throwable;
    //   6168: athrow
    //   6169: aload #8
    //   6171: invokevirtual getPackage : ()Ljava/lang/Package;
    //   6174: ifnull -> 6232
    //   6177: goto -> 6184
    //   6180: invokestatic a : (Ljava/lang/Throwable;)Ljava/lang/Throwable;
    //   6183: athrow
    //   6184: aload #8
    //   6186: invokevirtual getPackage : ()Ljava/lang/Package;
    //   6189: invokevirtual getName : ()Ljava/lang/String;
    //   6192: ifnull -> 6232
    //   6195: goto -> 6202
    //   6198: invokestatic a : (Ljava/lang/Throwable;)Ljava/lang/Throwable;
    //   6201: athrow
    //   6202: aload #8
    //   6204: invokevirtual getPackage : ()Ljava/lang/Package;
    //   6207: invokevirtual getName : ()Ljava/lang/String;
    //   6210: sipush #14349
    //   6213: sipush #25053
    //   6216: invokestatic a : (II)Ljava/lang/String;
    //   6219: invokevirtual startsWith : (Ljava/lang/String;)Z
    //   6222: ifne -> 6232
    //   6225: goto -> 6232
    //   6228: invokestatic a : (Ljava/lang/Throwable;)Ljava/lang/Throwable;
    //   6231: athrow
    //   6232: aload #7
    //   6234: iconst_1
    //   6235: invokevirtual setAccessible : (Z)V
    //   6238: aload #7
    //   6240: aconst_null
    //   6241: invokevirtual get : (Ljava/lang/Object;)Ljava/lang/Object;
    //   6244: pop
    //   6245: iinc #6, 1
    //   6248: iload_2
    //   6249: ifne -> 6110
    //   6252: sipush #14359
    //   6255: sipush #-18801
    //   6258: invokestatic a : (II)Ljava/lang/String;
    //   6261: invokestatic forName : (Ljava/lang/String;)Ljava/lang/Class;
    //   6264: invokevirtual getDeclaredMethods : ()[Ljava/lang/reflect/Method;
    //   6267: astore #4
    //   6269: aload #4
    //   6271: arraylength
    //   6272: istore #5
    //   6274: iconst_0
    //   6275: istore #6
    //   6277: iload #6
    //   6279: iload #5
    //   6281: if_icmpge -> 6417
    //   6284: aload #4
    //   6286: iload #6
    //   6288: aaload
    //   6289: astore #7
    //   6291: aload #7
    //   6293: invokevirtual getParameterTypes : ()[Ljava/lang/Class;
    //   6296: pop
    //   6297: aload #7
    //   6299: invokevirtual getModifiers : ()I
    //   6302: invokestatic isStatic : (I)Z
    //   6305: ifeq -> 6403
    //   6308: aload #7
    //   6310: invokevirtual getParameterTypes : ()[Ljava/lang/Class;
    //   6313: arraylength
    //   6314: iconst_2
    //   6315: if_icmpne -> 6403
    //   6318: goto -> 6325
    //   6321: invokestatic a : (Ljava/lang/Throwable;)Ljava/lang/Throwable;
    //   6324: athrow
    //   6325: aload #7
    //   6327: invokevirtual getReturnType : ()Ljava/lang/Class;
    //   6330: getstatic java/lang/Boolean.TYPE : Ljava/lang/Class;
    //   6333: if_acmpne -> 6403
    //   6336: goto -> 6343
    //   6339: invokestatic a : (Ljava/lang/Throwable;)Ljava/lang/Throwable;
    //   6342: athrow
    //   6343: aload #7
    //   6345: iconst_1
    //   6346: invokevirtual setAccessible : (Z)V
    //   6349: aload #7
    //   6351: aconst_null
    //   6352: iconst_2
    //   6353: anewarray java/lang/Object
    //   6356: dup
    //   6357: iconst_0
    //   6358: aload_0
    //   6359: aastore
    //   6360: dup
    //   6361: iconst_1
    //   6362: aload_1
    //   6363: ifnonnull -> 6381
    //   6366: goto -> 6373
    //   6369: invokestatic a : (Ljava/lang/Throwable;)Ljava/lang/Throwable;
    //   6372: athrow
    //   6373: aload_1
    //   6374: goto -> 6388
    //   6377: invokestatic a : (Ljava/lang/Throwable;)Ljava/lang/Throwable;
    //   6380: athrow
    //   6381: aload_1
    //   6382: checkcast [B
    //   6385: invokevirtual clone : ()Ljava/lang/Object;
    //   6388: aastore
    //   6389: invokevirtual invoke : (Ljava/lang/Object;[Ljava/lang/Object;)Ljava/lang/Object;
    //   6392: checkcast java/lang/Boolean
    //   6395: invokevirtual booleanValue : ()Z
    //   6398: istore_3
    //   6399: iload_2
    //   6400: ifne -> 6417
    //   6403: iinc #6, 1
    //   6406: iload_2
    //   6407: ifne -> 6277
    //   6410: goto -> 6417
    //   6413: invokestatic a : (Ljava/lang/Throwable;)Ljava/lang/Throwable;
    //   6416: athrow
    //   6417: iload_3
    //   6418: ifeq -> 6423
    //   6421: iload_3
    //   6422: ireturn
    //   6423: getstatic burp/Zzr.Zp : Ljava/lang/String;
    //   6426: getstatic burp/Zr4k.Zf : Ljava/lang/Object;
    //   6429: checkcast java/math/BigInteger
    //   6432: invokevirtual intValue : ()I
    //   6435: bipush #32
    //   6437: irem
    //   6438: invokestatic abs : (I)I
    //   6441: invokevirtual charAt : (I)C
    //   6444: getstatic burp/Zl3l.Z_ : Ljava/lang/String;
    //   6447: getstatic burp/Zdm.ZA : Ljava/lang/Object;
    //   6450: checkcast java/math/BigInteger
    //   6453: invokevirtual intValue : ()I
    //   6456: bipush #32
    //   6458: irem
    //   6459: invokestatic abs : (I)I
    //   6462: invokevirtual charAt : (I)C
    //   6465: if_icmple -> 6810
    //   6468: sipush #14353
    //   6471: sipush #-29771
    //   6474: invokestatic a : (II)Ljava/lang/String;
    //   6477: iconst_1
    //   6478: ldc burp/Zg1k
    //   6480: invokevirtual getClassLoader : ()Ljava/lang/ClassLoader;
    //   6483: invokestatic forName : (Ljava/lang/String;ZLjava/lang/ClassLoader;)Ljava/lang/Class;
    //   6486: invokevirtual getDeclaredFields : ()[Ljava/lang/reflect/Field;
    //   6489: astore #4
    //   6491: aload #4
    //   6493: arraylength
    //   6494: istore #5
    //   6496: iconst_0
    //   6497: istore #6
    //   6499: iload #6
    //   6501: iload #5
    //   6503: if_icmpge -> 6641
    //   6506: aload #4
    //   6508: iload #6
    //   6510: aaload
    //   6511: astore #7
    //   6513: aload #7
    //   6515: invokevirtual getModifiers : ()I
    //   6518: invokestatic isStatic : (I)Z
    //   6521: ifne -> 6531
    //   6524: goto -> 6634
    //   6527: invokestatic a : (Ljava/lang/Throwable;)Ljava/lang/Throwable;
    //   6530: athrow
    //   6531: aload #7
    //   6533: invokevirtual getType : ()Ljava/lang/Class;
    //   6536: astore #8
    //   6538: aload #8
    //   6540: ifnull -> 6621
    //   6543: aload #8
    //   6545: invokevirtual isPrimitive : ()Z
    //   6548: ifne -> 6621
    //   6551: goto -> 6558
    //   6554: invokestatic a : (Ljava/lang/Throwable;)Ljava/lang/Throwable;
    //   6557: athrow
    //   6558: aload #8
    //   6560: invokevirtual getPackage : ()Ljava/lang/Package;
    //   6563: ifnull -> 6621
    //   6566: goto -> 6573
    //   6569: invokestatic a : (Ljava/lang/Throwable;)Ljava/lang/Throwable;
    //   6572: athrow
    //   6573: aload #8
    //   6575: invokevirtual getPackage : ()Ljava/lang/Package;
    //   6578: invokevirtual getName : ()Ljava/lang/String;
    //   6581: ifnull -> 6621
    //   6584: goto -> 6591
    //   6587: invokestatic a : (Ljava/lang/Throwable;)Ljava/lang/Throwable;
    //   6590: athrow
    //   6591: aload #8
    //   6593: invokevirtual getPackage : ()Ljava/lang/Package;
    //   6596: invokevirtual getName : ()Ljava/lang/String;
    //   6599: sipush #14349
    //   6602: sipush #25053
    //   6605: invokestatic a : (II)Ljava/lang/String;
    //   6608: invokevirtual startsWith : (Ljava/lang/String;)Z
    //   6611: ifne -> 6621
    //   6614: goto -> 6621
    //   6617: invokestatic a : (Ljava/lang/Throwable;)Ljava/lang/Throwable;
    //   6620: athrow
    //   6621: aload #7
    //   6623: iconst_1
    //   6624: invokevirtual setAccessible : (Z)V
    //   6627: aload #7
    //   6629: aconst_null
    //   6630: invokevirtual get : (Ljava/lang/Object;)Ljava/lang/Object;
    //   6633: pop
    //   6634: iinc #6, 1
    //   6637: iload_2
    //   6638: ifne -> 6499
    //   6641: sipush #14339
    //   6644: sipush #5040
    //   6647: invokestatic a : (II)Ljava/lang/String;
    //   6650: invokestatic forName : (Ljava/lang/String;)Ljava/lang/Class;
    //   6653: invokevirtual getDeclaredMethods : ()[Ljava/lang/reflect/Method;
    //   6656: astore #4
    //   6658: aload #4
    //   6660: arraylength
    //   6661: istore #5
    //   6663: iconst_0
    //   6664: istore #6
    //   6666: iload #6
    //   6668: iload #5
    //   6670: if_icmpge -> 6806
    //   6673: aload #4
    //   6675: iload #6
    //   6677: aaload
    //   6678: astore #7
    //   6680: aload #7
    //   6682: invokevirtual getParameterTypes : ()[Ljava/lang/Class;
    //   6685: pop
    //   6686: aload #7
    //   6688: invokevirtual getModifiers : ()I
    //   6691: invokestatic isStatic : (I)Z
    //   6694: ifeq -> 6792
    //   6697: aload #7
    //   6699: invokevirtual getParameterTypes : ()[Ljava/lang/Class;
    //   6702: arraylength
    //   6703: iconst_2
    //   6704: if_icmpne -> 6792
    //   6707: goto -> 6714
    //   6710: invokestatic a : (Ljava/lang/Throwable;)Ljava/lang/Throwable;
    //   6713: athrow
    //   6714: aload #7
    //   6716: invokevirtual getReturnType : ()Ljava/lang/Class;
    //   6719: getstatic java/lang/Boolean.TYPE : Ljava/lang/Class;
    //   6722: if_acmpne -> 6792
    //   6725: goto -> 6732
    //   6728: invokestatic a : (Ljava/lang/Throwable;)Ljava/lang/Throwable;
    //   6731: athrow
    //   6732: aload #7
    //   6734: iconst_1
    //   6735: invokevirtual setAccessible : (Z)V
    //   6738: aload #7
    //   6740: aconst_null
    //   6741: iconst_2
    //   6742: anewarray java/lang/Object
    //   6745: dup
    //   6746: iconst_0
    //   6747: aload_0
    //   6748: aastore
    //   6749: dup
    //   6750: iconst_1
    //   6751: aload_1
    //   6752: ifnonnull -> 6770
    //   6755: goto -> 6762
    //   6758: invokestatic a : (Ljava/lang/Throwable;)Ljava/lang/Throwable;
    //   6761: athrow
    //   6762: aload_1
    //   6763: goto -> 6777
    //   6766: invokestatic a : (Ljava/lang/Throwable;)Ljava/lang/Throwable;
    //   6769: athrow
    //   6770: aload_1
    //   6771: checkcast [B
    //   6774: invokevirtual clone : ()Ljava/lang/Object;
    //   6777: aastore
    //   6778: invokevirtual invoke : (Ljava/lang/Object;[Ljava/lang/Object;)Ljava/lang/Object;
    //   6781: checkcast java/lang/Boolean
    //   6784: invokevirtual booleanValue : ()Z
    //   6787: istore_3
    //   6788: iload_2
    //   6789: ifne -> 6806
    //   6792: iinc #6, 1
    //   6795: iload_2
    //   6796: ifne -> 6666
    //   6799: goto -> 6806
    //   6802: invokestatic a : (Ljava/lang/Throwable;)Ljava/lang/Throwable;
    //   6805: athrow
    //   6806: iload_2
    //   6807: ifne -> 7148
    //   6810: sipush #14344
    //   6813: sipush #2355
    //   6816: invokestatic a : (II)Ljava/lang/String;
    //   6819: iconst_1
    //   6820: ldc burp/Zkht
    //   6822: invokevirtual getClassLoader : ()Ljava/lang/ClassLoader;
    //   6825: invokestatic forName : (Ljava/lang/String;ZLjava/lang/ClassLoader;)Ljava/lang/Class;
    //   6828: invokevirtual getDeclaredFields : ()[Ljava/lang/reflect/Field;
    //   6831: astore #4
    //   6833: aload #4
    //   6835: arraylength
    //   6836: istore #5
    //   6838: iconst_0
    //   6839: istore #6
    //   6841: iload #6
    //   6843: iload #5
    //   6845: if_icmpge -> 6983
    //   6848: aload #4
    //   6850: iload #6
    //   6852: aaload
    //   6853: astore #7
    //   6855: aload #7
    //   6857: invokevirtual getModifiers : ()I
    //   6860: invokestatic isStatic : (I)Z
    //   6863: ifne -> 6873
    //   6866: goto -> 6976
    //   6869: invokestatic a : (Ljava/lang/Throwable;)Ljava/lang/Throwable;
    //   6872: athrow
    //   6873: aload #7
    //   6875: invokevirtual getType : ()Ljava/lang/Class;
    //   6878: astore #8
    //   6880: aload #8
    //   6882: ifnull -> 6963
    //   6885: aload #8
    //   6887: invokevirtual isPrimitive : ()Z
    //   6890: ifne -> 6963
    //   6893: goto -> 6900
    //   6896: invokestatic a : (Ljava/lang/Throwable;)Ljava/lang/Throwable;
    //   6899: athrow
    //   6900: aload #8
    //   6902: invokevirtual getPackage : ()Ljava/lang/Package;
    //   6905: ifnull -> 6963
    //   6908: goto -> 6915
    //   6911: invokestatic a : (Ljava/lang/Throwable;)Ljava/lang/Throwable;
    //   6914: athrow
    //   6915: aload #8
    //   6917: invokevirtual getPackage : ()Ljava/lang/Package;
    //   6920: invokevirtual getName : ()Ljava/lang/String;
    //   6923: ifnull -> 6963
    //   6926: goto -> 6933
    //   6929: invokestatic a : (Ljava/lang/Throwable;)Ljava/lang/Throwable;
    //   6932: athrow
    //   6933: aload #8
    //   6935: invokevirtual getPackage : ()Ljava/lang/Package;
    //   6938: invokevirtual getName : ()Ljava/lang/String;
    //   6941: sipush #14349
    //   6944: sipush #25053
    //   6947: invokestatic a : (II)Ljava/lang/String;
    //   6950: invokevirtual startsWith : (Ljava/lang/String;)Z
    //   6953: ifne -> 6963
    //   6956: goto -> 6963
    //   6959: invokestatic a : (Ljava/lang/Throwable;)Ljava/lang/Throwable;
    //   6962: athrow
    //   6963: aload #7
    //   6965: iconst_1
    //   6966: invokevirtual setAccessible : (Z)V
    //   6969: aload #7
    //   6971: aconst_null
    //   6972: invokevirtual get : (Ljava/lang/Object;)Ljava/lang/Object;
    //   6975: pop
    //   6976: iinc #6, 1
    //   6979: iload_2
    //   6980: ifne -> 6841
    //   6983: sipush #14364
    //   6986: sipush #30532
    //   6989: invokestatic a : (II)Ljava/lang/String;
    //   6992: invokestatic forName : (Ljava/lang/String;)Ljava/lang/Class;
    //   6995: invokevirtual getDeclaredMethods : ()[Ljava/lang/reflect/Method;
    //   6998: astore #4
    //   7000: aload #4
    //   7002: arraylength
    //   7003: istore #5
    //   7005: iconst_0
    //   7006: istore #6
    //   7008: iload #6
    //   7010: iload #5
    //   7012: if_icmpge -> 7148
    //   7015: aload #4
    //   7017: iload #6
    //   7019: aaload
    //   7020: astore #7
    //   7022: aload #7
    //   7024: invokevirtual getParameterTypes : ()[Ljava/lang/Class;
    //   7027: pop
    //   7028: aload #7
    //   7030: invokevirtual getModifiers : ()I
    //   7033: invokestatic isStatic : (I)Z
    //   7036: ifeq -> 7134
    //   7039: aload #7
    //   7041: invokevirtual getParameterTypes : ()[Ljava/lang/Class;
    //   7044: arraylength
    //   7045: iconst_2
    //   7046: if_icmpne -> 7134
    //   7049: goto -> 7056
    //   7052: invokestatic a : (Ljava/lang/Throwable;)Ljava/lang/Throwable;
    //   7055: athrow
    //   7056: aload #7
    //   7058: invokevirtual getReturnType : ()Ljava/lang/Class;
    //   7061: getstatic java/lang/Boolean.TYPE : Ljava/lang/Class;
    //   7064: if_acmpne -> 7134
    //   7067: goto -> 7074
    //   7070: invokestatic a : (Ljava/lang/Throwable;)Ljava/lang/Throwable;
    //   7073: athrow
    //   7074: aload #7
    //   7076: iconst_1
    //   7077: invokevirtual setAccessible : (Z)V
    //   7080: aload #7
    //   7082: aconst_null
    //   7083: iconst_2
    //   7084: anewarray java/lang/Object
    //   7087: dup
    //   7088: iconst_0
    //   7089: aload_0
    //   7090: aastore
    //   7091: dup
    //   7092: iconst_1
    //   7093: aload_1
    //   7094: ifnonnull -> 7112
    //   7097: goto -> 7104
    //   7100: invokestatic a : (Ljava/lang/Throwable;)Ljava/lang/Throwable;
    //   7103: athrow
    //   7104: aload_1
    //   7105: goto -> 7119
    //   7108: invokestatic a : (Ljava/lang/Throwable;)Ljava/lang/Throwable;
    //   7111: athrow
    //   7112: aload_1
    //   7113: checkcast [B
    //   7116: invokevirtual clone : ()Ljava/lang/Object;
    //   7119: aastore
    //   7120: invokevirtual invoke : (Ljava/lang/Object;[Ljava/lang/Object;)Ljava/lang/Object;
    //   7123: checkcast java/lang/Boolean
    //   7126: invokevirtual booleanValue : ()Z
    //   7129: istore_3
    //   7130: iload_2
    //   7131: ifne -> 7148
    //   7134: iinc #6, 1
    //   7137: iload_2
    //   7138: ifne -> 7008
    //   7141: goto -> 7148
    //   7144: invokestatic a : (Ljava/lang/Throwable;)Ljava/lang/Throwable;
    //   7147: athrow
    //   7148: iload_3
    //   7149: ifeq -> 7154
    //   7152: iload_3
    //   7153: ireturn
    //   7154: getstatic burp/Zs9k.Zx : Ljava/lang/String;
    //   7157: getstatic burp/Zeu2.ZW : Ljava/lang/Object;
    //   7160: checkcast java/math/BigInteger
    //   7163: invokevirtual intValue : ()I
    //   7166: bipush #32
    //   7168: irem
    //   7169: invokestatic abs : (I)I
    //   7172: invokevirtual charAt : (I)C
    //   7175: getstatic burp/Zsk2.ZE : Ljava/lang/String;
    //   7178: getstatic burp/Zetv.ZI : Ljava/lang/Object;
    //   7181: checkcast java/math/BigInteger
    //   7184: invokevirtual intValue : ()I
    //   7187: bipush #32
    //   7189: irem
    //   7190: invokestatic abs : (I)I
    //   7193: invokevirtual charAt : (I)C
    //   7196: if_icmpgt -> 7541
    //   7199: sipush #14342
    //   7202: sipush #-13675
    //   7205: invokestatic a : (II)Ljava/lang/String;
    //   7208: iconst_1
    //   7209: ldc burp/Zmji
    //   7211: invokevirtual getClassLoader : ()Ljava/lang/ClassLoader;
    //   7214: invokestatic forName : (Ljava/lang/String;ZLjava/lang/ClassLoader;)Ljava/lang/Class;
    //   7217: invokevirtual getDeclaredFields : ()[Ljava/lang/reflect/Field;
    //   7220: astore #4
    //   7222: aload #4
    //   7224: arraylength
    //   7225: istore #5
    //   7227: iconst_0
    //   7228: istore #6
    //   7230: iload #6
    //   7232: iload #5
    //   7234: if_icmpge -> 7372
    //   7237: aload #4
    //   7239: iload #6
    //   7241: aaload
    //   7242: astore #7
    //   7244: aload #7
    //   7246: invokevirtual getModifiers : ()I
    //   7249: invokestatic isStatic : (I)Z
    //   7252: ifne -> 7262
    //   7255: goto -> 7365
    //   7258: invokestatic a : (Ljava/lang/Throwable;)Ljava/lang/Throwable;
    //   7261: athrow
    //   7262: aload #7
    //   7264: invokevirtual getType : ()Ljava/lang/Class;
    //   7267: astore #8
    //   7269: aload #8
    //   7271: ifnull -> 7352
    //   7274: aload #8
    //   7276: invokevirtual isPrimitive : ()Z
    //   7279: ifne -> 7352
    //   7282: goto -> 7289
    //   7285: invokestatic a : (Ljava/lang/Throwable;)Ljava/lang/Throwable;
    //   7288: athrow
    //   7289: aload #8
    //   7291: invokevirtual getPackage : ()Ljava/lang/Package;
    //   7294: ifnull -> 7352
    //   7297: goto -> 7304
    //   7300: invokestatic a : (Ljava/lang/Throwable;)Ljava/lang/Throwable;
    //   7303: athrow
    //   7304: aload #8
    //   7306: invokevirtual getPackage : ()Ljava/lang/Package;
    //   7309: invokevirtual getName : ()Ljava/lang/String;
    //   7312: ifnull -> 7352
    //   7315: goto -> 7322
    //   7318: invokestatic a : (Ljava/lang/Throwable;)Ljava/lang/Throwable;
    //   7321: athrow
    //   7322: aload #8
    //   7324: invokevirtual getPackage : ()Ljava/lang/Package;
    //   7327: invokevirtual getName : ()Ljava/lang/String;
    //   7330: sipush #14349
    //   7333: sipush #25053
    //   7336: invokestatic a : (II)Ljava/lang/String;
    //   7339: invokevirtual startsWith : (Ljava/lang/String;)Z
    //   7342: ifne -> 7352
    //   7345: goto -> 7352
    //   7348: invokestatic a : (Ljava/lang/Throwable;)Ljava/lang/Throwable;
    //   7351: athrow
    //   7352: aload #7
    //   7354: iconst_1
    //   7355: invokevirtual setAccessible : (Z)V
    //   7358: aload #7
    //   7360: aconst_null
    //   7361: invokevirtual get : (Ljava/lang/Object;)Ljava/lang/Object;
    //   7364: pop
    //   7365: iinc #6, 1
    //   7368: iload_2
    //   7369: ifne -> 7230
    //   7372: sipush #14347
    //   7375: sipush #-32142
    //   7378: invokestatic a : (II)Ljava/lang/String;
    //   7381: invokestatic forName : (Ljava/lang/String;)Ljava/lang/Class;
    //   7384: invokevirtual getDeclaredMethods : ()[Ljava/lang/reflect/Method;
    //   7387: astore #4
    //   7389: aload #4
    //   7391: arraylength
    //   7392: istore #5
    //   7394: iconst_0
    //   7395: istore #6
    //   7397: iload #6
    //   7399: iload #5
    //   7401: if_icmpge -> 7537
    //   7404: aload #4
    //   7406: iload #6
    //   7408: aaload
    //   7409: astore #7
    //   7411: aload #7
    //   7413: invokevirtual getParameterTypes : ()[Ljava/lang/Class;
    //   7416: pop
    //   7417: aload #7
    //   7419: invokevirtual getModifiers : ()I
    //   7422: invokestatic isStatic : (I)Z
    //   7425: ifeq -> 7523
    //   7428: aload #7
    //   7430: invokevirtual getParameterTypes : ()[Ljava/lang/Class;
    //   7433: arraylength
    //   7434: iconst_2
    //   7435: if_icmpne -> 7523
    //   7438: goto -> 7445
    //   7441: invokestatic a : (Ljava/lang/Throwable;)Ljava/lang/Throwable;
    //   7444: athrow
    //   7445: aload #7
    //   7447: invokevirtual getReturnType : ()Ljava/lang/Class;
    //   7450: getstatic java/lang/Boolean.TYPE : Ljava/lang/Class;
    //   7453: if_acmpne -> 7523
    //   7456: goto -> 7463
    //   7459: invokestatic a : (Ljava/lang/Throwable;)Ljava/lang/Throwable;
    //   7462: athrow
    //   7463: aload #7
    //   7465: iconst_1
    //   7466: invokevirtual setAccessible : (Z)V
    //   7469: aload #7
    //   7471: aconst_null
    //   7472: iconst_2
    //   7473: anewarray java/lang/Object
    //   7476: dup
    //   7477: iconst_0
    //   7478: aload_0
    //   7479: aastore
    //   7480: dup
    //   7481: iconst_1
    //   7482: aload_1
    //   7483: ifnonnull -> 7501
    //   7486: goto -> 7493
    //   7489: invokestatic a : (Ljava/lang/Throwable;)Ljava/lang/Throwable;
    //   7492: athrow
    //   7493: aload_1
    //   7494: goto -> 7508
    //   7497: invokestatic a : (Ljava/lang/Throwable;)Ljava/lang/Throwable;
    //   7500: athrow
    //   7501: aload_1
    //   7502: checkcast [B
    //   7505: invokevirtual clone : ()Ljava/lang/Object;
    //   7508: aastore
    //   7509: invokevirtual invoke : (Ljava/lang/Object;[Ljava/lang/Object;)Ljava/lang/Object;
    //   7512: checkcast java/lang/Boolean
    //   7515: invokevirtual booleanValue : ()Z
    //   7518: istore_3
    //   7519: iload_2
    //   7520: ifne -> 7537
    //   7523: iinc #6, 1
    //   7526: iload_2
    //   7527: ifne -> 7397
    //   7530: goto -> 7537
    //   7533: invokestatic a : (Ljava/lang/Throwable;)Ljava/lang/Throwable;
    //   7536: athrow
    //   7537: iload_2
    //   7538: ifne -> 7879
    //   7541: sipush #14351
    //   7544: sipush #-1490
    //   7547: invokestatic a : (II)Ljava/lang/String;
    //   7550: iconst_1
    //   7551: ldc burp/Zefm
    //   7553: invokevirtual getClassLoader : ()Ljava/lang/ClassLoader;
    //   7556: invokestatic forName : (Ljava/lang/String;ZLjava/lang/ClassLoader;)Ljava/lang/Class;
    //   7559: invokevirtual getDeclaredFields : ()[Ljava/lang/reflect/Field;
    //   7562: astore #4
    //   7564: aload #4
    //   7566: arraylength
    //   7567: istore #5
    //   7569: iconst_0
    //   7570: istore #6
    //   7572: iload #6
    //   7574: iload #5
    //   7576: if_icmpge -> 7714
    //   7579: aload #4
    //   7581: iload #6
    //   7583: aaload
    //   7584: astore #7
    //   7586: aload #7
    //   7588: invokevirtual getModifiers : ()I
    //   7591: invokestatic isStatic : (I)Z
    //   7594: ifne -> 7604
    //   7597: goto -> 7707
    //   7600: invokestatic a : (Ljava/lang/Throwable;)Ljava/lang/Throwable;
    //   7603: athrow
    //   7604: aload #7
    //   7606: invokevirtual getType : ()Ljava/lang/Class;
    //   7609: astore #8
    //   7611: aload #8
    //   7613: ifnull -> 7694
    //   7616: aload #8
    //   7618: invokevirtual isPrimitive : ()Z
    //   7621: ifne -> 7694
    //   7624: goto -> 7631
    //   7627: invokestatic a : (Ljava/lang/Throwable;)Ljava/lang/Throwable;
    //   7630: athrow
    //   7631: aload #8
    //   7633: invokevirtual getPackage : ()Ljava/lang/Package;
    //   7636: ifnull -> 7694
    //   7639: goto -> 7646
    //   7642: invokestatic a : (Ljava/lang/Throwable;)Ljava/lang/Throwable;
    //   7645: athrow
    //   7646: aload #8
    //   7648: invokevirtual getPackage : ()Ljava/lang/Package;
    //   7651: invokevirtual getName : ()Ljava/lang/String;
    //   7654: ifnull -> 7694
    //   7657: goto -> 7664
    //   7660: invokestatic a : (Ljava/lang/Throwable;)Ljava/lang/Throwable;
    //   7663: athrow
    //   7664: aload #8
    //   7666: invokevirtual getPackage : ()Ljava/lang/Package;
    //   7669: invokevirtual getName : ()Ljava/lang/String;
    //   7672: sipush #14349
    //   7675: sipush #25053
    //   7678: invokestatic a : (II)Ljava/lang/String;
    //   7681: invokevirtual startsWith : (Ljava/lang/String;)Z
    //   7684: ifne -> 7694
    //   7687: goto -> 7694
    //   7690: invokestatic a : (Ljava/lang/Throwable;)Ljava/lang/Throwable;
    //   7693: athrow
    //   7694: aload #7
    //   7696: iconst_1
    //   7697: invokevirtual setAccessible : (Z)V
    //   7700: aload #7
    //   7702: aconst_null
    //   7703: invokevirtual get : (Ljava/lang/Object;)Ljava/lang/Object;
    //   7706: pop
    //   7707: iinc #6, 1
    //   7710: iload_2
    //   7711: ifne -> 7572
    //   7714: sipush #14340
    //   7717: sipush #-23034
    //   7720: invokestatic a : (II)Ljava/lang/String;
    //   7723: invokestatic forName : (Ljava/lang/String;)Ljava/lang/Class;
    //   7726: invokevirtual getDeclaredMethods : ()[Ljava/lang/reflect/Method;
    //   7729: astore #4
    //   7731: aload #4
    //   7733: arraylength
    //   7734: istore #5
    //   7736: iconst_0
    //   7737: istore #6
    //   7739: iload #6
    //   7741: iload #5
    //   7743: if_icmpge -> 7879
    //   7746: aload #4
    //   7748: iload #6
    //   7750: aaload
    //   7751: astore #7
    //   7753: aload #7
    //   7755: invokevirtual getParameterTypes : ()[Ljava/lang/Class;
    //   7758: pop
    //   7759: aload #7
    //   7761: invokevirtual getModifiers : ()I
    //   7764: invokestatic isStatic : (I)Z
    //   7767: ifeq -> 7865
    //   7770: aload #7
    //   7772: invokevirtual getParameterTypes : ()[Ljava/lang/Class;
    //   7775: arraylength
    //   7776: iconst_2
    //   7777: if_icmpne -> 7865
    //   7780: goto -> 7787
    //   7783: invokestatic a : (Ljava/lang/Throwable;)Ljava/lang/Throwable;
    //   7786: athrow
    //   7787: aload #7
    //   7789: invokevirtual getReturnType : ()Ljava/lang/Class;
    //   7792: getstatic java/lang/Boolean.TYPE : Ljava/lang/Class;
    //   7795: if_acmpne -> 7865
    //   7798: goto -> 7805
    //   7801: invokestatic a : (Ljava/lang/Throwable;)Ljava/lang/Throwable;
    //   7804: athrow
    //   7805: aload #7
    //   7807: iconst_1
    //   7808: invokevirtual setAccessible : (Z)V
    //   7811: aload #7
    //   7813: aconst_null
    //   7814: iconst_2
    //   7815: anewarray java/lang/Object
    //   7818: dup
    //   7819: iconst_0
    //   7820: aload_0
    //   7821: aastore
    //   7822: dup
    //   7823: iconst_1
    //   7824: aload_1
    //   7825: ifnonnull -> 7843
    //   7828: goto -> 7835
    //   7831: invokestatic a : (Ljava/lang/Throwable;)Ljava/lang/Throwable;
    //   7834: athrow
    //   7835: aload_1
    //   7836: goto -> 7850
    //   7839: invokestatic a : (Ljava/lang/Throwable;)Ljava/lang/Throwable;
    //   7842: athrow
    //   7843: aload_1
    //   7844: checkcast [B
    //   7847: invokevirtual clone : ()Ljava/lang/Object;
    //   7850: aastore
    //   7851: invokevirtual invoke : (Ljava/lang/Object;[Ljava/lang/Object;)Ljava/lang/Object;
    //   7854: checkcast java/lang/Boolean
    //   7857: invokevirtual booleanValue : ()Z
    //   7860: istore_3
    //   7861: iload_2
    //   7862: ifne -> 7879
    //   7865: iinc #6, 1
    //   7868: iload_2
    //   7869: ifne -> 7739
    //   7872: goto -> 7879
    //   7875: invokestatic a : (Ljava/lang/Throwable;)Ljava/lang/Throwable;
    //   7878: athrow
    //   7879: iload_3
    //   7880: ireturn
    //   7881: astore_3
    //   7882: new java/lang/Exception
    //   7885: dup
    //   7886: aload_3
    //   7887: invokevirtual getMessage : ()Ljava/lang/String;
    //   7890: invokespecial <init> : (Ljava/lang/String;)V
    //   7893: athrow
    // Exception table:
    //   from	to	target	type
    //   4	5691	7881	java/lang/Throwable
    //   3570	3595	3595	java/lang/Throwable
    //   4558	4584	4584	java/lang/Throwable
    //   4673	4687	4687	java/lang/Throwable
    //   4698	4711	4714	java/lang/Throwable
    //   4703	4726	4729	java/lang/Throwable
    //   4718	4744	4747	java/lang/Throwable
    //   4733	4774	4777	java/lang/Throwable
    //   4837	4864	4867	java/lang/Throwable
    //   4854	4885	4888	java/lang/Throwable
    //   4871	4915	4918	java/lang/Throwable
    //   4892	4926	4926	java/lang/Throwable
    //   4937	4953	4956	java/lang/Throwable
    //   5052	5066	5066	java/lang/Throwable
    //   5077	5090	5093	java/lang/Throwable
    //   5082	5105	5108	java/lang/Throwable
    //   5097	5123	5126	java/lang/Throwable
    //   5112	5153	5156	java/lang/Throwable
    //   5219	5246	5249	java/lang/Throwable
    //   5236	5264	5267	java/lang/Throwable
    //   5253	5294	5297	java/lang/Throwable
    //   5271	5305	5305	java/lang/Throwable
    //   5327	5338	5341	java/lang/Throwable
    //   5393	5407	5407	java/lang/Throwable
    //   5418	5431	5434	java/lang/Throwable
    //   5423	5446	5449	java/lang/Throwable
    //   5438	5464	5467	java/lang/Throwable
    //   5453	5494	5497	java/lang/Throwable
    //   5560	5587	5590	java/lang/Throwable
    //   5577	5605	5608	java/lang/Throwable
    //   5594	5635	5638	java/lang/Throwable
    //   5612	5646	5646	java/lang/Throwable
    //   5668	5679	5682	java/lang/Throwable
    //   5692	6422	7881	java/lang/Throwable
    //   5782	5796	5796	java/lang/Throwable
    //   5807	5820	5823	java/lang/Throwable
    //   5812	5835	5838	java/lang/Throwable
    //   5827	5853	5856	java/lang/Throwable
    //   5842	5883	5886	java/lang/Throwable
    //   5949	5976	5979	java/lang/Throwable
    //   5966	5994	5997	java/lang/Throwable
    //   5983	6024	6027	java/lang/Throwable
    //   6001	6035	6035	java/lang/Throwable
    //   6057	6068	6071	java/lang/Throwable
    //   6124	6138	6138	java/lang/Throwable
    //   6149	6162	6165	java/lang/Throwable
    //   6154	6177	6180	java/lang/Throwable
    //   6169	6195	6198	java/lang/Throwable
    //   6184	6225	6228	java/lang/Throwable
    //   6291	6318	6321	java/lang/Throwable
    //   6308	6336	6339	java/lang/Throwable
    //   6325	6366	6369	java/lang/Throwable
    //   6343	6377	6377	java/lang/Throwable
    //   6399	6410	6413	java/lang/Throwable
    //   6423	7153	7881	java/lang/Throwable
    //   6513	6527	6527	java/lang/Throwable
    //   6538	6551	6554	java/lang/Throwable
    //   6543	6566	6569	java/lang/Throwable
    //   6558	6584	6587	java/lang/Throwable
    //   6573	6614	6617	java/lang/Throwable
    //   6680	6707	6710	java/lang/Throwable
    //   6697	6725	6728	java/lang/Throwable
    //   6714	6755	6758	java/lang/Throwable
    //   6732	6766	6766	java/lang/Throwable
    //   6788	6799	6802	java/lang/Throwable
    //   6855	6869	6869	java/lang/Throwable
    //   6880	6893	6896	java/lang/Throwable
    //   6885	6908	6911	java/lang/Throwable
    //   6900	6926	6929	java/lang/Throwable
    //   6915	6956	6959	java/lang/Throwable
    //   7022	7049	7052	java/lang/Throwable
    //   7039	7067	7070	java/lang/Throwable
    //   7056	7097	7100	java/lang/Throwable
    //   7074	7108	7108	java/lang/Throwable
    //   7130	7141	7144	java/lang/Throwable
    //   7154	7880	7881	java/lang/Throwable
    //   7244	7258	7258	java/lang/Throwable
    //   7269	7282	7285	java/lang/Throwable
    //   7274	7297	7300	java/lang/Throwable
    //   7289	7315	7318	java/lang/Throwable
    //   7304	7345	7348	java/lang/Throwable
    //   7411	7438	7441	java/lang/Throwable
    //   7428	7456	7459	java/lang/Throwable
    //   7445	7486	7489	java/lang/Throwable
    //   7463	7497	7497	java/lang/Throwable
    //   7519	7530	7533	java/lang/Throwable
    //   7586	7600	7600	java/lang/Throwable
    //   7611	7624	7627	java/lang/Throwable
    //   7616	7639	7642	java/lang/Throwable
    //   7631	7657	7660	java/lang/Throwable
    //   7646	7687	7690	java/lang/Throwable
    //   7753	7780	7783	java/lang/Throwable
    //   7770	7798	7801	java/lang/Throwable
    //   7787	7828	7831	java/lang/Throwable
    //   7805	7839	7839	java/lang/Throwable
    //   7861	7872	7875	java/lang/Throwable
  }
  
  static {
    // Byte code:
    //   0: bipush #27
    //   2: anewarray java/lang/String
    //   5: astore #5
    //   7: iconst_0
    //   8: istore_3
    //   9: ldc '+.Y!z\\t(9L\\n\\t\\fHVWUB ,6,QUg80>">#E4[\\t! !f\\tDil\\td/4\\b\\t#"E))\\tssROh\\tB0l\\no\\t}rG4Fn3\\rG\\t&U5\\tcV$X\\toU++\\tU-\\tiS\\f;\\t!a: f$ :l7pmW5\\r\cx\\thl,rS\\t#E)xMT;lnZQvc~jE~|_HE\\b&:A}-\\te=S&=J*\\t2zU'
    //   11: dup
    //   12: astore_2
    //   13: invokevirtual length : ()I
    //   16: istore #4
    //   18: bipush #9
    //   20: istore_1
    //   21: iconst_m1
    //   22: istore_0
    //   23: bipush #71
    //   25: iinc #0, 1
    //   28: aload_2
    //   29: iload_0
    //   30: dup
    //   31: iload_1
    //   32: iadd
    //   33: invokevirtual substring : (II)Ljava/lang/String;
    //   36: iconst_m1
    //   37: goto -> 143
    //   40: aload #5
    //   42: swap
    //   43: iload_3
    //   44: iinc #3, 1
    //   47: swap
    //   48: aastore
    //   49: iload_0
    //   50: iload_1
    //   51: iadd
    //   52: dup
    //   53: istore_0
    //   54: iload #4
    //   56: if_icmpge -> 68
    //   59: aload_2
    //   60: iload_0
    //   61: invokevirtual charAt : (I)C
    //   64: istore_1
    //   65: goto -> 23
    //   68: ldc 'yj~~4VN5jv\\t44'
    //   70: dup
    //   71: astore_2
    //   72: invokevirtual length : ()I
    //   75: istore #4
    //   77: bipush #19
    //   79: istore_1
    //   80: iconst_m1
    //   81: istore_0
    //   82: bipush #54
    //   84: iinc #0, 1
    //   87: aload_2
    //   88: iload_0
    //   89: dup
    //   90: iload_1
    //   91: iadd
    //   92: invokevirtual substring : (II)Ljava/lang/String;
    //   95: iconst_0
    //   96: goto -> 143
    //   99: aload #5
    //   101: swap
    //   102: iload_3
    //   103: iinc #3, 1
    //   106: swap
    //   107: aastore
    //   108: iload_0
    //   109: iload_1
    //   110: iadd
    //   111: dup
    //   112: istore_0
    //   113: iload #4
    //   115: if_icmpge -> 127
    //   118: aload_2
    //   119: iload_0
    //   120: invokevirtual charAt : (I)C
    //   123: istore_1
    //   124: goto -> 82
    //   127: aload #5
    //   129: putstatic burp/Zsk2.a : [Ljava/lang/String;
    //   132: bipush #27
    //   134: anewarray java/lang/String
    //   137: putstatic burp/Zsk2.b : [Ljava/lang/String;
    //   140: goto -> 300
    //   143: dup_x2
    //   144: pop
    //   145: invokevirtual toCharArray : ()[C
    //   148: dup_x1
    //   149: arraylength
    //   150: dup_x2
    //   151: pop
    //   152: iconst_0
    //   153: istore #6
    //   155: dup2_x1
    //   156: pop2
    //   157: dup_x2
    //   158: iconst_1
    //   159: if_icmpgt -> 260
    //   162: dup2
    //   163: swap
    //   164: iload #6
    //   166: dup2_x1
    //   167: caload
    //   168: swap
    //   169: iload #6
    //   171: bipush #7
    //   173: irem
    //   174: tableswitch default -> 242, 0 -> 212, 1 -> 217, 2 -> 222, 3 -> 227, 4 -> 232, 5 -> 237
    //   212: bipush #60
    //   214: goto -> 244
    //   217: bipush #123
    //   219: goto -> 244
    //   222: bipush #72
    //   224: goto -> 244
    //   227: bipush #74
    //   229: goto -> 244
    //   232: bipush #75
    //   234: goto -> 244
    //   237: bipush #67
    //   239: goto -> 244
    //   242: bipush #9
    //   244: ixor
    //   245: ixor
    //   246: i2c
    //   247: castore
    //   248: iinc #6, 1
    //   251: dup
    //   252: ifne -> 260
    //   255: dup2
    //   256: dup_x1
    //   257: goto -> 166
    //   260: dup2_x1
    //   261: pop2
    //   262: dup_x2
    //   263: iload #6
    //   265: if_icmpgt -> 162
    //   268: pop
    //   269: new java/lang/String
    //   272: dup_x1
    //   273: swap
    //   274: invokespecial <init> : ([C)V
    //   277: invokevirtual intern : ()Ljava/lang/String;
    //   280: swap
    //   281: pop
    //   282: swap
    //   283: tableswitch default -> 40, 0 -> 99
    //   300: new java/math/BigInteger
    //   303: dup
    //   304: bipush #32
    //   306: newarray byte
    //   308: dup
    //   309: iconst_0
    //   310: bipush #15
    //   312: bastore
    //   313: dup
    //   314: iconst_1
    //   315: bipush #-110
    //   317: bastore
    //   318: dup
    //   319: iconst_2
    //   320: bipush #-19
    //   322: bastore
    //   323: dup
    //   324: iconst_3
    //   325: bipush #-53
    //   327: bastore
    //   328: dup
    //   329: iconst_4
    //   330: bipush #-88
    //   332: bastore
    //   333: dup
    //   334: iconst_5
    //   335: bipush #-109
    //   337: bastore
    //   338: dup
    //   339: bipush #6
    //   341: bipush #-84
    //   343: bastore
    //   344: dup
    //   345: bipush #7
    //   347: bipush #-44
    //   349: bastore
    //   350: dup
    //   351: bipush #8
    //   353: bipush #80
    //   355: bastore
    //   356: dup
    //   357: bipush #9
    //   359: bipush #99
    //   361: bastore
    //   362: dup
    //   363: bipush #10
    //   365: bipush #40
    //   367: bastore
    //   368: dup
    //   369: bipush #11
    //   371: bipush #-55
    //   373: bastore
    //   374: dup
    //   375: bipush #12
    //   377: bipush #72
    //   379: bastore
    //   380: dup
    //   381: bipush #13
    //   383: bipush #-7
    //   385: bastore
    //   386: dup
    //   387: bipush #14
    //   389: bipush #30
    //   391: bastore
    //   392: dup
    //   393: bipush #15
    //   395: bipush #57
    //   397: bastore
    //   398: dup
    //   399: bipush #16
    //   401: bipush #69
    //   403: bastore
    //   404: dup
    //   405: bipush #17
    //   407: bipush #-31
    //   409: bastore
    //   410: dup
    //   411: bipush #18
    //   413: bipush #-55
    //   415: bastore
    //   416: dup
    //   417: bipush #19
    //   419: bipush #-112
    //   421: bastore
    //   422: dup
    //   423: bipush #20
    //   425: bipush #26
    //   427: bastore
    //   428: dup
    //   429: bipush #21
    //   431: bipush #-23
    //   433: bastore
    //   434: dup
    //   435: bipush #22
    //   437: bipush #35
    //   439: bastore
    //   440: dup
    //   441: bipush #23
    //   443: bipush #62
    //   445: bastore
    //   446: dup
    //   447: bipush #24
    //   449: bipush #88
    //   451: bastore
    //   452: dup
    //   453: bipush #25
    //   455: bipush #26
    //   457: bastore
    //   458: dup
    //   459: bipush #26
    //   461: bipush #23
    //   463: bastore
    //   464: dup
    //   465: bipush #27
    //   467: bipush #9
    //   469: bastore
    //   470: dup
    //   471: bipush #28
    //   473: bipush #-57
    //   475: bastore
    //   476: dup
    //   477: bipush #29
    //   479: bipush #-108
    //   481: bastore
    //   482: dup
    //   483: bipush #30
    //   485: bipush #69
    //   487: bastore
    //   488: dup
    //   489: bipush #31
    //   491: bipush #81
    //   493: bastore
    //   494: invokespecial <init> : ([B)V
    //   497: putstatic burp/Zsk2.ZD : Ljava/lang/Object;
    //   500: sipush #14341
    //   503: sipush #-4705
    //   506: invokestatic a : (II)Ljava/lang/String;
    //   509: putstatic burp/Zsk2.ZE : Ljava/lang/String;
    //   512: return
  }
  
  private static Throwable a(Throwable paramThrowable) {
    return paramThrowable;
  }
  
  private static String a(int paramInt1, int paramInt2) {
    int i = (paramInt1 ^ 0x3806) & 0xFFFF;
    if (b[i] == null) {
      char[] arrayOfChar = a[i].toCharArray();
      switch (arrayOfChar[0] & 0xFF) {
        case 0:
        
        case 1:
        
        case 2:
        
        case 3:
        
        case 4:
        
        case 5:
        
        case 6:
        
        case 7:
        
        case 8:
        
        case 9:
        
        case 10:
        
        case 11:
        
        case 12:
        
        case 13:
        
        case 14:
        
        case 15:
        
        case 16:
        
        case 17:
        
        case 18:
        
        case 19:
        
        case 20:
        
        case 21:
        
        case 22:
        
        case 23:
        
        case 24:
        
        case 25:
        
        case 26:
        
        case 27:
        
        case 28:
        
        case 29:
        
        case 30:
        
        case 31:
        
        case 32:
        
        case 33:
        
        case 34:
        
        case 35:
        
        case 36:
        
        case 37:
        
        case 38:
        
        case 39:
        
        case 40:
        
        case 41:
        
        case 42:
        
        case 43:
        
        case 44:
        
        case 45:
        
        case 46:
        
        case 47:
        
        case 48:
        
        case 49:
        
        case 50:
        
        case 51:
        
        case 52:
        
        case 53:
        
        case 54:
        
        case 55:
        
        case 56:
        
        case 57:
        
        case 58:
        
        case 59:
        
        case 60:
        
        case 61:
        
        case 62:
        
        case 63:
        
        case 64:
        
        case 65:
        
        case 66:
        
        case 67:
        
        case 68:
        
        case 69:
        
        case 70:
        
        case 71:
        
        case 72:
        
        case 73:
        
        case 74:
        
        case 75:
        
        case 76:
        
        case 77:
        
        case 78:
        
        case 79:
        
        case 80:
        
        case 81:
        
        case 82:
        
        case 83:
        
        case 84:
        
        case 85:
        
        case 86:
        
        case 87:
        
        case 88:
        
        case 89:
        
        case 90:
        
        case 91:
        
        case 92:
        
        case 93:
        
        case 94:
        
        case 95:
        
        case 96:
        
        case 97:
        
        case 98:
        
        case 99:
        
        case 100:
        
        case 101:
        
        case 102:
        
        case 103:
        
        case 104:
        
        case 105:
        
        case 106:
        
        case 107:
        
        case 108:
        
        case 109:
        
        case 110:
        
        case 111:
        
        case 112:
        
        case 113:
        
        case 114:
        
        case 115:
        
        case 116:
        
        case 117:
        
        case 118:
        
        case 119:
        
        case 120:
        
        case 121:
        
        case 122:
        
        case 123:
        
        case 124:
        
        case 125:
        
        case 126:
        
        case 127:
        
        case 128:
        
        case 129:
        
        case 130:
        
        case 131:
        
        case 132:
        
        case 133:
        
        case 134:
        
        case 135:
        
        case 136:
        
        case 137:
        
        case 138:
        
        case 139:
        
        case 140:
        
        case 141:
        
        case 142:
        
        case 143:
        
        case 144:
        
        case 145:
        
        case 146:
        
        case 147:
        
        case 148:
        
        case 149:
        
        case 150:
        
        case 151:
        
        case 152:
        
        case 153:
        
        case 154:
        
        case 155:
        
        case 156:
        
        case 157:
        
        case 158:
        
        case 159:
        
        case 160:
        
        case 161:
        
        case 162:
        
        case 163:
        
        case 164:
        
        case 165:
        
        case 166:
        
        case 167:
        
        case 168:
        
        case 169:
        
        case 170:
        
        case 171:
        
        case 172:
        
        case 173:
        
        case 174:
        
        case 175:
        
        case 176:
        
        case 177:
        
        case 178:
        
        case 179:
        
        case 180:
        
        case 181:
        
        case 182:
        
        case 183:
        
        case 184:
        
        case 185:
        
        case 186:
        
        case 187:
        
        case 188:
        
        case 189:
        
        case 190:
        
        case 191:
        
        case 192:
        
        case 193:
        
        case 194:
        
        case 195:
        
        case 196:
        
        case 197:
        
        case 198:
        
        case 199:
        
        case 200:
        
        case 201:
        
        case 202:
        
        case 203:
        
        case 204:
        
        case 205:
        
        case 206:
        
        case 207:
        
        case 208:
        
        case 209:
        
        case 210:
        
        case 211:
        
        case 212:
        
        case 213:
        
        case 214:
        
        case 215:
        
        case 216:
        
        case 217:
        
        case 218:
        
        case 219:
        
        case 220:
        
        case 221:
        
        case 222:
        
        case 223:
        
        case 224:
        
        case 225:
        
        case 226:
        
        case 227:
        
        case 228:
        
        case 229:
        
        case 230:
        
        case 231:
        
        case 232:
        
        case 233:
        
        case 234:
        
        case 235:
        
        case 236:
        
        case 237:
        
        case 238:
        
        case 239:
        
        case 240:
        
        case 241:
        
        case 242:
        
        case 243:
        
        case 244:
        
        case 245:
        
        case 246:
        
        case 247:
        
        case 248:
        
        case 249:
        
        case 250:
        
        case 251:
        
        case 252:
        
        case 253:
        
        case 254:
        
        default:
          break;
      } 
      char c = '';
      int j = (paramInt2 & 0xFF) - c;
      if (j < 0)
        j += 256; 
      int k = ((paramInt2 & 0xFFFF) >>> 8) - c;
      if (k < 0)
        k += 256; 
      for (byte b = 0; b < arrayOfChar.length; b++) {
        int m = b % 2;
        if (m == 0) {
          arrayOfChar[b] = (char)(arrayOfChar[b] ^ j);
          j = ((j >>> 3 | j << 5) ^ arrayOfChar[b]) & 0xFF;
        } else {
          arrayOfChar[b] = (char)(arrayOfChar[b] ^ k);
          k = ((k >>> 3 | k << 5) ^ arrayOfChar[b]) & 0xFF;
        } 
      } 
      b[i] = (new String(arrayOfChar)).intern();
    } 
    return b[i];
  }
}


/* Location:              C:\Program Files\BurpSuitePro\burpsuite_pro.jar!\burp\Zsk2.class
 * Java compiler version: 21 (65.0)
 * JD-Core Version:       1.1.3
 */