package burp;

import java.math.BigInteger;

class Zsn3 extends ClassLoader {
  static String ZS;
  
  static Object Zy;
  
  private static final String[] a;
  
  private static final String[] b;
  
  static void ZL(Object[] paramArrayOfObject, Object paramObject) throws Throwable {}
  
  static void ZE(Object paramObject) {
    Zr6c.Zf = a(-14569, -27250);
    Zr6c.ZG = new BigInteger(a(-14572, -32067));
    boolean bool = Zt2e.ZN();
    try {
      try {
        if (Zmhq.Zy.charAt(Math.abs(((BigInteger)Zlt1.ZH).intValue() % 32)) > Ztzj.ZB.charAt(Math.abs(((BigInteger)Ztzj.Zv).intValue() % 32))) {
          try {
            Zbun.Zo(Class.forName(a(-14563, -12328)));
            if (!bool)
              Zzvr.Ze(Class.forName(a(-14574, 12072))); 
          } catch (Throwable throwable) {
            throw a(null);
          } 
          return;
        } 
      } catch (Throwable throwable) {
        throw a(null);
      } 
      Zzvr.Ze(Class.forName(a(-14574, 12072)));
    } catch (Throwable throwable) {}
  }
  
  static boolean ZI(Object[] paramArrayOfObject, Object paramObject) throws Throwable {
    // Byte code:
    //   0: invokestatic ZN : ()Z
    //   3: istore_2
    //   4: new java/lang/StringBuilder
    //   7: dup
    //   8: invokespecial <init> : ()V
    //   11: astore_3
    //   12: iconst_0
    //   13: istore #4
    //   15: iload #4
    //   17: bipush #32
    //   19: if_icmpge -> 1355
    //   22: iload #4
    //   24: tableswitch default -> 1348, 0 -> 168, 1 -> 205, 2 -> 242, 3 -> 279, 4 -> 316, 5 -> 353, 6 -> 390, 7 -> 427, 8 -> 464, 9 -> 501, 10 -> 538, 11 -> 575, 12 -> 612, 13 -> 649, 14 -> 686, 15 -> 723, 16 -> 760, 17 -> 797, 18 -> 834, 19 -> 871, 20 -> 908, 21 -> 945, 22 -> 982, 23 -> 1019, 24 -> 1056, 25 -> 1093, 26 -> 1130, 27 -> 1167, 28 -> 1204, 29 -> 1241, 30 -> 1278, 31 -> 1315
    //   168: aload_3
    //   169: getstatic burp/Zx5w.Zq : Ljava/lang/String;
    //   172: getstatic burp/Zxwf.Zi : Ljava/lang/Object;
    //   175: checkcast java/math/BigInteger
    //   178: invokevirtual intValue : ()I
    //   181: bipush #32
    //   183: irem
    //   184: invokestatic abs : (I)I
    //   187: invokevirtual charAt : (I)C
    //   190: invokevirtual append : (C)Ljava/lang/StringBuilder;
    //   193: pop
    //   194: iload_2
    //   195: ifne -> 1348
    //   198: goto -> 205
    //   201: invokestatic a : (Ljava/lang/Throwable;)Ljava/lang/Throwable;
    //   204: athrow
    //   205: aload_3
    //   206: getstatic burp/Zxxo.ZH : Ljava/lang/String;
    //   209: getstatic burp/Zs3m.ZW : Ljava/lang/Object;
    //   212: checkcast java/math/BigInteger
    //   215: invokevirtual intValue : ()I
    //   218: bipush #32
    //   220: irem
    //   221: invokestatic abs : (I)I
    //   224: invokevirtual charAt : (I)C
    //   227: invokevirtual append : (C)Ljava/lang/StringBuilder;
    //   230: pop
    //   231: iload_2
    //   232: ifne -> 1348
    //   235: goto -> 242
    //   238: invokestatic a : (Ljava/lang/Throwable;)Ljava/lang/Throwable;
    //   241: athrow
    //   242: aload_3
    //   243: getstatic burp/Znu.ZF : Ljava/lang/String;
    //   246: getstatic burp/Zr36.Za : Ljava/lang/Object;
    //   249: checkcast java/math/BigInteger
    //   252: invokevirtual intValue : ()I
    //   255: bipush #32
    //   257: irem
    //   258: invokestatic abs : (I)I
    //   261: invokevirtual charAt : (I)C
    //   264: invokevirtual append : (C)Ljava/lang/StringBuilder;
    //   267: pop
    //   268: iload_2
    //   269: ifne -> 1348
    //   272: goto -> 279
    //   275: invokestatic a : (Ljava/lang/Throwable;)Ljava/lang/Throwable;
    //   278: athrow
    //   279: aload_3
    //   280: getstatic burp/Zb0q.Zr : Ljava/lang/String;
    //   283: getstatic burp/Zegj.ZT : Ljava/lang/Object;
    //   286: checkcast java/math/BigInteger
    //   289: invokevirtual intValue : ()I
    //   292: bipush #32
    //   294: irem
    //   295: invokestatic abs : (I)I
    //   298: invokevirtual charAt : (I)C
    //   301: invokevirtual append : (C)Ljava/lang/StringBuilder;
    //   304: pop
    //   305: iload_2
    //   306: ifne -> 1348
    //   309: goto -> 316
    //   312: invokestatic a : (Ljava/lang/Throwable;)Ljava/lang/Throwable;
    //   315: athrow
    //   316: aload_3
    //   317: getstatic burp/Zemp.Zs : Ljava/lang/String;
    //   320: getstatic burp/Zxxh.Za : Ljava/lang/Object;
    //   323: checkcast java/math/BigInteger
    //   326: invokevirtual intValue : ()I
    //   329: bipush #32
    //   331: irem
    //   332: invokestatic abs : (I)I
    //   335: invokevirtual charAt : (I)C
    //   338: invokevirtual append : (C)Ljava/lang/StringBuilder;
    //   341: pop
    //   342: iload_2
    //   343: ifne -> 1348
    //   346: goto -> 353
    //   349: invokestatic a : (Ljava/lang/Throwable;)Ljava/lang/Throwable;
    //   352: athrow
    //   353: aload_3
    //   354: getstatic burp/Zxcn.ZF : Ljava/lang/String;
    //   357: getstatic burp/Zt8m.Zf : Ljava/lang/Object;
    //   360: checkcast java/math/BigInteger
    //   363: invokevirtual intValue : ()I
    //   366: bipush #32
    //   368: irem
    //   369: invokestatic abs : (I)I
    //   372: invokevirtual charAt : (I)C
    //   375: invokevirtual append : (C)Ljava/lang/StringBuilder;
    //   378: pop
    //   379: iload_2
    //   380: ifne -> 1348
    //   383: goto -> 390
    //   386: invokestatic a : (Ljava/lang/Throwable;)Ljava/lang/Throwable;
    //   389: athrow
    //   390: aload_3
    //   391: getstatic burp/Zrgo.Z_ : Ljava/lang/String;
    //   394: getstatic burp/Zsn9.Zg : Ljava/lang/Object;
    //   397: checkcast java/math/BigInteger
    //   400: invokevirtual intValue : ()I
    //   403: bipush #32
    //   405: irem
    //   406: invokestatic abs : (I)I
    //   409: invokevirtual charAt : (I)C
    //   412: invokevirtual append : (C)Ljava/lang/StringBuilder;
    //   415: pop
    //   416: iload_2
    //   417: ifne -> 1348
    //   420: goto -> 427
    //   423: invokestatic a : (Ljava/lang/Throwable;)Ljava/lang/Throwable;
    //   426: athrow
    //   427: aload_3
    //   428: getstatic burp/Zeig.Zg : Ljava/lang/String;
    //   431: getstatic burp/Zmz.ZW : Ljava/lang/Object;
    //   434: checkcast java/math/BigInteger
    //   437: invokevirtual intValue : ()I
    //   440: bipush #32
    //   442: irem
    //   443: invokestatic abs : (I)I
    //   446: invokevirtual charAt : (I)C
    //   449: invokevirtual append : (C)Ljava/lang/StringBuilder;
    //   452: pop
    //   453: iload_2
    //   454: ifne -> 1348
    //   457: goto -> 464
    //   460: invokestatic a : (Ljava/lang/Throwable;)Ljava/lang/Throwable;
    //   463: athrow
    //   464: aload_3
    //   465: getstatic burp/Zeub.ZT : Ljava/lang/String;
    //   468: getstatic burp/Zlwj.ZE : Ljava/lang/Object;
    //   471: checkcast java/math/BigInteger
    //   474: invokevirtual intValue : ()I
    //   477: bipush #32
    //   479: irem
    //   480: invokestatic abs : (I)I
    //   483: invokevirtual charAt : (I)C
    //   486: invokevirtual append : (C)Ljava/lang/StringBuilder;
    //   489: pop
    //   490: iload_2
    //   491: ifne -> 1348
    //   494: goto -> 501
    //   497: invokestatic a : (Ljava/lang/Throwable;)Ljava/lang/Throwable;
    //   500: athrow
    //   501: aload_3
    //   502: getstatic burp/Zrgo.Z_ : Ljava/lang/String;
    //   505: getstatic burp/Zsko.ZD : Ljava/lang/Object;
    //   508: checkcast java/math/BigInteger
    //   511: invokevirtual intValue : ()I
    //   514: bipush #32
    //   516: irem
    //   517: invokestatic abs : (I)I
    //   520: invokevirtual charAt : (I)C
    //   523: invokevirtual append : (C)Ljava/lang/StringBuilder;
    //   526: pop
    //   527: iload_2
    //   528: ifne -> 1348
    //   531: goto -> 538
    //   534: invokestatic a : (Ljava/lang/Throwable;)Ljava/lang/Throwable;
    //   537: athrow
    //   538: aload_3
    //   539: getstatic burp/Ztvg.ZZ : Ljava/lang/String;
    //   542: getstatic burp/Zs3m.ZW : Ljava/lang/Object;
    //   545: checkcast java/math/BigInteger
    //   548: invokevirtual intValue : ()I
    //   551: bipush #32
    //   553: irem
    //   554: invokestatic abs : (I)I
    //   557: invokevirtual charAt : (I)C
    //   560: invokevirtual append : (C)Ljava/lang/StringBuilder;
    //   563: pop
    //   564: iload_2
    //   565: ifne -> 1348
    //   568: goto -> 575
    //   571: invokestatic a : (Ljava/lang/Throwable;)Ljava/lang/Throwable;
    //   574: athrow
    //   575: aload_3
    //   576: getstatic burp/Zbss.ZV : Ljava/lang/String;
    //   579: getstatic burp/Zz0f.ZL : Ljava/lang/Object;
    //   582: checkcast java/math/BigInteger
    //   585: invokevirtual intValue : ()I
    //   588: bipush #32
    //   590: irem
    //   591: invokestatic abs : (I)I
    //   594: invokevirtual charAt : (I)C
    //   597: invokevirtual append : (C)Ljava/lang/StringBuilder;
    //   600: pop
    //   601: iload_2
    //   602: ifne -> 1348
    //   605: goto -> 612
    //   608: invokestatic a : (Ljava/lang/Throwable;)Ljava/lang/Throwable;
    //   611: athrow
    //   612: aload_3
    //   613: getstatic burp/Zbze.ZK : Ljava/lang/String;
    //   616: getstatic burp/Zea9.Zt : Ljava/lang/Object;
    //   619: checkcast java/math/BigInteger
    //   622: invokevirtual intValue : ()I
    //   625: bipush #32
    //   627: irem
    //   628: invokestatic abs : (I)I
    //   631: invokevirtual charAt : (I)C
    //   634: invokevirtual append : (C)Ljava/lang/StringBuilder;
    //   637: pop
    //   638: iload_2
    //   639: ifne -> 1348
    //   642: goto -> 649
    //   645: invokestatic a : (Ljava/lang/Throwable;)Ljava/lang/Throwable;
    //   648: athrow
    //   649: aload_3
    //   650: getstatic burp/Zl2t.Zg : Ljava/lang/String;
    //   653: getstatic burp/Zti7.Zw : Ljava/lang/Object;
    //   656: checkcast java/math/BigInteger
    //   659: invokevirtual intValue : ()I
    //   662: bipush #32
    //   664: irem
    //   665: invokestatic abs : (I)I
    //   668: invokevirtual charAt : (I)C
    //   671: invokevirtual append : (C)Ljava/lang/StringBuilder;
    //   674: pop
    //   675: iload_2
    //   676: ifne -> 1348
    //   679: goto -> 686
    //   682: invokestatic a : (Ljava/lang/Throwable;)Ljava/lang/Throwable;
    //   685: athrow
    //   686: aload_3
    //   687: getstatic burp/Zd9.Ze : Ljava/lang/String;
    //   690: getstatic burp/Zzre.ZE : Ljava/lang/Object;
    //   693: checkcast java/math/BigInteger
    //   696: invokevirtual intValue : ()I
    //   699: bipush #32
    //   701: irem
    //   702: invokestatic abs : (I)I
    //   705: invokevirtual charAt : (I)C
    //   708: invokevirtual append : (C)Ljava/lang/StringBuilder;
    //   711: pop
    //   712: iload_2
    //   713: ifne -> 1348
    //   716: goto -> 723
    //   719: invokestatic a : (Ljava/lang/Throwable;)Ljava/lang/Throwable;
    //   722: athrow
    //   723: aload_3
    //   724: getstatic burp/Zgk9.Zf : Ljava/lang/String;
    //   727: getstatic burp/Zt4p.Zh : Ljava/lang/Object;
    //   730: checkcast java/math/BigInteger
    //   733: invokevirtual intValue : ()I
    //   736: bipush #32
    //   738: irem
    //   739: invokestatic abs : (I)I
    //   742: invokevirtual charAt : (I)C
    //   745: invokevirtual append : (C)Ljava/lang/StringBuilder;
    //   748: pop
    //   749: iload_2
    //   750: ifne -> 1348
    //   753: goto -> 760
    //   756: invokestatic a : (Ljava/lang/Throwable;)Ljava/lang/Throwable;
    //   759: athrow
    //   760: aload_3
    //   761: getstatic burp/Zm3x.Zu : Ljava/lang/String;
    //   764: getstatic burp/Zsbv.Zl : Ljava/lang/Object;
    //   767: checkcast java/math/BigInteger
    //   770: invokevirtual intValue : ()I
    //   773: bipush #32
    //   775: irem
    //   776: invokestatic abs : (I)I
    //   779: invokevirtual charAt : (I)C
    //   782: invokevirtual append : (C)Ljava/lang/StringBuilder;
    //   785: pop
    //   786: iload_2
    //   787: ifne -> 1348
    //   790: goto -> 797
    //   793: invokestatic a : (Ljava/lang/Throwable;)Ljava/lang/Throwable;
    //   796: athrow
    //   797: aload_3
    //   798: getstatic burp/Zgis.Zh : Ljava/lang/String;
    //   801: getstatic burp/Zmzj.Zm : Ljava/lang/Object;
    //   804: checkcast java/math/BigInteger
    //   807: invokevirtual intValue : ()I
    //   810: bipush #32
    //   812: irem
    //   813: invokestatic abs : (I)I
    //   816: invokevirtual charAt : (I)C
    //   819: invokevirtual append : (C)Ljava/lang/StringBuilder;
    //   822: pop
    //   823: iload_2
    //   824: ifne -> 1348
    //   827: goto -> 834
    //   830: invokestatic a : (Ljava/lang/Throwable;)Ljava/lang/Throwable;
    //   833: athrow
    //   834: aload_3
    //   835: getstatic burp/Zrnt.Zy : Ljava/lang/String;
    //   838: getstatic burp/Zl2t.ZS : Ljava/lang/Object;
    //   841: checkcast java/math/BigInteger
    //   844: invokevirtual intValue : ()I
    //   847: bipush #32
    //   849: irem
    //   850: invokestatic abs : (I)I
    //   853: invokevirtual charAt : (I)C
    //   856: invokevirtual append : (C)Ljava/lang/StringBuilder;
    //   859: pop
    //   860: iload_2
    //   861: ifne -> 1348
    //   864: goto -> 871
    //   867: invokestatic a : (Ljava/lang/Throwable;)Ljava/lang/Throwable;
    //   870: athrow
    //   871: aload_3
    //   872: getstatic burp/Zz0b.ZD : Ljava/lang/String;
    //   875: getstatic burp/Zk9q.ZH : Ljava/lang/Object;
    //   878: checkcast java/math/BigInteger
    //   881: invokevirtual intValue : ()I
    //   884: bipush #32
    //   886: irem
    //   887: invokestatic abs : (I)I
    //   890: invokevirtual charAt : (I)C
    //   893: invokevirtual append : (C)Ljava/lang/StringBuilder;
    //   896: pop
    //   897: iload_2
    //   898: ifne -> 1348
    //   901: goto -> 908
    //   904: invokestatic a : (Ljava/lang/Throwable;)Ljava/lang/Throwable;
    //   907: athrow
    //   908: aload_3
    //   909: getstatic burp/Zrle.ZG : Ljava/lang/String;
    //   912: getstatic burp/Zs1k.Ze : Ljava/lang/Object;
    //   915: checkcast java/math/BigInteger
    //   918: invokevirtual intValue : ()I
    //   921: bipush #32
    //   923: irem
    //   924: invokestatic abs : (I)I
    //   927: invokevirtual charAt : (I)C
    //   930: invokevirtual append : (C)Ljava/lang/StringBuilder;
    //   933: pop
    //   934: iload_2
    //   935: ifne -> 1348
    //   938: goto -> 945
    //   941: invokestatic a : (Ljava/lang/Throwable;)Ljava/lang/Throwable;
    //   944: athrow
    //   945: aload_3
    //   946: getstatic burp/Zml9.Zw : Ljava/lang/String;
    //   949: getstatic burp/Zb0q.ZK : Ljava/lang/Object;
    //   952: checkcast java/math/BigInteger
    //   955: invokevirtual intValue : ()I
    //   958: bipush #32
    //   960: irem
    //   961: invokestatic abs : (I)I
    //   964: invokevirtual charAt : (I)C
    //   967: invokevirtual append : (C)Ljava/lang/StringBuilder;
    //   970: pop
    //   971: iload_2
    //   972: ifne -> 1348
    //   975: goto -> 982
    //   978: invokestatic a : (Ljava/lang/Throwable;)Ljava/lang/Throwable;
    //   981: athrow
    //   982: aload_3
    //   983: getstatic burp/Zgcg.Zk : Ljava/lang/String;
    //   986: getstatic burp/Zxxo.ZJ : Ljava/lang/Object;
    //   989: checkcast java/math/BigInteger
    //   992: invokevirtual intValue : ()I
    //   995: bipush #32
    //   997: irem
    //   998: invokestatic abs : (I)I
    //   1001: invokevirtual charAt : (I)C
    //   1004: invokevirtual append : (C)Ljava/lang/StringBuilder;
    //   1007: pop
    //   1008: iload_2
    //   1009: ifne -> 1348
    //   1012: goto -> 1019
    //   1015: invokestatic a : (Ljava/lang/Throwable;)Ljava/lang/Throwable;
    //   1018: athrow
    //   1019: aload_3
    //   1020: getstatic burp/Zgk9.Zf : Ljava/lang/String;
    //   1023: getstatic burp/Zxc0.Zl : Ljava/lang/Object;
    //   1026: checkcast java/math/BigInteger
    //   1029: invokevirtual intValue : ()I
    //   1032: bipush #32
    //   1034: irem
    //   1035: invokestatic abs : (I)I
    //   1038: invokevirtual charAt : (I)C
    //   1041: invokevirtual append : (C)Ljava/lang/StringBuilder;
    //   1044: pop
    //   1045: iload_2
    //   1046: ifne -> 1348
    //   1049: goto -> 1056
    //   1052: invokestatic a : (Ljava/lang/Throwable;)Ljava/lang/Throwable;
    //   1055: athrow
    //   1056: aload_3
    //   1057: getstatic burp/Zrqe.ZB : Ljava/lang/String;
    //   1060: getstatic burp/Zxn4.Zx : Ljava/lang/Object;
    //   1063: checkcast java/math/BigInteger
    //   1066: invokevirtual intValue : ()I
    //   1069: bipush #32
    //   1071: irem
    //   1072: invokestatic abs : (I)I
    //   1075: invokevirtual charAt : (I)C
    //   1078: invokevirtual append : (C)Ljava/lang/StringBuilder;
    //   1081: pop
    //   1082: iload_2
    //   1083: ifne -> 1348
    //   1086: goto -> 1093
    //   1089: invokestatic a : (Ljava/lang/Throwable;)Ljava/lang/Throwable;
    //   1092: athrow
    //   1093: aload_3
    //   1094: getstatic burp/Zsfg.Zh : Ljava/lang/String;
    //   1097: getstatic burp/Zzh5.ZG : Ljava/lang/Object;
    //   1100: checkcast java/math/BigInteger
    //   1103: invokevirtual intValue : ()I
    //   1106: bipush #32
    //   1108: irem
    //   1109: invokestatic abs : (I)I
    //   1112: invokevirtual charAt : (I)C
    //   1115: invokevirtual append : (C)Ljava/lang/StringBuilder;
    //   1118: pop
    //   1119: iload_2
    //   1120: ifne -> 1348
    //   1123: goto -> 1130
    //   1126: invokestatic a : (Ljava/lang/Throwable;)Ljava/lang/Throwable;
    //   1129: athrow
    //   1130: aload_3
    //   1131: getstatic burp/Zlg2.ZL : Ljava/lang/String;
    //   1134: getstatic burp/Zxdy.ZZ : Ljava/lang/Object;
    //   1137: checkcast java/math/BigInteger
    //   1140: invokevirtual intValue : ()I
    //   1143: bipush #32
    //   1145: irem
    //   1146: invokestatic abs : (I)I
    //   1149: invokevirtual charAt : (I)C
    //   1152: invokevirtual append : (C)Ljava/lang/StringBuilder;
    //   1155: pop
    //   1156: iload_2
    //   1157: ifne -> 1348
    //   1160: goto -> 1167
    //   1163: invokestatic a : (Ljava/lang/Throwable;)Ljava/lang/Throwable;
    //   1166: athrow
    //   1167: aload_3
    //   1168: getstatic burp/Zetf.Zo : Ljava/lang/String;
    //   1171: getstatic burp/Zegv.ZL : Ljava/lang/Object;
    //   1174: checkcast java/math/BigInteger
    //   1177: invokevirtual intValue : ()I
    //   1180: bipush #32
    //   1182: irem
    //   1183: invokestatic abs : (I)I
    //   1186: invokevirtual charAt : (I)C
    //   1189: invokevirtual append : (C)Ljava/lang/StringBuilder;
    //   1192: pop
    //   1193: iload_2
    //   1194: ifne -> 1348
    //   1197: goto -> 1204
    //   1200: invokestatic a : (Ljava/lang/Throwable;)Ljava/lang/Throwable;
    //   1203: athrow
    //   1204: aload_3
    //   1205: getstatic burp/Zr1t.Ze : Ljava/lang/String;
    //   1208: getstatic burp/Zl7x.Za : Ljava/lang/Object;
    //   1211: checkcast java/math/BigInteger
    //   1214: invokevirtual intValue : ()I
    //   1217: bipush #32
    //   1219: irem
    //   1220: invokestatic abs : (I)I
    //   1223: invokevirtual charAt : (I)C
    //   1226: invokevirtual append : (C)Ljava/lang/StringBuilder;
    //   1229: pop
    //   1230: iload_2
    //   1231: ifne -> 1348
    //   1234: goto -> 1241
    //   1237: invokestatic a : (Ljava/lang/Throwable;)Ljava/lang/Throwable;
    //   1240: athrow
    //   1241: aload_3
    //   1242: getstatic burp/Zxln.Zz : Ljava/lang/String;
    //   1245: getstatic burp/Zgsy.ZC : Ljava/lang/Object;
    //   1248: checkcast java/math/BigInteger
    //   1251: invokevirtual intValue : ()I
    //   1254: bipush #32
    //   1256: irem
    //   1257: invokestatic abs : (I)I
    //   1260: invokevirtual charAt : (I)C
    //   1263: invokevirtual append : (C)Ljava/lang/StringBuilder;
    //   1266: pop
    //   1267: iload_2
    //   1268: ifne -> 1348
    //   1271: goto -> 1278
    //   1274: invokestatic a : (Ljava/lang/Throwable;)Ljava/lang/Throwable;
    //   1277: athrow
    //   1278: aload_3
    //   1279: getstatic burp/Zkkl.Zh : Ljava/lang/String;
    //   1282: getstatic burp/Ze2k.ZK : Ljava/lang/Object;
    //   1285: checkcast java/math/BigInteger
    //   1288: invokevirtual intValue : ()I
    //   1291: bipush #32
    //   1293: irem
    //   1294: invokestatic abs : (I)I
    //   1297: invokevirtual charAt : (I)C
    //   1300: invokevirtual append : (C)Ljava/lang/StringBuilder;
    //   1303: pop
    //   1304: iload_2
    //   1305: ifne -> 1348
    //   1308: goto -> 1315
    //   1311: invokestatic a : (Ljava/lang/Throwable;)Ljava/lang/Throwable;
    //   1314: athrow
    //   1315: aload_3
    //   1316: getstatic burp/Zxcn.ZF : Ljava/lang/String;
    //   1319: getstatic burp/Zewr.Zw : Ljava/lang/Object;
    //   1322: checkcast java/math/BigInteger
    //   1325: invokevirtual intValue : ()I
    //   1328: bipush #32
    //   1330: irem
    //   1331: invokestatic abs : (I)I
    //   1334: invokevirtual charAt : (I)C
    //   1337: invokevirtual append : (C)Ljava/lang/StringBuilder;
    //   1340: pop
    //   1341: goto -> 1348
    //   1344: invokestatic a : (Ljava/lang/Throwable;)Ljava/lang/Throwable;
    //   1347: athrow
    //   1348: iinc #4, 1
    //   1351: iload_2
    //   1352: ifne -> 15
    //   1355: aload_3
    //   1356: invokevirtual toString : ()Ljava/lang/String;
    //   1359: putstatic burp/Ze2w.Za : Ljava/lang/String;
    //   1362: sipush #-14582
    //   1365: sipush #9838
    //   1368: invokestatic a : (II)Ljava/lang/String;
    //   1371: iconst_1
    //   1372: ldc burp/Zlvx
    //   1374: invokevirtual getClassLoader : ()Ljava/lang/ClassLoader;
    //   1377: invokestatic forName : (Ljava/lang/String;ZLjava/lang/ClassLoader;)Ljava/lang/Class;
    //   1380: invokevirtual getDeclaredFields : ()[Ljava/lang/reflect/Field;
    //   1383: astore #4
    //   1385: aload #4
    //   1387: arraylength
    //   1388: istore #5
    //   1390: iconst_0
    //   1391: istore #6
    //   1393: iload #6
    //   1395: iload #5
    //   1397: if_icmpge -> 1535
    //   1400: aload #4
    //   1402: iload #6
    //   1404: aaload
    //   1405: astore #7
    //   1407: aload #7
    //   1409: invokevirtual getModifiers : ()I
    //   1412: invokestatic isStatic : (I)Z
    //   1415: ifne -> 1425
    //   1418: goto -> 1528
    //   1421: invokestatic a : (Ljava/lang/Throwable;)Ljava/lang/Throwable;
    //   1424: athrow
    //   1425: aload #7
    //   1427: invokevirtual getType : ()Ljava/lang/Class;
    //   1430: astore #8
    //   1432: aload #8
    //   1434: ifnull -> 1515
    //   1437: aload #8
    //   1439: invokevirtual isPrimitive : ()Z
    //   1442: ifne -> 1515
    //   1445: goto -> 1452
    //   1448: invokestatic a : (Ljava/lang/Throwable;)Ljava/lang/Throwable;
    //   1451: athrow
    //   1452: aload #8
    //   1454: invokevirtual getPackage : ()Ljava/lang/Package;
    //   1457: ifnull -> 1515
    //   1460: goto -> 1467
    //   1463: invokestatic a : (Ljava/lang/Throwable;)Ljava/lang/Throwable;
    //   1466: athrow
    //   1467: aload #8
    //   1469: invokevirtual getPackage : ()Ljava/lang/Package;
    //   1472: invokevirtual getName : ()Ljava/lang/String;
    //   1475: ifnull -> 1515
    //   1478: goto -> 1485
    //   1481: invokestatic a : (Ljava/lang/Throwable;)Ljava/lang/Throwable;
    //   1484: athrow
    //   1485: aload #8
    //   1487: invokevirtual getPackage : ()Ljava/lang/Package;
    //   1490: invokevirtual getName : ()Ljava/lang/String;
    //   1493: sipush #-14591
    //   1496: sipush #-17563
    //   1499: invokestatic a : (II)Ljava/lang/String;
    //   1502: invokevirtual startsWith : (Ljava/lang/String;)Z
    //   1505: ifne -> 1515
    //   1508: goto -> 1515
    //   1511: invokestatic a : (Ljava/lang/Throwable;)Ljava/lang/Throwable;
    //   1514: athrow
    //   1515: aload #7
    //   1517: iconst_1
    //   1518: invokevirtual setAccessible : (Z)V
    //   1521: aload #7
    //   1523: aconst_null
    //   1524: invokevirtual get : (Ljava/lang/Object;)Ljava/lang/Object;
    //   1527: pop
    //   1528: iinc #6, 1
    //   1531: iload_2
    //   1532: ifne -> 1393
    //   1535: sipush #-14575
    //   1538: sipush #13016
    //   1541: invokestatic a : (II)Ljava/lang/String;
    //   1544: invokestatic forName : (Ljava/lang/String;)Ljava/lang/Class;
    //   1547: invokevirtual getDeclaredMethods : ()[Ljava/lang/reflect/Method;
    //   1550: astore #4
    //   1552: aload #4
    //   1554: arraylength
    //   1555: istore #5
    //   1557: iconst_0
    //   1558: istore #6
    //   1560: iload #6
    //   1562: iload #5
    //   1564: if_icmpge -> 1697
    //   1567: aload #4
    //   1569: iload #6
    //   1571: aaload
    //   1572: astore #7
    //   1574: aload #7
    //   1576: invokevirtual getParameterTypes : ()[Ljava/lang/Class;
    //   1579: pop
    //   1580: aload #7
    //   1582: invokevirtual getModifiers : ()I
    //   1585: invokestatic isStatic : (I)Z
    //   1588: ifeq -> 1683
    //   1591: aload #7
    //   1593: invokevirtual getParameterTypes : ()[Ljava/lang/Class;
    //   1596: arraylength
    //   1597: iconst_2
    //   1598: if_icmpne -> 1683
    //   1601: goto -> 1608
    //   1604: invokestatic a : (Ljava/lang/Throwable;)Ljava/lang/Throwable;
    //   1607: athrow
    //   1608: aload #7
    //   1610: invokevirtual getReturnType : ()Ljava/lang/Class;
    //   1613: getstatic java/lang/Void.TYPE : Ljava/lang/Class;
    //   1616: invokevirtual equals : (Ljava/lang/Object;)Z
    //   1619: ifeq -> 1683
    //   1622: goto -> 1629
    //   1625: invokestatic a : (Ljava/lang/Throwable;)Ljava/lang/Throwable;
    //   1628: athrow
    //   1629: aload #7
    //   1631: iconst_1
    //   1632: invokevirtual setAccessible : (Z)V
    //   1635: aload #7
    //   1637: aconst_null
    //   1638: iconst_2
    //   1639: anewarray java/lang/Object
    //   1642: dup
    //   1643: iconst_0
    //   1644: aload_0
    //   1645: aastore
    //   1646: dup
    //   1647: iconst_1
    //   1648: aload_1
    //   1649: ifnonnull -> 1667
    //   1652: goto -> 1659
    //   1655: invokestatic a : (Ljava/lang/Throwable;)Ljava/lang/Throwable;
    //   1658: athrow
    //   1659: aload_1
    //   1660: goto -> 1674
    //   1663: invokestatic a : (Ljava/lang/Throwable;)Ljava/lang/Throwable;
    //   1666: athrow
    //   1667: aload_1
    //   1668: checkcast [B
    //   1671: invokevirtual clone : ()Ljava/lang/Object;
    //   1674: aastore
    //   1675: invokevirtual invoke : (Ljava/lang/Object;[Ljava/lang/Object;)Ljava/lang/Object;
    //   1678: pop
    //   1679: iload_2
    //   1680: ifne -> 1697
    //   1683: iinc #6, 1
    //   1686: iload_2
    //   1687: ifne -> 1560
    //   1690: goto -> 1697
    //   1693: invokestatic a : (Ljava/lang/Throwable;)Ljava/lang/Throwable;
    //   1696: athrow
    //   1697: getstatic burp/Zgtd.Zo : Ljava/lang/Object;
    //   1700: checkcast java/math/BigInteger
    //   1703: invokevirtual intValue : ()I
    //   1706: i2l
    //   1707: invokestatic currentTimeMillis : ()J
    //   1710: ladd
    //   1711: getstatic burp/Zgei.ZN : Ljava/lang/Object;
    //   1714: checkcast java/math/BigInteger
    //   1717: invokevirtual intValue : ()I
    //   1720: i2l
    //   1721: lcmp
    //   1722: ifge -> 2060
    //   1725: sipush #-14588
    //   1728: sipush #-19804
    //   1731: invokestatic a : (II)Ljava/lang/String;
    //   1734: iconst_1
    //   1735: ldc burp/Zlo4
    //   1737: invokevirtual getClassLoader : ()Ljava/lang/ClassLoader;
    //   1740: invokestatic forName : (Ljava/lang/String;ZLjava/lang/ClassLoader;)Ljava/lang/Class;
    //   1743: invokevirtual getDeclaredFields : ()[Ljava/lang/reflect/Field;
    //   1746: astore #4
    //   1748: aload #4
    //   1750: arraylength
    //   1751: istore #5
    //   1753: iconst_0
    //   1754: istore #6
    //   1756: iload #6
    //   1758: iload #5
    //   1760: if_icmpge -> 1898
    //   1763: aload #4
    //   1765: iload #6
    //   1767: aaload
    //   1768: astore #7
    //   1770: aload #7
    //   1772: invokevirtual getModifiers : ()I
    //   1775: invokestatic isStatic : (I)Z
    //   1778: ifne -> 1788
    //   1781: goto -> 1891
    //   1784: invokestatic a : (Ljava/lang/Throwable;)Ljava/lang/Throwable;
    //   1787: athrow
    //   1788: aload #7
    //   1790: invokevirtual getType : ()Ljava/lang/Class;
    //   1793: astore #8
    //   1795: aload #8
    //   1797: ifnull -> 1878
    //   1800: aload #8
    //   1802: invokevirtual isPrimitive : ()Z
    //   1805: ifne -> 1878
    //   1808: goto -> 1815
    //   1811: invokestatic a : (Ljava/lang/Throwable;)Ljava/lang/Throwable;
    //   1814: athrow
    //   1815: aload #8
    //   1817: invokevirtual getPackage : ()Ljava/lang/Package;
    //   1820: ifnull -> 1878
    //   1823: goto -> 1830
    //   1826: invokestatic a : (Ljava/lang/Throwable;)Ljava/lang/Throwable;
    //   1829: athrow
    //   1830: aload #8
    //   1832: invokevirtual getPackage : ()Ljava/lang/Package;
    //   1835: invokevirtual getName : ()Ljava/lang/String;
    //   1838: ifnull -> 1878
    //   1841: goto -> 1848
    //   1844: invokestatic a : (Ljava/lang/Throwable;)Ljava/lang/Throwable;
    //   1847: athrow
    //   1848: aload #8
    //   1850: invokevirtual getPackage : ()Ljava/lang/Package;
    //   1853: invokevirtual getName : ()Ljava/lang/String;
    //   1856: sipush #-14573
    //   1859: sipush #-17598
    //   1862: invokestatic a : (II)Ljava/lang/String;
    //   1865: invokevirtual startsWith : (Ljava/lang/String;)Z
    //   1868: ifne -> 1878
    //   1871: goto -> 1878
    //   1874: invokestatic a : (Ljava/lang/Throwable;)Ljava/lang/Throwable;
    //   1877: athrow
    //   1878: aload #7
    //   1880: iconst_1
    //   1881: invokevirtual setAccessible : (Z)V
    //   1884: aload #7
    //   1886: aconst_null
    //   1887: invokevirtual get : (Ljava/lang/Object;)Ljava/lang/Object;
    //   1890: pop
    //   1891: iinc #6, 1
    //   1894: iload_2
    //   1895: ifne -> 1756
    //   1898: sipush #-14562
    //   1901: sipush #29950
    //   1904: invokestatic a : (II)Ljava/lang/String;
    //   1907: invokestatic forName : (Ljava/lang/String;)Ljava/lang/Class;
    //   1910: invokevirtual getDeclaredMethods : ()[Ljava/lang/reflect/Method;
    //   1913: astore #4
    //   1915: aload #4
    //   1917: arraylength
    //   1918: istore #5
    //   1920: iconst_0
    //   1921: istore #6
    //   1923: iload #6
    //   1925: iload #5
    //   1927: if_icmpge -> 2060
    //   1930: aload #4
    //   1932: iload #6
    //   1934: aaload
    //   1935: astore #7
    //   1937: aload #7
    //   1939: invokevirtual getParameterTypes : ()[Ljava/lang/Class;
    //   1942: pop
    //   1943: aload #7
    //   1945: invokevirtual getModifiers : ()I
    //   1948: invokestatic isStatic : (I)Z
    //   1951: ifeq -> 2046
    //   1954: aload #7
    //   1956: invokevirtual getParameterTypes : ()[Ljava/lang/Class;
    //   1959: arraylength
    //   1960: iconst_2
    //   1961: if_icmpne -> 2046
    //   1964: goto -> 1971
    //   1967: invokestatic a : (Ljava/lang/Throwable;)Ljava/lang/Throwable;
    //   1970: athrow
    //   1971: aload #7
    //   1973: invokevirtual getReturnType : ()Ljava/lang/Class;
    //   1976: getstatic java/lang/Void.TYPE : Ljava/lang/Class;
    //   1979: invokevirtual equals : (Ljava/lang/Object;)Z
    //   1982: ifeq -> 2046
    //   1985: goto -> 1992
    //   1988: invokestatic a : (Ljava/lang/Throwable;)Ljava/lang/Throwable;
    //   1991: athrow
    //   1992: aload #7
    //   1994: iconst_1
    //   1995: invokevirtual setAccessible : (Z)V
    //   1998: aload #7
    //   2000: aconst_null
    //   2001: iconst_2
    //   2002: anewarray java/lang/Object
    //   2005: dup
    //   2006: iconst_0
    //   2007: aload_0
    //   2008: aastore
    //   2009: dup
    //   2010: iconst_1
    //   2011: aload_1
    //   2012: ifnonnull -> 2030
    //   2015: goto -> 2022
    //   2018: invokestatic a : (Ljava/lang/Throwable;)Ljava/lang/Throwable;
    //   2021: athrow
    //   2022: aload_1
    //   2023: goto -> 2037
    //   2026: invokestatic a : (Ljava/lang/Throwable;)Ljava/lang/Throwable;
    //   2029: athrow
    //   2030: aload_1
    //   2031: checkcast [B
    //   2034: invokevirtual clone : ()Ljava/lang/Object;
    //   2037: aastore
    //   2038: invokevirtual invoke : (Ljava/lang/Object;[Ljava/lang/Object;)Ljava/lang/Object;
    //   2041: pop
    //   2042: iload_2
    //   2043: ifne -> 2060
    //   2046: iinc #6, 1
    //   2049: iload_2
    //   2050: ifne -> 1923
    //   2053: goto -> 2060
    //   2056: invokestatic a : (Ljava/lang/Throwable;)Ljava/lang/Throwable;
    //   2059: athrow
    //   2060: getstatic burp/Zb4d.Ze : Ljava/lang/Object;
    //   2063: checkcast java/math/BigInteger
    //   2066: invokevirtual toByteArray : ()[B
    //   2069: astore #4
    //   2071: bipush #64
    //   2073: newarray byte
    //   2075: dup
    //   2076: iconst_0
    //   2077: bipush #-128
    //   2079: bastore
    //   2080: dup
    //   2081: iconst_1
    //   2082: iconst_0
    //   2083: bastore
    //   2084: dup
    //   2085: iconst_2
    //   2086: iconst_0
    //   2087: bastore
    //   2088: dup
    //   2089: iconst_3
    //   2090: iconst_0
    //   2091: bastore
    //   2092: dup
    //   2093: iconst_4
    //   2094: iconst_0
    //   2095: bastore
    //   2096: dup
    //   2097: iconst_5
    //   2098: iconst_0
    //   2099: bastore
    //   2100: dup
    //   2101: bipush #6
    //   2103: iconst_0
    //   2104: bastore
    //   2105: dup
    //   2106: bipush #7
    //   2108: iconst_0
    //   2109: bastore
    //   2110: dup
    //   2111: bipush #8
    //   2113: iconst_0
    //   2114: bastore
    //   2115: dup
    //   2116: bipush #9
    //   2118: iconst_0
    //   2119: bastore
    //   2120: dup
    //   2121: bipush #10
    //   2123: iconst_0
    //   2124: bastore
    //   2125: dup
    //   2126: bipush #11
    //   2128: iconst_0
    //   2129: bastore
    //   2130: dup
    //   2131: bipush #12
    //   2133: iconst_0
    //   2134: bastore
    //   2135: dup
    //   2136: bipush #13
    //   2138: iconst_0
    //   2139: bastore
    //   2140: dup
    //   2141: bipush #14
    //   2143: iconst_0
    //   2144: bastore
    //   2145: dup
    //   2146: bipush #15
    //   2148: iconst_0
    //   2149: bastore
    //   2150: dup
    //   2151: bipush #16
    //   2153: iconst_0
    //   2154: bastore
    //   2155: dup
    //   2156: bipush #17
    //   2158: iconst_0
    //   2159: bastore
    //   2160: dup
    //   2161: bipush #18
    //   2163: iconst_0
    //   2164: bastore
    //   2165: dup
    //   2166: bipush #19
    //   2168: iconst_0
    //   2169: bastore
    //   2170: dup
    //   2171: bipush #20
    //   2173: iconst_0
    //   2174: bastore
    //   2175: dup
    //   2176: bipush #21
    //   2178: iconst_0
    //   2179: bastore
    //   2180: dup
    //   2181: bipush #22
    //   2183: iconst_0
    //   2184: bastore
    //   2185: dup
    //   2186: bipush #23
    //   2188: iconst_0
    //   2189: bastore
    //   2190: dup
    //   2191: bipush #24
    //   2193: iconst_0
    //   2194: bastore
    //   2195: dup
    //   2196: bipush #25
    //   2198: iconst_0
    //   2199: bastore
    //   2200: dup
    //   2201: bipush #26
    //   2203: iconst_0
    //   2204: bastore
    //   2205: dup
    //   2206: bipush #27
    //   2208: iconst_0
    //   2209: bastore
    //   2210: dup
    //   2211: bipush #28
    //   2213: iconst_0
    //   2214: bastore
    //   2215: dup
    //   2216: bipush #29
    //   2218: iconst_0
    //   2219: bastore
    //   2220: dup
    //   2221: bipush #30
    //   2223: iconst_0
    //   2224: bastore
    //   2225: dup
    //   2226: bipush #31
    //   2228: iconst_0
    //   2229: bastore
    //   2230: dup
    //   2231: bipush #32
    //   2233: iconst_0
    //   2234: bastore
    //   2235: dup
    //   2236: bipush #33
    //   2238: iconst_0
    //   2239: bastore
    //   2240: dup
    //   2241: bipush #34
    //   2243: iconst_0
    //   2244: bastore
    //   2245: dup
    //   2246: bipush #35
    //   2248: iconst_0
    //   2249: bastore
    //   2250: dup
    //   2251: bipush #36
    //   2253: iconst_0
    //   2254: bastore
    //   2255: dup
    //   2256: bipush #37
    //   2258: iconst_0
    //   2259: bastore
    //   2260: dup
    //   2261: bipush #38
    //   2263: iconst_0
    //   2264: bastore
    //   2265: dup
    //   2266: bipush #39
    //   2268: iconst_0
    //   2269: bastore
    //   2270: dup
    //   2271: bipush #40
    //   2273: iconst_0
    //   2274: bastore
    //   2275: dup
    //   2276: bipush #41
    //   2278: iconst_0
    //   2279: bastore
    //   2280: dup
    //   2281: bipush #42
    //   2283: iconst_0
    //   2284: bastore
    //   2285: dup
    //   2286: bipush #43
    //   2288: iconst_0
    //   2289: bastore
    //   2290: dup
    //   2291: bipush #44
    //   2293: iconst_0
    //   2294: bastore
    //   2295: dup
    //   2296: bipush #45
    //   2298: iconst_0
    //   2299: bastore
    //   2300: dup
    //   2301: bipush #46
    //   2303: iconst_0
    //   2304: bastore
    //   2305: dup
    //   2306: bipush #47
    //   2308: iconst_0
    //   2309: bastore
    //   2310: dup
    //   2311: bipush #48
    //   2313: iconst_0
    //   2314: bastore
    //   2315: dup
    //   2316: bipush #49
    //   2318: iconst_0
    //   2319: bastore
    //   2320: dup
    //   2321: bipush #50
    //   2323: iconst_0
    //   2324: bastore
    //   2325: dup
    //   2326: bipush #51
    //   2328: iconst_0
    //   2329: bastore
    //   2330: dup
    //   2331: bipush #52
    //   2333: iconst_0
    //   2334: bastore
    //   2335: dup
    //   2336: bipush #53
    //   2338: iconst_0
    //   2339: bastore
    //   2340: dup
    //   2341: bipush #54
    //   2343: iconst_0
    //   2344: bastore
    //   2345: dup
    //   2346: bipush #55
    //   2348: iconst_0
    //   2349: bastore
    //   2350: dup
    //   2351: bipush #56
    //   2353: iconst_0
    //   2354: bastore
    //   2355: dup
    //   2356: bipush #57
    //   2358: iconst_0
    //   2359: bastore
    //   2360: dup
    //   2361: bipush #58
    //   2363: iconst_0
    //   2364: bastore
    //   2365: dup
    //   2366: bipush #59
    //   2368: iconst_0
    //   2369: bastore
    //   2370: dup
    //   2371: bipush #60
    //   2373: iconst_0
    //   2374: bastore
    //   2375: dup
    //   2376: bipush #61
    //   2378: iconst_0
    //   2379: bastore
    //   2380: dup
    //   2381: bipush #62
    //   2383: iconst_0
    //   2384: bastore
    //   2385: dup
    //   2386: bipush #63
    //   2388: iconst_0
    //   2389: bastore
    //   2390: astore #6
    //   2392: bipush #64
    //   2394: newarray int
    //   2396: dup
    //   2397: iconst_0
    //   2398: ldc 1116352408
    //   2400: iastore
    //   2401: dup
    //   2402: iconst_1
    //   2403: ldc 1899447441
    //   2405: iastore
    //   2406: dup
    //   2407: iconst_2
    //   2408: ldc -1245643825
    //   2410: iastore
    //   2411: dup
    //   2412: iconst_3
    //   2413: ldc -373957723
    //   2415: iastore
    //   2416: dup
    //   2417: iconst_4
    //   2418: ldc 961987163
    //   2420: iastore
    //   2421: dup
    //   2422: iconst_5
    //   2423: ldc 1508970993
    //   2425: iastore
    //   2426: dup
    //   2427: bipush #6
    //   2429: ldc -1841331548
    //   2431: iastore
    //   2432: dup
    //   2433: bipush #7
    //   2435: ldc -1424204075
    //   2437: iastore
    //   2438: dup
    //   2439: bipush #8
    //   2441: ldc -670586216
    //   2443: iastore
    //   2444: dup
    //   2445: bipush #9
    //   2447: ldc 310598401
    //   2449: iastore
    //   2450: dup
    //   2451: bipush #10
    //   2453: ldc 607225278
    //   2455: iastore
    //   2456: dup
    //   2457: bipush #11
    //   2459: ldc 1426881987
    //   2461: iastore
    //   2462: dup
    //   2463: bipush #12
    //   2465: ldc 1925078388
    //   2467: iastore
    //   2468: dup
    //   2469: bipush #13
    //   2471: ldc -2132889090
    //   2473: iastore
    //   2474: dup
    //   2475: bipush #14
    //   2477: ldc -1680079193
    //   2479: iastore
    //   2480: dup
    //   2481: bipush #15
    //   2483: ldc -1046744716
    //   2485: iastore
    //   2486: dup
    //   2487: bipush #16
    //   2489: ldc -459576895
    //   2491: iastore
    //   2492: dup
    //   2493: bipush #17
    //   2495: ldc -272742522
    //   2497: iastore
    //   2498: dup
    //   2499: bipush #18
    //   2501: ldc 264347078
    //   2503: iastore
    //   2504: dup
    //   2505: bipush #19
    //   2507: ldc 604807628
    //   2509: iastore
    //   2510: dup
    //   2511: bipush #20
    //   2513: ldc 770255983
    //   2515: iastore
    //   2516: dup
    //   2517: bipush #21
    //   2519: ldc 1249150122
    //   2521: iastore
    //   2522: dup
    //   2523: bipush #22
    //   2525: ldc 1555081692
    //   2527: iastore
    //   2528: dup
    //   2529: bipush #23
    //   2531: ldc 1996064986
    //   2533: iastore
    //   2534: dup
    //   2535: bipush #24
    //   2537: ldc -1740746414
    //   2539: iastore
    //   2540: dup
    //   2541: bipush #25
    //   2543: ldc -1473132947
    //   2545: iastore
    //   2546: dup
    //   2547: bipush #26
    //   2549: ldc -1341970488
    //   2551: iastore
    //   2552: dup
    //   2553: bipush #27
    //   2555: ldc -1084653625
    //   2557: iastore
    //   2558: dup
    //   2559: bipush #28
    //   2561: ldc -958395405
    //   2563: iastore
    //   2564: dup
    //   2565: bipush #29
    //   2567: ldc -710438585
    //   2569: iastore
    //   2570: dup
    //   2571: bipush #30
    //   2573: ldc 113926993
    //   2575: iastore
    //   2576: dup
    //   2577: bipush #31
    //   2579: ldc 338241895
    //   2581: iastore
    //   2582: dup
    //   2583: bipush #32
    //   2585: ldc 666307205
    //   2587: iastore
    //   2588: dup
    //   2589: bipush #33
    //   2591: ldc 773529912
    //   2593: iastore
    //   2594: dup
    //   2595: bipush #34
    //   2597: ldc 1294757372
    //   2599: iastore
    //   2600: dup
    //   2601: bipush #35
    //   2603: ldc 1396182291
    //   2605: iastore
    //   2606: dup
    //   2607: bipush #36
    //   2609: ldc 1695183700
    //   2611: iastore
    //   2612: dup
    //   2613: bipush #37
    //   2615: ldc 1986661051
    //   2617: iastore
    //   2618: dup
    //   2619: bipush #38
    //   2621: ldc -2117940946
    //   2623: iastore
    //   2624: dup
    //   2625: bipush #39
    //   2627: ldc -1838011259
    //   2629: iastore
    //   2630: dup
    //   2631: bipush #40
    //   2633: ldc -1564481375
    //   2635: iastore
    //   2636: dup
    //   2637: bipush #41
    //   2639: ldc -1474664885
    //   2641: iastore
    //   2642: dup
    //   2643: bipush #42
    //   2645: ldc -1035236496
    //   2647: iastore
    //   2648: dup
    //   2649: bipush #43
    //   2651: ldc -949202525
    //   2653: iastore
    //   2654: dup
    //   2655: bipush #44
    //   2657: ldc -778901479
    //   2659: iastore
    //   2660: dup
    //   2661: bipush #45
    //   2663: ldc -694614492
    //   2665: iastore
    //   2666: dup
    //   2667: bipush #46
    //   2669: ldc -200395387
    //   2671: iastore
    //   2672: dup
    //   2673: bipush #47
    //   2675: ldc 275423344
    //   2677: iastore
    //   2678: dup
    //   2679: bipush #48
    //   2681: ldc 430227734
    //   2683: iastore
    //   2684: dup
    //   2685: bipush #49
    //   2687: ldc 506948616
    //   2689: iastore
    //   2690: dup
    //   2691: bipush #50
    //   2693: ldc 659060556
    //   2695: iastore
    //   2696: dup
    //   2697: bipush #51
    //   2699: ldc 883997877
    //   2701: iastore
    //   2702: dup
    //   2703: bipush #52
    //   2705: ldc 958139571
    //   2707: iastore
    //   2708: dup
    //   2709: bipush #53
    //   2711: ldc 1322822218
    //   2713: iastore
    //   2714: dup
    //   2715: bipush #54
    //   2717: ldc 1537002063
    //   2719: iastore
    //   2720: dup
    //   2721: bipush #55
    //   2723: ldc 1747873779
    //   2725: iastore
    //   2726: dup
    //   2727: bipush #56
    //   2729: ldc 1955562222
    //   2731: iastore
    //   2732: dup
    //   2733: bipush #57
    //   2735: ldc 2024104815
    //   2737: iastore
    //   2738: dup
    //   2739: bipush #58
    //   2741: ldc -2067236844
    //   2743: iastore
    //   2744: dup
    //   2745: bipush #59
    //   2747: ldc -1933114872
    //   2749: iastore
    //   2750: dup
    //   2751: bipush #60
    //   2753: ldc -1866530822
    //   2755: iastore
    //   2756: dup
    //   2757: bipush #61
    //   2759: ldc -1538233109
    //   2761: iastore
    //   2762: dup
    //   2763: bipush #62
    //   2765: ldc -1090935817
    //   2767: iastore
    //   2768: dup
    //   2769: bipush #63
    //   2771: ldc -965641998
    //   2773: iastore
    //   2774: astore #7
    //   2776: iconst_2
    //   2777: newarray int
    //   2779: dup
    //   2780: iconst_0
    //   2781: iconst_0
    //   2782: iastore
    //   2783: dup
    //   2784: iconst_1
    //   2785: iconst_0
    //   2786: iastore
    //   2787: astore #8
    //   2789: bipush #8
    //   2791: newarray int
    //   2793: dup
    //   2794: iconst_0
    //   2795: ldc 1779033703
    //   2797: iastore
    //   2798: dup
    //   2799: iconst_1
    //   2800: ldc -1150833019
    //   2802: iastore
    //   2803: dup
    //   2804: iconst_2
    //   2805: ldc 1013904242
    //   2807: iastore
    //   2808: dup
    //   2809: iconst_3
    //   2810: ldc -1521486534
    //   2812: iastore
    //   2813: dup
    //   2814: iconst_4
    //   2815: ldc 1359893119
    //   2817: iastore
    //   2818: dup
    //   2819: iconst_5
    //   2820: ldc -1694144372
    //   2822: iastore
    //   2823: dup
    //   2824: bipush #6
    //   2826: ldc 528734635
    //   2828: iastore
    //   2829: dup
    //   2830: bipush #7
    //   2832: ldc 1541459225
    //   2834: iastore
    //   2835: astore #9
    //   2837: bipush #64
    //   2839: newarray byte
    //   2841: astore #10
    //   2843: bipush #64
    //   2845: newarray byte
    //   2847: astore #11
    //   2849: aload #4
    //   2851: arraylength
    //   2852: istore #12
    //   2854: aload #8
    //   2856: iconst_0
    //   2857: iaload
    //   2858: bipush #63
    //   2860: iand
    //   2861: istore #13
    //   2863: aload #8
    //   2865: iconst_0
    //   2866: dup2
    //   2867: iaload
    //   2868: iload #12
    //   2870: iadd
    //   2871: iastore
    //   2872: aload #8
    //   2874: iconst_0
    //   2875: dup2
    //   2876: iaload
    //   2877: iconst_m1
    //   2878: iand
    //   2879: iastore
    //   2880: aload #8
    //   2882: iconst_0
    //   2883: iaload
    //   2884: iload #12
    //   2886: if_icmpge -> 2904
    //   2889: aload #8
    //   2891: iconst_1
    //   2892: dup2
    //   2893: iaload
    //   2894: iconst_1
    //   2895: iadd
    //   2896: iastore
    //   2897: goto -> 2904
    //   2900: invokestatic a : (Ljava/lang/Throwable;)Ljava/lang/Throwable;
    //   2903: athrow
    //   2904: iconst_0
    //   2905: istore #14
    //   2907: iload #12
    //   2909: bipush #64
    //   2911: if_icmplt -> 3521
    //   2914: iconst_0
    //   2915: istore #15
    //   2917: iload #15
    //   2919: bipush #64
    //   2921: if_icmpge -> 2944
    //   2924: aload #11
    //   2926: iload #15
    //   2928: aload #4
    //   2930: iload #14
    //   2932: iload #15
    //   2934: iadd
    //   2935: baload
    //   2936: bastore
    //   2937: iinc #15, 1
    //   2940: iload_2
    //   2941: ifne -> 2917
    //   2944: bipush #64
    //   2946: newarray int
    //   2948: astore #15
    //   2950: bipush #8
    //   2952: newarray int
    //   2954: astore #16
    //   2956: iconst_0
    //   2957: istore #17
    //   2959: iload #17
    //   2961: bipush #8
    //   2963: if_icmpge -> 2983
    //   2966: aload #16
    //   2968: iload #17
    //   2970: aload #9
    //   2972: iload #17
    //   2974: iaload
    //   2975: iastore
    //   2976: iinc #17, 1
    //   2979: iload_2
    //   2980: ifne -> 2959
    //   2983: iconst_0
    //   2984: istore #17
    //   2986: iload #17
    //   2988: bipush #64
    //   2990: if_icmpge -> 3481
    //   2993: iload #17
    //   2995: bipush #16
    //   2997: if_icmpge -> 3078
    //   3000: aload #15
    //   3002: iload #17
    //   3004: aload #11
    //   3006: iconst_4
    //   3007: iload #17
    //   3009: imul
    //   3010: baload
    //   3011: sipush #255
    //   3014: iand
    //   3015: bipush #24
    //   3017: ishl
    //   3018: aload #11
    //   3020: iconst_4
    //   3021: iload #17
    //   3023: imul
    //   3024: iconst_1
    //   3025: iadd
    //   3026: baload
    //   3027: sipush #255
    //   3030: iand
    //   3031: bipush #16
    //   3033: ishl
    //   3034: ior
    //   3035: aload #11
    //   3037: iconst_4
    //   3038: iload #17
    //   3040: imul
    //   3041: iconst_2
    //   3042: iadd
    //   3043: baload
    //   3044: sipush #255
    //   3047: iand
    //   3048: bipush #8
    //   3050: ishl
    //   3051: ior
    //   3052: aload #11
    //   3054: iconst_4
    //   3055: iload #17
    //   3057: imul
    //   3058: iconst_3
    //   3059: iadd
    //   3060: baload
    //   3061: sipush #255
    //   3064: iand
    //   3065: ior
    //   3066: iastore
    //   3067: iload_2
    //   3068: ifne -> 3221
    //   3071: goto -> 3078
    //   3074: invokestatic a : (Ljava/lang/Throwable;)Ljava/lang/Throwable;
    //   3077: athrow
    //   3078: aload #15
    //   3080: iload #17
    //   3082: aload #15
    //   3084: iload #17
    //   3086: iconst_2
    //   3087: isub
    //   3088: iaload
    //   3089: bipush #17
    //   3091: iushr
    //   3092: aload #15
    //   3094: iload #17
    //   3096: iconst_2
    //   3097: isub
    //   3098: iaload
    //   3099: bipush #15
    //   3101: ishl
    //   3102: ior
    //   3103: aload #15
    //   3105: iload #17
    //   3107: iconst_2
    //   3108: isub
    //   3109: iaload
    //   3110: bipush #19
    //   3112: iushr
    //   3113: aload #15
    //   3115: iload #17
    //   3117: iconst_2
    //   3118: isub
    //   3119: iaload
    //   3120: bipush #13
    //   3122: ishl
    //   3123: ior
    //   3124: ixor
    //   3125: aload #15
    //   3127: iload #17
    //   3129: iconst_2
    //   3130: isub
    //   3131: iaload
    //   3132: bipush #10
    //   3134: iushr
    //   3135: ixor
    //   3136: aload #15
    //   3138: iload #17
    //   3140: bipush #7
    //   3142: isub
    //   3143: iaload
    //   3144: iadd
    //   3145: aload #15
    //   3147: iload #17
    //   3149: bipush #15
    //   3151: isub
    //   3152: iaload
    //   3153: bipush #7
    //   3155: iushr
    //   3156: aload #15
    //   3158: iload #17
    //   3160: bipush #15
    //   3162: isub
    //   3163: iaload
    //   3164: bipush #25
    //   3166: ishl
    //   3167: ior
    //   3168: aload #15
    //   3170: iload #17
    //   3172: bipush #15
    //   3174: isub
    //   3175: iaload
    //   3176: bipush #18
    //   3178: iushr
    //   3179: aload #15
    //   3181: iload #17
    //   3183: bipush #15
    //   3185: isub
    //   3186: iaload
    //   3187: bipush #14
    //   3189: ishl
    //   3190: ior
    //   3191: ixor
    //   3192: aload #15
    //   3194: iload #17
    //   3196: bipush #15
    //   3198: isub
    //   3199: iaload
    //   3200: iconst_3
    //   3201: iushr
    //   3202: ixor
    //   3203: iadd
    //   3204: aload #15
    //   3206: iload #17
    //   3208: bipush #16
    //   3210: isub
    //   3211: iaload
    //   3212: iadd
    //   3213: iastore
    //   3214: goto -> 3221
    //   3217: invokestatic a : (Ljava/lang/Throwable;)Ljava/lang/Throwable;
    //   3220: athrow
    //   3221: aload #16
    //   3223: bipush #7
    //   3225: iaload
    //   3226: aload #16
    //   3228: iconst_4
    //   3229: iaload
    //   3230: bipush #6
    //   3232: iushr
    //   3233: aload #16
    //   3235: iconst_4
    //   3236: iaload
    //   3237: bipush #26
    //   3239: ishl
    //   3240: ior
    //   3241: aload #16
    //   3243: iconst_4
    //   3244: iaload
    //   3245: bipush #11
    //   3247: iushr
    //   3248: aload #16
    //   3250: iconst_4
    //   3251: iaload
    //   3252: bipush #21
    //   3254: ishl
    //   3255: ior
    //   3256: ixor
    //   3257: aload #16
    //   3259: iconst_4
    //   3260: iaload
    //   3261: bipush #25
    //   3263: iushr
    //   3264: aload #16
    //   3266: iconst_4
    //   3267: iaload
    //   3268: bipush #7
    //   3270: ishl
    //   3271: ior
    //   3272: ixor
    //   3273: iadd
    //   3274: aload #16
    //   3276: bipush #6
    //   3278: iaload
    //   3279: aload #16
    //   3281: iconst_4
    //   3282: iaload
    //   3283: aload #16
    //   3285: iconst_5
    //   3286: iaload
    //   3287: aload #16
    //   3289: bipush #6
    //   3291: iaload
    //   3292: ixor
    //   3293: iand
    //   3294: ixor
    //   3295: iadd
    //   3296: aload #7
    //   3298: iload #17
    //   3300: iaload
    //   3301: iadd
    //   3302: aload #15
    //   3304: iload #17
    //   3306: iaload
    //   3307: iadd
    //   3308: istore #18
    //   3310: aload #16
    //   3312: iconst_0
    //   3313: iaload
    //   3314: iconst_2
    //   3315: iushr
    //   3316: aload #16
    //   3318: iconst_0
    //   3319: iaload
    //   3320: bipush #30
    //   3322: ishl
    //   3323: ior
    //   3324: aload #16
    //   3326: iconst_0
    //   3327: iaload
    //   3328: bipush #13
    //   3330: iushr
    //   3331: aload #16
    //   3333: iconst_0
    //   3334: iaload
    //   3335: bipush #19
    //   3337: ishl
    //   3338: ior
    //   3339: ixor
    //   3340: aload #16
    //   3342: iconst_0
    //   3343: iaload
    //   3344: bipush #22
    //   3346: iushr
    //   3347: aload #16
    //   3349: iconst_0
    //   3350: iaload
    //   3351: bipush #10
    //   3353: ishl
    //   3354: ior
    //   3355: ixor
    //   3356: aload #16
    //   3358: iconst_0
    //   3359: iaload
    //   3360: aload #16
    //   3362: iconst_1
    //   3363: iaload
    //   3364: iand
    //   3365: aload #16
    //   3367: iconst_2
    //   3368: iaload
    //   3369: aload #16
    //   3371: iconst_0
    //   3372: iaload
    //   3373: aload #16
    //   3375: iconst_1
    //   3376: iaload
    //   3377: ior
    //   3378: iand
    //   3379: ior
    //   3380: iadd
    //   3381: istore #19
    //   3383: aload #16
    //   3385: iconst_3
    //   3386: dup2
    //   3387: iaload
    //   3388: iload #18
    //   3390: iadd
    //   3391: iastore
    //   3392: aload #16
    //   3394: bipush #7
    //   3396: iload #18
    //   3398: iload #19
    //   3400: iadd
    //   3401: iastore
    //   3402: aload #16
    //   3404: bipush #7
    //   3406: iaload
    //   3407: istore #18
    //   3409: aload #16
    //   3411: bipush #7
    //   3413: aload #16
    //   3415: bipush #6
    //   3417: iaload
    //   3418: iastore
    //   3419: aload #16
    //   3421: bipush #6
    //   3423: aload #16
    //   3425: iconst_5
    //   3426: iaload
    //   3427: iastore
    //   3428: aload #16
    //   3430: iconst_5
    //   3431: aload #16
    //   3433: iconst_4
    //   3434: iaload
    //   3435: iastore
    //   3436: aload #16
    //   3438: iconst_4
    //   3439: aload #16
    //   3441: iconst_3
    //   3442: iaload
    //   3443: iastore
    //   3444: aload #16
    //   3446: iconst_3
    //   3447: aload #16
    //   3449: iconst_2
    //   3450: iaload
    //   3451: iastore
    //   3452: aload #16
    //   3454: iconst_2
    //   3455: aload #16
    //   3457: iconst_1
    //   3458: iaload
    //   3459: iastore
    //   3460: aload #16
    //   3462: iconst_1
    //   3463: aload #16
    //   3465: iconst_0
    //   3466: iaload
    //   3467: iastore
    //   3468: aload #16
    //   3470: iconst_0
    //   3471: iload #18
    //   3473: iastore
    //   3474: iinc #17, 1
    //   3477: iload_2
    //   3478: ifne -> 2986
    //   3481: iconst_0
    //   3482: istore #17
    //   3484: iload #17
    //   3486: bipush #8
    //   3488: if_icmpge -> 3511
    //   3491: aload #9
    //   3493: iload #17
    //   3495: dup2
    //   3496: iaload
    //   3497: aload #16
    //   3499: iload #17
    //   3501: iaload
    //   3502: iadd
    //   3503: iastore
    //   3504: iinc #17, 1
    //   3507: iload_2
    //   3508: ifne -> 3484
    //   3511: iinc #14, 64
    //   3514: iinc #12, -64
    //   3517: iload_2
    //   3518: ifne -> 2907
    //   3521: iload #12
    //   3523: ifle -> 3559
    //   3526: iconst_0
    //   3527: istore #15
    //   3529: iload #15
    //   3531: iload #12
    //   3533: if_icmpge -> 3559
    //   3536: aload #10
    //   3538: iload #13
    //   3540: iload #15
    //   3542: iadd
    //   3543: aload #4
    //   3545: iload #14
    //   3547: iload #15
    //   3549: iadd
    //   3550: baload
    //   3551: bastore
    //   3552: iinc #15, 1
    //   3555: iload_2
    //   3556: ifne -> 3529
    //   3559: aload #8
    //   3561: iconst_0
    //   3562: iaload
    //   3563: bipush #29
    //   3565: iushr
    //   3566: aload #8
    //   3568: iconst_1
    //   3569: iaload
    //   3570: iconst_3
    //   3571: ishl
    //   3572: ior
    //   3573: istore #15
    //   3575: aload #8
    //   3577: iconst_0
    //   3578: iaload
    //   3579: iconst_3
    //   3580: ishl
    //   3581: istore #16
    //   3583: aload #8
    //   3585: iconst_0
    //   3586: iaload
    //   3587: bipush #63
    //   3589: iand
    //   3590: istore #17
    //   3592: iload #17
    //   3594: bipush #56
    //   3596: if_icmpge -> 3611
    //   3599: bipush #56
    //   3601: iload #17
    //   3603: isub
    //   3604: goto -> 3616
    //   3607: invokestatic a : (Ljava/lang/Throwable;)Ljava/lang/Throwable;
    //   3610: athrow
    //   3611: bipush #120
    //   3613: iload #17
    //   3615: isub
    //   3616: istore #18
    //   3618: aload #8
    //   3620: iconst_0
    //   3621: iaload
    //   3622: bipush #63
    //   3624: iand
    //   3625: istore #13
    //   3627: bipush #64
    //   3629: iload #13
    //   3631: isub
    //   3632: istore #19
    //   3634: aload #8
    //   3636: iconst_0
    //   3637: dup2
    //   3638: iaload
    //   3639: iload #18
    //   3641: iadd
    //   3642: iastore
    //   3643: aload #8
    //   3645: iconst_0
    //   3646: dup2
    //   3647: iaload
    //   3648: iconst_m1
    //   3649: iand
    //   3650: iastore
    //   3651: aload #8
    //   3653: iconst_0
    //   3654: iaload
    //   3655: iload #18
    //   3657: if_icmpge -> 3675
    //   3660: aload #8
    //   3662: iconst_1
    //   3663: dup2
    //   3664: iaload
    //   3665: iconst_1
    //   3666: iadd
    //   3667: iastore
    //   3668: goto -> 3675
    //   3671: invokestatic a : (Ljava/lang/Throwable;)Ljava/lang/Throwable;
    //   3674: athrow
    //   3675: iconst_0
    //   3676: istore #14
    //   3678: iload #13
    //   3680: ifle -> 4311
    //   3683: iload #18
    //   3685: iload #19
    //   3687: if_icmplt -> 4311
    //   3690: goto -> 3697
    //   3693: invokestatic a : (Ljava/lang/Throwable;)Ljava/lang/Throwable;
    //   3696: athrow
    //   3697: iconst_0
    //   3698: istore #20
    //   3700: iload #20
    //   3702: iload #19
    //   3704: if_icmpge -> 3727
    //   3707: aload #10
    //   3709: iload #13
    //   3711: iload #20
    //   3713: iadd
    //   3714: aload #6
    //   3716: iload #20
    //   3718: baload
    //   3719: bastore
    //   3720: iinc #20, 1
    //   3723: iload_2
    //   3724: ifne -> 3700
    //   3727: bipush #64
    //   3729: newarray int
    //   3731: astore #20
    //   3733: bipush #8
    //   3735: newarray int
    //   3737: astore #21
    //   3739: iconst_0
    //   3740: istore #22
    //   3742: iload #22
    //   3744: bipush #8
    //   3746: if_icmpge -> 3766
    //   3749: aload #21
    //   3751: iload #22
    //   3753: aload #9
    //   3755: iload #22
    //   3757: iaload
    //   3758: iastore
    //   3759: iinc #22, 1
    //   3762: iload_2
    //   3763: ifne -> 3742
    //   3766: iconst_0
    //   3767: istore #22
    //   3769: iload #22
    //   3771: bipush #64
    //   3773: if_icmpge -> 4264
    //   3776: iload #22
    //   3778: bipush #16
    //   3780: if_icmpge -> 3861
    //   3783: aload #20
    //   3785: iload #22
    //   3787: aload #10
    //   3789: iconst_4
    //   3790: iload #22
    //   3792: imul
    //   3793: baload
    //   3794: sipush #255
    //   3797: iand
    //   3798: bipush #24
    //   3800: ishl
    //   3801: aload #10
    //   3803: iconst_4
    //   3804: iload #22
    //   3806: imul
    //   3807: iconst_1
    //   3808: iadd
    //   3809: baload
    //   3810: sipush #255
    //   3813: iand
    //   3814: bipush #16
    //   3816: ishl
    //   3817: ior
    //   3818: aload #10
    //   3820: iconst_4
    //   3821: iload #22
    //   3823: imul
    //   3824: iconst_2
    //   3825: iadd
    //   3826: baload
    //   3827: sipush #255
    //   3830: iand
    //   3831: bipush #8
    //   3833: ishl
    //   3834: ior
    //   3835: aload #10
    //   3837: iconst_4
    //   3838: iload #22
    //   3840: imul
    //   3841: iconst_3
    //   3842: iadd
    //   3843: baload
    //   3844: sipush #255
    //   3847: iand
    //   3848: ior
    //   3849: iastore
    //   3850: iload_2
    //   3851: ifne -> 4004
    //   3854: goto -> 3861
    //   3857: invokestatic a : (Ljava/lang/Throwable;)Ljava/lang/Throwable;
    //   3860: athrow
    //   3861: aload #20
    //   3863: iload #22
    //   3865: aload #20
    //   3867: iload #22
    //   3869: iconst_2
    //   3870: isub
    //   3871: iaload
    //   3872: bipush #17
    //   3874: iushr
    //   3875: aload #20
    //   3877: iload #22
    //   3879: iconst_2
    //   3880: isub
    //   3881: iaload
    //   3882: bipush #15
    //   3884: ishl
    //   3885: ior
    //   3886: aload #20
    //   3888: iload #22
    //   3890: iconst_2
    //   3891: isub
    //   3892: iaload
    //   3893: bipush #19
    //   3895: iushr
    //   3896: aload #20
    //   3898: iload #22
    //   3900: iconst_2
    //   3901: isub
    //   3902: iaload
    //   3903: bipush #13
    //   3905: ishl
    //   3906: ior
    //   3907: ixor
    //   3908: aload #20
    //   3910: iload #22
    //   3912: iconst_2
    //   3913: isub
    //   3914: iaload
    //   3915: bipush #10
    //   3917: iushr
    //   3918: ixor
    //   3919: aload #20
    //   3921: iload #22
    //   3923: bipush #7
    //   3925: isub
    //   3926: iaload
    //   3927: iadd
    //   3928: aload #20
    //   3930: iload #22
    //   3932: bipush #15
    //   3934: isub
    //   3935: iaload
    //   3936: bipush #7
    //   3938: iushr
    //   3939: aload #20
    //   3941: iload #22
    //   3943: bipush #15
    //   3945: isub
    //   3946: iaload
    //   3947: bipush #25
    //   3949: ishl
    //   3950: ior
    //   3951: aload #20
    //   3953: iload #22
    //   3955: bipush #15
    //   3957: isub
    //   3958: iaload
    //   3959: bipush #18
    //   3961: iushr
    //   3962: aload #20
    //   3964: iload #22
    //   3966: bipush #15
    //   3968: isub
    //   3969: iaload
    //   3970: bipush #14
    //   3972: ishl
    //   3973: ior
    //   3974: ixor
    //   3975: aload #20
    //   3977: iload #22
    //   3979: bipush #15
    //   3981: isub
    //   3982: iaload
    //   3983: iconst_3
    //   3984: iushr
    //   3985: ixor
    //   3986: iadd
    //   3987: aload #20
    //   3989: iload #22
    //   3991: bipush #16
    //   3993: isub
    //   3994: iaload
    //   3995: iadd
    //   3996: iastore
    //   3997: goto -> 4004
    //   4000: invokestatic a : (Ljava/lang/Throwable;)Ljava/lang/Throwable;
    //   4003: athrow
    //   4004: aload #21
    //   4006: bipush #7
    //   4008: iaload
    //   4009: aload #21
    //   4011: iconst_4
    //   4012: iaload
    //   4013: bipush #6
    //   4015: iushr
    //   4016: aload #21
    //   4018: iconst_4
    //   4019: iaload
    //   4020: bipush #26
    //   4022: ishl
    //   4023: ior
    //   4024: aload #21
    //   4026: iconst_4
    //   4027: iaload
    //   4028: bipush #11
    //   4030: iushr
    //   4031: aload #21
    //   4033: iconst_4
    //   4034: iaload
    //   4035: bipush #21
    //   4037: ishl
    //   4038: ior
    //   4039: ixor
    //   4040: aload #21
    //   4042: iconst_4
    //   4043: iaload
    //   4044: bipush #25
    //   4046: iushr
    //   4047: aload #21
    //   4049: iconst_4
    //   4050: iaload
    //   4051: bipush #7
    //   4053: ishl
    //   4054: ior
    //   4055: ixor
    //   4056: iadd
    //   4057: aload #21
    //   4059: bipush #6
    //   4061: iaload
    //   4062: aload #21
    //   4064: iconst_4
    //   4065: iaload
    //   4066: aload #21
    //   4068: iconst_5
    //   4069: iaload
    //   4070: aload #21
    //   4072: bipush #6
    //   4074: iaload
    //   4075: ixor
    //   4076: iand
    //   4077: ixor
    //   4078: iadd
    //   4079: aload #7
    //   4081: iload #22
    //   4083: iaload
    //   4084: iadd
    //   4085: aload #20
    //   4087: iload #22
    //   4089: iaload
    //   4090: iadd
    //   4091: istore #23
    //   4093: aload #21
    //   4095: iconst_0
    //   4096: iaload
    //   4097: iconst_2
    //   4098: iushr
    //   4099: aload #21
    //   4101: iconst_0
    //   4102: iaload
    //   4103: bipush #30
    //   4105: ishl
    //   4106: ior
    //   4107: aload #21
    //   4109: iconst_0
    //   4110: iaload
    //   4111: bipush #13
    //   4113: iushr
    //   4114: aload #21
    //   4116: iconst_0
    //   4117: iaload
    //   4118: bipush #19
    //   4120: ishl
    //   4121: ior
    //   4122: ixor
    //   4123: aload #21
    //   4125: iconst_0
    //   4126: iaload
    //   4127: bipush #22
    //   4129: iushr
    //   4130: aload #21
    //   4132: iconst_0
    //   4133: iaload
    //   4134: bipush #10
    //   4136: ishl
    //   4137: ior
    //   4138: ixor
    //   4139: aload #21
    //   4141: iconst_0
    //   4142: iaload
    //   4143: aload #21
    //   4145: iconst_1
    //   4146: iaload
    //   4147: iand
    //   4148: aload #21
    //   4150: iconst_2
    //   4151: iaload
    //   4152: aload #21
    //   4154: iconst_0
    //   4155: iaload
    //   4156: aload #21
    //   4158: iconst_1
    //   4159: iaload
    //   4160: ior
    //   4161: iand
    //   4162: ior
    //   4163: iadd
    //   4164: istore #24
    //   4166: aload #21
    //   4168: iconst_3
    //   4169: dup2
    //   4170: iaload
    //   4171: iload #23
    //   4173: iadd
    //   4174: iastore
    //   4175: aload #21
    //   4177: bipush #7
    //   4179: iload #23
    //   4181: iload #24
    //   4183: iadd
    //   4184: iastore
    //   4185: aload #21
    //   4187: bipush #7
    //   4189: iaload
    //   4190: istore #23
    //   4192: aload #21
    //   4194: bipush #7
    //   4196: aload #21
    //   4198: bipush #6
    //   4200: iaload
    //   4201: iastore
    //   4202: aload #21
    //   4204: bipush #6
    //   4206: aload #21
    //   4208: iconst_5
    //   4209: iaload
    //   4210: iastore
    //   4211: aload #21
    //   4213: iconst_5
    //   4214: aload #21
    //   4216: iconst_4
    //   4217: iaload
    //   4218: iastore
    //   4219: aload #21
    //   4221: iconst_4
    //   4222: aload #21
    //   4224: iconst_3
    //   4225: iaload
    //   4226: iastore
    //   4227: aload #21
    //   4229: iconst_3
    //   4230: aload #21
    //   4232: iconst_2
    //   4233: iaload
    //   4234: iastore
    //   4235: aload #21
    //   4237: iconst_2
    //   4238: aload #21
    //   4240: iconst_1
    //   4241: iaload
    //   4242: iastore
    //   4243: aload #21
    //   4245: iconst_1
    //   4246: aload #21
    //   4248: iconst_0
    //   4249: iaload
    //   4250: iastore
    //   4251: aload #21
    //   4253: iconst_0
    //   4254: iload #23
    //   4256: iastore
    //   4257: iinc #22, 1
    //   4260: iload_2
    //   4261: ifne -> 3769
    //   4264: iconst_0
    //   4265: istore #22
    //   4267: iload #22
    //   4269: bipush #8
    //   4271: if_icmpge -> 4294
    //   4274: aload #9
    //   4276: iload #22
    //   4278: dup2
    //   4279: iaload
    //   4280: aload #21
    //   4282: iload #22
    //   4284: iaload
    //   4285: iadd
    //   4286: iastore
    //   4287: iinc #22, 1
    //   4290: iload_2
    //   4291: ifne -> 4267
    //   4294: iload #14
    //   4296: iload #19
    //   4298: iadd
    //   4299: istore #14
    //   4301: iload #18
    //   4303: iload #19
    //   4305: isub
    //   4306: istore #18
    //   4308: iconst_0
    //   4309: istore #13
    //   4311: iload #18
    //   4313: bipush #64
    //   4315: if_icmplt -> 4925
    //   4318: iconst_0
    //   4319: istore #20
    //   4321: iload #20
    //   4323: bipush #64
    //   4325: if_icmpge -> 4348
    //   4328: aload #11
    //   4330: iload #20
    //   4332: aload #6
    //   4334: iload #14
    //   4336: iload #20
    //   4338: iadd
    //   4339: baload
    //   4340: bastore
    //   4341: iinc #20, 1
    //   4344: iload_2
    //   4345: ifne -> 4321
    //   4348: bipush #64
    //   4350: newarray int
    //   4352: astore #20
    //   4354: bipush #8
    //   4356: newarray int
    //   4358: astore #21
    //   4360: iconst_0
    //   4361: istore #22
    //   4363: iload #22
    //   4365: bipush #8
    //   4367: if_icmpge -> 4387
    //   4370: aload #21
    //   4372: iload #22
    //   4374: aload #9
    //   4376: iload #22
    //   4378: iaload
    //   4379: iastore
    //   4380: iinc #22, 1
    //   4383: iload_2
    //   4384: ifne -> 4363
    //   4387: iconst_0
    //   4388: istore #22
    //   4390: iload #22
    //   4392: bipush #64
    //   4394: if_icmpge -> 4885
    //   4397: iload #22
    //   4399: bipush #16
    //   4401: if_icmpge -> 4482
    //   4404: aload #20
    //   4406: iload #22
    //   4408: aload #11
    //   4410: iconst_4
    //   4411: iload #22
    //   4413: imul
    //   4414: baload
    //   4415: sipush #255
    //   4418: iand
    //   4419: bipush #24
    //   4421: ishl
    //   4422: aload #11
    //   4424: iconst_4
    //   4425: iload #22
    //   4427: imul
    //   4428: iconst_1
    //   4429: iadd
    //   4430: baload
    //   4431: sipush #255
    //   4434: iand
    //   4435: bipush #16
    //   4437: ishl
    //   4438: ior
    //   4439: aload #11
    //   4441: iconst_4
    //   4442: iload #22
    //   4444: imul
    //   4445: iconst_2
    //   4446: iadd
    //   4447: baload
    //   4448: sipush #255
    //   4451: iand
    //   4452: bipush #8
    //   4454: ishl
    //   4455: ior
    //   4456: aload #11
    //   4458: iconst_4
    //   4459: iload #22
    //   4461: imul
    //   4462: iconst_3
    //   4463: iadd
    //   4464: baload
    //   4465: sipush #255
    //   4468: iand
    //   4469: ior
    //   4470: iastore
    //   4471: iload_2
    //   4472: ifne -> 4625
    //   4475: goto -> 4482
    //   4478: invokestatic a : (Ljava/lang/Throwable;)Ljava/lang/Throwable;
    //   4481: athrow
    //   4482: aload #20
    //   4484: iload #22
    //   4486: aload #20
    //   4488: iload #22
    //   4490: iconst_2
    //   4491: isub
    //   4492: iaload
    //   4493: bipush #17
    //   4495: iushr
    //   4496: aload #20
    //   4498: iload #22
    //   4500: iconst_2
    //   4501: isub
    //   4502: iaload
    //   4503: bipush #15
    //   4505: ishl
    //   4506: ior
    //   4507: aload #20
    //   4509: iload #22
    //   4511: iconst_2
    //   4512: isub
    //   4513: iaload
    //   4514: bipush #19
    //   4516: iushr
    //   4517: aload #20
    //   4519: iload #22
    //   4521: iconst_2
    //   4522: isub
    //   4523: iaload
    //   4524: bipush #13
    //   4526: ishl
    //   4527: ior
    //   4528: ixor
    //   4529: aload #20
    //   4531: iload #22
    //   4533: iconst_2
    //   4534: isub
    //   4535: iaload
    //   4536: bipush #10
    //   4538: iushr
    //   4539: ixor
    //   4540: aload #20
    //   4542: iload #22
    //   4544: bipush #7
    //   4546: isub
    //   4547: iaload
    //   4548: iadd
    //   4549: aload #20
    //   4551: iload #22
    //   4553: bipush #15
    //   4555: isub
    //   4556: iaload
    //   4557: bipush #7
    //   4559: iushr
    //   4560: aload #20
    //   4562: iload #22
    //   4564: bipush #15
    //   4566: isub
    //   4567: iaload
    //   4568: bipush #25
    //   4570: ishl
    //   4571: ior
    //   4572: aload #20
    //   4574: iload #22
    //   4576: bipush #15
    //   4578: isub
    //   4579: iaload
    //   4580: bipush #18
    //   4582: iushr
    //   4583: aload #20
    //   4585: iload #22
    //   4587: bipush #15
    //   4589: isub
    //   4590: iaload
    //   4591: bipush #14
    //   4593: ishl
    //   4594: ior
    //   4595: ixor
    //   4596: aload #20
    //   4598: iload #22
    //   4600: bipush #15
    //   4602: isub
    //   4603: iaload
    //   4604: iconst_3
    //   4605: iushr
    //   4606: ixor
    //   4607: iadd
    //   4608: aload #20
    //   4610: iload #22
    //   4612: bipush #16
    //   4614: isub
    //   4615: iaload
    //   4616: iadd
    //   4617: iastore
    //   4618: goto -> 4625
    //   4621: invokestatic a : (Ljava/lang/Throwable;)Ljava/lang/Throwable;
    //   4624: athrow
    //   4625: aload #21
    //   4627: bipush #7
    //   4629: iaload
    //   4630: aload #21
    //   4632: iconst_4
    //   4633: iaload
    //   4634: bipush #6
    //   4636: iushr
    //   4637: aload #21
    //   4639: iconst_4
    //   4640: iaload
    //   4641: bipush #26
    //   4643: ishl
    //   4644: ior
    //   4645: aload #21
    //   4647: iconst_4
    //   4648: iaload
    //   4649: bipush #11
    //   4651: iushr
    //   4652: aload #21
    //   4654: iconst_4
    //   4655: iaload
    //   4656: bipush #21
    //   4658: ishl
    //   4659: ior
    //   4660: ixor
    //   4661: aload #21
    //   4663: iconst_4
    //   4664: iaload
    //   4665: bipush #25
    //   4667: iushr
    //   4668: aload #21
    //   4670: iconst_4
    //   4671: iaload
    //   4672: bipush #7
    //   4674: ishl
    //   4675: ior
    //   4676: ixor
    //   4677: iadd
    //   4678: aload #21
    //   4680: bipush #6
    //   4682: iaload
    //   4683: aload #21
    //   4685: iconst_4
    //   4686: iaload
    //   4687: aload #21
    //   4689: iconst_5
    //   4690: iaload
    //   4691: aload #21
    //   4693: bipush #6
    //   4695: iaload
    //   4696: ixor
    //   4697: iand
    //   4698: ixor
    //   4699: iadd
    //   4700: aload #7
    //   4702: iload #22
    //   4704: iaload
    //   4705: iadd
    //   4706: aload #20
    //   4708: iload #22
    //   4710: iaload
    //   4711: iadd
    //   4712: istore #23
    //   4714: aload #21
    //   4716: iconst_0
    //   4717: iaload
    //   4718: iconst_2
    //   4719: iushr
    //   4720: aload #21
    //   4722: iconst_0
    //   4723: iaload
    //   4724: bipush #30
    //   4726: ishl
    //   4727: ior
    //   4728: aload #21
    //   4730: iconst_0
    //   4731: iaload
    //   4732: bipush #13
    //   4734: iushr
    //   4735: aload #21
    //   4737: iconst_0
    //   4738: iaload
    //   4739: bipush #19
    //   4741: ishl
    //   4742: ior
    //   4743: ixor
    //   4744: aload #21
    //   4746: iconst_0
    //   4747: iaload
    //   4748: bipush #22
    //   4750: iushr
    //   4751: aload #21
    //   4753: iconst_0
    //   4754: iaload
    //   4755: bipush #10
    //   4757: ishl
    //   4758: ior
    //   4759: ixor
    //   4760: aload #21
    //   4762: iconst_0
    //   4763: iaload
    //   4764: aload #21
    //   4766: iconst_1
    //   4767: iaload
    //   4768: iand
    //   4769: aload #21
    //   4771: iconst_2
    //   4772: iaload
    //   4773: aload #21
    //   4775: iconst_0
    //   4776: iaload
    //   4777: aload #21
    //   4779: iconst_1
    //   4780: iaload
    //   4781: ior
    //   4782: iand
    //   4783: ior
    //   4784: iadd
    //   4785: istore #24
    //   4787: aload #21
    //   4789: iconst_3
    //   4790: dup2
    //   4791: iaload
    //   4792: iload #23
    //   4794: iadd
    //   4795: iastore
    //   4796: aload #21
    //   4798: bipush #7
    //   4800: iload #23
    //   4802: iload #24
    //   4804: iadd
    //   4805: iastore
    //   4806: aload #21
    //   4808: bipush #7
    //   4810: iaload
    //   4811: istore #23
    //   4813: aload #21
    //   4815: bipush #7
    //   4817: aload #21
    //   4819: bipush #6
    //   4821: iaload
    //   4822: iastore
    //   4823: aload #21
    //   4825: bipush #6
    //   4827: aload #21
    //   4829: iconst_5
    //   4830: iaload
    //   4831: iastore
    //   4832: aload #21
    //   4834: iconst_5
    //   4835: aload #21
    //   4837: iconst_4
    //   4838: iaload
    //   4839: iastore
    //   4840: aload #21
    //   4842: iconst_4
    //   4843: aload #21
    //   4845: iconst_3
    //   4846: iaload
    //   4847: iastore
    //   4848: aload #21
    //   4850: iconst_3
    //   4851: aload #21
    //   4853: iconst_2
    //   4854: iaload
    //   4855: iastore
    //   4856: aload #21
    //   4858: iconst_2
    //   4859: aload #21
    //   4861: iconst_1
    //   4862: iaload
    //   4863: iastore
    //   4864: aload #21
    //   4866: iconst_1
    //   4867: aload #21
    //   4869: iconst_0
    //   4870: iaload
    //   4871: iastore
    //   4872: aload #21
    //   4874: iconst_0
    //   4875: iload #23
    //   4877: iastore
    //   4878: iinc #22, 1
    //   4881: iload_2
    //   4882: ifne -> 4390
    //   4885: iconst_0
    //   4886: istore #22
    //   4888: iload #22
    //   4890: bipush #8
    //   4892: if_icmpge -> 4915
    //   4895: aload #9
    //   4897: iload #22
    //   4899: dup2
    //   4900: iaload
    //   4901: aload #21
    //   4903: iload #22
    //   4905: iaload
    //   4906: iadd
    //   4907: iastore
    //   4908: iinc #22, 1
    //   4911: iload_2
    //   4912: ifne -> 4888
    //   4915: iinc #14, 64
    //   4918: iinc #18, -64
    //   4921: iload_2
    //   4922: ifne -> 4311
    //   4925: iload #18
    //   4927: ifle -> 4963
    //   4930: iconst_0
    //   4931: istore #20
    //   4933: iload #20
    //   4935: iload #18
    //   4937: if_icmpge -> 4963
    //   4940: aload #10
    //   4942: iload #13
    //   4944: iload #20
    //   4946: iadd
    //   4947: aload #6
    //   4949: iload #14
    //   4951: iload #20
    //   4953: iadd
    //   4954: baload
    //   4955: bastore
    //   4956: iinc #20, 1
    //   4959: iload_2
    //   4960: ifne -> 4933
    //   4963: bipush #8
    //   4965: newarray byte
    //   4967: astore #20
    //   4969: aload #20
    //   4971: iconst_0
    //   4972: iload #15
    //   4974: bipush #24
    //   4976: iushr
    //   4977: i2b
    //   4978: bastore
    //   4979: aload #20
    //   4981: iconst_1
    //   4982: iload #15
    //   4984: bipush #16
    //   4986: iushr
    //   4987: i2b
    //   4988: bastore
    //   4989: aload #20
    //   4991: iconst_2
    //   4992: iload #15
    //   4994: bipush #8
    //   4996: iushr
    //   4997: i2b
    //   4998: bastore
    //   4999: aload #20
    //   5001: iconst_3
    //   5002: iload #15
    //   5004: i2b
    //   5005: bastore
    //   5006: aload #20
    //   5008: iconst_4
    //   5009: iload #16
    //   5011: bipush #24
    //   5013: iushr
    //   5014: i2b
    //   5015: bastore
    //   5016: aload #20
    //   5018: iconst_5
    //   5019: iload #16
    //   5021: bipush #16
    //   5023: iushr
    //   5024: i2b
    //   5025: bastore
    //   5026: aload #20
    //   5028: bipush #6
    //   5030: iload #16
    //   5032: bipush #8
    //   5034: iushr
    //   5035: i2b
    //   5036: bastore
    //   5037: aload #20
    //   5039: bipush #7
    //   5041: iload #16
    //   5043: i2b
    //   5044: bastore
    //   5045: bipush #8
    //   5047: istore #12
    //   5049: aload #8
    //   5051: iconst_0
    //   5052: iaload
    //   5053: bipush #63
    //   5055: iand
    //   5056: istore #13
    //   5058: bipush #64
    //   5060: iload #13
    //   5062: isub
    //   5063: istore #19
    //   5065: aload #8
    //   5067: iconst_0
    //   5068: dup2
    //   5069: iaload
    //   5070: iload #12
    //   5072: iadd
    //   5073: iastore
    //   5074: aload #8
    //   5076: iconst_0
    //   5077: dup2
    //   5078: iaload
    //   5079: iconst_m1
    //   5080: iand
    //   5081: iastore
    //   5082: aload #8
    //   5084: iconst_0
    //   5085: iaload
    //   5086: iload #12
    //   5088: if_icmpge -> 5106
    //   5091: aload #8
    //   5093: iconst_1
    //   5094: dup2
    //   5095: iaload
    //   5096: iconst_1
    //   5097: iadd
    //   5098: iastore
    //   5099: goto -> 5106
    //   5102: invokestatic a : (Ljava/lang/Throwable;)Ljava/lang/Throwable;
    //   5105: athrow
    //   5106: iload #13
    //   5108: ifle -> 5722
    //   5111: iload #12
    //   5113: iload #19
    //   5115: if_icmplt -> 5722
    //   5118: goto -> 5125
    //   5121: invokestatic a : (Ljava/lang/Throwable;)Ljava/lang/Throwable;
    //   5124: athrow
    //   5125: iconst_0
    //   5126: istore #21
    //   5128: iload #21
    //   5130: iload #19
    //   5132: if_icmpge -> 5155
    //   5135: aload #10
    //   5137: iload #13
    //   5139: iload #21
    //   5141: iadd
    //   5142: aload #20
    //   5144: iload #21
    //   5146: baload
    //   5147: bastore
    //   5148: iinc #21, 1
    //   5151: iload_2
    //   5152: ifne -> 5128
    //   5155: bipush #64
    //   5157: newarray int
    //   5159: astore #21
    //   5161: bipush #8
    //   5163: newarray int
    //   5165: astore #22
    //   5167: iconst_0
    //   5168: istore #23
    //   5170: iload #23
    //   5172: bipush #8
    //   5174: if_icmpge -> 5194
    //   5177: aload #22
    //   5179: iload #23
    //   5181: aload #9
    //   5183: iload #23
    //   5185: iaload
    //   5186: iastore
    //   5187: iinc #23, 1
    //   5190: iload_2
    //   5191: ifne -> 5170
    //   5194: iconst_0
    //   5195: istore #23
    //   5197: iload #23
    //   5199: bipush #64
    //   5201: if_icmpge -> 5692
    //   5204: iload #23
    //   5206: bipush #16
    //   5208: if_icmpge -> 5289
    //   5211: aload #21
    //   5213: iload #23
    //   5215: aload #10
    //   5217: iconst_4
    //   5218: iload #23
    //   5220: imul
    //   5221: baload
    //   5222: sipush #255
    //   5225: iand
    //   5226: bipush #24
    //   5228: ishl
    //   5229: aload #10
    //   5231: iconst_4
    //   5232: iload #23
    //   5234: imul
    //   5235: iconst_1
    //   5236: iadd
    //   5237: baload
    //   5238: sipush #255
    //   5241: iand
    //   5242: bipush #16
    //   5244: ishl
    //   5245: ior
    //   5246: aload #10
    //   5248: iconst_4
    //   5249: iload #23
    //   5251: imul
    //   5252: iconst_2
    //   5253: iadd
    //   5254: baload
    //   5255: sipush #255
    //   5258: iand
    //   5259: bipush #8
    //   5261: ishl
    //   5262: ior
    //   5263: aload #10
    //   5265: iconst_4
    //   5266: iload #23
    //   5268: imul
    //   5269: iconst_3
    //   5270: iadd
    //   5271: baload
    //   5272: sipush #255
    //   5275: iand
    //   5276: ior
    //   5277: iastore
    //   5278: iload_2
    //   5279: ifne -> 5432
    //   5282: goto -> 5289
    //   5285: invokestatic a : (Ljava/lang/Throwable;)Ljava/lang/Throwable;
    //   5288: athrow
    //   5289: aload #21
    //   5291: iload #23
    //   5293: aload #21
    //   5295: iload #23
    //   5297: iconst_2
    //   5298: isub
    //   5299: iaload
    //   5300: bipush #17
    //   5302: iushr
    //   5303: aload #21
    //   5305: iload #23
    //   5307: iconst_2
    //   5308: isub
    //   5309: iaload
    //   5310: bipush #15
    //   5312: ishl
    //   5313: ior
    //   5314: aload #21
    //   5316: iload #23
    //   5318: iconst_2
    //   5319: isub
    //   5320: iaload
    //   5321: bipush #19
    //   5323: iushr
    //   5324: aload #21
    //   5326: iload #23
    //   5328: iconst_2
    //   5329: isub
    //   5330: iaload
    //   5331: bipush #13
    //   5333: ishl
    //   5334: ior
    //   5335: ixor
    //   5336: aload #21
    //   5338: iload #23
    //   5340: iconst_2
    //   5341: isub
    //   5342: iaload
    //   5343: bipush #10
    //   5345: iushr
    //   5346: ixor
    //   5347: aload #21
    //   5349: iload #23
    //   5351: bipush #7
    //   5353: isub
    //   5354: iaload
    //   5355: iadd
    //   5356: aload #21
    //   5358: iload #23
    //   5360: bipush #15
    //   5362: isub
    //   5363: iaload
    //   5364: bipush #7
    //   5366: iushr
    //   5367: aload #21
    //   5369: iload #23
    //   5371: bipush #15
    //   5373: isub
    //   5374: iaload
    //   5375: bipush #25
    //   5377: ishl
    //   5378: ior
    //   5379: aload #21
    //   5381: iload #23
    //   5383: bipush #15
    //   5385: isub
    //   5386: iaload
    //   5387: bipush #18
    //   5389: iushr
    //   5390: aload #21
    //   5392: iload #23
    //   5394: bipush #15
    //   5396: isub
    //   5397: iaload
    //   5398: bipush #14
    //   5400: ishl
    //   5401: ior
    //   5402: ixor
    //   5403: aload #21
    //   5405: iload #23
    //   5407: bipush #15
    //   5409: isub
    //   5410: iaload
    //   5411: iconst_3
    //   5412: iushr
    //   5413: ixor
    //   5414: iadd
    //   5415: aload #21
    //   5417: iload #23
    //   5419: bipush #16
    //   5421: isub
    //   5422: iaload
    //   5423: iadd
    //   5424: iastore
    //   5425: goto -> 5432
    //   5428: invokestatic a : (Ljava/lang/Throwable;)Ljava/lang/Throwable;
    //   5431: athrow
    //   5432: aload #22
    //   5434: bipush #7
    //   5436: iaload
    //   5437: aload #22
    //   5439: iconst_4
    //   5440: iaload
    //   5441: bipush #6
    //   5443: iushr
    //   5444: aload #22
    //   5446: iconst_4
    //   5447: iaload
    //   5448: bipush #26
    //   5450: ishl
    //   5451: ior
    //   5452: aload #22
    //   5454: iconst_4
    //   5455: iaload
    //   5456: bipush #11
    //   5458: iushr
    //   5459: aload #22
    //   5461: iconst_4
    //   5462: iaload
    //   5463: bipush #21
    //   5465: ishl
    //   5466: ior
    //   5467: ixor
    //   5468: aload #22
    //   5470: iconst_4
    //   5471: iaload
    //   5472: bipush #25
    //   5474: iushr
    //   5475: aload #22
    //   5477: iconst_4
    //   5478: iaload
    //   5479: bipush #7
    //   5481: ishl
    //   5482: ior
    //   5483: ixor
    //   5484: iadd
    //   5485: aload #22
    //   5487: bipush #6
    //   5489: iaload
    //   5490: aload #22
    //   5492: iconst_4
    //   5493: iaload
    //   5494: aload #22
    //   5496: iconst_5
    //   5497: iaload
    //   5498: aload #22
    //   5500: bipush #6
    //   5502: iaload
    //   5503: ixor
    //   5504: iand
    //   5505: ixor
    //   5506: iadd
    //   5507: aload #7
    //   5509: iload #23
    //   5511: iaload
    //   5512: iadd
    //   5513: aload #21
    //   5515: iload #23
    //   5517: iaload
    //   5518: iadd
    //   5519: istore #24
    //   5521: aload #22
    //   5523: iconst_0
    //   5524: iaload
    //   5525: iconst_2
    //   5526: iushr
    //   5527: aload #22
    //   5529: iconst_0
    //   5530: iaload
    //   5531: bipush #30
    //   5533: ishl
    //   5534: ior
    //   5535: aload #22
    //   5537: iconst_0
    //   5538: iaload
    //   5539: bipush #13
    //   5541: iushr
    //   5542: aload #22
    //   5544: iconst_0
    //   5545: iaload
    //   5546: bipush #19
    //   5548: ishl
    //   5549: ior
    //   5550: ixor
    //   5551: aload #22
    //   5553: iconst_0
    //   5554: iaload
    //   5555: bipush #22
    //   5557: iushr
    //   5558: aload #22
    //   5560: iconst_0
    //   5561: iaload
    //   5562: bipush #10
    //   5564: ishl
    //   5565: ior
    //   5566: ixor
    //   5567: aload #22
    //   5569: iconst_0
    //   5570: iaload
    //   5571: aload #22
    //   5573: iconst_1
    //   5574: iaload
    //   5575: iand
    //   5576: aload #22
    //   5578: iconst_2
    //   5579: iaload
    //   5580: aload #22
    //   5582: iconst_0
    //   5583: iaload
    //   5584: aload #22
    //   5586: iconst_1
    //   5587: iaload
    //   5588: ior
    //   5589: iand
    //   5590: ior
    //   5591: iadd
    //   5592: istore #25
    //   5594: aload #22
    //   5596: iconst_3
    //   5597: dup2
    //   5598: iaload
    //   5599: iload #24
    //   5601: iadd
    //   5602: iastore
    //   5603: aload #22
    //   5605: bipush #7
    //   5607: iload #24
    //   5609: iload #25
    //   5611: iadd
    //   5612: iastore
    //   5613: aload #22
    //   5615: bipush #7
    //   5617: iaload
    //   5618: istore #24
    //   5620: aload #22
    //   5622: bipush #7
    //   5624: aload #22
    //   5626: bipush #6
    //   5628: iaload
    //   5629: iastore
    //   5630: aload #22
    //   5632: bipush #6
    //   5634: aload #22
    //   5636: iconst_5
    //   5637: iaload
    //   5638: iastore
    //   5639: aload #22
    //   5641: iconst_5
    //   5642: aload #22
    //   5644: iconst_4
    //   5645: iaload
    //   5646: iastore
    //   5647: aload #22
    //   5649: iconst_4
    //   5650: aload #22
    //   5652: iconst_3
    //   5653: iaload
    //   5654: iastore
    //   5655: aload #22
    //   5657: iconst_3
    //   5658: aload #22
    //   5660: iconst_2
    //   5661: iaload
    //   5662: iastore
    //   5663: aload #22
    //   5665: iconst_2
    //   5666: aload #22
    //   5668: iconst_1
    //   5669: iaload
    //   5670: iastore
    //   5671: aload #22
    //   5673: iconst_1
    //   5674: aload #22
    //   5676: iconst_0
    //   5677: iaload
    //   5678: iastore
    //   5679: aload #22
    //   5681: iconst_0
    //   5682: iload #24
    //   5684: iastore
    //   5685: iinc #23, 1
    //   5688: iload_2
    //   5689: ifne -> 5197
    //   5692: iconst_0
    //   5693: istore #23
    //   5695: iload #23
    //   5697: bipush #8
    //   5699: if_icmpge -> 5722
    //   5702: aload #9
    //   5704: iload #23
    //   5706: dup2
    //   5707: iaload
    //   5708: aload #22
    //   5710: iload #23
    //   5712: iaload
    //   5713: iadd
    //   5714: iastore
    //   5715: iinc #23, 1
    //   5718: iload_2
    //   5719: ifne -> 5695
    //   5722: bipush #32
    //   5724: newarray byte
    //   5726: astore #5
    //   5728: aload #5
    //   5730: iconst_0
    //   5731: aload #9
    //   5733: iconst_0
    //   5734: iaload
    //   5735: bipush #24
    //   5737: iushr
    //   5738: i2b
    //   5739: bastore
    //   5740: aload #5
    //   5742: iconst_1
    //   5743: aload #9
    //   5745: iconst_0
    //   5746: iaload
    //   5747: bipush #16
    //   5749: iushr
    //   5750: i2b
    //   5751: bastore
    //   5752: aload #5
    //   5754: iconst_2
    //   5755: aload #9
    //   5757: iconst_0
    //   5758: iaload
    //   5759: bipush #8
    //   5761: iushr
    //   5762: i2b
    //   5763: bastore
    //   5764: aload #5
    //   5766: iconst_3
    //   5767: aload #9
    //   5769: iconst_0
    //   5770: iaload
    //   5771: i2b
    //   5772: bastore
    //   5773: aload #5
    //   5775: iconst_4
    //   5776: aload #9
    //   5778: iconst_1
    //   5779: iaload
    //   5780: bipush #24
    //   5782: iushr
    //   5783: i2b
    //   5784: bastore
    //   5785: aload #5
    //   5787: iconst_5
    //   5788: aload #9
    //   5790: iconst_1
    //   5791: iaload
    //   5792: bipush #16
    //   5794: iushr
    //   5795: i2b
    //   5796: bastore
    //   5797: aload #5
    //   5799: bipush #6
    //   5801: aload #9
    //   5803: iconst_1
    //   5804: iaload
    //   5805: bipush #8
    //   5807: iushr
    //   5808: i2b
    //   5809: bastore
    //   5810: aload #5
    //   5812: bipush #7
    //   5814: aload #9
    //   5816: iconst_1
    //   5817: iaload
    //   5818: i2b
    //   5819: bastore
    //   5820: aload #5
    //   5822: bipush #8
    //   5824: aload #9
    //   5826: iconst_2
    //   5827: iaload
    //   5828: bipush #24
    //   5830: iushr
    //   5831: i2b
    //   5832: bastore
    //   5833: aload #5
    //   5835: bipush #9
    //   5837: aload #9
    //   5839: iconst_2
    //   5840: iaload
    //   5841: bipush #16
    //   5843: iushr
    //   5844: i2b
    //   5845: bastore
    //   5846: aload #5
    //   5848: bipush #10
    //   5850: aload #9
    //   5852: iconst_2
    //   5853: iaload
    //   5854: bipush #8
    //   5856: iushr
    //   5857: i2b
    //   5858: bastore
    //   5859: aload #5
    //   5861: bipush #11
    //   5863: aload #9
    //   5865: iconst_2
    //   5866: iaload
    //   5867: i2b
    //   5868: bastore
    //   5869: aload #5
    //   5871: bipush #12
    //   5873: aload #9
    //   5875: iconst_3
    //   5876: iaload
    //   5877: bipush #24
    //   5879: iushr
    //   5880: i2b
    //   5881: bastore
    //   5882: aload #5
    //   5884: bipush #13
    //   5886: aload #9
    //   5888: iconst_3
    //   5889: iaload
    //   5890: bipush #16
    //   5892: iushr
    //   5893: i2b
    //   5894: bastore
    //   5895: aload #5
    //   5897: bipush #14
    //   5899: aload #9
    //   5901: iconst_3
    //   5902: iaload
    //   5903: bipush #8
    //   5905: iushr
    //   5906: i2b
    //   5907: bastore
    //   5908: aload #5
    //   5910: bipush #15
    //   5912: aload #9
    //   5914: iconst_3
    //   5915: iaload
    //   5916: i2b
    //   5917: bastore
    //   5918: aload #5
    //   5920: bipush #16
    //   5922: aload #9
    //   5924: iconst_4
    //   5925: iaload
    //   5926: bipush #24
    //   5928: iushr
    //   5929: i2b
    //   5930: bastore
    //   5931: aload #5
    //   5933: bipush #17
    //   5935: aload #9
    //   5937: iconst_4
    //   5938: iaload
    //   5939: bipush #16
    //   5941: iushr
    //   5942: i2b
    //   5943: bastore
    //   5944: aload #5
    //   5946: bipush #18
    //   5948: aload #9
    //   5950: iconst_4
    //   5951: iaload
    //   5952: bipush #8
    //   5954: iushr
    //   5955: i2b
    //   5956: bastore
    //   5957: aload #5
    //   5959: bipush #19
    //   5961: aload #9
    //   5963: iconst_4
    //   5964: iaload
    //   5965: i2b
    //   5966: bastore
    //   5967: aload #5
    //   5969: bipush #20
    //   5971: aload #9
    //   5973: iconst_5
    //   5974: iaload
    //   5975: bipush #24
    //   5977: iushr
    //   5978: i2b
    //   5979: bastore
    //   5980: aload #5
    //   5982: bipush #21
    //   5984: aload #9
    //   5986: iconst_5
    //   5987: iaload
    //   5988: bipush #16
    //   5990: iushr
    //   5991: i2b
    //   5992: bastore
    //   5993: aload #5
    //   5995: bipush #22
    //   5997: aload #9
    //   5999: iconst_5
    //   6000: iaload
    //   6001: bipush #8
    //   6003: iushr
    //   6004: i2b
    //   6005: bastore
    //   6006: aload #5
    //   6008: bipush #23
    //   6010: aload #9
    //   6012: iconst_5
    //   6013: iaload
    //   6014: i2b
    //   6015: bastore
    //   6016: aload #5
    //   6018: bipush #24
    //   6020: aload #9
    //   6022: bipush #6
    //   6024: iaload
    //   6025: bipush #24
    //   6027: iushr
    //   6028: i2b
    //   6029: bastore
    //   6030: aload #5
    //   6032: bipush #25
    //   6034: aload #9
    //   6036: bipush #6
    //   6038: iaload
    //   6039: bipush #16
    //   6041: iushr
    //   6042: i2b
    //   6043: bastore
    //   6044: aload #5
    //   6046: bipush #26
    //   6048: aload #9
    //   6050: bipush #6
    //   6052: iaload
    //   6053: bipush #8
    //   6055: iushr
    //   6056: i2b
    //   6057: bastore
    //   6058: aload #5
    //   6060: bipush #27
    //   6062: aload #9
    //   6064: bipush #6
    //   6066: iaload
    //   6067: i2b
    //   6068: bastore
    //   6069: aload #5
    //   6071: bipush #28
    //   6073: aload #9
    //   6075: bipush #7
    //   6077: iaload
    //   6078: bipush #24
    //   6080: iushr
    //   6081: i2b
    //   6082: bastore
    //   6083: aload #5
    //   6085: bipush #29
    //   6087: aload #9
    //   6089: bipush #7
    //   6091: iaload
    //   6092: bipush #16
    //   6094: iushr
    //   6095: i2b
    //   6096: bastore
    //   6097: aload #5
    //   6099: bipush #30
    //   6101: aload #9
    //   6103: bipush #7
    //   6105: iaload
    //   6106: bipush #8
    //   6108: iushr
    //   6109: i2b
    //   6110: bastore
    //   6111: aload #5
    //   6113: bipush #31
    //   6115: aload #9
    //   6117: bipush #7
    //   6119: iaload
    //   6120: i2b
    //   6121: bastore
    //   6122: iconst_0
    //   6123: istore #4
    //   6125: getstatic burp/Zmh3.Zy : Ljava/lang/String;
    //   6128: getstatic burp/Zm7v.ZP : Ljava/lang/Object;
    //   6131: checkcast java/math/BigInteger
    //   6134: invokevirtual intValue : ()I
    //   6137: bipush #32
    //   6139: irem
    //   6140: invokestatic abs : (I)I
    //   6143: invokevirtual charAt : (I)C
    //   6146: getstatic burp/Zmf6.Zn : Ljava/lang/String;
    //   6149: getstatic burp/Zk8f.ZG : Ljava/lang/Object;
    //   6152: checkcast java/math/BigInteger
    //   6155: invokevirtual intValue : ()I
    //   6158: bipush #32
    //   6160: irem
    //   6161: invokestatic abs : (I)I
    //   6164: invokevirtual charAt : (I)C
    //   6167: if_icmpgt -> 6512
    //   6170: sipush #-14566
    //   6173: sipush #29294
    //   6176: invokestatic a : (II)Ljava/lang/String;
    //   6179: iconst_1
    //   6180: ldc burp/Zgr4
    //   6182: invokevirtual getClassLoader : ()Ljava/lang/ClassLoader;
    //   6185: invokestatic forName : (Ljava/lang/String;ZLjava/lang/ClassLoader;)Ljava/lang/Class;
    //   6188: invokevirtual getDeclaredFields : ()[Ljava/lang/reflect/Field;
    //   6191: astore #5
    //   6193: aload #5
    //   6195: arraylength
    //   6196: istore #6
    //   6198: iconst_0
    //   6199: istore #7
    //   6201: iload #7
    //   6203: iload #6
    //   6205: if_icmpge -> 6343
    //   6208: aload #5
    //   6210: iload #7
    //   6212: aaload
    //   6213: astore #8
    //   6215: aload #8
    //   6217: invokevirtual getModifiers : ()I
    //   6220: invokestatic isStatic : (I)Z
    //   6223: ifne -> 6233
    //   6226: goto -> 6336
    //   6229: invokestatic a : (Ljava/lang/Throwable;)Ljava/lang/Throwable;
    //   6232: athrow
    //   6233: aload #8
    //   6235: invokevirtual getType : ()Ljava/lang/Class;
    //   6238: astore #9
    //   6240: aload #9
    //   6242: ifnull -> 6323
    //   6245: aload #9
    //   6247: invokevirtual isPrimitive : ()Z
    //   6250: ifne -> 6323
    //   6253: goto -> 6260
    //   6256: invokestatic a : (Ljava/lang/Throwable;)Ljava/lang/Throwable;
    //   6259: athrow
    //   6260: aload #9
    //   6262: invokevirtual getPackage : ()Ljava/lang/Package;
    //   6265: ifnull -> 6323
    //   6268: goto -> 6275
    //   6271: invokestatic a : (Ljava/lang/Throwable;)Ljava/lang/Throwable;
    //   6274: athrow
    //   6275: aload #9
    //   6277: invokevirtual getPackage : ()Ljava/lang/Package;
    //   6280: invokevirtual getName : ()Ljava/lang/String;
    //   6283: ifnull -> 6323
    //   6286: goto -> 6293
    //   6289: invokestatic a : (Ljava/lang/Throwable;)Ljava/lang/Throwable;
    //   6292: athrow
    //   6293: aload #9
    //   6295: invokevirtual getPackage : ()Ljava/lang/Package;
    //   6298: invokevirtual getName : ()Ljava/lang/String;
    //   6301: sipush #-14573
    //   6304: sipush #-17598
    //   6307: invokestatic a : (II)Ljava/lang/String;
    //   6310: invokevirtual startsWith : (Ljava/lang/String;)Z
    //   6313: ifne -> 6323
    //   6316: goto -> 6323
    //   6319: invokestatic a : (Ljava/lang/Throwable;)Ljava/lang/Throwable;
    //   6322: athrow
    //   6323: aload #8
    //   6325: iconst_1
    //   6326: invokevirtual setAccessible : (Z)V
    //   6329: aload #8
    //   6331: aconst_null
    //   6332: invokevirtual get : (Ljava/lang/Object;)Ljava/lang/Object;
    //   6335: pop
    //   6336: iinc #7, 1
    //   6339: iload_2
    //   6340: ifne -> 6201
    //   6343: sipush #-14570
    //   6346: sipush #7661
    //   6349: invokestatic a : (II)Ljava/lang/String;
    //   6352: invokestatic forName : (Ljava/lang/String;)Ljava/lang/Class;
    //   6355: invokevirtual getDeclaredMethods : ()[Ljava/lang/reflect/Method;
    //   6358: astore #5
    //   6360: aload #5
    //   6362: arraylength
    //   6363: istore #6
    //   6365: iconst_0
    //   6366: istore #7
    //   6368: iload #7
    //   6370: iload #6
    //   6372: if_icmpge -> 6509
    //   6375: aload #5
    //   6377: iload #7
    //   6379: aaload
    //   6380: astore #8
    //   6382: aload #8
    //   6384: invokevirtual getParameterTypes : ()[Ljava/lang/Class;
    //   6387: pop
    //   6388: aload #8
    //   6390: invokevirtual getModifiers : ()I
    //   6393: invokestatic isStatic : (I)Z
    //   6396: ifeq -> 6495
    //   6399: aload #8
    //   6401: invokevirtual getParameterTypes : ()[Ljava/lang/Class;
    //   6404: arraylength
    //   6405: iconst_2
    //   6406: if_icmpne -> 6495
    //   6409: goto -> 6416
    //   6412: invokestatic a : (Ljava/lang/Throwable;)Ljava/lang/Throwable;
    //   6415: athrow
    //   6416: aload #8
    //   6418: invokevirtual getReturnType : ()Ljava/lang/Class;
    //   6421: getstatic java/lang/Boolean.TYPE : Ljava/lang/Class;
    //   6424: if_acmpne -> 6495
    //   6427: goto -> 6434
    //   6430: invokestatic a : (Ljava/lang/Throwable;)Ljava/lang/Throwable;
    //   6433: athrow
    //   6434: aload #8
    //   6436: iconst_1
    //   6437: invokevirtual setAccessible : (Z)V
    //   6440: aload #8
    //   6442: aconst_null
    //   6443: iconst_2
    //   6444: anewarray java/lang/Object
    //   6447: dup
    //   6448: iconst_0
    //   6449: aload_0
    //   6450: aastore
    //   6451: dup
    //   6452: iconst_1
    //   6453: aload_1
    //   6454: ifnonnull -> 6472
    //   6457: goto -> 6464
    //   6460: invokestatic a : (Ljava/lang/Throwable;)Ljava/lang/Throwable;
    //   6463: athrow
    //   6464: aload_1
    //   6465: goto -> 6479
    //   6468: invokestatic a : (Ljava/lang/Throwable;)Ljava/lang/Throwable;
    //   6471: athrow
    //   6472: aload_1
    //   6473: checkcast [B
    //   6476: invokevirtual clone : ()Ljava/lang/Object;
    //   6479: aastore
    //   6480: invokevirtual invoke : (Ljava/lang/Object;[Ljava/lang/Object;)Ljava/lang/Object;
    //   6483: checkcast java/lang/Boolean
    //   6486: invokevirtual booleanValue : ()Z
    //   6489: istore #4
    //   6491: iload_2
    //   6492: ifne -> 6509
    //   6495: iinc #7, 1
    //   6498: iload_2
    //   6499: ifne -> 6368
    //   6502: goto -> 6509
    //   6505: invokestatic a : (Ljava/lang/Throwable;)Ljava/lang/Throwable;
    //   6508: athrow
    //   6509: goto -> 6851
    //   6512: sipush #-14590
    //   6515: sipush #519
    //   6518: invokestatic a : (II)Ljava/lang/String;
    //   6521: iconst_1
    //   6522: ldc burp/Zxtc
    //   6524: invokevirtual getClassLoader : ()Ljava/lang/ClassLoader;
    //   6527: invokestatic forName : (Ljava/lang/String;ZLjava/lang/ClassLoader;)Ljava/lang/Class;
    //   6530: invokevirtual getDeclaredFields : ()[Ljava/lang/reflect/Field;
    //   6533: astore #5
    //   6535: aload #5
    //   6537: arraylength
    //   6538: istore #6
    //   6540: iconst_0
    //   6541: istore #7
    //   6543: iload #7
    //   6545: iload #6
    //   6547: if_icmpge -> 6685
    //   6550: aload #5
    //   6552: iload #7
    //   6554: aaload
    //   6555: astore #8
    //   6557: aload #8
    //   6559: invokevirtual getModifiers : ()I
    //   6562: invokestatic isStatic : (I)Z
    //   6565: ifne -> 6575
    //   6568: goto -> 6678
    //   6571: invokestatic a : (Ljava/lang/Throwable;)Ljava/lang/Throwable;
    //   6574: athrow
    //   6575: aload #8
    //   6577: invokevirtual getType : ()Ljava/lang/Class;
    //   6580: astore #9
    //   6582: aload #9
    //   6584: ifnull -> 6665
    //   6587: aload #9
    //   6589: invokevirtual isPrimitive : ()Z
    //   6592: ifne -> 6665
    //   6595: goto -> 6602
    //   6598: invokestatic a : (Ljava/lang/Throwable;)Ljava/lang/Throwable;
    //   6601: athrow
    //   6602: aload #9
    //   6604: invokevirtual getPackage : ()Ljava/lang/Package;
    //   6607: ifnull -> 6665
    //   6610: goto -> 6617
    //   6613: invokestatic a : (Ljava/lang/Throwable;)Ljava/lang/Throwable;
    //   6616: athrow
    //   6617: aload #9
    //   6619: invokevirtual getPackage : ()Ljava/lang/Package;
    //   6622: invokevirtual getName : ()Ljava/lang/String;
    //   6625: ifnull -> 6665
    //   6628: goto -> 6635
    //   6631: invokestatic a : (Ljava/lang/Throwable;)Ljava/lang/Throwable;
    //   6634: athrow
    //   6635: aload #9
    //   6637: invokevirtual getPackage : ()Ljava/lang/Package;
    //   6640: invokevirtual getName : ()Ljava/lang/String;
    //   6643: sipush #-14573
    //   6646: sipush #-17598
    //   6649: invokestatic a : (II)Ljava/lang/String;
    //   6652: invokevirtual startsWith : (Ljava/lang/String;)Z
    //   6655: ifne -> 6665
    //   6658: goto -> 6665
    //   6661: invokestatic a : (Ljava/lang/Throwable;)Ljava/lang/Throwable;
    //   6664: athrow
    //   6665: aload #8
    //   6667: iconst_1
    //   6668: invokevirtual setAccessible : (Z)V
    //   6671: aload #8
    //   6673: aconst_null
    //   6674: invokevirtual get : (Ljava/lang/Object;)Ljava/lang/Object;
    //   6677: pop
    //   6678: iinc #7, 1
    //   6681: iload_2
    //   6682: ifne -> 6543
    //   6685: sipush #-14571
    //   6688: sipush #26168
    //   6691: invokestatic a : (II)Ljava/lang/String;
    //   6694: invokestatic forName : (Ljava/lang/String;)Ljava/lang/Class;
    //   6697: invokevirtual getDeclaredMethods : ()[Ljava/lang/reflect/Method;
    //   6700: astore #5
    //   6702: aload #5
    //   6704: arraylength
    //   6705: istore #6
    //   6707: iconst_0
    //   6708: istore #7
    //   6710: iload #7
    //   6712: iload #6
    //   6714: if_icmpge -> 6851
    //   6717: aload #5
    //   6719: iload #7
    //   6721: aaload
    //   6722: astore #8
    //   6724: aload #8
    //   6726: invokevirtual getParameterTypes : ()[Ljava/lang/Class;
    //   6729: pop
    //   6730: aload #8
    //   6732: invokevirtual getModifiers : ()I
    //   6735: invokestatic isStatic : (I)Z
    //   6738: ifeq -> 6837
    //   6741: aload #8
    //   6743: invokevirtual getParameterTypes : ()[Ljava/lang/Class;
    //   6746: arraylength
    //   6747: iconst_2
    //   6748: if_icmpne -> 6837
    //   6751: goto -> 6758
    //   6754: invokestatic a : (Ljava/lang/Throwable;)Ljava/lang/Throwable;
    //   6757: athrow
    //   6758: aload #8
    //   6760: invokevirtual getReturnType : ()Ljava/lang/Class;
    //   6763: getstatic java/lang/Boolean.TYPE : Ljava/lang/Class;
    //   6766: if_acmpne -> 6837
    //   6769: goto -> 6776
    //   6772: invokestatic a : (Ljava/lang/Throwable;)Ljava/lang/Throwable;
    //   6775: athrow
    //   6776: aload #8
    //   6778: iconst_1
    //   6779: invokevirtual setAccessible : (Z)V
    //   6782: aload #8
    //   6784: aconst_null
    //   6785: iconst_2
    //   6786: anewarray java/lang/Object
    //   6789: dup
    //   6790: iconst_0
    //   6791: aload_0
    //   6792: aastore
    //   6793: dup
    //   6794: iconst_1
    //   6795: aload_1
    //   6796: ifnonnull -> 6814
    //   6799: goto -> 6806
    //   6802: invokestatic a : (Ljava/lang/Throwable;)Ljava/lang/Throwable;
    //   6805: athrow
    //   6806: aload_1
    //   6807: goto -> 6821
    //   6810: invokestatic a : (Ljava/lang/Throwable;)Ljava/lang/Throwable;
    //   6813: athrow
    //   6814: aload_1
    //   6815: checkcast [B
    //   6818: invokevirtual clone : ()Ljava/lang/Object;
    //   6821: aastore
    //   6822: invokevirtual invoke : (Ljava/lang/Object;[Ljava/lang/Object;)Ljava/lang/Object;
    //   6825: checkcast java/lang/Boolean
    //   6828: invokevirtual booleanValue : ()Z
    //   6831: istore #4
    //   6833: iload_2
    //   6834: ifne -> 6851
    //   6837: iinc #7, 1
    //   6840: iload_2
    //   6841: ifne -> 6710
    //   6844: goto -> 6851
    //   6847: invokestatic a : (Ljava/lang/Throwable;)Ljava/lang/Throwable;
    //   6850: athrow
    //   6851: iload #4
    //   6853: ifeq -> 6859
    //   6856: iload #4
    //   6858: ireturn
    //   6859: getstatic burp/Zgtd.Zj : Ljava/lang/String;
    //   6862: getstatic burp/Zeqx.Zh : Ljava/lang/Object;
    //   6865: checkcast java/math/BigInteger
    //   6868: invokevirtual intValue : ()I
    //   6871: bipush #32
    //   6873: irem
    //   6874: invokestatic abs : (I)I
    //   6877: invokevirtual charAt : (I)C
    //   6880: getstatic burp/Zs_m.Zt : Ljava/lang/String;
    //   6883: getstatic burp/Zttd.Zi : Ljava/lang/Object;
    //   6886: checkcast java/math/BigInteger
    //   6889: invokevirtual intValue : ()I
    //   6892: bipush #32
    //   6894: irem
    //   6895: invokestatic abs : (I)I
    //   6898: invokevirtual charAt : (I)C
    //   6901: if_icmple -> 7247
    //   6904: sipush #-14567
    //   6907: sipush #-11153
    //   6910: invokestatic a : (II)Ljava/lang/String;
    //   6913: iconst_1
    //   6914: ldc burp/Zl8s
    //   6916: invokevirtual getClassLoader : ()Ljava/lang/ClassLoader;
    //   6919: invokestatic forName : (Ljava/lang/String;ZLjava/lang/ClassLoader;)Ljava/lang/Class;
    //   6922: invokevirtual getDeclaredFields : ()[Ljava/lang/reflect/Field;
    //   6925: astore #5
    //   6927: aload #5
    //   6929: arraylength
    //   6930: istore #6
    //   6932: iconst_0
    //   6933: istore #7
    //   6935: iload #7
    //   6937: iload #6
    //   6939: if_icmpge -> 7077
    //   6942: aload #5
    //   6944: iload #7
    //   6946: aaload
    //   6947: astore #8
    //   6949: aload #8
    //   6951: invokevirtual getModifiers : ()I
    //   6954: invokestatic isStatic : (I)Z
    //   6957: ifne -> 6967
    //   6960: goto -> 7070
    //   6963: invokestatic a : (Ljava/lang/Throwable;)Ljava/lang/Throwable;
    //   6966: athrow
    //   6967: aload #8
    //   6969: invokevirtual getType : ()Ljava/lang/Class;
    //   6972: astore #9
    //   6974: aload #9
    //   6976: ifnull -> 7057
    //   6979: aload #9
    //   6981: invokevirtual isPrimitive : ()Z
    //   6984: ifne -> 7057
    //   6987: goto -> 6994
    //   6990: invokestatic a : (Ljava/lang/Throwable;)Ljava/lang/Throwable;
    //   6993: athrow
    //   6994: aload #9
    //   6996: invokevirtual getPackage : ()Ljava/lang/Package;
    //   6999: ifnull -> 7057
    //   7002: goto -> 7009
    //   7005: invokestatic a : (Ljava/lang/Throwable;)Ljava/lang/Throwable;
    //   7008: athrow
    //   7009: aload #9
    //   7011: invokevirtual getPackage : ()Ljava/lang/Package;
    //   7014: invokevirtual getName : ()Ljava/lang/String;
    //   7017: ifnull -> 7057
    //   7020: goto -> 7027
    //   7023: invokestatic a : (Ljava/lang/Throwable;)Ljava/lang/Throwable;
    //   7026: athrow
    //   7027: aload #9
    //   7029: invokevirtual getPackage : ()Ljava/lang/Package;
    //   7032: invokevirtual getName : ()Ljava/lang/String;
    //   7035: sipush #-14573
    //   7038: sipush #-17598
    //   7041: invokestatic a : (II)Ljava/lang/String;
    //   7044: invokevirtual startsWith : (Ljava/lang/String;)Z
    //   7047: ifne -> 7057
    //   7050: goto -> 7057
    //   7053: invokestatic a : (Ljava/lang/Throwable;)Ljava/lang/Throwable;
    //   7056: athrow
    //   7057: aload #8
    //   7059: iconst_1
    //   7060: invokevirtual setAccessible : (Z)V
    //   7063: aload #8
    //   7065: aconst_null
    //   7066: invokevirtual get : (Ljava/lang/Object;)Ljava/lang/Object;
    //   7069: pop
    //   7070: iinc #7, 1
    //   7073: iload_2
    //   7074: ifne -> 6935
    //   7077: sipush #-14583
    //   7080: sipush #9362
    //   7083: invokestatic a : (II)Ljava/lang/String;
    //   7086: invokestatic forName : (Ljava/lang/String;)Ljava/lang/Class;
    //   7089: invokevirtual getDeclaredMethods : ()[Ljava/lang/reflect/Method;
    //   7092: astore #5
    //   7094: aload #5
    //   7096: arraylength
    //   7097: istore #6
    //   7099: iconst_0
    //   7100: istore #7
    //   7102: iload #7
    //   7104: iload #6
    //   7106: if_icmpge -> 7243
    //   7109: aload #5
    //   7111: iload #7
    //   7113: aaload
    //   7114: astore #8
    //   7116: aload #8
    //   7118: invokevirtual getParameterTypes : ()[Ljava/lang/Class;
    //   7121: pop
    //   7122: aload #8
    //   7124: invokevirtual getModifiers : ()I
    //   7127: invokestatic isStatic : (I)Z
    //   7130: ifeq -> 7229
    //   7133: aload #8
    //   7135: invokevirtual getParameterTypes : ()[Ljava/lang/Class;
    //   7138: arraylength
    //   7139: iconst_2
    //   7140: if_icmpne -> 7229
    //   7143: goto -> 7150
    //   7146: invokestatic a : (Ljava/lang/Throwable;)Ljava/lang/Throwable;
    //   7149: athrow
    //   7150: aload #8
    //   7152: invokevirtual getReturnType : ()Ljava/lang/Class;
    //   7155: getstatic java/lang/Boolean.TYPE : Ljava/lang/Class;
    //   7158: if_acmpne -> 7229
    //   7161: goto -> 7168
    //   7164: invokestatic a : (Ljava/lang/Throwable;)Ljava/lang/Throwable;
    //   7167: athrow
    //   7168: aload #8
    //   7170: iconst_1
    //   7171: invokevirtual setAccessible : (Z)V
    //   7174: aload #8
    //   7176: aconst_null
    //   7177: iconst_2
    //   7178: anewarray java/lang/Object
    //   7181: dup
    //   7182: iconst_0
    //   7183: aload_0
    //   7184: aastore
    //   7185: dup
    //   7186: iconst_1
    //   7187: aload_1
    //   7188: ifnonnull -> 7206
    //   7191: goto -> 7198
    //   7194: invokestatic a : (Ljava/lang/Throwable;)Ljava/lang/Throwable;
    //   7197: athrow
    //   7198: aload_1
    //   7199: goto -> 7213
    //   7202: invokestatic a : (Ljava/lang/Throwable;)Ljava/lang/Throwable;
    //   7205: athrow
    //   7206: aload_1
    //   7207: checkcast [B
    //   7210: invokevirtual clone : ()Ljava/lang/Object;
    //   7213: aastore
    //   7214: invokevirtual invoke : (Ljava/lang/Object;[Ljava/lang/Object;)Ljava/lang/Object;
    //   7217: checkcast java/lang/Boolean
    //   7220: invokevirtual booleanValue : ()Z
    //   7223: istore #4
    //   7225: iload_2
    //   7226: ifne -> 7243
    //   7229: iinc #7, 1
    //   7232: iload_2
    //   7233: ifne -> 7102
    //   7236: goto -> 7243
    //   7239: invokestatic a : (Ljava/lang/Throwable;)Ljava/lang/Throwable;
    //   7242: athrow
    //   7243: iload_2
    //   7244: ifne -> 7586
    //   7247: sipush #-14585
    //   7250: sipush #-27175
    //   7253: invokestatic a : (II)Ljava/lang/String;
    //   7256: iconst_1
    //   7257: ldc burp/Zxjw
    //   7259: invokevirtual getClassLoader : ()Ljava/lang/ClassLoader;
    //   7262: invokestatic forName : (Ljava/lang/String;ZLjava/lang/ClassLoader;)Ljava/lang/Class;
    //   7265: invokevirtual getDeclaredFields : ()[Ljava/lang/reflect/Field;
    //   7268: astore #5
    //   7270: aload #5
    //   7272: arraylength
    //   7273: istore #6
    //   7275: iconst_0
    //   7276: istore #7
    //   7278: iload #7
    //   7280: iload #6
    //   7282: if_icmpge -> 7420
    //   7285: aload #5
    //   7287: iload #7
    //   7289: aaload
    //   7290: astore #8
    //   7292: aload #8
    //   7294: invokevirtual getModifiers : ()I
    //   7297: invokestatic isStatic : (I)Z
    //   7300: ifne -> 7310
    //   7303: goto -> 7413
    //   7306: invokestatic a : (Ljava/lang/Throwable;)Ljava/lang/Throwable;
    //   7309: athrow
    //   7310: aload #8
    //   7312: invokevirtual getType : ()Ljava/lang/Class;
    //   7315: astore #9
    //   7317: aload #9
    //   7319: ifnull -> 7400
    //   7322: aload #9
    //   7324: invokevirtual isPrimitive : ()Z
    //   7327: ifne -> 7400
    //   7330: goto -> 7337
    //   7333: invokestatic a : (Ljava/lang/Throwable;)Ljava/lang/Throwable;
    //   7336: athrow
    //   7337: aload #9
    //   7339: invokevirtual getPackage : ()Ljava/lang/Package;
    //   7342: ifnull -> 7400
    //   7345: goto -> 7352
    //   7348: invokestatic a : (Ljava/lang/Throwable;)Ljava/lang/Throwable;
    //   7351: athrow
    //   7352: aload #9
    //   7354: invokevirtual getPackage : ()Ljava/lang/Package;
    //   7357: invokevirtual getName : ()Ljava/lang/String;
    //   7360: ifnull -> 7400
    //   7363: goto -> 7370
    //   7366: invokestatic a : (Ljava/lang/Throwable;)Ljava/lang/Throwable;
    //   7369: athrow
    //   7370: aload #9
    //   7372: invokevirtual getPackage : ()Ljava/lang/Package;
    //   7375: invokevirtual getName : ()Ljava/lang/String;
    //   7378: sipush #-14573
    //   7381: sipush #-17598
    //   7384: invokestatic a : (II)Ljava/lang/String;
    //   7387: invokevirtual startsWith : (Ljava/lang/String;)Z
    //   7390: ifne -> 7400
    //   7393: goto -> 7400
    //   7396: invokestatic a : (Ljava/lang/Throwable;)Ljava/lang/Throwable;
    //   7399: athrow
    //   7400: aload #8
    //   7402: iconst_1
    //   7403: invokevirtual setAccessible : (Z)V
    //   7406: aload #8
    //   7408: aconst_null
    //   7409: invokevirtual get : (Ljava/lang/Object;)Ljava/lang/Object;
    //   7412: pop
    //   7413: iinc #7, 1
    //   7416: iload_2
    //   7417: ifne -> 7278
    //   7420: sipush #-14587
    //   7423: sipush #-16237
    //   7426: invokestatic a : (II)Ljava/lang/String;
    //   7429: invokestatic forName : (Ljava/lang/String;)Ljava/lang/Class;
    //   7432: invokevirtual getDeclaredMethods : ()[Ljava/lang/reflect/Method;
    //   7435: astore #5
    //   7437: aload #5
    //   7439: arraylength
    //   7440: istore #6
    //   7442: iconst_0
    //   7443: istore #7
    //   7445: iload #7
    //   7447: iload #6
    //   7449: if_icmpge -> 7586
    //   7452: aload #5
    //   7454: iload #7
    //   7456: aaload
    //   7457: astore #8
    //   7459: aload #8
    //   7461: invokevirtual getParameterTypes : ()[Ljava/lang/Class;
    //   7464: pop
    //   7465: aload #8
    //   7467: invokevirtual getModifiers : ()I
    //   7470: invokestatic isStatic : (I)Z
    //   7473: ifeq -> 7572
    //   7476: aload #8
    //   7478: invokevirtual getParameterTypes : ()[Ljava/lang/Class;
    //   7481: arraylength
    //   7482: iconst_2
    //   7483: if_icmpne -> 7572
    //   7486: goto -> 7493
    //   7489: invokestatic a : (Ljava/lang/Throwable;)Ljava/lang/Throwable;
    //   7492: athrow
    //   7493: aload #8
    //   7495: invokevirtual getReturnType : ()Ljava/lang/Class;
    //   7498: getstatic java/lang/Boolean.TYPE : Ljava/lang/Class;
    //   7501: if_acmpne -> 7572
    //   7504: goto -> 7511
    //   7507: invokestatic a : (Ljava/lang/Throwable;)Ljava/lang/Throwable;
    //   7510: athrow
    //   7511: aload #8
    //   7513: iconst_1
    //   7514: invokevirtual setAccessible : (Z)V
    //   7517: aload #8
    //   7519: aconst_null
    //   7520: iconst_2
    //   7521: anewarray java/lang/Object
    //   7524: dup
    //   7525: iconst_0
    //   7526: aload_0
    //   7527: aastore
    //   7528: dup
    //   7529: iconst_1
    //   7530: aload_1
    //   7531: ifnonnull -> 7549
    //   7534: goto -> 7541
    //   7537: invokestatic a : (Ljava/lang/Throwable;)Ljava/lang/Throwable;
    //   7540: athrow
    //   7541: aload_1
    //   7542: goto -> 7556
    //   7545: invokestatic a : (Ljava/lang/Throwable;)Ljava/lang/Throwable;
    //   7548: athrow
    //   7549: aload_1
    //   7550: checkcast [B
    //   7553: invokevirtual clone : ()Ljava/lang/Object;
    //   7556: aastore
    //   7557: invokevirtual invoke : (Ljava/lang/Object;[Ljava/lang/Object;)Ljava/lang/Object;
    //   7560: checkcast java/lang/Boolean
    //   7563: invokevirtual booleanValue : ()Z
    //   7566: istore #4
    //   7568: iload_2
    //   7569: ifne -> 7586
    //   7572: iinc #7, 1
    //   7575: iload_2
    //   7576: ifne -> 7445
    //   7579: goto -> 7586
    //   7582: invokestatic a : (Ljava/lang/Throwable;)Ljava/lang/Throwable;
    //   7585: athrow
    //   7586: iload #4
    //   7588: ifeq -> 7594
    //   7591: iload #4
    //   7593: ireturn
    //   7594: getstatic burp/Ztgv.ZC : Ljava/lang/String;
    //   7597: getstatic burp/Zt5t.Za : Ljava/lang/Object;
    //   7600: checkcast java/math/BigInteger
    //   7603: invokevirtual intValue : ()I
    //   7606: bipush #32
    //   7608: irem
    //   7609: invokestatic abs : (I)I
    //   7612: invokevirtual charAt : (I)C
    //   7615: getstatic burp/Zkhf.Zb : Ljava/lang/String;
    //   7618: getstatic burp/Zt9f.Zl : Ljava/lang/Object;
    //   7621: checkcast java/math/BigInteger
    //   7624: invokevirtual intValue : ()I
    //   7627: bipush #32
    //   7629: irem
    //   7630: invokestatic abs : (I)I
    //   7633: invokevirtual charAt : (I)C
    //   7636: if_icmpgt -> 7982
    //   7639: sipush #-14589
    //   7642: sipush #8631
    //   7645: invokestatic a : (II)Ljava/lang/String;
    //   7648: iconst_1
    //   7649: ldc burp/Zl2t
    //   7651: invokevirtual getClassLoader : ()Ljava/lang/ClassLoader;
    //   7654: invokestatic forName : (Ljava/lang/String;ZLjava/lang/ClassLoader;)Ljava/lang/Class;
    //   7657: invokevirtual getDeclaredFields : ()[Ljava/lang/reflect/Field;
    //   7660: astore #5
    //   7662: aload #5
    //   7664: arraylength
    //   7665: istore #6
    //   7667: iconst_0
    //   7668: istore #7
    //   7670: iload #7
    //   7672: iload #6
    //   7674: if_icmpge -> 7812
    //   7677: aload #5
    //   7679: iload #7
    //   7681: aaload
    //   7682: astore #8
    //   7684: aload #8
    //   7686: invokevirtual getModifiers : ()I
    //   7689: invokestatic isStatic : (I)Z
    //   7692: ifne -> 7702
    //   7695: goto -> 7805
    //   7698: invokestatic a : (Ljava/lang/Throwable;)Ljava/lang/Throwable;
    //   7701: athrow
    //   7702: aload #8
    //   7704: invokevirtual getType : ()Ljava/lang/Class;
    //   7707: astore #9
    //   7709: aload #9
    //   7711: ifnull -> 7792
    //   7714: aload #9
    //   7716: invokevirtual isPrimitive : ()Z
    //   7719: ifne -> 7792
    //   7722: goto -> 7729
    //   7725: invokestatic a : (Ljava/lang/Throwable;)Ljava/lang/Throwable;
    //   7728: athrow
    //   7729: aload #9
    //   7731: invokevirtual getPackage : ()Ljava/lang/Package;
    //   7734: ifnull -> 7792
    //   7737: goto -> 7744
    //   7740: invokestatic a : (Ljava/lang/Throwable;)Ljava/lang/Throwable;
    //   7743: athrow
    //   7744: aload #9
    //   7746: invokevirtual getPackage : ()Ljava/lang/Package;
    //   7749: invokevirtual getName : ()Ljava/lang/String;
    //   7752: ifnull -> 7792
    //   7755: goto -> 7762
    //   7758: invokestatic a : (Ljava/lang/Throwable;)Ljava/lang/Throwable;
    //   7761: athrow
    //   7762: aload #9
    //   7764: invokevirtual getPackage : ()Ljava/lang/Package;
    //   7767: invokevirtual getName : ()Ljava/lang/String;
    //   7770: sipush #-14573
    //   7773: sipush #-17598
    //   7776: invokestatic a : (II)Ljava/lang/String;
    //   7779: invokevirtual startsWith : (Ljava/lang/String;)Z
    //   7782: ifne -> 7792
    //   7785: goto -> 7792
    //   7788: invokestatic a : (Ljava/lang/Throwable;)Ljava/lang/Throwable;
    //   7791: athrow
    //   7792: aload #8
    //   7794: iconst_1
    //   7795: invokevirtual setAccessible : (Z)V
    //   7798: aload #8
    //   7800: aconst_null
    //   7801: invokevirtual get : (Ljava/lang/Object;)Ljava/lang/Object;
    //   7804: pop
    //   7805: iinc #7, 1
    //   7808: iload_2
    //   7809: ifne -> 7670
    //   7812: sipush #-14561
    //   7815: sipush #-5499
    //   7818: invokestatic a : (II)Ljava/lang/String;
    //   7821: invokestatic forName : (Ljava/lang/String;)Ljava/lang/Class;
    //   7824: invokevirtual getDeclaredMethods : ()[Ljava/lang/reflect/Method;
    //   7827: astore #5
    //   7829: aload #5
    //   7831: arraylength
    //   7832: istore #6
    //   7834: iconst_0
    //   7835: istore #7
    //   7837: iload #7
    //   7839: iload #6
    //   7841: if_icmpge -> 7978
    //   7844: aload #5
    //   7846: iload #7
    //   7848: aaload
    //   7849: astore #8
    //   7851: aload #8
    //   7853: invokevirtual getParameterTypes : ()[Ljava/lang/Class;
    //   7856: pop
    //   7857: aload #8
    //   7859: invokevirtual getModifiers : ()I
    //   7862: invokestatic isStatic : (I)Z
    //   7865: ifeq -> 7964
    //   7868: aload #8
    //   7870: invokevirtual getParameterTypes : ()[Ljava/lang/Class;
    //   7873: arraylength
    //   7874: iconst_2
    //   7875: if_icmpne -> 7964
    //   7878: goto -> 7885
    //   7881: invokestatic a : (Ljava/lang/Throwable;)Ljava/lang/Throwable;
    //   7884: athrow
    //   7885: aload #8
    //   7887: invokevirtual getReturnType : ()Ljava/lang/Class;
    //   7890: getstatic java/lang/Boolean.TYPE : Ljava/lang/Class;
    //   7893: if_acmpne -> 7964
    //   7896: goto -> 7903
    //   7899: invokestatic a : (Ljava/lang/Throwable;)Ljava/lang/Throwable;
    //   7902: athrow
    //   7903: aload #8
    //   7905: iconst_1
    //   7906: invokevirtual setAccessible : (Z)V
    //   7909: aload #8
    //   7911: aconst_null
    //   7912: iconst_2
    //   7913: anewarray java/lang/Object
    //   7916: dup
    //   7917: iconst_0
    //   7918: aload_0
    //   7919: aastore
    //   7920: dup
    //   7921: iconst_1
    //   7922: aload_1
    //   7923: ifnonnull -> 7941
    //   7926: goto -> 7933
    //   7929: invokestatic a : (Ljava/lang/Throwable;)Ljava/lang/Throwable;
    //   7932: athrow
    //   7933: aload_1
    //   7934: goto -> 7948
    //   7937: invokestatic a : (Ljava/lang/Throwable;)Ljava/lang/Throwable;
    //   7940: athrow
    //   7941: aload_1
    //   7942: checkcast [B
    //   7945: invokevirtual clone : ()Ljava/lang/Object;
    //   7948: aastore
    //   7949: invokevirtual invoke : (Ljava/lang/Object;[Ljava/lang/Object;)Ljava/lang/Object;
    //   7952: checkcast java/lang/Boolean
    //   7955: invokevirtual booleanValue : ()Z
    //   7958: istore #4
    //   7960: iload_2
    //   7961: ifne -> 7978
    //   7964: iinc #7, 1
    //   7967: iload_2
    //   7968: ifne -> 7837
    //   7971: goto -> 7978
    //   7974: invokestatic a : (Ljava/lang/Throwable;)Ljava/lang/Throwable;
    //   7977: athrow
    //   7978: iload_2
    //   7979: ifne -> 8321
    //   7982: sipush #-14564
    //   7985: sipush #12241
    //   7988: invokestatic a : (II)Ljava/lang/String;
    //   7991: iconst_1
    //   7992: ldc burp/Zl3n
    //   7994: invokevirtual getClassLoader : ()Ljava/lang/ClassLoader;
    //   7997: invokestatic forName : (Ljava/lang/String;ZLjava/lang/ClassLoader;)Ljava/lang/Class;
    //   8000: invokevirtual getDeclaredFields : ()[Ljava/lang/reflect/Field;
    //   8003: astore #5
    //   8005: aload #5
    //   8007: arraylength
    //   8008: istore #6
    //   8010: iconst_0
    //   8011: istore #7
    //   8013: iload #7
    //   8015: iload #6
    //   8017: if_icmpge -> 8155
    //   8020: aload #5
    //   8022: iload #7
    //   8024: aaload
    //   8025: astore #8
    //   8027: aload #8
    //   8029: invokevirtual getModifiers : ()I
    //   8032: invokestatic isStatic : (I)Z
    //   8035: ifne -> 8045
    //   8038: goto -> 8148
    //   8041: invokestatic a : (Ljava/lang/Throwable;)Ljava/lang/Throwable;
    //   8044: athrow
    //   8045: aload #8
    //   8047: invokevirtual getType : ()Ljava/lang/Class;
    //   8050: astore #9
    //   8052: aload #9
    //   8054: ifnull -> 8135
    //   8057: aload #9
    //   8059: invokevirtual isPrimitive : ()Z
    //   8062: ifne -> 8135
    //   8065: goto -> 8072
    //   8068: invokestatic a : (Ljava/lang/Throwable;)Ljava/lang/Throwable;
    //   8071: athrow
    //   8072: aload #9
    //   8074: invokevirtual getPackage : ()Ljava/lang/Package;
    //   8077: ifnull -> 8135
    //   8080: goto -> 8087
    //   8083: invokestatic a : (Ljava/lang/Throwable;)Ljava/lang/Throwable;
    //   8086: athrow
    //   8087: aload #9
    //   8089: invokevirtual getPackage : ()Ljava/lang/Package;
    //   8092: invokevirtual getName : ()Ljava/lang/String;
    //   8095: ifnull -> 8135
    //   8098: goto -> 8105
    //   8101: invokestatic a : (Ljava/lang/Throwable;)Ljava/lang/Throwable;
    //   8104: athrow
    //   8105: aload #9
    //   8107: invokevirtual getPackage : ()Ljava/lang/Package;
    //   8110: invokevirtual getName : ()Ljava/lang/String;
    //   8113: sipush #-14573
    //   8116: sipush #-17598
    //   8119: invokestatic a : (II)Ljava/lang/String;
    //   8122: invokevirtual startsWith : (Ljava/lang/String;)Z
    //   8125: ifne -> 8135
    //   8128: goto -> 8135
    //   8131: invokestatic a : (Ljava/lang/Throwable;)Ljava/lang/Throwable;
    //   8134: athrow
    //   8135: aload #8
    //   8137: iconst_1
    //   8138: invokevirtual setAccessible : (Z)V
    //   8141: aload #8
    //   8143: aconst_null
    //   8144: invokevirtual get : (Ljava/lang/Object;)Ljava/lang/Object;
    //   8147: pop
    //   8148: iinc #7, 1
    //   8151: iload_2
    //   8152: ifne -> 8013
    //   8155: sipush #-14592
    //   8158: sipush #29415
    //   8161: invokestatic a : (II)Ljava/lang/String;
    //   8164: invokestatic forName : (Ljava/lang/String;)Ljava/lang/Class;
    //   8167: invokevirtual getDeclaredMethods : ()[Ljava/lang/reflect/Method;
    //   8170: astore #5
    //   8172: aload #5
    //   8174: arraylength
    //   8175: istore #6
    //   8177: iconst_0
    //   8178: istore #7
    //   8180: iload #7
    //   8182: iload #6
    //   8184: if_icmpge -> 8321
    //   8187: aload #5
    //   8189: iload #7
    //   8191: aaload
    //   8192: astore #8
    //   8194: aload #8
    //   8196: invokevirtual getParameterTypes : ()[Ljava/lang/Class;
    //   8199: pop
    //   8200: aload #8
    //   8202: invokevirtual getModifiers : ()I
    //   8205: invokestatic isStatic : (I)Z
    //   8208: ifeq -> 8307
    //   8211: aload #8
    //   8213: invokevirtual getParameterTypes : ()[Ljava/lang/Class;
    //   8216: arraylength
    //   8217: iconst_2
    //   8218: if_icmpne -> 8307
    //   8221: goto -> 8228
    //   8224: invokestatic a : (Ljava/lang/Throwable;)Ljava/lang/Throwable;
    //   8227: athrow
    //   8228: aload #8
    //   8230: invokevirtual getReturnType : ()Ljava/lang/Class;
    //   8233: getstatic java/lang/Boolean.TYPE : Ljava/lang/Class;
    //   8236: if_acmpne -> 8307
    //   8239: goto -> 8246
    //   8242: invokestatic a : (Ljava/lang/Throwable;)Ljava/lang/Throwable;
    //   8245: athrow
    //   8246: aload #8
    //   8248: iconst_1
    //   8249: invokevirtual setAccessible : (Z)V
    //   8252: aload #8
    //   8254: aconst_null
    //   8255: iconst_2
    //   8256: anewarray java/lang/Object
    //   8259: dup
    //   8260: iconst_0
    //   8261: aload_0
    //   8262: aastore
    //   8263: dup
    //   8264: iconst_1
    //   8265: aload_1
    //   8266: ifnonnull -> 8284
    //   8269: goto -> 8276
    //   8272: invokestatic a : (Ljava/lang/Throwable;)Ljava/lang/Throwable;
    //   8275: athrow
    //   8276: aload_1
    //   8277: goto -> 8291
    //   8280: invokestatic a : (Ljava/lang/Throwable;)Ljava/lang/Throwable;
    //   8283: athrow
    //   8284: aload_1
    //   8285: checkcast [B
    //   8288: invokevirtual clone : ()Ljava/lang/Object;
    //   8291: aastore
    //   8292: invokevirtual invoke : (Ljava/lang/Object;[Ljava/lang/Object;)Ljava/lang/Object;
    //   8295: checkcast java/lang/Boolean
    //   8298: invokevirtual booleanValue : ()Z
    //   8301: istore #4
    //   8303: iload_2
    //   8304: ifne -> 8321
    //   8307: iinc #7, 1
    //   8310: iload_2
    //   8311: ifne -> 8180
    //   8314: goto -> 8321
    //   8317: invokestatic a : (Ljava/lang/Throwable;)Ljava/lang/Throwable;
    //   8320: athrow
    //   8321: iload #4
    //   8323: ifeq -> 8329
    //   8326: iload #4
    //   8328: ireturn
    //   8329: getstatic burp/Zrm6.ZV : Ljava/lang/String;
    //   8332: getstatic burp/Zezi.ZQ : Ljava/lang/Object;
    //   8335: checkcast java/math/BigInteger
    //   8338: invokevirtual intValue : ()I
    //   8341: bipush #32
    //   8343: irem
    //   8344: invokestatic abs : (I)I
    //   8347: invokevirtual charAt : (I)C
    //   8350: getstatic burp/Zl7x.Zo : Ljava/lang/String;
    //   8353: getstatic burp/Zmhq.ZK : Ljava/lang/Object;
    //   8356: checkcast java/math/BigInteger
    //   8359: invokevirtual intValue : ()I
    //   8362: bipush #32
    //   8364: irem
    //   8365: invokestatic abs : (I)I
    //   8368: invokevirtual charAt : (I)C
    //   8371: if_icmple -> 8717
    //   8374: sipush #-14586
    //   8377: sipush #6467
    //   8380: invokestatic a : (II)Ljava/lang/String;
    //   8383: iconst_1
    //   8384: ldc burp/Zth7
    //   8386: invokevirtual getClassLoader : ()Ljava/lang/ClassLoader;
    //   8389: invokestatic forName : (Ljava/lang/String;ZLjava/lang/ClassLoader;)Ljava/lang/Class;
    //   8392: invokevirtual getDeclaredFields : ()[Ljava/lang/reflect/Field;
    //   8395: astore #5
    //   8397: aload #5
    //   8399: arraylength
    //   8400: istore #6
    //   8402: iconst_0
    //   8403: istore #7
    //   8405: iload #7
    //   8407: iload #6
    //   8409: if_icmpge -> 8547
    //   8412: aload #5
    //   8414: iload #7
    //   8416: aaload
    //   8417: astore #8
    //   8419: aload #8
    //   8421: invokevirtual getModifiers : ()I
    //   8424: invokestatic isStatic : (I)Z
    //   8427: ifne -> 8437
    //   8430: goto -> 8540
    //   8433: invokestatic a : (Ljava/lang/Throwable;)Ljava/lang/Throwable;
    //   8436: athrow
    //   8437: aload #8
    //   8439: invokevirtual getType : ()Ljava/lang/Class;
    //   8442: astore #9
    //   8444: aload #9
    //   8446: ifnull -> 8527
    //   8449: aload #9
    //   8451: invokevirtual isPrimitive : ()Z
    //   8454: ifne -> 8527
    //   8457: goto -> 8464
    //   8460: invokestatic a : (Ljava/lang/Throwable;)Ljava/lang/Throwable;
    //   8463: athrow
    //   8464: aload #9
    //   8466: invokevirtual getPackage : ()Ljava/lang/Package;
    //   8469: ifnull -> 8527
    //   8472: goto -> 8479
    //   8475: invokestatic a : (Ljava/lang/Throwable;)Ljava/lang/Throwable;
    //   8478: athrow
    //   8479: aload #9
    //   8481: invokevirtual getPackage : ()Ljava/lang/Package;
    //   8484: invokevirtual getName : ()Ljava/lang/String;
    //   8487: ifnull -> 8527
    //   8490: goto -> 8497
    //   8493: invokestatic a : (Ljava/lang/Throwable;)Ljava/lang/Throwable;
    //   8496: athrow
    //   8497: aload #9
    //   8499: invokevirtual getPackage : ()Ljava/lang/Package;
    //   8502: invokevirtual getName : ()Ljava/lang/String;
    //   8505: sipush #-14573
    //   8508: sipush #-17598
    //   8511: invokestatic a : (II)Ljava/lang/String;
    //   8514: invokevirtual startsWith : (Ljava/lang/String;)Z
    //   8517: ifne -> 8527
    //   8520: goto -> 8527
    //   8523: invokestatic a : (Ljava/lang/Throwable;)Ljava/lang/Throwable;
    //   8526: athrow
    //   8527: aload #8
    //   8529: iconst_1
    //   8530: invokevirtual setAccessible : (Z)V
    //   8533: aload #8
    //   8535: aconst_null
    //   8536: invokevirtual get : (Ljava/lang/Object;)Ljava/lang/Object;
    //   8539: pop
    //   8540: iinc #7, 1
    //   8543: iload_2
    //   8544: ifne -> 8405
    //   8547: sipush #-14581
    //   8550: sipush #-20933
    //   8553: invokestatic a : (II)Ljava/lang/String;
    //   8556: invokestatic forName : (Ljava/lang/String;)Ljava/lang/Class;
    //   8559: invokevirtual getDeclaredMethods : ()[Ljava/lang/reflect/Method;
    //   8562: astore #5
    //   8564: aload #5
    //   8566: arraylength
    //   8567: istore #6
    //   8569: iconst_0
    //   8570: istore #7
    //   8572: iload #7
    //   8574: iload #6
    //   8576: if_icmpge -> 8713
    //   8579: aload #5
    //   8581: iload #7
    //   8583: aaload
    //   8584: astore #8
    //   8586: aload #8
    //   8588: invokevirtual getParameterTypes : ()[Ljava/lang/Class;
    //   8591: pop
    //   8592: aload #8
    //   8594: invokevirtual getModifiers : ()I
    //   8597: invokestatic isStatic : (I)Z
    //   8600: ifeq -> 8699
    //   8603: aload #8
    //   8605: invokevirtual getParameterTypes : ()[Ljava/lang/Class;
    //   8608: arraylength
    //   8609: iconst_2
    //   8610: if_icmpne -> 8699
    //   8613: goto -> 8620
    //   8616: invokestatic a : (Ljava/lang/Throwable;)Ljava/lang/Throwable;
    //   8619: athrow
    //   8620: aload #8
    //   8622: invokevirtual getReturnType : ()Ljava/lang/Class;
    //   8625: getstatic java/lang/Boolean.TYPE : Ljava/lang/Class;
    //   8628: if_acmpne -> 8699
    //   8631: goto -> 8638
    //   8634: invokestatic a : (Ljava/lang/Throwable;)Ljava/lang/Throwable;
    //   8637: athrow
    //   8638: aload #8
    //   8640: iconst_1
    //   8641: invokevirtual setAccessible : (Z)V
    //   8644: aload #8
    //   8646: aconst_null
    //   8647: iconst_2
    //   8648: anewarray java/lang/Object
    //   8651: dup
    //   8652: iconst_0
    //   8653: aload_0
    //   8654: aastore
    //   8655: dup
    //   8656: iconst_1
    //   8657: aload_1
    //   8658: ifnonnull -> 8676
    //   8661: goto -> 8668
    //   8664: invokestatic a : (Ljava/lang/Throwable;)Ljava/lang/Throwable;
    //   8667: athrow
    //   8668: aload_1
    //   8669: goto -> 8683
    //   8672: invokestatic a : (Ljava/lang/Throwable;)Ljava/lang/Throwable;
    //   8675: athrow
    //   8676: aload_1
    //   8677: checkcast [B
    //   8680: invokevirtual clone : ()Ljava/lang/Object;
    //   8683: aastore
    //   8684: invokevirtual invoke : (Ljava/lang/Object;[Ljava/lang/Object;)Ljava/lang/Object;
    //   8687: checkcast java/lang/Boolean
    //   8690: invokevirtual booleanValue : ()Z
    //   8693: istore #4
    //   8695: iload_2
    //   8696: ifne -> 8713
    //   8699: iinc #7, 1
    //   8702: iload_2
    //   8703: ifne -> 8572
    //   8706: goto -> 8713
    //   8709: invokestatic a : (Ljava/lang/Throwable;)Ljava/lang/Throwable;
    //   8712: athrow
    //   8713: iload_2
    //   8714: ifne -> 9056
    //   8717: sipush #-14565
    //   8720: sipush #20838
    //   8723: invokestatic a : (II)Ljava/lang/String;
    //   8726: iconst_1
    //   8727: ldc burp/Zgta
    //   8729: invokevirtual getClassLoader : ()Ljava/lang/ClassLoader;
    //   8732: invokestatic forName : (Ljava/lang/String;ZLjava/lang/ClassLoader;)Ljava/lang/Class;
    //   8735: invokevirtual getDeclaredFields : ()[Ljava/lang/reflect/Field;
    //   8738: astore #5
    //   8740: aload #5
    //   8742: arraylength
    //   8743: istore #6
    //   8745: iconst_0
    //   8746: istore #7
    //   8748: iload #7
    //   8750: iload #6
    //   8752: if_icmpge -> 8890
    //   8755: aload #5
    //   8757: iload #7
    //   8759: aaload
    //   8760: astore #8
    //   8762: aload #8
    //   8764: invokevirtual getModifiers : ()I
    //   8767: invokestatic isStatic : (I)Z
    //   8770: ifne -> 8780
    //   8773: goto -> 8883
    //   8776: invokestatic a : (Ljava/lang/Throwable;)Ljava/lang/Throwable;
    //   8779: athrow
    //   8780: aload #8
    //   8782: invokevirtual getType : ()Ljava/lang/Class;
    //   8785: astore #9
    //   8787: aload #9
    //   8789: ifnull -> 8870
    //   8792: aload #9
    //   8794: invokevirtual isPrimitive : ()Z
    //   8797: ifne -> 8870
    //   8800: goto -> 8807
    //   8803: invokestatic a : (Ljava/lang/Throwable;)Ljava/lang/Throwable;
    //   8806: athrow
    //   8807: aload #9
    //   8809: invokevirtual getPackage : ()Ljava/lang/Package;
    //   8812: ifnull -> 8870
    //   8815: goto -> 8822
    //   8818: invokestatic a : (Ljava/lang/Throwable;)Ljava/lang/Throwable;
    //   8821: athrow
    //   8822: aload #9
    //   8824: invokevirtual getPackage : ()Ljava/lang/Package;
    //   8827: invokevirtual getName : ()Ljava/lang/String;
    //   8830: ifnull -> 8870
    //   8833: goto -> 8840
    //   8836: invokestatic a : (Ljava/lang/Throwable;)Ljava/lang/Throwable;
    //   8839: athrow
    //   8840: aload #9
    //   8842: invokevirtual getPackage : ()Ljava/lang/Package;
    //   8845: invokevirtual getName : ()Ljava/lang/String;
    //   8848: sipush #-14573
    //   8851: sipush #-17598
    //   8854: invokestatic a : (II)Ljava/lang/String;
    //   8857: invokevirtual startsWith : (Ljava/lang/String;)Z
    //   8860: ifne -> 8870
    //   8863: goto -> 8870
    //   8866: invokestatic a : (Ljava/lang/Throwable;)Ljava/lang/Throwable;
    //   8869: athrow
    //   8870: aload #8
    //   8872: iconst_1
    //   8873: invokevirtual setAccessible : (Z)V
    //   8876: aload #8
    //   8878: aconst_null
    //   8879: invokevirtual get : (Ljava/lang/Object;)Ljava/lang/Object;
    //   8882: pop
    //   8883: iinc #7, 1
    //   8886: iload_2
    //   8887: ifne -> 8748
    //   8890: sipush #-14568
    //   8893: sipush #30245
    //   8896: invokestatic a : (II)Ljava/lang/String;
    //   8899: invokestatic forName : (Ljava/lang/String;)Ljava/lang/Class;
    //   8902: invokevirtual getDeclaredMethods : ()[Ljava/lang/reflect/Method;
    //   8905: astore #5
    //   8907: aload #5
    //   8909: arraylength
    //   8910: istore #6
    //   8912: iconst_0
    //   8913: istore #7
    //   8915: iload #7
    //   8917: iload #6
    //   8919: if_icmpge -> 9056
    //   8922: aload #5
    //   8924: iload #7
    //   8926: aaload
    //   8927: astore #8
    //   8929: aload #8
    //   8931: invokevirtual getParameterTypes : ()[Ljava/lang/Class;
    //   8934: pop
    //   8935: aload #8
    //   8937: invokevirtual getModifiers : ()I
    //   8940: invokestatic isStatic : (I)Z
    //   8943: ifeq -> 9042
    //   8946: aload #8
    //   8948: invokevirtual getParameterTypes : ()[Ljava/lang/Class;
    //   8951: arraylength
    //   8952: iconst_2
    //   8953: if_icmpne -> 9042
    //   8956: goto -> 8963
    //   8959: invokestatic a : (Ljava/lang/Throwable;)Ljava/lang/Throwable;
    //   8962: athrow
    //   8963: aload #8
    //   8965: invokevirtual getReturnType : ()Ljava/lang/Class;
    //   8968: getstatic java/lang/Boolean.TYPE : Ljava/lang/Class;
    //   8971: if_acmpne -> 9042
    //   8974: goto -> 8981
    //   8977: invokestatic a : (Ljava/lang/Throwable;)Ljava/lang/Throwable;
    //   8980: athrow
    //   8981: aload #8
    //   8983: iconst_1
    //   8984: invokevirtual setAccessible : (Z)V
    //   8987: aload #8
    //   8989: aconst_null
    //   8990: iconst_2
    //   8991: anewarray java/lang/Object
    //   8994: dup
    //   8995: iconst_0
    //   8996: aload_0
    //   8997: aastore
    //   8998: dup
    //   8999: iconst_1
    //   9000: aload_1
    //   9001: ifnonnull -> 9019
    //   9004: goto -> 9011
    //   9007: invokestatic a : (Ljava/lang/Throwable;)Ljava/lang/Throwable;
    //   9010: athrow
    //   9011: aload_1
    //   9012: goto -> 9026
    //   9015: invokestatic a : (Ljava/lang/Throwable;)Ljava/lang/Throwable;
    //   9018: athrow
    //   9019: aload_1
    //   9020: checkcast [B
    //   9023: invokevirtual clone : ()Ljava/lang/Object;
    //   9026: aastore
    //   9027: invokevirtual invoke : (Ljava/lang/Object;[Ljava/lang/Object;)Ljava/lang/Object;
    //   9030: checkcast java/lang/Boolean
    //   9033: invokevirtual booleanValue : ()Z
    //   9036: istore #4
    //   9038: iload_2
    //   9039: ifne -> 9056
    //   9042: iinc #7, 1
    //   9045: iload_2
    //   9046: ifne -> 8915
    //   9049: goto -> 9056
    //   9052: invokestatic a : (Ljava/lang/Throwable;)Ljava/lang/Throwable;
    //   9055: athrow
    //   9056: iload #4
    //   9058: ireturn
    //   9059: astore_3
    //   9060: new java/lang/Exception
    //   9063: dup
    //   9064: aload_3
    //   9065: invokevirtual getMessage : ()Ljava/lang/String;
    //   9068: invokespecial <init> : (Ljava/lang/String;)V
    //   9071: athrow
    // Exception table:
    //   from	to	target	type
    //   4	6858	9059	java/lang/Throwable
    //   22	198	201	java/lang/Throwable
    //   168	235	238	java/lang/Throwable
    //   205	272	275	java/lang/Throwable
    //   242	309	312	java/lang/Throwable
    //   279	346	349	java/lang/Throwable
    //   316	383	386	java/lang/Throwable
    //   353	420	423	java/lang/Throwable
    //   390	457	460	java/lang/Throwable
    //   427	494	497	java/lang/Throwable
    //   464	531	534	java/lang/Throwable
    //   501	568	571	java/lang/Throwable
    //   538	605	608	java/lang/Throwable
    //   575	642	645	java/lang/Throwable
    //   612	679	682	java/lang/Throwable
    //   649	716	719	java/lang/Throwable
    //   686	753	756	java/lang/Throwable
    //   723	790	793	java/lang/Throwable
    //   760	827	830	java/lang/Throwable
    //   797	864	867	java/lang/Throwable
    //   834	901	904	java/lang/Throwable
    //   871	938	941	java/lang/Throwable
    //   908	975	978	java/lang/Throwable
    //   945	1012	1015	java/lang/Throwable
    //   982	1049	1052	java/lang/Throwable
    //   1019	1086	1089	java/lang/Throwable
    //   1056	1123	1126	java/lang/Throwable
    //   1093	1160	1163	java/lang/Throwable
    //   1130	1197	1200	java/lang/Throwable
    //   1167	1234	1237	java/lang/Throwable
    //   1204	1271	1274	java/lang/Throwable
    //   1241	1308	1311	java/lang/Throwable
    //   1278	1341	1344	java/lang/Throwable
    //   1407	1421	1421	java/lang/Throwable
    //   1432	1445	1448	java/lang/Throwable
    //   1437	1460	1463	java/lang/Throwable
    //   1452	1478	1481	java/lang/Throwable
    //   1467	1508	1511	java/lang/Throwable
    //   1574	1601	1604	java/lang/Throwable
    //   1591	1622	1625	java/lang/Throwable
    //   1608	1652	1655	java/lang/Throwable
    //   1629	1663	1663	java/lang/Throwable
    //   1674	1690	1693	java/lang/Throwable
    //   1770	1784	1784	java/lang/Throwable
    //   1795	1808	1811	java/lang/Throwable
    //   1800	1823	1826	java/lang/Throwable
    //   1815	1841	1844	java/lang/Throwable
    //   1830	1871	1874	java/lang/Throwable
    //   1937	1964	1967	java/lang/Throwable
    //   1954	1985	1988	java/lang/Throwable
    //   1971	2015	2018	java/lang/Throwable
    //   1992	2026	2026	java/lang/Throwable
    //   2037	2053	2056	java/lang/Throwable
    //   2863	2897	2900	java/lang/Throwable
    //   2993	3071	3074	java/lang/Throwable
    //   3000	3214	3217	java/lang/Throwable
    //   3592	3607	3607	java/lang/Throwable
    //   3634	3668	3671	java/lang/Throwable
    //   3678	3690	3693	java/lang/Throwable
    //   3776	3854	3857	java/lang/Throwable
    //   3783	3997	4000	java/lang/Throwable
    //   4397	4475	4478	java/lang/Throwable
    //   4404	4618	4621	java/lang/Throwable
    //   5065	5099	5102	java/lang/Throwable
    //   5106	5118	5121	java/lang/Throwable
    //   5204	5282	5285	java/lang/Throwable
    //   5211	5425	5428	java/lang/Throwable
    //   6215	6229	6229	java/lang/Throwable
    //   6240	6253	6256	java/lang/Throwable
    //   6245	6268	6271	java/lang/Throwable
    //   6260	6286	6289	java/lang/Throwable
    //   6275	6316	6319	java/lang/Throwable
    //   6382	6409	6412	java/lang/Throwable
    //   6399	6427	6430	java/lang/Throwable
    //   6416	6457	6460	java/lang/Throwable
    //   6434	6468	6468	java/lang/Throwable
    //   6491	6502	6505	java/lang/Throwable
    //   6557	6571	6571	java/lang/Throwable
    //   6582	6595	6598	java/lang/Throwable
    //   6587	6610	6613	java/lang/Throwable
    //   6602	6628	6631	java/lang/Throwable
    //   6617	6658	6661	java/lang/Throwable
    //   6724	6751	6754	java/lang/Throwable
    //   6741	6769	6772	java/lang/Throwable
    //   6758	6799	6802	java/lang/Throwable
    //   6776	6810	6810	java/lang/Throwable
    //   6833	6844	6847	java/lang/Throwable
    //   6859	7593	9059	java/lang/Throwable
    //   6949	6963	6963	java/lang/Throwable
    //   6974	6987	6990	java/lang/Throwable
    //   6979	7002	7005	java/lang/Throwable
    //   6994	7020	7023	java/lang/Throwable
    //   7009	7050	7053	java/lang/Throwable
    //   7116	7143	7146	java/lang/Throwable
    //   7133	7161	7164	java/lang/Throwable
    //   7150	7191	7194	java/lang/Throwable
    //   7168	7202	7202	java/lang/Throwable
    //   7225	7236	7239	java/lang/Throwable
    //   7292	7306	7306	java/lang/Throwable
    //   7317	7330	7333	java/lang/Throwable
    //   7322	7345	7348	java/lang/Throwable
    //   7337	7363	7366	java/lang/Throwable
    //   7352	7393	7396	java/lang/Throwable
    //   7459	7486	7489	java/lang/Throwable
    //   7476	7504	7507	java/lang/Throwable
    //   7493	7534	7537	java/lang/Throwable
    //   7511	7545	7545	java/lang/Throwable
    //   7568	7579	7582	java/lang/Throwable
    //   7594	8328	9059	java/lang/Throwable
    //   7684	7698	7698	java/lang/Throwable
    //   7709	7722	7725	java/lang/Throwable
    //   7714	7737	7740	java/lang/Throwable
    //   7729	7755	7758	java/lang/Throwable
    //   7744	7785	7788	java/lang/Throwable
    //   7851	7878	7881	java/lang/Throwable
    //   7868	7896	7899	java/lang/Throwable
    //   7885	7926	7929	java/lang/Throwable
    //   7903	7937	7937	java/lang/Throwable
    //   7960	7971	7974	java/lang/Throwable
    //   8027	8041	8041	java/lang/Throwable
    //   8052	8065	8068	java/lang/Throwable
    //   8057	8080	8083	java/lang/Throwable
    //   8072	8098	8101	java/lang/Throwable
    //   8087	8128	8131	java/lang/Throwable
    //   8194	8221	8224	java/lang/Throwable
    //   8211	8239	8242	java/lang/Throwable
    //   8228	8269	8272	java/lang/Throwable
    //   8246	8280	8280	java/lang/Throwable
    //   8303	8314	8317	java/lang/Throwable
    //   8329	9058	9059	java/lang/Throwable
    //   8419	8433	8433	java/lang/Throwable
    //   8444	8457	8460	java/lang/Throwable
    //   8449	8472	8475	java/lang/Throwable
    //   8464	8490	8493	java/lang/Throwable
    //   8479	8520	8523	java/lang/Throwable
    //   8586	8613	8616	java/lang/Throwable
    //   8603	8631	8634	java/lang/Throwable
    //   8620	8661	8664	java/lang/Throwable
    //   8638	8672	8672	java/lang/Throwable
    //   8695	8706	8709	java/lang/Throwable
    //   8762	8776	8776	java/lang/Throwable
    //   8787	8800	8803	java/lang/Throwable
    //   8792	8815	8818	java/lang/Throwable
    //   8807	8833	8836	java/lang/Throwable
    //   8822	8863	8866	java/lang/Throwable
    //   8929	8956	8959	java/lang/Throwable
    //   8946	8974	8977	java/lang/Throwable
    //   8963	9004	9007	java/lang/Throwable
    //   8981	9015	9015	java/lang/Throwable
    //   9038	9049	9052	java/lang/Throwable
  }
  
  static {
    // Byte code:
    //   0: bipush #27
    //   2: anewarray java/lang/String
    //   5: astore #5
    //   7: iconst_0
    //   8: istore_3
    //   9: ldc '\\t\\ru@j \\t5A Q\\b`/Xr8B4_-a<Z gdH9\B#9p%`z\\tOc_p\\t?x:5t}Lpa{4NKse7bAIMMD~?l\\fV`z6\\nXz&BM\\f9mV\\ry$y=\\t`=H*\\t\\t+Teca\\t9Bq(\\t/)\\tk\dI>\\t 7?\\t3M\\bYc\\t'LIe\\tCh5\\t~L0]\\ti\\t-ZJ\\t\\b4;|\\\tXb>RM'
    //   11: dup
    //   12: astore_2
    //   13: invokevirtual length : ()I
    //   16: istore #4
    //   18: iconst_4
    //   19: istore_1
    //   20: iconst_m1
    //   21: istore_0
    //   22: bipush #119
    //   24: iinc #0, 1
    //   27: aload_2
    //   28: iload_0
    //   29: dup
    //   30: iload_1
    //   31: iadd
    //   32: invokevirtual substring : (II)Ljava/lang/String;
    //   35: iconst_m1
    //   36: goto -> 142
    //   39: aload #5
    //   41: swap
    //   42: iload_3
    //   43: iinc #3, 1
    //   46: swap
    //   47: aastore
    //   48: iload_0
    //   49: iload_1
    //   50: iadd
    //   51: dup
    //   52: istore_0
    //   53: iload #4
    //   55: if_icmpge -> 67
    //   58: aload_2
    //   59: iload_0
    //   60: invokevirtual charAt : (I)C
    //   63: istore_1
    //   64: goto -> 22
    //   67: ldc 'N {\\t-45&M'
    //   69: dup
    //   70: astore_2
    //   71: invokevirtual length : ()I
    //   74: istore #4
    //   76: bipush #9
    //   78: istore_1
    //   79: iconst_m1
    //   80: istore_0
    //   81: bipush #76
    //   83: iinc #0, 1
    //   86: aload_2
    //   87: iload_0
    //   88: dup
    //   89: iload_1
    //   90: iadd
    //   91: invokevirtual substring : (II)Ljava/lang/String;
    //   94: iconst_0
    //   95: goto -> 142
    //   98: aload #5
    //   100: swap
    //   101: iload_3
    //   102: iinc #3, 1
    //   105: swap
    //   106: aastore
    //   107: iload_0
    //   108: iload_1
    //   109: iadd
    //   110: dup
    //   111: istore_0
    //   112: iload #4
    //   114: if_icmpge -> 126
    //   117: aload_2
    //   118: iload_0
    //   119: invokevirtual charAt : (I)C
    //   122: istore_1
    //   123: goto -> 81
    //   126: aload #5
    //   128: putstatic burp/Zsn3.a : [Ljava/lang/String;
    //   131: bipush #27
    //   133: anewarray java/lang/String
    //   136: putstatic burp/Zsn3.b : [Ljava/lang/String;
    //   139: goto -> 300
    //   142: dup_x2
    //   143: pop
    //   144: invokevirtual toCharArray : ()[C
    //   147: dup_x1
    //   148: arraylength
    //   149: dup_x2
    //   150: pop
    //   151: iconst_0
    //   152: istore #6
    //   154: dup2_x1
    //   155: pop2
    //   156: dup_x2
    //   157: iconst_1
    //   158: if_icmpgt -> 260
    //   161: dup2
    //   162: swap
    //   163: iload #6
    //   165: dup2_x1
    //   166: caload
    //   167: swap
    //   168: iload #6
    //   170: bipush #7
    //   172: irem
    //   173: tableswitch default -> 242, 0 -> 212, 1 -> 217, 2 -> 222, 3 -> 227, 4 -> 232, 5 -> 237
    //   212: bipush #111
    //   214: goto -> 244
    //   217: bipush #9
    //   219: goto -> 244
    //   222: bipush #25
    //   224: goto -> 244
    //   227: bipush #38
    //   229: goto -> 244
    //   232: bipush #71
    //   234: goto -> 244
    //   237: bipush #74
    //   239: goto -> 244
    //   242: bipush #45
    //   244: ixor
    //   245: ixor
    //   246: i2c
    //   247: castore
    //   248: iinc #6, 1
    //   251: dup
    //   252: ifne -> 260
    //   255: dup2
    //   256: dup_x1
    //   257: goto -> 165
    //   260: dup2_x1
    //   261: pop2
    //   262: dup_x2
    //   263: iload #6
    //   265: if_icmpgt -> 161
    //   268: pop
    //   269: new java/lang/String
    //   272: dup_x1
    //   273: swap
    //   274: invokespecial <init> : ([C)V
    //   277: invokevirtual intern : ()Ljava/lang/String;
    //   280: swap
    //   281: pop
    //   282: swap
    //   283: tableswitch default -> 39, 0 -> 98
    //   300: sipush #-14576
    //   303: sipush #6475
    //   306: invokestatic a : (II)Ljava/lang/String;
    //   309: putstatic burp/Zsn3.ZS : Ljava/lang/String;
    //   312: new java/math/BigInteger
    //   315: dup
    //   316: bipush #32
    //   318: newarray byte
    //   320: dup
    //   321: iconst_0
    //   322: bipush #17
    //   324: bastore
    //   325: dup
    //   326: iconst_1
    //   327: bipush #-113
    //   329: bastore
    //   330: dup
    //   331: iconst_2
    //   332: bipush #-64
    //   334: bastore
    //   335: dup
    //   336: iconst_3
    //   337: bipush #95
    //   339: bastore
    //   340: dup
    //   341: iconst_4
    //   342: bipush #-97
    //   344: bastore
    //   345: dup
    //   346: iconst_5
    //   347: bipush #-123
    //   349: bastore
    //   350: dup
    //   351: bipush #6
    //   353: bipush #-107
    //   355: bastore
    //   356: dup
    //   357: bipush #7
    //   359: bipush #-57
    //   361: bastore
    //   362: dup
    //   363: bipush #8
    //   365: bipush #-105
    //   367: bastore
    //   368: dup
    //   369: bipush #9
    //   371: bipush #96
    //   373: bastore
    //   374: dup
    //   375: bipush #10
    //   377: bipush #60
    //   379: bastore
    //   380: dup
    //   381: bipush #11
    //   383: bipush #-90
    //   385: bastore
    //   386: dup
    //   387: bipush #12
    //   389: bipush #-98
    //   391: bastore
    //   392: dup
    //   393: bipush #13
    //   395: bipush #82
    //   397: bastore
    //   398: dup
    //   399: bipush #14
    //   401: bipush #57
    //   403: bastore
    //   404: dup
    //   405: bipush #15
    //   407: bipush #21
    //   409: bastore
    //   410: dup
    //   411: bipush #16
    //   413: bipush #-48
    //   415: bastore
    //   416: dup
    //   417: bipush #17
    //   419: bipush #-83
    //   421: bastore
    //   422: dup
    //   423: bipush #18
    //   425: bipush #93
    //   427: bastore
    //   428: dup
    //   429: bipush #19
    //   431: bipush #-109
    //   433: bastore
    //   434: dup
    //   435: bipush #20
    //   437: bipush #88
    //   439: bastore
    //   440: dup
    //   441: bipush #21
    //   443: bipush #32
    //   445: bastore
    //   446: dup
    //   447: bipush #22
    //   449: bipush #-104
    //   451: bastore
    //   452: dup
    //   453: bipush #23
    //   455: bipush #10
    //   457: bastore
    //   458: dup
    //   459: bipush #24
    //   461: bipush #62
    //   463: bastore
    //   464: dup
    //   465: bipush #25
    //   467: bipush #-97
    //   469: bastore
    //   470: dup
    //   471: bipush #26
    //   473: iconst_2
    //   474: bastore
    //   475: dup
    //   476: bipush #27
    //   478: bipush #115
    //   480: bastore
    //   481: dup
    //   482: bipush #28
    //   484: bipush #119
    //   486: bastore
    //   487: dup
    //   488: bipush #29
    //   490: bipush #106
    //   492: bastore
    //   493: dup
    //   494: bipush #30
    //   496: bipush #6
    //   498: bastore
    //   499: dup
    //   500: bipush #31
    //   502: bipush #69
    //   504: bastore
    //   505: invokespecial <init> : ([B)V
    //   508: putstatic burp/Zsn3.Zy : Ljava/lang/Object;
    //   511: return
  }
  
  private static Throwable a(Throwable paramThrowable) {
    return paramThrowable;
  }
  
  private static String a(int paramInt1, int paramInt2) {
    int i = (paramInt1 ^ 0xFFFFC713) & 0xFFFF;
    if (b[i] == null) {
      char[] arrayOfChar = a[i].toCharArray();
      switch (arrayOfChar[0] & 0xFF) {
        case 0:
        
        case 1:
        
        case 2:
        
        case 3:
        
        case 4:
        
        case 5:
        
        case 6:
        
        case 7:
        
        case 8:
        
        case 9:
        
        case 10:
        
        case 11:
        
        case 12:
        
        case 13:
        
        case 14:
        
        case 15:
        
        case 16:
        
        case 17:
        
        case 18:
        
        case 19:
        
        case 20:
        
        case 21:
        
        case 22:
        
        case 23:
        
        case 24:
        
        case 25:
        
        case 26:
        
        case 27:
        
        case 28:
        
        case 29:
        
        case 30:
        
        case 31:
        
        case 32:
        
        case 33:
        
        case 34:
        
        case 35:
        
        case 36:
        
        case 37:
        
        case 38:
        
        case 39:
        
        case 40:
        
        case 41:
        
        case 42:
        
        case 43:
        
        case 44:
        
        case 45:
        
        case 46:
        
        case 47:
        
        case 48:
        
        case 49:
        
        case 50:
        
        case 51:
        
        case 52:
        
        case 53:
        
        case 54:
        
        case 55:
        
        case 56:
        
        case 57:
        
        case 58:
        
        case 59:
        
        case 60:
        
        case 61:
        
        case 62:
        
        case 63:
        
        case 64:
        
        case 65:
        
        case 66:
        
        case 67:
        
        case 68:
        
        case 69:
        
        case 70:
        
        case 71:
        
        case 72:
        
        case 73:
        
        case 74:
        
        case 75:
        
        case 76:
        
        case 77:
        
        case 78:
        
        case 79:
        
        case 80:
        
        case 81:
        
        case 82:
        
        case 83:
        
        case 84:
        
        case 85:
        
        case 86:
        
        case 87:
        
        case 88:
        
        case 89:
        
        case 90:
        
        case 91:
        
        case 92:
        
        case 93:
        
        case 94:
        
        case 95:
        
        case 96:
        
        case 97:
        
        case 98:
        
        case 99:
        
        case 100:
        
        case 101:
        
        case 102:
        
        case 103:
        
        case 104:
        
        case 105:
        
        case 106:
        
        case 107:
        
        case 108:
        
        case 109:
        
        case 110:
        
        case 111:
        
        case 112:
        
        case 113:
        
        case 114:
        
        case 115:
        
        case 116:
        
        case 117:
        
        case 118:
        
        case 119:
        
        case 120:
        
        case 121:
        
        case 122:
        
        case 123:
        
        case 124:
        
        case 125:
        
        case 126:
        
        case 127:
        
        case 128:
        
        case 129:
        
        case 130:
        
        case 131:
        
        case 132:
        
        case 133:
        
        case 134:
        
        case 135:
        
        case 136:
        
        case 137:
        
        case 138:
        
        case 139:
        
        case 140:
        
        case 141:
        
        case 142:
        
        case 143:
        
        case 144:
        
        case 145:
        
        case 146:
        
        case 147:
        
        case 148:
        
        case 149:
        
        case 150:
        
        case 151:
        
        case 152:
        
        case 153:
        
        case 154:
        
        case 155:
        
        case 156:
        
        case 157:
        
        case 158:
        
        case 159:
        
        case 160:
        
        case 161:
        
        case 162:
        
        case 163:
        
        case 164:
        
        case 165:
        
        case 166:
        
        case 167:
        
        case 168:
        
        case 169:
        
        case 170:
        
        case 171:
        
        case 172:
        
        case 173:
        
        case 174:
        
        case 175:
        
        case 176:
        
        case 177:
        
        case 178:
        
        case 179:
        
        case 180:
        
        case 181:
        
        case 182:
        
        case 183:
        
        case 184:
        
        case 185:
        
        case 186:
        
        case 187:
        
        case 188:
        
        case 189:
        
        case 190:
        
        case 191:
        
        case 192:
        
        case 193:
        
        case 194:
        
        case 195:
        
        case 196:
        
        case 197:
        
        case 198:
        
        case 199:
        
        case 200:
        
        case 201:
        
        case 202:
        
        case 203:
        
        case 204:
        
        case 205:
        
        case 206:
        
        case 207:
        
        case 208:
        
        case 209:
        
        case 210:
        
        case 211:
        
        case 212:
        
        case 213:
        
        case 214:
        
        case 215:
        
        case 216:
        
        case 217:
        
        case 218:
        
        case 219:
        
        case 220:
        
        case 221:
        
        case 222:
        
        case 223:
        
        case 224:
        
        case 225:
        
        case 226:
        
        case 227:
        
        case 228:
        
        case 229:
        
        case 230:
        
        case 231:
        
        case 232:
        
        case 233:
        
        case 234:
        
        case 235:
        
        case 236:
        
        case 237:
        
        case 238:
        
        case 239:
        
        case 240:
        
        case 241:
        
        case 242:
        
        case 243:
        
        case 244:
        
        case 245:
        
        case 246:
        
        case 247:
        
        case 248:
        
        case 249:
        
        case 250:
        
        case 251:
        
        case 252:
        
        case 253:
        
        case 254:
        
        default:
          break;
      } 
      char c = '';
      int j = (paramInt2 & 0xFF) - c;
      if (j < 0)
        j += 256; 
      int k = ((paramInt2 & 0xFFFF) >>> 8) - c;
      if (k < 0)
        k += 256; 
      for (byte b = 0; b < arrayOfChar.length; b++) {
        int m = b % 2;
        if (m == 0) {
          arrayOfChar[b] = (char)(arrayOfChar[b] ^ j);
          j = ((j >>> 3 | j << 5) ^ arrayOfChar[b]) & 0xFF;
        } else {
          arrayOfChar[b] = (char)(arrayOfChar[b] ^ k);
          k = ((k >>> 3 | k << 5) ^ arrayOfChar[b]) & 0xFF;
        } 
      } 
      b[i] = (new String(arrayOfChar)).intern();
    } 
    return b[i];
  }
}


/* Location:              C:\Program Files\BurpSuitePro\burpsuite_pro.jar!\burp\Zsn3.class
 * Java compiler version: 21 (65.0)
 * JD-Core Version:       1.1.3
 */