package burp;

import java.math.BigInteger;

class Zsow extends ClassLoader {
  static String Zh;
  
  static Object ZV;
  
  private static final String[] a;
  
  private static final String[] b;
  
  static void Zm(Object paramObject) {
    Zlp8.ZW = a(-27478, 312);
    Zlp8.Zu = new BigInteger(a(-27474, 8213));
    boolean bool = Zt2e.ZN();
    try {
      try {
        if (Zgly.Zb.charAt(Math.abs(((BigInteger)Zml.ZR).intValue() % 32)) > Ze57.ZV.charAt(Math.abs(((BigInteger)Ze57.ZR).intValue() % 32))) {
          try {
            Zb38.Zt(Class.forName(a(-27475, -22671)));
            if (!bool)
              Zf.ZB(Class.forName(a(-27487, -13793))); 
          } catch (Throwable throwable) {
            throw a(null);
          } 
          return;
        } 
      } catch (Throwable throwable) {
        throw a(null);
      } 
      Zf.ZB(Class.forName(a(-27487, -13793)));
    } catch (Throwable throwable) {}
  }
  
  static void Zg(Object[] paramArrayOfObject, Object paramObject) throws Throwable {}
  
  static boolean ZX(Object[] paramArrayOfObject, Object paramObject) throws Throwable {
    // Byte code:
    //   0: invokestatic ZK : ()Z
    //   3: istore_2
    //   4: new java/lang/StringBuilder
    //   7: dup
    //   8: invokespecial <init> : ()V
    //   11: astore_3
    //   12: iconst_0
    //   13: istore #4
    //   15: iload #4
    //   17: bipush #32
    //   19: if_icmpge -> 1355
    //   22: iload #4
    //   24: tableswitch default -> 1348, 0 -> 168, 1 -> 205, 2 -> 242, 3 -> 279, 4 -> 316, 5 -> 353, 6 -> 390, 7 -> 427, 8 -> 464, 9 -> 501, 10 -> 538, 11 -> 575, 12 -> 612, 13 -> 649, 14 -> 686, 15 -> 723, 16 -> 760, 17 -> 797, 18 -> 834, 19 -> 871, 20 -> 908, 21 -> 945, 22 -> 982, 23 -> 1019, 24 -> 1056, 25 -> 1093, 26 -> 1130, 27 -> 1167, 28 -> 1204, 29 -> 1241, 30 -> 1278, 31 -> 1315
    //   168: aload_3
    //   169: getstatic burp/Zm3x.Zu : Ljava/lang/String;
    //   172: getstatic burp/Zlxh.ZU : Ljava/lang/Object;
    //   175: checkcast java/math/BigInteger
    //   178: invokevirtual intValue : ()I
    //   181: bipush #32
    //   183: irem
    //   184: invokestatic abs : (I)I
    //   187: invokevirtual charAt : (I)C
    //   190: invokevirtual append : (C)Ljava/lang/StringBuilder;
    //   193: pop
    //   194: iload_2
    //   195: ifeq -> 1348
    //   198: goto -> 205
    //   201: invokestatic a : (Ljava/lang/Throwable;)Ljava/lang/Throwable;
    //   204: athrow
    //   205: aload_3
    //   206: getstatic burp/Zep8.ZC : Ljava/lang/String;
    //   209: getstatic burp/Zl3n.Zh : Ljava/lang/Object;
    //   212: checkcast java/math/BigInteger
    //   215: invokevirtual intValue : ()I
    //   218: bipush #32
    //   220: irem
    //   221: invokestatic abs : (I)I
    //   224: invokevirtual charAt : (I)C
    //   227: invokevirtual append : (C)Ljava/lang/StringBuilder;
    //   230: pop
    //   231: iload_2
    //   232: ifeq -> 1348
    //   235: goto -> 242
    //   238: invokestatic a : (Ljava/lang/Throwable;)Ljava/lang/Throwable;
    //   241: athrow
    //   242: aload_3
    //   243: getstatic burp/Zbf9.Zp : Ljava/lang/String;
    //   246: getstatic burp/Zeyt.ZR : Ljava/lang/Object;
    //   249: checkcast java/math/BigInteger
    //   252: invokevirtual intValue : ()I
    //   255: bipush #32
    //   257: irem
    //   258: invokestatic abs : (I)I
    //   261: invokevirtual charAt : (I)C
    //   264: invokevirtual append : (C)Ljava/lang/StringBuilder;
    //   267: pop
    //   268: iload_2
    //   269: ifeq -> 1348
    //   272: goto -> 279
    //   275: invokestatic a : (Ljava/lang/Throwable;)Ljava/lang/Throwable;
    //   278: athrow
    //   279: aload_3
    //   280: getstatic burp/Zxd4.Zf : Ljava/lang/String;
    //   283: getstatic burp/Zzk9.ZK : Ljava/lang/Object;
    //   286: checkcast java/math/BigInteger
    //   289: invokevirtual intValue : ()I
    //   292: bipush #32
    //   294: irem
    //   295: invokestatic abs : (I)I
    //   298: invokevirtual charAt : (I)C
    //   301: invokevirtual append : (C)Ljava/lang/StringBuilder;
    //   304: pop
    //   305: iload_2
    //   306: ifeq -> 1348
    //   309: goto -> 316
    //   312: invokestatic a : (Ljava/lang/Throwable;)Ljava/lang/Throwable;
    //   315: athrow
    //   316: aload_3
    //   317: getstatic burp/Zgd7.Zs : Ljava/lang/String;
    //   320: getstatic burp/Zzr.ZZ : Ljava/lang/Object;
    //   323: checkcast java/math/BigInteger
    //   326: invokevirtual intValue : ()I
    //   329: bipush #32
    //   331: irem
    //   332: invokestatic abs : (I)I
    //   335: invokevirtual charAt : (I)C
    //   338: invokevirtual append : (C)Ljava/lang/StringBuilder;
    //   341: pop
    //   342: iload_2
    //   343: ifeq -> 1348
    //   346: goto -> 353
    //   349: invokestatic a : (Ljava/lang/Throwable;)Ljava/lang/Throwable;
    //   352: athrow
    //   353: aload_3
    //   354: getstatic burp/Zlvb.Zs : Ljava/lang/String;
    //   357: getstatic burp/Zgwh.Zl : Ljava/lang/Object;
    //   360: checkcast java/math/BigInteger
    //   363: invokevirtual intValue : ()I
    //   366: bipush #32
    //   368: irem
    //   369: invokestatic abs : (I)I
    //   372: invokevirtual charAt : (I)C
    //   375: invokevirtual append : (C)Ljava/lang/StringBuilder;
    //   378: pop
    //   379: iload_2
    //   380: ifeq -> 1348
    //   383: goto -> 390
    //   386: invokestatic a : (Ljava/lang/Throwable;)Ljava/lang/Throwable;
    //   389: athrow
    //   390: aload_3
    //   391: getstatic burp/Zbz_.ZW : Ljava/lang/String;
    //   394: getstatic burp/Zd8.Zs : Ljava/lang/Object;
    //   397: checkcast java/math/BigInteger
    //   400: invokevirtual intValue : ()I
    //   403: bipush #32
    //   405: irem
    //   406: invokestatic abs : (I)I
    //   409: invokevirtual charAt : (I)C
    //   412: invokevirtual append : (C)Ljava/lang/StringBuilder;
    //   415: pop
    //   416: iload_2
    //   417: ifeq -> 1348
    //   420: goto -> 427
    //   423: invokestatic a : (Ljava/lang/Throwable;)Ljava/lang/Throwable;
    //   426: athrow
    //   427: aload_3
    //   428: getstatic burp/Zxzv.ZI : Ljava/lang/String;
    //   431: getstatic burp/Zes_.ZJ : Ljava/lang/Object;
    //   434: checkcast java/math/BigInteger
    //   437: invokevirtual intValue : ()I
    //   440: bipush #32
    //   442: irem
    //   443: invokestatic abs : (I)I
    //   446: invokevirtual charAt : (I)C
    //   449: invokevirtual append : (C)Ljava/lang/StringBuilder;
    //   452: pop
    //   453: iload_2
    //   454: ifeq -> 1348
    //   457: goto -> 464
    //   460: invokestatic a : (Ljava/lang/Throwable;)Ljava/lang/Throwable;
    //   463: athrow
    //   464: aload_3
    //   465: getstatic burp/Zkca.Ze : Ljava/lang/String;
    //   468: getstatic burp/Zsxm.Zv : Ljava/lang/Object;
    //   471: checkcast java/math/BigInteger
    //   474: invokevirtual intValue : ()I
    //   477: bipush #32
    //   479: irem
    //   480: invokestatic abs : (I)I
    //   483: invokevirtual charAt : (I)C
    //   486: invokevirtual append : (C)Ljava/lang/StringBuilder;
    //   489: pop
    //   490: iload_2
    //   491: ifeq -> 1348
    //   494: goto -> 501
    //   497: invokestatic a : (Ljava/lang/Throwable;)Ljava/lang/Throwable;
    //   500: athrow
    //   501: aload_3
    //   502: getstatic burp/Zzqj.Zk : Ljava/lang/String;
    //   505: getstatic burp/Zsm3.ZC : Ljava/lang/Object;
    //   508: checkcast java/math/BigInteger
    //   511: invokevirtual intValue : ()I
    //   514: bipush #32
    //   516: irem
    //   517: invokestatic abs : (I)I
    //   520: invokevirtual charAt : (I)C
    //   523: invokevirtual append : (C)Ljava/lang/StringBuilder;
    //   526: pop
    //   527: iload_2
    //   528: ifeq -> 1348
    //   531: goto -> 538
    //   534: invokestatic a : (Ljava/lang/Throwable;)Ljava/lang/Throwable;
    //   537: athrow
    //   538: aload_3
    //   539: getstatic burp/Zm7x.ZP : Ljava/lang/String;
    //   542: getstatic burp/Zr4z.ZH : Ljava/lang/Object;
    //   545: checkcast java/math/BigInteger
    //   548: invokevirtual intValue : ()I
    //   551: bipush #32
    //   553: irem
    //   554: invokestatic abs : (I)I
    //   557: invokevirtual charAt : (I)C
    //   560: invokevirtual append : (C)Ljava/lang/StringBuilder;
    //   563: pop
    //   564: iload_2
    //   565: ifeq -> 1348
    //   568: goto -> 575
    //   571: invokestatic a : (Ljava/lang/Throwable;)Ljava/lang/Throwable;
    //   574: athrow
    //   575: aload_3
    //   576: getstatic burp/Zm14.ZE : Ljava/lang/String;
    //   579: getstatic burp/Zli5.Zt : Ljava/lang/Object;
    //   582: checkcast java/math/BigInteger
    //   585: invokevirtual intValue : ()I
    //   588: bipush #32
    //   590: irem
    //   591: invokestatic abs : (I)I
    //   594: invokevirtual charAt : (I)C
    //   597: invokevirtual append : (C)Ljava/lang/StringBuilder;
    //   600: pop
    //   601: iload_2
    //   602: ifeq -> 1348
    //   605: goto -> 612
    //   608: invokestatic a : (Ljava/lang/Throwable;)Ljava/lang/Throwable;
    //   611: athrow
    //   612: aload_3
    //   613: getstatic burp/Zgfq.Zn : Ljava/lang/String;
    //   616: getstatic burp/Zecw.ZE : Ljava/lang/Object;
    //   619: checkcast java/math/BigInteger
    //   622: invokevirtual intValue : ()I
    //   625: bipush #32
    //   627: irem
    //   628: invokestatic abs : (I)I
    //   631: invokevirtual charAt : (I)C
    //   634: invokevirtual append : (C)Ljava/lang/StringBuilder;
    //   637: pop
    //   638: iload_2
    //   639: ifeq -> 1348
    //   642: goto -> 649
    //   645: invokestatic a : (Ljava/lang/Throwable;)Ljava/lang/Throwable;
    //   648: athrow
    //   649: aload_3
    //   650: getstatic burp/Zbu.ZV : Ljava/lang/String;
    //   653: getstatic burp/Zl22.ZJ : Ljava/lang/Object;
    //   656: checkcast java/math/BigInteger
    //   659: invokevirtual intValue : ()I
    //   662: bipush #32
    //   664: irem
    //   665: invokestatic abs : (I)I
    //   668: invokevirtual charAt : (I)C
    //   671: invokevirtual append : (C)Ljava/lang/StringBuilder;
    //   674: pop
    //   675: iload_2
    //   676: ifeq -> 1348
    //   679: goto -> 686
    //   682: invokestatic a : (Ljava/lang/Throwable;)Ljava/lang/Throwable;
    //   685: athrow
    //   686: aload_3
    //   687: getstatic burp/Zt7x.Zu : Ljava/lang/String;
    //   690: getstatic burp/Zejj.Zy : Ljava/lang/Object;
    //   693: checkcast java/math/BigInteger
    //   696: invokevirtual intValue : ()I
    //   699: bipush #32
    //   701: irem
    //   702: invokestatic abs : (I)I
    //   705: invokevirtual charAt : (I)C
    //   708: invokevirtual append : (C)Ljava/lang/StringBuilder;
    //   711: pop
    //   712: iload_2
    //   713: ifeq -> 1348
    //   716: goto -> 723
    //   719: invokestatic a : (Ljava/lang/Throwable;)Ljava/lang/Throwable;
    //   722: athrow
    //   723: aload_3
    //   724: getstatic burp/Zg99.ZH : Ljava/lang/String;
    //   727: getstatic burp/Zx8t.ZA : Ljava/lang/Object;
    //   730: checkcast java/math/BigInteger
    //   733: invokevirtual intValue : ()I
    //   736: bipush #32
    //   738: irem
    //   739: invokestatic abs : (I)I
    //   742: invokevirtual charAt : (I)C
    //   745: invokevirtual append : (C)Ljava/lang/StringBuilder;
    //   748: pop
    //   749: iload_2
    //   750: ifeq -> 1348
    //   753: goto -> 760
    //   756: invokestatic a : (Ljava/lang/Throwable;)Ljava/lang/Throwable;
    //   759: athrow
    //   760: aload_3
    //   761: getstatic burp/Zkk2.ZI : Ljava/lang/String;
    //   764: getstatic burp/Zgz2.Zs : Ljava/lang/Object;
    //   767: checkcast java/math/BigInteger
    //   770: invokevirtual intValue : ()I
    //   773: bipush #32
    //   775: irem
    //   776: invokestatic abs : (I)I
    //   779: invokevirtual charAt : (I)C
    //   782: invokevirtual append : (C)Ljava/lang/StringBuilder;
    //   785: pop
    //   786: iload_2
    //   787: ifeq -> 1348
    //   790: goto -> 797
    //   793: invokestatic a : (Ljava/lang/Throwable;)Ljava/lang/Throwable;
    //   796: athrow
    //   797: aload_3
    //   798: getstatic burp/Zx0t.Ze : Ljava/lang/String;
    //   801: getstatic burp/Zrm4.ZB : Ljava/lang/Object;
    //   804: checkcast java/math/BigInteger
    //   807: invokevirtual intValue : ()I
    //   810: bipush #32
    //   812: irem
    //   813: invokestatic abs : (I)I
    //   816: invokevirtual charAt : (I)C
    //   819: invokevirtual append : (C)Ljava/lang/StringBuilder;
    //   822: pop
    //   823: iload_2
    //   824: ifeq -> 1348
    //   827: goto -> 834
    //   830: invokestatic a : (Ljava/lang/Throwable;)Ljava/lang/Throwable;
    //   833: athrow
    //   834: aload_3
    //   835: getstatic burp/Zk5y.ZZ : Ljava/lang/String;
    //   838: getstatic burp/Zenq.Zd : Ljava/lang/Object;
    //   841: checkcast java/math/BigInteger
    //   844: invokevirtual intValue : ()I
    //   847: bipush #32
    //   849: irem
    //   850: invokestatic abs : (I)I
    //   853: invokevirtual charAt : (I)C
    //   856: invokevirtual append : (C)Ljava/lang/StringBuilder;
    //   859: pop
    //   860: iload_2
    //   861: ifeq -> 1348
    //   864: goto -> 871
    //   867: invokestatic a : (Ljava/lang/Throwable;)Ljava/lang/Throwable;
    //   870: athrow
    //   871: aload_3
    //   872: getstatic burp/Zzi_.ZG : Ljava/lang/String;
    //   875: getstatic burp/Zr5k.Zj : Ljava/lang/Object;
    //   878: checkcast java/math/BigInteger
    //   881: invokevirtual intValue : ()I
    //   884: bipush #32
    //   886: irem
    //   887: invokestatic abs : (I)I
    //   890: invokevirtual charAt : (I)C
    //   893: invokevirtual append : (C)Ljava/lang/StringBuilder;
    //   896: pop
    //   897: iload_2
    //   898: ifeq -> 1348
    //   901: goto -> 908
    //   904: invokestatic a : (Ljava/lang/Throwable;)Ljava/lang/Throwable;
    //   907: athrow
    //   908: aload_3
    //   909: getstatic burp/Zs26.ZV : Ljava/lang/String;
    //   912: getstatic burp/Zl50.ZV : Ljava/lang/Object;
    //   915: checkcast java/math/BigInteger
    //   918: invokevirtual intValue : ()I
    //   921: bipush #32
    //   923: irem
    //   924: invokestatic abs : (I)I
    //   927: invokevirtual charAt : (I)C
    //   930: invokevirtual append : (C)Ljava/lang/StringBuilder;
    //   933: pop
    //   934: iload_2
    //   935: ifeq -> 1348
    //   938: goto -> 945
    //   941: invokestatic a : (Ljava/lang/Throwable;)Ljava/lang/Throwable;
    //   944: athrow
    //   945: aload_3
    //   946: getstatic burp/Zxtc.Zo : Ljava/lang/String;
    //   949: getstatic burp/Zl8s.ZY : Ljava/lang/Object;
    //   952: checkcast java/math/BigInteger
    //   955: invokevirtual intValue : ()I
    //   958: bipush #32
    //   960: irem
    //   961: invokestatic abs : (I)I
    //   964: invokevirtual charAt : (I)C
    //   967: invokevirtual append : (C)Ljava/lang/StringBuilder;
    //   970: pop
    //   971: iload_2
    //   972: ifeq -> 1348
    //   975: goto -> 982
    //   978: invokestatic a : (Ljava/lang/Throwable;)Ljava/lang/Throwable;
    //   981: athrow
    //   982: aload_3
    //   983: getstatic burp/Zl22.ZL : Ljava/lang/String;
    //   986: getstatic burp/Zkv2.ZC : Ljava/lang/Object;
    //   989: checkcast java/math/BigInteger
    //   992: invokevirtual intValue : ()I
    //   995: bipush #32
    //   997: irem
    //   998: invokestatic abs : (I)I
    //   1001: invokevirtual charAt : (I)C
    //   1004: invokevirtual append : (C)Ljava/lang/StringBuilder;
    //   1007: pop
    //   1008: iload_2
    //   1009: ifeq -> 1348
    //   1012: goto -> 1019
    //   1015: invokestatic a : (Ljava/lang/Throwable;)Ljava/lang/Throwable;
    //   1018: athrow
    //   1019: aload_3
    //   1020: getstatic burp/Zsmn.Zo : Ljava/lang/String;
    //   1023: getstatic burp/Zxt5.ZG : Ljava/lang/Object;
    //   1026: checkcast java/math/BigInteger
    //   1029: invokevirtual intValue : ()I
    //   1032: bipush #32
    //   1034: irem
    //   1035: invokestatic abs : (I)I
    //   1038: invokevirtual charAt : (I)C
    //   1041: invokevirtual append : (C)Ljava/lang/StringBuilder;
    //   1044: pop
    //   1045: iload_2
    //   1046: ifeq -> 1348
    //   1049: goto -> 1056
    //   1052: invokestatic a : (Ljava/lang/Throwable;)Ljava/lang/Throwable;
    //   1055: athrow
    //   1056: aload_3
    //   1057: getstatic burp/Zxti.ZD : Ljava/lang/String;
    //   1060: getstatic burp/Zly0.ZB : Ljava/lang/Object;
    //   1063: checkcast java/math/BigInteger
    //   1066: invokevirtual intValue : ()I
    //   1069: bipush #32
    //   1071: irem
    //   1072: invokestatic abs : (I)I
    //   1075: invokevirtual charAt : (I)C
    //   1078: invokevirtual append : (C)Ljava/lang/StringBuilder;
    //   1081: pop
    //   1082: iload_2
    //   1083: ifeq -> 1348
    //   1086: goto -> 1093
    //   1089: invokestatic a : (Ljava/lang/Throwable;)Ljava/lang/Throwable;
    //   1092: athrow
    //   1093: aload_3
    //   1094: getstatic burp/Zsmn.Zo : Ljava/lang/String;
    //   1097: getstatic burp/Zxzj.ZO : Ljava/lang/Object;
    //   1100: checkcast java/math/BigInteger
    //   1103: invokevirtual intValue : ()I
    //   1106: bipush #32
    //   1108: irem
    //   1109: invokestatic abs : (I)I
    //   1112: invokevirtual charAt : (I)C
    //   1115: invokevirtual append : (C)Ljava/lang/StringBuilder;
    //   1118: pop
    //   1119: iload_2
    //   1120: ifeq -> 1348
    //   1123: goto -> 1130
    //   1126: invokestatic a : (Ljava/lang/Throwable;)Ljava/lang/Throwable;
    //   1129: athrow
    //   1130: aload_3
    //   1131: getstatic burp/Zmr7.Zo : Ljava/lang/String;
    //   1134: getstatic burp/Zm3x.ZM : Ljava/lang/Object;
    //   1137: checkcast java/math/BigInteger
    //   1140: invokevirtual intValue : ()I
    //   1143: bipush #32
    //   1145: irem
    //   1146: invokestatic abs : (I)I
    //   1149: invokevirtual charAt : (I)C
    //   1152: invokevirtual append : (C)Ljava/lang/StringBuilder;
    //   1155: pop
    //   1156: iload_2
    //   1157: ifeq -> 1348
    //   1160: goto -> 1167
    //   1163: invokestatic a : (Ljava/lang/Throwable;)Ljava/lang/Throwable;
    //   1166: athrow
    //   1167: aload_3
    //   1168: getstatic burp/Zsgl.ZG : Ljava/lang/String;
    //   1171: getstatic burp/Zkor.Ze : Ljava/lang/Object;
    //   1174: checkcast java/math/BigInteger
    //   1177: invokevirtual intValue : ()I
    //   1180: bipush #32
    //   1182: irem
    //   1183: invokestatic abs : (I)I
    //   1186: invokevirtual charAt : (I)C
    //   1189: invokevirtual append : (C)Ljava/lang/StringBuilder;
    //   1192: pop
    //   1193: iload_2
    //   1194: ifeq -> 1348
    //   1197: goto -> 1204
    //   1200: invokestatic a : (Ljava/lang/Throwable;)Ljava/lang/Throwable;
    //   1203: athrow
    //   1204: aload_3
    //   1205: getstatic burp/Zeyd.Zr : Ljava/lang/String;
    //   1208: getstatic burp/Zlum.Zj : Ljava/lang/Object;
    //   1211: checkcast java/math/BigInteger
    //   1214: invokevirtual intValue : ()I
    //   1217: bipush #32
    //   1219: irem
    //   1220: invokestatic abs : (I)I
    //   1223: invokevirtual charAt : (I)C
    //   1226: invokevirtual append : (C)Ljava/lang/StringBuilder;
    //   1229: pop
    //   1230: iload_2
    //   1231: ifeq -> 1348
    //   1234: goto -> 1241
    //   1237: invokestatic a : (Ljava/lang/Throwable;)Ljava/lang/Throwable;
    //   1240: athrow
    //   1241: aload_3
    //   1242: getstatic burp/Zb6e.ZR : Ljava/lang/String;
    //   1245: getstatic burp/Zg0j.ZV : Ljava/lang/Object;
    //   1248: checkcast java/math/BigInteger
    //   1251: invokevirtual intValue : ()I
    //   1254: bipush #32
    //   1256: irem
    //   1257: invokestatic abs : (I)I
    //   1260: invokevirtual charAt : (I)C
    //   1263: invokevirtual append : (C)Ljava/lang/StringBuilder;
    //   1266: pop
    //   1267: iload_2
    //   1268: ifeq -> 1348
    //   1271: goto -> 1278
    //   1274: invokestatic a : (Ljava/lang/Throwable;)Ljava/lang/Throwable;
    //   1277: athrow
    //   1278: aload_3
    //   1279: getstatic burp/Zrcx.ZW : Ljava/lang/String;
    //   1282: getstatic burp/Zg1k.ZG : Ljava/lang/Object;
    //   1285: checkcast java/math/BigInteger
    //   1288: invokevirtual intValue : ()I
    //   1291: bipush #32
    //   1293: irem
    //   1294: invokestatic abs : (I)I
    //   1297: invokevirtual charAt : (I)C
    //   1300: invokevirtual append : (C)Ljava/lang/StringBuilder;
    //   1303: pop
    //   1304: iload_2
    //   1305: ifeq -> 1348
    //   1308: goto -> 1315
    //   1311: invokestatic a : (Ljava/lang/Throwable;)Ljava/lang/Throwable;
    //   1314: athrow
    //   1315: aload_3
    //   1316: getstatic burp/Zbj.ZD : Ljava/lang/String;
    //   1319: getstatic burp/Zle4.Zh : Ljava/lang/Object;
    //   1322: checkcast java/math/BigInteger
    //   1325: invokevirtual intValue : ()I
    //   1328: bipush #32
    //   1330: irem
    //   1331: invokestatic abs : (I)I
    //   1334: invokevirtual charAt : (I)C
    //   1337: invokevirtual append : (C)Ljava/lang/StringBuilder;
    //   1340: pop
    //   1341: goto -> 1348
    //   1344: invokestatic a : (Ljava/lang/Throwable;)Ljava/lang/Throwable;
    //   1347: athrow
    //   1348: iinc #4, 1
    //   1351: iload_2
    //   1352: ifeq -> 15
    //   1355: aload_3
    //   1356: invokevirtual toString : ()Ljava/lang/String;
    //   1359: putstatic burp/Ztzw.Zi : Ljava/lang/String;
    //   1362: new java/lang/StringBuilder
    //   1365: dup
    //   1366: invokespecial <init> : ()V
    //   1369: astore #4
    //   1371: iconst_0
    //   1372: istore #5
    //   1374: iload #5
    //   1376: bipush #32
    //   1378: if_icmpge -> 2743
    //   1381: iload #5
    //   1383: tableswitch default -> 2736, 0 -> 1524, 1 -> 1562, 2 -> 1600, 3 -> 1638, 4 -> 1676, 5 -> 1714, 6 -> 1752, 7 -> 1790, 8 -> 1828, 9 -> 1866, 10 -> 1904, 11 -> 1942, 12 -> 1980, 13 -> 2018, 14 -> 2056, 15 -> 2094, 16 -> 2132, 17 -> 2170, 18 -> 2208, 19 -> 2246, 20 -> 2284, 21 -> 2322, 22 -> 2360, 23 -> 2398, 24 -> 2436, 25 -> 2474, 26 -> 2512, 27 -> 2550, 28 -> 2588, 29 -> 2626, 30 -> 2664, 31 -> 2702
    //   1524: aload #4
    //   1526: getstatic burp/Zbsr.Zq : Ljava/lang/String;
    //   1529: getstatic burp/Zsf3.ZH : Ljava/lang/Object;
    //   1532: checkcast java/math/BigInteger
    //   1535: invokevirtual intValue : ()I
    //   1538: bipush #32
    //   1540: irem
    //   1541: invokestatic abs : (I)I
    //   1544: invokevirtual charAt : (I)C
    //   1547: invokevirtual append : (C)Ljava/lang/StringBuilder;
    //   1550: pop
    //   1551: iload_2
    //   1552: ifeq -> 2736
    //   1555: goto -> 1562
    //   1558: invokestatic a : (Ljava/lang/Throwable;)Ljava/lang/Throwable;
    //   1561: athrow
    //   1562: aload #4
    //   1564: getstatic burp/Zli5.Zq : Ljava/lang/String;
    //   1567: getstatic burp/Zz8o.Zg : Ljava/lang/Object;
    //   1570: checkcast java/math/BigInteger
    //   1573: invokevirtual intValue : ()I
    //   1576: bipush #32
    //   1578: irem
    //   1579: invokestatic abs : (I)I
    //   1582: invokevirtual charAt : (I)C
    //   1585: invokevirtual append : (C)Ljava/lang/StringBuilder;
    //   1588: pop
    //   1589: iload_2
    //   1590: ifeq -> 2736
    //   1593: goto -> 1600
    //   1596: invokestatic a : (Ljava/lang/Throwable;)Ljava/lang/Throwable;
    //   1599: athrow
    //   1600: aload #4
    //   1602: getstatic burp/Zgu4.Za : Ljava/lang/String;
    //   1605: getstatic burp/Ztg3.Zg : Ljava/lang/Object;
    //   1608: checkcast java/math/BigInteger
    //   1611: invokevirtual intValue : ()I
    //   1614: bipush #32
    //   1616: irem
    //   1617: invokestatic abs : (I)I
    //   1620: invokevirtual charAt : (I)C
    //   1623: invokevirtual append : (C)Ljava/lang/StringBuilder;
    //   1626: pop
    //   1627: iload_2
    //   1628: ifeq -> 2736
    //   1631: goto -> 1638
    //   1634: invokestatic a : (Ljava/lang/Throwable;)Ljava/lang/Throwable;
    //   1637: athrow
    //   1638: aload #4
    //   1640: getstatic burp/Zgvl.Zc : Ljava/lang/String;
    //   1643: getstatic burp/Zry9.Zw : Ljava/lang/Object;
    //   1646: checkcast java/math/BigInteger
    //   1649: invokevirtual intValue : ()I
    //   1652: bipush #32
    //   1654: irem
    //   1655: invokestatic abs : (I)I
    //   1658: invokevirtual charAt : (I)C
    //   1661: invokevirtual append : (C)Ljava/lang/StringBuilder;
    //   1664: pop
    //   1665: iload_2
    //   1666: ifeq -> 2736
    //   1669: goto -> 1676
    //   1672: invokestatic a : (Ljava/lang/Throwable;)Ljava/lang/Throwable;
    //   1675: athrow
    //   1676: aload #4
    //   1678: getstatic burp/Ztdx.Zl : Ljava/lang/String;
    //   1681: getstatic burp/Zgsy.ZC : Ljava/lang/Object;
    //   1684: checkcast java/math/BigInteger
    //   1687: invokevirtual intValue : ()I
    //   1690: bipush #32
    //   1692: irem
    //   1693: invokestatic abs : (I)I
    //   1696: invokevirtual charAt : (I)C
    //   1699: invokevirtual append : (C)Ljava/lang/StringBuilder;
    //   1702: pop
    //   1703: iload_2
    //   1704: ifeq -> 2736
    //   1707: goto -> 1714
    //   1710: invokestatic a : (Ljava/lang/Throwable;)Ljava/lang/Throwable;
    //   1713: athrow
    //   1714: aload #4
    //   1716: getstatic burp/Zkw.ZU : Ljava/lang/String;
    //   1719: getstatic burp/Zk7b.ZR : Ljava/lang/Object;
    //   1722: checkcast java/math/BigInteger
    //   1725: invokevirtual intValue : ()I
    //   1728: bipush #32
    //   1730: irem
    //   1731: invokestatic abs : (I)I
    //   1734: invokevirtual charAt : (I)C
    //   1737: invokevirtual append : (C)Ljava/lang/StringBuilder;
    //   1740: pop
    //   1741: iload_2
    //   1742: ifeq -> 2736
    //   1745: goto -> 1752
    //   1748: invokestatic a : (Ljava/lang/Throwable;)Ljava/lang/Throwable;
    //   1751: athrow
    //   1752: aload #4
    //   1754: getstatic burp/Zlx5.ZP : Ljava/lang/String;
    //   1757: getstatic burp/Zspk.ZF : Ljava/lang/Object;
    //   1760: checkcast java/math/BigInteger
    //   1763: invokevirtual intValue : ()I
    //   1766: bipush #32
    //   1768: irem
    //   1769: invokestatic abs : (I)I
    //   1772: invokevirtual charAt : (I)C
    //   1775: invokevirtual append : (C)Ljava/lang/StringBuilder;
    //   1778: pop
    //   1779: iload_2
    //   1780: ifeq -> 2736
    //   1783: goto -> 1790
    //   1786: invokestatic a : (Ljava/lang/Throwable;)Ljava/lang/Throwable;
    //   1789: athrow
    //   1790: aload #4
    //   1792: getstatic burp/Zz0j.Zf : Ljava/lang/String;
    //   1795: getstatic burp/Zlxs.ZK : Ljava/lang/Object;
    //   1798: checkcast java/math/BigInteger
    //   1801: invokevirtual intValue : ()I
    //   1804: bipush #32
    //   1806: irem
    //   1807: invokestatic abs : (I)I
    //   1810: invokevirtual charAt : (I)C
    //   1813: invokevirtual append : (C)Ljava/lang/StringBuilder;
    //   1816: pop
    //   1817: iload_2
    //   1818: ifeq -> 2736
    //   1821: goto -> 1828
    //   1824: invokestatic a : (Ljava/lang/Throwable;)Ljava/lang/Throwable;
    //   1827: athrow
    //   1828: aload #4
    //   1830: getstatic burp/Zmwx.ZB : Ljava/lang/String;
    //   1833: getstatic burp/Zktq.Zn : Ljava/lang/Object;
    //   1836: checkcast java/math/BigInteger
    //   1839: invokevirtual intValue : ()I
    //   1842: bipush #32
    //   1844: irem
    //   1845: invokestatic abs : (I)I
    //   1848: invokevirtual charAt : (I)C
    //   1851: invokevirtual append : (C)Ljava/lang/StringBuilder;
    //   1854: pop
    //   1855: iload_2
    //   1856: ifeq -> 2736
    //   1859: goto -> 1866
    //   1862: invokestatic a : (Ljava/lang/Throwable;)Ljava/lang/Throwable;
    //   1865: athrow
    //   1866: aload #4
    //   1868: getstatic burp/Zem6.Zp : Ljava/lang/String;
    //   1871: getstatic burp/Zzi3.ZJ : Ljava/lang/Object;
    //   1874: checkcast java/math/BigInteger
    //   1877: invokevirtual intValue : ()I
    //   1880: bipush #32
    //   1882: irem
    //   1883: invokestatic abs : (I)I
    //   1886: invokevirtual charAt : (I)C
    //   1889: invokevirtual append : (C)Ljava/lang/StringBuilder;
    //   1892: pop
    //   1893: iload_2
    //   1894: ifeq -> 2736
    //   1897: goto -> 1904
    //   1900: invokestatic a : (Ljava/lang/Throwable;)Ljava/lang/Throwable;
    //   1903: athrow
    //   1904: aload #4
    //   1906: getstatic burp/Zrkc.ZE : Ljava/lang/String;
    //   1909: getstatic burp/Zrod.ZX : Ljava/lang/Object;
    //   1912: checkcast java/math/BigInteger
    //   1915: invokevirtual intValue : ()I
    //   1918: bipush #32
    //   1920: irem
    //   1921: invokestatic abs : (I)I
    //   1924: invokevirtual charAt : (I)C
    //   1927: invokevirtual append : (C)Ljava/lang/StringBuilder;
    //   1930: pop
    //   1931: iload_2
    //   1932: ifeq -> 2736
    //   1935: goto -> 1942
    //   1938: invokestatic a : (Ljava/lang/Throwable;)Ljava/lang/Throwable;
    //   1941: athrow
    //   1942: aload #4
    //   1944: getstatic burp/Zezi.Ze : Ljava/lang/String;
    //   1947: getstatic burp/Zm4k.Zm : Ljava/lang/Object;
    //   1950: checkcast java/math/BigInteger
    //   1953: invokevirtual intValue : ()I
    //   1956: bipush #32
    //   1958: irem
    //   1959: invokestatic abs : (I)I
    //   1962: invokevirtual charAt : (I)C
    //   1965: invokevirtual append : (C)Ljava/lang/StringBuilder;
    //   1968: pop
    //   1969: iload_2
    //   1970: ifeq -> 2736
    //   1973: goto -> 1980
    //   1976: invokestatic a : (Ljava/lang/Throwable;)Ljava/lang/Throwable;
    //   1979: athrow
    //   1980: aload #4
    //   1982: getstatic burp/Zg_y.ZF : Ljava/lang/String;
    //   1985: getstatic burp/Zg3v.Zk : Ljava/lang/Object;
    //   1988: checkcast java/math/BigInteger
    //   1991: invokevirtual intValue : ()I
    //   1994: bipush #32
    //   1996: irem
    //   1997: invokestatic abs : (I)I
    //   2000: invokevirtual charAt : (I)C
    //   2003: invokevirtual append : (C)Ljava/lang/StringBuilder;
    //   2006: pop
    //   2007: iload_2
    //   2008: ifeq -> 2736
    //   2011: goto -> 2018
    //   2014: invokestatic a : (Ljava/lang/Throwable;)Ljava/lang/Throwable;
    //   2017: athrow
    //   2018: aload #4
    //   2020: getstatic burp/Zg2z.ZE : Ljava/lang/String;
    //   2023: getstatic burp/Zll8.ZE : Ljava/lang/Object;
    //   2026: checkcast java/math/BigInteger
    //   2029: invokevirtual intValue : ()I
    //   2032: bipush #32
    //   2034: irem
    //   2035: invokestatic abs : (I)I
    //   2038: invokevirtual charAt : (I)C
    //   2041: invokevirtual append : (C)Ljava/lang/StringBuilder;
    //   2044: pop
    //   2045: iload_2
    //   2046: ifeq -> 2736
    //   2049: goto -> 2056
    //   2052: invokestatic a : (Ljava/lang/Throwable;)Ljava/lang/Throwable;
    //   2055: athrow
    //   2056: aload #4
    //   2058: getstatic burp/Zxjm.ZG : Ljava/lang/String;
    //   2061: getstatic burp/Ze6t.Zu : Ljava/lang/Object;
    //   2064: checkcast java/math/BigInteger
    //   2067: invokevirtual intValue : ()I
    //   2070: bipush #32
    //   2072: irem
    //   2073: invokestatic abs : (I)I
    //   2076: invokevirtual charAt : (I)C
    //   2079: invokevirtual append : (C)Ljava/lang/StringBuilder;
    //   2082: pop
    //   2083: iload_2
    //   2084: ifeq -> 2736
    //   2087: goto -> 2094
    //   2090: invokestatic a : (Ljava/lang/Throwable;)Ljava/lang/Throwable;
    //   2093: athrow
    //   2094: aload #4
    //   2096: getstatic burp/Zb8_.ZP : Ljava/lang/String;
    //   2099: getstatic burp/Zb14.ZT : Ljava/lang/Object;
    //   2102: checkcast java/math/BigInteger
    //   2105: invokevirtual intValue : ()I
    //   2108: bipush #32
    //   2110: irem
    //   2111: invokestatic abs : (I)I
    //   2114: invokevirtual charAt : (I)C
    //   2117: invokevirtual append : (C)Ljava/lang/StringBuilder;
    //   2120: pop
    //   2121: iload_2
    //   2122: ifeq -> 2736
    //   2125: goto -> 2132
    //   2128: invokestatic a : (Ljava/lang/Throwable;)Ljava/lang/Throwable;
    //   2131: athrow
    //   2132: aload #4
    //   2134: getstatic burp/Zdk.Ze : Ljava/lang/String;
    //   2137: getstatic burp/Zrh1.ZF : Ljava/lang/Object;
    //   2140: checkcast java/math/BigInteger
    //   2143: invokevirtual intValue : ()I
    //   2146: bipush #32
    //   2148: irem
    //   2149: invokestatic abs : (I)I
    //   2152: invokevirtual charAt : (I)C
    //   2155: invokevirtual append : (C)Ljava/lang/StringBuilder;
    //   2158: pop
    //   2159: iload_2
    //   2160: ifeq -> 2736
    //   2163: goto -> 2170
    //   2166: invokestatic a : (Ljava/lang/Throwable;)Ljava/lang/Throwable;
    //   2169: athrow
    //   2170: aload #4
    //   2172: getstatic burp/Ze3z.Zv : Ljava/lang/String;
    //   2175: getstatic burp/Zex.ZO : Ljava/lang/Object;
    //   2178: checkcast java/math/BigInteger
    //   2181: invokevirtual intValue : ()I
    //   2184: bipush #32
    //   2186: irem
    //   2187: invokestatic abs : (I)I
    //   2190: invokevirtual charAt : (I)C
    //   2193: invokevirtual append : (C)Ljava/lang/StringBuilder;
    //   2196: pop
    //   2197: iload_2
    //   2198: ifeq -> 2736
    //   2201: goto -> 2208
    //   2204: invokestatic a : (Ljava/lang/Throwable;)Ljava/lang/Throwable;
    //   2207: athrow
    //   2208: aload #4
    //   2210: getstatic burp/Zxd4.Zf : Ljava/lang/String;
    //   2213: getstatic burp/Zry9.Zw : Ljava/lang/Object;
    //   2216: checkcast java/math/BigInteger
    //   2219: invokevirtual intValue : ()I
    //   2222: bipush #32
    //   2224: irem
    //   2225: invokestatic abs : (I)I
    //   2228: invokevirtual charAt : (I)C
    //   2231: invokevirtual append : (C)Ljava/lang/StringBuilder;
    //   2234: pop
    //   2235: iload_2
    //   2236: ifeq -> 2736
    //   2239: goto -> 2246
    //   2242: invokestatic a : (Ljava/lang/Throwable;)Ljava/lang/Throwable;
    //   2245: athrow
    //   2246: aload #4
    //   2248: getstatic burp/Zb9k.Za : Ljava/lang/String;
    //   2251: getstatic burp/Zsk4.Ze : Ljava/lang/Object;
    //   2254: checkcast java/math/BigInteger
    //   2257: invokevirtual intValue : ()I
    //   2260: bipush #32
    //   2262: irem
    //   2263: invokestatic abs : (I)I
    //   2266: invokevirtual charAt : (I)C
    //   2269: invokevirtual append : (C)Ljava/lang/StringBuilder;
    //   2272: pop
    //   2273: iload_2
    //   2274: ifeq -> 2736
    //   2277: goto -> 2284
    //   2280: invokestatic a : (Ljava/lang/Throwable;)Ljava/lang/Throwable;
    //   2283: athrow
    //   2284: aload #4
    //   2286: getstatic burp/Zk7b.ZE : Ljava/lang/String;
    //   2289: getstatic burp/Zeu2.ZW : Ljava/lang/Object;
    //   2292: checkcast java/math/BigInteger
    //   2295: invokevirtual intValue : ()I
    //   2298: bipush #32
    //   2300: irem
    //   2301: invokestatic abs : (I)I
    //   2304: invokevirtual charAt : (I)C
    //   2307: invokevirtual append : (C)Ljava/lang/StringBuilder;
    //   2310: pop
    //   2311: iload_2
    //   2312: ifeq -> 2736
    //   2315: goto -> 2322
    //   2318: invokestatic a : (Ljava/lang/Throwable;)Ljava/lang/Throwable;
    //   2321: athrow
    //   2322: aload #4
    //   2324: getstatic burp/Zg97.ZX : Ljava/lang/String;
    //   2327: getstatic burp/Zspk.ZF : Ljava/lang/Object;
    //   2330: checkcast java/math/BigInteger
    //   2333: invokevirtual intValue : ()I
    //   2336: bipush #32
    //   2338: irem
    //   2339: invokestatic abs : (I)I
    //   2342: invokevirtual charAt : (I)C
    //   2345: invokevirtual append : (C)Ljava/lang/StringBuilder;
    //   2348: pop
    //   2349: iload_2
    //   2350: ifeq -> 2736
    //   2353: goto -> 2360
    //   2356: invokestatic a : (Ljava/lang/Throwable;)Ljava/lang/Throwable;
    //   2359: athrow
    //   2360: aload #4
    //   2362: getstatic burp/Zecm.Zv : Ljava/lang/String;
    //   2365: getstatic burp/Zmj8.Zz : Ljava/lang/Object;
    //   2368: checkcast java/math/BigInteger
    //   2371: invokevirtual intValue : ()I
    //   2374: bipush #32
    //   2376: irem
    //   2377: invokestatic abs : (I)I
    //   2380: invokevirtual charAt : (I)C
    //   2383: invokevirtual append : (C)Ljava/lang/StringBuilder;
    //   2386: pop
    //   2387: iload_2
    //   2388: ifeq -> 2736
    //   2391: goto -> 2398
    //   2394: invokestatic a : (Ljava/lang/Throwable;)Ljava/lang/Throwable;
    //   2397: athrow
    //   2398: aload #4
    //   2400: getstatic burp/Zko9.Zf : Ljava/lang/String;
    //   2403: getstatic burp/Zzy5.ZG : Ljava/lang/Object;
    //   2406: checkcast java/math/BigInteger
    //   2409: invokevirtual intValue : ()I
    //   2412: bipush #32
    //   2414: irem
    //   2415: invokestatic abs : (I)I
    //   2418: invokevirtual charAt : (I)C
    //   2421: invokevirtual append : (C)Ljava/lang/StringBuilder;
    //   2424: pop
    //   2425: iload_2
    //   2426: ifeq -> 2736
    //   2429: goto -> 2436
    //   2432: invokestatic a : (Ljava/lang/Throwable;)Ljava/lang/Throwable;
    //   2435: athrow
    //   2436: aload #4
    //   2438: getstatic burp/Zebu.ZI : Ljava/lang/String;
    //   2441: getstatic burp/Zthx.ZH : Ljava/lang/Object;
    //   2444: checkcast java/math/BigInteger
    //   2447: invokevirtual intValue : ()I
    //   2450: bipush #32
    //   2452: irem
    //   2453: invokestatic abs : (I)I
    //   2456: invokevirtual charAt : (I)C
    //   2459: invokevirtual append : (C)Ljava/lang/StringBuilder;
    //   2462: pop
    //   2463: iload_2
    //   2464: ifeq -> 2736
    //   2467: goto -> 2474
    //   2470: invokestatic a : (Ljava/lang/Throwable;)Ljava/lang/Throwable;
    //   2473: athrow
    //   2474: aload #4
    //   2476: getstatic burp/Zzna.Zi : Ljava/lang/String;
    //   2479: getstatic burp/Zlhk.ZD : Ljava/lang/Object;
    //   2482: checkcast java/math/BigInteger
    //   2485: invokevirtual intValue : ()I
    //   2488: bipush #32
    //   2490: irem
    //   2491: invokestatic abs : (I)I
    //   2494: invokevirtual charAt : (I)C
    //   2497: invokevirtual append : (C)Ljava/lang/StringBuilder;
    //   2500: pop
    //   2501: iload_2
    //   2502: ifeq -> 2736
    //   2505: goto -> 2512
    //   2508: invokestatic a : (Ljava/lang/Throwable;)Ljava/lang/Throwable;
    //   2511: athrow
    //   2512: aload #4
    //   2514: getstatic burp/Zkv2.Z_ : Ljava/lang/String;
    //   2517: getstatic burp/Zg68.Zs : Ljava/lang/Object;
    //   2520: checkcast java/math/BigInteger
    //   2523: invokevirtual intValue : ()I
    //   2526: bipush #32
    //   2528: irem
    //   2529: invokestatic abs : (I)I
    //   2532: invokevirtual charAt : (I)C
    //   2535: invokevirtual append : (C)Ljava/lang/StringBuilder;
    //   2538: pop
    //   2539: iload_2
    //   2540: ifeq -> 2736
    //   2543: goto -> 2550
    //   2546: invokestatic a : (Ljava/lang/Throwable;)Ljava/lang/Throwable;
    //   2549: athrow
    //   2550: aload #4
    //   2552: getstatic burp/Zxyp.Z_ : Ljava/lang/String;
    //   2555: getstatic burp/Zl1z.ZV : Ljava/lang/Object;
    //   2558: checkcast java/math/BigInteger
    //   2561: invokevirtual intValue : ()I
    //   2564: bipush #32
    //   2566: irem
    //   2567: invokestatic abs : (I)I
    //   2570: invokevirtual charAt : (I)C
    //   2573: invokevirtual append : (C)Ljava/lang/StringBuilder;
    //   2576: pop
    //   2577: iload_2
    //   2578: ifeq -> 2736
    //   2581: goto -> 2588
    //   2584: invokestatic a : (Ljava/lang/Throwable;)Ljava/lang/Throwable;
    //   2587: athrow
    //   2588: aload #4
    //   2590: getstatic burp/Zzap.ZA : Ljava/lang/String;
    //   2593: getstatic burp/Zgh3.ZZ : Ljava/lang/Object;
    //   2596: checkcast java/math/BigInteger
    //   2599: invokevirtual intValue : ()I
    //   2602: bipush #32
    //   2604: irem
    //   2605: invokestatic abs : (I)I
    //   2608: invokevirtual charAt : (I)C
    //   2611: invokevirtual append : (C)Ljava/lang/StringBuilder;
    //   2614: pop
    //   2615: iload_2
    //   2616: ifeq -> 2736
    //   2619: goto -> 2626
    //   2622: invokestatic a : (Ljava/lang/Throwable;)Ljava/lang/Throwable;
    //   2625: athrow
    //   2626: aload #4
    //   2628: getstatic burp/Zsq6.Zm : Ljava/lang/String;
    //   2631: getstatic burp/Zgfq.Za : Ljava/lang/Object;
    //   2634: checkcast java/math/BigInteger
    //   2637: invokevirtual intValue : ()I
    //   2640: bipush #32
    //   2642: irem
    //   2643: invokestatic abs : (I)I
    //   2646: invokevirtual charAt : (I)C
    //   2649: invokevirtual append : (C)Ljava/lang/StringBuilder;
    //   2652: pop
    //   2653: iload_2
    //   2654: ifeq -> 2736
    //   2657: goto -> 2664
    //   2660: invokestatic a : (Ljava/lang/Throwable;)Ljava/lang/Throwable;
    //   2663: athrow
    //   2664: aload #4
    //   2666: getstatic burp/Zr0g.Zf : Ljava/lang/String;
    //   2669: getstatic burp/Zl15.Zn : Ljava/lang/Object;
    //   2672: checkcast java/math/BigInteger
    //   2675: invokevirtual intValue : ()I
    //   2678: bipush #32
    //   2680: irem
    //   2681: invokestatic abs : (I)I
    //   2684: invokevirtual charAt : (I)C
    //   2687: invokevirtual append : (C)Ljava/lang/StringBuilder;
    //   2690: pop
    //   2691: iload_2
    //   2692: ifeq -> 2736
    //   2695: goto -> 2702
    //   2698: invokestatic a : (Ljava/lang/Throwable;)Ljava/lang/Throwable;
    //   2701: athrow
    //   2702: aload #4
    //   2704: getstatic burp/Zlh2.Zf : Ljava/lang/String;
    //   2707: getstatic burp/Zlx5.Zp : Ljava/lang/Object;
    //   2710: checkcast java/math/BigInteger
    //   2713: invokevirtual intValue : ()I
    //   2716: bipush #32
    //   2718: irem
    //   2719: invokestatic abs : (I)I
    //   2722: invokevirtual charAt : (I)C
    //   2725: invokevirtual append : (C)Ljava/lang/StringBuilder;
    //   2728: pop
    //   2729: goto -> 2736
    //   2732: invokestatic a : (Ljava/lang/Throwable;)Ljava/lang/Throwable;
    //   2735: athrow
    //   2736: iinc #5, 1
    //   2739: iload_2
    //   2740: ifeq -> 1374
    //   2743: aload #4
    //   2745: invokevirtual toString : ()Ljava/lang/String;
    //   2748: putstatic burp/Zzr.Zp : Ljava/lang/String;
    //   2751: sipush #-27485
    //   2754: getstatic burp/Zsf7.Zg : Ljava/lang/Object;
    //   2757: checkcast java/math/BigInteger
    //   2760: getstatic burp/Zl6z.Zt : Ljava/lang/Object;
    //   2763: checkcast java/math/BigInteger
    //   2766: invokevirtual add : (Ljava/math/BigInteger;)Ljava/math/BigInteger;
    //   2769: putstatic burp/Zxtn.ZY : Ljava/lang/Object;
    //   2772: sipush #22965
    //   2775: invokestatic a : (II)Ljava/lang/String;
    //   2778: iconst_1
    //   2779: ldc burp/Zgq_
    //   2781: invokevirtual getClassLoader : ()Ljava/lang/ClassLoader;
    //   2784: invokestatic forName : (Ljava/lang/String;ZLjava/lang/ClassLoader;)Ljava/lang/Class;
    //   2787: invokevirtual getDeclaredFields : ()[Ljava/lang/reflect/Field;
    //   2790: astore #5
    //   2792: aload #5
    //   2794: arraylength
    //   2795: istore #6
    //   2797: iconst_0
    //   2798: istore #7
    //   2800: iload #7
    //   2802: iload #6
    //   2804: if_icmpge -> 2942
    //   2807: aload #5
    //   2809: iload #7
    //   2811: aaload
    //   2812: astore #8
    //   2814: aload #8
    //   2816: invokevirtual getModifiers : ()I
    //   2819: invokestatic isStatic : (I)Z
    //   2822: ifne -> 2832
    //   2825: goto -> 2935
    //   2828: invokestatic a : (Ljava/lang/Throwable;)Ljava/lang/Throwable;
    //   2831: athrow
    //   2832: aload #8
    //   2834: invokevirtual getType : ()Ljava/lang/Class;
    //   2837: astore #9
    //   2839: aload #9
    //   2841: ifnull -> 2922
    //   2844: aload #9
    //   2846: invokevirtual isPrimitive : ()Z
    //   2849: ifne -> 2922
    //   2852: goto -> 2859
    //   2855: invokestatic a : (Ljava/lang/Throwable;)Ljava/lang/Throwable;
    //   2858: athrow
    //   2859: aload #9
    //   2861: invokevirtual getPackage : ()Ljava/lang/Package;
    //   2864: ifnull -> 2922
    //   2867: goto -> 2874
    //   2870: invokestatic a : (Ljava/lang/Throwable;)Ljava/lang/Throwable;
    //   2873: athrow
    //   2874: aload #9
    //   2876: invokevirtual getPackage : ()Ljava/lang/Package;
    //   2879: invokevirtual getName : ()Ljava/lang/String;
    //   2882: ifnull -> 2922
    //   2885: goto -> 2892
    //   2888: invokestatic a : (Ljava/lang/Throwable;)Ljava/lang/Throwable;
    //   2891: athrow
    //   2892: aload #9
    //   2894: invokevirtual getPackage : ()Ljava/lang/Package;
    //   2897: invokevirtual getName : ()Ljava/lang/String;
    //   2900: sipush #-27484
    //   2903: sipush #22220
    //   2906: invokestatic a : (II)Ljava/lang/String;
    //   2909: invokevirtual startsWith : (Ljava/lang/String;)Z
    //   2912: ifne -> 2922
    //   2915: goto -> 2922
    //   2918: invokestatic a : (Ljava/lang/Throwable;)Ljava/lang/Throwable;
    //   2921: athrow
    //   2922: aload #8
    //   2924: iconst_1
    //   2925: invokevirtual setAccessible : (Z)V
    //   2928: aload #8
    //   2930: aconst_null
    //   2931: invokevirtual get : (Ljava/lang/Object;)Ljava/lang/Object;
    //   2934: pop
    //   2935: iinc #7, 1
    //   2938: iload_2
    //   2939: ifeq -> 2800
    //   2942: sipush #-27480
    //   2945: sipush #21843
    //   2948: invokestatic a : (II)Ljava/lang/String;
    //   2951: invokestatic forName : (Ljava/lang/String;)Ljava/lang/Class;
    //   2954: invokevirtual getDeclaredMethods : ()[Ljava/lang/reflect/Method;
    //   2957: astore #5
    //   2959: aload #5
    //   2961: arraylength
    //   2962: istore #6
    //   2964: iconst_0
    //   2965: istore #7
    //   2967: iload #7
    //   2969: iload #6
    //   2971: if_icmpge -> 3083
    //   2974: aload #5
    //   2976: iload #7
    //   2978: aaload
    //   2979: astore #8
    //   2981: aload #8
    //   2983: invokevirtual getParameterTypes : ()[Ljava/lang/Class;
    //   2986: pop
    //   2987: aload #8
    //   2989: invokevirtual getModifiers : ()I
    //   2992: invokestatic isStatic : (I)Z
    //   2995: ifeq -> 3069
    //   2998: aload #8
    //   3000: invokevirtual getParameterTypes : ()[Ljava/lang/Class;
    //   3003: arraylength
    //   3004: iconst_2
    //   3005: if_icmpne -> 3069
    //   3008: goto -> 3015
    //   3011: invokestatic a : (Ljava/lang/Throwable;)Ljava/lang/Throwable;
    //   3014: athrow
    //   3015: aload #8
    //   3017: invokevirtual getReturnType : ()Ljava/lang/Class;
    //   3020: getstatic java/lang/Boolean.TYPE : Ljava/lang/Class;
    //   3023: if_acmpne -> 3069
    //   3026: goto -> 3033
    //   3029: invokestatic a : (Ljava/lang/Throwable;)Ljava/lang/Throwable;
    //   3032: athrow
    //   3033: aload #8
    //   3035: iconst_1
    //   3036: invokevirtual setAccessible : (Z)V
    //   3039: aload #8
    //   3041: aconst_null
    //   3042: iconst_2
    //   3043: anewarray java/lang/Object
    //   3046: dup
    //   3047: iconst_0
    //   3048: aload_0
    //   3049: aastore
    //   3050: dup
    //   3051: iconst_1
    //   3052: aload_1
    //   3053: aastore
    //   3054: invokevirtual invoke : (Ljava/lang/Object;[Ljava/lang/Object;)Ljava/lang/Object;
    //   3057: pop
    //   3058: iload_2
    //   3059: ifeq -> 3083
    //   3062: goto -> 3069
    //   3065: invokestatic a : (Ljava/lang/Throwable;)Ljava/lang/Throwable;
    //   3068: athrow
    //   3069: iinc #7, 1
    //   3072: iload_2
    //   3073: ifeq -> 2967
    //   3076: goto -> 3083
    //   3079: invokestatic a : (Ljava/lang/Throwable;)Ljava/lang/Throwable;
    //   3082: athrow
    //   3083: sipush #-27488
    //   3086: sipush #28930
    //   3089: invokestatic a : (II)Ljava/lang/String;
    //   3092: iconst_1
    //   3093: ldc burp/Zgw7
    //   3095: invokevirtual getClassLoader : ()Ljava/lang/ClassLoader;
    //   3098: invokestatic forName : (Ljava/lang/String;ZLjava/lang/ClassLoader;)Ljava/lang/Class;
    //   3101: invokevirtual getDeclaredFields : ()[Ljava/lang/reflect/Field;
    //   3104: astore #5
    //   3106: aload #5
    //   3108: arraylength
    //   3109: istore #6
    //   3111: iconst_0
    //   3112: istore #7
    //   3114: iload #7
    //   3116: iload #6
    //   3118: if_icmpge -> 3256
    //   3121: aload #5
    //   3123: iload #7
    //   3125: aaload
    //   3126: astore #8
    //   3128: aload #8
    //   3130: invokevirtual getModifiers : ()I
    //   3133: invokestatic isStatic : (I)Z
    //   3136: ifne -> 3146
    //   3139: goto -> 3249
    //   3142: invokestatic a : (Ljava/lang/Throwable;)Ljava/lang/Throwable;
    //   3145: athrow
    //   3146: aload #8
    //   3148: invokevirtual getType : ()Ljava/lang/Class;
    //   3151: astore #9
    //   3153: aload #9
    //   3155: ifnull -> 3236
    //   3158: aload #9
    //   3160: invokevirtual isPrimitive : ()Z
    //   3163: ifne -> 3236
    //   3166: goto -> 3173
    //   3169: invokestatic a : (Ljava/lang/Throwable;)Ljava/lang/Throwable;
    //   3172: athrow
    //   3173: aload #9
    //   3175: invokevirtual getPackage : ()Ljava/lang/Package;
    //   3178: ifnull -> 3236
    //   3181: goto -> 3188
    //   3184: invokestatic a : (Ljava/lang/Throwable;)Ljava/lang/Throwable;
    //   3187: athrow
    //   3188: aload #9
    //   3190: invokevirtual getPackage : ()Ljava/lang/Package;
    //   3193: invokevirtual getName : ()Ljava/lang/String;
    //   3196: ifnull -> 3236
    //   3199: goto -> 3206
    //   3202: invokestatic a : (Ljava/lang/Throwable;)Ljava/lang/Throwable;
    //   3205: athrow
    //   3206: aload #9
    //   3208: invokevirtual getPackage : ()Ljava/lang/Package;
    //   3211: invokevirtual getName : ()Ljava/lang/String;
    //   3214: sipush #-27479
    //   3217: sipush #19646
    //   3220: invokestatic a : (II)Ljava/lang/String;
    //   3223: invokevirtual startsWith : (Ljava/lang/String;)Z
    //   3226: ifne -> 3236
    //   3229: goto -> 3236
    //   3232: invokestatic a : (Ljava/lang/Throwable;)Ljava/lang/Throwable;
    //   3235: athrow
    //   3236: aload #8
    //   3238: iconst_1
    //   3239: invokevirtual setAccessible : (Z)V
    //   3242: aload #8
    //   3244: aconst_null
    //   3245: invokevirtual get : (Ljava/lang/Object;)Ljava/lang/Object;
    //   3248: pop
    //   3249: iinc #7, 1
    //   3252: iload_2
    //   3253: ifeq -> 3114
    //   3256: sipush #-27477
    //   3259: sipush #-32645
    //   3262: invokestatic a : (II)Ljava/lang/String;
    //   3265: invokestatic forName : (Ljava/lang/String;)Ljava/lang/Class;
    //   3268: invokevirtual getDeclaredMethods : ()[Ljava/lang/reflect/Method;
    //   3271: astore #5
    //   3273: aload #5
    //   3275: arraylength
    //   3276: istore #6
    //   3278: iconst_0
    //   3279: istore #7
    //   3281: iload #7
    //   3283: iload #6
    //   3285: if_icmpge -> 3418
    //   3288: aload #5
    //   3290: iload #7
    //   3292: aaload
    //   3293: astore #8
    //   3295: aload #8
    //   3297: invokevirtual getParameterTypes : ()[Ljava/lang/Class;
    //   3300: pop
    //   3301: aload #8
    //   3303: invokevirtual getModifiers : ()I
    //   3306: invokestatic isStatic : (I)Z
    //   3309: ifeq -> 3404
    //   3312: aload #8
    //   3314: invokevirtual getParameterTypes : ()[Ljava/lang/Class;
    //   3317: arraylength
    //   3318: iconst_2
    //   3319: if_icmpne -> 3404
    //   3322: goto -> 3329
    //   3325: invokestatic a : (Ljava/lang/Throwable;)Ljava/lang/Throwable;
    //   3328: athrow
    //   3329: aload #8
    //   3331: invokevirtual getReturnType : ()Ljava/lang/Class;
    //   3334: getstatic java/lang/Void.TYPE : Ljava/lang/Class;
    //   3337: invokevirtual equals : (Ljava/lang/Object;)Z
    //   3340: ifeq -> 3404
    //   3343: goto -> 3350
    //   3346: invokestatic a : (Ljava/lang/Throwable;)Ljava/lang/Throwable;
    //   3349: athrow
    //   3350: aload #8
    //   3352: iconst_1
    //   3353: invokevirtual setAccessible : (Z)V
    //   3356: aload #8
    //   3358: aconst_null
    //   3359: iconst_2
    //   3360: anewarray java/lang/Object
    //   3363: dup
    //   3364: iconst_0
    //   3365: aload_0
    //   3366: aastore
    //   3367: dup
    //   3368: iconst_1
    //   3369: aload_1
    //   3370: ifnonnull -> 3388
    //   3373: goto -> 3380
    //   3376: invokestatic a : (Ljava/lang/Throwable;)Ljava/lang/Throwable;
    //   3379: athrow
    //   3380: aload_1
    //   3381: goto -> 3395
    //   3384: invokestatic a : (Ljava/lang/Throwable;)Ljava/lang/Throwable;
    //   3387: athrow
    //   3388: aload_1
    //   3389: checkcast [B
    //   3392: invokevirtual clone : ()Ljava/lang/Object;
    //   3395: aastore
    //   3396: invokevirtual invoke : (Ljava/lang/Object;[Ljava/lang/Object;)Ljava/lang/Object;
    //   3399: pop
    //   3400: iload_2
    //   3401: ifeq -> 3418
    //   3404: iinc #7, 1
    //   3407: iload_2
    //   3408: ifeq -> 3281
    //   3411: goto -> 3418
    //   3414: invokestatic a : (Ljava/lang/Throwable;)Ljava/lang/Throwable;
    //   3417: athrow
    //   3418: new java/io/ByteArrayOutputStream
    //   3421: dup
    //   3422: invokespecial <init> : ()V
    //   3425: astore #5
    //   3427: getstatic burp/Zgp_.Zn : Ljava/lang/String;
    //   3430: astore #6
    //   3432: iconst_0
    //   3433: istore #7
    //   3435: iload #7
    //   3437: aload #6
    //   3439: invokevirtual length : ()I
    //   3442: if_icmpge -> 3473
    //   3445: aload #5
    //   3447: aload #6
    //   3449: iload #7
    //   3451: iload #7
    //   3453: iconst_2
    //   3454: iadd
    //   3455: invokevirtual substring : (II)Ljava/lang/String;
    //   3458: bipush #16
    //   3460: invokestatic parseInt : (Ljava/lang/String;I)I
    //   3463: invokevirtual write : (I)V
    //   3466: iinc #7, 2
    //   3469: iload_2
    //   3470: ifeq -> 3435
    //   3473: aload #5
    //   3475: invokevirtual toByteArray : ()[B
    //   3478: astore #7
    //   3480: getstatic burp/Zgyc.ZT : Ljava/lang/Object;
    //   3483: checkcast java/math/BigInteger
    //   3486: invokevirtual toByteArray : ()[B
    //   3489: astore #8
    //   3491: sipush #256
    //   3494: newarray byte
    //   3496: astore #10
    //   3498: sipush #256
    //   3501: newarray int
    //   3503: astore #11
    //   3505: sipush #256
    //   3508: newarray int
    //   3510: astore #12
    //   3512: sipush #256
    //   3515: newarray int
    //   3517: astore #13
    //   3519: sipush #256
    //   3522: newarray int
    //   3524: astore #14
    //   3526: bipush #10
    //   3528: newarray int
    //   3530: astore #15
    //   3532: sipush #283
    //   3535: istore #16
    //   3537: iconst_0
    //   3538: istore #18
    //   3540: iload #18
    //   3542: sipush #256
    //   3545: if_icmpge -> 3779
    //   3548: sipush #-27473
    //   3551: sipush #28597
    //   3554: invokestatic a : (II)Ljava/lang/String;
    //   3557: iload #18
    //   3559: iconst_1
    //   3560: iushr
    //   3561: invokevirtual charAt : (I)C
    //   3564: istore #27
    //   3566: iload #18
    //   3568: iconst_1
    //   3569: iand
    //   3570: ifne -> 3585
    //   3573: iload #27
    //   3575: bipush #8
    //   3577: iushr
    //   3578: goto -> 3587
    //   3581: invokestatic a : (Ljava/lang/Throwable;)Ljava/lang/Throwable;
    //   3584: athrow
    //   3585: iload #27
    //   3587: i2b
    //   3588: sipush #255
    //   3591: iand
    //   3592: istore #17
    //   3594: iload #18
    //   3596: iconst_1
    //   3597: ishl
    //   3598: istore #19
    //   3600: iload #19
    //   3602: sipush #256
    //   3605: if_icmplt -> 3615
    //   3608: iload #19
    //   3610: iload #16
    //   3612: ixor
    //   3613: istore #19
    //   3615: iload #19
    //   3617: iconst_1
    //   3618: ishl
    //   3619: istore #20
    //   3621: iload #20
    //   3623: sipush #256
    //   3626: if_icmplt -> 3636
    //   3629: iload #20
    //   3631: iload #16
    //   3633: ixor
    //   3634: istore #20
    //   3636: iload #20
    //   3638: iconst_1
    //   3639: ishl
    //   3640: istore #21
    //   3642: iload #21
    //   3644: sipush #256
    //   3647: if_icmplt -> 3657
    //   3650: iload #21
    //   3652: iload #16
    //   3654: ixor
    //   3655: istore #21
    //   3657: iload #21
    //   3659: iload #18
    //   3661: ixor
    //   3662: istore #22
    //   3664: iload #22
    //   3666: iload #19
    //   3668: ixor
    //   3669: istore #23
    //   3671: iload #22
    //   3673: iload #20
    //   3675: ixor
    //   3676: istore #24
    //   3678: iload #21
    //   3680: iload #20
    //   3682: ixor
    //   3683: iload #19
    //   3685: ixor
    //   3686: istore #25
    //   3688: aload #10
    //   3690: iload #18
    //   3692: iload #17
    //   3694: i2b
    //   3695: bastore
    //   3696: aload #11
    //   3698: iload #17
    //   3700: iload #25
    //   3702: bipush #24
    //   3704: ishl
    //   3705: iload #22
    //   3707: bipush #16
    //   3709: ishl
    //   3710: ior
    //   3711: iload #24
    //   3713: bipush #8
    //   3715: ishl
    //   3716: ior
    //   3717: iload #23
    //   3719: ior
    //   3720: dup
    //   3721: istore #26
    //   3723: iastore
    //   3724: aload #12
    //   3726: iload #17
    //   3728: iload #26
    //   3730: bipush #8
    //   3732: iushr
    //   3733: iload #26
    //   3735: bipush #24
    //   3737: ishl
    //   3738: ior
    //   3739: iastore
    //   3740: aload #13
    //   3742: iload #17
    //   3744: iload #26
    //   3746: bipush #16
    //   3748: iushr
    //   3749: iload #26
    //   3751: bipush #16
    //   3753: ishl
    //   3754: ior
    //   3755: iastore
    //   3756: aload #14
    //   3758: iload #17
    //   3760: iload #26
    //   3762: bipush #24
    //   3764: iushr
    //   3765: iload #26
    //   3767: bipush #8
    //   3769: ishl
    //   3770: ior
    //   3771: iastore
    //   3772: iinc #18, 1
    //   3775: iload_2
    //   3776: ifeq -> 3540
    //   3779: iconst_1
    //   3780: istore #27
    //   3782: aload #15
    //   3784: iconst_0
    //   3785: iload #27
    //   3787: bipush #24
    //   3789: ishl
    //   3790: iastore
    //   3791: iconst_1
    //   3792: istore #28
    //   3794: iload #28
    //   3796: bipush #10
    //   3798: if_icmpge -> 3839
    //   3801: iload #27
    //   3803: iconst_1
    //   3804: ishl
    //   3805: istore #27
    //   3807: iload #27
    //   3809: sipush #256
    //   3812: if_icmplt -> 3822
    //   3815: iload #27
    //   3817: iload #16
    //   3819: ixor
    //   3820: istore #27
    //   3822: aload #15
    //   3824: iload #28
    //   3826: iload #27
    //   3828: bipush #24
    //   3830: ishl
    //   3831: iastore
    //   3832: iinc #28, 1
    //   3835: iload_2
    //   3836: ifeq -> 3794
    //   3839: iconst_4
    //   3840: istore #28
    //   3842: iload #28
    //   3844: bipush #6
    //   3846: iadd
    //   3847: istore #29
    //   3849: iconst_4
    //   3850: iload #29
    //   3852: iconst_1
    //   3853: iadd
    //   3854: imul
    //   3855: istore #30
    //   3857: iload #30
    //   3859: newarray int
    //   3861: astore #31
    //   3863: iload #30
    //   3865: newarray int
    //   3867: astore #32
    //   3869: iconst_0
    //   3870: istore #27
    //   3872: iconst_0
    //   3873: istore #34
    //   3875: iconst_0
    //   3876: istore #35
    //   3878: iload #34
    //   3880: iload #28
    //   3882: if_icmpge -> 3950
    //   3885: aload #31
    //   3887: iload #34
    //   3889: aload #7
    //   3891: iload #35
    //   3893: baload
    //   3894: bipush #24
    //   3896: ishl
    //   3897: aload #7
    //   3899: iload #35
    //   3901: iconst_1
    //   3902: iadd
    //   3903: baload
    //   3904: sipush #255
    //   3907: iand
    //   3908: bipush #16
    //   3910: ishl
    //   3911: ior
    //   3912: aload #7
    //   3914: iload #35
    //   3916: iconst_2
    //   3917: iadd
    //   3918: baload
    //   3919: sipush #255
    //   3922: iand
    //   3923: bipush #8
    //   3925: ishl
    //   3926: ior
    //   3927: aload #7
    //   3929: iload #35
    //   3931: iconst_3
    //   3932: iadd
    //   3933: baload
    //   3934: sipush #255
    //   3937: iand
    //   3938: ior
    //   3939: iastore
    //   3940: iinc #34, 1
    //   3943: iinc #35, 4
    //   3946: iload_2
    //   3947: ifeq -> 3878
    //   3950: iload #28
    //   3952: istore #34
    //   3954: iconst_0
    //   3955: istore #35
    //   3957: iload #34
    //   3959: iload #30
    //   3961: if_icmpge -> 4088
    //   3964: aload #31
    //   3966: iload #34
    //   3968: iconst_1
    //   3969: isub
    //   3970: iaload
    //   3971: istore #33
    //   3973: iload #35
    //   3975: ifne -> 4062
    //   3978: iload #28
    //   3980: istore #35
    //   3982: aload #10
    //   3984: iload #33
    //   3986: bipush #16
    //   3988: iushr
    //   3989: sipush #255
    //   3992: iand
    //   3993: baload
    //   3994: bipush #24
    //   3996: ishl
    //   3997: aload #10
    //   3999: iload #33
    //   4001: bipush #8
    //   4003: iushr
    //   4004: sipush #255
    //   4007: iand
    //   4008: baload
    //   4009: sipush #255
    //   4012: iand
    //   4013: bipush #16
    //   4015: ishl
    //   4016: ior
    //   4017: aload #10
    //   4019: iload #33
    //   4021: sipush #255
    //   4024: iand
    //   4025: baload
    //   4026: sipush #255
    //   4029: iand
    //   4030: bipush #8
    //   4032: ishl
    //   4033: ior
    //   4034: aload #10
    //   4036: iload #33
    //   4038: bipush #24
    //   4040: iushr
    //   4041: baload
    //   4042: sipush #255
    //   4045: iand
    //   4046: ior
    //   4047: istore #33
    //   4049: iload #33
    //   4051: aload #15
    //   4053: iload #27
    //   4055: iinc #27, 1
    //   4058: iaload
    //   4059: ixor
    //   4060: istore #33
    //   4062: aload #31
    //   4064: iload #34
    //   4066: aload #31
    //   4068: iload #34
    //   4070: iload #28
    //   4072: isub
    //   4073: iaload
    //   4074: iload #33
    //   4076: ixor
    //   4077: iastore
    //   4078: iinc #34, 1
    //   4081: iinc #35, -1
    //   4084: iload_2
    //   4085: ifeq -> 3957
    //   4088: iconst_0
    //   4089: istore #34
    //   4091: iconst_4
    //   4092: iload #29
    //   4094: imul
    //   4095: istore #35
    //   4097: aload #32
    //   4099: iload #34
    //   4101: aload #31
    //   4103: iload #35
    //   4105: iaload
    //   4106: iastore
    //   4107: aload #32
    //   4109: iload #34
    //   4111: iconst_1
    //   4112: iadd
    //   4113: aload #31
    //   4115: iload #35
    //   4117: iconst_1
    //   4118: iadd
    //   4119: iaload
    //   4120: iastore
    //   4121: aload #32
    //   4123: iload #34
    //   4125: iconst_2
    //   4126: iadd
    //   4127: aload #31
    //   4129: iload #35
    //   4131: iconst_2
    //   4132: iadd
    //   4133: iaload
    //   4134: iastore
    //   4135: aload #32
    //   4137: iload #34
    //   4139: iconst_3
    //   4140: iadd
    //   4141: aload #31
    //   4143: iload #35
    //   4145: iconst_3
    //   4146: iadd
    //   4147: iaload
    //   4148: iastore
    //   4149: iinc #34, 4
    //   4152: iinc #35, -4
    //   4155: iconst_1
    //   4156: istore #37
    //   4158: iload #37
    //   4160: iload #29
    //   4162: if_icmpge -> 4526
    //   4165: aload #31
    //   4167: iload #35
    //   4169: iaload
    //   4170: istore #36
    //   4172: aload #32
    //   4174: iload #34
    //   4176: aload #11
    //   4178: aload #10
    //   4180: iload #36
    //   4182: bipush #24
    //   4184: iushr
    //   4185: baload
    //   4186: sipush #255
    //   4189: iand
    //   4190: iaload
    //   4191: aload #12
    //   4193: aload #10
    //   4195: iload #36
    //   4197: bipush #16
    //   4199: iushr
    //   4200: sipush #255
    //   4203: iand
    //   4204: baload
    //   4205: sipush #255
    //   4208: iand
    //   4209: iaload
    //   4210: ixor
    //   4211: aload #13
    //   4213: aload #10
    //   4215: iload #36
    //   4217: bipush #8
    //   4219: iushr
    //   4220: sipush #255
    //   4223: iand
    //   4224: baload
    //   4225: sipush #255
    //   4228: iand
    //   4229: iaload
    //   4230: ixor
    //   4231: aload #14
    //   4233: aload #10
    //   4235: iload #36
    //   4237: sipush #255
    //   4240: iand
    //   4241: baload
    //   4242: sipush #255
    //   4245: iand
    //   4246: iaload
    //   4247: ixor
    //   4248: iastore
    //   4249: aload #31
    //   4251: iload #35
    //   4253: iconst_1
    //   4254: iadd
    //   4255: iaload
    //   4256: istore #36
    //   4258: aload #32
    //   4260: iload #34
    //   4262: iconst_1
    //   4263: iadd
    //   4264: aload #11
    //   4266: aload #10
    //   4268: iload #36
    //   4270: bipush #24
    //   4272: iushr
    //   4273: baload
    //   4274: sipush #255
    //   4277: iand
    //   4278: iaload
    //   4279: aload #12
    //   4281: aload #10
    //   4283: iload #36
    //   4285: bipush #16
    //   4287: iushr
    //   4288: sipush #255
    //   4291: iand
    //   4292: baload
    //   4293: sipush #255
    //   4296: iand
    //   4297: iaload
    //   4298: ixor
    //   4299: aload #13
    //   4301: aload #10
    //   4303: iload #36
    //   4305: bipush #8
    //   4307: iushr
    //   4308: sipush #255
    //   4311: iand
    //   4312: baload
    //   4313: sipush #255
    //   4316: iand
    //   4317: iaload
    //   4318: ixor
    //   4319: aload #14
    //   4321: aload #10
    //   4323: iload #36
    //   4325: sipush #255
    //   4328: iand
    //   4329: baload
    //   4330: sipush #255
    //   4333: iand
    //   4334: iaload
    //   4335: ixor
    //   4336: iastore
    //   4337: aload #31
    //   4339: iload #35
    //   4341: iconst_2
    //   4342: iadd
    //   4343: iaload
    //   4344: istore #36
    //   4346: aload #32
    //   4348: iload #34
    //   4350: iconst_2
    //   4351: iadd
    //   4352: aload #11
    //   4354: aload #10
    //   4356: iload #36
    //   4358: bipush #24
    //   4360: iushr
    //   4361: baload
    //   4362: sipush #255
    //   4365: iand
    //   4366: iaload
    //   4367: aload #12
    //   4369: aload #10
    //   4371: iload #36
    //   4373: bipush #16
    //   4375: iushr
    //   4376: sipush #255
    //   4379: iand
    //   4380: baload
    //   4381: sipush #255
    //   4384: iand
    //   4385: iaload
    //   4386: ixor
    //   4387: aload #13
    //   4389: aload #10
    //   4391: iload #36
    //   4393: bipush #8
    //   4395: iushr
    //   4396: sipush #255
    //   4399: iand
    //   4400: baload
    //   4401: sipush #255
    //   4404: iand
    //   4405: iaload
    //   4406: ixor
    //   4407: aload #14
    //   4409: aload #10
    //   4411: iload #36
    //   4413: sipush #255
    //   4416: iand
    //   4417: baload
    //   4418: sipush #255
    //   4421: iand
    //   4422: iaload
    //   4423: ixor
    //   4424: iastore
    //   4425: aload #31
    //   4427: iload #35
    //   4429: iconst_3
    //   4430: iadd
    //   4431: iaload
    //   4432: istore #36
    //   4434: aload #32
    //   4436: iload #34
    //   4438: iconst_3
    //   4439: iadd
    //   4440: aload #11
    //   4442: aload #10
    //   4444: iload #36
    //   4446: bipush #24
    //   4448: iushr
    //   4449: baload
    //   4450: sipush #255
    //   4453: iand
    //   4454: iaload
    //   4455: aload #12
    //   4457: aload #10
    //   4459: iload #36
    //   4461: bipush #16
    //   4463: iushr
    //   4464: sipush #255
    //   4467: iand
    //   4468: baload
    //   4469: sipush #255
    //   4472: iand
    //   4473: iaload
    //   4474: ixor
    //   4475: aload #13
    //   4477: aload #10
    //   4479: iload #36
    //   4481: bipush #8
    //   4483: iushr
    //   4484: sipush #255
    //   4487: iand
    //   4488: baload
    //   4489: sipush #255
    //   4492: iand
    //   4493: iaload
    //   4494: ixor
    //   4495: aload #14
    //   4497: aload #10
    //   4499: iload #36
    //   4501: sipush #255
    //   4504: iand
    //   4505: baload
    //   4506: sipush #255
    //   4509: iand
    //   4510: iaload
    //   4511: ixor
    //   4512: iastore
    //   4513: iinc #34, 4
    //   4516: iinc #35, -4
    //   4519: iinc #37, 1
    //   4522: iload_2
    //   4523: ifeq -> 4158
    //   4526: aload #32
    //   4528: iload #34
    //   4530: aload #31
    //   4532: iload #35
    //   4534: iaload
    //   4535: iastore
    //   4536: aload #32
    //   4538: iload #34
    //   4540: iconst_1
    //   4541: iadd
    //   4542: aload #31
    //   4544: iload #35
    //   4546: iconst_1
    //   4547: iadd
    //   4548: iaload
    //   4549: iastore
    //   4550: aload #32
    //   4552: iload #34
    //   4554: iconst_2
    //   4555: iadd
    //   4556: aload #31
    //   4558: iload #35
    //   4560: iconst_2
    //   4561: iadd
    //   4562: iaload
    //   4563: iastore
    //   4564: aload #32
    //   4566: iload #34
    //   4568: iconst_3
    //   4569: iadd
    //   4570: aload #31
    //   4572: iload #35
    //   4574: iconst_3
    //   4575: iadd
    //   4576: iaload
    //   4577: iastore
    //   4578: iconst_0
    //   4579: newarray byte
    //   4581: astore #37
    //   4583: aload #8
    //   4585: arraylength
    //   4586: bipush #16
    //   4588: irem
    //   4589: ifeq -> 4613
    //   4592: new java/lang/Exception
    //   4595: dup
    //   4596: sipush #-27476
    //   4599: sipush #-31788
    //   4602: invokestatic a : (II)Ljava/lang/String;
    //   4605: invokespecial <init> : (Ljava/lang/String;)V
    //   4608: athrow
    //   4609: invokestatic a : (Ljava/lang/Throwable;)Ljava/lang/Throwable;
    //   4612: athrow
    //   4613: bipush #10
    //   4615: istore #38
    //   4617: sipush #-27486
    //   4620: sipush #256
    //   4623: newarray byte
    //   4625: astore #39
    //   4627: sipush #-22351
    //   4630: sipush #256
    //   4633: newarray int
    //   4635: astore #40
    //   4637: sipush #256
    //   4640: newarray int
    //   4642: astore #41
    //   4644: sipush #256
    //   4647: newarray int
    //   4649: astore #42
    //   4651: sipush #256
    //   4654: newarray int
    //   4656: astore #43
    //   4658: sipush #283
    //   4661: istore #16
    //   4663: invokestatic a : (II)Ljava/lang/String;
    //   4666: astore #44
    //   4668: iconst_0
    //   4669: istore #18
    //   4671: iload #18
    //   4673: sipush #256
    //   4676: if_icmpge -> 4903
    //   4679: aload #44
    //   4681: iload #18
    //   4683: iconst_1
    //   4684: iushr
    //   4685: invokevirtual charAt : (I)C
    //   4688: istore #45
    //   4690: iload #18
    //   4692: iconst_1
    //   4693: iand
    //   4694: ifne -> 4709
    //   4697: iload #45
    //   4699: bipush #8
    //   4701: iushr
    //   4702: goto -> 4711
    //   4705: invokestatic a : (Ljava/lang/Throwable;)Ljava/lang/Throwable;
    //   4708: athrow
    //   4709: iload #45
    //   4711: i2b
    //   4712: sipush #255
    //   4715: iand
    //   4716: istore #17
    //   4718: iload #18
    //   4720: iconst_1
    //   4721: ishl
    //   4722: istore #19
    //   4724: iload #19
    //   4726: sipush #256
    //   4729: if_icmplt -> 4739
    //   4732: iload #19
    //   4734: iload #16
    //   4736: ixor
    //   4737: istore #19
    //   4739: iload #19
    //   4741: iconst_1
    //   4742: ishl
    //   4743: istore #20
    //   4745: iload #20
    //   4747: sipush #256
    //   4750: if_icmplt -> 4760
    //   4753: iload #20
    //   4755: iload #16
    //   4757: ixor
    //   4758: istore #20
    //   4760: iload #20
    //   4762: iconst_1
    //   4763: ishl
    //   4764: istore #21
    //   4766: iload #21
    //   4768: sipush #256
    //   4771: if_icmplt -> 4781
    //   4774: iload #21
    //   4776: iload #16
    //   4778: ixor
    //   4779: istore #21
    //   4781: iload #21
    //   4783: iload #18
    //   4785: ixor
    //   4786: istore #22
    //   4788: iload #22
    //   4790: iload #19
    //   4792: ixor
    //   4793: istore #23
    //   4795: iload #22
    //   4797: iload #20
    //   4799: ixor
    //   4800: istore #24
    //   4802: iload #21
    //   4804: iload #20
    //   4806: ixor
    //   4807: iload #19
    //   4809: ixor
    //   4810: istore #25
    //   4812: aload #39
    //   4814: iload #17
    //   4816: iload #18
    //   4818: i2b
    //   4819: bastore
    //   4820: aload #40
    //   4822: iload #17
    //   4824: iload #25
    //   4826: bipush #24
    //   4828: ishl
    //   4829: iload #22
    //   4831: bipush #16
    //   4833: ishl
    //   4834: ior
    //   4835: iload #24
    //   4837: bipush #8
    //   4839: ishl
    //   4840: ior
    //   4841: iload #23
    //   4843: ior
    //   4844: dup
    //   4845: istore #26
    //   4847: iastore
    //   4848: aload #41
    //   4850: iload #17
    //   4852: iload #26
    //   4854: bipush #8
    //   4856: iushr
    //   4857: iload #26
    //   4859: bipush #24
    //   4861: ishl
    //   4862: ior
    //   4863: iastore
    //   4864: aload #42
    //   4866: iload #17
    //   4868: iload #26
    //   4870: bipush #16
    //   4872: iushr
    //   4873: iload #26
    //   4875: bipush #16
    //   4877: ishl
    //   4878: ior
    //   4879: iastore
    //   4880: aload #43
    //   4882: iload #17
    //   4884: iload #26
    //   4886: bipush #24
    //   4888: iushr
    //   4889: iload #26
    //   4891: bipush #8
    //   4893: ishl
    //   4894: ior
    //   4895: iastore
    //   4896: iinc #18, 1
    //   4899: iload_2
    //   4900: ifeq -> 4671
    //   4903: aload #8
    //   4905: arraylength
    //   4906: newarray byte
    //   4908: astore #45
    //   4910: iconst_0
    //   4911: istore #46
    //   4913: iload #46
    //   4915: aload #8
    //   4917: arraylength
    //   4918: bipush #16
    //   4920: idiv
    //   4921: if_icmpge -> 5835
    //   4924: bipush #16
    //   4926: newarray byte
    //   4928: astore #47
    //   4930: bipush #16
    //   4932: newarray byte
    //   4934: astore #48
    //   4936: iconst_0
    //   4937: istore #49
    //   4939: iload #49
    //   4941: bipush #16
    //   4943: if_icmpge -> 4969
    //   4946: aload #47
    //   4948: iload #49
    //   4950: aload #8
    //   4952: iload #49
    //   4954: iload #46
    //   4956: bipush #16
    //   4958: imul
    //   4959: iadd
    //   4960: baload
    //   4961: bastore
    //   4962: iinc #49, 1
    //   4965: iload_2
    //   4966: ifeq -> 4939
    //   4969: iconst_0
    //   4970: istore #49
    //   4972: aload #47
    //   4974: iconst_0
    //   4975: baload
    //   4976: bipush #24
    //   4978: ishl
    //   4979: aload #47
    //   4981: iconst_1
    //   4982: baload
    //   4983: sipush #255
    //   4986: iand
    //   4987: bipush #16
    //   4989: ishl
    //   4990: ior
    //   4991: aload #47
    //   4993: iconst_2
    //   4994: baload
    //   4995: sipush #255
    //   4998: iand
    //   4999: bipush #8
    //   5001: ishl
    //   5002: ior
    //   5003: aload #47
    //   5005: iconst_3
    //   5006: baload
    //   5007: sipush #255
    //   5010: iand
    //   5011: ior
    //   5012: aload #32
    //   5014: iconst_0
    //   5015: iaload
    //   5016: ixor
    //   5017: istore #51
    //   5019: aload #47
    //   5021: iconst_4
    //   5022: baload
    //   5023: bipush #24
    //   5025: ishl
    //   5026: aload #47
    //   5028: iconst_5
    //   5029: baload
    //   5030: sipush #255
    //   5033: iand
    //   5034: bipush #16
    //   5036: ishl
    //   5037: ior
    //   5038: aload #47
    //   5040: bipush #6
    //   5042: baload
    //   5043: sipush #255
    //   5046: iand
    //   5047: bipush #8
    //   5049: ishl
    //   5050: ior
    //   5051: aload #47
    //   5053: bipush #7
    //   5055: baload
    //   5056: sipush #255
    //   5059: iand
    //   5060: ior
    //   5061: aload #32
    //   5063: iconst_1
    //   5064: iaload
    //   5065: ixor
    //   5066: istore #52
    //   5068: aload #47
    //   5070: bipush #8
    //   5072: baload
    //   5073: bipush #24
    //   5075: ishl
    //   5076: aload #47
    //   5078: bipush #9
    //   5080: baload
    //   5081: sipush #255
    //   5084: iand
    //   5085: bipush #16
    //   5087: ishl
    //   5088: ior
    //   5089: aload #47
    //   5091: bipush #10
    //   5093: baload
    //   5094: sipush #255
    //   5097: iand
    //   5098: bipush #8
    //   5100: ishl
    //   5101: ior
    //   5102: aload #47
    //   5104: bipush #11
    //   5106: baload
    //   5107: sipush #255
    //   5110: iand
    //   5111: ior
    //   5112: aload #32
    //   5114: iconst_2
    //   5115: iaload
    //   5116: ixor
    //   5117: istore #53
    //   5119: aload #47
    //   5121: bipush #12
    //   5123: baload
    //   5124: bipush #24
    //   5126: ishl
    //   5127: aload #47
    //   5129: bipush #13
    //   5131: baload
    //   5132: sipush #255
    //   5135: iand
    //   5136: bipush #16
    //   5138: ishl
    //   5139: ior
    //   5140: aload #47
    //   5142: bipush #14
    //   5144: baload
    //   5145: sipush #255
    //   5148: iand
    //   5149: bipush #8
    //   5151: ishl
    //   5152: ior
    //   5153: aload #47
    //   5155: bipush #15
    //   5157: baload
    //   5158: sipush #255
    //   5161: iand
    //   5162: ior
    //   5163: aload #32
    //   5165: iconst_3
    //   5166: iaload
    //   5167: ixor
    //   5168: istore #54
    //   5170: iconst_1
    //   5171: istore #55
    //   5173: iload #55
    //   5175: iload #38
    //   5177: if_icmpge -> 5420
    //   5180: iinc #49, 4
    //   5183: aload #40
    //   5185: iload #51
    //   5187: bipush #24
    //   5189: iushr
    //   5190: iaload
    //   5191: aload #41
    //   5193: iload #54
    //   5195: bipush #16
    //   5197: iushr
    //   5198: sipush #255
    //   5201: iand
    //   5202: iaload
    //   5203: ixor
    //   5204: aload #42
    //   5206: iload #53
    //   5208: bipush #8
    //   5210: iushr
    //   5211: sipush #255
    //   5214: iand
    //   5215: iaload
    //   5216: ixor
    //   5217: aload #43
    //   5219: iload #52
    //   5221: sipush #255
    //   5224: iand
    //   5225: iaload
    //   5226: ixor
    //   5227: aload #32
    //   5229: iload #49
    //   5231: iaload
    //   5232: ixor
    //   5233: istore #56
    //   5235: aload #40
    //   5237: iload #52
    //   5239: bipush #24
    //   5241: iushr
    //   5242: iaload
    //   5243: aload #41
    //   5245: iload #51
    //   5247: bipush #16
    //   5249: iushr
    //   5250: sipush #255
    //   5253: iand
    //   5254: iaload
    //   5255: ixor
    //   5256: aload #42
    //   5258: iload #54
    //   5260: bipush #8
    //   5262: iushr
    //   5263: sipush #255
    //   5266: iand
    //   5267: iaload
    //   5268: ixor
    //   5269: aload #43
    //   5271: iload #53
    //   5273: sipush #255
    //   5276: iand
    //   5277: iaload
    //   5278: ixor
    //   5279: aload #32
    //   5281: iload #49
    //   5283: iconst_1
    //   5284: iadd
    //   5285: iaload
    //   5286: ixor
    //   5287: istore #57
    //   5289: aload #40
    //   5291: iload #53
    //   5293: bipush #24
    //   5295: iushr
    //   5296: iaload
    //   5297: aload #41
    //   5299: iload #52
    //   5301: bipush #16
    //   5303: iushr
    //   5304: sipush #255
    //   5307: iand
    //   5308: iaload
    //   5309: ixor
    //   5310: aload #42
    //   5312: iload #51
    //   5314: bipush #8
    //   5316: iushr
    //   5317: sipush #255
    //   5320: iand
    //   5321: iaload
    //   5322: ixor
    //   5323: aload #43
    //   5325: iload #54
    //   5327: sipush #255
    //   5330: iand
    //   5331: iaload
    //   5332: ixor
    //   5333: aload #32
    //   5335: iload #49
    //   5337: iconst_2
    //   5338: iadd
    //   5339: iaload
    //   5340: ixor
    //   5341: istore #58
    //   5343: aload #40
    //   5345: iload #54
    //   5347: bipush #24
    //   5349: iushr
    //   5350: iaload
    //   5351: aload #41
    //   5353: iload #53
    //   5355: bipush #16
    //   5357: iushr
    //   5358: sipush #255
    //   5361: iand
    //   5362: iaload
    //   5363: ixor
    //   5364: aload #42
    //   5366: iload #52
    //   5368: bipush #8
    //   5370: iushr
    //   5371: sipush #255
    //   5374: iand
    //   5375: iaload
    //   5376: ixor
    //   5377: aload #43
    //   5379: iload #51
    //   5381: sipush #255
    //   5384: iand
    //   5385: iaload
    //   5386: ixor
    //   5387: aload #32
    //   5389: iload #49
    //   5391: iconst_3
    //   5392: iadd
    //   5393: iaload
    //   5394: ixor
    //   5395: istore #59
    //   5397: iload #56
    //   5399: istore #51
    //   5401: iload #57
    //   5403: istore #52
    //   5405: iload #58
    //   5407: istore #53
    //   5409: iload #59
    //   5411: istore #54
    //   5413: iinc #55, 1
    //   5416: iload_2
    //   5417: ifeq -> 5173
    //   5420: iinc #49, 4
    //   5423: aload #32
    //   5425: iload #49
    //   5427: iaload
    //   5428: istore #50
    //   5430: aload #48
    //   5432: iconst_0
    //   5433: aload #39
    //   5435: iload #51
    //   5437: bipush #24
    //   5439: iushr
    //   5440: baload
    //   5441: iload #50
    //   5443: bipush #24
    //   5445: iushr
    //   5446: ixor
    //   5447: i2b
    //   5448: bastore
    //   5449: aload #48
    //   5451: iconst_1
    //   5452: aload #39
    //   5454: iload #54
    //   5456: bipush #16
    //   5458: iushr
    //   5459: sipush #255
    //   5462: iand
    //   5463: baload
    //   5464: iload #50
    //   5466: bipush #16
    //   5468: iushr
    //   5469: ixor
    //   5470: i2b
    //   5471: bastore
    //   5472: aload #48
    //   5474: iconst_2
    //   5475: aload #39
    //   5477: iload #53
    //   5479: bipush #8
    //   5481: iushr
    //   5482: sipush #255
    //   5485: iand
    //   5486: baload
    //   5487: iload #50
    //   5489: bipush #8
    //   5491: iushr
    //   5492: ixor
    //   5493: i2b
    //   5494: bastore
    //   5495: aload #48
    //   5497: iconst_3
    //   5498: aload #39
    //   5500: iload #52
    //   5502: sipush #255
    //   5505: iand
    //   5506: baload
    //   5507: iload #50
    //   5509: ixor
    //   5510: i2b
    //   5511: bastore
    //   5512: aload #32
    //   5514: iload #49
    //   5516: iconst_1
    //   5517: iadd
    //   5518: iaload
    //   5519: istore #50
    //   5521: aload #48
    //   5523: iconst_4
    //   5524: aload #39
    //   5526: iload #52
    //   5528: bipush #24
    //   5530: iushr
    //   5531: baload
    //   5532: iload #50
    //   5534: bipush #24
    //   5536: iushr
    //   5537: ixor
    //   5538: i2b
    //   5539: bastore
    //   5540: aload #48
    //   5542: iconst_5
    //   5543: aload #39
    //   5545: iload #51
    //   5547: bipush #16
    //   5549: iushr
    //   5550: sipush #255
    //   5553: iand
    //   5554: baload
    //   5555: iload #50
    //   5557: bipush #16
    //   5559: iushr
    //   5560: ixor
    //   5561: i2b
    //   5562: bastore
    //   5563: aload #48
    //   5565: bipush #6
    //   5567: aload #39
    //   5569: iload #54
    //   5571: bipush #8
    //   5573: iushr
    //   5574: sipush #255
    //   5577: iand
    //   5578: baload
    //   5579: iload #50
    //   5581: bipush #8
    //   5583: iushr
    //   5584: ixor
    //   5585: i2b
    //   5586: bastore
    //   5587: aload #48
    //   5589: bipush #7
    //   5591: aload #39
    //   5593: iload #53
    //   5595: sipush #255
    //   5598: iand
    //   5599: baload
    //   5600: iload #50
    //   5602: ixor
    //   5603: i2b
    //   5604: bastore
    //   5605: aload #32
    //   5607: iload #49
    //   5609: iconst_2
    //   5610: iadd
    //   5611: iaload
    //   5612: istore #50
    //   5614: aload #48
    //   5616: bipush #8
    //   5618: aload #39
    //   5620: iload #53
    //   5622: bipush #24
    //   5624: iushr
    //   5625: baload
    //   5626: iload #50
    //   5628: bipush #24
    //   5630: iushr
    //   5631: ixor
    //   5632: i2b
    //   5633: bastore
    //   5634: aload #48
    //   5636: bipush #9
    //   5638: aload #39
    //   5640: iload #52
    //   5642: bipush #16
    //   5644: iushr
    //   5645: sipush #255
    //   5648: iand
    //   5649: baload
    //   5650: iload #50
    //   5652: bipush #16
    //   5654: iushr
    //   5655: ixor
    //   5656: i2b
    //   5657: bastore
    //   5658: aload #48
    //   5660: bipush #10
    //   5662: aload #39
    //   5664: iload #51
    //   5666: bipush #8
    //   5668: iushr
    //   5669: sipush #255
    //   5672: iand
    //   5673: baload
    //   5674: iload #50
    //   5676: bipush #8
    //   5678: iushr
    //   5679: ixor
    //   5680: i2b
    //   5681: bastore
    //   5682: aload #48
    //   5684: bipush #11
    //   5686: aload #39
    //   5688: iload #54
    //   5690: sipush #255
    //   5693: iand
    //   5694: baload
    //   5695: iload #50
    //   5697: ixor
    //   5698: i2b
    //   5699: bastore
    //   5700: aload #32
    //   5702: iload #49
    //   5704: iconst_3
    //   5705: iadd
    //   5706: iaload
    //   5707: istore #50
    //   5709: aload #48
    //   5711: bipush #12
    //   5713: aload #39
    //   5715: iload #54
    //   5717: bipush #24
    //   5719: iushr
    //   5720: baload
    //   5721: iload #50
    //   5723: bipush #24
    //   5725: iushr
    //   5726: ixor
    //   5727: i2b
    //   5728: bastore
    //   5729: aload #48
    //   5731: bipush #13
    //   5733: aload #39
    //   5735: iload #53
    //   5737: bipush #16
    //   5739: iushr
    //   5740: sipush #255
    //   5743: iand
    //   5744: baload
    //   5745: iload #50
    //   5747: bipush #16
    //   5749: iushr
    //   5750: ixor
    //   5751: i2b
    //   5752: bastore
    //   5753: aload #48
    //   5755: bipush #14
    //   5757: aload #39
    //   5759: iload #52
    //   5761: bipush #8
    //   5763: iushr
    //   5764: sipush #255
    //   5767: iand
    //   5768: baload
    //   5769: iload #50
    //   5771: bipush #8
    //   5773: iushr
    //   5774: ixor
    //   5775: i2b
    //   5776: bastore
    //   5777: aload #48
    //   5779: bipush #15
    //   5781: aload #39
    //   5783: iload #51
    //   5785: sipush #255
    //   5788: iand
    //   5789: baload
    //   5790: iload #50
    //   5792: ixor
    //   5793: i2b
    //   5794: bastore
    //   5795: iconst_0
    //   5796: istore #55
    //   5798: iload #55
    //   5800: bipush #16
    //   5802: if_icmpge -> 5828
    //   5805: aload #45
    //   5807: iload #55
    //   5809: iload #46
    //   5811: bipush #16
    //   5813: imul
    //   5814: iadd
    //   5815: aload #48
    //   5817: iload #55
    //   5819: baload
    //   5820: bastore
    //   5821: iinc #55, 1
    //   5824: iload_2
    //   5825: ifeq -> 5798
    //   5828: iinc #46, 1
    //   5831: iload_2
    //   5832: ifeq -> 4913
    //   5835: aload #45
    //   5837: arraylength
    //   5838: ifle -> 5919
    //   5841: aload #45
    //   5843: aload #45
    //   5845: arraylength
    //   5846: iconst_1
    //   5847: isub
    //   5848: baload
    //   5849: istore #46
    //   5851: iload #46
    //   5853: bipush #16
    //   5855: if_icmple -> 5866
    //   5858: aload #45
    //   5860: astore #37
    //   5862: iload_2
    //   5863: ifeq -> 5919
    //   5866: aload #45
    //   5868: arraylength
    //   5869: iload #46
    //   5871: isub
    //   5872: newarray byte
    //   5874: astore #37
    //   5876: iconst_0
    //   5877: istore #47
    //   5879: iload #47
    //   5881: aload #37
    //   5883: arraylength
    //   5884: if_icmpge -> 5919
    //   5887: iload #47
    //   5889: aload #45
    //   5891: arraylength
    //   5892: if_icmpge -> 5919
    //   5895: aload #37
    //   5897: iload #47
    //   5899: aload #45
    //   5901: iload #47
    //   5903: baload
    //   5904: bastore
    //   5905: iinc #47, 1
    //   5908: iload_2
    //   5909: ifeq -> 5879
    //   5912: goto -> 5919
    //   5915: invokestatic a : (Ljava/lang/Throwable;)Ljava/lang/Throwable;
    //   5918: athrow
    //   5919: aload #37
    //   5921: astore #9
    //   5923: getstatic burp/Zbsc.Zp : Ljava/lang/String;
    //   5926: getstatic burp/Zejg.ZR : Ljava/lang/Object;
    //   5929: checkcast java/math/BigInteger
    //   5932: invokevirtual intValue : ()I
    //   5935: bipush #32
    //   5937: irem
    //   5938: invokestatic abs : (I)I
    //   5941: invokevirtual charAt : (I)C
    //   5944: getstatic burp/Zzgh.Zn : Ljava/lang/String;
    //   5947: getstatic burp/Ztpa.Zv : Ljava/lang/Object;
    //   5950: checkcast java/math/BigInteger
    //   5953: invokevirtual intValue : ()I
    //   5956: bipush #32
    //   5958: irem
    //   5959: invokestatic abs : (I)I
    //   5962: invokevirtual charAt : (I)C
    //   5965: if_icmpgt -> 6080
    //   5968: getstatic burp/Zzxv.Z_ : Ljava/lang/String;
    //   5971: getstatic burp/Zx_x.Zi : Ljava/lang/Object;
    //   5974: checkcast java/math/BigInteger
    //   5977: invokevirtual intValue : ()I
    //   5980: bipush #32
    //   5982: irem
    //   5983: invokestatic abs : (I)I
    //   5986: invokevirtual charAt : (I)C
    //   5989: getstatic burp/Zd0.Zi : Ljava/lang/String;
    //   5992: getstatic burp/Zewo.ZZ : Ljava/lang/Object;
    //   5995: checkcast java/math/BigInteger
    //   5998: invokevirtual intValue : ()I
    //   6001: bipush #32
    //   6003: irem
    //   6004: invokestatic abs : (I)I
    //   6007: invokevirtual charAt : (I)C
    //   6010: if_icmpgt -> 6080
    //   6013: goto -> 6020
    //   6016: invokestatic a : (Ljava/lang/Throwable;)Ljava/lang/Throwable;
    //   6019: athrow
    //   6020: getstatic burp/Zxpb.ZQ : Ljava/lang/String;
    //   6023: getstatic burp/Zehi.Zb : Ljava/lang/Object;
    //   6026: checkcast java/math/BigInteger
    //   6029: invokevirtual intValue : ()I
    //   6032: bipush #32
    //   6034: irem
    //   6035: invokestatic abs : (I)I
    //   6038: invokevirtual charAt : (I)C
    //   6041: getstatic burp/Ztgt.ZQ : Ljava/lang/String;
    //   6044: getstatic burp/Zgfm.ZV : Ljava/lang/Object;
    //   6047: checkcast java/math/BigInteger
    //   6050: invokevirtual intValue : ()I
    //   6053: bipush #32
    //   6055: irem
    //   6056: invokestatic abs : (I)I
    //   6059: invokevirtual charAt : (I)C
    //   6062: if_icmpgt -> 6080
    //   6065: goto -> 6072
    //   6068: invokestatic a : (Ljava/lang/Throwable;)Ljava/lang/Throwable;
    //   6071: athrow
    //   6072: iconst_1
    //   6073: goto -> 6081
    //   6076: invokestatic a : (Ljava/lang/Throwable;)Ljava/lang/Throwable;
    //   6079: athrow
    //   6080: iconst_0
    //   6081: ireturn
    //   6082: astore_3
    //   6083: new java/lang/Exception
    //   6086: dup
    //   6087: aload_3
    //   6088: invokevirtual getMessage : ()Ljava/lang/String;
    //   6091: invokespecial <init> : (Ljava/lang/String;)V
    //   6094: athrow
    // Exception table:
    //   from	to	target	type
    //   4	6081	6082	java/lang/Throwable
    //   22	198	201	java/lang/Throwable
    //   168	235	238	java/lang/Throwable
    //   205	272	275	java/lang/Throwable
    //   242	309	312	java/lang/Throwable
    //   279	346	349	java/lang/Throwable
    //   316	383	386	java/lang/Throwable
    //   353	420	423	java/lang/Throwable
    //   390	457	460	java/lang/Throwable
    //   427	494	497	java/lang/Throwable
    //   464	531	534	java/lang/Throwable
    //   501	568	571	java/lang/Throwable
    //   538	605	608	java/lang/Throwable
    //   575	642	645	java/lang/Throwable
    //   612	679	682	java/lang/Throwable
    //   649	716	719	java/lang/Throwable
    //   686	753	756	java/lang/Throwable
    //   723	790	793	java/lang/Throwable
    //   760	827	830	java/lang/Throwable
    //   797	864	867	java/lang/Throwable
    //   834	901	904	java/lang/Throwable
    //   871	938	941	java/lang/Throwable
    //   908	975	978	java/lang/Throwable
    //   945	1012	1015	java/lang/Throwable
    //   982	1049	1052	java/lang/Throwable
    //   1019	1086	1089	java/lang/Throwable
    //   1056	1123	1126	java/lang/Throwable
    //   1093	1160	1163	java/lang/Throwable
    //   1130	1197	1200	java/lang/Throwable
    //   1167	1234	1237	java/lang/Throwable
    //   1204	1271	1274	java/lang/Throwable
    //   1241	1308	1311	java/lang/Throwable
    //   1278	1341	1344	java/lang/Throwable
    //   1381	1555	1558	java/lang/Throwable
    //   1524	1593	1596	java/lang/Throwable
    //   1562	1631	1634	java/lang/Throwable
    //   1600	1669	1672	java/lang/Throwable
    //   1638	1707	1710	java/lang/Throwable
    //   1676	1745	1748	java/lang/Throwable
    //   1714	1783	1786	java/lang/Throwable
    //   1752	1821	1824	java/lang/Throwable
    //   1790	1859	1862	java/lang/Throwable
    //   1828	1897	1900	java/lang/Throwable
    //   1866	1935	1938	java/lang/Throwable
    //   1904	1973	1976	java/lang/Throwable
    //   1942	2011	2014	java/lang/Throwable
    //   1980	2049	2052	java/lang/Throwable
    //   2018	2087	2090	java/lang/Throwable
    //   2056	2125	2128	java/lang/Throwable
    //   2094	2163	2166	java/lang/Throwable
    //   2132	2201	2204	java/lang/Throwable
    //   2170	2239	2242	java/lang/Throwable
    //   2208	2277	2280	java/lang/Throwable
    //   2246	2315	2318	java/lang/Throwable
    //   2284	2353	2356	java/lang/Throwable
    //   2322	2391	2394	java/lang/Throwable
    //   2360	2429	2432	java/lang/Throwable
    //   2398	2467	2470	java/lang/Throwable
    //   2436	2505	2508	java/lang/Throwable
    //   2474	2543	2546	java/lang/Throwable
    //   2512	2581	2584	java/lang/Throwable
    //   2550	2619	2622	java/lang/Throwable
    //   2588	2657	2660	java/lang/Throwable
    //   2626	2695	2698	java/lang/Throwable
    //   2664	2729	2732	java/lang/Throwable
    //   2814	2828	2828	java/lang/Throwable
    //   2839	2852	2855	java/lang/Throwable
    //   2844	2867	2870	java/lang/Throwable
    //   2859	2885	2888	java/lang/Throwable
    //   2874	2915	2918	java/lang/Throwable
    //   2981	3008	3011	java/lang/Throwable
    //   2998	3026	3029	java/lang/Throwable
    //   3015	3062	3065	java/lang/Throwable
    //   3033	3076	3079	java/lang/Throwable
    //   3128	3142	3142	java/lang/Throwable
    //   3153	3166	3169	java/lang/Throwable
    //   3158	3181	3184	java/lang/Throwable
    //   3173	3199	3202	java/lang/Throwable
    //   3188	3229	3232	java/lang/Throwable
    //   3295	3322	3325	java/lang/Throwable
    //   3312	3343	3346	java/lang/Throwable
    //   3329	3373	3376	java/lang/Throwable
    //   3350	3384	3384	java/lang/Throwable
    //   3395	3411	3414	java/lang/Throwable
    //   3566	3581	3581	java/lang/Throwable
    //   4583	4609	4609	java/lang/Throwable
    //   4690	4705	4705	java/lang/Throwable
    //   5887	5912	5915	java/lang/Throwable
    //   5923	6013	6016	java/lang/Throwable
    //   5968	6065	6068	java/lang/Throwable
    //   6020	6076	6076	java/lang/Throwable
  }
  
  static {
    // Byte code:
    //   0: bipush #14
    //   2: anewarray java/lang/String
    //   5: astore #5
    //   7: iconst_0
    //   8: istore_3
    //   9: ldc '+V,\\t@+;S]!:\\tj#wm {)BrqZN W/Zu\\tf1c'}6Y"??MrkFe`W`%T>L7KW0yJ\\b#VBb X5!*lO8%!(9a=U gMF\\tEIe~\\tg\\n\\tZ}"R@??'
    //   11: dup
    //   12: astore_2
    //   13: invokevirtual length : ()I
    //   16: istore #4
    //   18: iconst_4
    //   19: istore_1
    //   20: iconst_m1
    //   21: istore_0
    //   22: bipush #32
    //   24: iinc #0, 1
    //   27: aload_2
    //   28: iload_0
    //   29: dup
    //   30: iload_1
    //   31: iadd
    //   32: invokevirtual substring : (II)Ljava/lang/String;
    //   35: iconst_m1
    //   36: goto -> 142
    //   39: aload #5
    //   41: swap
    //   42: iload_3
    //   43: iinc #3, 1
    //   46: swap
    //   47: aastore
    //   48: iload_0
    //   49: iload_1
    //   50: iadd
    //   51: dup
    //   52: istore_0
    //   53: iload #4
    //   55: if_icmpge -> 67
    //   58: aload_2
    //   59: iload_0
    //   60: invokevirtual charAt : (I)C
    //   63: istore_1
    //   64: goto -> 22
    //   67: ldc '\\rSKvB&:,^$oEm8[+M#PA'
    //   69: dup
    //   70: astore_2
    //   71: invokevirtual length : ()I
    //   74: istore #4
    //   76: bipush #32
    //   78: istore_1
    //   79: iconst_m1
    //   80: istore_0
    //   81: bipush #59
    //   83: iinc #0, 1
    //   86: aload_2
    //   87: iload_0
    //   88: dup
    //   89: iload_1
    //   90: iadd
    //   91: invokevirtual substring : (II)Ljava/lang/String;
    //   94: iconst_0
    //   95: goto -> 142
    //   98: aload #5
    //   100: swap
    //   101: iload_3
    //   102: iinc #3, 1
    //   105: swap
    //   106: aastore
    //   107: iload_0
    //   108: iload_1
    //   109: iadd
    //   110: dup
    //   111: istore_0
    //   112: iload #4
    //   114: if_icmpge -> 126
    //   117: aload_2
    //   118: iload_0
    //   119: invokevirtual charAt : (I)C
    //   122: istore_1
    //   123: goto -> 81
    //   126: aload #5
    //   128: putstatic burp/Zsow.a : [Ljava/lang/String;
    //   131: bipush #14
    //   133: anewarray java/lang/String
    //   136: putstatic burp/Zsow.b : [Ljava/lang/String;
    //   139: goto -> 300
    //   142: dup_x2
    //   143: pop
    //   144: invokevirtual toCharArray : ()[C
    //   147: dup_x1
    //   148: arraylength
    //   149: dup_x2
    //   150: pop
    //   151: iconst_0
    //   152: istore #6
    //   154: dup2_x1
    //   155: pop2
    //   156: dup_x2
    //   157: iconst_1
    //   158: if_icmpgt -> 260
    //   161: dup2
    //   162: swap
    //   163: iload #6
    //   165: dup2_x1
    //   166: caload
    //   167: swap
    //   168: iload #6
    //   170: bipush #7
    //   172: irem
    //   173: tableswitch default -> 242, 0 -> 212, 1 -> 217, 2 -> 222, 3 -> 227, 4 -> 232, 5 -> 237
    //   212: bipush #75
    //   214: goto -> 244
    //   217: bipush #53
    //   219: goto -> 244
    //   222: bipush #34
    //   224: goto -> 244
    //   227: bipush #31
    //   229: goto -> 244
    //   232: bipush #72
    //   234: goto -> 244
    //   237: bipush #30
    //   239: goto -> 244
    //   242: bipush #46
    //   244: ixor
    //   245: ixor
    //   246: i2c
    //   247: castore
    //   248: iinc #6, 1
    //   251: dup
    //   252: ifne -> 260
    //   255: dup2
    //   256: dup_x1
    //   257: goto -> 165
    //   260: dup2_x1
    //   261: pop2
    //   262: dup_x2
    //   263: iload #6
    //   265: if_icmpgt -> 161
    //   268: pop
    //   269: new java/lang/String
    //   272: dup_x1
    //   273: swap
    //   274: invokespecial <init> : ([C)V
    //   277: invokevirtual intern : ()Ljava/lang/String;
    //   280: swap
    //   281: pop
    //   282: swap
    //   283: tableswitch default -> 39, 0 -> 98
    //   300: sipush #-27483
    //   303: sipush #-8043
    //   306: invokestatic a : (II)Ljava/lang/String;
    //   309: putstatic burp/Zsow.Zh : Ljava/lang/String;
    //   312: new java/math/BigInteger
    //   315: dup
    //   316: iconst_1
    //   317: bipush #32
    //   319: newarray byte
    //   321: dup
    //   322: iconst_0
    //   323: bipush #31
    //   325: bastore
    //   326: dup
    //   327: iconst_1
    //   328: bipush #-41
    //   330: bastore
    //   331: dup
    //   332: iconst_2
    //   333: bipush #84
    //   335: bastore
    //   336: dup
    //   337: iconst_3
    //   338: bipush #-59
    //   340: bastore
    //   341: dup
    //   342: iconst_4
    //   343: bipush #6
    //   345: bastore
    //   346: dup
    //   347: iconst_5
    //   348: bipush #-112
    //   350: bastore
    //   351: dup
    //   352: bipush #6
    //   354: bipush #-125
    //   356: bastore
    //   357: dup
    //   358: bipush #7
    //   360: bipush #-25
    //   362: bastore
    //   363: dup
    //   364: bipush #8
    //   366: bipush #-55
    //   368: bastore
    //   369: dup
    //   370: bipush #9
    //   372: bipush #-84
    //   374: bastore
    //   375: dup
    //   376: bipush #10
    //   378: bipush #95
    //   380: bastore
    //   381: dup
    //   382: bipush #11
    //   384: bipush #-95
    //   386: bastore
    //   387: dup
    //   388: bipush #12
    //   390: bipush #46
    //   392: bastore
    //   393: dup
    //   394: bipush #13
    //   396: bipush #-23
    //   398: bastore
    //   399: dup
    //   400: bipush #14
    //   402: bipush #-60
    //   404: bastore
    //   405: dup
    //   406: bipush #15
    //   408: bipush #7
    //   410: bastore
    //   411: dup
    //   412: bipush #16
    //   414: bipush #88
    //   416: bastore
    //   417: dup
    //   418: bipush #17
    //   420: bipush #-121
    //   422: bastore
    //   423: dup
    //   424: bipush #18
    //   426: bipush #-42
    //   428: bastore
    //   429: dup
    //   430: bipush #19
    //   432: bipush #-3
    //   434: bastore
    //   435: dup
    //   436: bipush #20
    //   438: bipush #106
    //   440: bastore
    //   441: dup
    //   442: bipush #21
    //   444: bipush #-85
    //   446: bastore
    //   447: dup
    //   448: bipush #22
    //   450: bipush #-18
    //   452: bastore
    //   453: dup
    //   454: bipush #23
    //   456: iconst_0
    //   457: bastore
    //   458: dup
    //   459: bipush #24
    //   461: bipush #-116
    //   463: bastore
    //   464: dup
    //   465: bipush #25
    //   467: bipush #26
    //   469: bastore
    //   470: dup
    //   471: bipush #26
    //   473: bipush #-82
    //   475: bastore
    //   476: dup
    //   477: bipush #27
    //   479: bipush #97
    //   481: bastore
    //   482: dup
    //   483: bipush #28
    //   485: bipush #24
    //   487: bastore
    //   488: dup
    //   489: bipush #29
    //   491: bipush #53
    //   493: bastore
    //   494: dup
    //   495: bipush #30
    //   497: bipush #104
    //   499: bastore
    //   500: dup
    //   501: bipush #31
    //   503: bipush #6
    //   505: bastore
    //   506: invokespecial <init> : (I[B)V
    //   509: putstatic burp/Zsow.ZV : Ljava/lang/Object;
    //   512: return
  }
  
  private static Throwable a(Throwable paramThrowable) {
    return paramThrowable;
  }
  
  private static String a(int paramInt1, int paramInt2) {
    int i = (paramInt1 ^ 0xFFFF94A9) & 0xFFFF;
    if (b[i] == null) {
      char[] arrayOfChar = a[i].toCharArray();
      switch (arrayOfChar[0] & 0xFF) {
        case 0:
        
        case 1:
        
        case 2:
        
        case 3:
        
        case 4:
        
        case 5:
        
        case 6:
        
        case 7:
        
        case 8:
        
        case 9:
        
        case 10:
        
        case 11:
        
        case 12:
        
        case 13:
        
        case 14:
        
        case 15:
        
        case 16:
        
        case 17:
        
        case 18:
        
        case 19:
        
        case 20:
        
        case 21:
        
        case 22:
        
        case 23:
        
        case 24:
        
        case 25:
        
        case 26:
        
        case 27:
        
        case 28:
        
        case 29:
        
        case 30:
        
        case 31:
        
        case 32:
        
        case 33:
        
        case 34:
        
        case 35:
        
        case 36:
        
        case 37:
        
        case 38:
        
        case 39:
        
        case 40:
        
        case 41:
        
        case 42:
        
        case 43:
        
        case 44:
        
        case 45:
        
        case 46:
        
        case 47:
        
        case 48:
        
        case 49:
        
        case 50:
        
        case 51:
        
        case 52:
        
        case 53:
        
        case 54:
        
        case 55:
        
        case 56:
        
        case 57:
        
        case 58:
        
        case 59:
        
        case 60:
        
        case 61:
        
        case 62:
        
        case 63:
        
        case 64:
        
        case 65:
        
        case 66:
        
        case 67:
        
        case 68:
        
        case 69:
        
        case 70:
        
        case 71:
        
        case 72:
        
        case 73:
        
        case 74:
        
        case 75:
        
        case 76:
        
        case 77:
        
        case 78:
        
        case 79:
        
        case 80:
        
        case 81:
        
        case 82:
        
        case 83:
        
        case 84:
        
        case 85:
        
        case 86:
        
        case 87:
        
        case 88:
        
        case 89:
        
        case 90:
        
        case 91:
        
        case 92:
        
        case 93:
        
        case 94:
        
        case 95:
        
        case 96:
        
        case 97:
        
        case 98:
        
        case 99:
        
        case 100:
        
        case 101:
        
        case 102:
        
        case 103:
        
        case 104:
        
        case 105:
        
        case 106:
        
        case 107:
        
        case 108:
        
        case 109:
        
        case 110:
        
        case 111:
        
        case 112:
        
        case 113:
        
        case 114:
        
        case 115:
        
        case 116:
        
        case 117:
        
        case 118:
        
        case 119:
        
        case 120:
        
        case 121:
        
        case 122:
        
        case 123:
        
        case 124:
        
        case 125:
        
        case 126:
        
        case 127:
        
        case 128:
        
        case 129:
        
        case 130:
        
        case 131:
        
        case 132:
        
        case 133:
        
        case 134:
        
        case 135:
        
        case 136:
        
        case 137:
        
        case 138:
        
        case 139:
        
        case 140:
        
        case 141:
        
        case 142:
        
        case 143:
        
        case 144:
        
        case 145:
        
        case 146:
        
        case 147:
        
        case 148:
        
        case 149:
        
        case 150:
        
        case 151:
        
        case 152:
        
        case 153:
        
        case 154:
        
        case 155:
        
        case 156:
        
        case 157:
        
        case 158:
        
        case 159:
        
        case 160:
        
        case 161:
        
        case 162:
        
        case 163:
        
        case 164:
        
        case 165:
        
        case 166:
        
        case 167:
        
        case 168:
        
        case 169:
        
        case 170:
        
        case 171:
        
        case 172:
        
        case 173:
        
        case 174:
        
        case 175:
        
        case 176:
        
        case 177:
        
        case 178:
        
        case 179:
        
        case 180:
        
        case 181:
        
        case 182:
        
        case 183:
        
        case 184:
        
        case 185:
        
        case 186:
        
        case 187:
        
        case 188:
        
        case 189:
        
        case 190:
        
        case 191:
        
        case 192:
        
        case 193:
        
        case 194:
        
        case 195:
        
        case 196:
        
        case 197:
        
        case 198:
        
        case 199:
        
        case 200:
        
        case 201:
        
        case 202:
        
        case 203:
        
        case 204:
        
        case 205:
        
        case 206:
        
        case 207:
        
        case 208:
        
        case 209:
        
        case 210:
        
        case 211:
        
        case 212:
        
        case 213:
        
        case 214:
        
        case 215:
        
        case 216:
        
        case 217:
        
        case 218:
        
        case 219:
        
        case 220:
        
        case 221:
        
        case 222:
        
        case 223:
        
        case 224:
        
        case 225:
        
        case 226:
        
        case 227:
        
        case 228:
        
        case 229:
        
        case 230:
        
        case 231:
        
        case 232:
        
        case 233:
        
        case 234:
        
        case 235:
        
        case 236:
        
        case 237:
        
        case 238:
        
        case 239:
        
        case 240:
        
        case 241:
        
        case 242:
        
        case 243:
        
        case 244:
        
        case 245:
        
        case 246:
        
        case 247:
        
        case 248:
        
        case 249:
        
        case 250:
        
        case 251:
        
        case 252:
        
        case 253:
        
        case 254:
        
        default:
          break;
      } 
      char c = '';
      int j = (paramInt2 & 0xFF) - c;
      if (j < 0)
        j += 256; 
      int k = ((paramInt2 & 0xFFFF) >>> 8) - c;
      if (k < 0)
        k += 256; 
      for (byte b = 0; b < arrayOfChar.length; b++) {
        int m = b % 2;
        if (m == 0) {
          arrayOfChar[b] = (char)(arrayOfChar[b] ^ j);
          j = ((j >>> 3 | j << 5) ^ arrayOfChar[b]) & 0xFF;
        } else {
          arrayOfChar[b] = (char)(arrayOfChar[b] ^ k);
          k = ((k >>> 3 | k << 5) ^ arrayOfChar[b]) & 0xFF;
        } 
      } 
      b[i] = (new String(arrayOfChar)).intern();
    } 
    return b[i];
  }
}


/* Location:              C:\Program Files\BurpSuitePro\burpsuite_pro.jar!\burp\Zsow.class
 * Java compiler version: 21 (65.0)
 * JD-Core Version:       1.1.3
 */