package burp;

import java.math.BigInteger;

class Zsq5 extends ClassLoader {
  static String ZA;
  
  static Object ZF;
  
  private static final String[] a;
  
  private static final String[] b;
  
  static void Zq(Object paramObject) {
    Ztod.Zj = a(-24922, 11858);
    Ztod.ZP = new BigInteger(a(-24904, 25639));
    boolean bool = Zt2e.ZK();
    try {
      try {
        if (Ztap.Zk.charAt(Math.abs(((BigInteger)Zek5.ZP).intValue() % 32)) > Zgj5.ZH.charAt(Math.abs(((BigInteger)Zz5s.Zg).intValue() % 32))) {
          try {
            Zty4.ZD(Class.forName(a(-24900, 17467)));
            if (bool)
              Zs9k.Za(Class.forName(a(-24905, -4919))); 
          } catch (Throwable throwable) {
            throw a(null);
          } 
          return;
        } 
      } catch (Throwable throwable) {
        throw a(null);
      } 
      Zs9k.Za(Class.forName(a(-24905, -4919)));
    } catch (Throwable throwable) {}
  }
  
  static void ZK(Object[] paramArrayOfObject, Object paramObject) throws Throwable {}
  
  static boolean ZI(Object[] paramArrayOfObject, Object paramObject) throws Throwable {
    // Byte code:
    //   0: invokestatic ZN : ()Z
    //   3: istore_2
    //   4: sipush #-24899
    //   7: sipush #617
    //   10: invokestatic a : (II)Ljava/lang/String;
    //   13: invokestatic forName : (Ljava/lang/String;)Ljava/lang/Class;
    //   16: invokestatic ZC : (Ljava/lang/Object;)V
    //   19: ldc2_w 8682522807148012
    //   22: invokestatic currentTimeMillis : ()J
    //   25: lxor
    //   26: lstore #4
    //   28: lload #4
    //   30: ldc2_w 25214903917
    //   33: lmul
    //   34: ldc2_w 11
    //   37: ladd
    //   38: ldc2_w 281474976710655
    //   41: land
    //   42: lstore #4
    //   44: lload #4
    //   46: bipush #32
    //   48: lshl
    //   49: lstore #6
    //   51: lload #4
    //   53: ldc2_w 25214903917
    //   56: lmul
    //   57: ldc2_w 11
    //   60: ladd
    //   61: ldc2_w 281474976710655
    //   64: land
    //   65: lstore #4
    //   67: lload #6
    //   69: lload #4
    //   71: ladd
    //   72: lstore #6
    //   74: bipush #16
    //   76: newarray byte
    //   78: dup
    //   79: iconst_0
    //   80: bipush #48
    //   82: bastore
    //   83: dup
    //   84: iconst_1
    //   85: bipush #49
    //   87: bastore
    //   88: dup
    //   89: iconst_2
    //   90: bipush #50
    //   92: bastore
    //   93: dup
    //   94: iconst_3
    //   95: bipush #51
    //   97: bastore
    //   98: dup
    //   99: iconst_4
    //   100: bipush #52
    //   102: bastore
    //   103: dup
    //   104: iconst_5
    //   105: bipush #53
    //   107: bastore
    //   108: dup
    //   109: bipush #6
    //   111: bipush #54
    //   113: bastore
    //   114: dup
    //   115: bipush #7
    //   117: bipush #55
    //   119: bastore
    //   120: dup
    //   121: bipush #8
    //   123: bipush #56
    //   125: bastore
    //   126: dup
    //   127: bipush #9
    //   129: bipush #57
    //   131: bastore
    //   132: dup
    //   133: bipush #10
    //   135: bipush #97
    //   137: bastore
    //   138: dup
    //   139: bipush #11
    //   141: bipush #98
    //   143: bastore
    //   144: dup
    //   145: bipush #12
    //   147: bipush #99
    //   149: bastore
    //   150: dup
    //   151: bipush #13
    //   153: bipush #100
    //   155: bastore
    //   156: dup
    //   157: bipush #14
    //   159: bipush #101
    //   161: bastore
    //   162: dup
    //   163: bipush #15
    //   165: bipush #102
    //   167: bastore
    //   168: astore #8
    //   170: bipush #64
    //   172: newarray byte
    //   174: astore #9
    //   176: bipush #64
    //   178: istore #10
    //   180: bipush #16
    //   182: istore #11
    //   184: iload #11
    //   186: iconst_1
    //   187: isub
    //   188: i2l
    //   189: lstore #12
    //   191: aload #9
    //   193: iinc #10, -1
    //   196: iload #10
    //   198: aload #8
    //   200: lload #6
    //   202: lload #12
    //   204: land
    //   205: l2i
    //   206: baload
    //   207: bastore
    //   208: lload #6
    //   210: iconst_4
    //   211: lushr
    //   212: lstore #6
    //   214: lload #6
    //   216: lconst_0
    //   217: lcmp
    //   218: ifne -> 191
    //   221: bipush #64
    //   223: iload #10
    //   225: isub
    //   226: newarray byte
    //   228: astore_3
    //   229: iconst_0
    //   230: istore #14
    //   232: iload #14
    //   234: aload_3
    //   235: arraylength
    //   236: if_icmpge -> 258
    //   239: aload_3
    //   240: iload #14
    //   242: aload #9
    //   244: iload #10
    //   246: iload #14
    //   248: iadd
    //   249: baload
    //   250: bastore
    //   251: iinc #14, 1
    //   254: iload_2
    //   255: ifne -> 232
    //   258: aload_3
    //   259: arraylength
    //   260: bipush #10
    //   262: if_icmplt -> 28
    //   265: new java/lang/StringBuilder
    //   268: dup
    //   269: invokespecial <init> : ()V
    //   272: astore_3
    //   273: iconst_0
    //   274: istore #4
    //   276: iload #4
    //   278: bipush #32
    //   280: if_icmpge -> 1615
    //   283: iload #4
    //   285: tableswitch default -> 1608, 0 -> 428, 1 -> 465, 2 -> 502, 3 -> 539, 4 -> 576, 5 -> 613, 6 -> 650, 7 -> 687, 8 -> 724, 9 -> 761, 10 -> 798, 11 -> 835, 12 -> 872, 13 -> 909, 14 -> 946, 15 -> 983, 16 -> 1020, 17 -> 1057, 18 -> 1094, 19 -> 1131, 20 -> 1168, 21 -> 1205, 22 -> 1242, 23 -> 1279, 24 -> 1316, 25 -> 1353, 26 -> 1390, 27 -> 1427, 28 -> 1464, 29 -> 1501, 30 -> 1538, 31 -> 1575
    //   428: aload_3
    //   429: getstatic burp/Zz5s.ZL : Ljava/lang/String;
    //   432: getstatic burp/Zl3l.Zv : Ljava/lang/Object;
    //   435: checkcast java/math/BigInteger
    //   438: invokevirtual intValue : ()I
    //   441: bipush #32
    //   443: irem
    //   444: invokestatic abs : (I)I
    //   447: invokevirtual charAt : (I)C
    //   450: invokevirtual append : (C)Ljava/lang/StringBuilder;
    //   453: pop
    //   454: iload_2
    //   455: ifne -> 1608
    //   458: goto -> 465
    //   461: invokestatic a : (Ljava/lang/Throwable;)Ljava/lang/Throwable;
    //   464: athrow
    //   465: aload_3
    //   466: getstatic burp/Zle4.ZX : Ljava/lang/String;
    //   469: getstatic burp/Zlg1.ZH : Ljava/lang/Object;
    //   472: checkcast java/math/BigInteger
    //   475: invokevirtual intValue : ()I
    //   478: bipush #32
    //   480: irem
    //   481: invokestatic abs : (I)I
    //   484: invokevirtual charAt : (I)C
    //   487: invokevirtual append : (C)Ljava/lang/StringBuilder;
    //   490: pop
    //   491: iload_2
    //   492: ifne -> 1608
    //   495: goto -> 502
    //   498: invokestatic a : (Ljava/lang/Throwable;)Ljava/lang/Throwable;
    //   501: athrow
    //   502: aload_3
    //   503: getstatic burp/Zzky.Zj : Ljava/lang/String;
    //   506: getstatic burp/Zrkc.ZI : Ljava/lang/Object;
    //   509: checkcast java/math/BigInteger
    //   512: invokevirtual intValue : ()I
    //   515: bipush #32
    //   517: irem
    //   518: invokestatic abs : (I)I
    //   521: invokevirtual charAt : (I)C
    //   524: invokevirtual append : (C)Ljava/lang/StringBuilder;
    //   527: pop
    //   528: iload_2
    //   529: ifne -> 1608
    //   532: goto -> 539
    //   535: invokestatic a : (Ljava/lang/Throwable;)Ljava/lang/Throwable;
    //   538: athrow
    //   539: aload_3
    //   540: getstatic burp/Zle4.ZX : Ljava/lang/String;
    //   543: getstatic burp/Zb29.ZM : Ljava/lang/Object;
    //   546: checkcast java/math/BigInteger
    //   549: invokevirtual intValue : ()I
    //   552: bipush #32
    //   554: irem
    //   555: invokestatic abs : (I)I
    //   558: invokevirtual charAt : (I)C
    //   561: invokevirtual append : (C)Ljava/lang/StringBuilder;
    //   564: pop
    //   565: iload_2
    //   566: ifne -> 1608
    //   569: goto -> 576
    //   572: invokestatic a : (Ljava/lang/Throwable;)Ljava/lang/Throwable;
    //   575: athrow
    //   576: aload_3
    //   577: getstatic burp/Zlhz.Zo : Ljava/lang/String;
    //   580: getstatic burp/Zbnb.ZZ : Ljava/lang/Object;
    //   583: checkcast java/math/BigInteger
    //   586: invokevirtual intValue : ()I
    //   589: bipush #32
    //   591: irem
    //   592: invokestatic abs : (I)I
    //   595: invokevirtual charAt : (I)C
    //   598: invokevirtual append : (C)Ljava/lang/StringBuilder;
    //   601: pop
    //   602: iload_2
    //   603: ifne -> 1608
    //   606: goto -> 613
    //   609: invokestatic a : (Ljava/lang/Throwable;)Ljava/lang/Throwable;
    //   612: athrow
    //   613: aload_3
    //   614: getstatic burp/Zz3k.Zn : Ljava/lang/String;
    //   617: getstatic burp/Zkdc.Zv : Ljava/lang/Object;
    //   620: checkcast java/math/BigInteger
    //   623: invokevirtual intValue : ()I
    //   626: bipush #32
    //   628: irem
    //   629: invokestatic abs : (I)I
    //   632: invokevirtual charAt : (I)C
    //   635: invokevirtual append : (C)Ljava/lang/StringBuilder;
    //   638: pop
    //   639: iload_2
    //   640: ifne -> 1608
    //   643: goto -> 650
    //   646: invokestatic a : (Ljava/lang/Throwable;)Ljava/lang/Throwable;
    //   649: athrow
    //   650: aload_3
    //   651: getstatic burp/Zrpx.ZM : Ljava/lang/String;
    //   654: getstatic burp/Zeno.Zo : Ljava/lang/Object;
    //   657: checkcast java/math/BigInteger
    //   660: invokevirtual intValue : ()I
    //   663: bipush #32
    //   665: irem
    //   666: invokestatic abs : (I)I
    //   669: invokevirtual charAt : (I)C
    //   672: invokevirtual append : (C)Ljava/lang/StringBuilder;
    //   675: pop
    //   676: iload_2
    //   677: ifne -> 1608
    //   680: goto -> 687
    //   683: invokestatic a : (Ljava/lang/Throwable;)Ljava/lang/Throwable;
    //   686: athrow
    //   687: aload_3
    //   688: getstatic burp/Zrd0.Zk : Ljava/lang/String;
    //   691: getstatic burp/Zle4.Zh : Ljava/lang/Object;
    //   694: checkcast java/math/BigInteger
    //   697: invokevirtual intValue : ()I
    //   700: bipush #32
    //   702: irem
    //   703: invokestatic abs : (I)I
    //   706: invokevirtual charAt : (I)C
    //   709: invokevirtual append : (C)Ljava/lang/StringBuilder;
    //   712: pop
    //   713: iload_2
    //   714: ifne -> 1608
    //   717: goto -> 724
    //   720: invokestatic a : (Ljava/lang/Throwable;)Ljava/lang/Throwable;
    //   723: athrow
    //   724: aload_3
    //   725: getstatic burp/Zrd0.Zk : Ljava/lang/String;
    //   728: getstatic burp/Zzlg.Z_ : Ljava/lang/Object;
    //   731: checkcast java/math/BigInteger
    //   734: invokevirtual intValue : ()I
    //   737: bipush #32
    //   739: irem
    //   740: invokestatic abs : (I)I
    //   743: invokevirtual charAt : (I)C
    //   746: invokevirtual append : (C)Ljava/lang/StringBuilder;
    //   749: pop
    //   750: iload_2
    //   751: ifne -> 1608
    //   754: goto -> 761
    //   757: invokestatic a : (Ljava/lang/Throwable;)Ljava/lang/Throwable;
    //   760: athrow
    //   761: aload_3
    //   762: getstatic burp/Zb6b.Zn : Ljava/lang/String;
    //   765: getstatic burp/Ztap.ZK : Ljava/lang/Object;
    //   768: checkcast java/math/BigInteger
    //   771: invokevirtual intValue : ()I
    //   774: bipush #32
    //   776: irem
    //   777: invokestatic abs : (I)I
    //   780: invokevirtual charAt : (I)C
    //   783: invokevirtual append : (C)Ljava/lang/StringBuilder;
    //   786: pop
    //   787: iload_2
    //   788: ifne -> 1608
    //   791: goto -> 798
    //   794: invokestatic a : (Ljava/lang/Throwable;)Ljava/lang/Throwable;
    //   797: athrow
    //   798: aload_3
    //   799: getstatic burp/Ztap.Zk : Ljava/lang/String;
    //   802: getstatic burp/Zetv.ZI : Ljava/lang/Object;
    //   805: checkcast java/math/BigInteger
    //   808: invokevirtual intValue : ()I
    //   811: bipush #32
    //   813: irem
    //   814: invokestatic abs : (I)I
    //   817: invokevirtual charAt : (I)C
    //   820: invokevirtual append : (C)Ljava/lang/StringBuilder;
    //   823: pop
    //   824: iload_2
    //   825: ifne -> 1608
    //   828: goto -> 835
    //   831: invokestatic a : (Ljava/lang/Throwable;)Ljava/lang/Throwable;
    //   834: athrow
    //   835: aload_3
    //   836: getstatic burp/Zb6b.Zn : Ljava/lang/String;
    //   839: getstatic burp/Ztt0.ZF : Ljava/lang/Object;
    //   842: checkcast java/math/BigInteger
    //   845: invokevirtual intValue : ()I
    //   848: bipush #32
    //   850: irem
    //   851: invokestatic abs : (I)I
    //   854: invokevirtual charAt : (I)C
    //   857: invokevirtual append : (C)Ljava/lang/StringBuilder;
    //   860: pop
    //   861: iload_2
    //   862: ifne -> 1608
    //   865: goto -> 872
    //   868: invokestatic a : (Ljava/lang/Throwable;)Ljava/lang/Throwable;
    //   871: athrow
    //   872: aload_3
    //   873: getstatic burp/Zrj3.ZT : Ljava/lang/String;
    //   876: getstatic burp/Ztev.Zr : Ljava/lang/Object;
    //   879: checkcast java/math/BigInteger
    //   882: invokevirtual intValue : ()I
    //   885: bipush #32
    //   887: irem
    //   888: invokestatic abs : (I)I
    //   891: invokevirtual charAt : (I)C
    //   894: invokevirtual append : (C)Ljava/lang/StringBuilder;
    //   897: pop
    //   898: iload_2
    //   899: ifne -> 1608
    //   902: goto -> 909
    //   905: invokestatic a : (Ljava/lang/Throwable;)Ljava/lang/Throwable;
    //   908: athrow
    //   909: aload_3
    //   910: getstatic burp/Zbnb.Zd : Ljava/lang/String;
    //   913: getstatic burp/Zb_c.ZN : Ljava/lang/Object;
    //   916: checkcast java/math/BigInteger
    //   919: invokevirtual intValue : ()I
    //   922: bipush #32
    //   924: irem
    //   925: invokestatic abs : (I)I
    //   928: invokevirtual charAt : (I)C
    //   931: invokevirtual append : (C)Ljava/lang/StringBuilder;
    //   934: pop
    //   935: iload_2
    //   936: ifne -> 1608
    //   939: goto -> 946
    //   942: invokestatic a : (Ljava/lang/Throwable;)Ljava/lang/Throwable;
    //   945: athrow
    //   946: aload_3
    //   947: getstatic burp/Zmcq.ZY : Ljava/lang/String;
    //   950: getstatic burp/Zbnb.ZZ : Ljava/lang/Object;
    //   953: checkcast java/math/BigInteger
    //   956: invokevirtual intValue : ()I
    //   959: bipush #32
    //   961: irem
    //   962: invokestatic abs : (I)I
    //   965: invokevirtual charAt : (I)C
    //   968: invokevirtual append : (C)Ljava/lang/StringBuilder;
    //   971: pop
    //   972: iload_2
    //   973: ifne -> 1608
    //   976: goto -> 983
    //   979: invokestatic a : (Ljava/lang/Throwable;)Ljava/lang/Throwable;
    //   982: athrow
    //   983: aload_3
    //   984: getstatic burp/Zz3k.Zn : Ljava/lang/String;
    //   987: getstatic burp/Zgkp.Zp : Ljava/lang/Object;
    //   990: checkcast java/math/BigInteger
    //   993: invokevirtual intValue : ()I
    //   996: bipush #32
    //   998: irem
    //   999: invokestatic abs : (I)I
    //   1002: invokevirtual charAt : (I)C
    //   1005: invokevirtual append : (C)Ljava/lang/StringBuilder;
    //   1008: pop
    //   1009: iload_2
    //   1010: ifne -> 1608
    //   1013: goto -> 1020
    //   1016: invokestatic a : (Ljava/lang/Throwable;)Ljava/lang/Throwable;
    //   1019: athrow
    //   1020: aload_3
    //   1021: getstatic burp/Zgwh.Zq : Ljava/lang/String;
    //   1024: getstatic burp/Zry7.ZZ : Ljava/lang/Object;
    //   1027: checkcast java/math/BigInteger
    //   1030: invokevirtual intValue : ()I
    //   1033: bipush #32
    //   1035: irem
    //   1036: invokestatic abs : (I)I
    //   1039: invokevirtual charAt : (I)C
    //   1042: invokevirtual append : (C)Ljava/lang/StringBuilder;
    //   1045: pop
    //   1046: iload_2
    //   1047: ifne -> 1608
    //   1050: goto -> 1057
    //   1053: invokestatic a : (Ljava/lang/Throwable;)Ljava/lang/Throwable;
    //   1056: athrow
    //   1057: aload_3
    //   1058: getstatic burp/Zth7.Zf : Ljava/lang/String;
    //   1061: getstatic burp/Zb29.ZM : Ljava/lang/Object;
    //   1064: checkcast java/math/BigInteger
    //   1067: invokevirtual intValue : ()I
    //   1070: bipush #32
    //   1072: irem
    //   1073: invokestatic abs : (I)I
    //   1076: invokevirtual charAt : (I)C
    //   1079: invokevirtual append : (C)Ljava/lang/StringBuilder;
    //   1082: pop
    //   1083: iload_2
    //   1084: ifne -> 1608
    //   1087: goto -> 1094
    //   1090: invokestatic a : (Ljava/lang/Throwable;)Ljava/lang/Throwable;
    //   1093: athrow
    //   1094: aload_3
    //   1095: getstatic burp/Zr8s.ZA : Ljava/lang/String;
    //   1098: getstatic burp/Zry7.ZZ : Ljava/lang/Object;
    //   1101: checkcast java/math/BigInteger
    //   1104: invokevirtual intValue : ()I
    //   1107: bipush #32
    //   1109: irem
    //   1110: invokestatic abs : (I)I
    //   1113: invokevirtual charAt : (I)C
    //   1116: invokevirtual append : (C)Ljava/lang/StringBuilder;
    //   1119: pop
    //   1120: iload_2
    //   1121: ifne -> 1608
    //   1124: goto -> 1131
    //   1127: invokestatic a : (Ljava/lang/Throwable;)Ljava/lang/Throwable;
    //   1130: athrow
    //   1131: aload_3
    //   1132: getstatic burp/Ztt0.Zl : Ljava/lang/String;
    //   1135: getstatic burp/Zb_c.ZN : Ljava/lang/Object;
    //   1138: checkcast java/math/BigInteger
    //   1141: invokevirtual intValue : ()I
    //   1144: bipush #32
    //   1146: irem
    //   1147: invokestatic abs : (I)I
    //   1150: invokevirtual charAt : (I)C
    //   1153: invokevirtual append : (C)Ljava/lang/StringBuilder;
    //   1156: pop
    //   1157: iload_2
    //   1158: ifne -> 1608
    //   1161: goto -> 1168
    //   1164: invokestatic a : (Ljava/lang/Throwable;)Ljava/lang/Throwable;
    //   1167: athrow
    //   1168: aload_3
    //   1169: getstatic burp/Zlzo.Zs : Ljava/lang/String;
    //   1172: getstatic burp/Zeno.Zo : Ljava/lang/Object;
    //   1175: checkcast java/math/BigInteger
    //   1178: invokevirtual intValue : ()I
    //   1181: bipush #32
    //   1183: irem
    //   1184: invokestatic abs : (I)I
    //   1187: invokevirtual charAt : (I)C
    //   1190: invokevirtual append : (C)Ljava/lang/StringBuilder;
    //   1193: pop
    //   1194: iload_2
    //   1195: ifne -> 1608
    //   1198: goto -> 1205
    //   1201: invokestatic a : (Ljava/lang/Throwable;)Ljava/lang/Throwable;
    //   1204: athrow
    //   1205: aload_3
    //   1206: getstatic burp/Zsk2.ZE : Ljava/lang/String;
    //   1209: getstatic burp/Zexu.ZI : Ljava/lang/Object;
    //   1212: checkcast java/math/BigInteger
    //   1215: invokevirtual intValue : ()I
    //   1218: bipush #32
    //   1220: irem
    //   1221: invokestatic abs : (I)I
    //   1224: invokevirtual charAt : (I)C
    //   1227: invokevirtual append : (C)Ljava/lang/StringBuilder;
    //   1230: pop
    //   1231: iload_2
    //   1232: ifne -> 1608
    //   1235: goto -> 1242
    //   1238: invokestatic a : (Ljava/lang/Throwable;)Ljava/lang/Throwable;
    //   1241: athrow
    //   1242: aload_3
    //   1243: getstatic burp/Zepm.Zl : Ljava/lang/String;
    //   1246: getstatic burp/Zttq.Zh : Ljava/lang/Object;
    //   1249: checkcast java/math/BigInteger
    //   1252: invokevirtual intValue : ()I
    //   1255: bipush #32
    //   1257: irem
    //   1258: invokestatic abs : (I)I
    //   1261: invokevirtual charAt : (I)C
    //   1264: invokevirtual append : (C)Ljava/lang/StringBuilder;
    //   1267: pop
    //   1268: iload_2
    //   1269: ifne -> 1608
    //   1272: goto -> 1279
    //   1275: invokestatic a : (Ljava/lang/Throwable;)Ljava/lang/Throwable;
    //   1278: athrow
    //   1279: aload_3
    //   1280: getstatic burp/Zz5s.ZL : Ljava/lang/String;
    //   1283: getstatic burp/Ztap.ZK : Ljava/lang/Object;
    //   1286: checkcast java/math/BigInteger
    //   1289: invokevirtual intValue : ()I
    //   1292: bipush #32
    //   1294: irem
    //   1295: invokestatic abs : (I)I
    //   1298: invokevirtual charAt : (I)C
    //   1301: invokevirtual append : (C)Ljava/lang/StringBuilder;
    //   1304: pop
    //   1305: iload_2
    //   1306: ifne -> 1608
    //   1309: goto -> 1316
    //   1312: invokestatic a : (Ljava/lang/Throwable;)Ljava/lang/Throwable;
    //   1315: athrow
    //   1316: aload_3
    //   1317: getstatic burp/Zm84.Zd : Ljava/lang/String;
    //   1320: getstatic burp/Ztmy.ZH : Ljava/lang/Object;
    //   1323: checkcast java/math/BigInteger
    //   1326: invokevirtual intValue : ()I
    //   1329: bipush #32
    //   1331: irem
    //   1332: invokestatic abs : (I)I
    //   1335: invokevirtual charAt : (I)C
    //   1338: invokevirtual append : (C)Ljava/lang/StringBuilder;
    //   1341: pop
    //   1342: iload_2
    //   1343: ifne -> 1608
    //   1346: goto -> 1353
    //   1349: invokestatic a : (Ljava/lang/Throwable;)Ljava/lang/Throwable;
    //   1352: athrow
    //   1353: aload_3
    //   1354: getstatic burp/Zr0.ZH : Ljava/lang/String;
    //   1357: getstatic burp/Zzky.Zo : Ljava/lang/Object;
    //   1360: checkcast java/math/BigInteger
    //   1363: invokevirtual intValue : ()I
    //   1366: bipush #32
    //   1368: irem
    //   1369: invokestatic abs : (I)I
    //   1372: invokevirtual charAt : (I)C
    //   1375: invokevirtual append : (C)Ljava/lang/StringBuilder;
    //   1378: pop
    //   1379: iload_2
    //   1380: ifne -> 1608
    //   1383: goto -> 1390
    //   1386: invokestatic a : (Ljava/lang/Throwable;)Ljava/lang/Throwable;
    //   1389: athrow
    //   1390: aload_3
    //   1391: getstatic burp/Zz9v.Zv : Ljava/lang/String;
    //   1394: getstatic burp/Zbnb.ZZ : Ljava/lang/Object;
    //   1397: checkcast java/math/BigInteger
    //   1400: invokevirtual intValue : ()I
    //   1403: bipush #32
    //   1405: irem
    //   1406: invokestatic abs : (I)I
    //   1409: invokevirtual charAt : (I)C
    //   1412: invokevirtual append : (C)Ljava/lang/StringBuilder;
    //   1415: pop
    //   1416: iload_2
    //   1417: ifne -> 1608
    //   1420: goto -> 1427
    //   1423: invokestatic a : (Ljava/lang/Throwable;)Ljava/lang/Throwable;
    //   1426: athrow
    //   1427: aload_3
    //   1428: getstatic burp/Zepm.Zl : Ljava/lang/String;
    //   1431: getstatic burp/Zblj.Zl : Ljava/lang/Object;
    //   1434: checkcast java/math/BigInteger
    //   1437: invokevirtual intValue : ()I
    //   1440: bipush #32
    //   1442: irem
    //   1443: invokestatic abs : (I)I
    //   1446: invokevirtual charAt : (I)C
    //   1449: invokevirtual append : (C)Ljava/lang/StringBuilder;
    //   1452: pop
    //   1453: iload_2
    //   1454: ifne -> 1608
    //   1457: goto -> 1464
    //   1460: invokestatic a : (Ljava/lang/Throwable;)Ljava/lang/Throwable;
    //   1463: athrow
    //   1464: aload_3
    //   1465: getstatic burp/Zgvf.ZM : Ljava/lang/String;
    //   1468: getstatic burp/Zlpl.Ze : Ljava/lang/Object;
    //   1471: checkcast java/math/BigInteger
    //   1474: invokevirtual intValue : ()I
    //   1477: bipush #32
    //   1479: irem
    //   1480: invokestatic abs : (I)I
    //   1483: invokevirtual charAt : (I)C
    //   1486: invokevirtual append : (C)Ljava/lang/StringBuilder;
    //   1489: pop
    //   1490: iload_2
    //   1491: ifne -> 1608
    //   1494: goto -> 1501
    //   1497: invokestatic a : (Ljava/lang/Throwable;)Ljava/lang/Throwable;
    //   1500: athrow
    //   1501: aload_3
    //   1502: getstatic burp/Zzlg.Zw : Ljava/lang/String;
    //   1505: getstatic burp/Zrxm.ZL : Ljava/lang/Object;
    //   1508: checkcast java/math/BigInteger
    //   1511: invokevirtual intValue : ()I
    //   1514: bipush #32
    //   1516: irem
    //   1517: invokestatic abs : (I)I
    //   1520: invokevirtual charAt : (I)C
    //   1523: invokevirtual append : (C)Ljava/lang/StringBuilder;
    //   1526: pop
    //   1527: iload_2
    //   1528: ifne -> 1608
    //   1531: goto -> 1538
    //   1534: invokestatic a : (Ljava/lang/Throwable;)Ljava/lang/Throwable;
    //   1537: athrow
    //   1538: aload_3
    //   1539: getstatic burp/Zgw7.ZN : Ljava/lang/String;
    //   1542: getstatic burp/Zry7.ZZ : Ljava/lang/Object;
    //   1545: checkcast java/math/BigInteger
    //   1548: invokevirtual intValue : ()I
    //   1551: bipush #32
    //   1553: irem
    //   1554: invokestatic abs : (I)I
    //   1557: invokevirtual charAt : (I)C
    //   1560: invokevirtual append : (C)Ljava/lang/StringBuilder;
    //   1563: pop
    //   1564: iload_2
    //   1565: ifne -> 1608
    //   1568: goto -> 1575
    //   1571: invokestatic a : (Ljava/lang/Throwable;)Ljava/lang/Throwable;
    //   1574: athrow
    //   1575: aload_3
    //   1576: getstatic burp/Zkcd.Zj : Ljava/lang/String;
    //   1579: getstatic burp/Zlxm.Zc : Ljava/lang/Object;
    //   1582: checkcast java/math/BigInteger
    //   1585: invokevirtual intValue : ()I
    //   1588: bipush #32
    //   1590: irem
    //   1591: invokestatic abs : (I)I
    //   1594: invokevirtual charAt : (I)C
    //   1597: invokevirtual append : (C)Ljava/lang/StringBuilder;
    //   1600: pop
    //   1601: goto -> 1608
    //   1604: invokestatic a : (Ljava/lang/Throwable;)Ljava/lang/Throwable;
    //   1607: athrow
    //   1608: iinc #4, 1
    //   1611: iload_2
    //   1612: ifne -> 276
    //   1615: aload_3
    //   1616: invokevirtual toString : ()Ljava/lang/String;
    //   1619: putstatic burp/Zgvl.Zc : Ljava/lang/String;
    //   1622: sipush #-24902
    //   1625: sipush #-19768
    //   1628: invokestatic a : (II)Ljava/lang/String;
    //   1631: iconst_1
    //   1632: ldc burp/Zevc
    //   1634: invokevirtual getClassLoader : ()Ljava/lang/ClassLoader;
    //   1637: invokestatic forName : (Ljava/lang/String;ZLjava/lang/ClassLoader;)Ljava/lang/Class;
    //   1640: invokevirtual getDeclaredFields : ()[Ljava/lang/reflect/Field;
    //   1643: astore #4
    //   1645: aload #4
    //   1647: arraylength
    //   1648: istore #5
    //   1650: iconst_0
    //   1651: istore #6
    //   1653: iload #6
    //   1655: iload #5
    //   1657: if_icmpge -> 1795
    //   1660: aload #4
    //   1662: iload #6
    //   1664: aaload
    //   1665: astore #7
    //   1667: aload #7
    //   1669: invokevirtual getModifiers : ()I
    //   1672: invokestatic isStatic : (I)Z
    //   1675: ifne -> 1685
    //   1678: goto -> 1788
    //   1681: invokestatic a : (Ljava/lang/Throwable;)Ljava/lang/Throwable;
    //   1684: athrow
    //   1685: aload #7
    //   1687: invokevirtual getType : ()Ljava/lang/Class;
    //   1690: astore #8
    //   1692: aload #8
    //   1694: ifnull -> 1775
    //   1697: aload #8
    //   1699: invokevirtual isPrimitive : ()Z
    //   1702: ifne -> 1775
    //   1705: goto -> 1712
    //   1708: invokestatic a : (Ljava/lang/Throwable;)Ljava/lang/Throwable;
    //   1711: athrow
    //   1712: aload #8
    //   1714: invokevirtual getPackage : ()Ljava/lang/Package;
    //   1717: ifnull -> 1775
    //   1720: goto -> 1727
    //   1723: invokestatic a : (Ljava/lang/Throwable;)Ljava/lang/Throwable;
    //   1726: athrow
    //   1727: aload #8
    //   1729: invokevirtual getPackage : ()Ljava/lang/Package;
    //   1732: invokevirtual getName : ()Ljava/lang/String;
    //   1735: ifnull -> 1775
    //   1738: goto -> 1745
    //   1741: invokestatic a : (Ljava/lang/Throwable;)Ljava/lang/Throwable;
    //   1744: athrow
    //   1745: aload #8
    //   1747: invokevirtual getPackage : ()Ljava/lang/Package;
    //   1750: invokevirtual getName : ()Ljava/lang/String;
    //   1753: sipush #-24928
    //   1756: sipush #-15507
    //   1759: invokestatic a : (II)Ljava/lang/String;
    //   1762: invokevirtual startsWith : (Ljava/lang/String;)Z
    //   1765: ifne -> 1775
    //   1768: goto -> 1775
    //   1771: invokestatic a : (Ljava/lang/Throwable;)Ljava/lang/Throwable;
    //   1774: athrow
    //   1775: aload #7
    //   1777: iconst_1
    //   1778: invokevirtual setAccessible : (Z)V
    //   1781: aload #7
    //   1783: aconst_null
    //   1784: invokevirtual get : (Ljava/lang/Object;)Ljava/lang/Object;
    //   1787: pop
    //   1788: iinc #6, 1
    //   1791: iload_2
    //   1792: ifne -> 1653
    //   1795: sipush #-24903
    //   1798: bipush #-80
    //   1800: invokestatic a : (II)Ljava/lang/String;
    //   1803: invokestatic forName : (Ljava/lang/String;)Ljava/lang/Class;
    //   1806: invokevirtual getDeclaredMethods : ()[Ljava/lang/reflect/Method;
    //   1809: astore #4
    //   1811: aload #4
    //   1813: arraylength
    //   1814: istore #5
    //   1816: iconst_0
    //   1817: istore #6
    //   1819: iload #6
    //   1821: iload #5
    //   1823: if_icmpge -> 1956
    //   1826: aload #4
    //   1828: iload #6
    //   1830: aaload
    //   1831: astore #7
    //   1833: aload #7
    //   1835: invokevirtual getParameterTypes : ()[Ljava/lang/Class;
    //   1838: pop
    //   1839: aload #7
    //   1841: invokevirtual getModifiers : ()I
    //   1844: invokestatic isStatic : (I)Z
    //   1847: ifeq -> 1942
    //   1850: aload #7
    //   1852: invokevirtual getParameterTypes : ()[Ljava/lang/Class;
    //   1855: arraylength
    //   1856: iconst_2
    //   1857: if_icmpne -> 1942
    //   1860: goto -> 1867
    //   1863: invokestatic a : (Ljava/lang/Throwable;)Ljava/lang/Throwable;
    //   1866: athrow
    //   1867: aload #7
    //   1869: invokevirtual getReturnType : ()Ljava/lang/Class;
    //   1872: getstatic java/lang/Void.TYPE : Ljava/lang/Class;
    //   1875: invokevirtual equals : (Ljava/lang/Object;)Z
    //   1878: ifeq -> 1942
    //   1881: goto -> 1888
    //   1884: invokestatic a : (Ljava/lang/Throwable;)Ljava/lang/Throwable;
    //   1887: athrow
    //   1888: aload #7
    //   1890: iconst_1
    //   1891: invokevirtual setAccessible : (Z)V
    //   1894: aload #7
    //   1896: aconst_null
    //   1897: iconst_2
    //   1898: anewarray java/lang/Object
    //   1901: dup
    //   1902: iconst_0
    //   1903: aload_0
    //   1904: aastore
    //   1905: dup
    //   1906: iconst_1
    //   1907: aload_1
    //   1908: ifnonnull -> 1926
    //   1911: goto -> 1918
    //   1914: invokestatic a : (Ljava/lang/Throwable;)Ljava/lang/Throwable;
    //   1917: athrow
    //   1918: aload_1
    //   1919: goto -> 1933
    //   1922: invokestatic a : (Ljava/lang/Throwable;)Ljava/lang/Throwable;
    //   1925: athrow
    //   1926: aload_1
    //   1927: checkcast [B
    //   1930: invokevirtual clone : ()Ljava/lang/Object;
    //   1933: aastore
    //   1934: invokevirtual invoke : (Ljava/lang/Object;[Ljava/lang/Object;)Ljava/lang/Object;
    //   1937: pop
    //   1938: iload_2
    //   1939: ifne -> 1956
    //   1942: iinc #6, 1
    //   1945: iload_2
    //   1946: ifne -> 1819
    //   1949: goto -> 1956
    //   1952: invokestatic a : (Ljava/lang/Throwable;)Ljava/lang/Throwable;
    //   1955: athrow
    //   1956: iconst_0
    //   1957: istore #4
    //   1959: getstatic burp/Zete.ZH : Ljava/lang/String;
    //   1962: getstatic burp/Zkk6.Zb : Ljava/lang/Object;
    //   1965: checkcast java/math/BigInteger
    //   1968: invokevirtual intValue : ()I
    //   1971: bipush #32
    //   1973: irem
    //   1974: invokestatic abs : (I)I
    //   1977: invokevirtual charAt : (I)C
    //   1980: getstatic burp/Zkaw.ZI : Ljava/lang/String;
    //   1983: getstatic burp/Zzr.ZZ : Ljava/lang/Object;
    //   1986: checkcast java/math/BigInteger
    //   1989: invokevirtual intValue : ()I
    //   1992: bipush #32
    //   1994: irem
    //   1995: invokestatic abs : (I)I
    //   1998: invokevirtual charAt : (I)C
    //   2001: if_icmpgt -> 2346
    //   2004: sipush #-24925
    //   2007: sipush #12407
    //   2010: invokestatic a : (II)Ljava/lang/String;
    //   2013: iconst_1
    //   2014: ldc burp/Zg0j
    //   2016: invokevirtual getClassLoader : ()Ljava/lang/ClassLoader;
    //   2019: invokestatic forName : (Ljava/lang/String;ZLjava/lang/ClassLoader;)Ljava/lang/Class;
    //   2022: invokevirtual getDeclaredFields : ()[Ljava/lang/reflect/Field;
    //   2025: astore #5
    //   2027: aload #5
    //   2029: arraylength
    //   2030: istore #6
    //   2032: iconst_0
    //   2033: istore #7
    //   2035: iload #7
    //   2037: iload #6
    //   2039: if_icmpge -> 2177
    //   2042: aload #5
    //   2044: iload #7
    //   2046: aaload
    //   2047: astore #8
    //   2049: aload #8
    //   2051: invokevirtual getModifiers : ()I
    //   2054: invokestatic isStatic : (I)Z
    //   2057: ifne -> 2067
    //   2060: goto -> 2170
    //   2063: invokestatic a : (Ljava/lang/Throwable;)Ljava/lang/Throwable;
    //   2066: athrow
    //   2067: aload #8
    //   2069: invokevirtual getType : ()Ljava/lang/Class;
    //   2072: astore #9
    //   2074: aload #9
    //   2076: ifnull -> 2157
    //   2079: aload #9
    //   2081: invokevirtual isPrimitive : ()Z
    //   2084: ifne -> 2157
    //   2087: goto -> 2094
    //   2090: invokestatic a : (Ljava/lang/Throwable;)Ljava/lang/Throwable;
    //   2093: athrow
    //   2094: aload #9
    //   2096: invokevirtual getPackage : ()Ljava/lang/Package;
    //   2099: ifnull -> 2157
    //   2102: goto -> 2109
    //   2105: invokestatic a : (Ljava/lang/Throwable;)Ljava/lang/Throwable;
    //   2108: athrow
    //   2109: aload #9
    //   2111: invokevirtual getPackage : ()Ljava/lang/Package;
    //   2114: invokevirtual getName : ()Ljava/lang/String;
    //   2117: ifnull -> 2157
    //   2120: goto -> 2127
    //   2123: invokestatic a : (Ljava/lang/Throwable;)Ljava/lang/Throwable;
    //   2126: athrow
    //   2127: aload #9
    //   2129: invokevirtual getPackage : ()Ljava/lang/Package;
    //   2132: invokevirtual getName : ()Ljava/lang/String;
    //   2135: sipush #-24908
    //   2138: sipush #10742
    //   2141: invokestatic a : (II)Ljava/lang/String;
    //   2144: invokevirtual startsWith : (Ljava/lang/String;)Z
    //   2147: ifne -> 2157
    //   2150: goto -> 2157
    //   2153: invokestatic a : (Ljava/lang/Throwable;)Ljava/lang/Throwable;
    //   2156: athrow
    //   2157: aload #8
    //   2159: iconst_1
    //   2160: invokevirtual setAccessible : (Z)V
    //   2163: aload #8
    //   2165: aconst_null
    //   2166: invokevirtual get : (Ljava/lang/Object;)Ljava/lang/Object;
    //   2169: pop
    //   2170: iinc #7, 1
    //   2173: iload_2
    //   2174: ifne -> 2035
    //   2177: sipush #-24926
    //   2180: sipush #-10273
    //   2183: invokestatic a : (II)Ljava/lang/String;
    //   2186: invokestatic forName : (Ljava/lang/String;)Ljava/lang/Class;
    //   2189: invokevirtual getDeclaredMethods : ()[Ljava/lang/reflect/Method;
    //   2192: astore #5
    //   2194: aload #5
    //   2196: arraylength
    //   2197: istore #6
    //   2199: iconst_0
    //   2200: istore #7
    //   2202: iload #7
    //   2204: iload #6
    //   2206: if_icmpge -> 2343
    //   2209: aload #5
    //   2211: iload #7
    //   2213: aaload
    //   2214: astore #8
    //   2216: aload #8
    //   2218: invokevirtual getParameterTypes : ()[Ljava/lang/Class;
    //   2221: pop
    //   2222: aload #8
    //   2224: invokevirtual getModifiers : ()I
    //   2227: invokestatic isStatic : (I)Z
    //   2230: ifeq -> 2329
    //   2233: aload #8
    //   2235: invokevirtual getParameterTypes : ()[Ljava/lang/Class;
    //   2238: arraylength
    //   2239: iconst_2
    //   2240: if_icmpne -> 2329
    //   2243: goto -> 2250
    //   2246: invokestatic a : (Ljava/lang/Throwable;)Ljava/lang/Throwable;
    //   2249: athrow
    //   2250: aload #8
    //   2252: invokevirtual getReturnType : ()Ljava/lang/Class;
    //   2255: getstatic java/lang/Boolean.TYPE : Ljava/lang/Class;
    //   2258: if_acmpne -> 2329
    //   2261: goto -> 2268
    //   2264: invokestatic a : (Ljava/lang/Throwable;)Ljava/lang/Throwable;
    //   2267: athrow
    //   2268: aload #8
    //   2270: iconst_1
    //   2271: invokevirtual setAccessible : (Z)V
    //   2274: aload #8
    //   2276: aconst_null
    //   2277: iconst_2
    //   2278: anewarray java/lang/Object
    //   2281: dup
    //   2282: iconst_0
    //   2283: aload_0
    //   2284: aastore
    //   2285: dup
    //   2286: iconst_1
    //   2287: aload_1
    //   2288: ifnonnull -> 2306
    //   2291: goto -> 2298
    //   2294: invokestatic a : (Ljava/lang/Throwable;)Ljava/lang/Throwable;
    //   2297: athrow
    //   2298: aload_1
    //   2299: goto -> 2313
    //   2302: invokestatic a : (Ljava/lang/Throwable;)Ljava/lang/Throwable;
    //   2305: athrow
    //   2306: aload_1
    //   2307: checkcast [B
    //   2310: invokevirtual clone : ()Ljava/lang/Object;
    //   2313: aastore
    //   2314: invokevirtual invoke : (Ljava/lang/Object;[Ljava/lang/Object;)Ljava/lang/Object;
    //   2317: checkcast java/lang/Boolean
    //   2320: invokevirtual booleanValue : ()Z
    //   2323: istore #4
    //   2325: iload_2
    //   2326: ifne -> 2343
    //   2329: iinc #7, 1
    //   2332: iload_2
    //   2333: ifne -> 2202
    //   2336: goto -> 2343
    //   2339: invokestatic a : (Ljava/lang/Throwable;)Ljava/lang/Throwable;
    //   2342: athrow
    //   2343: goto -> 2685
    //   2346: sipush #-24910
    //   2349: sipush #-28891
    //   2352: invokestatic a : (II)Ljava/lang/String;
    //   2355: iconst_1
    //   2356: ldc burp/Zetv
    //   2358: invokevirtual getClassLoader : ()Ljava/lang/ClassLoader;
    //   2361: invokestatic forName : (Ljava/lang/String;ZLjava/lang/ClassLoader;)Ljava/lang/Class;
    //   2364: invokevirtual getDeclaredFields : ()[Ljava/lang/reflect/Field;
    //   2367: astore #5
    //   2369: aload #5
    //   2371: arraylength
    //   2372: istore #6
    //   2374: iconst_0
    //   2375: istore #7
    //   2377: iload #7
    //   2379: iload #6
    //   2381: if_icmpge -> 2519
    //   2384: aload #5
    //   2386: iload #7
    //   2388: aaload
    //   2389: astore #8
    //   2391: aload #8
    //   2393: invokevirtual getModifiers : ()I
    //   2396: invokestatic isStatic : (I)Z
    //   2399: ifne -> 2409
    //   2402: goto -> 2512
    //   2405: invokestatic a : (Ljava/lang/Throwable;)Ljava/lang/Throwable;
    //   2408: athrow
    //   2409: aload #8
    //   2411: invokevirtual getType : ()Ljava/lang/Class;
    //   2414: astore #9
    //   2416: aload #9
    //   2418: ifnull -> 2499
    //   2421: aload #9
    //   2423: invokevirtual isPrimitive : ()Z
    //   2426: ifne -> 2499
    //   2429: goto -> 2436
    //   2432: invokestatic a : (Ljava/lang/Throwable;)Ljava/lang/Throwable;
    //   2435: athrow
    //   2436: aload #9
    //   2438: invokevirtual getPackage : ()Ljava/lang/Package;
    //   2441: ifnull -> 2499
    //   2444: goto -> 2451
    //   2447: invokestatic a : (Ljava/lang/Throwable;)Ljava/lang/Throwable;
    //   2450: athrow
    //   2451: aload #9
    //   2453: invokevirtual getPackage : ()Ljava/lang/Package;
    //   2456: invokevirtual getName : ()Ljava/lang/String;
    //   2459: ifnull -> 2499
    //   2462: goto -> 2469
    //   2465: invokestatic a : (Ljava/lang/Throwable;)Ljava/lang/Throwable;
    //   2468: athrow
    //   2469: aload #9
    //   2471: invokevirtual getPackage : ()Ljava/lang/Package;
    //   2474: invokevirtual getName : ()Ljava/lang/String;
    //   2477: sipush #-24908
    //   2480: sipush #10742
    //   2483: invokestatic a : (II)Ljava/lang/String;
    //   2486: invokevirtual startsWith : (Ljava/lang/String;)Z
    //   2489: ifne -> 2499
    //   2492: goto -> 2499
    //   2495: invokestatic a : (Ljava/lang/Throwable;)Ljava/lang/Throwable;
    //   2498: athrow
    //   2499: aload #8
    //   2501: iconst_1
    //   2502: invokevirtual setAccessible : (Z)V
    //   2505: aload #8
    //   2507: aconst_null
    //   2508: invokevirtual get : (Ljava/lang/Object;)Ljava/lang/Object;
    //   2511: pop
    //   2512: iinc #7, 1
    //   2515: iload_2
    //   2516: ifne -> 2377
    //   2519: sipush #-24924
    //   2522: sipush #-9738
    //   2525: invokestatic a : (II)Ljava/lang/String;
    //   2528: invokestatic forName : (Ljava/lang/String;)Ljava/lang/Class;
    //   2531: invokevirtual getDeclaredMethods : ()[Ljava/lang/reflect/Method;
    //   2534: astore #5
    //   2536: aload #5
    //   2538: arraylength
    //   2539: istore #6
    //   2541: iconst_0
    //   2542: istore #7
    //   2544: iload #7
    //   2546: iload #6
    //   2548: if_icmpge -> 2685
    //   2551: aload #5
    //   2553: iload #7
    //   2555: aaload
    //   2556: astore #8
    //   2558: aload #8
    //   2560: invokevirtual getParameterTypes : ()[Ljava/lang/Class;
    //   2563: pop
    //   2564: aload #8
    //   2566: invokevirtual getModifiers : ()I
    //   2569: invokestatic isStatic : (I)Z
    //   2572: ifeq -> 2671
    //   2575: aload #8
    //   2577: invokevirtual getParameterTypes : ()[Ljava/lang/Class;
    //   2580: arraylength
    //   2581: iconst_2
    //   2582: if_icmpne -> 2671
    //   2585: goto -> 2592
    //   2588: invokestatic a : (Ljava/lang/Throwable;)Ljava/lang/Throwable;
    //   2591: athrow
    //   2592: aload #8
    //   2594: invokevirtual getReturnType : ()Ljava/lang/Class;
    //   2597: getstatic java/lang/Boolean.TYPE : Ljava/lang/Class;
    //   2600: if_acmpne -> 2671
    //   2603: goto -> 2610
    //   2606: invokestatic a : (Ljava/lang/Throwable;)Ljava/lang/Throwable;
    //   2609: athrow
    //   2610: aload #8
    //   2612: iconst_1
    //   2613: invokevirtual setAccessible : (Z)V
    //   2616: aload #8
    //   2618: aconst_null
    //   2619: iconst_2
    //   2620: anewarray java/lang/Object
    //   2623: dup
    //   2624: iconst_0
    //   2625: aload_0
    //   2626: aastore
    //   2627: dup
    //   2628: iconst_1
    //   2629: aload_1
    //   2630: ifnonnull -> 2648
    //   2633: goto -> 2640
    //   2636: invokestatic a : (Ljava/lang/Throwable;)Ljava/lang/Throwable;
    //   2639: athrow
    //   2640: aload_1
    //   2641: goto -> 2655
    //   2644: invokestatic a : (Ljava/lang/Throwable;)Ljava/lang/Throwable;
    //   2647: athrow
    //   2648: aload_1
    //   2649: checkcast [B
    //   2652: invokevirtual clone : ()Ljava/lang/Object;
    //   2655: aastore
    //   2656: invokevirtual invoke : (Ljava/lang/Object;[Ljava/lang/Object;)Ljava/lang/Object;
    //   2659: checkcast java/lang/Boolean
    //   2662: invokevirtual booleanValue : ()Z
    //   2665: istore #4
    //   2667: iload_2
    //   2668: ifne -> 2685
    //   2671: iinc #7, 1
    //   2674: iload_2
    //   2675: ifne -> 2544
    //   2678: goto -> 2685
    //   2681: invokestatic a : (Ljava/lang/Throwable;)Ljava/lang/Throwable;
    //   2684: athrow
    //   2685: iload #4
    //   2687: ifeq -> 2693
    //   2690: iload #4
    //   2692: ireturn
    //   2693: getstatic burp/Zezn.Ze : Ljava/lang/String;
    //   2696: getstatic burp/Zlzo.ZJ : Ljava/lang/Object;
    //   2699: checkcast java/math/BigInteger
    //   2702: invokevirtual intValue : ()I
    //   2705: bipush #32
    //   2707: irem
    //   2708: invokestatic abs : (I)I
    //   2711: invokevirtual charAt : (I)C
    //   2714: getstatic burp/Zle4.ZX : Ljava/lang/String;
    //   2717: getstatic burp/Zxdh.ZD : Ljava/lang/Object;
    //   2720: checkcast java/math/BigInteger
    //   2723: invokevirtual intValue : ()I
    //   2726: bipush #32
    //   2728: irem
    //   2729: invokestatic abs : (I)I
    //   2732: invokevirtual charAt : (I)C
    //   2735: if_icmple -> 3081
    //   2738: sipush #-24923
    //   2741: sipush #31798
    //   2744: invokestatic a : (II)Ljava/lang/String;
    //   2747: iconst_1
    //   2748: ldc burp/Zg3v
    //   2750: invokevirtual getClassLoader : ()Ljava/lang/ClassLoader;
    //   2753: invokestatic forName : (Ljava/lang/String;ZLjava/lang/ClassLoader;)Ljava/lang/Class;
    //   2756: invokevirtual getDeclaredFields : ()[Ljava/lang/reflect/Field;
    //   2759: astore #5
    //   2761: aload #5
    //   2763: arraylength
    //   2764: istore #6
    //   2766: iconst_0
    //   2767: istore #7
    //   2769: iload #7
    //   2771: iload #6
    //   2773: if_icmpge -> 2911
    //   2776: aload #5
    //   2778: iload #7
    //   2780: aaload
    //   2781: astore #8
    //   2783: aload #8
    //   2785: invokevirtual getModifiers : ()I
    //   2788: invokestatic isStatic : (I)Z
    //   2791: ifne -> 2801
    //   2794: goto -> 2904
    //   2797: invokestatic a : (Ljava/lang/Throwable;)Ljava/lang/Throwable;
    //   2800: athrow
    //   2801: aload #8
    //   2803: invokevirtual getType : ()Ljava/lang/Class;
    //   2806: astore #9
    //   2808: aload #9
    //   2810: ifnull -> 2891
    //   2813: aload #9
    //   2815: invokevirtual isPrimitive : ()Z
    //   2818: ifne -> 2891
    //   2821: goto -> 2828
    //   2824: invokestatic a : (Ljava/lang/Throwable;)Ljava/lang/Throwable;
    //   2827: athrow
    //   2828: aload #9
    //   2830: invokevirtual getPackage : ()Ljava/lang/Package;
    //   2833: ifnull -> 2891
    //   2836: goto -> 2843
    //   2839: invokestatic a : (Ljava/lang/Throwable;)Ljava/lang/Throwable;
    //   2842: athrow
    //   2843: aload #9
    //   2845: invokevirtual getPackage : ()Ljava/lang/Package;
    //   2848: invokevirtual getName : ()Ljava/lang/String;
    //   2851: ifnull -> 2891
    //   2854: goto -> 2861
    //   2857: invokestatic a : (Ljava/lang/Throwable;)Ljava/lang/Throwable;
    //   2860: athrow
    //   2861: aload #9
    //   2863: invokevirtual getPackage : ()Ljava/lang/Package;
    //   2866: invokevirtual getName : ()Ljava/lang/String;
    //   2869: sipush #-24908
    //   2872: sipush #10742
    //   2875: invokestatic a : (II)Ljava/lang/String;
    //   2878: invokevirtual startsWith : (Ljava/lang/String;)Z
    //   2881: ifne -> 2891
    //   2884: goto -> 2891
    //   2887: invokestatic a : (Ljava/lang/Throwable;)Ljava/lang/Throwable;
    //   2890: athrow
    //   2891: aload #8
    //   2893: iconst_1
    //   2894: invokevirtual setAccessible : (Z)V
    //   2897: aload #8
    //   2899: aconst_null
    //   2900: invokevirtual get : (Ljava/lang/Object;)Ljava/lang/Object;
    //   2903: pop
    //   2904: iinc #7, 1
    //   2907: iload_2
    //   2908: ifne -> 2769
    //   2911: sipush #-24897
    //   2914: sipush #-16015
    //   2917: invokestatic a : (II)Ljava/lang/String;
    //   2920: invokestatic forName : (Ljava/lang/String;)Ljava/lang/Class;
    //   2923: invokevirtual getDeclaredMethods : ()[Ljava/lang/reflect/Method;
    //   2926: astore #5
    //   2928: aload #5
    //   2930: arraylength
    //   2931: istore #6
    //   2933: iconst_0
    //   2934: istore #7
    //   2936: iload #7
    //   2938: iload #6
    //   2940: if_icmpge -> 3077
    //   2943: aload #5
    //   2945: iload #7
    //   2947: aaload
    //   2948: astore #8
    //   2950: aload #8
    //   2952: invokevirtual getParameterTypes : ()[Ljava/lang/Class;
    //   2955: pop
    //   2956: aload #8
    //   2958: invokevirtual getModifiers : ()I
    //   2961: invokestatic isStatic : (I)Z
    //   2964: ifeq -> 3063
    //   2967: aload #8
    //   2969: invokevirtual getParameterTypes : ()[Ljava/lang/Class;
    //   2972: arraylength
    //   2973: iconst_2
    //   2974: if_icmpne -> 3063
    //   2977: goto -> 2984
    //   2980: invokestatic a : (Ljava/lang/Throwable;)Ljava/lang/Throwable;
    //   2983: athrow
    //   2984: aload #8
    //   2986: invokevirtual getReturnType : ()Ljava/lang/Class;
    //   2989: getstatic java/lang/Boolean.TYPE : Ljava/lang/Class;
    //   2992: if_acmpne -> 3063
    //   2995: goto -> 3002
    //   2998: invokestatic a : (Ljava/lang/Throwable;)Ljava/lang/Throwable;
    //   3001: athrow
    //   3002: aload #8
    //   3004: iconst_1
    //   3005: invokevirtual setAccessible : (Z)V
    //   3008: aload #8
    //   3010: aconst_null
    //   3011: iconst_2
    //   3012: anewarray java/lang/Object
    //   3015: dup
    //   3016: iconst_0
    //   3017: aload_0
    //   3018: aastore
    //   3019: dup
    //   3020: iconst_1
    //   3021: aload_1
    //   3022: ifnonnull -> 3040
    //   3025: goto -> 3032
    //   3028: invokestatic a : (Ljava/lang/Throwable;)Ljava/lang/Throwable;
    //   3031: athrow
    //   3032: aload_1
    //   3033: goto -> 3047
    //   3036: invokestatic a : (Ljava/lang/Throwable;)Ljava/lang/Throwable;
    //   3039: athrow
    //   3040: aload_1
    //   3041: checkcast [B
    //   3044: invokevirtual clone : ()Ljava/lang/Object;
    //   3047: aastore
    //   3048: invokevirtual invoke : (Ljava/lang/Object;[Ljava/lang/Object;)Ljava/lang/Object;
    //   3051: checkcast java/lang/Boolean
    //   3054: invokevirtual booleanValue : ()Z
    //   3057: istore #4
    //   3059: iload_2
    //   3060: ifne -> 3077
    //   3063: iinc #7, 1
    //   3066: iload_2
    //   3067: ifne -> 2936
    //   3070: goto -> 3077
    //   3073: invokestatic a : (Ljava/lang/Throwable;)Ljava/lang/Throwable;
    //   3076: athrow
    //   3077: iload_2
    //   3078: ifne -> 3420
    //   3081: sipush #-24919
    //   3084: sipush #18096
    //   3087: invokestatic a : (II)Ljava/lang/String;
    //   3090: iconst_1
    //   3091: ldc burp/Zxjw
    //   3093: invokevirtual getClassLoader : ()Ljava/lang/ClassLoader;
    //   3096: invokestatic forName : (Ljava/lang/String;ZLjava/lang/ClassLoader;)Ljava/lang/Class;
    //   3099: invokevirtual getDeclaredFields : ()[Ljava/lang/reflect/Field;
    //   3102: astore #5
    //   3104: aload #5
    //   3106: arraylength
    //   3107: istore #6
    //   3109: iconst_0
    //   3110: istore #7
    //   3112: iload #7
    //   3114: iload #6
    //   3116: if_icmpge -> 3254
    //   3119: aload #5
    //   3121: iload #7
    //   3123: aaload
    //   3124: astore #8
    //   3126: aload #8
    //   3128: invokevirtual getModifiers : ()I
    //   3131: invokestatic isStatic : (I)Z
    //   3134: ifne -> 3144
    //   3137: goto -> 3247
    //   3140: invokestatic a : (Ljava/lang/Throwable;)Ljava/lang/Throwable;
    //   3143: athrow
    //   3144: aload #8
    //   3146: invokevirtual getType : ()Ljava/lang/Class;
    //   3149: astore #9
    //   3151: aload #9
    //   3153: ifnull -> 3234
    //   3156: aload #9
    //   3158: invokevirtual isPrimitive : ()Z
    //   3161: ifne -> 3234
    //   3164: goto -> 3171
    //   3167: invokestatic a : (Ljava/lang/Throwable;)Ljava/lang/Throwable;
    //   3170: athrow
    //   3171: aload #9
    //   3173: invokevirtual getPackage : ()Ljava/lang/Package;
    //   3176: ifnull -> 3234
    //   3179: goto -> 3186
    //   3182: invokestatic a : (Ljava/lang/Throwable;)Ljava/lang/Throwable;
    //   3185: athrow
    //   3186: aload #9
    //   3188: invokevirtual getPackage : ()Ljava/lang/Package;
    //   3191: invokevirtual getName : ()Ljava/lang/String;
    //   3194: ifnull -> 3234
    //   3197: goto -> 3204
    //   3200: invokestatic a : (Ljava/lang/Throwable;)Ljava/lang/Throwable;
    //   3203: athrow
    //   3204: aload #9
    //   3206: invokevirtual getPackage : ()Ljava/lang/Package;
    //   3209: invokevirtual getName : ()Ljava/lang/String;
    //   3212: sipush #-24908
    //   3215: sipush #10742
    //   3218: invokestatic a : (II)Ljava/lang/String;
    //   3221: invokevirtual startsWith : (Ljava/lang/String;)Z
    //   3224: ifne -> 3234
    //   3227: goto -> 3234
    //   3230: invokestatic a : (Ljava/lang/Throwable;)Ljava/lang/Throwable;
    //   3233: athrow
    //   3234: aload #8
    //   3236: iconst_1
    //   3237: invokevirtual setAccessible : (Z)V
    //   3240: aload #8
    //   3242: aconst_null
    //   3243: invokevirtual get : (Ljava/lang/Object;)Ljava/lang/Object;
    //   3246: pop
    //   3247: iinc #7, 1
    //   3250: iload_2
    //   3251: ifne -> 3112
    //   3254: sipush #-24901
    //   3257: sipush #13140
    //   3260: invokestatic a : (II)Ljava/lang/String;
    //   3263: invokestatic forName : (Ljava/lang/String;)Ljava/lang/Class;
    //   3266: invokevirtual getDeclaredMethods : ()[Ljava/lang/reflect/Method;
    //   3269: astore #5
    //   3271: aload #5
    //   3273: arraylength
    //   3274: istore #6
    //   3276: iconst_0
    //   3277: istore #7
    //   3279: iload #7
    //   3281: iload #6
    //   3283: if_icmpge -> 3420
    //   3286: aload #5
    //   3288: iload #7
    //   3290: aaload
    //   3291: astore #8
    //   3293: aload #8
    //   3295: invokevirtual getParameterTypes : ()[Ljava/lang/Class;
    //   3298: pop
    //   3299: aload #8
    //   3301: invokevirtual getModifiers : ()I
    //   3304: invokestatic isStatic : (I)Z
    //   3307: ifeq -> 3406
    //   3310: aload #8
    //   3312: invokevirtual getParameterTypes : ()[Ljava/lang/Class;
    //   3315: arraylength
    //   3316: iconst_2
    //   3317: if_icmpne -> 3406
    //   3320: goto -> 3327
    //   3323: invokestatic a : (Ljava/lang/Throwable;)Ljava/lang/Throwable;
    //   3326: athrow
    //   3327: aload #8
    //   3329: invokevirtual getReturnType : ()Ljava/lang/Class;
    //   3332: getstatic java/lang/Boolean.TYPE : Ljava/lang/Class;
    //   3335: if_acmpne -> 3406
    //   3338: goto -> 3345
    //   3341: invokestatic a : (Ljava/lang/Throwable;)Ljava/lang/Throwable;
    //   3344: athrow
    //   3345: aload #8
    //   3347: iconst_1
    //   3348: invokevirtual setAccessible : (Z)V
    //   3351: aload #8
    //   3353: aconst_null
    //   3354: iconst_2
    //   3355: anewarray java/lang/Object
    //   3358: dup
    //   3359: iconst_0
    //   3360: aload_0
    //   3361: aastore
    //   3362: dup
    //   3363: iconst_1
    //   3364: aload_1
    //   3365: ifnonnull -> 3383
    //   3368: goto -> 3375
    //   3371: invokestatic a : (Ljava/lang/Throwable;)Ljava/lang/Throwable;
    //   3374: athrow
    //   3375: aload_1
    //   3376: goto -> 3390
    //   3379: invokestatic a : (Ljava/lang/Throwable;)Ljava/lang/Throwable;
    //   3382: athrow
    //   3383: aload_1
    //   3384: checkcast [B
    //   3387: invokevirtual clone : ()Ljava/lang/Object;
    //   3390: aastore
    //   3391: invokevirtual invoke : (Ljava/lang/Object;[Ljava/lang/Object;)Ljava/lang/Object;
    //   3394: checkcast java/lang/Boolean
    //   3397: invokevirtual booleanValue : ()Z
    //   3400: istore #4
    //   3402: iload_2
    //   3403: ifne -> 3420
    //   3406: iinc #7, 1
    //   3409: iload_2
    //   3410: ifne -> 3279
    //   3413: goto -> 3420
    //   3416: invokestatic a : (Ljava/lang/Throwable;)Ljava/lang/Throwable;
    //   3419: athrow
    //   3420: iload #4
    //   3422: ifeq -> 3428
    //   3425: iload #4
    //   3427: ireturn
    //   3428: getstatic burp/Ztmy.ZF : Ljava/lang/String;
    //   3431: getstatic burp/Zb6b.ZU : Ljava/lang/Object;
    //   3434: checkcast java/math/BigInteger
    //   3437: invokevirtual intValue : ()I
    //   3440: bipush #32
    //   3442: irem
    //   3443: invokestatic abs : (I)I
    //   3446: invokevirtual charAt : (I)C
    //   3449: getstatic burp/Ze0w.ZT : Ljava/lang/String;
    //   3452: getstatic burp/Zb_c.ZN : Ljava/lang/Object;
    //   3455: checkcast java/math/BigInteger
    //   3458: invokevirtual intValue : ()I
    //   3461: bipush #32
    //   3463: irem
    //   3464: invokestatic abs : (I)I
    //   3467: invokevirtual charAt : (I)C
    //   3470: if_icmple -> 3816
    //   3473: sipush #-24927
    //   3476: sipush #8335
    //   3479: invokestatic a : (II)Ljava/lang/String;
    //   3482: iconst_1
    //   3483: ldc burp/Zm54
    //   3485: invokevirtual getClassLoader : ()Ljava/lang/ClassLoader;
    //   3488: invokestatic forName : (Ljava/lang/String;ZLjava/lang/ClassLoader;)Ljava/lang/Class;
    //   3491: invokevirtual getDeclaredFields : ()[Ljava/lang/reflect/Field;
    //   3494: astore #5
    //   3496: aload #5
    //   3498: arraylength
    //   3499: istore #6
    //   3501: iconst_0
    //   3502: istore #7
    //   3504: iload #7
    //   3506: iload #6
    //   3508: if_icmpge -> 3646
    //   3511: aload #5
    //   3513: iload #7
    //   3515: aaload
    //   3516: astore #8
    //   3518: aload #8
    //   3520: invokevirtual getModifiers : ()I
    //   3523: invokestatic isStatic : (I)Z
    //   3526: ifne -> 3536
    //   3529: goto -> 3639
    //   3532: invokestatic a : (Ljava/lang/Throwable;)Ljava/lang/Throwable;
    //   3535: athrow
    //   3536: aload #8
    //   3538: invokevirtual getType : ()Ljava/lang/Class;
    //   3541: astore #9
    //   3543: aload #9
    //   3545: ifnull -> 3626
    //   3548: aload #9
    //   3550: invokevirtual isPrimitive : ()Z
    //   3553: ifne -> 3626
    //   3556: goto -> 3563
    //   3559: invokestatic a : (Ljava/lang/Throwable;)Ljava/lang/Throwable;
    //   3562: athrow
    //   3563: aload #9
    //   3565: invokevirtual getPackage : ()Ljava/lang/Package;
    //   3568: ifnull -> 3626
    //   3571: goto -> 3578
    //   3574: invokestatic a : (Ljava/lang/Throwable;)Ljava/lang/Throwable;
    //   3577: athrow
    //   3578: aload #9
    //   3580: invokevirtual getPackage : ()Ljava/lang/Package;
    //   3583: invokevirtual getName : ()Ljava/lang/String;
    //   3586: ifnull -> 3626
    //   3589: goto -> 3596
    //   3592: invokestatic a : (Ljava/lang/Throwable;)Ljava/lang/Throwable;
    //   3595: athrow
    //   3596: aload #9
    //   3598: invokevirtual getPackage : ()Ljava/lang/Package;
    //   3601: invokevirtual getName : ()Ljava/lang/String;
    //   3604: sipush #-24908
    //   3607: sipush #10742
    //   3610: invokestatic a : (II)Ljava/lang/String;
    //   3613: invokevirtual startsWith : (Ljava/lang/String;)Z
    //   3616: ifne -> 3626
    //   3619: goto -> 3626
    //   3622: invokestatic a : (Ljava/lang/Throwable;)Ljava/lang/Throwable;
    //   3625: athrow
    //   3626: aload #8
    //   3628: iconst_1
    //   3629: invokevirtual setAccessible : (Z)V
    //   3632: aload #8
    //   3634: aconst_null
    //   3635: invokevirtual get : (Ljava/lang/Object;)Ljava/lang/Object;
    //   3638: pop
    //   3639: iinc #7, 1
    //   3642: iload_2
    //   3643: ifne -> 3504
    //   3646: sipush #-24918
    //   3649: sipush #-16043
    //   3652: invokestatic a : (II)Ljava/lang/String;
    //   3655: invokestatic forName : (Ljava/lang/String;)Ljava/lang/Class;
    //   3658: invokevirtual getDeclaredMethods : ()[Ljava/lang/reflect/Method;
    //   3661: astore #5
    //   3663: aload #5
    //   3665: arraylength
    //   3666: istore #6
    //   3668: iconst_0
    //   3669: istore #7
    //   3671: iload #7
    //   3673: iload #6
    //   3675: if_icmpge -> 3812
    //   3678: aload #5
    //   3680: iload #7
    //   3682: aaload
    //   3683: astore #8
    //   3685: aload #8
    //   3687: invokevirtual getParameterTypes : ()[Ljava/lang/Class;
    //   3690: pop
    //   3691: aload #8
    //   3693: invokevirtual getModifiers : ()I
    //   3696: invokestatic isStatic : (I)Z
    //   3699: ifeq -> 3798
    //   3702: aload #8
    //   3704: invokevirtual getParameterTypes : ()[Ljava/lang/Class;
    //   3707: arraylength
    //   3708: iconst_2
    //   3709: if_icmpne -> 3798
    //   3712: goto -> 3719
    //   3715: invokestatic a : (Ljava/lang/Throwable;)Ljava/lang/Throwable;
    //   3718: athrow
    //   3719: aload #8
    //   3721: invokevirtual getReturnType : ()Ljava/lang/Class;
    //   3724: getstatic java/lang/Boolean.TYPE : Ljava/lang/Class;
    //   3727: if_acmpne -> 3798
    //   3730: goto -> 3737
    //   3733: invokestatic a : (Ljava/lang/Throwable;)Ljava/lang/Throwable;
    //   3736: athrow
    //   3737: aload #8
    //   3739: iconst_1
    //   3740: invokevirtual setAccessible : (Z)V
    //   3743: aload #8
    //   3745: aconst_null
    //   3746: iconst_2
    //   3747: anewarray java/lang/Object
    //   3750: dup
    //   3751: iconst_0
    //   3752: aload_0
    //   3753: aastore
    //   3754: dup
    //   3755: iconst_1
    //   3756: aload_1
    //   3757: ifnonnull -> 3775
    //   3760: goto -> 3767
    //   3763: invokestatic a : (Ljava/lang/Throwable;)Ljava/lang/Throwable;
    //   3766: athrow
    //   3767: aload_1
    //   3768: goto -> 3782
    //   3771: invokestatic a : (Ljava/lang/Throwable;)Ljava/lang/Throwable;
    //   3774: athrow
    //   3775: aload_1
    //   3776: checkcast [B
    //   3779: invokevirtual clone : ()Ljava/lang/Object;
    //   3782: aastore
    //   3783: invokevirtual invoke : (Ljava/lang/Object;[Ljava/lang/Object;)Ljava/lang/Object;
    //   3786: checkcast java/lang/Boolean
    //   3789: invokevirtual booleanValue : ()Z
    //   3792: istore #4
    //   3794: iload_2
    //   3795: ifne -> 3812
    //   3798: iinc #7, 1
    //   3801: iload_2
    //   3802: ifne -> 3671
    //   3805: goto -> 3812
    //   3808: invokestatic a : (Ljava/lang/Throwable;)Ljava/lang/Throwable;
    //   3811: athrow
    //   3812: iload_2
    //   3813: ifne -> 4155
    //   3816: sipush #-24911
    //   3819: sipush #27920
    //   3822: invokestatic a : (II)Ljava/lang/String;
    //   3825: iconst_1
    //   3826: ldc burp/Ze_0
    //   3828: invokevirtual getClassLoader : ()Ljava/lang/ClassLoader;
    //   3831: invokestatic forName : (Ljava/lang/String;ZLjava/lang/ClassLoader;)Ljava/lang/Class;
    //   3834: invokevirtual getDeclaredFields : ()[Ljava/lang/reflect/Field;
    //   3837: astore #5
    //   3839: aload #5
    //   3841: arraylength
    //   3842: istore #6
    //   3844: iconst_0
    //   3845: istore #7
    //   3847: iload #7
    //   3849: iload #6
    //   3851: if_icmpge -> 3989
    //   3854: aload #5
    //   3856: iload #7
    //   3858: aaload
    //   3859: astore #8
    //   3861: aload #8
    //   3863: invokevirtual getModifiers : ()I
    //   3866: invokestatic isStatic : (I)Z
    //   3869: ifne -> 3879
    //   3872: goto -> 3982
    //   3875: invokestatic a : (Ljava/lang/Throwable;)Ljava/lang/Throwable;
    //   3878: athrow
    //   3879: aload #8
    //   3881: invokevirtual getType : ()Ljava/lang/Class;
    //   3884: astore #9
    //   3886: aload #9
    //   3888: ifnull -> 3969
    //   3891: aload #9
    //   3893: invokevirtual isPrimitive : ()Z
    //   3896: ifne -> 3969
    //   3899: goto -> 3906
    //   3902: invokestatic a : (Ljava/lang/Throwable;)Ljava/lang/Throwable;
    //   3905: athrow
    //   3906: aload #9
    //   3908: invokevirtual getPackage : ()Ljava/lang/Package;
    //   3911: ifnull -> 3969
    //   3914: goto -> 3921
    //   3917: invokestatic a : (Ljava/lang/Throwable;)Ljava/lang/Throwable;
    //   3920: athrow
    //   3921: aload #9
    //   3923: invokevirtual getPackage : ()Ljava/lang/Package;
    //   3926: invokevirtual getName : ()Ljava/lang/String;
    //   3929: ifnull -> 3969
    //   3932: goto -> 3939
    //   3935: invokestatic a : (Ljava/lang/Throwable;)Ljava/lang/Throwable;
    //   3938: athrow
    //   3939: aload #9
    //   3941: invokevirtual getPackage : ()Ljava/lang/Package;
    //   3944: invokevirtual getName : ()Ljava/lang/String;
    //   3947: sipush #-24908
    //   3950: sipush #10742
    //   3953: invokestatic a : (II)Ljava/lang/String;
    //   3956: invokevirtual startsWith : (Ljava/lang/String;)Z
    //   3959: ifne -> 3969
    //   3962: goto -> 3969
    //   3965: invokestatic a : (Ljava/lang/Throwable;)Ljava/lang/Throwable;
    //   3968: athrow
    //   3969: aload #8
    //   3971: iconst_1
    //   3972: invokevirtual setAccessible : (Z)V
    //   3975: aload #8
    //   3977: aconst_null
    //   3978: invokevirtual get : (Ljava/lang/Object;)Ljava/lang/Object;
    //   3981: pop
    //   3982: iinc #7, 1
    //   3985: iload_2
    //   3986: ifne -> 3847
    //   3989: sipush #-24912
    //   3992: sipush #29726
    //   3995: invokestatic a : (II)Ljava/lang/String;
    //   3998: invokestatic forName : (Ljava/lang/String;)Ljava/lang/Class;
    //   4001: invokevirtual getDeclaredMethods : ()[Ljava/lang/reflect/Method;
    //   4004: astore #5
    //   4006: aload #5
    //   4008: arraylength
    //   4009: istore #6
    //   4011: iconst_0
    //   4012: istore #7
    //   4014: iload #7
    //   4016: iload #6
    //   4018: if_icmpge -> 4155
    //   4021: aload #5
    //   4023: iload #7
    //   4025: aaload
    //   4026: astore #8
    //   4028: aload #8
    //   4030: invokevirtual getParameterTypes : ()[Ljava/lang/Class;
    //   4033: pop
    //   4034: aload #8
    //   4036: invokevirtual getModifiers : ()I
    //   4039: invokestatic isStatic : (I)Z
    //   4042: ifeq -> 4141
    //   4045: aload #8
    //   4047: invokevirtual getParameterTypes : ()[Ljava/lang/Class;
    //   4050: arraylength
    //   4051: iconst_2
    //   4052: if_icmpne -> 4141
    //   4055: goto -> 4062
    //   4058: invokestatic a : (Ljava/lang/Throwable;)Ljava/lang/Throwable;
    //   4061: athrow
    //   4062: aload #8
    //   4064: invokevirtual getReturnType : ()Ljava/lang/Class;
    //   4067: getstatic java/lang/Boolean.TYPE : Ljava/lang/Class;
    //   4070: if_acmpne -> 4141
    //   4073: goto -> 4080
    //   4076: invokestatic a : (Ljava/lang/Throwable;)Ljava/lang/Throwable;
    //   4079: athrow
    //   4080: aload #8
    //   4082: iconst_1
    //   4083: invokevirtual setAccessible : (Z)V
    //   4086: aload #8
    //   4088: aconst_null
    //   4089: iconst_2
    //   4090: anewarray java/lang/Object
    //   4093: dup
    //   4094: iconst_0
    //   4095: aload_0
    //   4096: aastore
    //   4097: dup
    //   4098: iconst_1
    //   4099: aload_1
    //   4100: ifnonnull -> 4118
    //   4103: goto -> 4110
    //   4106: invokestatic a : (Ljava/lang/Throwable;)Ljava/lang/Throwable;
    //   4109: athrow
    //   4110: aload_1
    //   4111: goto -> 4125
    //   4114: invokestatic a : (Ljava/lang/Throwable;)Ljava/lang/Throwable;
    //   4117: athrow
    //   4118: aload_1
    //   4119: checkcast [B
    //   4122: invokevirtual clone : ()Ljava/lang/Object;
    //   4125: aastore
    //   4126: invokevirtual invoke : (Ljava/lang/Object;[Ljava/lang/Object;)Ljava/lang/Object;
    //   4129: checkcast java/lang/Boolean
    //   4132: invokevirtual booleanValue : ()Z
    //   4135: istore #4
    //   4137: iload_2
    //   4138: ifne -> 4155
    //   4141: iinc #7, 1
    //   4144: iload_2
    //   4145: ifne -> 4014
    //   4148: goto -> 4155
    //   4151: invokestatic a : (Ljava/lang/Throwable;)Ljava/lang/Throwable;
    //   4154: athrow
    //   4155: iload #4
    //   4157: ifeq -> 4163
    //   4160: iload #4
    //   4162: ireturn
    //   4163: getstatic burp/Ztod.Zj : Ljava/lang/String;
    //   4166: getstatic burp/Zry7.ZZ : Ljava/lang/Object;
    //   4169: checkcast java/math/BigInteger
    //   4172: invokevirtual intValue : ()I
    //   4175: bipush #32
    //   4177: irem
    //   4178: invokestatic abs : (I)I
    //   4181: invokevirtual charAt : (I)C
    //   4184: getstatic burp/Zsk2.ZE : Ljava/lang/String;
    //   4187: getstatic burp/Zxdh.ZD : Ljava/lang/Object;
    //   4190: checkcast java/math/BigInteger
    //   4193: invokevirtual intValue : ()I
    //   4196: bipush #32
    //   4198: irem
    //   4199: invokestatic abs : (I)I
    //   4202: invokevirtual charAt : (I)C
    //   4205: if_icmple -> 4551
    //   4208: sipush #-24921
    //   4211: sipush #-7371
    //   4214: invokestatic a : (II)Ljava/lang/String;
    //   4217: iconst_1
    //   4218: ldc burp/Zxzp
    //   4220: invokevirtual getClassLoader : ()Ljava/lang/ClassLoader;
    //   4223: invokestatic forName : (Ljava/lang/String;ZLjava/lang/ClassLoader;)Ljava/lang/Class;
    //   4226: invokevirtual getDeclaredFields : ()[Ljava/lang/reflect/Field;
    //   4229: astore #5
    //   4231: aload #5
    //   4233: arraylength
    //   4234: istore #6
    //   4236: iconst_0
    //   4237: istore #7
    //   4239: iload #7
    //   4241: iload #6
    //   4243: if_icmpge -> 4381
    //   4246: aload #5
    //   4248: iload #7
    //   4250: aaload
    //   4251: astore #8
    //   4253: aload #8
    //   4255: invokevirtual getModifiers : ()I
    //   4258: invokestatic isStatic : (I)Z
    //   4261: ifne -> 4271
    //   4264: goto -> 4374
    //   4267: invokestatic a : (Ljava/lang/Throwable;)Ljava/lang/Throwable;
    //   4270: athrow
    //   4271: aload #8
    //   4273: invokevirtual getType : ()Ljava/lang/Class;
    //   4276: astore #9
    //   4278: aload #9
    //   4280: ifnull -> 4361
    //   4283: aload #9
    //   4285: invokevirtual isPrimitive : ()Z
    //   4288: ifne -> 4361
    //   4291: goto -> 4298
    //   4294: invokestatic a : (Ljava/lang/Throwable;)Ljava/lang/Throwable;
    //   4297: athrow
    //   4298: aload #9
    //   4300: invokevirtual getPackage : ()Ljava/lang/Package;
    //   4303: ifnull -> 4361
    //   4306: goto -> 4313
    //   4309: invokestatic a : (Ljava/lang/Throwable;)Ljava/lang/Throwable;
    //   4312: athrow
    //   4313: aload #9
    //   4315: invokevirtual getPackage : ()Ljava/lang/Package;
    //   4318: invokevirtual getName : ()Ljava/lang/String;
    //   4321: ifnull -> 4361
    //   4324: goto -> 4331
    //   4327: invokestatic a : (Ljava/lang/Throwable;)Ljava/lang/Throwable;
    //   4330: athrow
    //   4331: aload #9
    //   4333: invokevirtual getPackage : ()Ljava/lang/Package;
    //   4336: invokevirtual getName : ()Ljava/lang/String;
    //   4339: sipush #-24908
    //   4342: sipush #10742
    //   4345: invokestatic a : (II)Ljava/lang/String;
    //   4348: invokevirtual startsWith : (Ljava/lang/String;)Z
    //   4351: ifne -> 4361
    //   4354: goto -> 4361
    //   4357: invokestatic a : (Ljava/lang/Throwable;)Ljava/lang/Throwable;
    //   4360: athrow
    //   4361: aload #8
    //   4363: iconst_1
    //   4364: invokevirtual setAccessible : (Z)V
    //   4367: aload #8
    //   4369: aconst_null
    //   4370: invokevirtual get : (Ljava/lang/Object;)Ljava/lang/Object;
    //   4373: pop
    //   4374: iinc #7, 1
    //   4377: iload_2
    //   4378: ifne -> 4239
    //   4381: sipush #-24906
    //   4384: sipush #-26486
    //   4387: invokestatic a : (II)Ljava/lang/String;
    //   4390: invokestatic forName : (Ljava/lang/String;)Ljava/lang/Class;
    //   4393: invokevirtual getDeclaredMethods : ()[Ljava/lang/reflect/Method;
    //   4396: astore #5
    //   4398: aload #5
    //   4400: arraylength
    //   4401: istore #6
    //   4403: iconst_0
    //   4404: istore #7
    //   4406: iload #7
    //   4408: iload #6
    //   4410: if_icmpge -> 4547
    //   4413: aload #5
    //   4415: iload #7
    //   4417: aaload
    //   4418: astore #8
    //   4420: aload #8
    //   4422: invokevirtual getParameterTypes : ()[Ljava/lang/Class;
    //   4425: pop
    //   4426: aload #8
    //   4428: invokevirtual getModifiers : ()I
    //   4431: invokestatic isStatic : (I)Z
    //   4434: ifeq -> 4533
    //   4437: aload #8
    //   4439: invokevirtual getParameterTypes : ()[Ljava/lang/Class;
    //   4442: arraylength
    //   4443: iconst_2
    //   4444: if_icmpne -> 4533
    //   4447: goto -> 4454
    //   4450: invokestatic a : (Ljava/lang/Throwable;)Ljava/lang/Throwable;
    //   4453: athrow
    //   4454: aload #8
    //   4456: invokevirtual getReturnType : ()Ljava/lang/Class;
    //   4459: getstatic java/lang/Boolean.TYPE : Ljava/lang/Class;
    //   4462: if_acmpne -> 4533
    //   4465: goto -> 4472
    //   4468: invokestatic a : (Ljava/lang/Throwable;)Ljava/lang/Throwable;
    //   4471: athrow
    //   4472: aload #8
    //   4474: iconst_1
    //   4475: invokevirtual setAccessible : (Z)V
    //   4478: aload #8
    //   4480: aconst_null
    //   4481: iconst_2
    //   4482: anewarray java/lang/Object
    //   4485: dup
    //   4486: iconst_0
    //   4487: aload_0
    //   4488: aastore
    //   4489: dup
    //   4490: iconst_1
    //   4491: aload_1
    //   4492: ifnonnull -> 4510
    //   4495: goto -> 4502
    //   4498: invokestatic a : (Ljava/lang/Throwable;)Ljava/lang/Throwable;
    //   4501: athrow
    //   4502: aload_1
    //   4503: goto -> 4517
    //   4506: invokestatic a : (Ljava/lang/Throwable;)Ljava/lang/Throwable;
    //   4509: athrow
    //   4510: aload_1
    //   4511: checkcast [B
    //   4514: invokevirtual clone : ()Ljava/lang/Object;
    //   4517: aastore
    //   4518: invokevirtual invoke : (Ljava/lang/Object;[Ljava/lang/Object;)Ljava/lang/Object;
    //   4521: checkcast java/lang/Boolean
    //   4524: invokevirtual booleanValue : ()Z
    //   4527: istore #4
    //   4529: iload_2
    //   4530: ifne -> 4547
    //   4533: iinc #7, 1
    //   4536: iload_2
    //   4537: ifne -> 4406
    //   4540: goto -> 4547
    //   4543: invokestatic a : (Ljava/lang/Throwable;)Ljava/lang/Throwable;
    //   4546: athrow
    //   4547: iload_2
    //   4548: ifne -> 4890
    //   4551: sipush #-24898
    //   4554: sipush #-11147
    //   4557: invokestatic a : (II)Ljava/lang/String;
    //   4560: iconst_1
    //   4561: ldc burp/Ze_0
    //   4563: invokevirtual getClassLoader : ()Ljava/lang/ClassLoader;
    //   4566: invokestatic forName : (Ljava/lang/String;ZLjava/lang/ClassLoader;)Ljava/lang/Class;
    //   4569: invokevirtual getDeclaredFields : ()[Ljava/lang/reflect/Field;
    //   4572: astore #5
    //   4574: aload #5
    //   4576: arraylength
    //   4577: istore #6
    //   4579: iconst_0
    //   4580: istore #7
    //   4582: iload #7
    //   4584: iload #6
    //   4586: if_icmpge -> 4724
    //   4589: aload #5
    //   4591: iload #7
    //   4593: aaload
    //   4594: astore #8
    //   4596: aload #8
    //   4598: invokevirtual getModifiers : ()I
    //   4601: invokestatic isStatic : (I)Z
    //   4604: ifne -> 4614
    //   4607: goto -> 4717
    //   4610: invokestatic a : (Ljava/lang/Throwable;)Ljava/lang/Throwable;
    //   4613: athrow
    //   4614: aload #8
    //   4616: invokevirtual getType : ()Ljava/lang/Class;
    //   4619: astore #9
    //   4621: aload #9
    //   4623: ifnull -> 4704
    //   4626: aload #9
    //   4628: invokevirtual isPrimitive : ()Z
    //   4631: ifne -> 4704
    //   4634: goto -> 4641
    //   4637: invokestatic a : (Ljava/lang/Throwable;)Ljava/lang/Throwable;
    //   4640: athrow
    //   4641: aload #9
    //   4643: invokevirtual getPackage : ()Ljava/lang/Package;
    //   4646: ifnull -> 4704
    //   4649: goto -> 4656
    //   4652: invokestatic a : (Ljava/lang/Throwable;)Ljava/lang/Throwable;
    //   4655: athrow
    //   4656: aload #9
    //   4658: invokevirtual getPackage : ()Ljava/lang/Package;
    //   4661: invokevirtual getName : ()Ljava/lang/String;
    //   4664: ifnull -> 4704
    //   4667: goto -> 4674
    //   4670: invokestatic a : (Ljava/lang/Throwable;)Ljava/lang/Throwable;
    //   4673: athrow
    //   4674: aload #9
    //   4676: invokevirtual getPackage : ()Ljava/lang/Package;
    //   4679: invokevirtual getName : ()Ljava/lang/String;
    //   4682: sipush #-24908
    //   4685: sipush #10742
    //   4688: invokestatic a : (II)Ljava/lang/String;
    //   4691: invokevirtual startsWith : (Ljava/lang/String;)Z
    //   4694: ifne -> 4704
    //   4697: goto -> 4704
    //   4700: invokestatic a : (Ljava/lang/Throwable;)Ljava/lang/Throwable;
    //   4703: athrow
    //   4704: aload #8
    //   4706: iconst_1
    //   4707: invokevirtual setAccessible : (Z)V
    //   4710: aload #8
    //   4712: aconst_null
    //   4713: invokevirtual get : (Ljava/lang/Object;)Ljava/lang/Object;
    //   4716: pop
    //   4717: iinc #7, 1
    //   4720: iload_2
    //   4721: ifne -> 4582
    //   4724: sipush #-24907
    //   4727: sipush #19383
    //   4730: invokestatic a : (II)Ljava/lang/String;
    //   4733: invokestatic forName : (Ljava/lang/String;)Ljava/lang/Class;
    //   4736: invokevirtual getDeclaredMethods : ()[Ljava/lang/reflect/Method;
    //   4739: astore #5
    //   4741: aload #5
    //   4743: arraylength
    //   4744: istore #6
    //   4746: iconst_0
    //   4747: istore #7
    //   4749: iload #7
    //   4751: iload #6
    //   4753: if_icmpge -> 4890
    //   4756: aload #5
    //   4758: iload #7
    //   4760: aaload
    //   4761: astore #8
    //   4763: aload #8
    //   4765: invokevirtual getParameterTypes : ()[Ljava/lang/Class;
    //   4768: pop
    //   4769: aload #8
    //   4771: invokevirtual getModifiers : ()I
    //   4774: invokestatic isStatic : (I)Z
    //   4777: ifeq -> 4876
    //   4780: aload #8
    //   4782: invokevirtual getParameterTypes : ()[Ljava/lang/Class;
    //   4785: arraylength
    //   4786: iconst_2
    //   4787: if_icmpne -> 4876
    //   4790: goto -> 4797
    //   4793: invokestatic a : (Ljava/lang/Throwable;)Ljava/lang/Throwable;
    //   4796: athrow
    //   4797: aload #8
    //   4799: invokevirtual getReturnType : ()Ljava/lang/Class;
    //   4802: getstatic java/lang/Boolean.TYPE : Ljava/lang/Class;
    //   4805: if_acmpne -> 4876
    //   4808: goto -> 4815
    //   4811: invokestatic a : (Ljava/lang/Throwable;)Ljava/lang/Throwable;
    //   4814: athrow
    //   4815: aload #8
    //   4817: iconst_1
    //   4818: invokevirtual setAccessible : (Z)V
    //   4821: aload #8
    //   4823: aconst_null
    //   4824: iconst_2
    //   4825: anewarray java/lang/Object
    //   4828: dup
    //   4829: iconst_0
    //   4830: aload_0
    //   4831: aastore
    //   4832: dup
    //   4833: iconst_1
    //   4834: aload_1
    //   4835: ifnonnull -> 4853
    //   4838: goto -> 4845
    //   4841: invokestatic a : (Ljava/lang/Throwable;)Ljava/lang/Throwable;
    //   4844: athrow
    //   4845: aload_1
    //   4846: goto -> 4860
    //   4849: invokestatic a : (Ljava/lang/Throwable;)Ljava/lang/Throwable;
    //   4852: athrow
    //   4853: aload_1
    //   4854: checkcast [B
    //   4857: invokevirtual clone : ()Ljava/lang/Object;
    //   4860: aastore
    //   4861: invokevirtual invoke : (Ljava/lang/Object;[Ljava/lang/Object;)Ljava/lang/Object;
    //   4864: checkcast java/lang/Boolean
    //   4867: invokevirtual booleanValue : ()Z
    //   4870: istore #4
    //   4872: iload_2
    //   4873: ifne -> 4890
    //   4876: iinc #7, 1
    //   4879: iload_2
    //   4880: ifne -> 4749
    //   4883: goto -> 4890
    //   4886: invokestatic a : (Ljava/lang/Throwable;)Ljava/lang/Throwable;
    //   4889: athrow
    //   4890: iload #4
    //   4892: ireturn
    //   4893: astore_3
    //   4894: new java/lang/Exception
    //   4897: dup
    //   4898: aload_3
    //   4899: invokevirtual getMessage : ()Ljava/lang/String;
    //   4902: invokespecial <init> : (Ljava/lang/String;)V
    //   4905: athrow
    // Exception table:
    //   from	to	target	type
    //   4	2692	4893	java/lang/Throwable
    //   283	458	461	java/lang/Throwable
    //   428	495	498	java/lang/Throwable
    //   465	532	535	java/lang/Throwable
    //   502	569	572	java/lang/Throwable
    //   539	606	609	java/lang/Throwable
    //   576	643	646	java/lang/Throwable
    //   613	680	683	java/lang/Throwable
    //   650	717	720	java/lang/Throwable
    //   687	754	757	java/lang/Throwable
    //   724	791	794	java/lang/Throwable
    //   761	828	831	java/lang/Throwable
    //   798	865	868	java/lang/Throwable
    //   835	902	905	java/lang/Throwable
    //   872	939	942	java/lang/Throwable
    //   909	976	979	java/lang/Throwable
    //   946	1013	1016	java/lang/Throwable
    //   983	1050	1053	java/lang/Throwable
    //   1020	1087	1090	java/lang/Throwable
    //   1057	1124	1127	java/lang/Throwable
    //   1094	1161	1164	java/lang/Throwable
    //   1131	1198	1201	java/lang/Throwable
    //   1168	1235	1238	java/lang/Throwable
    //   1205	1272	1275	java/lang/Throwable
    //   1242	1309	1312	java/lang/Throwable
    //   1279	1346	1349	java/lang/Throwable
    //   1316	1383	1386	java/lang/Throwable
    //   1353	1420	1423	java/lang/Throwable
    //   1390	1457	1460	java/lang/Throwable
    //   1427	1494	1497	java/lang/Throwable
    //   1464	1531	1534	java/lang/Throwable
    //   1501	1568	1571	java/lang/Throwable
    //   1538	1601	1604	java/lang/Throwable
    //   1667	1681	1681	java/lang/Throwable
    //   1692	1705	1708	java/lang/Throwable
    //   1697	1720	1723	java/lang/Throwable
    //   1712	1738	1741	java/lang/Throwable
    //   1727	1768	1771	java/lang/Throwable
    //   1833	1860	1863	java/lang/Throwable
    //   1850	1881	1884	java/lang/Throwable
    //   1867	1911	1914	java/lang/Throwable
    //   1888	1922	1922	java/lang/Throwable
    //   1933	1949	1952	java/lang/Throwable
    //   2049	2063	2063	java/lang/Throwable
    //   2074	2087	2090	java/lang/Throwable
    //   2079	2102	2105	java/lang/Throwable
    //   2094	2120	2123	java/lang/Throwable
    //   2109	2150	2153	java/lang/Throwable
    //   2216	2243	2246	java/lang/Throwable
    //   2233	2261	2264	java/lang/Throwable
    //   2250	2291	2294	java/lang/Throwable
    //   2268	2302	2302	java/lang/Throwable
    //   2325	2336	2339	java/lang/Throwable
    //   2391	2405	2405	java/lang/Throwable
    //   2416	2429	2432	java/lang/Throwable
    //   2421	2444	2447	java/lang/Throwable
    //   2436	2462	2465	java/lang/Throwable
    //   2451	2492	2495	java/lang/Throwable
    //   2558	2585	2588	java/lang/Throwable
    //   2575	2603	2606	java/lang/Throwable
    //   2592	2633	2636	java/lang/Throwable
    //   2610	2644	2644	java/lang/Throwable
    //   2667	2678	2681	java/lang/Throwable
    //   2693	3427	4893	java/lang/Throwable
    //   2783	2797	2797	java/lang/Throwable
    //   2808	2821	2824	java/lang/Throwable
    //   2813	2836	2839	java/lang/Throwable
    //   2828	2854	2857	java/lang/Throwable
    //   2843	2884	2887	java/lang/Throwable
    //   2950	2977	2980	java/lang/Throwable
    //   2967	2995	2998	java/lang/Throwable
    //   2984	3025	3028	java/lang/Throwable
    //   3002	3036	3036	java/lang/Throwable
    //   3059	3070	3073	java/lang/Throwable
    //   3126	3140	3140	java/lang/Throwable
    //   3151	3164	3167	java/lang/Throwable
    //   3156	3179	3182	java/lang/Throwable
    //   3171	3197	3200	java/lang/Throwable
    //   3186	3227	3230	java/lang/Throwable
    //   3293	3320	3323	java/lang/Throwable
    //   3310	3338	3341	java/lang/Throwable
    //   3327	3368	3371	java/lang/Throwable
    //   3345	3379	3379	java/lang/Throwable
    //   3402	3413	3416	java/lang/Throwable
    //   3428	4162	4893	java/lang/Throwable
    //   3518	3532	3532	java/lang/Throwable
    //   3543	3556	3559	java/lang/Throwable
    //   3548	3571	3574	java/lang/Throwable
    //   3563	3589	3592	java/lang/Throwable
    //   3578	3619	3622	java/lang/Throwable
    //   3685	3712	3715	java/lang/Throwable
    //   3702	3730	3733	java/lang/Throwable
    //   3719	3760	3763	java/lang/Throwable
    //   3737	3771	3771	java/lang/Throwable
    //   3794	3805	3808	java/lang/Throwable
    //   3861	3875	3875	java/lang/Throwable
    //   3886	3899	3902	java/lang/Throwable
    //   3891	3914	3917	java/lang/Throwable
    //   3906	3932	3935	java/lang/Throwable
    //   3921	3962	3965	java/lang/Throwable
    //   4028	4055	4058	java/lang/Throwable
    //   4045	4073	4076	java/lang/Throwable
    //   4062	4103	4106	java/lang/Throwable
    //   4080	4114	4114	java/lang/Throwable
    //   4137	4148	4151	java/lang/Throwable
    //   4163	4892	4893	java/lang/Throwable
    //   4253	4267	4267	java/lang/Throwable
    //   4278	4291	4294	java/lang/Throwable
    //   4283	4306	4309	java/lang/Throwable
    //   4298	4324	4327	java/lang/Throwable
    //   4313	4354	4357	java/lang/Throwable
    //   4420	4447	4450	java/lang/Throwable
    //   4437	4465	4468	java/lang/Throwable
    //   4454	4495	4498	java/lang/Throwable
    //   4472	4506	4506	java/lang/Throwable
    //   4529	4540	4543	java/lang/Throwable
    //   4596	4610	4610	java/lang/Throwable
    //   4621	4634	4637	java/lang/Throwable
    //   4626	4649	4652	java/lang/Throwable
    //   4641	4667	4670	java/lang/Throwable
    //   4656	4697	4700	java/lang/Throwable
    //   4763	4790	4793	java/lang/Throwable
    //   4780	4808	4811	java/lang/Throwable
    //   4797	4838	4841	java/lang/Throwable
    //   4815	4849	4849	java/lang/Throwable
    //   4872	4883	4886	java/lang/Throwable
  }
  
  static {
    // Byte code:
    //   0: bipush #27
    //   2: anewarray java/lang/String
    //   5: astore #5
    //   7: iconst_0
    //   8: istore_3
    //   9: ldc 'e&SsW$d^fQ,R\\rzi%\\twq[G\\tk]+l8\\t'\\b\\t,1}G\\t|OwgU\\t >^ \\t>++D\\t ~TZ\\tb4MfUq?m]\\t_\\bs$P~,t^;H/V\\tQouWpk14\\tl[7E\\tv__8y\\tDduK\\r\\t(v\\tM9R\\tM\\t*VA\\tQ #j}C;)H>\\fQ)\\b\\nyO/\\tZ38\\tIM;UC_zZU\\f<A]'3n|lHgdHrLx~\\t-fT3sE\\b~J'
    //   11: dup
    //   12: astore_2
    //   13: invokevirtual length : ()I
    //   16: istore #4
    //   18: bipush #32
    //   20: istore_1
    //   21: iconst_m1
    //   22: istore_0
    //   23: bipush #100
    //   25: iinc #0, 1
    //   28: aload_2
    //   29: iload_0
    //   30: dup
    //   31: iload_1
    //   32: iadd
    //   33: invokevirtual substring : (II)Ljava/lang/String;
    //   36: iconst_m1
    //   37: goto -> 142
    //   40: aload #5
    //   42: swap
    //   43: iload_3
    //   44: iinc #3, 1
    //   47: swap
    //   48: aastore
    //   49: iload_0
    //   50: iload_1
    //   51: iadd
    //   52: dup
    //   53: istore_0
    //   54: iload #4
    //   56: if_icmpge -> 68
    //   59: aload_2
    //   60: iload_0
    //   61: invokevirtual charAt : (I)C
    //   64: istore_1
    //   65: goto -> 23
    //   68: ldc 'p/\\t,xve!'
    //   70: dup
    //   71: astore_2
    //   72: invokevirtual length : ()I
    //   75: istore #4
    //   77: bipush #9
    //   79: istore_1
    //   80: iconst_m1
    //   81: istore_0
    //   82: iconst_4
    //   83: iinc #0, 1
    //   86: aload_2
    //   87: iload_0
    //   88: dup
    //   89: iload_1
    //   90: iadd
    //   91: invokevirtual substring : (II)Ljava/lang/String;
    //   94: iconst_0
    //   95: goto -> 142
    //   98: aload #5
    //   100: swap
    //   101: iload_3
    //   102: iinc #3, 1
    //   105: swap
    //   106: aastore
    //   107: iload_0
    //   108: iload_1
    //   109: iadd
    //   110: dup
    //   111: istore_0
    //   112: iload #4
    //   114: if_icmpge -> 126
    //   117: aload_2
    //   118: iload_0
    //   119: invokevirtual charAt : (I)C
    //   122: istore_1
    //   123: goto -> 82
    //   126: aload #5
    //   128: putstatic burp/Zsq5.a : [Ljava/lang/String;
    //   131: bipush #27
    //   133: anewarray java/lang/String
    //   136: putstatic burp/Zsq5.b : [Ljava/lang/String;
    //   139: goto -> 300
    //   142: dup_x2
    //   143: pop
    //   144: invokevirtual toCharArray : ()[C
    //   147: dup_x1
    //   148: arraylength
    //   149: dup_x2
    //   150: pop
    //   151: iconst_0
    //   152: istore #6
    //   154: dup2_x1
    //   155: pop2
    //   156: dup_x2
    //   157: iconst_1
    //   158: if_icmpgt -> 260
    //   161: dup2
    //   162: swap
    //   163: iload #6
    //   165: dup2_x1
    //   166: caload
    //   167: swap
    //   168: iload #6
    //   170: bipush #7
    //   172: irem
    //   173: tableswitch default -> 242, 0 -> 212, 1 -> 217, 2 -> 222, 3 -> 227, 4 -> 232, 5 -> 237
    //   212: bipush #40
    //   214: goto -> 244
    //   217: bipush #62
    //   219: goto -> 244
    //   222: bipush #32
    //   224: goto -> 244
    //   227: bipush #104
    //   229: goto -> 244
    //   232: bipush #74
    //   234: goto -> 244
    //   237: bipush #6
    //   239: goto -> 244
    //   242: bipush #71
    //   244: ixor
    //   245: ixor
    //   246: i2c
    //   247: castore
    //   248: iinc #6, 1
    //   251: dup
    //   252: ifne -> 260
    //   255: dup2
    //   256: dup_x1
    //   257: goto -> 165
    //   260: dup2_x1
    //   261: pop2
    //   262: dup_x2
    //   263: iload #6
    //   265: if_icmpgt -> 161
    //   268: pop
    //   269: new java/lang/String
    //   272: dup_x1
    //   273: swap
    //   274: invokespecial <init> : ([C)V
    //   277: invokevirtual intern : ()Ljava/lang/String;
    //   280: swap
    //   281: pop
    //   282: swap
    //   283: tableswitch default -> 40, 0 -> 98
    //   300: sipush #-24909
    //   303: sipush #432
    //   306: invokestatic a : (II)Ljava/lang/String;
    //   309: putstatic burp/Zsq5.ZA : Ljava/lang/String;
    //   312: new java/math/BigInteger
    //   315: dup
    //   316: sipush #-24917
    //   319: sipush #-951
    //   322: invokestatic a : (II)Ljava/lang/String;
    //   325: invokespecial <init> : (Ljava/lang/String;)V
    //   328: putstatic burp/Zsq5.ZF : Ljava/lang/Object;
    //   331: return
  }
  
  private static Throwable a(Throwable paramThrowable) {
    return paramThrowable;
  }
  
  private static String a(int paramInt1, int paramInt2) {
    int i = (paramInt1 ^ 0xFFFF9EB3) & 0xFFFF;
    if (b[i] == null) {
      char[] arrayOfChar = a[i].toCharArray();
      switch (arrayOfChar[0] & 0xFF) {
        case 0:
        
        case 1:
        
        case 2:
        
        case 3:
        
        case 4:
        
        case 5:
        
        case 6:
        
        case 7:
        
        case 8:
        
        case 9:
        
        case 10:
        
        case 11:
        
        case 12:
        
        case 13:
        
        case 14:
        
        case 15:
        
        case 16:
        
        case 17:
        
        case 18:
        
        case 19:
        
        case 20:
        
        case 21:
        
        case 22:
        
        case 23:
        
        case 24:
        
        case 25:
        
        case 26:
        
        case 27:
        
        case 28:
        
        case 29:
        
        case 30:
        
        case 31:
        
        case 32:
        
        case 33:
        
        case 34:
        
        case 35:
        
        case 36:
        
        case 37:
        
        case 38:
        
        case 39:
        
        case 40:
        
        case 41:
        
        case 42:
        
        case 43:
        
        case 44:
        
        case 45:
        
        case 46:
        
        case 47:
        
        case 48:
        
        case 49:
        
        case 50:
        
        case 51:
        
        case 52:
        
        case 53:
        
        case 54:
        
        case 55:
        
        case 56:
        
        case 57:
        
        case 58:
        
        case 59:
        
        case 60:
        
        case 61:
        
        case 62:
        
        case 63:
        
        case 64:
        
        case 65:
        
        case 66:
        
        case 67:
        
        case 68:
        
        case 69:
        
        case 70:
        
        case 71:
        
        case 72:
        
        case 73:
        
        case 74:
        
        case 75:
        
        case 76:
        
        case 77:
        
        case 78:
        
        case 79:
        
        case 80:
        
        case 81:
        
        case 82:
        
        case 83:
        
        case 84:
        
        case 85:
        
        case 86:
        
        case 87:
        
        case 88:
        
        case 89:
        
        case 90:
        
        case 91:
        
        case 92:
        
        case 93:
        
        case 94:
        
        case 95:
        
        case 96:
        
        case 97:
        
        case 98:
        
        case 99:
        
        case 100:
        
        case 101:
        
        case 102:
        
        case 103:
        
        case 104:
        
        case 105:
        
        case 106:
        
        case 107:
        
        case 108:
        
        case 109:
        
        case 110:
        
        case 111:
        
        case 112:
        
        case 113:
        
        case 114:
        
        case 115:
        
        case 116:
        
        case 117:
        
        case 118:
        
        case 119:
        
        case 120:
        
        case 121:
        
        case 122:
        
        case 123:
        
        case 124:
        
        case 125:
        
        case 126:
        
        case 127:
        
        case 128:
        
        case 129:
        
        case 130:
        
        case 131:
        
        case 132:
        
        case 133:
        
        case 134:
        
        case 135:
        
        case 136:
        
        case 137:
        
        case 138:
        
        case 139:
        
        case 140:
        
        case 141:
        
        case 142:
        
        case 143:
        
        case 144:
        
        case 145:
        
        case 146:
        
        case 147:
        
        case 148:
        
        case 149:
        
        case 150:
        
        case 151:
        
        case 152:
        
        case 153:
        
        case 154:
        
        case 155:
        
        case 156:
        
        case 157:
        
        case 158:
        
        case 159:
        
        case 160:
        
        case 161:
        
        case 162:
        
        case 163:
        
        case 164:
        
        case 165:
        
        case 166:
        
        case 167:
        
        case 168:
        
        case 169:
        
        case 170:
        
        case 171:
        
        case 172:
        
        case 173:
        
        case 174:
        
        case 175:
        
        case 176:
        
        case 177:
        
        case 178:
        
        case 179:
        
        case 180:
        
        case 181:
        
        case 182:
        
        case 183:
        
        case 184:
        
        case 185:
        
        case 186:
        
        case 187:
        
        case 188:
        
        case 189:
        
        case 190:
        
        case 191:
        
        case 192:
        
        case 193:
        
        case 194:
        
        case 195:
        
        case 196:
        
        case 197:
        
        case 198:
        
        case 199:
        
        case 200:
        
        case 201:
        
        case 202:
        
        case 203:
        
        case 204:
        
        case 205:
        
        case 206:
        
        case 207:
        
        case 208:
        
        case 209:
        
        case 210:
        
        case 211:
        
        case 212:
        
        case 213:
        
        case 214:
        
        case 215:
        
        case 216:
        
        case 217:
        
        case 218:
        
        case 219:
        
        case 220:
        
        case 221:
        
        case 222:
        
        case 223:
        
        case 224:
        
        case 225:
        
        case 226:
        
        case 227:
        
        case 228:
        
        case 229:
        
        case 230:
        
        case 231:
        
        case 232:
        
        case 233:
        
        case 234:
        
        case 235:
        
        case 236:
        
        case 237:
        
        case 238:
        
        case 239:
        
        case 240:
        
        case 241:
        
        case 242:
        
        case 243:
        
        case 244:
        
        case 245:
        
        case 246:
        
        case 247:
        
        case 248:
        
        case 249:
        
        case 250:
        
        case 251:
        
        case 252:
        
        case 253:
        
        case 254:
        
        default:
          break;
      } 
      byte b1 = 74;
      int j = (paramInt2 & 0xFF) - b1;
      if (j < 0)
        j += 256; 
      int k = ((paramInt2 & 0xFFFF) >>> 8) - b1;
      if (k < 0)
        k += 256; 
      for (byte b2 = 0; b2 < arrayOfChar.length; b2++) {
        int m = b2 % 2;
        if (m == 0) {
          arrayOfChar[b2] = (char)(arrayOfChar[b2] ^ j);
          j = ((j >>> 3 | j << 5) ^ arrayOfChar[b2]) & 0xFF;
        } else {
          arrayOfChar[b2] = (char)(arrayOfChar[b2] ^ k);
          k = ((k >>> 3 | k << 5) ^ arrayOfChar[b2]) & 0xFF;
        } 
      } 
      b[i] = (new String(arrayOfChar)).intern();
    } 
    return b[i];
  }
}


/* Location:              C:\Program Files\BurpSuitePro\burpsuite_pro.jar!\burp\Zsq5.class
 * Java compiler version: 21 (65.0)
 * JD-Core Version:       1.1.3
 */