package burp;

import java.util.TimerTask;

class Zstd extends TimerTask {
  final Zgv5 Zd;
  
  private Zstd(Zgv5 paramZgv5) {}
  
  public void run() {
    // Byte code:
    //   0: invokestatic Zj : ()Ljava/lang/String;
    //   3: aload_0
    //   4: getfield Zd : Lburp/Zgv5;
    //   7: dup
    //   8: astore_2
    //   9: monitorenter
    //   10: astore_1
    //   11: aload_0
    //   12: getfield Zd : Lburp/Zgv5;
    //   15: getfield Zq : I
    //   18: bipush #23
    //   20: if_icmplt -> 35
    //   23: aload_0
    //   24: getfield Zd : Lburp/Zgv5;
    //   27: iconst_0
    //   28: putfield Zq : I
    //   31: aload_1
    //   32: ifnull -> 48
    //   35: aload_0
    //   36: getfield Zd : Lburp/Zgv5;
    //   39: dup
    //   40: getfield Zq : I
    //   43: iconst_1
    //   44: iadd
    //   45: putfield Zq : I
    //   48: aload_0
    //   49: getfield Zd : Lburp/Zgv5;
    //   52: aload_0
    //   53: getfield Zd : Lburp/Zgv5;
    //   56: getfield Zs : Ljava/util/List;
    //   59: aload_0
    //   60: getfield Zd : Lburp/Zgv5;
    //   63: getfield Zq : I
    //   66: invokevirtual ZV : (Ljava/util/List;I)V
    //   69: aload_0
    //   70: getfield Zd : Lburp/Zgv5;
    //   73: aload_0
    //   74: getfield Zd : Lburp/Zgv5;
    //   77: getfield Zv : Ljava/util/List;
    //   80: aload_0
    //   81: getfield Zd : Lburp/Zgv5;
    //   84: getfield Zq : I
    //   87: invokevirtual ZV : (Ljava/util/List;I)V
    //   90: aload_0
    //   91: getfield Zd : Lburp/Zgv5;
    //   94: aload_0
    //   95: getfield Zd : Lburp/Zgv5;
    //   98: getfield ZQ : Ljava/util/List;
    //   101: aload_0
    //   102: getfield Zd : Lburp/Zgv5;
    //   105: getfield Zq : I
    //   108: invokevirtual ZV : (Ljava/util/List;I)V
    //   111: aload_0
    //   112: getfield Zd : Lburp/Zgv5;
    //   115: aload_0
    //   116: getfield Zd : Lburp/Zgv5;
    //   119: getfield Zf : Ljava/util/List;
    //   122: aload_0
    //   123: getfield Zd : Lburp/Zgv5;
    //   126: getfield Zq : I
    //   129: invokevirtual ZV : (Ljava/util/List;I)V
    //   132: aload_0
    //   133: getfield Zd : Lburp/Zgv5;
    //   136: invokestatic getInstance : ()Ljava/util/Calendar;
    //   139: bipush #11
    //   141: invokevirtual get : (I)I
    //   144: putfield Zp : I
    //   147: aload_2
    //   148: monitorexit
    //   149: goto -> 157
    //   152: astore_3
    //   153: aload_2
    //   154: monitorexit
    //   155: aload_3
    //   156: athrow
    //   157: return
    // Exception table:
    //   from	to	target	type
    //   11	149	152	finally
    //   152	155	152	finally
  }
}


/* Location:              C:\Program Files\BurpSuitePro\burpsuite_pro.jar!\burp\Zstd.class
 * Java compiler version: 21 (65.0)
 * JD-Core Version:       1.1.3
 */