package burp;

import java.awt.Component;
import java.io.File;
import java.io.OutputStream;
import java.net.URL;
import java.util.List;
import java.util.Map;
import net.portswigger.Zm2;

public class Zstj implements IBurpExtenderCallbacks {
  private final IBurpExtenderCallbacks ZB;
  
  private static final String[] a;
  
  private static final String[] b;
  
  public Zstj(IBurpExtenderCallbacks paramIBurpExtenderCallbacks) {
    this.ZB = paramIBurpExtenderCallbacks;
  }
  
  public void setExtensionName(String paramString) {
    Zm2.ZD(a(-11647, -21260));
    this.ZB.setExtensionName(paramString);
  }
  
  public IExtensionHelpers getHelpers() {
    Zm2.ZD(a(-11564, 22236));
    return this.ZB.getHelpers();
  }
  
  public OutputStream getStdout() {
    Zm2.ZD(a(-11540, -4156));
    return this.ZB.getStdout();
  }
  
  public OutputStream getStderr() {
    Zm2.ZD(a(-11578, -16866));
    return this.ZB.getStderr();
  }
  
  public void printOutput(String paramString) {
    Zm2.ZD(a(-11624, -9781));
    this.ZB.printOutput(paramString);
  }
  
  public void printError(String paramString) {
    Zm2.ZD(a(-11577, 13631));
    this.ZB.printError(paramString);
  }
  
  public void registerExtensionStateListener(IExtensionStateListener paramIExtensionStateListener) {
    Zm2.ZD(a(-11554, -25040));
    this.ZB.registerExtensionStateListener(paramIExtensionStateListener);
  }
  
  public List<IExtensionStateListener> getExtensionStateListeners() {
    Zm2.ZD(a(-11556, 27092));
    return this.ZB.getExtensionStateListeners();
  }
  
  public void removeExtensionStateListener(IExtensionStateListener paramIExtensionStateListener) {
    Zm2.ZD(a(-11530, -10830));
    this.ZB.removeExtensionStateListener(paramIExtensionStateListener);
  }
  
  public void registerHttpListener(IHttpListener paramIHttpListener) {
    Zm2.ZD(a(-11534, 23780));
    this.ZB.registerHttpListener(paramIHttpListener);
  }
  
  public List<IHttpListener> getHttpListeners() {
    Zm2.ZD(a(-11622, 27159));
    return this.ZB.getHttpListeners();
  }
  
  public void removeHttpListener(IHttpListener paramIHttpListener) {
    Zm2.ZD(a(-11572, -30343));
    this.ZB.removeHttpListener(paramIHttpListener);
  }
  
  public void registerProxyListener(IProxyListener paramIProxyListener) {
    Zm2.ZD(a(-11543, 23321));
    this.ZB.registerProxyListener(paramIProxyListener);
  }
  
  public List<IProxyListener> getProxyListeners() {
    Zm2.ZD(a(-11574, 2847));
    return this.ZB.getProxyListeners();
  }
  
  public void removeProxyListener(IProxyListener paramIProxyListener) {
    Zm2.ZD(a(-11635, -21721));
    this.ZB.removeProxyListener(paramIProxyListener);
  }
  
  public void registerScannerListener(IScannerListener paramIScannerListener) {
    Zm2.ZD(a(-11565, 13598));
    this.ZB.registerScannerListener(paramIScannerListener);
  }
  
  public List<IScannerListener> getScannerListeners() {
    Zm2.ZD(a(-11522, 2125));
    return this.ZB.getScannerListeners();
  }
  
  public void removeScannerListener(IScannerListener paramIScannerListener) {
    Zm2.ZD(a(-11637, -9737));
    this.ZB.removeScannerListener(paramIScannerListener);
  }
  
  public void registerScopeChangeListener(IScopeChangeListener paramIScopeChangeListener) {
    Zm2.ZD(a(-11529, 20035));
    this.ZB.registerScopeChangeListener(paramIScopeChangeListener);
  }
  
  public List<IScopeChangeListener> getScopeChangeListeners() {
    Zm2.ZD(a(-11626, -14809));
    return this.ZB.getScopeChangeListeners();
  }
  
  public void removeScopeChangeListener(IScopeChangeListener paramIScopeChangeListener) {
    Zm2.ZD(a(-11618, -14754));
    this.ZB.removeScopeChangeListener(paramIScopeChangeListener);
  }
  
  public void registerContextMenuFactory(IContextMenuFactory paramIContextMenuFactory) {
    Zm2.ZD(a(-11537, 32313));
    this.ZB.registerContextMenuFactory(paramIContextMenuFactory);
  }
  
  public List<IContextMenuFactory> getContextMenuFactories() {
    Zm2.ZD(a(-11526, -11553));
    return this.ZB.getContextMenuFactories();
  }
  
  public void removeContextMenuFactory(IContextMenuFactory paramIContextMenuFactory) {
    Zm2.ZD(a(-11632, -17231));
    this.ZB.removeContextMenuFactory(paramIContextMenuFactory);
  }
  
  public void registerMessageEditorTabFactory(IMessageEditorTabFactory paramIMessageEditorTabFactory) {
    Zm2.ZD(a(-11548, -20733));
    this.ZB.registerMessageEditorTabFactory(paramIMessageEditorTabFactory);
  }
  
  public List<IMessageEditorTabFactory> getMessageEditorTabFactories() {
    Zm2.ZD(a(-11597, 30499));
    return this.ZB.getMessageEditorTabFactories();
  }
  
  public void removeMessageEditorTabFactory(IMessageEditorTabFactory paramIMessageEditorTabFactory) {
    Zm2.ZD(a(-11560, 9768));
    this.ZB.removeMessageEditorTabFactory(paramIMessageEditorTabFactory);
  }
  
  public void registerScannerInsertionPointProvider(IScannerInsertionPointProvider paramIScannerInsertionPointProvider) {
    Zm2.ZD(a(-11552, -10370));
    this.ZB.registerScannerInsertionPointProvider(paramIScannerInsertionPointProvider);
  }
  
  public List<IScannerInsertionPointProvider> getScannerInsertionPointProviders() {
    Zm2.ZD(a(-11629, -15409));
    return this.ZB.getScannerInsertionPointProviders();
  }
  
  public void removeScannerInsertionPointProvider(IScannerInsertionPointProvider paramIScannerInsertionPointProvider) {
    Zm2.ZD(a(-11639, -30756));
    this.ZB.removeScannerInsertionPointProvider(paramIScannerInsertionPointProvider);
  }
  
  public void registerScannerCheck(IScannerCheck paramIScannerCheck) {
    Zm2.ZD(a(-11524, -24364));
    this.ZB.registerScannerCheck(paramIScannerCheck);
  }
  
  public List<IScannerCheck> getScannerChecks() {
    Zm2.ZD(a(-11621, 6827));
    return this.ZB.getScannerChecks();
  }
  
  public void removeScannerCheck(IScannerCheck paramIScannerCheck) {
    Zm2.ZD(a(-11539, -19527));
    this.ZB.removeScannerCheck(paramIScannerCheck);
  }
  
  public void registerIntruderPayloadGeneratorFactory(IIntruderPayloadGeneratorFactory paramIIntruderPayloadGeneratorFactory) {
    Zm2.ZD(a(-11553, 22925));
    this.ZB.registerIntruderPayloadGeneratorFactory(paramIIntruderPayloadGeneratorFactory);
  }
  
  public List<IIntruderPayloadGeneratorFactory> getIntruderPayloadGeneratorFactories() {
    Zm2.ZD(a(-11581, -17749));
    return this.ZB.getIntruderPayloadGeneratorFactories();
  }
  
  public void removeIntruderPayloadGeneratorFactory(IIntruderPayloadGeneratorFactory paramIIntruderPayloadGeneratorFactory) {
    Zm2.ZD(a(-11557, 26590));
    this.ZB.removeIntruderPayloadGeneratorFactory(paramIIntruderPayloadGeneratorFactory);
  }
  
  public void registerIntruderPayloadProcessor(IIntruderPayloadProcessor paramIIntruderPayloadProcessor) {
    Zm2.ZD(a(-11528, -29436));
    this.ZB.registerIntruderPayloadProcessor(paramIIntruderPayloadProcessor);
  }
  
  public List<IIntruderPayloadProcessor> getIntruderPayloadProcessors() {
    Zm2.ZD(a(-11648, -5089));
    return this.ZB.getIntruderPayloadProcessors();
  }
  
  public void removeIntruderPayloadProcessor(IIntruderPayloadProcessor paramIIntruderPayloadProcessor) {
    Zm2.ZD(a(-11521, 8201));
    this.ZB.removeIntruderPayloadProcessor(paramIIntruderPayloadProcessor);
  }
  
  public void registerSessionHandlingAction(ISessionHandlingAction paramISessionHandlingAction) {
    Zm2.ZD(a(-11523, -20103));
    this.ZB.registerSessionHandlingAction(paramISessionHandlingAction);
  }
  
  public List<ISessionHandlingAction> getSessionHandlingActions() {
    Zm2.ZD(a(-11617, -18961));
    return this.ZB.getSessionHandlingActions();
  }
  
  public void removeSessionHandlingAction(ISessionHandlingAction paramISessionHandlingAction) {
    Zm2.ZD(a(-11542, -17945));
    this.ZB.removeSessionHandlingAction(paramISessionHandlingAction);
  }
  
  public void unloadExtension() {
    Zm2.ZD(a(-11583, -18240));
    this.ZB.unloadExtension();
  }
  
  public void addSuiteTab(ITab paramITab) {
    Zm2.ZD(a(-11573, -10477));
    this.ZB.addSuiteTab(paramITab);
  }
  
  public void removeSuiteTab(ITab paramITab) {
    Zm2.ZD(a(-11525, -6864));
    this.ZB.removeSuiteTab(paramITab);
  }
  
  public void customizeUiComponent(Component paramComponent) {
    Zm2.ZD(a(-11620, -29826));
    this.ZB.customizeUiComponent(paramComponent);
  }
  
  public IMessageEditor createMessageEditor(IMessageEditorController paramIMessageEditorController, boolean paramBoolean) {
    Zm2.ZD(a(-11644, -8782));
    return this.ZB.createMessageEditor(paramIMessageEditorController, paramBoolean);
  }
  
  public String[] getCommandLineArguments() {
    Zm2.ZD(a(-11619, -440));
    return this.ZB.getCommandLineArguments();
  }
  
  public void saveExtensionSetting(String paramString1, String paramString2) {
    Zm2.ZD(a(-11551, -22902));
    this.ZB.saveExtensionSetting(paramString1, paramString2);
  }
  
  public String loadExtensionSetting(String paramString) {
    Zm2.ZD(a(-11544, 13096));
    return this.ZB.loadExtensionSetting(paramString);
  }
  
  public ITextEditor createTextEditor() {
    Zm2.ZD(a(-11563, -21989));
    return this.ZB.createTextEditor();
  }
  
  public void sendToRepeater(String paramString1, int paramInt, boolean paramBoolean, byte[] paramArrayOfbyte, String paramString2) {
    Zm2.ZD(a(-11643, 16433));
    this.ZB.sendToRepeater(paramString1, paramInt, paramBoolean, paramArrayOfbyte, paramString2);
  }
  
  public void sendToIntruder(String paramString, int paramInt, boolean paramBoolean, byte[] paramArrayOfbyte) {
    Zm2.ZD(a(-11531, -11273));
    this.ZB.sendToIntruder(paramString, paramInt, paramBoolean, paramArrayOfbyte);
  }
  
  public void sendToIntruder(String paramString, int paramInt, boolean paramBoolean, byte[] paramArrayOfbyte, List<int[]> paramList) {
    Zm2.ZD(a(-11571, 13315));
    this.ZB.sendToIntruder(paramString, paramInt, paramBoolean, paramArrayOfbyte, paramList);
  }
  
  public void sendToComparer(byte[] paramArrayOfbyte) {
    Zm2.ZD(a(-11634, -7356));
    this.ZB.sendToComparer(paramArrayOfbyte);
  }
  
  public void sendToSpider(URL paramURL) {
    Zm2.ZD(a(-11558, -15053));
    this.ZB.sendToSpider(paramURL);
  }
  
  public IScanQueueItem doActiveScan(String paramString, int paramInt, boolean paramBoolean, byte[] paramArrayOfbyte) {
    Zm2.ZD(a(-11584, -4573));
    return this.ZB.doActiveScan(paramString, paramInt, paramBoolean, paramArrayOfbyte);
  }
  
  public IScanQueueItem doActiveScan(String paramString, int paramInt, boolean paramBoolean, byte[] paramArrayOfbyte, List<int[]> paramList) {
    Zm2.ZD(a(-11536, -3273));
    return this.ZB.doActiveScan(paramString, paramInt, paramBoolean, paramArrayOfbyte, paramList);
  }
  
  public void doPassiveScan(String paramString, int paramInt, boolean paramBoolean, byte[] paramArrayOfbyte1, byte[] paramArrayOfbyte2) {
    Zm2.ZD(a(-11569, 19905));
    this.ZB.doPassiveScan(paramString, paramInt, paramBoolean, paramArrayOfbyte1, paramArrayOfbyte2);
  }
  
  public IHttpRequestResponse makeHttpRequest(IHttpService paramIHttpService, byte[] paramArrayOfbyte) {
    Zm2.ZD(a(-11628, -12691));
    return this.ZB.makeHttpRequest(paramIHttpService, paramArrayOfbyte);
  }
  
  public IHttpRequestResponse makeHttpRequest(IHttpService paramIHttpService, byte[] paramArrayOfbyte, boolean paramBoolean) {
    Zm2.ZD(a(-11561, -9025));
    return this.ZB.makeHttpRequest(paramIHttpService, paramArrayOfbyte, paramBoolean);
  }
  
  public byte[] makeHttpRequest(String paramString, int paramInt, boolean paramBoolean, byte[] paramArrayOfbyte) {
    Zm2.ZD(a(-11638, 8319));
    return this.ZB.makeHttpRequest(paramString, paramInt, paramBoolean, paramArrayOfbyte);
  }
  
  public byte[] makeHttpRequest(String paramString, int paramInt, boolean paramBoolean1, byte[] paramArrayOfbyte, boolean paramBoolean2) {
    Zbqc[] arrayOfZbqc = Zlv4.ZQ();
    Zm2.ZD(a(-11630, 25672));
    if (Zbqc.Zwu() == null)
      Zlv4.ZN(new Zbqc[2]); 
    return this.ZB.makeHttpRequest(paramString, paramInt, paramBoolean1, paramArrayOfbyte, paramBoolean2);
  }
  
  public byte[] makeHttp2Request(IHttpService paramIHttpService, List<IHttpHeader> paramList, byte[] paramArrayOfbyte) {
    Zm2.ZD(a(-11576, 4541));
    return this.ZB.makeHttp2Request(paramIHttpService, paramList, paramArrayOfbyte);
  }
  
  public byte[] makeHttp2Request(IHttpService paramIHttpService, List<IHttpHeader> paramList, byte[] paramArrayOfbyte, boolean paramBoolean) {
    Zm2.ZD(a(-11579, 29927));
    return this.ZB.makeHttp2Request(paramIHttpService, paramList, paramArrayOfbyte, paramBoolean);
  }
  
  public byte[] makeHttp2Request(IHttpService paramIHttpService, List<IHttpHeader> paramList, byte[] paramArrayOfbyte, boolean paramBoolean, String paramString) {
    Zbqc[] arrayOfZbqc = Zlv4.ZQ();
    Zm2.ZD(a(-11568, 13925));
    if (arrayOfZbqc == null)
      Zbqc.Zr(new Zbqc[1]); 
    return this.ZB.makeHttp2Request(paramIHttpService, paramList, paramArrayOfbyte, paramBoolean, paramString);
  }
  
  public boolean isInScope(URL paramURL) {
    Zm2.ZD(a(-11555, -17219));
    return this.ZB.isInScope(paramURL);
  }
  
  public void includeInScope(URL paramURL) {
    Zm2.ZD(a(-11562, -22407));
    this.ZB.includeInScope(paramURL);
  }
  
  public void excludeFromScope(URL paramURL) {
    Zm2.ZD(a(-11627, -12671));
    this.ZB.excludeFromScope(paramURL);
  }
  
  public void issueAlert(String paramString) {
    Zm2.ZD(a(-11545, 21475));
    this.ZB.issueAlert(paramString);
  }
  
  public IHttpRequestResponse[] getProxyHistory() {
    Zm2.ZD(a(-11535, -4592));
    return this.ZB.getProxyHistory();
  }
  
  public IHttpRequestResponse[] getSiteMap(String paramString) {
    Zm2.ZD(a(-11527, 29270));
    return this.ZB.getSiteMap(paramString);
  }
  
  public IScanIssue[] getScanIssues(String paramString) {
    Zm2.ZD(a(-11646, 43));
    return this.ZB.getScanIssues(paramString);
  }
  
  public void generateScanReport(String paramString, IScanIssue[] paramArrayOfIScanIssue, File paramFile) {
    Zm2.ZD(a(-11532, 14659));
    this.ZB.generateScanReport(paramString, paramArrayOfIScanIssue, paramFile);
  }
  
  public List<ICookie> getCookieJarContents() {
    Zm2.ZD(a(-11533, 20868));
    return this.ZB.getCookieJarContents();
  }
  
  public void updateCookieJar(ICookie paramICookie) {
    Zm2.ZD(a(-11566, 6321));
    this.ZB.updateCookieJar(paramICookie);
  }
  
  public void addToSiteMap(IHttpRequestResponse paramIHttpRequestResponse) {
    Zm2.ZD(a(-11541, -300));
    this.ZB.addToSiteMap(paramIHttpRequestResponse);
  }
  
  public void restoreState(File paramFile) {
    Zm2.ZD(a(-11567, -17120));
    this.ZB.restoreState(paramFile);
  }
  
  public void saveState(File paramFile) {
    Zm2.ZD(a(-11575, -7655));
    this.ZB.saveState(paramFile);
  }
  
  public Map<String, String> saveConfig() {
    Zm2.ZD(a(-11582, -16632));
    return this.ZB.saveConfig();
  }
  
  public void loadConfig(Map<String, String> paramMap) {
    Zm2.ZD(a(-11570, 21210));
    this.ZB.loadConfig(paramMap);
  }
  
  public String saveConfigAsJson(String... paramVarArgs) {
    Zm2.ZD(a(-11631, -30727));
    return this.ZB.saveConfigAsJson(paramVarArgs);
  }
  
  public void loadConfigFromJson(String paramString) {
    Zm2.ZD(a(-11636, -20891));
    this.ZB.loadConfigFromJson(paramString);
  }
  
  public void setProxyInterceptionEnabled(boolean paramBoolean) {
    Zm2.ZD(a(-11580, 2240));
    this.ZB.setProxyInterceptionEnabled(paramBoolean);
  }
  
  public String[] getBurpVersion() {
    Zm2.ZD(a(-11625, 12917));
    return this.ZB.getBurpVersion();
  }
  
  public String getExtensionFilename() {
    Zm2.ZD(a(-11559, -21295));
    return this.ZB.getExtensionFilename();
  }
  
  public boolean isExtensionBapp() {
    Zm2.ZD(a(-11623, -30855));
    return this.ZB.isExtensionBapp();
  }
  
  public void exitSuite(boolean paramBoolean) {
    Zm2.ZD(a(-11547, 22211));
    this.ZB.exitSuite(paramBoolean);
  }
  
  public ITempFile saveToTempFile(byte[] paramArrayOfbyte) {
    Zm2.ZD(a(-11549, -9287));
    return this.ZB.saveToTempFile(paramArrayOfbyte);
  }
  
  public IHttpRequestResponsePersisted saveBuffersToTempFiles(IHttpRequestResponse paramIHttpRequestResponse) {
    Zm2.ZD(a(-11550, 22500));
    return this.ZB.saveBuffersToTempFiles(paramIHttpRequestResponse);
  }
  
  public IHttpRequestResponseWithMarkers applyMarkers(IHttpRequestResponse paramIHttpRequestResponse, List<int[]> paramList1, List<int[]> paramList2) {
    Zm2.ZD(a(-11640, 8960));
    return this.ZB.applyMarkers(paramIHttpRequestResponse, paramList1, paramList2);
  }
  
  public String getToolName(int paramInt) {
    Zm2.ZD(a(-11538, -29913));
    return this.ZB.getToolName(paramInt);
  }
  
  public void addScanIssue(IScanIssue paramIScanIssue) {
    Zm2.ZD(a(-11642, -19113));
    this.ZB.addScanIssue(paramIScanIssue);
  }
  
  public IBurpCollaboratorClientContext createBurpCollaboratorClientContext() {
    Zm2.ZD(a(-11645, 10987));
    return this.ZB.createBurpCollaboratorClientContext();
  }
  
  public String[][] getParameters(byte[] paramArrayOfbyte) {
    Zm2.ZD(a(-11641, -4175));
    return this.ZB.getParameters(paramArrayOfbyte);
  }
  
  public String[] getHeaders(byte[] paramArrayOfbyte) {
    Zm2.ZD(a(-11546, 8882));
    return this.ZB.getHeaders(paramArrayOfbyte);
  }
  
  public void registerMenuItem(String paramString, IMenuItemHandler paramIMenuItemHandler) {
    Zm2.ZD(a(-11633, 2788));
    this.ZB.registerMenuItem(paramString, paramIMenuItemHandler);
  }
  
  static {
    // Byte code:
    //   0: bipush #97
    //   2: anewarray java/lang/String
    //   5: astore #5
    //   7: iconst_0
    //   8: istore_3
    //   9: ldc 'Â•Âœ-Ã„^a|MÂ‘Ãµ>@Â²{bÃ„>Ã’Ã®ÂƒÂ+Â‡eÃ®Â§ÃŸÂŸnÃSÃ´ÃŸÃ…Â'#+2Â‚`p&Ã˜3Â„Ã¯Ã±Ã Ã‡Â«Â™koaYÂ‰Â‘{Â¶1ÂÃ„Ã›Ã­ ÃÃ¬Â—Â¾}KÂÂ²\\n#Â’Â¿Ã›Â–f+{qÃœ"e1ÃŸP0@/Ã‘Â·aSÃ§Â³qÃÂºÃ¿mÂ‰z<Ã¿Ã¼`mÃŸTLÃ«Â—!Ã¾ÃšÂª(aÂ®^ÂŸÃ¢*;Â¸[qÃ¸h4Ã³6Ã¬ÂÂ¿Â½JÃ‹Ã¦ÂŒÃ­Ã¦Â¿Â¶Ã³n39*Ã¾pmPÃ¨Ã4PÃ…Â•1Ã“;ÂƒÃ~ÂŒ1Ã¤UÂ¨gjÃ…Â”ÃªÃ‰Â§BÂ•&bÂÂÂ¾Ã°ÃƒÃ…OÂªÃ”Ã…Â0ÂœÂ«Â·ÂƒdÂ£%IÃˆÂ¶ÂÂ·VÂ€Ã”LÂ–wÂ§ÂÃ€jIdÃ°ÃE%ÃœI0Â¬Â­XÂ]*Ã¬Â°\\t'Â¬O\\n` Ã½Â•ÃÂ¬Â‡Â™FÂ²Ã¼Ã½Ã­ÃµÂ”gÃ€Â·Ã¬Â=ÃªÃ¥[aM{Ã9ÂºÂÂ¸n!Âun'Â¬Ã¹lÂˆÃ¬ÃÃ­Ã†ÃˆÂ«-ÃÃ—Â‘Ã“Ã«(&ÃµÂ»Â‹Â’QÃ¨$Ã Ã´<~Â·PkÃ²Â”Ã©Ã³#"hÂºx$;/Â¯Â‹,#ÃÂÂ¤Â«V<MEÂ²CÃ±Ã¸Ã—\\fVhÂÃ‹_Ã¬kÃ¡fÃ´Ã¢gÂ«Â•{Â‹}fÂ¼ÃÂ#Â”\\rÃ‹Ã€dÃ¡;]yÃ·# sÃ…Â°Ã²?Â‡ÂµÂ«R\\nÃ³ÂˆvÂ¸0oÂ§=Â±Ã‚+Â‹ÃÃ®RÂ¼Wn]Â¬ÂµÃ‰ÂºÃ‡"Â‹pÃš|Â¦Ã»Â†$ Ã»1Â—[E\\nÂ¶\\nÃ–W XhÃ›HÂ·8Ã°4A3Â·Ã¯Â—Ã Â« k\auYÃÂ‘HÃ1AÃƒWÃ£(5ÃŒ Â¿bÂ‡TuÂŒÂ¶Â€Â­gMÃ‚ÂŸÂ¢vÃ\\bÃµÃºÃ>KoÃ¶dÂ¿Â‘Â…Â Â®HÃ™Ã·NÂÃ½Ã\\tÂÃ¸@DÃ­Ã·,:Â‚Y[)Â½3Â™Ã‡ÃŒhÃŠ4Â…Â‰Ãº;HÂ§Ã ÃŠÂÃ»Ã±Ã†Ã–4Ã¡ÃµÂ¢\\rÃ…Ã£'5HÂŠÂ–Ã˜Â³ÂwÂÃ°N77Â•Ã’(i,Ã´Ã—Ã…Ã‡r<IÂ™"19Â¨ÃšÃ¸Ã¡Ã–|YoÂÃ…Â¥EÃ¯Â¨/ÃšÂ³Â¼PÂ· Q ÂµÂÃ—Â¬"Z|GqÂ]Â‡ Â‚JyÂ}IQ@Ã­q\\rTw1 Ã­ÂŸ4Â’Â›Â«Ã„Â†ÃÃœ%Ã®Ã—Ã©QO`Ã€Ã•JÃ¡Â¹CÂ€=Â§Ã†ÃªÂ“]d~skÂ¼uÂÃ±ÂŠ}Â£ÃŠÃ¬;4wgBÃ±Â±Â‰W/Â¶Ã©(Hv=eÃ•Ã¦Â“ Ã»Ã´ Â«Ã¤Â¦aÃ‘Â…NNÂ¯ÂºÂ¥Ã¼|Ã•\\rO[fKÂ®E\\bÂ¶ÃŠ1]Qn p!(Â“ÂšÃ»2bÂ¿Ã»Â–aÂ /qÂ–y1euÂ³ÃµÂ’Ã…Ã³Ã´zyÂ¬Â’&u1*GXÂ¼CÂ‰4=xÃ’|n$Â¿ÃÃ Â‰[Ã“KÂŸÂ¡Âˆ.yÃŸÃ¦ÃC#vMQ KÂÂ”sÂŒ2ÂÂ¸Ã†dÃ¬'Ã¯Â®Ã”\\fÃˆÃšÃª.>@%@[Â£q!Ã©Â“Â¢Ã»5b_Ã»ÂŠa\\r _qÂ˜Â¸1]rÂ³Â‘ÃŠÃ¯o2%Â½Â±Â² Â•-)Ã„8aÂ°M\\bÃµ\\r@Ã”{Â®Ã„Â§Ã’ÃÂƒÃ©+ÃÂŒÂ½Ã Ã„Ã°ÂˆT-Â§XkÂ‚\\fMxnÃÂ‘Â·ÃŒÂƒÃªDÃ¶ÃºÂ”vKÂœ2i=LÃ«8Ã®AÃ]W=xÃ®-Â‘-ÃŠÂÂ¯Â¢&2Â¨Â€ÂŠÂ™0.Ã¿rÂPÂÂµÂ’Â‚Ã¹"umwÃ¿ÂµÃ‰Ã€Ã„oÂƒÃšÂ”Ã’Ã¢cÃºÂµÂŒ8Ã¦tÂ¶ÂŠb1Ã‰cÂÃ‡"ÃÃ©$Â´Ã¥Â‹EÃ†Ã‰Ã†eÃ”RÃ¯9Ã‰ÂŒKÃ›@Â¢ZÂ½ÂŸT,Ã¨Ã»ÃÃ”gÃ¸4(Ã³Â—Ã¡{]rRÃ¹+!9(Ã™pH:Â¢5ÂÂ£Â„|Â¥rÃƒUOÃ›#ÂÂ¶Â€$6Â¤Â¶ Â Â‹ÂªHÃ»Â¾Ã‰ÂŸ5\\rÃ“Ã’NÃ±Â»t^WÂ™Â±Ã—M[Ã¥/Ã„Ã¡A'QÂÂµ:Ã—ZÃ¼Â|<qÃ²]j ?JÃÂÂ‹IÂ‹RÂ³S0j?Â«Â’Ã£Ã€5:Ãª$gÂ›sÃºBÃ¿bÃ¡0Ã¼sÃ¬Z69ÂŒHÂ“RÂ?B`ÂÃ”bJmÂ‡\\nÂ¿!Â“{Ã­Ã¦ÃœÃbÂ-Ã¯Ã¹Ã±ÃKK]Ã‚Ã™Â›(Ã¹puÂŒ_8ÃiÂ€**WÃ´uÃÃ¿ HapÃ®Ã°Â¨m!VÂŠÃ£Âˆ.J!6ÂÂ»HÂ“oÂ—Ã¶yÂ³Ã†jeCÃ™Âš)Â³Ã³Ã©Ã·\Ã£rÃ‹/gÂ¹Ã Ã‰iJÃ¢Q28Â£xÃ¯ÃÂ´p9fg[ÃƒÂ™U+WÃcÃšqÂ¢Â™5-ÃºÂ©Â¡@G<CÃµ"Â—ÂÂ Ã¨Ã¤bÂ©Â¢_>qÂ¦Â¼[ÂŒKÂ±Â¦1Ã˜Ã–Y$+Ã ÂœÂ•Ã²Â¯Â§BÂ•VÃ®Ã†#Â­ÂIBcaÂµ~Ã­*Ã‚Ã”ÂœÂÂÂ¸Â³gÃ´Â½Ã«/Ã™Ã¢Â‰Â¬bj&ÃÂ‚Â…Ã™Ã‘&Ãƒsp5QÂ’Â z-Â–Ã·Â‰NÃ´4Ã©Â\\nÃ‚ÂÂ­Â§zÂ¨Â´d(_ctÃ¥Ã¯Â¡ÂƒÃ¡n`ÃÃ²M-ÂÃÂ‹Â¨pNÃ½Â¼Ãœy\\nÃÃª =<9Â»Â9\\tÃ 2Â«ÃÃªP<~UÂ®Â´Â‰ÂšÃ&ÂŠÃ°ÃºlÂ¤{Ã†4=Ã¹6Ã»Ãa3.\\rPÂ“ÂŠÂ»\XJEpAÃz0Â¿U\\b3XÃ·Â”wÃ³Ã³Â‡Ã‰Â‘'nÃ¨3h9\\tUkÂƒÂ´"ÃÂ¡Ã†Â¯Â¼ÂŠjKÂ•Â™Ã·Ã—Ã¿ZÃŸVÃ‡Â»Ã¾Â²ÃµD>Ã£EÃ%Â°$Â‰\\rPÂ¼Ã³ Â¿O\\tÂœRÂ§Ã¡Â†vÃ¹mÂ¹IHÂÃ€Â±Â§PÃ‰Â…Â©Y)Â«Ã•Ãª3<{~Ã˜Â®Â‰Â¬ÃÃ ÂŠ(ÃºwÃ‡{Âª4Â¥Ã¹Â›Ã·]xÂÂ­JÃ•u$ÂŸ1qÃ¤Â¼%Â´Ã¾Â¾Ã¾.hÂ¤ÃˆnÃ§Â¸Â#ZÃ«Ã¹/d Ã³Â›Â¼:^ÃŸÃ½ZÃš\\nGÂ.Âª)ÃŠÂ¬8ÂˆÃ¾Â¦Â¾ÃŠÂ‹UÂÃŸÂ‚ÃÃ»Â‹5XYÂ´Ã›Ã©NÃ“Â£Ã±nMÂºÃ·7Z)$nÂ£ÂÃ«Â´Ã¥Ez!5y9Â¦FÃ‰1ÂGÃÂ´ÃµhÃ‹~MdÃ›Ã†R{Ã³KÃ¼Ã¼Ã²Â¢\\n7zÂ³ÃÃ¿{Ã¢Â–Ã«Â³c*`Â»y+/<3ÃœÂƒÃ¤Ã¡X;lÂ Ã¼ÂŒÃ¯Â¿\ÃœÂ¿Ã°Â¤'HÃ«Cw9Ã­S)Âœn+Ã†5Ã…Â¬'Â…ÂIdHÂ’U^TÂ¾Ã¹Ã£Â”Ã˜Ã¨Ã‚O\\f!\\nÃ­ÃƒÂÂ\\tXÂ†Â›9`Â‹Ã¥4z(ÃšÂ’0Â­=Â­Ãµ|F*2Â™Ã™ÂºZJÂ²Ã¾7ÃÂº4Â©Ã³FJc;&NÂ›Ã¸Âƒ`EÃ²Ã(Ã‹Â¬NÂ({Â,AÃ NÂ©ÂŒ4Â³Â›Ã©Ãº\BrÃ¿/Ã¡Â¹0Ã‰sJZÃ¢9Â“8Â—xcÃ‹kgfÃ®Â§NÃšÂŒÂÂ€)nÃ•,HÂ€Ã›8Ã·Ã¥Â¶Zv+Âª]ÃœÃŠÂ†Â guÃ²Ã²RÂ ?gÃ“G\\bÂ¢(ÂWÃª"pÂ€\\t*Ãƒ.Ã­Ã¹#2Ã‘A=^ÃŒ%Â€ÂÂZÂVÃ«}Â±ÃŸ:2Ã“rÃ‘<pÂ®Ã—Â‡Â¡O#Â¥w<ÃªÂ .Ã¶-Ã·-Ã¸<Â–Ã¦Ã%NÃ…Ã—Ã¤Ã¶bÂ«?ALZÃƒbÂ¡o'Â–EÂÂ­AÂªkÃ±Â³Â©*ÃŒ(Ã›vÂ™&Ã¿Â–Ã§+Ãˆ\Â†Â±]ÃÂ˜ÂOÂ¿Â‚Â‘dÂ™Ã¾yÃ¶Ã¶ÂŒÂ…uÃ‹5Ã£9Â–Â¿Â·Â‡X}\\rÂ­Ã‚T3Â‡<Ãš=Ã’Ã†G!_EÃµÃ´Â²`#PDxÃ‚&ÂÂ–k7wÂ†Ã©Ã6Ã›Â­Ã®Â‰C<ÃÃœÃŠ.YÂ„Ã¥OÃ˜\\tÂ­Â¨ÃÂ¯Â¹Â·fC\\tÃ‡ÂŠÂ“!Â¢Â¢Ã‹ÃÂ¦Ãºc>rÂ›BÂ=Ã‚Â“Ã³ 4)_wÂ°Ã¿Ã£xÃˆÃ™ÂŸYÂ„!))ÂºÂ¬6Âˆ?Â¦Â†ÃŠÂŒUoÃŸÂÃxÂ‹EXqYuÃ›Ã‘NÃŸÂ©ÃµÃ«Ã³ Ãº9Ã€Â®yÃˆÃ–Â®Â»Ã‹+uÂ›Ã› OÂ«Â›?Z>ÂœÃ‘Ã±PYÃ¢ÂŠt?6ÂŠÃHÂ¸Ã®5Â¼Â¸Ã‹Â‡ÂƒÃ¶Ã›Â¬1Â¼Ã¿Ã…Â¤]Ã«:Â¹@)'wQÂ«x|Â­Â°Ã’Ã¶9Ã›Ãœ'7Â’Â‰Ã¢Ã²Â´Â»Â§#\\f]\\bÃŠÂ 4uÂ˜Ã²Â Â–gÃ¦GÂ®Â¢Ã¼ÂÃÃªO#\\nÂ¼94Â¿A'U(Ã2Â§k)\\f8xÂ°n\\bÂ‘\\rÃŒÃ”ÃªÂ®Ã¶Â§Â”ÃKÃ©2Ã˜9Â€Ã¥YuÂ³ÂˆÃaÂ©Â¡1Âno.FÂ»i'EÃ½Â½Â…Â³,ÃlDÃ©ÂÃ„Ã¹ÂcÃŸÂ’Â!Ã¥ÂÃÂ»Ã°Â®LÂlÂ®Â„<Â›Â…42=Â“Ã¯Ã‡ÂºK+Ã«Ã‡+ÃŒÂ£Ã½Â¡Â¢ÃÃ£Ã˜bG@}Â±Â›ÂÃ¹\\tÃ¦sÂ‡Â•Â…Ã¸2Ã¨Ã¸Ã·Â‡Â›Â€ÃÂÂ¿Â»Â $kÂ‰1Â¡ÂšÂ«ÃšF{Ã±Â2M3ÃšRÃ°8T.SÂ—1YsÃ¯iÃ£&~Â¿VÃ–Ãƒ2Â‰qÃº{Â±,Ã½LÃ˜AÂ±Ã„2"<(ÂŒbÂŒÂµ&Ã—ÃšÂ¦W*ÂŸ6Ã‡mÂŠÃ§x%]Ã¿[Â€^Ã©Â¡Â¢Â©DbÃ„)*PÃšÂƒ:mÂ¾Â¶]ÂŠÂ§Â¯ÂÂ†{Ã²%w}Â¼Ã´rÃ¡Ã•Ã¾Ã³Ã¦Ã¢uÃ·Ã©Ã‡Ã‚Â†ÂŸ5 Ã¦Â½C>\\tÃšÃ˜Ã¬zÂƒ|ÂœÃºÃ kÂ·Â¼ÃŠNÂ’Â‘-[Â‘Ã”Â8E7Â©Â‡(\\tÂ²@HTtÃ•Ã½ÂÂ£Ãˆ]Ã€Ã¹CÃÃŒÃ¿ÃµÃ­ÂŠÃ¹ÂµÂ’Â‹Ã§Â”Â°\\rÃ§t 1Â¹;ÃÃ°ÃÃ Ã1Ã“Ã˜?,j_Ã„ÂŠÂ…Â¨tÃ¾Ã’Ã“Â¤Ã§Ã•WÃˆÂ 0ÃTÃ¢p'oÂ¨\Â†ÃÃÃ Ã‹:6ÂœÃ± hÂ»*Â¸o'Ã¦UÂ‚Â·Â©AT6Ã–ÃŠ$,Ã·Â±UDÃ Â¡Ã…fÃ£(Â¤Â¬Â$ÃÂ¿Â¾Â–ÃÃŸb/Ã¥Â˜#ÂšNY~JÃ‘6\Â³Ã¸BÂ´:ÃœnBÂŸYabÃ¥Ã„Â,.'Â¸w^Ã»Â°\\tÂ—d1Ã†ÃŒÂ¡Â¨%6Â›YÃºJBÂ°Ã¿wÃ¡Â²0Â¨sfZg9Â¦\\rÂ“ÃºÂ‚ eÃ«Ãœ+CÂ…Â‚Â”Â8Â^.<Ã¯tbÂ“ÂµÃ…Ã—Â¦Â¦Ã˜*n6Ã¹mMÃ§Â€%BÃ¿Â¸Â€"Ã®"Â¥HÃ™Ã…PÂ–Ã¾Ã–jÂ—ÂÃ—V@SÃ©'JÃ¯Ã–tÂ»Â“ÂÃ…Â°Â¦JÃ˜Â·nÂ…Ã¹M)Â€Ã¼BÃ„ÂºÃº7 cÂ¯Â¡Ã‘~Ãº\\fÃ’Â¤Â¯Â‚.Ãª{Ã‚Ã¦9ÃÃÂÂºÃ¯Ã±ÂŸKÂ€]Â»Ã™=~Â”Ã¸Ã©~q~Â½Â‰Â·h' Â§/ÂµVÃµ.~Ã£ÂÂ¬'4Ã—sBsÂ±Ã™W%Â¶Â¨(`v8euÃ¦Â‡Â¢Ã»Â¤ Â¡Ã¾RÂ©XÂœ<ÂˆiÂºM"ÂÃ‰'Â½Â¸(ÂdÃunÃÃ“Â¥vJÂ»:CÃ¬Ã—j#?Â˜WÃ¶Â›Ã…ÂŠÂ„Â·Ã¬Â¢Ã®ÂœÂ†Ã˜&I+Â¶Ã¬Â·Â€Â§Â€ÃªLQw_ÂÃŸÂ‰IÃ°QEÃ”ÃQ9LnSÃ¶Ã’ÂeÃ¾Â¥h"Ã±Â³Â¡Ã¿UÃ¢SÃ«c=`YyXÂ ^3ÂKÃ­_r)Â²}\\fÃªÃ¯0Â’,Ã\\fÃ˜ÂœÃ¢$=ÂšÃ»_ÂÂCÃ§ÃƒÂ2Ã¸ÂŸMÂ¨YjÂ³Â£Â½Â¼4w(Ã“ Ã…tÃ½Ã‰Â¢Ã¿:#Â‚Ã±0Ã®fBE)ÂµÃœÃº>Ã‹Â\\fÂ ÂµÂ¿Ã„Â½Â±ndÂ–iÂ­Â¶wÂŸ'kÃ„ÃŠ-ÃšgÃ”Ã•aoÂÂ²iÃŸÃ‡ÂM.Â€_Â™ÂŠ.Â¨rtPÃ’Â¤ÂµÃ§Â‚W"Â mÃÃ¿Ã¢#Ã”ÂŠÃ°9Â‚\\fbj2ÃˆqÃˆÃª4DUÃµÂ‹+Ãš_Ã„bÃ¹QÃ†ÂÂ¹Â­kÂ¹Â“B|Â‹Ã½;Â–Â¾Â€ÂŒÃ¤Ã¾*Ãˆ;ÂWÃ @Ã˜K\Â»Ã•Â­9Â‡Â´:SÃ¢ÃµÃ•ÃŸÂ§C!vxÃ‚Ã±-MÂ‘@\\n!Â˜vH:aÃ§Â¾Â¤Â¢\\n5ZH"Â”NÃ !$8Ã¢V^ÃºQyQ+Ã¤Ã¸nÂÃ´P$Â†#OÃ­ÂˆÂ Ã¨Â£|jÃ“AÂ„]Ã£ÂŸÃ—ÂÂ°ÃqÂ¢Ã+Ã®Â›Â»e.ÂÂ½1'Ã¬Ã”!ÃXÃšÂ®Â Â° Â½vÃ½Ã§fÂ®Â—1ÂÂ…YÃÂœÃ˜ÂPÂ±Ã£aÃL`3Â‡8oÂÂŒÃŒh.lÃ›Ã‘wÃ„Â›Ã«GÃ–ÂšÂzÃ‹"S;_ÂƒÂ€JÂ²LÃ¿Ã½Ã™SkÃÂ¥r6Â¬rÃ“Â›lÃ…S5+$$Ã˜jÂ„Ã„Ã±Â…Ã‡Â™Ã¾oÃ“Ã•Â‰Ãˆ{0Â¶TÂzÃz$+Â‚:Â‹ÂÂ–Ã·#ÃPÃ¢Â¥UÃ•Â´Ã¦Âš"&7Ã°MlÃ£Â¤Â¥Ã†Ã¯.Âƒ&Â¯Â°ÂƒÃ¾Â¡8G%Ã‚Â¥Ã‡=Â™ÂºÃŠÃ 8[LÂ•Ã¼ÃÂ«Â“8Ã‰ÃkÂ€Â‰oÂˆ$-ÃœÃˆ;Â­aN*XÃ¿Â”vÃ³Ã“Â‡ÃÂ‘Â§nÃ¸3jy\\t]kÂ‚Â´ÃÂ´Ã‘6Â„fTÃªÃ¬-Â… Â¶Â¹Ã±Bhz,Â°.Â‰LPÂ”Ã³%ÂºÂ¿[\\tRÃ·Ã¡ÂŒvÂ¸EÂ¹MH2Ã‹Â°y6Â†mÂ—Â”\\rd~Ã‹5eÃ.&Ã¨9Â‚Â®1ÃˆÃŸÂ®ÂšÃ‹uÃ›ÂOÂ¹Â›}ZvÂ•Ã™Ã‰ZuÃº=Â§z%BÃ§\'Â¼: Ã§Â›uÂ³Â»Ã&ÂÃˆ-lÃ–Â¹qEdÂUbÃ±Â©AÂ®ÃªÂœÂ”Â²ÃˆÃ½^Â†4#^Â†Ã‡Ã›Âº Â±Â ÃµQÂ ÂªÂ‘BÂ½kÂ¸Â„#^*ÂªXÂ¬Â¼Ã´Â‰Ã‚=Â¦Ã’Â§n_Â¿Â¡ÃÃ­Â‰Ã¦Ã‡Â¶Â Â–gÃ;Jw\\f'7<oÃ¦Ã°%Â©Ã…+Ã¤ibX??LÂ•ÃƒÂ›Â¡!oÃÂ’Â©Â–2ÃŒMÂ›ÃœÃ u_j7Ã‚Â€%Ã¡0Â£ÂÃ¬[*\\n[g]Â™Ã˜Â°Â’\{R=C]Ã‘b2Ã¥Â¨Ã›Â¢CÂ‘Â›4N*Â‚~ÃFÂ˜Ã•Ãª\\r<Â¿Ã›Ã»Â…\\nÃƒuÃ“Ãœ0Â²ÃŸÂ ek7Â¯Â¯<nÂ¶\\tXÂ¾ÃÃ†<b\\tl'
    //   11: dup
    //   12: astore_2
    //   13: invokevirtual length : ()I
    //   16: istore #4
    //   18: bipush #46
    //   20: istore_1
    //   21: iconst_m1
    //   22: istore_0
    //   23: bipush #65
    //   25: iinc #0, 1
    //   28: aload_2
    //   29: iload_0
    //   30: dup
    //   31: iload_1
    //   32: iadd
    //   33: invokevirtual substring : (II)Ljava/lang/String;
    //   36: iconst_m1
    //   37: goto -> 143
    //   40: aload #5
    //   42: swap
    //   43: iload_3
    //   44: iinc #3, 1
    //   47: swap
    //   48: aastore
    //   49: iload_0
    //   50: iload_1
    //   51: iadd
    //   52: dup
    //   53: istore_0
    //   54: iload #4
    //   56: if_icmpge -> 68
    //   59: aload_2
    //   60: iload_0
    //   61: invokevirtual charAt : (I)C
    //   64: istore_1
    //   65: goto -> 23
    //   68: ldc 'Ã’YM*@Ãy%Ã†2\\fÃ‚Ã·Â¥\\bÂƒÃ»Â²Ã3SÂ›Â¨yl3'Ã•kTÃ£ÃÃ–s@Â3[ÃŸ|ÃºfÃŠÂ½f^ZÃÂ•I<\\n}Âƒ!Ã·\\tÃI3'}Ã§Ã…ÃbÃ¹+Â”V#Ã‰Â”Ã–Ã’Ã¸>Âƒ8Â¼'
    //   70: dup
    //   71: astore_2
    //   72: invokevirtual length : ()I
    //   75: istore #4
    //   77: bipush #41
    //   79: istore_1
    //   80: iconst_m1
    //   81: istore_0
    //   82: bipush #108
    //   84: iinc #0, 1
    //   87: aload_2
    //   88: iload_0
    //   89: dup
    //   90: iload_1
    //   91: iadd
    //   92: invokevirtual substring : (II)Ljava/lang/String;
    //   95: iconst_0
    //   96: goto -> 143
    //   99: aload #5
    //   101: swap
    //   102: iload_3
    //   103: iinc #3, 1
    //   106: swap
    //   107: aastore
    //   108: iload_0
    //   109: iload_1
    //   110: iadd
    //   111: dup
    //   112: istore_0
    //   113: iload #4
    //   115: if_icmpge -> 127
    //   118: aload_2
    //   119: iload_0
    //   120: invokevirtual charAt : (I)C
    //   123: istore_1
    //   124: goto -> 82
    //   127: aload #5
    //   129: putstatic burp/Zstj.a : [Ljava/lang/String;
    //   132: bipush #97
    //   134: anewarray java/lang/String
    //   137: putstatic burp/Zstj.b : [Ljava/lang/String;
    //   140: goto -> 300
    //   143: dup_x2
    //   144: pop
    //   145: invokevirtual toCharArray : ()[C
    //   148: dup_x1
    //   149: arraylength
    //   150: dup_x2
    //   151: pop
    //   152: iconst_0
    //   153: istore #6
    //   155: dup2_x1
    //   156: pop2
    //   157: dup_x2
    //   158: iconst_1
    //   159: if_icmpgt -> 260
    //   162: dup2
    //   163: swap
    //   164: iload #6
    //   166: dup2_x1
    //   167: caload
    //   168: swap
    //   169: iload #6
    //   171: bipush #7
    //   173: irem
    //   174: tableswitch default -> 242, 0 -> 212, 1 -> 217, 2 -> 222, 3 -> 227, 4 -> 232, 5 -> 237
    //   212: bipush #46
    //   214: goto -> 244
    //   217: bipush #85
    //   219: goto -> 244
    //   222: bipush #38
    //   224: goto -> 244
    //   227: bipush #50
    //   229: goto -> 244
    //   232: bipush #103
    //   234: goto -> 244
    //   237: bipush #75
    //   239: goto -> 244
    //   242: bipush #122
    //   244: ixor
    //   245: ixor
    //   246: i2c
    //   247: castore
    //   248: iinc #6, 1
    //   251: dup
    //   252: ifne -> 260
    //   255: dup2
    //   256: dup_x1
    //   257: goto -> 166
    //   260: dup2_x1
    //   261: pop2
    //   262: dup_x2
    //   263: iload #6
    //   265: if_icmpgt -> 162
    //   268: pop
    //   269: new java/lang/String
    //   272: dup_x1
    //   273: swap
    //   274: invokespecial <init> : ([C)V
    //   277: invokevirtual intern : ()Ljava/lang/String;
    //   280: swap
    //   281: pop
    //   282: swap
    //   283: tableswitch default -> 40, 0 -> 99
    //   300: return
  }
  
  private static String a(int paramInt1, int paramInt2) {
    int i = (paramInt1 ^ 0xFFFFD2D3) & 0xFFFF;
    if (b[i] == null) {
      char[] arrayOfChar = a[i].toCharArray();
      switch (arrayOfChar[0] & 0xFF) {
        case 0:
        
        case 1:
        
        case 2:
        
        case 3:
        
        case 4:
        
        case 5:
        
        case 6:
        
        case 7:
        
        case 8:
        
        case 9:
        
        case 10:
        
        case 11:
        
        case 12:
        
        case 13:
        
        case 14:
        
        case 15:
        
        case 16:
        
        case 17:
        
        case 18:
        
        case 19:
        
        case 20:
        
        case 21:
        
        case 22:
        
        case 23:
        
        case 24:
        
        case 25:
        
        case 26:
        
        case 27:
        
        case 28:
        
        case 29:
        
        case 30:
        
        case 31:
        
        case 32:
        
        case 33:
        
        case 34:
        
        case 35:
        
        case 36:
        
        case 37:
        
        case 38:
        
        case 39:
        
        case 40:
        
        case 41:
        
        case 42:
        
        case 43:
        
        case 44:
        
        case 45:
        
        case 46:
        
        case 47:
        
        case 48:
        
        case 49:
        
        case 50:
        
        case 51:
        
        case 52:
        
        case 53:
        
        case 54:
        
        case 55:
        
        case 56:
        
        case 57:
        
        case 58:
        
        case 59:
        
        case 60:
        
        case 61:
        
        case 62:
        
        case 63:
        
        case 64:
        
        case 65:
        
        case 66:
        
        case 67:
        
        case 68:
        
        case 69:
        
        case 70:
        
        case 71:
        
        case 72:
        
        case 73:
        
        case 74:
        
        case 75:
        
        case 76:
        
        case 77:
        
        case 78:
        
        case 79:
        
        case 80:
        
        case 81:
        
        case 82:
        
        case 83:
        
        case 84:
        
        case 85:
        
        case 86:
        
        case 87:
        
        case 88:
        
        case 89:
        
        case 90:
        
        case 91:
        
        case 92:
        
        case 93:
        
        case 94:
        
        case 95:
        
        case 96:
        
        case 97:
        
        case 98:
        
        case 99:
        
        case 100:
        
        case 101:
        
        case 102:
        
        case 103:
        
        case 104:
        
        case 105:
        
        case 106:
        
        case 107:
        
        case 108:
        
        case 109:
        
        case 110:
        
        case 111:
        
        case 112:
        
        case 113:
        
        case 114:
        
        case 115:
        
        case 116:
        
        case 117:
        
        case 118:
        
        case 119:
        
        case 120:
        
        case 121:
        
        case 122:
        
        case 123:
        
        case 124:
        
        case 125:
        
        case 126:
        
        case 127:
        
        case 128:
        
        case 129:
        
        case 130:
        
        case 131:
        
        case 132:
        
        case 133:
        
        case 134:
        
        case 135:
        
        case 136:
        
        case 137:
        
        case 138:
        
        case 139:
        
        case 140:
        
        case 141:
        
        case 142:
        
        case 143:
        
        case 144:
        
        case 145:
        
        case 146:
        
        case 147:
        
        case 148:
        
        case 149:
        
        case 150:
        
        case 151:
        
        case 152:
        
        case 153:
        
        case 154:
        
        case 155:
        
        case 156:
        
        case 157:
        
        case 158:
        
        case 159:
        
        case 160:
        
        case 161:
        
        case 162:
        
        case 163:
        
        case 164:
        
        case 165:
        
        case 166:
        
        case 167:
        
        case 168:
        
        case 169:
        
        case 170:
        
        case 171:
        
        case 172:
        
        case 173:
        
        case 174:
        
        case 175:
        
        case 176:
        
        case 177:
        
        case 178:
        
        case 179:
        
        case 180:
        
        case 181:
        
        case 182:
        
        case 183:
        
        case 184:
        
        case 185:
        
        case 186:
        
        case 187:
        
        case 188:
        
        case 189:
        
        case 190:
        
        case 191:
        
        case 192:
        
        case 193:
        
        case 194:
        
        case 195:
        
        case 196:
        
        case 197:
        
        case 198:
        
        case 199:
        
        case 200:
        
        case 201:
        
        case 202:
        
        case 203:
        
        case 204:
        
        case 205:
        
        case 206:
        
        case 207:
        
        case 208:
        
        case 209:
        
        case 210:
        
        case 211:
        
        case 212:
        
        case 213:
        
        case 214:
        
        case 215:
        
        case 216:
        
        case 217:
        
        case 218:
        
        case 219:
        
        case 220:
        
        case 221:
        
        case 222:
        
        case 223:
        
        case 224:
        
        case 225:
        
        case 226:
        
        case 227:
        
        case 228:
        
        case 229:
        
        case 230:
        
        case 231:
        
        case 232:
        
        case 233:
        
        case 234:
        
        case 235:
        
        case 236:
        
        case 237:
        
        case 238:
        
        case 239:
        
        case 240:
        
        case 241:
        
        case 242:
        
        case 243:
        
        case 244:
        
        case 245:
        
        case 246:
        
        case 247:
        
        case 248:
        
        case 249:
        
        case 250:
        
        case 251:
        
        case 252:
        
        case 253:
        
        case 254:
        
        default:
          break;
      } 
      byte b1 = 47;
      int j = (paramInt2 & 0xFF) - b1;
      if (j < 0)
        j += 256; 
      int k = ((paramInt2 & 0xFFFF) >>> 8) - b1;
      if (k < 0)
        k += 256; 
      for (byte b2 = 0; b2 < arrayOfChar.length; b2++) {
        int m = b2 % 2;
        if (m == 0) {
          arrayOfChar[b2] = (char)(arrayOfChar[b2] ^ j);
          j = ((j >>> 3 | j << 5) ^ arrayOfChar[b2]) & 0xFF;
        } else {
          arrayOfChar[b2] = (char)(arrayOfChar[b2] ^ k);
          k = ((k >>> 3 | k << 5) ^ arrayOfChar[b2]) & 0xFF;
        } 
      } 
      b[i] = (new String(arrayOfChar)).intern();
    } 
    return b[i];
  }
}


/* Location:              C:\Program Files\BurpSuitePro\burpsuite_pro.jar!\burp\Zstj.class
 * Java compiler version: 21 (65.0)
 * JD-Core Version:       1.1.3
 */