package burp;

import java.math.BigInteger;

class Zstq extends ClassLoader {
  static String ZL;
  
  static Object Zf;
  
  private static final String[] a;
  
  private static final String[] b;
  
  static boolean Zj(Object[] paramArrayOfObject, Object paramObject) throws Throwable {
    // Byte code:
    //   0: invokestatic ZK : ()Z
    //   3: istore_2
    //   4: new java/lang/StringBuilder
    //   7: dup
    //   8: invokespecial <init> : ()V
    //   11: astore_3
    //   12: iconst_0
    //   13: istore #4
    //   15: iload #4
    //   17: bipush #32
    //   19: if_icmpge -> 1355
    //   22: iload #4
    //   24: tableswitch default -> 1348, 0 -> 168, 1 -> 205, 2 -> 242, 3 -> 279, 4 -> 316, 5 -> 353, 6 -> 390, 7 -> 427, 8 -> 464, 9 -> 501, 10 -> 538, 11 -> 575, 12 -> 612, 13 -> 649, 14 -> 686, 15 -> 723, 16 -> 760, 17 -> 797, 18 -> 834, 19 -> 871, 20 -> 908, 21 -> 945, 22 -> 982, 23 -> 1019, 24 -> 1056, 25 -> 1093, 26 -> 1130, 27 -> 1167, 28 -> 1204, 29 -> 1241, 30 -> 1278, 31 -> 1315
    //   168: aload_3
    //   169: getstatic burp/Zbf9.Zp : Ljava/lang/String;
    //   172: getstatic burp/Zlfg.Zv : Ljava/lang/Object;
    //   175: checkcast java/math/BigInteger
    //   178: invokevirtual intValue : ()I
    //   181: bipush #32
    //   183: irem
    //   184: invokestatic abs : (I)I
    //   187: invokevirtual charAt : (I)C
    //   190: invokevirtual append : (C)Ljava/lang/StringBuilder;
    //   193: pop
    //   194: iload_2
    //   195: ifeq -> 1348
    //   198: goto -> 205
    //   201: invokestatic a : (Ljava/lang/Throwable;)Ljava/lang/Throwable;
    //   204: athrow
    //   205: aload_3
    //   206: getstatic burp/Zz5h.Zk : Ljava/lang/String;
    //   209: getstatic burp/Zgk1.ZD : Ljava/lang/Object;
    //   212: checkcast java/math/BigInteger
    //   215: invokevirtual intValue : ()I
    //   218: bipush #32
    //   220: irem
    //   221: invokestatic abs : (I)I
    //   224: invokevirtual charAt : (I)C
    //   227: invokevirtual append : (C)Ljava/lang/StringBuilder;
    //   230: pop
    //   231: iload_2
    //   232: ifeq -> 1348
    //   235: goto -> 242
    //   238: invokestatic a : (Ljava/lang/Throwable;)Ljava/lang/Throwable;
    //   241: athrow
    //   242: aload_3
    //   243: getstatic burp/Zss8.ZD : Ljava/lang/String;
    //   246: getstatic burp/Ztvn.Zl : Ljava/lang/Object;
    //   249: checkcast java/math/BigInteger
    //   252: invokevirtual intValue : ()I
    //   255: bipush #32
    //   257: irem
    //   258: invokestatic abs : (I)I
    //   261: invokevirtual charAt : (I)C
    //   264: invokevirtual append : (C)Ljava/lang/StringBuilder;
    //   267: pop
    //   268: iload_2
    //   269: ifeq -> 1348
    //   272: goto -> 279
    //   275: invokestatic a : (Ljava/lang/Throwable;)Ljava/lang/Throwable;
    //   278: athrow
    //   279: aload_3
    //   280: getstatic burp/Zlqq.Za : Ljava/lang/String;
    //   283: getstatic burp/Zts_.ZH : Ljava/lang/Object;
    //   286: checkcast java/math/BigInteger
    //   289: invokevirtual intValue : ()I
    //   292: bipush #32
    //   294: irem
    //   295: invokestatic abs : (I)I
    //   298: invokevirtual charAt : (I)C
    //   301: invokevirtual append : (C)Ljava/lang/StringBuilder;
    //   304: pop
    //   305: iload_2
    //   306: ifeq -> 1348
    //   309: goto -> 316
    //   312: invokestatic a : (Ljava/lang/Throwable;)Ljava/lang/Throwable;
    //   315: athrow
    //   316: aload_3
    //   317: getstatic burp/Zgz2.ZI : Ljava/lang/String;
    //   320: getstatic burp/Zgz1.ZX : Ljava/lang/Object;
    //   323: checkcast java/math/BigInteger
    //   326: invokevirtual intValue : ()I
    //   329: bipush #32
    //   331: irem
    //   332: invokestatic abs : (I)I
    //   335: invokevirtual charAt : (I)C
    //   338: invokevirtual append : (C)Ljava/lang/StringBuilder;
    //   341: pop
    //   342: iload_2
    //   343: ifeq -> 1348
    //   346: goto -> 353
    //   349: invokestatic a : (Ljava/lang/Throwable;)Ljava/lang/Throwable;
    //   352: athrow
    //   353: aload_3
    //   354: getstatic burp/Zz80.Ze : Ljava/lang/String;
    //   357: getstatic burp/Zrug.Zp : Ljava/lang/Object;
    //   360: checkcast java/math/BigInteger
    //   363: invokevirtual intValue : ()I
    //   366: bipush #32
    //   368: irem
    //   369: invokestatic abs : (I)I
    //   372: invokevirtual charAt : (I)C
    //   375: invokevirtual append : (C)Ljava/lang/StringBuilder;
    //   378: pop
    //   379: iload_2
    //   380: ifeq -> 1348
    //   383: goto -> 390
    //   386: invokestatic a : (Ljava/lang/Throwable;)Ljava/lang/Throwable;
    //   389: athrow
    //   390: aload_3
    //   391: getstatic burp/Zz80.Ze : Ljava/lang/String;
    //   394: getstatic burp/Zrc0.Zz : Ljava/lang/Object;
    //   397: checkcast java/math/BigInteger
    //   400: invokevirtual intValue : ()I
    //   403: bipush #32
    //   405: irem
    //   406: invokestatic abs : (I)I
    //   409: invokevirtual charAt : (I)C
    //   412: invokevirtual append : (C)Ljava/lang/StringBuilder;
    //   415: pop
    //   416: iload_2
    //   417: ifeq -> 1348
    //   420: goto -> 427
    //   423: invokestatic a : (Ljava/lang/Throwable;)Ljava/lang/Throwable;
    //   426: athrow
    //   427: aload_3
    //   428: getstatic burp/Zkup.Zr : Ljava/lang/String;
    //   431: getstatic burp/Zlqy.ZP : Ljava/lang/Object;
    //   434: checkcast java/math/BigInteger
    //   437: invokevirtual intValue : ()I
    //   440: bipush #32
    //   442: irem
    //   443: invokestatic abs : (I)I
    //   446: invokevirtual charAt : (I)C
    //   449: invokevirtual append : (C)Ljava/lang/StringBuilder;
    //   452: pop
    //   453: iload_2
    //   454: ifeq -> 1348
    //   457: goto -> 464
    //   460: invokestatic a : (Ljava/lang/Throwable;)Ljava/lang/Throwable;
    //   463: athrow
    //   464: aload_3
    //   465: getstatic burp/Zge1.Zx : Ljava/lang/String;
    //   468: getstatic burp/Zeoa.ZF : Ljava/lang/Object;
    //   471: checkcast java/math/BigInteger
    //   474: invokevirtual intValue : ()I
    //   477: bipush #32
    //   479: irem
    //   480: invokestatic abs : (I)I
    //   483: invokevirtual charAt : (I)C
    //   486: invokevirtual append : (C)Ljava/lang/StringBuilder;
    //   489: pop
    //   490: iload_2
    //   491: ifeq -> 1348
    //   494: goto -> 501
    //   497: invokestatic a : (Ljava/lang/Throwable;)Ljava/lang/Throwable;
    //   500: athrow
    //   501: aload_3
    //   502: getstatic burp/Zlqy.ZZ : Ljava/lang/String;
    //   505: getstatic burp/Zg_i.ZQ : Ljava/lang/Object;
    //   508: checkcast java/math/BigInteger
    //   511: invokevirtual intValue : ()I
    //   514: bipush #32
    //   516: irem
    //   517: invokestatic abs : (I)I
    //   520: invokevirtual charAt : (I)C
    //   523: invokevirtual append : (C)Ljava/lang/StringBuilder;
    //   526: pop
    //   527: iload_2
    //   528: ifeq -> 1348
    //   531: goto -> 538
    //   534: invokestatic a : (Ljava/lang/Throwable;)Ljava/lang/Throwable;
    //   537: athrow
    //   538: aload_3
    //   539: getstatic burp/Zeyd.Zr : Ljava/lang/String;
    //   542: getstatic burp/Zlhk.ZD : Ljava/lang/Object;
    //   545: checkcast java/math/BigInteger
    //   548: invokevirtual intValue : ()I
    //   551: bipush #32
    //   553: irem
    //   554: invokestatic abs : (I)I
    //   557: invokevirtual charAt : (I)C
    //   560: invokevirtual append : (C)Ljava/lang/StringBuilder;
    //   563: pop
    //   564: iload_2
    //   565: ifeq -> 1348
    //   568: goto -> 575
    //   571: invokestatic a : (Ljava/lang/Throwable;)Ljava/lang/Throwable;
    //   574: athrow
    //   575: aload_3
    //   576: getstatic burp/Zrdo.Zj : Ljava/lang/String;
    //   579: getstatic burp/Zkw.ZY : Ljava/lang/Object;
    //   582: checkcast java/math/BigInteger
    //   585: invokevirtual intValue : ()I
    //   588: bipush #32
    //   590: irem
    //   591: invokestatic abs : (I)I
    //   594: invokevirtual charAt : (I)C
    //   597: invokevirtual append : (C)Ljava/lang/StringBuilder;
    //   600: pop
    //   601: iload_2
    //   602: ifeq -> 1348
    //   605: goto -> 612
    //   608: invokestatic a : (Ljava/lang/Throwable;)Ljava/lang/Throwable;
    //   611: athrow
    //   612: aload_3
    //   613: getstatic burp/Zx0t.Ze : Ljava/lang/String;
    //   616: getstatic burp/Zss8.ZO : Ljava/lang/Object;
    //   619: checkcast java/math/BigInteger
    //   622: invokevirtual intValue : ()I
    //   625: bipush #32
    //   627: irem
    //   628: invokestatic abs : (I)I
    //   631: invokevirtual charAt : (I)C
    //   634: invokevirtual append : (C)Ljava/lang/StringBuilder;
    //   637: pop
    //   638: iload_2
    //   639: ifeq -> 1348
    //   642: goto -> 649
    //   645: invokestatic a : (Ljava/lang/Throwable;)Ljava/lang/Throwable;
    //   648: athrow
    //   649: aload_3
    //   650: getstatic burp/Zluk.ZW : Ljava/lang/String;
    //   653: getstatic burp/Zsji.Zg : Ljava/lang/Object;
    //   656: checkcast java/math/BigInteger
    //   659: invokevirtual intValue : ()I
    //   662: bipush #32
    //   664: irem
    //   665: invokestatic abs : (I)I
    //   668: invokevirtual charAt : (I)C
    //   671: invokevirtual append : (C)Ljava/lang/StringBuilder;
    //   674: pop
    //   675: iload_2
    //   676: ifeq -> 1348
    //   679: goto -> 686
    //   682: invokestatic a : (Ljava/lang/Throwable;)Ljava/lang/Throwable;
    //   685: athrow
    //   686: aload_3
    //   687: getstatic burp/Zm0v.Zd : Ljava/lang/String;
    //   690: getstatic burp/Zgx6.Zo : Ljava/lang/Object;
    //   693: checkcast java/math/BigInteger
    //   696: invokevirtual intValue : ()I
    //   699: bipush #32
    //   701: irem
    //   702: invokestatic abs : (I)I
    //   705: invokevirtual charAt : (I)C
    //   708: invokevirtual append : (C)Ljava/lang/StringBuilder;
    //   711: pop
    //   712: iload_2
    //   713: ifeq -> 1348
    //   716: goto -> 723
    //   719: invokestatic a : (Ljava/lang/Throwable;)Ljava/lang/Throwable;
    //   722: athrow
    //   723: aload_3
    //   724: getstatic burp/Zb9d.Zh : Ljava/lang/String;
    //   727: getstatic burp/Zluk.Zz : Ljava/lang/Object;
    //   730: checkcast java/math/BigInteger
    //   733: invokevirtual intValue : ()I
    //   736: bipush #32
    //   738: irem
    //   739: invokestatic abs : (I)I
    //   742: invokevirtual charAt : (I)C
    //   745: invokevirtual append : (C)Ljava/lang/StringBuilder;
    //   748: pop
    //   749: iload_2
    //   750: ifeq -> 1348
    //   753: goto -> 760
    //   756: invokestatic a : (Ljava/lang/Throwable;)Ljava/lang/Throwable;
    //   759: athrow
    //   760: aload_3
    //   761: getstatic burp/Ze6t.ZR : Ljava/lang/String;
    //   764: getstatic burp/Zxzt.ZY : Ljava/lang/Object;
    //   767: checkcast java/math/BigInteger
    //   770: invokevirtual intValue : ()I
    //   773: bipush #32
    //   775: irem
    //   776: invokestatic abs : (I)I
    //   779: invokevirtual charAt : (I)C
    //   782: invokevirtual append : (C)Ljava/lang/StringBuilder;
    //   785: pop
    //   786: iload_2
    //   787: ifeq -> 1348
    //   790: goto -> 797
    //   793: invokestatic a : (Ljava/lang/Throwable;)Ljava/lang/Throwable;
    //   796: athrow
    //   797: aload_3
    //   798: getstatic burp/Zr_z.ZE : Ljava/lang/String;
    //   801: getstatic burp/Zge1.ZK : Ljava/lang/Object;
    //   804: checkcast java/math/BigInteger
    //   807: invokevirtual intValue : ()I
    //   810: bipush #32
    //   812: irem
    //   813: invokestatic abs : (I)I
    //   816: invokevirtual charAt : (I)C
    //   819: invokevirtual append : (C)Ljava/lang/StringBuilder;
    //   822: pop
    //   823: iload_2
    //   824: ifeq -> 1348
    //   827: goto -> 834
    //   830: invokestatic a : (Ljava/lang/Throwable;)Ljava/lang/Throwable;
    //   833: athrow
    //   834: aload_3
    //   835: getstatic burp/Zrqd.Zk : Ljava/lang/String;
    //   838: getstatic burp/Zxti.ZJ : Ljava/lang/Object;
    //   841: checkcast java/math/BigInteger
    //   844: invokevirtual intValue : ()I
    //   847: bipush #32
    //   849: irem
    //   850: invokestatic abs : (I)I
    //   853: invokevirtual charAt : (I)C
    //   856: invokevirtual append : (C)Ljava/lang/StringBuilder;
    //   859: pop
    //   860: iload_2
    //   861: ifeq -> 1348
    //   864: goto -> 871
    //   867: invokestatic a : (Ljava/lang/Throwable;)Ljava/lang/Throwable;
    //   870: athrow
    //   871: aload_3
    //   872: getstatic burp/Zltp.ZY : Ljava/lang/String;
    //   875: getstatic burp/Zlhk.ZD : Ljava/lang/Object;
    //   878: checkcast java/math/BigInteger
    //   881: invokevirtual intValue : ()I
    //   884: bipush #32
    //   886: irem
    //   887: invokestatic abs : (I)I
    //   890: invokevirtual charAt : (I)C
    //   893: invokevirtual append : (C)Ljava/lang/StringBuilder;
    //   896: pop
    //   897: iload_2
    //   898: ifeq -> 1348
    //   901: goto -> 908
    //   904: invokestatic a : (Ljava/lang/Throwable;)Ljava/lang/Throwable;
    //   907: athrow
    //   908: aload_3
    //   909: getstatic burp/Zm7y.ZL : Ljava/lang/String;
    //   912: getstatic burp/Zgmo.Zo : Ljava/lang/Object;
    //   915: checkcast java/math/BigInteger
    //   918: invokevirtual intValue : ()I
    //   921: bipush #32
    //   923: irem
    //   924: invokestatic abs : (I)I
    //   927: invokevirtual charAt : (I)C
    //   930: invokevirtual append : (C)Ljava/lang/StringBuilder;
    //   933: pop
    //   934: iload_2
    //   935: ifeq -> 1348
    //   938: goto -> 945
    //   941: invokestatic a : (Ljava/lang/Throwable;)Ljava/lang/Throwable;
    //   944: athrow
    //   945: aload_3
    //   946: getstatic burp/Zmou.ZP : Ljava/lang/String;
    //   949: getstatic burp/Zgb9.Zb : Ljava/lang/Object;
    //   952: checkcast java/math/BigInteger
    //   955: invokevirtual intValue : ()I
    //   958: bipush #32
    //   960: irem
    //   961: invokestatic abs : (I)I
    //   964: invokevirtual charAt : (I)C
    //   967: invokevirtual append : (C)Ljava/lang/StringBuilder;
    //   970: pop
    //   971: iload_2
    //   972: ifeq -> 1348
    //   975: goto -> 982
    //   978: invokestatic a : (Ljava/lang/Throwable;)Ljava/lang/Throwable;
    //   981: athrow
    //   982: aload_3
    //   983: getstatic burp/Zkup.Zr : Ljava/lang/String;
    //   986: getstatic burp/Zr_w.ZK : Ljava/lang/Object;
    //   989: checkcast java/math/BigInteger
    //   992: invokevirtual intValue : ()I
    //   995: bipush #32
    //   997: irem
    //   998: invokestatic abs : (I)I
    //   1001: invokevirtual charAt : (I)C
    //   1004: invokevirtual append : (C)Ljava/lang/StringBuilder;
    //   1007: pop
    //   1008: iload_2
    //   1009: ifeq -> 1348
    //   1012: goto -> 1019
    //   1015: invokestatic a : (Ljava/lang/Throwable;)Ljava/lang/Throwable;
    //   1018: athrow
    //   1019: aload_3
    //   1020: getstatic burp/Zk52.ZL : Ljava/lang/String;
    //   1023: getstatic burp/Zk52.Zu : Ljava/lang/Object;
    //   1026: checkcast java/math/BigInteger
    //   1029: invokevirtual intValue : ()I
    //   1032: bipush #32
    //   1034: irem
    //   1035: invokestatic abs : (I)I
    //   1038: invokevirtual charAt : (I)C
    //   1041: invokevirtual append : (C)Ljava/lang/StringBuilder;
    //   1044: pop
    //   1045: iload_2
    //   1046: ifeq -> 1348
    //   1049: goto -> 1056
    //   1052: invokestatic a : (Ljava/lang/Throwable;)Ljava/lang/Throwable;
    //   1055: athrow
    //   1056: aload_3
    //   1057: getstatic burp/Zrdo.Zj : Ljava/lang/String;
    //   1060: getstatic burp/Zzuh.ZV : Ljava/lang/Object;
    //   1063: checkcast java/math/BigInteger
    //   1066: invokevirtual intValue : ()I
    //   1069: bipush #32
    //   1071: irem
    //   1072: invokestatic abs : (I)I
    //   1075: invokevirtual charAt : (I)C
    //   1078: invokevirtual append : (C)Ljava/lang/StringBuilder;
    //   1081: pop
    //   1082: iload_2
    //   1083: ifeq -> 1348
    //   1086: goto -> 1093
    //   1089: invokestatic a : (Ljava/lang/Throwable;)Ljava/lang/Throwable;
    //   1092: athrow
    //   1093: aload_3
    //   1094: getstatic burp/Zsq6.Zm : Ljava/lang/String;
    //   1097: getstatic burp/Zr_z.ZT : Ljava/lang/Object;
    //   1100: checkcast java/math/BigInteger
    //   1103: invokevirtual intValue : ()I
    //   1106: bipush #32
    //   1108: irem
    //   1109: invokestatic abs : (I)I
    //   1112: invokevirtual charAt : (I)C
    //   1115: invokevirtual append : (C)Ljava/lang/StringBuilder;
    //   1118: pop
    //   1119: iload_2
    //   1120: ifeq -> 1348
    //   1123: goto -> 1130
    //   1126: invokestatic a : (Ljava/lang/Throwable;)Ljava/lang/Throwable;
    //   1129: athrow
    //   1130: aload_3
    //   1131: getstatic burp/Zgmo.Zr : Ljava/lang/String;
    //   1134: getstatic burp/Zl55.ZZ : Ljava/lang/Object;
    //   1137: checkcast java/math/BigInteger
    //   1140: invokevirtual intValue : ()I
    //   1143: bipush #32
    //   1145: irem
    //   1146: invokestatic abs : (I)I
    //   1149: invokevirtual charAt : (I)C
    //   1152: invokevirtual append : (C)Ljava/lang/StringBuilder;
    //   1155: pop
    //   1156: iload_2
    //   1157: ifeq -> 1348
    //   1160: goto -> 1167
    //   1163: invokestatic a : (Ljava/lang/Throwable;)Ljava/lang/Throwable;
    //   1166: athrow
    //   1167: aload_3
    //   1168: getstatic burp/Zge1.Zx : Ljava/lang/String;
    //   1171: getstatic burp/Zgh3.ZZ : Ljava/lang/Object;
    //   1174: checkcast java/math/BigInteger
    //   1177: invokevirtual intValue : ()I
    //   1180: bipush #32
    //   1182: irem
    //   1183: invokestatic abs : (I)I
    //   1186: invokevirtual charAt : (I)C
    //   1189: invokevirtual append : (C)Ljava/lang/StringBuilder;
    //   1192: pop
    //   1193: iload_2
    //   1194: ifeq -> 1348
    //   1197: goto -> 1204
    //   1200: invokestatic a : (Ljava/lang/Throwable;)Ljava/lang/Throwable;
    //   1203: athrow
    //   1204: aload_3
    //   1205: getstatic burp/Ztgt.ZQ : Ljava/lang/String;
    //   1208: getstatic burp/Zrug.Zp : Ljava/lang/Object;
    //   1211: checkcast java/math/BigInteger
    //   1214: invokevirtual intValue : ()I
    //   1217: bipush #32
    //   1219: irem
    //   1220: invokestatic abs : (I)I
    //   1223: invokevirtual charAt : (I)C
    //   1226: invokevirtual append : (C)Ljava/lang/StringBuilder;
    //   1229: pop
    //   1230: iload_2
    //   1231: ifeq -> 1348
    //   1234: goto -> 1241
    //   1237: invokestatic a : (Ljava/lang/Throwable;)Ljava/lang/Throwable;
    //   1240: athrow
    //   1241: aload_3
    //   1242: getstatic burp/Zep8.ZC : Ljava/lang/String;
    //   1245: getstatic burp/Zmjw.ZD : Ljava/lang/Object;
    //   1248: checkcast java/math/BigInteger
    //   1251: invokevirtual intValue : ()I
    //   1254: bipush #32
    //   1256: irem
    //   1257: invokestatic abs : (I)I
    //   1260: invokevirtual charAt : (I)C
    //   1263: invokevirtual append : (C)Ljava/lang/StringBuilder;
    //   1266: pop
    //   1267: iload_2
    //   1268: ifeq -> 1348
    //   1271: goto -> 1278
    //   1274: invokestatic a : (Ljava/lang/Throwable;)Ljava/lang/Throwable;
    //   1277: athrow
    //   1278: aload_3
    //   1279: getstatic burp/Zvof.ZR : Ljava/lang/String;
    //   1282: getstatic burp/Zg_y.ZR : Ljava/lang/Object;
    //   1285: checkcast java/math/BigInteger
    //   1288: invokevirtual intValue : ()I
    //   1291: bipush #32
    //   1293: irem
    //   1294: invokestatic abs : (I)I
    //   1297: invokevirtual charAt : (I)C
    //   1300: invokevirtual append : (C)Ljava/lang/StringBuilder;
    //   1303: pop
    //   1304: iload_2
    //   1305: ifeq -> 1348
    //   1308: goto -> 1315
    //   1311: invokestatic a : (Ljava/lang/Throwable;)Ljava/lang/Throwable;
    //   1314: athrow
    //   1315: aload_3
    //   1316: getstatic burp/Zluk.ZW : Ljava/lang/String;
    //   1319: getstatic burp/Zts_.ZH : Ljava/lang/Object;
    //   1322: checkcast java/math/BigInteger
    //   1325: invokevirtual intValue : ()I
    //   1328: bipush #32
    //   1330: irem
    //   1331: invokestatic abs : (I)I
    //   1334: invokevirtual charAt : (I)C
    //   1337: invokevirtual append : (C)Ljava/lang/StringBuilder;
    //   1340: pop
    //   1341: goto -> 1348
    //   1344: invokestatic a : (Ljava/lang/Throwable;)Ljava/lang/Throwable;
    //   1347: athrow
    //   1348: iinc #4, 1
    //   1351: iload_2
    //   1352: ifeq -> 15
    //   1355: aload_3
    //   1356: invokevirtual toString : ()Ljava/lang/String;
    //   1359: putstatic burp/Ztvn.ZU : Ljava/lang/String;
    //   1362: getstatic burp/Zkby.Zv : Ljava/lang/Object;
    //   1365: checkcast java/math/BigInteger
    //   1368: invokevirtual toByteArray : ()[B
    //   1371: astore #4
    //   1373: bipush #32
    //   1375: newarray int
    //   1377: dup
    //   1378: iconst_0
    //   1379: ldc 876216579
    //   1381: iastore
    //   1382: dup
    //   1383: iconst_1
    //   1384: ldc 455999525
    //   1386: iastore
    //   1387: dup
    //   1388: iconst_2
    //   1389: ldc 1043334948
    //   1391: iastore
    //   1392: dup
    //   1393: iconst_3
    //   1394: ldc 439222784
    //   1396: iastore
    //   1397: dup
    //   1398: iconst_4
    //   1399: ldc 372376604
    //   1401: iastore
    //   1402: dup
    //   1403: iconst_5
    //   1404: ldc 707731490
    //   1406: iastore
    //   1407: dup
    //   1408: bipush #6
    //   1410: ldc 389426184
    //   1412: iastore
    //   1413: dup
    //   1414: bipush #7
    //   1416: ldc 973875457
    //   1418: iastore
    //   1419: dup
    //   1420: bipush #8
    //   1422: ldc 389160971
    //   1424: iastore
    //   1425: dup
    //   1426: bipush #9
    //   1428: ldc 907870729
    //   1430: iastore
    //   1431: dup
    //   1432: bipush #10
    //   1434: ldc 121057538
    //   1436: iastore
    //   1437: dup
    //   1438: bipush #11
    //   1440: ldc 840500228
    //   1442: iastore
    //   1443: dup
    //   1444: bipush #12
    //   1446: ldc 254150144
    //   1448: iastore
    //   1449: dup
    //   1450: bipush #13
    //   1452: ldc 924386310
    //   1454: iastore
    //   1455: dup
    //   1456: bipush #14
    //   1458: ldc 187632156
    //   1460: iastore
    //   1461: dup
    //   1462: bipush #15
    //   1464: ldc 874189824
    //   1466: iastore
    //   1467: dup
    //   1468: bipush #16
    //   1470: ldc 655302664
    //   1472: iastore
    //   1473: dup
    //   1474: bipush #17
    //   1476: ldc 890966315
    //   1478: iastore
    //   1479: dup
    //   1480: bipush #18
    //   1482: ldc 722417666
    //   1484: iastore
    //   1485: dup
    //   1486: bipush #19
    //   1488: ldc 1026621720
    //   1490: iastore
    //   1491: dup
    //   1492: bipush #20
    //   1494: ldc 957157408
    //   1496: iastore
    //   1497: dup
    //   1498: bipush #21
    //   1500: ldc 892536332
    //   1502: iastore
    //   1503: dup
    //   1504: bipush #22
    //   1506: ldc 689771012
    //   1508: iastore
    //   1509: dup
    //   1510: bipush #23
    //   1512: ldc 221709344
    //   1514: iastore
    //   1515: dup
    //   1516: bipush #24
    //   1518: ldc 940377620
    //   1520: iastore
    //   1521: dup
    //   1522: bipush #25
    //   1524: ldc 255209728
    //   1526: iastore
    //   1527: dup
    //   1528: bipush #26
    //   1530: ldc 1010368540
    //   1532: iastore
    //   1533: dup
    //   1534: bipush #27
    //   1536: ldc 220604441
    //   1538: iastore
    //   1539: dup
    //   1540: bipush #28
    //   1542: ldc 1008414755
    //   1544: iastore
    //   1545: dup
    //   1546: bipush #29
    //   1548: ldc 187049985
    //   1550: iastore
    //   1551: dup
    //   1552: bipush #30
    //   1554: ldc 943331329
    //   1556: iastore
    //   1557: dup
    //   1558: bipush #31
    //   1560: ldc 170788368
    //   1562: iastore
    //   1563: astore #6
    //   1565: bipush #64
    //   1567: newarray int
    //   1569: dup
    //   1570: iconst_0
    //   1571: ldc 16843776
    //   1573: iastore
    //   1574: dup
    //   1575: iconst_1
    //   1576: iconst_0
    //   1577: iastore
    //   1578: dup
    //   1579: iconst_2
    //   1580: ldc 65536
    //   1582: iastore
    //   1583: dup
    //   1584: iconst_3
    //   1585: ldc 16843780
    //   1587: iastore
    //   1588: dup
    //   1589: iconst_4
    //   1590: ldc 16842756
    //   1592: iastore
    //   1593: dup
    //   1594: iconst_5
    //   1595: ldc 66564
    //   1597: iastore
    //   1598: dup
    //   1599: bipush #6
    //   1601: iconst_4
    //   1602: iastore
    //   1603: dup
    //   1604: bipush #7
    //   1606: ldc 65536
    //   1608: iastore
    //   1609: dup
    //   1610: bipush #8
    //   1612: sipush #1024
    //   1615: iastore
    //   1616: dup
    //   1617: bipush #9
    //   1619: ldc 16843776
    //   1621: iastore
    //   1622: dup
    //   1623: bipush #10
    //   1625: ldc 16843780
    //   1627: iastore
    //   1628: dup
    //   1629: bipush #11
    //   1631: sipush #1024
    //   1634: iastore
    //   1635: dup
    //   1636: bipush #12
    //   1638: ldc 16778244
    //   1640: iastore
    //   1641: dup
    //   1642: bipush #13
    //   1644: ldc 16842756
    //   1646: iastore
    //   1647: dup
    //   1648: bipush #14
    //   1650: ldc 16777216
    //   1652: iastore
    //   1653: dup
    //   1654: bipush #15
    //   1656: iconst_4
    //   1657: iastore
    //   1658: dup
    //   1659: bipush #16
    //   1661: sipush #1028
    //   1664: iastore
    //   1665: dup
    //   1666: bipush #17
    //   1668: ldc 16778240
    //   1670: iastore
    //   1671: dup
    //   1672: bipush #18
    //   1674: ldc 16778240
    //   1676: iastore
    //   1677: dup
    //   1678: bipush #19
    //   1680: ldc 66560
    //   1682: iastore
    //   1683: dup
    //   1684: bipush #20
    //   1686: ldc 66560
    //   1688: iastore
    //   1689: dup
    //   1690: bipush #21
    //   1692: ldc 16842752
    //   1694: iastore
    //   1695: dup
    //   1696: bipush #22
    //   1698: ldc 16842752
    //   1700: iastore
    //   1701: dup
    //   1702: bipush #23
    //   1704: ldc 16778244
    //   1706: iastore
    //   1707: dup
    //   1708: bipush #24
    //   1710: ldc 65540
    //   1712: iastore
    //   1713: dup
    //   1714: bipush #25
    //   1716: ldc 16777220
    //   1718: iastore
    //   1719: dup
    //   1720: bipush #26
    //   1722: ldc 16777220
    //   1724: iastore
    //   1725: dup
    //   1726: bipush #27
    //   1728: ldc 65540
    //   1730: iastore
    //   1731: dup
    //   1732: bipush #28
    //   1734: iconst_0
    //   1735: iastore
    //   1736: dup
    //   1737: bipush #29
    //   1739: sipush #1028
    //   1742: iastore
    //   1743: dup
    //   1744: bipush #30
    //   1746: ldc 66564
    //   1748: iastore
    //   1749: dup
    //   1750: bipush #31
    //   1752: ldc 16777216
    //   1754: iastore
    //   1755: dup
    //   1756: bipush #32
    //   1758: ldc 65536
    //   1760: iastore
    //   1761: dup
    //   1762: bipush #33
    //   1764: ldc 16843780
    //   1766: iastore
    //   1767: dup
    //   1768: bipush #34
    //   1770: iconst_4
    //   1771: iastore
    //   1772: dup
    //   1773: bipush #35
    //   1775: ldc 16842752
    //   1777: iastore
    //   1778: dup
    //   1779: bipush #36
    //   1781: ldc 16843776
    //   1783: iastore
    //   1784: dup
    //   1785: bipush #37
    //   1787: ldc 16777216
    //   1789: iastore
    //   1790: dup
    //   1791: bipush #38
    //   1793: ldc 16777216
    //   1795: iastore
    //   1796: dup
    //   1797: bipush #39
    //   1799: sipush #1024
    //   1802: iastore
    //   1803: dup
    //   1804: bipush #40
    //   1806: ldc 16842756
    //   1808: iastore
    //   1809: dup
    //   1810: bipush #41
    //   1812: ldc 65536
    //   1814: iastore
    //   1815: dup
    //   1816: bipush #42
    //   1818: ldc 66560
    //   1820: iastore
    //   1821: dup
    //   1822: bipush #43
    //   1824: ldc 16777220
    //   1826: iastore
    //   1827: dup
    //   1828: bipush #44
    //   1830: sipush #1024
    //   1833: iastore
    //   1834: dup
    //   1835: bipush #45
    //   1837: iconst_4
    //   1838: iastore
    //   1839: dup
    //   1840: bipush #46
    //   1842: ldc 16778244
    //   1844: iastore
    //   1845: dup
    //   1846: bipush #47
    //   1848: ldc 66564
    //   1850: iastore
    //   1851: dup
    //   1852: bipush #48
    //   1854: ldc 16843780
    //   1856: iastore
    //   1857: dup
    //   1858: bipush #49
    //   1860: ldc 65540
    //   1862: iastore
    //   1863: dup
    //   1864: bipush #50
    //   1866: ldc 16842752
    //   1868: iastore
    //   1869: dup
    //   1870: bipush #51
    //   1872: ldc 16778244
    //   1874: iastore
    //   1875: dup
    //   1876: bipush #52
    //   1878: ldc 16777220
    //   1880: iastore
    //   1881: dup
    //   1882: bipush #53
    //   1884: sipush #1028
    //   1887: iastore
    //   1888: dup
    //   1889: bipush #54
    //   1891: ldc 66564
    //   1893: iastore
    //   1894: dup
    //   1895: bipush #55
    //   1897: ldc 16843776
    //   1899: iastore
    //   1900: dup
    //   1901: bipush #56
    //   1903: sipush #1028
    //   1906: iastore
    //   1907: dup
    //   1908: bipush #57
    //   1910: ldc 16778240
    //   1912: iastore
    //   1913: dup
    //   1914: bipush #58
    //   1916: ldc 16778240
    //   1918: iastore
    //   1919: dup
    //   1920: bipush #59
    //   1922: iconst_0
    //   1923: iastore
    //   1924: dup
    //   1925: bipush #60
    //   1927: ldc 65540
    //   1929: iastore
    //   1930: dup
    //   1931: bipush #61
    //   1933: ldc 66560
    //   1935: iastore
    //   1936: dup
    //   1937: bipush #62
    //   1939: iconst_0
    //   1940: iastore
    //   1941: dup
    //   1942: bipush #63
    //   1944: ldc 16842756
    //   1946: iastore
    //   1947: astore #7
    //   1949: bipush #64
    //   1951: newarray int
    //   1953: dup
    //   1954: iconst_0
    //   1955: ldc -2146402272
    //   1957: iastore
    //   1958: dup
    //   1959: iconst_1
    //   1960: ldc -2147450880
    //   1962: iastore
    //   1963: dup
    //   1964: iconst_2
    //   1965: ldc 32768
    //   1967: iastore
    //   1968: dup
    //   1969: iconst_3
    //   1970: ldc 1081376
    //   1972: iastore
    //   1973: dup
    //   1974: iconst_4
    //   1975: ldc 1048576
    //   1977: iastore
    //   1978: dup
    //   1979: iconst_5
    //   1980: bipush #32
    //   1982: iastore
    //   1983: dup
    //   1984: bipush #6
    //   1986: ldc -2146435040
    //   1988: iastore
    //   1989: dup
    //   1990: bipush #7
    //   1992: ldc -2147450848
    //   1994: iastore
    //   1995: dup
    //   1996: bipush #8
    //   1998: ldc -2147483616
    //   2000: iastore
    //   2001: dup
    //   2002: bipush #9
    //   2004: ldc -2146402272
    //   2006: iastore
    //   2007: dup
    //   2008: bipush #10
    //   2010: ldc -2146402304
    //   2012: iastore
    //   2013: dup
    //   2014: bipush #11
    //   2016: ldc -2147483648
    //   2018: iastore
    //   2019: dup
    //   2020: bipush #12
    //   2022: ldc -2147450880
    //   2024: iastore
    //   2025: dup
    //   2026: bipush #13
    //   2028: ldc 1048576
    //   2030: iastore
    //   2031: dup
    //   2032: bipush #14
    //   2034: bipush #32
    //   2036: iastore
    //   2037: dup
    //   2038: bipush #15
    //   2040: ldc -2146435040
    //   2042: iastore
    //   2043: dup
    //   2044: bipush #16
    //   2046: ldc 1081344
    //   2048: iastore
    //   2049: dup
    //   2050: bipush #17
    //   2052: ldc 1048608
    //   2054: iastore
    //   2055: dup
    //   2056: bipush #18
    //   2058: ldc -2147450848
    //   2060: iastore
    //   2061: dup
    //   2062: bipush #19
    //   2064: iconst_0
    //   2065: iastore
    //   2066: dup
    //   2067: bipush #20
    //   2069: ldc -2147483648
    //   2071: iastore
    //   2072: dup
    //   2073: bipush #21
    //   2075: ldc 32768
    //   2077: iastore
    //   2078: dup
    //   2079: bipush #22
    //   2081: ldc 1081376
    //   2083: iastore
    //   2084: dup
    //   2085: bipush #23
    //   2087: ldc -2146435072
    //   2089: iastore
    //   2090: dup
    //   2091: bipush #24
    //   2093: ldc 1048608
    //   2095: iastore
    //   2096: dup
    //   2097: bipush #25
    //   2099: ldc -2147483616
    //   2101: iastore
    //   2102: dup
    //   2103: bipush #26
    //   2105: iconst_0
    //   2106: iastore
    //   2107: dup
    //   2108: bipush #27
    //   2110: ldc 1081344
    //   2112: iastore
    //   2113: dup
    //   2114: bipush #28
    //   2116: ldc 32800
    //   2118: iastore
    //   2119: dup
    //   2120: bipush #29
    //   2122: ldc -2146402304
    //   2124: iastore
    //   2125: dup
    //   2126: bipush #30
    //   2128: ldc -2146435072
    //   2130: iastore
    //   2131: dup
    //   2132: bipush #31
    //   2134: ldc 32800
    //   2136: iastore
    //   2137: dup
    //   2138: bipush #32
    //   2140: iconst_0
    //   2141: iastore
    //   2142: dup
    //   2143: bipush #33
    //   2145: ldc 1081376
    //   2147: iastore
    //   2148: dup
    //   2149: bipush #34
    //   2151: ldc -2146435040
    //   2153: iastore
    //   2154: dup
    //   2155: bipush #35
    //   2157: ldc 1048576
    //   2159: iastore
    //   2160: dup
    //   2161: bipush #36
    //   2163: ldc -2147450848
    //   2165: iastore
    //   2166: dup
    //   2167: bipush #37
    //   2169: ldc -2146435072
    //   2171: iastore
    //   2172: dup
    //   2173: bipush #38
    //   2175: ldc -2146402304
    //   2177: iastore
    //   2178: dup
    //   2179: bipush #39
    //   2181: ldc 32768
    //   2183: iastore
    //   2184: dup
    //   2185: bipush #40
    //   2187: ldc -2146435072
    //   2189: iastore
    //   2190: dup
    //   2191: bipush #41
    //   2193: ldc -2147450880
    //   2195: iastore
    //   2196: dup
    //   2197: bipush #42
    //   2199: bipush #32
    //   2201: iastore
    //   2202: dup
    //   2203: bipush #43
    //   2205: ldc -2146402272
    //   2207: iastore
    //   2208: dup
    //   2209: bipush #44
    //   2211: ldc 1081376
    //   2213: iastore
    //   2214: dup
    //   2215: bipush #45
    //   2217: bipush #32
    //   2219: iastore
    //   2220: dup
    //   2221: bipush #46
    //   2223: ldc 32768
    //   2225: iastore
    //   2226: dup
    //   2227: bipush #47
    //   2229: ldc -2147483648
    //   2231: iastore
    //   2232: dup
    //   2233: bipush #48
    //   2235: ldc 32800
    //   2237: iastore
    //   2238: dup
    //   2239: bipush #49
    //   2241: ldc -2146402304
    //   2243: iastore
    //   2244: dup
    //   2245: bipush #50
    //   2247: ldc 1048576
    //   2249: iastore
    //   2250: dup
    //   2251: bipush #51
    //   2253: ldc -2147483616
    //   2255: iastore
    //   2256: dup
    //   2257: bipush #52
    //   2259: ldc 1048608
    //   2261: iastore
    //   2262: dup
    //   2263: bipush #53
    //   2265: ldc -2147450848
    //   2267: iastore
    //   2268: dup
    //   2269: bipush #54
    //   2271: ldc -2147483616
    //   2273: iastore
    //   2274: dup
    //   2275: bipush #55
    //   2277: ldc 1048608
    //   2279: iastore
    //   2280: dup
    //   2281: bipush #56
    //   2283: ldc 1081344
    //   2285: iastore
    //   2286: dup
    //   2287: bipush #57
    //   2289: iconst_0
    //   2290: iastore
    //   2291: dup
    //   2292: bipush #58
    //   2294: ldc -2147450880
    //   2296: iastore
    //   2297: dup
    //   2298: bipush #59
    //   2300: ldc 32800
    //   2302: iastore
    //   2303: dup
    //   2304: bipush #60
    //   2306: ldc -2147483648
    //   2308: iastore
    //   2309: dup
    //   2310: bipush #61
    //   2312: ldc -2146435040
    //   2314: iastore
    //   2315: dup
    //   2316: bipush #62
    //   2318: ldc -2146402272
    //   2320: iastore
    //   2321: dup
    //   2322: bipush #63
    //   2324: ldc 1081344
    //   2326: iastore
    //   2327: astore #8
    //   2329: bipush #64
    //   2331: newarray int
    //   2333: dup
    //   2334: iconst_0
    //   2335: sipush #520
    //   2338: iastore
    //   2339: dup
    //   2340: iconst_1
    //   2341: ldc 134349312
    //   2343: iastore
    //   2344: dup
    //   2345: iconst_2
    //   2346: iconst_0
    //   2347: iastore
    //   2348: dup
    //   2349: iconst_3
    //   2350: ldc 134348808
    //   2352: iastore
    //   2353: dup
    //   2354: iconst_4
    //   2355: ldc 134218240
    //   2357: iastore
    //   2358: dup
    //   2359: iconst_5
    //   2360: iconst_0
    //   2361: iastore
    //   2362: dup
    //   2363: bipush #6
    //   2365: ldc 131592
    //   2367: iastore
    //   2368: dup
    //   2369: bipush #7
    //   2371: ldc 134218240
    //   2373: iastore
    //   2374: dup
    //   2375: bipush #8
    //   2377: ldc 131080
    //   2379: iastore
    //   2380: dup
    //   2381: bipush #9
    //   2383: ldc 134217736
    //   2385: iastore
    //   2386: dup
    //   2387: bipush #10
    //   2389: ldc 134217736
    //   2391: iastore
    //   2392: dup
    //   2393: bipush #11
    //   2395: ldc 131072
    //   2397: iastore
    //   2398: dup
    //   2399: bipush #12
    //   2401: ldc 134349320
    //   2403: iastore
    //   2404: dup
    //   2405: bipush #13
    //   2407: ldc 131080
    //   2409: iastore
    //   2410: dup
    //   2411: bipush #14
    //   2413: ldc 134348800
    //   2415: iastore
    //   2416: dup
    //   2417: bipush #15
    //   2419: sipush #520
    //   2422: iastore
    //   2423: dup
    //   2424: bipush #16
    //   2426: ldc 134217728
    //   2428: iastore
    //   2429: dup
    //   2430: bipush #17
    //   2432: bipush #8
    //   2434: iastore
    //   2435: dup
    //   2436: bipush #18
    //   2438: ldc 134349312
    //   2440: iastore
    //   2441: dup
    //   2442: bipush #19
    //   2444: sipush #512
    //   2447: iastore
    //   2448: dup
    //   2449: bipush #20
    //   2451: ldc 131584
    //   2453: iastore
    //   2454: dup
    //   2455: bipush #21
    //   2457: ldc 134348800
    //   2459: iastore
    //   2460: dup
    //   2461: bipush #22
    //   2463: ldc 134348808
    //   2465: iastore
    //   2466: dup
    //   2467: bipush #23
    //   2469: ldc 131592
    //   2471: iastore
    //   2472: dup
    //   2473: bipush #24
    //   2475: ldc 134218248
    //   2477: iastore
    //   2478: dup
    //   2479: bipush #25
    //   2481: ldc 131584
    //   2483: iastore
    //   2484: dup
    //   2485: bipush #26
    //   2487: ldc 131072
    //   2489: iastore
    //   2490: dup
    //   2491: bipush #27
    //   2493: ldc 134218248
    //   2495: iastore
    //   2496: dup
    //   2497: bipush #28
    //   2499: bipush #8
    //   2501: iastore
    //   2502: dup
    //   2503: bipush #29
    //   2505: ldc 134349320
    //   2507: iastore
    //   2508: dup
    //   2509: bipush #30
    //   2511: sipush #512
    //   2514: iastore
    //   2515: dup
    //   2516: bipush #31
    //   2518: ldc 134217728
    //   2520: iastore
    //   2521: dup
    //   2522: bipush #32
    //   2524: ldc 134349312
    //   2526: iastore
    //   2527: dup
    //   2528: bipush #33
    //   2530: ldc 134217728
    //   2532: iastore
    //   2533: dup
    //   2534: bipush #34
    //   2536: ldc 131080
    //   2538: iastore
    //   2539: dup
    //   2540: bipush #35
    //   2542: sipush #520
    //   2545: iastore
    //   2546: dup
    //   2547: bipush #36
    //   2549: ldc 131072
    //   2551: iastore
    //   2552: dup
    //   2553: bipush #37
    //   2555: ldc 134349312
    //   2557: iastore
    //   2558: dup
    //   2559: bipush #38
    //   2561: ldc 134218240
    //   2563: iastore
    //   2564: dup
    //   2565: bipush #39
    //   2567: iconst_0
    //   2568: iastore
    //   2569: dup
    //   2570: bipush #40
    //   2572: sipush #512
    //   2575: iastore
    //   2576: dup
    //   2577: bipush #41
    //   2579: ldc 131080
    //   2581: iastore
    //   2582: dup
    //   2583: bipush #42
    //   2585: ldc 134349320
    //   2587: iastore
    //   2588: dup
    //   2589: bipush #43
    //   2591: ldc 134218240
    //   2593: iastore
    //   2594: dup
    //   2595: bipush #44
    //   2597: ldc 134217736
    //   2599: iastore
    //   2600: dup
    //   2601: bipush #45
    //   2603: sipush #512
    //   2606: iastore
    //   2607: dup
    //   2608: bipush #46
    //   2610: iconst_0
    //   2611: iastore
    //   2612: dup
    //   2613: bipush #47
    //   2615: ldc 134348808
    //   2617: iastore
    //   2618: dup
    //   2619: bipush #48
    //   2621: ldc 134218248
    //   2623: iastore
    //   2624: dup
    //   2625: bipush #49
    //   2627: ldc 131072
    //   2629: iastore
    //   2630: dup
    //   2631: bipush #50
    //   2633: ldc 134217728
    //   2635: iastore
    //   2636: dup
    //   2637: bipush #51
    //   2639: ldc 134349320
    //   2641: iastore
    //   2642: dup
    //   2643: bipush #52
    //   2645: bipush #8
    //   2647: iastore
    //   2648: dup
    //   2649: bipush #53
    //   2651: ldc 131592
    //   2653: iastore
    //   2654: dup
    //   2655: bipush #54
    //   2657: ldc 131584
    //   2659: iastore
    //   2660: dup
    //   2661: bipush #55
    //   2663: ldc 134217736
    //   2665: iastore
    //   2666: dup
    //   2667: bipush #56
    //   2669: ldc 134348800
    //   2671: iastore
    //   2672: dup
    //   2673: bipush #57
    //   2675: ldc 134218248
    //   2677: iastore
    //   2678: dup
    //   2679: bipush #58
    //   2681: sipush #520
    //   2684: iastore
    //   2685: dup
    //   2686: bipush #59
    //   2688: ldc 134348800
    //   2690: iastore
    //   2691: dup
    //   2692: bipush #60
    //   2694: ldc 131592
    //   2696: iastore
    //   2697: dup
    //   2698: bipush #61
    //   2700: bipush #8
    //   2702: iastore
    //   2703: dup
    //   2704: bipush #62
    //   2706: ldc 134348808
    //   2708: iastore
    //   2709: dup
    //   2710: bipush #63
    //   2712: ldc 131584
    //   2714: iastore
    //   2715: astore #9
    //   2717: bipush #64
    //   2719: newarray int
    //   2721: dup
    //   2722: iconst_0
    //   2723: ldc 8396801
    //   2725: iastore
    //   2726: dup
    //   2727: iconst_1
    //   2728: sipush #8321
    //   2731: iastore
    //   2732: dup
    //   2733: iconst_2
    //   2734: sipush #8321
    //   2737: iastore
    //   2738: dup
    //   2739: iconst_3
    //   2740: sipush #128
    //   2743: iastore
    //   2744: dup
    //   2745: iconst_4
    //   2746: ldc 8396928
    //   2748: iastore
    //   2749: dup
    //   2750: iconst_5
    //   2751: ldc 8388737
    //   2753: iastore
    //   2754: dup
    //   2755: bipush #6
    //   2757: ldc 8388609
    //   2759: iastore
    //   2760: dup
    //   2761: bipush #7
    //   2763: sipush #8193
    //   2766: iastore
    //   2767: dup
    //   2768: bipush #8
    //   2770: iconst_0
    //   2771: iastore
    //   2772: dup
    //   2773: bipush #9
    //   2775: ldc 8396800
    //   2777: iastore
    //   2778: dup
    //   2779: bipush #10
    //   2781: ldc 8396800
    //   2783: iastore
    //   2784: dup
    //   2785: bipush #11
    //   2787: ldc 8396929
    //   2789: iastore
    //   2790: dup
    //   2791: bipush #12
    //   2793: sipush #129
    //   2796: iastore
    //   2797: dup
    //   2798: bipush #13
    //   2800: iconst_0
    //   2801: iastore
    //   2802: dup
    //   2803: bipush #14
    //   2805: ldc 8388736
    //   2807: iastore
    //   2808: dup
    //   2809: bipush #15
    //   2811: ldc 8388609
    //   2813: iastore
    //   2814: dup
    //   2815: bipush #16
    //   2817: iconst_1
    //   2818: iastore
    //   2819: dup
    //   2820: bipush #17
    //   2822: sipush #8192
    //   2825: iastore
    //   2826: dup
    //   2827: bipush #18
    //   2829: ldc 8388608
    //   2831: iastore
    //   2832: dup
    //   2833: bipush #19
    //   2835: ldc 8396801
    //   2837: iastore
    //   2838: dup
    //   2839: bipush #20
    //   2841: sipush #128
    //   2844: iastore
    //   2845: dup
    //   2846: bipush #21
    //   2848: ldc 8388608
    //   2850: iastore
    //   2851: dup
    //   2852: bipush #22
    //   2854: sipush #8193
    //   2857: iastore
    //   2858: dup
    //   2859: bipush #23
    //   2861: sipush #8320
    //   2864: iastore
    //   2865: dup
    //   2866: bipush #24
    //   2868: ldc 8388737
    //   2870: iastore
    //   2871: dup
    //   2872: bipush #25
    //   2874: iconst_1
    //   2875: iastore
    //   2876: dup
    //   2877: bipush #26
    //   2879: sipush #8320
    //   2882: iastore
    //   2883: dup
    //   2884: bipush #27
    //   2886: ldc 8388736
    //   2888: iastore
    //   2889: dup
    //   2890: bipush #28
    //   2892: sipush #8192
    //   2895: iastore
    //   2896: dup
    //   2897: bipush #29
    //   2899: ldc 8396928
    //   2901: iastore
    //   2902: dup
    //   2903: bipush #30
    //   2905: ldc 8396929
    //   2907: iastore
    //   2908: dup
    //   2909: bipush #31
    //   2911: sipush #129
    //   2914: iastore
    //   2915: dup
    //   2916: bipush #32
    //   2918: ldc 8388736
    //   2920: iastore
    //   2921: dup
    //   2922: bipush #33
    //   2924: ldc 8388609
    //   2926: iastore
    //   2927: dup
    //   2928: bipush #34
    //   2930: ldc 8396800
    //   2932: iastore
    //   2933: dup
    //   2934: bipush #35
    //   2936: ldc 8396929
    //   2938: iastore
    //   2939: dup
    //   2940: bipush #36
    //   2942: sipush #129
    //   2945: iastore
    //   2946: dup
    //   2947: bipush #37
    //   2949: iconst_0
    //   2950: iastore
    //   2951: dup
    //   2952: bipush #38
    //   2954: iconst_0
    //   2955: iastore
    //   2956: dup
    //   2957: bipush #39
    //   2959: ldc 8396800
    //   2961: iastore
    //   2962: dup
    //   2963: bipush #40
    //   2965: sipush #8320
    //   2968: iastore
    //   2969: dup
    //   2970: bipush #41
    //   2972: ldc 8388736
    //   2974: iastore
    //   2975: dup
    //   2976: bipush #42
    //   2978: ldc 8388737
    //   2980: iastore
    //   2981: dup
    //   2982: bipush #43
    //   2984: iconst_1
    //   2985: iastore
    //   2986: dup
    //   2987: bipush #44
    //   2989: ldc 8396801
    //   2991: iastore
    //   2992: dup
    //   2993: bipush #45
    //   2995: sipush #8321
    //   2998: iastore
    //   2999: dup
    //   3000: bipush #46
    //   3002: sipush #8321
    //   3005: iastore
    //   3006: dup
    //   3007: bipush #47
    //   3009: sipush #128
    //   3012: iastore
    //   3013: dup
    //   3014: bipush #48
    //   3016: ldc 8396929
    //   3018: iastore
    //   3019: dup
    //   3020: bipush #49
    //   3022: sipush #129
    //   3025: iastore
    //   3026: dup
    //   3027: bipush #50
    //   3029: iconst_1
    //   3030: iastore
    //   3031: dup
    //   3032: bipush #51
    //   3034: sipush #8192
    //   3037: iastore
    //   3038: dup
    //   3039: bipush #52
    //   3041: ldc 8388609
    //   3043: iastore
    //   3044: dup
    //   3045: bipush #53
    //   3047: sipush #8193
    //   3050: iastore
    //   3051: dup
    //   3052: bipush #54
    //   3054: ldc 8396928
    //   3056: iastore
    //   3057: dup
    //   3058: bipush #55
    //   3060: ldc 8388737
    //   3062: iastore
    //   3063: dup
    //   3064: bipush #56
    //   3066: sipush #8193
    //   3069: iastore
    //   3070: dup
    //   3071: bipush #57
    //   3073: sipush #8320
    //   3076: iastore
    //   3077: dup
    //   3078: bipush #58
    //   3080: ldc 8388608
    //   3082: iastore
    //   3083: dup
    //   3084: bipush #59
    //   3086: ldc 8396801
    //   3088: iastore
    //   3089: dup
    //   3090: bipush #60
    //   3092: sipush #128
    //   3095: iastore
    //   3096: dup
    //   3097: bipush #61
    //   3099: ldc 8388608
    //   3101: iastore
    //   3102: dup
    //   3103: bipush #62
    //   3105: sipush #8192
    //   3108: iastore
    //   3109: dup
    //   3110: bipush #63
    //   3112: ldc 8396928
    //   3114: iastore
    //   3115: astore #10
    //   3117: bipush #64
    //   3119: newarray int
    //   3121: dup
    //   3122: iconst_0
    //   3123: sipush #256
    //   3126: iastore
    //   3127: dup
    //   3128: iconst_1
    //   3129: ldc 34078976
    //   3131: iastore
    //   3132: dup
    //   3133: iconst_2
    //   3134: ldc 34078720
    //   3136: iastore
    //   3137: dup
    //   3138: iconst_3
    //   3139: ldc 1107296512
    //   3141: iastore
    //   3142: dup
    //   3143: iconst_4
    //   3144: ldc 524288
    //   3146: iastore
    //   3147: dup
    //   3148: iconst_5
    //   3149: sipush #256
    //   3152: iastore
    //   3153: dup
    //   3154: bipush #6
    //   3156: ldc 1073741824
    //   3158: iastore
    //   3159: dup
    //   3160: bipush #7
    //   3162: ldc 34078720
    //   3164: iastore
    //   3165: dup
    //   3166: bipush #8
    //   3168: ldc 1074266368
    //   3170: iastore
    //   3171: dup
    //   3172: bipush #9
    //   3174: ldc 524288
    //   3176: iastore
    //   3177: dup
    //   3178: bipush #10
    //   3180: ldc 33554688
    //   3182: iastore
    //   3183: dup
    //   3184: bipush #11
    //   3186: ldc 1074266368
    //   3188: iastore
    //   3189: dup
    //   3190: bipush #12
    //   3192: ldc 1107296512
    //   3194: iastore
    //   3195: dup
    //   3196: bipush #13
    //   3198: ldc 1107820544
    //   3200: iastore
    //   3201: dup
    //   3202: bipush #14
    //   3204: ldc 524544
    //   3206: iastore
    //   3207: dup
    //   3208: bipush #15
    //   3210: ldc 1073741824
    //   3212: iastore
    //   3213: dup
    //   3214: bipush #16
    //   3216: ldc 33554432
    //   3218: iastore
    //   3219: dup
    //   3220: bipush #17
    //   3222: ldc 1074266112
    //   3224: iastore
    //   3225: dup
    //   3226: bipush #18
    //   3228: ldc 1074266112
    //   3230: iastore
    //   3231: dup
    //   3232: bipush #19
    //   3234: iconst_0
    //   3235: iastore
    //   3236: dup
    //   3237: bipush #20
    //   3239: ldc 1073742080
    //   3241: iastore
    //   3242: dup
    //   3243: bipush #21
    //   3245: ldc 1107820800
    //   3247: iastore
    //   3248: dup
    //   3249: bipush #22
    //   3251: ldc 1107820800
    //   3253: iastore
    //   3254: dup
    //   3255: bipush #23
    //   3257: ldc 33554688
    //   3259: iastore
    //   3260: dup
    //   3261: bipush #24
    //   3263: ldc 1107820544
    //   3265: iastore
    //   3266: dup
    //   3267: bipush #25
    //   3269: ldc 1073742080
    //   3271: iastore
    //   3272: dup
    //   3273: bipush #26
    //   3275: iconst_0
    //   3276: iastore
    //   3277: dup
    //   3278: bipush #27
    //   3280: ldc 1107296256
    //   3282: iastore
    //   3283: dup
    //   3284: bipush #28
    //   3286: ldc 34078976
    //   3288: iastore
    //   3289: dup
    //   3290: bipush #29
    //   3292: ldc 33554432
    //   3294: iastore
    //   3295: dup
    //   3296: bipush #30
    //   3298: ldc 1107296256
    //   3300: iastore
    //   3301: dup
    //   3302: bipush #31
    //   3304: ldc 524544
    //   3306: iastore
    //   3307: dup
    //   3308: bipush #32
    //   3310: ldc 524288
    //   3312: iastore
    //   3313: dup
    //   3314: bipush #33
    //   3316: ldc 1107296512
    //   3318: iastore
    //   3319: dup
    //   3320: bipush #34
    //   3322: sipush #256
    //   3325: iastore
    //   3326: dup
    //   3327: bipush #35
    //   3329: ldc 33554432
    //   3331: iastore
    //   3332: dup
    //   3333: bipush #36
    //   3335: ldc 1073741824
    //   3337: iastore
    //   3338: dup
    //   3339: bipush #37
    //   3341: ldc 34078720
    //   3343: iastore
    //   3344: dup
    //   3345: bipush #38
    //   3347: ldc 1107296512
    //   3349: iastore
    //   3350: dup
    //   3351: bipush #39
    //   3353: ldc 1074266368
    //   3355: iastore
    //   3356: dup
    //   3357: bipush #40
    //   3359: ldc 33554688
    //   3361: iastore
    //   3362: dup
    //   3363: bipush #41
    //   3365: ldc 1073741824
    //   3367: iastore
    //   3368: dup
    //   3369: bipush #42
    //   3371: ldc 1107820544
    //   3373: iastore
    //   3374: dup
    //   3375: bipush #43
    //   3377: ldc 34078976
    //   3379: iastore
    //   3380: dup
    //   3381: bipush #44
    //   3383: ldc 1074266368
    //   3385: iastore
    //   3386: dup
    //   3387: bipush #45
    //   3389: sipush #256
    //   3392: iastore
    //   3393: dup
    //   3394: bipush #46
    //   3396: ldc 33554432
    //   3398: iastore
    //   3399: dup
    //   3400: bipush #47
    //   3402: ldc 1107820544
    //   3404: iastore
    //   3405: dup
    //   3406: bipush #48
    //   3408: ldc 1107820800
    //   3410: iastore
    //   3411: dup
    //   3412: bipush #49
    //   3414: ldc 524544
    //   3416: iastore
    //   3417: dup
    //   3418: bipush #50
    //   3420: ldc 1107296256
    //   3422: iastore
    //   3423: dup
    //   3424: bipush #51
    //   3426: ldc 1107820800
    //   3428: iastore
    //   3429: dup
    //   3430: bipush #52
    //   3432: ldc 34078720
    //   3434: iastore
    //   3435: dup
    //   3436: bipush #53
    //   3438: iconst_0
    //   3439: iastore
    //   3440: dup
    //   3441: bipush #54
    //   3443: ldc 1074266112
    //   3445: iastore
    //   3446: dup
    //   3447: bipush #55
    //   3449: ldc 1107296256
    //   3451: iastore
    //   3452: dup
    //   3453: bipush #56
    //   3455: ldc 524544
    //   3457: iastore
    //   3458: dup
    //   3459: bipush #57
    //   3461: ldc 33554688
    //   3463: iastore
    //   3464: dup
    //   3465: bipush #58
    //   3467: ldc 1073742080
    //   3469: iastore
    //   3470: dup
    //   3471: bipush #59
    //   3473: ldc 524288
    //   3475: iastore
    //   3476: dup
    //   3477: bipush #60
    //   3479: iconst_0
    //   3480: iastore
    //   3481: dup
    //   3482: bipush #61
    //   3484: ldc 1074266112
    //   3486: iastore
    //   3487: dup
    //   3488: bipush #62
    //   3490: ldc 34078976
    //   3492: iastore
    //   3493: dup
    //   3494: bipush #63
    //   3496: ldc 1073742080
    //   3498: iastore
    //   3499: astore #11
    //   3501: bipush #64
    //   3503: newarray int
    //   3505: dup
    //   3506: iconst_0
    //   3507: ldc 536870928
    //   3509: iastore
    //   3510: dup
    //   3511: iconst_1
    //   3512: ldc 541065216
    //   3514: iastore
    //   3515: dup
    //   3516: iconst_2
    //   3517: sipush #16384
    //   3520: iastore
    //   3521: dup
    //   3522: iconst_3
    //   3523: ldc 541081616
    //   3525: iastore
    //   3526: dup
    //   3527: iconst_4
    //   3528: ldc 541065216
    //   3530: iastore
    //   3531: dup
    //   3532: iconst_5
    //   3533: bipush #16
    //   3535: iastore
    //   3536: dup
    //   3537: bipush #6
    //   3539: ldc 541081616
    //   3541: iastore
    //   3542: dup
    //   3543: bipush #7
    //   3545: ldc 4194304
    //   3547: iastore
    //   3548: dup
    //   3549: bipush #8
    //   3551: ldc 536887296
    //   3553: iastore
    //   3554: dup
    //   3555: bipush #9
    //   3557: ldc 4210704
    //   3559: iastore
    //   3560: dup
    //   3561: bipush #10
    //   3563: ldc 4194304
    //   3565: iastore
    //   3566: dup
    //   3567: bipush #11
    //   3569: ldc 536870928
    //   3571: iastore
    //   3572: dup
    //   3573: bipush #12
    //   3575: ldc 4194320
    //   3577: iastore
    //   3578: dup
    //   3579: bipush #13
    //   3581: ldc 536887296
    //   3583: iastore
    //   3584: dup
    //   3585: bipush #14
    //   3587: ldc 536870912
    //   3589: iastore
    //   3590: dup
    //   3591: bipush #15
    //   3593: sipush #16400
    //   3596: iastore
    //   3597: dup
    //   3598: bipush #16
    //   3600: iconst_0
    //   3601: iastore
    //   3602: dup
    //   3603: bipush #17
    //   3605: ldc 4194320
    //   3607: iastore
    //   3608: dup
    //   3609: bipush #18
    //   3611: ldc 536887312
    //   3613: iastore
    //   3614: dup
    //   3615: bipush #19
    //   3617: sipush #16384
    //   3620: iastore
    //   3621: dup
    //   3622: bipush #20
    //   3624: ldc 4210688
    //   3626: iastore
    //   3627: dup
    //   3628: bipush #21
    //   3630: ldc 536887312
    //   3632: iastore
    //   3633: dup
    //   3634: bipush #22
    //   3636: bipush #16
    //   3638: iastore
    //   3639: dup
    //   3640: bipush #23
    //   3642: ldc 541065232
    //   3644: iastore
    //   3645: dup
    //   3646: bipush #24
    //   3648: ldc 541065232
    //   3650: iastore
    //   3651: dup
    //   3652: bipush #25
    //   3654: iconst_0
    //   3655: iastore
    //   3656: dup
    //   3657: bipush #26
    //   3659: ldc 4210704
    //   3661: iastore
    //   3662: dup
    //   3663: bipush #27
    //   3665: ldc 541081600
    //   3667: iastore
    //   3668: dup
    //   3669: bipush #28
    //   3671: sipush #16400
    //   3674: iastore
    //   3675: dup
    //   3676: bipush #29
    //   3678: ldc 4210688
    //   3680: iastore
    //   3681: dup
    //   3682: bipush #30
    //   3684: ldc 541081600
    //   3686: iastore
    //   3687: dup
    //   3688: bipush #31
    //   3690: ldc 536870912
    //   3692: iastore
    //   3693: dup
    //   3694: bipush #32
    //   3696: ldc 536887296
    //   3698: iastore
    //   3699: dup
    //   3700: bipush #33
    //   3702: bipush #16
    //   3704: iastore
    //   3705: dup
    //   3706: bipush #34
    //   3708: ldc 541065232
    //   3710: iastore
    //   3711: dup
    //   3712: bipush #35
    //   3714: ldc 4210688
    //   3716: iastore
    //   3717: dup
    //   3718: bipush #36
    //   3720: ldc 541081616
    //   3722: iastore
    //   3723: dup
    //   3724: bipush #37
    //   3726: ldc 4194304
    //   3728: iastore
    //   3729: dup
    //   3730: bipush #38
    //   3732: sipush #16400
    //   3735: iastore
    //   3736: dup
    //   3737: bipush #39
    //   3739: ldc 536870928
    //   3741: iastore
    //   3742: dup
    //   3743: bipush #40
    //   3745: ldc 4194304
    //   3747: iastore
    //   3748: dup
    //   3749: bipush #41
    //   3751: ldc 536887296
    //   3753: iastore
    //   3754: dup
    //   3755: bipush #42
    //   3757: ldc 536870912
    //   3759: iastore
    //   3760: dup
    //   3761: bipush #43
    //   3763: sipush #16400
    //   3766: iastore
    //   3767: dup
    //   3768: bipush #44
    //   3770: ldc 536870928
    //   3772: iastore
    //   3773: dup
    //   3774: bipush #45
    //   3776: ldc 541081616
    //   3778: iastore
    //   3779: dup
    //   3780: bipush #46
    //   3782: ldc 4210688
    //   3784: iastore
    //   3785: dup
    //   3786: bipush #47
    //   3788: ldc 541065216
    //   3790: iastore
    //   3791: dup
    //   3792: bipush #48
    //   3794: ldc 4210704
    //   3796: iastore
    //   3797: dup
    //   3798: bipush #49
    //   3800: ldc 541081600
    //   3802: iastore
    //   3803: dup
    //   3804: bipush #50
    //   3806: iconst_0
    //   3807: iastore
    //   3808: dup
    //   3809: bipush #51
    //   3811: ldc 541065232
    //   3813: iastore
    //   3814: dup
    //   3815: bipush #52
    //   3817: bipush #16
    //   3819: iastore
    //   3820: dup
    //   3821: bipush #53
    //   3823: sipush #16384
    //   3826: iastore
    //   3827: dup
    //   3828: bipush #54
    //   3830: ldc 541065216
    //   3832: iastore
    //   3833: dup
    //   3834: bipush #55
    //   3836: ldc 4210704
    //   3838: iastore
    //   3839: dup
    //   3840: bipush #56
    //   3842: sipush #16384
    //   3845: iastore
    //   3846: dup
    //   3847: bipush #57
    //   3849: ldc 4194320
    //   3851: iastore
    //   3852: dup
    //   3853: bipush #58
    //   3855: ldc 536887312
    //   3857: iastore
    //   3858: dup
    //   3859: bipush #59
    //   3861: iconst_0
    //   3862: iastore
    //   3863: dup
    //   3864: bipush #60
    //   3866: ldc 541081600
    //   3868: iastore
    //   3869: dup
    //   3870: bipush #61
    //   3872: ldc 536870912
    //   3874: iastore
    //   3875: dup
    //   3876: bipush #62
    //   3878: ldc 4194320
    //   3880: iastore
    //   3881: dup
    //   3882: bipush #63
    //   3884: ldc 536887312
    //   3886: iastore
    //   3887: astore #12
    //   3889: bipush #64
    //   3891: newarray int
    //   3893: dup
    //   3894: iconst_0
    //   3895: ldc 2097152
    //   3897: iastore
    //   3898: dup
    //   3899: iconst_1
    //   3900: ldc 69206018
    //   3902: iastore
    //   3903: dup
    //   3904: iconst_2
    //   3905: ldc 67110914
    //   3907: iastore
    //   3908: dup
    //   3909: iconst_3
    //   3910: iconst_0
    //   3911: iastore
    //   3912: dup
    //   3913: iconst_4
    //   3914: sipush #2048
    //   3917: iastore
    //   3918: dup
    //   3919: iconst_5
    //   3920: ldc 67110914
    //   3922: iastore
    //   3923: dup
    //   3924: bipush #6
    //   3926: ldc 2099202
    //   3928: iastore
    //   3929: dup
    //   3930: bipush #7
    //   3932: ldc 69208064
    //   3934: iastore
    //   3935: dup
    //   3936: bipush #8
    //   3938: ldc 69208066
    //   3940: iastore
    //   3941: dup
    //   3942: bipush #9
    //   3944: ldc 2097152
    //   3946: iastore
    //   3947: dup
    //   3948: bipush #10
    //   3950: iconst_0
    //   3951: iastore
    //   3952: dup
    //   3953: bipush #11
    //   3955: ldc 67108866
    //   3957: iastore
    //   3958: dup
    //   3959: bipush #12
    //   3961: iconst_2
    //   3962: iastore
    //   3963: dup
    //   3964: bipush #13
    //   3966: ldc 67108864
    //   3968: iastore
    //   3969: dup
    //   3970: bipush #14
    //   3972: ldc 69206018
    //   3974: iastore
    //   3975: dup
    //   3976: bipush #15
    //   3978: sipush #2050
    //   3981: iastore
    //   3982: dup
    //   3983: bipush #16
    //   3985: ldc 67110912
    //   3987: iastore
    //   3988: dup
    //   3989: bipush #17
    //   3991: ldc 2099202
    //   3993: iastore
    //   3994: dup
    //   3995: bipush #18
    //   3997: ldc 2097154
    //   3999: iastore
    //   4000: dup
    //   4001: bipush #19
    //   4003: ldc 67110912
    //   4005: iastore
    //   4006: dup
    //   4007: bipush #20
    //   4009: ldc 67108866
    //   4011: iastore
    //   4012: dup
    //   4013: bipush #21
    //   4015: ldc 69206016
    //   4017: iastore
    //   4018: dup
    //   4019: bipush #22
    //   4021: ldc 69208064
    //   4023: iastore
    //   4024: dup
    //   4025: bipush #23
    //   4027: ldc 2097154
    //   4029: iastore
    //   4030: dup
    //   4031: bipush #24
    //   4033: ldc 69206016
    //   4035: iastore
    //   4036: dup
    //   4037: bipush #25
    //   4039: sipush #2048
    //   4042: iastore
    //   4043: dup
    //   4044: bipush #26
    //   4046: sipush #2050
    //   4049: iastore
    //   4050: dup
    //   4051: bipush #27
    //   4053: ldc 69208066
    //   4055: iastore
    //   4056: dup
    //   4057: bipush #28
    //   4059: ldc 2099200
    //   4061: iastore
    //   4062: dup
    //   4063: bipush #29
    //   4065: iconst_2
    //   4066: iastore
    //   4067: dup
    //   4068: bipush #30
    //   4070: ldc 67108864
    //   4072: iastore
    //   4073: dup
    //   4074: bipush #31
    //   4076: ldc 2099200
    //   4078: iastore
    //   4079: dup
    //   4080: bipush #32
    //   4082: ldc 67108864
    //   4084: iastore
    //   4085: dup
    //   4086: bipush #33
    //   4088: ldc 2099200
    //   4090: iastore
    //   4091: dup
    //   4092: bipush #34
    //   4094: ldc 2097152
    //   4096: iastore
    //   4097: dup
    //   4098: bipush #35
    //   4100: ldc 67110914
    //   4102: iastore
    //   4103: dup
    //   4104: bipush #36
    //   4106: ldc 67110914
    //   4108: iastore
    //   4109: dup
    //   4110: bipush #37
    //   4112: ldc 69206018
    //   4114: iastore
    //   4115: dup
    //   4116: bipush #38
    //   4118: ldc 69206018
    //   4120: iastore
    //   4121: dup
    //   4122: bipush #39
    //   4124: iconst_2
    //   4125: iastore
    //   4126: dup
    //   4127: bipush #40
    //   4129: ldc 2097154
    //   4131: iastore
    //   4132: dup
    //   4133: bipush #41
    //   4135: ldc 67108864
    //   4137: iastore
    //   4138: dup
    //   4139: bipush #42
    //   4141: ldc 67110912
    //   4143: iastore
    //   4144: dup
    //   4145: bipush #43
    //   4147: ldc 2097152
    //   4149: iastore
    //   4150: dup
    //   4151: bipush #44
    //   4153: ldc 69208064
    //   4155: iastore
    //   4156: dup
    //   4157: bipush #45
    //   4159: sipush #2050
    //   4162: iastore
    //   4163: dup
    //   4164: bipush #46
    //   4166: ldc 2099202
    //   4168: iastore
    //   4169: dup
    //   4170: bipush #47
    //   4172: ldc 69208064
    //   4174: iastore
    //   4175: dup
    //   4176: bipush #48
    //   4178: sipush #2050
    //   4181: iastore
    //   4182: dup
    //   4183: bipush #49
    //   4185: ldc 67108866
    //   4187: iastore
    //   4188: dup
    //   4189: bipush #50
    //   4191: ldc 69208066
    //   4193: iastore
    //   4194: dup
    //   4195: bipush #51
    //   4197: ldc 69206016
    //   4199: iastore
    //   4200: dup
    //   4201: bipush #52
    //   4203: ldc 2099200
    //   4205: iastore
    //   4206: dup
    //   4207: bipush #53
    //   4209: iconst_0
    //   4210: iastore
    //   4211: dup
    //   4212: bipush #54
    //   4214: iconst_2
    //   4215: iastore
    //   4216: dup
    //   4217: bipush #55
    //   4219: ldc 69208066
    //   4221: iastore
    //   4222: dup
    //   4223: bipush #56
    //   4225: iconst_0
    //   4226: iastore
    //   4227: dup
    //   4228: bipush #57
    //   4230: ldc 2099202
    //   4232: iastore
    //   4233: dup
    //   4234: bipush #58
    //   4236: ldc 69206016
    //   4238: iastore
    //   4239: dup
    //   4240: bipush #59
    //   4242: sipush #2048
    //   4245: iastore
    //   4246: dup
    //   4247: bipush #60
    //   4249: ldc 67108866
    //   4251: iastore
    //   4252: dup
    //   4253: bipush #61
    //   4255: ldc 67110912
    //   4257: iastore
    //   4258: dup
    //   4259: bipush #62
    //   4261: sipush #2048
    //   4264: iastore
    //   4265: dup
    //   4266: bipush #63
    //   4268: ldc 2097154
    //   4270: iastore
    //   4271: astore #13
    //   4273: bipush #64
    //   4275: newarray int
    //   4277: dup
    //   4278: iconst_0
    //   4279: ldc 268439616
    //   4281: iastore
    //   4282: dup
    //   4283: iconst_1
    //   4284: sipush #4096
    //   4287: iastore
    //   4288: dup
    //   4289: iconst_2
    //   4290: ldc 262144
    //   4292: iastore
    //   4293: dup
    //   4294: iconst_3
    //   4295: ldc 268701760
    //   4297: iastore
    //   4298: dup
    //   4299: iconst_4
    //   4300: ldc 268435456
    //   4302: iastore
    //   4303: dup
    //   4304: iconst_5
    //   4305: ldc 268439616
    //   4307: iastore
    //   4308: dup
    //   4309: bipush #6
    //   4311: bipush #64
    //   4313: iastore
    //   4314: dup
    //   4315: bipush #7
    //   4317: ldc 268435456
    //   4319: iastore
    //   4320: dup
    //   4321: bipush #8
    //   4323: ldc 262208
    //   4325: iastore
    //   4326: dup
    //   4327: bipush #9
    //   4329: ldc 268697600
    //   4331: iastore
    //   4332: dup
    //   4333: bipush #10
    //   4335: ldc 268701760
    //   4337: iastore
    //   4338: dup
    //   4339: bipush #11
    //   4341: ldc 266240
    //   4343: iastore
    //   4344: dup
    //   4345: bipush #12
    //   4347: ldc 268701696
    //   4349: iastore
    //   4350: dup
    //   4351: bipush #13
    //   4353: ldc 266304
    //   4355: iastore
    //   4356: dup
    //   4357: bipush #14
    //   4359: sipush #4096
    //   4362: iastore
    //   4363: dup
    //   4364: bipush #15
    //   4366: bipush #64
    //   4368: iastore
    //   4369: dup
    //   4370: bipush #16
    //   4372: ldc 268697600
    //   4374: iastore
    //   4375: dup
    //   4376: bipush #17
    //   4378: ldc 268435520
    //   4380: iastore
    //   4381: dup
    //   4382: bipush #18
    //   4384: ldc 268439552
    //   4386: iastore
    //   4387: dup
    //   4388: bipush #19
    //   4390: sipush #4160
    //   4393: iastore
    //   4394: dup
    //   4395: bipush #20
    //   4397: ldc 266240
    //   4399: iastore
    //   4400: dup
    //   4401: bipush #21
    //   4403: ldc 262208
    //   4405: iastore
    //   4406: dup
    //   4407: bipush #22
    //   4409: ldc 268697664
    //   4411: iastore
    //   4412: dup
    //   4413: bipush #23
    //   4415: ldc 268701696
    //   4417: iastore
    //   4418: dup
    //   4419: bipush #24
    //   4421: sipush #4160
    //   4424: iastore
    //   4425: dup
    //   4426: bipush #25
    //   4428: iconst_0
    //   4429: iastore
    //   4430: dup
    //   4431: bipush #26
    //   4433: iconst_0
    //   4434: iastore
    //   4435: dup
    //   4436: bipush #27
    //   4438: ldc 268697664
    //   4440: iastore
    //   4441: dup
    //   4442: bipush #28
    //   4444: ldc 268435520
    //   4446: iastore
    //   4447: dup
    //   4448: bipush #29
    //   4450: ldc 268439552
    //   4452: iastore
    //   4453: dup
    //   4454: bipush #30
    //   4456: ldc 266304
    //   4458: iastore
    //   4459: dup
    //   4460: bipush #31
    //   4462: ldc 262144
    //   4464: iastore
    //   4465: dup
    //   4466: bipush #32
    //   4468: ldc 266304
    //   4470: iastore
    //   4471: dup
    //   4472: bipush #33
    //   4474: ldc 262144
    //   4476: iastore
    //   4477: dup
    //   4478: bipush #34
    //   4480: ldc 268701696
    //   4482: iastore
    //   4483: dup
    //   4484: bipush #35
    //   4486: sipush #4096
    //   4489: iastore
    //   4490: dup
    //   4491: bipush #36
    //   4493: bipush #64
    //   4495: iastore
    //   4496: dup
    //   4497: bipush #37
    //   4499: ldc 268697664
    //   4501: iastore
    //   4502: dup
    //   4503: bipush #38
    //   4505: sipush #4096
    //   4508: iastore
    //   4509: dup
    //   4510: bipush #39
    //   4512: ldc 266304
    //   4514: iastore
    //   4515: dup
    //   4516: bipush #40
    //   4518: ldc 268439552
    //   4520: iastore
    //   4521: dup
    //   4522: bipush #41
    //   4524: bipush #64
    //   4526: iastore
    //   4527: dup
    //   4528: bipush #42
    //   4530: ldc 268435520
    //   4532: iastore
    //   4533: dup
    //   4534: bipush #43
    //   4536: ldc 268697600
    //   4538: iastore
    //   4539: dup
    //   4540: bipush #44
    //   4542: ldc 268697664
    //   4544: iastore
    //   4545: dup
    //   4546: bipush #45
    //   4548: ldc 268435456
    //   4550: iastore
    //   4551: dup
    //   4552: bipush #46
    //   4554: ldc 262144
    //   4556: iastore
    //   4557: dup
    //   4558: bipush #47
    //   4560: ldc 268439616
    //   4562: iastore
    //   4563: dup
    //   4564: bipush #48
    //   4566: iconst_0
    //   4567: iastore
    //   4568: dup
    //   4569: bipush #49
    //   4571: ldc 268701760
    //   4573: iastore
    //   4574: dup
    //   4575: bipush #50
    //   4577: ldc 262208
    //   4579: iastore
    //   4580: dup
    //   4581: bipush #51
    //   4583: ldc 268435520
    //   4585: iastore
    //   4586: dup
    //   4587: bipush #52
    //   4589: ldc 268697600
    //   4591: iastore
    //   4592: dup
    //   4593: bipush #53
    //   4595: ldc 268439552
    //   4597: iastore
    //   4598: dup
    //   4599: bipush #54
    //   4601: ldc 268439616
    //   4603: iastore
    //   4604: dup
    //   4605: bipush #55
    //   4607: iconst_0
    //   4608: iastore
    //   4609: dup
    //   4610: bipush #56
    //   4612: ldc 268701760
    //   4614: iastore
    //   4615: dup
    //   4616: bipush #57
    //   4618: ldc 266240
    //   4620: iastore
    //   4621: dup
    //   4622: bipush #58
    //   4624: ldc 266240
    //   4626: iastore
    //   4627: dup
    //   4628: bipush #59
    //   4630: sipush #4160
    //   4633: iastore
    //   4634: dup
    //   4635: bipush #60
    //   4637: sipush #4160
    //   4640: iastore
    //   4641: dup
    //   4642: bipush #61
    //   4644: ldc 262208
    //   4646: iastore
    //   4647: dup
    //   4648: bipush #62
    //   4650: ldc 268435456
    //   4652: iastore
    //   4653: dup
    //   4654: bipush #63
    //   4656: ldc 268701696
    //   4658: iastore
    //   4659: astore #14
    //   4661: aload #4
    //   4663: arraylength
    //   4664: istore #15
    //   4666: iload #15
    //   4668: bipush #8
    //   4670: irem
    //   4671: ifeq -> 4695
    //   4674: new java/lang/Exception
    //   4677: dup
    //   4678: sipush #-31025
    //   4681: sipush #3250
    //   4684: invokestatic a : (II)Ljava/lang/String;
    //   4687: invokespecial <init> : (Ljava/lang/String;)V
    //   4690: athrow
    //   4691: invokestatic a : (Ljava/lang/Throwable;)Ljava/lang/Throwable;
    //   4694: athrow
    //   4695: iconst_2
    //   4696: newarray int
    //   4698: astore #16
    //   4700: iload #15
    //   4702: newarray byte
    //   4704: astore #17
    //   4706: iload #15
    //   4708: bipush #8
    //   4710: idiv
    //   4711: istore #18
    //   4713: iconst_0
    //   4714: istore #19
    //   4716: iload #19
    //   4718: iload #18
    //   4720: if_icmpge -> 5638
    //   4723: iload #19
    //   4725: bipush #8
    //   4727: imul
    //   4728: istore #20
    //   4730: iconst_0
    //   4731: istore #21
    //   4733: iload #21
    //   4735: iconst_2
    //   4736: if_icmpge -> 4825
    //   4739: aload #16
    //   4741: iload #21
    //   4743: aload #4
    //   4745: iload #20
    //   4747: iload #21
    //   4749: iconst_4
    //   4750: imul
    //   4751: iadd
    //   4752: baload
    //   4753: sipush #255
    //   4756: iand
    //   4757: bipush #24
    //   4759: ishl
    //   4760: aload #4
    //   4762: iload #20
    //   4764: iload #21
    //   4766: iconst_4
    //   4767: imul
    //   4768: iadd
    //   4769: iconst_1
    //   4770: iadd
    //   4771: baload
    //   4772: sipush #255
    //   4775: iand
    //   4776: bipush #16
    //   4778: ishl
    //   4779: ior
    //   4780: aload #4
    //   4782: iload #20
    //   4784: iload #21
    //   4786: iconst_4
    //   4787: imul
    //   4788: iadd
    //   4789: iconst_2
    //   4790: iadd
    //   4791: baload
    //   4792: sipush #255
    //   4795: iand
    //   4796: bipush #8
    //   4798: ishl
    //   4799: ior
    //   4800: aload #4
    //   4802: iload #20
    //   4804: iload #21
    //   4806: iconst_4
    //   4807: imul
    //   4808: iadd
    //   4809: iconst_3
    //   4810: iadd
    //   4811: baload
    //   4812: sipush #255
    //   4815: iand
    //   4816: ior
    //   4817: iastore
    //   4818: iinc #21, 1
    //   4821: iload_2
    //   4822: ifeq -> 4733
    //   4825: iconst_0
    //   4826: istore #26
    //   4828: aload #16
    //   4830: iconst_0
    //   4831: iaload
    //   4832: istore #24
    //   4834: aload #16
    //   4836: iconst_1
    //   4837: iaload
    //   4838: istore #23
    //   4840: iload #24
    //   4842: iconst_4
    //   4843: iushr
    //   4844: iload #23
    //   4846: ixor
    //   4847: ldc 252645135
    //   4849: iand
    //   4850: istore #22
    //   4852: iload #23
    //   4854: iload #22
    //   4856: ixor
    //   4857: istore #23
    //   4859: iload #24
    //   4861: iload #22
    //   4863: iconst_4
    //   4864: ishl
    //   4865: ixor
    //   4866: istore #24
    //   4868: iload #24
    //   4870: bipush #16
    //   4872: iushr
    //   4873: iload #23
    //   4875: ixor
    //   4876: ldc 65535
    //   4878: iand
    //   4879: istore #22
    //   4881: iload #23
    //   4883: iload #22
    //   4885: ixor
    //   4886: istore #23
    //   4888: iload #24
    //   4890: iload #22
    //   4892: bipush #16
    //   4894: ishl
    //   4895: ixor
    //   4896: istore #24
    //   4898: iload #23
    //   4900: iconst_2
    //   4901: iushr
    //   4902: iload #24
    //   4904: ixor
    //   4905: ldc 858993459
    //   4907: iand
    //   4908: istore #22
    //   4910: iload #24
    //   4912: iload #22
    //   4914: ixor
    //   4915: istore #24
    //   4917: iload #23
    //   4919: iload #22
    //   4921: iconst_2
    //   4922: ishl
    //   4923: ixor
    //   4924: istore #23
    //   4926: iload #23
    //   4928: bipush #8
    //   4930: iushr
    //   4931: iload #24
    //   4933: ixor
    //   4934: ldc 16711935
    //   4936: iand
    //   4937: istore #22
    //   4939: iload #24
    //   4941: iload #22
    //   4943: ixor
    //   4944: istore #24
    //   4946: iload #23
    //   4948: iload #22
    //   4950: bipush #8
    //   4952: ishl
    //   4953: ixor
    //   4954: istore #23
    //   4956: iload #23
    //   4958: iconst_1
    //   4959: ishl
    //   4960: iload #23
    //   4962: bipush #31
    //   4964: iushr
    //   4965: iconst_1
    //   4966: iand
    //   4967: ior
    //   4968: istore #23
    //   4970: iload #24
    //   4972: iload #23
    //   4974: ixor
    //   4975: ldc -1431655766
    //   4977: iand
    //   4978: istore #22
    //   4980: iload #24
    //   4982: iload #22
    //   4984: ixor
    //   4985: istore #24
    //   4987: iload #23
    //   4989: iload #22
    //   4991: ixor
    //   4992: istore #23
    //   4994: iload #24
    //   4996: iconst_1
    //   4997: ishl
    //   4998: iload #24
    //   5000: bipush #31
    //   5002: iushr
    //   5003: iconst_1
    //   5004: iand
    //   5005: ior
    //   5006: istore #24
    //   5008: iconst_0
    //   5009: istore #25
    //   5011: iload #25
    //   5013: bipush #8
    //   5015: if_icmpge -> 5353
    //   5018: iload #23
    //   5020: bipush #28
    //   5022: ishl
    //   5023: iload #23
    //   5025: iconst_4
    //   5026: iushr
    //   5027: ior
    //   5028: istore #22
    //   5030: iload #22
    //   5032: aload #6
    //   5034: iload #26
    //   5036: iinc #26, 1
    //   5039: iaload
    //   5040: ixor
    //   5041: istore #22
    //   5043: aload #13
    //   5045: iload #22
    //   5047: bipush #63
    //   5049: iand
    //   5050: iaload
    //   5051: istore #21
    //   5053: iload #21
    //   5055: aload #11
    //   5057: iload #22
    //   5059: bipush #8
    //   5061: iushr
    //   5062: bipush #63
    //   5064: iand
    //   5065: iaload
    //   5066: ior
    //   5067: istore #21
    //   5069: iload #21
    //   5071: aload #9
    //   5073: iload #22
    //   5075: bipush #16
    //   5077: iushr
    //   5078: bipush #63
    //   5080: iand
    //   5081: iaload
    //   5082: ior
    //   5083: istore #21
    //   5085: iload #21
    //   5087: aload #7
    //   5089: iload #22
    //   5091: bipush #24
    //   5093: iushr
    //   5094: bipush #63
    //   5096: iand
    //   5097: iaload
    //   5098: ior
    //   5099: istore #21
    //   5101: iload #23
    //   5103: aload #6
    //   5105: iload #26
    //   5107: iinc #26, 1
    //   5110: iaload
    //   5111: ixor
    //   5112: istore #22
    //   5114: iload #21
    //   5116: aload #14
    //   5118: iload #22
    //   5120: bipush #63
    //   5122: iand
    //   5123: iaload
    //   5124: ior
    //   5125: istore #21
    //   5127: iload #21
    //   5129: aload #12
    //   5131: iload #22
    //   5133: bipush #8
    //   5135: iushr
    //   5136: bipush #63
    //   5138: iand
    //   5139: iaload
    //   5140: ior
    //   5141: istore #21
    //   5143: iload #21
    //   5145: aload #10
    //   5147: iload #22
    //   5149: bipush #16
    //   5151: iushr
    //   5152: bipush #63
    //   5154: iand
    //   5155: iaload
    //   5156: ior
    //   5157: istore #21
    //   5159: iload #21
    //   5161: aload #8
    //   5163: iload #22
    //   5165: bipush #24
    //   5167: iushr
    //   5168: bipush #63
    //   5170: iand
    //   5171: iaload
    //   5172: ior
    //   5173: istore #21
    //   5175: iload #24
    //   5177: iload #21
    //   5179: ixor
    //   5180: istore #24
    //   5182: iload #24
    //   5184: bipush #28
    //   5186: ishl
    //   5187: iload #24
    //   5189: iconst_4
    //   5190: iushr
    //   5191: ior
    //   5192: istore #22
    //   5194: iload #22
    //   5196: aload #6
    //   5198: iload #26
    //   5200: iinc #26, 1
    //   5203: iaload
    //   5204: ixor
    //   5205: istore #22
    //   5207: aload #13
    //   5209: iload #22
    //   5211: bipush #63
    //   5213: iand
    //   5214: iaload
    //   5215: istore #21
    //   5217: iload #21
    //   5219: aload #11
    //   5221: iload #22
    //   5223: bipush #8
    //   5225: iushr
    //   5226: bipush #63
    //   5228: iand
    //   5229: iaload
    //   5230: ior
    //   5231: istore #21
    //   5233: iload #21
    //   5235: aload #9
    //   5237: iload #22
    //   5239: bipush #16
    //   5241: iushr
    //   5242: bipush #63
    //   5244: iand
    //   5245: iaload
    //   5246: ior
    //   5247: istore #21
    //   5249: iload #21
    //   5251: aload #7
    //   5253: iload #22
    //   5255: bipush #24
    //   5257: iushr
    //   5258: bipush #63
    //   5260: iand
    //   5261: iaload
    //   5262: ior
    //   5263: istore #21
    //   5265: iload #24
    //   5267: aload #6
    //   5269: iload #26
    //   5271: iinc #26, 1
    //   5274: iaload
    //   5275: ixor
    //   5276: istore #22
    //   5278: iload #21
    //   5280: aload #14
    //   5282: iload #22
    //   5284: bipush #63
    //   5286: iand
    //   5287: iaload
    //   5288: ior
    //   5289: istore #21
    //   5291: iload #21
    //   5293: aload #12
    //   5295: iload #22
    //   5297: bipush #8
    //   5299: iushr
    //   5300: bipush #63
    //   5302: iand
    //   5303: iaload
    //   5304: ior
    //   5305: istore #21
    //   5307: iload #21
    //   5309: aload #10
    //   5311: iload #22
    //   5313: bipush #16
    //   5315: iushr
    //   5316: bipush #63
    //   5318: iand
    //   5319: iaload
    //   5320: ior
    //   5321: istore #21
    //   5323: iload #21
    //   5325: aload #8
    //   5327: iload #22
    //   5329: bipush #24
    //   5331: iushr
    //   5332: bipush #63
    //   5334: iand
    //   5335: iaload
    //   5336: ior
    //   5337: istore #21
    //   5339: iload #23
    //   5341: iload #21
    //   5343: ixor
    //   5344: istore #23
    //   5346: iinc #25, 1
    //   5349: iload_2
    //   5350: ifeq -> 5011
    //   5353: iload #23
    //   5355: bipush #31
    //   5357: ishl
    //   5358: iload #23
    //   5360: iconst_1
    //   5361: iushr
    //   5362: ior
    //   5363: istore #23
    //   5365: iload #24
    //   5367: iload #23
    //   5369: ixor
    //   5370: ldc -1431655766
    //   5372: iand
    //   5373: istore #22
    //   5375: iload #24
    //   5377: iload #22
    //   5379: ixor
    //   5380: istore #24
    //   5382: iload #23
    //   5384: iload #22
    //   5386: ixor
    //   5387: istore #23
    //   5389: iload #24
    //   5391: bipush #31
    //   5393: ishl
    //   5394: iload #24
    //   5396: iconst_1
    //   5397: iushr
    //   5398: ior
    //   5399: istore #24
    //   5401: iload #24
    //   5403: bipush #8
    //   5405: iushr
    //   5406: iload #23
    //   5408: ixor
    //   5409: ldc 16711935
    //   5411: iand
    //   5412: istore #22
    //   5414: iload #23
    //   5416: iload #22
    //   5418: ixor
    //   5419: istore #23
    //   5421: iload #24
    //   5423: iload #22
    //   5425: bipush #8
    //   5427: ishl
    //   5428: ixor
    //   5429: istore #24
    //   5431: iload #24
    //   5433: iconst_2
    //   5434: iushr
    //   5435: iload #23
    //   5437: ixor
    //   5438: ldc 858993459
    //   5440: iand
    //   5441: istore #22
    //   5443: iload #23
    //   5445: iload #22
    //   5447: ixor
    //   5448: istore #23
    //   5450: iload #24
    //   5452: iload #22
    //   5454: iconst_2
    //   5455: ishl
    //   5456: ixor
    //   5457: istore #24
    //   5459: iload #23
    //   5461: bipush #16
    //   5463: iushr
    //   5464: iload #24
    //   5466: ixor
    //   5467: ldc 65535
    //   5469: iand
    //   5470: istore #22
    //   5472: iload #24
    //   5474: iload #22
    //   5476: ixor
    //   5477: istore #24
    //   5479: iload #23
    //   5481: iload #22
    //   5483: bipush #16
    //   5485: ishl
    //   5486: ixor
    //   5487: istore #23
    //   5489: iload #23
    //   5491: iconst_4
    //   5492: iushr
    //   5493: iload #24
    //   5495: ixor
    //   5496: ldc 252645135
    //   5498: iand
    //   5499: istore #22
    //   5501: iload #24
    //   5503: iload #22
    //   5505: ixor
    //   5506: istore #24
    //   5508: iload #23
    //   5510: iload #22
    //   5512: iconst_4
    //   5513: ishl
    //   5514: ixor
    //   5515: istore #23
    //   5517: aload #16
    //   5519: iconst_0
    //   5520: iload #23
    //   5522: iastore
    //   5523: aload #16
    //   5525: iconst_1
    //   5526: iload #24
    //   5528: iastore
    //   5529: iload #19
    //   5531: bipush #8
    //   5533: imul
    //   5534: istore #27
    //   5536: iconst_0
    //   5537: istore #28
    //   5539: iload #28
    //   5541: iconst_2
    //   5542: if_icmpge -> 5631
    //   5545: aload #17
    //   5547: iload #27
    //   5549: iload #28
    //   5551: iconst_4
    //   5552: imul
    //   5553: iadd
    //   5554: aload #16
    //   5556: iload #28
    //   5558: iaload
    //   5559: bipush #24
    //   5561: iushr
    //   5562: i2b
    //   5563: bastore
    //   5564: aload #17
    //   5566: iload #27
    //   5568: iload #28
    //   5570: iconst_4
    //   5571: imul
    //   5572: iadd
    //   5573: iconst_1
    //   5574: iadd
    //   5575: aload #16
    //   5577: iload #28
    //   5579: iaload
    //   5580: bipush #16
    //   5582: iushr
    //   5583: i2b
    //   5584: bastore
    //   5585: aload #17
    //   5587: iload #27
    //   5589: iload #28
    //   5591: iconst_4
    //   5592: imul
    //   5593: iadd
    //   5594: iconst_2
    //   5595: iadd
    //   5596: aload #16
    //   5598: iload #28
    //   5600: iaload
    //   5601: bipush #8
    //   5603: iushr
    //   5604: i2b
    //   5605: bastore
    //   5606: aload #17
    //   5608: iload #27
    //   5610: iload #28
    //   5612: iconst_4
    //   5613: imul
    //   5614: iadd
    //   5615: iconst_3
    //   5616: iadd
    //   5617: aload #16
    //   5619: iload #28
    //   5621: iaload
    //   5622: i2b
    //   5623: bastore
    //   5624: iinc #28, 1
    //   5627: iload_2
    //   5628: ifeq -> 5539
    //   5631: iinc #19, 1
    //   5634: iload_2
    //   5635: ifeq -> 4716
    //   5638: aload #17
    //   5640: aload #17
    //   5642: arraylength
    //   5643: iconst_1
    //   5644: isub
    //   5645: baload
    //   5646: istore #19
    //   5648: aload #17
    //   5650: arraylength
    //   5651: iload #19
    //   5653: isub
    //   5654: newarray byte
    //   5656: astore #5
    //   5658: aload #17
    //   5660: arraylength
    //   5661: aload #5
    //   5663: arraylength
    //   5664: if_icmpge -> 5688
    //   5667: new java/lang/Exception
    //   5670: dup
    //   5671: sipush #-31028
    //   5674: sipush #3905
    //   5677: invokestatic a : (II)Ljava/lang/String;
    //   5680: invokespecial <init> : (Ljava/lang/String;)V
    //   5683: athrow
    //   5684: invokestatic a : (Ljava/lang/Throwable;)Ljava/lang/Throwable;
    //   5687: athrow
    //   5688: iconst_0
    //   5689: istore #20
    //   5691: iload #20
    //   5693: aload #5
    //   5695: arraylength
    //   5696: if_icmpge -> 5716
    //   5699: aload #5
    //   5701: iload #20
    //   5703: aload #17
    //   5705: iload #20
    //   5707: baload
    //   5708: bastore
    //   5709: iinc #20, 1
    //   5712: iload_2
    //   5713: ifeq -> 5691
    //   5716: new java/math/BigInteger
    //   5719: dup
    //   5720: aload #5
    //   5722: invokespecial <init> : ([B)V
    //   5725: invokevirtual abs : ()Ljava/math/BigInteger;
    //   5728: putstatic burp/Zmwx.Zk : Ljava/lang/Object;
    //   5731: sipush #-31035
    //   5734: sipush #28096
    //   5737: invokestatic a : (II)Ljava/lang/String;
    //   5740: iconst_1
    //   5741: ldc burp/Zr48
    //   5743: invokevirtual getClassLoader : ()Ljava/lang/ClassLoader;
    //   5746: invokestatic forName : (Ljava/lang/String;ZLjava/lang/ClassLoader;)Ljava/lang/Class;
    //   5749: invokevirtual getDeclaredFields : ()[Ljava/lang/reflect/Field;
    //   5752: astore #4
    //   5754: aload #4
    //   5756: arraylength
    //   5757: istore #5
    //   5759: iconst_0
    //   5760: istore #6
    //   5762: iload #6
    //   5764: iload #5
    //   5766: if_icmpge -> 5904
    //   5769: aload #4
    //   5771: iload #6
    //   5773: aaload
    //   5774: astore #7
    //   5776: aload #7
    //   5778: invokevirtual getModifiers : ()I
    //   5781: invokestatic isStatic : (I)Z
    //   5784: ifne -> 5794
    //   5787: goto -> 5897
    //   5790: invokestatic a : (Ljava/lang/Throwable;)Ljava/lang/Throwable;
    //   5793: athrow
    //   5794: aload #7
    //   5796: invokevirtual getType : ()Ljava/lang/Class;
    //   5799: astore #8
    //   5801: aload #8
    //   5803: ifnull -> 5884
    //   5806: aload #8
    //   5808: invokevirtual isPrimitive : ()Z
    //   5811: ifne -> 5884
    //   5814: goto -> 5821
    //   5817: invokestatic a : (Ljava/lang/Throwable;)Ljava/lang/Throwable;
    //   5820: athrow
    //   5821: aload #8
    //   5823: invokevirtual getPackage : ()Ljava/lang/Package;
    //   5826: ifnull -> 5884
    //   5829: goto -> 5836
    //   5832: invokestatic a : (Ljava/lang/Throwable;)Ljava/lang/Throwable;
    //   5835: athrow
    //   5836: aload #8
    //   5838: invokevirtual getPackage : ()Ljava/lang/Package;
    //   5841: invokevirtual getName : ()Ljava/lang/String;
    //   5844: ifnull -> 5884
    //   5847: goto -> 5854
    //   5850: invokestatic a : (Ljava/lang/Throwable;)Ljava/lang/Throwable;
    //   5853: athrow
    //   5854: aload #8
    //   5856: invokevirtual getPackage : ()Ljava/lang/Package;
    //   5859: invokevirtual getName : ()Ljava/lang/String;
    //   5862: sipush #-31036
    //   5865: sipush #-18188
    //   5868: invokestatic a : (II)Ljava/lang/String;
    //   5871: invokevirtual startsWith : (Ljava/lang/String;)Z
    //   5874: ifne -> 5884
    //   5877: goto -> 5884
    //   5880: invokestatic a : (Ljava/lang/Throwable;)Ljava/lang/Throwable;
    //   5883: athrow
    //   5884: aload #7
    //   5886: iconst_1
    //   5887: invokevirtual setAccessible : (Z)V
    //   5890: aload #7
    //   5892: aconst_null
    //   5893: invokevirtual get : (Ljava/lang/Object;)Ljava/lang/Object;
    //   5896: pop
    //   5897: iinc #6, 1
    //   5900: iload_2
    //   5901: ifeq -> 5762
    //   5904: sipush #-31027
    //   5907: sipush #-18232
    //   5910: invokestatic a : (II)Ljava/lang/String;
    //   5913: invokestatic forName : (Ljava/lang/String;)Ljava/lang/Class;
    //   5916: invokevirtual getDeclaredMethods : ()[Ljava/lang/reflect/Method;
    //   5919: astore #4
    //   5921: aload #4
    //   5923: arraylength
    //   5924: istore #5
    //   5926: iconst_0
    //   5927: istore #6
    //   5929: iload #6
    //   5931: iload #5
    //   5933: if_icmpge -> 6066
    //   5936: aload #4
    //   5938: iload #6
    //   5940: aaload
    //   5941: astore #7
    //   5943: aload #7
    //   5945: invokevirtual getParameterTypes : ()[Ljava/lang/Class;
    //   5948: pop
    //   5949: aload #7
    //   5951: invokevirtual getModifiers : ()I
    //   5954: invokestatic isStatic : (I)Z
    //   5957: ifeq -> 6052
    //   5960: aload #7
    //   5962: invokevirtual getParameterTypes : ()[Ljava/lang/Class;
    //   5965: arraylength
    //   5966: iconst_2
    //   5967: if_icmpne -> 6052
    //   5970: goto -> 5977
    //   5973: invokestatic a : (Ljava/lang/Throwable;)Ljava/lang/Throwable;
    //   5976: athrow
    //   5977: aload #7
    //   5979: invokevirtual getReturnType : ()Ljava/lang/Class;
    //   5982: getstatic java/lang/Void.TYPE : Ljava/lang/Class;
    //   5985: invokevirtual equals : (Ljava/lang/Object;)Z
    //   5988: ifeq -> 6052
    //   5991: goto -> 5998
    //   5994: invokestatic a : (Ljava/lang/Throwable;)Ljava/lang/Throwable;
    //   5997: athrow
    //   5998: aload #7
    //   6000: iconst_1
    //   6001: invokevirtual setAccessible : (Z)V
    //   6004: aload #7
    //   6006: aconst_null
    //   6007: iconst_2
    //   6008: anewarray java/lang/Object
    //   6011: dup
    //   6012: iconst_0
    //   6013: aload_0
    //   6014: aastore
    //   6015: dup
    //   6016: iconst_1
    //   6017: aload_1
    //   6018: ifnonnull -> 6036
    //   6021: goto -> 6028
    //   6024: invokestatic a : (Ljava/lang/Throwable;)Ljava/lang/Throwable;
    //   6027: athrow
    //   6028: aload_1
    //   6029: goto -> 6043
    //   6032: invokestatic a : (Ljava/lang/Throwable;)Ljava/lang/Throwable;
    //   6035: athrow
    //   6036: aload_1
    //   6037: checkcast [B
    //   6040: invokevirtual clone : ()Ljava/lang/Object;
    //   6043: aastore
    //   6044: invokevirtual invoke : (Ljava/lang/Object;[Ljava/lang/Object;)Ljava/lang/Object;
    //   6047: pop
    //   6048: iload_2
    //   6049: ifeq -> 6066
    //   6052: iinc #6, 1
    //   6055: iload_2
    //   6056: ifeq -> 5929
    //   6059: goto -> 6066
    //   6062: invokestatic a : (Ljava/lang/Throwable;)Ljava/lang/Throwable;
    //   6065: athrow
    //   6066: getstatic burp/Zg3v.Zk : Ljava/lang/Object;
    //   6069: checkcast java/math/BigInteger
    //   6072: invokevirtual intValue : ()I
    //   6075: i2l
    //   6076: invokestatic currentTimeMillis : ()J
    //   6079: ladd
    //   6080: getstatic burp/Zmwx.Zk : Ljava/lang/Object;
    //   6083: checkcast java/math/BigInteger
    //   6086: invokevirtual intValue : ()I
    //   6089: i2l
    //   6090: lcmp
    //   6091: ifge -> 6429
    //   6094: sipush #-31032
    //   6097: sipush #1152
    //   6100: invokestatic a : (II)Ljava/lang/String;
    //   6103: iconst_1
    //   6104: ldc burp/Zkfb
    //   6106: invokevirtual getClassLoader : ()Ljava/lang/ClassLoader;
    //   6109: invokestatic forName : (Ljava/lang/String;ZLjava/lang/ClassLoader;)Ljava/lang/Class;
    //   6112: invokevirtual getDeclaredFields : ()[Ljava/lang/reflect/Field;
    //   6115: astore #4
    //   6117: aload #4
    //   6119: arraylength
    //   6120: istore #5
    //   6122: iconst_0
    //   6123: istore #6
    //   6125: iload #6
    //   6127: iload #5
    //   6129: if_icmpge -> 6267
    //   6132: aload #4
    //   6134: iload #6
    //   6136: aaload
    //   6137: astore #7
    //   6139: aload #7
    //   6141: invokevirtual getModifiers : ()I
    //   6144: invokestatic isStatic : (I)Z
    //   6147: ifne -> 6157
    //   6150: goto -> 6260
    //   6153: invokestatic a : (Ljava/lang/Throwable;)Ljava/lang/Throwable;
    //   6156: athrow
    //   6157: aload #7
    //   6159: invokevirtual getType : ()Ljava/lang/Class;
    //   6162: astore #8
    //   6164: aload #8
    //   6166: ifnull -> 6247
    //   6169: aload #8
    //   6171: invokevirtual isPrimitive : ()Z
    //   6174: ifne -> 6247
    //   6177: goto -> 6184
    //   6180: invokestatic a : (Ljava/lang/Throwable;)Ljava/lang/Throwable;
    //   6183: athrow
    //   6184: aload #8
    //   6186: invokevirtual getPackage : ()Ljava/lang/Package;
    //   6189: ifnull -> 6247
    //   6192: goto -> 6199
    //   6195: invokestatic a : (Ljava/lang/Throwable;)Ljava/lang/Throwable;
    //   6198: athrow
    //   6199: aload #8
    //   6201: invokevirtual getPackage : ()Ljava/lang/Package;
    //   6204: invokevirtual getName : ()Ljava/lang/String;
    //   6207: ifnull -> 6247
    //   6210: goto -> 6217
    //   6213: invokestatic a : (Ljava/lang/Throwable;)Ljava/lang/Throwable;
    //   6216: athrow
    //   6217: aload #8
    //   6219: invokevirtual getPackage : ()Ljava/lang/Package;
    //   6222: invokevirtual getName : ()Ljava/lang/String;
    //   6225: sipush #-31039
    //   6228: sipush #-7340
    //   6231: invokestatic a : (II)Ljava/lang/String;
    //   6234: invokevirtual startsWith : (Ljava/lang/String;)Z
    //   6237: ifne -> 6247
    //   6240: goto -> 6247
    //   6243: invokestatic a : (Ljava/lang/Throwable;)Ljava/lang/Throwable;
    //   6246: athrow
    //   6247: aload #7
    //   6249: iconst_1
    //   6250: invokevirtual setAccessible : (Z)V
    //   6253: aload #7
    //   6255: aconst_null
    //   6256: invokevirtual get : (Ljava/lang/Object;)Ljava/lang/Object;
    //   6259: pop
    //   6260: iinc #6, 1
    //   6263: iload_2
    //   6264: ifeq -> 6125
    //   6267: sipush #-31040
    //   6270: sipush #-22582
    //   6273: invokestatic a : (II)Ljava/lang/String;
    //   6276: invokestatic forName : (Ljava/lang/String;)Ljava/lang/Class;
    //   6279: invokevirtual getDeclaredMethods : ()[Ljava/lang/reflect/Method;
    //   6282: astore #4
    //   6284: aload #4
    //   6286: arraylength
    //   6287: istore #5
    //   6289: iconst_0
    //   6290: istore #6
    //   6292: iload #6
    //   6294: iload #5
    //   6296: if_icmpge -> 6429
    //   6299: aload #4
    //   6301: iload #6
    //   6303: aaload
    //   6304: astore #7
    //   6306: aload #7
    //   6308: invokevirtual getParameterTypes : ()[Ljava/lang/Class;
    //   6311: pop
    //   6312: aload #7
    //   6314: invokevirtual getModifiers : ()I
    //   6317: invokestatic isStatic : (I)Z
    //   6320: ifeq -> 6415
    //   6323: aload #7
    //   6325: invokevirtual getParameterTypes : ()[Ljava/lang/Class;
    //   6328: arraylength
    //   6329: iconst_2
    //   6330: if_icmpne -> 6415
    //   6333: goto -> 6340
    //   6336: invokestatic a : (Ljava/lang/Throwable;)Ljava/lang/Throwable;
    //   6339: athrow
    //   6340: aload #7
    //   6342: invokevirtual getReturnType : ()Ljava/lang/Class;
    //   6345: getstatic java/lang/Void.TYPE : Ljava/lang/Class;
    //   6348: invokevirtual equals : (Ljava/lang/Object;)Z
    //   6351: ifeq -> 6415
    //   6354: goto -> 6361
    //   6357: invokestatic a : (Ljava/lang/Throwable;)Ljava/lang/Throwable;
    //   6360: athrow
    //   6361: aload #7
    //   6363: iconst_1
    //   6364: invokevirtual setAccessible : (Z)V
    //   6367: aload #7
    //   6369: aconst_null
    //   6370: iconst_2
    //   6371: anewarray java/lang/Object
    //   6374: dup
    //   6375: iconst_0
    //   6376: aload_0
    //   6377: aastore
    //   6378: dup
    //   6379: iconst_1
    //   6380: aload_1
    //   6381: ifnonnull -> 6399
    //   6384: goto -> 6391
    //   6387: invokestatic a : (Ljava/lang/Throwable;)Ljava/lang/Throwable;
    //   6390: athrow
    //   6391: aload_1
    //   6392: goto -> 6406
    //   6395: invokestatic a : (Ljava/lang/Throwable;)Ljava/lang/Throwable;
    //   6398: athrow
    //   6399: aload_1
    //   6400: checkcast [B
    //   6403: invokevirtual clone : ()Ljava/lang/Object;
    //   6406: aastore
    //   6407: invokevirtual invoke : (Ljava/lang/Object;[Ljava/lang/Object;)Ljava/lang/Object;
    //   6410: pop
    //   6411: iload_2
    //   6412: ifeq -> 6429
    //   6415: iinc #6, 1
    //   6418: iload_2
    //   6419: ifeq -> 6292
    //   6422: goto -> 6429
    //   6425: invokestatic a : (Ljava/lang/Throwable;)Ljava/lang/Throwable;
    //   6428: athrow
    //   6429: getstatic burp/Zm6g.ZG : Ljava/lang/String;
    //   6432: getstatic burp/Zluk.Zz : Ljava/lang/Object;
    //   6435: checkcast java/math/BigInteger
    //   6438: invokevirtual intValue : ()I
    //   6441: bipush #32
    //   6443: irem
    //   6444: invokestatic abs : (I)I
    //   6447: invokevirtual charAt : (I)C
    //   6450: getstatic burp/Zgx6.ZX : Ljava/lang/String;
    //   6453: getstatic burp/Zge1.ZK : Ljava/lang/Object;
    //   6456: checkcast java/math/BigInteger
    //   6459: invokevirtual intValue : ()I
    //   6462: bipush #32
    //   6464: irem
    //   6465: invokestatic abs : (I)I
    //   6468: invokevirtual charAt : (I)C
    //   6471: if_icmple -> 6578
    //   6474: getstatic burp/Zl55.Zp : Ljava/lang/String;
    //   6477: getstatic burp/Zg_i.ZQ : Ljava/lang/Object;
    //   6480: checkcast java/math/BigInteger
    //   6483: invokevirtual intValue : ()I
    //   6486: bipush #32
    //   6488: irem
    //   6489: invokestatic abs : (I)I
    //   6492: invokevirtual charAt : (I)C
    //   6495: getstatic burp/Zxz_.Zb : Ljava/lang/String;
    //   6498: getstatic burp/Zge1.ZK : Ljava/lang/Object;
    //   6501: checkcast java/math/BigInteger
    //   6504: invokevirtual intValue : ()I
    //   6507: bipush #32
    //   6509: irem
    //   6510: invokestatic abs : (I)I
    //   6513: invokevirtual charAt : (I)C
    //   6516: if_icmple -> 6578
    //   6519: goto -> 6526
    //   6522: invokestatic a : (Ljava/lang/Throwable;)Ljava/lang/Throwable;
    //   6525: athrow
    //   6526: getstatic burp/Zsji.Zr : Ljava/lang/String;
    //   6529: getstatic burp/Zm54.ZS : Ljava/lang/Object;
    //   6532: checkcast java/math/BigInteger
    //   6535: invokevirtual intValue : ()I
    //   6538: bipush #32
    //   6540: irem
    //   6541: invokestatic abs : (I)I
    //   6544: invokevirtual charAt : (I)C
    //   6547: getstatic burp/Zlfg.Zb : Ljava/lang/String;
    //   6550: getstatic burp/Zm54.ZS : Ljava/lang/Object;
    //   6553: checkcast java/math/BigInteger
    //   6556: invokevirtual intValue : ()I
    //   6559: bipush #32
    //   6561: irem
    //   6562: invokestatic abs : (I)I
    //   6565: invokevirtual charAt : (I)C
    //   6568: if_icmple -> 6586
    //   6571: goto -> 6578
    //   6574: invokestatic a : (Ljava/lang/Throwable;)Ljava/lang/Throwable;
    //   6577: athrow
    //   6578: iconst_1
    //   6579: goto -> 6587
    //   6582: invokestatic a : (Ljava/lang/Throwable;)Ljava/lang/Throwable;
    //   6585: athrow
    //   6586: iconst_0
    //   6587: ireturn
    //   6588: astore_3
    //   6589: new java/lang/Exception
    //   6592: dup
    //   6593: aload_3
    //   6594: invokevirtual getMessage : ()Ljava/lang/String;
    //   6597: invokespecial <init> : (Ljava/lang/String;)V
    //   6600: athrow
    // Exception table:
    //   from	to	target	type
    //   4	6587	6588	java/lang/Throwable
    //   22	198	201	java/lang/Throwable
    //   168	235	238	java/lang/Throwable
    //   205	272	275	java/lang/Throwable
    //   242	309	312	java/lang/Throwable
    //   279	346	349	java/lang/Throwable
    //   316	383	386	java/lang/Throwable
    //   353	420	423	java/lang/Throwable
    //   390	457	460	java/lang/Throwable
    //   427	494	497	java/lang/Throwable
    //   464	531	534	java/lang/Throwable
    //   501	568	571	java/lang/Throwable
    //   538	605	608	java/lang/Throwable
    //   575	642	645	java/lang/Throwable
    //   612	679	682	java/lang/Throwable
    //   649	716	719	java/lang/Throwable
    //   686	753	756	java/lang/Throwable
    //   723	790	793	java/lang/Throwable
    //   760	827	830	java/lang/Throwable
    //   797	864	867	java/lang/Throwable
    //   834	901	904	java/lang/Throwable
    //   871	938	941	java/lang/Throwable
    //   908	975	978	java/lang/Throwable
    //   945	1012	1015	java/lang/Throwable
    //   982	1049	1052	java/lang/Throwable
    //   1019	1086	1089	java/lang/Throwable
    //   1056	1123	1126	java/lang/Throwable
    //   1093	1160	1163	java/lang/Throwable
    //   1130	1197	1200	java/lang/Throwable
    //   1167	1234	1237	java/lang/Throwable
    //   1204	1271	1274	java/lang/Throwable
    //   1241	1308	1311	java/lang/Throwable
    //   1278	1341	1344	java/lang/Throwable
    //   4666	4691	4691	java/lang/Throwable
    //   5658	5684	5684	java/lang/Throwable
    //   5776	5790	5790	java/lang/Throwable
    //   5801	5814	5817	java/lang/Throwable
    //   5806	5829	5832	java/lang/Throwable
    //   5821	5847	5850	java/lang/Throwable
    //   5836	5877	5880	java/lang/Throwable
    //   5943	5970	5973	java/lang/Throwable
    //   5960	5991	5994	java/lang/Throwable
    //   5977	6021	6024	java/lang/Throwable
    //   5998	6032	6032	java/lang/Throwable
    //   6043	6059	6062	java/lang/Throwable
    //   6139	6153	6153	java/lang/Throwable
    //   6164	6177	6180	java/lang/Throwable
    //   6169	6192	6195	java/lang/Throwable
    //   6184	6210	6213	java/lang/Throwable
    //   6199	6240	6243	java/lang/Throwable
    //   6306	6333	6336	java/lang/Throwable
    //   6323	6354	6357	java/lang/Throwable
    //   6340	6384	6387	java/lang/Throwable
    //   6361	6395	6395	java/lang/Throwable
    //   6406	6422	6425	java/lang/Throwable
    //   6429	6519	6522	java/lang/Throwable
    //   6474	6571	6574	java/lang/Throwable
    //   6526	6582	6582	java/lang/Throwable
  }
  
  static void Zr(Object[] paramArrayOfObject, Object paramObject) throws Throwable {}
  
  static void ZC(Object paramObject) {
    Zr3j.Zj = a(-31034, 16960);
    Zr3j.ZT = new BigInteger(a(-31030, -25746));
    boolean bool = Zt2e.ZN();
    try {
      try {
        if (Zxz_.Zb.charAt(Math.abs(((BigInteger)Zmou.ZT).intValue() % 32)) <= Zxz_.Zb.charAt(Math.abs(((BigInteger)Ze0z.ZQ).intValue() % 32))) {
          try {
            Zeyd.ZJ(Class.forName(a(-31026, 30137)));
            if (!bool)
              Zk12.ZP(Class.forName(a(-31029, -7743))); 
          } catch (Throwable throwable) {
            throw a(null);
          } 
          return;
        } 
      } catch (Throwable throwable) {
        throw a(null);
      } 
      Zk12.ZP(Class.forName(a(-31029, -7743)));
    } catch (Throwable throwable) {}
  }
  
  static {
    // Byte code:
    //   0: bipush #14
    //   2: anewarray java/lang/String
    //   5: astore #5
    //   7: iconst_0
    //   8: istore_3
    //   9: ldc 'bPv\\tD6t\\tTe`B6\\t57Q7>i>5]fE\\t0W\\rM_, Fcu!f#v~RT^Dm|Mr]X[:BMP!`uMXK&z,Fe!/f>^og($3, e|a68]{\\flc\\t{@:E\\tu7> \w}q(N'&EF0Ocz"k8y! VkweI3<ekONp$tXi'
    //   11: dup
    //   12: astore_2
    //   13: invokevirtual length : ()I
    //   16: istore #4
    //   18: bipush #19
    //   20: istore_1
    //   21: iconst_m1
    //   22: istore_0
    //   23: bipush #34
    //   25: iinc #0, 1
    //   28: aload_2
    //   29: iload_0
    //   30: dup
    //   31: iload_1
    //   32: iadd
    //   33: invokevirtual substring : (II)Ljava/lang/String;
    //   36: iconst_m1
    //   37: goto -> 143
    //   40: aload #5
    //   42: swap
    //   43: iload_3
    //   44: iinc #3, 1
    //   47: swap
    //   48: aastore
    //   49: iload_0
    //   50: iload_1
    //   51: iadd
    //   52: dup
    //   53: istore_0
    //   54: iload #4
    //   56: if_icmpge -> 68
    //   59: aload_2
    //   60: iload_0
    //   61: invokevirtual charAt : (I)C
    //   64: istore_1
    //   65: goto -> 23
    //   68: ldc 'Q!P.+'
    //   70: dup
    //   71: astore_2
    //   72: invokevirtual length : ()I
    //   75: istore #4
    //   77: bipush #9
    //   79: istore_1
    //   80: iconst_m1
    //   81: istore_0
    //   82: bipush #114
    //   84: iinc #0, 1
    //   87: aload_2
    //   88: iload_0
    //   89: dup
    //   90: iload_1
    //   91: iadd
    //   92: invokevirtual substring : (II)Ljava/lang/String;
    //   95: iconst_0
    //   96: goto -> 143
    //   99: aload #5
    //   101: swap
    //   102: iload_3
    //   103: iinc #3, 1
    //   106: swap
    //   107: aastore
    //   108: iload_0
    //   109: iload_1
    //   110: iadd
    //   111: dup
    //   112: istore_0
    //   113: iload #4
    //   115: if_icmpge -> 127
    //   118: aload_2
    //   119: iload_0
    //   120: invokevirtual charAt : (I)C
    //   123: istore_1
    //   124: goto -> 82
    //   127: aload #5
    //   129: putstatic burp/Zstq.a : [Ljava/lang/String;
    //   132: bipush #14
    //   134: anewarray java/lang/String
    //   137: putstatic burp/Zstq.b : [Ljava/lang/String;
    //   140: goto -> 300
    //   143: dup_x2
    //   144: pop
    //   145: invokevirtual toCharArray : ()[C
    //   148: dup_x1
    //   149: arraylength
    //   150: dup_x2
    //   151: pop
    //   152: iconst_0
    //   153: istore #6
    //   155: dup2_x1
    //   156: pop2
    //   157: dup_x2
    //   158: iconst_1
    //   159: if_icmpgt -> 260
    //   162: dup2
    //   163: swap
    //   164: iload #6
    //   166: dup2_x1
    //   167: caload
    //   168: swap
    //   169: iload #6
    //   171: bipush #7
    //   173: irem
    //   174: tableswitch default -> 242, 0 -> 212, 1 -> 217, 2 -> 222, 3 -> 227, 4 -> 232, 5 -> 237
    //   212: bipush #27
    //   214: goto -> 244
    //   217: bipush #74
    //   219: goto -> 244
    //   222: bipush #114
    //   224: goto -> 244
    //   227: bipush #51
    //   229: goto -> 244
    //   232: bipush #107
    //   234: goto -> 244
    //   237: bipush #57
    //   239: goto -> 244
    //   242: bipush #125
    //   244: ixor
    //   245: ixor
    //   246: i2c
    //   247: castore
    //   248: iinc #6, 1
    //   251: dup
    //   252: ifne -> 260
    //   255: dup2
    //   256: dup_x1
    //   257: goto -> 166
    //   260: dup2_x1
    //   261: pop2
    //   262: dup_x2
    //   263: iload #6
    //   265: if_icmpgt -> 162
    //   268: pop
    //   269: new java/lang/String
    //   272: dup_x1
    //   273: swap
    //   274: invokespecial <init> : ([C)V
    //   277: invokevirtual intern : ()Ljava/lang/String;
    //   280: swap
    //   281: pop
    //   282: swap
    //   283: tableswitch default -> 40, 0 -> 99
    //   300: sipush #-31033
    //   303: sipush #17517
    //   306: invokestatic a : (II)Ljava/lang/String;
    //   309: putstatic burp/Zstq.ZL : Ljava/lang/String;
    //   312: new java/math/BigInteger
    //   315: dup
    //   316: sipush #-31031
    //   319: sipush #1924
    //   322: invokestatic a : (II)Ljava/lang/String;
    //   325: invokespecial <init> : (Ljava/lang/String;)V
    //   328: putstatic burp/Zstq.Zf : Ljava/lang/Object;
    //   331: return
  }
  
  private static Throwable a(Throwable paramThrowable) {
    return paramThrowable;
  }
  
  private static String a(int paramInt1, int paramInt2) {
    int i = (paramInt1 ^ 0xFFFF86CC) & 0xFFFF;
    if (b[i] == null) {
      char[] arrayOfChar = a[i].toCharArray();
      switch (arrayOfChar[0] & 0xFF) {
        case 0:
        
        case 1:
        
        case 2:
        
        case 3:
        
        case 4:
        
        case 5:
        
        case 6:
        
        case 7:
        
        case 8:
        
        case 9:
        
        case 10:
        
        case 11:
        
        case 12:
        
        case 13:
        
        case 14:
        
        case 15:
        
        case 16:
        
        case 17:
        
        case 18:
        
        case 19:
        
        case 20:
        
        case 21:
        
        case 22:
        
        case 23:
        
        case 24:
        
        case 25:
        
        case 26:
        
        case 27:
        
        case 28:
        
        case 29:
        
        case 30:
        
        case 31:
        
        case 32:
        
        case 33:
        
        case 34:
        
        case 35:
        
        case 36:
        
        case 37:
        
        case 38:
        
        case 39:
        
        case 40:
        
        case 41:
        
        case 42:
        
        case 43:
        
        case 44:
        
        case 45:
        
        case 46:
        
        case 47:
        
        case 48:
        
        case 49:
        
        case 50:
        
        case 51:
        
        case 52:
        
        case 53:
        
        case 54:
        
        case 55:
        
        case 56:
        
        case 57:
        
        case 58:
        
        case 59:
        
        case 60:
        
        case 61:
        
        case 62:
        
        case 63:
        
        case 64:
        
        case 65:
        
        case 66:
        
        case 67:
        
        case 68:
        
        case 69:
        
        case 70:
        
        case 71:
        
        case 72:
        
        case 73:
        
        case 74:
        
        case 75:
        
        case 76:
        
        case 77:
        
        case 78:
        
        case 79:
        
        case 80:
        
        case 81:
        
        case 82:
        
        case 83:
        
        case 84:
        
        case 85:
        
        case 86:
        
        case 87:
        
        case 88:
        
        case 89:
        
        case 90:
        
        case 91:
        
        case 92:
        
        case 93:
        
        case 94:
        
        case 95:
        
        case 96:
        
        case 97:
        
        case 98:
        
        case 99:
        
        case 100:
        
        case 101:
        
        case 102:
        
        case 103:
        
        case 104:
        
        case 105:
        
        case 106:
        
        case 107:
        
        case 108:
        
        case 109:
        
        case 110:
        
        case 111:
        
        case 112:
        
        case 113:
        
        case 114:
        
        case 115:
        
        case 116:
        
        case 117:
        
        case 118:
        
        case 119:
        
        case 120:
        
        case 121:
        
        case 122:
        
        case 123:
        
        case 124:
        
        case 125:
        
        case 126:
        
        case 127:
        
        case 128:
        
        case 129:
        
        case 130:
        
        case 131:
        
        case 132:
        
        case 133:
        
        case 134:
        
        case 135:
        
        case 136:
        
        case 137:
        
        case 138:
        
        case 139:
        
        case 140:
        
        case 141:
        
        case 142:
        
        case 143:
        
        case 144:
        
        case 145:
        
        case 146:
        
        case 147:
        
        case 148:
        
        case 149:
        
        case 150:
        
        case 151:
        
        case 152:
        
        case 153:
        
        case 154:
        
        case 155:
        
        case 156:
        
        case 157:
        
        case 158:
        
        case 159:
        
        case 160:
        
        case 161:
        
        case 162:
        
        case 163:
        
        case 164:
        
        case 165:
        
        case 166:
        
        case 167:
        
        case 168:
        
        case 169:
        
        case 170:
        
        case 171:
        
        case 172:
        
        case 173:
        
        case 174:
        
        case 175:
        
        case 176:
        
        case 177:
        
        case 178:
        
        case 179:
        
        case 180:
        
        case 181:
        
        case 182:
        
        case 183:
        
        case 184:
        
        case 185:
        
        case 186:
        
        case 187:
        
        case 188:
        
        case 189:
        
        case 190:
        
        case 191:
        
        case 192:
        
        case 193:
        
        case 194:
        
        case 195:
        
        case 196:
        
        case 197:
        
        case 198:
        
        case 199:
        
        case 200:
        
        case 201:
        
        case 202:
        
        case 203:
        
        case 204:
        
        case 205:
        
        case 206:
        
        case 207:
        
        case 208:
        
        case 209:
        
        case 210:
        
        case 211:
        
        case 212:
        
        case 213:
        
        case 214:
        
        case 215:
        
        case 216:
        
        case 217:
        
        case 218:
        
        case 219:
        
        case 220:
        
        case 221:
        
        case 222:
        
        case 223:
        
        case 224:
        
        case 225:
        
        case 226:
        
        case 227:
        
        case 228:
        
        case 229:
        
        case 230:
        
        case 231:
        
        case 232:
        
        case 233:
        
        case 234:
        
        case 235:
        
        case 236:
        
        case 237:
        
        case 238:
        
        case 239:
        
        case 240:
        
        case 241:
        
        case 242:
        
        case 243:
        
        case 244:
        
        case 245:
        
        case 246:
        
        case 247:
        
        case 248:
        
        case 249:
        
        case 250:
        
        case 251:
        
        case 252:
        
        case 253:
        
        case 254:
        
        default:
          break;
      } 
      byte b1 = 93;
      int j = (paramInt2 & 0xFF) - b1;
      if (j < 0)
        j += 256; 
      int k = ((paramInt2 & 0xFFFF) >>> 8) - b1;
      if (k < 0)
        k += 256; 
      for (byte b2 = 0; b2 < arrayOfChar.length; b2++) {
        int m = b2 % 2;
        if (m == 0) {
          arrayOfChar[b2] = (char)(arrayOfChar[b2] ^ j);
          j = ((j >>> 3 | j << 5) ^ arrayOfChar[b2]) & 0xFF;
        } else {
          arrayOfChar[b2] = (char)(arrayOfChar[b2] ^ k);
          k = ((k >>> 3 | k << 5) ^ arrayOfChar[b2]) & 0xFF;
        } 
      } 
      b[i] = (new String(arrayOfChar)).intern();
    } 
    return b[i];
  }
}


/* Location:              C:\Program Files\BurpSuitePro\burpsuite_pro.jar!\burp\Zstq.class
 * Java compiler version: 21 (65.0)
 * JD-Core Version:       1.1.3
 */