package burp;

import burp.api.montoya.internal.MontoyaObjectFactory;
import java.awt.Window;
import java.util.List;
import java.util.Optional;
import net.portswigger.Zah;
import net.portswigger.Zk_;
import net.portswigger.Zm2;

public class Zsu_<T extends Zmw9<T>> implements Zbw_<T> {
  private final List<Zm3g> ZJ;
  
  private final Zt4u ZA;
  
  private final Zerg Zj;
  
  private final Zkrw Zv;
  
  private final Ztwv ZD;
  
  private final Zlb7 ZP;
  
  private final Zbnt ZG;
  
  private final Zkl6 ZO;
  
  private final Zr_4 ZR;
  
  private final Zr_4 Zf;
  
  private final Zmw3 Zx;
  
  private final Ztpu ZE;
  
  private final Zslu Za;
  
  private final Zz4u Zq;
  
  private final Zbsd ZH;
  
  private final Zema Zi;
  
  private final Zmue Zh;
  
  private final Zznz ZV;
  
  private final Ze47 Ze;
  
  private final Zbp5 ZY;
  
  private Zekl Zc;
  
  private Zbes ZB;
  
  private Zbep Zl;
  
  private Zbep ZL;
  
  private Zbeq Zg;
  
  private Zbei Zy;
  
  private Zbe4 Zs;
  
  private Zbe2 ZM;
  
  private Zbe9 Zb;
  
  private Zbeu Zw;
  
  private Zbe1 Zp;
  
  private Zbe3 Z_;
  
  private Zbeh Zk;
  
  private Zzp8<Zeo2> ZT;
  
  private Zzp8<Zzh2> ZN;
  
  private Zgr_ ZK;
  
  private Zev Zn;
  
  private Zg0u Zr;
  
  private Zg0i Zo;
  
  private Ze9y ZS;
  
  private Zmkr Zm;
  
  private Zzu8 Zz;
  
  private Zgjf ZW;
  
  private Zza2 ZQ;
  
  private static final String[] a;
  
  private static final String[] b;
  
  public Zsu_(Zz0n paramZz0n, Zt4u paramZt4u, Zerg paramZerg, Zgbj paramZgbj, Zgb6 paramZgb6, Zkrw paramZkrw, Zskh paramZskh, Zslu paramZslu, Zkl6 paramZkl6, Zlod paramZlod, Zxp6 paramZxp6, Ztwv paramZtwv, Zr_4 paramZr_41, Zr_4 paramZr_42, Ze6o paramZe6o, Ztyg paramZtyg, Zgq7 paramZgq7, Ztdq paramZtdq, Zm6v paramZm6v, Zr1m paramZr1m, Ztpu paramZtpu, Zekl paramZekl, Zgr_ paramZgr_, Zz_r paramZz_r, Ze8b paramZe8b, Zbiv paramZbiv, Zkn paramZkn, Zbp5 paramZbp5, Zbsd paramZbsd, String paramString, Zzen paramZzen, Zr34 paramZr34, Zrz paramZrz, Zrid paramZrid, Zs0n paramZs0n, MontoyaObjectFactory paramMontoyaObjectFactory, Zz4u paramZz4u, Zb_j paramZb_j, Zs6i paramZs6i, Zm6x paramZm6x, Zs2p paramZs2p) {
    // Byte code:
    //   0: aload_0
    //   1: invokespecial <init> : ()V
    //   4: invokestatic ZI : ()I
    //   7: aload_0
    //   8: new java/util/ArrayList
    //   11: dup
    //   12: invokespecial <init> : ()V
    //   15: putfield ZJ : Ljava/util/List;
    //   18: istore #42
    //   20: aload_3
    //   21: ifnull -> 28
    //   24: iconst_1
    //   25: goto -> 29
    //   28: iconst_0
    //   29: getstatic net/portswigger/Zqf.Zv : Lnet/portswigger/Zqf;
    //   32: lconst_0
    //   33: invokestatic Zv : (ZLnet/portswigger/Zqf;J)V
    //   36: aload #4
    //   38: ifnull -> 45
    //   41: iconst_1
    //   42: goto -> 46
    //   45: iconst_0
    //   46: getstatic net/portswigger/Zqf.Zv : Lnet/portswigger/Zqf;
    //   49: lconst_1
    //   50: invokestatic Zv : (ZLnet/portswigger/Zqf;J)V
    //   53: aload #6
    //   55: ifnull -> 62
    //   58: iconst_1
    //   59: goto -> 63
    //   62: iconst_0
    //   63: getstatic net/portswigger/Zqf.Zv : Lnet/portswigger/Zqf;
    //   66: ldc2_w 2
    //   69: invokestatic Zv : (ZLnet/portswigger/Zqf;J)V
    //   72: aload #9
    //   74: ifnull -> 81
    //   77: iconst_1
    //   78: goto -> 82
    //   81: iconst_0
    //   82: getstatic net/portswigger/Zqf.Zv : Lnet/portswigger/Zqf;
    //   85: ldc2_w 3
    //   88: invokestatic Zv : (ZLnet/portswigger/Zqf;J)V
    //   91: aload #10
    //   93: ifnull -> 100
    //   96: iconst_1
    //   97: goto -> 101
    //   100: iconst_0
    //   101: getstatic net/portswigger/Zqf.Zv : Lnet/portswigger/Zqf;
    //   104: ldc2_w 4
    //   107: invokestatic Zv : (ZLnet/portswigger/Zqf;J)V
    //   110: aload #11
    //   112: ifnull -> 119
    //   115: iconst_1
    //   116: goto -> 120
    //   119: iconst_0
    //   120: getstatic net/portswigger/Zqf.Zv : Lnet/portswigger/Zqf;
    //   123: ldc2_w 5
    //   126: invokestatic Zv : (ZLnet/portswigger/Zqf;J)V
    //   129: aload #12
    //   131: ifnull -> 138
    //   134: iconst_1
    //   135: goto -> 139
    //   138: iconst_0
    //   139: getstatic net/portswigger/Zqf.Zv : Lnet/portswigger/Zqf;
    //   142: ldc2_w 6
    //   145: invokestatic Zv : (ZLnet/portswigger/Zqf;J)V
    //   148: aload #14
    //   150: ifnull -> 157
    //   153: iconst_1
    //   154: goto -> 158
    //   157: iconst_0
    //   158: getstatic net/portswigger/Zqf.Zv : Lnet/portswigger/Zqf;
    //   161: ldc2_w 7
    //   164: invokestatic Zv : (ZLnet/portswigger/Zqf;J)V
    //   167: aload_0
    //   168: aload_2
    //   169: putfield ZA : Lburp/Zt4u;
    //   172: aload_0
    //   173: aload_3
    //   174: putfield Zj : Lburp/Zerg;
    //   177: aload_0
    //   178: aload #6
    //   180: putfield Zv : Lburp/Zkrw;
    //   183: aload_0
    //   184: aload #12
    //   186: putfield ZD : Lburp/Ztwv;
    //   189: aload_0
    //   190: aload #8
    //   192: putfield Za : Lburp/Zslu;
    //   195: aload_0
    //   196: aload #21
    //   198: putfield ZE : Lburp/Ztpu;
    //   201: aload_0
    //   202: aload #22
    //   204: putfield Zc : Lburp/Zekl;
    //   207: aload_0
    //   208: aload #23
    //   210: putfield ZK : Lburp/Zgr_;
    //   213: aload_0
    //   214: aload #9
    //   216: putfield ZO : Lburp/Zkl6;
    //   219: aload_0
    //   220: aload #13
    //   222: putfield Zf : Lburp/Zr_4;
    //   225: aload_0
    //   226: aload #14
    //   228: putfield ZR : Lburp/Zr_4;
    //   231: aload_0
    //   232: aload #29
    //   234: putfield ZH : Lburp/Zbsd;
    //   237: aload_0
    //   238: aload #37
    //   240: putfield Zq : Lburp/Zz4u;
    //   243: aload_0
    //   244: aload #28
    //   246: putfield ZY : Lburp/Zbp5;
    //   249: aload_0
    //   250: aload #9
    //   252: invokeinterface ZB : ()Lburp/Zbnt;
    //   257: putfield ZG : Lburp/Zbnt;
    //   260: new burp/Zzwu
    //   263: dup
    //   264: aload #22
    //   266: aload #8
    //   268: invokespecial <init> : (Lburp/Zekl;Lburp/Zz28;)V
    //   271: astore #43
    //   273: new burp/Zr3p
    //   276: dup
    //   277: aload #12
    //   279: aload #28
    //   281: invokespecial <init> : (Lburp/Ztwv;Lburp/Zbp5;)V
    //   284: astore #44
    //   286: new burp/Zzw0
    //   289: dup
    //   290: aload #12
    //   292: aload_1
    //   293: invokeinterface ZP : ()Lburp/Zrgd;
    //   298: invokespecial <init> : (Lburp/Ztwv;Lburp/Zrgd;)V
    //   301: astore #45
    //   303: new burp/Zmdb
    //   306: dup
    //   307: aload #12
    //   309: aload_1
    //   310: invokeinterface ZP : ()Lburp/Zrgd;
    //   315: aload_1
    //   316: invokeinterface ZU : ()Lnet/portswigger/Zsy;
    //   321: aload #9
    //   323: invokeinterface ZM : ()Lburp/Ztbb;
    //   328: aload #9
    //   330: invokeinterface ZB : ()Lburp/Zbnt;
    //   335: aload #31
    //   337: invokespecial <init> : (Lburp/Ztwv;Lburp/Zrgd;Lnet/portswigger/Zsy;Lburp/Ztbb;Lburp/Zbnt;Lburp/Zzen;)V
    //   340: astore #46
    //   342: new burp/Zlcx
    //   345: dup
    //   346: aload #28
    //   348: invokespecial <init> : (Lburp/Zbp5;)V
    //   351: astore #47
    //   353: aload_0
    //   354: new burp/Ze47
    //   357: dup
    //   358: aload #9
    //   360: invokeinterface ZM : ()Lburp/Ztbb;
    //   365: aload #5
    //   367: dup
    //   368: invokestatic requireNonNull : (Ljava/lang/Object;)Ljava/lang/Object;
    //   371: pop
    //   372: <illegal opcode> get : (Lburp/Zgb6;)Ljava/util/function/Supplier;
    //   377: invokespecial <init> : (Lburp/Ztbb;Ljava/util/function/Supplier;)V
    //   380: putfield Ze : Lburp/Ze47;
    //   383: aload_0
    //   384: new burp/Zlb7
    //   387: dup
    //   388: aload_1
    //   389: invokeinterface ZP : ()Lburp/Zrgd;
    //   394: aload_0
    //   395: aload #9
    //   397: aload #5
    //   399: aload #7
    //   401: aload #43
    //   403: aload #12
    //   405: aload #27
    //   407: aload #44
    //   409: aload #30
    //   411: aload #15
    //   413: aload #45
    //   415: aload #46
    //   417: aload #40
    //   419: new burp/Zs_y
    //   422: dup
    //   423: aload #41
    //   425: aload #8
    //   427: invokespecial <init> : (Lburp/Zs2p;Lburp/Zz28;)V
    //   430: aload #47
    //   432: aload_0
    //   433: getfield Ze : Lburp/Ze47;
    //   436: invokespecial <init> : (Lburp/Zrgd;Lburp/Zbw_;Lburp/Zkl6;Lburp/Zgb6;Lburp/Zskh;Lburp/Zzxf;Lburp/Ztwv;Lburp/Zkn;Lburp/Zr3p;Ljava/lang/String;Lburp/Ze6o;Lburp/Zzw0;Lburp/Zmdb;Lburp/Zm6x;Lburp/Zs_y;Lburp/Zlcx;Lburp/Ze47;)V
    //   439: putfield ZP : Lburp/Zlb7;
    //   442: aload_0
    //   443: new burp/Zgjf
    //   446: dup
    //   447: aload #6
    //   449: aload_0
    //   450: aload #11
    //   452: invokeinterface Zy3 : ()Lburp/Zefg;
    //   457: aload #9
    //   459: aload #12
    //   461: aload #14
    //   463: aload_0
    //   464: getfield ZP : Lburp/Zlb7;
    //   467: aload #46
    //   469: new burp/Ze_h
    //   472: dup
    //   473: invokespecial <init> : ()V
    //   476: invokespecial <init> : (Lburp/Zkrw;Lburp/Zbw_;Lburp/Zefg;Lburp/Zkl6;Lburp/Ztwv;Lburp/Zr_4;Lburp/Zlb7;Lburp/Zmxj;Lburp/Ze_h;)V
    //   479: putfield ZW : Lburp/Zgjf;
    //   482: aload_0
    //   483: new burp/Ze9y
    //   486: dup
    //   487: aload_0
    //   488: aload #9
    //   490: aload #11
    //   492: aload #14
    //   494: aload #8
    //   496: invokespecial <init> : (Lburp/Zbw_;Lburp/Zkl6;Lburp/Zxp6;Lburp/Zr_4;Lburp/Zz28;)V
    //   499: putfield ZS : Lburp/Ze9y;
    //   502: new java/util/concurrent/atomic/AtomicReference
    //   505: dup
    //   506: invokespecial <init> : ()V
    //   509: astore #48
    //   511: aload_0
    //   512: new burp/Zg0u
    //   515: dup
    //   516: aload_1
    //   517: invokeinterface ZP : ()Lburp/Zrgd;
    //   522: aload #10
    //   524: aload #24
    //   526: aload #22
    //   528: aload #5
    //   530: aload #43
    //   532: aload #14
    //   534: aload #15
    //   536: aload #9
    //   538: aload_0
    //   539: getfield ZG : Lburp/Zbnt;
    //   542: aload #4
    //   544: new burp/Zswv
    //   547: dup
    //   548: aload #10
    //   550: invokeinterface ZGl : ()Lburp/Zefg;
    //   555: aload #14
    //   557: <illegal opcode> test : (Lburp/Zr_4;)Ljava/util/function/Predicate;
    //   562: aload #14
    //   564: <illegal opcode> apply : (Lburp/Zr_4;)Ljava/util/function/Function;
    //   569: invokespecial <init> : (Lburp/Zefg;Ljava/util/function/Predicate;Ljava/util/function/Function;)V
    //   572: aload #40
    //   574: invokespecial <init> : (Lburp/Zrgd;Lburp/Zlod;Lburp/Zz_r;Lburp/Zekl;Lburp/Zgb6;Lburp/Zzxf;Lburp/Zr_4;Lburp/Ze6o;Lburp/Zkl6;Lburp/Zbnt;Lburp/Zgbj;Lburp/Zswv;Lburp/Zm6x;)V
    //   577: putfield Zr : Lburp/Zg0u;
    //   580: new java/util/concurrent/atomic/AtomicReference
    //   583: dup
    //   584: invokespecial <init> : ()V
    //   587: astore #49
    //   589: aload_0
    //   590: new burp/Zg0i
    //   593: dup
    //   594: aload #10
    //   596: aload #22
    //   598: aload #43
    //   600: aload #28
    //   602: aload #47
    //   604: aload_0
    //   605: getfield ZG : Lburp/Zbnt;
    //   608: aload #14
    //   610: aload #15
    //   612: aload_1
    //   613: invokeinterface ZU : ()Lnet/portswigger/Zsy;
    //   618: aload_1
    //   619: invokeinterface ZP : ()Lburp/Zrgd;
    //   624: new burp/Zswv
    //   627: dup
    //   628: aload #10
    //   630: invokeinterface ZGW : ()Lburp/Zefg;
    //   635: <illegal opcode> test : ()Ljava/util/function/Predicate;
    //   640: invokestatic identity : ()Ljava/util/function/Function;
    //   643: invokespecial <init> : (Lburp/Zefg;Ljava/util/function/Predicate;Ljava/util/function/Function;)V
    //   646: aload #40
    //   648: invokespecial <init> : (Lburp/Zlod;Lburp/Zekl;Lburp/Zzxf;Lburp/Zbp5;Lburp/Zze3;Lburp/Zbnt;Lburp/Zr_4;Lburp/Ze6o;Lnet/portswigger/Zsy;Lburp/Zrgd;Lburp/Zswv;Lburp/Zm6x;)V
    //   651: putfield Zo : Lburp/Zg0i;
    //   654: aload_0
    //   655: new burp/Zmkr
    //   658: dup
    //   659: aload_1
    //   660: invokeinterface ZD : ()Lburp/Zb0h;
    //   665: invokespecial <init> : (Lburp/Zb0h;)V
    //   668: putfield Zm : Lburp/Zmkr;
    //   671: aload_0
    //   672: new burp/Zzu8
    //   675: dup
    //   676: aload_1
    //   677: invokeinterface ZD : ()Lburp/Zb0h;
    //   682: invokespecial <init> : (Lburp/Zb0h;)V
    //   685: putfield Zz : Lburp/Zzu8;
    //   688: aload_0
    //   689: aload #23
    //   691: invokevirtual ZF : (Lburp/Zm3g;)V
    //   694: aload_0
    //   695: new burp/Zema
    //   698: dup
    //   699: invokespecial <init> : ()V
    //   702: putfield Zi : Lburp/Zema;
    //   705: aload_0
    //   706: new burp/Zznz
    //   709: dup
    //   710: invokespecial <init> : ()V
    //   713: putfield ZV : Lburp/Zznz;
    //   716: aload_0
    //   717: new burp/Zmue
    //   720: dup
    //   721: aload_0
    //   722: getfield ZV : Lburp/Zznz;
    //   725: aload #28
    //   727: invokespecial <init> : (Lburp/Zkuc;Lburp/Zswu;)V
    //   730: putfield Zh : Lburp/Zmue;
    //   733: new burp/Zds
    //   736: dup
    //   737: aload #6
    //   739: aload #40
    //   741: invokespecial <init> : (Lburp/Zkrw;Lburp/Zm6x;)V
    //   744: pop
    //   745: aload_0
    //   746: new burp/Zbeh
    //   749: dup
    //   750: aload #14
    //   752: aload_1
    //   753: invokeinterface ZP : ()Lburp/Zrgd;
    //   758: aload_0
    //   759: aload_0
    //   760: getfield Zi : Lburp/Zema;
    //   763: aload #22
    //   765: aload_3
    //   766: aload #6
    //   768: aload #5
    //   770: aload #8
    //   772: aload_0
    //   773: getfield ZG : Lburp/Zbnt;
    //   776: aload #9
    //   778: aload #16
    //   780: aload #17
    //   782: aload_0
    //   783: aload #6
    //   785: aload #30
    //   787: <illegal opcode> Zp : (Lburp/Zsu_;Lburp/Zkrw;Ljava/lang/String;)Lburp/Zxs0;
    //   792: aload #28
    //   794: aload #26
    //   796: aload #37
    //   798: aload #40
    //   800: aload #23
    //   802: aload_0
    //   803: getfield Zh : Lburp/Zmue;
    //   806: aload #38
    //   808: invokespecial <init> : (Lburp/Zr_4;Lburp/Zrgd;Lburp/Zbw_;Lburp/Zmf9;Lburp/Zekl;Lburp/Zerg;Lburp/Zkrw;Lburp/Zgb6;Lburp/Zslu;Lburp/Zbnt;Lburp/Zkl6;Lburp/Ztyg;Lburp/Zgq7;Lburp/Zxs0;Lburp/Zbp5;Lburp/Zbiv;Lburp/Zsza;Lburp/Zm6x;Lburp/Zgr_;Lburp/Zmue;Lburp/Zb_j;)V
    //   811: putfield Zk : Lburp/Zbeh;
    //   814: new burp/Zles
    //   817: dup
    //   818: aload_1
    //   819: aload_2
    //   820: aload #13
    //   822: aload_3
    //   823: aload #4
    //   825: aload #5
    //   827: aload #19
    //   829: aload #11
    //   831: invokeinterface Zyt : ()Lburp/Zzt9;
    //   836: aload #10
    //   838: invokeinterface ZG2 : ()Lburp/Zefg;
    //   843: aload #7
    //   845: aload #8
    //   847: aload #26
    //   849: aload #12
    //   851: aload_0
    //   852: getfield Zr : Lburp/Zg0u;
    //   855: aload #16
    //   857: aload #17
    //   859: aload #34
    //   861: aload #9
    //   863: aload_0
    //   864: getfield ZG : Lburp/Zbnt;
    //   867: aload #25
    //   869: aload #18
    //   871: aload #35
    //   873: aload #36
    //   875: aload #6
    //   877: aload #37
    //   879: aload #38
    //   881: aload #40
    //   883: aload #14
    //   885: aload #39
    //   887: invokespecial <init> : (Lburp/Zz0n;Lburp/Zt4u;Lburp/Zr_4;Lburp/Zerg;Lburp/Zgbj;Lburp/Zgb6;Lburp/Zm6v;Lburp/Zzt9;Lburp/Zefg;Lburp/Zskh;Lburp/Zslu;Lburp/Zbiv;Lburp/Ztwv;Lburp/Zg0u;Lburp/Ztyg;Lburp/Zgq7;Lburp/Zrid;Lburp/Zkl6;Lburp/Zbnt;Lburp/Ze8b;Lburp/Ztdq;Lburp/Zs0n;Lburp/api/montoya/internal/MontoyaObjectFactory;Lburp/Zkrw;Lburp/Zz4u;Lburp/Zb_j;Lburp/Zm6x;Lburp/Zr_4;Lburp/Zs6i;)V
    //   890: astore #50
    //   892: new burp/Zsu6
    //   895: dup
    //   896: aload_1
    //   897: aload_2
    //   898: aload #13
    //   900: aload_3
    //   901: aload #5
    //   903: aload #19
    //   905: aload #11
    //   907: invokeinterface ZuK : ()Lburp/Zzdx;
    //   912: aload #10
    //   914: invokeinterface ZGi : ()Lburp/Zefg;
    //   919: aload #7
    //   921: aload #8
    //   923: aload #26
    //   925: aload #12
    //   927: aload_0
    //   928: getfield Zo : Lburp/Zg0i;
    //   931: aload #16
    //   933: aload #17
    //   935: aload #9
    //   937: aload_0
    //   938: getfield ZG : Lburp/Zbnt;
    //   941: aload #6
    //   943: aload #28
    //   945: aload #37
    //   947: aload #34
    //   949: aload #38
    //   951: aload #35
    //   953: aload #36
    //   955: aload #40
    //   957: aload #14
    //   959: aload #39
    //   961: invokespecial <init> : (Lburp/Zz0n;Lburp/Zt4u;Lburp/Zr_4;Lburp/Zerg;Lburp/Zgb6;Lburp/Zm6v;Lburp/Zzdx;Lburp/Zefg;Lburp/Zskh;Lburp/Zslu;Lburp/Zbiv;Lburp/Ztwv;Lburp/Zg0i;Lburp/Ztyg;Lburp/Zgq7;Lburp/Zkl6;Lburp/Zbnt;Lburp/Zkrw;Lburp/Zbp5;Lburp/Zz4u;Lburp/Zrid;Lburp/Zb_j;Lburp/Zs0n;Lburp/api/montoya/internal/MontoyaObjectFactory;Lburp/Zm6x;Lburp/Zr_4;Lburp/Zs6i;)V
    //   964: astore #51
    //   966: aload_0
    //   967: aload #50
    //   969: aload #48
    //   971: dup
    //   972: invokestatic requireNonNull : (Ljava/lang/Object;)Ljava/lang/Object;
    //   975: pop
    //   976: <illegal opcode> accept : (Ljava/util/concurrent/atomic/AtomicReference;)Ljava/util/function/Consumer;
    //   981: invokeinterface ZY : (Ljava/util/function/Consumer;)Lburp/Zzp8;
    //   986: putfield ZT : Lburp/Zzp8;
    //   989: aload_0
    //   990: getfield Zr : Lburp/Zg0u;
    //   993: aload_0
    //   994: getfield ZT : Lburp/Zzp8;
    //   997: invokeinterface Zu : ()Lburp/Zkuh;
    //   1002: invokevirtual Zc : (Lburp/Zkuh;)V
    //   1005: aload_0
    //   1006: aload #51
    //   1008: aload #49
    //   1010: dup
    //   1011: invokestatic requireNonNull : (Ljava/lang/Object;)Ljava/lang/Object;
    //   1014: pop
    //   1015: <illegal opcode> accept : (Ljava/util/concurrent/atomic/AtomicReference;)Ljava/util/function/Consumer;
    //   1020: invokeinterface ZY : (Ljava/util/function/Consumer;)Lburp/Zzp8;
    //   1025: putfield ZN : Lburp/Zzp8;
    //   1028: aload_0
    //   1029: getfield Zo : Lburp/Zg0i;
    //   1032: aload_0
    //   1033: getfield ZN : Lburp/Zzp8;
    //   1036: invokeinterface Zu : ()Lburp/Zkuh;
    //   1041: invokevirtual Zc : (Lburp/Zkuh;)V
    //   1044: aload_0
    //   1045: new burp/Zmw3
    //   1048: dup
    //   1049: aload #22
    //   1051: invokeinterface Zlb : ()Lburp/Zl34;
    //   1056: new burp/Zt_d
    //   1059: dup
    //   1060: aload #22
    //   1062: invokeinterface Zlb : ()Lburp/Zl34;
    //   1067: invokeinterface ZjM : ()Lburp/Zefg;
    //   1072: invokespecial <init> : (Lburp/Zefg;)V
    //   1075: aload #13
    //   1077: aload #14
    //   1079: aload #9
    //   1081: invokeinterface Zq : ()Lburp/Zr1j;
    //   1086: invokespecial <init> : (Lburp/Zl34;Lburp/Ztn0;Lburp/Zr_4;Lburp/Zr_4;Lburp/Zr1j;)V
    //   1089: putfield Zx : Lburp/Zmw3;
    //   1092: aload_0
    //   1093: getfield Zx : Lburp/Zmw3;
    //   1096: iconst_0
    //   1097: invokevirtual ZmL : (Z)V
    //   1100: aload_0
    //   1101: new burp/Zza2
    //   1104: dup
    //   1105: aload #6
    //   1107: aload_0
    //   1108: aload_0
    //   1109: getfield ZW : Lburp/Zgjf;
    //   1112: aload_0
    //   1113: getfield ZP : Lburp/Zlb7;
    //   1116: aload #21
    //   1118: aload #9
    //   1120: aload #12
    //   1122: aload #14
    //   1124: invokespecial <init> : (Lburp/Zkrw;Lburp/Zbw_;Lburp/Zgjf;Lburp/Zlb7;Lburp/Ztpu;Lburp/Zkl6;Lburp/Ztwv;Lburp/Zr_4;)V
    //   1127: putfield ZQ : Lburp/Zza2;
    //   1130: aload_0
    //   1131: new burp/Zbes
    //   1134: dup
    //   1135: aload_1
    //   1136: aload_2
    //   1137: aload_0
    //   1138: aload #7
    //   1140: aload_0
    //   1141: getfield ZW : Lburp/Zgjf;
    //   1144: invokevirtual ZM : ()Lburp/Zt_4;
    //   1147: aload #20
    //   1149: invokespecial <init> : (Lburp/Zz0n;Lburp/Zt4u;Lburp/Zbw_;Lburp/Zskh;Lburp/Zt_4;Lburp/Zr1m;)V
    //   1152: putfield ZB : Lburp/Zbes;
    //   1155: aload_0
    //   1156: new burp/Zbep
    //   1159: dup
    //   1160: aload #22
    //   1162: aload #23
    //   1164: iconst_1
    //   1165: aload #14
    //   1167: aload #20
    //   1169: aload #9
    //   1171: invokeinterface Zq : ()Lburp/Zr1j;
    //   1176: invokespecial <init> : (Lburp/Zekl;Lburp/Zgr_;ZLburp/Zr_4;Lburp/Zr1m;Lburp/Zr1j;)V
    //   1179: putfield Zl : Lburp/Zbep;
    //   1182: aload_0
    //   1183: new burp/Zbep
    //   1186: dup
    //   1187: aload #22
    //   1189: aload #23
    //   1191: iconst_0
    //   1192: aload #14
    //   1194: aload #20
    //   1196: aload #9
    //   1198: invokeinterface Zq : ()Lburp/Zr1j;
    //   1203: invokespecial <init> : (Lburp/Zekl;Lburp/Zgr_;ZLburp/Zr_4;Lburp/Zr1m;Lburp/Zr1j;)V
    //   1206: putfield ZL : Lburp/Zbep;
    //   1209: aload_0
    //   1210: new burp/Zbeq
    //   1213: dup
    //   1214: aload #22
    //   1216: aload #20
    //   1218: invokespecial <init> : (Lburp/Zekl;Lburp/Zr1m;)V
    //   1221: putfield Zg : Lburp/Zbeq;
    //   1224: aload_0
    //   1225: new burp/Zbei
    //   1228: dup
    //   1229: aload #22
    //   1231: aload #20
    //   1233: invokespecial <init> : (Lburp/Zekl;Lburp/Zr1m;)V
    //   1236: putfield Zy : Lburp/Zbei;
    //   1239: aload_0
    //   1240: new burp/Zbe4
    //   1243: dup
    //   1244: aload_0
    //   1245: getfield ZS : Lburp/Ze9y;
    //   1248: aload #9
    //   1250: aload #14
    //   1252: aload #20
    //   1254: invokespecial <init> : (Lburp/Ze9y;Lburp/Zkl6;Lburp/Zr_4;Lburp/Zr1m;)V
    //   1257: putfield Zs : Lburp/Zbe4;
    //   1260: aload_0
    //   1261: new burp/Zbe2
    //   1264: dup
    //   1265: aload #41
    //   1267: aload #20
    //   1269: invokespecial <init> : (Lburp/Zs2p;Lburp/Zr1m;)V
    //   1272: putfield ZM : Lburp/Zbe2;
    //   1275: aload_0
    //   1276: new burp/Zbe9
    //   1279: dup
    //   1280: aload_1
    //   1281: aload_2
    //   1282: aload_0
    //   1283: invokevirtual ZFY : ()Lburp/Zskh;
    //   1286: aload #22
    //   1288: aload_0
    //   1289: getfield Zx : Lburp/Zmw3;
    //   1292: aload #9
    //   1294: invokeinterface Zq : ()Lburp/Zr1j;
    //   1299: aload_0
    //   1300: getfield ZG : Lburp/Zbnt;
    //   1303: aload #14
    //   1305: aload #20
    //   1307: aload #37
    //   1309: invokespecial <init> : (Lburp/Zz0n;Lburp/Zt4u;Lburp/Zskh;Lburp/Zekl;Lburp/Zmw3;Lburp/Zr1j;Lburp/Zbnt;Lburp/Zr_4;Lburp/Zr1m;Lburp/Zsza;)V
    //   1312: putfield Zb : Lburp/Zbe9;
    //   1315: aload_0
    //   1316: new burp/Zbe1
    //   1319: dup
    //   1320: aload #5
    //   1322: aload #20
    //   1324: invokespecial <init> : (Lburp/Zgb6;Lburp/Zr1m;)V
    //   1327: putfield Zp : Lburp/Zbe1;
    //   1330: aload_0
    //   1331: new burp/Zbeu
    //   1334: dup
    //   1335: aload #33
    //   1337: aload #20
    //   1339: invokespecial <init> : (Lburp/Zrz;Lburp/Zr1m;)V
    //   1342: putfield Zw : Lburp/Zbeu;
    //   1345: aload_0
    //   1346: new burp/Zbe3
    //   1349: dup
    //   1350: aload #22
    //   1352: aload #20
    //   1354: invokespecial <init> : (Lburp/Zekl;Lburp/Zr1m;)V
    //   1357: putfield Z_ : Lburp/Zbe3;
    //   1360: aload #32
    //   1362: getstatic burp/Zs70.PROXY_PATH : Lburp/Zs70;
    //   1365: getstatic burp/Zg29.PROJECT : Lburp/Zg29;
    //   1368: aload_0
    //   1369: getfield ZB : Lburp/Zbes;
    //   1372: invokevirtual ZM : (Lburp/Zs70;Lburp/Zg29;Lburp/Zt3u;)V
    //   1375: aload #32
    //   1377: getstatic burp/Zs70.PROXY_PATH : Lburp/Zs70;
    //   1380: getstatic burp/Zg29.PROJECT : Lburp/Zg29;
    //   1383: aload_0
    //   1384: getfield Zl : Lburp/Zbep;
    //   1387: invokevirtual ZM : (Lburp/Zs70;Lburp/Zg29;Lburp/Zt3u;)V
    //   1390: aload #32
    //   1392: getstatic burp/Zs70.PROXY_PATH : Lburp/Zs70;
    //   1395: getstatic burp/Zg29.PROJECT : Lburp/Zg29;
    //   1398: aload_0
    //   1399: getfield ZL : Lburp/Zbep;
    //   1402: invokevirtual ZM : (Lburp/Zs70;Lburp/Zg29;Lburp/Zt3u;)V
    //   1405: aload #32
    //   1407: getstatic burp/Zs70.PROXY_PATH : Lburp/Zs70;
    //   1410: getstatic burp/Zg29.PROJECT : Lburp/Zg29;
    //   1413: aload_0
    //   1414: getfield Zg : Lburp/Zbeq;
    //   1417: invokevirtual ZM : (Lburp/Zs70;Lburp/Zg29;Lburp/Zt3u;)V
    //   1420: aload #32
    //   1422: getstatic burp/Zs70.PROXY_PATH : Lburp/Zs70;
    //   1425: getstatic burp/Zg29.PROJECT : Lburp/Zg29;
    //   1428: aload_0
    //   1429: getfield Zy : Lburp/Zbei;
    //   1432: invokevirtual ZM : (Lburp/Zs70;Lburp/Zg29;Lburp/Zt3u;)V
    //   1435: aload #32
    //   1437: getstatic burp/Zs70.PROXY_PATH : Lburp/Zs70;
    //   1440: getstatic burp/Zg29.PROJECT : Lburp/Zg29;
    //   1443: aload_0
    //   1444: getfield Zs : Lburp/Zbe4;
    //   1447: invokevirtual ZM : (Lburp/Zs70;Lburp/Zg29;Lburp/Zt3u;)V
    //   1450: aload #32
    //   1452: getstatic burp/Zs70.PROXY_PATH : Lburp/Zs70;
    //   1455: getstatic burp/Zg29.PROJECT : Lburp/Zg29;
    //   1458: aload_0
    //   1459: getfield ZM : Lburp/Zbe2;
    //   1462: invokevirtual ZM : (Lburp/Zs70;Lburp/Zg29;Lburp/Zt3u;)V
    //   1465: aload #32
    //   1467: getstatic burp/Zs70.PROXY_PATH : Lburp/Zs70;
    //   1470: getstatic burp/Zg29.PROJECT : Lburp/Zg29;
    //   1473: aload_0
    //   1474: getfield Zb : Lburp/Zbe9;
    //   1477: invokevirtual ZM : (Lburp/Zs70;Lburp/Zg29;Lburp/Zt3u;)V
    //   1480: aload #32
    //   1482: getstatic burp/Zs70.PROXY_PATH : Lburp/Zs70;
    //   1485: getstatic burp/Zg29.USER : Lburp/Zg29;
    //   1488: aload_0
    //   1489: getfield Zp : Lburp/Zbe1;
    //   1492: invokevirtual ZM : (Lburp/Zs70;Lburp/Zg29;Lburp/Zt3u;)V
    //   1495: aload #32
    //   1497: getstatic burp/Zs70.PROXY_PATH : Lburp/Zs70;
    //   1500: getstatic burp/Zg29.USER : Lburp/Zg29;
    //   1503: aload_0
    //   1504: getfield Zw : Lburp/Zbeu;
    //   1507: invokevirtual ZM : (Lburp/Zs70;Lburp/Zg29;Lburp/Zt3u;)V
    //   1510: aload #32
    //   1512: getstatic burp/Zs70.PROXY_PATH : Lburp/Zs70;
    //   1515: getstatic burp/Zg29.PROJECT : Lburp/Zg29;
    //   1518: aload_0
    //   1519: getfield Z_ : Lburp/Zbe3;
    //   1522: invokevirtual ZM : (Lburp/Zs70;Lburp/Zg29;Lburp/Zt3u;)V
    //   1525: iload #42
    //   1527: ifeq -> 1537
    //   1530: iconst_5
    //   1531: anewarray burp/Zbqc
    //   1534: invokestatic Zr : ([Lburp/Zbqc;)V
    //   1537: return
  }
  
  public Zm0o[] ZF1() {
    Zszh zszh1 = new Zszh(this.Zk, a(25843, -8450));
    Zszh zszh2 = new Zszh(this.ZT.ZW(), a(25840, -1539));
    Zszh zszh3 = new Zszh(this.ZN.ZW(), a(25844, 11426));
    return new Zm0o[] { zszh1, zszh2, zszh3 };
  }
  
  public Ztpu ZF0() {
    return this.ZE;
  }
  
  public Zskh ZFY() {
    return this.Zv.ZY4();
  }
  
  public Zerg ZFa() {
    return this.Zj;
  }
  
  public Zzh6<Zeo2> ZFS() {
    return new Zzh6<>(this.Zr, this.ZT, this.ZD);
  }
  
  public void Zj(Zr_4 paramZr_4, Zzir paramZzir, Ztg8 paramZtg8, Zeom paramZeom, Zlc8 paramZlc8, float paramFloat1, float paramFloat2) {
    float f = this.Zr.ZW(paramZr_4, paramZzir, paramZzir.Zvu().ZGl(), paramZtg8, paramZeom, paramZlc8, paramFloat1, paramFloat2);
    if (f < 0.0F)
      return; 
    this.Zo.ZW(paramZr_4, paramZzir, paramZzir.Zvu().ZGW(), paramZtg8, paramZeom, paramZlc8, f, paramFloat2);
  }
  
  public void ZFj() {
    this.Zn = new Zev(this.Zc, this.Zv.ZY4(), this.ZD, this.Zh, new Zkhg(this.Ze, this.ZY));
    this.Zi.ZB(this.Zn);
    this.ZV.ZU(this.Zn);
    this.ZW.Zc();
    ZFv();
  }
  
  public void ZFn() {
    this.ZW.ZZ();
    this.Zn.ZY();
    Zm2.Zi(Zv8r.PROXY_HISTORY_HTTP_NUMBER_OF_ENTRIES_AT_SHUTDOWN, ZFN().size());
    Zm2.Zi(Zv8r.PROXY_HISTORY_WEBSOCKETS_NUMBER_OF_ENTRIES_AT_SHUTDOWN, ZFh().size());
  }
  
  public void ZFf() {
    Zg5n zg5n = this.Zf.<Zg5n>ZH((new Zrk4()).ZD((byte)1).ZU((byte)1));
    Zb2z zb2z = new Zb2z(zg5n, this.ZO, this.ZD, this.ZP, ZFY(), this.ZE, Zxzw.ZT, null);
    int i = Zguu.Zb();
    Zr7c zr7c = new Zr7c(this.ZA, this.Zv, this, this.ZW, Zt2m.ZF(this.ZB), zb2z, true, this.ZO, this.ZD, this.ZR, this.Zf, this.ZP, true);
    zr7c.setVisible(true);
    if (Zbqc.Zwu() == null)
      Zguu.Zb(++i); 
  }
  
  public void ZE(int paramInt, boolean paramBoolean) {
    Zs9s zs9s = this.ZW.ZQ(paramInt);
    Zr7c zr7c = new Zr7c(this.ZA, this.Zv, this, this.ZW, Zt2m.ZF(this.ZB), zs9s, false, this.ZO, this.ZD, this.ZR, this.Zf, this.ZP, paramBoolean);
    zr7c.setVisible(true);
  }
  
  public void Zp(int paramInt) {
    this.ZW.Zk(paramInt);
    ZFv();
  }
  
  public boolean ZR(int paramInt, Window paramWindow) {
    boolean bool = this.ZW.ZJ(paramInt, paramWindow);
    ZFv();
    return bool;
  }
  
  public void Zz(int paramInt, Window paramWindow) {
    this.ZW.ZX(paramInt, paramWindow);
    ZFv();
  }
  
  public void ZD(Zl04 paramZl04, String paramString) {
    // Byte code:
    //   0: getstatic burp/Zrrh.BURP_BROWSER_PRE_WIRED_BROWSER_REQUESTED : Lburp/Zrrh;
    //   3: invokestatic ZC : (Lnet/portswigger/Zip;)V
    //   6: aload_0
    //   7: getfield ZD : Lburp/Ztwv;
    //   10: aload_0
    //   11: aload_1
    //   12: aload_2
    //   13: <illegal opcode> run : (Lburp/Zsu_;Lburp/Zl04;Ljava/lang/String;)Ljava/lang/Runnable;
    //   18: invokeinterface Zx : (Ljava/lang/Runnable;)Ljava/util/concurrent/Future;
    //   23: pop
    //   24: return
  }
  
  public void ZFv() {
    this.Zq.Zm(this.ZW.Zz(), this.ZW.Zd());
  }
  
  public Zekl ZFM() {
    return this.Zc;
  }
  
  public boolean ZJ(Zlbg paramZlbg, boolean paramBoolean, Zlit paramZlit) {
    return this.ZS.ZP(paramZlbg, paramBoolean, paramZlit);
  }
  
  public byte[] ZV(byte[] paramArrayOfbyte, Zs68 paramZs68) {
    return (new Ze1g(this.Zc, paramArrayOfbyte, paramZs68, this.ZG)).Zn();
  }
  
  public boolean ZO(Zml3 paramZml3, boolean paramBoolean) {
    return this.ZK.Zi(paramZml3, paramBoolean);
  }
  
  public boolean ZN(Zlit paramZlit, Ze3o paramZe3o) {
    return !this.ZK.ZO() ? false : ((this.Zc.ZlL() && !this.Za.ZG(paramZlit)) ? false : ((paramZe3o == Ze3o.CLIENT_TO_SERVER) ? this.Zc.ZlX() : this.Zc.ZlW()));
  }
  
  public boolean ZFL() {
    return this.Zk.Zv();
  }
  
  public void ZF2() {
    this.Zk.ZN();
  }
  
  public void ZF4() {
    this.Zk.Zt();
  }
  
  public void ZF_() {
    this.Zk.Za();
  }
  
  public void ZdN(boolean paramBoolean) {
    this.Zk.ZL(paramBoolean);
  }
  
  private void ZA9(boolean paramBoolean) {
    this.Zl.ZP(paramBoolean);
    this.ZL.ZP(paramBoolean);
    this.ZK.ZL(paramBoolean);
    if (!paramBoolean && this.Zn != null)
      this.Zn.Ze(); 
  }
  
  public void ZFA() {
    this.Zk.ZT();
  }
  
  public Zg0u ZFN() {
    return this.Zr;
  }
  
  public Zg0i ZFh() {
    return this.Zo;
  }
  
  public Zmkr ZFW() {
    return this.Zm;
  }
  
  public Zzu8 ZFC() {
    return this.Zz;
  }
  
  public void ZL(Zz6e<T> paramZz6e) {
    this.Zn.Zf(paramZz6e);
  }
  
  public boolean Zu(String paramString, int paramInt) {
    // Byte code:
    //   0: aload_0
    //   1: getfield ZG : Lburp/Zbnt;
    //   4: aload_1
    //   5: iload_2
    //   6: iconst_1
    //   7: invokevirtual ZY : (Ljava/lang/String;IZ)Lburp/Zmzk;
    //   10: astore_3
    //   11: aload_0
    //   12: getfield Zc : Lburp/Zekl;
    //   15: invokeinterface Zls : ()Z
    //   20: ifeq -> 50
    //   23: aload_0
    //   24: getfield Zc : Lburp/Zekl;
    //   27: invokeinterface ZlI : ()Z
    //   32: ifeq -> 50
    //   35: goto -> 42
    //   38: invokestatic a : (Lburp/Zxgy;)Lburp/Zxgy;
    //   41: athrow
    //   42: iconst_1
    //   43: goto -> 51
    //   46: invokestatic a : (Lburp/Zxgy;)Lburp/Zxgy;
    //   49: athrow
    //   50: iconst_0
    //   51: istore #4
    //   53: iload #4
    //   55: ifeq -> 86
    //   58: aload_0
    //   59: getfield Za : Lburp/Zslu;
    //   62: aload_3
    //   63: invokeinterface ZB : (Lburp/Zmzk;)Z
    //   68: ifne -> 86
    //   71: goto -> 78
    //   74: invokestatic a : (Lburp/Zxgy;)Lburp/Zxgy;
    //   77: athrow
    //   78: iconst_1
    //   79: goto -> 87
    //   82: invokestatic a : (Lburp/Zxgy;)Lburp/Zxgy;
    //   85: athrow
    //   86: iconst_0
    //   87: istore #5
    //   89: iload #5
    //   91: ifne -> 112
    //   94: aload_0
    //   95: getfield Zx : Lburp/Zmw3;
    //   98: aload_3
    //   99: invokevirtual ZI : (Lburp/Zmzk;)Z
    //   102: ifeq -> 120
    //   105: goto -> 112
    //   108: invokestatic a : (Lburp/Zxgy;)Lburp/Zxgy;
    //   111: athrow
    //   112: iconst_1
    //   113: goto -> 121
    //   116: invokestatic a : (Lburp/Zxgy;)Lburp/Zxgy;
    //   119: athrow
    //   120: iconst_0
    //   121: ireturn
    //   122: astore_3
    //   123: aload_3
    //   124: getstatic net/portswigger/Zk_.IGNORED : Lnet/portswigger/Zk_;
    //   127: invokestatic Zl : (Ljava/lang/Throwable;Lnet/portswigger/Zk_;)V
    //   130: iconst_0
    //   131: ireturn
    // Exception table:
    //   from	to	target	type
    //   0	121	122	burp/Zxgy
    //   0	121	122	burp/Zxg5
    //   11	35	38	burp/Zxgy
    //   23	46	46	burp/Zxgy
    //   53	71	74	burp/Zxgy
    //   58	82	82	burp/Zxgy
    //   89	105	108	burp/Zxgy
    //   94	116	116	burp/Zxgy
  }
  
  public void ZC(String paramString, int paramInt) throws Zxgy, Zxg5 {
    this.Zx.ZI(new Zax(this.ZG.ZY(paramString, paramInt, true), null));
  }
  
  public void ZM(int paramInt) {
    this.ZW.Zf(paramInt);
  }
  
  public void ZF(Zm3g paramZm3g) {
    this.ZJ.add(paramZm3g);
  }
  
  public void Zt2() {
    this.ZB.Zt2();
    this.Zl.Zt2();
    this.ZL.Zt2();
    this.Zg.Zt2();
    this.Zy.Zt2();
    this.Zs.Zt2();
    this.ZM.Zt2();
    this.Zb.Zt2();
    this.Zw.Zt2();
    this.Zp.Zt2();
    this.Z_.Zt2();
    this.Zk.Zm();
    this.ZT.Zv();
    this.ZN.Zv();
    ZA9(this.Zc.Zl6());
  }
  
  public void Zd(Zmf_ paramZmf_) {
    Zk(paramZmf_);
    this.Zc.Zd(paramZmf_);
    int i = Zguu.ZI();
    for (Zm3g zm3g : this.ZJ) {
      zm3g.Zd(paramZmf_);
      if (i != 0)
        break; 
    } 
    Zt2();
  }
  
  public void Zl(Zg4j paramZg4j) {
    ZB(paramZg4j);
    this.Zc.Zl(paramZg4j);
    int i = Zguu.ZI();
    for (Zm3g zm3g : this.ZJ) {
      zm3g.Zl(paramZg4j);
      if (i != 0)
        break; 
    } 
  }
  
  private void Zk(Zmf_ paramZmf_) {
    this.Zx.Zk(paramZmf_, a(25842, 30622), a(25847, -19801), a(25849, -29552));
    this.Zx.ZmL(false);
  }
  
  private void ZB(Zg4j paramZg4j) {
    this.Zx.Zh(paramZg4j, a(25848, -1791), a(25846, -24154));
  }
  
  private void lambda$launchPreWiredBrowser$4(Zl04 paramZl04, String paramString) {
    try {
      Optional<Zs9s> optional = this.ZQ.ZB(paramZl04);
      if (optional.isEmpty()) {
        Zx6o.Zt(paramZl04, a(25845, 32038), a(25841, -28577));
        return;
      } 
      this.ZH.ZD(((Zs9s)optional.get()).ZS(), paramString);
    } catch (Exception exception) {
      Zah.Zl(exception, Zk_.IGNORED);
      Zx6o.Zt(paramZl04, a(25850, -10911), exception.getMessage());
    } 
  }
  
  private void lambda$new$3(Zkrw paramZkrw, String paramString) {
    ZD(paramZkrw.ZYW(), paramString);
  }
  
  private static boolean lambda$new$2(Zzh2 paramZzh2) {
    return false;
  }
  
  private static Zeo2 lambda$new$1(Zr_4 paramZr_4, Zeo2 paramZeo2) {
    return (paramZr_4.Zi() && (!(paramZeo2 instanceof Zxsr) || !paramZr_4.Zl().ZV((Zxsr)paramZeo2))) ? paramZeo2.ZJ(paramZr_4) : paramZeo2;
  }
  
  private static boolean lambda$new$0(Zr_4 paramZr_4, Zeo2 paramZeo2) {
    return (paramZr_4.Zi() && (!(paramZeo2 instanceof Zxsr) || !paramZr_4.Zl().ZV((Zxsr)paramZeo2)));
  }
  
  private static Zxgy a(Zxgy paramZxgy) {
    return paramZxgy;
  }
  
  static {
    // Byte code:
    //   0: bipush #11
    //   2: anewarray java/lang/String
    //   5: astore #5
    //   7: iconst_0
    //   8: istore_3
    //   9: ldc 'ATÃªvÃ»bÃ²Ã Ã§Ã¦_<<;ÃŽÃ”Â OgÂŽoÃ™sÂÃ¼}Â¼ÂÂ¢- }Â¶Â–Â°@Â·Â—%fÂ·Ã‘Ã¤$'mÃ­\\t0Ã»Â¸ÃÃ±Ã®qÂ§zÃŠÂžÃlÃ¿FPTÂ·fR\\n|Ã¢HÂ¹Ã™ÃˆÂ®ÃºXÃŒÃµÂ“YyÃ‘}Ã­ÂŠF\\tAKÃ«ÃÂ­Â,Ã†Â¶@Ãµ V\\nÃ£Â½07~ÂÃŠ\\fÃ™LÂ”PÃ–Â¨L8L!r}Ã‰cÃ³Â®Â¦(BÂŒ1MÃŠl*Ã•2,Ã…POÂ–Ã±Ã¨Ã¯Ã›Ã‹Ã˜Â¾Ã¾ uÃ§#oÂšÃ§Â´Ã·lÂ¬ZÂ°Â°'
    //   11: dup
    //   12: astore_2
    //   13: invokevirtual length : ()I
    //   16: istore #4
    //   18: bipush #12
    //   20: istore_1
    //   21: iconst_m1
    //   22: istore_0
    //   23: bipush #93
    //   25: iinc #0, 1
    //   28: aload_2
    //   29: iload_0
    //   30: dup
    //   31: iload_1
    //   32: iadd
    //   33: invokevirtual substring : (II)Ljava/lang/String;
    //   36: iconst_m1
    //   37: goto -> 142
    //   40: aload #5
    //   42: swap
    //   43: iload_3
    //   44: iinc #3, 1
    //   47: swap
    //   48: aastore
    //   49: iload_0
    //   50: iload_1
    //   51: iadd
    //   52: dup
    //   53: istore_0
    //   54: iload #4
    //   56: if_icmpge -> 68
    //   59: aload_2
    //   60: iload_0
    //   61: invokevirtual charAt : (I)C
    //   64: istore_1
    //   65: goto -> 23
    //   68: ldc 'FpÂÂ—ÂVÃ¢LGt!Ã¼Â¾Ã¦Â´Ã¨p\@Pk'
    //   70: dup
    //   71: astore_2
    //   72: invokevirtual length : ()I
    //   75: istore #4
    //   77: iconst_5
    //   78: istore_1
    //   79: iconst_m1
    //   80: istore_0
    //   81: bipush #44
    //   83: iinc #0, 1
    //   86: aload_2
    //   87: iload_0
    //   88: dup
    //   89: iload_1
    //   90: iadd
    //   91: invokevirtual substring : (II)Ljava/lang/String;
    //   94: iconst_0
    //   95: goto -> 142
    //   98: aload #5
    //   100: swap
    //   101: iload_3
    //   102: iinc #3, 1
    //   105: swap
    //   106: aastore
    //   107: iload_0
    //   108: iload_1
    //   109: iadd
    //   110: dup
    //   111: istore_0
    //   112: iload #4
    //   114: if_icmpge -> 126
    //   117: aload_2
    //   118: iload_0
    //   119: invokevirtual charAt : (I)C
    //   122: istore_1
    //   123: goto -> 81
    //   126: aload #5
    //   128: putstatic burp/Zsu_.a : [Ljava/lang/String;
    //   131: bipush #11
    //   133: anewarray java/lang/String
    //   136: putstatic burp/Zsu_.b : [Ljava/lang/String;
    //   139: goto -> 300
    //   142: dup_x2
    //   143: pop
    //   144: invokevirtual toCharArray : ()[C
    //   147: dup_x1
    //   148: arraylength
    //   149: dup_x2
    //   150: pop
    //   151: iconst_0
    //   152: istore #6
    //   154: dup2_x1
    //   155: pop2
    //   156: dup_x2
    //   157: iconst_1
    //   158: if_icmpgt -> 260
    //   161: dup2
    //   162: swap
    //   163: iload #6
    //   165: dup2_x1
    //   166: caload
    //   167: swap
    //   168: iload #6
    //   170: bipush #7
    //   172: irem
    //   173: tableswitch default -> 242, 0 -> 212, 1 -> 217, 2 -> 222, 3 -> 227, 4 -> 232, 5 -> 237
    //   212: bipush #58
    //   214: goto -> 244
    //   217: bipush #55
    //   219: goto -> 244
    //   222: bipush #102
    //   224: goto -> 244
    //   227: bipush #98
    //   229: goto -> 244
    //   232: bipush #98
    //   234: goto -> 244
    //   237: bipush #36
    //   239: goto -> 244
    //   242: bipush #122
    //   244: ixor
    //   245: ixor
    //   246: i2c
    //   247: castore
    //   248: iinc #6, 1
    //   251: dup
    //   252: ifne -> 260
    //   255: dup2
    //   256: dup_x1
    //   257: goto -> 165
    //   260: dup2_x1
    //   261: pop2
    //   262: dup_x2
    //   263: iload #6
    //   265: if_icmpgt -> 161
    //   268: pop
    //   269: new java/lang/String
    //   272: dup_x1
    //   273: swap
    //   274: invokespecial <init> : ([C)V
    //   277: invokevirtual intern : ()Ljava/lang/String;
    //   280: swap
    //   281: pop
    //   282: swap
    //   283: tableswitch default -> 40, 0 -> 98
    //   300: return
  }
  
  private static String a(int paramInt1, int paramInt2) {
    int i = (paramInt1 ^ 0x64F0) & 0xFFFF;
    if (b[i] == null) {
      char[] arrayOfChar = a[i].toCharArray();
      switch (arrayOfChar[0] & 0xFF) {
        case 0:
        
        case 1:
        
        case 2:
        
        case 3:
        
        case 4:
        
        case 5:
        
        case 6:
        
        case 7:
        
        case 8:
        
        case 9:
        
        case 10:
        
        case 11:
        
        case 12:
        
        case 13:
        
        case 14:
        
        case 15:
        
        case 16:
        
        case 17:
        
        case 18:
        
        case 19:
        
        case 20:
        
        case 21:
        
        case 22:
        
        case 23:
        
        case 24:
        
        case 25:
        
        case 26:
        
        case 27:
        
        case 28:
        
        case 29:
        
        case 30:
        
        case 31:
        
        case 32:
        
        case 33:
        
        case 34:
        
        case 35:
        
        case 36:
        
        case 37:
        
        case 38:
        
        case 39:
        
        case 40:
        
        case 41:
        
        case 42:
        
        case 43:
        
        case 44:
        
        case 45:
        
        case 46:
        
        case 47:
        
        case 48:
        
        case 49:
        
        case 50:
        
        case 51:
        
        case 52:
        
        case 53:
        
        case 54:
        
        case 55:
        
        case 56:
        
        case 57:
        
        case 58:
        
        case 59:
        
        case 60:
        
        case 61:
        
        case 62:
        
        case 63:
        
        case 64:
        
        case 65:
        
        case 66:
        
        case 67:
        
        case 68:
        
        case 69:
        
        case 70:
        
        case 71:
        
        case 72:
        
        case 73:
        
        case 74:
        
        case 75:
        
        case 76:
        
        case 77:
        
        case 78:
        
        case 79:
        
        case 80:
        
        case 81:
        
        case 82:
        
        case 83:
        
        case 84:
        
        case 85:
        
        case 86:
        
        case 87:
        
        case 88:
        
        case 89:
        
        case 90:
        
        case 91:
        
        case 92:
        
        case 93:
        
        case 94:
        
        case 95:
        
        case 96:
        
        case 97:
        
        case 98:
        
        case 99:
        
        case 100:
        
        case 101:
        
        case 102:
        
        case 103:
        
        case 104:
        
        case 105:
        
        case 106:
        
        case 107:
        
        case 108:
        
        case 109:
        
        case 110:
        
        case 111:
        
        case 112:
        
        case 113:
        
        case 114:
        
        case 115:
        
        case 116:
        
        case 117:
        
        case 118:
        
        case 119:
        
        case 120:
        
        case 121:
        
        case 122:
        
        case 123:
        
        case 124:
        
        case 125:
        
        case 126:
        
        case 127:
        
        case 128:
        
        case 129:
        
        case 130:
        
        case 131:
        
        case 132:
        
        case 133:
        
        case 134:
        
        case 135:
        
        case 136:
        
        case 137:
        
        case 138:
        
        case 139:
        
        case 140:
        
        case 141:
        
        case 142:
        
        case 143:
        
        case 144:
        
        case 145:
        
        case 146:
        
        case 147:
        
        case 148:
        
        case 149:
        
        case 150:
        
        case 151:
        
        case 152:
        
        case 153:
        
        case 154:
        
        case 155:
        
        case 156:
        
        case 157:
        
        case 158:
        
        case 159:
        
        case 160:
        
        case 161:
        
        case 162:
        
        case 163:
        
        case 164:
        
        case 165:
        
        case 166:
        
        case 167:
        
        case 168:
        
        case 169:
        
        case 170:
        
        case 171:
        
        case 172:
        
        case 173:
        
        case 174:
        
        case 175:
        
        case 176:
        
        case 177:
        
        case 178:
        
        case 179:
        
        case 180:
        
        case 181:
        
        case 182:
        
        case 183:
        
        case 184:
        
        case 185:
        
        case 186:
        
        case 187:
        
        case 188:
        
        case 189:
        
        case 190:
        
        case 191:
        
        case 192:
        
        case 193:
        
        case 194:
        
        case 195:
        
        case 196:
        
        case 197:
        
        case 198:
        
        case 199:
        
        case 200:
        
        case 201:
        
        case 202:
        
        case 203:
        
        case 204:
        
        case 205:
        
        case 206:
        
        case 207:
        
        case 208:
        
        case 209:
        
        case 210:
        
        case 211:
        
        case 212:
        
        case 213:
        
        case 214:
        
        case 215:
        
        case 216:
        
        case 217:
        
        case 218:
        
        case 219:
        
        case 220:
        
        case 221:
        
        case 222:
        
        case 223:
        
        case 224:
        
        case 225:
        
        case 226:
        
        case 227:
        
        case 228:
        
        case 229:
        
        case 230:
        
        case 231:
        
        case 232:
        
        case 233:
        
        case 234:
        
        case 235:
        
        case 236:
        
        case 237:
        
        case 238:
        
        case 239:
        
        case 240:
        
        case 241:
        
        case 242:
        
        case 243:
        
        case 244:
        
        case 245:
        
        case 246:
        
        case 247:
        
        case 248:
        
        case 249:
        
        case 250:
        
        case 251:
        
        case 252:
        
        case 253:
        
        case 254:
        
        default:
          break;
      } 
      byte b1 = 23;
      int j = (paramInt2 & 0xFF) - b1;
      if (j < 0)
        j += 256; 
      int k = ((paramInt2 & 0xFFFF) >>> 8) - b1;
      if (k < 0)
        k += 256; 
      for (byte b2 = 0; b2 < arrayOfChar.length; b2++) {
        int m = b2 % 2;
        if (m == 0) {
          arrayOfChar[b2] = (char)(arrayOfChar[b2] ^ j);
          j = ((j >>> 3 | j << 5) ^ arrayOfChar[b2]) & 0xFF;
        } else {
          arrayOfChar[b2] = (char)(arrayOfChar[b2] ^ k);
          k = ((k >>> 3 | k << 5) ^ arrayOfChar[b2]) & 0xFF;
        } 
      } 
      b[i] = (new String(arrayOfChar)).intern();
    } 
    return b[i];
  }
}


/* Location:              C:\Program Files\BurpSuitePro\burpsuite_pro.jar!\burp\Zsu_.class
 * Java compiler version: 21 (65.0)
 * JD-Core Version:       1.1.3
 */