package burp;

import java.math.BigInteger;

class Zsxm extends ClassLoader {
  static Object Zv;
  
  static String Zq;
  
  private static final String[] a;
  
  private static final String[] b;
  
  static void ZK(Object[] paramArrayOfObject, Object paramObject) throws Throwable {}
  
  static boolean ZW(Object[] paramArrayOfObject, Object paramObject) throws Throwable {
    // Byte code:
    //   0: invokestatic ZN : ()Z
    //   3: istore_2
    //   4: getstatic burp/Zb3z.ZR : Ljava/lang/Object;
    //   7: checkcast java/math/BigInteger
    //   10: invokevirtual toByteArray : ()[B
    //   13: astore_3
    //   14: aload_3
    //   15: arraylength
    //   16: iconst_2
    //   17: iadd
    //   18: newarray byte
    //   20: astore #5
    //   22: iconst_0
    //   23: istore #6
    //   25: iload #6
    //   27: aload_3
    //   28: arraylength
    //   29: if_icmpge -> 48
    //   32: aload #5
    //   34: iload #6
    //   36: aload_3
    //   37: iload #6
    //   39: baload
    //   40: bastore
    //   41: iinc #6, 1
    //   44: iload_2
    //   45: ifne -> 25
    //   48: aload #5
    //   50: arraylength
    //   51: iconst_3
    //   52: idiv
    //   53: iconst_4
    //   54: imul
    //   55: newarray byte
    //   57: astore #4
    //   59: iconst_0
    //   60: istore #6
    //   62: iconst_0
    //   63: istore #7
    //   65: iload #6
    //   67: aload_3
    //   68: arraylength
    //   69: if_icmpge -> 180
    //   72: aload #4
    //   74: iload #7
    //   76: aload #5
    //   78: iload #6
    //   80: baload
    //   81: iconst_2
    //   82: iushr
    //   83: bipush #63
    //   85: iand
    //   86: i2b
    //   87: bastore
    //   88: aload #4
    //   90: iload #7
    //   92: iconst_1
    //   93: iadd
    //   94: aload #5
    //   96: iload #6
    //   98: iconst_1
    //   99: iadd
    //   100: baload
    //   101: iconst_4
    //   102: iushr
    //   103: bipush #15
    //   105: iand
    //   106: aload #5
    //   108: iload #6
    //   110: baload
    //   111: iconst_4
    //   112: ishl
    //   113: bipush #63
    //   115: iand
    //   116: ior
    //   117: i2b
    //   118: bastore
    //   119: aload #4
    //   121: iload #7
    //   123: iconst_2
    //   124: iadd
    //   125: aload #5
    //   127: iload #6
    //   129: iconst_2
    //   130: iadd
    //   131: baload
    //   132: bipush #6
    //   134: iushr
    //   135: iconst_3
    //   136: iand
    //   137: aload #5
    //   139: iload #6
    //   141: iconst_1
    //   142: iadd
    //   143: baload
    //   144: iconst_2
    //   145: ishl
    //   146: bipush #63
    //   148: iand
    //   149: ior
    //   150: i2b
    //   151: bastore
    //   152: aload #4
    //   154: iload #7
    //   156: iconst_3
    //   157: iadd
    //   158: aload #5
    //   160: iload #6
    //   162: iconst_2
    //   163: iadd
    //   164: baload
    //   165: bipush #63
    //   167: iand
    //   168: i2b
    //   169: bastore
    //   170: iinc #6, 3
    //   173: iinc #7, 4
    //   176: iload_2
    //   177: ifne -> 65
    //   180: iconst_0
    //   181: istore #6
    //   183: iload #6
    //   185: aload #4
    //   187: arraylength
    //   188: if_icmpge -> 372
    //   191: aload #4
    //   193: iload #6
    //   195: baload
    //   196: bipush #26
    //   198: if_icmpge -> 226
    //   201: aload #4
    //   203: iload #6
    //   205: aload #4
    //   207: iload #6
    //   209: baload
    //   210: bipush #65
    //   212: iadd
    //   213: i2b
    //   214: bastore
    //   215: iload_2
    //   216: ifne -> 365
    //   219: goto -> 226
    //   222: invokestatic a : (Ljava/lang/Throwable;)Ljava/lang/Throwable;
    //   225: athrow
    //   226: aload #4
    //   228: iload #6
    //   230: baload
    //   231: bipush #52
    //   233: if_icmpge -> 271
    //   236: goto -> 243
    //   239: invokestatic a : (Ljava/lang/Throwable;)Ljava/lang/Throwable;
    //   242: athrow
    //   243: aload #4
    //   245: iload #6
    //   247: aload #4
    //   249: iload #6
    //   251: baload
    //   252: bipush #97
    //   254: iadd
    //   255: bipush #26
    //   257: isub
    //   258: i2b
    //   259: bastore
    //   260: iload_2
    //   261: ifne -> 365
    //   264: goto -> 271
    //   267: invokestatic a : (Ljava/lang/Throwable;)Ljava/lang/Throwable;
    //   270: athrow
    //   271: aload #4
    //   273: iload #6
    //   275: baload
    //   276: bipush #62
    //   278: if_icmpge -> 316
    //   281: goto -> 288
    //   284: invokestatic a : (Ljava/lang/Throwable;)Ljava/lang/Throwable;
    //   287: athrow
    //   288: aload #4
    //   290: iload #6
    //   292: aload #4
    //   294: iload #6
    //   296: baload
    //   297: bipush #48
    //   299: iadd
    //   300: bipush #52
    //   302: isub
    //   303: i2b
    //   304: bastore
    //   305: iload_2
    //   306: ifne -> 365
    //   309: goto -> 316
    //   312: invokestatic a : (Ljava/lang/Throwable;)Ljava/lang/Throwable;
    //   315: athrow
    //   316: aload #4
    //   318: iload #6
    //   320: baload
    //   321: bipush #63
    //   323: if_icmpge -> 351
    //   326: goto -> 333
    //   329: invokestatic a : (Ljava/lang/Throwable;)Ljava/lang/Throwable;
    //   332: athrow
    //   333: aload #4
    //   335: iload #6
    //   337: bipush #43
    //   339: bastore
    //   340: iload_2
    //   341: ifne -> 365
    //   344: goto -> 351
    //   347: invokestatic a : (Ljava/lang/Throwable;)Ljava/lang/Throwable;
    //   350: athrow
    //   351: aload #4
    //   353: iload #6
    //   355: bipush #47
    //   357: bastore
    //   358: goto -> 365
    //   361: invokestatic a : (Ljava/lang/Throwable;)Ljava/lang/Throwable;
    //   364: athrow
    //   365: iinc #6, 1
    //   368: iload_2
    //   369: ifne -> 183
    //   372: aload #4
    //   374: arraylength
    //   375: iconst_1
    //   376: isub
    //   377: istore #6
    //   379: iload #6
    //   381: aload_3
    //   382: arraylength
    //   383: iconst_4
    //   384: imul
    //   385: iconst_3
    //   386: idiv
    //   387: if_icmple -> 404
    //   390: aload #4
    //   392: iload #6
    //   394: bipush #61
    //   396: bastore
    //   397: iinc #6, -1
    //   400: iload_2
    //   401: ifne -> 379
    //   404: new java/math/BigInteger
    //   407: dup
    //   408: aload #4
    //   410: invokespecial <init> : ([B)V
    //   413: invokevirtual abs : ()Ljava/math/BigInteger;
    //   416: putstatic burp/Zod.ZP : Ljava/lang/Object;
    //   419: getstatic burp/Zlhm.ZT : Ljava/lang/Object;
    //   422: checkcast java/math/BigInteger
    //   425: invokevirtual toByteArray : ()[B
    //   428: astore_3
    //   429: bipush #32
    //   431: newarray int
    //   433: dup
    //   434: iconst_0
    //   435: ldc 943331329
    //   437: iastore
    //   438: dup
    //   439: iconst_1
    //   440: ldc 170788368
    //   442: iastore
    //   443: dup
    //   444: iconst_2
    //   445: ldc 1008414755
    //   447: iastore
    //   448: dup
    //   449: iconst_3
    //   450: ldc 187049985
    //   452: iastore
    //   453: dup
    //   454: iconst_4
    //   455: ldc 1010368540
    //   457: iastore
    //   458: dup
    //   459: iconst_5
    //   460: ldc 220604441
    //   462: iastore
    //   463: dup
    //   464: bipush #6
    //   466: ldc 940377620
    //   468: iastore
    //   469: dup
    //   470: bipush #7
    //   472: ldc 255209728
    //   474: iastore
    //   475: dup
    //   476: bipush #8
    //   478: ldc 689771012
    //   480: iastore
    //   481: dup
    //   482: bipush #9
    //   484: ldc 221709344
    //   486: iastore
    //   487: dup
    //   488: bipush #10
    //   490: ldc 957157408
    //   492: iastore
    //   493: dup
    //   494: bipush #11
    //   496: ldc 892536332
    //   498: iastore
    //   499: dup
    //   500: bipush #12
    //   502: ldc 722417666
    //   504: iastore
    //   505: dup
    //   506: bipush #13
    //   508: ldc 1026621720
    //   510: iastore
    //   511: dup
    //   512: bipush #14
    //   514: ldc 655302664
    //   516: iastore
    //   517: dup
    //   518: bipush #15
    //   520: ldc 890966315
    //   522: iastore
    //   523: dup
    //   524: bipush #16
    //   526: ldc 187632156
    //   528: iastore
    //   529: dup
    //   530: bipush #17
    //   532: ldc 874189824
    //   534: iastore
    //   535: dup
    //   536: bipush #18
    //   538: ldc 254150144
    //   540: iastore
    //   541: dup
    //   542: bipush #19
    //   544: ldc 924386310
    //   546: iastore
    //   547: dup
    //   548: bipush #20
    //   550: ldc 121057538
    //   552: iastore
    //   553: dup
    //   554: bipush #21
    //   556: ldc 840500228
    //   558: iastore
    //   559: dup
    //   560: bipush #22
    //   562: ldc 389160971
    //   564: iastore
    //   565: dup
    //   566: bipush #23
    //   568: ldc 907870729
    //   570: iastore
    //   571: dup
    //   572: bipush #24
    //   574: ldc 389426184
    //   576: iastore
    //   577: dup
    //   578: bipush #25
    //   580: ldc 973875457
    //   582: iastore
    //   583: dup
    //   584: bipush #26
    //   586: ldc 372376604
    //   588: iastore
    //   589: dup
    //   590: bipush #27
    //   592: ldc 707731490
    //   594: iastore
    //   595: dup
    //   596: bipush #28
    //   598: ldc 1043334948
    //   600: iastore
    //   601: dup
    //   602: bipush #29
    //   604: ldc 439222784
    //   606: iastore
    //   607: dup
    //   608: bipush #30
    //   610: ldc 876216579
    //   612: iastore
    //   613: dup
    //   614: bipush #31
    //   616: ldc 455999525
    //   618: iastore
    //   619: astore #5
    //   621: bipush #8
    //   623: aload_3
    //   624: arraylength
    //   625: bipush #8
    //   627: irem
    //   628: isub
    //   629: istore #6
    //   631: aload_3
    //   632: arraylength
    //   633: iload #6
    //   635: iadd
    //   636: newarray byte
    //   638: astore #7
    //   640: iconst_0
    //   641: istore #8
    //   643: iload #8
    //   645: aload_3
    //   646: arraylength
    //   647: if_icmpge -> 666
    //   650: aload #7
    //   652: iload #8
    //   654: aload_3
    //   655: iload #8
    //   657: baload
    //   658: bastore
    //   659: iinc #8, 1
    //   662: iload_2
    //   663: ifne -> 643
    //   666: aload_3
    //   667: arraylength
    //   668: istore #8
    //   670: iload #8
    //   672: aload #7
    //   674: arraylength
    //   675: if_icmpge -> 693
    //   678: aload #7
    //   680: iload #8
    //   682: iload #6
    //   684: i2b
    //   685: bastore
    //   686: iinc #8, 1
    //   689: iload_2
    //   690: ifne -> 670
    //   693: aload #7
    //   695: astore_3
    //   696: bipush #64
    //   698: newarray int
    //   700: dup
    //   701: iconst_0
    //   702: ldc 16843776
    //   704: iastore
    //   705: dup
    //   706: iconst_1
    //   707: iconst_0
    //   708: iastore
    //   709: dup
    //   710: iconst_2
    //   711: ldc 65536
    //   713: iastore
    //   714: dup
    //   715: iconst_3
    //   716: ldc 16843780
    //   718: iastore
    //   719: dup
    //   720: iconst_4
    //   721: ldc 16842756
    //   723: iastore
    //   724: dup
    //   725: iconst_5
    //   726: ldc 66564
    //   728: iastore
    //   729: dup
    //   730: bipush #6
    //   732: iconst_4
    //   733: iastore
    //   734: dup
    //   735: bipush #7
    //   737: ldc 65536
    //   739: iastore
    //   740: dup
    //   741: bipush #8
    //   743: sipush #1024
    //   746: iastore
    //   747: dup
    //   748: bipush #9
    //   750: ldc 16843776
    //   752: iastore
    //   753: dup
    //   754: bipush #10
    //   756: ldc 16843780
    //   758: iastore
    //   759: dup
    //   760: bipush #11
    //   762: sipush #1024
    //   765: iastore
    //   766: dup
    //   767: bipush #12
    //   769: ldc 16778244
    //   771: iastore
    //   772: dup
    //   773: bipush #13
    //   775: ldc 16842756
    //   777: iastore
    //   778: dup
    //   779: bipush #14
    //   781: ldc 16777216
    //   783: iastore
    //   784: dup
    //   785: bipush #15
    //   787: iconst_4
    //   788: iastore
    //   789: dup
    //   790: bipush #16
    //   792: sipush #1028
    //   795: iastore
    //   796: dup
    //   797: bipush #17
    //   799: ldc 16778240
    //   801: iastore
    //   802: dup
    //   803: bipush #18
    //   805: ldc 16778240
    //   807: iastore
    //   808: dup
    //   809: bipush #19
    //   811: ldc 66560
    //   813: iastore
    //   814: dup
    //   815: bipush #20
    //   817: ldc 66560
    //   819: iastore
    //   820: dup
    //   821: bipush #21
    //   823: ldc 16842752
    //   825: iastore
    //   826: dup
    //   827: bipush #22
    //   829: ldc 16842752
    //   831: iastore
    //   832: dup
    //   833: bipush #23
    //   835: ldc 16778244
    //   837: iastore
    //   838: dup
    //   839: bipush #24
    //   841: ldc 65540
    //   843: iastore
    //   844: dup
    //   845: bipush #25
    //   847: ldc 16777220
    //   849: iastore
    //   850: dup
    //   851: bipush #26
    //   853: ldc 16777220
    //   855: iastore
    //   856: dup
    //   857: bipush #27
    //   859: ldc 65540
    //   861: iastore
    //   862: dup
    //   863: bipush #28
    //   865: iconst_0
    //   866: iastore
    //   867: dup
    //   868: bipush #29
    //   870: sipush #1028
    //   873: iastore
    //   874: dup
    //   875: bipush #30
    //   877: ldc 66564
    //   879: iastore
    //   880: dup
    //   881: bipush #31
    //   883: ldc 16777216
    //   885: iastore
    //   886: dup
    //   887: bipush #32
    //   889: ldc 65536
    //   891: iastore
    //   892: dup
    //   893: bipush #33
    //   895: ldc 16843780
    //   897: iastore
    //   898: dup
    //   899: bipush #34
    //   901: iconst_4
    //   902: iastore
    //   903: dup
    //   904: bipush #35
    //   906: ldc 16842752
    //   908: iastore
    //   909: dup
    //   910: bipush #36
    //   912: ldc 16843776
    //   914: iastore
    //   915: dup
    //   916: bipush #37
    //   918: ldc 16777216
    //   920: iastore
    //   921: dup
    //   922: bipush #38
    //   924: ldc 16777216
    //   926: iastore
    //   927: dup
    //   928: bipush #39
    //   930: sipush #1024
    //   933: iastore
    //   934: dup
    //   935: bipush #40
    //   937: ldc 16842756
    //   939: iastore
    //   940: dup
    //   941: bipush #41
    //   943: ldc 65536
    //   945: iastore
    //   946: dup
    //   947: bipush #42
    //   949: ldc 66560
    //   951: iastore
    //   952: dup
    //   953: bipush #43
    //   955: ldc 16777220
    //   957: iastore
    //   958: dup
    //   959: bipush #44
    //   961: sipush #1024
    //   964: iastore
    //   965: dup
    //   966: bipush #45
    //   968: iconst_4
    //   969: iastore
    //   970: dup
    //   971: bipush #46
    //   973: ldc 16778244
    //   975: iastore
    //   976: dup
    //   977: bipush #47
    //   979: ldc 66564
    //   981: iastore
    //   982: dup
    //   983: bipush #48
    //   985: ldc 16843780
    //   987: iastore
    //   988: dup
    //   989: bipush #49
    //   991: ldc 65540
    //   993: iastore
    //   994: dup
    //   995: bipush #50
    //   997: ldc 16842752
    //   999: iastore
    //   1000: dup
    //   1001: bipush #51
    //   1003: ldc 16778244
    //   1005: iastore
    //   1006: dup
    //   1007: bipush #52
    //   1009: ldc 16777220
    //   1011: iastore
    //   1012: dup
    //   1013: bipush #53
    //   1015: sipush #1028
    //   1018: iastore
    //   1019: dup
    //   1020: bipush #54
    //   1022: ldc 66564
    //   1024: iastore
    //   1025: dup
    //   1026: bipush #55
    //   1028: ldc 16843776
    //   1030: iastore
    //   1031: dup
    //   1032: bipush #56
    //   1034: sipush #1028
    //   1037: iastore
    //   1038: dup
    //   1039: bipush #57
    //   1041: ldc 16778240
    //   1043: iastore
    //   1044: dup
    //   1045: bipush #58
    //   1047: ldc 16778240
    //   1049: iastore
    //   1050: dup
    //   1051: bipush #59
    //   1053: iconst_0
    //   1054: iastore
    //   1055: dup
    //   1056: bipush #60
    //   1058: ldc 65540
    //   1060: iastore
    //   1061: dup
    //   1062: bipush #61
    //   1064: ldc 66560
    //   1066: iastore
    //   1067: dup
    //   1068: bipush #62
    //   1070: iconst_0
    //   1071: iastore
    //   1072: dup
    //   1073: bipush #63
    //   1075: ldc 16842756
    //   1077: iastore
    //   1078: astore #8
    //   1080: bipush #64
    //   1082: newarray int
    //   1084: dup
    //   1085: iconst_0
    //   1086: ldc -2146402272
    //   1088: iastore
    //   1089: dup
    //   1090: iconst_1
    //   1091: ldc -2147450880
    //   1093: iastore
    //   1094: dup
    //   1095: iconst_2
    //   1096: ldc 32768
    //   1098: iastore
    //   1099: dup
    //   1100: iconst_3
    //   1101: ldc 1081376
    //   1103: iastore
    //   1104: dup
    //   1105: iconst_4
    //   1106: ldc 1048576
    //   1108: iastore
    //   1109: dup
    //   1110: iconst_5
    //   1111: bipush #32
    //   1113: iastore
    //   1114: dup
    //   1115: bipush #6
    //   1117: ldc -2146435040
    //   1119: iastore
    //   1120: dup
    //   1121: bipush #7
    //   1123: ldc -2147450848
    //   1125: iastore
    //   1126: dup
    //   1127: bipush #8
    //   1129: ldc -2147483616
    //   1131: iastore
    //   1132: dup
    //   1133: bipush #9
    //   1135: ldc -2146402272
    //   1137: iastore
    //   1138: dup
    //   1139: bipush #10
    //   1141: ldc -2146402304
    //   1143: iastore
    //   1144: dup
    //   1145: bipush #11
    //   1147: ldc -2147483648
    //   1149: iastore
    //   1150: dup
    //   1151: bipush #12
    //   1153: ldc -2147450880
    //   1155: iastore
    //   1156: dup
    //   1157: bipush #13
    //   1159: ldc 1048576
    //   1161: iastore
    //   1162: dup
    //   1163: bipush #14
    //   1165: bipush #32
    //   1167: iastore
    //   1168: dup
    //   1169: bipush #15
    //   1171: ldc -2146435040
    //   1173: iastore
    //   1174: dup
    //   1175: bipush #16
    //   1177: ldc 1081344
    //   1179: iastore
    //   1180: dup
    //   1181: bipush #17
    //   1183: ldc 1048608
    //   1185: iastore
    //   1186: dup
    //   1187: bipush #18
    //   1189: ldc -2147450848
    //   1191: iastore
    //   1192: dup
    //   1193: bipush #19
    //   1195: iconst_0
    //   1196: iastore
    //   1197: dup
    //   1198: bipush #20
    //   1200: ldc -2147483648
    //   1202: iastore
    //   1203: dup
    //   1204: bipush #21
    //   1206: ldc 32768
    //   1208: iastore
    //   1209: dup
    //   1210: bipush #22
    //   1212: ldc 1081376
    //   1214: iastore
    //   1215: dup
    //   1216: bipush #23
    //   1218: ldc -2146435072
    //   1220: iastore
    //   1221: dup
    //   1222: bipush #24
    //   1224: ldc 1048608
    //   1226: iastore
    //   1227: dup
    //   1228: bipush #25
    //   1230: ldc -2147483616
    //   1232: iastore
    //   1233: dup
    //   1234: bipush #26
    //   1236: iconst_0
    //   1237: iastore
    //   1238: dup
    //   1239: bipush #27
    //   1241: ldc 1081344
    //   1243: iastore
    //   1244: dup
    //   1245: bipush #28
    //   1247: ldc 32800
    //   1249: iastore
    //   1250: dup
    //   1251: bipush #29
    //   1253: ldc -2146402304
    //   1255: iastore
    //   1256: dup
    //   1257: bipush #30
    //   1259: ldc -2146435072
    //   1261: iastore
    //   1262: dup
    //   1263: bipush #31
    //   1265: ldc 32800
    //   1267: iastore
    //   1268: dup
    //   1269: bipush #32
    //   1271: iconst_0
    //   1272: iastore
    //   1273: dup
    //   1274: bipush #33
    //   1276: ldc 1081376
    //   1278: iastore
    //   1279: dup
    //   1280: bipush #34
    //   1282: ldc -2146435040
    //   1284: iastore
    //   1285: dup
    //   1286: bipush #35
    //   1288: ldc 1048576
    //   1290: iastore
    //   1291: dup
    //   1292: bipush #36
    //   1294: ldc -2147450848
    //   1296: iastore
    //   1297: dup
    //   1298: bipush #37
    //   1300: ldc -2146435072
    //   1302: iastore
    //   1303: dup
    //   1304: bipush #38
    //   1306: ldc -2146402304
    //   1308: iastore
    //   1309: dup
    //   1310: bipush #39
    //   1312: ldc 32768
    //   1314: iastore
    //   1315: dup
    //   1316: bipush #40
    //   1318: ldc -2146435072
    //   1320: iastore
    //   1321: dup
    //   1322: bipush #41
    //   1324: ldc -2147450880
    //   1326: iastore
    //   1327: dup
    //   1328: bipush #42
    //   1330: bipush #32
    //   1332: iastore
    //   1333: dup
    //   1334: bipush #43
    //   1336: ldc -2146402272
    //   1338: iastore
    //   1339: dup
    //   1340: bipush #44
    //   1342: ldc 1081376
    //   1344: iastore
    //   1345: dup
    //   1346: bipush #45
    //   1348: bipush #32
    //   1350: iastore
    //   1351: dup
    //   1352: bipush #46
    //   1354: ldc 32768
    //   1356: iastore
    //   1357: dup
    //   1358: bipush #47
    //   1360: ldc -2147483648
    //   1362: iastore
    //   1363: dup
    //   1364: bipush #48
    //   1366: ldc 32800
    //   1368: iastore
    //   1369: dup
    //   1370: bipush #49
    //   1372: ldc -2146402304
    //   1374: iastore
    //   1375: dup
    //   1376: bipush #50
    //   1378: ldc 1048576
    //   1380: iastore
    //   1381: dup
    //   1382: bipush #51
    //   1384: ldc -2147483616
    //   1386: iastore
    //   1387: dup
    //   1388: bipush #52
    //   1390: ldc 1048608
    //   1392: iastore
    //   1393: dup
    //   1394: bipush #53
    //   1396: ldc -2147450848
    //   1398: iastore
    //   1399: dup
    //   1400: bipush #54
    //   1402: ldc -2147483616
    //   1404: iastore
    //   1405: dup
    //   1406: bipush #55
    //   1408: ldc 1048608
    //   1410: iastore
    //   1411: dup
    //   1412: bipush #56
    //   1414: ldc 1081344
    //   1416: iastore
    //   1417: dup
    //   1418: bipush #57
    //   1420: iconst_0
    //   1421: iastore
    //   1422: dup
    //   1423: bipush #58
    //   1425: ldc -2147450880
    //   1427: iastore
    //   1428: dup
    //   1429: bipush #59
    //   1431: ldc 32800
    //   1433: iastore
    //   1434: dup
    //   1435: bipush #60
    //   1437: ldc -2147483648
    //   1439: iastore
    //   1440: dup
    //   1441: bipush #61
    //   1443: ldc -2146435040
    //   1445: iastore
    //   1446: dup
    //   1447: bipush #62
    //   1449: ldc -2146402272
    //   1451: iastore
    //   1452: dup
    //   1453: bipush #63
    //   1455: ldc 1081344
    //   1457: iastore
    //   1458: astore #9
    //   1460: bipush #64
    //   1462: newarray int
    //   1464: dup
    //   1465: iconst_0
    //   1466: sipush #520
    //   1469: iastore
    //   1470: dup
    //   1471: iconst_1
    //   1472: ldc 134349312
    //   1474: iastore
    //   1475: dup
    //   1476: iconst_2
    //   1477: iconst_0
    //   1478: iastore
    //   1479: dup
    //   1480: iconst_3
    //   1481: ldc 134348808
    //   1483: iastore
    //   1484: dup
    //   1485: iconst_4
    //   1486: ldc 134218240
    //   1488: iastore
    //   1489: dup
    //   1490: iconst_5
    //   1491: iconst_0
    //   1492: iastore
    //   1493: dup
    //   1494: bipush #6
    //   1496: ldc 131592
    //   1498: iastore
    //   1499: dup
    //   1500: bipush #7
    //   1502: ldc 134218240
    //   1504: iastore
    //   1505: dup
    //   1506: bipush #8
    //   1508: ldc 131080
    //   1510: iastore
    //   1511: dup
    //   1512: bipush #9
    //   1514: ldc 134217736
    //   1516: iastore
    //   1517: dup
    //   1518: bipush #10
    //   1520: ldc 134217736
    //   1522: iastore
    //   1523: dup
    //   1524: bipush #11
    //   1526: ldc 131072
    //   1528: iastore
    //   1529: dup
    //   1530: bipush #12
    //   1532: ldc 134349320
    //   1534: iastore
    //   1535: dup
    //   1536: bipush #13
    //   1538: ldc 131080
    //   1540: iastore
    //   1541: dup
    //   1542: bipush #14
    //   1544: ldc 134348800
    //   1546: iastore
    //   1547: dup
    //   1548: bipush #15
    //   1550: sipush #520
    //   1553: iastore
    //   1554: dup
    //   1555: bipush #16
    //   1557: ldc 134217728
    //   1559: iastore
    //   1560: dup
    //   1561: bipush #17
    //   1563: bipush #8
    //   1565: iastore
    //   1566: dup
    //   1567: bipush #18
    //   1569: ldc 134349312
    //   1571: iastore
    //   1572: dup
    //   1573: bipush #19
    //   1575: sipush #512
    //   1578: iastore
    //   1579: dup
    //   1580: bipush #20
    //   1582: ldc 131584
    //   1584: iastore
    //   1585: dup
    //   1586: bipush #21
    //   1588: ldc 134348800
    //   1590: iastore
    //   1591: dup
    //   1592: bipush #22
    //   1594: ldc 134348808
    //   1596: iastore
    //   1597: dup
    //   1598: bipush #23
    //   1600: ldc 131592
    //   1602: iastore
    //   1603: dup
    //   1604: bipush #24
    //   1606: ldc 134218248
    //   1608: iastore
    //   1609: dup
    //   1610: bipush #25
    //   1612: ldc 131584
    //   1614: iastore
    //   1615: dup
    //   1616: bipush #26
    //   1618: ldc 131072
    //   1620: iastore
    //   1621: dup
    //   1622: bipush #27
    //   1624: ldc 134218248
    //   1626: iastore
    //   1627: dup
    //   1628: bipush #28
    //   1630: bipush #8
    //   1632: iastore
    //   1633: dup
    //   1634: bipush #29
    //   1636: ldc 134349320
    //   1638: iastore
    //   1639: dup
    //   1640: bipush #30
    //   1642: sipush #512
    //   1645: iastore
    //   1646: dup
    //   1647: bipush #31
    //   1649: ldc 134217728
    //   1651: iastore
    //   1652: dup
    //   1653: bipush #32
    //   1655: ldc 134349312
    //   1657: iastore
    //   1658: dup
    //   1659: bipush #33
    //   1661: ldc 134217728
    //   1663: iastore
    //   1664: dup
    //   1665: bipush #34
    //   1667: ldc 131080
    //   1669: iastore
    //   1670: dup
    //   1671: bipush #35
    //   1673: sipush #520
    //   1676: iastore
    //   1677: dup
    //   1678: bipush #36
    //   1680: ldc 131072
    //   1682: iastore
    //   1683: dup
    //   1684: bipush #37
    //   1686: ldc 134349312
    //   1688: iastore
    //   1689: dup
    //   1690: bipush #38
    //   1692: ldc 134218240
    //   1694: iastore
    //   1695: dup
    //   1696: bipush #39
    //   1698: iconst_0
    //   1699: iastore
    //   1700: dup
    //   1701: bipush #40
    //   1703: sipush #512
    //   1706: iastore
    //   1707: dup
    //   1708: bipush #41
    //   1710: ldc 131080
    //   1712: iastore
    //   1713: dup
    //   1714: bipush #42
    //   1716: ldc 134349320
    //   1718: iastore
    //   1719: dup
    //   1720: bipush #43
    //   1722: ldc 134218240
    //   1724: iastore
    //   1725: dup
    //   1726: bipush #44
    //   1728: ldc 134217736
    //   1730: iastore
    //   1731: dup
    //   1732: bipush #45
    //   1734: sipush #512
    //   1737: iastore
    //   1738: dup
    //   1739: bipush #46
    //   1741: iconst_0
    //   1742: iastore
    //   1743: dup
    //   1744: bipush #47
    //   1746: ldc 134348808
    //   1748: iastore
    //   1749: dup
    //   1750: bipush #48
    //   1752: ldc 134218248
    //   1754: iastore
    //   1755: dup
    //   1756: bipush #49
    //   1758: ldc 131072
    //   1760: iastore
    //   1761: dup
    //   1762: bipush #50
    //   1764: ldc 134217728
    //   1766: iastore
    //   1767: dup
    //   1768: bipush #51
    //   1770: ldc 134349320
    //   1772: iastore
    //   1773: dup
    //   1774: bipush #52
    //   1776: bipush #8
    //   1778: iastore
    //   1779: dup
    //   1780: bipush #53
    //   1782: ldc 131592
    //   1784: iastore
    //   1785: dup
    //   1786: bipush #54
    //   1788: ldc 131584
    //   1790: iastore
    //   1791: dup
    //   1792: bipush #55
    //   1794: ldc 134217736
    //   1796: iastore
    //   1797: dup
    //   1798: bipush #56
    //   1800: ldc 134348800
    //   1802: iastore
    //   1803: dup
    //   1804: bipush #57
    //   1806: ldc 134218248
    //   1808: iastore
    //   1809: dup
    //   1810: bipush #58
    //   1812: sipush #520
    //   1815: iastore
    //   1816: dup
    //   1817: bipush #59
    //   1819: ldc 134348800
    //   1821: iastore
    //   1822: dup
    //   1823: bipush #60
    //   1825: ldc 131592
    //   1827: iastore
    //   1828: dup
    //   1829: bipush #61
    //   1831: bipush #8
    //   1833: iastore
    //   1834: dup
    //   1835: bipush #62
    //   1837: ldc 134348808
    //   1839: iastore
    //   1840: dup
    //   1841: bipush #63
    //   1843: ldc 131584
    //   1845: iastore
    //   1846: astore #10
    //   1848: bipush #64
    //   1850: newarray int
    //   1852: dup
    //   1853: iconst_0
    //   1854: ldc 8396801
    //   1856: iastore
    //   1857: dup
    //   1858: iconst_1
    //   1859: sipush #8321
    //   1862: iastore
    //   1863: dup
    //   1864: iconst_2
    //   1865: sipush #8321
    //   1868: iastore
    //   1869: dup
    //   1870: iconst_3
    //   1871: sipush #128
    //   1874: iastore
    //   1875: dup
    //   1876: iconst_4
    //   1877: ldc 8396928
    //   1879: iastore
    //   1880: dup
    //   1881: iconst_5
    //   1882: ldc 8388737
    //   1884: iastore
    //   1885: dup
    //   1886: bipush #6
    //   1888: ldc 8388609
    //   1890: iastore
    //   1891: dup
    //   1892: bipush #7
    //   1894: sipush #8193
    //   1897: iastore
    //   1898: dup
    //   1899: bipush #8
    //   1901: iconst_0
    //   1902: iastore
    //   1903: dup
    //   1904: bipush #9
    //   1906: ldc 8396800
    //   1908: iastore
    //   1909: dup
    //   1910: bipush #10
    //   1912: ldc 8396800
    //   1914: iastore
    //   1915: dup
    //   1916: bipush #11
    //   1918: ldc 8396929
    //   1920: iastore
    //   1921: dup
    //   1922: bipush #12
    //   1924: sipush #129
    //   1927: iastore
    //   1928: dup
    //   1929: bipush #13
    //   1931: iconst_0
    //   1932: iastore
    //   1933: dup
    //   1934: bipush #14
    //   1936: ldc 8388736
    //   1938: iastore
    //   1939: dup
    //   1940: bipush #15
    //   1942: ldc 8388609
    //   1944: iastore
    //   1945: dup
    //   1946: bipush #16
    //   1948: iconst_1
    //   1949: iastore
    //   1950: dup
    //   1951: bipush #17
    //   1953: sipush #8192
    //   1956: iastore
    //   1957: dup
    //   1958: bipush #18
    //   1960: ldc 8388608
    //   1962: iastore
    //   1963: dup
    //   1964: bipush #19
    //   1966: ldc 8396801
    //   1968: iastore
    //   1969: dup
    //   1970: bipush #20
    //   1972: sipush #128
    //   1975: iastore
    //   1976: dup
    //   1977: bipush #21
    //   1979: ldc 8388608
    //   1981: iastore
    //   1982: dup
    //   1983: bipush #22
    //   1985: sipush #8193
    //   1988: iastore
    //   1989: dup
    //   1990: bipush #23
    //   1992: sipush #8320
    //   1995: iastore
    //   1996: dup
    //   1997: bipush #24
    //   1999: ldc 8388737
    //   2001: iastore
    //   2002: dup
    //   2003: bipush #25
    //   2005: iconst_1
    //   2006: iastore
    //   2007: dup
    //   2008: bipush #26
    //   2010: sipush #8320
    //   2013: iastore
    //   2014: dup
    //   2015: bipush #27
    //   2017: ldc 8388736
    //   2019: iastore
    //   2020: dup
    //   2021: bipush #28
    //   2023: sipush #8192
    //   2026: iastore
    //   2027: dup
    //   2028: bipush #29
    //   2030: ldc 8396928
    //   2032: iastore
    //   2033: dup
    //   2034: bipush #30
    //   2036: ldc 8396929
    //   2038: iastore
    //   2039: dup
    //   2040: bipush #31
    //   2042: sipush #129
    //   2045: iastore
    //   2046: dup
    //   2047: bipush #32
    //   2049: ldc 8388736
    //   2051: iastore
    //   2052: dup
    //   2053: bipush #33
    //   2055: ldc 8388609
    //   2057: iastore
    //   2058: dup
    //   2059: bipush #34
    //   2061: ldc 8396800
    //   2063: iastore
    //   2064: dup
    //   2065: bipush #35
    //   2067: ldc 8396929
    //   2069: iastore
    //   2070: dup
    //   2071: bipush #36
    //   2073: sipush #129
    //   2076: iastore
    //   2077: dup
    //   2078: bipush #37
    //   2080: iconst_0
    //   2081: iastore
    //   2082: dup
    //   2083: bipush #38
    //   2085: iconst_0
    //   2086: iastore
    //   2087: dup
    //   2088: bipush #39
    //   2090: ldc 8396800
    //   2092: iastore
    //   2093: dup
    //   2094: bipush #40
    //   2096: sipush #8320
    //   2099: iastore
    //   2100: dup
    //   2101: bipush #41
    //   2103: ldc 8388736
    //   2105: iastore
    //   2106: dup
    //   2107: bipush #42
    //   2109: ldc 8388737
    //   2111: iastore
    //   2112: dup
    //   2113: bipush #43
    //   2115: iconst_1
    //   2116: iastore
    //   2117: dup
    //   2118: bipush #44
    //   2120: ldc 8396801
    //   2122: iastore
    //   2123: dup
    //   2124: bipush #45
    //   2126: sipush #8321
    //   2129: iastore
    //   2130: dup
    //   2131: bipush #46
    //   2133: sipush #8321
    //   2136: iastore
    //   2137: dup
    //   2138: bipush #47
    //   2140: sipush #128
    //   2143: iastore
    //   2144: dup
    //   2145: bipush #48
    //   2147: ldc 8396929
    //   2149: iastore
    //   2150: dup
    //   2151: bipush #49
    //   2153: sipush #129
    //   2156: iastore
    //   2157: dup
    //   2158: bipush #50
    //   2160: iconst_1
    //   2161: iastore
    //   2162: dup
    //   2163: bipush #51
    //   2165: sipush #8192
    //   2168: iastore
    //   2169: dup
    //   2170: bipush #52
    //   2172: ldc 8388609
    //   2174: iastore
    //   2175: dup
    //   2176: bipush #53
    //   2178: sipush #8193
    //   2181: iastore
    //   2182: dup
    //   2183: bipush #54
    //   2185: ldc 8396928
    //   2187: iastore
    //   2188: dup
    //   2189: bipush #55
    //   2191: ldc 8388737
    //   2193: iastore
    //   2194: dup
    //   2195: bipush #56
    //   2197: sipush #8193
    //   2200: iastore
    //   2201: dup
    //   2202: bipush #57
    //   2204: sipush #8320
    //   2207: iastore
    //   2208: dup
    //   2209: bipush #58
    //   2211: ldc 8388608
    //   2213: iastore
    //   2214: dup
    //   2215: bipush #59
    //   2217: ldc 8396801
    //   2219: iastore
    //   2220: dup
    //   2221: bipush #60
    //   2223: sipush #128
    //   2226: iastore
    //   2227: dup
    //   2228: bipush #61
    //   2230: ldc 8388608
    //   2232: iastore
    //   2233: dup
    //   2234: bipush #62
    //   2236: sipush #8192
    //   2239: iastore
    //   2240: dup
    //   2241: bipush #63
    //   2243: ldc 8396928
    //   2245: iastore
    //   2246: astore #11
    //   2248: bipush #64
    //   2250: newarray int
    //   2252: dup
    //   2253: iconst_0
    //   2254: sipush #256
    //   2257: iastore
    //   2258: dup
    //   2259: iconst_1
    //   2260: ldc 34078976
    //   2262: iastore
    //   2263: dup
    //   2264: iconst_2
    //   2265: ldc 34078720
    //   2267: iastore
    //   2268: dup
    //   2269: iconst_3
    //   2270: ldc 1107296512
    //   2272: iastore
    //   2273: dup
    //   2274: iconst_4
    //   2275: ldc 524288
    //   2277: iastore
    //   2278: dup
    //   2279: iconst_5
    //   2280: sipush #256
    //   2283: iastore
    //   2284: dup
    //   2285: bipush #6
    //   2287: ldc 1073741824
    //   2289: iastore
    //   2290: dup
    //   2291: bipush #7
    //   2293: ldc 34078720
    //   2295: iastore
    //   2296: dup
    //   2297: bipush #8
    //   2299: ldc 1074266368
    //   2301: iastore
    //   2302: dup
    //   2303: bipush #9
    //   2305: ldc 524288
    //   2307: iastore
    //   2308: dup
    //   2309: bipush #10
    //   2311: ldc 33554688
    //   2313: iastore
    //   2314: dup
    //   2315: bipush #11
    //   2317: ldc 1074266368
    //   2319: iastore
    //   2320: dup
    //   2321: bipush #12
    //   2323: ldc 1107296512
    //   2325: iastore
    //   2326: dup
    //   2327: bipush #13
    //   2329: ldc 1107820544
    //   2331: iastore
    //   2332: dup
    //   2333: bipush #14
    //   2335: ldc 524544
    //   2337: iastore
    //   2338: dup
    //   2339: bipush #15
    //   2341: ldc 1073741824
    //   2343: iastore
    //   2344: dup
    //   2345: bipush #16
    //   2347: ldc 33554432
    //   2349: iastore
    //   2350: dup
    //   2351: bipush #17
    //   2353: ldc 1074266112
    //   2355: iastore
    //   2356: dup
    //   2357: bipush #18
    //   2359: ldc 1074266112
    //   2361: iastore
    //   2362: dup
    //   2363: bipush #19
    //   2365: iconst_0
    //   2366: iastore
    //   2367: dup
    //   2368: bipush #20
    //   2370: ldc 1073742080
    //   2372: iastore
    //   2373: dup
    //   2374: bipush #21
    //   2376: ldc 1107820800
    //   2378: iastore
    //   2379: dup
    //   2380: bipush #22
    //   2382: ldc 1107820800
    //   2384: iastore
    //   2385: dup
    //   2386: bipush #23
    //   2388: ldc 33554688
    //   2390: iastore
    //   2391: dup
    //   2392: bipush #24
    //   2394: ldc 1107820544
    //   2396: iastore
    //   2397: dup
    //   2398: bipush #25
    //   2400: ldc 1073742080
    //   2402: iastore
    //   2403: dup
    //   2404: bipush #26
    //   2406: iconst_0
    //   2407: iastore
    //   2408: dup
    //   2409: bipush #27
    //   2411: ldc 1107296256
    //   2413: iastore
    //   2414: dup
    //   2415: bipush #28
    //   2417: ldc 34078976
    //   2419: iastore
    //   2420: dup
    //   2421: bipush #29
    //   2423: ldc 33554432
    //   2425: iastore
    //   2426: dup
    //   2427: bipush #30
    //   2429: ldc 1107296256
    //   2431: iastore
    //   2432: dup
    //   2433: bipush #31
    //   2435: ldc 524544
    //   2437: iastore
    //   2438: dup
    //   2439: bipush #32
    //   2441: ldc 524288
    //   2443: iastore
    //   2444: dup
    //   2445: bipush #33
    //   2447: ldc 1107296512
    //   2449: iastore
    //   2450: dup
    //   2451: bipush #34
    //   2453: sipush #256
    //   2456: iastore
    //   2457: dup
    //   2458: bipush #35
    //   2460: ldc 33554432
    //   2462: iastore
    //   2463: dup
    //   2464: bipush #36
    //   2466: ldc 1073741824
    //   2468: iastore
    //   2469: dup
    //   2470: bipush #37
    //   2472: ldc 34078720
    //   2474: iastore
    //   2475: dup
    //   2476: bipush #38
    //   2478: ldc 1107296512
    //   2480: iastore
    //   2481: dup
    //   2482: bipush #39
    //   2484: ldc 1074266368
    //   2486: iastore
    //   2487: dup
    //   2488: bipush #40
    //   2490: ldc 33554688
    //   2492: iastore
    //   2493: dup
    //   2494: bipush #41
    //   2496: ldc 1073741824
    //   2498: iastore
    //   2499: dup
    //   2500: bipush #42
    //   2502: ldc 1107820544
    //   2504: iastore
    //   2505: dup
    //   2506: bipush #43
    //   2508: ldc 34078976
    //   2510: iastore
    //   2511: dup
    //   2512: bipush #44
    //   2514: ldc 1074266368
    //   2516: iastore
    //   2517: dup
    //   2518: bipush #45
    //   2520: sipush #256
    //   2523: iastore
    //   2524: dup
    //   2525: bipush #46
    //   2527: ldc 33554432
    //   2529: iastore
    //   2530: dup
    //   2531: bipush #47
    //   2533: ldc 1107820544
    //   2535: iastore
    //   2536: dup
    //   2537: bipush #48
    //   2539: ldc 1107820800
    //   2541: iastore
    //   2542: dup
    //   2543: bipush #49
    //   2545: ldc 524544
    //   2547: iastore
    //   2548: dup
    //   2549: bipush #50
    //   2551: ldc 1107296256
    //   2553: iastore
    //   2554: dup
    //   2555: bipush #51
    //   2557: ldc 1107820800
    //   2559: iastore
    //   2560: dup
    //   2561: bipush #52
    //   2563: ldc 34078720
    //   2565: iastore
    //   2566: dup
    //   2567: bipush #53
    //   2569: iconst_0
    //   2570: iastore
    //   2571: dup
    //   2572: bipush #54
    //   2574: ldc 1074266112
    //   2576: iastore
    //   2577: dup
    //   2578: bipush #55
    //   2580: ldc 1107296256
    //   2582: iastore
    //   2583: dup
    //   2584: bipush #56
    //   2586: ldc 524544
    //   2588: iastore
    //   2589: dup
    //   2590: bipush #57
    //   2592: ldc 33554688
    //   2594: iastore
    //   2595: dup
    //   2596: bipush #58
    //   2598: ldc 1073742080
    //   2600: iastore
    //   2601: dup
    //   2602: bipush #59
    //   2604: ldc 524288
    //   2606: iastore
    //   2607: dup
    //   2608: bipush #60
    //   2610: iconst_0
    //   2611: iastore
    //   2612: dup
    //   2613: bipush #61
    //   2615: ldc 1074266112
    //   2617: iastore
    //   2618: dup
    //   2619: bipush #62
    //   2621: ldc 34078976
    //   2623: iastore
    //   2624: dup
    //   2625: bipush #63
    //   2627: ldc 1073742080
    //   2629: iastore
    //   2630: astore #12
    //   2632: bipush #64
    //   2634: newarray int
    //   2636: dup
    //   2637: iconst_0
    //   2638: ldc 536870928
    //   2640: iastore
    //   2641: dup
    //   2642: iconst_1
    //   2643: ldc 541065216
    //   2645: iastore
    //   2646: dup
    //   2647: iconst_2
    //   2648: sipush #16384
    //   2651: iastore
    //   2652: dup
    //   2653: iconst_3
    //   2654: ldc 541081616
    //   2656: iastore
    //   2657: dup
    //   2658: iconst_4
    //   2659: ldc 541065216
    //   2661: iastore
    //   2662: dup
    //   2663: iconst_5
    //   2664: bipush #16
    //   2666: iastore
    //   2667: dup
    //   2668: bipush #6
    //   2670: ldc 541081616
    //   2672: iastore
    //   2673: dup
    //   2674: bipush #7
    //   2676: ldc 4194304
    //   2678: iastore
    //   2679: dup
    //   2680: bipush #8
    //   2682: ldc 536887296
    //   2684: iastore
    //   2685: dup
    //   2686: bipush #9
    //   2688: ldc 4210704
    //   2690: iastore
    //   2691: dup
    //   2692: bipush #10
    //   2694: ldc 4194304
    //   2696: iastore
    //   2697: dup
    //   2698: bipush #11
    //   2700: ldc 536870928
    //   2702: iastore
    //   2703: dup
    //   2704: bipush #12
    //   2706: ldc 4194320
    //   2708: iastore
    //   2709: dup
    //   2710: bipush #13
    //   2712: ldc 536887296
    //   2714: iastore
    //   2715: dup
    //   2716: bipush #14
    //   2718: ldc 536870912
    //   2720: iastore
    //   2721: dup
    //   2722: bipush #15
    //   2724: sipush #16400
    //   2727: iastore
    //   2728: dup
    //   2729: bipush #16
    //   2731: iconst_0
    //   2732: iastore
    //   2733: dup
    //   2734: bipush #17
    //   2736: ldc 4194320
    //   2738: iastore
    //   2739: dup
    //   2740: bipush #18
    //   2742: ldc 536887312
    //   2744: iastore
    //   2745: dup
    //   2746: bipush #19
    //   2748: sipush #16384
    //   2751: iastore
    //   2752: dup
    //   2753: bipush #20
    //   2755: ldc 4210688
    //   2757: iastore
    //   2758: dup
    //   2759: bipush #21
    //   2761: ldc 536887312
    //   2763: iastore
    //   2764: dup
    //   2765: bipush #22
    //   2767: bipush #16
    //   2769: iastore
    //   2770: dup
    //   2771: bipush #23
    //   2773: ldc 541065232
    //   2775: iastore
    //   2776: dup
    //   2777: bipush #24
    //   2779: ldc 541065232
    //   2781: iastore
    //   2782: dup
    //   2783: bipush #25
    //   2785: iconst_0
    //   2786: iastore
    //   2787: dup
    //   2788: bipush #26
    //   2790: ldc 4210704
    //   2792: iastore
    //   2793: dup
    //   2794: bipush #27
    //   2796: ldc 541081600
    //   2798: iastore
    //   2799: dup
    //   2800: bipush #28
    //   2802: sipush #16400
    //   2805: iastore
    //   2806: dup
    //   2807: bipush #29
    //   2809: ldc 4210688
    //   2811: iastore
    //   2812: dup
    //   2813: bipush #30
    //   2815: ldc 541081600
    //   2817: iastore
    //   2818: dup
    //   2819: bipush #31
    //   2821: ldc 536870912
    //   2823: iastore
    //   2824: dup
    //   2825: bipush #32
    //   2827: ldc 536887296
    //   2829: iastore
    //   2830: dup
    //   2831: bipush #33
    //   2833: bipush #16
    //   2835: iastore
    //   2836: dup
    //   2837: bipush #34
    //   2839: ldc 541065232
    //   2841: iastore
    //   2842: dup
    //   2843: bipush #35
    //   2845: ldc 4210688
    //   2847: iastore
    //   2848: dup
    //   2849: bipush #36
    //   2851: ldc 541081616
    //   2853: iastore
    //   2854: dup
    //   2855: bipush #37
    //   2857: ldc 4194304
    //   2859: iastore
    //   2860: dup
    //   2861: bipush #38
    //   2863: sipush #16400
    //   2866: iastore
    //   2867: dup
    //   2868: bipush #39
    //   2870: ldc 536870928
    //   2872: iastore
    //   2873: dup
    //   2874: bipush #40
    //   2876: ldc 4194304
    //   2878: iastore
    //   2879: dup
    //   2880: bipush #41
    //   2882: ldc 536887296
    //   2884: iastore
    //   2885: dup
    //   2886: bipush #42
    //   2888: ldc 536870912
    //   2890: iastore
    //   2891: dup
    //   2892: bipush #43
    //   2894: sipush #16400
    //   2897: iastore
    //   2898: dup
    //   2899: bipush #44
    //   2901: ldc 536870928
    //   2903: iastore
    //   2904: dup
    //   2905: bipush #45
    //   2907: ldc 541081616
    //   2909: iastore
    //   2910: dup
    //   2911: bipush #46
    //   2913: ldc 4210688
    //   2915: iastore
    //   2916: dup
    //   2917: bipush #47
    //   2919: ldc 541065216
    //   2921: iastore
    //   2922: dup
    //   2923: bipush #48
    //   2925: ldc 4210704
    //   2927: iastore
    //   2928: dup
    //   2929: bipush #49
    //   2931: ldc 541081600
    //   2933: iastore
    //   2934: dup
    //   2935: bipush #50
    //   2937: iconst_0
    //   2938: iastore
    //   2939: dup
    //   2940: bipush #51
    //   2942: ldc 541065232
    //   2944: iastore
    //   2945: dup
    //   2946: bipush #52
    //   2948: bipush #16
    //   2950: iastore
    //   2951: dup
    //   2952: bipush #53
    //   2954: sipush #16384
    //   2957: iastore
    //   2958: dup
    //   2959: bipush #54
    //   2961: ldc 541065216
    //   2963: iastore
    //   2964: dup
    //   2965: bipush #55
    //   2967: ldc 4210704
    //   2969: iastore
    //   2970: dup
    //   2971: bipush #56
    //   2973: sipush #16384
    //   2976: iastore
    //   2977: dup
    //   2978: bipush #57
    //   2980: ldc 4194320
    //   2982: iastore
    //   2983: dup
    //   2984: bipush #58
    //   2986: ldc 536887312
    //   2988: iastore
    //   2989: dup
    //   2990: bipush #59
    //   2992: iconst_0
    //   2993: iastore
    //   2994: dup
    //   2995: bipush #60
    //   2997: ldc 541081600
    //   2999: iastore
    //   3000: dup
    //   3001: bipush #61
    //   3003: ldc 536870912
    //   3005: iastore
    //   3006: dup
    //   3007: bipush #62
    //   3009: ldc 4194320
    //   3011: iastore
    //   3012: dup
    //   3013: bipush #63
    //   3015: ldc 536887312
    //   3017: iastore
    //   3018: astore #13
    //   3020: bipush #64
    //   3022: newarray int
    //   3024: dup
    //   3025: iconst_0
    //   3026: ldc 2097152
    //   3028: iastore
    //   3029: dup
    //   3030: iconst_1
    //   3031: ldc 69206018
    //   3033: iastore
    //   3034: dup
    //   3035: iconst_2
    //   3036: ldc 67110914
    //   3038: iastore
    //   3039: dup
    //   3040: iconst_3
    //   3041: iconst_0
    //   3042: iastore
    //   3043: dup
    //   3044: iconst_4
    //   3045: sipush #2048
    //   3048: iastore
    //   3049: dup
    //   3050: iconst_5
    //   3051: ldc 67110914
    //   3053: iastore
    //   3054: dup
    //   3055: bipush #6
    //   3057: ldc 2099202
    //   3059: iastore
    //   3060: dup
    //   3061: bipush #7
    //   3063: ldc 69208064
    //   3065: iastore
    //   3066: dup
    //   3067: bipush #8
    //   3069: ldc 69208066
    //   3071: iastore
    //   3072: dup
    //   3073: bipush #9
    //   3075: ldc 2097152
    //   3077: iastore
    //   3078: dup
    //   3079: bipush #10
    //   3081: iconst_0
    //   3082: iastore
    //   3083: dup
    //   3084: bipush #11
    //   3086: ldc 67108866
    //   3088: iastore
    //   3089: dup
    //   3090: bipush #12
    //   3092: iconst_2
    //   3093: iastore
    //   3094: dup
    //   3095: bipush #13
    //   3097: ldc 67108864
    //   3099: iastore
    //   3100: dup
    //   3101: bipush #14
    //   3103: ldc 69206018
    //   3105: iastore
    //   3106: dup
    //   3107: bipush #15
    //   3109: sipush #2050
    //   3112: iastore
    //   3113: dup
    //   3114: bipush #16
    //   3116: ldc 67110912
    //   3118: iastore
    //   3119: dup
    //   3120: bipush #17
    //   3122: ldc 2099202
    //   3124: iastore
    //   3125: dup
    //   3126: bipush #18
    //   3128: ldc 2097154
    //   3130: iastore
    //   3131: dup
    //   3132: bipush #19
    //   3134: ldc 67110912
    //   3136: iastore
    //   3137: dup
    //   3138: bipush #20
    //   3140: ldc 67108866
    //   3142: iastore
    //   3143: dup
    //   3144: bipush #21
    //   3146: ldc 69206016
    //   3148: iastore
    //   3149: dup
    //   3150: bipush #22
    //   3152: ldc 69208064
    //   3154: iastore
    //   3155: dup
    //   3156: bipush #23
    //   3158: ldc 2097154
    //   3160: iastore
    //   3161: dup
    //   3162: bipush #24
    //   3164: ldc 69206016
    //   3166: iastore
    //   3167: dup
    //   3168: bipush #25
    //   3170: sipush #2048
    //   3173: iastore
    //   3174: dup
    //   3175: bipush #26
    //   3177: sipush #2050
    //   3180: iastore
    //   3181: dup
    //   3182: bipush #27
    //   3184: ldc 69208066
    //   3186: iastore
    //   3187: dup
    //   3188: bipush #28
    //   3190: ldc 2099200
    //   3192: iastore
    //   3193: dup
    //   3194: bipush #29
    //   3196: iconst_2
    //   3197: iastore
    //   3198: dup
    //   3199: bipush #30
    //   3201: ldc 67108864
    //   3203: iastore
    //   3204: dup
    //   3205: bipush #31
    //   3207: ldc 2099200
    //   3209: iastore
    //   3210: dup
    //   3211: bipush #32
    //   3213: ldc 67108864
    //   3215: iastore
    //   3216: dup
    //   3217: bipush #33
    //   3219: ldc 2099200
    //   3221: iastore
    //   3222: dup
    //   3223: bipush #34
    //   3225: ldc 2097152
    //   3227: iastore
    //   3228: dup
    //   3229: bipush #35
    //   3231: ldc 67110914
    //   3233: iastore
    //   3234: dup
    //   3235: bipush #36
    //   3237: ldc 67110914
    //   3239: iastore
    //   3240: dup
    //   3241: bipush #37
    //   3243: ldc 69206018
    //   3245: iastore
    //   3246: dup
    //   3247: bipush #38
    //   3249: ldc 69206018
    //   3251: iastore
    //   3252: dup
    //   3253: bipush #39
    //   3255: iconst_2
    //   3256: iastore
    //   3257: dup
    //   3258: bipush #40
    //   3260: ldc 2097154
    //   3262: iastore
    //   3263: dup
    //   3264: bipush #41
    //   3266: ldc 67108864
    //   3268: iastore
    //   3269: dup
    //   3270: bipush #42
    //   3272: ldc 67110912
    //   3274: iastore
    //   3275: dup
    //   3276: bipush #43
    //   3278: ldc 2097152
    //   3280: iastore
    //   3281: dup
    //   3282: bipush #44
    //   3284: ldc 69208064
    //   3286: iastore
    //   3287: dup
    //   3288: bipush #45
    //   3290: sipush #2050
    //   3293: iastore
    //   3294: dup
    //   3295: bipush #46
    //   3297: ldc 2099202
    //   3299: iastore
    //   3300: dup
    //   3301: bipush #47
    //   3303: ldc 69208064
    //   3305: iastore
    //   3306: dup
    //   3307: bipush #48
    //   3309: sipush #2050
    //   3312: iastore
    //   3313: dup
    //   3314: bipush #49
    //   3316: ldc 67108866
    //   3318: iastore
    //   3319: dup
    //   3320: bipush #50
    //   3322: ldc 69208066
    //   3324: iastore
    //   3325: dup
    //   3326: bipush #51
    //   3328: ldc 69206016
    //   3330: iastore
    //   3331: dup
    //   3332: bipush #52
    //   3334: ldc 2099200
    //   3336: iastore
    //   3337: dup
    //   3338: bipush #53
    //   3340: iconst_0
    //   3341: iastore
    //   3342: dup
    //   3343: bipush #54
    //   3345: iconst_2
    //   3346: iastore
    //   3347: dup
    //   3348: bipush #55
    //   3350: ldc 69208066
    //   3352: iastore
    //   3353: dup
    //   3354: bipush #56
    //   3356: iconst_0
    //   3357: iastore
    //   3358: dup
    //   3359: bipush #57
    //   3361: ldc 2099202
    //   3363: iastore
    //   3364: dup
    //   3365: bipush #58
    //   3367: ldc 69206016
    //   3369: iastore
    //   3370: dup
    //   3371: bipush #59
    //   3373: sipush #2048
    //   3376: iastore
    //   3377: dup
    //   3378: bipush #60
    //   3380: ldc 67108866
    //   3382: iastore
    //   3383: dup
    //   3384: bipush #61
    //   3386: ldc 67110912
    //   3388: iastore
    //   3389: dup
    //   3390: bipush #62
    //   3392: sipush #2048
    //   3395: iastore
    //   3396: dup
    //   3397: bipush #63
    //   3399: ldc 2097154
    //   3401: iastore
    //   3402: astore #14
    //   3404: bipush #64
    //   3406: newarray int
    //   3408: dup
    //   3409: iconst_0
    //   3410: ldc 268439616
    //   3412: iastore
    //   3413: dup
    //   3414: iconst_1
    //   3415: sipush #4096
    //   3418: iastore
    //   3419: dup
    //   3420: iconst_2
    //   3421: ldc 262144
    //   3423: iastore
    //   3424: dup
    //   3425: iconst_3
    //   3426: ldc 268701760
    //   3428: iastore
    //   3429: dup
    //   3430: iconst_4
    //   3431: ldc 268435456
    //   3433: iastore
    //   3434: dup
    //   3435: iconst_5
    //   3436: ldc 268439616
    //   3438: iastore
    //   3439: dup
    //   3440: bipush #6
    //   3442: bipush #64
    //   3444: iastore
    //   3445: dup
    //   3446: bipush #7
    //   3448: ldc 268435456
    //   3450: iastore
    //   3451: dup
    //   3452: bipush #8
    //   3454: ldc 262208
    //   3456: iastore
    //   3457: dup
    //   3458: bipush #9
    //   3460: ldc 268697600
    //   3462: iastore
    //   3463: dup
    //   3464: bipush #10
    //   3466: ldc 268701760
    //   3468: iastore
    //   3469: dup
    //   3470: bipush #11
    //   3472: ldc 266240
    //   3474: iastore
    //   3475: dup
    //   3476: bipush #12
    //   3478: ldc 268701696
    //   3480: iastore
    //   3481: dup
    //   3482: bipush #13
    //   3484: ldc 266304
    //   3486: iastore
    //   3487: dup
    //   3488: bipush #14
    //   3490: sipush #4096
    //   3493: iastore
    //   3494: dup
    //   3495: bipush #15
    //   3497: bipush #64
    //   3499: iastore
    //   3500: dup
    //   3501: bipush #16
    //   3503: ldc 268697600
    //   3505: iastore
    //   3506: dup
    //   3507: bipush #17
    //   3509: ldc 268435520
    //   3511: iastore
    //   3512: dup
    //   3513: bipush #18
    //   3515: ldc 268439552
    //   3517: iastore
    //   3518: dup
    //   3519: bipush #19
    //   3521: sipush #4160
    //   3524: iastore
    //   3525: dup
    //   3526: bipush #20
    //   3528: ldc 266240
    //   3530: iastore
    //   3531: dup
    //   3532: bipush #21
    //   3534: ldc 262208
    //   3536: iastore
    //   3537: dup
    //   3538: bipush #22
    //   3540: ldc 268697664
    //   3542: iastore
    //   3543: dup
    //   3544: bipush #23
    //   3546: ldc 268701696
    //   3548: iastore
    //   3549: dup
    //   3550: bipush #24
    //   3552: sipush #4160
    //   3555: iastore
    //   3556: dup
    //   3557: bipush #25
    //   3559: iconst_0
    //   3560: iastore
    //   3561: dup
    //   3562: bipush #26
    //   3564: iconst_0
    //   3565: iastore
    //   3566: dup
    //   3567: bipush #27
    //   3569: ldc 268697664
    //   3571: iastore
    //   3572: dup
    //   3573: bipush #28
    //   3575: ldc 268435520
    //   3577: iastore
    //   3578: dup
    //   3579: bipush #29
    //   3581: ldc 268439552
    //   3583: iastore
    //   3584: dup
    //   3585: bipush #30
    //   3587: ldc 266304
    //   3589: iastore
    //   3590: dup
    //   3591: bipush #31
    //   3593: ldc 262144
    //   3595: iastore
    //   3596: dup
    //   3597: bipush #32
    //   3599: ldc 266304
    //   3601: iastore
    //   3602: dup
    //   3603: bipush #33
    //   3605: ldc 262144
    //   3607: iastore
    //   3608: dup
    //   3609: bipush #34
    //   3611: ldc 268701696
    //   3613: iastore
    //   3614: dup
    //   3615: bipush #35
    //   3617: sipush #4096
    //   3620: iastore
    //   3621: dup
    //   3622: bipush #36
    //   3624: bipush #64
    //   3626: iastore
    //   3627: dup
    //   3628: bipush #37
    //   3630: ldc 268697664
    //   3632: iastore
    //   3633: dup
    //   3634: bipush #38
    //   3636: sipush #4096
    //   3639: iastore
    //   3640: dup
    //   3641: bipush #39
    //   3643: ldc 266304
    //   3645: iastore
    //   3646: dup
    //   3647: bipush #40
    //   3649: ldc 268439552
    //   3651: iastore
    //   3652: dup
    //   3653: bipush #41
    //   3655: bipush #64
    //   3657: iastore
    //   3658: dup
    //   3659: bipush #42
    //   3661: ldc 268435520
    //   3663: iastore
    //   3664: dup
    //   3665: bipush #43
    //   3667: ldc 268697600
    //   3669: iastore
    //   3670: dup
    //   3671: bipush #44
    //   3673: ldc 268697664
    //   3675: iastore
    //   3676: dup
    //   3677: bipush #45
    //   3679: ldc 268435456
    //   3681: iastore
    //   3682: dup
    //   3683: bipush #46
    //   3685: ldc 262144
    //   3687: iastore
    //   3688: dup
    //   3689: bipush #47
    //   3691: ldc 268439616
    //   3693: iastore
    //   3694: dup
    //   3695: bipush #48
    //   3697: iconst_0
    //   3698: iastore
    //   3699: dup
    //   3700: bipush #49
    //   3702: ldc 268701760
    //   3704: iastore
    //   3705: dup
    //   3706: bipush #50
    //   3708: ldc 262208
    //   3710: iastore
    //   3711: dup
    //   3712: bipush #51
    //   3714: ldc 268435520
    //   3716: iastore
    //   3717: dup
    //   3718: bipush #52
    //   3720: ldc 268697600
    //   3722: iastore
    //   3723: dup
    //   3724: bipush #53
    //   3726: ldc 268439552
    //   3728: iastore
    //   3729: dup
    //   3730: bipush #54
    //   3732: ldc 268439616
    //   3734: iastore
    //   3735: dup
    //   3736: bipush #55
    //   3738: iconst_0
    //   3739: iastore
    //   3740: dup
    //   3741: bipush #56
    //   3743: ldc 268701760
    //   3745: iastore
    //   3746: dup
    //   3747: bipush #57
    //   3749: ldc 266240
    //   3751: iastore
    //   3752: dup
    //   3753: bipush #58
    //   3755: ldc 266240
    //   3757: iastore
    //   3758: dup
    //   3759: bipush #59
    //   3761: sipush #4160
    //   3764: iastore
    //   3765: dup
    //   3766: bipush #60
    //   3768: sipush #4160
    //   3771: iastore
    //   3772: dup
    //   3773: bipush #61
    //   3775: ldc 262208
    //   3777: iastore
    //   3778: dup
    //   3779: bipush #62
    //   3781: ldc 268435456
    //   3783: iastore
    //   3784: dup
    //   3785: bipush #63
    //   3787: ldc 268701696
    //   3789: iastore
    //   3790: astore #15
    //   3792: aload_3
    //   3793: arraylength
    //   3794: istore #16
    //   3796: iconst_2
    //   3797: newarray int
    //   3799: astore #17
    //   3801: iload #16
    //   3803: newarray byte
    //   3805: astore #4
    //   3807: iload #16
    //   3809: bipush #8
    //   3811: idiv
    //   3812: istore #18
    //   3814: iconst_0
    //   3815: istore #19
    //   3817: iload #19
    //   3819: iload #18
    //   3821: if_icmpge -> 4735
    //   3824: iload #19
    //   3826: bipush #8
    //   3828: imul
    //   3829: istore #20
    //   3831: iconst_0
    //   3832: istore #21
    //   3834: iload #21
    //   3836: iconst_2
    //   3837: if_icmpge -> 3922
    //   3840: aload #17
    //   3842: iload #21
    //   3844: aload_3
    //   3845: iload #20
    //   3847: iload #21
    //   3849: iconst_4
    //   3850: imul
    //   3851: iadd
    //   3852: baload
    //   3853: sipush #255
    //   3856: iand
    //   3857: bipush #24
    //   3859: ishl
    //   3860: aload_3
    //   3861: iload #20
    //   3863: iload #21
    //   3865: iconst_4
    //   3866: imul
    //   3867: iadd
    //   3868: iconst_1
    //   3869: iadd
    //   3870: baload
    //   3871: sipush #255
    //   3874: iand
    //   3875: bipush #16
    //   3877: ishl
    //   3878: ior
    //   3879: aload_3
    //   3880: iload #20
    //   3882: iload #21
    //   3884: iconst_4
    //   3885: imul
    //   3886: iadd
    //   3887: iconst_2
    //   3888: iadd
    //   3889: baload
    //   3890: sipush #255
    //   3893: iand
    //   3894: bipush #8
    //   3896: ishl
    //   3897: ior
    //   3898: aload_3
    //   3899: iload #20
    //   3901: iload #21
    //   3903: iconst_4
    //   3904: imul
    //   3905: iadd
    //   3906: iconst_3
    //   3907: iadd
    //   3908: baload
    //   3909: sipush #255
    //   3912: iand
    //   3913: ior
    //   3914: iastore
    //   3915: iinc #21, 1
    //   3918: iload_2
    //   3919: ifne -> 3834
    //   3922: iconst_0
    //   3923: istore #26
    //   3925: aload #17
    //   3927: iconst_0
    //   3928: iaload
    //   3929: istore #24
    //   3931: aload #17
    //   3933: iconst_1
    //   3934: iaload
    //   3935: istore #23
    //   3937: iload #24
    //   3939: iconst_4
    //   3940: iushr
    //   3941: iload #23
    //   3943: ixor
    //   3944: ldc 252645135
    //   3946: iand
    //   3947: istore #22
    //   3949: iload #23
    //   3951: iload #22
    //   3953: ixor
    //   3954: istore #23
    //   3956: iload #24
    //   3958: iload #22
    //   3960: iconst_4
    //   3961: ishl
    //   3962: ixor
    //   3963: istore #24
    //   3965: iload #24
    //   3967: bipush #16
    //   3969: iushr
    //   3970: iload #23
    //   3972: ixor
    //   3973: ldc 65535
    //   3975: iand
    //   3976: istore #22
    //   3978: iload #23
    //   3980: iload #22
    //   3982: ixor
    //   3983: istore #23
    //   3985: iload #24
    //   3987: iload #22
    //   3989: bipush #16
    //   3991: ishl
    //   3992: ixor
    //   3993: istore #24
    //   3995: iload #23
    //   3997: iconst_2
    //   3998: iushr
    //   3999: iload #24
    //   4001: ixor
    //   4002: ldc 858993459
    //   4004: iand
    //   4005: istore #22
    //   4007: iload #24
    //   4009: iload #22
    //   4011: ixor
    //   4012: istore #24
    //   4014: iload #23
    //   4016: iload #22
    //   4018: iconst_2
    //   4019: ishl
    //   4020: ixor
    //   4021: istore #23
    //   4023: iload #23
    //   4025: bipush #8
    //   4027: iushr
    //   4028: iload #24
    //   4030: ixor
    //   4031: ldc 16711935
    //   4033: iand
    //   4034: istore #22
    //   4036: iload #24
    //   4038: iload #22
    //   4040: ixor
    //   4041: istore #24
    //   4043: iload #23
    //   4045: iload #22
    //   4047: bipush #8
    //   4049: ishl
    //   4050: ixor
    //   4051: istore #23
    //   4053: iload #23
    //   4055: iconst_1
    //   4056: ishl
    //   4057: iload #23
    //   4059: bipush #31
    //   4061: iushr
    //   4062: iconst_1
    //   4063: iand
    //   4064: ior
    //   4065: istore #23
    //   4067: iload #24
    //   4069: iload #23
    //   4071: ixor
    //   4072: ldc -1431655766
    //   4074: iand
    //   4075: istore #22
    //   4077: iload #24
    //   4079: iload #22
    //   4081: ixor
    //   4082: istore #24
    //   4084: iload #23
    //   4086: iload #22
    //   4088: ixor
    //   4089: istore #23
    //   4091: iload #24
    //   4093: iconst_1
    //   4094: ishl
    //   4095: iload #24
    //   4097: bipush #31
    //   4099: iushr
    //   4100: iconst_1
    //   4101: iand
    //   4102: ior
    //   4103: istore #24
    //   4105: iconst_0
    //   4106: istore #25
    //   4108: iload #25
    //   4110: bipush #8
    //   4112: if_icmpge -> 4450
    //   4115: iload #23
    //   4117: bipush #28
    //   4119: ishl
    //   4120: iload #23
    //   4122: iconst_4
    //   4123: iushr
    //   4124: ior
    //   4125: istore #22
    //   4127: iload #22
    //   4129: aload #5
    //   4131: iload #26
    //   4133: iinc #26, 1
    //   4136: iaload
    //   4137: ixor
    //   4138: istore #22
    //   4140: aload #14
    //   4142: iload #22
    //   4144: bipush #63
    //   4146: iand
    //   4147: iaload
    //   4148: istore #21
    //   4150: iload #21
    //   4152: aload #12
    //   4154: iload #22
    //   4156: bipush #8
    //   4158: iushr
    //   4159: bipush #63
    //   4161: iand
    //   4162: iaload
    //   4163: ior
    //   4164: istore #21
    //   4166: iload #21
    //   4168: aload #10
    //   4170: iload #22
    //   4172: bipush #16
    //   4174: iushr
    //   4175: bipush #63
    //   4177: iand
    //   4178: iaload
    //   4179: ior
    //   4180: istore #21
    //   4182: iload #21
    //   4184: aload #8
    //   4186: iload #22
    //   4188: bipush #24
    //   4190: iushr
    //   4191: bipush #63
    //   4193: iand
    //   4194: iaload
    //   4195: ior
    //   4196: istore #21
    //   4198: iload #23
    //   4200: aload #5
    //   4202: iload #26
    //   4204: iinc #26, 1
    //   4207: iaload
    //   4208: ixor
    //   4209: istore #22
    //   4211: iload #21
    //   4213: aload #15
    //   4215: iload #22
    //   4217: bipush #63
    //   4219: iand
    //   4220: iaload
    //   4221: ior
    //   4222: istore #21
    //   4224: iload #21
    //   4226: aload #13
    //   4228: iload #22
    //   4230: bipush #8
    //   4232: iushr
    //   4233: bipush #63
    //   4235: iand
    //   4236: iaload
    //   4237: ior
    //   4238: istore #21
    //   4240: iload #21
    //   4242: aload #11
    //   4244: iload #22
    //   4246: bipush #16
    //   4248: iushr
    //   4249: bipush #63
    //   4251: iand
    //   4252: iaload
    //   4253: ior
    //   4254: istore #21
    //   4256: iload #21
    //   4258: aload #9
    //   4260: iload #22
    //   4262: bipush #24
    //   4264: iushr
    //   4265: bipush #63
    //   4267: iand
    //   4268: iaload
    //   4269: ior
    //   4270: istore #21
    //   4272: iload #24
    //   4274: iload #21
    //   4276: ixor
    //   4277: istore #24
    //   4279: iload #24
    //   4281: bipush #28
    //   4283: ishl
    //   4284: iload #24
    //   4286: iconst_4
    //   4287: iushr
    //   4288: ior
    //   4289: istore #22
    //   4291: iload #22
    //   4293: aload #5
    //   4295: iload #26
    //   4297: iinc #26, 1
    //   4300: iaload
    //   4301: ixor
    //   4302: istore #22
    //   4304: aload #14
    //   4306: iload #22
    //   4308: bipush #63
    //   4310: iand
    //   4311: iaload
    //   4312: istore #21
    //   4314: iload #21
    //   4316: aload #12
    //   4318: iload #22
    //   4320: bipush #8
    //   4322: iushr
    //   4323: bipush #63
    //   4325: iand
    //   4326: iaload
    //   4327: ior
    //   4328: istore #21
    //   4330: iload #21
    //   4332: aload #10
    //   4334: iload #22
    //   4336: bipush #16
    //   4338: iushr
    //   4339: bipush #63
    //   4341: iand
    //   4342: iaload
    //   4343: ior
    //   4344: istore #21
    //   4346: iload #21
    //   4348: aload #8
    //   4350: iload #22
    //   4352: bipush #24
    //   4354: iushr
    //   4355: bipush #63
    //   4357: iand
    //   4358: iaload
    //   4359: ior
    //   4360: istore #21
    //   4362: iload #24
    //   4364: aload #5
    //   4366: iload #26
    //   4368: iinc #26, 1
    //   4371: iaload
    //   4372: ixor
    //   4373: istore #22
    //   4375: iload #21
    //   4377: aload #15
    //   4379: iload #22
    //   4381: bipush #63
    //   4383: iand
    //   4384: iaload
    //   4385: ior
    //   4386: istore #21
    //   4388: iload #21
    //   4390: aload #13
    //   4392: iload #22
    //   4394: bipush #8
    //   4396: iushr
    //   4397: bipush #63
    //   4399: iand
    //   4400: iaload
    //   4401: ior
    //   4402: istore #21
    //   4404: iload #21
    //   4406: aload #11
    //   4408: iload #22
    //   4410: bipush #16
    //   4412: iushr
    //   4413: bipush #63
    //   4415: iand
    //   4416: iaload
    //   4417: ior
    //   4418: istore #21
    //   4420: iload #21
    //   4422: aload #9
    //   4424: iload #22
    //   4426: bipush #24
    //   4428: iushr
    //   4429: bipush #63
    //   4431: iand
    //   4432: iaload
    //   4433: ior
    //   4434: istore #21
    //   4436: iload #23
    //   4438: iload #21
    //   4440: ixor
    //   4441: istore #23
    //   4443: iinc #25, 1
    //   4446: iload_2
    //   4447: ifne -> 4108
    //   4450: iload #23
    //   4452: bipush #31
    //   4454: ishl
    //   4455: iload #23
    //   4457: iconst_1
    //   4458: iushr
    //   4459: ior
    //   4460: istore #23
    //   4462: iload #24
    //   4464: iload #23
    //   4466: ixor
    //   4467: ldc -1431655766
    //   4469: iand
    //   4470: istore #22
    //   4472: iload #24
    //   4474: iload #22
    //   4476: ixor
    //   4477: istore #24
    //   4479: iload #23
    //   4481: iload #22
    //   4483: ixor
    //   4484: istore #23
    //   4486: iload #24
    //   4488: bipush #31
    //   4490: ishl
    //   4491: iload #24
    //   4493: iconst_1
    //   4494: iushr
    //   4495: ior
    //   4496: istore #24
    //   4498: iload #24
    //   4500: bipush #8
    //   4502: iushr
    //   4503: iload #23
    //   4505: ixor
    //   4506: ldc 16711935
    //   4508: iand
    //   4509: istore #22
    //   4511: iload #23
    //   4513: iload #22
    //   4515: ixor
    //   4516: istore #23
    //   4518: iload #24
    //   4520: iload #22
    //   4522: bipush #8
    //   4524: ishl
    //   4525: ixor
    //   4526: istore #24
    //   4528: iload #24
    //   4530: iconst_2
    //   4531: iushr
    //   4532: iload #23
    //   4534: ixor
    //   4535: ldc 858993459
    //   4537: iand
    //   4538: istore #22
    //   4540: iload #23
    //   4542: iload #22
    //   4544: ixor
    //   4545: istore #23
    //   4547: iload #24
    //   4549: iload #22
    //   4551: iconst_2
    //   4552: ishl
    //   4553: ixor
    //   4554: istore #24
    //   4556: iload #23
    //   4558: bipush #16
    //   4560: iushr
    //   4561: iload #24
    //   4563: ixor
    //   4564: ldc 65535
    //   4566: iand
    //   4567: istore #22
    //   4569: iload #24
    //   4571: iload #22
    //   4573: ixor
    //   4574: istore #24
    //   4576: iload #23
    //   4578: iload #22
    //   4580: bipush #16
    //   4582: ishl
    //   4583: ixor
    //   4584: istore #23
    //   4586: iload #23
    //   4588: iconst_4
    //   4589: iushr
    //   4590: iload #24
    //   4592: ixor
    //   4593: ldc 252645135
    //   4595: iand
    //   4596: istore #22
    //   4598: iload #24
    //   4600: iload #22
    //   4602: ixor
    //   4603: istore #24
    //   4605: iload #23
    //   4607: iload #22
    //   4609: iconst_4
    //   4610: ishl
    //   4611: ixor
    //   4612: istore #23
    //   4614: aload #17
    //   4616: iconst_0
    //   4617: iload #23
    //   4619: iastore
    //   4620: aload #17
    //   4622: iconst_1
    //   4623: iload #24
    //   4625: iastore
    //   4626: iload #19
    //   4628: bipush #8
    //   4630: imul
    //   4631: istore #27
    //   4633: iconst_0
    //   4634: istore #28
    //   4636: iload #28
    //   4638: iconst_2
    //   4639: if_icmpge -> 4728
    //   4642: aload #4
    //   4644: iload #27
    //   4646: iload #28
    //   4648: iconst_4
    //   4649: imul
    //   4650: iadd
    //   4651: aload #17
    //   4653: iload #28
    //   4655: iaload
    //   4656: bipush #24
    //   4658: iushr
    //   4659: i2b
    //   4660: bastore
    //   4661: aload #4
    //   4663: iload #27
    //   4665: iload #28
    //   4667: iconst_4
    //   4668: imul
    //   4669: iadd
    //   4670: iconst_1
    //   4671: iadd
    //   4672: aload #17
    //   4674: iload #28
    //   4676: iaload
    //   4677: bipush #16
    //   4679: iushr
    //   4680: i2b
    //   4681: bastore
    //   4682: aload #4
    //   4684: iload #27
    //   4686: iload #28
    //   4688: iconst_4
    //   4689: imul
    //   4690: iadd
    //   4691: iconst_2
    //   4692: iadd
    //   4693: aload #17
    //   4695: iload #28
    //   4697: iaload
    //   4698: bipush #8
    //   4700: iushr
    //   4701: i2b
    //   4702: bastore
    //   4703: aload #4
    //   4705: iload #27
    //   4707: iload #28
    //   4709: iconst_4
    //   4710: imul
    //   4711: iadd
    //   4712: iconst_3
    //   4713: iadd
    //   4714: aload #17
    //   4716: iload #28
    //   4718: iaload
    //   4719: i2b
    //   4720: bastore
    //   4721: iinc #28, 1
    //   4724: iload_2
    //   4725: ifne -> 4636
    //   4728: iinc #19, 1
    //   4731: iload_2
    //   4732: ifne -> 3817
    //   4735: new java/math/BigInteger
    //   4738: dup
    //   4739: aload #4
    //   4741: invokespecial <init> : ([B)V
    //   4744: invokevirtual abs : ()Ljava/math/BigInteger;
    //   4747: putstatic burp/Zl_u.ZR : Ljava/lang/Object;
    //   4750: sipush #-2095
    //   4753: sipush #-22636
    //   4756: invokestatic a : (II)Ljava/lang/String;
    //   4759: iconst_1
    //   4760: ldc burp/Zrkc
    //   4762: invokevirtual getClassLoader : ()Ljava/lang/ClassLoader;
    //   4765: invokestatic forName : (Ljava/lang/String;ZLjava/lang/ClassLoader;)Ljava/lang/Class;
    //   4768: invokevirtual getDeclaredFields : ()[Ljava/lang/reflect/Field;
    //   4771: astore_3
    //   4772: aload_3
    //   4773: arraylength
    //   4774: istore #4
    //   4776: iconst_0
    //   4777: istore #5
    //   4779: iload #5
    //   4781: iload #4
    //   4783: if_icmpge -> 4920
    //   4786: aload_3
    //   4787: iload #5
    //   4789: aaload
    //   4790: astore #6
    //   4792: aload #6
    //   4794: invokevirtual getModifiers : ()I
    //   4797: invokestatic isStatic : (I)Z
    //   4800: ifne -> 4810
    //   4803: goto -> 4913
    //   4806: invokestatic a : (Ljava/lang/Throwable;)Ljava/lang/Throwable;
    //   4809: athrow
    //   4810: aload #6
    //   4812: invokevirtual getType : ()Ljava/lang/Class;
    //   4815: astore #7
    //   4817: aload #7
    //   4819: ifnull -> 4900
    //   4822: aload #7
    //   4824: invokevirtual isPrimitive : ()Z
    //   4827: ifne -> 4900
    //   4830: goto -> 4837
    //   4833: invokestatic a : (Ljava/lang/Throwable;)Ljava/lang/Throwable;
    //   4836: athrow
    //   4837: aload #7
    //   4839: invokevirtual getPackage : ()Ljava/lang/Package;
    //   4842: ifnull -> 4900
    //   4845: goto -> 4852
    //   4848: invokestatic a : (Ljava/lang/Throwable;)Ljava/lang/Throwable;
    //   4851: athrow
    //   4852: aload #7
    //   4854: invokevirtual getPackage : ()Ljava/lang/Package;
    //   4857: invokevirtual getName : ()Ljava/lang/String;
    //   4860: ifnull -> 4900
    //   4863: goto -> 4870
    //   4866: invokestatic a : (Ljava/lang/Throwable;)Ljava/lang/Throwable;
    //   4869: athrow
    //   4870: aload #7
    //   4872: invokevirtual getPackage : ()Ljava/lang/Package;
    //   4875: invokevirtual getName : ()Ljava/lang/String;
    //   4878: sipush #-2092
    //   4881: sipush #24662
    //   4884: invokestatic a : (II)Ljava/lang/String;
    //   4887: invokevirtual startsWith : (Ljava/lang/String;)Z
    //   4890: ifne -> 4900
    //   4893: goto -> 4900
    //   4896: invokestatic a : (Ljava/lang/Throwable;)Ljava/lang/Throwable;
    //   4899: athrow
    //   4900: aload #6
    //   4902: iconst_1
    //   4903: invokevirtual setAccessible : (Z)V
    //   4906: aload #6
    //   4908: aconst_null
    //   4909: invokevirtual get : (Ljava/lang/Object;)Ljava/lang/Object;
    //   4912: pop
    //   4913: iinc #5, 1
    //   4916: iload_2
    //   4917: ifne -> 4779
    //   4920: sipush #-2093
    //   4923: sipush #15379
    //   4926: invokestatic a : (II)Ljava/lang/String;
    //   4929: invokestatic forName : (Ljava/lang/String;)Ljava/lang/Class;
    //   4932: invokevirtual getDeclaredMethods : ()[Ljava/lang/reflect/Method;
    //   4935: astore_3
    //   4936: aload_3
    //   4937: arraylength
    //   4938: istore #4
    //   4940: iconst_0
    //   4941: istore #5
    //   4943: iload #5
    //   4945: iload #4
    //   4947: if_icmpge -> 5079
    //   4950: aload_3
    //   4951: iload #5
    //   4953: aaload
    //   4954: astore #6
    //   4956: aload #6
    //   4958: invokevirtual getParameterTypes : ()[Ljava/lang/Class;
    //   4961: pop
    //   4962: aload #6
    //   4964: invokevirtual getModifiers : ()I
    //   4967: invokestatic isStatic : (I)Z
    //   4970: ifeq -> 5065
    //   4973: aload #6
    //   4975: invokevirtual getParameterTypes : ()[Ljava/lang/Class;
    //   4978: arraylength
    //   4979: iconst_2
    //   4980: if_icmpne -> 5065
    //   4983: goto -> 4990
    //   4986: invokestatic a : (Ljava/lang/Throwable;)Ljava/lang/Throwable;
    //   4989: athrow
    //   4990: aload #6
    //   4992: invokevirtual getReturnType : ()Ljava/lang/Class;
    //   4995: getstatic java/lang/Void.TYPE : Ljava/lang/Class;
    //   4998: invokevirtual equals : (Ljava/lang/Object;)Z
    //   5001: ifeq -> 5065
    //   5004: goto -> 5011
    //   5007: invokestatic a : (Ljava/lang/Throwable;)Ljava/lang/Throwable;
    //   5010: athrow
    //   5011: aload #6
    //   5013: iconst_1
    //   5014: invokevirtual setAccessible : (Z)V
    //   5017: aload #6
    //   5019: aconst_null
    //   5020: iconst_2
    //   5021: anewarray java/lang/Object
    //   5024: dup
    //   5025: iconst_0
    //   5026: aload_0
    //   5027: aastore
    //   5028: dup
    //   5029: iconst_1
    //   5030: aload_1
    //   5031: ifnonnull -> 5049
    //   5034: goto -> 5041
    //   5037: invokestatic a : (Ljava/lang/Throwable;)Ljava/lang/Throwable;
    //   5040: athrow
    //   5041: aload_1
    //   5042: goto -> 5056
    //   5045: invokestatic a : (Ljava/lang/Throwable;)Ljava/lang/Throwable;
    //   5048: athrow
    //   5049: aload_1
    //   5050: checkcast [B
    //   5053: invokevirtual clone : ()Ljava/lang/Object;
    //   5056: aastore
    //   5057: invokevirtual invoke : (Ljava/lang/Object;[Ljava/lang/Object;)Ljava/lang/Object;
    //   5060: pop
    //   5061: iload_2
    //   5062: ifne -> 5079
    //   5065: iinc #5, 1
    //   5068: iload_2
    //   5069: ifne -> 4943
    //   5072: goto -> 5079
    //   5075: invokestatic a : (Ljava/lang/Throwable;)Ljava/lang/Throwable;
    //   5078: athrow
    //   5079: getstatic burp/Zr0g.Zf : Ljava/lang/String;
    //   5082: getstatic burp/Zsm3.ZC : Ljava/lang/Object;
    //   5085: checkcast java/math/BigInteger
    //   5088: invokevirtual intValue : ()I
    //   5091: bipush #32
    //   5093: irem
    //   5094: invokestatic abs : (I)I
    //   5097: invokevirtual charAt : (I)C
    //   5100: getstatic burp/Zxo6.Z_ : Ljava/lang/String;
    //   5103: getstatic burp/Zlv6.ZN : Ljava/lang/Object;
    //   5106: checkcast java/math/BigInteger
    //   5109: invokevirtual intValue : ()I
    //   5112: bipush #32
    //   5114: irem
    //   5115: invokestatic abs : (I)I
    //   5118: invokevirtual charAt : (I)C
    //   5121: if_icmpgt -> 5228
    //   5124: getstatic burp/Zb3z.Zi : Ljava/lang/String;
    //   5127: getstatic burp/Zb3z.ZR : Ljava/lang/Object;
    //   5130: checkcast java/math/BigInteger
    //   5133: invokevirtual intValue : ()I
    //   5136: bipush #32
    //   5138: irem
    //   5139: invokestatic abs : (I)I
    //   5142: invokevirtual charAt : (I)C
    //   5145: getstatic burp/Zsby.Zx : Ljava/lang/String;
    //   5148: getstatic burp/Zsgl.Zn : Ljava/lang/Object;
    //   5151: checkcast java/math/BigInteger
    //   5154: invokevirtual intValue : ()I
    //   5157: bipush #32
    //   5159: irem
    //   5160: invokestatic abs : (I)I
    //   5163: invokevirtual charAt : (I)C
    //   5166: if_icmple -> 5228
    //   5169: goto -> 5176
    //   5172: invokestatic a : (Ljava/lang/Throwable;)Ljava/lang/Throwable;
    //   5175: athrow
    //   5176: getstatic burp/Zgmt.Zu : Ljava/lang/String;
    //   5179: getstatic burp/Zl88.ZK : Ljava/lang/Object;
    //   5182: checkcast java/math/BigInteger
    //   5185: invokevirtual intValue : ()I
    //   5188: bipush #32
    //   5190: irem
    //   5191: invokestatic abs : (I)I
    //   5194: invokevirtual charAt : (I)C
    //   5197: getstatic burp/Zgss.Zc : Ljava/lang/String;
    //   5200: getstatic burp/Zr0g.Zj : Ljava/lang/Object;
    //   5203: checkcast java/math/BigInteger
    //   5206: invokevirtual intValue : ()I
    //   5209: bipush #32
    //   5211: irem
    //   5212: invokestatic abs : (I)I
    //   5215: invokevirtual charAt : (I)C
    //   5218: if_icmpgt -> 5236
    //   5221: goto -> 5228
    //   5224: invokestatic a : (Ljava/lang/Throwable;)Ljava/lang/Throwable;
    //   5227: athrow
    //   5228: iconst_1
    //   5229: goto -> 5237
    //   5232: invokestatic a : (Ljava/lang/Throwable;)Ljava/lang/Throwable;
    //   5235: athrow
    //   5236: iconst_0
    //   5237: ireturn
    //   5238: astore_3
    //   5239: new java/lang/Exception
    //   5242: dup
    //   5243: aload_3
    //   5244: invokevirtual getMessage : ()Ljava/lang/String;
    //   5247: invokespecial <init> : (Ljava/lang/String;)V
    //   5250: athrow
    // Exception table:
    //   from	to	target	type
    //   4	5237	5238	java/lang/Throwable
    //   191	219	222	java/lang/Throwable
    //   201	236	239	java/lang/Throwable
    //   226	264	267	java/lang/Throwable
    //   243	281	284	java/lang/Throwable
    //   271	309	312	java/lang/Throwable
    //   288	326	329	java/lang/Throwable
    //   316	344	347	java/lang/Throwable
    //   333	358	361	java/lang/Throwable
    //   4792	4806	4806	java/lang/Throwable
    //   4817	4830	4833	java/lang/Throwable
    //   4822	4845	4848	java/lang/Throwable
    //   4837	4863	4866	java/lang/Throwable
    //   4852	4893	4896	java/lang/Throwable
    //   4956	4983	4986	java/lang/Throwable
    //   4973	5004	5007	java/lang/Throwable
    //   4990	5034	5037	java/lang/Throwable
    //   5011	5045	5045	java/lang/Throwable
    //   5056	5072	5075	java/lang/Throwable
    //   5079	5169	5172	java/lang/Throwable
    //   5124	5221	5224	java/lang/Throwable
    //   5176	5232	5232	java/lang/Throwable
  }
  
  static void Zq(Object paramObject) {
    Zxk9.Zx = a(-2091, 13344);
    Zxk9.ZI = new BigInteger(a(-2096, 9838));
    boolean bool = Zt2e.ZK();
    try {
      try {
        if (Zl_u.Zc.charAt(Math.abs(((BigInteger)Zbo7.Zl).intValue() % 32)) <= Ze13.Zg.charAt(Math.abs(((BigInteger)Zlhm.ZT).intValue() % 32))) {
          try {
            Zgmt.Zj(Class.forName(a(-2090, 23758)));
            if (bool)
              Zr8s.Zz(Class.forName(a(-2089, -860))); 
          } catch (Throwable throwable) {
            throw a(null);
          } 
          return;
        } 
      } catch (Throwable throwable) {
        throw a(null);
      } 
      Zr8s.Zz(Class.forName(a(-2089, -860)));
    } catch (Throwable throwable) {}
  }
  
  static {
    // Byte code:
    //   0: bipush #8
    //   2: anewarray java/lang/String
    //   5: astore #5
    //   7: iconst_0
    //   8: istore_3
    //   9: ldc '9\\t<q(\mb} !;QK4%9u.Or.vH ^M\\r[ZQ}M WY41$aZ\\t]8d#}'
    //   11: dup
    //   12: astore_2
    //   13: invokevirtual length : ()I
    //   16: istore #4
    //   18: bipush #9
    //   20: istore_1
    //   21: iconst_m1
    //   22: istore_0
    //   23: bipush #64
    //   25: iinc #0, 1
    //   28: aload_2
    //   29: iload_0
    //   30: dup
    //   31: iload_1
    //   32: iadd
    //   33: invokevirtual substring : (II)Ljava/lang/String;
    //   36: iconst_m1
    //   37: goto -> 143
    //   40: aload #5
    //   42: swap
    //   43: iload_3
    //   44: iinc #3, 1
    //   47: swap
    //   48: aastore
    //   49: iload_0
    //   50: iload_1
    //   51: iadd
    //   52: dup
    //   53: istore_0
    //   54: iload #4
    //   56: if_icmpge -> 68
    //   59: aload_2
    //   60: iload_0
    //   61: invokevirtual charAt : (I)C
    //   64: istore_1
    //   65: goto -> 23
    //   68: ldc '{LhP\b2@0Y/i|EHa{\\b_C)QrlV{|_.t\\t\\fLed'
    //   70: dup
    //   71: astore_2
    //   72: invokevirtual length : ()I
    //   75: istore #4
    //   77: bipush #77
    //   79: istore_1
    //   80: iconst_m1
    //   81: istore_0
    //   82: bipush #84
    //   84: iinc #0, 1
    //   87: aload_2
    //   88: iload_0
    //   89: dup
    //   90: iload_1
    //   91: iadd
    //   92: invokevirtual substring : (II)Ljava/lang/String;
    //   95: iconst_0
    //   96: goto -> 143
    //   99: aload #5
    //   101: swap
    //   102: iload_3
    //   103: iinc #3, 1
    //   106: swap
    //   107: aastore
    //   108: iload_0
    //   109: iload_1
    //   110: iadd
    //   111: dup
    //   112: istore_0
    //   113: iload #4
    //   115: if_icmpge -> 127
    //   118: aload_2
    //   119: iload_0
    //   120: invokevirtual charAt : (I)C
    //   123: istore_1
    //   124: goto -> 82
    //   127: aload #5
    //   129: putstatic burp/Zsxm.a : [Ljava/lang/String;
    //   132: bipush #8
    //   134: anewarray java/lang/String
    //   137: putstatic burp/Zsxm.b : [Ljava/lang/String;
    //   140: goto -> 300
    //   143: dup_x2
    //   144: pop
    //   145: invokevirtual toCharArray : ()[C
    //   148: dup_x1
    //   149: arraylength
    //   150: dup_x2
    //   151: pop
    //   152: iconst_0
    //   153: istore #6
    //   155: dup2_x1
    //   156: pop2
    //   157: dup_x2
    //   158: iconst_1
    //   159: if_icmpgt -> 260
    //   162: dup2
    //   163: swap
    //   164: iload #6
    //   166: dup2_x1
    //   167: caload
    //   168: swap
    //   169: iload #6
    //   171: bipush #7
    //   173: irem
    //   174: tableswitch default -> 242, 0 -> 212, 1 -> 217, 2 -> 222, 3 -> 227, 4 -> 232, 5 -> 237
    //   212: bipush #55
    //   214: goto -> 244
    //   217: bipush #124
    //   219: goto -> 244
    //   222: bipush #61
    //   224: goto -> 244
    //   227: bipush #104
    //   229: goto -> 244
    //   232: bipush #82
    //   234: goto -> 244
    //   237: bipush #19
    //   239: goto -> 244
    //   242: bipush #85
    //   244: ixor
    //   245: ixor
    //   246: i2c
    //   247: castore
    //   248: iinc #6, 1
    //   251: dup
    //   252: ifne -> 260
    //   255: dup2
    //   256: dup_x1
    //   257: goto -> 166
    //   260: dup2_x1
    //   261: pop2
    //   262: dup_x2
    //   263: iload #6
    //   265: if_icmpgt -> 162
    //   268: pop
    //   269: new java/lang/String
    //   272: dup_x1
    //   273: swap
    //   274: invokespecial <init> : ([C)V
    //   277: invokevirtual intern : ()Ljava/lang/String;
    //   280: swap
    //   281: pop
    //   282: swap
    //   283: tableswitch default -> 40, 0 -> 99
    //   300: new java/math/BigInteger
    //   303: dup
    //   304: iconst_1
    //   305: bipush #32
    //   307: newarray byte
    //   309: dup
    //   310: iconst_0
    //   311: bipush #26
    //   313: bastore
    //   314: dup
    //   315: iconst_1
    //   316: bipush #57
    //   318: bastore
    //   319: dup
    //   320: iconst_2
    //   321: bipush #122
    //   323: bastore
    //   324: dup
    //   325: iconst_3
    //   326: bipush #-18
    //   328: bastore
    //   329: dup
    //   330: iconst_4
    //   331: bipush #-100
    //   333: bastore
    //   334: dup
    //   335: iconst_5
    //   336: bipush #49
    //   338: bastore
    //   339: dup
    //   340: bipush #6
    //   342: iconst_1
    //   343: bastore
    //   344: dup
    //   345: bipush #7
    //   347: bipush #-97
    //   349: bastore
    //   350: dup
    //   351: bipush #8
    //   353: bipush #-121
    //   355: bastore
    //   356: dup
    //   357: bipush #9
    //   359: bipush #-7
    //   361: bastore
    //   362: dup
    //   363: bipush #10
    //   365: bipush #-2
    //   367: bastore
    //   368: dup
    //   369: bipush #11
    //   371: bipush #-94
    //   373: bastore
    //   374: dup
    //   375: bipush #12
    //   377: bipush #17
    //   379: bastore
    //   380: dup
    //   381: bipush #13
    //   383: bipush #-41
    //   385: bastore
    //   386: dup
    //   387: bipush #14
    //   389: bipush #103
    //   391: bastore
    //   392: dup
    //   393: bipush #15
    //   395: bipush #54
    //   397: bastore
    //   398: dup
    //   399: bipush #16
    //   401: bipush #-34
    //   403: bastore
    //   404: dup
    //   405: bipush #17
    //   407: bipush #9
    //   409: bastore
    //   410: dup
    //   411: bipush #18
    //   413: bipush #-53
    //   415: bastore
    //   416: dup
    //   417: bipush #19
    //   419: bipush #-62
    //   421: bastore
    //   422: dup
    //   423: bipush #20
    //   425: bipush #94
    //   427: bastore
    //   428: dup
    //   429: bipush #21
    //   431: bipush #-15
    //   433: bastore
    //   434: dup
    //   435: bipush #22
    //   437: bipush #74
    //   439: bastore
    //   440: dup
    //   441: bipush #23
    //   443: bipush #16
    //   445: bastore
    //   446: dup
    //   447: bipush #24
    //   449: bipush #79
    //   451: bastore
    //   452: dup
    //   453: bipush #25
    //   455: bipush #-38
    //   457: bastore
    //   458: dup
    //   459: bipush #26
    //   461: bipush #38
    //   463: bastore
    //   464: dup
    //   465: bipush #27
    //   467: bipush #-35
    //   469: bastore
    //   470: dup
    //   471: bipush #28
    //   473: bipush #125
    //   475: bastore
    //   476: dup
    //   477: bipush #29
    //   479: bipush #126
    //   481: bastore
    //   482: dup
    //   483: bipush #30
    //   485: bipush #-52
    //   487: bastore
    //   488: dup
    //   489: bipush #31
    //   491: bipush #-125
    //   493: bastore
    //   494: invokespecial <init> : (I[B)V
    //   497: putstatic burp/Zsxm.Zv : Ljava/lang/Object;
    //   500: sipush #-2094
    //   503: sipush #14895
    //   506: invokestatic a : (II)Ljava/lang/String;
    //   509: putstatic burp/Zsxm.Zq : Ljava/lang/String;
    //   512: return
  }
  
  private static Throwable a(Throwable paramThrowable) {
    return paramThrowable;
  }
  
  private static String a(int paramInt1, int paramInt2) {
    int i = (paramInt1 ^ 0xFFFFF7D6) & 0xFFFF;
    if (b[i] == null) {
      char[] arrayOfChar = a[i].toCharArray();
      switch (arrayOfChar[0] & 0xFF) {
        case 0:
        
        case 1:
        
        case 2:
        
        case 3:
        
        case 4:
        
        case 5:
        
        case 6:
        
        case 7:
        
        case 8:
        
        case 9:
        
        case 10:
        
        case 11:
        
        case 12:
        
        case 13:
        
        case 14:
        
        case 15:
        
        case 16:
        
        case 17:
        
        case 18:
        
        case 19:
        
        case 20:
        
        case 21:
        
        case 22:
        
        case 23:
        
        case 24:
        
        case 25:
        
        case 26:
        
        case 27:
        
        case 28:
        
        case 29:
        
        case 30:
        
        case 31:
        
        case 32:
        
        case 33:
        
        case 34:
        
        case 35:
        
        case 36:
        
        case 37:
        
        case 38:
        
        case 39:
        
        case 40:
        
        case 41:
        
        case 42:
        
        case 43:
        
        case 44:
        
        case 45:
        
        case 46:
        
        case 47:
        
        case 48:
        
        case 49:
        
        case 50:
        
        case 51:
        
        case 52:
        
        case 53:
        
        case 54:
        
        case 55:
        
        case 56:
        
        case 57:
        
        case 58:
        
        case 59:
        
        case 60:
        
        case 61:
        
        case 62:
        
        case 63:
        
        case 64:
        
        case 65:
        
        case 66:
        
        case 67:
        
        case 68:
        
        case 69:
        
        case 70:
        
        case 71:
        
        case 72:
        
        case 73:
        
        case 74:
        
        case 75:
        
        case 76:
        
        case 77:
        
        case 78:
        
        case 79:
        
        case 80:
        
        case 81:
        
        case 82:
        
        case 83:
        
        case 84:
        
        case 85:
        
        case 86:
        
        case 87:
        
        case 88:
        
        case 89:
        
        case 90:
        
        case 91:
        
        case 92:
        
        case 93:
        
        case 94:
        
        case 95:
        
        case 96:
        
        case 97:
        
        case 98:
        
        case 99:
        
        case 100:
        
        case 101:
        
        case 102:
        
        case 103:
        
        case 104:
        
        case 105:
        
        case 106:
        
        case 107:
        
        case 108:
        
        case 109:
        
        case 110:
        
        case 111:
        
        case 112:
        
        case 113:
        
        case 114:
        
        case 115:
        
        case 116:
        
        case 117:
        
        case 118:
        
        case 119:
        
        case 120:
        
        case 121:
        
        case 122:
        
        case 123:
        
        case 124:
        
        case 125:
        
        case 126:
        
        case 127:
        
        case 128:
        
        case 129:
        
        case 130:
        
        case 131:
        
        case 132:
        
        case 133:
        
        case 134:
        
        case 135:
        
        case 136:
        
        case 137:
        
        case 138:
        
        case 139:
        
        case 140:
        
        case 141:
        
        case 142:
        
        case 143:
        
        case 144:
        
        case 145:
        
        case 146:
        
        case 147:
        
        case 148:
        
        case 149:
        
        case 150:
        
        case 151:
        
        case 152:
        
        case 153:
        
        case 154:
        
        case 155:
        
        case 156:
        
        case 157:
        
        case 158:
        
        case 159:
        
        case 160:
        
        case 161:
        
        case 162:
        
        case 163:
        
        case 164:
        
        case 165:
        
        case 166:
        
        case 167:
        
        case 168:
        
        case 169:
        
        case 170:
        
        case 171:
        
        case 172:
        
        case 173:
        
        case 174:
        
        case 175:
        
        case 176:
        
        case 177:
        
        case 178:
        
        case 179:
        
        case 180:
        
        case 181:
        
        case 182:
        
        case 183:
        
        case 184:
        
        case 185:
        
        case 186:
        
        case 187:
        
        case 188:
        
        case 189:
        
        case 190:
        
        case 191:
        
        case 192:
        
        case 193:
        
        case 194:
        
        case 195:
        
        case 196:
        
        case 197:
        
        case 198:
        
        case 199:
        
        case 200:
        
        case 201:
        
        case 202:
        
        case 203:
        
        case 204:
        
        case 205:
        
        case 206:
        
        case 207:
        
        case 208:
        
        case 209:
        
        case 210:
        
        case 211:
        
        case 212:
        
        case 213:
        
        case 214:
        
        case 215:
        
        case 216:
        
        case 217:
        
        case 218:
        
        case 219:
        
        case 220:
        
        case 221:
        
        case 222:
        
        case 223:
        
        case 224:
        
        case 225:
        
        case 226:
        
        case 227:
        
        case 228:
        
        case 229:
        
        case 230:
        
        case 231:
        
        case 232:
        
        case 233:
        
        case 234:
        
        case 235:
        
        case 236:
        
        case 237:
        
        case 238:
        
        case 239:
        
        case 240:
        
        case 241:
        
        case 242:
        
        case 243:
        
        case 244:
        
        case 245:
        
        case 246:
        
        case 247:
        
        case 248:
        
        case 249:
        
        case 250:
        
        case 251:
        
        case 252:
        
        case 253:
        
        case 254:
        
        default:
          break;
      } 
      byte b1 = 28;
      int j = (paramInt2 & 0xFF) - b1;
      if (j < 0)
        j += 256; 
      int k = ((paramInt2 & 0xFFFF) >>> 8) - b1;
      if (k < 0)
        k += 256; 
      for (byte b2 = 0; b2 < arrayOfChar.length; b2++) {
        int m = b2 % 2;
        if (m == 0) {
          arrayOfChar[b2] = (char)(arrayOfChar[b2] ^ j);
          j = ((j >>> 3 | j << 5) ^ arrayOfChar[b2]) & 0xFF;
        } else {
          arrayOfChar[b2] = (char)(arrayOfChar[b2] ^ k);
          k = ((k >>> 3 | k << 5) ^ arrayOfChar[b2]) & 0xFF;
        } 
      } 
      b[i] = (new String(arrayOfChar)).intern();
    } 
    return b[i];
  }
}


/* Location:              C:\Program Files\BurpSuitePro\burpsuite_pro.jar!\burp\Zsxm.class
 * Java compiler version: 21 (65.0)
 * JD-Core Version:       1.1.3
 */