package burp;

import java.math.BigInteger;

class Zsxw extends ClassLoader {
  static String Zm;
  
  static Object ZL;
  
  private static final String[] a;
  
  private static final String[] b;
  
  static boolean Zr(Object[] paramArrayOfObject, Object paramObject) throws Throwable {
    // Byte code:
    //   0: invokestatic ZK : ()Z
    //   3: istore_2
    //   4: sipush #-8856
    //   7: sipush #-14748
    //   10: invokestatic a : (II)Ljava/lang/String;
    //   13: invokestatic forName : (Ljava/lang/String;)Ljava/lang/Class;
    //   16: invokevirtual getDeclaredFields : ()[Ljava/lang/reflect/Field;
    //   19: astore_3
    //   20: aload_3
    //   21: arraylength
    //   22: istore #4
    //   24: iconst_0
    //   25: istore #5
    //   27: iload #5
    //   29: iload #4
    //   31: if_icmpge -> 107
    //   34: aload_3
    //   35: iload #5
    //   37: aaload
    //   38: astore #6
    //   40: aload #6
    //   42: invokevirtual getType : ()Ljava/lang/Class;
    //   45: ldc java/lang/String
    //   47: invokevirtual equals : (Ljava/lang/Object;)Z
    //   50: ifeq -> 93
    //   53: aload #6
    //   55: iconst_1
    //   56: invokevirtual setAccessible : (Z)V
    //   59: aload #6
    //   61: aconst_null
    //   62: aload #6
    //   64: aconst_null
    //   65: invokevirtual get : (Ljava/lang/Object;)Ljava/lang/Object;
    //   68: checkcast java/lang/String
    //   71: getstatic burp/Zsxw.Zm : Ljava/lang/String;
    //   74: <illegal opcode> makeConcatWithConstants : (Ljava/lang/String;Ljava/lang/String;)Ljava/lang/String;
    //   79: invokevirtual set : (Ljava/lang/Object;Ljava/lang/Object;)V
    //   82: iload_2
    //   83: ifeq -> 107
    //   86: goto -> 93
    //   89: invokestatic a : (Ljava/lang/Throwable;)Ljava/lang/Throwable;
    //   92: athrow
    //   93: iinc #5, 1
    //   96: iload_2
    //   97: ifeq -> 27
    //   100: goto -> 107
    //   103: invokestatic a : (Ljava/lang/Throwable;)Ljava/lang/Throwable;
    //   106: athrow
    //   107: sipush #-8861
    //   110: sipush #14430
    //   113: invokestatic a : (II)Ljava/lang/String;
    //   116: iconst_1
    //   117: ldc burp/Zenr
    //   119: invokevirtual getClassLoader : ()Ljava/lang/ClassLoader;
    //   122: invokestatic forName : (Ljava/lang/String;ZLjava/lang/ClassLoader;)Ljava/lang/Class;
    //   125: invokevirtual getDeclaredFields : ()[Ljava/lang/reflect/Field;
    //   128: astore_3
    //   129: aload_3
    //   130: arraylength
    //   131: istore #4
    //   133: iconst_0
    //   134: istore #5
    //   136: iload #5
    //   138: iload #4
    //   140: if_icmpge -> 277
    //   143: aload_3
    //   144: iload #5
    //   146: aaload
    //   147: astore #6
    //   149: aload #6
    //   151: invokevirtual getModifiers : ()I
    //   154: invokestatic isStatic : (I)Z
    //   157: ifne -> 167
    //   160: goto -> 270
    //   163: invokestatic a : (Ljava/lang/Throwable;)Ljava/lang/Throwable;
    //   166: athrow
    //   167: aload #6
    //   169: invokevirtual getType : ()Ljava/lang/Class;
    //   172: astore #7
    //   174: aload #7
    //   176: ifnull -> 257
    //   179: aload #7
    //   181: invokevirtual isPrimitive : ()Z
    //   184: ifne -> 257
    //   187: goto -> 194
    //   190: invokestatic a : (Ljava/lang/Throwable;)Ljava/lang/Throwable;
    //   193: athrow
    //   194: aload #7
    //   196: invokevirtual getPackage : ()Ljava/lang/Package;
    //   199: ifnull -> 257
    //   202: goto -> 209
    //   205: invokestatic a : (Ljava/lang/Throwable;)Ljava/lang/Throwable;
    //   208: athrow
    //   209: aload #7
    //   211: invokevirtual getPackage : ()Ljava/lang/Package;
    //   214: invokevirtual getName : ()Ljava/lang/String;
    //   217: ifnull -> 257
    //   220: goto -> 227
    //   223: invokestatic a : (Ljava/lang/Throwable;)Ljava/lang/Throwable;
    //   226: athrow
    //   227: aload #7
    //   229: invokevirtual getPackage : ()Ljava/lang/Package;
    //   232: invokevirtual getName : ()Ljava/lang/String;
    //   235: sipush #-8851
    //   238: sipush #-6815
    //   241: invokestatic a : (II)Ljava/lang/String;
    //   244: invokevirtual startsWith : (Ljava/lang/String;)Z
    //   247: ifne -> 257
    //   250: goto -> 257
    //   253: invokestatic a : (Ljava/lang/Throwable;)Ljava/lang/Throwable;
    //   256: athrow
    //   257: aload #6
    //   259: iconst_1
    //   260: invokevirtual setAccessible : (Z)V
    //   263: aload #6
    //   265: aconst_null
    //   266: invokevirtual get : (Ljava/lang/Object;)Ljava/lang/Object;
    //   269: pop
    //   270: iinc #5, 1
    //   273: iload_2
    //   274: ifeq -> 136
    //   277: sipush #-8850
    //   280: sipush #14548
    //   283: invokestatic a : (II)Ljava/lang/String;
    //   286: invokestatic forName : (Ljava/lang/String;)Ljava/lang/Class;
    //   289: invokevirtual getDeclaredMethods : ()[Ljava/lang/reflect/Method;
    //   292: astore_3
    //   293: aload_3
    //   294: arraylength
    //   295: istore #4
    //   297: iconst_0
    //   298: istore #5
    //   300: iload #5
    //   302: iload #4
    //   304: if_icmpge -> 436
    //   307: aload_3
    //   308: iload #5
    //   310: aaload
    //   311: astore #6
    //   313: aload #6
    //   315: invokevirtual getParameterTypes : ()[Ljava/lang/Class;
    //   318: pop
    //   319: aload #6
    //   321: invokevirtual getModifiers : ()I
    //   324: invokestatic isStatic : (I)Z
    //   327: ifeq -> 422
    //   330: aload #6
    //   332: invokevirtual getParameterTypes : ()[Ljava/lang/Class;
    //   335: arraylength
    //   336: iconst_2
    //   337: if_icmpne -> 422
    //   340: goto -> 347
    //   343: invokestatic a : (Ljava/lang/Throwable;)Ljava/lang/Throwable;
    //   346: athrow
    //   347: aload #6
    //   349: invokevirtual getReturnType : ()Ljava/lang/Class;
    //   352: getstatic java/lang/Void.TYPE : Ljava/lang/Class;
    //   355: invokevirtual equals : (Ljava/lang/Object;)Z
    //   358: ifeq -> 422
    //   361: goto -> 368
    //   364: invokestatic a : (Ljava/lang/Throwable;)Ljava/lang/Throwable;
    //   367: athrow
    //   368: aload #6
    //   370: iconst_1
    //   371: invokevirtual setAccessible : (Z)V
    //   374: aload #6
    //   376: aconst_null
    //   377: iconst_2
    //   378: anewarray java/lang/Object
    //   381: dup
    //   382: iconst_0
    //   383: aload_0
    //   384: aastore
    //   385: dup
    //   386: iconst_1
    //   387: aload_1
    //   388: ifnonnull -> 406
    //   391: goto -> 398
    //   394: invokestatic a : (Ljava/lang/Throwable;)Ljava/lang/Throwable;
    //   397: athrow
    //   398: aload_1
    //   399: goto -> 413
    //   402: invokestatic a : (Ljava/lang/Throwable;)Ljava/lang/Throwable;
    //   405: athrow
    //   406: aload_1
    //   407: checkcast [B
    //   410: invokevirtual clone : ()Ljava/lang/Object;
    //   413: aastore
    //   414: invokevirtual invoke : (Ljava/lang/Object;[Ljava/lang/Object;)Ljava/lang/Object;
    //   417: pop
    //   418: iload_2
    //   419: ifeq -> 436
    //   422: iinc #5, 1
    //   425: iload_2
    //   426: ifeq -> 300
    //   429: goto -> 436
    //   432: invokestatic a : (Ljava/lang/Throwable;)Ljava/lang/Throwable;
    //   435: athrow
    //   436: getstatic burp/Zsp9.ZA : Ljava/lang/String;
    //   439: getstatic burp/Zb6m.ZQ : Ljava/lang/Object;
    //   442: checkcast java/math/BigInteger
    //   445: invokevirtual intValue : ()I
    //   448: bipush #32
    //   450: irem
    //   451: invokestatic abs : (I)I
    //   454: invokevirtual charAt : (I)C
    //   457: getstatic burp/Ze4a.Zm : Ljava/lang/String;
    //   460: getstatic burp/Zrym.Zk : Ljava/lang/Object;
    //   463: checkcast java/math/BigInteger
    //   466: invokevirtual intValue : ()I
    //   469: bipush #32
    //   471: irem
    //   472: invokestatic abs : (I)I
    //   475: invokevirtual charAt : (I)C
    //   478: if_icmpgt -> 593
    //   481: getstatic burp/Zkdq.ZZ : Ljava/lang/String;
    //   484: getstatic burp/Zxzv.Zg : Ljava/lang/Object;
    //   487: checkcast java/math/BigInteger
    //   490: invokevirtual intValue : ()I
    //   493: bipush #32
    //   495: irem
    //   496: invokestatic abs : (I)I
    //   499: invokevirtual charAt : (I)C
    //   502: getstatic burp/Ze8j.ZU : Ljava/lang/String;
    //   505: getstatic burp/Zlwm.Ze : Ljava/lang/Object;
    //   508: checkcast java/math/BigInteger
    //   511: invokevirtual intValue : ()I
    //   514: bipush #32
    //   516: irem
    //   517: invokestatic abs : (I)I
    //   520: invokevirtual charAt : (I)C
    //   523: if_icmple -> 593
    //   526: goto -> 533
    //   529: invokestatic a : (Ljava/lang/Throwable;)Ljava/lang/Throwable;
    //   532: athrow
    //   533: getstatic burp/Zmc_.Zb : Ljava/lang/String;
    //   536: getstatic burp/Zs3m.ZW : Ljava/lang/Object;
    //   539: checkcast java/math/BigInteger
    //   542: invokevirtual intValue : ()I
    //   545: bipush #32
    //   547: irem
    //   548: invokestatic abs : (I)I
    //   551: invokevirtual charAt : (I)C
    //   554: getstatic burp/Zebe.ZW : Ljava/lang/String;
    //   557: getstatic burp/Zm0d.Zz : Ljava/lang/Object;
    //   560: checkcast java/math/BigInteger
    //   563: invokevirtual intValue : ()I
    //   566: bipush #32
    //   568: irem
    //   569: invokestatic abs : (I)I
    //   572: invokevirtual charAt : (I)C
    //   575: if_icmple -> 593
    //   578: goto -> 585
    //   581: invokestatic a : (Ljava/lang/Throwable;)Ljava/lang/Throwable;
    //   584: athrow
    //   585: iconst_1
    //   586: goto -> 594
    //   589: invokestatic a : (Ljava/lang/Throwable;)Ljava/lang/Throwable;
    //   592: athrow
    //   593: iconst_0
    //   594: ireturn
    //   595: astore_3
    //   596: new java/lang/Exception
    //   599: dup
    //   600: aload_3
    //   601: invokevirtual getMessage : ()Ljava/lang/String;
    //   604: invokespecial <init> : (Ljava/lang/String;)V
    //   607: athrow
    // Exception table:
    //   from	to	target	type
    //   4	594	595	java/lang/Throwable
    //   40	86	89	java/lang/Throwable
    //   53	100	103	java/lang/Throwable
    //   149	163	163	java/lang/Throwable
    //   174	187	190	java/lang/Throwable
    //   179	202	205	java/lang/Throwable
    //   194	220	223	java/lang/Throwable
    //   209	250	253	java/lang/Throwable
    //   313	340	343	java/lang/Throwable
    //   330	361	364	java/lang/Throwable
    //   347	391	394	java/lang/Throwable
    //   368	402	402	java/lang/Throwable
    //   413	429	432	java/lang/Throwable
    //   436	526	529	java/lang/Throwable
    //   481	578	581	java/lang/Throwable
    //   533	589	589	java/lang/Throwable
  }
  
  static void Zk(Object paramObject) {
    Zlwm.Zj = a(-8862, 4363);
    Zlwm.Ze = new BigInteger(new byte[] { 
          78, -28, -62, 30, 47, 65, 30, 9, -88, 63, 
          -21, -73, 112, -47, 41, -33, 5, 34, 119, 47, 
          -33, 62, 58, 61, 45, -47, -4, 121, 74, 19, 
          -28, 49 });
    boolean bool = Zt2e.ZK();
    try {
      try {
        if (Zrnu.ZO.charAt(Math.abs(((BigInteger)Ztzw.Zk).intValue() % 32)) <= Ztkh.ZP.charAt(Math.abs(((BigInteger)Zbu.ZW).intValue() % 32))) {
          try {
            Zb2p.Zh(Class.forName(a(-8853, 19804)));
            if (bool)
              Zt4g.Zz(Class.forName(a(-8852, -24040))); 
          } catch (Throwable throwable) {
            throw a(null);
          } 
          return;
        } 
      } catch (Throwable throwable) {
        throw a(null);
      } 
      Zt4g.Zz(Class.forName(a(-8852, -24040)));
    } catch (Throwable throwable) {}
  }
  
  static void Zz(Object[] paramArrayOfObject, Object paramObject) throws Throwable {}
  
  static {
    // Byte code:
    //   0: bipush #10
    //   2: anewarray java/lang/String
    //   5: astore #5
    //   7: iconst_0
    //   8: istore_3
    //   9: ldc 'IîÖ@+qBPÒvýðµïÏÁ´nçé§ÍÕ#â*ýÚ/nw^½ßÞ1Ønå¸ê­×õÁ7IËÕÛ"¥Îÿ¨m÷FV$JÐK½°û_·Bm#S¢ÍPýÒKGÁ¸\\n\\t®=ð7ÅÕ®ëoZeú_G2E­Þ?U\\r( Æa Ã©éù0$×+-Pøõç<Á©\\nÕTÏVs©½Ó±Võ4)Ò'.fZÅòµJmKàæ$È{R»%.k^frgMcüËUP HpærÀÿ­htÎl{³\\t,m¾!Ç^ì4¹ÇÕ9 S\\b±NºB~?i-i©~ósa@Uv"`\\fxÛ}Ï6­Ý:jyÑªÆrÕ7R³r/?äµ7G5nVü3W[×¸K¤.ñcª\.ºö1J-êPyZF$/óèàà<h)L\\t»È:Ç:P×D·Ïýå¬:¿3ÓE3èD_ÎêìPO,+\£A[2 O¶+!öS,­µ(&¨âÅeÙª,Æ.£EÖyRâÚª+=JÜ£D¶÷2òxAøßÞ/±U^O³µÁö÷{ç%%BuÁýåÒÿi6sæ¹Ë\\n?\\tü}Ïe}­¶ôÒ¢UTÕ¯ê-ÛÝnÜtW²CØµ!ã<5Ã!F0FF¨×EVx$Õ¼b0Óno]ºånE±yå<wt¸ÒLiìRIÍê@½pR9Æ\\nce\\t½Òv â_Fð'×úB¬1û®I¢ÕË*4ò|Õ/»XÊÖ\\bp­íX`QO -æ¶+ÿMæ{³NÙÿMJNß*¡Ò2x²°&ÎÊ_*ò©¿-~/¤/Ã?ùý5äT¼a²Ü­ªO5É×®ÿ÷ÔÎ'¾HUmSV0Èi\\báXl´9K¢a0öìIgZqÞóçq³{J6ÈÖË!¢ìåE}4ÅdÒobfe±Z±v1(Ý©å\yEhMæ´%ËVXÈâ×[\\f»À'=ýT\Rîtny,MÕYdóèd©Ï_¿ÒýóæëKüÊ¦íþ4qoW5<õªîÌÓ\¤g<ÁWòTËbÿ¶¼$ehÑþ®'­Y²T³^Îc6Ð¯0'Å}\\nÂ×Ò2Ï6õ^"[Búi!×*_¬·ÈÜ¼å¨-ßà \\tt\\tw]Kå©Ö¯nð°½Õ&)sWÚ×c#-Îó\\bÉ ÖäÈ¤Ë²½çmvüH¼rñO~2Ù´f±÷êòèn¿,W\\b½3åö÷ð>È°aÛ/ZY¨\rçt)Qøo²ÏªéUÂ@à_tÞ¥×9;<l±ö«ÕÛ~\\rÜ^Ñª¨©Ëz¢w\\t'úOù S-tnF\ëX>Ìº±ØægÌä ©û¡S \\t!_pýÝÐíy×>ÃË·£¬ÇÍ>&óJÛ³¦¼xäãSaj?4Ð¾5s/7¸zl½°q \\rY\\rØì$GÊHkñÒ,ùÖáA¦}ÂY¶ZúÀrOú<l³ø9ÅÖ^ 4 ¥Ñ çÌªªh2 é¼dàÐßµe+Jpa8ªüNJÜoÆå?ð²£¦¯ÁQÑX9|³³7«))ÚÚ2(j1hÍÁ$øúå©\\f®c¼"Ú»'PÎ%(r,vW2KÑÓ@àîùïªcx;C\\r'èþ?ïÛq1goÊò¢gìßH¼]lx÷?.³§ÓÖBÝdÖWÆ{t0ªµU\\bêÚÌ6­@Ð\\n×pÛñÃ2"»¦éw"Lº¶¢A÷5xuDû Ö¾#t(öÚ¸(æSm'\\f\\tÅc¤J¢¼ÑKÞ:´}Ew=r7tÇßSâ£þ?t¨Þ oÖC©³§{¸GDßjÏäA»*Ü¹FQø¾zL0,ÛîmÉÄVZ®>ûð»e)¬`w«] ÎýÚ\\n×W×¸ÙYxê¤sÔ`ÒrWÛ»F\\täÚ&ôu¥dÔJ¢ÝwùÒ3tÖ}kN±Q&\\\>»¡'~åâIçû4GYÏcn ìstqQhjÆ'Nà Ãá¶-<æ2É±ÕMÊrï¦+rîS`R{ÕöØ/\\fað6ÝI§\\fRÜýJ\»^Ò%¥´'"ÉHÒï¼E¡öÿZÈ°©þ(\\nÿÛJìVéâ \\fã%.KfqZ/aáã9<|_÷q»¡+²pWÊkýËnEFãVAÜtøË£å0ú^Ô2fýDAm¥ÃÜ¦êWïKTu"\\f\\b´Ø> ¥1µçO/´·Jè\\rä?ÅK¶U\\bjYÿÍ\\tÂØª¼ G¾f QG¾@·Ñ$b\\f\óÒ6;sv`­·e³Æo¡TO~ÖNZ; gë&Ä\\t*Z9µÿ:áÔvCÛ;2Î´GvÏ8°þipûa?8Hsf×> /×)OðOaÛ«6æ`ý¹düÃðº¼ÕÿÅkî¼¢ìó>éÍÒvÈF,×¡\Ã^ná{ï$Ð`ÿ>çp?_Í\FvÂí?þ7ÊÕ~,nÞ ýfÚ«êâ[Z 48ò![L-ôe1ý;*\\t83$±À:Ó(¡Eñ È\\n\\fIm~!òÑ¹j¾ÿhTd·;@i"ô\\txUÝ\\r¡ýOy;ì?öæã¥\\nêõßÖ®OÃ^¥Ì²dÊMcáìx;x8Lø´h'ô¢Ñºâæ#EâZz÷$qmÇèºy½ÞS:zçDzTùæÿti7@c\±Pm«¾ÿ"ÃÇù¤¨íh¨ÌsýbIÕ}+.UÙÇïuÇC[ø»ßÉ'&FmnZ#Äúj³ïî\c?ø¬üHófX»ì½ËLê-´³\¢ìo{ØØ\\bhdWú°múÕu°`\\bÀÎªÐ£ú¡¹Î¤ß¸iüÍ\\tÄ0Û?¬i¯èÑ-ÃÈ¥¾¶~Ã¦gYs\\tAUR¸3ú\\tPù>iìÞ/BC±~º«Ôx! ¹VþÑ%\\rb%JU$hàªDfá2nåmj\\f?6D|JCÍ¸ ÌöU.Ábùá}¾3\\b±!U«Y¿jÒ^³iBÊðsÇrc OU¶×"<_WQÉ]|Ua¬þB?\\nÏ§ÖÞPóDÎ\\b8emD@X E|nÅÎê9æ`*.9©\\n%·ìËôýF6²ûv" *³ìbÒççGu}j/ÜrüfI¨ï;K_YhIÙÅëOBEî§1µY¨Ð¯íýô¥±Áá9îVK½0!6ËÁ,Ï«CÓ,O;F/¸«©VOü ?ÂÐx÷v/fsCHIeÑ³j®ÛÊÌ³O1%æâM½þr¨W®ÍP¿ác/¤)K-HÝÙÄßÁÙï«þøHÔË2Ë\\n©¾(º!çØfá~ÅfIßÔ×=tÌg#CÃbWt;'t(¤_´ÙxëËT`¨xwÇÎþH"EKbÕ|§Tt~\\bµ ÚXÞ<»\\bHú¾Oýîd±Ki¡¼îh>l'¸C\\t_¹Ä~ÆuA¢ÜcÿDæJßFÉOD³õEn_ -'àwü$"Çøm<¤r<âÏÔÁýM\~Ð;k;1¸jà\"¸1÷CYüS´QBëÙ×ëÔ°­\\fvÍmT7ÍÇ³å67¾rç5Íy]ÓÇ['OíX4áåý~&üFë±uSí÷B`NJXýî\\r'\\rÏJI/*m Ã«²ÈpØtGÂ-Ñù6Çü|c¹nv^j­ñ_¢«ë0f°c4ZG¶R¥¶wgNr;8Ö1øÛ}8°y?3Ë»`éAÏ®2½'%£(Ö.g%(}øFRìÝI<ËÀ¯V\\rHµï©s]xÆÚÒIA%leù¥ÁßÖ#ünb__`ÌÇ;wø¯ÈÈE¶³l*¹ûRÂÖ0ï¾@5ïÚ2äyÅëª$Ç3rm÷¢(Ä¤X/Ô½:Á´nÉ¥Ê­D/t\\rV¨Î?ÃÈ³"v¡`¡©³8­{Ïz\\b>»³¡ÝAS®xiÃÐ¥.¦yòQTç¯²ËÇÌBÛ7\\bÕeøP¬îînà\\tGØhRÄº­Aç\\fÀ¹b³ö}åo®|Ü©¡¥,`b\\nÇdQNåEÚiÇbRõâ4ÌÂüù5Ò\P(aÃë_ÝM@ôrËdPNðÞú}ÎPÁ8/#¿ÐÚMO'*¨YÂSSgIOp«\\rxö:/TÒüÕ0ñ>Ü\\r:8.ä|0Nm%éQw^wf6´k¥à/µïiÅP#°-ºé\\fkHý®1æOc\\r)Ä`"ÖXWÔ¥m_á!Ò¹ìê¶_ßÚÉù«Ê­o²°)\\fÒ±{¼ ~ôþ(Ã,ÆxF ÒjÅt Ô9+öúHl`×ÛJ>±aÞ¡<jÒ4¼±?¾z5+¡wb¾ïÎj­UE&¼ØYSøÑO¯ëÍqkð [åPH®X~èþ%ÂÈ¾]oµ¯­õMò¯ü°ÎR¤¹_s¹ùxCÐÓ¸·vjä;\\tvÉª¡¯oÎÎÏÙ{³Bí×\\tùÞ÷&Ô2ô£0!_ü¯Þc¼`wåÿvð6ï®­¶ÓüÚûëRT¼Xª®âÙKýÍNéIðäEndtÓ½JNñ\\bßå`Ó0Yó9#KÛ\\ï¾ö¦Þã.ê|Óv>¿Ó&±T¹K13¼ê[ÏtàýåË'_\ÃXp s">À2ÇÀÄ%òÃÃRÙÞ fJ²ÁóÆum1å´Í#¾$l¤Ð\ÆÉÅ_Ì¥K-3Ã¾\wSørÀçFaF{qä³QVÒE©¼ÃhA×{ìNj3yC§éÈüq-®\\rIøT·¯D2Ï0PìCù°ìuJfË+Çt}\\tÞG×so>"Ä"HQnÄüD4ÜjËú¸\\bzUÇ&câÑ&Ó¡¯ÅÝº(\\nÎý¼tSa/7æ®ìÙ«sCåà"3õáu+N/þ#½ípv\\r)wõ~í©xA¢/ìi×2´ý50þ« ?ÏNQÇñ&ûÊlYIÃ¦U$ZF+O$SÁ6JNCghKåzd^ØÅ'f\\tË0(à+(ø¾\\b¥ÐÛZMísy=Ã ÔLô#Keæ#§tôõap¦{YÙýLðSÃè<H³ú~!ÒÃÿ"ö Nötr6,aç1Rª»òªJbâ[ô½ÂÁKþbüù(h©b_î¨­å)ôCÖ.ÖR9¶Á8¨?ð.ÛRUÁ-þ^Ï*:8å[Tj$Jîè¼=&Ñ\\f¶TSÛF|x³[¶/ÕÎR8¸æ\\npKãcv7¦Ç#P-¶Ò¹s =gÄ{&EðÓÇrÀé4**N´\\r²æ÷IqË¹ÙÎã#Ó©I\\fÏQrôÞÃquåïNù}1/ø4JäËc¾TõÒKs êjRÿ^TÛ¸Ôy¥²ÅDäË°å¾ Uôu#âeâÑ±@;/Ñ6©"²¬MQxOðäHT[bjúXý¿FR2.Ý:Î")»$F{=j«ïÚ²ø£?\\b0\\fk?ã±~u`¥øû¶Dï-Â};ëü+T k:óÀN¶ÙF&W3îpoüøb;íU³uú}>èwÉÑáÑàÓg&Bc#iÃB/O}\\r~ÆUæ(Çe\\rãþÖF§qû70&I­1ß÷¦c+Ã¾r1sÒ<iF¢Þkqûµ~ß\\fö75Ç0r³<¡o|b"Ý Y³}ÆÜº8vÃÍZñ®ÚF8S\\nG1/úö|zr8\\rÌ²+¥tyîSÒGlI²óÊwçÒÆ®¯ç(\\nöfPÜ[K¶«¦±ø|¢Iúyqòñó®`Nù'¼?tQX\\f¾B/'xDýV)ÍvVt:(º\\fr²µ0¢$×lñ%Ç+¤!¶<<\\rµÊè§¼Ì·¿>gÆÉ¨å:ØÂJ30ä  ¾Æ»Ñeòkì«¼9õ\PýN8ÎVY°ýf¼DP¢s²;Fúa~k<ËeGR·0åzû*fº&Úº³Ù3^;h¦¤i\\böë(k/h¸go¹ê6§°0ªbK}Þ%Ð:ÿÞoz-ôzÆï®x9tO6fZçþ¡bìEÙséÅeGónØÛ+Àz è<Ö\\fÿ/nÂ+ÒÏPÀG\\fX´ýå(]ú ]¿YÁ¨¤þ­Üñõ»¾ã.¡a1Ò`-Ê?^~³þ×s4AÂbÞ#R,óîóü3oOßhkªõGYî ø½Ýx7i'k¬k, ÙÐ«^êh7B7öHèìÿ®\\nFÅ3#4ÏçÓåý´¯\²Ñ³z¬¿Ëé^û¤Ü70#¸ÿIV¡Áá®ìÆxó¨­Qmåè:é|çkñ×þv:OYú2Ïd7³©mÀz«»ñÀJÒÒ¼#fÈ$dåàûãÏ{Bår&å1öÇTIT¼$ø\\n¹Hal9¦ÎÜQ¼îÂsMóÎ í YW9\\fMS¢{\\rTnñù¬eVÁ°Y[Ìý×â¬¿±7>ÜÿªFÙXÎÓ$K\\rK¨d~2æxO¢4~??w2.ÇïZ¬µÎÞ@£ýÑì\\t$+k¿ÖÕÝÕ\yf¯µ<Å%*­Ïz§áÂû!ñ\\tn9D¸`°ªTÕ^ò6Qä_\\fO¼Î"ÞHÎÊª#'µK=-ß*ê¿j1Éú×¦Õd5²Ú¨\\t¶ r*2IåEØÒ2eþîvÑÉéâÉð£q´çf¾ÏãÂkG-IÄøîê¼êØU·üá,"_X\\b/1O*),ÊIäSýE¹\\b¹Ä\\f#-¤ÄTý@Ãx'Úã\\bÑÙâ-Ì+T9ÇèË;5¾8¾ýXDUcð§ÂxJ\\räFÎzÍ±a$ØU²¬ÕÎ½TZ«ùvÃ®{ìr^¡«wg¯²¢ße®µ.Ë%®&µv`mL²&àÎ;±±Æès"´±°ê¯/ï¥a¢Q×fðBïJâßý÷ÿI[VK..ª]/DëIÁðúÅ\ëM,[ö¥ðmNÚ_ ·êc/êù Çu*ô®¥]ÊÖ×÷Çò5ß_1HQ8ÀIüèã\\nT54¾¹]p«é{\\bÜÞÍÈGQYD4&ð\\tÝIïË?'®|ÌÐ²ÑûGõlGak Ò Öç½J³â-SÕÌÅÝ6Æw&³y¦8C c 1óÑ\\füHý?ßÚ¤ø4ÙDdËYW\\rVæþÃ~­^¡y¦åÀ¡hñyl!ý§õY+²YðÞHJÂhá\\nß¨ó)`ÄÍT\\f?F(}/='{b,=­qa0wÀª¢£2ºÜNÄ ØÌÃ"oÑG%:$+»b­"ëõë0!k+\¢vF µD6);1ÅS¼æ÷ò&Ù<Zí¨ yöÂ¸¼°ògÀm·[ÿQô=`{ï®­Þãô­$8¿êµP·ÐF\\b]&ÅaYõR]{8¸\\b)÷D$-©Çä2ÂÔîòª-V³Ì¡tJjÕ~¼õ\\fV5|¦Ý¼k¶¬­m\\nÖw\\tösÛrÞ¨ºÒÊ¤Y)²1áï=³Z²øÍLCJäyàð3Æè¼&î9ð0Ð\\t·Tù_ò¦°q5@Úí ?Hð³ïIÍ¿Ó¬v¿aÃ õúß¢U_¬HÎW×]$x|â\\bRBÓ2VÀã\ç¢\\bì7£Ò³]c^X´OÇC÷6¯\\bÁ.ªªªx\\tuáXËhèà¢D@ÿè3± [¼¨gÙYaè¹$>÷&;_\\tYDæ0oAeÊ7÷\\tÕ:Õrp­E Í\\bco;Üõä<À«ßÛuðë§t*RÏê"¸à^<n±Ì»Y»»¡#T×¶ÛL#ÏtÇÄBÒEFp©±wS¦è\\f[ªËµëÈÆàce«6?_¹Ú^P~Ûå^Ë¤;ãaµº*wFîX°¹ÏJwÈ]©¹YKN`^4áHãc¼ÕQ¼×FØVÍ!BÜõc0P\¿Öæ%f8^D\\fò*S xg·WSt8¾\\bG ÓQÂ»¨ðn!F:´ºqK èÛ×== :å>Z«k!µÑ+Ì<áµû·ÒªrÏ·9<ñMoUDWÜrO»ïw©Åm#¡¨Úsi º.´hBr¿ãÙ\üHaàÖ-ïîÖòYhÍ§É5H±ÓÕ¢dÙÓÖpÔ;V9Å³{|$RÙcÏ%êë(CdÎÏÞìv¯VJÿ»\\rÕ³t\\rN^[ðåj¼9y@Oñ&2·d¢¹Ý­REÞadñcBdßSÓ|KÝÏóÏ"1&öÆ,Æà¾ý1[r ç#EØ¯WMëã_6àh[×ÛÁBM·\\n°N+¯±7eèv\\r/ZD,scë@ly9ÿHÂO²µ¨OQ·Fw0Ø.´6ô:N¹2,íTo¼Y8Ciû]3Àg¹ÈåéÌ¹©#T¸æ3Ó ½ÀÝ;¿Îu!`ýðbÃ vpÐc\\fÏ·ø;0;\\nô8fºCU}´ L¦1`1*m¯àªèe"É»§ô\\ro1Yäã¿ 7ÿm¥tTOø\yF±Â­\\b²Ûw¨­NÄ¿u\\fû®ð³oìèG¾B!p{yÕQÎ[daÑI}kU#ðí!ëðã*÷%º°Ö\\r¶Y\ñõäz\\bÄq` aÈí3ÿ«ðK0d[¥FI%µº?$ÊÖö\\rXI£áþìÝ¨®Ø=^ä¦*l¬AÝÑåby¦60à§8ÐQýäá:c@[Ûê/ù:TÏ}¯»?©té-qçÏ@o-´AùNå|CPÒð¯þÅ?ÜÈÿ?¹Ñj÷úUþ#½~ÃäêCuDqÅßÈAÙù»kãä9yNÂ'\\boTÿpòû×*Vaá xr,dÉ¥Eh%uËúìL¸!¢ªÓ*o[\\f]\\b<Û¯Ðú¡-éüõæg 0§!'hº)8-V9¯\\fW¢¢·ý\\nÁZ»§ÏxßrPwÎUÏ|j7<³¬.d÷)ò/ î²n©\\r²Ä®Ç%\\n6Âwþ\\bo&YÃé®'Ô®Ì-¿uÎÏßîhBû©úâ+ýØâÁ»ÖsÒ²ÌýÀ4|7Ëúèíe\\f±¿60«Õý}riO\\bxÍ¥®y¸»j¾¿töÀ¸¢¸ç6õ¼Õ5L á'\\f@-{ÉEÇ_p£ø+cg2¯ ¹=~z°ObõâÏ&Æ¹üôÄ îÊ_ä\\tÃ\\t÷v%²X¹i9\\býá`À§Cc)ÏEìÔk?çLüoBEmr ãÏ5fÊé)c~0´}À78 -¨0­;GXTÛ=¢ñ¸{oGù<z4ùb1OÜc»<¦èÒíièÊS]Ö$u¥H£ñÑü&)#Uè8óYKh/×®3Ì\\nî¶©B$î]Ûb&YÀF´Èvê+ë{çZå¿Í³Õ¿Ìã%¸Ø{·aÎ5 ×ÜyÈ5¶.+vy´]»WÙ=n²ìñ}®Bð¤óiÔ2Ã¥fY|úÀðàplò©ÆJ9(kAµ,?ÿØè°ñ]Cüf:Szè¼ {æ¬é>ûÇ®\\fóÏºÃ!Ê[lbülõiHJ\­x\\n{È9{×ùç4û3·ÌÇkå.eì­ÞA÷Ù¡µêvÐbôQ.¬/Õqø½ÌLhjûµ$í\\b6ÖÛ9P{¿À¹DÎDÃin²BidÝNcº#ß­$Ô(ö\\n© ù:bQóG22ð\\tçP)\\t3m²Ùá¸1üiZãÓºÁm.EH;<£aa¡(2òøL¢1YÆd¨vS?ªkÍtæt3#~i+OÀÚ¸ä·ß`ÓüÞ;ßÌ dtóÊð$¯R=8aÊ2µ'½tKBR@* i"q¥ÇËùÿÙÁ/EµjéEzá¯@KåÕ\\nm #ààq«Î÷P6vÝjöø¯êþTñÏÍ\\bÍ±%/ÒK+A[JSébxæb÷ô£yf97?´<úÅ¡4¸ÈdÔ«¼y¼Sù Ò×¬ñ+:õÑ0fkÃ\¿ÕFÔµÊ6P)1»¼û÷Q&jW<ÞZ×¨gëÂ¼ÄòéÀ¼·aÿôü=`¾{®#Þ2ô$¿µM·s2\\bÓ&acõ]æ{%¸«à)yDõzìôÕ[ßT¯ m6Ñ=C¼¯ÔÞ\\bhÞÐûHÏiô³dWi£Úà(7dPH\\be;®ÁôrÎ¶?0Âvèï{Ê];$$ó³ôÚÏÈi¹$Ã»4¸ÕÍÒ/p·}d\POIÞW±ô\\tYº>©¡ÆÇ8¾<¸:<¸Ï hÀ¶MñOÉ »õ¶ðd³{·E_!ýÛõâ¸'àí3hpãì¤3FD0Ë¬¿í ù¸eÁv VOfwçÎ,\\fÙmoÝïïüûÚð#°o5ÀÜ]bAÓ<°äÅtÉÌ">Âñ"ñm_jJ¬¢1qSøågÏW\\b.ÞÛ­ìlyJ\\fÒT¢è@K¼ð­¸²i+½%-Ób9Â=ÁU¶Ègh)S4µZ~\\rqDÿ»Dé6\\fª{È·XZ`ªþg#z½ÐrõâyO¤VV.öxÃ_áÓnì=Åú1¤Jã9´¼ÊÞ²6?^t¹Õ±,"±¢jÍÝM#ä¿îëå®Ï[½ê¬À»e:áëDJP³'4Lp¦5jöÉ'>CrY\\flÄ2Èµ=Câ\\fàþ6AJõ\\rÞ6û£çØ¥q) [ õîû»³aE®Á\\ní´ÈøþìåiÉZ;Kfàþ}év¸'>¸0ÌJ@õÞ $Á¯S§©&Dï\\ti,tqÞ^X_ê Æ 6l¿ô r^aÅíìGiÊ8âÿËL5_õK¢óÂì÷¢ÕJ´K¦mì¡A©W\{`Ã¦ ý¥sE*¥Ð.v69ÔÝÌYA`%`HÃ-»õ·kR·d´·ß )îîì?ôV\\bÇ\\t8fwÈCnËuqyííÀ´1þfùúÇ»sc-ð[¶HQJ2ÉªÞÝ÷ u\\n\Ætë³P`æ_fm6º6¥$\\ts bÐ7NçSM=í[H<ÞÙµúâh õ,F6ô£jáb:L Ê{ø\\fWràûBnÀ*k-¯?«¸k¶Ï_Âí^c7Ôr\\t\\rT<QòÜ¶«¥õükÅv¶"´i³ål·íVQèÂyKÚBow\\r¦¯Ú~U¿ã\\nNéáåÆM|NÌÀ6ÄÍYWäc¡lù9Jðü\\b}Üÿ$¼ðáõ×@>§jª\\rÖÅ7¹Q'=Îâr.osB.ý^´zð5×Ø-8Cy0þh¸ÆËc¢¤§0iqk»5ö³/ÏYsÓZÊ¦å»7õÀºá>¯ÊRµ/JÏXh½óæóeÇ¤ARE§oXZVM¡Ð\\te×¤¢âA±¢fQy`¥åÓ|~K8ù &¿Öm\\tÕLtCÎäûÄj]ÛÉ)¶ÿz§&Ö2#µiC8°TÇê=9ªfÙÜB7çÝòú¾`¢v¡éåÃ¹ù:ú åüVb2;"å¯2|~cWl®HsÀãyË}©\\tì/0ï'ßäÿÇ f½Ûh³ S5dâÔ<Ågc¸(ëð*ÉW¢S¾ãà)ÙZgÊã»|RÆy{&þª´üèß»êvh1yrÕÅ,IQ#I\MªÑ®`j0ÛrävM[5bï öO QCïÛ\\n?Njg=ùÏæÑÒ7¥±1Â²5\\t ;w?®uuvLY"E£å1X´\\bÕ÷v +t{~vÓèë¯ÉÙçß½â|rÿMÔîÀ¶ôðÐAäîötØÃÉö l\\bXä%Éë'Fñ©2þÌS#¬<ëÐÐ0ÒH®ÚlË²¹õè ¾ÒE@M/K&=*ù»õª7ËÌk?êùOI§à3,åÖå´ûªOÜu'®îaÏà<âþd§ýDåu38\§Ü´H´ìñý´k¥1¿¶¿ràj»Qh»\\rS|wMÝ0ÊÃ1¤PøÅUµ\\f:0÷¡¹|0)\\t[\Ø·ØA½+ßÞ8Kò§2±33´N=>«3Âø2ìyx¸79$±H<EÔIß×lãy÷YnÒn¤%/²¾.D )Ý}ýélë8²Y\\tû ìÒóO¸ókMÜê?WÓg¦FcÛóí\\nnï³s1;Ïpqg:ZÖ4q<ÃþÉ££Ñ/¶/}P¡ñnüÂ´{Á%Í»»ÀGC4´Å¼Éh(ÎS¤ïtc4aC-Ê)ï²ÞS¹ÉN¬ùñ±5:ßÞt¸Cà°êÒË/÷ôÇíè]Óñy;Ý½0w³åÃØók5)w^²6¬ëcÞZ\\fZt`çVzc\\tñYèìè¹CÏÝ-þ*þtYu1WVn_íéÌ\\tÂ)1µùzÄòmøØY\\nø)àh)þK++Ïømb7d<·*j}x\\nÀF"'í`E¡HAºo¯4òÒ·°G4É¬£®g9 T¾Y>5T(îá:Zë9`ûQS£\\b" ÞW+DØÜbC1®-|°|ý,{Ú@ú±L=¾Ì÷w=+Î&16*éeÑ%Ep,1Ú;BÆ>\\fL¨õñû@BULUÐÚlÎ7â.}vcCgUðq`Op²2Èïw\\tÛÚ äÎï9l-d¨QF¬Øg[n\\bãÁØYjWOÄ\\nÉÌ­D'RøP?-Ãe\\n°û\\fEü¡ÿ ÅÎ®DìÊôàò(â½ÚF<M²0Ëò_\\rD(ÙYÚ»W¿/.¤(µURK\\t±²!¤j]ù\\bjÏªRý:ÅP~[1óVí¼Àl\\n¿#b¹%:¨Î¼\ðs\\b¹W±tuêÅ®b¼eÇ?Ká cðïM#¨n½}@A'±ÑÉWd 7½H5#Gål±=½GÀâU§\Á_£´ÀyÖÑC¾»ôºÚdgtY¸ìlÚY-lí0én'ÁûbMJi«¤í-isF}R6Ë'æ~ä×WüS\\fÝc=ï'PañÚgª¾­Ò%Ø¸åÆ%tâaÒëãXèÜ\\f®:ðCk¼E'þ\\bn­vÍXÝ`Ì&\\tS½¸åzª¾¸ÈÎ¼ªØIóh¸PþûÍ"ã0I6z9®ò|9ÊÊ(!ßeq-Tð\\tìù\\b3-çCðO}1ê©P²ÎÀÆúd­2}"ì£´øl\\n;î¾E}1ªGèOþý$oåãÄÞÅ5À|L \¾K6þWY ª\\n*\\r 6 óö¹¼ý´pSè0ôÕLÞr>4É\\bÐ8LíCPô`¹u.åViêô+UÓÌ¹;ÊnK¡tÍx#épÑ@TN¡À!z'0Ú]}VéåÜü/CÛ7Þã$SªZÅ #->Ø<É,ÆlëÃ½{Ûý;0u}Ä¦#Sä^|H$u$ÜsC6ï~ºáÁR¯ø\\f=ÅÞÆ"WÅþãxcyÌõiNâEï0/Ò=eYåøß«cù1Ã;+júui»ÜEú,Ä2í10Ô0ûlÙòÏÛó×ßrñM"7tTÓ»¾ÎêêöÞÒoÄ¾ÇîÜ7¾»\\fO4J÷Á}GH,ZÊ~n¼EÞdÝª*û]"«>ßmû~C}MÜÙÔ?Ð2geöoÀÐ þUÂ ÂÎSxVEBmé|Ä½±¶yð£¦²UÈì6û·ïömè.©]ÝÏº$_û×s³¡U\\fÌ®µvÓÇsLúîFTcÙ±S# ¸;-ù 0·úIüqÂÔÕ=+Zià´Pó'¶C¿Yô mË4ÖÖ|¥rÃ\²îÃÿÝôK0*p3õéXG¡#þÐÍäÓ'9iÞÀF©/ùm7$¹[¦ÿ}ÂBRú¢qí)ËÔÁ!ø¬ZÝê´±\\rÌ\\tJOâaµ>Ëë¹ ½}¼ÙéÅ¦ ùì@Û=¨h3nvî_ c<~Â ´yçz±6Kh¾®@<a+¢>¦àjº%ë`\\nK¬çux_µÎî¼%ûb"÷Éh0X\\btRû}Ç~Ö#ÔÙÙó(­ ³æÒ'¿ëZÖPYÝck6µßìbA»<PFf¿¯å^\\tm}þ4kPËÒÊ\\tN|¨lrS¡ò¯:·çÊä{ÞUÒÆ×ÈÆV-¥\\føqèµ\\tÜUõ ;¸ËD8jÐ*;À2·ÀË³Û©0ïuW%6w2o\\tÿáMÿ\\b¬E¤Ø~Æ áÃT6zR¿Ø¿ô¥k ao¡Õë\\r:xZ¯¿9ï&%^`\\tPô]ÿÍ¬m«¯ÏÃbEY(Ã´ÚSÃ*qq^Ñ.F²OIOÍ»ìþly:cQTïö"\þË$ÛÃÚQS-\\bÊÆ+¨ZoéY0Þâé9G,fÃû¯ÃhLÖLÁxî\\f©5ýúÑµ|þLÞL0Öø}°¿Öº\«ñq&¼VñTVä,?mÎWÇZàr÷B5Â*âtW0G, ËÛðe£­ä\òT@)Î·=äE_H´ÏE[ôG ÂAÒñþó©0°ßeÙU$ùº ³¦=S.+WT |\´Öêfs «\\f}ÌlÊMÖ?¤¼0.7Ä'ÿuDÔë\U¶¸ý r@«_*§Ï\\bh¼ðóCö¯xþû sÈÔDvbÐêm($ÚPy5Eí)×À&tg)E/ÀéõÜa¼Vt½W¶\\rñómþ5pj\ÿXÃõï§\\tWLÓÅ>\\n,1ú^Ì®8_Å­kcå)®{¿óÀÔô¯©ï°è\\t¬ä.?ë#¡Î{rÇ¦p©zæárQ\\tG`{ÙDù2Ò>¼â±â½áôj»lÌMÉ;6a;.ã­>åÊRpµ>×¡x°ÔñfZ77(úÃÚ+|\\r.©¡tíUR¸N²Ë·¶6ë\\ftã×!ªÜ:JÊûùn÷S¢\\fÐö¼UlW~H* §xR\­oé GXI_qÜ<ÿó¢ZSºØ¿¹o©õv¨äºrÿÙ2Rl"÷´#=ky÷#±@©+ËÙ×ÑaíÁP0\\r-\\b'Kq"DN¿ÃùÀÿ0TK{?²½\\tä°«u®ÀÓç6Y*éï\\bHÏh´J?½JÆÓkúáåP7ì¼¤çNáã¹&¥Î³qýÓß¿Â1Ü3k¸á¢;ýÂ>¢¢§¢cæ«tcï>dP,Ìùn9×à®Ô.G9¿uÅ_Æ0/óÂ¦Ða@\\fv®úP/(gö%¶Ãô¿ôñFõà&búø§©N£É8²Ú Ñ}æÍð,Ææ1G$ØáyO·ó*iu$ö]9MyÐt¶«¸ò6½UWS ³¢ðIµ:>j\\nä4Û°ßìÚ[´8ù)8)ÿµ*½KÖ\\fÈ<§PocW&wdÀ/Ô{MÄ@Ü7¸EXó|J¢döôoÏõpìYÏãéÅ]K´Ò:ªnWüÒÜ^ãi¸'ÈîGþ¡(KëZY`Rù]ÐÄ|cbÓFlÂ0]¶Lr\úW°ö=jöøâEA¡¦YÓÐ\\r0ãy(Ê Çbce ^®&þù0ÿ68þ'p<QyÒm¬vnk!li§PbÛè¦¸|ødTGUÆTÄÁI?u¦8âW©8ÐÏrgî¶¾ïªÎD{!ÎxJ\\fîj¢±Ûº'Ðu]O½Æ9R.óó%?Ó°¦V®\\r2ÓHMYÌw\\r,ÔÓeþß!µ:.¶MÑØÜéD[Ý#k:ß \\rË#Yó\\r0kîrã¯v73£!SÜB,@ßÌÙï(vqº=¬Ù@üsaÇ^Y¡Ì@R¹aöB'¢`v~³_\\fuø°zÉ>Ë³ðv3HIOÈfA\ O=ß"¶z=!~Ã¡ÇÝïb<¥ú¤ù@\\tÊí­¾¥¬m!çYÚb0q´¤4BY¨UòWZÃ\\rg-¿\\t,ðáDh2kØÎaNn³¨ez¿ãdpööË)M©MäXÄtïO#SUR8ã>Ï¾YÜ'³z³d¢Åö×¶À}@¯ âôFÞ÷Án°3P!kd¿~û!ÏIH¯XnFçWß\\n·Ñò¹ðæ®=39ÌeNÏzóIÉ¿gý^ºë\\bº »T(Ì§.sÚäµvWÈÐòòlYÎUb¯Ä\\t\Í%\Ì<¢a^Ôêfÿ¼oQÝoY1OyçsW'W(ÑN!´óBvß2w£ö0òÓ­U$!zë^LìNkÿÜé±¿-|õ}´zý5yu(o´QâFÖ#6÷0ëk°~{ÞSå½jve~ÆtHÛó¶Ë6ñº%;Ú@ãÌOªaÞý1,Àxoõir²I3wÒ°\\r£ß5^õÂØzúÂNT¨W¶êÞáû\\tÁR6ÝN2DOÝÑK»oødÔÜÎÉÙÎ:À0ÀÎ÷iã¹ÛPT¼Rák³òX'6eZ!yqºúmnü8ûÖKtôÅÇ*®Ë\\fÓNNp³ÌaZA-þ%!ò4ÕE\\bmôÙ<L-AnöþpN·µÖ\\tàØó~êàÆ¥n8:È[vì2÷«*xH²\\t n¨s}?Ú@:úáQ\\rÜøóyàÄ}xVù[;è»7×£J¯,_+ð:ð@¸ºw\\fùÂî1yõ\\tVò1ïÏwõF×¬ú½·ãZðL]÷f6áNÀ\\rô¶É¸d ·ò°,ÆÛ^#7$ÕÖùAz¯@äíâ¦¥?aÍ£À\\thî­]wßÝUÕK8Îf ÝýÝò¦£t`ÌÜ°^æóVÕ«aaÔ×`ó~E¥¿¸\\bòð®±gäù09Kâ);@íztÞÈ°ÐLÅFë¬ÈÎþ!züÀ¶`h¾àl­\\r,ïJ\\fÓP½ÁXÐí5cU\\fé®¤õ&Í3ªòÅFrçJ¸Òn5-W¬5ôÓüü\\bb,[Oð~'Vèþl³hâÄ5L`ßÕ]Rÿ\\n.åÕ¦â5×¸×2=ôê%óªS´úÃ}¨Î¥þÖüR"=%çÚäØèªãÏn7~nÐá 94m®e.ÓP²M^]°Ùê£Þd¥ÿKo·eÑë¬ÊÏ\\fò ÒGÞ4`mÈá·ßlP·c¦Q"(Y£Ú8zDäRülÜWv­òaøÎ!'Ù©0¾!¬æçquÏ>@æmñ?ÆNbeº­6y¥E¾J2½ Ì³sÇÌ£#fJôZmöZèÇæ[Y§Ôº°â+Å`]É½·¾¥IÐM³ÿ:b=¡¡éyw.´PRcT7Å9Sk§ÒÄTvV¡í¥§ææÀ«Ú(ÿ´%`¶Ôsñ»u)ãz%' ð¯"¤q¢².X¼%¿´ì¿%¥o&¾IêF½Ý.þTýVbI¥òZÈþû®89Æãi=°÷8{DªËU$µèÛ¯!ÖJJ[°ÖÜÒO«·ÓfN[),ääþH¾$ÀN^IR%ÿ)î)nUGÒ`\\b³ª1àfÅ½_´¿Ö&~Ôã18>Ç?Ï6-h« Ç°(wµÉ s É#NíãKcôïêL£f¬Jfl<Ló<w?$DJbu¯×¨R\\rýdq«nëÚ¨+6òa³|.Ó²,\\rr#-cÝP!ïC¢æ=(\\nòJëé¦y%©U5~)àüH£9jñ÷ø¢Çå1¼håfOæ~\\r*'sÎaÇ=*ð®x«úÇ\ú !Ú\\b0ÂüL~U¢ç45·y[õw=Q©ìÐ¦\ãTEóÇÖPW?k{Ék(æ¾ÏQQcu«²QÓj­Þ&ÚÓÄÝtôêï©õ\(©nXYn6R?[h°¬¿+`¯?vÉ÷[=ÓVzÇkqÈ¤ÒuìÚíñm·Aýæòd\~ÌtI8õ×Ùÿ<aÁ\ý¢¾Óðsë\\n¬D=hãNíwI?0¨ mÈ>Ö]½L{lpMë»ó£yT¯<¥É©nèfMÎ´ºäDÛNÃÁ\úåèÝ®Y;ÉØ Ü¦æ=ðuó#G96xÄøePáhòw¸~äRq;j00RÍ5øqÈp\\fÊ\\bÒwo½sÚ~áU\\b¡¾í)0i9ÀëÏSmÂ9Àá±3óµsåo¡ pkª¾ \\rÛAW¹"X4÷õLcgçe\\f»rßÇ$s~r=LJO{ÊÔÛIøÁ÷hK×&(cáCX÷£  Ð¼_ \\fQVÄ>®ëuf\\bÿ1ÀPR]_¸\\n³l[@¶h¸»ûP\\fqA×n_@iÚÿì³OÖæ©oz2oµK@Y['\\t÷¿å·ØÝf4Ûg,$¶´ùÁ(ríÜ²À¢ïs)AÁòXám-<ÇâgÙ\\bÇ°dü´¸ÞNÇhÊ"õ üá Ð|X!ÝÎlíßcïáSÃªÙfôà¡ôÀ`îâbËÂXÛèÎ%Bd²$[6¡jù"pm½üÉåøzs*Ñ×,!äeGÄ'@ãÃ+ßHêÚ+XÜkInï-EQZim F?EÓ u³6*ºØ#È¿Ú.÷År(«åF5Ô?ZÐC½YN 7j8¤ïãÝ^Êû$mz|n)häPHWQç$ff5-~êÚ°çOìÑ÷>ó_/j¤|ª%]\\rêiHþRÜfü=xZÚl²ûíËøùäâbv)öyûÜ¡Ý>5KÊ,zÛZª£Î×°ÓIdß(Âû§^Üw*Æ±;^;~ÌÀGä¸Y¶m¥=á¬_­×2Ðäß>EqwGN±9Rº¡úôìñ _Ñè/PWú8ßYý$k/ZÎ× ýÎX«ìbîÙu 7§DdI0îtxàÒV¯ì¯³ã&è¦,ÐÉßæÃóOûòô\\t¨L}f¶z;u#åâîÏV_V"ÈêaB'K)ã\\f½¡\\r¿åÞqá1_é½í¦DoÉ=\/RG>M:4ÑXCù§«±¼/*HêhsñJÔwç­Ä9@8£³ÉN¶EþÜ·nFC¥1I¨\\n=ÃTÓÿv!W$|ßX42çÌM0e÷6ÐH\\nR\\b7M?új©CL¯ðÐ ¡:X¥tLm$£©T£äàñQz}2ûÂø=^p§ê\\bPêQÈ³HçÌì÷­½h$$,l¦Yfedô_·µ%þR}ÿ¦å¿«ÖðX0MË$RÚ)n»â?W3)lØ{÷és²·ôpð¥ó8v)Ú,J;B¬¿Ã¼âøþÛæÐÐÇ«òÀW{QÂíÊ2ÔTþä#ÿ«súü*yö9F+´1Ù¯ù2_fÝì{½7e»1òð"æÏ¸V²ðl\\b³9~WÌËb2.ëçÞÿáã\\terqr-êáuJ/øAÅ9\\bPOtü"ÔºÆOÝÊ§T¯Ø+Û±î.»,²¯D4j.v«]À3³\\f¾¦ÁSâpÞM~ÒE´zùUcqËN7¤¸MÂÖ "Üÿ{wõ±Þ(yÓmm{çç´ÈoõR¡\Ö-Ï±:@â¶\\fÑÚ×g©JöúËWÄÅåáÏ7ªç4±èS+½Ã¶n÷§PêdRé[öQ!wE\\tìú:Z3¹¹s¨¯$Oû@rBô znsþsÑÍµÆMÄÅyÑ#¿lÚj¶(<ô`öö©3äqA1­j"ÆgüÎåõDïlÖí·«yDqô«ñþñãÓ^H$­`FE°õ±V¹ÁyÁþÏ\\tbøºÇP å*JT#°c-YhiUú<íè:ÂÖ±æ\ìy§¦\\b]D8NÎÉøÆ³°\(òÀØ.he²+ÈÐuû½®ïÛa@ÕINÎBZå»Ì³é\\fÄ¦4Ù5ðy!ô¥P}pPñð>ÓÁ0¢|Må{æ¨^×:\\fð=iÑçålB­jróÀ)à:w<*5Ö§¤\\rcX)V(Dºq@··:·LâÎ_ZTOÉ.Nâ\\t\ûäÎ1ÍèsPóSYJÔ9Ém\\f8¡m@ÅÉÈB ø"º|£)\\r,×½>1{K|Q®LiZia ¢Ð~ûÔò'âä.È{Õ±\\r}o_ý®´°RÃ\>jH÷lÈ\\bTß&ªk²é*èôí¨F¼9ÍWÁ)$­R)Vv)«.²ÁÚ{pÇïIlñÏåÎ\QkfÿuÅ.ûIëÚ`ú>Äo!ýlE/ÚaB{Í0Ò#7°BÜÉZ¯±vGzáv2xÎQÃ»\\f!ïË'{¿ÁBZÍ}þDy&A7yw¹Eèc>Øãm3¶vÐÞ/cÆºìÆ4çús¹Ê¾|kZ"¬aeè°ZY8xb6òlá§~ËöAyMXgâãa]¡)á¢CÙ()Ë£@C¡âÂßQ åô¸\\bV^ð;^o´ÕÌü¶³áää&k©î$ãøÎItç¦ïc913Ïo¼B}.iêÞ¡P·ÆMmPÑ!ÅN.¯@Fd»ÐÙ¯æë³¢±vw¡K`ÿÇ­J/\\n01EkÕL>6ñ!èÆ!òwÕP+9ípÿ]òÊòjW¬=MïÛ¢ùªO\\f'iCÔp¶:tüof!»{^ l¢R¥¼iúH¾6Zø¤Ûkô²<ÏbXèÊ¼¼3ÑNÉ¤¯²¾Â%ã²Ý½ælÞ]¹W÷\\foùSyØ ^­ t j¤{Âµª¥îúLõ¶,oÝ\\tÁdÙÆqÊ¹ÅUÎ­¤NÍä8©1Àq8áVä½0l Þ$Pß©2ã¿ ÷Â!«?¿±k ÇÙl£UT^øèrÏ.´/1IA"Õ?5`hîÍ?,J´Üf¡2TRåUÃ\\n½Òà k4÷+»'sÌøaåjÈ5uñ'\\ts¬ÏF%3Ø\ñ×°qÆPþÄÆuzM¹.7Æê3}öÚ»>=»hóTfa»L©Ü\\r¼sTÞ?¼7ÀºEM÷»}û\\bNvT,qÆ[ÌºD~÷Çéªï}6M«1QÕ;©´L)ÍwXMíkÁ,Öñ÷ÞMª¥HîäJ7Ù'ÅÚ1è Çe ~zR²<e0·p2S$BDOS=«eÆÕ%K;%¾?¨ò=´ÈÛ@&ö'Ìjû¦Ê¼ã$úJ$`;X÷À «¢C¥ÅPÂ2§Øù\\fÇ//1L-Fàð1Ð% i&LÞÏ>E/`»£¨ðj~øp2;×Ô×dß«3<UýñÌ!ÚYÒ©ÏÇÌ½pJxµ÷KJ!$Ê¬Æ¹µ\\ngL¬bÓÓE:¯aÜýnLÉÇ2Áêºº|ìÝè\\t!e\\t=ý÷ûôéòiyJ¸j«$DÿÉõÕ]Äw=ûëÔ²°Ì4ù³hæ;þèB ~Þ³]<«tqbKïG69Ùa Fâ-/ÀfcÎ0lë¯û\\tÍ¯Â¹O4<kÙ0ü³çb@:.ÿ~mÿ«³Öþ,L4qFoÁ:â-Ì\\bÉcgJm©hÓá¦@«ìÀþ%m§lAõ·âÌ0õ&ú´ÍìS½U<x÷ öÒ´&hïc:Ð¾ðàÞñ\\fqâKâª:­×CºEÂ£íP*3GÎR&^Ú¬\\fµ1Cnåàô/\\fç²kU5ÍénÃÁj-«SêS_ªgH½ÖL|XÈõ\\tbm6&:IÌz"ÂÄùWòÐh$®Þ\\nÜ´'|y»6P-[ÅE\\bÛuvW¦*AÓ&/Æ÷Ì÷Q§¯<-y'i=v¾¨xÙÀ#6eÓð~M\Ð#·¾7ï<VÒñÓûbêøfIl·`é@ÅwÞ |e­pZm+4IT q÷ :`BGÐ¢Ãra Îÿ ÛÚÕìkÉâSÇMòÈ[Íl ÇµL¡Oí2Û´+è:\\n¹ë³/ìYM_&Å4¦{{tÿ<xÑY¿zSN¿R81H&âÀÎàÇ>cÆçP£76nsí{Î¢!×4XÉÓ°ä$e¬:ªx²üÍ_3c|Z|ªýÒÐ _oþHêçÃgÛßëÖú\\n\\fïa\ÎNzðÁFu46Ï>§µÖ0 ³"ËF)}PØ\;y'ÀEöWñíùæaLýL1«^¨ðJÇW_(Æ´,Â¯Íç÷J5bF#cshÅÏ2t=ãzó(0ÆÐµæ\\rîu4x(\\f_8Ð\\bASýÌûÈ;À(îAGmsÿ2åÙ¯|Õr¼ÂtèìC¼øØûãÌt@ròé¾/jà&Óúççº^+0ßá£8gõ+«/?¾ÏþHæ~)rSÌÛn\\fg¼2?&\\tBcô¾#ÃSo{\\n|a]Eñ¶>>­;à2¿0ÞèsnÞíü²NÉá9©j·¹D¹+¦ÇB4Ê4Î!þT\\n£\:*¾ËÏü`ao¾Oé¬×«´\\fðÜßSh®¸\\b"\\t]lW/ëÝ¬ß¿èpRÔî¡­ÍxÚñbñ¼ë­©À¾Êµ¡@ßñ1ªÙL±T¼+r){¯ª|nRégÙ!U_=îÍ<ß´}QÐÐ.è5-ò½Ýc÷nÿ3EÙ\âús3­IÄÓjP7­ò§ööèq³!\\r¸©f@ÜôÙ~Ù8"Æºë%ÿ]ºÅ@S ¦ÕwæÄÒÌÁk¬Ø(:­zö=TóìiLaØzÙßº&ÌÅ´'`Ð1©L§\\t.Ê~ÄKøÏª!8'Ù3·Ä>bÈ(¼P(£CëÛC{4kï:31xÆÁ3þCÝêø©3Â1AX@(ÿg($¯\\n£É¥0ØèTM ÁÊJBá¸ùèXKíùAJÊö«F=^X§ýªa\\b²`F/MÚ·Ç«ýþsÿn/TÁD5[pià\\n'öÛk3kã¥/A15n(`7ýAíõ­å¶ÆjlßAïûó6lÊ<¬LÉ÷dZy8r)©Ì5n¨7Æñ¨·]~·@@²ß&Z¸ë:2³®^H¯ñ¬Ú÷k»\\t~:c(º£í\ÀÕ´+J^­k¡Þù\ËÒþÇ¬¿UËAÿ£º­~ ø.ªµ¯ìõ½lôJ5ÔuèWg]é3Cj"ÖXa½£C#5Sàc¶¿ã©±¸U/M=úgkÍ¿<¥hCüQÐÅöù®G'Ù0Q×+aAºpV¼Þy²4xcwÒ©ûPòÛe\\fyðBYÊ"e%±f¸3°wY¬ö6=Å34ÿyIrXàÛ¶ô+æB±\\fPªÍëÅ¾£úµñÎÃÕb"xSº­kÉüÀ«ÌEM©èÜ´CMÊ4bX^j{2rÈº|-Ý#¦XaÈLº¾Ã9mÆ«åÆ5ãxx×Èpº\\nÐAúm7©Ê¢ç#wW}ëë¡'¦\\t°r»¬è6{¨\\rëQÈÚ²oOolÕõ?ºÉ\\f/¡nP¨¤7¿ýësNûF/çÅâè×Õcgïìl__\\tÛ|ú(ù.9m\\f¶²°¸FÃÄ&"»ä'QïdÏ Ô\\nDª¾BÇ¶³¤x÷_µ<g~öØbÓKI _¦.$¸2\\bçvà7Û`wsâx©7ß\\rmØð(¥ëË¥×ñ WÕÇcjÊ­;ßïÁ\k1I+Ú+}ÐIÖûÊ¾úç%äÞS[©ÍÌn9h5å«$Âë¦ ®z¦EXÍàÇ\ÌÍ²Í*ºñ\HÈéu^ßjc×mõ",\\t¦dÞØ1ðëYì$Ô5q±Í±n/®J<_nI´EhTxî±6·uû_ m¶Vwø;¸ç\\f½ÔêgôÎ@0ÁÓuµ5Þi;ðù¢x§\,¡<Ô=s@2ö0è:¢±k³ëôdúm¿îû¬±L¨p1ÄAC¬ÿT{ùm¯¸k«TSt@Ïuïhñ=\\bäë-¯ÂçE"4ã^p¨%$Ôn`²`ÒÀ ëç´¬ae Û·jCs Øn=wÿåT÷\ÈµKnù\\nö2AÉ9îçÜàüõe|6Ê\\tªçõd\\r"x^»úOö5OÜò¸!Açá^¿ØqóV·¡ÒÀùfÿfÖÔÍæwwyâPÒyù%ä».Ù¶ÁÏÏÑCñèÒÈ>cÁà¯lÙmü×ãð\\r\\nÏïXçëNÐ0ÝÇù°;¿ýóptÛØYÄoÜÊãÎK¤]¶¦2ô)â6QëÄáatù9û­ê×©g,Ç|ä,z±ì2H;=ówba3@^[º\\n[wýªZQRJÈ(ïòÃt,To-#oÀ±»/7Ò÷bvÓMCO´*Ô§Í\\n[í-aÍdèT\)©\\th~wýîLØ®úÃ¡zï\5¡MN¶@qÔöðÕ¬¨>&·U³h¾"ûÀÿ\\fvR =À¯¶ù\\fåb£\\n>=ìYÝ&Ñ7ÑØàäN$¶Y2-q{÷ð¤ËÀT%Ús@R3îWüEfþg¡Ö¡8¢ö­QI.'­&ÍSOçsÔ@»¯ý6+=eÎÒ~%ÿ)&õu5c:ÌbétA~øaTY³\Ê,çdônµ6Qr%¯ç?6JÕ7ú»¹ïUg#2S¾µ\\fþ1¿þUVM¨3¥Ö8ë@<ê´ôÂÚ:eëúÝö«sØ@bxì'~AäüLQ½)9RÕcØ^¼ÒIÆð®1Î²%ÃÇ$¥ëÁ2qsÄ'K ØJk¤AÏ«ÑXïùÒÕ´\\b'um_äe(áhÛðµvo.¬çÂÙòIéªö)([ÿ£0®[\\r\\nãµúñ&Îzq¢z~I\ì#£ìÝ©õ08:ö\\t\\rì\\t¬=Lt¨úkðzo¸zºú^¹ý®Mê¾ù(Ç«4³ÅUÚY"$\û\\n$ÞââgçÅçyL=,F¹U\\nu×¨ùÍãÀj%­^½¼6^6e\\rV°Wv5áZq:M_þÝË¡µìX`é/9utæãá­1õÍø&ÿûV>¡1ý7ÒÁòRýùæè{¡xæñ9B8á>rÖü<xÙXÌçáY1þ[à|8DêsT`ÒíÌaî \\bÃªÙÊ-;DÒg4|o:ñÁ"?rÆQf«¸Â«¬ÃMX¾[-7Y'iXÏÄZ÷ÚUíú}?¡NZNr=¸èq(5Ïc¤§`«qµõ¨ËÒ£(0©"²\\r.\rÊg¶ÉâÃÏôb³&ûëì haëªzæÁìp1+8§(?6}hhÁ\Ùô%zcI!\xòöK<{æ80¬ÍÈµè3äJÓr¬­zí»þý°Á<k#qEsÐ6ÛX¤mÈ0àGNü\\nCãVÀØÊôxP^½³n|éÒ¹S¿èÓËÝ\\fÆ^kk¡O(yç[Éí¦ÀÐÖ)X¼à÷ft_[X×U/¥zs³lùújõ^MæuÙ·ÝA¶.gÏ°ï¯~×Ó¹Å¡DüÛ¹f×Õf(á1Ç ½tz~9ïtÑ±Ýþú díHJ :/22Ã\\bN\\fü)Ì9#ÿ\\tëþ¶¬XÒØC«I4ùÿí¼1nATý}÷¼)WuÔëo{T«J0½8É"ÇôFÖ«¿rñAº2ÁÍÄø\t«qZ¿yÒ®ut$\\nmNûå%(àHZóÌ¤'Ëzð{é¨ü|ÆÒ¼ÀEEÄ¿êã®J×#\\b°½Ã¼9\\n\\rÞ_Bdì±ÛêtöuV}hq¼¦T" &ïããêÚ³Ý\1Ü¢þ¾<'.YÒ§Óë?Ò~a7A¤S¶DySF1Ô$Å\áO-ÐFìßßrp¢Á:¦ýcô²bBN'Û-TÆ¶c *¥B[³wÚX©ÍC]øÛ\\bâòí|#æ$Òéw&¦èÙ£+ù¢ ,h~TRíTfÞ.¡9{Ú¹ÍÙú\\bÛm{#B¡ÂÔ]jÖÒw¨!ªÇèçkJesIßÕbíUbÔÒRKÉ`Âî}\\fì+HÄÕ$ÏZ+"º+C{¸,éw¨^ÂGj.Á&íÑzaaà¦ÈàOð4ÕG=ú¨ë.7BÁ*g|EQºÀØ\\ng% ÀÃ»åGmÑPlwI»£Ó¼O«¾g1Sê*VTèÒifÔEÈZóæéïDxñ ã}ºV¥\\np@¬ºÛ4 ÞomyN4r¨OÚÇ¼»Rùùõ:áô\\rÎ³]§2}vDÊ«`ª»<ÁÜí\\t8¡Ôá#\\bKý\\fu\\r½6©¾¸cBOè¼îE<ZOù¸y<¯ÛåÎE9øþ?µ<§UÆýAÍ U¹õ)[ã%}çrÛ@ëá¹>ÓºÍïK¼_à|Àª<Éä§ISnå$§\\b¹oÚÀðÓôËø¶\\rá9f8þü"#º"¥ôüN)b\bd\\t&Ó!ÔkfÒÿN[VXº/Irt·~=B/*¾Nri|ïü¡l¢@[AÌÝ0ädfv¹êêýn%ªUá*÷ùÝpúân@ÞRIK¯W=f½zÃ5[.~d#8¼M\\bUà­Hº®©ýtÚa$3Ý47Ä-Ì?½Ïõeeh¸ñ\\tãÉð\\ríKxÐCBt^øEÅª·¨\\bUwÞ[­\\tÙ\\rÉÕ\Ç2þ8'êUnWc>O¥ÊåBrw\\\b4ÍÆ²É[¤¨ÒócçÔ\\n\\rr¨×f÷¶L(É",ZV²8Ã6ÞÖôÅ9çùnðåýåF¼æüÜ½¾di\\bÃj©\\r¨µ³ÂªÄ%C6ËI¾cûû|Uî¬?MI{Î.P[e½bÓvW ¸µ0´zËoÀëÆ?¾lÍr¢J'LGÏsBFà)UãäwÞ+}¦ù°@ìÄÕZïzi5ú}þHK~Üs·³63?æ1^Wh¸@°öR«ë¦tæûÖó©°y\\r÷ü`äö¥³XÁ£¥÷ðP¢ÆÅÑ6\\bGOªû²yÝ\\nü×^¼!Vs2GÖ¬EmÅÙèzÈ£>ÔëlÃ²|æëE\\rhÓHúòõUßß!>£¸eKáô7]÷ÆÕóIÇ¹8¾È]¨ßK:L¿.Ä Qh]`~¶Ö0 ÷!5GbÂ¦r~\\nÖ_åNQûR/zõgX{Ø®'ÈwèuË¢'nü]¬il%É¹¯_B2_5ÀãÉtÀÁàVcÕå\\fc¢þpyßb\\n$«ù$x@°·ÏW&BÜö|ý^Þ{ï÷©¥çÆëèÄä7Ãì1úàÉ­59_[¢c~qµ¸ÀV#i'ÕÊÇQ7°dÜ¸·Q6Ë_4 (~xÁd_JkMãöË-!8++2ë«rO¿Äß_hÀùq¬Æ¯OH\\\nÈ.ãæÞi°Þû¤$R¥écLì_,øÁÜúmß¤$q=ÜÕ\©ÛPÆÙiýã»Qýo\\bJcöóN­`LñÍyÊæêÖmkÄ90ÿ9¼ôî¼O7yB·jvþ`&}ßyFóRN$=;7s#®ñmØÜc2üÈ~IÞ¶øX|ªbå;øºtÉgvE$w\üÀ}"]su¿wâ\\f³"\\ryôï?ülåõôÆ³æeØÐú·¶ã9°Cx8RÕ\\fc1»ñÿ(Ê¾Îÿ8Kà\\fªYëª^¯&:NÙxËr¾(<åôÿ,Q ü(acwpÜÂXø²´mWçEN÷f¢ÅÜ1a{\\bÞüA©á*/¯Éæx"6­%¬ªJ³Vå{/­ ÿÚ?ÚÌm§><iØä³:±"WGÔõê]t"Ê'&´Ïmß£ÆHXÎ&ÏÏW`ïr mSì_Êrº§Î[Äm\\ntG¹+¿_EÔ*Ð«FL#õ£7üÒåó\×&ë^EÇ9ÁGlØA3«á&tÅrÕúS|_&¸°½Â1ypO¦oì'0»n ab©¢T/sY¼\\bcpHÖ@\\b#£\\nÎqAsã¤ÍüÍ¸xr»³ÚgpÛ×\d7s+cNÃ¤ÉùÒQªº+|&\\n2\\nyKã¹Äì|k°[\\f/Å"(POÅ^»2i@sÉ¸;Y¯É¾ÿ!}¡}VÀAÄUØ=\\fâ%shßg·hLÁ¶#t_¤Üâ¨¢{AX~\\n»àÙíRÍåÉd©]þjU«­­O@67<VÀxX¯"<¸ôóH©;ÝÂ\\nJÑ¨JÄeZ.Ç\\rÉùÅI¸K«DêÿæÈËZÝ#°å¡~2Èmíö®¥M-AA¤úWs\\r©]ö,ÚdÏQ8äé)^6²½C°ãÿZÈ®ÃÌù"KÃ'äEÃcë(¬xÖ£I¢IÅc<4\\nèiÈ]\\n:/Gü²úw¸õáßäm¬D©Q·.^s LÍr}«²pr¼á0¸¯Gm¶I\ÅìJ}oéÆAÒËeüàDæ)2èþXî!-7^»Yg¥_ûc@þúÜÊsìfi9÷ø©ªU $Ý=½­-ÇBL÷²êðßÞNM¯.°Z´zbX^Ufb¹`Í»?0}þV#×tt§äâ}9>å.D²ÂBÏoà÷Îï9ÅÌÜ~äçìq±Ø³BÅò¿ymÎtéïP?Ê¹Îö¡6W°®Ë$` ö¹}±j@r8k>ýzû¤6Y¼ ÑZgµü3²ÑØæÁ¹IÌÇ]KóÊÓ;qÁKÝ¾üöù7HlÒcÉÙr;d¯\GÒq»ãóÜ·®kÖØbé¿Òkw5®\\tÆ"¤ }svUÕîVµ6ýïMõ)Å¯4Ä *YV-Ô|Ð¼QÎO3¿`È>ÿÝ¸ûûjý3ìl¥õõe2ºªÕ ÅKeÊà2 ÄFÑ\\t*ðlíö!ÖPIêöL×k¶®¦rý^Ââ\\frøÔmKi¯Ò¤\\fô\\fÝ/ÂIw±Pot@ó½aZO1=ZÊ³sÿÊq!¬? Ö\\bÆòÿkXY\\t4dÞmÆ3!«ÕÃ\\nç¢\é&7y5Ôt5ñD;RÀÉ8¨yã|¤¼ÒËÜ¼ì¯Ø8û%ÈéfÏÒôÏ¸dæÂîW{6Ò=üí¹±nN´-×´ÂÇì{¾¬wå^®áuÀæJ\\bé\\r=&üpPg7²QÞù¥e¡FrwõÐgqÜ4¡À0oz;;§Å§='ÓaÕ\\b²ÇAw:Eçìk(%åØçâ,Ìï^TA¹Ù_¹ÜÏê¥#emFÌ¶cg+dÍÇÚsõ¼}õ×QR÷¥¿ó'g=ÎA °Ò h³²\\f¬bh7lÇ^D0áÕ6í@?vM#ì3³6½ÉFó795N\\bQßrR\¸bæCÜ j[_°ìg_Já¤C#¼cÿÂZòø9\xHF©±n0ÃGÊÑXç ½$62:e©\\bá'>^¥<&\JAN2#Êç1=â7F*¥DAÀÇÓÑÊ8²®¢ê¨&t®á7A¥7·Iü:õjâÉ*­L$Y>órÝ^ô=/Ç:¼·L¥úm${Á]¯pãy¦·VV¯r¹ZKTÇý¼1eJÏ\\rùfc·]rü®neèqs»d¤+ÙÄgãÓ9rêK/¹(m¶é[ËétÇ)ûÅá/ÐÇq"%!rÚîx,Nlõß¥ãÔ)Ìù!ÁõyfÐTÚ_Æu¶µ .éåÃ7ê;ÖÜô\\fdüÆÚ/.×¤ðÚã­"~ÏÌ!ã.\¦ë¡²Í4æEøô»Äº {3µø¿±ÂNÒ´°Mfç¯D'};oóÄdÒsÞý5AË\ÅtGsîFNÄ9Üa\\fø¯rO¾Ì}­ôOèüû¨\\tÙRìÚþ0ù3äÏþ÷H,âHÆw\\tcµ§»ßH'èEk*ÄØØ§ Jª£ýÅPc&ü êðÛ-Kò±\\nóÌú¡·(YÕEkËy}·,@8ý¼³TîZÛË@Åláà0 ~[Aè.géðØÈ}ê¶Ç\vaL-JÐ±õ/¿Yø\\fGôGIÝtDv\\nóÂ¸Ó}IZÌ/\\t½µkú|æíÔw+"eQo®K×>Swôâ#¸ú>NÖD½À9ñ8~Õ?ÛpØ¼FiÚßP@À+Ï«,2[fÀ1ñP>\\bÆAú\<¯(5\\t¡{AÅÛ-üÑ%Ãæbº´÷ªï©ð0-ó¥v$î¤«·F.UBw«¸{d·0¤Z§oø\Ô(}D.½\\b Þë7ð\\f11¦ËoA!Â¨-±LFl§\\bºàrËh\êí^Nÿ`LéÏÓ,rö$G36<Jdö ?¶"2` ¨N¶{U6\\n[Þ\\fP.£¡ØÜ¬Ü=ö¤Q/Ôtâ`N5!\\bÚ,[B'lÏAÛ.ïÜWàì\\r¶¦! Ö¼N*Þ©\\b[]]LrØ4qü=îã;øLÿàDÉöxJZÛkVÜó§÷îNÇ7£q­46(zÃÅ `3Ìê\sæMìî¥)öVjé~gòé.i¦~?§(Ó\\r¢`I¸È*ÖÍ8 DWËÙo½og²ÇÑ4iÕ`Áa\¥Öã)ÅJdM}9 ½rîJÈütUf^xØ4+\\f\\b++¤¸\\n[ÅõÖ=Åo9>NLi£bzUÊÁþêOò}\E£Òüø¸ºiPÊ_ók» M;0½ëH01_øævg !&¶ï]öd¥=lgf[Ý{|5î_ÏBðäx/:±:sGîÏönäít$"$z÷ÀãÒ_ª\\nWÔþÿ&'¥ÉÖËËëéÕ"nÐZ©7îªÔÊ\\nNñz-ÆÐY\\ryÔzXvÐÕß³«Àdh2ðc¯_Dªn0ûø`¹îP~ídØ<n±O¾ÃO=S ÉK¯Ï¯øõµLJ}àæç/y#oôÏ¹y¿ä©s~4ñzxx®\\f\\n}Ï®\\f*\\nufy\\tD÷AõRÃ>íXÙåc~éò¸YÕÝvç#+Â·k5S<+\\f®äKÐuÀ¥k~-Ã?äD®32Ó|vÚÙNÁw»¹TµÍqLh\\nµ'¢jÁÏékào%¡\\f¾U]ýXD\\nNª\\r¯­å×ZÇ8)/Wÿ'ù@ù¦ÑüõZHÛdd\\r÷ì1ùkWQíáëëZCÛØ¬"»G¢Ù÷x ¬ã¶¤y [iÁ£ $Ogjj ¯üçúâ Ò }V§k¼»\\nq¾Ö¯üy'é£>¥,N´Y»2¯ò 6·[GÝ,á9¹ðZÃSçkÏÀÕ?Áº*v ÈÛöó³Zü½½-1YdI<Ë°ÅÈÍEUuO±xK¡äRîEÎP >Ð|(+&ÎmPfâ¨È~y×·giVySÊK¼>àÁ­E¾"£àGß8\\tØY ¨é§(Q·¤àÛl¯ã@ÁkgUÓ%ëäàFfà×ÏÎ`ÝjN ×Wñla=á±3ò£;©ÛÝÁåÉ/FEXÕ¶iØÉ(äÜK-RmÑä2¶[¬ý¹h26åDõfxNÅÁ5#Gý¥ôN÷8ÆÖ&Æâï|\\t0®<Äî8ËGrÍ=·]xV£¼ÀýpÒKÞ6|ÉY£9mI?(âçûMaoñ2fc¹áâÏ4=«ä*Â5Ù±~1ýV»ë~¡HÙLm±ÚCáÛ)1J·©\\n(S_E¥ì iÔÚ°lkÉ<r@&pâ¦jóám{6/ð¢Ï~¤XFq1õ\JÃetvÃìÆí.û]ðéE¦v÷FbÎ"×\\nè6:[ÓS©CÆÑªaéÖ¨M£mXéêÊÈóõZÁÑ±f2gfaåe*e.\\tV2Ãõ:t¬\\tZ&Ai®·d¬fÿF§@µ¥Õ#IèuæÓÎäN²»çK5øX+ÚÐHú3±§lAwèÚø'HqµÔnípLpöR¼Õ«Nä¿ý¤ñ®°/5]Zó«å\\fåûÄpúqÛÌÃn¿«Àz9©·5ÍR"j(÷dDKgÛ±É;ÍüßáTô(\\nÈéwÒ6C»¶ÔjTãpé¶;æ;Z\\rJ»B)éqWiÇ·0Ó¾ëÂT%¿¬ÔçÄ~¹TÌtßæË.£{¸XZÚHN#z-ê»å'ÄÍD@V¼ái=m\\nhäJÁ^g2ÔIEÙ$Ç÷ÆØ$of<lO ãº 0Å¶ ²·\3ÎXa,+!Áv!»¯$À?ýüR¹F´]v&%ºj8Gê¸ô8J½qQ£:¢þsQbÏºènÌ8KoßËÙÓÓÔvç7äLÜì$ÝûlüZ&áKân¦,26â@¯ÈZÎqÿø6V³Z]ÇÁÓö¶wÊ³SÀfenk³²ïXù·jÿIÈ¤|G^^Í©*¬ëcVcá®w¨³ÚHÚ½üÒèCëõ¢¡{XÔL]ý÷eLãÒ¶"_b{I¾ÔAþ*Ýí¨:cÇÂ&æÀß3ô¢$7áïcµ&ÕýÖGA<Abq\\fLó¨Èº`1½ÎÈ:õÄ9æWÅÀh\õøW½±C>Ò»L´`>_<{hüâUv|º*, È B]WÖ^*®9¯Ñjüt`*7Ê/|»H³/o@ã¾\\b3íÛ+/fjldn\\nÍndmè:N¨9½ÕZ=#?n8¿W[P¯a;`#çòa7U1SôàüF (ÿ.LÇßT6ê¹¼V¤»|q{ü{x±t@°ýö6uÀ3KVvÚÌÊ4·È·¤j6P¶òHE©®=ë¶îÙ@}áñ²è8ZaRhn\\r`xÇ¹ËÑ¹ô¼i»iFÎM6¬\\fóqêøy\\nvãÍfv§ödR9X \\bF·!Y<k]ª'QøètöS:i `¶ $9ø7Ú<,D]w]6{På ùÍmÚ·°kÎÀ1Ü¸£c\\tLªM@ÑîÔD¢{'ÄñÌlGë9>ËÄÐ\\b%Zn5JÑ6Ö*é¶lg7Qò$øWòï\<¼UåeÄèäÝ%jÇÿCîì²¤¨»oÀ³Ú%YÉ;» ]¼AJØÀÑgr{BIÝnVçHäÖ{EîÕM!¸.-ËÃD z>õtÜ\\b×Èú8 ³Åáþ¦YâXü¸ôéd#ØåÇ&êà9TÄ0ÂUÖSÿ µbÔM1Lôº=þUáá6HBM<X´4mD(\\n3Qs½¯Q-é`ÞlVî/t÷-ô]Ê?|r(<¶WaTçIo¢~Y=-4Îa×¥h;­}êîXºÅBñ²{Æ®³;ãj~ZÅy¶0 iô¼³;k»9ïÍ,ÂÎ¥úK¥)z6i·Gñ" îí«B¸]ésÄàäÉoIuS¶òßoX*Úg ¤ÿðùXliîì4|Ml"÷Y·ÍïùL¬i3Ä­+yAÊ[1-ÿ)ÇßjNÜx¬Z·>ª\\r]pY°Ó+xÞÂ¥vUyÅ$§gäDäåw~ªC¢GÄÕ\\t{Ðâ9g±Ê]äou«q§0dRÿ±°Ì\ÂÏ*9 ÑÙØ¹ÁÐýºL´xI¢ÉÖI0þÔ9T£å»¯rîÖ×¿@ùåkµ9$P²µ©>Ùª½X©;ßÍs±}d×Íð<J4Ëh°¼]Ú7þì )%D$¼Ìý¿\\rFYZbGý\\b ]]{Ô2MVùÍÖ\\taÃ1>×vx×Pv¢½ùÊCDd.F§7ÝoRÃ\\tî\\t[§-á%±+Ö¢=w ¨vÙ¹9öG kðaÏq¡huWâAÞðHÙÃ@?ä¾JêSxøÆcgíFd\\fÑìÿ6Ú.½5²È;kîÙRê]å-¨Ê½OKÅÕpÁÓ5û7éì÷ßIòwdlØCa¸(øßÃ1­V)Æ\\n"E¼p(¥^¹¨éD¢âuà1eú+´vá³ìÒd÷áÑ¹"RäÀèòëjª¤iJ¹H¦Óh/óts8X¬{o,}|ÙL×/µÙÔ|èkyS*²¼ÏþÖÝ ú> *§Î¦!;a_LÊºZn @§2`#t®5ñ`\\f@ÛÖ¶ÕôîT slvùÝNK-Å@ë×Ç1\\rÅI'çdé\\b\\t¬ËãÄ¡Ã³`$åEe:Ïü÷ÖÊ çf¯õFBEÄp¡C6ø³ñ!ìeÚpXÓlH;zÅî[\\bìNòúy¾¥ZS©ÂÇÝB¥òíTë÷,áÓÕXÕ¤ N"a÷u²´ÛÐpÄÿ#uð!cS#HÜ>=)Å4^`¾wfÑ \\nJíÇÍZ\\r:(Ð¥SyÎ½¨:O±}®äFò<í%Ø8ÑÈL´TJèÍ×A×þ\\bd;£ÏýD`§°zfGÐÿ¹\\ræG× >EØõáÃòò'^4V+¶÷Ût éPÅë\¹´CNH$uë+AB×àèÛóåüº¸.RiëLÆ¿C¼4¬E?®-OyR]cFÔîÁ*!}®å\\r×l¬î,kQEDê(®}¼È@ì®ÇiV\Ð~7,üOFKuM/mïçø?PåKÇ hnaÝÚû><¥% ')7±ì-¢ªlb¨ÂÄg=¤ÍÞMT¹J{ßåm¼(ýµü44\\f\`Pöº8èç>[\\tKd×¯ëW$çÙOÿÔÏ é¬g@Å}J&£C9k°Né:BS¬Óð¦}ëf¦WAÔý~ðøÄ\\fÊü\\tL&kÎÕHï®7fyExi^*Øy°wÊþ¥jJÍ9>[!fÉö?1ýxpøT\\bRßnpQ3D~Ïüü¸|ÊáìÝÏ!íiÏÖÂ\\n$ùÇlK¶¶ZÎ>Ý{dTcbà<éð3~ ¯\\boZ¸Á©HÕ~×º#zY;¯ËqÌï1ðC1Ðw]âÖ>h\\rñkÀöK×T¤1Mðæ´·\\flÌ×í"ü¥¤4jºaàÖ@P:t"{â>¼^d(zz§0Ë½óôW«Ò`àaµ|ólYìÄ²ÅÆ^SÏWòw¸¤èï|%sgYMp\\rWµÚ{]§!P¦(!kò3«(tÌ"cyþ¢Ý®4?[¬ÙÿÅÁ§\\ræRµg± ÕÏ®ÔÇU'Ú{P¸p±|;1þ×x×Y½B\\t ýs;lÂqçoêêßeK¹Y¸óè??¶¢¢öò\\tjÂNþþÿÑuß"NmRÛKóC`þÖ×qÒí³NþÎKåp»Ü§ë)R¥!X¦·J´pgüº±&ý´?ýÃ£Éöþ|¡[åT|Ò\\bÙÇÏH\\rÞ|IÎ÷\\\f«\\b¶Ú.(0D3öêüY¥òò¨aí¨6ÜÄ.EÞ:¨z\\rñ>j}/YÁ,ÿhWë\\r½ê_¸¬PfùdøêÔþ&Ky\\rÞµV.ÍOß2QêH÷×&²ôS¾öÅÝ|oB\\f¿C/\\fyHÜRÐlªÔ¸ÿ[øÄ¼±ÿ:øqk²Éú¾f±¬ß9w+©'x·ñöØéÆ¡eÞ > owã\\rêí9 SW§\\bPJ'tno!¦áí\\nèíf®ú¶G®ÛPH\Á«uÞ`=Í)\\tCÏóÈW¸ÀuDWÁöOI1^ÕÎ2r5õ´û'!1i+&;§8iÞ;zìó W¢¥ïºhDDò ~â)º¬¡¾y!Ð÷Ì]ÕkQ¢hÓ¡þE¯jìmÇ\\fV:±³E%¥Ãi3'_Ýá6Ýû(øÏ è!wâùHt²äN5*®Ò¨¥3E¾WjªÐ\\f6Ê7\\rÄ6-W±RëÙ)GGNËÄYyÓÍÝàÇsº\\n®XÔÉÕ8^aÚV>Ô;û80¢ìT³¬:ÌÉmTj?í?pøv1ñàõêÊ;$zPº;3 LCÎÙ ¡ÙlÙöÉ»~¶Ï¥­Ëkqe>Ä¿±ÜåL\\fÊm3¤\\tÍ²Ùh{ÐÈªYîm*(sGpcHÎü¾¨eºË¹â@#Õ@©ECUÅØþÂÎ2³HG^! 'm\\bV,OöyðWÙP6ÌP0o¼|ÎeêBeqÕ6VÖ¯ÉÁ ø¤\\rI4¤ÔÂaH/Ôr´w¶òM§t5Á1Â[Éñ\D@ü÷TëY3)¿E"ÜÚ_¦§è8Í\\rk'òÑÊ+ [ß¡¢ûYÃjÛ§RI.*´k²ÌÍW1ÞP"gV?H*c9¹üf·«\\t\\rPvØcõÏÅQ­¤,oI\\bcÿbêVÛU¯Â¬~0j×OQ«Ê("ZzíùêJm/EÏh#HaýÙ¨çý)àÏ@®Ú8ù8ÙNã°Ö\\bÖ$l¦óövCZcsK"¸ßIù¦yÁ«¶uPTB\\tóå3`fi®\/j×9`ò`¤7Ìq¦UËØ\ñ\\t?â¤½9&ëxr(ÔÃÞ×\\fÏÜcBQËï£ÿCëâ©\\t×Wä[X¶|×6çÉÊòý8w¤eUbMßö¦ðnÄ}qCÃLªÀÏem\\tîùBù/?»ÊRèÙÌÈB\oa}ÖJ>_ÊYÜQF´^êÍ'¯ÌFDÑ.ÓôzÞ>^ãlú«EÁ[Ô\\nà)§°!WaêÀÓØ-UÖqäY;áHØ¨{)ÕÄ Ä_fé¤·õÁðãÏï!Þ9Â2AÒ·«ú)ítf¢Aß&Ø÷\\n÷|ø@Ç\¬5\\fÆ,Õ¯W\\n÷êAc÷ÀîJõf@ P¢ÃÁ;W+£ÉÔÑhÀ¶ÝO Ì?bøVÎX"óç¬U\\f#Ñíè¿±3àÂ6Ðá·ä2Ø\\bÏÙóßõHJ^v£Ô"yÕ¹6î?À'ýtñ~ãXäÈd-^JbÎèNÙ±Z\¼YÜà¢\ÚqxÎKg¢Qy[MkX±ÓK¼`?aÖ\\\r|sÆ ¤?z?7tVLHP°\\n¸·»K«ÿz7:8m¢Åê³ÒH½Èu10ß6\\fKt_¥Åé¬ÙX[Pè¤î¾]rW­è6+|!ó½)Øµ{)î¯à÷T~äþ{ Ô \\n×¿]ÜÝ·Öª¼I!&³m_1Ã*a Ø|R¯è=ÿ ZGJ/Ô0;©ÜX 7ãÛ¦þÜòéïé`b.Ø«%í¬=¿.S»io3q1¥Ï|,Ý¡l%DÂüC3R\\f\\nç¹´;ÿ²\\bÅr[Vi|;¥Ã\\fjxÇú,8Ç{òF»¸6=À2 N1öÆ:jêEòQSìâLLd\\nO4¡#9ý£·¾kØ­î«9¶Bwë`0´¯q;$wWa¹ÐÝ¥ëûpÐ+Ã6¨¯Èz¢±BTEÙ2[~µ©äÞ'9à5ËØVO`wdù¢ ÷üÐ4·\\fÞjÒô8yÌdg·Ë¶/P`gV ë¸ì{w÷4{pu}Ã1 @OþO¶Ý½p`-y´À§W}²åxzN«¹îF³}åyº'Û,ºð¼C´ý\\fÛ2ÀÆ,8Ù\\t¬®îË×4KtñpØádÉ`è4JqDôBEá©¢F$Üv¼tP?rÞÌ.]÷ÞÝF|ý1| ¤»W¬ëReBf%£yBó.¬a48\\n¶ñÍé{íe\\tlØCÈGêÞô/Þ'3boçóAÕ|dc\N:Ãq»=T9A¢ÇDºµE&./¢ét1ó2T×¢PX:wH¬À8$±ç.F(ßãê¤imZ8ÐtïÈåùL§K?RØ³É±sÎP2àçnAÆÕ¤Àt\\r`\\n@R2?©ÓyÃöÊ1~Ö]} ð)À\\nïÄÏ\\rìª+ ¥MwzcÝÐù2¼`V*¯þ­¢ß3ªlÌÑ}¬ÇÀ_\\f©dÇúY©¹Ý#Gmî¢F$ÅüVúÆÆÈVw>³*ãA2ÞåV\\t3¤Ò7JåÂBu%þÙ;À]ÊºÎÞH7ãÎ¢àÛàS­×rT;î%lúåC¨´ÊÔÈCZ1Ñ*ùþgá\\bÜf(y¸hÕn0\2Ä(U`h×ÝvW²N\\rìE's{¸Ö\\b¿u'\\b^6ïPF·zùï"r>]ÌÛlã½ô]`¯LaôE5ÚUf\\b}î»y»_q¦¡©çxã$Ü}imÇÃÂéñ÷yÝýQÚ\\tg4MXwQçjjRR\\fûV·ÍuÂ¢fÉ{(?àUYÈÃïØÃìÂáôU&÷6E%*q2®L;Ò.¤;»ºTHË¿û4µv?bF>3Úk|·6ÚÙ\\tÜlÎB)ÿ6§éäÔÊ7Rc2.zG2íís[¯åEÚFÀü`É[öÙ¬F:2r¾ã.ç^ñDHúj-ù±à ÑÝXLóÝw\\bÖRTrë8\\f»V¤ðVy¡ZÜ/æ%Aî±ÀèCÂÀ ¶¿jSÐKm4Q|Çø¥7fæ¿?ùï_²Úêwu´c6l66nUq0TBEÃò `¼ºÆSçt&kh5$¤×ùÌF¿{{N2¶¨(6SÒÒÉ¤EöýÌx!ÖÙGJPOÕõ<ìÞock_8^øÕCà<S"Dì\\f\\nÈµtq \\\n²Á¸@97ÂÀîî©»HjÝ¸sDÏ\ æÛ£ÍC`(¥¦®FÁAÏuD"¾ 647µîZ[óªæ\FJj8ýY_ÍAiUËTïË§:¯:a.£ûCÈ=½ö/ j¯6OzÁ#\ó¦(ÿK¬gûgwbÿbÕSsÁÞ«m»×ò,ìèÂ(Ñì\\n¶8RüB]¹ðhSæ{ÕÿOkÙCH¾-\Î b.Û?vZ«1¾R(aQ&dÆU¸Àw-*y\\bXr{RGâÚOMzs¿æÿåeÞÍM¤Í|Á,Ò¬çÞûÑÅèãX1«< Dip÷ì@Á§Àl\\tWáóÄ(o·ËSÆærÀ²Z¶8\\füpp¸(b(-¢¾hºÜpUl±ÜµcD¨MièÄøi`ëRôå%äbèF>qìáBæE¢?ð7UEk'
    //   11: dup
    //   12: astore_2
    //   13: invokevirtual length : ()I
    //   16: istore #4
    //   18: sipush #32767
    //   21: istore_1
    //   22: iconst_m1
    //   23: istore_0
    //   24: bipush #100
    //   26: iinc #0, 1
    //   29: aload_2
    //   30: iload_0
    //   31: dup
    //   32: iload_1
    //   33: iadd
    //   34: invokevirtual substring : (II)Ljava/lang/String;
    //   37: iconst_m1
    //   38: goto -> 144
    //   41: aload #5
    //   43: swap
    //   44: iload_3
    //   45: iinc #3, 1
    //   48: swap
    //   49: aastore
    //   50: iload_0
    //   51: iload_1
    //   52: iadd
    //   53: dup
    //   54: istore_0
    //   55: iload #4
    //   57: if_icmpge -> 69
    //   60: aload_2
    //   61: iload_0
    //   62: invokevirtual charAt : (I)C
    //   65: istore_1
    //   66: goto -> 24
    //   69: ldc 'PèÅ¦Nx\\tlBKìóÝ⋡s]°±Ì..òÎãBâBÚÝ]jäÑF5GgR®FVè¿:`Þì  lÜ)v6¦ïZZ<²ÄdúûÂG;¬qÏNC=×:w5¼$UvA£<LÆ÷i:$9¥ñÑN\\n6gÆ<x·pøëó>:\ß æô¹XÛçµá©¾`B~Äp²"¯å#ç©4H½¯Î£ÝæèN³\\rãíuÄUA6¾Ã\\rVE¨ÚXµ(¸&úo2\\tö%l$íâ #=1fîQaÓTÉÛëRîÃÈåÃÏÄ\3î/`6¢TN\×ñÆÒq->Êcz}ÚïËÚËÁÁPy,.Såráf+ÂÇäæ-M"2J¡wºwmÈ?>K ffø\\r¹Áûqð(¯¤F¼!X×5z~4ëíø¢Ö ÃæªÜgH,d¹ÄR"iðº¨L\ß¤\\b¦BÀõD·àATCî#Få+~rN\\ræã4I~ÚLE\\nö#³Ègëd«õó.OãXóµ{oòO0YêXßvVé]ßæPr½Õm*\\tÔhE@úFäqâÌÌ6AñU=£¥¦Çº¦ÕW±\s~·ªi+«ôW3öÂlgÞ\yQ¨Ì,ÄiÛÙÅsÔ4×G]jÝ½R$(ûDÝdxjr[»xµúËãvZCîÒú'¡ØÈâ@¤,ù¿§Ï8\\fðrÜå)f±©¢Ð{·)ÑsÞÂµa7R³)Ë&ÍtÅ¾­>üÃêÞ×ÐÎ»SÅÔCÄ!üÅ¥Dgüâ´lÚ%hÞcÍ\\tÓAª.è ^é\\fÜ ÐÏ)iAç¶-iº(N}ÝKtbÍ£ ·itÔprÀ3øXnÐ~>#A}µÑy3#<¨å¡Ti}øã\\t~ÓJ6 ø\\fbåóÙ²>Éî'mý:lºÏ/ÌfLRê jú¿gù÷QBðÊ¸ó°01Þ½eHYÁk\\r|\\t\\bìbLØg4²[°è­pt,0Õ}b¦èñÛh=Æº øcÜEþB ªDÆ*vË^®8ÞêðSûkRyôï§mÇT£MkhÉ¹&»Ì«¢SEåqMºCËK0®ÀÄæ¹r\\t~hyoãºØ=°®ª'7õ>»5yãÅ¤Yl¿À}iip@\¼nEÎ\k+÷û\\t{[m¬¿.°aó~\ R!Ö8Ñc®³i5äÂ§Ílàhà]¥7o×Kæôú,õG\\nj÷ÕfQ®Y\\fé@ß³X&é:>V¥(`¼øXtmh{(Oiá¢Ss.ÆCD­ßFtaÆ·éû¤£A;  P^þËÊe\yçhP(Ñ2þNLçN¼i°þãnf¨X (Qw9®{¸Å&Î½Çãº°ß-PÙõ%GNúºø"¬å ºåïÉ·CÔ·ZlÖ¤L»³Fc¼°.ÞBÄ)²OJöòC,zÞB¦n;F(ZSI_Öbu3¤ð4háí,Ñr½Nÿñ%DVNh"^ºHfÃÚ]ë_²­hdð³Kâ¨û(Zæø_ù³sÜ<H´SÃÛDLeª±Ã #ÆR¦­?¯cø®·'=6@»JêS ïÕ-±ÌàíKÄÊ­§?tÝ1ê(OLhÿ!yÉ,,"]KSWQÀÎé Ô¥ubÝ½*\\rÃszÍþT\üA¶Où[àöÒ`p`G£üÝñfé#nShæi&_Iq4Z*ñÍµÄ®òÝè9f=hÔ·9BöÉD«-øîlp÷5" |¼RÛÓb&Ôr3ØejÕ*£¬Ï{7d­ÉcGb!å2Gü$TÜUâðÙÙ($-ráªµZ*[g4Æ¥.ð1q\\fßÿZ8qã@~¶_¼¨½á$ÆN\\t2°¬ò¥êL14A¾Ä¶Ý_c1P\\fU Ó¶hJºjá÷jK§ÀBæaC[bÓCzv{|÷w!¶¦mÍ§1ÛF\\bÏsäÜ3V^åÞûîP32àºi Áï.\\nÆ?ÛpEãO4¹wgîaq@.IP\\bcµÐ5Ç*.°W,ºÝê(;Àòj¤}Ü®}öãøÃlþ@òYô´Ùê´ÂW1t±êÉÕ¢¾sTCçÃE}Ð9wV¥2þXÄen_eG$#­à}ú":)Ë5¸ÄPh´ ­7©\\rk3Æë\\nãwv%ðyÈHllÝ8CVÍA"¸©¤kVáîßG#T]üêTuf,op3ãói¥eÎ©Ëød7fDq\\b\\néYÈ)b R¹¬B~1Ó\\fO1(ÅU¶è£¾)P»@%©;3¼,¦KÓxLº{ÃÑåxÿDî·ÜgM)3­3 |pÛ6+Ú\\n¼õ\\r]>üÓ¸a¨q@ã'äXzMhAs\\n«Br,ÁÂ8ö£¥ÜüàÄcÙÊgQRÛ¸éº¥j*¨AÃpS+fèÄÛLF:xAÓ³®t;eC²ÊV:3xIÞÎú¾ì3ÔXåÙaª*~¯ïU¿5,4²8Ô?ç\\fTê¥/!@7ÐoÊànCUë9ôÏÈ³åTêøÿõ0µ>¶v{pÜ(&`X¯Tz1\\fgÏêßÞº(é¤gª1Ór_QªDñ+Î°çµalµ±uçl=a¬ÖÛX¨ü(.ÚmK¹b¿} kvVÖ¾|ËV^´)@/`iãÞFS'¹pºKU'btópi8JÁø!Î|ã$o÷6ÂcuÕÇÏKÿÒ\\tûKïÜx®¶$êÒÈ¡D±þoývyÃ¯6Ñ?ÃÜtÃêxÞnâÄBuû®ÜØ£z\6É\\fS_ @çF!¦êéJµI²ELÞÁP]ñE&øoìûé/­[Rî¢PíÉ¦\\n«y\\t£+zT(²ôC¶·KMCZN»W1ÿTÞ¡çs_,`ZÁ^wu0"=\\tÔ¾}åÀ¢£Ï°æ`f§wzsÈRçÇÏ®â_ËY$_.e¶npSiniï²EÊiD%»Á?,j[&z?;óKm´ãË·áó\\rëvÜÝO3KyN[|ö«Fo¢H_l®´éÌ£¯pb]ìò^\\f3÷*Â\¤½aêzX^í§\\bó³L\\tþ»Çè "g×Ïì4tÌgÜ\\rÖìQÙ"¦³8]rÂÀhª½k\\bsìTL´Có,ÿ4ÔæsÏìØ&vlTG·O%"ÏxÝ>ß,$=2*dléÄÜ`&½B¢Í·¢tpg{Ò=^ÛLìË8bÎ%yÈÖµuw<tx¶Â,û³e¾°Ø¬å\\tqÃ6½¡Üwíý4 gËàéóf ÍãÅ\ö+ëd\\ta¬x ´M*jßGò7þhëÚü¶ÏûZà²Ç8ø¡,k7~ò(mç^Ö1Ä=9î>´dÜT¿}òYó¬í`ýÙ{´:kL³'D°Kº¿Ø\\rpðéUcÅÔÉâ\\t5±jHXßòëÿG]ìvvD1ôÅJ ó(èZ³Ê`àÈ¿Uçc\èu55øW\\n\\f2ÎhG¯¨»×ç\VnÎMÕÌ\\fG(ÜÄJiM9ëûBf»­à]B^«Ìc¦ uZáìLt<2ÂQ¨Qª À)ð C'èö×ýä=¸$ýÞÙºû#íøíx>2BóÝ±õRLì=ü_xóÂ))ì-cUÆfFõÕ»,¨½QË7bt&4¨VÞæpÛîa»9ø½"1ó·=èîq w©³Ã rkxsÒA[aÑÒð^\Uîy%7jCbÌÂ½º±/u,hØ¤ Õ#Ï¦ªÎX¯ã'cñø³ VsuÓ¿½ªÒs´qLÀ8DqË0]ó8y7è»×£6&;A6Q@Û:ð\\n°Ò{-e\\n¢'jÁÛÌ.RÆíC¹¢4·bG$pÀegÎÍ4Q]´ãÝ{¬È"o8'ü%h-L9(à¿]zpþÄr&¦%t\\f*euH¤Xðv²âÒÄeM2Ç\\f§{ïðrþàx<ÚÐªd0\\n¢göRÀï ÝÙèçµ#Íh¯Ý8ÖÉ¯Ux*\\r¦W8lò d¯¿3Aì2!3RÓ½q¥Æ»v`h_ £±ÞC{ÕÊÐâ¢ûÕZ{§rW½\\nêA(¨µ±~.(¬0Þ¸â!·P_Å¸Ù(µóÓDÁ\\nOøEÇ"µ^\\t®2k½w^.HmÈzºíÍ7¶º¬ª¡o|Pì²ÀYpµÎöôP\\tÇ=³`VeSðäòÀ­=¤©SÿôÚ¦ð\\rÒ(ÁëÖþÍ@¨ßCøÖ;èAê ý1¤×fvÛüÒ!|Ô0(òôW´|ï%®ªí·sÒDÚÇå~`!\\njjªÜ0>¥ªJg´óï«ù7h:×cIÏÑ\\bd¸mëìòÂ¬\\ty¢áÒ/zÈ8a7Þá6ôrõåº4DÀ®.®Y>Ílý7$kÝÉ`®õz«Rk»ÓH«¿ídêÀÅb÷þôNY<9²%RÒ Ä¸7DòÌ¯¿¥6(ïTæ)àÑkÆöø:\gòÛR1ÏÑCùj0¬£D«xT_(©!¢Ú\Ê4÷ûÿÅ\\t¹y%\\n«©2AìwÉ2"[ÍðW×o±¯9Ãíõ_nt&­0%¦ZD\\tgÚU¦7#u)ìQy]³+¬:sÐZ³ï@OËyD\\f.9/±FÃA`ãhÞ¢.Z«¦é±Ø}Ò¾â!ïIevß¦¯®¡Ã3×ýá7m\\bÖo3ÐØ¾G@¦UÈGñX×ÐØtGõæ)×\\résÊr\\tC?mslâË!ÌÒ[ÐÙ§¬Ç\\b¾.79dqÉÅáÈ%Q¿NV\ Ø5NJì+NJù| +;àÈÖ%È¥Ôì¾áq õò(DhÛ¿è¹j^»,Ã²{½@@D\\r»°ýGÞIùËlÚ*>§d\T¦;³êúfJn\AØº¸H\\tl[(ÿÕ{)\\fá·<6ØU¿KÝe'Wæ[Ù&àw_[ú]d®å¦jü7Ô;cÉe[ØÑÔÆ§vb4%WÊ(Ú92à{½ü~µ<õF÷]\\bÁ§S"ù{ÿ²È]+Vßþmêôñ_¥²" ÒËÿùÈÏø;¢\\fíøckòøùFË!i¾#y]~]ÓfW"sÃÕX,«U°BA³¬JYÃ9\¼ÞvÓ²­äû<B v_ÑÆ­¿õÉsérÓÌ{äÅ:|CØ%1q°1«dÃy9E òÅ}Um  Hÿü´þEt\\nýëh[~ÄÑ Í1ÊÕ0#µz·ÿ±HÃlÁÃ'ÂÜ>ÔFU fóÐrÅ»-U®÷uÚ Áwu\\r}t,"ü­äBb`d¦\\bón'.YýöûßÙ6ãþË\¶XS6*`4´%2ç éïy½ ï%­ÛÇû+ÞènÑQ¼]@cY/`òå>ÉGYÅÚ½t\\tI®fB­QÀ4Æj3]c^\1£\\f=m5M6ßðb¾dpÚ¿N9çÑÙÐ´ÕnÐppcÜ:gèèC¢Î%7uÆ~5´I£m×?A\\fóBh½±\\r1,´·wc÷7åö©1&ÚÔm\\t?^ôTjÏ¬©-·´F{tÍúa6£¼1å»h°`¶[Ã¢\\t0ÄÙ¦_1íë\\bdBý>À¥÷ý\\fK_!Üx(%P½Ã©öñë=>m±frÁ!pÆ3,¡X(»Ñ¨ªÜK¦«k¢½ÁcöóÑ×W^ØdTíU¿ãcÝA_ÐÚÁþ»\\n¡+O¼ Vó+2Úqû½A`!p»{IBû8Ð+,3ñðUÕ(yöíteØ¼ÍÓÏùF6äÚH3&c¦EÇÐµ+ÇÛò;AÓî³º·~/[ù¸Á6üìeÔJ\÷¿Ã-«)Ù©¼<ÅÁ9OÕK¼f`-Rïpþ¦ä\\b¼vã:bà©e-­ÇCGañ óîzöA\\teÂ_½¡à­Ög0Jêû,²½»{ðWMüóÎê=©®ôg! \\tPÓ?]øKfqÁm<aþ/2®@õãX@Ñ²UwÃ±ÍOÂn\îk!üRH$êZí);¹ ²H-³(3ª<r¹]PâªCç\\nÏ»4KE®u ¹CÝ·¾]FÆ ],²HA@úGØS×NóèÈrV§!pVÀ\\b& Ê5£BCNróÖÇm[þÃß*voÇ¦ÇÓAü[üÃ~E~YÏÆIQçëäpx{Ý©<\\tËÑÏ-^9ëC_´i_$QàõMz©¯q:OÄ¾/àÙ<þv*êoÏ¦EëëÂªAî\HÏëPíã óÈ!L6£]m¾öÿB*Ñ\\nîÊÌÑ½¢Ê6»ÐÔs"{Üæ:å.¶©²Ì´éCuvò3'®iÞ\i¥¸»Õ÷7\\fäY`§Ly¦à6B1¤ÔfICâä¹çÀÞhÔË¿uo+­ôÎ;RÐç»ë?Õè§Yì@SIuö±¬¢Üå¹i6;R³/ëô¬û®Qá°@6É:¡ûè<O³êùk*-sÕðó\f`]¤YK©vI£¬Ô?÷ô^"ìwFþh)ðkm63Wâ·Òn18~b¿éÂÞÒäÜªø@Ûs²Àó²íÍ³\\nñ÷ïâ«å.\¹T)p¸KåõXò$âÈà5ïÆfy\\r@ãzbÕç÷ï¾¤ÍÁì¥²í%DÒ4bA]i¤M+ÑE¯'"x«£\\r5ã\\bõ\\nþÓ|]D|ÂCÊåNÈK!YM9¤ÆS§æN*üô2$Æ4keäFÁõ¡N6\\nl¾"q^<Á»ÕH²{-1ÅôçêÙÆ\\bµã¥¯Ðô½S¹çï^:áÅôÓùnÍ5o)×8|Û$+Ô(-¹½òp¤eº}¹zfÔ8\\fKÔä\\fVjÃ9Z~&dy½¿Ì%§9Ë¸B~³{¦×%Î{  J]ª¹Í>Ò²\\r):(h(ãu§¬Þ]MGeT¦Ýì-e\\nö`àp&ÁT§¦x«£5b®\\b½|M-- ÊO:ö^÷\\bñ_\3èô!@ÛË/'B;ª#¶üJ\¾Vüh)\\ræ©*OZ'R$ÔË»£ô¹¥~G½P\ñÙXö>ûo¯9ÄóîBD¼|Q|IvU|áU\\f\\fÜ}U÷g2úsãÀ\\r §í9ö;xSÉÃ.;U|ú±Q\\tÂÚZþÉ×Em*´²à$J0·Yä¤;|n-®ìJ¹'¬] ÆbÎv\\tå?×±wî_=dyEf¤I_k»ò1­î¾Ç²§æDG¹<ëºþ^wTSøxµ:t5b¡d§PIÞÅ¦-`J©ã[¸ñþe½Ï¹ïÖËÀâh'"#'¸¢ÆîË·l¨~wÆF9&ËB°iÞVòO[øúåÊ´a¹kÞm¯\\ffbmE£Ù\\bUÒ\\n\\f\\tH#9ÿwu]¦?sWNÚÑNÝùcxûûîUk\\bþÍ^s~ËJå\\nµ^^MTn±!0\\tôåP¿CBÏbÝM³zµ'\\fãËÔF&<ë»Þáz2õwÁÅãÞ²ëy!änáäÍ¶Wü°\\t`cÎI\\rÞbÛ8¯£/JgÇÀ-ÆïëâNK£KÏÒ0$RgjzÊQBÁnÎýhá¤ß]@´GS2TÁS¶ é_Ï,'&«8» iCkªå :%ÙÏ@¦éùÝ[¤´KN~ocìµppXW·H×o¹µ\\n²ýwß«}í-/ \\b\\fd³J8ÇÃ·c)jâ?©+Ûð3òu,¹o6¦VP;²3))íÄ.©¶5ò'quÂ'w7ÑÐÖ¸É­åÅ7¶z¸\\f/\\nFÎ>ÿ4Õ\\bAeø1}áì.ÙÈL×ÇÊÀ\\fã¥E«ÏH)KÄñrJfl[}J4"2Å\µmhé=ûñ+iïÜ'/WÑ&ÑÉ;xn\\n¹/nïlÅl¥ºÍÇnK©Q\\tRåÿv7WòQêªÄEg¢_U/÷£eJøÏûÛsKª &KØ¿n,L&{Èæj<@£Û3õÚÃ4!v«WP)ì²ï~\\tO]Z­}ÿKÔV7ñ+¸-cûÿGü¸`¿7¥xÈ|ËÀe>ª¡säÂwÚL'áer?$åýt`\åhÚÐö©:¯²Ñçl{Ãs¸vJSËBÛ' Å0ÖD9d¹Bple¡4³ÜÛ\\b&ïg+)¨NØVLA½°oò(^ÜSKâù¦t9Èü"U`É®8p¹hYÆC8»­0Í^jÜÞg`dx'Á\\b'»âµ¡PdGPÈ{XR9¡¼(÷w{~§ÞK0x,¾Îqß1*ÊuÝüüä¯O.Ò^ÏÍ]ü½ik®ÔYvØ;é[¢Ébb>É¯¶¿D`2ÆÔdN%ö\\t+9WÌkó:ú\\n1ß¬ïs÷Vðß©©âKPþÆ:?PÆðÝ`)Ëx¶¯4c~jGpùÓ5+ |#4ýKFGü×GèÊÍSPùÕXqê÷ÏÝ]ºWö0²a2¦[÷üýÑ'ibðaÅQ¦O`ÓD^»»ø3HÙ8d³±#ë»i1µÈ©Ä½+¤-öð{Ìa´[û.{wQç<HC !?3ÁE¬Ý8hµüGÏAJìÏ3bÉP Ülkø¦úX\qjÃí-|\Vðö*KÎTM³>AÞÀúÙ²SnsOËV¢ëJ ùÙ¯é¶"ÎBþ×ýãgé¿G1 f$É5\\b.\\rN»cuÓ¡m_ßùõc§ä:`T[¬¿&à ¤WkôAg*æ¯(xN¦ rÛ½!*H~]a" PÅ37RÉP}LP¡ÐLñFzLQ»Ý?õÕKÃ×ÌEî°&$ÃäR«ÎF'ÝN3ªTvGïÍÊnìO\\nL¶~=D¯²°CèÈw¸ìx^óI*õfßuQýqåÿ÷rè÷Ytî5µa¥àsEÅÔÓnX×[ÿ^×ê_.Õ±¶.ÒE4ÃZijiËj]Ã1úÎ\\fÝÃl.{õ]\ÁóÆL3×¡ì¤v6Qó­ÿ\\thIåoX3g$ã·Xy~o¬ óDïyÇ¢W\\rÄB°\'¿KÆz¹º4d0]He«â¿ ÝòW%C,Es3Tøíè7"8ê¸¬2~ðRÐ\ìöâ;Ä½PdÚ÷ðûáiIÜ {FU·úALNä@w$âøøÛ\\rb§V¶á2±x¹Î.3¹·-¸­U<£ÕÍ¬øH6ø£jä¥¿ÿ÷¹áuc&§b8=\\b%r`6¯ÐÈJ&_¦ã ×È@1yÐ×ìÛYØ5¹Xz«ïñiVVQW¹Ã0=°qZ£«°±ÚFarXâfwÅJôQ\\rÇ0ÖÆîôX\\nßÄy×Ý4V,\&!¹R{e8í:Ë«E:zûaÓgÈáí­Õ#\\r[ýÿõZM8,ÊjVA¼µù'ä?ZAs Ã¼0Bðµê¡ÿq¦êh©*óXKÆèìÿQ¹xå{ÏJü`{+\év³{.àßðè[Õé¨êIÙQ¬°få`aý>/ÐÃ?ºSU×6±Ë:´(×½­»uaæÚ]6ïA(;þ 2®/Óh\\f|\±î¿¤Àä£¶þ¼ÃÉá#)ªÓ(+/ùs¤w°4Òd-tVÂÚsø\\t'¾!nNùû´28ÃyN!¯ÐÕîïÊjNêRyÉ²ï uÞDnPvóSAÚveÞçsk¥C+¢qÚ}Î°¯*yçõæu¡Ûhö±îtGK'ü§ôâÖàÝ^ [ ¿G.Þ4oê^ÍFõN»ë°}3]wþ¾.v{92 ß,è_W\\n¡¹²\\b ðÀ8ðH3®|4bsÀo¾øûT(&ÝÌÒûä§®Â:zKífc#÷|6ný{ÆØ§ÛÂÑÝé\.ü~!¤;3LüÐ¹¾ÏÊðxæ Aë¦½W§ÕTÃKkµþt _Wä»ÛÑ}Æt£Z3#µ{3³øë;<ð¹-î¡×¥ã¼§Ègïx|ËH\\r]Y(´Ä©t Ë'iÿv÷>raLXQØÓð}\\tÞõ6uù&\\rhåFS´³Òô®jþYj=a¢Cm5O|¢\\f Qg½>¥¾÷ÜÁâÁý´W²øs!Èõ~ÒÔó­t|\\nè}jÍbUÓ;\\rm\\t¹zØ9Uu¾Ù|Eb÷¨\I7\\béaÕ®®Â¯Ísü"úÚ)B¶8iÜ\\t Å&°ÿiÜÎ0V¥vu¬³([¸EFSÓÕ'ï)Ò½æQZ¹ÑãÏY-8ÃºL´U Û Ù,NPYoªÎ_A4Î{¿±¢ºq?IlRòÈÈ|4FñP7Ú·dìy¸)ñHÔÝ~Õ¨kq¼ìB©1òÍÅ¥,FMÂaIÁuPnçÒ·üð¾ñZ]ÏÆõÅ/zmÏ_ÇÝ/pãàÇÅÝ)\\fÂ5õAæöÎç9}óyRq6õ¤ÚÙC}¨Ú¹Ò.ïl:ýï§zjÎ\\tË¶xrY¨MP4½bÌÁ!f¤|~^ºÀ9ÈÅíì¢x\\t-45^\\t<*óÕ\\rC]} Ô«_ Ü_'j÷íJ\\tjNâ|.ôÎ­ñæ eÉ\\tñ2ñý%BI[Ð «¦6ê*<zÒxr_Dà[YüCrÃ[`?\\rK-¬\\tÉjöözDX8'
    //   71: dup
    //   72: astore_2
    //   73: invokevirtual length : ()I
    //   76: istore #4
    //   78: bipush #9
    //   80: istore_1
    //   81: iconst_m1
    //   82: istore_0
    //   83: bipush #103
    //   85: iinc #0, 1
    //   88: aload_2
    //   89: iload_0
    //   90: dup
    //   91: iload_1
    //   92: iadd
    //   93: invokevirtual substring : (II)Ljava/lang/String;
    //   96: iconst_0
    //   97: goto -> 144
    //   100: aload #5
    //   102: swap
    //   103: iload_3
    //   104: iinc #3, 1
    //   107: swap
    //   108: aastore
    //   109: iload_0
    //   110: iload_1
    //   111: iadd
    //   112: dup
    //   113: istore_0
    //   114: iload #4
    //   116: if_icmpge -> 128
    //   119: aload_2
    //   120: iload_0
    //   121: invokevirtual charAt : (I)C
    //   124: istore_1
    //   125: goto -> 83
    //   128: aload #5
    //   130: putstatic burp/Zsxw.a : [Ljava/lang/String;
    //   133: bipush #10
    //   135: anewarray java/lang/String
    //   138: putstatic burp/Zsxw.b : [Ljava/lang/String;
    //   141: goto -> 300
    //   144: dup_x2
    //   145: pop
    //   146: invokevirtual toCharArray : ()[C
    //   149: dup_x1
    //   150: arraylength
    //   151: dup_x2
    //   152: pop
    //   153: iconst_0
    //   154: istore #6
    //   156: dup2_x1
    //   157: pop2
    //   158: dup_x2
    //   159: iconst_1
    //   160: if_icmpgt -> 260
    //   163: dup2
    //   164: swap
    //   165: iload #6
    //   167: dup2_x1
    //   168: caload
    //   169: swap
    //   170: iload #6
    //   172: bipush #7
    //   174: irem
    //   175: tableswitch default -> 242, 0 -> 212, 1 -> 217, 2 -> 222, 3 -> 227, 4 -> 232, 5 -> 237
    //   212: bipush #81
    //   214: goto -> 244
    //   217: bipush #15
    //   219: goto -> 244
    //   222: bipush #50
    //   224: goto -> 244
    //   227: bipush #122
    //   229: goto -> 244
    //   232: bipush #123
    //   234: goto -> 244
    //   237: bipush #122
    //   239: goto -> 244
    //   242: bipush #108
    //   244: ixor
    //   245: ixor
    //   246: i2c
    //   247: castore
    //   248: iinc #6, 1
    //   251: dup
    //   252: ifne -> 260
    //   255: dup2
    //   256: dup_x1
    //   257: goto -> 167
    //   260: dup2_x1
    //   261: pop2
    //   262: dup_x2
    //   263: iload #6
    //   265: if_icmpgt -> 163
    //   268: pop
    //   269: new java/lang/String
    //   272: dup_x1
    //   273: swap
    //   274: invokespecial <init> : ([C)V
    //   277: invokevirtual intern : ()Ljava/lang/String;
    //   280: swap
    //   281: pop
    //   282: swap
    //   283: tableswitch default -> 41, 0 -> 100
    //   300: sipush #-8854
    //   303: sipush #-7507
    //   306: invokestatic a : (II)Ljava/lang/String;
    //   309: putstatic burp/Zsxw.Zm : Ljava/lang/String;
    //   312: getstatic burp/Zsxw.Zm : Ljava/lang/String;
    //   315: sipush #-8855
    //   318: sipush #15960
    //   321: invokestatic a : (II)Ljava/lang/String;
    //   324: <illegal opcode> makeConcatWithConstants : (Ljava/lang/String;Ljava/lang/String;)Ljava/lang/String;
    //   329: putstatic burp/Zsxw.Zm : Ljava/lang/String;
    //   332: new java/math/BigInteger
    //   335: dup
    //   336: sipush #-8849
    //   339: sipush #-17233
    //   342: invokestatic a : (II)Ljava/lang/String;
    //   345: invokespecial <init> : (Ljava/lang/String;)V
    //   348: putstatic burp/Zsxw.ZL : Ljava/lang/Object;
    //   351: return
  }
  
  private static Throwable a(Throwable paramThrowable) {
    return paramThrowable;
  }
  
  private static String a(int paramInt1, int paramInt2) {
    int i = (paramInt1 ^ 0xFFFFDD6A) & 0xFFFF;
    if (b[i] == null) {
      char[] arrayOfChar = a[i].toCharArray();
      switch (arrayOfChar[0] & 0xFF) {
        case 0:
        
        case 1:
        
        case 2:
        
        case 3:
        
        case 4:
        
        case 5:
        
        case 6:
        
        case 7:
        
        case 8:
        
        case 9:
        
        case 10:
        
        case 11:
        
        case 12:
        
        case 13:
        
        case 14:
        
        case 15:
        
        case 16:
        
        case 17:
        
        case 18:
        
        case 19:
        
        case 20:
        
        case 21:
        
        case 22:
        
        case 23:
        
        case 24:
        
        case 25:
        
        case 26:
        
        case 27:
        
        case 28:
        
        case 29:
        
        case 30:
        
        case 31:
        
        case 32:
        
        case 33:
        
        case 34:
        
        case 35:
        
        case 36:
        
        case 37:
        
        case 38:
        
        case 39:
        
        case 40:
        
        case 41:
        
        case 42:
        
        case 43:
        
        case 44:
        
        case 45:
        
        case 46:
        
        case 47:
        
        case 48:
        
        case 49:
        
        case 50:
        
        case 51:
        
        case 52:
        
        case 53:
        
        case 54:
        
        case 55:
        
        case 56:
        
        case 57:
        
        case 58:
        
        case 59:
        
        case 60:
        
        case 61:
        
        case 62:
        
        case 63:
        
        case 64:
        
        case 65:
        
        case 66:
        
        case 67:
        
        case 68:
        
        case 69:
        
        case 70:
        
        case 71:
        
        case 72:
        
        case 73:
        
        case 74:
        
        case 75:
        
        case 76:
        
        case 77:
        
        case 78:
        
        case 79:
        
        case 80:
        
        case 81:
        
        case 82:
        
        case 83:
        
        case 84:
        
        case 85:
        
        case 86:
        
        case 87:
        
        case 88:
        
        case 89:
        
        case 90:
        
        case 91:
        
        case 92:
        
        case 93:
        
        case 94:
        
        case 95:
        
        case 96:
        
        case 97:
        
        case 98:
        
        case 99:
        
        case 100:
        
        case 101:
        
        case 102:
        
        case 103:
        
        case 104:
        
        case 105:
        
        case 106:
        
        case 107:
        
        case 108:
        
        case 109:
        
        case 110:
        
        case 111:
        
        case 112:
        
        case 113:
        
        case 114:
        
        case 115:
        
        case 116:
        
        case 117:
        
        case 118:
        
        case 119:
        
        case 120:
        
        case 121:
        
        case 122:
        
        case 123:
        
        case 124:
        
        case 125:
        
        case 126:
        
        case 127:
        
        case 128:
        
        case 129:
        
        case 130:
        
        case 131:
        
        case 132:
        
        case 133:
        
        case 134:
        
        case 135:
        
        case 136:
        
        case 137:
        
        case 138:
        
        case 139:
        
        case 140:
        
        case 141:
        
        case 142:
        
        case 143:
        
        case 144:
        
        case 145:
        
        case 146:
        
        case 147:
        
        case 148:
        
        case 149:
        
        case 150:
        
        case 151:
        
        case 152:
        
        case 153:
        
        case 154:
        
        case 155:
        
        case 156:
        
        case 157:
        
        case 158:
        
        case 159:
        
        case 160:
        
        case 161:
        
        case 162:
        
        case 163:
        
        case 164:
        
        case 165:
        
        case 166:
        
        case 167:
        
        case 168:
        
        case 169:
        
        case 170:
        
        case 171:
        
        case 172:
        
        case 173:
        
        case 174:
        
        case 175:
        
        case 176:
        
        case 177:
        
        case 178:
        
        case 179:
        
        case 180:
        
        case 181:
        
        case 182:
        
        case 183:
        
        case 184:
        
        case 185:
        
        case 186:
        
        case 187:
        
        case 188:
        
        case 189:
        
        case 190:
        
        case 191:
        
        case 192:
        
        case 193:
        
        case 194:
        
        case 195:
        
        case 196:
        
        case 197:
        
        case 198:
        
        case 199:
        
        case 200:
        
        case 201:
        
        case 202:
        
        case 203:
        
        case 204:
        
        case 205:
        
        case 206:
        
        case 207:
        
        case 208:
        
        case 209:
        
        case 210:
        
        case 211:
        
        case 212:
        
        case 213:
        
        case 214:
        
        case 215:
        
        case 216:
        
        case 217:
        
        case 218:
        
        case 219:
        
        case 220:
        
        case 221:
        
        case 222:
        
        case 223:
        
        case 224:
        
        case 225:
        
        case 226:
        
        case 227:
        
        case 228:
        
        case 229:
        
        case 230:
        
        case 231:
        
        case 232:
        
        case 233:
        
        case 234:
        
        case 235:
        
        case 236:
        
        case 237:
        
        case 238:
        
        case 239:
        
        case 240:
        
        case 241:
        
        case 242:
        
        case 243:
        
        case 244:
        
        case 245:
        
        case 246:
        
        case 247:
        
        case 248:
        
        case 249:
        
        case 250:
        
        case 251:
        
        case 252:
        
        case 253:
        
        case 254:
        
        default:
          break;
      } 
      char c = 'Á';
      int j = (paramInt2 & 0xFF) - c;
      if (j < 0)
        j += 256; 
      int k = ((paramInt2 & 0xFFFF) >>> 8) - c;
      if (k < 0)
        k += 256; 
      for (byte b = 0; b < arrayOfChar.length; b++) {
        int m = b % 2;
        if (m == 0) {
          arrayOfChar[b] = (char)(arrayOfChar[b] ^ j);
          j = ((j >>> 3 | j << 5) ^ arrayOfChar[b]) & 0xFF;
        } else {
          arrayOfChar[b] = (char)(arrayOfChar[b] ^ k);
          k = ((k >>> 3 | k << 5) ^ arrayOfChar[b]) & 0xFF;
        } 
      } 
      b[i] = (new String(arrayOfChar)).intern();
    } 
    return b[i];
  }
}


/* Location:              C:\Program Files\BurpSuitePro\burpsuite_pro.jar!\burp\Zsxw.class
 * Java compiler version: 21 (65.0)
 * JD-Core Version:       1.1.3
 */