package burp;

import java.math.BigInteger;

class Zszm extends ClassLoader {
  static Object ZI;
  
  static String Zf;
  
  private static final String[] a;
  
  private static final String[] b;
  
  static void Zx(Object[] paramArrayOfObject, Object paramObject) throws Throwable {}
  
  static boolean ZL(Object[] paramArrayOfObject, Object paramObject) throws Throwable {
    // Byte code:
    //   0: invokestatic ZK : ()Z
    //   3: istore_2
    //   4: new java/lang/StringBuilder
    //   7: dup
    //   8: invokespecial <init> : ()V
    //   11: astore_3
    //   12: iconst_0
    //   13: istore #4
    //   15: iload #4
    //   17: bipush #32
    //   19: if_icmpge -> 1355
    //   22: iload #4
    //   24: tableswitch default -> 1348, 0 -> 168, 1 -> 205, 2 -> 242, 3 -> 279, 4 -> 316, 5 -> 353, 6 -> 390, 7 -> 427, 8 -> 464, 9 -> 501, 10 -> 538, 11 -> 575, 12 -> 612, 13 -> 649, 14 -> 686, 15 -> 723, 16 -> 760, 17 -> 797, 18 -> 834, 19 -> 871, 20 -> 908, 21 -> 945, 22 -> 982, 23 -> 1019, 24 -> 1056, 25 -> 1093, 26 -> 1130, 27 -> 1167, 28 -> 1204, 29 -> 1241, 30 -> 1278, 31 -> 1315
    //   168: aload_3
    //   169: getstatic burp/Zecm.Zv : Ljava/lang/String;
    //   172: getstatic burp/Zrh1.ZF : Ljava/lang/Object;
    //   175: checkcast java/math/BigInteger
    //   178: invokevirtual intValue : ()I
    //   181: bipush #32
    //   183: irem
    //   184: invokestatic abs : (I)I
    //   187: invokevirtual charAt : (I)C
    //   190: invokevirtual append : (C)Ljava/lang/StringBuilder;
    //   193: pop
    //   194: iload_2
    //   195: ifeq -> 1348
    //   198: goto -> 205
    //   201: invokestatic a : (Ljava/lang/Throwable;)Ljava/lang/Throwable;
    //   204: athrow
    //   205: aload_3
    //   206: getstatic burp/Zt5a.Zl : Ljava/lang/String;
    //   209: getstatic burp/Zgr1.Zf : Ljava/lang/Object;
    //   212: checkcast java/math/BigInteger
    //   215: invokevirtual intValue : ()I
    //   218: bipush #32
    //   220: irem
    //   221: invokestatic abs : (I)I
    //   224: invokevirtual charAt : (I)C
    //   227: invokevirtual append : (C)Ljava/lang/StringBuilder;
    //   230: pop
    //   231: iload_2
    //   232: ifeq -> 1348
    //   235: goto -> 242
    //   238: invokestatic a : (Ljava/lang/Throwable;)Ljava/lang/Throwable;
    //   241: athrow
    //   242: aload_3
    //   243: getstatic burp/Zrp3.Zf : Ljava/lang/String;
    //   246: getstatic burp/Zs5i.ZD : Ljava/lang/Object;
    //   249: checkcast java/math/BigInteger
    //   252: invokevirtual intValue : ()I
    //   255: bipush #32
    //   257: irem
    //   258: invokestatic abs : (I)I
    //   261: invokevirtual charAt : (I)C
    //   264: invokevirtual append : (C)Ljava/lang/StringBuilder;
    //   267: pop
    //   268: iload_2
    //   269: ifeq -> 1348
    //   272: goto -> 279
    //   275: invokestatic a : (Ljava/lang/Throwable;)Ljava/lang/Throwable;
    //   278: athrow
    //   279: aload_3
    //   280: getstatic burp/Zl15.ZI : Ljava/lang/String;
    //   283: getstatic burp/Zgs6.Za : Ljava/lang/Object;
    //   286: checkcast java/math/BigInteger
    //   289: invokevirtual intValue : ()I
    //   292: bipush #32
    //   294: irem
    //   295: invokestatic abs : (I)I
    //   298: invokevirtual charAt : (I)C
    //   301: invokevirtual append : (C)Ljava/lang/StringBuilder;
    //   304: pop
    //   305: iload_2
    //   306: ifeq -> 1348
    //   309: goto -> 316
    //   312: invokestatic a : (Ljava/lang/Throwable;)Ljava/lang/Throwable;
    //   315: athrow
    //   316: aload_3
    //   317: getstatic burp/Zr9j.Zc : Ljava/lang/String;
    //   320: getstatic burp/Zg_6.ZU : Ljava/lang/Object;
    //   323: checkcast java/math/BigInteger
    //   326: invokevirtual intValue : ()I
    //   329: bipush #32
    //   331: irem
    //   332: invokestatic abs : (I)I
    //   335: invokevirtual charAt : (I)C
    //   338: invokevirtual append : (C)Ljava/lang/StringBuilder;
    //   341: pop
    //   342: iload_2
    //   343: ifeq -> 1348
    //   346: goto -> 353
    //   349: invokestatic a : (Ljava/lang/Throwable;)Ljava/lang/Throwable;
    //   352: athrow
    //   353: aload_3
    //   354: getstatic burp/Zzxa.Zl : Ljava/lang/String;
    //   357: getstatic burp/Ze9.Zu : Ljava/lang/Object;
    //   360: checkcast java/math/BigInteger
    //   363: invokevirtual intValue : ()I
    //   366: bipush #32
    //   368: irem
    //   369: invokestatic abs : (I)I
    //   372: invokevirtual charAt : (I)C
    //   375: invokevirtual append : (C)Ljava/lang/StringBuilder;
    //   378: pop
    //   379: iload_2
    //   380: ifeq -> 1348
    //   383: goto -> 390
    //   386: invokestatic a : (Ljava/lang/Throwable;)Ljava/lang/Throwable;
    //   389: athrow
    //   390: aload_3
    //   391: getstatic burp/Zs5k.ZI : Ljava/lang/String;
    //   394: getstatic burp/Zeju.Zk : Ljava/lang/Object;
    //   397: checkcast java/math/BigInteger
    //   400: invokevirtual intValue : ()I
    //   403: bipush #32
    //   405: irem
    //   406: invokestatic abs : (I)I
    //   409: invokevirtual charAt : (I)C
    //   412: invokevirtual append : (C)Ljava/lang/StringBuilder;
    //   415: pop
    //   416: iload_2
    //   417: ifeq -> 1348
    //   420: goto -> 427
    //   423: invokestatic a : (Ljava/lang/Throwable;)Ljava/lang/Throwable;
    //   426: athrow
    //   427: aload_3
    //   428: getstatic burp/Zr8r.Zn : Ljava/lang/String;
    //   431: getstatic burp/Zg_6.ZU : Ljava/lang/Object;
    //   434: checkcast java/math/BigInteger
    //   437: invokevirtual intValue : ()I
    //   440: bipush #32
    //   442: irem
    //   443: invokestatic abs : (I)I
    //   446: invokevirtual charAt : (I)C
    //   449: invokevirtual append : (C)Ljava/lang/StringBuilder;
    //   452: pop
    //   453: iload_2
    //   454: ifeq -> 1348
    //   457: goto -> 464
    //   460: invokestatic a : (Ljava/lang/Throwable;)Ljava/lang/Throwable;
    //   463: athrow
    //   464: aload_3
    //   465: getstatic burp/Zgl2.Zw : Ljava/lang/String;
    //   468: getstatic burp/Zsot.ZJ : Ljava/lang/Object;
    //   471: checkcast java/math/BigInteger
    //   474: invokevirtual intValue : ()I
    //   477: bipush #32
    //   479: irem
    //   480: invokestatic abs : (I)I
    //   483: invokevirtual charAt : (I)C
    //   486: invokevirtual append : (C)Ljava/lang/StringBuilder;
    //   489: pop
    //   490: iload_2
    //   491: ifeq -> 1348
    //   494: goto -> 501
    //   497: invokestatic a : (Ljava/lang/Throwable;)Ljava/lang/Throwable;
    //   500: athrow
    //   501: aload_3
    //   502: getstatic burp/Zr9j.Zc : Ljava/lang/String;
    //   505: getstatic burp/Zt5a.Zs : Ljava/lang/Object;
    //   508: checkcast java/math/BigInteger
    //   511: invokevirtual intValue : ()I
    //   514: bipush #32
    //   516: irem
    //   517: invokestatic abs : (I)I
    //   520: invokevirtual charAt : (I)C
    //   523: invokevirtual append : (C)Ljava/lang/StringBuilder;
    //   526: pop
    //   527: iload_2
    //   528: ifeq -> 1348
    //   531: goto -> 538
    //   534: invokestatic a : (Ljava/lang/Throwable;)Ljava/lang/Throwable;
    //   537: athrow
    //   538: aload_3
    //   539: getstatic burp/Ztw4.Zb : Ljava/lang/String;
    //   542: getstatic burp/Zg5.Zs : Ljava/lang/Object;
    //   545: checkcast java/math/BigInteger
    //   548: invokevirtual intValue : ()I
    //   551: bipush #32
    //   553: irem
    //   554: invokestatic abs : (I)I
    //   557: invokevirtual charAt : (I)C
    //   560: invokevirtual append : (C)Ljava/lang/StringBuilder;
    //   563: pop
    //   564: iload_2
    //   565: ifeq -> 1348
    //   568: goto -> 575
    //   571: invokestatic a : (Ljava/lang/Throwable;)Ljava/lang/Throwable;
    //   574: athrow
    //   575: aload_3
    //   576: getstatic burp/Zszm.Zf : Ljava/lang/String;
    //   579: getstatic burp/Zms1.ZE : Ljava/lang/Object;
    //   582: checkcast java/math/BigInteger
    //   585: invokevirtual intValue : ()I
    //   588: bipush #32
    //   590: irem
    //   591: invokestatic abs : (I)I
    //   594: invokevirtual charAt : (I)C
    //   597: invokevirtual append : (C)Ljava/lang/StringBuilder;
    //   600: pop
    //   601: iload_2
    //   602: ifeq -> 1348
    //   605: goto -> 612
    //   608: invokestatic a : (Ljava/lang/Throwable;)Ljava/lang/Throwable;
    //   611: athrow
    //   612: aload_3
    //   613: getstatic burp/Zxee.Zd : Ljava/lang/String;
    //   616: getstatic burp/Ztdg.ZE : Ljava/lang/Object;
    //   619: checkcast java/math/BigInteger
    //   622: invokevirtual intValue : ()I
    //   625: bipush #32
    //   627: irem
    //   628: invokestatic abs : (I)I
    //   631: invokevirtual charAt : (I)C
    //   634: invokevirtual append : (C)Ljava/lang/StringBuilder;
    //   637: pop
    //   638: iload_2
    //   639: ifeq -> 1348
    //   642: goto -> 649
    //   645: invokestatic a : (Ljava/lang/Throwable;)Ljava/lang/Throwable;
    //   648: athrow
    //   649: aload_3
    //   650: getstatic burp/Zenq.ZG : Ljava/lang/String;
    //   653: getstatic burp/Zl5.ZY : Ljava/lang/Object;
    //   656: checkcast java/math/BigInteger
    //   659: invokevirtual intValue : ()I
    //   662: bipush #32
    //   664: irem
    //   665: invokestatic abs : (I)I
    //   668: invokevirtual charAt : (I)C
    //   671: invokevirtual append : (C)Ljava/lang/StringBuilder;
    //   674: pop
    //   675: iload_2
    //   676: ifeq -> 1348
    //   679: goto -> 686
    //   682: invokestatic a : (Ljava/lang/Throwable;)Ljava/lang/Throwable;
    //   685: athrow
    //   686: aload_3
    //   687: getstatic burp/Zr4z.Zw : Ljava/lang/String;
    //   690: getstatic burp/Zl5.ZY : Ljava/lang/Object;
    //   693: checkcast java/math/BigInteger
    //   696: invokevirtual intValue : ()I
    //   699: bipush #32
    //   701: irem
    //   702: invokestatic abs : (I)I
    //   705: invokevirtual charAt : (I)C
    //   708: invokevirtual append : (C)Ljava/lang/StringBuilder;
    //   711: pop
    //   712: iload_2
    //   713: ifeq -> 1348
    //   716: goto -> 723
    //   719: invokestatic a : (Ljava/lang/Throwable;)Ljava/lang/Throwable;
    //   722: athrow
    //   723: aload_3
    //   724: getstatic burp/Zeqw.Zw : Ljava/lang/String;
    //   727: getstatic burp/Zrxf.ZS : Ljava/lang/Object;
    //   730: checkcast java/math/BigInteger
    //   733: invokevirtual intValue : ()I
    //   736: bipush #32
    //   738: irem
    //   739: invokestatic abs : (I)I
    //   742: invokevirtual charAt : (I)C
    //   745: invokevirtual append : (C)Ljava/lang/StringBuilder;
    //   748: pop
    //   749: iload_2
    //   750: ifeq -> 1348
    //   753: goto -> 760
    //   756: invokestatic a : (Ljava/lang/Throwable;)Ljava/lang/Throwable;
    //   759: athrow
    //   760: aload_3
    //   761: getstatic burp/Zrxf.ZG : Ljava/lang/String;
    //   764: getstatic burp/Zzhu.ZW : Ljava/lang/Object;
    //   767: checkcast java/math/BigInteger
    //   770: invokevirtual intValue : ()I
    //   773: bipush #32
    //   775: irem
    //   776: invokestatic abs : (I)I
    //   779: invokevirtual charAt : (I)C
    //   782: invokevirtual append : (C)Ljava/lang/StringBuilder;
    //   785: pop
    //   786: iload_2
    //   787: ifeq -> 1348
    //   790: goto -> 797
    //   793: invokestatic a : (Ljava/lang/Throwable;)Ljava/lang/Throwable;
    //   796: athrow
    //   797: aload_3
    //   798: getstatic burp/Ztpg.Zr : Ljava/lang/String;
    //   801: getstatic burp/Zz5l.Zb : Ljava/lang/Object;
    //   804: checkcast java/math/BigInteger
    //   807: invokevirtual intValue : ()I
    //   810: bipush #32
    //   812: irem
    //   813: invokestatic abs : (I)I
    //   816: invokevirtual charAt : (I)C
    //   819: invokevirtual append : (C)Ljava/lang/StringBuilder;
    //   822: pop
    //   823: iload_2
    //   824: ifeq -> 1348
    //   827: goto -> 834
    //   830: invokestatic a : (Ljava/lang/Throwable;)Ljava/lang/Throwable;
    //   833: athrow
    //   834: aload_3
    //   835: getstatic burp/Zlvx.Zr : Ljava/lang/String;
    //   838: getstatic burp/Zecm.ZJ : Ljava/lang/Object;
    //   841: checkcast java/math/BigInteger
    //   844: invokevirtual intValue : ()I
    //   847: bipush #32
    //   849: irem
    //   850: invokestatic abs : (I)I
    //   853: invokevirtual charAt : (I)C
    //   856: invokevirtual append : (C)Ljava/lang/StringBuilder;
    //   859: pop
    //   860: iload_2
    //   861: ifeq -> 1348
    //   864: goto -> 871
    //   867: invokestatic a : (Ljava/lang/Throwable;)Ljava/lang/Throwable;
    //   870: athrow
    //   871: aload_3
    //   872: getstatic burp/Zro_.Zz : Ljava/lang/String;
    //   875: getstatic burp/Zrxf.ZS : Ljava/lang/Object;
    //   878: checkcast java/math/BigInteger
    //   881: invokevirtual intValue : ()I
    //   884: bipush #32
    //   886: irem
    //   887: invokestatic abs : (I)I
    //   890: invokevirtual charAt : (I)C
    //   893: invokevirtual append : (C)Ljava/lang/StringBuilder;
    //   896: pop
    //   897: iload_2
    //   898: ifeq -> 1348
    //   901: goto -> 908
    //   904: invokestatic a : (Ljava/lang/Throwable;)Ljava/lang/Throwable;
    //   907: athrow
    //   908: aload_3
    //   909: getstatic burp/Zmh0.Zs : Ljava/lang/String;
    //   912: getstatic burp/Zs56.ZC : Ljava/lang/Object;
    //   915: checkcast java/math/BigInteger
    //   918: invokevirtual intValue : ()I
    //   921: bipush #32
    //   923: irem
    //   924: invokestatic abs : (I)I
    //   927: invokevirtual charAt : (I)C
    //   930: invokevirtual append : (C)Ljava/lang/StringBuilder;
    //   933: pop
    //   934: iload_2
    //   935: ifeq -> 1348
    //   938: goto -> 945
    //   941: invokestatic a : (Ljava/lang/Throwable;)Ljava/lang/Throwable;
    //   944: athrow
    //   945: aload_3
    //   946: getstatic burp/Zrxf.ZG : Ljava/lang/String;
    //   949: getstatic burp/Ztdg.ZE : Ljava/lang/Object;
    //   952: checkcast java/math/BigInteger
    //   955: invokevirtual intValue : ()I
    //   958: bipush #32
    //   960: irem
    //   961: invokestatic abs : (I)I
    //   964: invokevirtual charAt : (I)C
    //   967: invokevirtual append : (C)Ljava/lang/StringBuilder;
    //   970: pop
    //   971: iload_2
    //   972: ifeq -> 1348
    //   975: goto -> 982
    //   978: invokestatic a : (Ljava/lang/Throwable;)Ljava/lang/Throwable;
    //   981: athrow
    //   982: aload_3
    //   983: getstatic burp/Zbzj.Zw : Ljava/lang/String;
    //   986: getstatic burp/Zg5.Zs : Ljava/lang/Object;
    //   989: checkcast java/math/BigInteger
    //   992: invokevirtual intValue : ()I
    //   995: bipush #32
    //   997: irem
    //   998: invokestatic abs : (I)I
    //   1001: invokevirtual charAt : (I)C
    //   1004: invokevirtual append : (C)Ljava/lang/StringBuilder;
    //   1007: pop
    //   1008: iload_2
    //   1009: ifeq -> 1348
    //   1012: goto -> 1019
    //   1015: invokestatic a : (Ljava/lang/Throwable;)Ljava/lang/Throwable;
    //   1018: athrow
    //   1019: aload_3
    //   1020: getstatic burp/Zmvk.Z_ : Ljava/lang/String;
    //   1023: getstatic burp/Zlvx.ZM : Ljava/lang/Object;
    //   1026: checkcast java/math/BigInteger
    //   1029: invokevirtual intValue : ()I
    //   1032: bipush #32
    //   1034: irem
    //   1035: invokestatic abs : (I)I
    //   1038: invokevirtual charAt : (I)C
    //   1041: invokevirtual append : (C)Ljava/lang/StringBuilder;
    //   1044: pop
    //   1045: iload_2
    //   1046: ifeq -> 1348
    //   1049: goto -> 1056
    //   1052: invokestatic a : (Ljava/lang/Throwable;)Ljava/lang/Throwable;
    //   1055: athrow
    //   1056: aload_3
    //   1057: getstatic burp/Zlwi.ZN : Ljava/lang/String;
    //   1060: getstatic burp/Zs5i.ZD : Ljava/lang/Object;
    //   1063: checkcast java/math/BigInteger
    //   1066: invokevirtual intValue : ()I
    //   1069: bipush #32
    //   1071: irem
    //   1072: invokestatic abs : (I)I
    //   1075: invokevirtual charAt : (I)C
    //   1078: invokevirtual append : (C)Ljava/lang/StringBuilder;
    //   1081: pop
    //   1082: iload_2
    //   1083: ifeq -> 1348
    //   1086: goto -> 1093
    //   1089: invokestatic a : (Ljava/lang/Throwable;)Ljava/lang/Throwable;
    //   1092: athrow
    //   1093: aload_3
    //   1094: getstatic burp/Zl15.ZI : Ljava/lang/String;
    //   1097: getstatic burp/Zrt9.Zy : Ljava/lang/Object;
    //   1100: checkcast java/math/BigInteger
    //   1103: invokevirtual intValue : ()I
    //   1106: bipush #32
    //   1108: irem
    //   1109: invokestatic abs : (I)I
    //   1112: invokevirtual charAt : (I)C
    //   1115: invokevirtual append : (C)Ljava/lang/StringBuilder;
    //   1118: pop
    //   1119: iload_2
    //   1120: ifeq -> 1348
    //   1123: goto -> 1130
    //   1126: invokestatic a : (Ljava/lang/Throwable;)Ljava/lang/Throwable;
    //   1129: athrow
    //   1130: aload_3
    //   1131: getstatic burp/Zrnw.Zg : Ljava/lang/String;
    //   1134: getstatic burp/Zr4z.ZH : Ljava/lang/Object;
    //   1137: checkcast java/math/BigInteger
    //   1140: invokevirtual intValue : ()I
    //   1143: bipush #32
    //   1145: irem
    //   1146: invokestatic abs : (I)I
    //   1149: invokevirtual charAt : (I)C
    //   1152: invokevirtual append : (C)Ljava/lang/StringBuilder;
    //   1155: pop
    //   1156: iload_2
    //   1157: ifeq -> 1348
    //   1160: goto -> 1167
    //   1163: invokestatic a : (Ljava/lang/Throwable;)Ljava/lang/Throwable;
    //   1166: athrow
    //   1167: aload_3
    //   1168: getstatic burp/Zmdm.Za : Ljava/lang/String;
    //   1171: getstatic burp/Zrnw.ZN : Ljava/lang/Object;
    //   1174: checkcast java/math/BigInteger
    //   1177: invokevirtual intValue : ()I
    //   1180: bipush #32
    //   1182: irem
    //   1183: invokestatic abs : (I)I
    //   1186: invokevirtual charAt : (I)C
    //   1189: invokevirtual append : (C)Ljava/lang/StringBuilder;
    //   1192: pop
    //   1193: iload_2
    //   1194: ifeq -> 1348
    //   1197: goto -> 1204
    //   1200: invokestatic a : (Ljava/lang/Throwable;)Ljava/lang/Throwable;
    //   1203: athrow
    //   1204: aload_3
    //   1205: getstatic burp/Zs5i.ZJ : Ljava/lang/String;
    //   1208: getstatic burp/Zz0.ZJ : Ljava/lang/Object;
    //   1211: checkcast java/math/BigInteger
    //   1214: invokevirtual intValue : ()I
    //   1217: bipush #32
    //   1219: irem
    //   1220: invokestatic abs : (I)I
    //   1223: invokevirtual charAt : (I)C
    //   1226: invokevirtual append : (C)Ljava/lang/StringBuilder;
    //   1229: pop
    //   1230: iload_2
    //   1231: ifeq -> 1348
    //   1234: goto -> 1241
    //   1237: invokestatic a : (Ljava/lang/Throwable;)Ljava/lang/Throwable;
    //   1240: athrow
    //   1241: aload_3
    //   1242: getstatic burp/Zktq.Zc : Ljava/lang/String;
    //   1245: getstatic burp/Zs5i.ZD : Ljava/lang/Object;
    //   1248: checkcast java/math/BigInteger
    //   1251: invokevirtual intValue : ()I
    //   1254: bipush #32
    //   1256: irem
    //   1257: invokestatic abs : (I)I
    //   1260: invokevirtual charAt : (I)C
    //   1263: invokevirtual append : (C)Ljava/lang/StringBuilder;
    //   1266: pop
    //   1267: iload_2
    //   1268: ifeq -> 1348
    //   1271: goto -> 1278
    //   1274: invokestatic a : (Ljava/lang/Throwable;)Ljava/lang/Throwable;
    //   1277: athrow
    //   1278: aload_3
    //   1279: getstatic burp/Zzxa.Zl : Ljava/lang/String;
    //   1282: getstatic burp/Zso7.ZB : Ljava/lang/Object;
    //   1285: checkcast java/math/BigInteger
    //   1288: invokevirtual intValue : ()I
    //   1291: bipush #32
    //   1293: irem
    //   1294: invokestatic abs : (I)I
    //   1297: invokevirtual charAt : (I)C
    //   1300: invokevirtual append : (C)Ljava/lang/StringBuilder;
    //   1303: pop
    //   1304: iload_2
    //   1305: ifeq -> 1348
    //   1308: goto -> 1315
    //   1311: invokestatic a : (Ljava/lang/Throwable;)Ljava/lang/Throwable;
    //   1314: athrow
    //   1315: aload_3
    //   1316: getstatic burp/Zl8s.Zn : Ljava/lang/String;
    //   1319: getstatic burp/Zmly.ZT : Ljava/lang/Object;
    //   1322: checkcast java/math/BigInteger
    //   1325: invokevirtual intValue : ()I
    //   1328: bipush #32
    //   1330: irem
    //   1331: invokestatic abs : (I)I
    //   1334: invokevirtual charAt : (I)C
    //   1337: invokevirtual append : (C)Ljava/lang/StringBuilder;
    //   1340: pop
    //   1341: goto -> 1348
    //   1344: invokestatic a : (Ljava/lang/Throwable;)Ljava/lang/Throwable;
    //   1347: athrow
    //   1348: iinc #4, 1
    //   1351: iload_2
    //   1352: ifeq -> 15
    //   1355: aload_3
    //   1356: invokevirtual toString : ()Ljava/lang/String;
    //   1359: putstatic burp/Zml2.Zh : Ljava/lang/String;
    //   1362: getstatic burp/Zm5s.ZB : Ljava/lang/Object;
    //   1365: checkcast java/math/BigInteger
    //   1368: invokevirtual toByteArray : ()[B
    //   1371: astore #4
    //   1373: aload #4
    //   1375: arraylength
    //   1376: iconst_2
    //   1377: iadd
    //   1378: newarray byte
    //   1380: astore #6
    //   1382: iconst_0
    //   1383: istore #7
    //   1385: iload #7
    //   1387: aload #4
    //   1389: arraylength
    //   1390: if_icmpge -> 1410
    //   1393: aload #6
    //   1395: iload #7
    //   1397: aload #4
    //   1399: iload #7
    //   1401: baload
    //   1402: bastore
    //   1403: iinc #7, 1
    //   1406: iload_2
    //   1407: ifeq -> 1385
    //   1410: aload #6
    //   1412: arraylength
    //   1413: iconst_3
    //   1414: idiv
    //   1415: iconst_4
    //   1416: imul
    //   1417: newarray byte
    //   1419: astore #5
    //   1421: iconst_0
    //   1422: istore #7
    //   1424: iconst_0
    //   1425: istore #8
    //   1427: iload #7
    //   1429: aload #4
    //   1431: arraylength
    //   1432: if_icmpge -> 1543
    //   1435: aload #5
    //   1437: iload #8
    //   1439: aload #6
    //   1441: iload #7
    //   1443: baload
    //   1444: iconst_2
    //   1445: iushr
    //   1446: bipush #63
    //   1448: iand
    //   1449: i2b
    //   1450: bastore
    //   1451: aload #5
    //   1453: iload #8
    //   1455: iconst_1
    //   1456: iadd
    //   1457: aload #6
    //   1459: iload #7
    //   1461: iconst_1
    //   1462: iadd
    //   1463: baload
    //   1464: iconst_4
    //   1465: iushr
    //   1466: bipush #15
    //   1468: iand
    //   1469: aload #6
    //   1471: iload #7
    //   1473: baload
    //   1474: iconst_4
    //   1475: ishl
    //   1476: bipush #63
    //   1478: iand
    //   1479: ior
    //   1480: i2b
    //   1481: bastore
    //   1482: aload #5
    //   1484: iload #8
    //   1486: iconst_2
    //   1487: iadd
    //   1488: aload #6
    //   1490: iload #7
    //   1492: iconst_2
    //   1493: iadd
    //   1494: baload
    //   1495: bipush #6
    //   1497: iushr
    //   1498: iconst_3
    //   1499: iand
    //   1500: aload #6
    //   1502: iload #7
    //   1504: iconst_1
    //   1505: iadd
    //   1506: baload
    //   1507: iconst_2
    //   1508: ishl
    //   1509: bipush #63
    //   1511: iand
    //   1512: ior
    //   1513: i2b
    //   1514: bastore
    //   1515: aload #5
    //   1517: iload #8
    //   1519: iconst_3
    //   1520: iadd
    //   1521: aload #6
    //   1523: iload #7
    //   1525: iconst_2
    //   1526: iadd
    //   1527: baload
    //   1528: bipush #63
    //   1530: iand
    //   1531: i2b
    //   1532: bastore
    //   1533: iinc #7, 3
    //   1536: iinc #8, 4
    //   1539: iload_2
    //   1540: ifeq -> 1427
    //   1543: iconst_0
    //   1544: istore #7
    //   1546: iload #7
    //   1548: aload #5
    //   1550: arraylength
    //   1551: if_icmpge -> 1735
    //   1554: aload #5
    //   1556: iload #7
    //   1558: baload
    //   1559: bipush #26
    //   1561: if_icmpge -> 1589
    //   1564: aload #5
    //   1566: iload #7
    //   1568: aload #5
    //   1570: iload #7
    //   1572: baload
    //   1573: bipush #65
    //   1575: iadd
    //   1576: i2b
    //   1577: bastore
    //   1578: iload_2
    //   1579: ifeq -> 1728
    //   1582: goto -> 1589
    //   1585: invokestatic a : (Ljava/lang/Throwable;)Ljava/lang/Throwable;
    //   1588: athrow
    //   1589: aload #5
    //   1591: iload #7
    //   1593: baload
    //   1594: bipush #52
    //   1596: if_icmpge -> 1634
    //   1599: goto -> 1606
    //   1602: invokestatic a : (Ljava/lang/Throwable;)Ljava/lang/Throwable;
    //   1605: athrow
    //   1606: aload #5
    //   1608: iload #7
    //   1610: aload #5
    //   1612: iload #7
    //   1614: baload
    //   1615: bipush #97
    //   1617: iadd
    //   1618: bipush #26
    //   1620: isub
    //   1621: i2b
    //   1622: bastore
    //   1623: iload_2
    //   1624: ifeq -> 1728
    //   1627: goto -> 1634
    //   1630: invokestatic a : (Ljava/lang/Throwable;)Ljava/lang/Throwable;
    //   1633: athrow
    //   1634: aload #5
    //   1636: iload #7
    //   1638: baload
    //   1639: bipush #62
    //   1641: if_icmpge -> 1679
    //   1644: goto -> 1651
    //   1647: invokestatic a : (Ljava/lang/Throwable;)Ljava/lang/Throwable;
    //   1650: athrow
    //   1651: aload #5
    //   1653: iload #7
    //   1655: aload #5
    //   1657: iload #7
    //   1659: baload
    //   1660: bipush #48
    //   1662: iadd
    //   1663: bipush #52
    //   1665: isub
    //   1666: i2b
    //   1667: bastore
    //   1668: iload_2
    //   1669: ifeq -> 1728
    //   1672: goto -> 1679
    //   1675: invokestatic a : (Ljava/lang/Throwable;)Ljava/lang/Throwable;
    //   1678: athrow
    //   1679: aload #5
    //   1681: iload #7
    //   1683: baload
    //   1684: bipush #63
    //   1686: if_icmpge -> 1714
    //   1689: goto -> 1696
    //   1692: invokestatic a : (Ljava/lang/Throwable;)Ljava/lang/Throwable;
    //   1695: athrow
    //   1696: aload #5
    //   1698: iload #7
    //   1700: bipush #43
    //   1702: bastore
    //   1703: iload_2
    //   1704: ifeq -> 1728
    //   1707: goto -> 1714
    //   1710: invokestatic a : (Ljava/lang/Throwable;)Ljava/lang/Throwable;
    //   1713: athrow
    //   1714: aload #5
    //   1716: iload #7
    //   1718: bipush #47
    //   1720: bastore
    //   1721: goto -> 1728
    //   1724: invokestatic a : (Ljava/lang/Throwable;)Ljava/lang/Throwable;
    //   1727: athrow
    //   1728: iinc #7, 1
    //   1731: iload_2
    //   1732: ifeq -> 1546
    //   1735: aload #5
    //   1737: arraylength
    //   1738: iconst_1
    //   1739: isub
    //   1740: istore #7
    //   1742: iload #7
    //   1744: aload #4
    //   1746: arraylength
    //   1747: iconst_4
    //   1748: imul
    //   1749: iconst_3
    //   1750: idiv
    //   1751: if_icmple -> 1768
    //   1754: aload #5
    //   1756: iload #7
    //   1758: bipush #61
    //   1760: bastore
    //   1761: iinc #7, -1
    //   1764: iload_2
    //   1765: ifeq -> 1742
    //   1768: new java/math/BigInteger
    //   1771: dup
    //   1772: aload #5
    //   1774: invokespecial <init> : ([B)V
    //   1777: invokevirtual abs : ()Ljava/math/BigInteger;
    //   1780: putstatic burp/Zr9j.Zw : Ljava/lang/Object;
    //   1783: new java/lang/StringBuilder
    //   1786: dup
    //   1787: invokespecial <init> : ()V
    //   1790: astore #4
    //   1792: iconst_0
    //   1793: istore #5
    //   1795: iload #5
    //   1797: bipush #32
    //   1799: if_icmpge -> 3167
    //   1802: iload #5
    //   1804: tableswitch default -> 3160, 0 -> 1948, 1 -> 1986, 2 -> 2024, 3 -> 2062, 4 -> 2100, 5 -> 2138, 6 -> 2176, 7 -> 2214, 8 -> 2252, 9 -> 2290, 10 -> 2328, 11 -> 2366, 12 -> 2404, 13 -> 2442, 14 -> 2480, 15 -> 2518, 16 -> 2556, 17 -> 2594, 18 -> 2632, 19 -> 2670, 20 -> 2708, 21 -> 2746, 22 -> 2784, 23 -> 2822, 24 -> 2860, 25 -> 2898, 26 -> 2936, 27 -> 2974, 28 -> 3012, 29 -> 3050, 30 -> 3088, 31 -> 3126
    //   1948: aload #4
    //   1950: getstatic burp/Zszm.Zf : Ljava/lang/String;
    //   1953: getstatic burp/Zr4z.ZH : Ljava/lang/Object;
    //   1956: checkcast java/math/BigInteger
    //   1959: invokevirtual intValue : ()I
    //   1962: bipush #32
    //   1964: irem
    //   1965: invokestatic abs : (I)I
    //   1968: invokevirtual charAt : (I)C
    //   1971: invokevirtual append : (C)Ljava/lang/StringBuilder;
    //   1974: pop
    //   1975: iload_2
    //   1976: ifeq -> 3160
    //   1979: goto -> 1986
    //   1982: invokestatic a : (Ljava/lang/Throwable;)Ljava/lang/Throwable;
    //   1985: athrow
    //   1986: aload #4
    //   1988: getstatic burp/Zrnw.Zg : Ljava/lang/String;
    //   1991: getstatic burp/Zlhu.ZJ : Ljava/lang/Object;
    //   1994: checkcast java/math/BigInteger
    //   1997: invokevirtual intValue : ()I
    //   2000: bipush #32
    //   2002: irem
    //   2003: invokestatic abs : (I)I
    //   2006: invokevirtual charAt : (I)C
    //   2009: invokevirtual append : (C)Ljava/lang/StringBuilder;
    //   2012: pop
    //   2013: iload_2
    //   2014: ifeq -> 3160
    //   2017: goto -> 2024
    //   2020: invokestatic a : (Ljava/lang/Throwable;)Ljava/lang/Throwable;
    //   2023: athrow
    //   2024: aload #4
    //   2026: getstatic burp/Zej5.Zo : Ljava/lang/String;
    //   2029: getstatic burp/Zr9j.Zw : Ljava/lang/Object;
    //   2032: checkcast java/math/BigInteger
    //   2035: invokevirtual intValue : ()I
    //   2038: bipush #32
    //   2040: irem
    //   2041: invokestatic abs : (I)I
    //   2044: invokevirtual charAt : (I)C
    //   2047: invokevirtual append : (C)Ljava/lang/StringBuilder;
    //   2050: pop
    //   2051: iload_2
    //   2052: ifeq -> 3160
    //   2055: goto -> 2062
    //   2058: invokestatic a : (Ljava/lang/Throwable;)Ljava/lang/Throwable;
    //   2061: athrow
    //   2062: aload #4
    //   2064: getstatic burp/Ze_e.ZH : Ljava/lang/String;
    //   2067: getstatic burp/Zzxa.ZI : Ljava/lang/Object;
    //   2070: checkcast java/math/BigInteger
    //   2073: invokevirtual intValue : ()I
    //   2076: bipush #32
    //   2078: irem
    //   2079: invokestatic abs : (I)I
    //   2082: invokevirtual charAt : (I)C
    //   2085: invokevirtual append : (C)Ljava/lang/StringBuilder;
    //   2088: pop
    //   2089: iload_2
    //   2090: ifeq -> 3160
    //   2093: goto -> 2100
    //   2096: invokestatic a : (Ljava/lang/Throwable;)Ljava/lang/Throwable;
    //   2099: athrow
    //   2100: aload #4
    //   2102: getstatic burp/Zszm.Zf : Ljava/lang/String;
    //   2105: getstatic burp/Zr4z.ZH : Ljava/lang/Object;
    //   2108: checkcast java/math/BigInteger
    //   2111: invokevirtual intValue : ()I
    //   2114: bipush #32
    //   2116: irem
    //   2117: invokestatic abs : (I)I
    //   2120: invokevirtual charAt : (I)C
    //   2123: invokevirtual append : (C)Ljava/lang/StringBuilder;
    //   2126: pop
    //   2127: iload_2
    //   2128: ifeq -> 3160
    //   2131: goto -> 2138
    //   2134: invokestatic a : (Ljava/lang/Throwable;)Ljava/lang/Throwable;
    //   2137: athrow
    //   2138: aload #4
    //   2140: getstatic burp/Zrxf.ZG : Ljava/lang/String;
    //   2143: getstatic burp/Zmec.ZY : Ljava/lang/Object;
    //   2146: checkcast java/math/BigInteger
    //   2149: invokevirtual intValue : ()I
    //   2152: bipush #32
    //   2154: irem
    //   2155: invokestatic abs : (I)I
    //   2158: invokevirtual charAt : (I)C
    //   2161: invokevirtual append : (C)Ljava/lang/StringBuilder;
    //   2164: pop
    //   2165: iload_2
    //   2166: ifeq -> 3160
    //   2169: goto -> 2176
    //   2172: invokestatic a : (Ljava/lang/Throwable;)Ljava/lang/Throwable;
    //   2175: athrow
    //   2176: aload #4
    //   2178: getstatic burp/Zbsc.Zp : Ljava/lang/String;
    //   2181: getstatic burp/Zr4z.ZH : Ljava/lang/Object;
    //   2184: checkcast java/math/BigInteger
    //   2187: invokevirtual intValue : ()I
    //   2190: bipush #32
    //   2192: irem
    //   2193: invokestatic abs : (I)I
    //   2196: invokevirtual charAt : (I)C
    //   2199: invokevirtual append : (C)Ljava/lang/StringBuilder;
    //   2202: pop
    //   2203: iload_2
    //   2204: ifeq -> 3160
    //   2207: goto -> 2214
    //   2210: invokestatic a : (Ljava/lang/Throwable;)Ljava/lang/Throwable;
    //   2213: athrow
    //   2214: aload #4
    //   2216: getstatic burp/Zrt9.Zc : Ljava/lang/String;
    //   2219: getstatic burp/Ztg3.Zg : Ljava/lang/Object;
    //   2222: checkcast java/math/BigInteger
    //   2225: invokevirtual intValue : ()I
    //   2228: bipush #32
    //   2230: irem
    //   2231: invokestatic abs : (I)I
    //   2234: invokevirtual charAt : (I)C
    //   2237: invokevirtual append : (C)Ljava/lang/StringBuilder;
    //   2240: pop
    //   2241: iload_2
    //   2242: ifeq -> 3160
    //   2245: goto -> 2252
    //   2248: invokestatic a : (Ljava/lang/Throwable;)Ljava/lang/Throwable;
    //   2251: athrow
    //   2252: aload #4
    //   2254: getstatic burp/Zms1.ZZ : Ljava/lang/String;
    //   2257: getstatic burp/Zecm.ZJ : Ljava/lang/Object;
    //   2260: checkcast java/math/BigInteger
    //   2263: invokevirtual intValue : ()I
    //   2266: bipush #32
    //   2268: irem
    //   2269: invokestatic abs : (I)I
    //   2272: invokevirtual charAt : (I)C
    //   2275: invokevirtual append : (C)Ljava/lang/StringBuilder;
    //   2278: pop
    //   2279: iload_2
    //   2280: ifeq -> 3160
    //   2283: goto -> 2290
    //   2286: invokestatic a : (Ljava/lang/Throwable;)Ljava/lang/Throwable;
    //   2289: athrow
    //   2290: aload #4
    //   2292: getstatic burp/Zgr1.Za : Ljava/lang/String;
    //   2295: getstatic burp/Zza3.Zb : Ljava/lang/Object;
    //   2298: checkcast java/math/BigInteger
    //   2301: invokevirtual intValue : ()I
    //   2304: bipush #32
    //   2306: irem
    //   2307: invokestatic abs : (I)I
    //   2310: invokevirtual charAt : (I)C
    //   2313: invokevirtual append : (C)Ljava/lang/StringBuilder;
    //   2316: pop
    //   2317: iload_2
    //   2318: ifeq -> 3160
    //   2321: goto -> 2328
    //   2324: invokestatic a : (Ljava/lang/Throwable;)Ljava/lang/Throwable;
    //   2327: athrow
    //   2328: aload #4
    //   2330: getstatic burp/Zefn.Ze : Ljava/lang/String;
    //   2333: getstatic burp/Zz0.ZJ : Ljava/lang/Object;
    //   2336: checkcast java/math/BigInteger
    //   2339: invokevirtual intValue : ()I
    //   2342: bipush #32
    //   2344: irem
    //   2345: invokestatic abs : (I)I
    //   2348: invokevirtual charAt : (I)C
    //   2351: invokevirtual append : (C)Ljava/lang/StringBuilder;
    //   2354: pop
    //   2355: iload_2
    //   2356: ifeq -> 3160
    //   2359: goto -> 2366
    //   2362: invokestatic a : (Ljava/lang/Throwable;)Ljava/lang/Throwable;
    //   2365: athrow
    //   2366: aload #4
    //   2368: getstatic burp/Ztw4.Zb : Ljava/lang/String;
    //   2371: getstatic burp/Zrnw.ZN : Ljava/lang/Object;
    //   2374: checkcast java/math/BigInteger
    //   2377: invokevirtual intValue : ()I
    //   2380: bipush #32
    //   2382: irem
    //   2383: invokestatic abs : (I)I
    //   2386: invokevirtual charAt : (I)C
    //   2389: invokevirtual append : (C)Ljava/lang/StringBuilder;
    //   2392: pop
    //   2393: iload_2
    //   2394: ifeq -> 3160
    //   2397: goto -> 2404
    //   2400: invokestatic a : (Ljava/lang/Throwable;)Ljava/lang/Throwable;
    //   2403: athrow
    //   2404: aload #4
    //   2406: getstatic burp/Zmec.Zi : Ljava/lang/String;
    //   2409: getstatic burp/Ze_e.Za : Ljava/lang/Object;
    //   2412: checkcast java/math/BigInteger
    //   2415: invokevirtual intValue : ()I
    //   2418: bipush #32
    //   2420: irem
    //   2421: invokestatic abs : (I)I
    //   2424: invokevirtual charAt : (I)C
    //   2427: invokevirtual append : (C)Ljava/lang/StringBuilder;
    //   2430: pop
    //   2431: iload_2
    //   2432: ifeq -> 3160
    //   2435: goto -> 2442
    //   2438: invokestatic a : (Ljava/lang/Throwable;)Ljava/lang/Throwable;
    //   2441: athrow
    //   2442: aload #4
    //   2444: getstatic burp/Zmvk.Z_ : Ljava/lang/String;
    //   2447: getstatic burp/Zbsc.ZA : Ljava/lang/Object;
    //   2450: checkcast java/math/BigInteger
    //   2453: invokevirtual intValue : ()I
    //   2456: bipush #32
    //   2458: irem
    //   2459: invokestatic abs : (I)I
    //   2462: invokevirtual charAt : (I)C
    //   2465: invokevirtual append : (C)Ljava/lang/StringBuilder;
    //   2468: pop
    //   2469: iload_2
    //   2470: ifeq -> 3160
    //   2473: goto -> 2480
    //   2476: invokestatic a : (Ljava/lang/Throwable;)Ljava/lang/Throwable;
    //   2479: athrow
    //   2480: aload #4
    //   2482: getstatic burp/Zro_.Zz : Ljava/lang/String;
    //   2485: getstatic burp/Zgr1.Zf : Ljava/lang/Object;
    //   2488: checkcast java/math/BigInteger
    //   2491: invokevirtual intValue : ()I
    //   2494: bipush #32
    //   2496: irem
    //   2497: invokestatic abs : (I)I
    //   2500: invokevirtual charAt : (I)C
    //   2503: invokevirtual append : (C)Ljava/lang/StringBuilder;
    //   2506: pop
    //   2507: iload_2
    //   2508: ifeq -> 3160
    //   2511: goto -> 2518
    //   2514: invokestatic a : (Ljava/lang/Throwable;)Ljava/lang/Throwable;
    //   2517: athrow
    //   2518: aload #4
    //   2520: getstatic burp/Zso7.Zr : Ljava/lang/String;
    //   2523: getstatic burp/Zl1z.ZV : Ljava/lang/Object;
    //   2526: checkcast java/math/BigInteger
    //   2529: invokevirtual intValue : ()I
    //   2532: bipush #32
    //   2534: irem
    //   2535: invokestatic abs : (I)I
    //   2538: invokevirtual charAt : (I)C
    //   2541: invokevirtual append : (C)Ljava/lang/StringBuilder;
    //   2544: pop
    //   2545: iload_2
    //   2546: ifeq -> 3160
    //   2549: goto -> 2556
    //   2552: invokestatic a : (Ljava/lang/Throwable;)Ljava/lang/Throwable;
    //   2555: athrow
    //   2556: aload #4
    //   2558: getstatic burp/Zspk.ZA : Ljava/lang/String;
    //   2561: getstatic burp/Zkc5.ZZ : Ljava/lang/Object;
    //   2564: checkcast java/math/BigInteger
    //   2567: invokevirtual intValue : ()I
    //   2570: bipush #32
    //   2572: irem
    //   2573: invokestatic abs : (I)I
    //   2576: invokevirtual charAt : (I)C
    //   2579: invokevirtual append : (C)Ljava/lang/StringBuilder;
    //   2582: pop
    //   2583: iload_2
    //   2584: ifeq -> 3160
    //   2587: goto -> 2594
    //   2590: invokestatic a : (Ljava/lang/Throwable;)Ljava/lang/Throwable;
    //   2593: athrow
    //   2594: aload #4
    //   2596: getstatic burp/Zs5k.ZI : Ljava/lang/String;
    //   2599: getstatic burp/Zevc.Zm : Ljava/lang/Object;
    //   2602: checkcast java/math/BigInteger
    //   2605: invokevirtual intValue : ()I
    //   2608: bipush #32
    //   2610: irem
    //   2611: invokestatic abs : (I)I
    //   2614: invokevirtual charAt : (I)C
    //   2617: invokevirtual append : (C)Ljava/lang/StringBuilder;
    //   2620: pop
    //   2621: iload_2
    //   2622: ifeq -> 3160
    //   2625: goto -> 2632
    //   2628: invokestatic a : (Ljava/lang/Throwable;)Ljava/lang/Throwable;
    //   2631: athrow
    //   2632: aload #4
    //   2634: getstatic burp/Ze9.Zh : Ljava/lang/String;
    //   2637: getstatic burp/Zmly.ZT : Ljava/lang/Object;
    //   2640: checkcast java/math/BigInteger
    //   2643: invokevirtual intValue : ()I
    //   2646: bipush #32
    //   2648: irem
    //   2649: invokestatic abs : (I)I
    //   2652: invokevirtual charAt : (I)C
    //   2655: invokevirtual append : (C)Ljava/lang/StringBuilder;
    //   2658: pop
    //   2659: iload_2
    //   2660: ifeq -> 3160
    //   2663: goto -> 2670
    //   2666: invokestatic a : (Ljava/lang/Throwable;)Ljava/lang/Throwable;
    //   2669: athrow
    //   2670: aload #4
    //   2672: getstatic burp/Zg5.ZF : Ljava/lang/String;
    //   2675: getstatic burp/Zb8_.ZT : Ljava/lang/Object;
    //   2678: checkcast java/math/BigInteger
    //   2681: invokevirtual intValue : ()I
    //   2684: bipush #32
    //   2686: irem
    //   2687: invokestatic abs : (I)I
    //   2690: invokevirtual charAt : (I)C
    //   2693: invokevirtual append : (C)Ljava/lang/StringBuilder;
    //   2696: pop
    //   2697: iload_2
    //   2698: ifeq -> 3160
    //   2701: goto -> 2708
    //   2704: invokestatic a : (Ljava/lang/Throwable;)Ljava/lang/Throwable;
    //   2707: athrow
    //   2708: aload #4
    //   2710: getstatic burp/Zsot.Zb : Ljava/lang/String;
    //   2713: getstatic burp/Zsf4.Zr : Ljava/lang/Object;
    //   2716: checkcast java/math/BigInteger
    //   2719: invokevirtual intValue : ()I
    //   2722: bipush #32
    //   2724: irem
    //   2725: invokestatic abs : (I)I
    //   2728: invokevirtual charAt : (I)C
    //   2731: invokevirtual append : (C)Ljava/lang/StringBuilder;
    //   2734: pop
    //   2735: iload_2
    //   2736: ifeq -> 3160
    //   2739: goto -> 2746
    //   2742: invokestatic a : (Ljava/lang/Throwable;)Ljava/lang/Throwable;
    //   2745: athrow
    //   2746: aload #4
    //   2748: getstatic burp/Zmh0.Zs : Ljava/lang/String;
    //   2751: getstatic burp/Zt5a.Zs : Ljava/lang/Object;
    //   2754: checkcast java/math/BigInteger
    //   2757: invokevirtual intValue : ()I
    //   2760: bipush #32
    //   2762: irem
    //   2763: invokestatic abs : (I)I
    //   2766: invokevirtual charAt : (I)C
    //   2769: invokevirtual append : (C)Ljava/lang/StringBuilder;
    //   2772: pop
    //   2773: iload_2
    //   2774: ifeq -> 3160
    //   2777: goto -> 2784
    //   2780: invokestatic a : (Ljava/lang/Throwable;)Ljava/lang/Throwable;
    //   2783: athrow
    //   2784: aload #4
    //   2786: getstatic burp/Zm5s.Z_ : Ljava/lang/String;
    //   2789: getstatic burp/Zmly.ZT : Ljava/lang/Object;
    //   2792: checkcast java/math/BigInteger
    //   2795: invokevirtual intValue : ()I
    //   2798: bipush #32
    //   2800: irem
    //   2801: invokestatic abs : (I)I
    //   2804: invokevirtual charAt : (I)C
    //   2807: invokevirtual append : (C)Ljava/lang/StringBuilder;
    //   2810: pop
    //   2811: iload_2
    //   2812: ifeq -> 3160
    //   2815: goto -> 2822
    //   2818: invokestatic a : (Ljava/lang/Throwable;)Ljava/lang/Throwable;
    //   2821: athrow
    //   2822: aload #4
    //   2824: getstatic burp/Zl6z.ZL : Ljava/lang/String;
    //   2827: getstatic burp/Zrct.ZV : Ljava/lang/Object;
    //   2830: checkcast java/math/BigInteger
    //   2833: invokevirtual intValue : ()I
    //   2836: bipush #32
    //   2838: irem
    //   2839: invokestatic abs : (I)I
    //   2842: invokevirtual charAt : (I)C
    //   2845: invokevirtual append : (C)Ljava/lang/StringBuilder;
    //   2848: pop
    //   2849: iload_2
    //   2850: ifeq -> 3160
    //   2853: goto -> 2860
    //   2856: invokestatic a : (Ljava/lang/Throwable;)Ljava/lang/Throwable;
    //   2859: athrow
    //   2860: aload #4
    //   2862: getstatic burp/Zkc5.ZH : Ljava/lang/String;
    //   2865: getstatic burp/Zmfw.ZS : Ljava/lang/Object;
    //   2868: checkcast java/math/BigInteger
    //   2871: invokevirtual intValue : ()I
    //   2874: bipush #32
    //   2876: irem
    //   2877: invokestatic abs : (I)I
    //   2880: invokevirtual charAt : (I)C
    //   2883: invokevirtual append : (C)Ljava/lang/StringBuilder;
    //   2886: pop
    //   2887: iload_2
    //   2888: ifeq -> 3160
    //   2891: goto -> 2898
    //   2894: invokestatic a : (Ljava/lang/Throwable;)Ljava/lang/Throwable;
    //   2897: athrow
    //   2898: aload #4
    //   2900: getstatic burp/Zg5.ZF : Ljava/lang/String;
    //   2903: getstatic burp/Zmfw.ZS : Ljava/lang/Object;
    //   2906: checkcast java/math/BigInteger
    //   2909: invokevirtual intValue : ()I
    //   2912: bipush #32
    //   2914: irem
    //   2915: invokestatic abs : (I)I
    //   2918: invokevirtual charAt : (I)C
    //   2921: invokevirtual append : (C)Ljava/lang/StringBuilder;
    //   2924: pop
    //   2925: iload_2
    //   2926: ifeq -> 3160
    //   2929: goto -> 2936
    //   2932: invokestatic a : (Ljava/lang/Throwable;)Ljava/lang/Throwable;
    //   2935: athrow
    //   2936: aload #4
    //   2938: getstatic burp/Ztdg.ZS : Ljava/lang/String;
    //   2941: getstatic burp/Zth8.Zk : Ljava/lang/Object;
    //   2944: checkcast java/math/BigInteger
    //   2947: invokevirtual intValue : ()I
    //   2950: bipush #32
    //   2952: irem
    //   2953: invokestatic abs : (I)I
    //   2956: invokevirtual charAt : (I)C
    //   2959: invokevirtual append : (C)Ljava/lang/StringBuilder;
    //   2962: pop
    //   2963: iload_2
    //   2964: ifeq -> 3160
    //   2967: goto -> 2974
    //   2970: invokestatic a : (Ljava/lang/Throwable;)Ljava/lang/Throwable;
    //   2973: athrow
    //   2974: aload #4
    //   2976: getstatic burp/Zeqw.Zw : Ljava/lang/String;
    //   2979: getstatic burp/Zrh1.ZF : Ljava/lang/Object;
    //   2982: checkcast java/math/BigInteger
    //   2985: invokevirtual intValue : ()I
    //   2988: bipush #32
    //   2990: irem
    //   2991: invokestatic abs : (I)I
    //   2994: invokevirtual charAt : (I)C
    //   2997: invokevirtual append : (C)Ljava/lang/StringBuilder;
    //   3000: pop
    //   3001: iload_2
    //   3002: ifeq -> 3160
    //   3005: goto -> 3012
    //   3008: invokestatic a : (Ljava/lang/Throwable;)Ljava/lang/Throwable;
    //   3011: athrow
    //   3012: aload #4
    //   3014: getstatic burp/Zl8s.Zn : Ljava/lang/String;
    //   3017: getstatic burp/Zlhu.ZJ : Ljava/lang/Object;
    //   3020: checkcast java/math/BigInteger
    //   3023: invokevirtual intValue : ()I
    //   3026: bipush #32
    //   3028: irem
    //   3029: invokestatic abs : (I)I
    //   3032: invokevirtual charAt : (I)C
    //   3035: invokevirtual append : (C)Ljava/lang/StringBuilder;
    //   3038: pop
    //   3039: iload_2
    //   3040: ifeq -> 3160
    //   3043: goto -> 3050
    //   3046: invokestatic a : (Ljava/lang/Throwable;)Ljava/lang/Throwable;
    //   3049: athrow
    //   3050: aload #4
    //   3052: getstatic burp/Zlvx.Zr : Ljava/lang/String;
    //   3055: getstatic burp/Zrp3.Zd : Ljava/lang/Object;
    //   3058: checkcast java/math/BigInteger
    //   3061: invokevirtual intValue : ()I
    //   3064: bipush #32
    //   3066: irem
    //   3067: invokestatic abs : (I)I
    //   3070: invokevirtual charAt : (I)C
    //   3073: invokevirtual append : (C)Ljava/lang/StringBuilder;
    //   3076: pop
    //   3077: iload_2
    //   3078: ifeq -> 3160
    //   3081: goto -> 3088
    //   3084: invokestatic a : (Ljava/lang/Throwable;)Ljava/lang/Throwable;
    //   3087: athrow
    //   3088: aload #4
    //   3090: getstatic burp/Zeqw.Zw : Ljava/lang/String;
    //   3093: getstatic burp/Zrxf.ZS : Ljava/lang/Object;
    //   3096: checkcast java/math/BigInteger
    //   3099: invokevirtual intValue : ()I
    //   3102: bipush #32
    //   3104: irem
    //   3105: invokestatic abs : (I)I
    //   3108: invokevirtual charAt : (I)C
    //   3111: invokevirtual append : (C)Ljava/lang/StringBuilder;
    //   3114: pop
    //   3115: iload_2
    //   3116: ifeq -> 3160
    //   3119: goto -> 3126
    //   3122: invokestatic a : (Ljava/lang/Throwable;)Ljava/lang/Throwable;
    //   3125: athrow
    //   3126: aload #4
    //   3128: getstatic burp/Zkfb.ZV : Ljava/lang/String;
    //   3131: getstatic burp/Zs5i.ZD : Ljava/lang/Object;
    //   3134: checkcast java/math/BigInteger
    //   3137: invokevirtual intValue : ()I
    //   3140: bipush #32
    //   3142: irem
    //   3143: invokestatic abs : (I)I
    //   3146: invokevirtual charAt : (I)C
    //   3149: invokevirtual append : (C)Ljava/lang/StringBuilder;
    //   3152: pop
    //   3153: goto -> 3160
    //   3156: invokestatic a : (Ljava/lang/Throwable;)Ljava/lang/Throwable;
    //   3159: athrow
    //   3160: iinc #5, 1
    //   3163: iload_2
    //   3164: ifeq -> 1795
    //   3167: aload #4
    //   3169: invokevirtual toString : ()Ljava/lang/String;
    //   3172: putstatic burp/Zmh0.Zs : Ljava/lang/String;
    //   3175: sipush #-29439
    //   3178: sipush #9148
    //   3181: invokestatic a : (II)Ljava/lang/String;
    //   3184: iconst_1
    //   3185: ldc burp/Zlw8
    //   3187: invokevirtual getClassLoader : ()Ljava/lang/ClassLoader;
    //   3190: invokestatic forName : (Ljava/lang/String;ZLjava/lang/ClassLoader;)Ljava/lang/Class;
    //   3193: invokevirtual getDeclaredFields : ()[Ljava/lang/reflect/Field;
    //   3196: astore #5
    //   3198: aload #5
    //   3200: arraylength
    //   3201: istore #6
    //   3203: iconst_0
    //   3204: istore #7
    //   3206: iload #7
    //   3208: iload #6
    //   3210: if_icmpge -> 3348
    //   3213: aload #5
    //   3215: iload #7
    //   3217: aaload
    //   3218: astore #8
    //   3220: aload #8
    //   3222: invokevirtual getModifiers : ()I
    //   3225: invokestatic isStatic : (I)Z
    //   3228: ifne -> 3238
    //   3231: goto -> 3341
    //   3234: invokestatic a : (Ljava/lang/Throwable;)Ljava/lang/Throwable;
    //   3237: athrow
    //   3238: aload #8
    //   3240: invokevirtual getType : ()Ljava/lang/Class;
    //   3243: astore #9
    //   3245: aload #9
    //   3247: ifnull -> 3328
    //   3250: aload #9
    //   3252: invokevirtual isPrimitive : ()Z
    //   3255: ifne -> 3328
    //   3258: goto -> 3265
    //   3261: invokestatic a : (Ljava/lang/Throwable;)Ljava/lang/Throwable;
    //   3264: athrow
    //   3265: aload #9
    //   3267: invokevirtual getPackage : ()Ljava/lang/Package;
    //   3270: ifnull -> 3328
    //   3273: goto -> 3280
    //   3276: invokestatic a : (Ljava/lang/Throwable;)Ljava/lang/Throwable;
    //   3279: athrow
    //   3280: aload #9
    //   3282: invokevirtual getPackage : ()Ljava/lang/Package;
    //   3285: invokevirtual getName : ()Ljava/lang/String;
    //   3288: ifnull -> 3328
    //   3291: goto -> 3298
    //   3294: invokestatic a : (Ljava/lang/Throwable;)Ljava/lang/Throwable;
    //   3297: athrow
    //   3298: aload #9
    //   3300: invokevirtual getPackage : ()Ljava/lang/Package;
    //   3303: invokevirtual getName : ()Ljava/lang/String;
    //   3306: sipush #-29436
    //   3309: sipush #7564
    //   3312: invokestatic a : (II)Ljava/lang/String;
    //   3315: invokevirtual startsWith : (Ljava/lang/String;)Z
    //   3318: ifne -> 3328
    //   3321: goto -> 3328
    //   3324: invokestatic a : (Ljava/lang/Throwable;)Ljava/lang/Throwable;
    //   3327: athrow
    //   3328: aload #8
    //   3330: iconst_1
    //   3331: invokevirtual setAccessible : (Z)V
    //   3334: aload #8
    //   3336: aconst_null
    //   3337: invokevirtual get : (Ljava/lang/Object;)Ljava/lang/Object;
    //   3340: pop
    //   3341: iinc #7, 1
    //   3344: iload_2
    //   3345: ifeq -> 3206
    //   3348: sipush #-29433
    //   3351: sipush #-28947
    //   3354: invokestatic a : (II)Ljava/lang/String;
    //   3357: invokestatic forName : (Ljava/lang/String;)Ljava/lang/Class;
    //   3360: invokevirtual getDeclaredMethods : ()[Ljava/lang/reflect/Method;
    //   3363: astore #5
    //   3365: aload #5
    //   3367: arraylength
    //   3368: istore #6
    //   3370: iconst_0
    //   3371: istore #7
    //   3373: iload #7
    //   3375: iload #6
    //   3377: if_icmpge -> 3510
    //   3380: aload #5
    //   3382: iload #7
    //   3384: aaload
    //   3385: astore #8
    //   3387: aload #8
    //   3389: invokevirtual getParameterTypes : ()[Ljava/lang/Class;
    //   3392: pop
    //   3393: aload #8
    //   3395: invokevirtual getModifiers : ()I
    //   3398: invokestatic isStatic : (I)Z
    //   3401: ifeq -> 3496
    //   3404: aload #8
    //   3406: invokevirtual getParameterTypes : ()[Ljava/lang/Class;
    //   3409: arraylength
    //   3410: iconst_2
    //   3411: if_icmpne -> 3496
    //   3414: goto -> 3421
    //   3417: invokestatic a : (Ljava/lang/Throwable;)Ljava/lang/Throwable;
    //   3420: athrow
    //   3421: aload #8
    //   3423: invokevirtual getReturnType : ()Ljava/lang/Class;
    //   3426: getstatic java/lang/Void.TYPE : Ljava/lang/Class;
    //   3429: invokevirtual equals : (Ljava/lang/Object;)Z
    //   3432: ifeq -> 3496
    //   3435: goto -> 3442
    //   3438: invokestatic a : (Ljava/lang/Throwable;)Ljava/lang/Throwable;
    //   3441: athrow
    //   3442: aload #8
    //   3444: iconst_1
    //   3445: invokevirtual setAccessible : (Z)V
    //   3448: aload #8
    //   3450: aconst_null
    //   3451: iconst_2
    //   3452: anewarray java/lang/Object
    //   3455: dup
    //   3456: iconst_0
    //   3457: aload_0
    //   3458: aastore
    //   3459: dup
    //   3460: iconst_1
    //   3461: aload_1
    //   3462: ifnonnull -> 3480
    //   3465: goto -> 3472
    //   3468: invokestatic a : (Ljava/lang/Throwable;)Ljava/lang/Throwable;
    //   3471: athrow
    //   3472: aload_1
    //   3473: goto -> 3487
    //   3476: invokestatic a : (Ljava/lang/Throwable;)Ljava/lang/Throwable;
    //   3479: athrow
    //   3480: aload_1
    //   3481: checkcast [B
    //   3484: invokevirtual clone : ()Ljava/lang/Object;
    //   3487: aastore
    //   3488: invokevirtual invoke : (Ljava/lang/Object;[Ljava/lang/Object;)Ljava/lang/Object;
    //   3491: pop
    //   3492: iload_2
    //   3493: ifeq -> 3510
    //   3496: iinc #7, 1
    //   3499: iload_2
    //   3500: ifeq -> 3373
    //   3503: goto -> 3510
    //   3506: invokestatic a : (Ljava/lang/Throwable;)Ljava/lang/Throwable;
    //   3509: athrow
    //   3510: getstatic burp/Zg1k.Ze : Ljava/lang/String;
    //   3513: getstatic burp/Zms1.ZE : Ljava/lang/Object;
    //   3516: checkcast java/math/BigInteger
    //   3519: invokevirtual intValue : ()I
    //   3522: bipush #32
    //   3524: irem
    //   3525: invokestatic abs : (I)I
    //   3528: invokevirtual charAt : (I)C
    //   3531: getstatic burp/Zzhu.ZT : Ljava/lang/String;
    //   3534: getstatic burp/Zeai.ZI : Ljava/lang/Object;
    //   3537: checkcast java/math/BigInteger
    //   3540: invokevirtual intValue : ()I
    //   3543: bipush #32
    //   3545: irem
    //   3546: invokestatic abs : (I)I
    //   3549: invokevirtual charAt : (I)C
    //   3552: if_icmple -> 3659
    //   3555: getstatic burp/Ztpg.Zr : Ljava/lang/String;
    //   3558: getstatic burp/Zb8_.ZT : Ljava/lang/Object;
    //   3561: checkcast java/math/BigInteger
    //   3564: invokevirtual intValue : ()I
    //   3567: bipush #32
    //   3569: irem
    //   3570: invokestatic abs : (I)I
    //   3573: invokevirtual charAt : (I)C
    //   3576: getstatic burp/Ze_e.ZH : Ljava/lang/String;
    //   3579: getstatic burp/Zeqw.ZV : Ljava/lang/Object;
    //   3582: checkcast java/math/BigInteger
    //   3585: invokevirtual intValue : ()I
    //   3588: bipush #32
    //   3590: irem
    //   3591: invokestatic abs : (I)I
    //   3594: invokevirtual charAt : (I)C
    //   3597: if_icmpgt -> 3659
    //   3600: goto -> 3607
    //   3603: invokestatic a : (Ljava/lang/Throwable;)Ljava/lang/Throwable;
    //   3606: athrow
    //   3607: getstatic burp/Zeai.ZA : Ljava/lang/String;
    //   3610: getstatic burp/Zktq.Zn : Ljava/lang/Object;
    //   3613: checkcast java/math/BigInteger
    //   3616: invokevirtual intValue : ()I
    //   3619: bipush #32
    //   3621: irem
    //   3622: invokestatic abs : (I)I
    //   3625: invokevirtual charAt : (I)C
    //   3628: getstatic burp/Zzhu.ZT : Ljava/lang/String;
    //   3631: getstatic burp/Zr4z.ZH : Ljava/lang/Object;
    //   3634: checkcast java/math/BigInteger
    //   3637: invokevirtual intValue : ()I
    //   3640: bipush #32
    //   3642: irem
    //   3643: invokestatic abs : (I)I
    //   3646: invokevirtual charAt : (I)C
    //   3649: if_icmple -> 3667
    //   3652: goto -> 3659
    //   3655: invokestatic a : (Ljava/lang/Throwable;)Ljava/lang/Throwable;
    //   3658: athrow
    //   3659: iconst_1
    //   3660: goto -> 3668
    //   3663: invokestatic a : (Ljava/lang/Throwable;)Ljava/lang/Throwable;
    //   3666: athrow
    //   3667: iconst_0
    //   3668: ireturn
    //   3669: astore_3
    //   3670: new java/lang/Exception
    //   3673: dup
    //   3674: aload_3
    //   3675: invokevirtual getMessage : ()Ljava/lang/String;
    //   3678: invokespecial <init> : (Ljava/lang/String;)V
    //   3681: athrow
    // Exception table:
    //   from	to	target	type
    //   4	3668	3669	java/lang/Throwable
    //   22	198	201	java/lang/Throwable
    //   168	235	238	java/lang/Throwable
    //   205	272	275	java/lang/Throwable
    //   242	309	312	java/lang/Throwable
    //   279	346	349	java/lang/Throwable
    //   316	383	386	java/lang/Throwable
    //   353	420	423	java/lang/Throwable
    //   390	457	460	java/lang/Throwable
    //   427	494	497	java/lang/Throwable
    //   464	531	534	java/lang/Throwable
    //   501	568	571	java/lang/Throwable
    //   538	605	608	java/lang/Throwable
    //   575	642	645	java/lang/Throwable
    //   612	679	682	java/lang/Throwable
    //   649	716	719	java/lang/Throwable
    //   686	753	756	java/lang/Throwable
    //   723	790	793	java/lang/Throwable
    //   760	827	830	java/lang/Throwable
    //   797	864	867	java/lang/Throwable
    //   834	901	904	java/lang/Throwable
    //   871	938	941	java/lang/Throwable
    //   908	975	978	java/lang/Throwable
    //   945	1012	1015	java/lang/Throwable
    //   982	1049	1052	java/lang/Throwable
    //   1019	1086	1089	java/lang/Throwable
    //   1056	1123	1126	java/lang/Throwable
    //   1093	1160	1163	java/lang/Throwable
    //   1130	1197	1200	java/lang/Throwable
    //   1167	1234	1237	java/lang/Throwable
    //   1204	1271	1274	java/lang/Throwable
    //   1241	1308	1311	java/lang/Throwable
    //   1278	1341	1344	java/lang/Throwable
    //   1554	1582	1585	java/lang/Throwable
    //   1564	1599	1602	java/lang/Throwable
    //   1589	1627	1630	java/lang/Throwable
    //   1606	1644	1647	java/lang/Throwable
    //   1634	1672	1675	java/lang/Throwable
    //   1651	1689	1692	java/lang/Throwable
    //   1679	1707	1710	java/lang/Throwable
    //   1696	1721	1724	java/lang/Throwable
    //   1802	1979	1982	java/lang/Throwable
    //   1948	2017	2020	java/lang/Throwable
    //   1986	2055	2058	java/lang/Throwable
    //   2024	2093	2096	java/lang/Throwable
    //   2062	2131	2134	java/lang/Throwable
    //   2100	2169	2172	java/lang/Throwable
    //   2138	2207	2210	java/lang/Throwable
    //   2176	2245	2248	java/lang/Throwable
    //   2214	2283	2286	java/lang/Throwable
    //   2252	2321	2324	java/lang/Throwable
    //   2290	2359	2362	java/lang/Throwable
    //   2328	2397	2400	java/lang/Throwable
    //   2366	2435	2438	java/lang/Throwable
    //   2404	2473	2476	java/lang/Throwable
    //   2442	2511	2514	java/lang/Throwable
    //   2480	2549	2552	java/lang/Throwable
    //   2518	2587	2590	java/lang/Throwable
    //   2556	2625	2628	java/lang/Throwable
    //   2594	2663	2666	java/lang/Throwable
    //   2632	2701	2704	java/lang/Throwable
    //   2670	2739	2742	java/lang/Throwable
    //   2708	2777	2780	java/lang/Throwable
    //   2746	2815	2818	java/lang/Throwable
    //   2784	2853	2856	java/lang/Throwable
    //   2822	2891	2894	java/lang/Throwable
    //   2860	2929	2932	java/lang/Throwable
    //   2898	2967	2970	java/lang/Throwable
    //   2936	3005	3008	java/lang/Throwable
    //   2974	3043	3046	java/lang/Throwable
    //   3012	3081	3084	java/lang/Throwable
    //   3050	3119	3122	java/lang/Throwable
    //   3088	3153	3156	java/lang/Throwable
    //   3220	3234	3234	java/lang/Throwable
    //   3245	3258	3261	java/lang/Throwable
    //   3250	3273	3276	java/lang/Throwable
    //   3265	3291	3294	java/lang/Throwable
    //   3280	3321	3324	java/lang/Throwable
    //   3387	3414	3417	java/lang/Throwable
    //   3404	3435	3438	java/lang/Throwable
    //   3421	3465	3468	java/lang/Throwable
    //   3442	3476	3476	java/lang/Throwable
    //   3487	3503	3506	java/lang/Throwable
    //   3510	3600	3603	java/lang/Throwable
    //   3555	3652	3655	java/lang/Throwable
    //   3607	3663	3663	java/lang/Throwable
  }
  
  static void ZJ(Object paramObject) {
    Ztg3.ZM = a(-29440, 4831);
    Ztg3.Zg = new BigInteger(a(-29435, -9211));
    boolean bool = Zt2e.ZK();
    try {
      try {
        if (Zl5.ZE.charAt(Math.abs(((BigInteger)Zml2.Zo).intValue() % 32)) <= Zr4z.Zw.charAt(Math.abs(((BigInteger)Zzxa.ZI).intValue() % 32))) {
          try {
            Zr8r.ZA(Class.forName(a(-29434, 9303)));
            if (bool)
              Zrxf.Zh(Class.forName(a(-29438, 23811))); 
          } catch (Throwable throwable) {
            throw a(null);
          } 
          return;
        } 
      } catch (Throwable throwable) {
        throw a(null);
      } 
      Zrxf.Zh(Class.forName(a(-29438, 23811)));
    } catch (Throwable throwable) {}
  }
  
  static {
    // Byte code:
    //   0: bipush #8
    //   2: anewarray java/lang/String
    //   5: astore #5
    //   7: iconst_0
    //   8: istore_3
    //   9: ldc '5R}%`+0*d7BhH&"\\t=\\t^\WY N9}|M.Q]4-kHRS\\t'0!B \\tDF\db4'
    //   11: dup
    //   12: astore_2
    //   13: invokevirtual length : ()I
    //   16: istore #4
    //   18: bipush #32
    //   20: istore_1
    //   21: iconst_m1
    //   22: istore_0
    //   23: bipush #69
    //   25: iinc #0, 1
    //   28: aload_2
    //   29: iload_0
    //   30: dup
    //   31: iload_1
    //   32: iadd
    //   33: invokevirtual substring : (II)Ljava/lang/String;
    //   36: iconst_m1
    //   37: goto -> 143
    //   40: aload #5
    //   42: swap
    //   43: iload_3
    //   44: iinc #3, 1
    //   47: swap
    //   48: aastore
    //   49: iload_0
    //   50: iload_1
    //   51: iadd
    //   52: dup
    //   53: istore_0
    //   54: iload #4
    //   56: if_icmpge -> 68
    //   59: aload_2
    //   60: iload_0
    //   61: invokevirtual charAt : (I)C
    //   64: istore_1
    //   65: goto -> 23
    //   68: ldc '"PAAWj%nM6JC!ZI}o:N\\tln8IQ#ISRrd"'
    //   70: dup
    //   71: astore_2
    //   72: invokevirtual length : ()I
    //   75: istore #4
    //   77: bipush #76
    //   79: istore_1
    //   80: iconst_m1
    //   81: istore_0
    //   82: bipush #18
    //   84: iinc #0, 1
    //   87: aload_2
    //   88: iload_0
    //   89: dup
    //   90: iload_1
    //   91: iadd
    //   92: invokevirtual substring : (II)Ljava/lang/String;
    //   95: iconst_0
    //   96: goto -> 143
    //   99: aload #5
    //   101: swap
    //   102: iload_3
    //   103: iinc #3, 1
    //   106: swap
    //   107: aastore
    //   108: iload_0
    //   109: iload_1
    //   110: iadd
    //   111: dup
    //   112: istore_0
    //   113: iload #4
    //   115: if_icmpge -> 127
    //   118: aload_2
    //   119: iload_0
    //   120: invokevirtual charAt : (I)C
    //   123: istore_1
    //   124: goto -> 82
    //   127: aload #5
    //   129: putstatic burp/Zszm.a : [Ljava/lang/String;
    //   132: bipush #8
    //   134: anewarray java/lang/String
    //   137: putstatic burp/Zszm.b : [Ljava/lang/String;
    //   140: goto -> 300
    //   143: dup_x2
    //   144: pop
    //   145: invokevirtual toCharArray : ()[C
    //   148: dup_x1
    //   149: arraylength
    //   150: dup_x2
    //   151: pop
    //   152: iconst_0
    //   153: istore #6
    //   155: dup2_x1
    //   156: pop2
    //   157: dup_x2
    //   158: iconst_1
    //   159: if_icmpgt -> 258
    //   162: dup2
    //   163: swap
    //   164: iload #6
    //   166: dup2_x1
    //   167: caload
    //   168: swap
    //   169: iload #6
    //   171: bipush #7
    //   173: irem
    //   174: tableswitch default -> 240, 0 -> 212, 1 -> 216, 2 -> 221, 3 -> 225, 4 -> 230, 5 -> 235
    //   212: iconst_3
    //   213: goto -> 242
    //   216: bipush #91
    //   218: goto -> 242
    //   221: iconst_5
    //   222: goto -> 242
    //   225: bipush #32
    //   227: goto -> 242
    //   230: bipush #120
    //   232: goto -> 242
    //   235: bipush #17
    //   237: goto -> 242
    //   240: bipush #104
    //   242: ixor
    //   243: ixor
    //   244: i2c
    //   245: castore
    //   246: iinc #6, 1
    //   249: dup
    //   250: ifne -> 258
    //   253: dup2
    //   254: dup_x1
    //   255: goto -> 166
    //   258: dup2_x1
    //   259: pop2
    //   260: dup_x2
    //   261: iload #6
    //   263: if_icmpgt -> 162
    //   266: pop
    //   267: new java/lang/String
    //   270: dup_x1
    //   271: swap
    //   272: invokespecial <init> : ([C)V
    //   275: invokevirtual intern : ()Ljava/lang/String;
    //   278: swap
    //   279: pop
    //   280: swap
    //   281: tableswitch default -> 40, 0 -> 99
    //   300: new java/math/BigInteger
    //   303: dup
    //   304: bipush #32
    //   306: newarray byte
    //   308: dup
    //   309: iconst_0
    //   310: bipush #38
    //   312: bastore
    //   313: dup
    //   314: iconst_1
    //   315: bipush #-24
    //   317: bastore
    //   318: dup
    //   319: iconst_2
    //   320: bipush #113
    //   322: bastore
    //   323: dup
    //   324: iconst_3
    //   325: bipush #-57
    //   327: bastore
    //   328: dup
    //   329: iconst_4
    //   330: bipush #-39
    //   332: bastore
    //   333: dup
    //   334: iconst_5
    //   335: bipush #-67
    //   337: bastore
    //   338: dup
    //   339: bipush #6
    //   341: bipush #68
    //   343: bastore
    //   344: dup
    //   345: bipush #7
    //   347: bipush #76
    //   349: bastore
    //   350: dup
    //   351: bipush #8
    //   353: bipush #28
    //   355: bastore
    //   356: dup
    //   357: bipush #9
    //   359: bipush #55
    //   361: bastore
    //   362: dup
    //   363: bipush #10
    //   365: bipush #-69
    //   367: bastore
    //   368: dup
    //   369: bipush #11
    //   371: bipush #-114
    //   373: bastore
    //   374: dup
    //   375: bipush #12
    //   377: bipush #-59
    //   379: bastore
    //   380: dup
    //   381: bipush #13
    //   383: bipush #-112
    //   385: bastore
    //   386: dup
    //   387: bipush #14
    //   389: bipush #-10
    //   391: bastore
    //   392: dup
    //   393: bipush #15
    //   395: bipush #98
    //   397: bastore
    //   398: dup
    //   399: bipush #16
    //   401: bipush #61
    //   403: bastore
    //   404: dup
    //   405: bipush #17
    //   407: bipush #92
    //   409: bastore
    //   410: dup
    //   411: bipush #18
    //   413: bipush #-32
    //   415: bastore
    //   416: dup
    //   417: bipush #19
    //   419: iconst_1
    //   420: bastore
    //   421: dup
    //   422: bipush #20
    //   424: bipush #-51
    //   426: bastore
    //   427: dup
    //   428: bipush #21
    //   430: bipush #22
    //   432: bastore
    //   433: dup
    //   434: bipush #22
    //   436: bipush #-35
    //   438: bastore
    //   439: dup
    //   440: bipush #23
    //   442: bipush #-17
    //   444: bastore
    //   445: dup
    //   446: bipush #24
    //   448: bipush #36
    //   450: bastore
    //   451: dup
    //   452: bipush #25
    //   454: bipush #55
    //   456: bastore
    //   457: dup
    //   458: bipush #26
    //   460: bipush #-94
    //   462: bastore
    //   463: dup
    //   464: bipush #27
    //   466: bipush #-13
    //   468: bastore
    //   469: dup
    //   470: bipush #28
    //   472: bipush #100
    //   474: bastore
    //   475: dup
    //   476: bipush #29
    //   478: bipush #111
    //   480: bastore
    //   481: dup
    //   482: bipush #30
    //   484: bipush #61
    //   486: bastore
    //   487: dup
    //   488: bipush #31
    //   490: bipush #-96
    //   492: bastore
    //   493: invokespecial <init> : ([B)V
    //   496: putstatic burp/Zszm.ZI : Ljava/lang/Object;
    //   499: sipush #-29437
    //   502: sipush #-30200
    //   505: invokestatic a : (II)Ljava/lang/String;
    //   508: putstatic burp/Zszm.Zf : Ljava/lang/String;
    //   511: return
  }
  
  private static Throwable a(Throwable paramThrowable) {
    return paramThrowable;
  }
  
  private static String a(int paramInt1, int paramInt2) {
    int i = (paramInt1 ^ 0xFFFF8D03) & 0xFFFF;
    if (b[i] == null) {
      char[] arrayOfChar = a[i].toCharArray();
      switch (arrayOfChar[0] & 0xFF) {
        case 0:
        
        case 1:
        
        case 2:
        
        case 3:
        
        case 4:
        
        case 5:
        
        case 6:
        
        case 7:
        
        case 8:
        
        case 9:
        
        case 10:
        
        case 11:
        
        case 12:
        
        case 13:
        
        case 14:
        
        case 15:
        
        case 16:
        
        case 17:
        
        case 18:
        
        case 19:
        
        case 20:
        
        case 21:
        
        case 22:
        
        case 23:
        
        case 24:
        
        case 25:
        
        case 26:
        
        case 27:
        
        case 28:
        
        case 29:
        
        case 30:
        
        case 31:
        
        case 32:
        
        case 33:
        
        case 34:
        
        case 35:
        
        case 36:
        
        case 37:
        
        case 38:
        
        case 39:
        
        case 40:
        
        case 41:
        
        case 42:
        
        case 43:
        
        case 44:
        
        case 45:
        
        case 46:
        
        case 47:
        
        case 48:
        
        case 49:
        
        case 50:
        
        case 51:
        
        case 52:
        
        case 53:
        
        case 54:
        
        case 55:
        
        case 56:
        
        case 57:
        
        case 58:
        
        case 59:
        
        case 60:
        
        case 61:
        
        case 62:
        
        case 63:
        
        case 64:
        
        case 65:
        
        case 66:
        
        case 67:
        
        case 68:
        
        case 69:
        
        case 70:
        
        case 71:
        
        case 72:
        
        case 73:
        
        case 74:
        
        case 75:
        
        case 76:
        
        case 77:
        
        case 78:
        
        case 79:
        
        case 80:
        
        case 81:
        
        case 82:
        
        case 83:
        
        case 84:
        
        case 85:
        
        case 86:
        
        case 87:
        
        case 88:
        
        case 89:
        
        case 90:
        
        case 91:
        
        case 92:
        
        case 93:
        
        case 94:
        
        case 95:
        
        case 96:
        
        case 97:
        
        case 98:
        
        case 99:
        
        case 100:
        
        case 101:
        
        case 102:
        
        case 103:
        
        case 104:
        
        case 105:
        
        case 106:
        
        case 107:
        
        case 108:
        
        case 109:
        
        case 110:
        
        case 111:
        
        case 112:
        
        case 113:
        
        case 114:
        
        case 115:
        
        case 116:
        
        case 117:
        
        case 118:
        
        case 119:
        
        case 120:
        
        case 121:
        
        case 122:
        
        case 123:
        
        case 124:
        
        case 125:
        
        case 126:
        
        case 127:
        
        case 128:
        
        case 129:
        
        case 130:
        
        case 131:
        
        case 132:
        
        case 133:
        
        case 134:
        
        case 135:
        
        case 136:
        
        case 137:
        
        case 138:
        
        case 139:
        
        case 140:
        
        case 141:
        
        case 142:
        
        case 143:
        
        case 144:
        
        case 145:
        
        case 146:
        
        case 147:
        
        case 148:
        
        case 149:
        
        case 150:
        
        case 151:
        
        case 152:
        
        case 153:
        
        case 154:
        
        case 155:
        
        case 156:
        
        case 157:
        
        case 158:
        
        case 159:
        
        case 160:
        
        case 161:
        
        case 162:
        
        case 163:
        
        case 164:
        
        case 165:
        
        case 166:
        
        case 167:
        
        case 168:
        
        case 169:
        
        case 170:
        
        case 171:
        
        case 172:
        
        case 173:
        
        case 174:
        
        case 175:
        
        case 176:
        
        case 177:
        
        case 178:
        
        case 179:
        
        case 180:
        
        case 181:
        
        case 182:
        
        case 183:
        
        case 184:
        
        case 185:
        
        case 186:
        
        case 187:
        
        case 188:
        
        case 189:
        
        case 190:
        
        case 191:
        
        case 192:
        
        case 193:
        
        case 194:
        
        case 195:
        
        case 196:
        
        case 197:
        
        case 198:
        
        case 199:
        
        case 200:
        
        case 201:
        
        case 202:
        
        case 203:
        
        case 204:
        
        case 205:
        
        case 206:
        
        case 207:
        
        case 208:
        
        case 209:
        
        case 210:
        
        case 211:
        
        case 212:
        
        case 213:
        
        case 214:
        
        case 215:
        
        case 216:
        
        case 217:
        
        case 218:
        
        case 219:
        
        case 220:
        
        case 221:
        
        case 222:
        
        case 223:
        
        case 224:
        
        case 225:
        
        case 226:
        
        case 227:
        
        case 228:
        
        case 229:
        
        case 230:
        
        case 231:
        
        case 232:
        
        case 233:
        
        case 234:
        
        case 235:
        
        case 236:
        
        case 237:
        
        case 238:
        
        case 239:
        
        case 240:
        
        case 241:
        
        case 242:
        
        case 243:
        
        case 244:
        
        case 245:
        
        case 246:
        
        case 247:
        
        case 248:
        
        case 249:
        
        case 250:
        
        case 251:
        
        case 252:
        
        case 253:
        
        case 254:
        
        default:
          break;
      } 
      byte b1 = 21;
      int j = (paramInt2 & 0xFF) - b1;
      if (j < 0)
        j += 256; 
      int k = ((paramInt2 & 0xFFFF) >>> 8) - b1;
      if (k < 0)
        k += 256; 
      for (byte b2 = 0; b2 < arrayOfChar.length; b2++) {
        int m = b2 % 2;
        if (m == 0) {
          arrayOfChar[b2] = (char)(arrayOfChar[b2] ^ j);
          j = ((j >>> 3 | j << 5) ^ arrayOfChar[b2]) & 0xFF;
        } else {
          arrayOfChar[b2] = (char)(arrayOfChar[b2] ^ k);
          k = ((k >>> 3 | k << 5) ^ arrayOfChar[b2]) & 0xFF;
        } 
      } 
      b[i] = (new String(arrayOfChar)).intern();
    } 
    return b[i];
  }
}


/* Location:              C:\Program Files\BurpSuitePro\burpsuite_pro.jar!\burp\Zszm.class
 * Java compiler version: 21 (65.0)
 * JD-Core Version:       1.1.3
 */