package burp;

public class Zt1o extends Zt3y {
  public static final Zlnb<Void> Zv;
  
  public static final Zxr8<Void> Zb;
  
  public static final Zlnb<Void> Zx;
  
  public static final Zxr8<Void> Zg;
  
  public static final Zlnb<Zb6l> ZH;
  
  public static final Zlnb<Void> ZD;
  
  public static final Zxr8<Void> Zf;
  
  public static final Zlnb<Zx5p> ZR;
  
  public static final Zlnb<Ze6e> ZS;
  
  public static final Zlnb<Zl5x> ZG;
  
  public static final Zlnb<Zlj9> Zu;
  
  public static final Zlnb<Zski> Ze;
  
  public static final Zlnb<Zga> Z_;
  
  public static final Zlnb<Zebg> Zt;
  
  public static final Zlnb<Zlj9> Zd;
  
  public static final Zlnb<Zeaa> ZZ;
  
  public static final Zlnb<Zeaa> Zk;
  
  public static final Zlnb<Zeaa> ZT;
  
  public static final Zlnb<String> Zc;
  
  public static final Zlnb<Zx50> ZM;
  
  public static final Zlnb<Zblw> Zq;
  
  private static final Zt1o Zp;
  
  private Zt1o() {
    super((Zlnb<?>[])new Zlnb[] { 
          Zv, Zx, ZH, Zu, Zd, Ze, Zt, ZD, ZR, ZS, 
          ZG, ZZ, Zk, ZT, Zc, Z_, ZM, Zq });
  }
  
  public static Zt1o Zn() {
    return Zp;
  }
  
  public static Zxr8<Zebg> Za(int paramInt1, int paramInt2, int paramInt3, int paramInt4) {
    Zbqc[] arrayOfZbqc = Zx50.Zd();
    if (arrayOfZbqc == null)
      Zbqc.Zr(new Zbqc[3]); 
    return new Zxr8<>(Zt, new Zebg(paramInt1, paramInt2, paramInt3, paramInt4));
  }
  
  public static Zxr8<Zga> Zy(Zga paramZga) {
    return new Zxr8<>(Z_, paramZga);
  }
  
  static {
    // Byte code:
    //   0: bipush #18
    //   2: anewarray java/lang/String
    //   5: astore_0
    //   6: iconst_0
    //   7: istore #4
    //   9: ldc 'NAnDpH+_PrO._cJEiB5_*MUyH)-YRoD3NcYRq\\f(J*MTxEESnT8IcYPy@)_*$MUyH)'BSxS)S!B\\rmN4T:Si@)O=UmE<N+H^ElT8I:_\\r|E9_*Tr\\f<O*ETMUyH)(ENtR5_*MUyH)'_ShDpY!YNiRpO>HAiD9 OR|V1/BD0@(^'X\\rmS2]<ISn\\f(J*MTxE\AdM2[*InR(_*MUyH)>DAnDp\/ELxE\\fESnT8IcMDyD9\\fMUyH)(MIqD9ESnT8Ic_UmD/I+HEy\\tMUyH)"CGMUyH)>^OzS8I=UmE<N+H\\rMUyH)=XAoU8^'
    //   11: dup
    //   12: astore_3
    //   13: invokevirtual length : ()I
    //   16: istore #5
    //   18: bipush #21
    //   20: istore_2
    //   21: iconst_m1
    //   22: istore_1
    //   23: bipush #83
    //   25: iinc #1, 1
    //   28: aload_3
    //   29: iload_1
    //   30: dup
    //   31: iload_2
    //   32: iadd
    //   33: invokevirtual substring : (II)Ljava/lang/String;
    //   36: iconst_m1
    //   37: goto -> 130
    //   40: aload_0
    //   41: swap
    //   42: iload #4
    //   44: iinc #4, 1
    //   47: swap
    //   48: aastore
    //   49: iload_1
    //   50: iload_2
    //   51: iadd
    //   52: dup
    //   53: istore_1
    //   54: iload #5
    //   56: if_icmpge -> 68
    //   59: aload_3
    //   60: iload_1
    //   61: invokevirtual charAt : (I)C
    //   64: istore_2
    //   65: goto -> 23
    //   68: ldc ')1,MsC<!hJ*K:0!!0(?N,!hM1)1,Ms[=!\\f '
    //   70: dup
    //   71: astore_3
    //   72: invokevirtual length : ()I
    //   75: istore #5
    //   77: bipush #18
    //   79: istore_2
    //   80: iconst_m1
    //   81: istore_1
    //   82: bipush #55
    //   84: iinc #1, 1
    //   87: aload_3
    //   88: iload_1
    //   89: dup
    //   90: iload_2
    //   91: iadd
    //   92: invokevirtual substring : (II)Ljava/lang/String;
    //   95: iconst_0
    //   96: goto -> 130
    //   99: aload_0
    //   100: swap
    //   101: iload #4
    //   103: iinc #4, 1
    //   106: swap
    //   107: aastore
    //   108: iload_1
    //   109: iload_2
    //   110: iadd
    //   111: dup
    //   112: istore_1
    //   113: iload #5
    //   115: if_icmpge -> 127
    //   118: aload_3
    //   119: iload_1
    //   120: invokevirtual charAt : (I)C
    //   123: istore_2
    //   124: goto -> 82
    //   127: goto -> 288
    //   130: dup_x2
    //   131: pop
    //   132: invokevirtual toCharArray : ()[C
    //   135: dup_x1
    //   136: arraylength
    //   137: dup_x2
    //   138: pop
    //   139: iconst_0
    //   140: istore #6
    //   142: dup2_x1
    //   143: pop2
    //   144: dup_x2
    //   145: iconst_1
    //   146: if_icmpgt -> 248
    //   149: dup2
    //   150: swap
    //   151: iload #6
    //   153: dup2_x1
    //   154: caload
    //   155: swap
    //   156: iload #6
    //   158: bipush #7
    //   160: irem
    //   161: tableswitch default -> 230, 0 -> 200, 1 -> 205, 2 -> 210, 3 -> 215, 4 -> 220, 5 -> 225
    //   200: bipush #127
    //   202: goto -> 232
    //   205: bipush #115
    //   207: goto -> 232
    //   210: bipush #78
    //   212: goto -> 232
    //   215: bipush #114
    //   217: goto -> 232
    //   220: bipush #14
    //   222: goto -> 232
    //   225: bipush #105
    //   227: goto -> 232
    //   230: bipush #29
    //   232: ixor
    //   233: ixor
    //   234: i2c
    //   235: castore
    //   236: iinc #6, 1
    //   239: dup
    //   240: ifne -> 248
    //   243: dup2
    //   244: dup_x1
    //   245: goto -> 153
    //   248: dup2_x1
    //   249: pop2
    //   250: dup_x2
    //   251: iload #6
    //   253: if_icmpgt -> 149
    //   256: pop
    //   257: new java/lang/String
    //   260: dup_x1
    //   261: swap
    //   262: invokespecial <init> : ([C)V
    //   265: invokevirtual intern : ()Ljava/lang/String;
    //   268: swap
    //   269: pop
    //   270: swap
    //   271: tableswitch default -> 40, 0 -> 99
    //   288: aload_0
    //   289: bipush #15
    //   291: aaload
    //   292: invokestatic ZW : (Ljava/lang/String;)Lburp/Zlnb;
    //   295: putstatic burp/Zt1o.Zv : Lburp/Zlnb;
    //   298: new burp/Zxr8
    //   301: dup
    //   302: getstatic burp/Zt1o.Zv : Lburp/Zlnb;
    //   305: invokespecial <init> : (Lburp/Zlnb;)V
    //   308: putstatic burp/Zt1o.Zb : Lburp/Zxr8;
    //   311: aload_0
    //   312: iconst_5
    //   313: aaload
    //   314: invokestatic ZW : (Ljava/lang/String;)Lburp/Zlnb;
    //   317: putstatic burp/Zt1o.Zx : Lburp/Zlnb;
    //   320: new burp/Zxr8
    //   323: dup
    //   324: getstatic burp/Zt1o.Zx : Lburp/Zlnb;
    //   327: invokespecial <init> : (Lburp/Zlnb;)V
    //   330: putstatic burp/Zt1o.Zg : Lburp/Zxr8;
    //   333: aload_0
    //   334: bipush #11
    //   336: aaload
    //   337: ldc burp/Zb6l
    //   339: invokestatic Zo : (Ljava/lang/String;Ljava/lang/Class;)Lburp/Zlnb;
    //   342: putstatic burp/Zt1o.ZH : Lburp/Zlnb;
    //   345: aload_0
    //   346: bipush #17
    //   348: aaload
    //   349: invokestatic ZW : (Ljava/lang/String;)Lburp/Zlnb;
    //   352: putstatic burp/Zt1o.ZD : Lburp/Zlnb;
    //   355: new burp/Zxr8
    //   358: dup
    //   359: getstatic burp/Zt1o.ZD : Lburp/Zlnb;
    //   362: invokespecial <init> : (Lburp/Zlnb;)V
    //   365: putstatic burp/Zt1o.Zf : Lburp/Zxr8;
    //   368: aload_0
    //   369: iconst_4
    //   370: aaload
    //   371: ldc burp/Zx5p
    //   373: invokestatic Zo : (Ljava/lang/String;Ljava/lang/Class;)Lburp/Zlnb;
    //   376: putstatic burp/Zt1o.ZR : Lburp/Zlnb;
    //   379: aload_0
    //   380: bipush #16
    //   382: aaload
    //   383: ldc burp/Ze6e
    //   385: invokestatic Zo : (Ljava/lang/String;Ljava/lang/Class;)Lburp/Zlnb;
    //   388: putstatic burp/Zt1o.ZS : Lburp/Zlnb;
    //   391: aload_0
    //   392: bipush #9
    //   394: aaload
    //   395: ldc burp/Zl5x
    //   397: invokestatic Zo : (Ljava/lang/String;Ljava/lang/Class;)Lburp/Zlnb;
    //   400: putstatic burp/Zt1o.ZG : Lburp/Zlnb;
    //   403: aload_0
    //   404: bipush #14
    //   406: aaload
    //   407: ldc burp/Zlj9
    //   409: invokestatic Zo : (Ljava/lang/String;Ljava/lang/Class;)Lburp/Zlnb;
    //   412: putstatic burp/Zt1o.Zu : Lburp/Zlnb;
    //   415: aload_0
    //   416: iconst_1
    //   417: aaload
    //   418: ldc burp/Zski
    //   420: invokestatic Zo : (Ljava/lang/String;Ljava/lang/Class;)Lburp/Zlnb;
    //   423: putstatic burp/Zt1o.Ze : Lburp/Zlnb;
    //   426: aload_0
    //   427: iconst_3
    //   428: aaload
    //   429: ldc burp/Zga
    //   431: invokestatic Zo : (Ljava/lang/String;Ljava/lang/Class;)Lburp/Zlnb;
    //   434: putstatic burp/Zt1o.Z_ : Lburp/Zlnb;
    //   437: aload_0
    //   438: bipush #6
    //   440: aaload
    //   441: ldc burp/Zebg
    //   443: invokestatic Zo : (Ljava/lang/String;Ljava/lang/Class;)Lburp/Zlnb;
    //   446: putstatic burp/Zt1o.Zt : Lburp/Zlnb;
    //   449: aload_0
    //   450: bipush #7
    //   452: aaload
    //   453: ldc burp/Zlj9
    //   455: invokestatic Zo : (Ljava/lang/String;Ljava/lang/Class;)Lburp/Zlnb;
    //   458: putstatic burp/Zt1o.Zd : Lburp/Zlnb;
    //   461: aload_0
    //   462: bipush #10
    //   464: aaload
    //   465: ldc burp/Zeaa
    //   467: invokestatic Zo : (Ljava/lang/String;Ljava/lang/Class;)Lburp/Zlnb;
    //   470: putstatic burp/Zt1o.ZZ : Lburp/Zlnb;
    //   473: aload_0
    //   474: iconst_2
    //   475: aaload
    //   476: ldc burp/Zeaa
    //   478: invokestatic Zo : (Ljava/lang/String;Ljava/lang/Class;)Lburp/Zlnb;
    //   481: putstatic burp/Zt1o.Zk : Lburp/Zlnb;
    //   484: aload_0
    //   485: bipush #12
    //   487: aaload
    //   488: ldc burp/Zeaa
    //   490: invokestatic Zo : (Ljava/lang/String;Ljava/lang/Class;)Lburp/Zlnb;
    //   493: putstatic burp/Zt1o.ZT : Lburp/Zlnb;
    //   496: aload_0
    //   497: bipush #13
    //   499: aaload
    //   500: ldc java/lang/String
    //   502: invokestatic Zo : (Ljava/lang/String;Ljava/lang/Class;)Lburp/Zlnb;
    //   505: putstatic burp/Zt1o.Zc : Lburp/Zlnb;
    //   508: aload_0
    //   509: bipush #8
    //   511: aaload
    //   512: ldc burp/Zx50
    //   514: invokestatic Zo : (Ljava/lang/String;Ljava/lang/Class;)Lburp/Zlnb;
    //   517: putstatic burp/Zt1o.ZM : Lburp/Zlnb;
    //   520: aload_0
    //   521: iconst_0
    //   522: aaload
    //   523: ldc burp/Zblw
    //   525: invokestatic Zo : (Ljava/lang/String;Ljava/lang/Class;)Lburp/Zlnb;
    //   528: putstatic burp/Zt1o.Zq : Lburp/Zlnb;
    //   531: new burp/Zt1o
    //   534: dup
    //   535: invokespecial <init> : ()V
    //   538: putstatic burp/Zt1o.Zp : Lburp/Zt1o;
    //   541: return
  }
}


/* Location:              C:\Program Files\BurpSuitePro\burpsuite_pro.jar!\burp\Zt1o.class
 * Java compiler version: 21 (65.0)
 * JD-Core Version:       1.1.3
 */