package burp;

import java.math.BigInteger;

class Zt2l extends ClassLoader {
  static String Zs;
  
  static Object Zg;
  
  private static final String[] a;
  
  private static final String[] b;
  
  static void ZC(Object[] paramArrayOfObject, Object paramObject) throws Throwable {}
  
  static void Zr(Object paramObject) {
    Zk1.Zg = a(-11446, 25588);
    Zk1.Z_ = new BigInteger(1, new byte[] { 
          12, 77, 69, -7, 60, 75, -73, -114, 55, -71, 
          -34, 42, 102, 35, -12, 26, 119, -4, -41, -10, 
          -119, 42, -86, 34, -48, -126, 82, 23, 108, 50, 
          -86, 121 });
    boolean bool = Zt2e.ZK();
    try {
      try {
        if (Zltp.ZY.charAt(Math.abs(((BigInteger)Zgds.Z_).intValue() % 32)) <= Zm6g.ZG.charAt(Math.abs(((BigInteger)Zm84.Zf).intValue() % 32))) {
          try {
            Zs59.ZM(Class.forName(a(-11450, 8689)));
            if (bool)
              Zs36.ZK(Class.forName(a(-11449, 14697))); 
          } catch (Throwable throwable) {
            throw a(null);
          } 
          return;
        } 
      } catch (Throwable throwable) {
        throw a(null);
      } 
      Zs36.ZK(Class.forName(a(-11449, 14697)));
    } catch (Throwable throwable) {}
  }
  
  static boolean ZP(Object[] paramArrayOfObject, Object paramObject) throws Throwable {
    // Byte code:
    //   0: invokestatic ZK : ()Z
    //   3: istore_2
    //   4: new java/lang/StringBuilder
    //   7: dup
    //   8: invokespecial <init> : ()V
    //   11: astore_3
    //   12: iconst_0
    //   13: istore #4
    //   15: iload #4
    //   17: bipush #32
    //   19: if_icmpge -> 1355
    //   22: iload #4
    //   24: tableswitch default -> 1348, 0 -> 168, 1 -> 205, 2 -> 242, 3 -> 279, 4 -> 316, 5 -> 353, 6 -> 390, 7 -> 427, 8 -> 464, 9 -> 501, 10 -> 538, 11 -> 575, 12 -> 612, 13 -> 649, 14 -> 686, 15 -> 723, 16 -> 760, 17 -> 797, 18 -> 834, 19 -> 871, 20 -> 908, 21 -> 945, 22 -> 982, 23 -> 1019, 24 -> 1056, 25 -> 1093, 26 -> 1130, 27 -> 1167, 28 -> 1204, 29 -> 1241, 30 -> 1278, 31 -> 1315
    //   168: aload_3
    //   169: getstatic burp/Zxxo.ZH : Ljava/lang/String;
    //   172: getstatic burp/Zg7e.Zr : Ljava/lang/Object;
    //   175: checkcast java/math/BigInteger
    //   178: invokevirtual intValue : ()I
    //   181: bipush #32
    //   183: irem
    //   184: invokestatic abs : (I)I
    //   187: invokevirtual charAt : (I)C
    //   190: invokevirtual append : (C)Ljava/lang/StringBuilder;
    //   193: pop
    //   194: iload_2
    //   195: ifeq -> 1348
    //   198: goto -> 205
    //   201: invokestatic a : (Ljava/lang/Throwable;)Ljava/lang/Throwable;
    //   204: athrow
    //   205: aload_3
    //   206: getstatic burp/Zvob.Zn : Ljava/lang/String;
    //   209: getstatic burp/Zxwf.Zi : Ljava/lang/Object;
    //   212: checkcast java/math/BigInteger
    //   215: invokevirtual intValue : ()I
    //   218: bipush #32
    //   220: irem
    //   221: invokestatic abs : (I)I
    //   224: invokevirtual charAt : (I)C
    //   227: invokevirtual append : (C)Ljava/lang/StringBuilder;
    //   230: pop
    //   231: iload_2
    //   232: ifeq -> 1348
    //   235: goto -> 242
    //   238: invokestatic a : (Ljava/lang/Throwable;)Ljava/lang/Throwable;
    //   241: athrow
    //   242: aload_3
    //   243: getstatic burp/Zg7e.Zg : Ljava/lang/String;
    //   246: getstatic burp/Zzr8.ZC : Ljava/lang/Object;
    //   249: checkcast java/math/BigInteger
    //   252: invokevirtual intValue : ()I
    //   255: bipush #32
    //   257: irem
    //   258: invokestatic abs : (I)I
    //   261: invokevirtual charAt : (I)C
    //   264: invokevirtual append : (C)Ljava/lang/StringBuilder;
    //   267: pop
    //   268: iload_2
    //   269: ifeq -> 1348
    //   272: goto -> 279
    //   275: invokestatic a : (Ljava/lang/Throwable;)Ljava/lang/Throwable;
    //   278: athrow
    //   279: aload_3
    //   280: getstatic burp/Zlo0.ZD : Ljava/lang/String;
    //   283: getstatic burp/Zedq.Zy : Ljava/lang/Object;
    //   286: checkcast java/math/BigInteger
    //   289: invokevirtual intValue : ()I
    //   292: bipush #32
    //   294: irem
    //   295: invokestatic abs : (I)I
    //   298: invokevirtual charAt : (I)C
    //   301: invokevirtual append : (C)Ljava/lang/StringBuilder;
    //   304: pop
    //   305: iload_2
    //   306: ifeq -> 1348
    //   309: goto -> 316
    //   312: invokestatic a : (Ljava/lang/Throwable;)Ljava/lang/Throwable;
    //   315: athrow
    //   316: aload_3
    //   317: getstatic burp/Zrgo.Z_ : Ljava/lang/String;
    //   320: getstatic burp/Zmll.ZU : Ljava/lang/Object;
    //   323: checkcast java/math/BigInteger
    //   326: invokevirtual intValue : ()I
    //   329: bipush #32
    //   331: irem
    //   332: invokestatic abs : (I)I
    //   335: invokevirtual charAt : (I)C
    //   338: invokevirtual append : (C)Ljava/lang/StringBuilder;
    //   341: pop
    //   342: iload_2
    //   343: ifeq -> 1348
    //   346: goto -> 353
    //   349: invokestatic a : (Ljava/lang/Throwable;)Ljava/lang/Throwable;
    //   352: athrow
    //   353: aload_3
    //   354: getstatic burp/Zti4.ZI : Ljava/lang/String;
    //   357: getstatic burp/Zl3j.ZY : Ljava/lang/Object;
    //   360: checkcast java/math/BigInteger
    //   363: invokevirtual intValue : ()I
    //   366: bipush #32
    //   368: irem
    //   369: invokestatic abs : (I)I
    //   372: invokevirtual charAt : (I)C
    //   375: invokevirtual append : (C)Ljava/lang/StringBuilder;
    //   378: pop
    //   379: iload_2
    //   380: ifeq -> 1348
    //   383: goto -> 390
    //   386: invokestatic a : (Ljava/lang/Throwable;)Ljava/lang/Throwable;
    //   389: athrow
    //   390: aload_3
    //   391: getstatic burp/Zgi9.Zv : Ljava/lang/String;
    //   394: getstatic burp/Zrgo.ZJ : Ljava/lang/Object;
    //   397: checkcast java/math/BigInteger
    //   400: invokevirtual intValue : ()I
    //   403: bipush #32
    //   405: irem
    //   406: invokestatic abs : (I)I
    //   409: invokevirtual charAt : (I)C
    //   412: invokevirtual append : (C)Ljava/lang/StringBuilder;
    //   415: pop
    //   416: iload_2
    //   417: ifeq -> 1348
    //   420: goto -> 427
    //   423: invokestatic a : (Ljava/lang/Throwable;)Ljava/lang/Throwable;
    //   426: athrow
    //   427: aload_3
    //   428: getstatic burp/Zrjw.Zz : Ljava/lang/String;
    //   431: getstatic burp/Zl7b.ZK : Ljava/lang/Object;
    //   434: checkcast java/math/BigInteger
    //   437: invokevirtual intValue : ()I
    //   440: bipush #32
    //   442: irem
    //   443: invokestatic abs : (I)I
    //   446: invokevirtual charAt : (I)C
    //   449: invokevirtual append : (C)Ljava/lang/StringBuilder;
    //   452: pop
    //   453: iload_2
    //   454: ifeq -> 1348
    //   457: goto -> 464
    //   460: invokestatic a : (Ljava/lang/Throwable;)Ljava/lang/Throwable;
    //   463: athrow
    //   464: aload_3
    //   465: getstatic burp/Zemp.Zs : Ljava/lang/String;
    //   468: getstatic burp/Zexl.ZG : Ljava/lang/Object;
    //   471: checkcast java/math/BigInteger
    //   474: invokevirtual intValue : ()I
    //   477: bipush #32
    //   479: irem
    //   480: invokestatic abs : (I)I
    //   483: invokevirtual charAt : (I)C
    //   486: invokevirtual append : (C)Ljava/lang/StringBuilder;
    //   489: pop
    //   490: iload_2
    //   491: ifeq -> 1348
    //   494: goto -> 501
    //   497: invokestatic a : (Ljava/lang/Throwable;)Ljava/lang/Throwable;
    //   500: athrow
    //   501: aload_3
    //   502: getstatic burp/Zxp5.ZO : Ljava/lang/String;
    //   505: getstatic burp/Zvh.Zb : Ljava/lang/Object;
    //   508: checkcast java/math/BigInteger
    //   511: invokevirtual intValue : ()I
    //   514: bipush #32
    //   516: irem
    //   517: invokestatic abs : (I)I
    //   520: invokevirtual charAt : (I)C
    //   523: invokevirtual append : (C)Ljava/lang/StringBuilder;
    //   526: pop
    //   527: iload_2
    //   528: ifeq -> 1348
    //   531: goto -> 538
    //   534: invokestatic a : (Ljava/lang/Throwable;)Ljava/lang/Throwable;
    //   537: athrow
    //   538: aload_3
    //   539: getstatic burp/Zsbv.Zr : Ljava/lang/String;
    //   542: getstatic burp/Zxci.Zx : Ljava/lang/Object;
    //   545: checkcast java/math/BigInteger
    //   548: invokevirtual intValue : ()I
    //   551: bipush #32
    //   553: irem
    //   554: invokestatic abs : (I)I
    //   557: invokevirtual charAt : (I)C
    //   560: invokevirtual append : (C)Ljava/lang/StringBuilder;
    //   563: pop
    //   564: iload_2
    //   565: ifeq -> 1348
    //   568: goto -> 575
    //   571: invokestatic a : (Ljava/lang/Throwable;)Ljava/lang/Throwable;
    //   574: athrow
    //   575: aload_3
    //   576: getstatic burp/Zrjq.Zx : Ljava/lang/String;
    //   579: getstatic burp/Zl_a.ZP : Ljava/lang/Object;
    //   582: checkcast java/math/BigInteger
    //   585: invokevirtual intValue : ()I
    //   588: bipush #32
    //   590: irem
    //   591: invokestatic abs : (I)I
    //   594: invokevirtual charAt : (I)C
    //   597: invokevirtual append : (C)Ljava/lang/StringBuilder;
    //   600: pop
    //   601: iload_2
    //   602: ifeq -> 1348
    //   605: goto -> 612
    //   608: invokestatic a : (Ljava/lang/Throwable;)Ljava/lang/Throwable;
    //   611: athrow
    //   612: aload_3
    //   613: getstatic burp/Zgsy.Zv : Ljava/lang/String;
    //   616: getstatic burp/Zemp.Zr : Ljava/lang/Object;
    //   619: checkcast java/math/BigInteger
    //   622: invokevirtual intValue : ()I
    //   625: bipush #32
    //   627: irem
    //   628: invokestatic abs : (I)I
    //   631: invokevirtual charAt : (I)C
    //   634: invokevirtual append : (C)Ljava/lang/StringBuilder;
    //   637: pop
    //   638: iload_2
    //   639: ifeq -> 1348
    //   642: goto -> 649
    //   645: invokestatic a : (Ljava/lang/Throwable;)Ljava/lang/Throwable;
    //   648: athrow
    //   649: aload_3
    //   650: getstatic burp/Zbjx.ZA : Ljava/lang/String;
    //   653: getstatic burp/Zl2t.ZS : Ljava/lang/Object;
    //   656: checkcast java/math/BigInteger
    //   659: invokevirtual intValue : ()I
    //   662: bipush #32
    //   664: irem
    //   665: invokestatic abs : (I)I
    //   668: invokevirtual charAt : (I)C
    //   671: invokevirtual append : (C)Ljava/lang/StringBuilder;
    //   674: pop
    //   675: iload_2
    //   676: ifeq -> 1348
    //   679: goto -> 686
    //   682: invokestatic a : (Ljava/lang/Throwable;)Ljava/lang/Throwable;
    //   685: athrow
    //   686: aload_3
    //   687: getstatic burp/Zrqi.Zu : Ljava/lang/String;
    //   690: getstatic burp/Zk8f.ZG : Ljava/lang/Object;
    //   693: checkcast java/math/BigInteger
    //   696: invokevirtual intValue : ()I
    //   699: bipush #32
    //   701: irem
    //   702: invokestatic abs : (I)I
    //   705: invokevirtual charAt : (I)C
    //   708: invokevirtual append : (C)Ljava/lang/StringBuilder;
    //   711: pop
    //   712: iload_2
    //   713: ifeq -> 1348
    //   716: goto -> 723
    //   719: invokestatic a : (Ljava/lang/Throwable;)Ljava/lang/Throwable;
    //   722: athrow
    //   723: aload_3
    //   724: getstatic burp/Zsn4.ZZ : Ljava/lang/String;
    //   727: getstatic burp/Zz41.Zv : Ljava/lang/Object;
    //   730: checkcast java/math/BigInteger
    //   733: invokevirtual intValue : ()I
    //   736: bipush #32
    //   738: irem
    //   739: invokestatic abs : (I)I
    //   742: invokevirtual charAt : (I)C
    //   745: invokevirtual append : (C)Ljava/lang/StringBuilder;
    //   748: pop
    //   749: iload_2
    //   750: ifeq -> 1348
    //   753: goto -> 760
    //   756: invokestatic a : (Ljava/lang/Throwable;)Ljava/lang/Throwable;
    //   759: athrow
    //   760: aload_3
    //   761: getstatic burp/Zb2n.Za : Ljava/lang/String;
    //   764: getstatic burp/Zl_f.ZI : Ljava/lang/Object;
    //   767: checkcast java/math/BigInteger
    //   770: invokevirtual intValue : ()I
    //   773: bipush #32
    //   775: irem
    //   776: invokestatic abs : (I)I
    //   779: invokevirtual charAt : (I)C
    //   782: invokevirtual append : (C)Ljava/lang/StringBuilder;
    //   785: pop
    //   786: iload_2
    //   787: ifeq -> 1348
    //   790: goto -> 797
    //   793: invokestatic a : (Ljava/lang/Throwable;)Ljava/lang/Throwable;
    //   796: athrow
    //   797: aload_3
    //   798: getstatic burp/Zxju.Zt : Ljava/lang/String;
    //   801: getstatic burp/Zspg.ZJ : Ljava/lang/Object;
    //   804: checkcast java/math/BigInteger
    //   807: invokevirtual intValue : ()I
    //   810: bipush #32
    //   812: irem
    //   813: invokestatic abs : (I)I
    //   816: invokevirtual charAt : (I)C
    //   819: invokevirtual append : (C)Ljava/lang/StringBuilder;
    //   822: pop
    //   823: iload_2
    //   824: ifeq -> 1348
    //   827: goto -> 834
    //   830: invokestatic a : (Ljava/lang/Throwable;)Ljava/lang/Throwable;
    //   833: athrow
    //   834: aload_3
    //   835: getstatic burp/Zm63.Zs : Ljava/lang/String;
    //   838: getstatic burp/Zej8.Zu : Ljava/lang/Object;
    //   841: checkcast java/math/BigInteger
    //   844: invokevirtual intValue : ()I
    //   847: bipush #32
    //   849: irem
    //   850: invokestatic abs : (I)I
    //   853: invokevirtual charAt : (I)C
    //   856: invokevirtual append : (C)Ljava/lang/StringBuilder;
    //   859: pop
    //   860: iload_2
    //   861: ifeq -> 1348
    //   864: goto -> 871
    //   867: invokestatic a : (Ljava/lang/Throwable;)Ljava/lang/Throwable;
    //   870: athrow
    //   871: aload_3
    //   872: getstatic burp/Zlo0.ZD : Ljava/lang/String;
    //   875: getstatic burp/Zrh_.Zb : Ljava/lang/Object;
    //   878: checkcast java/math/BigInteger
    //   881: invokevirtual intValue : ()I
    //   884: bipush #32
    //   886: irem
    //   887: invokestatic abs : (I)I
    //   890: invokevirtual charAt : (I)C
    //   893: invokevirtual append : (C)Ljava/lang/StringBuilder;
    //   896: pop
    //   897: iload_2
    //   898: ifeq -> 1348
    //   901: goto -> 908
    //   904: invokestatic a : (Ljava/lang/Throwable;)Ljava/lang/Throwable;
    //   907: athrow
    //   908: aload_3
    //   909: getstatic burp/Zrip.Zy : Ljava/lang/String;
    //   912: getstatic burp/Zrjw.Zu : Ljava/lang/Object;
    //   915: checkcast java/math/BigInteger
    //   918: invokevirtual intValue : ()I
    //   921: bipush #32
    //   923: irem
    //   924: invokestatic abs : (I)I
    //   927: invokevirtual charAt : (I)C
    //   930: invokevirtual append : (C)Ljava/lang/StringBuilder;
    //   933: pop
    //   934: iload_2
    //   935: ifeq -> 1348
    //   938: goto -> 945
    //   941: invokestatic a : (Ljava/lang/Throwable;)Ljava/lang/Throwable;
    //   944: athrow
    //   945: aload_3
    //   946: getstatic burp/Zgk9.Zf : Ljava/lang/String;
    //   949: getstatic burp/Zz3b.Zu : Ljava/lang/Object;
    //   952: checkcast java/math/BigInteger
    //   955: invokevirtual intValue : ()I
    //   958: bipush #32
    //   960: irem
    //   961: invokestatic abs : (I)I
    //   964: invokevirtual charAt : (I)C
    //   967: invokevirtual append : (C)Ljava/lang/StringBuilder;
    //   970: pop
    //   971: iload_2
    //   972: ifeq -> 1348
    //   975: goto -> 982
    //   978: invokestatic a : (Ljava/lang/Throwable;)Ljava/lang/Throwable;
    //   981: athrow
    //   982: aload_3
    //   983: getstatic burp/Zt9f.Zg : Ljava/lang/String;
    //   986: getstatic burp/Zd9.Zr : Ljava/lang/Object;
    //   989: checkcast java/math/BigInteger
    //   992: invokevirtual intValue : ()I
    //   995: bipush #32
    //   997: irem
    //   998: invokestatic abs : (I)I
    //   1001: invokevirtual charAt : (I)C
    //   1004: invokevirtual append : (C)Ljava/lang/StringBuilder;
    //   1007: pop
    //   1008: iload_2
    //   1009: ifeq -> 1348
    //   1012: goto -> 1019
    //   1015: invokestatic a : (Ljava/lang/Throwable;)Ljava/lang/Throwable;
    //   1018: athrow
    //   1019: aload_3
    //   1020: getstatic burp/Zbnz.Zp : Ljava/lang/String;
    //   1023: getstatic burp/Ztbn.ZA : Ljava/lang/Object;
    //   1026: checkcast java/math/BigInteger
    //   1029: invokevirtual intValue : ()I
    //   1032: bipush #32
    //   1034: irem
    //   1035: invokestatic abs : (I)I
    //   1038: invokevirtual charAt : (I)C
    //   1041: invokevirtual append : (C)Ljava/lang/StringBuilder;
    //   1044: pop
    //   1045: iload_2
    //   1046: ifeq -> 1348
    //   1049: goto -> 1056
    //   1052: invokestatic a : (Ljava/lang/Throwable;)Ljava/lang/Throwable;
    //   1055: athrow
    //   1056: aload_3
    //   1057: getstatic burp/Ze4w.Zc : Ljava/lang/String;
    //   1060: getstatic burp/Zlwc.ZG : Ljava/lang/Object;
    //   1063: checkcast java/math/BigInteger
    //   1066: invokevirtual intValue : ()I
    //   1069: bipush #32
    //   1071: irem
    //   1072: invokestatic abs : (I)I
    //   1075: invokevirtual charAt : (I)C
    //   1078: invokevirtual append : (C)Ljava/lang/StringBuilder;
    //   1081: pop
    //   1082: iload_2
    //   1083: ifeq -> 1348
    //   1086: goto -> 1093
    //   1089: invokestatic a : (Ljava/lang/Throwable;)Ljava/lang/Throwable;
    //   1092: athrow
    //   1093: aload_3
    //   1094: getstatic burp/Zry1.Zk : Ljava/lang/String;
    //   1097: getstatic burp/Ze1k.ZD : Ljava/lang/Object;
    //   1100: checkcast java/math/BigInteger
    //   1103: invokevirtual intValue : ()I
    //   1106: bipush #32
    //   1108: irem
    //   1109: invokestatic abs : (I)I
    //   1112: invokevirtual charAt : (I)C
    //   1115: invokevirtual append : (C)Ljava/lang/StringBuilder;
    //   1118: pop
    //   1119: iload_2
    //   1120: ifeq -> 1348
    //   1123: goto -> 1130
    //   1126: invokestatic a : (Ljava/lang/Throwable;)Ljava/lang/Throwable;
    //   1129: athrow
    //   1130: aload_3
    //   1131: getstatic burp/Zsu2.Zq : Ljava/lang/String;
    //   1134: getstatic burp/Zej8.Zu : Ljava/lang/Object;
    //   1137: checkcast java/math/BigInteger
    //   1140: invokevirtual intValue : ()I
    //   1143: bipush #32
    //   1145: irem
    //   1146: invokestatic abs : (I)I
    //   1149: invokevirtual charAt : (I)C
    //   1152: invokevirtual append : (C)Ljava/lang/StringBuilder;
    //   1155: pop
    //   1156: iload_2
    //   1157: ifeq -> 1348
    //   1160: goto -> 1167
    //   1163: invokestatic a : (Ljava/lang/Throwable;)Ljava/lang/Throwable;
    //   1166: athrow
    //   1167: aload_3
    //   1168: getstatic burp/Zsbv.Zr : Ljava/lang/String;
    //   1171: getstatic burp/Zmig.Zh : Ljava/lang/Object;
    //   1174: checkcast java/math/BigInteger
    //   1177: invokevirtual intValue : ()I
    //   1180: bipush #32
    //   1182: irem
    //   1183: invokestatic abs : (I)I
    //   1186: invokevirtual charAt : (I)C
    //   1189: invokevirtual append : (C)Ljava/lang/StringBuilder;
    //   1192: pop
    //   1193: iload_2
    //   1194: ifeq -> 1348
    //   1197: goto -> 1204
    //   1200: invokestatic a : (Ljava/lang/Throwable;)Ljava/lang/Throwable;
    //   1203: athrow
    //   1204: aload_3
    //   1205: getstatic burp/Zbjx.ZA : Ljava/lang/String;
    //   1208: getstatic burp/Ztgv.Zg : Ljava/lang/Object;
    //   1211: checkcast java/math/BigInteger
    //   1214: invokevirtual intValue : ()I
    //   1217: bipush #32
    //   1219: irem
    //   1220: invokestatic abs : (I)I
    //   1223: invokevirtual charAt : (I)C
    //   1226: invokevirtual append : (C)Ljava/lang/StringBuilder;
    //   1229: pop
    //   1230: iload_2
    //   1231: ifeq -> 1348
    //   1234: goto -> 1241
    //   1237: invokestatic a : (Ljava/lang/Throwable;)Ljava/lang/Throwable;
    //   1240: athrow
    //   1241: aload_3
    //   1242: getstatic burp/Zz41.Zc : Ljava/lang/String;
    //   1245: getstatic burp/Zkeb.ZH : Ljava/lang/Object;
    //   1248: checkcast java/math/BigInteger
    //   1251: invokevirtual intValue : ()I
    //   1254: bipush #32
    //   1256: irem
    //   1257: invokestatic abs : (I)I
    //   1260: invokevirtual charAt : (I)C
    //   1263: invokevirtual append : (C)Ljava/lang/StringBuilder;
    //   1266: pop
    //   1267: iload_2
    //   1268: ifeq -> 1348
    //   1271: goto -> 1278
    //   1274: invokestatic a : (Ljava/lang/Throwable;)Ljava/lang/Throwable;
    //   1277: athrow
    //   1278: aload_3
    //   1279: getstatic burp/Zs1d.Zl : Ljava/lang/String;
    //   1282: getstatic burp/Zlxw.Zi : Ljava/lang/Object;
    //   1285: checkcast java/math/BigInteger
    //   1288: invokevirtual intValue : ()I
    //   1291: bipush #32
    //   1293: irem
    //   1294: invokestatic abs : (I)I
    //   1297: invokevirtual charAt : (I)C
    //   1300: invokevirtual append : (C)Ljava/lang/StringBuilder;
    //   1303: pop
    //   1304: iload_2
    //   1305: ifeq -> 1348
    //   1308: goto -> 1315
    //   1311: invokestatic a : (Ljava/lang/Throwable;)Ljava/lang/Throwable;
    //   1314: athrow
    //   1315: aload_3
    //   1316: getstatic burp/Zld9.Zx : Ljava/lang/String;
    //   1319: getstatic burp/Zkf6.ZS : Ljava/lang/Object;
    //   1322: checkcast java/math/BigInteger
    //   1325: invokevirtual intValue : ()I
    //   1328: bipush #32
    //   1330: irem
    //   1331: invokestatic abs : (I)I
    //   1334: invokevirtual charAt : (I)C
    //   1337: invokevirtual append : (C)Ljava/lang/StringBuilder;
    //   1340: pop
    //   1341: goto -> 1348
    //   1344: invokestatic a : (Ljava/lang/Throwable;)Ljava/lang/Throwable;
    //   1347: athrow
    //   1348: iinc #4, 1
    //   1351: iload_2
    //   1352: ifeq -> 15
    //   1355: sipush #-11453
    //   1358: sipush #-11692
    //   1361: invokestatic a : (II)Ljava/lang/String;
    //   1364: invokestatic forName : (Ljava/lang/String;)Ljava/lang/Class;
    //   1367: invokevirtual getDeclaredFields : ()[Ljava/lang/reflect/Field;
    //   1370: astore #4
    //   1372: aload #4
    //   1374: arraylength
    //   1375: istore #5
    //   1377: iconst_0
    //   1378: istore #6
    //   1380: iload #6
    //   1382: iload #5
    //   1384: if_icmpge -> 1447
    //   1387: aload #4
    //   1389: iload #6
    //   1391: aaload
    //   1392: astore #7
    //   1394: aload #7
    //   1396: invokevirtual getType : ()Ljava/lang/Class;
    //   1399: ldc java/lang/String
    //   1401: invokevirtual equals : (Ljava/lang/Object;)Z
    //   1404: ifeq -> 1433
    //   1407: aload #7
    //   1409: iconst_1
    //   1410: invokevirtual setAccessible : (Z)V
    //   1413: aload #7
    //   1415: aconst_null
    //   1416: getstatic burp/Zt2l.Zs : Ljava/lang/String;
    //   1419: invokevirtual set : (Ljava/lang/Object;Ljava/lang/Object;)V
    //   1422: iload_2
    //   1423: ifeq -> 1447
    //   1426: goto -> 1433
    //   1429: invokestatic a : (Ljava/lang/Throwable;)Ljava/lang/Throwable;
    //   1432: athrow
    //   1433: iinc #6, 1
    //   1436: iload_2
    //   1437: ifeq -> 1380
    //   1440: goto -> 1447
    //   1443: invokestatic a : (Ljava/lang/Throwable;)Ljava/lang/Throwable;
    //   1446: athrow
    //   1447: sipush #-11451
    //   1450: sipush #-3803
    //   1453: invokestatic a : (II)Ljava/lang/String;
    //   1456: iconst_1
    //   1457: ldc burp/Ze_e
    //   1459: invokevirtual getClassLoader : ()Ljava/lang/ClassLoader;
    //   1462: invokestatic forName : (Ljava/lang/String;ZLjava/lang/ClassLoader;)Ljava/lang/Class;
    //   1465: invokevirtual getDeclaredFields : ()[Ljava/lang/reflect/Field;
    //   1468: astore #4
    //   1470: aload #4
    //   1472: arraylength
    //   1473: istore #5
    //   1475: iconst_0
    //   1476: istore #6
    //   1478: iload #6
    //   1480: iload #5
    //   1482: if_icmpge -> 1620
    //   1485: aload #4
    //   1487: iload #6
    //   1489: aaload
    //   1490: astore #7
    //   1492: aload #7
    //   1494: invokevirtual getModifiers : ()I
    //   1497: invokestatic isStatic : (I)Z
    //   1500: ifne -> 1510
    //   1503: goto -> 1613
    //   1506: invokestatic a : (Ljava/lang/Throwable;)Ljava/lang/Throwable;
    //   1509: athrow
    //   1510: aload #7
    //   1512: invokevirtual getType : ()Ljava/lang/Class;
    //   1515: astore #8
    //   1517: aload #8
    //   1519: ifnull -> 1600
    //   1522: aload #8
    //   1524: invokevirtual isPrimitive : ()Z
    //   1527: ifne -> 1600
    //   1530: goto -> 1537
    //   1533: invokestatic a : (Ljava/lang/Throwable;)Ljava/lang/Throwable;
    //   1536: athrow
    //   1537: aload #8
    //   1539: invokevirtual getPackage : ()Ljava/lang/Package;
    //   1542: ifnull -> 1600
    //   1545: goto -> 1552
    //   1548: invokestatic a : (Ljava/lang/Throwable;)Ljava/lang/Throwable;
    //   1551: athrow
    //   1552: aload #8
    //   1554: invokevirtual getPackage : ()Ljava/lang/Package;
    //   1557: invokevirtual getName : ()Ljava/lang/String;
    //   1560: ifnull -> 1600
    //   1563: goto -> 1570
    //   1566: invokestatic a : (Ljava/lang/Throwable;)Ljava/lang/Throwable;
    //   1569: athrow
    //   1570: aload #8
    //   1572: invokevirtual getPackage : ()Ljava/lang/Package;
    //   1575: invokevirtual getName : ()Ljava/lang/String;
    //   1578: sipush #-11454
    //   1581: sipush #-27732
    //   1584: invokestatic a : (II)Ljava/lang/String;
    //   1587: invokevirtual startsWith : (Ljava/lang/String;)Z
    //   1590: ifne -> 1600
    //   1593: goto -> 1600
    //   1596: invokestatic a : (Ljava/lang/Throwable;)Ljava/lang/Throwable;
    //   1599: athrow
    //   1600: aload #7
    //   1602: iconst_1
    //   1603: invokevirtual setAccessible : (Z)V
    //   1606: aload #7
    //   1608: aconst_null
    //   1609: invokevirtual get : (Ljava/lang/Object;)Ljava/lang/Object;
    //   1612: pop
    //   1613: iinc #6, 1
    //   1616: iload_2
    //   1617: ifeq -> 1478
    //   1620: sipush #-11455
    //   1623: sipush #-6080
    //   1626: invokestatic a : (II)Ljava/lang/String;
    //   1629: invokestatic forName : (Ljava/lang/String;)Ljava/lang/Class;
    //   1632: invokevirtual getDeclaredMethods : ()[Ljava/lang/reflect/Method;
    //   1635: astore #4
    //   1637: aload #4
    //   1639: arraylength
    //   1640: istore #5
    //   1642: iconst_0
    //   1643: istore #6
    //   1645: iload #6
    //   1647: iload #5
    //   1649: if_icmpge -> 1782
    //   1652: aload #4
    //   1654: iload #6
    //   1656: aaload
    //   1657: astore #7
    //   1659: aload #7
    //   1661: invokevirtual getParameterTypes : ()[Ljava/lang/Class;
    //   1664: pop
    //   1665: aload #7
    //   1667: invokevirtual getModifiers : ()I
    //   1670: invokestatic isStatic : (I)Z
    //   1673: ifeq -> 1768
    //   1676: aload #7
    //   1678: invokevirtual getParameterTypes : ()[Ljava/lang/Class;
    //   1681: arraylength
    //   1682: iconst_2
    //   1683: if_icmpne -> 1768
    //   1686: goto -> 1693
    //   1689: invokestatic a : (Ljava/lang/Throwable;)Ljava/lang/Throwable;
    //   1692: athrow
    //   1693: aload #7
    //   1695: invokevirtual getReturnType : ()Ljava/lang/Class;
    //   1698: getstatic java/lang/Void.TYPE : Ljava/lang/Class;
    //   1701: invokevirtual equals : (Ljava/lang/Object;)Z
    //   1704: ifeq -> 1768
    //   1707: goto -> 1714
    //   1710: invokestatic a : (Ljava/lang/Throwable;)Ljava/lang/Throwable;
    //   1713: athrow
    //   1714: aload #7
    //   1716: iconst_1
    //   1717: invokevirtual setAccessible : (Z)V
    //   1720: aload #7
    //   1722: aconst_null
    //   1723: iconst_2
    //   1724: anewarray java/lang/Object
    //   1727: dup
    //   1728: iconst_0
    //   1729: aload_0
    //   1730: aastore
    //   1731: dup
    //   1732: iconst_1
    //   1733: aload_1
    //   1734: ifnonnull -> 1752
    //   1737: goto -> 1744
    //   1740: invokestatic a : (Ljava/lang/Throwable;)Ljava/lang/Throwable;
    //   1743: athrow
    //   1744: aload_1
    //   1745: goto -> 1759
    //   1748: invokestatic a : (Ljava/lang/Throwable;)Ljava/lang/Throwable;
    //   1751: athrow
    //   1752: aload_1
    //   1753: checkcast [B
    //   1756: invokevirtual clone : ()Ljava/lang/Object;
    //   1759: aastore
    //   1760: invokevirtual invoke : (Ljava/lang/Object;[Ljava/lang/Object;)Ljava/lang/Object;
    //   1763: pop
    //   1764: iload_2
    //   1765: ifeq -> 1782
    //   1768: iinc #6, 1
    //   1771: iload_2
    //   1772: ifeq -> 1645
    //   1775: goto -> 1782
    //   1778: invokestatic a : (Ljava/lang/Throwable;)Ljava/lang/Throwable;
    //   1781: athrow
    //   1782: getstatic burp/Zg7e.Zg : Ljava/lang/String;
    //   1785: getstatic burp/Zb6m.ZQ : Ljava/lang/Object;
    //   1788: checkcast java/math/BigInteger
    //   1791: invokevirtual intValue : ()I
    //   1794: bipush #32
    //   1796: irem
    //   1797: invokestatic abs : (I)I
    //   1800: invokevirtual charAt : (I)C
    //   1803: getstatic burp/Zgpx.Z_ : Ljava/lang/String;
    //   1806: getstatic burp/Zrtp.Zy : Ljava/lang/Object;
    //   1809: checkcast java/math/BigInteger
    //   1812: invokevirtual intValue : ()I
    //   1815: bipush #32
    //   1817: irem
    //   1818: invokestatic abs : (I)I
    //   1821: invokevirtual charAt : (I)C
    //   1824: if_icmpgt -> 1939
    //   1827: getstatic burp/Zz66.ZM : Ljava/lang/String;
    //   1830: getstatic burp/Zt6z.Zl : Ljava/lang/Object;
    //   1833: checkcast java/math/BigInteger
    //   1836: invokevirtual intValue : ()I
    //   1839: bipush #32
    //   1841: irem
    //   1842: invokestatic abs : (I)I
    //   1845: invokevirtual charAt : (I)C
    //   1848: getstatic burp/Zenr.Z_ : Ljava/lang/String;
    //   1851: getstatic burp/Zlg2.ZO : Ljava/lang/Object;
    //   1854: checkcast java/math/BigInteger
    //   1857: invokevirtual intValue : ()I
    //   1860: bipush #32
    //   1862: irem
    //   1863: invokestatic abs : (I)I
    //   1866: invokevirtual charAt : (I)C
    //   1869: if_icmpgt -> 1939
    //   1872: goto -> 1879
    //   1875: invokestatic a : (Ljava/lang/Throwable;)Ljava/lang/Throwable;
    //   1878: athrow
    //   1879: getstatic burp/Ze6w.ZY : Ljava/lang/String;
    //   1882: getstatic burp/Zkkl.ZE : Ljava/lang/Object;
    //   1885: checkcast java/math/BigInteger
    //   1888: invokevirtual intValue : ()I
    //   1891: bipush #32
    //   1893: irem
    //   1894: invokestatic abs : (I)I
    //   1897: invokevirtual charAt : (I)C
    //   1900: getstatic burp/Zti4.ZI : Ljava/lang/String;
    //   1903: getstatic burp/Zscz.ZN : Ljava/lang/Object;
    //   1906: checkcast java/math/BigInteger
    //   1909: invokevirtual intValue : ()I
    //   1912: bipush #32
    //   1914: irem
    //   1915: invokestatic abs : (I)I
    //   1918: invokevirtual charAt : (I)C
    //   1921: if_icmpgt -> 1939
    //   1924: goto -> 1931
    //   1927: invokestatic a : (Ljava/lang/Throwable;)Ljava/lang/Throwable;
    //   1930: athrow
    //   1931: iconst_1
    //   1932: goto -> 1940
    //   1935: invokestatic a : (Ljava/lang/Throwable;)Ljava/lang/Throwable;
    //   1938: athrow
    //   1939: iconst_0
    //   1940: ireturn
    //   1941: astore_3
    //   1942: new java/lang/Exception
    //   1945: dup
    //   1946: aload_3
    //   1947: invokevirtual getMessage : ()Ljava/lang/String;
    //   1950: invokespecial <init> : (Ljava/lang/String;)V
    //   1953: athrow
    // Exception table:
    //   from	to	target	type
    //   4	1940	1941	java/lang/Throwable
    //   22	198	201	java/lang/Throwable
    //   168	235	238	java/lang/Throwable
    //   205	272	275	java/lang/Throwable
    //   242	309	312	java/lang/Throwable
    //   279	346	349	java/lang/Throwable
    //   316	383	386	java/lang/Throwable
    //   353	420	423	java/lang/Throwable
    //   390	457	460	java/lang/Throwable
    //   427	494	497	java/lang/Throwable
    //   464	531	534	java/lang/Throwable
    //   501	568	571	java/lang/Throwable
    //   538	605	608	java/lang/Throwable
    //   575	642	645	java/lang/Throwable
    //   612	679	682	java/lang/Throwable
    //   649	716	719	java/lang/Throwable
    //   686	753	756	java/lang/Throwable
    //   723	790	793	java/lang/Throwable
    //   760	827	830	java/lang/Throwable
    //   797	864	867	java/lang/Throwable
    //   834	901	904	java/lang/Throwable
    //   871	938	941	java/lang/Throwable
    //   908	975	978	java/lang/Throwable
    //   945	1012	1015	java/lang/Throwable
    //   982	1049	1052	java/lang/Throwable
    //   1019	1086	1089	java/lang/Throwable
    //   1056	1123	1126	java/lang/Throwable
    //   1093	1160	1163	java/lang/Throwable
    //   1130	1197	1200	java/lang/Throwable
    //   1167	1234	1237	java/lang/Throwable
    //   1204	1271	1274	java/lang/Throwable
    //   1241	1308	1311	java/lang/Throwable
    //   1278	1341	1344	java/lang/Throwable
    //   1394	1426	1429	java/lang/Throwable
    //   1407	1440	1443	java/lang/Throwable
    //   1492	1506	1506	java/lang/Throwable
    //   1517	1530	1533	java/lang/Throwable
    //   1522	1545	1548	java/lang/Throwable
    //   1537	1563	1566	java/lang/Throwable
    //   1552	1593	1596	java/lang/Throwable
    //   1659	1686	1689	java/lang/Throwable
    //   1676	1707	1710	java/lang/Throwable
    //   1693	1737	1740	java/lang/Throwable
    //   1714	1748	1748	java/lang/Throwable
    //   1759	1775	1778	java/lang/Throwable
    //   1782	1872	1875	java/lang/Throwable
    //   1827	1924	1927	java/lang/Throwable
    //   1879	1935	1935	java/lang/Throwable
  }
  
  static {
    // Byte code:
    //   0: bipush #10
    //   2: anewarray java/lang/String
    //   5: astore #5
    //   7: iconst_0
    //   8: istore_3
    //   9: ldc 'ÛØêº\\t*äÃ3R'
    //   11: dup
    //   12: astore_2
    //   13: invokevirtual length : ()I
    //   16: istore #4
    //   18: iconst_4
    //   19: istore_1
    //   20: iconst_m1
    //   21: istore_0
    //   22: bipush #64
    //   24: iinc #0, 1
    //   27: aload_2
    //   28: iload_0
    //   29: dup
    //   30: iload_1
    //   31: iadd
    //   32: invokevirtual substring : (II)Ljava/lang/String;
    //   35: iconst_m1
    //   36: goto -> 202
    //   39: aload #5
    //   41: swap
    //   42: iload_3
    //   43: iinc #3, 1
    //   46: swap
    //   47: aastore
    //   48: iload_0
    //   49: iload_1
    //   50: iadd
    //   51: dup
    //   52: istore_0
    //   53: iload #4
    //   55: if_icmpge -> 67
    //   58: aload_2
    //   59: iload_0
    //   60: invokevirtual charAt : (I)C
    //   63: istore_1
    //   64: goto -> 22
    //   67: ldc ';6S°SpJÓ9û÷ªã\=R1IÜ2TÒes õu/»Ûºm\\bA&ÇÙäßåj]#ØV¬¼V4Ï¥úXºþlÃ4RpóLL}gA Ý¿Ë!#é¯$ë$øj\\tÌGÐüsà_8'#³MÒr <ÐWäï«Á×nø© £\û«_\\fæ8((ü8('èmê;ÚVÃI\\ncÏMlòªrÌýÄDµ{\wÇþ2"|ªÛö¸¼VK\\b\\t1¡Oäii×¯´\\r®3\\tE§Ð^2´]¢¢oõ^úº¹ù¿¸íP\\tï`5UXÄªÔ2]ö+s-¼TpqÐ(²llõþÜä·}l¯aj\í³ªñ4Í¢½¿ÃÞ-8+IO"úY­.oA;î£\\rÒ+nÇi\\b²<Fè`I¸\\rµ³µºx£dÿ¨¬Æe¤d!åÑÎRÍÎ¤ÒÏ´Ö)|Á|?Oå]n»üùE\\bÎ×ØSÇXËèR9¢xLÝÈNqî$ém|ÙÏ\\b¯°!¬^ïÌ}ÊàjsN(}U\\fþú@ú*w.tâÀt¬fQD¤d?@Äªÿz\\fbª*÷ÆzOWtf\\b?ì¸²Ul5G¦¶±(!\\føv,ujÎùÉ%¦üL|.Ðõt1È¡¿´ÔüüLÃDqE».iLÀë¶¶óf\\rz´^i²ãLKYZz£lê¡Ç¥å®³ñKÐ[:¯ÇHýæçúÈz¯±y´Ä9JÀr½ªtäçØªFíÄÚÝôºPSMç\\rÄBÀ"`Òaú.i­M«?=Q;Ü±KÀ3e­\\r¡1÷xgÓË(ÚµX¸hW«%&7\<×tðò¿BQm®°c`k³ÔúÒ%¦6r>æeUÆSÜ~X°GäÌWÛçïíÅOî¡¢*xPx¢;ð]>R:èToÇ¹aRQúsU¤^.zre®ÖÉO¹¬æYáDSqðWsFÒ\\f¶D.E+¡R°À÷ÛªPO>á;~6òSU~Ùa\\tß¤«jG';|øÙ[{ì°X·NSJZÇÈLY÷@Rä.Ô\t6(¼ð³w­=ÜßH©5Ð¯{ Y¯dPÌ{DO0buÄtq»@xOÐÕOìö« \\f9Vc1Ü;ÄU-ðú­lëU2ås¯µ¼èPO@}o÷`/Ø°R^wØÈX~g5øã5ÙB¸ßI-ý³Ñ4 -sã¼é0¶p÷BVmð{ïÕ÷½øLT@Ý`OÚSi4/ßÐñãH Íf¢d¶¦sÏzCFuÑÅo \AIÄ "!l7GzÚ³WÄ×£ì±w/ªÒâu·ßÊÐ"6Éçf1´-8iÕØ\\fÙËJº´\ç3ä m±ºp¡`í3§é)e¼\\nÛ¸%ÙÃRù5YT>î¶á½x¦ÚUß{m¦á§G­F¦zÜf\\r%,¸Ï&Y62{´WaÀ&NºÛÕla°oàhÔóþ®¿Û?Ü'`è©)u04ìqÕbØv8ø('Jõ£3ÝmËHH¿©s,HÐ\\f°uÇµõZ«Ê¾e­3i×¦î×Ô4ÓRvãçHHÅªg9~ÝWw7ð¡At bkùÝôð;Ï¿Ç\\r<Úå$êE_Ú´Ê+6ü)ÂÌÇÙhÈ8xírÁÀ»JYKuÖg=güVÒÇ\\t#<*À,àãL;ð}LUðÜo;F"êFZ330Iå²yV=f@ÿ¹#h]C]'KZÓÅíÀ_\\fè¬£B ÓÇ¹Ø³ÎZV9{`è<!I\\r¨SECAÖYÞ²BVDV>T? R£ ¯MðfGUüÓt ¢=Ï¢=c®I.å³eÚó¬W¹u6bQ·³|jÛé¢/RÅÌ¶sZÍpëUÿùÃæc Á¾~Iå\\tkP8'Ýålt«Ú´MRè§RmÈ&\\nö<tÈ\õöíëR%Wq¨ãÖüXé,ÚF¯ùÔ"d£IãÃx/\\rm@]r£×ÆæP­²OBç,T¡L'z^J\\rdÚÒ¨2qrÐ#?Ý-¼Q >x¸5O£P;ê>dßî>T­µÞ=\\fruP#M÷±*ÌxØçø©ÙºÈ×[óÕ2ÊzT3LL{@L}ï­ò\\bÃ>ÕùO@*ûQ~ÄÛíÛîcOÌCÊ#ÆöÝUc"JwØ)ÕÿAW£T¯-ùJ*Â8ø&I2ë>û¡Ë'ï3ñØ¥Õ·áÞÞX=@Ï\\r>'ê<³²üdë¯8RN  f{U*¦_heW\\f.,'Þ·X`uqq#¯ýï=JÕ¹º÷_@î\\fóGNOXmÀbß.ì/Î¬3®7\\nA"Ì.Îªé«\\nãè?&²ðëUiÛ«ÍEc(lÍ'ò¿è-ü!Õu\\fyÚTõ.>rdÛ1¸×\\t¼ùÎß%¯lpjðHÂk¥M·~jf=­8\\b± mCþ\\fRñÓaVü´ñyI®=©W/ù¶[D©« ó79ýüÔì9Z«ÂËd)f3\\bèì`Y°Î6ýÚx-ç¿\\nzï]L±èm¦¯Jà¤Ó6» ú\\fF%p¦¨]ÁuÝºQî\\t"Âís¨FB×)®ô«F_([V{^VNêKÄx´AÑìÿú®IACÁâû%f×ø¤äò¥Ù*ÓÍIÝPi¼Î÷¢ë²é±¹\\fâÃÐ¥VÁù?FÛÇkêß«ªÑï&}~ ç1cóðn³Ì>³\\ryC|uÁü&Rî\\f´»¿Yü9D¾RÎÃ÷ÇþLîTWCÖæ´Ø7@A°KK©RÔûêOÜ ðôqÞPéb2Ç[ýb<»Î ¬|5é/èÎout!Óö¸ä/¸ëXB#É^*\\bc(ÁßÃVø+Æ\&}Æ2+ÉU3^J@DZ%ÄcdäB×qc\>q%ßþ;<\\nøíQðWÌ;¶(qÇ¯Ñt¿Yv¡ÌD¿:\\rMà£ßÐ4@0/NW5÷9õ3\\fÛÉÓho»+­ÁÚú=á-úêó³Úð)-ÞÙº<\\f;O}&\\bö¬H ¯=\åa¦^öhö:Tbúºè±RðoÍC1*j0c©dÚo¸O\\txDâTO.¥äÙmjîy ÖWû¶]Ñ¾C?Êfwþ<·¢÷g)!)Îíà4Öù3q]Þ©\\b¾YR?W×Å;ö©ø0±W ×¥Yß%=K}Qµ«ÕÏUz%&u´Ý\\bè~k£}nÕ\µ@\\fïÒã°I'ù*roàÕýÛ¤W&ës¡ÈT¹qþ4êò\ï\\fÐM~×â$gqTäY·gFÞÊ)ÂºçÞë§¦S4f¨%KÌl8àKxÅô@ðW$õ®þÝkCþ& ÆWl·ê _a&]:¡\\fÉWqxölÈEáj|¤¤}\\fÐpCôÃfYÊù8ãqyN]æHK®Úåq<þ¼pq ùN¬|L\\n]C¡÷_ú´sØ¥$-æç2¯ú²ÎËÕ¼ Ñ3âîh8½q¬óÑª]¿±êB ý\\rc«È¯eïHÏ¬³¬Aë úúIE0ªÓé\\tÖèýß^è²,rzL·«YBqúÕõH÷øxR;{ùÑÉóûðaeNCÃÚÎ¿¢®è¹$KßÇ«tÈ8äÞèÛ\\bQEÑ·\\f·S(Å¸Á´Áb²up² §[Éa@Ítü~6ÔõýùIhNvÈEÝ«W`\\fÊVª_[÷}[4<âÚ±g?¾ ÓÒ8z~?±©bN38(«(Ï3´ì÷9G÷Ö³vEÖU>E\\b÷A1bâõièÁ]÷yo}>é§áUòr¦!G 2Ão4>#\\büS?H¬$<÷P5Ðáeéâ43]W¯ý\\b=GÊÀ£í¦¨±X>øª¹&®û»Ï<§Y0yHPpU<ÅHÍR2@¶!wÔ±ÀXWspÍñSD:ûâèàC÷EHøæ§³6ÊÜ\/q°Ý«\\nSDýØp»Ï£Ò_¡ HcÄöÕ¾NßªÝÍÞ¨ÃçYáÏfa¹0ÉxüQõ¬&×¼Ãâ¼ueL°·T½´P³îB\\fåSÏÙ:Å<ºI­¯ðFä9Û=ú/ÛÈjfod[>Õwôä®=Î¼ÈW\\nÌ¦ï4ìÏOÁ3NÆÚYJnèïZë Ù»ëÎ1+6ù(î³<ûÑíÐ®ÑX`É÷Ì¹ç%½n, ý/z\\bõ\\r_bßQìfFàJR>~úXmånFC²éõØ=º\\tãÓGôX¤F)8ÊlÁ¯ÕL èÊ©@SíïØ4»íX¡NL§mu\\fqä§ÌÈá~Ö~]ú¿\\n¯Ì4%ùñul:ÑÔZØ«=Y50À t£ëE_&&A!:µQ×[7C|n¹h'ÅÉÊqJQ9©´7e¸\\rLå¡¸*3fotñåÌßèAP\AÛXèÎV;/é÷ôÎÇ-=IôéqF<i{²z÷0¾÷ZÒü9çÍ*\\nG(hjhYNßZáFöÝë$yÃ\\bk`»x­¹ù?7ÛR¡®s÷Î7[Es<Å¸®òðª"ùòKÍ/ïØFe¹µùG/ÍÑá[Y!°\\rY]bçÕãÇÓZÓUeä¦ä(PU¿4ÿÁºæäòO\\n#RÜ:Ú[÷5<´e¼ÅÈYÄ×MÀ(ûG³jk{h?Ê[yZ#´Õ¶GÕý?-\\f¼°¤ÿó< a%]Ä&u×¼fY0FûeP¼ÅiL(@@ªÃÉLñW+6ªÐÆ»èÃòÒ:fÑ6ËÒ]<ýá>q\\b Ëì¶AYÌ¬Ê:#èàïkÀQæÕ`î¥ö*~ ¸¸R;åÌüÑYÖã?MµÑ@-â;B\\n{ë1ìY+Iº:ù¸¥n<À<8ôÞ-Já;Ü}MKö6Ët·×V7Þè¥¹Ø¿ê\\\n÷\O¡ÕºÄ£-Ä´ÞO³§Fõhü¿)+Sþ&­º¯}Ä0¡ù$×mÛ^ó¹÷òËJP¦Ýx*Ü¥DMXd¬"*©àd\\rÀcPü½ôrZI!ñ\\f- ¹:æd²gQ_uz¢3@öbóÚO%?s´çï1u=ÆL\\b¿®Ã©21¡\\bFg¾ûfÞ&ÇãÅ@BÏ÷;OO2*ËHíÂnÁâaxN\\r\\fM¦0ÖE/HûÔXcR!¶j)?]½;×¦I¤\±©Lö;â`ãvTä[©\\rÓ£ýHÙö0Ü üCaËÜÏ;ÁZ;ÈºÏW\\fÀ ³! ÁE¹Æ%Ê ÌZ£Vi}RS´wbº/|¿\\rD0|_húÇÒ`Wþ!Á/fP²ôRZ5©LRHCq)A²<Õ·yýÏ%g<ù¢o)¼í)#ºª¶9ÿÒÀÈ¤7F²ÃýÀFZî%Ð?nÂX}6é0zE /9?Î¨nççeMrÇéîï#£>A`pØ9úÚ\\b°vsëTEË~ns×àCmrÀ­Kÿ¨k\´Áß¹æb¥X©íÊmáÕ(ë|J/×ªLZX¤E[¤4¡ÞpFíPÃd÷Æ³:P]CòO\\fi½Y%efÔµTÔPià»>gøøàÖã"üÍ¦%uÓÝ\\fù'Ìº/L¤ì§`Ô·=ÊqýÊù*V Ëb£¯N³<&~u2H'ÌTWk>Q~1ã[ß&òX%ÕQ\\tUJðJÒwqZÔJj·O N²&Z÷ûfðô®¼NØï¡óÈÕAÂÖL_õg¦ÒKª$XçÃa­»è`B:zÉøG¿ü¾­¾½àT¡¥qóÎbÛôkøêúzÃ$»0¢ñ[×qØ\\n¾ÎQù;êmX¯'ºá8%rR¤ì_ò½QòaxºÀHÂ~vùG_t{7_ ][¡6ÉMÀ AE:jL4»?*®Ô\\tçäúki,UVÛX=*`wø5ÑèØÊu³.¦ë®§\Ùå ô4+X*bn;ñW¼N!LºWèÉÆXªã|ÃYLÆ.Éµ&Ô|hR(@ÉÈ $º|¯¡aodÒf!Ã0Ô¡>PËåJË4?¤¥_ÌÏ¨*¢h.SÂ[âò2"Mçzª×\\b\\bWUÄÈEÚ3P¥²dáFJ¾m¬LÂN]þÿÕ¯p[wïßôíêhäÇ<ÂDíºÚ¦ËUÃ·ÒR\\rò7(3 UüüUñüÕµì Ýv¨µ'.\\f¬\\b:ÌëíQ8rÚ¿ÅÕÜC\\t[þ©G§Î¸3\\nkÔºo­Æõab>%ä=\\n\1¬Ö¶YðàAä¯³æ\\t\\r÷lÂM³)ö }\\rVoç2\\ræúÛgè)Ñnk\éD£ÁÅðßjYxï7\\fo¤rÛ]6gÆMóãaÂ·ÇÛéµå!ËòÆù}±\\b%¯y­ÁDúù©ÿ~ÂN`ÕdnG×âNG±N^d×5§ïW5á.½Ú6@ÑýºHôÜ)GÍVè­0þõÙ!\ÆKø3ÌÄÙç\\f¢/H)$ÔhRîYEñ1ÜD:¿mkbÍÓØ/ÁUH¯Ûá¯"fg9ÜúÀ\\fïfoí»ô"*>êÖ eM!C@(ÊÞ¯+Úxm?lâÅÜ{9?'GLkªùæÅþá·h[¸ÏõÙjr'ÇT¿rL)#æyB|sô_@ï}´¼ÎL",\\bYÊ0·z¡xz?·ùj¼&ÐBbxµÔïõýºGõÂ¾}WÒ£º® ªño ñß³hÚyÉ{Ç}úÿøóf/Ü8NÃp]Fd5 àEd<L'âÿ6nØÐmB»,dàI^¾ßîÁtÑJ/Æ«N"¾Oå9ä6þYHå-ÍÕ=²ØÍøº$Õ²ôPjbN¶éïT£ ;~_­ïdêÍü½e¾,$×QbÜegÀQE©ØOn¼UZòÄ:*1í6{\\nËáÀè4.;0¡GFPÖUÅÁÑÍlsUxÊ\\b\\ngóª(qì2dû!ß4Zà/©:Zi+£Î\ö\\nú]Þ\\n¥4¿ ª:ÄOÂWóîk%ÍÈ\\bRû¯×Þ¥/ÒøsöeZxv«çIw_|Ôò] ¸¢$¢«ø\ÄhþÇ8'ò8Â7Àþl=ÔªÍrJy2\\n»åú½"y6ß'ýÅ¡?ª.¿JwÒõÁÌgTp\\f/\\bM|¼eEFxg}½¼Y^î6$÷·WSÈHRNæiyP[U%©fhèC\\fswÙ"£â\\r|¹Ã×æ$/iÈÚ}4Õlljl¦û6vÏVäÇ³Èp8"6N!iG ÀrÔÌ+¤Ièo§WH{4Ìý«NóÕ Ô¢Çâ8XòI?AÁR±'¸n>¬X¼[#Ä|¼£þºðë"÷AUT®I@¡¡ûYþSÃi\\n *HñW:tig£û\\bq\\nØaùïr\\tÿkÿ*Gµæ)Áà2øõÖûîãEü6,ÿÿ]v>\\rÑ'Á©¡\\n%}e.Ö_lmu¬KQSã¥×)ÚÏ·ó_\\nÎ{c}ÓE,6±¢ABã<¦læJ¥Ü\\tKÔ÷¥®6K[÷)\\bT¥ e¨éæraS7Ö&çqÞo e"F>e¸è5¶ÚÉcPhú¢>np!þ¢Ý¥ÔHËÔRf5cYÚÝ`¤Ø-ôÏ'ÒìeäÚ9©ïùÓ{úÓD¯eL>ÂcÅ¼2ÚºfB¬CièuR·_·ØÉÞN;s©r` (déIÜwuáæ\\f5@Èo¤8aÕáWØÐ«UâÛCÑ>`º<^´ìL"²¨\\f¤úýöCÁ9*èd¯/5Baï @yÇ5þ 6çËësÌú³C÷7æ¾\\bµ5NÕ\\fl4Ç¨gÁASË¨E1QlðÜ"øjJ2y¤1ÇK[)óÊÛT)üuH>úw4¢¼úÁßÔ(BZCìj¦Eå;Â|3×é¤)¢:>±\\nX02ü²ïUn`ì<IËáÿÇÝpåhë®:¡T`þbh¹úËëÃ¾+ô¶ï;ã¤^ÿæõ³\\b+âù#ZÀ´²1G ze]ï\\ndxÀ`í©TÍ»ïf\ôÛÿ\\fnµÜÔPÇá¢Í.ÃLðáô´Rú¤\\tÕìOTäsíA·ÍäÎ½ÍäÕXûh¿ê¡«ÏDr°B<­-âG2»Î±yyLÃ´%éóU<ÃMAÏ¦ætp²AU 6°ç±åNP¯xðmjw°gV¬9CPô_ô¦ZåxTäÞût5¡RTóëÉÓýÇ1ï+_ ¦Ç´)Tb P-»Çrª³FäÂT%®Nñ2O9WMsV1Jäb´6bÂ:«yÏli\\b4w ÀË;$¥5ÑÝ=a\\b DÆ­Ûò¸O+Ô)J\\r!eõÄÞJ^,³Ý-(ó"Ldlùï(¯]TD¿âB[kªÂ ¥Kâª÷'kö¥í ÆÅò\\rÁ¢1cMÝ,:Gÿp2H\\rßÖ!gZ%õ7Ø4]çÕÕ»è¬ªVÑ¤ÑFÐQ©$@~LN´¥Ýç­Ì[$ï£5ÄDMBò8\\t]1Ú÷z î7ÏkºG o¢üíÚK¸W)Ð0zö;²¶uæc\\býÇÞù·ÒF·ÞS õñ.Õ¦÷úÌÀß¿I;r%ìO³Ü!,[è_LÇ\\t5mþÐ*q¿@ÚX"RZ¬§"w¿(©u.gë^TüeõO'O¬jË¨@b¨KÿP60ë¸T\\bÐ\\tëÁ;®8ú`2c2¹t8UA§Fkzºs½h{ìÐ£ñåj!f³i¥\\bÁ÷tª6;\\t*ÿ_ÔÇ8ÒÝä©ÒÀõ)k*ÓË¥ZºN|·-¿a}Ö]3ÖCC &A]|%àP-"/Ü\\tòò}ñ£6ê±MÂRRV7¸ÓY²T !1[Hc¹U·§WL\\bu\\rËVNa¼X<7#¦¶Ø~Z®ß&ð¦iõ"9C´AâÓg{T½ÐíkqAÓpÀ±Ùíª»[N¸ßmõ=ËÖ\\nôìÒ(/h£§\\nïf1âUØ4ò¹íÐ¾âxãI2?s8v`18ísÅÑÉcù~_v#µ|ã~\\n­âPÂ<ÿæks4:MLïG\\r è¿^¹ªd7pü¬º»õríQ~£zZkë*O%]Üê1~ê;¨Ý\\nGÿÛÂÚ#ÿþ­ãJa²ÀElöë _Øé\\bDã+%CÍâ +D¾üÚ s-³¿<FmåÚýp.æT2_uÑyy²íÜnA§ÅFÈ×%Ç¶Q¹!ÍTF?²\à%Þ)\\t¹~F¡µ{*YÒ:ãÖOÿ¢®ÙUý\\t"<æáaSZWEûFPqxù+?I}áÉ7\\rI÷¡Pz!$o*ôöor1zYÕXÈë½gR±ÒXD¨¬½üºbÿÌÚs¯õBÉô¹8Â°ÅÄ\\n/]ÀÐ¨Ö*ôÚÊX¹\)è­sô§ÛïWUâèoÕÀDÅN©~Y(Å¼ÉP.ª%ý2[:ÿDNA"®ÚÑ^¬~òiMç§ù_jJ«\\tÜXìã¬¨.Ò\\r-ÞvýÕtãUf¹ß¡&ùÜ´9ÃP­Y«µ;Y[F3â×33Ù8Ì))ü_#Éñ*z(ã'é­Îþ±l±«uZ¨`k¬pQ?#§Æ²vI÷èw*ÛêQr'LE\´à«\\b(ê.´;ª»Xzøçîé­ø¨>ÑfMÇ(HNJÀT8øE7Ç¾ô¬ï\\bÄÖL9öå-ÈÝ@%X~èÇt÷*Ì\\b×aû»ýôí\\tg)aªÀæG¤ü\ÿwTú¦$~ô÷¨äXÅ3ü±à£&kú°nÊ[õe8óx¨D·½½A;ãÙo÷´;Ô§,VÉ´<Á\\bA5 l~ö[uPè?jÌykçOX}ÜLf+Døæà¡ivh3øôÂmÅ¯â@ü¶øÒDnaÑm_9 `Ö3ù*dvNª§Mò½ã,ËÚÊ,\¹J{ÓSi¶á<«Eû}é5©Ù¸ªÓßÑ¹ñmHéV>Ân¦îÔ¯ 5xÊ¥<![åÓ-jÌÇÐ~ò\\nÇ04xÞúÀ]Ö\\nM>Iéo²´]?4ÜEîßL»§Ø_Æ@On8ÙÝFH&ª°"ß)84hÎg5|v4Ú`6¾ñW°GòVÆÅæµ) dºIÈ²Ð/oÝjaêÙÖßêé>é\\rr&RðÃÚÚãDÂ\xr¸B&F­ÊÐ%Vú¹jdº\\r¬²Zzlf¬uåP7Ø´ûäÛ«ë<W>ð§ÜTõóï%¸+Q9%ÁÿRîS.h«ýe»9ÆHq;6fø7ª:«$M¿¢ÊuhRÏõÚW¨=v¾«Ýñ"mÙ¦Òâ}UÜ¶#C Éï¼\\ríW.1ÌðºÉZõEJÝ¬LÎSÝÔ÷áÜ!3DiCs÷4çK½¹Çxñv4ï=\\bÏõ.SMtÅ9p+\ÜQjJq¿tïÞ´-a¥¥JÿÐn ³_]\\tiä°lÿ¥iV«µ~þr\\bªßÒRèzì¯$)\\\rÇÆú÷æÀX:ÜÚ~/8¶h"²öðj^ð½°¶8"Y ´zN³_Kç¡Ç)F1o\\r~u;×è_BÇþ`¾9ö\\nÃe×âÅ4\\n\\b£ÐÓ.HÂdØyÅD®\»Ò¸ÉAüå|à®ueR£Ñ%þ@æÍ/%ºlo7³Õ|\\bJÀÛJkNåÇÒi#´x©üPã1:FLoâ4ìJ¹"a×ýÏÇó;:ÒC5.ùú¼m vÂÇeâÛmCPîáül!Fºû!éÚÜ¦h\\r\\bgXE+?¾(Áí4ò¯Jó¿ôì>{\\ræÊ³aMzJk0%5Å\\f /]ð°Ûå=g¹ð5ÀÊ;"¡¾E½Ò~ÌhÝkzÏ÷+¤ý*\\r¹½Ïø°\\tø7Ô$ª1¤ôèWÿcÕ¡øSéÆ é´??X`>ù~­1ö!ÁÀÍ±(tgc7þÌ1d»J9}EL²¬ öeÚ_1èæþ~±°ÄSföùÀmªM«V%8;müäà<6ZY(å\\t Kc U½®áìÑÅt?Z8QüãºõXtlñ BødGHnSù¤ñ-þÜ5Õ«gH{=³ýÉC\\rÅg \\n»=éaÏ¥ÄÍÓ»ÉxWÑ\Ò ¨èBïUìk¶fNø3ÆËI©³\\t7KªPÂ/y)±IWñåüðº#.A¥# mCD3D!CÊuÛSÈ[gæiöÔÑ©u¾5\\fpÃöéÅ¥C@Õ<CPF,ÔRSû,kñkÜQÜ0\\nò¦Ê"ºë¦äqâÿ_i.Ï\áXÎÀÁ´·´­'óÀ£#gÜ/Ðÿ<LG­«øo yU©>Èx¯®%þ\\bLÒÓA±vú«½#¯Ø ¬×P{Ux3Qu»>F·©¨\\rl)gÎi@²ÀF£NøØ¦YàÚeÅ¤Ðóì_Ò­ó×W\\bh¡<ñ`ÁþàQwÞÐbx%¯Ëúð\«ë#©;ÍV2øïÍM|;ÊrÄSMi}ï \\tü:â k·4õÅ'(þcÓ^M¨ÝYÃ:ì§ùíà5²q .7mzÇ84½/°X£\¿ÃÿGÅÃÕ¸é}«äâÔ$¡WFÉïÚØr`pÅÈá«ö!g6hÉ\\tâáY­~½UgÑcBVæÝ]ñ´8¤\\fúJOTÐý:ù+ÓS1êÆrÇº5bUý­øï\\r\ö~£Ý\\rKÐ[]±¹Ìkë6-³ìÀ&mµRªJ`á'Ë-DÄ*N¡Ðµ¤Ï\\f\\t%ÿï+«ë Êà¥`ÙtÃ.õõ7Nx©Øø³ùëéäÓ)dw°CnZmÊ¿Ö0Ç×ÔùwÐôpÈ£Öè½¹¹Ý;Îû}>²ÔUckµývÕï%T¦Øöb.ÊÕCTjO§®Tüãì\\bÎ_7ØÇKLÄ#¥ôù__-s]°¬Ã8¢­+¶Ã-:ÔònïøÐHîI\\nNâ:l<|ÂUoë¡nMÂ8÷\ñY\\tz$.>pÃ½SLþ,ggâ³©I\\t´rûè¦¤],âËÅj±:ÄÑ¼c÷¨»¬t¨AØO:?7J1§ý2±3vyÐpu8Ä\\tI¹ô²ý­Î«óGç4ù£A³E÷ÐMx\\f$2&gt2üC}\\fó®"ïx7åP*ð°g<Ðãa\\t°«& àb87.£ÒÄRÇü§ÅÎÍJLïYÒ·x Ä:èãY+GmR/'.Ô`j(EE¶@àtH¦®r@4C¥vNòÕÙ-ÔÈ¹nFÏ¶:<¤@'§QË°Äq1 hØa«"q<Ôèø×öäpýÅ­3¨aè?ô¼ØÀkEí²NØ"ç;0{@Üòÿùá\þËÄ{ªÙêOë\\b6i¸6yÂ&ªJARãä¶þ±M¨í!yu7,~8èôqÆ£66aÖªµÜ\\n×Ö\\få_l÷ß¨93aj#f¶²nØ\\rö±hÀÝÌãNoVLzkC"\ëÿL¤[I2n¼É_°ByÔì0VÅ­è ¡ÝÑ\\råë;è®\\r³÷(£W³jv2,,÷o´ª;oµüÄ\\b¾Ò.3Z×R¬Mÿ«a\\bÒë'lJÄ¬wÈì¹®ÙçL½{¬ÏX·É\\rIäfQc:Ä]l³°Õ-¿ýËz)l^iêÚVXÑ#¨¿aþô|y³kæÖ¡8kFcÂCT¯®}e ¹°vgp»âÚMwEõ»ûÎaéµ¯ña¼B¸Rx÷;Eowg!BÇ §:pS$AÉìH#©'\\n²|s½[B\6ê¦ÓÄeLIî$oëÄoßM²â6ÒºwXôâ+Ö·ÎN·Ü´³­Ñ"ä¥pÈ:FÅÝU">~®ä8âÞúÖð+À·ë¹vÂzv%°oI~m-ò«ô+t¹Ðß7"·*±ÿI80Ð­ÚÅföël÷Æo´t·Õ²O4F¶\V8óùjÙ\\n(\\b]W­øz¼ªúiy%¾#IýÒ¡7¹ÉuA]æòãõÎÃIz.4»rx¡³æhìÌ°® ÷â,'Rlâm=Uén©YE¬Ê\\rX¸Ù?³%8oRfe¹pçIo5Ð)»¸*ó$Ö#Øïd1@Ýå=¾ÙQyÀ¼â»}Ì2~Ç{¦®sª]pA#>Ò×KËQÄ4¸ÊÊ.)Þ\\nÐWÿÑG=<¦ØUöMI­ÿØÌe£þÎ;&õÖ,`¡D·6bçÍQ7þÞp!ù}°ª?$Pÿj4ôì9:Wc¾B!.¿m#°IúÍoRªl\\t#/¯À²í1ÀEgmÔéK0¿`t¹QÔøôGlbJhD{¼X]"úàl QCÀtîP\\n7á@qù11(É'%¦è¡1_c[ûIw¾Vßïãø$ ¦õîº÷öÿ!-Ã¥÷Và[£$Èd¨íBÏ=ßù`|§Á0sw¶-»®³aâîôT9FÅ#áu,µh\\büÌj-&iUí6÷3^<Ô Û¤ïJ&dàgÅ~]¿"÷Z¯Fs±A)S¹&ÍUÕd±p¶Á%NDÁ~ÝfX&î ê¨¢³ÜûÓçjø¢ËüÇ.å3ì­s÷úÞØßuègUÂVXØ$Ï#m*Ô1Û28j\>^%("Rq.WãP½pv¬#âP°Õ¾¯¢2w¹ÝfÞé{Rmh}ÁãjHi\\fbãÁAÕ%äÀníÆo\\rWxldÆ>ò¢dFp<c¡0+Bd)_ÕÿêBÉh8 ÇÎº¦þv\Y²þ4ü©}¦.Î5¸®á0þ`Å\\b®êiÚ`©\\bõV¾S`Öp,ÈK¨"§ º2yx/{7¹\\fDÑU1Ëê¥'WuÅëYËkµëLðãëåªDõº~z°ö\\r(4ÖqÃ~¬ g½w¿y!°ÄÜ^Ê¹é^2¤eÏ&%<ÁÙË²«îGÒ¸:)Ö+0±sÍGzÃnØlÏ,48]´§ã:_6ÈcðLXÞ{¾,PÁ`t­·8/ùq}\\tH½P{¿ê^IÉÅÝp~xÍy´2ÎMf£^åP @!ÞÖb3´Çê\\ruC?&x­J³[&©þ2~ãü²ä¹$87\\nKSÉ_T§y9|»E}Õ*¸°Îý½%ÿPw$$Ì³9@f3FÞ<¼¤|YûpH]p'â\U¥æ´T,÷kËõ¿\\bD(+äã¨Åc\\r(ÈW¸ÒQM§ëï\l«Ã¶ÜZwu;1hµD±\\b¦I;ÒÎrê\±ß5ÅÃ´*ë\\t\\b\\t<çù>]¯\\f ðEkÚFJSjç¢µëèz?²%ãÅÝQ§¸ ­=7ä(D¿wÑùFÞ?bãÏ  a\\tÙ»ï`e4\\fÿÏ}£aIö;\\fØJ*ÆÊ¬ä£ìq^2ÔÝ+ìX<Rs°a·0­õ¯DÈ\è 'r.ØÇ%Êçþ.ÿ½!uùÕ^GPaôÎ}Ã)\lþª®û/t»EOèÕÂhrffÅ9ûý±¸q=ü&³1ÒË!¨-ÐÕ$¨(ì_ÒA¨HßÎVº%biþßDB}p­ AÞïßwÂ@ª\\bO£P¤1LOÂ5<ØÎC\\f\\f4FmnúXÄ5âk ²WÝ+2KÛ5¿ÈM×üój§ÌdõêRù+}6p2^È&ë0æåÎú0Â=K££@¦~h\\fÖ¤ ^Vï(äÐ£¸MøÙÊ;Öìöß¯]-n\\bÆ£\\bäEzÌ¼SDSÁâWE\\f__ZÊ+ïc ¢Pf)¹ø£ÚÓpçÎPµÈmP{`»fÑµ)|£e¨1ôå÷³ÖU¹xÇ¸Ë/ÖH&½FæÜ5¹m.áIæÝªñ:ª±£Ïú5 ð5]AÓý1êñ­Äm³å¯¸rµ³p¶ÍÉK,£Ã\\b7å\\fÞm¦ßïcEò*Fri6jÅ"Å#Î\\tã¹ZÜi>y»QÄSmåÇ7HâKù«J"_üé²g_7?Èr\\n®¸íÇî]°«æTýr&¢b!\\n(Ê6Ó^Þþ\\f/W!ïÊæÉ÷?;dlF§DÆGÖN#_Lï"9ÇÞæÿ§°/êö;Ç8TNýEr),ñGÃ\\r}EµùT]mÿÒãµ\\tÆP­ïu}êáà[½R£ui/¦íÔä0=þqùüq\ËJtzëöÔWRq4+k¿}Fþëã[\\b¨U¼Cîsgõ/5ÌS"jÂå¶ý¢ÌLíCu­L5èIhÿÎÈ¹Ý:© |0_I÷²ËveF"sîòìlöù©\\tx§Qä«-bN¥DA.xÃ{rUº>ÍþÇTV+¥KKJ«,§;§Àó«-Wf­¢a{?5¤Ò°4 M)¡~è(_÷|Ô×)È]ÓfLÂî ®1/73þÞ:×®FÉÊYøÛ`¢CÂv´®ÚôÝË}¶är_ð6Ø~kêPöõ \\fJ½üì|\\f½ÃáÄÆAw\\f\ÎÇë\\r¡¿¶®¼Z§Å³MhÐ8(;ÎjÌÓêC³Ëå(aã:ª|âe"ÜÀ«XPXC,·¤qi,£ÞÛHÚ\\rý¸ÿÀ\\r°¢µYEbÆD¡8dòb¾â-¸LÅ´¬æþ8ó%x´>lrsdTÊâWW«â±£ÝVíä\Ò°k#ºßò%þ8z{5£ÉzùL/d½°C:"42ú\\nå?<Æøï-å=ñgÊ£¿¥úTbYCäTBÁåMm¤} ¡m$Ui¨Ýù3ÚÝºÊ;þ¸ÙQsx+£&þ{ ÓZÉÅ¸Á[Úý-Æ/HU(Õtgû4"È91¾ç/xì4\\b÷¥¼4&­óiú&B{­È`q!"!ª&Úy6àû\F1ÐX>_'b®ÞE¨µ÷JMB?¢h\\nÚ:HÂ{}¾¤ÔNßÁl¿A=ÒJ&h»«\\fôÒaÏ¿X'(½{.éªh.!Qëø1x@`Ûó2vÙpòhÙÛBd(©[[UoPæ=5þóUËýR\røÜ4d5P>Gµ¦#âva¤JqsÇ<¼ð4ÜNèÞâæ }é\\f¤¡½1@Â7$Íy­¨å?­R4ÿÃwý\\r(ßtüÄ»\\r<7òw§õ b°ú·\\rS!XÐK\\r,ÿÎò}oÃ:¼(SPL¶}Vcö0òOÌ$ï7\\twÚ$ <ÌT·¦ç¨eè¯Ë:1Uâíû=aÅ\\n\\r^É¶càß¦ª%ÝNlçR Ã~CÑ[ó¼5ÄäWWóÊ~(E­ð.1ÀÕd¡BJÂÕPêPË-S£uv ;÷z-C9i]¨)Ï!\\ni­".FÝ wZGV×T«Ñÿî¨·+Mp*+ØGwb®®åÓaáºßéeÁ³BñvHQåH1\\td3sç@æ®ø(ø¼¹ÿÊáo{a7=Üôo"Hr­ãò­¸±ØF_ÜkÉ<ÆÞ@½6¦Ò¨=Ù½ô!èEÕ\\nÎ\çÅñZyCøîTo¹'1 çßÍ SqvÑhÍ½Øºðô8b§v¬Û½Ìï×a×\\f®¬åõÜK$Ô¡Tùbö¨ýõZ:¶½6g¯ýÞ¡HÖÇåÍ¸f/:u\\f«Â$ÛW\\r%ìâ~¹¢ ,ªIÃ\\b×^Â§!Mj¼fZ7ÇÖA¶,YÉv° Ù[w|àR«ÂH5ÒÁç=|ïåéqÑ®õº+U¾Y'%>³d)©+M*aÈ¾eõ!ÚfÛ¹\\têg}ºý7ÿÿÿsOÑôO·u àûZçén4\Î¬èôÏz¤H¹¬6nEÜðòÆòt{¡PÍ<\ØymfÒdfMm~Fß{Èã¿¡l4¢Äz;KcÏqï}?kP5´êö,Í¹ÌÄè@RmkXs¬áaÌ|©t-ÖÑZ&u¼? à]To±êÛ8t2Déöâ:àÓP¯¦{Uá ¤°\\b¸¢Ngoç"÷âñÏtùl·²e´õ»&\\tºñj3$á$6 Wß·å¿6o¥zxà% g$cã ª¦kú«ZÀR toN ¼Òæ2JKà0)ÍÍ3¼30è:>e4²ÏÆ!ñEÙÐö'Tî¨(UÂÕfLqz\\tpb¨$Ü.%Áñ~¨_9¤O,5ße²C£¡ïµNùíÕ#5º&ûb_®rØÔÔ¶ã¨Zs²,wAEJ¸¨Ë­A5ûQ4@Az\\f¹g²\\fIpFB$\\tãeoÀL! Ko.¡]òdÜ:Èx-Ñª7iÛ#ãÀ#\\nvä­øªWMF\\fãÆ}<&Ôä>#Õ\\fí<ñ!FôV]´ès.Ø¡ìõ%ë«xúaV1%x£vÐyÛ&ÉýøñÌUWFK^C^aVòL¤­ò\µAúBÅXbar{ mÝÆÙ®«øÿ@í@i¶VdKÇJ/ÿ²Ë$¢·ÖdoõS»Ej8ÐóÎgt0ÉjÜ{u M«>ÓiøpÝZÕ;Ô²õ5Sò12  G71zïýú½<CçA-N|¥<³xRx]wÁq%'àm2r#L/(W¶Ê¯Ø(rÁRDø)ûhìÊ_ä©¬æøgbÈ'FßôÎü-öç ïP.ÏÎf\\t2¥ÇNáÄëà~bní¦f?µyT½ÅÈÒ¤%xQ1U@iÒ¥?ÞÅO ÔOh  ó9ÆÎÈú¬7CÿÐ «)bÈD¡::@Qh#*÷V¸Å}a1¹»GÝÄ¼· 3÷©\\bÅN½ÂüÜ¸Y«Hý¢P |$Ëd+Øl¶1º$YrRÞotÜK:ÀæõêP1Îý;Ðá¥jz\\t³!½UÁÔ#«¼fíÔ=Ù!ïH×ebo¸º\\fæ*bÖÚkÄ¹\\b0©hêÊÉ,\\n~øRv³¸ROíI2ZõêÈ3Ó-kÝð$íÆÒ=aDXÖê~¨,Ù¹7i^îp\\t3¾Ç~\\t§$¨*NX¥DÖ®?Ò ·¤ÀÝEõ;6ËLõQ¥ëêÊh`©#\\fãÛzÂk1fgz®Á5Ì¼MUÚ~äQ¸õÿ8¹âZ)gä¦0:@çù¬4ftÆDMóoÎù»ãøW½60Ê·¢Ó,Uìº\\b7o±ôJÃî¼´M®Þyáíh§EÎ_ÉÜ¢¢®,íè<\\nÈÄKJ*za(®vðz25Ì³É£qÆÑÿXë#§ûêBCÙ¥Z\\ry®pá/wè®lÐ°UÞ"Õgv·ë¹PØq76~ðòÀ~bÅñ\\t O©+M*¼^ÏÎòV£¹3$bG0£Ç¿>¼wò^ËNëv:ÂXÌ|ÌUÝE}t«a_A] RV ÞÝþäãMU,1õÜ\\t]§@Õ{êÑý?Ø -¥"²Ö$¥\\näÏôxÛkêH=½Ó®¥?Êm\\bI¨'ZÏ\\niø¸ ·lý\\tÞûrQxÿiåy'XªåVñ\&)mµûPfDê¨Áö\\féìÀéûã(\\be\\nÛWÓO1I´M:×\\tû\\fñ°ðIòÓPEòÈ Õ9ËÜCþD.t«c|n4¹0í*­Xä[¦sDÆ»çÌúTÃ[×¿>vQ¯<õàÉ/]½®·{Ä¹îâ(Õ»¬ºmµkä(®NÖMÞñ.!òxiQ/Þ ¦¢~\üüÃèb§¯ö`÷­H;ôsö\\tjgS^ÈX¯¶eNP\\fçÁÈ_DI¦*¸ý>»h\\fü¤ßjHÉ*üp5±úÀfìÍ÷RyísLj;Þ¶EC]rV´rÈ$.ùü?îÍ²ZJbp$ªØdÇæ°<¦ïÌôèÑ½3û§í@þ¹läÿjüºµZ¥/ÅÌû%ç(o¦-Yõ¼.Ë§\C£EÕÉFÛ³üë«\\rÄ¼'¬t@·×Þ°Ö¦¯£ \Ø®Êã;¥µÈ;Gú¥\\r½\\bu0 ÜKªßÙ*\\bu:g¿×êã¦Úì¯ìêò;8|LQ¾3ysÂGc',ñhàBfHùfÚ¯î%Rä-²FøxÁ¹V+W}4¯Â@¤¨:h\2?øf;u[û¯@UbÊ¤ÿ'°Å!§\ÎF5#k¨¼·KÞ[E©L\\nØ#/µìç\\r­¢¤Â=¤¼ÀS9`:4WU°gáý¹2¸ÐGÑk³ç7\\bOHýå?`ý:_ûCrºxÖiåóÛÚR¹qXJ1IâÕxCé\\t¸Ä ¼}ü¡i3<eÔ Å®ßÏÐp\\bz%£ú(E³LêEö\\beCLÉHe¤KteJø~5©r{dÓ8hîª)Ø4Ò$\\tôi(\\r%fÍÚ?¾:´Òt!cwÛÊ×MióÌ\\t×ãéN´ÑØæ(c}à¿öZÍ«³\\n\\ne®Õñ\\tÒ\\bÁ¾pôÁ·)®´ô¶ÓV1è±HÒïÃ<`ÀD`¦¬7¯Õ^.tÐT~Ï¶¿ôýä-Ý¸¿ÁlÓMJS¿lÇ/×}U\\rë|\\n9ìºì1}-â«9Ù·#w¼ï"}ñ¿W#ÁMõÏÈ·C¹Çnpcyêh°Å À*py"Vù]© Ü]èúÉ>Äg!áJ]ÐÄýn? ]zð\\tËHIP² DÛ\\ná«6b¾yÁ8$TçôNÃ¡Y®¸j»¿8¹\\nWS¯©h3Z¤â34|mÑ«`È{¸QÀvÓðSKã+dÆV­8õÀ\\nÞVßK4-[ò¡cwË!59õÂDvÏ¶ª¸ã¼puBVà¿ ²¸ÔZ®SÄÃy`þôÝÑÛoÄÀ%©«%I#3Ã6øû,rNUDíÆíÚÇÒ­A®í¾±«Q$V.Èäø<"çëAÀf©)×äGH3½Â1LiTrbWè<¶\\t\wÈö,û"E+m#dJRz?ç¹!ñHÞ\\fÏ|¼ÿFÚã¥Â9Äk[Æx¶çÊrd©ñþ\\f#ÝòÌûÿ]À»)è%ÎØlj?aÖå5ú0]j=AMq·n®´ë¥«^ÃÞ!üc©0<Ô÷%"_ ÔFÿÌ©?õ\\r?Ifï\\fÌªú@ªp}¯·BÜc3A\\riÉ±ÉtøõµÝ½nìM_ÎÔ³¾×ßÎÇ&¾eôºüJÌ\\b¡@³429(52ízfCÑÊAâÔ17\\nÚÅÚcJ·Êé(Ã#×ç¶ÞA pzûSõÆ¯t~Æq¾EK3°ÄXjÅ,ÇrÚÿ^ý-\\t#ñ¿Ü[]>³Ä>º6Ò¦2j*ô?­f-þPmqõU[%:×F=Nt"õ®&áÁq®àéê¼PQ¤zX\\r«h5ã 4´8ÓÄ¼âí´<·§Wù6UTË@Ï,)ÌÛ,ÈUäûð@FÒA­fIúµtèv(OëÕ0¸O¯2zoQjeÕíÁï¯Èr÷°½Ã4«§è7J¨G\¹¤6¼BVÐXE¯q¶­ÜÓXl\\bÿU[7»nUÑíHoÀÁ/uÕ#Á<Uà¼@×ÛüF¼÷ttÐ&W½~*Í\Eoæ½°¡\\b#üÿd&kòÓ! Ð¿Ù%nãW5Ó}3Ð;Q3»Bá/}b4©ö ì!T\\r6ç´\Z¾¬Ù¶Ð$)ÂTF·®ø<Ñ¿6ÏV@°¬îëð¢J0ÔÅ¢ß*ZFW ÜhúÙ-¨"A@_OT©-éËóïupJAu^âÂG5¿±Ê}e1RPWØ´5¨£èH-Ûo±,Ü¬@!Èù#.¦öÉé`f]\\b9}¥Ôá°\\nJð/EÖ½/è'D! ÇÉ"öiÄÄ6ÙYÏåôgV© ¯ÇëÇgÅS·×b0®7Q6¹ÓI.ûÑWµu&5¤´=¿X®jÕHÕA\\fÓÏ\\tèÁ¨°ªFðoµð¢>ÛýVcàÕ¾;ád¼beWÝ¯ðu¤Bíþ\\r¬ãõ7·#7&Ï¾ £`x²jKfn\\tÏëi/÷íâÎHG?×8K;M-àEá2´Ý\h¨W!$)50K!IFüN&íU9à¤¯ç=°Á@M\\r4ôÈòé³ Ìm`ûB\\r(æ\\t¤Ê?vÆë®:IWg!öÒë!=½oe~S#¦m#û ¹8ÂGQuM·AOc¬>MÂQe¹mC¼[¤X>â}ßaÎ§ÁÆslvÜLY\\rLòµà¿&1\\rÞ(óË°Öõx%|µÊ ¤¼$GÿêÐåv§ÌCºÙÄ;©/Ú\îõãÖìV°&ÔcþS`±u7\\b`È(,èêôh¿¶:6,*ÅM_®¬o3®íÈºYÿbïH~ ¹;AÚ2ù«JX\\b·Á3Y­YÅ\g®0¼`iÚ¬ôm×«0B:UÐÅô­§|`®´aÌê¹lÊ\\br²aEÓ#1þõ8P²âé¨ôÙAÃKD`üýÏO!íçìr,aï?Ybh­\\bÝ!ö£ø°X`r¬í\õõÔ¼}(TlÃà÷L)xm^oé`b"@©­Å=!ÿ.çñÉ#I} Óµ»fæ±Z~{Ä¢þ8ñ½7µ$Z!ªThE79Æ>sÿÀ&ÿAK®ù­oÞBNº^~]sáádªíøK«­miÌpõ0*ÚMëLáAdù`ÜmÔÜë¤Ú¬jõÏªÊ-ø:î¾y·¨iµeÞW8U²ßÑ?ødí§¡a[½åÈÑ/:½ïÚür\\t­ÒAX"èþ2½eAñ#ÊpXò&zÄYWL|µÿâäwwLH|WO@]WÒ¤¬V¢AVüÇïØçÏc¤ª{H¹¬\\n\\fä*^®XYÒ¤æñ\\bnÈ·{¦¸:úÈ'ÔzI&^øð6òuRïõ:Ínë\\t²ÄÎèÑ.é|÷ÍgÉ²¡kJò%N¬1+<aZ±£O¶nß~<ª7ãs_\\rí3Ïl_ôz>Z×uxTÜ=¾ë¡{)\\t9/Maf©¹¾Yæ¦g/QÀ5>J®H~Þ»p¨I-â«%yËG`c`¨\\b¯£Ü´sèi\\b¿\\rø½¬/z«´ï±tÍ¿²Æ_¤ÏV­fÞ94@ÿk\\r¨äã\\f\\fUÏÛDëã»!ÆK[>z³\\r{~E G®ð\\f¸ÄÑ\\r®õ+6$q$A=ç÷uiáï{Æîn[EÎ/³|GûçtBº¦Ê+´ò°¿ìÊj0³ä{.iÀã¡[wSÇÃ0y7\1?Ù«¥±ÅiÑVuë\ÓÈÜê&ÎýeÝÒ"=û[Duk#ÈFÖÐ²?k\\t>xÇ'Sÿyè¦ ÷Üªôk$eÙÎÕP)ÅDñ:ö®Ï6AånRáTO<vÊâþh¬þÝd(:\\thÇC×½\\nÛT]íâåZ2;´¼ï4ULêµ8Ìæ%ÿzEk×»¹}£D¢Î,ø 9±°`1kZþÛï5<Ð×c¬,4Vï«â±^Óû×gt÷ß¥ÄW"¥3{_¬Z¦ÒiaÛÐeºDÛa×Q\\rJ\\fé7éVÖ ¤Q&P³Ú \ÌØHo¹Ü02*î·9P¿£:á(kÒ/ÅD½\\t«9OozÀB=È3"úüéê°úTí/ï ¤¼ÓTÆ òÒÓsïç¬À@L|Y´ó\¶Ä1X\\tW\\f\\bIDÔ×áúû¡­ãÖ£ínVs\\f×bÞÓÆ,ÚQâÅ3\\r¶p/Q#byY©e¼¦m§ú°&ÛeøÒ7 Áªý%ñ:vþçP·gZËN¾,hìi3-±_(×µ®ë¢0ícO\\f¶Eß\\f+·§t¥Ô®P9\\fÚú2¿²ì\\n`óºcÖ`ZèwÁãÚ·r=Î®ú*ûÒÈÂ¹r²¬Àz #w´úV¯u¤\\f4Àør­lÈÕBd©F yKÃÍr?ö×k\\bKuÜÉ¡q!Ó!:z~WÝ\\r4R`ÍóØ<éL¸'cÅïÙ~ÈMX¤«dë\\r]wy-Eà¬<ÚÑÆß\\fô¨¯¾Gñ4·\_4ÝïÙÆë\\nwúÓ¾L¤àq6 Ï´pßd£ÝçaJöäæKp~h»~\\bo8ñD³Ej£Bx~t.²À5D©)º1R"+[hGËñ³d¼¼ 2Ó´£^X­;¸]ú©iyXrÿ¤ü\\t2{ùÎÖ ºÜôÈSØ]ÓØ°Kq0Ûå²g\\nSº=hR©Éø¡×³ sÚþGý´S©e)PsB|\\fñ^,KK+§|Áû2|7qÛþ!¨Þ¯¼5õ×\\tS~8ÿrâ»3\\n1#Z>Y s!\\b\'{9 ¥¡ÃI_ü-QÇ7l56¨ªbJQ(ÜìX4m<ïÓ>E¦\\rd7¤!ñ&ãó%j"j'-oQ×{ÿÞ°ý¥DIÁO¸©%Ù¯aà£x\ç¦³ä3LáõêIÆ FL \\r\\naÌâÔ´ÕÄ©ñÐÿNEeó·YfeîPE\\râà"Çavfò#wÐ]Q¶bÁõ\\b*Éûcø*÷v¸ -=7YÎ¬nÊ2n ¹îi\É]Í@g!ê\\fË¶ÇÈå¨¯k2u)´CX ïE»²´ÝqDµMæíKZáù]=Í-mÝ~© îO¢z|(A³B ß+!êG\\rÇgÊ[8ÉúïóDñ«ìÎÔÓô#j»¾Õr|MR1ùE×åÇ»7S¥$1ÌÚò\\tÇ°~Ô«\\r/|Lß½[ðì]`ª»Æ)ÕFqÙG~uâvç6¨í$$r1`¤äôÊmoSåhÙú¥14ë²´}ÖNãÜ¯ó<9>FþÊYäRÈõ°HînØÕp§¸û?/¤Ãw¿¤¦yÚ wx'T¬gøøJ§»ÑjÚI\\n?-z¹ÍKç®ó_XzÀ`Tjò\\r[Õjð¦]ÿ´mýægÊÉsG0Õñ$;¬¤ÂÏûúW®ÑÝkÌ­±µ¦á«Ps$\\b \\fxµº\\b¡\\n? UçqûéZi,J}ÕùGzH=Tì¯Ä\\bBoæóIAPx+xM\\tUzO]Ëk+õbÑOs#\\tf}u¢çKvÐ£1ÚáZîÊê:¤&ßâc1ÔÙMîç8Æ¦ù hoZ\\f¹\C1¿ús,=_øÊ` .»ªÅ?öy¹]zJäS$aývg}ÒØÊDáy5Ë,­©\\nr©Ë "<l(®#l~/@rÐÑzñAðKD¨s#^aÖ?ÞuÁrÝl`÷Ri$üqømM<KÇ@0òsTÅIA-ÿöñ\\nXáëÁ5ëf]°ÿrÂ½ÑÅ M¡TË0ÔAomÌÕ6ãVðrÛª#ôuª~ôã9°Æõ·~ Oÿw³NÁé(5Ññ[RBq>dëÓWG»µhËa~ ^sú"nM¤\\bÎ5p¿7ìÆInº÷Ég§kFb\Øú¿3uÂÁ¦8Ôü¸xÒû®ÁWÔÈÐá{yÜq½sXDÉ+O "{í\\b\\røÔríqÔgijÍnÚhîsÞ^Îà®aí\\n:¹ýì× bat>«<¼õÐx )³æ\\t^(hO½ºt>?ãºrµ{YÒEX0ÐôO¼dN\\t)_Jô¤Úïiýî« i Q¬¸¸ïýOPÊ¯@ï%`q²îö¸¥§vø -·ì`2/î·I×@ð1Ú©æà÷¯ÄÙ' ZTê8©W CãVËÃD6éí½HÉ4[âòëh³^[Túm3Ùb'w¶3·)HÍ/Ü¡¹füöº(#h±\\n ÇÉ -íÃúUÄVôÞYiºCm¨ýPDbÛkâP$´|"ZìýW>¿oçÂy½³½DÝ àöq~ºÇº«H%H²1®®\\raígÅ.Îe~d#®m²Jám÷DÚAÝtïoßI«¡Aò?gêJâ\\fr[a@?ä\\fIhÍ£}êKå>Ð3øööñ1º$Åðøª«ØãÝ sA1^GñÁp\\n4a¢SÓ3?Ï±P!g¾©\\b}¡²£¬Üý\\tý·ÃS]2¡æÃõ4­ÃFT¯Ñ×fÈç>òdnùß) 3dÜJn\\n$XÎ?@:fÒ`j»Õ3§«D-Â»øÕã-»l­A+wdüj>ÜDÝëOã ÄäÂ_RçÜÙoU½äõ]-z¡7¬ãÁhÒç}fÎ¼4B¬ª  s!øT³âlaÜ\ûv*ÿ©oÏUê¾åæ9\\nv¯R4â*$^uãÉIf@ôwÌ·Â^\\t\\b%¹õ:8Û\\fËjD§\\n1¿Ø¬ÎF_äØëfF»#FÜ/R<d¥è#µköyöO#&\\n$Ú=!º%g@åHæÒ÷ \\f ÷R¶4sDÂÉÉû)Øó*ÇïÛþqV¥ãgçe8° ?«ÿ«Û0ú&c+xÝâî\\rÑbX\\bqÿÁmÜß\\bð\\tÝÂ «×«­óMKúx©º{ÒÜºüK8pfÙjªÕÃñóð¬Y.C#°¢(õÄ³\\tü\\f8T¡V¨îÜ4Åà  pp\\nÿæNêñ´Rhí]^Eå?d;õÞþPÔi#Y­³+ia6NUïù<ÄCÿ¹J½&;m2ðÔO®¸£u?;r£Uøíò®ª\\f´¸ÏC7ÇcÑ¶ÅïãrÀ¸\\nâMmø}ËåT>f¦;¢\\túíSüì\\fMcÄo\\ty)=ýC\ôéÇÚ|XaD¥ó§ñ×p\\r&ÝZ&üG:5ð¿È6©ÛÿC²ý8ó!c5cYÐEª¿(W¾ü¼¼©H¦Øc~.oÏð\ðD]*$q¦øW]Ç¹DÎKµgjú/&$,Â\LcËºÇGA3FéÖ#¼{"ÅqóCÆM\\rèð-Öd®ælph®,¡éaå\\nMØ¾Cæ\\bt¦Îmê°#po3ó=Ì×»øª¥_æS\»«1û£p)&á2Z^¢Ö«¥ÿkk/W}©Þ¦/´Üg^ÿP %ð±yINåÙ\\tû4IÎI(};GÌÍí¥*SK*ùÐÚá¿%\\f-ó¿4aã\¾×·\\nÒF`~QÈbÝØ¡ØÂ3j:K´Ï `µÐ¥(Ó\\t<Èà\\n¦µ\\tª´[s^hÎX¯nh«{WdïN¢ Ûêcä $oÞ#l*ÏþÉ«µÕ®Ó(Ôß£î:¯8»SHÎÕX^6ÉÊ2\\nñè\\b¼ä¹øxÝÕîLìvÖ¯òç»ÈÄß­f*©À«À1[¾Yn\\tC£¤ådY9«×ÔÌmÇãVWéFÇ\\fá²¼y·H}5q \\ttù`P¼1ÏÍ@W@÷óêW=ÓZ^ùØ=ÍÇkê\\nâ/µ¦): o×:lÌz!ûìá¡Ñ;DZtd:®}Êâ1 þÈñT Ú,+®\\nu­Èî\\rO¨ÈYÔ|'³K\\fWiÑ~ÐÑ8ß^k÷l\\b°82+Å ­+|öÂ­!·µè~Ð\\tþQsuó¿ô52»Yq{CÃÏÔõ@Ýpó+äø«1l/v½tw"º<ÜÂ :\\tô=ùÏ"tý'sÍaÆbæ/w*ÃPªiAÞ#ï4Ø¼h}î¿y'}\\fô À£Vÿ@+=³e[VÐ%q@õ!Ñ¢mÝZ¥°3>½FñBfß¾z¤8x°âRÌ³¼ï¿àÐÍhëGàðQ·.éc)yB' e©x\\f\\t¶$ìÄ¤v½_Tq¥Þ¥«"ä3]&u+jx>]ÆHL`0OX¿G=u+ÆØÖ#@ó ß¦Ödv!Ï$vy¦å>\\nÚ\\b%°1å®À<=ï+³K.»ëÝI£:L¼Î#RÃFøØÏ·fé`¡ëðíx °fêKòÛ°)HÕöÝ<Ã<$e®¸\\b"<*ózKN3\\nÇ¡ÊiÑä¯^è¸Ð(ù¹¿9¹ePÜhT»-×è#||ìæaê&1ìx!ð.leÈFfïbG(ä½½KÐä&ïÃËUfDâíì\\f6jþÒvþû,Râ3c°ì.þAAé^Eko-`IGÏö~ X@/Gòç3øS@FãÙKw.@ÆÄmªj+È"Ò\\r|¯GRÄÍ}¿ÖëI i# (-p¥AgöGªêçïà­8Ä}ôMîá-àí¸øwÜ`nÿkCÃiù¼vÕ­s2&xtÈ©HÂ3Lo§ÎçÉWïAB÷ÑÇåBæì¥¯Ãð¦R*r ÎÈôhÁJßÄçÃ\ÎJu§+¼¡6i«Q[tv!£K\\rJ¢@»QÖµï¢ÑìJÎÜ\\rÅL|_Ü7Fµ@!ÀZ>N¿XÆUk´1%*ÊqE³÷ z\\tDrn;\\bÑaãÐéÞà0½Ð\¹®Mî¸nË»»ÇbÊ.CÎûEx6¦~ú±uÂÆlûõÛn|\\n¹Ç7~CÕ±Õà¤pßg9ÐC0Õ^Ï»Ý´¢Ú<w¦\\r&ORt~åw\\t`£7IçGy#ûkØ:.8zhéó¼©â÷0ÀX±RçÈFÕÏþQÇfzÇÈf]æ;ðkÔ3sP\\baJÒ®mË"kòkH\\f¢1<2S¨ù]2Vk¤·\\nçq?útf\\tËüR¶\\rMoÀÉÂ~rC,ô,ÔÆ.Y\\bn×ÁrÚìÂí0áÝµ\\nBôTrã/å`©ÉNò¹|:Ô\\t\\f_º¯öá>®È3Õìë¶»Oý¬ÊÜ§" q*t\\tÿgÐpEEÔK©ê®ß}ÇzsÿN¢EÆHjÝÓèaË^{ç7Þß§0ñ0p©ûLÔs¹!Pbô/!F½Î÷dþY¡D÷|9«Îp,$ºeOZWÌRÐÃýùXbª"#å¡Ò%çìzúñå&ú5ºoÞhËd-}ºÑ©Cfé.æ¶ñÑ<k?ê3ôK÷\íFÏ×5QÐ]åã GÛ]8DÐ<°!×\bAq\\rÃ@«f] [+`Þî7§èu}µÐ±,`»;³pFqdsÒ­Gõ²V}þÆ\\fT8³NE\\f7ÎÖÕ,ñÿs¥kF#âæ¾m]#>6yÀ6rÌ^(Cö%èªE s%:q2Í¿µéårâàF *\\bäDÛ¾ãSvÁ }êÊóÂ¥G3~Ñh6|ýLÎhV¸ë¶Cõô\\t(ÝÓíú>.6_(ÂK²Aâ¢"úÃ>9z¦½ÍËPdå¥\TKòÚÎ1â¶(Ô²(¹ÒÒÃeáÍ8ÊZ\\t1Ãÿc=©Sõ¡Ò Tçv|V·m-²>?WÏîµ£Ûn\\bÀ×Ñr¾h±BeE;¼8Ø o¦³`d¼«àzá÷°¢$pXTs9>nýý,öÜFW¶°EP Gy<Oó=§ïA2_dîëÍ\\fÅS\\r\À5í\\nÜ9ÚC}É¤/Èø­9fË×à9Á;):1GIQr>¥èlN@,d¢É'ÈxP¬ÜÄöyzNÏ#¹ü·<ø{*Xl§Z)îÄ¯6§'*K°1ØFÈÝUãÓò!Ó¡Ù}Ãæ!´q÷Ôñ®ãek+Ã±SC¢t«ªR\\n5\\nf[yêÔãÂòNþ¢à²çácÏ7´´k1ÕôÐsÖ*Öå8SIû-´ÓÏh3vbºlT!þ¶zô´Ùî!Ê@ü^º¢wÀ÷ÅJ·Æ0&K_£³êµTJ#ÆT.tO g¢ Éþ:âéü¶Eú\\b±TêåtnþF\\nHN* À7è+qxh\\rC2ð;Ô3ý2ê%ËM-fÖ¹*9e:ßlMy¤^¾ç ê¢OHT;ÀË*.ÁÓ*Þ¼¬ýö§%×Élì¶ 5M½Éÿ%&ÏÔ>gJÑØaVîÊø9¿Ýæ·KAr¯@·õ:Ý¼ïvë«ÐºkJíøp-/'8Ø·¦÷\\f_ºÁ1 ]æqÙ¿Äø7Â&Jñ«_kÛf4Ø(`¤ú2îÍÖEèõ¤z¦¿<÷S7W¿µ2² ÖÛkêÍÇüë£xUÀÝTúÛI¦@øsy-)3¡ábnÉ¤Ááqç0ùO7<cÒúÞ¨J*nñüâ+²{­ÜÕ§Oÿ- ul´Åü¹äXí_±ë¾\\fÄrwKÒ4ÈhqÉ¥íhí «m\{w6ùgsMò$\\bOzúãTÚËÿLº`)õsË\\nÀHÙûâ\\nY=¢ÒÔJ?«>øµwô1m¡÷dgÎ½n47+xz¨T% ¾\\r b±È´:¥¶A¡U2sO\}×)LAû\\n¼¡q#¤1i@\\f{ýzI[WAå©3\l*5x£Â\\fõi¨^QËß+CÌíõ$îÊðcðýú½,ìMkæ_/´à¤Þ;ÓX«LwÂÅcRtCªõÀ«[,kyÛëý^5ÀÑF?jwü×ÿà_)ÿ ö<Ùù\\rUÌofèæ O,ô/¨vD=ÆMa²PwØÇ~\\néÉ y-woÕ.®5i$§Ð\\fE®ð@¼eVÔ^­é¸Ca{j½¿ä1P÷¼Û³°6HBqoYÏ¥Å@m½¤X¿·íêØ3d^²¢)qQ~Þæ-\\fæ\\r¤âôÐkyü]êåwÂ;7ÝÜ9yO0äGU*·:¯ä_-ïÙqÐ¯§ QAìôTÿX¶æW<±,ö½¾ñÕÈ7oiàþ\\tHUGôûµ¥ÈíË@à¿Åh*Í.Ùwj~p¼çòîèpÐêF½ú®xñ¿&²ØxíT=û'1[·m\\n`O²èt­ìë5±áèBk_bÕ,þ)fºðøgRÎ¦qÊ dU*]Xæ¡þÌßM÷\\f­%'H§DÔÆíúâO`ReuÏÄê£\\rÌBá¶ÂÓij¬ø±19txç%ÝBÇXôSyàÛlÕÜdNÛyØc:ïr9ÆÃêÄrj7Ìuö;wIÔÊòwØ;.1·§¿ÎýNïÛ®á!£Bm\iÔHÛ±Çts#º°m¾FÃø¾õC"/dtÄí!!©¨*KÔ#Öå\\rûÆ³ëxæàC³¦»âó±~\\t2Æ¢mJn×Ïxê#q"_tUuï®xEÄú¶c¡gZ@ÀA´{ãLUxpÜÿýÐóÞÐîº-õ:.êÎy\\rGhë5`cWä´l4ÓÕ#\\t)\ký2öK~#?§äêh¯7)ü?p#"dÚD=ðµÐGrùCðcØ½8Ñfj?ì×oYtN§=jÀ."¥Ä±Ý·åZ¼!"tã$ö%uÿVD´­FÊg ÖEP¿J°_Ê3õ\\føè'Î`SÊðIË!F¸®óØæÂÚkÏ8Z­}¨øKÔuÚ XB\\nÙ¥AÒ­gdØÌ¥Íì¥õû 7^MIN°<^Ý«ïnÇ»ÝqaZÏ§Ö·CìõëòuKÅæ Wº¤{ôñÅúÑ\\böGuà!>Ñ9Õý]Ia`JÁèb©BÄúì¬Fà©ÚÄc\\bggmoydÒ-±btaALîUÜ["J¦ÌgN3D(*Mè;ý\\bÐo­¢qiuæûÅ25CµW®\\fÈ¡N .o¹Ñ$uHÄú¾ANÁhOû¶aZV\\t¸lBó&*<¶qõêßÔÐñ©tË|åÈâªð$\\n#Ä\_*"¹&'BñÁGX¦µGiÊsÉ\ùÓ¦$k.\\bøæ.8NÎ@ï¥+^ {0sÚ·F±ÆæàÕ¢ËV2\\f?µðY¾Ùâ}jÑ\\ntT\\bÑdÕúXMß9ÒI¥oIK +[|þV$\\ræ7<ñÁfn>ïÌeK\\n8UÃg}Ñò´¾X°(bÀ\\f-ÿd¦H~<Â¨7`KÙ¥5ZÃ°"miÇi²Júfcýx"2H%ÿ0=4à[^Y!Bèãõ^êHDðÙJ5^ØÍì^Ã7.£Õq5#«ì^ÇWÊþ4zA)Ý²(ØÇüðtÔv¿kâQP&Áõói¶î¹ÃSñ¢Üâ©ßMµý";.ôN¦Å{ØÉpcüÉx0©ÂÅ;ßGÛ-òjÁ·+²«Æ½Åþ.êbÈ á bíiIw3qúµ¥ %çpU¶ºµâÙ²Vë»\ÂðãèçØÄ}K¿,EENP\\t£±<w¸cFuI7aù>|íYtÝ³Hnn-£íÑ/@ÊÛ/.Ë\\fÊîR9EKînä]=Cw¥²GÂ÷Æ\\foö¸XÝ«Ý¥ù«MUû>Þsð'Ùåà4TÎË":g×TÍ\\ný¶xbÜ<ïË¦~XÔ670\\rÚÇã,¬X8ààöå¯y&k´Ñ½¢Úb)ùï"Q4RJ^Ñ$\\f%í`G}è6 VPªxGý¥Â]é>©^\x`Q§ºÔzst»ú-ZP²"ÀYâjWÑ°øazRDÎ'ùpÊíqõe,ëAd\\nÿîÛ]9[?Áò?[úî84\\tI4R£¡ªu õP9xÛ¿/Ä´²Jô©¿KÑmüè"43eKZªØ.D6ÕÍ{\\bó>«½­&¨{¡ÃÙÓF)4×Ä³!õ(Z$·wnën y[¢·ÇÁÊ\^áÏ"2³[WØò8\\fh\\rôÿ,ÌÕ·Ü®¦Öô.ºÖ°¯(ß¥¦îúoïÏpðÃªâ¾¨kùîªözÌ=Á (µ¢_¦*BcUw÷Ó,ß7OM¯Á403Éüq\\nl%I{AhÕRQPÁºS,èõ@æý¡De$Ob¶Ü²:Á1÷f?®ÂnYó½²/nbG»ú­gÖÆ÷ÏúúP¾8öÐ%ï6g\\ràË³@ýu«E'!Td@ á¿T^:*UF:ø&p`êº\\ràã¼ËÞ¼R3*ð¿C»w×ûh·½9*ÍãÄÔ¾cg\\t>?ÂQ]æ ~àé9ôÞ²;M57BÔæRÿ½ÞC«ÖÑÞÁ\\nH:5.ØöUIG§\\nSØQª]ã$UÃB8ÁÅLñ¹1ü:Ø9OÕf«Hã/¸töâoÒ6¶@².üÒ_Zö(bÆMÈ?ØÝÊÞèBDBÛtVðu%XAÊZ&j¶úý"´l|ÛîtnÃ¸}èÂ=!dÖµ=ß½úïÙ§.ºo3þFI¢r\ Zû%hó¨¾ÖbåÔ¸kP*uõ°ê¢uØ>ÿqSd©O{äè¼Z\\fÛ§°^;|½J@ðYY²ª÷\\féÃ_Y0Idßø¶ASpJ÷ÈÃl\\nÙ[¦óS«Åjv@#@ñdýü§D½ñ¿á\\b³ý'þ­CÚÆÕjÐHªF;)Cd735ïa³¤1öqÛ:w­ºs-#ìµâx)ë[iÎ TÃW¯)x(ô½\\bé6Çl¹ÊÄE'ÚÑÆAä0îÂ]±Îö¼PIÏYY%>Ìïâ:É!³.W½"¢j\\f9ØK+`ï+Pð.°ÖÝüóêüÉ#Äêpv?°[VírÉ(n/7Þò\ºFç&w+¶ÖóÉåäëYlrx$ô4¼\\r°â³é´Ðø~éÈü¨|ËycPÇÎÃcªx.ëa¹FìÐÝ¹mgxèçù¨è£ÿ¬ôMÆ°²ËÂoØCið¹7X6·ãoðæ=-½X¼L_ x.;|FúNí¡´Â *NpP6¿«$Ûâ?9 $«]J¶YÃõnÐÐU_ðn²m½¡T)ô¨Ô-.Í0¹¬ÁÊÀÜÙHiMó¿ø²g}hùEo¨@-\¸ÈÅKÿìÄ.[ëÉT=ia{µÑB§"¡ò óf6J30¦KâM[ö§±YfJÚ(F0}ÇÈ}åo9VñèùÆDæ]m-¹´©ÜTÓû 1é8ÊÝÜLJs`ÉcÆ½y?"d­ G<ÌÌÖ½þ½c®8?yY\Âiè)Ü÷Û)ègE³Îà@¶Iµ­c°ÀHü³Ü}§tøYz¼KDÌü¸Ç ´Óñi]¶;ÙD|RaUüDÚ\\fVñQãu³æjs³÷ÍqyJE?1x\O2jzÚîA¬æ5ksü`Òc\\r\7-=sÎ×¶óÍZ÷\\f5Ä©½gm;ùîèçf£é²é \\r®8¤yGhh°¬Þfþäâ_Âkù×Fâ»"½\\b%õLÊñ÷µì/­¯L°£6¶ç5&È6¨°\\rNvïhÆ;B-b3µµh¢õëD@,±0×\\bñÃëtÂ{7NÖè,:G33"Vìd¹ñÜ¦±«·ÌjYK2\»³¯§6lê¥IÂ»·\\fzß¼¶qÓ§h\î)®&aÜòÅüÑ\\biâÂ7,G0Ï¬m-Ë=9ÊfýÓ0ÄÐ÷#py>:édn¨6¨óõ|øùEË1å¯ýÁØ`r¶[¨¥B\\nb/-]Ô¿äIPá2M.?ÅMMª`lÁÛÅQ;Ì¦JXj©¡MÖKXTìÿ(Û°¨ÀÞöÖÌ"Ú](X'NTfò/õc¥TIÌí!ða>wNh£,½ÏëXFbª°ç_Î$ÅFç¢ópCµ­u"I#&5ÀûRî¨Ø^éz9_\\t<N¥æ\\ráûZíø¦Ks«eveÐ«Uål]áîï¥]A¢ËýDâhzÍØÐ¡[½Áq7áíúÈ)3,±)ô³>Þ¸ð/¿Kê%É<µ5Çúî¶X5ày<}3Ç÷Þ±È FKi7/ßÕój¶N j\\nÈ#-Ë­BokasÔ"#h/^XeÐ4Äåj.g:]dÅw¢Ñ'\\fãÞ#Ó-@/È«!=1iö:ÎÈ^^Ü^ÝÖ³^§)§¸ èÌ­¼ôc3bvÑÑ®ÍE ¬ à h`Ð¥\\fÛæMä!K¥H Y\\b2cÆÍTz¶¶FgÃC¥Î+É\\f¡uÊ¯Æ1Jâ\\te/ºXz ',¾N=ÕxxgZ+Õ¦ÈÛ¥6Æ RÙ4rù$DA§{æOsJ\\b'µ1Ag@Q@:É)éàß à¼ý×8C2Øî£/ÈÆL>À@\\r\5P%8N\kÌ*IhYkX¢9¥9É<MrúGfiý³FÀêÆçóüÞmÂ6VðmÌY¡¼2Ãz(´RþUüÕáÂ8];eéH¥=Fâ·qUBÜJÝ*÷?Óa¨TpÀ{±g%m<ó©Üi<'DpÌ¡Ì®E¡G\\t2&jb =¶À¯_LlÀJ)à/C4+¯µz{vLh-`§cQ7æè\\rE¨SÛ¢:&0ÝåtH¥RÜo\\fë² ö]NlrIsÈX^SIãrÖÜèzË§²6hFjUm¡{e6÷·hªOÈìpøè½ù_èÂ çB·\\r¶0`\\n&4528Õj.d?lëK#NP¹räîÿåÓT¼ ³Á8Jâæ¢Q*pF,2@bS|üñ¾gw¬­~=þîâQüÂÙ\\bD}Çk·æïã£ÌÀxÔ]{P?º:EºF'hé\5\\nÄáÃ¯Ñ\\bSÙW\\ná£èû2Ú`\\nKDDÝëôÑ°}Êµ³æçN>.þä~ï½så\ÅÔ6ß;ãA·¾Jpé:APÎa¯ÜÄ¾Óxq#Ï>od~4ÂNºIÕX^ðDbFÈ~Ü`~^\\nT/ªôËybûñ"§c.N»ñk\\t¨GÐ£êZåôØ è`66òô_Aj¯,ðY¥Î7õµô:X¢¤=V¸[ÖVðÝfáÉÖXqDX(,Ó·Ô#I8\\fâ¢¬ëÄz½CE^ «ÃÔRhùÀÕ':ÐÖL1¹Ax4¡Æ]ÖFg\<ëþa¾Jp-àcëÆOã}}§zmÁ6Ð¹BÄ. F¹º÷ IZö²»¤\ëñ­QæÖzÎØ§É¬J³Ïã@ê­ÏÄÓp­X«\\bÉÃ½rDá¯ÓfÛÀc=Vï4{òx}ùMâÌ0wÐ¡ò?[<åøÑ=K»ö>ug¡ÞR_NtÏ}ZýNòÙ±î·©C}Ú½kÌ¥ Â=ÄS¾â?R"ªC«F±ä[!kÒÄª}1¹êú\\b1ßî\\bþ[¾ô²(¨"]íú"A.¯}èXé""íPôçæ³ ì =¶þ@#ä­F`Ã_x=¤â¡-M_^åKI³D¬üÃ+@ê¨¡)¼\\t¥6êú¢ b÷ ]"{b¶Þ\\nHvö\\bó²oªEþ\\tNôÐ¡0æ¨1Î3¡|B~Ôf gÍ(¾ ùËcô\\r×\\tl\\b±\\fE­Å¡BjÍ||A¨ê2µ.âÎÔ5&µ7i ûÔÁV:\\brAþ7IG¯âu3³|}É¢­lÚ­ædj³¢ Ù.øàÝôéòút/6Ô1W}&$DÝ±ãÅcÑWUÕuÏuÃ½àx1çØtàÙ[%ëÃ]ÿ\\t<ü6xÅô¸]u}F¥»tÛäé{èKëfÖÇ9ëåÅ:DõfóZ(3S"3ÁhÀ¡Ú¥b#¸u\\rÏ¢©Wü÷ìGÀÚ`µÇ¬ØóÉn\\f-=Üñ/#FíÔä:ÝX~tì÷¾!Ý¢°jGõñÁ\\roðz1Mie¥Û&m$Àg7áWÄèµZ¹@ã°T è¨¥k¤yILk]mï7ª?#¹côõ¥í%¿u3³@M MM128RI\\r=AòüQ ¬es]ça{íbWt\\t¼ª\RÛ®µgÓ°â§jÛs\\r«`²Uïf\\f\\f,µ,£âêj&$´pË¿å-ì¢þ@ýÏè¸#x¡ýÞâ@N«}Ãðveb5Â©ª¿q\\r-á9Ñ\\f¢½2"4ÑËy"¨Êµ#2bRúzAÐn¢§lÌÞ~½U4Ó|{y.×\\rÒª×;EKo!xðò{³Ô½¶'Ê,\\f×æú£é½ä®;Áös\>½}²ä=)Ö'¿«)Õ,§«5µw2¶vÈEr­$ØÆd-÷oÛºM:MW®8-a¥`Nó}éäáXH½:Ñ9øãj4Ç£Í²ÕõºèqH¼\\r­w\\nå\\n9ïÚè¸E:@þ5|Ãñ{&(2ÖÞßø³9ÇüMiiéàÙÍn/õøí\\n¢IÄ¬±HÒMò+4È ¥c-­î'Ú°ûW)6>yÅð¹°ª³îþÇ:\\n2eþ¢hP&êç2)oÂù{yçfGF¼ÂJØZ8ÓëRsí_²Rô(Z/Ëü-«gd±g®;Ãþh2DlWÕo@1C¢3çUUÿ¯¡¶EÖ^X`/zîj\\tâS«ûM]ó>U¸Ý®f¤iÝ½Ðl¸®1ÜêÎ ì²¢9¡<Rlzê\Fú8XC$Õ O\\tqaâ2`|SVÙú¸o2¥uVjÑ?¬5:´'ÀNuÖeÝÝf{ÖWhíTºEæ{aÒú¦é÷è¢sd]R7äÂyÝË½QÅÐÎHÜìø®¬ù{,#gÁé7*´²¦0ÒÿóËW>]Ei[-ÞUúÈ½ý¾ýwÎ¾g%pkÌ%øFÌ×»áÎ}E¿×æàÍ ­×}õ[Þ%á\\f$:J§£ða`µ0`X£0X¢ÿJ1$Å+£Jà'þ¡]Al»BÍs;9\\n~÷fg«´m¨:ÓÃpQ\E\IF@Mh^m\\nXl!²¿8ºÌgR!N õf¸ ,r{xòF3Eg}Íèsf)õjîàið¼Ì8Ï¾ÎØ +pôZ ^bÿ¹¡ÜPçzº\×hs"{ïXa«(¤¶èôd8z´L q¹ß\\nfbÌÀÑñÐKÅ É ¡ÐÀC2©\\tm»²+ÍCÄÆª#}H.$¶Ùg+×±­È-úp/hL¸Á*Æà^ù#Õ¹ÈrÑJN2ÛÅúÆTÓ¼=Þ°È_¦ÉuõÐwóM»kÄ£"Ìä¡H²ç³l¤&IÀU²òÏºàW§°¾¨3VÌÎ»ç½TèF\\npxz@ç^ôù,5¹ßrZknÇ9li:IlQ¡ºibg¦9H¬éÆ{Ä4j?GÍ³3V]CC°Üö×t£öHq¬çiÀ4ZÞÔmB÷¡Øâ,^ìÌy¬ìñp;Ê¼½*aÊóìþ*Íjyå³q%1çÿ\\t5±ñÑpË:>îYZmÄ7HñÙ¥µ_5ØxlGÎn ¶¢~LpõÎÐ§%­xnº=ökÕ'µ\\fnáp­ûð°ÚµnæD+]³æùNérárZ5ÏhJí;}I¦èÞ ob¼jUZOSÖoÖ§<\\f^ÉÐ=X¢ß}lÝÆEâvk¾-×A[æ~â¿Î,·Û´ÞZú±è;æùY=pÕùû{rÂÏï`ØÒ*Å³Ã-¨ÿhV0õ®Xm³8¯iÃæ¾Bfsñõ³òiC¸{ÎÂu¢iV¤$­ï¦*iíÈ¦5ãqét~BJµûK½/íÚÑÂ!ZÉñ©¢\\ný(ö(Tã¥úÂÛÀ·¸XUUÕ41Ú/\\r#msV¼õ];_æúÒ_(þvë:Tý²;/ðEþ)ò«:]nà&¢§ÒðckÏI§ý®Ovðo\\bÜ+5´qÚ-ÕHkWy"/vw´EuÓË°ÎqgróÄiá7YE ¡º<¥¿¹;(\\tqæyuÞãõþ&¸àäæÄØÿ_âúÕË"¯»ß¦ÂøóeE#h;ä·§ÕNçHñ~T§µä¥Qé¡ùÅnóÕÙúMÍÏA®}Àðe´oðe§ï(Ï×-@<Ã:+7}Ù?½Hq}<â\\bC¾Ëøæ/°+7ÛL.¿v¯¦W~\\tJqÌíÃòÙ1&¨ê-8_fåºø©.·%¡`?\\tçT3¨t¤~©F¤}°QçrÝÏðºµâ2Ì5¢\\n¸I;Ý;%°ã[?IXê|s\[]%^ÂÌrö[6rÀ%hÛ'SEª¶b4uÔNãå­qÒ&(>[~`ÀÁ¾q_lÑ)¥÷Å¨9î7gºË7·ó-±±èoçÿ×uÃ.ú¾ñ¥tñ^øãý¿¶srMR¦#]ÈgJÕæ´7¶Ì!83ü£ww~Nø°¶:H^'¼A¯Þ/$C/ô÷í\¥¹¸Ã%øúýAº¯\\rö<¥\\\fÄÍ;Òúñ|J¸t³ê¥(ýg,ÖK4.?ÚózãÖïÙønpa©O Îyiô$¿Ôµ`ôáÍv&cZÚ-¸pckÿ­Gü¬EÁ¸qý­Õ²úÑõôê¦@v¡R*^¯Ää@kíçûD3d\\bÖ{4<ÐÎ®:ü3»Æd1^þËsf¤¥3À°¾|GMOÏPk\Ëê¯eÎ)é¥áü·ÃEßÜ>ðà5©[Ô­®éIeA.4T1ßZòHÄ3*ÈÓ0{»±×I|nº4.Âºê)F?QëCÇÇý\\r°Ýs([J\\f\\f%ùóý'Æ}½ÆUsì°ÌÂ=Ï~Áf)óÓDÑÀ}rý«.¨Ä9 ìWTÄ¥ûåå¦ÙKUö6~±M&\\býôcùÊÉøz|ÌìYÙøûW\\rôù»\\f"K9P¢; µNÑxToºwN\\rû©d³bTw¬HñMÒö%$Küí/ûæ¦<F¾Ï¨hv :AÎ{Ê÷U¨VS/ºB¦Q§û¿ÿ¿Iså%Zà7¡¦p+*úÇ¡OáípgH)ËU]úb)`8ZÐ\\r±6\\tû\l6Ä¶,H/Åkv\\r2nÒÅ4 7\\bKJÇ*_j]ÒqgÌUNÜVÝÊðÔü3nJCÕ]Ë©Ð÷ò¾`Ý¦òÓ> ÖÑUbzi\\bã^ÝØ:£½\\nã '
    //   69: dup
    //   70: astore_2
    //   71: invokevirtual length : ()I
    //   74: istore #4
    //   76: sipush #32767
    //   79: istore_1
    //   80: iconst_m1
    //   81: istore_0
    //   82: bipush #68
    //   84: iinc #0, 1
    //   87: aload_2
    //   88: iload_0
    //   89: dup
    //   90: iload_1
    //   91: iadd
    //   92: invokevirtual substring : (II)Ljava/lang/String;
    //   95: iconst_0
    //   96: goto -> 202
    //   99: aload #5
    //   101: swap
    //   102: iload_3
    //   103: iinc #3, 1
    //   106: swap
    //   107: aastore
    //   108: iload_0
    //   109: iload_1
    //   110: iadd
    //   111: dup
    //   112: istore_0
    //   113: iload #4
    //   115: if_icmpge -> 127
    //   118: aload_2
    //   119: iload_0
    //   120: invokevirtual charAt : (I)C
    //   123: istore_1
    //   124: goto -> 82
    //   127: ldc '9ÙmAõ` b¯\\t­åÿÆ§db»\\t|tÅôàÖò§MÈ¢bA\\tÄ%Ð«AÀNWnþÔOÔ'ÚÊ¨ãÑðýiNÆÆ+¤ì»=Öäó\QÌødÑ¡ò(ùD}\\b¤áy¶ÔyXXÕÃÖz\\t\\ráëF%:~ì õc§³íD¯\\bTgA ùù]=1+ì`ö¥⋡ F°x-Äµp/Á¸dBE­ñ2Ë[zÁpû½i=[$Ñ©¹ÝPÇJÆ×dõªoHjNÝ/@Ê×Èñ¢¥ZwëÇÙh^e13\\t\\tçïý;ûï´~{-é5ò5y\\r¾¦R¼q®ÄvúÊ%Ò¶;®EgCeqbG=À K6+Ôu·Â<Q*ªS´L(Ð.{#L0Fìì&iØ3«6\\bZ|þ\\bz7\\rÀør!=Åè¡+a\\fêtåµ·h³ùs|i¢hÁxý³RZ[ñUTt<±¿Ý^r¯/e\\n0=êý5À|Þº9zOfÉ#z5nÝíCz:7 _ë"¤ò÷Õ\\r^X)Üõd½ó¡\\fí¹qM£©Ou&ãpÞ.iµü4¿ðwvSö|î¹ìRÙ«¬âf@ØÖØ§ý+D§ôyTÉS AâSyw£&PAÇZ2wQ)\\t!Â0½ÀD($D³Õ¢«¹Hm÷ºLék?|mÜr¼+P¾XREµ>²ÙmdS}('¦Ä\\n_\\fÞxö«Ê[ØÅåK¼,¯-Mffíÿ£ó·ng\\r*4¬e.¤\\b&ÈË9c7g¬Ä\ìQ:HöVb}ÍÐ×$BÕÖÓ±³ZÁrzqH`Û¾âm«LMVGÜbÖ}íê@¸Ù+¨¨ÖWðçé<2ñ²ÍGv÷·Ì²âF\\t3¹oº=}Ñ»@¿8¡4$ÓÒÔÄkâ3e¿Â|mC¸3´W=|@$K\\n­|yUo{ùFbÒ´ïhC)-Ñª&2A¹M ÞòÍ>y£½Y~9d¥·¦KÛ9\\bDÂ´/¥?|ÇÉ.ÅU<½Mù8ûæ~ýËÚÝÌài\\b_À¢\\nr°\\nÆòRÛzÀ\\tò£álMý 1ã§IÞ¼¸óÖC%h³H`ãLÏ»t[kâ ì'v¿äLº§äÊ M¹}ä¯ût©¿×µÄê\Y»\BÕ!×KÇ¦k²BÿMjA'éqWåÌN©Xå±ÚlrÜÈ*k&$³é\\f¯¥z àÎ@¥¬£Ûþ«±&×µ:ë¢0=7øèì[Ùº¨qßH<¢ â\\b\\tr¡ ñÓojQjiäØëÿO²ïùÌºþ©C3ñs_¾#Þ#åMèNó ¡BrÊø1rÄsxÛ)*;Bßç¡Aêl¤=(fr#Ò.¾Û³, M.§£ái_<é\\bN¡ÝÙ{73C.¢OÎí{¹¿\Ut#ÎëuE£Sñ$ÆrW9*2³?zÁëWMl¹ÊÎø¦^ÊJ¯2Â\^î­Fê/"AÔìÅ{O~ìlQf\-©8Î# âM#>\\nsÿ§ÑÏðñZþíìÔ,û]ÀÐX~K½<G÷!Ðw3¡¸a%Ç¥vBÈ\\nB<´jxÉoùr-}åðü7ï"ÝIÊÎÙûe/b¹/çh_*yÔ|=v\\nºÅb§÷*i4­ûS¸è,Äÿ1È»r6Úü^«kDú}´)P%Ä¥=I äÅh;÷ÏuhÁ¯ñB!<%ØÐë?»ïhøèô2X]\}R;ð2¤âé\\tèÈµÑÖ4A\\tì!Cmºe$*$¸&ØþY×mãÊiT.Yµü\Ü»®Ü)4ÑMºÊbgÁ{ï"(¢¢ËÈ ñG|eÎ\è/æõÝ²ÏÙekà|üâ¨·gÈV'õ0¤PÉ\îù;OÇ2?7£áB­êhæUÔ4(²³¼Oò&Ç¡\\fk-i¨ýú½v~×Ìxë±]\\tÏyØÓp`ÛpV%3J¬9[ª¿Àó?©zÜGÙÒN\×Ñn¼7§ÊxûAÃ8~Ã8qFiÓ;£hf¦ðí2ú yæ/Ùõ@ÿÔÂæÊAåKÛ¡^¹|R½¬Jà3Hv\\tÙh'¯ÁàÖæ°L¡Hs¼ËL£\\t¼´nÐ¡"£äh´Óç|õ±-bt-²»{º½p}T<P)Yô)¸§67t¡ArF½'q \\rÒ\\nS¥1t@O7ÄI>×>¾á:ö;pZu×½­y8º2'ÅÎU²8ûBEÒÉô¤u¸(ýÛÙTñ¤\\nÓ ÙÒ4qs=a_¯-Õé×±ÒÒóÁ÷ÕO<?üèø)Æ¸i09£4yã¿ÚkJvh\\bOÇ¦=±¨­t\\f½êx5ÿ>a^`ïi\\rdmx¬nâM\\bÐ=!íÏº0àtu?©cjÞé¹0Æ³ùYá¬v÷ ¸ Gºã@Þ´¯Ü÷Q©^Xê<®-Lý#2´ÝE7<ÂÍ&Åèè¦\\fÛÌ$IÚÔ$kâç$i!=Tì|k£C´ÀÀ+>Ãµ[ï÷²ßArÛ©þg©(ïÌq/bêBÌX3ãmEË;©êÌòî\\b5Ó{ô\\rwÄ`OFzãé8^Ø\\nÆ£×^3;ÂÖ$«ªÆ Ê2"áÐWe ¶Û\\nÄ{ìÐ;@R\\r2³\\b*EZa%Ø=&Þ£~þP­©E}\\fí¡¿Éúò[%ÕIÒ´pãú¯cEWCyÆLª®>DU¢ÉÛ~oF?KßmXJMP!AÐU&¡ÎÌ_xuËíåþ5ödÎöÙK(Ëháå(6*°31Þ±¯xÇÏ¥mQn\è8Ä·¨çwç©óVëv-HÉ(GÝ´^\\nH#>«ÎRµÙÁòx¬W-®ÐsZW.íX_K #Ê)Oâ¿d!Àn°ÜñÌªëú8b9rmØ«\\tæ*®\\bfóXÅDóPÎ)ÜajSµ3õ>º0å½?õ¢õ±ÒüØÖ O\\rdÃSh¿WºR¼f6ëy0k%kEf0o\\rÝ,_ªÔFZà\\nPÖ2Ô_ÙigbÉ~ ¸8Ü®CÃõ¿ÌÓyî ér5Ù¿ÿgºãÁryÉ*B[+ÈÆÞõr{Z^Z2ùÚ]+AmtùNæÐ\\f¶÷ò«\\rºnÑÚQLVçt"èza'ìÍ9{"fÐïºü?\\t!öÀ;~N5Ø²¹ó°ñ/\\t¶¬dû£ý{»2Ð/@m:¹1äÎsÿ¨Åóo#ÆÞ=\\t¡ÁÅ'9Ýg¼©­µ\\nl6ÿ»»Ï(»*w¦àæ v¨åÅ<:ö²³©Û.\\t*îãJÃ?%[VwQïÀ\\fÎ«H3}s Bg-Ü\\tñJdìcC%ÍëbÈ¤Vl«\\néxqR¥a{ÅZ.ó¶\\n\co Åøu<já!L¹£LÕ©¿w\\r½lS×ëãª\\rµJ¾É©ÎéÅ>;\\fr]zk:FÕÆ5Ü¿&í{yÔëù>µäíÎ\\n\\n`©fd´,È Dpá<Óöÿ£°xpOÀ '>*ý³®bx]KÜþV~Ô\ûÈ±ÞK{¡Æè+è]"etÎ?´0"n Óù½.Ú¯!ýáþA¹ëèZ(²Êü½V];ZìÄ¼N3ó'Øg×Æ0;ãT¡ðÜ!(ÜðNv¾ÿJ°¶ÉVNî¾>­òqgNÕñá×aOðô.lj5mLï{ 3?S2iÿ,¼-®±^OÈMÁ!¬0í@Î½q÷@óÚ¢AÆÀñ®|¼³Ç2ðÕpÏÜ&XÍp[ô´öò:ð{ Ð\\rhíüJDx KôñgëyÛtóËäòjÜ±Ïÿ7$­VfÁ£\¿kÆ³Njðw¶º»x<â±JÌÅísø>UGä1Iw\\bJ(åo¾±3Máh\\bl4íØª2»î+ßkóº|nEÙèG³"vöú>²{ÒfÔÞ¦©Ãzï7\\fGk±Ýª¨fÄa[ÓOwT«á6®ÿEÃa³îKaí6°¸èî{ *"®Î>ÏÓ)=÷2ÐrÝõÑó]W£pjïI@ÌZ50]ATïPÑÇ|HØDäOÞjëF®ïº:Ñ'(niØÒÐ¢ãÅÃ\\b#½MÒíGM²]Y8²vbªcõDE°]wÏ×*êû\\tÆTýÝü]3ïfÝûC¨Åzö^s+*ËÓ­"×ê&<¿®'¯ ÔôÛ/üu^â3æÍnAõ©y!ZìL&â\\n[Û ¥ß¾\aB,í=_}ÁäÙæ«½9úbù\\t\\r ¢ÛEôóflý©ïê·¦þÑ¶ÆµÑ=;×\\rÍõa¸ÞP<ñ×Ò}E\\róðT¾Ë_Î­`ÛÂ9®zeôY_sN²ÁäEìTï÷ÆnJiXGA´cÎ2"Ì8cáPàúø^øgßKõÅñ`G{£¤{Éð<pmáõ0ßUE®à\yÔÆeM§Óp$äøo¬qÃL8¥\\f¯¯>dp|\\t$_>÷y"oÓ«tòªßÉÒ& ÍA$ÎM@hXiÍ]WæqòRÓöønuN'gÖÄ,Â6YTF±²~9«[\ë"öÂ!N®'­÷Ïè§~)Ê($Âvù±0{6^#°VÉÆÔìßh; a¥ÄC)wc<3EeÒ. Wsé8ZbrêÄ0ÙÃÂxCG@eûE-+£àaQäÑÒÖZNDO?ÐþuøºîEY°*îÙ!¤\\n3#}|ày2ÈúW$ª§Ó+ïSÈ÷±Ç"uÕMYa­©/7£ÿü;ú@Åö½öÄ2°'s¡g³mOR¸ ä\\tÅÈ(õFr°\\r"su:"× <¡¯â®¿_Ô¿GqÓ¶>Òij.ÃËXòkyP5­É´¼ÿ·îâWøÅ2,Ú:3Ü¿¶ÖÿÛø¢árÄ0\\në\\rG¢Ð-;µ¼Êï¿ÒÀ×wûúAð|àéSÉ(¹"áÕù0Ò6ÓZQPÓ£úH´2ÃºµêÅóª=îÔ%F[$9"Ö\\fwÌÿî£Ê³éD.f¹½ÖY¦Ox_b§20@\FëÝÂ k¥8dþ .tcD[Neëï{ÿ¬é»ÔKÅB\\tÔ7tUãofÌÈÙ$!ku-qPÑxOÓñ6¯Tÿ+bÊ0ÊQûÍñ+wóºü¹ÖUèßc¯¬¢Y¤s<ðZÕ'J¶è¹§ôoÔ±A5MÇ:5ÝTpx±µüdßJô:¬®$Ô¡_¼Ü2Íuÿ¨8`§T¤\Éë&ïÝp¿bêHñÙk>ò¼4ÙïüyÏ¦t~ÚRû7u\\bw)R(.¹Às6öv\\nqÁ3êR#¥Ï;ò<qý!º@ÁÈ0Ì&3l¥ºsøó{íÓËWÞ IOo[ù©Ç9ñøwg¬ Ý28Àmol96z ¡ìFz[¥ÎJ+ºLÓ,'ícIû÷õëØî¦UZ³\\bsFbámÈï±ÒÂÕ$[l'$"½&7ëm¡9þ\\tÃÓ§À¸ ùü\\taÛ\\nRßæGúSÜ®.¿öß oÕ¸:Ïp^÷»´ÈÐ¼Ü>¼±\\nLnµèú¬Â8ÿ8cÊtvÚÎá×«7[D÷î tÃ|Î|}ÅÏö/!s,|Á?ñ\\rÀa<7[|'h§wIcéq4¼[IGiÙÀR\\bã´0¥A;2Ê|ä×\¢'§k­Þ7oÀÇ¯$ó#«\\t\\\t÷¡¿`4ÉAÔ\\bÙ4òu=QmíÂ!tnd¼ß&ÚG[äi\\r;F¹EÐõµw<vTþ,sf[÷!/Ùz0*'\\bÆ~CNqºôV7ê Mìxå¯,ØJÐ¨Ã\íëag$UÑ|ÂK¢Ä¥ÄkÒuÂ¶Ò¿è&Ö°n¡¡8D¨yN¿ønçP`©[Ù\\n'>®äõú©fpe°ëuÇéDxÛh{Ó/\¤<KäÅ½ÿÍ·É¥òâXÿOM\\rwÆç¦4óÁÅ*ØD±Q8?dÆ²þw° é¯Ô ºaBëõYoí±òù)ÄIXêrÜÙÓf°ä¿c !W\\ne%4äwÀµÕ]\þúkR/ïú[óZGß9+¼ð"«<âìmÐ°5Ôâèsä´ê®_õA÷ÍLâ*XÎ³EÔuA|DI.:ßFËSâX¹ÂM.g$\\rVbJ\\fdðôçìÇ±s9JÇÝÅª$mW¦P*ErÙ>¾lÈù^ùÜp+ÜÚ+³B»ÚV\\nîºÚ3 ³`fß4RÍLú4g$äõJ5²ÀÓÉÍµ¨f\\nDöÌäÔ¤)çª8Éójqzìñh¤¼þ á¤á\\nY\\rQÉ¨[Ló{!Ü`sÇ1Nß´·[Âï±­9ØBÌûü÷Â_-Cù%Ón O1-ÖéÈ*ËÏ%¿i\\nç×aG£vVþÆ\\t£kWøj/ÇöüïÃ¶t²_âEé´¨a ÇBY@õÔØ7AE kR¬.J^ä²´ööfío7K©W¸\*OÎðm~J÷Ä×âä=¾Lª¥Ä[ù¦l»)7ç*ï=3É'¶ÕzðR­Iþ³«8²×6&B°ÆæÏs]ìþÿ=´yÊ "¿ïö@s=¾¶jX Q©õÉQ0\\f¼¨HµeI:BÄeÿ0!EG:ÀB\\b®e³ùÛO8r\\b\\bE Dæ¥Øÿ´ÉqûðbÝ8-dóùà°ZWüVÎc9Ðp(Ý0Á=/8Gy\\ro3([(¼É#WÝY1§a\\tËÊ1{gëUv"éºgU|¸tÉD J\\tG¸-úÇ^Îhàg·Õaí1å?RÒ)/ªçØJd8]º"Û\\têÒúI_ÇáÈ*sÎß»ð(Å§Æ*ô]hÁbØæv*]~¿âhshæGp-7ÙòÜ+¯sFÁ@1KzÒ+´äãX´Ëf9ö+¢MV±{4Ñ@eØª1¼É¾$Ï­Ì,\\byº&É5Ãí¹à`¦úc0íýgzÈûqÔè*ÃÍù|Å¸pèn#¨íØKT{·81I~²á\\tu8ÿÖåËA2³gÕÿùÿó¹'»ÖV+øbkäÏ!ÞAèçgeº|äðË¦ñ2ó$®£ Ë0$]Þ<Ë¨¨RÀ»­hf×|¡0noû³hüô.Ó>\\nHy OÂÓõ²[b¡úæt@^81b`µÓ©WpU NûB¾²g²Hh.!;)]ÓôE°\\r`øü|4 ;ólø§\\fÌ÷:¹í2w>\zFñõ8æ©lãIajZ3¿2ÜÊtfK\\r{HÉÎE¹O¶ý\\f¨°r> Úö!4@ÖÆ$!o#à^Â)XÙF7À±+·]S\\b'wb¶4Âî·õï[ä§õ°ßÖ4+e³doGyC%Ä8.1eÕF!rI~U=ýHÜ Gºâ®(A·7^ÑE(ÿ)&tdÇ¼3uÕFab2Lû`;\\n«#7¨ðÃÎê\\fÊ¯w"D»ß+ÁKýÁ×¤­B¨Pä:Þ#úÕ]ýßÏý!»g©\\t5²Â£yÒNÝÔ±Snêºþhzñ+Ñ<ÑX^ß+ç66j&Á»åýg«ðâ@&Á£83Us(þLI½#\\r´vÅ­È·3>.Äá´yõùg}þ>/ÃÊÜzøò§Är\\rüÕ"® ÉIßM9çn@I/u!£V}û0e{w Íbõ¬â¾nÔþ'"³:Ö'kó\\tí+a«ý îX½/ª²QÔ·_Jôh¢m+Æ¬lx-UìÛýbVf_±Õ*:Ê¨eyãq'gÕÃGwãà¨YW·¼¥!Á¡vÄ iqóðô*ðAX_qñK(LêÓ0ãIóû¦-æÕð83h! ¿7Á[¤HuM£\\bqØ¡¡]ÌmëâÙì¨!$ñm_F¯NdìItb^ùóq\\bà6f´Æ¦ 2Öº-Ð ó¯cYçäþøSËoQ\\nFRÚ?Cn{¬^?LËAò( xø\\bn¡KÌV¯?±¢ö×ðpýg·ÜaAù¸K¤Fx×-·XPk¶Qªi]ÇíEqÍþ¸Û"ð=wänèÎVH®±¹¤FE223úÙ<¢x°ûV·{iGHXç_4½}QõDü\\nÛWæ«¤c«à-0Vç:ÆëÓõ|µÛñ,?©F^ù,£\\fi~·îé*Í\pÈoa5JFÅcó³Í`»{K¨e±=ÀÖ¬ tÒ6|ÿ ¾[W©æ¸r2¹Q¬×ëÜ:vøÁ_¨ æ¬sjÀ*ôeþVö=Àõÿ\þ)sñ:÷öÞø£aRÏB*rkÉÕNÙÓúéöÃDÑ~/ÿY\\nK\\f2¼½£r¹Øs\\nô-Â>/+4N#IDp Z lÁáøÛÜ§\>÷I2ù%n®¬Ú{Ä£ÏÍ·äçt#ë¤ÝÁÚ_ÇUD³k/e«Á5ì@J{v®1¸lû9ËÈïó Bõ|.ù¥øÃ5«ßhy?)½¶ã¢Âu;³!ÑM7<êw]Î çáx¬'_qêgNdl¢Î$öv ?Lj÷èè,lÄï¥ý6ëBe,¿øºkñÐ_Ypaúpmt5qtò­]ÃÖH1âÀæ\\b@ÿy_Áè=õÍvè·1Öu¤%Ä&ÈB5Ä2ÌTè>Åå ÔáD·÷zãYÓEb{9×ÙrZîïI;o¢,z»îÙ\\n¤9Vùk»h(\\bØnBxXl¼N50Å;x¤mp $/!2lxe£tdô|ÚîÃìªÐn~×F·LÁë?ãædæEnÌÚhV~Ïó!PÑx9tÎ\\tÁanJ=JÈ}ï½øI¢RCq)s"õÎÑ6/ÒÇ]V{9°£#tëbµm;×MSÜëEp/ ×ÈVëLÕF`|ÿTß£øÙN9å>Ýtý©§Áª¿Â©ÑAYàË¡@hKYôçº¿ü0ý6FñèQ \\nz²8\\rûsîô(\\t]Ý\\t9m¥äÝrËDØÛð(Dó©ooÅ®ÍÒa`Ó²0-q¢lPsò,P±×,iZ d\\rÌÇ×:n/ÐNÜÜÆSb±7§UB?1ÛëìçÌËe0('æYûá¹ï{Ak>EíuôpýKégÅ­Vö§ýðÆã}\\tÃ0;O¤¡¸3áRëÁPËÜ´<F°uïí9.áÐfRñ%qµô3^~×ùôZ\\tÔ¾A0LF²ÑHt¶}©9V-#ÈpÌäâsGßÿV°Ùªc§rØvõ¨\\r±õXzÝ])w\º°Øà )Êgab_Éùwtuøö¢9lÛé?s¨øµDqW`-J\\tÇ &:òú«âmç¨WÉ÷LÖ_þ¤|ò}'¼\\b×ò!QlÞ¥ÍÅ6ç5käOÐ¨},:y<ûðxºP}¾>)ªÆm×Ã ü½°¦I¶)}=k}\\nè;Ç¶Ë"Ql;ÀØÉxÅçÐM67 8£¤SR+®ýÝ²ëDÉÚ 675H:ÈX¹Vß-Q~±äÐ~Úe.>$|+KEG1ÇA,¢ß±%.¾WL4¢á¹²%û\½$hÛ¦º·=°Vá#rº\\f`\\nÛýGÜª`~¢Äó×·N­sÉ":jLwSOi1Û\\t8Mù¸Ua¯À\\fÛ-! ÝÇ¯~ÖíGÚÕ'¥`'ÚÏ#­80OôÑpYæ$» w[*Sp%TéîÚ3²\\rÎ°/:Û¼\N4cý\\rò[aÍw3Ö\\nºPÿw¾.á¾¸°µ%Fn<O¬zÓ®#TQ}=ÓÉ¶°«Î?Aàøúl¯)P[æÛ§¶Ø3cúFðèÀ\\fãÀ\\tu Aø8?Oo!A5c©©úô=£¤}Âosí½1UÁªøÂH>Oý¹UT_°ýIÐX\\nV¾VÏ`K8Ò7ÀÀð!êk ÕHai¾l²¥\\b#×J¸i1¡UÔcá0­xo#ag5\\rÔè|ÈÙý;ù(^Ü }ñ²(~,üÂã7 ö¼Þ³EzG6ñÀ¢°·±srÅ¿¿ S:\\n~{Ndül0÷ÎÀ m;rg,ÿDÚîÐ+°"bèiyåÎ6Å|²6OEá:F¢¿Ç\\tþùtÙÌ53¸êv|3j]ìó@m.¦;B1Ia>\\b6ùJàÝ^yå5rì4\\t©p¼w¡GþíEI÷aï}ÎÍh*Ùî1ØN`¿HÑ7hP,%ÂöõLýOÉ²^úmµ3¤Oh "Î+H»å2 ù(2Í¬íéf¡ì~mÍýM%ÐT¿èà©9:/â·\\t¾êÐ@qbíEÅ},÷Ê>¸\\t\\rHGaºqþÉi÷sC=7<S;oMFkIâr±iå0[í;rí¯ÚÞeÓR.(u¸Î4:¤ñ\\b"6MÝB¸±\\tyMôKx¤iÊúd«²èg[@æ¿ä²ýâLÊh%çvkNpKùwôÎ¢ÊMHácé`Ì\\nXéÛµ|v*\\bRØîuó[jºOõËL*Ïý«bE\\róÇRyª)d&©äâ¬¹¥«Ó6®ñVáó6}ñ6Do©è?þh!B4:#Úu«ÎG»âBaðé]@ÝØ¶ÆðRr[ÒÛVØSÝ¯ðÑ¼ëHN3´iUY8YÖQuN) ËYX_'4S,Ïá>m²¶»ü¨×ïp/iºï~`w*:]mOàPìcÔüF¨²®ìRÀ¶Nç¹>ÖÍÝ§&¯0¡êÒ;jÆ7¯{w'
    //   129: dup
    //   130: astore_2
    //   131: invokevirtual length : ()I
    //   134: istore #4
    //   136: bipush #9
    //   138: istore_1
    //   139: iconst_m1
    //   140: istore_0
    //   141: bipush #53
    //   143: iinc #0, 1
    //   146: aload_2
    //   147: iload_0
    //   148: dup
    //   149: iload_1
    //   150: iadd
    //   151: invokevirtual substring : (II)Ljava/lang/String;
    //   154: iconst_1
    //   155: goto -> 202
    //   158: aload #5
    //   160: swap
    //   161: iload_3
    //   162: iinc #3, 1
    //   165: swap
    //   166: aastore
    //   167: iload_0
    //   168: iload_1
    //   169: iadd
    //   170: dup
    //   171: istore_0
    //   172: iload #4
    //   174: if_icmpge -> 186
    //   177: aload_2
    //   178: iload_0
    //   179: invokevirtual charAt : (I)C
    //   182: istore_1
    //   183: goto -> 141
    //   186: aload #5
    //   188: putstatic burp/Zt2l.a : [Ljava/lang/String;
    //   191: bipush #10
    //   193: anewarray java/lang/String
    //   196: putstatic burp/Zt2l.b : [Ljava/lang/String;
    //   199: goto -> 364
    //   202: dup_x2
    //   203: pop
    //   204: invokevirtual toCharArray : ()[C
    //   207: dup_x1
    //   208: arraylength
    //   209: dup_x2
    //   210: pop
    //   211: iconst_0
    //   212: istore #6
    //   214: dup2_x1
    //   215: pop2
    //   216: dup_x2
    //   217: iconst_1
    //   218: if_icmpgt -> 320
    //   221: dup2
    //   222: swap
    //   223: iload #6
    //   225: dup2_x1
    //   226: caload
    //   227: swap
    //   228: iload #6
    //   230: bipush #7
    //   232: irem
    //   233: tableswitch default -> 302, 0 -> 272, 1 -> 277, 2 -> 282, 3 -> 287, 4 -> 292, 5 -> 297
    //   272: bipush #87
    //   274: goto -> 304
    //   277: bipush #120
    //   279: goto -> 304
    //   282: bipush #111
    //   284: goto -> 304
    //   287: bipush #77
    //   289: goto -> 304
    //   292: bipush #52
    //   294: goto -> 304
    //   297: bipush #86
    //   299: goto -> 304
    //   302: bipush #20
    //   304: ixor
    //   305: ixor
    //   306: i2c
    //   307: castore
    //   308: iinc #6, 1
    //   311: dup
    //   312: ifne -> 320
    //   315: dup2
    //   316: dup_x1
    //   317: goto -> 225
    //   320: dup2_x1
    //   321: pop2
    //   322: dup_x2
    //   323: iload #6
    //   325: if_icmpgt -> 221
    //   328: pop
    //   329: new java/lang/String
    //   332: dup_x1
    //   333: swap
    //   334: invokespecial <init> : ([C)V
    //   337: invokevirtual intern : ()Ljava/lang/String;
    //   340: swap
    //   341: pop
    //   342: swap
    //   343: tableswitch default -> 39, 0 -> 99, 1 -> 158
    //   364: sipush #-11456
    //   367: sipush #-9034
    //   370: invokestatic a : (II)Ljava/lang/String;
    //   373: putstatic burp/Zt2l.Zs : Ljava/lang/String;
    //   376: getstatic burp/Zt2l.Zs : Ljava/lang/String;
    //   379: sipush #-11445
    //   382: sipush #-15420
    //   385: invokestatic a : (II)Ljava/lang/String;
    //   388: <illegal opcode> makeConcatWithConstants : (Ljava/lang/String;Ljava/lang/String;)Ljava/lang/String;
    //   393: putstatic burp/Zt2l.Zs : Ljava/lang/String;
    //   396: new java/math/BigInteger
    //   399: dup
    //   400: sipush #-11452
    //   403: sipush #11500
    //   406: invokestatic a : (II)Ljava/lang/String;
    //   409: invokespecial <init> : (Ljava/lang/String;)V
    //   412: putstatic burp/Zt2l.Zg : Ljava/lang/Object;
    //   415: return
  }
  
  private static Throwable a(Throwable paramThrowable) {
    return paramThrowable;
  }
  
  private static String a(int paramInt1, int paramInt2) {
    int i = (paramInt1 ^ 0xFFFFD342) & 0xFFFF;
    if (b[i] == null) {
      char[] arrayOfChar = a[i].toCharArray();
      switch (arrayOfChar[0] & 0xFF) {
        case 0:
        
        case 1:
        
        case 2:
        
        case 3:
        
        case 4:
        
        case 5:
        
        case 6:
        
        case 7:
        
        case 8:
        
        case 9:
        
        case 10:
        
        case 11:
        
        case 12:
        
        case 13:
        
        case 14:
        
        case 15:
        
        case 16:
        
        case 17:
        
        case 18:
        
        case 19:
        
        case 20:
        
        case 21:
        
        case 22:
        
        case 23:
        
        case 24:
        
        case 25:
        
        case 26:
        
        case 27:
        
        case 28:
        
        case 29:
        
        case 30:
        
        case 31:
        
        case 32:
        
        case 33:
        
        case 34:
        
        case 35:
        
        case 36:
        
        case 37:
        
        case 38:
        
        case 39:
        
        case 40:
        
        case 41:
        
        case 42:
        
        case 43:
        
        case 44:
        
        case 45:
        
        case 46:
        
        case 47:
        
        case 48:
        
        case 49:
        
        case 50:
        
        case 51:
        
        case 52:
        
        case 53:
        
        case 54:
        
        case 55:
        
        case 56:
        
        case 57:
        
        case 58:
        
        case 59:
        
        case 60:
        
        case 61:
        
        case 62:
        
        case 63:
        
        case 64:
        
        case 65:
        
        case 66:
        
        case 67:
        
        case 68:
        
        case 69:
        
        case 70:
        
        case 71:
        
        case 72:
        
        case 73:
        
        case 74:
        
        case 75:
        
        case 76:
        
        case 77:
        
        case 78:
        
        case 79:
        
        case 80:
        
        case 81:
        
        case 82:
        
        case 83:
        
        case 84:
        
        case 85:
        
        case 86:
        
        case 87:
        
        case 88:
        
        case 89:
        
        case 90:
        
        case 91:
        
        case 92:
        
        case 93:
        
        case 94:
        
        case 95:
        
        case 96:
        
        case 97:
        
        case 98:
        
        case 99:
        
        case 100:
        
        case 101:
        
        case 102:
        
        case 103:
        
        case 104:
        
        case 105:
        
        case 106:
        
        case 107:
        
        case 108:
        
        case 109:
        
        case 110:
        
        case 111:
        
        case 112:
        
        case 113:
        
        case 114:
        
        case 115:
        
        case 116:
        
        case 117:
        
        case 118:
        
        case 119:
        
        case 120:
        
        case 121:
        
        case 122:
        
        case 123:
        
        case 124:
        
        case 125:
        
        case 126:
        
        case 127:
        
        case 128:
        
        case 129:
        
        case 130:
        
        case 131:
        
        case 132:
        
        case 133:
        
        case 134:
        
        case 135:
        
        case 136:
        
        case 137:
        
        case 138:
        
        case 139:
        
        case 140:
        
        case 141:
        
        case 142:
        
        case 143:
        
        case 144:
        
        case 145:
        
        case 146:
        
        case 147:
        
        case 148:
        
        case 149:
        
        case 150:
        
        case 151:
        
        case 152:
        
        case 153:
        
        case 154:
        
        case 155:
        
        case 156:
        
        case 157:
        
        case 158:
        
        case 159:
        
        case 160:
        
        case 161:
        
        case 162:
        
        case 163:
        
        case 164:
        
        case 165:
        
        case 166:
        
        case 167:
        
        case 168:
        
        case 169:
        
        case 170:
        
        case 171:
        
        case 172:
        
        case 173:
        
        case 174:
        
        case 175:
        
        case 176:
        
        case 177:
        
        case 178:
        
        case 179:
        
        case 180:
        
        case 181:
        
        case 182:
        
        case 183:
        
        case 184:
        
        case 185:
        
        case 186:
        
        case 187:
        
        case 188:
        
        case 189:
        
        case 190:
        
        case 191:
        
        case 192:
        
        case 193:
        
        case 194:
        
        case 195:
        
        case 196:
        
        case 197:
        
        case 198:
        
        case 199:
        
        case 200:
        
        case 201:
        
        case 202:
        
        case 203:
        
        case 204:
        
        case 205:
        
        case 206:
        
        case 207:
        
        case 208:
        
        case 209:
        
        case 210:
        
        case 211:
        
        case 212:
        
        case 213:
        
        case 214:
        
        case 215:
        
        case 216:
        
        case 217:
        
        case 218:
        
        case 219:
        
        case 220:
        
        case 221:
        
        case 222:
        
        case 223:
        
        case 224:
        
        case 225:
        
        case 226:
        
        case 227:
        
        case 228:
        
        case 229:
        
        case 230:
        
        case 231:
        
        case 232:
        
        case 233:
        
        case 234:
        
        case 235:
        
        case 236:
        
        case 237:
        
        case 238:
        
        case 239:
        
        case 240:
        
        case 241:
        
        case 242:
        
        case 243:
        
        case 244:
        
        case 245:
        
        case 246:
        
        case 247:
        
        case 248:
        
        case 249:
        
        case 250:
        
        case 251:
        
        case 252:
        
        case 253:
        
        case 254:
        
        default:
          break;
      } 
      byte b1 = 123;
      int j = (paramInt2 & 0xFF) - b1;
      if (j < 0)
        j += 256; 
      int k = ((paramInt2 & 0xFFFF) >>> 8) - b1;
      if (k < 0)
        k += 256; 
      for (byte b2 = 0; b2 < arrayOfChar.length; b2++) {
        int m = b2 % 2;
        if (m == 0) {
          arrayOfChar[b2] = (char)(arrayOfChar[b2] ^ j);
          j = ((j >>> 3 | j << 5) ^ arrayOfChar[b2]) & 0xFF;
        } else {
          arrayOfChar[b2] = (char)(arrayOfChar[b2] ^ k);
          k = ((k >>> 3 | k << 5) ^ arrayOfChar[b2]) & 0xFF;
        } 
      } 
      b[i] = (new String(arrayOfChar)).intern();
    } 
    return b[i];
  }
}


/* Location:              C:\Program Files\BurpSuitePro\burpsuite_pro.jar!\burp\Zt2l.class
 * Java compiler version: 21 (65.0)
 * JD-Core Version:       1.1.3
 */