package burp;

import java.io.IOException;
import java.io.Writer;
import net.portswigger.Zqf;
import net.portswigger.Zuh;

public class Zt34 {
  private static final String[] a;
  
  private static final String[] b;
  
  public static String ZD(int paramInt) {
    switch (paramInt) {
      case 0:
        return a(-25478, 13399);
      case 1:
        return a(-25495, 8841);
    } 
    Zuh.Zv(false, Zqf.Zk, paramInt);
    return "";
  }
  
  static void ZW(Zvon paramZvon, Zglw paramZglw, Zbnt paramZbnt, Zsh9 paramZsh9, Zey9 paramZey9) throws IOException {
    try {
      paramZvon.Zv(a(-25498, -16084));
      paramZvon.ZW(a(-25513, -17665), paramZglw.ZDM().ZSF());
      paramZvon.ZW(a(-25528, -26050), ZD(paramZglw.ZDM().ZSC()));
      paramZvon.ZW(a(-25521, 4568), paramZglw.ZDM().ZSQ());
      if (paramZglw.ZDM().ZSB() != null)
        paramZvon.ZW(a(-25494, -24939), paramZglw.ZDM().ZSB()); 
    } catch (IOException iOException) {
      throw a(null);
    } 
    try {
      if (paramZglw.ZDM().ZSt() != null)
        paramZvon.ZW(a(-25497, -8447), paramZglw.ZDM().ZSt()); 
    } catch (IOException iOException) {
      throw a(null);
    } 
    Zxyc zxyc = new Zxyc(paramZvon, paramZsh9, paramZbnt, paramZey9);
    ((Ztkk)paramZglw.ZDt().ZRH().get(0)).ZC(zxyc);
    paramZvon.ZW(a(-25480, -16248));
  }
  
  static void ZL(Writer paramWriter, Zglw paramZglw, Zsh9 paramZsh9, Zey9 paramZey9) throws IOException {
    // Byte code:
    //   0: invokestatic ZK : ()[I
    //   3: astore #4
    //   5: aload_1
    //   6: invokeinterface ZDa : ()Lburp/Zzi8;
    //   11: ifnull -> 65
    //   14: new burp/Zzoq
    //   17: dup
    //   18: aload_1
    //   19: invokeinterface ZDa : ()Lburp/Zzi8;
    //   24: iconst_4
    //   25: aload_3
    //   26: invokespecial <init> : (Lburp/Zzi8;ILburp/Zey9;)V
    //   29: astore #5
    //   31: aload #5
    //   33: iconst_1
    //   34: sipush #-25493
    //   37: sipush #13203
    //   40: invokestatic a : (II)Ljava/lang/String;
    //   43: aload_0
    //   44: aload_2
    //   45: invokevirtual Za : (ZLjava/lang/String;Ljava/io/Writer;Lburp/Zsh9;)V
    //   48: aload #5
    //   50: iconst_0
    //   51: sipush #-25535
    //   54: sipush #-20863
    //   57: invokestatic a : (II)Ljava/lang/String;
    //   60: aload_0
    //   61: aload_2
    //   62: invokevirtual Za : (ZLjava/lang/String;Ljava/io/Writer;Lburp/Zsh9;)V
    //   65: aload_0
    //   66: sipush #-25519
    //   69: sipush #-32464
    //   72: invokestatic a : (II)Ljava/lang/String;
    //   75: invokevirtual write : (Ljava/lang/String;)V
    //   78: aload_0
    //   79: sipush #-25531
    //   82: sipush #-23412
    //   85: invokestatic a : (II)Ljava/lang/String;
    //   88: invokevirtual write : (Ljava/lang/String;)V
    //   91: new java/lang/StringBuilder
    //   94: dup
    //   95: sipush #-25476
    //   98: sipush #15897
    //   101: invokestatic a : (II)Ljava/lang/String;
    //   104: iconst_1
    //   105: anewarray java/lang/Object
    //   108: dup
    //   109: iconst_0
    //   110: aload_1
    //   111: invokeinterface ZDM : ()Lburp/Zegg;
    //   116: invokeinterface ZSC : ()I
    //   121: invokestatic ZD : (I)Ljava/lang/String;
    //   124: aastore
    //   125: invokestatic format : (Ljava/lang/String;[Ljava/lang/Object;)Ljava/lang/String;
    //   128: invokespecial <init> : (Ljava/lang/String;)V
    //   131: astore #5
    //   133: aload #5
    //   135: sipush #-25477
    //   138: sipush #-16626
    //   141: invokestatic a : (II)Ljava/lang/String;
    //   144: invokevirtual append : (Ljava/lang/String;)Ljava/lang/StringBuilder;
    //   147: pop
    //   148: aload #5
    //   150: aload_1
    //   151: invokeinterface ZDM : ()Lburp/Zegg;
    //   156: invokeinterface ZSQ : ()Ljava/lang/String;
    //   161: aload_1
    //   162: invokeinterface ZDM : ()Lburp/Zegg;
    //   167: invokeinterface ZSC : ()I
    //   172: invokestatic Zy : (Ljava/lang/String;I)Ljava/lang/String;
    //   175: invokestatic Zp : (Ljava/lang/StringBuilder;Ljava/lang/String;)V
    //   178: aload #5
    //   180: sipush #-25484
    //   183: sipush #-2151
    //   186: invokestatic a : (II)Ljava/lang/String;
    //   189: invokevirtual append : (Ljava/lang/String;)Ljava/lang/StringBuilder;
    //   192: pop
    //   193: aload_1
    //   194: invokeinterface ZDM : ()Lburp/Zegg;
    //   199: invokeinterface ZSt : ()Ljava/lang/String;
    //   204: ifnull -> 316
    //   207: aload_1
    //   208: invokeinterface ZDM : ()Lburp/Zegg;
    //   213: invokeinterface ZSF : ()Ljava/lang/String;
    //   218: ifnull -> 289
    //   221: goto -> 228
    //   224: invokestatic a : (Ljava/io/IOException;)Ljava/io/IOException;
    //   227: athrow
    //   228: aload #5
    //   230: sipush #-25516
    //   233: sipush #-2423
    //   236: invokestatic a : (II)Ljava/lang/String;
    //   239: invokevirtual append : (Ljava/lang/String;)Ljava/lang/StringBuilder;
    //   242: pop
    //   243: aload #5
    //   245: aload_1
    //   246: invokeinterface ZDM : ()Lburp/Zegg;
    //   251: invokeinterface ZSF : ()Ljava/lang/String;
    //   256: invokestatic ZX : (Ljava/lang/String;)Ljava/lang/String;
    //   259: invokestatic Zp : (Ljava/lang/StringBuilder;Ljava/lang/String;)V
    //   262: aload #5
    //   264: sipush #-25502
    //   267: sipush #25289
    //   270: invokestatic a : (II)Ljava/lang/String;
    //   273: invokevirtual append : (Ljava/lang/String;)Ljava/lang/StringBuilder;
    //   276: pop
    //   277: aload #4
    //   279: ifnull -> 420
    //   282: goto -> 289
    //   285: invokestatic a : (Ljava/io/IOException;)Ljava/io/IOException;
    //   288: athrow
    //   289: aload #5
    //   291: sipush #-25518
    //   294: sipush #1861
    //   297: invokestatic a : (II)Ljava/lang/String;
    //   300: invokevirtual append : (Ljava/lang/String;)Ljava/lang/StringBuilder;
    //   303: pop
    //   304: aload #4
    //   306: ifnull -> 420
    //   309: goto -> 316
    //   312: invokestatic a : (Ljava/io/IOException;)Ljava/io/IOException;
    //   315: athrow
    //   316: aload_1
    //   317: invokeinterface ZDM : ()Lburp/Zegg;
    //   322: invokeinterface ZSF : ()Ljava/lang/String;
    //   327: ifnull -> 398
    //   330: goto -> 337
    //   333: invokestatic a : (Ljava/io/IOException;)Ljava/io/IOException;
    //   336: athrow
    //   337: aload #5
    //   339: sipush #-25520
    //   342: sipush #-6893
    //   345: invokestatic a : (II)Ljava/lang/String;
    //   348: invokevirtual append : (Ljava/lang/String;)Ljava/lang/StringBuilder;
    //   351: pop
    //   352: aload #5
    //   354: aload_1
    //   355: invokeinterface ZDM : ()Lburp/Zegg;
    //   360: invokeinterface ZSF : ()Ljava/lang/String;
    //   365: invokestatic ZX : (Ljava/lang/String;)Ljava/lang/String;
    //   368: invokestatic Zp : (Ljava/lang/StringBuilder;Ljava/lang/String;)V
    //   371: aload #5
    //   373: sipush #-25504
    //   376: sipush #-3066
    //   379: invokestatic a : (II)Ljava/lang/String;
    //   382: invokevirtual append : (Ljava/lang/String;)Ljava/lang/StringBuilder;
    //   385: pop
    //   386: aload #4
    //   388: ifnull -> 420
    //   391: goto -> 398
    //   394: invokestatic a : (Ljava/io/IOException;)Ljava/io/IOException;
    //   397: athrow
    //   398: aload #5
    //   400: sipush #-25500
    //   403: sipush #-25008
    //   406: invokestatic a : (II)Ljava/lang/String;
    //   409: invokevirtual append : (Ljava/lang/String;)Ljava/lang/StringBuilder;
    //   412: pop
    //   413: goto -> 420
    //   416: invokestatic a : (Ljava/io/IOException;)Ljava/io/IOException;
    //   419: athrow
    //   420: aload_1
    //   421: invokeinterface ZDM : ()Lburp/Zegg;
    //   426: invokeinterface ZSt : ()Ljava/lang/String;
    //   431: ifnull -> 490
    //   434: aload #5
    //   436: sipush #-25489
    //   439: sipush #12830
    //   442: invokestatic a : (II)Ljava/lang/String;
    //   445: invokevirtual append : (Ljava/lang/String;)Ljava/lang/StringBuilder;
    //   448: pop
    //   449: aload #5
    //   451: aload_1
    //   452: invokeinterface ZDM : ()Lburp/Zegg;
    //   457: invokeinterface ZSt : ()Ljava/lang/String;
    //   462: invokestatic ZW : (Ljava/lang/String;)Ljava/lang/String;
    //   465: invokestatic ZZ : (Ljava/lang/StringBuilder;Ljava/lang/String;)V
    //   468: aload #5
    //   470: sipush #-25479
    //   473: sipush #-12161
    //   476: invokestatic a : (II)Ljava/lang/String;
    //   479: invokevirtual append : (Ljava/lang/String;)Ljava/lang/StringBuilder;
    //   482: pop
    //   483: goto -> 490
    //   486: invokestatic a : (Ljava/io/IOException;)Ljava/io/IOException;
    //   489: athrow
    //   490: aload_1
    //   491: invokeinterface ZDM : ()Lburp/Zegg;
    //   496: invokeinterface ZSB : ()Ljava/lang/String;
    //   501: ifnull -> 569
    //   504: aload #5
    //   506: sipush #-25473
    //   509: sipush #32202
    //   512: invokestatic a : (II)Ljava/lang/String;
    //   515: invokevirtual append : (Ljava/lang/String;)Ljava/lang/StringBuilder;
    //   518: sipush #-25489
    //   521: sipush #12830
    //   524: invokestatic a : (II)Ljava/lang/String;
    //   527: invokevirtual append : (Ljava/lang/String;)Ljava/lang/StringBuilder;
    //   530: pop
    //   531: aload #5
    //   533: aload_1
    //   534: invokeinterface ZDM : ()Lburp/Zegg;
    //   539: invokeinterface ZSB : ()Ljava/lang/String;
    //   544: invokestatic Zn : (Ljava/lang/StringBuilder;Ljava/lang/String;)V
    //   547: aload #5
    //   549: sipush #-25488
    //   552: sipush #30651
    //   555: invokestatic a : (II)Ljava/lang/String;
    //   558: invokevirtual append : (Ljava/lang/String;)Ljava/lang/StringBuilder;
    //   561: pop
    //   562: goto -> 569
    //   565: invokestatic a : (Ljava/io/IOException;)Ljava/io/IOException;
    //   568: athrow
    //   569: aload #5
    //   571: sipush #-25490
    //   574: sipush #-19008
    //   577: invokestatic a : (II)Ljava/lang/String;
    //   580: invokevirtual append : (Ljava/lang/String;)Ljava/lang/StringBuilder;
    //   583: pop
    //   584: aload #5
    //   586: sipush #-25486
    //   589: sipush #23000
    //   592: invokestatic a : (II)Ljava/lang/String;
    //   595: invokevirtual append : (Ljava/lang/String;)Ljava/lang/StringBuilder;
    //   598: pop
    //   599: aload_0
    //   600: aload #5
    //   602: invokevirtual toString : ()Ljava/lang/String;
    //   605: invokevirtual write : (Ljava/lang/String;)V
    //   608: new burp/Zlkn
    //   611: dup
    //   612: aload_0
    //   613: aload_2
    //   614: aload_3
    //   615: invokespecial <init> : (Ljava/io/Writer;Lburp/Zsh9;Lburp/Zey9;)V
    //   618: astore #6
    //   620: aload_1
    //   621: invokeinterface ZDt : ()Lburp/Zzq1;
    //   626: invokeinterface ZRH : ()Ljava/util/List;
    //   631: iconst_0
    //   632: invokeinterface get : (I)Ljava/lang/Object;
    //   637: checkcast burp/Ztkk
    //   640: aload #6
    //   642: invokeinterface ZC : (Lburp/Zmp5;)V
    //   647: invokestatic Zwu : ()[Lburp/Zbqc;
    //   650: ifnonnull -> 666
    //   653: iconst_5
    //   654: newarray int
    //   656: invokestatic Zo : ([I)V
    //   659: goto -> 666
    //   662: invokestatic a : (Ljava/io/IOException;)Ljava/io/IOException;
    //   665: athrow
    //   666: return
    // Exception table:
    //   from	to	target	type
    //   133	221	224	java/io/IOException
    //   207	282	285	java/io/IOException
    //   228	309	312	java/io/IOException
    //   289	330	333	java/io/IOException
    //   316	391	394	java/io/IOException
    //   337	413	416	java/io/IOException
    //   420	483	486	java/io/IOException
    //   490	562	565	java/io/IOException
    //   620	659	662	java/io/IOException
  }
  
  public static String Zq(Zglw paramZglw) {
    // Byte code:
    //   0: new java/lang/StringBuilder
    //   3: dup
    //   4: invokespecial <init> : ()V
    //   7: astore_2
    //   8: getstatic burp/Zt00.DEFAULT_FONT : Lburp/Zt00;
    //   11: invokevirtual ZV : ()Ljava/awt/Font;
    //   14: astore_3
    //   15: aload_3
    //   16: invokevirtual getFamily : ()Ljava/lang/String;
    //   19: sipush #-25524
    //   22: sipush #-1891
    //   25: invokestatic a : (II)Ljava/lang/String;
    //   28: swap
    //   29: sipush #-25526
    //   32: sipush #22532
    //   35: invokestatic a : (II)Ljava/lang/String;
    //   38: <illegal opcode> makeConcatWithConstants : (Ljava/lang/String;Ljava/lang/String;Ljava/lang/String;)Ljava/lang/String;
    //   43: astore #4
    //   45: invokestatic ZK : ()[I
    //   48: aload_3
    //   49: invokevirtual getSize : ()I
    //   52: iconst_2
    //   53: isub
    //   54: sipush #-25533
    //   57: sipush #-14681
    //   60: invokestatic a : (II)Ljava/lang/String;
    //   63: swap
    //   64: sipush #-25492
    //   67: sipush #-21983
    //   70: invokestatic a : (II)Ljava/lang/String;
    //   73: <illegal opcode> makeConcatWithConstants : (Ljava/lang/String;ILjava/lang/String;)Ljava/lang/String;
    //   78: astore #5
    //   80: aload_2
    //   81: sipush #-25522
    //   84: sipush #16904
    //   87: invokestatic a : (II)Ljava/lang/String;
    //   90: invokevirtual append : (Ljava/lang/String;)Ljava/lang/StringBuilder;
    //   93: aload #4
    //   95: invokevirtual append : (Ljava/lang/String;)Ljava/lang/StringBuilder;
    //   98: aload #5
    //   100: invokevirtual append : (Ljava/lang/String;)Ljava/lang/StringBuilder;
    //   103: sipush #-25483
    //   106: sipush #3460
    //   109: invokestatic a : (II)Ljava/lang/String;
    //   112: invokevirtual append : (Ljava/lang/String;)Ljava/lang/StringBuilder;
    //   115: aload #4
    //   117: invokevirtual append : (Ljava/lang/String;)Ljava/lang/StringBuilder;
    //   120: aload #5
    //   122: invokevirtual append : (Ljava/lang/String;)Ljava/lang/StringBuilder;
    //   125: sipush #-25487
    //   128: sipush #22436
    //   131: invokestatic a : (II)Ljava/lang/String;
    //   134: invokevirtual append : (Ljava/lang/String;)Ljava/lang/StringBuilder;
    //   137: pop
    //   138: aload_2
    //   139: sipush #-25514
    //   142: sipush #3911
    //   145: invokestatic a : (II)Ljava/lang/String;
    //   148: iconst_1
    //   149: anewarray java/lang/Object
    //   152: dup
    //   153: iconst_0
    //   154: aload_0
    //   155: invokeinterface ZDM : ()Lburp/Zegg;
    //   160: invokeinterface ZSC : ()I
    //   165: invokestatic ZD : (I)Ljava/lang/String;
    //   168: aastore
    //   169: invokestatic format : (Ljava/lang/String;[Ljava/lang/Object;)Ljava/lang/String;
    //   172: invokevirtual append : (Ljava/lang/String;)Ljava/lang/StringBuilder;
    //   175: pop
    //   176: astore_1
    //   177: aload_2
    //   178: sipush #-25530
    //   181: sipush #-13451
    //   184: invokestatic a : (II)Ljava/lang/String;
    //   187: invokevirtual append : (Ljava/lang/String;)Ljava/lang/StringBuilder;
    //   190: pop
    //   191: aload_2
    //   192: aload_0
    //   193: invokeinterface ZDM : ()Lburp/Zegg;
    //   198: invokeinterface ZSQ : ()Ljava/lang/String;
    //   203: aload_0
    //   204: invokeinterface ZDM : ()Lburp/Zegg;
    //   209: invokeinterface ZSC : ()I
    //   214: invokestatic Zy : (Ljava/lang/String;I)Ljava/lang/String;
    //   217: invokestatic Zp : (Ljava/lang/StringBuilder;Ljava/lang/String;)V
    //   220: aload_2
    //   221: sipush #-25525
    //   224: sipush #7412
    //   227: invokestatic a : (II)Ljava/lang/String;
    //   230: invokevirtual append : (Ljava/lang/String;)Ljava/lang/StringBuilder;
    //   233: pop
    //   234: aload_2
    //   235: sipush #-25491
    //   238: sipush #19261
    //   241: invokestatic a : (II)Ljava/lang/String;
    //   244: invokevirtual append : (Ljava/lang/String;)Ljava/lang/StringBuilder;
    //   247: pop
    //   248: aload_0
    //   249: invokeinterface ZDM : ()Lburp/Zegg;
    //   254: invokeinterface ZSt : ()Ljava/lang/String;
    //   259: ifnull -> 375
    //   262: aload_0
    //   263: invokeinterface ZDM : ()Lburp/Zegg;
    //   268: invokeinterface ZSF : ()Ljava/lang/String;
    //   273: ifnull -> 357
    //   276: aload_2
    //   277: sipush #-25503
    //   280: sipush #-8219
    //   283: invokestatic a : (II)Ljava/lang/String;
    //   286: invokevirtual append : (Ljava/lang/String;)Ljava/lang/StringBuilder;
    //   289: sipush #-25532
    //   292: sipush #-5863
    //   295: invokestatic a : (II)Ljava/lang/String;
    //   298: invokevirtual append : (Ljava/lang/String;)Ljava/lang/StringBuilder;
    //   301: pop
    //   302: aload_2
    //   303: aload_0
    //   304: invokeinterface ZDM : ()Lburp/Zegg;
    //   309: invokeinterface ZSF : ()Ljava/lang/String;
    //   314: invokestatic ZX : (Ljava/lang/String;)Ljava/lang/String;
    //   317: invokestatic Zp : (Ljava/lang/StringBuilder;Ljava/lang/String;)V
    //   320: aload_2
    //   321: sipush #-25485
    //   324: sipush #-21303
    //   327: invokestatic a : (II)Ljava/lang/String;
    //   330: invokevirtual append : (Ljava/lang/String;)Ljava/lang/StringBuilder;
    //   333: sipush #-25496
    //   336: sipush #-8067
    //   339: invokestatic a : (II)Ljava/lang/String;
    //   342: invokevirtual append : (Ljava/lang/String;)Ljava/lang/StringBuilder;
    //   345: pop
    //   346: aload_1
    //   347: ifnull -> 453
    //   350: iconst_4
    //   351: anewarray burp/Zbqc
    //   354: invokestatic Zr : ([Lburp/Zbqc;)V
    //   357: aload_2
    //   358: sipush #-25529
    //   361: sipush #26064
    //   364: invokestatic a : (II)Ljava/lang/String;
    //   367: invokevirtual append : (Ljava/lang/String;)Ljava/lang/StringBuilder;
    //   370: pop
    //   371: aload_1
    //   372: ifnull -> 453
    //   375: aload_0
    //   376: invokeinterface ZDM : ()Lburp/Zegg;
    //   381: invokeinterface ZSF : ()Ljava/lang/String;
    //   386: ifnull -> 439
    //   389: aload_2
    //   390: sipush #-25481
    //   393: sipush #1744
    //   396: invokestatic a : (II)Ljava/lang/String;
    //   399: invokevirtual append : (Ljava/lang/String;)Ljava/lang/StringBuilder;
    //   402: pop
    //   403: aload_2
    //   404: aload_0
    //   405: invokeinterface ZDM : ()Lburp/Zegg;
    //   410: invokeinterface ZSF : ()Ljava/lang/String;
    //   415: invokestatic ZX : (Ljava/lang/String;)Ljava/lang/String;
    //   418: invokestatic Zp : (Ljava/lang/StringBuilder;Ljava/lang/String;)V
    //   421: aload_2
    //   422: sipush #-25482
    //   425: sipush #-29899
    //   428: invokestatic a : (II)Ljava/lang/String;
    //   431: invokevirtual append : (Ljava/lang/String;)Ljava/lang/StringBuilder;
    //   434: pop
    //   435: aload_1
    //   436: ifnull -> 453
    //   439: aload_2
    //   440: sipush #-25475
    //   443: sipush #-30453
    //   446: invokestatic a : (II)Ljava/lang/String;
    //   449: invokevirtual append : (Ljava/lang/String;)Ljava/lang/StringBuilder;
    //   452: pop
    //   453: aload_0
    //   454: invokeinterface ZDM : ()Lburp/Zegg;
    //   459: invokeinterface ZSt : ()Ljava/lang/String;
    //   464: ifnull -> 513
    //   467: aload_2
    //   468: sipush #-25499
    //   471: sipush #-8842
    //   474: invokestatic a : (II)Ljava/lang/String;
    //   477: invokevirtual append : (Ljava/lang/String;)Ljava/lang/StringBuilder;
    //   480: pop
    //   481: aload_2
    //   482: aload_0
    //   483: invokeinterface ZDM : ()Lburp/Zegg;
    //   488: invokeinterface ZSt : ()Ljava/lang/String;
    //   493: invokestatic ZW : (Ljava/lang/String;)Ljava/lang/String;
    //   496: invokestatic ZZ : (Ljava/lang/StringBuilder;Ljava/lang/String;)V
    //   499: aload_2
    //   500: sipush #-25523
    //   503: sipush #-15557
    //   506: invokestatic a : (II)Ljava/lang/String;
    //   509: invokevirtual append : (Ljava/lang/String;)Ljava/lang/StringBuilder;
    //   512: pop
    //   513: aload_2
    //   514: sipush #-25501
    //   517: sipush #-5919
    //   520: invokestatic a : (II)Ljava/lang/String;
    //   523: invokevirtual append : (Ljava/lang/String;)Ljava/lang/StringBuilder;
    //   526: pop
    //   527: aload_0
    //   528: invokeinterface ZDM : ()Lburp/Zegg;
    //   533: invokeinterface ZSB : ()Ljava/lang/String;
    //   538: ifnull -> 598
    //   541: aload_2
    //   542: sipush #-25536
    //   545: sipush #-6227
    //   548: invokestatic a : (II)Ljava/lang/String;
    //   551: invokevirtual append : (Ljava/lang/String;)Ljava/lang/StringBuilder;
    //   554: pop
    //   555: aload_2
    //   556: sipush #-25527
    //   559: sipush #-18801
    //   562: invokestatic a : (II)Ljava/lang/String;
    //   565: invokevirtual append : (Ljava/lang/String;)Ljava/lang/StringBuilder;
    //   568: pop
    //   569: aload_2
    //   570: aload_0
    //   571: invokeinterface ZDM : ()Lburp/Zegg;
    //   576: invokeinterface ZSB : ()Ljava/lang/String;
    //   581: invokestatic Zn : (Ljava/lang/StringBuilder;Ljava/lang/String;)V
    //   584: aload_2
    //   585: sipush #-25515
    //   588: sipush #23697
    //   591: invokestatic a : (II)Ljava/lang/String;
    //   594: invokevirtual append : (Ljava/lang/String;)Ljava/lang/StringBuilder;
    //   597: pop
    //   598: aload_2
    //   599: invokevirtual toString : ()Ljava/lang/String;
    //   602: areturn
  }
  
  private static String ZX(String paramString) {
    if (!paramString.contains(" ")) {
      Zuh.ZT(false, Zqf.Zr, paramString);
      return paramString;
    } 
    return paramString.split(" ")[1];
  }
  
  private static String Zy(String paramString, int paramInt) {
    if (paramInt == 0) {
      if (!paramString.contains("("))
        return paramString; 
      String str = paramString.substring(0, paramString.indexOf("("));
      if (str.contains(" "))
        paramString = paramString.substring(paramString.indexOf(" ") + 1); 
      if (paramString.contains(a(-25474, 19186)))
        return paramString.substring(0, paramString.indexOf(a(-25517, 6632))); 
    } 
    return paramString;
  }
  
  private static void Zp(StringBuilder paramStringBuilder, String paramString) {
    ZZ(paramStringBuilder, paramString.replace(a(-25534, -23297), "").replace("/", "."));
  }
  
  private static void ZZ(StringBuilder paramStringBuilder, String paramString) {
    String str = paramString;
    if (paramString.length() > 4096)
      str = paramString.substring(0, 4096); 
    Zrlp.Zn(paramStringBuilder, Zmey.ZW(str));
  }
  
  private static IOException a(IOException paramIOException) {
    return paramIOException;
  }
  
  static {
    // Byte code:
    //   0: bipush #56
    //   2: anewarray java/lang/String
    //   5: astore #5
    //   7: iconst_0
    //   8: istore_3
    //   9: ldc '-Â®Â¯\\f`Ã”Â»~Ã´XGÃœÂ¼VhoÃ¦Â¸Â“Ã€|Â£Â¼Â¯ÂµFc 4Â±ÂÂ‘Ã£vÃ¢Âª_ ÃUÃ‘Â \\bÃ¦Â³JlÃ—4ÃµÃ§ÂˆÂ›:Ã‘|Â½ÃªÂ»&Â»Ã·Ã’\\t(ÂÃ¨iTÃ½FÂ—ÃŸbÂˆÃ˜ÂºAÃ®Ã½Â…DÃ—Ã½Ã¥\\fÂÂ€\\bG&Ã6Ã­Â²Ã°Ã–@Ã­,Â»ÂŠ&KÃ´ÃŒMrÂ–AV0\\n4Â’ÂƒÂ‰DÃ´Â‡Ã»Â³yy~5\\rÃÂ•5aMÂ¦Ã²&Ã—Â¤Â*#Â%*2\\fV)z!Ã…yÂ³Ã¬Â­ÃµÂŒÂŒc#Ãº~Ãv7Â¯ÃÂÂ±Ã»Â±Ã¥=xÂ³ kE"e cÂŒ"(Ã©:Â”WÂ‰Ã˜Ã Ã¬Ã•)Ã°Â«7ÂÂ‹XÃ¶=6ÂÂ„&R>Â•ÂŠÂ‹Ã¥/&ÂˆÃœÂ”Â½ÂˆÂµ\\nBÃ«Â‚Â˜sÃ›)ÂŒ%Ã»8'<ÃÂ“gÃ¨nÂ¡bÃ·Ã¸Â©TÃ”Ã»Â²JJOFÂ¸Ã’Ã•!ÂÂªÂ¾Ã˜"Ã DÂ»Ã˜3Â…Â³ÂoÃ¦Â…Ã–Â‚(Ã¢Â“FÃ¬qÂ’OdÂÂ˜Â˜b(Ã‹ÂŸwÃªÃ¸Â‡?Ã²Â¹Ã…RÂ¢Ã»Âšk\pÂ‘\\f\\bÂ«ÃˆÂ®XÂÃÃˆ6ÂªÂ‘ÃµqÂºÂ¯Ãª+Â²\\rÂ’zÃ·Â°DÂ–6Ã®tÃ™ynÃ–Â¬Ã Ã«0Ã­ÂšÂ»\Â‹msÃ³ÃµÂ¤Â´Â¢Ã©ÂdÂªÃ–MÂ‡Ã„!Â’RÂ«Â¾ \\fÃ¹ÃšÂ«ÃˆeO-UÃ¥/Â–Â§JÂ‹}Ã e Â°Â»s~Â…>Â¨Ã¦Â­Â€Â¶6 cÂ¯M+Ã¨Â”Â°(Â¹}ÂRGÃ¯GÃœ6Ãš;Â˜X6ÂŠaÂ»ÂÂ‘Â†Â•Â¾Ã¤Ã…Ã²Ã‡jÂŒM4ÃÃ›Â€~CÃ”eKÂ£Ã„ÃœÃ«]Ã¹LÂ†Ã·Â–Ã‘Â›<Ã–Ã©ÃŸdÃ”ÂœpFcÃ´*Â±\\f0$dÃ¯Pi_ÂŸÂ¨Â†Ã•4u0ÃŠSÂ·;Â€Ã•sÂ“5Â•&Â“Â„ÂªUÃ„hÂÃ—Â¶Â”Â™[O"!Ã„BÃ‰Ã¬ÂFÂ‡Ã¤\\b\\bÃ½Â’ÃŒAÂ–Ã¦9Â½Ã¥Ã­msÂ…Â¬mÃˆÃƒÂ¼y@$Â‰}Ã¥ÂcKÂ˜\\nÂ¤ÂB?KÃŸÃŒÂƒÂ›ÂšpÃ£Ã°Â–Ã»LÃ¸JsÃ‘Ã#Ã‡i<wÂ›aY{qÂ¨Ã½Ã¾Â“Â´]VÃµÂŸ\\tÂ¢uÂyÂ€Ã°&ÂšÂ·1ÃŸÂ›eÃ·?ÂÂ©-!Â˜\\bÃ°Ã§,ÃÃ¢Â„Ã hÂ¬\\t|Ã±JÂ£MÂŸÃºÃ¶RÃF{<Â’Â²W:j|Ãƒ;nÃ«0Ã˜Ã«9Ã–ÂºÃ¥TÂ„57Ã¦Â¼ZÃ¢Â¥Â†]A4Â¬P2ZÃ•$Â¹Ã–ÃœÃ·ÃÂ–Ã“Ã ÂˆÂ®Â‡Ãn@Ã‚inJÃ™ J;ÃÃ½Â„Â¦Ã«NÂ¦>Â¦{9Â£1Â.'(ÂŠÃ1!Â ÂÃƒ"<~ÂŒÃ°8Ã³RÂ‰ÂƒÂ…:>n/Â G}Â’ZdÂ£Â¶6CÂ’__9.CÂÃ­Ã¼Ã¢Ã¢Ã§(Â¸Â¶jÃ\\rÂ„1Â™`Ã±OJÃ«Ã¦Â‡Ã†cÃx~@1OÂŸn6Â²j(3v^Ã¿c;PPnÂ´=NÃ¦PJCYÃ€Â›Ã¹Ã4]kÂ’_Â YÂ‚1ÃÂŸÃ–Â’Ã¬5Â‰Ã¯@Ã†ÂBÂ¬QÃ®Ã¦Ã®y*]Ã¹FÃ³ÃÂ—Ã“fÂª }?Â…YÂ¾qÂ¹G#o+"]2Ã¦ÂƒÂ£Ãœ=Ã9ÂŸÂ­L\\nÃ«Ã†Ã³Â¶SÃºÂ’mÂ®Â‰Ã<\\bÂgÂ£Ã•Â¤Â¨9Ã«Â'Ãƒ*PÂ‡Ã—Â­FoVÃ¬Â–"+ÂKÃÃ…Â³Â°ÃÃ–Ã®Ã•ÃÂ‚~Â¼Ã•Ã®PÃX6<JÃ³Â¬Ã Â†SÃ¸Ã˜Â‡Â¥Ã©i0Ã©\Â»Ã¾\\bFÃ•|Ã¸Â¢Âœ""*ÃªÂ‰MÃ‚`5V@\\fÃ“Ã—VÂ½Ã‡Â„Â¨XÂ‹%Â«Y^Â·Ã›GÃ«Ã­Â·Ã½Â°Ã½5ÃÂ·Ã™aÂ…Â¯\\tÃ·}[~ÃÂ‹dÂ*\\r4Ã“ÂwbÃ¡"ÂŒxÃ¢Ã‰Ã˜ÃœÂ¾lÃ€ÃŒ;Â“Â«Â¼aÂ˜(pa.Â–tÃ¬TlÂ¾ÃA\\fÃ­Â—Ã°L$7VLSÃ¹Â¬Â‰1+Ã¤Ã¿ÂÂŸ:i0RÂ§jÂ¿\\rÃ Ã ?ÂŸ\\bLÃµIÃ]Ã´'Ã˜Ã°ÂœQmmÂ’Ã›Â¾Âœ{Ã­ÃÃ¨Ã«aaÂ¼vPÃ¡ÂWÃ&zÂ‘Ã¸Ã–ÂœMJ~x9Â†TÂ²hÂ¯kÃ¾Â Â‘Ãª&`Ã¨Ã¬ÂPÂ mÂŠÂ©Â’1Ã{\\tÂªÂ¿Â®Â†Â†ÃÃƒÂ·Âº.ÃœÂ•JÂ·%vÂŸÂ’Â¿KÃ¡Ã¥ÃÃ•Â½Â´Â›)Ã”eÃ€*mÂ«Ã©Gcy\\rÂŒÃ±F0s5Âµ6Ã®`hÂ·):Ã’#Ã¤Â”DÃ“Ã¬kÂÃ…Â¼ÂªÃŠ^Âš;;UÂ•$ÂšL2Â¿<Ã¢p\\f5<ÃÂÃÃƒDoÃ‰ÃÂº-Â¿kÃ£bEÃÃ§~B?ÂÂ¦Â‹B8XÂ¯Â»Ã±Ã½cÂ´Â¯MÂÂÂÃ Â‚ÂŠJÃÃ°Ã¶Ã¨Âˆ\\tXP0ÂÂœÃ¬ÂŠÃ¦ÂÃ¯\\nÂ°Ã½Ã»siÂ‡%dt@Â¦DÂ„sÃ4ÂœÃ³}:Â"\\bÂ¿UdÃ™Ã™Ã£MÂ²'
    //   11: dup
    //   12: astore_2
    //   13: invokevirtual length : ()I
    //   16: istore #4
    //   18: bipush #18
    //   20: istore_1
    //   21: iconst_m1
    //   22: istore_0
    //   23: bipush #102
    //   25: iinc #0, 1
    //   28: aload_2
    //   29: iload_0
    //   30: dup
    //   31: iload_1
    //   32: iadd
    //   33: invokevirtual substring : (II)Ljava/lang/String;
    //   36: iconst_m1
    //   37: goto -> 143
    //   40: aload #5
    //   42: swap
    //   43: iload_3
    //   44: iinc #3, 1
    //   47: swap
    //   48: aastore
    //   49: iload_0
    //   50: iload_1
    //   51: iadd
    //   52: dup
    //   53: istore_0
    //   54: iload #4
    //   56: if_icmpge -> 68
    //   59: aload_2
    //   60: iload_0
    //   61: invokevirtual charAt : (I)C
    //   64: istore_1
    //   65: goto -> 23
    //   68: ldc 'Â£Â«]Â«aeÃ†!A#Ã³Â‚ÃºÃ¬#Â¡|Â ÂŸ#rÂ‹Ã¶Â˜DÃ”w/Ã§Ã±|Â©XÂ´Ã“Â¸ÂŠÂÃ”ÂˆwhTKÂ£ÃªÃ¡I*Ã™Â™Ã¯ÃÂ¸Â‘9Â'
    //   70: dup
    //   71: astore_2
    //   72: invokevirtual length : ()I
    //   75: istore #4
    //   77: bipush #34
    //   79: istore_1
    //   80: iconst_m1
    //   81: istore_0
    //   82: bipush #32
    //   84: iinc #0, 1
    //   87: aload_2
    //   88: iload_0
    //   89: dup
    //   90: iload_1
    //   91: iadd
    //   92: invokevirtual substring : (II)Ljava/lang/String;
    //   95: iconst_0
    //   96: goto -> 143
    //   99: aload #5
    //   101: swap
    //   102: iload_3
    //   103: iinc #3, 1
    //   106: swap
    //   107: aastore
    //   108: iload_0
    //   109: iload_1
    //   110: iadd
    //   111: dup
    //   112: istore_0
    //   113: iload #4
    //   115: if_icmpge -> 127
    //   118: aload_2
    //   119: iload_0
    //   120: invokevirtual charAt : (I)C
    //   123: istore_1
    //   124: goto -> 82
    //   127: aload #5
    //   129: putstatic burp/Zt34.a : [Ljava/lang/String;
    //   132: bipush #56
    //   134: anewarray java/lang/String
    //   137: putstatic burp/Zt34.b : [Ljava/lang/String;
    //   140: goto -> 300
    //   143: dup_x2
    //   144: pop
    //   145: invokevirtual toCharArray : ()[C
    //   148: dup_x1
    //   149: arraylength
    //   150: dup_x2
    //   151: pop
    //   152: iconst_0
    //   153: istore #6
    //   155: dup2_x1
    //   156: pop2
    //   157: dup_x2
    //   158: iconst_1
    //   159: if_icmpgt -> 260
    //   162: dup2
    //   163: swap
    //   164: iload #6
    //   166: dup2_x1
    //   167: caload
    //   168: swap
    //   169: iload #6
    //   171: bipush #7
    //   173: irem
    //   174: tableswitch default -> 242, 0 -> 212, 1 -> 217, 2 -> 222, 3 -> 227, 4 -> 232, 5 -> 237
    //   212: bipush #18
    //   214: goto -> 244
    //   217: bipush #91
    //   219: goto -> 244
    //   222: bipush #55
    //   224: goto -> 244
    //   227: bipush #58
    //   229: goto -> 244
    //   232: bipush #19
    //   234: goto -> 244
    //   237: bipush #126
    //   239: goto -> 244
    //   242: bipush #79
    //   244: ixor
    //   245: ixor
    //   246: i2c
    //   247: castore
    //   248: iinc #6, 1
    //   251: dup
    //   252: ifne -> 260
    //   255: dup2
    //   256: dup_x1
    //   257: goto -> 166
    //   260: dup2_x1
    //   261: pop2
    //   262: dup_x2
    //   263: iload #6
    //   265: if_icmpgt -> 162
    //   268: pop
    //   269: new java/lang/String
    //   272: dup_x1
    //   273: swap
    //   274: invokespecial <init> : ([C)V
    //   277: invokevirtual intern : ()Ljava/lang/String;
    //   280: swap
    //   281: pop
    //   282: swap
    //   283: tableswitch default -> 40, 0 -> 99
    //   300: return
  }
  
  private static String a(int paramInt1, int paramInt2) {
    int i = (paramInt1 ^ 0xFFFF9C66) & 0xFFFF;
    if (b[i] == null) {
      char[] arrayOfChar = a[i].toCharArray();
      switch (arrayOfChar[0] & 0xFF) {
        case 0:
        
        case 1:
        
        case 2:
        
        case 3:
        
        case 4:
        
        case 5:
        
        case 6:
        
        case 7:
        
        case 8:
        
        case 9:
        
        case 10:
        
        case 11:
        
        case 12:
        
        case 13:
        
        case 14:
        
        case 15:
        
        case 16:
        
        case 17:
        
        case 18:
        
        case 19:
        
        case 20:
        
        case 21:
        
        case 22:
        
        case 23:
        
        case 24:
        
        case 25:
        
        case 26:
        
        case 27:
        
        case 28:
        
        case 29:
        
        case 30:
        
        case 31:
        
        case 32:
        
        case 33:
        
        case 34:
        
        case 35:
        
        case 36:
        
        case 37:
        
        case 38:
        
        case 39:
        
        case 40:
        
        case 41:
        
        case 42:
        
        case 43:
        
        case 44:
        
        case 45:
        
        case 46:
        
        case 47:
        
        case 48:
        
        case 49:
        
        case 50:
        
        case 51:
        
        case 52:
        
        case 53:
        
        case 54:
        
        case 55:
        
        case 56:
        
        case 57:
        
        case 58:
        
        case 59:
        
        case 60:
        
        case 61:
        
        case 62:
        
        case 63:
        
        case 64:
        
        case 65:
        
        case 66:
        
        case 67:
        
        case 68:
        
        case 69:
        
        case 70:
        
        case 71:
        
        case 72:
        
        case 73:
        
        case 74:
        
        case 75:
        
        case 76:
        
        case 77:
        
        case 78:
        
        case 79:
        
        case 80:
        
        case 81:
        
        case 82:
        
        case 83:
        
        case 84:
        
        case 85:
        
        case 86:
        
        case 87:
        
        case 88:
        
        case 89:
        
        case 90:
        
        case 91:
        
        case 92:
        
        case 93:
        
        case 94:
        
        case 95:
        
        case 96:
        
        case 97:
        
        case 98:
        
        case 99:
        
        case 100:
        
        case 101:
        
        case 102:
        
        case 103:
        
        case 104:
        
        case 105:
        
        case 106:
        
        case 107:
        
        case 108:
        
        case 109:
        
        case 110:
        
        case 111:
        
        case 112:
        
        case 113:
        
        case 114:
        
        case 115:
        
        case 116:
        
        case 117:
        
        case 118:
        
        case 119:
        
        case 120:
        
        case 121:
        
        case 122:
        
        case 123:
        
        case 124:
        
        case 125:
        
        case 126:
        
        case 127:
        
        case 128:
        
        case 129:
        
        case 130:
        
        case 131:
        
        case 132:
        
        case 133:
        
        case 134:
        
        case 135:
        
        case 136:
        
        case 137:
        
        case 138:
        
        case 139:
        
        case 140:
        
        case 141:
        
        case 142:
        
        case 143:
        
        case 144:
        
        case 145:
        
        case 146:
        
        case 147:
        
        case 148:
        
        case 149:
        
        case 150:
        
        case 151:
        
        case 152:
        
        case 153:
        
        case 154:
        
        case 155:
        
        case 156:
        
        case 157:
        
        case 158:
        
        case 159:
        
        case 160:
        
        case 161:
        
        case 162:
        
        case 163:
        
        case 164:
        
        case 165:
        
        case 166:
        
        case 167:
        
        case 168:
        
        case 169:
        
        case 170:
        
        case 171:
        
        case 172:
        
        case 173:
        
        case 174:
        
        case 175:
        
        case 176:
        
        case 177:
        
        case 178:
        
        case 179:
        
        case 180:
        
        case 181:
        
        case 182:
        
        case 183:
        
        case 184:
        
        case 185:
        
        case 186:
        
        case 187:
        
        case 188:
        
        case 189:
        
        case 190:
        
        case 191:
        
        case 192:
        
        case 193:
        
        case 194:
        
        case 195:
        
        case 196:
        
        case 197:
        
        case 198:
        
        case 199:
        
        case 200:
        
        case 201:
        
        case 202:
        
        case 203:
        
        case 204:
        
        case 205:
        
        case 206:
        
        case 207:
        
        case 208:
        
        case 209:
        
        case 210:
        
        case 211:
        
        case 212:
        
        case 213:
        
        case 214:
        
        case 215:
        
        case 216:
        
        case 217:
        
        case 218:
        
        case 219:
        
        case 220:
        
        case 221:
        
        case 222:
        
        case 223:
        
        case 224:
        
        case 225:
        
        case 226:
        
        case 227:
        
        case 228:
        
        case 229:
        
        case 230:
        
        case 231:
        
        case 232:
        
        case 233:
        
        case 234:
        
        case 235:
        
        case 236:
        
        case 237:
        
        case 238:
        
        case 239:
        
        case 240:
        
        case 241:
        
        case 242:
        
        case 243:
        
        case 244:
        
        case 245:
        
        case 246:
        
        case 247:
        
        case 248:
        
        case 249:
        
        case 250:
        
        case 251:
        
        case 252:
        
        case 253:
        
        case 254:
        
        default:
          break;
      } 
      char c = 'Ã¸';
      int j = (paramInt2 & 0xFF) - c;
      if (j < 0)
        j += 256; 
      int k = ((paramInt2 & 0xFFFF) >>> 8) - c;
      if (k < 0)
        k += 256; 
      for (byte b = 0; b < arrayOfChar.length; b++) {
        int m = b % 2;
        if (m == 0) {
          arrayOfChar[b] = (char)(arrayOfChar[b] ^ j);
          j = ((j >>> 3 | j << 5) ^ arrayOfChar[b]) & 0xFF;
        } else {
          arrayOfChar[b] = (char)(arrayOfChar[b] ^ k);
          k = ((k >>> 3 | k << 5) ^ arrayOfChar[b]) & 0xFF;
        } 
      } 
      b[i] = (new String(arrayOfChar)).intern();
    } 
    return b[i];
  }
}


/* Location:              C:\Program Files\BurpSuitePro\burpsuite_pro.jar!\burp\Zt34.class
 * Java compiler version: 21 (65.0)
 * JD-Core Version:       1.1.3
 */