package burp;

import java.math.BigInteger;

class Zt3l extends ClassLoader {
  static Object Zq;
  
  static String Zi;
  
  private static final String[] a;
  
  private static final String[] b;
  
  static boolean Zp(Object[] paramArrayOfObject, Object paramObject) throws Throwable {
    // Byte code:
    //   0: invokestatic ZN : ()Z
    //   3: istore_2
    //   4: new java/lang/StringBuilder
    //   7: dup
    //   8: invokespecial <init> : ()V
    //   11: astore_3
    //   12: iconst_0
    //   13: istore #4
    //   15: iload #4
    //   17: bipush #32
    //   19: if_icmpge -> 1355
    //   22: iload #4
    //   24: tableswitch default -> 1348, 0 -> 168, 1 -> 205, 2 -> 242, 3 -> 279, 4 -> 316, 5 -> 353, 6 -> 390, 7 -> 427, 8 -> 464, 9 -> 501, 10 -> 538, 11 -> 575, 12 -> 612, 13 -> 649, 14 -> 686, 15 -> 723, 16 -> 760, 17 -> 797, 18 -> 834, 19 -> 871, 20 -> 908, 21 -> 945, 22 -> 982, 23 -> 1019, 24 -> 1056, 25 -> 1093, 26 -> 1130, 27 -> 1167, 28 -> 1204, 29 -> 1241, 30 -> 1278, 31 -> 1315
    //   168: aload_3
    //   169: getstatic burp/Zlos.Zp : Ljava/lang/String;
    //   172: getstatic burp/Zxl5.Zh : Ljava/lang/Object;
    //   175: checkcast java/math/BigInteger
    //   178: invokevirtual intValue : ()I
    //   181: bipush #32
    //   183: irem
    //   184: invokestatic abs : (I)I
    //   187: invokevirtual charAt : (I)C
    //   190: invokevirtual append : (C)Ljava/lang/StringBuilder;
    //   193: pop
    //   194: iload_2
    //   195: ifne -> 1348
    //   198: goto -> 205
    //   201: invokestatic a : (Ljava/lang/Throwable;)Ljava/lang/Throwable;
    //   204: athrow
    //   205: aload_3
    //   206: getstatic burp/Zllw.Zg : Ljava/lang/String;
    //   209: getstatic burp/Zx4l.Zt : Ljava/lang/Object;
    //   212: checkcast java/math/BigInteger
    //   215: invokevirtual intValue : ()I
    //   218: bipush #32
    //   220: irem
    //   221: invokestatic abs : (I)I
    //   224: invokevirtual charAt : (I)C
    //   227: invokevirtual append : (C)Ljava/lang/StringBuilder;
    //   230: pop
    //   231: iload_2
    //   232: ifne -> 1348
    //   235: goto -> 242
    //   238: invokestatic a : (Ljava/lang/Throwable;)Ljava/lang/Throwable;
    //   241: athrow
    //   242: aload_3
    //   243: getstatic burp/Zxl5.Zq : Ljava/lang/String;
    //   246: getstatic burp/Zshq.ZK : Ljava/lang/Object;
    //   249: checkcast java/math/BigInteger
    //   252: invokevirtual intValue : ()I
    //   255: bipush #32
    //   257: irem
    //   258: invokestatic abs : (I)I
    //   261: invokevirtual charAt : (I)C
    //   264: invokevirtual append : (C)Ljava/lang/StringBuilder;
    //   267: pop
    //   268: iload_2
    //   269: ifne -> 1348
    //   272: goto -> 279
    //   275: invokestatic a : (Ljava/lang/Throwable;)Ljava/lang/Throwable;
    //   278: athrow
    //   279: aload_3
    //   280: getstatic burp/Zz1k.ZC : Ljava/lang/String;
    //   283: getstatic burp/Zg7z.ZV : Ljava/lang/Object;
    //   286: checkcast java/math/BigInteger
    //   289: invokevirtual intValue : ()I
    //   292: bipush #32
    //   294: irem
    //   295: invokestatic abs : (I)I
    //   298: invokevirtual charAt : (I)C
    //   301: invokevirtual append : (C)Ljava/lang/StringBuilder;
    //   304: pop
    //   305: iload_2
    //   306: ifne -> 1348
    //   309: goto -> 316
    //   312: invokestatic a : (Ljava/lang/Throwable;)Ljava/lang/Throwable;
    //   315: athrow
    //   316: aload_3
    //   317: getstatic burp/Zl2q.ZI : Ljava/lang/String;
    //   320: getstatic burp/Zsm3.ZC : Ljava/lang/Object;
    //   323: checkcast java/math/BigInteger
    //   326: invokevirtual intValue : ()I
    //   329: bipush #32
    //   331: irem
    //   332: invokestatic abs : (I)I
    //   335: invokevirtual charAt : (I)C
    //   338: invokevirtual append : (C)Ljava/lang/StringBuilder;
    //   341: pop
    //   342: iload_2
    //   343: ifne -> 1348
    //   346: goto -> 353
    //   349: invokestatic a : (Ljava/lang/Throwable;)Ljava/lang/Throwable;
    //   352: athrow
    //   353: aload_3
    //   354: getstatic burp/Zxk9.Zx : Ljava/lang/String;
    //   357: getstatic burp/Zt4g.Zv : Ljava/lang/Object;
    //   360: checkcast java/math/BigInteger
    //   363: invokevirtual intValue : ()I
    //   366: bipush #32
    //   368: irem
    //   369: invokestatic abs : (I)I
    //   372: invokevirtual charAt : (I)C
    //   375: invokevirtual append : (C)Ljava/lang/StringBuilder;
    //   378: pop
    //   379: iload_2
    //   380: ifne -> 1348
    //   383: goto -> 390
    //   386: invokestatic a : (Ljava/lang/Throwable;)Ljava/lang/Throwable;
    //   389: athrow
    //   390: aload_3
    //   391: getstatic burp/Zxfu.Zo : Ljava/lang/String;
    //   394: getstatic burp/Zm0s.Zl : Ljava/lang/Object;
    //   397: checkcast java/math/BigInteger
    //   400: invokevirtual intValue : ()I
    //   403: bipush #32
    //   405: irem
    //   406: invokestatic abs : (I)I
    //   409: invokevirtual charAt : (I)C
    //   412: invokevirtual append : (C)Ljava/lang/StringBuilder;
    //   415: pop
    //   416: iload_2
    //   417: ifne -> 1348
    //   420: goto -> 427
    //   423: invokestatic a : (Ljava/lang/Throwable;)Ljava/lang/Throwable;
    //   426: athrow
    //   427: aload_3
    //   428: getstatic burp/Zl88.Zd : Ljava/lang/String;
    //   431: getstatic burp/Zod.ZP : Ljava/lang/Object;
    //   434: checkcast java/math/BigInteger
    //   437: invokevirtual intValue : ()I
    //   440: bipush #32
    //   442: irem
    //   443: invokestatic abs : (I)I
    //   446: invokevirtual charAt : (I)C
    //   449: invokevirtual append : (C)Ljava/lang/StringBuilder;
    //   452: pop
    //   453: iload_2
    //   454: ifne -> 1348
    //   457: goto -> 464
    //   460: invokestatic a : (Ljava/lang/Throwable;)Ljava/lang/Throwable;
    //   463: athrow
    //   464: aload_3
    //   465: getstatic burp/Zt4g.Zj : Ljava/lang/String;
    //   468: getstatic burp/Ze3d.Ze : Ljava/lang/Object;
    //   471: checkcast java/math/BigInteger
    //   474: invokevirtual intValue : ()I
    //   477: bipush #32
    //   479: irem
    //   480: invokestatic abs : (I)I
    //   483: invokevirtual charAt : (I)C
    //   486: invokevirtual append : (C)Ljava/lang/StringBuilder;
    //   489: pop
    //   490: iload_2
    //   491: ifne -> 1348
    //   494: goto -> 501
    //   497: invokestatic a : (Ljava/lang/Throwable;)Ljava/lang/Throwable;
    //   500: athrow
    //   501: aload_3
    //   502: getstatic burp/Zr0g.Zf : Ljava/lang/String;
    //   505: getstatic burp/Zxso.ZF : Ljava/lang/Object;
    //   508: checkcast java/math/BigInteger
    //   511: invokevirtual intValue : ()I
    //   514: bipush #32
    //   516: irem
    //   517: invokestatic abs : (I)I
    //   520: invokevirtual charAt : (I)C
    //   523: invokevirtual append : (C)Ljava/lang/StringBuilder;
    //   526: pop
    //   527: iload_2
    //   528: ifne -> 1348
    //   531: goto -> 538
    //   534: invokestatic a : (Ljava/lang/Throwable;)Ljava/lang/Throwable;
    //   537: athrow
    //   538: aload_3
    //   539: getstatic burp/Ze13.Zg : Ljava/lang/String;
    //   542: getstatic burp/Zxwl.Ze : Ljava/lang/Object;
    //   545: checkcast java/math/BigInteger
    //   548: invokevirtual intValue : ()I
    //   551: bipush #32
    //   553: irem
    //   554: invokestatic abs : (I)I
    //   557: invokevirtual charAt : (I)C
    //   560: invokevirtual append : (C)Ljava/lang/StringBuilder;
    //   563: pop
    //   564: iload_2
    //   565: ifne -> 1348
    //   568: goto -> 575
    //   571: invokestatic a : (Ljava/lang/Throwable;)Ljava/lang/Throwable;
    //   574: athrow
    //   575: aload_3
    //   576: getstatic burp/Zg99.ZH : Ljava/lang/String;
    //   579: getstatic burp/Zz1k.ZP : Ljava/lang/Object;
    //   582: checkcast java/math/BigInteger
    //   585: invokevirtual intValue : ()I
    //   588: bipush #32
    //   590: irem
    //   591: invokestatic abs : (I)I
    //   594: invokevirtual charAt : (I)C
    //   597: invokevirtual append : (C)Ljava/lang/StringBuilder;
    //   600: pop
    //   601: iload_2
    //   602: ifne -> 1348
    //   605: goto -> 612
    //   608: invokestatic a : (Ljava/lang/Throwable;)Ljava/lang/Throwable;
    //   611: athrow
    //   612: aload_3
    //   613: getstatic burp/Zkyc.ZK : Ljava/lang/String;
    //   616: getstatic burp/Zmj4.Zm : Ljava/lang/Object;
    //   619: checkcast java/math/BigInteger
    //   622: invokevirtual intValue : ()I
    //   625: bipush #32
    //   627: irem
    //   628: invokestatic abs : (I)I
    //   631: invokevirtual charAt : (I)C
    //   634: invokevirtual append : (C)Ljava/lang/StringBuilder;
    //   637: pop
    //   638: iload_2
    //   639: ifne -> 1348
    //   642: goto -> 649
    //   645: invokestatic a : (Ljava/lang/Throwable;)Ljava/lang/Throwable;
    //   648: athrow
    //   649: aload_3
    //   650: getstatic burp/Zr0u.Z_ : Ljava/lang/String;
    //   653: getstatic burp/Zsde.Zx : Ljava/lang/Object;
    //   656: checkcast java/math/BigInteger
    //   659: invokevirtual intValue : ()I
    //   662: bipush #32
    //   664: irem
    //   665: invokestatic abs : (I)I
    //   668: invokevirtual charAt : (I)C
    //   671: invokevirtual append : (C)Ljava/lang/StringBuilder;
    //   674: pop
    //   675: iload_2
    //   676: ifne -> 1348
    //   679: goto -> 686
    //   682: invokestatic a : (Ljava/lang/Throwable;)Ljava/lang/Throwable;
    //   685: athrow
    //   686: aload_3
    //   687: getstatic burp/Zkyc.ZK : Ljava/lang/String;
    //   690: getstatic burp/Ze3j.Ze : Ljava/lang/Object;
    //   693: checkcast java/math/BigInteger
    //   696: invokevirtual intValue : ()I
    //   699: bipush #32
    //   701: irem
    //   702: invokestatic abs : (I)I
    //   705: invokevirtual charAt : (I)C
    //   708: invokevirtual append : (C)Ljava/lang/StringBuilder;
    //   711: pop
    //   712: iload_2
    //   713: ifne -> 1348
    //   716: goto -> 723
    //   719: invokestatic a : (Ljava/lang/Throwable;)Ljava/lang/Throwable;
    //   722: athrow
    //   723: aload_3
    //   724: getstatic burp/Zzap.ZA : Ljava/lang/String;
    //   727: getstatic burp/Zxso.ZF : Ljava/lang/Object;
    //   730: checkcast java/math/BigInteger
    //   733: invokevirtual intValue : ()I
    //   736: bipush #32
    //   738: irem
    //   739: invokestatic abs : (I)I
    //   742: invokevirtual charAt : (I)C
    //   745: invokevirtual append : (C)Ljava/lang/StringBuilder;
    //   748: pop
    //   749: iload_2
    //   750: ifne -> 1348
    //   753: goto -> 760
    //   756: invokestatic a : (Ljava/lang/Throwable;)Ljava/lang/Throwable;
    //   759: athrow
    //   760: aload_3
    //   761: getstatic burp/Zehi.Zi : Ljava/lang/String;
    //   764: getstatic burp/Zbp.ZD : Ljava/lang/Object;
    //   767: checkcast java/math/BigInteger
    //   770: invokevirtual intValue : ()I
    //   773: bipush #32
    //   775: irem
    //   776: invokestatic abs : (I)I
    //   779: invokevirtual charAt : (I)C
    //   782: invokevirtual append : (C)Ljava/lang/StringBuilder;
    //   785: pop
    //   786: iload_2
    //   787: ifne -> 1348
    //   790: goto -> 797
    //   793: invokestatic a : (Ljava/lang/Throwable;)Ljava/lang/Throwable;
    //   796: athrow
    //   797: aload_3
    //   798: getstatic burp/Zxzj.ZZ : Ljava/lang/String;
    //   801: getstatic burp/Zrnu.Zs : Ljava/lang/Object;
    //   804: checkcast java/math/BigInteger
    //   807: invokevirtual intValue : ()I
    //   810: bipush #32
    //   812: irem
    //   813: invokestatic abs : (I)I
    //   816: invokevirtual charAt : (I)C
    //   819: invokevirtual append : (C)Ljava/lang/StringBuilder;
    //   822: pop
    //   823: iload_2
    //   824: ifne -> 1348
    //   827: goto -> 834
    //   830: invokestatic a : (Ljava/lang/Throwable;)Ljava/lang/Throwable;
    //   833: athrow
    //   834: aload_3
    //   835: getstatic burp/Zg99.ZH : Ljava/lang/String;
    //   838: getstatic burp/Zxwl.Ze : Ljava/lang/Object;
    //   841: checkcast java/math/BigInteger
    //   844: invokevirtual intValue : ()I
    //   847: bipush #32
    //   849: irem
    //   850: invokestatic abs : (I)I
    //   853: invokevirtual charAt : (I)C
    //   856: invokevirtual append : (C)Ljava/lang/StringBuilder;
    //   859: pop
    //   860: iload_2
    //   861: ifne -> 1348
    //   864: goto -> 871
    //   867: invokestatic a : (Ljava/lang/Throwable;)Ljava/lang/Throwable;
    //   870: athrow
    //   871: aload_3
    //   872: getstatic burp/Zk8b.ZT : Ljava/lang/String;
    //   875: getstatic burp/Zxso.ZF : Ljava/lang/Object;
    //   878: checkcast java/math/BigInteger
    //   881: invokevirtual intValue : ()I
    //   884: bipush #32
    //   886: irem
    //   887: invokestatic abs : (I)I
    //   890: invokevirtual charAt : (I)C
    //   893: invokevirtual append : (C)Ljava/lang/StringBuilder;
    //   896: pop
    //   897: iload_2
    //   898: ifne -> 1348
    //   901: goto -> 908
    //   904: invokestatic a : (Ljava/lang/Throwable;)Ljava/lang/Throwable;
    //   907: athrow
    //   908: aload_3
    //   909: getstatic burp/Ze3d.ZL : Ljava/lang/String;
    //   912: getstatic burp/Zt3l.Zq : Ljava/lang/Object;
    //   915: checkcast java/math/BigInteger
    //   918: invokevirtual intValue : ()I
    //   921: bipush #32
    //   923: irem
    //   924: invokestatic abs : (I)I
    //   927: invokevirtual charAt : (I)C
    //   930: invokevirtual append : (C)Ljava/lang/StringBuilder;
    //   933: pop
    //   934: iload_2
    //   935: ifne -> 1348
    //   938: goto -> 945
    //   941: invokestatic a : (Ljava/lang/Throwable;)Ljava/lang/Throwable;
    //   944: athrow
    //   945: aload_3
    //   946: getstatic burp/Ztnw.Zr : Ljava/lang/String;
    //   949: getstatic burp/Zsgl.Zn : Ljava/lang/Object;
    //   952: checkcast java/math/BigInteger
    //   955: invokevirtual intValue : ()I
    //   958: bipush #32
    //   960: irem
    //   961: invokestatic abs : (I)I
    //   964: invokevirtual charAt : (I)C
    //   967: invokevirtual append : (C)Ljava/lang/StringBuilder;
    //   970: pop
    //   971: iload_2
    //   972: ifne -> 1348
    //   975: goto -> 982
    //   978: invokestatic a : (Ljava/lang/Throwable;)Ljava/lang/Throwable;
    //   981: athrow
    //   982: aload_3
    //   983: getstatic burp/Zrbp.Ze : Ljava/lang/String;
    //   986: getstatic burp/Zgss.Zl : Ljava/lang/Object;
    //   989: checkcast java/math/BigInteger
    //   992: invokevirtual intValue : ()I
    //   995: bipush #32
    //   997: irem
    //   998: invokestatic abs : (I)I
    //   1001: invokevirtual charAt : (I)C
    //   1004: invokevirtual append : (C)Ljava/lang/StringBuilder;
    //   1007: pop
    //   1008: iload_2
    //   1009: ifne -> 1348
    //   1012: goto -> 1019
    //   1015: invokestatic a : (Ljava/lang/Throwable;)Ljava/lang/Throwable;
    //   1018: athrow
    //   1019: aload_3
    //   1020: getstatic burp/Zeh9.ZF : Ljava/lang/String;
    //   1023: getstatic burp/Zg0j.ZV : Ljava/lang/Object;
    //   1026: checkcast java/math/BigInteger
    //   1029: invokevirtual intValue : ()I
    //   1032: bipush #32
    //   1034: irem
    //   1035: invokestatic abs : (I)I
    //   1038: invokevirtual charAt : (I)C
    //   1041: invokevirtual append : (C)Ljava/lang/StringBuilder;
    //   1044: pop
    //   1045: iload_2
    //   1046: ifne -> 1348
    //   1049: goto -> 1056
    //   1052: invokestatic a : (Ljava/lang/Throwable;)Ljava/lang/Throwable;
    //   1055: athrow
    //   1056: aload_3
    //   1057: getstatic burp/Zkyc.ZK : Ljava/lang/String;
    //   1060: getstatic burp/Zxk9.ZI : Ljava/lang/Object;
    //   1063: checkcast java/math/BigInteger
    //   1066: invokevirtual intValue : ()I
    //   1069: bipush #32
    //   1071: irem
    //   1072: invokestatic abs : (I)I
    //   1075: invokevirtual charAt : (I)C
    //   1078: invokevirtual append : (C)Ljava/lang/StringBuilder;
    //   1081: pop
    //   1082: iload_2
    //   1083: ifne -> 1348
    //   1086: goto -> 1093
    //   1089: invokestatic a : (Ljava/lang/Throwable;)Ljava/lang/Throwable;
    //   1092: athrow
    //   1093: aload_3
    //   1094: getstatic burp/Zl_k.Zw : Ljava/lang/String;
    //   1097: getstatic burp/Zkfz.Zr : Ljava/lang/Object;
    //   1100: checkcast java/math/BigInteger
    //   1103: invokevirtual intValue : ()I
    //   1106: bipush #32
    //   1108: irem
    //   1109: invokestatic abs : (I)I
    //   1112: invokevirtual charAt : (I)C
    //   1115: invokevirtual append : (C)Ljava/lang/StringBuilder;
    //   1118: pop
    //   1119: iload_2
    //   1120: ifne -> 1348
    //   1123: goto -> 1130
    //   1126: invokestatic a : (Ljava/lang/Throwable;)Ljava/lang/Throwable;
    //   1129: athrow
    //   1130: aload_3
    //   1131: getstatic burp/Zxzd.ZM : Ljava/lang/String;
    //   1134: getstatic burp/Zxzd.ZD : Ljava/lang/Object;
    //   1137: checkcast java/math/BigInteger
    //   1140: invokevirtual intValue : ()I
    //   1143: bipush #32
    //   1145: irem
    //   1146: invokestatic abs : (I)I
    //   1149: invokevirtual charAt : (I)C
    //   1152: invokevirtual append : (C)Ljava/lang/StringBuilder;
    //   1155: pop
    //   1156: iload_2
    //   1157: ifne -> 1348
    //   1160: goto -> 1167
    //   1163: invokestatic a : (Ljava/lang/Throwable;)Ljava/lang/Throwable;
    //   1166: athrow
    //   1167: aload_3
    //   1168: getstatic burp/Zl_u.Zc : Ljava/lang/String;
    //   1171: getstatic burp/Zm0s.Zl : Ljava/lang/Object;
    //   1174: checkcast java/math/BigInteger
    //   1177: invokevirtual intValue : ()I
    //   1180: bipush #32
    //   1182: irem
    //   1183: invokestatic abs : (I)I
    //   1186: invokevirtual charAt : (I)C
    //   1189: invokevirtual append : (C)Ljava/lang/StringBuilder;
    //   1192: pop
    //   1193: iload_2
    //   1194: ifne -> 1348
    //   1197: goto -> 1204
    //   1200: invokestatic a : (Ljava/lang/Throwable;)Ljava/lang/Throwable;
    //   1203: athrow
    //   1204: aload_3
    //   1205: getstatic burp/Zg0j.Ze : Ljava/lang/String;
    //   1208: getstatic burp/Zkyc.ZD : Ljava/lang/Object;
    //   1211: checkcast java/math/BigInteger
    //   1214: invokevirtual intValue : ()I
    //   1217: bipush #32
    //   1219: irem
    //   1220: invokestatic abs : (I)I
    //   1223: invokevirtual charAt : (I)C
    //   1226: invokevirtual append : (C)Ljava/lang/StringBuilder;
    //   1229: pop
    //   1230: iload_2
    //   1231: ifne -> 1348
    //   1234: goto -> 1241
    //   1237: invokestatic a : (Ljava/lang/Throwable;)Ljava/lang/Throwable;
    //   1240: athrow
    //   1241: aload_3
    //   1242: getstatic burp/Zkbf.Zv : Ljava/lang/String;
    //   1245: getstatic burp/Zg7z.ZV : Ljava/lang/Object;
    //   1248: checkcast java/math/BigInteger
    //   1251: invokevirtual intValue : ()I
    //   1254: bipush #32
    //   1256: irem
    //   1257: invokestatic abs : (I)I
    //   1260: invokevirtual charAt : (I)C
    //   1263: invokevirtual append : (C)Ljava/lang/StringBuilder;
    //   1266: pop
    //   1267: iload_2
    //   1268: ifne -> 1348
    //   1271: goto -> 1278
    //   1274: invokestatic a : (Ljava/lang/Throwable;)Ljava/lang/Throwable;
    //   1277: athrow
    //   1278: aload_3
    //   1279: getstatic burp/Zb8v.Zo : Ljava/lang/String;
    //   1282: getstatic burp/Zsgl.Zn : Ljava/lang/Object;
    //   1285: checkcast java/math/BigInteger
    //   1288: invokevirtual intValue : ()I
    //   1291: bipush #32
    //   1293: irem
    //   1294: invokestatic abs : (I)I
    //   1297: invokevirtual charAt : (I)C
    //   1300: invokevirtual append : (C)Ljava/lang/StringBuilder;
    //   1303: pop
    //   1304: iload_2
    //   1305: ifne -> 1348
    //   1308: goto -> 1315
    //   1311: invokestatic a : (Ljava/lang/Throwable;)Ljava/lang/Throwable;
    //   1314: athrow
    //   1315: aload_3
    //   1316: getstatic burp/Ztnw.Zr : Ljava/lang/String;
    //   1319: getstatic burp/Ztnw.Zt : Ljava/lang/Object;
    //   1322: checkcast java/math/BigInteger
    //   1325: invokevirtual intValue : ()I
    //   1328: bipush #32
    //   1330: irem
    //   1331: invokestatic abs : (I)I
    //   1334: invokevirtual charAt : (I)C
    //   1337: invokevirtual append : (C)Ljava/lang/StringBuilder;
    //   1340: pop
    //   1341: goto -> 1348
    //   1344: invokestatic a : (Ljava/lang/Throwable;)Ljava/lang/Throwable;
    //   1347: athrow
    //   1348: iinc #4, 1
    //   1351: iload_2
    //   1352: ifne -> 15
    //   1355: aload_3
    //   1356: invokevirtual toString : ()Ljava/lang/String;
    //   1359: putstatic burp/Zk8b.ZT : Ljava/lang/String;
    //   1362: sipush #-5248
    //   1365: getstatic burp/Zzqj.Zq : Ljava/lang/Object;
    //   1368: checkcast java/math/BigInteger
    //   1371: getstatic burp/Zzai.Z_ : Ljava/lang/Object;
    //   1374: checkcast java/math/BigInteger
    //   1377: invokevirtual add : (Ljava/math/BigInteger;)Ljava/math/BigInteger;
    //   1380: putstatic burp/Zl_k.ZH : Ljava/lang/Object;
    //   1383: sipush #21989
    //   1386: getstatic burp/Zzap.ZL : Ljava/lang/Object;
    //   1389: checkcast java/math/BigInteger
    //   1392: getstatic burp/Zxfu.ZA : Ljava/lang/Object;
    //   1395: checkcast java/math/BigInteger
    //   1398: invokevirtual subtract : (Ljava/math/BigInteger;)Ljava/math/BigInteger;
    //   1401: putstatic burp/Zzip.ZW : Ljava/lang/Object;
    //   1404: invokestatic a : (II)Ljava/lang/String;
    //   1407: iconst_1
    //   1408: ldc burp/Zeoi
    //   1410: invokevirtual getClassLoader : ()Ljava/lang/ClassLoader;
    //   1413: invokestatic forName : (Ljava/lang/String;ZLjava/lang/ClassLoader;)Ljava/lang/Class;
    //   1416: invokevirtual getDeclaredFields : ()[Ljava/lang/reflect/Field;
    //   1419: astore #4
    //   1421: aload #4
    //   1423: arraylength
    //   1424: istore #5
    //   1426: iconst_0
    //   1427: istore #6
    //   1429: iload #6
    //   1431: iload #5
    //   1433: if_icmpge -> 1571
    //   1436: aload #4
    //   1438: iload #6
    //   1440: aaload
    //   1441: astore #7
    //   1443: aload #7
    //   1445: invokevirtual getModifiers : ()I
    //   1448: invokestatic isStatic : (I)Z
    //   1451: ifne -> 1461
    //   1454: goto -> 1564
    //   1457: invokestatic a : (Ljava/lang/Throwable;)Ljava/lang/Throwable;
    //   1460: athrow
    //   1461: aload #7
    //   1463: invokevirtual getType : ()Ljava/lang/Class;
    //   1466: astore #8
    //   1468: aload #8
    //   1470: ifnull -> 1551
    //   1473: aload #8
    //   1475: invokevirtual isPrimitive : ()Z
    //   1478: ifne -> 1551
    //   1481: goto -> 1488
    //   1484: invokestatic a : (Ljava/lang/Throwable;)Ljava/lang/Throwable;
    //   1487: athrow
    //   1488: aload #8
    //   1490: invokevirtual getPackage : ()Ljava/lang/Package;
    //   1493: ifnull -> 1551
    //   1496: goto -> 1503
    //   1499: invokestatic a : (Ljava/lang/Throwable;)Ljava/lang/Throwable;
    //   1502: athrow
    //   1503: aload #8
    //   1505: invokevirtual getPackage : ()Ljava/lang/Package;
    //   1508: invokevirtual getName : ()Ljava/lang/String;
    //   1511: ifnull -> 1551
    //   1514: goto -> 1521
    //   1517: invokestatic a : (Ljava/lang/Throwable;)Ljava/lang/Throwable;
    //   1520: athrow
    //   1521: aload #8
    //   1523: invokevirtual getPackage : ()Ljava/lang/Package;
    //   1526: invokevirtual getName : ()Ljava/lang/String;
    //   1529: sipush #-5241
    //   1532: sipush #1608
    //   1535: invokestatic a : (II)Ljava/lang/String;
    //   1538: invokevirtual startsWith : (Ljava/lang/String;)Z
    //   1541: ifne -> 1551
    //   1544: goto -> 1551
    //   1547: invokestatic a : (Ljava/lang/Throwable;)Ljava/lang/Throwable;
    //   1550: athrow
    //   1551: aload #7
    //   1553: iconst_1
    //   1554: invokevirtual setAccessible : (Z)V
    //   1557: aload #7
    //   1559: aconst_null
    //   1560: invokevirtual get : (Ljava/lang/Object;)Ljava/lang/Object;
    //   1563: pop
    //   1564: iinc #6, 1
    //   1567: iload_2
    //   1568: ifne -> 1429
    //   1571: sipush #-5242
    //   1574: sipush #27049
    //   1577: invokestatic a : (II)Ljava/lang/String;
    //   1580: invokestatic forName : (Ljava/lang/String;)Ljava/lang/Class;
    //   1583: invokevirtual getDeclaredMethods : ()[Ljava/lang/reflect/Method;
    //   1586: astore #4
    //   1588: aload #4
    //   1590: arraylength
    //   1591: istore #5
    //   1593: iconst_0
    //   1594: istore #6
    //   1596: iload #6
    //   1598: iload #5
    //   1600: if_icmpge -> 1733
    //   1603: aload #4
    //   1605: iload #6
    //   1607: aaload
    //   1608: astore #7
    //   1610: aload #7
    //   1612: invokevirtual getParameterTypes : ()[Ljava/lang/Class;
    //   1615: pop
    //   1616: aload #7
    //   1618: invokevirtual getModifiers : ()I
    //   1621: invokestatic isStatic : (I)Z
    //   1624: ifeq -> 1719
    //   1627: aload #7
    //   1629: invokevirtual getParameterTypes : ()[Ljava/lang/Class;
    //   1632: arraylength
    //   1633: iconst_2
    //   1634: if_icmpne -> 1719
    //   1637: goto -> 1644
    //   1640: invokestatic a : (Ljava/lang/Throwable;)Ljava/lang/Throwable;
    //   1643: athrow
    //   1644: aload #7
    //   1646: invokevirtual getReturnType : ()Ljava/lang/Class;
    //   1649: getstatic java/lang/Void.TYPE : Ljava/lang/Class;
    //   1652: invokevirtual equals : (Ljava/lang/Object;)Z
    //   1655: ifeq -> 1719
    //   1658: goto -> 1665
    //   1661: invokestatic a : (Ljava/lang/Throwable;)Ljava/lang/Throwable;
    //   1664: athrow
    //   1665: aload #7
    //   1667: iconst_1
    //   1668: invokevirtual setAccessible : (Z)V
    //   1671: aload #7
    //   1673: aconst_null
    //   1674: iconst_2
    //   1675: anewarray java/lang/Object
    //   1678: dup
    //   1679: iconst_0
    //   1680: aload_0
    //   1681: aastore
    //   1682: dup
    //   1683: iconst_1
    //   1684: aload_1
    //   1685: ifnonnull -> 1703
    //   1688: goto -> 1695
    //   1691: invokestatic a : (Ljava/lang/Throwable;)Ljava/lang/Throwable;
    //   1694: athrow
    //   1695: aload_1
    //   1696: goto -> 1710
    //   1699: invokestatic a : (Ljava/lang/Throwable;)Ljava/lang/Throwable;
    //   1702: athrow
    //   1703: aload_1
    //   1704: checkcast [B
    //   1707: invokevirtual clone : ()Ljava/lang/Object;
    //   1710: aastore
    //   1711: invokevirtual invoke : (Ljava/lang/Object;[Ljava/lang/Object;)Ljava/lang/Object;
    //   1714: pop
    //   1715: iload_2
    //   1716: ifne -> 1733
    //   1719: iinc #6, 1
    //   1722: iload_2
    //   1723: ifne -> 1596
    //   1726: goto -> 1733
    //   1729: invokestatic a : (Ljava/lang/Throwable;)Ljava/lang/Throwable;
    //   1732: athrow
    //   1733: getstatic burp/Zxso.ZF : Ljava/lang/Object;
    //   1736: checkcast java/math/BigInteger
    //   1739: invokevirtual intValue : ()I
    //   1742: i2l
    //   1743: invokestatic currentTimeMillis : ()J
    //   1746: ladd
    //   1747: getstatic burp/Zrbp.Z_ : Ljava/lang/Object;
    //   1750: checkcast java/math/BigInteger
    //   1753: invokevirtual intValue : ()I
    //   1756: i2l
    //   1757: lcmp
    //   1758: ifge -> 2096
    //   1761: sipush #-5233
    //   1764: sipush #-28577
    //   1767: invokestatic a : (II)Ljava/lang/String;
    //   1770: iconst_1
    //   1771: ldc burp/Zzip
    //   1773: invokevirtual getClassLoader : ()Ljava/lang/ClassLoader;
    //   1776: invokestatic forName : (Ljava/lang/String;ZLjava/lang/ClassLoader;)Ljava/lang/Class;
    //   1779: invokevirtual getDeclaredFields : ()[Ljava/lang/reflect/Field;
    //   1782: astore #4
    //   1784: aload #4
    //   1786: arraylength
    //   1787: istore #5
    //   1789: iconst_0
    //   1790: istore #6
    //   1792: iload #6
    //   1794: iload #5
    //   1796: if_icmpge -> 1934
    //   1799: aload #4
    //   1801: iload #6
    //   1803: aaload
    //   1804: astore #7
    //   1806: aload #7
    //   1808: invokevirtual getModifiers : ()I
    //   1811: invokestatic isStatic : (I)Z
    //   1814: ifne -> 1824
    //   1817: goto -> 1927
    //   1820: invokestatic a : (Ljava/lang/Throwable;)Ljava/lang/Throwable;
    //   1823: athrow
    //   1824: aload #7
    //   1826: invokevirtual getType : ()Ljava/lang/Class;
    //   1829: astore #8
    //   1831: aload #8
    //   1833: ifnull -> 1914
    //   1836: aload #8
    //   1838: invokevirtual isPrimitive : ()Z
    //   1841: ifne -> 1914
    //   1844: goto -> 1851
    //   1847: invokestatic a : (Ljava/lang/Throwable;)Ljava/lang/Throwable;
    //   1850: athrow
    //   1851: aload #8
    //   1853: invokevirtual getPackage : ()Ljava/lang/Package;
    //   1856: ifnull -> 1914
    //   1859: goto -> 1866
    //   1862: invokestatic a : (Ljava/lang/Throwable;)Ljava/lang/Throwable;
    //   1865: athrow
    //   1866: aload #8
    //   1868: invokevirtual getPackage : ()Ljava/lang/Package;
    //   1871: invokevirtual getName : ()Ljava/lang/String;
    //   1874: ifnull -> 1914
    //   1877: goto -> 1884
    //   1880: invokestatic a : (Ljava/lang/Throwable;)Ljava/lang/Throwable;
    //   1883: athrow
    //   1884: aload #8
    //   1886: invokevirtual getPackage : ()Ljava/lang/Package;
    //   1889: invokevirtual getName : ()Ljava/lang/String;
    //   1892: sipush #-5235
    //   1895: sipush #-8104
    //   1898: invokestatic a : (II)Ljava/lang/String;
    //   1901: invokevirtual startsWith : (Ljava/lang/String;)Z
    //   1904: ifne -> 1914
    //   1907: goto -> 1914
    //   1910: invokestatic a : (Ljava/lang/Throwable;)Ljava/lang/Throwable;
    //   1913: athrow
    //   1914: aload #7
    //   1916: iconst_1
    //   1917: invokevirtual setAccessible : (Z)V
    //   1920: aload #7
    //   1922: aconst_null
    //   1923: invokevirtual get : (Ljava/lang/Object;)Ljava/lang/Object;
    //   1926: pop
    //   1927: iinc #6, 1
    //   1930: iload_2
    //   1931: ifne -> 1792
    //   1934: sipush #-5234
    //   1937: sipush #-7022
    //   1940: invokestatic a : (II)Ljava/lang/String;
    //   1943: invokestatic forName : (Ljava/lang/String;)Ljava/lang/Class;
    //   1946: invokevirtual getDeclaredMethods : ()[Ljava/lang/reflect/Method;
    //   1949: astore #4
    //   1951: aload #4
    //   1953: arraylength
    //   1954: istore #5
    //   1956: iconst_0
    //   1957: istore #6
    //   1959: iload #6
    //   1961: iload #5
    //   1963: if_icmpge -> 2096
    //   1966: aload #4
    //   1968: iload #6
    //   1970: aaload
    //   1971: astore #7
    //   1973: aload #7
    //   1975: invokevirtual getParameterTypes : ()[Ljava/lang/Class;
    //   1978: pop
    //   1979: aload #7
    //   1981: invokevirtual getModifiers : ()I
    //   1984: invokestatic isStatic : (I)Z
    //   1987: ifeq -> 2082
    //   1990: aload #7
    //   1992: invokevirtual getParameterTypes : ()[Ljava/lang/Class;
    //   1995: arraylength
    //   1996: iconst_2
    //   1997: if_icmpne -> 2082
    //   2000: goto -> 2007
    //   2003: invokestatic a : (Ljava/lang/Throwable;)Ljava/lang/Throwable;
    //   2006: athrow
    //   2007: aload #7
    //   2009: invokevirtual getReturnType : ()Ljava/lang/Class;
    //   2012: getstatic java/lang/Void.TYPE : Ljava/lang/Class;
    //   2015: invokevirtual equals : (Ljava/lang/Object;)Z
    //   2018: ifeq -> 2082
    //   2021: goto -> 2028
    //   2024: invokestatic a : (Ljava/lang/Throwable;)Ljava/lang/Throwable;
    //   2027: athrow
    //   2028: aload #7
    //   2030: iconst_1
    //   2031: invokevirtual setAccessible : (Z)V
    //   2034: aload #7
    //   2036: aconst_null
    //   2037: iconst_2
    //   2038: anewarray java/lang/Object
    //   2041: dup
    //   2042: iconst_0
    //   2043: aload_0
    //   2044: aastore
    //   2045: dup
    //   2046: iconst_1
    //   2047: aload_1
    //   2048: ifnonnull -> 2066
    //   2051: goto -> 2058
    //   2054: invokestatic a : (Ljava/lang/Throwable;)Ljava/lang/Throwable;
    //   2057: athrow
    //   2058: aload_1
    //   2059: goto -> 2073
    //   2062: invokestatic a : (Ljava/lang/Throwable;)Ljava/lang/Throwable;
    //   2065: athrow
    //   2066: aload_1
    //   2067: checkcast [B
    //   2070: invokevirtual clone : ()Ljava/lang/Object;
    //   2073: aastore
    //   2074: invokevirtual invoke : (Ljava/lang/Object;[Ljava/lang/Object;)Ljava/lang/Object;
    //   2077: pop
    //   2078: iload_2
    //   2079: ifne -> 2096
    //   2082: iinc #6, 1
    //   2085: iload_2
    //   2086: ifne -> 1959
    //   2089: goto -> 2096
    //   2092: invokestatic a : (Ljava/lang/Throwable;)Ljava/lang/Throwable;
    //   2095: athrow
    //   2096: getstatic burp/Zlhm.ZT : Ljava/lang/Object;
    //   2099: checkcast java/math/BigInteger
    //   2102: invokevirtual toByteArray : ()[B
    //   2105: astore #4
    //   2107: bipush #64
    //   2109: newarray byte
    //   2111: dup
    //   2112: iconst_0
    //   2113: bipush #-128
    //   2115: bastore
    //   2116: dup
    //   2117: iconst_1
    //   2118: iconst_0
    //   2119: bastore
    //   2120: dup
    //   2121: iconst_2
    //   2122: iconst_0
    //   2123: bastore
    //   2124: dup
    //   2125: iconst_3
    //   2126: iconst_0
    //   2127: bastore
    //   2128: dup
    //   2129: iconst_4
    //   2130: iconst_0
    //   2131: bastore
    //   2132: dup
    //   2133: iconst_5
    //   2134: iconst_0
    //   2135: bastore
    //   2136: dup
    //   2137: bipush #6
    //   2139: iconst_0
    //   2140: bastore
    //   2141: dup
    //   2142: bipush #7
    //   2144: iconst_0
    //   2145: bastore
    //   2146: dup
    //   2147: bipush #8
    //   2149: iconst_0
    //   2150: bastore
    //   2151: dup
    //   2152: bipush #9
    //   2154: iconst_0
    //   2155: bastore
    //   2156: dup
    //   2157: bipush #10
    //   2159: iconst_0
    //   2160: bastore
    //   2161: dup
    //   2162: bipush #11
    //   2164: iconst_0
    //   2165: bastore
    //   2166: dup
    //   2167: bipush #12
    //   2169: iconst_0
    //   2170: bastore
    //   2171: dup
    //   2172: bipush #13
    //   2174: iconst_0
    //   2175: bastore
    //   2176: dup
    //   2177: bipush #14
    //   2179: iconst_0
    //   2180: bastore
    //   2181: dup
    //   2182: bipush #15
    //   2184: iconst_0
    //   2185: bastore
    //   2186: dup
    //   2187: bipush #16
    //   2189: iconst_0
    //   2190: bastore
    //   2191: dup
    //   2192: bipush #17
    //   2194: iconst_0
    //   2195: bastore
    //   2196: dup
    //   2197: bipush #18
    //   2199: iconst_0
    //   2200: bastore
    //   2201: dup
    //   2202: bipush #19
    //   2204: iconst_0
    //   2205: bastore
    //   2206: dup
    //   2207: bipush #20
    //   2209: iconst_0
    //   2210: bastore
    //   2211: dup
    //   2212: bipush #21
    //   2214: iconst_0
    //   2215: bastore
    //   2216: dup
    //   2217: bipush #22
    //   2219: iconst_0
    //   2220: bastore
    //   2221: dup
    //   2222: bipush #23
    //   2224: iconst_0
    //   2225: bastore
    //   2226: dup
    //   2227: bipush #24
    //   2229: iconst_0
    //   2230: bastore
    //   2231: dup
    //   2232: bipush #25
    //   2234: iconst_0
    //   2235: bastore
    //   2236: dup
    //   2237: bipush #26
    //   2239: iconst_0
    //   2240: bastore
    //   2241: dup
    //   2242: bipush #27
    //   2244: iconst_0
    //   2245: bastore
    //   2246: dup
    //   2247: bipush #28
    //   2249: iconst_0
    //   2250: bastore
    //   2251: dup
    //   2252: bipush #29
    //   2254: iconst_0
    //   2255: bastore
    //   2256: dup
    //   2257: bipush #30
    //   2259: iconst_0
    //   2260: bastore
    //   2261: dup
    //   2262: bipush #31
    //   2264: iconst_0
    //   2265: bastore
    //   2266: dup
    //   2267: bipush #32
    //   2269: iconst_0
    //   2270: bastore
    //   2271: dup
    //   2272: bipush #33
    //   2274: iconst_0
    //   2275: bastore
    //   2276: dup
    //   2277: bipush #34
    //   2279: iconst_0
    //   2280: bastore
    //   2281: dup
    //   2282: bipush #35
    //   2284: iconst_0
    //   2285: bastore
    //   2286: dup
    //   2287: bipush #36
    //   2289: iconst_0
    //   2290: bastore
    //   2291: dup
    //   2292: bipush #37
    //   2294: iconst_0
    //   2295: bastore
    //   2296: dup
    //   2297: bipush #38
    //   2299: iconst_0
    //   2300: bastore
    //   2301: dup
    //   2302: bipush #39
    //   2304: iconst_0
    //   2305: bastore
    //   2306: dup
    //   2307: bipush #40
    //   2309: iconst_0
    //   2310: bastore
    //   2311: dup
    //   2312: bipush #41
    //   2314: iconst_0
    //   2315: bastore
    //   2316: dup
    //   2317: bipush #42
    //   2319: iconst_0
    //   2320: bastore
    //   2321: dup
    //   2322: bipush #43
    //   2324: iconst_0
    //   2325: bastore
    //   2326: dup
    //   2327: bipush #44
    //   2329: iconst_0
    //   2330: bastore
    //   2331: dup
    //   2332: bipush #45
    //   2334: iconst_0
    //   2335: bastore
    //   2336: dup
    //   2337: bipush #46
    //   2339: iconst_0
    //   2340: bastore
    //   2341: dup
    //   2342: bipush #47
    //   2344: iconst_0
    //   2345: bastore
    //   2346: dup
    //   2347: bipush #48
    //   2349: iconst_0
    //   2350: bastore
    //   2351: dup
    //   2352: bipush #49
    //   2354: iconst_0
    //   2355: bastore
    //   2356: dup
    //   2357: bipush #50
    //   2359: iconst_0
    //   2360: bastore
    //   2361: dup
    //   2362: bipush #51
    //   2364: iconst_0
    //   2365: bastore
    //   2366: dup
    //   2367: bipush #52
    //   2369: iconst_0
    //   2370: bastore
    //   2371: dup
    //   2372: bipush #53
    //   2374: iconst_0
    //   2375: bastore
    //   2376: dup
    //   2377: bipush #54
    //   2379: iconst_0
    //   2380: bastore
    //   2381: dup
    //   2382: bipush #55
    //   2384: iconst_0
    //   2385: bastore
    //   2386: dup
    //   2387: bipush #56
    //   2389: iconst_0
    //   2390: bastore
    //   2391: dup
    //   2392: bipush #57
    //   2394: iconst_0
    //   2395: bastore
    //   2396: dup
    //   2397: bipush #58
    //   2399: iconst_0
    //   2400: bastore
    //   2401: dup
    //   2402: bipush #59
    //   2404: iconst_0
    //   2405: bastore
    //   2406: dup
    //   2407: bipush #60
    //   2409: iconst_0
    //   2410: bastore
    //   2411: dup
    //   2412: bipush #61
    //   2414: iconst_0
    //   2415: bastore
    //   2416: dup
    //   2417: bipush #62
    //   2419: iconst_0
    //   2420: bastore
    //   2421: dup
    //   2422: bipush #63
    //   2424: iconst_0
    //   2425: bastore
    //   2426: astore #6
    //   2428: bipush #64
    //   2430: newarray int
    //   2432: dup
    //   2433: iconst_0
    //   2434: ldc 1116352408
    //   2436: iastore
    //   2437: dup
    //   2438: iconst_1
    //   2439: ldc 1899447441
    //   2441: iastore
    //   2442: dup
    //   2443: iconst_2
    //   2444: ldc -1245643825
    //   2446: iastore
    //   2447: dup
    //   2448: iconst_3
    //   2449: ldc -373957723
    //   2451: iastore
    //   2452: dup
    //   2453: iconst_4
    //   2454: ldc 961987163
    //   2456: iastore
    //   2457: dup
    //   2458: iconst_5
    //   2459: ldc 1508970993
    //   2461: iastore
    //   2462: dup
    //   2463: bipush #6
    //   2465: ldc -1841331548
    //   2467: iastore
    //   2468: dup
    //   2469: bipush #7
    //   2471: ldc -1424204075
    //   2473: iastore
    //   2474: dup
    //   2475: bipush #8
    //   2477: ldc -670586216
    //   2479: iastore
    //   2480: dup
    //   2481: bipush #9
    //   2483: ldc 310598401
    //   2485: iastore
    //   2486: dup
    //   2487: bipush #10
    //   2489: ldc 607225278
    //   2491: iastore
    //   2492: dup
    //   2493: bipush #11
    //   2495: ldc 1426881987
    //   2497: iastore
    //   2498: dup
    //   2499: bipush #12
    //   2501: ldc 1925078388
    //   2503: iastore
    //   2504: dup
    //   2505: bipush #13
    //   2507: ldc -2132889090
    //   2509: iastore
    //   2510: dup
    //   2511: bipush #14
    //   2513: ldc -1680079193
    //   2515: iastore
    //   2516: dup
    //   2517: bipush #15
    //   2519: ldc -1046744716
    //   2521: iastore
    //   2522: dup
    //   2523: bipush #16
    //   2525: ldc -459576895
    //   2527: iastore
    //   2528: dup
    //   2529: bipush #17
    //   2531: ldc -272742522
    //   2533: iastore
    //   2534: dup
    //   2535: bipush #18
    //   2537: ldc 264347078
    //   2539: iastore
    //   2540: dup
    //   2541: bipush #19
    //   2543: ldc 604807628
    //   2545: iastore
    //   2546: dup
    //   2547: bipush #20
    //   2549: ldc 770255983
    //   2551: iastore
    //   2552: dup
    //   2553: bipush #21
    //   2555: ldc 1249150122
    //   2557: iastore
    //   2558: dup
    //   2559: bipush #22
    //   2561: ldc 1555081692
    //   2563: iastore
    //   2564: dup
    //   2565: bipush #23
    //   2567: ldc 1996064986
    //   2569: iastore
    //   2570: dup
    //   2571: bipush #24
    //   2573: ldc -1740746414
    //   2575: iastore
    //   2576: dup
    //   2577: bipush #25
    //   2579: ldc -1473132947
    //   2581: iastore
    //   2582: dup
    //   2583: bipush #26
    //   2585: ldc -1341970488
    //   2587: iastore
    //   2588: dup
    //   2589: bipush #27
    //   2591: ldc -1084653625
    //   2593: iastore
    //   2594: dup
    //   2595: bipush #28
    //   2597: ldc -958395405
    //   2599: iastore
    //   2600: dup
    //   2601: bipush #29
    //   2603: ldc -710438585
    //   2605: iastore
    //   2606: dup
    //   2607: bipush #30
    //   2609: ldc 113926993
    //   2611: iastore
    //   2612: dup
    //   2613: bipush #31
    //   2615: ldc 338241895
    //   2617: iastore
    //   2618: dup
    //   2619: bipush #32
    //   2621: ldc 666307205
    //   2623: iastore
    //   2624: dup
    //   2625: bipush #33
    //   2627: ldc 773529912
    //   2629: iastore
    //   2630: dup
    //   2631: bipush #34
    //   2633: ldc 1294757372
    //   2635: iastore
    //   2636: dup
    //   2637: bipush #35
    //   2639: ldc 1396182291
    //   2641: iastore
    //   2642: dup
    //   2643: bipush #36
    //   2645: ldc 1695183700
    //   2647: iastore
    //   2648: dup
    //   2649: bipush #37
    //   2651: ldc 1986661051
    //   2653: iastore
    //   2654: dup
    //   2655: bipush #38
    //   2657: ldc -2117940946
    //   2659: iastore
    //   2660: dup
    //   2661: bipush #39
    //   2663: ldc -1838011259
    //   2665: iastore
    //   2666: dup
    //   2667: bipush #40
    //   2669: ldc -1564481375
    //   2671: iastore
    //   2672: dup
    //   2673: bipush #41
    //   2675: ldc -1474664885
    //   2677: iastore
    //   2678: dup
    //   2679: bipush #42
    //   2681: ldc -1035236496
    //   2683: iastore
    //   2684: dup
    //   2685: bipush #43
    //   2687: ldc -949202525
    //   2689: iastore
    //   2690: dup
    //   2691: bipush #44
    //   2693: ldc -778901479
    //   2695: iastore
    //   2696: dup
    //   2697: bipush #45
    //   2699: ldc -694614492
    //   2701: iastore
    //   2702: dup
    //   2703: bipush #46
    //   2705: ldc -200395387
    //   2707: iastore
    //   2708: dup
    //   2709: bipush #47
    //   2711: ldc 275423344
    //   2713: iastore
    //   2714: dup
    //   2715: bipush #48
    //   2717: ldc 430227734
    //   2719: iastore
    //   2720: dup
    //   2721: bipush #49
    //   2723: ldc 506948616
    //   2725: iastore
    //   2726: dup
    //   2727: bipush #50
    //   2729: ldc 659060556
    //   2731: iastore
    //   2732: dup
    //   2733: bipush #51
    //   2735: ldc 883997877
    //   2737: iastore
    //   2738: dup
    //   2739: bipush #52
    //   2741: ldc 958139571
    //   2743: iastore
    //   2744: dup
    //   2745: bipush #53
    //   2747: ldc 1322822218
    //   2749: iastore
    //   2750: dup
    //   2751: bipush #54
    //   2753: ldc 1537002063
    //   2755: iastore
    //   2756: dup
    //   2757: bipush #55
    //   2759: ldc 1747873779
    //   2761: iastore
    //   2762: dup
    //   2763: bipush #56
    //   2765: ldc 1955562222
    //   2767: iastore
    //   2768: dup
    //   2769: bipush #57
    //   2771: ldc 2024104815
    //   2773: iastore
    //   2774: dup
    //   2775: bipush #58
    //   2777: ldc -2067236844
    //   2779: iastore
    //   2780: dup
    //   2781: bipush #59
    //   2783: ldc -1933114872
    //   2785: iastore
    //   2786: dup
    //   2787: bipush #60
    //   2789: ldc -1866530822
    //   2791: iastore
    //   2792: dup
    //   2793: bipush #61
    //   2795: ldc -1538233109
    //   2797: iastore
    //   2798: dup
    //   2799: bipush #62
    //   2801: ldc -1090935817
    //   2803: iastore
    //   2804: dup
    //   2805: bipush #63
    //   2807: ldc -965641998
    //   2809: iastore
    //   2810: astore #7
    //   2812: iconst_2
    //   2813: newarray int
    //   2815: dup
    //   2816: iconst_0
    //   2817: iconst_0
    //   2818: iastore
    //   2819: dup
    //   2820: iconst_1
    //   2821: iconst_0
    //   2822: iastore
    //   2823: astore #8
    //   2825: bipush #8
    //   2827: newarray int
    //   2829: dup
    //   2830: iconst_0
    //   2831: ldc 1779033703
    //   2833: iastore
    //   2834: dup
    //   2835: iconst_1
    //   2836: ldc -1150833019
    //   2838: iastore
    //   2839: dup
    //   2840: iconst_2
    //   2841: ldc 1013904242
    //   2843: iastore
    //   2844: dup
    //   2845: iconst_3
    //   2846: ldc -1521486534
    //   2848: iastore
    //   2849: dup
    //   2850: iconst_4
    //   2851: ldc 1359893119
    //   2853: iastore
    //   2854: dup
    //   2855: iconst_5
    //   2856: ldc -1694144372
    //   2858: iastore
    //   2859: dup
    //   2860: bipush #6
    //   2862: ldc 528734635
    //   2864: iastore
    //   2865: dup
    //   2866: bipush #7
    //   2868: ldc 1541459225
    //   2870: iastore
    //   2871: astore #9
    //   2873: bipush #64
    //   2875: newarray byte
    //   2877: astore #10
    //   2879: bipush #64
    //   2881: newarray byte
    //   2883: astore #11
    //   2885: aload #4
    //   2887: arraylength
    //   2888: istore #12
    //   2890: aload #8
    //   2892: iconst_0
    //   2893: iaload
    //   2894: bipush #63
    //   2896: iand
    //   2897: istore #13
    //   2899: aload #8
    //   2901: iconst_0
    //   2902: dup2
    //   2903: iaload
    //   2904: iload #12
    //   2906: iadd
    //   2907: iastore
    //   2908: aload #8
    //   2910: iconst_0
    //   2911: dup2
    //   2912: iaload
    //   2913: iconst_m1
    //   2914: iand
    //   2915: iastore
    //   2916: aload #8
    //   2918: iconst_0
    //   2919: iaload
    //   2920: iload #12
    //   2922: if_icmpge -> 2940
    //   2925: aload #8
    //   2927: iconst_1
    //   2928: dup2
    //   2929: iaload
    //   2930: iconst_1
    //   2931: iadd
    //   2932: iastore
    //   2933: goto -> 2940
    //   2936: invokestatic a : (Ljava/lang/Throwable;)Ljava/lang/Throwable;
    //   2939: athrow
    //   2940: iconst_0
    //   2941: istore #14
    //   2943: iload #12
    //   2945: bipush #64
    //   2947: if_icmplt -> 3557
    //   2950: iconst_0
    //   2951: istore #15
    //   2953: iload #15
    //   2955: bipush #64
    //   2957: if_icmpge -> 2980
    //   2960: aload #11
    //   2962: iload #15
    //   2964: aload #4
    //   2966: iload #14
    //   2968: iload #15
    //   2970: iadd
    //   2971: baload
    //   2972: bastore
    //   2973: iinc #15, 1
    //   2976: iload_2
    //   2977: ifne -> 2953
    //   2980: bipush #64
    //   2982: newarray int
    //   2984: astore #15
    //   2986: bipush #8
    //   2988: newarray int
    //   2990: astore #16
    //   2992: iconst_0
    //   2993: istore #17
    //   2995: iload #17
    //   2997: bipush #8
    //   2999: if_icmpge -> 3019
    //   3002: aload #16
    //   3004: iload #17
    //   3006: aload #9
    //   3008: iload #17
    //   3010: iaload
    //   3011: iastore
    //   3012: iinc #17, 1
    //   3015: iload_2
    //   3016: ifne -> 2995
    //   3019: iconst_0
    //   3020: istore #17
    //   3022: iload #17
    //   3024: bipush #64
    //   3026: if_icmpge -> 3517
    //   3029: iload #17
    //   3031: bipush #16
    //   3033: if_icmpge -> 3114
    //   3036: aload #15
    //   3038: iload #17
    //   3040: aload #11
    //   3042: iconst_4
    //   3043: iload #17
    //   3045: imul
    //   3046: baload
    //   3047: sipush #255
    //   3050: iand
    //   3051: bipush #24
    //   3053: ishl
    //   3054: aload #11
    //   3056: iconst_4
    //   3057: iload #17
    //   3059: imul
    //   3060: iconst_1
    //   3061: iadd
    //   3062: baload
    //   3063: sipush #255
    //   3066: iand
    //   3067: bipush #16
    //   3069: ishl
    //   3070: ior
    //   3071: aload #11
    //   3073: iconst_4
    //   3074: iload #17
    //   3076: imul
    //   3077: iconst_2
    //   3078: iadd
    //   3079: baload
    //   3080: sipush #255
    //   3083: iand
    //   3084: bipush #8
    //   3086: ishl
    //   3087: ior
    //   3088: aload #11
    //   3090: iconst_4
    //   3091: iload #17
    //   3093: imul
    //   3094: iconst_3
    //   3095: iadd
    //   3096: baload
    //   3097: sipush #255
    //   3100: iand
    //   3101: ior
    //   3102: iastore
    //   3103: iload_2
    //   3104: ifne -> 3257
    //   3107: goto -> 3114
    //   3110: invokestatic a : (Ljava/lang/Throwable;)Ljava/lang/Throwable;
    //   3113: athrow
    //   3114: aload #15
    //   3116: iload #17
    //   3118: aload #15
    //   3120: iload #17
    //   3122: iconst_2
    //   3123: isub
    //   3124: iaload
    //   3125: bipush #17
    //   3127: iushr
    //   3128: aload #15
    //   3130: iload #17
    //   3132: iconst_2
    //   3133: isub
    //   3134: iaload
    //   3135: bipush #15
    //   3137: ishl
    //   3138: ior
    //   3139: aload #15
    //   3141: iload #17
    //   3143: iconst_2
    //   3144: isub
    //   3145: iaload
    //   3146: bipush #19
    //   3148: iushr
    //   3149: aload #15
    //   3151: iload #17
    //   3153: iconst_2
    //   3154: isub
    //   3155: iaload
    //   3156: bipush #13
    //   3158: ishl
    //   3159: ior
    //   3160: ixor
    //   3161: aload #15
    //   3163: iload #17
    //   3165: iconst_2
    //   3166: isub
    //   3167: iaload
    //   3168: bipush #10
    //   3170: iushr
    //   3171: ixor
    //   3172: aload #15
    //   3174: iload #17
    //   3176: bipush #7
    //   3178: isub
    //   3179: iaload
    //   3180: iadd
    //   3181: aload #15
    //   3183: iload #17
    //   3185: bipush #15
    //   3187: isub
    //   3188: iaload
    //   3189: bipush #7
    //   3191: iushr
    //   3192: aload #15
    //   3194: iload #17
    //   3196: bipush #15
    //   3198: isub
    //   3199: iaload
    //   3200: bipush #25
    //   3202: ishl
    //   3203: ior
    //   3204: aload #15
    //   3206: iload #17
    //   3208: bipush #15
    //   3210: isub
    //   3211: iaload
    //   3212: bipush #18
    //   3214: iushr
    //   3215: aload #15
    //   3217: iload #17
    //   3219: bipush #15
    //   3221: isub
    //   3222: iaload
    //   3223: bipush #14
    //   3225: ishl
    //   3226: ior
    //   3227: ixor
    //   3228: aload #15
    //   3230: iload #17
    //   3232: bipush #15
    //   3234: isub
    //   3235: iaload
    //   3236: iconst_3
    //   3237: iushr
    //   3238: ixor
    //   3239: iadd
    //   3240: aload #15
    //   3242: iload #17
    //   3244: bipush #16
    //   3246: isub
    //   3247: iaload
    //   3248: iadd
    //   3249: iastore
    //   3250: goto -> 3257
    //   3253: invokestatic a : (Ljava/lang/Throwable;)Ljava/lang/Throwable;
    //   3256: athrow
    //   3257: aload #16
    //   3259: bipush #7
    //   3261: iaload
    //   3262: aload #16
    //   3264: iconst_4
    //   3265: iaload
    //   3266: bipush #6
    //   3268: iushr
    //   3269: aload #16
    //   3271: iconst_4
    //   3272: iaload
    //   3273: bipush #26
    //   3275: ishl
    //   3276: ior
    //   3277: aload #16
    //   3279: iconst_4
    //   3280: iaload
    //   3281: bipush #11
    //   3283: iushr
    //   3284: aload #16
    //   3286: iconst_4
    //   3287: iaload
    //   3288: bipush #21
    //   3290: ishl
    //   3291: ior
    //   3292: ixor
    //   3293: aload #16
    //   3295: iconst_4
    //   3296: iaload
    //   3297: bipush #25
    //   3299: iushr
    //   3300: aload #16
    //   3302: iconst_4
    //   3303: iaload
    //   3304: bipush #7
    //   3306: ishl
    //   3307: ior
    //   3308: ixor
    //   3309: iadd
    //   3310: aload #16
    //   3312: bipush #6
    //   3314: iaload
    //   3315: aload #16
    //   3317: iconst_4
    //   3318: iaload
    //   3319: aload #16
    //   3321: iconst_5
    //   3322: iaload
    //   3323: aload #16
    //   3325: bipush #6
    //   3327: iaload
    //   3328: ixor
    //   3329: iand
    //   3330: ixor
    //   3331: iadd
    //   3332: aload #7
    //   3334: iload #17
    //   3336: iaload
    //   3337: iadd
    //   3338: aload #15
    //   3340: iload #17
    //   3342: iaload
    //   3343: iadd
    //   3344: istore #18
    //   3346: aload #16
    //   3348: iconst_0
    //   3349: iaload
    //   3350: iconst_2
    //   3351: iushr
    //   3352: aload #16
    //   3354: iconst_0
    //   3355: iaload
    //   3356: bipush #30
    //   3358: ishl
    //   3359: ior
    //   3360: aload #16
    //   3362: iconst_0
    //   3363: iaload
    //   3364: bipush #13
    //   3366: iushr
    //   3367: aload #16
    //   3369: iconst_0
    //   3370: iaload
    //   3371: bipush #19
    //   3373: ishl
    //   3374: ior
    //   3375: ixor
    //   3376: aload #16
    //   3378: iconst_0
    //   3379: iaload
    //   3380: bipush #22
    //   3382: iushr
    //   3383: aload #16
    //   3385: iconst_0
    //   3386: iaload
    //   3387: bipush #10
    //   3389: ishl
    //   3390: ior
    //   3391: ixor
    //   3392: aload #16
    //   3394: iconst_0
    //   3395: iaload
    //   3396: aload #16
    //   3398: iconst_1
    //   3399: iaload
    //   3400: iand
    //   3401: aload #16
    //   3403: iconst_2
    //   3404: iaload
    //   3405: aload #16
    //   3407: iconst_0
    //   3408: iaload
    //   3409: aload #16
    //   3411: iconst_1
    //   3412: iaload
    //   3413: ior
    //   3414: iand
    //   3415: ior
    //   3416: iadd
    //   3417: istore #19
    //   3419: aload #16
    //   3421: iconst_3
    //   3422: dup2
    //   3423: iaload
    //   3424: iload #18
    //   3426: iadd
    //   3427: iastore
    //   3428: aload #16
    //   3430: bipush #7
    //   3432: iload #18
    //   3434: iload #19
    //   3436: iadd
    //   3437: iastore
    //   3438: aload #16
    //   3440: bipush #7
    //   3442: iaload
    //   3443: istore #18
    //   3445: aload #16
    //   3447: bipush #7
    //   3449: aload #16
    //   3451: bipush #6
    //   3453: iaload
    //   3454: iastore
    //   3455: aload #16
    //   3457: bipush #6
    //   3459: aload #16
    //   3461: iconst_5
    //   3462: iaload
    //   3463: iastore
    //   3464: aload #16
    //   3466: iconst_5
    //   3467: aload #16
    //   3469: iconst_4
    //   3470: iaload
    //   3471: iastore
    //   3472: aload #16
    //   3474: iconst_4
    //   3475: aload #16
    //   3477: iconst_3
    //   3478: iaload
    //   3479: iastore
    //   3480: aload #16
    //   3482: iconst_3
    //   3483: aload #16
    //   3485: iconst_2
    //   3486: iaload
    //   3487: iastore
    //   3488: aload #16
    //   3490: iconst_2
    //   3491: aload #16
    //   3493: iconst_1
    //   3494: iaload
    //   3495: iastore
    //   3496: aload #16
    //   3498: iconst_1
    //   3499: aload #16
    //   3501: iconst_0
    //   3502: iaload
    //   3503: iastore
    //   3504: aload #16
    //   3506: iconst_0
    //   3507: iload #18
    //   3509: iastore
    //   3510: iinc #17, 1
    //   3513: iload_2
    //   3514: ifne -> 3022
    //   3517: iconst_0
    //   3518: istore #17
    //   3520: iload #17
    //   3522: bipush #8
    //   3524: if_icmpge -> 3547
    //   3527: aload #9
    //   3529: iload #17
    //   3531: dup2
    //   3532: iaload
    //   3533: aload #16
    //   3535: iload #17
    //   3537: iaload
    //   3538: iadd
    //   3539: iastore
    //   3540: iinc #17, 1
    //   3543: iload_2
    //   3544: ifne -> 3520
    //   3547: iinc #14, 64
    //   3550: iinc #12, -64
    //   3553: iload_2
    //   3554: ifne -> 2943
    //   3557: iload #12
    //   3559: ifle -> 3595
    //   3562: iconst_0
    //   3563: istore #15
    //   3565: iload #15
    //   3567: iload #12
    //   3569: if_icmpge -> 3595
    //   3572: aload #10
    //   3574: iload #13
    //   3576: iload #15
    //   3578: iadd
    //   3579: aload #4
    //   3581: iload #14
    //   3583: iload #15
    //   3585: iadd
    //   3586: baload
    //   3587: bastore
    //   3588: iinc #15, 1
    //   3591: iload_2
    //   3592: ifne -> 3565
    //   3595: aload #8
    //   3597: iconst_0
    //   3598: iaload
    //   3599: bipush #29
    //   3601: iushr
    //   3602: aload #8
    //   3604: iconst_1
    //   3605: iaload
    //   3606: iconst_3
    //   3607: ishl
    //   3608: ior
    //   3609: istore #15
    //   3611: aload #8
    //   3613: iconst_0
    //   3614: iaload
    //   3615: iconst_3
    //   3616: ishl
    //   3617: istore #16
    //   3619: aload #8
    //   3621: iconst_0
    //   3622: iaload
    //   3623: bipush #63
    //   3625: iand
    //   3626: istore #17
    //   3628: iload #17
    //   3630: bipush #56
    //   3632: if_icmpge -> 3647
    //   3635: bipush #56
    //   3637: iload #17
    //   3639: isub
    //   3640: goto -> 3652
    //   3643: invokestatic a : (Ljava/lang/Throwable;)Ljava/lang/Throwable;
    //   3646: athrow
    //   3647: bipush #120
    //   3649: iload #17
    //   3651: isub
    //   3652: istore #18
    //   3654: aload #8
    //   3656: iconst_0
    //   3657: iaload
    //   3658: bipush #63
    //   3660: iand
    //   3661: istore #13
    //   3663: bipush #64
    //   3665: iload #13
    //   3667: isub
    //   3668: istore #19
    //   3670: aload #8
    //   3672: iconst_0
    //   3673: dup2
    //   3674: iaload
    //   3675: iload #18
    //   3677: iadd
    //   3678: iastore
    //   3679: aload #8
    //   3681: iconst_0
    //   3682: dup2
    //   3683: iaload
    //   3684: iconst_m1
    //   3685: iand
    //   3686: iastore
    //   3687: aload #8
    //   3689: iconst_0
    //   3690: iaload
    //   3691: iload #18
    //   3693: if_icmpge -> 3711
    //   3696: aload #8
    //   3698: iconst_1
    //   3699: dup2
    //   3700: iaload
    //   3701: iconst_1
    //   3702: iadd
    //   3703: iastore
    //   3704: goto -> 3711
    //   3707: invokestatic a : (Ljava/lang/Throwable;)Ljava/lang/Throwable;
    //   3710: athrow
    //   3711: iconst_0
    //   3712: istore #14
    //   3714: iload #13
    //   3716: ifle -> 4347
    //   3719: iload #18
    //   3721: iload #19
    //   3723: if_icmplt -> 4347
    //   3726: goto -> 3733
    //   3729: invokestatic a : (Ljava/lang/Throwable;)Ljava/lang/Throwable;
    //   3732: athrow
    //   3733: iconst_0
    //   3734: istore #20
    //   3736: iload #20
    //   3738: iload #19
    //   3740: if_icmpge -> 3763
    //   3743: aload #10
    //   3745: iload #13
    //   3747: iload #20
    //   3749: iadd
    //   3750: aload #6
    //   3752: iload #20
    //   3754: baload
    //   3755: bastore
    //   3756: iinc #20, 1
    //   3759: iload_2
    //   3760: ifne -> 3736
    //   3763: bipush #64
    //   3765: newarray int
    //   3767: astore #20
    //   3769: bipush #8
    //   3771: newarray int
    //   3773: astore #21
    //   3775: iconst_0
    //   3776: istore #22
    //   3778: iload #22
    //   3780: bipush #8
    //   3782: if_icmpge -> 3802
    //   3785: aload #21
    //   3787: iload #22
    //   3789: aload #9
    //   3791: iload #22
    //   3793: iaload
    //   3794: iastore
    //   3795: iinc #22, 1
    //   3798: iload_2
    //   3799: ifne -> 3778
    //   3802: iconst_0
    //   3803: istore #22
    //   3805: iload #22
    //   3807: bipush #64
    //   3809: if_icmpge -> 4300
    //   3812: iload #22
    //   3814: bipush #16
    //   3816: if_icmpge -> 3897
    //   3819: aload #20
    //   3821: iload #22
    //   3823: aload #10
    //   3825: iconst_4
    //   3826: iload #22
    //   3828: imul
    //   3829: baload
    //   3830: sipush #255
    //   3833: iand
    //   3834: bipush #24
    //   3836: ishl
    //   3837: aload #10
    //   3839: iconst_4
    //   3840: iload #22
    //   3842: imul
    //   3843: iconst_1
    //   3844: iadd
    //   3845: baload
    //   3846: sipush #255
    //   3849: iand
    //   3850: bipush #16
    //   3852: ishl
    //   3853: ior
    //   3854: aload #10
    //   3856: iconst_4
    //   3857: iload #22
    //   3859: imul
    //   3860: iconst_2
    //   3861: iadd
    //   3862: baload
    //   3863: sipush #255
    //   3866: iand
    //   3867: bipush #8
    //   3869: ishl
    //   3870: ior
    //   3871: aload #10
    //   3873: iconst_4
    //   3874: iload #22
    //   3876: imul
    //   3877: iconst_3
    //   3878: iadd
    //   3879: baload
    //   3880: sipush #255
    //   3883: iand
    //   3884: ior
    //   3885: iastore
    //   3886: iload_2
    //   3887: ifne -> 4040
    //   3890: goto -> 3897
    //   3893: invokestatic a : (Ljava/lang/Throwable;)Ljava/lang/Throwable;
    //   3896: athrow
    //   3897: aload #20
    //   3899: iload #22
    //   3901: aload #20
    //   3903: iload #22
    //   3905: iconst_2
    //   3906: isub
    //   3907: iaload
    //   3908: bipush #17
    //   3910: iushr
    //   3911: aload #20
    //   3913: iload #22
    //   3915: iconst_2
    //   3916: isub
    //   3917: iaload
    //   3918: bipush #15
    //   3920: ishl
    //   3921: ior
    //   3922: aload #20
    //   3924: iload #22
    //   3926: iconst_2
    //   3927: isub
    //   3928: iaload
    //   3929: bipush #19
    //   3931: iushr
    //   3932: aload #20
    //   3934: iload #22
    //   3936: iconst_2
    //   3937: isub
    //   3938: iaload
    //   3939: bipush #13
    //   3941: ishl
    //   3942: ior
    //   3943: ixor
    //   3944: aload #20
    //   3946: iload #22
    //   3948: iconst_2
    //   3949: isub
    //   3950: iaload
    //   3951: bipush #10
    //   3953: iushr
    //   3954: ixor
    //   3955: aload #20
    //   3957: iload #22
    //   3959: bipush #7
    //   3961: isub
    //   3962: iaload
    //   3963: iadd
    //   3964: aload #20
    //   3966: iload #22
    //   3968: bipush #15
    //   3970: isub
    //   3971: iaload
    //   3972: bipush #7
    //   3974: iushr
    //   3975: aload #20
    //   3977: iload #22
    //   3979: bipush #15
    //   3981: isub
    //   3982: iaload
    //   3983: bipush #25
    //   3985: ishl
    //   3986: ior
    //   3987: aload #20
    //   3989: iload #22
    //   3991: bipush #15
    //   3993: isub
    //   3994: iaload
    //   3995: bipush #18
    //   3997: iushr
    //   3998: aload #20
    //   4000: iload #22
    //   4002: bipush #15
    //   4004: isub
    //   4005: iaload
    //   4006: bipush #14
    //   4008: ishl
    //   4009: ior
    //   4010: ixor
    //   4011: aload #20
    //   4013: iload #22
    //   4015: bipush #15
    //   4017: isub
    //   4018: iaload
    //   4019: iconst_3
    //   4020: iushr
    //   4021: ixor
    //   4022: iadd
    //   4023: aload #20
    //   4025: iload #22
    //   4027: bipush #16
    //   4029: isub
    //   4030: iaload
    //   4031: iadd
    //   4032: iastore
    //   4033: goto -> 4040
    //   4036: invokestatic a : (Ljava/lang/Throwable;)Ljava/lang/Throwable;
    //   4039: athrow
    //   4040: aload #21
    //   4042: bipush #7
    //   4044: iaload
    //   4045: aload #21
    //   4047: iconst_4
    //   4048: iaload
    //   4049: bipush #6
    //   4051: iushr
    //   4052: aload #21
    //   4054: iconst_4
    //   4055: iaload
    //   4056: bipush #26
    //   4058: ishl
    //   4059: ior
    //   4060: aload #21
    //   4062: iconst_4
    //   4063: iaload
    //   4064: bipush #11
    //   4066: iushr
    //   4067: aload #21
    //   4069: iconst_4
    //   4070: iaload
    //   4071: bipush #21
    //   4073: ishl
    //   4074: ior
    //   4075: ixor
    //   4076: aload #21
    //   4078: iconst_4
    //   4079: iaload
    //   4080: bipush #25
    //   4082: iushr
    //   4083: aload #21
    //   4085: iconst_4
    //   4086: iaload
    //   4087: bipush #7
    //   4089: ishl
    //   4090: ior
    //   4091: ixor
    //   4092: iadd
    //   4093: aload #21
    //   4095: bipush #6
    //   4097: iaload
    //   4098: aload #21
    //   4100: iconst_4
    //   4101: iaload
    //   4102: aload #21
    //   4104: iconst_5
    //   4105: iaload
    //   4106: aload #21
    //   4108: bipush #6
    //   4110: iaload
    //   4111: ixor
    //   4112: iand
    //   4113: ixor
    //   4114: iadd
    //   4115: aload #7
    //   4117: iload #22
    //   4119: iaload
    //   4120: iadd
    //   4121: aload #20
    //   4123: iload #22
    //   4125: iaload
    //   4126: iadd
    //   4127: istore #23
    //   4129: aload #21
    //   4131: iconst_0
    //   4132: iaload
    //   4133: iconst_2
    //   4134: iushr
    //   4135: aload #21
    //   4137: iconst_0
    //   4138: iaload
    //   4139: bipush #30
    //   4141: ishl
    //   4142: ior
    //   4143: aload #21
    //   4145: iconst_0
    //   4146: iaload
    //   4147: bipush #13
    //   4149: iushr
    //   4150: aload #21
    //   4152: iconst_0
    //   4153: iaload
    //   4154: bipush #19
    //   4156: ishl
    //   4157: ior
    //   4158: ixor
    //   4159: aload #21
    //   4161: iconst_0
    //   4162: iaload
    //   4163: bipush #22
    //   4165: iushr
    //   4166: aload #21
    //   4168: iconst_0
    //   4169: iaload
    //   4170: bipush #10
    //   4172: ishl
    //   4173: ior
    //   4174: ixor
    //   4175: aload #21
    //   4177: iconst_0
    //   4178: iaload
    //   4179: aload #21
    //   4181: iconst_1
    //   4182: iaload
    //   4183: iand
    //   4184: aload #21
    //   4186: iconst_2
    //   4187: iaload
    //   4188: aload #21
    //   4190: iconst_0
    //   4191: iaload
    //   4192: aload #21
    //   4194: iconst_1
    //   4195: iaload
    //   4196: ior
    //   4197: iand
    //   4198: ior
    //   4199: iadd
    //   4200: istore #24
    //   4202: aload #21
    //   4204: iconst_3
    //   4205: dup2
    //   4206: iaload
    //   4207: iload #23
    //   4209: iadd
    //   4210: iastore
    //   4211: aload #21
    //   4213: bipush #7
    //   4215: iload #23
    //   4217: iload #24
    //   4219: iadd
    //   4220: iastore
    //   4221: aload #21
    //   4223: bipush #7
    //   4225: iaload
    //   4226: istore #23
    //   4228: aload #21
    //   4230: bipush #7
    //   4232: aload #21
    //   4234: bipush #6
    //   4236: iaload
    //   4237: iastore
    //   4238: aload #21
    //   4240: bipush #6
    //   4242: aload #21
    //   4244: iconst_5
    //   4245: iaload
    //   4246: iastore
    //   4247: aload #21
    //   4249: iconst_5
    //   4250: aload #21
    //   4252: iconst_4
    //   4253: iaload
    //   4254: iastore
    //   4255: aload #21
    //   4257: iconst_4
    //   4258: aload #21
    //   4260: iconst_3
    //   4261: iaload
    //   4262: iastore
    //   4263: aload #21
    //   4265: iconst_3
    //   4266: aload #21
    //   4268: iconst_2
    //   4269: iaload
    //   4270: iastore
    //   4271: aload #21
    //   4273: iconst_2
    //   4274: aload #21
    //   4276: iconst_1
    //   4277: iaload
    //   4278: iastore
    //   4279: aload #21
    //   4281: iconst_1
    //   4282: aload #21
    //   4284: iconst_0
    //   4285: iaload
    //   4286: iastore
    //   4287: aload #21
    //   4289: iconst_0
    //   4290: iload #23
    //   4292: iastore
    //   4293: iinc #22, 1
    //   4296: iload_2
    //   4297: ifne -> 3805
    //   4300: iconst_0
    //   4301: istore #22
    //   4303: iload #22
    //   4305: bipush #8
    //   4307: if_icmpge -> 4330
    //   4310: aload #9
    //   4312: iload #22
    //   4314: dup2
    //   4315: iaload
    //   4316: aload #21
    //   4318: iload #22
    //   4320: iaload
    //   4321: iadd
    //   4322: iastore
    //   4323: iinc #22, 1
    //   4326: iload_2
    //   4327: ifne -> 4303
    //   4330: iload #14
    //   4332: iload #19
    //   4334: iadd
    //   4335: istore #14
    //   4337: iload #18
    //   4339: iload #19
    //   4341: isub
    //   4342: istore #18
    //   4344: iconst_0
    //   4345: istore #13
    //   4347: iload #18
    //   4349: bipush #64
    //   4351: if_icmplt -> 4961
    //   4354: iconst_0
    //   4355: istore #20
    //   4357: iload #20
    //   4359: bipush #64
    //   4361: if_icmpge -> 4384
    //   4364: aload #11
    //   4366: iload #20
    //   4368: aload #6
    //   4370: iload #14
    //   4372: iload #20
    //   4374: iadd
    //   4375: baload
    //   4376: bastore
    //   4377: iinc #20, 1
    //   4380: iload_2
    //   4381: ifne -> 4357
    //   4384: bipush #64
    //   4386: newarray int
    //   4388: astore #20
    //   4390: bipush #8
    //   4392: newarray int
    //   4394: astore #21
    //   4396: iconst_0
    //   4397: istore #22
    //   4399: iload #22
    //   4401: bipush #8
    //   4403: if_icmpge -> 4423
    //   4406: aload #21
    //   4408: iload #22
    //   4410: aload #9
    //   4412: iload #22
    //   4414: iaload
    //   4415: iastore
    //   4416: iinc #22, 1
    //   4419: iload_2
    //   4420: ifne -> 4399
    //   4423: iconst_0
    //   4424: istore #22
    //   4426: iload #22
    //   4428: bipush #64
    //   4430: if_icmpge -> 4921
    //   4433: iload #22
    //   4435: bipush #16
    //   4437: if_icmpge -> 4518
    //   4440: aload #20
    //   4442: iload #22
    //   4444: aload #11
    //   4446: iconst_4
    //   4447: iload #22
    //   4449: imul
    //   4450: baload
    //   4451: sipush #255
    //   4454: iand
    //   4455: bipush #24
    //   4457: ishl
    //   4458: aload #11
    //   4460: iconst_4
    //   4461: iload #22
    //   4463: imul
    //   4464: iconst_1
    //   4465: iadd
    //   4466: baload
    //   4467: sipush #255
    //   4470: iand
    //   4471: bipush #16
    //   4473: ishl
    //   4474: ior
    //   4475: aload #11
    //   4477: iconst_4
    //   4478: iload #22
    //   4480: imul
    //   4481: iconst_2
    //   4482: iadd
    //   4483: baload
    //   4484: sipush #255
    //   4487: iand
    //   4488: bipush #8
    //   4490: ishl
    //   4491: ior
    //   4492: aload #11
    //   4494: iconst_4
    //   4495: iload #22
    //   4497: imul
    //   4498: iconst_3
    //   4499: iadd
    //   4500: baload
    //   4501: sipush #255
    //   4504: iand
    //   4505: ior
    //   4506: iastore
    //   4507: iload_2
    //   4508: ifne -> 4661
    //   4511: goto -> 4518
    //   4514: invokestatic a : (Ljava/lang/Throwable;)Ljava/lang/Throwable;
    //   4517: athrow
    //   4518: aload #20
    //   4520: iload #22
    //   4522: aload #20
    //   4524: iload #22
    //   4526: iconst_2
    //   4527: isub
    //   4528: iaload
    //   4529: bipush #17
    //   4531: iushr
    //   4532: aload #20
    //   4534: iload #22
    //   4536: iconst_2
    //   4537: isub
    //   4538: iaload
    //   4539: bipush #15
    //   4541: ishl
    //   4542: ior
    //   4543: aload #20
    //   4545: iload #22
    //   4547: iconst_2
    //   4548: isub
    //   4549: iaload
    //   4550: bipush #19
    //   4552: iushr
    //   4553: aload #20
    //   4555: iload #22
    //   4557: iconst_2
    //   4558: isub
    //   4559: iaload
    //   4560: bipush #13
    //   4562: ishl
    //   4563: ior
    //   4564: ixor
    //   4565: aload #20
    //   4567: iload #22
    //   4569: iconst_2
    //   4570: isub
    //   4571: iaload
    //   4572: bipush #10
    //   4574: iushr
    //   4575: ixor
    //   4576: aload #20
    //   4578: iload #22
    //   4580: bipush #7
    //   4582: isub
    //   4583: iaload
    //   4584: iadd
    //   4585: aload #20
    //   4587: iload #22
    //   4589: bipush #15
    //   4591: isub
    //   4592: iaload
    //   4593: bipush #7
    //   4595: iushr
    //   4596: aload #20
    //   4598: iload #22
    //   4600: bipush #15
    //   4602: isub
    //   4603: iaload
    //   4604: bipush #25
    //   4606: ishl
    //   4607: ior
    //   4608: aload #20
    //   4610: iload #22
    //   4612: bipush #15
    //   4614: isub
    //   4615: iaload
    //   4616: bipush #18
    //   4618: iushr
    //   4619: aload #20
    //   4621: iload #22
    //   4623: bipush #15
    //   4625: isub
    //   4626: iaload
    //   4627: bipush #14
    //   4629: ishl
    //   4630: ior
    //   4631: ixor
    //   4632: aload #20
    //   4634: iload #22
    //   4636: bipush #15
    //   4638: isub
    //   4639: iaload
    //   4640: iconst_3
    //   4641: iushr
    //   4642: ixor
    //   4643: iadd
    //   4644: aload #20
    //   4646: iload #22
    //   4648: bipush #16
    //   4650: isub
    //   4651: iaload
    //   4652: iadd
    //   4653: iastore
    //   4654: goto -> 4661
    //   4657: invokestatic a : (Ljava/lang/Throwable;)Ljava/lang/Throwable;
    //   4660: athrow
    //   4661: aload #21
    //   4663: bipush #7
    //   4665: iaload
    //   4666: aload #21
    //   4668: iconst_4
    //   4669: iaload
    //   4670: bipush #6
    //   4672: iushr
    //   4673: aload #21
    //   4675: iconst_4
    //   4676: iaload
    //   4677: bipush #26
    //   4679: ishl
    //   4680: ior
    //   4681: aload #21
    //   4683: iconst_4
    //   4684: iaload
    //   4685: bipush #11
    //   4687: iushr
    //   4688: aload #21
    //   4690: iconst_4
    //   4691: iaload
    //   4692: bipush #21
    //   4694: ishl
    //   4695: ior
    //   4696: ixor
    //   4697: aload #21
    //   4699: iconst_4
    //   4700: iaload
    //   4701: bipush #25
    //   4703: iushr
    //   4704: aload #21
    //   4706: iconst_4
    //   4707: iaload
    //   4708: bipush #7
    //   4710: ishl
    //   4711: ior
    //   4712: ixor
    //   4713: iadd
    //   4714: aload #21
    //   4716: bipush #6
    //   4718: iaload
    //   4719: aload #21
    //   4721: iconst_4
    //   4722: iaload
    //   4723: aload #21
    //   4725: iconst_5
    //   4726: iaload
    //   4727: aload #21
    //   4729: bipush #6
    //   4731: iaload
    //   4732: ixor
    //   4733: iand
    //   4734: ixor
    //   4735: iadd
    //   4736: aload #7
    //   4738: iload #22
    //   4740: iaload
    //   4741: iadd
    //   4742: aload #20
    //   4744: iload #22
    //   4746: iaload
    //   4747: iadd
    //   4748: istore #23
    //   4750: aload #21
    //   4752: iconst_0
    //   4753: iaload
    //   4754: iconst_2
    //   4755: iushr
    //   4756: aload #21
    //   4758: iconst_0
    //   4759: iaload
    //   4760: bipush #30
    //   4762: ishl
    //   4763: ior
    //   4764: aload #21
    //   4766: iconst_0
    //   4767: iaload
    //   4768: bipush #13
    //   4770: iushr
    //   4771: aload #21
    //   4773: iconst_0
    //   4774: iaload
    //   4775: bipush #19
    //   4777: ishl
    //   4778: ior
    //   4779: ixor
    //   4780: aload #21
    //   4782: iconst_0
    //   4783: iaload
    //   4784: bipush #22
    //   4786: iushr
    //   4787: aload #21
    //   4789: iconst_0
    //   4790: iaload
    //   4791: bipush #10
    //   4793: ishl
    //   4794: ior
    //   4795: ixor
    //   4796: aload #21
    //   4798: iconst_0
    //   4799: iaload
    //   4800: aload #21
    //   4802: iconst_1
    //   4803: iaload
    //   4804: iand
    //   4805: aload #21
    //   4807: iconst_2
    //   4808: iaload
    //   4809: aload #21
    //   4811: iconst_0
    //   4812: iaload
    //   4813: aload #21
    //   4815: iconst_1
    //   4816: iaload
    //   4817: ior
    //   4818: iand
    //   4819: ior
    //   4820: iadd
    //   4821: istore #24
    //   4823: aload #21
    //   4825: iconst_3
    //   4826: dup2
    //   4827: iaload
    //   4828: iload #23
    //   4830: iadd
    //   4831: iastore
    //   4832: aload #21
    //   4834: bipush #7
    //   4836: iload #23
    //   4838: iload #24
    //   4840: iadd
    //   4841: iastore
    //   4842: aload #21
    //   4844: bipush #7
    //   4846: iaload
    //   4847: istore #23
    //   4849: aload #21
    //   4851: bipush #7
    //   4853: aload #21
    //   4855: bipush #6
    //   4857: iaload
    //   4858: iastore
    //   4859: aload #21
    //   4861: bipush #6
    //   4863: aload #21
    //   4865: iconst_5
    //   4866: iaload
    //   4867: iastore
    //   4868: aload #21
    //   4870: iconst_5
    //   4871: aload #21
    //   4873: iconst_4
    //   4874: iaload
    //   4875: iastore
    //   4876: aload #21
    //   4878: iconst_4
    //   4879: aload #21
    //   4881: iconst_3
    //   4882: iaload
    //   4883: iastore
    //   4884: aload #21
    //   4886: iconst_3
    //   4887: aload #21
    //   4889: iconst_2
    //   4890: iaload
    //   4891: iastore
    //   4892: aload #21
    //   4894: iconst_2
    //   4895: aload #21
    //   4897: iconst_1
    //   4898: iaload
    //   4899: iastore
    //   4900: aload #21
    //   4902: iconst_1
    //   4903: aload #21
    //   4905: iconst_0
    //   4906: iaload
    //   4907: iastore
    //   4908: aload #21
    //   4910: iconst_0
    //   4911: iload #23
    //   4913: iastore
    //   4914: iinc #22, 1
    //   4917: iload_2
    //   4918: ifne -> 4426
    //   4921: iconst_0
    //   4922: istore #22
    //   4924: iload #22
    //   4926: bipush #8
    //   4928: if_icmpge -> 4951
    //   4931: aload #9
    //   4933: iload #22
    //   4935: dup2
    //   4936: iaload
    //   4937: aload #21
    //   4939: iload #22
    //   4941: iaload
    //   4942: iadd
    //   4943: iastore
    //   4944: iinc #22, 1
    //   4947: iload_2
    //   4948: ifne -> 4924
    //   4951: iinc #14, 64
    //   4954: iinc #18, -64
    //   4957: iload_2
    //   4958: ifne -> 4347
    //   4961: iload #18
    //   4963: ifle -> 4999
    //   4966: iconst_0
    //   4967: istore #20
    //   4969: iload #20
    //   4971: iload #18
    //   4973: if_icmpge -> 4999
    //   4976: aload #10
    //   4978: iload #13
    //   4980: iload #20
    //   4982: iadd
    //   4983: aload #6
    //   4985: iload #14
    //   4987: iload #20
    //   4989: iadd
    //   4990: baload
    //   4991: bastore
    //   4992: iinc #20, 1
    //   4995: iload_2
    //   4996: ifne -> 4969
    //   4999: bipush #8
    //   5001: newarray byte
    //   5003: astore #20
    //   5005: aload #20
    //   5007: iconst_0
    //   5008: iload #15
    //   5010: bipush #24
    //   5012: iushr
    //   5013: i2b
    //   5014: bastore
    //   5015: aload #20
    //   5017: iconst_1
    //   5018: iload #15
    //   5020: bipush #16
    //   5022: iushr
    //   5023: i2b
    //   5024: bastore
    //   5025: aload #20
    //   5027: iconst_2
    //   5028: iload #15
    //   5030: bipush #8
    //   5032: iushr
    //   5033: i2b
    //   5034: bastore
    //   5035: aload #20
    //   5037: iconst_3
    //   5038: iload #15
    //   5040: i2b
    //   5041: bastore
    //   5042: aload #20
    //   5044: iconst_4
    //   5045: iload #16
    //   5047: bipush #24
    //   5049: iushr
    //   5050: i2b
    //   5051: bastore
    //   5052: aload #20
    //   5054: iconst_5
    //   5055: iload #16
    //   5057: bipush #16
    //   5059: iushr
    //   5060: i2b
    //   5061: bastore
    //   5062: aload #20
    //   5064: bipush #6
    //   5066: iload #16
    //   5068: bipush #8
    //   5070: iushr
    //   5071: i2b
    //   5072: bastore
    //   5073: aload #20
    //   5075: bipush #7
    //   5077: iload #16
    //   5079: i2b
    //   5080: bastore
    //   5081: bipush #8
    //   5083: istore #12
    //   5085: aload #8
    //   5087: iconst_0
    //   5088: iaload
    //   5089: bipush #63
    //   5091: iand
    //   5092: istore #13
    //   5094: bipush #64
    //   5096: iload #13
    //   5098: isub
    //   5099: istore #19
    //   5101: aload #8
    //   5103: iconst_0
    //   5104: dup2
    //   5105: iaload
    //   5106: iload #12
    //   5108: iadd
    //   5109: iastore
    //   5110: aload #8
    //   5112: iconst_0
    //   5113: dup2
    //   5114: iaload
    //   5115: iconst_m1
    //   5116: iand
    //   5117: iastore
    //   5118: aload #8
    //   5120: iconst_0
    //   5121: iaload
    //   5122: iload #12
    //   5124: if_icmpge -> 5142
    //   5127: aload #8
    //   5129: iconst_1
    //   5130: dup2
    //   5131: iaload
    //   5132: iconst_1
    //   5133: iadd
    //   5134: iastore
    //   5135: goto -> 5142
    //   5138: invokestatic a : (Ljava/lang/Throwable;)Ljava/lang/Throwable;
    //   5141: athrow
    //   5142: iload #13
    //   5144: ifle -> 5758
    //   5147: iload #12
    //   5149: iload #19
    //   5151: if_icmplt -> 5758
    //   5154: goto -> 5161
    //   5157: invokestatic a : (Ljava/lang/Throwable;)Ljava/lang/Throwable;
    //   5160: athrow
    //   5161: iconst_0
    //   5162: istore #21
    //   5164: iload #21
    //   5166: iload #19
    //   5168: if_icmpge -> 5191
    //   5171: aload #10
    //   5173: iload #13
    //   5175: iload #21
    //   5177: iadd
    //   5178: aload #20
    //   5180: iload #21
    //   5182: baload
    //   5183: bastore
    //   5184: iinc #21, 1
    //   5187: iload_2
    //   5188: ifne -> 5164
    //   5191: bipush #64
    //   5193: newarray int
    //   5195: astore #21
    //   5197: bipush #8
    //   5199: newarray int
    //   5201: astore #22
    //   5203: iconst_0
    //   5204: istore #23
    //   5206: iload #23
    //   5208: bipush #8
    //   5210: if_icmpge -> 5230
    //   5213: aload #22
    //   5215: iload #23
    //   5217: aload #9
    //   5219: iload #23
    //   5221: iaload
    //   5222: iastore
    //   5223: iinc #23, 1
    //   5226: iload_2
    //   5227: ifne -> 5206
    //   5230: iconst_0
    //   5231: istore #23
    //   5233: iload #23
    //   5235: bipush #64
    //   5237: if_icmpge -> 5728
    //   5240: iload #23
    //   5242: bipush #16
    //   5244: if_icmpge -> 5325
    //   5247: aload #21
    //   5249: iload #23
    //   5251: aload #10
    //   5253: iconst_4
    //   5254: iload #23
    //   5256: imul
    //   5257: baload
    //   5258: sipush #255
    //   5261: iand
    //   5262: bipush #24
    //   5264: ishl
    //   5265: aload #10
    //   5267: iconst_4
    //   5268: iload #23
    //   5270: imul
    //   5271: iconst_1
    //   5272: iadd
    //   5273: baload
    //   5274: sipush #255
    //   5277: iand
    //   5278: bipush #16
    //   5280: ishl
    //   5281: ior
    //   5282: aload #10
    //   5284: iconst_4
    //   5285: iload #23
    //   5287: imul
    //   5288: iconst_2
    //   5289: iadd
    //   5290: baload
    //   5291: sipush #255
    //   5294: iand
    //   5295: bipush #8
    //   5297: ishl
    //   5298: ior
    //   5299: aload #10
    //   5301: iconst_4
    //   5302: iload #23
    //   5304: imul
    //   5305: iconst_3
    //   5306: iadd
    //   5307: baload
    //   5308: sipush #255
    //   5311: iand
    //   5312: ior
    //   5313: iastore
    //   5314: iload_2
    //   5315: ifne -> 5468
    //   5318: goto -> 5325
    //   5321: invokestatic a : (Ljava/lang/Throwable;)Ljava/lang/Throwable;
    //   5324: athrow
    //   5325: aload #21
    //   5327: iload #23
    //   5329: aload #21
    //   5331: iload #23
    //   5333: iconst_2
    //   5334: isub
    //   5335: iaload
    //   5336: bipush #17
    //   5338: iushr
    //   5339: aload #21
    //   5341: iload #23
    //   5343: iconst_2
    //   5344: isub
    //   5345: iaload
    //   5346: bipush #15
    //   5348: ishl
    //   5349: ior
    //   5350: aload #21
    //   5352: iload #23
    //   5354: iconst_2
    //   5355: isub
    //   5356: iaload
    //   5357: bipush #19
    //   5359: iushr
    //   5360: aload #21
    //   5362: iload #23
    //   5364: iconst_2
    //   5365: isub
    //   5366: iaload
    //   5367: bipush #13
    //   5369: ishl
    //   5370: ior
    //   5371: ixor
    //   5372: aload #21
    //   5374: iload #23
    //   5376: iconst_2
    //   5377: isub
    //   5378: iaload
    //   5379: bipush #10
    //   5381: iushr
    //   5382: ixor
    //   5383: aload #21
    //   5385: iload #23
    //   5387: bipush #7
    //   5389: isub
    //   5390: iaload
    //   5391: iadd
    //   5392: aload #21
    //   5394: iload #23
    //   5396: bipush #15
    //   5398: isub
    //   5399: iaload
    //   5400: bipush #7
    //   5402: iushr
    //   5403: aload #21
    //   5405: iload #23
    //   5407: bipush #15
    //   5409: isub
    //   5410: iaload
    //   5411: bipush #25
    //   5413: ishl
    //   5414: ior
    //   5415: aload #21
    //   5417: iload #23
    //   5419: bipush #15
    //   5421: isub
    //   5422: iaload
    //   5423: bipush #18
    //   5425: iushr
    //   5426: aload #21
    //   5428: iload #23
    //   5430: bipush #15
    //   5432: isub
    //   5433: iaload
    //   5434: bipush #14
    //   5436: ishl
    //   5437: ior
    //   5438: ixor
    //   5439: aload #21
    //   5441: iload #23
    //   5443: bipush #15
    //   5445: isub
    //   5446: iaload
    //   5447: iconst_3
    //   5448: iushr
    //   5449: ixor
    //   5450: iadd
    //   5451: aload #21
    //   5453: iload #23
    //   5455: bipush #16
    //   5457: isub
    //   5458: iaload
    //   5459: iadd
    //   5460: iastore
    //   5461: goto -> 5468
    //   5464: invokestatic a : (Ljava/lang/Throwable;)Ljava/lang/Throwable;
    //   5467: athrow
    //   5468: aload #22
    //   5470: bipush #7
    //   5472: iaload
    //   5473: aload #22
    //   5475: iconst_4
    //   5476: iaload
    //   5477: bipush #6
    //   5479: iushr
    //   5480: aload #22
    //   5482: iconst_4
    //   5483: iaload
    //   5484: bipush #26
    //   5486: ishl
    //   5487: ior
    //   5488: aload #22
    //   5490: iconst_4
    //   5491: iaload
    //   5492: bipush #11
    //   5494: iushr
    //   5495: aload #22
    //   5497: iconst_4
    //   5498: iaload
    //   5499: bipush #21
    //   5501: ishl
    //   5502: ior
    //   5503: ixor
    //   5504: aload #22
    //   5506: iconst_4
    //   5507: iaload
    //   5508: bipush #25
    //   5510: iushr
    //   5511: aload #22
    //   5513: iconst_4
    //   5514: iaload
    //   5515: bipush #7
    //   5517: ishl
    //   5518: ior
    //   5519: ixor
    //   5520: iadd
    //   5521: aload #22
    //   5523: bipush #6
    //   5525: iaload
    //   5526: aload #22
    //   5528: iconst_4
    //   5529: iaload
    //   5530: aload #22
    //   5532: iconst_5
    //   5533: iaload
    //   5534: aload #22
    //   5536: bipush #6
    //   5538: iaload
    //   5539: ixor
    //   5540: iand
    //   5541: ixor
    //   5542: iadd
    //   5543: aload #7
    //   5545: iload #23
    //   5547: iaload
    //   5548: iadd
    //   5549: aload #21
    //   5551: iload #23
    //   5553: iaload
    //   5554: iadd
    //   5555: istore #24
    //   5557: aload #22
    //   5559: iconst_0
    //   5560: iaload
    //   5561: iconst_2
    //   5562: iushr
    //   5563: aload #22
    //   5565: iconst_0
    //   5566: iaload
    //   5567: bipush #30
    //   5569: ishl
    //   5570: ior
    //   5571: aload #22
    //   5573: iconst_0
    //   5574: iaload
    //   5575: bipush #13
    //   5577: iushr
    //   5578: aload #22
    //   5580: iconst_0
    //   5581: iaload
    //   5582: bipush #19
    //   5584: ishl
    //   5585: ior
    //   5586: ixor
    //   5587: aload #22
    //   5589: iconst_0
    //   5590: iaload
    //   5591: bipush #22
    //   5593: iushr
    //   5594: aload #22
    //   5596: iconst_0
    //   5597: iaload
    //   5598: bipush #10
    //   5600: ishl
    //   5601: ior
    //   5602: ixor
    //   5603: aload #22
    //   5605: iconst_0
    //   5606: iaload
    //   5607: aload #22
    //   5609: iconst_1
    //   5610: iaload
    //   5611: iand
    //   5612: aload #22
    //   5614: iconst_2
    //   5615: iaload
    //   5616: aload #22
    //   5618: iconst_0
    //   5619: iaload
    //   5620: aload #22
    //   5622: iconst_1
    //   5623: iaload
    //   5624: ior
    //   5625: iand
    //   5626: ior
    //   5627: iadd
    //   5628: istore #25
    //   5630: aload #22
    //   5632: iconst_3
    //   5633: dup2
    //   5634: iaload
    //   5635: iload #24
    //   5637: iadd
    //   5638: iastore
    //   5639: aload #22
    //   5641: bipush #7
    //   5643: iload #24
    //   5645: iload #25
    //   5647: iadd
    //   5648: iastore
    //   5649: aload #22
    //   5651: bipush #7
    //   5653: iaload
    //   5654: istore #24
    //   5656: aload #22
    //   5658: bipush #7
    //   5660: aload #22
    //   5662: bipush #6
    //   5664: iaload
    //   5665: iastore
    //   5666: aload #22
    //   5668: bipush #6
    //   5670: aload #22
    //   5672: iconst_5
    //   5673: iaload
    //   5674: iastore
    //   5675: aload #22
    //   5677: iconst_5
    //   5678: aload #22
    //   5680: iconst_4
    //   5681: iaload
    //   5682: iastore
    //   5683: aload #22
    //   5685: iconst_4
    //   5686: aload #22
    //   5688: iconst_3
    //   5689: iaload
    //   5690: iastore
    //   5691: aload #22
    //   5693: iconst_3
    //   5694: aload #22
    //   5696: iconst_2
    //   5697: iaload
    //   5698: iastore
    //   5699: aload #22
    //   5701: iconst_2
    //   5702: aload #22
    //   5704: iconst_1
    //   5705: iaload
    //   5706: iastore
    //   5707: aload #22
    //   5709: iconst_1
    //   5710: aload #22
    //   5712: iconst_0
    //   5713: iaload
    //   5714: iastore
    //   5715: aload #22
    //   5717: iconst_0
    //   5718: iload #24
    //   5720: iastore
    //   5721: iinc #23, 1
    //   5724: iload_2
    //   5725: ifne -> 5233
    //   5728: iconst_0
    //   5729: istore #23
    //   5731: iload #23
    //   5733: bipush #8
    //   5735: if_icmpge -> 5758
    //   5738: aload #9
    //   5740: iload #23
    //   5742: dup2
    //   5743: iaload
    //   5744: aload #22
    //   5746: iload #23
    //   5748: iaload
    //   5749: iadd
    //   5750: iastore
    //   5751: iinc #23, 1
    //   5754: iload_2
    //   5755: ifne -> 5731
    //   5758: bipush #32
    //   5760: newarray byte
    //   5762: astore #5
    //   5764: aload #5
    //   5766: iconst_0
    //   5767: aload #9
    //   5769: iconst_0
    //   5770: iaload
    //   5771: bipush #24
    //   5773: iushr
    //   5774: i2b
    //   5775: bastore
    //   5776: aload #5
    //   5778: iconst_1
    //   5779: aload #9
    //   5781: iconst_0
    //   5782: iaload
    //   5783: bipush #16
    //   5785: iushr
    //   5786: i2b
    //   5787: bastore
    //   5788: aload #5
    //   5790: iconst_2
    //   5791: aload #9
    //   5793: iconst_0
    //   5794: iaload
    //   5795: bipush #8
    //   5797: iushr
    //   5798: i2b
    //   5799: bastore
    //   5800: aload #5
    //   5802: iconst_3
    //   5803: aload #9
    //   5805: iconst_0
    //   5806: iaload
    //   5807: i2b
    //   5808: bastore
    //   5809: aload #5
    //   5811: iconst_4
    //   5812: aload #9
    //   5814: iconst_1
    //   5815: iaload
    //   5816: bipush #24
    //   5818: iushr
    //   5819: i2b
    //   5820: bastore
    //   5821: aload #5
    //   5823: iconst_5
    //   5824: aload #9
    //   5826: iconst_1
    //   5827: iaload
    //   5828: bipush #16
    //   5830: iushr
    //   5831: i2b
    //   5832: bastore
    //   5833: aload #5
    //   5835: bipush #6
    //   5837: aload #9
    //   5839: iconst_1
    //   5840: iaload
    //   5841: bipush #8
    //   5843: iushr
    //   5844: i2b
    //   5845: bastore
    //   5846: aload #5
    //   5848: bipush #7
    //   5850: aload #9
    //   5852: iconst_1
    //   5853: iaload
    //   5854: i2b
    //   5855: bastore
    //   5856: aload #5
    //   5858: bipush #8
    //   5860: aload #9
    //   5862: iconst_2
    //   5863: iaload
    //   5864: bipush #24
    //   5866: iushr
    //   5867: i2b
    //   5868: bastore
    //   5869: aload #5
    //   5871: bipush #9
    //   5873: aload #9
    //   5875: iconst_2
    //   5876: iaload
    //   5877: bipush #16
    //   5879: iushr
    //   5880: i2b
    //   5881: bastore
    //   5882: aload #5
    //   5884: bipush #10
    //   5886: aload #9
    //   5888: iconst_2
    //   5889: iaload
    //   5890: bipush #8
    //   5892: iushr
    //   5893: i2b
    //   5894: bastore
    //   5895: aload #5
    //   5897: bipush #11
    //   5899: aload #9
    //   5901: iconst_2
    //   5902: iaload
    //   5903: i2b
    //   5904: bastore
    //   5905: aload #5
    //   5907: bipush #12
    //   5909: aload #9
    //   5911: iconst_3
    //   5912: iaload
    //   5913: bipush #24
    //   5915: iushr
    //   5916: i2b
    //   5917: bastore
    //   5918: aload #5
    //   5920: bipush #13
    //   5922: aload #9
    //   5924: iconst_3
    //   5925: iaload
    //   5926: bipush #16
    //   5928: iushr
    //   5929: i2b
    //   5930: bastore
    //   5931: aload #5
    //   5933: bipush #14
    //   5935: aload #9
    //   5937: iconst_3
    //   5938: iaload
    //   5939: bipush #8
    //   5941: iushr
    //   5942: i2b
    //   5943: bastore
    //   5944: aload #5
    //   5946: bipush #15
    //   5948: aload #9
    //   5950: iconst_3
    //   5951: iaload
    //   5952: i2b
    //   5953: bastore
    //   5954: aload #5
    //   5956: bipush #16
    //   5958: aload #9
    //   5960: iconst_4
    //   5961: iaload
    //   5962: bipush #24
    //   5964: iushr
    //   5965: i2b
    //   5966: bastore
    //   5967: aload #5
    //   5969: bipush #17
    //   5971: aload #9
    //   5973: iconst_4
    //   5974: iaload
    //   5975: bipush #16
    //   5977: iushr
    //   5978: i2b
    //   5979: bastore
    //   5980: aload #5
    //   5982: bipush #18
    //   5984: aload #9
    //   5986: iconst_4
    //   5987: iaload
    //   5988: bipush #8
    //   5990: iushr
    //   5991: i2b
    //   5992: bastore
    //   5993: aload #5
    //   5995: bipush #19
    //   5997: aload #9
    //   5999: iconst_4
    //   6000: iaload
    //   6001: i2b
    //   6002: bastore
    //   6003: aload #5
    //   6005: bipush #20
    //   6007: aload #9
    //   6009: iconst_5
    //   6010: iaload
    //   6011: bipush #24
    //   6013: iushr
    //   6014: i2b
    //   6015: bastore
    //   6016: aload #5
    //   6018: bipush #21
    //   6020: aload #9
    //   6022: iconst_5
    //   6023: iaload
    //   6024: bipush #16
    //   6026: iushr
    //   6027: i2b
    //   6028: bastore
    //   6029: aload #5
    //   6031: bipush #22
    //   6033: aload #9
    //   6035: iconst_5
    //   6036: iaload
    //   6037: bipush #8
    //   6039: iushr
    //   6040: i2b
    //   6041: bastore
    //   6042: aload #5
    //   6044: bipush #23
    //   6046: aload #9
    //   6048: iconst_5
    //   6049: iaload
    //   6050: i2b
    //   6051: bastore
    //   6052: aload #5
    //   6054: bipush #24
    //   6056: aload #9
    //   6058: bipush #6
    //   6060: iaload
    //   6061: bipush #24
    //   6063: iushr
    //   6064: i2b
    //   6065: bastore
    //   6066: aload #5
    //   6068: bipush #25
    //   6070: aload #9
    //   6072: bipush #6
    //   6074: iaload
    //   6075: bipush #16
    //   6077: iushr
    //   6078: i2b
    //   6079: bastore
    //   6080: aload #5
    //   6082: bipush #26
    //   6084: aload #9
    //   6086: bipush #6
    //   6088: iaload
    //   6089: bipush #8
    //   6091: iushr
    //   6092: i2b
    //   6093: bastore
    //   6094: aload #5
    //   6096: bipush #27
    //   6098: aload #9
    //   6100: bipush #6
    //   6102: iaload
    //   6103: i2b
    //   6104: bastore
    //   6105: aload #5
    //   6107: bipush #28
    //   6109: aload #9
    //   6111: bipush #7
    //   6113: iaload
    //   6114: bipush #24
    //   6116: iushr
    //   6117: i2b
    //   6118: bastore
    //   6119: aload #5
    //   6121: bipush #29
    //   6123: aload #9
    //   6125: bipush #7
    //   6127: iaload
    //   6128: bipush #16
    //   6130: iushr
    //   6131: i2b
    //   6132: bastore
    //   6133: aload #5
    //   6135: bipush #30
    //   6137: aload #9
    //   6139: bipush #7
    //   6141: iaload
    //   6142: bipush #8
    //   6144: iushr
    //   6145: i2b
    //   6146: bastore
    //   6147: aload #5
    //   6149: bipush #31
    //   6151: aload #9
    //   6153: bipush #7
    //   6155: iaload
    //   6156: i2b
    //   6157: bastore
    //   6158: getstatic burp/Zsgl.ZG : Ljava/lang/String;
    //   6161: getstatic burp/Zl_k.ZH : Ljava/lang/Object;
    //   6164: checkcast java/math/BigInteger
    //   6167: invokevirtual intValue : ()I
    //   6170: bipush #32
    //   6172: irem
    //   6173: invokestatic abs : (I)I
    //   6176: invokevirtual charAt : (I)C
    //   6179: getstatic burp/Zer.Zp : Ljava/lang/String;
    //   6182: getstatic burp/Zr8h.ZH : Ljava/lang/Object;
    //   6185: checkcast java/math/BigInteger
    //   6188: invokevirtual intValue : ()I
    //   6191: bipush #32
    //   6193: irem
    //   6194: invokestatic abs : (I)I
    //   6197: invokevirtual charAt : (I)C
    //   6200: if_icmpgt -> 6307
    //   6203: getstatic burp/Zl_k.Zw : Ljava/lang/String;
    //   6206: getstatic burp/Zedz.Za : Ljava/lang/Object;
    //   6209: checkcast java/math/BigInteger
    //   6212: invokevirtual intValue : ()I
    //   6215: bipush #32
    //   6217: irem
    //   6218: invokestatic abs : (I)I
    //   6221: invokevirtual charAt : (I)C
    //   6224: getstatic burp/Zbo7.ZZ : Ljava/lang/String;
    //   6227: getstatic burp/Zllw.ZW : Ljava/lang/Object;
    //   6230: checkcast java/math/BigInteger
    //   6233: invokevirtual intValue : ()I
    //   6236: bipush #32
    //   6238: irem
    //   6239: invokestatic abs : (I)I
    //   6242: invokevirtual charAt : (I)C
    //   6245: if_icmpgt -> 6307
    //   6248: goto -> 6255
    //   6251: invokestatic a : (Ljava/lang/Throwable;)Ljava/lang/Throwable;
    //   6254: athrow
    //   6255: getstatic burp/Zkig.ZE : Ljava/lang/String;
    //   6258: getstatic burp/Ze3d.Ze : Ljava/lang/Object;
    //   6261: checkcast java/math/BigInteger
    //   6264: invokevirtual intValue : ()I
    //   6267: bipush #32
    //   6269: irem
    //   6270: invokestatic abs : (I)I
    //   6273: invokevirtual charAt : (I)C
    //   6276: getstatic burp/Zedz.Zh : Ljava/lang/String;
    //   6279: getstatic burp/Zzip.ZW : Ljava/lang/Object;
    //   6282: checkcast java/math/BigInteger
    //   6285: invokevirtual intValue : ()I
    //   6288: bipush #32
    //   6290: irem
    //   6291: invokestatic abs : (I)I
    //   6294: invokevirtual charAt : (I)C
    //   6297: if_icmple -> 6315
    //   6300: goto -> 6307
    //   6303: invokestatic a : (Ljava/lang/Throwable;)Ljava/lang/Throwable;
    //   6306: athrow
    //   6307: iconst_1
    //   6308: goto -> 6316
    //   6311: invokestatic a : (Ljava/lang/Throwable;)Ljava/lang/Throwable;
    //   6314: athrow
    //   6315: iconst_0
    //   6316: ireturn
    //   6317: astore_3
    //   6318: new java/lang/Exception
    //   6321: dup
    //   6322: aload_3
    //   6323: invokevirtual getMessage : ()Ljava/lang/String;
    //   6326: invokespecial <init> : (Ljava/lang/String;)V
    //   6329: athrow
    // Exception table:
    //   from	to	target	type
    //   4	6316	6317	java/lang/Throwable
    //   22	198	201	java/lang/Throwable
    //   168	235	238	java/lang/Throwable
    //   205	272	275	java/lang/Throwable
    //   242	309	312	java/lang/Throwable
    //   279	346	349	java/lang/Throwable
    //   316	383	386	java/lang/Throwable
    //   353	420	423	java/lang/Throwable
    //   390	457	460	java/lang/Throwable
    //   427	494	497	java/lang/Throwable
    //   464	531	534	java/lang/Throwable
    //   501	568	571	java/lang/Throwable
    //   538	605	608	java/lang/Throwable
    //   575	642	645	java/lang/Throwable
    //   612	679	682	java/lang/Throwable
    //   649	716	719	java/lang/Throwable
    //   686	753	756	java/lang/Throwable
    //   723	790	793	java/lang/Throwable
    //   760	827	830	java/lang/Throwable
    //   797	864	867	java/lang/Throwable
    //   834	901	904	java/lang/Throwable
    //   871	938	941	java/lang/Throwable
    //   908	975	978	java/lang/Throwable
    //   945	1012	1015	java/lang/Throwable
    //   982	1049	1052	java/lang/Throwable
    //   1019	1086	1089	java/lang/Throwable
    //   1056	1123	1126	java/lang/Throwable
    //   1093	1160	1163	java/lang/Throwable
    //   1130	1197	1200	java/lang/Throwable
    //   1167	1234	1237	java/lang/Throwable
    //   1204	1271	1274	java/lang/Throwable
    //   1241	1308	1311	java/lang/Throwable
    //   1278	1341	1344	java/lang/Throwable
    //   1443	1457	1457	java/lang/Throwable
    //   1468	1481	1484	java/lang/Throwable
    //   1473	1496	1499	java/lang/Throwable
    //   1488	1514	1517	java/lang/Throwable
    //   1503	1544	1547	java/lang/Throwable
    //   1610	1637	1640	java/lang/Throwable
    //   1627	1658	1661	java/lang/Throwable
    //   1644	1688	1691	java/lang/Throwable
    //   1665	1699	1699	java/lang/Throwable
    //   1710	1726	1729	java/lang/Throwable
    //   1806	1820	1820	java/lang/Throwable
    //   1831	1844	1847	java/lang/Throwable
    //   1836	1859	1862	java/lang/Throwable
    //   1851	1877	1880	java/lang/Throwable
    //   1866	1907	1910	java/lang/Throwable
    //   1973	2000	2003	java/lang/Throwable
    //   1990	2021	2024	java/lang/Throwable
    //   2007	2051	2054	java/lang/Throwable
    //   2028	2062	2062	java/lang/Throwable
    //   2073	2089	2092	java/lang/Throwable
    //   2899	2933	2936	java/lang/Throwable
    //   3029	3107	3110	java/lang/Throwable
    //   3036	3250	3253	java/lang/Throwable
    //   3628	3643	3643	java/lang/Throwable
    //   3670	3704	3707	java/lang/Throwable
    //   3714	3726	3729	java/lang/Throwable
    //   3812	3890	3893	java/lang/Throwable
    //   3819	4033	4036	java/lang/Throwable
    //   4433	4511	4514	java/lang/Throwable
    //   4440	4654	4657	java/lang/Throwable
    //   5101	5135	5138	java/lang/Throwable
    //   5142	5154	5157	java/lang/Throwable
    //   5240	5318	5321	java/lang/Throwable
    //   5247	5461	5464	java/lang/Throwable
    //   5764	6248	6251	java/lang/Throwable
    //   6203	6300	6303	java/lang/Throwable
    //   6255	6311	6311	java/lang/Throwable
  }
  
  static void ZS(Object paramObject) {
    Zter.ZE = a(-5243, -5431);
    Zter.Zc = new BigInteger(a(-5245, 31046));
    boolean bool = Zt2e.ZN();
    try {
      try {
        if (Zxzd.ZM.charAt(Math.abs(((BigInteger)Zgss.Zl).intValue() % 32)) <= Zxzd.ZM.charAt(Math.abs(((BigInteger)Zxzd.ZD).intValue() % 32))) {
          try {
            Zkig.ZE(Class.forName(a(-5247, -23870)));
            if (!bool)
              Zzc7.Zu(Class.forName(a(-5246, -1238))); 
          } catch (Throwable throwable) {
            throw a(null);
          } 
          return;
        } 
      } catch (Throwable throwable) {
        throw a(null);
      } 
      Zzc7.Zu(Class.forName(a(-5246, -1238)));
    } catch (Throwable throwable) {}
  }
  
  static void ZT(Object[] paramArrayOfObject, Object paramObject) throws Throwable {}
  
  static {
    // Byte code:
    //   0: bipush #11
    //   2: anewarray java/lang/String
    //   5: astore #5
    //   7: iconst_0
    //   8: istore_3
    //   9: ldc 's1\\t,#Ln =:/sRU by7}CiFy(MRQN]skID(m!\=u\\tXnk+jmZ&n,f:y,c(\\tL]@\\tmT8/\\t|\\t55E'
    //   11: dup
    //   12: astore_2
    //   13: invokevirtual length : ()I
    //   16: istore #4
    //   18: iconst_4
    //   19: istore_1
    //   20: iconst_m1
    //   21: istore_0
    //   22: bipush #72
    //   24: iinc #0, 1
    //   27: aload_2
    //   28: iload_0
    //   29: dup
    //   30: iload_1
    //   31: iadd
    //   32: invokevirtual substring : (II)Ljava/lang/String;
    //   35: iconst_m1
    //   36: goto -> 142
    //   39: aload #5
    //   41: swap
    //   42: iload_3
    //   43: iinc #3, 1
    //   46: swap
    //   47: aastore
    //   48: iload_0
    //   49: iload_1
    //   50: iadd
    //   51: dup
    //   52: istore_0
    //   53: iload #4
    //   55: if_icmpge -> 67
    //   58: aload_2
    //   59: iload_0
    //   60: invokevirtual charAt : (I)C
    //   63: istore_1
    //   64: goto -> 22
    //   67: ldc 'Ym\\r5'
    //   69: dup
    //   70: astore_2
    //   71: invokevirtual length : ()I
    //   74: istore #4
    //   76: bipush #9
    //   78: istore_1
    //   79: iconst_m1
    //   80: istore_0
    //   81: bipush #49
    //   83: iinc #0, 1
    //   86: aload_2
    //   87: iload_0
    //   88: dup
    //   89: iload_1
    //   90: iadd
    //   91: invokevirtual substring : (II)Ljava/lang/String;
    //   94: iconst_0
    //   95: goto -> 142
    //   98: aload #5
    //   100: swap
    //   101: iload_3
    //   102: iinc #3, 1
    //   105: swap
    //   106: aastore
    //   107: iload_0
    //   108: iload_1
    //   109: iadd
    //   110: dup
    //   111: istore_0
    //   112: iload #4
    //   114: if_icmpge -> 126
    //   117: aload_2
    //   118: iload_0
    //   119: invokevirtual charAt : (I)C
    //   122: istore_1
    //   123: goto -> 81
    //   126: aload #5
    //   128: putstatic burp/Zt3l.a : [Ljava/lang/String;
    //   131: bipush #11
    //   133: anewarray java/lang/String
    //   136: putstatic burp/Zt3l.b : [Ljava/lang/String;
    //   139: goto -> 300
    //   142: dup_x2
    //   143: pop
    //   144: invokevirtual toCharArray : ()[C
    //   147: dup_x1
    //   148: arraylength
    //   149: dup_x2
    //   150: pop
    //   151: iconst_0
    //   152: istore #6
    //   154: dup2_x1
    //   155: pop2
    //   156: dup_x2
    //   157: iconst_1
    //   158: if_icmpgt -> 260
    //   161: dup2
    //   162: swap
    //   163: iload #6
    //   165: dup2_x1
    //   166: caload
    //   167: swap
    //   168: iload #6
    //   170: bipush #7
    //   172: irem
    //   173: tableswitch default -> 242, 0 -> 212, 1 -> 217, 2 -> 222, 3 -> 227, 4 -> 232, 5 -> 237
    //   212: bipush #83
    //   214: goto -> 244
    //   217: bipush #75
    //   219: goto -> 244
    //   222: bipush #40
    //   224: goto -> 244
    //   227: bipush #74
    //   229: goto -> 244
    //   232: bipush #92
    //   234: goto -> 244
    //   237: bipush #39
    //   239: goto -> 244
    //   242: bipush #110
    //   244: ixor
    //   245: ixor
    //   246: i2c
    //   247: castore
    //   248: iinc #6, 1
    //   251: dup
    //   252: ifne -> 260
    //   255: dup2
    //   256: dup_x1
    //   257: goto -> 165
    //   260: dup2_x1
    //   261: pop2
    //   262: dup_x2
    //   263: iload #6
    //   265: if_icmpgt -> 161
    //   268: pop
    //   269: new java/lang/String
    //   272: dup_x1
    //   273: swap
    //   274: invokespecial <init> : ([C)V
    //   277: invokevirtual intern : ()Ljava/lang/String;
    //   280: swap
    //   281: pop
    //   282: swap
    //   283: tableswitch default -> 39, 0 -> 98
    //   300: new java/math/BigInteger
    //   303: dup
    //   304: iconst_1
    //   305: bipush #32
    //   307: newarray byte
    //   309: dup
    //   310: iconst_0
    //   311: bipush #122
    //   313: bastore
    //   314: dup
    //   315: iconst_1
    //   316: bipush #-121
    //   318: bastore
    //   319: dup
    //   320: iconst_2
    //   321: bipush #32
    //   323: bastore
    //   324: dup
    //   325: iconst_3
    //   326: iconst_0
    //   327: bastore
    //   328: dup
    //   329: iconst_4
    //   330: bipush #99
    //   332: bastore
    //   333: dup
    //   334: iconst_5
    //   335: bipush #96
    //   337: bastore
    //   338: dup
    //   339: bipush #6
    //   341: bipush #-4
    //   343: bastore
    //   344: dup
    //   345: bipush #7
    //   347: bipush #-7
    //   349: bastore
    //   350: dup
    //   351: bipush #8
    //   353: bipush #93
    //   355: bastore
    //   356: dup
    //   357: bipush #9
    //   359: bipush #-47
    //   361: bastore
    //   362: dup
    //   363: bipush #10
    //   365: bipush #-76
    //   367: bastore
    //   368: dup
    //   369: bipush #11
    //   371: bipush #66
    //   373: bastore
    //   374: dup
    //   375: bipush #12
    //   377: bipush #122
    //   379: bastore
    //   380: dup
    //   381: bipush #13
    //   383: bipush #-117
    //   385: bastore
    //   386: dup
    //   387: bipush #14
    //   389: bipush #31
    //   391: bastore
    //   392: dup
    //   393: bipush #15
    //   395: bipush #-52
    //   397: bastore
    //   398: dup
    //   399: bipush #16
    //   401: bipush #-9
    //   403: bastore
    //   404: dup
    //   405: bipush #17
    //   407: bipush #103
    //   409: bastore
    //   410: dup
    //   411: bipush #18
    //   413: bipush #43
    //   415: bastore
    //   416: dup
    //   417: bipush #19
    //   419: bipush #-93
    //   421: bastore
    //   422: dup
    //   423: bipush #20
    //   425: bipush #38
    //   427: bastore
    //   428: dup
    //   429: bipush #21
    //   431: bipush #79
    //   433: bastore
    //   434: dup
    //   435: bipush #22
    //   437: bipush #17
    //   439: bastore
    //   440: dup
    //   441: bipush #23
    //   443: bipush #33
    //   445: bastore
    //   446: dup
    //   447: bipush #24
    //   449: bipush #-121
    //   451: bastore
    //   452: dup
    //   453: bipush #25
    //   455: bipush #-120
    //   457: bastore
    //   458: dup
    //   459: bipush #26
    //   461: bipush #105
    //   463: bastore
    //   464: dup
    //   465: bipush #27
    //   467: iconst_1
    //   468: bastore
    //   469: dup
    //   470: bipush #28
    //   472: bipush #118
    //   474: bastore
    //   475: dup
    //   476: bipush #29
    //   478: bipush #44
    //   480: bastore
    //   481: dup
    //   482: bipush #30
    //   484: bipush #43
    //   486: bastore
    //   487: dup
    //   488: bipush #31
    //   490: bipush #-112
    //   492: bastore
    //   493: invokespecial <init> : (I[B)V
    //   496: putstatic burp/Zt3l.Zq : Ljava/lang/Object;
    //   499: sipush #-5244
    //   502: sipush #-7966
    //   505: invokestatic a : (II)Ljava/lang/String;
    //   508: putstatic burp/Zt3l.Zi : Ljava/lang/String;
    //   511: return
  }
  
  private static Throwable a(Throwable paramThrowable) {
    return paramThrowable;
  }
  
  private static String a(int paramInt1, int paramInt2) {
    int i = (paramInt1 ^ 0xFFFFEB87) & 0xFFFF;
    if (b[i] == null) {
      char[] arrayOfChar = a[i].toCharArray();
      switch (arrayOfChar[0] & 0xFF) {
        case 0:
        
        case 1:
        
        case 2:
        
        case 3:
        
        case 4:
        
        case 5:
        
        case 6:
        
        case 7:
        
        case 8:
        
        case 9:
        
        case 10:
        
        case 11:
        
        case 12:
        
        case 13:
        
        case 14:
        
        case 15:
        
        case 16:
        
        case 17:
        
        case 18:
        
        case 19:
        
        case 20:
        
        case 21:
        
        case 22:
        
        case 23:
        
        case 24:
        
        case 25:
        
        case 26:
        
        case 27:
        
        case 28:
        
        case 29:
        
        case 30:
        
        case 31:
        
        case 32:
        
        case 33:
        
        case 34:
        
        case 35:
        
        case 36:
        
        case 37:
        
        case 38:
        
        case 39:
        
        case 40:
        
        case 41:
        
        case 42:
        
        case 43:
        
        case 44:
        
        case 45:
        
        case 46:
        
        case 47:
        
        case 48:
        
        case 49:
        
        case 50:
        
        case 51:
        
        case 52:
        
        case 53:
        
        case 54:
        
        case 55:
        
        case 56:
        
        case 57:
        
        case 58:
        
        case 59:
        
        case 60:
        
        case 61:
        
        case 62:
        
        case 63:
        
        case 64:
        
        case 65:
        
        case 66:
        
        case 67:
        
        case 68:
        
        case 69:
        
        case 70:
        
        case 71:
        
        case 72:
        
        case 73:
        
        case 74:
        
        case 75:
        
        case 76:
        
        case 77:
        
        case 78:
        
        case 79:
        
        case 80:
        
        case 81:
        
        case 82:
        
        case 83:
        
        case 84:
        
        case 85:
        
        case 86:
        
        case 87:
        
        case 88:
        
        case 89:
        
        case 90:
        
        case 91:
        
        case 92:
        
        case 93:
        
        case 94:
        
        case 95:
        
        case 96:
        
        case 97:
        
        case 98:
        
        case 99:
        
        case 100:
        
        case 101:
        
        case 102:
        
        case 103:
        
        case 104:
        
        case 105:
        
        case 106:
        
        case 107:
        
        case 108:
        
        case 109:
        
        case 110:
        
        case 111:
        
        case 112:
        
        case 113:
        
        case 114:
        
        case 115:
        
        case 116:
        
        case 117:
        
        case 118:
        
        case 119:
        
        case 120:
        
        case 121:
        
        case 122:
        
        case 123:
        
        case 124:
        
        case 125:
        
        case 126:
        
        case 127:
        
        case 128:
        
        case 129:
        
        case 130:
        
        case 131:
        
        case 132:
        
        case 133:
        
        case 134:
        
        case 135:
        
        case 136:
        
        case 137:
        
        case 138:
        
        case 139:
        
        case 140:
        
        case 141:
        
        case 142:
        
        case 143:
        
        case 144:
        
        case 145:
        
        case 146:
        
        case 147:
        
        case 148:
        
        case 149:
        
        case 150:
        
        case 151:
        
        case 152:
        
        case 153:
        
        case 154:
        
        case 155:
        
        case 156:
        
        case 157:
        
        case 158:
        
        case 159:
        
        case 160:
        
        case 161:
        
        case 162:
        
        case 163:
        
        case 164:
        
        case 165:
        
        case 166:
        
        case 167:
        
        case 168:
        
        case 169:
        
        case 170:
        
        case 171:
        
        case 172:
        
        case 173:
        
        case 174:
        
        case 175:
        
        case 176:
        
        case 177:
        
        case 178:
        
        case 179:
        
        case 180:
        
        case 181:
        
        case 182:
        
        case 183:
        
        case 184:
        
        case 185:
        
        case 186:
        
        case 187:
        
        case 188:
        
        case 189:
        
        case 190:
        
        case 191:
        
        case 192:
        
        case 193:
        
        case 194:
        
        case 195:
        
        case 196:
        
        case 197:
        
        case 198:
        
        case 199:
        
        case 200:
        
        case 201:
        
        case 202:
        
        case 203:
        
        case 204:
        
        case 205:
        
        case 206:
        
        case 207:
        
        case 208:
        
        case 209:
        
        case 210:
        
        case 211:
        
        case 212:
        
        case 213:
        
        case 214:
        
        case 215:
        
        case 216:
        
        case 217:
        
        case 218:
        
        case 219:
        
        case 220:
        
        case 221:
        
        case 222:
        
        case 223:
        
        case 224:
        
        case 225:
        
        case 226:
        
        case 227:
        
        case 228:
        
        case 229:
        
        case 230:
        
        case 231:
        
        case 232:
        
        case 233:
        
        case 234:
        
        case 235:
        
        case 236:
        
        case 237:
        
        case 238:
        
        case 239:
        
        case 240:
        
        case 241:
        
        case 242:
        
        case 243:
        
        case 244:
        
        case 245:
        
        case 246:
        
        case 247:
        
        case 248:
        
        case 249:
        
        case 250:
        
        case 251:
        
        case 252:
        
        case 253:
        
        case 254:
        
        default:
          break;
      } 
      byte b1 = 48;
      int j = (paramInt2 & 0xFF) - b1;
      if (j < 0)
        j += 256; 
      int k = ((paramInt2 & 0xFFFF) >>> 8) - b1;
      if (k < 0)
        k += 256; 
      for (byte b2 = 0; b2 < arrayOfChar.length; b2++) {
        int m = b2 % 2;
        if (m == 0) {
          arrayOfChar[b2] = (char)(arrayOfChar[b2] ^ j);
          j = ((j >>> 3 | j << 5) ^ arrayOfChar[b2]) & 0xFF;
        } else {
          arrayOfChar[b2] = (char)(arrayOfChar[b2] ^ k);
          k = ((k >>> 3 | k << 5) ^ arrayOfChar[b2]) & 0xFF;
        } 
      } 
      b[i] = (new String(arrayOfChar)).intern();
    } 
    return b[i];
  }
}


/* Location:              C:\Program Files\BurpSuitePro\burpsuite_pro.jar!\burp\Zt3l.class
 * Java compiler version: 21 (65.0)
 * JD-Core Version:       1.1.3
 */