package burp;

import java.math.BigInteger;

class Zt4g extends ClassLoader {
  static Object Zv;
  
  static String Zj;
  
  private static final String[] a;
  
  private static final String[] b;
  
  static void ZG(Object[] paramArrayOfObject, Object paramObject) throws Throwable {}
  
  static void Zz(Object paramObject) {
    Zj = a(1793, 20495);
    Zv = new BigInteger(a(1799, -17794));
    boolean bool = Zt2e.ZK();
    try {
      try {
        if (Zl2q.ZI.charAt(Math.abs(((BigInteger)Zxzd.ZD).intValue() % 32)) <= Zkfz.Zs.charAt(Math.abs(((BigInteger)Zter.Zc).intValue() % 32))) {
          try {
            Zrva.ZO(Class.forName(a(1822, 2116)));
            if (bool)
              Zg7z.ZW(Class.forName(a(1821, 13646))); 
          } catch (Throwable throwable) {
            throw a(null);
          } 
          return;
        } 
      } catch (Throwable throwable) {
        throw a(null);
      } 
      Zg7z.ZW(Class.forName(a(1821, 13646)));
    } catch (Throwable throwable) {}
  }
  
  static boolean ZY(Object[] paramArrayOfObject, Object paramObject) throws Throwable {
    // Byte code:
    //   0: invokestatic ZN : ()Z
    //   3: istore_2
    //   4: getstatic burp/Zxwl.Ze : Ljava/lang/Object;
    //   7: checkcast java/math/BigInteger
    //   10: invokevirtual toByteArray : ()[B
    //   13: astore_3
    //   14: bipush #32
    //   16: newarray int
    //   18: dup
    //   19: iconst_0
    //   20: ldc 943331329
    //   22: iastore
    //   23: dup
    //   24: iconst_1
    //   25: ldc 170788368
    //   27: iastore
    //   28: dup
    //   29: iconst_2
    //   30: ldc 1008414755
    //   32: iastore
    //   33: dup
    //   34: iconst_3
    //   35: ldc 187049985
    //   37: iastore
    //   38: dup
    //   39: iconst_4
    //   40: ldc 1010368540
    //   42: iastore
    //   43: dup
    //   44: iconst_5
    //   45: ldc 220604441
    //   47: iastore
    //   48: dup
    //   49: bipush #6
    //   51: ldc 940377620
    //   53: iastore
    //   54: dup
    //   55: bipush #7
    //   57: ldc 255209728
    //   59: iastore
    //   60: dup
    //   61: bipush #8
    //   63: ldc 689771012
    //   65: iastore
    //   66: dup
    //   67: bipush #9
    //   69: ldc 221709344
    //   71: iastore
    //   72: dup
    //   73: bipush #10
    //   75: ldc 957157408
    //   77: iastore
    //   78: dup
    //   79: bipush #11
    //   81: ldc 892536332
    //   83: iastore
    //   84: dup
    //   85: bipush #12
    //   87: ldc 722417666
    //   89: iastore
    //   90: dup
    //   91: bipush #13
    //   93: ldc 1026621720
    //   95: iastore
    //   96: dup
    //   97: bipush #14
    //   99: ldc 655302664
    //   101: iastore
    //   102: dup
    //   103: bipush #15
    //   105: ldc 890966315
    //   107: iastore
    //   108: dup
    //   109: bipush #16
    //   111: ldc 187632156
    //   113: iastore
    //   114: dup
    //   115: bipush #17
    //   117: ldc 874189824
    //   119: iastore
    //   120: dup
    //   121: bipush #18
    //   123: ldc 254150144
    //   125: iastore
    //   126: dup
    //   127: bipush #19
    //   129: ldc 924386310
    //   131: iastore
    //   132: dup
    //   133: bipush #20
    //   135: ldc 121057538
    //   137: iastore
    //   138: dup
    //   139: bipush #21
    //   141: ldc 840500228
    //   143: iastore
    //   144: dup
    //   145: bipush #22
    //   147: ldc 389160971
    //   149: iastore
    //   150: dup
    //   151: bipush #23
    //   153: ldc 907870729
    //   155: iastore
    //   156: dup
    //   157: bipush #24
    //   159: ldc 389426184
    //   161: iastore
    //   162: dup
    //   163: bipush #25
    //   165: ldc 973875457
    //   167: iastore
    //   168: dup
    //   169: bipush #26
    //   171: ldc 372376604
    //   173: iastore
    //   174: dup
    //   175: bipush #27
    //   177: ldc 707731490
    //   179: iastore
    //   180: dup
    //   181: bipush #28
    //   183: ldc 1043334948
    //   185: iastore
    //   186: dup
    //   187: bipush #29
    //   189: ldc 439222784
    //   191: iastore
    //   192: dup
    //   193: bipush #30
    //   195: ldc 876216579
    //   197: iastore
    //   198: dup
    //   199: bipush #31
    //   201: ldc 455999525
    //   203: iastore
    //   204: astore #5
    //   206: bipush #8
    //   208: aload_3
    //   209: arraylength
    //   210: bipush #8
    //   212: irem
    //   213: isub
    //   214: istore #6
    //   216: aload_3
    //   217: arraylength
    //   218: iload #6
    //   220: iadd
    //   221: newarray byte
    //   223: astore #7
    //   225: iconst_0
    //   226: istore #8
    //   228: iload #8
    //   230: aload_3
    //   231: arraylength
    //   232: if_icmpge -> 251
    //   235: aload #7
    //   237: iload #8
    //   239: aload_3
    //   240: iload #8
    //   242: baload
    //   243: bastore
    //   244: iinc #8, 1
    //   247: iload_2
    //   248: ifne -> 228
    //   251: aload_3
    //   252: arraylength
    //   253: istore #8
    //   255: iload #8
    //   257: aload #7
    //   259: arraylength
    //   260: if_icmpge -> 278
    //   263: aload #7
    //   265: iload #8
    //   267: iload #6
    //   269: i2b
    //   270: bastore
    //   271: iinc #8, 1
    //   274: iload_2
    //   275: ifne -> 255
    //   278: aload #7
    //   280: astore_3
    //   281: bipush #64
    //   283: newarray int
    //   285: dup
    //   286: iconst_0
    //   287: ldc 16843776
    //   289: iastore
    //   290: dup
    //   291: iconst_1
    //   292: iconst_0
    //   293: iastore
    //   294: dup
    //   295: iconst_2
    //   296: ldc 65536
    //   298: iastore
    //   299: dup
    //   300: iconst_3
    //   301: ldc 16843780
    //   303: iastore
    //   304: dup
    //   305: iconst_4
    //   306: ldc 16842756
    //   308: iastore
    //   309: dup
    //   310: iconst_5
    //   311: ldc 66564
    //   313: iastore
    //   314: dup
    //   315: bipush #6
    //   317: iconst_4
    //   318: iastore
    //   319: dup
    //   320: bipush #7
    //   322: ldc 65536
    //   324: iastore
    //   325: dup
    //   326: bipush #8
    //   328: sipush #1024
    //   331: iastore
    //   332: dup
    //   333: bipush #9
    //   335: ldc 16843776
    //   337: iastore
    //   338: dup
    //   339: bipush #10
    //   341: ldc 16843780
    //   343: iastore
    //   344: dup
    //   345: bipush #11
    //   347: sipush #1024
    //   350: iastore
    //   351: dup
    //   352: bipush #12
    //   354: ldc 16778244
    //   356: iastore
    //   357: dup
    //   358: bipush #13
    //   360: ldc 16842756
    //   362: iastore
    //   363: dup
    //   364: bipush #14
    //   366: ldc 16777216
    //   368: iastore
    //   369: dup
    //   370: bipush #15
    //   372: iconst_4
    //   373: iastore
    //   374: dup
    //   375: bipush #16
    //   377: sipush #1028
    //   380: iastore
    //   381: dup
    //   382: bipush #17
    //   384: ldc 16778240
    //   386: iastore
    //   387: dup
    //   388: bipush #18
    //   390: ldc 16778240
    //   392: iastore
    //   393: dup
    //   394: bipush #19
    //   396: ldc 66560
    //   398: iastore
    //   399: dup
    //   400: bipush #20
    //   402: ldc 66560
    //   404: iastore
    //   405: dup
    //   406: bipush #21
    //   408: ldc 16842752
    //   410: iastore
    //   411: dup
    //   412: bipush #22
    //   414: ldc 16842752
    //   416: iastore
    //   417: dup
    //   418: bipush #23
    //   420: ldc 16778244
    //   422: iastore
    //   423: dup
    //   424: bipush #24
    //   426: ldc 65540
    //   428: iastore
    //   429: dup
    //   430: bipush #25
    //   432: ldc 16777220
    //   434: iastore
    //   435: dup
    //   436: bipush #26
    //   438: ldc 16777220
    //   440: iastore
    //   441: dup
    //   442: bipush #27
    //   444: ldc 65540
    //   446: iastore
    //   447: dup
    //   448: bipush #28
    //   450: iconst_0
    //   451: iastore
    //   452: dup
    //   453: bipush #29
    //   455: sipush #1028
    //   458: iastore
    //   459: dup
    //   460: bipush #30
    //   462: ldc 66564
    //   464: iastore
    //   465: dup
    //   466: bipush #31
    //   468: ldc 16777216
    //   470: iastore
    //   471: dup
    //   472: bipush #32
    //   474: ldc 65536
    //   476: iastore
    //   477: dup
    //   478: bipush #33
    //   480: ldc 16843780
    //   482: iastore
    //   483: dup
    //   484: bipush #34
    //   486: iconst_4
    //   487: iastore
    //   488: dup
    //   489: bipush #35
    //   491: ldc 16842752
    //   493: iastore
    //   494: dup
    //   495: bipush #36
    //   497: ldc 16843776
    //   499: iastore
    //   500: dup
    //   501: bipush #37
    //   503: ldc 16777216
    //   505: iastore
    //   506: dup
    //   507: bipush #38
    //   509: ldc 16777216
    //   511: iastore
    //   512: dup
    //   513: bipush #39
    //   515: sipush #1024
    //   518: iastore
    //   519: dup
    //   520: bipush #40
    //   522: ldc 16842756
    //   524: iastore
    //   525: dup
    //   526: bipush #41
    //   528: ldc 65536
    //   530: iastore
    //   531: dup
    //   532: bipush #42
    //   534: ldc 66560
    //   536: iastore
    //   537: dup
    //   538: bipush #43
    //   540: ldc 16777220
    //   542: iastore
    //   543: dup
    //   544: bipush #44
    //   546: sipush #1024
    //   549: iastore
    //   550: dup
    //   551: bipush #45
    //   553: iconst_4
    //   554: iastore
    //   555: dup
    //   556: bipush #46
    //   558: ldc 16778244
    //   560: iastore
    //   561: dup
    //   562: bipush #47
    //   564: ldc 66564
    //   566: iastore
    //   567: dup
    //   568: bipush #48
    //   570: ldc 16843780
    //   572: iastore
    //   573: dup
    //   574: bipush #49
    //   576: ldc 65540
    //   578: iastore
    //   579: dup
    //   580: bipush #50
    //   582: ldc 16842752
    //   584: iastore
    //   585: dup
    //   586: bipush #51
    //   588: ldc 16778244
    //   590: iastore
    //   591: dup
    //   592: bipush #52
    //   594: ldc 16777220
    //   596: iastore
    //   597: dup
    //   598: bipush #53
    //   600: sipush #1028
    //   603: iastore
    //   604: dup
    //   605: bipush #54
    //   607: ldc 66564
    //   609: iastore
    //   610: dup
    //   611: bipush #55
    //   613: ldc 16843776
    //   615: iastore
    //   616: dup
    //   617: bipush #56
    //   619: sipush #1028
    //   622: iastore
    //   623: dup
    //   624: bipush #57
    //   626: ldc 16778240
    //   628: iastore
    //   629: dup
    //   630: bipush #58
    //   632: ldc 16778240
    //   634: iastore
    //   635: dup
    //   636: bipush #59
    //   638: iconst_0
    //   639: iastore
    //   640: dup
    //   641: bipush #60
    //   643: ldc 65540
    //   645: iastore
    //   646: dup
    //   647: bipush #61
    //   649: ldc 66560
    //   651: iastore
    //   652: dup
    //   653: bipush #62
    //   655: iconst_0
    //   656: iastore
    //   657: dup
    //   658: bipush #63
    //   660: ldc 16842756
    //   662: iastore
    //   663: astore #8
    //   665: bipush #64
    //   667: newarray int
    //   669: dup
    //   670: iconst_0
    //   671: ldc -2146402272
    //   673: iastore
    //   674: dup
    //   675: iconst_1
    //   676: ldc -2147450880
    //   678: iastore
    //   679: dup
    //   680: iconst_2
    //   681: ldc 32768
    //   683: iastore
    //   684: dup
    //   685: iconst_3
    //   686: ldc 1081376
    //   688: iastore
    //   689: dup
    //   690: iconst_4
    //   691: ldc 1048576
    //   693: iastore
    //   694: dup
    //   695: iconst_5
    //   696: bipush #32
    //   698: iastore
    //   699: dup
    //   700: bipush #6
    //   702: ldc -2146435040
    //   704: iastore
    //   705: dup
    //   706: bipush #7
    //   708: ldc -2147450848
    //   710: iastore
    //   711: dup
    //   712: bipush #8
    //   714: ldc -2147483616
    //   716: iastore
    //   717: dup
    //   718: bipush #9
    //   720: ldc -2146402272
    //   722: iastore
    //   723: dup
    //   724: bipush #10
    //   726: ldc -2146402304
    //   728: iastore
    //   729: dup
    //   730: bipush #11
    //   732: ldc -2147483648
    //   734: iastore
    //   735: dup
    //   736: bipush #12
    //   738: ldc -2147450880
    //   740: iastore
    //   741: dup
    //   742: bipush #13
    //   744: ldc 1048576
    //   746: iastore
    //   747: dup
    //   748: bipush #14
    //   750: bipush #32
    //   752: iastore
    //   753: dup
    //   754: bipush #15
    //   756: ldc -2146435040
    //   758: iastore
    //   759: dup
    //   760: bipush #16
    //   762: ldc 1081344
    //   764: iastore
    //   765: dup
    //   766: bipush #17
    //   768: ldc 1048608
    //   770: iastore
    //   771: dup
    //   772: bipush #18
    //   774: ldc -2147450848
    //   776: iastore
    //   777: dup
    //   778: bipush #19
    //   780: iconst_0
    //   781: iastore
    //   782: dup
    //   783: bipush #20
    //   785: ldc -2147483648
    //   787: iastore
    //   788: dup
    //   789: bipush #21
    //   791: ldc 32768
    //   793: iastore
    //   794: dup
    //   795: bipush #22
    //   797: ldc 1081376
    //   799: iastore
    //   800: dup
    //   801: bipush #23
    //   803: ldc -2146435072
    //   805: iastore
    //   806: dup
    //   807: bipush #24
    //   809: ldc 1048608
    //   811: iastore
    //   812: dup
    //   813: bipush #25
    //   815: ldc -2147483616
    //   817: iastore
    //   818: dup
    //   819: bipush #26
    //   821: iconst_0
    //   822: iastore
    //   823: dup
    //   824: bipush #27
    //   826: ldc 1081344
    //   828: iastore
    //   829: dup
    //   830: bipush #28
    //   832: ldc 32800
    //   834: iastore
    //   835: dup
    //   836: bipush #29
    //   838: ldc -2146402304
    //   840: iastore
    //   841: dup
    //   842: bipush #30
    //   844: ldc -2146435072
    //   846: iastore
    //   847: dup
    //   848: bipush #31
    //   850: ldc 32800
    //   852: iastore
    //   853: dup
    //   854: bipush #32
    //   856: iconst_0
    //   857: iastore
    //   858: dup
    //   859: bipush #33
    //   861: ldc 1081376
    //   863: iastore
    //   864: dup
    //   865: bipush #34
    //   867: ldc -2146435040
    //   869: iastore
    //   870: dup
    //   871: bipush #35
    //   873: ldc 1048576
    //   875: iastore
    //   876: dup
    //   877: bipush #36
    //   879: ldc -2147450848
    //   881: iastore
    //   882: dup
    //   883: bipush #37
    //   885: ldc -2146435072
    //   887: iastore
    //   888: dup
    //   889: bipush #38
    //   891: ldc -2146402304
    //   893: iastore
    //   894: dup
    //   895: bipush #39
    //   897: ldc 32768
    //   899: iastore
    //   900: dup
    //   901: bipush #40
    //   903: ldc -2146435072
    //   905: iastore
    //   906: dup
    //   907: bipush #41
    //   909: ldc -2147450880
    //   911: iastore
    //   912: dup
    //   913: bipush #42
    //   915: bipush #32
    //   917: iastore
    //   918: dup
    //   919: bipush #43
    //   921: ldc -2146402272
    //   923: iastore
    //   924: dup
    //   925: bipush #44
    //   927: ldc 1081376
    //   929: iastore
    //   930: dup
    //   931: bipush #45
    //   933: bipush #32
    //   935: iastore
    //   936: dup
    //   937: bipush #46
    //   939: ldc 32768
    //   941: iastore
    //   942: dup
    //   943: bipush #47
    //   945: ldc -2147483648
    //   947: iastore
    //   948: dup
    //   949: bipush #48
    //   951: ldc 32800
    //   953: iastore
    //   954: dup
    //   955: bipush #49
    //   957: ldc -2146402304
    //   959: iastore
    //   960: dup
    //   961: bipush #50
    //   963: ldc 1048576
    //   965: iastore
    //   966: dup
    //   967: bipush #51
    //   969: ldc -2147483616
    //   971: iastore
    //   972: dup
    //   973: bipush #52
    //   975: ldc 1048608
    //   977: iastore
    //   978: dup
    //   979: bipush #53
    //   981: ldc -2147450848
    //   983: iastore
    //   984: dup
    //   985: bipush #54
    //   987: ldc -2147483616
    //   989: iastore
    //   990: dup
    //   991: bipush #55
    //   993: ldc 1048608
    //   995: iastore
    //   996: dup
    //   997: bipush #56
    //   999: ldc 1081344
    //   1001: iastore
    //   1002: dup
    //   1003: bipush #57
    //   1005: iconst_0
    //   1006: iastore
    //   1007: dup
    //   1008: bipush #58
    //   1010: ldc -2147450880
    //   1012: iastore
    //   1013: dup
    //   1014: bipush #59
    //   1016: ldc 32800
    //   1018: iastore
    //   1019: dup
    //   1020: bipush #60
    //   1022: ldc -2147483648
    //   1024: iastore
    //   1025: dup
    //   1026: bipush #61
    //   1028: ldc -2146435040
    //   1030: iastore
    //   1031: dup
    //   1032: bipush #62
    //   1034: ldc -2146402272
    //   1036: iastore
    //   1037: dup
    //   1038: bipush #63
    //   1040: ldc 1081344
    //   1042: iastore
    //   1043: astore #9
    //   1045: bipush #64
    //   1047: newarray int
    //   1049: dup
    //   1050: iconst_0
    //   1051: sipush #520
    //   1054: iastore
    //   1055: dup
    //   1056: iconst_1
    //   1057: ldc 134349312
    //   1059: iastore
    //   1060: dup
    //   1061: iconst_2
    //   1062: iconst_0
    //   1063: iastore
    //   1064: dup
    //   1065: iconst_3
    //   1066: ldc 134348808
    //   1068: iastore
    //   1069: dup
    //   1070: iconst_4
    //   1071: ldc 134218240
    //   1073: iastore
    //   1074: dup
    //   1075: iconst_5
    //   1076: iconst_0
    //   1077: iastore
    //   1078: dup
    //   1079: bipush #6
    //   1081: ldc 131592
    //   1083: iastore
    //   1084: dup
    //   1085: bipush #7
    //   1087: ldc 134218240
    //   1089: iastore
    //   1090: dup
    //   1091: bipush #8
    //   1093: ldc 131080
    //   1095: iastore
    //   1096: dup
    //   1097: bipush #9
    //   1099: ldc 134217736
    //   1101: iastore
    //   1102: dup
    //   1103: bipush #10
    //   1105: ldc 134217736
    //   1107: iastore
    //   1108: dup
    //   1109: bipush #11
    //   1111: ldc 131072
    //   1113: iastore
    //   1114: dup
    //   1115: bipush #12
    //   1117: ldc 134349320
    //   1119: iastore
    //   1120: dup
    //   1121: bipush #13
    //   1123: ldc 131080
    //   1125: iastore
    //   1126: dup
    //   1127: bipush #14
    //   1129: ldc 134348800
    //   1131: iastore
    //   1132: dup
    //   1133: bipush #15
    //   1135: sipush #520
    //   1138: iastore
    //   1139: dup
    //   1140: bipush #16
    //   1142: ldc 134217728
    //   1144: iastore
    //   1145: dup
    //   1146: bipush #17
    //   1148: bipush #8
    //   1150: iastore
    //   1151: dup
    //   1152: bipush #18
    //   1154: ldc 134349312
    //   1156: iastore
    //   1157: dup
    //   1158: bipush #19
    //   1160: sipush #512
    //   1163: iastore
    //   1164: dup
    //   1165: bipush #20
    //   1167: ldc 131584
    //   1169: iastore
    //   1170: dup
    //   1171: bipush #21
    //   1173: ldc 134348800
    //   1175: iastore
    //   1176: dup
    //   1177: bipush #22
    //   1179: ldc 134348808
    //   1181: iastore
    //   1182: dup
    //   1183: bipush #23
    //   1185: ldc 131592
    //   1187: iastore
    //   1188: dup
    //   1189: bipush #24
    //   1191: ldc 134218248
    //   1193: iastore
    //   1194: dup
    //   1195: bipush #25
    //   1197: ldc 131584
    //   1199: iastore
    //   1200: dup
    //   1201: bipush #26
    //   1203: ldc 131072
    //   1205: iastore
    //   1206: dup
    //   1207: bipush #27
    //   1209: ldc 134218248
    //   1211: iastore
    //   1212: dup
    //   1213: bipush #28
    //   1215: bipush #8
    //   1217: iastore
    //   1218: dup
    //   1219: bipush #29
    //   1221: ldc 134349320
    //   1223: iastore
    //   1224: dup
    //   1225: bipush #30
    //   1227: sipush #512
    //   1230: iastore
    //   1231: dup
    //   1232: bipush #31
    //   1234: ldc 134217728
    //   1236: iastore
    //   1237: dup
    //   1238: bipush #32
    //   1240: ldc 134349312
    //   1242: iastore
    //   1243: dup
    //   1244: bipush #33
    //   1246: ldc 134217728
    //   1248: iastore
    //   1249: dup
    //   1250: bipush #34
    //   1252: ldc 131080
    //   1254: iastore
    //   1255: dup
    //   1256: bipush #35
    //   1258: sipush #520
    //   1261: iastore
    //   1262: dup
    //   1263: bipush #36
    //   1265: ldc 131072
    //   1267: iastore
    //   1268: dup
    //   1269: bipush #37
    //   1271: ldc 134349312
    //   1273: iastore
    //   1274: dup
    //   1275: bipush #38
    //   1277: ldc 134218240
    //   1279: iastore
    //   1280: dup
    //   1281: bipush #39
    //   1283: iconst_0
    //   1284: iastore
    //   1285: dup
    //   1286: bipush #40
    //   1288: sipush #512
    //   1291: iastore
    //   1292: dup
    //   1293: bipush #41
    //   1295: ldc 131080
    //   1297: iastore
    //   1298: dup
    //   1299: bipush #42
    //   1301: ldc 134349320
    //   1303: iastore
    //   1304: dup
    //   1305: bipush #43
    //   1307: ldc 134218240
    //   1309: iastore
    //   1310: dup
    //   1311: bipush #44
    //   1313: ldc 134217736
    //   1315: iastore
    //   1316: dup
    //   1317: bipush #45
    //   1319: sipush #512
    //   1322: iastore
    //   1323: dup
    //   1324: bipush #46
    //   1326: iconst_0
    //   1327: iastore
    //   1328: dup
    //   1329: bipush #47
    //   1331: ldc 134348808
    //   1333: iastore
    //   1334: dup
    //   1335: bipush #48
    //   1337: ldc 134218248
    //   1339: iastore
    //   1340: dup
    //   1341: bipush #49
    //   1343: ldc 131072
    //   1345: iastore
    //   1346: dup
    //   1347: bipush #50
    //   1349: ldc 134217728
    //   1351: iastore
    //   1352: dup
    //   1353: bipush #51
    //   1355: ldc 134349320
    //   1357: iastore
    //   1358: dup
    //   1359: bipush #52
    //   1361: bipush #8
    //   1363: iastore
    //   1364: dup
    //   1365: bipush #53
    //   1367: ldc 131592
    //   1369: iastore
    //   1370: dup
    //   1371: bipush #54
    //   1373: ldc 131584
    //   1375: iastore
    //   1376: dup
    //   1377: bipush #55
    //   1379: ldc 134217736
    //   1381: iastore
    //   1382: dup
    //   1383: bipush #56
    //   1385: ldc 134348800
    //   1387: iastore
    //   1388: dup
    //   1389: bipush #57
    //   1391: ldc 134218248
    //   1393: iastore
    //   1394: dup
    //   1395: bipush #58
    //   1397: sipush #520
    //   1400: iastore
    //   1401: dup
    //   1402: bipush #59
    //   1404: ldc 134348800
    //   1406: iastore
    //   1407: dup
    //   1408: bipush #60
    //   1410: ldc 131592
    //   1412: iastore
    //   1413: dup
    //   1414: bipush #61
    //   1416: bipush #8
    //   1418: iastore
    //   1419: dup
    //   1420: bipush #62
    //   1422: ldc 134348808
    //   1424: iastore
    //   1425: dup
    //   1426: bipush #63
    //   1428: ldc 131584
    //   1430: iastore
    //   1431: astore #10
    //   1433: bipush #64
    //   1435: newarray int
    //   1437: dup
    //   1438: iconst_0
    //   1439: ldc 8396801
    //   1441: iastore
    //   1442: dup
    //   1443: iconst_1
    //   1444: sipush #8321
    //   1447: iastore
    //   1448: dup
    //   1449: iconst_2
    //   1450: sipush #8321
    //   1453: iastore
    //   1454: dup
    //   1455: iconst_3
    //   1456: sipush #128
    //   1459: iastore
    //   1460: dup
    //   1461: iconst_4
    //   1462: ldc 8396928
    //   1464: iastore
    //   1465: dup
    //   1466: iconst_5
    //   1467: ldc 8388737
    //   1469: iastore
    //   1470: dup
    //   1471: bipush #6
    //   1473: ldc 8388609
    //   1475: iastore
    //   1476: dup
    //   1477: bipush #7
    //   1479: sipush #8193
    //   1482: iastore
    //   1483: dup
    //   1484: bipush #8
    //   1486: iconst_0
    //   1487: iastore
    //   1488: dup
    //   1489: bipush #9
    //   1491: ldc 8396800
    //   1493: iastore
    //   1494: dup
    //   1495: bipush #10
    //   1497: ldc 8396800
    //   1499: iastore
    //   1500: dup
    //   1501: bipush #11
    //   1503: ldc 8396929
    //   1505: iastore
    //   1506: dup
    //   1507: bipush #12
    //   1509: sipush #129
    //   1512: iastore
    //   1513: dup
    //   1514: bipush #13
    //   1516: iconst_0
    //   1517: iastore
    //   1518: dup
    //   1519: bipush #14
    //   1521: ldc 8388736
    //   1523: iastore
    //   1524: dup
    //   1525: bipush #15
    //   1527: ldc 8388609
    //   1529: iastore
    //   1530: dup
    //   1531: bipush #16
    //   1533: iconst_1
    //   1534: iastore
    //   1535: dup
    //   1536: bipush #17
    //   1538: sipush #8192
    //   1541: iastore
    //   1542: dup
    //   1543: bipush #18
    //   1545: ldc 8388608
    //   1547: iastore
    //   1548: dup
    //   1549: bipush #19
    //   1551: ldc 8396801
    //   1553: iastore
    //   1554: dup
    //   1555: bipush #20
    //   1557: sipush #128
    //   1560: iastore
    //   1561: dup
    //   1562: bipush #21
    //   1564: ldc 8388608
    //   1566: iastore
    //   1567: dup
    //   1568: bipush #22
    //   1570: sipush #8193
    //   1573: iastore
    //   1574: dup
    //   1575: bipush #23
    //   1577: sipush #8320
    //   1580: iastore
    //   1581: dup
    //   1582: bipush #24
    //   1584: ldc 8388737
    //   1586: iastore
    //   1587: dup
    //   1588: bipush #25
    //   1590: iconst_1
    //   1591: iastore
    //   1592: dup
    //   1593: bipush #26
    //   1595: sipush #8320
    //   1598: iastore
    //   1599: dup
    //   1600: bipush #27
    //   1602: ldc 8388736
    //   1604: iastore
    //   1605: dup
    //   1606: bipush #28
    //   1608: sipush #8192
    //   1611: iastore
    //   1612: dup
    //   1613: bipush #29
    //   1615: ldc 8396928
    //   1617: iastore
    //   1618: dup
    //   1619: bipush #30
    //   1621: ldc 8396929
    //   1623: iastore
    //   1624: dup
    //   1625: bipush #31
    //   1627: sipush #129
    //   1630: iastore
    //   1631: dup
    //   1632: bipush #32
    //   1634: ldc 8388736
    //   1636: iastore
    //   1637: dup
    //   1638: bipush #33
    //   1640: ldc 8388609
    //   1642: iastore
    //   1643: dup
    //   1644: bipush #34
    //   1646: ldc 8396800
    //   1648: iastore
    //   1649: dup
    //   1650: bipush #35
    //   1652: ldc 8396929
    //   1654: iastore
    //   1655: dup
    //   1656: bipush #36
    //   1658: sipush #129
    //   1661: iastore
    //   1662: dup
    //   1663: bipush #37
    //   1665: iconst_0
    //   1666: iastore
    //   1667: dup
    //   1668: bipush #38
    //   1670: iconst_0
    //   1671: iastore
    //   1672: dup
    //   1673: bipush #39
    //   1675: ldc 8396800
    //   1677: iastore
    //   1678: dup
    //   1679: bipush #40
    //   1681: sipush #8320
    //   1684: iastore
    //   1685: dup
    //   1686: bipush #41
    //   1688: ldc 8388736
    //   1690: iastore
    //   1691: dup
    //   1692: bipush #42
    //   1694: ldc 8388737
    //   1696: iastore
    //   1697: dup
    //   1698: bipush #43
    //   1700: iconst_1
    //   1701: iastore
    //   1702: dup
    //   1703: bipush #44
    //   1705: ldc 8396801
    //   1707: iastore
    //   1708: dup
    //   1709: bipush #45
    //   1711: sipush #8321
    //   1714: iastore
    //   1715: dup
    //   1716: bipush #46
    //   1718: sipush #8321
    //   1721: iastore
    //   1722: dup
    //   1723: bipush #47
    //   1725: sipush #128
    //   1728: iastore
    //   1729: dup
    //   1730: bipush #48
    //   1732: ldc 8396929
    //   1734: iastore
    //   1735: dup
    //   1736: bipush #49
    //   1738: sipush #129
    //   1741: iastore
    //   1742: dup
    //   1743: bipush #50
    //   1745: iconst_1
    //   1746: iastore
    //   1747: dup
    //   1748: bipush #51
    //   1750: sipush #8192
    //   1753: iastore
    //   1754: dup
    //   1755: bipush #52
    //   1757: ldc 8388609
    //   1759: iastore
    //   1760: dup
    //   1761: bipush #53
    //   1763: sipush #8193
    //   1766: iastore
    //   1767: dup
    //   1768: bipush #54
    //   1770: ldc 8396928
    //   1772: iastore
    //   1773: dup
    //   1774: bipush #55
    //   1776: ldc 8388737
    //   1778: iastore
    //   1779: dup
    //   1780: bipush #56
    //   1782: sipush #8193
    //   1785: iastore
    //   1786: dup
    //   1787: bipush #57
    //   1789: sipush #8320
    //   1792: iastore
    //   1793: dup
    //   1794: bipush #58
    //   1796: ldc 8388608
    //   1798: iastore
    //   1799: dup
    //   1800: bipush #59
    //   1802: ldc 8396801
    //   1804: iastore
    //   1805: dup
    //   1806: bipush #60
    //   1808: sipush #128
    //   1811: iastore
    //   1812: dup
    //   1813: bipush #61
    //   1815: ldc 8388608
    //   1817: iastore
    //   1818: dup
    //   1819: bipush #62
    //   1821: sipush #8192
    //   1824: iastore
    //   1825: dup
    //   1826: bipush #63
    //   1828: ldc 8396928
    //   1830: iastore
    //   1831: astore #11
    //   1833: bipush #64
    //   1835: newarray int
    //   1837: dup
    //   1838: iconst_0
    //   1839: sipush #256
    //   1842: iastore
    //   1843: dup
    //   1844: iconst_1
    //   1845: ldc 34078976
    //   1847: iastore
    //   1848: dup
    //   1849: iconst_2
    //   1850: ldc 34078720
    //   1852: iastore
    //   1853: dup
    //   1854: iconst_3
    //   1855: ldc 1107296512
    //   1857: iastore
    //   1858: dup
    //   1859: iconst_4
    //   1860: ldc 524288
    //   1862: iastore
    //   1863: dup
    //   1864: iconst_5
    //   1865: sipush #256
    //   1868: iastore
    //   1869: dup
    //   1870: bipush #6
    //   1872: ldc 1073741824
    //   1874: iastore
    //   1875: dup
    //   1876: bipush #7
    //   1878: ldc 34078720
    //   1880: iastore
    //   1881: dup
    //   1882: bipush #8
    //   1884: ldc 1074266368
    //   1886: iastore
    //   1887: dup
    //   1888: bipush #9
    //   1890: ldc 524288
    //   1892: iastore
    //   1893: dup
    //   1894: bipush #10
    //   1896: ldc 33554688
    //   1898: iastore
    //   1899: dup
    //   1900: bipush #11
    //   1902: ldc 1074266368
    //   1904: iastore
    //   1905: dup
    //   1906: bipush #12
    //   1908: ldc 1107296512
    //   1910: iastore
    //   1911: dup
    //   1912: bipush #13
    //   1914: ldc 1107820544
    //   1916: iastore
    //   1917: dup
    //   1918: bipush #14
    //   1920: ldc 524544
    //   1922: iastore
    //   1923: dup
    //   1924: bipush #15
    //   1926: ldc 1073741824
    //   1928: iastore
    //   1929: dup
    //   1930: bipush #16
    //   1932: ldc 33554432
    //   1934: iastore
    //   1935: dup
    //   1936: bipush #17
    //   1938: ldc 1074266112
    //   1940: iastore
    //   1941: dup
    //   1942: bipush #18
    //   1944: ldc 1074266112
    //   1946: iastore
    //   1947: dup
    //   1948: bipush #19
    //   1950: iconst_0
    //   1951: iastore
    //   1952: dup
    //   1953: bipush #20
    //   1955: ldc 1073742080
    //   1957: iastore
    //   1958: dup
    //   1959: bipush #21
    //   1961: ldc 1107820800
    //   1963: iastore
    //   1964: dup
    //   1965: bipush #22
    //   1967: ldc 1107820800
    //   1969: iastore
    //   1970: dup
    //   1971: bipush #23
    //   1973: ldc 33554688
    //   1975: iastore
    //   1976: dup
    //   1977: bipush #24
    //   1979: ldc 1107820544
    //   1981: iastore
    //   1982: dup
    //   1983: bipush #25
    //   1985: ldc 1073742080
    //   1987: iastore
    //   1988: dup
    //   1989: bipush #26
    //   1991: iconst_0
    //   1992: iastore
    //   1993: dup
    //   1994: bipush #27
    //   1996: ldc 1107296256
    //   1998: iastore
    //   1999: dup
    //   2000: bipush #28
    //   2002: ldc 34078976
    //   2004: iastore
    //   2005: dup
    //   2006: bipush #29
    //   2008: ldc 33554432
    //   2010: iastore
    //   2011: dup
    //   2012: bipush #30
    //   2014: ldc 1107296256
    //   2016: iastore
    //   2017: dup
    //   2018: bipush #31
    //   2020: ldc 524544
    //   2022: iastore
    //   2023: dup
    //   2024: bipush #32
    //   2026: ldc 524288
    //   2028: iastore
    //   2029: dup
    //   2030: bipush #33
    //   2032: ldc 1107296512
    //   2034: iastore
    //   2035: dup
    //   2036: bipush #34
    //   2038: sipush #256
    //   2041: iastore
    //   2042: dup
    //   2043: bipush #35
    //   2045: ldc 33554432
    //   2047: iastore
    //   2048: dup
    //   2049: bipush #36
    //   2051: ldc 1073741824
    //   2053: iastore
    //   2054: dup
    //   2055: bipush #37
    //   2057: ldc 34078720
    //   2059: iastore
    //   2060: dup
    //   2061: bipush #38
    //   2063: ldc 1107296512
    //   2065: iastore
    //   2066: dup
    //   2067: bipush #39
    //   2069: ldc 1074266368
    //   2071: iastore
    //   2072: dup
    //   2073: bipush #40
    //   2075: ldc 33554688
    //   2077: iastore
    //   2078: dup
    //   2079: bipush #41
    //   2081: ldc 1073741824
    //   2083: iastore
    //   2084: dup
    //   2085: bipush #42
    //   2087: ldc 1107820544
    //   2089: iastore
    //   2090: dup
    //   2091: bipush #43
    //   2093: ldc 34078976
    //   2095: iastore
    //   2096: dup
    //   2097: bipush #44
    //   2099: ldc 1074266368
    //   2101: iastore
    //   2102: dup
    //   2103: bipush #45
    //   2105: sipush #256
    //   2108: iastore
    //   2109: dup
    //   2110: bipush #46
    //   2112: ldc 33554432
    //   2114: iastore
    //   2115: dup
    //   2116: bipush #47
    //   2118: ldc 1107820544
    //   2120: iastore
    //   2121: dup
    //   2122: bipush #48
    //   2124: ldc 1107820800
    //   2126: iastore
    //   2127: dup
    //   2128: bipush #49
    //   2130: ldc 524544
    //   2132: iastore
    //   2133: dup
    //   2134: bipush #50
    //   2136: ldc 1107296256
    //   2138: iastore
    //   2139: dup
    //   2140: bipush #51
    //   2142: ldc 1107820800
    //   2144: iastore
    //   2145: dup
    //   2146: bipush #52
    //   2148: ldc 34078720
    //   2150: iastore
    //   2151: dup
    //   2152: bipush #53
    //   2154: iconst_0
    //   2155: iastore
    //   2156: dup
    //   2157: bipush #54
    //   2159: ldc 1074266112
    //   2161: iastore
    //   2162: dup
    //   2163: bipush #55
    //   2165: ldc 1107296256
    //   2167: iastore
    //   2168: dup
    //   2169: bipush #56
    //   2171: ldc 524544
    //   2173: iastore
    //   2174: dup
    //   2175: bipush #57
    //   2177: ldc 33554688
    //   2179: iastore
    //   2180: dup
    //   2181: bipush #58
    //   2183: ldc 1073742080
    //   2185: iastore
    //   2186: dup
    //   2187: bipush #59
    //   2189: ldc 524288
    //   2191: iastore
    //   2192: dup
    //   2193: bipush #60
    //   2195: iconst_0
    //   2196: iastore
    //   2197: dup
    //   2198: bipush #61
    //   2200: ldc 1074266112
    //   2202: iastore
    //   2203: dup
    //   2204: bipush #62
    //   2206: ldc 34078976
    //   2208: iastore
    //   2209: dup
    //   2210: bipush #63
    //   2212: ldc 1073742080
    //   2214: iastore
    //   2215: astore #12
    //   2217: bipush #64
    //   2219: newarray int
    //   2221: dup
    //   2222: iconst_0
    //   2223: ldc 536870928
    //   2225: iastore
    //   2226: dup
    //   2227: iconst_1
    //   2228: ldc 541065216
    //   2230: iastore
    //   2231: dup
    //   2232: iconst_2
    //   2233: sipush #16384
    //   2236: iastore
    //   2237: dup
    //   2238: iconst_3
    //   2239: ldc 541081616
    //   2241: iastore
    //   2242: dup
    //   2243: iconst_4
    //   2244: ldc 541065216
    //   2246: iastore
    //   2247: dup
    //   2248: iconst_5
    //   2249: bipush #16
    //   2251: iastore
    //   2252: dup
    //   2253: bipush #6
    //   2255: ldc 541081616
    //   2257: iastore
    //   2258: dup
    //   2259: bipush #7
    //   2261: ldc 4194304
    //   2263: iastore
    //   2264: dup
    //   2265: bipush #8
    //   2267: ldc 536887296
    //   2269: iastore
    //   2270: dup
    //   2271: bipush #9
    //   2273: ldc 4210704
    //   2275: iastore
    //   2276: dup
    //   2277: bipush #10
    //   2279: ldc 4194304
    //   2281: iastore
    //   2282: dup
    //   2283: bipush #11
    //   2285: ldc 536870928
    //   2287: iastore
    //   2288: dup
    //   2289: bipush #12
    //   2291: ldc 4194320
    //   2293: iastore
    //   2294: dup
    //   2295: bipush #13
    //   2297: ldc 536887296
    //   2299: iastore
    //   2300: dup
    //   2301: bipush #14
    //   2303: ldc 536870912
    //   2305: iastore
    //   2306: dup
    //   2307: bipush #15
    //   2309: sipush #16400
    //   2312: iastore
    //   2313: dup
    //   2314: bipush #16
    //   2316: iconst_0
    //   2317: iastore
    //   2318: dup
    //   2319: bipush #17
    //   2321: ldc 4194320
    //   2323: iastore
    //   2324: dup
    //   2325: bipush #18
    //   2327: ldc 536887312
    //   2329: iastore
    //   2330: dup
    //   2331: bipush #19
    //   2333: sipush #16384
    //   2336: iastore
    //   2337: dup
    //   2338: bipush #20
    //   2340: ldc 4210688
    //   2342: iastore
    //   2343: dup
    //   2344: bipush #21
    //   2346: ldc 536887312
    //   2348: iastore
    //   2349: dup
    //   2350: bipush #22
    //   2352: bipush #16
    //   2354: iastore
    //   2355: dup
    //   2356: bipush #23
    //   2358: ldc 541065232
    //   2360: iastore
    //   2361: dup
    //   2362: bipush #24
    //   2364: ldc 541065232
    //   2366: iastore
    //   2367: dup
    //   2368: bipush #25
    //   2370: iconst_0
    //   2371: iastore
    //   2372: dup
    //   2373: bipush #26
    //   2375: ldc 4210704
    //   2377: iastore
    //   2378: dup
    //   2379: bipush #27
    //   2381: ldc 541081600
    //   2383: iastore
    //   2384: dup
    //   2385: bipush #28
    //   2387: sipush #16400
    //   2390: iastore
    //   2391: dup
    //   2392: bipush #29
    //   2394: ldc 4210688
    //   2396: iastore
    //   2397: dup
    //   2398: bipush #30
    //   2400: ldc 541081600
    //   2402: iastore
    //   2403: dup
    //   2404: bipush #31
    //   2406: ldc 536870912
    //   2408: iastore
    //   2409: dup
    //   2410: bipush #32
    //   2412: ldc 536887296
    //   2414: iastore
    //   2415: dup
    //   2416: bipush #33
    //   2418: bipush #16
    //   2420: iastore
    //   2421: dup
    //   2422: bipush #34
    //   2424: ldc 541065232
    //   2426: iastore
    //   2427: dup
    //   2428: bipush #35
    //   2430: ldc 4210688
    //   2432: iastore
    //   2433: dup
    //   2434: bipush #36
    //   2436: ldc 541081616
    //   2438: iastore
    //   2439: dup
    //   2440: bipush #37
    //   2442: ldc 4194304
    //   2444: iastore
    //   2445: dup
    //   2446: bipush #38
    //   2448: sipush #16400
    //   2451: iastore
    //   2452: dup
    //   2453: bipush #39
    //   2455: ldc 536870928
    //   2457: iastore
    //   2458: dup
    //   2459: bipush #40
    //   2461: ldc 4194304
    //   2463: iastore
    //   2464: dup
    //   2465: bipush #41
    //   2467: ldc 536887296
    //   2469: iastore
    //   2470: dup
    //   2471: bipush #42
    //   2473: ldc 536870912
    //   2475: iastore
    //   2476: dup
    //   2477: bipush #43
    //   2479: sipush #16400
    //   2482: iastore
    //   2483: dup
    //   2484: bipush #44
    //   2486: ldc 536870928
    //   2488: iastore
    //   2489: dup
    //   2490: bipush #45
    //   2492: ldc 541081616
    //   2494: iastore
    //   2495: dup
    //   2496: bipush #46
    //   2498: ldc 4210688
    //   2500: iastore
    //   2501: dup
    //   2502: bipush #47
    //   2504: ldc 541065216
    //   2506: iastore
    //   2507: dup
    //   2508: bipush #48
    //   2510: ldc 4210704
    //   2512: iastore
    //   2513: dup
    //   2514: bipush #49
    //   2516: ldc 541081600
    //   2518: iastore
    //   2519: dup
    //   2520: bipush #50
    //   2522: iconst_0
    //   2523: iastore
    //   2524: dup
    //   2525: bipush #51
    //   2527: ldc 541065232
    //   2529: iastore
    //   2530: dup
    //   2531: bipush #52
    //   2533: bipush #16
    //   2535: iastore
    //   2536: dup
    //   2537: bipush #53
    //   2539: sipush #16384
    //   2542: iastore
    //   2543: dup
    //   2544: bipush #54
    //   2546: ldc 541065216
    //   2548: iastore
    //   2549: dup
    //   2550: bipush #55
    //   2552: ldc 4210704
    //   2554: iastore
    //   2555: dup
    //   2556: bipush #56
    //   2558: sipush #16384
    //   2561: iastore
    //   2562: dup
    //   2563: bipush #57
    //   2565: ldc 4194320
    //   2567: iastore
    //   2568: dup
    //   2569: bipush #58
    //   2571: ldc 536887312
    //   2573: iastore
    //   2574: dup
    //   2575: bipush #59
    //   2577: iconst_0
    //   2578: iastore
    //   2579: dup
    //   2580: bipush #60
    //   2582: ldc 541081600
    //   2584: iastore
    //   2585: dup
    //   2586: bipush #61
    //   2588: ldc 536870912
    //   2590: iastore
    //   2591: dup
    //   2592: bipush #62
    //   2594: ldc 4194320
    //   2596: iastore
    //   2597: dup
    //   2598: bipush #63
    //   2600: ldc 536887312
    //   2602: iastore
    //   2603: astore #13
    //   2605: bipush #64
    //   2607: newarray int
    //   2609: dup
    //   2610: iconst_0
    //   2611: ldc 2097152
    //   2613: iastore
    //   2614: dup
    //   2615: iconst_1
    //   2616: ldc 69206018
    //   2618: iastore
    //   2619: dup
    //   2620: iconst_2
    //   2621: ldc 67110914
    //   2623: iastore
    //   2624: dup
    //   2625: iconst_3
    //   2626: iconst_0
    //   2627: iastore
    //   2628: dup
    //   2629: iconst_4
    //   2630: sipush #2048
    //   2633: iastore
    //   2634: dup
    //   2635: iconst_5
    //   2636: ldc 67110914
    //   2638: iastore
    //   2639: dup
    //   2640: bipush #6
    //   2642: ldc 2099202
    //   2644: iastore
    //   2645: dup
    //   2646: bipush #7
    //   2648: ldc 69208064
    //   2650: iastore
    //   2651: dup
    //   2652: bipush #8
    //   2654: ldc 69208066
    //   2656: iastore
    //   2657: dup
    //   2658: bipush #9
    //   2660: ldc 2097152
    //   2662: iastore
    //   2663: dup
    //   2664: bipush #10
    //   2666: iconst_0
    //   2667: iastore
    //   2668: dup
    //   2669: bipush #11
    //   2671: ldc 67108866
    //   2673: iastore
    //   2674: dup
    //   2675: bipush #12
    //   2677: iconst_2
    //   2678: iastore
    //   2679: dup
    //   2680: bipush #13
    //   2682: ldc 67108864
    //   2684: iastore
    //   2685: dup
    //   2686: bipush #14
    //   2688: ldc 69206018
    //   2690: iastore
    //   2691: dup
    //   2692: bipush #15
    //   2694: sipush #2050
    //   2697: iastore
    //   2698: dup
    //   2699: bipush #16
    //   2701: ldc 67110912
    //   2703: iastore
    //   2704: dup
    //   2705: bipush #17
    //   2707: ldc 2099202
    //   2709: iastore
    //   2710: dup
    //   2711: bipush #18
    //   2713: ldc 2097154
    //   2715: iastore
    //   2716: dup
    //   2717: bipush #19
    //   2719: ldc 67110912
    //   2721: iastore
    //   2722: dup
    //   2723: bipush #20
    //   2725: ldc 67108866
    //   2727: iastore
    //   2728: dup
    //   2729: bipush #21
    //   2731: ldc 69206016
    //   2733: iastore
    //   2734: dup
    //   2735: bipush #22
    //   2737: ldc 69208064
    //   2739: iastore
    //   2740: dup
    //   2741: bipush #23
    //   2743: ldc 2097154
    //   2745: iastore
    //   2746: dup
    //   2747: bipush #24
    //   2749: ldc 69206016
    //   2751: iastore
    //   2752: dup
    //   2753: bipush #25
    //   2755: sipush #2048
    //   2758: iastore
    //   2759: dup
    //   2760: bipush #26
    //   2762: sipush #2050
    //   2765: iastore
    //   2766: dup
    //   2767: bipush #27
    //   2769: ldc 69208066
    //   2771: iastore
    //   2772: dup
    //   2773: bipush #28
    //   2775: ldc 2099200
    //   2777: iastore
    //   2778: dup
    //   2779: bipush #29
    //   2781: iconst_2
    //   2782: iastore
    //   2783: dup
    //   2784: bipush #30
    //   2786: ldc 67108864
    //   2788: iastore
    //   2789: dup
    //   2790: bipush #31
    //   2792: ldc 2099200
    //   2794: iastore
    //   2795: dup
    //   2796: bipush #32
    //   2798: ldc 67108864
    //   2800: iastore
    //   2801: dup
    //   2802: bipush #33
    //   2804: ldc 2099200
    //   2806: iastore
    //   2807: dup
    //   2808: bipush #34
    //   2810: ldc 2097152
    //   2812: iastore
    //   2813: dup
    //   2814: bipush #35
    //   2816: ldc 67110914
    //   2818: iastore
    //   2819: dup
    //   2820: bipush #36
    //   2822: ldc 67110914
    //   2824: iastore
    //   2825: dup
    //   2826: bipush #37
    //   2828: ldc 69206018
    //   2830: iastore
    //   2831: dup
    //   2832: bipush #38
    //   2834: ldc 69206018
    //   2836: iastore
    //   2837: dup
    //   2838: bipush #39
    //   2840: iconst_2
    //   2841: iastore
    //   2842: dup
    //   2843: bipush #40
    //   2845: ldc 2097154
    //   2847: iastore
    //   2848: dup
    //   2849: bipush #41
    //   2851: ldc 67108864
    //   2853: iastore
    //   2854: dup
    //   2855: bipush #42
    //   2857: ldc 67110912
    //   2859: iastore
    //   2860: dup
    //   2861: bipush #43
    //   2863: ldc 2097152
    //   2865: iastore
    //   2866: dup
    //   2867: bipush #44
    //   2869: ldc 69208064
    //   2871: iastore
    //   2872: dup
    //   2873: bipush #45
    //   2875: sipush #2050
    //   2878: iastore
    //   2879: dup
    //   2880: bipush #46
    //   2882: ldc 2099202
    //   2884: iastore
    //   2885: dup
    //   2886: bipush #47
    //   2888: ldc 69208064
    //   2890: iastore
    //   2891: dup
    //   2892: bipush #48
    //   2894: sipush #2050
    //   2897: iastore
    //   2898: dup
    //   2899: bipush #49
    //   2901: ldc 67108866
    //   2903: iastore
    //   2904: dup
    //   2905: bipush #50
    //   2907: ldc 69208066
    //   2909: iastore
    //   2910: dup
    //   2911: bipush #51
    //   2913: ldc 69206016
    //   2915: iastore
    //   2916: dup
    //   2917: bipush #52
    //   2919: ldc 2099200
    //   2921: iastore
    //   2922: dup
    //   2923: bipush #53
    //   2925: iconst_0
    //   2926: iastore
    //   2927: dup
    //   2928: bipush #54
    //   2930: iconst_2
    //   2931: iastore
    //   2932: dup
    //   2933: bipush #55
    //   2935: ldc 69208066
    //   2937: iastore
    //   2938: dup
    //   2939: bipush #56
    //   2941: iconst_0
    //   2942: iastore
    //   2943: dup
    //   2944: bipush #57
    //   2946: ldc 2099202
    //   2948: iastore
    //   2949: dup
    //   2950: bipush #58
    //   2952: ldc 69206016
    //   2954: iastore
    //   2955: dup
    //   2956: bipush #59
    //   2958: sipush #2048
    //   2961: iastore
    //   2962: dup
    //   2963: bipush #60
    //   2965: ldc 67108866
    //   2967: iastore
    //   2968: dup
    //   2969: bipush #61
    //   2971: ldc 67110912
    //   2973: iastore
    //   2974: dup
    //   2975: bipush #62
    //   2977: sipush #2048
    //   2980: iastore
    //   2981: dup
    //   2982: bipush #63
    //   2984: ldc 2097154
    //   2986: iastore
    //   2987: astore #14
    //   2989: bipush #64
    //   2991: newarray int
    //   2993: dup
    //   2994: iconst_0
    //   2995: ldc 268439616
    //   2997: iastore
    //   2998: dup
    //   2999: iconst_1
    //   3000: sipush #4096
    //   3003: iastore
    //   3004: dup
    //   3005: iconst_2
    //   3006: ldc 262144
    //   3008: iastore
    //   3009: dup
    //   3010: iconst_3
    //   3011: ldc 268701760
    //   3013: iastore
    //   3014: dup
    //   3015: iconst_4
    //   3016: ldc 268435456
    //   3018: iastore
    //   3019: dup
    //   3020: iconst_5
    //   3021: ldc 268439616
    //   3023: iastore
    //   3024: dup
    //   3025: bipush #6
    //   3027: bipush #64
    //   3029: iastore
    //   3030: dup
    //   3031: bipush #7
    //   3033: ldc 268435456
    //   3035: iastore
    //   3036: dup
    //   3037: bipush #8
    //   3039: ldc 262208
    //   3041: iastore
    //   3042: dup
    //   3043: bipush #9
    //   3045: ldc 268697600
    //   3047: iastore
    //   3048: dup
    //   3049: bipush #10
    //   3051: ldc 268701760
    //   3053: iastore
    //   3054: dup
    //   3055: bipush #11
    //   3057: ldc 266240
    //   3059: iastore
    //   3060: dup
    //   3061: bipush #12
    //   3063: ldc 268701696
    //   3065: iastore
    //   3066: dup
    //   3067: bipush #13
    //   3069: ldc 266304
    //   3071: iastore
    //   3072: dup
    //   3073: bipush #14
    //   3075: sipush #4096
    //   3078: iastore
    //   3079: dup
    //   3080: bipush #15
    //   3082: bipush #64
    //   3084: iastore
    //   3085: dup
    //   3086: bipush #16
    //   3088: ldc 268697600
    //   3090: iastore
    //   3091: dup
    //   3092: bipush #17
    //   3094: ldc 268435520
    //   3096: iastore
    //   3097: dup
    //   3098: bipush #18
    //   3100: ldc 268439552
    //   3102: iastore
    //   3103: dup
    //   3104: bipush #19
    //   3106: sipush #4160
    //   3109: iastore
    //   3110: dup
    //   3111: bipush #20
    //   3113: ldc 266240
    //   3115: iastore
    //   3116: dup
    //   3117: bipush #21
    //   3119: ldc 262208
    //   3121: iastore
    //   3122: dup
    //   3123: bipush #22
    //   3125: ldc 268697664
    //   3127: iastore
    //   3128: dup
    //   3129: bipush #23
    //   3131: ldc 268701696
    //   3133: iastore
    //   3134: dup
    //   3135: bipush #24
    //   3137: sipush #4160
    //   3140: iastore
    //   3141: dup
    //   3142: bipush #25
    //   3144: iconst_0
    //   3145: iastore
    //   3146: dup
    //   3147: bipush #26
    //   3149: iconst_0
    //   3150: iastore
    //   3151: dup
    //   3152: bipush #27
    //   3154: ldc 268697664
    //   3156: iastore
    //   3157: dup
    //   3158: bipush #28
    //   3160: ldc 268435520
    //   3162: iastore
    //   3163: dup
    //   3164: bipush #29
    //   3166: ldc 268439552
    //   3168: iastore
    //   3169: dup
    //   3170: bipush #30
    //   3172: ldc 266304
    //   3174: iastore
    //   3175: dup
    //   3176: bipush #31
    //   3178: ldc 262144
    //   3180: iastore
    //   3181: dup
    //   3182: bipush #32
    //   3184: ldc 266304
    //   3186: iastore
    //   3187: dup
    //   3188: bipush #33
    //   3190: ldc 262144
    //   3192: iastore
    //   3193: dup
    //   3194: bipush #34
    //   3196: ldc 268701696
    //   3198: iastore
    //   3199: dup
    //   3200: bipush #35
    //   3202: sipush #4096
    //   3205: iastore
    //   3206: dup
    //   3207: bipush #36
    //   3209: bipush #64
    //   3211: iastore
    //   3212: dup
    //   3213: bipush #37
    //   3215: ldc 268697664
    //   3217: iastore
    //   3218: dup
    //   3219: bipush #38
    //   3221: sipush #4096
    //   3224: iastore
    //   3225: dup
    //   3226: bipush #39
    //   3228: ldc 266304
    //   3230: iastore
    //   3231: dup
    //   3232: bipush #40
    //   3234: ldc 268439552
    //   3236: iastore
    //   3237: dup
    //   3238: bipush #41
    //   3240: bipush #64
    //   3242: iastore
    //   3243: dup
    //   3244: bipush #42
    //   3246: ldc 268435520
    //   3248: iastore
    //   3249: dup
    //   3250: bipush #43
    //   3252: ldc 268697600
    //   3254: iastore
    //   3255: dup
    //   3256: bipush #44
    //   3258: ldc 268697664
    //   3260: iastore
    //   3261: dup
    //   3262: bipush #45
    //   3264: ldc 268435456
    //   3266: iastore
    //   3267: dup
    //   3268: bipush #46
    //   3270: ldc 262144
    //   3272: iastore
    //   3273: dup
    //   3274: bipush #47
    //   3276: ldc 268439616
    //   3278: iastore
    //   3279: dup
    //   3280: bipush #48
    //   3282: iconst_0
    //   3283: iastore
    //   3284: dup
    //   3285: bipush #49
    //   3287: ldc 268701760
    //   3289: iastore
    //   3290: dup
    //   3291: bipush #50
    //   3293: ldc 262208
    //   3295: iastore
    //   3296: dup
    //   3297: bipush #51
    //   3299: ldc 268435520
    //   3301: iastore
    //   3302: dup
    //   3303: bipush #52
    //   3305: ldc 268697600
    //   3307: iastore
    //   3308: dup
    //   3309: bipush #53
    //   3311: ldc 268439552
    //   3313: iastore
    //   3314: dup
    //   3315: bipush #54
    //   3317: ldc 268439616
    //   3319: iastore
    //   3320: dup
    //   3321: bipush #55
    //   3323: iconst_0
    //   3324: iastore
    //   3325: dup
    //   3326: bipush #56
    //   3328: ldc 268701760
    //   3330: iastore
    //   3331: dup
    //   3332: bipush #57
    //   3334: ldc 266240
    //   3336: iastore
    //   3337: dup
    //   3338: bipush #58
    //   3340: ldc 266240
    //   3342: iastore
    //   3343: dup
    //   3344: bipush #59
    //   3346: sipush #4160
    //   3349: iastore
    //   3350: dup
    //   3351: bipush #60
    //   3353: sipush #4160
    //   3356: iastore
    //   3357: dup
    //   3358: bipush #61
    //   3360: ldc 262208
    //   3362: iastore
    //   3363: dup
    //   3364: bipush #62
    //   3366: ldc 268435456
    //   3368: iastore
    //   3369: dup
    //   3370: bipush #63
    //   3372: ldc 268701696
    //   3374: iastore
    //   3375: astore #15
    //   3377: aload_3
    //   3378: arraylength
    //   3379: istore #16
    //   3381: iconst_2
    //   3382: newarray int
    //   3384: astore #17
    //   3386: iload #16
    //   3388: newarray byte
    //   3390: astore #4
    //   3392: iload #16
    //   3394: bipush #8
    //   3396: idiv
    //   3397: istore #18
    //   3399: iconst_0
    //   3400: istore #19
    //   3402: iload #19
    //   3404: iload #18
    //   3406: if_icmpge -> 4320
    //   3409: iload #19
    //   3411: bipush #8
    //   3413: imul
    //   3414: istore #20
    //   3416: iconst_0
    //   3417: istore #21
    //   3419: iload #21
    //   3421: iconst_2
    //   3422: if_icmpge -> 3507
    //   3425: aload #17
    //   3427: iload #21
    //   3429: aload_3
    //   3430: iload #20
    //   3432: iload #21
    //   3434: iconst_4
    //   3435: imul
    //   3436: iadd
    //   3437: baload
    //   3438: sipush #255
    //   3441: iand
    //   3442: bipush #24
    //   3444: ishl
    //   3445: aload_3
    //   3446: iload #20
    //   3448: iload #21
    //   3450: iconst_4
    //   3451: imul
    //   3452: iadd
    //   3453: iconst_1
    //   3454: iadd
    //   3455: baload
    //   3456: sipush #255
    //   3459: iand
    //   3460: bipush #16
    //   3462: ishl
    //   3463: ior
    //   3464: aload_3
    //   3465: iload #20
    //   3467: iload #21
    //   3469: iconst_4
    //   3470: imul
    //   3471: iadd
    //   3472: iconst_2
    //   3473: iadd
    //   3474: baload
    //   3475: sipush #255
    //   3478: iand
    //   3479: bipush #8
    //   3481: ishl
    //   3482: ior
    //   3483: aload_3
    //   3484: iload #20
    //   3486: iload #21
    //   3488: iconst_4
    //   3489: imul
    //   3490: iadd
    //   3491: iconst_3
    //   3492: iadd
    //   3493: baload
    //   3494: sipush #255
    //   3497: iand
    //   3498: ior
    //   3499: iastore
    //   3500: iinc #21, 1
    //   3503: iload_2
    //   3504: ifne -> 3419
    //   3507: iconst_0
    //   3508: istore #26
    //   3510: aload #17
    //   3512: iconst_0
    //   3513: iaload
    //   3514: istore #24
    //   3516: aload #17
    //   3518: iconst_1
    //   3519: iaload
    //   3520: istore #23
    //   3522: iload #24
    //   3524: iconst_4
    //   3525: iushr
    //   3526: iload #23
    //   3528: ixor
    //   3529: ldc 252645135
    //   3531: iand
    //   3532: istore #22
    //   3534: iload #23
    //   3536: iload #22
    //   3538: ixor
    //   3539: istore #23
    //   3541: iload #24
    //   3543: iload #22
    //   3545: iconst_4
    //   3546: ishl
    //   3547: ixor
    //   3548: istore #24
    //   3550: iload #24
    //   3552: bipush #16
    //   3554: iushr
    //   3555: iload #23
    //   3557: ixor
    //   3558: ldc 65535
    //   3560: iand
    //   3561: istore #22
    //   3563: iload #23
    //   3565: iload #22
    //   3567: ixor
    //   3568: istore #23
    //   3570: iload #24
    //   3572: iload #22
    //   3574: bipush #16
    //   3576: ishl
    //   3577: ixor
    //   3578: istore #24
    //   3580: iload #23
    //   3582: iconst_2
    //   3583: iushr
    //   3584: iload #24
    //   3586: ixor
    //   3587: ldc 858993459
    //   3589: iand
    //   3590: istore #22
    //   3592: iload #24
    //   3594: iload #22
    //   3596: ixor
    //   3597: istore #24
    //   3599: iload #23
    //   3601: iload #22
    //   3603: iconst_2
    //   3604: ishl
    //   3605: ixor
    //   3606: istore #23
    //   3608: iload #23
    //   3610: bipush #8
    //   3612: iushr
    //   3613: iload #24
    //   3615: ixor
    //   3616: ldc 16711935
    //   3618: iand
    //   3619: istore #22
    //   3621: iload #24
    //   3623: iload #22
    //   3625: ixor
    //   3626: istore #24
    //   3628: iload #23
    //   3630: iload #22
    //   3632: bipush #8
    //   3634: ishl
    //   3635: ixor
    //   3636: istore #23
    //   3638: iload #23
    //   3640: iconst_1
    //   3641: ishl
    //   3642: iload #23
    //   3644: bipush #31
    //   3646: iushr
    //   3647: iconst_1
    //   3648: iand
    //   3649: ior
    //   3650: istore #23
    //   3652: iload #24
    //   3654: iload #23
    //   3656: ixor
    //   3657: ldc -1431655766
    //   3659: iand
    //   3660: istore #22
    //   3662: iload #24
    //   3664: iload #22
    //   3666: ixor
    //   3667: istore #24
    //   3669: iload #23
    //   3671: iload #22
    //   3673: ixor
    //   3674: istore #23
    //   3676: iload #24
    //   3678: iconst_1
    //   3679: ishl
    //   3680: iload #24
    //   3682: bipush #31
    //   3684: iushr
    //   3685: iconst_1
    //   3686: iand
    //   3687: ior
    //   3688: istore #24
    //   3690: iconst_0
    //   3691: istore #25
    //   3693: iload #25
    //   3695: bipush #8
    //   3697: if_icmpge -> 4035
    //   3700: iload #23
    //   3702: bipush #28
    //   3704: ishl
    //   3705: iload #23
    //   3707: iconst_4
    //   3708: iushr
    //   3709: ior
    //   3710: istore #22
    //   3712: iload #22
    //   3714: aload #5
    //   3716: iload #26
    //   3718: iinc #26, 1
    //   3721: iaload
    //   3722: ixor
    //   3723: istore #22
    //   3725: aload #14
    //   3727: iload #22
    //   3729: bipush #63
    //   3731: iand
    //   3732: iaload
    //   3733: istore #21
    //   3735: iload #21
    //   3737: aload #12
    //   3739: iload #22
    //   3741: bipush #8
    //   3743: iushr
    //   3744: bipush #63
    //   3746: iand
    //   3747: iaload
    //   3748: ior
    //   3749: istore #21
    //   3751: iload #21
    //   3753: aload #10
    //   3755: iload #22
    //   3757: bipush #16
    //   3759: iushr
    //   3760: bipush #63
    //   3762: iand
    //   3763: iaload
    //   3764: ior
    //   3765: istore #21
    //   3767: iload #21
    //   3769: aload #8
    //   3771: iload #22
    //   3773: bipush #24
    //   3775: iushr
    //   3776: bipush #63
    //   3778: iand
    //   3779: iaload
    //   3780: ior
    //   3781: istore #21
    //   3783: iload #23
    //   3785: aload #5
    //   3787: iload #26
    //   3789: iinc #26, 1
    //   3792: iaload
    //   3793: ixor
    //   3794: istore #22
    //   3796: iload #21
    //   3798: aload #15
    //   3800: iload #22
    //   3802: bipush #63
    //   3804: iand
    //   3805: iaload
    //   3806: ior
    //   3807: istore #21
    //   3809: iload #21
    //   3811: aload #13
    //   3813: iload #22
    //   3815: bipush #8
    //   3817: iushr
    //   3818: bipush #63
    //   3820: iand
    //   3821: iaload
    //   3822: ior
    //   3823: istore #21
    //   3825: iload #21
    //   3827: aload #11
    //   3829: iload #22
    //   3831: bipush #16
    //   3833: iushr
    //   3834: bipush #63
    //   3836: iand
    //   3837: iaload
    //   3838: ior
    //   3839: istore #21
    //   3841: iload #21
    //   3843: aload #9
    //   3845: iload #22
    //   3847: bipush #24
    //   3849: iushr
    //   3850: bipush #63
    //   3852: iand
    //   3853: iaload
    //   3854: ior
    //   3855: istore #21
    //   3857: iload #24
    //   3859: iload #21
    //   3861: ixor
    //   3862: istore #24
    //   3864: iload #24
    //   3866: bipush #28
    //   3868: ishl
    //   3869: iload #24
    //   3871: iconst_4
    //   3872: iushr
    //   3873: ior
    //   3874: istore #22
    //   3876: iload #22
    //   3878: aload #5
    //   3880: iload #26
    //   3882: iinc #26, 1
    //   3885: iaload
    //   3886: ixor
    //   3887: istore #22
    //   3889: aload #14
    //   3891: iload #22
    //   3893: bipush #63
    //   3895: iand
    //   3896: iaload
    //   3897: istore #21
    //   3899: iload #21
    //   3901: aload #12
    //   3903: iload #22
    //   3905: bipush #8
    //   3907: iushr
    //   3908: bipush #63
    //   3910: iand
    //   3911: iaload
    //   3912: ior
    //   3913: istore #21
    //   3915: iload #21
    //   3917: aload #10
    //   3919: iload #22
    //   3921: bipush #16
    //   3923: iushr
    //   3924: bipush #63
    //   3926: iand
    //   3927: iaload
    //   3928: ior
    //   3929: istore #21
    //   3931: iload #21
    //   3933: aload #8
    //   3935: iload #22
    //   3937: bipush #24
    //   3939: iushr
    //   3940: bipush #63
    //   3942: iand
    //   3943: iaload
    //   3944: ior
    //   3945: istore #21
    //   3947: iload #24
    //   3949: aload #5
    //   3951: iload #26
    //   3953: iinc #26, 1
    //   3956: iaload
    //   3957: ixor
    //   3958: istore #22
    //   3960: iload #21
    //   3962: aload #15
    //   3964: iload #22
    //   3966: bipush #63
    //   3968: iand
    //   3969: iaload
    //   3970: ior
    //   3971: istore #21
    //   3973: iload #21
    //   3975: aload #13
    //   3977: iload #22
    //   3979: bipush #8
    //   3981: iushr
    //   3982: bipush #63
    //   3984: iand
    //   3985: iaload
    //   3986: ior
    //   3987: istore #21
    //   3989: iload #21
    //   3991: aload #11
    //   3993: iload #22
    //   3995: bipush #16
    //   3997: iushr
    //   3998: bipush #63
    //   4000: iand
    //   4001: iaload
    //   4002: ior
    //   4003: istore #21
    //   4005: iload #21
    //   4007: aload #9
    //   4009: iload #22
    //   4011: bipush #24
    //   4013: iushr
    //   4014: bipush #63
    //   4016: iand
    //   4017: iaload
    //   4018: ior
    //   4019: istore #21
    //   4021: iload #23
    //   4023: iload #21
    //   4025: ixor
    //   4026: istore #23
    //   4028: iinc #25, 1
    //   4031: iload_2
    //   4032: ifne -> 3693
    //   4035: iload #23
    //   4037: bipush #31
    //   4039: ishl
    //   4040: iload #23
    //   4042: iconst_1
    //   4043: iushr
    //   4044: ior
    //   4045: istore #23
    //   4047: iload #24
    //   4049: iload #23
    //   4051: ixor
    //   4052: ldc -1431655766
    //   4054: iand
    //   4055: istore #22
    //   4057: iload #24
    //   4059: iload #22
    //   4061: ixor
    //   4062: istore #24
    //   4064: iload #23
    //   4066: iload #22
    //   4068: ixor
    //   4069: istore #23
    //   4071: iload #24
    //   4073: bipush #31
    //   4075: ishl
    //   4076: iload #24
    //   4078: iconst_1
    //   4079: iushr
    //   4080: ior
    //   4081: istore #24
    //   4083: iload #24
    //   4085: bipush #8
    //   4087: iushr
    //   4088: iload #23
    //   4090: ixor
    //   4091: ldc 16711935
    //   4093: iand
    //   4094: istore #22
    //   4096: iload #23
    //   4098: iload #22
    //   4100: ixor
    //   4101: istore #23
    //   4103: iload #24
    //   4105: iload #22
    //   4107: bipush #8
    //   4109: ishl
    //   4110: ixor
    //   4111: istore #24
    //   4113: iload #24
    //   4115: iconst_2
    //   4116: iushr
    //   4117: iload #23
    //   4119: ixor
    //   4120: ldc 858993459
    //   4122: iand
    //   4123: istore #22
    //   4125: iload #23
    //   4127: iload #22
    //   4129: ixor
    //   4130: istore #23
    //   4132: iload #24
    //   4134: iload #22
    //   4136: iconst_2
    //   4137: ishl
    //   4138: ixor
    //   4139: istore #24
    //   4141: iload #23
    //   4143: bipush #16
    //   4145: iushr
    //   4146: iload #24
    //   4148: ixor
    //   4149: ldc 65535
    //   4151: iand
    //   4152: istore #22
    //   4154: iload #24
    //   4156: iload #22
    //   4158: ixor
    //   4159: istore #24
    //   4161: iload #23
    //   4163: iload #22
    //   4165: bipush #16
    //   4167: ishl
    //   4168: ixor
    //   4169: istore #23
    //   4171: iload #23
    //   4173: iconst_4
    //   4174: iushr
    //   4175: iload #24
    //   4177: ixor
    //   4178: ldc 252645135
    //   4180: iand
    //   4181: istore #22
    //   4183: iload #24
    //   4185: iload #22
    //   4187: ixor
    //   4188: istore #24
    //   4190: iload #23
    //   4192: iload #22
    //   4194: iconst_4
    //   4195: ishl
    //   4196: ixor
    //   4197: istore #23
    //   4199: aload #17
    //   4201: iconst_0
    //   4202: iload #23
    //   4204: iastore
    //   4205: aload #17
    //   4207: iconst_1
    //   4208: iload #24
    //   4210: iastore
    //   4211: iload #19
    //   4213: bipush #8
    //   4215: imul
    //   4216: istore #27
    //   4218: iconst_0
    //   4219: istore #28
    //   4221: iload #28
    //   4223: iconst_2
    //   4224: if_icmpge -> 4313
    //   4227: aload #4
    //   4229: iload #27
    //   4231: iload #28
    //   4233: iconst_4
    //   4234: imul
    //   4235: iadd
    //   4236: aload #17
    //   4238: iload #28
    //   4240: iaload
    //   4241: bipush #24
    //   4243: iushr
    //   4244: i2b
    //   4245: bastore
    //   4246: aload #4
    //   4248: iload #27
    //   4250: iload #28
    //   4252: iconst_4
    //   4253: imul
    //   4254: iadd
    //   4255: iconst_1
    //   4256: iadd
    //   4257: aload #17
    //   4259: iload #28
    //   4261: iaload
    //   4262: bipush #16
    //   4264: iushr
    //   4265: i2b
    //   4266: bastore
    //   4267: aload #4
    //   4269: iload #27
    //   4271: iload #28
    //   4273: iconst_4
    //   4274: imul
    //   4275: iadd
    //   4276: iconst_2
    //   4277: iadd
    //   4278: aload #17
    //   4280: iload #28
    //   4282: iaload
    //   4283: bipush #8
    //   4285: iushr
    //   4286: i2b
    //   4287: bastore
    //   4288: aload #4
    //   4290: iload #27
    //   4292: iload #28
    //   4294: iconst_4
    //   4295: imul
    //   4296: iadd
    //   4297: iconst_3
    //   4298: iadd
    //   4299: aload #17
    //   4301: iload #28
    //   4303: iaload
    //   4304: i2b
    //   4305: bastore
    //   4306: iinc #28, 1
    //   4309: iload_2
    //   4310: ifne -> 4221
    //   4313: iinc #19, 1
    //   4316: iload_2
    //   4317: ifne -> 3402
    //   4320: new java/math/BigInteger
    //   4323: dup
    //   4324: aload #4
    //   4326: invokespecial <init> : ([B)V
    //   4329: invokevirtual abs : ()Ljava/math/BigInteger;
    //   4332: putstatic burp/Zzip.ZW : Ljava/lang/Object;
    //   4335: getstatic burp/Zk9s.ZY : Ljava/lang/Object;
    //   4338: checkcast java/math/BigInteger
    //   4341: invokevirtual toByteArray : ()[B
    //   4344: astore_3
    //   4345: bipush #64
    //   4347: newarray byte
    //   4349: dup
    //   4350: iconst_0
    //   4351: bipush #-128
    //   4353: bastore
    //   4354: dup
    //   4355: iconst_1
    //   4356: iconst_0
    //   4357: bastore
    //   4358: dup
    //   4359: iconst_2
    //   4360: iconst_0
    //   4361: bastore
    //   4362: dup
    //   4363: iconst_3
    //   4364: iconst_0
    //   4365: bastore
    //   4366: dup
    //   4367: iconst_4
    //   4368: iconst_0
    //   4369: bastore
    //   4370: dup
    //   4371: iconst_5
    //   4372: iconst_0
    //   4373: bastore
    //   4374: dup
    //   4375: bipush #6
    //   4377: iconst_0
    //   4378: bastore
    //   4379: dup
    //   4380: bipush #7
    //   4382: iconst_0
    //   4383: bastore
    //   4384: dup
    //   4385: bipush #8
    //   4387: iconst_0
    //   4388: bastore
    //   4389: dup
    //   4390: bipush #9
    //   4392: iconst_0
    //   4393: bastore
    //   4394: dup
    //   4395: bipush #10
    //   4397: iconst_0
    //   4398: bastore
    //   4399: dup
    //   4400: bipush #11
    //   4402: iconst_0
    //   4403: bastore
    //   4404: dup
    //   4405: bipush #12
    //   4407: iconst_0
    //   4408: bastore
    //   4409: dup
    //   4410: bipush #13
    //   4412: iconst_0
    //   4413: bastore
    //   4414: dup
    //   4415: bipush #14
    //   4417: iconst_0
    //   4418: bastore
    //   4419: dup
    //   4420: bipush #15
    //   4422: iconst_0
    //   4423: bastore
    //   4424: dup
    //   4425: bipush #16
    //   4427: iconst_0
    //   4428: bastore
    //   4429: dup
    //   4430: bipush #17
    //   4432: iconst_0
    //   4433: bastore
    //   4434: dup
    //   4435: bipush #18
    //   4437: iconst_0
    //   4438: bastore
    //   4439: dup
    //   4440: bipush #19
    //   4442: iconst_0
    //   4443: bastore
    //   4444: dup
    //   4445: bipush #20
    //   4447: iconst_0
    //   4448: bastore
    //   4449: dup
    //   4450: bipush #21
    //   4452: iconst_0
    //   4453: bastore
    //   4454: dup
    //   4455: bipush #22
    //   4457: iconst_0
    //   4458: bastore
    //   4459: dup
    //   4460: bipush #23
    //   4462: iconst_0
    //   4463: bastore
    //   4464: dup
    //   4465: bipush #24
    //   4467: iconst_0
    //   4468: bastore
    //   4469: dup
    //   4470: bipush #25
    //   4472: iconst_0
    //   4473: bastore
    //   4474: dup
    //   4475: bipush #26
    //   4477: iconst_0
    //   4478: bastore
    //   4479: dup
    //   4480: bipush #27
    //   4482: iconst_0
    //   4483: bastore
    //   4484: dup
    //   4485: bipush #28
    //   4487: iconst_0
    //   4488: bastore
    //   4489: dup
    //   4490: bipush #29
    //   4492: iconst_0
    //   4493: bastore
    //   4494: dup
    //   4495: bipush #30
    //   4497: iconst_0
    //   4498: bastore
    //   4499: dup
    //   4500: bipush #31
    //   4502: iconst_0
    //   4503: bastore
    //   4504: dup
    //   4505: bipush #32
    //   4507: iconst_0
    //   4508: bastore
    //   4509: dup
    //   4510: bipush #33
    //   4512: iconst_0
    //   4513: bastore
    //   4514: dup
    //   4515: bipush #34
    //   4517: iconst_0
    //   4518: bastore
    //   4519: dup
    //   4520: bipush #35
    //   4522: iconst_0
    //   4523: bastore
    //   4524: dup
    //   4525: bipush #36
    //   4527: iconst_0
    //   4528: bastore
    //   4529: dup
    //   4530: bipush #37
    //   4532: iconst_0
    //   4533: bastore
    //   4534: dup
    //   4535: bipush #38
    //   4537: iconst_0
    //   4538: bastore
    //   4539: dup
    //   4540: bipush #39
    //   4542: iconst_0
    //   4543: bastore
    //   4544: dup
    //   4545: bipush #40
    //   4547: iconst_0
    //   4548: bastore
    //   4549: dup
    //   4550: bipush #41
    //   4552: iconst_0
    //   4553: bastore
    //   4554: dup
    //   4555: bipush #42
    //   4557: iconst_0
    //   4558: bastore
    //   4559: dup
    //   4560: bipush #43
    //   4562: iconst_0
    //   4563: bastore
    //   4564: dup
    //   4565: bipush #44
    //   4567: iconst_0
    //   4568: bastore
    //   4569: dup
    //   4570: bipush #45
    //   4572: iconst_0
    //   4573: bastore
    //   4574: dup
    //   4575: bipush #46
    //   4577: iconst_0
    //   4578: bastore
    //   4579: dup
    //   4580: bipush #47
    //   4582: iconst_0
    //   4583: bastore
    //   4584: dup
    //   4585: bipush #48
    //   4587: iconst_0
    //   4588: bastore
    //   4589: dup
    //   4590: bipush #49
    //   4592: iconst_0
    //   4593: bastore
    //   4594: dup
    //   4595: bipush #50
    //   4597: iconst_0
    //   4598: bastore
    //   4599: dup
    //   4600: bipush #51
    //   4602: iconst_0
    //   4603: bastore
    //   4604: dup
    //   4605: bipush #52
    //   4607: iconst_0
    //   4608: bastore
    //   4609: dup
    //   4610: bipush #53
    //   4612: iconst_0
    //   4613: bastore
    //   4614: dup
    //   4615: bipush #54
    //   4617: iconst_0
    //   4618: bastore
    //   4619: dup
    //   4620: bipush #55
    //   4622: iconst_0
    //   4623: bastore
    //   4624: dup
    //   4625: bipush #56
    //   4627: iconst_0
    //   4628: bastore
    //   4629: dup
    //   4630: bipush #57
    //   4632: iconst_0
    //   4633: bastore
    //   4634: dup
    //   4635: bipush #58
    //   4637: iconst_0
    //   4638: bastore
    //   4639: dup
    //   4640: bipush #59
    //   4642: iconst_0
    //   4643: bastore
    //   4644: dup
    //   4645: bipush #60
    //   4647: iconst_0
    //   4648: bastore
    //   4649: dup
    //   4650: bipush #61
    //   4652: iconst_0
    //   4653: bastore
    //   4654: dup
    //   4655: bipush #62
    //   4657: iconst_0
    //   4658: bastore
    //   4659: dup
    //   4660: bipush #63
    //   4662: iconst_0
    //   4663: bastore
    //   4664: astore #5
    //   4666: bipush #64
    //   4668: newarray int
    //   4670: dup
    //   4671: iconst_0
    //   4672: ldc 1116352408
    //   4674: iastore
    //   4675: dup
    //   4676: iconst_1
    //   4677: ldc 1899447441
    //   4679: iastore
    //   4680: dup
    //   4681: iconst_2
    //   4682: ldc -1245643825
    //   4684: iastore
    //   4685: dup
    //   4686: iconst_3
    //   4687: ldc -373957723
    //   4689: iastore
    //   4690: dup
    //   4691: iconst_4
    //   4692: ldc 961987163
    //   4694: iastore
    //   4695: dup
    //   4696: iconst_5
    //   4697: ldc 1508970993
    //   4699: iastore
    //   4700: dup
    //   4701: bipush #6
    //   4703: ldc -1841331548
    //   4705: iastore
    //   4706: dup
    //   4707: bipush #7
    //   4709: ldc -1424204075
    //   4711: iastore
    //   4712: dup
    //   4713: bipush #8
    //   4715: ldc -670586216
    //   4717: iastore
    //   4718: dup
    //   4719: bipush #9
    //   4721: ldc 310598401
    //   4723: iastore
    //   4724: dup
    //   4725: bipush #10
    //   4727: ldc 607225278
    //   4729: iastore
    //   4730: dup
    //   4731: bipush #11
    //   4733: ldc 1426881987
    //   4735: iastore
    //   4736: dup
    //   4737: bipush #12
    //   4739: ldc 1925078388
    //   4741: iastore
    //   4742: dup
    //   4743: bipush #13
    //   4745: ldc -2132889090
    //   4747: iastore
    //   4748: dup
    //   4749: bipush #14
    //   4751: ldc -1680079193
    //   4753: iastore
    //   4754: dup
    //   4755: bipush #15
    //   4757: ldc -1046744716
    //   4759: iastore
    //   4760: dup
    //   4761: bipush #16
    //   4763: ldc -459576895
    //   4765: iastore
    //   4766: dup
    //   4767: bipush #17
    //   4769: ldc -272742522
    //   4771: iastore
    //   4772: dup
    //   4773: bipush #18
    //   4775: ldc 264347078
    //   4777: iastore
    //   4778: dup
    //   4779: bipush #19
    //   4781: ldc 604807628
    //   4783: iastore
    //   4784: dup
    //   4785: bipush #20
    //   4787: ldc 770255983
    //   4789: iastore
    //   4790: dup
    //   4791: bipush #21
    //   4793: ldc 1249150122
    //   4795: iastore
    //   4796: dup
    //   4797: bipush #22
    //   4799: ldc 1555081692
    //   4801: iastore
    //   4802: dup
    //   4803: bipush #23
    //   4805: ldc 1996064986
    //   4807: iastore
    //   4808: dup
    //   4809: bipush #24
    //   4811: ldc -1740746414
    //   4813: iastore
    //   4814: dup
    //   4815: bipush #25
    //   4817: ldc -1473132947
    //   4819: iastore
    //   4820: dup
    //   4821: bipush #26
    //   4823: ldc -1341970488
    //   4825: iastore
    //   4826: dup
    //   4827: bipush #27
    //   4829: ldc -1084653625
    //   4831: iastore
    //   4832: dup
    //   4833: bipush #28
    //   4835: ldc -958395405
    //   4837: iastore
    //   4838: dup
    //   4839: bipush #29
    //   4841: ldc -710438585
    //   4843: iastore
    //   4844: dup
    //   4845: bipush #30
    //   4847: ldc 113926993
    //   4849: iastore
    //   4850: dup
    //   4851: bipush #31
    //   4853: ldc 338241895
    //   4855: iastore
    //   4856: dup
    //   4857: bipush #32
    //   4859: ldc 666307205
    //   4861: iastore
    //   4862: dup
    //   4863: bipush #33
    //   4865: ldc 773529912
    //   4867: iastore
    //   4868: dup
    //   4869: bipush #34
    //   4871: ldc 1294757372
    //   4873: iastore
    //   4874: dup
    //   4875: bipush #35
    //   4877: ldc 1396182291
    //   4879: iastore
    //   4880: dup
    //   4881: bipush #36
    //   4883: ldc 1695183700
    //   4885: iastore
    //   4886: dup
    //   4887: bipush #37
    //   4889: ldc 1986661051
    //   4891: iastore
    //   4892: dup
    //   4893: bipush #38
    //   4895: ldc -2117940946
    //   4897: iastore
    //   4898: dup
    //   4899: bipush #39
    //   4901: ldc -1838011259
    //   4903: iastore
    //   4904: dup
    //   4905: bipush #40
    //   4907: ldc -1564481375
    //   4909: iastore
    //   4910: dup
    //   4911: bipush #41
    //   4913: ldc -1474664885
    //   4915: iastore
    //   4916: dup
    //   4917: bipush #42
    //   4919: ldc -1035236496
    //   4921: iastore
    //   4922: dup
    //   4923: bipush #43
    //   4925: ldc -949202525
    //   4927: iastore
    //   4928: dup
    //   4929: bipush #44
    //   4931: ldc -778901479
    //   4933: iastore
    //   4934: dup
    //   4935: bipush #45
    //   4937: ldc -694614492
    //   4939: iastore
    //   4940: dup
    //   4941: bipush #46
    //   4943: ldc -200395387
    //   4945: iastore
    //   4946: dup
    //   4947: bipush #47
    //   4949: ldc 275423344
    //   4951: iastore
    //   4952: dup
    //   4953: bipush #48
    //   4955: ldc 430227734
    //   4957: iastore
    //   4958: dup
    //   4959: bipush #49
    //   4961: ldc 506948616
    //   4963: iastore
    //   4964: dup
    //   4965: bipush #50
    //   4967: ldc 659060556
    //   4969: iastore
    //   4970: dup
    //   4971: bipush #51
    //   4973: ldc 883997877
    //   4975: iastore
    //   4976: dup
    //   4977: bipush #52
    //   4979: ldc 958139571
    //   4981: iastore
    //   4982: dup
    //   4983: bipush #53
    //   4985: ldc 1322822218
    //   4987: iastore
    //   4988: dup
    //   4989: bipush #54
    //   4991: ldc 1537002063
    //   4993: iastore
    //   4994: dup
    //   4995: bipush #55
    //   4997: ldc 1747873779
    //   4999: iastore
    //   5000: dup
    //   5001: bipush #56
    //   5003: ldc 1955562222
    //   5005: iastore
    //   5006: dup
    //   5007: bipush #57
    //   5009: ldc 2024104815
    //   5011: iastore
    //   5012: dup
    //   5013: bipush #58
    //   5015: ldc -2067236844
    //   5017: iastore
    //   5018: dup
    //   5019: bipush #59
    //   5021: ldc -1933114872
    //   5023: iastore
    //   5024: dup
    //   5025: bipush #60
    //   5027: ldc -1866530822
    //   5029: iastore
    //   5030: dup
    //   5031: bipush #61
    //   5033: ldc -1538233109
    //   5035: iastore
    //   5036: dup
    //   5037: bipush #62
    //   5039: ldc -1090935817
    //   5041: iastore
    //   5042: dup
    //   5043: bipush #63
    //   5045: ldc -965641998
    //   5047: iastore
    //   5048: astore #6
    //   5050: iconst_2
    //   5051: newarray int
    //   5053: dup
    //   5054: iconst_0
    //   5055: iconst_0
    //   5056: iastore
    //   5057: dup
    //   5058: iconst_1
    //   5059: iconst_0
    //   5060: iastore
    //   5061: astore #7
    //   5063: bipush #8
    //   5065: newarray int
    //   5067: dup
    //   5068: iconst_0
    //   5069: ldc 1779033703
    //   5071: iastore
    //   5072: dup
    //   5073: iconst_1
    //   5074: ldc -1150833019
    //   5076: iastore
    //   5077: dup
    //   5078: iconst_2
    //   5079: ldc 1013904242
    //   5081: iastore
    //   5082: dup
    //   5083: iconst_3
    //   5084: ldc -1521486534
    //   5086: iastore
    //   5087: dup
    //   5088: iconst_4
    //   5089: ldc 1359893119
    //   5091: iastore
    //   5092: dup
    //   5093: iconst_5
    //   5094: ldc -1694144372
    //   5096: iastore
    //   5097: dup
    //   5098: bipush #6
    //   5100: ldc 528734635
    //   5102: iastore
    //   5103: dup
    //   5104: bipush #7
    //   5106: ldc 1541459225
    //   5108: iastore
    //   5109: astore #8
    //   5111: bipush #64
    //   5113: newarray byte
    //   5115: astore #9
    //   5117: bipush #64
    //   5119: newarray byte
    //   5121: astore #10
    //   5123: aload_3
    //   5124: arraylength
    //   5125: istore #11
    //   5127: aload #7
    //   5129: iconst_0
    //   5130: iaload
    //   5131: bipush #63
    //   5133: iand
    //   5134: istore #12
    //   5136: aload #7
    //   5138: iconst_0
    //   5139: dup2
    //   5140: iaload
    //   5141: iload #11
    //   5143: iadd
    //   5144: iastore
    //   5145: aload #7
    //   5147: iconst_0
    //   5148: dup2
    //   5149: iaload
    //   5150: iconst_m1
    //   5151: iand
    //   5152: iastore
    //   5153: aload #7
    //   5155: iconst_0
    //   5156: iaload
    //   5157: iload #11
    //   5159: if_icmpge -> 5177
    //   5162: aload #7
    //   5164: iconst_1
    //   5165: dup2
    //   5166: iaload
    //   5167: iconst_1
    //   5168: iadd
    //   5169: iastore
    //   5170: goto -> 5177
    //   5173: invokestatic a : (Ljava/lang/Throwable;)Ljava/lang/Throwable;
    //   5176: athrow
    //   5177: iconst_0
    //   5178: istore #13
    //   5180: iload #11
    //   5182: bipush #64
    //   5184: if_icmplt -> 5793
    //   5187: iconst_0
    //   5188: istore #14
    //   5190: iload #14
    //   5192: bipush #64
    //   5194: if_icmpge -> 5216
    //   5197: aload #10
    //   5199: iload #14
    //   5201: aload_3
    //   5202: iload #13
    //   5204: iload #14
    //   5206: iadd
    //   5207: baload
    //   5208: bastore
    //   5209: iinc #14, 1
    //   5212: iload_2
    //   5213: ifne -> 5190
    //   5216: bipush #64
    //   5218: newarray int
    //   5220: astore #14
    //   5222: bipush #8
    //   5224: newarray int
    //   5226: astore #15
    //   5228: iconst_0
    //   5229: istore #16
    //   5231: iload #16
    //   5233: bipush #8
    //   5235: if_icmpge -> 5255
    //   5238: aload #15
    //   5240: iload #16
    //   5242: aload #8
    //   5244: iload #16
    //   5246: iaload
    //   5247: iastore
    //   5248: iinc #16, 1
    //   5251: iload_2
    //   5252: ifne -> 5231
    //   5255: iconst_0
    //   5256: istore #16
    //   5258: iload #16
    //   5260: bipush #64
    //   5262: if_icmpge -> 5753
    //   5265: iload #16
    //   5267: bipush #16
    //   5269: if_icmpge -> 5350
    //   5272: aload #14
    //   5274: iload #16
    //   5276: aload #10
    //   5278: iconst_4
    //   5279: iload #16
    //   5281: imul
    //   5282: baload
    //   5283: sipush #255
    //   5286: iand
    //   5287: bipush #24
    //   5289: ishl
    //   5290: aload #10
    //   5292: iconst_4
    //   5293: iload #16
    //   5295: imul
    //   5296: iconst_1
    //   5297: iadd
    //   5298: baload
    //   5299: sipush #255
    //   5302: iand
    //   5303: bipush #16
    //   5305: ishl
    //   5306: ior
    //   5307: aload #10
    //   5309: iconst_4
    //   5310: iload #16
    //   5312: imul
    //   5313: iconst_2
    //   5314: iadd
    //   5315: baload
    //   5316: sipush #255
    //   5319: iand
    //   5320: bipush #8
    //   5322: ishl
    //   5323: ior
    //   5324: aload #10
    //   5326: iconst_4
    //   5327: iload #16
    //   5329: imul
    //   5330: iconst_3
    //   5331: iadd
    //   5332: baload
    //   5333: sipush #255
    //   5336: iand
    //   5337: ior
    //   5338: iastore
    //   5339: iload_2
    //   5340: ifne -> 5493
    //   5343: goto -> 5350
    //   5346: invokestatic a : (Ljava/lang/Throwable;)Ljava/lang/Throwable;
    //   5349: athrow
    //   5350: aload #14
    //   5352: iload #16
    //   5354: aload #14
    //   5356: iload #16
    //   5358: iconst_2
    //   5359: isub
    //   5360: iaload
    //   5361: bipush #17
    //   5363: iushr
    //   5364: aload #14
    //   5366: iload #16
    //   5368: iconst_2
    //   5369: isub
    //   5370: iaload
    //   5371: bipush #15
    //   5373: ishl
    //   5374: ior
    //   5375: aload #14
    //   5377: iload #16
    //   5379: iconst_2
    //   5380: isub
    //   5381: iaload
    //   5382: bipush #19
    //   5384: iushr
    //   5385: aload #14
    //   5387: iload #16
    //   5389: iconst_2
    //   5390: isub
    //   5391: iaload
    //   5392: bipush #13
    //   5394: ishl
    //   5395: ior
    //   5396: ixor
    //   5397: aload #14
    //   5399: iload #16
    //   5401: iconst_2
    //   5402: isub
    //   5403: iaload
    //   5404: bipush #10
    //   5406: iushr
    //   5407: ixor
    //   5408: aload #14
    //   5410: iload #16
    //   5412: bipush #7
    //   5414: isub
    //   5415: iaload
    //   5416: iadd
    //   5417: aload #14
    //   5419: iload #16
    //   5421: bipush #15
    //   5423: isub
    //   5424: iaload
    //   5425: bipush #7
    //   5427: iushr
    //   5428: aload #14
    //   5430: iload #16
    //   5432: bipush #15
    //   5434: isub
    //   5435: iaload
    //   5436: bipush #25
    //   5438: ishl
    //   5439: ior
    //   5440: aload #14
    //   5442: iload #16
    //   5444: bipush #15
    //   5446: isub
    //   5447: iaload
    //   5448: bipush #18
    //   5450: iushr
    //   5451: aload #14
    //   5453: iload #16
    //   5455: bipush #15
    //   5457: isub
    //   5458: iaload
    //   5459: bipush #14
    //   5461: ishl
    //   5462: ior
    //   5463: ixor
    //   5464: aload #14
    //   5466: iload #16
    //   5468: bipush #15
    //   5470: isub
    //   5471: iaload
    //   5472: iconst_3
    //   5473: iushr
    //   5474: ixor
    //   5475: iadd
    //   5476: aload #14
    //   5478: iload #16
    //   5480: bipush #16
    //   5482: isub
    //   5483: iaload
    //   5484: iadd
    //   5485: iastore
    //   5486: goto -> 5493
    //   5489: invokestatic a : (Ljava/lang/Throwable;)Ljava/lang/Throwable;
    //   5492: athrow
    //   5493: aload #15
    //   5495: bipush #7
    //   5497: iaload
    //   5498: aload #15
    //   5500: iconst_4
    //   5501: iaload
    //   5502: bipush #6
    //   5504: iushr
    //   5505: aload #15
    //   5507: iconst_4
    //   5508: iaload
    //   5509: bipush #26
    //   5511: ishl
    //   5512: ior
    //   5513: aload #15
    //   5515: iconst_4
    //   5516: iaload
    //   5517: bipush #11
    //   5519: iushr
    //   5520: aload #15
    //   5522: iconst_4
    //   5523: iaload
    //   5524: bipush #21
    //   5526: ishl
    //   5527: ior
    //   5528: ixor
    //   5529: aload #15
    //   5531: iconst_4
    //   5532: iaload
    //   5533: bipush #25
    //   5535: iushr
    //   5536: aload #15
    //   5538: iconst_4
    //   5539: iaload
    //   5540: bipush #7
    //   5542: ishl
    //   5543: ior
    //   5544: ixor
    //   5545: iadd
    //   5546: aload #15
    //   5548: bipush #6
    //   5550: iaload
    //   5551: aload #15
    //   5553: iconst_4
    //   5554: iaload
    //   5555: aload #15
    //   5557: iconst_5
    //   5558: iaload
    //   5559: aload #15
    //   5561: bipush #6
    //   5563: iaload
    //   5564: ixor
    //   5565: iand
    //   5566: ixor
    //   5567: iadd
    //   5568: aload #6
    //   5570: iload #16
    //   5572: iaload
    //   5573: iadd
    //   5574: aload #14
    //   5576: iload #16
    //   5578: iaload
    //   5579: iadd
    //   5580: istore #17
    //   5582: aload #15
    //   5584: iconst_0
    //   5585: iaload
    //   5586: iconst_2
    //   5587: iushr
    //   5588: aload #15
    //   5590: iconst_0
    //   5591: iaload
    //   5592: bipush #30
    //   5594: ishl
    //   5595: ior
    //   5596: aload #15
    //   5598: iconst_0
    //   5599: iaload
    //   5600: bipush #13
    //   5602: iushr
    //   5603: aload #15
    //   5605: iconst_0
    //   5606: iaload
    //   5607: bipush #19
    //   5609: ishl
    //   5610: ior
    //   5611: ixor
    //   5612: aload #15
    //   5614: iconst_0
    //   5615: iaload
    //   5616: bipush #22
    //   5618: iushr
    //   5619: aload #15
    //   5621: iconst_0
    //   5622: iaload
    //   5623: bipush #10
    //   5625: ishl
    //   5626: ior
    //   5627: ixor
    //   5628: aload #15
    //   5630: iconst_0
    //   5631: iaload
    //   5632: aload #15
    //   5634: iconst_1
    //   5635: iaload
    //   5636: iand
    //   5637: aload #15
    //   5639: iconst_2
    //   5640: iaload
    //   5641: aload #15
    //   5643: iconst_0
    //   5644: iaload
    //   5645: aload #15
    //   5647: iconst_1
    //   5648: iaload
    //   5649: ior
    //   5650: iand
    //   5651: ior
    //   5652: iadd
    //   5653: istore #18
    //   5655: aload #15
    //   5657: iconst_3
    //   5658: dup2
    //   5659: iaload
    //   5660: iload #17
    //   5662: iadd
    //   5663: iastore
    //   5664: aload #15
    //   5666: bipush #7
    //   5668: iload #17
    //   5670: iload #18
    //   5672: iadd
    //   5673: iastore
    //   5674: aload #15
    //   5676: bipush #7
    //   5678: iaload
    //   5679: istore #17
    //   5681: aload #15
    //   5683: bipush #7
    //   5685: aload #15
    //   5687: bipush #6
    //   5689: iaload
    //   5690: iastore
    //   5691: aload #15
    //   5693: bipush #6
    //   5695: aload #15
    //   5697: iconst_5
    //   5698: iaload
    //   5699: iastore
    //   5700: aload #15
    //   5702: iconst_5
    //   5703: aload #15
    //   5705: iconst_4
    //   5706: iaload
    //   5707: iastore
    //   5708: aload #15
    //   5710: iconst_4
    //   5711: aload #15
    //   5713: iconst_3
    //   5714: iaload
    //   5715: iastore
    //   5716: aload #15
    //   5718: iconst_3
    //   5719: aload #15
    //   5721: iconst_2
    //   5722: iaload
    //   5723: iastore
    //   5724: aload #15
    //   5726: iconst_2
    //   5727: aload #15
    //   5729: iconst_1
    //   5730: iaload
    //   5731: iastore
    //   5732: aload #15
    //   5734: iconst_1
    //   5735: aload #15
    //   5737: iconst_0
    //   5738: iaload
    //   5739: iastore
    //   5740: aload #15
    //   5742: iconst_0
    //   5743: iload #17
    //   5745: iastore
    //   5746: iinc #16, 1
    //   5749: iload_2
    //   5750: ifne -> 5258
    //   5753: iconst_0
    //   5754: istore #16
    //   5756: iload #16
    //   5758: bipush #8
    //   5760: if_icmpge -> 5783
    //   5763: aload #8
    //   5765: iload #16
    //   5767: dup2
    //   5768: iaload
    //   5769: aload #15
    //   5771: iload #16
    //   5773: iaload
    //   5774: iadd
    //   5775: iastore
    //   5776: iinc #16, 1
    //   5779: iload_2
    //   5780: ifne -> 5756
    //   5783: iinc #13, 64
    //   5786: iinc #11, -64
    //   5789: iload_2
    //   5790: ifne -> 5180
    //   5793: iload #11
    //   5795: ifle -> 5830
    //   5798: iconst_0
    //   5799: istore #14
    //   5801: iload #14
    //   5803: iload #11
    //   5805: if_icmpge -> 5830
    //   5808: aload #9
    //   5810: iload #12
    //   5812: iload #14
    //   5814: iadd
    //   5815: aload_3
    //   5816: iload #13
    //   5818: iload #14
    //   5820: iadd
    //   5821: baload
    //   5822: bastore
    //   5823: iinc #14, 1
    //   5826: iload_2
    //   5827: ifne -> 5801
    //   5830: aload #7
    //   5832: iconst_0
    //   5833: iaload
    //   5834: bipush #29
    //   5836: iushr
    //   5837: aload #7
    //   5839: iconst_1
    //   5840: iaload
    //   5841: iconst_3
    //   5842: ishl
    //   5843: ior
    //   5844: istore #14
    //   5846: aload #7
    //   5848: iconst_0
    //   5849: iaload
    //   5850: iconst_3
    //   5851: ishl
    //   5852: istore #15
    //   5854: aload #7
    //   5856: iconst_0
    //   5857: iaload
    //   5858: bipush #63
    //   5860: iand
    //   5861: istore #16
    //   5863: iload #16
    //   5865: bipush #56
    //   5867: if_icmpge -> 5882
    //   5870: bipush #56
    //   5872: iload #16
    //   5874: isub
    //   5875: goto -> 5887
    //   5878: invokestatic a : (Ljava/lang/Throwable;)Ljava/lang/Throwable;
    //   5881: athrow
    //   5882: bipush #120
    //   5884: iload #16
    //   5886: isub
    //   5887: istore #17
    //   5889: aload #7
    //   5891: iconst_0
    //   5892: iaload
    //   5893: bipush #63
    //   5895: iand
    //   5896: istore #12
    //   5898: bipush #64
    //   5900: iload #12
    //   5902: isub
    //   5903: istore #18
    //   5905: aload #7
    //   5907: iconst_0
    //   5908: dup2
    //   5909: iaload
    //   5910: iload #17
    //   5912: iadd
    //   5913: iastore
    //   5914: aload #7
    //   5916: iconst_0
    //   5917: dup2
    //   5918: iaload
    //   5919: iconst_m1
    //   5920: iand
    //   5921: iastore
    //   5922: aload #7
    //   5924: iconst_0
    //   5925: iaload
    //   5926: iload #17
    //   5928: if_icmpge -> 5946
    //   5931: aload #7
    //   5933: iconst_1
    //   5934: dup2
    //   5935: iaload
    //   5936: iconst_1
    //   5937: iadd
    //   5938: iastore
    //   5939: goto -> 5946
    //   5942: invokestatic a : (Ljava/lang/Throwable;)Ljava/lang/Throwable;
    //   5945: athrow
    //   5946: iconst_0
    //   5947: istore #13
    //   5949: iload #12
    //   5951: ifle -> 6582
    //   5954: iload #17
    //   5956: iload #18
    //   5958: if_icmplt -> 6582
    //   5961: goto -> 5968
    //   5964: invokestatic a : (Ljava/lang/Throwable;)Ljava/lang/Throwable;
    //   5967: athrow
    //   5968: iconst_0
    //   5969: istore #19
    //   5971: iload #19
    //   5973: iload #18
    //   5975: if_icmpge -> 5998
    //   5978: aload #9
    //   5980: iload #12
    //   5982: iload #19
    //   5984: iadd
    //   5985: aload #5
    //   5987: iload #19
    //   5989: baload
    //   5990: bastore
    //   5991: iinc #19, 1
    //   5994: iload_2
    //   5995: ifne -> 5971
    //   5998: bipush #64
    //   6000: newarray int
    //   6002: astore #19
    //   6004: bipush #8
    //   6006: newarray int
    //   6008: astore #20
    //   6010: iconst_0
    //   6011: istore #21
    //   6013: iload #21
    //   6015: bipush #8
    //   6017: if_icmpge -> 6037
    //   6020: aload #20
    //   6022: iload #21
    //   6024: aload #8
    //   6026: iload #21
    //   6028: iaload
    //   6029: iastore
    //   6030: iinc #21, 1
    //   6033: iload_2
    //   6034: ifne -> 6013
    //   6037: iconst_0
    //   6038: istore #21
    //   6040: iload #21
    //   6042: bipush #64
    //   6044: if_icmpge -> 6535
    //   6047: iload #21
    //   6049: bipush #16
    //   6051: if_icmpge -> 6132
    //   6054: aload #19
    //   6056: iload #21
    //   6058: aload #9
    //   6060: iconst_4
    //   6061: iload #21
    //   6063: imul
    //   6064: baload
    //   6065: sipush #255
    //   6068: iand
    //   6069: bipush #24
    //   6071: ishl
    //   6072: aload #9
    //   6074: iconst_4
    //   6075: iload #21
    //   6077: imul
    //   6078: iconst_1
    //   6079: iadd
    //   6080: baload
    //   6081: sipush #255
    //   6084: iand
    //   6085: bipush #16
    //   6087: ishl
    //   6088: ior
    //   6089: aload #9
    //   6091: iconst_4
    //   6092: iload #21
    //   6094: imul
    //   6095: iconst_2
    //   6096: iadd
    //   6097: baload
    //   6098: sipush #255
    //   6101: iand
    //   6102: bipush #8
    //   6104: ishl
    //   6105: ior
    //   6106: aload #9
    //   6108: iconst_4
    //   6109: iload #21
    //   6111: imul
    //   6112: iconst_3
    //   6113: iadd
    //   6114: baload
    //   6115: sipush #255
    //   6118: iand
    //   6119: ior
    //   6120: iastore
    //   6121: iload_2
    //   6122: ifne -> 6275
    //   6125: goto -> 6132
    //   6128: invokestatic a : (Ljava/lang/Throwable;)Ljava/lang/Throwable;
    //   6131: athrow
    //   6132: aload #19
    //   6134: iload #21
    //   6136: aload #19
    //   6138: iload #21
    //   6140: iconst_2
    //   6141: isub
    //   6142: iaload
    //   6143: bipush #17
    //   6145: iushr
    //   6146: aload #19
    //   6148: iload #21
    //   6150: iconst_2
    //   6151: isub
    //   6152: iaload
    //   6153: bipush #15
    //   6155: ishl
    //   6156: ior
    //   6157: aload #19
    //   6159: iload #21
    //   6161: iconst_2
    //   6162: isub
    //   6163: iaload
    //   6164: bipush #19
    //   6166: iushr
    //   6167: aload #19
    //   6169: iload #21
    //   6171: iconst_2
    //   6172: isub
    //   6173: iaload
    //   6174: bipush #13
    //   6176: ishl
    //   6177: ior
    //   6178: ixor
    //   6179: aload #19
    //   6181: iload #21
    //   6183: iconst_2
    //   6184: isub
    //   6185: iaload
    //   6186: bipush #10
    //   6188: iushr
    //   6189: ixor
    //   6190: aload #19
    //   6192: iload #21
    //   6194: bipush #7
    //   6196: isub
    //   6197: iaload
    //   6198: iadd
    //   6199: aload #19
    //   6201: iload #21
    //   6203: bipush #15
    //   6205: isub
    //   6206: iaload
    //   6207: bipush #7
    //   6209: iushr
    //   6210: aload #19
    //   6212: iload #21
    //   6214: bipush #15
    //   6216: isub
    //   6217: iaload
    //   6218: bipush #25
    //   6220: ishl
    //   6221: ior
    //   6222: aload #19
    //   6224: iload #21
    //   6226: bipush #15
    //   6228: isub
    //   6229: iaload
    //   6230: bipush #18
    //   6232: iushr
    //   6233: aload #19
    //   6235: iload #21
    //   6237: bipush #15
    //   6239: isub
    //   6240: iaload
    //   6241: bipush #14
    //   6243: ishl
    //   6244: ior
    //   6245: ixor
    //   6246: aload #19
    //   6248: iload #21
    //   6250: bipush #15
    //   6252: isub
    //   6253: iaload
    //   6254: iconst_3
    //   6255: iushr
    //   6256: ixor
    //   6257: iadd
    //   6258: aload #19
    //   6260: iload #21
    //   6262: bipush #16
    //   6264: isub
    //   6265: iaload
    //   6266: iadd
    //   6267: iastore
    //   6268: goto -> 6275
    //   6271: invokestatic a : (Ljava/lang/Throwable;)Ljava/lang/Throwable;
    //   6274: athrow
    //   6275: aload #20
    //   6277: bipush #7
    //   6279: iaload
    //   6280: aload #20
    //   6282: iconst_4
    //   6283: iaload
    //   6284: bipush #6
    //   6286: iushr
    //   6287: aload #20
    //   6289: iconst_4
    //   6290: iaload
    //   6291: bipush #26
    //   6293: ishl
    //   6294: ior
    //   6295: aload #20
    //   6297: iconst_4
    //   6298: iaload
    //   6299: bipush #11
    //   6301: iushr
    //   6302: aload #20
    //   6304: iconst_4
    //   6305: iaload
    //   6306: bipush #21
    //   6308: ishl
    //   6309: ior
    //   6310: ixor
    //   6311: aload #20
    //   6313: iconst_4
    //   6314: iaload
    //   6315: bipush #25
    //   6317: iushr
    //   6318: aload #20
    //   6320: iconst_4
    //   6321: iaload
    //   6322: bipush #7
    //   6324: ishl
    //   6325: ior
    //   6326: ixor
    //   6327: iadd
    //   6328: aload #20
    //   6330: bipush #6
    //   6332: iaload
    //   6333: aload #20
    //   6335: iconst_4
    //   6336: iaload
    //   6337: aload #20
    //   6339: iconst_5
    //   6340: iaload
    //   6341: aload #20
    //   6343: bipush #6
    //   6345: iaload
    //   6346: ixor
    //   6347: iand
    //   6348: ixor
    //   6349: iadd
    //   6350: aload #6
    //   6352: iload #21
    //   6354: iaload
    //   6355: iadd
    //   6356: aload #19
    //   6358: iload #21
    //   6360: iaload
    //   6361: iadd
    //   6362: istore #22
    //   6364: aload #20
    //   6366: iconst_0
    //   6367: iaload
    //   6368: iconst_2
    //   6369: iushr
    //   6370: aload #20
    //   6372: iconst_0
    //   6373: iaload
    //   6374: bipush #30
    //   6376: ishl
    //   6377: ior
    //   6378: aload #20
    //   6380: iconst_0
    //   6381: iaload
    //   6382: bipush #13
    //   6384: iushr
    //   6385: aload #20
    //   6387: iconst_0
    //   6388: iaload
    //   6389: bipush #19
    //   6391: ishl
    //   6392: ior
    //   6393: ixor
    //   6394: aload #20
    //   6396: iconst_0
    //   6397: iaload
    //   6398: bipush #22
    //   6400: iushr
    //   6401: aload #20
    //   6403: iconst_0
    //   6404: iaload
    //   6405: bipush #10
    //   6407: ishl
    //   6408: ior
    //   6409: ixor
    //   6410: aload #20
    //   6412: iconst_0
    //   6413: iaload
    //   6414: aload #20
    //   6416: iconst_1
    //   6417: iaload
    //   6418: iand
    //   6419: aload #20
    //   6421: iconst_2
    //   6422: iaload
    //   6423: aload #20
    //   6425: iconst_0
    //   6426: iaload
    //   6427: aload #20
    //   6429: iconst_1
    //   6430: iaload
    //   6431: ior
    //   6432: iand
    //   6433: ior
    //   6434: iadd
    //   6435: istore #23
    //   6437: aload #20
    //   6439: iconst_3
    //   6440: dup2
    //   6441: iaload
    //   6442: iload #22
    //   6444: iadd
    //   6445: iastore
    //   6446: aload #20
    //   6448: bipush #7
    //   6450: iload #22
    //   6452: iload #23
    //   6454: iadd
    //   6455: iastore
    //   6456: aload #20
    //   6458: bipush #7
    //   6460: iaload
    //   6461: istore #22
    //   6463: aload #20
    //   6465: bipush #7
    //   6467: aload #20
    //   6469: bipush #6
    //   6471: iaload
    //   6472: iastore
    //   6473: aload #20
    //   6475: bipush #6
    //   6477: aload #20
    //   6479: iconst_5
    //   6480: iaload
    //   6481: iastore
    //   6482: aload #20
    //   6484: iconst_5
    //   6485: aload #20
    //   6487: iconst_4
    //   6488: iaload
    //   6489: iastore
    //   6490: aload #20
    //   6492: iconst_4
    //   6493: aload #20
    //   6495: iconst_3
    //   6496: iaload
    //   6497: iastore
    //   6498: aload #20
    //   6500: iconst_3
    //   6501: aload #20
    //   6503: iconst_2
    //   6504: iaload
    //   6505: iastore
    //   6506: aload #20
    //   6508: iconst_2
    //   6509: aload #20
    //   6511: iconst_1
    //   6512: iaload
    //   6513: iastore
    //   6514: aload #20
    //   6516: iconst_1
    //   6517: aload #20
    //   6519: iconst_0
    //   6520: iaload
    //   6521: iastore
    //   6522: aload #20
    //   6524: iconst_0
    //   6525: iload #22
    //   6527: iastore
    //   6528: iinc #21, 1
    //   6531: iload_2
    //   6532: ifne -> 6040
    //   6535: iconst_0
    //   6536: istore #21
    //   6538: iload #21
    //   6540: bipush #8
    //   6542: if_icmpge -> 6565
    //   6545: aload #8
    //   6547: iload #21
    //   6549: dup2
    //   6550: iaload
    //   6551: aload #20
    //   6553: iload #21
    //   6555: iaload
    //   6556: iadd
    //   6557: iastore
    //   6558: iinc #21, 1
    //   6561: iload_2
    //   6562: ifne -> 6538
    //   6565: iload #13
    //   6567: iload #18
    //   6569: iadd
    //   6570: istore #13
    //   6572: iload #17
    //   6574: iload #18
    //   6576: isub
    //   6577: istore #17
    //   6579: iconst_0
    //   6580: istore #12
    //   6582: iload #17
    //   6584: bipush #64
    //   6586: if_icmplt -> 7196
    //   6589: iconst_0
    //   6590: istore #19
    //   6592: iload #19
    //   6594: bipush #64
    //   6596: if_icmpge -> 6619
    //   6599: aload #10
    //   6601: iload #19
    //   6603: aload #5
    //   6605: iload #13
    //   6607: iload #19
    //   6609: iadd
    //   6610: baload
    //   6611: bastore
    //   6612: iinc #19, 1
    //   6615: iload_2
    //   6616: ifne -> 6592
    //   6619: bipush #64
    //   6621: newarray int
    //   6623: astore #19
    //   6625: bipush #8
    //   6627: newarray int
    //   6629: astore #20
    //   6631: iconst_0
    //   6632: istore #21
    //   6634: iload #21
    //   6636: bipush #8
    //   6638: if_icmpge -> 6658
    //   6641: aload #20
    //   6643: iload #21
    //   6645: aload #8
    //   6647: iload #21
    //   6649: iaload
    //   6650: iastore
    //   6651: iinc #21, 1
    //   6654: iload_2
    //   6655: ifne -> 6634
    //   6658: iconst_0
    //   6659: istore #21
    //   6661: iload #21
    //   6663: bipush #64
    //   6665: if_icmpge -> 7156
    //   6668: iload #21
    //   6670: bipush #16
    //   6672: if_icmpge -> 6753
    //   6675: aload #19
    //   6677: iload #21
    //   6679: aload #10
    //   6681: iconst_4
    //   6682: iload #21
    //   6684: imul
    //   6685: baload
    //   6686: sipush #255
    //   6689: iand
    //   6690: bipush #24
    //   6692: ishl
    //   6693: aload #10
    //   6695: iconst_4
    //   6696: iload #21
    //   6698: imul
    //   6699: iconst_1
    //   6700: iadd
    //   6701: baload
    //   6702: sipush #255
    //   6705: iand
    //   6706: bipush #16
    //   6708: ishl
    //   6709: ior
    //   6710: aload #10
    //   6712: iconst_4
    //   6713: iload #21
    //   6715: imul
    //   6716: iconst_2
    //   6717: iadd
    //   6718: baload
    //   6719: sipush #255
    //   6722: iand
    //   6723: bipush #8
    //   6725: ishl
    //   6726: ior
    //   6727: aload #10
    //   6729: iconst_4
    //   6730: iload #21
    //   6732: imul
    //   6733: iconst_3
    //   6734: iadd
    //   6735: baload
    //   6736: sipush #255
    //   6739: iand
    //   6740: ior
    //   6741: iastore
    //   6742: iload_2
    //   6743: ifne -> 6896
    //   6746: goto -> 6753
    //   6749: invokestatic a : (Ljava/lang/Throwable;)Ljava/lang/Throwable;
    //   6752: athrow
    //   6753: aload #19
    //   6755: iload #21
    //   6757: aload #19
    //   6759: iload #21
    //   6761: iconst_2
    //   6762: isub
    //   6763: iaload
    //   6764: bipush #17
    //   6766: iushr
    //   6767: aload #19
    //   6769: iload #21
    //   6771: iconst_2
    //   6772: isub
    //   6773: iaload
    //   6774: bipush #15
    //   6776: ishl
    //   6777: ior
    //   6778: aload #19
    //   6780: iload #21
    //   6782: iconst_2
    //   6783: isub
    //   6784: iaload
    //   6785: bipush #19
    //   6787: iushr
    //   6788: aload #19
    //   6790: iload #21
    //   6792: iconst_2
    //   6793: isub
    //   6794: iaload
    //   6795: bipush #13
    //   6797: ishl
    //   6798: ior
    //   6799: ixor
    //   6800: aload #19
    //   6802: iload #21
    //   6804: iconst_2
    //   6805: isub
    //   6806: iaload
    //   6807: bipush #10
    //   6809: iushr
    //   6810: ixor
    //   6811: aload #19
    //   6813: iload #21
    //   6815: bipush #7
    //   6817: isub
    //   6818: iaload
    //   6819: iadd
    //   6820: aload #19
    //   6822: iload #21
    //   6824: bipush #15
    //   6826: isub
    //   6827: iaload
    //   6828: bipush #7
    //   6830: iushr
    //   6831: aload #19
    //   6833: iload #21
    //   6835: bipush #15
    //   6837: isub
    //   6838: iaload
    //   6839: bipush #25
    //   6841: ishl
    //   6842: ior
    //   6843: aload #19
    //   6845: iload #21
    //   6847: bipush #15
    //   6849: isub
    //   6850: iaload
    //   6851: bipush #18
    //   6853: iushr
    //   6854: aload #19
    //   6856: iload #21
    //   6858: bipush #15
    //   6860: isub
    //   6861: iaload
    //   6862: bipush #14
    //   6864: ishl
    //   6865: ior
    //   6866: ixor
    //   6867: aload #19
    //   6869: iload #21
    //   6871: bipush #15
    //   6873: isub
    //   6874: iaload
    //   6875: iconst_3
    //   6876: iushr
    //   6877: ixor
    //   6878: iadd
    //   6879: aload #19
    //   6881: iload #21
    //   6883: bipush #16
    //   6885: isub
    //   6886: iaload
    //   6887: iadd
    //   6888: iastore
    //   6889: goto -> 6896
    //   6892: invokestatic a : (Ljava/lang/Throwable;)Ljava/lang/Throwable;
    //   6895: athrow
    //   6896: aload #20
    //   6898: bipush #7
    //   6900: iaload
    //   6901: aload #20
    //   6903: iconst_4
    //   6904: iaload
    //   6905: bipush #6
    //   6907: iushr
    //   6908: aload #20
    //   6910: iconst_4
    //   6911: iaload
    //   6912: bipush #26
    //   6914: ishl
    //   6915: ior
    //   6916: aload #20
    //   6918: iconst_4
    //   6919: iaload
    //   6920: bipush #11
    //   6922: iushr
    //   6923: aload #20
    //   6925: iconst_4
    //   6926: iaload
    //   6927: bipush #21
    //   6929: ishl
    //   6930: ior
    //   6931: ixor
    //   6932: aload #20
    //   6934: iconst_4
    //   6935: iaload
    //   6936: bipush #25
    //   6938: iushr
    //   6939: aload #20
    //   6941: iconst_4
    //   6942: iaload
    //   6943: bipush #7
    //   6945: ishl
    //   6946: ior
    //   6947: ixor
    //   6948: iadd
    //   6949: aload #20
    //   6951: bipush #6
    //   6953: iaload
    //   6954: aload #20
    //   6956: iconst_4
    //   6957: iaload
    //   6958: aload #20
    //   6960: iconst_5
    //   6961: iaload
    //   6962: aload #20
    //   6964: bipush #6
    //   6966: iaload
    //   6967: ixor
    //   6968: iand
    //   6969: ixor
    //   6970: iadd
    //   6971: aload #6
    //   6973: iload #21
    //   6975: iaload
    //   6976: iadd
    //   6977: aload #19
    //   6979: iload #21
    //   6981: iaload
    //   6982: iadd
    //   6983: istore #22
    //   6985: aload #20
    //   6987: iconst_0
    //   6988: iaload
    //   6989: iconst_2
    //   6990: iushr
    //   6991: aload #20
    //   6993: iconst_0
    //   6994: iaload
    //   6995: bipush #30
    //   6997: ishl
    //   6998: ior
    //   6999: aload #20
    //   7001: iconst_0
    //   7002: iaload
    //   7003: bipush #13
    //   7005: iushr
    //   7006: aload #20
    //   7008: iconst_0
    //   7009: iaload
    //   7010: bipush #19
    //   7012: ishl
    //   7013: ior
    //   7014: ixor
    //   7015: aload #20
    //   7017: iconst_0
    //   7018: iaload
    //   7019: bipush #22
    //   7021: iushr
    //   7022: aload #20
    //   7024: iconst_0
    //   7025: iaload
    //   7026: bipush #10
    //   7028: ishl
    //   7029: ior
    //   7030: ixor
    //   7031: aload #20
    //   7033: iconst_0
    //   7034: iaload
    //   7035: aload #20
    //   7037: iconst_1
    //   7038: iaload
    //   7039: iand
    //   7040: aload #20
    //   7042: iconst_2
    //   7043: iaload
    //   7044: aload #20
    //   7046: iconst_0
    //   7047: iaload
    //   7048: aload #20
    //   7050: iconst_1
    //   7051: iaload
    //   7052: ior
    //   7053: iand
    //   7054: ior
    //   7055: iadd
    //   7056: istore #23
    //   7058: aload #20
    //   7060: iconst_3
    //   7061: dup2
    //   7062: iaload
    //   7063: iload #22
    //   7065: iadd
    //   7066: iastore
    //   7067: aload #20
    //   7069: bipush #7
    //   7071: iload #22
    //   7073: iload #23
    //   7075: iadd
    //   7076: iastore
    //   7077: aload #20
    //   7079: bipush #7
    //   7081: iaload
    //   7082: istore #22
    //   7084: aload #20
    //   7086: bipush #7
    //   7088: aload #20
    //   7090: bipush #6
    //   7092: iaload
    //   7093: iastore
    //   7094: aload #20
    //   7096: bipush #6
    //   7098: aload #20
    //   7100: iconst_5
    //   7101: iaload
    //   7102: iastore
    //   7103: aload #20
    //   7105: iconst_5
    //   7106: aload #20
    //   7108: iconst_4
    //   7109: iaload
    //   7110: iastore
    //   7111: aload #20
    //   7113: iconst_4
    //   7114: aload #20
    //   7116: iconst_3
    //   7117: iaload
    //   7118: iastore
    //   7119: aload #20
    //   7121: iconst_3
    //   7122: aload #20
    //   7124: iconst_2
    //   7125: iaload
    //   7126: iastore
    //   7127: aload #20
    //   7129: iconst_2
    //   7130: aload #20
    //   7132: iconst_1
    //   7133: iaload
    //   7134: iastore
    //   7135: aload #20
    //   7137: iconst_1
    //   7138: aload #20
    //   7140: iconst_0
    //   7141: iaload
    //   7142: iastore
    //   7143: aload #20
    //   7145: iconst_0
    //   7146: iload #22
    //   7148: iastore
    //   7149: iinc #21, 1
    //   7152: iload_2
    //   7153: ifne -> 6661
    //   7156: iconst_0
    //   7157: istore #21
    //   7159: iload #21
    //   7161: bipush #8
    //   7163: if_icmpge -> 7186
    //   7166: aload #8
    //   7168: iload #21
    //   7170: dup2
    //   7171: iaload
    //   7172: aload #20
    //   7174: iload #21
    //   7176: iaload
    //   7177: iadd
    //   7178: iastore
    //   7179: iinc #21, 1
    //   7182: iload_2
    //   7183: ifne -> 7159
    //   7186: iinc #13, 64
    //   7189: iinc #17, -64
    //   7192: iload_2
    //   7193: ifne -> 6582
    //   7196: iload #17
    //   7198: ifle -> 7234
    //   7201: iconst_0
    //   7202: istore #19
    //   7204: iload #19
    //   7206: iload #17
    //   7208: if_icmpge -> 7234
    //   7211: aload #9
    //   7213: iload #12
    //   7215: iload #19
    //   7217: iadd
    //   7218: aload #5
    //   7220: iload #13
    //   7222: iload #19
    //   7224: iadd
    //   7225: baload
    //   7226: bastore
    //   7227: iinc #19, 1
    //   7230: iload_2
    //   7231: ifne -> 7204
    //   7234: bipush #8
    //   7236: newarray byte
    //   7238: astore #19
    //   7240: aload #19
    //   7242: iconst_0
    //   7243: iload #14
    //   7245: bipush #24
    //   7247: iushr
    //   7248: i2b
    //   7249: bastore
    //   7250: aload #19
    //   7252: iconst_1
    //   7253: iload #14
    //   7255: bipush #16
    //   7257: iushr
    //   7258: i2b
    //   7259: bastore
    //   7260: aload #19
    //   7262: iconst_2
    //   7263: iload #14
    //   7265: bipush #8
    //   7267: iushr
    //   7268: i2b
    //   7269: bastore
    //   7270: aload #19
    //   7272: iconst_3
    //   7273: iload #14
    //   7275: i2b
    //   7276: bastore
    //   7277: aload #19
    //   7279: iconst_4
    //   7280: iload #15
    //   7282: bipush #24
    //   7284: iushr
    //   7285: i2b
    //   7286: bastore
    //   7287: aload #19
    //   7289: iconst_5
    //   7290: iload #15
    //   7292: bipush #16
    //   7294: iushr
    //   7295: i2b
    //   7296: bastore
    //   7297: aload #19
    //   7299: bipush #6
    //   7301: iload #15
    //   7303: bipush #8
    //   7305: iushr
    //   7306: i2b
    //   7307: bastore
    //   7308: aload #19
    //   7310: bipush #7
    //   7312: iload #15
    //   7314: i2b
    //   7315: bastore
    //   7316: bipush #8
    //   7318: istore #11
    //   7320: aload #7
    //   7322: iconst_0
    //   7323: iaload
    //   7324: bipush #63
    //   7326: iand
    //   7327: istore #12
    //   7329: bipush #64
    //   7331: iload #12
    //   7333: isub
    //   7334: istore #18
    //   7336: aload #7
    //   7338: iconst_0
    //   7339: dup2
    //   7340: iaload
    //   7341: iload #11
    //   7343: iadd
    //   7344: iastore
    //   7345: aload #7
    //   7347: iconst_0
    //   7348: dup2
    //   7349: iaload
    //   7350: iconst_m1
    //   7351: iand
    //   7352: iastore
    //   7353: aload #7
    //   7355: iconst_0
    //   7356: iaload
    //   7357: iload #11
    //   7359: if_icmpge -> 7377
    //   7362: aload #7
    //   7364: iconst_1
    //   7365: dup2
    //   7366: iaload
    //   7367: iconst_1
    //   7368: iadd
    //   7369: iastore
    //   7370: goto -> 7377
    //   7373: invokestatic a : (Ljava/lang/Throwable;)Ljava/lang/Throwable;
    //   7376: athrow
    //   7377: iload #12
    //   7379: ifle -> 7993
    //   7382: iload #11
    //   7384: iload #18
    //   7386: if_icmplt -> 7993
    //   7389: goto -> 7396
    //   7392: invokestatic a : (Ljava/lang/Throwable;)Ljava/lang/Throwable;
    //   7395: athrow
    //   7396: iconst_0
    //   7397: istore #20
    //   7399: iload #20
    //   7401: iload #18
    //   7403: if_icmpge -> 7426
    //   7406: aload #9
    //   7408: iload #12
    //   7410: iload #20
    //   7412: iadd
    //   7413: aload #19
    //   7415: iload #20
    //   7417: baload
    //   7418: bastore
    //   7419: iinc #20, 1
    //   7422: iload_2
    //   7423: ifne -> 7399
    //   7426: bipush #64
    //   7428: newarray int
    //   7430: astore #20
    //   7432: bipush #8
    //   7434: newarray int
    //   7436: astore #21
    //   7438: iconst_0
    //   7439: istore #22
    //   7441: iload #22
    //   7443: bipush #8
    //   7445: if_icmpge -> 7465
    //   7448: aload #21
    //   7450: iload #22
    //   7452: aload #8
    //   7454: iload #22
    //   7456: iaload
    //   7457: iastore
    //   7458: iinc #22, 1
    //   7461: iload_2
    //   7462: ifne -> 7441
    //   7465: iconst_0
    //   7466: istore #22
    //   7468: iload #22
    //   7470: bipush #64
    //   7472: if_icmpge -> 7963
    //   7475: iload #22
    //   7477: bipush #16
    //   7479: if_icmpge -> 7560
    //   7482: aload #20
    //   7484: iload #22
    //   7486: aload #9
    //   7488: iconst_4
    //   7489: iload #22
    //   7491: imul
    //   7492: baload
    //   7493: sipush #255
    //   7496: iand
    //   7497: bipush #24
    //   7499: ishl
    //   7500: aload #9
    //   7502: iconst_4
    //   7503: iload #22
    //   7505: imul
    //   7506: iconst_1
    //   7507: iadd
    //   7508: baload
    //   7509: sipush #255
    //   7512: iand
    //   7513: bipush #16
    //   7515: ishl
    //   7516: ior
    //   7517: aload #9
    //   7519: iconst_4
    //   7520: iload #22
    //   7522: imul
    //   7523: iconst_2
    //   7524: iadd
    //   7525: baload
    //   7526: sipush #255
    //   7529: iand
    //   7530: bipush #8
    //   7532: ishl
    //   7533: ior
    //   7534: aload #9
    //   7536: iconst_4
    //   7537: iload #22
    //   7539: imul
    //   7540: iconst_3
    //   7541: iadd
    //   7542: baload
    //   7543: sipush #255
    //   7546: iand
    //   7547: ior
    //   7548: iastore
    //   7549: iload_2
    //   7550: ifne -> 7703
    //   7553: goto -> 7560
    //   7556: invokestatic a : (Ljava/lang/Throwable;)Ljava/lang/Throwable;
    //   7559: athrow
    //   7560: aload #20
    //   7562: iload #22
    //   7564: aload #20
    //   7566: iload #22
    //   7568: iconst_2
    //   7569: isub
    //   7570: iaload
    //   7571: bipush #17
    //   7573: iushr
    //   7574: aload #20
    //   7576: iload #22
    //   7578: iconst_2
    //   7579: isub
    //   7580: iaload
    //   7581: bipush #15
    //   7583: ishl
    //   7584: ior
    //   7585: aload #20
    //   7587: iload #22
    //   7589: iconst_2
    //   7590: isub
    //   7591: iaload
    //   7592: bipush #19
    //   7594: iushr
    //   7595: aload #20
    //   7597: iload #22
    //   7599: iconst_2
    //   7600: isub
    //   7601: iaload
    //   7602: bipush #13
    //   7604: ishl
    //   7605: ior
    //   7606: ixor
    //   7607: aload #20
    //   7609: iload #22
    //   7611: iconst_2
    //   7612: isub
    //   7613: iaload
    //   7614: bipush #10
    //   7616: iushr
    //   7617: ixor
    //   7618: aload #20
    //   7620: iload #22
    //   7622: bipush #7
    //   7624: isub
    //   7625: iaload
    //   7626: iadd
    //   7627: aload #20
    //   7629: iload #22
    //   7631: bipush #15
    //   7633: isub
    //   7634: iaload
    //   7635: bipush #7
    //   7637: iushr
    //   7638: aload #20
    //   7640: iload #22
    //   7642: bipush #15
    //   7644: isub
    //   7645: iaload
    //   7646: bipush #25
    //   7648: ishl
    //   7649: ior
    //   7650: aload #20
    //   7652: iload #22
    //   7654: bipush #15
    //   7656: isub
    //   7657: iaload
    //   7658: bipush #18
    //   7660: iushr
    //   7661: aload #20
    //   7663: iload #22
    //   7665: bipush #15
    //   7667: isub
    //   7668: iaload
    //   7669: bipush #14
    //   7671: ishl
    //   7672: ior
    //   7673: ixor
    //   7674: aload #20
    //   7676: iload #22
    //   7678: bipush #15
    //   7680: isub
    //   7681: iaload
    //   7682: iconst_3
    //   7683: iushr
    //   7684: ixor
    //   7685: iadd
    //   7686: aload #20
    //   7688: iload #22
    //   7690: bipush #16
    //   7692: isub
    //   7693: iaload
    //   7694: iadd
    //   7695: iastore
    //   7696: goto -> 7703
    //   7699: invokestatic a : (Ljava/lang/Throwable;)Ljava/lang/Throwable;
    //   7702: athrow
    //   7703: aload #21
    //   7705: bipush #7
    //   7707: iaload
    //   7708: aload #21
    //   7710: iconst_4
    //   7711: iaload
    //   7712: bipush #6
    //   7714: iushr
    //   7715: aload #21
    //   7717: iconst_4
    //   7718: iaload
    //   7719: bipush #26
    //   7721: ishl
    //   7722: ior
    //   7723: aload #21
    //   7725: iconst_4
    //   7726: iaload
    //   7727: bipush #11
    //   7729: iushr
    //   7730: aload #21
    //   7732: iconst_4
    //   7733: iaload
    //   7734: bipush #21
    //   7736: ishl
    //   7737: ior
    //   7738: ixor
    //   7739: aload #21
    //   7741: iconst_4
    //   7742: iaload
    //   7743: bipush #25
    //   7745: iushr
    //   7746: aload #21
    //   7748: iconst_4
    //   7749: iaload
    //   7750: bipush #7
    //   7752: ishl
    //   7753: ior
    //   7754: ixor
    //   7755: iadd
    //   7756: aload #21
    //   7758: bipush #6
    //   7760: iaload
    //   7761: aload #21
    //   7763: iconst_4
    //   7764: iaload
    //   7765: aload #21
    //   7767: iconst_5
    //   7768: iaload
    //   7769: aload #21
    //   7771: bipush #6
    //   7773: iaload
    //   7774: ixor
    //   7775: iand
    //   7776: ixor
    //   7777: iadd
    //   7778: aload #6
    //   7780: iload #22
    //   7782: iaload
    //   7783: iadd
    //   7784: aload #20
    //   7786: iload #22
    //   7788: iaload
    //   7789: iadd
    //   7790: istore #23
    //   7792: aload #21
    //   7794: iconst_0
    //   7795: iaload
    //   7796: iconst_2
    //   7797: iushr
    //   7798: aload #21
    //   7800: iconst_0
    //   7801: iaload
    //   7802: bipush #30
    //   7804: ishl
    //   7805: ior
    //   7806: aload #21
    //   7808: iconst_0
    //   7809: iaload
    //   7810: bipush #13
    //   7812: iushr
    //   7813: aload #21
    //   7815: iconst_0
    //   7816: iaload
    //   7817: bipush #19
    //   7819: ishl
    //   7820: ior
    //   7821: ixor
    //   7822: aload #21
    //   7824: iconst_0
    //   7825: iaload
    //   7826: bipush #22
    //   7828: iushr
    //   7829: aload #21
    //   7831: iconst_0
    //   7832: iaload
    //   7833: bipush #10
    //   7835: ishl
    //   7836: ior
    //   7837: ixor
    //   7838: aload #21
    //   7840: iconst_0
    //   7841: iaload
    //   7842: aload #21
    //   7844: iconst_1
    //   7845: iaload
    //   7846: iand
    //   7847: aload #21
    //   7849: iconst_2
    //   7850: iaload
    //   7851: aload #21
    //   7853: iconst_0
    //   7854: iaload
    //   7855: aload #21
    //   7857: iconst_1
    //   7858: iaload
    //   7859: ior
    //   7860: iand
    //   7861: ior
    //   7862: iadd
    //   7863: istore #24
    //   7865: aload #21
    //   7867: iconst_3
    //   7868: dup2
    //   7869: iaload
    //   7870: iload #23
    //   7872: iadd
    //   7873: iastore
    //   7874: aload #21
    //   7876: bipush #7
    //   7878: iload #23
    //   7880: iload #24
    //   7882: iadd
    //   7883: iastore
    //   7884: aload #21
    //   7886: bipush #7
    //   7888: iaload
    //   7889: istore #23
    //   7891: aload #21
    //   7893: bipush #7
    //   7895: aload #21
    //   7897: bipush #6
    //   7899: iaload
    //   7900: iastore
    //   7901: aload #21
    //   7903: bipush #6
    //   7905: aload #21
    //   7907: iconst_5
    //   7908: iaload
    //   7909: iastore
    //   7910: aload #21
    //   7912: iconst_5
    //   7913: aload #21
    //   7915: iconst_4
    //   7916: iaload
    //   7917: iastore
    //   7918: aload #21
    //   7920: iconst_4
    //   7921: aload #21
    //   7923: iconst_3
    //   7924: iaload
    //   7925: iastore
    //   7926: aload #21
    //   7928: iconst_3
    //   7929: aload #21
    //   7931: iconst_2
    //   7932: iaload
    //   7933: iastore
    //   7934: aload #21
    //   7936: iconst_2
    //   7937: aload #21
    //   7939: iconst_1
    //   7940: iaload
    //   7941: iastore
    //   7942: aload #21
    //   7944: iconst_1
    //   7945: aload #21
    //   7947: iconst_0
    //   7948: iaload
    //   7949: iastore
    //   7950: aload #21
    //   7952: iconst_0
    //   7953: iload #23
    //   7955: iastore
    //   7956: iinc #22, 1
    //   7959: iload_2
    //   7960: ifne -> 7468
    //   7963: iconst_0
    //   7964: istore #22
    //   7966: iload #22
    //   7968: bipush #8
    //   7970: if_icmpge -> 7993
    //   7973: aload #8
    //   7975: iload #22
    //   7977: dup2
    //   7978: iaload
    //   7979: aload #21
    //   7981: iload #22
    //   7983: iaload
    //   7984: iadd
    //   7985: iastore
    //   7986: iinc #22, 1
    //   7989: iload_2
    //   7990: ifne -> 7966
    //   7993: bipush #32
    //   7995: newarray byte
    //   7997: astore #4
    //   7999: sipush #1801
    //   8002: aload #4
    //   8004: iconst_0
    //   8005: aload #8
    //   8007: iconst_0
    //   8008: iaload
    //   8009: bipush #24
    //   8011: iushr
    //   8012: i2b
    //   8013: bastore
    //   8014: sipush #-19979
    //   8017: aload #4
    //   8019: iconst_1
    //   8020: aload #8
    //   8022: iconst_0
    //   8023: iaload
    //   8024: bipush #16
    //   8026: iushr
    //   8027: i2b
    //   8028: bastore
    //   8029: aload #4
    //   8031: iconst_2
    //   8032: aload #8
    //   8034: iconst_0
    //   8035: iaload
    //   8036: bipush #8
    //   8038: iushr
    //   8039: i2b
    //   8040: bastore
    //   8041: aload #4
    //   8043: iconst_3
    //   8044: aload #8
    //   8046: iconst_0
    //   8047: iaload
    //   8048: i2b
    //   8049: bastore
    //   8050: aload #4
    //   8052: iconst_4
    //   8053: aload #8
    //   8055: iconst_1
    //   8056: iaload
    //   8057: bipush #24
    //   8059: iushr
    //   8060: i2b
    //   8061: bastore
    //   8062: aload #4
    //   8064: iconst_5
    //   8065: aload #8
    //   8067: iconst_1
    //   8068: iaload
    //   8069: bipush #16
    //   8071: iushr
    //   8072: i2b
    //   8073: bastore
    //   8074: aload #4
    //   8076: bipush #6
    //   8078: aload #8
    //   8080: iconst_1
    //   8081: iaload
    //   8082: bipush #8
    //   8084: iushr
    //   8085: i2b
    //   8086: bastore
    //   8087: aload #4
    //   8089: bipush #7
    //   8091: aload #8
    //   8093: iconst_1
    //   8094: iaload
    //   8095: i2b
    //   8096: bastore
    //   8097: aload #4
    //   8099: bipush #8
    //   8101: aload #8
    //   8103: iconst_2
    //   8104: iaload
    //   8105: bipush #24
    //   8107: iushr
    //   8108: i2b
    //   8109: bastore
    //   8110: aload #4
    //   8112: bipush #9
    //   8114: aload #8
    //   8116: iconst_2
    //   8117: iaload
    //   8118: bipush #16
    //   8120: iushr
    //   8121: i2b
    //   8122: bastore
    //   8123: aload #4
    //   8125: bipush #10
    //   8127: aload #8
    //   8129: iconst_2
    //   8130: iaload
    //   8131: bipush #8
    //   8133: iushr
    //   8134: i2b
    //   8135: bastore
    //   8136: aload #4
    //   8138: bipush #11
    //   8140: aload #8
    //   8142: iconst_2
    //   8143: iaload
    //   8144: i2b
    //   8145: bastore
    //   8146: aload #4
    //   8148: bipush #12
    //   8150: aload #8
    //   8152: iconst_3
    //   8153: iaload
    //   8154: bipush #24
    //   8156: iushr
    //   8157: i2b
    //   8158: bastore
    //   8159: aload #4
    //   8161: bipush #13
    //   8163: aload #8
    //   8165: iconst_3
    //   8166: iaload
    //   8167: bipush #16
    //   8169: iushr
    //   8170: i2b
    //   8171: bastore
    //   8172: aload #4
    //   8174: bipush #14
    //   8176: aload #8
    //   8178: iconst_3
    //   8179: iaload
    //   8180: bipush #8
    //   8182: iushr
    //   8183: i2b
    //   8184: bastore
    //   8185: aload #4
    //   8187: bipush #15
    //   8189: aload #8
    //   8191: iconst_3
    //   8192: iaload
    //   8193: i2b
    //   8194: bastore
    //   8195: aload #4
    //   8197: bipush #16
    //   8199: aload #8
    //   8201: iconst_4
    //   8202: iaload
    //   8203: bipush #24
    //   8205: iushr
    //   8206: i2b
    //   8207: bastore
    //   8208: aload #4
    //   8210: bipush #17
    //   8212: aload #8
    //   8214: iconst_4
    //   8215: iaload
    //   8216: bipush #16
    //   8218: iushr
    //   8219: i2b
    //   8220: bastore
    //   8221: aload #4
    //   8223: bipush #18
    //   8225: aload #8
    //   8227: iconst_4
    //   8228: iaload
    //   8229: bipush #8
    //   8231: iushr
    //   8232: i2b
    //   8233: bastore
    //   8234: aload #4
    //   8236: bipush #19
    //   8238: aload #8
    //   8240: iconst_4
    //   8241: iaload
    //   8242: i2b
    //   8243: bastore
    //   8244: aload #4
    //   8246: bipush #20
    //   8248: aload #8
    //   8250: iconst_5
    //   8251: iaload
    //   8252: bipush #24
    //   8254: iushr
    //   8255: i2b
    //   8256: bastore
    //   8257: aload #4
    //   8259: bipush #21
    //   8261: aload #8
    //   8263: iconst_5
    //   8264: iaload
    //   8265: bipush #16
    //   8267: iushr
    //   8268: i2b
    //   8269: bastore
    //   8270: aload #4
    //   8272: bipush #22
    //   8274: aload #8
    //   8276: iconst_5
    //   8277: iaload
    //   8278: bipush #8
    //   8280: iushr
    //   8281: i2b
    //   8282: bastore
    //   8283: aload #4
    //   8285: bipush #23
    //   8287: aload #8
    //   8289: iconst_5
    //   8290: iaload
    //   8291: i2b
    //   8292: bastore
    //   8293: aload #4
    //   8295: bipush #24
    //   8297: aload #8
    //   8299: bipush #6
    //   8301: iaload
    //   8302: bipush #24
    //   8304: iushr
    //   8305: i2b
    //   8306: bastore
    //   8307: aload #4
    //   8309: bipush #25
    //   8311: aload #8
    //   8313: bipush #6
    //   8315: iaload
    //   8316: bipush #16
    //   8318: iushr
    //   8319: i2b
    //   8320: bastore
    //   8321: aload #4
    //   8323: bipush #26
    //   8325: aload #8
    //   8327: bipush #6
    //   8329: iaload
    //   8330: bipush #8
    //   8332: iushr
    //   8333: i2b
    //   8334: bastore
    //   8335: aload #4
    //   8337: bipush #27
    //   8339: aload #8
    //   8341: bipush #6
    //   8343: iaload
    //   8344: i2b
    //   8345: bastore
    //   8346: aload #4
    //   8348: bipush #28
    //   8350: aload #8
    //   8352: bipush #7
    //   8354: iaload
    //   8355: bipush #24
    //   8357: iushr
    //   8358: i2b
    //   8359: bastore
    //   8360: aload #4
    //   8362: bipush #29
    //   8364: aload #8
    //   8366: bipush #7
    //   8368: iaload
    //   8369: bipush #16
    //   8371: iushr
    //   8372: i2b
    //   8373: bastore
    //   8374: aload #4
    //   8376: bipush #30
    //   8378: aload #8
    //   8380: bipush #7
    //   8382: iaload
    //   8383: bipush #8
    //   8385: iushr
    //   8386: i2b
    //   8387: bastore
    //   8388: aload #4
    //   8390: bipush #31
    //   8392: aload #8
    //   8394: bipush #7
    //   8396: iaload
    //   8397: i2b
    //   8398: bastore
    //   8399: new java/math/BigInteger
    //   8402: dup
    //   8403: aload #4
    //   8405: invokespecial <init> : ([B)V
    //   8408: invokevirtual abs : ()Ljava/math/BigInteger;
    //   8411: putstatic burp/Zt4g.Zv : Ljava/lang/Object;
    //   8414: invokestatic a : (II)Ljava/lang/String;
    //   8417: iconst_1
    //   8418: ldc burp/Zkv2
    //   8420: invokevirtual getClassLoader : ()Ljava/lang/ClassLoader;
    //   8423: invokestatic forName : (Ljava/lang/String;ZLjava/lang/ClassLoader;)Ljava/lang/Class;
    //   8426: invokevirtual getDeclaredFields : ()[Ljava/lang/reflect/Field;
    //   8429: astore_3
    //   8430: aload_3
    //   8431: arraylength
    //   8432: istore #4
    //   8434: iconst_0
    //   8435: istore #5
    //   8437: iload #5
    //   8439: iload #4
    //   8441: if_icmpge -> 8578
    //   8444: aload_3
    //   8445: iload #5
    //   8447: aaload
    //   8448: astore #6
    //   8450: aload #6
    //   8452: invokevirtual getModifiers : ()I
    //   8455: invokestatic isStatic : (I)Z
    //   8458: ifne -> 8468
    //   8461: goto -> 8571
    //   8464: invokestatic a : (Ljava/lang/Throwable;)Ljava/lang/Throwable;
    //   8467: athrow
    //   8468: aload #6
    //   8470: invokevirtual getType : ()Ljava/lang/Class;
    //   8473: astore #7
    //   8475: aload #7
    //   8477: ifnull -> 8558
    //   8480: aload #7
    //   8482: invokevirtual isPrimitive : ()Z
    //   8485: ifne -> 8558
    //   8488: goto -> 8495
    //   8491: invokestatic a : (Ljava/lang/Throwable;)Ljava/lang/Throwable;
    //   8494: athrow
    //   8495: aload #7
    //   8497: invokevirtual getPackage : ()Ljava/lang/Package;
    //   8500: ifnull -> 8558
    //   8503: goto -> 8510
    //   8506: invokestatic a : (Ljava/lang/Throwable;)Ljava/lang/Throwable;
    //   8509: athrow
    //   8510: aload #7
    //   8512: invokevirtual getPackage : ()Ljava/lang/Package;
    //   8515: invokevirtual getName : ()Ljava/lang/String;
    //   8518: ifnull -> 8558
    //   8521: goto -> 8528
    //   8524: invokestatic a : (Ljava/lang/Throwable;)Ljava/lang/Throwable;
    //   8527: athrow
    //   8528: aload #7
    //   8530: invokevirtual getPackage : ()Ljava/lang/Package;
    //   8533: invokevirtual getName : ()Ljava/lang/String;
    //   8536: sipush #1798
    //   8539: sipush #-10165
    //   8542: invokestatic a : (II)Ljava/lang/String;
    //   8545: invokevirtual startsWith : (Ljava/lang/String;)Z
    //   8548: ifne -> 8558
    //   8551: goto -> 8558
    //   8554: invokestatic a : (Ljava/lang/Throwable;)Ljava/lang/Throwable;
    //   8557: athrow
    //   8558: aload #6
    //   8560: iconst_1
    //   8561: invokevirtual setAccessible : (Z)V
    //   8564: aload #6
    //   8566: aconst_null
    //   8567: invokevirtual get : (Ljava/lang/Object;)Ljava/lang/Object;
    //   8570: pop
    //   8571: iinc #5, 1
    //   8574: iload_2
    //   8575: ifne -> 8437
    //   8578: sipush #1804
    //   8581: sipush #24397
    //   8584: invokestatic a : (II)Ljava/lang/String;
    //   8587: invokestatic forName : (Ljava/lang/String;)Ljava/lang/Class;
    //   8590: invokevirtual getDeclaredMethods : ()[Ljava/lang/reflect/Method;
    //   8593: astore_3
    //   8594: aload_3
    //   8595: arraylength
    //   8596: istore #4
    //   8598: iconst_0
    //   8599: istore #5
    //   8601: iload #5
    //   8603: iload #4
    //   8605: if_icmpge -> 8737
    //   8608: aload_3
    //   8609: iload #5
    //   8611: aaload
    //   8612: astore #6
    //   8614: aload #6
    //   8616: invokevirtual getParameterTypes : ()[Ljava/lang/Class;
    //   8619: pop
    //   8620: aload #6
    //   8622: invokevirtual getModifiers : ()I
    //   8625: invokestatic isStatic : (I)Z
    //   8628: ifeq -> 8723
    //   8631: aload #6
    //   8633: invokevirtual getParameterTypes : ()[Ljava/lang/Class;
    //   8636: arraylength
    //   8637: iconst_2
    //   8638: if_icmpne -> 8723
    //   8641: goto -> 8648
    //   8644: invokestatic a : (Ljava/lang/Throwable;)Ljava/lang/Throwable;
    //   8647: athrow
    //   8648: aload #6
    //   8650: invokevirtual getReturnType : ()Ljava/lang/Class;
    //   8653: getstatic java/lang/Void.TYPE : Ljava/lang/Class;
    //   8656: invokevirtual equals : (Ljava/lang/Object;)Z
    //   8659: ifeq -> 8723
    //   8662: goto -> 8669
    //   8665: invokestatic a : (Ljava/lang/Throwable;)Ljava/lang/Throwable;
    //   8668: athrow
    //   8669: aload #6
    //   8671: iconst_1
    //   8672: invokevirtual setAccessible : (Z)V
    //   8675: aload #6
    //   8677: aconst_null
    //   8678: iconst_2
    //   8679: anewarray java/lang/Object
    //   8682: dup
    //   8683: iconst_0
    //   8684: aload_0
    //   8685: aastore
    //   8686: dup
    //   8687: iconst_1
    //   8688: aload_1
    //   8689: ifnonnull -> 8707
    //   8692: goto -> 8699
    //   8695: invokestatic a : (Ljava/lang/Throwable;)Ljava/lang/Throwable;
    //   8698: athrow
    //   8699: aload_1
    //   8700: goto -> 8714
    //   8703: invokestatic a : (Ljava/lang/Throwable;)Ljava/lang/Throwable;
    //   8706: athrow
    //   8707: aload_1
    //   8708: checkcast [B
    //   8711: invokevirtual clone : ()Ljava/lang/Object;
    //   8714: aastore
    //   8715: invokevirtual invoke : (Ljava/lang/Object;[Ljava/lang/Object;)Ljava/lang/Object;
    //   8718: pop
    //   8719: iload_2
    //   8720: ifne -> 8737
    //   8723: iinc #5, 1
    //   8726: iload_2
    //   8727: ifne -> 8601
    //   8730: goto -> 8737
    //   8733: invokestatic a : (Ljava/lang/Throwable;)Ljava/lang/Throwable;
    //   8736: athrow
    //   8737: iconst_0
    //   8738: istore_3
    //   8739: getstatic burp/Zxso.ZH : Ljava/lang/String;
    //   8742: getstatic burp/Zb2s.Ze : Ljava/lang/Object;
    //   8745: checkcast java/math/BigInteger
    //   8748: invokevirtual intValue : ()I
    //   8751: bipush #32
    //   8753: irem
    //   8754: invokestatic abs : (I)I
    //   8757: invokevirtual charAt : (I)C
    //   8760: getstatic burp/Zzip.Za : Ljava/lang/String;
    //   8763: getstatic burp/Zsxm.Zv : Ljava/lang/Object;
    //   8766: checkcast java/math/BigInteger
    //   8769: invokevirtual intValue : ()I
    //   8772: bipush #32
    //   8774: irem
    //   8775: invokestatic abs : (I)I
    //   8778: invokevirtual charAt : (I)C
    //   8781: if_icmple -> 9125
    //   8784: sipush #1795
    //   8787: sipush #5023
    //   8790: invokestatic a : (II)Ljava/lang/String;
    //   8793: iconst_1
    //   8794: ldc burp/Ztzh
    //   8796: invokevirtual getClassLoader : ()Ljava/lang/ClassLoader;
    //   8799: invokestatic forName : (Ljava/lang/String;ZLjava/lang/ClassLoader;)Ljava/lang/Class;
    //   8802: invokevirtual getDeclaredFields : ()[Ljava/lang/reflect/Field;
    //   8805: astore #4
    //   8807: aload #4
    //   8809: arraylength
    //   8810: istore #5
    //   8812: iconst_0
    //   8813: istore #6
    //   8815: iload #6
    //   8817: iload #5
    //   8819: if_icmpge -> 8957
    //   8822: aload #4
    //   8824: iload #6
    //   8826: aaload
    //   8827: astore #7
    //   8829: aload #7
    //   8831: invokevirtual getModifiers : ()I
    //   8834: invokestatic isStatic : (I)Z
    //   8837: ifne -> 8847
    //   8840: goto -> 8950
    //   8843: invokestatic a : (Ljava/lang/Throwable;)Ljava/lang/Throwable;
    //   8846: athrow
    //   8847: aload #7
    //   8849: invokevirtual getType : ()Ljava/lang/Class;
    //   8852: astore #8
    //   8854: aload #8
    //   8856: ifnull -> 8937
    //   8859: aload #8
    //   8861: invokevirtual isPrimitive : ()Z
    //   8864: ifne -> 8937
    //   8867: goto -> 8874
    //   8870: invokestatic a : (Ljava/lang/Throwable;)Ljava/lang/Throwable;
    //   8873: athrow
    //   8874: aload #8
    //   8876: invokevirtual getPackage : ()Ljava/lang/Package;
    //   8879: ifnull -> 8937
    //   8882: goto -> 8889
    //   8885: invokestatic a : (Ljava/lang/Throwable;)Ljava/lang/Throwable;
    //   8888: athrow
    //   8889: aload #8
    //   8891: invokevirtual getPackage : ()Ljava/lang/Package;
    //   8894: invokevirtual getName : ()Ljava/lang/String;
    //   8897: ifnull -> 8937
    //   8900: goto -> 8907
    //   8903: invokestatic a : (Ljava/lang/Throwable;)Ljava/lang/Throwable;
    //   8906: athrow
    //   8907: aload #8
    //   8909: invokevirtual getPackage : ()Ljava/lang/Package;
    //   8912: invokevirtual getName : ()Ljava/lang/String;
    //   8915: sipush #1805
    //   8918: sipush #-29435
    //   8921: invokestatic a : (II)Ljava/lang/String;
    //   8924: invokevirtual startsWith : (Ljava/lang/String;)Z
    //   8927: ifne -> 8937
    //   8930: goto -> 8937
    //   8933: invokestatic a : (Ljava/lang/Throwable;)Ljava/lang/Throwable;
    //   8936: athrow
    //   8937: aload #7
    //   8939: iconst_1
    //   8940: invokevirtual setAccessible : (Z)V
    //   8943: aload #7
    //   8945: aconst_null
    //   8946: invokevirtual get : (Ljava/lang/Object;)Ljava/lang/Object;
    //   8949: pop
    //   8950: iinc #6, 1
    //   8953: iload_2
    //   8954: ifne -> 8815
    //   8957: sipush #1797
    //   8960: sipush #27387
    //   8963: invokestatic a : (II)Ljava/lang/String;
    //   8966: invokestatic forName : (Ljava/lang/String;)Ljava/lang/Class;
    //   8969: invokevirtual getDeclaredMethods : ()[Ljava/lang/reflect/Method;
    //   8972: astore #4
    //   8974: aload #4
    //   8976: arraylength
    //   8977: istore #5
    //   8979: iconst_0
    //   8980: istore #6
    //   8982: iload #6
    //   8984: iload #5
    //   8986: if_icmpge -> 9122
    //   8989: aload #4
    //   8991: iload #6
    //   8993: aaload
    //   8994: astore #7
    //   8996: aload #7
    //   8998: invokevirtual getParameterTypes : ()[Ljava/lang/Class;
    //   9001: pop
    //   9002: aload #7
    //   9004: invokevirtual getModifiers : ()I
    //   9007: invokestatic isStatic : (I)Z
    //   9010: ifeq -> 9108
    //   9013: aload #7
    //   9015: invokevirtual getParameterTypes : ()[Ljava/lang/Class;
    //   9018: arraylength
    //   9019: iconst_2
    //   9020: if_icmpne -> 9108
    //   9023: goto -> 9030
    //   9026: invokestatic a : (Ljava/lang/Throwable;)Ljava/lang/Throwable;
    //   9029: athrow
    //   9030: aload #7
    //   9032: invokevirtual getReturnType : ()Ljava/lang/Class;
    //   9035: getstatic java/lang/Boolean.TYPE : Ljava/lang/Class;
    //   9038: if_acmpne -> 9108
    //   9041: goto -> 9048
    //   9044: invokestatic a : (Ljava/lang/Throwable;)Ljava/lang/Throwable;
    //   9047: athrow
    //   9048: aload #7
    //   9050: iconst_1
    //   9051: invokevirtual setAccessible : (Z)V
    //   9054: aload #7
    //   9056: aconst_null
    //   9057: iconst_2
    //   9058: anewarray java/lang/Object
    //   9061: dup
    //   9062: iconst_0
    //   9063: aload_0
    //   9064: aastore
    //   9065: dup
    //   9066: iconst_1
    //   9067: aload_1
    //   9068: ifnonnull -> 9086
    //   9071: goto -> 9078
    //   9074: invokestatic a : (Ljava/lang/Throwable;)Ljava/lang/Throwable;
    //   9077: athrow
    //   9078: aload_1
    //   9079: goto -> 9093
    //   9082: invokestatic a : (Ljava/lang/Throwable;)Ljava/lang/Throwable;
    //   9085: athrow
    //   9086: aload_1
    //   9087: checkcast [B
    //   9090: invokevirtual clone : ()Ljava/lang/Object;
    //   9093: aastore
    //   9094: invokevirtual invoke : (Ljava/lang/Object;[Ljava/lang/Object;)Ljava/lang/Object;
    //   9097: checkcast java/lang/Boolean
    //   9100: invokevirtual booleanValue : ()Z
    //   9103: istore_3
    //   9104: iload_2
    //   9105: ifne -> 9122
    //   9108: iinc #6, 1
    //   9111: iload_2
    //   9112: ifne -> 8982
    //   9115: goto -> 9122
    //   9118: invokestatic a : (Ljava/lang/Throwable;)Ljava/lang/Throwable;
    //   9121: athrow
    //   9122: goto -> 9463
    //   9125: sipush #1792
    //   9128: sipush #-3823
    //   9131: invokestatic a : (II)Ljava/lang/String;
    //   9134: iconst_1
    //   9135: ldc burp/Ztzw
    //   9137: invokevirtual getClassLoader : ()Ljava/lang/ClassLoader;
    //   9140: invokestatic forName : (Ljava/lang/String;ZLjava/lang/ClassLoader;)Ljava/lang/Class;
    //   9143: invokevirtual getDeclaredFields : ()[Ljava/lang/reflect/Field;
    //   9146: astore #4
    //   9148: aload #4
    //   9150: arraylength
    //   9151: istore #5
    //   9153: iconst_0
    //   9154: istore #6
    //   9156: iload #6
    //   9158: iload #5
    //   9160: if_icmpge -> 9298
    //   9163: aload #4
    //   9165: iload #6
    //   9167: aaload
    //   9168: astore #7
    //   9170: aload #7
    //   9172: invokevirtual getModifiers : ()I
    //   9175: invokestatic isStatic : (I)Z
    //   9178: ifne -> 9188
    //   9181: goto -> 9291
    //   9184: invokestatic a : (Ljava/lang/Throwable;)Ljava/lang/Throwable;
    //   9187: athrow
    //   9188: aload #7
    //   9190: invokevirtual getType : ()Ljava/lang/Class;
    //   9193: astore #8
    //   9195: aload #8
    //   9197: ifnull -> 9278
    //   9200: aload #8
    //   9202: invokevirtual isPrimitive : ()Z
    //   9205: ifne -> 9278
    //   9208: goto -> 9215
    //   9211: invokestatic a : (Ljava/lang/Throwable;)Ljava/lang/Throwable;
    //   9214: athrow
    //   9215: aload #8
    //   9217: invokevirtual getPackage : ()Ljava/lang/Package;
    //   9220: ifnull -> 9278
    //   9223: goto -> 9230
    //   9226: invokestatic a : (Ljava/lang/Throwable;)Ljava/lang/Throwable;
    //   9229: athrow
    //   9230: aload #8
    //   9232: invokevirtual getPackage : ()Ljava/lang/Package;
    //   9235: invokevirtual getName : ()Ljava/lang/String;
    //   9238: ifnull -> 9278
    //   9241: goto -> 9248
    //   9244: invokestatic a : (Ljava/lang/Throwable;)Ljava/lang/Throwable;
    //   9247: athrow
    //   9248: aload #8
    //   9250: invokevirtual getPackage : ()Ljava/lang/Package;
    //   9253: invokevirtual getName : ()Ljava/lang/String;
    //   9256: sipush #1805
    //   9259: sipush #-29435
    //   9262: invokestatic a : (II)Ljava/lang/String;
    //   9265: invokevirtual startsWith : (Ljava/lang/String;)Z
    //   9268: ifne -> 9278
    //   9271: goto -> 9278
    //   9274: invokestatic a : (Ljava/lang/Throwable;)Ljava/lang/Throwable;
    //   9277: athrow
    //   9278: aload #7
    //   9280: iconst_1
    //   9281: invokevirtual setAccessible : (Z)V
    //   9284: aload #7
    //   9286: aconst_null
    //   9287: invokevirtual get : (Ljava/lang/Object;)Ljava/lang/Object;
    //   9290: pop
    //   9291: iinc #6, 1
    //   9294: iload_2
    //   9295: ifne -> 9156
    //   9298: sipush #1818
    //   9301: sipush #-21821
    //   9304: invokestatic a : (II)Ljava/lang/String;
    //   9307: invokestatic forName : (Ljava/lang/String;)Ljava/lang/Class;
    //   9310: invokevirtual getDeclaredMethods : ()[Ljava/lang/reflect/Method;
    //   9313: astore #4
    //   9315: aload #4
    //   9317: arraylength
    //   9318: istore #5
    //   9320: iconst_0
    //   9321: istore #6
    //   9323: iload #6
    //   9325: iload #5
    //   9327: if_icmpge -> 9463
    //   9330: aload #4
    //   9332: iload #6
    //   9334: aaload
    //   9335: astore #7
    //   9337: aload #7
    //   9339: invokevirtual getParameterTypes : ()[Ljava/lang/Class;
    //   9342: pop
    //   9343: aload #7
    //   9345: invokevirtual getModifiers : ()I
    //   9348: invokestatic isStatic : (I)Z
    //   9351: ifeq -> 9449
    //   9354: aload #7
    //   9356: invokevirtual getParameterTypes : ()[Ljava/lang/Class;
    //   9359: arraylength
    //   9360: iconst_2
    //   9361: if_icmpne -> 9449
    //   9364: goto -> 9371
    //   9367: invokestatic a : (Ljava/lang/Throwable;)Ljava/lang/Throwable;
    //   9370: athrow
    //   9371: aload #7
    //   9373: invokevirtual getReturnType : ()Ljava/lang/Class;
    //   9376: getstatic java/lang/Boolean.TYPE : Ljava/lang/Class;
    //   9379: if_acmpne -> 9449
    //   9382: goto -> 9389
    //   9385: invokestatic a : (Ljava/lang/Throwable;)Ljava/lang/Throwable;
    //   9388: athrow
    //   9389: aload #7
    //   9391: iconst_1
    //   9392: invokevirtual setAccessible : (Z)V
    //   9395: aload #7
    //   9397: aconst_null
    //   9398: iconst_2
    //   9399: anewarray java/lang/Object
    //   9402: dup
    //   9403: iconst_0
    //   9404: aload_0
    //   9405: aastore
    //   9406: dup
    //   9407: iconst_1
    //   9408: aload_1
    //   9409: ifnonnull -> 9427
    //   9412: goto -> 9419
    //   9415: invokestatic a : (Ljava/lang/Throwable;)Ljava/lang/Throwable;
    //   9418: athrow
    //   9419: aload_1
    //   9420: goto -> 9434
    //   9423: invokestatic a : (Ljava/lang/Throwable;)Ljava/lang/Throwable;
    //   9426: athrow
    //   9427: aload_1
    //   9428: checkcast [B
    //   9431: invokevirtual clone : ()Ljava/lang/Object;
    //   9434: aastore
    //   9435: invokevirtual invoke : (Ljava/lang/Object;[Ljava/lang/Object;)Ljava/lang/Object;
    //   9438: checkcast java/lang/Boolean
    //   9441: invokevirtual booleanValue : ()Z
    //   9444: istore_3
    //   9445: iload_2
    //   9446: ifne -> 9463
    //   9449: iinc #6, 1
    //   9452: iload_2
    //   9453: ifne -> 9323
    //   9456: goto -> 9463
    //   9459: invokestatic a : (Ljava/lang/Throwable;)Ljava/lang/Throwable;
    //   9462: athrow
    //   9463: iload_3
    //   9464: ifeq -> 9469
    //   9467: iload_3
    //   9468: ireturn
    //   9469: getstatic burp/Zl_k.Zw : Ljava/lang/String;
    //   9472: getstatic burp/Zx4w.Zp : Ljava/lang/Object;
    //   9475: checkcast java/math/BigInteger
    //   9478: invokevirtual intValue : ()I
    //   9481: bipush #32
    //   9483: irem
    //   9484: invokestatic abs : (I)I
    //   9487: invokevirtual charAt : (I)C
    //   9490: getstatic burp/Zkfz.Zs : Ljava/lang/String;
    //   9493: getstatic burp/Zl_u.ZR : Ljava/lang/Object;
    //   9496: checkcast java/math/BigInteger
    //   9499: invokevirtual intValue : ()I
    //   9502: bipush #32
    //   9504: irem
    //   9505: invokestatic abs : (I)I
    //   9508: invokevirtual charAt : (I)C
    //   9511: if_icmpgt -> 9856
    //   9514: sipush #1802
    //   9517: sipush #-15508
    //   9520: invokestatic a : (II)Ljava/lang/String;
    //   9523: iconst_1
    //   9524: ldc burp/Zlhk
    //   9526: invokevirtual getClassLoader : ()Ljava/lang/ClassLoader;
    //   9529: invokestatic forName : (Ljava/lang/String;ZLjava/lang/ClassLoader;)Ljava/lang/Class;
    //   9532: invokevirtual getDeclaredFields : ()[Ljava/lang/reflect/Field;
    //   9535: astore #4
    //   9537: aload #4
    //   9539: arraylength
    //   9540: istore #5
    //   9542: iconst_0
    //   9543: istore #6
    //   9545: iload #6
    //   9547: iload #5
    //   9549: if_icmpge -> 9687
    //   9552: aload #4
    //   9554: iload #6
    //   9556: aaload
    //   9557: astore #7
    //   9559: aload #7
    //   9561: invokevirtual getModifiers : ()I
    //   9564: invokestatic isStatic : (I)Z
    //   9567: ifne -> 9577
    //   9570: goto -> 9680
    //   9573: invokestatic a : (Ljava/lang/Throwable;)Ljava/lang/Throwable;
    //   9576: athrow
    //   9577: aload #7
    //   9579: invokevirtual getType : ()Ljava/lang/Class;
    //   9582: astore #8
    //   9584: aload #8
    //   9586: ifnull -> 9667
    //   9589: aload #8
    //   9591: invokevirtual isPrimitive : ()Z
    //   9594: ifne -> 9667
    //   9597: goto -> 9604
    //   9600: invokestatic a : (Ljava/lang/Throwable;)Ljava/lang/Throwable;
    //   9603: athrow
    //   9604: aload #8
    //   9606: invokevirtual getPackage : ()Ljava/lang/Package;
    //   9609: ifnull -> 9667
    //   9612: goto -> 9619
    //   9615: invokestatic a : (Ljava/lang/Throwable;)Ljava/lang/Throwable;
    //   9618: athrow
    //   9619: aload #8
    //   9621: invokevirtual getPackage : ()Ljava/lang/Package;
    //   9624: invokevirtual getName : ()Ljava/lang/String;
    //   9627: ifnull -> 9667
    //   9630: goto -> 9637
    //   9633: invokestatic a : (Ljava/lang/Throwable;)Ljava/lang/Throwable;
    //   9636: athrow
    //   9637: aload #8
    //   9639: invokevirtual getPackage : ()Ljava/lang/Package;
    //   9642: invokevirtual getName : ()Ljava/lang/String;
    //   9645: sipush #1805
    //   9648: sipush #-29435
    //   9651: invokestatic a : (II)Ljava/lang/String;
    //   9654: invokevirtual startsWith : (Ljava/lang/String;)Z
    //   9657: ifne -> 9667
    //   9660: goto -> 9667
    //   9663: invokestatic a : (Ljava/lang/Throwable;)Ljava/lang/Throwable;
    //   9666: athrow
    //   9667: aload #7
    //   9669: iconst_1
    //   9670: invokevirtual setAccessible : (Z)V
    //   9673: aload #7
    //   9675: aconst_null
    //   9676: invokevirtual get : (Ljava/lang/Object;)Ljava/lang/Object;
    //   9679: pop
    //   9680: iinc #6, 1
    //   9683: iload_2
    //   9684: ifne -> 9545
    //   9687: sipush #1794
    //   9690: sipush #-11801
    //   9693: invokestatic a : (II)Ljava/lang/String;
    //   9696: invokestatic forName : (Ljava/lang/String;)Ljava/lang/Class;
    //   9699: invokevirtual getDeclaredMethods : ()[Ljava/lang/reflect/Method;
    //   9702: astore #4
    //   9704: aload #4
    //   9706: arraylength
    //   9707: istore #5
    //   9709: iconst_0
    //   9710: istore #6
    //   9712: iload #6
    //   9714: iload #5
    //   9716: if_icmpge -> 9852
    //   9719: aload #4
    //   9721: iload #6
    //   9723: aaload
    //   9724: astore #7
    //   9726: aload #7
    //   9728: invokevirtual getParameterTypes : ()[Ljava/lang/Class;
    //   9731: pop
    //   9732: aload #7
    //   9734: invokevirtual getModifiers : ()I
    //   9737: invokestatic isStatic : (I)Z
    //   9740: ifeq -> 9838
    //   9743: aload #7
    //   9745: invokevirtual getParameterTypes : ()[Ljava/lang/Class;
    //   9748: arraylength
    //   9749: iconst_2
    //   9750: if_icmpne -> 9838
    //   9753: goto -> 9760
    //   9756: invokestatic a : (Ljava/lang/Throwable;)Ljava/lang/Throwable;
    //   9759: athrow
    //   9760: aload #7
    //   9762: invokevirtual getReturnType : ()Ljava/lang/Class;
    //   9765: getstatic java/lang/Boolean.TYPE : Ljava/lang/Class;
    //   9768: if_acmpne -> 9838
    //   9771: goto -> 9778
    //   9774: invokestatic a : (Ljava/lang/Throwable;)Ljava/lang/Throwable;
    //   9777: athrow
    //   9778: aload #7
    //   9780: iconst_1
    //   9781: invokevirtual setAccessible : (Z)V
    //   9784: aload #7
    //   9786: aconst_null
    //   9787: iconst_2
    //   9788: anewarray java/lang/Object
    //   9791: dup
    //   9792: iconst_0
    //   9793: aload_0
    //   9794: aastore
    //   9795: dup
    //   9796: iconst_1
    //   9797: aload_1
    //   9798: ifnonnull -> 9816
    //   9801: goto -> 9808
    //   9804: invokestatic a : (Ljava/lang/Throwable;)Ljava/lang/Throwable;
    //   9807: athrow
    //   9808: aload_1
    //   9809: goto -> 9823
    //   9812: invokestatic a : (Ljava/lang/Throwable;)Ljava/lang/Throwable;
    //   9815: athrow
    //   9816: aload_1
    //   9817: checkcast [B
    //   9820: invokevirtual clone : ()Ljava/lang/Object;
    //   9823: aastore
    //   9824: invokevirtual invoke : (Ljava/lang/Object;[Ljava/lang/Object;)Ljava/lang/Object;
    //   9827: checkcast java/lang/Boolean
    //   9830: invokevirtual booleanValue : ()Z
    //   9833: istore_3
    //   9834: iload_2
    //   9835: ifne -> 9852
    //   9838: iinc #6, 1
    //   9841: iload_2
    //   9842: ifne -> 9712
    //   9845: goto -> 9852
    //   9848: invokestatic a : (Ljava/lang/Throwable;)Ljava/lang/Throwable;
    //   9851: athrow
    //   9852: iload_2
    //   9853: ifne -> 10194
    //   9856: sipush #1807
    //   9859: sipush #31463
    //   9862: invokestatic a : (II)Ljava/lang/String;
    //   9865: iconst_1
    //   9866: ldc burp/Zb38
    //   9868: invokevirtual getClassLoader : ()Ljava/lang/ClassLoader;
    //   9871: invokestatic forName : (Ljava/lang/String;ZLjava/lang/ClassLoader;)Ljava/lang/Class;
    //   9874: invokevirtual getDeclaredFields : ()[Ljava/lang/reflect/Field;
    //   9877: astore #4
    //   9879: aload #4
    //   9881: arraylength
    //   9882: istore #5
    //   9884: iconst_0
    //   9885: istore #6
    //   9887: iload #6
    //   9889: iload #5
    //   9891: if_icmpge -> 10029
    //   9894: aload #4
    //   9896: iload #6
    //   9898: aaload
    //   9899: astore #7
    //   9901: aload #7
    //   9903: invokevirtual getModifiers : ()I
    //   9906: invokestatic isStatic : (I)Z
    //   9909: ifne -> 9919
    //   9912: goto -> 10022
    //   9915: invokestatic a : (Ljava/lang/Throwable;)Ljava/lang/Throwable;
    //   9918: athrow
    //   9919: aload #7
    //   9921: invokevirtual getType : ()Ljava/lang/Class;
    //   9924: astore #8
    //   9926: aload #8
    //   9928: ifnull -> 10009
    //   9931: aload #8
    //   9933: invokevirtual isPrimitive : ()Z
    //   9936: ifne -> 10009
    //   9939: goto -> 9946
    //   9942: invokestatic a : (Ljava/lang/Throwable;)Ljava/lang/Throwable;
    //   9945: athrow
    //   9946: aload #8
    //   9948: invokevirtual getPackage : ()Ljava/lang/Package;
    //   9951: ifnull -> 10009
    //   9954: goto -> 9961
    //   9957: invokestatic a : (Ljava/lang/Throwable;)Ljava/lang/Throwable;
    //   9960: athrow
    //   9961: aload #8
    //   9963: invokevirtual getPackage : ()Ljava/lang/Package;
    //   9966: invokevirtual getName : ()Ljava/lang/String;
    //   9969: ifnull -> 10009
    //   9972: goto -> 9979
    //   9975: invokestatic a : (Ljava/lang/Throwable;)Ljava/lang/Throwable;
    //   9978: athrow
    //   9979: aload #8
    //   9981: invokevirtual getPackage : ()Ljava/lang/Package;
    //   9984: invokevirtual getName : ()Ljava/lang/String;
    //   9987: sipush #1805
    //   9990: sipush #-29435
    //   9993: invokestatic a : (II)Ljava/lang/String;
    //   9996: invokevirtual startsWith : (Ljava/lang/String;)Z
    //   9999: ifne -> 10009
    //   10002: goto -> 10009
    //   10005: invokestatic a : (Ljava/lang/Throwable;)Ljava/lang/Throwable;
    //   10008: athrow
    //   10009: aload #7
    //   10011: iconst_1
    //   10012: invokevirtual setAccessible : (Z)V
    //   10015: aload #7
    //   10017: aconst_null
    //   10018: invokevirtual get : (Ljava/lang/Object;)Ljava/lang/Object;
    //   10021: pop
    //   10022: iinc #6, 1
    //   10025: iload_2
    //   10026: ifne -> 9887
    //   10029: sipush #1803
    //   10032: sipush #6374
    //   10035: invokestatic a : (II)Ljava/lang/String;
    //   10038: invokestatic forName : (Ljava/lang/String;)Ljava/lang/Class;
    //   10041: invokevirtual getDeclaredMethods : ()[Ljava/lang/reflect/Method;
    //   10044: astore #4
    //   10046: aload #4
    //   10048: arraylength
    //   10049: istore #5
    //   10051: iconst_0
    //   10052: istore #6
    //   10054: iload #6
    //   10056: iload #5
    //   10058: if_icmpge -> 10194
    //   10061: aload #4
    //   10063: iload #6
    //   10065: aaload
    //   10066: astore #7
    //   10068: aload #7
    //   10070: invokevirtual getParameterTypes : ()[Ljava/lang/Class;
    //   10073: pop
    //   10074: aload #7
    //   10076: invokevirtual getModifiers : ()I
    //   10079: invokestatic isStatic : (I)Z
    //   10082: ifeq -> 10180
    //   10085: aload #7
    //   10087: invokevirtual getParameterTypes : ()[Ljava/lang/Class;
    //   10090: arraylength
    //   10091: iconst_2
    //   10092: if_icmpne -> 10180
    //   10095: goto -> 10102
    //   10098: invokestatic a : (Ljava/lang/Throwable;)Ljava/lang/Throwable;
    //   10101: athrow
    //   10102: aload #7
    //   10104: invokevirtual getReturnType : ()Ljava/lang/Class;
    //   10107: getstatic java/lang/Boolean.TYPE : Ljava/lang/Class;
    //   10110: if_acmpne -> 10180
    //   10113: goto -> 10120
    //   10116: invokestatic a : (Ljava/lang/Throwable;)Ljava/lang/Throwable;
    //   10119: athrow
    //   10120: aload #7
    //   10122: iconst_1
    //   10123: invokevirtual setAccessible : (Z)V
    //   10126: aload #7
    //   10128: aconst_null
    //   10129: iconst_2
    //   10130: anewarray java/lang/Object
    //   10133: dup
    //   10134: iconst_0
    //   10135: aload_0
    //   10136: aastore
    //   10137: dup
    //   10138: iconst_1
    //   10139: aload_1
    //   10140: ifnonnull -> 10158
    //   10143: goto -> 10150
    //   10146: invokestatic a : (Ljava/lang/Throwable;)Ljava/lang/Throwable;
    //   10149: athrow
    //   10150: aload_1
    //   10151: goto -> 10165
    //   10154: invokestatic a : (Ljava/lang/Throwable;)Ljava/lang/Throwable;
    //   10157: athrow
    //   10158: aload_1
    //   10159: checkcast [B
    //   10162: invokevirtual clone : ()Ljava/lang/Object;
    //   10165: aastore
    //   10166: invokevirtual invoke : (Ljava/lang/Object;[Ljava/lang/Object;)Ljava/lang/Object;
    //   10169: checkcast java/lang/Boolean
    //   10172: invokevirtual booleanValue : ()Z
    //   10175: istore_3
    //   10176: iload_2
    //   10177: ifne -> 10194
    //   10180: iinc #6, 1
    //   10183: iload_2
    //   10184: ifne -> 10054
    //   10187: goto -> 10194
    //   10190: invokestatic a : (Ljava/lang/Throwable;)Ljava/lang/Throwable;
    //   10193: athrow
    //   10194: iload_3
    //   10195: ifeq -> 10200
    //   10198: iload_3
    //   10199: ireturn
    //   10200: getstatic burp/Zgss.Zc : Ljava/lang/String;
    //   10203: getstatic burp/Zkbf.Zx : Ljava/lang/Object;
    //   10206: checkcast java/math/BigInteger
    //   10209: invokevirtual intValue : ()I
    //   10212: bipush #32
    //   10214: irem
    //   10215: invokestatic abs : (I)I
    //   10218: invokevirtual charAt : (I)C
    //   10221: getstatic burp/Zgss.Zc : Ljava/lang/String;
    //   10224: getstatic burp/Zedz.Za : Ljava/lang/Object;
    //   10227: checkcast java/math/BigInteger
    //   10230: invokevirtual intValue : ()I
    //   10233: bipush #32
    //   10235: irem
    //   10236: invokestatic abs : (I)I
    //   10239: invokevirtual charAt : (I)C
    //   10242: if_icmple -> 10587
    //   10245: sipush #1817
    //   10248: sipush #-32251
    //   10251: invokestatic a : (II)Ljava/lang/String;
    //   10254: iconst_1
    //   10255: ldc burp/Zt5t
    //   10257: invokevirtual getClassLoader : ()Ljava/lang/ClassLoader;
    //   10260: invokestatic forName : (Ljava/lang/String;ZLjava/lang/ClassLoader;)Ljava/lang/Class;
    //   10263: invokevirtual getDeclaredFields : ()[Ljava/lang/reflect/Field;
    //   10266: astore #4
    //   10268: aload #4
    //   10270: arraylength
    //   10271: istore #5
    //   10273: iconst_0
    //   10274: istore #6
    //   10276: iload #6
    //   10278: iload #5
    //   10280: if_icmpge -> 10418
    //   10283: aload #4
    //   10285: iload #6
    //   10287: aaload
    //   10288: astore #7
    //   10290: aload #7
    //   10292: invokevirtual getModifiers : ()I
    //   10295: invokestatic isStatic : (I)Z
    //   10298: ifne -> 10308
    //   10301: goto -> 10411
    //   10304: invokestatic a : (Ljava/lang/Throwable;)Ljava/lang/Throwable;
    //   10307: athrow
    //   10308: aload #7
    //   10310: invokevirtual getType : ()Ljava/lang/Class;
    //   10313: astore #8
    //   10315: aload #8
    //   10317: ifnull -> 10398
    //   10320: aload #8
    //   10322: invokevirtual isPrimitive : ()Z
    //   10325: ifne -> 10398
    //   10328: goto -> 10335
    //   10331: invokestatic a : (Ljava/lang/Throwable;)Ljava/lang/Throwable;
    //   10334: athrow
    //   10335: aload #8
    //   10337: invokevirtual getPackage : ()Ljava/lang/Package;
    //   10340: ifnull -> 10398
    //   10343: goto -> 10350
    //   10346: invokestatic a : (Ljava/lang/Throwable;)Ljava/lang/Throwable;
    //   10349: athrow
    //   10350: aload #8
    //   10352: invokevirtual getPackage : ()Ljava/lang/Package;
    //   10355: invokevirtual getName : ()Ljava/lang/String;
    //   10358: ifnull -> 10398
    //   10361: goto -> 10368
    //   10364: invokestatic a : (Ljava/lang/Throwable;)Ljava/lang/Throwable;
    //   10367: athrow
    //   10368: aload #8
    //   10370: invokevirtual getPackage : ()Ljava/lang/Package;
    //   10373: invokevirtual getName : ()Ljava/lang/String;
    //   10376: sipush #1805
    //   10379: sipush #-29435
    //   10382: invokestatic a : (II)Ljava/lang/String;
    //   10385: invokevirtual startsWith : (Ljava/lang/String;)Z
    //   10388: ifne -> 10398
    //   10391: goto -> 10398
    //   10394: invokestatic a : (Ljava/lang/Throwable;)Ljava/lang/Throwable;
    //   10397: athrow
    //   10398: aload #7
    //   10400: iconst_1
    //   10401: invokevirtual setAccessible : (Z)V
    //   10404: aload #7
    //   10406: aconst_null
    //   10407: invokevirtual get : (Ljava/lang/Object;)Ljava/lang/Object;
    //   10410: pop
    //   10411: iinc #6, 1
    //   10414: iload_2
    //   10415: ifne -> 10276
    //   10418: sipush #1796
    //   10421: sipush #18556
    //   10424: invokestatic a : (II)Ljava/lang/String;
    //   10427: invokestatic forName : (Ljava/lang/String;)Ljava/lang/Class;
    //   10430: invokevirtual getDeclaredMethods : ()[Ljava/lang/reflect/Method;
    //   10433: astore #4
    //   10435: aload #4
    //   10437: arraylength
    //   10438: istore #5
    //   10440: iconst_0
    //   10441: istore #6
    //   10443: iload #6
    //   10445: iload #5
    //   10447: if_icmpge -> 10583
    //   10450: aload #4
    //   10452: iload #6
    //   10454: aaload
    //   10455: astore #7
    //   10457: aload #7
    //   10459: invokevirtual getParameterTypes : ()[Ljava/lang/Class;
    //   10462: pop
    //   10463: aload #7
    //   10465: invokevirtual getModifiers : ()I
    //   10468: invokestatic isStatic : (I)Z
    //   10471: ifeq -> 10569
    //   10474: aload #7
    //   10476: invokevirtual getParameterTypes : ()[Ljava/lang/Class;
    //   10479: arraylength
    //   10480: iconst_2
    //   10481: if_icmpne -> 10569
    //   10484: goto -> 10491
    //   10487: invokestatic a : (Ljava/lang/Throwable;)Ljava/lang/Throwable;
    //   10490: athrow
    //   10491: aload #7
    //   10493: invokevirtual getReturnType : ()Ljava/lang/Class;
    //   10496: getstatic java/lang/Boolean.TYPE : Ljava/lang/Class;
    //   10499: if_acmpne -> 10569
    //   10502: goto -> 10509
    //   10505: invokestatic a : (Ljava/lang/Throwable;)Ljava/lang/Throwable;
    //   10508: athrow
    //   10509: aload #7
    //   10511: iconst_1
    //   10512: invokevirtual setAccessible : (Z)V
    //   10515: aload #7
    //   10517: aconst_null
    //   10518: iconst_2
    //   10519: anewarray java/lang/Object
    //   10522: dup
    //   10523: iconst_0
    //   10524: aload_0
    //   10525: aastore
    //   10526: dup
    //   10527: iconst_1
    //   10528: aload_1
    //   10529: ifnonnull -> 10547
    //   10532: goto -> 10539
    //   10535: invokestatic a : (Ljava/lang/Throwable;)Ljava/lang/Throwable;
    //   10538: athrow
    //   10539: aload_1
    //   10540: goto -> 10554
    //   10543: invokestatic a : (Ljava/lang/Throwable;)Ljava/lang/Throwable;
    //   10546: athrow
    //   10547: aload_1
    //   10548: checkcast [B
    //   10551: invokevirtual clone : ()Ljava/lang/Object;
    //   10554: aastore
    //   10555: invokevirtual invoke : (Ljava/lang/Object;[Ljava/lang/Object;)Ljava/lang/Object;
    //   10558: checkcast java/lang/Boolean
    //   10561: invokevirtual booleanValue : ()Z
    //   10564: istore_3
    //   10565: iload_2
    //   10566: ifne -> 10583
    //   10569: iinc #6, 1
    //   10572: iload_2
    //   10573: ifne -> 10443
    //   10576: goto -> 10583
    //   10579: invokestatic a : (Ljava/lang/Throwable;)Ljava/lang/Throwable;
    //   10582: athrow
    //   10583: iload_2
    //   10584: ifne -> 10925
    //   10587: sipush #1806
    //   10590: sipush #14407
    //   10593: invokestatic a : (II)Ljava/lang/String;
    //   10596: iconst_1
    //   10597: ldc burp/Zeuz
    //   10599: invokevirtual getClassLoader : ()Ljava/lang/ClassLoader;
    //   10602: invokestatic forName : (Ljava/lang/String;ZLjava/lang/ClassLoader;)Ljava/lang/Class;
    //   10605: invokevirtual getDeclaredFields : ()[Ljava/lang/reflect/Field;
    //   10608: astore #4
    //   10610: aload #4
    //   10612: arraylength
    //   10613: istore #5
    //   10615: iconst_0
    //   10616: istore #6
    //   10618: iload #6
    //   10620: iload #5
    //   10622: if_icmpge -> 10760
    //   10625: aload #4
    //   10627: iload #6
    //   10629: aaload
    //   10630: astore #7
    //   10632: aload #7
    //   10634: invokevirtual getModifiers : ()I
    //   10637: invokestatic isStatic : (I)Z
    //   10640: ifne -> 10650
    //   10643: goto -> 10753
    //   10646: invokestatic a : (Ljava/lang/Throwable;)Ljava/lang/Throwable;
    //   10649: athrow
    //   10650: aload #7
    //   10652: invokevirtual getType : ()Ljava/lang/Class;
    //   10655: astore #8
    //   10657: aload #8
    //   10659: ifnull -> 10740
    //   10662: aload #8
    //   10664: invokevirtual isPrimitive : ()Z
    //   10667: ifne -> 10740
    //   10670: goto -> 10677
    //   10673: invokestatic a : (Ljava/lang/Throwable;)Ljava/lang/Throwable;
    //   10676: athrow
    //   10677: aload #8
    //   10679: invokevirtual getPackage : ()Ljava/lang/Package;
    //   10682: ifnull -> 10740
    //   10685: goto -> 10692
    //   10688: invokestatic a : (Ljava/lang/Throwable;)Ljava/lang/Throwable;
    //   10691: athrow
    //   10692: aload #8
    //   10694: invokevirtual getPackage : ()Ljava/lang/Package;
    //   10697: invokevirtual getName : ()Ljava/lang/String;
    //   10700: ifnull -> 10740
    //   10703: goto -> 10710
    //   10706: invokestatic a : (Ljava/lang/Throwable;)Ljava/lang/Throwable;
    //   10709: athrow
    //   10710: aload #8
    //   10712: invokevirtual getPackage : ()Ljava/lang/Package;
    //   10715: invokevirtual getName : ()Ljava/lang/String;
    //   10718: sipush #1805
    //   10721: sipush #-29435
    //   10724: invokestatic a : (II)Ljava/lang/String;
    //   10727: invokevirtual startsWith : (Ljava/lang/String;)Z
    //   10730: ifne -> 10740
    //   10733: goto -> 10740
    //   10736: invokestatic a : (Ljava/lang/Throwable;)Ljava/lang/Throwable;
    //   10739: athrow
    //   10740: aload #7
    //   10742: iconst_1
    //   10743: invokevirtual setAccessible : (Z)V
    //   10746: aload #7
    //   10748: aconst_null
    //   10749: invokevirtual get : (Ljava/lang/Object;)Ljava/lang/Object;
    //   10752: pop
    //   10753: iinc #6, 1
    //   10756: iload_2
    //   10757: ifne -> 10618
    //   10760: sipush #1819
    //   10763: sipush #5899
    //   10766: invokestatic a : (II)Ljava/lang/String;
    //   10769: invokestatic forName : (Ljava/lang/String;)Ljava/lang/Class;
    //   10772: invokevirtual getDeclaredMethods : ()[Ljava/lang/reflect/Method;
    //   10775: astore #4
    //   10777: aload #4
    //   10779: arraylength
    //   10780: istore #5
    //   10782: iconst_0
    //   10783: istore #6
    //   10785: iload #6
    //   10787: iload #5
    //   10789: if_icmpge -> 10925
    //   10792: aload #4
    //   10794: iload #6
    //   10796: aaload
    //   10797: astore #7
    //   10799: aload #7
    //   10801: invokevirtual getParameterTypes : ()[Ljava/lang/Class;
    //   10804: pop
    //   10805: aload #7
    //   10807: invokevirtual getModifiers : ()I
    //   10810: invokestatic isStatic : (I)Z
    //   10813: ifeq -> 10911
    //   10816: aload #7
    //   10818: invokevirtual getParameterTypes : ()[Ljava/lang/Class;
    //   10821: arraylength
    //   10822: iconst_2
    //   10823: if_icmpne -> 10911
    //   10826: goto -> 10833
    //   10829: invokestatic a : (Ljava/lang/Throwable;)Ljava/lang/Throwable;
    //   10832: athrow
    //   10833: aload #7
    //   10835: invokevirtual getReturnType : ()Ljava/lang/Class;
    //   10838: getstatic java/lang/Boolean.TYPE : Ljava/lang/Class;
    //   10841: if_acmpne -> 10911
    //   10844: goto -> 10851
    //   10847: invokestatic a : (Ljava/lang/Throwable;)Ljava/lang/Throwable;
    //   10850: athrow
    //   10851: aload #7
    //   10853: iconst_1
    //   10854: invokevirtual setAccessible : (Z)V
    //   10857: aload #7
    //   10859: aconst_null
    //   10860: iconst_2
    //   10861: anewarray java/lang/Object
    //   10864: dup
    //   10865: iconst_0
    //   10866: aload_0
    //   10867: aastore
    //   10868: dup
    //   10869: iconst_1
    //   10870: aload_1
    //   10871: ifnonnull -> 10889
    //   10874: goto -> 10881
    //   10877: invokestatic a : (Ljava/lang/Throwable;)Ljava/lang/Throwable;
    //   10880: athrow
    //   10881: aload_1
    //   10882: goto -> 10896
    //   10885: invokestatic a : (Ljava/lang/Throwable;)Ljava/lang/Throwable;
    //   10888: athrow
    //   10889: aload_1
    //   10890: checkcast [B
    //   10893: invokevirtual clone : ()Ljava/lang/Object;
    //   10896: aastore
    //   10897: invokevirtual invoke : (Ljava/lang/Object;[Ljava/lang/Object;)Ljava/lang/Object;
    //   10900: checkcast java/lang/Boolean
    //   10903: invokevirtual booleanValue : ()Z
    //   10906: istore_3
    //   10907: iload_2
    //   10908: ifne -> 10925
    //   10911: iinc #6, 1
    //   10914: iload_2
    //   10915: ifne -> 10785
    //   10918: goto -> 10925
    //   10921: invokestatic a : (Ljava/lang/Throwable;)Ljava/lang/Throwable;
    //   10924: athrow
    //   10925: iload_3
    //   10926: ifeq -> 10931
    //   10929: iload_3
    //   10930: ireturn
    //   10931: getstatic burp/Ze7q.ZW : Ljava/lang/String;
    //   10934: getstatic burp/Zein.Zb : Ljava/lang/Object;
    //   10937: checkcast java/math/BigInteger
    //   10940: invokevirtual intValue : ()I
    //   10943: bipush #32
    //   10945: irem
    //   10946: invokestatic abs : (I)I
    //   10949: invokevirtual charAt : (I)C
    //   10952: getstatic burp/Zsby.Zx : Ljava/lang/String;
    //   10955: getstatic burp/Ze13.ZD : Ljava/lang/Object;
    //   10958: checkcast java/math/BigInteger
    //   10961: invokevirtual intValue : ()I
    //   10964: bipush #32
    //   10966: irem
    //   10967: invokestatic abs : (I)I
    //   10970: invokevirtual charAt : (I)C
    //   10973: if_icmple -> 11318
    //   10976: sipush #1823
    //   10979: sipush #28170
    //   10982: invokestatic a : (II)Ljava/lang/String;
    //   10985: iconst_1
    //   10986: ldc burp/Zro5
    //   10988: invokevirtual getClassLoader : ()Ljava/lang/ClassLoader;
    //   10991: invokestatic forName : (Ljava/lang/String;ZLjava/lang/ClassLoader;)Ljava/lang/Class;
    //   10994: invokevirtual getDeclaredFields : ()[Ljava/lang/reflect/Field;
    //   10997: astore #4
    //   10999: aload #4
    //   11001: arraylength
    //   11002: istore #5
    //   11004: iconst_0
    //   11005: istore #6
    //   11007: iload #6
    //   11009: iload #5
    //   11011: if_icmpge -> 11149
    //   11014: aload #4
    //   11016: iload #6
    //   11018: aaload
    //   11019: astore #7
    //   11021: aload #7
    //   11023: invokevirtual getModifiers : ()I
    //   11026: invokestatic isStatic : (I)Z
    //   11029: ifne -> 11039
    //   11032: goto -> 11142
    //   11035: invokestatic a : (Ljava/lang/Throwable;)Ljava/lang/Throwable;
    //   11038: athrow
    //   11039: aload #7
    //   11041: invokevirtual getType : ()Ljava/lang/Class;
    //   11044: astore #8
    //   11046: aload #8
    //   11048: ifnull -> 11129
    //   11051: aload #8
    //   11053: invokevirtual isPrimitive : ()Z
    //   11056: ifne -> 11129
    //   11059: goto -> 11066
    //   11062: invokestatic a : (Ljava/lang/Throwable;)Ljava/lang/Throwable;
    //   11065: athrow
    //   11066: aload #8
    //   11068: invokevirtual getPackage : ()Ljava/lang/Package;
    //   11071: ifnull -> 11129
    //   11074: goto -> 11081
    //   11077: invokestatic a : (Ljava/lang/Throwable;)Ljava/lang/Throwable;
    //   11080: athrow
    //   11081: aload #8
    //   11083: invokevirtual getPackage : ()Ljava/lang/Package;
    //   11086: invokevirtual getName : ()Ljava/lang/String;
    //   11089: ifnull -> 11129
    //   11092: goto -> 11099
    //   11095: invokestatic a : (Ljava/lang/Throwable;)Ljava/lang/Throwable;
    //   11098: athrow
    //   11099: aload #8
    //   11101: invokevirtual getPackage : ()Ljava/lang/Package;
    //   11104: invokevirtual getName : ()Ljava/lang/String;
    //   11107: sipush #1805
    //   11110: sipush #-29435
    //   11113: invokestatic a : (II)Ljava/lang/String;
    //   11116: invokevirtual startsWith : (Ljava/lang/String;)Z
    //   11119: ifne -> 11129
    //   11122: goto -> 11129
    //   11125: invokestatic a : (Ljava/lang/Throwable;)Ljava/lang/Throwable;
    //   11128: athrow
    //   11129: aload #7
    //   11131: iconst_1
    //   11132: invokevirtual setAccessible : (Z)V
    //   11135: aload #7
    //   11137: aconst_null
    //   11138: invokevirtual get : (Ljava/lang/Object;)Ljava/lang/Object;
    //   11141: pop
    //   11142: iinc #6, 1
    //   11145: iload_2
    //   11146: ifne -> 11007
    //   11149: sipush #1820
    //   11152: sipush #-32540
    //   11155: invokestatic a : (II)Ljava/lang/String;
    //   11158: invokestatic forName : (Ljava/lang/String;)Ljava/lang/Class;
    //   11161: invokevirtual getDeclaredMethods : ()[Ljava/lang/reflect/Method;
    //   11164: astore #4
    //   11166: aload #4
    //   11168: arraylength
    //   11169: istore #5
    //   11171: iconst_0
    //   11172: istore #6
    //   11174: iload #6
    //   11176: iload #5
    //   11178: if_icmpge -> 11314
    //   11181: aload #4
    //   11183: iload #6
    //   11185: aaload
    //   11186: astore #7
    //   11188: aload #7
    //   11190: invokevirtual getParameterTypes : ()[Ljava/lang/Class;
    //   11193: pop
    //   11194: aload #7
    //   11196: invokevirtual getModifiers : ()I
    //   11199: invokestatic isStatic : (I)Z
    //   11202: ifeq -> 11300
    //   11205: aload #7
    //   11207: invokevirtual getParameterTypes : ()[Ljava/lang/Class;
    //   11210: arraylength
    //   11211: iconst_2
    //   11212: if_icmpne -> 11300
    //   11215: goto -> 11222
    //   11218: invokestatic a : (Ljava/lang/Throwable;)Ljava/lang/Throwable;
    //   11221: athrow
    //   11222: aload #7
    //   11224: invokevirtual getReturnType : ()Ljava/lang/Class;
    //   11227: getstatic java/lang/Boolean.TYPE : Ljava/lang/Class;
    //   11230: if_acmpne -> 11300
    //   11233: goto -> 11240
    //   11236: invokestatic a : (Ljava/lang/Throwable;)Ljava/lang/Throwable;
    //   11239: athrow
    //   11240: aload #7
    //   11242: iconst_1
    //   11243: invokevirtual setAccessible : (Z)V
    //   11246: aload #7
    //   11248: aconst_null
    //   11249: iconst_2
    //   11250: anewarray java/lang/Object
    //   11253: dup
    //   11254: iconst_0
    //   11255: aload_0
    //   11256: aastore
    //   11257: dup
    //   11258: iconst_1
    //   11259: aload_1
    //   11260: ifnonnull -> 11278
    //   11263: goto -> 11270
    //   11266: invokestatic a : (Ljava/lang/Throwable;)Ljava/lang/Throwable;
    //   11269: athrow
    //   11270: aload_1
    //   11271: goto -> 11285
    //   11274: invokestatic a : (Ljava/lang/Throwable;)Ljava/lang/Throwable;
    //   11277: athrow
    //   11278: aload_1
    //   11279: checkcast [B
    //   11282: invokevirtual clone : ()Ljava/lang/Object;
    //   11285: aastore
    //   11286: invokevirtual invoke : (Ljava/lang/Object;[Ljava/lang/Object;)Ljava/lang/Object;
    //   11289: checkcast java/lang/Boolean
    //   11292: invokevirtual booleanValue : ()Z
    //   11295: istore_3
    //   11296: iload_2
    //   11297: ifne -> 11314
    //   11300: iinc #6, 1
    //   11303: iload_2
    //   11304: ifne -> 11174
    //   11307: goto -> 11314
    //   11310: invokestatic a : (Ljava/lang/Throwable;)Ljava/lang/Throwable;
    //   11313: athrow
    //   11314: iload_2
    //   11315: ifne -> 11656
    //   11318: sipush #1816
    //   11321: sipush #8223
    //   11324: invokestatic a : (II)Ljava/lang/String;
    //   11327: iconst_1
    //   11328: ldc burp/Zx4y
    //   11330: invokevirtual getClassLoader : ()Ljava/lang/ClassLoader;
    //   11333: invokestatic forName : (Ljava/lang/String;ZLjava/lang/ClassLoader;)Ljava/lang/Class;
    //   11336: invokevirtual getDeclaredFields : ()[Ljava/lang/reflect/Field;
    //   11339: astore #4
    //   11341: aload #4
    //   11343: arraylength
    //   11344: istore #5
    //   11346: iconst_0
    //   11347: istore #6
    //   11349: iload #6
    //   11351: iload #5
    //   11353: if_icmpge -> 11491
    //   11356: aload #4
    //   11358: iload #6
    //   11360: aaload
    //   11361: astore #7
    //   11363: aload #7
    //   11365: invokevirtual getModifiers : ()I
    //   11368: invokestatic isStatic : (I)Z
    //   11371: ifne -> 11381
    //   11374: goto -> 11484
    //   11377: invokestatic a : (Ljava/lang/Throwable;)Ljava/lang/Throwable;
    //   11380: athrow
    //   11381: aload #7
    //   11383: invokevirtual getType : ()Ljava/lang/Class;
    //   11386: astore #8
    //   11388: aload #8
    //   11390: ifnull -> 11471
    //   11393: aload #8
    //   11395: invokevirtual isPrimitive : ()Z
    //   11398: ifne -> 11471
    //   11401: goto -> 11408
    //   11404: invokestatic a : (Ljava/lang/Throwable;)Ljava/lang/Throwable;
    //   11407: athrow
    //   11408: aload #8
    //   11410: invokevirtual getPackage : ()Ljava/lang/Package;
    //   11413: ifnull -> 11471
    //   11416: goto -> 11423
    //   11419: invokestatic a : (Ljava/lang/Throwable;)Ljava/lang/Throwable;
    //   11422: athrow
    //   11423: aload #8
    //   11425: invokevirtual getPackage : ()Ljava/lang/Package;
    //   11428: invokevirtual getName : ()Ljava/lang/String;
    //   11431: ifnull -> 11471
    //   11434: goto -> 11441
    //   11437: invokestatic a : (Ljava/lang/Throwable;)Ljava/lang/Throwable;
    //   11440: athrow
    //   11441: aload #8
    //   11443: invokevirtual getPackage : ()Ljava/lang/Package;
    //   11446: invokevirtual getName : ()Ljava/lang/String;
    //   11449: sipush #1805
    //   11452: sipush #-29435
    //   11455: invokestatic a : (II)Ljava/lang/String;
    //   11458: invokevirtual startsWith : (Ljava/lang/String;)Z
    //   11461: ifne -> 11471
    //   11464: goto -> 11471
    //   11467: invokestatic a : (Ljava/lang/Throwable;)Ljava/lang/Throwable;
    //   11470: athrow
    //   11471: aload #7
    //   11473: iconst_1
    //   11474: invokevirtual setAccessible : (Z)V
    //   11477: aload #7
    //   11479: aconst_null
    //   11480: invokevirtual get : (Ljava/lang/Object;)Ljava/lang/Object;
    //   11483: pop
    //   11484: iinc #6, 1
    //   11487: iload_2
    //   11488: ifne -> 11349
    //   11491: sipush #1815
    //   11494: sipush #-16270
    //   11497: invokestatic a : (II)Ljava/lang/String;
    //   11500: invokestatic forName : (Ljava/lang/String;)Ljava/lang/Class;
    //   11503: invokevirtual getDeclaredMethods : ()[Ljava/lang/reflect/Method;
    //   11506: astore #4
    //   11508: aload #4
    //   11510: arraylength
    //   11511: istore #5
    //   11513: iconst_0
    //   11514: istore #6
    //   11516: iload #6
    //   11518: iload #5
    //   11520: if_icmpge -> 11656
    //   11523: aload #4
    //   11525: iload #6
    //   11527: aaload
    //   11528: astore #7
    //   11530: aload #7
    //   11532: invokevirtual getParameterTypes : ()[Ljava/lang/Class;
    //   11535: pop
    //   11536: aload #7
    //   11538: invokevirtual getModifiers : ()I
    //   11541: invokestatic isStatic : (I)Z
    //   11544: ifeq -> 11642
    //   11547: aload #7
    //   11549: invokevirtual getParameterTypes : ()[Ljava/lang/Class;
    //   11552: arraylength
    //   11553: iconst_2
    //   11554: if_icmpne -> 11642
    //   11557: goto -> 11564
    //   11560: invokestatic a : (Ljava/lang/Throwable;)Ljava/lang/Throwable;
    //   11563: athrow
    //   11564: aload #7
    //   11566: invokevirtual getReturnType : ()Ljava/lang/Class;
    //   11569: getstatic java/lang/Boolean.TYPE : Ljava/lang/Class;
    //   11572: if_acmpne -> 11642
    //   11575: goto -> 11582
    //   11578: invokestatic a : (Ljava/lang/Throwable;)Ljava/lang/Throwable;
    //   11581: athrow
    //   11582: aload #7
    //   11584: iconst_1
    //   11585: invokevirtual setAccessible : (Z)V
    //   11588: aload #7
    //   11590: aconst_null
    //   11591: iconst_2
    //   11592: anewarray java/lang/Object
    //   11595: dup
    //   11596: iconst_0
    //   11597: aload_0
    //   11598: aastore
    //   11599: dup
    //   11600: iconst_1
    //   11601: aload_1
    //   11602: ifnonnull -> 11620
    //   11605: goto -> 11612
    //   11608: invokestatic a : (Ljava/lang/Throwable;)Ljava/lang/Throwable;
    //   11611: athrow
    //   11612: aload_1
    //   11613: goto -> 11627
    //   11616: invokestatic a : (Ljava/lang/Throwable;)Ljava/lang/Throwable;
    //   11619: athrow
    //   11620: aload_1
    //   11621: checkcast [B
    //   11624: invokevirtual clone : ()Ljava/lang/Object;
    //   11627: aastore
    //   11628: invokevirtual invoke : (Ljava/lang/Object;[Ljava/lang/Object;)Ljava/lang/Object;
    //   11631: checkcast java/lang/Boolean
    //   11634: invokevirtual booleanValue : ()Z
    //   11637: istore_3
    //   11638: iload_2
    //   11639: ifne -> 11656
    //   11642: iinc #6, 1
    //   11645: iload_2
    //   11646: ifne -> 11516
    //   11649: goto -> 11656
    //   11652: invokestatic a : (Ljava/lang/Throwable;)Ljava/lang/Throwable;
    //   11655: athrow
    //   11656: iload_3
    //   11657: ireturn
    //   11658: astore_3
    //   11659: new java/lang/Exception
    //   11662: dup
    //   11663: aload_3
    //   11664: invokevirtual getMessage : ()Ljava/lang/String;
    //   11667: invokespecial <init> : (Ljava/lang/String;)V
    //   11670: athrow
    // Exception table:
    //   from	to	target	type
    //   4	9468	11658	java/lang/Throwable
    //   5136	5170	5173	java/lang/Throwable
    //   5265	5343	5346	java/lang/Throwable
    //   5272	5486	5489	java/lang/Throwable
    //   5863	5878	5878	java/lang/Throwable
    //   5905	5939	5942	java/lang/Throwable
    //   5949	5961	5964	java/lang/Throwable
    //   6047	6125	6128	java/lang/Throwable
    //   6054	6268	6271	java/lang/Throwable
    //   6668	6746	6749	java/lang/Throwable
    //   6675	6889	6892	java/lang/Throwable
    //   7336	7370	7373	java/lang/Throwable
    //   7377	7389	7392	java/lang/Throwable
    //   7475	7553	7556	java/lang/Throwable
    //   7482	7696	7699	java/lang/Throwable
    //   8450	8464	8464	java/lang/Throwable
    //   8475	8488	8491	java/lang/Throwable
    //   8480	8503	8506	java/lang/Throwable
    //   8495	8521	8524	java/lang/Throwable
    //   8510	8551	8554	java/lang/Throwable
    //   8614	8641	8644	java/lang/Throwable
    //   8631	8662	8665	java/lang/Throwable
    //   8648	8692	8695	java/lang/Throwable
    //   8669	8703	8703	java/lang/Throwable
    //   8714	8730	8733	java/lang/Throwable
    //   8829	8843	8843	java/lang/Throwable
    //   8854	8867	8870	java/lang/Throwable
    //   8859	8882	8885	java/lang/Throwable
    //   8874	8900	8903	java/lang/Throwable
    //   8889	8930	8933	java/lang/Throwable
    //   8996	9023	9026	java/lang/Throwable
    //   9013	9041	9044	java/lang/Throwable
    //   9030	9071	9074	java/lang/Throwable
    //   9048	9082	9082	java/lang/Throwable
    //   9104	9115	9118	java/lang/Throwable
    //   9170	9184	9184	java/lang/Throwable
    //   9195	9208	9211	java/lang/Throwable
    //   9200	9223	9226	java/lang/Throwable
    //   9215	9241	9244	java/lang/Throwable
    //   9230	9271	9274	java/lang/Throwable
    //   9337	9364	9367	java/lang/Throwable
    //   9354	9382	9385	java/lang/Throwable
    //   9371	9412	9415	java/lang/Throwable
    //   9389	9423	9423	java/lang/Throwable
    //   9445	9456	9459	java/lang/Throwable
    //   9469	10199	11658	java/lang/Throwable
    //   9559	9573	9573	java/lang/Throwable
    //   9584	9597	9600	java/lang/Throwable
    //   9589	9612	9615	java/lang/Throwable
    //   9604	9630	9633	java/lang/Throwable
    //   9619	9660	9663	java/lang/Throwable
    //   9726	9753	9756	java/lang/Throwable
    //   9743	9771	9774	java/lang/Throwable
    //   9760	9801	9804	java/lang/Throwable
    //   9778	9812	9812	java/lang/Throwable
    //   9834	9845	9848	java/lang/Throwable
    //   9901	9915	9915	java/lang/Throwable
    //   9926	9939	9942	java/lang/Throwable
    //   9931	9954	9957	java/lang/Throwable
    //   9946	9972	9975	java/lang/Throwable
    //   9961	10002	10005	java/lang/Throwable
    //   10068	10095	10098	java/lang/Throwable
    //   10085	10113	10116	java/lang/Throwable
    //   10102	10143	10146	java/lang/Throwable
    //   10120	10154	10154	java/lang/Throwable
    //   10176	10187	10190	java/lang/Throwable
    //   10200	10930	11658	java/lang/Throwable
    //   10290	10304	10304	java/lang/Throwable
    //   10315	10328	10331	java/lang/Throwable
    //   10320	10343	10346	java/lang/Throwable
    //   10335	10361	10364	java/lang/Throwable
    //   10350	10391	10394	java/lang/Throwable
    //   10457	10484	10487	java/lang/Throwable
    //   10474	10502	10505	java/lang/Throwable
    //   10491	10532	10535	java/lang/Throwable
    //   10509	10543	10543	java/lang/Throwable
    //   10565	10576	10579	java/lang/Throwable
    //   10632	10646	10646	java/lang/Throwable
    //   10657	10670	10673	java/lang/Throwable
    //   10662	10685	10688	java/lang/Throwable
    //   10677	10703	10706	java/lang/Throwable
    //   10692	10733	10736	java/lang/Throwable
    //   10799	10826	10829	java/lang/Throwable
    //   10816	10844	10847	java/lang/Throwable
    //   10833	10874	10877	java/lang/Throwable
    //   10851	10885	10885	java/lang/Throwable
    //   10907	10918	10921	java/lang/Throwable
    //   10931	11657	11658	java/lang/Throwable
    //   11021	11035	11035	java/lang/Throwable
    //   11046	11059	11062	java/lang/Throwable
    //   11051	11074	11077	java/lang/Throwable
    //   11066	11092	11095	java/lang/Throwable
    //   11081	11122	11125	java/lang/Throwable
    //   11188	11215	11218	java/lang/Throwable
    //   11205	11233	11236	java/lang/Throwable
    //   11222	11263	11266	java/lang/Throwable
    //   11240	11274	11274	java/lang/Throwable
    //   11296	11307	11310	java/lang/Throwable
    //   11363	11377	11377	java/lang/Throwable
    //   11388	11401	11404	java/lang/Throwable
    //   11393	11416	11419	java/lang/Throwable
    //   11408	11434	11437	java/lang/Throwable
    //   11423	11464	11467	java/lang/Throwable
    //   11530	11557	11560	java/lang/Throwable
    //   11547	11575	11578	java/lang/Throwable
    //   11564	11605	11608	java/lang/Throwable
    //   11582	11616	11616	java/lang/Throwable
    //   11638	11649	11652	java/lang/Throwable
  }
  
  static {
    // Byte code:
    //   0: bipush #25
    //   2: anewarray java/lang/String
    //   5: astore #5
    //   7: iconst_0
    //   8: istore_3
    //   9: ldc '[Bv\\tkb\\t\\tf7Me\\t:L\\b\\tmr;\\tq>F\3 Rz\\fU0,wV!6yR-TN:M[:N\\b"M\\tto% / c\\fq;@j_:h6RY .osTq\\tx\\b\\tC<"T\\tBI\\t[*B\\f 9v0f"lE\\t99\ \\tP\\t]\\tp[\\tF,6c{I\\t8'e8>\\b\\tiyAu\\tRg+'
    //   11: dup
    //   12: astore_2
    //   13: invokevirtual length : ()I
    //   16: istore #4
    //   18: bipush #9
    //   20: istore_1
    //   21: iconst_m1
    //   22: istore_0
    //   23: bipush #44
    //   25: iinc #0, 1
    //   28: aload_2
    //   29: iload_0
    //   30: dup
    //   31: iload_1
    //   32: iadd
    //   33: invokevirtual substring : (II)Ljava/lang/String;
    //   36: iconst_m1
    //   37: goto -> 143
    //   40: aload #5
    //   42: swap
    //   43: iload_3
    //   44: iinc #3, 1
    //   47: swap
    //   48: aastore
    //   49: iload_0
    //   50: iload_1
    //   51: iadd
    //   52: dup
    //   53: istore_0
    //   54: iload #4
    //   56: if_icmpge -> 68
    //   59: aload_2
    //   60: iload_0
    //   61: invokevirtual charAt : (I)C
    //   64: istore_1
    //   65: goto -> 23
    //   68: ldc 'ZW\\t^ ^K6u'
    //   70: dup
    //   71: astore_2
    //   72: invokevirtual length : ()I
    //   75: istore #4
    //   77: bipush #9
    //   79: istore_1
    //   80: iconst_m1
    //   81: istore_0
    //   82: bipush #87
    //   84: iinc #0, 1
    //   87: aload_2
    //   88: iload_0
    //   89: dup
    //   90: iload_1
    //   91: iadd
    //   92: invokevirtual substring : (II)Ljava/lang/String;
    //   95: iconst_0
    //   96: goto -> 143
    //   99: aload #5
    //   101: swap
    //   102: iload_3
    //   103: iinc #3, 1
    //   106: swap
    //   107: aastore
    //   108: iload_0
    //   109: iload_1
    //   110: iadd
    //   111: dup
    //   112: istore_0
    //   113: iload #4
    //   115: if_icmpge -> 127
    //   118: aload_2
    //   119: iload_0
    //   120: invokevirtual charAt : (I)C
    //   123: istore_1
    //   124: goto -> 82
    //   127: aload #5
    //   129: putstatic burp/Zt4g.a : [Ljava/lang/String;
    //   132: bipush #25
    //   134: anewarray java/lang/String
    //   137: putstatic burp/Zt4g.b : [Ljava/lang/String;
    //   140: goto -> 300
    //   143: dup_x2
    //   144: pop
    //   145: invokevirtual toCharArray : ()[C
    //   148: dup_x1
    //   149: arraylength
    //   150: dup_x2
    //   151: pop
    //   152: iconst_0
    //   153: istore #6
    //   155: dup2_x1
    //   156: pop2
    //   157: dup_x2
    //   158: iconst_1
    //   159: if_icmpgt -> 260
    //   162: dup2
    //   163: swap
    //   164: iload #6
    //   166: dup2_x1
    //   167: caload
    //   168: swap
    //   169: iload #6
    //   171: bipush #7
    //   173: irem
    //   174: tableswitch default -> 242, 0 -> 212, 1 -> 217, 2 -> 222, 3 -> 227, 4 -> 232, 5 -> 237
    //   212: bipush #89
    //   214: goto -> 244
    //   217: bipush #69
    //   219: goto -> 244
    //   222: bipush #58
    //   224: goto -> 244
    //   227: bipush #43
    //   229: goto -> 244
    //   232: bipush #79
    //   234: goto -> 244
    //   237: bipush #124
    //   239: goto -> 244
    //   242: bipush #22
    //   244: ixor
    //   245: ixor
    //   246: i2c
    //   247: castore
    //   248: iinc #6, 1
    //   251: dup
    //   252: ifne -> 260
    //   255: dup2
    //   256: dup_x1
    //   257: goto -> 166
    //   260: dup2_x1
    //   261: pop2
    //   262: dup_x2
    //   263: iload #6
    //   265: if_icmpgt -> 162
    //   268: pop
    //   269: new java/lang/String
    //   272: dup_x1
    //   273: swap
    //   274: invokespecial <init> : ([C)V
    //   277: invokevirtual intern : ()Ljava/lang/String;
    //   280: swap
    //   281: pop
    //   282: swap
    //   283: tableswitch default -> 40, 0 -> 99
    //   300: new java/math/BigInteger
    //   303: dup
    //   304: bipush #32
    //   306: newarray byte
    //   308: dup
    //   309: iconst_0
    //   310: bipush #123
    //   312: bastore
    //   313: dup
    //   314: iconst_1
    //   315: bipush #67
    //   317: bastore
    //   318: dup
    //   319: iconst_2
    //   320: bipush #11
    //   322: bastore
    //   323: dup
    //   324: iconst_3
    //   325: bipush #-38
    //   327: bastore
    //   328: dup
    //   329: iconst_4
    //   330: bipush #54
    //   332: bastore
    //   333: dup
    //   334: iconst_5
    //   335: bipush #127
    //   337: bastore
    //   338: dup
    //   339: bipush #6
    //   341: iconst_3
    //   342: bastore
    //   343: dup
    //   344: bipush #7
    //   346: bipush #-79
    //   348: bastore
    //   349: dup
    //   350: bipush #8
    //   352: bipush #105
    //   354: bastore
    //   355: dup
    //   356: bipush #9
    //   358: bipush #-41
    //   360: bastore
    //   361: dup
    //   362: bipush #10
    //   364: bipush #-107
    //   366: bastore
    //   367: dup
    //   368: bipush #11
    //   370: iconst_2
    //   371: bastore
    //   372: dup
    //   373: bipush #12
    //   375: bipush #-50
    //   377: bastore
    //   378: dup
    //   379: bipush #13
    //   381: bipush #101
    //   383: bastore
    //   384: dup
    //   385: bipush #14
    //   387: bipush #45
    //   389: bastore
    //   390: dup
    //   391: bipush #15
    //   393: bipush #106
    //   395: bastore
    //   396: dup
    //   397: bipush #16
    //   399: bipush #-74
    //   401: bastore
    //   402: dup
    //   403: bipush #17
    //   405: bipush #88
    //   407: bastore
    //   408: dup
    //   409: bipush #18
    //   411: bipush #-69
    //   413: bastore
    //   414: dup
    //   415: bipush #19
    //   417: bipush #29
    //   419: bastore
    //   420: dup
    //   421: bipush #20
    //   423: bipush #-14
    //   425: bastore
    //   426: dup
    //   427: bipush #21
    //   429: bipush #87
    //   431: bastore
    //   432: dup
    //   433: bipush #22
    //   435: bipush #117
    //   437: bastore
    //   438: dup
    //   439: bipush #23
    //   441: bipush #-6
    //   443: bastore
    //   444: dup
    //   445: bipush #24
    //   447: bipush #104
    //   449: bastore
    //   450: dup
    //   451: bipush #25
    //   453: bipush #-10
    //   455: bastore
    //   456: dup
    //   457: bipush #26
    //   459: bipush #73
    //   461: bastore
    //   462: dup
    //   463: bipush #27
    //   465: bipush #124
    //   467: bastore
    //   468: dup
    //   469: bipush #28
    //   471: bipush #93
    //   473: bastore
    //   474: dup
    //   475: bipush #29
    //   477: bipush #28
    //   479: bastore
    //   480: dup
    //   481: bipush #30
    //   483: bipush #51
    //   485: bastore
    //   486: dup
    //   487: bipush #31
    //   489: bipush #-51
    //   491: bastore
    //   492: invokespecial <init> : ([B)V
    //   495: putstatic burp/Zt4g.Zv : Ljava/lang/Object;
    //   498: sipush #1800
    //   501: sipush #7392
    //   504: invokestatic a : (II)Ljava/lang/String;
    //   507: putstatic burp/Zt4g.Zj : Ljava/lang/String;
    //   510: return
  }
  
  private static Throwable a(Throwable paramThrowable) {
    return paramThrowable;
  }
  
  private static String a(int paramInt1, int paramInt2) {
    int i = (paramInt1 ^ 0x70F) & 0xFFFF;
    if (b[i] == null) {
      char[] arrayOfChar = a[i].toCharArray();
      switch (arrayOfChar[0] & 0xFF) {
        case 0:
        
        case 1:
        
        case 2:
        
        case 3:
        
        case 4:
        
        case 5:
        
        case 6:
        
        case 7:
        
        case 8:
        
        case 9:
        
        case 10:
        
        case 11:
        
        case 12:
        
        case 13:
        
        case 14:
        
        case 15:
        
        case 16:
        
        case 17:
        
        case 18:
        
        case 19:
        
        case 20:
        
        case 21:
        
        case 22:
        
        case 23:
        
        case 24:
        
        case 25:
        
        case 26:
        
        case 27:
        
        case 28:
        
        case 29:
        
        case 30:
        
        case 31:
        
        case 32:
        
        case 33:
        
        case 34:
        
        case 35:
        
        case 36:
        
        case 37:
        
        case 38:
        
        case 39:
        
        case 40:
        
        case 41:
        
        case 42:
        
        case 43:
        
        case 44:
        
        case 45:
        
        case 46:
        
        case 47:
        
        case 48:
        
        case 49:
        
        case 50:
        
        case 51:
        
        case 52:
        
        case 53:
        
        case 54:
        
        case 55:
        
        case 56:
        
        case 57:
        
        case 58:
        
        case 59:
        
        case 60:
        
        case 61:
        
        case 62:
        
        case 63:
        
        case 64:
        
        case 65:
        
        case 66:
        
        case 67:
        
        case 68:
        
        case 69:
        
        case 70:
        
        case 71:
        
        case 72:
        
        case 73:
        
        case 74:
        
        case 75:
        
        case 76:
        
        case 77:
        
        case 78:
        
        case 79:
        
        case 80:
        
        case 81:
        
        case 82:
        
        case 83:
        
        case 84:
        
        case 85:
        
        case 86:
        
        case 87:
        
        case 88:
        
        case 89:
        
        case 90:
        
        case 91:
        
        case 92:
        
        case 93:
        
        case 94:
        
        case 95:
        
        case 96:
        
        case 97:
        
        case 98:
        
        case 99:
        
        case 100:
        
        case 101:
        
        case 102:
        
        case 103:
        
        case 104:
        
        case 105:
        
        case 106:
        
        case 107:
        
        case 108:
        
        case 109:
        
        case 110:
        
        case 111:
        
        case 112:
        
        case 113:
        
        case 114:
        
        case 115:
        
        case 116:
        
        case 117:
        
        case 118:
        
        case 119:
        
        case 120:
        
        case 121:
        
        case 122:
        
        case 123:
        
        case 124:
        
        case 125:
        
        case 126:
        
        case 127:
        
        case 128:
        
        case 129:
        
        case 130:
        
        case 131:
        
        case 132:
        
        case 133:
        
        case 134:
        
        case 135:
        
        case 136:
        
        case 137:
        
        case 138:
        
        case 139:
        
        case 140:
        
        case 141:
        
        case 142:
        
        case 143:
        
        case 144:
        
        case 145:
        
        case 146:
        
        case 147:
        
        case 148:
        
        case 149:
        
        case 150:
        
        case 151:
        
        case 152:
        
        case 153:
        
        case 154:
        
        case 155:
        
        case 156:
        
        case 157:
        
        case 158:
        
        case 159:
        
        case 160:
        
        case 161:
        
        case 162:
        
        case 163:
        
        case 164:
        
        case 165:
        
        case 166:
        
        case 167:
        
        case 168:
        
        case 169:
        
        case 170:
        
        case 171:
        
        case 172:
        
        case 173:
        
        case 174:
        
        case 175:
        
        case 176:
        
        case 177:
        
        case 178:
        
        case 179:
        
        case 180:
        
        case 181:
        
        case 182:
        
        case 183:
        
        case 184:
        
        case 185:
        
        case 186:
        
        case 187:
        
        case 188:
        
        case 189:
        
        case 190:
        
        case 191:
        
        case 192:
        
        case 193:
        
        case 194:
        
        case 195:
        
        case 196:
        
        case 197:
        
        case 198:
        
        case 199:
        
        case 200:
        
        case 201:
        
        case 202:
        
        case 203:
        
        case 204:
        
        case 205:
        
        case 206:
        
        case 207:
        
        case 208:
        
        case 209:
        
        case 210:
        
        case 211:
        
        case 212:
        
        case 213:
        
        case 214:
        
        case 215:
        
        case 216:
        
        case 217:
        
        case 218:
        
        case 219:
        
        case 220:
        
        case 221:
        
        case 222:
        
        case 223:
        
        case 224:
        
        case 225:
        
        case 226:
        
        case 227:
        
        case 228:
        
        case 229:
        
        case 230:
        
        case 231:
        
        case 232:
        
        case 233:
        
        case 234:
        
        case 235:
        
        case 236:
        
        case 237:
        
        case 238:
        
        case 239:
        
        case 240:
        
        case 241:
        
        case 242:
        
        case 243:
        
        case 244:
        
        case 245:
        
        case 246:
        
        case 247:
        
        case 248:
        
        case 249:
        
        case 250:
        
        case 251:
        
        case 252:
        
        case 253:
        
        case 254:
        
        default:
          break;
      } 
      char c = '';
      int j = (paramInt2 & 0xFF) - c;
      if (j < 0)
        j += 256; 
      int k = ((paramInt2 & 0xFFFF) >>> 8) - c;
      if (k < 0)
        k += 256; 
      for (byte b = 0; b < arrayOfChar.length; b++) {
        int m = b % 2;
        if (m == 0) {
          arrayOfChar[b] = (char)(arrayOfChar[b] ^ j);
          j = ((j >>> 3 | j << 5) ^ arrayOfChar[b]) & 0xFF;
        } else {
          arrayOfChar[b] = (char)(arrayOfChar[b] ^ k);
          k = ((k >>> 3 | k << 5) ^ arrayOfChar[b]) & 0xFF;
        } 
      } 
      b[i] = (new String(arrayOfChar)).intern();
    } 
    return b[i];
  }
}


/* Location:              C:\Program Files\BurpSuitePro\burpsuite_pro.jar!\burp\Zt4g.class
 * Java compiler version: 21 (65.0)
 * JD-Core Version:       1.1.3
 */