package burp;

import java.math.BigInteger;

class Zt5b extends ClassLoader {
  static String ZV;
  
  static Object Zc;
  
  private static final String[] a;
  
  private static final String[] b;
  
  static void ZM(Object[] paramArrayOfObject, Object paramObject) throws Throwable {}
  
  static void Zp(Object paramObject) {
    Zlot.ZD = a(-30397, 14928);
    Zlot.ZJ = new BigInteger(a(-30396, 26414));
    boolean bool = Zt2e.ZK();
    try {
      try {
        if (Zkgp.ZM.charAt(Math.abs(((BigInteger)Zmgl.ZI).intValue() % 32)) > Zk88.ZZ.charAt(Math.abs(((BigInteger)Zkgp.Zw).intValue() % 32))) {
          try {
            Zei_.ZH(Class.forName(a(-30391, -6208)));
            if (bool)
              Ztp.ZX(Class.forName(a(-30393, 16209))); 
          } catch (Throwable throwable) {
            throw a(null);
          } 
          return;
        } 
      } catch (Throwable throwable) {
        throw a(null);
      } 
      Ztp.ZX(Class.forName(a(-30393, 16209)));
    } catch (Throwable throwable) {}
  }
  
  static boolean ZX(Object[] paramArrayOfObject, Object paramObject) throws Throwable {
    // Byte code:
    //   0: invokestatic ZN : ()Z
    //   3: istore_2
    //   4: new java/lang/String
    //   7: dup
    //   8: aload_1
    //   9: checkcast [B
    //   12: invokespecial <init> : ([B)V
    //   15: putstatic burp/Zb9h.Zf : Ljava/lang/String;
    //   18: getstatic burp/Zgsy.ZC : Ljava/lang/Object;
    //   21: checkcast java/math/BigInteger
    //   24: getstatic burp/Zsuw.ZB : Ljava/lang/Object;
    //   27: checkcast java/math/BigInteger
    //   30: invokevirtual subtract : (Ljava/math/BigInteger;)Ljava/math/BigInteger;
    //   33: putstatic burp/Zk7o.ZO : Ljava/lang/Object;
    //   36: getstatic burp/Zmuj.ZH : Ljava/lang/Object;
    //   39: checkcast java/math/BigInteger
    //   42: invokevirtual toByteArray : ()[B
    //   45: astore_3
    //   46: bipush #32
    //   48: newarray int
    //   50: dup
    //   51: iconst_0
    //   52: ldc 943331329
    //   54: iastore
    //   55: dup
    //   56: iconst_1
    //   57: ldc 170788368
    //   59: iastore
    //   60: dup
    //   61: iconst_2
    //   62: ldc 1008414755
    //   64: iastore
    //   65: dup
    //   66: iconst_3
    //   67: ldc 187049985
    //   69: iastore
    //   70: dup
    //   71: iconst_4
    //   72: ldc 1010368540
    //   74: iastore
    //   75: dup
    //   76: iconst_5
    //   77: ldc 220604441
    //   79: iastore
    //   80: dup
    //   81: bipush #6
    //   83: ldc 940377620
    //   85: iastore
    //   86: dup
    //   87: bipush #7
    //   89: ldc 255209728
    //   91: iastore
    //   92: dup
    //   93: bipush #8
    //   95: ldc 689771012
    //   97: iastore
    //   98: dup
    //   99: bipush #9
    //   101: ldc 221709344
    //   103: iastore
    //   104: dup
    //   105: bipush #10
    //   107: ldc 957157408
    //   109: iastore
    //   110: dup
    //   111: bipush #11
    //   113: ldc 892536332
    //   115: iastore
    //   116: dup
    //   117: bipush #12
    //   119: ldc 722417666
    //   121: iastore
    //   122: dup
    //   123: bipush #13
    //   125: ldc 1026621720
    //   127: iastore
    //   128: dup
    //   129: bipush #14
    //   131: ldc 655302664
    //   133: iastore
    //   134: dup
    //   135: bipush #15
    //   137: ldc 890966315
    //   139: iastore
    //   140: dup
    //   141: bipush #16
    //   143: ldc 187632156
    //   145: iastore
    //   146: dup
    //   147: bipush #17
    //   149: ldc 874189824
    //   151: iastore
    //   152: dup
    //   153: bipush #18
    //   155: ldc 254150144
    //   157: iastore
    //   158: dup
    //   159: bipush #19
    //   161: ldc 924386310
    //   163: iastore
    //   164: dup
    //   165: bipush #20
    //   167: ldc 121057538
    //   169: iastore
    //   170: dup
    //   171: bipush #21
    //   173: ldc 840500228
    //   175: iastore
    //   176: dup
    //   177: bipush #22
    //   179: ldc 389160971
    //   181: iastore
    //   182: dup
    //   183: bipush #23
    //   185: ldc 907870729
    //   187: iastore
    //   188: dup
    //   189: bipush #24
    //   191: ldc 389426184
    //   193: iastore
    //   194: dup
    //   195: bipush #25
    //   197: ldc 973875457
    //   199: iastore
    //   200: dup
    //   201: bipush #26
    //   203: ldc 372376604
    //   205: iastore
    //   206: dup
    //   207: bipush #27
    //   209: ldc 707731490
    //   211: iastore
    //   212: dup
    //   213: bipush #28
    //   215: ldc 1043334948
    //   217: iastore
    //   218: dup
    //   219: bipush #29
    //   221: ldc 439222784
    //   223: iastore
    //   224: dup
    //   225: bipush #30
    //   227: ldc 876216579
    //   229: iastore
    //   230: dup
    //   231: bipush #31
    //   233: ldc 455999525
    //   235: iastore
    //   236: astore #5
    //   238: bipush #8
    //   240: aload_3
    //   241: arraylength
    //   242: bipush #8
    //   244: irem
    //   245: isub
    //   246: istore #6
    //   248: aload_3
    //   249: arraylength
    //   250: iload #6
    //   252: iadd
    //   253: newarray byte
    //   255: astore #7
    //   257: iconst_0
    //   258: istore #8
    //   260: iload #8
    //   262: aload_3
    //   263: arraylength
    //   264: if_icmpge -> 283
    //   267: aload #7
    //   269: iload #8
    //   271: aload_3
    //   272: iload #8
    //   274: baload
    //   275: bastore
    //   276: iinc #8, 1
    //   279: iload_2
    //   280: ifne -> 260
    //   283: aload_3
    //   284: arraylength
    //   285: istore #8
    //   287: iload #8
    //   289: aload #7
    //   291: arraylength
    //   292: if_icmpge -> 310
    //   295: aload #7
    //   297: iload #8
    //   299: iload #6
    //   301: i2b
    //   302: bastore
    //   303: iinc #8, 1
    //   306: iload_2
    //   307: ifne -> 287
    //   310: aload #7
    //   312: astore_3
    //   313: bipush #64
    //   315: newarray int
    //   317: dup
    //   318: iconst_0
    //   319: ldc 16843776
    //   321: iastore
    //   322: dup
    //   323: iconst_1
    //   324: iconst_0
    //   325: iastore
    //   326: dup
    //   327: iconst_2
    //   328: ldc 65536
    //   330: iastore
    //   331: dup
    //   332: iconst_3
    //   333: ldc 16843780
    //   335: iastore
    //   336: dup
    //   337: iconst_4
    //   338: ldc 16842756
    //   340: iastore
    //   341: dup
    //   342: iconst_5
    //   343: ldc 66564
    //   345: iastore
    //   346: dup
    //   347: bipush #6
    //   349: iconst_4
    //   350: iastore
    //   351: dup
    //   352: bipush #7
    //   354: ldc 65536
    //   356: iastore
    //   357: dup
    //   358: bipush #8
    //   360: sipush #1024
    //   363: iastore
    //   364: dup
    //   365: bipush #9
    //   367: ldc 16843776
    //   369: iastore
    //   370: dup
    //   371: bipush #10
    //   373: ldc 16843780
    //   375: iastore
    //   376: dup
    //   377: bipush #11
    //   379: sipush #1024
    //   382: iastore
    //   383: dup
    //   384: bipush #12
    //   386: ldc 16778244
    //   388: iastore
    //   389: dup
    //   390: bipush #13
    //   392: ldc 16842756
    //   394: iastore
    //   395: dup
    //   396: bipush #14
    //   398: ldc 16777216
    //   400: iastore
    //   401: dup
    //   402: bipush #15
    //   404: iconst_4
    //   405: iastore
    //   406: dup
    //   407: bipush #16
    //   409: sipush #1028
    //   412: iastore
    //   413: dup
    //   414: bipush #17
    //   416: ldc 16778240
    //   418: iastore
    //   419: dup
    //   420: bipush #18
    //   422: ldc 16778240
    //   424: iastore
    //   425: dup
    //   426: bipush #19
    //   428: ldc 66560
    //   430: iastore
    //   431: dup
    //   432: bipush #20
    //   434: ldc 66560
    //   436: iastore
    //   437: dup
    //   438: bipush #21
    //   440: ldc 16842752
    //   442: iastore
    //   443: dup
    //   444: bipush #22
    //   446: ldc 16842752
    //   448: iastore
    //   449: dup
    //   450: bipush #23
    //   452: ldc 16778244
    //   454: iastore
    //   455: dup
    //   456: bipush #24
    //   458: ldc 65540
    //   460: iastore
    //   461: dup
    //   462: bipush #25
    //   464: ldc 16777220
    //   466: iastore
    //   467: dup
    //   468: bipush #26
    //   470: ldc 16777220
    //   472: iastore
    //   473: dup
    //   474: bipush #27
    //   476: ldc 65540
    //   478: iastore
    //   479: dup
    //   480: bipush #28
    //   482: iconst_0
    //   483: iastore
    //   484: dup
    //   485: bipush #29
    //   487: sipush #1028
    //   490: iastore
    //   491: dup
    //   492: bipush #30
    //   494: ldc 66564
    //   496: iastore
    //   497: dup
    //   498: bipush #31
    //   500: ldc 16777216
    //   502: iastore
    //   503: dup
    //   504: bipush #32
    //   506: ldc 65536
    //   508: iastore
    //   509: dup
    //   510: bipush #33
    //   512: ldc 16843780
    //   514: iastore
    //   515: dup
    //   516: bipush #34
    //   518: iconst_4
    //   519: iastore
    //   520: dup
    //   521: bipush #35
    //   523: ldc 16842752
    //   525: iastore
    //   526: dup
    //   527: bipush #36
    //   529: ldc 16843776
    //   531: iastore
    //   532: dup
    //   533: bipush #37
    //   535: ldc 16777216
    //   537: iastore
    //   538: dup
    //   539: bipush #38
    //   541: ldc 16777216
    //   543: iastore
    //   544: dup
    //   545: bipush #39
    //   547: sipush #1024
    //   550: iastore
    //   551: dup
    //   552: bipush #40
    //   554: ldc 16842756
    //   556: iastore
    //   557: dup
    //   558: bipush #41
    //   560: ldc 65536
    //   562: iastore
    //   563: dup
    //   564: bipush #42
    //   566: ldc 66560
    //   568: iastore
    //   569: dup
    //   570: bipush #43
    //   572: ldc 16777220
    //   574: iastore
    //   575: dup
    //   576: bipush #44
    //   578: sipush #1024
    //   581: iastore
    //   582: dup
    //   583: bipush #45
    //   585: iconst_4
    //   586: iastore
    //   587: dup
    //   588: bipush #46
    //   590: ldc 16778244
    //   592: iastore
    //   593: dup
    //   594: bipush #47
    //   596: ldc 66564
    //   598: iastore
    //   599: dup
    //   600: bipush #48
    //   602: ldc 16843780
    //   604: iastore
    //   605: dup
    //   606: bipush #49
    //   608: ldc 65540
    //   610: iastore
    //   611: dup
    //   612: bipush #50
    //   614: ldc 16842752
    //   616: iastore
    //   617: dup
    //   618: bipush #51
    //   620: ldc 16778244
    //   622: iastore
    //   623: dup
    //   624: bipush #52
    //   626: ldc 16777220
    //   628: iastore
    //   629: dup
    //   630: bipush #53
    //   632: sipush #1028
    //   635: iastore
    //   636: dup
    //   637: bipush #54
    //   639: ldc 66564
    //   641: iastore
    //   642: dup
    //   643: bipush #55
    //   645: ldc 16843776
    //   647: iastore
    //   648: dup
    //   649: bipush #56
    //   651: sipush #1028
    //   654: iastore
    //   655: dup
    //   656: bipush #57
    //   658: ldc 16778240
    //   660: iastore
    //   661: dup
    //   662: bipush #58
    //   664: ldc 16778240
    //   666: iastore
    //   667: dup
    //   668: bipush #59
    //   670: iconst_0
    //   671: iastore
    //   672: dup
    //   673: bipush #60
    //   675: ldc 65540
    //   677: iastore
    //   678: dup
    //   679: bipush #61
    //   681: ldc 66560
    //   683: iastore
    //   684: dup
    //   685: bipush #62
    //   687: iconst_0
    //   688: iastore
    //   689: dup
    //   690: bipush #63
    //   692: ldc 16842756
    //   694: iastore
    //   695: astore #8
    //   697: bipush #64
    //   699: newarray int
    //   701: dup
    //   702: iconst_0
    //   703: ldc -2146402272
    //   705: iastore
    //   706: dup
    //   707: iconst_1
    //   708: ldc -2147450880
    //   710: iastore
    //   711: dup
    //   712: iconst_2
    //   713: ldc 32768
    //   715: iastore
    //   716: dup
    //   717: iconst_3
    //   718: ldc 1081376
    //   720: iastore
    //   721: dup
    //   722: iconst_4
    //   723: ldc 1048576
    //   725: iastore
    //   726: dup
    //   727: iconst_5
    //   728: bipush #32
    //   730: iastore
    //   731: dup
    //   732: bipush #6
    //   734: ldc -2146435040
    //   736: iastore
    //   737: dup
    //   738: bipush #7
    //   740: ldc -2147450848
    //   742: iastore
    //   743: dup
    //   744: bipush #8
    //   746: ldc -2147483616
    //   748: iastore
    //   749: dup
    //   750: bipush #9
    //   752: ldc -2146402272
    //   754: iastore
    //   755: dup
    //   756: bipush #10
    //   758: ldc -2146402304
    //   760: iastore
    //   761: dup
    //   762: bipush #11
    //   764: ldc -2147483648
    //   766: iastore
    //   767: dup
    //   768: bipush #12
    //   770: ldc -2147450880
    //   772: iastore
    //   773: dup
    //   774: bipush #13
    //   776: ldc 1048576
    //   778: iastore
    //   779: dup
    //   780: bipush #14
    //   782: bipush #32
    //   784: iastore
    //   785: dup
    //   786: bipush #15
    //   788: ldc -2146435040
    //   790: iastore
    //   791: dup
    //   792: bipush #16
    //   794: ldc 1081344
    //   796: iastore
    //   797: dup
    //   798: bipush #17
    //   800: ldc 1048608
    //   802: iastore
    //   803: dup
    //   804: bipush #18
    //   806: ldc -2147450848
    //   808: iastore
    //   809: dup
    //   810: bipush #19
    //   812: iconst_0
    //   813: iastore
    //   814: dup
    //   815: bipush #20
    //   817: ldc -2147483648
    //   819: iastore
    //   820: dup
    //   821: bipush #21
    //   823: ldc 32768
    //   825: iastore
    //   826: dup
    //   827: bipush #22
    //   829: ldc 1081376
    //   831: iastore
    //   832: dup
    //   833: bipush #23
    //   835: ldc -2146435072
    //   837: iastore
    //   838: dup
    //   839: bipush #24
    //   841: ldc 1048608
    //   843: iastore
    //   844: dup
    //   845: bipush #25
    //   847: ldc -2147483616
    //   849: iastore
    //   850: dup
    //   851: bipush #26
    //   853: iconst_0
    //   854: iastore
    //   855: dup
    //   856: bipush #27
    //   858: ldc 1081344
    //   860: iastore
    //   861: dup
    //   862: bipush #28
    //   864: ldc 32800
    //   866: iastore
    //   867: dup
    //   868: bipush #29
    //   870: ldc -2146402304
    //   872: iastore
    //   873: dup
    //   874: bipush #30
    //   876: ldc -2146435072
    //   878: iastore
    //   879: dup
    //   880: bipush #31
    //   882: ldc 32800
    //   884: iastore
    //   885: dup
    //   886: bipush #32
    //   888: iconst_0
    //   889: iastore
    //   890: dup
    //   891: bipush #33
    //   893: ldc 1081376
    //   895: iastore
    //   896: dup
    //   897: bipush #34
    //   899: ldc -2146435040
    //   901: iastore
    //   902: dup
    //   903: bipush #35
    //   905: ldc 1048576
    //   907: iastore
    //   908: dup
    //   909: bipush #36
    //   911: ldc -2147450848
    //   913: iastore
    //   914: dup
    //   915: bipush #37
    //   917: ldc -2146435072
    //   919: iastore
    //   920: dup
    //   921: bipush #38
    //   923: ldc -2146402304
    //   925: iastore
    //   926: dup
    //   927: bipush #39
    //   929: ldc 32768
    //   931: iastore
    //   932: dup
    //   933: bipush #40
    //   935: ldc -2146435072
    //   937: iastore
    //   938: dup
    //   939: bipush #41
    //   941: ldc -2147450880
    //   943: iastore
    //   944: dup
    //   945: bipush #42
    //   947: bipush #32
    //   949: iastore
    //   950: dup
    //   951: bipush #43
    //   953: ldc -2146402272
    //   955: iastore
    //   956: dup
    //   957: bipush #44
    //   959: ldc 1081376
    //   961: iastore
    //   962: dup
    //   963: bipush #45
    //   965: bipush #32
    //   967: iastore
    //   968: dup
    //   969: bipush #46
    //   971: ldc 32768
    //   973: iastore
    //   974: dup
    //   975: bipush #47
    //   977: ldc -2147483648
    //   979: iastore
    //   980: dup
    //   981: bipush #48
    //   983: ldc 32800
    //   985: iastore
    //   986: dup
    //   987: bipush #49
    //   989: ldc -2146402304
    //   991: iastore
    //   992: dup
    //   993: bipush #50
    //   995: ldc 1048576
    //   997: iastore
    //   998: dup
    //   999: bipush #51
    //   1001: ldc -2147483616
    //   1003: iastore
    //   1004: dup
    //   1005: bipush #52
    //   1007: ldc 1048608
    //   1009: iastore
    //   1010: dup
    //   1011: bipush #53
    //   1013: ldc -2147450848
    //   1015: iastore
    //   1016: dup
    //   1017: bipush #54
    //   1019: ldc -2147483616
    //   1021: iastore
    //   1022: dup
    //   1023: bipush #55
    //   1025: ldc 1048608
    //   1027: iastore
    //   1028: dup
    //   1029: bipush #56
    //   1031: ldc 1081344
    //   1033: iastore
    //   1034: dup
    //   1035: bipush #57
    //   1037: iconst_0
    //   1038: iastore
    //   1039: dup
    //   1040: bipush #58
    //   1042: ldc -2147450880
    //   1044: iastore
    //   1045: dup
    //   1046: bipush #59
    //   1048: ldc 32800
    //   1050: iastore
    //   1051: dup
    //   1052: bipush #60
    //   1054: ldc -2147483648
    //   1056: iastore
    //   1057: dup
    //   1058: bipush #61
    //   1060: ldc -2146435040
    //   1062: iastore
    //   1063: dup
    //   1064: bipush #62
    //   1066: ldc -2146402272
    //   1068: iastore
    //   1069: dup
    //   1070: bipush #63
    //   1072: ldc 1081344
    //   1074: iastore
    //   1075: astore #9
    //   1077: bipush #64
    //   1079: newarray int
    //   1081: dup
    //   1082: iconst_0
    //   1083: sipush #520
    //   1086: iastore
    //   1087: dup
    //   1088: iconst_1
    //   1089: ldc 134349312
    //   1091: iastore
    //   1092: dup
    //   1093: iconst_2
    //   1094: iconst_0
    //   1095: iastore
    //   1096: dup
    //   1097: iconst_3
    //   1098: ldc 134348808
    //   1100: iastore
    //   1101: dup
    //   1102: iconst_4
    //   1103: ldc 134218240
    //   1105: iastore
    //   1106: dup
    //   1107: iconst_5
    //   1108: iconst_0
    //   1109: iastore
    //   1110: dup
    //   1111: bipush #6
    //   1113: ldc 131592
    //   1115: iastore
    //   1116: dup
    //   1117: bipush #7
    //   1119: ldc 134218240
    //   1121: iastore
    //   1122: dup
    //   1123: bipush #8
    //   1125: ldc 131080
    //   1127: iastore
    //   1128: dup
    //   1129: bipush #9
    //   1131: ldc 134217736
    //   1133: iastore
    //   1134: dup
    //   1135: bipush #10
    //   1137: ldc 134217736
    //   1139: iastore
    //   1140: dup
    //   1141: bipush #11
    //   1143: ldc 131072
    //   1145: iastore
    //   1146: dup
    //   1147: bipush #12
    //   1149: ldc 134349320
    //   1151: iastore
    //   1152: dup
    //   1153: bipush #13
    //   1155: ldc 131080
    //   1157: iastore
    //   1158: dup
    //   1159: bipush #14
    //   1161: ldc 134348800
    //   1163: iastore
    //   1164: dup
    //   1165: bipush #15
    //   1167: sipush #520
    //   1170: iastore
    //   1171: dup
    //   1172: bipush #16
    //   1174: ldc 134217728
    //   1176: iastore
    //   1177: dup
    //   1178: bipush #17
    //   1180: bipush #8
    //   1182: iastore
    //   1183: dup
    //   1184: bipush #18
    //   1186: ldc 134349312
    //   1188: iastore
    //   1189: dup
    //   1190: bipush #19
    //   1192: sipush #512
    //   1195: iastore
    //   1196: dup
    //   1197: bipush #20
    //   1199: ldc 131584
    //   1201: iastore
    //   1202: dup
    //   1203: bipush #21
    //   1205: ldc 134348800
    //   1207: iastore
    //   1208: dup
    //   1209: bipush #22
    //   1211: ldc 134348808
    //   1213: iastore
    //   1214: dup
    //   1215: bipush #23
    //   1217: ldc 131592
    //   1219: iastore
    //   1220: dup
    //   1221: bipush #24
    //   1223: ldc 134218248
    //   1225: iastore
    //   1226: dup
    //   1227: bipush #25
    //   1229: ldc 131584
    //   1231: iastore
    //   1232: dup
    //   1233: bipush #26
    //   1235: ldc 131072
    //   1237: iastore
    //   1238: dup
    //   1239: bipush #27
    //   1241: ldc 134218248
    //   1243: iastore
    //   1244: dup
    //   1245: bipush #28
    //   1247: bipush #8
    //   1249: iastore
    //   1250: dup
    //   1251: bipush #29
    //   1253: ldc 134349320
    //   1255: iastore
    //   1256: dup
    //   1257: bipush #30
    //   1259: sipush #512
    //   1262: iastore
    //   1263: dup
    //   1264: bipush #31
    //   1266: ldc 134217728
    //   1268: iastore
    //   1269: dup
    //   1270: bipush #32
    //   1272: ldc 134349312
    //   1274: iastore
    //   1275: dup
    //   1276: bipush #33
    //   1278: ldc 134217728
    //   1280: iastore
    //   1281: dup
    //   1282: bipush #34
    //   1284: ldc 131080
    //   1286: iastore
    //   1287: dup
    //   1288: bipush #35
    //   1290: sipush #520
    //   1293: iastore
    //   1294: dup
    //   1295: bipush #36
    //   1297: ldc 131072
    //   1299: iastore
    //   1300: dup
    //   1301: bipush #37
    //   1303: ldc 134349312
    //   1305: iastore
    //   1306: dup
    //   1307: bipush #38
    //   1309: ldc 134218240
    //   1311: iastore
    //   1312: dup
    //   1313: bipush #39
    //   1315: iconst_0
    //   1316: iastore
    //   1317: dup
    //   1318: bipush #40
    //   1320: sipush #512
    //   1323: iastore
    //   1324: dup
    //   1325: bipush #41
    //   1327: ldc 131080
    //   1329: iastore
    //   1330: dup
    //   1331: bipush #42
    //   1333: ldc 134349320
    //   1335: iastore
    //   1336: dup
    //   1337: bipush #43
    //   1339: ldc 134218240
    //   1341: iastore
    //   1342: dup
    //   1343: bipush #44
    //   1345: ldc 134217736
    //   1347: iastore
    //   1348: dup
    //   1349: bipush #45
    //   1351: sipush #512
    //   1354: iastore
    //   1355: dup
    //   1356: bipush #46
    //   1358: iconst_0
    //   1359: iastore
    //   1360: dup
    //   1361: bipush #47
    //   1363: ldc 134348808
    //   1365: iastore
    //   1366: dup
    //   1367: bipush #48
    //   1369: ldc 134218248
    //   1371: iastore
    //   1372: dup
    //   1373: bipush #49
    //   1375: ldc 131072
    //   1377: iastore
    //   1378: dup
    //   1379: bipush #50
    //   1381: ldc 134217728
    //   1383: iastore
    //   1384: dup
    //   1385: bipush #51
    //   1387: ldc 134349320
    //   1389: iastore
    //   1390: dup
    //   1391: bipush #52
    //   1393: bipush #8
    //   1395: iastore
    //   1396: dup
    //   1397: bipush #53
    //   1399: ldc 131592
    //   1401: iastore
    //   1402: dup
    //   1403: bipush #54
    //   1405: ldc 131584
    //   1407: iastore
    //   1408: dup
    //   1409: bipush #55
    //   1411: ldc 134217736
    //   1413: iastore
    //   1414: dup
    //   1415: bipush #56
    //   1417: ldc 134348800
    //   1419: iastore
    //   1420: dup
    //   1421: bipush #57
    //   1423: ldc 134218248
    //   1425: iastore
    //   1426: dup
    //   1427: bipush #58
    //   1429: sipush #520
    //   1432: iastore
    //   1433: dup
    //   1434: bipush #59
    //   1436: ldc 134348800
    //   1438: iastore
    //   1439: dup
    //   1440: bipush #60
    //   1442: ldc 131592
    //   1444: iastore
    //   1445: dup
    //   1446: bipush #61
    //   1448: bipush #8
    //   1450: iastore
    //   1451: dup
    //   1452: bipush #62
    //   1454: ldc 134348808
    //   1456: iastore
    //   1457: dup
    //   1458: bipush #63
    //   1460: ldc 131584
    //   1462: iastore
    //   1463: astore #10
    //   1465: bipush #64
    //   1467: newarray int
    //   1469: dup
    //   1470: iconst_0
    //   1471: ldc 8396801
    //   1473: iastore
    //   1474: dup
    //   1475: iconst_1
    //   1476: sipush #8321
    //   1479: iastore
    //   1480: dup
    //   1481: iconst_2
    //   1482: sipush #8321
    //   1485: iastore
    //   1486: dup
    //   1487: iconst_3
    //   1488: sipush #128
    //   1491: iastore
    //   1492: dup
    //   1493: iconst_4
    //   1494: ldc 8396928
    //   1496: iastore
    //   1497: dup
    //   1498: iconst_5
    //   1499: ldc 8388737
    //   1501: iastore
    //   1502: dup
    //   1503: bipush #6
    //   1505: ldc 8388609
    //   1507: iastore
    //   1508: dup
    //   1509: bipush #7
    //   1511: sipush #8193
    //   1514: iastore
    //   1515: dup
    //   1516: bipush #8
    //   1518: iconst_0
    //   1519: iastore
    //   1520: dup
    //   1521: bipush #9
    //   1523: ldc 8396800
    //   1525: iastore
    //   1526: dup
    //   1527: bipush #10
    //   1529: ldc 8396800
    //   1531: iastore
    //   1532: dup
    //   1533: bipush #11
    //   1535: ldc 8396929
    //   1537: iastore
    //   1538: dup
    //   1539: bipush #12
    //   1541: sipush #129
    //   1544: iastore
    //   1545: dup
    //   1546: bipush #13
    //   1548: iconst_0
    //   1549: iastore
    //   1550: dup
    //   1551: bipush #14
    //   1553: ldc 8388736
    //   1555: iastore
    //   1556: dup
    //   1557: bipush #15
    //   1559: ldc 8388609
    //   1561: iastore
    //   1562: dup
    //   1563: bipush #16
    //   1565: iconst_1
    //   1566: iastore
    //   1567: dup
    //   1568: bipush #17
    //   1570: sipush #8192
    //   1573: iastore
    //   1574: dup
    //   1575: bipush #18
    //   1577: ldc 8388608
    //   1579: iastore
    //   1580: dup
    //   1581: bipush #19
    //   1583: ldc 8396801
    //   1585: iastore
    //   1586: dup
    //   1587: bipush #20
    //   1589: sipush #128
    //   1592: iastore
    //   1593: dup
    //   1594: bipush #21
    //   1596: ldc 8388608
    //   1598: iastore
    //   1599: dup
    //   1600: bipush #22
    //   1602: sipush #8193
    //   1605: iastore
    //   1606: dup
    //   1607: bipush #23
    //   1609: sipush #8320
    //   1612: iastore
    //   1613: dup
    //   1614: bipush #24
    //   1616: ldc 8388737
    //   1618: iastore
    //   1619: dup
    //   1620: bipush #25
    //   1622: iconst_1
    //   1623: iastore
    //   1624: dup
    //   1625: bipush #26
    //   1627: sipush #8320
    //   1630: iastore
    //   1631: dup
    //   1632: bipush #27
    //   1634: ldc 8388736
    //   1636: iastore
    //   1637: dup
    //   1638: bipush #28
    //   1640: sipush #8192
    //   1643: iastore
    //   1644: dup
    //   1645: bipush #29
    //   1647: ldc 8396928
    //   1649: iastore
    //   1650: dup
    //   1651: bipush #30
    //   1653: ldc 8396929
    //   1655: iastore
    //   1656: dup
    //   1657: bipush #31
    //   1659: sipush #129
    //   1662: iastore
    //   1663: dup
    //   1664: bipush #32
    //   1666: ldc 8388736
    //   1668: iastore
    //   1669: dup
    //   1670: bipush #33
    //   1672: ldc 8388609
    //   1674: iastore
    //   1675: dup
    //   1676: bipush #34
    //   1678: ldc 8396800
    //   1680: iastore
    //   1681: dup
    //   1682: bipush #35
    //   1684: ldc 8396929
    //   1686: iastore
    //   1687: dup
    //   1688: bipush #36
    //   1690: sipush #129
    //   1693: iastore
    //   1694: dup
    //   1695: bipush #37
    //   1697: iconst_0
    //   1698: iastore
    //   1699: dup
    //   1700: bipush #38
    //   1702: iconst_0
    //   1703: iastore
    //   1704: dup
    //   1705: bipush #39
    //   1707: ldc 8396800
    //   1709: iastore
    //   1710: dup
    //   1711: bipush #40
    //   1713: sipush #8320
    //   1716: iastore
    //   1717: dup
    //   1718: bipush #41
    //   1720: ldc 8388736
    //   1722: iastore
    //   1723: dup
    //   1724: bipush #42
    //   1726: ldc 8388737
    //   1728: iastore
    //   1729: dup
    //   1730: bipush #43
    //   1732: iconst_1
    //   1733: iastore
    //   1734: dup
    //   1735: bipush #44
    //   1737: ldc 8396801
    //   1739: iastore
    //   1740: dup
    //   1741: bipush #45
    //   1743: sipush #8321
    //   1746: iastore
    //   1747: dup
    //   1748: bipush #46
    //   1750: sipush #8321
    //   1753: iastore
    //   1754: dup
    //   1755: bipush #47
    //   1757: sipush #128
    //   1760: iastore
    //   1761: dup
    //   1762: bipush #48
    //   1764: ldc 8396929
    //   1766: iastore
    //   1767: dup
    //   1768: bipush #49
    //   1770: sipush #129
    //   1773: iastore
    //   1774: dup
    //   1775: bipush #50
    //   1777: iconst_1
    //   1778: iastore
    //   1779: dup
    //   1780: bipush #51
    //   1782: sipush #8192
    //   1785: iastore
    //   1786: dup
    //   1787: bipush #52
    //   1789: ldc 8388609
    //   1791: iastore
    //   1792: dup
    //   1793: bipush #53
    //   1795: sipush #8193
    //   1798: iastore
    //   1799: dup
    //   1800: bipush #54
    //   1802: ldc 8396928
    //   1804: iastore
    //   1805: dup
    //   1806: bipush #55
    //   1808: ldc 8388737
    //   1810: iastore
    //   1811: dup
    //   1812: bipush #56
    //   1814: sipush #8193
    //   1817: iastore
    //   1818: dup
    //   1819: bipush #57
    //   1821: sipush #8320
    //   1824: iastore
    //   1825: dup
    //   1826: bipush #58
    //   1828: ldc 8388608
    //   1830: iastore
    //   1831: dup
    //   1832: bipush #59
    //   1834: ldc 8396801
    //   1836: iastore
    //   1837: dup
    //   1838: bipush #60
    //   1840: sipush #128
    //   1843: iastore
    //   1844: dup
    //   1845: bipush #61
    //   1847: ldc 8388608
    //   1849: iastore
    //   1850: dup
    //   1851: bipush #62
    //   1853: sipush #8192
    //   1856: iastore
    //   1857: dup
    //   1858: bipush #63
    //   1860: ldc 8396928
    //   1862: iastore
    //   1863: astore #11
    //   1865: bipush #64
    //   1867: newarray int
    //   1869: dup
    //   1870: iconst_0
    //   1871: sipush #256
    //   1874: iastore
    //   1875: dup
    //   1876: iconst_1
    //   1877: ldc 34078976
    //   1879: iastore
    //   1880: dup
    //   1881: iconst_2
    //   1882: ldc 34078720
    //   1884: iastore
    //   1885: dup
    //   1886: iconst_3
    //   1887: ldc 1107296512
    //   1889: iastore
    //   1890: dup
    //   1891: iconst_4
    //   1892: ldc 524288
    //   1894: iastore
    //   1895: dup
    //   1896: iconst_5
    //   1897: sipush #256
    //   1900: iastore
    //   1901: dup
    //   1902: bipush #6
    //   1904: ldc 1073741824
    //   1906: iastore
    //   1907: dup
    //   1908: bipush #7
    //   1910: ldc 34078720
    //   1912: iastore
    //   1913: dup
    //   1914: bipush #8
    //   1916: ldc 1074266368
    //   1918: iastore
    //   1919: dup
    //   1920: bipush #9
    //   1922: ldc 524288
    //   1924: iastore
    //   1925: dup
    //   1926: bipush #10
    //   1928: ldc 33554688
    //   1930: iastore
    //   1931: dup
    //   1932: bipush #11
    //   1934: ldc 1074266368
    //   1936: iastore
    //   1937: dup
    //   1938: bipush #12
    //   1940: ldc 1107296512
    //   1942: iastore
    //   1943: dup
    //   1944: bipush #13
    //   1946: ldc 1107820544
    //   1948: iastore
    //   1949: dup
    //   1950: bipush #14
    //   1952: ldc 524544
    //   1954: iastore
    //   1955: dup
    //   1956: bipush #15
    //   1958: ldc 1073741824
    //   1960: iastore
    //   1961: dup
    //   1962: bipush #16
    //   1964: ldc 33554432
    //   1966: iastore
    //   1967: dup
    //   1968: bipush #17
    //   1970: ldc 1074266112
    //   1972: iastore
    //   1973: dup
    //   1974: bipush #18
    //   1976: ldc 1074266112
    //   1978: iastore
    //   1979: dup
    //   1980: bipush #19
    //   1982: iconst_0
    //   1983: iastore
    //   1984: dup
    //   1985: bipush #20
    //   1987: ldc 1073742080
    //   1989: iastore
    //   1990: dup
    //   1991: bipush #21
    //   1993: ldc 1107820800
    //   1995: iastore
    //   1996: dup
    //   1997: bipush #22
    //   1999: ldc 1107820800
    //   2001: iastore
    //   2002: dup
    //   2003: bipush #23
    //   2005: ldc 33554688
    //   2007: iastore
    //   2008: dup
    //   2009: bipush #24
    //   2011: ldc 1107820544
    //   2013: iastore
    //   2014: dup
    //   2015: bipush #25
    //   2017: ldc 1073742080
    //   2019: iastore
    //   2020: dup
    //   2021: bipush #26
    //   2023: iconst_0
    //   2024: iastore
    //   2025: dup
    //   2026: bipush #27
    //   2028: ldc 1107296256
    //   2030: iastore
    //   2031: dup
    //   2032: bipush #28
    //   2034: ldc 34078976
    //   2036: iastore
    //   2037: dup
    //   2038: bipush #29
    //   2040: ldc 33554432
    //   2042: iastore
    //   2043: dup
    //   2044: bipush #30
    //   2046: ldc 1107296256
    //   2048: iastore
    //   2049: dup
    //   2050: bipush #31
    //   2052: ldc 524544
    //   2054: iastore
    //   2055: dup
    //   2056: bipush #32
    //   2058: ldc 524288
    //   2060: iastore
    //   2061: dup
    //   2062: bipush #33
    //   2064: ldc 1107296512
    //   2066: iastore
    //   2067: dup
    //   2068: bipush #34
    //   2070: sipush #256
    //   2073: iastore
    //   2074: dup
    //   2075: bipush #35
    //   2077: ldc 33554432
    //   2079: iastore
    //   2080: dup
    //   2081: bipush #36
    //   2083: ldc 1073741824
    //   2085: iastore
    //   2086: dup
    //   2087: bipush #37
    //   2089: ldc 34078720
    //   2091: iastore
    //   2092: dup
    //   2093: bipush #38
    //   2095: ldc 1107296512
    //   2097: iastore
    //   2098: dup
    //   2099: bipush #39
    //   2101: ldc 1074266368
    //   2103: iastore
    //   2104: dup
    //   2105: bipush #40
    //   2107: ldc 33554688
    //   2109: iastore
    //   2110: dup
    //   2111: bipush #41
    //   2113: ldc 1073741824
    //   2115: iastore
    //   2116: dup
    //   2117: bipush #42
    //   2119: ldc 1107820544
    //   2121: iastore
    //   2122: dup
    //   2123: bipush #43
    //   2125: ldc 34078976
    //   2127: iastore
    //   2128: dup
    //   2129: bipush #44
    //   2131: ldc 1074266368
    //   2133: iastore
    //   2134: dup
    //   2135: bipush #45
    //   2137: sipush #256
    //   2140: iastore
    //   2141: dup
    //   2142: bipush #46
    //   2144: ldc 33554432
    //   2146: iastore
    //   2147: dup
    //   2148: bipush #47
    //   2150: ldc 1107820544
    //   2152: iastore
    //   2153: dup
    //   2154: bipush #48
    //   2156: ldc 1107820800
    //   2158: iastore
    //   2159: dup
    //   2160: bipush #49
    //   2162: ldc 524544
    //   2164: iastore
    //   2165: dup
    //   2166: bipush #50
    //   2168: ldc 1107296256
    //   2170: iastore
    //   2171: dup
    //   2172: bipush #51
    //   2174: ldc 1107820800
    //   2176: iastore
    //   2177: dup
    //   2178: bipush #52
    //   2180: ldc 34078720
    //   2182: iastore
    //   2183: dup
    //   2184: bipush #53
    //   2186: iconst_0
    //   2187: iastore
    //   2188: dup
    //   2189: bipush #54
    //   2191: ldc 1074266112
    //   2193: iastore
    //   2194: dup
    //   2195: bipush #55
    //   2197: ldc 1107296256
    //   2199: iastore
    //   2200: dup
    //   2201: bipush #56
    //   2203: ldc 524544
    //   2205: iastore
    //   2206: dup
    //   2207: bipush #57
    //   2209: ldc 33554688
    //   2211: iastore
    //   2212: dup
    //   2213: bipush #58
    //   2215: ldc 1073742080
    //   2217: iastore
    //   2218: dup
    //   2219: bipush #59
    //   2221: ldc 524288
    //   2223: iastore
    //   2224: dup
    //   2225: bipush #60
    //   2227: iconst_0
    //   2228: iastore
    //   2229: dup
    //   2230: bipush #61
    //   2232: ldc 1074266112
    //   2234: iastore
    //   2235: dup
    //   2236: bipush #62
    //   2238: ldc 34078976
    //   2240: iastore
    //   2241: dup
    //   2242: bipush #63
    //   2244: ldc 1073742080
    //   2246: iastore
    //   2247: astore #12
    //   2249: bipush #64
    //   2251: newarray int
    //   2253: dup
    //   2254: iconst_0
    //   2255: ldc 536870928
    //   2257: iastore
    //   2258: dup
    //   2259: iconst_1
    //   2260: ldc 541065216
    //   2262: iastore
    //   2263: dup
    //   2264: iconst_2
    //   2265: sipush #16384
    //   2268: iastore
    //   2269: dup
    //   2270: iconst_3
    //   2271: ldc 541081616
    //   2273: iastore
    //   2274: dup
    //   2275: iconst_4
    //   2276: ldc 541065216
    //   2278: iastore
    //   2279: dup
    //   2280: iconst_5
    //   2281: bipush #16
    //   2283: iastore
    //   2284: dup
    //   2285: bipush #6
    //   2287: ldc 541081616
    //   2289: iastore
    //   2290: dup
    //   2291: bipush #7
    //   2293: ldc 4194304
    //   2295: iastore
    //   2296: dup
    //   2297: bipush #8
    //   2299: ldc 536887296
    //   2301: iastore
    //   2302: dup
    //   2303: bipush #9
    //   2305: ldc 4210704
    //   2307: iastore
    //   2308: dup
    //   2309: bipush #10
    //   2311: ldc 4194304
    //   2313: iastore
    //   2314: dup
    //   2315: bipush #11
    //   2317: ldc 536870928
    //   2319: iastore
    //   2320: dup
    //   2321: bipush #12
    //   2323: ldc 4194320
    //   2325: iastore
    //   2326: dup
    //   2327: bipush #13
    //   2329: ldc 536887296
    //   2331: iastore
    //   2332: dup
    //   2333: bipush #14
    //   2335: ldc 536870912
    //   2337: iastore
    //   2338: dup
    //   2339: bipush #15
    //   2341: sipush #16400
    //   2344: iastore
    //   2345: dup
    //   2346: bipush #16
    //   2348: iconst_0
    //   2349: iastore
    //   2350: dup
    //   2351: bipush #17
    //   2353: ldc 4194320
    //   2355: iastore
    //   2356: dup
    //   2357: bipush #18
    //   2359: ldc 536887312
    //   2361: iastore
    //   2362: dup
    //   2363: bipush #19
    //   2365: sipush #16384
    //   2368: iastore
    //   2369: dup
    //   2370: bipush #20
    //   2372: ldc 4210688
    //   2374: iastore
    //   2375: dup
    //   2376: bipush #21
    //   2378: ldc 536887312
    //   2380: iastore
    //   2381: dup
    //   2382: bipush #22
    //   2384: bipush #16
    //   2386: iastore
    //   2387: dup
    //   2388: bipush #23
    //   2390: ldc 541065232
    //   2392: iastore
    //   2393: dup
    //   2394: bipush #24
    //   2396: ldc 541065232
    //   2398: iastore
    //   2399: dup
    //   2400: bipush #25
    //   2402: iconst_0
    //   2403: iastore
    //   2404: dup
    //   2405: bipush #26
    //   2407: ldc 4210704
    //   2409: iastore
    //   2410: dup
    //   2411: bipush #27
    //   2413: ldc 541081600
    //   2415: iastore
    //   2416: dup
    //   2417: bipush #28
    //   2419: sipush #16400
    //   2422: iastore
    //   2423: dup
    //   2424: bipush #29
    //   2426: ldc 4210688
    //   2428: iastore
    //   2429: dup
    //   2430: bipush #30
    //   2432: ldc 541081600
    //   2434: iastore
    //   2435: dup
    //   2436: bipush #31
    //   2438: ldc 536870912
    //   2440: iastore
    //   2441: dup
    //   2442: bipush #32
    //   2444: ldc 536887296
    //   2446: iastore
    //   2447: dup
    //   2448: bipush #33
    //   2450: bipush #16
    //   2452: iastore
    //   2453: dup
    //   2454: bipush #34
    //   2456: ldc 541065232
    //   2458: iastore
    //   2459: dup
    //   2460: bipush #35
    //   2462: ldc 4210688
    //   2464: iastore
    //   2465: dup
    //   2466: bipush #36
    //   2468: ldc 541081616
    //   2470: iastore
    //   2471: dup
    //   2472: bipush #37
    //   2474: ldc 4194304
    //   2476: iastore
    //   2477: dup
    //   2478: bipush #38
    //   2480: sipush #16400
    //   2483: iastore
    //   2484: dup
    //   2485: bipush #39
    //   2487: ldc 536870928
    //   2489: iastore
    //   2490: dup
    //   2491: bipush #40
    //   2493: ldc 4194304
    //   2495: iastore
    //   2496: dup
    //   2497: bipush #41
    //   2499: ldc 536887296
    //   2501: iastore
    //   2502: dup
    //   2503: bipush #42
    //   2505: ldc 536870912
    //   2507: iastore
    //   2508: dup
    //   2509: bipush #43
    //   2511: sipush #16400
    //   2514: iastore
    //   2515: dup
    //   2516: bipush #44
    //   2518: ldc 536870928
    //   2520: iastore
    //   2521: dup
    //   2522: bipush #45
    //   2524: ldc 541081616
    //   2526: iastore
    //   2527: dup
    //   2528: bipush #46
    //   2530: ldc 4210688
    //   2532: iastore
    //   2533: dup
    //   2534: bipush #47
    //   2536: ldc 541065216
    //   2538: iastore
    //   2539: dup
    //   2540: bipush #48
    //   2542: ldc 4210704
    //   2544: iastore
    //   2545: dup
    //   2546: bipush #49
    //   2548: ldc 541081600
    //   2550: iastore
    //   2551: dup
    //   2552: bipush #50
    //   2554: iconst_0
    //   2555: iastore
    //   2556: dup
    //   2557: bipush #51
    //   2559: ldc 541065232
    //   2561: iastore
    //   2562: dup
    //   2563: bipush #52
    //   2565: bipush #16
    //   2567: iastore
    //   2568: dup
    //   2569: bipush #53
    //   2571: sipush #16384
    //   2574: iastore
    //   2575: dup
    //   2576: bipush #54
    //   2578: ldc 541065216
    //   2580: iastore
    //   2581: dup
    //   2582: bipush #55
    //   2584: ldc 4210704
    //   2586: iastore
    //   2587: dup
    //   2588: bipush #56
    //   2590: sipush #16384
    //   2593: iastore
    //   2594: dup
    //   2595: bipush #57
    //   2597: ldc 4194320
    //   2599: iastore
    //   2600: dup
    //   2601: bipush #58
    //   2603: ldc 536887312
    //   2605: iastore
    //   2606: dup
    //   2607: bipush #59
    //   2609: iconst_0
    //   2610: iastore
    //   2611: dup
    //   2612: bipush #60
    //   2614: ldc 541081600
    //   2616: iastore
    //   2617: dup
    //   2618: bipush #61
    //   2620: ldc 536870912
    //   2622: iastore
    //   2623: dup
    //   2624: bipush #62
    //   2626: ldc 4194320
    //   2628: iastore
    //   2629: dup
    //   2630: bipush #63
    //   2632: ldc 536887312
    //   2634: iastore
    //   2635: astore #13
    //   2637: bipush #64
    //   2639: newarray int
    //   2641: dup
    //   2642: iconst_0
    //   2643: ldc 2097152
    //   2645: iastore
    //   2646: dup
    //   2647: iconst_1
    //   2648: ldc 69206018
    //   2650: iastore
    //   2651: dup
    //   2652: iconst_2
    //   2653: ldc 67110914
    //   2655: iastore
    //   2656: dup
    //   2657: iconst_3
    //   2658: iconst_0
    //   2659: iastore
    //   2660: dup
    //   2661: iconst_4
    //   2662: sipush #2048
    //   2665: iastore
    //   2666: dup
    //   2667: iconst_5
    //   2668: ldc 67110914
    //   2670: iastore
    //   2671: dup
    //   2672: bipush #6
    //   2674: ldc 2099202
    //   2676: iastore
    //   2677: dup
    //   2678: bipush #7
    //   2680: ldc 69208064
    //   2682: iastore
    //   2683: dup
    //   2684: bipush #8
    //   2686: ldc 69208066
    //   2688: iastore
    //   2689: dup
    //   2690: bipush #9
    //   2692: ldc 2097152
    //   2694: iastore
    //   2695: dup
    //   2696: bipush #10
    //   2698: iconst_0
    //   2699: iastore
    //   2700: dup
    //   2701: bipush #11
    //   2703: ldc 67108866
    //   2705: iastore
    //   2706: dup
    //   2707: bipush #12
    //   2709: iconst_2
    //   2710: iastore
    //   2711: dup
    //   2712: bipush #13
    //   2714: ldc 67108864
    //   2716: iastore
    //   2717: dup
    //   2718: bipush #14
    //   2720: ldc 69206018
    //   2722: iastore
    //   2723: dup
    //   2724: bipush #15
    //   2726: sipush #2050
    //   2729: iastore
    //   2730: dup
    //   2731: bipush #16
    //   2733: ldc 67110912
    //   2735: iastore
    //   2736: dup
    //   2737: bipush #17
    //   2739: ldc 2099202
    //   2741: iastore
    //   2742: dup
    //   2743: bipush #18
    //   2745: ldc 2097154
    //   2747: iastore
    //   2748: dup
    //   2749: bipush #19
    //   2751: ldc 67110912
    //   2753: iastore
    //   2754: dup
    //   2755: bipush #20
    //   2757: ldc 67108866
    //   2759: iastore
    //   2760: dup
    //   2761: bipush #21
    //   2763: ldc 69206016
    //   2765: iastore
    //   2766: dup
    //   2767: bipush #22
    //   2769: ldc 69208064
    //   2771: iastore
    //   2772: dup
    //   2773: bipush #23
    //   2775: ldc 2097154
    //   2777: iastore
    //   2778: dup
    //   2779: bipush #24
    //   2781: ldc 69206016
    //   2783: iastore
    //   2784: dup
    //   2785: bipush #25
    //   2787: sipush #2048
    //   2790: iastore
    //   2791: dup
    //   2792: bipush #26
    //   2794: sipush #2050
    //   2797: iastore
    //   2798: dup
    //   2799: bipush #27
    //   2801: ldc 69208066
    //   2803: iastore
    //   2804: dup
    //   2805: bipush #28
    //   2807: ldc 2099200
    //   2809: iastore
    //   2810: dup
    //   2811: bipush #29
    //   2813: iconst_2
    //   2814: iastore
    //   2815: dup
    //   2816: bipush #30
    //   2818: ldc 67108864
    //   2820: iastore
    //   2821: dup
    //   2822: bipush #31
    //   2824: ldc 2099200
    //   2826: iastore
    //   2827: dup
    //   2828: bipush #32
    //   2830: ldc 67108864
    //   2832: iastore
    //   2833: dup
    //   2834: bipush #33
    //   2836: ldc 2099200
    //   2838: iastore
    //   2839: dup
    //   2840: bipush #34
    //   2842: ldc 2097152
    //   2844: iastore
    //   2845: dup
    //   2846: bipush #35
    //   2848: ldc 67110914
    //   2850: iastore
    //   2851: dup
    //   2852: bipush #36
    //   2854: ldc 67110914
    //   2856: iastore
    //   2857: dup
    //   2858: bipush #37
    //   2860: ldc 69206018
    //   2862: iastore
    //   2863: dup
    //   2864: bipush #38
    //   2866: ldc 69206018
    //   2868: iastore
    //   2869: dup
    //   2870: bipush #39
    //   2872: iconst_2
    //   2873: iastore
    //   2874: dup
    //   2875: bipush #40
    //   2877: ldc 2097154
    //   2879: iastore
    //   2880: dup
    //   2881: bipush #41
    //   2883: ldc 67108864
    //   2885: iastore
    //   2886: dup
    //   2887: bipush #42
    //   2889: ldc 67110912
    //   2891: iastore
    //   2892: dup
    //   2893: bipush #43
    //   2895: ldc 2097152
    //   2897: iastore
    //   2898: dup
    //   2899: bipush #44
    //   2901: ldc 69208064
    //   2903: iastore
    //   2904: dup
    //   2905: bipush #45
    //   2907: sipush #2050
    //   2910: iastore
    //   2911: dup
    //   2912: bipush #46
    //   2914: ldc 2099202
    //   2916: iastore
    //   2917: dup
    //   2918: bipush #47
    //   2920: ldc 69208064
    //   2922: iastore
    //   2923: dup
    //   2924: bipush #48
    //   2926: sipush #2050
    //   2929: iastore
    //   2930: dup
    //   2931: bipush #49
    //   2933: ldc 67108866
    //   2935: iastore
    //   2936: dup
    //   2937: bipush #50
    //   2939: ldc 69208066
    //   2941: iastore
    //   2942: dup
    //   2943: bipush #51
    //   2945: ldc 69206016
    //   2947: iastore
    //   2948: dup
    //   2949: bipush #52
    //   2951: ldc 2099200
    //   2953: iastore
    //   2954: dup
    //   2955: bipush #53
    //   2957: iconst_0
    //   2958: iastore
    //   2959: dup
    //   2960: bipush #54
    //   2962: iconst_2
    //   2963: iastore
    //   2964: dup
    //   2965: bipush #55
    //   2967: ldc 69208066
    //   2969: iastore
    //   2970: dup
    //   2971: bipush #56
    //   2973: iconst_0
    //   2974: iastore
    //   2975: dup
    //   2976: bipush #57
    //   2978: ldc 2099202
    //   2980: iastore
    //   2981: dup
    //   2982: bipush #58
    //   2984: ldc 69206016
    //   2986: iastore
    //   2987: dup
    //   2988: bipush #59
    //   2990: sipush #2048
    //   2993: iastore
    //   2994: dup
    //   2995: bipush #60
    //   2997: ldc 67108866
    //   2999: iastore
    //   3000: dup
    //   3001: bipush #61
    //   3003: ldc 67110912
    //   3005: iastore
    //   3006: dup
    //   3007: bipush #62
    //   3009: sipush #2048
    //   3012: iastore
    //   3013: dup
    //   3014: bipush #63
    //   3016: ldc 2097154
    //   3018: iastore
    //   3019: astore #14
    //   3021: bipush #64
    //   3023: newarray int
    //   3025: dup
    //   3026: iconst_0
    //   3027: ldc 268439616
    //   3029: iastore
    //   3030: dup
    //   3031: iconst_1
    //   3032: sipush #4096
    //   3035: iastore
    //   3036: dup
    //   3037: iconst_2
    //   3038: ldc 262144
    //   3040: iastore
    //   3041: dup
    //   3042: iconst_3
    //   3043: ldc 268701760
    //   3045: iastore
    //   3046: dup
    //   3047: iconst_4
    //   3048: ldc 268435456
    //   3050: iastore
    //   3051: dup
    //   3052: iconst_5
    //   3053: ldc 268439616
    //   3055: iastore
    //   3056: dup
    //   3057: bipush #6
    //   3059: bipush #64
    //   3061: iastore
    //   3062: dup
    //   3063: bipush #7
    //   3065: ldc 268435456
    //   3067: iastore
    //   3068: dup
    //   3069: bipush #8
    //   3071: ldc 262208
    //   3073: iastore
    //   3074: dup
    //   3075: bipush #9
    //   3077: ldc 268697600
    //   3079: iastore
    //   3080: dup
    //   3081: bipush #10
    //   3083: ldc 268701760
    //   3085: iastore
    //   3086: dup
    //   3087: bipush #11
    //   3089: ldc 266240
    //   3091: iastore
    //   3092: dup
    //   3093: bipush #12
    //   3095: ldc 268701696
    //   3097: iastore
    //   3098: dup
    //   3099: bipush #13
    //   3101: ldc 266304
    //   3103: iastore
    //   3104: dup
    //   3105: bipush #14
    //   3107: sipush #4096
    //   3110: iastore
    //   3111: dup
    //   3112: bipush #15
    //   3114: bipush #64
    //   3116: iastore
    //   3117: dup
    //   3118: bipush #16
    //   3120: ldc 268697600
    //   3122: iastore
    //   3123: dup
    //   3124: bipush #17
    //   3126: ldc 268435520
    //   3128: iastore
    //   3129: dup
    //   3130: bipush #18
    //   3132: ldc 268439552
    //   3134: iastore
    //   3135: dup
    //   3136: bipush #19
    //   3138: sipush #4160
    //   3141: iastore
    //   3142: dup
    //   3143: bipush #20
    //   3145: ldc 266240
    //   3147: iastore
    //   3148: dup
    //   3149: bipush #21
    //   3151: ldc 262208
    //   3153: iastore
    //   3154: dup
    //   3155: bipush #22
    //   3157: ldc 268697664
    //   3159: iastore
    //   3160: dup
    //   3161: bipush #23
    //   3163: ldc 268701696
    //   3165: iastore
    //   3166: dup
    //   3167: bipush #24
    //   3169: sipush #4160
    //   3172: iastore
    //   3173: dup
    //   3174: bipush #25
    //   3176: iconst_0
    //   3177: iastore
    //   3178: dup
    //   3179: bipush #26
    //   3181: iconst_0
    //   3182: iastore
    //   3183: dup
    //   3184: bipush #27
    //   3186: ldc 268697664
    //   3188: iastore
    //   3189: dup
    //   3190: bipush #28
    //   3192: ldc 268435520
    //   3194: iastore
    //   3195: dup
    //   3196: bipush #29
    //   3198: ldc 268439552
    //   3200: iastore
    //   3201: dup
    //   3202: bipush #30
    //   3204: ldc 266304
    //   3206: iastore
    //   3207: dup
    //   3208: bipush #31
    //   3210: ldc 262144
    //   3212: iastore
    //   3213: dup
    //   3214: bipush #32
    //   3216: ldc 266304
    //   3218: iastore
    //   3219: dup
    //   3220: bipush #33
    //   3222: ldc 262144
    //   3224: iastore
    //   3225: dup
    //   3226: bipush #34
    //   3228: ldc 268701696
    //   3230: iastore
    //   3231: dup
    //   3232: bipush #35
    //   3234: sipush #4096
    //   3237: iastore
    //   3238: dup
    //   3239: bipush #36
    //   3241: bipush #64
    //   3243: iastore
    //   3244: dup
    //   3245: bipush #37
    //   3247: ldc 268697664
    //   3249: iastore
    //   3250: dup
    //   3251: bipush #38
    //   3253: sipush #4096
    //   3256: iastore
    //   3257: dup
    //   3258: bipush #39
    //   3260: ldc 266304
    //   3262: iastore
    //   3263: dup
    //   3264: bipush #40
    //   3266: ldc 268439552
    //   3268: iastore
    //   3269: dup
    //   3270: bipush #41
    //   3272: bipush #64
    //   3274: iastore
    //   3275: dup
    //   3276: bipush #42
    //   3278: ldc 268435520
    //   3280: iastore
    //   3281: dup
    //   3282: bipush #43
    //   3284: ldc 268697600
    //   3286: iastore
    //   3287: dup
    //   3288: bipush #44
    //   3290: ldc 268697664
    //   3292: iastore
    //   3293: dup
    //   3294: bipush #45
    //   3296: ldc 268435456
    //   3298: iastore
    //   3299: dup
    //   3300: bipush #46
    //   3302: ldc 262144
    //   3304: iastore
    //   3305: dup
    //   3306: bipush #47
    //   3308: ldc 268439616
    //   3310: iastore
    //   3311: dup
    //   3312: bipush #48
    //   3314: iconst_0
    //   3315: iastore
    //   3316: dup
    //   3317: bipush #49
    //   3319: ldc 268701760
    //   3321: iastore
    //   3322: dup
    //   3323: bipush #50
    //   3325: ldc 262208
    //   3327: iastore
    //   3328: dup
    //   3329: bipush #51
    //   3331: ldc 268435520
    //   3333: iastore
    //   3334: dup
    //   3335: bipush #52
    //   3337: ldc 268697600
    //   3339: iastore
    //   3340: dup
    //   3341: bipush #53
    //   3343: ldc 268439552
    //   3345: iastore
    //   3346: dup
    //   3347: bipush #54
    //   3349: ldc 268439616
    //   3351: iastore
    //   3352: dup
    //   3353: bipush #55
    //   3355: iconst_0
    //   3356: iastore
    //   3357: dup
    //   3358: bipush #56
    //   3360: ldc 268701760
    //   3362: iastore
    //   3363: dup
    //   3364: bipush #57
    //   3366: ldc 266240
    //   3368: iastore
    //   3369: dup
    //   3370: bipush #58
    //   3372: ldc 266240
    //   3374: iastore
    //   3375: dup
    //   3376: bipush #59
    //   3378: sipush #4160
    //   3381: iastore
    //   3382: dup
    //   3383: bipush #60
    //   3385: sipush #4160
    //   3388: iastore
    //   3389: dup
    //   3390: bipush #61
    //   3392: ldc 262208
    //   3394: iastore
    //   3395: dup
    //   3396: bipush #62
    //   3398: ldc 268435456
    //   3400: iastore
    //   3401: dup
    //   3402: bipush #63
    //   3404: ldc 268701696
    //   3406: iastore
    //   3407: astore #15
    //   3409: aload_3
    //   3410: arraylength
    //   3411: istore #16
    //   3413: iconst_2
    //   3414: newarray int
    //   3416: astore #17
    //   3418: iload #16
    //   3420: newarray byte
    //   3422: astore #4
    //   3424: iload #16
    //   3426: bipush #8
    //   3428: idiv
    //   3429: istore #18
    //   3431: iconst_0
    //   3432: istore #19
    //   3434: iload #19
    //   3436: iload #18
    //   3438: if_icmpge -> 4352
    //   3441: iload #19
    //   3443: bipush #8
    //   3445: imul
    //   3446: istore #20
    //   3448: iconst_0
    //   3449: istore #21
    //   3451: iload #21
    //   3453: iconst_2
    //   3454: if_icmpge -> 3539
    //   3457: aload #17
    //   3459: iload #21
    //   3461: aload_3
    //   3462: iload #20
    //   3464: iload #21
    //   3466: iconst_4
    //   3467: imul
    //   3468: iadd
    //   3469: baload
    //   3470: sipush #255
    //   3473: iand
    //   3474: bipush #24
    //   3476: ishl
    //   3477: aload_3
    //   3478: iload #20
    //   3480: iload #21
    //   3482: iconst_4
    //   3483: imul
    //   3484: iadd
    //   3485: iconst_1
    //   3486: iadd
    //   3487: baload
    //   3488: sipush #255
    //   3491: iand
    //   3492: bipush #16
    //   3494: ishl
    //   3495: ior
    //   3496: aload_3
    //   3497: iload #20
    //   3499: iload #21
    //   3501: iconst_4
    //   3502: imul
    //   3503: iadd
    //   3504: iconst_2
    //   3505: iadd
    //   3506: baload
    //   3507: sipush #255
    //   3510: iand
    //   3511: bipush #8
    //   3513: ishl
    //   3514: ior
    //   3515: aload_3
    //   3516: iload #20
    //   3518: iload #21
    //   3520: iconst_4
    //   3521: imul
    //   3522: iadd
    //   3523: iconst_3
    //   3524: iadd
    //   3525: baload
    //   3526: sipush #255
    //   3529: iand
    //   3530: ior
    //   3531: iastore
    //   3532: iinc #21, 1
    //   3535: iload_2
    //   3536: ifne -> 3451
    //   3539: iconst_0
    //   3540: istore #26
    //   3542: aload #17
    //   3544: iconst_0
    //   3545: iaload
    //   3546: istore #24
    //   3548: aload #17
    //   3550: iconst_1
    //   3551: iaload
    //   3552: istore #23
    //   3554: iload #24
    //   3556: iconst_4
    //   3557: iushr
    //   3558: iload #23
    //   3560: ixor
    //   3561: ldc 252645135
    //   3563: iand
    //   3564: istore #22
    //   3566: iload #23
    //   3568: iload #22
    //   3570: ixor
    //   3571: istore #23
    //   3573: iload #24
    //   3575: iload #22
    //   3577: iconst_4
    //   3578: ishl
    //   3579: ixor
    //   3580: istore #24
    //   3582: iload #24
    //   3584: bipush #16
    //   3586: iushr
    //   3587: iload #23
    //   3589: ixor
    //   3590: ldc 65535
    //   3592: iand
    //   3593: istore #22
    //   3595: iload #23
    //   3597: iload #22
    //   3599: ixor
    //   3600: istore #23
    //   3602: iload #24
    //   3604: iload #22
    //   3606: bipush #16
    //   3608: ishl
    //   3609: ixor
    //   3610: istore #24
    //   3612: iload #23
    //   3614: iconst_2
    //   3615: iushr
    //   3616: iload #24
    //   3618: ixor
    //   3619: ldc 858993459
    //   3621: iand
    //   3622: istore #22
    //   3624: iload #24
    //   3626: iload #22
    //   3628: ixor
    //   3629: istore #24
    //   3631: iload #23
    //   3633: iload #22
    //   3635: iconst_2
    //   3636: ishl
    //   3637: ixor
    //   3638: istore #23
    //   3640: iload #23
    //   3642: bipush #8
    //   3644: iushr
    //   3645: iload #24
    //   3647: ixor
    //   3648: ldc 16711935
    //   3650: iand
    //   3651: istore #22
    //   3653: iload #24
    //   3655: iload #22
    //   3657: ixor
    //   3658: istore #24
    //   3660: iload #23
    //   3662: iload #22
    //   3664: bipush #8
    //   3666: ishl
    //   3667: ixor
    //   3668: istore #23
    //   3670: iload #23
    //   3672: iconst_1
    //   3673: ishl
    //   3674: iload #23
    //   3676: bipush #31
    //   3678: iushr
    //   3679: iconst_1
    //   3680: iand
    //   3681: ior
    //   3682: istore #23
    //   3684: iload #24
    //   3686: iload #23
    //   3688: ixor
    //   3689: ldc -1431655766
    //   3691: iand
    //   3692: istore #22
    //   3694: iload #24
    //   3696: iload #22
    //   3698: ixor
    //   3699: istore #24
    //   3701: iload #23
    //   3703: iload #22
    //   3705: ixor
    //   3706: istore #23
    //   3708: iload #24
    //   3710: iconst_1
    //   3711: ishl
    //   3712: iload #24
    //   3714: bipush #31
    //   3716: iushr
    //   3717: iconst_1
    //   3718: iand
    //   3719: ior
    //   3720: istore #24
    //   3722: iconst_0
    //   3723: istore #25
    //   3725: iload #25
    //   3727: bipush #8
    //   3729: if_icmpge -> 4067
    //   3732: iload #23
    //   3734: bipush #28
    //   3736: ishl
    //   3737: iload #23
    //   3739: iconst_4
    //   3740: iushr
    //   3741: ior
    //   3742: istore #22
    //   3744: iload #22
    //   3746: aload #5
    //   3748: iload #26
    //   3750: iinc #26, 1
    //   3753: iaload
    //   3754: ixor
    //   3755: istore #22
    //   3757: aload #14
    //   3759: iload #22
    //   3761: bipush #63
    //   3763: iand
    //   3764: iaload
    //   3765: istore #21
    //   3767: iload #21
    //   3769: aload #12
    //   3771: iload #22
    //   3773: bipush #8
    //   3775: iushr
    //   3776: bipush #63
    //   3778: iand
    //   3779: iaload
    //   3780: ior
    //   3781: istore #21
    //   3783: iload #21
    //   3785: aload #10
    //   3787: iload #22
    //   3789: bipush #16
    //   3791: iushr
    //   3792: bipush #63
    //   3794: iand
    //   3795: iaload
    //   3796: ior
    //   3797: istore #21
    //   3799: iload #21
    //   3801: aload #8
    //   3803: iload #22
    //   3805: bipush #24
    //   3807: iushr
    //   3808: bipush #63
    //   3810: iand
    //   3811: iaload
    //   3812: ior
    //   3813: istore #21
    //   3815: iload #23
    //   3817: aload #5
    //   3819: iload #26
    //   3821: iinc #26, 1
    //   3824: iaload
    //   3825: ixor
    //   3826: istore #22
    //   3828: iload #21
    //   3830: aload #15
    //   3832: iload #22
    //   3834: bipush #63
    //   3836: iand
    //   3837: iaload
    //   3838: ior
    //   3839: istore #21
    //   3841: iload #21
    //   3843: aload #13
    //   3845: iload #22
    //   3847: bipush #8
    //   3849: iushr
    //   3850: bipush #63
    //   3852: iand
    //   3853: iaload
    //   3854: ior
    //   3855: istore #21
    //   3857: iload #21
    //   3859: aload #11
    //   3861: iload #22
    //   3863: bipush #16
    //   3865: iushr
    //   3866: bipush #63
    //   3868: iand
    //   3869: iaload
    //   3870: ior
    //   3871: istore #21
    //   3873: iload #21
    //   3875: aload #9
    //   3877: iload #22
    //   3879: bipush #24
    //   3881: iushr
    //   3882: bipush #63
    //   3884: iand
    //   3885: iaload
    //   3886: ior
    //   3887: istore #21
    //   3889: iload #24
    //   3891: iload #21
    //   3893: ixor
    //   3894: istore #24
    //   3896: iload #24
    //   3898: bipush #28
    //   3900: ishl
    //   3901: iload #24
    //   3903: iconst_4
    //   3904: iushr
    //   3905: ior
    //   3906: istore #22
    //   3908: iload #22
    //   3910: aload #5
    //   3912: iload #26
    //   3914: iinc #26, 1
    //   3917: iaload
    //   3918: ixor
    //   3919: istore #22
    //   3921: aload #14
    //   3923: iload #22
    //   3925: bipush #63
    //   3927: iand
    //   3928: iaload
    //   3929: istore #21
    //   3931: iload #21
    //   3933: aload #12
    //   3935: iload #22
    //   3937: bipush #8
    //   3939: iushr
    //   3940: bipush #63
    //   3942: iand
    //   3943: iaload
    //   3944: ior
    //   3945: istore #21
    //   3947: iload #21
    //   3949: aload #10
    //   3951: iload #22
    //   3953: bipush #16
    //   3955: iushr
    //   3956: bipush #63
    //   3958: iand
    //   3959: iaload
    //   3960: ior
    //   3961: istore #21
    //   3963: iload #21
    //   3965: aload #8
    //   3967: iload #22
    //   3969: bipush #24
    //   3971: iushr
    //   3972: bipush #63
    //   3974: iand
    //   3975: iaload
    //   3976: ior
    //   3977: istore #21
    //   3979: iload #24
    //   3981: aload #5
    //   3983: iload #26
    //   3985: iinc #26, 1
    //   3988: iaload
    //   3989: ixor
    //   3990: istore #22
    //   3992: iload #21
    //   3994: aload #15
    //   3996: iload #22
    //   3998: bipush #63
    //   4000: iand
    //   4001: iaload
    //   4002: ior
    //   4003: istore #21
    //   4005: iload #21
    //   4007: aload #13
    //   4009: iload #22
    //   4011: bipush #8
    //   4013: iushr
    //   4014: bipush #63
    //   4016: iand
    //   4017: iaload
    //   4018: ior
    //   4019: istore #21
    //   4021: iload #21
    //   4023: aload #11
    //   4025: iload #22
    //   4027: bipush #16
    //   4029: iushr
    //   4030: bipush #63
    //   4032: iand
    //   4033: iaload
    //   4034: ior
    //   4035: istore #21
    //   4037: iload #21
    //   4039: aload #9
    //   4041: iload #22
    //   4043: bipush #24
    //   4045: iushr
    //   4046: bipush #63
    //   4048: iand
    //   4049: iaload
    //   4050: ior
    //   4051: istore #21
    //   4053: iload #23
    //   4055: iload #21
    //   4057: ixor
    //   4058: istore #23
    //   4060: iinc #25, 1
    //   4063: iload_2
    //   4064: ifne -> 3725
    //   4067: iload #23
    //   4069: bipush #31
    //   4071: ishl
    //   4072: iload #23
    //   4074: iconst_1
    //   4075: iushr
    //   4076: ior
    //   4077: istore #23
    //   4079: iload #24
    //   4081: iload #23
    //   4083: ixor
    //   4084: ldc -1431655766
    //   4086: iand
    //   4087: istore #22
    //   4089: iload #24
    //   4091: iload #22
    //   4093: ixor
    //   4094: istore #24
    //   4096: iload #23
    //   4098: iload #22
    //   4100: ixor
    //   4101: istore #23
    //   4103: iload #24
    //   4105: bipush #31
    //   4107: ishl
    //   4108: iload #24
    //   4110: iconst_1
    //   4111: iushr
    //   4112: ior
    //   4113: istore #24
    //   4115: iload #24
    //   4117: bipush #8
    //   4119: iushr
    //   4120: iload #23
    //   4122: ixor
    //   4123: ldc 16711935
    //   4125: iand
    //   4126: istore #22
    //   4128: iload #23
    //   4130: iload #22
    //   4132: ixor
    //   4133: istore #23
    //   4135: iload #24
    //   4137: iload #22
    //   4139: bipush #8
    //   4141: ishl
    //   4142: ixor
    //   4143: istore #24
    //   4145: iload #24
    //   4147: iconst_2
    //   4148: iushr
    //   4149: iload #23
    //   4151: ixor
    //   4152: ldc 858993459
    //   4154: iand
    //   4155: istore #22
    //   4157: iload #23
    //   4159: iload #22
    //   4161: ixor
    //   4162: istore #23
    //   4164: iload #24
    //   4166: iload #22
    //   4168: iconst_2
    //   4169: ishl
    //   4170: ixor
    //   4171: istore #24
    //   4173: iload #23
    //   4175: bipush #16
    //   4177: iushr
    //   4178: iload #24
    //   4180: ixor
    //   4181: ldc 65535
    //   4183: iand
    //   4184: istore #22
    //   4186: iload #24
    //   4188: iload #22
    //   4190: ixor
    //   4191: istore #24
    //   4193: iload #23
    //   4195: iload #22
    //   4197: bipush #16
    //   4199: ishl
    //   4200: ixor
    //   4201: istore #23
    //   4203: iload #23
    //   4205: iconst_4
    //   4206: iushr
    //   4207: iload #24
    //   4209: ixor
    //   4210: ldc 252645135
    //   4212: iand
    //   4213: istore #22
    //   4215: iload #24
    //   4217: iload #22
    //   4219: ixor
    //   4220: istore #24
    //   4222: iload #23
    //   4224: iload #22
    //   4226: iconst_4
    //   4227: ishl
    //   4228: ixor
    //   4229: istore #23
    //   4231: aload #17
    //   4233: iconst_0
    //   4234: iload #23
    //   4236: iastore
    //   4237: aload #17
    //   4239: iconst_1
    //   4240: iload #24
    //   4242: iastore
    //   4243: iload #19
    //   4245: bipush #8
    //   4247: imul
    //   4248: istore #27
    //   4250: iconst_0
    //   4251: istore #28
    //   4253: iload #28
    //   4255: iconst_2
    //   4256: if_icmpge -> 4345
    //   4259: aload #4
    //   4261: iload #27
    //   4263: iload #28
    //   4265: iconst_4
    //   4266: imul
    //   4267: iadd
    //   4268: aload #17
    //   4270: iload #28
    //   4272: iaload
    //   4273: bipush #24
    //   4275: iushr
    //   4276: i2b
    //   4277: bastore
    //   4278: aload #4
    //   4280: iload #27
    //   4282: iload #28
    //   4284: iconst_4
    //   4285: imul
    //   4286: iadd
    //   4287: iconst_1
    //   4288: iadd
    //   4289: aload #17
    //   4291: iload #28
    //   4293: iaload
    //   4294: bipush #16
    //   4296: iushr
    //   4297: i2b
    //   4298: bastore
    //   4299: aload #4
    //   4301: iload #27
    //   4303: iload #28
    //   4305: iconst_4
    //   4306: imul
    //   4307: iadd
    //   4308: iconst_2
    //   4309: iadd
    //   4310: aload #17
    //   4312: iload #28
    //   4314: iaload
    //   4315: bipush #8
    //   4317: iushr
    //   4318: i2b
    //   4319: bastore
    //   4320: aload #4
    //   4322: iload #27
    //   4324: iload #28
    //   4326: iconst_4
    //   4327: imul
    //   4328: iadd
    //   4329: iconst_3
    //   4330: iadd
    //   4331: aload #17
    //   4333: iload #28
    //   4335: iaload
    //   4336: i2b
    //   4337: bastore
    //   4338: iinc #28, 1
    //   4341: iload_2
    //   4342: ifne -> 4253
    //   4345: iinc #19, 1
    //   4348: iload_2
    //   4349: ifne -> 3434
    //   4352: new java/math/BigInteger
    //   4355: dup
    //   4356: aload #4
    //   4358: invokespecial <init> : ([B)V
    //   4361: invokevirtual abs : ()Ljava/math/BigInteger;
    //   4364: putstatic burp/Ze57.ZR : Ljava/lang/Object;
    //   4367: sipush #-30395
    //   4370: getstatic burp/Zgfm.ZV : Ljava/lang/Object;
    //   4373: checkcast java/math/BigInteger
    //   4376: getstatic burp/Zg0j.ZV : Ljava/lang/Object;
    //   4379: checkcast java/math/BigInteger
    //   4382: invokevirtual subtract : (Ljava/math/BigInteger;)Ljava/math/BigInteger;
    //   4385: putstatic burp/Zss6.ZG : Ljava/lang/Object;
    //   4388: sipush #24058
    //   4391: invokestatic a : (II)Ljava/lang/String;
    //   4394: iconst_1
    //   4395: ldc burp/Zzai
    //   4397: invokevirtual getClassLoader : ()Ljava/lang/ClassLoader;
    //   4400: invokestatic forName : (Ljava/lang/String;ZLjava/lang/ClassLoader;)Ljava/lang/Class;
    //   4403: invokevirtual getDeclaredFields : ()[Ljava/lang/reflect/Field;
    //   4406: astore_3
    //   4407: aload_3
    //   4408: arraylength
    //   4409: istore #4
    //   4411: iconst_0
    //   4412: istore #5
    //   4414: iload #5
    //   4416: iload #4
    //   4418: if_icmpge -> 4555
    //   4421: aload_3
    //   4422: iload #5
    //   4424: aaload
    //   4425: astore #6
    //   4427: aload #6
    //   4429: invokevirtual getModifiers : ()I
    //   4432: invokestatic isStatic : (I)Z
    //   4435: ifne -> 4445
    //   4438: goto -> 4548
    //   4441: invokestatic a : (Ljava/lang/Throwable;)Ljava/lang/Throwable;
    //   4444: athrow
    //   4445: aload #6
    //   4447: invokevirtual getType : ()Ljava/lang/Class;
    //   4450: astore #7
    //   4452: aload #7
    //   4454: ifnull -> 4535
    //   4457: aload #7
    //   4459: invokevirtual isPrimitive : ()Z
    //   4462: ifne -> 4535
    //   4465: goto -> 4472
    //   4468: invokestatic a : (Ljava/lang/Throwable;)Ljava/lang/Throwable;
    //   4471: athrow
    //   4472: aload #7
    //   4474: invokevirtual getPackage : ()Ljava/lang/Package;
    //   4477: ifnull -> 4535
    //   4480: goto -> 4487
    //   4483: invokestatic a : (Ljava/lang/Throwable;)Ljava/lang/Throwable;
    //   4486: athrow
    //   4487: aload #7
    //   4489: invokevirtual getPackage : ()Ljava/lang/Package;
    //   4492: invokevirtual getName : ()Ljava/lang/String;
    //   4495: ifnull -> 4535
    //   4498: goto -> 4505
    //   4501: invokestatic a : (Ljava/lang/Throwable;)Ljava/lang/Throwable;
    //   4504: athrow
    //   4505: aload #7
    //   4507: invokevirtual getPackage : ()Ljava/lang/Package;
    //   4510: invokevirtual getName : ()Ljava/lang/String;
    //   4513: sipush #-30400
    //   4516: sipush #2750
    //   4519: invokestatic a : (II)Ljava/lang/String;
    //   4522: invokevirtual startsWith : (Ljava/lang/String;)Z
    //   4525: ifne -> 4535
    //   4528: goto -> 4535
    //   4531: invokestatic a : (Ljava/lang/Throwable;)Ljava/lang/Throwable;
    //   4534: athrow
    //   4535: aload #6
    //   4537: iconst_1
    //   4538: invokevirtual setAccessible : (Z)V
    //   4541: aload #6
    //   4543: aconst_null
    //   4544: invokevirtual get : (Ljava/lang/Object;)Ljava/lang/Object;
    //   4547: pop
    //   4548: iinc #5, 1
    //   4551: iload_2
    //   4552: ifne -> 4414
    //   4555: sipush #-30398
    //   4558: sipush #12551
    //   4561: invokestatic a : (II)Ljava/lang/String;
    //   4564: invokestatic forName : (Ljava/lang/String;)Ljava/lang/Class;
    //   4567: invokevirtual getDeclaredMethods : ()[Ljava/lang/reflect/Method;
    //   4570: astore_3
    //   4571: aload_3
    //   4572: arraylength
    //   4573: istore #4
    //   4575: iconst_0
    //   4576: istore #5
    //   4578: iload #5
    //   4580: iload #4
    //   4582: if_icmpge -> 4714
    //   4585: aload_3
    //   4586: iload #5
    //   4588: aaload
    //   4589: astore #6
    //   4591: aload #6
    //   4593: invokevirtual getParameterTypes : ()[Ljava/lang/Class;
    //   4596: pop
    //   4597: aload #6
    //   4599: invokevirtual getModifiers : ()I
    //   4602: invokestatic isStatic : (I)Z
    //   4605: ifeq -> 4700
    //   4608: aload #6
    //   4610: invokevirtual getParameterTypes : ()[Ljava/lang/Class;
    //   4613: arraylength
    //   4614: iconst_2
    //   4615: if_icmpne -> 4700
    //   4618: goto -> 4625
    //   4621: invokestatic a : (Ljava/lang/Throwable;)Ljava/lang/Throwable;
    //   4624: athrow
    //   4625: aload #6
    //   4627: invokevirtual getReturnType : ()Ljava/lang/Class;
    //   4630: getstatic java/lang/Void.TYPE : Ljava/lang/Class;
    //   4633: invokevirtual equals : (Ljava/lang/Object;)Z
    //   4636: ifeq -> 4700
    //   4639: goto -> 4646
    //   4642: invokestatic a : (Ljava/lang/Throwable;)Ljava/lang/Throwable;
    //   4645: athrow
    //   4646: aload #6
    //   4648: iconst_1
    //   4649: invokevirtual setAccessible : (Z)V
    //   4652: aload #6
    //   4654: aconst_null
    //   4655: iconst_2
    //   4656: anewarray java/lang/Object
    //   4659: dup
    //   4660: iconst_0
    //   4661: aload_0
    //   4662: aastore
    //   4663: dup
    //   4664: iconst_1
    //   4665: aload_1
    //   4666: ifnonnull -> 4684
    //   4669: goto -> 4676
    //   4672: invokestatic a : (Ljava/lang/Throwable;)Ljava/lang/Throwable;
    //   4675: athrow
    //   4676: aload_1
    //   4677: goto -> 4691
    //   4680: invokestatic a : (Ljava/lang/Throwable;)Ljava/lang/Throwable;
    //   4683: athrow
    //   4684: aload_1
    //   4685: checkcast [B
    //   4688: invokevirtual clone : ()Ljava/lang/Object;
    //   4691: aastore
    //   4692: invokevirtual invoke : (Ljava/lang/Object;[Ljava/lang/Object;)Ljava/lang/Object;
    //   4695: pop
    //   4696: iload_2
    //   4697: ifne -> 4714
    //   4700: iinc #5, 1
    //   4703: iload_2
    //   4704: ifne -> 4578
    //   4707: goto -> 4714
    //   4710: invokestatic a : (Ljava/lang/Throwable;)Ljava/lang/Throwable;
    //   4713: athrow
    //   4714: getstatic burp/Zl7k.ZX : Ljava/lang/String;
    //   4717: getstatic burp/Zxrd.ZL : Ljava/lang/Object;
    //   4720: checkcast java/math/BigInteger
    //   4723: invokevirtual intValue : ()I
    //   4726: bipush #32
    //   4728: irem
    //   4729: invokestatic abs : (I)I
    //   4732: invokevirtual charAt : (I)C
    //   4735: getstatic burp/Zgmt.Zu : Ljava/lang/String;
    //   4738: getstatic burp/Zttj.ZF : Ljava/lang/Object;
    //   4741: checkcast java/math/BigInteger
    //   4744: invokevirtual intValue : ()I
    //   4747: bipush #32
    //   4749: irem
    //   4750: invokestatic abs : (I)I
    //   4753: invokevirtual charAt : (I)C
    //   4756: if_icmple -> 4863
    //   4759: getstatic burp/Zl2t.Zg : Ljava/lang/String;
    //   4762: getstatic burp/Zxxd.Zn : Ljava/lang/Object;
    //   4765: checkcast java/math/BigInteger
    //   4768: invokevirtual intValue : ()I
    //   4771: bipush #32
    //   4773: irem
    //   4774: invokestatic abs : (I)I
    //   4777: invokevirtual charAt : (I)C
    //   4780: getstatic burp/Zt0t.ZR : Ljava/lang/String;
    //   4783: getstatic burp/Zezi.ZQ : Ljava/lang/Object;
    //   4786: checkcast java/math/BigInteger
    //   4789: invokevirtual intValue : ()I
    //   4792: bipush #32
    //   4794: irem
    //   4795: invokestatic abs : (I)I
    //   4798: invokevirtual charAt : (I)C
    //   4801: if_icmpgt -> 4863
    //   4804: goto -> 4811
    //   4807: invokestatic a : (Ljava/lang/Throwable;)Ljava/lang/Throwable;
    //   4810: athrow
    //   4811: getstatic burp/Zstq.ZL : Ljava/lang/String;
    //   4814: getstatic burp/Zsf7.Zg : Ljava/lang/Object;
    //   4817: checkcast java/math/BigInteger
    //   4820: invokevirtual intValue : ()I
    //   4823: bipush #32
    //   4825: irem
    //   4826: invokestatic abs : (I)I
    //   4829: invokevirtual charAt : (I)C
    //   4832: getstatic burp/Zbzk.ZS : Ljava/lang/String;
    //   4835: getstatic burp/Zl2g.ZG : Ljava/lang/Object;
    //   4838: checkcast java/math/BigInteger
    //   4841: invokevirtual intValue : ()I
    //   4844: bipush #32
    //   4846: irem
    //   4847: invokestatic abs : (I)I
    //   4850: invokevirtual charAt : (I)C
    //   4853: if_icmple -> 4871
    //   4856: goto -> 4863
    //   4859: invokestatic a : (Ljava/lang/Throwable;)Ljava/lang/Throwable;
    //   4862: athrow
    //   4863: iconst_1
    //   4864: goto -> 4872
    //   4867: invokestatic a : (Ljava/lang/Throwable;)Ljava/lang/Throwable;
    //   4870: athrow
    //   4871: iconst_0
    //   4872: ireturn
    //   4873: astore_3
    //   4874: new java/lang/Exception
    //   4877: dup
    //   4878: aload_3
    //   4879: invokevirtual getMessage : ()Ljava/lang/String;
    //   4882: invokespecial <init> : (Ljava/lang/String;)V
    //   4885: athrow
    // Exception table:
    //   from	to	target	type
    //   4	4872	4873	java/lang/Throwable
    //   4427	4441	4441	java/lang/Throwable
    //   4452	4465	4468	java/lang/Throwable
    //   4457	4480	4483	java/lang/Throwable
    //   4472	4498	4501	java/lang/Throwable
    //   4487	4528	4531	java/lang/Throwable
    //   4591	4618	4621	java/lang/Throwable
    //   4608	4639	4642	java/lang/Throwable
    //   4625	4669	4672	java/lang/Throwable
    //   4646	4680	4680	java/lang/Throwable
    //   4691	4707	4710	java/lang/Throwable
    //   4714	4804	4807	java/lang/Throwable
    //   4759	4856	4859	java/lang/Throwable
    //   4811	4867	4867	java/lang/Throwable
  }
  
  static {
    // Byte code:
    //   0: bipush #9
    //   2: anewarray java/lang/String
    //   5: astore #5
    //   7: iconst_0
    //   8: istore_3
    //   9: ldc 'jNi}ZE/*XGI7Tn4  unPeC5'\\t\\rla9PI/\\tw5~uL2{ni<qddH6[1\\fSVSmUKLY@pfmy7Ve\9b\\ti\\fsx;'
    //   11: dup
    //   12: astore_2
    //   13: invokevirtual length : ()I
    //   16: istore #4
    //   18: bipush #32
    //   20: istore_1
    //   21: iconst_m1
    //   22: istore_0
    //   23: bipush #125
    //   25: iinc #0, 1
    //   28: aload_2
    //   29: iload_0
    //   30: dup
    //   31: iload_1
    //   32: iadd
    //   33: invokevirtual substring : (II)Ljava/lang/String;
    //   36: iconst_m1
    //   37: goto -> 143
    //   40: aload #5
    //   42: swap
    //   43: iload_3
    //   44: iinc #3, 1
    //   47: swap
    //   48: aastore
    //   49: iload_0
    //   50: iload_1
    //   51: iadd
    //   52: dup
    //   53: istore_0
    //   54: iload #4
    //   56: if_icmpge -> 68
    //   59: aload_2
    //   60: iload_0
    //   61: invokevirtual charAt : (I)C
    //   64: istore_1
    //   65: goto -> 23
    //   68: ldc '\\n4QFJ qUZx` ,?y}\m+=mu/owY_\\tbN\\f4'
    //   70: dup
    //   71: astore_2
    //   72: invokevirtual length : ()I
    //   75: istore #4
    //   77: bipush #77
    //   79: istore_1
    //   80: iconst_m1
    //   81: istore_0
    //   82: bipush #57
    //   84: iinc #0, 1
    //   87: aload_2
    //   88: iload_0
    //   89: dup
    //   90: iload_1
    //   91: iadd
    //   92: invokevirtual substring : (II)Ljava/lang/String;
    //   95: iconst_0
    //   96: goto -> 143
    //   99: aload #5
    //   101: swap
    //   102: iload_3
    //   103: iinc #3, 1
    //   106: swap
    //   107: aastore
    //   108: iload_0
    //   109: iload_1
    //   110: iadd
    //   111: dup
    //   112: istore_0
    //   113: iload #4
    //   115: if_icmpge -> 127
    //   118: aload_2
    //   119: iload_0
    //   120: invokevirtual charAt : (I)C
    //   123: istore_1
    //   124: goto -> 82
    //   127: aload #5
    //   129: putstatic burp/Zt5b.a : [Ljava/lang/String;
    //   132: bipush #9
    //   134: anewarray java/lang/String
    //   137: putstatic burp/Zt5b.b : [Ljava/lang/String;
    //   140: goto -> 300
    //   143: dup_x2
    //   144: pop
    //   145: invokevirtual toCharArray : ()[C
    //   148: dup_x1
    //   149: arraylength
    //   150: dup_x2
    //   151: pop
    //   152: iconst_0
    //   153: istore #6
    //   155: dup2_x1
    //   156: pop2
    //   157: dup_x2
    //   158: iconst_1
    //   159: if_icmpgt -> 258
    //   162: dup2
    //   163: swap
    //   164: iload #6
    //   166: dup2_x1
    //   167: caload
    //   168: swap
    //   169: iload #6
    //   171: bipush #7
    //   173: irem
    //   174: tableswitch default -> 240, 0 -> 212, 1 -> 217, 2 -> 222, 3 -> 226, 4 -> 231, 5 -> 236
    //   212: bipush #21
    //   214: goto -> 242
    //   217: bipush #85
    //   219: goto -> 242
    //   222: iconst_3
    //   223: goto -> 242
    //   226: bipush #81
    //   228: goto -> 242
    //   231: bipush #16
    //   233: goto -> 242
    //   236: iconst_4
    //   237: goto -> 242
    //   240: bipush #61
    //   242: ixor
    //   243: ixor
    //   244: i2c
    //   245: castore
    //   246: iinc #6, 1
    //   249: dup
    //   250: ifne -> 258
    //   253: dup2
    //   254: dup_x1
    //   255: goto -> 166
    //   258: dup2_x1
    //   259: pop2
    //   260: dup_x2
    //   261: iload #6
    //   263: if_icmpgt -> 162
    //   266: pop
    //   267: new java/lang/String
    //   270: dup_x1
    //   271: swap
    //   272: invokespecial <init> : ([C)V
    //   275: invokevirtual intern : ()Ljava/lang/String;
    //   278: swap
    //   279: pop
    //   280: swap
    //   281: tableswitch default -> 40, 0 -> 99
    //   300: sipush #-30399
    //   303: sipush #-6906
    //   306: invokestatic a : (II)Ljava/lang/String;
    //   309: putstatic burp/Zt5b.ZV : Ljava/lang/String;
    //   312: new java/math/BigInteger
    //   315: dup
    //   316: sipush #-30394
    //   319: sipush #-25087
    //   322: invokestatic a : (II)Ljava/lang/String;
    //   325: invokespecial <init> : (Ljava/lang/String;)V
    //   328: putstatic burp/Zt5b.Zc : Ljava/lang/Object;
    //   331: return
  }
  
  private static Throwable a(Throwable paramThrowable) {
    return paramThrowable;
  }
  
  private static String a(int paramInt1, int paramInt2) {
    int i = (paramInt1 ^ 0xFFFF8941) & 0xFFFF;
    if (b[i] == null) {
      char[] arrayOfChar = a[i].toCharArray();
      switch (arrayOfChar[0] & 0xFF) {
        case 0:
        
        case 1:
        
        case 2:
        
        case 3:
        
        case 4:
        
        case 5:
        
        case 6:
        
        case 7:
        
        case 8:
        
        case 9:
        
        case 10:
        
        case 11:
        
        case 12:
        
        case 13:
        
        case 14:
        
        case 15:
        
        case 16:
        
        case 17:
        
        case 18:
        
        case 19:
        
        case 20:
        
        case 21:
        
        case 22:
        
        case 23:
        
        case 24:
        
        case 25:
        
        case 26:
        
        case 27:
        
        case 28:
        
        case 29:
        
        case 30:
        
        case 31:
        
        case 32:
        
        case 33:
        
        case 34:
        
        case 35:
        
        case 36:
        
        case 37:
        
        case 38:
        
        case 39:
        
        case 40:
        
        case 41:
        
        case 42:
        
        case 43:
        
        case 44:
        
        case 45:
        
        case 46:
        
        case 47:
        
        case 48:
        
        case 49:
        
        case 50:
        
        case 51:
        
        case 52:
        
        case 53:
        
        case 54:
        
        case 55:
        
        case 56:
        
        case 57:
        
        case 58:
        
        case 59:
        
        case 60:
        
        case 61:
        
        case 62:
        
        case 63:
        
        case 64:
        
        case 65:
        
        case 66:
        
        case 67:
        
        case 68:
        
        case 69:
        
        case 70:
        
        case 71:
        
        case 72:
        
        case 73:
        
        case 74:
        
        case 75:
        
        case 76:
        
        case 77:
        
        case 78:
        
        case 79:
        
        case 80:
        
        case 81:
        
        case 82:
        
        case 83:
        
        case 84:
        
        case 85:
        
        case 86:
        
        case 87:
        
        case 88:
        
        case 89:
        
        case 90:
        
        case 91:
        
        case 92:
        
        case 93:
        
        case 94:
        
        case 95:
        
        case 96:
        
        case 97:
        
        case 98:
        
        case 99:
        
        case 100:
        
        case 101:
        
        case 102:
        
        case 103:
        
        case 104:
        
        case 105:
        
        case 106:
        
        case 107:
        
        case 108:
        
        case 109:
        
        case 110:
        
        case 111:
        
        case 112:
        
        case 113:
        
        case 114:
        
        case 115:
        
        case 116:
        
        case 117:
        
        case 118:
        
        case 119:
        
        case 120:
        
        case 121:
        
        case 122:
        
        case 123:
        
        case 124:
        
        case 125:
        
        case 126:
        
        case 127:
        
        case 128:
        
        case 129:
        
        case 130:
        
        case 131:
        
        case 132:
        
        case 133:
        
        case 134:
        
        case 135:
        
        case 136:
        
        case 137:
        
        case 138:
        
        case 139:
        
        case 140:
        
        case 141:
        
        case 142:
        
        case 143:
        
        case 144:
        
        case 145:
        
        case 146:
        
        case 147:
        
        case 148:
        
        case 149:
        
        case 150:
        
        case 151:
        
        case 152:
        
        case 153:
        
        case 154:
        
        case 155:
        
        case 156:
        
        case 157:
        
        case 158:
        
        case 159:
        
        case 160:
        
        case 161:
        
        case 162:
        
        case 163:
        
        case 164:
        
        case 165:
        
        case 166:
        
        case 167:
        
        case 168:
        
        case 169:
        
        case 170:
        
        case 171:
        
        case 172:
        
        case 173:
        
        case 174:
        
        case 175:
        
        case 176:
        
        case 177:
        
        case 178:
        
        case 179:
        
        case 180:
        
        case 181:
        
        case 182:
        
        case 183:
        
        case 184:
        
        case 185:
        
        case 186:
        
        case 187:
        
        case 188:
        
        case 189:
        
        case 190:
        
        case 191:
        
        case 192:
        
        case 193:
        
        case 194:
        
        case 195:
        
        case 196:
        
        case 197:
        
        case 198:
        
        case 199:
        
        case 200:
        
        case 201:
        
        case 202:
        
        case 203:
        
        case 204:
        
        case 205:
        
        case 206:
        
        case 207:
        
        case 208:
        
        case 209:
        
        case 210:
        
        case 211:
        
        case 212:
        
        case 213:
        
        case 214:
        
        case 215:
        
        case 216:
        
        case 217:
        
        case 218:
        
        case 219:
        
        case 220:
        
        case 221:
        
        case 222:
        
        case 223:
        
        case 224:
        
        case 225:
        
        case 226:
        
        case 227:
        
        case 228:
        
        case 229:
        
        case 230:
        
        case 231:
        
        case 232:
        
        case 233:
        
        case 234:
        
        case 235:
        
        case 236:
        
        case 237:
        
        case 238:
        
        case 239:
        
        case 240:
        
        case 241:
        
        case 242:
        
        case 243:
        
        case 244:
        
        case 245:
        
        case 246:
        
        case 247:
        
        case 248:
        
        case 249:
        
        case 250:
        
        case 251:
        
        case 252:
        
        case 253:
        
        case 254:
        
        default:
          break;
      } 
      char c = '';
      int j = (paramInt2 & 0xFF) - c;
      if (j < 0)
        j += 256; 
      int k = ((paramInt2 & 0xFFFF) >>> 8) - c;
      if (k < 0)
        k += 256; 
      for (byte b = 0; b < arrayOfChar.length; b++) {
        int m = b % 2;
        if (m == 0) {
          arrayOfChar[b] = (char)(arrayOfChar[b] ^ j);
          j = ((j >>> 3 | j << 5) ^ arrayOfChar[b]) & 0xFF;
        } else {
          arrayOfChar[b] = (char)(arrayOfChar[b] ^ k);
          k = ((k >>> 3 | k << 5) ^ arrayOfChar[b]) & 0xFF;
        } 
      } 
      b[i] = (new String(arrayOfChar)).intern();
    } 
    return b[i];
  }
}


/* Location:              C:\Program Files\BurpSuitePro\burpsuite_pro.jar!\burp\Zt5b.class
 * Java compiler version: 21 (65.0)
 * JD-Core Version:       1.1.3
 */