package burp;

import java.math.BigInteger;

class Zt6z extends ClassLoader {
  static String ZL;
  
  static Object Zl;
  
  private static final String[] a;
  
  private static final String[] b;
  
  static void Za(Object paramObject) {
    Zrfa.ZT = a(3833, 24653);
    Zrfa.Zj = new BigInteger(a(3808, 27452));
    boolean bool = Zt2e.ZK();
    try {
      try {
        if (Zrh_.ZU.charAt(Math.abs(((BigInteger)Zscz.ZN).intValue() % 32)) > Zer1.ZV.charAt(Math.abs(((BigInteger)Zk7o.ZO).intValue() % 32))) {
          try {
            Zk5y.ZO(Class.forName(a(3824, 22982)));
            if (bool)
              Zs4g.ZK(Class.forName(a(3822, -7949))); 
          } catch (Throwable throwable) {
            throw a(null);
          } 
          return;
        } 
      } catch (Throwable throwable) {
        throw a(null);
      } 
      Zs4g.ZK(Class.forName(a(3822, -7949)));
    } catch (Throwable throwable) {}
  }
  
  static void Z_(Object[] paramArrayOfObject, Object paramObject) throws Throwable {}
  
  static boolean Zo(Object[] paramArrayOfObject, Object paramObject) throws Throwable {
    // Byte code:
    //   0: invokestatic ZN : ()Z
    //   3: istore_2
    //   4: new java/lang/StringBuilder
    //   7: dup
    //   8: invokespecial <init> : ()V
    //   11: astore_3
    //   12: iconst_0
    //   13: istore #4
    //   15: iload #4
    //   17: bipush #32
    //   19: if_icmpge -> 1355
    //   22: iload #4
    //   24: tableswitch default -> 1348, 0 -> 168, 1 -> 205, 2 -> 242, 3 -> 279, 4 -> 316, 5 -> 353, 6 -> 390, 7 -> 427, 8 -> 464, 9 -> 501, 10 -> 538, 11 -> 575, 12 -> 612, 13 -> 649, 14 -> 686, 15 -> 723, 16 -> 760, 17 -> 797, 18 -> 834, 19 -> 871, 20 -> 908, 21 -> 945, 22 -> 982, 23 -> 1019, 24 -> 1056, 25 -> 1093, 26 -> 1130, 27 -> 1167, 28 -> 1204, 29 -> 1241, 30 -> 1278, 31 -> 1315
    //   168: aload_3
    //   169: getstatic burp/Zst7.Zi : Ljava/lang/String;
    //   172: getstatic burp/Zmyk.Za : Ljava/lang/Object;
    //   175: checkcast java/math/BigInteger
    //   178: invokevirtual intValue : ()I
    //   181: bipush #32
    //   183: irem
    //   184: invokestatic abs : (I)I
    //   187: invokevirtual charAt : (I)C
    //   190: invokevirtual append : (C)Ljava/lang/StringBuilder;
    //   193: pop
    //   194: iload_2
    //   195: ifne -> 1348
    //   198: goto -> 205
    //   201: invokestatic a : (Ljava/lang/Throwable;)Ljava/lang/Throwable;
    //   204: athrow
    //   205: aload_3
    //   206: getstatic burp/Zkql.ZR : Ljava/lang/String;
    //   209: getstatic burp/Zemp.Zr : Ljava/lang/Object;
    //   212: checkcast java/math/BigInteger
    //   215: invokevirtual intValue : ()I
    //   218: bipush #32
    //   220: irem
    //   221: invokestatic abs : (I)I
    //   224: invokevirtual charAt : (I)C
    //   227: invokevirtual append : (C)Ljava/lang/StringBuilder;
    //   230: pop
    //   231: iload_2
    //   232: ifne -> 1348
    //   235: goto -> 242
    //   238: invokestatic a : (Ljava/lang/Throwable;)Ljava/lang/Throwable;
    //   241: athrow
    //   242: aload_3
    //   243: getstatic burp/Zt9f.Zg : Ljava/lang/String;
    //   246: getstatic burp/Zbsz.ZP : Ljava/lang/Object;
    //   249: checkcast java/math/BigInteger
    //   252: invokevirtual intValue : ()I
    //   255: bipush #32
    //   257: irem
    //   258: invokestatic abs : (I)I
    //   261: invokevirtual charAt : (I)C
    //   264: invokevirtual append : (C)Ljava/lang/StringBuilder;
    //   267: pop
    //   268: iload_2
    //   269: ifne -> 1348
    //   272: goto -> 279
    //   275: invokestatic a : (Ljava/lang/Throwable;)Ljava/lang/Throwable;
    //   278: athrow
    //   279: aload_3
    //   280: getstatic burp/Zeqz.ZV : Ljava/lang/String;
    //   283: getstatic burp/Zr17.ZR : Ljava/lang/Object;
    //   286: checkcast java/math/BigInteger
    //   289: invokevirtual intValue : ()I
    //   292: bipush #32
    //   294: irem
    //   295: invokestatic abs : (I)I
    //   298: invokevirtual charAt : (I)C
    //   301: invokevirtual append : (C)Ljava/lang/StringBuilder;
    //   304: pop
    //   305: iload_2
    //   306: ifne -> 1348
    //   309: goto -> 316
    //   312: invokestatic a : (Ljava/lang/Throwable;)Ljava/lang/Throwable;
    //   315: athrow
    //   316: aload_3
    //   317: getstatic burp/Zxp5.ZO : Ljava/lang/String;
    //   320: getstatic burp/Zmui.Zz : Ljava/lang/Object;
    //   323: checkcast java/math/BigInteger
    //   326: invokevirtual intValue : ()I
    //   329: bipush #32
    //   331: irem
    //   332: invokestatic abs : (I)I
    //   335: invokevirtual charAt : (I)C
    //   338: invokevirtual append : (C)Ljava/lang/StringBuilder;
    //   341: pop
    //   342: iload_2
    //   343: ifne -> 1348
    //   346: goto -> 353
    //   349: invokestatic a : (Ljava/lang/Throwable;)Ljava/lang/Throwable;
    //   352: athrow
    //   353: aload_3
    //   354: getstatic burp/Zkhf.Zb : Ljava/lang/String;
    //   357: getstatic burp/Zxxh.Za : Ljava/lang/Object;
    //   360: checkcast java/math/BigInteger
    //   363: invokevirtual intValue : ()I
    //   366: bipush #32
    //   368: irem
    //   369: invokestatic abs : (I)I
    //   372: invokevirtual charAt : (I)C
    //   375: invokevirtual append : (C)Ljava/lang/StringBuilder;
    //   378: pop
    //   379: iload_2
    //   380: ifne -> 1348
    //   383: goto -> 390
    //   386: invokestatic a : (Ljava/lang/Throwable;)Ljava/lang/Throwable;
    //   389: athrow
    //   390: aload_3
    //   391: getstatic burp/Znu.ZF : Ljava/lang/String;
    //   394: getstatic burp/Zrm6.Z_ : Ljava/lang/Object;
    //   397: checkcast java/math/BigInteger
    //   400: invokevirtual intValue : ()I
    //   403: bipush #32
    //   405: irem
    //   406: invokestatic abs : (I)I
    //   409: invokevirtual charAt : (I)C
    //   412: invokevirtual append : (C)Ljava/lang/StringBuilder;
    //   415: pop
    //   416: iload_2
    //   417: ifne -> 1348
    //   420: goto -> 427
    //   423: invokestatic a : (Ljava/lang/Throwable;)Ljava/lang/Throwable;
    //   426: athrow
    //   427: aload_3
    //   428: getstatic burp/Zzgb.ZT : Ljava/lang/String;
    //   431: getstatic burp/Zmdi.Zw : Ljava/lang/Object;
    //   434: checkcast java/math/BigInteger
    //   437: invokevirtual intValue : ()I
    //   440: bipush #32
    //   442: irem
    //   443: invokestatic abs : (I)I
    //   446: invokevirtual charAt : (I)C
    //   449: invokevirtual append : (C)Ljava/lang/StringBuilder;
    //   452: pop
    //   453: iload_2
    //   454: ifne -> 1348
    //   457: goto -> 464
    //   460: invokestatic a : (Ljava/lang/Throwable;)Ljava/lang/Throwable;
    //   463: athrow
    //   464: aload_3
    //   465: getstatic burp/Zsdl.ZJ : Ljava/lang/String;
    //   468: getstatic burp/Zezi.ZQ : Ljava/lang/Object;
    //   471: checkcast java/math/BigInteger
    //   474: invokevirtual intValue : ()I
    //   477: bipush #32
    //   479: irem
    //   480: invokestatic abs : (I)I
    //   483: invokevirtual charAt : (I)C
    //   486: invokevirtual append : (C)Ljava/lang/StringBuilder;
    //   489: pop
    //   490: iload_2
    //   491: ifne -> 1348
    //   494: goto -> 501
    //   497: invokestatic a : (Ljava/lang/Throwable;)Ljava/lang/Throwable;
    //   500: athrow
    //   501: aload_3
    //   502: getstatic burp/Zezi.Ze : Ljava/lang/String;
    //   505: getstatic burp/Zejz.ZF : Ljava/lang/Object;
    //   508: checkcast java/math/BigInteger
    //   511: invokevirtual intValue : ()I
    //   514: bipush #32
    //   516: irem
    //   517: invokestatic abs : (I)I
    //   520: invokevirtual charAt : (I)C
    //   523: invokevirtual append : (C)Ljava/lang/StringBuilder;
    //   526: pop
    //   527: iload_2
    //   528: ifne -> 1348
    //   531: goto -> 538
    //   534: invokestatic a : (Ljava/lang/Throwable;)Ljava/lang/Throwable;
    //   537: athrow
    //   538: aload_3
    //   539: getstatic burp/Zmui.ZY : Ljava/lang/String;
    //   542: getstatic burp/Zm63.ZT : Ljava/lang/Object;
    //   545: checkcast java/math/BigInteger
    //   548: invokevirtual intValue : ()I
    //   551: bipush #32
    //   553: irem
    //   554: invokestatic abs : (I)I
    //   557: invokevirtual charAt : (I)C
    //   560: invokevirtual append : (C)Ljava/lang/StringBuilder;
    //   563: pop
    //   564: iload_2
    //   565: ifne -> 1348
    //   568: goto -> 575
    //   571: invokestatic a : (Ljava/lang/Throwable;)Ljava/lang/Throwable;
    //   574: athrow
    //   575: aload_3
    //   576: getstatic burp/Zsbv.Zr : Ljava/lang/String;
    //   579: getstatic burp/Zrjq.ZU : Ljava/lang/Object;
    //   582: checkcast java/math/BigInteger
    //   585: invokevirtual intValue : ()I
    //   588: bipush #32
    //   590: irem
    //   591: invokestatic abs : (I)I
    //   594: invokevirtual charAt : (I)C
    //   597: invokevirtual append : (C)Ljava/lang/StringBuilder;
    //   600: pop
    //   601: iload_2
    //   602: ifne -> 1348
    //   605: goto -> 612
    //   608: invokestatic a : (Ljava/lang/Throwable;)Ljava/lang/Throwable;
    //   611: athrow
    //   612: aload_3
    //   613: getstatic burp/Zbsz.Zu : Ljava/lang/String;
    //   616: getstatic burp/Zkjj.Zh : Ljava/lang/Object;
    //   619: checkcast java/math/BigInteger
    //   622: invokevirtual intValue : ()I
    //   625: bipush #32
    //   627: irem
    //   628: invokestatic abs : (I)I
    //   631: invokevirtual charAt : (I)C
    //   634: invokevirtual append : (C)Ljava/lang/StringBuilder;
    //   637: pop
    //   638: iload_2
    //   639: ifne -> 1348
    //   642: goto -> 649
    //   645: invokestatic a : (Ljava/lang/Throwable;)Ljava/lang/Throwable;
    //   648: athrow
    //   649: aload_3
    //   650: getstatic burp/Zmpx.ZC : Ljava/lang/String;
    //   653: getstatic burp/Zkdq.ZG : Ljava/lang/Object;
    //   656: checkcast java/math/BigInteger
    //   659: invokevirtual intValue : ()I
    //   662: bipush #32
    //   664: irem
    //   665: invokestatic abs : (I)I
    //   668: invokevirtual charAt : (I)C
    //   671: invokevirtual append : (C)Ljava/lang/StringBuilder;
    //   674: pop
    //   675: iload_2
    //   676: ifne -> 1348
    //   679: goto -> 686
    //   682: invokestatic a : (Ljava/lang/Throwable;)Ljava/lang/Throwable;
    //   685: athrow
    //   686: aload_3
    //   687: getstatic burp/Zzac.ZE : Ljava/lang/String;
    //   690: getstatic burp/Zk8f.ZG : Ljava/lang/Object;
    //   693: checkcast java/math/BigInteger
    //   696: invokevirtual intValue : ()I
    //   699: bipush #32
    //   701: irem
    //   702: invokestatic abs : (I)I
    //   705: invokevirtual charAt : (I)C
    //   708: invokevirtual append : (C)Ljava/lang/StringBuilder;
    //   711: pop
    //   712: iload_2
    //   713: ifne -> 1348
    //   716: goto -> 723
    //   719: invokestatic a : (Ljava/lang/Throwable;)Ljava/lang/Throwable;
    //   722: athrow
    //   723: aload_3
    //   724: getstatic burp/Zrt3.Zu : Ljava/lang/String;
    //   727: getstatic burp/Zmdi.Zw : Ljava/lang/Object;
    //   730: checkcast java/math/BigInteger
    //   733: invokevirtual intValue : ()I
    //   736: bipush #32
    //   738: irem
    //   739: invokestatic abs : (I)I
    //   742: invokevirtual charAt : (I)C
    //   745: invokevirtual append : (C)Ljava/lang/StringBuilder;
    //   748: pop
    //   749: iload_2
    //   750: ifne -> 1348
    //   753: goto -> 760
    //   756: invokestatic a : (Ljava/lang/Throwable;)Ljava/lang/Throwable;
    //   759: athrow
    //   760: aload_3
    //   761: getstatic burp/Zegj.ZS : Ljava/lang/String;
    //   764: getstatic burp/Zrqe.ZX : Ljava/lang/Object;
    //   767: checkcast java/math/BigInteger
    //   770: invokevirtual intValue : ()I
    //   773: bipush #32
    //   775: irem
    //   776: invokestatic abs : (I)I
    //   779: invokevirtual charAt : (I)C
    //   782: invokevirtual append : (C)Ljava/lang/StringBuilder;
    //   785: pop
    //   786: iload_2
    //   787: ifne -> 1348
    //   790: goto -> 797
    //   793: invokestatic a : (Ljava/lang/Throwable;)Ljava/lang/Throwable;
    //   796: athrow
    //   797: aload_3
    //   798: getstatic burp/Zld9.Zx : Ljava/lang/String;
    //   801: getstatic burp/Zrov.Zk : Ljava/lang/Object;
    //   804: checkcast java/math/BigInteger
    //   807: invokevirtual intValue : ()I
    //   810: bipush #32
    //   812: irem
    //   813: invokestatic abs : (I)I
    //   816: invokevirtual charAt : (I)C
    //   819: invokevirtual append : (C)Ljava/lang/StringBuilder;
    //   822: pop
    //   823: iload_2
    //   824: ifne -> 1348
    //   827: goto -> 834
    //   830: invokestatic a : (Ljava/lang/Throwable;)Ljava/lang/Throwable;
    //   833: athrow
    //   834: aload_3
    //   835: getstatic burp/Zxwf.ZX : Ljava/lang/String;
    //   838: getstatic burp/Zs_m.Z_ : Ljava/lang/Object;
    //   841: checkcast java/math/BigInteger
    //   844: invokevirtual intValue : ()I
    //   847: bipush #32
    //   849: irem
    //   850: invokestatic abs : (I)I
    //   853: invokevirtual charAt : (I)C
    //   856: invokevirtual append : (C)Ljava/lang/StringBuilder;
    //   859: pop
    //   860: iload_2
    //   861: ifne -> 1348
    //   864: goto -> 871
    //   867: invokestatic a : (Ljava/lang/Throwable;)Ljava/lang/Throwable;
    //   870: athrow
    //   871: aload_3
    //   872: getstatic burp/Zgei.Zl : Ljava/lang/String;
    //   875: getstatic burp/Zrqe.ZX : Ljava/lang/Object;
    //   878: checkcast java/math/BigInteger
    //   881: invokevirtual intValue : ()I
    //   884: bipush #32
    //   886: irem
    //   887: invokestatic abs : (I)I
    //   890: invokevirtual charAt : (I)C
    //   893: invokevirtual append : (C)Ljava/lang/StringBuilder;
    //   896: pop
    //   897: iload_2
    //   898: ifne -> 1348
    //   901: goto -> 908
    //   904: invokestatic a : (Ljava/lang/Throwable;)Ljava/lang/Throwable;
    //   907: athrow
    //   908: aload_3
    //   909: getstatic burp/Zl2t.Zg : Ljava/lang/String;
    //   912: getstatic burp/Zzi_.Zf : Ljava/lang/Object;
    //   915: checkcast java/math/BigInteger
    //   918: invokevirtual intValue : ()I
    //   921: bipush #32
    //   923: irem
    //   924: invokestatic abs : (I)I
    //   927: invokevirtual charAt : (I)C
    //   930: invokevirtual append : (C)Ljava/lang/StringBuilder;
    //   933: pop
    //   934: iload_2
    //   935: ifne -> 1348
    //   938: goto -> 945
    //   941: invokestatic a : (Ljava/lang/Throwable;)Ljava/lang/Throwable;
    //   944: athrow
    //   945: aload_3
    //   946: getstatic burp/Zql.Zf : Ljava/lang/String;
    //   949: getstatic burp/Zg7u.Zh : Ljava/lang/Object;
    //   952: checkcast java/math/BigInteger
    //   955: invokevirtual intValue : ()I
    //   958: bipush #32
    //   960: irem
    //   961: invokestatic abs : (I)I
    //   964: invokevirtual charAt : (I)C
    //   967: invokevirtual append : (C)Ljava/lang/StringBuilder;
    //   970: pop
    //   971: iload_2
    //   972: ifne -> 1348
    //   975: goto -> 982
    //   978: invokestatic a : (Ljava/lang/Throwable;)Ljava/lang/Throwable;
    //   981: athrow
    //   982: aload_3
    //   983: getstatic burp/Zsjc.ZO : Ljava/lang/String;
    //   986: getstatic burp/Zeub.ZD : Ljava/lang/Object;
    //   989: checkcast java/math/BigInteger
    //   992: invokevirtual intValue : ()I
    //   995: bipush #32
    //   997: irem
    //   998: invokestatic abs : (I)I
    //   1001: invokevirtual charAt : (I)C
    //   1004: invokevirtual append : (C)Ljava/lang/StringBuilder;
    //   1007: pop
    //   1008: iload_2
    //   1009: ifne -> 1348
    //   1012: goto -> 1019
    //   1015: invokestatic a : (Ljava/lang/Throwable;)Ljava/lang/Throwable;
    //   1018: athrow
    //   1019: aload_3
    //   1020: getstatic burp/Zst7.Zi : Ljava/lang/String;
    //   1023: getstatic burp/Zssc.Zr : Ljava/lang/Object;
    //   1026: checkcast java/math/BigInteger
    //   1029: invokevirtual intValue : ()I
    //   1032: bipush #32
    //   1034: irem
    //   1035: invokestatic abs : (I)I
    //   1038: invokevirtual charAt : (I)C
    //   1041: invokevirtual append : (C)Ljava/lang/StringBuilder;
    //   1044: pop
    //   1045: iload_2
    //   1046: ifne -> 1348
    //   1049: goto -> 1056
    //   1052: invokestatic a : (Ljava/lang/Throwable;)Ljava/lang/Throwable;
    //   1055: athrow
    //   1056: aload_3
    //   1057: getstatic burp/Zb4d.ZS : Ljava/lang/String;
    //   1060: getstatic burp/Zewr.Zw : Ljava/lang/Object;
    //   1063: checkcast java/math/BigInteger
    //   1066: invokevirtual intValue : ()I
    //   1069: bipush #32
    //   1071: irem
    //   1072: invokestatic abs : (I)I
    //   1075: invokevirtual charAt : (I)C
    //   1078: invokevirtual append : (C)Ljava/lang/StringBuilder;
    //   1081: pop
    //   1082: iload_2
    //   1083: ifne -> 1348
    //   1086: goto -> 1093
    //   1089: invokestatic a : (Ljava/lang/Throwable;)Ljava/lang/Throwable;
    //   1092: athrow
    //   1093: aload_3
    //   1094: getstatic burp/Ztgv.ZC : Ljava/lang/String;
    //   1097: getstatic burp/Zenr.ZA : Ljava/lang/Object;
    //   1100: checkcast java/math/BigInteger
    //   1103: invokevirtual intValue : ()I
    //   1106: bipush #32
    //   1108: irem
    //   1109: invokestatic abs : (I)I
    //   1112: invokevirtual charAt : (I)C
    //   1115: invokevirtual append : (C)Ljava/lang/StringBuilder;
    //   1118: pop
    //   1119: iload_2
    //   1120: ifne -> 1348
    //   1123: goto -> 1130
    //   1126: invokestatic a : (Ljava/lang/Throwable;)Ljava/lang/Throwable;
    //   1129: athrow
    //   1130: aload_3
    //   1131: getstatic burp/Znu.ZF : Ljava/lang/String;
    //   1134: getstatic burp/Zmlr.Zh : Ljava/lang/Object;
    //   1137: checkcast java/math/BigInteger
    //   1140: invokevirtual intValue : ()I
    //   1143: bipush #32
    //   1145: irem
    //   1146: invokestatic abs : (I)I
    //   1149: invokevirtual charAt : (I)C
    //   1152: invokevirtual append : (C)Ljava/lang/StringBuilder;
    //   1155: pop
    //   1156: iload_2
    //   1157: ifne -> 1348
    //   1160: goto -> 1167
    //   1163: invokestatic a : (Ljava/lang/Throwable;)Ljava/lang/Throwable;
    //   1166: athrow
    //   1167: aload_3
    //   1168: getstatic burp/Zbss.ZV : Ljava/lang/String;
    //   1171: getstatic burp/Zgcg.Zi : Ljava/lang/Object;
    //   1174: checkcast java/math/BigInteger
    //   1177: invokevirtual intValue : ()I
    //   1180: bipush #32
    //   1182: irem
    //   1183: invokestatic abs : (I)I
    //   1186: invokevirtual charAt : (I)C
    //   1189: invokevirtual append : (C)Ljava/lang/StringBuilder;
    //   1192: pop
    //   1193: iload_2
    //   1194: ifne -> 1348
    //   1197: goto -> 1204
    //   1200: invokestatic a : (Ljava/lang/Throwable;)Ljava/lang/Throwable;
    //   1203: athrow
    //   1204: aload_3
    //   1205: getstatic burp/Zz41.Zc : Ljava/lang/String;
    //   1208: getstatic burp/Zkjj.Zh : Ljava/lang/Object;
    //   1211: checkcast java/math/BigInteger
    //   1214: invokevirtual intValue : ()I
    //   1217: bipush #32
    //   1219: irem
    //   1220: invokestatic abs : (I)I
    //   1223: invokevirtual charAt : (I)C
    //   1226: invokevirtual append : (C)Ljava/lang/StringBuilder;
    //   1229: pop
    //   1230: iload_2
    //   1231: ifne -> 1348
    //   1234: goto -> 1241
    //   1237: invokestatic a : (Ljava/lang/Throwable;)Ljava/lang/Throwable;
    //   1240: athrow
    //   1241: aload_3
    //   1242: getstatic burp/Zrgo.Z_ : Ljava/lang/String;
    //   1245: getstatic burp/Zkdx.Zn : Ljava/lang/Object;
    //   1248: checkcast java/math/BigInteger
    //   1251: invokevirtual intValue : ()I
    //   1254: bipush #32
    //   1256: irem
    //   1257: invokestatic abs : (I)I
    //   1260: invokevirtual charAt : (I)C
    //   1263: invokevirtual append : (C)Ljava/lang/StringBuilder;
    //   1266: pop
    //   1267: iload_2
    //   1268: ifne -> 1348
    //   1271: goto -> 1278
    //   1274: invokestatic a : (Ljava/lang/Throwable;)Ljava/lang/Throwable;
    //   1277: athrow
    //   1278: aload_3
    //   1279: getstatic burp/Zmh3.Zy : Ljava/lang/String;
    //   1282: getstatic burp/Zrn4.Zq : Ljava/lang/Object;
    //   1285: checkcast java/math/BigInteger
    //   1288: invokevirtual intValue : ()I
    //   1291: bipush #32
    //   1293: irem
    //   1294: invokestatic abs : (I)I
    //   1297: invokevirtual charAt : (I)C
    //   1300: invokevirtual append : (C)Ljava/lang/StringBuilder;
    //   1303: pop
    //   1304: iload_2
    //   1305: ifne -> 1348
    //   1308: goto -> 1315
    //   1311: invokestatic a : (Ljava/lang/Throwable;)Ljava/lang/Throwable;
    //   1314: athrow
    //   1315: aload_3
    //   1316: getstatic burp/Zmc_.Zb : Ljava/lang/String;
    //   1319: getstatic burp/Zg61.Zp : Ljava/lang/Object;
    //   1322: checkcast java/math/BigInteger
    //   1325: invokevirtual intValue : ()I
    //   1328: bipush #32
    //   1330: irem
    //   1331: invokestatic abs : (I)I
    //   1334: invokevirtual charAt : (I)C
    //   1337: invokevirtual append : (C)Ljava/lang/StringBuilder;
    //   1340: pop
    //   1341: goto -> 1348
    //   1344: invokestatic a : (Ljava/lang/Throwable;)Ljava/lang/Throwable;
    //   1347: athrow
    //   1348: iinc #4, 1
    //   1351: iload_2
    //   1352: ifne -> 15
    //   1355: aload_3
    //   1356: invokevirtual toString : ()Ljava/lang/String;
    //   1359: putstatic burp/Zxp1.Zg : Ljava/lang/String;
    //   1362: getstatic burp/Zrkw.ZV : Ljava/lang/Object;
    //   1365: checkcast java/math/BigInteger
    //   1368: getstatic burp/Zrip.ZB : Ljava/lang/Object;
    //   1371: checkcast java/math/BigInteger
    //   1374: invokevirtual add : (Ljava/math/BigInteger;)Ljava/math/BigInteger;
    //   1377: putstatic burp/Zld9.ZF : Ljava/lang/Object;
    //   1380: getstatic burp/Zzk_.Zx : Ljava/lang/Object;
    //   1383: checkcast java/math/BigInteger
    //   1386: invokevirtual toByteArray : ()[B
    //   1389: astore #4
    //   1391: bipush #32
    //   1393: newarray int
    //   1395: dup
    //   1396: iconst_0
    //   1397: ldc 876216579
    //   1399: iastore
    //   1400: dup
    //   1401: iconst_1
    //   1402: ldc 455999525
    //   1404: iastore
    //   1405: dup
    //   1406: iconst_2
    //   1407: ldc 1043334948
    //   1409: iastore
    //   1410: dup
    //   1411: iconst_3
    //   1412: ldc 439222784
    //   1414: iastore
    //   1415: dup
    //   1416: iconst_4
    //   1417: ldc 372376604
    //   1419: iastore
    //   1420: dup
    //   1421: iconst_5
    //   1422: ldc 707731490
    //   1424: iastore
    //   1425: dup
    //   1426: bipush #6
    //   1428: ldc 389426184
    //   1430: iastore
    //   1431: dup
    //   1432: bipush #7
    //   1434: ldc 973875457
    //   1436: iastore
    //   1437: dup
    //   1438: bipush #8
    //   1440: ldc 389160971
    //   1442: iastore
    //   1443: dup
    //   1444: bipush #9
    //   1446: ldc 907870729
    //   1448: iastore
    //   1449: dup
    //   1450: bipush #10
    //   1452: ldc 121057538
    //   1454: iastore
    //   1455: dup
    //   1456: bipush #11
    //   1458: ldc 840500228
    //   1460: iastore
    //   1461: dup
    //   1462: bipush #12
    //   1464: ldc 254150144
    //   1466: iastore
    //   1467: dup
    //   1468: bipush #13
    //   1470: ldc 924386310
    //   1472: iastore
    //   1473: dup
    //   1474: bipush #14
    //   1476: ldc 187632156
    //   1478: iastore
    //   1479: dup
    //   1480: bipush #15
    //   1482: ldc 874189824
    //   1484: iastore
    //   1485: dup
    //   1486: bipush #16
    //   1488: ldc 655302664
    //   1490: iastore
    //   1491: dup
    //   1492: bipush #17
    //   1494: ldc 890966315
    //   1496: iastore
    //   1497: dup
    //   1498: bipush #18
    //   1500: ldc 722417666
    //   1502: iastore
    //   1503: dup
    //   1504: bipush #19
    //   1506: ldc 1026621720
    //   1508: iastore
    //   1509: dup
    //   1510: bipush #20
    //   1512: ldc 957157408
    //   1514: iastore
    //   1515: dup
    //   1516: bipush #21
    //   1518: ldc 892536332
    //   1520: iastore
    //   1521: dup
    //   1522: bipush #22
    //   1524: ldc 689771012
    //   1526: iastore
    //   1527: dup
    //   1528: bipush #23
    //   1530: ldc 221709344
    //   1532: iastore
    //   1533: dup
    //   1534: bipush #24
    //   1536: ldc 940377620
    //   1538: iastore
    //   1539: dup
    //   1540: bipush #25
    //   1542: ldc 255209728
    //   1544: iastore
    //   1545: dup
    //   1546: bipush #26
    //   1548: ldc 1010368540
    //   1550: iastore
    //   1551: dup
    //   1552: bipush #27
    //   1554: ldc 220604441
    //   1556: iastore
    //   1557: dup
    //   1558: bipush #28
    //   1560: ldc 1008414755
    //   1562: iastore
    //   1563: dup
    //   1564: bipush #29
    //   1566: ldc 187049985
    //   1568: iastore
    //   1569: dup
    //   1570: bipush #30
    //   1572: ldc 943331329
    //   1574: iastore
    //   1575: dup
    //   1576: bipush #31
    //   1578: ldc 170788368
    //   1580: iastore
    //   1581: astore #6
    //   1583: bipush #64
    //   1585: newarray int
    //   1587: dup
    //   1588: iconst_0
    //   1589: ldc 16843776
    //   1591: iastore
    //   1592: dup
    //   1593: iconst_1
    //   1594: iconst_0
    //   1595: iastore
    //   1596: dup
    //   1597: iconst_2
    //   1598: ldc 65536
    //   1600: iastore
    //   1601: dup
    //   1602: iconst_3
    //   1603: ldc 16843780
    //   1605: iastore
    //   1606: dup
    //   1607: iconst_4
    //   1608: ldc 16842756
    //   1610: iastore
    //   1611: dup
    //   1612: iconst_5
    //   1613: ldc 66564
    //   1615: iastore
    //   1616: dup
    //   1617: bipush #6
    //   1619: iconst_4
    //   1620: iastore
    //   1621: dup
    //   1622: bipush #7
    //   1624: ldc 65536
    //   1626: iastore
    //   1627: dup
    //   1628: bipush #8
    //   1630: sipush #1024
    //   1633: iastore
    //   1634: dup
    //   1635: bipush #9
    //   1637: ldc 16843776
    //   1639: iastore
    //   1640: dup
    //   1641: bipush #10
    //   1643: ldc 16843780
    //   1645: iastore
    //   1646: dup
    //   1647: bipush #11
    //   1649: sipush #1024
    //   1652: iastore
    //   1653: dup
    //   1654: bipush #12
    //   1656: ldc 16778244
    //   1658: iastore
    //   1659: dup
    //   1660: bipush #13
    //   1662: ldc 16842756
    //   1664: iastore
    //   1665: dup
    //   1666: bipush #14
    //   1668: ldc 16777216
    //   1670: iastore
    //   1671: dup
    //   1672: bipush #15
    //   1674: iconst_4
    //   1675: iastore
    //   1676: dup
    //   1677: bipush #16
    //   1679: sipush #1028
    //   1682: iastore
    //   1683: dup
    //   1684: bipush #17
    //   1686: ldc 16778240
    //   1688: iastore
    //   1689: dup
    //   1690: bipush #18
    //   1692: ldc 16778240
    //   1694: iastore
    //   1695: dup
    //   1696: bipush #19
    //   1698: ldc 66560
    //   1700: iastore
    //   1701: dup
    //   1702: bipush #20
    //   1704: ldc 66560
    //   1706: iastore
    //   1707: dup
    //   1708: bipush #21
    //   1710: ldc 16842752
    //   1712: iastore
    //   1713: dup
    //   1714: bipush #22
    //   1716: ldc 16842752
    //   1718: iastore
    //   1719: dup
    //   1720: bipush #23
    //   1722: ldc 16778244
    //   1724: iastore
    //   1725: dup
    //   1726: bipush #24
    //   1728: ldc 65540
    //   1730: iastore
    //   1731: dup
    //   1732: bipush #25
    //   1734: ldc 16777220
    //   1736: iastore
    //   1737: dup
    //   1738: bipush #26
    //   1740: ldc 16777220
    //   1742: iastore
    //   1743: dup
    //   1744: bipush #27
    //   1746: ldc 65540
    //   1748: iastore
    //   1749: dup
    //   1750: bipush #28
    //   1752: iconst_0
    //   1753: iastore
    //   1754: dup
    //   1755: bipush #29
    //   1757: sipush #1028
    //   1760: iastore
    //   1761: dup
    //   1762: bipush #30
    //   1764: ldc 66564
    //   1766: iastore
    //   1767: dup
    //   1768: bipush #31
    //   1770: ldc 16777216
    //   1772: iastore
    //   1773: dup
    //   1774: bipush #32
    //   1776: ldc 65536
    //   1778: iastore
    //   1779: dup
    //   1780: bipush #33
    //   1782: ldc 16843780
    //   1784: iastore
    //   1785: dup
    //   1786: bipush #34
    //   1788: iconst_4
    //   1789: iastore
    //   1790: dup
    //   1791: bipush #35
    //   1793: ldc 16842752
    //   1795: iastore
    //   1796: dup
    //   1797: bipush #36
    //   1799: ldc 16843776
    //   1801: iastore
    //   1802: dup
    //   1803: bipush #37
    //   1805: ldc 16777216
    //   1807: iastore
    //   1808: dup
    //   1809: bipush #38
    //   1811: ldc 16777216
    //   1813: iastore
    //   1814: dup
    //   1815: bipush #39
    //   1817: sipush #1024
    //   1820: iastore
    //   1821: dup
    //   1822: bipush #40
    //   1824: ldc 16842756
    //   1826: iastore
    //   1827: dup
    //   1828: bipush #41
    //   1830: ldc 65536
    //   1832: iastore
    //   1833: dup
    //   1834: bipush #42
    //   1836: ldc 66560
    //   1838: iastore
    //   1839: dup
    //   1840: bipush #43
    //   1842: ldc 16777220
    //   1844: iastore
    //   1845: dup
    //   1846: bipush #44
    //   1848: sipush #1024
    //   1851: iastore
    //   1852: dup
    //   1853: bipush #45
    //   1855: iconst_4
    //   1856: iastore
    //   1857: dup
    //   1858: bipush #46
    //   1860: ldc 16778244
    //   1862: iastore
    //   1863: dup
    //   1864: bipush #47
    //   1866: ldc 66564
    //   1868: iastore
    //   1869: dup
    //   1870: bipush #48
    //   1872: ldc 16843780
    //   1874: iastore
    //   1875: dup
    //   1876: bipush #49
    //   1878: ldc 65540
    //   1880: iastore
    //   1881: dup
    //   1882: bipush #50
    //   1884: ldc 16842752
    //   1886: iastore
    //   1887: dup
    //   1888: bipush #51
    //   1890: ldc 16778244
    //   1892: iastore
    //   1893: dup
    //   1894: bipush #52
    //   1896: ldc 16777220
    //   1898: iastore
    //   1899: dup
    //   1900: bipush #53
    //   1902: sipush #1028
    //   1905: iastore
    //   1906: dup
    //   1907: bipush #54
    //   1909: ldc 66564
    //   1911: iastore
    //   1912: dup
    //   1913: bipush #55
    //   1915: ldc 16843776
    //   1917: iastore
    //   1918: dup
    //   1919: bipush #56
    //   1921: sipush #1028
    //   1924: iastore
    //   1925: dup
    //   1926: bipush #57
    //   1928: ldc 16778240
    //   1930: iastore
    //   1931: dup
    //   1932: bipush #58
    //   1934: ldc 16778240
    //   1936: iastore
    //   1937: dup
    //   1938: bipush #59
    //   1940: iconst_0
    //   1941: iastore
    //   1942: dup
    //   1943: bipush #60
    //   1945: ldc 65540
    //   1947: iastore
    //   1948: dup
    //   1949: bipush #61
    //   1951: ldc 66560
    //   1953: iastore
    //   1954: dup
    //   1955: bipush #62
    //   1957: iconst_0
    //   1958: iastore
    //   1959: dup
    //   1960: bipush #63
    //   1962: ldc 16842756
    //   1964: iastore
    //   1965: astore #7
    //   1967: bipush #64
    //   1969: newarray int
    //   1971: dup
    //   1972: iconst_0
    //   1973: ldc -2146402272
    //   1975: iastore
    //   1976: dup
    //   1977: iconst_1
    //   1978: ldc -2147450880
    //   1980: iastore
    //   1981: dup
    //   1982: iconst_2
    //   1983: ldc 32768
    //   1985: iastore
    //   1986: dup
    //   1987: iconst_3
    //   1988: ldc 1081376
    //   1990: iastore
    //   1991: dup
    //   1992: iconst_4
    //   1993: ldc 1048576
    //   1995: iastore
    //   1996: dup
    //   1997: iconst_5
    //   1998: bipush #32
    //   2000: iastore
    //   2001: dup
    //   2002: bipush #6
    //   2004: ldc -2146435040
    //   2006: iastore
    //   2007: dup
    //   2008: bipush #7
    //   2010: ldc -2147450848
    //   2012: iastore
    //   2013: dup
    //   2014: bipush #8
    //   2016: ldc -2147483616
    //   2018: iastore
    //   2019: dup
    //   2020: bipush #9
    //   2022: ldc -2146402272
    //   2024: iastore
    //   2025: dup
    //   2026: bipush #10
    //   2028: ldc -2146402304
    //   2030: iastore
    //   2031: dup
    //   2032: bipush #11
    //   2034: ldc -2147483648
    //   2036: iastore
    //   2037: dup
    //   2038: bipush #12
    //   2040: ldc -2147450880
    //   2042: iastore
    //   2043: dup
    //   2044: bipush #13
    //   2046: ldc 1048576
    //   2048: iastore
    //   2049: dup
    //   2050: bipush #14
    //   2052: bipush #32
    //   2054: iastore
    //   2055: dup
    //   2056: bipush #15
    //   2058: ldc -2146435040
    //   2060: iastore
    //   2061: dup
    //   2062: bipush #16
    //   2064: ldc 1081344
    //   2066: iastore
    //   2067: dup
    //   2068: bipush #17
    //   2070: ldc 1048608
    //   2072: iastore
    //   2073: dup
    //   2074: bipush #18
    //   2076: ldc -2147450848
    //   2078: iastore
    //   2079: dup
    //   2080: bipush #19
    //   2082: iconst_0
    //   2083: iastore
    //   2084: dup
    //   2085: bipush #20
    //   2087: ldc -2147483648
    //   2089: iastore
    //   2090: dup
    //   2091: bipush #21
    //   2093: ldc 32768
    //   2095: iastore
    //   2096: dup
    //   2097: bipush #22
    //   2099: ldc 1081376
    //   2101: iastore
    //   2102: dup
    //   2103: bipush #23
    //   2105: ldc -2146435072
    //   2107: iastore
    //   2108: dup
    //   2109: bipush #24
    //   2111: ldc 1048608
    //   2113: iastore
    //   2114: dup
    //   2115: bipush #25
    //   2117: ldc -2147483616
    //   2119: iastore
    //   2120: dup
    //   2121: bipush #26
    //   2123: iconst_0
    //   2124: iastore
    //   2125: dup
    //   2126: bipush #27
    //   2128: ldc 1081344
    //   2130: iastore
    //   2131: dup
    //   2132: bipush #28
    //   2134: ldc 32800
    //   2136: iastore
    //   2137: dup
    //   2138: bipush #29
    //   2140: ldc -2146402304
    //   2142: iastore
    //   2143: dup
    //   2144: bipush #30
    //   2146: ldc -2146435072
    //   2148: iastore
    //   2149: dup
    //   2150: bipush #31
    //   2152: ldc 32800
    //   2154: iastore
    //   2155: dup
    //   2156: bipush #32
    //   2158: iconst_0
    //   2159: iastore
    //   2160: dup
    //   2161: bipush #33
    //   2163: ldc 1081376
    //   2165: iastore
    //   2166: dup
    //   2167: bipush #34
    //   2169: ldc -2146435040
    //   2171: iastore
    //   2172: dup
    //   2173: bipush #35
    //   2175: ldc 1048576
    //   2177: iastore
    //   2178: dup
    //   2179: bipush #36
    //   2181: ldc -2147450848
    //   2183: iastore
    //   2184: dup
    //   2185: bipush #37
    //   2187: ldc -2146435072
    //   2189: iastore
    //   2190: dup
    //   2191: bipush #38
    //   2193: ldc -2146402304
    //   2195: iastore
    //   2196: dup
    //   2197: bipush #39
    //   2199: ldc 32768
    //   2201: iastore
    //   2202: dup
    //   2203: bipush #40
    //   2205: ldc -2146435072
    //   2207: iastore
    //   2208: dup
    //   2209: bipush #41
    //   2211: ldc -2147450880
    //   2213: iastore
    //   2214: dup
    //   2215: bipush #42
    //   2217: bipush #32
    //   2219: iastore
    //   2220: dup
    //   2221: bipush #43
    //   2223: ldc -2146402272
    //   2225: iastore
    //   2226: dup
    //   2227: bipush #44
    //   2229: ldc 1081376
    //   2231: iastore
    //   2232: dup
    //   2233: bipush #45
    //   2235: bipush #32
    //   2237: iastore
    //   2238: dup
    //   2239: bipush #46
    //   2241: ldc 32768
    //   2243: iastore
    //   2244: dup
    //   2245: bipush #47
    //   2247: ldc -2147483648
    //   2249: iastore
    //   2250: dup
    //   2251: bipush #48
    //   2253: ldc 32800
    //   2255: iastore
    //   2256: dup
    //   2257: bipush #49
    //   2259: ldc -2146402304
    //   2261: iastore
    //   2262: dup
    //   2263: bipush #50
    //   2265: ldc 1048576
    //   2267: iastore
    //   2268: dup
    //   2269: bipush #51
    //   2271: ldc -2147483616
    //   2273: iastore
    //   2274: dup
    //   2275: bipush #52
    //   2277: ldc 1048608
    //   2279: iastore
    //   2280: dup
    //   2281: bipush #53
    //   2283: ldc -2147450848
    //   2285: iastore
    //   2286: dup
    //   2287: bipush #54
    //   2289: ldc -2147483616
    //   2291: iastore
    //   2292: dup
    //   2293: bipush #55
    //   2295: ldc 1048608
    //   2297: iastore
    //   2298: dup
    //   2299: bipush #56
    //   2301: ldc 1081344
    //   2303: iastore
    //   2304: dup
    //   2305: bipush #57
    //   2307: iconst_0
    //   2308: iastore
    //   2309: dup
    //   2310: bipush #58
    //   2312: ldc -2147450880
    //   2314: iastore
    //   2315: dup
    //   2316: bipush #59
    //   2318: ldc 32800
    //   2320: iastore
    //   2321: dup
    //   2322: bipush #60
    //   2324: ldc -2147483648
    //   2326: iastore
    //   2327: dup
    //   2328: bipush #61
    //   2330: ldc -2146435040
    //   2332: iastore
    //   2333: dup
    //   2334: bipush #62
    //   2336: ldc -2146402272
    //   2338: iastore
    //   2339: dup
    //   2340: bipush #63
    //   2342: ldc 1081344
    //   2344: iastore
    //   2345: astore #8
    //   2347: bipush #64
    //   2349: newarray int
    //   2351: dup
    //   2352: iconst_0
    //   2353: sipush #520
    //   2356: iastore
    //   2357: dup
    //   2358: iconst_1
    //   2359: ldc 134349312
    //   2361: iastore
    //   2362: dup
    //   2363: iconst_2
    //   2364: iconst_0
    //   2365: iastore
    //   2366: dup
    //   2367: iconst_3
    //   2368: ldc 134348808
    //   2370: iastore
    //   2371: dup
    //   2372: iconst_4
    //   2373: ldc 134218240
    //   2375: iastore
    //   2376: dup
    //   2377: iconst_5
    //   2378: iconst_0
    //   2379: iastore
    //   2380: dup
    //   2381: bipush #6
    //   2383: ldc 131592
    //   2385: iastore
    //   2386: dup
    //   2387: bipush #7
    //   2389: ldc 134218240
    //   2391: iastore
    //   2392: dup
    //   2393: bipush #8
    //   2395: ldc 131080
    //   2397: iastore
    //   2398: dup
    //   2399: bipush #9
    //   2401: ldc 134217736
    //   2403: iastore
    //   2404: dup
    //   2405: bipush #10
    //   2407: ldc 134217736
    //   2409: iastore
    //   2410: dup
    //   2411: bipush #11
    //   2413: ldc 131072
    //   2415: iastore
    //   2416: dup
    //   2417: bipush #12
    //   2419: ldc 134349320
    //   2421: iastore
    //   2422: dup
    //   2423: bipush #13
    //   2425: ldc 131080
    //   2427: iastore
    //   2428: dup
    //   2429: bipush #14
    //   2431: ldc 134348800
    //   2433: iastore
    //   2434: dup
    //   2435: bipush #15
    //   2437: sipush #520
    //   2440: iastore
    //   2441: dup
    //   2442: bipush #16
    //   2444: ldc 134217728
    //   2446: iastore
    //   2447: dup
    //   2448: bipush #17
    //   2450: bipush #8
    //   2452: iastore
    //   2453: dup
    //   2454: bipush #18
    //   2456: ldc 134349312
    //   2458: iastore
    //   2459: dup
    //   2460: bipush #19
    //   2462: sipush #512
    //   2465: iastore
    //   2466: dup
    //   2467: bipush #20
    //   2469: ldc 131584
    //   2471: iastore
    //   2472: dup
    //   2473: bipush #21
    //   2475: ldc 134348800
    //   2477: iastore
    //   2478: dup
    //   2479: bipush #22
    //   2481: ldc 134348808
    //   2483: iastore
    //   2484: dup
    //   2485: bipush #23
    //   2487: ldc 131592
    //   2489: iastore
    //   2490: dup
    //   2491: bipush #24
    //   2493: ldc 134218248
    //   2495: iastore
    //   2496: dup
    //   2497: bipush #25
    //   2499: ldc 131584
    //   2501: iastore
    //   2502: dup
    //   2503: bipush #26
    //   2505: ldc 131072
    //   2507: iastore
    //   2508: dup
    //   2509: bipush #27
    //   2511: ldc 134218248
    //   2513: iastore
    //   2514: dup
    //   2515: bipush #28
    //   2517: bipush #8
    //   2519: iastore
    //   2520: dup
    //   2521: bipush #29
    //   2523: ldc 134349320
    //   2525: iastore
    //   2526: dup
    //   2527: bipush #30
    //   2529: sipush #512
    //   2532: iastore
    //   2533: dup
    //   2534: bipush #31
    //   2536: ldc 134217728
    //   2538: iastore
    //   2539: dup
    //   2540: bipush #32
    //   2542: ldc 134349312
    //   2544: iastore
    //   2545: dup
    //   2546: bipush #33
    //   2548: ldc 134217728
    //   2550: iastore
    //   2551: dup
    //   2552: bipush #34
    //   2554: ldc 131080
    //   2556: iastore
    //   2557: dup
    //   2558: bipush #35
    //   2560: sipush #520
    //   2563: iastore
    //   2564: dup
    //   2565: bipush #36
    //   2567: ldc 131072
    //   2569: iastore
    //   2570: dup
    //   2571: bipush #37
    //   2573: ldc 134349312
    //   2575: iastore
    //   2576: dup
    //   2577: bipush #38
    //   2579: ldc 134218240
    //   2581: iastore
    //   2582: dup
    //   2583: bipush #39
    //   2585: iconst_0
    //   2586: iastore
    //   2587: dup
    //   2588: bipush #40
    //   2590: sipush #512
    //   2593: iastore
    //   2594: dup
    //   2595: bipush #41
    //   2597: ldc 131080
    //   2599: iastore
    //   2600: dup
    //   2601: bipush #42
    //   2603: ldc 134349320
    //   2605: iastore
    //   2606: dup
    //   2607: bipush #43
    //   2609: ldc 134218240
    //   2611: iastore
    //   2612: dup
    //   2613: bipush #44
    //   2615: ldc 134217736
    //   2617: iastore
    //   2618: dup
    //   2619: bipush #45
    //   2621: sipush #512
    //   2624: iastore
    //   2625: dup
    //   2626: bipush #46
    //   2628: iconst_0
    //   2629: iastore
    //   2630: dup
    //   2631: bipush #47
    //   2633: ldc 134348808
    //   2635: iastore
    //   2636: dup
    //   2637: bipush #48
    //   2639: ldc 134218248
    //   2641: iastore
    //   2642: dup
    //   2643: bipush #49
    //   2645: ldc 131072
    //   2647: iastore
    //   2648: dup
    //   2649: bipush #50
    //   2651: ldc 134217728
    //   2653: iastore
    //   2654: dup
    //   2655: bipush #51
    //   2657: ldc 134349320
    //   2659: iastore
    //   2660: dup
    //   2661: bipush #52
    //   2663: bipush #8
    //   2665: iastore
    //   2666: dup
    //   2667: bipush #53
    //   2669: ldc 131592
    //   2671: iastore
    //   2672: dup
    //   2673: bipush #54
    //   2675: ldc 131584
    //   2677: iastore
    //   2678: dup
    //   2679: bipush #55
    //   2681: ldc 134217736
    //   2683: iastore
    //   2684: dup
    //   2685: bipush #56
    //   2687: ldc 134348800
    //   2689: iastore
    //   2690: dup
    //   2691: bipush #57
    //   2693: ldc 134218248
    //   2695: iastore
    //   2696: dup
    //   2697: bipush #58
    //   2699: sipush #520
    //   2702: iastore
    //   2703: dup
    //   2704: bipush #59
    //   2706: ldc 134348800
    //   2708: iastore
    //   2709: dup
    //   2710: bipush #60
    //   2712: ldc 131592
    //   2714: iastore
    //   2715: dup
    //   2716: bipush #61
    //   2718: bipush #8
    //   2720: iastore
    //   2721: dup
    //   2722: bipush #62
    //   2724: ldc 134348808
    //   2726: iastore
    //   2727: dup
    //   2728: bipush #63
    //   2730: ldc 131584
    //   2732: iastore
    //   2733: astore #9
    //   2735: bipush #64
    //   2737: newarray int
    //   2739: dup
    //   2740: iconst_0
    //   2741: ldc 8396801
    //   2743: iastore
    //   2744: dup
    //   2745: iconst_1
    //   2746: sipush #8321
    //   2749: iastore
    //   2750: dup
    //   2751: iconst_2
    //   2752: sipush #8321
    //   2755: iastore
    //   2756: dup
    //   2757: iconst_3
    //   2758: sipush #128
    //   2761: iastore
    //   2762: dup
    //   2763: iconst_4
    //   2764: ldc 8396928
    //   2766: iastore
    //   2767: dup
    //   2768: iconst_5
    //   2769: ldc 8388737
    //   2771: iastore
    //   2772: dup
    //   2773: bipush #6
    //   2775: ldc 8388609
    //   2777: iastore
    //   2778: dup
    //   2779: bipush #7
    //   2781: sipush #8193
    //   2784: iastore
    //   2785: dup
    //   2786: bipush #8
    //   2788: iconst_0
    //   2789: iastore
    //   2790: dup
    //   2791: bipush #9
    //   2793: ldc 8396800
    //   2795: iastore
    //   2796: dup
    //   2797: bipush #10
    //   2799: ldc 8396800
    //   2801: iastore
    //   2802: dup
    //   2803: bipush #11
    //   2805: ldc 8396929
    //   2807: iastore
    //   2808: dup
    //   2809: bipush #12
    //   2811: sipush #129
    //   2814: iastore
    //   2815: dup
    //   2816: bipush #13
    //   2818: iconst_0
    //   2819: iastore
    //   2820: dup
    //   2821: bipush #14
    //   2823: ldc 8388736
    //   2825: iastore
    //   2826: dup
    //   2827: bipush #15
    //   2829: ldc 8388609
    //   2831: iastore
    //   2832: dup
    //   2833: bipush #16
    //   2835: iconst_1
    //   2836: iastore
    //   2837: dup
    //   2838: bipush #17
    //   2840: sipush #8192
    //   2843: iastore
    //   2844: dup
    //   2845: bipush #18
    //   2847: ldc 8388608
    //   2849: iastore
    //   2850: dup
    //   2851: bipush #19
    //   2853: ldc 8396801
    //   2855: iastore
    //   2856: dup
    //   2857: bipush #20
    //   2859: sipush #128
    //   2862: iastore
    //   2863: dup
    //   2864: bipush #21
    //   2866: ldc 8388608
    //   2868: iastore
    //   2869: dup
    //   2870: bipush #22
    //   2872: sipush #8193
    //   2875: iastore
    //   2876: dup
    //   2877: bipush #23
    //   2879: sipush #8320
    //   2882: iastore
    //   2883: dup
    //   2884: bipush #24
    //   2886: ldc 8388737
    //   2888: iastore
    //   2889: dup
    //   2890: bipush #25
    //   2892: iconst_1
    //   2893: iastore
    //   2894: dup
    //   2895: bipush #26
    //   2897: sipush #8320
    //   2900: iastore
    //   2901: dup
    //   2902: bipush #27
    //   2904: ldc 8388736
    //   2906: iastore
    //   2907: dup
    //   2908: bipush #28
    //   2910: sipush #8192
    //   2913: iastore
    //   2914: dup
    //   2915: bipush #29
    //   2917: ldc 8396928
    //   2919: iastore
    //   2920: dup
    //   2921: bipush #30
    //   2923: ldc 8396929
    //   2925: iastore
    //   2926: dup
    //   2927: bipush #31
    //   2929: sipush #129
    //   2932: iastore
    //   2933: dup
    //   2934: bipush #32
    //   2936: ldc 8388736
    //   2938: iastore
    //   2939: dup
    //   2940: bipush #33
    //   2942: ldc 8388609
    //   2944: iastore
    //   2945: dup
    //   2946: bipush #34
    //   2948: ldc 8396800
    //   2950: iastore
    //   2951: dup
    //   2952: bipush #35
    //   2954: ldc 8396929
    //   2956: iastore
    //   2957: dup
    //   2958: bipush #36
    //   2960: sipush #129
    //   2963: iastore
    //   2964: dup
    //   2965: bipush #37
    //   2967: iconst_0
    //   2968: iastore
    //   2969: dup
    //   2970: bipush #38
    //   2972: iconst_0
    //   2973: iastore
    //   2974: dup
    //   2975: bipush #39
    //   2977: ldc 8396800
    //   2979: iastore
    //   2980: dup
    //   2981: bipush #40
    //   2983: sipush #8320
    //   2986: iastore
    //   2987: dup
    //   2988: bipush #41
    //   2990: ldc 8388736
    //   2992: iastore
    //   2993: dup
    //   2994: bipush #42
    //   2996: ldc 8388737
    //   2998: iastore
    //   2999: dup
    //   3000: bipush #43
    //   3002: iconst_1
    //   3003: iastore
    //   3004: dup
    //   3005: bipush #44
    //   3007: ldc 8396801
    //   3009: iastore
    //   3010: dup
    //   3011: bipush #45
    //   3013: sipush #8321
    //   3016: iastore
    //   3017: dup
    //   3018: bipush #46
    //   3020: sipush #8321
    //   3023: iastore
    //   3024: dup
    //   3025: bipush #47
    //   3027: sipush #128
    //   3030: iastore
    //   3031: dup
    //   3032: bipush #48
    //   3034: ldc 8396929
    //   3036: iastore
    //   3037: dup
    //   3038: bipush #49
    //   3040: sipush #129
    //   3043: iastore
    //   3044: dup
    //   3045: bipush #50
    //   3047: iconst_1
    //   3048: iastore
    //   3049: dup
    //   3050: bipush #51
    //   3052: sipush #8192
    //   3055: iastore
    //   3056: dup
    //   3057: bipush #52
    //   3059: ldc 8388609
    //   3061: iastore
    //   3062: dup
    //   3063: bipush #53
    //   3065: sipush #8193
    //   3068: iastore
    //   3069: dup
    //   3070: bipush #54
    //   3072: ldc 8396928
    //   3074: iastore
    //   3075: dup
    //   3076: bipush #55
    //   3078: ldc 8388737
    //   3080: iastore
    //   3081: dup
    //   3082: bipush #56
    //   3084: sipush #8193
    //   3087: iastore
    //   3088: dup
    //   3089: bipush #57
    //   3091: sipush #8320
    //   3094: iastore
    //   3095: dup
    //   3096: bipush #58
    //   3098: ldc 8388608
    //   3100: iastore
    //   3101: dup
    //   3102: bipush #59
    //   3104: ldc 8396801
    //   3106: iastore
    //   3107: dup
    //   3108: bipush #60
    //   3110: sipush #128
    //   3113: iastore
    //   3114: dup
    //   3115: bipush #61
    //   3117: ldc 8388608
    //   3119: iastore
    //   3120: dup
    //   3121: bipush #62
    //   3123: sipush #8192
    //   3126: iastore
    //   3127: dup
    //   3128: bipush #63
    //   3130: ldc 8396928
    //   3132: iastore
    //   3133: astore #10
    //   3135: bipush #64
    //   3137: newarray int
    //   3139: dup
    //   3140: iconst_0
    //   3141: sipush #256
    //   3144: iastore
    //   3145: dup
    //   3146: iconst_1
    //   3147: ldc 34078976
    //   3149: iastore
    //   3150: dup
    //   3151: iconst_2
    //   3152: ldc 34078720
    //   3154: iastore
    //   3155: dup
    //   3156: iconst_3
    //   3157: ldc 1107296512
    //   3159: iastore
    //   3160: dup
    //   3161: iconst_4
    //   3162: ldc 524288
    //   3164: iastore
    //   3165: dup
    //   3166: iconst_5
    //   3167: sipush #256
    //   3170: iastore
    //   3171: dup
    //   3172: bipush #6
    //   3174: ldc 1073741824
    //   3176: iastore
    //   3177: dup
    //   3178: bipush #7
    //   3180: ldc 34078720
    //   3182: iastore
    //   3183: dup
    //   3184: bipush #8
    //   3186: ldc 1074266368
    //   3188: iastore
    //   3189: dup
    //   3190: bipush #9
    //   3192: ldc 524288
    //   3194: iastore
    //   3195: dup
    //   3196: bipush #10
    //   3198: ldc 33554688
    //   3200: iastore
    //   3201: dup
    //   3202: bipush #11
    //   3204: ldc 1074266368
    //   3206: iastore
    //   3207: dup
    //   3208: bipush #12
    //   3210: ldc 1107296512
    //   3212: iastore
    //   3213: dup
    //   3214: bipush #13
    //   3216: ldc 1107820544
    //   3218: iastore
    //   3219: dup
    //   3220: bipush #14
    //   3222: ldc 524544
    //   3224: iastore
    //   3225: dup
    //   3226: bipush #15
    //   3228: ldc 1073741824
    //   3230: iastore
    //   3231: dup
    //   3232: bipush #16
    //   3234: ldc 33554432
    //   3236: iastore
    //   3237: dup
    //   3238: bipush #17
    //   3240: ldc 1074266112
    //   3242: iastore
    //   3243: dup
    //   3244: bipush #18
    //   3246: ldc 1074266112
    //   3248: iastore
    //   3249: dup
    //   3250: bipush #19
    //   3252: iconst_0
    //   3253: iastore
    //   3254: dup
    //   3255: bipush #20
    //   3257: ldc 1073742080
    //   3259: iastore
    //   3260: dup
    //   3261: bipush #21
    //   3263: ldc 1107820800
    //   3265: iastore
    //   3266: dup
    //   3267: bipush #22
    //   3269: ldc 1107820800
    //   3271: iastore
    //   3272: dup
    //   3273: bipush #23
    //   3275: ldc 33554688
    //   3277: iastore
    //   3278: dup
    //   3279: bipush #24
    //   3281: ldc 1107820544
    //   3283: iastore
    //   3284: dup
    //   3285: bipush #25
    //   3287: ldc 1073742080
    //   3289: iastore
    //   3290: dup
    //   3291: bipush #26
    //   3293: iconst_0
    //   3294: iastore
    //   3295: dup
    //   3296: bipush #27
    //   3298: ldc 1107296256
    //   3300: iastore
    //   3301: dup
    //   3302: bipush #28
    //   3304: ldc 34078976
    //   3306: iastore
    //   3307: dup
    //   3308: bipush #29
    //   3310: ldc 33554432
    //   3312: iastore
    //   3313: dup
    //   3314: bipush #30
    //   3316: ldc 1107296256
    //   3318: iastore
    //   3319: dup
    //   3320: bipush #31
    //   3322: ldc 524544
    //   3324: iastore
    //   3325: dup
    //   3326: bipush #32
    //   3328: ldc 524288
    //   3330: iastore
    //   3331: dup
    //   3332: bipush #33
    //   3334: ldc 1107296512
    //   3336: iastore
    //   3337: dup
    //   3338: bipush #34
    //   3340: sipush #256
    //   3343: iastore
    //   3344: dup
    //   3345: bipush #35
    //   3347: ldc 33554432
    //   3349: iastore
    //   3350: dup
    //   3351: bipush #36
    //   3353: ldc 1073741824
    //   3355: iastore
    //   3356: dup
    //   3357: bipush #37
    //   3359: ldc 34078720
    //   3361: iastore
    //   3362: dup
    //   3363: bipush #38
    //   3365: ldc 1107296512
    //   3367: iastore
    //   3368: dup
    //   3369: bipush #39
    //   3371: ldc 1074266368
    //   3373: iastore
    //   3374: dup
    //   3375: bipush #40
    //   3377: ldc 33554688
    //   3379: iastore
    //   3380: dup
    //   3381: bipush #41
    //   3383: ldc 1073741824
    //   3385: iastore
    //   3386: dup
    //   3387: bipush #42
    //   3389: ldc 1107820544
    //   3391: iastore
    //   3392: dup
    //   3393: bipush #43
    //   3395: ldc 34078976
    //   3397: iastore
    //   3398: dup
    //   3399: bipush #44
    //   3401: ldc 1074266368
    //   3403: iastore
    //   3404: dup
    //   3405: bipush #45
    //   3407: sipush #256
    //   3410: iastore
    //   3411: dup
    //   3412: bipush #46
    //   3414: ldc 33554432
    //   3416: iastore
    //   3417: dup
    //   3418: bipush #47
    //   3420: ldc 1107820544
    //   3422: iastore
    //   3423: dup
    //   3424: bipush #48
    //   3426: ldc 1107820800
    //   3428: iastore
    //   3429: dup
    //   3430: bipush #49
    //   3432: ldc 524544
    //   3434: iastore
    //   3435: dup
    //   3436: bipush #50
    //   3438: ldc 1107296256
    //   3440: iastore
    //   3441: dup
    //   3442: bipush #51
    //   3444: ldc 1107820800
    //   3446: iastore
    //   3447: dup
    //   3448: bipush #52
    //   3450: ldc 34078720
    //   3452: iastore
    //   3453: dup
    //   3454: bipush #53
    //   3456: iconst_0
    //   3457: iastore
    //   3458: dup
    //   3459: bipush #54
    //   3461: ldc 1074266112
    //   3463: iastore
    //   3464: dup
    //   3465: bipush #55
    //   3467: ldc 1107296256
    //   3469: iastore
    //   3470: dup
    //   3471: bipush #56
    //   3473: ldc 524544
    //   3475: iastore
    //   3476: dup
    //   3477: bipush #57
    //   3479: ldc 33554688
    //   3481: iastore
    //   3482: dup
    //   3483: bipush #58
    //   3485: ldc 1073742080
    //   3487: iastore
    //   3488: dup
    //   3489: bipush #59
    //   3491: ldc 524288
    //   3493: iastore
    //   3494: dup
    //   3495: bipush #60
    //   3497: iconst_0
    //   3498: iastore
    //   3499: dup
    //   3500: bipush #61
    //   3502: ldc 1074266112
    //   3504: iastore
    //   3505: dup
    //   3506: bipush #62
    //   3508: ldc 34078976
    //   3510: iastore
    //   3511: dup
    //   3512: bipush #63
    //   3514: ldc 1073742080
    //   3516: iastore
    //   3517: astore #11
    //   3519: bipush #64
    //   3521: newarray int
    //   3523: dup
    //   3524: iconst_0
    //   3525: ldc 536870928
    //   3527: iastore
    //   3528: dup
    //   3529: iconst_1
    //   3530: ldc 541065216
    //   3532: iastore
    //   3533: dup
    //   3534: iconst_2
    //   3535: sipush #16384
    //   3538: iastore
    //   3539: dup
    //   3540: iconst_3
    //   3541: ldc 541081616
    //   3543: iastore
    //   3544: dup
    //   3545: iconst_4
    //   3546: ldc 541065216
    //   3548: iastore
    //   3549: dup
    //   3550: iconst_5
    //   3551: bipush #16
    //   3553: iastore
    //   3554: dup
    //   3555: bipush #6
    //   3557: ldc 541081616
    //   3559: iastore
    //   3560: dup
    //   3561: bipush #7
    //   3563: ldc 4194304
    //   3565: iastore
    //   3566: dup
    //   3567: bipush #8
    //   3569: ldc 536887296
    //   3571: iastore
    //   3572: dup
    //   3573: bipush #9
    //   3575: ldc 4210704
    //   3577: iastore
    //   3578: dup
    //   3579: bipush #10
    //   3581: ldc 4194304
    //   3583: iastore
    //   3584: dup
    //   3585: bipush #11
    //   3587: ldc 536870928
    //   3589: iastore
    //   3590: dup
    //   3591: bipush #12
    //   3593: ldc 4194320
    //   3595: iastore
    //   3596: dup
    //   3597: bipush #13
    //   3599: ldc 536887296
    //   3601: iastore
    //   3602: dup
    //   3603: bipush #14
    //   3605: ldc 536870912
    //   3607: iastore
    //   3608: dup
    //   3609: bipush #15
    //   3611: sipush #16400
    //   3614: iastore
    //   3615: dup
    //   3616: bipush #16
    //   3618: iconst_0
    //   3619: iastore
    //   3620: dup
    //   3621: bipush #17
    //   3623: ldc 4194320
    //   3625: iastore
    //   3626: dup
    //   3627: bipush #18
    //   3629: ldc 536887312
    //   3631: iastore
    //   3632: dup
    //   3633: bipush #19
    //   3635: sipush #16384
    //   3638: iastore
    //   3639: dup
    //   3640: bipush #20
    //   3642: ldc 4210688
    //   3644: iastore
    //   3645: dup
    //   3646: bipush #21
    //   3648: ldc 536887312
    //   3650: iastore
    //   3651: dup
    //   3652: bipush #22
    //   3654: bipush #16
    //   3656: iastore
    //   3657: dup
    //   3658: bipush #23
    //   3660: ldc 541065232
    //   3662: iastore
    //   3663: dup
    //   3664: bipush #24
    //   3666: ldc 541065232
    //   3668: iastore
    //   3669: dup
    //   3670: bipush #25
    //   3672: iconst_0
    //   3673: iastore
    //   3674: dup
    //   3675: bipush #26
    //   3677: ldc 4210704
    //   3679: iastore
    //   3680: dup
    //   3681: bipush #27
    //   3683: ldc 541081600
    //   3685: iastore
    //   3686: dup
    //   3687: bipush #28
    //   3689: sipush #16400
    //   3692: iastore
    //   3693: dup
    //   3694: bipush #29
    //   3696: ldc 4210688
    //   3698: iastore
    //   3699: dup
    //   3700: bipush #30
    //   3702: ldc 541081600
    //   3704: iastore
    //   3705: dup
    //   3706: bipush #31
    //   3708: ldc 536870912
    //   3710: iastore
    //   3711: dup
    //   3712: bipush #32
    //   3714: ldc 536887296
    //   3716: iastore
    //   3717: dup
    //   3718: bipush #33
    //   3720: bipush #16
    //   3722: iastore
    //   3723: dup
    //   3724: bipush #34
    //   3726: ldc 541065232
    //   3728: iastore
    //   3729: dup
    //   3730: bipush #35
    //   3732: ldc 4210688
    //   3734: iastore
    //   3735: dup
    //   3736: bipush #36
    //   3738: ldc 541081616
    //   3740: iastore
    //   3741: dup
    //   3742: bipush #37
    //   3744: ldc 4194304
    //   3746: iastore
    //   3747: dup
    //   3748: bipush #38
    //   3750: sipush #16400
    //   3753: iastore
    //   3754: dup
    //   3755: bipush #39
    //   3757: ldc 536870928
    //   3759: iastore
    //   3760: dup
    //   3761: bipush #40
    //   3763: ldc 4194304
    //   3765: iastore
    //   3766: dup
    //   3767: bipush #41
    //   3769: ldc 536887296
    //   3771: iastore
    //   3772: dup
    //   3773: bipush #42
    //   3775: ldc 536870912
    //   3777: iastore
    //   3778: dup
    //   3779: bipush #43
    //   3781: sipush #16400
    //   3784: iastore
    //   3785: dup
    //   3786: bipush #44
    //   3788: ldc 536870928
    //   3790: iastore
    //   3791: dup
    //   3792: bipush #45
    //   3794: ldc 541081616
    //   3796: iastore
    //   3797: dup
    //   3798: bipush #46
    //   3800: ldc 4210688
    //   3802: iastore
    //   3803: dup
    //   3804: bipush #47
    //   3806: ldc 541065216
    //   3808: iastore
    //   3809: dup
    //   3810: bipush #48
    //   3812: ldc 4210704
    //   3814: iastore
    //   3815: dup
    //   3816: bipush #49
    //   3818: ldc 541081600
    //   3820: iastore
    //   3821: dup
    //   3822: bipush #50
    //   3824: iconst_0
    //   3825: iastore
    //   3826: dup
    //   3827: bipush #51
    //   3829: ldc 541065232
    //   3831: iastore
    //   3832: dup
    //   3833: bipush #52
    //   3835: bipush #16
    //   3837: iastore
    //   3838: dup
    //   3839: bipush #53
    //   3841: sipush #16384
    //   3844: iastore
    //   3845: dup
    //   3846: bipush #54
    //   3848: ldc 541065216
    //   3850: iastore
    //   3851: dup
    //   3852: bipush #55
    //   3854: ldc 4210704
    //   3856: iastore
    //   3857: dup
    //   3858: bipush #56
    //   3860: sipush #16384
    //   3863: iastore
    //   3864: dup
    //   3865: bipush #57
    //   3867: ldc 4194320
    //   3869: iastore
    //   3870: dup
    //   3871: bipush #58
    //   3873: ldc 536887312
    //   3875: iastore
    //   3876: dup
    //   3877: bipush #59
    //   3879: iconst_0
    //   3880: iastore
    //   3881: dup
    //   3882: bipush #60
    //   3884: ldc 541081600
    //   3886: iastore
    //   3887: dup
    //   3888: bipush #61
    //   3890: ldc 536870912
    //   3892: iastore
    //   3893: dup
    //   3894: bipush #62
    //   3896: ldc 4194320
    //   3898: iastore
    //   3899: dup
    //   3900: bipush #63
    //   3902: ldc 536887312
    //   3904: iastore
    //   3905: astore #12
    //   3907: bipush #64
    //   3909: newarray int
    //   3911: dup
    //   3912: iconst_0
    //   3913: ldc 2097152
    //   3915: iastore
    //   3916: dup
    //   3917: iconst_1
    //   3918: ldc 69206018
    //   3920: iastore
    //   3921: dup
    //   3922: iconst_2
    //   3923: ldc 67110914
    //   3925: iastore
    //   3926: dup
    //   3927: iconst_3
    //   3928: iconst_0
    //   3929: iastore
    //   3930: dup
    //   3931: iconst_4
    //   3932: sipush #2048
    //   3935: iastore
    //   3936: dup
    //   3937: iconst_5
    //   3938: ldc 67110914
    //   3940: iastore
    //   3941: dup
    //   3942: bipush #6
    //   3944: ldc 2099202
    //   3946: iastore
    //   3947: dup
    //   3948: bipush #7
    //   3950: ldc 69208064
    //   3952: iastore
    //   3953: dup
    //   3954: bipush #8
    //   3956: ldc 69208066
    //   3958: iastore
    //   3959: dup
    //   3960: bipush #9
    //   3962: ldc 2097152
    //   3964: iastore
    //   3965: dup
    //   3966: bipush #10
    //   3968: iconst_0
    //   3969: iastore
    //   3970: dup
    //   3971: bipush #11
    //   3973: ldc 67108866
    //   3975: iastore
    //   3976: dup
    //   3977: bipush #12
    //   3979: iconst_2
    //   3980: iastore
    //   3981: dup
    //   3982: bipush #13
    //   3984: ldc 67108864
    //   3986: iastore
    //   3987: dup
    //   3988: bipush #14
    //   3990: ldc 69206018
    //   3992: iastore
    //   3993: dup
    //   3994: bipush #15
    //   3996: sipush #2050
    //   3999: iastore
    //   4000: dup
    //   4001: bipush #16
    //   4003: ldc 67110912
    //   4005: iastore
    //   4006: dup
    //   4007: bipush #17
    //   4009: ldc 2099202
    //   4011: iastore
    //   4012: dup
    //   4013: bipush #18
    //   4015: ldc 2097154
    //   4017: iastore
    //   4018: dup
    //   4019: bipush #19
    //   4021: ldc 67110912
    //   4023: iastore
    //   4024: dup
    //   4025: bipush #20
    //   4027: ldc 67108866
    //   4029: iastore
    //   4030: dup
    //   4031: bipush #21
    //   4033: ldc 69206016
    //   4035: iastore
    //   4036: dup
    //   4037: bipush #22
    //   4039: ldc 69208064
    //   4041: iastore
    //   4042: dup
    //   4043: bipush #23
    //   4045: ldc 2097154
    //   4047: iastore
    //   4048: dup
    //   4049: bipush #24
    //   4051: ldc 69206016
    //   4053: iastore
    //   4054: dup
    //   4055: bipush #25
    //   4057: sipush #2048
    //   4060: iastore
    //   4061: dup
    //   4062: bipush #26
    //   4064: sipush #2050
    //   4067: iastore
    //   4068: dup
    //   4069: bipush #27
    //   4071: ldc 69208066
    //   4073: iastore
    //   4074: dup
    //   4075: bipush #28
    //   4077: ldc 2099200
    //   4079: iastore
    //   4080: dup
    //   4081: bipush #29
    //   4083: iconst_2
    //   4084: iastore
    //   4085: dup
    //   4086: bipush #30
    //   4088: ldc 67108864
    //   4090: iastore
    //   4091: dup
    //   4092: bipush #31
    //   4094: ldc 2099200
    //   4096: iastore
    //   4097: dup
    //   4098: bipush #32
    //   4100: ldc 67108864
    //   4102: iastore
    //   4103: dup
    //   4104: bipush #33
    //   4106: ldc 2099200
    //   4108: iastore
    //   4109: dup
    //   4110: bipush #34
    //   4112: ldc 2097152
    //   4114: iastore
    //   4115: dup
    //   4116: bipush #35
    //   4118: ldc 67110914
    //   4120: iastore
    //   4121: dup
    //   4122: bipush #36
    //   4124: ldc 67110914
    //   4126: iastore
    //   4127: dup
    //   4128: bipush #37
    //   4130: ldc 69206018
    //   4132: iastore
    //   4133: dup
    //   4134: bipush #38
    //   4136: ldc 69206018
    //   4138: iastore
    //   4139: dup
    //   4140: bipush #39
    //   4142: iconst_2
    //   4143: iastore
    //   4144: dup
    //   4145: bipush #40
    //   4147: ldc 2097154
    //   4149: iastore
    //   4150: dup
    //   4151: bipush #41
    //   4153: ldc 67108864
    //   4155: iastore
    //   4156: dup
    //   4157: bipush #42
    //   4159: ldc 67110912
    //   4161: iastore
    //   4162: dup
    //   4163: bipush #43
    //   4165: ldc 2097152
    //   4167: iastore
    //   4168: dup
    //   4169: bipush #44
    //   4171: ldc 69208064
    //   4173: iastore
    //   4174: dup
    //   4175: bipush #45
    //   4177: sipush #2050
    //   4180: iastore
    //   4181: dup
    //   4182: bipush #46
    //   4184: ldc 2099202
    //   4186: iastore
    //   4187: dup
    //   4188: bipush #47
    //   4190: ldc 69208064
    //   4192: iastore
    //   4193: dup
    //   4194: bipush #48
    //   4196: sipush #2050
    //   4199: iastore
    //   4200: dup
    //   4201: bipush #49
    //   4203: ldc 67108866
    //   4205: iastore
    //   4206: dup
    //   4207: bipush #50
    //   4209: ldc 69208066
    //   4211: iastore
    //   4212: dup
    //   4213: bipush #51
    //   4215: ldc 69206016
    //   4217: iastore
    //   4218: dup
    //   4219: bipush #52
    //   4221: ldc 2099200
    //   4223: iastore
    //   4224: dup
    //   4225: bipush #53
    //   4227: iconst_0
    //   4228: iastore
    //   4229: dup
    //   4230: bipush #54
    //   4232: iconst_2
    //   4233: iastore
    //   4234: dup
    //   4235: bipush #55
    //   4237: ldc 69208066
    //   4239: iastore
    //   4240: dup
    //   4241: bipush #56
    //   4243: iconst_0
    //   4244: iastore
    //   4245: dup
    //   4246: bipush #57
    //   4248: ldc 2099202
    //   4250: iastore
    //   4251: dup
    //   4252: bipush #58
    //   4254: ldc 69206016
    //   4256: iastore
    //   4257: dup
    //   4258: bipush #59
    //   4260: sipush #2048
    //   4263: iastore
    //   4264: dup
    //   4265: bipush #60
    //   4267: ldc 67108866
    //   4269: iastore
    //   4270: dup
    //   4271: bipush #61
    //   4273: ldc 67110912
    //   4275: iastore
    //   4276: dup
    //   4277: bipush #62
    //   4279: sipush #2048
    //   4282: iastore
    //   4283: dup
    //   4284: bipush #63
    //   4286: ldc 2097154
    //   4288: iastore
    //   4289: astore #13
    //   4291: bipush #64
    //   4293: newarray int
    //   4295: dup
    //   4296: iconst_0
    //   4297: ldc 268439616
    //   4299: iastore
    //   4300: dup
    //   4301: iconst_1
    //   4302: sipush #4096
    //   4305: iastore
    //   4306: dup
    //   4307: iconst_2
    //   4308: ldc 262144
    //   4310: iastore
    //   4311: dup
    //   4312: iconst_3
    //   4313: ldc 268701760
    //   4315: iastore
    //   4316: dup
    //   4317: iconst_4
    //   4318: ldc 268435456
    //   4320: iastore
    //   4321: dup
    //   4322: iconst_5
    //   4323: ldc 268439616
    //   4325: iastore
    //   4326: dup
    //   4327: bipush #6
    //   4329: bipush #64
    //   4331: iastore
    //   4332: dup
    //   4333: bipush #7
    //   4335: ldc 268435456
    //   4337: iastore
    //   4338: dup
    //   4339: bipush #8
    //   4341: ldc 262208
    //   4343: iastore
    //   4344: dup
    //   4345: bipush #9
    //   4347: ldc 268697600
    //   4349: iastore
    //   4350: dup
    //   4351: bipush #10
    //   4353: ldc 268701760
    //   4355: iastore
    //   4356: dup
    //   4357: bipush #11
    //   4359: ldc 266240
    //   4361: iastore
    //   4362: dup
    //   4363: bipush #12
    //   4365: ldc 268701696
    //   4367: iastore
    //   4368: dup
    //   4369: bipush #13
    //   4371: ldc 266304
    //   4373: iastore
    //   4374: dup
    //   4375: bipush #14
    //   4377: sipush #4096
    //   4380: iastore
    //   4381: dup
    //   4382: bipush #15
    //   4384: bipush #64
    //   4386: iastore
    //   4387: dup
    //   4388: bipush #16
    //   4390: ldc 268697600
    //   4392: iastore
    //   4393: dup
    //   4394: bipush #17
    //   4396: ldc 268435520
    //   4398: iastore
    //   4399: dup
    //   4400: bipush #18
    //   4402: ldc 268439552
    //   4404: iastore
    //   4405: dup
    //   4406: bipush #19
    //   4408: sipush #4160
    //   4411: iastore
    //   4412: dup
    //   4413: bipush #20
    //   4415: ldc 266240
    //   4417: iastore
    //   4418: dup
    //   4419: bipush #21
    //   4421: ldc 262208
    //   4423: iastore
    //   4424: dup
    //   4425: bipush #22
    //   4427: ldc 268697664
    //   4429: iastore
    //   4430: dup
    //   4431: bipush #23
    //   4433: ldc 268701696
    //   4435: iastore
    //   4436: dup
    //   4437: bipush #24
    //   4439: sipush #4160
    //   4442: iastore
    //   4443: dup
    //   4444: bipush #25
    //   4446: iconst_0
    //   4447: iastore
    //   4448: dup
    //   4449: bipush #26
    //   4451: iconst_0
    //   4452: iastore
    //   4453: dup
    //   4454: bipush #27
    //   4456: ldc 268697664
    //   4458: iastore
    //   4459: dup
    //   4460: bipush #28
    //   4462: ldc 268435520
    //   4464: iastore
    //   4465: dup
    //   4466: bipush #29
    //   4468: ldc 268439552
    //   4470: iastore
    //   4471: dup
    //   4472: bipush #30
    //   4474: ldc 266304
    //   4476: iastore
    //   4477: dup
    //   4478: bipush #31
    //   4480: ldc 262144
    //   4482: iastore
    //   4483: dup
    //   4484: bipush #32
    //   4486: ldc 266304
    //   4488: iastore
    //   4489: dup
    //   4490: bipush #33
    //   4492: ldc 262144
    //   4494: iastore
    //   4495: dup
    //   4496: bipush #34
    //   4498: ldc 268701696
    //   4500: iastore
    //   4501: dup
    //   4502: bipush #35
    //   4504: sipush #4096
    //   4507: iastore
    //   4508: dup
    //   4509: bipush #36
    //   4511: bipush #64
    //   4513: iastore
    //   4514: dup
    //   4515: bipush #37
    //   4517: ldc 268697664
    //   4519: iastore
    //   4520: dup
    //   4521: bipush #38
    //   4523: sipush #4096
    //   4526: iastore
    //   4527: dup
    //   4528: bipush #39
    //   4530: ldc 266304
    //   4532: iastore
    //   4533: dup
    //   4534: bipush #40
    //   4536: ldc 268439552
    //   4538: iastore
    //   4539: dup
    //   4540: bipush #41
    //   4542: bipush #64
    //   4544: iastore
    //   4545: dup
    //   4546: bipush #42
    //   4548: ldc 268435520
    //   4550: iastore
    //   4551: dup
    //   4552: bipush #43
    //   4554: ldc 268697600
    //   4556: iastore
    //   4557: dup
    //   4558: bipush #44
    //   4560: ldc 268697664
    //   4562: iastore
    //   4563: dup
    //   4564: bipush #45
    //   4566: ldc 268435456
    //   4568: iastore
    //   4569: dup
    //   4570: bipush #46
    //   4572: ldc 262144
    //   4574: iastore
    //   4575: dup
    //   4576: bipush #47
    //   4578: ldc 268439616
    //   4580: iastore
    //   4581: dup
    //   4582: bipush #48
    //   4584: iconst_0
    //   4585: iastore
    //   4586: dup
    //   4587: bipush #49
    //   4589: ldc 268701760
    //   4591: iastore
    //   4592: dup
    //   4593: bipush #50
    //   4595: ldc 262208
    //   4597: iastore
    //   4598: dup
    //   4599: bipush #51
    //   4601: ldc 268435520
    //   4603: iastore
    //   4604: dup
    //   4605: bipush #52
    //   4607: ldc 268697600
    //   4609: iastore
    //   4610: dup
    //   4611: bipush #53
    //   4613: ldc 268439552
    //   4615: iastore
    //   4616: dup
    //   4617: bipush #54
    //   4619: ldc 268439616
    //   4621: iastore
    //   4622: dup
    //   4623: bipush #55
    //   4625: iconst_0
    //   4626: iastore
    //   4627: dup
    //   4628: bipush #56
    //   4630: ldc 268701760
    //   4632: iastore
    //   4633: dup
    //   4634: bipush #57
    //   4636: ldc 266240
    //   4638: iastore
    //   4639: dup
    //   4640: bipush #58
    //   4642: ldc 266240
    //   4644: iastore
    //   4645: dup
    //   4646: bipush #59
    //   4648: sipush #4160
    //   4651: iastore
    //   4652: dup
    //   4653: bipush #60
    //   4655: sipush #4160
    //   4658: iastore
    //   4659: dup
    //   4660: bipush #61
    //   4662: ldc 262208
    //   4664: iastore
    //   4665: dup
    //   4666: bipush #62
    //   4668: ldc 268435456
    //   4670: iastore
    //   4671: dup
    //   4672: bipush #63
    //   4674: ldc 268701696
    //   4676: iastore
    //   4677: astore #14
    //   4679: aload #4
    //   4681: arraylength
    //   4682: istore #15
    //   4684: iload #15
    //   4686: bipush #8
    //   4688: irem
    //   4689: ifeq -> 4713
    //   4692: new java/lang/Exception
    //   4695: dup
    //   4696: sipush #3827
    //   4699: sipush #-15407
    //   4702: invokestatic a : (II)Ljava/lang/String;
    //   4705: invokespecial <init> : (Ljava/lang/String;)V
    //   4708: athrow
    //   4709: invokestatic a : (Ljava/lang/Throwable;)Ljava/lang/Throwable;
    //   4712: athrow
    //   4713: iconst_2
    //   4714: newarray int
    //   4716: astore #16
    //   4718: iload #15
    //   4720: newarray byte
    //   4722: astore #17
    //   4724: iload #15
    //   4726: bipush #8
    //   4728: idiv
    //   4729: istore #18
    //   4731: iconst_0
    //   4732: istore #19
    //   4734: iload #19
    //   4736: iload #18
    //   4738: if_icmpge -> 5656
    //   4741: iload #19
    //   4743: bipush #8
    //   4745: imul
    //   4746: istore #20
    //   4748: iconst_0
    //   4749: istore #21
    //   4751: iload #21
    //   4753: iconst_2
    //   4754: if_icmpge -> 4843
    //   4757: aload #16
    //   4759: iload #21
    //   4761: aload #4
    //   4763: iload #20
    //   4765: iload #21
    //   4767: iconst_4
    //   4768: imul
    //   4769: iadd
    //   4770: baload
    //   4771: sipush #255
    //   4774: iand
    //   4775: bipush #24
    //   4777: ishl
    //   4778: aload #4
    //   4780: iload #20
    //   4782: iload #21
    //   4784: iconst_4
    //   4785: imul
    //   4786: iadd
    //   4787: iconst_1
    //   4788: iadd
    //   4789: baload
    //   4790: sipush #255
    //   4793: iand
    //   4794: bipush #16
    //   4796: ishl
    //   4797: ior
    //   4798: aload #4
    //   4800: iload #20
    //   4802: iload #21
    //   4804: iconst_4
    //   4805: imul
    //   4806: iadd
    //   4807: iconst_2
    //   4808: iadd
    //   4809: baload
    //   4810: sipush #255
    //   4813: iand
    //   4814: bipush #8
    //   4816: ishl
    //   4817: ior
    //   4818: aload #4
    //   4820: iload #20
    //   4822: iload #21
    //   4824: iconst_4
    //   4825: imul
    //   4826: iadd
    //   4827: iconst_3
    //   4828: iadd
    //   4829: baload
    //   4830: sipush #255
    //   4833: iand
    //   4834: ior
    //   4835: iastore
    //   4836: iinc #21, 1
    //   4839: iload_2
    //   4840: ifne -> 4751
    //   4843: iconst_0
    //   4844: istore #26
    //   4846: aload #16
    //   4848: iconst_0
    //   4849: iaload
    //   4850: istore #24
    //   4852: aload #16
    //   4854: iconst_1
    //   4855: iaload
    //   4856: istore #23
    //   4858: iload #24
    //   4860: iconst_4
    //   4861: iushr
    //   4862: iload #23
    //   4864: ixor
    //   4865: ldc 252645135
    //   4867: iand
    //   4868: istore #22
    //   4870: iload #23
    //   4872: iload #22
    //   4874: ixor
    //   4875: istore #23
    //   4877: iload #24
    //   4879: iload #22
    //   4881: iconst_4
    //   4882: ishl
    //   4883: ixor
    //   4884: istore #24
    //   4886: iload #24
    //   4888: bipush #16
    //   4890: iushr
    //   4891: iload #23
    //   4893: ixor
    //   4894: ldc 65535
    //   4896: iand
    //   4897: istore #22
    //   4899: iload #23
    //   4901: iload #22
    //   4903: ixor
    //   4904: istore #23
    //   4906: iload #24
    //   4908: iload #22
    //   4910: bipush #16
    //   4912: ishl
    //   4913: ixor
    //   4914: istore #24
    //   4916: iload #23
    //   4918: iconst_2
    //   4919: iushr
    //   4920: iload #24
    //   4922: ixor
    //   4923: ldc 858993459
    //   4925: iand
    //   4926: istore #22
    //   4928: iload #24
    //   4930: iload #22
    //   4932: ixor
    //   4933: istore #24
    //   4935: iload #23
    //   4937: iload #22
    //   4939: iconst_2
    //   4940: ishl
    //   4941: ixor
    //   4942: istore #23
    //   4944: iload #23
    //   4946: bipush #8
    //   4948: iushr
    //   4949: iload #24
    //   4951: ixor
    //   4952: ldc 16711935
    //   4954: iand
    //   4955: istore #22
    //   4957: iload #24
    //   4959: iload #22
    //   4961: ixor
    //   4962: istore #24
    //   4964: iload #23
    //   4966: iload #22
    //   4968: bipush #8
    //   4970: ishl
    //   4971: ixor
    //   4972: istore #23
    //   4974: iload #23
    //   4976: iconst_1
    //   4977: ishl
    //   4978: iload #23
    //   4980: bipush #31
    //   4982: iushr
    //   4983: iconst_1
    //   4984: iand
    //   4985: ior
    //   4986: istore #23
    //   4988: iload #24
    //   4990: iload #23
    //   4992: ixor
    //   4993: ldc -1431655766
    //   4995: iand
    //   4996: istore #22
    //   4998: iload #24
    //   5000: iload #22
    //   5002: ixor
    //   5003: istore #24
    //   5005: iload #23
    //   5007: iload #22
    //   5009: ixor
    //   5010: istore #23
    //   5012: iload #24
    //   5014: iconst_1
    //   5015: ishl
    //   5016: iload #24
    //   5018: bipush #31
    //   5020: iushr
    //   5021: iconst_1
    //   5022: iand
    //   5023: ior
    //   5024: istore #24
    //   5026: iconst_0
    //   5027: istore #25
    //   5029: iload #25
    //   5031: bipush #8
    //   5033: if_icmpge -> 5371
    //   5036: iload #23
    //   5038: bipush #28
    //   5040: ishl
    //   5041: iload #23
    //   5043: iconst_4
    //   5044: iushr
    //   5045: ior
    //   5046: istore #22
    //   5048: iload #22
    //   5050: aload #6
    //   5052: iload #26
    //   5054: iinc #26, 1
    //   5057: iaload
    //   5058: ixor
    //   5059: istore #22
    //   5061: aload #13
    //   5063: iload #22
    //   5065: bipush #63
    //   5067: iand
    //   5068: iaload
    //   5069: istore #21
    //   5071: iload #21
    //   5073: aload #11
    //   5075: iload #22
    //   5077: bipush #8
    //   5079: iushr
    //   5080: bipush #63
    //   5082: iand
    //   5083: iaload
    //   5084: ior
    //   5085: istore #21
    //   5087: iload #21
    //   5089: aload #9
    //   5091: iload #22
    //   5093: bipush #16
    //   5095: iushr
    //   5096: bipush #63
    //   5098: iand
    //   5099: iaload
    //   5100: ior
    //   5101: istore #21
    //   5103: iload #21
    //   5105: aload #7
    //   5107: iload #22
    //   5109: bipush #24
    //   5111: iushr
    //   5112: bipush #63
    //   5114: iand
    //   5115: iaload
    //   5116: ior
    //   5117: istore #21
    //   5119: iload #23
    //   5121: aload #6
    //   5123: iload #26
    //   5125: iinc #26, 1
    //   5128: iaload
    //   5129: ixor
    //   5130: istore #22
    //   5132: iload #21
    //   5134: aload #14
    //   5136: iload #22
    //   5138: bipush #63
    //   5140: iand
    //   5141: iaload
    //   5142: ior
    //   5143: istore #21
    //   5145: iload #21
    //   5147: aload #12
    //   5149: iload #22
    //   5151: bipush #8
    //   5153: iushr
    //   5154: bipush #63
    //   5156: iand
    //   5157: iaload
    //   5158: ior
    //   5159: istore #21
    //   5161: iload #21
    //   5163: aload #10
    //   5165: iload #22
    //   5167: bipush #16
    //   5169: iushr
    //   5170: bipush #63
    //   5172: iand
    //   5173: iaload
    //   5174: ior
    //   5175: istore #21
    //   5177: iload #21
    //   5179: aload #8
    //   5181: iload #22
    //   5183: bipush #24
    //   5185: iushr
    //   5186: bipush #63
    //   5188: iand
    //   5189: iaload
    //   5190: ior
    //   5191: istore #21
    //   5193: iload #24
    //   5195: iload #21
    //   5197: ixor
    //   5198: istore #24
    //   5200: iload #24
    //   5202: bipush #28
    //   5204: ishl
    //   5205: iload #24
    //   5207: iconst_4
    //   5208: iushr
    //   5209: ior
    //   5210: istore #22
    //   5212: iload #22
    //   5214: aload #6
    //   5216: iload #26
    //   5218: iinc #26, 1
    //   5221: iaload
    //   5222: ixor
    //   5223: istore #22
    //   5225: aload #13
    //   5227: iload #22
    //   5229: bipush #63
    //   5231: iand
    //   5232: iaload
    //   5233: istore #21
    //   5235: iload #21
    //   5237: aload #11
    //   5239: iload #22
    //   5241: bipush #8
    //   5243: iushr
    //   5244: bipush #63
    //   5246: iand
    //   5247: iaload
    //   5248: ior
    //   5249: istore #21
    //   5251: iload #21
    //   5253: aload #9
    //   5255: iload #22
    //   5257: bipush #16
    //   5259: iushr
    //   5260: bipush #63
    //   5262: iand
    //   5263: iaload
    //   5264: ior
    //   5265: istore #21
    //   5267: iload #21
    //   5269: aload #7
    //   5271: iload #22
    //   5273: bipush #24
    //   5275: iushr
    //   5276: bipush #63
    //   5278: iand
    //   5279: iaload
    //   5280: ior
    //   5281: istore #21
    //   5283: iload #24
    //   5285: aload #6
    //   5287: iload #26
    //   5289: iinc #26, 1
    //   5292: iaload
    //   5293: ixor
    //   5294: istore #22
    //   5296: iload #21
    //   5298: aload #14
    //   5300: iload #22
    //   5302: bipush #63
    //   5304: iand
    //   5305: iaload
    //   5306: ior
    //   5307: istore #21
    //   5309: iload #21
    //   5311: aload #12
    //   5313: iload #22
    //   5315: bipush #8
    //   5317: iushr
    //   5318: bipush #63
    //   5320: iand
    //   5321: iaload
    //   5322: ior
    //   5323: istore #21
    //   5325: iload #21
    //   5327: aload #10
    //   5329: iload #22
    //   5331: bipush #16
    //   5333: iushr
    //   5334: bipush #63
    //   5336: iand
    //   5337: iaload
    //   5338: ior
    //   5339: istore #21
    //   5341: iload #21
    //   5343: aload #8
    //   5345: iload #22
    //   5347: bipush #24
    //   5349: iushr
    //   5350: bipush #63
    //   5352: iand
    //   5353: iaload
    //   5354: ior
    //   5355: istore #21
    //   5357: iload #23
    //   5359: iload #21
    //   5361: ixor
    //   5362: istore #23
    //   5364: iinc #25, 1
    //   5367: iload_2
    //   5368: ifne -> 5029
    //   5371: iload #23
    //   5373: bipush #31
    //   5375: ishl
    //   5376: iload #23
    //   5378: iconst_1
    //   5379: iushr
    //   5380: ior
    //   5381: istore #23
    //   5383: iload #24
    //   5385: iload #23
    //   5387: ixor
    //   5388: ldc -1431655766
    //   5390: iand
    //   5391: istore #22
    //   5393: iload #24
    //   5395: iload #22
    //   5397: ixor
    //   5398: istore #24
    //   5400: iload #23
    //   5402: iload #22
    //   5404: ixor
    //   5405: istore #23
    //   5407: iload #24
    //   5409: bipush #31
    //   5411: ishl
    //   5412: iload #24
    //   5414: iconst_1
    //   5415: iushr
    //   5416: ior
    //   5417: istore #24
    //   5419: iload #24
    //   5421: bipush #8
    //   5423: iushr
    //   5424: iload #23
    //   5426: ixor
    //   5427: ldc 16711935
    //   5429: iand
    //   5430: istore #22
    //   5432: iload #23
    //   5434: iload #22
    //   5436: ixor
    //   5437: istore #23
    //   5439: iload #24
    //   5441: iload #22
    //   5443: bipush #8
    //   5445: ishl
    //   5446: ixor
    //   5447: istore #24
    //   5449: iload #24
    //   5451: iconst_2
    //   5452: iushr
    //   5453: iload #23
    //   5455: ixor
    //   5456: ldc 858993459
    //   5458: iand
    //   5459: istore #22
    //   5461: iload #23
    //   5463: iload #22
    //   5465: ixor
    //   5466: istore #23
    //   5468: iload #24
    //   5470: iload #22
    //   5472: iconst_2
    //   5473: ishl
    //   5474: ixor
    //   5475: istore #24
    //   5477: iload #23
    //   5479: bipush #16
    //   5481: iushr
    //   5482: iload #24
    //   5484: ixor
    //   5485: ldc 65535
    //   5487: iand
    //   5488: istore #22
    //   5490: iload #24
    //   5492: iload #22
    //   5494: ixor
    //   5495: istore #24
    //   5497: iload #23
    //   5499: iload #22
    //   5501: bipush #16
    //   5503: ishl
    //   5504: ixor
    //   5505: istore #23
    //   5507: iload #23
    //   5509: iconst_4
    //   5510: iushr
    //   5511: iload #24
    //   5513: ixor
    //   5514: ldc 252645135
    //   5516: iand
    //   5517: istore #22
    //   5519: iload #24
    //   5521: iload #22
    //   5523: ixor
    //   5524: istore #24
    //   5526: iload #23
    //   5528: iload #22
    //   5530: iconst_4
    //   5531: ishl
    //   5532: ixor
    //   5533: istore #23
    //   5535: aload #16
    //   5537: iconst_0
    //   5538: iload #23
    //   5540: iastore
    //   5541: aload #16
    //   5543: iconst_1
    //   5544: iload #24
    //   5546: iastore
    //   5547: iload #19
    //   5549: bipush #8
    //   5551: imul
    //   5552: istore #27
    //   5554: iconst_0
    //   5555: istore #28
    //   5557: iload #28
    //   5559: iconst_2
    //   5560: if_icmpge -> 5649
    //   5563: aload #17
    //   5565: iload #27
    //   5567: iload #28
    //   5569: iconst_4
    //   5570: imul
    //   5571: iadd
    //   5572: aload #16
    //   5574: iload #28
    //   5576: iaload
    //   5577: bipush #24
    //   5579: iushr
    //   5580: i2b
    //   5581: bastore
    //   5582: aload #17
    //   5584: iload #27
    //   5586: iload #28
    //   5588: iconst_4
    //   5589: imul
    //   5590: iadd
    //   5591: iconst_1
    //   5592: iadd
    //   5593: aload #16
    //   5595: iload #28
    //   5597: iaload
    //   5598: bipush #16
    //   5600: iushr
    //   5601: i2b
    //   5602: bastore
    //   5603: aload #17
    //   5605: iload #27
    //   5607: iload #28
    //   5609: iconst_4
    //   5610: imul
    //   5611: iadd
    //   5612: iconst_2
    //   5613: iadd
    //   5614: aload #16
    //   5616: iload #28
    //   5618: iaload
    //   5619: bipush #8
    //   5621: iushr
    //   5622: i2b
    //   5623: bastore
    //   5624: aload #17
    //   5626: iload #27
    //   5628: iload #28
    //   5630: iconst_4
    //   5631: imul
    //   5632: iadd
    //   5633: iconst_3
    //   5634: iadd
    //   5635: aload #16
    //   5637: iload #28
    //   5639: iaload
    //   5640: i2b
    //   5641: bastore
    //   5642: iinc #28, 1
    //   5645: iload_2
    //   5646: ifne -> 5557
    //   5649: iinc #19, 1
    //   5652: iload_2
    //   5653: ifne -> 4734
    //   5656: aload #17
    //   5658: aload #17
    //   5660: arraylength
    //   5661: iconst_1
    //   5662: isub
    //   5663: baload
    //   5664: istore #19
    //   5666: aload #17
    //   5668: arraylength
    //   5669: iload #19
    //   5671: isub
    //   5672: newarray byte
    //   5674: astore #5
    //   5676: aload #17
    //   5678: arraylength
    //   5679: aload #5
    //   5681: arraylength
    //   5682: if_icmpge -> 5706
    //   5685: new java/lang/Exception
    //   5688: dup
    //   5689: sipush #3819
    //   5692: sipush #6566
    //   5695: invokestatic a : (II)Ljava/lang/String;
    //   5698: invokespecial <init> : (Ljava/lang/String;)V
    //   5701: athrow
    //   5702: invokestatic a : (Ljava/lang/Throwable;)Ljava/lang/Throwable;
    //   5705: athrow
    //   5706: iconst_0
    //   5707: istore #20
    //   5709: iload #20
    //   5711: aload #5
    //   5713: arraylength
    //   5714: if_icmpge -> 5734
    //   5717: aload #5
    //   5719: iload #20
    //   5721: aload #17
    //   5723: iload #20
    //   5725: baload
    //   5726: bastore
    //   5727: iinc #20, 1
    //   5730: iload_2
    //   5731: ifne -> 5709
    //   5734: new java/math/BigInteger
    //   5737: dup
    //   5738: aload #5
    //   5740: invokespecial <init> : ([B)V
    //   5743: invokevirtual abs : ()Ljava/math/BigInteger;
    //   5746: putstatic burp/Zmt_.Zl : Ljava/lang/Object;
    //   5749: sipush #3821
    //   5752: sipush #13675
    //   5755: invokestatic a : (II)Ljava/lang/String;
    //   5758: iconst_1
    //   5759: ldc burp/Ztd3
    //   5761: invokevirtual getClassLoader : ()Ljava/lang/ClassLoader;
    //   5764: invokestatic forName : (Ljava/lang/String;ZLjava/lang/ClassLoader;)Ljava/lang/Class;
    //   5767: invokevirtual getDeclaredFields : ()[Ljava/lang/reflect/Field;
    //   5770: astore #4
    //   5772: aload #4
    //   5774: arraylength
    //   5775: istore #5
    //   5777: iconst_0
    //   5778: istore #6
    //   5780: iload #6
    //   5782: iload #5
    //   5784: if_icmpge -> 5922
    //   5787: aload #4
    //   5789: iload #6
    //   5791: aaload
    //   5792: astore #7
    //   5794: aload #7
    //   5796: invokevirtual getModifiers : ()I
    //   5799: invokestatic isStatic : (I)Z
    //   5802: ifne -> 5812
    //   5805: goto -> 5915
    //   5808: invokestatic a : (Ljava/lang/Throwable;)Ljava/lang/Throwable;
    //   5811: athrow
    //   5812: aload #7
    //   5814: invokevirtual getType : ()Ljava/lang/Class;
    //   5817: astore #8
    //   5819: aload #8
    //   5821: ifnull -> 5902
    //   5824: aload #8
    //   5826: invokevirtual isPrimitive : ()Z
    //   5829: ifne -> 5902
    //   5832: goto -> 5839
    //   5835: invokestatic a : (Ljava/lang/Throwable;)Ljava/lang/Throwable;
    //   5838: athrow
    //   5839: aload #8
    //   5841: invokevirtual getPackage : ()Ljava/lang/Package;
    //   5844: ifnull -> 5902
    //   5847: goto -> 5854
    //   5850: invokestatic a : (Ljava/lang/Throwable;)Ljava/lang/Throwable;
    //   5853: athrow
    //   5854: aload #8
    //   5856: invokevirtual getPackage : ()Ljava/lang/Package;
    //   5859: invokevirtual getName : ()Ljava/lang/String;
    //   5862: ifnull -> 5902
    //   5865: goto -> 5872
    //   5868: invokestatic a : (Ljava/lang/Throwable;)Ljava/lang/Throwable;
    //   5871: athrow
    //   5872: aload #8
    //   5874: invokevirtual getPackage : ()Ljava/lang/Package;
    //   5877: invokevirtual getName : ()Ljava/lang/String;
    //   5880: sipush #3815
    //   5883: sipush #-15868
    //   5886: invokestatic a : (II)Ljava/lang/String;
    //   5889: invokevirtual startsWith : (Ljava/lang/String;)Z
    //   5892: ifne -> 5902
    //   5895: goto -> 5902
    //   5898: invokestatic a : (Ljava/lang/Throwable;)Ljava/lang/Throwable;
    //   5901: athrow
    //   5902: aload #7
    //   5904: iconst_1
    //   5905: invokevirtual setAccessible : (Z)V
    //   5908: aload #7
    //   5910: aconst_null
    //   5911: invokevirtual get : (Ljava/lang/Object;)Ljava/lang/Object;
    //   5914: pop
    //   5915: iinc #6, 1
    //   5918: iload_2
    //   5919: ifne -> 5780
    //   5922: sipush #3820
    //   5925: sipush #-14035
    //   5928: invokestatic a : (II)Ljava/lang/String;
    //   5931: invokestatic forName : (Ljava/lang/String;)Ljava/lang/Class;
    //   5934: invokevirtual getDeclaredMethods : ()[Ljava/lang/reflect/Method;
    //   5937: astore #4
    //   5939: aload #4
    //   5941: arraylength
    //   5942: istore #5
    //   5944: iconst_0
    //   5945: istore #6
    //   5947: iload #6
    //   5949: iload #5
    //   5951: if_icmpge -> 6084
    //   5954: aload #4
    //   5956: iload #6
    //   5958: aaload
    //   5959: astore #7
    //   5961: aload #7
    //   5963: invokevirtual getParameterTypes : ()[Ljava/lang/Class;
    //   5966: pop
    //   5967: aload #7
    //   5969: invokevirtual getModifiers : ()I
    //   5972: invokestatic isStatic : (I)Z
    //   5975: ifeq -> 6070
    //   5978: aload #7
    //   5980: invokevirtual getParameterTypes : ()[Ljava/lang/Class;
    //   5983: arraylength
    //   5984: iconst_2
    //   5985: if_icmpne -> 6070
    //   5988: goto -> 5995
    //   5991: invokestatic a : (Ljava/lang/Throwable;)Ljava/lang/Throwable;
    //   5994: athrow
    //   5995: aload #7
    //   5997: invokevirtual getReturnType : ()Ljava/lang/Class;
    //   6000: getstatic java/lang/Void.TYPE : Ljava/lang/Class;
    //   6003: invokevirtual equals : (Ljava/lang/Object;)Z
    //   6006: ifeq -> 6070
    //   6009: goto -> 6016
    //   6012: invokestatic a : (Ljava/lang/Throwable;)Ljava/lang/Throwable;
    //   6015: athrow
    //   6016: aload #7
    //   6018: iconst_1
    //   6019: invokevirtual setAccessible : (Z)V
    //   6022: aload #7
    //   6024: aconst_null
    //   6025: iconst_2
    //   6026: anewarray java/lang/Object
    //   6029: dup
    //   6030: iconst_0
    //   6031: aload_0
    //   6032: aastore
    //   6033: dup
    //   6034: iconst_1
    //   6035: aload_1
    //   6036: ifnonnull -> 6054
    //   6039: goto -> 6046
    //   6042: invokestatic a : (Ljava/lang/Throwable;)Ljava/lang/Throwable;
    //   6045: athrow
    //   6046: aload_1
    //   6047: goto -> 6061
    //   6050: invokestatic a : (Ljava/lang/Throwable;)Ljava/lang/Throwable;
    //   6053: athrow
    //   6054: aload_1
    //   6055: checkcast [B
    //   6058: invokevirtual clone : ()Ljava/lang/Object;
    //   6061: aastore
    //   6062: invokevirtual invoke : (Ljava/lang/Object;[Ljava/lang/Object;)Ljava/lang/Object;
    //   6065: pop
    //   6066: iload_2
    //   6067: ifne -> 6084
    //   6070: iinc #6, 1
    //   6073: iload_2
    //   6074: ifne -> 5947
    //   6077: goto -> 6084
    //   6080: invokestatic a : (Ljava/lang/Throwable;)Ljava/lang/Throwable;
    //   6083: athrow
    //   6084: iconst_0
    //   6085: istore #4
    //   6087: getstatic burp/Zzac.ZE : Ljava/lang/String;
    //   6090: getstatic burp/Ztr5.ZZ : Ljava/lang/Object;
    //   6093: checkcast java/math/BigInteger
    //   6096: invokevirtual intValue : ()I
    //   6099: bipush #32
    //   6101: irem
    //   6102: invokestatic abs : (I)I
    //   6105: invokevirtual charAt : (I)C
    //   6108: getstatic burp/Zzac.ZE : Ljava/lang/String;
    //   6111: getstatic burp/Zm83.Zl : Ljava/lang/Object;
    //   6114: checkcast java/math/BigInteger
    //   6117: invokevirtual intValue : ()I
    //   6120: bipush #32
    //   6122: irem
    //   6123: invokestatic abs : (I)I
    //   6126: invokevirtual charAt : (I)C
    //   6129: if_icmpgt -> 6474
    //   6132: sipush #3826
    //   6135: sipush #-29372
    //   6138: invokestatic a : (II)Ljava/lang/String;
    //   6141: iconst_1
    //   6142: ldc burp/Zb6e
    //   6144: invokevirtual getClassLoader : ()Ljava/lang/ClassLoader;
    //   6147: invokestatic forName : (Ljava/lang/String;ZLjava/lang/ClassLoader;)Ljava/lang/Class;
    //   6150: invokevirtual getDeclaredFields : ()[Ljava/lang/reflect/Field;
    //   6153: astore #5
    //   6155: aload #5
    //   6157: arraylength
    //   6158: istore #6
    //   6160: iconst_0
    //   6161: istore #7
    //   6163: iload #7
    //   6165: iload #6
    //   6167: if_icmpge -> 6305
    //   6170: aload #5
    //   6172: iload #7
    //   6174: aaload
    //   6175: astore #8
    //   6177: aload #8
    //   6179: invokevirtual getModifiers : ()I
    //   6182: invokestatic isStatic : (I)Z
    //   6185: ifne -> 6195
    //   6188: goto -> 6298
    //   6191: invokestatic a : (Ljava/lang/Throwable;)Ljava/lang/Throwable;
    //   6194: athrow
    //   6195: aload #8
    //   6197: invokevirtual getType : ()Ljava/lang/Class;
    //   6200: astore #9
    //   6202: aload #9
    //   6204: ifnull -> 6285
    //   6207: aload #9
    //   6209: invokevirtual isPrimitive : ()Z
    //   6212: ifne -> 6285
    //   6215: goto -> 6222
    //   6218: invokestatic a : (Ljava/lang/Throwable;)Ljava/lang/Throwable;
    //   6221: athrow
    //   6222: aload #9
    //   6224: invokevirtual getPackage : ()Ljava/lang/Package;
    //   6227: ifnull -> 6285
    //   6230: goto -> 6237
    //   6233: invokestatic a : (Ljava/lang/Throwable;)Ljava/lang/Throwable;
    //   6236: athrow
    //   6237: aload #9
    //   6239: invokevirtual getPackage : ()Ljava/lang/Package;
    //   6242: invokevirtual getName : ()Ljava/lang/String;
    //   6245: ifnull -> 6285
    //   6248: goto -> 6255
    //   6251: invokestatic a : (Ljava/lang/Throwable;)Ljava/lang/Throwable;
    //   6254: athrow
    //   6255: aload #9
    //   6257: invokevirtual getPackage : ()Ljava/lang/Package;
    //   6260: invokevirtual getName : ()Ljava/lang/String;
    //   6263: sipush #3811
    //   6266: sipush #18153
    //   6269: invokestatic a : (II)Ljava/lang/String;
    //   6272: invokevirtual startsWith : (Ljava/lang/String;)Z
    //   6275: ifne -> 6285
    //   6278: goto -> 6285
    //   6281: invokestatic a : (Ljava/lang/Throwable;)Ljava/lang/Throwable;
    //   6284: athrow
    //   6285: aload #8
    //   6287: iconst_1
    //   6288: invokevirtual setAccessible : (Z)V
    //   6291: aload #8
    //   6293: aconst_null
    //   6294: invokevirtual get : (Ljava/lang/Object;)Ljava/lang/Object;
    //   6297: pop
    //   6298: iinc #7, 1
    //   6301: iload_2
    //   6302: ifne -> 6163
    //   6305: sipush #3829
    //   6308: sipush #-10718
    //   6311: invokestatic a : (II)Ljava/lang/String;
    //   6314: invokestatic forName : (Ljava/lang/String;)Ljava/lang/Class;
    //   6317: invokevirtual getDeclaredMethods : ()[Ljava/lang/reflect/Method;
    //   6320: astore #5
    //   6322: aload #5
    //   6324: arraylength
    //   6325: istore #6
    //   6327: iconst_0
    //   6328: istore #7
    //   6330: iload #7
    //   6332: iload #6
    //   6334: if_icmpge -> 6471
    //   6337: aload #5
    //   6339: iload #7
    //   6341: aaload
    //   6342: astore #8
    //   6344: aload #8
    //   6346: invokevirtual getParameterTypes : ()[Ljava/lang/Class;
    //   6349: pop
    //   6350: aload #8
    //   6352: invokevirtual getModifiers : ()I
    //   6355: invokestatic isStatic : (I)Z
    //   6358: ifeq -> 6457
    //   6361: aload #8
    //   6363: invokevirtual getParameterTypes : ()[Ljava/lang/Class;
    //   6366: arraylength
    //   6367: iconst_2
    //   6368: if_icmpne -> 6457
    //   6371: goto -> 6378
    //   6374: invokestatic a : (Ljava/lang/Throwable;)Ljava/lang/Throwable;
    //   6377: athrow
    //   6378: aload #8
    //   6380: invokevirtual getReturnType : ()Ljava/lang/Class;
    //   6383: getstatic java/lang/Boolean.TYPE : Ljava/lang/Class;
    //   6386: if_acmpne -> 6457
    //   6389: goto -> 6396
    //   6392: invokestatic a : (Ljava/lang/Throwable;)Ljava/lang/Throwable;
    //   6395: athrow
    //   6396: aload #8
    //   6398: iconst_1
    //   6399: invokevirtual setAccessible : (Z)V
    //   6402: aload #8
    //   6404: aconst_null
    //   6405: iconst_2
    //   6406: anewarray java/lang/Object
    //   6409: dup
    //   6410: iconst_0
    //   6411: aload_0
    //   6412: aastore
    //   6413: dup
    //   6414: iconst_1
    //   6415: aload_1
    //   6416: ifnonnull -> 6434
    //   6419: goto -> 6426
    //   6422: invokestatic a : (Ljava/lang/Throwable;)Ljava/lang/Throwable;
    //   6425: athrow
    //   6426: aload_1
    //   6427: goto -> 6441
    //   6430: invokestatic a : (Ljava/lang/Throwable;)Ljava/lang/Throwable;
    //   6433: athrow
    //   6434: aload_1
    //   6435: checkcast [B
    //   6438: invokevirtual clone : ()Ljava/lang/Object;
    //   6441: aastore
    //   6442: invokevirtual invoke : (Ljava/lang/Object;[Ljava/lang/Object;)Ljava/lang/Object;
    //   6445: checkcast java/lang/Boolean
    //   6448: invokevirtual booleanValue : ()Z
    //   6451: istore #4
    //   6453: iload_2
    //   6454: ifne -> 6471
    //   6457: iinc #7, 1
    //   6460: iload_2
    //   6461: ifne -> 6330
    //   6464: goto -> 6471
    //   6467: invokestatic a : (Ljava/lang/Throwable;)Ljava/lang/Throwable;
    //   6470: athrow
    //   6471: goto -> 6813
    //   6474: sipush #3828
    //   6477: sipush #4217
    //   6480: invokestatic a : (II)Ljava/lang/String;
    //   6483: iconst_1
    //   6484: ldc burp/Zr3q
    //   6486: invokevirtual getClassLoader : ()Ljava/lang/ClassLoader;
    //   6489: invokestatic forName : (Ljava/lang/String;ZLjava/lang/ClassLoader;)Ljava/lang/Class;
    //   6492: invokevirtual getDeclaredFields : ()[Ljava/lang/reflect/Field;
    //   6495: astore #5
    //   6497: aload #5
    //   6499: arraylength
    //   6500: istore #6
    //   6502: iconst_0
    //   6503: istore #7
    //   6505: iload #7
    //   6507: iload #6
    //   6509: if_icmpge -> 6647
    //   6512: aload #5
    //   6514: iload #7
    //   6516: aaload
    //   6517: astore #8
    //   6519: aload #8
    //   6521: invokevirtual getModifiers : ()I
    //   6524: invokestatic isStatic : (I)Z
    //   6527: ifne -> 6537
    //   6530: goto -> 6640
    //   6533: invokestatic a : (Ljava/lang/Throwable;)Ljava/lang/Throwable;
    //   6536: athrow
    //   6537: aload #8
    //   6539: invokevirtual getType : ()Ljava/lang/Class;
    //   6542: astore #9
    //   6544: aload #9
    //   6546: ifnull -> 6627
    //   6549: aload #9
    //   6551: invokevirtual isPrimitive : ()Z
    //   6554: ifne -> 6627
    //   6557: goto -> 6564
    //   6560: invokestatic a : (Ljava/lang/Throwable;)Ljava/lang/Throwable;
    //   6563: athrow
    //   6564: aload #9
    //   6566: invokevirtual getPackage : ()Ljava/lang/Package;
    //   6569: ifnull -> 6627
    //   6572: goto -> 6579
    //   6575: invokestatic a : (Ljava/lang/Throwable;)Ljava/lang/Throwable;
    //   6578: athrow
    //   6579: aload #9
    //   6581: invokevirtual getPackage : ()Ljava/lang/Package;
    //   6584: invokevirtual getName : ()Ljava/lang/String;
    //   6587: ifnull -> 6627
    //   6590: goto -> 6597
    //   6593: invokestatic a : (Ljava/lang/Throwable;)Ljava/lang/Throwable;
    //   6596: athrow
    //   6597: aload #9
    //   6599: invokevirtual getPackage : ()Ljava/lang/Package;
    //   6602: invokevirtual getName : ()Ljava/lang/String;
    //   6605: sipush #3811
    //   6608: sipush #18153
    //   6611: invokestatic a : (II)Ljava/lang/String;
    //   6614: invokevirtual startsWith : (Ljava/lang/String;)Z
    //   6617: ifne -> 6627
    //   6620: goto -> 6627
    //   6623: invokestatic a : (Ljava/lang/Throwable;)Ljava/lang/Throwable;
    //   6626: athrow
    //   6627: aload #8
    //   6629: iconst_1
    //   6630: invokevirtual setAccessible : (Z)V
    //   6633: aload #8
    //   6635: aconst_null
    //   6636: invokevirtual get : (Ljava/lang/Object;)Ljava/lang/Object;
    //   6639: pop
    //   6640: iinc #7, 1
    //   6643: iload_2
    //   6644: ifne -> 6505
    //   6647: sipush #3834
    //   6650: sipush #-22435
    //   6653: invokestatic a : (II)Ljava/lang/String;
    //   6656: invokestatic forName : (Ljava/lang/String;)Ljava/lang/Class;
    //   6659: invokevirtual getDeclaredMethods : ()[Ljava/lang/reflect/Method;
    //   6662: astore #5
    //   6664: aload #5
    //   6666: arraylength
    //   6667: istore #6
    //   6669: iconst_0
    //   6670: istore #7
    //   6672: iload #7
    //   6674: iload #6
    //   6676: if_icmpge -> 6813
    //   6679: aload #5
    //   6681: iload #7
    //   6683: aaload
    //   6684: astore #8
    //   6686: aload #8
    //   6688: invokevirtual getParameterTypes : ()[Ljava/lang/Class;
    //   6691: pop
    //   6692: aload #8
    //   6694: invokevirtual getModifiers : ()I
    //   6697: invokestatic isStatic : (I)Z
    //   6700: ifeq -> 6799
    //   6703: aload #8
    //   6705: invokevirtual getParameterTypes : ()[Ljava/lang/Class;
    //   6708: arraylength
    //   6709: iconst_2
    //   6710: if_icmpne -> 6799
    //   6713: goto -> 6720
    //   6716: invokestatic a : (Ljava/lang/Throwable;)Ljava/lang/Throwable;
    //   6719: athrow
    //   6720: aload #8
    //   6722: invokevirtual getReturnType : ()Ljava/lang/Class;
    //   6725: getstatic java/lang/Boolean.TYPE : Ljava/lang/Class;
    //   6728: if_acmpne -> 6799
    //   6731: goto -> 6738
    //   6734: invokestatic a : (Ljava/lang/Throwable;)Ljava/lang/Throwable;
    //   6737: athrow
    //   6738: aload #8
    //   6740: iconst_1
    //   6741: invokevirtual setAccessible : (Z)V
    //   6744: aload #8
    //   6746: aconst_null
    //   6747: iconst_2
    //   6748: anewarray java/lang/Object
    //   6751: dup
    //   6752: iconst_0
    //   6753: aload_0
    //   6754: aastore
    //   6755: dup
    //   6756: iconst_1
    //   6757: aload_1
    //   6758: ifnonnull -> 6776
    //   6761: goto -> 6768
    //   6764: invokestatic a : (Ljava/lang/Throwable;)Ljava/lang/Throwable;
    //   6767: athrow
    //   6768: aload_1
    //   6769: goto -> 6783
    //   6772: invokestatic a : (Ljava/lang/Throwable;)Ljava/lang/Throwable;
    //   6775: athrow
    //   6776: aload_1
    //   6777: checkcast [B
    //   6780: invokevirtual clone : ()Ljava/lang/Object;
    //   6783: aastore
    //   6784: invokevirtual invoke : (Ljava/lang/Object;[Ljava/lang/Object;)Ljava/lang/Object;
    //   6787: checkcast java/lang/Boolean
    //   6790: invokevirtual booleanValue : ()Z
    //   6793: istore #4
    //   6795: iload_2
    //   6796: ifne -> 6813
    //   6799: iinc #7, 1
    //   6802: iload_2
    //   6803: ifne -> 6672
    //   6806: goto -> 6813
    //   6809: invokestatic a : (Ljava/lang/Throwable;)Ljava/lang/Throwable;
    //   6812: athrow
    //   6813: iload #4
    //   6815: ifeq -> 6821
    //   6818: iload #4
    //   6820: ireturn
    //   6821: getstatic burp/Zz3b.Zi : Ljava/lang/String;
    //   6824: getstatic burp/Zm63.ZT : Ljava/lang/Object;
    //   6827: checkcast java/math/BigInteger
    //   6830: invokevirtual intValue : ()I
    //   6833: bipush #32
    //   6835: irem
    //   6836: invokestatic abs : (I)I
    //   6839: invokevirtual charAt : (I)C
    //   6842: getstatic burp/Zs4g.ZV : Ljava/lang/String;
    //   6845: getstatic burp/Ztq8.Zm : Ljava/lang/Object;
    //   6848: checkcast java/math/BigInteger
    //   6851: invokevirtual intValue : ()I
    //   6854: bipush #32
    //   6856: irem
    //   6857: invokestatic abs : (I)I
    //   6860: invokevirtual charAt : (I)C
    //   6863: if_icmpgt -> 7209
    //   6866: sipush #3830
    //   6869: sipush #14458
    //   6872: invokestatic a : (II)Ljava/lang/String;
    //   6875: iconst_1
    //   6876: ldc burp/Zrjg
    //   6878: invokevirtual getClassLoader : ()Ljava/lang/ClassLoader;
    //   6881: invokestatic forName : (Ljava/lang/String;ZLjava/lang/ClassLoader;)Ljava/lang/Class;
    //   6884: invokevirtual getDeclaredFields : ()[Ljava/lang/reflect/Field;
    //   6887: astore #5
    //   6889: aload #5
    //   6891: arraylength
    //   6892: istore #6
    //   6894: iconst_0
    //   6895: istore #7
    //   6897: iload #7
    //   6899: iload #6
    //   6901: if_icmpge -> 7039
    //   6904: aload #5
    //   6906: iload #7
    //   6908: aaload
    //   6909: astore #8
    //   6911: aload #8
    //   6913: invokevirtual getModifiers : ()I
    //   6916: invokestatic isStatic : (I)Z
    //   6919: ifne -> 6929
    //   6922: goto -> 7032
    //   6925: invokestatic a : (Ljava/lang/Throwable;)Ljava/lang/Throwable;
    //   6928: athrow
    //   6929: aload #8
    //   6931: invokevirtual getType : ()Ljava/lang/Class;
    //   6934: astore #9
    //   6936: aload #9
    //   6938: ifnull -> 7019
    //   6941: aload #9
    //   6943: invokevirtual isPrimitive : ()Z
    //   6946: ifne -> 7019
    //   6949: goto -> 6956
    //   6952: invokestatic a : (Ljava/lang/Throwable;)Ljava/lang/Throwable;
    //   6955: athrow
    //   6956: aload #9
    //   6958: invokevirtual getPackage : ()Ljava/lang/Package;
    //   6961: ifnull -> 7019
    //   6964: goto -> 6971
    //   6967: invokestatic a : (Ljava/lang/Throwable;)Ljava/lang/Throwable;
    //   6970: athrow
    //   6971: aload #9
    //   6973: invokevirtual getPackage : ()Ljava/lang/Package;
    //   6976: invokevirtual getName : ()Ljava/lang/String;
    //   6979: ifnull -> 7019
    //   6982: goto -> 6989
    //   6985: invokestatic a : (Ljava/lang/Throwable;)Ljava/lang/Throwable;
    //   6988: athrow
    //   6989: aload #9
    //   6991: invokevirtual getPackage : ()Ljava/lang/Package;
    //   6994: invokevirtual getName : ()Ljava/lang/String;
    //   6997: sipush #3811
    //   7000: sipush #18153
    //   7003: invokestatic a : (II)Ljava/lang/String;
    //   7006: invokevirtual startsWith : (Ljava/lang/String;)Z
    //   7009: ifne -> 7019
    //   7012: goto -> 7019
    //   7015: invokestatic a : (Ljava/lang/Throwable;)Ljava/lang/Throwable;
    //   7018: athrow
    //   7019: aload #8
    //   7021: iconst_1
    //   7022: invokevirtual setAccessible : (Z)V
    //   7025: aload #8
    //   7027: aconst_null
    //   7028: invokevirtual get : (Ljava/lang/Object;)Ljava/lang/Object;
    //   7031: pop
    //   7032: iinc #7, 1
    //   7035: iload_2
    //   7036: ifne -> 6897
    //   7039: sipush #3832
    //   7042: sipush #-31912
    //   7045: invokestatic a : (II)Ljava/lang/String;
    //   7048: invokestatic forName : (Ljava/lang/String;)Ljava/lang/Class;
    //   7051: invokevirtual getDeclaredMethods : ()[Ljava/lang/reflect/Method;
    //   7054: astore #5
    //   7056: aload #5
    //   7058: arraylength
    //   7059: istore #6
    //   7061: iconst_0
    //   7062: istore #7
    //   7064: iload #7
    //   7066: iload #6
    //   7068: if_icmpge -> 7205
    //   7071: aload #5
    //   7073: iload #7
    //   7075: aaload
    //   7076: astore #8
    //   7078: aload #8
    //   7080: invokevirtual getParameterTypes : ()[Ljava/lang/Class;
    //   7083: pop
    //   7084: aload #8
    //   7086: invokevirtual getModifiers : ()I
    //   7089: invokestatic isStatic : (I)Z
    //   7092: ifeq -> 7191
    //   7095: aload #8
    //   7097: invokevirtual getParameterTypes : ()[Ljava/lang/Class;
    //   7100: arraylength
    //   7101: iconst_2
    //   7102: if_icmpne -> 7191
    //   7105: goto -> 7112
    //   7108: invokestatic a : (Ljava/lang/Throwable;)Ljava/lang/Throwable;
    //   7111: athrow
    //   7112: aload #8
    //   7114: invokevirtual getReturnType : ()Ljava/lang/Class;
    //   7117: getstatic java/lang/Boolean.TYPE : Ljava/lang/Class;
    //   7120: if_acmpne -> 7191
    //   7123: goto -> 7130
    //   7126: invokestatic a : (Ljava/lang/Throwable;)Ljava/lang/Throwable;
    //   7129: athrow
    //   7130: aload #8
    //   7132: iconst_1
    //   7133: invokevirtual setAccessible : (Z)V
    //   7136: aload #8
    //   7138: aconst_null
    //   7139: iconst_2
    //   7140: anewarray java/lang/Object
    //   7143: dup
    //   7144: iconst_0
    //   7145: aload_0
    //   7146: aastore
    //   7147: dup
    //   7148: iconst_1
    //   7149: aload_1
    //   7150: ifnonnull -> 7168
    //   7153: goto -> 7160
    //   7156: invokestatic a : (Ljava/lang/Throwable;)Ljava/lang/Throwable;
    //   7159: athrow
    //   7160: aload_1
    //   7161: goto -> 7175
    //   7164: invokestatic a : (Ljava/lang/Throwable;)Ljava/lang/Throwable;
    //   7167: athrow
    //   7168: aload_1
    //   7169: checkcast [B
    //   7172: invokevirtual clone : ()Ljava/lang/Object;
    //   7175: aastore
    //   7176: invokevirtual invoke : (Ljava/lang/Object;[Ljava/lang/Object;)Ljava/lang/Object;
    //   7179: checkcast java/lang/Boolean
    //   7182: invokevirtual booleanValue : ()Z
    //   7185: istore #4
    //   7187: iload_2
    //   7188: ifne -> 7205
    //   7191: iinc #7, 1
    //   7194: iload_2
    //   7195: ifne -> 7064
    //   7198: goto -> 7205
    //   7201: invokestatic a : (Ljava/lang/Throwable;)Ljava/lang/Throwable;
    //   7204: athrow
    //   7205: iload_2
    //   7206: ifne -> 7548
    //   7209: sipush #3813
    //   7212: sipush #-11184
    //   7215: invokestatic a : (II)Ljava/lang/String;
    //   7218: iconst_1
    //   7219: ldc burp/Zegk
    //   7221: invokevirtual getClassLoader : ()Ljava/lang/ClassLoader;
    //   7224: invokestatic forName : (Ljava/lang/String;ZLjava/lang/ClassLoader;)Ljava/lang/Class;
    //   7227: invokevirtual getDeclaredFields : ()[Ljava/lang/reflect/Field;
    //   7230: astore #5
    //   7232: aload #5
    //   7234: arraylength
    //   7235: istore #6
    //   7237: iconst_0
    //   7238: istore #7
    //   7240: iload #7
    //   7242: iload #6
    //   7244: if_icmpge -> 7382
    //   7247: aload #5
    //   7249: iload #7
    //   7251: aaload
    //   7252: astore #8
    //   7254: aload #8
    //   7256: invokevirtual getModifiers : ()I
    //   7259: invokestatic isStatic : (I)Z
    //   7262: ifne -> 7272
    //   7265: goto -> 7375
    //   7268: invokestatic a : (Ljava/lang/Throwable;)Ljava/lang/Throwable;
    //   7271: athrow
    //   7272: aload #8
    //   7274: invokevirtual getType : ()Ljava/lang/Class;
    //   7277: astore #9
    //   7279: aload #9
    //   7281: ifnull -> 7362
    //   7284: aload #9
    //   7286: invokevirtual isPrimitive : ()Z
    //   7289: ifne -> 7362
    //   7292: goto -> 7299
    //   7295: invokestatic a : (Ljava/lang/Throwable;)Ljava/lang/Throwable;
    //   7298: athrow
    //   7299: aload #9
    //   7301: invokevirtual getPackage : ()Ljava/lang/Package;
    //   7304: ifnull -> 7362
    //   7307: goto -> 7314
    //   7310: invokestatic a : (Ljava/lang/Throwable;)Ljava/lang/Throwable;
    //   7313: athrow
    //   7314: aload #9
    //   7316: invokevirtual getPackage : ()Ljava/lang/Package;
    //   7319: invokevirtual getName : ()Ljava/lang/String;
    //   7322: ifnull -> 7362
    //   7325: goto -> 7332
    //   7328: invokestatic a : (Ljava/lang/Throwable;)Ljava/lang/Throwable;
    //   7331: athrow
    //   7332: aload #9
    //   7334: invokevirtual getPackage : ()Ljava/lang/Package;
    //   7337: invokevirtual getName : ()Ljava/lang/String;
    //   7340: sipush #3811
    //   7343: sipush #18153
    //   7346: invokestatic a : (II)Ljava/lang/String;
    //   7349: invokevirtual startsWith : (Ljava/lang/String;)Z
    //   7352: ifne -> 7362
    //   7355: goto -> 7362
    //   7358: invokestatic a : (Ljava/lang/Throwable;)Ljava/lang/Throwable;
    //   7361: athrow
    //   7362: aload #8
    //   7364: iconst_1
    //   7365: invokevirtual setAccessible : (Z)V
    //   7368: aload #8
    //   7370: aconst_null
    //   7371: invokevirtual get : (Ljava/lang/Object;)Ljava/lang/Object;
    //   7374: pop
    //   7375: iinc #7, 1
    //   7378: iload_2
    //   7379: ifne -> 7240
    //   7382: sipush #3816
    //   7385: sipush #-20122
    //   7388: invokestatic a : (II)Ljava/lang/String;
    //   7391: invokestatic forName : (Ljava/lang/String;)Ljava/lang/Class;
    //   7394: invokevirtual getDeclaredMethods : ()[Ljava/lang/reflect/Method;
    //   7397: astore #5
    //   7399: aload #5
    //   7401: arraylength
    //   7402: istore #6
    //   7404: iconst_0
    //   7405: istore #7
    //   7407: iload #7
    //   7409: iload #6
    //   7411: if_icmpge -> 7548
    //   7414: aload #5
    //   7416: iload #7
    //   7418: aaload
    //   7419: astore #8
    //   7421: aload #8
    //   7423: invokevirtual getParameterTypes : ()[Ljava/lang/Class;
    //   7426: pop
    //   7427: aload #8
    //   7429: invokevirtual getModifiers : ()I
    //   7432: invokestatic isStatic : (I)Z
    //   7435: ifeq -> 7534
    //   7438: aload #8
    //   7440: invokevirtual getParameterTypes : ()[Ljava/lang/Class;
    //   7443: arraylength
    //   7444: iconst_2
    //   7445: if_icmpne -> 7534
    //   7448: goto -> 7455
    //   7451: invokestatic a : (Ljava/lang/Throwable;)Ljava/lang/Throwable;
    //   7454: athrow
    //   7455: aload #8
    //   7457: invokevirtual getReturnType : ()Ljava/lang/Class;
    //   7460: getstatic java/lang/Boolean.TYPE : Ljava/lang/Class;
    //   7463: if_acmpne -> 7534
    //   7466: goto -> 7473
    //   7469: invokestatic a : (Ljava/lang/Throwable;)Ljava/lang/Throwable;
    //   7472: athrow
    //   7473: aload #8
    //   7475: iconst_1
    //   7476: invokevirtual setAccessible : (Z)V
    //   7479: aload #8
    //   7481: aconst_null
    //   7482: iconst_2
    //   7483: anewarray java/lang/Object
    //   7486: dup
    //   7487: iconst_0
    //   7488: aload_0
    //   7489: aastore
    //   7490: dup
    //   7491: iconst_1
    //   7492: aload_1
    //   7493: ifnonnull -> 7511
    //   7496: goto -> 7503
    //   7499: invokestatic a : (Ljava/lang/Throwable;)Ljava/lang/Throwable;
    //   7502: athrow
    //   7503: aload_1
    //   7504: goto -> 7518
    //   7507: invokestatic a : (Ljava/lang/Throwable;)Ljava/lang/Throwable;
    //   7510: athrow
    //   7511: aload_1
    //   7512: checkcast [B
    //   7515: invokevirtual clone : ()Ljava/lang/Object;
    //   7518: aastore
    //   7519: invokevirtual invoke : (Ljava/lang/Object;[Ljava/lang/Object;)Ljava/lang/Object;
    //   7522: checkcast java/lang/Boolean
    //   7525: invokevirtual booleanValue : ()Z
    //   7528: istore #4
    //   7530: iload_2
    //   7531: ifne -> 7548
    //   7534: iinc #7, 1
    //   7537: iload_2
    //   7538: ifne -> 7407
    //   7541: goto -> 7548
    //   7544: invokestatic a : (Ljava/lang/Throwable;)Ljava/lang/Throwable;
    //   7547: athrow
    //   7548: iload #4
    //   7550: ifeq -> 7556
    //   7553: iload #4
    //   7555: ireturn
    //   7556: getstatic burp/Zeig.Zg : Ljava/lang/String;
    //   7559: getstatic burp/Zb2n.ZR : Ljava/lang/Object;
    //   7562: checkcast java/math/BigInteger
    //   7565: invokevirtual intValue : ()I
    //   7568: bipush #32
    //   7570: irem
    //   7571: invokestatic abs : (I)I
    //   7574: invokevirtual charAt : (I)C
    //   7577: getstatic burp/Zz4a.ZC : Ljava/lang/String;
    //   7580: getstatic burp/Zx63.ZX : Ljava/lang/Object;
    //   7583: checkcast java/math/BigInteger
    //   7586: invokevirtual intValue : ()I
    //   7589: bipush #32
    //   7591: irem
    //   7592: invokestatic abs : (I)I
    //   7595: invokevirtual charAt : (I)C
    //   7598: if_icmpgt -> 7944
    //   7601: sipush #3823
    //   7604: sipush #-2994
    //   7607: invokestatic a : (II)Ljava/lang/String;
    //   7610: iconst_1
    //   7611: ldc burp/Zmvk
    //   7613: invokevirtual getClassLoader : ()Ljava/lang/ClassLoader;
    //   7616: invokestatic forName : (Ljava/lang/String;ZLjava/lang/ClassLoader;)Ljava/lang/Class;
    //   7619: invokevirtual getDeclaredFields : ()[Ljava/lang/reflect/Field;
    //   7622: astore #5
    //   7624: aload #5
    //   7626: arraylength
    //   7627: istore #6
    //   7629: iconst_0
    //   7630: istore #7
    //   7632: iload #7
    //   7634: iload #6
    //   7636: if_icmpge -> 7774
    //   7639: aload #5
    //   7641: iload #7
    //   7643: aaload
    //   7644: astore #8
    //   7646: aload #8
    //   7648: invokevirtual getModifiers : ()I
    //   7651: invokestatic isStatic : (I)Z
    //   7654: ifne -> 7664
    //   7657: goto -> 7767
    //   7660: invokestatic a : (Ljava/lang/Throwable;)Ljava/lang/Throwable;
    //   7663: athrow
    //   7664: aload #8
    //   7666: invokevirtual getType : ()Ljava/lang/Class;
    //   7669: astore #9
    //   7671: aload #9
    //   7673: ifnull -> 7754
    //   7676: aload #9
    //   7678: invokevirtual isPrimitive : ()Z
    //   7681: ifne -> 7754
    //   7684: goto -> 7691
    //   7687: invokestatic a : (Ljava/lang/Throwable;)Ljava/lang/Throwable;
    //   7690: athrow
    //   7691: aload #9
    //   7693: invokevirtual getPackage : ()Ljava/lang/Package;
    //   7696: ifnull -> 7754
    //   7699: goto -> 7706
    //   7702: invokestatic a : (Ljava/lang/Throwable;)Ljava/lang/Throwable;
    //   7705: athrow
    //   7706: aload #9
    //   7708: invokevirtual getPackage : ()Ljava/lang/Package;
    //   7711: invokevirtual getName : ()Ljava/lang/String;
    //   7714: ifnull -> 7754
    //   7717: goto -> 7724
    //   7720: invokestatic a : (Ljava/lang/Throwable;)Ljava/lang/Throwable;
    //   7723: athrow
    //   7724: aload #9
    //   7726: invokevirtual getPackage : ()Ljava/lang/Package;
    //   7729: invokevirtual getName : ()Ljava/lang/String;
    //   7732: sipush #3811
    //   7735: sipush #18153
    //   7738: invokestatic a : (II)Ljava/lang/String;
    //   7741: invokevirtual startsWith : (Ljava/lang/String;)Z
    //   7744: ifne -> 7754
    //   7747: goto -> 7754
    //   7750: invokestatic a : (Ljava/lang/Throwable;)Ljava/lang/Throwable;
    //   7753: athrow
    //   7754: aload #8
    //   7756: iconst_1
    //   7757: invokevirtual setAccessible : (Z)V
    //   7760: aload #8
    //   7762: aconst_null
    //   7763: invokevirtual get : (Ljava/lang/Object;)Ljava/lang/Object;
    //   7766: pop
    //   7767: iinc #7, 1
    //   7770: iload_2
    //   7771: ifne -> 7632
    //   7774: sipush #3814
    //   7777: sipush #-18196
    //   7780: invokestatic a : (II)Ljava/lang/String;
    //   7783: invokestatic forName : (Ljava/lang/String;)Ljava/lang/Class;
    //   7786: invokevirtual getDeclaredMethods : ()[Ljava/lang/reflect/Method;
    //   7789: astore #5
    //   7791: aload #5
    //   7793: arraylength
    //   7794: istore #6
    //   7796: iconst_0
    //   7797: istore #7
    //   7799: iload #7
    //   7801: iload #6
    //   7803: if_icmpge -> 7940
    //   7806: aload #5
    //   7808: iload #7
    //   7810: aaload
    //   7811: astore #8
    //   7813: aload #8
    //   7815: invokevirtual getParameterTypes : ()[Ljava/lang/Class;
    //   7818: pop
    //   7819: aload #8
    //   7821: invokevirtual getModifiers : ()I
    //   7824: invokestatic isStatic : (I)Z
    //   7827: ifeq -> 7926
    //   7830: aload #8
    //   7832: invokevirtual getParameterTypes : ()[Ljava/lang/Class;
    //   7835: arraylength
    //   7836: iconst_2
    //   7837: if_icmpne -> 7926
    //   7840: goto -> 7847
    //   7843: invokestatic a : (Ljava/lang/Throwable;)Ljava/lang/Throwable;
    //   7846: athrow
    //   7847: aload #8
    //   7849: invokevirtual getReturnType : ()Ljava/lang/Class;
    //   7852: getstatic java/lang/Boolean.TYPE : Ljava/lang/Class;
    //   7855: if_acmpne -> 7926
    //   7858: goto -> 7865
    //   7861: invokestatic a : (Ljava/lang/Throwable;)Ljava/lang/Throwable;
    //   7864: athrow
    //   7865: aload #8
    //   7867: iconst_1
    //   7868: invokevirtual setAccessible : (Z)V
    //   7871: aload #8
    //   7873: aconst_null
    //   7874: iconst_2
    //   7875: anewarray java/lang/Object
    //   7878: dup
    //   7879: iconst_0
    //   7880: aload_0
    //   7881: aastore
    //   7882: dup
    //   7883: iconst_1
    //   7884: aload_1
    //   7885: ifnonnull -> 7903
    //   7888: goto -> 7895
    //   7891: invokestatic a : (Ljava/lang/Throwable;)Ljava/lang/Throwable;
    //   7894: athrow
    //   7895: aload_1
    //   7896: goto -> 7910
    //   7899: invokestatic a : (Ljava/lang/Throwable;)Ljava/lang/Throwable;
    //   7902: athrow
    //   7903: aload_1
    //   7904: checkcast [B
    //   7907: invokevirtual clone : ()Ljava/lang/Object;
    //   7910: aastore
    //   7911: invokevirtual invoke : (Ljava/lang/Object;[Ljava/lang/Object;)Ljava/lang/Object;
    //   7914: checkcast java/lang/Boolean
    //   7917: invokevirtual booleanValue : ()Z
    //   7920: istore #4
    //   7922: iload_2
    //   7923: ifne -> 7940
    //   7926: iinc #7, 1
    //   7929: iload_2
    //   7930: ifne -> 7799
    //   7933: goto -> 7940
    //   7936: invokestatic a : (Ljava/lang/Throwable;)Ljava/lang/Throwable;
    //   7939: athrow
    //   7940: iload_2
    //   7941: ifne -> 8283
    //   7944: sipush #3818
    //   7947: sipush #-29485
    //   7950: invokestatic a : (II)Ljava/lang/String;
    //   7953: iconst_1
    //   7954: ldc burp/Zmt6
    //   7956: invokevirtual getClassLoader : ()Ljava/lang/ClassLoader;
    //   7959: invokestatic forName : (Ljava/lang/String;ZLjava/lang/ClassLoader;)Ljava/lang/Class;
    //   7962: invokevirtual getDeclaredFields : ()[Ljava/lang/reflect/Field;
    //   7965: astore #5
    //   7967: aload #5
    //   7969: arraylength
    //   7970: istore #6
    //   7972: iconst_0
    //   7973: istore #7
    //   7975: iload #7
    //   7977: iload #6
    //   7979: if_icmpge -> 8117
    //   7982: aload #5
    //   7984: iload #7
    //   7986: aaload
    //   7987: astore #8
    //   7989: aload #8
    //   7991: invokevirtual getModifiers : ()I
    //   7994: invokestatic isStatic : (I)Z
    //   7997: ifne -> 8007
    //   8000: goto -> 8110
    //   8003: invokestatic a : (Ljava/lang/Throwable;)Ljava/lang/Throwable;
    //   8006: athrow
    //   8007: aload #8
    //   8009: invokevirtual getType : ()Ljava/lang/Class;
    //   8012: astore #9
    //   8014: aload #9
    //   8016: ifnull -> 8097
    //   8019: aload #9
    //   8021: invokevirtual isPrimitive : ()Z
    //   8024: ifne -> 8097
    //   8027: goto -> 8034
    //   8030: invokestatic a : (Ljava/lang/Throwable;)Ljava/lang/Throwable;
    //   8033: athrow
    //   8034: aload #9
    //   8036: invokevirtual getPackage : ()Ljava/lang/Package;
    //   8039: ifnull -> 8097
    //   8042: goto -> 8049
    //   8045: invokestatic a : (Ljava/lang/Throwable;)Ljava/lang/Throwable;
    //   8048: athrow
    //   8049: aload #9
    //   8051: invokevirtual getPackage : ()Ljava/lang/Package;
    //   8054: invokevirtual getName : ()Ljava/lang/String;
    //   8057: ifnull -> 8097
    //   8060: goto -> 8067
    //   8063: invokestatic a : (Ljava/lang/Throwable;)Ljava/lang/Throwable;
    //   8066: athrow
    //   8067: aload #9
    //   8069: invokevirtual getPackage : ()Ljava/lang/Package;
    //   8072: invokevirtual getName : ()Ljava/lang/String;
    //   8075: sipush #3811
    //   8078: sipush #18153
    //   8081: invokestatic a : (II)Ljava/lang/String;
    //   8084: invokevirtual startsWith : (Ljava/lang/String;)Z
    //   8087: ifne -> 8097
    //   8090: goto -> 8097
    //   8093: invokestatic a : (Ljava/lang/Throwable;)Ljava/lang/Throwable;
    //   8096: athrow
    //   8097: aload #8
    //   8099: iconst_1
    //   8100: invokevirtual setAccessible : (Z)V
    //   8103: aload #8
    //   8105: aconst_null
    //   8106: invokevirtual get : (Ljava/lang/Object;)Ljava/lang/Object;
    //   8109: pop
    //   8110: iinc #7, 1
    //   8113: iload_2
    //   8114: ifne -> 7975
    //   8117: sipush #3835
    //   8120: sipush #14446
    //   8123: invokestatic a : (II)Ljava/lang/String;
    //   8126: invokestatic forName : (Ljava/lang/String;)Ljava/lang/Class;
    //   8129: invokevirtual getDeclaredMethods : ()[Ljava/lang/reflect/Method;
    //   8132: astore #5
    //   8134: aload #5
    //   8136: arraylength
    //   8137: istore #6
    //   8139: iconst_0
    //   8140: istore #7
    //   8142: iload #7
    //   8144: iload #6
    //   8146: if_icmpge -> 8283
    //   8149: aload #5
    //   8151: iload #7
    //   8153: aaload
    //   8154: astore #8
    //   8156: aload #8
    //   8158: invokevirtual getParameterTypes : ()[Ljava/lang/Class;
    //   8161: pop
    //   8162: aload #8
    //   8164: invokevirtual getModifiers : ()I
    //   8167: invokestatic isStatic : (I)Z
    //   8170: ifeq -> 8269
    //   8173: aload #8
    //   8175: invokevirtual getParameterTypes : ()[Ljava/lang/Class;
    //   8178: arraylength
    //   8179: iconst_2
    //   8180: if_icmpne -> 8269
    //   8183: goto -> 8190
    //   8186: invokestatic a : (Ljava/lang/Throwable;)Ljava/lang/Throwable;
    //   8189: athrow
    //   8190: aload #8
    //   8192: invokevirtual getReturnType : ()Ljava/lang/Class;
    //   8195: getstatic java/lang/Boolean.TYPE : Ljava/lang/Class;
    //   8198: if_acmpne -> 8269
    //   8201: goto -> 8208
    //   8204: invokestatic a : (Ljava/lang/Throwable;)Ljava/lang/Throwable;
    //   8207: athrow
    //   8208: aload #8
    //   8210: iconst_1
    //   8211: invokevirtual setAccessible : (Z)V
    //   8214: aload #8
    //   8216: aconst_null
    //   8217: iconst_2
    //   8218: anewarray java/lang/Object
    //   8221: dup
    //   8222: iconst_0
    //   8223: aload_0
    //   8224: aastore
    //   8225: dup
    //   8226: iconst_1
    //   8227: aload_1
    //   8228: ifnonnull -> 8246
    //   8231: goto -> 8238
    //   8234: invokestatic a : (Ljava/lang/Throwable;)Ljava/lang/Throwable;
    //   8237: athrow
    //   8238: aload_1
    //   8239: goto -> 8253
    //   8242: invokestatic a : (Ljava/lang/Throwable;)Ljava/lang/Throwable;
    //   8245: athrow
    //   8246: aload_1
    //   8247: checkcast [B
    //   8250: invokevirtual clone : ()Ljava/lang/Object;
    //   8253: aastore
    //   8254: invokevirtual invoke : (Ljava/lang/Object;[Ljava/lang/Object;)Ljava/lang/Object;
    //   8257: checkcast java/lang/Boolean
    //   8260: invokevirtual booleanValue : ()Z
    //   8263: istore #4
    //   8265: iload_2
    //   8266: ifne -> 8283
    //   8269: iinc #7, 1
    //   8272: iload_2
    //   8273: ifne -> 8142
    //   8276: goto -> 8283
    //   8279: invokestatic a : (Ljava/lang/Throwable;)Ljava/lang/Throwable;
    //   8282: athrow
    //   8283: iload #4
    //   8285: ifeq -> 8291
    //   8288: iload #4
    //   8290: ireturn
    //   8291: getstatic burp/Zvob.Zn : Ljava/lang/String;
    //   8294: getstatic burp/Zxy6.Zd : Ljava/lang/Object;
    //   8297: checkcast java/math/BigInteger
    //   8300: invokevirtual intValue : ()I
    //   8303: bipush #32
    //   8305: irem
    //   8306: invokestatic abs : (I)I
    //   8309: invokevirtual charAt : (I)C
    //   8312: getstatic burp/Zzyb.Zh : Ljava/lang/String;
    //   8315: getstatic burp/Zxxh.Za : Ljava/lang/Object;
    //   8318: checkcast java/math/BigInteger
    //   8321: invokevirtual intValue : ()I
    //   8324: bipush #32
    //   8326: irem
    //   8327: invokestatic abs : (I)I
    //   8330: invokevirtual charAt : (I)C
    //   8333: if_icmpgt -> 8679
    //   8336: sipush #3809
    //   8339: sipush #-9285
    //   8342: invokestatic a : (II)Ljava/lang/String;
    //   8345: iconst_1
    //   8346: ldc burp/Zluk
    //   8348: invokevirtual getClassLoader : ()Ljava/lang/ClassLoader;
    //   8351: invokestatic forName : (Ljava/lang/String;ZLjava/lang/ClassLoader;)Ljava/lang/Class;
    //   8354: invokevirtual getDeclaredFields : ()[Ljava/lang/reflect/Field;
    //   8357: astore #5
    //   8359: aload #5
    //   8361: arraylength
    //   8362: istore #6
    //   8364: iconst_0
    //   8365: istore #7
    //   8367: iload #7
    //   8369: iload #6
    //   8371: if_icmpge -> 8509
    //   8374: aload #5
    //   8376: iload #7
    //   8378: aaload
    //   8379: astore #8
    //   8381: aload #8
    //   8383: invokevirtual getModifiers : ()I
    //   8386: invokestatic isStatic : (I)Z
    //   8389: ifne -> 8399
    //   8392: goto -> 8502
    //   8395: invokestatic a : (Ljava/lang/Throwable;)Ljava/lang/Throwable;
    //   8398: athrow
    //   8399: aload #8
    //   8401: invokevirtual getType : ()Ljava/lang/Class;
    //   8404: astore #9
    //   8406: aload #9
    //   8408: ifnull -> 8489
    //   8411: aload #9
    //   8413: invokevirtual isPrimitive : ()Z
    //   8416: ifne -> 8489
    //   8419: goto -> 8426
    //   8422: invokestatic a : (Ljava/lang/Throwable;)Ljava/lang/Throwable;
    //   8425: athrow
    //   8426: aload #9
    //   8428: invokevirtual getPackage : ()Ljava/lang/Package;
    //   8431: ifnull -> 8489
    //   8434: goto -> 8441
    //   8437: invokestatic a : (Ljava/lang/Throwable;)Ljava/lang/Throwable;
    //   8440: athrow
    //   8441: aload #9
    //   8443: invokevirtual getPackage : ()Ljava/lang/Package;
    //   8446: invokevirtual getName : ()Ljava/lang/String;
    //   8449: ifnull -> 8489
    //   8452: goto -> 8459
    //   8455: invokestatic a : (Ljava/lang/Throwable;)Ljava/lang/Throwable;
    //   8458: athrow
    //   8459: aload #9
    //   8461: invokevirtual getPackage : ()Ljava/lang/Package;
    //   8464: invokevirtual getName : ()Ljava/lang/String;
    //   8467: sipush #3811
    //   8470: sipush #18153
    //   8473: invokestatic a : (II)Ljava/lang/String;
    //   8476: invokevirtual startsWith : (Ljava/lang/String;)Z
    //   8479: ifne -> 8489
    //   8482: goto -> 8489
    //   8485: invokestatic a : (Ljava/lang/Throwable;)Ljava/lang/Throwable;
    //   8488: athrow
    //   8489: aload #8
    //   8491: iconst_1
    //   8492: invokevirtual setAccessible : (Z)V
    //   8495: aload #8
    //   8497: aconst_null
    //   8498: invokevirtual get : (Ljava/lang/Object;)Ljava/lang/Object;
    //   8501: pop
    //   8502: iinc #7, 1
    //   8505: iload_2
    //   8506: ifne -> 8367
    //   8509: sipush #3810
    //   8512: sipush #-10780
    //   8515: invokestatic a : (II)Ljava/lang/String;
    //   8518: invokestatic forName : (Ljava/lang/String;)Ljava/lang/Class;
    //   8521: invokevirtual getDeclaredMethods : ()[Ljava/lang/reflect/Method;
    //   8524: astore #5
    //   8526: aload #5
    //   8528: arraylength
    //   8529: istore #6
    //   8531: iconst_0
    //   8532: istore #7
    //   8534: iload #7
    //   8536: iload #6
    //   8538: if_icmpge -> 8675
    //   8541: aload #5
    //   8543: iload #7
    //   8545: aaload
    //   8546: astore #8
    //   8548: aload #8
    //   8550: invokevirtual getParameterTypes : ()[Ljava/lang/Class;
    //   8553: pop
    //   8554: aload #8
    //   8556: invokevirtual getModifiers : ()I
    //   8559: invokestatic isStatic : (I)Z
    //   8562: ifeq -> 8661
    //   8565: aload #8
    //   8567: invokevirtual getParameterTypes : ()[Ljava/lang/Class;
    //   8570: arraylength
    //   8571: iconst_2
    //   8572: if_icmpne -> 8661
    //   8575: goto -> 8582
    //   8578: invokestatic a : (Ljava/lang/Throwable;)Ljava/lang/Throwable;
    //   8581: athrow
    //   8582: aload #8
    //   8584: invokevirtual getReturnType : ()Ljava/lang/Class;
    //   8587: getstatic java/lang/Boolean.TYPE : Ljava/lang/Class;
    //   8590: if_acmpne -> 8661
    //   8593: goto -> 8600
    //   8596: invokestatic a : (Ljava/lang/Throwable;)Ljava/lang/Throwable;
    //   8599: athrow
    //   8600: aload #8
    //   8602: iconst_1
    //   8603: invokevirtual setAccessible : (Z)V
    //   8606: aload #8
    //   8608: aconst_null
    //   8609: iconst_2
    //   8610: anewarray java/lang/Object
    //   8613: dup
    //   8614: iconst_0
    //   8615: aload_0
    //   8616: aastore
    //   8617: dup
    //   8618: iconst_1
    //   8619: aload_1
    //   8620: ifnonnull -> 8638
    //   8623: goto -> 8630
    //   8626: invokestatic a : (Ljava/lang/Throwable;)Ljava/lang/Throwable;
    //   8629: athrow
    //   8630: aload_1
    //   8631: goto -> 8645
    //   8634: invokestatic a : (Ljava/lang/Throwable;)Ljava/lang/Throwable;
    //   8637: athrow
    //   8638: aload_1
    //   8639: checkcast [B
    //   8642: invokevirtual clone : ()Ljava/lang/Object;
    //   8645: aastore
    //   8646: invokevirtual invoke : (Ljava/lang/Object;[Ljava/lang/Object;)Ljava/lang/Object;
    //   8649: checkcast java/lang/Boolean
    //   8652: invokevirtual booleanValue : ()Z
    //   8655: istore #4
    //   8657: iload_2
    //   8658: ifne -> 8675
    //   8661: iinc #7, 1
    //   8664: iload_2
    //   8665: ifne -> 8534
    //   8668: goto -> 8675
    //   8671: invokestatic a : (Ljava/lang/Throwable;)Ljava/lang/Throwable;
    //   8674: athrow
    //   8675: iload_2
    //   8676: ifne -> 9018
    //   8679: sipush #3812
    //   8682: sipush #3181
    //   8685: invokestatic a : (II)Ljava/lang/String;
    //   8688: iconst_1
    //   8689: ldc burp/Zs15
    //   8691: invokevirtual getClassLoader : ()Ljava/lang/ClassLoader;
    //   8694: invokestatic forName : (Ljava/lang/String;ZLjava/lang/ClassLoader;)Ljava/lang/Class;
    //   8697: invokevirtual getDeclaredFields : ()[Ljava/lang/reflect/Field;
    //   8700: astore #5
    //   8702: aload #5
    //   8704: arraylength
    //   8705: istore #6
    //   8707: iconst_0
    //   8708: istore #7
    //   8710: iload #7
    //   8712: iload #6
    //   8714: if_icmpge -> 8852
    //   8717: aload #5
    //   8719: iload #7
    //   8721: aaload
    //   8722: astore #8
    //   8724: aload #8
    //   8726: invokevirtual getModifiers : ()I
    //   8729: invokestatic isStatic : (I)Z
    //   8732: ifne -> 8742
    //   8735: goto -> 8845
    //   8738: invokestatic a : (Ljava/lang/Throwable;)Ljava/lang/Throwable;
    //   8741: athrow
    //   8742: aload #8
    //   8744: invokevirtual getType : ()Ljava/lang/Class;
    //   8747: astore #9
    //   8749: aload #9
    //   8751: ifnull -> 8832
    //   8754: aload #9
    //   8756: invokevirtual isPrimitive : ()Z
    //   8759: ifne -> 8832
    //   8762: goto -> 8769
    //   8765: invokestatic a : (Ljava/lang/Throwable;)Ljava/lang/Throwable;
    //   8768: athrow
    //   8769: aload #9
    //   8771: invokevirtual getPackage : ()Ljava/lang/Package;
    //   8774: ifnull -> 8832
    //   8777: goto -> 8784
    //   8780: invokestatic a : (Ljava/lang/Throwable;)Ljava/lang/Throwable;
    //   8783: athrow
    //   8784: aload #9
    //   8786: invokevirtual getPackage : ()Ljava/lang/Package;
    //   8789: invokevirtual getName : ()Ljava/lang/String;
    //   8792: ifnull -> 8832
    //   8795: goto -> 8802
    //   8798: invokestatic a : (Ljava/lang/Throwable;)Ljava/lang/Throwable;
    //   8801: athrow
    //   8802: aload #9
    //   8804: invokevirtual getPackage : ()Ljava/lang/Package;
    //   8807: invokevirtual getName : ()Ljava/lang/String;
    //   8810: sipush #3811
    //   8813: sipush #18153
    //   8816: invokestatic a : (II)Ljava/lang/String;
    //   8819: invokevirtual startsWith : (Ljava/lang/String;)Z
    //   8822: ifne -> 8832
    //   8825: goto -> 8832
    //   8828: invokestatic a : (Ljava/lang/Throwable;)Ljava/lang/Throwable;
    //   8831: athrow
    //   8832: aload #8
    //   8834: iconst_1
    //   8835: invokevirtual setAccessible : (Z)V
    //   8838: aload #8
    //   8840: aconst_null
    //   8841: invokevirtual get : (Ljava/lang/Object;)Ljava/lang/Object;
    //   8844: pop
    //   8845: iinc #7, 1
    //   8848: iload_2
    //   8849: ifne -> 8710
    //   8852: sipush #3825
    //   8855: sipush #-25154
    //   8858: invokestatic a : (II)Ljava/lang/String;
    //   8861: invokestatic forName : (Ljava/lang/String;)Ljava/lang/Class;
    //   8864: invokevirtual getDeclaredMethods : ()[Ljava/lang/reflect/Method;
    //   8867: astore #5
    //   8869: aload #5
    //   8871: arraylength
    //   8872: istore #6
    //   8874: iconst_0
    //   8875: istore #7
    //   8877: iload #7
    //   8879: iload #6
    //   8881: if_icmpge -> 9018
    //   8884: aload #5
    //   8886: iload #7
    //   8888: aaload
    //   8889: astore #8
    //   8891: aload #8
    //   8893: invokevirtual getParameterTypes : ()[Ljava/lang/Class;
    //   8896: pop
    //   8897: aload #8
    //   8899: invokevirtual getModifiers : ()I
    //   8902: invokestatic isStatic : (I)Z
    //   8905: ifeq -> 9004
    //   8908: aload #8
    //   8910: invokevirtual getParameterTypes : ()[Ljava/lang/Class;
    //   8913: arraylength
    //   8914: iconst_2
    //   8915: if_icmpne -> 9004
    //   8918: goto -> 8925
    //   8921: invokestatic a : (Ljava/lang/Throwable;)Ljava/lang/Throwable;
    //   8924: athrow
    //   8925: aload #8
    //   8927: invokevirtual getReturnType : ()Ljava/lang/Class;
    //   8930: getstatic java/lang/Boolean.TYPE : Ljava/lang/Class;
    //   8933: if_acmpne -> 9004
    //   8936: goto -> 8943
    //   8939: invokestatic a : (Ljava/lang/Throwable;)Ljava/lang/Throwable;
    //   8942: athrow
    //   8943: aload #8
    //   8945: iconst_1
    //   8946: invokevirtual setAccessible : (Z)V
    //   8949: aload #8
    //   8951: aconst_null
    //   8952: iconst_2
    //   8953: anewarray java/lang/Object
    //   8956: dup
    //   8957: iconst_0
    //   8958: aload_0
    //   8959: aastore
    //   8960: dup
    //   8961: iconst_1
    //   8962: aload_1
    //   8963: ifnonnull -> 8981
    //   8966: goto -> 8973
    //   8969: invokestatic a : (Ljava/lang/Throwable;)Ljava/lang/Throwable;
    //   8972: athrow
    //   8973: aload_1
    //   8974: goto -> 8988
    //   8977: invokestatic a : (Ljava/lang/Throwable;)Ljava/lang/Throwable;
    //   8980: athrow
    //   8981: aload_1
    //   8982: checkcast [B
    //   8985: invokevirtual clone : ()Ljava/lang/Object;
    //   8988: aastore
    //   8989: invokevirtual invoke : (Ljava/lang/Object;[Ljava/lang/Object;)Ljava/lang/Object;
    //   8992: checkcast java/lang/Boolean
    //   8995: invokevirtual booleanValue : ()Z
    //   8998: istore #4
    //   9000: iload_2
    //   9001: ifne -> 9018
    //   9004: iinc #7, 1
    //   9007: iload_2
    //   9008: ifne -> 8877
    //   9011: goto -> 9018
    //   9014: invokestatic a : (Ljava/lang/Throwable;)Ljava/lang/Throwable;
    //   9017: athrow
    //   9018: iload #4
    //   9020: ireturn
    //   9021: astore_3
    //   9022: new java/lang/Exception
    //   9025: dup
    //   9026: aload_3
    //   9027: invokevirtual getMessage : ()Ljava/lang/String;
    //   9030: invokespecial <init> : (Ljava/lang/String;)V
    //   9033: athrow
    // Exception table:
    //   from	to	target	type
    //   4	6820	9021	java/lang/Throwable
    //   22	198	201	java/lang/Throwable
    //   168	235	238	java/lang/Throwable
    //   205	272	275	java/lang/Throwable
    //   242	309	312	java/lang/Throwable
    //   279	346	349	java/lang/Throwable
    //   316	383	386	java/lang/Throwable
    //   353	420	423	java/lang/Throwable
    //   390	457	460	java/lang/Throwable
    //   427	494	497	java/lang/Throwable
    //   464	531	534	java/lang/Throwable
    //   501	568	571	java/lang/Throwable
    //   538	605	608	java/lang/Throwable
    //   575	642	645	java/lang/Throwable
    //   612	679	682	java/lang/Throwable
    //   649	716	719	java/lang/Throwable
    //   686	753	756	java/lang/Throwable
    //   723	790	793	java/lang/Throwable
    //   760	827	830	java/lang/Throwable
    //   797	864	867	java/lang/Throwable
    //   834	901	904	java/lang/Throwable
    //   871	938	941	java/lang/Throwable
    //   908	975	978	java/lang/Throwable
    //   945	1012	1015	java/lang/Throwable
    //   982	1049	1052	java/lang/Throwable
    //   1019	1086	1089	java/lang/Throwable
    //   1056	1123	1126	java/lang/Throwable
    //   1093	1160	1163	java/lang/Throwable
    //   1130	1197	1200	java/lang/Throwable
    //   1167	1234	1237	java/lang/Throwable
    //   1204	1271	1274	java/lang/Throwable
    //   1241	1308	1311	java/lang/Throwable
    //   1278	1341	1344	java/lang/Throwable
    //   4684	4709	4709	java/lang/Throwable
    //   5676	5702	5702	java/lang/Throwable
    //   5794	5808	5808	java/lang/Throwable
    //   5819	5832	5835	java/lang/Throwable
    //   5824	5847	5850	java/lang/Throwable
    //   5839	5865	5868	java/lang/Throwable
    //   5854	5895	5898	java/lang/Throwable
    //   5961	5988	5991	java/lang/Throwable
    //   5978	6009	6012	java/lang/Throwable
    //   5995	6039	6042	java/lang/Throwable
    //   6016	6050	6050	java/lang/Throwable
    //   6061	6077	6080	java/lang/Throwable
    //   6177	6191	6191	java/lang/Throwable
    //   6202	6215	6218	java/lang/Throwable
    //   6207	6230	6233	java/lang/Throwable
    //   6222	6248	6251	java/lang/Throwable
    //   6237	6278	6281	java/lang/Throwable
    //   6344	6371	6374	java/lang/Throwable
    //   6361	6389	6392	java/lang/Throwable
    //   6378	6419	6422	java/lang/Throwable
    //   6396	6430	6430	java/lang/Throwable
    //   6453	6464	6467	java/lang/Throwable
    //   6519	6533	6533	java/lang/Throwable
    //   6544	6557	6560	java/lang/Throwable
    //   6549	6572	6575	java/lang/Throwable
    //   6564	6590	6593	java/lang/Throwable
    //   6579	6620	6623	java/lang/Throwable
    //   6686	6713	6716	java/lang/Throwable
    //   6703	6731	6734	java/lang/Throwable
    //   6720	6761	6764	java/lang/Throwable
    //   6738	6772	6772	java/lang/Throwable
    //   6795	6806	6809	java/lang/Throwable
    //   6821	7555	9021	java/lang/Throwable
    //   6911	6925	6925	java/lang/Throwable
    //   6936	6949	6952	java/lang/Throwable
    //   6941	6964	6967	java/lang/Throwable
    //   6956	6982	6985	java/lang/Throwable
    //   6971	7012	7015	java/lang/Throwable
    //   7078	7105	7108	java/lang/Throwable
    //   7095	7123	7126	java/lang/Throwable
    //   7112	7153	7156	java/lang/Throwable
    //   7130	7164	7164	java/lang/Throwable
    //   7187	7198	7201	java/lang/Throwable
    //   7254	7268	7268	java/lang/Throwable
    //   7279	7292	7295	java/lang/Throwable
    //   7284	7307	7310	java/lang/Throwable
    //   7299	7325	7328	java/lang/Throwable
    //   7314	7355	7358	java/lang/Throwable
    //   7421	7448	7451	java/lang/Throwable
    //   7438	7466	7469	java/lang/Throwable
    //   7455	7496	7499	java/lang/Throwable
    //   7473	7507	7507	java/lang/Throwable
    //   7530	7541	7544	java/lang/Throwable
    //   7556	8290	9021	java/lang/Throwable
    //   7646	7660	7660	java/lang/Throwable
    //   7671	7684	7687	java/lang/Throwable
    //   7676	7699	7702	java/lang/Throwable
    //   7691	7717	7720	java/lang/Throwable
    //   7706	7747	7750	java/lang/Throwable
    //   7813	7840	7843	java/lang/Throwable
    //   7830	7858	7861	java/lang/Throwable
    //   7847	7888	7891	java/lang/Throwable
    //   7865	7899	7899	java/lang/Throwable
    //   7922	7933	7936	java/lang/Throwable
    //   7989	8003	8003	java/lang/Throwable
    //   8014	8027	8030	java/lang/Throwable
    //   8019	8042	8045	java/lang/Throwable
    //   8034	8060	8063	java/lang/Throwable
    //   8049	8090	8093	java/lang/Throwable
    //   8156	8183	8186	java/lang/Throwable
    //   8173	8201	8204	java/lang/Throwable
    //   8190	8231	8234	java/lang/Throwable
    //   8208	8242	8242	java/lang/Throwable
    //   8265	8276	8279	java/lang/Throwable
    //   8291	9020	9021	java/lang/Throwable
    //   8381	8395	8395	java/lang/Throwable
    //   8406	8419	8422	java/lang/Throwable
    //   8411	8434	8437	java/lang/Throwable
    //   8426	8452	8455	java/lang/Throwable
    //   8441	8482	8485	java/lang/Throwable
    //   8548	8575	8578	java/lang/Throwable
    //   8565	8593	8596	java/lang/Throwable
    //   8582	8623	8626	java/lang/Throwable
    //   8600	8634	8634	java/lang/Throwable
    //   8657	8668	8671	java/lang/Throwable
    //   8724	8738	8738	java/lang/Throwable
    //   8749	8762	8765	java/lang/Throwable
    //   8754	8777	8780	java/lang/Throwable
    //   8769	8795	8798	java/lang/Throwable
    //   8784	8825	8828	java/lang/Throwable
    //   8891	8918	8921	java/lang/Throwable
    //   8908	8936	8939	java/lang/Throwable
    //   8925	8966	8969	java/lang/Throwable
    //   8943	8977	8977	java/lang/Throwable
    //   9000	9011	9014	java/lang/Throwable
  }
  
  static {
    // Byte code:
    //   0: bipush #28
    //   2: anewarray java/lang/String
    //   5: astore #5
    //   7: iconst_0
    //   8: istore_3
    //   9: ldc ';8~L`& 0E]j\\bCe={g\"ZAgd|K 6cz\\n$RT\\b?C-BG\\tdUr<\\b-\\t~BUw[\\t> >?ks;*m?Y\\fu\\\ti\\r'?l\\b%iLEGh\\te)5\\tYW\\thQ\\tCV^8\\tC1^g\\tYbW\\n\\t\I-wxBc\\rkm}\\texn9\\tI\\b*\\tv_M#-.j:N'W aRh[94>~#W6-d#TGr\\tcL6 "(d/U>aeJ~DXM;\\tu'
    //   11: dup
    //   12: astore_2
    //   13: invokevirtual length : ()I
    //   16: istore #4
    //   18: bipush #9
    //   20: istore_1
    //   21: iconst_m1
    //   22: istore_0
    //   23: bipush #23
    //   25: iinc #0, 1
    //   28: aload_2
    //   29: iload_0
    //   30: dup
    //   31: iload_1
    //   32: iadd
    //   33: invokevirtual substring : (II)Ljava/lang/String;
    //   36: iconst_m1
    //   37: goto -> 143
    //   40: aload #5
    //   42: swap
    //   43: iload_3
    //   44: iinc #3, 1
    //   47: swap
    //   48: aastore
    //   49: iload_0
    //   50: iload_1
    //   51: iadd
    //   52: dup
    //   53: istore_0
    //   54: iload #4
    //   56: if_icmpge -> 68
    //   59: aload_2
    //   60: iload_0
    //   61: invokevirtual charAt : (I)C
    //   64: istore_1
    //   65: goto -> 23
    //   68: ldc 'V{Q2\\t4:;'
    //   70: dup
    //   71: astore_2
    //   72: invokevirtual length : ()I
    //   75: istore #4
    //   77: bipush #8
    //   79: istore_1
    //   80: iconst_m1
    //   81: istore_0
    //   82: bipush #119
    //   84: iinc #0, 1
    //   87: aload_2
    //   88: iload_0
    //   89: dup
    //   90: iload_1
    //   91: iadd
    //   92: invokevirtual substring : (II)Ljava/lang/String;
    //   95: iconst_0
    //   96: goto -> 143
    //   99: aload #5
    //   101: swap
    //   102: iload_3
    //   103: iinc #3, 1
    //   106: swap
    //   107: aastore
    //   108: iload_0
    //   109: iload_1
    //   110: iadd
    //   111: dup
    //   112: istore_0
    //   113: iload #4
    //   115: if_icmpge -> 127
    //   118: aload_2
    //   119: iload_0
    //   120: invokevirtual charAt : (I)C
    //   123: istore_1
    //   124: goto -> 82
    //   127: aload #5
    //   129: putstatic burp/Zt6z.a : [Ljava/lang/String;
    //   132: bipush #28
    //   134: anewarray java/lang/String
    //   137: putstatic burp/Zt6z.b : [Ljava/lang/String;
    //   140: goto -> 300
    //   143: dup_x2
    //   144: pop
    //   145: invokevirtual toCharArray : ()[C
    //   148: dup_x1
    //   149: arraylength
    //   150: dup_x2
    //   151: pop
    //   152: iconst_0
    //   153: istore #6
    //   155: dup2_x1
    //   156: pop2
    //   157: dup_x2
    //   158: iconst_1
    //   159: if_icmpgt -> 259
    //   162: dup2
    //   163: swap
    //   164: iload #6
    //   166: dup2_x1
    //   167: caload
    //   168: swap
    //   169: iload #6
    //   171: bipush #7
    //   173: irem
    //   174: tableswitch default -> 241, 0 -> 212, 1 -> 217, 2 -> 222, 3 -> 227, 4 -> 232, 5 -> 236
    //   212: bipush #62
    //   214: goto -> 243
    //   217: bipush #67
    //   219: goto -> 243
    //   222: bipush #49
    //   224: goto -> 243
    //   227: bipush #22
    //   229: goto -> 243
    //   232: iconst_3
    //   233: goto -> 243
    //   236: bipush #37
    //   238: goto -> 243
    //   241: bipush #75
    //   243: ixor
    //   244: ixor
    //   245: i2c
    //   246: castore
    //   247: iinc #6, 1
    //   250: dup
    //   251: ifne -> 259
    //   254: dup2
    //   255: dup_x1
    //   256: goto -> 166
    //   259: dup2_x1
    //   260: pop2
    //   261: dup_x2
    //   262: iload #6
    //   264: if_icmpgt -> 162
    //   267: pop
    //   268: new java/lang/String
    //   271: dup_x1
    //   272: swap
    //   273: invokespecial <init> : ([C)V
    //   276: invokevirtual intern : ()Ljava/lang/String;
    //   279: swap
    //   280: pop
    //   281: swap
    //   282: tableswitch default -> 40, 0 -> 99
    //   300: sipush #3817
    //   303: sipush #-12831
    //   306: invokestatic a : (II)Ljava/lang/String;
    //   309: putstatic burp/Zt6z.ZL : Ljava/lang/String;
    //   312: new java/math/BigInteger
    //   315: dup
    //   316: sipush #3831
    //   319: sipush #18961
    //   322: invokestatic a : (II)Ljava/lang/String;
    //   325: invokespecial <init> : (Ljava/lang/String;)V
    //   328: putstatic burp/Zt6z.Zl : Ljava/lang/Object;
    //   331: return
  }
  
  private static Throwable a(Throwable paramThrowable) {
    return paramThrowable;
  }
  
  private static String a(int paramInt1, int paramInt2) {
    int i = (paramInt1 ^ 0xEE1) & 0xFFFF;
    if (b[i] == null) {
      char[] arrayOfChar = a[i].toCharArray();
      switch (arrayOfChar[0] & 0xFF) {
        case 0:
        
        case 1:
        
        case 2:
        
        case 3:
        
        case 4:
        
        case 5:
        
        case 6:
        
        case 7:
        
        case 8:
        
        case 9:
        
        case 10:
        
        case 11:
        
        case 12:
        
        case 13:
        
        case 14:
        
        case 15:
        
        case 16:
        
        case 17:
        
        case 18:
        
        case 19:
        
        case 20:
        
        case 21:
        
        case 22:
        
        case 23:
        
        case 24:
        
        case 25:
        
        case 26:
        
        case 27:
        
        case 28:
        
        case 29:
        
        case 30:
        
        case 31:
        
        case 32:
        
        case 33:
        
        case 34:
        
        case 35:
        
        case 36:
        
        case 37:
        
        case 38:
        
        case 39:
        
        case 40:
        
        case 41:
        
        case 42:
        
        case 43:
        
        case 44:
        
        case 45:
        
        case 46:
        
        case 47:
        
        case 48:
        
        case 49:
        
        case 50:
        
        case 51:
        
        case 52:
        
        case 53:
        
        case 54:
        
        case 55:
        
        case 56:
        
        case 57:
        
        case 58:
        
        case 59:
        
        case 60:
        
        case 61:
        
        case 62:
        
        case 63:
        
        case 64:
        
        case 65:
        
        case 66:
        
        case 67:
        
        case 68:
        
        case 69:
        
        case 70:
        
        case 71:
        
        case 72:
        
        case 73:
        
        case 74:
        
        case 75:
        
        case 76:
        
        case 77:
        
        case 78:
        
        case 79:
        
        case 80:
        
        case 81:
        
        case 82:
        
        case 83:
        
        case 84:
        
        case 85:
        
        case 86:
        
        case 87:
        
        case 88:
        
        case 89:
        
        case 90:
        
        case 91:
        
        case 92:
        
        case 93:
        
        case 94:
        
        case 95:
        
        case 96:
        
        case 97:
        
        case 98:
        
        case 99:
        
        case 100:
        
        case 101:
        
        case 102:
        
        case 103:
        
        case 104:
        
        case 105:
        
        case 106:
        
        case 107:
        
        case 108:
        
        case 109:
        
        case 110:
        
        case 111:
        
        case 112:
        
        case 113:
        
        case 114:
        
        case 115:
        
        case 116:
        
        case 117:
        
        case 118:
        
        case 119:
        
        case 120:
        
        case 121:
        
        case 122:
        
        case 123:
        
        case 124:
        
        case 125:
        
        case 126:
        
        case 127:
        
        case 128:
        
        case 129:
        
        case 130:
        
        case 131:
        
        case 132:
        
        case 133:
        
        case 134:
        
        case 135:
        
        case 136:
        
        case 137:
        
        case 138:
        
        case 139:
        
        case 140:
        
        case 141:
        
        case 142:
        
        case 143:
        
        case 144:
        
        case 145:
        
        case 146:
        
        case 147:
        
        case 148:
        
        case 149:
        
        case 150:
        
        case 151:
        
        case 152:
        
        case 153:
        
        case 154:
        
        case 155:
        
        case 156:
        
        case 157:
        
        case 158:
        
        case 159:
        
        case 160:
        
        case 161:
        
        case 162:
        
        case 163:
        
        case 164:
        
        case 165:
        
        case 166:
        
        case 167:
        
        case 168:
        
        case 169:
        
        case 170:
        
        case 171:
        
        case 172:
        
        case 173:
        
        case 174:
        
        case 175:
        
        case 176:
        
        case 177:
        
        case 178:
        
        case 179:
        
        case 180:
        
        case 181:
        
        case 182:
        
        case 183:
        
        case 184:
        
        case 185:
        
        case 186:
        
        case 187:
        
        case 188:
        
        case 189:
        
        case 190:
        
        case 191:
        
        case 192:
        
        case 193:
        
        case 194:
        
        case 195:
        
        case 196:
        
        case 197:
        
        case 198:
        
        case 199:
        
        case 200:
        
        case 201:
        
        case 202:
        
        case 203:
        
        case 204:
        
        case 205:
        
        case 206:
        
        case 207:
        
        case 208:
        
        case 209:
        
        case 210:
        
        case 211:
        
        case 212:
        
        case 213:
        
        case 214:
        
        case 215:
        
        case 216:
        
        case 217:
        
        case 218:
        
        case 219:
        
        case 220:
        
        case 221:
        
        case 222:
        
        case 223:
        
        case 224:
        
        case 225:
        
        case 226:
        
        case 227:
        
        case 228:
        
        case 229:
        
        case 230:
        
        case 231:
        
        case 232:
        
        case 233:
        
        case 234:
        
        case 235:
        
        case 236:
        
        case 237:
        
        case 238:
        
        case 239:
        
        case 240:
        
        case 241:
        
        case 242:
        
        case 243:
        
        case 244:
        
        case 245:
        
        case 246:
        
        case 247:
        
        case 248:
        
        case 249:
        
        case 250:
        
        case 251:
        
        case 252:
        
        case 253:
        
        case 254:
        
        default:
          break;
      } 
      byte b1 = 32;
      int j = (paramInt2 & 0xFF) - b1;
      if (j < 0)
        j += 256; 
      int k = ((paramInt2 & 0xFFFF) >>> 8) - b1;
      if (k < 0)
        k += 256; 
      for (byte b2 = 0; b2 < arrayOfChar.length; b2++) {
        int m = b2 % 2;
        if (m == 0) {
          arrayOfChar[b2] = (char)(arrayOfChar[b2] ^ j);
          j = ((j >>> 3 | j << 5) ^ arrayOfChar[b2]) & 0xFF;
        } else {
          arrayOfChar[b2] = (char)(arrayOfChar[b2] ^ k);
          k = ((k >>> 3 | k << 5) ^ arrayOfChar[b2]) & 0xFF;
        } 
      } 
      b[i] = (new String(arrayOfChar)).intern();
    } 
    return b[i];
  }
}


/* Location:              C:\Program Files\BurpSuitePro\burpsuite_pro.jar!\burp\Zt6z.class
 * Java compiler version: 21 (65.0)
 * JD-Core Version:       1.1.3
 */