package burp;

import java.math.BigInteger;

class Zt7k extends ClassLoader {
  static Object Zc;
  
  static String ZH;
  
  private static final String[] a;
  
  private static final String[] b;
  
  static void Zp(Object paramObject) {
    Zeqw.Zw = a(-2257, -5652);
    Zeqw.ZV = new BigInteger(a(-2261, -28793));
    boolean bool = Zt2e.ZK();
    try {
      try {
        if (Zrx5.ZD.charAt(Math.abs(((BigInteger)Zlzs.ZL).intValue() % 32)) > Zrh1.Zg.charAt(Math.abs(((BigInteger)Zzpj.ZI).intValue() % 32))) {
          try {
            Zgu4.Zi(Class.forName(a(-2264, -1379)));
            if (bool)
              Zenq.ZR(Class.forName(a(-2265, 14982))); 
          } catch (Throwable throwable) {
            throw a(null);
          } 
          return;
        } 
      } catch (Throwable throwable) {
        throw a(null);
      } 
      Zenq.ZR(Class.forName(a(-2265, 14982)));
    } catch (Throwable throwable) {}
  }
  
  static boolean ZE(Object[] paramArrayOfObject, Object paramObject) throws Throwable {
    // Byte code:
    //   0: invokestatic ZK : ()Z
    //   3: istore_2
    //   4: new java/lang/StringBuilder
    //   7: dup
    //   8: invokespecial <init> : ()V
    //   11: astore_3
    //   12: iconst_0
    //   13: istore #4
    //   15: iload #4
    //   17: bipush #32
    //   19: if_icmpge -> 1355
    //   22: iload #4
    //   24: tableswitch default -> 1348, 0 -> 168, 1 -> 205, 2 -> 242, 3 -> 279, 4 -> 316, 5 -> 353, 6 -> 390, 7 -> 427, 8 -> 464, 9 -> 501, 10 -> 538, 11 -> 575, 12 -> 612, 13 -> 649, 14 -> 686, 15 -> 723, 16 -> 760, 17 -> 797, 18 -> 834, 19 -> 871, 20 -> 908, 21 -> 945, 22 -> 982, 23 -> 1019, 24 -> 1056, 25 -> 1093, 26 -> 1130, 27 -> 1167, 28 -> 1204, 29 -> 1241, 30 -> 1278, 31 -> 1315
    //   168: aload_3
    //   169: getstatic burp/Zr_y.Zb : Ljava/lang/String;
    //   172: getstatic burp/Zm7x.Zv : Ljava/lang/Object;
    //   175: checkcast java/math/BigInteger
    //   178: invokevirtual intValue : ()I
    //   181: bipush #32
    //   183: irem
    //   184: invokestatic abs : (I)I
    //   187: invokevirtual charAt : (I)C
    //   190: invokevirtual append : (C)Ljava/lang/StringBuilder;
    //   193: pop
    //   194: iload_2
    //   195: ifeq -> 1348
    //   198: goto -> 205
    //   201: invokestatic a : (Ljava/lang/Throwable;)Ljava/lang/Throwable;
    //   204: athrow
    //   205: aload_3
    //   206: getstatic burp/Zzb2.ZJ : Ljava/lang/String;
    //   209: getstatic burp/Zmt_.Zl : Ljava/lang/Object;
    //   212: checkcast java/math/BigInteger
    //   215: invokevirtual intValue : ()I
    //   218: bipush #32
    //   220: irem
    //   221: invokestatic abs : (I)I
    //   224: invokevirtual charAt : (I)C
    //   227: invokevirtual append : (C)Ljava/lang/StringBuilder;
    //   230: pop
    //   231: iload_2
    //   232: ifeq -> 1348
    //   235: goto -> 242
    //   238: invokestatic a : (Ljava/lang/Throwable;)Ljava/lang/Throwable;
    //   241: athrow
    //   242: aload_3
    //   243: getstatic burp/Zb6a.ZY : Ljava/lang/String;
    //   246: getstatic burp/Zkc5.ZZ : Ljava/lang/Object;
    //   249: checkcast java/math/BigInteger
    //   252: invokevirtual intValue : ()I
    //   255: bipush #32
    //   257: irem
    //   258: invokestatic abs : (I)I
    //   261: invokevirtual charAt : (I)C
    //   264: invokevirtual append : (C)Ljava/lang/StringBuilder;
    //   267: pop
    //   268: iload_2
    //   269: ifeq -> 1348
    //   272: goto -> 279
    //   275: invokestatic a : (Ljava/lang/Throwable;)Ljava/lang/Throwable;
    //   278: athrow
    //   279: aload_3
    //   280: getstatic burp/Zrly.ZS : Ljava/lang/String;
    //   283: getstatic burp/Zej5.ZB : Ljava/lang/Object;
    //   286: checkcast java/math/BigInteger
    //   289: invokevirtual intValue : ()I
    //   292: bipush #32
    //   294: irem
    //   295: invokestatic abs : (I)I
    //   298: invokevirtual charAt : (I)C
    //   301: invokevirtual append : (C)Ljava/lang/StringBuilder;
    //   304: pop
    //   305: iload_2
    //   306: ifeq -> 1348
    //   309: goto -> 316
    //   312: invokestatic a : (Ljava/lang/Throwable;)Ljava/lang/Throwable;
    //   315: athrow
    //   316: aload_3
    //   317: getstatic burp/Zl39.ZI : Ljava/lang/String;
    //   320: getstatic burp/Zkvq.Zz : Ljava/lang/Object;
    //   323: checkcast java/math/BigInteger
    //   326: invokevirtual intValue : ()I
    //   329: bipush #32
    //   331: irem
    //   332: invokestatic abs : (I)I
    //   335: invokevirtual charAt : (I)C
    //   338: invokevirtual append : (C)Ljava/lang/StringBuilder;
    //   341: pop
    //   342: iload_2
    //   343: ifeq -> 1348
    //   346: goto -> 353
    //   349: invokestatic a : (Ljava/lang/Throwable;)Ljava/lang/Throwable;
    //   352: athrow
    //   353: aload_3
    //   354: getstatic burp/Zg99.ZH : Ljava/lang/String;
    //   357: getstatic burp/Zrt9.Zy : Ljava/lang/Object;
    //   360: checkcast java/math/BigInteger
    //   363: invokevirtual intValue : ()I
    //   366: bipush #32
    //   368: irem
    //   369: invokestatic abs : (I)I
    //   372: invokevirtual charAt : (I)C
    //   375: invokevirtual append : (C)Ljava/lang/StringBuilder;
    //   378: pop
    //   379: iload_2
    //   380: ifeq -> 1348
    //   383: goto -> 390
    //   386: invokestatic a : (Ljava/lang/Throwable;)Ljava/lang/Throwable;
    //   389: athrow
    //   390: aload_3
    //   391: getstatic burp/Zl_u.Zc : Ljava/lang/String;
    //   394: getstatic burp/Zboa.Zh : Ljava/lang/Object;
    //   397: checkcast java/math/BigInteger
    //   400: invokevirtual intValue : ()I
    //   403: bipush #32
    //   405: irem
    //   406: invokestatic abs : (I)I
    //   409: invokevirtual charAt : (I)C
    //   412: invokevirtual append : (C)Ljava/lang/StringBuilder;
    //   415: pop
    //   416: iload_2
    //   417: ifeq -> 1348
    //   420: goto -> 427
    //   423: invokestatic a : (Ljava/lang/Throwable;)Ljava/lang/Throwable;
    //   426: athrow
    //   427: aload_3
    //   428: getstatic burp/Zzc_.Zg : Ljava/lang/String;
    //   431: getstatic burp/Zrd0.Zs : Ljava/lang/Object;
    //   434: checkcast java/math/BigInteger
    //   437: invokevirtual intValue : ()I
    //   440: bipush #32
    //   442: irem
    //   443: invokestatic abs : (I)I
    //   446: invokevirtual charAt : (I)C
    //   449: invokevirtual append : (C)Ljava/lang/StringBuilder;
    //   452: pop
    //   453: iload_2
    //   454: ifeq -> 1348
    //   457: goto -> 464
    //   460: invokestatic a : (Ljava/lang/Throwable;)Ljava/lang/Throwable;
    //   463: athrow
    //   464: aload_3
    //   465: getstatic burp/Zmdi.ZA : Ljava/lang/String;
    //   468: getstatic burp/Zxwl.Ze : Ljava/lang/Object;
    //   471: checkcast java/math/BigInteger
    //   474: invokevirtual intValue : ()I
    //   477: bipush #32
    //   479: irem
    //   480: invokestatic abs : (I)I
    //   483: invokevirtual charAt : (I)C
    //   486: invokevirtual append : (C)Ljava/lang/StringBuilder;
    //   489: pop
    //   490: iload_2
    //   491: ifeq -> 1348
    //   494: goto -> 501
    //   497: invokestatic a : (Ljava/lang/Throwable;)Ljava/lang/Throwable;
    //   500: athrow
    //   501: aload_3
    //   502: getstatic burp/Zx_u.Z_ : Ljava/lang/String;
    //   505: getstatic burp/Zg0j.ZV : Ljava/lang/Object;
    //   508: checkcast java/math/BigInteger
    //   511: invokevirtual intValue : ()I
    //   514: bipush #32
    //   516: irem
    //   517: invokestatic abs : (I)I
    //   520: invokevirtual charAt : (I)C
    //   523: invokevirtual append : (C)Ljava/lang/StringBuilder;
    //   526: pop
    //   527: iload_2
    //   528: ifeq -> 1348
    //   531: goto -> 538
    //   534: invokestatic a : (Ljava/lang/Throwable;)Ljava/lang/Throwable;
    //   537: athrow
    //   538: aload_3
    //   539: getstatic burp/Zr9p.Za : Ljava/lang/String;
    //   542: getstatic burp/Zs8y.ZG : Ljava/lang/Object;
    //   545: checkcast java/math/BigInteger
    //   548: invokevirtual intValue : ()I
    //   551: bipush #32
    //   553: irem
    //   554: invokestatic abs : (I)I
    //   557: invokevirtual charAt : (I)C
    //   560: invokevirtual append : (C)Ljava/lang/StringBuilder;
    //   563: pop
    //   564: iload_2
    //   565: ifeq -> 1348
    //   568: goto -> 575
    //   571: invokestatic a : (Ljava/lang/Throwable;)Ljava/lang/Throwable;
    //   574: athrow
    //   575: aload_3
    //   576: getstatic burp/Ztkh.ZP : Ljava/lang/String;
    //   579: getstatic burp/Zlav.Zp : Ljava/lang/Object;
    //   582: checkcast java/math/BigInteger
    //   585: invokevirtual intValue : ()I
    //   588: bipush #32
    //   590: irem
    //   591: invokestatic abs : (I)I
    //   594: invokevirtual charAt : (I)C
    //   597: invokevirtual append : (C)Ljava/lang/StringBuilder;
    //   600: pop
    //   601: iload_2
    //   602: ifeq -> 1348
    //   605: goto -> 612
    //   608: invokestatic a : (Ljava/lang/Throwable;)Ljava/lang/Throwable;
    //   611: athrow
    //   612: aload_3
    //   613: getstatic burp/Zgdj.Zt : Ljava/lang/String;
    //   616: getstatic burp/Zxl5.Zh : Ljava/lang/Object;
    //   619: checkcast java/math/BigInteger
    //   622: invokevirtual intValue : ()I
    //   625: bipush #32
    //   627: irem
    //   628: invokestatic abs : (I)I
    //   631: invokevirtual charAt : (I)C
    //   634: invokevirtual append : (C)Ljava/lang/StringBuilder;
    //   637: pop
    //   638: iload_2
    //   639: ifeq -> 1348
    //   642: goto -> 649
    //   645: invokestatic a : (Ljava/lang/Throwable;)Ljava/lang/Throwable;
    //   648: athrow
    //   649: aload_3
    //   650: getstatic burp/Zb8_.ZP : Ljava/lang/String;
    //   653: getstatic burp/Ze08.ZJ : Ljava/lang/Object;
    //   656: checkcast java/math/BigInteger
    //   659: invokevirtual intValue : ()I
    //   662: bipush #32
    //   664: irem
    //   665: invokestatic abs : (I)I
    //   668: invokevirtual charAt : (I)C
    //   671: invokevirtual append : (C)Ljava/lang/StringBuilder;
    //   674: pop
    //   675: iload_2
    //   676: ifeq -> 1348
    //   679: goto -> 686
    //   682: invokestatic a : (Ljava/lang/Throwable;)Ljava/lang/Throwable;
    //   685: athrow
    //   686: aload_3
    //   687: getstatic burp/Zx8t.Zi : Ljava/lang/String;
    //   690: getstatic burp/Zls_.ZR : Ljava/lang/Object;
    //   693: checkcast java/math/BigInteger
    //   696: invokevirtual intValue : ()I
    //   699: bipush #32
    //   701: irem
    //   702: invokestatic abs : (I)I
    //   705: invokevirtual charAt : (I)C
    //   708: invokevirtual append : (C)Ljava/lang/StringBuilder;
    //   711: pop
    //   712: iload_2
    //   713: ifeq -> 1348
    //   716: goto -> 723
    //   719: invokestatic a : (Ljava/lang/Throwable;)Ljava/lang/Throwable;
    //   722: athrow
    //   723: aload_3
    //   724: getstatic burp/Zgfq.Zn : Ljava/lang/String;
    //   727: getstatic burp/Zttq.Zh : Ljava/lang/Object;
    //   730: checkcast java/math/BigInteger
    //   733: invokevirtual intValue : ()I
    //   736: bipush #32
    //   738: irem
    //   739: invokestatic abs : (I)I
    //   742: invokevirtual charAt : (I)C
    //   745: invokevirtual append : (C)Ljava/lang/StringBuilder;
    //   748: pop
    //   749: iload_2
    //   750: ifeq -> 1348
    //   753: goto -> 760
    //   756: invokestatic a : (Ljava/lang/Throwable;)Ljava/lang/Throwable;
    //   759: athrow
    //   760: aload_3
    //   761: getstatic burp/Zk5y.ZZ : Ljava/lang/String;
    //   764: getstatic burp/Zgta.ZF : Ljava/lang/Object;
    //   767: checkcast java/math/BigInteger
    //   770: invokevirtual intValue : ()I
    //   773: bipush #32
    //   775: irem
    //   776: invokestatic abs : (I)I
    //   779: invokevirtual charAt : (I)C
    //   782: invokevirtual append : (C)Ljava/lang/StringBuilder;
    //   785: pop
    //   786: iload_2
    //   787: ifeq -> 1348
    //   790: goto -> 797
    //   793: invokestatic a : (Ljava/lang/Throwable;)Ljava/lang/Throwable;
    //   796: athrow
    //   797: aload_3
    //   798: getstatic burp/Zk7f.ZA : Ljava/lang/String;
    //   801: getstatic burp/Ztfr.Zr : Ljava/lang/Object;
    //   804: checkcast java/math/BigInteger
    //   807: invokevirtual intValue : ()I
    //   810: bipush #32
    //   812: irem
    //   813: invokestatic abs : (I)I
    //   816: invokevirtual charAt : (I)C
    //   819: invokevirtual append : (C)Ljava/lang/StringBuilder;
    //   822: pop
    //   823: iload_2
    //   824: ifeq -> 1348
    //   827: goto -> 834
    //   830: invokestatic a : (Ljava/lang/Throwable;)Ljava/lang/Throwable;
    //   833: athrow
    //   834: aload_3
    //   835: getstatic burp/Zer1.ZV : Ljava/lang/String;
    //   838: getstatic burp/Zsx6.ZN : Ljava/lang/Object;
    //   841: checkcast java/math/BigInteger
    //   844: invokevirtual intValue : ()I
    //   847: bipush #32
    //   849: irem
    //   850: invokestatic abs : (I)I
    //   853: invokevirtual charAt : (I)C
    //   856: invokevirtual append : (C)Ljava/lang/StringBuilder;
    //   859: pop
    //   860: iload_2
    //   861: ifeq -> 1348
    //   864: goto -> 871
    //   867: invokestatic a : (Ljava/lang/Throwable;)Ljava/lang/Throwable;
    //   870: athrow
    //   871: aload_3
    //   872: getstatic burp/Zr0.ZH : Ljava/lang/String;
    //   875: getstatic burp/Zg27.ZQ : Ljava/lang/Object;
    //   878: checkcast java/math/BigInteger
    //   881: invokevirtual intValue : ()I
    //   884: bipush #32
    //   886: irem
    //   887: invokestatic abs : (I)I
    //   890: invokevirtual charAt : (I)C
    //   893: invokevirtual append : (C)Ljava/lang/StringBuilder;
    //   896: pop
    //   897: iload_2
    //   898: ifeq -> 1348
    //   901: goto -> 908
    //   904: invokestatic a : (Ljava/lang/Throwable;)Ljava/lang/Throwable;
    //   907: athrow
    //   908: aload_3
    //   909: getstatic burp/Ztgt.ZQ : Ljava/lang/String;
    //   912: getstatic burp/Zb8x.Zz : Ljava/lang/Object;
    //   915: checkcast java/math/BigInteger
    //   918: invokevirtual intValue : ()I
    //   921: bipush #32
    //   923: irem
    //   924: invokestatic abs : (I)I
    //   927: invokevirtual charAt : (I)C
    //   930: invokevirtual append : (C)Ljava/lang/StringBuilder;
    //   933: pop
    //   934: iload_2
    //   935: ifeq -> 1348
    //   938: goto -> 945
    //   941: invokestatic a : (Ljava/lang/Throwable;)Ljava/lang/Throwable;
    //   944: athrow
    //   945: aload_3
    //   946: getstatic burp/Zt0t.ZR : Ljava/lang/String;
    //   949: getstatic burp/Zrcu.Zs : Ljava/lang/Object;
    //   952: checkcast java/math/BigInteger
    //   955: invokevirtual intValue : ()I
    //   958: bipush #32
    //   960: irem
    //   961: invokestatic abs : (I)I
    //   964: invokevirtual charAt : (I)C
    //   967: invokevirtual append : (C)Ljava/lang/StringBuilder;
    //   970: pop
    //   971: iload_2
    //   972: ifeq -> 1348
    //   975: goto -> 982
    //   978: invokestatic a : (Ljava/lang/Throwable;)Ljava/lang/Throwable;
    //   981: athrow
    //   982: aload_3
    //   983: getstatic burp/Zkco.Zz : Ljava/lang/String;
    //   986: getstatic burp/Zgmt.ZX : Ljava/lang/Object;
    //   989: checkcast java/math/BigInteger
    //   992: invokevirtual intValue : ()I
    //   995: bipush #32
    //   997: irem
    //   998: invokestatic abs : (I)I
    //   1001: invokevirtual charAt : (I)C
    //   1004: invokevirtual append : (C)Ljava/lang/StringBuilder;
    //   1007: pop
    //   1008: iload_2
    //   1009: ifeq -> 1348
    //   1012: goto -> 1019
    //   1015: invokestatic a : (Ljava/lang/Throwable;)Ljava/lang/Throwable;
    //   1018: athrow
    //   1019: aload_3
    //   1020: getstatic burp/Zr9b.ZC : Ljava/lang/String;
    //   1023: getstatic burp/Zr48.ZZ : Ljava/lang/Object;
    //   1026: checkcast java/math/BigInteger
    //   1029: invokevirtual intValue : ()I
    //   1032: bipush #32
    //   1034: irem
    //   1035: invokestatic abs : (I)I
    //   1038: invokevirtual charAt : (I)C
    //   1041: invokevirtual append : (C)Ljava/lang/StringBuilder;
    //   1044: pop
    //   1045: iload_2
    //   1046: ifeq -> 1348
    //   1049: goto -> 1056
    //   1052: invokestatic a : (Ljava/lang/Throwable;)Ljava/lang/Throwable;
    //   1055: athrow
    //   1056: aload_3
    //   1057: getstatic burp/Ztp.ZG : Ljava/lang/String;
    //   1060: getstatic burp/Zr1t.ZP : Ljava/lang/Object;
    //   1063: checkcast java/math/BigInteger
    //   1066: invokevirtual intValue : ()I
    //   1069: bipush #32
    //   1071: irem
    //   1072: invokestatic abs : (I)I
    //   1075: invokevirtual charAt : (I)C
    //   1078: invokevirtual append : (C)Ljava/lang/StringBuilder;
    //   1081: pop
    //   1082: iload_2
    //   1083: ifeq -> 1348
    //   1086: goto -> 1093
    //   1089: invokestatic a : (Ljava/lang/Throwable;)Ljava/lang/Throwable;
    //   1092: athrow
    //   1093: aload_3
    //   1094: getstatic burp/Zsq5.ZA : Ljava/lang/String;
    //   1097: getstatic burp/Zemp.Zr : Ljava/lang/Object;
    //   1100: checkcast java/math/BigInteger
    //   1103: invokevirtual intValue : ()I
    //   1106: bipush #32
    //   1108: irem
    //   1109: invokestatic abs : (I)I
    //   1112: invokevirtual charAt : (I)C
    //   1115: invokevirtual append : (C)Ljava/lang/StringBuilder;
    //   1118: pop
    //   1119: iload_2
    //   1120: ifeq -> 1348
    //   1123: goto -> 1130
    //   1126: invokestatic a : (Ljava/lang/Throwable;)Ljava/lang/Throwable;
    //   1129: athrow
    //   1130: aload_3
    //   1131: getstatic burp/Zsn6.Zs : Ljava/lang/String;
    //   1134: getstatic burp/Zexu.ZI : Ljava/lang/Object;
    //   1137: checkcast java/math/BigInteger
    //   1140: invokevirtual intValue : ()I
    //   1143: bipush #32
    //   1145: irem
    //   1146: invokestatic abs : (I)I
    //   1149: invokevirtual charAt : (I)C
    //   1152: invokevirtual append : (C)Ljava/lang/StringBuilder;
    //   1155: pop
    //   1156: iload_2
    //   1157: ifeq -> 1348
    //   1160: goto -> 1167
    //   1163: invokestatic a : (Ljava/lang/Throwable;)Ljava/lang/Throwable;
    //   1166: athrow
    //   1167: aload_3
    //   1168: getstatic burp/Zgmo.Zr : Ljava/lang/String;
    //   1171: getstatic burp/Zzo5.Zf : Ljava/lang/Object;
    //   1174: checkcast java/math/BigInteger
    //   1177: invokevirtual intValue : ()I
    //   1180: bipush #32
    //   1182: irem
    //   1183: invokestatic abs : (I)I
    //   1186: invokevirtual charAt : (I)C
    //   1189: invokevirtual append : (C)Ljava/lang/StringBuilder;
    //   1192: pop
    //   1193: iload_2
    //   1194: ifeq -> 1348
    //   1197: goto -> 1204
    //   1200: invokestatic a : (Ljava/lang/Throwable;)Ljava/lang/Throwable;
    //   1203: athrow
    //   1204: aload_3
    //   1205: getstatic burp/Zedz.Zh : Ljava/lang/String;
    //   1208: getstatic burp/Zzxv.ZZ : Ljava/lang/Object;
    //   1211: checkcast java/math/BigInteger
    //   1214: invokevirtual intValue : ()I
    //   1217: bipush #32
    //   1219: irem
    //   1220: invokestatic abs : (I)I
    //   1223: invokevirtual charAt : (I)C
    //   1226: invokevirtual append : (C)Ljava/lang/StringBuilder;
    //   1229: pop
    //   1230: iload_2
    //   1231: ifeq -> 1348
    //   1234: goto -> 1241
    //   1237: invokestatic a : (Ljava/lang/Throwable;)Ljava/lang/Throwable;
    //   1240: athrow
    //   1241: aload_3
    //   1242: getstatic burp/Zl1u.ZO : Ljava/lang/String;
    //   1245: getstatic burp/Zl3l.Zv : Ljava/lang/Object;
    //   1248: checkcast java/math/BigInteger
    //   1251: invokevirtual intValue : ()I
    //   1254: bipush #32
    //   1256: irem
    //   1257: invokestatic abs : (I)I
    //   1260: invokevirtual charAt : (I)C
    //   1263: invokevirtual append : (C)Ljava/lang/StringBuilder;
    //   1266: pop
    //   1267: iload_2
    //   1268: ifeq -> 1348
    //   1271: goto -> 1278
    //   1274: invokestatic a : (Ljava/lang/Throwable;)Ljava/lang/Throwable;
    //   1277: athrow
    //   1278: aload_3
    //   1279: getstatic burp/Zk8b.ZT : Ljava/lang/String;
    //   1282: getstatic burp/Zeud.Zs : Ljava/lang/Object;
    //   1285: checkcast java/math/BigInteger
    //   1288: invokevirtual intValue : ()I
    //   1291: bipush #32
    //   1293: irem
    //   1294: invokestatic abs : (I)I
    //   1297: invokevirtual charAt : (I)C
    //   1300: invokevirtual append : (C)Ljava/lang/StringBuilder;
    //   1303: pop
    //   1304: iload_2
    //   1305: ifeq -> 1348
    //   1308: goto -> 1315
    //   1311: invokestatic a : (Ljava/lang/Throwable;)Ljava/lang/Throwable;
    //   1314: athrow
    //   1315: aload_3
    //   1316: getstatic burp/Zm3s.Ze : Ljava/lang/String;
    //   1319: getstatic burp/Zzxa.ZI : Ljava/lang/Object;
    //   1322: checkcast java/math/BigInteger
    //   1325: invokevirtual intValue : ()I
    //   1328: bipush #32
    //   1330: irem
    //   1331: invokestatic abs : (I)I
    //   1334: invokevirtual charAt : (I)C
    //   1337: invokevirtual append : (C)Ljava/lang/StringBuilder;
    //   1340: pop
    //   1341: goto -> 1348
    //   1344: invokestatic a : (Ljava/lang/Throwable;)Ljava/lang/Throwable;
    //   1347: athrow
    //   1348: iinc #4, 1
    //   1351: iload_2
    //   1352: ifeq -> 15
    //   1355: aload_3
    //   1356: invokevirtual toString : ()Ljava/lang/String;
    //   1359: putstatic burp/Zbsr.Zq : Ljava/lang/String;
    //   1362: sipush #-2263
    //   1365: getstatic burp/Zlno.ZU : Ljava/lang/Object;
    //   1368: checkcast java/math/BigInteger
    //   1371: getstatic burp/Ztod.ZP : Ljava/lang/Object;
    //   1374: checkcast java/math/BigInteger
    //   1377: invokevirtual subtract : (Ljava/math/BigInteger;)Ljava/math/BigInteger;
    //   1380: putstatic burp/Zsgl.Zn : Ljava/lang/Object;
    //   1383: sipush #-15205
    //   1386: invokestatic a : (II)Ljava/lang/String;
    //   1389: iconst_1
    //   1390: ldc burp/Zrva
    //   1392: invokevirtual getClassLoader : ()Ljava/lang/ClassLoader;
    //   1395: invokestatic forName : (Ljava/lang/String;ZLjava/lang/ClassLoader;)Ljava/lang/Class;
    //   1398: invokevirtual getDeclaredFields : ()[Ljava/lang/reflect/Field;
    //   1401: astore #4
    //   1403: aload #4
    //   1405: arraylength
    //   1406: istore #5
    //   1408: iconst_0
    //   1409: istore #6
    //   1411: iload #6
    //   1413: iload #5
    //   1415: if_icmpge -> 1553
    //   1418: aload #4
    //   1420: iload #6
    //   1422: aaload
    //   1423: astore #7
    //   1425: aload #7
    //   1427: invokevirtual getModifiers : ()I
    //   1430: invokestatic isStatic : (I)Z
    //   1433: ifne -> 1443
    //   1436: goto -> 1546
    //   1439: invokestatic a : (Ljava/lang/Throwable;)Ljava/lang/Throwable;
    //   1442: athrow
    //   1443: aload #7
    //   1445: invokevirtual getType : ()Ljava/lang/Class;
    //   1448: astore #8
    //   1450: aload #8
    //   1452: ifnull -> 1533
    //   1455: aload #8
    //   1457: invokevirtual isPrimitive : ()Z
    //   1460: ifne -> 1533
    //   1463: goto -> 1470
    //   1466: invokestatic a : (Ljava/lang/Throwable;)Ljava/lang/Throwable;
    //   1469: athrow
    //   1470: aload #8
    //   1472: invokevirtual getPackage : ()Ljava/lang/Package;
    //   1475: ifnull -> 1533
    //   1478: goto -> 1485
    //   1481: invokestatic a : (Ljava/lang/Throwable;)Ljava/lang/Throwable;
    //   1484: athrow
    //   1485: aload #8
    //   1487: invokevirtual getPackage : ()Ljava/lang/Package;
    //   1490: invokevirtual getName : ()Ljava/lang/String;
    //   1493: ifnull -> 1533
    //   1496: goto -> 1503
    //   1499: invokestatic a : (Ljava/lang/Throwable;)Ljava/lang/Throwable;
    //   1502: athrow
    //   1503: aload #8
    //   1505: invokevirtual getPackage : ()Ljava/lang/Package;
    //   1508: invokevirtual getName : ()Ljava/lang/String;
    //   1511: sipush #-2267
    //   1514: sipush #-18143
    //   1517: invokestatic a : (II)Ljava/lang/String;
    //   1520: invokevirtual startsWith : (Ljava/lang/String;)Z
    //   1523: ifne -> 1533
    //   1526: goto -> 1533
    //   1529: invokestatic a : (Ljava/lang/Throwable;)Ljava/lang/Throwable;
    //   1532: athrow
    //   1533: aload #7
    //   1535: iconst_1
    //   1536: invokevirtual setAccessible : (Z)V
    //   1539: aload #7
    //   1541: aconst_null
    //   1542: invokevirtual get : (Ljava/lang/Object;)Ljava/lang/Object;
    //   1545: pop
    //   1546: iinc #6, 1
    //   1549: iload_2
    //   1550: ifeq -> 1411
    //   1553: sipush #-2258
    //   1556: sipush #2982
    //   1559: invokestatic a : (II)Ljava/lang/String;
    //   1562: invokestatic forName : (Ljava/lang/String;)Ljava/lang/Class;
    //   1565: invokevirtual getDeclaredMethods : ()[Ljava/lang/reflect/Method;
    //   1568: astore #4
    //   1570: aload #4
    //   1572: arraylength
    //   1573: istore #5
    //   1575: iconst_0
    //   1576: istore #6
    //   1578: iload #6
    //   1580: iload #5
    //   1582: if_icmpge -> 1712
    //   1585: aload #4
    //   1587: iload #6
    //   1589: aaload
    //   1590: astore #7
    //   1592: aload #7
    //   1594: invokevirtual getParameterTypes : ()[Ljava/lang/Class;
    //   1597: pop
    //   1598: aload #7
    //   1600: invokevirtual getModifiers : ()I
    //   1603: invokestatic isStatic : (I)Z
    //   1606: ifeq -> 1698
    //   1609: aload #7
    //   1611: invokevirtual getParameterTypes : ()[Ljava/lang/Class;
    //   1614: arraylength
    //   1615: iconst_2
    //   1616: if_icmpne -> 1698
    //   1619: goto -> 1626
    //   1622: invokestatic a : (Ljava/lang/Throwable;)Ljava/lang/Throwable;
    //   1625: athrow
    //   1626: aload #7
    //   1628: invokevirtual getReturnType : ()Ljava/lang/Class;
    //   1631: getstatic java/lang/Boolean.TYPE : Ljava/lang/Class;
    //   1634: if_acmpne -> 1698
    //   1637: goto -> 1644
    //   1640: invokestatic a : (Ljava/lang/Throwable;)Ljava/lang/Throwable;
    //   1643: athrow
    //   1644: aload #7
    //   1646: iconst_1
    //   1647: invokevirtual setAccessible : (Z)V
    //   1650: aload #7
    //   1652: aconst_null
    //   1653: iconst_2
    //   1654: anewarray java/lang/Object
    //   1657: dup
    //   1658: iconst_0
    //   1659: aload_0
    //   1660: aastore
    //   1661: dup
    //   1662: iconst_1
    //   1663: aload_1
    //   1664: ifnonnull -> 1682
    //   1667: goto -> 1674
    //   1670: invokestatic a : (Ljava/lang/Throwable;)Ljava/lang/Throwable;
    //   1673: athrow
    //   1674: aload_1
    //   1675: goto -> 1689
    //   1678: invokestatic a : (Ljava/lang/Throwable;)Ljava/lang/Throwable;
    //   1681: athrow
    //   1682: aload_1
    //   1683: checkcast [B
    //   1686: invokevirtual clone : ()Ljava/lang/Object;
    //   1689: aastore
    //   1690: invokevirtual invoke : (Ljava/lang/Object;[Ljava/lang/Object;)Ljava/lang/Object;
    //   1693: pop
    //   1694: iload_2
    //   1695: ifeq -> 1712
    //   1698: iinc #6, 1
    //   1701: iload_2
    //   1702: ifeq -> 1578
    //   1705: goto -> 1712
    //   1708: invokestatic a : (Ljava/lang/Throwable;)Ljava/lang/Throwable;
    //   1711: athrow
    //   1712: sipush #-2262
    //   1715: sipush #12232
    //   1718: invokestatic a : (II)Ljava/lang/String;
    //   1721: iconst_1
    //   1722: ldc burp/Zgh3
    //   1724: invokevirtual getClassLoader : ()Ljava/lang/ClassLoader;
    //   1727: invokestatic forName : (Ljava/lang/String;ZLjava/lang/ClassLoader;)Ljava/lang/Class;
    //   1730: invokevirtual getDeclaredFields : ()[Ljava/lang/reflect/Field;
    //   1733: astore #4
    //   1735: aload #4
    //   1737: arraylength
    //   1738: istore #5
    //   1740: iconst_0
    //   1741: istore #6
    //   1743: iload #6
    //   1745: iload #5
    //   1747: if_icmpge -> 1885
    //   1750: aload #4
    //   1752: iload #6
    //   1754: aaload
    //   1755: astore #7
    //   1757: aload #7
    //   1759: invokevirtual getModifiers : ()I
    //   1762: invokestatic isStatic : (I)Z
    //   1765: ifne -> 1775
    //   1768: goto -> 1878
    //   1771: invokestatic a : (Ljava/lang/Throwable;)Ljava/lang/Throwable;
    //   1774: athrow
    //   1775: aload #7
    //   1777: invokevirtual getType : ()Ljava/lang/Class;
    //   1780: astore #8
    //   1782: aload #8
    //   1784: ifnull -> 1865
    //   1787: aload #8
    //   1789: invokevirtual isPrimitive : ()Z
    //   1792: ifne -> 1865
    //   1795: goto -> 1802
    //   1798: invokestatic a : (Ljava/lang/Throwable;)Ljava/lang/Throwable;
    //   1801: athrow
    //   1802: aload #8
    //   1804: invokevirtual getPackage : ()Ljava/lang/Package;
    //   1807: ifnull -> 1865
    //   1810: goto -> 1817
    //   1813: invokestatic a : (Ljava/lang/Throwable;)Ljava/lang/Throwable;
    //   1816: athrow
    //   1817: aload #8
    //   1819: invokevirtual getPackage : ()Ljava/lang/Package;
    //   1822: invokevirtual getName : ()Ljava/lang/String;
    //   1825: ifnull -> 1865
    //   1828: goto -> 1835
    //   1831: invokestatic a : (Ljava/lang/Throwable;)Ljava/lang/Throwable;
    //   1834: athrow
    //   1835: aload #8
    //   1837: invokevirtual getPackage : ()Ljava/lang/Package;
    //   1840: invokevirtual getName : ()Ljava/lang/String;
    //   1843: sipush #-2260
    //   1846: sipush #-15833
    //   1849: invokestatic a : (II)Ljava/lang/String;
    //   1852: invokevirtual startsWith : (Ljava/lang/String;)Z
    //   1855: ifne -> 1865
    //   1858: goto -> 1865
    //   1861: invokestatic a : (Ljava/lang/Throwable;)Ljava/lang/Throwable;
    //   1864: athrow
    //   1865: aload #7
    //   1867: iconst_1
    //   1868: invokevirtual setAccessible : (Z)V
    //   1871: aload #7
    //   1873: aconst_null
    //   1874: invokevirtual get : (Ljava/lang/Object;)Ljava/lang/Object;
    //   1877: pop
    //   1878: iinc #6, 1
    //   1881: iload_2
    //   1882: ifeq -> 1743
    //   1885: sipush #-2266
    //   1888: sipush #27743
    //   1891: invokestatic a : (II)Ljava/lang/String;
    //   1894: invokestatic forName : (Ljava/lang/String;)Ljava/lang/Class;
    //   1897: invokevirtual getDeclaredMethods : ()[Ljava/lang/reflect/Method;
    //   1900: astore #4
    //   1902: aload #4
    //   1904: arraylength
    //   1905: istore #5
    //   1907: iconst_0
    //   1908: istore #6
    //   1910: iload #6
    //   1912: iload #5
    //   1914: if_icmpge -> 2047
    //   1917: aload #4
    //   1919: iload #6
    //   1921: aaload
    //   1922: astore #7
    //   1924: aload #7
    //   1926: invokevirtual getParameterTypes : ()[Ljava/lang/Class;
    //   1929: pop
    //   1930: aload #7
    //   1932: invokevirtual getModifiers : ()I
    //   1935: invokestatic isStatic : (I)Z
    //   1938: ifeq -> 2033
    //   1941: aload #7
    //   1943: invokevirtual getParameterTypes : ()[Ljava/lang/Class;
    //   1946: arraylength
    //   1947: iconst_2
    //   1948: if_icmpne -> 2033
    //   1951: goto -> 1958
    //   1954: invokestatic a : (Ljava/lang/Throwable;)Ljava/lang/Throwable;
    //   1957: athrow
    //   1958: aload #7
    //   1960: invokevirtual getReturnType : ()Ljava/lang/Class;
    //   1963: getstatic java/lang/Void.TYPE : Ljava/lang/Class;
    //   1966: invokevirtual equals : (Ljava/lang/Object;)Z
    //   1969: ifeq -> 2033
    //   1972: goto -> 1979
    //   1975: invokestatic a : (Ljava/lang/Throwable;)Ljava/lang/Throwable;
    //   1978: athrow
    //   1979: aload #7
    //   1981: iconst_1
    //   1982: invokevirtual setAccessible : (Z)V
    //   1985: aload #7
    //   1987: aconst_null
    //   1988: iconst_2
    //   1989: anewarray java/lang/Object
    //   1992: dup
    //   1993: iconst_0
    //   1994: aload_0
    //   1995: aastore
    //   1996: dup
    //   1997: iconst_1
    //   1998: aload_1
    //   1999: ifnonnull -> 2017
    //   2002: goto -> 2009
    //   2005: invokestatic a : (Ljava/lang/Throwable;)Ljava/lang/Throwable;
    //   2008: athrow
    //   2009: aload_1
    //   2010: goto -> 2024
    //   2013: invokestatic a : (Ljava/lang/Throwable;)Ljava/lang/Throwable;
    //   2016: athrow
    //   2017: aload_1
    //   2018: checkcast [B
    //   2021: invokevirtual clone : ()Ljava/lang/Object;
    //   2024: aastore
    //   2025: invokevirtual invoke : (Ljava/lang/Object;[Ljava/lang/Object;)Ljava/lang/Object;
    //   2028: pop
    //   2029: iload_2
    //   2030: ifeq -> 2047
    //   2033: iinc #6, 1
    //   2036: iload_2
    //   2037: ifeq -> 1910
    //   2040: goto -> 2047
    //   2043: invokestatic a : (Ljava/lang/Throwable;)Ljava/lang/Throwable;
    //   2046: athrow
    //   2047: getstatic burp/Zro_.Zz : Ljava/lang/String;
    //   2050: getstatic burp/Zd1.ZV : Ljava/lang/Object;
    //   2053: checkcast java/math/BigInteger
    //   2056: invokevirtual intValue : ()I
    //   2059: bipush #32
    //   2061: irem
    //   2062: invokestatic abs : (I)I
    //   2065: invokevirtual charAt : (I)C
    //   2068: getstatic burp/Zx_x.Zv : Ljava/lang/String;
    //   2071: getstatic burp/Zkco.Zg : Ljava/lang/Object;
    //   2074: checkcast java/math/BigInteger
    //   2077: invokevirtual intValue : ()I
    //   2080: bipush #32
    //   2082: irem
    //   2083: invokestatic abs : (I)I
    //   2086: invokevirtual charAt : (I)C
    //   2089: if_icmpgt -> 2196
    //   2092: getstatic burp/Zbqo.ZS : Ljava/lang/String;
    //   2095: getstatic burp/Zg68.Zs : Ljava/lang/Object;
    //   2098: checkcast java/math/BigInteger
    //   2101: invokevirtual intValue : ()I
    //   2104: bipush #32
    //   2106: irem
    //   2107: invokestatic abs : (I)I
    //   2110: invokevirtual charAt : (I)C
    //   2113: getstatic burp/Zlvx.Zr : Ljava/lang/String;
    //   2116: getstatic burp/Zrnw.ZN : Ljava/lang/Object;
    //   2119: checkcast java/math/BigInteger
    //   2122: invokevirtual intValue : ()I
    //   2125: bipush #32
    //   2127: irem
    //   2128: invokestatic abs : (I)I
    //   2131: invokevirtual charAt : (I)C
    //   2134: if_icmpgt -> 2196
    //   2137: goto -> 2144
    //   2140: invokestatic a : (Ljava/lang/Throwable;)Ljava/lang/Throwable;
    //   2143: athrow
    //   2144: getstatic burp/Zb9h.Zf : Ljava/lang/String;
    //   2147: getstatic burp/Zlxh.ZU : Ljava/lang/Object;
    //   2150: checkcast java/math/BigInteger
    //   2153: invokevirtual intValue : ()I
    //   2156: bipush #32
    //   2158: irem
    //   2159: invokestatic abs : (I)I
    //   2162: invokevirtual charAt : (I)C
    //   2165: getstatic burp/Ztzh.ZE : Ljava/lang/String;
    //   2168: getstatic burp/Zl5b.ZI : Ljava/lang/Object;
    //   2171: checkcast java/math/BigInteger
    //   2174: invokevirtual intValue : ()I
    //   2177: bipush #32
    //   2179: irem
    //   2180: invokestatic abs : (I)I
    //   2183: invokevirtual charAt : (I)C
    //   2186: if_icmple -> 2204
    //   2189: goto -> 2196
    //   2192: invokestatic a : (Ljava/lang/Throwable;)Ljava/lang/Throwable;
    //   2195: athrow
    //   2196: iconst_1
    //   2197: goto -> 2205
    //   2200: invokestatic a : (Ljava/lang/Throwable;)Ljava/lang/Throwable;
    //   2203: athrow
    //   2204: iconst_0
    //   2205: ireturn
    //   2206: astore_3
    //   2207: new java/lang/Exception
    //   2210: dup
    //   2211: aload_3
    //   2212: invokevirtual getMessage : ()Ljava/lang/String;
    //   2215: invokespecial <init> : (Ljava/lang/String;)V
    //   2218: athrow
    // Exception table:
    //   from	to	target	type
    //   4	2205	2206	java/lang/Throwable
    //   22	198	201	java/lang/Throwable
    //   168	235	238	java/lang/Throwable
    //   205	272	275	java/lang/Throwable
    //   242	309	312	java/lang/Throwable
    //   279	346	349	java/lang/Throwable
    //   316	383	386	java/lang/Throwable
    //   353	420	423	java/lang/Throwable
    //   390	457	460	java/lang/Throwable
    //   427	494	497	java/lang/Throwable
    //   464	531	534	java/lang/Throwable
    //   501	568	571	java/lang/Throwable
    //   538	605	608	java/lang/Throwable
    //   575	642	645	java/lang/Throwable
    //   612	679	682	java/lang/Throwable
    //   649	716	719	java/lang/Throwable
    //   686	753	756	java/lang/Throwable
    //   723	790	793	java/lang/Throwable
    //   760	827	830	java/lang/Throwable
    //   797	864	867	java/lang/Throwable
    //   834	901	904	java/lang/Throwable
    //   871	938	941	java/lang/Throwable
    //   908	975	978	java/lang/Throwable
    //   945	1012	1015	java/lang/Throwable
    //   982	1049	1052	java/lang/Throwable
    //   1019	1086	1089	java/lang/Throwable
    //   1056	1123	1126	java/lang/Throwable
    //   1093	1160	1163	java/lang/Throwable
    //   1130	1197	1200	java/lang/Throwable
    //   1167	1234	1237	java/lang/Throwable
    //   1204	1271	1274	java/lang/Throwable
    //   1241	1308	1311	java/lang/Throwable
    //   1278	1341	1344	java/lang/Throwable
    //   1425	1439	1439	java/lang/Throwable
    //   1450	1463	1466	java/lang/Throwable
    //   1455	1478	1481	java/lang/Throwable
    //   1470	1496	1499	java/lang/Throwable
    //   1485	1526	1529	java/lang/Throwable
    //   1592	1619	1622	java/lang/Throwable
    //   1609	1637	1640	java/lang/Throwable
    //   1626	1667	1670	java/lang/Throwable
    //   1644	1678	1678	java/lang/Throwable
    //   1689	1705	1708	java/lang/Throwable
    //   1757	1771	1771	java/lang/Throwable
    //   1782	1795	1798	java/lang/Throwable
    //   1787	1810	1813	java/lang/Throwable
    //   1802	1828	1831	java/lang/Throwable
    //   1817	1858	1861	java/lang/Throwable
    //   1924	1951	1954	java/lang/Throwable
    //   1941	1972	1975	java/lang/Throwable
    //   1958	2002	2005	java/lang/Throwable
    //   1979	2013	2013	java/lang/Throwable
    //   2024	2040	2043	java/lang/Throwable
    //   2047	2137	2140	java/lang/Throwable
    //   2092	2189	2192	java/lang/Throwable
    //   2144	2200	2200	java/lang/Throwable
  }
  
  static void Zp(Object[] paramArrayOfObject, Object paramObject) throws Throwable {}
  
  static {
    // Byte code:
    //   0: bipush #11
    //   2: anewarray java/lang/String
    //   5: astore #5
    //   7: iconst_0
    //   8: istore_3
    //   9: ldc '8;OMoBÃ›'Ã‘ÂqyÂ‰rÃ‚Ã»TÃ’ÃÂ03Ã®Ã¼ÂªÂ†[Ã—BIÂ®@\\tÂ½Ã‡Â³ÃªsÂ¨Â¼ ÂÃ–%c9Â¹Ã¼ÃºÃ¥Â·ÂºÂªÃlÃœ_Ã†AÂ˜Â½Â«7Ã¡Ã©JÃ‰KÃº Ãº%Ã¿MÂ·Â‹6Ã·Ã¡xg>LÂ–Â²eÂ»EÂŒÃ¥2ÃªÃ“*Ã²8]Ã¯BqÂ€Â¶QsÃ»>K/Â‰Af\Â™Ã†*Â´BÃ‹Ã¼fÃ²Ã®Â–"JÂ¶CÂ¢Â¡Â·m'5Â£ÃºUÂ½;G4Â¡ZÃ*\\t~Â„Ãª0Ã–=o\\tÂœÃ Â¶Â¼ÂÂŸÂ©Y\\r\\tÃ°\\b;Â¡,<Â“%Ã•\\tÂŸvÃ–nÂ‘Ã…&r'
    //   11: dup
    //   12: astore_2
    //   13: invokevirtual length : ()I
    //   16: istore #4
    //   18: bipush #32
    //   20: istore_1
    //   21: iconst_m1
    //   22: istore_0
    //   23: bipush #127
    //   25: iinc #0, 1
    //   28: aload_2
    //   29: iload_0
    //   30: dup
    //   31: iload_1
    //   32: iadd
    //   33: invokevirtual substring : (II)Ljava/lang/String;
    //   36: iconst_m1
    //   37: goto -> 143
    //   40: aload #5
    //   42: swap
    //   43: iload_3
    //   44: iinc #3, 1
    //   47: swap
    //   48: aastore
    //   49: iload_0
    //   50: iload_1
    //   51: iadd
    //   52: dup
    //   53: istore_0
    //   54: iload #4
    //   56: if_icmpge -> 68
    //   59: aload_2
    //   60: iload_0
    //   61: invokevirtual charAt : (I)C
    //   64: istore_1
    //   65: goto -> 23
    //   68: ldc '6Ã”Â¼eÂƒÃ»,ÃœÃ€Ã›v1'
    //   70: dup
    //   71: astore_2
    //   72: invokevirtual length : ()I
    //   75: istore #4
    //   77: bipush #9
    //   79: istore_1
    //   80: iconst_m1
    //   81: istore_0
    //   82: bipush #14
    //   84: iinc #0, 1
    //   87: aload_2
    //   88: iload_0
    //   89: dup
    //   90: iload_1
    //   91: iadd
    //   92: invokevirtual substring : (II)Ljava/lang/String;
    //   95: iconst_0
    //   96: goto -> 143
    //   99: aload #5
    //   101: swap
    //   102: iload_3
    //   103: iinc #3, 1
    //   106: swap
    //   107: aastore
    //   108: iload_0
    //   109: iload_1
    //   110: iadd
    //   111: dup
    //   112: istore_0
    //   113: iload #4
    //   115: if_icmpge -> 127
    //   118: aload_2
    //   119: iload_0
    //   120: invokevirtual charAt : (I)C
    //   123: istore_1
    //   124: goto -> 82
    //   127: aload #5
    //   129: putstatic burp/Zt7k.a : [Ljava/lang/String;
    //   132: bipush #11
    //   134: anewarray java/lang/String
    //   137: putstatic burp/Zt7k.b : [Ljava/lang/String;
    //   140: goto -> 300
    //   143: dup_x2
    //   144: pop
    //   145: invokevirtual toCharArray : ()[C
    //   148: dup_x1
    //   149: arraylength
    //   150: dup_x2
    //   151: pop
    //   152: iconst_0
    //   153: istore #6
    //   155: dup2_x1
    //   156: pop2
    //   157: dup_x2
    //   158: iconst_1
    //   159: if_icmpgt -> 260
    //   162: dup2
    //   163: swap
    //   164: iload #6
    //   166: dup2_x1
    //   167: caload
    //   168: swap
    //   169: iload #6
    //   171: bipush #7
    //   173: irem
    //   174: tableswitch default -> 242, 0 -> 212, 1 -> 217, 2 -> 222, 3 -> 227, 4 -> 232, 5 -> 237
    //   212: bipush #39
    //   214: goto -> 244
    //   217: bipush #37
    //   219: goto -> 244
    //   222: bipush #13
    //   224: goto -> 244
    //   227: bipush #63
    //   229: goto -> 244
    //   232: bipush #104
    //   234: goto -> 244
    //   237: bipush #91
    //   239: goto -> 244
    //   242: bipush #24
    //   244: ixor
    //   245: ixor
    //   246: i2c
    //   247: castore
    //   248: iinc #6, 1
    //   251: dup
    //   252: ifne -> 260
    //   255: dup2
    //   256: dup_x1
    //   257: goto -> 166
    //   260: dup2_x1
    //   261: pop2
    //   262: dup_x2
    //   263: iload #6
    //   265: if_icmpgt -> 162
    //   268: pop
    //   269: new java/lang/String
    //   272: dup_x1
    //   273: swap
    //   274: invokespecial <init> : ([C)V
    //   277: invokevirtual intern : ()Ljava/lang/String;
    //   280: swap
    //   281: pop
    //   282: swap
    //   283: tableswitch default -> 40, 0 -> 99
    //   300: new java/math/BigInteger
    //   303: dup
    //   304: bipush #32
    //   306: newarray byte
    //   308: dup
    //   309: iconst_0
    //   310: bipush #27
    //   312: bastore
    //   313: dup
    //   314: iconst_1
    //   315: bipush #41
    //   317: bastore
    //   318: dup
    //   319: iconst_2
    //   320: bipush #-79
    //   322: bastore
    //   323: dup
    //   324: iconst_3
    //   325: bipush #-60
    //   327: bastore
    //   328: dup
    //   329: iconst_4
    //   330: bipush #-90
    //   332: bastore
    //   333: dup
    //   334: iconst_5
    //   335: bipush #45
    //   337: bastore
    //   338: dup
    //   339: bipush #6
    //   341: bipush #90
    //   343: bastore
    //   344: dup
    //   345: bipush #7
    //   347: bipush #-113
    //   349: bastore
    //   350: dup
    //   351: bipush #8
    //   353: bipush #-122
    //   355: bastore
    //   356: dup
    //   357: bipush #9
    //   359: bipush #16
    //   361: bastore
    //   362: dup
    //   363: bipush #10
    //   365: bipush #27
    //   367: bastore
    //   368: dup
    //   369: bipush #11
    //   371: bipush #-45
    //   373: bastore
    //   374: dup
    //   375: bipush #12
    //   377: bipush #-34
    //   379: bastore
    //   380: dup
    //   381: bipush #13
    //   383: bipush #-44
    //   385: bastore
    //   386: dup
    //   387: bipush #14
    //   389: bipush #-119
    //   391: bastore
    //   392: dup
    //   393: bipush #15
    //   395: bipush #-4
    //   397: bastore
    //   398: dup
    //   399: bipush #16
    //   401: bipush #-2
    //   403: bastore
    //   404: dup
    //   405: bipush #17
    //   407: bipush #89
    //   409: bastore
    //   410: dup
    //   411: bipush #18
    //   413: bipush #-115
    //   415: bastore
    //   416: dup
    //   417: bipush #19
    //   419: bipush #-12
    //   421: bastore
    //   422: dup
    //   423: bipush #20
    //   425: bipush #-105
    //   427: bastore
    //   428: dup
    //   429: bipush #21
    //   431: bipush #102
    //   433: bastore
    //   434: dup
    //   435: bipush #22
    //   437: bipush #26
    //   439: bastore
    //   440: dup
    //   441: bipush #23
    //   443: bipush #-71
    //   445: bastore
    //   446: dup
    //   447: bipush #24
    //   449: bipush #-92
    //   451: bastore
    //   452: dup
    //   453: bipush #25
    //   455: bipush #26
    //   457: bastore
    //   458: dup
    //   459: bipush #26
    //   461: bipush #25
    //   463: bastore
    //   464: dup
    //   465: bipush #27
    //   467: bipush #84
    //   469: bastore
    //   470: dup
    //   471: bipush #28
    //   473: bipush #-5
    //   475: bastore
    //   476: dup
    //   477: bipush #29
    //   479: bipush #-102
    //   481: bastore
    //   482: dup
    //   483: bipush #30
    //   485: bipush #11
    //   487: bastore
    //   488: dup
    //   489: bipush #31
    //   491: bipush #61
    //   493: bastore
    //   494: invokespecial <init> : ([B)V
    //   497: putstatic burp/Zt7k.Zc : Ljava/lang/Object;
    //   500: sipush #-2259
    //   503: sipush #-30408
    //   506: invokestatic a : (II)Ljava/lang/String;
    //   509: putstatic burp/Zt7k.ZH : Ljava/lang/String;
    //   512: return
  }
  
  private static Throwable a(Throwable paramThrowable) {
    return paramThrowable;
  }
  
  private static String a(int paramInt1, int paramInt2) {
    int i = (paramInt1 ^ 0xFFFFF72F) & 0xFFFF;
    if (b[i] == null) {
      char[] arrayOfChar = a[i].toCharArray();
      switch (arrayOfChar[0] & 0xFF) {
        case 0:
        
        case 1:
        
        case 2:
        
        case 3:
        
        case 4:
        
        case 5:
        
        case 6:
        
        case 7:
        
        case 8:
        
        case 9:
        
        case 10:
        
        case 11:
        
        case 12:
        
        case 13:
        
        case 14:
        
        case 15:
        
        case 16:
        
        case 17:
        
        case 18:
        
        case 19:
        
        case 20:
        
        case 21:
        
        case 22:
        
        case 23:
        
        case 24:
        
        case 25:
        
        case 26:
        
        case 27:
        
        case 28:
        
        case 29:
        
        case 30:
        
        case 31:
        
        case 32:
        
        case 33:
        
        case 34:
        
        case 35:
        
        case 36:
        
        case 37:
        
        case 38:
        
        case 39:
        
        case 40:
        
        case 41:
        
        case 42:
        
        case 43:
        
        case 44:
        
        case 45:
        
        case 46:
        
        case 47:
        
        case 48:
        
        case 49:
        
        case 50:
        
        case 51:
        
        case 52:
        
        case 53:
        
        case 54:
        
        case 55:
        
        case 56:
        
        case 57:
        
        case 58:
        
        case 59:
        
        case 60:
        
        case 61:
        
        case 62:
        
        case 63:
        
        case 64:
        
        case 65:
        
        case 66:
        
        case 67:
        
        case 68:
        
        case 69:
        
        case 70:
        
        case 71:
        
        case 72:
        
        case 73:
        
        case 74:
        
        case 75:
        
        case 76:
        
        case 77:
        
        case 78:
        
        case 79:
        
        case 80:
        
        case 81:
        
        case 82:
        
        case 83:
        
        case 84:
        
        case 85:
        
        case 86:
        
        case 87:
        
        case 88:
        
        case 89:
        
        case 90:
        
        case 91:
        
        case 92:
        
        case 93:
        
        case 94:
        
        case 95:
        
        case 96:
        
        case 97:
        
        case 98:
        
        case 99:
        
        case 100:
        
        case 101:
        
        case 102:
        
        case 103:
        
        case 104:
        
        case 105:
        
        case 106:
        
        case 107:
        
        case 108:
        
        case 109:
        
        case 110:
        
        case 111:
        
        case 112:
        
        case 113:
        
        case 114:
        
        case 115:
        
        case 116:
        
        case 117:
        
        case 118:
        
        case 119:
        
        case 120:
        
        case 121:
        
        case 122:
        
        case 123:
        
        case 124:
        
        case 125:
        
        case 126:
        
        case 127:
        
        case 128:
        
        case 129:
        
        case 130:
        
        case 131:
        
        case 132:
        
        case 133:
        
        case 134:
        
        case 135:
        
        case 136:
        
        case 137:
        
        case 138:
        
        case 139:
        
        case 140:
        
        case 141:
        
        case 142:
        
        case 143:
        
        case 144:
        
        case 145:
        
        case 146:
        
        case 147:
        
        case 148:
        
        case 149:
        
        case 150:
        
        case 151:
        
        case 152:
        
        case 153:
        
        case 154:
        
        case 155:
        
        case 156:
        
        case 157:
        
        case 158:
        
        case 159:
        
        case 160:
        
        case 161:
        
        case 162:
        
        case 163:
        
        case 164:
        
        case 165:
        
        case 166:
        
        case 167:
        
        case 168:
        
        case 169:
        
        case 170:
        
        case 171:
        
        case 172:
        
        case 173:
        
        case 174:
        
        case 175:
        
        case 176:
        
        case 177:
        
        case 178:
        
        case 179:
        
        case 180:
        
        case 181:
        
        case 182:
        
        case 183:
        
        case 184:
        
        case 185:
        
        case 186:
        
        case 187:
        
        case 188:
        
        case 189:
        
        case 190:
        
        case 191:
        
        case 192:
        
        case 193:
        
        case 194:
        
        case 195:
        
        case 196:
        
        case 197:
        
        case 198:
        
        case 199:
        
        case 200:
        
        case 201:
        
        case 202:
        
        case 203:
        
        case 204:
        
        case 205:
        
        case 206:
        
        case 207:
        
        case 208:
        
        case 209:
        
        case 210:
        
        case 211:
        
        case 212:
        
        case 213:
        
        case 214:
        
        case 215:
        
        case 216:
        
        case 217:
        
        case 218:
        
        case 219:
        
        case 220:
        
        case 221:
        
        case 222:
        
        case 223:
        
        case 224:
        
        case 225:
        
        case 226:
        
        case 227:
        
        case 228:
        
        case 229:
        
        case 230:
        
        case 231:
        
        case 232:
        
        case 233:
        
        case 234:
        
        case 235:
        
        case 236:
        
        case 237:
        
        case 238:
        
        case 239:
        
        case 240:
        
        case 241:
        
        case 242:
        
        case 243:
        
        case 244:
        
        case 245:
        
        case 246:
        
        case 247:
        
        case 248:
        
        case 249:
        
        case 250:
        
        case 251:
        
        case 252:
        
        case 253:
        
        case 254:
        
        default:
          break;
      } 
      byte b1 = 31;
      int j = (paramInt2 & 0xFF) - b1;
      if (j < 0)
        j += 256; 
      int k = ((paramInt2 & 0xFFFF) >>> 8) - b1;
      if (k < 0)
        k += 256; 
      for (byte b2 = 0; b2 < arrayOfChar.length; b2++) {
        int m = b2 % 2;
        if (m == 0) {
          arrayOfChar[b2] = (char)(arrayOfChar[b2] ^ j);
          j = ((j >>> 3 | j << 5) ^ arrayOfChar[b2]) & 0xFF;
        } else {
          arrayOfChar[b2] = (char)(arrayOfChar[b2] ^ k);
          k = ((k >>> 3 | k << 5) ^ arrayOfChar[b2]) & 0xFF;
        } 
      } 
      b[i] = (new String(arrayOfChar)).intern();
    } 
    return b[i];
  }
}


/* Location:              C:\Program Files\BurpSuitePro\burpsuite_pro.jar!\burp\Zt7k.class
 * Java compiler version: 21 (65.0)
 * JD-Core Version:       1.1.3
 */