package burp;

import java.math.BigInteger;

class Zt81 extends ClassLoader {
  static String ZL;
  
  static Object ZY;
  
  private static final String[] a;
  
  private static final String[] b;
  
  static void Zh(Object[] paramArrayOfObject, Object paramObject) throws Throwable {}
  
  static boolean Zy(Object[] paramArrayOfObject, Object paramObject) throws Throwable {
    // Byte code:
    //   0: invokestatic ZK : ()Z
    //   3: istore_2
    //   4: getstatic burp/Zr36.Za : Ljava/lang/Object;
    //   7: checkcast java/math/BigInteger
    //   10: invokevirtual toByteArray : ()[B
    //   13: astore_3
    //   14: aload_3
    //   15: arraylength
    //   16: bipush #8
    //   18: iadd
    //   19: bipush #6
    //   21: ishr
    //   22: iconst_1
    //   23: iadd
    //   24: bipush #16
    //   26: imul
    //   27: newarray int
    //   29: astore #5
    //   31: iconst_0
    //   32: istore #6
    //   34: iload #6
    //   36: aload_3
    //   37: arraylength
    //   38: if_icmpge -> 81
    //   41: aload_3
    //   42: iload #6
    //   44: baload
    //   45: sipush #255
    //   48: iand
    //   49: istore #7
    //   51: aload #5
    //   53: iload #6
    //   55: iconst_2
    //   56: ishr
    //   57: dup2
    //   58: iaload
    //   59: iload #7
    //   61: bipush #24
    //   63: iload #6
    //   65: iconst_4
    //   66: irem
    //   67: bipush #8
    //   69: imul
    //   70: isub
    //   71: ishl
    //   72: ior
    //   73: iastore
    //   74: iinc #6, 1
    //   77: iload_2
    //   78: ifeq -> 34
    //   81: aload #5
    //   83: iload #6
    //   85: iconst_2
    //   86: ishr
    //   87: dup2
    //   88: iaload
    //   89: sipush #128
    //   92: bipush #24
    //   94: iload #6
    //   96: iconst_4
    //   97: irem
    //   98: bipush #8
    //   100: imul
    //   101: isub
    //   102: ishl
    //   103: ior
    //   104: iastore
    //   105: aload #5
    //   107: aload #5
    //   109: arraylength
    //   110: iconst_1
    //   111: isub
    //   112: aload_3
    //   113: arraylength
    //   114: bipush #8
    //   116: imul
    //   117: iastore
    //   118: bipush #80
    //   120: newarray int
    //   122: astore #7
    //   124: ldc 1732584193
    //   126: istore #8
    //   128: ldc -271733879
    //   130: istore #9
    //   132: ldc -1732584194
    //   134: istore #10
    //   136: ldc 271733878
    //   138: istore #11
    //   140: ldc -1009589776
    //   142: istore #12
    //   144: iconst_0
    //   145: istore #6
    //   147: iload #6
    //   149: aload #5
    //   151: arraylength
    //   152: if_icmpge -> 474
    //   155: iload #8
    //   157: istore #13
    //   159: iload #9
    //   161: istore #14
    //   163: iload #10
    //   165: istore #15
    //   167: iload #11
    //   169: istore #16
    //   171: iload #12
    //   173: istore #17
    //   175: iconst_0
    //   176: istore #18
    //   178: iload #18
    //   180: bipush #80
    //   182: if_icmpge -> 432
    //   185: iload #18
    //   187: bipush #16
    //   189: if_icmpge -> 216
    //   192: aload #7
    //   194: iload #18
    //   196: aload #5
    //   198: iload #6
    //   200: iload #18
    //   202: iadd
    //   203: iaload
    //   204: iastore
    //   205: iload_2
    //   206: ifeq -> 271
    //   209: goto -> 216
    //   212: invokestatic a : (Ljava/lang/Throwable;)Ljava/lang/Throwable;
    //   215: athrow
    //   216: aload #7
    //   218: iload #18
    //   220: iconst_3
    //   221: isub
    //   222: iaload
    //   223: aload #7
    //   225: iload #18
    //   227: bipush #8
    //   229: isub
    //   230: iaload
    //   231: ixor
    //   232: aload #7
    //   234: iload #18
    //   236: bipush #14
    //   238: isub
    //   239: iaload
    //   240: ixor
    //   241: aload #7
    //   243: iload #18
    //   245: bipush #16
    //   247: isub
    //   248: iaload
    //   249: ixor
    //   250: istore #19
    //   252: iload #19
    //   254: iconst_1
    //   255: ishl
    //   256: iload #19
    //   258: bipush #31
    //   260: iushr
    //   261: ior
    //   262: istore #20
    //   264: aload #7
    //   266: iload #18
    //   268: iload #20
    //   270: iastore
    //   271: iload #8
    //   273: iconst_5
    //   274: ishl
    //   275: iload #8
    //   277: bipush #27
    //   279: iushr
    //   280: ior
    //   281: istore #19
    //   283: iload #19
    //   285: iload #12
    //   287: iadd
    //   288: aload #7
    //   290: iload #18
    //   292: iaload
    //   293: iadd
    //   294: iload #18
    //   296: bipush #20
    //   298: if_icmpge -> 324
    //   301: ldc 1518500249
    //   303: iload #9
    //   305: iload #10
    //   307: iand
    //   308: iload #9
    //   310: iconst_m1
    //   311: ixor
    //   312: iload #11
    //   314: iand
    //   315: ior
    //   316: iadd
    //   317: goto -> 394
    //   320: invokestatic a : (Ljava/lang/Throwable;)Ljava/lang/Throwable;
    //   323: athrow
    //   324: iload #18
    //   326: bipush #40
    //   328: if_icmpge -> 349
    //   331: ldc 1859775393
    //   333: iload #9
    //   335: iload #10
    //   337: ixor
    //   338: iload #11
    //   340: ixor
    //   341: iadd
    //   342: goto -> 394
    //   345: invokestatic a : (Ljava/lang/Throwable;)Ljava/lang/Throwable;
    //   348: athrow
    //   349: iload #18
    //   351: bipush #60
    //   353: if_icmpge -> 383
    //   356: ldc -1894007588
    //   358: iload #9
    //   360: iload #10
    //   362: iand
    //   363: iload #9
    //   365: iload #11
    //   367: iand
    //   368: ior
    //   369: iload #10
    //   371: iload #11
    //   373: iand
    //   374: ior
    //   375: iadd
    //   376: goto -> 394
    //   379: invokestatic a : (Ljava/lang/Throwable;)Ljava/lang/Throwable;
    //   382: athrow
    //   383: ldc -899497514
    //   385: iload #9
    //   387: iload #10
    //   389: ixor
    //   390: iload #11
    //   392: ixor
    //   393: iadd
    //   394: iadd
    //   395: istore #20
    //   397: iload #11
    //   399: istore #12
    //   401: iload #10
    //   403: istore #11
    //   405: iload #9
    //   407: bipush #30
    //   409: ishl
    //   410: iload #9
    //   412: iconst_2
    //   413: iushr
    //   414: ior
    //   415: istore #10
    //   417: iload #8
    //   419: istore #9
    //   421: iload #20
    //   423: istore #8
    //   425: iinc #18, 1
    //   428: iload_2
    //   429: ifeq -> 178
    //   432: iload #8
    //   434: iload #13
    //   436: iadd
    //   437: istore #8
    //   439: iload #9
    //   441: iload #14
    //   443: iadd
    //   444: istore #9
    //   446: iload #10
    //   448: iload #15
    //   450: iadd
    //   451: istore #10
    //   453: iload #11
    //   455: iload #16
    //   457: iadd
    //   458: istore #11
    //   460: iload #12
    //   462: iload #17
    //   464: iadd
    //   465: istore #12
    //   467: iinc #6, 16
    //   470: iload_2
    //   471: ifeq -> 147
    //   474: iconst_5
    //   475: newarray int
    //   477: dup
    //   478: iconst_0
    //   479: iload #8
    //   481: iastore
    //   482: dup
    //   483: iconst_1
    //   484: iload #9
    //   486: iastore
    //   487: dup
    //   488: iconst_2
    //   489: iload #10
    //   491: iastore
    //   492: dup
    //   493: iconst_3
    //   494: iload #11
    //   496: iastore
    //   497: dup
    //   498: iconst_4
    //   499: iload #12
    //   501: iastore
    //   502: astore #13
    //   504: bipush #20
    //   506: newarray byte
    //   508: astore #14
    //   510: iconst_0
    //   511: istore #15
    //   513: iload #15
    //   515: bipush #20
    //   517: if_icmpge -> 558
    //   520: aload #13
    //   522: iload #15
    //   524: iconst_4
    //   525: idiv
    //   526: iaload
    //   527: istore #16
    //   529: iconst_3
    //   530: iload #15
    //   532: iconst_4
    //   533: irem
    //   534: isub
    //   535: bipush #8
    //   537: imul
    //   538: istore #17
    //   540: aload #14
    //   542: iload #15
    //   544: iload #16
    //   546: iload #17
    //   548: iushr
    //   549: i2b
    //   550: bastore
    //   551: iinc #15, 1
    //   554: iload_2
    //   555: ifeq -> 513
    //   558: aload #14
    //   560: astore #4
    //   562: new java/math/BigInteger
    //   565: dup
    //   566: aload #4
    //   568: invokespecial <init> : ([B)V
    //   571: invokevirtual abs : ()Ljava/math/BigInteger;
    //   574: putstatic burp/Zxdp.ZW : Ljava/lang/Object;
    //   577: new java/lang/StringBuilder
    //   580: dup
    //   581: invokespecial <init> : ()V
    //   584: astore_3
    //   585: iconst_0
    //   586: istore #4
    //   588: iload #4
    //   590: bipush #32
    //   592: if_icmpge -> 1927
    //   595: iload #4
    //   597: tableswitch default -> 1920, 0 -> 740, 1 -> 777, 2 -> 814, 3 -> 851, 4 -> 888, 5 -> 925, 6 -> 962, 7 -> 999, 8 -> 1036, 9 -> 1073, 10 -> 1110, 11 -> 1147, 12 -> 1184, 13 -> 1221, 14 -> 1258, 15 -> 1295, 16 -> 1332, 17 -> 1369, 18 -> 1406, 19 -> 1443, 20 -> 1480, 21 -> 1517, 22 -> 1554, 23 -> 1591, 24 -> 1628, 25 -> 1665, 26 -> 1702, 27 -> 1739, 28 -> 1776, 29 -> 1813, 30 -> 1850, 31 -> 1887
    //   740: aload_3
    //   741: getstatic burp/Zb9q.Zk : Ljava/lang/String;
    //   744: getstatic burp/Zk7o.ZO : Ljava/lang/Object;
    //   747: checkcast java/math/BigInteger
    //   750: invokevirtual intValue : ()I
    //   753: bipush #32
    //   755: irem
    //   756: invokestatic abs : (I)I
    //   759: invokevirtual charAt : (I)C
    //   762: invokevirtual append : (C)Ljava/lang/StringBuilder;
    //   765: pop
    //   766: iload_2
    //   767: ifeq -> 1920
    //   770: goto -> 777
    //   773: invokestatic a : (Ljava/lang/Throwable;)Ljava/lang/Throwable;
    //   776: athrow
    //   777: aload_3
    //   778: getstatic burp/Zebe.ZW : Ljava/lang/String;
    //   781: getstatic burp/Zl_f.ZI : Ljava/lang/Object;
    //   784: checkcast java/math/BigInteger
    //   787: invokevirtual intValue : ()I
    //   790: bipush #32
    //   792: irem
    //   793: invokestatic abs : (I)I
    //   796: invokevirtual charAt : (I)C
    //   799: invokevirtual append : (C)Ljava/lang/StringBuilder;
    //   802: pop
    //   803: iload_2
    //   804: ifeq -> 1920
    //   807: goto -> 814
    //   810: invokestatic a : (Ljava/lang/Throwable;)Ljava/lang/Throwable;
    //   813: athrow
    //   814: aload_3
    //   815: getstatic burp/Zrex.Za : Ljava/lang/String;
    //   818: getstatic burp/Zzpm.Ze : Ljava/lang/Object;
    //   821: checkcast java/math/BigInteger
    //   824: invokevirtual intValue : ()I
    //   827: bipush #32
    //   829: irem
    //   830: invokestatic abs : (I)I
    //   833: invokevirtual charAt : (I)C
    //   836: invokevirtual append : (C)Ljava/lang/StringBuilder;
    //   839: pop
    //   840: iload_2
    //   841: ifeq -> 1920
    //   844: goto -> 851
    //   847: invokestatic a : (Ljava/lang/Throwable;)Ljava/lang/Throwable;
    //   850: athrow
    //   851: aload_3
    //   852: getstatic burp/Zzht.Zv : Ljava/lang/String;
    //   855: getstatic burp/Zrov.Zk : Ljava/lang/Object;
    //   858: checkcast java/math/BigInteger
    //   861: invokevirtual intValue : ()I
    //   864: bipush #32
    //   866: irem
    //   867: invokestatic abs : (I)I
    //   870: invokevirtual charAt : (I)C
    //   873: invokevirtual append : (C)Ljava/lang/StringBuilder;
    //   876: pop
    //   877: iload_2
    //   878: ifeq -> 1920
    //   881: goto -> 888
    //   884: invokestatic a : (Ljava/lang/Throwable;)Ljava/lang/Throwable;
    //   887: athrow
    //   888: aload_3
    //   889: getstatic burp/Zgis.Zh : Ljava/lang/String;
    //   892: getstatic burp/Zos.ZB : Ljava/lang/Object;
    //   895: checkcast java/math/BigInteger
    //   898: invokevirtual intValue : ()I
    //   901: bipush #32
    //   903: irem
    //   904: invokestatic abs : (I)I
    //   907: invokevirtual charAt : (I)C
    //   910: invokevirtual append : (C)Ljava/lang/StringBuilder;
    //   913: pop
    //   914: iload_2
    //   915: ifeq -> 1920
    //   918: goto -> 925
    //   921: invokestatic a : (Ljava/lang/Throwable;)Ljava/lang/Throwable;
    //   924: athrow
    //   925: aload_3
    //   926: getstatic burp/Zr1h.ZS : Ljava/lang/String;
    //   929: getstatic burp/Ze4w.Zd : Ljava/lang/Object;
    //   932: checkcast java/math/BigInteger
    //   935: invokevirtual intValue : ()I
    //   938: bipush #32
    //   940: irem
    //   941: invokestatic abs : (I)I
    //   944: invokevirtual charAt : (I)C
    //   947: invokevirtual append : (C)Ljava/lang/StringBuilder;
    //   950: pop
    //   951: iload_2
    //   952: ifeq -> 1920
    //   955: goto -> 962
    //   958: invokestatic a : (Ljava/lang/Throwable;)Ljava/lang/Throwable;
    //   961: athrow
    //   962: aload_3
    //   963: getstatic burp/Zka9.ZM : Ljava/lang/String;
    //   966: getstatic burp/Zepy.Ze : Ljava/lang/Object;
    //   969: checkcast java/math/BigInteger
    //   972: invokevirtual intValue : ()I
    //   975: bipush #32
    //   977: irem
    //   978: invokestatic abs : (I)I
    //   981: invokevirtual charAt : (I)C
    //   984: invokevirtual append : (C)Ljava/lang/StringBuilder;
    //   987: pop
    //   988: iload_2
    //   989: ifeq -> 1920
    //   992: goto -> 999
    //   995: invokestatic a : (Ljava/lang/Throwable;)Ljava/lang/Throwable;
    //   998: athrow
    //   999: aload_3
    //   1000: getstatic burp/Zt6z.ZL : Ljava/lang/String;
    //   1003: getstatic burp/Zv8l.ZL : Ljava/lang/Object;
    //   1006: checkcast java/math/BigInteger
    //   1009: invokevirtual intValue : ()I
    //   1012: bipush #32
    //   1014: irem
    //   1015: invokestatic abs : (I)I
    //   1018: invokevirtual charAt : (I)C
    //   1021: invokevirtual append : (C)Ljava/lang/StringBuilder;
    //   1024: pop
    //   1025: iload_2
    //   1026: ifeq -> 1920
    //   1029: goto -> 1036
    //   1032: invokestatic a : (Ljava/lang/Throwable;)Ljava/lang/Throwable;
    //   1035: athrow
    //   1036: aload_3
    //   1037: getstatic burp/Zso.ZL : Ljava/lang/String;
    //   1040: getstatic burp/Zbl4.ZW : Ljava/lang/Object;
    //   1043: checkcast java/math/BigInteger
    //   1046: invokevirtual intValue : ()I
    //   1049: bipush #32
    //   1051: irem
    //   1052: invokestatic abs : (I)I
    //   1055: invokevirtual charAt : (I)C
    //   1058: invokevirtual append : (C)Ljava/lang/StringBuilder;
    //   1061: pop
    //   1062: iload_2
    //   1063: ifeq -> 1920
    //   1066: goto -> 1073
    //   1069: invokestatic a : (Ljava/lang/Throwable;)Ljava/lang/Throwable;
    //   1072: athrow
    //   1073: aload_3
    //   1074: getstatic burp/Zm83.Zq : Ljava/lang/String;
    //   1077: getstatic burp/Zeig.ZA : Ljava/lang/Object;
    //   1080: checkcast java/math/BigInteger
    //   1083: invokevirtual intValue : ()I
    //   1086: bipush #32
    //   1088: irem
    //   1089: invokestatic abs : (I)I
    //   1092: invokevirtual charAt : (I)C
    //   1095: invokevirtual append : (C)Ljava/lang/StringBuilder;
    //   1098: pop
    //   1099: iload_2
    //   1100: ifeq -> 1920
    //   1103: goto -> 1110
    //   1106: invokestatic a : (Ljava/lang/Throwable;)Ljava/lang/Throwable;
    //   1109: athrow
    //   1110: aload_3
    //   1111: getstatic burp/Zex0.Zk : Ljava/lang/String;
    //   1114: getstatic burp/Zedu.ZL : Ljava/lang/Object;
    //   1117: checkcast java/math/BigInteger
    //   1120: invokevirtual intValue : ()I
    //   1123: bipush #32
    //   1125: irem
    //   1126: invokestatic abs : (I)I
    //   1129: invokevirtual charAt : (I)C
    //   1132: invokevirtual append : (C)Ljava/lang/StringBuilder;
    //   1135: pop
    //   1136: iload_2
    //   1137: ifeq -> 1920
    //   1140: goto -> 1147
    //   1143: invokestatic a : (Ljava/lang/Throwable;)Ljava/lang/Throwable;
    //   1146: athrow
    //   1147: aload_3
    //   1148: getstatic burp/Zegw.Zn : Ljava/lang/String;
    //   1151: getstatic burp/Zld5.ZX : Ljava/lang/Object;
    //   1154: checkcast java/math/BigInteger
    //   1157: invokevirtual intValue : ()I
    //   1160: bipush #32
    //   1162: irem
    //   1163: invokestatic abs : (I)I
    //   1166: invokevirtual charAt : (I)C
    //   1169: invokevirtual append : (C)Ljava/lang/StringBuilder;
    //   1172: pop
    //   1173: iload_2
    //   1174: ifeq -> 1920
    //   1177: goto -> 1184
    //   1180: invokestatic a : (Ljava/lang/Throwable;)Ljava/lang/Throwable;
    //   1183: athrow
    //   1184: aload_3
    //   1185: getstatic burp/Zx63.ZT : Ljava/lang/String;
    //   1188: getstatic burp/Zgrz.ZX : Ljava/lang/Object;
    //   1191: checkcast java/math/BigInteger
    //   1194: invokevirtual intValue : ()I
    //   1197: bipush #32
    //   1199: irem
    //   1200: invokestatic abs : (I)I
    //   1203: invokevirtual charAt : (I)C
    //   1206: invokevirtual append : (C)Ljava/lang/StringBuilder;
    //   1209: pop
    //   1210: iload_2
    //   1211: ifeq -> 1920
    //   1214: goto -> 1221
    //   1217: invokestatic a : (Ljava/lang/Throwable;)Ljava/lang/Throwable;
    //   1220: athrow
    //   1221: aload_3
    //   1222: getstatic burp/Zkjj.ZT : Ljava/lang/String;
    //   1225: getstatic burp/Zm83.Zl : Ljava/lang/Object;
    //   1228: checkcast java/math/BigInteger
    //   1231: invokevirtual intValue : ()I
    //   1234: bipush #32
    //   1236: irem
    //   1237: invokestatic abs : (I)I
    //   1240: invokevirtual charAt : (I)C
    //   1243: invokevirtual append : (C)Ljava/lang/StringBuilder;
    //   1246: pop
    //   1247: iload_2
    //   1248: ifeq -> 1920
    //   1251: goto -> 1258
    //   1254: invokestatic a : (Ljava/lang/Throwable;)Ljava/lang/Throwable;
    //   1257: athrow
    //   1258: aload_3
    //   1259: getstatic burp/Zbze.ZK : Ljava/lang/String;
    //   1262: getstatic burp/Ztq4.ZA : Ljava/lang/Object;
    //   1265: checkcast java/math/BigInteger
    //   1268: invokevirtual intValue : ()I
    //   1271: bipush #32
    //   1273: irem
    //   1274: invokestatic abs : (I)I
    //   1277: invokevirtual charAt : (I)C
    //   1280: invokevirtual append : (C)Ljava/lang/StringBuilder;
    //   1283: pop
    //   1284: iload_2
    //   1285: ifeq -> 1920
    //   1288: goto -> 1295
    //   1291: invokestatic a : (Ljava/lang/Throwable;)Ljava/lang/Throwable;
    //   1294: athrow
    //   1295: aload_3
    //   1296: getstatic burp/Zb0q.Zr : Ljava/lang/String;
    //   1299: getstatic burp/Zv8d.ZN : Ljava/lang/Object;
    //   1302: checkcast java/math/BigInteger
    //   1305: invokevirtual intValue : ()I
    //   1308: bipush #32
    //   1310: irem
    //   1311: invokestatic abs : (I)I
    //   1314: invokevirtual charAt : (I)C
    //   1317: invokevirtual append : (C)Ljava/lang/StringBuilder;
    //   1320: pop
    //   1321: iload_2
    //   1322: ifeq -> 1920
    //   1325: goto -> 1332
    //   1328: invokestatic a : (Ljava/lang/Throwable;)Ljava/lang/Throwable;
    //   1331: athrow
    //   1332: aload_3
    //   1333: getstatic burp/Zek4.Zo : Ljava/lang/String;
    //   1336: getstatic burp/Zs3m.ZW : Ljava/lang/Object;
    //   1339: checkcast java/math/BigInteger
    //   1342: invokevirtual intValue : ()I
    //   1345: bipush #32
    //   1347: irem
    //   1348: invokestatic abs : (I)I
    //   1351: invokevirtual charAt : (I)C
    //   1354: invokevirtual append : (C)Ljava/lang/StringBuilder;
    //   1357: pop
    //   1358: iload_2
    //   1359: ifeq -> 1920
    //   1362: goto -> 1369
    //   1365: invokestatic a : (Ljava/lang/Throwable;)Ljava/lang/Throwable;
    //   1368: athrow
    //   1369: aload_3
    //   1370: getstatic burp/Ze6w.ZY : Ljava/lang/String;
    //   1373: getstatic burp/Zzef.Zw : Ljava/lang/Object;
    //   1376: checkcast java/math/BigInteger
    //   1379: invokevirtual intValue : ()I
    //   1382: bipush #32
    //   1384: irem
    //   1385: invokestatic abs : (I)I
    //   1388: invokevirtual charAt : (I)C
    //   1391: invokevirtual append : (C)Ljava/lang/StringBuilder;
    //   1394: pop
    //   1395: iload_2
    //   1396: ifeq -> 1920
    //   1399: goto -> 1406
    //   1402: invokestatic a : (Ljava/lang/Throwable;)Ljava/lang/Throwable;
    //   1405: athrow
    //   1406: aload_3
    //   1407: getstatic burp/Zvob.Zn : Ljava/lang/String;
    //   1410: getstatic burp/Zb3r.ZI : Ljava/lang/Object;
    //   1413: checkcast java/math/BigInteger
    //   1416: invokevirtual intValue : ()I
    //   1419: bipush #32
    //   1421: irem
    //   1422: invokestatic abs : (I)I
    //   1425: invokevirtual charAt : (I)C
    //   1428: invokevirtual append : (C)Ljava/lang/StringBuilder;
    //   1431: pop
    //   1432: iload_2
    //   1433: ifeq -> 1920
    //   1436: goto -> 1443
    //   1439: invokestatic a : (Ljava/lang/Throwable;)Ljava/lang/Throwable;
    //   1442: athrow
    //   1443: aload_3
    //   1444: getstatic burp/Zku9.Zl : Ljava/lang/String;
    //   1447: getstatic burp/Zml9.ZH : Ljava/lang/Object;
    //   1450: checkcast java/math/BigInteger
    //   1453: invokevirtual intValue : ()I
    //   1456: bipush #32
    //   1458: irem
    //   1459: invokestatic abs : (I)I
    //   1462: invokevirtual charAt : (I)C
    //   1465: invokevirtual append : (C)Ljava/lang/StringBuilder;
    //   1468: pop
    //   1469: iload_2
    //   1470: ifeq -> 1920
    //   1473: goto -> 1480
    //   1476: invokestatic a : (Ljava/lang/Throwable;)Ljava/lang/Throwable;
    //   1479: athrow
    //   1480: aload_3
    //   1481: getstatic burp/Ztq2.Zt : Ljava/lang/String;
    //   1484: getstatic burp/Zz0f.ZL : Ljava/lang/Object;
    //   1487: checkcast java/math/BigInteger
    //   1490: invokevirtual intValue : ()I
    //   1493: bipush #32
    //   1495: irem
    //   1496: invokestatic abs : (I)I
    //   1499: invokevirtual charAt : (I)C
    //   1502: invokevirtual append : (C)Ljava/lang/StringBuilder;
    //   1505: pop
    //   1506: iload_2
    //   1507: ifeq -> 1920
    //   1510: goto -> 1517
    //   1513: invokestatic a : (Ljava/lang/Throwable;)Ljava/lang/Throwable;
    //   1516: athrow
    //   1517: aload_3
    //   1518: getstatic burp/Zedq.Zj : Ljava/lang/String;
    //   1521: getstatic burp/Zsko.ZD : Ljava/lang/Object;
    //   1524: checkcast java/math/BigInteger
    //   1527: invokevirtual intValue : ()I
    //   1530: bipush #32
    //   1532: irem
    //   1533: invokestatic abs : (I)I
    //   1536: invokevirtual charAt : (I)C
    //   1539: invokevirtual append : (C)Ljava/lang/StringBuilder;
    //   1542: pop
    //   1543: iload_2
    //   1544: ifeq -> 1920
    //   1547: goto -> 1554
    //   1550: invokestatic a : (Ljava/lang/Throwable;)Ljava/lang/Throwable;
    //   1553: athrow
    //   1554: aload_3
    //   1555: getstatic burp/Zlsg.Zs : Ljava/lang/String;
    //   1558: getstatic burp/Zxcn.Zq : Ljava/lang/Object;
    //   1561: checkcast java/math/BigInteger
    //   1564: invokevirtual intValue : ()I
    //   1567: bipush #32
    //   1569: irem
    //   1570: invokestatic abs : (I)I
    //   1573: invokevirtual charAt : (I)C
    //   1576: invokevirtual append : (C)Ljava/lang/StringBuilder;
    //   1579: pop
    //   1580: iload_2
    //   1581: ifeq -> 1920
    //   1584: goto -> 1591
    //   1587: invokestatic a : (Ljava/lang/Throwable;)Ljava/lang/Throwable;
    //   1590: athrow
    //   1591: aload_3
    //   1592: getstatic burp/Zsbv.Zr : Ljava/lang/String;
    //   1595: getstatic burp/Ztwp.Ze : Ljava/lang/Object;
    //   1598: checkcast java/math/BigInteger
    //   1601: invokevirtual intValue : ()I
    //   1604: bipush #32
    //   1606: irem
    //   1607: invokestatic abs : (I)I
    //   1610: invokevirtual charAt : (I)C
    //   1613: invokevirtual append : (C)Ljava/lang/StringBuilder;
    //   1616: pop
    //   1617: iload_2
    //   1618: ifeq -> 1920
    //   1621: goto -> 1628
    //   1624: invokestatic a : (Ljava/lang/Throwable;)Ljava/lang/Throwable;
    //   1627: athrow
    //   1628: aload_3
    //   1629: getstatic burp/Zz5e.Zd : Ljava/lang/String;
    //   1632: getstatic burp/Zrn4.Zq : Ljava/lang/Object;
    //   1635: checkcast java/math/BigInteger
    //   1638: invokevirtual intValue : ()I
    //   1641: bipush #32
    //   1643: irem
    //   1644: invokestatic abs : (I)I
    //   1647: invokevirtual charAt : (I)C
    //   1650: invokevirtual append : (C)Ljava/lang/StringBuilder;
    //   1653: pop
    //   1654: iload_2
    //   1655: ifeq -> 1920
    //   1658: goto -> 1665
    //   1661: invokestatic a : (Ljava/lang/Throwable;)Ljava/lang/Throwable;
    //   1664: athrow
    //   1665: aload_3
    //   1666: getstatic burp/Zxn9.ZU : Ljava/lang/String;
    //   1669: getstatic burp/Zql.Zt : Ljava/lang/Object;
    //   1672: checkcast java/math/BigInteger
    //   1675: invokevirtual intValue : ()I
    //   1678: bipush #32
    //   1680: irem
    //   1681: invokestatic abs : (I)I
    //   1684: invokevirtual charAt : (I)C
    //   1687: invokevirtual append : (C)Ljava/lang/StringBuilder;
    //   1690: pop
    //   1691: iload_2
    //   1692: ifeq -> 1920
    //   1695: goto -> 1702
    //   1698: invokestatic a : (Ljava/lang/Throwable;)Ljava/lang/Throwable;
    //   1701: athrow
    //   1702: aload_3
    //   1703: getstatic burp/Zmyk.Zx : Ljava/lang/String;
    //   1706: getstatic burp/Zrw0.ZC : Ljava/lang/Object;
    //   1709: checkcast java/math/BigInteger
    //   1712: invokevirtual intValue : ()I
    //   1715: bipush #32
    //   1717: irem
    //   1718: invokestatic abs : (I)I
    //   1721: invokevirtual charAt : (I)C
    //   1724: invokevirtual append : (C)Ljava/lang/StringBuilder;
    //   1727: pop
    //   1728: iload_2
    //   1729: ifeq -> 1920
    //   1732: goto -> 1739
    //   1735: invokestatic a : (Ljava/lang/Throwable;)Ljava/lang/Throwable;
    //   1738: athrow
    //   1739: aload_3
    //   1740: getstatic burp/Zbl4.Ze : Ljava/lang/String;
    //   1743: getstatic burp/Zs1k.Ze : Ljava/lang/Object;
    //   1746: checkcast java/math/BigInteger
    //   1749: invokevirtual intValue : ()I
    //   1752: bipush #32
    //   1754: irem
    //   1755: invokestatic abs : (I)I
    //   1758: invokevirtual charAt : (I)C
    //   1761: invokevirtual append : (C)Ljava/lang/StringBuilder;
    //   1764: pop
    //   1765: iload_2
    //   1766: ifeq -> 1920
    //   1769: goto -> 1776
    //   1772: invokestatic a : (Ljava/lang/Throwable;)Ljava/lang/Throwable;
    //   1775: athrow
    //   1776: aload_3
    //   1777: getstatic burp/Zmpx.ZC : Ljava/lang/String;
    //   1780: getstatic burp/Zbun.ZH : Ljava/lang/Object;
    //   1783: checkcast java/math/BigInteger
    //   1786: invokevirtual intValue : ()I
    //   1789: bipush #32
    //   1791: irem
    //   1792: invokestatic abs : (I)I
    //   1795: invokevirtual charAt : (I)C
    //   1798: invokevirtual append : (C)Ljava/lang/StringBuilder;
    //   1801: pop
    //   1802: iload_2
    //   1803: ifeq -> 1920
    //   1806: goto -> 1813
    //   1809: invokestatic a : (Ljava/lang/Throwable;)Ljava/lang/Throwable;
    //   1812: athrow
    //   1813: aload_3
    //   1814: getstatic burp/Zmf2.ZK : Ljava/lang/String;
    //   1817: getstatic burp/Zk92.Zn : Ljava/lang/Object;
    //   1820: checkcast java/math/BigInteger
    //   1823: invokevirtual intValue : ()I
    //   1826: bipush #32
    //   1828: irem
    //   1829: invokestatic abs : (I)I
    //   1832: invokevirtual charAt : (I)C
    //   1835: invokevirtual append : (C)Ljava/lang/StringBuilder;
    //   1838: pop
    //   1839: iload_2
    //   1840: ifeq -> 1920
    //   1843: goto -> 1850
    //   1846: invokestatic a : (Ljava/lang/Throwable;)Ljava/lang/Throwable;
    //   1849: athrow
    //   1850: aload_3
    //   1851: getstatic burp/Zmzj.Zb : Ljava/lang/String;
    //   1854: getstatic burp/Zmli.Zh : Ljava/lang/Object;
    //   1857: checkcast java/math/BigInteger
    //   1860: invokevirtual intValue : ()I
    //   1863: bipush #32
    //   1865: irem
    //   1866: invokestatic abs : (I)I
    //   1869: invokevirtual charAt : (I)C
    //   1872: invokevirtual append : (C)Ljava/lang/StringBuilder;
    //   1875: pop
    //   1876: iload_2
    //   1877: ifeq -> 1920
    //   1880: goto -> 1887
    //   1883: invokestatic a : (Ljava/lang/Throwable;)Ljava/lang/Throwable;
    //   1886: athrow
    //   1887: aload_3
    //   1888: getstatic burp/Zea8.ZE : Ljava/lang/String;
    //   1891: getstatic burp/Zxci.Zx : Ljava/lang/Object;
    //   1894: checkcast java/math/BigInteger
    //   1897: invokevirtual intValue : ()I
    //   1900: bipush #32
    //   1902: irem
    //   1903: invokestatic abs : (I)I
    //   1906: invokevirtual charAt : (I)C
    //   1909: invokevirtual append : (C)Ljava/lang/StringBuilder;
    //   1912: pop
    //   1913: goto -> 1920
    //   1916: invokestatic a : (Ljava/lang/Throwable;)Ljava/lang/Throwable;
    //   1919: athrow
    //   1920: iinc #4, 1
    //   1923: iload_2
    //   1924: ifeq -> 588
    //   1927: aload_3
    //   1928: invokevirtual toString : ()Ljava/lang/String;
    //   1931: putstatic burp/Zedq.Zj : Ljava/lang/String;
    //   1934: sipush #-10104
    //   1937: sipush #-5302
    //   1940: invokestatic a : (II)Ljava/lang/String;
    //   1943: iconst_1
    //   1944: ldc burp/Zb6e
    //   1946: invokevirtual getClassLoader : ()Ljava/lang/ClassLoader;
    //   1949: invokestatic forName : (Ljava/lang/String;ZLjava/lang/ClassLoader;)Ljava/lang/Class;
    //   1952: invokevirtual getDeclaredFields : ()[Ljava/lang/reflect/Field;
    //   1955: astore #4
    //   1957: aload #4
    //   1959: arraylength
    //   1960: istore #5
    //   1962: iconst_0
    //   1963: istore #6
    //   1965: iload #6
    //   1967: iload #5
    //   1969: if_icmpge -> 2107
    //   1972: aload #4
    //   1974: iload #6
    //   1976: aaload
    //   1977: astore #7
    //   1979: aload #7
    //   1981: invokevirtual getModifiers : ()I
    //   1984: invokestatic isStatic : (I)Z
    //   1987: ifne -> 1997
    //   1990: goto -> 2100
    //   1993: invokestatic a : (Ljava/lang/Throwable;)Ljava/lang/Throwable;
    //   1996: athrow
    //   1997: aload #7
    //   1999: invokevirtual getType : ()Ljava/lang/Class;
    //   2002: astore #8
    //   2004: aload #8
    //   2006: ifnull -> 2087
    //   2009: aload #8
    //   2011: invokevirtual isPrimitive : ()Z
    //   2014: ifne -> 2087
    //   2017: goto -> 2024
    //   2020: invokestatic a : (Ljava/lang/Throwable;)Ljava/lang/Throwable;
    //   2023: athrow
    //   2024: aload #8
    //   2026: invokevirtual getPackage : ()Ljava/lang/Package;
    //   2029: ifnull -> 2087
    //   2032: goto -> 2039
    //   2035: invokestatic a : (Ljava/lang/Throwable;)Ljava/lang/Throwable;
    //   2038: athrow
    //   2039: aload #8
    //   2041: invokevirtual getPackage : ()Ljava/lang/Package;
    //   2044: invokevirtual getName : ()Ljava/lang/String;
    //   2047: ifnull -> 2087
    //   2050: goto -> 2057
    //   2053: invokestatic a : (Ljava/lang/Throwable;)Ljava/lang/Throwable;
    //   2056: athrow
    //   2057: aload #8
    //   2059: invokevirtual getPackage : ()Ljava/lang/Package;
    //   2062: invokevirtual getName : ()Ljava/lang/String;
    //   2065: sipush #-10099
    //   2068: sipush #31817
    //   2071: invokestatic a : (II)Ljava/lang/String;
    //   2074: invokevirtual startsWith : (Ljava/lang/String;)Z
    //   2077: ifne -> 2087
    //   2080: goto -> 2087
    //   2083: invokestatic a : (Ljava/lang/Throwable;)Ljava/lang/Throwable;
    //   2086: athrow
    //   2087: aload #7
    //   2089: iconst_1
    //   2090: invokevirtual setAccessible : (Z)V
    //   2093: aload #7
    //   2095: aconst_null
    //   2096: invokevirtual get : (Ljava/lang/Object;)Ljava/lang/Object;
    //   2099: pop
    //   2100: iinc #6, 1
    //   2103: iload_2
    //   2104: ifeq -> 1965
    //   2107: sipush #-10097
    //   2110: sipush #19987
    //   2113: invokestatic a : (II)Ljava/lang/String;
    //   2116: invokestatic forName : (Ljava/lang/String;)Ljava/lang/Class;
    //   2119: invokevirtual getDeclaredMethods : ()[Ljava/lang/reflect/Method;
    //   2122: astore #4
    //   2124: aload #4
    //   2126: arraylength
    //   2127: istore #5
    //   2129: iconst_0
    //   2130: istore #6
    //   2132: iload #6
    //   2134: iload #5
    //   2136: if_icmpge -> 2269
    //   2139: aload #4
    //   2141: iload #6
    //   2143: aaload
    //   2144: astore #7
    //   2146: aload #7
    //   2148: invokevirtual getParameterTypes : ()[Ljava/lang/Class;
    //   2151: pop
    //   2152: aload #7
    //   2154: invokevirtual getModifiers : ()I
    //   2157: invokestatic isStatic : (I)Z
    //   2160: ifeq -> 2255
    //   2163: aload #7
    //   2165: invokevirtual getParameterTypes : ()[Ljava/lang/Class;
    //   2168: arraylength
    //   2169: iconst_2
    //   2170: if_icmpne -> 2255
    //   2173: goto -> 2180
    //   2176: invokestatic a : (Ljava/lang/Throwable;)Ljava/lang/Throwable;
    //   2179: athrow
    //   2180: aload #7
    //   2182: invokevirtual getReturnType : ()Ljava/lang/Class;
    //   2185: getstatic java/lang/Void.TYPE : Ljava/lang/Class;
    //   2188: invokevirtual equals : (Ljava/lang/Object;)Z
    //   2191: ifeq -> 2255
    //   2194: goto -> 2201
    //   2197: invokestatic a : (Ljava/lang/Throwable;)Ljava/lang/Throwable;
    //   2200: athrow
    //   2201: aload #7
    //   2203: iconst_1
    //   2204: invokevirtual setAccessible : (Z)V
    //   2207: aload #7
    //   2209: aconst_null
    //   2210: iconst_2
    //   2211: anewarray java/lang/Object
    //   2214: dup
    //   2215: iconst_0
    //   2216: aload_0
    //   2217: aastore
    //   2218: dup
    //   2219: iconst_1
    //   2220: aload_1
    //   2221: ifnonnull -> 2239
    //   2224: goto -> 2231
    //   2227: invokestatic a : (Ljava/lang/Throwable;)Ljava/lang/Throwable;
    //   2230: athrow
    //   2231: aload_1
    //   2232: goto -> 2246
    //   2235: invokestatic a : (Ljava/lang/Throwable;)Ljava/lang/Throwable;
    //   2238: athrow
    //   2239: aload_1
    //   2240: checkcast [B
    //   2243: invokevirtual clone : ()Ljava/lang/Object;
    //   2246: aastore
    //   2247: invokevirtual invoke : (Ljava/lang/Object;[Ljava/lang/Object;)Ljava/lang/Object;
    //   2250: pop
    //   2251: iload_2
    //   2252: ifeq -> 2269
    //   2255: iinc #6, 1
    //   2258: iload_2
    //   2259: ifeq -> 2132
    //   2262: goto -> 2269
    //   2265: invokestatic a : (Ljava/lang/Throwable;)Ljava/lang/Throwable;
    //   2268: athrow
    //   2269: getstatic burp/Zej8.ZP : Ljava/lang/String;
    //   2272: getstatic burp/Zxxo.ZJ : Ljava/lang/Object;
    //   2275: checkcast java/math/BigInteger
    //   2278: invokevirtual intValue : ()I
    //   2281: bipush #32
    //   2283: irem
    //   2284: invokestatic abs : (I)I
    //   2287: invokevirtual charAt : (I)C
    //   2290: getstatic burp/Zmdf.Zo : Ljava/lang/String;
    //   2293: getstatic burp/Zenr.ZA : Ljava/lang/Object;
    //   2296: checkcast java/math/BigInteger
    //   2299: invokevirtual intValue : ()I
    //   2302: bipush #32
    //   2304: irem
    //   2305: invokestatic abs : (I)I
    //   2308: invokevirtual charAt : (I)C
    //   2311: if_icmpgt -> 2418
    //   2314: getstatic burp/Zt1h.Zw : Ljava/lang/String;
    //   2317: getstatic burp/Zepy.Ze : Ljava/lang/Object;
    //   2320: checkcast java/math/BigInteger
    //   2323: invokevirtual intValue : ()I
    //   2326: bipush #32
    //   2328: irem
    //   2329: invokestatic abs : (I)I
    //   2332: invokevirtual charAt : (I)C
    //   2335: getstatic burp/Zscf.Zu : Ljava/lang/String;
    //   2338: getstatic burp/Zvh.Zb : Ljava/lang/Object;
    //   2341: checkcast java/math/BigInteger
    //   2344: invokevirtual intValue : ()I
    //   2347: bipush #32
    //   2349: irem
    //   2350: invokestatic abs : (I)I
    //   2353: invokevirtual charAt : (I)C
    //   2356: if_icmpgt -> 2418
    //   2359: goto -> 2366
    //   2362: invokestatic a : (Ljava/lang/Throwable;)Ljava/lang/Throwable;
    //   2365: athrow
    //   2366: getstatic burp/Zs1k.Zd : Ljava/lang/String;
    //   2369: getstatic burp/Zkeb.ZH : Ljava/lang/Object;
    //   2372: checkcast java/math/BigInteger
    //   2375: invokevirtual intValue : ()I
    //   2378: bipush #32
    //   2380: irem
    //   2381: invokestatic abs : (I)I
    //   2384: invokevirtual charAt : (I)C
    //   2387: getstatic burp/Zrn4.ZY : Ljava/lang/String;
    //   2390: getstatic burp/Ztlo.ZP : Ljava/lang/Object;
    //   2393: checkcast java/math/BigInteger
    //   2396: invokevirtual intValue : ()I
    //   2399: bipush #32
    //   2401: irem
    //   2402: invokestatic abs : (I)I
    //   2405: invokevirtual charAt : (I)C
    //   2408: if_icmpgt -> 2426
    //   2411: goto -> 2418
    //   2414: invokestatic a : (Ljava/lang/Throwable;)Ljava/lang/Throwable;
    //   2417: athrow
    //   2418: iconst_1
    //   2419: goto -> 2427
    //   2422: invokestatic a : (Ljava/lang/Throwable;)Ljava/lang/Throwable;
    //   2425: athrow
    //   2426: iconst_0
    //   2427: ireturn
    //   2428: astore_3
    //   2429: new java/lang/Exception
    //   2432: dup
    //   2433: aload_3
    //   2434: invokevirtual getMessage : ()Ljava/lang/String;
    //   2437: invokespecial <init> : (Ljava/lang/String;)V
    //   2440: athrow
    // Exception table:
    //   from	to	target	type
    //   4	2427	2428	java/lang/Throwable
    //   185	209	212	java/lang/Throwable
    //   283	320	320	java/lang/Throwable
    //   324	345	345	java/lang/Throwable
    //   349	379	379	java/lang/Throwable
    //   595	770	773	java/lang/Throwable
    //   740	807	810	java/lang/Throwable
    //   777	844	847	java/lang/Throwable
    //   814	881	884	java/lang/Throwable
    //   851	918	921	java/lang/Throwable
    //   888	955	958	java/lang/Throwable
    //   925	992	995	java/lang/Throwable
    //   962	1029	1032	java/lang/Throwable
    //   999	1066	1069	java/lang/Throwable
    //   1036	1103	1106	java/lang/Throwable
    //   1073	1140	1143	java/lang/Throwable
    //   1110	1177	1180	java/lang/Throwable
    //   1147	1214	1217	java/lang/Throwable
    //   1184	1251	1254	java/lang/Throwable
    //   1221	1288	1291	java/lang/Throwable
    //   1258	1325	1328	java/lang/Throwable
    //   1295	1362	1365	java/lang/Throwable
    //   1332	1399	1402	java/lang/Throwable
    //   1369	1436	1439	java/lang/Throwable
    //   1406	1473	1476	java/lang/Throwable
    //   1443	1510	1513	java/lang/Throwable
    //   1480	1547	1550	java/lang/Throwable
    //   1517	1584	1587	java/lang/Throwable
    //   1554	1621	1624	java/lang/Throwable
    //   1591	1658	1661	java/lang/Throwable
    //   1628	1695	1698	java/lang/Throwable
    //   1665	1732	1735	java/lang/Throwable
    //   1702	1769	1772	java/lang/Throwable
    //   1739	1806	1809	java/lang/Throwable
    //   1776	1843	1846	java/lang/Throwable
    //   1813	1880	1883	java/lang/Throwable
    //   1850	1913	1916	java/lang/Throwable
    //   1979	1993	1993	java/lang/Throwable
    //   2004	2017	2020	java/lang/Throwable
    //   2009	2032	2035	java/lang/Throwable
    //   2024	2050	2053	java/lang/Throwable
    //   2039	2080	2083	java/lang/Throwable
    //   2146	2173	2176	java/lang/Throwable
    //   2163	2194	2197	java/lang/Throwable
    //   2180	2224	2227	java/lang/Throwable
    //   2201	2235	2235	java/lang/Throwable
    //   2246	2262	2265	java/lang/Throwable
    //   2269	2359	2362	java/lang/Throwable
    //   2314	2411	2414	java/lang/Throwable
    //   2366	2422	2422	java/lang/Throwable
  }
  
  static void ZE(Object paramObject) {
    Zt7x.Zu = a(-10101, 14291);
    Zt7x.ZE = new BigInteger(a(-10100, 21941));
    boolean bool = Zt2e.ZK();
    try {
      try {
        if (Zrov.ZU.charAt(Math.abs(((BigInteger)Zrw0.ZC).intValue() % 32)) <= Zz3b.Zi.charAt(Math.abs(((BigInteger)Zmdf.ZH).intValue() % 32))) {
          try {
            Zmll.Zp(Class.forName(a(-10112, -8509)));
            if (bool)
              Zs0b.Zn(Class.forName(a(-10103, -27991))); 
          } catch (Throwable throwable) {
            throw a(null);
          } 
          return;
        } 
      } catch (Throwable throwable) {
        throw a(null);
      } 
      Zs0b.Zn(Class.forName(a(-10103, -27991)));
    } catch (Throwable throwable) {}
  }
  
  static {
    // Byte code:
    //   0: bipush #9
    //   2: anewarray java/lang/String
    //   5: astore #5
    //   7: iconst_0
    //   8: istore_3
    //   9: ldc 'gÂ½ÃŠÃƒÃ®Â?\\tOHÂ¸Ã€cÂ¯Â3Ã´ Ã²Ã«2MÃ¶Ãª,Ã¦ÃÃ²Â¸Dxjb,Ã¦Ãƒ_Â¶Â9~NÂ§a,Â‹ Ã½ÃŠDÂš~Ã­| ÂƒÂ‚Ã²2Ã“Â¼Â¿Ã¥4Â– Â«ÃŒÂ°Ã¦Ã´Ã·Ã¦OÃžÂºMÃ•zÃ’ÂŠ3@?ÂºV~Ã‰Ã!Ã£Â¿Ã„Ã¼Â—Ã·oÂŽ|hÃ¤#ÂœÃ¾ÂÂ£Âƒ^7Â‚8\\bÂŸÂ¸Â’4Â³3hÃ´\\nÃ°ÂƒÃ©Ã®Â¦bÃ²Â¯ÂšÃ—ÃŸP>Ã¯ÃŸÂ h$Â‰Â·I&ÂœÃˆÂ–Â–Â£5Â“oMÃ¢Â·40Ã¤qÂ£1NÃŒÂ‘Ã Ã‚ÂwÂŸ.oWÂ“Ã9Y]Â–),Â£Ã°ÂŽ\\fÂˆÃ–Â®Â‰IÂ‹Ã–Vq*ÂšÂ°ÃŠÂ Ã±c\\npÃŠ#Ã‘\Â­S\\bTÂŸÃ¹Â¬ÃºÂš3ÃŠÂ¼'
    //   11: dup
    //   12: astore_2
    //   13: invokevirtual length : ()I
    //   16: istore #4
    //   18: bipush #9
    //   20: istore_1
    //   21: iconst_m1
    //   22: istore_0
    //   23: bipush #112
    //   25: iinc #0, 1
    //   28: aload_2
    //   29: iload_0
    //   30: dup
    //   31: iload_1
    //   32: iadd
    //   33: invokevirtual substring : (II)Ljava/lang/String;
    //   36: iconst_m1
    //   37: goto -> 143
    //   40: aload #5
    //   42: swap
    //   43: iload_3
    //   44: iinc #3, 1
    //   47: swap
    //   48: aastore
    //   49: iload_0
    //   50: iload_1
    //   51: iadd
    //   52: dup
    //   53: istore_0
    //   54: iload #4
    //   56: if_icmpge -> 68
    //   59: aload_2
    //   60: iload_0
    //   61: invokevirtual charAt : (I)C
    //   64: istore_1
    //   65: goto -> 23
    //   68: ldc '\OÂ¿\\bÃ•mÃ§7\\t[~Â¯Â“PÃ¦Y\\n'
    //   70: dup
    //   71: astore_2
    //   72: invokevirtual length : ()I
    //   75: istore #4
    //   77: bipush #9
    //   79: istore_1
    //   80: iconst_m1
    //   81: istore_0
    //   82: bipush #46
    //   84: iinc #0, 1
    //   87: aload_2
    //   88: iload_0
    //   89: dup
    //   90: iload_1
    //   91: iadd
    //   92: invokevirtual substring : (II)Ljava/lang/String;
    //   95: iconst_0
    //   96: goto -> 143
    //   99: aload #5
    //   101: swap
    //   102: iload_3
    //   103: iinc #3, 1
    //   106: swap
    //   107: aastore
    //   108: iload_0
    //   109: iload_1
    //   110: iadd
    //   111: dup
    //   112: istore_0
    //   113: iload #4
    //   115: if_icmpge -> 127
    //   118: aload_2
    //   119: iload_0
    //   120: invokevirtual charAt : (I)C
    //   123: istore_1
    //   124: goto -> 82
    //   127: aload #5
    //   129: putstatic burp/Zt81.a : [Ljava/lang/String;
    //   132: bipush #9
    //   134: anewarray java/lang/String
    //   137: putstatic burp/Zt81.b : [Ljava/lang/String;
    //   140: goto -> 300
    //   143: dup_x2
    //   144: pop
    //   145: invokevirtual toCharArray : ()[C
    //   148: dup_x1
    //   149: arraylength
    //   150: dup_x2
    //   151: pop
    //   152: iconst_0
    //   153: istore #6
    //   155: dup2_x1
    //   156: pop2
    //   157: dup_x2
    //   158: iconst_1
    //   159: if_icmpgt -> 259
    //   162: dup2
    //   163: swap
    //   164: iload #6
    //   166: dup2_x1
    //   167: caload
    //   168: swap
    //   169: iload #6
    //   171: bipush #7
    //   173: irem
    //   174: tableswitch default -> 241, 0 -> 212, 1 -> 216, 2 -> 221, 3 -> 226, 4 -> 231, 5 -> 236
    //   212: iconst_3
    //   213: goto -> 243
    //   216: bipush #10
    //   218: goto -> 243
    //   221: bipush #19
    //   223: goto -> 243
    //   226: bipush #93
    //   228: goto -> 243
    //   231: bipush #122
    //   233: goto -> 243
    //   236: bipush #70
    //   238: goto -> 243
    //   241: bipush #78
    //   243: ixor
    //   244: ixor
    //   245: i2c
    //   246: castore
    //   247: iinc #6, 1
    //   250: dup
    //   251: ifne -> 259
    //   254: dup2
    //   255: dup_x1
    //   256: goto -> 166
    //   259: dup2_x1
    //   260: pop2
    //   261: dup_x2
    //   262: iload #6
    //   264: if_icmpgt -> 162
    //   267: pop
    //   268: new java/lang/String
    //   271: dup_x1
    //   272: swap
    //   273: invokespecial <init> : ([C)V
    //   276: invokevirtual intern : ()Ljava/lang/String;
    //   279: swap
    //   280: pop
    //   281: swap
    //   282: tableswitch default -> 40, 0 -> 99
    //   300: sipush #-10102
    //   303: sipush #14666
    //   306: invokestatic a : (II)Ljava/lang/String;
    //   309: putstatic burp/Zt81.ZL : Ljava/lang/String;
    //   312: new java/math/BigInteger
    //   315: dup
    //   316: sipush #-10098
    //   319: sipush #-30927
    //   322: invokestatic a : (II)Ljava/lang/String;
    //   325: invokespecial <init> : (Ljava/lang/String;)V
    //   328: putstatic burp/Zt81.ZY : Ljava/lang/Object;
    //   331: return
  }
  
  private static Throwable a(Throwable paramThrowable) {
    return paramThrowable;
  }
  
  private static String a(int paramInt1, int paramInt2) {
    int i = (paramInt1 ^ 0xFFFFD888) & 0xFFFF;
    if (b[i] == null) {
      char[] arrayOfChar = a[i].toCharArray();
      switch (arrayOfChar[0] & 0xFF) {
        case 0:
        
        case 1:
        
        case 2:
        
        case 3:
        
        case 4:
        
        case 5:
        
        case 6:
        
        case 7:
        
        case 8:
        
        case 9:
        
        case 10:
        
        case 11:
        
        case 12:
        
        case 13:
        
        case 14:
        
        case 15:
        
        case 16:
        
        case 17:
        
        case 18:
        
        case 19:
        
        case 20:
        
        case 21:
        
        case 22:
        
        case 23:
        
        case 24:
        
        case 25:
        
        case 26:
        
        case 27:
        
        case 28:
        
        case 29:
        
        case 30:
        
        case 31:
        
        case 32:
        
        case 33:
        
        case 34:
        
        case 35:
        
        case 36:
        
        case 37:
        
        case 38:
        
        case 39:
        
        case 40:
        
        case 41:
        
        case 42:
        
        case 43:
        
        case 44:
        
        case 45:
        
        case 46:
        
        case 47:
        
        case 48:
        
        case 49:
        
        case 50:
        
        case 51:
        
        case 52:
        
        case 53:
        
        case 54:
        
        case 55:
        
        case 56:
        
        case 57:
        
        case 58:
        
        case 59:
        
        case 60:
        
        case 61:
        
        case 62:
        
        case 63:
        
        case 64:
        
        case 65:
        
        case 66:
        
        case 67:
        
        case 68:
        
        case 69:
        
        case 70:
        
        case 71:
        
        case 72:
        
        case 73:
        
        case 74:
        
        case 75:
        
        case 76:
        
        case 77:
        
        case 78:
        
        case 79:
        
        case 80:
        
        case 81:
        
        case 82:
        
        case 83:
        
        case 84:
        
        case 85:
        
        case 86:
        
        case 87:
        
        case 88:
        
        case 89:
        
        case 90:
        
        case 91:
        
        case 92:
        
        case 93:
        
        case 94:
        
        case 95:
        
        case 96:
        
        case 97:
        
        case 98:
        
        case 99:
        
        case 100:
        
        case 101:
        
        case 102:
        
        case 103:
        
        case 104:
        
        case 105:
        
        case 106:
        
        case 107:
        
        case 108:
        
        case 109:
        
        case 110:
        
        case 111:
        
        case 112:
        
        case 113:
        
        case 114:
        
        case 115:
        
        case 116:
        
        case 117:
        
        case 118:
        
        case 119:
        
        case 120:
        
        case 121:
        
        case 122:
        
        case 123:
        
        case 124:
        
        case 125:
        
        case 126:
        
        case 127:
        
        case 128:
        
        case 129:
        
        case 130:
        
        case 131:
        
        case 132:
        
        case 133:
        
        case 134:
        
        case 135:
        
        case 136:
        
        case 137:
        
        case 138:
        
        case 139:
        
        case 140:
        
        case 141:
        
        case 142:
        
        case 143:
        
        case 144:
        
        case 145:
        
        case 146:
        
        case 147:
        
        case 148:
        
        case 149:
        
        case 150:
        
        case 151:
        
        case 152:
        
        case 153:
        
        case 154:
        
        case 155:
        
        case 156:
        
        case 157:
        
        case 158:
        
        case 159:
        
        case 160:
        
        case 161:
        
        case 162:
        
        case 163:
        
        case 164:
        
        case 165:
        
        case 166:
        
        case 167:
        
        case 168:
        
        case 169:
        
        case 170:
        
        case 171:
        
        case 172:
        
        case 173:
        
        case 174:
        
        case 175:
        
        case 176:
        
        case 177:
        
        case 178:
        
        case 179:
        
        case 180:
        
        case 181:
        
        case 182:
        
        case 183:
        
        case 184:
        
        case 185:
        
        case 186:
        
        case 187:
        
        case 188:
        
        case 189:
        
        case 190:
        
        case 191:
        
        case 192:
        
        case 193:
        
        case 194:
        
        case 195:
        
        case 196:
        
        case 197:
        
        case 198:
        
        case 199:
        
        case 200:
        
        case 201:
        
        case 202:
        
        case 203:
        
        case 204:
        
        case 205:
        
        case 206:
        
        case 207:
        
        case 208:
        
        case 209:
        
        case 210:
        
        case 211:
        
        case 212:
        
        case 213:
        
        case 214:
        
        case 215:
        
        case 216:
        
        case 217:
        
        case 218:
        
        case 219:
        
        case 220:
        
        case 221:
        
        case 222:
        
        case 223:
        
        case 224:
        
        case 225:
        
        case 226:
        
        case 227:
        
        case 228:
        
        case 229:
        
        case 230:
        
        case 231:
        
        case 232:
        
        case 233:
        
        case 234:
        
        case 235:
        
        case 236:
        
        case 237:
        
        case 238:
        
        case 239:
        
        case 240:
        
        case 241:
        
        case 242:
        
        case 243:
        
        case 244:
        
        case 245:
        
        case 246:
        
        case 247:
        
        case 248:
        
        case 249:
        
        case 250:
        
        case 251:
        
        case 252:
        
        case 253:
        
        case 254:
        
        default:
          break;
      } 
      char c = 'Â—';
      int j = (paramInt2 & 0xFF) - c;
      if (j < 0)
        j += 256; 
      int k = ((paramInt2 & 0xFFFF) >>> 8) - c;
      if (k < 0)
        k += 256; 
      for (byte b = 0; b < arrayOfChar.length; b++) {
        int m = b % 2;
        if (m == 0) {
          arrayOfChar[b] = (char)(arrayOfChar[b] ^ j);
          j = ((j >>> 3 | j << 5) ^ arrayOfChar[b]) & 0xFF;
        } else {
          arrayOfChar[b] = (char)(arrayOfChar[b] ^ k);
          k = ((k >>> 3 | k << 5) ^ arrayOfChar[b]) & 0xFF;
        } 
      } 
      b[i] = (new String(arrayOfChar)).intern();
    } 
    return b[i];
  }
}


/* Location:              C:\Program Files\BurpSuitePro\burpsuite_pro.jar!\burp\Zt81.class
 * Java compiler version: 21 (65.0)
 * JD-Core Version:       1.1.3
 */