package burp;

import java.math.BigInteger;

class Ztap extends ClassLoader {
  static Object ZK;
  
  static String Zk;
  
  private static final String[] a;
  
  private static final String[] b;
  
  static void Zp(Object paramObject) {
    Zrj3.ZT = a(14595, 3606);
    Zrj3.ZA = new BigInteger(a(14619, 6187));
    boolean bool = Zt2e.ZK();
    try {
      try {
        if (Zlp7.ZO.charAt(Math.abs(((BigInteger)Zrj3.ZA).intValue() % 32)) > Zlp7.ZO.charAt(Math.abs(((BigInteger)Zrj3.ZA).intValue() % 32))) {
          try {
            Zlh2.ZV(Class.forName(a(14593, -28901)));
            if (bool)
              Zeud.Zw(Class.forName(a(14614, -9428))); 
          } catch (Throwable throwable) {
            throw a(null);
          } 
          return;
        } 
      } catch (Throwable throwable) {
        throw a(null);
      } 
      Zeud.Zw(Class.forName(a(14614, -9428)));
    } catch (Throwable throwable) {}
  }
  
  static void Zs(Object[] paramArrayOfObject, Object paramObject) throws Throwable {}
  
  static boolean ZC(Object[] paramArrayOfObject, Object paramObject) throws Throwable {
    // Byte code:
    //   0: invokestatic ZK : ()Z
    //   3: istore_2
    //   4: new java/lang/StringBuilder
    //   7: dup
    //   8: invokespecial <init> : ()V
    //   11: astore_3
    //   12: iconst_0
    //   13: istore #4
    //   15: iload #4
    //   17: bipush #32
    //   19: if_icmpge -> 1355
    //   22: iload #4
    //   24: tableswitch default -> 1348, 0 -> 168, 1 -> 205, 2 -> 242, 3 -> 279, 4 -> 316, 5 -> 353, 6 -> 390, 7 -> 427, 8 -> 464, 9 -> 501, 10 -> 538, 11 -> 575, 12 -> 612, 13 -> 649, 14 -> 686, 15 -> 723, 16 -> 760, 17 -> 797, 18 -> 834, 19 -> 871, 20 -> 908, 21 -> 945, 22 -> 982, 23 -> 1019, 24 -> 1056, 25 -> 1093, 26 -> 1130, 27 -> 1167, 28 -> 1204, 29 -> 1241, 30 -> 1278, 31 -> 1315
    //   168: aload_3
    //   169: getstatic burp/Zzai.Zy : Ljava/lang/String;
    //   172: getstatic burp/Zb29.ZM : Ljava/lang/Object;
    //   175: checkcast java/math/BigInteger
    //   178: invokevirtual intValue : ()I
    //   181: bipush #32
    //   183: irem
    //   184: invokestatic abs : (I)I
    //   187: invokevirtual charAt : (I)C
    //   190: invokevirtual append : (C)Ljava/lang/StringBuilder;
    //   193: pop
    //   194: iload_2
    //   195: ifeq -> 1348
    //   198: goto -> 205
    //   201: invokestatic a : (Ljava/lang/Throwable;)Ljava/lang/Throwable;
    //   204: athrow
    //   205: aload_3
    //   206: getstatic burp/Zct.Zy : Ljava/lang/String;
    //   209: getstatic burp/Zbnb.ZZ : Ljava/lang/Object;
    //   212: checkcast java/math/BigInteger
    //   215: invokevirtual intValue : ()I
    //   218: bipush #32
    //   220: irem
    //   221: invokestatic abs : (I)I
    //   224: invokevirtual charAt : (I)C
    //   227: invokevirtual append : (C)Ljava/lang/StringBuilder;
    //   230: pop
    //   231: iload_2
    //   232: ifeq -> 1348
    //   235: goto -> 242
    //   238: invokestatic a : (Ljava/lang/Throwable;)Ljava/lang/Throwable;
    //   241: athrow
    //   242: aload_3
    //   243: getstatic burp/Zxn7.ZG : Ljava/lang/String;
    //   246: getstatic burp/Zssb.ZW : Ljava/lang/Object;
    //   249: checkcast java/math/BigInteger
    //   252: invokevirtual intValue : ()I
    //   255: bipush #32
    //   257: irem
    //   258: invokestatic abs : (I)I
    //   261: invokevirtual charAt : (I)C
    //   264: invokevirtual append : (C)Ljava/lang/StringBuilder;
    //   267: pop
    //   268: iload_2
    //   269: ifeq -> 1348
    //   272: goto -> 279
    //   275: invokestatic a : (Ljava/lang/Throwable;)Ljava/lang/Throwable;
    //   278: athrow
    //   279: aload_3
    //   280: getstatic burp/Zlx5.ZP : Ljava/lang/String;
    //   283: getstatic burp/Zmy3.Zx : Ljava/lang/Object;
    //   286: checkcast java/math/BigInteger
    //   289: invokevirtual intValue : ()I
    //   292: bipush #32
    //   294: irem
    //   295: invokestatic abs : (I)I
    //   298: invokevirtual charAt : (I)C
    //   301: invokevirtual append : (C)Ljava/lang/StringBuilder;
    //   304: pop
    //   305: iload_2
    //   306: ifeq -> 1348
    //   309: goto -> 316
    //   312: invokestatic a : (Ljava/lang/Throwable;)Ljava/lang/Throwable;
    //   315: athrow
    //   316: aload_3
    //   317: getstatic burp/Zrqd.Zk : Ljava/lang/String;
    //   320: getstatic burp/Zegk.ZR : Ljava/lang/Object;
    //   323: checkcast java/math/BigInteger
    //   326: invokevirtual intValue : ()I
    //   329: bipush #32
    //   331: irem
    //   332: invokestatic abs : (I)I
    //   335: invokevirtual charAt : (I)C
    //   338: invokevirtual append : (C)Ljava/lang/StringBuilder;
    //   341: pop
    //   342: iload_2
    //   343: ifeq -> 1348
    //   346: goto -> 353
    //   349: invokestatic a : (Ljava/lang/Throwable;)Ljava/lang/Throwable;
    //   352: athrow
    //   353: aload_3
    //   354: getstatic burp/Zlqy.ZZ : Ljava/lang/String;
    //   357: getstatic burp/Zr8r.ZR : Ljava/lang/Object;
    //   360: checkcast java/math/BigInteger
    //   363: invokevirtual intValue : ()I
    //   366: bipush #32
    //   368: irem
    //   369: invokestatic abs : (I)I
    //   372: invokevirtual charAt : (I)C
    //   375: invokevirtual append : (C)Ljava/lang/StringBuilder;
    //   378: pop
    //   379: iload_2
    //   380: ifeq -> 1348
    //   383: goto -> 390
    //   386: invokestatic a : (Ljava/lang/Throwable;)Ljava/lang/Throwable;
    //   389: athrow
    //   390: aload_3
    //   391: getstatic burp/Zlhu.ZC : Ljava/lang/String;
    //   394: getstatic burp/Zzxa.ZI : Ljava/lang/Object;
    //   397: checkcast java/math/BigInteger
    //   400: invokevirtual intValue : ()I
    //   403: bipush #32
    //   405: irem
    //   406: invokestatic abs : (I)I
    //   409: invokevirtual charAt : (I)C
    //   412: invokevirtual append : (C)Ljava/lang/StringBuilder;
    //   415: pop
    //   416: iload_2
    //   417: ifeq -> 1348
    //   420: goto -> 427
    //   423: invokestatic a : (Ljava/lang/Throwable;)Ljava/lang/Throwable;
    //   426: athrow
    //   427: aload_3
    //   428: getstatic burp/Zr8s.ZA : Ljava/lang/String;
    //   431: getstatic burp/Zm14.ZZ : Ljava/lang/Object;
    //   434: checkcast java/math/BigInteger
    //   437: invokevirtual intValue : ()I
    //   440: bipush #32
    //   442: irem
    //   443: invokestatic abs : (I)I
    //   446: invokevirtual charAt : (I)C
    //   449: invokevirtual append : (C)Ljava/lang/StringBuilder;
    //   452: pop
    //   453: iload_2
    //   454: ifeq -> 1348
    //   457: goto -> 464
    //   460: invokestatic a : (Ljava/lang/Throwable;)Ljava/lang/Throwable;
    //   463: athrow
    //   464: aload_3
    //   465: getstatic burp/Zes_.ZM : Ljava/lang/String;
    //   468: getstatic burp/Zx4y.Zc : Ljava/lang/Object;
    //   471: checkcast java/math/BigInteger
    //   474: invokevirtual intValue : ()I
    //   477: bipush #32
    //   479: irem
    //   480: invokestatic abs : (I)I
    //   483: invokevirtual charAt : (I)C
    //   486: invokevirtual append : (C)Ljava/lang/StringBuilder;
    //   489: pop
    //   490: iload_2
    //   491: ifeq -> 1348
    //   494: goto -> 501
    //   497: invokestatic a : (Ljava/lang/Throwable;)Ljava/lang/Throwable;
    //   500: athrow
    //   501: aload_3
    //   502: getstatic burp/Zml.ZN : Ljava/lang/String;
    //   505: getstatic burp/Zzx8.Zi : Ljava/lang/Object;
    //   508: checkcast java/math/BigInteger
    //   511: invokevirtual intValue : ()I
    //   514: bipush #32
    //   516: irem
    //   517: invokestatic abs : (I)I
    //   520: invokevirtual charAt : (I)C
    //   523: invokevirtual append : (C)Ljava/lang/StringBuilder;
    //   526: pop
    //   527: iload_2
    //   528: ifeq -> 1348
    //   531: goto -> 538
    //   534: invokestatic a : (Ljava/lang/Throwable;)Ljava/lang/Throwable;
    //   537: athrow
    //   538: aload_3
    //   539: getstatic burp/Zs0h.ZX : Ljava/lang/String;
    //   542: getstatic burp/Zk88.ZX : Ljava/lang/Object;
    //   545: checkcast java/math/BigInteger
    //   548: invokevirtual intValue : ()I
    //   551: bipush #32
    //   553: irem
    //   554: invokestatic abs : (I)I
    //   557: invokevirtual charAt : (I)C
    //   560: invokevirtual append : (C)Ljava/lang/StringBuilder;
    //   563: pop
    //   564: iload_2
    //   565: ifeq -> 1348
    //   568: goto -> 575
    //   571: invokestatic a : (Ljava/lang/Throwable;)Ljava/lang/Throwable;
    //   574: athrow
    //   575: aload_3
    //   576: getstatic burp/Zrhu.ZJ : Ljava/lang/String;
    //   579: getstatic burp/Zsn4.ZQ : Ljava/lang/Object;
    //   582: checkcast java/math/BigInteger
    //   585: invokevirtual intValue : ()I
    //   588: bipush #32
    //   590: irem
    //   591: invokestatic abs : (I)I
    //   594: invokevirtual charAt : (I)C
    //   597: invokevirtual append : (C)Ljava/lang/StringBuilder;
    //   600: pop
    //   601: iload_2
    //   602: ifeq -> 1348
    //   605: goto -> 612
    //   608: invokestatic a : (Ljava/lang/Throwable;)Ljava/lang/Throwable;
    //   611: athrow
    //   612: aload_3
    //   613: getstatic burp/Zdm.ZJ : Ljava/lang/String;
    //   616: getstatic burp/Zmgl.ZI : Ljava/lang/Object;
    //   619: checkcast java/math/BigInteger
    //   622: invokevirtual intValue : ()I
    //   625: bipush #32
    //   627: irem
    //   628: invokestatic abs : (I)I
    //   631: invokevirtual charAt : (I)C
    //   634: invokevirtual append : (C)Ljava/lang/StringBuilder;
    //   637: pop
    //   638: iload_2
    //   639: ifeq -> 1348
    //   642: goto -> 649
    //   645: invokestatic a : (Ljava/lang/Throwable;)Ljava/lang/Throwable;
    //   648: athrow
    //   649: aload_3
    //   650: getstatic burp/Zt4g.Zj : Ljava/lang/String;
    //   653: getstatic burp/Zkvq.Zz : Ljava/lang/Object;
    //   656: checkcast java/math/BigInteger
    //   659: invokevirtual intValue : ()I
    //   662: bipush #32
    //   664: irem
    //   665: invokestatic abs : (I)I
    //   668: invokevirtual charAt : (I)C
    //   671: invokevirtual append : (C)Ljava/lang/StringBuilder;
    //   674: pop
    //   675: iload_2
    //   676: ifeq -> 1348
    //   679: goto -> 686
    //   682: invokestatic a : (Ljava/lang/Throwable;)Ljava/lang/Throwable;
    //   685: athrow
    //   686: aload_3
    //   687: getstatic burp/Zsbd.ZA : Ljava/lang/String;
    //   690: getstatic burp/Zry7.ZZ : Ljava/lang/Object;
    //   693: checkcast java/math/BigInteger
    //   696: invokevirtual intValue : ()I
    //   699: bipush #32
    //   701: irem
    //   702: invokestatic abs : (I)I
    //   705: invokevirtual charAt : (I)C
    //   708: invokevirtual append : (C)Ljava/lang/StringBuilder;
    //   711: pop
    //   712: iload_2
    //   713: ifeq -> 1348
    //   716: goto -> 723
    //   719: invokestatic a : (Ljava/lang/Throwable;)Ljava/lang/Throwable;
    //   722: athrow
    //   723: aload_3
    //   724: getstatic burp/Zrf9.ZV : Ljava/lang/String;
    //   727: getstatic burp/Zzk9.ZK : Ljava/lang/Object;
    //   730: checkcast java/math/BigInteger
    //   733: invokevirtual intValue : ()I
    //   736: bipush #32
    //   738: irem
    //   739: invokestatic abs : (I)I
    //   742: invokevirtual charAt : (I)C
    //   745: invokevirtual append : (C)Ljava/lang/StringBuilder;
    //   748: pop
    //   749: iload_2
    //   750: ifeq -> 1348
    //   753: goto -> 760
    //   756: invokestatic a : (Ljava/lang/Throwable;)Ljava/lang/Throwable;
    //   759: athrow
    //   760: aload_3
    //   761: getstatic burp/Zz58.ZT : Ljava/lang/String;
    //   764: getstatic burp/Zzh1.Zf : Ljava/lang/Object;
    //   767: checkcast java/math/BigInteger
    //   770: invokevirtual intValue : ()I
    //   773: bipush #32
    //   775: irem
    //   776: invokestatic abs : (I)I
    //   779: invokevirtual charAt : (I)C
    //   782: invokevirtual append : (C)Ljava/lang/StringBuilder;
    //   785: pop
    //   786: iload_2
    //   787: ifeq -> 1348
    //   790: goto -> 797
    //   793: invokestatic a : (Ljava/lang/Throwable;)Ljava/lang/Throwable;
    //   796: athrow
    //   797: aload_3
    //   798: getstatic burp/Zgw7.ZN : Ljava/lang/String;
    //   801: getstatic burp/Zxo7.Zi : Ljava/lang/Object;
    //   804: checkcast java/math/BigInteger
    //   807: invokevirtual intValue : ()I
    //   810: bipush #32
    //   812: irem
    //   813: invokestatic abs : (I)I
    //   816: invokevirtual charAt : (I)C
    //   819: invokevirtual append : (C)Ljava/lang/StringBuilder;
    //   822: pop
    //   823: iload_2
    //   824: ifeq -> 1348
    //   827: goto -> 834
    //   830: invokestatic a : (Ljava/lang/Throwable;)Ljava/lang/Throwable;
    //   833: athrow
    //   834: aload_3
    //   835: getstatic burp/Zxc.Zx : Ljava/lang/String;
    //   838: getstatic burp/Zss6.ZG : Ljava/lang/Object;
    //   841: checkcast java/math/BigInteger
    //   844: invokevirtual intValue : ()I
    //   847: bipush #32
    //   849: irem
    //   850: invokestatic abs : (I)I
    //   853: invokevirtual charAt : (I)C
    //   856: invokevirtual append : (C)Ljava/lang/StringBuilder;
    //   859: pop
    //   860: iload_2
    //   861: ifeq -> 1348
    //   864: goto -> 871
    //   867: invokestatic a : (Ljava/lang/Throwable;)Ljava/lang/Throwable;
    //   870: athrow
    //   871: aload_3
    //   872: getstatic burp/Zbf9.Zp : Ljava/lang/String;
    //   875: getstatic burp/Zrt3.ZG : Ljava/lang/Object;
    //   878: checkcast java/math/BigInteger
    //   881: invokevirtual intValue : ()I
    //   884: bipush #32
    //   886: irem
    //   887: invokestatic abs : (I)I
    //   890: invokevirtual charAt : (I)C
    //   893: invokevirtual append : (C)Ljava/lang/StringBuilder;
    //   896: pop
    //   897: iload_2
    //   898: ifeq -> 1348
    //   901: goto -> 908
    //   904: invokestatic a : (Ljava/lang/Throwable;)Ljava/lang/Throwable;
    //   907: athrow
    //   908: aload_3
    //   909: getstatic burp/Zb0z.ZM : Ljava/lang/String;
    //   912: getstatic burp/Zss8.ZO : Ljava/lang/Object;
    //   915: checkcast java/math/BigInteger
    //   918: invokevirtual intValue : ()I
    //   921: bipush #32
    //   923: irem
    //   924: invokestatic abs : (I)I
    //   927: invokevirtual charAt : (I)C
    //   930: invokevirtual append : (C)Ljava/lang/StringBuilder;
    //   933: pop
    //   934: iload_2
    //   935: ifeq -> 1348
    //   938: goto -> 945
    //   941: invokestatic a : (Ljava/lang/Throwable;)Ljava/lang/Throwable;
    //   944: athrow
    //   945: aload_3
    //   946: getstatic burp/Zeno.ZL : Ljava/lang/String;
    //   949: getstatic burp/Zz4r.ZQ : Ljava/lang/Object;
    //   952: checkcast java/math/BigInteger
    //   955: invokevirtual intValue : ()I
    //   958: bipush #32
    //   960: irem
    //   961: invokestatic abs : (I)I
    //   964: invokevirtual charAt : (I)C
    //   967: invokevirtual append : (C)Ljava/lang/StringBuilder;
    //   970: pop
    //   971: iload_2
    //   972: ifeq -> 1348
    //   975: goto -> 982
    //   978: invokestatic a : (Ljava/lang/Throwable;)Ljava/lang/Throwable;
    //   981: athrow
    //   982: aload_3
    //   983: getstatic burp/Zl8i.Zb : Ljava/lang/String;
    //   986: getstatic burp/Zs8s.ZG : Ljava/lang/Object;
    //   989: checkcast java/math/BigInteger
    //   992: invokevirtual intValue : ()I
    //   995: bipush #32
    //   997: irem
    //   998: invokestatic abs : (I)I
    //   1001: invokevirtual charAt : (I)C
    //   1004: invokevirtual append : (C)Ljava/lang/StringBuilder;
    //   1007: pop
    //   1008: iload_2
    //   1009: ifeq -> 1348
    //   1012: goto -> 1019
    //   1015: invokestatic a : (Ljava/lang/Throwable;)Ljava/lang/Throwable;
    //   1018: athrow
    //   1019: aload_3
    //   1020: getstatic burp/Zs56.ZW : Ljava/lang/String;
    //   1023: getstatic burp/Zbf9.ZC : Ljava/lang/Object;
    //   1026: checkcast java/math/BigInteger
    //   1029: invokevirtual intValue : ()I
    //   1032: bipush #32
    //   1034: irem
    //   1035: invokestatic abs : (I)I
    //   1038: invokevirtual charAt : (I)C
    //   1041: invokevirtual append : (C)Ljava/lang/StringBuilder;
    //   1044: pop
    //   1045: iload_2
    //   1046: ifeq -> 1348
    //   1049: goto -> 1056
    //   1052: invokestatic a : (Ljava/lang/Throwable;)Ljava/lang/Throwable;
    //   1055: athrow
    //   1056: aload_3
    //   1057: getstatic burp/Zer1.ZV : Ljava/lang/String;
    //   1060: getstatic burp/Zmvk.ZK : Ljava/lang/Object;
    //   1063: checkcast java/math/BigInteger
    //   1066: invokevirtual intValue : ()I
    //   1069: bipush #32
    //   1071: irem
    //   1072: invokestatic abs : (I)I
    //   1075: invokevirtual charAt : (I)C
    //   1078: invokevirtual append : (C)Ljava/lang/StringBuilder;
    //   1081: pop
    //   1082: iload_2
    //   1083: ifeq -> 1348
    //   1086: goto -> 1093
    //   1089: invokestatic a : (Ljava/lang/Throwable;)Ljava/lang/Throwable;
    //   1092: athrow
    //   1093: aload_3
    //   1094: getstatic burp/Zb9q.Zk : Ljava/lang/String;
    //   1097: getstatic burp/Zxpb.Zo : Ljava/lang/Object;
    //   1100: checkcast java/math/BigInteger
    //   1103: invokevirtual intValue : ()I
    //   1106: bipush #32
    //   1108: irem
    //   1109: invokestatic abs : (I)I
    //   1112: invokevirtual charAt : (I)C
    //   1115: invokevirtual append : (C)Ljava/lang/StringBuilder;
    //   1118: pop
    //   1119: iload_2
    //   1120: ifeq -> 1348
    //   1123: goto -> 1130
    //   1126: invokestatic a : (Ljava/lang/Throwable;)Ljava/lang/Throwable;
    //   1129: athrow
    //   1130: aload_3
    //   1131: getstatic burp/Zb8_.ZP : Ljava/lang/String;
    //   1134: getstatic burp/Zlg1.ZH : Ljava/lang/Object;
    //   1137: checkcast java/math/BigInteger
    //   1140: invokevirtual intValue : ()I
    //   1143: bipush #32
    //   1145: irem
    //   1146: invokestatic abs : (I)I
    //   1149: invokevirtual charAt : (I)C
    //   1152: invokevirtual append : (C)Ljava/lang/StringBuilder;
    //   1155: pop
    //   1156: iload_2
    //   1157: ifeq -> 1348
    //   1160: goto -> 1167
    //   1163: invokestatic a : (Ljava/lang/Throwable;)Ljava/lang/Throwable;
    //   1166: athrow
    //   1167: aload_3
    //   1168: getstatic burp/Zgwu.Zd : Ljava/lang/String;
    //   1171: getstatic burp/Ze3j.Ze : Ljava/lang/Object;
    //   1174: checkcast java/math/BigInteger
    //   1177: invokevirtual intValue : ()I
    //   1180: bipush #32
    //   1182: irem
    //   1183: invokestatic abs : (I)I
    //   1186: invokevirtual charAt : (I)C
    //   1189: invokevirtual append : (C)Ljava/lang/StringBuilder;
    //   1192: pop
    //   1193: iload_2
    //   1194: ifeq -> 1348
    //   1197: goto -> 1204
    //   1200: invokestatic a : (Ljava/lang/Throwable;)Ljava/lang/Throwable;
    //   1203: athrow
    //   1204: aload_3
    //   1205: getstatic burp/Ztpg.Zr : Ljava/lang/String;
    //   1208: getstatic burp/Znp.ZJ : Ljava/lang/Object;
    //   1211: checkcast java/math/BigInteger
    //   1214: invokevirtual intValue : ()I
    //   1217: bipush #32
    //   1219: irem
    //   1220: invokestatic abs : (I)I
    //   1223: invokevirtual charAt : (I)C
    //   1226: invokevirtual append : (C)Ljava/lang/StringBuilder;
    //   1229: pop
    //   1230: iload_2
    //   1231: ifeq -> 1348
    //   1234: goto -> 1241
    //   1237: invokestatic a : (Ljava/lang/Throwable;)Ljava/lang/Throwable;
    //   1240: athrow
    //   1241: aload_3
    //   1242: getstatic burp/Zltp.ZY : Ljava/lang/String;
    //   1245: getstatic burp/Zmha.ZM : Ljava/lang/Object;
    //   1248: checkcast java/math/BigInteger
    //   1251: invokevirtual intValue : ()I
    //   1254: bipush #32
    //   1256: irem
    //   1257: invokestatic abs : (I)I
    //   1260: invokevirtual charAt : (I)C
    //   1263: invokevirtual append : (C)Ljava/lang/StringBuilder;
    //   1266: pop
    //   1267: iload_2
    //   1268: ifeq -> 1348
    //   1271: goto -> 1278
    //   1274: invokestatic a : (Ljava/lang/Throwable;)Ljava/lang/Throwable;
    //   1277: athrow
    //   1278: aload_3
    //   1279: getstatic burp/Zg_5.ZG : Ljava/lang/String;
    //   1282: getstatic burp/Zmpc.Zc : Ljava/lang/Object;
    //   1285: checkcast java/math/BigInteger
    //   1288: invokevirtual intValue : ()I
    //   1291: bipush #32
    //   1293: irem
    //   1294: invokestatic abs : (I)I
    //   1297: invokevirtual charAt : (I)C
    //   1300: invokevirtual append : (C)Ljava/lang/StringBuilder;
    //   1303: pop
    //   1304: iload_2
    //   1305: ifeq -> 1348
    //   1308: goto -> 1315
    //   1311: invokestatic a : (Ljava/lang/Throwable;)Ljava/lang/Throwable;
    //   1314: athrow
    //   1315: aload_3
    //   1316: getstatic burp/Ztid.Zz : Ljava/lang/String;
    //   1319: getstatic burp/Ze_0.ZY : Ljava/lang/Object;
    //   1322: checkcast java/math/BigInteger
    //   1325: invokevirtual intValue : ()I
    //   1328: bipush #32
    //   1330: irem
    //   1331: invokestatic abs : (I)I
    //   1334: invokevirtual charAt : (I)C
    //   1337: invokevirtual append : (C)Ljava/lang/StringBuilder;
    //   1340: pop
    //   1341: goto -> 1348
    //   1344: invokestatic a : (Ljava/lang/Throwable;)Ljava/lang/Throwable;
    //   1347: athrow
    //   1348: iinc #4, 1
    //   1351: iload_2
    //   1352: ifeq -> 15
    //   1355: aload_3
    //   1356: invokevirtual toString : ()Ljava/lang/String;
    //   1359: putstatic burp/Zb8v.Zo : Ljava/lang/String;
    //   1362: new java/lang/StringBuilder
    //   1365: dup
    //   1366: invokespecial <init> : ()V
    //   1369: astore #4
    //   1371: iconst_0
    //   1372: istore #5
    //   1374: iload #5
    //   1376: bipush #32
    //   1378: if_icmpge -> 2743
    //   1381: iload #5
    //   1383: tableswitch default -> 2736, 0 -> 1524, 1 -> 1562, 2 -> 1600, 3 -> 1638, 4 -> 1676, 5 -> 1714, 6 -> 1752, 7 -> 1790, 8 -> 1828, 9 -> 1866, 10 -> 1904, 11 -> 1942, 12 -> 1980, 13 -> 2018, 14 -> 2056, 15 -> 2094, 16 -> 2132, 17 -> 2170, 18 -> 2208, 19 -> 2246, 20 -> 2284, 21 -> 2322, 22 -> 2360, 23 -> 2398, 24 -> 2436, 25 -> 2474, 26 -> 2512, 27 -> 2550, 28 -> 2588, 29 -> 2626, 30 -> 2664, 31 -> 2702
    //   1524: aload #4
    //   1526: getstatic burp/Zlzs.Zp : Ljava/lang/String;
    //   1529: getstatic burp/Zlsw.ZJ : Ljava/lang/Object;
    //   1532: checkcast java/math/BigInteger
    //   1535: invokevirtual intValue : ()I
    //   1538: bipush #32
    //   1540: irem
    //   1541: invokestatic abs : (I)I
    //   1544: invokevirtual charAt : (I)C
    //   1547: invokevirtual append : (C)Ljava/lang/StringBuilder;
    //   1550: pop
    //   1551: iload_2
    //   1552: ifeq -> 2736
    //   1555: goto -> 1562
    //   1558: invokestatic a : (Ljava/lang/Throwable;)Ljava/lang/Throwable;
    //   1561: athrow
    //   1562: aload #4
    //   1564: getstatic burp/Zea9.Zd : Ljava/lang/String;
    //   1567: getstatic burp/Zmhx.ZQ : Ljava/lang/Object;
    //   1570: checkcast java/math/BigInteger
    //   1573: invokevirtual intValue : ()I
    //   1576: bipush #32
    //   1578: irem
    //   1579: invokestatic abs : (I)I
    //   1582: invokevirtual charAt : (I)C
    //   1585: invokevirtual append : (C)Ljava/lang/StringBuilder;
    //   1588: pop
    //   1589: iload_2
    //   1590: ifeq -> 2736
    //   1593: goto -> 1600
    //   1596: invokestatic a : (Ljava/lang/Throwable;)Ljava/lang/Throwable;
    //   1599: athrow
    //   1600: aload #4
    //   1602: getstatic burp/Zlp7.ZO : Ljava/lang/String;
    //   1605: getstatic burp/Zmji.ZB : Ljava/lang/Object;
    //   1608: checkcast java/math/BigInteger
    //   1611: invokevirtual intValue : ()I
    //   1614: bipush #32
    //   1616: irem
    //   1617: invokestatic abs : (I)I
    //   1620: invokevirtual charAt : (I)C
    //   1623: invokevirtual append : (C)Ljava/lang/StringBuilder;
    //   1626: pop
    //   1627: iload_2
    //   1628: ifeq -> 2736
    //   1631: goto -> 1638
    //   1634: invokestatic a : (Ljava/lang/Throwable;)Ljava/lang/Throwable;
    //   1637: athrow
    //   1638: aload #4
    //   1640: getstatic burp/Zrcy.Zq : Ljava/lang/String;
    //   1643: getstatic burp/Zrf9.Zu : Ljava/lang/Object;
    //   1646: checkcast java/math/BigInteger
    //   1649: invokevirtual intValue : ()I
    //   1652: bipush #32
    //   1654: irem
    //   1655: invokestatic abs : (I)I
    //   1658: invokevirtual charAt : (I)C
    //   1661: invokevirtual append : (C)Ljava/lang/StringBuilder;
    //   1664: pop
    //   1665: iload_2
    //   1666: ifeq -> 2736
    //   1669: goto -> 1676
    //   1672: invokestatic a : (Ljava/lang/Throwable;)Ljava/lang/Throwable;
    //   1675: athrow
    //   1676: aload #4
    //   1678: getstatic burp/Zmji.Zs : Ljava/lang/String;
    //   1681: getstatic burp/Zzip.ZW : Ljava/lang/Object;
    //   1684: checkcast java/math/BigInteger
    //   1687: invokevirtual intValue : ()I
    //   1690: bipush #32
    //   1692: irem
    //   1693: invokestatic abs : (I)I
    //   1696: invokevirtual charAt : (I)C
    //   1699: invokevirtual append : (C)Ljava/lang/StringBuilder;
    //   1702: pop
    //   1703: iload_2
    //   1704: ifeq -> 2736
    //   1707: goto -> 1714
    //   1710: invokestatic a : (Ljava/lang/Throwable;)Ljava/lang/Throwable;
    //   1713: athrow
    //   1714: aload #4
    //   1716: getstatic burp/Zkc5.ZH : Ljava/lang/String;
    //   1719: getstatic burp/Zzox.Zq : Ljava/lang/Object;
    //   1722: checkcast java/math/BigInteger
    //   1725: invokevirtual intValue : ()I
    //   1728: bipush #32
    //   1730: irem
    //   1731: invokestatic abs : (I)I
    //   1734: invokevirtual charAt : (I)C
    //   1737: invokevirtual append : (C)Ljava/lang/StringBuilder;
    //   1740: pop
    //   1741: iload_2
    //   1742: ifeq -> 2736
    //   1745: goto -> 1752
    //   1748: invokestatic a : (Ljava/lang/Throwable;)Ljava/lang/Throwable;
    //   1751: athrow
    //   1752: aload #4
    //   1754: getstatic burp/Zvk.ZG : Ljava/lang/String;
    //   1757: getstatic burp/Ze13.ZD : Ljava/lang/Object;
    //   1760: checkcast java/math/BigInteger
    //   1763: invokevirtual intValue : ()I
    //   1766: bipush #32
    //   1768: irem
    //   1769: invokestatic abs : (I)I
    //   1772: invokevirtual charAt : (I)C
    //   1775: invokevirtual append : (C)Ljava/lang/StringBuilder;
    //   1778: pop
    //   1779: iload_2
    //   1780: ifeq -> 2736
    //   1783: goto -> 1790
    //   1786: invokestatic a : (Ljava/lang/Throwable;)Ljava/lang/Throwable;
    //   1789: athrow
    //   1790: aload #4
    //   1792: getstatic burp/Zm1l.Zp : Ljava/lang/String;
    //   1795: getstatic burp/Zme.Zd : Ljava/lang/Object;
    //   1798: checkcast java/math/BigInteger
    //   1801: invokevirtual intValue : ()I
    //   1804: bipush #32
    //   1806: irem
    //   1807: invokestatic abs : (I)I
    //   1810: invokevirtual charAt : (I)C
    //   1813: invokevirtual append : (C)Ljava/lang/StringBuilder;
    //   1816: pop
    //   1817: iload_2
    //   1818: ifeq -> 2736
    //   1821: goto -> 1828
    //   1824: invokestatic a : (Ljava/lang/Throwable;)Ljava/lang/Throwable;
    //   1827: athrow
    //   1828: aload #4
    //   1830: getstatic burp/Zep8.ZC : Ljava/lang/String;
    //   1833: getstatic burp/Zt7j.ZH : Ljava/lang/Object;
    //   1836: checkcast java/math/BigInteger
    //   1839: invokevirtual intValue : ()I
    //   1842: bipush #32
    //   1844: irem
    //   1845: invokestatic abs : (I)I
    //   1848: invokevirtual charAt : (I)C
    //   1851: invokevirtual append : (C)Ljava/lang/StringBuilder;
    //   1854: pop
    //   1855: iload_2
    //   1856: ifeq -> 2736
    //   1859: goto -> 1866
    //   1862: invokestatic a : (Ljava/lang/Throwable;)Ljava/lang/Throwable;
    //   1865: athrow
    //   1866: aload #4
    //   1868: getstatic burp/Ztv8.ZJ : Ljava/lang/String;
    //   1871: getstatic burp/Zct.ZW : Ljava/lang/Object;
    //   1874: checkcast java/math/BigInteger
    //   1877: invokevirtual intValue : ()I
    //   1880: bipush #32
    //   1882: irem
    //   1883: invokestatic abs : (I)I
    //   1886: invokevirtual charAt : (I)C
    //   1889: invokevirtual append : (C)Ljava/lang/StringBuilder;
    //   1892: pop
    //   1893: iload_2
    //   1894: ifeq -> 2736
    //   1897: goto -> 1904
    //   1900: invokestatic a : (Ljava/lang/Throwable;)Ljava/lang/Throwable;
    //   1903: athrow
    //   1904: aload #4
    //   1906: getstatic burp/Ztzw.Zi : Ljava/lang/String;
    //   1909: getstatic burp/Zx4k.ZE : Ljava/lang/Object;
    //   1912: checkcast java/math/BigInteger
    //   1915: invokevirtual intValue : ()I
    //   1918: bipush #32
    //   1920: irem
    //   1921: invokestatic abs : (I)I
    //   1924: invokevirtual charAt : (I)C
    //   1927: invokevirtual append : (C)Ljava/lang/StringBuilder;
    //   1930: pop
    //   1931: iload_2
    //   1932: ifeq -> 2736
    //   1935: goto -> 1942
    //   1938: invokestatic a : (Ljava/lang/Throwable;)Ljava/lang/Throwable;
    //   1941: athrow
    //   1942: aload #4
    //   1944: getstatic burp/Ztgv.ZC : Ljava/lang/String;
    //   1947: getstatic burp/Zlqq.ZV : Ljava/lang/Object;
    //   1950: checkcast java/math/BigInteger
    //   1953: invokevirtual intValue : ()I
    //   1956: bipush #32
    //   1958: irem
    //   1959: invokestatic abs : (I)I
    //   1962: invokevirtual charAt : (I)C
    //   1965: invokevirtual append : (C)Ljava/lang/StringBuilder;
    //   1968: pop
    //   1969: iload_2
    //   1970: ifeq -> 2736
    //   1973: goto -> 1980
    //   1976: invokestatic a : (Ljava/lang/Throwable;)Ljava/lang/Throwable;
    //   1979: athrow
    //   1980: aload #4
    //   1982: getstatic burp/Zluk.ZW : Ljava/lang/String;
    //   1985: getstatic burp/Zep1.ZW : Ljava/lang/Object;
    //   1988: checkcast java/math/BigInteger
    //   1991: invokevirtual intValue : ()I
    //   1994: bipush #32
    //   1996: irem
    //   1997: invokestatic abs : (I)I
    //   2000: invokevirtual charAt : (I)C
    //   2003: invokevirtual append : (C)Ljava/lang/StringBuilder;
    //   2006: pop
    //   2007: iload_2
    //   2008: ifeq -> 2736
    //   2011: goto -> 2018
    //   2014: invokestatic a : (Ljava/lang/Throwable;)Ljava/lang/Throwable;
    //   2017: athrow
    //   2018: aload #4
    //   2020: getstatic burp/Zt3l.Zi : Ljava/lang/String;
    //   2023: getstatic burp/Zkbf.Zx : Ljava/lang/Object;
    //   2026: checkcast java/math/BigInteger
    //   2029: invokevirtual intValue : ()I
    //   2032: bipush #32
    //   2034: irem
    //   2035: invokestatic abs : (I)I
    //   2038: invokevirtual charAt : (I)C
    //   2041: invokevirtual append : (C)Ljava/lang/StringBuilder;
    //   2044: pop
    //   2045: iload_2
    //   2046: ifeq -> 2736
    //   2049: goto -> 2056
    //   2052: invokestatic a : (Ljava/lang/Throwable;)Ljava/lang/Throwable;
    //   2055: athrow
    //   2056: aload #4
    //   2058: getstatic burp/Zsxj.Zp : Ljava/lang/String;
    //   2061: getstatic burp/Zt3l.Zq : Ljava/lang/Object;
    //   2064: checkcast java/math/BigInteger
    //   2067: invokevirtual intValue : ()I
    //   2070: bipush #32
    //   2072: irem
    //   2073: invokestatic abs : (I)I
    //   2076: invokevirtual charAt : (I)C
    //   2079: invokevirtual append : (C)Ljava/lang/StringBuilder;
    //   2082: pop
    //   2083: iload_2
    //   2084: ifeq -> 2736
    //   2087: goto -> 2094
    //   2090: invokestatic a : (Ljava/lang/Throwable;)Ljava/lang/Throwable;
    //   2093: athrow
    //   2094: aload #4
    //   2096: getstatic burp/Zgsy.Zv : Ljava/lang/String;
    //   2099: getstatic burp/Zlfg.Zv : Ljava/lang/Object;
    //   2102: checkcast java/math/BigInteger
    //   2105: invokevirtual intValue : ()I
    //   2108: bipush #32
    //   2110: irem
    //   2111: invokestatic abs : (I)I
    //   2114: invokevirtual charAt : (I)C
    //   2117: invokevirtual append : (C)Ljava/lang/StringBuilder;
    //   2120: pop
    //   2121: iload_2
    //   2122: ifeq -> 2736
    //   2125: goto -> 2132
    //   2128: invokestatic a : (Ljava/lang/Throwable;)Ljava/lang/Throwable;
    //   2131: athrow
    //   2132: aload #4
    //   2134: getstatic burp/Zldx.Zm : Ljava/lang/String;
    //   2137: getstatic burp/Zr3q.Zn : Ljava/lang/Object;
    //   2140: checkcast java/math/BigInteger
    //   2143: invokevirtual intValue : ()I
    //   2146: bipush #32
    //   2148: irem
    //   2149: invokestatic abs : (I)I
    //   2152: invokevirtual charAt : (I)C
    //   2155: invokevirtual append : (C)Ljava/lang/StringBuilder;
    //   2158: pop
    //   2159: iload_2
    //   2160: ifeq -> 2736
    //   2163: goto -> 2170
    //   2166: invokestatic a : (Ljava/lang/Throwable;)Ljava/lang/Throwable;
    //   2169: athrow
    //   2170: aload #4
    //   2172: getstatic burp/Zrvb.ZU : Ljava/lang/String;
    //   2175: getstatic burp/Ztq2.Zj : Ljava/lang/Object;
    //   2178: checkcast java/math/BigInteger
    //   2181: invokevirtual intValue : ()I
    //   2184: bipush #32
    //   2186: irem
    //   2187: invokestatic abs : (I)I
    //   2190: invokevirtual charAt : (I)C
    //   2193: invokevirtual append : (C)Ljava/lang/StringBuilder;
    //   2196: pop
    //   2197: iload_2
    //   2198: ifeq -> 2736
    //   2201: goto -> 2208
    //   2204: invokestatic a : (Ljava/lang/Throwable;)Ljava/lang/Throwable;
    //   2207: athrow
    //   2208: aload #4
    //   2210: getstatic burp/Zrpu.Zy : Ljava/lang/String;
    //   2213: getstatic burp/Zlx5.Zp : Ljava/lang/Object;
    //   2216: checkcast java/math/BigInteger
    //   2219: invokevirtual intValue : ()I
    //   2222: bipush #32
    //   2224: irem
    //   2225: invokestatic abs : (I)I
    //   2228: invokevirtual charAt : (I)C
    //   2231: invokevirtual append : (C)Ljava/lang/StringBuilder;
    //   2234: pop
    //   2235: iload_2
    //   2236: ifeq -> 2736
    //   2239: goto -> 2246
    //   2242: invokestatic a : (Ljava/lang/Throwable;)Ljava/lang/Throwable;
    //   2245: athrow
    //   2246: aload #4
    //   2248: getstatic burp/Zz3k.Zn : Ljava/lang/String;
    //   2251: getstatic burp/Zrdo.ZK : Ljava/lang/Object;
    //   2254: checkcast java/math/BigInteger
    //   2257: invokevirtual intValue : ()I
    //   2260: bipush #32
    //   2262: irem
    //   2263: invokestatic abs : (I)I
    //   2266: invokevirtual charAt : (I)C
    //   2269: invokevirtual append : (C)Ljava/lang/StringBuilder;
    //   2272: pop
    //   2273: iload_2
    //   2274: ifeq -> 2736
    //   2277: goto -> 2284
    //   2280: invokestatic a : (Ljava/lang/Throwable;)Ljava/lang/Throwable;
    //   2283: athrow
    //   2284: aload #4
    //   2286: getstatic burp/Ztw4.Zb : Ljava/lang/String;
    //   2289: getstatic burp/Zlid.Zx : Ljava/lang/Object;
    //   2292: checkcast java/math/BigInteger
    //   2295: invokevirtual intValue : ()I
    //   2298: bipush #32
    //   2300: irem
    //   2301: invokestatic abs : (I)I
    //   2304: invokevirtual charAt : (I)C
    //   2307: invokevirtual append : (C)Ljava/lang/StringBuilder;
    //   2310: pop
    //   2311: iload_2
    //   2312: ifeq -> 2736
    //   2315: goto -> 2322
    //   2318: invokestatic a : (Ljava/lang/Throwable;)Ljava/lang/Throwable;
    //   2321: athrow
    //   2322: aload #4
    //   2324: getstatic burp/Zllw.Zg : Ljava/lang/String;
    //   2327: getstatic burp/Zbqo.Zb : Ljava/lang/Object;
    //   2330: checkcast java/math/BigInteger
    //   2333: invokevirtual intValue : ()I
    //   2336: bipush #32
    //   2338: irem
    //   2339: invokestatic abs : (I)I
    //   2342: invokevirtual charAt : (I)C
    //   2345: invokevirtual append : (C)Ljava/lang/StringBuilder;
    //   2348: pop
    //   2349: iload_2
    //   2350: ifeq -> 2736
    //   2353: goto -> 2360
    //   2356: invokestatic a : (Ljava/lang/Throwable;)Ljava/lang/Throwable;
    //   2359: athrow
    //   2360: aload #4
    //   2362: getstatic burp/Zlbt.ZE : Ljava/lang/String;
    //   2365: getstatic burp/Zm3s.ZW : Ljava/lang/Object;
    //   2368: checkcast java/math/BigInteger
    //   2371: invokevirtual intValue : ()I
    //   2374: bipush #32
    //   2376: irem
    //   2377: invokestatic abs : (I)I
    //   2380: invokevirtual charAt : (I)C
    //   2383: invokevirtual append : (C)Ljava/lang/StringBuilder;
    //   2386: pop
    //   2387: iload_2
    //   2388: ifeq -> 2736
    //   2391: goto -> 2398
    //   2394: invokestatic a : (Ljava/lang/Throwable;)Ljava/lang/Throwable;
    //   2397: athrow
    //   2398: aload #4
    //   2400: getstatic burp/Zb_c.ZS : Ljava/lang/String;
    //   2403: getstatic burp/Zlhy.ZN : Ljava/lang/Object;
    //   2406: checkcast java/math/BigInteger
    //   2409: invokevirtual intValue : ()I
    //   2412: bipush #32
    //   2414: irem
    //   2415: invokestatic abs : (I)I
    //   2418: invokevirtual charAt : (I)C
    //   2421: invokevirtual append : (C)Ljava/lang/StringBuilder;
    //   2424: pop
    //   2425: iload_2
    //   2426: ifeq -> 2736
    //   2429: goto -> 2436
    //   2432: invokestatic a : (Ljava/lang/Throwable;)Ljava/lang/Throwable;
    //   2435: athrow
    //   2436: aload #4
    //   2438: getstatic burp/Ze40.Zr : Ljava/lang/String;
    //   2441: getstatic burp/Zbqk.ZT : Ljava/lang/Object;
    //   2444: checkcast java/math/BigInteger
    //   2447: invokevirtual intValue : ()I
    //   2450: bipush #32
    //   2452: irem
    //   2453: invokestatic abs : (I)I
    //   2456: invokevirtual charAt : (I)C
    //   2459: invokevirtual append : (C)Ljava/lang/StringBuilder;
    //   2462: pop
    //   2463: iload_2
    //   2464: ifeq -> 2736
    //   2467: goto -> 2474
    //   2470: invokestatic a : (Ljava/lang/Throwable;)Ljava/lang/Throwable;
    //   2473: athrow
    //   2474: aload #4
    //   2476: getstatic burp/Ztys.Zn : Ljava/lang/String;
    //   2479: getstatic burp/Zg2z.ZU : Ljava/lang/Object;
    //   2482: checkcast java/math/BigInteger
    //   2485: invokevirtual intValue : ()I
    //   2488: bipush #32
    //   2490: irem
    //   2491: invokestatic abs : (I)I
    //   2494: invokevirtual charAt : (I)C
    //   2497: invokevirtual append : (C)Ljava/lang/StringBuilder;
    //   2500: pop
    //   2501: iload_2
    //   2502: ifeq -> 2736
    //   2505: goto -> 2512
    //   2508: invokestatic a : (Ljava/lang/Throwable;)Ljava/lang/Throwable;
    //   2511: athrow
    //   2512: aload #4
    //   2514: getstatic burp/Zg_5.ZG : Ljava/lang/String;
    //   2517: getstatic burp/Zm81.Zy : Ljava/lang/Object;
    //   2520: checkcast java/math/BigInteger
    //   2523: invokevirtual intValue : ()I
    //   2526: bipush #32
    //   2528: irem
    //   2529: invokestatic abs : (I)I
    //   2532: invokevirtual charAt : (I)C
    //   2535: invokevirtual append : (C)Ljava/lang/StringBuilder;
    //   2538: pop
    //   2539: iload_2
    //   2540: ifeq -> 2736
    //   2543: goto -> 2550
    //   2546: invokestatic a : (Ljava/lang/Throwable;)Ljava/lang/Throwable;
    //   2549: athrow
    //   2550: aload #4
    //   2552: getstatic burp/Zzxa.Zl : Ljava/lang/String;
    //   2555: getstatic burp/Zr64.ZN : Ljava/lang/Object;
    //   2558: checkcast java/math/BigInteger
    //   2561: invokevirtual intValue : ()I
    //   2564: bipush #32
    //   2566: irem
    //   2567: invokestatic abs : (I)I
    //   2570: invokevirtual charAt : (I)C
    //   2573: invokevirtual append : (C)Ljava/lang/StringBuilder;
    //   2576: pop
    //   2577: iload_2
    //   2578: ifeq -> 2736
    //   2581: goto -> 2588
    //   2584: invokestatic a : (Ljava/lang/Throwable;)Ljava/lang/Throwable;
    //   2587: athrow
    //   2588: aload #4
    //   2590: getstatic burp/Zxti.ZD : Ljava/lang/String;
    //   2593: getstatic burp/Zmgl.ZI : Ljava/lang/Object;
    //   2596: checkcast java/math/BigInteger
    //   2599: invokevirtual intValue : ()I
    //   2602: bipush #32
    //   2604: irem
    //   2605: invokestatic abs : (I)I
    //   2608: invokevirtual charAt : (I)C
    //   2611: invokevirtual append : (C)Ljava/lang/StringBuilder;
    //   2614: pop
    //   2615: iload_2
    //   2616: ifeq -> 2736
    //   2619: goto -> 2626
    //   2622: invokestatic a : (Ljava/lang/Throwable;)Ljava/lang/Throwable;
    //   2625: athrow
    //   2626: aload #4
    //   2628: getstatic burp/Ztnw.Zr : Ljava/lang/String;
    //   2631: getstatic burp/Zztx.ZM : Ljava/lang/Object;
    //   2634: checkcast java/math/BigInteger
    //   2637: invokevirtual intValue : ()I
    //   2640: bipush #32
    //   2642: irem
    //   2643: invokestatic abs : (I)I
    //   2646: invokevirtual charAt : (I)C
    //   2649: invokevirtual append : (C)Ljava/lang/StringBuilder;
    //   2652: pop
    //   2653: iload_2
    //   2654: ifeq -> 2736
    //   2657: goto -> 2664
    //   2660: invokestatic a : (Ljava/lang/Throwable;)Ljava/lang/Throwable;
    //   2663: athrow
    //   2664: aload #4
    //   2666: getstatic burp/Zxzj.ZZ : Ljava/lang/String;
    //   2669: getstatic burp/Zl1z.ZV : Ljava/lang/Object;
    //   2672: checkcast java/math/BigInteger
    //   2675: invokevirtual intValue : ()I
    //   2678: bipush #32
    //   2680: irem
    //   2681: invokestatic abs : (I)I
    //   2684: invokevirtual charAt : (I)C
    //   2687: invokevirtual append : (C)Ljava/lang/StringBuilder;
    //   2690: pop
    //   2691: iload_2
    //   2692: ifeq -> 2736
    //   2695: goto -> 2702
    //   2698: invokestatic a : (Ljava/lang/Throwable;)Ljava/lang/Throwable;
    //   2701: athrow
    //   2702: aload #4
    //   2704: getstatic burp/Zb9d.Zh : Ljava/lang/String;
    //   2707: getstatic burp/Zr64.ZN : Ljava/lang/Object;
    //   2710: checkcast java/math/BigInteger
    //   2713: invokevirtual intValue : ()I
    //   2716: bipush #32
    //   2718: irem
    //   2719: invokestatic abs : (I)I
    //   2722: invokevirtual charAt : (I)C
    //   2725: invokevirtual append : (C)Ljava/lang/StringBuilder;
    //   2728: pop
    //   2729: goto -> 2736
    //   2732: invokestatic a : (Ljava/lang/Throwable;)Ljava/lang/Throwable;
    //   2735: athrow
    //   2736: iinc #5, 1
    //   2739: iload_2
    //   2740: ifeq -> 1374
    //   2743: aload #4
    //   2745: invokevirtual toString : ()Ljava/lang/String;
    //   2748: putstatic burp/Zgjj.Zi : Ljava/lang/String;
    //   2751: sipush #14598
    //   2754: sipush #-21022
    //   2757: invokestatic a : (II)Ljava/lang/String;
    //   2760: iconst_1
    //   2761: ldc burp/Zenr
    //   2763: invokevirtual getClassLoader : ()Ljava/lang/ClassLoader;
    //   2766: invokestatic forName : (Ljava/lang/String;ZLjava/lang/ClassLoader;)Ljava/lang/Class;
    //   2769: invokevirtual getDeclaredFields : ()[Ljava/lang/reflect/Field;
    //   2772: astore #5
    //   2774: aload #5
    //   2776: arraylength
    //   2777: istore #6
    //   2779: iconst_0
    //   2780: istore #7
    //   2782: iload #7
    //   2784: iload #6
    //   2786: if_icmpge -> 2923
    //   2789: aload #5
    //   2791: iload #7
    //   2793: aaload
    //   2794: astore #8
    //   2796: aload #8
    //   2798: invokevirtual getModifiers : ()I
    //   2801: invokestatic isStatic : (I)Z
    //   2804: ifne -> 2814
    //   2807: goto -> 2916
    //   2810: invokestatic a : (Ljava/lang/Throwable;)Ljava/lang/Throwable;
    //   2813: athrow
    //   2814: aload #8
    //   2816: invokevirtual getType : ()Ljava/lang/Class;
    //   2819: astore #9
    //   2821: aload #9
    //   2823: ifnull -> 2903
    //   2826: aload #9
    //   2828: invokevirtual isPrimitive : ()Z
    //   2831: ifne -> 2903
    //   2834: goto -> 2841
    //   2837: invokestatic a : (Ljava/lang/Throwable;)Ljava/lang/Throwable;
    //   2840: athrow
    //   2841: aload #9
    //   2843: invokevirtual getPackage : ()Ljava/lang/Package;
    //   2846: ifnull -> 2903
    //   2849: goto -> 2856
    //   2852: invokestatic a : (Ljava/lang/Throwable;)Ljava/lang/Throwable;
    //   2855: athrow
    //   2856: aload #9
    //   2858: invokevirtual getPackage : ()Ljava/lang/Package;
    //   2861: invokevirtual getName : ()Ljava/lang/String;
    //   2864: ifnull -> 2903
    //   2867: goto -> 2874
    //   2870: invokestatic a : (Ljava/lang/Throwable;)Ljava/lang/Throwable;
    //   2873: athrow
    //   2874: aload #9
    //   2876: invokevirtual getPackage : ()Ljava/lang/Package;
    //   2879: invokevirtual getName : ()Ljava/lang/String;
    //   2882: sipush #14613
    //   2885: bipush #-31
    //   2887: invokestatic a : (II)Ljava/lang/String;
    //   2890: invokevirtual startsWith : (Ljava/lang/String;)Z
    //   2893: ifne -> 2903
    //   2896: goto -> 2903
    //   2899: invokestatic a : (Ljava/lang/Throwable;)Ljava/lang/Throwable;
    //   2902: athrow
    //   2903: aload #8
    //   2905: iconst_1
    //   2906: invokevirtual setAccessible : (Z)V
    //   2909: aload #8
    //   2911: aconst_null
    //   2912: invokevirtual get : (Ljava/lang/Object;)Ljava/lang/Object;
    //   2915: pop
    //   2916: iinc #7, 1
    //   2919: iload_2
    //   2920: ifeq -> 2782
    //   2923: sipush #14623
    //   2926: sipush #-31268
    //   2929: invokestatic a : (II)Ljava/lang/String;
    //   2932: invokestatic forName : (Ljava/lang/String;)Ljava/lang/Class;
    //   2935: invokevirtual getDeclaredMethods : ()[Ljava/lang/reflect/Method;
    //   2938: astore #5
    //   2940: aload #5
    //   2942: arraylength
    //   2943: istore #6
    //   2945: iconst_0
    //   2946: istore #7
    //   2948: iload #7
    //   2950: iload #6
    //   2952: if_icmpge -> 3082
    //   2955: aload #5
    //   2957: iload #7
    //   2959: aaload
    //   2960: astore #8
    //   2962: aload #8
    //   2964: invokevirtual getParameterTypes : ()[Ljava/lang/Class;
    //   2967: pop
    //   2968: aload #8
    //   2970: invokevirtual getModifiers : ()I
    //   2973: invokestatic isStatic : (I)Z
    //   2976: ifeq -> 3068
    //   2979: aload #8
    //   2981: invokevirtual getParameterTypes : ()[Ljava/lang/Class;
    //   2984: arraylength
    //   2985: iconst_2
    //   2986: if_icmpne -> 3068
    //   2989: goto -> 2996
    //   2992: invokestatic a : (Ljava/lang/Throwable;)Ljava/lang/Throwable;
    //   2995: athrow
    //   2996: aload #8
    //   2998: invokevirtual getReturnType : ()Ljava/lang/Class;
    //   3001: getstatic java/lang/Boolean.TYPE : Ljava/lang/Class;
    //   3004: if_acmpne -> 3068
    //   3007: goto -> 3014
    //   3010: invokestatic a : (Ljava/lang/Throwable;)Ljava/lang/Throwable;
    //   3013: athrow
    //   3014: aload #8
    //   3016: iconst_1
    //   3017: invokevirtual setAccessible : (Z)V
    //   3020: aload #8
    //   3022: aconst_null
    //   3023: iconst_2
    //   3024: anewarray java/lang/Object
    //   3027: dup
    //   3028: iconst_0
    //   3029: aload_0
    //   3030: aastore
    //   3031: dup
    //   3032: iconst_1
    //   3033: aload_1
    //   3034: ifnonnull -> 3052
    //   3037: goto -> 3044
    //   3040: invokestatic a : (Ljava/lang/Throwable;)Ljava/lang/Throwable;
    //   3043: athrow
    //   3044: aload_1
    //   3045: goto -> 3059
    //   3048: invokestatic a : (Ljava/lang/Throwable;)Ljava/lang/Throwable;
    //   3051: athrow
    //   3052: aload_1
    //   3053: checkcast [B
    //   3056: invokevirtual clone : ()Ljava/lang/Object;
    //   3059: aastore
    //   3060: invokevirtual invoke : (Ljava/lang/Object;[Ljava/lang/Object;)Ljava/lang/Object;
    //   3063: pop
    //   3064: iload_2
    //   3065: ifeq -> 3082
    //   3068: iinc #7, 1
    //   3071: iload_2
    //   3072: ifeq -> 2948
    //   3075: goto -> 3082
    //   3078: invokestatic a : (Ljava/lang/Throwable;)Ljava/lang/Throwable;
    //   3081: athrow
    //   3082: sipush #14618
    //   3085: sipush #19756
    //   3088: invokestatic a : (II)Ljava/lang/String;
    //   3091: iconst_1
    //   3092: ldc burp/Zr8h
    //   3094: invokevirtual getClassLoader : ()Ljava/lang/ClassLoader;
    //   3097: invokestatic forName : (Ljava/lang/String;ZLjava/lang/ClassLoader;)Ljava/lang/Class;
    //   3100: invokevirtual getDeclaredFields : ()[Ljava/lang/reflect/Field;
    //   3103: astore #5
    //   3105: aload #5
    //   3107: arraylength
    //   3108: istore #6
    //   3110: iconst_0
    //   3111: istore #7
    //   3113: iload #7
    //   3115: iload #6
    //   3117: if_icmpge -> 3255
    //   3120: aload #5
    //   3122: iload #7
    //   3124: aaload
    //   3125: astore #8
    //   3127: aload #8
    //   3129: invokevirtual getModifiers : ()I
    //   3132: invokestatic isStatic : (I)Z
    //   3135: ifne -> 3145
    //   3138: goto -> 3248
    //   3141: invokestatic a : (Ljava/lang/Throwable;)Ljava/lang/Throwable;
    //   3144: athrow
    //   3145: aload #8
    //   3147: invokevirtual getType : ()Ljava/lang/Class;
    //   3150: astore #9
    //   3152: aload #9
    //   3154: ifnull -> 3235
    //   3157: aload #9
    //   3159: invokevirtual isPrimitive : ()Z
    //   3162: ifne -> 3235
    //   3165: goto -> 3172
    //   3168: invokestatic a : (Ljava/lang/Throwable;)Ljava/lang/Throwable;
    //   3171: athrow
    //   3172: aload #9
    //   3174: invokevirtual getPackage : ()Ljava/lang/Package;
    //   3177: ifnull -> 3235
    //   3180: goto -> 3187
    //   3183: invokestatic a : (Ljava/lang/Throwable;)Ljava/lang/Throwable;
    //   3186: athrow
    //   3187: aload #9
    //   3189: invokevirtual getPackage : ()Ljava/lang/Package;
    //   3192: invokevirtual getName : ()Ljava/lang/String;
    //   3195: ifnull -> 3235
    //   3198: goto -> 3205
    //   3201: invokestatic a : (Ljava/lang/Throwable;)Ljava/lang/Throwable;
    //   3204: athrow
    //   3205: aload #9
    //   3207: invokevirtual getPackage : ()Ljava/lang/Package;
    //   3210: invokevirtual getName : ()Ljava/lang/String;
    //   3213: sipush #14617
    //   3216: sipush #10258
    //   3219: invokestatic a : (II)Ljava/lang/String;
    //   3222: invokevirtual startsWith : (Ljava/lang/String;)Z
    //   3225: ifne -> 3235
    //   3228: goto -> 3235
    //   3231: invokestatic a : (Ljava/lang/Throwable;)Ljava/lang/Throwable;
    //   3234: athrow
    //   3235: aload #8
    //   3237: iconst_1
    //   3238: invokevirtual setAccessible : (Z)V
    //   3241: aload #8
    //   3243: aconst_null
    //   3244: invokevirtual get : (Ljava/lang/Object;)Ljava/lang/Object;
    //   3247: pop
    //   3248: iinc #7, 1
    //   3251: iload_2
    //   3252: ifeq -> 3113
    //   3255: sipush #14602
    //   3258: sipush #-8911
    //   3261: invokestatic a : (II)Ljava/lang/String;
    //   3264: invokestatic forName : (Ljava/lang/String;)Ljava/lang/Class;
    //   3267: invokevirtual getDeclaredMethods : ()[Ljava/lang/reflect/Method;
    //   3270: astore #5
    //   3272: aload #5
    //   3274: arraylength
    //   3275: istore #6
    //   3277: iconst_0
    //   3278: istore #7
    //   3280: iload #7
    //   3282: iload #6
    //   3284: if_icmpge -> 3417
    //   3287: aload #5
    //   3289: iload #7
    //   3291: aaload
    //   3292: astore #8
    //   3294: aload #8
    //   3296: invokevirtual getParameterTypes : ()[Ljava/lang/Class;
    //   3299: pop
    //   3300: aload #8
    //   3302: invokevirtual getModifiers : ()I
    //   3305: invokestatic isStatic : (I)Z
    //   3308: ifeq -> 3403
    //   3311: aload #8
    //   3313: invokevirtual getParameterTypes : ()[Ljava/lang/Class;
    //   3316: arraylength
    //   3317: iconst_2
    //   3318: if_icmpne -> 3403
    //   3321: goto -> 3328
    //   3324: invokestatic a : (Ljava/lang/Throwable;)Ljava/lang/Throwable;
    //   3327: athrow
    //   3328: aload #8
    //   3330: invokevirtual getReturnType : ()Ljava/lang/Class;
    //   3333: getstatic java/lang/Void.TYPE : Ljava/lang/Class;
    //   3336: invokevirtual equals : (Ljava/lang/Object;)Z
    //   3339: ifeq -> 3403
    //   3342: goto -> 3349
    //   3345: invokestatic a : (Ljava/lang/Throwable;)Ljava/lang/Throwable;
    //   3348: athrow
    //   3349: aload #8
    //   3351: iconst_1
    //   3352: invokevirtual setAccessible : (Z)V
    //   3355: aload #8
    //   3357: aconst_null
    //   3358: iconst_2
    //   3359: anewarray java/lang/Object
    //   3362: dup
    //   3363: iconst_0
    //   3364: aload_0
    //   3365: aastore
    //   3366: dup
    //   3367: iconst_1
    //   3368: aload_1
    //   3369: ifnonnull -> 3387
    //   3372: goto -> 3379
    //   3375: invokestatic a : (Ljava/lang/Throwable;)Ljava/lang/Throwable;
    //   3378: athrow
    //   3379: aload_1
    //   3380: goto -> 3394
    //   3383: invokestatic a : (Ljava/lang/Throwable;)Ljava/lang/Throwable;
    //   3386: athrow
    //   3387: aload_1
    //   3388: checkcast [B
    //   3391: invokevirtual clone : ()Ljava/lang/Object;
    //   3394: aastore
    //   3395: invokevirtual invoke : (Ljava/lang/Object;[Ljava/lang/Object;)Ljava/lang/Object;
    //   3398: pop
    //   3399: iload_2
    //   3400: ifeq -> 3417
    //   3403: iinc #7, 1
    //   3406: iload_2
    //   3407: ifeq -> 3280
    //   3410: goto -> 3417
    //   3413: invokestatic a : (Ljava/lang/Throwable;)Ljava/lang/Throwable;
    //   3416: athrow
    //   3417: getstatic burp/Zl7k.ZS : Ljava/lang/Object;
    //   3420: checkcast java/math/BigInteger
    //   3423: invokevirtual toByteArray : ()[B
    //   3426: astore #5
    //   3428: aload #5
    //   3430: arraylength
    //   3431: iconst_2
    //   3432: iadd
    //   3433: newarray byte
    //   3435: astore #7
    //   3437: iconst_0
    //   3438: istore #8
    //   3440: iload #8
    //   3442: aload #5
    //   3444: arraylength
    //   3445: if_icmpge -> 3465
    //   3448: aload #7
    //   3450: iload #8
    //   3452: aload #5
    //   3454: iload #8
    //   3456: baload
    //   3457: bastore
    //   3458: iinc #8, 1
    //   3461: iload_2
    //   3462: ifeq -> 3440
    //   3465: aload #7
    //   3467: arraylength
    //   3468: iconst_3
    //   3469: idiv
    //   3470: iconst_4
    //   3471: imul
    //   3472: newarray byte
    //   3474: astore #6
    //   3476: iconst_0
    //   3477: istore #8
    //   3479: iconst_0
    //   3480: istore #9
    //   3482: iload #8
    //   3484: aload #5
    //   3486: arraylength
    //   3487: if_icmpge -> 3598
    //   3490: aload #6
    //   3492: iload #9
    //   3494: aload #7
    //   3496: iload #8
    //   3498: baload
    //   3499: iconst_2
    //   3500: iushr
    //   3501: bipush #63
    //   3503: iand
    //   3504: i2b
    //   3505: bastore
    //   3506: aload #6
    //   3508: iload #9
    //   3510: iconst_1
    //   3511: iadd
    //   3512: aload #7
    //   3514: iload #8
    //   3516: iconst_1
    //   3517: iadd
    //   3518: baload
    //   3519: iconst_4
    //   3520: iushr
    //   3521: bipush #15
    //   3523: iand
    //   3524: aload #7
    //   3526: iload #8
    //   3528: baload
    //   3529: iconst_4
    //   3530: ishl
    //   3531: bipush #63
    //   3533: iand
    //   3534: ior
    //   3535: i2b
    //   3536: bastore
    //   3537: aload #6
    //   3539: iload #9
    //   3541: iconst_2
    //   3542: iadd
    //   3543: aload #7
    //   3545: iload #8
    //   3547: iconst_2
    //   3548: iadd
    //   3549: baload
    //   3550: bipush #6
    //   3552: iushr
    //   3553: iconst_3
    //   3554: iand
    //   3555: aload #7
    //   3557: iload #8
    //   3559: iconst_1
    //   3560: iadd
    //   3561: baload
    //   3562: iconst_2
    //   3563: ishl
    //   3564: bipush #63
    //   3566: iand
    //   3567: ior
    //   3568: i2b
    //   3569: bastore
    //   3570: aload #6
    //   3572: iload #9
    //   3574: iconst_3
    //   3575: iadd
    //   3576: aload #7
    //   3578: iload #8
    //   3580: iconst_2
    //   3581: iadd
    //   3582: baload
    //   3583: bipush #63
    //   3585: iand
    //   3586: i2b
    //   3587: bastore
    //   3588: iinc #8, 3
    //   3591: iinc #9, 4
    //   3594: iload_2
    //   3595: ifeq -> 3482
    //   3598: iconst_0
    //   3599: istore #8
    //   3601: iload #8
    //   3603: aload #6
    //   3605: arraylength
    //   3606: if_icmpge -> 3790
    //   3609: aload #6
    //   3611: iload #8
    //   3613: baload
    //   3614: bipush #26
    //   3616: if_icmpge -> 3644
    //   3619: aload #6
    //   3621: iload #8
    //   3623: aload #6
    //   3625: iload #8
    //   3627: baload
    //   3628: bipush #65
    //   3630: iadd
    //   3631: i2b
    //   3632: bastore
    //   3633: iload_2
    //   3634: ifeq -> 3783
    //   3637: goto -> 3644
    //   3640: invokestatic a : (Ljava/lang/Throwable;)Ljava/lang/Throwable;
    //   3643: athrow
    //   3644: aload #6
    //   3646: iload #8
    //   3648: baload
    //   3649: bipush #52
    //   3651: if_icmpge -> 3689
    //   3654: goto -> 3661
    //   3657: invokestatic a : (Ljava/lang/Throwable;)Ljava/lang/Throwable;
    //   3660: athrow
    //   3661: aload #6
    //   3663: iload #8
    //   3665: aload #6
    //   3667: iload #8
    //   3669: baload
    //   3670: bipush #97
    //   3672: iadd
    //   3673: bipush #26
    //   3675: isub
    //   3676: i2b
    //   3677: bastore
    //   3678: iload_2
    //   3679: ifeq -> 3783
    //   3682: goto -> 3689
    //   3685: invokestatic a : (Ljava/lang/Throwable;)Ljava/lang/Throwable;
    //   3688: athrow
    //   3689: aload #6
    //   3691: iload #8
    //   3693: baload
    //   3694: bipush #62
    //   3696: if_icmpge -> 3734
    //   3699: goto -> 3706
    //   3702: invokestatic a : (Ljava/lang/Throwable;)Ljava/lang/Throwable;
    //   3705: athrow
    //   3706: aload #6
    //   3708: iload #8
    //   3710: aload #6
    //   3712: iload #8
    //   3714: baload
    //   3715: bipush #48
    //   3717: iadd
    //   3718: bipush #52
    //   3720: isub
    //   3721: i2b
    //   3722: bastore
    //   3723: iload_2
    //   3724: ifeq -> 3783
    //   3727: goto -> 3734
    //   3730: invokestatic a : (Ljava/lang/Throwable;)Ljava/lang/Throwable;
    //   3733: athrow
    //   3734: aload #6
    //   3736: iload #8
    //   3738: baload
    //   3739: bipush #63
    //   3741: if_icmpge -> 3769
    //   3744: goto -> 3751
    //   3747: invokestatic a : (Ljava/lang/Throwable;)Ljava/lang/Throwable;
    //   3750: athrow
    //   3751: aload #6
    //   3753: iload #8
    //   3755: bipush #43
    //   3757: bastore
    //   3758: iload_2
    //   3759: ifeq -> 3783
    //   3762: goto -> 3769
    //   3765: invokestatic a : (Ljava/lang/Throwable;)Ljava/lang/Throwable;
    //   3768: athrow
    //   3769: aload #6
    //   3771: iload #8
    //   3773: bipush #47
    //   3775: bastore
    //   3776: goto -> 3783
    //   3779: invokestatic a : (Ljava/lang/Throwable;)Ljava/lang/Throwable;
    //   3782: athrow
    //   3783: iinc #8, 1
    //   3786: iload_2
    //   3787: ifeq -> 3601
    //   3790: aload #6
    //   3792: arraylength
    //   3793: iconst_1
    //   3794: isub
    //   3795: istore #8
    //   3797: iload #8
    //   3799: aload #5
    //   3801: arraylength
    //   3802: iconst_4
    //   3803: imul
    //   3804: iconst_3
    //   3805: idiv
    //   3806: if_icmple -> 3823
    //   3809: aload #6
    //   3811: iload #8
    //   3813: bipush #61
    //   3815: bastore
    //   3816: iinc #8, -1
    //   3819: iload_2
    //   3820: ifeq -> 3797
    //   3823: new java/io/ByteArrayOutputStream
    //   3826: dup
    //   3827: invokespecial <init> : ()V
    //   3830: astore #5
    //   3832: sipush #14610
    //   3835: aload #5
    //   3837: sipush #202
    //   3840: invokevirtual write : (I)V
    //   3843: sipush #22012
    //   3846: aload #5
    //   3848: sipush #254
    //   3851: invokevirtual write : (I)V
    //   3854: aload #5
    //   3856: sipush #186
    //   3859: invokevirtual write : (I)V
    //   3862: aload #5
    //   3864: sipush #190
    //   3867: invokevirtual write : (I)V
    //   3870: aload #5
    //   3872: iconst_0
    //   3873: invokevirtual write : (I)V
    //   3876: aload #5
    //   3878: iconst_1
    //   3879: invokevirtual write : (I)V
    //   3882: aload #5
    //   3884: iconst_0
    //   3885: invokevirtual write : (I)V
    //   3888: aload #5
    //   3890: bipush #50
    //   3892: invokevirtual write : (I)V
    //   3895: aload #5
    //   3897: getstatic burp/Zrnu.Zs : Ljava/lang/Object;
    //   3900: checkcast java/math/BigInteger
    //   3903: invokevirtual toByteArray : ()[B
    //   3906: invokevirtual write : ([B)V
    //   3909: aload #5
    //   3911: getstatic burp/Zxso.ZF : Ljava/lang/Object;
    //   3914: checkcast java/math/BigInteger
    //   3917: invokevirtual toByteArray : ()[B
    //   3920: invokevirtual write : ([B)V
    //   3923: aload #5
    //   3925: getstatic burp/Zxyu.Zp : Ljava/lang/Object;
    //   3928: checkcast java/math/BigInteger
    //   3931: invokevirtual toByteArray : ()[B
    //   3934: invokevirtual write : ([B)V
    //   3937: aload #5
    //   3939: invokevirtual toByteArray : ()[B
    //   3942: astore #6
    //   3944: aconst_null
    //   3945: astore #7
    //   3947: invokestatic a : (II)Ljava/lang/String;
    //   3950: invokestatic forName : (Ljava/lang/String;)Ljava/lang/Class;
    //   3953: invokevirtual getDeclaredMethods : ()[Ljava/lang/reflect/Method;
    //   3956: astore #8
    //   3958: aload #8
    //   3960: arraylength
    //   3961: istore #9
    //   3963: iconst_0
    //   3964: istore #10
    //   3966: iload #10
    //   3968: iload #9
    //   3970: if_icmpge -> 4098
    //   3973: aload #8
    //   3975: iload #10
    //   3977: aaload
    //   3978: astore #11
    //   3980: aload #11
    //   3982: invokevirtual getName : ()Ljava/lang/String;
    //   3985: sipush #14615
    //   3988: sipush #32158
    //   3991: invokestatic a : (II)Ljava/lang/String;
    //   3994: invokevirtual equals : (Ljava/lang/Object;)Z
    //   3997: ifeq -> 4091
    //   4000: aload #11
    //   4002: invokevirtual getParameterTypes : ()[Ljava/lang/Class;
    //   4005: astore #12
    //   4007: aload #12
    //   4009: arraylength
    //   4010: iconst_4
    //   4011: if_icmpeq -> 4021
    //   4014: goto -> 4091
    //   4017: invokestatic a : (Ljava/lang/Throwable;)Ljava/lang/Throwable;
    //   4020: athrow
    //   4021: aload #12
    //   4023: iconst_0
    //   4024: aaload
    //   4025: ldc java/lang/String
    //   4027: if_acmpeq -> 4037
    //   4030: goto -> 4091
    //   4033: invokestatic a : (Ljava/lang/Throwable;)Ljava/lang/Throwable;
    //   4036: athrow
    //   4037: aload #12
    //   4039: iconst_1
    //   4040: aaload
    //   4041: ldc [B
    //   4043: if_acmpeq -> 4053
    //   4046: goto -> 4091
    //   4049: invokestatic a : (Ljava/lang/Throwable;)Ljava/lang/Throwable;
    //   4052: athrow
    //   4053: aload #12
    //   4055: iconst_2
    //   4056: aaload
    //   4057: getstatic java/lang/Integer.TYPE : Ljava/lang/Class;
    //   4060: if_acmpeq -> 4070
    //   4063: goto -> 4091
    //   4066: invokestatic a : (Ljava/lang/Throwable;)Ljava/lang/Throwable;
    //   4069: athrow
    //   4070: aload #12
    //   4072: iconst_3
    //   4073: aaload
    //   4074: getstatic java/lang/Integer.TYPE : Ljava/lang/Class;
    //   4077: if_acmpeq -> 4087
    //   4080: goto -> 4091
    //   4083: invokestatic a : (Ljava/lang/Throwable;)Ljava/lang/Throwable;
    //   4086: athrow
    //   4087: aload #11
    //   4089: astore #7
    //   4091: iinc #10, 1
    //   4094: iload_2
    //   4095: ifeq -> 3966
    //   4098: aload #7
    //   4100: iconst_1
    //   4101: invokevirtual setAccessible : (Z)V
    //   4104: ldc burp/Zxzp
    //   4106: iconst_0
    //   4107: anewarray java/lang/Class
    //   4110: invokevirtual getDeclaredConstructor : ([Ljava/lang/Class;)Ljava/lang/reflect/Constructor;
    //   4113: astore #8
    //   4115: aload #8
    //   4117: iconst_1
    //   4118: invokevirtual setAccessible : (Z)V
    //   4121: aload #7
    //   4123: aload #8
    //   4125: iconst_0
    //   4126: anewarray java/lang/Object
    //   4129: invokevirtual newInstance : ([Ljava/lang/Object;)Ljava/lang/Object;
    //   4132: iconst_4
    //   4133: anewarray java/lang/Object
    //   4136: dup
    //   4137: iconst_0
    //   4138: sipush #14616
    //   4141: sipush #-30457
    //   4144: invokestatic a : (II)Ljava/lang/String;
    //   4147: aastore
    //   4148: dup
    //   4149: iconst_1
    //   4150: aload #6
    //   4152: aastore
    //   4153: dup
    //   4154: iconst_2
    //   4155: iconst_0
    //   4156: invokestatic valueOf : (I)Ljava/lang/Integer;
    //   4159: aastore
    //   4160: dup
    //   4161: iconst_3
    //   4162: aload #6
    //   4164: arraylength
    //   4165: invokestatic valueOf : (I)Ljava/lang/Integer;
    //   4168: aastore
    //   4169: invokevirtual invoke : (Ljava/lang/Object;[Ljava/lang/Object;)Ljava/lang/Object;
    //   4172: pop
    //   4173: goto -> 4178
    //   4176: astore #5
    //   4178: iconst_0
    //   4179: istore #5
    //   4181: getstatic burp/Zrm4.ZK : Ljava/lang/String;
    //   4184: getstatic burp/Zl7k.ZS : Ljava/lang/Object;
    //   4187: checkcast java/math/BigInteger
    //   4190: invokevirtual intValue : ()I
    //   4193: bipush #32
    //   4195: irem
    //   4196: invokestatic abs : (I)I
    //   4199: invokevirtual charAt : (I)C
    //   4202: getstatic burp/Zsq5.ZA : Ljava/lang/String;
    //   4205: getstatic burp/Zezn.Zh : Ljava/lang/Object;
    //   4208: checkcast java/math/BigInteger
    //   4211: invokevirtual intValue : ()I
    //   4214: bipush #32
    //   4216: irem
    //   4217: invokestatic abs : (I)I
    //   4220: invokevirtual charAt : (I)C
    //   4223: if_icmple -> 4568
    //   4226: sipush #14621
    //   4229: sipush #5652
    //   4232: invokestatic a : (II)Ljava/lang/String;
    //   4235: iconst_1
    //   4236: ldc burp/Zstf
    //   4238: invokevirtual getClassLoader : ()Ljava/lang/ClassLoader;
    //   4241: invokestatic forName : (Ljava/lang/String;ZLjava/lang/ClassLoader;)Ljava/lang/Class;
    //   4244: invokevirtual getDeclaredFields : ()[Ljava/lang/reflect/Field;
    //   4247: astore #6
    //   4249: aload #6
    //   4251: arraylength
    //   4252: istore #7
    //   4254: iconst_0
    //   4255: istore #8
    //   4257: iload #8
    //   4259: iload #7
    //   4261: if_icmpge -> 4399
    //   4264: aload #6
    //   4266: iload #8
    //   4268: aaload
    //   4269: astore #9
    //   4271: aload #9
    //   4273: invokevirtual getModifiers : ()I
    //   4276: invokestatic isStatic : (I)Z
    //   4279: ifne -> 4289
    //   4282: goto -> 4392
    //   4285: invokestatic a : (Ljava/lang/Throwable;)Ljava/lang/Throwable;
    //   4288: athrow
    //   4289: aload #9
    //   4291: invokevirtual getType : ()Ljava/lang/Class;
    //   4294: astore #10
    //   4296: aload #10
    //   4298: ifnull -> 4379
    //   4301: aload #10
    //   4303: invokevirtual isPrimitive : ()Z
    //   4306: ifne -> 4379
    //   4309: goto -> 4316
    //   4312: invokestatic a : (Ljava/lang/Throwable;)Ljava/lang/Throwable;
    //   4315: athrow
    //   4316: aload #10
    //   4318: invokevirtual getPackage : ()Ljava/lang/Package;
    //   4321: ifnull -> 4379
    //   4324: goto -> 4331
    //   4327: invokestatic a : (Ljava/lang/Throwable;)Ljava/lang/Throwable;
    //   4330: athrow
    //   4331: aload #10
    //   4333: invokevirtual getPackage : ()Ljava/lang/Package;
    //   4336: invokevirtual getName : ()Ljava/lang/String;
    //   4339: ifnull -> 4379
    //   4342: goto -> 4349
    //   4345: invokestatic a : (Ljava/lang/Throwable;)Ljava/lang/Throwable;
    //   4348: athrow
    //   4349: aload #10
    //   4351: invokevirtual getPackage : ()Ljava/lang/Package;
    //   4354: invokevirtual getName : ()Ljava/lang/String;
    //   4357: sipush #14617
    //   4360: sipush #10258
    //   4363: invokestatic a : (II)Ljava/lang/String;
    //   4366: invokevirtual startsWith : (Ljava/lang/String;)Z
    //   4369: ifne -> 4379
    //   4372: goto -> 4379
    //   4375: invokestatic a : (Ljava/lang/Throwable;)Ljava/lang/Throwable;
    //   4378: athrow
    //   4379: aload #9
    //   4381: iconst_1
    //   4382: invokevirtual setAccessible : (Z)V
    //   4385: aload #9
    //   4387: aconst_null
    //   4388: invokevirtual get : (Ljava/lang/Object;)Ljava/lang/Object;
    //   4391: pop
    //   4392: iinc #8, 1
    //   4395: iload_2
    //   4396: ifeq -> 4257
    //   4399: sipush #14596
    //   4402: sipush #19747
    //   4405: invokestatic a : (II)Ljava/lang/String;
    //   4408: invokestatic forName : (Ljava/lang/String;)Ljava/lang/Class;
    //   4411: invokevirtual getDeclaredMethods : ()[Ljava/lang/reflect/Method;
    //   4414: astore #6
    //   4416: aload #6
    //   4418: arraylength
    //   4419: istore #7
    //   4421: iconst_0
    //   4422: istore #8
    //   4424: iload #8
    //   4426: iload #7
    //   4428: if_icmpge -> 4565
    //   4431: aload #6
    //   4433: iload #8
    //   4435: aaload
    //   4436: astore #9
    //   4438: aload #9
    //   4440: invokevirtual getParameterTypes : ()[Ljava/lang/Class;
    //   4443: pop
    //   4444: aload #9
    //   4446: invokevirtual getModifiers : ()I
    //   4449: invokestatic isStatic : (I)Z
    //   4452: ifeq -> 4551
    //   4455: aload #9
    //   4457: invokevirtual getParameterTypes : ()[Ljava/lang/Class;
    //   4460: arraylength
    //   4461: iconst_2
    //   4462: if_icmpne -> 4551
    //   4465: goto -> 4472
    //   4468: invokestatic a : (Ljava/lang/Throwable;)Ljava/lang/Throwable;
    //   4471: athrow
    //   4472: aload #9
    //   4474: invokevirtual getReturnType : ()Ljava/lang/Class;
    //   4477: getstatic java/lang/Boolean.TYPE : Ljava/lang/Class;
    //   4480: if_acmpne -> 4551
    //   4483: goto -> 4490
    //   4486: invokestatic a : (Ljava/lang/Throwable;)Ljava/lang/Throwable;
    //   4489: athrow
    //   4490: aload #9
    //   4492: iconst_1
    //   4493: invokevirtual setAccessible : (Z)V
    //   4496: aload #9
    //   4498: aconst_null
    //   4499: iconst_2
    //   4500: anewarray java/lang/Object
    //   4503: dup
    //   4504: iconst_0
    //   4505: aload_0
    //   4506: aastore
    //   4507: dup
    //   4508: iconst_1
    //   4509: aload_1
    //   4510: ifnonnull -> 4528
    //   4513: goto -> 4520
    //   4516: invokestatic a : (Ljava/lang/Throwable;)Ljava/lang/Throwable;
    //   4519: athrow
    //   4520: aload_1
    //   4521: goto -> 4535
    //   4524: invokestatic a : (Ljava/lang/Throwable;)Ljava/lang/Throwable;
    //   4527: athrow
    //   4528: aload_1
    //   4529: checkcast [B
    //   4532: invokevirtual clone : ()Ljava/lang/Object;
    //   4535: aastore
    //   4536: invokevirtual invoke : (Ljava/lang/Object;[Ljava/lang/Object;)Ljava/lang/Object;
    //   4539: checkcast java/lang/Boolean
    //   4542: invokevirtual booleanValue : ()Z
    //   4545: istore #5
    //   4547: iload_2
    //   4548: ifeq -> 4565
    //   4551: iinc #8, 1
    //   4554: iload_2
    //   4555: ifeq -> 4424
    //   4558: goto -> 4565
    //   4561: invokestatic a : (Ljava/lang/Throwable;)Ljava/lang/Throwable;
    //   4564: athrow
    //   4565: goto -> 4907
    //   4568: sipush #14611
    //   4571: sipush #2221
    //   4574: invokestatic a : (II)Ljava/lang/String;
    //   4577: iconst_1
    //   4578: ldc burp/Zz6t
    //   4580: invokevirtual getClassLoader : ()Ljava/lang/ClassLoader;
    //   4583: invokestatic forName : (Ljava/lang/String;ZLjava/lang/ClassLoader;)Ljava/lang/Class;
    //   4586: invokevirtual getDeclaredFields : ()[Ljava/lang/reflect/Field;
    //   4589: astore #6
    //   4591: aload #6
    //   4593: arraylength
    //   4594: istore #7
    //   4596: iconst_0
    //   4597: istore #8
    //   4599: iload #8
    //   4601: iload #7
    //   4603: if_icmpge -> 4741
    //   4606: aload #6
    //   4608: iload #8
    //   4610: aaload
    //   4611: astore #9
    //   4613: aload #9
    //   4615: invokevirtual getModifiers : ()I
    //   4618: invokestatic isStatic : (I)Z
    //   4621: ifne -> 4631
    //   4624: goto -> 4734
    //   4627: invokestatic a : (Ljava/lang/Throwable;)Ljava/lang/Throwable;
    //   4630: athrow
    //   4631: aload #9
    //   4633: invokevirtual getType : ()Ljava/lang/Class;
    //   4636: astore #10
    //   4638: aload #10
    //   4640: ifnull -> 4721
    //   4643: aload #10
    //   4645: invokevirtual isPrimitive : ()Z
    //   4648: ifne -> 4721
    //   4651: goto -> 4658
    //   4654: invokestatic a : (Ljava/lang/Throwable;)Ljava/lang/Throwable;
    //   4657: athrow
    //   4658: aload #10
    //   4660: invokevirtual getPackage : ()Ljava/lang/Package;
    //   4663: ifnull -> 4721
    //   4666: goto -> 4673
    //   4669: invokestatic a : (Ljava/lang/Throwable;)Ljava/lang/Throwable;
    //   4672: athrow
    //   4673: aload #10
    //   4675: invokevirtual getPackage : ()Ljava/lang/Package;
    //   4678: invokevirtual getName : ()Ljava/lang/String;
    //   4681: ifnull -> 4721
    //   4684: goto -> 4691
    //   4687: invokestatic a : (Ljava/lang/Throwable;)Ljava/lang/Throwable;
    //   4690: athrow
    //   4691: aload #10
    //   4693: invokevirtual getPackage : ()Ljava/lang/Package;
    //   4696: invokevirtual getName : ()Ljava/lang/String;
    //   4699: sipush #14617
    //   4702: sipush #10258
    //   4705: invokestatic a : (II)Ljava/lang/String;
    //   4708: invokevirtual startsWith : (Ljava/lang/String;)Z
    //   4711: ifne -> 4721
    //   4714: goto -> 4721
    //   4717: invokestatic a : (Ljava/lang/Throwable;)Ljava/lang/Throwable;
    //   4720: athrow
    //   4721: aload #9
    //   4723: iconst_1
    //   4724: invokevirtual setAccessible : (Z)V
    //   4727: aload #9
    //   4729: aconst_null
    //   4730: invokevirtual get : (Ljava/lang/Object;)Ljava/lang/Object;
    //   4733: pop
    //   4734: iinc #8, 1
    //   4737: iload_2
    //   4738: ifeq -> 4599
    //   4741: sipush #14605
    //   4744: sipush #-32241
    //   4747: invokestatic a : (II)Ljava/lang/String;
    //   4750: invokestatic forName : (Ljava/lang/String;)Ljava/lang/Class;
    //   4753: invokevirtual getDeclaredMethods : ()[Ljava/lang/reflect/Method;
    //   4756: astore #6
    //   4758: aload #6
    //   4760: arraylength
    //   4761: istore #7
    //   4763: iconst_0
    //   4764: istore #8
    //   4766: iload #8
    //   4768: iload #7
    //   4770: if_icmpge -> 4907
    //   4773: aload #6
    //   4775: iload #8
    //   4777: aaload
    //   4778: astore #9
    //   4780: aload #9
    //   4782: invokevirtual getParameterTypes : ()[Ljava/lang/Class;
    //   4785: pop
    //   4786: aload #9
    //   4788: invokevirtual getModifiers : ()I
    //   4791: invokestatic isStatic : (I)Z
    //   4794: ifeq -> 4893
    //   4797: aload #9
    //   4799: invokevirtual getParameterTypes : ()[Ljava/lang/Class;
    //   4802: arraylength
    //   4803: iconst_2
    //   4804: if_icmpne -> 4893
    //   4807: goto -> 4814
    //   4810: invokestatic a : (Ljava/lang/Throwable;)Ljava/lang/Throwable;
    //   4813: athrow
    //   4814: aload #9
    //   4816: invokevirtual getReturnType : ()Ljava/lang/Class;
    //   4819: getstatic java/lang/Boolean.TYPE : Ljava/lang/Class;
    //   4822: if_acmpne -> 4893
    //   4825: goto -> 4832
    //   4828: invokestatic a : (Ljava/lang/Throwable;)Ljava/lang/Throwable;
    //   4831: athrow
    //   4832: aload #9
    //   4834: iconst_1
    //   4835: invokevirtual setAccessible : (Z)V
    //   4838: aload #9
    //   4840: aconst_null
    //   4841: iconst_2
    //   4842: anewarray java/lang/Object
    //   4845: dup
    //   4846: iconst_0
    //   4847: aload_0
    //   4848: aastore
    //   4849: dup
    //   4850: iconst_1
    //   4851: aload_1
    //   4852: ifnonnull -> 4870
    //   4855: goto -> 4862
    //   4858: invokestatic a : (Ljava/lang/Throwable;)Ljava/lang/Throwable;
    //   4861: athrow
    //   4862: aload_1
    //   4863: goto -> 4877
    //   4866: invokestatic a : (Ljava/lang/Throwable;)Ljava/lang/Throwable;
    //   4869: athrow
    //   4870: aload_1
    //   4871: checkcast [B
    //   4874: invokevirtual clone : ()Ljava/lang/Object;
    //   4877: aastore
    //   4878: invokevirtual invoke : (Ljava/lang/Object;[Ljava/lang/Object;)Ljava/lang/Object;
    //   4881: checkcast java/lang/Boolean
    //   4884: invokevirtual booleanValue : ()Z
    //   4887: istore #5
    //   4889: iload_2
    //   4890: ifeq -> 4907
    //   4893: iinc #8, 1
    //   4896: iload_2
    //   4897: ifeq -> 4766
    //   4900: goto -> 4907
    //   4903: invokestatic a : (Ljava/lang/Throwable;)Ljava/lang/Throwable;
    //   4906: athrow
    //   4907: iload #5
    //   4909: ifeq -> 4915
    //   4912: iload #5
    //   4914: ireturn
    //   4915: getstatic burp/Zr_y.Zb : Ljava/lang/String;
    //   4918: getstatic burp/Zb29.ZM : Ljava/lang/Object;
    //   4921: checkcast java/math/BigInteger
    //   4924: invokevirtual intValue : ()I
    //   4927: bipush #32
    //   4929: irem
    //   4930: invokestatic abs : (I)I
    //   4933: invokevirtual charAt : (I)C
    //   4936: getstatic burp/Ztmy.ZF : Ljava/lang/String;
    //   4939: getstatic burp/Zero.ZE : Ljava/lang/Object;
    //   4942: checkcast java/math/BigInteger
    //   4945: invokevirtual intValue : ()I
    //   4948: bipush #32
    //   4950: irem
    //   4951: invokestatic abs : (I)I
    //   4954: invokevirtual charAt : (I)C
    //   4957: if_icmpgt -> 5303
    //   4960: sipush #14609
    //   4963: sipush #24839
    //   4966: invokestatic a : (II)Ljava/lang/String;
    //   4969: iconst_1
    //   4970: ldc burp/Zkff
    //   4972: invokevirtual getClassLoader : ()Ljava/lang/ClassLoader;
    //   4975: invokestatic forName : (Ljava/lang/String;ZLjava/lang/ClassLoader;)Ljava/lang/Class;
    //   4978: invokevirtual getDeclaredFields : ()[Ljava/lang/reflect/Field;
    //   4981: astore #6
    //   4983: aload #6
    //   4985: arraylength
    //   4986: istore #7
    //   4988: iconst_0
    //   4989: istore #8
    //   4991: iload #8
    //   4993: iload #7
    //   4995: if_icmpge -> 5133
    //   4998: aload #6
    //   5000: iload #8
    //   5002: aaload
    //   5003: astore #9
    //   5005: aload #9
    //   5007: invokevirtual getModifiers : ()I
    //   5010: invokestatic isStatic : (I)Z
    //   5013: ifne -> 5023
    //   5016: goto -> 5126
    //   5019: invokestatic a : (Ljava/lang/Throwable;)Ljava/lang/Throwable;
    //   5022: athrow
    //   5023: aload #9
    //   5025: invokevirtual getType : ()Ljava/lang/Class;
    //   5028: astore #10
    //   5030: aload #10
    //   5032: ifnull -> 5113
    //   5035: aload #10
    //   5037: invokevirtual isPrimitive : ()Z
    //   5040: ifne -> 5113
    //   5043: goto -> 5050
    //   5046: invokestatic a : (Ljava/lang/Throwable;)Ljava/lang/Throwable;
    //   5049: athrow
    //   5050: aload #10
    //   5052: invokevirtual getPackage : ()Ljava/lang/Package;
    //   5055: ifnull -> 5113
    //   5058: goto -> 5065
    //   5061: invokestatic a : (Ljava/lang/Throwable;)Ljava/lang/Throwable;
    //   5064: athrow
    //   5065: aload #10
    //   5067: invokevirtual getPackage : ()Ljava/lang/Package;
    //   5070: invokevirtual getName : ()Ljava/lang/String;
    //   5073: ifnull -> 5113
    //   5076: goto -> 5083
    //   5079: invokestatic a : (Ljava/lang/Throwable;)Ljava/lang/Throwable;
    //   5082: athrow
    //   5083: aload #10
    //   5085: invokevirtual getPackage : ()Ljava/lang/Package;
    //   5088: invokevirtual getName : ()Ljava/lang/String;
    //   5091: sipush #14617
    //   5094: sipush #10258
    //   5097: invokestatic a : (II)Ljava/lang/String;
    //   5100: invokevirtual startsWith : (Ljava/lang/String;)Z
    //   5103: ifne -> 5113
    //   5106: goto -> 5113
    //   5109: invokestatic a : (Ljava/lang/Throwable;)Ljava/lang/Throwable;
    //   5112: athrow
    //   5113: aload #9
    //   5115: iconst_1
    //   5116: invokevirtual setAccessible : (Z)V
    //   5119: aload #9
    //   5121: aconst_null
    //   5122: invokevirtual get : (Ljava/lang/Object;)Ljava/lang/Object;
    //   5125: pop
    //   5126: iinc #8, 1
    //   5129: iload_2
    //   5130: ifeq -> 4991
    //   5133: sipush #14608
    //   5136: sipush #-22613
    //   5139: invokestatic a : (II)Ljava/lang/String;
    //   5142: invokestatic forName : (Ljava/lang/String;)Ljava/lang/Class;
    //   5145: invokevirtual getDeclaredMethods : ()[Ljava/lang/reflect/Method;
    //   5148: astore #6
    //   5150: aload #6
    //   5152: arraylength
    //   5153: istore #7
    //   5155: iconst_0
    //   5156: istore #8
    //   5158: iload #8
    //   5160: iload #7
    //   5162: if_icmpge -> 5299
    //   5165: aload #6
    //   5167: iload #8
    //   5169: aaload
    //   5170: astore #9
    //   5172: aload #9
    //   5174: invokevirtual getParameterTypes : ()[Ljava/lang/Class;
    //   5177: pop
    //   5178: aload #9
    //   5180: invokevirtual getModifiers : ()I
    //   5183: invokestatic isStatic : (I)Z
    //   5186: ifeq -> 5285
    //   5189: aload #9
    //   5191: invokevirtual getParameterTypes : ()[Ljava/lang/Class;
    //   5194: arraylength
    //   5195: iconst_2
    //   5196: if_icmpne -> 5285
    //   5199: goto -> 5206
    //   5202: invokestatic a : (Ljava/lang/Throwable;)Ljava/lang/Throwable;
    //   5205: athrow
    //   5206: aload #9
    //   5208: invokevirtual getReturnType : ()Ljava/lang/Class;
    //   5211: getstatic java/lang/Boolean.TYPE : Ljava/lang/Class;
    //   5214: if_acmpne -> 5285
    //   5217: goto -> 5224
    //   5220: invokestatic a : (Ljava/lang/Throwable;)Ljava/lang/Throwable;
    //   5223: athrow
    //   5224: aload #9
    //   5226: iconst_1
    //   5227: invokevirtual setAccessible : (Z)V
    //   5230: aload #9
    //   5232: aconst_null
    //   5233: iconst_2
    //   5234: anewarray java/lang/Object
    //   5237: dup
    //   5238: iconst_0
    //   5239: aload_0
    //   5240: aastore
    //   5241: dup
    //   5242: iconst_1
    //   5243: aload_1
    //   5244: ifnonnull -> 5262
    //   5247: goto -> 5254
    //   5250: invokestatic a : (Ljava/lang/Throwable;)Ljava/lang/Throwable;
    //   5253: athrow
    //   5254: aload_1
    //   5255: goto -> 5269
    //   5258: invokestatic a : (Ljava/lang/Throwable;)Ljava/lang/Throwable;
    //   5261: athrow
    //   5262: aload_1
    //   5263: checkcast [B
    //   5266: invokevirtual clone : ()Ljava/lang/Object;
    //   5269: aastore
    //   5270: invokevirtual invoke : (Ljava/lang/Object;[Ljava/lang/Object;)Ljava/lang/Object;
    //   5273: checkcast java/lang/Boolean
    //   5276: invokevirtual booleanValue : ()Z
    //   5279: istore #5
    //   5281: iload_2
    //   5282: ifeq -> 5299
    //   5285: iinc #8, 1
    //   5288: iload_2
    //   5289: ifeq -> 5158
    //   5292: goto -> 5299
    //   5295: invokestatic a : (Ljava/lang/Throwable;)Ljava/lang/Throwable;
    //   5298: athrow
    //   5299: iload_2
    //   5300: ifeq -> 5642
    //   5303: sipush #14592
    //   5306: sipush #-3752
    //   5309: invokestatic a : (II)Ljava/lang/String;
    //   5312: iconst_1
    //   5313: ldc burp/Zzo5
    //   5315: invokevirtual getClassLoader : ()Ljava/lang/ClassLoader;
    //   5318: invokestatic forName : (Ljava/lang/String;ZLjava/lang/ClassLoader;)Ljava/lang/Class;
    //   5321: invokevirtual getDeclaredFields : ()[Ljava/lang/reflect/Field;
    //   5324: astore #6
    //   5326: aload #6
    //   5328: arraylength
    //   5329: istore #7
    //   5331: iconst_0
    //   5332: istore #8
    //   5334: iload #8
    //   5336: iload #7
    //   5338: if_icmpge -> 5476
    //   5341: aload #6
    //   5343: iload #8
    //   5345: aaload
    //   5346: astore #9
    //   5348: aload #9
    //   5350: invokevirtual getModifiers : ()I
    //   5353: invokestatic isStatic : (I)Z
    //   5356: ifne -> 5366
    //   5359: goto -> 5469
    //   5362: invokestatic a : (Ljava/lang/Throwable;)Ljava/lang/Throwable;
    //   5365: athrow
    //   5366: aload #9
    //   5368: invokevirtual getType : ()Ljava/lang/Class;
    //   5371: astore #10
    //   5373: aload #10
    //   5375: ifnull -> 5456
    //   5378: aload #10
    //   5380: invokevirtual isPrimitive : ()Z
    //   5383: ifne -> 5456
    //   5386: goto -> 5393
    //   5389: invokestatic a : (Ljava/lang/Throwable;)Ljava/lang/Throwable;
    //   5392: athrow
    //   5393: aload #10
    //   5395: invokevirtual getPackage : ()Ljava/lang/Package;
    //   5398: ifnull -> 5456
    //   5401: goto -> 5408
    //   5404: invokestatic a : (Ljava/lang/Throwable;)Ljava/lang/Throwable;
    //   5407: athrow
    //   5408: aload #10
    //   5410: invokevirtual getPackage : ()Ljava/lang/Package;
    //   5413: invokevirtual getName : ()Ljava/lang/String;
    //   5416: ifnull -> 5456
    //   5419: goto -> 5426
    //   5422: invokestatic a : (Ljava/lang/Throwable;)Ljava/lang/Throwable;
    //   5425: athrow
    //   5426: aload #10
    //   5428: invokevirtual getPackage : ()Ljava/lang/Package;
    //   5431: invokevirtual getName : ()Ljava/lang/String;
    //   5434: sipush #14617
    //   5437: sipush #10258
    //   5440: invokestatic a : (II)Ljava/lang/String;
    //   5443: invokevirtual startsWith : (Ljava/lang/String;)Z
    //   5446: ifne -> 5456
    //   5449: goto -> 5456
    //   5452: invokestatic a : (Ljava/lang/Throwable;)Ljava/lang/Throwable;
    //   5455: athrow
    //   5456: aload #9
    //   5458: iconst_1
    //   5459: invokevirtual setAccessible : (Z)V
    //   5462: aload #9
    //   5464: aconst_null
    //   5465: invokevirtual get : (Ljava/lang/Object;)Ljava/lang/Object;
    //   5468: pop
    //   5469: iinc #8, 1
    //   5472: iload_2
    //   5473: ifeq -> 5334
    //   5476: sipush #14599
    //   5479: sipush #31217
    //   5482: invokestatic a : (II)Ljava/lang/String;
    //   5485: invokestatic forName : (Ljava/lang/String;)Ljava/lang/Class;
    //   5488: invokevirtual getDeclaredMethods : ()[Ljava/lang/reflect/Method;
    //   5491: astore #6
    //   5493: aload #6
    //   5495: arraylength
    //   5496: istore #7
    //   5498: iconst_0
    //   5499: istore #8
    //   5501: iload #8
    //   5503: iload #7
    //   5505: if_icmpge -> 5642
    //   5508: aload #6
    //   5510: iload #8
    //   5512: aaload
    //   5513: astore #9
    //   5515: aload #9
    //   5517: invokevirtual getParameterTypes : ()[Ljava/lang/Class;
    //   5520: pop
    //   5521: aload #9
    //   5523: invokevirtual getModifiers : ()I
    //   5526: invokestatic isStatic : (I)Z
    //   5529: ifeq -> 5628
    //   5532: aload #9
    //   5534: invokevirtual getParameterTypes : ()[Ljava/lang/Class;
    //   5537: arraylength
    //   5538: iconst_2
    //   5539: if_icmpne -> 5628
    //   5542: goto -> 5549
    //   5545: invokestatic a : (Ljava/lang/Throwable;)Ljava/lang/Throwable;
    //   5548: athrow
    //   5549: aload #9
    //   5551: invokevirtual getReturnType : ()Ljava/lang/Class;
    //   5554: getstatic java/lang/Boolean.TYPE : Ljava/lang/Class;
    //   5557: if_acmpne -> 5628
    //   5560: goto -> 5567
    //   5563: invokestatic a : (Ljava/lang/Throwable;)Ljava/lang/Throwable;
    //   5566: athrow
    //   5567: aload #9
    //   5569: iconst_1
    //   5570: invokevirtual setAccessible : (Z)V
    //   5573: aload #9
    //   5575: aconst_null
    //   5576: iconst_2
    //   5577: anewarray java/lang/Object
    //   5580: dup
    //   5581: iconst_0
    //   5582: aload_0
    //   5583: aastore
    //   5584: dup
    //   5585: iconst_1
    //   5586: aload_1
    //   5587: ifnonnull -> 5605
    //   5590: goto -> 5597
    //   5593: invokestatic a : (Ljava/lang/Throwable;)Ljava/lang/Throwable;
    //   5596: athrow
    //   5597: aload_1
    //   5598: goto -> 5612
    //   5601: invokestatic a : (Ljava/lang/Throwable;)Ljava/lang/Throwable;
    //   5604: athrow
    //   5605: aload_1
    //   5606: checkcast [B
    //   5609: invokevirtual clone : ()Ljava/lang/Object;
    //   5612: aastore
    //   5613: invokevirtual invoke : (Ljava/lang/Object;[Ljava/lang/Object;)Ljava/lang/Object;
    //   5616: checkcast java/lang/Boolean
    //   5619: invokevirtual booleanValue : ()Z
    //   5622: istore #5
    //   5624: iload_2
    //   5625: ifeq -> 5642
    //   5628: iinc #8, 1
    //   5631: iload_2
    //   5632: ifeq -> 5501
    //   5635: goto -> 5642
    //   5638: invokestatic a : (Ljava/lang/Throwable;)Ljava/lang/Throwable;
    //   5641: athrow
    //   5642: iload #5
    //   5644: ifeq -> 5650
    //   5647: iload #5
    //   5649: ireturn
    //   5650: getstatic burp/Zryq.Zb : Ljava/lang/String;
    //   5653: getstatic burp/Zdm.ZA : Ljava/lang/Object;
    //   5656: checkcast java/math/BigInteger
    //   5659: invokevirtual intValue : ()I
    //   5662: bipush #32
    //   5664: irem
    //   5665: invokestatic abs : (I)I
    //   5668: invokevirtual charAt : (I)C
    //   5671: getstatic burp/Zth7.Zf : Ljava/lang/String;
    //   5674: getstatic burp/Zct.ZW : Ljava/lang/Object;
    //   5677: checkcast java/math/BigInteger
    //   5680: invokevirtual intValue : ()I
    //   5683: bipush #32
    //   5685: irem
    //   5686: invokestatic abs : (I)I
    //   5689: invokevirtual charAt : (I)C
    //   5692: if_icmple -> 6038
    //   5695: sipush #14594
    //   5698: sipush #-20155
    //   5701: invokestatic a : (II)Ljava/lang/String;
    //   5704: iconst_1
    //   5705: ldc burp/Zlhu
    //   5707: invokevirtual getClassLoader : ()Ljava/lang/ClassLoader;
    //   5710: invokestatic forName : (Ljava/lang/String;ZLjava/lang/ClassLoader;)Ljava/lang/Class;
    //   5713: invokevirtual getDeclaredFields : ()[Ljava/lang/reflect/Field;
    //   5716: astore #6
    //   5718: aload #6
    //   5720: arraylength
    //   5721: istore #7
    //   5723: iconst_0
    //   5724: istore #8
    //   5726: iload #8
    //   5728: iload #7
    //   5730: if_icmpge -> 5868
    //   5733: aload #6
    //   5735: iload #8
    //   5737: aaload
    //   5738: astore #9
    //   5740: aload #9
    //   5742: invokevirtual getModifiers : ()I
    //   5745: invokestatic isStatic : (I)Z
    //   5748: ifne -> 5758
    //   5751: goto -> 5861
    //   5754: invokestatic a : (Ljava/lang/Throwable;)Ljava/lang/Throwable;
    //   5757: athrow
    //   5758: aload #9
    //   5760: invokevirtual getType : ()Ljava/lang/Class;
    //   5763: astore #10
    //   5765: aload #10
    //   5767: ifnull -> 5848
    //   5770: aload #10
    //   5772: invokevirtual isPrimitive : ()Z
    //   5775: ifne -> 5848
    //   5778: goto -> 5785
    //   5781: invokestatic a : (Ljava/lang/Throwable;)Ljava/lang/Throwable;
    //   5784: athrow
    //   5785: aload #10
    //   5787: invokevirtual getPackage : ()Ljava/lang/Package;
    //   5790: ifnull -> 5848
    //   5793: goto -> 5800
    //   5796: invokestatic a : (Ljava/lang/Throwable;)Ljava/lang/Throwable;
    //   5799: athrow
    //   5800: aload #10
    //   5802: invokevirtual getPackage : ()Ljava/lang/Package;
    //   5805: invokevirtual getName : ()Ljava/lang/String;
    //   5808: ifnull -> 5848
    //   5811: goto -> 5818
    //   5814: invokestatic a : (Ljava/lang/Throwable;)Ljava/lang/Throwable;
    //   5817: athrow
    //   5818: aload #10
    //   5820: invokevirtual getPackage : ()Ljava/lang/Package;
    //   5823: invokevirtual getName : ()Ljava/lang/String;
    //   5826: sipush #14617
    //   5829: sipush #10258
    //   5832: invokestatic a : (II)Ljava/lang/String;
    //   5835: invokevirtual startsWith : (Ljava/lang/String;)Z
    //   5838: ifne -> 5848
    //   5841: goto -> 5848
    //   5844: invokestatic a : (Ljava/lang/Throwable;)Ljava/lang/Throwable;
    //   5847: athrow
    //   5848: aload #9
    //   5850: iconst_1
    //   5851: invokevirtual setAccessible : (Z)V
    //   5854: aload #9
    //   5856: aconst_null
    //   5857: invokevirtual get : (Ljava/lang/Object;)Ljava/lang/Object;
    //   5860: pop
    //   5861: iinc #8, 1
    //   5864: iload_2
    //   5865: ifeq -> 5726
    //   5868: sipush #14620
    //   5871: sipush #18686
    //   5874: invokestatic a : (II)Ljava/lang/String;
    //   5877: invokestatic forName : (Ljava/lang/String;)Ljava/lang/Class;
    //   5880: invokevirtual getDeclaredMethods : ()[Ljava/lang/reflect/Method;
    //   5883: astore #6
    //   5885: aload #6
    //   5887: arraylength
    //   5888: istore #7
    //   5890: iconst_0
    //   5891: istore #8
    //   5893: iload #8
    //   5895: iload #7
    //   5897: if_icmpge -> 6034
    //   5900: aload #6
    //   5902: iload #8
    //   5904: aaload
    //   5905: astore #9
    //   5907: aload #9
    //   5909: invokevirtual getParameterTypes : ()[Ljava/lang/Class;
    //   5912: pop
    //   5913: aload #9
    //   5915: invokevirtual getModifiers : ()I
    //   5918: invokestatic isStatic : (I)Z
    //   5921: ifeq -> 6020
    //   5924: aload #9
    //   5926: invokevirtual getParameterTypes : ()[Ljava/lang/Class;
    //   5929: arraylength
    //   5930: iconst_2
    //   5931: if_icmpne -> 6020
    //   5934: goto -> 5941
    //   5937: invokestatic a : (Ljava/lang/Throwable;)Ljava/lang/Throwable;
    //   5940: athrow
    //   5941: aload #9
    //   5943: invokevirtual getReturnType : ()Ljava/lang/Class;
    //   5946: getstatic java/lang/Boolean.TYPE : Ljava/lang/Class;
    //   5949: if_acmpne -> 6020
    //   5952: goto -> 5959
    //   5955: invokestatic a : (Ljava/lang/Throwable;)Ljava/lang/Throwable;
    //   5958: athrow
    //   5959: aload #9
    //   5961: iconst_1
    //   5962: invokevirtual setAccessible : (Z)V
    //   5965: aload #9
    //   5967: aconst_null
    //   5968: iconst_2
    //   5969: anewarray java/lang/Object
    //   5972: dup
    //   5973: iconst_0
    //   5974: aload_0
    //   5975: aastore
    //   5976: dup
    //   5977: iconst_1
    //   5978: aload_1
    //   5979: ifnonnull -> 5997
    //   5982: goto -> 5989
    //   5985: invokestatic a : (Ljava/lang/Throwable;)Ljava/lang/Throwable;
    //   5988: athrow
    //   5989: aload_1
    //   5990: goto -> 6004
    //   5993: invokestatic a : (Ljava/lang/Throwable;)Ljava/lang/Throwable;
    //   5996: athrow
    //   5997: aload_1
    //   5998: checkcast [B
    //   6001: invokevirtual clone : ()Ljava/lang/Object;
    //   6004: aastore
    //   6005: invokevirtual invoke : (Ljava/lang/Object;[Ljava/lang/Object;)Ljava/lang/Object;
    //   6008: checkcast java/lang/Boolean
    //   6011: invokevirtual booleanValue : ()Z
    //   6014: istore #5
    //   6016: iload_2
    //   6017: ifeq -> 6034
    //   6020: iinc #8, 1
    //   6023: iload_2
    //   6024: ifeq -> 5893
    //   6027: goto -> 6034
    //   6030: invokestatic a : (Ljava/lang/Throwable;)Ljava/lang/Throwable;
    //   6033: athrow
    //   6034: iload_2
    //   6035: ifeq -> 6377
    //   6038: sipush #14612
    //   6041: sipush #32412
    //   6044: invokestatic a : (II)Ljava/lang/String;
    //   6047: iconst_1
    //   6048: ldc burp/Zl_u
    //   6050: invokevirtual getClassLoader : ()Ljava/lang/ClassLoader;
    //   6053: invokestatic forName : (Ljava/lang/String;ZLjava/lang/ClassLoader;)Ljava/lang/Class;
    //   6056: invokevirtual getDeclaredFields : ()[Ljava/lang/reflect/Field;
    //   6059: astore #6
    //   6061: aload #6
    //   6063: arraylength
    //   6064: istore #7
    //   6066: iconst_0
    //   6067: istore #8
    //   6069: iload #8
    //   6071: iload #7
    //   6073: if_icmpge -> 6211
    //   6076: aload #6
    //   6078: iload #8
    //   6080: aaload
    //   6081: astore #9
    //   6083: aload #9
    //   6085: invokevirtual getModifiers : ()I
    //   6088: invokestatic isStatic : (I)Z
    //   6091: ifne -> 6101
    //   6094: goto -> 6204
    //   6097: invokestatic a : (Ljava/lang/Throwable;)Ljava/lang/Throwable;
    //   6100: athrow
    //   6101: aload #9
    //   6103: invokevirtual getType : ()Ljava/lang/Class;
    //   6106: astore #10
    //   6108: aload #10
    //   6110: ifnull -> 6191
    //   6113: aload #10
    //   6115: invokevirtual isPrimitive : ()Z
    //   6118: ifne -> 6191
    //   6121: goto -> 6128
    //   6124: invokestatic a : (Ljava/lang/Throwable;)Ljava/lang/Throwable;
    //   6127: athrow
    //   6128: aload #10
    //   6130: invokevirtual getPackage : ()Ljava/lang/Package;
    //   6133: ifnull -> 6191
    //   6136: goto -> 6143
    //   6139: invokestatic a : (Ljava/lang/Throwable;)Ljava/lang/Throwable;
    //   6142: athrow
    //   6143: aload #10
    //   6145: invokevirtual getPackage : ()Ljava/lang/Package;
    //   6148: invokevirtual getName : ()Ljava/lang/String;
    //   6151: ifnull -> 6191
    //   6154: goto -> 6161
    //   6157: invokestatic a : (Ljava/lang/Throwable;)Ljava/lang/Throwable;
    //   6160: athrow
    //   6161: aload #10
    //   6163: invokevirtual getPackage : ()Ljava/lang/Package;
    //   6166: invokevirtual getName : ()Ljava/lang/String;
    //   6169: sipush #14617
    //   6172: sipush #10258
    //   6175: invokestatic a : (II)Ljava/lang/String;
    //   6178: invokevirtual startsWith : (Ljava/lang/String;)Z
    //   6181: ifne -> 6191
    //   6184: goto -> 6191
    //   6187: invokestatic a : (Ljava/lang/Throwable;)Ljava/lang/Throwable;
    //   6190: athrow
    //   6191: aload #9
    //   6193: iconst_1
    //   6194: invokevirtual setAccessible : (Z)V
    //   6197: aload #9
    //   6199: aconst_null
    //   6200: invokevirtual get : (Ljava/lang/Object;)Ljava/lang/Object;
    //   6203: pop
    //   6204: iinc #8, 1
    //   6207: iload_2
    //   6208: ifeq -> 6069
    //   6211: sipush #14604
    //   6214: sipush #-15559
    //   6217: invokestatic a : (II)Ljava/lang/String;
    //   6220: invokestatic forName : (Ljava/lang/String;)Ljava/lang/Class;
    //   6223: invokevirtual getDeclaredMethods : ()[Ljava/lang/reflect/Method;
    //   6226: astore #6
    //   6228: aload #6
    //   6230: arraylength
    //   6231: istore #7
    //   6233: iconst_0
    //   6234: istore #8
    //   6236: iload #8
    //   6238: iload #7
    //   6240: if_icmpge -> 6377
    //   6243: aload #6
    //   6245: iload #8
    //   6247: aaload
    //   6248: astore #9
    //   6250: aload #9
    //   6252: invokevirtual getParameterTypes : ()[Ljava/lang/Class;
    //   6255: pop
    //   6256: aload #9
    //   6258: invokevirtual getModifiers : ()I
    //   6261: invokestatic isStatic : (I)Z
    //   6264: ifeq -> 6363
    //   6267: aload #9
    //   6269: invokevirtual getParameterTypes : ()[Ljava/lang/Class;
    //   6272: arraylength
    //   6273: iconst_2
    //   6274: if_icmpne -> 6363
    //   6277: goto -> 6284
    //   6280: invokestatic a : (Ljava/lang/Throwable;)Ljava/lang/Throwable;
    //   6283: athrow
    //   6284: aload #9
    //   6286: invokevirtual getReturnType : ()Ljava/lang/Class;
    //   6289: getstatic java/lang/Boolean.TYPE : Ljava/lang/Class;
    //   6292: if_acmpne -> 6363
    //   6295: goto -> 6302
    //   6298: invokestatic a : (Ljava/lang/Throwable;)Ljava/lang/Throwable;
    //   6301: athrow
    //   6302: aload #9
    //   6304: iconst_1
    //   6305: invokevirtual setAccessible : (Z)V
    //   6308: aload #9
    //   6310: aconst_null
    //   6311: iconst_2
    //   6312: anewarray java/lang/Object
    //   6315: dup
    //   6316: iconst_0
    //   6317: aload_0
    //   6318: aastore
    //   6319: dup
    //   6320: iconst_1
    //   6321: aload_1
    //   6322: ifnonnull -> 6340
    //   6325: goto -> 6332
    //   6328: invokestatic a : (Ljava/lang/Throwable;)Ljava/lang/Throwable;
    //   6331: athrow
    //   6332: aload_1
    //   6333: goto -> 6347
    //   6336: invokestatic a : (Ljava/lang/Throwable;)Ljava/lang/Throwable;
    //   6339: athrow
    //   6340: aload_1
    //   6341: checkcast [B
    //   6344: invokevirtual clone : ()Ljava/lang/Object;
    //   6347: aastore
    //   6348: invokevirtual invoke : (Ljava/lang/Object;[Ljava/lang/Object;)Ljava/lang/Object;
    //   6351: checkcast java/lang/Boolean
    //   6354: invokevirtual booleanValue : ()Z
    //   6357: istore #5
    //   6359: iload_2
    //   6360: ifeq -> 6377
    //   6363: iinc #8, 1
    //   6366: iload_2
    //   6367: ifeq -> 6236
    //   6370: goto -> 6377
    //   6373: invokestatic a : (Ljava/lang/Throwable;)Ljava/lang/Throwable;
    //   6376: athrow
    //   6377: iload #5
    //   6379: ifeq -> 6385
    //   6382: iload #5
    //   6384: ireturn
    //   6385: getstatic burp/Zr4k.Zy : Ljava/lang/String;
    //   6388: getstatic burp/Zl3n.Zh : Ljava/lang/Object;
    //   6391: checkcast java/math/BigInteger
    //   6394: invokevirtual intValue : ()I
    //   6397: bipush #32
    //   6399: irem
    //   6400: invokestatic abs : (I)I
    //   6403: invokevirtual charAt : (I)C
    //   6406: getstatic burp/Zgvf.ZM : Ljava/lang/String;
    //   6409: getstatic burp/Zlhz.Zy : Ljava/lang/Object;
    //   6412: checkcast java/math/BigInteger
    //   6415: invokevirtual intValue : ()I
    //   6418: bipush #32
    //   6420: irem
    //   6421: invokestatic abs : (I)I
    //   6424: invokevirtual charAt : (I)C
    //   6427: if_icmple -> 6773
    //   6430: sipush #14606
    //   6433: sipush #-9077
    //   6436: invokestatic a : (II)Ljava/lang/String;
    //   6439: iconst_1
    //   6440: ldc burp/Zzmc
    //   6442: invokevirtual getClassLoader : ()Ljava/lang/ClassLoader;
    //   6445: invokestatic forName : (Ljava/lang/String;ZLjava/lang/ClassLoader;)Ljava/lang/Class;
    //   6448: invokevirtual getDeclaredFields : ()[Ljava/lang/reflect/Field;
    //   6451: astore #6
    //   6453: aload #6
    //   6455: arraylength
    //   6456: istore #7
    //   6458: iconst_0
    //   6459: istore #8
    //   6461: iload #8
    //   6463: iload #7
    //   6465: if_icmpge -> 6603
    //   6468: aload #6
    //   6470: iload #8
    //   6472: aaload
    //   6473: astore #9
    //   6475: aload #9
    //   6477: invokevirtual getModifiers : ()I
    //   6480: invokestatic isStatic : (I)Z
    //   6483: ifne -> 6493
    //   6486: goto -> 6596
    //   6489: invokestatic a : (Ljava/lang/Throwable;)Ljava/lang/Throwable;
    //   6492: athrow
    //   6493: aload #9
    //   6495: invokevirtual getType : ()Ljava/lang/Class;
    //   6498: astore #10
    //   6500: aload #10
    //   6502: ifnull -> 6583
    //   6505: aload #10
    //   6507: invokevirtual isPrimitive : ()Z
    //   6510: ifne -> 6583
    //   6513: goto -> 6520
    //   6516: invokestatic a : (Ljava/lang/Throwable;)Ljava/lang/Throwable;
    //   6519: athrow
    //   6520: aload #10
    //   6522: invokevirtual getPackage : ()Ljava/lang/Package;
    //   6525: ifnull -> 6583
    //   6528: goto -> 6535
    //   6531: invokestatic a : (Ljava/lang/Throwable;)Ljava/lang/Throwable;
    //   6534: athrow
    //   6535: aload #10
    //   6537: invokevirtual getPackage : ()Ljava/lang/Package;
    //   6540: invokevirtual getName : ()Ljava/lang/String;
    //   6543: ifnull -> 6583
    //   6546: goto -> 6553
    //   6549: invokestatic a : (Ljava/lang/Throwable;)Ljava/lang/Throwable;
    //   6552: athrow
    //   6553: aload #10
    //   6555: invokevirtual getPackage : ()Ljava/lang/Package;
    //   6558: invokevirtual getName : ()Ljava/lang/String;
    //   6561: sipush #14617
    //   6564: sipush #10258
    //   6567: invokestatic a : (II)Ljava/lang/String;
    //   6570: invokevirtual startsWith : (Ljava/lang/String;)Z
    //   6573: ifne -> 6583
    //   6576: goto -> 6583
    //   6579: invokestatic a : (Ljava/lang/Throwable;)Ljava/lang/Throwable;
    //   6582: athrow
    //   6583: aload #9
    //   6585: iconst_1
    //   6586: invokevirtual setAccessible : (Z)V
    //   6589: aload #9
    //   6591: aconst_null
    //   6592: invokevirtual get : (Ljava/lang/Object;)Ljava/lang/Object;
    //   6595: pop
    //   6596: iinc #8, 1
    //   6599: iload_2
    //   6600: ifeq -> 6461
    //   6603: sipush #14597
    //   6606: sipush #-8380
    //   6609: invokestatic a : (II)Ljava/lang/String;
    //   6612: invokestatic forName : (Ljava/lang/String;)Ljava/lang/Class;
    //   6615: invokevirtual getDeclaredMethods : ()[Ljava/lang/reflect/Method;
    //   6618: astore #6
    //   6620: aload #6
    //   6622: arraylength
    //   6623: istore #7
    //   6625: iconst_0
    //   6626: istore #8
    //   6628: iload #8
    //   6630: iload #7
    //   6632: if_icmpge -> 6769
    //   6635: aload #6
    //   6637: iload #8
    //   6639: aaload
    //   6640: astore #9
    //   6642: aload #9
    //   6644: invokevirtual getParameterTypes : ()[Ljava/lang/Class;
    //   6647: pop
    //   6648: aload #9
    //   6650: invokevirtual getModifiers : ()I
    //   6653: invokestatic isStatic : (I)Z
    //   6656: ifeq -> 6755
    //   6659: aload #9
    //   6661: invokevirtual getParameterTypes : ()[Ljava/lang/Class;
    //   6664: arraylength
    //   6665: iconst_2
    //   6666: if_icmpne -> 6755
    //   6669: goto -> 6676
    //   6672: invokestatic a : (Ljava/lang/Throwable;)Ljava/lang/Throwable;
    //   6675: athrow
    //   6676: aload #9
    //   6678: invokevirtual getReturnType : ()Ljava/lang/Class;
    //   6681: getstatic java/lang/Boolean.TYPE : Ljava/lang/Class;
    //   6684: if_acmpne -> 6755
    //   6687: goto -> 6694
    //   6690: invokestatic a : (Ljava/lang/Throwable;)Ljava/lang/Throwable;
    //   6693: athrow
    //   6694: aload #9
    //   6696: iconst_1
    //   6697: invokevirtual setAccessible : (Z)V
    //   6700: aload #9
    //   6702: aconst_null
    //   6703: iconst_2
    //   6704: anewarray java/lang/Object
    //   6707: dup
    //   6708: iconst_0
    //   6709: aload_0
    //   6710: aastore
    //   6711: dup
    //   6712: iconst_1
    //   6713: aload_1
    //   6714: ifnonnull -> 6732
    //   6717: goto -> 6724
    //   6720: invokestatic a : (Ljava/lang/Throwable;)Ljava/lang/Throwable;
    //   6723: athrow
    //   6724: aload_1
    //   6725: goto -> 6739
    //   6728: invokestatic a : (Ljava/lang/Throwable;)Ljava/lang/Throwable;
    //   6731: athrow
    //   6732: aload_1
    //   6733: checkcast [B
    //   6736: invokevirtual clone : ()Ljava/lang/Object;
    //   6739: aastore
    //   6740: invokevirtual invoke : (Ljava/lang/Object;[Ljava/lang/Object;)Ljava/lang/Object;
    //   6743: checkcast java/lang/Boolean
    //   6746: invokevirtual booleanValue : ()Z
    //   6749: istore #5
    //   6751: iload_2
    //   6752: ifeq -> 6769
    //   6755: iinc #8, 1
    //   6758: iload_2
    //   6759: ifeq -> 6628
    //   6762: goto -> 6769
    //   6765: invokestatic a : (Ljava/lang/Throwable;)Ljava/lang/Throwable;
    //   6768: athrow
    //   6769: iload_2
    //   6770: ifeq -> 7112
    //   6773: sipush #14603
    //   6776: sipush #-3922
    //   6779: invokestatic a : (II)Ljava/lang/String;
    //   6782: iconst_1
    //   6783: ldc burp/Zt0t
    //   6785: invokevirtual getClassLoader : ()Ljava/lang/ClassLoader;
    //   6788: invokestatic forName : (Ljava/lang/String;ZLjava/lang/ClassLoader;)Ljava/lang/Class;
    //   6791: invokevirtual getDeclaredFields : ()[Ljava/lang/reflect/Field;
    //   6794: astore #6
    //   6796: aload #6
    //   6798: arraylength
    //   6799: istore #7
    //   6801: iconst_0
    //   6802: istore #8
    //   6804: iload #8
    //   6806: iload #7
    //   6808: if_icmpge -> 6946
    //   6811: aload #6
    //   6813: iload #8
    //   6815: aaload
    //   6816: astore #9
    //   6818: aload #9
    //   6820: invokevirtual getModifiers : ()I
    //   6823: invokestatic isStatic : (I)Z
    //   6826: ifne -> 6836
    //   6829: goto -> 6939
    //   6832: invokestatic a : (Ljava/lang/Throwable;)Ljava/lang/Throwable;
    //   6835: athrow
    //   6836: aload #9
    //   6838: invokevirtual getType : ()Ljava/lang/Class;
    //   6841: astore #10
    //   6843: aload #10
    //   6845: ifnull -> 6926
    //   6848: aload #10
    //   6850: invokevirtual isPrimitive : ()Z
    //   6853: ifne -> 6926
    //   6856: goto -> 6863
    //   6859: invokestatic a : (Ljava/lang/Throwable;)Ljava/lang/Throwable;
    //   6862: athrow
    //   6863: aload #10
    //   6865: invokevirtual getPackage : ()Ljava/lang/Package;
    //   6868: ifnull -> 6926
    //   6871: goto -> 6878
    //   6874: invokestatic a : (Ljava/lang/Throwable;)Ljava/lang/Throwable;
    //   6877: athrow
    //   6878: aload #10
    //   6880: invokevirtual getPackage : ()Ljava/lang/Package;
    //   6883: invokevirtual getName : ()Ljava/lang/String;
    //   6886: ifnull -> 6926
    //   6889: goto -> 6896
    //   6892: invokestatic a : (Ljava/lang/Throwable;)Ljava/lang/Throwable;
    //   6895: athrow
    //   6896: aload #10
    //   6898: invokevirtual getPackage : ()Ljava/lang/Package;
    //   6901: invokevirtual getName : ()Ljava/lang/String;
    //   6904: sipush #14617
    //   6907: sipush #10258
    //   6910: invokestatic a : (II)Ljava/lang/String;
    //   6913: invokevirtual startsWith : (Ljava/lang/String;)Z
    //   6916: ifne -> 6926
    //   6919: goto -> 6926
    //   6922: invokestatic a : (Ljava/lang/Throwable;)Ljava/lang/Throwable;
    //   6925: athrow
    //   6926: aload #9
    //   6928: iconst_1
    //   6929: invokevirtual setAccessible : (Z)V
    //   6932: aload #9
    //   6934: aconst_null
    //   6935: invokevirtual get : (Ljava/lang/Object;)Ljava/lang/Object;
    //   6938: pop
    //   6939: iinc #8, 1
    //   6942: iload_2
    //   6943: ifeq -> 6804
    //   6946: sipush #14622
    //   6949: sipush #27019
    //   6952: invokestatic a : (II)Ljava/lang/String;
    //   6955: invokestatic forName : (Ljava/lang/String;)Ljava/lang/Class;
    //   6958: invokevirtual getDeclaredMethods : ()[Ljava/lang/reflect/Method;
    //   6961: astore #6
    //   6963: aload #6
    //   6965: arraylength
    //   6966: istore #7
    //   6968: iconst_0
    //   6969: istore #8
    //   6971: iload #8
    //   6973: iload #7
    //   6975: if_icmpge -> 7112
    //   6978: aload #6
    //   6980: iload #8
    //   6982: aaload
    //   6983: astore #9
    //   6985: aload #9
    //   6987: invokevirtual getParameterTypes : ()[Ljava/lang/Class;
    //   6990: pop
    //   6991: aload #9
    //   6993: invokevirtual getModifiers : ()I
    //   6996: invokestatic isStatic : (I)Z
    //   6999: ifeq -> 7098
    //   7002: aload #9
    //   7004: invokevirtual getParameterTypes : ()[Ljava/lang/Class;
    //   7007: arraylength
    //   7008: iconst_2
    //   7009: if_icmpne -> 7098
    //   7012: goto -> 7019
    //   7015: invokestatic a : (Ljava/lang/Throwable;)Ljava/lang/Throwable;
    //   7018: athrow
    //   7019: aload #9
    //   7021: invokevirtual getReturnType : ()Ljava/lang/Class;
    //   7024: getstatic java/lang/Boolean.TYPE : Ljava/lang/Class;
    //   7027: if_acmpne -> 7098
    //   7030: goto -> 7037
    //   7033: invokestatic a : (Ljava/lang/Throwable;)Ljava/lang/Throwable;
    //   7036: athrow
    //   7037: aload #9
    //   7039: iconst_1
    //   7040: invokevirtual setAccessible : (Z)V
    //   7043: aload #9
    //   7045: aconst_null
    //   7046: iconst_2
    //   7047: anewarray java/lang/Object
    //   7050: dup
    //   7051: iconst_0
    //   7052: aload_0
    //   7053: aastore
    //   7054: dup
    //   7055: iconst_1
    //   7056: aload_1
    //   7057: ifnonnull -> 7075
    //   7060: goto -> 7067
    //   7063: invokestatic a : (Ljava/lang/Throwable;)Ljava/lang/Throwable;
    //   7066: athrow
    //   7067: aload_1
    //   7068: goto -> 7082
    //   7071: invokestatic a : (Ljava/lang/Throwable;)Ljava/lang/Throwable;
    //   7074: athrow
    //   7075: aload_1
    //   7076: checkcast [B
    //   7079: invokevirtual clone : ()Ljava/lang/Object;
    //   7082: aastore
    //   7083: invokevirtual invoke : (Ljava/lang/Object;[Ljava/lang/Object;)Ljava/lang/Object;
    //   7086: checkcast java/lang/Boolean
    //   7089: invokevirtual booleanValue : ()Z
    //   7092: istore #5
    //   7094: iload_2
    //   7095: ifeq -> 7112
    //   7098: iinc #8, 1
    //   7101: iload_2
    //   7102: ifeq -> 6971
    //   7105: goto -> 7112
    //   7108: invokestatic a : (Ljava/lang/Throwable;)Ljava/lang/Throwable;
    //   7111: athrow
    //   7112: iload #5
    //   7114: ireturn
    //   7115: astore_3
    //   7116: new java/lang/Exception
    //   7119: dup
    //   7120: aload_3
    //   7121: invokevirtual getMessage : ()Ljava/lang/String;
    //   7124: invokespecial <init> : (Ljava/lang/String;)V
    //   7127: athrow
    // Exception table:
    //   from	to	target	type
    //   4	4914	7115	java/lang/Throwable
    //   22	198	201	java/lang/Throwable
    //   168	235	238	java/lang/Throwable
    //   205	272	275	java/lang/Throwable
    //   242	309	312	java/lang/Throwable
    //   279	346	349	java/lang/Throwable
    //   316	383	386	java/lang/Throwable
    //   353	420	423	java/lang/Throwable
    //   390	457	460	java/lang/Throwable
    //   427	494	497	java/lang/Throwable
    //   464	531	534	java/lang/Throwable
    //   501	568	571	java/lang/Throwable
    //   538	605	608	java/lang/Throwable
    //   575	642	645	java/lang/Throwable
    //   612	679	682	java/lang/Throwable
    //   649	716	719	java/lang/Throwable
    //   686	753	756	java/lang/Throwable
    //   723	790	793	java/lang/Throwable
    //   760	827	830	java/lang/Throwable
    //   797	864	867	java/lang/Throwable
    //   834	901	904	java/lang/Throwable
    //   871	938	941	java/lang/Throwable
    //   908	975	978	java/lang/Throwable
    //   945	1012	1015	java/lang/Throwable
    //   982	1049	1052	java/lang/Throwable
    //   1019	1086	1089	java/lang/Throwable
    //   1056	1123	1126	java/lang/Throwable
    //   1093	1160	1163	java/lang/Throwable
    //   1130	1197	1200	java/lang/Throwable
    //   1167	1234	1237	java/lang/Throwable
    //   1204	1271	1274	java/lang/Throwable
    //   1241	1308	1311	java/lang/Throwable
    //   1278	1341	1344	java/lang/Throwable
    //   1381	1555	1558	java/lang/Throwable
    //   1524	1593	1596	java/lang/Throwable
    //   1562	1631	1634	java/lang/Throwable
    //   1600	1669	1672	java/lang/Throwable
    //   1638	1707	1710	java/lang/Throwable
    //   1676	1745	1748	java/lang/Throwable
    //   1714	1783	1786	java/lang/Throwable
    //   1752	1821	1824	java/lang/Throwable
    //   1790	1859	1862	java/lang/Throwable
    //   1828	1897	1900	java/lang/Throwable
    //   1866	1935	1938	java/lang/Throwable
    //   1904	1973	1976	java/lang/Throwable
    //   1942	2011	2014	java/lang/Throwable
    //   1980	2049	2052	java/lang/Throwable
    //   2018	2087	2090	java/lang/Throwable
    //   2056	2125	2128	java/lang/Throwable
    //   2094	2163	2166	java/lang/Throwable
    //   2132	2201	2204	java/lang/Throwable
    //   2170	2239	2242	java/lang/Throwable
    //   2208	2277	2280	java/lang/Throwable
    //   2246	2315	2318	java/lang/Throwable
    //   2284	2353	2356	java/lang/Throwable
    //   2322	2391	2394	java/lang/Throwable
    //   2360	2429	2432	java/lang/Throwable
    //   2398	2467	2470	java/lang/Throwable
    //   2436	2505	2508	java/lang/Throwable
    //   2474	2543	2546	java/lang/Throwable
    //   2512	2581	2584	java/lang/Throwable
    //   2550	2619	2622	java/lang/Throwable
    //   2588	2657	2660	java/lang/Throwable
    //   2626	2695	2698	java/lang/Throwable
    //   2664	2729	2732	java/lang/Throwable
    //   2796	2810	2810	java/lang/Throwable
    //   2821	2834	2837	java/lang/Throwable
    //   2826	2849	2852	java/lang/Throwable
    //   2841	2867	2870	java/lang/Throwable
    //   2856	2896	2899	java/lang/Throwable
    //   2962	2989	2992	java/lang/Throwable
    //   2979	3007	3010	java/lang/Throwable
    //   2996	3037	3040	java/lang/Throwable
    //   3014	3048	3048	java/lang/Throwable
    //   3059	3075	3078	java/lang/Throwable
    //   3127	3141	3141	java/lang/Throwable
    //   3152	3165	3168	java/lang/Throwable
    //   3157	3180	3183	java/lang/Throwable
    //   3172	3198	3201	java/lang/Throwable
    //   3187	3228	3231	java/lang/Throwable
    //   3294	3321	3324	java/lang/Throwable
    //   3311	3342	3345	java/lang/Throwable
    //   3328	3372	3375	java/lang/Throwable
    //   3349	3383	3383	java/lang/Throwable
    //   3394	3410	3413	java/lang/Throwable
    //   3609	3637	3640	java/lang/Throwable
    //   3619	3654	3657	java/lang/Throwable
    //   3644	3682	3685	java/lang/Throwable
    //   3661	3699	3702	java/lang/Throwable
    //   3689	3727	3730	java/lang/Throwable
    //   3706	3744	3747	java/lang/Throwable
    //   3734	3762	3765	java/lang/Throwable
    //   3751	3776	3779	java/lang/Throwable
    //   3823	4173	4176	java/lang/Throwable
    //   4007	4017	4017	java/lang/Throwable
    //   4021	4033	4033	java/lang/Throwable
    //   4037	4049	4049	java/lang/Throwable
    //   4053	4066	4066	java/lang/Throwable
    //   4070	4083	4083	java/lang/Throwable
    //   4271	4285	4285	java/lang/Throwable
    //   4296	4309	4312	java/lang/Throwable
    //   4301	4324	4327	java/lang/Throwable
    //   4316	4342	4345	java/lang/Throwable
    //   4331	4372	4375	java/lang/Throwable
    //   4438	4465	4468	java/lang/Throwable
    //   4455	4483	4486	java/lang/Throwable
    //   4472	4513	4516	java/lang/Throwable
    //   4490	4524	4524	java/lang/Throwable
    //   4547	4558	4561	java/lang/Throwable
    //   4613	4627	4627	java/lang/Throwable
    //   4638	4651	4654	java/lang/Throwable
    //   4643	4666	4669	java/lang/Throwable
    //   4658	4684	4687	java/lang/Throwable
    //   4673	4714	4717	java/lang/Throwable
    //   4780	4807	4810	java/lang/Throwable
    //   4797	4825	4828	java/lang/Throwable
    //   4814	4855	4858	java/lang/Throwable
    //   4832	4866	4866	java/lang/Throwable
    //   4889	4900	4903	java/lang/Throwable
    //   4915	5649	7115	java/lang/Throwable
    //   5005	5019	5019	java/lang/Throwable
    //   5030	5043	5046	java/lang/Throwable
    //   5035	5058	5061	java/lang/Throwable
    //   5050	5076	5079	java/lang/Throwable
    //   5065	5106	5109	java/lang/Throwable
    //   5172	5199	5202	java/lang/Throwable
    //   5189	5217	5220	java/lang/Throwable
    //   5206	5247	5250	java/lang/Throwable
    //   5224	5258	5258	java/lang/Throwable
    //   5281	5292	5295	java/lang/Throwable
    //   5348	5362	5362	java/lang/Throwable
    //   5373	5386	5389	java/lang/Throwable
    //   5378	5401	5404	java/lang/Throwable
    //   5393	5419	5422	java/lang/Throwable
    //   5408	5449	5452	java/lang/Throwable
    //   5515	5542	5545	java/lang/Throwable
    //   5532	5560	5563	java/lang/Throwable
    //   5549	5590	5593	java/lang/Throwable
    //   5567	5601	5601	java/lang/Throwable
    //   5624	5635	5638	java/lang/Throwable
    //   5650	6384	7115	java/lang/Throwable
    //   5740	5754	5754	java/lang/Throwable
    //   5765	5778	5781	java/lang/Throwable
    //   5770	5793	5796	java/lang/Throwable
    //   5785	5811	5814	java/lang/Throwable
    //   5800	5841	5844	java/lang/Throwable
    //   5907	5934	5937	java/lang/Throwable
    //   5924	5952	5955	java/lang/Throwable
    //   5941	5982	5985	java/lang/Throwable
    //   5959	5993	5993	java/lang/Throwable
    //   6016	6027	6030	java/lang/Throwable
    //   6083	6097	6097	java/lang/Throwable
    //   6108	6121	6124	java/lang/Throwable
    //   6113	6136	6139	java/lang/Throwable
    //   6128	6154	6157	java/lang/Throwable
    //   6143	6184	6187	java/lang/Throwable
    //   6250	6277	6280	java/lang/Throwable
    //   6267	6295	6298	java/lang/Throwable
    //   6284	6325	6328	java/lang/Throwable
    //   6302	6336	6336	java/lang/Throwable
    //   6359	6370	6373	java/lang/Throwable
    //   6385	7114	7115	java/lang/Throwable
    //   6475	6489	6489	java/lang/Throwable
    //   6500	6513	6516	java/lang/Throwable
    //   6505	6528	6531	java/lang/Throwable
    //   6520	6546	6549	java/lang/Throwable
    //   6535	6576	6579	java/lang/Throwable
    //   6642	6669	6672	java/lang/Throwable
    //   6659	6687	6690	java/lang/Throwable
    //   6676	6717	6720	java/lang/Throwable
    //   6694	6728	6728	java/lang/Throwable
    //   6751	6762	6765	java/lang/Throwable
    //   6818	6832	6832	java/lang/Throwable
    //   6843	6856	6859	java/lang/Throwable
    //   6848	6871	6874	java/lang/Throwable
    //   6863	6889	6892	java/lang/Throwable
    //   6878	6919	6922	java/lang/Throwable
    //   6985	7012	7015	java/lang/Throwable
    //   7002	7030	7033	java/lang/Throwable
    //   7019	7060	7063	java/lang/Throwable
    //   7037	7071	7071	java/lang/Throwable
    //   7094	7105	7108	java/lang/Throwable
  }
  
  static {
    // Byte code:
    //   0: bipush #30
    //   2: anewarray java/lang/String
    //   5: astore #5
    //   7: iconst_0
    //   8: istore_3
    //   9: ldc 'OI?Eng\\tT\\n\\tmCTEg\\f6bUm^\\t\\f2y)\\tqp\\t~Qy \\b\\t\\r#Kj\\t<&\\t(_^\\tx9PMHlF^wGZ?[DBc,J-\\r%CQNw.\\rR\\bMC6;< k\\f\\tG\\t7\\f8"&\\t`]|\\tsp+_&\\twM Ctyn(>CHQAp3)B~B\\tk^\\fhKU\\t8Y\\t<x /#g,hbe1RH1\\tDb\\bY\\t"r%n>]'
    //   11: dup
    //   12: astore_2
    //   13: invokevirtual length : ()I
    //   16: istore #4
    //   18: bipush #9
    //   20: istore_1
    //   21: iconst_m1
    //   22: istore_0
    //   23: bipush #10
    //   25: iinc #0, 1
    //   28: aload_2
    //   29: iload_0
    //   30: dup
    //   31: iload_1
    //   32: iadd
    //   33: invokevirtual substring : (II)Ljava/lang/String;
    //   36: iconst_m1
    //   37: goto -> 143
    //   40: aload #5
    //   42: swap
    //   43: iload_3
    //   44: iinc #3, 1
    //   47: swap
    //   48: aastore
    //   49: iload_0
    //   50: iload_1
    //   51: iadd
    //   52: dup
    //   53: istore_0
    //   54: iload #4
    //   56: if_icmpge -> 68
    //   59: aload_2
    //   60: iload_0
    //   61: invokevirtual charAt : (I)C
    //   64: istore_1
    //   65: goto -> 23
    //   68: ldc 'n)6$\\b%{Tb'
    //   70: dup
    //   71: astore_2
    //   72: invokevirtual length : ()I
    //   75: istore #4
    //   77: bipush #9
    //   79: istore_1
    //   80: iconst_m1
    //   81: istore_0
    //   82: bipush #23
    //   84: iinc #0, 1
    //   87: aload_2
    //   88: iload_0
    //   89: dup
    //   90: iload_1
    //   91: iadd
    //   92: invokevirtual substring : (II)Ljava/lang/String;
    //   95: iconst_0
    //   96: goto -> 143
    //   99: aload #5
    //   101: swap
    //   102: iload_3
    //   103: iinc #3, 1
    //   106: swap
    //   107: aastore
    //   108: iload_0
    //   109: iload_1
    //   110: iadd
    //   111: dup
    //   112: istore_0
    //   113: iload #4
    //   115: if_icmpge -> 127
    //   118: aload_2
    //   119: iload_0
    //   120: invokevirtual charAt : (I)C
    //   123: istore_1
    //   124: goto -> 82
    //   127: aload #5
    //   129: putstatic burp/Ztap.a : [Ljava/lang/String;
    //   132: bipush #30
    //   134: anewarray java/lang/String
    //   137: putstatic burp/Ztap.b : [Ljava/lang/String;
    //   140: goto -> 300
    //   143: dup_x2
    //   144: pop
    //   145: invokevirtual toCharArray : ()[C
    //   148: dup_x1
    //   149: arraylength
    //   150: dup_x2
    //   151: pop
    //   152: iconst_0
    //   153: istore #6
    //   155: dup2_x1
    //   156: pop2
    //   157: dup_x2
    //   158: iconst_1
    //   159: if_icmpgt -> 260
    //   162: dup2
    //   163: swap
    //   164: iload #6
    //   166: dup2_x1
    //   167: caload
    //   168: swap
    //   169: iload #6
    //   171: bipush #7
    //   173: irem
    //   174: tableswitch default -> 242, 0 -> 212, 1 -> 217, 2 -> 222, 3 -> 227, 4 -> 232, 5 -> 237
    //   212: bipush #28
    //   214: goto -> 244
    //   217: bipush #126
    //   219: goto -> 244
    //   222: bipush #126
    //   224: goto -> 244
    //   227: bipush #78
    //   229: goto -> 244
    //   232: bipush #53
    //   234: goto -> 244
    //   237: bipush #108
    //   239: goto -> 244
    //   242: bipush #50
    //   244: ixor
    //   245: ixor
    //   246: i2c
    //   247: castore
    //   248: iinc #6, 1
    //   251: dup
    //   252: ifne -> 260
    //   255: dup2
    //   256: dup_x1
    //   257: goto -> 166
    //   260: dup2_x1
    //   261: pop2
    //   262: dup_x2
    //   263: iload #6
    //   265: if_icmpgt -> 162
    //   268: pop
    //   269: new java/lang/String
    //   272: dup_x1
    //   273: swap
    //   274: invokespecial <init> : ([C)V
    //   277: invokevirtual intern : ()Ljava/lang/String;
    //   280: swap
    //   281: pop
    //   282: swap
    //   283: tableswitch default -> 40, 0 -> 99
    //   300: new java/math/BigInteger
    //   303: dup
    //   304: iconst_1
    //   305: bipush #32
    //   307: newarray byte
    //   309: dup
    //   310: iconst_0
    //   311: bipush #83
    //   313: bastore
    //   314: dup
    //   315: iconst_1
    //   316: bipush #10
    //   318: bastore
    //   319: dup
    //   320: iconst_2
    //   321: bipush #32
    //   323: bastore
    //   324: dup
    //   325: iconst_3
    //   326: bipush #-41
    //   328: bastore
    //   329: dup
    //   330: iconst_4
    //   331: bipush #11
    //   333: bastore
    //   334: dup
    //   335: iconst_5
    //   336: bipush #119
    //   338: bastore
    //   339: dup
    //   340: bipush #6
    //   342: bipush #-110
    //   344: bastore
    //   345: dup
    //   346: bipush #7
    //   348: bipush #-103
    //   350: bastore
    //   351: dup
    //   352: bipush #8
    //   354: bipush #-120
    //   356: bastore
    //   357: dup
    //   358: bipush #9
    //   360: bipush #112
    //   362: bastore
    //   363: dup
    //   364: bipush #10
    //   366: bipush #-32
    //   368: bastore
    //   369: dup
    //   370: bipush #11
    //   372: bipush #-115
    //   374: bastore
    //   375: dup
    //   376: bipush #12
    //   378: bipush #29
    //   380: bastore
    //   381: dup
    //   382: bipush #13
    //   384: bipush #102
    //   386: bastore
    //   387: dup
    //   388: bipush #14
    //   390: bipush #-58
    //   392: bastore
    //   393: dup
    //   394: bipush #15
    //   396: bipush #100
    //   398: bastore
    //   399: dup
    //   400: bipush #16
    //   402: bipush #-40
    //   404: bastore
    //   405: dup
    //   406: bipush #17
    //   408: bipush #-10
    //   410: bastore
    //   411: dup
    //   412: bipush #18
    //   414: bipush #125
    //   416: bastore
    //   417: dup
    //   418: bipush #19
    //   420: bipush #-27
    //   422: bastore
    //   423: dup
    //   424: bipush #20
    //   426: bipush #116
    //   428: bastore
    //   429: dup
    //   430: bipush #21
    //   432: bipush #-59
    //   434: bastore
    //   435: dup
    //   436: bipush #22
    //   438: bipush #122
    //   440: bastore
    //   441: dup
    //   442: bipush #23
    //   444: iconst_1
    //   445: bastore
    //   446: dup
    //   447: bipush #24
    //   449: bipush #-35
    //   451: bastore
    //   452: dup
    //   453: bipush #25
    //   455: bipush #-46
    //   457: bastore
    //   458: dup
    //   459: bipush #26
    //   461: bipush #45
    //   463: bastore
    //   464: dup
    //   465: bipush #27
    //   467: bipush #-57
    //   469: bastore
    //   470: dup
    //   471: bipush #28
    //   473: bipush #-50
    //   475: bastore
    //   476: dup
    //   477: bipush #29
    //   479: bipush #120
    //   481: bastore
    //   482: dup
    //   483: bipush #30
    //   485: bipush #59
    //   487: bastore
    //   488: dup
    //   489: bipush #31
    //   491: bipush #64
    //   493: bastore
    //   494: invokespecial <init> : (I[B)V
    //   497: putstatic burp/Ztap.ZK : Ljava/lang/Object;
    //   500: sipush #14607
    //   503: sipush #31568
    //   506: invokestatic a : (II)Ljava/lang/String;
    //   509: putstatic burp/Ztap.Zk : Ljava/lang/String;
    //   512: return
  }
  
  private static Throwable a(Throwable paramThrowable) {
    return paramThrowable;
  }
  
  private static String a(int paramInt1, int paramInt2) {
    int i = (paramInt1 ^ 0x3916) & 0xFFFF;
    if (b[i] == null) {
      char[] arrayOfChar = a[i].toCharArray();
      switch (arrayOfChar[0] & 0xFF) {
        case 0:
        
        case 1:
        
        case 2:
        
        case 3:
        
        case 4:
        
        case 5:
        
        case 6:
        
        case 7:
        
        case 8:
        
        case 9:
        
        case 10:
        
        case 11:
        
        case 12:
        
        case 13:
        
        case 14:
        
        case 15:
        
        case 16:
        
        case 17:
        
        case 18:
        
        case 19:
        
        case 20:
        
        case 21:
        
        case 22:
        
        case 23:
        
        case 24:
        
        case 25:
        
        case 26:
        
        case 27:
        
        case 28:
        
        case 29:
        
        case 30:
        
        case 31:
        
        case 32:
        
        case 33:
        
        case 34:
        
        case 35:
        
        case 36:
        
        case 37:
        
        case 38:
        
        case 39:
        
        case 40:
        
        case 41:
        
        case 42:
        
        case 43:
        
        case 44:
        
        case 45:
        
        case 46:
        
        case 47:
        
        case 48:
        
        case 49:
        
        case 50:
        
        case 51:
        
        case 52:
        
        case 53:
        
        case 54:
        
        case 55:
        
        case 56:
        
        case 57:
        
        case 58:
        
        case 59:
        
        case 60:
        
        case 61:
        
        case 62:
        
        case 63:
        
        case 64:
        
        case 65:
        
        case 66:
        
        case 67:
        
        case 68:
        
        case 69:
        
        case 70:
        
        case 71:
        
        case 72:
        
        case 73:
        
        case 74:
        
        case 75:
        
        case 76:
        
        case 77:
        
        case 78:
        
        case 79:
        
        case 80:
        
        case 81:
        
        case 82:
        
        case 83:
        
        case 84:
        
        case 85:
        
        case 86:
        
        case 87:
        
        case 88:
        
        case 89:
        
        case 90:
        
        case 91:
        
        case 92:
        
        case 93:
        
        case 94:
        
        case 95:
        
        case 96:
        
        case 97:
        
        case 98:
        
        case 99:
        
        case 100:
        
        case 101:
        
        case 102:
        
        case 103:
        
        case 104:
        
        case 105:
        
        case 106:
        
        case 107:
        
        case 108:
        
        case 109:
        
        case 110:
        
        case 111:
        
        case 112:
        
        case 113:
        
        case 114:
        
        case 115:
        
        case 116:
        
        case 117:
        
        case 118:
        
        case 119:
        
        case 120:
        
        case 121:
        
        case 122:
        
        case 123:
        
        case 124:
        
        case 125:
        
        case 126:
        
        case 127:
        
        case 128:
        
        case 129:
        
        case 130:
        
        case 131:
        
        case 132:
        
        case 133:
        
        case 134:
        
        case 135:
        
        case 136:
        
        case 137:
        
        case 138:
        
        case 139:
        
        case 140:
        
        case 141:
        
        case 142:
        
        case 143:
        
        case 144:
        
        case 145:
        
        case 146:
        
        case 147:
        
        case 148:
        
        case 149:
        
        case 150:
        
        case 151:
        
        case 152:
        
        case 153:
        
        case 154:
        
        case 155:
        
        case 156:
        
        case 157:
        
        case 158:
        
        case 159:
        
        case 160:
        
        case 161:
        
        case 162:
        
        case 163:
        
        case 164:
        
        case 165:
        
        case 166:
        
        case 167:
        
        case 168:
        
        case 169:
        
        case 170:
        
        case 171:
        
        case 172:
        
        case 173:
        
        case 174:
        
        case 175:
        
        case 176:
        
        case 177:
        
        case 178:
        
        case 179:
        
        case 180:
        
        case 181:
        
        case 182:
        
        case 183:
        
        case 184:
        
        case 185:
        
        case 186:
        
        case 187:
        
        case 188:
        
        case 189:
        
        case 190:
        
        case 191:
        
        case 192:
        
        case 193:
        
        case 194:
        
        case 195:
        
        case 196:
        
        case 197:
        
        case 198:
        
        case 199:
        
        case 200:
        
        case 201:
        
        case 202:
        
        case 203:
        
        case 204:
        
        case 205:
        
        case 206:
        
        case 207:
        
        case 208:
        
        case 209:
        
        case 210:
        
        case 211:
        
        case 212:
        
        case 213:
        
        case 214:
        
        case 215:
        
        case 216:
        
        case 217:
        
        case 218:
        
        case 219:
        
        case 220:
        
        case 221:
        
        case 222:
        
        case 223:
        
        case 224:
        
        case 225:
        
        case 226:
        
        case 227:
        
        case 228:
        
        case 229:
        
        case 230:
        
        case 231:
        
        case 232:
        
        case 233:
        
        case 234:
        
        case 235:
        
        case 236:
        
        case 237:
        
        case 238:
        
        case 239:
        
        case 240:
        
        case 241:
        
        case 242:
        
        case 243:
        
        case 244:
        
        case 245:
        
        case 246:
        
        case 247:
        
        case 248:
        
        case 249:
        
        case 250:
        
        case 251:
        
        case 252:
        
        case 253:
        
        case 254:
        
        default:
          break;
      } 
      char c = '';
      int j = (paramInt2 & 0xFF) - c;
      if (j < 0)
        j += 256; 
      int k = ((paramInt2 & 0xFFFF) >>> 8) - c;
      if (k < 0)
        k += 256; 
      for (byte b = 0; b < arrayOfChar.length; b++) {
        int m = b % 2;
        if (m == 0) {
          arrayOfChar[b] = (char)(arrayOfChar[b] ^ j);
          j = ((j >>> 3 | j << 5) ^ arrayOfChar[b]) & 0xFF;
        } else {
          arrayOfChar[b] = (char)(arrayOfChar[b] ^ k);
          k = ((k >>> 3 | k << 5) ^ arrayOfChar[b]) & 0xFF;
        } 
      } 
      b[i] = (new String(arrayOfChar)).intern();
    } 
    return b[i];
  }
}


/* Location:              C:\Program Files\BurpSuitePro\burpsuite_pro.jar!\burp\Ztap.class
 * Java compiler version: 21 (65.0)
 * JD-Core Version:       1.1.3
 */