package burp;

import java.util.Arrays;
import java.util.LinkedList;
import java.util.List;
import net.portswigger.Zen;
import net.portswigger.Zkb;
import net.portswigger.Zsy;

class Ztb3 implements Zzwz {
  private final Zlk4 Zh;
  
  private final int ZQ;
  
  private final int Zn;
  
  private final Zbjl ZA;
  
  private final Zsy ZK;
  
  private final Zxs7 ZT;
  
  private Zen Zf;
  
  private static final String[] a;
  
  private static final String[] b;
  
  Ztb3(Zlk4 paramZlk4, int paramInt1, int paramInt2, Zbjl paramZbjl, Zsy paramZsy, Zxs7 paramZxs7) {
    this.Zh = paramZlk4;
    this.ZQ = paramInt1;
    this.Zn = paramInt2;
    this.ZA = paramZbjl;
    this.ZK = paramZsy;
    this.ZT = paramZxs7;
  }
  
  public List<Zewx> ZK() {
    try {
      switch (Zb27.ZX[this.Zh.ordinal()]) {
        default:
          throw new MatchException(null, null);
        case 1:
        
        case 2:
        
        case 3:
          break;
      } 
    } catch (MatchException matchException) {
      throw a(null);
    } 
    return Za();
  }
  
  public Zewx Zt(Zlp9 paramZlp9) {
    int[] arrayOfInt = Ztok.ZS();
    for (Zewx zewx : Zk()) {
      try {
        if (zewx.ZG() == paramZlp9)
          return zewx; 
      } catch (MatchException matchException) {
        throw a(null);
      } 
      if (arrayOfInt == null)
        break; 
    } 
    return null;
  }
  
  public Zewx ZK(Zlp9 paramZlp9, Zen paramZen) {
    this.Zf = paramZen;
    return Zt(paramZlp9);
  }
  
  public Zkfj ZZ(Zewx paramZewx) {
    return new Ztok(null);
  }
  
  private List<Zewx> Za() {
    List<Zewx> list = ZU();
    try {
      if (!Zd()) {
        try {
          if (this.Zh.ZH(Zlk4.NORMAL)) {
            list.add(Zu(a(25836, -4008), Zlp9.MSSQL_SQLI_PAYLOAD_NUMBER_INSERT_TWO_COLS));
            list.add(Zu(a(25849, -3006), Zlp9.MSSQL_SQLI_PAYLOAD_NUMERIC_INSERT_THREE_COLS));
            list.add(Zu(a(25846, -6099), Zlp9.MSSQL_SQLI_PAYLOAD_NUMERIC_INSERT_FOUR_COLS));
            list.add(Zu(a(25840, -18627), Zlp9.MSSQL_SQLI_PAYLOAD_NUMERIC_NESTED_FUNCTION));
            list.add(Zu(a(25837, 10341), Zlp9.MSSQL_SQLI_PAYLOAD_STRING_INSERT_TWO_COLS));
            list.add(Zu(a(25841, 20944), Zlp9.MSSQL_SQLI_PAYLOAD_STRING_INSERT_THREE_COLS));
            list.add(Zu(a(25845, -21672), Zlp9.MSSQL_SQLI_PAYLOAD_STRING_INSERT_FOUR_COLS));
            list.add(Zu(a(25847, 14855), Zlp9.MSSQL_SQLI_PAYLOAD_STRING_NESTED_FUNCTION));
            return list;
          } 
        } catch (MatchException matchException) {
          throw a(null);
        } 
        list.add(Zu(a(25837, 10341), Zlp9.MSSQL_SQLI_PAYLOAD_STRING_INSERT_TWO_COLS));
        list.add(Zu(a(25841, 20944), Zlp9.MSSQL_SQLI_PAYLOAD_STRING_INSERT_THREE_COLS));
        list.add(Zu(a(25845, -21672), Zlp9.MSSQL_SQLI_PAYLOAD_STRING_INSERT_FOUR_COLS));
        list.add(Zu(a(25847, 14855), Zlp9.MSSQL_SQLI_PAYLOAD_STRING_NESTED_FUNCTION));
        return list;
      } 
    } catch (MatchException matchException) {
      throw a(null);
    } 
    list.add(Zu(a(25836, -4008), Zlp9.MSSQL_SQLI_PAYLOAD_NUMBER_INSERT_TWO_COLS));
    list.add(Zu(a(25849, -3006), Zlp9.MSSQL_SQLI_PAYLOAD_NUMERIC_INSERT_THREE_COLS));
    list.add(Zu(a(25846, -6099), Zlp9.MSSQL_SQLI_PAYLOAD_NUMERIC_INSERT_FOUR_COLS));
    list.add(Zu(a(25840, -18627), Zlp9.MSSQL_SQLI_PAYLOAD_NUMERIC_NESTED_FUNCTION));
    list.add(Zu(a(25837, 10341), Zlp9.MSSQL_SQLI_PAYLOAD_STRING_INSERT_TWO_COLS));
    list.add(Zu(a(25841, 20944), Zlp9.MSSQL_SQLI_PAYLOAD_STRING_INSERT_THREE_COLS));
    list.add(Zu(a(25845, -21672), Zlp9.MSSQL_SQLI_PAYLOAD_STRING_INSERT_FOUR_COLS));
    list.add(Zu(a(25847, 14855), Zlp9.MSSQL_SQLI_PAYLOAD_STRING_NESTED_FUNCTION));
    return list;
  }
  
  private List<Zewx> Zk() {
    return Arrays.asList(new Zewx[] { 
          Zu("", Zlp9.MSSQL_SQLI_PAYLOAD_NUMERIC_RAW), Zu("'", Zlp9.MSSQL_SQLI_PAYLOAD_STRING_RAW), Zu(")", Zlp9.MSSQL_SQLI_PAYLOAD_NUMERIC_INSERT_ONE_COL), Zu(a(25852, 29228), Zlp9.MSSQL_SQLI_PAYLOAD_STRING_INSERT_ONE_COL), Zu(a(25854, 7827), Zlp9.MSSQL_SQLI_PAYLOAD_NUMBER_INSERT_TWO_COLS), Zu(a(25853, 5279), Zlp9.MSSQL_SQLI_PAYLOAD_NUMERIC_INSERT_THREE_COLS), Zu(a(25848, 25488), Zlp9.MSSQL_SQLI_PAYLOAD_NUMERIC_INSERT_FOUR_COLS), Zu(a(25842, 26285), Zlp9.MSSQL_SQLI_PAYLOAD_NUMERIC_NESTED_FUNCTION), Zu(a(25855, 7616), Zlp9.MSSQL_SQLI_PAYLOAD_STRING_INSERT_TWO_COLS), Zu(a(25838, 10601), Zlp9.MSSQL_SQLI_PAYLOAD_STRING_INSERT_THREE_COLS), 
          Zu(a(25850, -17683), Zlp9.MSSQL_SQLI_PAYLOAD_STRING_INSERT_FOUR_COLS), Zu(a(25839, -10344), Zlp9.MSSQL_SQLI_PAYLOAD_STRING_NESTED_FUNCTION) });
  }
  
  private List<Zewx> ZU() {
    List<Zewx> list = Zt();
    try {
      if (!Zd()) {
        try {
          if (this.Zh.ZH(Zlk4.NORMAL)) {
            list.add(Zu(")", Zlp9.MSSQL_SQLI_PAYLOAD_NUMERIC_INSERT_ONE_COL));
            list.add(Zu(a(25844, -6045), Zlp9.MSSQL_SQLI_PAYLOAD_STRING_INSERT_ONE_COL));
            return list;
          } 
        } catch (MatchException matchException) {
          throw a(null);
        } 
        list.add(Zu(a(25844, -6045), Zlp9.MSSQL_SQLI_PAYLOAD_STRING_INSERT_ONE_COL));
        return list;
      } 
    } catch (MatchException matchException) {
      throw a(null);
    } 
    list.add(Zu(")", Zlp9.MSSQL_SQLI_PAYLOAD_NUMERIC_INSERT_ONE_COL));
    list.add(Zu(a(25844, -6045), Zlp9.MSSQL_SQLI_PAYLOAD_STRING_INSERT_ONE_COL));
    return list;
  }
  
  private List<Zewx> Zt() {
    LinkedList<Zewx> linkedList = new LinkedList();
    try {
      if (!Zd()) {
        try {
          if (this.Zh.ZH(Zlk4.NORMAL)) {
            linkedList.add(Zu("", Zlp9.MSSQL_SQLI_PAYLOAD_NUMERIC_RAW));
            linkedList.add(Zu("'", Zlp9.MSSQL_SQLI_PAYLOAD_STRING_RAW));
            return linkedList;
          } 
        } catch (MatchException matchException) {
          throw a(null);
        } 
        linkedList.add(Zu("'", Zlp9.MSSQL_SQLI_PAYLOAD_STRING_RAW));
        return linkedList;
      } 
    } catch (MatchException matchException) {
      throw a(null);
    } 
    linkedList.add(Zu("", Zlp9.MSSQL_SQLI_PAYLOAD_NUMERIC_RAW));
    linkedList.add(Zu("'", Zlp9.MSSQL_SQLI_PAYLOAD_STRING_RAW));
    return linkedList;
  }
  
  private boolean Zd() {
    return this.ZT.Zg();
  }
  
  private Zewx Zu(String paramString, Zlp9 paramZlp9) {
    Zen zen = Zr(paramZlp9);
    Zzi5 zzi5 = this.ZA.ZB();
    a(25851, 32173);
    return new Zewx(zen, Zkb.Zy(paramString + paramString + a(25851, 32173) + zzi5.Ze("+", "'", zen) + "\\" + Zo()), paramZlp9, new Zmhr(zzi5.ZU(zen), 80, false), (byte)1, Zewx.ZA);
  }
  
  private String Zo() {
    return this.ZK.Zi().Zq().ZK(3);
  }
  
  private Zen Zr(Zlp9 paramZlp9) {
    try {
      if (this.Zf != null)
        return this.Zf; 
    } catch (MatchException matchException) {
      throw a(null);
    } 
    Ztt6 ztt6 = new Ztt6(this.ZQ, this.Zn, paramZlp9, this.ZT.Zl());
    return this.ZA.ZK(1, ztt6.toString());
  }
  
  private static MatchException a(MatchException paramMatchException) {
    return paramMatchException;
  }
  
  static {
    // Byte code:
    //   0: bipush #20
    //   2: anewarray java/lang/String
    //   5: astore #5
    //   7: iconst_0
    //   8: istore_3
    //   9: ldc 'Â¬,Â„Ã‹VÃÂ t\\bÂ‚e4WCÃ£y7Â•uÃ¢Â¡6Ã¹Ãš3:ÂˆÂ¶Ã’ÃÂŽ5tS"Ã˜Â€Â«Ã˜Ã™ÂÃ²@vi2Â²)Â‹\\boÂŒÂ² /8Ã•Â†\\tÃ³5Â‚ÂÂŸÃ„\\nÃ†Ã‚Ã‰Â²Ã¯ÂywÃ²Ã¿ÃÃ‘o\\nÂ³5gÃ­Ã’ÃŽ\\bÃšÃ¥ÃŸÂ©\Â½Ã¡z CecÃÃ‹ÃªrÂ‰Ã€Â”Ã­Ã™Â§$jJ'3Â±"x4,Juy>Ã½Â¹Â¦7Ã¯<Â³Ãœ"B}Ã®jÃ¥Â£ÂªÃÃªÃˆLÃ±\\fÂ­ÃŸÃÃ§ÃµÂÃ„|(Â´\\fÃ¡ÂV~Ã–ÃƒÂ»Â¸ÃŸÂ°Â¯Ã€8{'
    //   11: dup
    //   12: astore_2
    //   13: invokevirtual length : ()I
    //   16: istore #4
    //   18: iconst_4
    //   19: istore_1
    //   20: iconst_m1
    //   21: istore_0
    //   22: bipush #55
    //   24: iinc #0, 1
    //   27: aload_2
    //   28: iload_0
    //   29: dup
    //   30: iload_1
    //   31: iadd
    //   32: invokevirtual substring : (II)Ljava/lang/String;
    //   35: iconst_m1
    //   36: goto -> 141
    //   39: aload #5
    //   41: swap
    //   42: iload_3
    //   43: iinc #3, 1
    //   46: swap
    //   47: aastore
    //   48: iload_0
    //   49: iload_1
    //   50: iadd
    //   51: dup
    //   52: istore_0
    //   53: iload #4
    //   55: if_icmpge -> 67
    //   58: aload_2
    //   59: iload_0
    //   60: invokevirtual charAt : (I)C
    //   63: istore_1
    //   64: goto -> 22
    //   67: ldc ''Â„iBÃ—,\\fÃ”\\nÃ˜'
    //   69: dup
    //   70: astore_2
    //   71: invokevirtual length : ()I
    //   74: istore #4
    //   76: iconst_4
    //   77: istore_1
    //   78: iconst_m1
    //   79: istore_0
    //   80: bipush #97
    //   82: iinc #0, 1
    //   85: aload_2
    //   86: iload_0
    //   87: dup
    //   88: iload_1
    //   89: iadd
    //   90: invokevirtual substring : (II)Ljava/lang/String;
    //   93: iconst_0
    //   94: goto -> 141
    //   97: aload #5
    //   99: swap
    //   100: iload_3
    //   101: iinc #3, 1
    //   104: swap
    //   105: aastore
    //   106: iload_0
    //   107: iload_1
    //   108: iadd
    //   109: dup
    //   110: istore_0
    //   111: iload #4
    //   113: if_icmpge -> 125
    //   116: aload_2
    //   117: iload_0
    //   118: invokevirtual charAt : (I)C
    //   121: istore_1
    //   122: goto -> 80
    //   125: aload #5
    //   127: putstatic burp/Ztb3.a : [Ljava/lang/String;
    //   130: bipush #20
    //   132: anewarray java/lang/String
    //   135: putstatic burp/Ztb3.b : [Ljava/lang/String;
    //   138: goto -> 300
    //   141: dup_x2
    //   142: pop
    //   143: invokevirtual toCharArray : ()[C
    //   146: dup_x1
    //   147: arraylength
    //   148: dup_x2
    //   149: pop
    //   150: iconst_0
    //   151: istore #6
    //   153: dup2_x1
    //   154: pop2
    //   155: dup_x2
    //   156: iconst_1
    //   157: if_icmpgt -> 260
    //   160: dup2
    //   161: swap
    //   162: iload #6
    //   164: dup2_x1
    //   165: caload
    //   166: swap
    //   167: iload #6
    //   169: bipush #7
    //   171: irem
    //   172: tableswitch default -> 242, 0 -> 212, 1 -> 217, 2 -> 222, 3 -> 227, 4 -> 232, 5 -> 237
    //   212: bipush #43
    //   214: goto -> 244
    //   217: bipush #28
    //   219: goto -> 244
    //   222: bipush #61
    //   224: goto -> 244
    //   227: bipush #17
    //   229: goto -> 244
    //   232: bipush #127
    //   234: goto -> 244
    //   237: bipush #27
    //   239: goto -> 244
    //   242: bipush #100
    //   244: ixor
    //   245: ixor
    //   246: i2c
    //   247: castore
    //   248: iinc #6, 1
    //   251: dup
    //   252: ifne -> 260
    //   255: dup2
    //   256: dup_x1
    //   257: goto -> 164
    //   260: dup2_x1
    //   261: pop2
    //   262: dup_x2
    //   263: iload #6
    //   265: if_icmpgt -> 160
    //   268: pop
    //   269: new java/lang/String
    //   272: dup_x1
    //   273: swap
    //   274: invokespecial <init> : ([C)V
    //   277: invokevirtual intern : ()Ljava/lang/String;
    //   280: swap
    //   281: pop
    //   282: swap
    //   283: tableswitch default -> 39, 0 -> 97
    //   300: return
  }
  
  private static String a(int paramInt1, int paramInt2) {
    int i = (paramInt1 ^ 0x64FE) & 0xFFFF;
    if (b[i] == null) {
      char[] arrayOfChar = a[i].toCharArray();
      switch (arrayOfChar[0] & 0xFF) {
        case 0:
        
        case 1:
        
        case 2:
        
        case 3:
        
        case 4:
        
        case 5:
        
        case 6:
        
        case 7:
        
        case 8:
        
        case 9:
        
        case 10:
        
        case 11:
        
        case 12:
        
        case 13:
        
        case 14:
        
        case 15:
        
        case 16:
        
        case 17:
        
        case 18:
        
        case 19:
        
        case 20:
        
        case 21:
        
        case 22:
        
        case 23:
        
        case 24:
        
        case 25:
        
        case 26:
        
        case 27:
        
        case 28:
        
        case 29:
        
        case 30:
        
        case 31:
        
        case 32:
        
        case 33:
        
        case 34:
        
        case 35:
        
        case 36:
        
        case 37:
        
        case 38:
        
        case 39:
        
        case 40:
        
        case 41:
        
        case 42:
        
        case 43:
        
        case 44:
        
        case 45:
        
        case 46:
        
        case 47:
        
        case 48:
        
        case 49:
        
        case 50:
        
        case 51:
        
        case 52:
        
        case 53:
        
        case 54:
        
        case 55:
        
        case 56:
        
        case 57:
        
        case 58:
        
        case 59:
        
        case 60:
        
        case 61:
        
        case 62:
        
        case 63:
        
        case 64:
        
        case 65:
        
        case 66:
        
        case 67:
        
        case 68:
        
        case 69:
        
        case 70:
        
        case 71:
        
        case 72:
        
        case 73:
        
        case 74:
        
        case 75:
        
        case 76:
        
        case 77:
        
        case 78:
        
        case 79:
        
        case 80:
        
        case 81:
        
        case 82:
        
        case 83:
        
        case 84:
        
        case 85:
        
        case 86:
        
        case 87:
        
        case 88:
        
        case 89:
        
        case 90:
        
        case 91:
        
        case 92:
        
        case 93:
        
        case 94:
        
        case 95:
        
        case 96:
        
        case 97:
        
        case 98:
        
        case 99:
        
        case 100:
        
        case 101:
        
        case 102:
        
        case 103:
        
        case 104:
        
        case 105:
        
        case 106:
        
        case 107:
        
        case 108:
        
        case 109:
        
        case 110:
        
        case 111:
        
        case 112:
        
        case 113:
        
        case 114:
        
        case 115:
        
        case 116:
        
        case 117:
        
        case 118:
        
        case 119:
        
        case 120:
        
        case 121:
        
        case 122:
        
        case 123:
        
        case 124:
        
        case 125:
        
        case 126:
        
        case 127:
        
        case 128:
        
        case 129:
        
        case 130:
        
        case 131:
        
        case 132:
        
        case 133:
        
        case 134:
        
        case 135:
        
        case 136:
        
        case 137:
        
        case 138:
        
        case 139:
        
        case 140:
        
        case 141:
        
        case 142:
        
        case 143:
        
        case 144:
        
        case 145:
        
        case 146:
        
        case 147:
        
        case 148:
        
        case 149:
        
        case 150:
        
        case 151:
        
        case 152:
        
        case 153:
        
        case 154:
        
        case 155:
        
        case 156:
        
        case 157:
        
        case 158:
        
        case 159:
        
        case 160:
        
        case 161:
        
        case 162:
        
        case 163:
        
        case 164:
        
        case 165:
        
        case 166:
        
        case 167:
        
        case 168:
        
        case 169:
        
        case 170:
        
        case 171:
        
        case 172:
        
        case 173:
        
        case 174:
        
        case 175:
        
        case 176:
        
        case 177:
        
        case 178:
        
        case 179:
        
        case 180:
        
        case 181:
        
        case 182:
        
        case 183:
        
        case 184:
        
        case 185:
        
        case 186:
        
        case 187:
        
        case 188:
        
        case 189:
        
        case 190:
        
        case 191:
        
        case 192:
        
        case 193:
        
        case 194:
        
        case 195:
        
        case 196:
        
        case 197:
        
        case 198:
        
        case 199:
        
        case 200:
        
        case 201:
        
        case 202:
        
        case 203:
        
        case 204:
        
        case 205:
        
        case 206:
        
        case 207:
        
        case 208:
        
        case 209:
        
        case 210:
        
        case 211:
        
        case 212:
        
        case 213:
        
        case 214:
        
        case 215:
        
        case 216:
        
        case 217:
        
        case 218:
        
        case 219:
        
        case 220:
        
        case 221:
        
        case 222:
        
        case 223:
        
        case 224:
        
        case 225:
        
        case 226:
        
        case 227:
        
        case 228:
        
        case 229:
        
        case 230:
        
        case 231:
        
        case 232:
        
        case 233:
        
        case 234:
        
        case 235:
        
        case 236:
        
        case 237:
        
        case 238:
        
        case 239:
        
        case 240:
        
        case 241:
        
        case 242:
        
        case 243:
        
        case 244:
        
        case 245:
        
        case 246:
        
        case 247:
        
        case 248:
        
        case 249:
        
        case 250:
        
        case 251:
        
        case 252:
        
        case 253:
        
        case 254:
        
        default:
          break;
      } 
      char c = 'Ã‰';
      int j = (paramInt2 & 0xFF) - c;
      if (j < 0)
        j += 256; 
      int k = ((paramInt2 & 0xFFFF) >>> 8) - c;
      if (k < 0)
        k += 256; 
      for (byte b = 0; b < arrayOfChar.length; b++) {
        int m = b % 2;
        if (m == 0) {
          arrayOfChar[b] = (char)(arrayOfChar[b] ^ j);
          j = ((j >>> 3 | j << 5) ^ arrayOfChar[b]) & 0xFF;
        } else {
          arrayOfChar[b] = (char)(arrayOfChar[b] ^ k);
          k = ((k >>> 3 | k << 5) ^ arrayOfChar[b]) & 0xFF;
        } 
      } 
      b[i] = (new String(arrayOfChar)).intern();
    } 
    return b[i];
  }
}


/* Location:              C:\Program Files\BurpSuitePro\burpsuite_pro.jar!\burp\Ztb3.class
 * Java compiler version: 21 (65.0)
 * JD-Core Version:       1.1.3
 */