package burp;

import java.security.cert.Certificate;
import java.security.cert.X509Certificate;
import java.util.ArrayList;
import java.util.Collection;
import java.util.List;
import net.portswigger.Zah;
import net.portswigger.Zk_;
import net.portswigger.Zkb;
import net.portswigger.Zqf;
import net.portswigger.Zuh;
import net.portswigger.Zvy;

@FunctionalInterface
public interface Ztbq {
  public static final Ztbq ZU;
  
  public static final Ztbq Zk;
  
  public static final String[] a;
  
  public static final String[] b;
  
  void Zs(Zmzk paramZmzk, Certificate[] paramArrayOfCertificate);
  
  static Zgvp ZE(X509Certificate paramX509Certificate) {
    String str1 = paramX509Certificate.getSubjectX500Principal().getName();
    try {
      int i = str1.indexOf(a(-18271, -5975));
      if (i == -1)
        i = str1.indexOf(a(-18267, 23205)); 
      if (i != -1) {
        str1 = str1.substring(i + 3);
        int j = str1.indexOf(a(-18272, 23075));
        if (j != -1)
          str1 = str1.substring(0, j); 
        j = str1.indexOf(a(-18266, 16302));
        if (j != -1)
          str1 = str1.substring(0, j); 
      } 
    } catch (Exception exception) {
      Zah.Zl(exception, Zk_.UNEXPECTED);
    } 
    String str2 = paramX509Certificate.getIssuerX500Principal().getName();
    try {
      int i = str2.indexOf(a(-18269, -10426));
      if (i == -1)
        i = str2.indexOf(a(-18268, 4609)); 
      if (i != -1) {
        int j = str2.indexOf(",", i);
        if (j == -1)
          j = str2.indexOf("/", i); 
        if (j != -1)
          str2 = str2.substring(i + 3, j); 
      } 
    } catch (Exception exception) {
      Zah.Zl(exception, Zk_.UNEXPECTED);
    } 
    ArrayList<String> arrayList = new ArrayList();
    try {
      Collection<List<?>> collection = paramX509Certificate.getSubjectAlternativeNames();
      if (collection != null)
        for (List<Object> list : collection) {
          Integer integer = (Integer)list.get(0);
          String str = (String)list.get(1);
          try {
            if (((Integer)integer).intValue() == 0)
              try {
                if (str instanceof byte[])
                  continue; 
              } catch (Exception exception) {
                throw a(null);
              }  
          } catch (Exception exception) {
            throw a(null);
          } 
          try {
            if (str instanceof String) {
              arrayList.add(str);
              continue;
            } 
          } catch (Exception exception) {
            throw a(null);
          } 
          Zuh.Zb(false, Zqf.Zk, Zf(integer), Zf(str));
        }  
    } catch (Exception exception) {
      Zah.Zl(exception, Zk_.UNEXPECTED);
    } 
    return new Zgvp(str1, str2, arrayList);
  }
  
  static String Zf(Object paramObject) {
    try {
      if (paramObject instanceof byte[])
        return Zkb.ZG(Zvy.ZZ((byte[])paramObject)); 
    } catch (UnsupportedOperationException unsupportedOperationException) {
      throw a(null);
    } 
    return String.valueOf(paramObject);
  }
  
  private static void lambda$static$1(Zmzk paramZmzk, Certificate[] paramArrayOfCertificate) {
    throw new UnsupportedOperationException(a(-18265, 23056));
  }
  
  private static void lambda$static$0(Zmzk paramZmzk, Certificate[] paramArrayOfCertificate) {}
  
  static {
    // Byte code:
    //   0: bipush #7
    //   2: anewarray java/lang/String
    //   5: astore #5
    //   7: iconst_0
    //   8: istore_3
    //   9: ldc 'Â¤Â¾Â…Ã Â–\\rPÃµÃœÃ¼Â„P`Â›kJÃŒÃ¥Ã‘Â¼Ã¯Ã˜Â¢xÃ®l4Ã›Ã•Ã Â‹Â¤;\\b'
    //   11: dup
    //   12: astore_2
    //   13: invokevirtual length : ()I
    //   16: istore #4
    //   18: iconst_3
    //   19: istore_1
    //   20: iconst_m1
    //   21: istore_0
    //   22: iconst_2
    //   23: iinc #0, 1
    //   26: aload_2
    //   27: iload_0
    //   28: dup
    //   29: iload_1
    //   30: iadd
    //   31: invokevirtual substring : (II)Ljava/lang/String;
    //   34: iconst_m1
    //   35: goto -> 140
    //   38: aload #5
    //   40: swap
    //   41: iload_3
    //   42: iinc #3, 1
    //   45: swap
    //   46: aastore
    //   47: iload_0
    //   48: iload_1
    //   49: iadd
    //   50: dup
    //   51: istore_0
    //   52: iload #4
    //   54: if_icmpge -> 66
    //   57: aload_2
    //   58: iload_0
    //   59: invokevirtual charAt : (I)C
    //   62: istore_1
    //   63: goto -> 22
    //   66: ldc '?ÃšÃÃº6'
    //   68: dup
    //   69: astore_2
    //   70: invokevirtual length : ()I
    //   73: istore #4
    //   75: iconst_2
    //   76: istore_1
    //   77: iconst_m1
    //   78: istore_0
    //   79: bipush #88
    //   81: iinc #0, 1
    //   84: aload_2
    //   85: iload_0
    //   86: dup
    //   87: iload_1
    //   88: iadd
    //   89: invokevirtual substring : (II)Ljava/lang/String;
    //   92: iconst_0
    //   93: goto -> 140
    //   96: aload #5
    //   98: swap
    //   99: iload_3
    //   100: iinc #3, 1
    //   103: swap
    //   104: aastore
    //   105: iload_0
    //   106: iload_1
    //   107: iadd
    //   108: dup
    //   109: istore_0
    //   110: iload #4
    //   112: if_icmpge -> 124
    //   115: aload_2
    //   116: iload_0
    //   117: invokevirtual charAt : (I)C
    //   120: istore_1
    //   121: goto -> 79
    //   124: aload #5
    //   126: putstatic burp/Ztbq.a : [Ljava/lang/String;
    //   129: bipush #7
    //   131: anewarray java/lang/String
    //   134: putstatic burp/Ztbq.b : [Ljava/lang/String;
    //   137: goto -> 296
    //   140: dup_x2
    //   141: pop
    //   142: invokevirtual toCharArray : ()[C
    //   145: dup_x1
    //   146: arraylength
    //   147: dup_x2
    //   148: pop
    //   149: iconst_0
    //   150: istore #6
    //   152: dup2_x1
    //   153: pop2
    //   154: dup_x2
    //   155: iconst_1
    //   156: if_icmpgt -> 256
    //   159: dup2
    //   160: swap
    //   161: iload #6
    //   163: dup2_x1
    //   164: caload
    //   165: swap
    //   166: iload #6
    //   168: bipush #7
    //   170: irem
    //   171: tableswitch default -> 238, 0 -> 208, 1 -> 213, 2 -> 218, 3 -> 223, 4 -> 228, 5 -> 233
    //   208: bipush #61
    //   210: goto -> 240
    //   213: bipush #96
    //   215: goto -> 240
    //   218: bipush #111
    //   220: goto -> 240
    //   223: bipush #57
    //   225: goto -> 240
    //   228: bipush #120
    //   230: goto -> 240
    //   233: bipush #123
    //   235: goto -> 240
    //   238: bipush #32
    //   240: ixor
    //   241: ixor
    //   242: i2c
    //   243: castore
    //   244: iinc #6, 1
    //   247: dup
    //   248: ifne -> 256
    //   251: dup2
    //   252: dup_x1
    //   253: goto -> 163
    //   256: dup2_x1
    //   257: pop2
    //   258: dup_x2
    //   259: iload #6
    //   261: if_icmpgt -> 159
    //   264: pop
    //   265: new java/lang/String
    //   268: dup_x1
    //   269: swap
    //   270: invokespecial <init> : ([C)V
    //   273: invokevirtual intern : ()Ljava/lang/String;
    //   276: swap
    //   277: pop
    //   278: swap
    //   279: tableswitch default -> 38, 0 -> 96
    //   296: <illegal opcode> Zs : ()Lburp/Ztbq;
    //   301: putstatic burp/Ztbq.ZU : Lburp/Ztbq;
    //   304: <illegal opcode> Zs : ()Lburp/Ztbq;
    //   309: putstatic burp/Ztbq.Zk : Lburp/Ztbq;
    //   312: return
  }
  
  private static Exception a(Exception paramException) {
    return paramException;
  }
  
  private static String a(int paramInt1, int paramInt2) {
    int i = (paramInt1 ^ 0xFFFFB8A5) & 0xFFFF;
    if (b[i] == null) {
      char[] arrayOfChar = a[i].toCharArray();
      switch (arrayOfChar[0] & 0xFF) {
        case 0:
        
        case 1:
        
        case 2:
        
        case 3:
        
        case 4:
        
        case 5:
        
        case 6:
        
        case 7:
        
        case 8:
        
        case 9:
        
        case 10:
        
        case 11:
        
        case 12:
        
        case 13:
        
        case 14:
        
        case 15:
        
        case 16:
        
        case 17:
        
        case 18:
        
        case 19:
        
        case 20:
        
        case 21:
        
        case 22:
        
        case 23:
        
        case 24:
        
        case 25:
        
        case 26:
        
        case 27:
        
        case 28:
        
        case 29:
        
        case 30:
        
        case 31:
        
        case 32:
        
        case 33:
        
        case 34:
        
        case 35:
        
        case 36:
        
        case 37:
        
        case 38:
        
        case 39:
        
        case 40:
        
        case 41:
        
        case 42:
        
        case 43:
        
        case 44:
        
        case 45:
        
        case 46:
        
        case 47:
        
        case 48:
        
        case 49:
        
        case 50:
        
        case 51:
        
        case 52:
        
        case 53:
        
        case 54:
        
        case 55:
        
        case 56:
        
        case 57:
        
        case 58:
        
        case 59:
        
        case 60:
        
        case 61:
        
        case 62:
        
        case 63:
        
        case 64:
        
        case 65:
        
        case 66:
        
        case 67:
        
        case 68:
        
        case 69:
        
        case 70:
        
        case 71:
        
        case 72:
        
        case 73:
        
        case 74:
        
        case 75:
        
        case 76:
        
        case 77:
        
        case 78:
        
        case 79:
        
        case 80:
        
        case 81:
        
        case 82:
        
        case 83:
        
        case 84:
        
        case 85:
        
        case 86:
        
        case 87:
        
        case 88:
        
        case 89:
        
        case 90:
        
        case 91:
        
        case 92:
        
        case 93:
        
        case 94:
        
        case 95:
        
        case 96:
        
        case 97:
        
        case 98:
        
        case 99:
        
        case 100:
        
        case 101:
        
        case 102:
        
        case 103:
        
        case 104:
        
        case 105:
        
        case 106:
        
        case 107:
        
        case 108:
        
        case 109:
        
        case 110:
        
        case 111:
        
        case 112:
        
        case 113:
        
        case 114:
        
        case 115:
        
        case 116:
        
        case 117:
        
        case 118:
        
        case 119:
        
        case 120:
        
        case 121:
        
        case 122:
        
        case 123:
        
        case 124:
        
        case 125:
        
        case 126:
        
        case 127:
        
        case 128:
        
        case 129:
        
        case 130:
        
        case 131:
        
        case 132:
        
        case 133:
        
        case 134:
        
        case 135:
        
        case 136:
        
        case 137:
        
        case 138:
        
        case 139:
        
        case 140:
        
        case 141:
        
        case 142:
        
        case 143:
        
        case 144:
        
        case 145:
        
        case 146:
        
        case 147:
        
        case 148:
        
        case 149:
        
        case 150:
        
        case 151:
        
        case 152:
        
        case 153:
        
        case 154:
        
        case 155:
        
        case 156:
        
        case 157:
        
        case 158:
        
        case 159:
        
        case 160:
        
        case 161:
        
        case 162:
        
        case 163:
        
        case 164:
        
        case 165:
        
        case 166:
        
        case 167:
        
        case 168:
        
        case 169:
        
        case 170:
        
        case 171:
        
        case 172:
        
        case 173:
        
        case 174:
        
        case 175:
        
        case 176:
        
        case 177:
        
        case 178:
        
        case 179:
        
        case 180:
        
        case 181:
        
        case 182:
        
        case 183:
        
        case 184:
        
        case 185:
        
        case 186:
        
        case 187:
        
        case 188:
        
        case 189:
        
        case 190:
        
        case 191:
        
        case 192:
        
        case 193:
        
        case 194:
        
        case 195:
        
        case 196:
        
        case 197:
        
        case 198:
        
        case 199:
        
        case 200:
        
        case 201:
        
        case 202:
        
        case 203:
        
        case 204:
        
        case 205:
        
        case 206:
        
        case 207:
        
        case 208:
        
        case 209:
        
        case 210:
        
        case 211:
        
        case 212:
        
        case 213:
        
        case 214:
        
        case 215:
        
        case 216:
        
        case 217:
        
        case 218:
        
        case 219:
        
        case 220:
        
        case 221:
        
        case 222:
        
        case 223:
        
        case 224:
        
        case 225:
        
        case 226:
        
        case 227:
        
        case 228:
        
        case 229:
        
        case 230:
        
        case 231:
        
        case 232:
        
        case 233:
        
        case 234:
        
        case 235:
        
        case 236:
        
        case 237:
        
        case 238:
        
        case 239:
        
        case 240:
        
        case 241:
        
        case 242:
        
        case 243:
        
        case 244:
        
        case 245:
        
        case 246:
        
        case 247:
        
        case 248:
        
        case 249:
        
        case 250:
        
        case 251:
        
        case 252:
        
        case 253:
        
        case 254:
        
        default:
          break;
      } 
      byte b1 = 117;
      int j = (paramInt2 & 0xFF) - b1;
      if (j < 0)
        j += 256; 
      int k = ((paramInt2 & 0xFFFF) >>> 8) - b1;
      if (k < 0)
        k += 256; 
      for (byte b2 = 0; b2 < arrayOfChar.length; b2++) {
        int m = b2 % 2;
        if (m == 0) {
          arrayOfChar[b2] = (char)(arrayOfChar[b2] ^ j);
          j = ((j >>> 3 | j << 5) ^ arrayOfChar[b2]) & 0xFF;
        } else {
          arrayOfChar[b2] = (char)(arrayOfChar[b2] ^ k);
          k = ((k >>> 3 | k << 5) ^ arrayOfChar[b2]) & 0xFF;
        } 
      } 
      b[i] = (new String(arrayOfChar)).intern();
    } 
    return b[i];
  }
}


/* Location:              C:\Program Files\BurpSuitePro\burpsuite_pro.jar!\burp\Ztbq.class
 * Java compiler version: 21 (65.0)
 * JD-Core Version:       1.1.3
 */