package burp;

import java.math.BigInteger;

class Ztd3 extends ClassLoader {
  static String ZC;
  
  static Object ZX;
  
  private static final String[] a;
  
  private static final String[] b;
  
  static boolean ZY(Object[] paramArrayOfObject, Object paramObject) throws Throwable {
    // Byte code:
    //   0: invokestatic ZN : ()Z
    //   3: istore_2
    //   4: getstatic burp/Zxtc.ZF : Ljava/lang/Object;
    //   7: checkcast java/math/BigInteger
    //   10: getstatic burp/Zlhm.ZT : Ljava/lang/Object;
    //   13: checkcast java/math/BigInteger
    //   16: invokevirtual subtract : (Ljava/math/BigInteger;)Ljava/math/BigInteger;
    //   19: putstatic burp/Zgw7.Zi : Ljava/lang/Object;
    //   22: sipush #-4834
    //   25: sipush #20686
    //   28: invokestatic a : (II)Ljava/lang/String;
    //   31: iconst_1
    //   32: ldc burp/Zlnq
    //   34: invokevirtual getClassLoader : ()Ljava/lang/ClassLoader;
    //   37: invokestatic forName : (Ljava/lang/String;ZLjava/lang/ClassLoader;)Ljava/lang/Class;
    //   40: invokevirtual getDeclaredFields : ()[Ljava/lang/reflect/Field;
    //   43: astore_3
    //   44: aload_3
    //   45: arraylength
    //   46: istore #4
    //   48: iconst_0
    //   49: istore #5
    //   51: iload #5
    //   53: iload #4
    //   55: if_icmpge -> 192
    //   58: aload_3
    //   59: iload #5
    //   61: aaload
    //   62: astore #6
    //   64: aload #6
    //   66: invokevirtual getModifiers : ()I
    //   69: invokestatic isStatic : (I)Z
    //   72: ifne -> 82
    //   75: goto -> 185
    //   78: invokestatic a : (Ljava/lang/Throwable;)Ljava/lang/Throwable;
    //   81: athrow
    //   82: aload #6
    //   84: invokevirtual getType : ()Ljava/lang/Class;
    //   87: astore #7
    //   89: aload #7
    //   91: ifnull -> 172
    //   94: aload #7
    //   96: invokevirtual isPrimitive : ()Z
    //   99: ifne -> 172
    //   102: goto -> 109
    //   105: invokestatic a : (Ljava/lang/Throwable;)Ljava/lang/Throwable;
    //   108: athrow
    //   109: aload #7
    //   111: invokevirtual getPackage : ()Ljava/lang/Package;
    //   114: ifnull -> 172
    //   117: goto -> 124
    //   120: invokestatic a : (Ljava/lang/Throwable;)Ljava/lang/Throwable;
    //   123: athrow
    //   124: aload #7
    //   126: invokevirtual getPackage : ()Ljava/lang/Package;
    //   129: invokevirtual getName : ()Ljava/lang/String;
    //   132: ifnull -> 172
    //   135: goto -> 142
    //   138: invokestatic a : (Ljava/lang/Throwable;)Ljava/lang/Throwable;
    //   141: athrow
    //   142: aload #7
    //   144: invokevirtual getPackage : ()Ljava/lang/Package;
    //   147: invokevirtual getName : ()Ljava/lang/String;
    //   150: sipush #-4836
    //   153: sipush #-15079
    //   156: invokestatic a : (II)Ljava/lang/String;
    //   159: invokevirtual startsWith : (Ljava/lang/String;)Z
    //   162: ifne -> 172
    //   165: goto -> 172
    //   168: invokestatic a : (Ljava/lang/Throwable;)Ljava/lang/Throwable;
    //   171: athrow
    //   172: aload #6
    //   174: iconst_1
    //   175: invokevirtual setAccessible : (Z)V
    //   178: aload #6
    //   180: aconst_null
    //   181: invokevirtual get : (Ljava/lang/Object;)Ljava/lang/Object;
    //   184: pop
    //   185: iinc #5, 1
    //   188: iload_2
    //   189: ifne -> 51
    //   192: sipush #-4839
    //   195: sipush #-25469
    //   198: invokestatic a : (II)Ljava/lang/String;
    //   201: invokestatic forName : (Ljava/lang/String;)Ljava/lang/Class;
    //   204: invokevirtual getDeclaredMethods : ()[Ljava/lang/reflect/Method;
    //   207: astore_3
    //   208: aload_3
    //   209: arraylength
    //   210: istore #4
    //   212: iconst_0
    //   213: istore #5
    //   215: iload #5
    //   217: iload #4
    //   219: if_icmpge -> 351
    //   222: aload_3
    //   223: iload #5
    //   225: aaload
    //   226: astore #6
    //   228: aload #6
    //   230: invokevirtual getParameterTypes : ()[Ljava/lang/Class;
    //   233: pop
    //   234: aload #6
    //   236: invokevirtual getModifiers : ()I
    //   239: invokestatic isStatic : (I)Z
    //   242: ifeq -> 337
    //   245: aload #6
    //   247: invokevirtual getParameterTypes : ()[Ljava/lang/Class;
    //   250: arraylength
    //   251: iconst_2
    //   252: if_icmpne -> 337
    //   255: goto -> 262
    //   258: invokestatic a : (Ljava/lang/Throwable;)Ljava/lang/Throwable;
    //   261: athrow
    //   262: aload #6
    //   264: invokevirtual getReturnType : ()Ljava/lang/Class;
    //   267: getstatic java/lang/Void.TYPE : Ljava/lang/Class;
    //   270: invokevirtual equals : (Ljava/lang/Object;)Z
    //   273: ifeq -> 337
    //   276: goto -> 283
    //   279: invokestatic a : (Ljava/lang/Throwable;)Ljava/lang/Throwable;
    //   282: athrow
    //   283: aload #6
    //   285: iconst_1
    //   286: invokevirtual setAccessible : (Z)V
    //   289: aload #6
    //   291: aconst_null
    //   292: iconst_2
    //   293: anewarray java/lang/Object
    //   296: dup
    //   297: iconst_0
    //   298: aload_0
    //   299: aastore
    //   300: dup
    //   301: iconst_1
    //   302: aload_1
    //   303: ifnonnull -> 321
    //   306: goto -> 313
    //   309: invokestatic a : (Ljava/lang/Throwable;)Ljava/lang/Throwable;
    //   312: athrow
    //   313: aload_1
    //   314: goto -> 328
    //   317: invokestatic a : (Ljava/lang/Throwable;)Ljava/lang/Throwable;
    //   320: athrow
    //   321: aload_1
    //   322: checkcast [B
    //   325: invokevirtual clone : ()Ljava/lang/Object;
    //   328: aastore
    //   329: invokevirtual invoke : (Ljava/lang/Object;[Ljava/lang/Object;)Ljava/lang/Object;
    //   332: pop
    //   333: iload_2
    //   334: ifne -> 351
    //   337: iinc #5, 1
    //   340: iload_2
    //   341: ifne -> 215
    //   344: goto -> 351
    //   347: invokestatic a : (Ljava/lang/Throwable;)Ljava/lang/Throwable;
    //   350: athrow
    //   351: getstatic burp/Zro5.ZT : Ljava/lang/Object;
    //   354: checkcast java/math/BigInteger
    //   357: invokevirtual intValue : ()I
    //   360: i2l
    //   361: invokestatic currentTimeMillis : ()J
    //   364: ladd
    //   365: getstatic burp/Zz35.ZB : Ljava/lang/Object;
    //   368: checkcast java/math/BigInteger
    //   371: invokevirtual intValue : ()I
    //   374: i2l
    //   375: lcmp
    //   376: ifge -> 708
    //   379: sipush #-4848
    //   382: sipush #-16032
    //   385: invokestatic a : (II)Ljava/lang/String;
    //   388: iconst_1
    //   389: ldc burp/Zlqy
    //   391: invokevirtual getClassLoader : ()Ljava/lang/ClassLoader;
    //   394: invokestatic forName : (Ljava/lang/String;ZLjava/lang/ClassLoader;)Ljava/lang/Class;
    //   397: invokevirtual getDeclaredFields : ()[Ljava/lang/reflect/Field;
    //   400: astore_3
    //   401: aload_3
    //   402: arraylength
    //   403: istore #4
    //   405: iconst_0
    //   406: istore #5
    //   408: iload #5
    //   410: iload #4
    //   412: if_icmpge -> 549
    //   415: aload_3
    //   416: iload #5
    //   418: aaload
    //   419: astore #6
    //   421: aload #6
    //   423: invokevirtual getModifiers : ()I
    //   426: invokestatic isStatic : (I)Z
    //   429: ifne -> 439
    //   432: goto -> 542
    //   435: invokestatic a : (Ljava/lang/Throwable;)Ljava/lang/Throwable;
    //   438: athrow
    //   439: aload #6
    //   441: invokevirtual getType : ()Ljava/lang/Class;
    //   444: astore #7
    //   446: aload #7
    //   448: ifnull -> 529
    //   451: aload #7
    //   453: invokevirtual isPrimitive : ()Z
    //   456: ifne -> 529
    //   459: goto -> 466
    //   462: invokestatic a : (Ljava/lang/Throwable;)Ljava/lang/Throwable;
    //   465: athrow
    //   466: aload #7
    //   468: invokevirtual getPackage : ()Ljava/lang/Package;
    //   471: ifnull -> 529
    //   474: goto -> 481
    //   477: invokestatic a : (Ljava/lang/Throwable;)Ljava/lang/Throwable;
    //   480: athrow
    //   481: aload #7
    //   483: invokevirtual getPackage : ()Ljava/lang/Package;
    //   486: invokevirtual getName : ()Ljava/lang/String;
    //   489: ifnull -> 529
    //   492: goto -> 499
    //   495: invokestatic a : (Ljava/lang/Throwable;)Ljava/lang/Throwable;
    //   498: athrow
    //   499: aload #7
    //   501: invokevirtual getPackage : ()Ljava/lang/Package;
    //   504: invokevirtual getName : ()Ljava/lang/String;
    //   507: sipush #-4837
    //   510: sipush #-5238
    //   513: invokestatic a : (II)Ljava/lang/String;
    //   516: invokevirtual startsWith : (Ljava/lang/String;)Z
    //   519: ifne -> 529
    //   522: goto -> 529
    //   525: invokestatic a : (Ljava/lang/Throwable;)Ljava/lang/Throwable;
    //   528: athrow
    //   529: aload #6
    //   531: iconst_1
    //   532: invokevirtual setAccessible : (Z)V
    //   535: aload #6
    //   537: aconst_null
    //   538: invokevirtual get : (Ljava/lang/Object;)Ljava/lang/Object;
    //   541: pop
    //   542: iinc #5, 1
    //   545: iload_2
    //   546: ifne -> 408
    //   549: sipush #-4845
    //   552: sipush #31247
    //   555: invokestatic a : (II)Ljava/lang/String;
    //   558: invokestatic forName : (Ljava/lang/String;)Ljava/lang/Class;
    //   561: invokevirtual getDeclaredMethods : ()[Ljava/lang/reflect/Method;
    //   564: astore_3
    //   565: aload_3
    //   566: arraylength
    //   567: istore #4
    //   569: iconst_0
    //   570: istore #5
    //   572: iload #5
    //   574: iload #4
    //   576: if_icmpge -> 708
    //   579: aload_3
    //   580: iload #5
    //   582: aaload
    //   583: astore #6
    //   585: aload #6
    //   587: invokevirtual getParameterTypes : ()[Ljava/lang/Class;
    //   590: pop
    //   591: aload #6
    //   593: invokevirtual getModifiers : ()I
    //   596: invokestatic isStatic : (I)Z
    //   599: ifeq -> 694
    //   602: aload #6
    //   604: invokevirtual getParameterTypes : ()[Ljava/lang/Class;
    //   607: arraylength
    //   608: iconst_2
    //   609: if_icmpne -> 694
    //   612: goto -> 619
    //   615: invokestatic a : (Ljava/lang/Throwable;)Ljava/lang/Throwable;
    //   618: athrow
    //   619: aload #6
    //   621: invokevirtual getReturnType : ()Ljava/lang/Class;
    //   624: getstatic java/lang/Void.TYPE : Ljava/lang/Class;
    //   627: invokevirtual equals : (Ljava/lang/Object;)Z
    //   630: ifeq -> 694
    //   633: goto -> 640
    //   636: invokestatic a : (Ljava/lang/Throwable;)Ljava/lang/Throwable;
    //   639: athrow
    //   640: aload #6
    //   642: iconst_1
    //   643: invokevirtual setAccessible : (Z)V
    //   646: aload #6
    //   648: aconst_null
    //   649: iconst_2
    //   650: anewarray java/lang/Object
    //   653: dup
    //   654: iconst_0
    //   655: aload_0
    //   656: aastore
    //   657: dup
    //   658: iconst_1
    //   659: aload_1
    //   660: ifnonnull -> 678
    //   663: goto -> 670
    //   666: invokestatic a : (Ljava/lang/Throwable;)Ljava/lang/Throwable;
    //   669: athrow
    //   670: aload_1
    //   671: goto -> 685
    //   674: invokestatic a : (Ljava/lang/Throwable;)Ljava/lang/Throwable;
    //   677: athrow
    //   678: aload_1
    //   679: checkcast [B
    //   682: invokevirtual clone : ()Ljava/lang/Object;
    //   685: aastore
    //   686: invokevirtual invoke : (Ljava/lang/Object;[Ljava/lang/Object;)Ljava/lang/Object;
    //   689: pop
    //   690: iload_2
    //   691: ifne -> 708
    //   694: iinc #5, 1
    //   697: iload_2
    //   698: ifne -> 572
    //   701: goto -> 708
    //   704: invokestatic a : (Ljava/lang/Throwable;)Ljava/lang/Throwable;
    //   707: athrow
    //   708: new java/io/ByteArrayOutputStream
    //   711: dup
    //   712: invokespecial <init> : ()V
    //   715: astore_3
    //   716: getstatic burp/Zlo2.ZJ : Ljava/lang/String;
    //   719: astore #4
    //   721: iconst_0
    //   722: istore #5
    //   724: iload #5
    //   726: aload #4
    //   728: invokevirtual length : ()I
    //   731: if_icmpge -> 761
    //   734: aload_3
    //   735: aload #4
    //   737: iload #5
    //   739: iload #5
    //   741: iconst_2
    //   742: iadd
    //   743: invokevirtual substring : (II)Ljava/lang/String;
    //   746: bipush #16
    //   748: invokestatic parseInt : (Ljava/lang/String;I)I
    //   751: invokevirtual write : (I)V
    //   754: iinc #5, 2
    //   757: iload_2
    //   758: ifne -> 724
    //   761: aload_3
    //   762: invokevirtual toByteArray : ()[B
    //   765: astore #5
    //   767: getstatic burp/Zry0.Zr : Ljava/lang/Object;
    //   770: checkcast java/math/BigInteger
    //   773: invokevirtual toByteArray : ()[B
    //   776: astore #6
    //   778: sipush #256
    //   781: newarray byte
    //   783: astore #8
    //   785: sipush #256
    //   788: newarray int
    //   790: astore #9
    //   792: sipush #256
    //   795: newarray int
    //   797: astore #10
    //   799: sipush #256
    //   802: newarray int
    //   804: astore #11
    //   806: sipush #256
    //   809: newarray int
    //   811: astore #12
    //   813: bipush #10
    //   815: newarray int
    //   817: astore #13
    //   819: sipush #283
    //   822: istore #14
    //   824: iconst_0
    //   825: istore #16
    //   827: iload #16
    //   829: sipush #256
    //   832: if_icmpge -> 1066
    //   835: sipush #-4846
    //   838: sipush #14192
    //   841: invokestatic a : (II)Ljava/lang/String;
    //   844: iload #16
    //   846: iconst_1
    //   847: iushr
    //   848: invokevirtual charAt : (I)C
    //   851: istore #25
    //   853: iload #16
    //   855: iconst_1
    //   856: iand
    //   857: ifne -> 872
    //   860: iload #25
    //   862: bipush #8
    //   864: iushr
    //   865: goto -> 874
    //   868: invokestatic a : (Ljava/lang/Throwable;)Ljava/lang/Throwable;
    //   871: athrow
    //   872: iload #25
    //   874: i2b
    //   875: sipush #255
    //   878: iand
    //   879: istore #15
    //   881: iload #16
    //   883: iconst_1
    //   884: ishl
    //   885: istore #17
    //   887: iload #17
    //   889: sipush #256
    //   892: if_icmplt -> 902
    //   895: iload #17
    //   897: iload #14
    //   899: ixor
    //   900: istore #17
    //   902: iload #17
    //   904: iconst_1
    //   905: ishl
    //   906: istore #18
    //   908: iload #18
    //   910: sipush #256
    //   913: if_icmplt -> 923
    //   916: iload #18
    //   918: iload #14
    //   920: ixor
    //   921: istore #18
    //   923: iload #18
    //   925: iconst_1
    //   926: ishl
    //   927: istore #19
    //   929: iload #19
    //   931: sipush #256
    //   934: if_icmplt -> 944
    //   937: iload #19
    //   939: iload #14
    //   941: ixor
    //   942: istore #19
    //   944: iload #19
    //   946: iload #16
    //   948: ixor
    //   949: istore #20
    //   951: iload #20
    //   953: iload #17
    //   955: ixor
    //   956: istore #21
    //   958: iload #20
    //   960: iload #18
    //   962: ixor
    //   963: istore #22
    //   965: iload #19
    //   967: iload #18
    //   969: ixor
    //   970: iload #17
    //   972: ixor
    //   973: istore #23
    //   975: aload #8
    //   977: iload #16
    //   979: iload #15
    //   981: i2b
    //   982: bastore
    //   983: aload #9
    //   985: iload #15
    //   987: iload #23
    //   989: bipush #24
    //   991: ishl
    //   992: iload #20
    //   994: bipush #16
    //   996: ishl
    //   997: ior
    //   998: iload #22
    //   1000: bipush #8
    //   1002: ishl
    //   1003: ior
    //   1004: iload #21
    //   1006: ior
    //   1007: dup
    //   1008: istore #24
    //   1010: iastore
    //   1011: aload #10
    //   1013: iload #15
    //   1015: iload #24
    //   1017: bipush #8
    //   1019: iushr
    //   1020: iload #24
    //   1022: bipush #24
    //   1024: ishl
    //   1025: ior
    //   1026: iastore
    //   1027: aload #11
    //   1029: iload #15
    //   1031: iload #24
    //   1033: bipush #16
    //   1035: iushr
    //   1036: iload #24
    //   1038: bipush #16
    //   1040: ishl
    //   1041: ior
    //   1042: iastore
    //   1043: aload #12
    //   1045: iload #15
    //   1047: iload #24
    //   1049: bipush #24
    //   1051: iushr
    //   1052: iload #24
    //   1054: bipush #8
    //   1056: ishl
    //   1057: ior
    //   1058: iastore
    //   1059: iinc #16, 1
    //   1062: iload_2
    //   1063: ifne -> 827
    //   1066: iconst_1
    //   1067: istore #25
    //   1069: aload #13
    //   1071: iconst_0
    //   1072: iload #25
    //   1074: bipush #24
    //   1076: ishl
    //   1077: iastore
    //   1078: iconst_1
    //   1079: istore #26
    //   1081: iload #26
    //   1083: bipush #10
    //   1085: if_icmpge -> 1126
    //   1088: iload #25
    //   1090: iconst_1
    //   1091: ishl
    //   1092: istore #25
    //   1094: iload #25
    //   1096: sipush #256
    //   1099: if_icmplt -> 1109
    //   1102: iload #25
    //   1104: iload #14
    //   1106: ixor
    //   1107: istore #25
    //   1109: aload #13
    //   1111: iload #26
    //   1113: iload #25
    //   1115: bipush #24
    //   1117: ishl
    //   1118: iastore
    //   1119: iinc #26, 1
    //   1122: iload_2
    //   1123: ifne -> 1081
    //   1126: iconst_4
    //   1127: istore #26
    //   1129: iload #26
    //   1131: bipush #6
    //   1133: iadd
    //   1134: istore #27
    //   1136: iconst_4
    //   1137: iload #27
    //   1139: iconst_1
    //   1140: iadd
    //   1141: imul
    //   1142: istore #28
    //   1144: iload #28
    //   1146: newarray int
    //   1148: astore #29
    //   1150: iload #28
    //   1152: newarray int
    //   1154: astore #30
    //   1156: iconst_0
    //   1157: istore #25
    //   1159: iconst_0
    //   1160: istore #32
    //   1162: iconst_0
    //   1163: istore #33
    //   1165: iload #32
    //   1167: iload #26
    //   1169: if_icmpge -> 1237
    //   1172: aload #29
    //   1174: iload #32
    //   1176: aload #5
    //   1178: iload #33
    //   1180: baload
    //   1181: bipush #24
    //   1183: ishl
    //   1184: aload #5
    //   1186: iload #33
    //   1188: iconst_1
    //   1189: iadd
    //   1190: baload
    //   1191: sipush #255
    //   1194: iand
    //   1195: bipush #16
    //   1197: ishl
    //   1198: ior
    //   1199: aload #5
    //   1201: iload #33
    //   1203: iconst_2
    //   1204: iadd
    //   1205: baload
    //   1206: sipush #255
    //   1209: iand
    //   1210: bipush #8
    //   1212: ishl
    //   1213: ior
    //   1214: aload #5
    //   1216: iload #33
    //   1218: iconst_3
    //   1219: iadd
    //   1220: baload
    //   1221: sipush #255
    //   1224: iand
    //   1225: ior
    //   1226: iastore
    //   1227: iinc #32, 1
    //   1230: iinc #33, 4
    //   1233: iload_2
    //   1234: ifne -> 1165
    //   1237: iload #26
    //   1239: istore #32
    //   1241: iconst_0
    //   1242: istore #33
    //   1244: iload #32
    //   1246: iload #28
    //   1248: if_icmpge -> 1375
    //   1251: aload #29
    //   1253: iload #32
    //   1255: iconst_1
    //   1256: isub
    //   1257: iaload
    //   1258: istore #31
    //   1260: iload #33
    //   1262: ifne -> 1349
    //   1265: iload #26
    //   1267: istore #33
    //   1269: aload #8
    //   1271: iload #31
    //   1273: bipush #16
    //   1275: iushr
    //   1276: sipush #255
    //   1279: iand
    //   1280: baload
    //   1281: bipush #24
    //   1283: ishl
    //   1284: aload #8
    //   1286: iload #31
    //   1288: bipush #8
    //   1290: iushr
    //   1291: sipush #255
    //   1294: iand
    //   1295: baload
    //   1296: sipush #255
    //   1299: iand
    //   1300: bipush #16
    //   1302: ishl
    //   1303: ior
    //   1304: aload #8
    //   1306: iload #31
    //   1308: sipush #255
    //   1311: iand
    //   1312: baload
    //   1313: sipush #255
    //   1316: iand
    //   1317: bipush #8
    //   1319: ishl
    //   1320: ior
    //   1321: aload #8
    //   1323: iload #31
    //   1325: bipush #24
    //   1327: iushr
    //   1328: baload
    //   1329: sipush #255
    //   1332: iand
    //   1333: ior
    //   1334: istore #31
    //   1336: iload #31
    //   1338: aload #13
    //   1340: iload #25
    //   1342: iinc #25, 1
    //   1345: iaload
    //   1346: ixor
    //   1347: istore #31
    //   1349: aload #29
    //   1351: iload #32
    //   1353: aload #29
    //   1355: iload #32
    //   1357: iload #26
    //   1359: isub
    //   1360: iaload
    //   1361: iload #31
    //   1363: ixor
    //   1364: iastore
    //   1365: iinc #32, 1
    //   1368: iinc #33, -1
    //   1371: iload_2
    //   1372: ifne -> 1244
    //   1375: iconst_0
    //   1376: istore #32
    //   1378: iconst_4
    //   1379: iload #27
    //   1381: imul
    //   1382: istore #33
    //   1384: aload #30
    //   1386: iload #32
    //   1388: aload #29
    //   1390: iload #33
    //   1392: iaload
    //   1393: iastore
    //   1394: aload #30
    //   1396: iload #32
    //   1398: iconst_1
    //   1399: iadd
    //   1400: aload #29
    //   1402: iload #33
    //   1404: iconst_1
    //   1405: iadd
    //   1406: iaload
    //   1407: iastore
    //   1408: aload #30
    //   1410: iload #32
    //   1412: iconst_2
    //   1413: iadd
    //   1414: aload #29
    //   1416: iload #33
    //   1418: iconst_2
    //   1419: iadd
    //   1420: iaload
    //   1421: iastore
    //   1422: aload #30
    //   1424: iload #32
    //   1426: iconst_3
    //   1427: iadd
    //   1428: aload #29
    //   1430: iload #33
    //   1432: iconst_3
    //   1433: iadd
    //   1434: iaload
    //   1435: iastore
    //   1436: iinc #32, 4
    //   1439: iinc #33, -4
    //   1442: iconst_1
    //   1443: istore #35
    //   1445: iload #35
    //   1447: iload #27
    //   1449: if_icmpge -> 1813
    //   1452: aload #29
    //   1454: iload #33
    //   1456: iaload
    //   1457: istore #34
    //   1459: aload #30
    //   1461: iload #32
    //   1463: aload #9
    //   1465: aload #8
    //   1467: iload #34
    //   1469: bipush #24
    //   1471: iushr
    //   1472: baload
    //   1473: sipush #255
    //   1476: iand
    //   1477: iaload
    //   1478: aload #10
    //   1480: aload #8
    //   1482: iload #34
    //   1484: bipush #16
    //   1486: iushr
    //   1487: sipush #255
    //   1490: iand
    //   1491: baload
    //   1492: sipush #255
    //   1495: iand
    //   1496: iaload
    //   1497: ixor
    //   1498: aload #11
    //   1500: aload #8
    //   1502: iload #34
    //   1504: bipush #8
    //   1506: iushr
    //   1507: sipush #255
    //   1510: iand
    //   1511: baload
    //   1512: sipush #255
    //   1515: iand
    //   1516: iaload
    //   1517: ixor
    //   1518: aload #12
    //   1520: aload #8
    //   1522: iload #34
    //   1524: sipush #255
    //   1527: iand
    //   1528: baload
    //   1529: sipush #255
    //   1532: iand
    //   1533: iaload
    //   1534: ixor
    //   1535: iastore
    //   1536: aload #29
    //   1538: iload #33
    //   1540: iconst_1
    //   1541: iadd
    //   1542: iaload
    //   1543: istore #34
    //   1545: aload #30
    //   1547: iload #32
    //   1549: iconst_1
    //   1550: iadd
    //   1551: aload #9
    //   1553: aload #8
    //   1555: iload #34
    //   1557: bipush #24
    //   1559: iushr
    //   1560: baload
    //   1561: sipush #255
    //   1564: iand
    //   1565: iaload
    //   1566: aload #10
    //   1568: aload #8
    //   1570: iload #34
    //   1572: bipush #16
    //   1574: iushr
    //   1575: sipush #255
    //   1578: iand
    //   1579: baload
    //   1580: sipush #255
    //   1583: iand
    //   1584: iaload
    //   1585: ixor
    //   1586: aload #11
    //   1588: aload #8
    //   1590: iload #34
    //   1592: bipush #8
    //   1594: iushr
    //   1595: sipush #255
    //   1598: iand
    //   1599: baload
    //   1600: sipush #255
    //   1603: iand
    //   1604: iaload
    //   1605: ixor
    //   1606: aload #12
    //   1608: aload #8
    //   1610: iload #34
    //   1612: sipush #255
    //   1615: iand
    //   1616: baload
    //   1617: sipush #255
    //   1620: iand
    //   1621: iaload
    //   1622: ixor
    //   1623: iastore
    //   1624: aload #29
    //   1626: iload #33
    //   1628: iconst_2
    //   1629: iadd
    //   1630: iaload
    //   1631: istore #34
    //   1633: aload #30
    //   1635: iload #32
    //   1637: iconst_2
    //   1638: iadd
    //   1639: aload #9
    //   1641: aload #8
    //   1643: iload #34
    //   1645: bipush #24
    //   1647: iushr
    //   1648: baload
    //   1649: sipush #255
    //   1652: iand
    //   1653: iaload
    //   1654: aload #10
    //   1656: aload #8
    //   1658: iload #34
    //   1660: bipush #16
    //   1662: iushr
    //   1663: sipush #255
    //   1666: iand
    //   1667: baload
    //   1668: sipush #255
    //   1671: iand
    //   1672: iaload
    //   1673: ixor
    //   1674: aload #11
    //   1676: aload #8
    //   1678: iload #34
    //   1680: bipush #8
    //   1682: iushr
    //   1683: sipush #255
    //   1686: iand
    //   1687: baload
    //   1688: sipush #255
    //   1691: iand
    //   1692: iaload
    //   1693: ixor
    //   1694: aload #12
    //   1696: aload #8
    //   1698: iload #34
    //   1700: sipush #255
    //   1703: iand
    //   1704: baload
    //   1705: sipush #255
    //   1708: iand
    //   1709: iaload
    //   1710: ixor
    //   1711: iastore
    //   1712: aload #29
    //   1714: iload #33
    //   1716: iconst_3
    //   1717: iadd
    //   1718: iaload
    //   1719: istore #34
    //   1721: aload #30
    //   1723: iload #32
    //   1725: iconst_3
    //   1726: iadd
    //   1727: aload #9
    //   1729: aload #8
    //   1731: iload #34
    //   1733: bipush #24
    //   1735: iushr
    //   1736: baload
    //   1737: sipush #255
    //   1740: iand
    //   1741: iaload
    //   1742: aload #10
    //   1744: aload #8
    //   1746: iload #34
    //   1748: bipush #16
    //   1750: iushr
    //   1751: sipush #255
    //   1754: iand
    //   1755: baload
    //   1756: sipush #255
    //   1759: iand
    //   1760: iaload
    //   1761: ixor
    //   1762: aload #11
    //   1764: aload #8
    //   1766: iload #34
    //   1768: bipush #8
    //   1770: iushr
    //   1771: sipush #255
    //   1774: iand
    //   1775: baload
    //   1776: sipush #255
    //   1779: iand
    //   1780: iaload
    //   1781: ixor
    //   1782: aload #12
    //   1784: aload #8
    //   1786: iload #34
    //   1788: sipush #255
    //   1791: iand
    //   1792: baload
    //   1793: sipush #255
    //   1796: iand
    //   1797: iaload
    //   1798: ixor
    //   1799: iastore
    //   1800: iinc #32, 4
    //   1803: iinc #33, -4
    //   1806: iinc #35, 1
    //   1809: iload_2
    //   1810: ifne -> 1445
    //   1813: aload #30
    //   1815: iload #32
    //   1817: aload #29
    //   1819: iload #33
    //   1821: iaload
    //   1822: iastore
    //   1823: aload #30
    //   1825: iload #32
    //   1827: iconst_1
    //   1828: iadd
    //   1829: aload #29
    //   1831: iload #33
    //   1833: iconst_1
    //   1834: iadd
    //   1835: iaload
    //   1836: iastore
    //   1837: aload #30
    //   1839: iload #32
    //   1841: iconst_2
    //   1842: iadd
    //   1843: aload #29
    //   1845: iload #33
    //   1847: iconst_2
    //   1848: iadd
    //   1849: iaload
    //   1850: iastore
    //   1851: aload #30
    //   1853: iload #32
    //   1855: iconst_3
    //   1856: iadd
    //   1857: aload #29
    //   1859: iload #33
    //   1861: iconst_3
    //   1862: iadd
    //   1863: iaload
    //   1864: iastore
    //   1865: iconst_0
    //   1866: newarray byte
    //   1868: astore #35
    //   1870: aload #6
    //   1872: arraylength
    //   1873: bipush #16
    //   1875: irem
    //   1876: ifeq -> 1900
    //   1879: new java/lang/Exception
    //   1882: dup
    //   1883: sipush #-4841
    //   1886: sipush #-24047
    //   1889: invokestatic a : (II)Ljava/lang/String;
    //   1892: invokespecial <init> : (Ljava/lang/String;)V
    //   1895: athrow
    //   1896: invokestatic a : (Ljava/lang/Throwable;)Ljava/lang/Throwable;
    //   1899: athrow
    //   1900: bipush #10
    //   1902: istore #36
    //   1904: sipush #-4835
    //   1907: sipush #256
    //   1910: newarray byte
    //   1912: astore #37
    //   1914: sipush #-11137
    //   1917: sipush #256
    //   1920: newarray int
    //   1922: astore #38
    //   1924: sipush #256
    //   1927: newarray int
    //   1929: astore #39
    //   1931: sipush #256
    //   1934: newarray int
    //   1936: astore #40
    //   1938: sipush #256
    //   1941: newarray int
    //   1943: astore #41
    //   1945: sipush #283
    //   1948: istore #14
    //   1950: invokestatic a : (II)Ljava/lang/String;
    //   1953: astore #42
    //   1955: iconst_0
    //   1956: istore #16
    //   1958: iload #16
    //   1960: sipush #256
    //   1963: if_icmpge -> 2190
    //   1966: aload #42
    //   1968: iload #16
    //   1970: iconst_1
    //   1971: iushr
    //   1972: invokevirtual charAt : (I)C
    //   1975: istore #43
    //   1977: iload #16
    //   1979: iconst_1
    //   1980: iand
    //   1981: ifne -> 1996
    //   1984: iload #43
    //   1986: bipush #8
    //   1988: iushr
    //   1989: goto -> 1998
    //   1992: invokestatic a : (Ljava/lang/Throwable;)Ljava/lang/Throwable;
    //   1995: athrow
    //   1996: iload #43
    //   1998: i2b
    //   1999: sipush #255
    //   2002: iand
    //   2003: istore #15
    //   2005: iload #16
    //   2007: iconst_1
    //   2008: ishl
    //   2009: istore #17
    //   2011: iload #17
    //   2013: sipush #256
    //   2016: if_icmplt -> 2026
    //   2019: iload #17
    //   2021: iload #14
    //   2023: ixor
    //   2024: istore #17
    //   2026: iload #17
    //   2028: iconst_1
    //   2029: ishl
    //   2030: istore #18
    //   2032: iload #18
    //   2034: sipush #256
    //   2037: if_icmplt -> 2047
    //   2040: iload #18
    //   2042: iload #14
    //   2044: ixor
    //   2045: istore #18
    //   2047: iload #18
    //   2049: iconst_1
    //   2050: ishl
    //   2051: istore #19
    //   2053: iload #19
    //   2055: sipush #256
    //   2058: if_icmplt -> 2068
    //   2061: iload #19
    //   2063: iload #14
    //   2065: ixor
    //   2066: istore #19
    //   2068: iload #19
    //   2070: iload #16
    //   2072: ixor
    //   2073: istore #20
    //   2075: iload #20
    //   2077: iload #17
    //   2079: ixor
    //   2080: istore #21
    //   2082: iload #20
    //   2084: iload #18
    //   2086: ixor
    //   2087: istore #22
    //   2089: iload #19
    //   2091: iload #18
    //   2093: ixor
    //   2094: iload #17
    //   2096: ixor
    //   2097: istore #23
    //   2099: aload #37
    //   2101: iload #15
    //   2103: iload #16
    //   2105: i2b
    //   2106: bastore
    //   2107: aload #38
    //   2109: iload #15
    //   2111: iload #23
    //   2113: bipush #24
    //   2115: ishl
    //   2116: iload #20
    //   2118: bipush #16
    //   2120: ishl
    //   2121: ior
    //   2122: iload #22
    //   2124: bipush #8
    //   2126: ishl
    //   2127: ior
    //   2128: iload #21
    //   2130: ior
    //   2131: dup
    //   2132: istore #24
    //   2134: iastore
    //   2135: aload #39
    //   2137: iload #15
    //   2139: iload #24
    //   2141: bipush #8
    //   2143: iushr
    //   2144: iload #24
    //   2146: bipush #24
    //   2148: ishl
    //   2149: ior
    //   2150: iastore
    //   2151: aload #40
    //   2153: iload #15
    //   2155: iload #24
    //   2157: bipush #16
    //   2159: iushr
    //   2160: iload #24
    //   2162: bipush #16
    //   2164: ishl
    //   2165: ior
    //   2166: iastore
    //   2167: aload #41
    //   2169: iload #15
    //   2171: iload #24
    //   2173: bipush #24
    //   2175: iushr
    //   2176: iload #24
    //   2178: bipush #8
    //   2180: ishl
    //   2181: ior
    //   2182: iastore
    //   2183: iinc #16, 1
    //   2186: iload_2
    //   2187: ifne -> 1958
    //   2190: aload #6
    //   2192: arraylength
    //   2193: newarray byte
    //   2195: astore #43
    //   2197: iconst_0
    //   2198: istore #44
    //   2200: iload #44
    //   2202: aload #6
    //   2204: arraylength
    //   2205: bipush #16
    //   2207: idiv
    //   2208: if_icmpge -> 3122
    //   2211: bipush #16
    //   2213: newarray byte
    //   2215: astore #45
    //   2217: bipush #16
    //   2219: newarray byte
    //   2221: astore #46
    //   2223: iconst_0
    //   2224: istore #47
    //   2226: iload #47
    //   2228: bipush #16
    //   2230: if_icmpge -> 2256
    //   2233: aload #45
    //   2235: iload #47
    //   2237: aload #6
    //   2239: iload #47
    //   2241: iload #44
    //   2243: bipush #16
    //   2245: imul
    //   2246: iadd
    //   2247: baload
    //   2248: bastore
    //   2249: iinc #47, 1
    //   2252: iload_2
    //   2253: ifne -> 2226
    //   2256: iconst_0
    //   2257: istore #47
    //   2259: aload #45
    //   2261: iconst_0
    //   2262: baload
    //   2263: bipush #24
    //   2265: ishl
    //   2266: aload #45
    //   2268: iconst_1
    //   2269: baload
    //   2270: sipush #255
    //   2273: iand
    //   2274: bipush #16
    //   2276: ishl
    //   2277: ior
    //   2278: aload #45
    //   2280: iconst_2
    //   2281: baload
    //   2282: sipush #255
    //   2285: iand
    //   2286: bipush #8
    //   2288: ishl
    //   2289: ior
    //   2290: aload #45
    //   2292: iconst_3
    //   2293: baload
    //   2294: sipush #255
    //   2297: iand
    //   2298: ior
    //   2299: aload #30
    //   2301: iconst_0
    //   2302: iaload
    //   2303: ixor
    //   2304: istore #49
    //   2306: aload #45
    //   2308: iconst_4
    //   2309: baload
    //   2310: bipush #24
    //   2312: ishl
    //   2313: aload #45
    //   2315: iconst_5
    //   2316: baload
    //   2317: sipush #255
    //   2320: iand
    //   2321: bipush #16
    //   2323: ishl
    //   2324: ior
    //   2325: aload #45
    //   2327: bipush #6
    //   2329: baload
    //   2330: sipush #255
    //   2333: iand
    //   2334: bipush #8
    //   2336: ishl
    //   2337: ior
    //   2338: aload #45
    //   2340: bipush #7
    //   2342: baload
    //   2343: sipush #255
    //   2346: iand
    //   2347: ior
    //   2348: aload #30
    //   2350: iconst_1
    //   2351: iaload
    //   2352: ixor
    //   2353: istore #50
    //   2355: aload #45
    //   2357: bipush #8
    //   2359: baload
    //   2360: bipush #24
    //   2362: ishl
    //   2363: aload #45
    //   2365: bipush #9
    //   2367: baload
    //   2368: sipush #255
    //   2371: iand
    //   2372: bipush #16
    //   2374: ishl
    //   2375: ior
    //   2376: aload #45
    //   2378: bipush #10
    //   2380: baload
    //   2381: sipush #255
    //   2384: iand
    //   2385: bipush #8
    //   2387: ishl
    //   2388: ior
    //   2389: aload #45
    //   2391: bipush #11
    //   2393: baload
    //   2394: sipush #255
    //   2397: iand
    //   2398: ior
    //   2399: aload #30
    //   2401: iconst_2
    //   2402: iaload
    //   2403: ixor
    //   2404: istore #51
    //   2406: aload #45
    //   2408: bipush #12
    //   2410: baload
    //   2411: bipush #24
    //   2413: ishl
    //   2414: aload #45
    //   2416: bipush #13
    //   2418: baload
    //   2419: sipush #255
    //   2422: iand
    //   2423: bipush #16
    //   2425: ishl
    //   2426: ior
    //   2427: aload #45
    //   2429: bipush #14
    //   2431: baload
    //   2432: sipush #255
    //   2435: iand
    //   2436: bipush #8
    //   2438: ishl
    //   2439: ior
    //   2440: aload #45
    //   2442: bipush #15
    //   2444: baload
    //   2445: sipush #255
    //   2448: iand
    //   2449: ior
    //   2450: aload #30
    //   2452: iconst_3
    //   2453: iaload
    //   2454: ixor
    //   2455: istore #52
    //   2457: iconst_1
    //   2458: istore #53
    //   2460: iload #53
    //   2462: iload #36
    //   2464: if_icmpge -> 2707
    //   2467: iinc #47, 4
    //   2470: aload #38
    //   2472: iload #49
    //   2474: bipush #24
    //   2476: iushr
    //   2477: iaload
    //   2478: aload #39
    //   2480: iload #52
    //   2482: bipush #16
    //   2484: iushr
    //   2485: sipush #255
    //   2488: iand
    //   2489: iaload
    //   2490: ixor
    //   2491: aload #40
    //   2493: iload #51
    //   2495: bipush #8
    //   2497: iushr
    //   2498: sipush #255
    //   2501: iand
    //   2502: iaload
    //   2503: ixor
    //   2504: aload #41
    //   2506: iload #50
    //   2508: sipush #255
    //   2511: iand
    //   2512: iaload
    //   2513: ixor
    //   2514: aload #30
    //   2516: iload #47
    //   2518: iaload
    //   2519: ixor
    //   2520: istore #54
    //   2522: aload #38
    //   2524: iload #50
    //   2526: bipush #24
    //   2528: iushr
    //   2529: iaload
    //   2530: aload #39
    //   2532: iload #49
    //   2534: bipush #16
    //   2536: iushr
    //   2537: sipush #255
    //   2540: iand
    //   2541: iaload
    //   2542: ixor
    //   2543: aload #40
    //   2545: iload #52
    //   2547: bipush #8
    //   2549: iushr
    //   2550: sipush #255
    //   2553: iand
    //   2554: iaload
    //   2555: ixor
    //   2556: aload #41
    //   2558: iload #51
    //   2560: sipush #255
    //   2563: iand
    //   2564: iaload
    //   2565: ixor
    //   2566: aload #30
    //   2568: iload #47
    //   2570: iconst_1
    //   2571: iadd
    //   2572: iaload
    //   2573: ixor
    //   2574: istore #55
    //   2576: aload #38
    //   2578: iload #51
    //   2580: bipush #24
    //   2582: iushr
    //   2583: iaload
    //   2584: aload #39
    //   2586: iload #50
    //   2588: bipush #16
    //   2590: iushr
    //   2591: sipush #255
    //   2594: iand
    //   2595: iaload
    //   2596: ixor
    //   2597: aload #40
    //   2599: iload #49
    //   2601: bipush #8
    //   2603: iushr
    //   2604: sipush #255
    //   2607: iand
    //   2608: iaload
    //   2609: ixor
    //   2610: aload #41
    //   2612: iload #52
    //   2614: sipush #255
    //   2617: iand
    //   2618: iaload
    //   2619: ixor
    //   2620: aload #30
    //   2622: iload #47
    //   2624: iconst_2
    //   2625: iadd
    //   2626: iaload
    //   2627: ixor
    //   2628: istore #56
    //   2630: aload #38
    //   2632: iload #52
    //   2634: bipush #24
    //   2636: iushr
    //   2637: iaload
    //   2638: aload #39
    //   2640: iload #51
    //   2642: bipush #16
    //   2644: iushr
    //   2645: sipush #255
    //   2648: iand
    //   2649: iaload
    //   2650: ixor
    //   2651: aload #40
    //   2653: iload #50
    //   2655: bipush #8
    //   2657: iushr
    //   2658: sipush #255
    //   2661: iand
    //   2662: iaload
    //   2663: ixor
    //   2664: aload #41
    //   2666: iload #49
    //   2668: sipush #255
    //   2671: iand
    //   2672: iaload
    //   2673: ixor
    //   2674: aload #30
    //   2676: iload #47
    //   2678: iconst_3
    //   2679: iadd
    //   2680: iaload
    //   2681: ixor
    //   2682: istore #57
    //   2684: iload #54
    //   2686: istore #49
    //   2688: iload #55
    //   2690: istore #50
    //   2692: iload #56
    //   2694: istore #51
    //   2696: iload #57
    //   2698: istore #52
    //   2700: iinc #53, 1
    //   2703: iload_2
    //   2704: ifne -> 2460
    //   2707: iinc #47, 4
    //   2710: aload #30
    //   2712: iload #47
    //   2714: iaload
    //   2715: istore #48
    //   2717: aload #46
    //   2719: iconst_0
    //   2720: aload #37
    //   2722: iload #49
    //   2724: bipush #24
    //   2726: iushr
    //   2727: baload
    //   2728: iload #48
    //   2730: bipush #24
    //   2732: iushr
    //   2733: ixor
    //   2734: i2b
    //   2735: bastore
    //   2736: aload #46
    //   2738: iconst_1
    //   2739: aload #37
    //   2741: iload #52
    //   2743: bipush #16
    //   2745: iushr
    //   2746: sipush #255
    //   2749: iand
    //   2750: baload
    //   2751: iload #48
    //   2753: bipush #16
    //   2755: iushr
    //   2756: ixor
    //   2757: i2b
    //   2758: bastore
    //   2759: aload #46
    //   2761: iconst_2
    //   2762: aload #37
    //   2764: iload #51
    //   2766: bipush #8
    //   2768: iushr
    //   2769: sipush #255
    //   2772: iand
    //   2773: baload
    //   2774: iload #48
    //   2776: bipush #8
    //   2778: iushr
    //   2779: ixor
    //   2780: i2b
    //   2781: bastore
    //   2782: aload #46
    //   2784: iconst_3
    //   2785: aload #37
    //   2787: iload #50
    //   2789: sipush #255
    //   2792: iand
    //   2793: baload
    //   2794: iload #48
    //   2796: ixor
    //   2797: i2b
    //   2798: bastore
    //   2799: aload #30
    //   2801: iload #47
    //   2803: iconst_1
    //   2804: iadd
    //   2805: iaload
    //   2806: istore #48
    //   2808: aload #46
    //   2810: iconst_4
    //   2811: aload #37
    //   2813: iload #50
    //   2815: bipush #24
    //   2817: iushr
    //   2818: baload
    //   2819: iload #48
    //   2821: bipush #24
    //   2823: iushr
    //   2824: ixor
    //   2825: i2b
    //   2826: bastore
    //   2827: aload #46
    //   2829: iconst_5
    //   2830: aload #37
    //   2832: iload #49
    //   2834: bipush #16
    //   2836: iushr
    //   2837: sipush #255
    //   2840: iand
    //   2841: baload
    //   2842: iload #48
    //   2844: bipush #16
    //   2846: iushr
    //   2847: ixor
    //   2848: i2b
    //   2849: bastore
    //   2850: aload #46
    //   2852: bipush #6
    //   2854: aload #37
    //   2856: iload #52
    //   2858: bipush #8
    //   2860: iushr
    //   2861: sipush #255
    //   2864: iand
    //   2865: baload
    //   2866: iload #48
    //   2868: bipush #8
    //   2870: iushr
    //   2871: ixor
    //   2872: i2b
    //   2873: bastore
    //   2874: aload #46
    //   2876: bipush #7
    //   2878: aload #37
    //   2880: iload #51
    //   2882: sipush #255
    //   2885: iand
    //   2886: baload
    //   2887: iload #48
    //   2889: ixor
    //   2890: i2b
    //   2891: bastore
    //   2892: aload #30
    //   2894: iload #47
    //   2896: iconst_2
    //   2897: iadd
    //   2898: iaload
    //   2899: istore #48
    //   2901: aload #46
    //   2903: bipush #8
    //   2905: aload #37
    //   2907: iload #51
    //   2909: bipush #24
    //   2911: iushr
    //   2912: baload
    //   2913: iload #48
    //   2915: bipush #24
    //   2917: iushr
    //   2918: ixor
    //   2919: i2b
    //   2920: bastore
    //   2921: aload #46
    //   2923: bipush #9
    //   2925: aload #37
    //   2927: iload #50
    //   2929: bipush #16
    //   2931: iushr
    //   2932: sipush #255
    //   2935: iand
    //   2936: baload
    //   2937: iload #48
    //   2939: bipush #16
    //   2941: iushr
    //   2942: ixor
    //   2943: i2b
    //   2944: bastore
    //   2945: aload #46
    //   2947: bipush #10
    //   2949: aload #37
    //   2951: iload #49
    //   2953: bipush #8
    //   2955: iushr
    //   2956: sipush #255
    //   2959: iand
    //   2960: baload
    //   2961: iload #48
    //   2963: bipush #8
    //   2965: iushr
    //   2966: ixor
    //   2967: i2b
    //   2968: bastore
    //   2969: aload #46
    //   2971: bipush #11
    //   2973: aload #37
    //   2975: iload #52
    //   2977: sipush #255
    //   2980: iand
    //   2981: baload
    //   2982: iload #48
    //   2984: ixor
    //   2985: i2b
    //   2986: bastore
    //   2987: aload #30
    //   2989: iload #47
    //   2991: iconst_3
    //   2992: iadd
    //   2993: iaload
    //   2994: istore #48
    //   2996: aload #46
    //   2998: bipush #12
    //   3000: aload #37
    //   3002: iload #52
    //   3004: bipush #24
    //   3006: iushr
    //   3007: baload
    //   3008: iload #48
    //   3010: bipush #24
    //   3012: iushr
    //   3013: ixor
    //   3014: i2b
    //   3015: bastore
    //   3016: aload #46
    //   3018: bipush #13
    //   3020: aload #37
    //   3022: iload #51
    //   3024: bipush #16
    //   3026: iushr
    //   3027: sipush #255
    //   3030: iand
    //   3031: baload
    //   3032: iload #48
    //   3034: bipush #16
    //   3036: iushr
    //   3037: ixor
    //   3038: i2b
    //   3039: bastore
    //   3040: aload #46
    //   3042: bipush #14
    //   3044: aload #37
    //   3046: iload #50
    //   3048: bipush #8
    //   3050: iushr
    //   3051: sipush #255
    //   3054: iand
    //   3055: baload
    //   3056: iload #48
    //   3058: bipush #8
    //   3060: iushr
    //   3061: ixor
    //   3062: i2b
    //   3063: bastore
    //   3064: aload #46
    //   3066: bipush #15
    //   3068: aload #37
    //   3070: iload #49
    //   3072: sipush #255
    //   3075: iand
    //   3076: baload
    //   3077: iload #48
    //   3079: ixor
    //   3080: i2b
    //   3081: bastore
    //   3082: iconst_0
    //   3083: istore #53
    //   3085: iload #53
    //   3087: bipush #16
    //   3089: if_icmpge -> 3115
    //   3092: aload #43
    //   3094: iload #53
    //   3096: iload #44
    //   3098: bipush #16
    //   3100: imul
    //   3101: iadd
    //   3102: aload #46
    //   3104: iload #53
    //   3106: baload
    //   3107: bastore
    //   3108: iinc #53, 1
    //   3111: iload_2
    //   3112: ifne -> 3085
    //   3115: iinc #44, 1
    //   3118: iload_2
    //   3119: ifne -> 2200
    //   3122: aload #43
    //   3124: arraylength
    //   3125: ifle -> 3206
    //   3128: aload #43
    //   3130: aload #43
    //   3132: arraylength
    //   3133: iconst_1
    //   3134: isub
    //   3135: baload
    //   3136: istore #44
    //   3138: iload #44
    //   3140: bipush #16
    //   3142: if_icmple -> 3153
    //   3145: aload #43
    //   3147: astore #35
    //   3149: iload_2
    //   3150: ifne -> 3206
    //   3153: aload #43
    //   3155: arraylength
    //   3156: iload #44
    //   3158: isub
    //   3159: newarray byte
    //   3161: astore #35
    //   3163: iconst_0
    //   3164: istore #45
    //   3166: iload #45
    //   3168: aload #35
    //   3170: arraylength
    //   3171: if_icmpge -> 3206
    //   3174: iload #45
    //   3176: aload #43
    //   3178: arraylength
    //   3179: if_icmpge -> 3206
    //   3182: aload #35
    //   3184: iload #45
    //   3186: aload #43
    //   3188: iload #45
    //   3190: baload
    //   3191: bastore
    //   3192: iinc #45, 1
    //   3195: iload_2
    //   3196: ifne -> 3166
    //   3199: goto -> 3206
    //   3202: invokestatic a : (Ljava/lang/Throwable;)Ljava/lang/Throwable;
    //   3205: athrow
    //   3206: aload #35
    //   3208: astore #7
    //   3210: getstatic burp/Ze0w.ZT : Ljava/lang/String;
    //   3213: getstatic burp/Zzyr.Za : Ljava/lang/Object;
    //   3216: checkcast java/math/BigInteger
    //   3219: invokevirtual intValue : ()I
    //   3222: bipush #32
    //   3224: irem
    //   3225: invokestatic abs : (I)I
    //   3228: invokevirtual charAt : (I)C
    //   3231: getstatic burp/Ztpg.Zr : Ljava/lang/String;
    //   3234: getstatic burp/Zzyr.Za : Ljava/lang/Object;
    //   3237: checkcast java/math/BigInteger
    //   3240: invokevirtual intValue : ()I
    //   3243: bipush #32
    //   3245: irem
    //   3246: invokestatic abs : (I)I
    //   3249: invokevirtual charAt : (I)C
    //   3252: if_icmpgt -> 3359
    //   3255: getstatic burp/Zf.Zd : Ljava/lang/String;
    //   3258: getstatic burp/Zmlu.Zi : Ljava/lang/Object;
    //   3261: checkcast java/math/BigInteger
    //   3264: invokevirtual intValue : ()I
    //   3267: bipush #32
    //   3269: irem
    //   3270: invokestatic abs : (I)I
    //   3273: invokevirtual charAt : (I)C
    //   3276: getstatic burp/Zk9s.ZM : Ljava/lang/String;
    //   3279: getstatic burp/Zbsc.ZA : Ljava/lang/Object;
    //   3282: checkcast java/math/BigInteger
    //   3285: invokevirtual intValue : ()I
    //   3288: bipush #32
    //   3290: irem
    //   3291: invokestatic abs : (I)I
    //   3294: invokevirtual charAt : (I)C
    //   3297: if_icmpgt -> 3359
    //   3300: goto -> 3307
    //   3303: invokestatic a : (Ljava/lang/Throwable;)Ljava/lang/Throwable;
    //   3306: athrow
    //   3307: getstatic burp/Zza3.ZU : Ljava/lang/String;
    //   3310: getstatic burp/Zmtr.Zv : Ljava/lang/Object;
    //   3313: checkcast java/math/BigInteger
    //   3316: invokevirtual intValue : ()I
    //   3319: bipush #32
    //   3321: irem
    //   3322: invokestatic abs : (I)I
    //   3325: invokevirtual charAt : (I)C
    //   3328: getstatic burp/Zts_.Zx : Ljava/lang/String;
    //   3331: getstatic burp/Ztc2.ZM : Ljava/lang/Object;
    //   3334: checkcast java/math/BigInteger
    //   3337: invokevirtual intValue : ()I
    //   3340: bipush #32
    //   3342: irem
    //   3343: invokestatic abs : (I)I
    //   3346: invokevirtual charAt : (I)C
    //   3349: if_icmple -> 3367
    //   3352: goto -> 3359
    //   3355: invokestatic a : (Ljava/lang/Throwable;)Ljava/lang/Throwable;
    //   3358: athrow
    //   3359: iconst_1
    //   3360: goto -> 3368
    //   3363: invokestatic a : (Ljava/lang/Throwable;)Ljava/lang/Throwable;
    //   3366: athrow
    //   3367: iconst_0
    //   3368: ireturn
    //   3369: astore_3
    //   3370: new java/lang/Exception
    //   3373: dup
    //   3374: aload_3
    //   3375: invokevirtual getMessage : ()Ljava/lang/String;
    //   3378: invokespecial <init> : (Ljava/lang/String;)V
    //   3381: athrow
    // Exception table:
    //   from	to	target	type
    //   4	3368	3369	java/lang/Throwable
    //   64	78	78	java/lang/Throwable
    //   89	102	105	java/lang/Throwable
    //   94	117	120	java/lang/Throwable
    //   109	135	138	java/lang/Throwable
    //   124	165	168	java/lang/Throwable
    //   228	255	258	java/lang/Throwable
    //   245	276	279	java/lang/Throwable
    //   262	306	309	java/lang/Throwable
    //   283	317	317	java/lang/Throwable
    //   328	344	347	java/lang/Throwable
    //   421	435	435	java/lang/Throwable
    //   446	459	462	java/lang/Throwable
    //   451	474	477	java/lang/Throwable
    //   466	492	495	java/lang/Throwable
    //   481	522	525	java/lang/Throwable
    //   585	612	615	java/lang/Throwable
    //   602	633	636	java/lang/Throwable
    //   619	663	666	java/lang/Throwable
    //   640	674	674	java/lang/Throwable
    //   685	701	704	java/lang/Throwable
    //   853	868	868	java/lang/Throwable
    //   1870	1896	1896	java/lang/Throwable
    //   1977	1992	1992	java/lang/Throwable
    //   3174	3199	3202	java/lang/Throwable
    //   3210	3300	3303	java/lang/Throwable
    //   3255	3352	3355	java/lang/Throwable
    //   3307	3363	3363	java/lang/Throwable
  }
  
  static void Zt(Object paramObject) {
    Zrpy.Zr = a(-4847, 29905);
    Zrpy.ZG = new BigInteger(a(-4844, -27747));
    boolean bool = Zt2e.ZK();
    try {
      try {
        if (Zmji.Zs.charAt(Math.abs(((BigInteger)Zzxv.ZZ).intValue() % 32)) > Zb9h.Zf.charAt(Math.abs(((BigInteger)Zrs0.Zz).intValue() % 32))) {
          try {
            Zrd4.Zp(Class.forName(a(-4840, -4545)));
            if (bool)
              Zz5d.Zi(Class.forName(a(-4842, 32574))); 
          } catch (Throwable throwable) {
            throw a(null);
          } 
          return;
        } 
      } catch (Throwable throwable) {
        throw a(null);
      } 
      Zz5d.Zi(Class.forName(a(-4842, 32574)));
    } catch (Throwable throwable) {}
  }
  
  static void ZG(Object[] paramArrayOfObject, Object paramObject) throws Throwable {}
  
  static {
    // Byte code:
    //   0: bipush #15
    //   2: anewarray java/lang/String
    //   5: astore #5
    //   7: iconst_0
    //   8: istore_3
    //   9: ldc 'sPl_=gn`%L%(<uT*9?.y `4`\\r9}[\\tA).+lg:5{[B\\t\\rXE\\t=|5\\r\\ttb 6;3&o#~P&~6<"????\\t1[+!\\b/?@cE QG?\\f!W' !\\r\\bl.<'
    //   11: dup
    //   12: astore_2
    //   13: invokevirtual length : ()I
    //   16: istore #4
    //   18: bipush #76
    //   20: istore_1
    //   21: iconst_m1
    //   22: istore_0
    //   23: bipush #11
    //   25: iinc #0, 1
    //   28: aload_2
    //   29: iload_0
    //   30: dup
    //   31: iload_1
    //   32: iadd
    //   33: invokevirtual substring : (II)Ljava/lang/String;
    //   36: iconst_m1
    //   37: goto -> 143
    //   40: aload #5
    //   42: swap
    //   43: iload_3
    //   44: iinc #3, 1
    //   47: swap
    //   48: aastore
    //   49: iload_0
    //   50: iload_1
    //   51: iadd
    //   52: dup
    //   53: istore_0
    //   54: iload #4
    //   56: if_icmpge -> 68
    //   59: aload_2
    //   60: iload_0
    //   61: invokevirtual charAt : (I)C
    //   64: istore_1
    //   65: goto -> 23
    //   68: ldc 'B_w5BXlMH\\b9Ji<I-*4X9^R<b:}}5^bM\\f~~lxZ\\n*'rt'
    //   70: dup
    //   71: astore_2
    //   72: invokevirtual length : ()I
    //   75: istore #4
    //   77: bipush #19
    //   79: istore_1
    //   80: iconst_m1
    //   81: istore_0
    //   82: bipush #85
    //   84: iinc #0, 1
    //   87: aload_2
    //   88: iload_0
    //   89: dup
    //   90: iload_1
    //   91: iadd
    //   92: invokevirtual substring : (II)Ljava/lang/String;
    //   95: iconst_0
    //   96: goto -> 143
    //   99: aload #5
    //   101: swap
    //   102: iload_3
    //   103: iinc #3, 1
    //   106: swap
    //   107: aastore
    //   108: iload_0
    //   109: iload_1
    //   110: iadd
    //   111: dup
    //   112: istore_0
    //   113: iload #4
    //   115: if_icmpge -> 127
    //   118: aload_2
    //   119: iload_0
    //   120: invokevirtual charAt : (I)C
    //   123: istore_1
    //   124: goto -> 82
    //   127: aload #5
    //   129: putstatic burp/Ztd3.a : [Ljava/lang/String;
    //   132: bipush #15
    //   134: anewarray java/lang/String
    //   137: putstatic burp/Ztd3.b : [Ljava/lang/String;
    //   140: goto -> 300
    //   143: dup_x2
    //   144: pop
    //   145: invokevirtual toCharArray : ()[C
    //   148: dup_x1
    //   149: arraylength
    //   150: dup_x2
    //   151: pop
    //   152: iconst_0
    //   153: istore #6
    //   155: dup2_x1
    //   156: pop2
    //   157: dup_x2
    //   158: iconst_1
    //   159: if_icmpgt -> 260
    //   162: dup2
    //   163: swap
    //   164: iload #6
    //   166: dup2_x1
    //   167: caload
    //   168: swap
    //   169: iload #6
    //   171: bipush #7
    //   173: irem
    //   174: tableswitch default -> 242, 0 -> 212, 1 -> 217, 2 -> 222, 3 -> 227, 4 -> 232, 5 -> 237
    //   212: bipush #77
    //   214: goto -> 244
    //   217: bipush #45
    //   219: goto -> 244
    //   222: bipush #58
    //   224: goto -> 244
    //   227: bipush #77
    //   229: goto -> 244
    //   232: bipush #33
    //   234: goto -> 244
    //   237: bipush #93
    //   239: goto -> 244
    //   242: bipush #64
    //   244: ixor
    //   245: ixor
    //   246: i2c
    //   247: castore
    //   248: iinc #6, 1
    //   251: dup
    //   252: ifne -> 260
    //   255: dup2
    //   256: dup_x1
    //   257: goto -> 166
    //   260: dup2_x1
    //   261: pop2
    //   262: dup_x2
    //   263: iload #6
    //   265: if_icmpgt -> 162
    //   268: pop
    //   269: new java/lang/String
    //   272: dup_x1
    //   273: swap
    //   274: invokespecial <init> : ([C)V
    //   277: invokevirtual intern : ()Ljava/lang/String;
    //   280: swap
    //   281: pop
    //   282: swap
    //   283: tableswitch default -> 40, 0 -> 99
    //   300: sipush #-4833
    //   303: sipush #-12702
    //   306: invokestatic a : (II)Ljava/lang/String;
    //   309: putstatic burp/Ztd3.ZC : Ljava/lang/String;
    //   312: new java/math/BigInteger
    //   315: dup
    //   316: sipush #-4838
    //   319: sipush #20808
    //   322: invokestatic a : (II)Ljava/lang/String;
    //   325: invokespecial <init> : (Ljava/lang/String;)V
    //   328: putstatic burp/Ztd3.ZX : Ljava/lang/Object;
    //   331: return
  }
  
  private static Throwable a(Throwable paramThrowable) {
    return paramThrowable;
  }
  
  private static String a(int paramInt1, int paramInt2) {
    int i = (paramInt1 ^ 0xFFFFED1A) & 0xFFFF;
    if (b[i] == null) {
      char[] arrayOfChar = a[i].toCharArray();
      switch (arrayOfChar[0] & 0xFF) {
        case 0:
        
        case 1:
        
        case 2:
        
        case 3:
        
        case 4:
        
        case 5:
        
        case 6:
        
        case 7:
        
        case 8:
        
        case 9:
        
        case 10:
        
        case 11:
        
        case 12:
        
        case 13:
        
        case 14:
        
        case 15:
        
        case 16:
        
        case 17:
        
        case 18:
        
        case 19:
        
        case 20:
        
        case 21:
        
        case 22:
        
        case 23:
        
        case 24:
        
        case 25:
        
        case 26:
        
        case 27:
        
        case 28:
        
        case 29:
        
        case 30:
        
        case 31:
        
        case 32:
        
        case 33:
        
        case 34:
        
        case 35:
        
        case 36:
        
        case 37:
        
        case 38:
        
        case 39:
        
        case 40:
        
        case 41:
        
        case 42:
        
        case 43:
        
        case 44:
        
        case 45:
        
        case 46:
        
        case 47:
        
        case 48:
        
        case 49:
        
        case 50:
        
        case 51:
        
        case 52:
        
        case 53:
        
        case 54:
        
        case 55:
        
        case 56:
        
        case 57:
        
        case 58:
        
        case 59:
        
        case 60:
        
        case 61:
        
        case 62:
        
        case 63:
        
        case 64:
        
        case 65:
        
        case 66:
        
        case 67:
        
        case 68:
        
        case 69:
        
        case 70:
        
        case 71:
        
        case 72:
        
        case 73:
        
        case 74:
        
        case 75:
        
        case 76:
        
        case 77:
        
        case 78:
        
        case 79:
        
        case 80:
        
        case 81:
        
        case 82:
        
        case 83:
        
        case 84:
        
        case 85:
        
        case 86:
        
        case 87:
        
        case 88:
        
        case 89:
        
        case 90:
        
        case 91:
        
        case 92:
        
        case 93:
        
        case 94:
        
        case 95:
        
        case 96:
        
        case 97:
        
        case 98:
        
        case 99:
        
        case 100:
        
        case 101:
        
        case 102:
        
        case 103:
        
        case 104:
        
        case 105:
        
        case 106:
        
        case 107:
        
        case 108:
        
        case 109:
        
        case 110:
        
        case 111:
        
        case 112:
        
        case 113:
        
        case 114:
        
        case 115:
        
        case 116:
        
        case 117:
        
        case 118:
        
        case 119:
        
        case 120:
        
        case 121:
        
        case 122:
        
        case 123:
        
        case 124:
        
        case 125:
        
        case 126:
        
        case 127:
        
        case 128:
        
        case 129:
        
        case 130:
        
        case 131:
        
        case 132:
        
        case 133:
        
        case 134:
        
        case 135:
        
        case 136:
        
        case 137:
        
        case 138:
        
        case 139:
        
        case 140:
        
        case 141:
        
        case 142:
        
        case 143:
        
        case 144:
        
        case 145:
        
        case 146:
        
        case 147:
        
        case 148:
        
        case 149:
        
        case 150:
        
        case 151:
        
        case 152:
        
        case 153:
        
        case 154:
        
        case 155:
        
        case 156:
        
        case 157:
        
        case 158:
        
        case 159:
        
        case 160:
        
        case 161:
        
        case 162:
        
        case 163:
        
        case 164:
        
        case 165:
        
        case 166:
        
        case 167:
        
        case 168:
        
        case 169:
        
        case 170:
        
        case 171:
        
        case 172:
        
        case 173:
        
        case 174:
        
        case 175:
        
        case 176:
        
        case 177:
        
        case 178:
        
        case 179:
        
        case 180:
        
        case 181:
        
        case 182:
        
        case 183:
        
        case 184:
        
        case 185:
        
        case 186:
        
        case 187:
        
        case 188:
        
        case 189:
        
        case 190:
        
        case 191:
        
        case 192:
        
        case 193:
        
        case 194:
        
        case 195:
        
        case 196:
        
        case 197:
        
        case 198:
        
        case 199:
        
        case 200:
        
        case 201:
        
        case 202:
        
        case 203:
        
        case 204:
        
        case 205:
        
        case 206:
        
        case 207:
        
        case 208:
        
        case 209:
        
        case 210:
        
        case 211:
        
        case 212:
        
        case 213:
        
        case 214:
        
        case 215:
        
        case 216:
        
        case 217:
        
        case 218:
        
        case 219:
        
        case 220:
        
        case 221:
        
        case 222:
        
        case 223:
        
        case 224:
        
        case 225:
        
        case 226:
        
        case 227:
        
        case 228:
        
        case 229:
        
        case 230:
        
        case 231:
        
        case 232:
        
        case 233:
        
        case 234:
        
        case 235:
        
        case 236:
        
        case 237:
        
        case 238:
        
        case 239:
        
        case 240:
        
        case 241:
        
        case 242:
        
        case 243:
        
        case 244:
        
        case 245:
        
        case 246:
        
        case 247:
        
        case 248:
        
        case 249:
        
        case 250:
        
        case 251:
        
        case 252:
        
        case 253:
        
        case 254:
        
        default:
          break;
      } 
      byte b1 = 60;
      int j = (paramInt2 & 0xFF) - b1;
      if (j < 0)
        j += 256; 
      int k = ((paramInt2 & 0xFFFF) >>> 8) - b1;
      if (k < 0)
        k += 256; 
      for (byte b2 = 0; b2 < arrayOfChar.length; b2++) {
        int m = b2 % 2;
        if (m == 0) {
          arrayOfChar[b2] = (char)(arrayOfChar[b2] ^ j);
          j = ((j >>> 3 | j << 5) ^ arrayOfChar[b2]) & 0xFF;
        } else {
          arrayOfChar[b2] = (char)(arrayOfChar[b2] ^ k);
          k = ((k >>> 3 | k << 5) ^ arrayOfChar[b2]) & 0xFF;
        } 
      } 
      b[i] = (new String(arrayOfChar)).intern();
    } 
    return b[i];
  }
}


/* Location:              C:\Program Files\BurpSuitePro\burpsuite_pro.jar!\burp\Ztd3.class
 * Java compiler version: 21 (65.0)
 * JD-Core Version:       1.1.3
 */