package burp;

import java.math.BigInteger;

class Ztdt extends ClassLoader {
  static String Zk;
  
  static Object ZN;
  
  private static final String[] a;
  
  private static final String[] b;
  
  static void Zx(Object[] paramArrayOfObject, Object paramObject) throws Throwable {}
  
  static void Zo(Object paramObject) {
    Zr9p.Za = a(26780, 30871);
    Zr9p.ZC = new BigInteger(a(26771, -12049));
    boolean bool = Zt2e.ZN();
    try {
      try {
        if (Zs9k.Zx.charAt(Math.abs(((BigInteger)Zl7k.ZS).intValue() % 32)) > Zs9k.Zx.charAt(Math.abs(((BigInteger)Zl7k.ZS).intValue() % 32))) {
          try {
            Zl1u.Zl(Class.forName(a(26779, 15712)));
            if (!bool)
              Zgvf.ZU(Class.forName(a(26768, -7316))); 
          } catch (Throwable throwable) {
            throw a(null);
          } 
          return;
        } 
      } catch (Throwable throwable) {
        throw a(null);
      } 
      Zgvf.ZU(Class.forName(a(26768, -7316)));
    } catch (Throwable throwable) {}
  }
  
  static boolean ZY(Object[] paramArrayOfObject, Object paramObject) throws Throwable {
    // Byte code:
    //   0: invokestatic ZN : ()Z
    //   3: istore_2
    //   4: sipush #26777
    //   7: sipush #6551
    //   10: invokestatic a : (II)Ljava/lang/String;
    //   13: invokestatic forName : (Ljava/lang/String;)Ljava/lang/Class;
    //   16: invokestatic ZD : (Ljava/lang/Object;)V
    //   19: new java/lang/StringBuilder
    //   22: dup
    //   23: invokespecial <init> : ()V
    //   26: astore_3
    //   27: iconst_0
    //   28: istore #4
    //   30: iload #4
    //   32: bipush #32
    //   34: if_icmpge -> 1367
    //   37: iload #4
    //   39: tableswitch default -> 1360, 0 -> 180, 1 -> 217, 2 -> 254, 3 -> 291, 4 -> 328, 5 -> 365, 6 -> 402, 7 -> 439, 8 -> 476, 9 -> 513, 10 -> 550, 11 -> 587, 12 -> 624, 13 -> 661, 14 -> 698, 15 -> 735, 16 -> 772, 17 -> 809, 18 -> 846, 19 -> 883, 20 -> 920, 21 -> 957, 22 -> 994, 23 -> 1031, 24 -> 1068, 25 -> 1105, 26 -> 1142, 27 -> 1179, 28 -> 1216, 29 -> 1253, 30 -> 1290, 31 -> 1327
    //   180: aload_3
    //   181: getstatic burp/Zzv.Zy : Ljava/lang/String;
    //   184: getstatic burp/Zl_1.ZL : Ljava/lang/Object;
    //   187: checkcast java/math/BigInteger
    //   190: invokevirtual intValue : ()I
    //   193: bipush #32
    //   195: irem
    //   196: invokestatic abs : (I)I
    //   199: invokevirtual charAt : (I)C
    //   202: invokevirtual append : (C)Ljava/lang/StringBuilder;
    //   205: pop
    //   206: iload_2
    //   207: ifne -> 1360
    //   210: goto -> 217
    //   213: invokestatic a : (Ljava/lang/Throwable;)Ljava/lang/Throwable;
    //   216: athrow
    //   217: aload_3
    //   218: getstatic burp/Ze69.ZA : Ljava/lang/String;
    //   221: getstatic burp/Zro2.Zu : Ljava/lang/Object;
    //   224: checkcast java/math/BigInteger
    //   227: invokevirtual intValue : ()I
    //   230: bipush #32
    //   232: irem
    //   233: invokestatic abs : (I)I
    //   236: invokevirtual charAt : (I)C
    //   239: invokevirtual append : (C)Ljava/lang/StringBuilder;
    //   242: pop
    //   243: iload_2
    //   244: ifne -> 1360
    //   247: goto -> 254
    //   250: invokestatic a : (Ljava/lang/Throwable;)Ljava/lang/Throwable;
    //   253: athrow
    //   254: aload_3
    //   255: getstatic burp/Zm84.Zd : Ljava/lang/String;
    //   258: getstatic burp/Zsuw.ZB : Ljava/lang/Object;
    //   261: checkcast java/math/BigInteger
    //   264: invokevirtual intValue : ()I
    //   267: bipush #32
    //   269: irem
    //   270: invokestatic abs : (I)I
    //   273: invokevirtual charAt : (I)C
    //   276: invokevirtual append : (C)Ljava/lang/StringBuilder;
    //   279: pop
    //   280: iload_2
    //   281: ifne -> 1360
    //   284: goto -> 291
    //   287: invokestatic a : (Ljava/lang/Throwable;)Ljava/lang/Throwable;
    //   290: athrow
    //   291: aload_3
    //   292: getstatic burp/Znp.Zr : Ljava/lang/String;
    //   295: getstatic burp/Zz5s.Zg : Ljava/lang/Object;
    //   298: checkcast java/math/BigInteger
    //   301: invokevirtual intValue : ()I
    //   304: bipush #32
    //   306: irem
    //   307: invokestatic abs : (I)I
    //   310: invokevirtual charAt : (I)C
    //   313: invokevirtual append : (C)Ljava/lang/StringBuilder;
    //   316: pop
    //   317: iload_2
    //   318: ifne -> 1360
    //   321: goto -> 328
    //   324: invokestatic a : (Ljava/lang/Throwable;)Ljava/lang/Throwable;
    //   327: athrow
    //   328: aload_3
    //   329: getstatic burp/Zkaw.ZI : Ljava/lang/String;
    //   332: getstatic burp/Zek5.ZP : Ljava/lang/Object;
    //   335: checkcast java/math/BigInteger
    //   338: invokevirtual intValue : ()I
    //   341: bipush #32
    //   343: irem
    //   344: invokestatic abs : (I)I
    //   347: invokevirtual charAt : (I)C
    //   350: invokevirtual append : (C)Ljava/lang/StringBuilder;
    //   353: pop
    //   354: iload_2
    //   355: ifne -> 1360
    //   358: goto -> 365
    //   361: invokestatic a : (Ljava/lang/Throwable;)Ljava/lang/Throwable;
    //   364: athrow
    //   365: aload_3
    //   366: getstatic burp/Ze_l.ZY : Ljava/lang/String;
    //   369: getstatic burp/Zmji.ZB : Ljava/lang/Object;
    //   372: checkcast java/math/BigInteger
    //   375: invokevirtual intValue : ()I
    //   378: bipush #32
    //   380: irem
    //   381: invokestatic abs : (I)I
    //   384: invokevirtual charAt : (I)C
    //   387: invokevirtual append : (C)Ljava/lang/StringBuilder;
    //   390: pop
    //   391: iload_2
    //   392: ifne -> 1360
    //   395: goto -> 402
    //   398: invokestatic a : (Ljava/lang/Throwable;)Ljava/lang/Throwable;
    //   401: athrow
    //   402: aload_3
    //   403: getstatic burp/Zk7b.ZE : Ljava/lang/String;
    //   406: getstatic burp/Zgsy.ZC : Ljava/lang/Object;
    //   409: checkcast java/math/BigInteger
    //   412: invokevirtual intValue : ()I
    //   415: bipush #32
    //   417: irem
    //   418: invokestatic abs : (I)I
    //   421: invokevirtual charAt : (I)C
    //   424: invokevirtual append : (C)Ljava/lang/StringBuilder;
    //   427: pop
    //   428: iload_2
    //   429: ifne -> 1360
    //   432: goto -> 439
    //   435: invokestatic a : (Ljava/lang/Throwable;)Ljava/lang/Throwable;
    //   438: athrow
    //   439: aload_3
    //   440: getstatic burp/Zgsy.Zv : Ljava/lang/String;
    //   443: getstatic burp/Zl8i.ZY : Ljava/lang/Object;
    //   446: checkcast java/math/BigInteger
    //   449: invokevirtual intValue : ()I
    //   452: bipush #32
    //   454: irem
    //   455: invokestatic abs : (I)I
    //   458: invokevirtual charAt : (I)C
    //   461: invokevirtual append : (C)Ljava/lang/StringBuilder;
    //   464: pop
    //   465: iload_2
    //   466: ifne -> 1360
    //   469: goto -> 476
    //   472: invokestatic a : (Ljava/lang/Throwable;)Ljava/lang/Throwable;
    //   475: athrow
    //   476: aload_3
    //   477: getstatic burp/Zts_.Zx : Ljava/lang/String;
    //   480: getstatic burp/Zlpl.Ze : Ljava/lang/Object;
    //   483: checkcast java/math/BigInteger
    //   486: invokevirtual intValue : ()I
    //   489: bipush #32
    //   491: irem
    //   492: invokestatic abs : (I)I
    //   495: invokevirtual charAt : (I)C
    //   498: invokevirtual append : (C)Ljava/lang/StringBuilder;
    //   501: pop
    //   502: iload_2
    //   503: ifne -> 1360
    //   506: goto -> 513
    //   509: invokestatic a : (Ljava/lang/Throwable;)Ljava/lang/Throwable;
    //   512: athrow
    //   513: aload_3
    //   514: getstatic burp/Zrc0.ZL : Ljava/lang/String;
    //   517: getstatic burp/Zrnw.ZN : Ljava/lang/Object;
    //   520: checkcast java/math/BigInteger
    //   523: invokevirtual intValue : ()I
    //   526: bipush #32
    //   528: irem
    //   529: invokestatic abs : (I)I
    //   532: invokevirtual charAt : (I)C
    //   535: invokevirtual append : (C)Ljava/lang/StringBuilder;
    //   538: pop
    //   539: iload_2
    //   540: ifne -> 1360
    //   543: goto -> 550
    //   546: invokestatic a : (Ljava/lang/Throwable;)Ljava/lang/Throwable;
    //   549: athrow
    //   550: aload_3
    //   551: getstatic burp/Zry9.ZW : Ljava/lang/String;
    //   554: getstatic burp/Zlot.ZJ : Ljava/lang/Object;
    //   557: checkcast java/math/BigInteger
    //   560: invokevirtual intValue : ()I
    //   563: bipush #32
    //   565: irem
    //   566: invokestatic abs : (I)I
    //   569: invokevirtual charAt : (I)C
    //   572: invokevirtual append : (C)Ljava/lang/StringBuilder;
    //   575: pop
    //   576: iload_2
    //   577: ifne -> 1360
    //   580: goto -> 587
    //   583: invokestatic a : (Ljava/lang/Throwable;)Ljava/lang/Throwable;
    //   586: athrow
    //   587: aload_3
    //   588: getstatic burp/Zsn6.Zs : Ljava/lang/String;
    //   591: getstatic burp/Zejj.Zy : Ljava/lang/Object;
    //   594: checkcast java/math/BigInteger
    //   597: invokevirtual intValue : ()I
    //   600: bipush #32
    //   602: irem
    //   603: invokestatic abs : (I)I
    //   606: invokevirtual charAt : (I)C
    //   609: invokevirtual append : (C)Ljava/lang/StringBuilder;
    //   612: pop
    //   613: iload_2
    //   614: ifne -> 1360
    //   617: goto -> 624
    //   620: invokestatic a : (Ljava/lang/Throwable;)Ljava/lang/Throwable;
    //   623: athrow
    //   624: aload_3
    //   625: getstatic burp/Zly7.ZC : Ljava/lang/String;
    //   628: getstatic burp/Zs26.Z_ : Ljava/lang/Object;
    //   631: checkcast java/math/BigInteger
    //   634: invokevirtual intValue : ()I
    //   637: bipush #32
    //   639: irem
    //   640: invokestatic abs : (I)I
    //   643: invokevirtual charAt : (I)C
    //   646: invokevirtual append : (C)Ljava/lang/StringBuilder;
    //   649: pop
    //   650: iload_2
    //   651: ifne -> 1360
    //   654: goto -> 661
    //   657: invokestatic a : (Ljava/lang/Throwable;)Ljava/lang/Throwable;
    //   660: athrow
    //   661: aload_3
    //   662: getstatic burp/Zb_c.ZS : Ljava/lang/String;
    //   665: getstatic burp/Zml2.Zo : Ljava/lang/Object;
    //   668: checkcast java/math/BigInteger
    //   671: invokevirtual intValue : ()I
    //   674: bipush #32
    //   676: irem
    //   677: invokestatic abs : (I)I
    //   680: invokevirtual charAt : (I)C
    //   683: invokevirtual append : (C)Ljava/lang/StringBuilder;
    //   686: pop
    //   687: iload_2
    //   688: ifne -> 1360
    //   691: goto -> 698
    //   694: invokestatic a : (Ljava/lang/Throwable;)Ljava/lang/Throwable;
    //   697: athrow
    //   698: aload_3
    //   699: getstatic burp/Zz5h.Zk : Ljava/lang/String;
    //   702: getstatic burp/Zk8b.ZK : Ljava/lang/Object;
    //   705: checkcast java/math/BigInteger
    //   708: invokevirtual intValue : ()I
    //   711: bipush #32
    //   713: irem
    //   714: invokestatic abs : (I)I
    //   717: invokevirtual charAt : (I)C
    //   720: invokevirtual append : (C)Ljava/lang/StringBuilder;
    //   723: pop
    //   724: iload_2
    //   725: ifne -> 1360
    //   728: goto -> 735
    //   731: invokestatic a : (Ljava/lang/Throwable;)Ljava/lang/Throwable;
    //   734: athrow
    //   735: aload_3
    //   736: getstatic burp/Zeju.ZR : Ljava/lang/String;
    //   739: getstatic burp/Zgvl.ZK : Ljava/lang/Object;
    //   742: checkcast java/math/BigInteger
    //   745: invokevirtual intValue : ()I
    //   748: bipush #32
    //   750: irem
    //   751: invokestatic abs : (I)I
    //   754: invokevirtual charAt : (I)C
    //   757: invokevirtual append : (C)Ljava/lang/StringBuilder;
    //   760: pop
    //   761: iload_2
    //   762: ifne -> 1360
    //   765: goto -> 772
    //   768: invokestatic a : (Ljava/lang/Throwable;)Ljava/lang/Throwable;
    //   771: athrow
    //   772: aload_3
    //   773: getstatic burp/Zr14.ZL : Ljava/lang/String;
    //   776: getstatic burp/Zstf.ZA : Ljava/lang/Object;
    //   779: checkcast java/math/BigInteger
    //   782: invokevirtual intValue : ()I
    //   785: bipush #32
    //   787: irem
    //   788: invokestatic abs : (I)I
    //   791: invokevirtual charAt : (I)C
    //   794: invokevirtual append : (C)Ljava/lang/StringBuilder;
    //   797: pop
    //   798: iload_2
    //   799: ifne -> 1360
    //   802: goto -> 809
    //   805: invokestatic a : (Ljava/lang/Throwable;)Ljava/lang/Throwable;
    //   808: athrow
    //   809: aload_3
    //   810: getstatic burp/Zszz.Zg : Ljava/lang/String;
    //   813: getstatic burp/Zrvb.ZD : Ljava/lang/Object;
    //   816: checkcast java/math/BigInteger
    //   819: invokevirtual intValue : ()I
    //   822: bipush #32
    //   824: irem
    //   825: invokestatic abs : (I)I
    //   828: invokevirtual charAt : (I)C
    //   831: invokevirtual append : (C)Ljava/lang/StringBuilder;
    //   834: pop
    //   835: iload_2
    //   836: ifne -> 1360
    //   839: goto -> 846
    //   842: invokestatic a : (Ljava/lang/Throwable;)Ljava/lang/Throwable;
    //   845: athrow
    //   846: aload_3
    //   847: getstatic burp/Zz75.ZT : Ljava/lang/String;
    //   850: getstatic burp/Zlbr.Zp : Ljava/lang/Object;
    //   853: checkcast java/math/BigInteger
    //   856: invokevirtual intValue : ()I
    //   859: bipush #32
    //   861: irem
    //   862: invokestatic abs : (I)I
    //   865: invokevirtual charAt : (I)C
    //   868: invokevirtual append : (C)Ljava/lang/StringBuilder;
    //   871: pop
    //   872: iload_2
    //   873: ifne -> 1360
    //   876: goto -> 883
    //   879: invokestatic a : (Ljava/lang/Throwable;)Ljava/lang/Throwable;
    //   882: athrow
    //   883: aload_3
    //   884: getstatic burp/Zz5h.Zk : Ljava/lang/String;
    //   887: getstatic burp/Ze3z.Zf : Ljava/lang/Object;
    //   890: checkcast java/math/BigInteger
    //   893: invokevirtual intValue : ()I
    //   896: bipush #32
    //   898: irem
    //   899: invokestatic abs : (I)I
    //   902: invokevirtual charAt : (I)C
    //   905: invokevirtual append : (C)Ljava/lang/StringBuilder;
    //   908: pop
    //   909: iload_2
    //   910: ifne -> 1360
    //   913: goto -> 920
    //   916: invokestatic a : (Ljava/lang/Throwable;)Ljava/lang/Throwable;
    //   919: athrow
    //   920: aload_3
    //   921: getstatic burp/Zmpc.ZT : Ljava/lang/String;
    //   924: getstatic burp/Zt7j.ZH : Ljava/lang/Object;
    //   927: checkcast java/math/BigInteger
    //   930: invokevirtual intValue : ()I
    //   933: bipush #32
    //   935: irem
    //   936: invokestatic abs : (I)I
    //   939: invokevirtual charAt : (I)C
    //   942: invokevirtual append : (C)Ljava/lang/StringBuilder;
    //   945: pop
    //   946: iload_2
    //   947: ifne -> 1360
    //   950: goto -> 957
    //   953: invokestatic a : (Ljava/lang/Throwable;)Ljava/lang/Throwable;
    //   956: athrow
    //   957: aload_3
    //   958: getstatic burp/Zkq9.ZO : Ljava/lang/String;
    //   961: getstatic burp/Ztv8.ZS : Ljava/lang/Object;
    //   964: checkcast java/math/BigInteger
    //   967: invokevirtual intValue : ()I
    //   970: bipush #32
    //   972: irem
    //   973: invokestatic abs : (I)I
    //   976: invokevirtual charAt : (I)C
    //   979: invokevirtual append : (C)Ljava/lang/StringBuilder;
    //   982: pop
    //   983: iload_2
    //   984: ifne -> 1360
    //   987: goto -> 994
    //   990: invokestatic a : (Ljava/lang/Throwable;)Ljava/lang/Throwable;
    //   993: athrow
    //   994: aload_3
    //   995: getstatic burp/Zoa.ZF : Ljava/lang/String;
    //   998: getstatic burp/Zlhu.ZJ : Ljava/lang/Object;
    //   1001: checkcast java/math/BigInteger
    //   1004: invokevirtual intValue : ()I
    //   1007: bipush #32
    //   1009: irem
    //   1010: invokestatic abs : (I)I
    //   1013: invokevirtual charAt : (I)C
    //   1016: invokevirtual append : (C)Ljava/lang/StringBuilder;
    //   1019: pop
    //   1020: iload_2
    //   1021: ifne -> 1360
    //   1024: goto -> 1031
    //   1027: invokestatic a : (Ljava/lang/Throwable;)Ljava/lang/Throwable;
    //   1030: athrow
    //   1031: aload_3
    //   1032: getstatic burp/Zboa.Zq : Ljava/lang/String;
    //   1035: getstatic burp/Zrjw.Zu : Ljava/lang/Object;
    //   1038: checkcast java/math/BigInteger
    //   1041: invokevirtual intValue : ()I
    //   1044: bipush #32
    //   1046: irem
    //   1047: invokestatic abs : (I)I
    //   1050: invokevirtual charAt : (I)C
    //   1053: invokevirtual append : (C)Ljava/lang/StringBuilder;
    //   1056: pop
    //   1057: iload_2
    //   1058: ifne -> 1360
    //   1061: goto -> 1068
    //   1064: invokestatic a : (Ljava/lang/Throwable;)Ljava/lang/Throwable;
    //   1067: athrow
    //   1068: aload_3
    //   1069: getstatic burp/Zgd7.Zs : Ljava/lang/String;
    //   1072: getstatic burp/Zl_k.ZH : Ljava/lang/Object;
    //   1075: checkcast java/math/BigInteger
    //   1078: invokevirtual intValue : ()I
    //   1081: bipush #32
    //   1083: irem
    //   1084: invokestatic abs : (I)I
    //   1087: invokevirtual charAt : (I)C
    //   1090: invokevirtual append : (C)Ljava/lang/StringBuilder;
    //   1093: pop
    //   1094: iload_2
    //   1095: ifne -> 1360
    //   1098: goto -> 1105
    //   1101: invokestatic a : (Ljava/lang/Throwable;)Ljava/lang/Throwable;
    //   1104: athrow
    //   1105: aload_3
    //   1106: getstatic burp/Zgkp.ZS : Ljava/lang/String;
    //   1109: getstatic burp/Zepm.Zp : Ljava/lang/Object;
    //   1112: checkcast java/math/BigInteger
    //   1115: invokevirtual intValue : ()I
    //   1118: bipush #32
    //   1120: irem
    //   1121: invokestatic abs : (I)I
    //   1124: invokevirtual charAt : (I)C
    //   1127: invokevirtual append : (C)Ljava/lang/StringBuilder;
    //   1130: pop
    //   1131: iload_2
    //   1132: ifne -> 1360
    //   1135: goto -> 1142
    //   1138: invokestatic a : (Ljava/lang/Throwable;)Ljava/lang/Throwable;
    //   1141: athrow
    //   1142: aload_3
    //   1143: getstatic burp/Zmzh.Zm : Ljava/lang/String;
    //   1146: getstatic burp/Zexn.Zl : Ljava/lang/Object;
    //   1149: checkcast java/math/BigInteger
    //   1152: invokevirtual intValue : ()I
    //   1155: bipush #32
    //   1157: irem
    //   1158: invokestatic abs : (I)I
    //   1161: invokevirtual charAt : (I)C
    //   1164: invokevirtual append : (C)Ljava/lang/StringBuilder;
    //   1167: pop
    //   1168: iload_2
    //   1169: ifne -> 1360
    //   1172: goto -> 1179
    //   1175: invokestatic a : (Ljava/lang/Throwable;)Ljava/lang/Throwable;
    //   1178: athrow
    //   1179: aload_3
    //   1180: getstatic burp/Zrf9.ZV : Ljava/lang/String;
    //   1183: getstatic burp/Zg99.ZZ : Ljava/lang/Object;
    //   1186: checkcast java/math/BigInteger
    //   1189: invokevirtual intValue : ()I
    //   1192: bipush #32
    //   1194: irem
    //   1195: invokestatic abs : (I)I
    //   1198: invokevirtual charAt : (I)C
    //   1201: invokevirtual append : (C)Ljava/lang/StringBuilder;
    //   1204: pop
    //   1205: iload_2
    //   1206: ifne -> 1360
    //   1209: goto -> 1216
    //   1212: invokestatic a : (Ljava/lang/Throwable;)Ljava/lang/Throwable;
    //   1215: athrow
    //   1216: aload_3
    //   1217: getstatic burp/Zbow.Zr : Ljava/lang/String;
    //   1220: getstatic burp/Zbsr.ZD : Ljava/lang/Object;
    //   1223: checkcast java/math/BigInteger
    //   1226: invokevirtual intValue : ()I
    //   1229: bipush #32
    //   1231: irem
    //   1232: invokestatic abs : (I)I
    //   1235: invokevirtual charAt : (I)C
    //   1238: invokevirtual append : (C)Ljava/lang/StringBuilder;
    //   1241: pop
    //   1242: iload_2
    //   1243: ifne -> 1360
    //   1246: goto -> 1253
    //   1249: invokestatic a : (Ljava/lang/Throwable;)Ljava/lang/Throwable;
    //   1252: athrow
    //   1253: aload_3
    //   1254: getstatic burp/Zlhk.Zb : Ljava/lang/String;
    //   1257: getstatic burp/Ztdx.ZX : Ljava/lang/Object;
    //   1260: checkcast java/math/BigInteger
    //   1263: invokevirtual intValue : ()I
    //   1266: bipush #32
    //   1268: irem
    //   1269: invokestatic abs : (I)I
    //   1272: invokevirtual charAt : (I)C
    //   1275: invokevirtual append : (C)Ljava/lang/StringBuilder;
    //   1278: pop
    //   1279: iload_2
    //   1280: ifne -> 1360
    //   1283: goto -> 1290
    //   1286: invokestatic a : (Ljava/lang/Throwable;)Ljava/lang/Throwable;
    //   1289: athrow
    //   1290: aload_3
    //   1291: getstatic burp/Zkk6.ZP : Ljava/lang/String;
    //   1294: getstatic burp/Zs0b.ZI : Ljava/lang/Object;
    //   1297: checkcast java/math/BigInteger
    //   1300: invokevirtual intValue : ()I
    //   1303: bipush #32
    //   1305: irem
    //   1306: invokestatic abs : (I)I
    //   1309: invokevirtual charAt : (I)C
    //   1312: invokevirtual append : (C)Ljava/lang/StringBuilder;
    //   1315: pop
    //   1316: iload_2
    //   1317: ifne -> 1360
    //   1320: goto -> 1327
    //   1323: invokestatic a : (Ljava/lang/Throwable;)Ljava/lang/Throwable;
    //   1326: athrow
    //   1327: aload_3
    //   1328: getstatic burp/Zb0s.Zi : Ljava/lang/String;
    //   1331: getstatic burp/Zgyc.ZT : Ljava/lang/Object;
    //   1334: checkcast java/math/BigInteger
    //   1337: invokevirtual intValue : ()I
    //   1340: bipush #32
    //   1342: irem
    //   1343: invokestatic abs : (I)I
    //   1346: invokevirtual charAt : (I)C
    //   1349: invokevirtual append : (C)Ljava/lang/StringBuilder;
    //   1352: pop
    //   1353: goto -> 1360
    //   1356: invokestatic a : (Ljava/lang/Throwable;)Ljava/lang/Throwable;
    //   1359: athrow
    //   1360: iinc #4, 1
    //   1363: iload_2
    //   1364: ifne -> 30
    //   1367: aload_3
    //   1368: invokevirtual toString : ()Ljava/lang/String;
    //   1371: putstatic burp/Zkaw.ZI : Ljava/lang/String;
    //   1374: sipush #26769
    //   1377: sipush #13951
    //   1380: invokestatic a : (II)Ljava/lang/String;
    //   1383: iconst_1
    //   1384: ldc burp/Zrnw
    //   1386: invokevirtual getClassLoader : ()Ljava/lang/ClassLoader;
    //   1389: invokestatic forName : (Ljava/lang/String;ZLjava/lang/ClassLoader;)Ljava/lang/Class;
    //   1392: invokevirtual getDeclaredFields : ()[Ljava/lang/reflect/Field;
    //   1395: astore #4
    //   1397: aload #4
    //   1399: arraylength
    //   1400: istore #5
    //   1402: iconst_0
    //   1403: istore #6
    //   1405: iload #6
    //   1407: iload #5
    //   1409: if_icmpge -> 1547
    //   1412: aload #4
    //   1414: iload #6
    //   1416: aaload
    //   1417: astore #7
    //   1419: aload #7
    //   1421: invokevirtual getModifiers : ()I
    //   1424: invokestatic isStatic : (I)Z
    //   1427: ifne -> 1437
    //   1430: goto -> 1540
    //   1433: invokestatic a : (Ljava/lang/Throwable;)Ljava/lang/Throwable;
    //   1436: athrow
    //   1437: aload #7
    //   1439: invokevirtual getType : ()Ljava/lang/Class;
    //   1442: astore #8
    //   1444: aload #8
    //   1446: ifnull -> 1527
    //   1449: aload #8
    //   1451: invokevirtual isPrimitive : ()Z
    //   1454: ifne -> 1527
    //   1457: goto -> 1464
    //   1460: invokestatic a : (Ljava/lang/Throwable;)Ljava/lang/Throwable;
    //   1463: athrow
    //   1464: aload #8
    //   1466: invokevirtual getPackage : ()Ljava/lang/Package;
    //   1469: ifnull -> 1527
    //   1472: goto -> 1479
    //   1475: invokestatic a : (Ljava/lang/Throwable;)Ljava/lang/Throwable;
    //   1478: athrow
    //   1479: aload #8
    //   1481: invokevirtual getPackage : ()Ljava/lang/Package;
    //   1484: invokevirtual getName : ()Ljava/lang/String;
    //   1487: ifnull -> 1527
    //   1490: goto -> 1497
    //   1493: invokestatic a : (Ljava/lang/Throwable;)Ljava/lang/Throwable;
    //   1496: athrow
    //   1497: aload #8
    //   1499: invokevirtual getPackage : ()Ljava/lang/Package;
    //   1502: invokevirtual getName : ()Ljava/lang/String;
    //   1505: sipush #26783
    //   1508: sipush #17958
    //   1511: invokestatic a : (II)Ljava/lang/String;
    //   1514: invokevirtual startsWith : (Ljava/lang/String;)Z
    //   1517: ifne -> 1527
    //   1520: goto -> 1527
    //   1523: invokestatic a : (Ljava/lang/Throwable;)Ljava/lang/Throwable;
    //   1526: athrow
    //   1527: aload #7
    //   1529: iconst_1
    //   1530: invokevirtual setAccessible : (Z)V
    //   1533: aload #7
    //   1535: aconst_null
    //   1536: invokevirtual get : (Ljava/lang/Object;)Ljava/lang/Object;
    //   1539: pop
    //   1540: iinc #6, 1
    //   1543: iload_2
    //   1544: ifne -> 1405
    //   1547: sipush #26776
    //   1550: sipush #11211
    //   1553: invokestatic a : (II)Ljava/lang/String;
    //   1556: invokestatic forName : (Ljava/lang/String;)Ljava/lang/Class;
    //   1559: invokevirtual getDeclaredMethods : ()[Ljava/lang/reflect/Method;
    //   1562: astore #4
    //   1564: aload #4
    //   1566: arraylength
    //   1567: istore #5
    //   1569: iconst_0
    //   1570: istore #6
    //   1572: iload #6
    //   1574: iload #5
    //   1576: if_icmpge -> 1688
    //   1579: aload #4
    //   1581: iload #6
    //   1583: aaload
    //   1584: astore #7
    //   1586: aload #7
    //   1588: invokevirtual getParameterTypes : ()[Ljava/lang/Class;
    //   1591: pop
    //   1592: aload #7
    //   1594: invokevirtual getModifiers : ()I
    //   1597: invokestatic isStatic : (I)Z
    //   1600: ifeq -> 1674
    //   1603: aload #7
    //   1605: invokevirtual getParameterTypes : ()[Ljava/lang/Class;
    //   1608: arraylength
    //   1609: iconst_2
    //   1610: if_icmpne -> 1674
    //   1613: goto -> 1620
    //   1616: invokestatic a : (Ljava/lang/Throwable;)Ljava/lang/Throwable;
    //   1619: athrow
    //   1620: aload #7
    //   1622: invokevirtual getReturnType : ()Ljava/lang/Class;
    //   1625: getstatic java/lang/Boolean.TYPE : Ljava/lang/Class;
    //   1628: if_acmpne -> 1674
    //   1631: goto -> 1638
    //   1634: invokestatic a : (Ljava/lang/Throwable;)Ljava/lang/Throwable;
    //   1637: athrow
    //   1638: aload #7
    //   1640: iconst_1
    //   1641: invokevirtual setAccessible : (Z)V
    //   1644: aload #7
    //   1646: aconst_null
    //   1647: iconst_2
    //   1648: anewarray java/lang/Object
    //   1651: dup
    //   1652: iconst_0
    //   1653: aload_0
    //   1654: aastore
    //   1655: dup
    //   1656: iconst_1
    //   1657: aload_1
    //   1658: aastore
    //   1659: invokevirtual invoke : (Ljava/lang/Object;[Ljava/lang/Object;)Ljava/lang/Object;
    //   1662: pop
    //   1663: iload_2
    //   1664: ifne -> 1688
    //   1667: goto -> 1674
    //   1670: invokestatic a : (Ljava/lang/Throwable;)Ljava/lang/Throwable;
    //   1673: athrow
    //   1674: iinc #6, 1
    //   1677: iload_2
    //   1678: ifne -> 1572
    //   1681: goto -> 1688
    //   1684: invokestatic a : (Ljava/lang/Throwable;)Ljava/lang/Throwable;
    //   1687: athrow
    //   1688: sipush #26781
    //   1691: sipush #1435
    //   1694: invokestatic a : (II)Ljava/lang/String;
    //   1697: iconst_1
    //   1698: ldc burp/Zzi3
    //   1700: invokevirtual getClassLoader : ()Ljava/lang/ClassLoader;
    //   1703: invokestatic forName : (Ljava/lang/String;ZLjava/lang/ClassLoader;)Ljava/lang/Class;
    //   1706: invokevirtual getDeclaredFields : ()[Ljava/lang/reflect/Field;
    //   1709: astore #4
    //   1711: aload #4
    //   1713: arraylength
    //   1714: istore #5
    //   1716: iconst_0
    //   1717: istore #6
    //   1719: iload #6
    //   1721: iload #5
    //   1723: if_icmpge -> 1861
    //   1726: aload #4
    //   1728: iload #6
    //   1730: aaload
    //   1731: astore #7
    //   1733: aload #7
    //   1735: invokevirtual getModifiers : ()I
    //   1738: invokestatic isStatic : (I)Z
    //   1741: ifne -> 1751
    //   1744: goto -> 1854
    //   1747: invokestatic a : (Ljava/lang/Throwable;)Ljava/lang/Throwable;
    //   1750: athrow
    //   1751: aload #7
    //   1753: invokevirtual getType : ()Ljava/lang/Class;
    //   1756: astore #8
    //   1758: aload #8
    //   1760: ifnull -> 1841
    //   1763: aload #8
    //   1765: invokevirtual isPrimitive : ()Z
    //   1768: ifne -> 1841
    //   1771: goto -> 1778
    //   1774: invokestatic a : (Ljava/lang/Throwable;)Ljava/lang/Throwable;
    //   1777: athrow
    //   1778: aload #8
    //   1780: invokevirtual getPackage : ()Ljava/lang/Package;
    //   1783: ifnull -> 1841
    //   1786: goto -> 1793
    //   1789: invokestatic a : (Ljava/lang/Throwable;)Ljava/lang/Throwable;
    //   1792: athrow
    //   1793: aload #8
    //   1795: invokevirtual getPackage : ()Ljava/lang/Package;
    //   1798: invokevirtual getName : ()Ljava/lang/String;
    //   1801: ifnull -> 1841
    //   1804: goto -> 1811
    //   1807: invokestatic a : (Ljava/lang/Throwable;)Ljava/lang/Throwable;
    //   1810: athrow
    //   1811: aload #8
    //   1813: invokevirtual getPackage : ()Ljava/lang/Package;
    //   1816: invokevirtual getName : ()Ljava/lang/String;
    //   1819: sipush #26775
    //   1822: sipush #-32127
    //   1825: invokestatic a : (II)Ljava/lang/String;
    //   1828: invokevirtual startsWith : (Ljava/lang/String;)Z
    //   1831: ifne -> 1841
    //   1834: goto -> 1841
    //   1837: invokestatic a : (Ljava/lang/Throwable;)Ljava/lang/Throwable;
    //   1840: athrow
    //   1841: aload #7
    //   1843: iconst_1
    //   1844: invokevirtual setAccessible : (Z)V
    //   1847: aload #7
    //   1849: aconst_null
    //   1850: invokevirtual get : (Ljava/lang/Object;)Ljava/lang/Object;
    //   1853: pop
    //   1854: iinc #6, 1
    //   1857: iload_2
    //   1858: ifne -> 1719
    //   1861: sipush #26772
    //   1864: sipush #26248
    //   1867: invokestatic a : (II)Ljava/lang/String;
    //   1870: invokestatic forName : (Ljava/lang/String;)Ljava/lang/Class;
    //   1873: invokevirtual getDeclaredMethods : ()[Ljava/lang/reflect/Method;
    //   1876: astore #4
    //   1878: aload #4
    //   1880: arraylength
    //   1881: istore #5
    //   1883: iconst_0
    //   1884: istore #6
    //   1886: iload #6
    //   1888: iload #5
    //   1890: if_icmpge -> 2020
    //   1893: aload #4
    //   1895: iload #6
    //   1897: aaload
    //   1898: astore #7
    //   1900: aload #7
    //   1902: invokevirtual getParameterTypes : ()[Ljava/lang/Class;
    //   1905: pop
    //   1906: aload #7
    //   1908: invokevirtual getModifiers : ()I
    //   1911: invokestatic isStatic : (I)Z
    //   1914: ifeq -> 2006
    //   1917: aload #7
    //   1919: invokevirtual getParameterTypes : ()[Ljava/lang/Class;
    //   1922: arraylength
    //   1923: iconst_2
    //   1924: if_icmpne -> 2006
    //   1927: goto -> 1934
    //   1930: invokestatic a : (Ljava/lang/Throwable;)Ljava/lang/Throwable;
    //   1933: athrow
    //   1934: aload #7
    //   1936: invokevirtual getReturnType : ()Ljava/lang/Class;
    //   1939: getstatic java/lang/Boolean.TYPE : Ljava/lang/Class;
    //   1942: if_acmpne -> 2006
    //   1945: goto -> 1952
    //   1948: invokestatic a : (Ljava/lang/Throwable;)Ljava/lang/Throwable;
    //   1951: athrow
    //   1952: aload #7
    //   1954: iconst_1
    //   1955: invokevirtual setAccessible : (Z)V
    //   1958: aload #7
    //   1960: aconst_null
    //   1961: iconst_2
    //   1962: anewarray java/lang/Object
    //   1965: dup
    //   1966: iconst_0
    //   1967: aload_0
    //   1968: aastore
    //   1969: dup
    //   1970: iconst_1
    //   1971: aload_1
    //   1972: ifnonnull -> 1990
    //   1975: goto -> 1982
    //   1978: invokestatic a : (Ljava/lang/Throwable;)Ljava/lang/Throwable;
    //   1981: athrow
    //   1982: aload_1
    //   1983: goto -> 1997
    //   1986: invokestatic a : (Ljava/lang/Throwable;)Ljava/lang/Throwable;
    //   1989: athrow
    //   1990: aload_1
    //   1991: checkcast [B
    //   1994: invokevirtual clone : ()Ljava/lang/Object;
    //   1997: aastore
    //   1998: invokevirtual invoke : (Ljava/lang/Object;[Ljava/lang/Object;)Ljava/lang/Object;
    //   2001: pop
    //   2002: iload_2
    //   2003: ifne -> 2020
    //   2006: iinc #6, 1
    //   2009: iload_2
    //   2010: ifne -> 1886
    //   2013: goto -> 2020
    //   2016: invokestatic a : (Ljava/lang/Throwable;)Ljava/lang/Throwable;
    //   2019: athrow
    //   2020: sipush #26774
    //   2023: sipush #-31640
    //   2026: invokestatic a : (II)Ljava/lang/String;
    //   2029: iconst_1
    //   2030: ldc burp/Zzi_
    //   2032: invokevirtual getClassLoader : ()Ljava/lang/ClassLoader;
    //   2035: invokestatic forName : (Ljava/lang/String;ZLjava/lang/ClassLoader;)Ljava/lang/Class;
    //   2038: invokevirtual getDeclaredFields : ()[Ljava/lang/reflect/Field;
    //   2041: astore #4
    //   2043: aload #4
    //   2045: arraylength
    //   2046: istore #5
    //   2048: iconst_0
    //   2049: istore #6
    //   2051: iload #6
    //   2053: iload #5
    //   2055: if_icmpge -> 2193
    //   2058: aload #4
    //   2060: iload #6
    //   2062: aaload
    //   2063: astore #7
    //   2065: aload #7
    //   2067: invokevirtual getModifiers : ()I
    //   2070: invokestatic isStatic : (I)Z
    //   2073: ifne -> 2083
    //   2076: goto -> 2186
    //   2079: invokestatic a : (Ljava/lang/Throwable;)Ljava/lang/Throwable;
    //   2082: athrow
    //   2083: aload #7
    //   2085: invokevirtual getType : ()Ljava/lang/Class;
    //   2088: astore #8
    //   2090: aload #8
    //   2092: ifnull -> 2173
    //   2095: aload #8
    //   2097: invokevirtual isPrimitive : ()Z
    //   2100: ifne -> 2173
    //   2103: goto -> 2110
    //   2106: invokestatic a : (Ljava/lang/Throwable;)Ljava/lang/Throwable;
    //   2109: athrow
    //   2110: aload #8
    //   2112: invokevirtual getPackage : ()Ljava/lang/Package;
    //   2115: ifnull -> 2173
    //   2118: goto -> 2125
    //   2121: invokestatic a : (Ljava/lang/Throwable;)Ljava/lang/Throwable;
    //   2124: athrow
    //   2125: aload #8
    //   2127: invokevirtual getPackage : ()Ljava/lang/Package;
    //   2130: invokevirtual getName : ()Ljava/lang/String;
    //   2133: ifnull -> 2173
    //   2136: goto -> 2143
    //   2139: invokestatic a : (Ljava/lang/Throwable;)Ljava/lang/Throwable;
    //   2142: athrow
    //   2143: aload #8
    //   2145: invokevirtual getPackage : ()Ljava/lang/Package;
    //   2148: invokevirtual getName : ()Ljava/lang/String;
    //   2151: sipush #26775
    //   2154: sipush #-32127
    //   2157: invokestatic a : (II)Ljava/lang/String;
    //   2160: invokevirtual startsWith : (Ljava/lang/String;)Z
    //   2163: ifne -> 2173
    //   2166: goto -> 2173
    //   2169: invokestatic a : (Ljava/lang/Throwable;)Ljava/lang/Throwable;
    //   2172: athrow
    //   2173: aload #7
    //   2175: iconst_1
    //   2176: invokevirtual setAccessible : (Z)V
    //   2179: aload #7
    //   2181: aconst_null
    //   2182: invokevirtual get : (Ljava/lang/Object;)Ljava/lang/Object;
    //   2185: pop
    //   2186: iinc #6, 1
    //   2189: iload_2
    //   2190: ifne -> 2051
    //   2193: sipush #26773
    //   2196: sipush #723
    //   2199: invokestatic a : (II)Ljava/lang/String;
    //   2202: invokestatic forName : (Ljava/lang/String;)Ljava/lang/Class;
    //   2205: invokevirtual getDeclaredMethods : ()[Ljava/lang/reflect/Method;
    //   2208: astore #4
    //   2210: aload #4
    //   2212: arraylength
    //   2213: istore #5
    //   2215: iconst_0
    //   2216: istore #6
    //   2218: iload #6
    //   2220: iload #5
    //   2222: if_icmpge -> 2355
    //   2225: aload #4
    //   2227: iload #6
    //   2229: aaload
    //   2230: astore #7
    //   2232: aload #7
    //   2234: invokevirtual getParameterTypes : ()[Ljava/lang/Class;
    //   2237: pop
    //   2238: aload #7
    //   2240: invokevirtual getModifiers : ()I
    //   2243: invokestatic isStatic : (I)Z
    //   2246: ifeq -> 2341
    //   2249: aload #7
    //   2251: invokevirtual getParameterTypes : ()[Ljava/lang/Class;
    //   2254: arraylength
    //   2255: iconst_2
    //   2256: if_icmpne -> 2341
    //   2259: goto -> 2266
    //   2262: invokestatic a : (Ljava/lang/Throwable;)Ljava/lang/Throwable;
    //   2265: athrow
    //   2266: aload #7
    //   2268: invokevirtual getReturnType : ()Ljava/lang/Class;
    //   2271: getstatic java/lang/Void.TYPE : Ljava/lang/Class;
    //   2274: invokevirtual equals : (Ljava/lang/Object;)Z
    //   2277: ifeq -> 2341
    //   2280: goto -> 2287
    //   2283: invokestatic a : (Ljava/lang/Throwable;)Ljava/lang/Throwable;
    //   2286: athrow
    //   2287: aload #7
    //   2289: iconst_1
    //   2290: invokevirtual setAccessible : (Z)V
    //   2293: aload #7
    //   2295: aconst_null
    //   2296: iconst_2
    //   2297: anewarray java/lang/Object
    //   2300: dup
    //   2301: iconst_0
    //   2302: aload_0
    //   2303: aastore
    //   2304: dup
    //   2305: iconst_1
    //   2306: aload_1
    //   2307: ifnonnull -> 2325
    //   2310: goto -> 2317
    //   2313: invokestatic a : (Ljava/lang/Throwable;)Ljava/lang/Throwable;
    //   2316: athrow
    //   2317: aload_1
    //   2318: goto -> 2332
    //   2321: invokestatic a : (Ljava/lang/Throwable;)Ljava/lang/Throwable;
    //   2324: athrow
    //   2325: aload_1
    //   2326: checkcast [B
    //   2329: invokevirtual clone : ()Ljava/lang/Object;
    //   2332: aastore
    //   2333: invokevirtual invoke : (Ljava/lang/Object;[Ljava/lang/Object;)Ljava/lang/Object;
    //   2336: pop
    //   2337: iload_2
    //   2338: ifne -> 2355
    //   2341: iinc #6, 1
    //   2344: iload_2
    //   2345: ifne -> 2218
    //   2348: goto -> 2355
    //   2351: invokestatic a : (Ljava/lang/Throwable;)Ljava/lang/Throwable;
    //   2354: athrow
    //   2355: getstatic burp/Zzx8.Z_ : Ljava/lang/String;
    //   2358: getstatic burp/Zzox.Zq : Ljava/lang/Object;
    //   2361: checkcast java/math/BigInteger
    //   2364: invokevirtual intValue : ()I
    //   2367: bipush #32
    //   2369: irem
    //   2370: invokestatic abs : (I)I
    //   2373: invokevirtual charAt : (I)C
    //   2376: getstatic burp/Zzsq.Zc : Ljava/lang/String;
    //   2379: getstatic burp/Zmrc.ZU : Ljava/lang/Object;
    //   2382: checkcast java/math/BigInteger
    //   2385: invokevirtual intValue : ()I
    //   2388: bipush #32
    //   2390: irem
    //   2391: invokestatic abs : (I)I
    //   2394: invokevirtual charAt : (I)C
    //   2397: if_icmple -> 2512
    //   2400: getstatic burp/Zgzv.Zy : Ljava/lang/String;
    //   2403: getstatic burp/Ztod.ZP : Ljava/lang/Object;
    //   2406: checkcast java/math/BigInteger
    //   2409: invokevirtual intValue : ()I
    //   2412: bipush #32
    //   2414: irem
    //   2415: invokestatic abs : (I)I
    //   2418: invokevirtual charAt : (I)C
    //   2421: getstatic burp/Zbzk.ZS : Ljava/lang/String;
    //   2424: getstatic burp/Zg2u.ZI : Ljava/lang/Object;
    //   2427: checkcast java/math/BigInteger
    //   2430: invokevirtual intValue : ()I
    //   2433: bipush #32
    //   2435: irem
    //   2436: invokestatic abs : (I)I
    //   2439: invokevirtual charAt : (I)C
    //   2442: if_icmpgt -> 2512
    //   2445: goto -> 2452
    //   2448: invokestatic a : (Ljava/lang/Throwable;)Ljava/lang/Throwable;
    //   2451: athrow
    //   2452: getstatic burp/Zbj.ZD : Ljava/lang/String;
    //   2455: getstatic burp/Zb6a.Zz : Ljava/lang/Object;
    //   2458: checkcast java/math/BigInteger
    //   2461: invokevirtual intValue : ()I
    //   2464: bipush #32
    //   2466: irem
    //   2467: invokestatic abs : (I)I
    //   2470: invokevirtual charAt : (I)C
    //   2473: getstatic burp/Zer.Zp : Ljava/lang/String;
    //   2476: getstatic burp/Zgvf.Zd : Ljava/lang/Object;
    //   2479: checkcast java/math/BigInteger
    //   2482: invokevirtual intValue : ()I
    //   2485: bipush #32
    //   2487: irem
    //   2488: invokestatic abs : (I)I
    //   2491: invokevirtual charAt : (I)C
    //   2494: if_icmple -> 2512
    //   2497: goto -> 2504
    //   2500: invokestatic a : (Ljava/lang/Throwable;)Ljava/lang/Throwable;
    //   2503: athrow
    //   2504: iconst_1
    //   2505: goto -> 2513
    //   2508: invokestatic a : (Ljava/lang/Throwable;)Ljava/lang/Throwable;
    //   2511: athrow
    //   2512: iconst_0
    //   2513: ireturn
    //   2514: astore_3
    //   2515: new java/lang/Exception
    //   2518: dup
    //   2519: aload_3
    //   2520: invokevirtual getMessage : ()Ljava/lang/String;
    //   2523: invokespecial <init> : (Ljava/lang/String;)V
    //   2526: athrow
    // Exception table:
    //   from	to	target	type
    //   4	2513	2514	java/lang/Throwable
    //   37	210	213	java/lang/Throwable
    //   180	247	250	java/lang/Throwable
    //   217	284	287	java/lang/Throwable
    //   254	321	324	java/lang/Throwable
    //   291	358	361	java/lang/Throwable
    //   328	395	398	java/lang/Throwable
    //   365	432	435	java/lang/Throwable
    //   402	469	472	java/lang/Throwable
    //   439	506	509	java/lang/Throwable
    //   476	543	546	java/lang/Throwable
    //   513	580	583	java/lang/Throwable
    //   550	617	620	java/lang/Throwable
    //   587	654	657	java/lang/Throwable
    //   624	691	694	java/lang/Throwable
    //   661	728	731	java/lang/Throwable
    //   698	765	768	java/lang/Throwable
    //   735	802	805	java/lang/Throwable
    //   772	839	842	java/lang/Throwable
    //   809	876	879	java/lang/Throwable
    //   846	913	916	java/lang/Throwable
    //   883	950	953	java/lang/Throwable
    //   920	987	990	java/lang/Throwable
    //   957	1024	1027	java/lang/Throwable
    //   994	1061	1064	java/lang/Throwable
    //   1031	1098	1101	java/lang/Throwable
    //   1068	1135	1138	java/lang/Throwable
    //   1105	1172	1175	java/lang/Throwable
    //   1142	1209	1212	java/lang/Throwable
    //   1179	1246	1249	java/lang/Throwable
    //   1216	1283	1286	java/lang/Throwable
    //   1253	1320	1323	java/lang/Throwable
    //   1290	1353	1356	java/lang/Throwable
    //   1419	1433	1433	java/lang/Throwable
    //   1444	1457	1460	java/lang/Throwable
    //   1449	1472	1475	java/lang/Throwable
    //   1464	1490	1493	java/lang/Throwable
    //   1479	1520	1523	java/lang/Throwable
    //   1586	1613	1616	java/lang/Throwable
    //   1603	1631	1634	java/lang/Throwable
    //   1620	1667	1670	java/lang/Throwable
    //   1638	1681	1684	java/lang/Throwable
    //   1733	1747	1747	java/lang/Throwable
    //   1758	1771	1774	java/lang/Throwable
    //   1763	1786	1789	java/lang/Throwable
    //   1778	1804	1807	java/lang/Throwable
    //   1793	1834	1837	java/lang/Throwable
    //   1900	1927	1930	java/lang/Throwable
    //   1917	1945	1948	java/lang/Throwable
    //   1934	1975	1978	java/lang/Throwable
    //   1952	1986	1986	java/lang/Throwable
    //   1997	2013	2016	java/lang/Throwable
    //   2065	2079	2079	java/lang/Throwable
    //   2090	2103	2106	java/lang/Throwable
    //   2095	2118	2121	java/lang/Throwable
    //   2110	2136	2139	java/lang/Throwable
    //   2125	2166	2169	java/lang/Throwable
    //   2232	2259	2262	java/lang/Throwable
    //   2249	2280	2283	java/lang/Throwable
    //   2266	2310	2313	java/lang/Throwable
    //   2287	2321	2321	java/lang/Throwable
    //   2332	2348	2351	java/lang/Throwable
    //   2355	2445	2448	java/lang/Throwable
    //   2400	2497	2500	java/lang/Throwable
    //   2452	2508	2508	java/lang/Throwable
  }
  
  static {
    // Byte code:
    //   0: bipush #15
    //   2: anewarray java/lang/String
    //   5: astore #5
    //   7: iconst_0
    //   8: istore_3
    //   9: ldc 'Ã€eÃ«Â¥Â­>Ã†#/\\tÃ§Ã¯Ã´1JdÂˆÃ¿Ã¢Ã¶\\t1cÃ•ej&25>\\tÃ¡ÃŽÃÃ)ÂVÃ³l\\tXÂ¥Ã¸Â½Ã=ÂžWÂºMÃ¸Ã³Ã¬_~JyZÂ¨Ã­VxÃ"ÃµÂ>Ã´PHÂ¦Ã‹Â½v\Â¸ÃÂ–Â˜Ã¼Ã·H\\rÃ ÃªÂ˜ÃºÂ¿\\rMoÂ¨Â­Â´[,Ã—Â;Ã±\\fÃžÂ·Â¯Ã“ÃœÂ·Ã´Â»wÃœmÃ½Ã®!hÂŒÃƒ|Ã»eM{\Â¤+xIÃ‚Â»ÂŽÂ«k8U"Ã©ÂŽÂÃ‘)Â¯\\fÃÃ‹Ã™ÃŽi}Ã£Ã­Ãº\\bÂœh2IÃºU0ÃŠÃÂ²Â¹Ã§Â²ÂšÃ¯Â¾l*Ã§ÃŠÂÂ•QÃ‹Ã¼Â«Ã™Ã—Ã”kÃšlÂ’\\tFÂš;ZÂ·ÃÂšÂ‹ Â“Ã’-{\\nÂ·Â¶HAÂ¸Ã¶Ãš?Â‘\\rSÃ‹Ã´RÂ¹=zÂ¿;Â§Â²Â^Ã¥Â³O ^ÃŒÃºÃ²IÃUdÃŸÃ¸Ã°Ã±%~qA=ÃŠ=Ã„Ã‰[Ã’Ã‚Ã‡Ã¦&H\\tÃ“'Â‰Ã­Ã¡7DO'
    //   11: dup
    //   12: astore_2
    //   13: invokevirtual length : ()I
    //   16: istore #4
    //   18: bipush #9
    //   20: istore_1
    //   21: iconst_m1
    //   22: istore_0
    //   23: bipush #111
    //   25: iinc #0, 1
    //   28: aload_2
    //   29: iload_0
    //   30: dup
    //   31: iload_1
    //   32: iadd
    //   33: invokevirtual substring : (II)Ljava/lang/String;
    //   36: iconst_m1
    //   37: goto -> 143
    //   40: aload #5
    //   42: swap
    //   43: iload_3
    //   44: iinc #3, 1
    //   47: swap
    //   48: aastore
    //   49: iload_0
    //   50: iload_1
    //   51: iadd
    //   52: dup
    //   53: istore_0
    //   54: iload #4
    //   56: if_icmpge -> 68
    //   59: aload_2
    //   60: iload_0
    //   61: invokevirtual charAt : (I)C
    //   64: istore_1
    //   65: goto -> 23
    //   68: ldc 'Â€VFfÂ½Ã£a8/\\tÂ¿,Â¡)A\\nÃ¾Ã›'
    //   70: dup
    //   71: astore_2
    //   72: invokevirtual length : ()I
    //   75: istore #4
    //   77: bipush #9
    //   79: istore_1
    //   80: iconst_m1
    //   81: istore_0
    //   82: bipush #106
    //   84: iinc #0, 1
    //   87: aload_2
    //   88: iload_0
    //   89: dup
    //   90: iload_1
    //   91: iadd
    //   92: invokevirtual substring : (II)Ljava/lang/String;
    //   95: iconst_0
    //   96: goto -> 143
    //   99: aload #5
    //   101: swap
    //   102: iload_3
    //   103: iinc #3, 1
    //   106: swap
    //   107: aastore
    //   108: iload_0
    //   109: iload_1
    //   110: iadd
    //   111: dup
    //   112: istore_0
    //   113: iload #4
    //   115: if_icmpge -> 127
    //   118: aload_2
    //   119: iload_0
    //   120: invokevirtual charAt : (I)C
    //   123: istore_1
    //   124: goto -> 82
    //   127: aload #5
    //   129: putstatic burp/Ztdt.a : [Ljava/lang/String;
    //   132: bipush #15
    //   134: anewarray java/lang/String
    //   137: putstatic burp/Ztdt.b : [Ljava/lang/String;
    //   140: goto -> 300
    //   143: dup_x2
    //   144: pop
    //   145: invokevirtual toCharArray : ()[C
    //   148: dup_x1
    //   149: arraylength
    //   150: dup_x2
    //   151: pop
    //   152: iconst_0
    //   153: istore #6
    //   155: dup2_x1
    //   156: pop2
    //   157: dup_x2
    //   158: iconst_1
    //   159: if_icmpgt -> 260
    //   162: dup2
    //   163: swap
    //   164: iload #6
    //   166: dup2_x1
    //   167: caload
    //   168: swap
    //   169: iload #6
    //   171: bipush #7
    //   173: irem
    //   174: tableswitch default -> 242, 0 -> 212, 1 -> 217, 2 -> 222, 3 -> 227, 4 -> 232, 5 -> 237
    //   212: bipush #59
    //   214: goto -> 244
    //   217: bipush #90
    //   219: goto -> 244
    //   222: bipush #74
    //   224: goto -> 244
    //   227: bipush #107
    //   229: goto -> 244
    //   232: bipush #9
    //   234: goto -> 244
    //   237: bipush #65
    //   239: goto -> 244
    //   242: bipush #67
    //   244: ixor
    //   245: ixor
    //   246: i2c
    //   247: castore
    //   248: iinc #6, 1
    //   251: dup
    //   252: ifne -> 260
    //   255: dup2
    //   256: dup_x1
    //   257: goto -> 166
    //   260: dup2_x1
    //   261: pop2
    //   262: dup_x2
    //   263: iload #6
    //   265: if_icmpgt -> 162
    //   268: pop
    //   269: new java/lang/String
    //   272: dup_x1
    //   273: swap
    //   274: invokespecial <init> : ([C)V
    //   277: invokevirtual intern : ()Ljava/lang/String;
    //   280: swap
    //   281: pop
    //   282: swap
    //   283: tableswitch default -> 40, 0 -> 99
    //   300: sipush #26782
    //   303: sipush #22565
    //   306: invokestatic a : (II)Ljava/lang/String;
    //   309: putstatic burp/Ztdt.Zk : Ljava/lang/String;
    //   312: new java/math/BigInteger
    //   315: dup
    //   316: sipush #26770
    //   319: sipush #-10599
    //   322: invokestatic a : (II)Ljava/lang/String;
    //   325: invokespecial <init> : (Ljava/lang/String;)V
    //   328: putstatic burp/Ztdt.ZN : Ljava/lang/Object;
    //   331: return
  }
  
  private static Throwable a(Throwable paramThrowable) {
    return paramThrowable;
  }
  
  private static String a(int paramInt1, int paramInt2) {
    int i = (paramInt1 ^ 0x6895) & 0xFFFF;
    if (b[i] == null) {
      char[] arrayOfChar = a[i].toCharArray();
      switch (arrayOfChar[0] & 0xFF) {
        case 0:
        
        case 1:
        
        case 2:
        
        case 3:
        
        case 4:
        
        case 5:
        
        case 6:
        
        case 7:
        
        case 8:
        
        case 9:
        
        case 10:
        
        case 11:
        
        case 12:
        
        case 13:
        
        case 14:
        
        case 15:
        
        case 16:
        
        case 17:
        
        case 18:
        
        case 19:
        
        case 20:
        
        case 21:
        
        case 22:
        
        case 23:
        
        case 24:
        
        case 25:
        
        case 26:
        
        case 27:
        
        case 28:
        
        case 29:
        
        case 30:
        
        case 31:
        
        case 32:
        
        case 33:
        
        case 34:
        
        case 35:
        
        case 36:
        
        case 37:
        
        case 38:
        
        case 39:
        
        case 40:
        
        case 41:
        
        case 42:
        
        case 43:
        
        case 44:
        
        case 45:
        
        case 46:
        
        case 47:
        
        case 48:
        
        case 49:
        
        case 50:
        
        case 51:
        
        case 52:
        
        case 53:
        
        case 54:
        
        case 55:
        
        case 56:
        
        case 57:
        
        case 58:
        
        case 59:
        
        case 60:
        
        case 61:
        
        case 62:
        
        case 63:
        
        case 64:
        
        case 65:
        
        case 66:
        
        case 67:
        
        case 68:
        
        case 69:
        
        case 70:
        
        case 71:
        
        case 72:
        
        case 73:
        
        case 74:
        
        case 75:
        
        case 76:
        
        case 77:
        
        case 78:
        
        case 79:
        
        case 80:
        
        case 81:
        
        case 82:
        
        case 83:
        
        case 84:
        
        case 85:
        
        case 86:
        
        case 87:
        
        case 88:
        
        case 89:
        
        case 90:
        
        case 91:
        
        case 92:
        
        case 93:
        
        case 94:
        
        case 95:
        
        case 96:
        
        case 97:
        
        case 98:
        
        case 99:
        
        case 100:
        
        case 101:
        
        case 102:
        
        case 103:
        
        case 104:
        
        case 105:
        
        case 106:
        
        case 107:
        
        case 108:
        
        case 109:
        
        case 110:
        
        case 111:
        
        case 112:
        
        case 113:
        
        case 114:
        
        case 115:
        
        case 116:
        
        case 117:
        
        case 118:
        
        case 119:
        
        case 120:
        
        case 121:
        
        case 122:
        
        case 123:
        
        case 124:
        
        case 125:
        
        case 126:
        
        case 127:
        
        case 128:
        
        case 129:
        
        case 130:
        
        case 131:
        
        case 132:
        
        case 133:
        
        case 134:
        
        case 135:
        
        case 136:
        
        case 137:
        
        case 138:
        
        case 139:
        
        case 140:
        
        case 141:
        
        case 142:
        
        case 143:
        
        case 144:
        
        case 145:
        
        case 146:
        
        case 147:
        
        case 148:
        
        case 149:
        
        case 150:
        
        case 151:
        
        case 152:
        
        case 153:
        
        case 154:
        
        case 155:
        
        case 156:
        
        case 157:
        
        case 158:
        
        case 159:
        
        case 160:
        
        case 161:
        
        case 162:
        
        case 163:
        
        case 164:
        
        case 165:
        
        case 166:
        
        case 167:
        
        case 168:
        
        case 169:
        
        case 170:
        
        case 171:
        
        case 172:
        
        case 173:
        
        case 174:
        
        case 175:
        
        case 176:
        
        case 177:
        
        case 178:
        
        case 179:
        
        case 180:
        
        case 181:
        
        case 182:
        
        case 183:
        
        case 184:
        
        case 185:
        
        case 186:
        
        case 187:
        
        case 188:
        
        case 189:
        
        case 190:
        
        case 191:
        
        case 192:
        
        case 193:
        
        case 194:
        
        case 195:
        
        case 196:
        
        case 197:
        
        case 198:
        
        case 199:
        
        case 200:
        
        case 201:
        
        case 202:
        
        case 203:
        
        case 204:
        
        case 205:
        
        case 206:
        
        case 207:
        
        case 208:
        
        case 209:
        
        case 210:
        
        case 211:
        
        case 212:
        
        case 213:
        
        case 214:
        
        case 215:
        
        case 216:
        
        case 217:
        
        case 218:
        
        case 219:
        
        case 220:
        
        case 221:
        
        case 222:
        
        case 223:
        
        case 224:
        
        case 225:
        
        case 226:
        
        case 227:
        
        case 228:
        
        case 229:
        
        case 230:
        
        case 231:
        
        case 232:
        
        case 233:
        
        case 234:
        
        case 235:
        
        case 236:
        
        case 237:
        
        case 238:
        
        case 239:
        
        case 240:
        
        case 241:
        
        case 242:
        
        case 243:
        
        case 244:
        
        case 245:
        
        case 246:
        
        case 247:
        
        case 248:
        
        case 249:
        
        case 250:
        
        case 251:
        
        case 252:
        
        case 253:
        
        case 254:
        
        default:
          break;
      } 
      char c = 'Â„';
      int j = (paramInt2 & 0xFF) - c;
      if (j < 0)
        j += 256; 
      int k = ((paramInt2 & 0xFFFF) >>> 8) - c;
      if (k < 0)
        k += 256; 
      for (byte b = 0; b < arrayOfChar.length; b++) {
        int m = b % 2;
        if (m == 0) {
          arrayOfChar[b] = (char)(arrayOfChar[b] ^ j);
          j = ((j >>> 3 | j << 5) ^ arrayOfChar[b]) & 0xFF;
        } else {
          arrayOfChar[b] = (char)(arrayOfChar[b] ^ k);
          k = ((k >>> 3 | k << 5) ^ arrayOfChar[b]) & 0xFF;
        } 
      } 
      b[i] = (new String(arrayOfChar)).intern();
    } 
    return b[i];
  }
}


/* Location:              C:\Program Files\BurpSuitePro\burpsuite_pro.jar!\burp\Ztdt.class
 * Java compiler version: 21 (65.0)
 * JD-Core Version:       1.1.3
 */