package burp;

import java.math.BigInteger;

class Zth7 extends ClassLoader {
  static String Zf;
  
  static Object ZT;
  
  private static final String[] a;
  
  private static final String[] b;
  
  static boolean ZL(Object[] paramArrayOfObject, Object paramObject) throws Throwable {
    // Byte code:
    //   0: invokestatic ZN : ()Z
    //   3: istore_2
    //   4: sipush #882
    //   7: sipush #25263
    //   10: invokestatic a : (II)Ljava/lang/String;
    //   13: invokestatic forName : (Ljava/lang/String;)Ljava/lang/Class;
    //   16: invokestatic ZO : (Ljava/lang/Object;)V
    //   19: new java/lang/StringBuilder
    //   22: dup
    //   23: invokespecial <init> : ()V
    //   26: astore_3
    //   27: iconst_0
    //   28: istore #4
    //   30: iload #4
    //   32: bipush #32
    //   34: if_icmpge -> 1367
    //   37: iload #4
    //   39: tableswitch default -> 1360, 0 -> 180, 1 -> 217, 2 -> 254, 3 -> 291, 4 -> 328, 5 -> 365, 6 -> 402, 7 -> 439, 8 -> 476, 9 -> 513, 10 -> 550, 11 -> 587, 12 -> 624, 13 -> 661, 14 -> 698, 15 -> 735, 16 -> 772, 17 -> 809, 18 -> 846, 19 -> 883, 20 -> 920, 21 -> 957, 22 -> 994, 23 -> 1031, 24 -> 1068, 25 -> 1105, 26 -> 1142, 27 -> 1179, 28 -> 1216, 29 -> 1253, 30 -> 1290, 31 -> 1327
    //   180: aload_3
    //   181: getstatic burp/Zxn7.ZG : Ljava/lang/String;
    //   184: getstatic burp/Zeb7.ZJ : Ljava/lang/Object;
    //   187: checkcast java/math/BigInteger
    //   190: invokevirtual intValue : ()I
    //   193: bipush #32
    //   195: irem
    //   196: invokestatic abs : (I)I
    //   199: invokevirtual charAt : (I)C
    //   202: invokevirtual append : (C)Ljava/lang/StringBuilder;
    //   205: pop
    //   206: iload_2
    //   207: ifne -> 1360
    //   210: goto -> 217
    //   213: invokestatic a : (Ljava/lang/Throwable;)Ljava/lang/Throwable;
    //   216: athrow
    //   217: aload_3
    //   218: getstatic burp/Zml.ZN : Ljava/lang/String;
    //   221: getstatic burp/Zkht.ZR : Ljava/lang/Object;
    //   224: checkcast java/math/BigInteger
    //   227: invokevirtual intValue : ()I
    //   230: bipush #32
    //   232: irem
    //   233: invokestatic abs : (I)I
    //   236: invokevirtual charAt : (I)C
    //   239: invokevirtual append : (C)Ljava/lang/StringBuilder;
    //   242: pop
    //   243: iload_2
    //   244: ifne -> 1360
    //   247: goto -> 254
    //   250: invokestatic a : (Ljava/lang/Throwable;)Ljava/lang/Throwable;
    //   253: athrow
    //   254: aload_3
    //   255: getstatic burp/Zkvq.Zg : Ljava/lang/String;
    //   258: getstatic burp/Zxoa.Zr : Ljava/lang/Object;
    //   261: checkcast java/math/BigInteger
    //   264: invokevirtual intValue : ()I
    //   267: bipush #32
    //   269: irem
    //   270: invokestatic abs : (I)I
    //   273: invokevirtual charAt : (I)C
    //   276: invokevirtual append : (C)Ljava/lang/StringBuilder;
    //   279: pop
    //   280: iload_2
    //   281: ifne -> 1360
    //   284: goto -> 291
    //   287: invokestatic a : (Ljava/lang/Throwable;)Ljava/lang/Throwable;
    //   290: athrow
    //   291: aload_3
    //   292: getstatic burp/Ze_b.ZX : Ljava/lang/String;
    //   295: getstatic burp/Zb0s.Zv : Ljava/lang/Object;
    //   298: checkcast java/math/BigInteger
    //   301: invokevirtual intValue : ()I
    //   304: bipush #32
    //   306: irem
    //   307: invokestatic abs : (I)I
    //   310: invokevirtual charAt : (I)C
    //   313: invokevirtual append : (C)Ljava/lang/StringBuilder;
    //   316: pop
    //   317: iload_2
    //   318: ifne -> 1360
    //   321: goto -> 328
    //   324: invokestatic a : (Ljava/lang/Throwable;)Ljava/lang/Throwable;
    //   327: athrow
    //   328: aload_3
    //   329: getstatic burp/Zzoc.Zg : Ljava/lang/String;
    //   332: getstatic burp/Zlhm.ZT : Ljava/lang/Object;
    //   335: checkcast java/math/BigInteger
    //   338: invokevirtual intValue : ()I
    //   341: bipush #32
    //   343: irem
    //   344: invokestatic abs : (I)I
    //   347: invokevirtual charAt : (I)C
    //   350: invokevirtual append : (C)Ljava/lang/StringBuilder;
    //   353: pop
    //   354: iload_2
    //   355: ifne -> 1360
    //   358: goto -> 365
    //   361: invokestatic a : (Ljava/lang/Throwable;)Ljava/lang/Throwable;
    //   364: athrow
    //   365: aload_3
    //   366: getstatic burp/Zl8y.ZY : Ljava/lang/String;
    //   369: getstatic burp/Ztes.ZX : Ljava/lang/Object;
    //   372: checkcast java/math/BigInteger
    //   375: invokevirtual intValue : ()I
    //   378: bipush #32
    //   380: irem
    //   381: invokestatic abs : (I)I
    //   384: invokevirtual charAt : (I)C
    //   387: invokevirtual append : (C)Ljava/lang/StringBuilder;
    //   390: pop
    //   391: iload_2
    //   392: ifne -> 1360
    //   395: goto -> 402
    //   398: invokestatic a : (Ljava/lang/Throwable;)Ljava/lang/Throwable;
    //   401: athrow
    //   402: aload_3
    //   403: getstatic burp/Zgwq.ZV : Ljava/lang/String;
    //   406: getstatic burp/Zsqi.Zf : Ljava/lang/Object;
    //   409: checkcast java/math/BigInteger
    //   412: invokevirtual intValue : ()I
    //   415: bipush #32
    //   417: irem
    //   418: invokestatic abs : (I)I
    //   421: invokevirtual charAt : (I)C
    //   424: invokevirtual append : (C)Ljava/lang/StringBuilder;
    //   427: pop
    //   428: iload_2
    //   429: ifne -> 1360
    //   432: goto -> 439
    //   435: invokestatic a : (Ljava/lang/Throwable;)Ljava/lang/Throwable;
    //   438: athrow
    //   439: aload_3
    //   440: getstatic burp/Zb6e.ZR : Ljava/lang/String;
    //   443: getstatic burp/Zxo4.ZV : Ljava/lang/Object;
    //   446: checkcast java/math/BigInteger
    //   449: invokevirtual intValue : ()I
    //   452: bipush #32
    //   454: irem
    //   455: invokestatic abs : (I)I
    //   458: invokevirtual charAt : (I)C
    //   461: invokevirtual append : (C)Ljava/lang/StringBuilder;
    //   464: pop
    //   465: iload_2
    //   466: ifne -> 1360
    //   469: goto -> 476
    //   472: invokestatic a : (Ljava/lang/Throwable;)Ljava/lang/Throwable;
    //   475: athrow
    //   476: aload_3
    //   477: getstatic burp/Zem6.Zp : Ljava/lang/String;
    //   480: getstatic burp/Zsfj.ZL : Ljava/lang/Object;
    //   483: checkcast java/math/BigInteger
    //   486: invokevirtual intValue : ()I
    //   489: bipush #32
    //   491: irem
    //   492: invokestatic abs : (I)I
    //   495: invokevirtual charAt : (I)C
    //   498: invokevirtual append : (C)Ljava/lang/StringBuilder;
    //   501: pop
    //   502: iload_2
    //   503: ifne -> 1360
    //   506: goto -> 513
    //   509: invokestatic a : (Ljava/lang/Throwable;)Ljava/lang/Throwable;
    //   512: athrow
    //   513: aload_3
    //   514: getstatic burp/Zein.ZN : Ljava/lang/String;
    //   517: getstatic burp/Zkaw.ZB : Ljava/lang/Object;
    //   520: checkcast java/math/BigInteger
    //   523: invokevirtual intValue : ()I
    //   526: bipush #32
    //   528: irem
    //   529: invokestatic abs : (I)I
    //   532: invokevirtual charAt : (I)C
    //   535: invokevirtual append : (C)Ljava/lang/StringBuilder;
    //   538: pop
    //   539: iload_2
    //   540: ifne -> 1360
    //   543: goto -> 550
    //   546: invokestatic a : (Ljava/lang/Throwable;)Ljava/lang/Throwable;
    //   549: athrow
    //   550: aload_3
    //   551: getstatic burp/Zgl4.ZX : Ljava/lang/String;
    //   554: getstatic burp/Zxn9.ZN : Ljava/lang/Object;
    //   557: checkcast java/math/BigInteger
    //   560: invokevirtual intValue : ()I
    //   563: bipush #32
    //   565: irem
    //   566: invokestatic abs : (I)I
    //   569: invokevirtual charAt : (I)C
    //   572: invokevirtual append : (C)Ljava/lang/StringBuilder;
    //   575: pop
    //   576: iload_2
    //   577: ifne -> 1360
    //   580: goto -> 587
    //   583: invokestatic a : (Ljava/lang/Throwable;)Ljava/lang/Throwable;
    //   586: athrow
    //   587: aload_3
    //   588: getstatic burp/Zead.Zo : Ljava/lang/String;
    //   591: getstatic burp/Zzoc.Zx : Ljava/lang/Object;
    //   594: checkcast java/math/BigInteger
    //   597: invokevirtual intValue : ()I
    //   600: bipush #32
    //   602: irem
    //   603: invokestatic abs : (I)I
    //   606: invokevirtual charAt : (I)C
    //   609: invokevirtual append : (C)Ljava/lang/StringBuilder;
    //   612: pop
    //   613: iload_2
    //   614: ifne -> 1360
    //   617: goto -> 624
    //   620: invokestatic a : (Ljava/lang/Throwable;)Ljava/lang/Throwable;
    //   623: athrow
    //   624: aload_3
    //   625: getstatic burp/Zty2.ZR : Ljava/lang/String;
    //   628: getstatic burp/Ztys.Zs : Ljava/lang/Object;
    //   631: checkcast java/math/BigInteger
    //   634: invokevirtual intValue : ()I
    //   637: bipush #32
    //   639: irem
    //   640: invokestatic abs : (I)I
    //   643: invokevirtual charAt : (I)C
    //   646: invokevirtual append : (C)Ljava/lang/StringBuilder;
    //   649: pop
    //   650: iload_2
    //   651: ifne -> 1360
    //   654: goto -> 661
    //   657: invokestatic a : (Ljava/lang/Throwable;)Ljava/lang/Throwable;
    //   660: athrow
    //   661: aload_3
    //   662: getstatic burp/Zea9.Zd : Ljava/lang/String;
    //   665: getstatic burp/Zva.Zu : Ljava/lang/Object;
    //   668: checkcast java/math/BigInteger
    //   671: invokevirtual intValue : ()I
    //   674: bipush #32
    //   676: irem
    //   677: invokestatic abs : (I)I
    //   680: invokevirtual charAt : (I)C
    //   683: invokevirtual append : (C)Ljava/lang/StringBuilder;
    //   686: pop
    //   687: iload_2
    //   688: ifne -> 1360
    //   691: goto -> 698
    //   694: invokestatic a : (Ljava/lang/Throwable;)Ljava/lang/Throwable;
    //   697: athrow
    //   698: aload_3
    //   699: getstatic burp/Zt7w.Zi : Ljava/lang/String;
    //   702: getstatic burp/Zlp7.ZM : Ljava/lang/Object;
    //   705: checkcast java/math/BigInteger
    //   708: invokevirtual intValue : ()I
    //   711: bipush #32
    //   713: irem
    //   714: invokestatic abs : (I)I
    //   717: invokevirtual charAt : (I)C
    //   720: invokevirtual append : (C)Ljava/lang/StringBuilder;
    //   723: pop
    //   724: iload_2
    //   725: ifne -> 1360
    //   728: goto -> 735
    //   731: invokestatic a : (Ljava/lang/Throwable;)Ljava/lang/Throwable;
    //   734: athrow
    //   735: aload_3
    //   736: getstatic burp/Zx4k.ZC : Ljava/lang/String;
    //   739: getstatic burp/Zmly.ZT : Ljava/lang/Object;
    //   742: checkcast java/math/BigInteger
    //   745: invokevirtual intValue : ()I
    //   748: bipush #32
    //   750: irem
    //   751: invokestatic abs : (I)I
    //   754: invokevirtual charAt : (I)C
    //   757: invokevirtual append : (C)Ljava/lang/StringBuilder;
    //   760: pop
    //   761: iload_2
    //   762: ifne -> 1360
    //   765: goto -> 772
    //   768: invokestatic a : (Ljava/lang/Throwable;)Ljava/lang/Throwable;
    //   771: athrow
    //   772: aload_3
    //   773: getstatic burp/Zlo5.ZJ : Ljava/lang/String;
    //   776: getstatic burp/Zr_z.ZT : Ljava/lang/Object;
    //   779: checkcast java/math/BigInteger
    //   782: invokevirtual intValue : ()I
    //   785: bipush #32
    //   787: irem
    //   788: invokestatic abs : (I)I
    //   791: invokevirtual charAt : (I)C
    //   794: invokevirtual append : (C)Ljava/lang/StringBuilder;
    //   797: pop
    //   798: iload_2
    //   799: ifne -> 1360
    //   802: goto -> 809
    //   805: invokestatic a : (Ljava/lang/Throwable;)Ljava/lang/Throwable;
    //   808: athrow
    //   809: aload_3
    //   810: getstatic burp/Zefn.Ze : Ljava/lang/String;
    //   813: getstatic burp/Zz0.ZJ : Ljava/lang/Object;
    //   816: checkcast java/math/BigInteger
    //   819: invokevirtual intValue : ()I
    //   822: bipush #32
    //   824: irem
    //   825: invokestatic abs : (I)I
    //   828: invokevirtual charAt : (I)C
    //   831: invokevirtual append : (C)Ljava/lang/StringBuilder;
    //   834: pop
    //   835: iload_2
    //   836: ifne -> 1360
    //   839: goto -> 846
    //   842: invokestatic a : (Ljava/lang/Throwable;)Ljava/lang/Throwable;
    //   845: athrow
    //   846: aload_3
    //   847: getstatic burp/Ztex.Zx : Ljava/lang/String;
    //   850: getstatic burp/Zbp_.Zi : Ljava/lang/Object;
    //   853: checkcast java/math/BigInteger
    //   856: invokevirtual intValue : ()I
    //   859: bipush #32
    //   861: irem
    //   862: invokestatic abs : (I)I
    //   865: invokevirtual charAt : (I)C
    //   868: invokevirtual append : (C)Ljava/lang/StringBuilder;
    //   871: pop
    //   872: iload_2
    //   873: ifne -> 1360
    //   876: goto -> 883
    //   879: invokestatic a : (Ljava/lang/Throwable;)Ljava/lang/Throwable;
    //   882: athrow
    //   883: aload_3
    //   884: getstatic burp/Ze5f.Zt : Ljava/lang/String;
    //   887: getstatic burp/Zmt_.Zl : Ljava/lang/Object;
    //   890: checkcast java/math/BigInteger
    //   893: invokevirtual intValue : ()I
    //   896: bipush #32
    //   898: irem
    //   899: invokestatic abs : (I)I
    //   902: invokevirtual charAt : (I)C
    //   905: invokevirtual append : (C)Ljava/lang/StringBuilder;
    //   908: pop
    //   909: iload_2
    //   910: ifne -> 1360
    //   913: goto -> 920
    //   916: invokestatic a : (Ljava/lang/Throwable;)Ljava/lang/Throwable;
    //   919: athrow
    //   920: aload_3
    //   921: getstatic burp/Zttj.ZN : Ljava/lang/String;
    //   924: getstatic burp/Zegw.ZW : Ljava/lang/Object;
    //   927: checkcast java/math/BigInteger
    //   930: invokevirtual intValue : ()I
    //   933: bipush #32
    //   935: irem
    //   936: invokestatic abs : (I)I
    //   939: invokevirtual charAt : (I)C
    //   942: invokevirtual append : (C)Ljava/lang/StringBuilder;
    //   945: pop
    //   946: iload_2
    //   947: ifne -> 1360
    //   950: goto -> 957
    //   953: invokestatic a : (Ljava/lang/Throwable;)Ljava/lang/Throwable;
    //   956: athrow
    //   957: aload_3
    //   958: getstatic burp/Zktq.Zc : Ljava/lang/String;
    //   961: getstatic burp/Zxt5.ZG : Ljava/lang/Object;
    //   964: checkcast java/math/BigInteger
    //   967: invokevirtual intValue : ()I
    //   970: bipush #32
    //   972: irem
    //   973: invokestatic abs : (I)I
    //   976: invokevirtual charAt : (I)C
    //   979: invokevirtual append : (C)Ljava/lang/StringBuilder;
    //   982: pop
    //   983: iload_2
    //   984: ifne -> 1360
    //   987: goto -> 994
    //   990: invokestatic a : (Ljava/lang/Throwable;)Ljava/lang/Throwable;
    //   993: athrow
    //   994: aload_3
    //   995: getstatic burp/Zg0j.Ze : Ljava/lang/String;
    //   998: getstatic burp/Zlhm.ZT : Ljava/lang/Object;
    //   1001: checkcast java/math/BigInteger
    //   1004: invokevirtual intValue : ()I
    //   1007: bipush #32
    //   1009: irem
    //   1010: invokestatic abs : (I)I
    //   1013: invokevirtual charAt : (I)C
    //   1016: invokevirtual append : (C)Ljava/lang/StringBuilder;
    //   1019: pop
    //   1020: iload_2
    //   1021: ifne -> 1360
    //   1024: goto -> 1031
    //   1027: invokestatic a : (Ljava/lang/Throwable;)Ljava/lang/Throwable;
    //   1030: athrow
    //   1031: aload_3
    //   1032: getstatic burp/Zttq.ZO : Ljava/lang/String;
    //   1035: getstatic burp/Zram.ZF : Ljava/lang/Object;
    //   1038: checkcast java/math/BigInteger
    //   1041: invokevirtual intValue : ()I
    //   1044: bipush #32
    //   1046: irem
    //   1047: invokestatic abs : (I)I
    //   1050: invokevirtual charAt : (I)C
    //   1053: invokevirtual append : (C)Ljava/lang/StringBuilder;
    //   1056: pop
    //   1057: iload_2
    //   1058: ifne -> 1360
    //   1061: goto -> 1068
    //   1064: invokestatic a : (Ljava/lang/Throwable;)Ljava/lang/Throwable;
    //   1067: athrow
    //   1068: aload_3
    //   1069: getstatic burp/Zk7o.Zb : Ljava/lang/String;
    //   1072: getstatic burp/Zmd.ZU : Ljava/lang/Object;
    //   1075: checkcast java/math/BigInteger
    //   1078: invokevirtual intValue : ()I
    //   1081: bipush #32
    //   1083: irem
    //   1084: invokestatic abs : (I)I
    //   1087: invokevirtual charAt : (I)C
    //   1090: invokevirtual append : (C)Ljava/lang/StringBuilder;
    //   1093: pop
    //   1094: iload_2
    //   1095: ifne -> 1360
    //   1098: goto -> 1105
    //   1101: invokestatic a : (Ljava/lang/Throwable;)Ljava/lang/Throwable;
    //   1104: athrow
    //   1105: aload_3
    //   1106: getstatic burp/Zmpp.Zk : Ljava/lang/String;
    //   1109: getstatic burp/Zlkm.ZQ : Ljava/lang/Object;
    //   1112: checkcast java/math/BigInteger
    //   1115: invokevirtual intValue : ()I
    //   1118: bipush #32
    //   1120: irem
    //   1121: invokestatic abs : (I)I
    //   1124: invokevirtual charAt : (I)C
    //   1127: invokevirtual append : (C)Ljava/lang/StringBuilder;
    //   1130: pop
    //   1131: iload_2
    //   1132: ifne -> 1360
    //   1135: goto -> 1142
    //   1138: invokestatic a : (Ljava/lang/Throwable;)Ljava/lang/Throwable;
    //   1141: athrow
    //   1142: aload_3
    //   1143: getstatic burp/Zmh5.Zh : Ljava/lang/String;
    //   1146: getstatic burp/Ztzj.Zv : Ljava/lang/Object;
    //   1149: checkcast java/math/BigInteger
    //   1152: invokevirtual intValue : ()I
    //   1155: bipush #32
    //   1157: irem
    //   1158: invokestatic abs : (I)I
    //   1161: invokevirtual charAt : (I)C
    //   1164: invokevirtual append : (C)Ljava/lang/StringBuilder;
    //   1167: pop
    //   1168: iload_2
    //   1169: ifne -> 1360
    //   1172: goto -> 1179
    //   1175: invokestatic a : (Ljava/lang/Throwable;)Ljava/lang/Throwable;
    //   1178: athrow
    //   1179: aload_3
    //   1180: getstatic burp/Zg99.ZH : Ljava/lang/String;
    //   1183: getstatic burp/Zmf6.ZD : Ljava/lang/Object;
    //   1186: checkcast java/math/BigInteger
    //   1189: invokevirtual intValue : ()I
    //   1192: bipush #32
    //   1194: irem
    //   1195: invokestatic abs : (I)I
    //   1198: invokevirtual charAt : (I)C
    //   1201: invokevirtual append : (C)Ljava/lang/StringBuilder;
    //   1204: pop
    //   1205: iload_2
    //   1206: ifne -> 1360
    //   1209: goto -> 1216
    //   1212: invokestatic a : (Ljava/lang/Throwable;)Ljava/lang/Throwable;
    //   1215: athrow
    //   1216: aload_3
    //   1217: getstatic burp/Zxzd.ZM : Ljava/lang/String;
    //   1220: getstatic burp/Zmjw.ZD : Ljava/lang/Object;
    //   1223: checkcast java/math/BigInteger
    //   1226: invokevirtual intValue : ()I
    //   1229: bipush #32
    //   1231: irem
    //   1232: invokestatic abs : (I)I
    //   1235: invokevirtual charAt : (I)C
    //   1238: invokevirtual append : (C)Ljava/lang/StringBuilder;
    //   1241: pop
    //   1242: iload_2
    //   1243: ifne -> 1360
    //   1246: goto -> 1253
    //   1249: invokestatic a : (Ljava/lang/Throwable;)Ljava/lang/Throwable;
    //   1252: athrow
    //   1253: aload_3
    //   1254: getstatic burp/Zt7x.Zu : Ljava/lang/String;
    //   1257: getstatic burp/Zl_u.ZR : Ljava/lang/Object;
    //   1260: checkcast java/math/BigInteger
    //   1263: invokevirtual intValue : ()I
    //   1266: bipush #32
    //   1268: irem
    //   1269: invokestatic abs : (I)I
    //   1272: invokevirtual charAt : (I)C
    //   1275: invokevirtual append : (C)Ljava/lang/StringBuilder;
    //   1278: pop
    //   1279: iload_2
    //   1280: ifne -> 1360
    //   1283: goto -> 1290
    //   1286: invokestatic a : (Ljava/lang/Throwable;)Ljava/lang/Throwable;
    //   1289: athrow
    //   1290: aload_3
    //   1291: getstatic burp/Zzou.ZN : Ljava/lang/String;
    //   1294: getstatic burp/Zb3l.Zl : Ljava/lang/Object;
    //   1297: checkcast java/math/BigInteger
    //   1300: invokevirtual intValue : ()I
    //   1303: bipush #32
    //   1305: irem
    //   1306: invokestatic abs : (I)I
    //   1309: invokevirtual charAt : (I)C
    //   1312: invokevirtual append : (C)Ljava/lang/StringBuilder;
    //   1315: pop
    //   1316: iload_2
    //   1317: ifne -> 1360
    //   1320: goto -> 1327
    //   1323: invokestatic a : (Ljava/lang/Throwable;)Ljava/lang/Throwable;
    //   1326: athrow
    //   1327: aload_3
    //   1328: getstatic burp/Zxxo.ZH : Ljava/lang/String;
    //   1331: getstatic burp/Zt0t.ZL : Ljava/lang/Object;
    //   1334: checkcast java/math/BigInteger
    //   1337: invokevirtual intValue : ()I
    //   1340: bipush #32
    //   1342: irem
    //   1343: invokestatic abs : (I)I
    //   1346: invokevirtual charAt : (I)C
    //   1349: invokevirtual append : (C)Ljava/lang/StringBuilder;
    //   1352: pop
    //   1353: goto -> 1360
    //   1356: invokestatic a : (Ljava/lang/Throwable;)Ljava/lang/Throwable;
    //   1359: athrow
    //   1360: iinc #4, 1
    //   1363: iload_2
    //   1364: ifne -> 30
    //   1367: aload_3
    //   1368: invokevirtual toString : ()Ljava/lang/String;
    //   1371: putstatic burp/Zl15.ZI : Ljava/lang/String;
    //   1374: sipush #889
    //   1377: getstatic burp/Zl_k.ZH : Ljava/lang/Object;
    //   1380: checkcast java/math/BigInteger
    //   1383: getstatic burp/Zkby.Zv : Ljava/lang/Object;
    //   1386: checkcast java/math/BigInteger
    //   1389: invokevirtual subtract : (Ljava/math/BigInteger;)Ljava/math/BigInteger;
    //   1392: putstatic burp/Zsin.Za : Ljava/lang/Object;
    //   1395: sipush #-10003
    //   1398: invokestatic a : (II)Ljava/lang/String;
    //   1401: iconst_1
    //   1402: ldc burp/Zxyp
    //   1404: invokevirtual getClassLoader : ()Ljava/lang/ClassLoader;
    //   1407: invokestatic forName : (Ljava/lang/String;ZLjava/lang/ClassLoader;)Ljava/lang/Class;
    //   1410: invokevirtual getDeclaredFields : ()[Ljava/lang/reflect/Field;
    //   1413: astore #4
    //   1415: aload #4
    //   1417: arraylength
    //   1418: istore #5
    //   1420: iconst_0
    //   1421: istore #6
    //   1423: iload #6
    //   1425: iload #5
    //   1427: if_icmpge -> 1565
    //   1430: aload #4
    //   1432: iload #6
    //   1434: aaload
    //   1435: astore #7
    //   1437: aload #7
    //   1439: invokevirtual getModifiers : ()I
    //   1442: invokestatic isStatic : (I)Z
    //   1445: ifne -> 1455
    //   1448: goto -> 1558
    //   1451: invokestatic a : (Ljava/lang/Throwable;)Ljava/lang/Throwable;
    //   1454: athrow
    //   1455: aload #7
    //   1457: invokevirtual getType : ()Ljava/lang/Class;
    //   1460: astore #8
    //   1462: aload #8
    //   1464: ifnull -> 1545
    //   1467: aload #8
    //   1469: invokevirtual isPrimitive : ()Z
    //   1472: ifne -> 1545
    //   1475: goto -> 1482
    //   1478: invokestatic a : (Ljava/lang/Throwable;)Ljava/lang/Throwable;
    //   1481: athrow
    //   1482: aload #8
    //   1484: invokevirtual getPackage : ()Ljava/lang/Package;
    //   1487: ifnull -> 1545
    //   1490: goto -> 1497
    //   1493: invokestatic a : (Ljava/lang/Throwable;)Ljava/lang/Throwable;
    //   1496: athrow
    //   1497: aload #8
    //   1499: invokevirtual getPackage : ()Ljava/lang/Package;
    //   1502: invokevirtual getName : ()Ljava/lang/String;
    //   1505: ifnull -> 1545
    //   1508: goto -> 1515
    //   1511: invokestatic a : (Ljava/lang/Throwable;)Ljava/lang/Throwable;
    //   1514: athrow
    //   1515: aload #8
    //   1517: invokevirtual getPackage : ()Ljava/lang/Package;
    //   1520: invokevirtual getName : ()Ljava/lang/String;
    //   1523: sipush #888
    //   1526: sipush #-22612
    //   1529: invokestatic a : (II)Ljava/lang/String;
    //   1532: invokevirtual startsWith : (Ljava/lang/String;)Z
    //   1535: ifne -> 1545
    //   1538: goto -> 1545
    //   1541: invokestatic a : (Ljava/lang/Throwable;)Ljava/lang/Throwable;
    //   1544: athrow
    //   1545: aload #7
    //   1547: iconst_1
    //   1548: invokevirtual setAccessible : (Z)V
    //   1551: aload #7
    //   1553: aconst_null
    //   1554: invokevirtual get : (Ljava/lang/Object;)Ljava/lang/Object;
    //   1557: pop
    //   1558: iinc #6, 1
    //   1561: iload_2
    //   1562: ifne -> 1423
    //   1565: sipush #891
    //   1568: sipush #26659
    //   1571: invokestatic a : (II)Ljava/lang/String;
    //   1574: invokestatic forName : (Ljava/lang/String;)Ljava/lang/Class;
    //   1577: invokevirtual getDeclaredMethods : ()[Ljava/lang/reflect/Method;
    //   1580: astore #4
    //   1582: aload #4
    //   1584: arraylength
    //   1585: istore #5
    //   1587: iconst_0
    //   1588: istore #6
    //   1590: iload #6
    //   1592: iload #5
    //   1594: if_icmpge -> 1727
    //   1597: aload #4
    //   1599: iload #6
    //   1601: aaload
    //   1602: astore #7
    //   1604: aload #7
    //   1606: invokevirtual getParameterTypes : ()[Ljava/lang/Class;
    //   1609: pop
    //   1610: aload #7
    //   1612: invokevirtual getModifiers : ()I
    //   1615: invokestatic isStatic : (I)Z
    //   1618: ifeq -> 1713
    //   1621: aload #7
    //   1623: invokevirtual getParameterTypes : ()[Ljava/lang/Class;
    //   1626: arraylength
    //   1627: iconst_2
    //   1628: if_icmpne -> 1713
    //   1631: goto -> 1638
    //   1634: invokestatic a : (Ljava/lang/Throwable;)Ljava/lang/Throwable;
    //   1637: athrow
    //   1638: aload #7
    //   1640: invokevirtual getReturnType : ()Ljava/lang/Class;
    //   1643: getstatic java/lang/Void.TYPE : Ljava/lang/Class;
    //   1646: invokevirtual equals : (Ljava/lang/Object;)Z
    //   1649: ifeq -> 1713
    //   1652: goto -> 1659
    //   1655: invokestatic a : (Ljava/lang/Throwable;)Ljava/lang/Throwable;
    //   1658: athrow
    //   1659: aload #7
    //   1661: iconst_1
    //   1662: invokevirtual setAccessible : (Z)V
    //   1665: aload #7
    //   1667: aconst_null
    //   1668: iconst_2
    //   1669: anewarray java/lang/Object
    //   1672: dup
    //   1673: iconst_0
    //   1674: aload_0
    //   1675: aastore
    //   1676: dup
    //   1677: iconst_1
    //   1678: aload_1
    //   1679: ifnonnull -> 1697
    //   1682: goto -> 1689
    //   1685: invokestatic a : (Ljava/lang/Throwable;)Ljava/lang/Throwable;
    //   1688: athrow
    //   1689: aload_1
    //   1690: goto -> 1704
    //   1693: invokestatic a : (Ljava/lang/Throwable;)Ljava/lang/Throwable;
    //   1696: athrow
    //   1697: aload_1
    //   1698: checkcast [B
    //   1701: invokevirtual clone : ()Ljava/lang/Object;
    //   1704: aastore
    //   1705: invokevirtual invoke : (Ljava/lang/Object;[Ljava/lang/Object;)Ljava/lang/Object;
    //   1708: pop
    //   1709: iload_2
    //   1710: ifne -> 1727
    //   1713: iinc #6, 1
    //   1716: iload_2
    //   1717: ifne -> 1590
    //   1720: goto -> 1727
    //   1723: invokestatic a : (Ljava/lang/Throwable;)Ljava/lang/Throwable;
    //   1726: athrow
    //   1727: iconst_0
    //   1728: istore #4
    //   1730: sipush #883
    //   1733: sipush #29136
    //   1736: invokestatic a : (II)Ljava/lang/String;
    //   1739: iconst_1
    //   1740: ldc burp/Zlwm
    //   1742: invokevirtual getClassLoader : ()Ljava/lang/ClassLoader;
    //   1745: invokestatic forName : (Ljava/lang/String;ZLjava/lang/ClassLoader;)Ljava/lang/Class;
    //   1748: invokevirtual getDeclaredFields : ()[Ljava/lang/reflect/Field;
    //   1751: astore #5
    //   1753: aload #5
    //   1755: arraylength
    //   1756: istore #6
    //   1758: iconst_0
    //   1759: istore #7
    //   1761: iload #7
    //   1763: iload #6
    //   1765: if_icmpge -> 1903
    //   1768: aload #5
    //   1770: iload #7
    //   1772: aaload
    //   1773: astore #8
    //   1775: aload #8
    //   1777: invokevirtual getModifiers : ()I
    //   1780: invokestatic isStatic : (I)Z
    //   1783: ifne -> 1793
    //   1786: goto -> 1896
    //   1789: invokestatic a : (Ljava/lang/Throwable;)Ljava/lang/Throwable;
    //   1792: athrow
    //   1793: aload #8
    //   1795: invokevirtual getType : ()Ljava/lang/Class;
    //   1798: astore #9
    //   1800: aload #9
    //   1802: ifnull -> 1883
    //   1805: aload #9
    //   1807: invokevirtual isPrimitive : ()Z
    //   1810: ifne -> 1883
    //   1813: goto -> 1820
    //   1816: invokestatic a : (Ljava/lang/Throwable;)Ljava/lang/Throwable;
    //   1819: athrow
    //   1820: aload #9
    //   1822: invokevirtual getPackage : ()Ljava/lang/Package;
    //   1825: ifnull -> 1883
    //   1828: goto -> 1835
    //   1831: invokestatic a : (Ljava/lang/Throwable;)Ljava/lang/Throwable;
    //   1834: athrow
    //   1835: aload #9
    //   1837: invokevirtual getPackage : ()Ljava/lang/Package;
    //   1840: invokevirtual getName : ()Ljava/lang/String;
    //   1843: ifnull -> 1883
    //   1846: goto -> 1853
    //   1849: invokestatic a : (Ljava/lang/Throwable;)Ljava/lang/Throwable;
    //   1852: athrow
    //   1853: aload #9
    //   1855: invokevirtual getPackage : ()Ljava/lang/Package;
    //   1858: invokevirtual getName : ()Ljava/lang/String;
    //   1861: sipush #884
    //   1864: sipush #-1990
    //   1867: invokestatic a : (II)Ljava/lang/String;
    //   1870: invokevirtual startsWith : (Ljava/lang/String;)Z
    //   1873: ifne -> 1883
    //   1876: goto -> 1883
    //   1879: invokestatic a : (Ljava/lang/Throwable;)Ljava/lang/Throwable;
    //   1882: athrow
    //   1883: aload #8
    //   1885: iconst_1
    //   1886: invokevirtual setAccessible : (Z)V
    //   1889: aload #8
    //   1891: aconst_null
    //   1892: invokevirtual get : (Ljava/lang/Object;)Ljava/lang/Object;
    //   1895: pop
    //   1896: iinc #7, 1
    //   1899: iload_2
    //   1900: ifne -> 1761
    //   1903: sipush #885
    //   1906: sipush #7300
    //   1909: invokestatic a : (II)Ljava/lang/String;
    //   1912: invokestatic forName : (Ljava/lang/String;)Ljava/lang/Class;
    //   1915: invokevirtual getDeclaredMethods : ()[Ljava/lang/reflect/Method;
    //   1918: astore #5
    //   1920: aload #5
    //   1922: arraylength
    //   1923: istore #6
    //   1925: iconst_0
    //   1926: istore #7
    //   1928: iload #7
    //   1930: iload #6
    //   1932: if_icmpge -> 2069
    //   1935: aload #5
    //   1937: iload #7
    //   1939: aaload
    //   1940: astore #8
    //   1942: aload #8
    //   1944: invokevirtual getParameterTypes : ()[Ljava/lang/Class;
    //   1947: pop
    //   1948: aload #8
    //   1950: invokevirtual getModifiers : ()I
    //   1953: invokestatic isStatic : (I)Z
    //   1956: ifeq -> 2055
    //   1959: aload #8
    //   1961: invokevirtual getParameterTypes : ()[Ljava/lang/Class;
    //   1964: arraylength
    //   1965: iconst_2
    //   1966: if_icmpne -> 2055
    //   1969: goto -> 1976
    //   1972: invokestatic a : (Ljava/lang/Throwable;)Ljava/lang/Throwable;
    //   1975: athrow
    //   1976: aload #8
    //   1978: invokevirtual getReturnType : ()Ljava/lang/Class;
    //   1981: getstatic java/lang/Boolean.TYPE : Ljava/lang/Class;
    //   1984: if_acmpne -> 2055
    //   1987: goto -> 1994
    //   1990: invokestatic a : (Ljava/lang/Throwable;)Ljava/lang/Throwable;
    //   1993: athrow
    //   1994: aload #8
    //   1996: iconst_1
    //   1997: invokevirtual setAccessible : (Z)V
    //   2000: aload #8
    //   2002: aconst_null
    //   2003: iconst_2
    //   2004: anewarray java/lang/Object
    //   2007: dup
    //   2008: iconst_0
    //   2009: aload_0
    //   2010: aastore
    //   2011: dup
    //   2012: iconst_1
    //   2013: aload_1
    //   2014: ifnonnull -> 2032
    //   2017: goto -> 2024
    //   2020: invokestatic a : (Ljava/lang/Throwable;)Ljava/lang/Throwable;
    //   2023: athrow
    //   2024: aload_1
    //   2025: goto -> 2039
    //   2028: invokestatic a : (Ljava/lang/Throwable;)Ljava/lang/Throwable;
    //   2031: athrow
    //   2032: aload_1
    //   2033: checkcast [B
    //   2036: invokevirtual clone : ()Ljava/lang/Object;
    //   2039: aastore
    //   2040: invokevirtual invoke : (Ljava/lang/Object;[Ljava/lang/Object;)Ljava/lang/Object;
    //   2043: checkcast java/lang/Boolean
    //   2046: invokevirtual booleanValue : ()Z
    //   2049: istore #4
    //   2051: iload_2
    //   2052: ifne -> 2069
    //   2055: iinc #7, 1
    //   2058: iload_2
    //   2059: ifne -> 1928
    //   2062: goto -> 2069
    //   2065: invokestatic a : (Ljava/lang/Throwable;)Ljava/lang/Throwable;
    //   2068: athrow
    //   2069: iload #4
    //   2071: ireturn
    //   2072: astore_3
    //   2073: new java/lang/Exception
    //   2076: dup
    //   2077: aload_3
    //   2078: invokevirtual getMessage : ()Ljava/lang/String;
    //   2081: invokespecial <init> : (Ljava/lang/String;)V
    //   2084: athrow
    // Exception table:
    //   from	to	target	type
    //   4	2071	2072	java/lang/Throwable
    //   37	210	213	java/lang/Throwable
    //   180	247	250	java/lang/Throwable
    //   217	284	287	java/lang/Throwable
    //   254	321	324	java/lang/Throwable
    //   291	358	361	java/lang/Throwable
    //   328	395	398	java/lang/Throwable
    //   365	432	435	java/lang/Throwable
    //   402	469	472	java/lang/Throwable
    //   439	506	509	java/lang/Throwable
    //   476	543	546	java/lang/Throwable
    //   513	580	583	java/lang/Throwable
    //   550	617	620	java/lang/Throwable
    //   587	654	657	java/lang/Throwable
    //   624	691	694	java/lang/Throwable
    //   661	728	731	java/lang/Throwable
    //   698	765	768	java/lang/Throwable
    //   735	802	805	java/lang/Throwable
    //   772	839	842	java/lang/Throwable
    //   809	876	879	java/lang/Throwable
    //   846	913	916	java/lang/Throwable
    //   883	950	953	java/lang/Throwable
    //   920	987	990	java/lang/Throwable
    //   957	1024	1027	java/lang/Throwable
    //   994	1061	1064	java/lang/Throwable
    //   1031	1098	1101	java/lang/Throwable
    //   1068	1135	1138	java/lang/Throwable
    //   1105	1172	1175	java/lang/Throwable
    //   1142	1209	1212	java/lang/Throwable
    //   1179	1246	1249	java/lang/Throwable
    //   1216	1283	1286	java/lang/Throwable
    //   1253	1320	1323	java/lang/Throwable
    //   1290	1353	1356	java/lang/Throwable
    //   1437	1451	1451	java/lang/Throwable
    //   1462	1475	1478	java/lang/Throwable
    //   1467	1490	1493	java/lang/Throwable
    //   1482	1508	1511	java/lang/Throwable
    //   1497	1538	1541	java/lang/Throwable
    //   1604	1631	1634	java/lang/Throwable
    //   1621	1652	1655	java/lang/Throwable
    //   1638	1682	1685	java/lang/Throwable
    //   1659	1693	1693	java/lang/Throwable
    //   1704	1720	1723	java/lang/Throwable
    //   1775	1789	1789	java/lang/Throwable
    //   1800	1813	1816	java/lang/Throwable
    //   1805	1828	1831	java/lang/Throwable
    //   1820	1846	1849	java/lang/Throwable
    //   1835	1876	1879	java/lang/Throwable
    //   1942	1969	1972	java/lang/Throwable
    //   1959	1987	1990	java/lang/Throwable
    //   1976	2017	2020	java/lang/Throwable
    //   1994	2028	2028	java/lang/Throwable
    //   2051	2062	2065	java/lang/Throwable
  }
  
  static void ZN(Object[] paramArrayOfObject, Object paramObject) throws Throwable {}
  
  static void ZN(Object paramObject) {
    Zl3l.Z_ = a(881, -6467);
    Zl3l.Zv = new BigInteger(a(886, 32679));
    boolean bool = Zt2e.ZN();
    try {
      try {
        if (Zek5.ZE.charAt(Math.abs(((BigInteger)Zdm.ZA).intValue() % 32)) <= Zle4.ZX.charAt(Math.abs(((BigInteger)Zdm.ZA).intValue() % 32))) {
          try {
            Zmtf.ZN(Class.forName(a(887, 31397)));
            if (!bool)
              Zb6b.Zo(Class.forName(a(880, 13479))); 
          } catch (Throwable throwable) {
            throw a(null);
          } 
          return;
        } 
      } catch (Throwable throwable) {
        throw a(null);
      } 
      Zb6b.Zo(Class.forName(a(880, 13479)));
    } catch (Throwable throwable) {}
  }
  
  static {
    // Byte code:
    //   0: bipush #12
    //   2: anewarray java/lang/String
    //   5: astore #5
    //   7: iconst_0
    //   8: istore_3
    //   9: ldc 'Ãƒ|OÃ—Ã€Ã­Â½\\t4FÂ‚$\\bÂ­\\tÂ±ÂŽ UÂšÂ«ÃœÂ¡Âœt@AÂ™Ã…Â‹"Â¶V<[Âš;UÂ¾Â¾Ã±rÂ‰DÂ™Ã¿b\\tÃ©[9Â‡Ã™Ã {V\\t0xÃ£UÂ©Â‡MÃ·Â·Ã§ÃµÂ±1Âš%FÃMÂ€AAÃ"HCÃ¶Â¯\?%W\\nÂ§FmLÃ®Ã°{Â“a Â¨Ã§isoÃÂ©9ÂFÃŸÃŽ\\ny@Ã¶Â§Ã·Ã–Â¨ÃžS&jH&YÂ€Â Â {pÂ£Âž\\tÂ”ÃƒÂ–Â”ÂŠÂ»O#Ã“`Â‘\\bÃž\\tÃ¨ÂÃ¾{Ã¶sÂž ÂšÃ¦Ã»ÃNÃ¦Â©Ã°ÂœÃ¬Â·Â¯jÃ¹zÂ™/Ã¯Ã©Â¤Â¨- Â£pÂ‰?zuXÃ´'
    //   11: dup
    //   12: astore_2
    //   13: invokevirtual length : ()I
    //   16: istore #4
    //   18: bipush #9
    //   20: istore_1
    //   21: iconst_m1
    //   22: istore_0
    //   23: bipush #106
    //   25: iinc #0, 1
    //   28: aload_2
    //   29: iload_0
    //   30: dup
    //   31: iload_1
    //   32: iadd
    //   33: invokevirtual substring : (II)Ljava/lang/String;
    //   36: iconst_m1
    //   37: goto -> 143
    //   40: aload #5
    //   42: swap
    //   43: iload_3
    //   44: iinc #3, 1
    //   47: swap
    //   48: aastore
    //   49: iload_0
    //   50: iload_1
    //   51: iadd
    //   52: dup
    //   53: istore_0
    //   54: iload #4
    //   56: if_icmpge -> 68
    //   59: aload_2
    //   60: iload_0
    //   61: invokevirtual charAt : (I)C
    //   64: istore_1
    //   65: goto -> 23
    //   68: ldc 'ÃœÃºK;|TÃ¢Âº>Â¸'
    //   70: dup
    //   71: astore_2
    //   72: invokevirtual length : ()I
    //   75: istore #4
    //   77: bipush #9
    //   79: istore_1
    //   80: iconst_m1
    //   81: istore_0
    //   82: bipush #24
    //   84: iinc #0, 1
    //   87: aload_2
    //   88: iload_0
    //   89: dup
    //   90: iload_1
    //   91: iadd
    //   92: invokevirtual substring : (II)Ljava/lang/String;
    //   95: iconst_0
    //   96: goto -> 143
    //   99: aload #5
    //   101: swap
    //   102: iload_3
    //   103: iinc #3, 1
    //   106: swap
    //   107: aastore
    //   108: iload_0
    //   109: iload_1
    //   110: iadd
    //   111: dup
    //   112: istore_0
    //   113: iload #4
    //   115: if_icmpge -> 127
    //   118: aload_2
    //   119: iload_0
    //   120: invokevirtual charAt : (I)C
    //   123: istore_1
    //   124: goto -> 82
    //   127: aload #5
    //   129: putstatic burp/Zth7.a : [Ljava/lang/String;
    //   132: bipush #12
    //   134: anewarray java/lang/String
    //   137: putstatic burp/Zth7.b : [Ljava/lang/String;
    //   140: goto -> 300
    //   143: dup_x2
    //   144: pop
    //   145: invokevirtual toCharArray : ()[C
    //   148: dup_x1
    //   149: arraylength
    //   150: dup_x2
    //   151: pop
    //   152: iconst_0
    //   153: istore #6
    //   155: dup2_x1
    //   156: pop2
    //   157: dup_x2
    //   158: iconst_1
    //   159: if_icmpgt -> 259
    //   162: dup2
    //   163: swap
    //   164: iload #6
    //   166: dup2_x1
    //   167: caload
    //   168: swap
    //   169: iload #6
    //   171: bipush #7
    //   173: irem
    //   174: tableswitch default -> 241, 0 -> 212, 1 -> 217, 2 -> 222, 3 -> 227, 4 -> 232, 5 -> 237
    //   212: bipush #97
    //   214: goto -> 243
    //   217: bipush #73
    //   219: goto -> 243
    //   222: bipush #83
    //   224: goto -> 243
    //   227: bipush #73
    //   229: goto -> 243
    //   232: bipush #7
    //   234: goto -> 243
    //   237: iconst_3
    //   238: goto -> 243
    //   241: bipush #87
    //   243: ixor
    //   244: ixor
    //   245: i2c
    //   246: castore
    //   247: iinc #6, 1
    //   250: dup
    //   251: ifne -> 259
    //   254: dup2
    //   255: dup_x1
    //   256: goto -> 166
    //   259: dup2_x1
    //   260: pop2
    //   261: dup_x2
    //   262: iload #6
    //   264: if_icmpgt -> 162
    //   267: pop
    //   268: new java/lang/String
    //   271: dup_x1
    //   272: swap
    //   273: invokespecial <init> : ([C)V
    //   276: invokevirtual intern : ()Ljava/lang/String;
    //   279: swap
    //   280: pop
    //   281: swap
    //   282: tableswitch default -> 40, 0 -> 99
    //   300: sipush #890
    //   303: sipush #-13287
    //   306: invokestatic a : (II)Ljava/lang/String;
    //   309: putstatic burp/Zth7.Zf : Ljava/lang/String;
    //   312: new java/math/BigInteger
    //   315: dup
    //   316: bipush #32
    //   318: newarray byte
    //   320: dup
    //   321: iconst_0
    //   322: bipush #88
    //   324: bastore
    //   325: dup
    //   326: iconst_1
    //   327: bipush #62
    //   329: bastore
    //   330: dup
    //   331: iconst_2
    //   332: bipush #-16
    //   334: bastore
    //   335: dup
    //   336: iconst_3
    //   337: bipush #-13
    //   339: bastore
    //   340: dup
    //   341: iconst_4
    //   342: bipush #75
    //   344: bastore
    //   345: dup
    //   346: iconst_5
    //   347: bipush #-89
    //   349: bastore
    //   350: dup
    //   351: bipush #6
    //   353: bipush #-33
    //   355: bastore
    //   356: dup
    //   357: bipush #7
    //   359: bipush #73
    //   361: bastore
    //   362: dup
    //   363: bipush #8
    //   365: bipush #53
    //   367: bastore
    //   368: dup
    //   369: bipush #9
    //   371: bipush #-5
    //   373: bastore
    //   374: dup
    //   375: bipush #10
    //   377: bipush #-12
    //   379: bastore
    //   380: dup
    //   381: bipush #11
    //   383: bipush #65
    //   385: bastore
    //   386: dup
    //   387: bipush #12
    //   389: bipush #107
    //   391: bastore
    //   392: dup
    //   393: bipush #13
    //   395: bipush #-90
    //   397: bastore
    //   398: dup
    //   399: bipush #14
    //   401: bipush #56
    //   403: bastore
    //   404: dup
    //   405: bipush #15
    //   407: bipush #-88
    //   409: bastore
    //   410: dup
    //   411: bipush #16
    //   413: bipush #-96
    //   415: bastore
    //   416: dup
    //   417: bipush #17
    //   419: bipush #6
    //   421: bastore
    //   422: dup
    //   423: bipush #18
    //   425: bipush #-72
    //   427: bastore
    //   428: dup
    //   429: bipush #19
    //   431: bipush #52
    //   433: bastore
    //   434: dup
    //   435: bipush #20
    //   437: bipush #-125
    //   439: bastore
    //   440: dup
    //   441: bipush #21
    //   443: bipush #-23
    //   445: bastore
    //   446: dup
    //   447: bipush #22
    //   449: bipush #-40
    //   451: bastore
    //   452: dup
    //   453: bipush #23
    //   455: bipush #124
    //   457: bastore
    //   458: dup
    //   459: bipush #24
    //   461: bipush #-40
    //   463: bastore
    //   464: dup
    //   465: bipush #25
    //   467: bipush #35
    //   469: bastore
    //   470: dup
    //   471: bipush #26
    //   473: bipush #9
    //   475: bastore
    //   476: dup
    //   477: bipush #27
    //   479: bipush #50
    //   481: bastore
    //   482: dup
    //   483: bipush #28
    //   485: bipush #-114
    //   487: bastore
    //   488: dup
    //   489: bipush #29
    //   491: bipush #-61
    //   493: bastore
    //   494: dup
    //   495: bipush #30
    //   497: bipush #-69
    //   499: bastore
    //   500: dup
    //   501: bipush #31
    //   503: bipush #26
    //   505: bastore
    //   506: invokespecial <init> : ([B)V
    //   509: putstatic burp/Zth7.ZT : Ljava/lang/Object;
    //   512: return
  }
  
  private static Throwable a(Throwable paramThrowable) {
    return paramThrowable;
  }
  
  private static String a(int paramInt1, int paramInt2) {
    int i = (paramInt1 ^ 0x373) & 0xFFFF;
    if (b[i] == null) {
      char[] arrayOfChar = a[i].toCharArray();
      switch (arrayOfChar[0] & 0xFF) {
        case 0:
        
        case 1:
        
        case 2:
        
        case 3:
        
        case 4:
        
        case 5:
        
        case 6:
        
        case 7:
        
        case 8:
        
        case 9:
        
        case 10:
        
        case 11:
        
        case 12:
        
        case 13:
        
        case 14:
        
        case 15:
        
        case 16:
        
        case 17:
        
        case 18:
        
        case 19:
        
        case 20:
        
        case 21:
        
        case 22:
        
        case 23:
        
        case 24:
        
        case 25:
        
        case 26:
        
        case 27:
        
        case 28:
        
        case 29:
        
        case 30:
        
        case 31:
        
        case 32:
        
        case 33:
        
        case 34:
        
        case 35:
        
        case 36:
        
        case 37:
        
        case 38:
        
        case 39:
        
        case 40:
        
        case 41:
        
        case 42:
        
        case 43:
        
        case 44:
        
        case 45:
        
        case 46:
        
        case 47:
        
        case 48:
        
        case 49:
        
        case 50:
        
        case 51:
        
        case 52:
        
        case 53:
        
        case 54:
        
        case 55:
        
        case 56:
        
        case 57:
        
        case 58:
        
        case 59:
        
        case 60:
        
        case 61:
        
        case 62:
        
        case 63:
        
        case 64:
        
        case 65:
        
        case 66:
        
        case 67:
        
        case 68:
        
        case 69:
        
        case 70:
        
        case 71:
        
        case 72:
        
        case 73:
        
        case 74:
        
        case 75:
        
        case 76:
        
        case 77:
        
        case 78:
        
        case 79:
        
        case 80:
        
        case 81:
        
        case 82:
        
        case 83:
        
        case 84:
        
        case 85:
        
        case 86:
        
        case 87:
        
        case 88:
        
        case 89:
        
        case 90:
        
        case 91:
        
        case 92:
        
        case 93:
        
        case 94:
        
        case 95:
        
        case 96:
        
        case 97:
        
        case 98:
        
        case 99:
        
        case 100:
        
        case 101:
        
        case 102:
        
        case 103:
        
        case 104:
        
        case 105:
        
        case 106:
        
        case 107:
        
        case 108:
        
        case 109:
        
        case 110:
        
        case 111:
        
        case 112:
        
        case 113:
        
        case 114:
        
        case 115:
        
        case 116:
        
        case 117:
        
        case 118:
        
        case 119:
        
        case 120:
        
        case 121:
        
        case 122:
        
        case 123:
        
        case 124:
        
        case 125:
        
        case 126:
        
        case 127:
        
        case 128:
        
        case 129:
        
        case 130:
        
        case 131:
        
        case 132:
        
        case 133:
        
        case 134:
        
        case 135:
        
        case 136:
        
        case 137:
        
        case 138:
        
        case 139:
        
        case 140:
        
        case 141:
        
        case 142:
        
        case 143:
        
        case 144:
        
        case 145:
        
        case 146:
        
        case 147:
        
        case 148:
        
        case 149:
        
        case 150:
        
        case 151:
        
        case 152:
        
        case 153:
        
        case 154:
        
        case 155:
        
        case 156:
        
        case 157:
        
        case 158:
        
        case 159:
        
        case 160:
        
        case 161:
        
        case 162:
        
        case 163:
        
        case 164:
        
        case 165:
        
        case 166:
        
        case 167:
        
        case 168:
        
        case 169:
        
        case 170:
        
        case 171:
        
        case 172:
        
        case 173:
        
        case 174:
        
        case 175:
        
        case 176:
        
        case 177:
        
        case 178:
        
        case 179:
        
        case 180:
        
        case 181:
        
        case 182:
        
        case 183:
        
        case 184:
        
        case 185:
        
        case 186:
        
        case 187:
        
        case 188:
        
        case 189:
        
        case 190:
        
        case 191:
        
        case 192:
        
        case 193:
        
        case 194:
        
        case 195:
        
        case 196:
        
        case 197:
        
        case 198:
        
        case 199:
        
        case 200:
        
        case 201:
        
        case 202:
        
        case 203:
        
        case 204:
        
        case 205:
        
        case 206:
        
        case 207:
        
        case 208:
        
        case 209:
        
        case 210:
        
        case 211:
        
        case 212:
        
        case 213:
        
        case 214:
        
        case 215:
        
        case 216:
        
        case 217:
        
        case 218:
        
        case 219:
        
        case 220:
        
        case 221:
        
        case 222:
        
        case 223:
        
        case 224:
        
        case 225:
        
        case 226:
        
        case 227:
        
        case 228:
        
        case 229:
        
        case 230:
        
        case 231:
        
        case 232:
        
        case 233:
        
        case 234:
        
        case 235:
        
        case 236:
        
        case 237:
        
        case 238:
        
        case 239:
        
        case 240:
        
        case 241:
        
        case 242:
        
        case 243:
        
        case 244:
        
        case 245:
        
        case 246:
        
        case 247:
        
        case 248:
        
        case 249:
        
        case 250:
        
        case 251:
        
        case 252:
        
        case 253:
        
        case 254:
        
        default:
          break;
      } 
      char c = 'Ã¸';
      int j = (paramInt2 & 0xFF) - c;
      if (j < 0)
        j += 256; 
      int k = ((paramInt2 & 0xFFFF) >>> 8) - c;
      if (k < 0)
        k += 256; 
      for (byte b = 0; b < arrayOfChar.length; b++) {
        int m = b % 2;
        if (m == 0) {
          arrayOfChar[b] = (char)(arrayOfChar[b] ^ j);
          j = ((j >>> 3 | j << 5) ^ arrayOfChar[b]) & 0xFF;
        } else {
          arrayOfChar[b] = (char)(arrayOfChar[b] ^ k);
          k = ((k >>> 3 | k << 5) ^ arrayOfChar[b]) & 0xFF;
        } 
      } 
      b[i] = (new String(arrayOfChar)).intern();
    } 
    return b[i];
  }
}


/* Location:              C:\Program Files\BurpSuitePro\burpsuite_pro.jar!\burp\Zth7.class
 * Java compiler version: 21 (65.0)
 * JD-Core Version:       1.1.3
 */