package burp;

import java.math.BigInteger;

class Zti3 extends ClassLoader {
  static String ZU;
  
  static Object ZW;
  
  private static final String[] a;
  
  private static final String[] b;
  
  static void Z_(Object[] paramArrayOfObject, Object paramObject) throws Throwable {}
  
  static boolean ZD(Object[] paramArrayOfObject, Object paramObject) throws Throwable {
    // Byte code:
    //   0: invokestatic ZK : ()Z
    //   3: istore_2
    //   4: new java/lang/StringBuilder
    //   7: dup
    //   8: invokespecial <init> : ()V
    //   11: astore_3
    //   12: iconst_0
    //   13: istore #4
    //   15: iload #4
    //   17: bipush #32
    //   19: if_icmpge -> 1355
    //   22: iload #4
    //   24: tableswitch default -> 1348, 0 -> 168, 1 -> 205, 2 -> 242, 3 -> 279, 4 -> 316, 5 -> 353, 6 -> 390, 7 -> 427, 8 -> 464, 9 -> 501, 10 -> 538, 11 -> 575, 12 -> 612, 13 -> 649, 14 -> 686, 15 -> 723, 16 -> 760, 17 -> 797, 18 -> 834, 19 -> 871, 20 -> 908, 21 -> 945, 22 -> 982, 23 -> 1019, 24 -> 1056, 25 -> 1093, 26 -> 1130, 27 -> 1167, 28 -> 1204, 29 -> 1241, 30 -> 1278, 31 -> 1315
    //   168: aload_3
    //   169: getstatic burp/Zmf6.Zn : Ljava/lang/String;
    //   172: getstatic burp/Zrm6.Z_ : Ljava/lang/Object;
    //   175: checkcast java/math/BigInteger
    //   178: invokevirtual intValue : ()I
    //   181: bipush #32
    //   183: irem
    //   184: invokestatic abs : (I)I
    //   187: invokevirtual charAt : (I)C
    //   190: invokevirtual append : (C)Ljava/lang/StringBuilder;
    //   193: pop
    //   194: iload_2
    //   195: ifeq -> 1348
    //   198: goto -> 205
    //   201: invokestatic a : (Ljava/lang/Throwable;)Ljava/lang/Throwable;
    //   204: athrow
    //   205: aload_3
    //   206: getstatic burp/Zm83.Zq : Ljava/lang/String;
    //   209: getstatic burp/Zsjw.Zw : Ljava/lang/Object;
    //   212: checkcast java/math/BigInteger
    //   215: invokevirtual intValue : ()I
    //   218: bipush #32
    //   220: irem
    //   221: invokestatic abs : (I)I
    //   224: invokevirtual charAt : (I)C
    //   227: invokevirtual append : (C)Ljava/lang/StringBuilder;
    //   230: pop
    //   231: iload_2
    //   232: ifeq -> 1348
    //   235: goto -> 242
    //   238: invokestatic a : (Ljava/lang/Throwable;)Ljava/lang/Throwable;
    //   241: athrow
    //   242: aload_3
    //   243: getstatic burp/Ztdl.ZK : Ljava/lang/String;
    //   246: getstatic burp/Zz0b.ZT : Ljava/lang/Object;
    //   249: checkcast java/math/BigInteger
    //   252: invokevirtual intValue : ()I
    //   255: bipush #32
    //   257: irem
    //   258: invokestatic abs : (I)I
    //   261: invokevirtual charAt : (I)C
    //   264: invokevirtual append : (C)Ljava/lang/StringBuilder;
    //   267: pop
    //   268: iload_2
    //   269: ifeq -> 1348
    //   272: goto -> 279
    //   275: invokestatic a : (Ljava/lang/Throwable;)Ljava/lang/Throwable;
    //   278: athrow
    //   279: aload_3
    //   280: getstatic burp/Zrfa.ZT : Ljava/lang/String;
    //   283: getstatic burp/Zthx.ZH : Ljava/lang/Object;
    //   286: checkcast java/math/BigInteger
    //   289: invokevirtual intValue : ()I
    //   292: bipush #32
    //   294: irem
    //   295: invokestatic abs : (I)I
    //   298: invokevirtual charAt : (I)C
    //   301: invokevirtual append : (C)Ljava/lang/StringBuilder;
    //   304: pop
    //   305: iload_2
    //   306: ifeq -> 1348
    //   309: goto -> 316
    //   312: invokestatic a : (Ljava/lang/Throwable;)Ljava/lang/Throwable;
    //   315: athrow
    //   316: aload_3
    //   317: getstatic burp/Zmf6.Zn : Ljava/lang/String;
    //   320: getstatic burp/Ztwp.Ze : Ljava/lang/Object;
    //   323: checkcast java/math/BigInteger
    //   326: invokevirtual intValue : ()I
    //   329: bipush #32
    //   331: irem
    //   332: invokestatic abs : (I)I
    //   335: invokevirtual charAt : (I)C
    //   338: invokevirtual append : (C)Ljava/lang/StringBuilder;
    //   341: pop
    //   342: iload_2
    //   343: ifeq -> 1348
    //   346: goto -> 353
    //   349: invokestatic a : (Ljava/lang/Throwable;)Ljava/lang/Throwable;
    //   352: athrow
    //   353: aload_3
    //   354: getstatic burp/Zssc.ZR : Ljava/lang/String;
    //   357: getstatic burp/Zmn0.Zo : Ljava/lang/Object;
    //   360: checkcast java/math/BigInteger
    //   363: invokevirtual intValue : ()I
    //   366: bipush #32
    //   368: irem
    //   369: invokestatic abs : (I)I
    //   372: invokevirtual charAt : (I)C
    //   375: invokevirtual append : (C)Ljava/lang/StringBuilder;
    //   378: pop
    //   379: iload_2
    //   380: ifeq -> 1348
    //   383: goto -> 390
    //   386: invokestatic a : (Ljava/lang/Throwable;)Ljava/lang/Throwable;
    //   389: athrow
    //   390: aload_3
    //   391: getstatic burp/Zrwp.ZS : Ljava/lang/String;
    //   394: getstatic burp/Zg4z.ZB : Ljava/lang/Object;
    //   397: checkcast java/math/BigInteger
    //   400: invokevirtual intValue : ()I
    //   403: bipush #32
    //   405: irem
    //   406: invokestatic abs : (I)I
    //   409: invokevirtual charAt : (I)C
    //   412: invokevirtual append : (C)Ljava/lang/StringBuilder;
    //   415: pop
    //   416: iload_2
    //   417: ifeq -> 1348
    //   420: goto -> 427
    //   423: invokestatic a : (Ljava/lang/Throwable;)Ljava/lang/Throwable;
    //   426: athrow
    //   427: aload_3
    //   428: getstatic burp/Zepy.Zg : Ljava/lang/String;
    //   431: getstatic burp/Zmyk.Za : Ljava/lang/Object;
    //   434: checkcast java/math/BigInteger
    //   437: invokevirtual intValue : ()I
    //   440: bipush #32
    //   442: irem
    //   443: invokestatic abs : (I)I
    //   446: invokevirtual charAt : (I)C
    //   449: invokevirtual append : (C)Ljava/lang/StringBuilder;
    //   452: pop
    //   453: iload_2
    //   454: ifeq -> 1348
    //   457: goto -> 464
    //   460: invokestatic a : (Ljava/lang/Throwable;)Ljava/lang/Throwable;
    //   463: athrow
    //   464: aload_3
    //   465: getstatic burp/Zsn9.Zp : Ljava/lang/String;
    //   468: getstatic burp/Zt81.ZY : Ljava/lang/Object;
    //   471: checkcast java/math/BigInteger
    //   474: invokevirtual intValue : ()I
    //   477: bipush #32
    //   479: irem
    //   480: invokestatic abs : (I)I
    //   483: invokevirtual charAt : (I)C
    //   486: invokevirtual append : (C)Ljava/lang/StringBuilder;
    //   489: pop
    //   490: iload_2
    //   491: ifeq -> 1348
    //   494: goto -> 501
    //   497: invokestatic a : (Ljava/lang/Throwable;)Ljava/lang/Throwable;
    //   500: athrow
    //   501: aload_3
    //   502: getstatic burp/Zb3l.Zz : Ljava/lang/String;
    //   505: getstatic burp/Zg7e.Zr : Ljava/lang/Object;
    //   508: checkcast java/math/BigInteger
    //   511: invokevirtual intValue : ()I
    //   514: bipush #32
    //   516: irem
    //   517: invokestatic abs : (I)I
    //   520: invokevirtual charAt : (I)C
    //   523: invokevirtual append : (C)Ljava/lang/StringBuilder;
    //   526: pop
    //   527: iload_2
    //   528: ifeq -> 1348
    //   531: goto -> 538
    //   534: invokestatic a : (Ljava/lang/Throwable;)Ljava/lang/Throwable;
    //   537: athrow
    //   538: aload_3
    //   539: getstatic burp/Zxxf.Zw : Ljava/lang/String;
    //   542: getstatic burp/Zsu2.ZG : Ljava/lang/Object;
    //   545: checkcast java/math/BigInteger
    //   548: invokevirtual intValue : ()I
    //   551: bipush #32
    //   553: irem
    //   554: invokestatic abs : (I)I
    //   557: invokevirtual charAt : (I)C
    //   560: invokevirtual append : (C)Ljava/lang/StringBuilder;
    //   563: pop
    //   564: iload_2
    //   565: ifeq -> 1348
    //   568: goto -> 575
    //   571: invokestatic a : (Ljava/lang/Throwable;)Ljava/lang/Throwable;
    //   574: athrow
    //   575: aload_3
    //   576: getstatic burp/Zrov.ZU : Ljava/lang/String;
    //   579: getstatic burp/Zr_x.Zd : Ljava/lang/Object;
    //   582: checkcast java/math/BigInteger
    //   585: invokevirtual intValue : ()I
    //   588: bipush #32
    //   590: irem
    //   591: invokestatic abs : (I)I
    //   594: invokevirtual charAt : (I)C
    //   597: invokevirtual append : (C)Ljava/lang/StringBuilder;
    //   600: pop
    //   601: iload_2
    //   602: ifeq -> 1348
    //   605: goto -> 612
    //   608: invokestatic a : (Ljava/lang/Throwable;)Ljava/lang/Throwable;
    //   611: athrow
    //   612: aload_3
    //   613: getstatic burp/Zrjq.Zx : Ljava/lang/String;
    //   616: getstatic burp/Zmll.ZU : Ljava/lang/Object;
    //   619: checkcast java/math/BigInteger
    //   622: invokevirtual intValue : ()I
    //   625: bipush #32
    //   627: irem
    //   628: invokestatic abs : (I)I
    //   631: invokevirtual charAt : (I)C
    //   634: invokevirtual append : (C)Ljava/lang/StringBuilder;
    //   637: pop
    //   638: iload_2
    //   639: ifeq -> 1348
    //   642: goto -> 649
    //   645: invokestatic a : (Ljava/lang/Throwable;)Ljava/lang/Throwable;
    //   648: athrow
    //   649: aload_3
    //   650: getstatic burp/Zk9q.Zk : Ljava/lang/String;
    //   653: getstatic burp/Ze8j.ZQ : Ljava/lang/Object;
    //   656: checkcast java/math/BigInteger
    //   659: invokevirtual intValue : ()I
    //   662: bipush #32
    //   664: irem
    //   665: invokestatic abs : (I)I
    //   668: invokevirtual charAt : (I)C
    //   671: invokevirtual append : (C)Ljava/lang/StringBuilder;
    //   674: pop
    //   675: iload_2
    //   676: ifeq -> 1348
    //   679: goto -> 686
    //   682: invokestatic a : (Ljava/lang/Throwable;)Ljava/lang/Throwable;
    //   685: athrow
    //   686: aload_3
    //   687: getstatic burp/Zbx4.ZS : Ljava/lang/String;
    //   690: getstatic burp/Zg7e.Zr : Ljava/lang/Object;
    //   693: checkcast java/math/BigInteger
    //   696: invokevirtual intValue : ()I
    //   699: bipush #32
    //   701: irem
    //   702: invokestatic abs : (I)I
    //   705: invokevirtual charAt : (I)C
    //   708: invokevirtual append : (C)Ljava/lang/StringBuilder;
    //   711: pop
    //   712: iload_2
    //   713: ifeq -> 1348
    //   716: goto -> 723
    //   719: invokestatic a : (Ljava/lang/Throwable;)Ljava/lang/Throwable;
    //   722: athrow
    //   723: aload_3
    //   724: getstatic burp/Zk7o.Zb : Ljava/lang/String;
    //   727: getstatic burp/Zz66.ZQ : Ljava/lang/Object;
    //   730: checkcast java/math/BigInteger
    //   733: invokevirtual intValue : ()I
    //   736: bipush #32
    //   738: irem
    //   739: invokestatic abs : (I)I
    //   742: invokevirtual charAt : (I)C
    //   745: invokevirtual append : (C)Ljava/lang/StringBuilder;
    //   748: pop
    //   749: iload_2
    //   750: ifeq -> 1348
    //   753: goto -> 760
    //   756: invokestatic a : (Ljava/lang/Throwable;)Ljava/lang/Throwable;
    //   759: athrow
    //   760: aload_3
    //   761: getstatic burp/Zt6z.ZL : Ljava/lang/String;
    //   764: getstatic burp/Zz0f.ZL : Ljava/lang/Object;
    //   767: checkcast java/math/BigInteger
    //   770: invokevirtual intValue : ()I
    //   773: bipush #32
    //   775: irem
    //   776: invokestatic abs : (I)I
    //   779: invokevirtual charAt : (I)C
    //   782: invokevirtual append : (C)Ljava/lang/StringBuilder;
    //   785: pop
    //   786: iload_2
    //   787: ifeq -> 1348
    //   790: goto -> 797
    //   793: invokestatic a : (Ljava/lang/Throwable;)Ljava/lang/Throwable;
    //   796: athrow
    //   797: aload_3
    //   798: getstatic burp/Zxan.ZJ : Ljava/lang/String;
    //   801: getstatic burp/Zrnk.ZM : Ljava/lang/Object;
    //   804: checkcast java/math/BigInteger
    //   807: invokevirtual intValue : ()I
    //   810: bipush #32
    //   812: irem
    //   813: invokestatic abs : (I)I
    //   816: invokevirtual charAt : (I)C
    //   819: invokevirtual append : (C)Ljava/lang/StringBuilder;
    //   822: pop
    //   823: iload_2
    //   824: ifeq -> 1348
    //   827: goto -> 834
    //   830: invokestatic a : (Ljava/lang/Throwable;)Ljava/lang/Throwable;
    //   833: athrow
    //   834: aload_3
    //   835: getstatic burp/Zgei.Zl : Ljava/lang/String;
    //   838: getstatic burp/Zx63.ZX : Ljava/lang/Object;
    //   841: checkcast java/math/BigInteger
    //   844: invokevirtual intValue : ()I
    //   847: bipush #32
    //   849: irem
    //   850: invokestatic abs : (I)I
    //   853: invokevirtual charAt : (I)C
    //   856: invokevirtual append : (C)Ljava/lang/StringBuilder;
    //   859: pop
    //   860: iload_2
    //   861: ifeq -> 1348
    //   864: goto -> 871
    //   867: invokestatic a : (Ljava/lang/Throwable;)Ljava/lang/Throwable;
    //   870: athrow
    //   871: aload_3
    //   872: getstatic burp/Zg0q.Ze : Ljava/lang/String;
    //   875: getstatic burp/Zeqx.Zh : Ljava/lang/Object;
    //   878: checkcast java/math/BigInteger
    //   881: invokevirtual intValue : ()I
    //   884: bipush #32
    //   886: irem
    //   887: invokestatic abs : (I)I
    //   890: invokevirtual charAt : (I)C
    //   893: invokevirtual append : (C)Ljava/lang/StringBuilder;
    //   896: pop
    //   897: iload_2
    //   898: ifeq -> 1348
    //   901: goto -> 908
    //   904: invokestatic a : (Ljava/lang/Throwable;)Ljava/lang/Throwable;
    //   907: athrow
    //   908: aload_3
    //   909: getstatic burp/Zb0q.Zr : Ljava/lang/String;
    //   912: getstatic burp/Ze6w.Ze : Ljava/lang/Object;
    //   915: checkcast java/math/BigInteger
    //   918: invokevirtual intValue : ()I
    //   921: bipush #32
    //   923: irem
    //   924: invokestatic abs : (I)I
    //   927: invokevirtual charAt : (I)C
    //   930: invokevirtual append : (C)Ljava/lang/StringBuilder;
    //   933: pop
    //   934: iload_2
    //   935: ifeq -> 1348
    //   938: goto -> 945
    //   941: invokestatic a : (Ljava/lang/Throwable;)Ljava/lang/Throwable;
    //   944: athrow
    //   945: aload_3
    //   946: getstatic burp/Zrd3.Z_ : Ljava/lang/String;
    //   949: getstatic burp/Zkjj.Zh : Ljava/lang/Object;
    //   952: checkcast java/math/BigInteger
    //   955: invokevirtual intValue : ()I
    //   958: bipush #32
    //   960: irem
    //   961: invokestatic abs : (I)I
    //   964: invokevirtual charAt : (I)C
    //   967: invokevirtual append : (C)Ljava/lang/StringBuilder;
    //   970: pop
    //   971: iload_2
    //   972: ifeq -> 1348
    //   975: goto -> 982
    //   978: invokestatic a : (Ljava/lang/Throwable;)Ljava/lang/Throwable;
    //   981: athrow
    //   982: aload_3
    //   983: getstatic burp/Zkql.ZR : Ljava/lang/String;
    //   986: getstatic burp/Zegj.ZT : Ljava/lang/Object;
    //   989: checkcast java/math/BigInteger
    //   992: invokevirtual intValue : ()I
    //   995: bipush #32
    //   997: irem
    //   998: invokestatic abs : (I)I
    //   1001: invokevirtual charAt : (I)C
    //   1004: invokevirtual append : (C)Ljava/lang/StringBuilder;
    //   1007: pop
    //   1008: iload_2
    //   1009: ifeq -> 1348
    //   1012: goto -> 1019
    //   1015: invokestatic a : (Ljava/lang/Throwable;)Ljava/lang/Throwable;
    //   1018: athrow
    //   1019: aload_3
    //   1020: getstatic burp/Ze2w.Za : Ljava/lang/String;
    //   1023: getstatic burp/Zegv.ZL : Ljava/lang/Object;
    //   1026: checkcast java/math/BigInteger
    //   1029: invokevirtual intValue : ()I
    //   1032: bipush #32
    //   1034: irem
    //   1035: invokestatic abs : (I)I
    //   1038: invokevirtual charAt : (I)C
    //   1041: invokevirtual append : (C)Ljava/lang/StringBuilder;
    //   1044: pop
    //   1045: iload_2
    //   1046: ifeq -> 1348
    //   1049: goto -> 1056
    //   1052: invokestatic a : (Ljava/lang/Throwable;)Ljava/lang/Throwable;
    //   1055: athrow
    //   1056: aload_3
    //   1057: getstatic burp/Zzef.Za : Ljava/lang/String;
    //   1060: getstatic burp/Ztzj.Zv : Ljava/lang/Object;
    //   1063: checkcast java/math/BigInteger
    //   1066: invokevirtual intValue : ()I
    //   1069: bipush #32
    //   1071: irem
    //   1072: invokestatic abs : (I)I
    //   1075: invokevirtual charAt : (I)C
    //   1078: invokevirtual append : (C)Ljava/lang/StringBuilder;
    //   1081: pop
    //   1082: iload_2
    //   1083: ifeq -> 1348
    //   1086: goto -> 1093
    //   1089: invokestatic a : (Ljava/lang/Throwable;)Ljava/lang/Throwable;
    //   1092: athrow
    //   1093: aload_3
    //   1094: getstatic burp/Zzyb.Zh : Ljava/lang/String;
    //   1097: getstatic burp/Zz7m.Zh : Ljava/lang/Object;
    //   1100: checkcast java/math/BigInteger
    //   1103: invokevirtual intValue : ()I
    //   1106: bipush #32
    //   1108: irem
    //   1109: invokestatic abs : (I)I
    //   1112: invokevirtual charAt : (I)C
    //   1115: invokevirtual append : (C)Ljava/lang/StringBuilder;
    //   1118: pop
    //   1119: iload_2
    //   1120: ifeq -> 1348
    //   1123: goto -> 1130
    //   1126: invokestatic a : (Ljava/lang/Throwable;)Ljava/lang/Throwable;
    //   1129: athrow
    //   1130: aload_3
    //   1131: getstatic burp/Zbss.ZV : Ljava/lang/String;
    //   1134: getstatic burp/Zxd1.Zc : Ljava/lang/Object;
    //   1137: checkcast java/math/BigInteger
    //   1140: invokevirtual intValue : ()I
    //   1143: bipush #32
    //   1145: irem
    //   1146: invokestatic abs : (I)I
    //   1149: invokevirtual charAt : (I)C
    //   1152: invokevirtual append : (C)Ljava/lang/StringBuilder;
    //   1155: pop
    //   1156: iload_2
    //   1157: ifeq -> 1348
    //   1160: goto -> 1167
    //   1163: invokestatic a : (Ljava/lang/Throwable;)Ljava/lang/Throwable;
    //   1166: athrow
    //   1167: aload_3
    //   1168: getstatic burp/Zr1t.Ze : Ljava/lang/String;
    //   1171: getstatic burp/Zr02.ZB : Ljava/lang/Object;
    //   1174: checkcast java/math/BigInteger
    //   1177: invokevirtual intValue : ()I
    //   1180: bipush #32
    //   1182: irem
    //   1183: invokestatic abs : (I)I
    //   1186: invokevirtual charAt : (I)C
    //   1189: invokevirtual append : (C)Ljava/lang/StringBuilder;
    //   1192: pop
    //   1193: iload_2
    //   1194: ifeq -> 1348
    //   1197: goto -> 1204
    //   1200: invokestatic a : (Ljava/lang/Throwable;)Ljava/lang/Throwable;
    //   1203: athrow
    //   1204: aload_3
    //   1205: getstatic burp/Zz66.ZM : Ljava/lang/String;
    //   1208: getstatic burp/Zejz.ZF : Ljava/lang/Object;
    //   1211: checkcast java/math/BigInteger
    //   1214: invokevirtual intValue : ()I
    //   1217: bipush #32
    //   1219: irem
    //   1220: invokestatic abs : (I)I
    //   1223: invokevirtual charAt : (I)C
    //   1226: invokevirtual append : (C)Ljava/lang/StringBuilder;
    //   1229: pop
    //   1230: iload_2
    //   1231: ifeq -> 1348
    //   1234: goto -> 1241
    //   1237: invokestatic a : (Ljava/lang/Throwable;)Ljava/lang/Throwable;
    //   1240: athrow
    //   1241: aload_3
    //   1242: getstatic burp/Zemp.Zs : Ljava/lang/String;
    //   1245: getstatic burp/Zti4.Zi : Ljava/lang/Object;
    //   1248: checkcast java/math/BigInteger
    //   1251: invokevirtual intValue : ()I
    //   1254: bipush #32
    //   1256: irem
    //   1257: invokestatic abs : (I)I
    //   1260: invokevirtual charAt : (I)C
    //   1263: invokevirtual append : (C)Ljava/lang/StringBuilder;
    //   1266: pop
    //   1267: iload_2
    //   1268: ifeq -> 1348
    //   1271: goto -> 1278
    //   1274: invokestatic a : (Ljava/lang/Throwable;)Ljava/lang/Throwable;
    //   1277: athrow
    //   1278: aload_3
    //   1279: getstatic burp/Zt85.ZR : Ljava/lang/String;
    //   1282: getstatic burp/Zly9.Zz : Ljava/lang/Object;
    //   1285: checkcast java/math/BigInteger
    //   1288: invokevirtual intValue : ()I
    //   1291: bipush #32
    //   1293: irem
    //   1294: invokestatic abs : (I)I
    //   1297: invokevirtual charAt : (I)C
    //   1300: invokevirtual append : (C)Ljava/lang/StringBuilder;
    //   1303: pop
    //   1304: iload_2
    //   1305: ifeq -> 1348
    //   1308: goto -> 1315
    //   1311: invokestatic a : (Ljava/lang/Throwable;)Ljava/lang/Throwable;
    //   1314: athrow
    //   1315: aload_3
    //   1316: getstatic burp/Zlwm.Zj : Ljava/lang/String;
    //   1319: getstatic burp/Zmll.ZU : Ljava/lang/Object;
    //   1322: checkcast java/math/BigInteger
    //   1325: invokevirtual intValue : ()I
    //   1328: bipush #32
    //   1330: irem
    //   1331: invokestatic abs : (I)I
    //   1334: invokevirtual charAt : (I)C
    //   1337: invokevirtual append : (C)Ljava/lang/StringBuilder;
    //   1340: pop
    //   1341: goto -> 1348
    //   1344: invokestatic a : (Ljava/lang/Throwable;)Ljava/lang/Throwable;
    //   1347: athrow
    //   1348: iinc #4, 1
    //   1351: iload_2
    //   1352: ifeq -> 15
    //   1355: sipush #-466
    //   1358: sipush #21166
    //   1361: invokestatic a : (II)Ljava/lang/String;
    //   1364: invokestatic forName : (Ljava/lang/String;)Ljava/lang/Class;
    //   1367: invokevirtual getDeclaredFields : ()[Ljava/lang/reflect/Field;
    //   1370: astore #4
    //   1372: aload #4
    //   1374: arraylength
    //   1375: istore #5
    //   1377: iconst_0
    //   1378: istore #6
    //   1380: iload #6
    //   1382: iload #5
    //   1384: if_icmpge -> 1461
    //   1387: aload #4
    //   1389: iload #6
    //   1391: aaload
    //   1392: astore #7
    //   1394: aload #7
    //   1396: invokevirtual getType : ()Ljava/lang/Class;
    //   1399: ldc java/lang/String
    //   1401: invokevirtual equals : (Ljava/lang/Object;)Z
    //   1404: ifeq -> 1447
    //   1407: aload #7
    //   1409: iconst_1
    //   1410: invokevirtual setAccessible : (Z)V
    //   1413: aload #7
    //   1415: aconst_null
    //   1416: aload #7
    //   1418: aconst_null
    //   1419: invokevirtual get : (Ljava/lang/Object;)Ljava/lang/Object;
    //   1422: checkcast java/lang/String
    //   1425: getstatic burp/Zti3.ZU : Ljava/lang/String;
    //   1428: <illegal opcode> makeConcatWithConstants : (Ljava/lang/String;Ljava/lang/String;)Ljava/lang/String;
    //   1433: invokevirtual set : (Ljava/lang/Object;Ljava/lang/Object;)V
    //   1436: iload_2
    //   1437: ifeq -> 1461
    //   1440: goto -> 1447
    //   1443: invokestatic a : (Ljava/lang/Throwable;)Ljava/lang/Throwable;
    //   1446: athrow
    //   1447: iinc #6, 1
    //   1450: iload_2
    //   1451: ifeq -> 1380
    //   1454: goto -> 1461
    //   1457: invokestatic a : (Ljava/lang/Throwable;)Ljava/lang/Throwable;
    //   1460: athrow
    //   1461: sipush #-470
    //   1464: sipush #4554
    //   1467: invokestatic a : (II)Ljava/lang/String;
    //   1470: iconst_1
    //   1471: ldc burp/Zl88
    //   1473: invokevirtual getClassLoader : ()Ljava/lang/ClassLoader;
    //   1476: invokestatic forName : (Ljava/lang/String;ZLjava/lang/ClassLoader;)Ljava/lang/Class;
    //   1479: invokevirtual getDeclaredFields : ()[Ljava/lang/reflect/Field;
    //   1482: astore #4
    //   1484: aload #4
    //   1486: arraylength
    //   1487: istore #5
    //   1489: iconst_0
    //   1490: istore #6
    //   1492: iload #6
    //   1494: iload #5
    //   1496: if_icmpge -> 1634
    //   1499: aload #4
    //   1501: iload #6
    //   1503: aaload
    //   1504: astore #7
    //   1506: aload #7
    //   1508: invokevirtual getModifiers : ()I
    //   1511: invokestatic isStatic : (I)Z
    //   1514: ifne -> 1524
    //   1517: goto -> 1627
    //   1520: invokestatic a : (Ljava/lang/Throwable;)Ljava/lang/Throwable;
    //   1523: athrow
    //   1524: aload #7
    //   1526: invokevirtual getType : ()Ljava/lang/Class;
    //   1529: astore #8
    //   1531: aload #8
    //   1533: ifnull -> 1614
    //   1536: aload #8
    //   1538: invokevirtual isPrimitive : ()Z
    //   1541: ifne -> 1614
    //   1544: goto -> 1551
    //   1547: invokestatic a : (Ljava/lang/Throwable;)Ljava/lang/Throwable;
    //   1550: athrow
    //   1551: aload #8
    //   1553: invokevirtual getPackage : ()Ljava/lang/Package;
    //   1556: ifnull -> 1614
    //   1559: goto -> 1566
    //   1562: invokestatic a : (Ljava/lang/Throwable;)Ljava/lang/Throwable;
    //   1565: athrow
    //   1566: aload #8
    //   1568: invokevirtual getPackage : ()Ljava/lang/Package;
    //   1571: invokevirtual getName : ()Ljava/lang/String;
    //   1574: ifnull -> 1614
    //   1577: goto -> 1584
    //   1580: invokestatic a : (Ljava/lang/Throwable;)Ljava/lang/Throwable;
    //   1583: athrow
    //   1584: aload #8
    //   1586: invokevirtual getPackage : ()Ljava/lang/Package;
    //   1589: invokevirtual getName : ()Ljava/lang/String;
    //   1592: sipush #-469
    //   1595: sipush #-21860
    //   1598: invokestatic a : (II)Ljava/lang/String;
    //   1601: invokevirtual startsWith : (Ljava/lang/String;)Z
    //   1604: ifne -> 1614
    //   1607: goto -> 1614
    //   1610: invokestatic a : (Ljava/lang/Throwable;)Ljava/lang/Throwable;
    //   1613: athrow
    //   1614: aload #7
    //   1616: iconst_1
    //   1617: invokevirtual setAccessible : (Z)V
    //   1620: aload #7
    //   1622: aconst_null
    //   1623: invokevirtual get : (Ljava/lang/Object;)Ljava/lang/Object;
    //   1626: pop
    //   1627: iinc #6, 1
    //   1630: iload_2
    //   1631: ifeq -> 1492
    //   1634: sipush #-472
    //   1637: sipush #-24097
    //   1640: invokestatic a : (II)Ljava/lang/String;
    //   1643: invokestatic forName : (Ljava/lang/String;)Ljava/lang/Class;
    //   1646: invokevirtual getDeclaredMethods : ()[Ljava/lang/reflect/Method;
    //   1649: astore #4
    //   1651: aload #4
    //   1653: arraylength
    //   1654: istore #5
    //   1656: iconst_0
    //   1657: istore #6
    //   1659: iload #6
    //   1661: iload #5
    //   1663: if_icmpge -> 1796
    //   1666: aload #4
    //   1668: iload #6
    //   1670: aaload
    //   1671: astore #7
    //   1673: aload #7
    //   1675: invokevirtual getParameterTypes : ()[Ljava/lang/Class;
    //   1678: pop
    //   1679: aload #7
    //   1681: invokevirtual getModifiers : ()I
    //   1684: invokestatic isStatic : (I)Z
    //   1687: ifeq -> 1782
    //   1690: aload #7
    //   1692: invokevirtual getParameterTypes : ()[Ljava/lang/Class;
    //   1695: arraylength
    //   1696: iconst_2
    //   1697: if_icmpne -> 1782
    //   1700: goto -> 1707
    //   1703: invokestatic a : (Ljava/lang/Throwable;)Ljava/lang/Throwable;
    //   1706: athrow
    //   1707: aload #7
    //   1709: invokevirtual getReturnType : ()Ljava/lang/Class;
    //   1712: getstatic java/lang/Void.TYPE : Ljava/lang/Class;
    //   1715: invokevirtual equals : (Ljava/lang/Object;)Z
    //   1718: ifeq -> 1782
    //   1721: goto -> 1728
    //   1724: invokestatic a : (Ljava/lang/Throwable;)Ljava/lang/Throwable;
    //   1727: athrow
    //   1728: aload #7
    //   1730: iconst_1
    //   1731: invokevirtual setAccessible : (Z)V
    //   1734: aload #7
    //   1736: aconst_null
    //   1737: iconst_2
    //   1738: anewarray java/lang/Object
    //   1741: dup
    //   1742: iconst_0
    //   1743: aload_0
    //   1744: aastore
    //   1745: dup
    //   1746: iconst_1
    //   1747: aload_1
    //   1748: ifnonnull -> 1766
    //   1751: goto -> 1758
    //   1754: invokestatic a : (Ljava/lang/Throwable;)Ljava/lang/Throwable;
    //   1757: athrow
    //   1758: aload_1
    //   1759: goto -> 1773
    //   1762: invokestatic a : (Ljava/lang/Throwable;)Ljava/lang/Throwable;
    //   1765: athrow
    //   1766: aload_1
    //   1767: checkcast [B
    //   1770: invokevirtual clone : ()Ljava/lang/Object;
    //   1773: aastore
    //   1774: invokevirtual invoke : (Ljava/lang/Object;[Ljava/lang/Object;)Ljava/lang/Object;
    //   1777: pop
    //   1778: iload_2
    //   1779: ifeq -> 1796
    //   1782: iinc #6, 1
    //   1785: iload_2
    //   1786: ifeq -> 1659
    //   1789: goto -> 1796
    //   1792: invokestatic a : (Ljava/lang/Throwable;)Ljava/lang/Throwable;
    //   1795: athrow
    //   1796: getstatic burp/Zmdi.ZA : Ljava/lang/String;
    //   1799: getstatic burp/Zlwc.ZG : Ljava/lang/Object;
    //   1802: checkcast java/math/BigInteger
    //   1805: invokevirtual intValue : ()I
    //   1808: bipush #32
    //   1810: irem
    //   1811: invokestatic abs : (I)I
    //   1814: invokevirtual charAt : (I)C
    //   1817: getstatic burp/Zxxo.ZH : Ljava/lang/String;
    //   1820: getstatic burp/Zedq.Zy : Ljava/lang/Object;
    //   1823: checkcast java/math/BigInteger
    //   1826: invokevirtual intValue : ()I
    //   1829: bipush #32
    //   1831: irem
    //   1832: invokestatic abs : (I)I
    //   1835: invokevirtual charAt : (I)C
    //   1838: if_icmpgt -> 1953
    //   1841: getstatic burp/Zz7m.Zq : Ljava/lang/String;
    //   1844: getstatic burp/Ze2k.ZK : Ljava/lang/Object;
    //   1847: checkcast java/math/BigInteger
    //   1850: invokevirtual intValue : ()I
    //   1853: bipush #32
    //   1855: irem
    //   1856: invokestatic abs : (I)I
    //   1859: invokevirtual charAt : (I)C
    //   1862: getstatic burp/Zmig.ZR : Ljava/lang/String;
    //   1865: getstatic burp/Zkeb.ZH : Ljava/lang/Object;
    //   1868: checkcast java/math/BigInteger
    //   1871: invokevirtual intValue : ()I
    //   1874: bipush #32
    //   1876: irem
    //   1877: invokestatic abs : (I)I
    //   1880: invokevirtual charAt : (I)C
    //   1883: if_icmple -> 1953
    //   1886: goto -> 1893
    //   1889: invokestatic a : (Ljava/lang/Throwable;)Ljava/lang/Throwable;
    //   1892: athrow
    //   1893: getstatic burp/Zt81.ZL : Ljava/lang/String;
    //   1896: getstatic burp/Zx5w.Zo : Ljava/lang/Object;
    //   1899: checkcast java/math/BigInteger
    //   1902: invokevirtual intValue : ()I
    //   1905: bipush #32
    //   1907: irem
    //   1908: invokestatic abs : (I)I
    //   1911: invokevirtual charAt : (I)C
    //   1914: getstatic burp/Zz3b.Zi : Ljava/lang/String;
    //   1917: getstatic burp/Zmdf.ZH : Ljava/lang/Object;
    //   1920: checkcast java/math/BigInteger
    //   1923: invokevirtual intValue : ()I
    //   1926: bipush #32
    //   1928: irem
    //   1929: invokestatic abs : (I)I
    //   1932: invokevirtual charAt : (I)C
    //   1935: if_icmpgt -> 1953
    //   1938: goto -> 1945
    //   1941: invokestatic a : (Ljava/lang/Throwable;)Ljava/lang/Throwable;
    //   1944: athrow
    //   1945: iconst_1
    //   1946: goto -> 1954
    //   1949: invokestatic a : (Ljava/lang/Throwable;)Ljava/lang/Throwable;
    //   1952: athrow
    //   1953: iconst_0
    //   1954: ireturn
    //   1955: astore_3
    //   1956: new java/lang/Exception
    //   1959: dup
    //   1960: aload_3
    //   1961: invokevirtual getMessage : ()Ljava/lang/String;
    //   1964: invokespecial <init> : (Ljava/lang/String;)V
    //   1967: athrow
    // Exception table:
    //   from	to	target	type
    //   4	1954	1955	java/lang/Throwable
    //   22	198	201	java/lang/Throwable
    //   168	235	238	java/lang/Throwable
    //   205	272	275	java/lang/Throwable
    //   242	309	312	java/lang/Throwable
    //   279	346	349	java/lang/Throwable
    //   316	383	386	java/lang/Throwable
    //   353	420	423	java/lang/Throwable
    //   390	457	460	java/lang/Throwable
    //   427	494	497	java/lang/Throwable
    //   464	531	534	java/lang/Throwable
    //   501	568	571	java/lang/Throwable
    //   538	605	608	java/lang/Throwable
    //   575	642	645	java/lang/Throwable
    //   612	679	682	java/lang/Throwable
    //   649	716	719	java/lang/Throwable
    //   686	753	756	java/lang/Throwable
    //   723	790	793	java/lang/Throwable
    //   760	827	830	java/lang/Throwable
    //   797	864	867	java/lang/Throwable
    //   834	901	904	java/lang/Throwable
    //   871	938	941	java/lang/Throwable
    //   908	975	978	java/lang/Throwable
    //   945	1012	1015	java/lang/Throwable
    //   982	1049	1052	java/lang/Throwable
    //   1019	1086	1089	java/lang/Throwable
    //   1056	1123	1126	java/lang/Throwable
    //   1093	1160	1163	java/lang/Throwable
    //   1130	1197	1200	java/lang/Throwable
    //   1167	1234	1237	java/lang/Throwable
    //   1204	1271	1274	java/lang/Throwable
    //   1241	1308	1311	java/lang/Throwable
    //   1278	1341	1344	java/lang/Throwable
    //   1394	1440	1443	java/lang/Throwable
    //   1407	1454	1457	java/lang/Throwable
    //   1506	1520	1520	java/lang/Throwable
    //   1531	1544	1547	java/lang/Throwable
    //   1536	1559	1562	java/lang/Throwable
    //   1551	1577	1580	java/lang/Throwable
    //   1566	1607	1610	java/lang/Throwable
    //   1673	1700	1703	java/lang/Throwable
    //   1690	1721	1724	java/lang/Throwable
    //   1707	1751	1754	java/lang/Throwable
    //   1728	1762	1762	java/lang/Throwable
    //   1773	1789	1792	java/lang/Throwable
    //   1796	1886	1889	java/lang/Throwable
    //   1841	1938	1941	java/lang/Throwable
    //   1893	1949	1949	java/lang/Throwable
  }
  
  static void ZO(Object paramObject) {
    Zti7.Zc = a(-468, 14980);
    Zti7.Zw = new BigInteger(new byte[] { 
          4, -8, 98, -89, -8, -26, -30, 12, -70, -96, 
          -90, -65, -89, -61, -96, -125, -36, 121, 98, -83, 
          -81, -37, 41, 33, -26, 97, -22, -74, -38, 83, 
          11, -15 });
    boolean bool = Zt2e.ZN();
    try {
      try {
        if (Zs34.Zq.charAt(Math.abs(((BigInteger)Zlzo.ZJ).intValue() % 32)) > Zsk4.ZH.charAt(Math.abs(((BigInteger)Zr3j.ZT).intValue() % 32))) {
          try {
            Zs_3.ZI(Class.forName(a(-471, 15585)));
            if (!bool)
              Zlo2.ZL(Class.forName(a(-480, -17688))); 
          } catch (Throwable throwable) {
            throw a(null);
          } 
          return;
        } 
      } catch (Throwable throwable) {
        throw a(null);
      } 
      Zlo2.ZL(Class.forName(a(-480, -17688)));
    } catch (Throwable throwable) {}
  }
  
  static {
    // Byte code:
    //   0: bipush #10
    //   2: anewarray java/lang/String
    //   5: astore #5
    //   7: iconst_0
    //   8: istore_3
    //   9: ldc 'ªuð-µ\\tÖ'YOÃ\\t\\r¶U+TêÏW\ VHBø©L*«áÍ»JèôífúÑOÅßQq⋡^T\\r\\bÇQÒÏLzòs¾Ê\F_\\nÀ÷D,Á \\nFúpö¡ U 7ê@Mê»¨é¥>UØ"UýtX\\f\\n¤còÃÊÒPg¦ Ê.^ÿ³#þcÔz\\nSÒûa\\n&Xgá¹H.ÕN¬ôÔ§FÿÚ²?G¹ò*Îv£*Ns¡ýAa2'hºÓ=^ª%I§?LÔñ¶8]<y§"Òn°¿yÊÅÎ(ÐïßVn9ïÎù!Õ_»2=à!5ZîÀæ×ºE }7|¨Ý6ðb!\\t6Û^¢m|¦tcíÜrÒW¾vOZî¯ÿÿh7ôåºRßc¿i"ÿ¡\&Ô^@Hi³Û¸«å#i\\tÕÙO(^iy8Þ\\b1}7½ª±¾ÔXÙ¡ÆåWzß¤²¶3±ßfqzIÛQ!¿ñêcÉéF\\f#¼UÑ~-ñÎB*A«evÃ&\\bí\\nÑ\âÜíØ+¥¸NMz:Í «M]ºÛ\a2¡%²Ãn¥8ßÑÜãn\\bxOU¶ºÕééÞF³üz+HôP\Ù2u§üLÜ{øa¤¬Ëùþ 7,ó».E¸µÒZWXRÓSiUtgãù½ÌYÕI¢hdFÕ×²*£Vú\pªæ×¹éc¥Ú5îÜ|Ü-0.?W/Uÿ$[7xCí^H¾,"Åê'åÕ: ÇçÜçrPej4âè¿ÐS\\bep}î"½9á$j[8n¬^ßø^úê8;p¯Àæ­m®*P{©¢XÁusxeÑjIraZÀd½½\\nß0áÉ¾ºèÃî³adn£Ï=77~>\\rEL$îîS ñú&ØÞ\\tõ¥§àA?¨K}"¥HîÜ\\nÛÂ¢<ãM+xdÜó,Ù6B¶¦SÈKqbi«x.¤nÞÿ.£éD§'ÉÁìAÕMe\vÞá+ í3F¬µ¦âÕåøk'9/ç¦{¾ø~!L*TV'»^±â©Ás({ÐißÏ¿mózÌÊ[7|Fr¤¾øhÇ)üó`¤\\bs)¢óåUâ¹·Vº¾°SÄÐ;æÍF>¿ÊXrò\\rM\\nÙ\\n%ÍyÀÜÖèE êãËç÷ó¤ÎS­¢ó¦Lä«ý2HjM2Ä^Í½g?z°©GbéÀÈÆ)&=Õ3Æ^_Z¾nèä$ÊªWtÚa\eÎjËp.ÑüL%fÇÜ·jö°©4;*¡Äú2{_ð³§OÔï\Ôd ³'v~=_´èÙv ómÑktèÒ(Ï çòÿ»÷RFÂÒ{:\E~[<<èÔÀäA:Ø¿\¯ÀÑ@G¥ÔÙ}{à7Cª$vL_-#M¥]t¦~¬ûI{KÌ/ÉýØW¬5ÿ\¡\\ni0YÁo \\bµy¡'½h°¬>ø´I,E«è3xÂ©ï¿4a\\n³ÿUd]Z$Î:}y:cÊ}Ú Ý>Ýy$3\'ÞügÍLÔr3p1éÙ`&sÍTÌË ÙA"dDK¸ßámàÔ=êï»çcÞÕEÈÅJÚgzî,ÀþyY ë×Ì*b0^èîµ°Z¦+Z£\\bùu=ÂnMãe¥À\\tC£sÅÕýF`¤é¦á}Mó:U\Õ\\fÒgV"O|þ9à³/OàÙEÈ,hâp×Í)Þ×$6R:Ö¨OvLN$¼3£å³aÖª±_QÐ7Äè Òñ,üêjê·ÍFÛSÏ/-¿ßÖ»û9~¼¥:g±stkaå_\\nc:ªþÛnkùN¬)£çÕ¼ô<½}Óm±ÔóP"YM7QoRÆçkªB!yüAnVÙÒx1V\\rp4¼+kJ²?é¬õAçU¹[E-w®áÉ"VÉ%â³'f\\bö[óSî8ïM«úBàãMí¦3èôþ\\fp?G´"`×®âÚ?è/(#Ê¥\\tÃ³LXÞ8Ê×xXl\µEö"Rr¼Ãz5ÖÅûÞX$XßëÓ$tvÍË'ÿÖÝ1Q5A®íG¶ÖÔ_nOYîF^¶£þEèké\\tpÅõÃ]¦!ï?gn­U¡N<1$|3ôJ|ÁsmÒ`Ð-. ZóM\\nÄQk6týµR4)µ°âx×\\r»2947S@5`úLb]«túPe\\nÚoÆ`¥¥7÷sBqóÇ­ø^hq<6¤(¶ª/·Ëpòxc~R{Ýv÷|êyÎü²) 0/o¸=D×EûX\\f}» çâÇ«æOÛ0±ÚÞ¬\\t*à6kò­ô¿ó0ÓqGÍ£ô1o £Ë¶ÜÌå>®ôÒD¢fôÅkÇÓizæ²©)àS3?=¯áQrÔ9/ÖA,ô4r8KeýlÿßApÎÇ$ÕçtkZ£0Ibh1ÑZZK"¨s\\tì~×³j§VìÑ\\tø#\¯F¸e«½ýM¶;TrÈN5¿mÛá~LÏ[ä>ÞêÂIô}AÈm¼Ê9]0ËlWð¹I§<ôÀûFGé¯i^J`·äþìIA\\rCþÍdîK^#äò·þ]Ì©5ª&*ð9ÖS¡.&AqN¬Ç¼oúõpPüR:¦ÈI;×cZ)h9mëÿµ}ÔÓègW_NÚc^ÔÅRg ^µÿX8V¡çÑ[ðtôÛ(ÂÕvGÌÅö¬4%g»i\\n7B.ÈöÑ'ª¹í.LöØ<ERM¦p0ýü^¡ã8d¼¼ÅnH§ÚÍ|SIÝ§MG-@Ö\\t@^&ÙÛòñ;\\f5E²Çît2¨£H·ÝqÆzXó÷\6®¾îY¸Q¶ÉRds\\bX>dá¨¢èÂÛíXhð<ìñÙì~!êð1¯ôH)ÏOÂ2jÔôò¡ÖXul:þ´xºõWñ õ`p÷aÝÖWà|ö ü²4Êåh-.ÞJÏFC vÔ¤|±È&rcïX^uÌþÕKïY­0_JÇçé¢¥E/î: ÙË^i­Æ÷äqðÈ»þK¥Jm¨DôJ'\\t Ù/ú¸Ù7æzRkg¬´²<>Y§JWÆÊIJµjsá1þü§-Ho;Qþê<$Ôì)CÜjå\\t*ZmjóÜ`Ë ÊrÙ>IQHR»éEÙñ,9½\\t+3DNédâ~5\\bÈHAR³[É7Lå3ü²øv¨hìÏÞã½æA<aÆÿÝÆ<«Ñûk«2WMViïsK{5jÁÚµäEcIBFCªÌgi6\\nÎ\\râYÄ kOe\\t1\\r7nØãz!Ì#|ó§ctÝ¢«ì\\töÂ¥>G§°D(´Y´ß7iÐÃ ÒLep`óÏä«4ýêht{n¤LìàC¨E3SÄºRó£\\bû¬HZÑFªã=(4÷h°0b%ñx¦ª¼gÊÊ/vàù Þrcwb|îFÇíÇÔás\\bwÎêÊ©)ÖÄ¢»-f_¶ÛcæÕ\\f×¶S)Ì²!Ç aÞîdS¾òåò}îÿ@XÙ£*å[+nù¹Í=;kd(TNÆ3b4z'@éDu»QMªWsß»ËË¾`Å4îbÇ\\trR¢òãÂX÷våvv\\fÈ.ÚS6¦p½»\\f)tèÔmd­sÒw(û5^bs=çÝ; ¯ÐäXÓWµË'\\b)ið¹*A¥ÑG&zçý\Ò\\nÊWhÙâL>cg 5ËÏO1ÜDºØ,"\\rØøó2§éýSG±TY/@Fn®Ö¢®ð_Ó"ee"c¡¹V6ß2íáA,²É/^ï4SÅáÏGe}ÜFÂïé4X'Ï- ¶¬Î¶|]/B\\to·ÔÒÂâ1»Y[RtÕøe>Ý^çÇ¬« ó?LÄ5<&c7kèC,(ï3£\\toQ1pm32NÈd\\tÓî%M\\r@>NBô\:ò7ü7hÆÞñ?}±X5|)¾õ®0(Nb*7{ø®â£Çt«P-#ªOU'b/\\fÄ¨$ñDl{l3¢T¨¯C?hã\Åôí:¨ÝñîÉf¾øù±\\nzKZÛ¥LÓ%3 ÷)eÒæ\\tßé@ôL·éROéK~kMtBU­~§L&Þ²\\n/ú¾~¸èIáC´#~o¨\\nlùÛìÆ¹)eF½í¡^ôôjc}ÄðBÄ;úýðÒêÅ\Ù"h2jÞÍ»b!Ý íëWEeN×Ð3öY\ µ+\\rå,ã ÁaäCýË#HþÚ´¯C»ý{§Å7©©G U@{jä]÷s\\bW¡Éß\\txÕ2U#;\\rü³N¼®âé£éG¥|~aÐÝrìÖÙ^#kíÃ3üØÌgðØEÈ{vj~ùÎ£<¿¿\\tåÙÉq<lUöeðÃ|Àq4¢,ö[Y&ÜTNB+ûD¶9®Â0cÈ­\\fÆ4mV\ø"è`ì$«©¬²°~Ó®Äøpnv´ÝîPc|ßPXD=øæEÎAé{WB4!´ÞíÀg½\\b/ªaÏ³ÝÖÅèwâ{ :¥;õ$×õÞSR¡×¯MäKJ¹'ÒÈÈHRT?\\tþ¬I*®þVÊ]ç.ê:kc·©²}èÑü \\tT´3zwvXìG<ûéè§@/ãäöhøµb¨0¥ÁoÚA$J\\bÇªg°Br.eÒ{l?Ø¡?"Å³t×øp$/MìÑà´1ëÈàeÌkÅöÆ0úà;otÌ¨ÇeH4Ø÷e*g!N8XäY¶ß¶÷¢/ Ä#ª\ã¿Ïp3þÆÊÇ\è³¹¿0-Ò·E|[Óe/Ý÷{q*Ïg~\\fhb¢h¬ïn8Ù¬ò7ý=ïÃJe7JyêÀÝ¥@Ï.Ù!öºýÃªí;Ëb±Ý¹ u¯ÚllìøA@ÕÁG©J53\\tjTG%Â¶}Ü9òaÃa·nî»æ\\b8Ù*ä¬i»¨bP×³ßot \\fè{]½B¸eØ>.¾Ð¦:ïµqØÝÅ#N}ÍMJ?RX'£µtp¥ªU÷?M3û£ÿ ³LTDúX]F:\\nnw\\fWøm %ïJC²ü;if'0Ýn^ÐqÅÒÖS]ì\\tGÉl¯FGË5=¦óOã}x>&Àôp©æWS¬ÓØBN\\foOCNüú÷6A\´ÃÀx\\f#hóDãîRÛû¥\\nÂïßEâ¼ÈESø¨>«Ô3£Cº*¬ÌlÔÒý\\bÑ¡04N@.ß¶4tmE2t}d"ñÍ,ùÿ0_¶þó by'vx}kç¨¹FF<*DÂ\\rG!w¬nü\\t[Wëùa«å³$líéë½(áC\\nzóIÎ¥íDË{~WÆ/<Gq¸a¦?ÉI6Õ6ãñy#E/x«§ÒÛÇJ\\r$Ù<º?84îI±VXii'¦!BÂù·6$êÎç \LE!\\f\\f¡×/¤VöÎË§¾ì»J§Îä;k²UUÎÂöòBOx¥?û*¡QF}¨ðß-liÊßÞGºÅigøZ¬Ù¤öûv°vúÃWÙ;O<L+\½ðtì£*RùW,ý-§ÇÅ§vj yj¢ìõ°ÑÕd;3n§àb£Ñý­F±¾×{\\rRå/¿Ò(kÇÂ*ÕôÒÁk "8)1Ää¼^Q;³HZ:ÂÚÄÞàç´ì*Ï.ÈI 1ÄsõyB¡öðµý`\\f×Åµ'Y+/¥þ÷@*häª`È¸#æ2Çrq²¢ÞìÁ2J.ÛtO«!ÍÜ¨\\bÇn\\fkèR`Â²ûÖ¯;Pç¹U*ØþBÜ·NÐK¦:QÅàñ§©¸\\tìÇ*PÖpf7Ô$ æyÊÚBso¾)zò²Às&ôëàË°&¯§ \\f+]ª1Ñ3K ·$\\bo©°GYØ/* Ïä5îìZÚn>õô¿å-~í®Á å7VNðLËþdépÈ³­§ýqÛÿRåÊt½È}©Ñu<?,õÀHEG>lûNâ%½¸òÌÇ4LL¹CsOz¤§ýÇ\\n+n<x°ü¹s^×PLZ49-½j§P([Ù@"<ý{Öµ¬I^ü:Ä{¦Õ¥þüK¿/ÆÏñ÷Cvóí ÷ºö,Jê@þñÉTÀ¬¸ë).+¡ÐÇ¨(,÷gvº$#èR&uaÁH¼çP\\b¥ØÜö o:ïf&>ýNC{ªÛýq'¶¼~>³½>¡Ôç"[V¯èÐï^ªðÌ_BqNQzÞ¢e è=8ÃFBÙºK×ØwZ§Sè¿T\\bK!úb8T}aÊàªjÁkà¡gÓ\\fØû°YqñãuëxwbÓ34ø®nÞ;aã?[ÀÍw!Û<¢S)²[æïSnÛØ\\t?Íæ~2XoÅww¤&è¦¤ÐÕÒ\\bm2R@yoèÕDÈ=Saú¦ßâÕpgãOÍW²DÜ|ÿÔo³kÉ9ÖW}-¡9¢ù¤;LÄtÈEþûáq é>eÂW2Á\\b.·ßL­x\\rÕòÖÞ *°\`YÁõî-\\b°ÂÚ5\\rÙÐ18Õ*õ´.n)¼ü*Áu#w|ä³³È:~ù@ºÊF!1}\\bÝD=¬\\n¾Ó§Eµ©\¯ë~#ULÐYL \\rY3~+$h.Yä£{'ÕÙ¡¤aÏ¶MPtédµ­Ä2úSJóá.è±ó³!ßæ´yÝÞ#0²Òàz¦\\r¥iKJêÀ~k6r?AëO\\b©;ï\\t°rZù¥Î+áí{ ÆÃØ:þ#ûvöµ2Õß:®ÎÝÁ}¤$´×ØÖ  árèA 7oüª+h1p¤±Ç¯'Ô¢î±.Póp¦ç§)é(ã'5Æx@xÀy Q}cb+ âõ¼\Ä±ÒäÐ¸oE@ÐMÁð±ª¡§ì,5ÛXCö®îdêªöÃd³¥%C±©ï¯.È[×sÝ8_¿òcöº¤¥©/À)È¼´Dë­IØ\\tXÉFùêÉ&Õ¶oªòõx§¢ÿÿ­¹\\n!â\\râaßIRó;ÊçOkOÔmÜ" >YéDBc^ú5¥©§¡"7Ì¹ÏdÙGîzÔ³ÕßuMÏpÃ£³öu8á\\ngAôô7Æ°U{¹6øsÉ/íi\\bi°²ùÎx¿K=0¦®ßX"[:ªHYíì)¯ø¾OxÎs7qZÏ»Mø¥¦µ¼|Î2Ó÷üùDú ý{£ÿ»½ôz£C¾díª2Mx¶¦Ò4¬Ï)k;\Eµø2åÝï°ß¿LÔ¡½<=ß¹)ËzWJËYðÜ ³¶;Ë_p¶ÊzIßRïðhªYRýí©?CÍÈÎxÌNýÞ9¶øå<*ü[ï±³$$9vÞ\\bäX%X SjoÏ.ªüÐ&`"ïæÁÎ¸Ø¦Æ\q¿ªÍÇRAcÈÊcè¢§8'nx:ý:¡*\\nîí0÷ñþÞõBìi?º\\näM~ßÇ7{TgçqFø´Ð}ý«¯H°N0Öá+§.üÛòBp^vcE\\fë¦'8/À¶È2ðÊu9r/ÀBÿ/Ü%ÆtM1ûpðçB±AI×e\\r8EÔ5GGAÅ^PuàÐÙö}ºI;Äv| c[wÒE!l]¶¶Ïãûx$T2þJQîçD;­bDÇ©jÒUâxÒßà³\\rÃwD×mV?/L1IKw^~7&íØ@{) T°½ýQÈä=Ã¥ÕLÁãXrµ+Yl*2ÜÖ`×|­KíÌxkz9~ö{¹éÇ³tsâ)y¦öÄwòTó¬ÜÝPÿÇ¨w*}ÿ\\fdÂUö=_8¶%l>©£x}Ôì\\r<@Ñ ÓBfwÏ_áBíIÁìÿ¸|u{£fªfÞ÷z"!Í½­F¸`®xkÒoùo×¯Ñüøle¨àÞU© kÁ\Ex´¸¥rþh¹ik0µ»³ÿþäZe¬µVYºôÿ(ß1Êâá$¹©ÛÛã'ÑcªÀ&ø²Ýr¥\\r³%ó\Ík6 íl¡)×Ú8\ÇbÈnFJ)qæuµ_\\f¤\ùoÃù6Ä>îÞ>Ç7b+\\rQ¡Ä°aDwëï¤ë {Ùnèo|±(°t[UÜ\\f^SPG¹E0ø.´ÿË:<ÌEL#%6t!º=úl2ª³â ¼¿¹Ò.oÉVÕe³0· uzÖR½£uo²i6Ä'ó}ö&â^óÄ<ëßlÇu!6\\fpþc\\tNOÅÍ\\t«¨?q$1ù<ÕÚWRjVYM¡"ÆÊµíL¡'%#ÍdºiHc;¹CÕ ²[úüWÀ·°7Ä÷èÌq!9¯Oµ¨å[¢C!îEºËé¾ÊxÜò\\nqÓÃ=èûj¦  ÙÂûc\#uSi;µ ä«i\\tU Y+QKoâU4Ä(4ï%ßsßd+?j©®ë7«ßèéµïÄîýtbjq)x[]5]n·!àÇÃÏêüë¶¿ÒèÚ(Fv­î7õã 9Ø0ÁÜÍ~'ÍO¦ð)ÂåëéZ3¹w¦E¦Í\*­ÏÎÀ=*¥dYÉëîæÿmÕvªfØºÉWÔÌö¾ï©[´r½ªáÒ1^DÄ«R\\rCO¶Pê©³c·ïÔY^J.m°©O0ÕÌ~EÎY*iì-ßN_Zº~dÁL£{'PÞ$PV×|S¹7Ãç¶ÍzýÑ]ò¥tôy«¹;Ó¬¬dÅ'¬¨'>:ç [@«bÃm69Ñ0qÖtÄ¸ªKöoCõÌ\\r,µvÄ'Zã5{þð?ý  c«NÙÞ1µ°±ö¡N}ÀLÏàæ7X%úÎ]ºÒ4\\fY|ÍpË}ËÚh`zÂûHâôëHP´YÙ4?æåÚsÆºv*LïÌº\ÐÙºêM@Ó½¤Fâ6Ú"ÆÁ$,bò/»ÓCÝA0DÇ¯÷# \\rVµb½>+UMÌ¦¡Çª¤aeêP0­â¬,S\\nC+»Áüéí-ÎÓ°ëT²OaáÅÓ¢cuÈ¶ãWDãCY¯Q\\rÙ\²Eª^Ò|ÉÇî/?(Ú\\tÿíJ\\r°>@Pz °@ûÈÄ¯¨øÂ9ZT.tÉ$d\\rk0®Nî×8J.ªñ¹æÇYE\\nOD^u¾|ÎÇKqÁ2Pcló\\b}7óÝ\\rÊ,ÿa\\b.2a{ èWÇæ20>ñ¼X-îÜ¯Þò®©Z½Í\\t§gT¬µjl»i3Ï«äKmbúrÀ]Ø«ÏIî|*PL:Hë/ªø@¡dÔ¶¬Ðh&Üµê72/&ªªv¸%ÆÕL))?òTs²99{Í8÷TÃÓ9³1ôm48²ÓºAñ åÖ5à1êíÐF±RxxyÉµü±á2ÚTº:ãÛu¿_"`ðë?Î2"Y~ã¿­êÓ`sbJÚÚo¼ÉÂzÚuv4µ72(µuo9/,oØïCÉ\\näòbm8íü zöHfä!ÆÜÐ×o$D­üF.E1B(I\×MÍBQuOÇ (ûDcÚÈ¸S* á\\rÝð9ÎkÏËýx­®ºbKµâ~~¿B1VR:$wÒiê9"¯îUjZ'k÷T¥ü¡±#Iü$z­ÂAßrê.¤<ê©Ù¾Zº5\\r¤çx%â^!\\bu>8èz´íÎ}l³ ì¨å7$ógR "nÌÆ<É\\n._`¹Äós[F­³ç¬R.Û÷çÜS7YÿÇo@W9T?$çÇvÃ*³\üCU#ºmÖï\\rub¤!#GLÊ£â,6Ø½1m³nü­ Múñ4Ù.c\\b\\fKwê8:ÅðZSÿK.S®#.,éð\\nj!7E\\nÕZ94ºïCýGÉ®KõbúæñFRÒ6Q\\rw7X@ëÔà¾µ³ëmÖaBh`& ïÌ?¿ë²ÖýÃÚæ±ïü2ö=~Vöæûüïg<ÎÜá¢\\t»È£R\\tg^W4vÍ;­ÙëA ©¸ð¦²ò}%eº×:ÉÛhÿ·)åÉ¿?è¿ÎH0-êÞUì'aF-qâm70@V¥Øé7",íy·KûT>b¨ýõÈmX-÷"qP&;>Q+ß:÷NùèùéÍ£(VÆV«<;ý3wQAÓ{è£\\bÕF/2fÅQlJ.ÕXÊæïy&@Ò[0®,@ÎZqxR)Sn<à%ãtøÌv^¤p;<Ða[üu\h\\r}CÕÿÔöd×.X¡\\tólýM5 õ)ÚÒÎeú°%,åÿOz¾Q_M§?4ÒMhU£ÛÁíÆcÐÜÖû\\f[\\n'? ¸IàãgÖuåüÞ©±¤Áàñóÿ¦Íu·ìhÔÑá«<æ9'%KdÛãñû×¾³¯¶fÉÙ± ÝaÔJ¾ÉÚ©3æF$Q4üçÃÂøË FåÇWü<nØ4Ì&8«{«#©"(*Û·»Ñ\\rñï(UòÒ|û-½âùF:A*ï&E ¯ÙØò¼5X´DñT/0E\\b[\\t&7CóÃ[K:MÍOá%Do;¼|Ê§Y"Õ¸¬CL»| òÉªÖá/ì2á\\tæPÆ"©ï¦ÏÃ£üNu½_\\nBuCÓÿB "ïÂÏ\\n¡*MË7Ìy -$O}'
    //   11: dup
    //   12: astore_2
    //   13: invokevirtual length : ()I
    //   16: istore #4
    //   18: bipush #9
    //   20: istore_1
    //   21: iconst_m1
    //   22: istore_0
    //   23: bipush #123
    //   25: iinc #0, 1
    //   28: aload_2
    //   29: iload_0
    //   30: dup
    //   31: iload_1
    //   32: iadd
    //   33: invokevirtual substring : (II)Ljava/lang/String;
    //   36: iconst_m1
    //   37: goto -> 203
    //   40: aload #5
    //   42: swap
    //   43: iload_3
    //   44: iinc #3, 1
    //   47: swap
    //   48: aastore
    //   49: iload_0
    //   50: iload_1
    //   51: iadd
    //   52: dup
    //   53: istore_0
    //   54: iload #4
    //   56: if_icmpge -> 68
    //   59: aload_2
    //   60: iload_0
    //   61: invokevirtual charAt : (I)C
    //   64: istore_1
    //   65: goto -> 23
    //   68: ldc '®¯¨®f5*'
    //   70: dup
    //   71: astore_2
    //   72: invokevirtual length : ()I
    //   75: istore #4
    //   77: bipush #9
    //   79: istore_1
    //   80: iconst_m1
    //   81: istore_0
    //   82: bipush #68
    //   84: iinc #0, 1
    //   87: aload_2
    //   88: iload_0
    //   89: dup
    //   90: iload_1
    //   91: iadd
    //   92: invokevirtual substring : (II)Ljava/lang/String;
    //   95: iconst_0
    //   96: goto -> 203
    //   99: aload #5
    //   101: swap
    //   102: iload_3
    //   103: iinc #3, 1
    //   106: swap
    //   107: aastore
    //   108: iload_0
    //   109: iload_1
    //   110: iadd
    //   111: dup
    //   112: istore_0
    //   113: iload #4
    //   115: if_icmpge -> 127
    //   118: aload_2
    //   119: iload_0
    //   120: invokevirtual charAt : (I)C
    //   123: istore_1
    //   124: goto -> 82
    //   127: ldc 'uP<ä<Í­ÞróW3·ÔrhU\\nNeduLÁ(1ÑÄ.ÐZé}Õµ×Ä¢n!æÝÜ2YõÆzßô§$}¼ï[\\bÐY¦F÷\\bà[õ®Cø: ÏsmB®«`OÖ½f#÷¤icèxÄT­xTdÞ Á'Æ¤{á¯\\fÞpå?~Ö÷S¼½Øsý :1A©pKVYíkb^º "@Í!¯s1)úUgõ¢=ÓÊ)¹¢±ø<.çúTæU÷/\\tÙØ$}?¾ÖéCM¾Ð¢+6øþ./CÔf¨1K³:\\bêNr¦y $}>qB¹N6OÉÞÛ\\r~ÓÓhìsKÆÈÞøÝLmpAÔ´\\nÒ=(?·dÉ á%y'^g«F\\fáEëÚ=zèY1å|ýúæ¥HÃÐ#¤*åuéüq¿óÎµYüÉþ½B$âû*î|±fËxëð&Rª;Òï=/U«Ã(b`x¶} è\\nÒæÃS)%×Ü'q{I;ËÏZGÒ'âÜÐçíÚ|íº^Èd^î×·v~XhlýÆ$ü!Nº2"{Ä{G£Öbº ÷b+ïÈïÆÂ^g¾àªÐ¹Öÿ¬Ýkú&/ãZ5¤­´ïøxp¸¢xq-ÝPmb{û;¤(ÛÀi·¥¬½Åsìé\\tìH)¢7ÄÖ3Õ%xÏ3¢iÜ¸26+õQbô|É÷¢1ès$®_æ á[5M Áq\\t½¼¥íòÆ\\n_\\tºD4UVÏf«Ü½úÊKzÚ8ìáaØCMí8\\rÆìx{&òuÅJ-ojz9Þ÷¸JôåÛó´­ß®q(·ÓåíÆÙ¶êxl®¾ßT4z05²æKÓüRâÚ\\ts«¤#æAÎ¿ÆoEøÏ%XÝhôE>r²èé1¹N´q@±]EÔ!ÞÁ&i ïº§ÿìMMRZÅ÷ÿ})¾×Þ-ñ2J£5âÃÙtö±sv³»z¶Ê¶¬q¬Üµ7æöÒ'Ûfd'¹½Ådø\¾':6^ÿ ²N-Æ¹%Î.5îú]Ðb´`~BlTÈ#cMNalÄ±*Ùl¢PK%³ý¨_àÅö²`}ÎÃðÇEÐº4ËýÒ´ÚR>×óãÖä/¹¯ðHbÝ)åM7~866ÿó/vïà:ïÇc27XC\\rZxkòHFäÙZYoHCÚþü¦´µ#HÎX8úÞÿM2Órtm<Á2ÑäK^B"Õe¦àÞÐ)ÉsÝËaO2÷¹£ftq]þf&3ñ\dOüµ1ñ¬Iæêõ'àÖqÊø2îÝÇkÐ¯> ì)¶«Xkryj´÷9À©*]jÌü5³ãnÚip6rê+2dºÄ&ÚVÛò9×NðV\\f!ù;ØC*òDpÁlú44©ï$£Èaª^ëF#k5ÎObÌqyÂh²ªp\\t÷ö¸pT-Åþ~x×Ù!¹U~cýH@aM£üE1O-' ø\éPé}¥_0|W`¦yì¸<¤bUBÏEû'Ö"u2ôÃî@!þÔZò´+ÄôUÁ kONÁ2-zëwÙ¬í lÀöÅê8Zé(r·à\\t!»:ãñ4\\bDáAXQz\\b}~ÏÎO?ó©.¹\\nîdpÓ©óöÏC´QÛ«ÊÈAÍîè^íÂF@¨C¦Ã?1¼»ÅÝ}ØÜÊGcó3}®Ì(xj6Gñªnú\\t­<2ãG'5I,¸A~äU´WµRÄ8ÁDù½¿6Ð^ÐEÆ&!v~þEÇÞç´ÏÀ¥\\nôEn)÷2,6öPWÌ\\t®9WÞwH¥\\fÖmáVùl$ýiCðÅJ[t´:ÔÔõh @&"yZÀÚc©jäùïv\\rmNÃUQÎ\\r&-h@lä cRb³97*Pm½K9¨Aîg~v6\oì,JmÏIõùÇþm½[£xóUÊ,®¡´Þ§ä?9¢mâeÌáf¬Ó§°²ÜKïö¸%üægèù··juoÀ&ÒN!Aè.'6ÈtìaèskRAØ¡mæ±/¦ìÎÐ=»ÝYó"cc/z¤Å½yIø+]?dÙ¬ØÖ©x:èßA2nnØÁº¼H[?TLô8)ö_©\\rÅéD(D:(àÊBpN/P-Ó>M´;Q8ÈÒ&¯»{=PÒ½MæÒt§#cêÓà:êÄ«a¼*ämD©$C3DÒ¤CI|­exÃH²|fëm3¤BGò];ZaùÒc»îoxÕ<¤{]jmNõ%JÀp6HýMèì11IÐqqz?ðêí[»¦(V²l £îXúuûaE^I'}ÿJC°â¹Ûnà/~që+Â¸Oo.J#zBÅ(èó6*¶nñzÁt»üõÍ½­GD}]0Z6áþÍãYÎÖ®ó©u+×m'6º&74Ó!÷R±}Pj³÷sÏ§íW}Þõ§ò0ÀÂÝ¦çëvcÇu§Lú¿Y\\tXa`½Qÿ½óA:ç:KÞñÿ>Â;ÝW}`|gâýäRÆ!²"sWi_úy5d?)&¶÷¯f"Ùl£uZ,ù1}Ïhèb/þ÷¡e@Å7O\\ti|*¶ÆÅ%å0Ìv9³¯×=@!ôÚréþ¥k° [å_³YÈÁ´£°9Äµ Sßzhì£yi§õ 7à<¹>±îð«Ø¤²-­Ýé\\rx¹åyX7r9 ¢%MÅÂ'êÙòewHdZ;i$Ë#´çÃY\1àq'3þ¸E±-}ØÀ^Zv0|jHÜL²[r¸§-¬°7U×M\oFl\£¶AüË0DÈo<¤N=ä®lÓ{¦¸êp&nÛ)4/\\tx¯72 (mo¤EËxÉO½îÖÕ*Å<ò÷9`ßúMgðÜXj¶Ëö·Ge=½¿ÝêÎ*ÐÙô.r?QzÔlEt\}ê3ËçhÑv»\÷á?ZÐ;{uôi ç#¶tGBé½.¥×kú±Umï_ä}LÆ7«½rÝp<ô¨Ú¦99Ýªsê(ÆÙý¨>í2EàZ¤³2qI¤ßÌ!eCÒÉ)>ýMuHr4y²éàîÜ¡jîÚIñ¢ÿ(·ÔªÔC©ü Ë=½,µ;k´"Olká­÷öÊØÌnà×5s:]1V?z>w$cÖílBÆ©óþWm%åXÆVÚ3Ëw+áW¸¯0#R[3áñï°ÄÙü<kyÖÜ·6:Q'=ê[7\\t?æØF9{à=å}þpÜ7åcÎH8Ç>`\\båkJí ö¯Â*ä±CC'Ý)òÈZì§½ØyJ¥ïëÉ\\t0Ð?Ã­L}ò4]£/pé\\tÁÚ«_6XçÍãmK9C×©\\fx¨¤vVß9g$ý7DÿX´Üâ-!S«þpt<vó¦Bµ">yd^¡3zî"$ÿpr¤¿¤N_©yáÙk¥ÊUa#Z÷¹kgþOóhï-ä¹â£y»h|À¾{¿®HU÷½âÕ!z2Gõ?S£,b7£nân/ª¬{Ï<~ yUÀü8lâGæóp¸ÿKãÙRhµ±Æà±VGæ³«j)»ÃÛÍLÏD4\\r]½5|ÿãE3/ä ÷&j¹âÌÄH!­½*Æ´ã' aE\\fSÎÂ(0\èÞJjèSJb+´Â<Îëà¿Tj\\bí->qúô_ÞÙ¤\\t\\nÑÃÑö®SB@;ùkÑ´j?X®1ht6ÙRHÑöáÅÕ\\b°~z$«WÅ2Ü-\\t~&1(v\\býýl?ï Ø×"Q}Ì¼¨+È¼qNa'ëwôLñ¾m>ê ß¡¼!ðj\\bÿ[»\\fµxr'\\r¹Z6³-Ú¹¶wì³­Xb,²xnà8ý:ÛOª5oí²Í¿ý\\b²ÇÂBWÿ3Îæv<7Ôç1¼ÅÎq?PWh¯¶G};`¬HJú{Ý \\t×A.l'((v>0@"Ù»©¸\\n_Ó¯ãH¥vLÎèhÔüceË3qã#Á4<G&¢P#xÈißí©ø+>ô©½¼=&aØªXv}/%P=\\fHÅëÓbq¶Áò×ÊÍO¨yéM%ivx`Ík-?-:bK~ëu4²Üî±7ÂØrrvÕÙ`ÛÆÉ\\rR>}vµcÊo¦WTÝ;gá¿¨]Ê]Dbs?2a,+}ãÁ³êUjß÷>Ê*+bx¸ÎÕ×­r¤p¦>mCªJô¥¾öúÂ\\t*<>µ{kyöú'Ì¬¥¾|­ø]@¹zÿóÜj³W¹kèþ\\t3¶Ûnñ8z½ÎÇ 0fÑx^{@c±C©¦Ò\\tªNdBUyüüºÜAÜt²àpÉö[vÙÞ73üïKn®ÜÌí<£ReSùìVGðSn²tGñ²0M*Ï(hW4fÛgF$Ùº}¯ZÃÝ°*lûéÞ/ÝqOØÚÔxÐ"Oë<®ûFN2É'~? »VuÁX~ì:û'ÃËÜs{T¶ó,ë÷ñj¿xkºUW:¥\\n£Ó½E.#ÉÓê¢7¿á³÷wÜ°tÌê,ëjVªÅXõ9ÓzÉøê/mé¹ºÙ³Ö×äañ·¶À(êl¾îþ¸nÏ[êå£-Âôý4¶LñK)SNe¼\É­ÿÙÃÖAodãi¬vö8o·ª7w×»çÅD¬¿Tu|ô[ÖoÖ`o7¥¼6GRÁ²\\f3îasñ[.}§R¦Yq¶c-C£vÓap:MÞ\\böC1\\nr0s|4ær­0´&#BÉåàp$2±ýþ¥s\\fz;õXÚJØ/åXÛêÀÇÅ\|9®·zlÈ<Rà¶Áp6RóG¨#øê«ÐDcPdÒà¥ì­=f5±üZ\\rÙ2ômcew*4Î¯rÃÉñçQ3Õs¨ñßÊXPÞ*2â2/á<'C~`r{d¾¼«!\*èï4Ñ\H±NÏ'©¸ËìWeß$}\\b5àö¢[42'\\rbnÞÂù4[æ_SÑÒf-YÒTòlâêQïó^¼¹ÃsïûÐÑ]XúÁãCpxgÐÐR \\t"yõÅM:»LÒÑj¡ñ.¹ÁIh^ÃfU80É¹ÿ=µy(¾r_|ó i{T}¬ËaÄW²{gÂ$ÉØ¯öà@%¶â¥é¼Õ«ã!eFâgâ¹?}Ä¬P 9§ï_Nj53R×o[ÿÍßÙ]?Ñ{¸åìû#Âb\\tÀlO@ÁE<JLo´wô5P0ïM>²Hfñ\\rÀÆ»Î;ÚQÙÎËuÊCR0þ£ë&ÅÄULw»ÊWÌ ¿¥Ådbh\\fp¥s òhË³p+*dÜKæqi4±ñ>$·ÝVâo^²Æ\\nY ³O Ã³ÀËv­8ëÒ6pç>/zÊ)¼Ï54ßÊÊ~íÃååy\\b.­=J ÝPÊJ¯µvd¤òÄÝÒ3/Z'9î¤rò)+\\f+JIZyU%C|Hy\;B"&ÆA ¥µgðâû¾w=!¹CmO)¯à\\nlØ|^6éukjüÝÎâÇwá »ëT¼vµ16B®ÊnJÙóÀñT@u ÷'n6çÀ¢èdÖRßsyJÖB¨ÔîeÆ/ýnèöôbûÇ7SÂUãD$jí£%Ì×YÏõBi]Ú{i»#jÒ¤vlÌíOìÞ¨ \\rgàQòª¼\µ,?@­È\\n[_u?u{sM(ì èÂ®C³Óâa\\f^?/÷³¯æW­3ÞlrWG\íîUÌ2\\f¦<+W±ö\\rcñt¡\\búq/GÑ'S& .#5òÞÂÙlcnùöÉ«äBöÇss¬Ú9ôúó¸ÄIMÄßÜÜÉ?]Ôn *k!AØË¯\\ti/£*èì²Uc-á|ª"»O£¨t\\nrré¥¬ÂT4Seÿ5SvfQÐ¤·Ô¶ëº{Ë> X°pÛ`¹hÑ=­¹1ÚåØ(ÔZçñâ[Nb.OÑºðsÍyzuÈäW=;Ñ²áÎ\\t÷k5Myá@)ÂâgeÕªÒ"ÎðÎkò¢«Ñ} þywêî¶oa¬óÎÁöúÄ»î;[¬sI!ö¹¤×Ö'tx}/HÉ'ÚÄtúÔ±u¨@©T(_ìQÀb{Ú ¸øw2Ä0ÝÃ;$úúÊÌG[2ðF*¥3r/Ê^=2ÏÇ§{íwÑ4ÈHÁç­ñÒF\\thz!sN5ÆûÍJÖe^KÞyöQ5¹%C]¯ É~O(e<úFy,¥bµµÇ ÀÆ'û.I)ÕMÀîvÔR»ðºLòWÞG< .h\\n!JêL»¼hnÁP¢Fpùâ4Á<Ë|Àb¶è£RâïÑ-K×K2Go\\tÔ¯B\\tUN ]zX¡ñ$í®iíQº£Hÿ/U?]YèX=}±®0Ú©ª"7kÓOSñÁí½/:þqÑÍø¾óàEDlÕ{æ^jKC%¶ÚËä#Aür1Xîû÷ú*^È/F¹tî~éþæ¸3çþ×ÁÙh)ÃûÊ6f)\\rSÞ\\f×ßMfã<ô¶Vçpjòj\\bÁ¡Aì\\to=Xú¤méÕÀÞëaÐ¡pk5ðª!7mý*Ã<OAñ/ÿ,OÕ3ø"Ý¨,&ìí%Þr"ÏEÓKrÓu<0ÓÉLS¦Åø,rQ.Zh³ÆEðÚ~VäÚzÌÀç7<J´²]Û.Yù\\f¯È9-¥¡ü6(fG«úã&â¶'ZP¯P?6¹~`é¹ß)¶c©'Ü¢¥\\n¸ºÏU#;7H²ëëe\\b\\nò¹à®1xn8;w\V4°0²½@EL\\nUbß:mõ'üü® ÑË;ýx\\nÜè~±Ðþ*îß9._,ô·®u¦Ê}81½tR\\rV¼SxýñrºÓ÷b<V·¸@qC\\fÁ"ýíÅjöet§{Ô,Ùï`í×bÐdIà"Þraèæ}FÚ\\r3.T 'V;ýs.û¡¨»÷>rá0v±qÀ?í¥g{2/ZÖMT¡æmÍãÀ$h¨;åIÂ@8Î"o@á0êþÖlÌ4îN¤zêçÂÌvÍ\\t9IS&t&P²*áÌXon ÏjÖj\}¡¸Àõå£ìÚ£ñGÑ!úT+YüHºÈB-¢)¹°¥ ü¿8.÷\\nÓû«\\büoÃàh"ÔÏl*/:¿ß"ðñðÒl=zN)öGæXÍØÊêÄVzÔ`µ+A\\bªúâmBø<rcÜÈâ¢wÛ©ÐQá'«Q·Iëz*³j®¢HªÙ¡PYiº¾Úz3álBXô±j|Zúëeµ8Ã'¸Ûj9D¨¨wæM\\rî¦úhbîñÂ,b>aLgö@?>ðTÅÿo=;§¸Æ_±ùþçþ_²5ÂpÅ×«pLÍmo£¼»oØ¡/Ê$F¡17yès³øeå Â,ÑåýSLóÚ½\\fUpæèqOVoh¶ÓÝ1S?D-ü1±\\nGØ¯jZLtÔ¯È]°.ó*\\fxð²ð5}Þ<PùBêÿTÆ L LxØím·xPcrÙañ"4­ä$òéevÌüQ«ðQ¯5tßÝkCª_Ëö^y >úÅìð¤1ÒÓªé(+ò¶5KÏò rº%[6óic®Nä ÝâTo"¯=Xr]xâ%ç¿R+IóDqö®£h¤2Dèê°y\\tÀÞ£CãòM±ä\\rx®è©ÞµE*õÙù\\nÔhÙèm¾17úþú"32Â \\tvÐÆR¤Ê9°½E«ÛXÁÑµ  ~^Ù!ùbí.²Ö6hÖrýî¼Êx¢ü^ÄíÑo\\nÊù[üuÆ6³È«rL|´¹\\rOM:µ!)RÉ40KL\\nÃ0ß4§°â=M¹ÂD39BZý)Y\\fØ-\\nD»|X}'Ëá7Ì]¿Á}4(FØ·»¿63_¥¸!Rt=ü_Èë^AdîâÎï4Ípá\\tlÝZèEª½÷ê!òr¾:Çfªúe³´Ð$N)¯ÅAÆ6$×³Ï¦<å\\rkN~Íê3ð+3¤ò­¹ÓÞ~ÏF«ZÈS+Tt-öSFNQºþmêíöI$ÂW´\\r ê7xnÂÉM2A$Ô¢à£îª¥Zè§ÊOÿÖ×!è¸ÀÃGi=-.Zvt\\nS×nÑñ¬¨¡*äîLî°Ëþ8Õjà9sÁî æn1)þt/YQóÐfëÐ¨¯WímôÜÿiL*MRl]6«*Ogy2Ñ÷~¥òá¾ÝwSN&6²÷À(¡QÑùd9r÷ßÑO´ÒùUý©¸yè=¹,uãrplhô¹\\nGãVÆÈ~y3=r÷@Æ§ézä 6u2í&µóåègÝ"¯_;%&`}4ÐqL¤r~Ñ)Þî|¤zÕ_uÌMÁfP\\n\\r,v@¾ÑÈçf^L½`1yõ\\tÚðìÿ¾,zsä®á¬lº½Ã á0d;cSh\\f{dÄ£YàÍ{]µÍ±ÙéÜQêójÑ°¦Z-®}ë+{J\\t-fº§ølÆ^Ëê&â¢Ø_µÊÉä*ñ¤õý|7Ùj©åTÄ¤Ågk| OÂ?\\tmÈ|ü9Â0dÿLÈõSlN\\buó\\rUVÌÏ"¤m\\f÷Ó.÷w©ÄX1õ_Ôàb¾BÉ,Û>HÖ¦=äÈ¸g:Sk¡lìÍÖr<¡õ½'9_\\tÿ'WõyÎïÍùäP~ñ£Å².\\f7\\r3¹åô¶t &ð¬ª7¬4nSSÉý-¡9½8Ùdífã (Ú¸¿ñLK"È®_X\\r\~ÊEoëY2\\r: ¼+çá\\r@ñe²õ¿yÈ\\n]¯¡Pû:ÐëN,Z²g\\r±Á1DDè;Ó¹_àL²½Iß¡CÉ"³È?3La\\rOL:ù¦nY Áô³TOäcÅ´%B½ÀSåaâN_kN»§sYm¦±?¸.¸¦µLIGùwpºL´3WS#ö$vüs¬¸@ÁX=L;©Ìu/£Vi\\t-¹4CÒu`µÌ,µÇÊÊÔk¾Ãñ¾Ó@Ñ¶ao%ÔxÃF>ÙÃ¤´Ï®\\rg»,.YëÜV¬2¢c¿Ðx!çâù0¢ð?pTLúGô'Ñ°ïÆË¿µ,S¾ÌlP½Äi¸æDÑ¯_¼ÿ7t+­í½ ,Úô®i§B(ÓeHä\\nê?ºÆê=÷dLÈ>è£Û£ù79ÁÒïï['L\\n.f=ÕåëEOÒÃ\\nLç5"èË\åÎÐW»®IkN«ô<jA\\rÑ`/U^¦@Ä¤Qfò²ð7 }C/É\\nKÁ+ÑYénV:§{!þ¶ÆÊ¿ÐUr£\\nû$ûÇIÜËq³\cSUiÈ&$¯Ð|Po/)Ê¯\\nFDH7lsa­Í/«ôêÃó(\\ne\éÊ.ýÝó¤èóÀnëÐS£µ³JIù=C³Éß©^óOte!½EöQÔÜçÊm³Ã÷ªj¾Y~¶Oê½-¯»ªÓæÅÖ¦ÅìÚëÉ(½ÆÐÅ{üj}»ðO1r|V¹ödíì5äæ¹6ù7ÿííóäü²'~Ã¯ÚWWÃNåegÜõñs8Hñ÷î\\b_rÒ3N#5ÐÜ?8³ ÏfÂz÷¶gøQg¤NèDÞ©¦»^Õò«Ï«hK(D ÕugzëY¤ï8h½ =dq¸/ã¦H¿ømB®Ò°);þÉD~ÈeÅ3çxðãÊÖo0±ÛçQc ax8½üØv¾^\\nrDô16!õ¬ôÎþ£Íb®ÞÙH¶vy*ý¨HÏÆ¼IL3/¢@!aælH\\rÆ<z!+´zXý­ íÛç\\rÒl>pR ÄÞJÿ8ÔæA@|ÁVº¢NY¯âyrö at\\tNWÊgx8.¨¤tÓ\IuA¶@àO¾ÂwáÉÙq9õ7$áY[~ûª*ûÈÁya^R?Rl(p\\bs4¸8¼ö)éÂuoÌ}ôàÎ0þÔ|§JýU@fÙF-\\fRCÆ~-IÐÐD\DæP×]¶{@©âBSeÜ 3H_=¶Rã´8={ýÓõýOJs±GÃuõAêGg)òRÚy¶/Oü]9Q8þLvÉ{B´qì¼!JÕ Ceòè\\t\\tRqsní^©MM=pû¯Ç¤W£(DLrÐ\\nAÁÙypÉç½§yãÌ©óî\\nv?PÀä¼ÿVàµ!dääìÛ\Ô\\n4X7ßñÇ!%¢Þ¦ÑiäYW&#2M¯%NÓªfîÖÉ¼>¼´±ºàäºøñÎi5Ì´;g`n»YðcWx¦DlÅ¨¡_G¬!ç¡Á£Ù;µ_e?Á~^©{ì<ÿÓÜ­Á6¼³¦Ò~HóÂº\\b ýÆ`â]¶i\\rS2NeõT-ëÜKi=Kù ¢|¥ÁÓ8+/Sä[jàá½1{°ßô\\n]¶$\\bó5ªÛÂï±Íà§é±¢¶\\fÝÉ®$\\bK,AÔq÷W:³ÑÇôïü»Ã!>ßDb%lhofpÊg5¢vn\\f¿]¡\ZÛþù*'(÷ðûN¦³\\rr^Z~u{*p ¶T Bø¼yK¨U" üá'fC~b51`wÉ¥c$c['1Ñ´kÝg¿Åhwì;«\Ë+9g2zxh<Ú¥©Yaû#mW4ÅgqÅ p;âm1áÓt0ÎÎNÁR"iéJéÇ,1,$Aúr±ËÉ°R«öØ^h5Î^ûþzGñ \\týÿ6·uzÃ_ªf!'Éîº0¼ãm!{\\tÒ÷3Á*UÒ9¦\\npí@ØGKwD·>y6ºêDË±ÜAÖ±GowÃ{¢JrßÆQh.]º&îè5Í(j\\rã~¢dþ YÔ½å/TvJf8¿)Ë¬êñÞø$ zc|i@ VÐYKtî\\bYø¨Ü.Ðw ÕÁÄ_#·%°¦ÁßýGçÖ rwýbsû»:ÕåÅ|´P©ã<MÁ©ì2ú64öôFqãÜe+Æoûeñ#,ÖQÎVH¸V0_¥ýaÚË$ª(ë:sïú^Ù»ó]cMNÏ¡;VÍ\\ràJÔ_:KqñÒ &it?y/±Çô¯HÒKU1DbúÊH(¿HMq5U~yðáuM5rÉ[«Ö4v´å  m«Þª+ôsÞ*íSÐÒ©°û(¡&;¿¼{@xÌøÊê¢Ç\\nO µnõËíí%Cu{ÜÈb9à?F&ÊN/L­fépådù5Eúf\\rkÆâY4>VJLto ñäãÙ)¢àsõZø¶z\\n¿¡Ã£æ"d./ô?5qi°¢WH¸øa§IE´ÔÔ¦LoéûÈÂ FòGaÙ:ó\\fÐ9y¼©ÜGÂ9âd¶ÛD~Cä³Ðü%ò?àÖUçÐÎeqvxp'õ+Ijúó5]Ð\\b"l«"ÔH*·ó³í.ª¢¡K[½ï§-l´jSã.?¤Ñ¨cgWb9Ø÷89_-ÅÂ3þg{ÿwÍñV\\f÷b^témoì8Ï£S*öê¼h­ÞµlFR­¶¢¼ûáoz2H^ÍÑ t:+!+É!åaÏú0åpÜÓù ôGsk^âÔÁSV8F8Ò¦'iÛèuÞUaÿO²ýøîl¬ÓÏ>t¹³È§ÎPiÊÜ\\r @ÛÐYleaÑÔxè=Ïµ#vêk-¬m@îÏyb«ºE·¼~åÏBÝÚ\\r4Ãc¼CRvM0]oEdi¤1·¨J:Vè6w¸@ð<ìODVrÖÅn¨{t]óñ¢ræ"U¶EN*´ªh9Jî·GÓ¥zÍ\\tM?eª½R$sþv'NÑ! ÖÈÉÎ\\bÒ>ôÔ&ÑT¶3\\r=ô¯æozJ½¶¸ºÃ¥:á\\fÁ'"¿Õ`;nÝiÒÉtnZz×«V$²|#4¬-D3¿Ïp¦w>yûÅ¶j"ë<zþDº¸~# \\bÆ{§þÐòâ©®ùU^5Åà·8j½Q*Y$ÛZË\Þ;àSÒÓ³ù+\\nï)¦9ËH×3HKW>2uÌ÷uðÇÛ1tùÿB»X7ÕÆÔë?ã4ÁWVl_`7'Îùq<qVö`D­%réÈÔ¬POóW¡¹ñk!Ö¡Ë*ÊmV!*ÇÑ7ðáD!\\rXh¿]wêè°M8ÞîÔÖóKæ.Î ¾)C¾â¦Øã³°Ù\\fný|Þ0}lCÞ#±Í$1®§âR)¦cà!»d{òí°¯©:BÄ¥3m{| :gÚ#µ8¡â¸ÚÃVBQüY\\fñZíhÅxàÊ¹Cø ¥¢tþ&hiö¿w0o6i\\b-?¶iz6]^pãqWÊ>^Ã[¬®\ôVÙ³ë´-×Þó¬YÚntFl47³jÐÐêëgÀæVÊÒR]£]Ä/Ì '\ÎtïVÙfÐ¹lÐÜ·Ñ­uícÕ[\\b`0ÃµÐ¹ÛÒÈß{¬ )N®ÄwFÎ¥Ð¨®^x¶]t!I­\\ff²éù^K{Uø?ç~æSÂ.ß-ÝMÔý*Aû }§>4OÄ ø]ÐÝx÷k1\\tbmÎZ\\n îÂiE5x¼hL×62Uâ§õQÄuZ-¦¨ÜÞþ³apuÿÔ=ÎºKÅ²\èõ§ÏÎó3J;´¾+»Î[¦µ=4øÒÜ¿&þF5Á|~l°Å.ôõr"s(Ñ¦d©Û6ñ­ÚwIfCNMÚùã°ÜÚýèoúáorÌøAÛ;]õT5UØæÄ«¬}´ë¨ ë÷ßº{ø¡U«"Ð ,yPÝ]ÛJ|²%Øg øZ§Ó Û4±¾{t+¤x{ÒW1ðw\\báè'Ë¨%ôP2m0ûh%ÕÎb¯ªÙmZGð}Zð±¥¤§H¡uÇØûùþ¢bmÝjÞb §¼s-Áø¾^4µFPc8ýµõí\¸ÉiýîdÔy[]}"¿(øö«FH\\tÅÅ¦Yaiè[¶õOÄ·Cv@w£\\r;h!Þo ¬¿Ñ1{·>!¤VveÆqS½fRKUµWÉ±?äÁº*z÷´H´:þõ1Ïm¹!;Ù¡>k÷wêâµMØHù.UÊý´%ºðÚõ**Ëã¶(Æ­ê[¬2+3x³½¢oQ5²%\\nOïgÎpS£Ñµ°I­êx>lb>ÔªèRNá6Ä²t¸Q=Es¦jÁÂi2ÑûÊÍ¹ÄëÍZñd+Céik#<³¯BÖ,âîØ-V´·9VD&8ñÄi«¨är-¥rþ÷UH=°ÀB¡!óÓñànÌì²jòØÉß­D)Í¦W[Dq{.ÿUzå½ÀhÊcË>&Û²/Ã5å~J\\b~;WàÁI\\f!\S2­úe áå5h·tÎx¸y|J[s2»9!Ú×(\\bOÚ?òÕÞ³ÜÌéN0º°×ì-\\rÒ0\\rÞ¯G\\b¢Æ8|Ý¹#L`ìÓhjÑY#b¦æç«ú·öL\\f­êw×¥Ì¤x«L7j£ýV=~¿Äá®ò¬Æùè¡áf)Ü @÷øè"ëeËgâ{h¨qQ£ñP}tí§1u°N+v³e iÝQpÔê8ÓsB® ^®æè#¤*\\\f;\\b¾º!B:uZÕßnYQ¡³uüOÌfyq~É\8+fcãýn a7AÎÿû&È§rõE|º/Öª©<¸¼§9.Lq©\\f\\r0TY°¶lî,rÇd%XÜRÈD:NMöËâáéÊwÑè¸\W'Íòm§?à·f}5\\nU|,èý¿6\\taÐàf(È4Hæqøÿ÷Ó·¥^ºnhÕeªãÁÊ¸å¤¤XAFòÞùþºüÒª8¢00~ó°°¢¡&\\f§óþ~¦/ÕT,XÆA|£Êâ÷ ä;t¹Ò\\tíÝ1X¬ìwg±æé¹h²èAkÍÜ¼*f\\b©À1·ó×'«l¯õp$n2ét M\\tI@ôãµ­9Îå8<âæÔÁ¨±«¼ÒUnd X3á¤ßÆ9ÿå¬¿?[y\\tKùNÊÙÐíÅÙø³iç¦}bãâH"¤þïÀ¤©¹ó}Æ"C¿~À%Â]èÉ_ò¦9³«õu)ü×W(7{º¹ ªÙ(<¤Y3¶2d?,î4tm²xë§óTÌåÈß_]sóm·ö²ypÇ§Jq1BEø?{ DÒËßC<$C8óôF7¬eTé;\¢Ñ/¹cKü²$?xÚW¹}WbÜéÏ0< 0Ì±\\rX«øl²L q¥çn§(]hkOÌÔRp®Lâft[v0VBSG'#QÓ·ÉC°ç6|ÜBÆê°9ÅüørZµ.ýf|øÈi¡á¦@òÈr_hSõ#ØÑß\\b¥Zâä çÿß´`}l^èKÀ\\f¨Ì)0ÃU2«AH¢Hd¯ý5ßV+&Fs ·/+¶ÚÎÍ^Å¹eE1¨±w°yÇÕU23w Ø^j,»&MqàÔ'Âdh*wc\\b¨¦ff{DÞ¤JùsJÆ%d R% !¢Òqk²Ï(îã¶ß]ò]CÛª×fPêêkÃAû\\r &{uÓ5w=ìÕ¨«kâyçÕQpnòÞ`¤ø¤Øþõ·"¢­éw u§Åð'»P¶__ML%N)Ø :¸¶º5ão\\r)@ß.2ÌæLfî2è"@S´¤/Â²h»B£ÌK¡"¸}£|¦Úw×ÀýÜ>Èä3Þ ²r9ç¼óÎ[,æ[*Y IÞ_µ|¿ÃNa-9Þ\\rñzs>é.\\bÀ³B{+ï,4+«Ù#K,È\\fQî|O¨WæÀ¶ý>Ölë³÷÷Aa¼ALî8$XßR^þ^§`jeðÃv©¯gQQ|7ÆoãNiÞ:;W¹BÎñ¤§¨$V(¿ÕíËù¤a¤&¯´«/!æ#CßvÁÅîsÌ¿^ý»§-äõ@45;Ju.3Áì,ãU5¦~\\n/Åm°ÿ©§èÃ¦¹YTÀµ°´P\\tM¡ãDËV3Qw|rD\\fS×>­Tc`mÙÂ\\n¶1ºp,·2ök4­3h4\\f·éÉÆ/È_hDHU9,ÙìSPÎp¦"*ÎP·3X~\\tõ\\fu;yÎ\\núZ^¥Yé@u^åºdwÞ%«úbüMè½fÕÎIÿ©Ðaxzã>­BÆùEý1ïî~þK¥rø7ð¤i®¼7¸ÑêÿÇ¹=V$·nù|O[È%I)×HÍK¶§®Õó+ì¢+Á\\fNò\\b~Rük ¸ËYþþ¡!DÄ\\b%éÉ$û±>Ë"ønHðxÔy=-ùß(%4úµÂúi*=ö¢uia>½½Ùäeò40~æ½ÿvp½ÅÒn¾ãú·´Í µÉF©9h ¢£ï\]¯®|&,\¯Ï¿ x8>ñëâá5ìç»ïGÈW¸à\\nz®ñHï]µüÔv|Ú¦9gw¼0Òb+s¼qóúÿJoÁ¬xå=Ñ@2¸?\\t'qDcá'~ÿÔL =·`Y>ÃM/n5ÿÁéíþ®\\rHa¢?ÞÀºDPWmJíèôóU\\n\;1¤z@­bu±¸UÍªZyýÜåô4AÊ?îUÌ#øãUöc-SUª0Aõ¼ÈÝi¶è<f¹TÀ~|Xp£Úm[}¾UlSq¿ O(º\\tB§ÒfHÓ3¥OØsbhkõäC¢©p¿*Hûõ¤)9Û¸Î¯ô oÜ§½LõÛíõáÑç­Ü%._· Ôo+c[OúaªLX8#2mÙEqà#Íý, h=ÃtÊè\{H¯{¯ãõ«Ûe§`cr3ÂÝÀþXXpu7«9ÀÕR¨bP bÅµÜðø¯&üý(x:Cýá\\b.-nê©Q\\býð^ÊdA¼ gßIÓ«Ç`Èç<(ØbOMÂcÎºþ4*¦£p%,e%'TÞûW¦¤àsVd/é }2ÚÏ^l9fÓV¤.%¸'Ñ?À¥7^ÁÂÆEã¼þ1î_³,J2Ú ¸¼D·rà×Ùß;Z4¢÷ÀqÕÀ¤IÎKÚÊW3Ö?@Ë\\nw¥{¶Mþÿß]×!)¡õÆìMFz*Þ¾$oWà;\\n¼ò'á0eBü)ª;Èp1ôÅ$HÙg¹iêDéS­bmE~cE¸o\LqÓF"m EX×K~çE4ó¥2ÂÇ¸çJÝø¢5£@ëÀ}`pþ»si½ç±ç»ÈwØ]hG,ò6Ò-S]VîáÑ{uMÐ«}Í7ü£®z:¯\\bú<mX£DÜ.ò&Áp3}3 ô"zéa QòG¾Ôzêç>;HÓ{fj¯ý'¾_`Ñ|ÍÐyµjB*9æ{ÊóÆúó×$y,3Ý¢| Í½Á{#±[\·=NaÁHM£8hq£ñmiZY\\b"Ã´æüÍ¿£)Ý«è\\b³o9 {Ô¸ù±®RØ9Mþ¦cA^x÷)?ûIahCý}SdØ¶XØ.È]J«±¹Öl\\r4¼j-.A:[ið /ÿ­±ò/~W,©í2þh¨ûü°ê×¸J'}Âs6É }ÃYä]ÃÍöØJzÔ)ÁJCÚèCþ@9»«oc¯Ð;\\r OSþS#vÏfMØÿÎ(%éR ¹îEîJ¦êïãaz¬KvÑÃwJì1Â\\b(+».yåà»ãqòÚÁP|fH}7ãlÓ¹Æ© ñ1íðO¡Úyêq¾¶Â4=Û³÷%¹¶ø`ÿ½90o³3ý)½4ElÑW#aês?ûÙ^_H2ýS ÞIYAm%}<jÓ 1>r0F)³<\\f$S¼i§\\tÎjläZë²¬BzmºJ*ùbì pMbß~ûJÞßZóò¡]JµimLwq3Òüºñ×·lGÔ[X_ÃBËçJU8ÓÊ\\b°­3ÔÞoC÷H=3NÿâÊÍFî¹VW.Â&µÔÜ½°lûú¡h(ÉRÿ4ÎØYâ\\t#:DC+ìµcÅt0\\n÷xðMÉîÇr *ºÐ`rð:üR\\bb*ùEfP'jq4bËN0YªDtsê¡c^t×²6M¨%~c0@É@5{ZH5ß"1ÿm ¡¡göÉo<´FÀ0Ø04=4Ñ ÙÄ$\\tü*7JùÅ "vçuÏcæ_q¯ã½ÌQíáÃ15ªß}ýB#¨ÈÅz<N"*sþ¢É¡²1\\rú@X©øò±ýÞ\\r·Ý\\rÈz;£OÜW·¹qS@._di Õ©ÆRPÑÞ\\tSºÀª~{¢Wæ£ 2ë¨*1ôUî Å²¦gÂ!9nÏzÖ®"6A]µLF<U\\rq+³ãLÑj´­õL§ËZ¼CÍ ¢¯¹nJªs è1GAÊ¾7DÄòã§f\\b} Î¬£TÃ»ü\\nogÅ¢yÉ³ R÷áÆÞ°gºMüNyÓ½T6-û)òÔ=MÕqSj°m÷ùµt?Þî¶ÑûÐ"*ÀQÇÕì)1ç\\r3?\$Îð\\t»æÍ±ÜfãM×§©IìfX¥CB{+ ½d;cw@»ë\\rîôYOøÂbc±1i\\tlâ;âQéQêbÇn?a§9¥³\\fûØÌfêdÛs¡@ÈLTq0ò6|ÿö²*ÀÆ%e ÙÔ\\r\\f®Ðr UgOü¹©RHÿ?*òïuo\\fõ².^Fªs.ø¯û\\tÜJfÂ¨ì$3ÙWXt©Ôê@­\Þ`ùEZÄªEúÀ¼vÛD Û4^4Î½óµ!ë7­K¸ÍÊ^`¤ECÖ|Üc@{0âèY;Â\\bC|c8c |á¿kE/¤gU® F/Y¼ QË:{@2jqùkfü\\rðÔî,(ä±Y%R$PìÎs®9T÷ÑºÇî|Ù\\r+UGÇî¥*5fLÁ·UÖÀÿCÚÆÐG$-³g}ø«XÇ(EìápIµ\\rädîôø)NéÐ\\b$ä0mðm52àNõË(én-À¢7ÙKôÎ+FhÁ{Õ{ÕÛó×ÊM(QqQéáÛQ¬îºÜWÛÜêðliÿþAô-ú¤ò¦dÊãTuÿÁÈÁG!^®½eÙïþÃ9Ij5±8ùÄñQ\\nÛN<Ãèvçk Ö<"}|³Aæ­öT×$àä,^Vw§øù²¤]iê?LLùL>ú\\rÆ¬Ç¤Æô%?¼éy¨)KÜòDk.4öÖL+_Mhù\\n¨¯r¸ÖF&(Õ-Áv_y\\tOLÝÊã(E08Xøç\\rÍ2 T]U'$÷á¶lØ3ðmÍÌÖ\ÔÚ*8àÓÎ±(äMßÔTjí )þ»s'Nó8Àí±rÚ)\\\bV!!;¦À@4'iræ§sôrìFÀè°!{ %ÄÀ¨OÅõ÷"Æk,3·û\\rÝã8­µ¼D«ÊÃ-ÇD½Ã[\\r¬ã×}âÞPÞÎCÑóóIBØ_Eí`ìº!¹20Òø±9èÿìÃ(Ëd¥æ$6ð;wÝ2£3Nö³ÖE ð Ý<L¢å,EÛ¾ÓrhÚl\\fë)&mípºû\\tN»yN°ÛuÝ+«E¾îJ&ón¢ûÕ§¡¶µ\\n¥|]ÜÚÅovLSÚ\\fºk¬óL&¹MâÕiÄÎ®êë óµ>ªÞN1Qj`)ß"é¹*£>¬¦g\\nÛòÞÆ«×ÿ\N§NÎ~tù¿Â±:ÕF(1c2ªFEz\\nö­C'W½/n¸sóØ¸wS­r5¡ÍåaY÷éØ}Ó½¯d0\\rCÙðó8ÝüS:}æûS^]¢(\\bÏßd#UuE®ïºfÇ[|\\nWý½~¨¥XåìÜO|»¹EÐ¦ÍGàð7(²íc\\n»Ía>H¾ò]±¨6dØ@\\tùMØSJ±4ñ{P7g#ð6¥Í?,¨a&bqNHð4=Ñ\\rïí{ ôª¯òêV§Õ^Ø!)Ä½è\SXt1Ùw¿ßï:rNßL m©Ë©náåò°rýÓÞ«èüd# "/bØ÷sêeÇóv.f´ ×l!Äalëdß¬qò¬±ñÒïHLÄ$Äo¾8÷] XÚºwF×Fh(QtÜë¹¦¥ØLû$[@ÚÂÏÂ¿hn|ºS"LÑàÍgÆ#6éRQgÜ{H¯uQ!NèeÊ¶ÉNZ,e¢m·zotI­·ªêb7ÁÂN)§í^]TfÃ]¬]ßò÷x)lÎJ!]=¯ölïçÏBi0©·àøüãH0tÒ ¹'îÄ(£¹Ì=%I2Ù®DüÍFÞu\ä¥Äaù¡Õú&Ic(³Êä@~x¢7ÌÈ,)ºOPùRJCfD\\f_ÀAµÙ×¨9±â°¡¤ß9ü-f:ÚÝèD06¸hlóXB].|äaw&ÒIªßÛÙ? Ñ]®Øï]@E>2gôÐ\\tðE uK Úþ:åÅæy\\n«wjb.ÖWyû°âad3?ðÓ¦;ÀX)º~!ôY7;29o@1¹\\n³ç¥ÍÏÙM­||¸g?1íÆÓ0°SÓLÉ¾Ñ\\tØn;õÔ­*Ó´Èÿú© ôÐG?f:¹Lûï´ßÝþúdsA¿Ptª­Ý²\\t».JT|lbÿ#üå´N%j#Å÷mùÿºpòrõ}à¥á,\\bÕ{Òso¡¥x\\rkdÀ?üóþµSW'ìs]3y«² ¹\\n\\nÎýv8Q}q­!mü3ªeh PQðJl¤uîvØ:bYÂÀV0.¸hÍX*#íóÚÀw*êlÅöÇ¹«ã¦íûdË$í% Oô:.ù§#Ü+_}à¿±|½{%Y7\\r×YU\\n)ÊÚ?7Üïî$`=óGAñ3[zÉÿHVî©¿a¹U:4ÆPÀßîµmbÇeªAtr!7è ìayõWÙZyÀ­)Ï¶ËÌ«vÄüÄRk¶Om¸Î4vCßÀ2*Çiê§ 3øÇ/¼ºiíCZN5Ud°"ùó{)_ðV-{ÄöVx<¯ûí}èPÏÀÜ<HmÿÁS+HQzFÄô3V°^âT´ÞUJ%0YkPKÎ¼ô¦+©\\nïÍuÉz\\rñ%fóG)nü»c_qÖ§ÈEÚV³§Z¨8±3ú0Ú;Û<BFÈëùÓÍÜYáô6õ\\n)·.ûz«nõØpmÞ}m-ú1Q+¬àTü\\f@Ù7ú¦{ò§¢a²Å±T¿ó»K=ÑÊË$!éÈP~+x6A\\b|=ª×LãÆ~{+?6â Óc\èr²PÕGùÅêCÆcìg-´V«Ï_f±·³qÅ ]Ñóû½\'£kPÖ(·W@à;²è\\nä÷BSÆä¢¯_²S#`b}þº}\\rn^éxHo¶ÝIÛsM]6O©jc±pÓJ\\r°pÍ%Î8"jÒÀ¤#£H§ùòD\\n¹õ=<rËº>^ï+_fßÃ÷l_¶òö°W­W®(7Ë²9Ý*^ñ]¸5gÑü*"}r«å´µ7ÉeöÈboi2¾&LÃª!ÝyÄ¹>¯%Ým¶\\f1åÙü»¥EÒLÑº\\naWÜÞ*ù2·¯Ûú ù¯µ±ªë<UD2Õ/ z|]ÓÍ2ô®MU!ìâ'N °S¬ka]ÅT×H{fRe +¸Ó¿DXúÄ\\f\\fw±ae=¢¸<ïÙö­éøguÿ¶{Eµ]¦}©6,¹ñðD"ÕÅAEÛ+è\\t\\tÑ=Æ9¨Ê#NC¸}mC¦>¸Ò«IÁ_¤¢tå££¾Y)ã{^nzzæ-\\rÀeµ:1ôûx 1]MK}2ö~ýVÐ¿\\fF8:ýÈ@¶O¦sÐ³Â×¬\\bO¢àÃZ" "ûkºÛ¥!1SM$cØækø^è,¾É(\\t(àEýYpý¯aßþA'òÁäØ:ÌLîãÆ.yÀMõkD0±ÇzA¶ÃøJ7'õflo^"1k}õïò{tgh&}F\\bZüÜvYíÃÊÅ²¿3hyá7¶cKñ·rËÏá°8þ´MU8×j¸¢øXH©»°2\\bqGÁ?hÁÔ¹WAËUCgßVÅW®\\tâº o,Ý¿ª®À\\nrÐõÎwê/ÓÓMÒ,ûI{°{}[Éü0m) mN$ETVÂkÍ®B\\tû´HáFõÙ$XÇßìt{Ó"ùÅ-ó¦\\nöEÙ%lè6á{åNt®8MfúZ÷rx P,S¢:uzúxLÙÈ­CO«Ö·|H¥'ðçØ`JðIKúgHd÷XÂ/,òVÃPþÔ\\nÅíÏóàe \\rÇ@(_°ÿ4­¿<o]7«mD¦¼Û\\ráR¼ÑÄ\\r7Àùcá£Xa÷²DÇº&*óßÅ;OØ3¥éìJ(sd ËÏ¸l«çBÇjÜøêëf]¼8/@èÎ*¾òïd´óöxmLS"õheä÷±!{¿²SL¼ÿf%9»`; 6á$ÓD_]';i+ê·3ÑTo&9sN]QÈ£0Noæf¸ äþÅ\\\féyp¢ûuÌy#X±«ª91±ã¼ßÉ(]2xÅ\\rBf9.54r³4î\\nøQ{e[Ã¤ÉÀS3ùÌh» º¥[\\bo\\bþÂ¥ÁR5ß@ ¬î¯`GØ~PzX¯ß<vé¸Þ&WL2Mîøy¤¬>0üóÎ°Ö`U¨R»>(Ö9ã¼íhh¢$é á¡Õ·ÌqIWëz{ÈÌAkéµ¿G«×d¼ÙÉ-i¬âÉ_á/71ül^Wã2kæÍñSÏ½+ÄD Oèóê ªW²B] ÂÒl7½ÌÁ°ÖUD¬D\\f®zµÖ+ °/ÄB.p»2^Ò\\nþ!þ¤ç{QÑY¬zèÌú6íbÔÛt¢qÐ6HB&NiD¶>¢ÈÂC}ïéÕ¥_Óel< \\nAçCÔEÒnÙ$[6\\t6U:Ñ$ÇÌ!ãö}L^¹Ðcì@£¬SÐÄµólñòÍûC/Jõòsq×ëïª.%).:yÍF{Ed_Óõg\\rsm]×k^{-Ýêñ,¬1³:Ý·+ 1^`Å+xºó?;8Ík¬BgÏ¿¨89y\\bòwÑ¦\\tñº÷ªÕÂuFªDDïÚ¿\\fntV0-!}ÊYO\\bÃHn¯y^D«ÅòTwb!O+¾×gÑë£¬¸yq£r4ù°å;üÎâVÑt×ÍylO¨/Ij ä.ÂÊæø÷zpY1ðª¦¢¯¯Bé¥6EH½ö{YÌ+j-Ñz®´)EZ©KÕ\\f`U0lÜIû\\bÄ#ÄFEr+ßó=ÆTes·®ÐtÒ°Øé4éW¼ÎÐ©oØyêõÄÖº×¿sFÓØÚõÊ¹~ÙBácôôÆà¯Ñr\ÿ«¬3ÔÿMsúPJg2i\\f¶òÁÆG½iè/Å$þ§:O¹(©7ÎÈ­´ÊH½2ËN×Í­@Oç·/uåytø¶¶qß\\f¬ñ7ÄR{þ\(¦cméû%-s­§;ÅO¡X¼ÄÁÔã¿¹÷cÃ­áN.iq8¡,:°¿SÁuË\\nûèÁz{È]vø\\t)RÛ " àµMLq½ûÄæ¡Âå-h¿ ß¼ã5Ï×jdc\àá¹ÃUL8­-­ª©Ñ©æ&ø²ôêÖF.Î¡ \\ne&\=Y¸öfxô$L~ ëÏî2;äÅ«ËZSA}ýÄâéwÔ7:XØ"gÇ/ñ>Vù_ò¦âè¯;úæÉc.÷´Êì³Ï4¬n³\\tÛ.»í5´£¼Á)±½Ô$\\reÝª1þòJí§¬ûÁâé¶´vüä5Ãe­®Û5"YyæíCîv-¦j>£+ÒÈøu¿$±ûCL Í ôyöÁÉiD+(ì÷îà)Ç£yoì~²¼½@ªáëù,å<,õ`òc¬½»R¡;©³\\f1;¿ý:=S¬pÿîÞë\\bBØçïë¦¥£=é·G||)ª\é<\\nÕP(«zs_É7KáÂ×ÜØT·Ñåï¼V¼Õmà÷Ö´\\tXl^Å¹÷µ'ïÇ.}0\ÝÓ.ïjOCñ|¦ü» ,ôbw®U!`[.#J¢}·G]ñç¤"YÎ+ß:@5OZ*®kÊ-î3t¯[ÜeíX¹røcz¶ZÇô­:Ï²Ma«ªú3FDðXîT´Hù¨`7KÎµûwÉwi§u9ÓEbYd&\\n9â®Ù_\\b/&N\\f"QÅHçWèõýÎ×íKuÂ5)ÓNÀ(î=\\b©UHi§sõOÅ£÷èÀÝBÜÁPxIJL^eÌ.ý¥ÑÒT+¢SÁÂ½jTC3Àù&Òá'Qv±V)Ú¾&´ÖX²k4)qc¤ßu?t'´àøÜÿõ¯ÖËèÔãVógá6²êÂ×ê1`­âY|z|tßÞêB³yyÈ%|y/LûÛÜ9â!2D«ò.O1U¼¯Ø`Ç,Æ±\\rÁmpkaó¢ Éá³aëá/wþ,Ve)t¿áv»²;´Ó{*!¨iQQh8\\fF ;\\nêPôcY\\tCøÇxbçå\\n0ß.?_`À70ü­ïZØ´®(ä¢`DÝ\\r)b«ELãëlKÉiâ|ÔVÖö´cf¹¼?Å)aªNq¼õ¬È<Ìý´Ýÿïx<î´Ùú¹ÊzmôÖi\\tâ\\rWrÛ»à­?TÏÙ\\n[±mF^Å£_\\f 1ý]yóqdÑçZ:»"¼Ï*ãZ~Êdºst¢.ÈÜçnST@ ÑÇT¶SHaovpë3!74ªÄÈý8¦kãõòÏ3µ@·N Ù?¤¶XÎ9ÂC¼\\f;VráóßëExÙ³ Hç, ÚÊ80qGÞ¸{"y)«<,2¤=57`ìØ«SpÊrVåÂ­5òe ÓÙ¿x(ÿ2í1#y«Æéü^Ù}¢\\b8þ¢|¯e¨ÏRÔ_ÂS`ïmK§Æ}B#°2»\\nì\\t@;1`-¡#w@Î´áf¦´Ý\\reö$ÂÑ.ë¹R»þ³×åc«Ë\\n({6êµ 8»ú¹É®ñG.pE{º×3M5´5.µí(­I¿ì;.Êw>70Ha^ïf²`´ASA&ÝÈ'åÙÄ®~- 2°Â\\toüj±ÀJ²Ã©sg$Ê´ôT\\bÒè"ß<©0ëlEù´ºçt\Ë6ë'%î>õÂZµ78ÖÏÖ^\\tzs¥mK¤Ü¸zcwx$6OÁnÆâ+6 Û¾»þ\\fäHÇÕJàß7ë{ææ\\\bFF0ït\\nÞ­ê*áKÿ$vf\sD´å*m)¿X8ýÌüU<c!û\\rj cRùKùÞ»ú Ø¹HB+ÝÀ¡Ó?È_Æ_íÁzrè}Öp/ÄÒ¸bap|7Õ\\f¥7×qkbèÜwÞ¼[G5(õÜQ53ßÔÝ\\rÁ\\bÞ¼£$Å&É·T×Nà\\fÝ,0¹ñðÎå:,ÁD×k8ô"¡ç«\\r.eýkLÙumÑ+góD£¤]®'q£b¹×~b>{ow^\\fµ"Câ+´Üú»ÎH~ü3äN¬`kt¶´v¹Hb+m×\\n_9*XàòÉYtö;õ­cîiÀ§ùå×"ßÒø¶óÐ&B,E£G²IgLÞ"¢\÷¬åKÞt\\b¥ÝÈ³{îÜ<,\\fÇþ}í¢eåw"ýTÇUùIýEW{Uð¨6J°o{ÓüA\\n³ÆBÛôRó#AàVäïAûÐ;r3ò'7rw~ðsåv:[§ÌÜÅX<ÊÎåÉI·á¤ÝÅm@#!dDÁÎø]¶ÚÙÎ*1pÀáô(L\\b*!ò4ð!%;ïâØÇQcéIjÈrÔn­ù&[¹\\tÆSLKCç:ÑqÑ¥%Èú_Ó§mÒA§1Ds&¥æp/*þå8SÿÓD}±\"øø×Á¯=:ùWù½?·`Ïsµ>ïRû\\r¤$±u&G¶)þ \\tQÐLÕ­M|.ú>&L¾eéC\\tûÊ³Iô®Üúõe!rE|øï"\\tò²RÕ8¢©@lÍ÷YP\\t,#E7 ]Û¿$:<,úH:ôgÇì,5RlöÁ~gÏ¾êGíX½pÛ` 7ï(r9{à%Ó'p ä)ÜÙäJWÙAFK7Îâþä õ¥`e ºF\\núõ©^¹d"úS0T¬sÍÊ5ì°¼Ú&aZc6jÛ#¯$"«Æ]ØÝÛ}> Óä\\töÒ­*"ø+åÑdïÊ±ñ§Ì¬ç±lH«ÑeË»ÙY"-Nà{qÛìY¢>(^ÁU_$+;Ê@nÒ^æÞ'­s\\tÜûØ¦?)]à¾x\\n¸oÊÀýàªãà¯³\\n¹"B­NVA^gD­Ç*ó*ÆEû-è,ÇU1dYnOE*ePnpÔ{I:s*l\\fÐ^ÓWX-\\t¿,úê0¨Ý'tL8ú\\rlÝðé):o'{HHN®J}yzô»ãÀ c®síTþ±\\ttMuCV ¹ÚuÞaxÈc¸°òhV´Â^çÅ¢+Nó¸¬Ð,/ú<vãÿ;Wvg¿xt\\rx7 ~BuþjÄH4+<ÇqxJûk4¤© düA­cÖÚS»Uh¸kØ¤g)Î+±·{2ÃOä#,]d×Íe«J«¨ëVÙuCk©Ì²$+vw3vÚpÕ_Û#ÃôÃ`Ô3ïu­F^úÞðå6a÷uSkgAyN0Æ9¨7OøÏÃÎîæäP¾Ïôá<´+­áè!"TI=ìÏr«ú¸Ûª;ÂÜ©oÌyØ î7»é@X~e×1µ ìMEK¸«ë¨½?åÿà÷~tza=.ÕWúÒ?]¬3ØOmÑ[7»f u=WÛ`\çu.Ý!(Ãº2b:ÿ@C?à«Á¤ñ6N<OÏ.6ÄåÃ«%Ëæí^d<U.y\\fé$§"âæïS+^Æ÷Þ9'Ì&oå§=¤®«£®¤k¨i¬²ÅætPì\\f£G¸Ð!¡æ]ïN"S±[Y]øs"&ëö9=c ¤=ÈqágãÌÕðwã>·ÐgmÑ5ÍYdêá«iÚD¡M|KT­½Õ**¦¿9H2{=ð\\f²Òùð=ømÚ\\t%"§÷´P¼;¦ý¶hÇy·SC]7Ôr[Ùv¹Óhvy(´ÈEì$kÐôõQ¾ ³ù"ÆRªm;Ë©<ò+ñªbýVVvr°Z Ö~ÚVt¦1ëVÕ£Jéc·&Bh©Q!«cÉ^çb£Ñ¼ßÓ\\bRÕµ!½þºýÀ|ãB@Åp´¶§êÔú÷mCÓpÁ,Á}I[;Ðí$QXQû©|ç|¢3e÷ÄH&ÌY?uzWïo5V3ßÝÕK~g·öÂÇíÞª$ôz·1o$¬ÿÌà,~YT¥B øpÄÊ! 4âdy°2KÆÃÙ\\bÜ^§J<ø³SÂ:Ýå¸ÉCÄwÒ`ZÎO78ðôâêèmD±öªÙ>¬¶¡Qn·0tWÃ©©úËgz0vÀ]~a'îï6ó»üá°o¨ükLuJ9×OõRÂ$ÐÎ¡M¡C ,¯q£0EvÅÞªÝÀH>¹­e¸üñA î1à±Æ&ytFQ^µ"%bÆÁ~ÂÎÅçÎácæ²LNN·>¼¾]t]óÇØ3kÔßè}e¤×,Û©¨ç×É`u¥\\f£7ÕÖg(ï×Ó.±1\\tÐâ²3t°o¹`VÍvP×ÏËBñ\\fúCU 'HøX<~Û:ßuÉÉmcMóµxýù¨ÂG £§1uçàËÆ¡Ðx^DCBÝá1§ó¦*çÖ«7(ëáy5æ§)b)\\rüù\\n¨¤#Hrrq«¥äÎ·Á8úÝTüÖP7#.íæ_óêKÃSWfh%Ö]Ü<Ê-Þ¡ý6©]kØMÈáå¨Ô"ü³éþDôbe\\t®A¦IÞ'D´ë¾f½<ÄCp©[µ®+úÆ\\t%ibñM:¢ÀîôÅÕïï]XÞDM±tøØ.Î«'S¹YÉ>Ï®Sì©ßlÈê?f"n[Öê£æ³ÎÃ±^Wg+äoò\\b-×¨¤$Âröc¼L ð6RÚR\\fÅûå0q££+Þ{ðà6´N*¶ ;üp)rÊ,´®ÉJdJÕÅ·½´¹ñ>Ü¥,Â`zOïö)êù'þÒ4{\ê6a\*!êØ4ÔFM}ùxSOaÒaèDVd*«Î½ÍG)N±ÄwIÃírmE¡M¶=Â~¡é5(\\n±â¬v×pÏWx(³PRÉ¢Ô{DtêÔo_Ñù?`³È±pQÃ×îbÑòÑ!~%éãÌî§ÄÄ§ñ.öÃöÈ çÚ\\r×?£9Ë.î]OlÙÉRà\\r{%púÜæ ¤×ÂÝ®9úëÖZj]5¯Ü8.ñáþ²'vÇ¦¤}¢ìÓF º¢¨)PiÎíàETSWi/×¿_&dü§àOÖà&ñë¶pÕý2®\Ö§ö³ø>ø£\\r:óZÊÑ(³Ø¾ÑîÆ>!ÖuûÊü0¸|¹Ù ]©ZR¼4{ðuþK\\rÅ A¸¥ã]È\\rH¸Q\\fN,QO-ã%iúÕÇH3õÞ@J`øò;¹¢(Ü0c]×å'lUòÌ$¥¼Ä0#tøm&\\n=&g1­ø(:Á;¢çÆ" ÀdÞ¶ÛMþÍlhfàþ½Ùcäyn´ð»ùñæýìv¡:ÓèôòðTù842ºÑ"û\­´:I­ôôKÒOc\\rQ´S8úf$¾ÑÚæ5qçk½ I\\nît«Ôh³ÒnkJõî^ª2ÃXÈÄ(æ¦ $³í}­*ÌB³´'P[:6K+§èoG=»Ð¹­ûR°&bÎß¢txR7 ¢W\\nÞ2åcñ¿Êó61áò+gÌ÷*·N@b£ë~vªD÷Ã.I®ù  ó&±& ©ÎkËÜJdëã6KLsDéìò©ó¹\\b0­eO=#)N]e¥êaúìÊU)0T³w'½JOýÿÇLC&"£FºÌHøìõ\¬<ÎëüTÿ´¨uµÿt§,+}TS\\b.âàú7ªNðá(?´ÌÜU1<\\nj=ex±ewí6ÏZTßÏÙPEÔ\\nbÞÝÚÆq7£Þ°{GR½áNùÚäz°ø·ò§ëi}, ñ­kyJõ_13èzÖ\\nËÃMÁ÷rM¥L]4pºUü­:u!=T³ÃéC³B4þi/A'Ô*oYz/ÚU-'-Æ1iÕtDØ¶±Q!ãæCÖzÇn7ðJi«_àó\\rihÁ)ZêK²áÌ÷´çö´ûèL` Kz Pèô9rÞawï¬ ¸1¡<_¸~H;,i¥FÕfe*í1Ò²ÐbÏ´íh9dñá|päa3.ÞôC:U£?\\b\\ba|kËKyâEýêE¤kIÁbÔmZ{\\t·^SiLî¯Um\\b68MTÞ5NNY`§â)o]%úxr¦ÇUFoäøT}Ú7ëFZ${6üZÁb¤ÓU)$Ç\\t^%ÌmnTôe4·í{=¿ì8-°\\rVßèad¢Ü2É|+8!Qú¯ÛS¿<á²w\\n£][«qXÝ¹ø¨ÀuáÝ-b[¤tx$½ø®¶mõ\\f.Æ>\\rÄ¾èÿQ¿¾ÄBù¡ìày§¡á^Ñ½pÓKpHc%e¤ÁG®G©ðeÿ\\ný;ÈmÙ>Ñ7æÐXÖqè-*BIÐ¹¤å3ÇSÙý¾}7H4õå 6\\tö¿{$¾/õRÅ <BÚwSj;Ôÿÿ_>S8¬FE~9fÆ§èÎ4n]WPAîQ_ì@¨ÒyãéE¥Z)åh65ÌD®PÀuEÔpßÍY\\føÑ£åþXZ'2`w~g¾Ó\\nr{nuÛ÷«¢¨ßÔÄ)%ó¸AèçÇE¢ÄXhÜH-zúnÝý7£õÎ!mLm_^4e÷ì¨\\t§j~\¦âÏªoÐ\\f®!Ô¡âù` ÆHçøÝ÷8 ÓúnºC~fù±ëê(~Ä366sºÃ¢³g\\tÊñØë8Ár&ÃI¼In¹æ)ö×LCKÈÄÜ;¸û01n3ÒØ h1bpµÇ=Ù·ù¿óõÐÍ©`Î2¶ÉU_É«<Zjdµ6<íûabñn¾çf÷çäÔ\\t¹Ä8*Þæ@Þ)V^Í»OÜBÓ×>úAË_\\t>DoÏÃ<ï­Î\\rßâ}>µ/ñ^¸×üQþûµl9t0ïÞl£\¿qF_¹#\\nÕß<hKgOáiÛAºc\V::½]-Ä&Á6G.^Ú«ýwçòçx5¦#}.ÿ±\eáoF!{\\bY3béôk")â2]îÄ-ÐÕå¸nÓ.-ú#Ö8²D¹FÞ\LSyÅÑmKæ[4ØLÏILPW/)4ýâ¶ÞR¶#·¬~¸]®®+áËÛÕÆ¸ÄkÂÛ«âã¥ñµ1øÁè§W-^1d¾»æ>´Ì(_\\rú÷£ñJ©²P-ßZ¸c%H(b@ÒjËè |xrh[é´dªó$yþ>2[ßÂöW_LE£~ìFfçOx7'§ÌßìqÀ1ùÜTE!óùdTéÒý<f¥¥ÈÔ!×Ï{Nq2=ÉP*~)¨¨½âñ{÷âÑ·#Zp;ÎÊ£ÓbÌÜÿÒÙµºÁ¸½Ùæ)(Ç`OéËïQá|Íò:ÒrÆ¸´<nY©¸²Ý,&}ÍÜp¥%û¯YONØkRzðÌ;ÿ¿¢Cf=à¼øçº²kÙÌ¤©ÊÂ8íûä<q5fØGGªDS±ÆÈ,A8äÒ8C«ÿü\E$1ÂT]|jÊ²ÍÒrÎÅÿ?S7i\W¾ÝÜ0<!bÅº\WïÎån÷FÖ\\t\\tYC¦½xò§n§sÐxkPÛÄCQÇCß\\rZwrbX+Þ{uzÄX|o(Û¢hö¾¸äÕ'ºÎ»O3w¤ãNÍÈøx¶ *®!g·Ç4Ð±ôÍåV2uË9Õ1·û±Ù¼\\fDvÕI68g»þø:~[r¶XÜ×ß@¾DUovó\mÃ³ø|¥¨îø±wrm^@59¬ÇôÚ»ík¢×fyºÖ´¥Õ£Oâ%È%a¤7e+qUà®J,Øõb¹c°þÕÞfHI%Í~çi¸ÖÏ²xòe³ðîhÌ*«_ÚÄJÕ<WÌ=>¼×Ô¥;Çe&­¬¤4.ÁBòdèß+Ì4qBg`z,w/ÿ/p^l\\bhoÐ¸®¤÷VE¸o¨ >­üÂilh,çUfáfm;\\rÌ"½º ×(OÈ¸x¾Ì§!\\r¼\\r½_æ!´ÝæýË\\tu|­Zâ,êÕÍ FúÛnÆ$5ß ËÞÑÜÎ÷|t Ùû(&y9¦|q-ûÑ6­÷×4\Øò;õçÄ®¬Ô]l¦%v]ZWVûÀö 81hI¦l.ixVÞê­aÓë]åù[%é¼wË)i_Ëó× ñ4vc¤ïWí]<Ø3Ë´|\\fFð÷éärãÔYÁ¶V ö¨HåR9æLvµyÔ¦Nòw\\nßéÊ×Aû¡M@î{¶ÜÒpOÑj¨#SÆÖ5|×ï©lÏóUäòÎ\\r'ö.5îàæÐÂ]:'ôäÿ^zÒcDÎØ¦^¬R#LR ln¼Û~´qi·"oòUòÛôBUÙ@nZÚ*×yFI§­ëg\ã+Hm¡¬I®[+´\Ó³M`8bÛËq¬ÄÖªðcyoÑÁZ¬aZ÷Fµg¢êÌ« ¡%ý*v1CÃÊk¿Å(É<§6åh¾¶ò~iÍp9Õ¼R©1QÌ°¡í­T.,¿ËÊüÁ=:Õ`¿JØÈõÛè²Ê~á8¬a¯¤9±G.­@ÓçºËÙÓ·Vx8Âeµ·Ïøî]xXL =ÅóT¹cÆgáFôe\\f!A9wÚð'ÃNÏãe7¨z"2­êr|» â\\rA=¾~cù2ÆTØ0«c¢³O¾`q2Ìb]§Wí|RµxÏ]ku"÷ÇRb:uA³ê] eZ¡wï\\r²]x4tã©À¯í~®qßv¬Å¨ÙÝ©²-\\bÚ3Êð}Z-\\nq]3gWÚÙÿAgýÖ¿ræp!-nÜÃ>µ1¿:ïó}úé; Áu0Bq.ùµ\\t<V&_ù9(Ã]gCk1\\t­ÕÎWéxÔ]Æ1yE»räo%D|Ma¸àeBb:?\\bçVâlM9W,þ´^ÏÚ$Oû]#vMz1ßº|L;?þ ·z9é¨Z$½#-ß[ïP¨ %Y>`,qvö|®sIöÛæç5;*³3¢ûÏ:&¹ÿ2É¥Eç|Rµ6I2K.Í{¨5f¹ Q¹ùû\\nÈpÁ¸5HXÎå =¥ÏçÆ^9D£@P,ÃNÜiW&â¡¢èñßù*Åóbë)ø÷ ÜÙ>7ýP±H[<Ø¶7ílÊMë²ÎKIú1²Ë!dôüÃ ¯(Ñ¡À¤âì\eÑø ßº»bU½Éï1pÉ@« %?]Ðé  »ÿ  Û\\f]ÊÂ¤%¸¶éÔ¡µ\fîüÌgÃe7[÷;ø ç(óä$<QçðÁ¦x5+õx*åu&X©heÛ>} ¾¤/j|B¢}~º>oïÞá¢`g\j¶¾Æ{ûps0b\\\rÛú-uhñù¯QúSdëzXà¿x×¢Éu.B!-áçÊ#&%Wª}ÂÄôF4Küøe7þá÷\\rð´Ú%ÉqME±å¹<:__ÑEAe­D¤Kå×3KÓÃIÍ %`ó Mòb´G¬IôFÀ?:ü9,ÈöàÍ/É4÷9?åU~xùBL­ã#Åÿ&¥lq°Ü &ô?Xõ=ÑA­Ü#/øáåÖØúú¨Ú\\tÈgß#{ÏÞ\\nØ;½³$ïñ^Q«éUñLÅø~Jû\\nü}dØI¬Ooè a\\fõ¹IÁ÷¡á%fí-Ú²^=\\n´Ìè´{R\\t®W®\\f\\fãË\\reåùüï¨`UúÜÂ¯-¼WøVRE#(®¶°*lö.Äeçdñáð)Âà°e4ÀÃó!©±(F6ªN£{ÝÀ:Þ¤å\\b×¹'¾Ø(%ªü¿Ü`±blüá)èÁ×md%1©@àµvgd×zk*ÒF^WÅQè37ZéB__*Ñ¿ñÐ¹Ãâ&çÄÌûgR>wÈ]h°p=LÙßí(r:³àY¿<aZexnZ?mZÍåOëú$r7¾wÝ3gÊÃD¨Hr",æç{ø¸Vü¸¤QYóy/ÉG9àÀÉ>òScä)û7e3":+ £ÇÊVO?ôRºÄü*7¥Üy?\\tß«ÂµÚõû]STÖèÆ£¾ï&9z1þ<!þ%8ä!ã£è«Çro÷kTea¬¯@À³èßìzª8ýÆð¢*ÛÇà*\\n¾ýJ¼üiÍð%ó1rßÅ³:«\\fìF­ÜHß4ª_ñÐÆ¤¶PÙv§µ5YR?^lRj¨±9.Õ¿ö\\fÝðfm(2â÷ÈWno@óÆói\\t¯m¶·ÚÞúQ^:u+ üÜÀ×d¥èv¬Qò"b"òºñcÒvôåÊßát®+i\¥3¼Æ vs U#{¼^jÑEbe2ÝsÅØnù1Ò>ªnD3/ÀNc´4ÒÇc!Ð´4¯Í,ã\\\bv/Ô>©@MëL9­Û\\t\\tÝU¦O Þ¸X:cÑkå1©ülY`áµW5Å ö!Ã¾­Ï¼íUw\SYøoEûÉò1*ë:Â¯" u·pnVqÁ@`>PÁnE­øá-ÿÞXH1\\n´y¶Ê#Þ\\rxz¯&y*ó0NñÖØgð×²­¦g)iÌÞ¿ *>Äã^á?­¤?ØtÔ¦g*¢éÏ\\fàCZZG\\rzÉ*æøÚÇ¼_ðÕÒL²ïA\\tØv`%9 S=Ë Sõ(]Ú!éùxd*ÿ@|ä%?ðÈäub÷ý¦Ã@¡¥>ÕoV¶ õ[·Áýª×óÊÄ(§Ú±è²ùAK\\n"F1Â0J!÷B;:ê±Rwý­f@ï`9ËjëwÆârzs*¡[-$giIô¿Ç\Úïêß ð~O#Ôl ³ùújY\\nòÀ9<7G5µFçé·UÝ(î5¹SßÞ''¹\\bÁéÄo§É|Ç0ÅàÑv¸x¬bØ@y_Îÿa2Æèµô)vd8<ø\\b#fÜéY`¢ùç÷ÝOPOCaâf2(ßjdÙ<áûç£C.þAT»s|X²UÏ0Fèå"-§yògî1¦)»×ûý¦hë2ÁVAÐëÖWÄÄ-Ï?ú·Ãöÿ!ác`B×2ß¤\\rLòV¾\\n|&¼\\tÒÔ:UFüúáçð¾+Éã)½ýbCxCb¼Q¸áâÌÃ¶´j¡wõ[ÛàØÖÃLh:×ûM¥DFDÍÂÜ­vAêÚâØÆñÏÀÒ$k¥l[ÍjÞ¾ÐØ+§{hßÍ9PH# WÀÃÅäýÌå<<WÃu­¿KGjq/¾FHÂÊvÃF£U×Îx,¹Ø9râçS¾ráFòØnMêà¥]?Ä\\fg®|W;'£ÓbsS2äTÖFMß]vAÖÓ)lÛg\\fÑÃT)0ÉK øoº%Ò¾M©Dë-âü­Í_îVä0_ªpv¤ZéÅØR0&Øúv×*ñÝDmNcpµìk+Öâ8¤É³ ÷aUÁÐEDT2S\\rÔöäsëå$Þ:$¥É$Ø}Zæ»×¼«vÌâáÓ7ô6V¸}Æêõ4à«òÉ|Íji°ÑÏ£ÌçUI»éÈ*8¹3_ÅKÐÓðQìò¥£¡N¢;¶<&uÓAktÄ>\\tÍ½$xÉÔqFþW¡Ý£ÁN¯³F¯qG?µHÖ\\nê8xÁ\\n©Õ´ºxÔ¶»gCiÛÓnUi?·\\nö-æIãÄ<;õÌ\\fw?^ãµó./¹ÏòÉí¡úÞ!vd]Ù(p¿X¯+T_ÚÔ%÷ÝÞ±.é\+¥©¢Iûå"«$\\b&§ß&ObRGÛ@öÒsN8èÖKQwWèKä¢1g]~âUJ¹úËº`Ihó#ÿÂçMi­í^dïlkØ_ì8ÆÐVð{z[¢íMÞ5&\\fp£-O\\fÂúj-þ\\n»0 øþ,vPC£Ï}ó¨ ¸pÜ»EA±¦Z´#jb3¦_%\\b.8bU,Ü¹ÜDC;`´¦·þd?ärùÕdøÿD±¼xWJyWG×«§À%ü!¼Ã*¿\\ruÓPÈ>ûjêÓxr\Ôtl³úîÜ{r ôA§|éOªöëã$#øßîvuz_.!*ªþ;Ó§¨ÓêÒ¨*{Ðç\\r(,9³0´õî*`ú}´øm©ü¥!D|zI<.ïz ª'0:=ömO+ÿOºÿ%M©\\bÒ?áÍ°z2ÒVýä= ¶±ÕäÒºRh³vA*t¡;F­oæç×øuFjX$O#®/EÃ>G+þkW;\\næ_ç<9 [l¹Præ)õ¤~^\\r[}Õ8&«øôì»ÈAéó)^~ß/¶<Ðó¿º¹\\f..qè(÷Úÿ7¾&úÀ&'~TÖF\\r×^Ù#CÚ\\bÂÆo×ZHT¸Ì\\b«SÒ\\bgptKÜD!\\tü×§C[²ãv¨©ütäA©~»HìïÖ½ÞêOi2¹¤zm5¿ÁBÓ ]`y?mÒ²\\b{ÅTÅ`G³ÿD&'¬*dÃùBKþ@ôÅQ<È(ñOàÅ"[ÀZu>wå7 oÞYûëE@ ²òJF¦Obv±uÛéßúãg`»çÏ'LÁzï&\äPÁ·À¼7\\fSvûcy²ÜcN­a¾Ö°ÈÁËÉöcÖÇÊöÛ\\t:z  IDRkÝôìoÆ¶¼ÏkÙ:ñûÛ*Ê÷ÚÒl%2N6T@dË<þ3ë=ÿðvròÒ èÎ]i¥H!/¥Åt¤U\Ò´\\bRö+4FV\\t!b¶§sj;4ÖÕFðg,jlûEøléPZ=Êz°ÖJÕ¾}Õ.TêStøÒº±G»°EOöYPº2czTll¢Å­«Ü áD§{`Dµùbp^`qÀ¤}l"¾(ñ®þ¥ÿ.ÉMø=äß>ï¶mI±¤Ûä87ñ«b°8zïï#C(YgÚ9ÊD3_à\)þmÔdÓKT¦<\\rÀ(Qó1?^¥{d7¾;øÐFËïTbÆ©A$ïztÛ<juÑÃÄÃ­\\bÒ­á°µ©ô<àPí\\fæ\\r¾¼·¥x¹ö²R=Ñ<R{²§;äØ¡×­Á!@:£\Ø5\\nÖP4òBåda}Í£êÚ\\t8ä}â\\t?\\rý}×O÷\\b»Aô,g­¨³?tò7àX\\tÖX}KN¼máÌ¨¹òvàw©\\bQ3îÔJÜ_7ö^+Á\\n^Æ!c}Ç¡Ð)èfÉ (nï}q*.zºs~èHóR\\bèlo4»L Ã­ôP¿RèyR¯0<oý0^ b\\rÊSZèeËðc­\\nvÂé;;Ë\\fe¨úåôÄ­e¤9yÚwßµÆÌ\\nË±H.¸øÆÓôóæ®Ð^ÅC+ö³Oÿ2{ÿt©lkLÖ}T_ºä`Böù.I>²øãPÔcAå¶Úî<{~:Diñé÷xc?à¼8û¿T»ü¶e²~ÖÓ/*Ñ)×*¬|Î¸Ì+ê,\Ølo_ä@õ`El±ö[\\t7M±y\\bOiw°Î+ÍHøÄ %Õ^:Ú¢¢ãMàxjb\\rÿ?Û¥§¹°¤LåÛNSÃý»ØÆ³ç}q¾aë\\fÅxÍMP¨/K¬%Ëâ 4å]ç \\fz½ß{($n+F4îÕf4ýýÞ»-!eÈu¤ÆhÐQs¤¶A×uáhOoõå×}5Ù\\f¶Dü§!ÿèá{àÔÛÍ(ñ$l'5üÞÞ_`ú M·Ó{kMyDèUYÜ­£xÀð\\fàæC@ëôYò&U`®B¥ÅBYo¹^\\fS'CEÁ<ÆzÖG©3ïD|ËQlÂ=½#ìï¿=«"Ô.äO87øx\\n>3,¯QÞòOÿÛd!³ªos¼ðæA©g@DòÉ¡Wz\\rPO{µnÎÒ¨mitºw¯¨Òò§@¨ÑÖ,|&\\nwj4>M¸H)×y^¥d÷½;\\f!tfôò«tSÃ² àt_ÆeþÈ$ïÖQO·6G5ýX¥z¹ðñ°À_ú)|¹Ó³8µa}à'ÁXÂ½«á¾¯¼àJÃ*¡NQÐïtà0ÝL:®A¿N¯LÁ·ãÛunqúÑ«z>>=ÕNÇ®JKµ3y³é;ÌÇVÙe¯^ò¦º´r0¬\yÖþÒÎoªQ©\\f+æêôµßPë¨å7^èvÒJðè:¥SÄg9zBõw(¸Õ«eto1¿Ñ¬=;Þ»¦'*Ëñ~hÖºÆÖgbã: o¾ÖósTf¼e£;Ì7ÿYß¼NÝ¿éP §ùBü.íïGòuqí)U7Ò3­:ðÝsÒha&¹ÈywXIDé¤Ë@ßó²OûÑäÉîÇÂ¦îª23?¨¢cu±äz®¡+axÂ/æOFB:Ïô#«.öLð\6>ñµ0È¢ØïË¤üO÷îíÿ¡êdv°¬üÿ÷EzTöïí ÕRÒèz\\b·°[Ôð¤8DÙI"N¶Û\\rN\\b6X]FøT×¿®ÎÜX¸NÛûSU ËèÀÛgÉ»}\\næ\[­ÿ¯'9¡óRéUÐ²=BT§ø<·9$VWVØfÎ^Y©HY9±ddÁûü÷öäåÃ.SÙBUÞHµy>\\f=î\ë\\bW%óoF;ÛhØÏ377¨Ýêú'Qð¨môiV­P·\\fµð°Á)­  ¢æ¿N¸ÄhI°\\r(FUøÊ5pLÁÌ`ð@Gí¦OQ1³×,GA×ïÌÅALhaz»¬\\fÿ*ÔèGÓ%ctß;^vï3:(åN'0f¯GpÏ®ê+¬½wm&3WüRìÜ§·ÊH(Ì\\rÑi¶u\\n=½]ják-¾[dÎgåk×¤Ì}d~ÖÐ^y¦#¡·êmÝOjÆ¸/+DÊè7F,îdW6s{o(òk³5Yÿ§cÄc4å¢Ôqtu,\\r¦y áWæ2a2wædhüq@*ÞÜ,í2rövU+\¡¿Á=ÒÇ«¬RZ0Ø@ë<Výò¤bæ?{>5Õmq×îÎR9 + Lì«®Øë+Ô|{s÷ÍeqÔ>ëéYYR¸gë­1Õ»gî9÷³{g³eÿÓdï^Ý\\tQ4_dy¬spÄyo²HKoÂ\\nìq\\b¯3CvC@éJJµ\hkgÍ´'Èíµ4Ø3ý¯)Ë¢»é+é#åÉTòJ[ÙÝ¨TWoÜ-ÍZ|ÚZ|ñÉ%ßûÃzÓFõ¡äÈ®×KC7^åæJq/6Íl.PòìS-²u;Ñ]6{>¹ÿá¼\\tùPb3ÔôÉÎðã!ñ2Åd¤IVª¸bpØS\\t'Ì:+H°ò&\\b*Rü"n§ËÙ»wp|iH|T·ÍaÕÅ[õ*%|º¡­±úÛe:Lö¬$%:÷ÒÞT*µáµVîÆ5!mþKÞñ;Øµ"tÃãÕÎ-?,ó\\næ'@-÷j+n\\b·idU\\b!ÑÑýÝ)'Á0½®Çýó^íÆ*G/\CpçC8V©\\r2îã2ûFE9!¿g\\f0[äþîq&^|ú;ÊäIf+"¢­·\\fJ'&jgºáw`]ÔÌrÆJÕjERÀÞAZëã®tCêq¿6ÈZÆpêTç\\t¶ õ®³áLF×"«reX¦Õ¶qÊØ»ËÄèQBgªç»ýböÉq÷ªRæ»Ó\\r=ÅÌ°?ó.ð¬' ÷GCIàû&BÙMÐªe6¸¢ÂÐcÏ­D>°c/ðgG{ia©3ÐèK=5Ë¾"()ædª'b£Vò\\n#HòÈÖGÕ^+«ÉÑäD¨É»V^XoMý*»¾#}ç#¼Ç[¾^,{j>ûHq1áÔÀ¶.8Q¸ç¬ë>òóú!G'
    //   129: dup
    //   130: astore_2
    //   131: invokevirtual length : ()I
    //   134: istore #4
    //   136: sipush #32767
    //   139: istore_1
    //   140: iconst_m1
    //   141: istore_0
    //   142: bipush #60
    //   144: iinc #0, 1
    //   147: aload_2
    //   148: iload_0
    //   149: dup
    //   150: iload_1
    //   151: iadd
    //   152: invokevirtual substring : (II)Ljava/lang/String;
    //   155: iconst_1
    //   156: goto -> 203
    //   159: aload #5
    //   161: swap
    //   162: iload_3
    //   163: iinc #3, 1
    //   166: swap
    //   167: aastore
    //   168: iload_0
    //   169: iload_1
    //   170: iadd
    //   171: dup
    //   172: istore_0
    //   173: iload #4
    //   175: if_icmpge -> 187
    //   178: aload_2
    //   179: iload_0
    //   180: invokevirtual charAt : (I)C
    //   183: istore_1
    //   184: goto -> 142
    //   187: aload #5
    //   189: putstatic burp/Zti3.a : [Ljava/lang/String;
    //   192: bipush #10
    //   194: anewarray java/lang/String
    //   197: putstatic burp/Zti3.b : [Ljava/lang/String;
    //   200: goto -> 364
    //   203: dup_x2
    //   204: pop
    //   205: invokevirtual toCharArray : ()[C
    //   208: dup_x1
    //   209: arraylength
    //   210: dup_x2
    //   211: pop
    //   212: iconst_0
    //   213: istore #6
    //   215: dup2_x1
    //   216: pop2
    //   217: dup_x2
    //   218: iconst_1
    //   219: if_icmpgt -> 320
    //   222: dup2
    //   223: swap
    //   224: iload #6
    //   226: dup2_x1
    //   227: caload
    //   228: swap
    //   229: iload #6
    //   231: bipush #7
    //   233: irem
    //   234: tableswitch default -> 302, 0 -> 272, 1 -> 277, 2 -> 282, 3 -> 287, 4 -> 292, 5 -> 297
    //   272: bipush #74
    //   274: goto -> 304
    //   277: bipush #32
    //   279: goto -> 304
    //   282: bipush #70
    //   284: goto -> 304
    //   287: bipush #30
    //   289: goto -> 304
    //   292: bipush #77
    //   294: goto -> 304
    //   297: bipush #88
    //   299: goto -> 304
    //   302: bipush #9
    //   304: ixor
    //   305: ixor
    //   306: i2c
    //   307: castore
    //   308: iinc #6, 1
    //   311: dup
    //   312: ifne -> 320
    //   315: dup2
    //   316: dup_x1
    //   317: goto -> 226
    //   320: dup2_x1
    //   321: pop2
    //   322: dup_x2
    //   323: iload #6
    //   325: if_icmpgt -> 222
    //   328: pop
    //   329: new java/lang/String
    //   332: dup_x1
    //   333: swap
    //   334: invokespecial <init> : ([C)V
    //   337: invokevirtual intern : ()Ljava/lang/String;
    //   340: swap
    //   341: pop
    //   342: swap
    //   343: tableswitch default -> 40, 0 -> 99, 1 -> 159
    //   364: sipush #-479
    //   367: sipush #-5895
    //   370: invokestatic a : (II)Ljava/lang/String;
    //   373: putstatic burp/Zti3.ZU : Ljava/lang/String;
    //   376: getstatic burp/Zti3.ZU : Ljava/lang/String;
    //   379: sipush #-467
    //   382: sipush #13267
    //   385: invokestatic a : (II)Ljava/lang/String;
    //   388: <illegal opcode> makeConcatWithConstants : (Ljava/lang/String;Ljava/lang/String;)Ljava/lang/String;
    //   393: putstatic burp/Zti3.ZU : Ljava/lang/String;
    //   396: new java/math/BigInteger
    //   399: dup
    //   400: sipush #-465
    //   403: sipush #27158
    //   406: invokestatic a : (II)Ljava/lang/String;
    //   409: invokespecial <init> : (Ljava/lang/String;)V
    //   412: putstatic burp/Zti3.ZW : Ljava/lang/Object;
    //   415: return
  }
  
  private static Throwable a(Throwable paramThrowable) {
    return paramThrowable;
  }
  
  private static String a(int paramInt1, int paramInt2) {
    int i = (paramInt1 ^ 0xFFFFFE28) & 0xFFFF;
    if (b[i] == null) {
      char[] arrayOfChar = a[i].toCharArray();
      switch (arrayOfChar[0] & 0xFF) {
        case 0:
        
        case 1:
        
        case 2:
        
        case 3:
        
        case 4:
        
        case 5:
        
        case 6:
        
        case 7:
        
        case 8:
        
        case 9:
        
        case 10:
        
        case 11:
        
        case 12:
        
        case 13:
        
        case 14:
        
        case 15:
        
        case 16:
        
        case 17:
        
        case 18:
        
        case 19:
        
        case 20:
        
        case 21:
        
        case 22:
        
        case 23:
        
        case 24:
        
        case 25:
        
        case 26:
        
        case 27:
        
        case 28:
        
        case 29:
        
        case 30:
        
        case 31:
        
        case 32:
        
        case 33:
        
        case 34:
        
        case 35:
        
        case 36:
        
        case 37:
        
        case 38:
        
        case 39:
        
        case 40:
        
        case 41:
        
        case 42:
        
        case 43:
        
        case 44:
        
        case 45:
        
        case 46:
        
        case 47:
        
        case 48:
        
        case 49:
        
        case 50:
        
        case 51:
        
        case 52:
        
        case 53:
        
        case 54:
        
        case 55:
        
        case 56:
        
        case 57:
        
        case 58:
        
        case 59:
        
        case 60:
        
        case 61:
        
        case 62:
        
        case 63:
        
        case 64:
        
        case 65:
        
        case 66:
        
        case 67:
        
        case 68:
        
        case 69:
        
        case 70:
        
        case 71:
        
        case 72:
        
        case 73:
        
        case 74:
        
        case 75:
        
        case 76:
        
        case 77:
        
        case 78:
        
        case 79:
        
        case 80:
        
        case 81:
        
        case 82:
        
        case 83:
        
        case 84:
        
        case 85:
        
        case 86:
        
        case 87:
        
        case 88:
        
        case 89:
        
        case 90:
        
        case 91:
        
        case 92:
        
        case 93:
        
        case 94:
        
        case 95:
        
        case 96:
        
        case 97:
        
        case 98:
        
        case 99:
        
        case 100:
        
        case 101:
        
        case 102:
        
        case 103:
        
        case 104:
        
        case 105:
        
        case 106:
        
        case 107:
        
        case 108:
        
        case 109:
        
        case 110:
        
        case 111:
        
        case 112:
        
        case 113:
        
        case 114:
        
        case 115:
        
        case 116:
        
        case 117:
        
        case 118:
        
        case 119:
        
        case 120:
        
        case 121:
        
        case 122:
        
        case 123:
        
        case 124:
        
        case 125:
        
        case 126:
        
        case 127:
        
        case 128:
        
        case 129:
        
        case 130:
        
        case 131:
        
        case 132:
        
        case 133:
        
        case 134:
        
        case 135:
        
        case 136:
        
        case 137:
        
        case 138:
        
        case 139:
        
        case 140:
        
        case 141:
        
        case 142:
        
        case 143:
        
        case 144:
        
        case 145:
        
        case 146:
        
        case 147:
        
        case 148:
        
        case 149:
        
        case 150:
        
        case 151:
        
        case 152:
        
        case 153:
        
        case 154:
        
        case 155:
        
        case 156:
        
        case 157:
        
        case 158:
        
        case 159:
        
        case 160:
        
        case 161:
        
        case 162:
        
        case 163:
        
        case 164:
        
        case 165:
        
        case 166:
        
        case 167:
        
        case 168:
        
        case 169:
        
        case 170:
        
        case 171:
        
        case 172:
        
        case 173:
        
        case 174:
        
        case 175:
        
        case 176:
        
        case 177:
        
        case 178:
        
        case 179:
        
        case 180:
        
        case 181:
        
        case 182:
        
        case 183:
        
        case 184:
        
        case 185:
        
        case 186:
        
        case 187:
        
        case 188:
        
        case 189:
        
        case 190:
        
        case 191:
        
        case 192:
        
        case 193:
        
        case 194:
        
        case 195:
        
        case 196:
        
        case 197:
        
        case 198:
        
        case 199:
        
        case 200:
        
        case 201:
        
        case 202:
        
        case 203:
        
        case 204:
        
        case 205:
        
        case 206:
        
        case 207:
        
        case 208:
        
        case 209:
        
        case 210:
        
        case 211:
        
        case 212:
        
        case 213:
        
        case 214:
        
        case 215:
        
        case 216:
        
        case 217:
        
        case 218:
        
        case 219:
        
        case 220:
        
        case 221:
        
        case 222:
        
        case 223:
        
        case 224:
        
        case 225:
        
        case 226:
        
        case 227:
        
        case 228:
        
        case 229:
        
        case 230:
        
        case 231:
        
        case 232:
        
        case 233:
        
        case 234:
        
        case 235:
        
        case 236:
        
        case 237:
        
        case 238:
        
        case 239:
        
        case 240:
        
        case 241:
        
        case 242:
        
        case 243:
        
        case 244:
        
        case 245:
        
        case 246:
        
        case 247:
        
        case 248:
        
        case 249:
        
        case 250:
        
        case 251:
        
        case 252:
        
        case 253:
        
        case 254:
        
        default:
          break;
      } 
      char c = 'ñ';
      int j = (paramInt2 & 0xFF) - c;
      if (j < 0)
        j += 256; 
      int k = ((paramInt2 & 0xFFFF) >>> 8) - c;
      if (k < 0)
        k += 256; 
      for (byte b = 0; b < arrayOfChar.length; b++) {
        int m = b % 2;
        if (m == 0) {
          arrayOfChar[b] = (char)(arrayOfChar[b] ^ j);
          j = ((j >>> 3 | j << 5) ^ arrayOfChar[b]) & 0xFF;
        } else {
          arrayOfChar[b] = (char)(arrayOfChar[b] ^ k);
          k = ((k >>> 3 | k << 5) ^ arrayOfChar[b]) & 0xFF;
        } 
      } 
      b[i] = (new String(arrayOfChar)).intern();
    } 
    return b[i];
  }
}


/* Location:              C:\Program Files\BurpSuitePro\burpsuite_pro.jar!\burp\Zti3.class
 * Java compiler version: 21 (65.0)
 * JD-Core Version:       1.1.3
 */