package burp;

import java.math.BigInteger;

class Zti7 extends ClassLoader {
  static Object Zw;
  
  static String Zc;
  
  private static final String[] a;
  
  private static final String[] b;
  
  static boolean ZQ(Object[] paramArrayOfObject, Object paramObject) throws Throwable {
    // Byte code:
    //   0: invokestatic ZK : ()Z
    //   3: istore_2
    //   4: getstatic burp/Zssc.Zr : Ljava/lang/Object;
    //   7: checkcast java/math/BigInteger
    //   10: invokevirtual toByteArray : ()[B
    //   13: astore_3
    //   14: iconst_0
    //   15: istore #5
    //   17: iconst_0
    //   18: istore #6
    //   20: iload #6
    //   22: aload_3
    //   23: arraylength
    //   24: if_icmpge -> 169
    //   27: aload_3
    //   28: iload #6
    //   30: baload
    //   31: istore #7
    //   33: iload #7
    //   35: bipush #48
    //   37: if_icmplt -> 54
    //   40: iload #7
    //   42: bipush #57
    //   44: if_icmple -> 152
    //   47: goto -> 54
    //   50: invokestatic a : (Ljava/lang/Throwable;)Ljava/lang/Throwable;
    //   53: athrow
    //   54: iload #7
    //   56: bipush #65
    //   58: if_icmplt -> 82
    //   61: goto -> 68
    //   64: invokestatic a : (Ljava/lang/Throwable;)Ljava/lang/Throwable;
    //   67: athrow
    //   68: iload #7
    //   70: bipush #90
    //   72: if_icmple -> 152
    //   75: goto -> 82
    //   78: invokestatic a : (Ljava/lang/Throwable;)Ljava/lang/Throwable;
    //   81: athrow
    //   82: iload #7
    //   84: bipush #97
    //   86: if_icmplt -> 110
    //   89: goto -> 96
    //   92: invokestatic a : (Ljava/lang/Throwable;)Ljava/lang/Throwable;
    //   95: athrow
    //   96: iload #7
    //   98: bipush #122
    //   100: if_icmple -> 152
    //   103: goto -> 110
    //   106: invokestatic a : (Ljava/lang/Throwable;)Ljava/lang/Throwable;
    //   109: athrow
    //   110: iload #7
    //   112: bipush #43
    //   114: if_icmpeq -> 152
    //   117: goto -> 124
    //   120: invokestatic a : (Ljava/lang/Throwable;)Ljava/lang/Throwable;
    //   123: athrow
    //   124: iload #7
    //   126: bipush #47
    //   128: if_icmpeq -> 152
    //   131: goto -> 138
    //   134: invokestatic a : (Ljava/lang/Throwable;)Ljava/lang/Throwable;
    //   137: athrow
    //   138: iload #7
    //   140: bipush #61
    //   142: if_icmpne -> 162
    //   145: goto -> 152
    //   148: invokestatic a : (Ljava/lang/Throwable;)Ljava/lang/Throwable;
    //   151: athrow
    //   152: iinc #5, 1
    //   155: goto -> 162
    //   158: invokestatic a : (Ljava/lang/Throwable;)Ljava/lang/Throwable;
    //   161: athrow
    //   162: iinc #6, 1
    //   165: iload_2
    //   166: ifeq -> 20
    //   169: iload #5
    //   171: newarray byte
    //   173: astore #6
    //   175: iconst_0
    //   176: istore #7
    //   178: iconst_0
    //   179: istore #8
    //   181: iload #8
    //   183: aload_3
    //   184: arraylength
    //   185: if_icmpge -> 337
    //   188: aload_3
    //   189: iload #8
    //   191: baload
    //   192: istore #9
    //   194: iload #9
    //   196: bipush #48
    //   198: if_icmplt -> 215
    //   201: iload #9
    //   203: bipush #57
    //   205: if_icmple -> 313
    //   208: goto -> 215
    //   211: invokestatic a : (Ljava/lang/Throwable;)Ljava/lang/Throwable;
    //   214: athrow
    //   215: iload #9
    //   217: bipush #65
    //   219: if_icmplt -> 243
    //   222: goto -> 229
    //   225: invokestatic a : (Ljava/lang/Throwable;)Ljava/lang/Throwable;
    //   228: athrow
    //   229: iload #9
    //   231: bipush #90
    //   233: if_icmple -> 313
    //   236: goto -> 243
    //   239: invokestatic a : (Ljava/lang/Throwable;)Ljava/lang/Throwable;
    //   242: athrow
    //   243: iload #9
    //   245: bipush #97
    //   247: if_icmplt -> 271
    //   250: goto -> 257
    //   253: invokestatic a : (Ljava/lang/Throwable;)Ljava/lang/Throwable;
    //   256: athrow
    //   257: iload #9
    //   259: bipush #122
    //   261: if_icmple -> 313
    //   264: goto -> 271
    //   267: invokestatic a : (Ljava/lang/Throwable;)Ljava/lang/Throwable;
    //   270: athrow
    //   271: iload #9
    //   273: bipush #43
    //   275: if_icmpeq -> 313
    //   278: goto -> 285
    //   281: invokestatic a : (Ljava/lang/Throwable;)Ljava/lang/Throwable;
    //   284: athrow
    //   285: iload #9
    //   287: bipush #47
    //   289: if_icmpeq -> 313
    //   292: goto -> 299
    //   295: invokestatic a : (Ljava/lang/Throwable;)Ljava/lang/Throwable;
    //   298: athrow
    //   299: iload #9
    //   301: bipush #61
    //   303: if_icmpne -> 330
    //   306: goto -> 313
    //   309: invokestatic a : (Ljava/lang/Throwable;)Ljava/lang/Throwable;
    //   312: athrow
    //   313: aload #6
    //   315: iload #7
    //   317: iload #9
    //   319: bastore
    //   320: iinc #7, 1
    //   323: goto -> 330
    //   326: invokestatic a : (Ljava/lang/Throwable;)Ljava/lang/Throwable;
    //   329: athrow
    //   330: iinc #8, 1
    //   333: iload_2
    //   334: ifeq -> 181
    //   337: aload #6
    //   339: astore #4
    //   341: aload #4
    //   343: astore_3
    //   344: aload_3
    //   345: arraylength
    //   346: istore #5
    //   348: aload_3
    //   349: iload #5
    //   351: iconst_1
    //   352: isub
    //   353: baload
    //   354: bipush #61
    //   356: if_icmpne -> 366
    //   359: iinc #5, -1
    //   362: iload_2
    //   363: ifeq -> 348
    //   366: iload #5
    //   368: aload_3
    //   369: arraylength
    //   370: iconst_4
    //   371: idiv
    //   372: isub
    //   373: newarray byte
    //   375: astore #6
    //   377: iconst_0
    //   378: istore #7
    //   380: iload #7
    //   382: aload_3
    //   383: arraylength
    //   384: if_icmpge -> 646
    //   387: aload_3
    //   388: iload #7
    //   390: baload
    //   391: bipush #61
    //   393: if_icmpne -> 412
    //   396: aload_3
    //   397: iload #7
    //   399: iconst_0
    //   400: bastore
    //   401: iload_2
    //   402: ifeq -> 639
    //   405: goto -> 412
    //   408: invokestatic a : (Ljava/lang/Throwable;)Ljava/lang/Throwable;
    //   411: athrow
    //   412: aload_3
    //   413: iload #7
    //   415: baload
    //   416: bipush #47
    //   418: if_icmpne -> 445
    //   421: goto -> 428
    //   424: invokestatic a : (Ljava/lang/Throwable;)Ljava/lang/Throwable;
    //   427: athrow
    //   428: aload_3
    //   429: iload #7
    //   431: bipush #63
    //   433: bastore
    //   434: iload_2
    //   435: ifeq -> 639
    //   438: goto -> 445
    //   441: invokestatic a : (Ljava/lang/Throwable;)Ljava/lang/Throwable;
    //   444: athrow
    //   445: aload_3
    //   446: iload #7
    //   448: baload
    //   449: bipush #43
    //   451: if_icmpne -> 478
    //   454: goto -> 461
    //   457: invokestatic a : (Ljava/lang/Throwable;)Ljava/lang/Throwable;
    //   460: athrow
    //   461: aload_3
    //   462: iload #7
    //   464: bipush #62
    //   466: bastore
    //   467: iload_2
    //   468: ifeq -> 639
    //   471: goto -> 478
    //   474: invokestatic a : (Ljava/lang/Throwable;)Ljava/lang/Throwable;
    //   477: athrow
    //   478: aload_3
    //   479: iload #7
    //   481: baload
    //   482: bipush #48
    //   484: if_icmplt -> 533
    //   487: goto -> 494
    //   490: invokestatic a : (Ljava/lang/Throwable;)Ljava/lang/Throwable;
    //   493: athrow
    //   494: aload_3
    //   495: iload #7
    //   497: baload
    //   498: bipush #57
    //   500: if_icmpgt -> 533
    //   503: goto -> 510
    //   506: invokestatic a : (Ljava/lang/Throwable;)Ljava/lang/Throwable;
    //   509: athrow
    //   510: aload_3
    //   511: iload #7
    //   513: aload_3
    //   514: iload #7
    //   516: baload
    //   517: bipush #-4
    //   519: isub
    //   520: i2b
    //   521: bastore
    //   522: iload_2
    //   523: ifeq -> 639
    //   526: goto -> 533
    //   529: invokestatic a : (Ljava/lang/Throwable;)Ljava/lang/Throwable;
    //   532: athrow
    //   533: aload_3
    //   534: iload #7
    //   536: baload
    //   537: bipush #97
    //   539: if_icmplt -> 588
    //   542: goto -> 549
    //   545: invokestatic a : (Ljava/lang/Throwable;)Ljava/lang/Throwable;
    //   548: athrow
    //   549: aload_3
    //   550: iload #7
    //   552: baload
    //   553: bipush #122
    //   555: if_icmpgt -> 588
    //   558: goto -> 565
    //   561: invokestatic a : (Ljava/lang/Throwable;)Ljava/lang/Throwable;
    //   564: athrow
    //   565: aload_3
    //   566: iload #7
    //   568: aload_3
    //   569: iload #7
    //   571: baload
    //   572: bipush #71
    //   574: isub
    //   575: i2b
    //   576: bastore
    //   577: iload_2
    //   578: ifeq -> 639
    //   581: goto -> 588
    //   584: invokestatic a : (Ljava/lang/Throwable;)Ljava/lang/Throwable;
    //   587: athrow
    //   588: aload_3
    //   589: iload #7
    //   591: baload
    //   592: bipush #65
    //   594: if_icmplt -> 639
    //   597: goto -> 604
    //   600: invokestatic a : (Ljava/lang/Throwable;)Ljava/lang/Throwable;
    //   603: athrow
    //   604: aload_3
    //   605: iload #7
    //   607: baload
    //   608: bipush #90
    //   610: if_icmpgt -> 639
    //   613: goto -> 620
    //   616: invokestatic a : (Ljava/lang/Throwable;)Ljava/lang/Throwable;
    //   619: athrow
    //   620: aload_3
    //   621: iload #7
    //   623: aload_3
    //   624: iload #7
    //   626: baload
    //   627: bipush #65
    //   629: isub
    //   630: i2b
    //   631: bastore
    //   632: goto -> 639
    //   635: invokestatic a : (Ljava/lang/Throwable;)Ljava/lang/Throwable;
    //   638: athrow
    //   639: iinc #7, 1
    //   642: iload_2
    //   643: ifeq -> 380
    //   646: iconst_0
    //   647: istore #7
    //   649: iconst_0
    //   650: istore #8
    //   652: iload #8
    //   654: aload #6
    //   656: arraylength
    //   657: iconst_2
    //   658: isub
    //   659: if_icmpge -> 762
    //   662: aload #6
    //   664: iload #8
    //   666: aload_3
    //   667: iload #7
    //   669: baload
    //   670: iconst_2
    //   671: ishl
    //   672: sipush #255
    //   675: iand
    //   676: aload_3
    //   677: iload #7
    //   679: iconst_1
    //   680: iadd
    //   681: baload
    //   682: iconst_4
    //   683: iushr
    //   684: iconst_3
    //   685: iand
    //   686: ior
    //   687: i2b
    //   688: bastore
    //   689: aload #6
    //   691: iload #8
    //   693: iconst_1
    //   694: iadd
    //   695: aload_3
    //   696: iload #7
    //   698: iconst_1
    //   699: iadd
    //   700: baload
    //   701: iconst_4
    //   702: ishl
    //   703: sipush #255
    //   706: iand
    //   707: aload_3
    //   708: iload #7
    //   710: iconst_2
    //   711: iadd
    //   712: baload
    //   713: iconst_2
    //   714: iushr
    //   715: bipush #15
    //   717: iand
    //   718: ior
    //   719: i2b
    //   720: bastore
    //   721: aload #6
    //   723: iload #8
    //   725: iconst_2
    //   726: iadd
    //   727: aload_3
    //   728: iload #7
    //   730: iconst_2
    //   731: iadd
    //   732: baload
    //   733: bipush #6
    //   735: ishl
    //   736: sipush #255
    //   739: iand
    //   740: aload_3
    //   741: iload #7
    //   743: iconst_3
    //   744: iadd
    //   745: baload
    //   746: bipush #63
    //   748: iand
    //   749: ior
    //   750: i2b
    //   751: bastore
    //   752: iinc #7, 4
    //   755: iinc #8, 3
    //   758: iload_2
    //   759: ifeq -> 652
    //   762: iload #8
    //   764: aload #6
    //   766: arraylength
    //   767: if_icmpge -> 804
    //   770: aload #6
    //   772: iload #8
    //   774: aload_3
    //   775: iload #7
    //   777: baload
    //   778: iconst_2
    //   779: ishl
    //   780: sipush #255
    //   783: iand
    //   784: aload_3
    //   785: iload #7
    //   787: iconst_1
    //   788: iadd
    //   789: baload
    //   790: iconst_4
    //   791: iushr
    //   792: iconst_3
    //   793: iand
    //   794: ior
    //   795: i2b
    //   796: bastore
    //   797: goto -> 804
    //   800: invokestatic a : (Ljava/lang/Throwable;)Ljava/lang/Throwable;
    //   803: athrow
    //   804: iinc #8, 1
    //   807: iload #8
    //   809: aload #6
    //   811: arraylength
    //   812: if_icmpge -> 852
    //   815: aload #6
    //   817: iload #8
    //   819: aload_3
    //   820: iload #7
    //   822: iconst_1
    //   823: iadd
    //   824: baload
    //   825: iconst_4
    //   826: ishl
    //   827: sipush #255
    //   830: iand
    //   831: aload_3
    //   832: iload #7
    //   834: iconst_2
    //   835: iadd
    //   836: baload
    //   837: iconst_2
    //   838: iushr
    //   839: bipush #15
    //   841: iand
    //   842: ior
    //   843: i2b
    //   844: bastore
    //   845: goto -> 852
    //   848: invokestatic a : (Ljava/lang/Throwable;)Ljava/lang/Throwable;
    //   851: athrow
    //   852: aload #6
    //   854: astore #4
    //   856: new java/math/BigInteger
    //   859: dup
    //   860: aload #4
    //   862: invokespecial <init> : ([B)V
    //   865: invokevirtual abs : ()Ljava/math/BigInteger;
    //   868: putstatic burp/Zzk_.Zx : Ljava/lang/Object;
    //   871: new java/lang/StringBuilder
    //   874: dup
    //   875: invokespecial <init> : ()V
    //   878: astore_3
    //   879: iconst_0
    //   880: istore #4
    //   882: iload #4
    //   884: bipush #32
    //   886: if_icmpge -> 2219
    //   889: iload #4
    //   891: tableswitch default -> 2212, 0 -> 1032, 1 -> 1069, 2 -> 1106, 3 -> 1143, 4 -> 1180, 5 -> 1217, 6 -> 1254, 7 -> 1291, 8 -> 1328, 9 -> 1365, 10 -> 1402, 11 -> 1439, 12 -> 1476, 13 -> 1513, 14 -> 1550, 15 -> 1587, 16 -> 1624, 17 -> 1661, 18 -> 1698, 19 -> 1735, 20 -> 1772, 21 -> 1809, 22 -> 1846, 23 -> 1883, 24 -> 1920, 25 -> 1957, 26 -> 1994, 27 -> 2031, 28 -> 2068, 29 -> 2105, 30 -> 2142, 31 -> 2179
    //   1032: aload_3
    //   1033: getstatic burp/Zsu2.Zq : Ljava/lang/String;
    //   1036: getstatic burp/Zrfa.Zj : Ljava/lang/Object;
    //   1039: checkcast java/math/BigInteger
    //   1042: invokevirtual intValue : ()I
    //   1045: bipush #32
    //   1047: irem
    //   1048: invokestatic abs : (I)I
    //   1051: invokevirtual charAt : (I)C
    //   1054: invokevirtual append : (C)Ljava/lang/StringBuilder;
    //   1057: pop
    //   1058: iload_2
    //   1059: ifeq -> 2212
    //   1062: goto -> 1069
    //   1065: invokestatic a : (Ljava/lang/Throwable;)Ljava/lang/Throwable;
    //   1068: athrow
    //   1069: aload_3
    //   1070: getstatic burp/Zb4d.ZS : Ljava/lang/String;
    //   1073: getstatic burp/Zlwm.Ze : Ljava/lang/Object;
    //   1076: checkcast java/math/BigInteger
    //   1079: invokevirtual intValue : ()I
    //   1082: bipush #32
    //   1084: irem
    //   1085: invokestatic abs : (I)I
    //   1088: invokevirtual charAt : (I)C
    //   1091: invokevirtual append : (C)Ljava/lang/StringBuilder;
    //   1094: pop
    //   1095: iload_2
    //   1096: ifeq -> 2212
    //   1099: goto -> 1106
    //   1102: invokestatic a : (Ljava/lang/Throwable;)Ljava/lang/Throwable;
    //   1105: athrow
    //   1106: aload_3
    //   1107: getstatic burp/Zsbo.Zg : Ljava/lang/String;
    //   1110: getstatic burp/Zzef.Zw : Ljava/lang/Object;
    //   1113: checkcast java/math/BigInteger
    //   1116: invokevirtual intValue : ()I
    //   1119: bipush #32
    //   1121: irem
    //   1122: invokestatic abs : (I)I
    //   1125: invokevirtual charAt : (I)C
    //   1128: invokevirtual append : (C)Ljava/lang/StringBuilder;
    //   1131: pop
    //   1132: iload_2
    //   1133: ifeq -> 2212
    //   1136: goto -> 1143
    //   1139: invokestatic a : (Ljava/lang/Throwable;)Ljava/lang/Throwable;
    //   1142: athrow
    //   1143: aload_3
    //   1144: getstatic burp/Zetf.Zo : Ljava/lang/String;
    //   1147: getstatic burp/Zbx5.ZL : Ljava/lang/Object;
    //   1150: checkcast java/math/BigInteger
    //   1153: invokevirtual intValue : ()I
    //   1156: bipush #32
    //   1158: irem
    //   1159: invokestatic abs : (I)I
    //   1162: invokevirtual charAt : (I)C
    //   1165: invokevirtual append : (C)Ljava/lang/StringBuilder;
    //   1168: pop
    //   1169: iload_2
    //   1170: ifeq -> 2212
    //   1173: goto -> 1180
    //   1176: invokestatic a : (Ljava/lang/Throwable;)Ljava/lang/Throwable;
    //   1179: athrow
    //   1180: aload_3
    //   1181: getstatic burp/Zbw5.ZC : Ljava/lang/String;
    //   1184: getstatic burp/Zmdf.ZH : Ljava/lang/Object;
    //   1187: checkcast java/math/BigInteger
    //   1190: invokevirtual intValue : ()I
    //   1193: bipush #32
    //   1195: irem
    //   1196: invokestatic abs : (I)I
    //   1199: invokevirtual charAt : (I)C
    //   1202: invokevirtual append : (C)Ljava/lang/StringBuilder;
    //   1205: pop
    //   1206: iload_2
    //   1207: ifeq -> 2212
    //   1210: goto -> 1217
    //   1213: invokestatic a : (Ljava/lang/Throwable;)Ljava/lang/Throwable;
    //   1216: athrow
    //   1217: aload_3
    //   1218: getstatic burp/Zl1e.Z_ : Ljava/lang/String;
    //   1221: getstatic burp/Zbx4.Zw : Ljava/lang/Object;
    //   1224: checkcast java/math/BigInteger
    //   1227: invokevirtual intValue : ()I
    //   1230: bipush #32
    //   1232: irem
    //   1233: invokestatic abs : (I)I
    //   1236: invokevirtual charAt : (I)C
    //   1239: invokevirtual append : (C)Ljava/lang/StringBuilder;
    //   1242: pop
    //   1243: iload_2
    //   1244: ifeq -> 2212
    //   1247: goto -> 1254
    //   1250: invokestatic a : (Ljava/lang/Throwable;)Ljava/lang/Throwable;
    //   1253: athrow
    //   1254: aload_3
    //   1255: getstatic burp/Zbnk.Zg : Ljava/lang/String;
    //   1258: getstatic burp/Zbze.ZM : Ljava/lang/Object;
    //   1261: checkcast java/math/BigInteger
    //   1264: invokevirtual intValue : ()I
    //   1267: bipush #32
    //   1269: irem
    //   1270: invokestatic abs : (I)I
    //   1273: invokevirtual charAt : (I)C
    //   1276: invokevirtual append : (C)Ljava/lang/StringBuilder;
    //   1279: pop
    //   1280: iload_2
    //   1281: ifeq -> 2212
    //   1284: goto -> 1291
    //   1287: invokestatic a : (Ljava/lang/Throwable;)Ljava/lang/Throwable;
    //   1290: athrow
    //   1291: aload_3
    //   1292: getstatic burp/Ze1k.ZI : Ljava/lang/String;
    //   1295: getstatic burp/Zeig.ZA : Ljava/lang/Object;
    //   1298: checkcast java/math/BigInteger
    //   1301: invokevirtual intValue : ()I
    //   1304: bipush #32
    //   1306: irem
    //   1307: invokestatic abs : (I)I
    //   1310: invokevirtual charAt : (I)C
    //   1313: invokevirtual append : (C)Ljava/lang/StringBuilder;
    //   1316: pop
    //   1317: iload_2
    //   1318: ifeq -> 2212
    //   1321: goto -> 1328
    //   1324: invokestatic a : (Ljava/lang/Throwable;)Ljava/lang/Throwable;
    //   1327: athrow
    //   1328: aload_3
    //   1329: getstatic burp/Zl1e.Z_ : Ljava/lang/String;
    //   1332: getstatic burp/Zmh3.ZF : Ljava/lang/Object;
    //   1335: checkcast java/math/BigInteger
    //   1338: invokevirtual intValue : ()I
    //   1341: bipush #32
    //   1343: irem
    //   1344: invokestatic abs : (I)I
    //   1347: invokevirtual charAt : (I)C
    //   1350: invokevirtual append : (C)Ljava/lang/StringBuilder;
    //   1353: pop
    //   1354: iload_2
    //   1355: ifeq -> 2212
    //   1358: goto -> 1365
    //   1361: invokestatic a : (Ljava/lang/Throwable;)Ljava/lang/Throwable;
    //   1364: athrow
    //   1365: aload_3
    //   1366: getstatic burp/Zt7x.Zu : Ljava/lang/String;
    //   1369: getstatic burp/Zsfj.ZL : Ljava/lang/Object;
    //   1372: checkcast java/math/BigInteger
    //   1375: invokevirtual intValue : ()I
    //   1378: bipush #32
    //   1380: irem
    //   1381: invokestatic abs : (I)I
    //   1384: invokevirtual charAt : (I)C
    //   1387: invokevirtual append : (C)Ljava/lang/StringBuilder;
    //   1390: pop
    //   1391: iload_2
    //   1392: ifeq -> 2212
    //   1395: goto -> 1402
    //   1398: invokestatic a : (Ljava/lang/Throwable;)Ljava/lang/Throwable;
    //   1401: athrow
    //   1402: aload_3
    //   1403: getstatic burp/Zxcn.ZF : Ljava/lang/String;
    //   1406: getstatic burp/Zmt_.Zl : Ljava/lang/Object;
    //   1409: checkcast java/math/BigInteger
    //   1412: invokevirtual intValue : ()I
    //   1415: bipush #32
    //   1417: irem
    //   1418: invokestatic abs : (I)I
    //   1421: invokevirtual charAt : (I)C
    //   1424: invokevirtual append : (C)Ljava/lang/StringBuilder;
    //   1427: pop
    //   1428: iload_2
    //   1429: ifeq -> 2212
    //   1432: goto -> 1439
    //   1435: invokestatic a : (Ljava/lang/Throwable;)Ljava/lang/Throwable;
    //   1438: athrow
    //   1439: aload_3
    //   1440: getstatic burp/Zl1e.Z_ : Ljava/lang/String;
    //   1443: getstatic burp/Zso.ZA : Ljava/lang/Object;
    //   1446: checkcast java/math/BigInteger
    //   1449: invokevirtual intValue : ()I
    //   1452: bipush #32
    //   1454: irem
    //   1455: invokestatic abs : (I)I
    //   1458: invokevirtual charAt : (I)C
    //   1461: invokevirtual append : (C)Ljava/lang/StringBuilder;
    //   1464: pop
    //   1465: iload_2
    //   1466: ifeq -> 2212
    //   1469: goto -> 1476
    //   1472: invokestatic a : (Ljava/lang/Throwable;)Ljava/lang/Throwable;
    //   1475: athrow
    //   1476: aload_3
    //   1477: getstatic burp/Zrfs.ZD : Ljava/lang/String;
    //   1480: getstatic burp/Zegv.ZL : Ljava/lang/Object;
    //   1483: checkcast java/math/BigInteger
    //   1486: invokevirtual intValue : ()I
    //   1489: bipush #32
    //   1491: irem
    //   1492: invokestatic abs : (I)I
    //   1495: invokevirtual charAt : (I)C
    //   1498: invokevirtual append : (C)Ljava/lang/StringBuilder;
    //   1501: pop
    //   1502: iload_2
    //   1503: ifeq -> 2212
    //   1506: goto -> 1513
    //   1509: invokestatic a : (Ljava/lang/Throwable;)Ljava/lang/Throwable;
    //   1512: athrow
    //   1513: aload_3
    //   1514: getstatic burp/Zedq.Zj : Ljava/lang/String;
    //   1517: getstatic burp/Zskf.ZQ : Ljava/lang/Object;
    //   1520: checkcast java/math/BigInteger
    //   1523: invokevirtual intValue : ()I
    //   1526: bipush #32
    //   1528: irem
    //   1529: invokestatic abs : (I)I
    //   1532: invokevirtual charAt : (I)C
    //   1535: invokevirtual append : (C)Ljava/lang/StringBuilder;
    //   1538: pop
    //   1539: iload_2
    //   1540: ifeq -> 2212
    //   1543: goto -> 1550
    //   1546: invokestatic a : (Ljava/lang/Throwable;)Ljava/lang/Throwable;
    //   1549: athrow
    //   1550: aload_3
    //   1551: getstatic burp/Zedu.ZD : Ljava/lang/String;
    //   1554: getstatic burp/Zrqi.Zb : Ljava/lang/Object;
    //   1557: checkcast java/math/BigInteger
    //   1560: invokevirtual intValue : ()I
    //   1563: bipush #32
    //   1565: irem
    //   1566: invokestatic abs : (I)I
    //   1569: invokevirtual charAt : (I)C
    //   1572: invokevirtual append : (C)Ljava/lang/StringBuilder;
    //   1575: pop
    //   1576: iload_2
    //   1577: ifeq -> 2212
    //   1580: goto -> 1587
    //   1583: invokestatic a : (Ljava/lang/Throwable;)Ljava/lang/Throwable;
    //   1586: athrow
    //   1587: aload_3
    //   1588: getstatic burp/Zr60.ZQ : Ljava/lang/String;
    //   1591: getstatic burp/Zz7j.ZR : Ljava/lang/Object;
    //   1594: checkcast java/math/BigInteger
    //   1597: invokevirtual intValue : ()I
    //   1600: bipush #32
    //   1602: irem
    //   1603: invokestatic abs : (I)I
    //   1606: invokevirtual charAt : (I)C
    //   1609: invokevirtual append : (C)Ljava/lang/StringBuilder;
    //   1612: pop
    //   1613: iload_2
    //   1614: ifeq -> 2212
    //   1617: goto -> 1624
    //   1620: invokestatic a : (Ljava/lang/Throwable;)Ljava/lang/Throwable;
    //   1623: athrow
    //   1624: aload_3
    //   1625: getstatic burp/Ztq2.Zt : Ljava/lang/String;
    //   1628: getstatic burp/Zrtp.Zy : Ljava/lang/Object;
    //   1631: checkcast java/math/BigInteger
    //   1634: invokevirtual intValue : ()I
    //   1637: bipush #32
    //   1639: irem
    //   1640: invokestatic abs : (I)I
    //   1643: invokevirtual charAt : (I)C
    //   1646: invokevirtual append : (C)Ljava/lang/StringBuilder;
    //   1649: pop
    //   1650: iload_2
    //   1651: ifeq -> 2212
    //   1654: goto -> 1661
    //   1657: invokestatic a : (Ljava/lang/Throwable;)Ljava/lang/Throwable;
    //   1660: athrow
    //   1661: aload_3
    //   1662: getstatic burp/Zg4l.Z_ : Ljava/lang/String;
    //   1665: getstatic burp/Zl7x.Za : Ljava/lang/Object;
    //   1668: checkcast java/math/BigInteger
    //   1671: invokevirtual intValue : ()I
    //   1674: bipush #32
    //   1676: irem
    //   1677: invokestatic abs : (I)I
    //   1680: invokevirtual charAt : (I)C
    //   1683: invokevirtual append : (C)Ljava/lang/StringBuilder;
    //   1686: pop
    //   1687: iload_2
    //   1688: ifeq -> 2212
    //   1691: goto -> 1698
    //   1694: invokestatic a : (Ljava/lang/Throwable;)Ljava/lang/Throwable;
    //   1697: athrow
    //   1698: aload_3
    //   1699: getstatic burp/Zry1.Zk : Ljava/lang/String;
    //   1702: getstatic burp/Zmdf.ZH : Ljava/lang/Object;
    //   1705: checkcast java/math/BigInteger
    //   1708: invokevirtual intValue : ()I
    //   1711: bipush #32
    //   1713: irem
    //   1714: invokestatic abs : (I)I
    //   1717: invokevirtual charAt : (I)C
    //   1720: invokevirtual append : (C)Ljava/lang/StringBuilder;
    //   1723: pop
    //   1724: iload_2
    //   1725: ifeq -> 2212
    //   1728: goto -> 1735
    //   1731: invokestatic a : (Ljava/lang/Throwable;)Ljava/lang/Throwable;
    //   1734: athrow
    //   1735: aload_3
    //   1736: getstatic burp/Zb9q.Zk : Ljava/lang/String;
    //   1739: getstatic burp/Zm8j.Zj : Ljava/lang/Object;
    //   1742: checkcast java/math/BigInteger
    //   1745: invokevirtual intValue : ()I
    //   1748: bipush #32
    //   1750: irem
    //   1751: invokestatic abs : (I)I
    //   1754: invokevirtual charAt : (I)C
    //   1757: invokevirtual append : (C)Ljava/lang/StringBuilder;
    //   1760: pop
    //   1761: iload_2
    //   1762: ifeq -> 2212
    //   1765: goto -> 1772
    //   1768: invokestatic a : (Ljava/lang/Throwable;)Ljava/lang/Throwable;
    //   1771: athrow
    //   1772: aload_3
    //   1773: getstatic burp/Zlf7.ZM : Ljava/lang/String;
    //   1776: getstatic burp/Zg4l.ZI : Ljava/lang/Object;
    //   1779: checkcast java/math/BigInteger
    //   1782: invokevirtual intValue : ()I
    //   1785: bipush #32
    //   1787: irem
    //   1788: invokestatic abs : (I)I
    //   1791: invokevirtual charAt : (I)C
    //   1794: invokevirtual append : (C)Ljava/lang/StringBuilder;
    //   1797: pop
    //   1798: iload_2
    //   1799: ifeq -> 2212
    //   1802: goto -> 1809
    //   1805: invokestatic a : (Ljava/lang/Throwable;)Ljava/lang/Throwable;
    //   1808: athrow
    //   1809: aload_3
    //   1810: getstatic burp/Zso.ZL : Ljava/lang/String;
    //   1813: getstatic burp/Zxwf.Zi : Ljava/lang/Object;
    //   1816: checkcast java/math/BigInteger
    //   1819: invokevirtual intValue : ()I
    //   1822: bipush #32
    //   1824: irem
    //   1825: invokestatic abs : (I)I
    //   1828: invokevirtual charAt : (I)C
    //   1831: invokevirtual append : (C)Ljava/lang/StringBuilder;
    //   1834: pop
    //   1835: iload_2
    //   1836: ifeq -> 2212
    //   1839: goto -> 1846
    //   1842: invokestatic a : (Ljava/lang/Throwable;)Ljava/lang/Throwable;
    //   1845: athrow
    //   1846: aload_3
    //   1847: getstatic burp/Zbjx.ZA : Ljava/lang/String;
    //   1850: getstatic burp/Zzyb.ZV : Ljava/lang/Object;
    //   1853: checkcast java/math/BigInteger
    //   1856: invokevirtual intValue : ()I
    //   1859: bipush #32
    //   1861: irem
    //   1862: invokestatic abs : (I)I
    //   1865: invokevirtual charAt : (I)C
    //   1868: invokevirtual append : (C)Ljava/lang/StringBuilder;
    //   1871: pop
    //   1872: iload_2
    //   1873: ifeq -> 2212
    //   1876: goto -> 1883
    //   1879: invokestatic a : (Ljava/lang/Throwable;)Ljava/lang/Throwable;
    //   1882: athrow
    //   1883: aload_3
    //   1884: getstatic burp/Zrjq.Zx : Ljava/lang/String;
    //   1887: getstatic burp/Zrjq.ZU : Ljava/lang/Object;
    //   1890: checkcast java/math/BigInteger
    //   1893: invokevirtual intValue : ()I
    //   1896: bipush #32
    //   1898: irem
    //   1899: invokestatic abs : (I)I
    //   1902: invokevirtual charAt : (I)C
    //   1905: invokevirtual append : (C)Ljava/lang/StringBuilder;
    //   1908: pop
    //   1909: iload_2
    //   1910: ifeq -> 2212
    //   1913: goto -> 1920
    //   1916: invokestatic a : (Ljava/lang/Throwable;)Ljava/lang/Throwable;
    //   1919: athrow
    //   1920: aload_3
    //   1921: getstatic burp/Zkjj.ZT : Ljava/lang/String;
    //   1924: getstatic burp/Zmt_.Zl : Ljava/lang/Object;
    //   1927: checkcast java/math/BigInteger
    //   1930: invokevirtual intValue : ()I
    //   1933: bipush #32
    //   1935: irem
    //   1936: invokestatic abs : (I)I
    //   1939: invokevirtual charAt : (I)C
    //   1942: invokevirtual append : (C)Ljava/lang/StringBuilder;
    //   1945: pop
    //   1946: iload_2
    //   1947: ifeq -> 2212
    //   1950: goto -> 1957
    //   1953: invokestatic a : (Ljava/lang/Throwable;)Ljava/lang/Throwable;
    //   1956: athrow
    //   1957: aload_3
    //   1958: getstatic burp/Ztq2.Zt : Ljava/lang/String;
    //   1961: getstatic burp/Zscf.ZG : Ljava/lang/Object;
    //   1964: checkcast java/math/BigInteger
    //   1967: invokevirtual intValue : ()I
    //   1970: bipush #32
    //   1972: irem
    //   1973: invokestatic abs : (I)I
    //   1976: invokevirtual charAt : (I)C
    //   1979: invokevirtual append : (C)Ljava/lang/StringBuilder;
    //   1982: pop
    //   1983: iload_2
    //   1984: ifeq -> 2212
    //   1987: goto -> 1994
    //   1990: invokestatic a : (Ljava/lang/Throwable;)Ljava/lang/Throwable;
    //   1993: athrow
    //   1994: aload_3
    //   1995: getstatic burp/Zepy.Zg : Ljava/lang/String;
    //   1998: getstatic burp/Zbze.ZM : Ljava/lang/Object;
    //   2001: checkcast java/math/BigInteger
    //   2004: invokevirtual intValue : ()I
    //   2007: bipush #32
    //   2009: irem
    //   2010: invokestatic abs : (I)I
    //   2013: invokevirtual charAt : (I)C
    //   2016: invokevirtual append : (C)Ljava/lang/StringBuilder;
    //   2019: pop
    //   2020: iload_2
    //   2021: ifeq -> 2212
    //   2024: goto -> 2031
    //   2027: invokestatic a : (Ljava/lang/Throwable;)Ljava/lang/Throwable;
    //   2030: athrow
    //   2031: aload_3
    //   2032: getstatic burp/Zbx5.Zz : Ljava/lang/String;
    //   2035: getstatic burp/Zzii.ZO : Ljava/lang/Object;
    //   2038: checkcast java/math/BigInteger
    //   2041: invokevirtual intValue : ()I
    //   2044: bipush #32
    //   2046: irem
    //   2047: invokestatic abs : (I)I
    //   2050: invokevirtual charAt : (I)C
    //   2053: invokevirtual append : (C)Ljava/lang/StringBuilder;
    //   2056: pop
    //   2057: iload_2
    //   2058: ifeq -> 2212
    //   2061: goto -> 2068
    //   2064: invokestatic a : (Ljava/lang/Throwable;)Ljava/lang/Throwable;
    //   2067: athrow
    //   2068: aload_3
    //   2069: getstatic burp/Zz0b.ZD : Ljava/lang/String;
    //   2072: getstatic burp/Zgei.ZN : Ljava/lang/Object;
    //   2075: checkcast java/math/BigInteger
    //   2078: invokevirtual intValue : ()I
    //   2081: bipush #32
    //   2083: irem
    //   2084: invokestatic abs : (I)I
    //   2087: invokevirtual charAt : (I)C
    //   2090: invokevirtual append : (C)Ljava/lang/StringBuilder;
    //   2093: pop
    //   2094: iload_2
    //   2095: ifeq -> 2212
    //   2098: goto -> 2105
    //   2101: invokestatic a : (Ljava/lang/Throwable;)Ljava/lang/Throwable;
    //   2104: athrow
    //   2105: aload_3
    //   2106: getstatic burp/Zelt.ZJ : Ljava/lang/String;
    //   2109: getstatic burp/Zl7b.ZK : Ljava/lang/Object;
    //   2112: checkcast java/math/BigInteger
    //   2115: invokevirtual intValue : ()I
    //   2118: bipush #32
    //   2120: irem
    //   2121: invokestatic abs : (I)I
    //   2124: invokevirtual charAt : (I)C
    //   2127: invokevirtual append : (C)Ljava/lang/StringBuilder;
    //   2130: pop
    //   2131: iload_2
    //   2132: ifeq -> 2212
    //   2135: goto -> 2142
    //   2138: invokestatic a : (Ljava/lang/Throwable;)Ljava/lang/Throwable;
    //   2141: athrow
    //   2142: aload_3
    //   2143: getstatic burp/Zrle.ZG : Ljava/lang/String;
    //   2146: getstatic burp/Zmz.ZW : Ljava/lang/Object;
    //   2149: checkcast java/math/BigInteger
    //   2152: invokevirtual intValue : ()I
    //   2155: bipush #32
    //   2157: irem
    //   2158: invokestatic abs : (I)I
    //   2161: invokevirtual charAt : (I)C
    //   2164: invokevirtual append : (C)Ljava/lang/StringBuilder;
    //   2167: pop
    //   2168: iload_2
    //   2169: ifeq -> 2212
    //   2172: goto -> 2179
    //   2175: invokestatic a : (Ljava/lang/Throwable;)Ljava/lang/Throwable;
    //   2178: athrow
    //   2179: aload_3
    //   2180: getstatic burp/Zs1d.Zl : Ljava/lang/String;
    //   2183: getstatic burp/Zea9.Zt : Ljava/lang/Object;
    //   2186: checkcast java/math/BigInteger
    //   2189: invokevirtual intValue : ()I
    //   2192: bipush #32
    //   2194: irem
    //   2195: invokestatic abs : (I)I
    //   2198: invokevirtual charAt : (I)C
    //   2201: invokevirtual append : (C)Ljava/lang/StringBuilder;
    //   2204: pop
    //   2205: goto -> 2212
    //   2208: invokestatic a : (Ljava/lang/Throwable;)Ljava/lang/Throwable;
    //   2211: athrow
    //   2212: iinc #4, 1
    //   2215: iload_2
    //   2216: ifeq -> 882
    //   2219: aload_3
    //   2220: invokevirtual toString : ()Ljava/lang/String;
    //   2223: putstatic burp/Znu.ZF : Ljava/lang/String;
    //   2226: getstatic burp/Zmn0.Zo : Ljava/lang/Object;
    //   2229: checkcast java/math/BigInteger
    //   2232: invokevirtual toByteArray : ()[B
    //   2235: astore #4
    //   2237: bipush #64
    //   2239: newarray byte
    //   2241: dup
    //   2242: iconst_0
    //   2243: bipush #-128
    //   2245: bastore
    //   2246: dup
    //   2247: iconst_1
    //   2248: iconst_0
    //   2249: bastore
    //   2250: dup
    //   2251: iconst_2
    //   2252: iconst_0
    //   2253: bastore
    //   2254: dup
    //   2255: iconst_3
    //   2256: iconst_0
    //   2257: bastore
    //   2258: dup
    //   2259: iconst_4
    //   2260: iconst_0
    //   2261: bastore
    //   2262: dup
    //   2263: iconst_5
    //   2264: iconst_0
    //   2265: bastore
    //   2266: dup
    //   2267: bipush #6
    //   2269: iconst_0
    //   2270: bastore
    //   2271: dup
    //   2272: bipush #7
    //   2274: iconst_0
    //   2275: bastore
    //   2276: dup
    //   2277: bipush #8
    //   2279: iconst_0
    //   2280: bastore
    //   2281: dup
    //   2282: bipush #9
    //   2284: iconst_0
    //   2285: bastore
    //   2286: dup
    //   2287: bipush #10
    //   2289: iconst_0
    //   2290: bastore
    //   2291: dup
    //   2292: bipush #11
    //   2294: iconst_0
    //   2295: bastore
    //   2296: dup
    //   2297: bipush #12
    //   2299: iconst_0
    //   2300: bastore
    //   2301: dup
    //   2302: bipush #13
    //   2304: iconst_0
    //   2305: bastore
    //   2306: dup
    //   2307: bipush #14
    //   2309: iconst_0
    //   2310: bastore
    //   2311: dup
    //   2312: bipush #15
    //   2314: iconst_0
    //   2315: bastore
    //   2316: dup
    //   2317: bipush #16
    //   2319: iconst_0
    //   2320: bastore
    //   2321: dup
    //   2322: bipush #17
    //   2324: iconst_0
    //   2325: bastore
    //   2326: dup
    //   2327: bipush #18
    //   2329: iconst_0
    //   2330: bastore
    //   2331: dup
    //   2332: bipush #19
    //   2334: iconst_0
    //   2335: bastore
    //   2336: dup
    //   2337: bipush #20
    //   2339: iconst_0
    //   2340: bastore
    //   2341: dup
    //   2342: bipush #21
    //   2344: iconst_0
    //   2345: bastore
    //   2346: dup
    //   2347: bipush #22
    //   2349: iconst_0
    //   2350: bastore
    //   2351: dup
    //   2352: bipush #23
    //   2354: iconst_0
    //   2355: bastore
    //   2356: dup
    //   2357: bipush #24
    //   2359: iconst_0
    //   2360: bastore
    //   2361: dup
    //   2362: bipush #25
    //   2364: iconst_0
    //   2365: bastore
    //   2366: dup
    //   2367: bipush #26
    //   2369: iconst_0
    //   2370: bastore
    //   2371: dup
    //   2372: bipush #27
    //   2374: iconst_0
    //   2375: bastore
    //   2376: dup
    //   2377: bipush #28
    //   2379: iconst_0
    //   2380: bastore
    //   2381: dup
    //   2382: bipush #29
    //   2384: iconst_0
    //   2385: bastore
    //   2386: dup
    //   2387: bipush #30
    //   2389: iconst_0
    //   2390: bastore
    //   2391: dup
    //   2392: bipush #31
    //   2394: iconst_0
    //   2395: bastore
    //   2396: dup
    //   2397: bipush #32
    //   2399: iconst_0
    //   2400: bastore
    //   2401: dup
    //   2402: bipush #33
    //   2404: iconst_0
    //   2405: bastore
    //   2406: dup
    //   2407: bipush #34
    //   2409: iconst_0
    //   2410: bastore
    //   2411: dup
    //   2412: bipush #35
    //   2414: iconst_0
    //   2415: bastore
    //   2416: dup
    //   2417: bipush #36
    //   2419: iconst_0
    //   2420: bastore
    //   2421: dup
    //   2422: bipush #37
    //   2424: iconst_0
    //   2425: bastore
    //   2426: dup
    //   2427: bipush #38
    //   2429: iconst_0
    //   2430: bastore
    //   2431: dup
    //   2432: bipush #39
    //   2434: iconst_0
    //   2435: bastore
    //   2436: dup
    //   2437: bipush #40
    //   2439: iconst_0
    //   2440: bastore
    //   2441: dup
    //   2442: bipush #41
    //   2444: iconst_0
    //   2445: bastore
    //   2446: dup
    //   2447: bipush #42
    //   2449: iconst_0
    //   2450: bastore
    //   2451: dup
    //   2452: bipush #43
    //   2454: iconst_0
    //   2455: bastore
    //   2456: dup
    //   2457: bipush #44
    //   2459: iconst_0
    //   2460: bastore
    //   2461: dup
    //   2462: bipush #45
    //   2464: iconst_0
    //   2465: bastore
    //   2466: dup
    //   2467: bipush #46
    //   2469: iconst_0
    //   2470: bastore
    //   2471: dup
    //   2472: bipush #47
    //   2474: iconst_0
    //   2475: bastore
    //   2476: dup
    //   2477: bipush #48
    //   2479: iconst_0
    //   2480: bastore
    //   2481: dup
    //   2482: bipush #49
    //   2484: iconst_0
    //   2485: bastore
    //   2486: dup
    //   2487: bipush #50
    //   2489: iconst_0
    //   2490: bastore
    //   2491: dup
    //   2492: bipush #51
    //   2494: iconst_0
    //   2495: bastore
    //   2496: dup
    //   2497: bipush #52
    //   2499: iconst_0
    //   2500: bastore
    //   2501: dup
    //   2502: bipush #53
    //   2504: iconst_0
    //   2505: bastore
    //   2506: dup
    //   2507: bipush #54
    //   2509: iconst_0
    //   2510: bastore
    //   2511: dup
    //   2512: bipush #55
    //   2514: iconst_0
    //   2515: bastore
    //   2516: dup
    //   2517: bipush #56
    //   2519: iconst_0
    //   2520: bastore
    //   2521: dup
    //   2522: bipush #57
    //   2524: iconst_0
    //   2525: bastore
    //   2526: dup
    //   2527: bipush #58
    //   2529: iconst_0
    //   2530: bastore
    //   2531: dup
    //   2532: bipush #59
    //   2534: iconst_0
    //   2535: bastore
    //   2536: dup
    //   2537: bipush #60
    //   2539: iconst_0
    //   2540: bastore
    //   2541: dup
    //   2542: bipush #61
    //   2544: iconst_0
    //   2545: bastore
    //   2546: dup
    //   2547: bipush #62
    //   2549: iconst_0
    //   2550: bastore
    //   2551: dup
    //   2552: bipush #63
    //   2554: iconst_0
    //   2555: bastore
    //   2556: astore #6
    //   2558: bipush #64
    //   2560: newarray int
    //   2562: dup
    //   2563: iconst_0
    //   2564: ldc 1116352408
    //   2566: iastore
    //   2567: dup
    //   2568: iconst_1
    //   2569: ldc 1899447441
    //   2571: iastore
    //   2572: dup
    //   2573: iconst_2
    //   2574: ldc -1245643825
    //   2576: iastore
    //   2577: dup
    //   2578: iconst_3
    //   2579: ldc -373957723
    //   2581: iastore
    //   2582: dup
    //   2583: iconst_4
    //   2584: ldc 961987163
    //   2586: iastore
    //   2587: dup
    //   2588: iconst_5
    //   2589: ldc 1508970993
    //   2591: iastore
    //   2592: dup
    //   2593: bipush #6
    //   2595: ldc -1841331548
    //   2597: iastore
    //   2598: dup
    //   2599: bipush #7
    //   2601: ldc -1424204075
    //   2603: iastore
    //   2604: dup
    //   2605: bipush #8
    //   2607: ldc -670586216
    //   2609: iastore
    //   2610: dup
    //   2611: bipush #9
    //   2613: ldc 310598401
    //   2615: iastore
    //   2616: dup
    //   2617: bipush #10
    //   2619: ldc 607225278
    //   2621: iastore
    //   2622: dup
    //   2623: bipush #11
    //   2625: ldc 1426881987
    //   2627: iastore
    //   2628: dup
    //   2629: bipush #12
    //   2631: ldc 1925078388
    //   2633: iastore
    //   2634: dup
    //   2635: bipush #13
    //   2637: ldc -2132889090
    //   2639: iastore
    //   2640: dup
    //   2641: bipush #14
    //   2643: ldc -1680079193
    //   2645: iastore
    //   2646: dup
    //   2647: bipush #15
    //   2649: ldc -1046744716
    //   2651: iastore
    //   2652: dup
    //   2653: bipush #16
    //   2655: ldc -459576895
    //   2657: iastore
    //   2658: dup
    //   2659: bipush #17
    //   2661: ldc -272742522
    //   2663: iastore
    //   2664: dup
    //   2665: bipush #18
    //   2667: ldc 264347078
    //   2669: iastore
    //   2670: dup
    //   2671: bipush #19
    //   2673: ldc 604807628
    //   2675: iastore
    //   2676: dup
    //   2677: bipush #20
    //   2679: ldc 770255983
    //   2681: iastore
    //   2682: dup
    //   2683: bipush #21
    //   2685: ldc 1249150122
    //   2687: iastore
    //   2688: dup
    //   2689: bipush #22
    //   2691: ldc 1555081692
    //   2693: iastore
    //   2694: dup
    //   2695: bipush #23
    //   2697: ldc 1996064986
    //   2699: iastore
    //   2700: dup
    //   2701: bipush #24
    //   2703: ldc -1740746414
    //   2705: iastore
    //   2706: dup
    //   2707: bipush #25
    //   2709: ldc -1473132947
    //   2711: iastore
    //   2712: dup
    //   2713: bipush #26
    //   2715: ldc -1341970488
    //   2717: iastore
    //   2718: dup
    //   2719: bipush #27
    //   2721: ldc -1084653625
    //   2723: iastore
    //   2724: dup
    //   2725: bipush #28
    //   2727: ldc -958395405
    //   2729: iastore
    //   2730: dup
    //   2731: bipush #29
    //   2733: ldc -710438585
    //   2735: iastore
    //   2736: dup
    //   2737: bipush #30
    //   2739: ldc 113926993
    //   2741: iastore
    //   2742: dup
    //   2743: bipush #31
    //   2745: ldc 338241895
    //   2747: iastore
    //   2748: dup
    //   2749: bipush #32
    //   2751: ldc 666307205
    //   2753: iastore
    //   2754: dup
    //   2755: bipush #33
    //   2757: ldc 773529912
    //   2759: iastore
    //   2760: dup
    //   2761: bipush #34
    //   2763: ldc 1294757372
    //   2765: iastore
    //   2766: dup
    //   2767: bipush #35
    //   2769: ldc 1396182291
    //   2771: iastore
    //   2772: dup
    //   2773: bipush #36
    //   2775: ldc 1695183700
    //   2777: iastore
    //   2778: dup
    //   2779: bipush #37
    //   2781: ldc 1986661051
    //   2783: iastore
    //   2784: dup
    //   2785: bipush #38
    //   2787: ldc -2117940946
    //   2789: iastore
    //   2790: dup
    //   2791: bipush #39
    //   2793: ldc -1838011259
    //   2795: iastore
    //   2796: dup
    //   2797: bipush #40
    //   2799: ldc -1564481375
    //   2801: iastore
    //   2802: dup
    //   2803: bipush #41
    //   2805: ldc -1474664885
    //   2807: iastore
    //   2808: dup
    //   2809: bipush #42
    //   2811: ldc -1035236496
    //   2813: iastore
    //   2814: dup
    //   2815: bipush #43
    //   2817: ldc -949202525
    //   2819: iastore
    //   2820: dup
    //   2821: bipush #44
    //   2823: ldc -778901479
    //   2825: iastore
    //   2826: dup
    //   2827: bipush #45
    //   2829: ldc -694614492
    //   2831: iastore
    //   2832: dup
    //   2833: bipush #46
    //   2835: ldc -200395387
    //   2837: iastore
    //   2838: dup
    //   2839: bipush #47
    //   2841: ldc 275423344
    //   2843: iastore
    //   2844: dup
    //   2845: bipush #48
    //   2847: ldc 430227734
    //   2849: iastore
    //   2850: dup
    //   2851: bipush #49
    //   2853: ldc 506948616
    //   2855: iastore
    //   2856: dup
    //   2857: bipush #50
    //   2859: ldc 659060556
    //   2861: iastore
    //   2862: dup
    //   2863: bipush #51
    //   2865: ldc 883997877
    //   2867: iastore
    //   2868: dup
    //   2869: bipush #52
    //   2871: ldc 958139571
    //   2873: iastore
    //   2874: dup
    //   2875: bipush #53
    //   2877: ldc 1322822218
    //   2879: iastore
    //   2880: dup
    //   2881: bipush #54
    //   2883: ldc 1537002063
    //   2885: iastore
    //   2886: dup
    //   2887: bipush #55
    //   2889: ldc 1747873779
    //   2891: iastore
    //   2892: dup
    //   2893: bipush #56
    //   2895: ldc 1955562222
    //   2897: iastore
    //   2898: dup
    //   2899: bipush #57
    //   2901: ldc 2024104815
    //   2903: iastore
    //   2904: dup
    //   2905: bipush #58
    //   2907: ldc -2067236844
    //   2909: iastore
    //   2910: dup
    //   2911: bipush #59
    //   2913: ldc -1933114872
    //   2915: iastore
    //   2916: dup
    //   2917: bipush #60
    //   2919: ldc -1866530822
    //   2921: iastore
    //   2922: dup
    //   2923: bipush #61
    //   2925: ldc -1538233109
    //   2927: iastore
    //   2928: dup
    //   2929: bipush #62
    //   2931: ldc -1090935817
    //   2933: iastore
    //   2934: dup
    //   2935: bipush #63
    //   2937: ldc -965641998
    //   2939: iastore
    //   2940: astore #7
    //   2942: iconst_2
    //   2943: newarray int
    //   2945: dup
    //   2946: iconst_0
    //   2947: iconst_0
    //   2948: iastore
    //   2949: dup
    //   2950: iconst_1
    //   2951: iconst_0
    //   2952: iastore
    //   2953: astore #8
    //   2955: bipush #8
    //   2957: newarray int
    //   2959: dup
    //   2960: iconst_0
    //   2961: ldc 1779033703
    //   2963: iastore
    //   2964: dup
    //   2965: iconst_1
    //   2966: ldc -1150833019
    //   2968: iastore
    //   2969: dup
    //   2970: iconst_2
    //   2971: ldc 1013904242
    //   2973: iastore
    //   2974: dup
    //   2975: iconst_3
    //   2976: ldc -1521486534
    //   2978: iastore
    //   2979: dup
    //   2980: iconst_4
    //   2981: ldc 1359893119
    //   2983: iastore
    //   2984: dup
    //   2985: iconst_5
    //   2986: ldc -1694144372
    //   2988: iastore
    //   2989: dup
    //   2990: bipush #6
    //   2992: ldc 528734635
    //   2994: iastore
    //   2995: dup
    //   2996: bipush #7
    //   2998: ldc 1541459225
    //   3000: iastore
    //   3001: astore #9
    //   3003: bipush #64
    //   3005: newarray byte
    //   3007: astore #10
    //   3009: bipush #64
    //   3011: newarray byte
    //   3013: astore #11
    //   3015: aload #4
    //   3017: arraylength
    //   3018: istore #12
    //   3020: aload #8
    //   3022: iconst_0
    //   3023: iaload
    //   3024: bipush #63
    //   3026: iand
    //   3027: istore #13
    //   3029: aload #8
    //   3031: iconst_0
    //   3032: dup2
    //   3033: iaload
    //   3034: iload #12
    //   3036: iadd
    //   3037: iastore
    //   3038: aload #8
    //   3040: iconst_0
    //   3041: dup2
    //   3042: iaload
    //   3043: iconst_m1
    //   3044: iand
    //   3045: iastore
    //   3046: aload #8
    //   3048: iconst_0
    //   3049: iaload
    //   3050: iload #12
    //   3052: if_icmpge -> 3070
    //   3055: aload #8
    //   3057: iconst_1
    //   3058: dup2
    //   3059: iaload
    //   3060: iconst_1
    //   3061: iadd
    //   3062: iastore
    //   3063: goto -> 3070
    //   3066: invokestatic a : (Ljava/lang/Throwable;)Ljava/lang/Throwable;
    //   3069: athrow
    //   3070: iconst_0
    //   3071: istore #14
    //   3073: iload #12
    //   3075: bipush #64
    //   3077: if_icmplt -> 3687
    //   3080: iconst_0
    //   3081: istore #15
    //   3083: iload #15
    //   3085: bipush #64
    //   3087: if_icmpge -> 3110
    //   3090: aload #11
    //   3092: iload #15
    //   3094: aload #4
    //   3096: iload #14
    //   3098: iload #15
    //   3100: iadd
    //   3101: baload
    //   3102: bastore
    //   3103: iinc #15, 1
    //   3106: iload_2
    //   3107: ifeq -> 3083
    //   3110: bipush #64
    //   3112: newarray int
    //   3114: astore #15
    //   3116: bipush #8
    //   3118: newarray int
    //   3120: astore #16
    //   3122: iconst_0
    //   3123: istore #17
    //   3125: iload #17
    //   3127: bipush #8
    //   3129: if_icmpge -> 3149
    //   3132: aload #16
    //   3134: iload #17
    //   3136: aload #9
    //   3138: iload #17
    //   3140: iaload
    //   3141: iastore
    //   3142: iinc #17, 1
    //   3145: iload_2
    //   3146: ifeq -> 3125
    //   3149: iconst_0
    //   3150: istore #17
    //   3152: iload #17
    //   3154: bipush #64
    //   3156: if_icmpge -> 3647
    //   3159: iload #17
    //   3161: bipush #16
    //   3163: if_icmpge -> 3244
    //   3166: aload #15
    //   3168: iload #17
    //   3170: aload #11
    //   3172: iconst_4
    //   3173: iload #17
    //   3175: imul
    //   3176: baload
    //   3177: sipush #255
    //   3180: iand
    //   3181: bipush #24
    //   3183: ishl
    //   3184: aload #11
    //   3186: iconst_4
    //   3187: iload #17
    //   3189: imul
    //   3190: iconst_1
    //   3191: iadd
    //   3192: baload
    //   3193: sipush #255
    //   3196: iand
    //   3197: bipush #16
    //   3199: ishl
    //   3200: ior
    //   3201: aload #11
    //   3203: iconst_4
    //   3204: iload #17
    //   3206: imul
    //   3207: iconst_2
    //   3208: iadd
    //   3209: baload
    //   3210: sipush #255
    //   3213: iand
    //   3214: bipush #8
    //   3216: ishl
    //   3217: ior
    //   3218: aload #11
    //   3220: iconst_4
    //   3221: iload #17
    //   3223: imul
    //   3224: iconst_3
    //   3225: iadd
    //   3226: baload
    //   3227: sipush #255
    //   3230: iand
    //   3231: ior
    //   3232: iastore
    //   3233: iload_2
    //   3234: ifeq -> 3387
    //   3237: goto -> 3244
    //   3240: invokestatic a : (Ljava/lang/Throwable;)Ljava/lang/Throwable;
    //   3243: athrow
    //   3244: aload #15
    //   3246: iload #17
    //   3248: aload #15
    //   3250: iload #17
    //   3252: iconst_2
    //   3253: isub
    //   3254: iaload
    //   3255: bipush #17
    //   3257: iushr
    //   3258: aload #15
    //   3260: iload #17
    //   3262: iconst_2
    //   3263: isub
    //   3264: iaload
    //   3265: bipush #15
    //   3267: ishl
    //   3268: ior
    //   3269: aload #15
    //   3271: iload #17
    //   3273: iconst_2
    //   3274: isub
    //   3275: iaload
    //   3276: bipush #19
    //   3278: iushr
    //   3279: aload #15
    //   3281: iload #17
    //   3283: iconst_2
    //   3284: isub
    //   3285: iaload
    //   3286: bipush #13
    //   3288: ishl
    //   3289: ior
    //   3290: ixor
    //   3291: aload #15
    //   3293: iload #17
    //   3295: iconst_2
    //   3296: isub
    //   3297: iaload
    //   3298: bipush #10
    //   3300: iushr
    //   3301: ixor
    //   3302: aload #15
    //   3304: iload #17
    //   3306: bipush #7
    //   3308: isub
    //   3309: iaload
    //   3310: iadd
    //   3311: aload #15
    //   3313: iload #17
    //   3315: bipush #15
    //   3317: isub
    //   3318: iaload
    //   3319: bipush #7
    //   3321: iushr
    //   3322: aload #15
    //   3324: iload #17
    //   3326: bipush #15
    //   3328: isub
    //   3329: iaload
    //   3330: bipush #25
    //   3332: ishl
    //   3333: ior
    //   3334: aload #15
    //   3336: iload #17
    //   3338: bipush #15
    //   3340: isub
    //   3341: iaload
    //   3342: bipush #18
    //   3344: iushr
    //   3345: aload #15
    //   3347: iload #17
    //   3349: bipush #15
    //   3351: isub
    //   3352: iaload
    //   3353: bipush #14
    //   3355: ishl
    //   3356: ior
    //   3357: ixor
    //   3358: aload #15
    //   3360: iload #17
    //   3362: bipush #15
    //   3364: isub
    //   3365: iaload
    //   3366: iconst_3
    //   3367: iushr
    //   3368: ixor
    //   3369: iadd
    //   3370: aload #15
    //   3372: iload #17
    //   3374: bipush #16
    //   3376: isub
    //   3377: iaload
    //   3378: iadd
    //   3379: iastore
    //   3380: goto -> 3387
    //   3383: invokestatic a : (Ljava/lang/Throwable;)Ljava/lang/Throwable;
    //   3386: athrow
    //   3387: aload #16
    //   3389: bipush #7
    //   3391: iaload
    //   3392: aload #16
    //   3394: iconst_4
    //   3395: iaload
    //   3396: bipush #6
    //   3398: iushr
    //   3399: aload #16
    //   3401: iconst_4
    //   3402: iaload
    //   3403: bipush #26
    //   3405: ishl
    //   3406: ior
    //   3407: aload #16
    //   3409: iconst_4
    //   3410: iaload
    //   3411: bipush #11
    //   3413: iushr
    //   3414: aload #16
    //   3416: iconst_4
    //   3417: iaload
    //   3418: bipush #21
    //   3420: ishl
    //   3421: ior
    //   3422: ixor
    //   3423: aload #16
    //   3425: iconst_4
    //   3426: iaload
    //   3427: bipush #25
    //   3429: iushr
    //   3430: aload #16
    //   3432: iconst_4
    //   3433: iaload
    //   3434: bipush #7
    //   3436: ishl
    //   3437: ior
    //   3438: ixor
    //   3439: iadd
    //   3440: aload #16
    //   3442: bipush #6
    //   3444: iaload
    //   3445: aload #16
    //   3447: iconst_4
    //   3448: iaload
    //   3449: aload #16
    //   3451: iconst_5
    //   3452: iaload
    //   3453: aload #16
    //   3455: bipush #6
    //   3457: iaload
    //   3458: ixor
    //   3459: iand
    //   3460: ixor
    //   3461: iadd
    //   3462: aload #7
    //   3464: iload #17
    //   3466: iaload
    //   3467: iadd
    //   3468: aload #15
    //   3470: iload #17
    //   3472: iaload
    //   3473: iadd
    //   3474: istore #18
    //   3476: aload #16
    //   3478: iconst_0
    //   3479: iaload
    //   3480: iconst_2
    //   3481: iushr
    //   3482: aload #16
    //   3484: iconst_0
    //   3485: iaload
    //   3486: bipush #30
    //   3488: ishl
    //   3489: ior
    //   3490: aload #16
    //   3492: iconst_0
    //   3493: iaload
    //   3494: bipush #13
    //   3496: iushr
    //   3497: aload #16
    //   3499: iconst_0
    //   3500: iaload
    //   3501: bipush #19
    //   3503: ishl
    //   3504: ior
    //   3505: ixor
    //   3506: aload #16
    //   3508: iconst_0
    //   3509: iaload
    //   3510: bipush #22
    //   3512: iushr
    //   3513: aload #16
    //   3515: iconst_0
    //   3516: iaload
    //   3517: bipush #10
    //   3519: ishl
    //   3520: ior
    //   3521: ixor
    //   3522: aload #16
    //   3524: iconst_0
    //   3525: iaload
    //   3526: aload #16
    //   3528: iconst_1
    //   3529: iaload
    //   3530: iand
    //   3531: aload #16
    //   3533: iconst_2
    //   3534: iaload
    //   3535: aload #16
    //   3537: iconst_0
    //   3538: iaload
    //   3539: aload #16
    //   3541: iconst_1
    //   3542: iaload
    //   3543: ior
    //   3544: iand
    //   3545: ior
    //   3546: iadd
    //   3547: istore #19
    //   3549: aload #16
    //   3551: iconst_3
    //   3552: dup2
    //   3553: iaload
    //   3554: iload #18
    //   3556: iadd
    //   3557: iastore
    //   3558: aload #16
    //   3560: bipush #7
    //   3562: iload #18
    //   3564: iload #19
    //   3566: iadd
    //   3567: iastore
    //   3568: aload #16
    //   3570: bipush #7
    //   3572: iaload
    //   3573: istore #18
    //   3575: aload #16
    //   3577: bipush #7
    //   3579: aload #16
    //   3581: bipush #6
    //   3583: iaload
    //   3584: iastore
    //   3585: aload #16
    //   3587: bipush #6
    //   3589: aload #16
    //   3591: iconst_5
    //   3592: iaload
    //   3593: iastore
    //   3594: aload #16
    //   3596: iconst_5
    //   3597: aload #16
    //   3599: iconst_4
    //   3600: iaload
    //   3601: iastore
    //   3602: aload #16
    //   3604: iconst_4
    //   3605: aload #16
    //   3607: iconst_3
    //   3608: iaload
    //   3609: iastore
    //   3610: aload #16
    //   3612: iconst_3
    //   3613: aload #16
    //   3615: iconst_2
    //   3616: iaload
    //   3617: iastore
    //   3618: aload #16
    //   3620: iconst_2
    //   3621: aload #16
    //   3623: iconst_1
    //   3624: iaload
    //   3625: iastore
    //   3626: aload #16
    //   3628: iconst_1
    //   3629: aload #16
    //   3631: iconst_0
    //   3632: iaload
    //   3633: iastore
    //   3634: aload #16
    //   3636: iconst_0
    //   3637: iload #18
    //   3639: iastore
    //   3640: iinc #17, 1
    //   3643: iload_2
    //   3644: ifeq -> 3152
    //   3647: iconst_0
    //   3648: istore #17
    //   3650: iload #17
    //   3652: bipush #8
    //   3654: if_icmpge -> 3677
    //   3657: aload #9
    //   3659: iload #17
    //   3661: dup2
    //   3662: iaload
    //   3663: aload #16
    //   3665: iload #17
    //   3667: iaload
    //   3668: iadd
    //   3669: iastore
    //   3670: iinc #17, 1
    //   3673: iload_2
    //   3674: ifeq -> 3650
    //   3677: iinc #14, 64
    //   3680: iinc #12, -64
    //   3683: iload_2
    //   3684: ifeq -> 3073
    //   3687: iload #12
    //   3689: ifle -> 3725
    //   3692: iconst_0
    //   3693: istore #15
    //   3695: iload #15
    //   3697: iload #12
    //   3699: if_icmpge -> 3725
    //   3702: aload #10
    //   3704: iload #13
    //   3706: iload #15
    //   3708: iadd
    //   3709: aload #4
    //   3711: iload #14
    //   3713: iload #15
    //   3715: iadd
    //   3716: baload
    //   3717: bastore
    //   3718: iinc #15, 1
    //   3721: iload_2
    //   3722: ifeq -> 3695
    //   3725: aload #8
    //   3727: iconst_0
    //   3728: iaload
    //   3729: bipush #29
    //   3731: iushr
    //   3732: aload #8
    //   3734: iconst_1
    //   3735: iaload
    //   3736: iconst_3
    //   3737: ishl
    //   3738: ior
    //   3739: istore #15
    //   3741: aload #8
    //   3743: iconst_0
    //   3744: iaload
    //   3745: iconst_3
    //   3746: ishl
    //   3747: istore #16
    //   3749: aload #8
    //   3751: iconst_0
    //   3752: iaload
    //   3753: bipush #63
    //   3755: iand
    //   3756: istore #17
    //   3758: iload #17
    //   3760: bipush #56
    //   3762: if_icmpge -> 3777
    //   3765: bipush #56
    //   3767: iload #17
    //   3769: isub
    //   3770: goto -> 3782
    //   3773: invokestatic a : (Ljava/lang/Throwable;)Ljava/lang/Throwable;
    //   3776: athrow
    //   3777: bipush #120
    //   3779: iload #17
    //   3781: isub
    //   3782: istore #18
    //   3784: aload #8
    //   3786: iconst_0
    //   3787: iaload
    //   3788: bipush #63
    //   3790: iand
    //   3791: istore #13
    //   3793: bipush #64
    //   3795: iload #13
    //   3797: isub
    //   3798: istore #19
    //   3800: aload #8
    //   3802: iconst_0
    //   3803: dup2
    //   3804: iaload
    //   3805: iload #18
    //   3807: iadd
    //   3808: iastore
    //   3809: aload #8
    //   3811: iconst_0
    //   3812: dup2
    //   3813: iaload
    //   3814: iconst_m1
    //   3815: iand
    //   3816: iastore
    //   3817: aload #8
    //   3819: iconst_0
    //   3820: iaload
    //   3821: iload #18
    //   3823: if_icmpge -> 3841
    //   3826: aload #8
    //   3828: iconst_1
    //   3829: dup2
    //   3830: iaload
    //   3831: iconst_1
    //   3832: iadd
    //   3833: iastore
    //   3834: goto -> 3841
    //   3837: invokestatic a : (Ljava/lang/Throwable;)Ljava/lang/Throwable;
    //   3840: athrow
    //   3841: iconst_0
    //   3842: istore #14
    //   3844: iload #13
    //   3846: ifle -> 4477
    //   3849: iload #18
    //   3851: iload #19
    //   3853: if_icmplt -> 4477
    //   3856: goto -> 3863
    //   3859: invokestatic a : (Ljava/lang/Throwable;)Ljava/lang/Throwable;
    //   3862: athrow
    //   3863: iconst_0
    //   3864: istore #20
    //   3866: iload #20
    //   3868: iload #19
    //   3870: if_icmpge -> 3893
    //   3873: aload #10
    //   3875: iload #13
    //   3877: iload #20
    //   3879: iadd
    //   3880: aload #6
    //   3882: iload #20
    //   3884: baload
    //   3885: bastore
    //   3886: iinc #20, 1
    //   3889: iload_2
    //   3890: ifeq -> 3866
    //   3893: bipush #64
    //   3895: newarray int
    //   3897: astore #20
    //   3899: bipush #8
    //   3901: newarray int
    //   3903: astore #21
    //   3905: iconst_0
    //   3906: istore #22
    //   3908: iload #22
    //   3910: bipush #8
    //   3912: if_icmpge -> 3932
    //   3915: aload #21
    //   3917: iload #22
    //   3919: aload #9
    //   3921: iload #22
    //   3923: iaload
    //   3924: iastore
    //   3925: iinc #22, 1
    //   3928: iload_2
    //   3929: ifeq -> 3908
    //   3932: iconst_0
    //   3933: istore #22
    //   3935: iload #22
    //   3937: bipush #64
    //   3939: if_icmpge -> 4430
    //   3942: iload #22
    //   3944: bipush #16
    //   3946: if_icmpge -> 4027
    //   3949: aload #20
    //   3951: iload #22
    //   3953: aload #10
    //   3955: iconst_4
    //   3956: iload #22
    //   3958: imul
    //   3959: baload
    //   3960: sipush #255
    //   3963: iand
    //   3964: bipush #24
    //   3966: ishl
    //   3967: aload #10
    //   3969: iconst_4
    //   3970: iload #22
    //   3972: imul
    //   3973: iconst_1
    //   3974: iadd
    //   3975: baload
    //   3976: sipush #255
    //   3979: iand
    //   3980: bipush #16
    //   3982: ishl
    //   3983: ior
    //   3984: aload #10
    //   3986: iconst_4
    //   3987: iload #22
    //   3989: imul
    //   3990: iconst_2
    //   3991: iadd
    //   3992: baload
    //   3993: sipush #255
    //   3996: iand
    //   3997: bipush #8
    //   3999: ishl
    //   4000: ior
    //   4001: aload #10
    //   4003: iconst_4
    //   4004: iload #22
    //   4006: imul
    //   4007: iconst_3
    //   4008: iadd
    //   4009: baload
    //   4010: sipush #255
    //   4013: iand
    //   4014: ior
    //   4015: iastore
    //   4016: iload_2
    //   4017: ifeq -> 4170
    //   4020: goto -> 4027
    //   4023: invokestatic a : (Ljava/lang/Throwable;)Ljava/lang/Throwable;
    //   4026: athrow
    //   4027: aload #20
    //   4029: iload #22
    //   4031: aload #20
    //   4033: iload #22
    //   4035: iconst_2
    //   4036: isub
    //   4037: iaload
    //   4038: bipush #17
    //   4040: iushr
    //   4041: aload #20
    //   4043: iload #22
    //   4045: iconst_2
    //   4046: isub
    //   4047: iaload
    //   4048: bipush #15
    //   4050: ishl
    //   4051: ior
    //   4052: aload #20
    //   4054: iload #22
    //   4056: iconst_2
    //   4057: isub
    //   4058: iaload
    //   4059: bipush #19
    //   4061: iushr
    //   4062: aload #20
    //   4064: iload #22
    //   4066: iconst_2
    //   4067: isub
    //   4068: iaload
    //   4069: bipush #13
    //   4071: ishl
    //   4072: ior
    //   4073: ixor
    //   4074: aload #20
    //   4076: iload #22
    //   4078: iconst_2
    //   4079: isub
    //   4080: iaload
    //   4081: bipush #10
    //   4083: iushr
    //   4084: ixor
    //   4085: aload #20
    //   4087: iload #22
    //   4089: bipush #7
    //   4091: isub
    //   4092: iaload
    //   4093: iadd
    //   4094: aload #20
    //   4096: iload #22
    //   4098: bipush #15
    //   4100: isub
    //   4101: iaload
    //   4102: bipush #7
    //   4104: iushr
    //   4105: aload #20
    //   4107: iload #22
    //   4109: bipush #15
    //   4111: isub
    //   4112: iaload
    //   4113: bipush #25
    //   4115: ishl
    //   4116: ior
    //   4117: aload #20
    //   4119: iload #22
    //   4121: bipush #15
    //   4123: isub
    //   4124: iaload
    //   4125: bipush #18
    //   4127: iushr
    //   4128: aload #20
    //   4130: iload #22
    //   4132: bipush #15
    //   4134: isub
    //   4135: iaload
    //   4136: bipush #14
    //   4138: ishl
    //   4139: ior
    //   4140: ixor
    //   4141: aload #20
    //   4143: iload #22
    //   4145: bipush #15
    //   4147: isub
    //   4148: iaload
    //   4149: iconst_3
    //   4150: iushr
    //   4151: ixor
    //   4152: iadd
    //   4153: aload #20
    //   4155: iload #22
    //   4157: bipush #16
    //   4159: isub
    //   4160: iaload
    //   4161: iadd
    //   4162: iastore
    //   4163: goto -> 4170
    //   4166: invokestatic a : (Ljava/lang/Throwable;)Ljava/lang/Throwable;
    //   4169: athrow
    //   4170: aload #21
    //   4172: bipush #7
    //   4174: iaload
    //   4175: aload #21
    //   4177: iconst_4
    //   4178: iaload
    //   4179: bipush #6
    //   4181: iushr
    //   4182: aload #21
    //   4184: iconst_4
    //   4185: iaload
    //   4186: bipush #26
    //   4188: ishl
    //   4189: ior
    //   4190: aload #21
    //   4192: iconst_4
    //   4193: iaload
    //   4194: bipush #11
    //   4196: iushr
    //   4197: aload #21
    //   4199: iconst_4
    //   4200: iaload
    //   4201: bipush #21
    //   4203: ishl
    //   4204: ior
    //   4205: ixor
    //   4206: aload #21
    //   4208: iconst_4
    //   4209: iaload
    //   4210: bipush #25
    //   4212: iushr
    //   4213: aload #21
    //   4215: iconst_4
    //   4216: iaload
    //   4217: bipush #7
    //   4219: ishl
    //   4220: ior
    //   4221: ixor
    //   4222: iadd
    //   4223: aload #21
    //   4225: bipush #6
    //   4227: iaload
    //   4228: aload #21
    //   4230: iconst_4
    //   4231: iaload
    //   4232: aload #21
    //   4234: iconst_5
    //   4235: iaload
    //   4236: aload #21
    //   4238: bipush #6
    //   4240: iaload
    //   4241: ixor
    //   4242: iand
    //   4243: ixor
    //   4244: iadd
    //   4245: aload #7
    //   4247: iload #22
    //   4249: iaload
    //   4250: iadd
    //   4251: aload #20
    //   4253: iload #22
    //   4255: iaload
    //   4256: iadd
    //   4257: istore #23
    //   4259: aload #21
    //   4261: iconst_0
    //   4262: iaload
    //   4263: iconst_2
    //   4264: iushr
    //   4265: aload #21
    //   4267: iconst_0
    //   4268: iaload
    //   4269: bipush #30
    //   4271: ishl
    //   4272: ior
    //   4273: aload #21
    //   4275: iconst_0
    //   4276: iaload
    //   4277: bipush #13
    //   4279: iushr
    //   4280: aload #21
    //   4282: iconst_0
    //   4283: iaload
    //   4284: bipush #19
    //   4286: ishl
    //   4287: ior
    //   4288: ixor
    //   4289: aload #21
    //   4291: iconst_0
    //   4292: iaload
    //   4293: bipush #22
    //   4295: iushr
    //   4296: aload #21
    //   4298: iconst_0
    //   4299: iaload
    //   4300: bipush #10
    //   4302: ishl
    //   4303: ior
    //   4304: ixor
    //   4305: aload #21
    //   4307: iconst_0
    //   4308: iaload
    //   4309: aload #21
    //   4311: iconst_1
    //   4312: iaload
    //   4313: iand
    //   4314: aload #21
    //   4316: iconst_2
    //   4317: iaload
    //   4318: aload #21
    //   4320: iconst_0
    //   4321: iaload
    //   4322: aload #21
    //   4324: iconst_1
    //   4325: iaload
    //   4326: ior
    //   4327: iand
    //   4328: ior
    //   4329: iadd
    //   4330: istore #24
    //   4332: aload #21
    //   4334: iconst_3
    //   4335: dup2
    //   4336: iaload
    //   4337: iload #23
    //   4339: iadd
    //   4340: iastore
    //   4341: aload #21
    //   4343: bipush #7
    //   4345: iload #23
    //   4347: iload #24
    //   4349: iadd
    //   4350: iastore
    //   4351: aload #21
    //   4353: bipush #7
    //   4355: iaload
    //   4356: istore #23
    //   4358: aload #21
    //   4360: bipush #7
    //   4362: aload #21
    //   4364: bipush #6
    //   4366: iaload
    //   4367: iastore
    //   4368: aload #21
    //   4370: bipush #6
    //   4372: aload #21
    //   4374: iconst_5
    //   4375: iaload
    //   4376: iastore
    //   4377: aload #21
    //   4379: iconst_5
    //   4380: aload #21
    //   4382: iconst_4
    //   4383: iaload
    //   4384: iastore
    //   4385: aload #21
    //   4387: iconst_4
    //   4388: aload #21
    //   4390: iconst_3
    //   4391: iaload
    //   4392: iastore
    //   4393: aload #21
    //   4395: iconst_3
    //   4396: aload #21
    //   4398: iconst_2
    //   4399: iaload
    //   4400: iastore
    //   4401: aload #21
    //   4403: iconst_2
    //   4404: aload #21
    //   4406: iconst_1
    //   4407: iaload
    //   4408: iastore
    //   4409: aload #21
    //   4411: iconst_1
    //   4412: aload #21
    //   4414: iconst_0
    //   4415: iaload
    //   4416: iastore
    //   4417: aload #21
    //   4419: iconst_0
    //   4420: iload #23
    //   4422: iastore
    //   4423: iinc #22, 1
    //   4426: iload_2
    //   4427: ifeq -> 3935
    //   4430: iconst_0
    //   4431: istore #22
    //   4433: iload #22
    //   4435: bipush #8
    //   4437: if_icmpge -> 4460
    //   4440: aload #9
    //   4442: iload #22
    //   4444: dup2
    //   4445: iaload
    //   4446: aload #21
    //   4448: iload #22
    //   4450: iaload
    //   4451: iadd
    //   4452: iastore
    //   4453: iinc #22, 1
    //   4456: iload_2
    //   4457: ifeq -> 4433
    //   4460: iload #14
    //   4462: iload #19
    //   4464: iadd
    //   4465: istore #14
    //   4467: iload #18
    //   4469: iload #19
    //   4471: isub
    //   4472: istore #18
    //   4474: iconst_0
    //   4475: istore #13
    //   4477: iload #18
    //   4479: bipush #64
    //   4481: if_icmplt -> 5091
    //   4484: iconst_0
    //   4485: istore #20
    //   4487: iload #20
    //   4489: bipush #64
    //   4491: if_icmpge -> 4514
    //   4494: aload #11
    //   4496: iload #20
    //   4498: aload #6
    //   4500: iload #14
    //   4502: iload #20
    //   4504: iadd
    //   4505: baload
    //   4506: bastore
    //   4507: iinc #20, 1
    //   4510: iload_2
    //   4511: ifeq -> 4487
    //   4514: bipush #64
    //   4516: newarray int
    //   4518: astore #20
    //   4520: bipush #8
    //   4522: newarray int
    //   4524: astore #21
    //   4526: iconst_0
    //   4527: istore #22
    //   4529: iload #22
    //   4531: bipush #8
    //   4533: if_icmpge -> 4553
    //   4536: aload #21
    //   4538: iload #22
    //   4540: aload #9
    //   4542: iload #22
    //   4544: iaload
    //   4545: iastore
    //   4546: iinc #22, 1
    //   4549: iload_2
    //   4550: ifeq -> 4529
    //   4553: iconst_0
    //   4554: istore #22
    //   4556: iload #22
    //   4558: bipush #64
    //   4560: if_icmpge -> 5051
    //   4563: iload #22
    //   4565: bipush #16
    //   4567: if_icmpge -> 4648
    //   4570: aload #20
    //   4572: iload #22
    //   4574: aload #11
    //   4576: iconst_4
    //   4577: iload #22
    //   4579: imul
    //   4580: baload
    //   4581: sipush #255
    //   4584: iand
    //   4585: bipush #24
    //   4587: ishl
    //   4588: aload #11
    //   4590: iconst_4
    //   4591: iload #22
    //   4593: imul
    //   4594: iconst_1
    //   4595: iadd
    //   4596: baload
    //   4597: sipush #255
    //   4600: iand
    //   4601: bipush #16
    //   4603: ishl
    //   4604: ior
    //   4605: aload #11
    //   4607: iconst_4
    //   4608: iload #22
    //   4610: imul
    //   4611: iconst_2
    //   4612: iadd
    //   4613: baload
    //   4614: sipush #255
    //   4617: iand
    //   4618: bipush #8
    //   4620: ishl
    //   4621: ior
    //   4622: aload #11
    //   4624: iconst_4
    //   4625: iload #22
    //   4627: imul
    //   4628: iconst_3
    //   4629: iadd
    //   4630: baload
    //   4631: sipush #255
    //   4634: iand
    //   4635: ior
    //   4636: iastore
    //   4637: iload_2
    //   4638: ifeq -> 4791
    //   4641: goto -> 4648
    //   4644: invokestatic a : (Ljava/lang/Throwable;)Ljava/lang/Throwable;
    //   4647: athrow
    //   4648: aload #20
    //   4650: iload #22
    //   4652: aload #20
    //   4654: iload #22
    //   4656: iconst_2
    //   4657: isub
    //   4658: iaload
    //   4659: bipush #17
    //   4661: iushr
    //   4662: aload #20
    //   4664: iload #22
    //   4666: iconst_2
    //   4667: isub
    //   4668: iaload
    //   4669: bipush #15
    //   4671: ishl
    //   4672: ior
    //   4673: aload #20
    //   4675: iload #22
    //   4677: iconst_2
    //   4678: isub
    //   4679: iaload
    //   4680: bipush #19
    //   4682: iushr
    //   4683: aload #20
    //   4685: iload #22
    //   4687: iconst_2
    //   4688: isub
    //   4689: iaload
    //   4690: bipush #13
    //   4692: ishl
    //   4693: ior
    //   4694: ixor
    //   4695: aload #20
    //   4697: iload #22
    //   4699: iconst_2
    //   4700: isub
    //   4701: iaload
    //   4702: bipush #10
    //   4704: iushr
    //   4705: ixor
    //   4706: aload #20
    //   4708: iload #22
    //   4710: bipush #7
    //   4712: isub
    //   4713: iaload
    //   4714: iadd
    //   4715: aload #20
    //   4717: iload #22
    //   4719: bipush #15
    //   4721: isub
    //   4722: iaload
    //   4723: bipush #7
    //   4725: iushr
    //   4726: aload #20
    //   4728: iload #22
    //   4730: bipush #15
    //   4732: isub
    //   4733: iaload
    //   4734: bipush #25
    //   4736: ishl
    //   4737: ior
    //   4738: aload #20
    //   4740: iload #22
    //   4742: bipush #15
    //   4744: isub
    //   4745: iaload
    //   4746: bipush #18
    //   4748: iushr
    //   4749: aload #20
    //   4751: iload #22
    //   4753: bipush #15
    //   4755: isub
    //   4756: iaload
    //   4757: bipush #14
    //   4759: ishl
    //   4760: ior
    //   4761: ixor
    //   4762: aload #20
    //   4764: iload #22
    //   4766: bipush #15
    //   4768: isub
    //   4769: iaload
    //   4770: iconst_3
    //   4771: iushr
    //   4772: ixor
    //   4773: iadd
    //   4774: aload #20
    //   4776: iload #22
    //   4778: bipush #16
    //   4780: isub
    //   4781: iaload
    //   4782: iadd
    //   4783: iastore
    //   4784: goto -> 4791
    //   4787: invokestatic a : (Ljava/lang/Throwable;)Ljava/lang/Throwable;
    //   4790: athrow
    //   4791: aload #21
    //   4793: bipush #7
    //   4795: iaload
    //   4796: aload #21
    //   4798: iconst_4
    //   4799: iaload
    //   4800: bipush #6
    //   4802: iushr
    //   4803: aload #21
    //   4805: iconst_4
    //   4806: iaload
    //   4807: bipush #26
    //   4809: ishl
    //   4810: ior
    //   4811: aload #21
    //   4813: iconst_4
    //   4814: iaload
    //   4815: bipush #11
    //   4817: iushr
    //   4818: aload #21
    //   4820: iconst_4
    //   4821: iaload
    //   4822: bipush #21
    //   4824: ishl
    //   4825: ior
    //   4826: ixor
    //   4827: aload #21
    //   4829: iconst_4
    //   4830: iaload
    //   4831: bipush #25
    //   4833: iushr
    //   4834: aload #21
    //   4836: iconst_4
    //   4837: iaload
    //   4838: bipush #7
    //   4840: ishl
    //   4841: ior
    //   4842: ixor
    //   4843: iadd
    //   4844: aload #21
    //   4846: bipush #6
    //   4848: iaload
    //   4849: aload #21
    //   4851: iconst_4
    //   4852: iaload
    //   4853: aload #21
    //   4855: iconst_5
    //   4856: iaload
    //   4857: aload #21
    //   4859: bipush #6
    //   4861: iaload
    //   4862: ixor
    //   4863: iand
    //   4864: ixor
    //   4865: iadd
    //   4866: aload #7
    //   4868: iload #22
    //   4870: iaload
    //   4871: iadd
    //   4872: aload #20
    //   4874: iload #22
    //   4876: iaload
    //   4877: iadd
    //   4878: istore #23
    //   4880: aload #21
    //   4882: iconst_0
    //   4883: iaload
    //   4884: iconst_2
    //   4885: iushr
    //   4886: aload #21
    //   4888: iconst_0
    //   4889: iaload
    //   4890: bipush #30
    //   4892: ishl
    //   4893: ior
    //   4894: aload #21
    //   4896: iconst_0
    //   4897: iaload
    //   4898: bipush #13
    //   4900: iushr
    //   4901: aload #21
    //   4903: iconst_0
    //   4904: iaload
    //   4905: bipush #19
    //   4907: ishl
    //   4908: ior
    //   4909: ixor
    //   4910: aload #21
    //   4912: iconst_0
    //   4913: iaload
    //   4914: bipush #22
    //   4916: iushr
    //   4917: aload #21
    //   4919: iconst_0
    //   4920: iaload
    //   4921: bipush #10
    //   4923: ishl
    //   4924: ior
    //   4925: ixor
    //   4926: aload #21
    //   4928: iconst_0
    //   4929: iaload
    //   4930: aload #21
    //   4932: iconst_1
    //   4933: iaload
    //   4934: iand
    //   4935: aload #21
    //   4937: iconst_2
    //   4938: iaload
    //   4939: aload #21
    //   4941: iconst_0
    //   4942: iaload
    //   4943: aload #21
    //   4945: iconst_1
    //   4946: iaload
    //   4947: ior
    //   4948: iand
    //   4949: ior
    //   4950: iadd
    //   4951: istore #24
    //   4953: aload #21
    //   4955: iconst_3
    //   4956: dup2
    //   4957: iaload
    //   4958: iload #23
    //   4960: iadd
    //   4961: iastore
    //   4962: aload #21
    //   4964: bipush #7
    //   4966: iload #23
    //   4968: iload #24
    //   4970: iadd
    //   4971: iastore
    //   4972: aload #21
    //   4974: bipush #7
    //   4976: iaload
    //   4977: istore #23
    //   4979: aload #21
    //   4981: bipush #7
    //   4983: aload #21
    //   4985: bipush #6
    //   4987: iaload
    //   4988: iastore
    //   4989: aload #21
    //   4991: bipush #6
    //   4993: aload #21
    //   4995: iconst_5
    //   4996: iaload
    //   4997: iastore
    //   4998: aload #21
    //   5000: iconst_5
    //   5001: aload #21
    //   5003: iconst_4
    //   5004: iaload
    //   5005: iastore
    //   5006: aload #21
    //   5008: iconst_4
    //   5009: aload #21
    //   5011: iconst_3
    //   5012: iaload
    //   5013: iastore
    //   5014: aload #21
    //   5016: iconst_3
    //   5017: aload #21
    //   5019: iconst_2
    //   5020: iaload
    //   5021: iastore
    //   5022: aload #21
    //   5024: iconst_2
    //   5025: aload #21
    //   5027: iconst_1
    //   5028: iaload
    //   5029: iastore
    //   5030: aload #21
    //   5032: iconst_1
    //   5033: aload #21
    //   5035: iconst_0
    //   5036: iaload
    //   5037: iastore
    //   5038: aload #21
    //   5040: iconst_0
    //   5041: iload #23
    //   5043: iastore
    //   5044: iinc #22, 1
    //   5047: iload_2
    //   5048: ifeq -> 4556
    //   5051: iconst_0
    //   5052: istore #22
    //   5054: iload #22
    //   5056: bipush #8
    //   5058: if_icmpge -> 5081
    //   5061: aload #9
    //   5063: iload #22
    //   5065: dup2
    //   5066: iaload
    //   5067: aload #21
    //   5069: iload #22
    //   5071: iaload
    //   5072: iadd
    //   5073: iastore
    //   5074: iinc #22, 1
    //   5077: iload_2
    //   5078: ifeq -> 5054
    //   5081: iinc #14, 64
    //   5084: iinc #18, -64
    //   5087: iload_2
    //   5088: ifeq -> 4477
    //   5091: iload #18
    //   5093: ifle -> 5129
    //   5096: iconst_0
    //   5097: istore #20
    //   5099: iload #20
    //   5101: iload #18
    //   5103: if_icmpge -> 5129
    //   5106: aload #10
    //   5108: iload #13
    //   5110: iload #20
    //   5112: iadd
    //   5113: aload #6
    //   5115: iload #14
    //   5117: iload #20
    //   5119: iadd
    //   5120: baload
    //   5121: bastore
    //   5122: iinc #20, 1
    //   5125: iload_2
    //   5126: ifeq -> 5099
    //   5129: bipush #8
    //   5131: newarray byte
    //   5133: astore #20
    //   5135: aload #20
    //   5137: iconst_0
    //   5138: iload #15
    //   5140: bipush #24
    //   5142: iushr
    //   5143: i2b
    //   5144: bastore
    //   5145: aload #20
    //   5147: iconst_1
    //   5148: iload #15
    //   5150: bipush #16
    //   5152: iushr
    //   5153: i2b
    //   5154: bastore
    //   5155: aload #20
    //   5157: iconst_2
    //   5158: iload #15
    //   5160: bipush #8
    //   5162: iushr
    //   5163: i2b
    //   5164: bastore
    //   5165: aload #20
    //   5167: iconst_3
    //   5168: iload #15
    //   5170: i2b
    //   5171: bastore
    //   5172: aload #20
    //   5174: iconst_4
    //   5175: iload #16
    //   5177: bipush #24
    //   5179: iushr
    //   5180: i2b
    //   5181: bastore
    //   5182: aload #20
    //   5184: iconst_5
    //   5185: iload #16
    //   5187: bipush #16
    //   5189: iushr
    //   5190: i2b
    //   5191: bastore
    //   5192: aload #20
    //   5194: bipush #6
    //   5196: iload #16
    //   5198: bipush #8
    //   5200: iushr
    //   5201: i2b
    //   5202: bastore
    //   5203: aload #20
    //   5205: bipush #7
    //   5207: iload #16
    //   5209: i2b
    //   5210: bastore
    //   5211: bipush #8
    //   5213: istore #12
    //   5215: aload #8
    //   5217: iconst_0
    //   5218: iaload
    //   5219: bipush #63
    //   5221: iand
    //   5222: istore #13
    //   5224: bipush #64
    //   5226: iload #13
    //   5228: isub
    //   5229: istore #19
    //   5231: aload #8
    //   5233: iconst_0
    //   5234: dup2
    //   5235: iaload
    //   5236: iload #12
    //   5238: iadd
    //   5239: iastore
    //   5240: aload #8
    //   5242: iconst_0
    //   5243: dup2
    //   5244: iaload
    //   5245: iconst_m1
    //   5246: iand
    //   5247: iastore
    //   5248: aload #8
    //   5250: iconst_0
    //   5251: iaload
    //   5252: iload #12
    //   5254: if_icmpge -> 5272
    //   5257: aload #8
    //   5259: iconst_1
    //   5260: dup2
    //   5261: iaload
    //   5262: iconst_1
    //   5263: iadd
    //   5264: iastore
    //   5265: goto -> 5272
    //   5268: invokestatic a : (Ljava/lang/Throwable;)Ljava/lang/Throwable;
    //   5271: athrow
    //   5272: iload #13
    //   5274: ifle -> 5888
    //   5277: iload #12
    //   5279: iload #19
    //   5281: if_icmplt -> 5888
    //   5284: goto -> 5291
    //   5287: invokestatic a : (Ljava/lang/Throwable;)Ljava/lang/Throwable;
    //   5290: athrow
    //   5291: iconst_0
    //   5292: istore #21
    //   5294: iload #21
    //   5296: iload #19
    //   5298: if_icmpge -> 5321
    //   5301: aload #10
    //   5303: iload #13
    //   5305: iload #21
    //   5307: iadd
    //   5308: aload #20
    //   5310: iload #21
    //   5312: baload
    //   5313: bastore
    //   5314: iinc #21, 1
    //   5317: iload_2
    //   5318: ifeq -> 5294
    //   5321: bipush #64
    //   5323: newarray int
    //   5325: astore #21
    //   5327: bipush #8
    //   5329: newarray int
    //   5331: astore #22
    //   5333: iconst_0
    //   5334: istore #23
    //   5336: iload #23
    //   5338: bipush #8
    //   5340: if_icmpge -> 5360
    //   5343: aload #22
    //   5345: iload #23
    //   5347: aload #9
    //   5349: iload #23
    //   5351: iaload
    //   5352: iastore
    //   5353: iinc #23, 1
    //   5356: iload_2
    //   5357: ifeq -> 5336
    //   5360: iconst_0
    //   5361: istore #23
    //   5363: iload #23
    //   5365: bipush #64
    //   5367: if_icmpge -> 5858
    //   5370: iload #23
    //   5372: bipush #16
    //   5374: if_icmpge -> 5455
    //   5377: aload #21
    //   5379: iload #23
    //   5381: aload #10
    //   5383: iconst_4
    //   5384: iload #23
    //   5386: imul
    //   5387: baload
    //   5388: sipush #255
    //   5391: iand
    //   5392: bipush #24
    //   5394: ishl
    //   5395: aload #10
    //   5397: iconst_4
    //   5398: iload #23
    //   5400: imul
    //   5401: iconst_1
    //   5402: iadd
    //   5403: baload
    //   5404: sipush #255
    //   5407: iand
    //   5408: bipush #16
    //   5410: ishl
    //   5411: ior
    //   5412: aload #10
    //   5414: iconst_4
    //   5415: iload #23
    //   5417: imul
    //   5418: iconst_2
    //   5419: iadd
    //   5420: baload
    //   5421: sipush #255
    //   5424: iand
    //   5425: bipush #8
    //   5427: ishl
    //   5428: ior
    //   5429: aload #10
    //   5431: iconst_4
    //   5432: iload #23
    //   5434: imul
    //   5435: iconst_3
    //   5436: iadd
    //   5437: baload
    //   5438: sipush #255
    //   5441: iand
    //   5442: ior
    //   5443: iastore
    //   5444: iload_2
    //   5445: ifeq -> 5598
    //   5448: goto -> 5455
    //   5451: invokestatic a : (Ljava/lang/Throwable;)Ljava/lang/Throwable;
    //   5454: athrow
    //   5455: aload #21
    //   5457: iload #23
    //   5459: aload #21
    //   5461: iload #23
    //   5463: iconst_2
    //   5464: isub
    //   5465: iaload
    //   5466: bipush #17
    //   5468: iushr
    //   5469: aload #21
    //   5471: iload #23
    //   5473: iconst_2
    //   5474: isub
    //   5475: iaload
    //   5476: bipush #15
    //   5478: ishl
    //   5479: ior
    //   5480: aload #21
    //   5482: iload #23
    //   5484: iconst_2
    //   5485: isub
    //   5486: iaload
    //   5487: bipush #19
    //   5489: iushr
    //   5490: aload #21
    //   5492: iload #23
    //   5494: iconst_2
    //   5495: isub
    //   5496: iaload
    //   5497: bipush #13
    //   5499: ishl
    //   5500: ior
    //   5501: ixor
    //   5502: aload #21
    //   5504: iload #23
    //   5506: iconst_2
    //   5507: isub
    //   5508: iaload
    //   5509: bipush #10
    //   5511: iushr
    //   5512: ixor
    //   5513: aload #21
    //   5515: iload #23
    //   5517: bipush #7
    //   5519: isub
    //   5520: iaload
    //   5521: iadd
    //   5522: aload #21
    //   5524: iload #23
    //   5526: bipush #15
    //   5528: isub
    //   5529: iaload
    //   5530: bipush #7
    //   5532: iushr
    //   5533: aload #21
    //   5535: iload #23
    //   5537: bipush #15
    //   5539: isub
    //   5540: iaload
    //   5541: bipush #25
    //   5543: ishl
    //   5544: ior
    //   5545: aload #21
    //   5547: iload #23
    //   5549: bipush #15
    //   5551: isub
    //   5552: iaload
    //   5553: bipush #18
    //   5555: iushr
    //   5556: aload #21
    //   5558: iload #23
    //   5560: bipush #15
    //   5562: isub
    //   5563: iaload
    //   5564: bipush #14
    //   5566: ishl
    //   5567: ior
    //   5568: ixor
    //   5569: aload #21
    //   5571: iload #23
    //   5573: bipush #15
    //   5575: isub
    //   5576: iaload
    //   5577: iconst_3
    //   5578: iushr
    //   5579: ixor
    //   5580: iadd
    //   5581: aload #21
    //   5583: iload #23
    //   5585: bipush #16
    //   5587: isub
    //   5588: iaload
    //   5589: iadd
    //   5590: iastore
    //   5591: goto -> 5598
    //   5594: invokestatic a : (Ljava/lang/Throwable;)Ljava/lang/Throwable;
    //   5597: athrow
    //   5598: aload #22
    //   5600: bipush #7
    //   5602: iaload
    //   5603: aload #22
    //   5605: iconst_4
    //   5606: iaload
    //   5607: bipush #6
    //   5609: iushr
    //   5610: aload #22
    //   5612: iconst_4
    //   5613: iaload
    //   5614: bipush #26
    //   5616: ishl
    //   5617: ior
    //   5618: aload #22
    //   5620: iconst_4
    //   5621: iaload
    //   5622: bipush #11
    //   5624: iushr
    //   5625: aload #22
    //   5627: iconst_4
    //   5628: iaload
    //   5629: bipush #21
    //   5631: ishl
    //   5632: ior
    //   5633: ixor
    //   5634: aload #22
    //   5636: iconst_4
    //   5637: iaload
    //   5638: bipush #25
    //   5640: iushr
    //   5641: aload #22
    //   5643: iconst_4
    //   5644: iaload
    //   5645: bipush #7
    //   5647: ishl
    //   5648: ior
    //   5649: ixor
    //   5650: iadd
    //   5651: aload #22
    //   5653: bipush #6
    //   5655: iaload
    //   5656: aload #22
    //   5658: iconst_4
    //   5659: iaload
    //   5660: aload #22
    //   5662: iconst_5
    //   5663: iaload
    //   5664: aload #22
    //   5666: bipush #6
    //   5668: iaload
    //   5669: ixor
    //   5670: iand
    //   5671: ixor
    //   5672: iadd
    //   5673: aload #7
    //   5675: iload #23
    //   5677: iaload
    //   5678: iadd
    //   5679: aload #21
    //   5681: iload #23
    //   5683: iaload
    //   5684: iadd
    //   5685: istore #24
    //   5687: aload #22
    //   5689: iconst_0
    //   5690: iaload
    //   5691: iconst_2
    //   5692: iushr
    //   5693: aload #22
    //   5695: iconst_0
    //   5696: iaload
    //   5697: bipush #30
    //   5699: ishl
    //   5700: ior
    //   5701: aload #22
    //   5703: iconst_0
    //   5704: iaload
    //   5705: bipush #13
    //   5707: iushr
    //   5708: aload #22
    //   5710: iconst_0
    //   5711: iaload
    //   5712: bipush #19
    //   5714: ishl
    //   5715: ior
    //   5716: ixor
    //   5717: aload #22
    //   5719: iconst_0
    //   5720: iaload
    //   5721: bipush #22
    //   5723: iushr
    //   5724: aload #22
    //   5726: iconst_0
    //   5727: iaload
    //   5728: bipush #10
    //   5730: ishl
    //   5731: ior
    //   5732: ixor
    //   5733: aload #22
    //   5735: iconst_0
    //   5736: iaload
    //   5737: aload #22
    //   5739: iconst_1
    //   5740: iaload
    //   5741: iand
    //   5742: aload #22
    //   5744: iconst_2
    //   5745: iaload
    //   5746: aload #22
    //   5748: iconst_0
    //   5749: iaload
    //   5750: aload #22
    //   5752: iconst_1
    //   5753: iaload
    //   5754: ior
    //   5755: iand
    //   5756: ior
    //   5757: iadd
    //   5758: istore #25
    //   5760: aload #22
    //   5762: iconst_3
    //   5763: dup2
    //   5764: iaload
    //   5765: iload #24
    //   5767: iadd
    //   5768: iastore
    //   5769: aload #22
    //   5771: bipush #7
    //   5773: iload #24
    //   5775: iload #25
    //   5777: iadd
    //   5778: iastore
    //   5779: aload #22
    //   5781: bipush #7
    //   5783: iaload
    //   5784: istore #24
    //   5786: aload #22
    //   5788: bipush #7
    //   5790: aload #22
    //   5792: bipush #6
    //   5794: iaload
    //   5795: iastore
    //   5796: aload #22
    //   5798: bipush #6
    //   5800: aload #22
    //   5802: iconst_5
    //   5803: iaload
    //   5804: iastore
    //   5805: aload #22
    //   5807: iconst_5
    //   5808: aload #22
    //   5810: iconst_4
    //   5811: iaload
    //   5812: iastore
    //   5813: aload #22
    //   5815: iconst_4
    //   5816: aload #22
    //   5818: iconst_3
    //   5819: iaload
    //   5820: iastore
    //   5821: aload #22
    //   5823: iconst_3
    //   5824: aload #22
    //   5826: iconst_2
    //   5827: iaload
    //   5828: iastore
    //   5829: aload #22
    //   5831: iconst_2
    //   5832: aload #22
    //   5834: iconst_1
    //   5835: iaload
    //   5836: iastore
    //   5837: aload #22
    //   5839: iconst_1
    //   5840: aload #22
    //   5842: iconst_0
    //   5843: iaload
    //   5844: iastore
    //   5845: aload #22
    //   5847: iconst_0
    //   5848: iload #24
    //   5850: iastore
    //   5851: iinc #23, 1
    //   5854: iload_2
    //   5855: ifeq -> 5363
    //   5858: iconst_0
    //   5859: istore #23
    //   5861: iload #23
    //   5863: bipush #8
    //   5865: if_icmpge -> 5888
    //   5868: aload #9
    //   5870: iload #23
    //   5872: dup2
    //   5873: iaload
    //   5874: aload #22
    //   5876: iload #23
    //   5878: iaload
    //   5879: iadd
    //   5880: iastore
    //   5881: iinc #23, 1
    //   5884: iload_2
    //   5885: ifeq -> 5861
    //   5888: bipush #32
    //   5890: newarray byte
    //   5892: astore #5
    //   5894: sipush #-23393
    //   5897: aload #5
    //   5899: iconst_0
    //   5900: aload #9
    //   5902: iconst_0
    //   5903: iaload
    //   5904: bipush #24
    //   5906: iushr
    //   5907: i2b
    //   5908: bastore
    //   5909: sipush #-23432
    //   5912: aload #5
    //   5914: iconst_1
    //   5915: aload #9
    //   5917: iconst_0
    //   5918: iaload
    //   5919: bipush #16
    //   5921: iushr
    //   5922: i2b
    //   5923: bastore
    //   5924: aload #5
    //   5926: iconst_2
    //   5927: aload #9
    //   5929: iconst_0
    //   5930: iaload
    //   5931: bipush #8
    //   5933: iushr
    //   5934: i2b
    //   5935: bastore
    //   5936: aload #5
    //   5938: iconst_3
    //   5939: aload #9
    //   5941: iconst_0
    //   5942: iaload
    //   5943: i2b
    //   5944: bastore
    //   5945: aload #5
    //   5947: iconst_4
    //   5948: aload #9
    //   5950: iconst_1
    //   5951: iaload
    //   5952: bipush #24
    //   5954: iushr
    //   5955: i2b
    //   5956: bastore
    //   5957: aload #5
    //   5959: iconst_5
    //   5960: aload #9
    //   5962: iconst_1
    //   5963: iaload
    //   5964: bipush #16
    //   5966: iushr
    //   5967: i2b
    //   5968: bastore
    //   5969: aload #5
    //   5971: bipush #6
    //   5973: aload #9
    //   5975: iconst_1
    //   5976: iaload
    //   5977: bipush #8
    //   5979: iushr
    //   5980: i2b
    //   5981: bastore
    //   5982: aload #5
    //   5984: bipush #7
    //   5986: aload #9
    //   5988: iconst_1
    //   5989: iaload
    //   5990: i2b
    //   5991: bastore
    //   5992: aload #5
    //   5994: bipush #8
    //   5996: aload #9
    //   5998: iconst_2
    //   5999: iaload
    //   6000: bipush #24
    //   6002: iushr
    //   6003: i2b
    //   6004: bastore
    //   6005: aload #5
    //   6007: bipush #9
    //   6009: aload #9
    //   6011: iconst_2
    //   6012: iaload
    //   6013: bipush #16
    //   6015: iushr
    //   6016: i2b
    //   6017: bastore
    //   6018: aload #5
    //   6020: bipush #10
    //   6022: aload #9
    //   6024: iconst_2
    //   6025: iaload
    //   6026: bipush #8
    //   6028: iushr
    //   6029: i2b
    //   6030: bastore
    //   6031: aload #5
    //   6033: bipush #11
    //   6035: aload #9
    //   6037: iconst_2
    //   6038: iaload
    //   6039: i2b
    //   6040: bastore
    //   6041: aload #5
    //   6043: bipush #12
    //   6045: aload #9
    //   6047: iconst_3
    //   6048: iaload
    //   6049: bipush #24
    //   6051: iushr
    //   6052: i2b
    //   6053: bastore
    //   6054: aload #5
    //   6056: bipush #13
    //   6058: aload #9
    //   6060: iconst_3
    //   6061: iaload
    //   6062: bipush #16
    //   6064: iushr
    //   6065: i2b
    //   6066: bastore
    //   6067: aload #5
    //   6069: bipush #14
    //   6071: aload #9
    //   6073: iconst_3
    //   6074: iaload
    //   6075: bipush #8
    //   6077: iushr
    //   6078: i2b
    //   6079: bastore
    //   6080: aload #5
    //   6082: bipush #15
    //   6084: aload #9
    //   6086: iconst_3
    //   6087: iaload
    //   6088: i2b
    //   6089: bastore
    //   6090: aload #5
    //   6092: bipush #16
    //   6094: aload #9
    //   6096: iconst_4
    //   6097: iaload
    //   6098: bipush #24
    //   6100: iushr
    //   6101: i2b
    //   6102: bastore
    //   6103: aload #5
    //   6105: bipush #17
    //   6107: aload #9
    //   6109: iconst_4
    //   6110: iaload
    //   6111: bipush #16
    //   6113: iushr
    //   6114: i2b
    //   6115: bastore
    //   6116: aload #5
    //   6118: bipush #18
    //   6120: aload #9
    //   6122: iconst_4
    //   6123: iaload
    //   6124: bipush #8
    //   6126: iushr
    //   6127: i2b
    //   6128: bastore
    //   6129: aload #5
    //   6131: bipush #19
    //   6133: aload #9
    //   6135: iconst_4
    //   6136: iaload
    //   6137: i2b
    //   6138: bastore
    //   6139: aload #5
    //   6141: bipush #20
    //   6143: aload #9
    //   6145: iconst_5
    //   6146: iaload
    //   6147: bipush #24
    //   6149: iushr
    //   6150: i2b
    //   6151: bastore
    //   6152: aload #5
    //   6154: bipush #21
    //   6156: aload #9
    //   6158: iconst_5
    //   6159: iaload
    //   6160: bipush #16
    //   6162: iushr
    //   6163: i2b
    //   6164: bastore
    //   6165: aload #5
    //   6167: bipush #22
    //   6169: aload #9
    //   6171: iconst_5
    //   6172: iaload
    //   6173: bipush #8
    //   6175: iushr
    //   6176: i2b
    //   6177: bastore
    //   6178: aload #5
    //   6180: bipush #23
    //   6182: aload #9
    //   6184: iconst_5
    //   6185: iaload
    //   6186: i2b
    //   6187: bastore
    //   6188: aload #5
    //   6190: bipush #24
    //   6192: aload #9
    //   6194: bipush #6
    //   6196: iaload
    //   6197: bipush #24
    //   6199: iushr
    //   6200: i2b
    //   6201: bastore
    //   6202: aload #5
    //   6204: bipush #25
    //   6206: aload #9
    //   6208: bipush #6
    //   6210: iaload
    //   6211: bipush #16
    //   6213: iushr
    //   6214: i2b
    //   6215: bastore
    //   6216: aload #5
    //   6218: bipush #26
    //   6220: aload #9
    //   6222: bipush #6
    //   6224: iaload
    //   6225: bipush #8
    //   6227: iushr
    //   6228: i2b
    //   6229: bastore
    //   6230: aload #5
    //   6232: bipush #27
    //   6234: aload #9
    //   6236: bipush #6
    //   6238: iaload
    //   6239: i2b
    //   6240: bastore
    //   6241: aload #5
    //   6243: bipush #28
    //   6245: aload #9
    //   6247: bipush #7
    //   6249: iaload
    //   6250: bipush #24
    //   6252: iushr
    //   6253: i2b
    //   6254: bastore
    //   6255: aload #5
    //   6257: bipush #29
    //   6259: aload #9
    //   6261: bipush #7
    //   6263: iaload
    //   6264: bipush #16
    //   6266: iushr
    //   6267: i2b
    //   6268: bastore
    //   6269: aload #5
    //   6271: bipush #30
    //   6273: aload #9
    //   6275: bipush #7
    //   6277: iaload
    //   6278: bipush #8
    //   6280: iushr
    //   6281: i2b
    //   6282: bastore
    //   6283: aload #5
    //   6285: bipush #31
    //   6287: aload #9
    //   6289: bipush #7
    //   6291: iaload
    //   6292: i2b
    //   6293: bastore
    //   6294: new java/math/BigInteger
    //   6297: dup
    //   6298: aload #5
    //   6300: invokespecial <init> : ([B)V
    //   6303: invokevirtual abs : ()Ljava/math/BigInteger;
    //   6306: putstatic burp/Zl_f.ZI : Ljava/lang/Object;
    //   6309: invokestatic a : (II)Ljava/lang/String;
    //   6312: iconst_1
    //   6313: ldc burp/Zle4
    //   6315: invokevirtual getClassLoader : ()Ljava/lang/ClassLoader;
    //   6318: invokestatic forName : (Ljava/lang/String;ZLjava/lang/ClassLoader;)Ljava/lang/Class;
    //   6321: invokevirtual getDeclaredFields : ()[Ljava/lang/reflect/Field;
    //   6324: astore #4
    //   6326: aload #4
    //   6328: arraylength
    //   6329: istore #5
    //   6331: iconst_0
    //   6332: istore #6
    //   6334: iload #6
    //   6336: iload #5
    //   6338: if_icmpge -> 6476
    //   6341: aload #4
    //   6343: iload #6
    //   6345: aaload
    //   6346: astore #7
    //   6348: aload #7
    //   6350: invokevirtual getModifiers : ()I
    //   6353: invokestatic isStatic : (I)Z
    //   6356: ifne -> 6366
    //   6359: goto -> 6469
    //   6362: invokestatic a : (Ljava/lang/Throwable;)Ljava/lang/Throwable;
    //   6365: athrow
    //   6366: aload #7
    //   6368: invokevirtual getType : ()Ljava/lang/Class;
    //   6371: astore #8
    //   6373: aload #8
    //   6375: ifnull -> 6456
    //   6378: aload #8
    //   6380: invokevirtual isPrimitive : ()Z
    //   6383: ifne -> 6456
    //   6386: goto -> 6393
    //   6389: invokestatic a : (Ljava/lang/Throwable;)Ljava/lang/Throwable;
    //   6392: athrow
    //   6393: aload #8
    //   6395: invokevirtual getPackage : ()Ljava/lang/Package;
    //   6398: ifnull -> 6456
    //   6401: goto -> 6408
    //   6404: invokestatic a : (Ljava/lang/Throwable;)Ljava/lang/Throwable;
    //   6407: athrow
    //   6408: aload #8
    //   6410: invokevirtual getPackage : ()Ljava/lang/Package;
    //   6413: invokevirtual getName : ()Ljava/lang/String;
    //   6416: ifnull -> 6456
    //   6419: goto -> 6426
    //   6422: invokestatic a : (Ljava/lang/Throwable;)Ljava/lang/Throwable;
    //   6425: athrow
    //   6426: aload #8
    //   6428: invokevirtual getPackage : ()Ljava/lang/Package;
    //   6431: invokevirtual getName : ()Ljava/lang/String;
    //   6434: sipush #-23398
    //   6437: sipush #7522
    //   6440: invokestatic a : (II)Ljava/lang/String;
    //   6443: invokevirtual startsWith : (Ljava/lang/String;)Z
    //   6446: ifne -> 6456
    //   6449: goto -> 6456
    //   6452: invokestatic a : (Ljava/lang/Throwable;)Ljava/lang/Throwable;
    //   6455: athrow
    //   6456: aload #7
    //   6458: iconst_1
    //   6459: invokevirtual setAccessible : (Z)V
    //   6462: aload #7
    //   6464: aconst_null
    //   6465: invokevirtual get : (Ljava/lang/Object;)Ljava/lang/Object;
    //   6468: pop
    //   6469: iinc #6, 1
    //   6472: iload_2
    //   6473: ifeq -> 6334
    //   6476: sipush #-23417
    //   6479: sipush #-31959
    //   6482: invokestatic a : (II)Ljava/lang/String;
    //   6485: invokestatic forName : (Ljava/lang/String;)Ljava/lang/Class;
    //   6488: invokevirtual getDeclaredMethods : ()[Ljava/lang/reflect/Method;
    //   6491: astore #4
    //   6493: aload #4
    //   6495: arraylength
    //   6496: istore #5
    //   6498: iconst_0
    //   6499: istore #6
    //   6501: iload #6
    //   6503: iload #5
    //   6505: if_icmpge -> 6638
    //   6508: aload #4
    //   6510: iload #6
    //   6512: aaload
    //   6513: astore #7
    //   6515: aload #7
    //   6517: invokevirtual getParameterTypes : ()[Ljava/lang/Class;
    //   6520: pop
    //   6521: aload #7
    //   6523: invokevirtual getModifiers : ()I
    //   6526: invokestatic isStatic : (I)Z
    //   6529: ifeq -> 6624
    //   6532: aload #7
    //   6534: invokevirtual getParameterTypes : ()[Ljava/lang/Class;
    //   6537: arraylength
    //   6538: iconst_2
    //   6539: if_icmpne -> 6624
    //   6542: goto -> 6549
    //   6545: invokestatic a : (Ljava/lang/Throwable;)Ljava/lang/Throwable;
    //   6548: athrow
    //   6549: aload #7
    //   6551: invokevirtual getReturnType : ()Ljava/lang/Class;
    //   6554: getstatic java/lang/Void.TYPE : Ljava/lang/Class;
    //   6557: invokevirtual equals : (Ljava/lang/Object;)Z
    //   6560: ifeq -> 6624
    //   6563: goto -> 6570
    //   6566: invokestatic a : (Ljava/lang/Throwable;)Ljava/lang/Throwable;
    //   6569: athrow
    //   6570: aload #7
    //   6572: iconst_1
    //   6573: invokevirtual setAccessible : (Z)V
    //   6576: aload #7
    //   6578: aconst_null
    //   6579: iconst_2
    //   6580: anewarray java/lang/Object
    //   6583: dup
    //   6584: iconst_0
    //   6585: aload_0
    //   6586: aastore
    //   6587: dup
    //   6588: iconst_1
    //   6589: aload_1
    //   6590: ifnonnull -> 6608
    //   6593: goto -> 6600
    //   6596: invokestatic a : (Ljava/lang/Throwable;)Ljava/lang/Throwable;
    //   6599: athrow
    //   6600: aload_1
    //   6601: goto -> 6615
    //   6604: invokestatic a : (Ljava/lang/Throwable;)Ljava/lang/Throwable;
    //   6607: athrow
    //   6608: aload_1
    //   6609: checkcast [B
    //   6612: invokevirtual clone : ()Ljava/lang/Object;
    //   6615: aastore
    //   6616: invokevirtual invoke : (Ljava/lang/Object;[Ljava/lang/Object;)Ljava/lang/Object;
    //   6619: pop
    //   6620: iload_2
    //   6621: ifeq -> 6638
    //   6624: iinc #6, 1
    //   6627: iload_2
    //   6628: ifeq -> 6501
    //   6631: goto -> 6638
    //   6634: invokestatic a : (Ljava/lang/Throwable;)Ljava/lang/Throwable;
    //   6637: athrow
    //   6638: iconst_0
    //   6639: istore #4
    //   6641: getstatic burp/Zbx4.ZS : Ljava/lang/String;
    //   6644: getstatic burp/Zbwj.ZW : Ljava/lang/Object;
    //   6647: checkcast java/math/BigInteger
    //   6650: invokevirtual intValue : ()I
    //   6653: bipush #32
    //   6655: irem
    //   6656: invokestatic abs : (I)I
    //   6659: invokevirtual charAt : (I)C
    //   6662: getstatic burp/Zbss.ZV : Ljava/lang/String;
    //   6665: getstatic burp/Zmdi.Zw : Ljava/lang/Object;
    //   6668: checkcast java/math/BigInteger
    //   6671: invokevirtual intValue : ()I
    //   6674: bipush #32
    //   6676: irem
    //   6677: invokestatic abs : (I)I
    //   6680: invokevirtual charAt : (I)C
    //   6683: if_icmpgt -> 7028
    //   6686: sipush #-23396
    //   6689: sipush #-16759
    //   6692: invokestatic a : (II)Ljava/lang/String;
    //   6695: iconst_1
    //   6696: ldc burp/Zkbf
    //   6698: invokevirtual getClassLoader : ()Ljava/lang/ClassLoader;
    //   6701: invokestatic forName : (Ljava/lang/String;ZLjava/lang/ClassLoader;)Ljava/lang/Class;
    //   6704: invokevirtual getDeclaredFields : ()[Ljava/lang/reflect/Field;
    //   6707: astore #5
    //   6709: aload #5
    //   6711: arraylength
    //   6712: istore #6
    //   6714: iconst_0
    //   6715: istore #7
    //   6717: iload #7
    //   6719: iload #6
    //   6721: if_icmpge -> 6859
    //   6724: aload #5
    //   6726: iload #7
    //   6728: aaload
    //   6729: astore #8
    //   6731: aload #8
    //   6733: invokevirtual getModifiers : ()I
    //   6736: invokestatic isStatic : (I)Z
    //   6739: ifne -> 6749
    //   6742: goto -> 6852
    //   6745: invokestatic a : (Ljava/lang/Throwable;)Ljava/lang/Throwable;
    //   6748: athrow
    //   6749: aload #8
    //   6751: invokevirtual getType : ()Ljava/lang/Class;
    //   6754: astore #9
    //   6756: aload #9
    //   6758: ifnull -> 6839
    //   6761: aload #9
    //   6763: invokevirtual isPrimitive : ()Z
    //   6766: ifne -> 6839
    //   6769: goto -> 6776
    //   6772: invokestatic a : (Ljava/lang/Throwable;)Ljava/lang/Throwable;
    //   6775: athrow
    //   6776: aload #9
    //   6778: invokevirtual getPackage : ()Ljava/lang/Package;
    //   6781: ifnull -> 6839
    //   6784: goto -> 6791
    //   6787: invokestatic a : (Ljava/lang/Throwable;)Ljava/lang/Throwable;
    //   6790: athrow
    //   6791: aload #9
    //   6793: invokevirtual getPackage : ()Ljava/lang/Package;
    //   6796: invokevirtual getName : ()Ljava/lang/String;
    //   6799: ifnull -> 6839
    //   6802: goto -> 6809
    //   6805: invokestatic a : (Ljava/lang/Throwable;)Ljava/lang/Throwable;
    //   6808: athrow
    //   6809: aload #9
    //   6811: invokevirtual getPackage : ()Ljava/lang/Package;
    //   6814: invokevirtual getName : ()Ljava/lang/String;
    //   6817: sipush #-23414
    //   6820: sipush #-30892
    //   6823: invokestatic a : (II)Ljava/lang/String;
    //   6826: invokevirtual startsWith : (Ljava/lang/String;)Z
    //   6829: ifne -> 6839
    //   6832: goto -> 6839
    //   6835: invokestatic a : (Ljava/lang/Throwable;)Ljava/lang/Throwable;
    //   6838: athrow
    //   6839: aload #8
    //   6841: iconst_1
    //   6842: invokevirtual setAccessible : (Z)V
    //   6845: aload #8
    //   6847: aconst_null
    //   6848: invokevirtual get : (Ljava/lang/Object;)Ljava/lang/Object;
    //   6851: pop
    //   6852: iinc #7, 1
    //   6855: iload_2
    //   6856: ifeq -> 6717
    //   6859: sipush #-23412
    //   6862: sipush #13525
    //   6865: invokestatic a : (II)Ljava/lang/String;
    //   6868: invokestatic forName : (Ljava/lang/String;)Ljava/lang/Class;
    //   6871: invokevirtual getDeclaredMethods : ()[Ljava/lang/reflect/Method;
    //   6874: astore #5
    //   6876: aload #5
    //   6878: arraylength
    //   6879: istore #6
    //   6881: iconst_0
    //   6882: istore #7
    //   6884: iload #7
    //   6886: iload #6
    //   6888: if_icmpge -> 7025
    //   6891: aload #5
    //   6893: iload #7
    //   6895: aaload
    //   6896: astore #8
    //   6898: aload #8
    //   6900: invokevirtual getParameterTypes : ()[Ljava/lang/Class;
    //   6903: pop
    //   6904: aload #8
    //   6906: invokevirtual getModifiers : ()I
    //   6909: invokestatic isStatic : (I)Z
    //   6912: ifeq -> 7011
    //   6915: aload #8
    //   6917: invokevirtual getParameterTypes : ()[Ljava/lang/Class;
    //   6920: arraylength
    //   6921: iconst_2
    //   6922: if_icmpne -> 7011
    //   6925: goto -> 6932
    //   6928: invokestatic a : (Ljava/lang/Throwable;)Ljava/lang/Throwable;
    //   6931: athrow
    //   6932: aload #8
    //   6934: invokevirtual getReturnType : ()Ljava/lang/Class;
    //   6937: getstatic java/lang/Boolean.TYPE : Ljava/lang/Class;
    //   6940: if_acmpne -> 7011
    //   6943: goto -> 6950
    //   6946: invokestatic a : (Ljava/lang/Throwable;)Ljava/lang/Throwable;
    //   6949: athrow
    //   6950: aload #8
    //   6952: iconst_1
    //   6953: invokevirtual setAccessible : (Z)V
    //   6956: aload #8
    //   6958: aconst_null
    //   6959: iconst_2
    //   6960: anewarray java/lang/Object
    //   6963: dup
    //   6964: iconst_0
    //   6965: aload_0
    //   6966: aastore
    //   6967: dup
    //   6968: iconst_1
    //   6969: aload_1
    //   6970: ifnonnull -> 6988
    //   6973: goto -> 6980
    //   6976: invokestatic a : (Ljava/lang/Throwable;)Ljava/lang/Throwable;
    //   6979: athrow
    //   6980: aload_1
    //   6981: goto -> 6995
    //   6984: invokestatic a : (Ljava/lang/Throwable;)Ljava/lang/Throwable;
    //   6987: athrow
    //   6988: aload_1
    //   6989: checkcast [B
    //   6992: invokevirtual clone : ()Ljava/lang/Object;
    //   6995: aastore
    //   6996: invokevirtual invoke : (Ljava/lang/Object;[Ljava/lang/Object;)Ljava/lang/Object;
    //   6999: checkcast java/lang/Boolean
    //   7002: invokevirtual booleanValue : ()Z
    //   7005: istore #4
    //   7007: iload_2
    //   7008: ifeq -> 7025
    //   7011: iinc #7, 1
    //   7014: iload_2
    //   7015: ifeq -> 6884
    //   7018: goto -> 7025
    //   7021: invokestatic a : (Ljava/lang/Throwable;)Ljava/lang/Throwable;
    //   7024: athrow
    //   7025: goto -> 7367
    //   7028: sipush #-23424
    //   7031: sipush #-19637
    //   7034: invokestatic a : (II)Ljava/lang/String;
    //   7037: iconst_1
    //   7038: ldc burp/Zg3v
    //   7040: invokevirtual getClassLoader : ()Ljava/lang/ClassLoader;
    //   7043: invokestatic forName : (Ljava/lang/String;ZLjava/lang/ClassLoader;)Ljava/lang/Class;
    //   7046: invokevirtual getDeclaredFields : ()[Ljava/lang/reflect/Field;
    //   7049: astore #5
    //   7051: aload #5
    //   7053: arraylength
    //   7054: istore #6
    //   7056: iconst_0
    //   7057: istore #7
    //   7059: iload #7
    //   7061: iload #6
    //   7063: if_icmpge -> 7201
    //   7066: aload #5
    //   7068: iload #7
    //   7070: aaload
    //   7071: astore #8
    //   7073: aload #8
    //   7075: invokevirtual getModifiers : ()I
    //   7078: invokestatic isStatic : (I)Z
    //   7081: ifne -> 7091
    //   7084: goto -> 7194
    //   7087: invokestatic a : (Ljava/lang/Throwable;)Ljava/lang/Throwable;
    //   7090: athrow
    //   7091: aload #8
    //   7093: invokevirtual getType : ()Ljava/lang/Class;
    //   7096: astore #9
    //   7098: aload #9
    //   7100: ifnull -> 7181
    //   7103: aload #9
    //   7105: invokevirtual isPrimitive : ()Z
    //   7108: ifne -> 7181
    //   7111: goto -> 7118
    //   7114: invokestatic a : (Ljava/lang/Throwable;)Ljava/lang/Throwable;
    //   7117: athrow
    //   7118: aload #9
    //   7120: invokevirtual getPackage : ()Ljava/lang/Package;
    //   7123: ifnull -> 7181
    //   7126: goto -> 7133
    //   7129: invokestatic a : (Ljava/lang/Throwable;)Ljava/lang/Throwable;
    //   7132: athrow
    //   7133: aload #9
    //   7135: invokevirtual getPackage : ()Ljava/lang/Package;
    //   7138: invokevirtual getName : ()Ljava/lang/String;
    //   7141: ifnull -> 7181
    //   7144: goto -> 7151
    //   7147: invokestatic a : (Ljava/lang/Throwable;)Ljava/lang/Throwable;
    //   7150: athrow
    //   7151: aload #9
    //   7153: invokevirtual getPackage : ()Ljava/lang/Package;
    //   7156: invokevirtual getName : ()Ljava/lang/String;
    //   7159: sipush #-23414
    //   7162: sipush #-30892
    //   7165: invokestatic a : (II)Ljava/lang/String;
    //   7168: invokevirtual startsWith : (Ljava/lang/String;)Z
    //   7171: ifne -> 7181
    //   7174: goto -> 7181
    //   7177: invokestatic a : (Ljava/lang/Throwable;)Ljava/lang/Throwable;
    //   7180: athrow
    //   7181: aload #8
    //   7183: iconst_1
    //   7184: invokevirtual setAccessible : (Z)V
    //   7187: aload #8
    //   7189: aconst_null
    //   7190: invokevirtual get : (Ljava/lang/Object;)Ljava/lang/Object;
    //   7193: pop
    //   7194: iinc #7, 1
    //   7197: iload_2
    //   7198: ifeq -> 7059
    //   7201: sipush #-23416
    //   7204: sipush #-1630
    //   7207: invokestatic a : (II)Ljava/lang/String;
    //   7210: invokestatic forName : (Ljava/lang/String;)Ljava/lang/Class;
    //   7213: invokevirtual getDeclaredMethods : ()[Ljava/lang/reflect/Method;
    //   7216: astore #5
    //   7218: aload #5
    //   7220: arraylength
    //   7221: istore #6
    //   7223: iconst_0
    //   7224: istore #7
    //   7226: iload #7
    //   7228: iload #6
    //   7230: if_icmpge -> 7367
    //   7233: aload #5
    //   7235: iload #7
    //   7237: aaload
    //   7238: astore #8
    //   7240: aload #8
    //   7242: invokevirtual getParameterTypes : ()[Ljava/lang/Class;
    //   7245: pop
    //   7246: aload #8
    //   7248: invokevirtual getModifiers : ()I
    //   7251: invokestatic isStatic : (I)Z
    //   7254: ifeq -> 7353
    //   7257: aload #8
    //   7259: invokevirtual getParameterTypes : ()[Ljava/lang/Class;
    //   7262: arraylength
    //   7263: iconst_2
    //   7264: if_icmpne -> 7353
    //   7267: goto -> 7274
    //   7270: invokestatic a : (Ljava/lang/Throwable;)Ljava/lang/Throwable;
    //   7273: athrow
    //   7274: aload #8
    //   7276: invokevirtual getReturnType : ()Ljava/lang/Class;
    //   7279: getstatic java/lang/Boolean.TYPE : Ljava/lang/Class;
    //   7282: if_acmpne -> 7353
    //   7285: goto -> 7292
    //   7288: invokestatic a : (Ljava/lang/Throwable;)Ljava/lang/Throwable;
    //   7291: athrow
    //   7292: aload #8
    //   7294: iconst_1
    //   7295: invokevirtual setAccessible : (Z)V
    //   7298: aload #8
    //   7300: aconst_null
    //   7301: iconst_2
    //   7302: anewarray java/lang/Object
    //   7305: dup
    //   7306: iconst_0
    //   7307: aload_0
    //   7308: aastore
    //   7309: dup
    //   7310: iconst_1
    //   7311: aload_1
    //   7312: ifnonnull -> 7330
    //   7315: goto -> 7322
    //   7318: invokestatic a : (Ljava/lang/Throwable;)Ljava/lang/Throwable;
    //   7321: athrow
    //   7322: aload_1
    //   7323: goto -> 7337
    //   7326: invokestatic a : (Ljava/lang/Throwable;)Ljava/lang/Throwable;
    //   7329: athrow
    //   7330: aload_1
    //   7331: checkcast [B
    //   7334: invokevirtual clone : ()Ljava/lang/Object;
    //   7337: aastore
    //   7338: invokevirtual invoke : (Ljava/lang/Object;[Ljava/lang/Object;)Ljava/lang/Object;
    //   7341: checkcast java/lang/Boolean
    //   7344: invokevirtual booleanValue : ()Z
    //   7347: istore #4
    //   7349: iload_2
    //   7350: ifeq -> 7367
    //   7353: iinc #7, 1
    //   7356: iload_2
    //   7357: ifeq -> 7226
    //   7360: goto -> 7367
    //   7363: invokestatic a : (Ljava/lang/Throwable;)Ljava/lang/Throwable;
    //   7366: athrow
    //   7367: iload #4
    //   7369: ifeq -> 7375
    //   7372: iload #4
    //   7374: ireturn
    //   7375: getstatic burp/Zmn0.Zk : Ljava/lang/String;
    //   7378: getstatic burp/Zm0d.Zz : Ljava/lang/Object;
    //   7381: checkcast java/math/BigInteger
    //   7384: invokevirtual intValue : ()I
    //   7387: bipush #32
    //   7389: irem
    //   7390: invokestatic abs : (I)I
    //   7393: invokevirtual charAt : (I)C
    //   7396: getstatic burp/Zxan.ZJ : Ljava/lang/String;
    //   7399: getstatic burp/Zbsz.ZP : Ljava/lang/Object;
    //   7402: checkcast java/math/BigInteger
    //   7405: invokevirtual intValue : ()I
    //   7408: bipush #32
    //   7410: irem
    //   7411: invokestatic abs : (I)I
    //   7414: invokevirtual charAt : (I)C
    //   7417: if_icmpgt -> 7763
    //   7420: sipush #-23394
    //   7423: sipush #-16305
    //   7426: invokestatic a : (II)Ljava/lang/String;
    //   7429: iconst_1
    //   7430: ldc burp/Zgds
    //   7432: invokevirtual getClassLoader : ()Ljava/lang/ClassLoader;
    //   7435: invokestatic forName : (Ljava/lang/String;ZLjava/lang/ClassLoader;)Ljava/lang/Class;
    //   7438: invokevirtual getDeclaredFields : ()[Ljava/lang/reflect/Field;
    //   7441: astore #5
    //   7443: aload #5
    //   7445: arraylength
    //   7446: istore #6
    //   7448: iconst_0
    //   7449: istore #7
    //   7451: iload #7
    //   7453: iload #6
    //   7455: if_icmpge -> 7593
    //   7458: aload #5
    //   7460: iload #7
    //   7462: aaload
    //   7463: astore #8
    //   7465: aload #8
    //   7467: invokevirtual getModifiers : ()I
    //   7470: invokestatic isStatic : (I)Z
    //   7473: ifne -> 7483
    //   7476: goto -> 7586
    //   7479: invokestatic a : (Ljava/lang/Throwable;)Ljava/lang/Throwable;
    //   7482: athrow
    //   7483: aload #8
    //   7485: invokevirtual getType : ()Ljava/lang/Class;
    //   7488: astore #9
    //   7490: aload #9
    //   7492: ifnull -> 7573
    //   7495: aload #9
    //   7497: invokevirtual isPrimitive : ()Z
    //   7500: ifne -> 7573
    //   7503: goto -> 7510
    //   7506: invokestatic a : (Ljava/lang/Throwable;)Ljava/lang/Throwable;
    //   7509: athrow
    //   7510: aload #9
    //   7512: invokevirtual getPackage : ()Ljava/lang/Package;
    //   7515: ifnull -> 7573
    //   7518: goto -> 7525
    //   7521: invokestatic a : (Ljava/lang/Throwable;)Ljava/lang/Throwable;
    //   7524: athrow
    //   7525: aload #9
    //   7527: invokevirtual getPackage : ()Ljava/lang/Package;
    //   7530: invokevirtual getName : ()Ljava/lang/String;
    //   7533: ifnull -> 7573
    //   7536: goto -> 7543
    //   7539: invokestatic a : (Ljava/lang/Throwable;)Ljava/lang/Throwable;
    //   7542: athrow
    //   7543: aload #9
    //   7545: invokevirtual getPackage : ()Ljava/lang/Package;
    //   7548: invokevirtual getName : ()Ljava/lang/String;
    //   7551: sipush #-23414
    //   7554: sipush #-30892
    //   7557: invokestatic a : (II)Ljava/lang/String;
    //   7560: invokevirtual startsWith : (Ljava/lang/String;)Z
    //   7563: ifne -> 7573
    //   7566: goto -> 7573
    //   7569: invokestatic a : (Ljava/lang/Throwable;)Ljava/lang/Throwable;
    //   7572: athrow
    //   7573: aload #8
    //   7575: iconst_1
    //   7576: invokevirtual setAccessible : (Z)V
    //   7579: aload #8
    //   7581: aconst_null
    //   7582: invokevirtual get : (Ljava/lang/Object;)Ljava/lang/Object;
    //   7585: pop
    //   7586: iinc #7, 1
    //   7589: iload_2
    //   7590: ifeq -> 7451
    //   7593: sipush #-23409
    //   7596: sipush #31003
    //   7599: invokestatic a : (II)Ljava/lang/String;
    //   7602: invokestatic forName : (Ljava/lang/String;)Ljava/lang/Class;
    //   7605: invokevirtual getDeclaredMethods : ()[Ljava/lang/reflect/Method;
    //   7608: astore #5
    //   7610: aload #5
    //   7612: arraylength
    //   7613: istore #6
    //   7615: iconst_0
    //   7616: istore #7
    //   7618: iload #7
    //   7620: iload #6
    //   7622: if_icmpge -> 7759
    //   7625: aload #5
    //   7627: iload #7
    //   7629: aaload
    //   7630: astore #8
    //   7632: aload #8
    //   7634: invokevirtual getParameterTypes : ()[Ljava/lang/Class;
    //   7637: pop
    //   7638: aload #8
    //   7640: invokevirtual getModifiers : ()I
    //   7643: invokestatic isStatic : (I)Z
    //   7646: ifeq -> 7745
    //   7649: aload #8
    //   7651: invokevirtual getParameterTypes : ()[Ljava/lang/Class;
    //   7654: arraylength
    //   7655: iconst_2
    //   7656: if_icmpne -> 7745
    //   7659: goto -> 7666
    //   7662: invokestatic a : (Ljava/lang/Throwable;)Ljava/lang/Throwable;
    //   7665: athrow
    //   7666: aload #8
    //   7668: invokevirtual getReturnType : ()Ljava/lang/Class;
    //   7671: getstatic java/lang/Boolean.TYPE : Ljava/lang/Class;
    //   7674: if_acmpne -> 7745
    //   7677: goto -> 7684
    //   7680: invokestatic a : (Ljava/lang/Throwable;)Ljava/lang/Throwable;
    //   7683: athrow
    //   7684: aload #8
    //   7686: iconst_1
    //   7687: invokevirtual setAccessible : (Z)V
    //   7690: aload #8
    //   7692: aconst_null
    //   7693: iconst_2
    //   7694: anewarray java/lang/Object
    //   7697: dup
    //   7698: iconst_0
    //   7699: aload_0
    //   7700: aastore
    //   7701: dup
    //   7702: iconst_1
    //   7703: aload_1
    //   7704: ifnonnull -> 7722
    //   7707: goto -> 7714
    //   7710: invokestatic a : (Ljava/lang/Throwable;)Ljava/lang/Throwable;
    //   7713: athrow
    //   7714: aload_1
    //   7715: goto -> 7729
    //   7718: invokestatic a : (Ljava/lang/Throwable;)Ljava/lang/Throwable;
    //   7721: athrow
    //   7722: aload_1
    //   7723: checkcast [B
    //   7726: invokevirtual clone : ()Ljava/lang/Object;
    //   7729: aastore
    //   7730: invokevirtual invoke : (Ljava/lang/Object;[Ljava/lang/Object;)Ljava/lang/Object;
    //   7733: checkcast java/lang/Boolean
    //   7736: invokevirtual booleanValue : ()Z
    //   7739: istore #4
    //   7741: iload_2
    //   7742: ifeq -> 7759
    //   7745: iinc #7, 1
    //   7748: iload_2
    //   7749: ifeq -> 7618
    //   7752: goto -> 7759
    //   7755: invokestatic a : (Ljava/lang/Throwable;)Ljava/lang/Throwable;
    //   7758: athrow
    //   7759: iload_2
    //   7760: ifeq -> 8102
    //   7763: sipush #-23419
    //   7766: sipush #30336
    //   7769: invokestatic a : (II)Ljava/lang/String;
    //   7772: iconst_1
    //   7773: ldc burp/Ztnw
    //   7775: invokevirtual getClassLoader : ()Ljava/lang/ClassLoader;
    //   7778: invokestatic forName : (Ljava/lang/String;ZLjava/lang/ClassLoader;)Ljava/lang/Class;
    //   7781: invokevirtual getDeclaredFields : ()[Ljava/lang/reflect/Field;
    //   7784: astore #5
    //   7786: aload #5
    //   7788: arraylength
    //   7789: istore #6
    //   7791: iconst_0
    //   7792: istore #7
    //   7794: iload #7
    //   7796: iload #6
    //   7798: if_icmpge -> 7936
    //   7801: aload #5
    //   7803: iload #7
    //   7805: aaload
    //   7806: astore #8
    //   7808: aload #8
    //   7810: invokevirtual getModifiers : ()I
    //   7813: invokestatic isStatic : (I)Z
    //   7816: ifne -> 7826
    //   7819: goto -> 7929
    //   7822: invokestatic a : (Ljava/lang/Throwable;)Ljava/lang/Throwable;
    //   7825: athrow
    //   7826: aload #8
    //   7828: invokevirtual getType : ()Ljava/lang/Class;
    //   7831: astore #9
    //   7833: aload #9
    //   7835: ifnull -> 7916
    //   7838: aload #9
    //   7840: invokevirtual isPrimitive : ()Z
    //   7843: ifne -> 7916
    //   7846: goto -> 7853
    //   7849: invokestatic a : (Ljava/lang/Throwable;)Ljava/lang/Throwable;
    //   7852: athrow
    //   7853: aload #9
    //   7855: invokevirtual getPackage : ()Ljava/lang/Package;
    //   7858: ifnull -> 7916
    //   7861: goto -> 7868
    //   7864: invokestatic a : (Ljava/lang/Throwable;)Ljava/lang/Throwable;
    //   7867: athrow
    //   7868: aload #9
    //   7870: invokevirtual getPackage : ()Ljava/lang/Package;
    //   7873: invokevirtual getName : ()Ljava/lang/String;
    //   7876: ifnull -> 7916
    //   7879: goto -> 7886
    //   7882: invokestatic a : (Ljava/lang/Throwable;)Ljava/lang/Throwable;
    //   7885: athrow
    //   7886: aload #9
    //   7888: invokevirtual getPackage : ()Ljava/lang/Package;
    //   7891: invokevirtual getName : ()Ljava/lang/String;
    //   7894: sipush #-23414
    //   7897: sipush #-30892
    //   7900: invokestatic a : (II)Ljava/lang/String;
    //   7903: invokevirtual startsWith : (Ljava/lang/String;)Z
    //   7906: ifne -> 7916
    //   7909: goto -> 7916
    //   7912: invokestatic a : (Ljava/lang/Throwable;)Ljava/lang/Throwable;
    //   7915: athrow
    //   7916: aload #8
    //   7918: iconst_1
    //   7919: invokevirtual setAccessible : (Z)V
    //   7922: aload #8
    //   7924: aconst_null
    //   7925: invokevirtual get : (Ljava/lang/Object;)Ljava/lang/Object;
    //   7928: pop
    //   7929: iinc #7, 1
    //   7932: iload_2
    //   7933: ifeq -> 7794
    //   7936: sipush #-23418
    //   7939: sipush #-13127
    //   7942: invokestatic a : (II)Ljava/lang/String;
    //   7945: invokestatic forName : (Ljava/lang/String;)Ljava/lang/Class;
    //   7948: invokevirtual getDeclaredMethods : ()[Ljava/lang/reflect/Method;
    //   7951: astore #5
    //   7953: aload #5
    //   7955: arraylength
    //   7956: istore #6
    //   7958: iconst_0
    //   7959: istore #7
    //   7961: iload #7
    //   7963: iload #6
    //   7965: if_icmpge -> 8102
    //   7968: aload #5
    //   7970: iload #7
    //   7972: aaload
    //   7973: astore #8
    //   7975: aload #8
    //   7977: invokevirtual getParameterTypes : ()[Ljava/lang/Class;
    //   7980: pop
    //   7981: aload #8
    //   7983: invokevirtual getModifiers : ()I
    //   7986: invokestatic isStatic : (I)Z
    //   7989: ifeq -> 8088
    //   7992: aload #8
    //   7994: invokevirtual getParameterTypes : ()[Ljava/lang/Class;
    //   7997: arraylength
    //   7998: iconst_2
    //   7999: if_icmpne -> 8088
    //   8002: goto -> 8009
    //   8005: invokestatic a : (Ljava/lang/Throwable;)Ljava/lang/Throwable;
    //   8008: athrow
    //   8009: aload #8
    //   8011: invokevirtual getReturnType : ()Ljava/lang/Class;
    //   8014: getstatic java/lang/Boolean.TYPE : Ljava/lang/Class;
    //   8017: if_acmpne -> 8088
    //   8020: goto -> 8027
    //   8023: invokestatic a : (Ljava/lang/Throwable;)Ljava/lang/Throwable;
    //   8026: athrow
    //   8027: aload #8
    //   8029: iconst_1
    //   8030: invokevirtual setAccessible : (Z)V
    //   8033: aload #8
    //   8035: aconst_null
    //   8036: iconst_2
    //   8037: anewarray java/lang/Object
    //   8040: dup
    //   8041: iconst_0
    //   8042: aload_0
    //   8043: aastore
    //   8044: dup
    //   8045: iconst_1
    //   8046: aload_1
    //   8047: ifnonnull -> 8065
    //   8050: goto -> 8057
    //   8053: invokestatic a : (Ljava/lang/Throwable;)Ljava/lang/Throwable;
    //   8056: athrow
    //   8057: aload_1
    //   8058: goto -> 8072
    //   8061: invokestatic a : (Ljava/lang/Throwable;)Ljava/lang/Throwable;
    //   8064: athrow
    //   8065: aload_1
    //   8066: checkcast [B
    //   8069: invokevirtual clone : ()Ljava/lang/Object;
    //   8072: aastore
    //   8073: invokevirtual invoke : (Ljava/lang/Object;[Ljava/lang/Object;)Ljava/lang/Object;
    //   8076: checkcast java/lang/Boolean
    //   8079: invokevirtual booleanValue : ()Z
    //   8082: istore #4
    //   8084: iload_2
    //   8085: ifeq -> 8102
    //   8088: iinc #7, 1
    //   8091: iload_2
    //   8092: ifeq -> 7961
    //   8095: goto -> 8102
    //   8098: invokestatic a : (Ljava/lang/Throwable;)Ljava/lang/Throwable;
    //   8101: athrow
    //   8102: iload #4
    //   8104: ifeq -> 8110
    //   8107: iload #4
    //   8109: ireturn
    //   8110: getstatic burp/Zmdf.Zo : Ljava/lang/String;
    //   8113: getstatic burp/Zlbd.ZU : Ljava/lang/Object;
    //   8116: checkcast java/math/BigInteger
    //   8119: invokevirtual intValue : ()I
    //   8122: bipush #32
    //   8124: irem
    //   8125: invokestatic abs : (I)I
    //   8128: invokevirtual charAt : (I)C
    //   8131: getstatic burp/Zgrz.Zu : Ljava/lang/String;
    //   8134: getstatic burp/Zti4.Zi : Ljava/lang/Object;
    //   8137: checkcast java/math/BigInteger
    //   8140: invokevirtual intValue : ()I
    //   8143: bipush #32
    //   8145: irem
    //   8146: invokestatic abs : (I)I
    //   8149: invokevirtual charAt : (I)C
    //   8152: if_icmple -> 8498
    //   8155: sipush #-23399
    //   8158: sipush #-13529
    //   8161: invokestatic a : (II)Ljava/lang/String;
    //   8164: iconst_1
    //   8165: ldc burp/Zsq5
    //   8167: invokevirtual getClassLoader : ()Ljava/lang/ClassLoader;
    //   8170: invokestatic forName : (Ljava/lang/String;ZLjava/lang/ClassLoader;)Ljava/lang/Class;
    //   8173: invokevirtual getDeclaredFields : ()[Ljava/lang/reflect/Field;
    //   8176: astore #5
    //   8178: aload #5
    //   8180: arraylength
    //   8181: istore #6
    //   8183: iconst_0
    //   8184: istore #7
    //   8186: iload #7
    //   8188: iload #6
    //   8190: if_icmpge -> 8328
    //   8193: aload #5
    //   8195: iload #7
    //   8197: aaload
    //   8198: astore #8
    //   8200: aload #8
    //   8202: invokevirtual getModifiers : ()I
    //   8205: invokestatic isStatic : (I)Z
    //   8208: ifne -> 8218
    //   8211: goto -> 8321
    //   8214: invokestatic a : (Ljava/lang/Throwable;)Ljava/lang/Throwable;
    //   8217: athrow
    //   8218: aload #8
    //   8220: invokevirtual getType : ()Ljava/lang/Class;
    //   8223: astore #9
    //   8225: aload #9
    //   8227: ifnull -> 8308
    //   8230: aload #9
    //   8232: invokevirtual isPrimitive : ()Z
    //   8235: ifne -> 8308
    //   8238: goto -> 8245
    //   8241: invokestatic a : (Ljava/lang/Throwable;)Ljava/lang/Throwable;
    //   8244: athrow
    //   8245: aload #9
    //   8247: invokevirtual getPackage : ()Ljava/lang/Package;
    //   8250: ifnull -> 8308
    //   8253: goto -> 8260
    //   8256: invokestatic a : (Ljava/lang/Throwable;)Ljava/lang/Throwable;
    //   8259: athrow
    //   8260: aload #9
    //   8262: invokevirtual getPackage : ()Ljava/lang/Package;
    //   8265: invokevirtual getName : ()Ljava/lang/String;
    //   8268: ifnull -> 8308
    //   8271: goto -> 8278
    //   8274: invokestatic a : (Ljava/lang/Throwable;)Ljava/lang/Throwable;
    //   8277: athrow
    //   8278: aload #9
    //   8280: invokevirtual getPackage : ()Ljava/lang/Package;
    //   8283: invokevirtual getName : ()Ljava/lang/String;
    //   8286: sipush #-23414
    //   8289: sipush #-30892
    //   8292: invokestatic a : (II)Ljava/lang/String;
    //   8295: invokevirtual startsWith : (Ljava/lang/String;)Z
    //   8298: ifne -> 8308
    //   8301: goto -> 8308
    //   8304: invokestatic a : (Ljava/lang/Throwable;)Ljava/lang/Throwable;
    //   8307: athrow
    //   8308: aload #8
    //   8310: iconst_1
    //   8311: invokevirtual setAccessible : (Z)V
    //   8314: aload #8
    //   8316: aconst_null
    //   8317: invokevirtual get : (Ljava/lang/Object;)Ljava/lang/Object;
    //   8320: pop
    //   8321: iinc #7, 1
    //   8324: iload_2
    //   8325: ifeq -> 8186
    //   8328: sipush #-23410
    //   8331: sipush #-16224
    //   8334: invokestatic a : (II)Ljava/lang/String;
    //   8337: invokestatic forName : (Ljava/lang/String;)Ljava/lang/Class;
    //   8340: invokevirtual getDeclaredMethods : ()[Ljava/lang/reflect/Method;
    //   8343: astore #5
    //   8345: aload #5
    //   8347: arraylength
    //   8348: istore #6
    //   8350: iconst_0
    //   8351: istore #7
    //   8353: iload #7
    //   8355: iload #6
    //   8357: if_icmpge -> 8494
    //   8360: aload #5
    //   8362: iload #7
    //   8364: aaload
    //   8365: astore #8
    //   8367: aload #8
    //   8369: invokevirtual getParameterTypes : ()[Ljava/lang/Class;
    //   8372: pop
    //   8373: aload #8
    //   8375: invokevirtual getModifiers : ()I
    //   8378: invokestatic isStatic : (I)Z
    //   8381: ifeq -> 8480
    //   8384: aload #8
    //   8386: invokevirtual getParameterTypes : ()[Ljava/lang/Class;
    //   8389: arraylength
    //   8390: iconst_2
    //   8391: if_icmpne -> 8480
    //   8394: goto -> 8401
    //   8397: invokestatic a : (Ljava/lang/Throwable;)Ljava/lang/Throwable;
    //   8400: athrow
    //   8401: aload #8
    //   8403: invokevirtual getReturnType : ()Ljava/lang/Class;
    //   8406: getstatic java/lang/Boolean.TYPE : Ljava/lang/Class;
    //   8409: if_acmpne -> 8480
    //   8412: goto -> 8419
    //   8415: invokestatic a : (Ljava/lang/Throwable;)Ljava/lang/Throwable;
    //   8418: athrow
    //   8419: aload #8
    //   8421: iconst_1
    //   8422: invokevirtual setAccessible : (Z)V
    //   8425: aload #8
    //   8427: aconst_null
    //   8428: iconst_2
    //   8429: anewarray java/lang/Object
    //   8432: dup
    //   8433: iconst_0
    //   8434: aload_0
    //   8435: aastore
    //   8436: dup
    //   8437: iconst_1
    //   8438: aload_1
    //   8439: ifnonnull -> 8457
    //   8442: goto -> 8449
    //   8445: invokestatic a : (Ljava/lang/Throwable;)Ljava/lang/Throwable;
    //   8448: athrow
    //   8449: aload_1
    //   8450: goto -> 8464
    //   8453: invokestatic a : (Ljava/lang/Throwable;)Ljava/lang/Throwable;
    //   8456: athrow
    //   8457: aload_1
    //   8458: checkcast [B
    //   8461: invokevirtual clone : ()Ljava/lang/Object;
    //   8464: aastore
    //   8465: invokevirtual invoke : (Ljava/lang/Object;[Ljava/lang/Object;)Ljava/lang/Object;
    //   8468: checkcast java/lang/Boolean
    //   8471: invokevirtual booleanValue : ()Z
    //   8474: istore #4
    //   8476: iload_2
    //   8477: ifeq -> 8494
    //   8480: iinc #7, 1
    //   8483: iload_2
    //   8484: ifeq -> 8353
    //   8487: goto -> 8494
    //   8490: invokestatic a : (Ljava/lang/Throwable;)Ljava/lang/Throwable;
    //   8493: athrow
    //   8494: iload_2
    //   8495: ifeq -> 8837
    //   8498: sipush #-23422
    //   8501: sipush #15115
    //   8504: invokestatic a : (II)Ljava/lang/String;
    //   8507: iconst_1
    //   8508: ldc burp/Zz3k
    //   8510: invokevirtual getClassLoader : ()Ljava/lang/ClassLoader;
    //   8513: invokestatic forName : (Ljava/lang/String;ZLjava/lang/ClassLoader;)Ljava/lang/Class;
    //   8516: invokevirtual getDeclaredFields : ()[Ljava/lang/reflect/Field;
    //   8519: astore #5
    //   8521: aload #5
    //   8523: arraylength
    //   8524: istore #6
    //   8526: iconst_0
    //   8527: istore #7
    //   8529: iload #7
    //   8531: iload #6
    //   8533: if_icmpge -> 8671
    //   8536: aload #5
    //   8538: iload #7
    //   8540: aaload
    //   8541: astore #8
    //   8543: aload #8
    //   8545: invokevirtual getModifiers : ()I
    //   8548: invokestatic isStatic : (I)Z
    //   8551: ifne -> 8561
    //   8554: goto -> 8664
    //   8557: invokestatic a : (Ljava/lang/Throwable;)Ljava/lang/Throwable;
    //   8560: athrow
    //   8561: aload #8
    //   8563: invokevirtual getType : ()Ljava/lang/Class;
    //   8566: astore #9
    //   8568: aload #9
    //   8570: ifnull -> 8651
    //   8573: aload #9
    //   8575: invokevirtual isPrimitive : ()Z
    //   8578: ifne -> 8651
    //   8581: goto -> 8588
    //   8584: invokestatic a : (Ljava/lang/Throwable;)Ljava/lang/Throwable;
    //   8587: athrow
    //   8588: aload #9
    //   8590: invokevirtual getPackage : ()Ljava/lang/Package;
    //   8593: ifnull -> 8651
    //   8596: goto -> 8603
    //   8599: invokestatic a : (Ljava/lang/Throwable;)Ljava/lang/Throwable;
    //   8602: athrow
    //   8603: aload #9
    //   8605: invokevirtual getPackage : ()Ljava/lang/Package;
    //   8608: invokevirtual getName : ()Ljava/lang/String;
    //   8611: ifnull -> 8651
    //   8614: goto -> 8621
    //   8617: invokestatic a : (Ljava/lang/Throwable;)Ljava/lang/Throwable;
    //   8620: athrow
    //   8621: aload #9
    //   8623: invokevirtual getPackage : ()Ljava/lang/Package;
    //   8626: invokevirtual getName : ()Ljava/lang/String;
    //   8629: sipush #-23414
    //   8632: sipush #-30892
    //   8635: invokestatic a : (II)Ljava/lang/String;
    //   8638: invokevirtual startsWith : (Ljava/lang/String;)Z
    //   8641: ifne -> 8651
    //   8644: goto -> 8651
    //   8647: invokestatic a : (Ljava/lang/Throwable;)Ljava/lang/Throwable;
    //   8650: athrow
    //   8651: aload #8
    //   8653: iconst_1
    //   8654: invokevirtual setAccessible : (Z)V
    //   8657: aload #8
    //   8659: aconst_null
    //   8660: invokevirtual get : (Ljava/lang/Object;)Ljava/lang/Object;
    //   8663: pop
    //   8664: iinc #7, 1
    //   8667: iload_2
    //   8668: ifeq -> 8529
    //   8671: sipush #-23411
    //   8674: sipush #12152
    //   8677: invokestatic a : (II)Ljava/lang/String;
    //   8680: invokestatic forName : (Ljava/lang/String;)Ljava/lang/Class;
    //   8683: invokevirtual getDeclaredMethods : ()[Ljava/lang/reflect/Method;
    //   8686: astore #5
    //   8688: aload #5
    //   8690: arraylength
    //   8691: istore #6
    //   8693: iconst_0
    //   8694: istore #7
    //   8696: iload #7
    //   8698: iload #6
    //   8700: if_icmpge -> 8837
    //   8703: aload #5
    //   8705: iload #7
    //   8707: aaload
    //   8708: astore #8
    //   8710: aload #8
    //   8712: invokevirtual getParameterTypes : ()[Ljava/lang/Class;
    //   8715: pop
    //   8716: aload #8
    //   8718: invokevirtual getModifiers : ()I
    //   8721: invokestatic isStatic : (I)Z
    //   8724: ifeq -> 8823
    //   8727: aload #8
    //   8729: invokevirtual getParameterTypes : ()[Ljava/lang/Class;
    //   8732: arraylength
    //   8733: iconst_2
    //   8734: if_icmpne -> 8823
    //   8737: goto -> 8744
    //   8740: invokestatic a : (Ljava/lang/Throwable;)Ljava/lang/Throwable;
    //   8743: athrow
    //   8744: aload #8
    //   8746: invokevirtual getReturnType : ()Ljava/lang/Class;
    //   8749: getstatic java/lang/Boolean.TYPE : Ljava/lang/Class;
    //   8752: if_acmpne -> 8823
    //   8755: goto -> 8762
    //   8758: invokestatic a : (Ljava/lang/Throwable;)Ljava/lang/Throwable;
    //   8761: athrow
    //   8762: aload #8
    //   8764: iconst_1
    //   8765: invokevirtual setAccessible : (Z)V
    //   8768: aload #8
    //   8770: aconst_null
    //   8771: iconst_2
    //   8772: anewarray java/lang/Object
    //   8775: dup
    //   8776: iconst_0
    //   8777: aload_0
    //   8778: aastore
    //   8779: dup
    //   8780: iconst_1
    //   8781: aload_1
    //   8782: ifnonnull -> 8800
    //   8785: goto -> 8792
    //   8788: invokestatic a : (Ljava/lang/Throwable;)Ljava/lang/Throwable;
    //   8791: athrow
    //   8792: aload_1
    //   8793: goto -> 8807
    //   8796: invokestatic a : (Ljava/lang/Throwable;)Ljava/lang/Throwable;
    //   8799: athrow
    //   8800: aload_1
    //   8801: checkcast [B
    //   8804: invokevirtual clone : ()Ljava/lang/Object;
    //   8807: aastore
    //   8808: invokevirtual invoke : (Ljava/lang/Object;[Ljava/lang/Object;)Ljava/lang/Object;
    //   8811: checkcast java/lang/Boolean
    //   8814: invokevirtual booleanValue : ()Z
    //   8817: istore #4
    //   8819: iload_2
    //   8820: ifeq -> 8837
    //   8823: iinc #7, 1
    //   8826: iload_2
    //   8827: ifeq -> 8696
    //   8830: goto -> 8837
    //   8833: invokestatic a : (Ljava/lang/Throwable;)Ljava/lang/Throwable;
    //   8836: athrow
    //   8837: iload #4
    //   8839: ifeq -> 8845
    //   8842: iload #4
    //   8844: ireturn
    //   8845: getstatic burp/Zl7x.Zo : Ljava/lang/String;
    //   8848: getstatic burp/Ztle.ZP : Ljava/lang/Object;
    //   8851: checkcast java/math/BigInteger
    //   8854: invokevirtual intValue : ()I
    //   8857: bipush #32
    //   8859: irem
    //   8860: invokestatic abs : (I)I
    //   8863: invokevirtual charAt : (I)C
    //   8866: getstatic burp/Zrh_.ZU : Ljava/lang/String;
    //   8869: getstatic burp/Zsdl.Zx : Ljava/lang/Object;
    //   8872: checkcast java/math/BigInteger
    //   8875: invokevirtual intValue : ()I
    //   8878: bipush #32
    //   8880: irem
    //   8881: invokestatic abs : (I)I
    //   8884: invokevirtual charAt : (I)C
    //   8887: if_icmpgt -> 9233
    //   8890: sipush #-23421
    //   8893: sipush #-14610
    //   8896: invokestatic a : (II)Ljava/lang/String;
    //   8899: iconst_1
    //   8900: ldc burp/Zmh0
    //   8902: invokevirtual getClassLoader : ()Ljava/lang/ClassLoader;
    //   8905: invokestatic forName : (Ljava/lang/String;ZLjava/lang/ClassLoader;)Ljava/lang/Class;
    //   8908: invokevirtual getDeclaredFields : ()[Ljava/lang/reflect/Field;
    //   8911: astore #5
    //   8913: aload #5
    //   8915: arraylength
    //   8916: istore #6
    //   8918: iconst_0
    //   8919: istore #7
    //   8921: iload #7
    //   8923: iload #6
    //   8925: if_icmpge -> 9063
    //   8928: aload #5
    //   8930: iload #7
    //   8932: aaload
    //   8933: astore #8
    //   8935: aload #8
    //   8937: invokevirtual getModifiers : ()I
    //   8940: invokestatic isStatic : (I)Z
    //   8943: ifne -> 8953
    //   8946: goto -> 9056
    //   8949: invokestatic a : (Ljava/lang/Throwable;)Ljava/lang/Throwable;
    //   8952: athrow
    //   8953: aload #8
    //   8955: invokevirtual getType : ()Ljava/lang/Class;
    //   8958: astore #9
    //   8960: aload #9
    //   8962: ifnull -> 9043
    //   8965: aload #9
    //   8967: invokevirtual isPrimitive : ()Z
    //   8970: ifne -> 9043
    //   8973: goto -> 8980
    //   8976: invokestatic a : (Ljava/lang/Throwable;)Ljava/lang/Throwable;
    //   8979: athrow
    //   8980: aload #9
    //   8982: invokevirtual getPackage : ()Ljava/lang/Package;
    //   8985: ifnull -> 9043
    //   8988: goto -> 8995
    //   8991: invokestatic a : (Ljava/lang/Throwable;)Ljava/lang/Throwable;
    //   8994: athrow
    //   8995: aload #9
    //   8997: invokevirtual getPackage : ()Ljava/lang/Package;
    //   9000: invokevirtual getName : ()Ljava/lang/String;
    //   9003: ifnull -> 9043
    //   9006: goto -> 9013
    //   9009: invokestatic a : (Ljava/lang/Throwable;)Ljava/lang/Throwable;
    //   9012: athrow
    //   9013: aload #9
    //   9015: invokevirtual getPackage : ()Ljava/lang/Package;
    //   9018: invokevirtual getName : ()Ljava/lang/String;
    //   9021: sipush #-23414
    //   9024: sipush #-30892
    //   9027: invokestatic a : (II)Ljava/lang/String;
    //   9030: invokevirtual startsWith : (Ljava/lang/String;)Z
    //   9033: ifne -> 9043
    //   9036: goto -> 9043
    //   9039: invokestatic a : (Ljava/lang/Throwable;)Ljava/lang/Throwable;
    //   9042: athrow
    //   9043: aload #8
    //   9045: iconst_1
    //   9046: invokevirtual setAccessible : (Z)V
    //   9049: aload #8
    //   9051: aconst_null
    //   9052: invokevirtual get : (Ljava/lang/Object;)Ljava/lang/Object;
    //   9055: pop
    //   9056: iinc #7, 1
    //   9059: iload_2
    //   9060: ifeq -> 8921
    //   9063: sipush #-23404
    //   9066: sipush #-17825
    //   9069: invokestatic a : (II)Ljava/lang/String;
    //   9072: invokestatic forName : (Ljava/lang/String;)Ljava/lang/Class;
    //   9075: invokevirtual getDeclaredMethods : ()[Ljava/lang/reflect/Method;
    //   9078: astore #5
    //   9080: aload #5
    //   9082: arraylength
    //   9083: istore #6
    //   9085: iconst_0
    //   9086: istore #7
    //   9088: iload #7
    //   9090: iload #6
    //   9092: if_icmpge -> 9229
    //   9095: aload #5
    //   9097: iload #7
    //   9099: aaload
    //   9100: astore #8
    //   9102: aload #8
    //   9104: invokevirtual getParameterTypes : ()[Ljava/lang/Class;
    //   9107: pop
    //   9108: aload #8
    //   9110: invokevirtual getModifiers : ()I
    //   9113: invokestatic isStatic : (I)Z
    //   9116: ifeq -> 9215
    //   9119: aload #8
    //   9121: invokevirtual getParameterTypes : ()[Ljava/lang/Class;
    //   9124: arraylength
    //   9125: iconst_2
    //   9126: if_icmpne -> 9215
    //   9129: goto -> 9136
    //   9132: invokestatic a : (Ljava/lang/Throwable;)Ljava/lang/Throwable;
    //   9135: athrow
    //   9136: aload #8
    //   9138: invokevirtual getReturnType : ()Ljava/lang/Class;
    //   9141: getstatic java/lang/Boolean.TYPE : Ljava/lang/Class;
    //   9144: if_acmpne -> 9215
    //   9147: goto -> 9154
    //   9150: invokestatic a : (Ljava/lang/Throwable;)Ljava/lang/Throwable;
    //   9153: athrow
    //   9154: aload #8
    //   9156: iconst_1
    //   9157: invokevirtual setAccessible : (Z)V
    //   9160: aload #8
    //   9162: aconst_null
    //   9163: iconst_2
    //   9164: anewarray java/lang/Object
    //   9167: dup
    //   9168: iconst_0
    //   9169: aload_0
    //   9170: aastore
    //   9171: dup
    //   9172: iconst_1
    //   9173: aload_1
    //   9174: ifnonnull -> 9192
    //   9177: goto -> 9184
    //   9180: invokestatic a : (Ljava/lang/Throwable;)Ljava/lang/Throwable;
    //   9183: athrow
    //   9184: aload_1
    //   9185: goto -> 9199
    //   9188: invokestatic a : (Ljava/lang/Throwable;)Ljava/lang/Throwable;
    //   9191: athrow
    //   9192: aload_1
    //   9193: checkcast [B
    //   9196: invokevirtual clone : ()Ljava/lang/Object;
    //   9199: aastore
    //   9200: invokevirtual invoke : (Ljava/lang/Object;[Ljava/lang/Object;)Ljava/lang/Object;
    //   9203: checkcast java/lang/Boolean
    //   9206: invokevirtual booleanValue : ()Z
    //   9209: istore #4
    //   9211: iload_2
    //   9212: ifeq -> 9229
    //   9215: iinc #7, 1
    //   9218: iload_2
    //   9219: ifeq -> 9088
    //   9222: goto -> 9229
    //   9225: invokestatic a : (Ljava/lang/Throwable;)Ljava/lang/Throwable;
    //   9228: athrow
    //   9229: iload_2
    //   9230: ifeq -> 9572
    //   9233: sipush #-23397
    //   9236: sipush #-24086
    //   9239: invokestatic a : (II)Ljava/lang/String;
    //   9242: iconst_1
    //   9243: ldc burp/Zly7
    //   9245: invokevirtual getClassLoader : ()Ljava/lang/ClassLoader;
    //   9248: invokestatic forName : (Ljava/lang/String;ZLjava/lang/ClassLoader;)Ljava/lang/Class;
    //   9251: invokevirtual getDeclaredFields : ()[Ljava/lang/reflect/Field;
    //   9254: astore #5
    //   9256: aload #5
    //   9258: arraylength
    //   9259: istore #6
    //   9261: iconst_0
    //   9262: istore #7
    //   9264: iload #7
    //   9266: iload #6
    //   9268: if_icmpge -> 9406
    //   9271: aload #5
    //   9273: iload #7
    //   9275: aaload
    //   9276: astore #8
    //   9278: aload #8
    //   9280: invokevirtual getModifiers : ()I
    //   9283: invokestatic isStatic : (I)Z
    //   9286: ifne -> 9296
    //   9289: goto -> 9399
    //   9292: invokestatic a : (Ljava/lang/Throwable;)Ljava/lang/Throwable;
    //   9295: athrow
    //   9296: aload #8
    //   9298: invokevirtual getType : ()Ljava/lang/Class;
    //   9301: astore #9
    //   9303: aload #9
    //   9305: ifnull -> 9386
    //   9308: aload #9
    //   9310: invokevirtual isPrimitive : ()Z
    //   9313: ifne -> 9386
    //   9316: goto -> 9323
    //   9319: invokestatic a : (Ljava/lang/Throwable;)Ljava/lang/Throwable;
    //   9322: athrow
    //   9323: aload #9
    //   9325: invokevirtual getPackage : ()Ljava/lang/Package;
    //   9328: ifnull -> 9386
    //   9331: goto -> 9338
    //   9334: invokestatic a : (Ljava/lang/Throwable;)Ljava/lang/Throwable;
    //   9337: athrow
    //   9338: aload #9
    //   9340: invokevirtual getPackage : ()Ljava/lang/Package;
    //   9343: invokevirtual getName : ()Ljava/lang/String;
    //   9346: ifnull -> 9386
    //   9349: goto -> 9356
    //   9352: invokestatic a : (Ljava/lang/Throwable;)Ljava/lang/Throwable;
    //   9355: athrow
    //   9356: aload #9
    //   9358: invokevirtual getPackage : ()Ljava/lang/Package;
    //   9361: invokevirtual getName : ()Ljava/lang/String;
    //   9364: sipush #-23414
    //   9367: sipush #-30892
    //   9370: invokestatic a : (II)Ljava/lang/String;
    //   9373: invokevirtual startsWith : (Ljava/lang/String;)Z
    //   9376: ifne -> 9386
    //   9379: goto -> 9386
    //   9382: invokestatic a : (Ljava/lang/Throwable;)Ljava/lang/Throwable;
    //   9385: athrow
    //   9386: aload #8
    //   9388: iconst_1
    //   9389: invokevirtual setAccessible : (Z)V
    //   9392: aload #8
    //   9394: aconst_null
    //   9395: invokevirtual get : (Ljava/lang/Object;)Ljava/lang/Object;
    //   9398: pop
    //   9399: iinc #7, 1
    //   9402: iload_2
    //   9403: ifeq -> 9264
    //   9406: sipush #-23415
    //   9409: sipush #-24281
    //   9412: invokestatic a : (II)Ljava/lang/String;
    //   9415: invokestatic forName : (Ljava/lang/String;)Ljava/lang/Class;
    //   9418: invokevirtual getDeclaredMethods : ()[Ljava/lang/reflect/Method;
    //   9421: astore #5
    //   9423: aload #5
    //   9425: arraylength
    //   9426: istore #6
    //   9428: iconst_0
    //   9429: istore #7
    //   9431: iload #7
    //   9433: iload #6
    //   9435: if_icmpge -> 9572
    //   9438: aload #5
    //   9440: iload #7
    //   9442: aaload
    //   9443: astore #8
    //   9445: aload #8
    //   9447: invokevirtual getParameterTypes : ()[Ljava/lang/Class;
    //   9450: pop
    //   9451: aload #8
    //   9453: invokevirtual getModifiers : ()I
    //   9456: invokestatic isStatic : (I)Z
    //   9459: ifeq -> 9558
    //   9462: aload #8
    //   9464: invokevirtual getParameterTypes : ()[Ljava/lang/Class;
    //   9467: arraylength
    //   9468: iconst_2
    //   9469: if_icmpne -> 9558
    //   9472: goto -> 9479
    //   9475: invokestatic a : (Ljava/lang/Throwable;)Ljava/lang/Throwable;
    //   9478: athrow
    //   9479: aload #8
    //   9481: invokevirtual getReturnType : ()Ljava/lang/Class;
    //   9484: getstatic java/lang/Boolean.TYPE : Ljava/lang/Class;
    //   9487: if_acmpne -> 9558
    //   9490: goto -> 9497
    //   9493: invokestatic a : (Ljava/lang/Throwable;)Ljava/lang/Throwable;
    //   9496: athrow
    //   9497: aload #8
    //   9499: iconst_1
    //   9500: invokevirtual setAccessible : (Z)V
    //   9503: aload #8
    //   9505: aconst_null
    //   9506: iconst_2
    //   9507: anewarray java/lang/Object
    //   9510: dup
    //   9511: iconst_0
    //   9512: aload_0
    //   9513: aastore
    //   9514: dup
    //   9515: iconst_1
    //   9516: aload_1
    //   9517: ifnonnull -> 9535
    //   9520: goto -> 9527
    //   9523: invokestatic a : (Ljava/lang/Throwable;)Ljava/lang/Throwable;
    //   9526: athrow
    //   9527: aload_1
    //   9528: goto -> 9542
    //   9531: invokestatic a : (Ljava/lang/Throwable;)Ljava/lang/Throwable;
    //   9534: athrow
    //   9535: aload_1
    //   9536: checkcast [B
    //   9539: invokevirtual clone : ()Ljava/lang/Object;
    //   9542: aastore
    //   9543: invokevirtual invoke : (Ljava/lang/Object;[Ljava/lang/Object;)Ljava/lang/Object;
    //   9546: checkcast java/lang/Boolean
    //   9549: invokevirtual booleanValue : ()Z
    //   9552: istore #4
    //   9554: iload_2
    //   9555: ifeq -> 9572
    //   9558: iinc #7, 1
    //   9561: iload_2
    //   9562: ifeq -> 9431
    //   9565: goto -> 9572
    //   9568: invokestatic a : (Ljava/lang/Throwable;)Ljava/lang/Throwable;
    //   9571: athrow
    //   9572: iload #4
    //   9574: ireturn
    //   9575: astore_3
    //   9576: new java/lang/Exception
    //   9579: dup
    //   9580: aload_3
    //   9581: invokevirtual getMessage : ()Ljava/lang/String;
    //   9584: invokespecial <init> : (Ljava/lang/String;)V
    //   9587: athrow
    // Exception table:
    //   from	to	target	type
    //   4	7374	9575	java/lang/Throwable
    //   33	47	50	java/lang/Throwable
    //   40	61	64	java/lang/Throwable
    //   54	75	78	java/lang/Throwable
    //   68	89	92	java/lang/Throwable
    //   82	103	106	java/lang/Throwable
    //   96	117	120	java/lang/Throwable
    //   110	131	134	java/lang/Throwable
    //   124	145	148	java/lang/Throwable
    //   138	155	158	java/lang/Throwable
    //   194	208	211	java/lang/Throwable
    //   201	222	225	java/lang/Throwable
    //   215	236	239	java/lang/Throwable
    //   229	250	253	java/lang/Throwable
    //   243	264	267	java/lang/Throwable
    //   257	278	281	java/lang/Throwable
    //   271	292	295	java/lang/Throwable
    //   285	306	309	java/lang/Throwable
    //   299	323	326	java/lang/Throwable
    //   387	405	408	java/lang/Throwable
    //   396	421	424	java/lang/Throwable
    //   412	438	441	java/lang/Throwable
    //   428	454	457	java/lang/Throwable
    //   445	471	474	java/lang/Throwable
    //   461	487	490	java/lang/Throwable
    //   478	503	506	java/lang/Throwable
    //   494	526	529	java/lang/Throwable
    //   510	542	545	java/lang/Throwable
    //   533	558	561	java/lang/Throwable
    //   549	581	584	java/lang/Throwable
    //   565	597	600	java/lang/Throwable
    //   588	613	616	java/lang/Throwable
    //   604	632	635	java/lang/Throwable
    //   762	797	800	java/lang/Throwable
    //   804	845	848	java/lang/Throwable
    //   889	1062	1065	java/lang/Throwable
    //   1032	1099	1102	java/lang/Throwable
    //   1069	1136	1139	java/lang/Throwable
    //   1106	1173	1176	java/lang/Throwable
    //   1143	1210	1213	java/lang/Throwable
    //   1180	1247	1250	java/lang/Throwable
    //   1217	1284	1287	java/lang/Throwable
    //   1254	1321	1324	java/lang/Throwable
    //   1291	1358	1361	java/lang/Throwable
    //   1328	1395	1398	java/lang/Throwable
    //   1365	1432	1435	java/lang/Throwable
    //   1402	1469	1472	java/lang/Throwable
    //   1439	1506	1509	java/lang/Throwable
    //   1476	1543	1546	java/lang/Throwable
    //   1513	1580	1583	java/lang/Throwable
    //   1550	1617	1620	java/lang/Throwable
    //   1587	1654	1657	java/lang/Throwable
    //   1624	1691	1694	java/lang/Throwable
    //   1661	1728	1731	java/lang/Throwable
    //   1698	1765	1768	java/lang/Throwable
    //   1735	1802	1805	java/lang/Throwable
    //   1772	1839	1842	java/lang/Throwable
    //   1809	1876	1879	java/lang/Throwable
    //   1846	1913	1916	java/lang/Throwable
    //   1883	1950	1953	java/lang/Throwable
    //   1920	1987	1990	java/lang/Throwable
    //   1957	2024	2027	java/lang/Throwable
    //   1994	2061	2064	java/lang/Throwable
    //   2031	2098	2101	java/lang/Throwable
    //   2068	2135	2138	java/lang/Throwable
    //   2105	2172	2175	java/lang/Throwable
    //   2142	2205	2208	java/lang/Throwable
    //   3029	3063	3066	java/lang/Throwable
    //   3159	3237	3240	java/lang/Throwable
    //   3166	3380	3383	java/lang/Throwable
    //   3758	3773	3773	java/lang/Throwable
    //   3800	3834	3837	java/lang/Throwable
    //   3844	3856	3859	java/lang/Throwable
    //   3942	4020	4023	java/lang/Throwable
    //   3949	4163	4166	java/lang/Throwable
    //   4563	4641	4644	java/lang/Throwable
    //   4570	4784	4787	java/lang/Throwable
    //   5231	5265	5268	java/lang/Throwable
    //   5272	5284	5287	java/lang/Throwable
    //   5370	5448	5451	java/lang/Throwable
    //   5377	5591	5594	java/lang/Throwable
    //   6348	6362	6362	java/lang/Throwable
    //   6373	6386	6389	java/lang/Throwable
    //   6378	6401	6404	java/lang/Throwable
    //   6393	6419	6422	java/lang/Throwable
    //   6408	6449	6452	java/lang/Throwable
    //   6515	6542	6545	java/lang/Throwable
    //   6532	6563	6566	java/lang/Throwable
    //   6549	6593	6596	java/lang/Throwable
    //   6570	6604	6604	java/lang/Throwable
    //   6615	6631	6634	java/lang/Throwable
    //   6731	6745	6745	java/lang/Throwable
    //   6756	6769	6772	java/lang/Throwable
    //   6761	6784	6787	java/lang/Throwable
    //   6776	6802	6805	java/lang/Throwable
    //   6791	6832	6835	java/lang/Throwable
    //   6898	6925	6928	java/lang/Throwable
    //   6915	6943	6946	java/lang/Throwable
    //   6932	6973	6976	java/lang/Throwable
    //   6950	6984	6984	java/lang/Throwable
    //   7007	7018	7021	java/lang/Throwable
    //   7073	7087	7087	java/lang/Throwable
    //   7098	7111	7114	java/lang/Throwable
    //   7103	7126	7129	java/lang/Throwable
    //   7118	7144	7147	java/lang/Throwable
    //   7133	7174	7177	java/lang/Throwable
    //   7240	7267	7270	java/lang/Throwable
    //   7257	7285	7288	java/lang/Throwable
    //   7274	7315	7318	java/lang/Throwable
    //   7292	7326	7326	java/lang/Throwable
    //   7349	7360	7363	java/lang/Throwable
    //   7375	8109	9575	java/lang/Throwable
    //   7465	7479	7479	java/lang/Throwable
    //   7490	7503	7506	java/lang/Throwable
    //   7495	7518	7521	java/lang/Throwable
    //   7510	7536	7539	java/lang/Throwable
    //   7525	7566	7569	java/lang/Throwable
    //   7632	7659	7662	java/lang/Throwable
    //   7649	7677	7680	java/lang/Throwable
    //   7666	7707	7710	java/lang/Throwable
    //   7684	7718	7718	java/lang/Throwable
    //   7741	7752	7755	java/lang/Throwable
    //   7808	7822	7822	java/lang/Throwable
    //   7833	7846	7849	java/lang/Throwable
    //   7838	7861	7864	java/lang/Throwable
    //   7853	7879	7882	java/lang/Throwable
    //   7868	7909	7912	java/lang/Throwable
    //   7975	8002	8005	java/lang/Throwable
    //   7992	8020	8023	java/lang/Throwable
    //   8009	8050	8053	java/lang/Throwable
    //   8027	8061	8061	java/lang/Throwable
    //   8084	8095	8098	java/lang/Throwable
    //   8110	8844	9575	java/lang/Throwable
    //   8200	8214	8214	java/lang/Throwable
    //   8225	8238	8241	java/lang/Throwable
    //   8230	8253	8256	java/lang/Throwable
    //   8245	8271	8274	java/lang/Throwable
    //   8260	8301	8304	java/lang/Throwable
    //   8367	8394	8397	java/lang/Throwable
    //   8384	8412	8415	java/lang/Throwable
    //   8401	8442	8445	java/lang/Throwable
    //   8419	8453	8453	java/lang/Throwable
    //   8476	8487	8490	java/lang/Throwable
    //   8543	8557	8557	java/lang/Throwable
    //   8568	8581	8584	java/lang/Throwable
    //   8573	8596	8599	java/lang/Throwable
    //   8588	8614	8617	java/lang/Throwable
    //   8603	8644	8647	java/lang/Throwable
    //   8710	8737	8740	java/lang/Throwable
    //   8727	8755	8758	java/lang/Throwable
    //   8744	8785	8788	java/lang/Throwable
    //   8762	8796	8796	java/lang/Throwable
    //   8819	8830	8833	java/lang/Throwable
    //   8845	9574	9575	java/lang/Throwable
    //   8935	8949	8949	java/lang/Throwable
    //   8960	8973	8976	java/lang/Throwable
    //   8965	8988	8991	java/lang/Throwable
    //   8980	9006	9009	java/lang/Throwable
    //   8995	9036	9039	java/lang/Throwable
    //   9102	9129	9132	java/lang/Throwable
    //   9119	9147	9150	java/lang/Throwable
    //   9136	9177	9180	java/lang/Throwable
    //   9154	9188	9188	java/lang/Throwable
    //   9211	9222	9225	java/lang/Throwable
    //   9278	9292	9292	java/lang/Throwable
    //   9303	9316	9319	java/lang/Throwable
    //   9308	9331	9334	java/lang/Throwable
    //   9323	9349	9352	java/lang/Throwable
    //   9338	9379	9382	java/lang/Throwable
    //   9445	9472	9475	java/lang/Throwable
    //   9462	9490	9493	java/lang/Throwable
    //   9479	9520	9523	java/lang/Throwable
    //   9497	9531	9531	java/lang/Throwable
    //   9554	9565	9568	java/lang/Throwable
  }
  
  static void ZU(Object[] paramArrayOfObject, Object paramObject) throws Throwable {}
  
  static void Zf(Object paramObject) {
    Zgsb.ZM = a(-23395, -24653);
    Zgsb.Zl = new BigInteger(a(-23420, -10316));
    boolean bool = Zt2e.ZK();
    try {
      try {
        if (Ztq4.Zb.charAt(Math.abs(((BigInteger)Zebc.Zr).intValue() % 32)) > Zz4a.ZC.charAt(Math.abs(((BigInteger)Zkdq.ZG).intValue() % 32))) {
          try {
            Zb3p.Zp(Class.forName(a(-23423, -12106)));
            if (bool)
              Zld9.ZO(Class.forName(a(-23413, 8002))); 
          } catch (Throwable throwable) {
            throw a(null);
          } 
          return;
        } 
      } catch (Throwable throwable) {
        throw a(null);
      } 
      Zld9.ZO(Class.forName(a(-23413, 8002)));
    } catch (Throwable throwable) {}
  }
  
  static {
    // Byte code:
    //   0: bipush #25
    //   2: anewarray java/lang/String
    //   5: astore #5
    //   7: iconst_0
    //   8: istore_3
    //   9: ldc ''Il$\\tYqNQ\\tdqXC[\\t,>\\b\\tEy|B\\f\\bNAE\\n{G\\n\\t'lhMz%!3D7!+znC6&k]HAw,#A(?8Vi=sQ\\r\\t\\fY\\tLaC\\tO"T\\tx\\t\\nT!\\t2e\\t3<+S\\b*\\tEc]\\tLM3 .<<1&~a,9A QU\\t{\\rt\\tY;q $p3W\\n9\\tInDq/\\t\\nL]T!A'
    //   11: dup
    //   12: astore_2
    //   13: invokevirtual length : ()I
    //   16: istore #4
    //   18: bipush #9
    //   20: istore_1
    //   21: iconst_m1
    //   22: istore_0
    //   23: bipush #28
    //   25: iinc #0, 1
    //   28: aload_2
    //   29: iload_0
    //   30: dup
    //   31: iload_1
    //   32: iadd
    //   33: invokevirtual substring : (II)Ljava/lang/String;
    //   36: iconst_m1
    //   37: goto -> 143
    //   40: aload #5
    //   42: swap
    //   43: iload_3
    //   44: iinc #3, 1
    //   47: swap
    //   48: aastore
    //   49: iload_0
    //   50: iload_1
    //   51: iadd
    //   52: dup
    //   53: istore_0
    //   54: iload #4
    //   56: if_icmpge -> 68
    //   59: aload_2
    //   60: iload_0
    //   61: invokevirtual charAt : (I)C
    //   64: istore_1
    //   65: goto -> 23
    //   68: ldc '#j7;e\\tzIsr'
    //   70: dup
    //   71: astore_2
    //   72: invokevirtual length : ()I
    //   75: istore #4
    //   77: bipush #8
    //   79: istore_1
    //   80: iconst_m1
    //   81: istore_0
    //   82: bipush #20
    //   84: iinc #0, 1
    //   87: aload_2
    //   88: iload_0
    //   89: dup
    //   90: iload_1
    //   91: iadd
    //   92: invokevirtual substring : (II)Ljava/lang/String;
    //   95: iconst_0
    //   96: goto -> 143
    //   99: aload #5
    //   101: swap
    //   102: iload_3
    //   103: iinc #3, 1
    //   106: swap
    //   107: aastore
    //   108: iload_0
    //   109: iload_1
    //   110: iadd
    //   111: dup
    //   112: istore_0
    //   113: iload #4
    //   115: if_icmpge -> 127
    //   118: aload_2
    //   119: iload_0
    //   120: invokevirtual charAt : (I)C
    //   123: istore_1
    //   124: goto -> 82
    //   127: aload #5
    //   129: putstatic burp/Zti7.a : [Ljava/lang/String;
    //   132: bipush #25
    //   134: anewarray java/lang/String
    //   137: putstatic burp/Zti7.b : [Ljava/lang/String;
    //   140: goto -> 300
    //   143: dup_x2
    //   144: pop
    //   145: invokevirtual toCharArray : ()[C
    //   148: dup_x1
    //   149: arraylength
    //   150: dup_x2
    //   151: pop
    //   152: iconst_0
    //   153: istore #6
    //   155: dup2_x1
    //   156: pop2
    //   157: dup_x2
    //   158: iconst_1
    //   159: if_icmpgt -> 259
    //   162: dup2
    //   163: swap
    //   164: iload #6
    //   166: dup2_x1
    //   167: caload
    //   168: swap
    //   169: iload #6
    //   171: bipush #7
    //   173: irem
    //   174: tableswitch default -> 241, 0 -> 212, 1 -> 217, 2 -> 221, 3 -> 226, 4 -> 231, 5 -> 236
    //   212: bipush #13
    //   214: goto -> 243
    //   217: iconst_4
    //   218: goto -> 243
    //   221: bipush #56
    //   223: goto -> 243
    //   226: bipush #60
    //   228: goto -> 243
    //   231: bipush #94
    //   233: goto -> 243
    //   236: bipush #81
    //   238: goto -> 243
    //   241: bipush #70
    //   243: ixor
    //   244: ixor
    //   245: i2c
    //   246: castore
    //   247: iinc #6, 1
    //   250: dup
    //   251: ifne -> 259
    //   254: dup2
    //   255: dup_x1
    //   256: goto -> 166
    //   259: dup2_x1
    //   260: pop2
    //   261: dup_x2
    //   262: iload #6
    //   264: if_icmpgt -> 162
    //   267: pop
    //   268: new java/lang/String
    //   271: dup_x1
    //   272: swap
    //   273: invokespecial <init> : ([C)V
    //   276: invokevirtual intern : ()Ljava/lang/String;
    //   279: swap
    //   280: pop
    //   281: swap
    //   282: tableswitch default -> 40, 0 -> 99
    //   300: new java/math/BigInteger
    //   303: dup
    //   304: bipush #32
    //   306: newarray byte
    //   308: dup
    //   309: iconst_0
    //   310: bipush #37
    //   312: bastore
    //   313: dup
    //   314: iconst_1
    //   315: bipush #31
    //   317: bastore
    //   318: dup
    //   319: iconst_2
    //   320: bipush #-49
    //   322: bastore
    //   323: dup
    //   324: iconst_3
    //   325: bipush #-72
    //   327: bastore
    //   328: dup
    //   329: iconst_4
    //   330: bipush #-56
    //   332: bastore
    //   333: dup
    //   334: iconst_5
    //   335: bipush #-122
    //   337: bastore
    //   338: dup
    //   339: bipush #6
    //   341: bipush #-106
    //   343: bastore
    //   344: dup
    //   345: bipush #7
    //   347: bipush #-6
    //   349: bastore
    //   350: dup
    //   351: bipush #8
    //   353: bipush #103
    //   355: bastore
    //   356: dup
    //   357: bipush #9
    //   359: bipush #97
    //   361: bastore
    //   362: dup
    //   363: bipush #10
    //   365: bipush #-11
    //   367: bastore
    //   368: dup
    //   369: bipush #11
    //   371: bipush #-87
    //   373: bastore
    //   374: dup
    //   375: bipush #12
    //   377: bipush #-2
    //   379: bastore
    //   380: dup
    //   381: bipush #13
    //   383: bipush #-93
    //   385: bastore
    //   386: dup
    //   387: bipush #14
    //   389: bipush #-43
    //   391: bastore
    //   392: dup
    //   393: bipush #15
    //   395: bipush #-13
    //   397: bastore
    //   398: dup
    //   399: bipush #16
    //   401: bipush #60
    //   403: bastore
    //   404: dup
    //   405: bipush #17
    //   407: bipush #-89
    //   409: bastore
    //   410: dup
    //   411: bipush #18
    //   413: bipush #69
    //   415: bastore
    //   416: dup
    //   417: bipush #19
    //   419: bipush #111
    //   421: bastore
    //   422: dup
    //   423: bipush #20
    //   425: bipush #-34
    //   427: bastore
    //   428: dup
    //   429: bipush #21
    //   431: bipush #124
    //   433: bastore
    //   434: dup
    //   435: bipush #22
    //   437: bipush #55
    //   439: bastore
    //   440: dup
    //   441: bipush #23
    //   443: bipush #-29
    //   445: bastore
    //   446: dup
    //   447: bipush #24
    //   449: bipush #26
    //   451: bastore
    //   452: dup
    //   453: bipush #25
    //   455: bipush #30
    //   457: bastore
    //   458: dup
    //   459: bipush #26
    //   461: bipush #32
    //   463: bastore
    //   464: dup
    //   465: bipush #27
    //   467: bipush #-128
    //   469: bastore
    //   470: dup
    //   471: bipush #28
    //   473: bipush #87
    //   475: bastore
    //   476: dup
    //   477: bipush #29
    //   479: bipush #-112
    //   481: bastore
    //   482: dup
    //   483: bipush #30
    //   485: bipush #125
    //   487: bastore
    //   488: dup
    //   489: bipush #31
    //   491: bipush #-88
    //   493: bastore
    //   494: invokespecial <init> : ([B)V
    //   497: putstatic burp/Zti7.Zw : Ljava/lang/Object;
    //   500: sipush #-23400
    //   503: sipush #23282
    //   506: invokestatic a : (II)Ljava/lang/String;
    //   509: putstatic burp/Zti7.Zc : Ljava/lang/String;
    //   512: return
  }
  
  private static Throwable a(Throwable paramThrowable) {
    return paramThrowable;
  }
  
  private static String a(int paramInt1, int paramInt2) {
    int i = (paramInt1 ^ 0xFFFFA48C) & 0xFFFF;
    if (b[i] == null) {
      char[] arrayOfChar = a[i].toCharArray();
      switch (arrayOfChar[0] & 0xFF) {
        case 0:
        
        case 1:
        
        case 2:
        
        case 3:
        
        case 4:
        
        case 5:
        
        case 6:
        
        case 7:
        
        case 8:
        
        case 9:
        
        case 10:
        
        case 11:
        
        case 12:
        
        case 13:
        
        case 14:
        
        case 15:
        
        case 16:
        
        case 17:
        
        case 18:
        
        case 19:
        
        case 20:
        
        case 21:
        
        case 22:
        
        case 23:
        
        case 24:
        
        case 25:
        
        case 26:
        
        case 27:
        
        case 28:
        
        case 29:
        
        case 30:
        
        case 31:
        
        case 32:
        
        case 33:
        
        case 34:
        
        case 35:
        
        case 36:
        
        case 37:
        
        case 38:
        
        case 39:
        
        case 40:
        
        case 41:
        
        case 42:
        
        case 43:
        
        case 44:
        
        case 45:
        
        case 46:
        
        case 47:
        
        case 48:
        
        case 49:
        
        case 50:
        
        case 51:
        
        case 52:
        
        case 53:
        
        case 54:
        
        case 55:
        
        case 56:
        
        case 57:
        
        case 58:
        
        case 59:
        
        case 60:
        
        case 61:
        
        case 62:
        
        case 63:
        
        case 64:
        
        case 65:
        
        case 66:
        
        case 67:
        
        case 68:
        
        case 69:
        
        case 70:
        
        case 71:
        
        case 72:
        
        case 73:
        
        case 74:
        
        case 75:
        
        case 76:
        
        case 77:
        
        case 78:
        
        case 79:
        
        case 80:
        
        case 81:
        
        case 82:
        
        case 83:
        
        case 84:
        
        case 85:
        
        case 86:
        
        case 87:
        
        case 88:
        
        case 89:
        
        case 90:
        
        case 91:
        
        case 92:
        
        case 93:
        
        case 94:
        
        case 95:
        
        case 96:
        
        case 97:
        
        case 98:
        
        case 99:
        
        case 100:
        
        case 101:
        
        case 102:
        
        case 103:
        
        case 104:
        
        case 105:
        
        case 106:
        
        case 107:
        
        case 108:
        
        case 109:
        
        case 110:
        
        case 111:
        
        case 112:
        
        case 113:
        
        case 114:
        
        case 115:
        
        case 116:
        
        case 117:
        
        case 118:
        
        case 119:
        
        case 120:
        
        case 121:
        
        case 122:
        
        case 123:
        
        case 124:
        
        case 125:
        
        case 126:
        
        case 127:
        
        case 128:
        
        case 129:
        
        case 130:
        
        case 131:
        
        case 132:
        
        case 133:
        
        case 134:
        
        case 135:
        
        case 136:
        
        case 137:
        
        case 138:
        
        case 139:
        
        case 140:
        
        case 141:
        
        case 142:
        
        case 143:
        
        case 144:
        
        case 145:
        
        case 146:
        
        case 147:
        
        case 148:
        
        case 149:
        
        case 150:
        
        case 151:
        
        case 152:
        
        case 153:
        
        case 154:
        
        case 155:
        
        case 156:
        
        case 157:
        
        case 158:
        
        case 159:
        
        case 160:
        
        case 161:
        
        case 162:
        
        case 163:
        
        case 164:
        
        case 165:
        
        case 166:
        
        case 167:
        
        case 168:
        
        case 169:
        
        case 170:
        
        case 171:
        
        case 172:
        
        case 173:
        
        case 174:
        
        case 175:
        
        case 176:
        
        case 177:
        
        case 178:
        
        case 179:
        
        case 180:
        
        case 181:
        
        case 182:
        
        case 183:
        
        case 184:
        
        case 185:
        
        case 186:
        
        case 187:
        
        case 188:
        
        case 189:
        
        case 190:
        
        case 191:
        
        case 192:
        
        case 193:
        
        case 194:
        
        case 195:
        
        case 196:
        
        case 197:
        
        case 198:
        
        case 199:
        
        case 200:
        
        case 201:
        
        case 202:
        
        case 203:
        
        case 204:
        
        case 205:
        
        case 206:
        
        case 207:
        
        case 208:
        
        case 209:
        
        case 210:
        
        case 211:
        
        case 212:
        
        case 213:
        
        case 214:
        
        case 215:
        
        case 216:
        
        case 217:
        
        case 218:
        
        case 219:
        
        case 220:
        
        case 221:
        
        case 222:
        
        case 223:
        
        case 224:
        
        case 225:
        
        case 226:
        
        case 227:
        
        case 228:
        
        case 229:
        
        case 230:
        
        case 231:
        
        case 232:
        
        case 233:
        
        case 234:
        
        case 235:
        
        case 236:
        
        case 237:
        
        case 238:
        
        case 239:
        
        case 240:
        
        case 241:
        
        case 242:
        
        case 243:
        
        case 244:
        
        case 245:
        
        case 246:
        
        case 247:
        
        case 248:
        
        case 249:
        
        case 250:
        
        case 251:
        
        case 252:
        
        case 253:
        
        case 254:
        
        default:
          break;
      } 
      char c = '';
      int j = (paramInt2 & 0xFF) - c;
      if (j < 0)
        j += 256; 
      int k = ((paramInt2 & 0xFFFF) >>> 8) - c;
      if (k < 0)
        k += 256; 
      for (byte b = 0; b < arrayOfChar.length; b++) {
        int m = b % 2;
        if (m == 0) {
          arrayOfChar[b] = (char)(arrayOfChar[b] ^ j);
          j = ((j >>> 3 | j << 5) ^ arrayOfChar[b]) & 0xFF;
        } else {
          arrayOfChar[b] = (char)(arrayOfChar[b] ^ k);
          k = ((k >>> 3 | k << 5) ^ arrayOfChar[b]) & 0xFF;
        } 
      } 
      b[i] = (new String(arrayOfChar)).intern();
    } 
    return b[i];
  }
}


/* Location:              C:\Program Files\BurpSuitePro\burpsuite_pro.jar!\burp\Zti7.class
 * Java compiler version: 21 (65.0)
 * JD-Core Version:       1.1.3
 */