package burp;

import java.math.BigInteger;

class Ztid extends ClassLoader {
  static Object ZL;
  
  static String Zz;
  
  private static final String[] a;
  
  private static final String[] b;
  
  static void ZV(Object[] paramArrayOfObject, Object paramObject) throws Throwable {}
  
  static boolean ZP(Object[] paramArrayOfObject, Object paramObject) throws Throwable {
    // Byte code:
    //   0: invokestatic ZK : ()Z
    //   3: istore_2
    //   4: new java/lang/StringBuilder
    //   7: dup
    //   8: invokespecial <init> : ()V
    //   11: astore_3
    //   12: iconst_0
    //   13: istore #4
    //   15: iload #4
    //   17: bipush #32
    //   19: if_icmpge -> 1355
    //   22: iload #4
    //   24: tableswitch default -> 1348, 0 -> 168, 1 -> 205, 2 -> 242, 3 -> 279, 4 -> 316, 5 -> 353, 6 -> 390, 7 -> 427, 8 -> 464, 9 -> 501, 10 -> 538, 11 -> 575, 12 -> 612, 13 -> 649, 14 -> 686, 15 -> 723, 16 -> 760, 17 -> 797, 18 -> 834, 19 -> 871, 20 -> 908, 21 -> 945, 22 -> 982, 23 -> 1019, 24 -> 1056, 25 -> 1093, 26 -> 1130, 27 -> 1167, 28 -> 1204, 29 -> 1241, 30 -> 1278, 31 -> 1315
    //   168: aload_3
    //   169: getstatic burp/Zblv.ZF : Ljava/lang/String;
    //   172: getstatic burp/Zz58.ZD : Ljava/lang/Object;
    //   175: checkcast java/math/BigInteger
    //   178: invokevirtual intValue : ()I
    //   181: bipush #32
    //   183: irem
    //   184: invokestatic abs : (I)I
    //   187: invokevirtual charAt : (I)C
    //   190: invokevirtual append : (C)Ljava/lang/StringBuilder;
    //   193: pop
    //   194: iload_2
    //   195: ifeq -> 1348
    //   198: goto -> 205
    //   201: invokestatic a : (Ljava/lang/Throwable;)Ljava/lang/Throwable;
    //   204: athrow
    //   205: aload_3
    //   206: getstatic burp/Ztd6.Zu : Ljava/lang/String;
    //   209: getstatic burp/Zmjr.ZU : Ljava/lang/Object;
    //   212: checkcast java/math/BigInteger
    //   215: invokevirtual intValue : ()I
    //   218: bipush #32
    //   220: irem
    //   221: invokestatic abs : (I)I
    //   224: invokevirtual charAt : (I)C
    //   227: invokevirtual append : (C)Ljava/lang/StringBuilder;
    //   230: pop
    //   231: iload_2
    //   232: ifeq -> 1348
    //   235: goto -> 242
    //   238: invokestatic a : (Ljava/lang/Throwable;)Ljava/lang/Throwable;
    //   241: athrow
    //   242: aload_3
    //   243: getstatic burp/Zxoa.Z_ : Ljava/lang/String;
    //   246: getstatic burp/Zl_9.ZM : Ljava/lang/Object;
    //   249: checkcast java/math/BigInteger
    //   252: invokevirtual intValue : ()I
    //   255: bipush #32
    //   257: irem
    //   258: invokestatic abs : (I)I
    //   261: invokevirtual charAt : (I)C
    //   264: invokevirtual append : (C)Ljava/lang/StringBuilder;
    //   267: pop
    //   268: iload_2
    //   269: ifeq -> 1348
    //   272: goto -> 279
    //   275: invokestatic a : (Ljava/lang/Throwable;)Ljava/lang/Throwable;
    //   278: athrow
    //   279: aload_3
    //   280: getstatic burp/Zead.Zo : Ljava/lang/String;
    //   283: getstatic burp/Ztte.ZR : Ljava/lang/Object;
    //   286: checkcast java/math/BigInteger
    //   289: invokevirtual intValue : ()I
    //   292: bipush #32
    //   294: irem
    //   295: invokestatic abs : (I)I
    //   298: invokevirtual charAt : (I)C
    //   301: invokevirtual append : (C)Ljava/lang/StringBuilder;
    //   304: pop
    //   305: iload_2
    //   306: ifeq -> 1348
    //   309: goto -> 316
    //   312: invokestatic a : (Ljava/lang/Throwable;)Ljava/lang/Throwable;
    //   315: athrow
    //   316: aload_3
    //   317: getstatic burp/Zzvr.Zc : Ljava/lang/String;
    //   320: getstatic burp/Zxrd.ZL : Ljava/lang/Object;
    //   323: checkcast java/math/BigInteger
    //   326: invokevirtual intValue : ()I
    //   329: bipush #32
    //   331: irem
    //   332: invokestatic abs : (I)I
    //   335: invokevirtual charAt : (I)C
    //   338: invokevirtual append : (C)Ljava/lang/StringBuilder;
    //   341: pop
    //   342: iload_2
    //   343: ifeq -> 1348
    //   346: goto -> 353
    //   349: invokestatic a : (Ljava/lang/Throwable;)Ljava/lang/Throwable;
    //   352: athrow
    //   353: aload_3
    //   354: getstatic burp/Zblv.ZF : Ljava/lang/String;
    //   357: getstatic burp/Zsgj.ZK : Ljava/lang/Object;
    //   360: checkcast java/math/BigInteger
    //   363: invokevirtual intValue : ()I
    //   366: bipush #32
    //   368: irem
    //   369: invokestatic abs : (I)I
    //   372: invokevirtual charAt : (I)C
    //   375: invokevirtual append : (C)Ljava/lang/StringBuilder;
    //   378: pop
    //   379: iload_2
    //   380: ifeq -> 1348
    //   383: goto -> 390
    //   386: invokestatic a : (Ljava/lang/Throwable;)Ljava/lang/Throwable;
    //   389: athrow
    //   390: aload_3
    //   391: getstatic burp/Zb3p.ZX : Ljava/lang/String;
    //   394: getstatic burp/Zg97.Zc : Ljava/lang/Object;
    //   397: checkcast java/math/BigInteger
    //   400: invokevirtual intValue : ()I
    //   403: bipush #32
    //   405: irem
    //   406: invokestatic abs : (I)I
    //   409: invokevirtual charAt : (I)C
    //   412: invokevirtual append : (C)Ljava/lang/StringBuilder;
    //   415: pop
    //   416: iload_2
    //   417: ifeq -> 1348
    //   420: goto -> 427
    //   423: invokestatic a : (Ljava/lang/Throwable;)Ljava/lang/Throwable;
    //   426: athrow
    //   427: aload_3
    //   428: getstatic burp/Zs36.Zr : Ljava/lang/String;
    //   431: getstatic burp/Zxtn.ZY : Ljava/lang/Object;
    //   434: checkcast java/math/BigInteger
    //   437: invokevirtual intValue : ()I
    //   440: bipush #32
    //   442: irem
    //   443: invokestatic abs : (I)I
    //   446: invokevirtual charAt : (I)C
    //   449: invokevirtual append : (C)Ljava/lang/StringBuilder;
    //   452: pop
    //   453: iload_2
    //   454: ifeq -> 1348
    //   457: goto -> 464
    //   460: invokestatic a : (Ljava/lang/Throwable;)Ljava/lang/Throwable;
    //   463: athrow
    //   464: aload_3
    //   465: getstatic burp/Zko9.Zf : Ljava/lang/String;
    //   468: getstatic burp/Zmiy.Zi : Ljava/lang/Object;
    //   471: checkcast java/math/BigInteger
    //   474: invokevirtual intValue : ()I
    //   477: bipush #32
    //   479: irem
    //   480: invokestatic abs : (I)I
    //   483: invokevirtual charAt : (I)C
    //   486: invokevirtual append : (C)Ljava/lang/StringBuilder;
    //   489: pop
    //   490: iload_2
    //   491: ifeq -> 1348
    //   494: goto -> 501
    //   497: invokestatic a : (Ljava/lang/Throwable;)Ljava/lang/Throwable;
    //   500: athrow
    //   501: aload_3
    //   502: getstatic burp/Zre1.ZA : Ljava/lang/String;
    //   505: getstatic burp/Zzwl.Z_ : Ljava/lang/Object;
    //   508: checkcast java/math/BigInteger
    //   511: invokevirtual intValue : ()I
    //   514: bipush #32
    //   516: irem
    //   517: invokestatic abs : (I)I
    //   520: invokevirtual charAt : (I)C
    //   523: invokevirtual append : (C)Ljava/lang/StringBuilder;
    //   526: pop
    //   527: iload_2
    //   528: ifeq -> 1348
    //   531: goto -> 538
    //   534: invokestatic a : (Ljava/lang/Throwable;)Ljava/lang/Throwable;
    //   537: athrow
    //   538: aload_3
    //   539: getstatic burp/Zsgj.ZN : Ljava/lang/String;
    //   542: getstatic burp/Zgny.ZR : Ljava/lang/Object;
    //   545: checkcast java/math/BigInteger
    //   548: invokevirtual intValue : ()I
    //   551: bipush #32
    //   553: irem
    //   554: invokestatic abs : (I)I
    //   557: invokevirtual charAt : (I)C
    //   560: invokevirtual append : (C)Ljava/lang/StringBuilder;
    //   563: pop
    //   564: iload_2
    //   565: ifeq -> 1348
    //   568: goto -> 575
    //   571: invokestatic a : (Ljava/lang/Throwable;)Ljava/lang/Throwable;
    //   574: athrow
    //   575: aload_3
    //   576: getstatic burp/Zltb.ZO : Ljava/lang/String;
    //   579: getstatic burp/Zei_.Za : Ljava/lang/Object;
    //   582: checkcast java/math/BigInteger
    //   585: invokevirtual intValue : ()I
    //   588: bipush #32
    //   590: irem
    //   591: invokestatic abs : (I)I
    //   594: invokevirtual charAt : (I)C
    //   597: invokevirtual append : (C)Ljava/lang/StringBuilder;
    //   600: pop
    //   601: iload_2
    //   602: ifeq -> 1348
    //   605: goto -> 612
    //   608: invokestatic a : (Ljava/lang/Throwable;)Ljava/lang/Throwable;
    //   611: athrow
    //   612: aload_3
    //   613: getstatic burp/Zljx.ZD : Ljava/lang/String;
    //   616: getstatic burp/Zrvb.ZD : Ljava/lang/Object;
    //   619: checkcast java/math/BigInteger
    //   622: invokevirtual intValue : ()I
    //   625: bipush #32
    //   627: irem
    //   628: invokestatic abs : (I)I
    //   631: invokevirtual charAt : (I)C
    //   634: invokevirtual append : (C)Ljava/lang/StringBuilder;
    //   637: pop
    //   638: iload_2
    //   639: ifeq -> 1348
    //   642: goto -> 649
    //   645: invokestatic a : (Ljava/lang/Throwable;)Ljava/lang/Throwable;
    //   648: athrow
    //   649: aload_3
    //   650: getstatic burp/Zs0b.ZT : Ljava/lang/String;
    //   653: getstatic burp/Ztid.ZL : Ljava/lang/Object;
    //   656: checkcast java/math/BigInteger
    //   659: invokevirtual intValue : ()I
    //   662: bipush #32
    //   664: irem
    //   665: invokestatic abs : (I)I
    //   668: invokevirtual charAt : (I)C
    //   671: invokevirtual append : (C)Ljava/lang/StringBuilder;
    //   674: pop
    //   675: iload_2
    //   676: ifeq -> 1348
    //   679: goto -> 686
    //   682: invokestatic a : (Ljava/lang/Throwable;)Ljava/lang/Throwable;
    //   685: athrow
    //   686: aload_3
    //   687: getstatic burp/Zgd7.Zs : Ljava/lang/String;
    //   690: getstatic burp/Zgii.ZD : Ljava/lang/Object;
    //   693: checkcast java/math/BigInteger
    //   696: invokevirtual intValue : ()I
    //   699: bipush #32
    //   701: irem
    //   702: invokestatic abs : (I)I
    //   705: invokevirtual charAt : (I)C
    //   708: invokevirtual append : (C)Ljava/lang/StringBuilder;
    //   711: pop
    //   712: iload_2
    //   713: ifeq -> 1348
    //   716: goto -> 723
    //   719: invokestatic a : (Ljava/lang/Throwable;)Ljava/lang/Throwable;
    //   722: athrow
    //   723: aload_3
    //   724: getstatic burp/Zs6g.ZU : Ljava/lang/String;
    //   727: getstatic burp/Ze3t.Zp : Ljava/lang/Object;
    //   730: checkcast java/math/BigInteger
    //   733: invokevirtual intValue : ()I
    //   736: bipush #32
    //   738: irem
    //   739: invokestatic abs : (I)I
    //   742: invokevirtual charAt : (I)C
    //   745: invokevirtual append : (C)Ljava/lang/StringBuilder;
    //   748: pop
    //   749: iload_2
    //   750: ifeq -> 1348
    //   753: goto -> 760
    //   756: invokestatic a : (Ljava/lang/Throwable;)Ljava/lang/Throwable;
    //   759: athrow
    //   760: aload_3
    //   761: getstatic burp/Zr3x.ZM : Ljava/lang/String;
    //   764: getstatic burp/Zxnm.ZW : Ljava/lang/Object;
    //   767: checkcast java/math/BigInteger
    //   770: invokevirtual intValue : ()I
    //   773: bipush #32
    //   775: irem
    //   776: invokestatic abs : (I)I
    //   779: invokevirtual charAt : (I)C
    //   782: invokevirtual append : (C)Ljava/lang/StringBuilder;
    //   785: pop
    //   786: iload_2
    //   787: ifeq -> 1348
    //   790: goto -> 797
    //   793: invokestatic a : (Ljava/lang/Throwable;)Ljava/lang/Throwable;
    //   796: athrow
    //   797: aload_3
    //   798: getstatic burp/Zmhx.ZD : Ljava/lang/String;
    //   801: getstatic burp/Zs_.Zs : Ljava/lang/Object;
    //   804: checkcast java/math/BigInteger
    //   807: invokevirtual intValue : ()I
    //   810: bipush #32
    //   812: irem
    //   813: invokestatic abs : (I)I
    //   816: invokevirtual charAt : (I)C
    //   819: invokevirtual append : (C)Ljava/lang/StringBuilder;
    //   822: pop
    //   823: iload_2
    //   824: ifeq -> 1348
    //   827: goto -> 834
    //   830: invokestatic a : (Ljava/lang/Throwable;)Ljava/lang/Throwable;
    //   833: athrow
    //   834: aload_3
    //   835: getstatic burp/Zs6g.ZU : Ljava/lang/String;
    //   838: getstatic burp/Zttj.ZF : Ljava/lang/Object;
    //   841: checkcast java/math/BigInteger
    //   844: invokevirtual intValue : ()I
    //   847: bipush #32
    //   849: irem
    //   850: invokestatic abs : (I)I
    //   853: invokevirtual charAt : (I)C
    //   856: invokevirtual append : (C)Ljava/lang/StringBuilder;
    //   859: pop
    //   860: iload_2
    //   861: ifeq -> 1348
    //   864: goto -> 871
    //   867: invokestatic a : (Ljava/lang/Throwable;)Ljava/lang/Throwable;
    //   870: athrow
    //   871: aload_3
    //   872: getstatic burp/Ze3t.ZG : Ljava/lang/String;
    //   875: getstatic burp/Zxrd.ZL : Ljava/lang/Object;
    //   878: checkcast java/math/BigInteger
    //   881: invokevirtual intValue : ()I
    //   884: bipush #32
    //   886: irem
    //   887: invokestatic abs : (I)I
    //   890: invokevirtual charAt : (I)C
    //   893: invokevirtual append : (C)Ljava/lang/StringBuilder;
    //   896: pop
    //   897: iload_2
    //   898: ifeq -> 1348
    //   901: goto -> 908
    //   904: invokestatic a : (Ljava/lang/Throwable;)Ljava/lang/Throwable;
    //   907: athrow
    //   908: aload_3
    //   909: getstatic burp/Zko9.Zf : Ljava/lang/String;
    //   912: getstatic burp/Zs36.Zs : Ljava/lang/Object;
    //   915: checkcast java/math/BigInteger
    //   918: invokevirtual intValue : ()I
    //   921: bipush #32
    //   923: irem
    //   924: invokestatic abs : (I)I
    //   927: invokevirtual charAt : (I)C
    //   930: invokevirtual append : (C)Ljava/lang/StringBuilder;
    //   933: pop
    //   934: iload_2
    //   935: ifeq -> 1348
    //   938: goto -> 945
    //   941: invokestatic a : (Ljava/lang/Throwable;)Ljava/lang/Throwable;
    //   944: athrow
    //   945: aload_3
    //   946: getstatic burp/Zxyq.Zr : Ljava/lang/String;
    //   949: getstatic burp/Zlno.ZU : Ljava/lang/Object;
    //   952: checkcast java/math/BigInteger
    //   955: invokevirtual intValue : ()I
    //   958: bipush #32
    //   960: irem
    //   961: invokestatic abs : (I)I
    //   964: invokevirtual charAt : (I)C
    //   967: invokevirtual append : (C)Ljava/lang/StringBuilder;
    //   970: pop
    //   971: iload_2
    //   972: ifeq -> 1348
    //   975: goto -> 982
    //   978: invokestatic a : (Ljava/lang/Throwable;)Ljava/lang/Throwable;
    //   981: athrow
    //   982: aload_3
    //   983: getstatic burp/Zgii.Ze : Ljava/lang/String;
    //   986: getstatic burp/Zb_u.Zp : Ljava/lang/Object;
    //   989: checkcast java/math/BigInteger
    //   992: invokevirtual intValue : ()I
    //   995: bipush #32
    //   997: irem
    //   998: invokestatic abs : (I)I
    //   1001: invokevirtual charAt : (I)C
    //   1004: invokevirtual append : (C)Ljava/lang/StringBuilder;
    //   1007: pop
    //   1008: iload_2
    //   1009: ifeq -> 1348
    //   1012: goto -> 1019
    //   1015: invokestatic a : (Ljava/lang/Throwable;)Ljava/lang/Throwable;
    //   1018: athrow
    //   1019: aload_3
    //   1020: getstatic burp/Zgwq.ZV : Ljava/lang/String;
    //   1023: getstatic burp/Zzv.Zu : Ljava/lang/Object;
    //   1026: checkcast java/math/BigInteger
    //   1029: invokevirtual intValue : ()I
    //   1032: bipush #32
    //   1034: irem
    //   1035: invokestatic abs : (I)I
    //   1038: invokevirtual charAt : (I)C
    //   1041: invokevirtual append : (C)Ljava/lang/StringBuilder;
    //   1044: pop
    //   1045: iload_2
    //   1046: ifeq -> 1348
    //   1049: goto -> 1056
    //   1052: invokestatic a : (Ljava/lang/Throwable;)Ljava/lang/Throwable;
    //   1055: athrow
    //   1056: aload_3
    //   1057: getstatic burp/Zzvr.Zc : Ljava/lang/String;
    //   1060: getstatic burp/Zgdj.ZT : Ljava/lang/Object;
    //   1063: checkcast java/math/BigInteger
    //   1066: invokevirtual intValue : ()I
    //   1069: bipush #32
    //   1071: irem
    //   1072: invokestatic abs : (I)I
    //   1075: invokevirtual charAt : (I)C
    //   1078: invokevirtual append : (C)Ljava/lang/StringBuilder;
    //   1081: pop
    //   1082: iload_2
    //   1083: ifeq -> 1348
    //   1086: goto -> 1093
    //   1089: invokestatic a : (Ljava/lang/Throwable;)Ljava/lang/Throwable;
    //   1092: athrow
    //   1093: aload_3
    //   1094: getstatic burp/Zkul.ZJ : Ljava/lang/String;
    //   1097: getstatic burp/Zejg.ZR : Ljava/lang/Object;
    //   1100: checkcast java/math/BigInteger
    //   1103: invokevirtual intValue : ()I
    //   1106: bipush #32
    //   1108: irem
    //   1109: invokestatic abs : (I)I
    //   1112: invokevirtual charAt : (I)C
    //   1115: invokevirtual append : (C)Ljava/lang/StringBuilder;
    //   1118: pop
    //   1119: iload_2
    //   1120: ifeq -> 1348
    //   1123: goto -> 1130
    //   1126: invokestatic a : (Ljava/lang/Throwable;)Ljava/lang/Throwable;
    //   1129: athrow
    //   1130: aload_3
    //   1131: getstatic burp/Zb3p.ZX : Ljava/lang/String;
    //   1134: getstatic burp/Zm06.ZU : Ljava/lang/Object;
    //   1137: checkcast java/math/BigInteger
    //   1140: invokevirtual intValue : ()I
    //   1143: bipush #32
    //   1145: irem
    //   1146: invokestatic abs : (I)I
    //   1149: invokevirtual charAt : (I)C
    //   1152: invokevirtual append : (C)Ljava/lang/StringBuilder;
    //   1155: pop
    //   1156: iload_2
    //   1157: ifeq -> 1348
    //   1160: goto -> 1167
    //   1163: invokestatic a : (Ljava/lang/Throwable;)Ljava/lang/Throwable;
    //   1166: athrow
    //   1167: aload_3
    //   1168: getstatic burp/Zgd7.Zs : Ljava/lang/String;
    //   1171: getstatic burp/Zb3p.Zx : Ljava/lang/Object;
    //   1174: checkcast java/math/BigInteger
    //   1177: invokevirtual intValue : ()I
    //   1180: bipush #32
    //   1182: irem
    //   1183: invokestatic abs : (I)I
    //   1186: invokevirtual charAt : (I)C
    //   1189: invokevirtual append : (C)Ljava/lang/StringBuilder;
    //   1192: pop
    //   1193: iload_2
    //   1194: ifeq -> 1348
    //   1197: goto -> 1204
    //   1200: invokestatic a : (Ljava/lang/Throwable;)Ljava/lang/Throwable;
    //   1203: athrow
    //   1204: aload_3
    //   1205: getstatic burp/Zm06.Zg : Ljava/lang/String;
    //   1208: getstatic burp/Zl_9.ZM : Ljava/lang/Object;
    //   1211: checkcast java/math/BigInteger
    //   1214: invokevirtual intValue : ()I
    //   1217: bipush #32
    //   1219: irem
    //   1220: invokestatic abs : (I)I
    //   1223: invokevirtual charAt : (I)C
    //   1226: invokevirtual append : (C)Ljava/lang/StringBuilder;
    //   1229: pop
    //   1230: iload_2
    //   1231: ifeq -> 1348
    //   1234: goto -> 1241
    //   1237: invokestatic a : (Ljava/lang/Throwable;)Ljava/lang/Throwable;
    //   1240: athrow
    //   1241: aload_3
    //   1242: getstatic burp/Zgny.Zf : Ljava/lang/String;
    //   1245: getstatic burp/Zb_u.Zp : Ljava/lang/Object;
    //   1248: checkcast java/math/BigInteger
    //   1251: invokevirtual intValue : ()I
    //   1254: bipush #32
    //   1256: irem
    //   1257: invokestatic abs : (I)I
    //   1260: invokevirtual charAt : (I)C
    //   1263: invokevirtual append : (C)Ljava/lang/StringBuilder;
    //   1266: pop
    //   1267: iload_2
    //   1268: ifeq -> 1348
    //   1271: goto -> 1278
    //   1274: invokestatic a : (Ljava/lang/Throwable;)Ljava/lang/Throwable;
    //   1277: athrow
    //   1278: aload_3
    //   1279: getstatic burp/Zgkl.ZR : Ljava/lang/String;
    //   1282: getstatic burp/Zty5.Zf : Ljava/lang/Object;
    //   1285: checkcast java/math/BigInteger
    //   1288: invokevirtual intValue : ()I
    //   1291: bipush #32
    //   1293: irem
    //   1294: invokestatic abs : (I)I
    //   1297: invokevirtual charAt : (I)C
    //   1300: invokevirtual append : (C)Ljava/lang/StringBuilder;
    //   1303: pop
    //   1304: iload_2
    //   1305: ifeq -> 1348
    //   1308: goto -> 1315
    //   1311: invokestatic a : (Ljava/lang/Throwable;)Ljava/lang/Throwable;
    //   1314: athrow
    //   1315: aload_3
    //   1316: getstatic burp/Zljx.ZD : Ljava/lang/String;
    //   1319: getstatic burp/Zezz.Zu : Ljava/lang/Object;
    //   1322: checkcast java/math/BigInteger
    //   1325: invokevirtual intValue : ()I
    //   1328: bipush #32
    //   1330: irem
    //   1331: invokestatic abs : (I)I
    //   1334: invokevirtual charAt : (I)C
    //   1337: invokevirtual append : (C)Ljava/lang/StringBuilder;
    //   1340: pop
    //   1341: goto -> 1348
    //   1344: invokestatic a : (Ljava/lang/Throwable;)Ljava/lang/Throwable;
    //   1347: athrow
    //   1348: iinc #4, 1
    //   1351: iload_2
    //   1352: ifeq -> 15
    //   1355: aload_3
    //   1356: invokevirtual toString : ()Ljava/lang/String;
    //   1359: putstatic burp/Zzvr.Zc : Ljava/lang/String;
    //   1362: getstatic burp/Zljx.ZZ : Ljava/lang/Object;
    //   1365: checkcast java/math/BigInteger
    //   1368: getstatic burp/Zgkl.ZK : Ljava/lang/Object;
    //   1371: checkcast java/math/BigInteger
    //   1374: invokevirtual subtract : (Ljava/math/BigInteger;)Ljava/math/BigInteger;
    //   1377: putstatic burp/Zk7w.ZF : Ljava/lang/Object;
    //   1380: new java/lang/StringBuilder
    //   1383: dup
    //   1384: invokespecial <init> : ()V
    //   1387: astore #4
    //   1389: iconst_0
    //   1390: istore #5
    //   1392: iload #5
    //   1394: bipush #32
    //   1396: if_icmpge -> 2763
    //   1399: iload #5
    //   1401: tableswitch default -> 2756, 0 -> 1544, 1 -> 1582, 2 -> 1620, 3 -> 1658, 4 -> 1696, 5 -> 1734, 6 -> 1772, 7 -> 1810, 8 -> 1848, 9 -> 1886, 10 -> 1924, 11 -> 1962, 12 -> 2000, 13 -> 2038, 14 -> 2076, 15 -> 2114, 16 -> 2152, 17 -> 2190, 18 -> 2228, 19 -> 2266, 20 -> 2304, 21 -> 2342, 22 -> 2380, 23 -> 2418, 24 -> 2456, 25 -> 2494, 26 -> 2532, 27 -> 2570, 28 -> 2608, 29 -> 2646, 30 -> 2684, 31 -> 2722
    //   1544: aload #4
    //   1546: getstatic burp/Zkvq.Zg : Ljava/lang/String;
    //   1549: getstatic burp/Ztd6.ZI : Ljava/lang/Object;
    //   1552: checkcast java/math/BigInteger
    //   1555: invokevirtual intValue : ()I
    //   1558: bipush #32
    //   1560: irem
    //   1561: invokestatic abs : (I)I
    //   1564: invokevirtual charAt : (I)C
    //   1567: invokevirtual append : (C)Ljava/lang/StringBuilder;
    //   1570: pop
    //   1571: iload_2
    //   1572: ifeq -> 2756
    //   1575: goto -> 1582
    //   1578: invokestatic a : (Ljava/lang/Throwable;)Ljava/lang/Throwable;
    //   1581: athrow
    //   1582: aload #4
    //   1584: getstatic burp/Zb9k.Za : Ljava/lang/String;
    //   1587: getstatic burp/Zezz.Zu : Ljava/lang/Object;
    //   1590: checkcast java/math/BigInteger
    //   1593: invokevirtual intValue : ()I
    //   1596: bipush #32
    //   1598: irem
    //   1599: invokestatic abs : (I)I
    //   1602: invokevirtual charAt : (I)C
    //   1605: invokevirtual append : (C)Ljava/lang/StringBuilder;
    //   1608: pop
    //   1609: iload_2
    //   1610: ifeq -> 2756
    //   1613: goto -> 1620
    //   1616: invokestatic a : (Ljava/lang/Throwable;)Ljava/lang/Throwable;
    //   1619: athrow
    //   1620: aload #4
    //   1622: getstatic burp/Zxsb.Zh : Ljava/lang/String;
    //   1625: getstatic burp/Zebj.Zf : Ljava/lang/Object;
    //   1628: checkcast java/math/BigInteger
    //   1631: invokevirtual intValue : ()I
    //   1634: bipush #32
    //   1636: irem
    //   1637: invokestatic abs : (I)I
    //   1640: invokevirtual charAt : (I)C
    //   1643: invokevirtual append : (C)Ljava/lang/StringBuilder;
    //   1646: pop
    //   1647: iload_2
    //   1648: ifeq -> 2756
    //   1651: goto -> 1658
    //   1654: invokestatic a : (Ljava/lang/Throwable;)Ljava/lang/Throwable;
    //   1657: athrow
    //   1658: aload #4
    //   1660: getstatic burp/Zsej.Zd : Ljava/lang/String;
    //   1663: getstatic burp/Zxn7.ZU : Ljava/lang/Object;
    //   1666: checkcast java/math/BigInteger
    //   1669: invokevirtual intValue : ()I
    //   1672: bipush #32
    //   1674: irem
    //   1675: invokestatic abs : (I)I
    //   1678: invokevirtual charAt : (I)C
    //   1681: invokevirtual append : (C)Ljava/lang/StringBuilder;
    //   1684: pop
    //   1685: iload_2
    //   1686: ifeq -> 2756
    //   1689: goto -> 1696
    //   1692: invokestatic a : (Ljava/lang/Throwable;)Ljava/lang/Throwable;
    //   1695: athrow
    //   1696: aload #4
    //   1698: getstatic burp/Zsej.Zd : Ljava/lang/String;
    //   1701: getstatic burp/Zz67.ZE : Ljava/lang/Object;
    //   1704: checkcast java/math/BigInteger
    //   1707: invokevirtual intValue : ()I
    //   1710: bipush #32
    //   1712: irem
    //   1713: invokestatic abs : (I)I
    //   1716: invokevirtual charAt : (I)C
    //   1719: invokevirtual append : (C)Ljava/lang/StringBuilder;
    //   1722: pop
    //   1723: iload_2
    //   1724: ifeq -> 2756
    //   1727: goto -> 1734
    //   1730: invokestatic a : (Ljava/lang/Throwable;)Ljava/lang/Throwable;
    //   1733: athrow
    //   1734: aload #4
    //   1736: getstatic burp/Zmhx.ZD : Ljava/lang/String;
    //   1739: getstatic burp/Zlc5.ZH : Ljava/lang/Object;
    //   1742: checkcast java/math/BigInteger
    //   1745: invokevirtual intValue : ()I
    //   1748: bipush #32
    //   1750: irem
    //   1751: invokestatic abs : (I)I
    //   1754: invokevirtual charAt : (I)C
    //   1757: invokevirtual append : (C)Ljava/lang/StringBuilder;
    //   1760: pop
    //   1761: iload_2
    //   1762: ifeq -> 2756
    //   1765: goto -> 1772
    //   1768: invokestatic a : (Ljava/lang/Throwable;)Ljava/lang/Throwable;
    //   1771: athrow
    //   1772: aload #4
    //   1774: getstatic burp/Ztpa.ZZ : Ljava/lang/String;
    //   1777: getstatic burp/Zxyq.ZQ : Ljava/lang/Object;
    //   1780: checkcast java/math/BigInteger
    //   1783: invokevirtual intValue : ()I
    //   1786: bipush #32
    //   1788: irem
    //   1789: invokestatic abs : (I)I
    //   1792: invokevirtual charAt : (I)C
    //   1795: invokevirtual append : (C)Ljava/lang/StringBuilder;
    //   1798: pop
    //   1799: iload_2
    //   1800: ifeq -> 2756
    //   1803: goto -> 1810
    //   1806: invokestatic a : (Ljava/lang/Throwable;)Ljava/lang/Throwable;
    //   1809: athrow
    //   1810: aload #4
    //   1812: getstatic burp/Zl_9.ZP : Ljava/lang/String;
    //   1815: getstatic burp/Zs59.Zw : Ljava/lang/Object;
    //   1818: checkcast java/math/BigInteger
    //   1821: invokevirtual intValue : ()I
    //   1824: bipush #32
    //   1826: irem
    //   1827: invokestatic abs : (I)I
    //   1830: invokevirtual charAt : (I)C
    //   1833: invokevirtual append : (C)Ljava/lang/StringBuilder;
    //   1836: pop
    //   1837: iload_2
    //   1838: ifeq -> 2756
    //   1841: goto -> 1848
    //   1844: invokestatic a : (Ljava/lang/Throwable;)Ljava/lang/Throwable;
    //   1847: athrow
    //   1848: aload #4
    //   1850: getstatic burp/Zko9.Zf : Ljava/lang/String;
    //   1853: getstatic burp/Ztd6.ZI : Ljava/lang/Object;
    //   1856: checkcast java/math/BigInteger
    //   1859: invokevirtual intValue : ()I
    //   1862: bipush #32
    //   1864: irem
    //   1865: invokestatic abs : (I)I
    //   1868: invokevirtual charAt : (I)C
    //   1871: invokevirtual append : (C)Ljava/lang/StringBuilder;
    //   1874: pop
    //   1875: iload_2
    //   1876: ifeq -> 2756
    //   1879: goto -> 1886
    //   1882: invokestatic a : (Ljava/lang/Throwable;)Ljava/lang/Throwable;
    //   1885: athrow
    //   1886: aload #4
    //   1888: getstatic burp/Zgdj.Zt : Ljava/lang/String;
    //   1891: getstatic burp/Zeyt.ZR : Ljava/lang/Object;
    //   1894: checkcast java/math/BigInteger
    //   1897: invokevirtual intValue : ()I
    //   1900: bipush #32
    //   1902: irem
    //   1903: invokestatic abs : (I)I
    //   1906: invokevirtual charAt : (I)C
    //   1909: invokevirtual append : (C)Ljava/lang/StringBuilder;
    //   1912: pop
    //   1913: iload_2
    //   1914: ifeq -> 2756
    //   1917: goto -> 1924
    //   1920: invokestatic a : (Ljava/lang/Throwable;)Ljava/lang/Throwable;
    //   1923: athrow
    //   1924: aload #4
    //   1926: getstatic burp/Zm06.Zg : Ljava/lang/String;
    //   1929: getstatic burp/Zs_.Zs : Ljava/lang/Object;
    //   1932: checkcast java/math/BigInteger
    //   1935: invokevirtual intValue : ()I
    //   1938: bipush #32
    //   1940: irem
    //   1941: invokestatic abs : (I)I
    //   1944: invokevirtual charAt : (I)C
    //   1947: invokevirtual append : (C)Ljava/lang/StringBuilder;
    //   1950: pop
    //   1951: iload_2
    //   1952: ifeq -> 2756
    //   1955: goto -> 1962
    //   1958: invokestatic a : (Ljava/lang/Throwable;)Ljava/lang/Throwable;
    //   1961: athrow
    //   1962: aload #4
    //   1964: getstatic burp/Zeyt.ZS : Ljava/lang/String;
    //   1967: getstatic burp/Zs36.Zs : Ljava/lang/Object;
    //   1970: checkcast java/math/BigInteger
    //   1973: invokevirtual intValue : ()I
    //   1976: bipush #32
    //   1978: irem
    //   1979: invokestatic abs : (I)I
    //   1982: invokevirtual charAt : (I)C
    //   1985: invokevirtual append : (C)Ljava/lang/StringBuilder;
    //   1988: pop
    //   1989: iload_2
    //   1990: ifeq -> 2756
    //   1993: goto -> 2000
    //   1996: invokestatic a : (Ljava/lang/Throwable;)Ljava/lang/Throwable;
    //   1999: athrow
    //   2000: aload #4
    //   2002: getstatic burp/Zsgj.ZN : Ljava/lang/String;
    //   2005: getstatic burp/Zsej.ZT : Ljava/lang/Object;
    //   2008: checkcast java/math/BigInteger
    //   2011: invokevirtual intValue : ()I
    //   2014: bipush #32
    //   2016: irem
    //   2017: invokestatic abs : (I)I
    //   2020: invokevirtual charAt : (I)C
    //   2023: invokevirtual append : (C)Ljava/lang/StringBuilder;
    //   2026: pop
    //   2027: iload_2
    //   2028: ifeq -> 2756
    //   2031: goto -> 2038
    //   2034: invokestatic a : (Ljava/lang/Throwable;)Ljava/lang/Throwable;
    //   2037: athrow
    //   2038: aload #4
    //   2040: getstatic burp/Zzvr.Zc : Ljava/lang/String;
    //   2043: getstatic burp/Zs9u.Zd : Ljava/lang/Object;
    //   2046: checkcast java/math/BigInteger
    //   2049: invokevirtual intValue : ()I
    //   2052: bipush #32
    //   2054: irem
    //   2055: invokestatic abs : (I)I
    //   2058: invokevirtual charAt : (I)C
    //   2061: invokevirtual append : (C)Ljava/lang/StringBuilder;
    //   2064: pop
    //   2065: iload_2
    //   2066: ifeq -> 2756
    //   2069: goto -> 2076
    //   2072: invokestatic a : (Ljava/lang/Throwable;)Ljava/lang/Throwable;
    //   2075: athrow
    //   2076: aload #4
    //   2078: getstatic burp/Zrvb.ZU : Ljava/lang/String;
    //   2081: getstatic burp/Zrvb.ZD : Ljava/lang/Object;
    //   2084: checkcast java/math/BigInteger
    //   2087: invokevirtual intValue : ()I
    //   2090: bipush #32
    //   2092: irem
    //   2093: invokestatic abs : (I)I
    //   2096: invokevirtual charAt : (I)C
    //   2099: invokevirtual append : (C)Ljava/lang/StringBuilder;
    //   2102: pop
    //   2103: iload_2
    //   2104: ifeq -> 2756
    //   2107: goto -> 2114
    //   2110: invokestatic a : (Ljava/lang/Throwable;)Ljava/lang/Throwable;
    //   2113: athrow
    //   2114: aload #4
    //   2116: getstatic burp/Zzv.Zy : Ljava/lang/String;
    //   2119: getstatic burp/Zzc7.ZG : Ljava/lang/Object;
    //   2122: checkcast java/math/BigInteger
    //   2125: invokevirtual intValue : ()I
    //   2128: bipush #32
    //   2130: irem
    //   2131: invokestatic abs : (I)I
    //   2134: invokevirtual charAt : (I)C
    //   2137: invokevirtual append : (C)Ljava/lang/StringBuilder;
    //   2140: pop
    //   2141: iload_2
    //   2142: ifeq -> 2756
    //   2145: goto -> 2152
    //   2148: invokestatic a : (Ljava/lang/Throwable;)Ljava/lang/Throwable;
    //   2151: athrow
    //   2152: aload #4
    //   2154: getstatic burp/Zz9p.ZC : Ljava/lang/String;
    //   2157: getstatic burp/Zxd0.Za : Ljava/lang/Object;
    //   2160: checkcast java/math/BigInteger
    //   2163: invokevirtual intValue : ()I
    //   2166: bipush #32
    //   2168: irem
    //   2169: invokestatic abs : (I)I
    //   2172: invokevirtual charAt : (I)C
    //   2175: invokevirtual append : (C)Ljava/lang/StringBuilder;
    //   2178: pop
    //   2179: iload_2
    //   2180: ifeq -> 2756
    //   2183: goto -> 2190
    //   2186: invokestatic a : (Ljava/lang/Throwable;)Ljava/lang/Throwable;
    //   2189: athrow
    //   2190: aload #4
    //   2192: getstatic burp/Zr3x.ZM : Ljava/lang/String;
    //   2195: getstatic burp/Zzv.Zu : Ljava/lang/Object;
    //   2198: checkcast java/math/BigInteger
    //   2201: invokevirtual intValue : ()I
    //   2204: bipush #32
    //   2206: irem
    //   2207: invokestatic abs : (I)I
    //   2210: invokevirtual charAt : (I)C
    //   2213: invokevirtual append : (C)Ljava/lang/StringBuilder;
    //   2216: pop
    //   2217: iload_2
    //   2218: ifeq -> 2756
    //   2221: goto -> 2228
    //   2224: invokestatic a : (Ljava/lang/Throwable;)Ljava/lang/Throwable;
    //   2227: athrow
    //   2228: aload #4
    //   2230: getstatic burp/Zkvq.Zg : Ljava/lang/String;
    //   2233: getstatic burp/Zr8g.ZF : Ljava/lang/Object;
    //   2236: checkcast java/math/BigInteger
    //   2239: invokevirtual intValue : ()I
    //   2242: bipush #32
    //   2244: irem
    //   2245: invokestatic abs : (I)I
    //   2248: invokevirtual charAt : (I)C
    //   2251: invokevirtual append : (C)Ljava/lang/StringBuilder;
    //   2254: pop
    //   2255: iload_2
    //   2256: ifeq -> 2756
    //   2259: goto -> 2266
    //   2262: invokestatic a : (Ljava/lang/Throwable;)Ljava/lang/Throwable;
    //   2265: athrow
    //   2266: aload #4
    //   2268: getstatic burp/Zgii.Ze : Ljava/lang/String;
    //   2271: getstatic burp/Zr8g.ZF : Ljava/lang/Object;
    //   2274: checkcast java/math/BigInteger
    //   2277: invokevirtual intValue : ()I
    //   2280: bipush #32
    //   2282: irem
    //   2283: invokestatic abs : (I)I
    //   2286: invokevirtual charAt : (I)C
    //   2289: invokevirtual append : (C)Ljava/lang/StringBuilder;
    //   2292: pop
    //   2293: iload_2
    //   2294: ifeq -> 2756
    //   2297: goto -> 2304
    //   2300: invokestatic a : (Ljava/lang/Throwable;)Ljava/lang/Throwable;
    //   2303: athrow
    //   2304: aload #4
    //   2306: getstatic burp/Zr3x.ZM : Ljava/lang/String;
    //   2309: getstatic burp/Zz0j.Zn : Ljava/lang/Object;
    //   2312: checkcast java/math/BigInteger
    //   2315: invokevirtual intValue : ()I
    //   2318: bipush #32
    //   2320: irem
    //   2321: invokestatic abs : (I)I
    //   2324: invokevirtual charAt : (I)C
    //   2327: invokevirtual append : (C)Ljava/lang/StringBuilder;
    //   2330: pop
    //   2331: iload_2
    //   2332: ifeq -> 2756
    //   2335: goto -> 2342
    //   2338: invokestatic a : (Ljava/lang/Throwable;)Ljava/lang/Throwable;
    //   2341: athrow
    //   2342: aload #4
    //   2344: getstatic burp/Zmhx.ZD : Ljava/lang/String;
    //   2347: getstatic burp/Zoa.ZI : Ljava/lang/Object;
    //   2350: checkcast java/math/BigInteger
    //   2353: invokevirtual intValue : ()I
    //   2356: bipush #32
    //   2358: irem
    //   2359: invokestatic abs : (I)I
    //   2362: invokevirtual charAt : (I)C
    //   2365: invokevirtual append : (C)Ljava/lang/StringBuilder;
    //   2368: pop
    //   2369: iload_2
    //   2370: ifeq -> 2756
    //   2373: goto -> 2380
    //   2376: invokestatic a : (Ljava/lang/Throwable;)Ljava/lang/Throwable;
    //   2379: athrow
    //   2380: aload #4
    //   2382: getstatic burp/Zs9u.ZM : Ljava/lang/String;
    //   2385: getstatic burp/Zghe.ZJ : Ljava/lang/Object;
    //   2388: checkcast java/math/BigInteger
    //   2391: invokevirtual intValue : ()I
    //   2394: bipush #32
    //   2396: irem
    //   2397: invokestatic abs : (I)I
    //   2400: invokevirtual charAt : (I)C
    //   2403: invokevirtual append : (C)Ljava/lang/StringBuilder;
    //   2406: pop
    //   2407: iload_2
    //   2408: ifeq -> 2756
    //   2411: goto -> 2418
    //   2414: invokestatic a : (Ljava/lang/Throwable;)Ljava/lang/Throwable;
    //   2417: athrow
    //   2418: aload #4
    //   2420: getstatic burp/Ztd6.Zu : Ljava/lang/String;
    //   2423: getstatic burp/Ztpa.Zv : Ljava/lang/Object;
    //   2426: checkcast java/math/BigInteger
    //   2429: invokevirtual intValue : ()I
    //   2432: bipush #32
    //   2434: irem
    //   2435: invokestatic abs : (I)I
    //   2438: invokevirtual charAt : (I)C
    //   2441: invokevirtual append : (C)Ljava/lang/StringBuilder;
    //   2444: pop
    //   2445: iload_2
    //   2446: ifeq -> 2756
    //   2449: goto -> 2456
    //   2452: invokestatic a : (Ljava/lang/Throwable;)Ljava/lang/Throwable;
    //   2455: athrow
    //   2456: aload #4
    //   2458: getstatic burp/Zls_.Zn : Ljava/lang/String;
    //   2461: getstatic burp/Zz0j.Zn : Ljava/lang/Object;
    //   2464: checkcast java/math/BigInteger
    //   2467: invokevirtual intValue : ()I
    //   2470: bipush #32
    //   2472: irem
    //   2473: invokestatic abs : (I)I
    //   2476: invokevirtual charAt : (I)C
    //   2479: invokevirtual append : (C)Ljava/lang/StringBuilder;
    //   2482: pop
    //   2483: iload_2
    //   2484: ifeq -> 2756
    //   2487: goto -> 2494
    //   2490: invokestatic a : (Ljava/lang/Throwable;)Ljava/lang/Throwable;
    //   2493: athrow
    //   2494: aload #4
    //   2496: getstatic burp/Zeyt.ZS : Ljava/lang/String;
    //   2499: getstatic burp/Zlno.ZU : Ljava/lang/Object;
    //   2502: checkcast java/math/BigInteger
    //   2505: invokevirtual intValue : ()I
    //   2508: bipush #32
    //   2510: irem
    //   2511: invokestatic abs : (I)I
    //   2514: invokevirtual charAt : (I)C
    //   2517: invokevirtual append : (C)Ljava/lang/StringBuilder;
    //   2520: pop
    //   2521: iload_2
    //   2522: ifeq -> 2756
    //   2525: goto -> 2532
    //   2528: invokestatic a : (Ljava/lang/Throwable;)Ljava/lang/Throwable;
    //   2531: athrow
    //   2532: aload #4
    //   2534: getstatic burp/Zm06.Zg : Ljava/lang/String;
    //   2537: getstatic burp/Zxd0.Za : Ljava/lang/Object;
    //   2540: checkcast java/math/BigInteger
    //   2543: invokevirtual intValue : ()I
    //   2546: bipush #32
    //   2548: irem
    //   2549: invokestatic abs : (I)I
    //   2552: invokevirtual charAt : (I)C
    //   2555: invokevirtual append : (C)Ljava/lang/StringBuilder;
    //   2558: pop
    //   2559: iload_2
    //   2560: ifeq -> 2756
    //   2563: goto -> 2570
    //   2566: invokestatic a : (Ljava/lang/Throwable;)Ljava/lang/Throwable;
    //   2569: athrow
    //   2570: aload #4
    //   2572: getstatic burp/Ztpa.ZZ : Ljava/lang/String;
    //   2575: getstatic burp/Zead.ZI : Ljava/lang/Object;
    //   2578: checkcast java/math/BigInteger
    //   2581: invokevirtual intValue : ()I
    //   2584: bipush #32
    //   2586: irem
    //   2587: invokestatic abs : (I)I
    //   2590: invokevirtual charAt : (I)C
    //   2593: invokevirtual append : (C)Ljava/lang/StringBuilder;
    //   2596: pop
    //   2597: iload_2
    //   2598: ifeq -> 2756
    //   2601: goto -> 2608
    //   2604: invokestatic a : (Ljava/lang/Throwable;)Ljava/lang/Throwable;
    //   2607: athrow
    //   2608: aload #4
    //   2610: getstatic burp/Zxrd.ZF : Ljava/lang/String;
    //   2613: getstatic burp/Zre1.ZN : Ljava/lang/Object;
    //   2616: checkcast java/math/BigInteger
    //   2619: invokevirtual intValue : ()I
    //   2622: bipush #32
    //   2624: irem
    //   2625: invokestatic abs : (I)I
    //   2628: invokevirtual charAt : (I)C
    //   2631: invokevirtual append : (C)Ljava/lang/StringBuilder;
    //   2634: pop
    //   2635: iload_2
    //   2636: ifeq -> 2756
    //   2639: goto -> 2646
    //   2642: invokestatic a : (Ljava/lang/Throwable;)Ljava/lang/Throwable;
    //   2645: athrow
    //   2646: aload #4
    //   2648: getstatic burp/Zmt6.Zx : Ljava/lang/String;
    //   2651: getstatic burp/Zeyt.ZR : Ljava/lang/Object;
    //   2654: checkcast java/math/BigInteger
    //   2657: invokevirtual intValue : ()I
    //   2660: bipush #32
    //   2662: irem
    //   2663: invokestatic abs : (I)I
    //   2666: invokevirtual charAt : (I)C
    //   2669: invokevirtual append : (C)Ljava/lang/StringBuilder;
    //   2672: pop
    //   2673: iload_2
    //   2674: ifeq -> 2756
    //   2677: goto -> 2684
    //   2680: invokestatic a : (Ljava/lang/Throwable;)Ljava/lang/Throwable;
    //   2683: athrow
    //   2684: aload #4
    //   2686: getstatic burp/Zeyt.ZS : Ljava/lang/String;
    //   2689: getstatic burp/Zlno.ZU : Ljava/lang/Object;
    //   2692: checkcast java/math/BigInteger
    //   2695: invokevirtual intValue : ()I
    //   2698: bipush #32
    //   2700: irem
    //   2701: invokestatic abs : (I)I
    //   2704: invokevirtual charAt : (I)C
    //   2707: invokevirtual append : (C)Ljava/lang/StringBuilder;
    //   2710: pop
    //   2711: iload_2
    //   2712: ifeq -> 2756
    //   2715: goto -> 2722
    //   2718: invokestatic a : (Ljava/lang/Throwable;)Ljava/lang/Throwable;
    //   2721: athrow
    //   2722: aload #4
    //   2724: getstatic burp/Zty3.ZW : Ljava/lang/String;
    //   2727: getstatic burp/Zs36.Zs : Ljava/lang/Object;
    //   2730: checkcast java/math/BigInteger
    //   2733: invokevirtual intValue : ()I
    //   2736: bipush #32
    //   2738: irem
    //   2739: invokestatic abs : (I)I
    //   2742: invokevirtual charAt : (I)C
    //   2745: invokevirtual append : (C)Ljava/lang/StringBuilder;
    //   2748: pop
    //   2749: goto -> 2756
    //   2752: invokestatic a : (Ljava/lang/Throwable;)Ljava/lang/Throwable;
    //   2755: athrow
    //   2756: iinc #5, 1
    //   2759: iload_2
    //   2760: ifeq -> 1392
    //   2763: aload #4
    //   2765: invokevirtual toString : ()Ljava/lang/String;
    //   2768: putstatic burp/Zxrd.ZF : Ljava/lang/String;
    //   2771: sipush #22142
    //   2774: sipush #14109
    //   2777: invokestatic a : (II)Ljava/lang/String;
    //   2780: iconst_1
    //   2781: ldc burp/Zera
    //   2783: invokevirtual getClassLoader : ()Ljava/lang/ClassLoader;
    //   2786: invokestatic forName : (Ljava/lang/String;ZLjava/lang/ClassLoader;)Ljava/lang/Class;
    //   2789: invokevirtual getDeclaredFields : ()[Ljava/lang/reflect/Field;
    //   2792: astore #5
    //   2794: aload #5
    //   2796: arraylength
    //   2797: istore #6
    //   2799: iconst_0
    //   2800: istore #7
    //   2802: iload #7
    //   2804: iload #6
    //   2806: if_icmpge -> 2944
    //   2809: aload #5
    //   2811: iload #7
    //   2813: aaload
    //   2814: astore #8
    //   2816: aload #8
    //   2818: invokevirtual getModifiers : ()I
    //   2821: invokestatic isStatic : (I)Z
    //   2824: ifne -> 2834
    //   2827: goto -> 2937
    //   2830: invokestatic a : (Ljava/lang/Throwable;)Ljava/lang/Throwable;
    //   2833: athrow
    //   2834: aload #8
    //   2836: invokevirtual getType : ()Ljava/lang/Class;
    //   2839: astore #9
    //   2841: aload #9
    //   2843: ifnull -> 2924
    //   2846: aload #9
    //   2848: invokevirtual isPrimitive : ()Z
    //   2851: ifne -> 2924
    //   2854: goto -> 2861
    //   2857: invokestatic a : (Ljava/lang/Throwable;)Ljava/lang/Throwable;
    //   2860: athrow
    //   2861: aload #9
    //   2863: invokevirtual getPackage : ()Ljava/lang/Package;
    //   2866: ifnull -> 2924
    //   2869: goto -> 2876
    //   2872: invokestatic a : (Ljava/lang/Throwable;)Ljava/lang/Throwable;
    //   2875: athrow
    //   2876: aload #9
    //   2878: invokevirtual getPackage : ()Ljava/lang/Package;
    //   2881: invokevirtual getName : ()Ljava/lang/String;
    //   2884: ifnull -> 2924
    //   2887: goto -> 2894
    //   2890: invokestatic a : (Ljava/lang/Throwable;)Ljava/lang/Throwable;
    //   2893: athrow
    //   2894: aload #9
    //   2896: invokevirtual getPackage : ()Ljava/lang/Package;
    //   2899: invokevirtual getName : ()Ljava/lang/String;
    //   2902: sipush #22139
    //   2905: sipush #21781
    //   2908: invokestatic a : (II)Ljava/lang/String;
    //   2911: invokevirtual startsWith : (Ljava/lang/String;)Z
    //   2914: ifne -> 2924
    //   2917: goto -> 2924
    //   2920: invokestatic a : (Ljava/lang/Throwable;)Ljava/lang/Throwable;
    //   2923: athrow
    //   2924: aload #8
    //   2926: iconst_1
    //   2927: invokevirtual setAccessible : (Z)V
    //   2930: aload #8
    //   2932: aconst_null
    //   2933: invokevirtual get : (Ljava/lang/Object;)Ljava/lang/Object;
    //   2936: pop
    //   2937: iinc #7, 1
    //   2940: iload_2
    //   2941: ifeq -> 2802
    //   2944: sipush #22137
    //   2947: sipush #32634
    //   2950: invokestatic a : (II)Ljava/lang/String;
    //   2953: invokestatic forName : (Ljava/lang/String;)Ljava/lang/Class;
    //   2956: invokevirtual getDeclaredMethods : ()[Ljava/lang/reflect/Method;
    //   2959: astore #5
    //   2961: aload #5
    //   2963: arraylength
    //   2964: istore #6
    //   2966: iconst_0
    //   2967: istore #7
    //   2969: iload #7
    //   2971: iload #6
    //   2973: if_icmpge -> 3106
    //   2976: aload #5
    //   2978: iload #7
    //   2980: aaload
    //   2981: astore #8
    //   2983: aload #8
    //   2985: invokevirtual getParameterTypes : ()[Ljava/lang/Class;
    //   2988: pop
    //   2989: aload #8
    //   2991: invokevirtual getModifiers : ()I
    //   2994: invokestatic isStatic : (I)Z
    //   2997: ifeq -> 3092
    //   3000: aload #8
    //   3002: invokevirtual getParameterTypes : ()[Ljava/lang/Class;
    //   3005: arraylength
    //   3006: iconst_2
    //   3007: if_icmpne -> 3092
    //   3010: goto -> 3017
    //   3013: invokestatic a : (Ljava/lang/Throwable;)Ljava/lang/Throwable;
    //   3016: athrow
    //   3017: aload #8
    //   3019: invokevirtual getReturnType : ()Ljava/lang/Class;
    //   3022: getstatic java/lang/Void.TYPE : Ljava/lang/Class;
    //   3025: invokevirtual equals : (Ljava/lang/Object;)Z
    //   3028: ifeq -> 3092
    //   3031: goto -> 3038
    //   3034: invokestatic a : (Ljava/lang/Throwable;)Ljava/lang/Throwable;
    //   3037: athrow
    //   3038: aload #8
    //   3040: iconst_1
    //   3041: invokevirtual setAccessible : (Z)V
    //   3044: aload #8
    //   3046: aconst_null
    //   3047: iconst_2
    //   3048: anewarray java/lang/Object
    //   3051: dup
    //   3052: iconst_0
    //   3053: aload_0
    //   3054: aastore
    //   3055: dup
    //   3056: iconst_1
    //   3057: aload_1
    //   3058: ifnonnull -> 3076
    //   3061: goto -> 3068
    //   3064: invokestatic a : (Ljava/lang/Throwable;)Ljava/lang/Throwable;
    //   3067: athrow
    //   3068: aload_1
    //   3069: goto -> 3083
    //   3072: invokestatic a : (Ljava/lang/Throwable;)Ljava/lang/Throwable;
    //   3075: athrow
    //   3076: aload_1
    //   3077: checkcast [B
    //   3080: invokevirtual clone : ()Ljava/lang/Object;
    //   3083: aastore
    //   3084: invokevirtual invoke : (Ljava/lang/Object;[Ljava/lang/Object;)Ljava/lang/Object;
    //   3087: pop
    //   3088: iload_2
    //   3089: ifeq -> 3106
    //   3092: iinc #7, 1
    //   3095: iload_2
    //   3096: ifeq -> 2969
    //   3099: goto -> 3106
    //   3102: invokestatic a : (Ljava/lang/Throwable;)Ljava/lang/Throwable;
    //   3105: athrow
    //   3106: new java/io/ByteArrayOutputStream
    //   3109: dup
    //   3110: invokespecial <init> : ()V
    //   3113: astore #5
    //   3115: sipush #22141
    //   3118: aload #5
    //   3120: sipush #202
    //   3123: invokevirtual write : (I)V
    //   3126: sipush #29661
    //   3129: aload #5
    //   3131: sipush #254
    //   3134: invokevirtual write : (I)V
    //   3137: aload #5
    //   3139: sipush #186
    //   3142: invokevirtual write : (I)V
    //   3145: aload #5
    //   3147: sipush #190
    //   3150: invokevirtual write : (I)V
    //   3153: aload #5
    //   3155: iconst_0
    //   3156: invokevirtual write : (I)V
    //   3159: aload #5
    //   3161: iconst_1
    //   3162: invokevirtual write : (I)V
    //   3165: aload #5
    //   3167: iconst_0
    //   3168: invokevirtual write : (I)V
    //   3171: aload #5
    //   3173: bipush #50
    //   3175: invokevirtual write : (I)V
    //   3178: aload #5
    //   3180: getstatic burp/Zxof.Zi : Ljava/lang/Object;
    //   3183: checkcast java/math/BigInteger
    //   3186: invokevirtual toByteArray : ()[B
    //   3189: invokevirtual write : ([B)V
    //   3192: aload #5
    //   3194: getstatic burp/Zl8s.ZY : Ljava/lang/Object;
    //   3197: checkcast java/math/BigInteger
    //   3200: invokevirtual toByteArray : ()[B
    //   3203: invokevirtual write : ([B)V
    //   3206: aload #5
    //   3208: getstatic burp/Zgp_.Zm : Ljava/lang/Object;
    //   3211: checkcast java/math/BigInteger
    //   3214: invokevirtual toByteArray : ()[B
    //   3217: invokevirtual write : ([B)V
    //   3220: aload #5
    //   3222: invokevirtual toByteArray : ()[B
    //   3225: astore #6
    //   3227: aconst_null
    //   3228: astore #7
    //   3230: invokestatic a : (II)Ljava/lang/String;
    //   3233: invokestatic forName : (Ljava/lang/String;)Ljava/lang/Class;
    //   3236: invokevirtual getDeclaredMethods : ()[Ljava/lang/reflect/Method;
    //   3239: astore #8
    //   3241: aload #8
    //   3243: arraylength
    //   3244: istore #9
    //   3246: iconst_0
    //   3247: istore #10
    //   3249: iload #10
    //   3251: iload #9
    //   3253: if_icmpge -> 3381
    //   3256: aload #8
    //   3258: iload #10
    //   3260: aaload
    //   3261: astore #11
    //   3263: aload #11
    //   3265: invokevirtual getName : ()Ljava/lang/String;
    //   3268: sipush #22138
    //   3271: sipush #16751
    //   3274: invokestatic a : (II)Ljava/lang/String;
    //   3277: invokevirtual equals : (Ljava/lang/Object;)Z
    //   3280: ifeq -> 3374
    //   3283: aload #11
    //   3285: invokevirtual getParameterTypes : ()[Ljava/lang/Class;
    //   3288: astore #12
    //   3290: aload #12
    //   3292: arraylength
    //   3293: iconst_4
    //   3294: if_icmpeq -> 3304
    //   3297: goto -> 3374
    //   3300: invokestatic a : (Ljava/lang/Throwable;)Ljava/lang/Throwable;
    //   3303: athrow
    //   3304: aload #12
    //   3306: iconst_0
    //   3307: aaload
    //   3308: ldc java/lang/String
    //   3310: if_acmpeq -> 3320
    //   3313: goto -> 3374
    //   3316: invokestatic a : (Ljava/lang/Throwable;)Ljava/lang/Throwable;
    //   3319: athrow
    //   3320: aload #12
    //   3322: iconst_1
    //   3323: aaload
    //   3324: ldc [B
    //   3326: if_acmpeq -> 3336
    //   3329: goto -> 3374
    //   3332: invokestatic a : (Ljava/lang/Throwable;)Ljava/lang/Throwable;
    //   3335: athrow
    //   3336: aload #12
    //   3338: iconst_2
    //   3339: aaload
    //   3340: getstatic java/lang/Integer.TYPE : Ljava/lang/Class;
    //   3343: if_acmpeq -> 3353
    //   3346: goto -> 3374
    //   3349: invokestatic a : (Ljava/lang/Throwable;)Ljava/lang/Throwable;
    //   3352: athrow
    //   3353: aload #12
    //   3355: iconst_3
    //   3356: aaload
    //   3357: getstatic java/lang/Integer.TYPE : Ljava/lang/Class;
    //   3360: if_acmpeq -> 3370
    //   3363: goto -> 3374
    //   3366: invokestatic a : (Ljava/lang/Throwable;)Ljava/lang/Throwable;
    //   3369: athrow
    //   3370: aload #11
    //   3372: astore #7
    //   3374: iinc #10, 1
    //   3377: iload_2
    //   3378: ifeq -> 3249
    //   3381: aload #7
    //   3383: iconst_1
    //   3384: invokevirtual setAccessible : (Z)V
    //   3387: ldc burp/Zgta
    //   3389: iconst_0
    //   3390: anewarray java/lang/Class
    //   3393: invokevirtual getDeclaredConstructor : ([Ljava/lang/Class;)Ljava/lang/reflect/Constructor;
    //   3396: astore #8
    //   3398: aload #8
    //   3400: iconst_1
    //   3401: invokevirtual setAccessible : (Z)V
    //   3404: aload #7
    //   3406: aload #8
    //   3408: iconst_0
    //   3409: anewarray java/lang/Object
    //   3412: invokevirtual newInstance : ([Ljava/lang/Object;)Ljava/lang/Object;
    //   3415: iconst_4
    //   3416: anewarray java/lang/Object
    //   3419: dup
    //   3420: iconst_0
    //   3421: sipush #22143
    //   3424: sipush #7688
    //   3427: invokestatic a : (II)Ljava/lang/String;
    //   3430: aastore
    //   3431: dup
    //   3432: iconst_1
    //   3433: aload #6
    //   3435: aastore
    //   3436: dup
    //   3437: iconst_2
    //   3438: iconst_0
    //   3439: invokestatic valueOf : (I)Ljava/lang/Integer;
    //   3442: aastore
    //   3443: dup
    //   3444: iconst_3
    //   3445: aload #6
    //   3447: arraylength
    //   3448: invokestatic valueOf : (I)Ljava/lang/Integer;
    //   3451: aastore
    //   3452: invokevirtual invoke : (Ljava/lang/Object;[Ljava/lang/Object;)Ljava/lang/Object;
    //   3455: pop
    //   3456: goto -> 3461
    //   3459: astore #5
    //   3461: getstatic burp/Zkv2.Z_ : Ljava/lang/String;
    //   3464: getstatic burp/Zeyt.ZR : Ljava/lang/Object;
    //   3467: checkcast java/math/BigInteger
    //   3470: invokevirtual intValue : ()I
    //   3473: bipush #32
    //   3475: irem
    //   3476: invokestatic abs : (I)I
    //   3479: invokevirtual charAt : (I)C
    //   3482: getstatic burp/Zgii.Ze : Ljava/lang/String;
    //   3485: getstatic burp/Zty3.Zz : Ljava/lang/Object;
    //   3488: checkcast java/math/BigInteger
    //   3491: invokevirtual intValue : ()I
    //   3494: bipush #32
    //   3496: irem
    //   3497: invokestatic abs : (I)I
    //   3500: invokevirtual charAt : (I)C
    //   3503: if_icmple -> 3610
    //   3506: getstatic burp/Zxyq.Zr : Ljava/lang/String;
    //   3509: getstatic burp/Zkvq.Zz : Ljava/lang/Object;
    //   3512: checkcast java/math/BigInteger
    //   3515: invokevirtual intValue : ()I
    //   3518: bipush #32
    //   3520: irem
    //   3521: invokestatic abs : (I)I
    //   3524: invokevirtual charAt : (I)C
    //   3527: getstatic burp/Zgwq.ZV : Ljava/lang/String;
    //   3530: getstatic burp/Ztte.ZR : Ljava/lang/Object;
    //   3533: checkcast java/math/BigInteger
    //   3536: invokevirtual intValue : ()I
    //   3539: bipush #32
    //   3541: irem
    //   3542: invokestatic abs : (I)I
    //   3545: invokevirtual charAt : (I)C
    //   3548: if_icmpgt -> 3610
    //   3551: goto -> 3558
    //   3554: invokestatic a : (Ljava/lang/Throwable;)Ljava/lang/Throwable;
    //   3557: athrow
    //   3558: getstatic burp/Zl_1.ZH : Ljava/lang/String;
    //   3561: getstatic burp/Zzc7.ZG : Ljava/lang/Object;
    //   3564: checkcast java/math/BigInteger
    //   3567: invokevirtual intValue : ()I
    //   3570: bipush #32
    //   3572: irem
    //   3573: invokestatic abs : (I)I
    //   3576: invokevirtual charAt : (I)C
    //   3579: getstatic burp/Zttj.ZN : Ljava/lang/String;
    //   3582: getstatic burp/Zbxp.ZW : Ljava/lang/Object;
    //   3585: checkcast java/math/BigInteger
    //   3588: invokevirtual intValue : ()I
    //   3591: bipush #32
    //   3593: irem
    //   3594: invokestatic abs : (I)I
    //   3597: invokevirtual charAt : (I)C
    //   3600: if_icmpgt -> 3618
    //   3603: goto -> 3610
    //   3606: invokestatic a : (Ljava/lang/Throwable;)Ljava/lang/Throwable;
    //   3609: athrow
    //   3610: iconst_1
    //   3611: goto -> 3619
    //   3614: invokestatic a : (Ljava/lang/Throwable;)Ljava/lang/Throwable;
    //   3617: athrow
    //   3618: iconst_0
    //   3619: ireturn
    //   3620: astore_3
    //   3621: new java/lang/Exception
    //   3624: dup
    //   3625: aload_3
    //   3626: invokevirtual getMessage : ()Ljava/lang/String;
    //   3629: invokespecial <init> : (Ljava/lang/String;)V
    //   3632: athrow
    // Exception table:
    //   from	to	target	type
    //   4	3619	3620	java/lang/Throwable
    //   22	198	201	java/lang/Throwable
    //   168	235	238	java/lang/Throwable
    //   205	272	275	java/lang/Throwable
    //   242	309	312	java/lang/Throwable
    //   279	346	349	java/lang/Throwable
    //   316	383	386	java/lang/Throwable
    //   353	420	423	java/lang/Throwable
    //   390	457	460	java/lang/Throwable
    //   427	494	497	java/lang/Throwable
    //   464	531	534	java/lang/Throwable
    //   501	568	571	java/lang/Throwable
    //   538	605	608	java/lang/Throwable
    //   575	642	645	java/lang/Throwable
    //   612	679	682	java/lang/Throwable
    //   649	716	719	java/lang/Throwable
    //   686	753	756	java/lang/Throwable
    //   723	790	793	java/lang/Throwable
    //   760	827	830	java/lang/Throwable
    //   797	864	867	java/lang/Throwable
    //   834	901	904	java/lang/Throwable
    //   871	938	941	java/lang/Throwable
    //   908	975	978	java/lang/Throwable
    //   945	1012	1015	java/lang/Throwable
    //   982	1049	1052	java/lang/Throwable
    //   1019	1086	1089	java/lang/Throwable
    //   1056	1123	1126	java/lang/Throwable
    //   1093	1160	1163	java/lang/Throwable
    //   1130	1197	1200	java/lang/Throwable
    //   1167	1234	1237	java/lang/Throwable
    //   1204	1271	1274	java/lang/Throwable
    //   1241	1308	1311	java/lang/Throwable
    //   1278	1341	1344	java/lang/Throwable
    //   1399	1575	1578	java/lang/Throwable
    //   1544	1613	1616	java/lang/Throwable
    //   1582	1651	1654	java/lang/Throwable
    //   1620	1689	1692	java/lang/Throwable
    //   1658	1727	1730	java/lang/Throwable
    //   1696	1765	1768	java/lang/Throwable
    //   1734	1803	1806	java/lang/Throwable
    //   1772	1841	1844	java/lang/Throwable
    //   1810	1879	1882	java/lang/Throwable
    //   1848	1917	1920	java/lang/Throwable
    //   1886	1955	1958	java/lang/Throwable
    //   1924	1993	1996	java/lang/Throwable
    //   1962	2031	2034	java/lang/Throwable
    //   2000	2069	2072	java/lang/Throwable
    //   2038	2107	2110	java/lang/Throwable
    //   2076	2145	2148	java/lang/Throwable
    //   2114	2183	2186	java/lang/Throwable
    //   2152	2221	2224	java/lang/Throwable
    //   2190	2259	2262	java/lang/Throwable
    //   2228	2297	2300	java/lang/Throwable
    //   2266	2335	2338	java/lang/Throwable
    //   2304	2373	2376	java/lang/Throwable
    //   2342	2411	2414	java/lang/Throwable
    //   2380	2449	2452	java/lang/Throwable
    //   2418	2487	2490	java/lang/Throwable
    //   2456	2525	2528	java/lang/Throwable
    //   2494	2563	2566	java/lang/Throwable
    //   2532	2601	2604	java/lang/Throwable
    //   2570	2639	2642	java/lang/Throwable
    //   2608	2677	2680	java/lang/Throwable
    //   2646	2715	2718	java/lang/Throwable
    //   2684	2749	2752	java/lang/Throwable
    //   2816	2830	2830	java/lang/Throwable
    //   2841	2854	2857	java/lang/Throwable
    //   2846	2869	2872	java/lang/Throwable
    //   2861	2887	2890	java/lang/Throwable
    //   2876	2917	2920	java/lang/Throwable
    //   2983	3010	3013	java/lang/Throwable
    //   3000	3031	3034	java/lang/Throwable
    //   3017	3061	3064	java/lang/Throwable
    //   3038	3072	3072	java/lang/Throwable
    //   3083	3099	3102	java/lang/Throwable
    //   3106	3456	3459	java/lang/Throwable
    //   3290	3300	3300	java/lang/Throwable
    //   3304	3316	3316	java/lang/Throwable
    //   3320	3332	3332	java/lang/Throwable
    //   3336	3349	3349	java/lang/Throwable
    //   3353	3366	3366	java/lang/Throwable
    //   3461	3551	3554	java/lang/Throwable
    //   3506	3603	3606	java/lang/Throwable
    //   3558	3614	3614	java/lang/Throwable
  }
  
  static void ZV(Object paramObject) {
    Zs0b.ZT = a(22133, 27804);
    Zs0b.ZI = new BigInteger(a(22136, -24329));
    boolean bool = Zt2e.ZK();
    try {
      try {
        if (Zxd0.Zc.charAt(Math.abs(((BigInteger)Zl1u.Zq).intValue() % 32)) > Zkul.ZJ.charAt(Math.abs(((BigInteger)Zlyf.Zm).intValue() % 32))) {
          try {
            Zl1u.Zl(Class.forName(a(22132, -29039)));
            if (bool)
              Ze_b.ZP(Class.forName(a(22135, 1462))); 
          } catch (Throwable throwable) {
            throw a(null);
          } 
          return;
        } 
      } catch (Throwable throwable) {
        throw a(null);
      } 
      Ze_b.ZP(Class.forName(a(22135, 1462)));
    } catch (Throwable throwable) {}
  }
  
  static {
    // Byte code:
    //   0: bipush #11
    //   2: anewarray java/lang/String
    //   5: astore #5
    //   7: iconst_0
    //   8: istore_3
    //   9: ldc 'akjp\\ngMp =`=N2 bmFVOR[\\b$e\\t;Ph\\tWiF?M]J\\t9T|N3\\rZ\\tT0\M)D\\ni:Xg0\\nOHNhucTnkf"NVx ?cc mu_Ld.}25E2xO'
    //   11: dup
    //   12: astore_2
    //   13: invokevirtual length : ()I
    //   16: istore #4
    //   18: bipush #21
    //   20: istore_1
    //   21: iconst_m1
    //   22: istore_0
    //   23: bipush #10
    //   25: iinc #0, 1
    //   28: aload_2
    //   29: iload_0
    //   30: dup
    //   31: iload_1
    //   32: iadd
    //   33: invokevirtual substring : (II)Ljava/lang/String;
    //   36: iconst_m1
    //   37: goto -> 143
    //   40: aload #5
    //   42: swap
    //   43: iload_3
    //   44: iinc #3, 1
    //   47: swap
    //   48: aastore
    //   49: iload_0
    //   50: iload_1
    //   51: iadd
    //   52: dup
    //   53: istore_0
    //   54: iload #4
    //   56: if_icmpge -> 68
    //   59: aload_2
    //   60: iload_0
    //   61: invokevirtual charAt : (I)C
    //   64: istore_1
    //   65: goto -> 23
    //   68: ldc 'gi(\\b"\\tv[H'
    //   70: dup
    //   71: astore_2
    //   72: invokevirtual length : ()I
    //   75: istore #4
    //   77: bipush #8
    //   79: istore_1
    //   80: iconst_m1
    //   81: istore_0
    //   82: bipush #76
    //   84: iinc #0, 1
    //   87: aload_2
    //   88: iload_0
    //   89: dup
    //   90: iload_1
    //   91: iadd
    //   92: invokevirtual substring : (II)Ljava/lang/String;
    //   95: iconst_0
    //   96: goto -> 143
    //   99: aload #5
    //   101: swap
    //   102: iload_3
    //   103: iinc #3, 1
    //   106: swap
    //   107: aastore
    //   108: iload_0
    //   109: iload_1
    //   110: iadd
    //   111: dup
    //   112: istore_0
    //   113: iload #4
    //   115: if_icmpge -> 127
    //   118: aload_2
    //   119: iload_0
    //   120: invokevirtual charAt : (I)C
    //   123: istore_1
    //   124: goto -> 82
    //   127: aload #5
    //   129: putstatic burp/Ztid.a : [Ljava/lang/String;
    //   132: bipush #11
    //   134: anewarray java/lang/String
    //   137: putstatic burp/Ztid.b : [Ljava/lang/String;
    //   140: goto -> 300
    //   143: dup_x2
    //   144: pop
    //   145: invokevirtual toCharArray : ()[C
    //   148: dup_x1
    //   149: arraylength
    //   150: dup_x2
    //   151: pop
    //   152: iconst_0
    //   153: istore #6
    //   155: dup2_x1
    //   156: pop2
    //   157: dup_x2
    //   158: iconst_1
    //   159: if_icmpgt -> 259
    //   162: dup2
    //   163: swap
    //   164: iload #6
    //   166: dup2_x1
    //   167: caload
    //   168: swap
    //   169: iload #6
    //   171: bipush #7
    //   173: irem
    //   174: tableswitch default -> 241, 0 -> 212, 1 -> 217, 2 -> 222, 3 -> 227, 4 -> 232, 5 -> 237
    //   212: bipush #64
    //   214: goto -> 243
    //   217: bipush #86
    //   219: goto -> 243
    //   222: bipush #85
    //   224: goto -> 243
    //   227: bipush #37
    //   229: goto -> 243
    //   232: bipush #112
    //   234: goto -> 243
    //   237: iconst_4
    //   238: goto -> 243
    //   241: bipush #110
    //   243: ixor
    //   244: ixor
    //   245: i2c
    //   246: castore
    //   247: iinc #6, 1
    //   250: dup
    //   251: ifne -> 259
    //   254: dup2
    //   255: dup_x1
    //   256: goto -> 166
    //   259: dup2_x1
    //   260: pop2
    //   261: dup_x2
    //   262: iload #6
    //   264: if_icmpgt -> 162
    //   267: pop
    //   268: new java/lang/String
    //   271: dup_x1
    //   272: swap
    //   273: invokespecial <init> : ([C)V
    //   276: invokevirtual intern : ()Ljava/lang/String;
    //   279: swap
    //   280: pop
    //   281: swap
    //   282: tableswitch default -> 40, 0 -> 99
    //   300: new java/math/BigInteger
    //   303: dup
    //   304: iconst_1
    //   305: bipush #32
    //   307: newarray byte
    //   309: dup
    //   310: iconst_0
    //   311: bipush #13
    //   313: bastore
    //   314: dup
    //   315: iconst_1
    //   316: bipush #-58
    //   318: bastore
    //   319: dup
    //   320: iconst_2
    //   321: bipush #59
    //   323: bastore
    //   324: dup
    //   325: iconst_3
    //   326: bipush #59
    //   328: bastore
    //   329: dup
    //   330: iconst_4
    //   331: bipush #127
    //   333: bastore
    //   334: dup
    //   335: iconst_5
    //   336: bipush #16
    //   338: bastore
    //   339: dup
    //   340: bipush #6
    //   342: bipush #-120
    //   344: bastore
    //   345: dup
    //   346: bipush #7
    //   348: bipush #93
    //   350: bastore
    //   351: dup
    //   352: bipush #8
    //   354: bipush #11
    //   356: bastore
    //   357: dup
    //   358: bipush #9
    //   360: bipush #79
    //   362: bastore
    //   363: dup
    //   364: bipush #10
    //   366: bipush #-109
    //   368: bastore
    //   369: dup
    //   370: bipush #11
    //   372: bipush #83
    //   374: bastore
    //   375: dup
    //   376: bipush #12
    //   378: bipush #-97
    //   380: bastore
    //   381: dup
    //   382: bipush #13
    //   384: bipush #35
    //   386: bastore
    //   387: dup
    //   388: bipush #14
    //   390: bipush #-108
    //   392: bastore
    //   393: dup
    //   394: bipush #15
    //   396: bipush #-41
    //   398: bastore
    //   399: dup
    //   400: bipush #16
    //   402: bipush #-51
    //   404: bastore
    //   405: dup
    //   406: bipush #17
    //   408: bipush #102
    //   410: bastore
    //   411: dup
    //   412: bipush #18
    //   414: bipush #-98
    //   416: bastore
    //   417: dup
    //   418: bipush #19
    //   420: bipush #-80
    //   422: bastore
    //   423: dup
    //   424: bipush #20
    //   426: bipush #60
    //   428: bastore
    //   429: dup
    //   430: bipush #21
    //   432: bipush #-14
    //   434: bastore
    //   435: dup
    //   436: bipush #22
    //   438: bipush #16
    //   440: bastore
    //   441: dup
    //   442: bipush #23
    //   444: bipush #-127
    //   446: bastore
    //   447: dup
    //   448: bipush #24
    //   450: bipush #33
    //   452: bastore
    //   453: dup
    //   454: bipush #25
    //   456: bipush #83
    //   458: bastore
    //   459: dup
    //   460: bipush #26
    //   462: bipush #34
    //   464: bastore
    //   465: dup
    //   466: bipush #27
    //   468: bipush #-104
    //   470: bastore
    //   471: dup
    //   472: bipush #28
    //   474: bipush #26
    //   476: bastore
    //   477: dup
    //   478: bipush #29
    //   480: bipush #-26
    //   482: bastore
    //   483: dup
    //   484: bipush #30
    //   486: bipush #110
    //   488: bastore
    //   489: dup
    //   490: bipush #31
    //   492: bipush #-66
    //   494: bastore
    //   495: invokespecial <init> : (I[B)V
    //   498: putstatic burp/Ztid.ZL : Ljava/lang/Object;
    //   501: sipush #22140
    //   504: sipush #24326
    //   507: invokestatic a : (II)Ljava/lang/String;
    //   510: putstatic burp/Ztid.Zz : Ljava/lang/String;
    //   513: return
  }
  
  private static Throwable a(Throwable paramThrowable) {
    return paramThrowable;
  }
  
  private static String a(int paramInt1, int paramInt2) {
    int i = (paramInt1 ^ 0x567D) & 0xFFFF;
    if (b[i] == null) {
      char[] arrayOfChar = a[i].toCharArray();
      switch (arrayOfChar[0] & 0xFF) {
        case 0:
        
        case 1:
        
        case 2:
        
        case 3:
        
        case 4:
        
        case 5:
        
        case 6:
        
        case 7:
        
        case 8:
        
        case 9:
        
        case 10:
        
        case 11:
        
        case 12:
        
        case 13:
        
        case 14:
        
        case 15:
        
        case 16:
        
        case 17:
        
        case 18:
        
        case 19:
        
        case 20:
        
        case 21:
        
        case 22:
        
        case 23:
        
        case 24:
        
        case 25:
        
        case 26:
        
        case 27:
        
        case 28:
        
        case 29:
        
        case 30:
        
        case 31:
        
        case 32:
        
        case 33:
        
        case 34:
        
        case 35:
        
        case 36:
        
        case 37:
        
        case 38:
        
        case 39:
        
        case 40:
        
        case 41:
        
        case 42:
        
        case 43:
        
        case 44:
        
        case 45:
        
        case 46:
        
        case 47:
        
        case 48:
        
        case 49:
        
        case 50:
        
        case 51:
        
        case 52:
        
        case 53:
        
        case 54:
        
        case 55:
        
        case 56:
        
        case 57:
        
        case 58:
        
        case 59:
        
        case 60:
        
        case 61:
        
        case 62:
        
        case 63:
        
        case 64:
        
        case 65:
        
        case 66:
        
        case 67:
        
        case 68:
        
        case 69:
        
        case 70:
        
        case 71:
        
        case 72:
        
        case 73:
        
        case 74:
        
        case 75:
        
        case 76:
        
        case 77:
        
        case 78:
        
        case 79:
        
        case 80:
        
        case 81:
        
        case 82:
        
        case 83:
        
        case 84:
        
        case 85:
        
        case 86:
        
        case 87:
        
        case 88:
        
        case 89:
        
        case 90:
        
        case 91:
        
        case 92:
        
        case 93:
        
        case 94:
        
        case 95:
        
        case 96:
        
        case 97:
        
        case 98:
        
        case 99:
        
        case 100:
        
        case 101:
        
        case 102:
        
        case 103:
        
        case 104:
        
        case 105:
        
        case 106:
        
        case 107:
        
        case 108:
        
        case 109:
        
        case 110:
        
        case 111:
        
        case 112:
        
        case 113:
        
        case 114:
        
        case 115:
        
        case 116:
        
        case 117:
        
        case 118:
        
        case 119:
        
        case 120:
        
        case 121:
        
        case 122:
        
        case 123:
        
        case 124:
        
        case 125:
        
        case 126:
        
        case 127:
        
        case 128:
        
        case 129:
        
        case 130:
        
        case 131:
        
        case 132:
        
        case 133:
        
        case 134:
        
        case 135:
        
        case 136:
        
        case 137:
        
        case 138:
        
        case 139:
        
        case 140:
        
        case 141:
        
        case 142:
        
        case 143:
        
        case 144:
        
        case 145:
        
        case 146:
        
        case 147:
        
        case 148:
        
        case 149:
        
        case 150:
        
        case 151:
        
        case 152:
        
        case 153:
        
        case 154:
        
        case 155:
        
        case 156:
        
        case 157:
        
        case 158:
        
        case 159:
        
        case 160:
        
        case 161:
        
        case 162:
        
        case 163:
        
        case 164:
        
        case 165:
        
        case 166:
        
        case 167:
        
        case 168:
        
        case 169:
        
        case 170:
        
        case 171:
        
        case 172:
        
        case 173:
        
        case 174:
        
        case 175:
        
        case 176:
        
        case 177:
        
        case 178:
        
        case 179:
        
        case 180:
        
        case 181:
        
        case 182:
        
        case 183:
        
        case 184:
        
        case 185:
        
        case 186:
        
        case 187:
        
        case 188:
        
        case 189:
        
        case 190:
        
        case 191:
        
        case 192:
        
        case 193:
        
        case 194:
        
        case 195:
        
        case 196:
        
        case 197:
        
        case 198:
        
        case 199:
        
        case 200:
        
        case 201:
        
        case 202:
        
        case 203:
        
        case 204:
        
        case 205:
        
        case 206:
        
        case 207:
        
        case 208:
        
        case 209:
        
        case 210:
        
        case 211:
        
        case 212:
        
        case 213:
        
        case 214:
        
        case 215:
        
        case 216:
        
        case 217:
        
        case 218:
        
        case 219:
        
        case 220:
        
        case 221:
        
        case 222:
        
        case 223:
        
        case 224:
        
        case 225:
        
        case 226:
        
        case 227:
        
        case 228:
        
        case 229:
        
        case 230:
        
        case 231:
        
        case 232:
        
        case 233:
        
        case 234:
        
        case 235:
        
        case 236:
        
        case 237:
        
        case 238:
        
        case 239:
        
        case 240:
        
        case 241:
        
        case 242:
        
        case 243:
        
        case 244:
        
        case 245:
        
        case 246:
        
        case 247:
        
        case 248:
        
        case 249:
        
        case 250:
        
        case 251:
        
        case 252:
        
        case 253:
        
        case 254:
        
        default:
          break;
      } 
      byte b1 = 104;
      int j = (paramInt2 & 0xFF) - b1;
      if (j < 0)
        j += 256; 
      int k = ((paramInt2 & 0xFFFF) >>> 8) - b1;
      if (k < 0)
        k += 256; 
      for (byte b2 = 0; b2 < arrayOfChar.length; b2++) {
        int m = b2 % 2;
        if (m == 0) {
          arrayOfChar[b2] = (char)(arrayOfChar[b2] ^ j);
          j = ((j >>> 3 | j << 5) ^ arrayOfChar[b2]) & 0xFF;
        } else {
          arrayOfChar[b2] = (char)(arrayOfChar[b2] ^ k);
          k = ((k >>> 3 | k << 5) ^ arrayOfChar[b2]) & 0xFF;
        } 
      } 
      b[i] = (new String(arrayOfChar)).intern();
    } 
    return b[i];
  }
}


/* Location:              C:\Program Files\BurpSuitePro\burpsuite_pro.jar!\burp\Ztid.class
 * Java compiler version: 21 (65.0)
 * JD-Core Version:       1.1.3
 */