package burp;

import java.util.concurrent.atomic.AtomicBoolean;
import java.util.function.Supplier;

public class Ztj1 {
  private final Zgna Zr;
  
  private final Zrbm Za;
  
  private final Zx5d ZJ;
  
  private final Zbfl ZX;
  
  private final Zmc9 Zd;
  
  private final Zz4b ZV;
  
  private final Zgu7 ZN;
  
  private final Supplier<Zen5> ZH;
  
  private final Zto9 Ze;
  
  private final Zvf8 Zf;
  
  private final AtomicBoolean Zn;
  
  private final AtomicBoolean Zx;
  
  private volatile Zr5_ ZO;
  
  private static String ZY;
  
  private static final String[] a;
  
  private static final String[] b;
  
  public Ztj1(Zgna paramZgna, Zrbm paramZrbm, Zr5_ paramZr5_, Zx5d paramZx5d, Zbfl paramZbfl, Zmc9 paramZmc9, Zz4b paramZz4b, Zgu7 paramZgu7, Supplier<Zen5> paramSupplier, Zto9 paramZto9, Zvf8 paramZvf8) {
    this.Zr = paramZgna;
    this.Za = paramZrbm;
    this.ZO = paramZr5_;
    this.ZJ = paramZx5d;
    this.ZX = paramZbfl;
    this.Zd = paramZmc9;
    this.ZV = paramZz4b;
    this.ZN = paramZgu7;
    this.ZH = paramSupplier;
    this.Ze = paramZto9;
    this.Zf = paramZvf8;
    this.Zn = new AtomicBoolean();
    this.Zx = new AtomicBoolean();
  }
  
  public int Zh() {
    return this.Zr.ZPo();
  }
  
  public String Zn() {
    return this.Zr.ZPy();
  }
  
  public String ZM() {
    String str = this.Zr.ZP6();
    return (str == null || str.isEmpty()) ? Zm() : str;
  }
  
  public String ZO() {
    return "" + Zh() + Zh() + a(-7298, 19743);
  }
  
  public void ZN(String paramString) {
    this.Zr.Zon(paramString);
  }
  
  private String Zm() {
    return Zl().Zr(Zh(), Zs(), this.ZV.ZVO(), this.ZV.ZV7());
  }
  
  public String Zs() {
    return this.Zr.ZPl();
  }
  
  public String Zz() {
    return this.Zr.ZPK();
  }
  
  public Zkcl Zl() {
    return this.Zr.ZNs();
  }
  
  public Zgna ZG() {
    return this.Zr;
  }
  
  public void Zv() {
    this.Ze.Ze();
    this.Zd.Zh();
  }
  
  public void Zp() {
    this.Ze.Zd();
    this.Zd.Zk();
    this.Ze.ZD(Zt13.Z_);
    this.Ze.ZD(Zt13.Zf);
  }
  
  public void Zw() {
    this.Ze.ZD(new Zxr8(Zt13.Zv, this));
  }
  
  public void Zz(Zr5_ paramZr5_) {
    if (this.ZO == paramZr5_)
      return; 
    this.ZO.ZA(this);
    paramZr5_.ZK(this);
    this.ZX.Za(paramZr5_.Ze());
    this.ZJ.ZY(paramZr5_.ZO());
    this.ZO = paramZr5_;
    this.Ze.ZD(Zt13.Zf);
  }
  
  public Zrbm Zi() {
    return this.Za;
  }
  
  public Supplier<Zen5> ZY() {
    return this.ZH;
  }
  
  void Zu(Zx6t paramZx6t) {
    Zen5 zen5 = this.ZH.get();
    paramZx6t.ZQ(a(-7297, 21327), Integer.valueOf(zen5.ZB()));
    paramZx6t.ZQ(a(-7299, -4296), Integer.valueOf(zen5.ZF()));
    this.Zr.ZV(paramZx6t, this.Za);
  }
  
  public void Zx(Zz9t paramZz9t) {
    this.ZJ.Zi(paramZz9t);
    this.ZX.Zl(paramZz9t);
  }
  
  public int Zf() {
    return this.Zr.ZPm();
  }
  
  public Ztos<Zt13> Zr() {
    return this.Ze;
  }
  
  void ZH() {
    this.Ze.ZD(Zt13.ZD);
    this.Zx.set(true);
    this.ZO.ZA(this);
    this.Zr.ZHG();
    this.ZN.ZV(this.Zr);
  }
  
  public boolean ZF() {
    return (this.Zn.get() || this.Za.Zn());
  }
  
  public boolean ZE() {
    return this.Zr.ZPw();
  }
  
  public void Za() {
    this.ZJ.ZK();
    this.Zf.Z_();
    this.Zn.set(true);
  }
  
  public Zx5d Zx() {
    return this.ZJ;
  }
  
  public void ZG(int paramInt) {
    this.Zr.ZzT(paramInt);
  }
  
  public void Zq() {
    Zp();
  }
  
  public static void Zb(String paramString) {
    ZY = paramString;
  }
  
  public static String Ze() {
    return ZY;
  }
  
  static {
    // Byte code:
    //   0: iconst_3
    //   1: anewarray java/lang/String
    //   4: astore #5
    //   6: iconst_0
    //   7: istore_3
    //   8: ldc '!Â‡Ã£Â–Ã«bIÃ‰ÃÃ°Ã§Â½ÃªÃ—Â‘Ã²}Â $ÂŒÂ‘Ãº>`CÂŒSÃªÂ…Â´Ã–\\n<Ã¾Ã°'
    //   10: dup
    //   11: astore_2
    //   12: invokevirtual length : ()I
    //   15: istore #4
    //   17: bipush #25
    //   19: istore_1
    //   20: ldc 'Z6CG6b'
    //   22: iconst_m1
    //   23: istore_0
    //   24: invokestatic Zb : (Ljava/lang/String;)V
    //   27: bipush #72
    //   29: iinc #0, 1
    //   32: aload_2
    //   33: iload_0
    //   34: dup
    //   35: iload_1
    //   36: iadd
    //   37: invokevirtual substring : (II)Ljava/lang/String;
    //   40: iconst_m1
    //   41: goto -> 87
    //   44: aload #5
    //   46: swap
    //   47: iload_3
    //   48: iinc #3, 1
    //   51: swap
    //   52: aastore
    //   53: iload_0
    //   54: iload_1
    //   55: iadd
    //   56: dup
    //   57: istore_0
    //   58: iload #4
    //   60: if_icmpge -> 72
    //   63: aload_2
    //   64: iload_0
    //   65: invokevirtual charAt : (I)C
    //   68: istore_1
    //   69: goto -> 27
    //   72: aload #5
    //   74: putstatic burp/Ztj1.a : [Ljava/lang/String;
    //   77: iconst_3
    //   78: anewarray java/lang/String
    //   81: putstatic burp/Ztj1.b : [Ljava/lang/String;
    //   84: goto -> 231
    //   87: dup_x2
    //   88: pop
    //   89: invokevirtual toCharArray : ()[C
    //   92: dup_x1
    //   93: arraylength
    //   94: dup_x2
    //   95: pop
    //   96: iconst_0
    //   97: istore #6
    //   99: dup2_x1
    //   100: pop2
    //   101: dup_x2
    //   102: iconst_1
    //   103: if_icmpgt -> 204
    //   106: dup2
    //   107: swap
    //   108: iload #6
    //   110: dup2_x1
    //   111: caload
    //   112: swap
    //   113: iload #6
    //   115: bipush #7
    //   117: irem
    //   118: tableswitch default -> 186, 0 -> 156, 1 -> 161, 2 -> 166, 3 -> 171, 4 -> 176, 5 -> 181
    //   156: bipush #98
    //   158: goto -> 188
    //   161: bipush #79
    //   163: goto -> 188
    //   166: bipush #78
    //   168: goto -> 188
    //   171: bipush #77
    //   173: goto -> 188
    //   176: bipush #26
    //   178: goto -> 188
    //   181: bipush #68
    //   183: goto -> 188
    //   186: bipush #79
    //   188: ixor
    //   189: ixor
    //   190: i2c
    //   191: castore
    //   192: iinc #6, 1
    //   195: dup
    //   196: ifne -> 204
    //   199: dup2
    //   200: dup_x1
    //   201: goto -> 110
    //   204: dup2_x1
    //   205: pop2
    //   206: dup_x2
    //   207: iload #6
    //   209: if_icmpgt -> 106
    //   212: pop
    //   213: new java/lang/String
    //   216: dup_x1
    //   217: swap
    //   218: invokespecial <init> : ([C)V
    //   221: invokevirtual intern : ()Ljava/lang/String;
    //   224: swap
    //   225: pop
    //   226: swap
    //   227: pop
    //   228: goto -> 44
    //   231: return
  }
  
  private static String a(int paramInt1, int paramInt2) {
    int i = (paramInt1 ^ 0xFFFFE37F) & 0xFFFF;
    if (b[i] == null) {
      char[] arrayOfChar = a[i].toCharArray();
      switch (arrayOfChar[0] & 0xFF) {
        case 0:
        
        case 1:
        
        case 2:
        
        case 3:
        
        case 4:
        
        case 5:
        
        case 6:
        
        case 7:
        
        case 8:
        
        case 9:
        
        case 10:
        
        case 11:
        
        case 12:
        
        case 13:
        
        case 14:
        
        case 15:
        
        case 16:
        
        case 17:
        
        case 18:
        
        case 19:
        
        case 20:
        
        case 21:
        
        case 22:
        
        case 23:
        
        case 24:
        
        case 25:
        
        case 26:
        
        case 27:
        
        case 28:
        
        case 29:
        
        case 30:
        
        case 31:
        
        case 32:
        
        case 33:
        
        case 34:
        
        case 35:
        
        case 36:
        
        case 37:
        
        case 38:
        
        case 39:
        
        case 40:
        
        case 41:
        
        case 42:
        
        case 43:
        
        case 44:
        
        case 45:
        
        case 46:
        
        case 47:
        
        case 48:
        
        case 49:
        
        case 50:
        
        case 51:
        
        case 52:
        
        case 53:
        
        case 54:
        
        case 55:
        
        case 56:
        
        case 57:
        
        case 58:
        
        case 59:
        
        case 60:
        
        case 61:
        
        case 62:
        
        case 63:
        
        case 64:
        
        case 65:
        
        case 66:
        
        case 67:
        
        case 68:
        
        case 69:
        
        case 70:
        
        case 71:
        
        case 72:
        
        case 73:
        
        case 74:
        
        case 75:
        
        case 76:
        
        case 77:
        
        case 78:
        
        case 79:
        
        case 80:
        
        case 81:
        
        case 82:
        
        case 83:
        
        case 84:
        
        case 85:
        
        case 86:
        
        case 87:
        
        case 88:
        
        case 89:
        
        case 90:
        
        case 91:
        
        case 92:
        
        case 93:
        
        case 94:
        
        case 95:
        
        case 96:
        
        case 97:
        
        case 98:
        
        case 99:
        
        case 100:
        
        case 101:
        
        case 102:
        
        case 103:
        
        case 104:
        
        case 105:
        
        case 106:
        
        case 107:
        
        case 108:
        
        case 109:
        
        case 110:
        
        case 111:
        
        case 112:
        
        case 113:
        
        case 114:
        
        case 115:
        
        case 116:
        
        case 117:
        
        case 118:
        
        case 119:
        
        case 120:
        
        case 121:
        
        case 122:
        
        case 123:
        
        case 124:
        
        case 125:
        
        case 126:
        
        case 127:
        
        case 128:
        
        case 129:
        
        case 130:
        
        case 131:
        
        case 132:
        
        case 133:
        
        case 134:
        
        case 135:
        
        case 136:
        
        case 137:
        
        case 138:
        
        case 139:
        
        case 140:
        
        case 141:
        
        case 142:
        
        case 143:
        
        case 144:
        
        case 145:
        
        case 146:
        
        case 147:
        
        case 148:
        
        case 149:
        
        case 150:
        
        case 151:
        
        case 152:
        
        case 153:
        
        case 154:
        
        case 155:
        
        case 156:
        
        case 157:
        
        case 158:
        
        case 159:
        
        case 160:
        
        case 161:
        
        case 162:
        
        case 163:
        
        case 164:
        
        case 165:
        
        case 166:
        
        case 167:
        
        case 168:
        
        case 169:
        
        case 170:
        
        case 171:
        
        case 172:
        
        case 173:
        
        case 174:
        
        case 175:
        
        case 176:
        
        case 177:
        
        case 178:
        
        case 179:
        
        case 180:
        
        case 181:
        
        case 182:
        
        case 183:
        
        case 184:
        
        case 185:
        
        case 186:
        
        case 187:
        
        case 188:
        
        case 189:
        
        case 190:
        
        case 191:
        
        case 192:
        
        case 193:
        
        case 194:
        
        case 195:
        
        case 196:
        
        case 197:
        
        case 198:
        
        case 199:
        
        case 200:
        
        case 201:
        
        case 202:
        
        case 203:
        
        case 204:
        
        case 205:
        
        case 206:
        
        case 207:
        
        case 208:
        
        case 209:
        
        case 210:
        
        case 211:
        
        case 212:
        
        case 213:
        
        case 214:
        
        case 215:
        
        case 216:
        
        case 217:
        
        case 218:
        
        case 219:
        
        case 220:
        
        case 221:
        
        case 222:
        
        case 223:
        
        case 224:
        
        case 225:
        
        case 226:
        
        case 227:
        
        case 228:
        
        case 229:
        
        case 230:
        
        case 231:
        
        case 232:
        
        case 233:
        
        case 234:
        
        case 235:
        
        case 236:
        
        case 237:
        
        case 238:
        
        case 239:
        
        case 240:
        
        case 241:
        
        case 242:
        
        case 243:
        
        case 244:
        
        case 245:
        
        case 246:
        
        case 247:
        
        case 248:
        
        case 249:
        
        case 250:
        
        case 251:
        
        case 252:
        
        case 253:
        
        case 254:
        
        default:
          break;
      } 
      char c = 'Ã¬';
      int j = (paramInt2 & 0xFF) - c;
      if (j < 0)
        j += 256; 
      int k = ((paramInt2 & 0xFFFF) >>> 8) - c;
      if (k < 0)
        k += 256; 
      for (byte b = 0; b < arrayOfChar.length; b++) {
        int m = b % 2;
        if (m == 0) {
          arrayOfChar[b] = (char)(arrayOfChar[b] ^ j);
          j = ((j >>> 3 | j << 5) ^ arrayOfChar[b]) & 0xFF;
        } else {
          arrayOfChar[b] = (char)(arrayOfChar[b] ^ k);
          k = ((k >>> 3 | k << 5) ^ arrayOfChar[b]) & 0xFF;
        } 
      } 
      b[i] = (new String(arrayOfChar)).intern();
    } 
    return b[i];
  }
}


/* Location:              C:\Program Files\BurpSuitePro\burpsuite_pro.jar!\burp\Ztj1.class
 * Java compiler version: 21 (65.0)
 * JD-Core Version:       1.1.3
 */