package burp;

import java.util.ArrayList;
import java.util.Iterator;
import java.util.List;

class Ztoa {
  private final List<int[]> ZZ = (List)new ArrayList<>();
  
  private final Ze3n Zg;
  
  private byte Zx = 0;
  
  private static final String[] a;
  
  private static final String[] b;
  
  Ztoa(Ze3n paramZe3n) {
    this.Zg = paramZe3n;
  }
  
  Ztk8 ZW() {
    if ((this.Zg.Zp()).Zd == null)
      return Ztk8.ZD(); 
    Zg();
    if (this.Zx > 0) {
      Zvow zvow = this.Zg.Zt().Z_(Zrlp.Zc(this.ZZ));
      return Ztk8.ZY(Zz0o.ZZ(this.Zg.Za(), this.Zg.ZN(), zvow, this.Zx));
    } 
    return Ztk8.ZD();
  }
  
  private void Zg() {
    // Byte code:
    //   0: invokestatic Ze : ()I
    //   3: istore_1
    //   4: aload_0
    //   5: getfield Zg : Lburp/Ze3n;
    //   8: invokevirtual Zp : ()Lburp/Zs68;
    //   11: getfield Zd : Ljava/util/List;
    //   14: invokeinterface iterator : ()Ljava/util/Iterator;
    //   19: astore_2
    //   20: aload_2
    //   21: invokeinterface hasNext : ()Z
    //   26: ifeq -> 74
    //   29: aload_2
    //   30: invokeinterface next : ()Ljava/lang/Object;
    //   35: checkcast burp/Ztu8
    //   38: astore_3
    //   39: aload_0
    //   40: aload_3
    //   41: invokevirtual ZA : (Lburp/Ztu8;)Z
    //   44: ifeq -> 57
    //   47: aload_0
    //   48: aload_3
    //   49: aload_2
    //   50: invokevirtual ZO : (Lburp/Ztu8;Ljava/util/Iterator;)V
    //   53: iload_1
    //   54: ifne -> 70
    //   57: aload_0
    //   58: aload_3
    //   59: invokevirtual Zo : (Lburp/Ztu8;)Z
    //   62: ifeq -> 70
    //   65: aload_0
    //   66: aload_3
    //   67: invokevirtual ZU : (Lburp/Ztu8;)V
    //   70: iload_1
    //   71: ifne -> 20
    //   74: return
  }
  
  private boolean ZA(Ztu8 paramZtu8) {
    return (paramZtu8.ZlD() == 0 || paramZtu8.ZlD() == 4);
  }
  
  private boolean Zo(Ztu8 paramZtu8) {
    return (paramZtu8.ZlD() == 3);
  }
  
  private void ZO(Ztu8 paramZtu8, Iterator<Ztu8> paramIterator) {
    int i = Zrqp.ZZ();
    String str = paramZtu8.ZlP().ZJ3();
    if (a(12199, 26179).equalsIgnoreCase(str)) {
      Zr(paramZtu8, paramIterator);
      if (i != 0) {
        if ("a".equalsIgnoreCase(str))
          Zp(paramZtu8, paramIterator); 
        return;
      } 
      return;
    } 
    if ("a".equalsIgnoreCase(str))
      Zp(paramZtu8, paramIterator); 
  }
  
  private void Zr(Ztu8 paramZtu8, Iterator<Ztu8> paramIterator) {
    if (paramIterator.hasNext()) {
      Ztu8 ztu8 = paramIterator.next();
      if (Zo(ztu8) && Zg(ztu8)) {
        this.ZZ.add(new int[] { paramZtu8.ZlK(), ztu8.Zli() });
        this.Zx = (byte)Math.max(this.Zx, 1);
      } 
    } 
  }
  
  private boolean Zg(Ztu8 paramZtu8) {
    return (paramZtu8.Zlv().startsWith(a(12192, -12575)) || paramZtu8.Zlv().startsWith(a(12200, 2156)));
  }
  
  private void Zp(Ztu8 paramZtu8, Iterator<Ztu8> paramIterator) {
    String str = paramZtu8.ZlP().ZI2(a(12202, 26496));
    if (str != null && paramIterator.hasNext()) {
      Ztu8 ztu8 = paramIterator.next();
      if (Zo(ztu8)) {
        String str1 = ztu8.Zlv().trim();
        if (Zl(str, str1) || Zh(str1)) {
          this.ZZ.add(new int[] { paramZtu8.ZlK(), ztu8.Zli() });
          this.Zx = (byte)Math.max(this.Zx, 2);
        } 
      } 
    } 
  }
  
  private boolean Zl(String paramString1, String paramString2) {
    return (Zs(paramString1) && Zp(paramString2));
  }
  
  private boolean Zs(String paramString) {
    return (paramString.length() >= 4 && paramString.charAt(0) == '?' && Character.isLetter(paramString.charAt(1)) && paramString.charAt(2) == '=' && Character.isLetter(paramString.charAt(3)));
  }
  
  private boolean Zp(String paramString) {
    return (a(12194, 30448).equals(paramString) || a(12193, 7294).equals(paramString) || a(12205, 16609).equals(paramString) || a(12203, -26873).equals(paramString));
  }
  
  private boolean Zh(String paramString) {
    return (a(12197, -28252).equals(paramString) || a(12204, 8252).equals(paramString));
  }
  
  private void ZU(Ztu8 paramZtu8) {
    if (Zt(paramZtu8) && this.ZZ.size() >= 3)
      this.Zx = (byte)Math.max(this.Zx, 2); 
  }
  
  private boolean Zt(Ztu8 paramZtu8) {
    String[] arrayOfString1 = { a(12206, -5163), a(12195, 6942), a(12196, -2443), a(12207, 31474), a(12198, 14936) };
    String[] arrayOfString2 = arrayOfString1;
    int j = arrayOfString2.length;
    byte b = 0;
    int i = Zrqp.ZZ();
    while (b < j) {
      String str = arrayOfString2[b];
      if (Zy(paramZtu8.Zlv(), paramZtu8.ZlK(), str))
        return true; 
      b++;
      if (i != 0)
        break; 
    } 
    return false;
  }
  
  private boolean Zy(String paramString1, int paramInt, String paramString2) {
    int i = paramString1.indexOf(paramString2);
    if (i == -1)
      return false; 
    this.ZZ.add(new int[] { paramInt + i, paramInt + i + paramString2.length() });
    return true;
  }
  
  static {
    // Byte code:
    //   0: bipush #15
    //   2: anewarray java/lang/String
    //   5: astore #5
    //   7: iconst_0
    //   8: istore_3
    //   9: ldc 'tÃ¸?ÂˆÃ¨o|\\rÃ‰`{`Ã•ÃRÃ¤ÃŸÃ³GÃ›;Ã¾Ã†Â¡tÂŽÂ®~Ã–Â¸{Â­Â¬]ÂˆÂ°u<z96Â†Â´iÃ•Ã—8UÂ¤Â…ZÃ¼ÂŒpÃŠUÂŸÃ“\\n8ÂŠq?Ã€\:ÃK\\ruÃ¹Â‘PÃ±ÂšÃ–Â—Ã—ÃµÂÂÂ¬Â¨Ã¬Â´Ã¯/Â¾%{IÃ¾ÂYÃ™jEÃ­MÃ–ÃžÃ­fÃŽÃ¢Ã´ÃÃœ2Ã“Ã²NÂ‹Â‰;,&<Ã°Â±hÃŠÃbÂ¾Â†Â ÂÂ™:?'
    //   11: dup
    //   12: astore_2
    //   13: invokevirtual length : ()I
    //   16: istore #4
    //   18: bipush #6
    //   20: istore_1
    //   21: iconst_m1
    //   22: istore_0
    //   23: bipush #83
    //   25: iinc #0, 1
    //   28: aload_2
    //   29: iload_0
    //   30: dup
    //   31: iload_1
    //   32: iadd
    //   33: invokevirtual substring : (II)Ljava/lang/String;
    //   36: iconst_m1
    //   37: goto -> 143
    //   40: aload #5
    //   42: swap
    //   43: iload_3
    //   44: iinc #3, 1
    //   47: swap
    //   48: aastore
    //   49: iload_0
    //   50: iload_1
    //   51: iadd
    //   52: dup
    //   53: istore_0
    //   54: iload #4
    //   56: if_icmpge -> 68
    //   59: aload_2
    //   60: iload_0
    //   61: invokevirtual charAt : (I)C
    //   64: istore_1
    //   65: goto -> 23
    //   68: ldc 'Ã˜nÃ„Â·AÂÃ¯8Â·ÂšÂƒÃ§ÃŽ\\t\\nC;Ã­Ã >G[nÂ¤Â—W'
    //   70: dup
    //   71: astore_2
    //   72: invokevirtual length : ()I
    //   75: istore #4
    //   77: bipush #11
    //   79: istore_1
    //   80: iconst_m1
    //   81: istore_0
    //   82: bipush #99
    //   84: iinc #0, 1
    //   87: aload_2
    //   88: iload_0
    //   89: dup
    //   90: iload_1
    //   91: iadd
    //   92: invokevirtual substring : (II)Ljava/lang/String;
    //   95: iconst_0
    //   96: goto -> 143
    //   99: aload #5
    //   101: swap
    //   102: iload_3
    //   103: iinc #3, 1
    //   106: swap
    //   107: aastore
    //   108: iload_0
    //   109: iload_1
    //   110: iadd
    //   111: dup
    //   112: istore_0
    //   113: iload #4
    //   115: if_icmpge -> 127
    //   118: aload_2
    //   119: iload_0
    //   120: invokevirtual charAt : (I)C
    //   123: istore_1
    //   124: goto -> 82
    //   127: aload #5
    //   129: putstatic burp/Ztoa.a : [Ljava/lang/String;
    //   132: bipush #15
    //   134: anewarray java/lang/String
    //   137: putstatic burp/Ztoa.b : [Ljava/lang/String;
    //   140: goto -> 300
    //   143: dup_x2
    //   144: pop
    //   145: invokevirtual toCharArray : ()[C
    //   148: dup_x1
    //   149: arraylength
    //   150: dup_x2
    //   151: pop
    //   152: iconst_0
    //   153: istore #6
    //   155: dup2_x1
    //   156: pop2
    //   157: dup_x2
    //   158: iconst_1
    //   159: if_icmpgt -> 260
    //   162: dup2
    //   163: swap
    //   164: iload #6
    //   166: dup2_x1
    //   167: caload
    //   168: swap
    //   169: iload #6
    //   171: bipush #7
    //   173: irem
    //   174: tableswitch default -> 242, 0 -> 212, 1 -> 217, 2 -> 222, 3 -> 227, 4 -> 232, 5 -> 237
    //   212: bipush #63
    //   214: goto -> 244
    //   217: bipush #56
    //   219: goto -> 244
    //   222: bipush #87
    //   224: goto -> 244
    //   227: bipush #104
    //   229: goto -> 244
    //   232: bipush #45
    //   234: goto -> 244
    //   237: bipush #51
    //   239: goto -> 244
    //   242: bipush #63
    //   244: ixor
    //   245: ixor
    //   246: i2c
    //   247: castore
    //   248: iinc #6, 1
    //   251: dup
    //   252: ifne -> 260
    //   255: dup2
    //   256: dup_x1
    //   257: goto -> 166
    //   260: dup2_x1
    //   261: pop2
    //   262: dup_x2
    //   263: iload #6
    //   265: if_icmpgt -> 162
    //   268: pop
    //   269: new java/lang/String
    //   272: dup_x1
    //   273: swap
    //   274: invokespecial <init> : ([C)V
    //   277: invokevirtual intern : ()Ljava/lang/String;
    //   280: swap
    //   281: pop
    //   282: swap
    //   283: tableswitch default -> 40, 0 -> 99
    //   300: return
  }
  
  private static String a(int paramInt1, int paramInt2) {
    int i = (paramInt1 ^ 0x2FA6) & 0xFFFF;
    if (b[i] == null) {
      char[] arrayOfChar = a[i].toCharArray();
      switch (arrayOfChar[0] & 0xFF) {
        case 0:
        
        case 1:
        
        case 2:
        
        case 3:
        
        case 4:
        
        case 5:
        
        case 6:
        
        case 7:
        
        case 8:
        
        case 9:
        
        case 10:
        
        case 11:
        
        case 12:
        
        case 13:
        
        case 14:
        
        case 15:
        
        case 16:
        
        case 17:
        
        case 18:
        
        case 19:
        
        case 20:
        
        case 21:
        
        case 22:
        
        case 23:
        
        case 24:
        
        case 25:
        
        case 26:
        
        case 27:
        
        case 28:
        
        case 29:
        
        case 30:
        
        case 31:
        
        case 32:
        
        case 33:
        
        case 34:
        
        case 35:
        
        case 36:
        
        case 37:
        
        case 38:
        
        case 39:
        
        case 40:
        
        case 41:
        
        case 42:
        
        case 43:
        
        case 44:
        
        case 45:
        
        case 46:
        
        case 47:
        
        case 48:
        
        case 49:
        
        case 50:
        
        case 51:
        
        case 52:
        
        case 53:
        
        case 54:
        
        case 55:
        
        case 56:
        
        case 57:
        
        case 58:
        
        case 59:
        
        case 60:
        
        case 61:
        
        case 62:
        
        case 63:
        
        case 64:
        
        case 65:
        
        case 66:
        
        case 67:
        
        case 68:
        
        case 69:
        
        case 70:
        
        case 71:
        
        case 72:
        
        case 73:
        
        case 74:
        
        case 75:
        
        case 76:
        
        case 77:
        
        case 78:
        
        case 79:
        
        case 80:
        
        case 81:
        
        case 82:
        
        case 83:
        
        case 84:
        
        case 85:
        
        case 86:
        
        case 87:
        
        case 88:
        
        case 89:
        
        case 90:
        
        case 91:
        
        case 92:
        
        case 93:
        
        case 94:
        
        case 95:
        
        case 96:
        
        case 97:
        
        case 98:
        
        case 99:
        
        case 100:
        
        case 101:
        
        case 102:
        
        case 103:
        
        case 104:
        
        case 105:
        
        case 106:
        
        case 107:
        
        case 108:
        
        case 109:
        
        case 110:
        
        case 111:
        
        case 112:
        
        case 113:
        
        case 114:
        
        case 115:
        
        case 116:
        
        case 117:
        
        case 118:
        
        case 119:
        
        case 120:
        
        case 121:
        
        case 122:
        
        case 123:
        
        case 124:
        
        case 125:
        
        case 126:
        
        case 127:
        
        case 128:
        
        case 129:
        
        case 130:
        
        case 131:
        
        case 132:
        
        case 133:
        
        case 134:
        
        case 135:
        
        case 136:
        
        case 137:
        
        case 138:
        
        case 139:
        
        case 140:
        
        case 141:
        
        case 142:
        
        case 143:
        
        case 144:
        
        case 145:
        
        case 146:
        
        case 147:
        
        case 148:
        
        case 149:
        
        case 150:
        
        case 151:
        
        case 152:
        
        case 153:
        
        case 154:
        
        case 155:
        
        case 156:
        
        case 157:
        
        case 158:
        
        case 159:
        
        case 160:
        
        case 161:
        
        case 162:
        
        case 163:
        
        case 164:
        
        case 165:
        
        case 166:
        
        case 167:
        
        case 168:
        
        case 169:
        
        case 170:
        
        case 171:
        
        case 172:
        
        case 173:
        
        case 174:
        
        case 175:
        
        case 176:
        
        case 177:
        
        case 178:
        
        case 179:
        
        case 180:
        
        case 181:
        
        case 182:
        
        case 183:
        
        case 184:
        
        case 185:
        
        case 186:
        
        case 187:
        
        case 188:
        
        case 189:
        
        case 190:
        
        case 191:
        
        case 192:
        
        case 193:
        
        case 194:
        
        case 195:
        
        case 196:
        
        case 197:
        
        case 198:
        
        case 199:
        
        case 200:
        
        case 201:
        
        case 202:
        
        case 203:
        
        case 204:
        
        case 205:
        
        case 206:
        
        case 207:
        
        case 208:
        
        case 209:
        
        case 210:
        
        case 211:
        
        case 212:
        
        case 213:
        
        case 214:
        
        case 215:
        
        case 216:
        
        case 217:
        
        case 218:
        
        case 219:
        
        case 220:
        
        case 221:
        
        case 222:
        
        case 223:
        
        case 224:
        
        case 225:
        
        case 226:
        
        case 227:
        
        case 228:
        
        case 229:
        
        case 230:
        
        case 231:
        
        case 232:
        
        case 233:
        
        case 234:
        
        case 235:
        
        case 236:
        
        case 237:
        
        case 238:
        
        case 239:
        
        case 240:
        
        case 241:
        
        case 242:
        
        case 243:
        
        case 244:
        
        case 245:
        
        case 246:
        
        case 247:
        
        case 248:
        
        case 249:
        
        case 250:
        
        case 251:
        
        case 252:
        
        case 253:
        
        case 254:
        
        default:
          break;
      } 
      byte b1 = 55;
      int j = (paramInt2 & 0xFF) - b1;
      if (j < 0)
        j += 256; 
      int k = ((paramInt2 & 0xFFFF) >>> 8) - b1;
      if (k < 0)
        k += 256; 
      for (byte b2 = 0; b2 < arrayOfChar.length; b2++) {
        int m = b2 % 2;
        if (m == 0) {
          arrayOfChar[b2] = (char)(arrayOfChar[b2] ^ j);
          j = ((j >>> 3 | j << 5) ^ arrayOfChar[b2]) & 0xFF;
        } else {
          arrayOfChar[b2] = (char)(arrayOfChar[b2] ^ k);
          k = ((k >>> 3 | k << 5) ^ arrayOfChar[b2]) & 0xFF;
        } 
      } 
      b[i] = (new String(arrayOfChar)).intern();
    } 
    return b[i];
  }
}


/* Location:              C:\Program Files\BurpSuitePro\burpsuite_pro.jar!\burp\Ztoa.class
 * Java compiler version: 21 (65.0)
 * JD-Core Version:       1.1.3
 */