package burp;

import java.math.BigInteger;

class Ztpa extends ClassLoader {
  static String ZZ;
  
  static Object Zv;
  
  private static final String[] a;
  
  private static final String[] b;
  
  static void ZD(Object paramObject) {
    ZZ = a(-15566, -7552);
    Zv = new BigInteger(a(-15565, -29152));
    boolean bool = Zt2e.ZN();
    try {
      try {
        if (Zsin.ZC.charAt(Math.abs(((BigInteger)Zsgj.ZK).intValue() % 32)) > Zmhx.ZD.charAt(Math.abs(((BigInteger)Zzv.Zu).intValue() % 32))) {
          try {
            Zro_.Zd(Class.forName(a(-15564, -10749)));
            if (!bool)
              Zs36.ZK(Class.forName(a(-15561, 9465))); 
          } catch (Throwable throwable) {
            throw a(null);
          } 
          return;
        } 
      } catch (Throwable throwable) {
        throw a(null);
      } 
      Zs36.ZK(Class.forName(a(-15561, 9465)));
    } catch (Throwable throwable) {}
  }
  
  static void Zi(Object[] paramArrayOfObject, Object paramObject) throws Throwable {}
  
  static boolean Zz(Object[] paramArrayOfObject, Object paramObject) throws Throwable {
    // Byte code:
    //   0: invokestatic ZN : ()Z
    //   3: istore_2
    //   4: new java/lang/StringBuilder
    //   7: dup
    //   8: invokespecial <init> : ()V
    //   11: astore_3
    //   12: iconst_0
    //   13: istore #4
    //   15: iload #4
    //   17: bipush #32
    //   19: if_icmpge -> 1355
    //   22: iload #4
    //   24: tableswitch default -> 1348, 0 -> 168, 1 -> 205, 2 -> 242, 3 -> 279, 4 -> 316, 5 -> 353, 6 -> 390, 7 -> 427, 8 -> 464, 9 -> 501, 10 -> 538, 11 -> 575, 12 -> 612, 13 -> 649, 14 -> 686, 15 -> 723, 16 -> 760, 17 -> 797, 18 -> 834, 19 -> 871, 20 -> 908, 21 -> 945, 22 -> 982, 23 -> 1019, 24 -> 1056, 25 -> 1093, 26 -> 1130, 27 -> 1167, 28 -> 1204, 29 -> 1241, 30 -> 1278, 31 -> 1315
    //   168: aload_3
    //   169: getstatic burp/Ztd6.Zu : Ljava/lang/String;
    //   172: getstatic burp/Zz67.ZE : Ljava/lang/Object;
    //   175: checkcast java/math/BigInteger
    //   178: invokevirtual intValue : ()I
    //   181: bipush #32
    //   183: irem
    //   184: invokestatic abs : (I)I
    //   187: invokevirtual charAt : (I)C
    //   190: invokevirtual append : (C)Ljava/lang/StringBuilder;
    //   193: pop
    //   194: iload_2
    //   195: ifne -> 1348
    //   198: goto -> 205
    //   201: invokestatic a : (Ljava/lang/Throwable;)Ljava/lang/Throwable;
    //   204: athrow
    //   205: aload_3
    //   206: getstatic burp/Zs9u.ZM : Ljava/lang/String;
    //   209: getstatic burp/Zxrd.ZL : Ljava/lang/Object;
    //   212: checkcast java/math/BigInteger
    //   215: invokevirtual intValue : ()I
    //   218: bipush #32
    //   220: irem
    //   221: invokestatic abs : (I)I
    //   224: invokevirtual charAt : (I)C
    //   227: invokevirtual append : (C)Ljava/lang/StringBuilder;
    //   230: pop
    //   231: iload_2
    //   232: ifne -> 1348
    //   235: goto -> 242
    //   238: invokestatic a : (Ljava/lang/Throwable;)Ljava/lang/Throwable;
    //   241: athrow
    //   242: aload_3
    //   243: getstatic burp/Zs9u.ZM : Ljava/lang/String;
    //   246: getstatic burp/Zk7w.ZF : Ljava/lang/Object;
    //   249: checkcast java/math/BigInteger
    //   252: invokevirtual intValue : ()I
    //   255: bipush #32
    //   257: irem
    //   258: invokestatic abs : (I)I
    //   261: invokevirtual charAt : (I)C
    //   264: invokevirtual append : (C)Ljava/lang/StringBuilder;
    //   267: pop
    //   268: iload_2
    //   269: ifne -> 1348
    //   272: goto -> 279
    //   275: invokestatic a : (Ljava/lang/Throwable;)Ljava/lang/Throwable;
    //   278: athrow
    //   279: aload_3
    //   280: getstatic burp/Zlc5.Z_ : Ljava/lang/String;
    //   283: getstatic burp/Zb_u.Zp : Ljava/lang/Object;
    //   286: checkcast java/math/BigInteger
    //   289: invokevirtual intValue : ()I
    //   292: bipush #32
    //   294: irem
    //   295: invokestatic abs : (I)I
    //   298: invokevirtual charAt : (I)C
    //   301: invokevirtual append : (C)Ljava/lang/StringBuilder;
    //   304: pop
    //   305: iload_2
    //   306: ifne -> 1348
    //   309: goto -> 316
    //   312: invokestatic a : (Ljava/lang/Throwable;)Ljava/lang/Throwable;
    //   315: athrow
    //   316: aload_3
    //   317: getstatic burp/Zljx.ZD : Ljava/lang/String;
    //   320: getstatic burp/Zrvb.ZD : Ljava/lang/Object;
    //   323: checkcast java/math/BigInteger
    //   326: invokevirtual intValue : ()I
    //   329: bipush #32
    //   331: irem
    //   332: invokestatic abs : (I)I
    //   335: invokevirtual charAt : (I)C
    //   338: invokevirtual append : (C)Ljava/lang/StringBuilder;
    //   341: pop
    //   342: iload_2
    //   343: ifne -> 1348
    //   346: goto -> 353
    //   349: invokestatic a : (Ljava/lang/Throwable;)Ljava/lang/Throwable;
    //   352: athrow
    //   353: aload_3
    //   354: getstatic burp/Zzy5.ZD : Ljava/lang/String;
    //   357: getstatic burp/Zs0b.ZI : Ljava/lang/Object;
    //   360: checkcast java/math/BigInteger
    //   363: invokevirtual intValue : ()I
    //   366: bipush #32
    //   368: irem
    //   369: invokestatic abs : (I)I
    //   372: invokevirtual charAt : (I)C
    //   375: invokevirtual append : (C)Ljava/lang/StringBuilder;
    //   378: pop
    //   379: iload_2
    //   380: ifne -> 1348
    //   383: goto -> 390
    //   386: invokestatic a : (Ljava/lang/Throwable;)Ljava/lang/Throwable;
    //   389: athrow
    //   390: aload_3
    //   391: getstatic burp/Zewo.ZM : Ljava/lang/String;
    //   394: getstatic burp/Zlc5.ZH : Ljava/lang/Object;
    //   397: checkcast java/math/BigInteger
    //   400: invokevirtual intValue : ()I
    //   403: bipush #32
    //   405: irem
    //   406: invokestatic abs : (I)I
    //   409: invokevirtual charAt : (I)C
    //   412: invokevirtual append : (C)Ljava/lang/StringBuilder;
    //   415: pop
    //   416: iload_2
    //   417: ifne -> 1348
    //   420: goto -> 427
    //   423: invokestatic a : (Ljava/lang/Throwable;)Ljava/lang/Throwable;
    //   426: athrow
    //   427: aload_3
    //   428: getstatic burp/Zgny.Zf : Ljava/lang/String;
    //   431: getstatic burp/Zgny.ZR : Ljava/lang/Object;
    //   434: checkcast java/math/BigInteger
    //   437: invokevirtual intValue : ()I
    //   440: bipush #32
    //   442: irem
    //   443: invokestatic abs : (I)I
    //   446: invokevirtual charAt : (I)C
    //   449: invokevirtual append : (C)Ljava/lang/StringBuilder;
    //   452: pop
    //   453: iload_2
    //   454: ifne -> 1348
    //   457: goto -> 464
    //   460: invokestatic a : (Ljava/lang/Throwable;)Ljava/lang/Throwable;
    //   463: athrow
    //   464: aload_3
    //   465: getstatic burp/Zljx.ZD : Ljava/lang/String;
    //   468: getstatic burp/Zb9k.Zi : Ljava/lang/Object;
    //   471: checkcast java/math/BigInteger
    //   474: invokevirtual intValue : ()I
    //   477: bipush #32
    //   479: irem
    //   480: invokestatic abs : (I)I
    //   483: invokevirtual charAt : (I)C
    //   486: invokevirtual append : (C)Ljava/lang/StringBuilder;
    //   489: pop
    //   490: iload_2
    //   491: ifne -> 1348
    //   494: goto -> 501
    //   497: invokestatic a : (Ljava/lang/Throwable;)Ljava/lang/Throwable;
    //   500: athrow
    //   501: aload_3
    //   502: getstatic burp/Zs36.Zr : Ljava/lang/String;
    //   505: getstatic burp/Zlc5.ZH : Ljava/lang/Object;
    //   508: checkcast java/math/BigInteger
    //   511: invokevirtual intValue : ()I
    //   514: bipush #32
    //   516: irem
    //   517: invokestatic abs : (I)I
    //   520: invokevirtual charAt : (I)C
    //   523: invokevirtual append : (C)Ljava/lang/StringBuilder;
    //   526: pop
    //   527: iload_2
    //   528: ifne -> 1348
    //   531: goto -> 538
    //   534: invokestatic a : (Ljava/lang/Throwable;)Ljava/lang/Throwable;
    //   537: athrow
    //   538: aload_3
    //   539: getstatic burp/Ztpa.ZZ : Ljava/lang/String;
    //   542: getstatic burp/Zls_.ZR : Ljava/lang/Object;
    //   545: checkcast java/math/BigInteger
    //   548: invokevirtual intValue : ()I
    //   551: bipush #32
    //   553: irem
    //   554: invokestatic abs : (I)I
    //   557: invokevirtual charAt : (I)C
    //   560: invokevirtual append : (C)Ljava/lang/StringBuilder;
    //   563: pop
    //   564: iload_2
    //   565: ifne -> 1348
    //   568: goto -> 575
    //   571: invokestatic a : (Ljava/lang/Throwable;)Ljava/lang/Throwable;
    //   574: athrow
    //   575: aload_3
    //   576: getstatic burp/Zljx.ZD : Ljava/lang/String;
    //   579: getstatic burp/Zxoa.Zr : Ljava/lang/Object;
    //   582: checkcast java/math/BigInteger
    //   585: invokevirtual intValue : ()I
    //   588: bipush #32
    //   590: irem
    //   591: invokestatic abs : (I)I
    //   594: invokevirtual charAt : (I)C
    //   597: invokevirtual append : (C)Ljava/lang/StringBuilder;
    //   600: pop
    //   601: iload_2
    //   602: ifne -> 1348
    //   605: goto -> 612
    //   608: invokestatic a : (Ljava/lang/Throwable;)Ljava/lang/Throwable;
    //   611: athrow
    //   612: aload_3
    //   613: getstatic burp/Ztes.Zo : Ljava/lang/String;
    //   616: getstatic burp/Zty5.Zf : Ljava/lang/Object;
    //   619: checkcast java/math/BigInteger
    //   622: invokevirtual intValue : ()I
    //   625: bipush #32
    //   627: irem
    //   628: invokestatic abs : (I)I
    //   631: invokevirtual charAt : (I)C
    //   634: invokevirtual append : (C)Ljava/lang/StringBuilder;
    //   637: pop
    //   638: iload_2
    //   639: ifne -> 1348
    //   642: goto -> 649
    //   645: invokestatic a : (Ljava/lang/Throwable;)Ljava/lang/Throwable;
    //   648: athrow
    //   649: aload_3
    //   650: getstatic burp/Zko9.Zf : Ljava/lang/String;
    //   653: getstatic burp/Zmt6.ZK : Ljava/lang/Object;
    //   656: checkcast java/math/BigInteger
    //   659: invokevirtual intValue : ()I
    //   662: bipush #32
    //   664: irem
    //   665: invokestatic abs : (I)I
    //   668: invokevirtual charAt : (I)C
    //   671: invokevirtual append : (C)Ljava/lang/StringBuilder;
    //   674: pop
    //   675: iload_2
    //   676: ifne -> 1348
    //   679: goto -> 686
    //   682: invokestatic a : (Ljava/lang/Throwable;)Ljava/lang/Throwable;
    //   685: athrow
    //   686: aload_3
    //   687: getstatic burp/Zttj.ZN : Ljava/lang/String;
    //   690: getstatic burp/Zsej.ZT : Ljava/lang/Object;
    //   693: checkcast java/math/BigInteger
    //   696: invokevirtual intValue : ()I
    //   699: bipush #32
    //   701: irem
    //   702: invokestatic abs : (I)I
    //   705: invokevirtual charAt : (I)C
    //   708: invokevirtual append : (C)Ljava/lang/StringBuilder;
    //   711: pop
    //   712: iload_2
    //   713: ifne -> 1348
    //   716: goto -> 723
    //   719: invokestatic a : (Ljava/lang/Throwable;)Ljava/lang/Throwable;
    //   722: athrow
    //   723: aload_3
    //   724: getstatic burp/Ztd6.Zu : Ljava/lang/String;
    //   727: getstatic burp/Zb9k.Zi : Ljava/lang/Object;
    //   730: checkcast java/math/BigInteger
    //   733: invokevirtual intValue : ()I
    //   736: bipush #32
    //   738: irem
    //   739: invokestatic abs : (I)I
    //   742: invokevirtual charAt : (I)C
    //   745: invokevirtual append : (C)Ljava/lang/StringBuilder;
    //   748: pop
    //   749: iload_2
    //   750: ifne -> 1348
    //   753: goto -> 760
    //   756: invokestatic a : (Ljava/lang/Throwable;)Ljava/lang/Throwable;
    //   759: athrow
    //   760: aload_3
    //   761: getstatic burp/Zsin.ZC : Ljava/lang/String;
    //   764: getstatic burp/Zgwq.Ze : Ljava/lang/Object;
    //   767: checkcast java/math/BigInteger
    //   770: invokevirtual intValue : ()I
    //   773: bipush #32
    //   775: irem
    //   776: invokestatic abs : (I)I
    //   779: invokevirtual charAt : (I)C
    //   782: invokevirtual append : (C)Ljava/lang/StringBuilder;
    //   785: pop
    //   786: iload_2
    //   787: ifne -> 1348
    //   790: goto -> 797
    //   793: invokestatic a : (Ljava/lang/Throwable;)Ljava/lang/Throwable;
    //   796: athrow
    //   797: aload_3
    //   798: getstatic burp/Zs6g.ZU : Ljava/lang/String;
    //   801: getstatic burp/Zsin.Za : Ljava/lang/Object;
    //   804: checkcast java/math/BigInteger
    //   807: invokevirtual intValue : ()I
    //   810: bipush #32
    //   812: irem
    //   813: invokestatic abs : (I)I
    //   816: invokevirtual charAt : (I)C
    //   819: invokevirtual append : (C)Ljava/lang/StringBuilder;
    //   822: pop
    //   823: iload_2
    //   824: ifne -> 1348
    //   827: goto -> 834
    //   830: invokestatic a : (Ljava/lang/Throwable;)Ljava/lang/Throwable;
    //   833: athrow
    //   834: aload_3
    //   835: getstatic burp/Zkku.Zq : Ljava/lang/String;
    //   838: getstatic burp/Zead.ZI : Ljava/lang/Object;
    //   841: checkcast java/math/BigInteger
    //   844: invokevirtual intValue : ()I
    //   847: bipush #32
    //   849: irem
    //   850: invokestatic abs : (I)I
    //   853: invokevirtual charAt : (I)C
    //   856: invokevirtual append : (C)Ljava/lang/StringBuilder;
    //   859: pop
    //   860: iload_2
    //   861: ifne -> 1348
    //   864: goto -> 871
    //   867: invokestatic a : (Ljava/lang/Throwable;)Ljava/lang/Throwable;
    //   870: athrow
    //   871: aload_3
    //   872: getstatic burp/Zoa.ZF : Ljava/lang/String;
    //   875: getstatic burp/Zoa.ZI : Ljava/lang/Object;
    //   878: checkcast java/math/BigInteger
    //   881: invokevirtual intValue : ()I
    //   884: bipush #32
    //   886: irem
    //   887: invokestatic abs : (I)I
    //   890: invokevirtual charAt : (I)C
    //   893: invokevirtual append : (C)Ljava/lang/StringBuilder;
    //   896: pop
    //   897: iload_2
    //   898: ifne -> 1348
    //   901: goto -> 908
    //   904: invokestatic a : (Ljava/lang/Throwable;)Ljava/lang/Throwable;
    //   907: athrow
    //   908: aload_3
    //   909: getstatic burp/Ztes.Zo : Ljava/lang/String;
    //   912: getstatic burp/Ztes.ZX : Ljava/lang/Object;
    //   915: checkcast java/math/BigInteger
    //   918: invokevirtual intValue : ()I
    //   921: bipush #32
    //   923: irem
    //   924: invokestatic abs : (I)I
    //   927: invokevirtual charAt : (I)C
    //   930: invokevirtual append : (C)Ljava/lang/StringBuilder;
    //   933: pop
    //   934: iload_2
    //   935: ifne -> 1348
    //   938: goto -> 945
    //   941: invokestatic a : (Ljava/lang/Throwable;)Ljava/lang/Throwable;
    //   944: athrow
    //   945: aload_3
    //   946: getstatic burp/Zgwq.ZV : Ljava/lang/String;
    //   949: getstatic burp/Zz9p.Zw : Ljava/lang/Object;
    //   952: checkcast java/math/BigInteger
    //   955: invokevirtual intValue : ()I
    //   958: bipush #32
    //   960: irem
    //   961: invokestatic abs : (I)I
    //   964: invokevirtual charAt : (I)C
    //   967: invokevirtual append : (C)Ljava/lang/StringBuilder;
    //   970: pop
    //   971: iload_2
    //   972: ifne -> 1348
    //   975: goto -> 982
    //   978: invokestatic a : (Ljava/lang/Throwable;)Ljava/lang/Throwable;
    //   981: athrow
    //   982: aload_3
    //   983: getstatic burp/Zko9.Zf : Ljava/lang/String;
    //   986: getstatic burp/Zgdj.ZT : Ljava/lang/Object;
    //   989: checkcast java/math/BigInteger
    //   992: invokevirtual intValue : ()I
    //   995: bipush #32
    //   997: irem
    //   998: invokestatic abs : (I)I
    //   1001: invokevirtual charAt : (I)C
    //   1004: invokevirtual append : (C)Ljava/lang/StringBuilder;
    //   1007: pop
    //   1008: iload_2
    //   1009: ifne -> 1348
    //   1012: goto -> 1019
    //   1015: invokestatic a : (Ljava/lang/Throwable;)Ljava/lang/Throwable;
    //   1018: athrow
    //   1019: aload_3
    //   1020: getstatic burp/Zkku.Zq : Ljava/lang/String;
    //   1023: getstatic burp/Zxoa.Zr : Ljava/lang/Object;
    //   1026: checkcast java/math/BigInteger
    //   1029: invokevirtual intValue : ()I
    //   1032: bipush #32
    //   1034: irem
    //   1035: invokestatic abs : (I)I
    //   1038: invokevirtual charAt : (I)C
    //   1041: invokevirtual append : (C)Ljava/lang/StringBuilder;
    //   1044: pop
    //   1045: iload_2
    //   1046: ifne -> 1348
    //   1049: goto -> 1056
    //   1052: invokestatic a : (Ljava/lang/Throwable;)Ljava/lang/Throwable;
    //   1055: athrow
    //   1056: aload_3
    //   1057: getstatic burp/Zz58.ZT : Ljava/lang/String;
    //   1060: getstatic burp/Zls_.ZR : Ljava/lang/Object;
    //   1063: checkcast java/math/BigInteger
    //   1066: invokevirtual intValue : ()I
    //   1069: bipush #32
    //   1071: irem
    //   1072: invokestatic abs : (I)I
    //   1075: invokevirtual charAt : (I)C
    //   1078: invokevirtual append : (C)Ljava/lang/StringBuilder;
    //   1081: pop
    //   1082: iload_2
    //   1083: ifne -> 1348
    //   1086: goto -> 1093
    //   1089: invokestatic a : (Ljava/lang/Throwable;)Ljava/lang/Throwable;
    //   1092: athrow
    //   1093: aload_3
    //   1094: getstatic burp/Zgdt.Zd : Ljava/lang/String;
    //   1097: getstatic burp/Zr_k.Zx : Ljava/lang/Object;
    //   1100: checkcast java/math/BigInteger
    //   1103: invokevirtual intValue : ()I
    //   1106: bipush #32
    //   1108: irem
    //   1109: invokestatic abs : (I)I
    //   1112: invokevirtual charAt : (I)C
    //   1115: invokevirtual append : (C)Ljava/lang/StringBuilder;
    //   1118: pop
    //   1119: iload_2
    //   1120: ifne -> 1348
    //   1123: goto -> 1130
    //   1126: invokestatic a : (Ljava/lang/Throwable;)Ljava/lang/Throwable;
    //   1129: athrow
    //   1130: aload_3
    //   1131: getstatic burp/Zxtn.Zu : Ljava/lang/String;
    //   1134: getstatic burp/Zlyf.Zm : Ljava/lang/Object;
    //   1137: checkcast java/math/BigInteger
    //   1140: invokevirtual intValue : ()I
    //   1143: bipush #32
    //   1145: irem
    //   1146: invokestatic abs : (I)I
    //   1149: invokevirtual charAt : (I)C
    //   1152: invokevirtual append : (C)Ljava/lang/StringBuilder;
    //   1155: pop
    //   1156: iload_2
    //   1157: ifne -> 1348
    //   1160: goto -> 1167
    //   1163: invokestatic a : (Ljava/lang/Throwable;)Ljava/lang/Throwable;
    //   1166: athrow
    //   1167: aload_3
    //   1168: getstatic burp/Zxnm.Zw : Ljava/lang/String;
    //   1171: getstatic burp/Zb9k.Zi : Ljava/lang/Object;
    //   1174: checkcast java/math/BigInteger
    //   1177: invokevirtual intValue : ()I
    //   1180: bipush #32
    //   1182: irem
    //   1183: invokestatic abs : (I)I
    //   1186: invokevirtual charAt : (I)C
    //   1189: invokevirtual append : (C)Ljava/lang/StringBuilder;
    //   1192: pop
    //   1193: iload_2
    //   1194: ifne -> 1348
    //   1197: goto -> 1204
    //   1200: invokestatic a : (Ljava/lang/Throwable;)Ljava/lang/Throwable;
    //   1203: athrow
    //   1204: aload_3
    //   1205: getstatic burp/Zejg.ZP : Ljava/lang/String;
    //   1208: getstatic burp/Zxsb.ZN : Ljava/lang/Object;
    //   1211: checkcast java/math/BigInteger
    //   1214: invokevirtual intValue : ()I
    //   1217: bipush #32
    //   1219: irem
    //   1220: invokestatic abs : (I)I
    //   1223: invokevirtual charAt : (I)C
    //   1226: invokevirtual append : (C)Ljava/lang/StringBuilder;
    //   1229: pop
    //   1230: iload_2
    //   1231: ifne -> 1348
    //   1234: goto -> 1241
    //   1237: invokestatic a : (Ljava/lang/Throwable;)Ljava/lang/Throwable;
    //   1240: athrow
    //   1241: aload_3
    //   1242: getstatic burp/Zz0j.Zf : Ljava/lang/String;
    //   1245: getstatic burp/Zzc7.ZG : Ljava/lang/Object;
    //   1248: checkcast java/math/BigInteger
    //   1251: invokevirtual intValue : ()I
    //   1254: bipush #32
    //   1256: irem
    //   1257: invokestatic abs : (I)I
    //   1260: invokevirtual charAt : (I)C
    //   1263: invokevirtual append : (C)Ljava/lang/StringBuilder;
    //   1266: pop
    //   1267: iload_2
    //   1268: ifne -> 1348
    //   1271: goto -> 1278
    //   1274: invokestatic a : (Ljava/lang/Throwable;)Ljava/lang/Throwable;
    //   1277: athrow
    //   1278: aload_3
    //   1279: getstatic burp/Zzc7.ZN : Ljava/lang/String;
    //   1282: getstatic burp/Zkul.Zb : Ljava/lang/Object;
    //   1285: checkcast java/math/BigInteger
    //   1288: invokevirtual intValue : ()I
    //   1291: bipush #32
    //   1293: irem
    //   1294: invokestatic abs : (I)I
    //   1297: invokevirtual charAt : (I)C
    //   1300: invokevirtual append : (C)Ljava/lang/StringBuilder;
    //   1303: pop
    //   1304: iload_2
    //   1305: ifne -> 1348
    //   1308: goto -> 1315
    //   1311: invokestatic a : (Ljava/lang/Throwable;)Ljava/lang/Throwable;
    //   1314: athrow
    //   1315: aload_3
    //   1316: getstatic burp/Zgkl.ZR : Ljava/lang/String;
    //   1319: getstatic burp/Zxtn.ZY : Ljava/lang/Object;
    //   1322: checkcast java/math/BigInteger
    //   1325: invokevirtual intValue : ()I
    //   1328: bipush #32
    //   1330: irem
    //   1331: invokestatic abs : (I)I
    //   1334: invokevirtual charAt : (I)C
    //   1337: invokevirtual append : (C)Ljava/lang/StringBuilder;
    //   1340: pop
    //   1341: goto -> 1348
    //   1344: invokestatic a : (Ljava/lang/Throwable;)Ljava/lang/Throwable;
    //   1347: athrow
    //   1348: iinc #4, 1
    //   1351: iload_2
    //   1352: ifne -> 15
    //   1355: aload_3
    //   1356: invokevirtual toString : ()Ljava/lang/String;
    //   1359: putstatic burp/Zejg.ZP : Ljava/lang/String;
    //   1362: getstatic burp/Zoa.ZI : Ljava/lang/Object;
    //   1365: checkcast java/math/BigInteger
    //   1368: invokevirtual toByteArray : ()[B
    //   1371: astore #4
    //   1373: iconst_0
    //   1374: istore #6
    //   1376: iconst_0
    //   1377: istore #7
    //   1379: iload #7
    //   1381: aload #4
    //   1383: arraylength
    //   1384: if_icmpge -> 1530
    //   1387: aload #4
    //   1389: iload #7
    //   1391: baload
    //   1392: istore #8
    //   1394: iload #8
    //   1396: bipush #48
    //   1398: if_icmplt -> 1415
    //   1401: iload #8
    //   1403: bipush #57
    //   1405: if_icmple -> 1513
    //   1408: goto -> 1415
    //   1411: invokestatic a : (Ljava/lang/Throwable;)Ljava/lang/Throwable;
    //   1414: athrow
    //   1415: iload #8
    //   1417: bipush #65
    //   1419: if_icmplt -> 1443
    //   1422: goto -> 1429
    //   1425: invokestatic a : (Ljava/lang/Throwable;)Ljava/lang/Throwable;
    //   1428: athrow
    //   1429: iload #8
    //   1431: bipush #90
    //   1433: if_icmple -> 1513
    //   1436: goto -> 1443
    //   1439: invokestatic a : (Ljava/lang/Throwable;)Ljava/lang/Throwable;
    //   1442: athrow
    //   1443: iload #8
    //   1445: bipush #97
    //   1447: if_icmplt -> 1471
    //   1450: goto -> 1457
    //   1453: invokestatic a : (Ljava/lang/Throwable;)Ljava/lang/Throwable;
    //   1456: athrow
    //   1457: iload #8
    //   1459: bipush #122
    //   1461: if_icmple -> 1513
    //   1464: goto -> 1471
    //   1467: invokestatic a : (Ljava/lang/Throwable;)Ljava/lang/Throwable;
    //   1470: athrow
    //   1471: iload #8
    //   1473: bipush #43
    //   1475: if_icmpeq -> 1513
    //   1478: goto -> 1485
    //   1481: invokestatic a : (Ljava/lang/Throwable;)Ljava/lang/Throwable;
    //   1484: athrow
    //   1485: iload #8
    //   1487: bipush #47
    //   1489: if_icmpeq -> 1513
    //   1492: goto -> 1499
    //   1495: invokestatic a : (Ljava/lang/Throwable;)Ljava/lang/Throwable;
    //   1498: athrow
    //   1499: iload #8
    //   1501: bipush #61
    //   1503: if_icmpne -> 1523
    //   1506: goto -> 1513
    //   1509: invokestatic a : (Ljava/lang/Throwable;)Ljava/lang/Throwable;
    //   1512: athrow
    //   1513: iinc #6, 1
    //   1516: goto -> 1523
    //   1519: invokestatic a : (Ljava/lang/Throwable;)Ljava/lang/Throwable;
    //   1522: athrow
    //   1523: iinc #7, 1
    //   1526: iload_2
    //   1527: ifne -> 1379
    //   1530: iload #6
    //   1532: newarray byte
    //   1534: astore #7
    //   1536: iconst_0
    //   1537: istore #8
    //   1539: iconst_0
    //   1540: istore #9
    //   1542: iload #9
    //   1544: aload #4
    //   1546: arraylength
    //   1547: if_icmpge -> 1700
    //   1550: aload #4
    //   1552: iload #9
    //   1554: baload
    //   1555: istore #10
    //   1557: iload #10
    //   1559: bipush #48
    //   1561: if_icmplt -> 1578
    //   1564: iload #10
    //   1566: bipush #57
    //   1568: if_icmple -> 1676
    //   1571: goto -> 1578
    //   1574: invokestatic a : (Ljava/lang/Throwable;)Ljava/lang/Throwable;
    //   1577: athrow
    //   1578: iload #10
    //   1580: bipush #65
    //   1582: if_icmplt -> 1606
    //   1585: goto -> 1592
    //   1588: invokestatic a : (Ljava/lang/Throwable;)Ljava/lang/Throwable;
    //   1591: athrow
    //   1592: iload #10
    //   1594: bipush #90
    //   1596: if_icmple -> 1676
    //   1599: goto -> 1606
    //   1602: invokestatic a : (Ljava/lang/Throwable;)Ljava/lang/Throwable;
    //   1605: athrow
    //   1606: iload #10
    //   1608: bipush #97
    //   1610: if_icmplt -> 1634
    //   1613: goto -> 1620
    //   1616: invokestatic a : (Ljava/lang/Throwable;)Ljava/lang/Throwable;
    //   1619: athrow
    //   1620: iload #10
    //   1622: bipush #122
    //   1624: if_icmple -> 1676
    //   1627: goto -> 1634
    //   1630: invokestatic a : (Ljava/lang/Throwable;)Ljava/lang/Throwable;
    //   1633: athrow
    //   1634: iload #10
    //   1636: bipush #43
    //   1638: if_icmpeq -> 1676
    //   1641: goto -> 1648
    //   1644: invokestatic a : (Ljava/lang/Throwable;)Ljava/lang/Throwable;
    //   1647: athrow
    //   1648: iload #10
    //   1650: bipush #47
    //   1652: if_icmpeq -> 1676
    //   1655: goto -> 1662
    //   1658: invokestatic a : (Ljava/lang/Throwable;)Ljava/lang/Throwable;
    //   1661: athrow
    //   1662: iload #10
    //   1664: bipush #61
    //   1666: if_icmpne -> 1693
    //   1669: goto -> 1676
    //   1672: invokestatic a : (Ljava/lang/Throwable;)Ljava/lang/Throwable;
    //   1675: athrow
    //   1676: aload #7
    //   1678: iload #8
    //   1680: iload #10
    //   1682: bastore
    //   1683: iinc #8, 1
    //   1686: goto -> 1693
    //   1689: invokestatic a : (Ljava/lang/Throwable;)Ljava/lang/Throwable;
    //   1692: athrow
    //   1693: iinc #9, 1
    //   1696: iload_2
    //   1697: ifne -> 1542
    //   1700: aload #7
    //   1702: astore #5
    //   1704: aload #5
    //   1706: astore #4
    //   1708: aload #4
    //   1710: arraylength
    //   1711: istore #6
    //   1713: aload #4
    //   1715: iload #6
    //   1717: iconst_1
    //   1718: isub
    //   1719: baload
    //   1720: bipush #61
    //   1722: if_icmpne -> 1732
    //   1725: iinc #6, -1
    //   1728: iload_2
    //   1729: ifne -> 1713
    //   1732: iload #6
    //   1734: aload #4
    //   1736: arraylength
    //   1737: iconst_4
    //   1738: idiv
    //   1739: isub
    //   1740: newarray byte
    //   1742: astore #7
    //   1744: iconst_0
    //   1745: istore #8
    //   1747: iload #8
    //   1749: aload #4
    //   1751: arraylength
    //   1752: if_icmpge -> 2032
    //   1755: aload #4
    //   1757: iload #8
    //   1759: baload
    //   1760: bipush #61
    //   1762: if_icmpne -> 1782
    //   1765: aload #4
    //   1767: iload #8
    //   1769: iconst_0
    //   1770: bastore
    //   1771: iload_2
    //   1772: ifne -> 2025
    //   1775: goto -> 1782
    //   1778: invokestatic a : (Ljava/lang/Throwable;)Ljava/lang/Throwable;
    //   1781: athrow
    //   1782: aload #4
    //   1784: iload #8
    //   1786: baload
    //   1787: bipush #47
    //   1789: if_icmpne -> 1817
    //   1792: goto -> 1799
    //   1795: invokestatic a : (Ljava/lang/Throwable;)Ljava/lang/Throwable;
    //   1798: athrow
    //   1799: aload #4
    //   1801: iload #8
    //   1803: bipush #63
    //   1805: bastore
    //   1806: iload_2
    //   1807: ifne -> 2025
    //   1810: goto -> 1817
    //   1813: invokestatic a : (Ljava/lang/Throwable;)Ljava/lang/Throwable;
    //   1816: athrow
    //   1817: aload #4
    //   1819: iload #8
    //   1821: baload
    //   1822: bipush #43
    //   1824: if_icmpne -> 1852
    //   1827: goto -> 1834
    //   1830: invokestatic a : (Ljava/lang/Throwable;)Ljava/lang/Throwable;
    //   1833: athrow
    //   1834: aload #4
    //   1836: iload #8
    //   1838: bipush #62
    //   1840: bastore
    //   1841: iload_2
    //   1842: ifne -> 2025
    //   1845: goto -> 1852
    //   1848: invokestatic a : (Ljava/lang/Throwable;)Ljava/lang/Throwable;
    //   1851: athrow
    //   1852: aload #4
    //   1854: iload #8
    //   1856: baload
    //   1857: bipush #48
    //   1859: if_icmplt -> 1911
    //   1862: goto -> 1869
    //   1865: invokestatic a : (Ljava/lang/Throwable;)Ljava/lang/Throwable;
    //   1868: athrow
    //   1869: aload #4
    //   1871: iload #8
    //   1873: baload
    //   1874: bipush #57
    //   1876: if_icmpgt -> 1911
    //   1879: goto -> 1886
    //   1882: invokestatic a : (Ljava/lang/Throwable;)Ljava/lang/Throwable;
    //   1885: athrow
    //   1886: aload #4
    //   1888: iload #8
    //   1890: aload #4
    //   1892: iload #8
    //   1894: baload
    //   1895: bipush #-4
    //   1897: isub
    //   1898: i2b
    //   1899: bastore
    //   1900: iload_2
    //   1901: ifne -> 2025
    //   1904: goto -> 1911
    //   1907: invokestatic a : (Ljava/lang/Throwable;)Ljava/lang/Throwable;
    //   1910: athrow
    //   1911: aload #4
    //   1913: iload #8
    //   1915: baload
    //   1916: bipush #97
    //   1918: if_icmplt -> 1970
    //   1921: goto -> 1928
    //   1924: invokestatic a : (Ljava/lang/Throwable;)Ljava/lang/Throwable;
    //   1927: athrow
    //   1928: aload #4
    //   1930: iload #8
    //   1932: baload
    //   1933: bipush #122
    //   1935: if_icmpgt -> 1970
    //   1938: goto -> 1945
    //   1941: invokestatic a : (Ljava/lang/Throwable;)Ljava/lang/Throwable;
    //   1944: athrow
    //   1945: aload #4
    //   1947: iload #8
    //   1949: aload #4
    //   1951: iload #8
    //   1953: baload
    //   1954: bipush #71
    //   1956: isub
    //   1957: i2b
    //   1958: bastore
    //   1959: iload_2
    //   1960: ifne -> 2025
    //   1963: goto -> 1970
    //   1966: invokestatic a : (Ljava/lang/Throwable;)Ljava/lang/Throwable;
    //   1969: athrow
    //   1970: aload #4
    //   1972: iload #8
    //   1974: baload
    //   1975: bipush #65
    //   1977: if_icmplt -> 2025
    //   1980: goto -> 1987
    //   1983: invokestatic a : (Ljava/lang/Throwable;)Ljava/lang/Throwable;
    //   1986: athrow
    //   1987: aload #4
    //   1989: iload #8
    //   1991: baload
    //   1992: bipush #90
    //   1994: if_icmpgt -> 2025
    //   1997: goto -> 2004
    //   2000: invokestatic a : (Ljava/lang/Throwable;)Ljava/lang/Throwable;
    //   2003: athrow
    //   2004: aload #4
    //   2006: iload #8
    //   2008: aload #4
    //   2010: iload #8
    //   2012: baload
    //   2013: bipush #65
    //   2015: isub
    //   2016: i2b
    //   2017: bastore
    //   2018: goto -> 2025
    //   2021: invokestatic a : (Ljava/lang/Throwable;)Ljava/lang/Throwable;
    //   2024: athrow
    //   2025: iinc #8, 1
    //   2028: iload_2
    //   2029: ifne -> 1747
    //   2032: iconst_0
    //   2033: istore #8
    //   2035: iconst_0
    //   2036: istore #9
    //   2038: iload #9
    //   2040: aload #7
    //   2042: arraylength
    //   2043: iconst_2
    //   2044: isub
    //   2045: if_icmpge -> 2154
    //   2048: aload #7
    //   2050: iload #9
    //   2052: aload #4
    //   2054: iload #8
    //   2056: baload
    //   2057: iconst_2
    //   2058: ishl
    //   2059: sipush #255
    //   2062: iand
    //   2063: aload #4
    //   2065: iload #8
    //   2067: iconst_1
    //   2068: iadd
    //   2069: baload
    //   2070: iconst_4
    //   2071: iushr
    //   2072: iconst_3
    //   2073: iand
    //   2074: ior
    //   2075: i2b
    //   2076: bastore
    //   2077: aload #7
    //   2079: iload #9
    //   2081: iconst_1
    //   2082: iadd
    //   2083: aload #4
    //   2085: iload #8
    //   2087: iconst_1
    //   2088: iadd
    //   2089: baload
    //   2090: iconst_4
    //   2091: ishl
    //   2092: sipush #255
    //   2095: iand
    //   2096: aload #4
    //   2098: iload #8
    //   2100: iconst_2
    //   2101: iadd
    //   2102: baload
    //   2103: iconst_2
    //   2104: iushr
    //   2105: bipush #15
    //   2107: iand
    //   2108: ior
    //   2109: i2b
    //   2110: bastore
    //   2111: aload #7
    //   2113: iload #9
    //   2115: iconst_2
    //   2116: iadd
    //   2117: aload #4
    //   2119: iload #8
    //   2121: iconst_2
    //   2122: iadd
    //   2123: baload
    //   2124: bipush #6
    //   2126: ishl
    //   2127: sipush #255
    //   2130: iand
    //   2131: aload #4
    //   2133: iload #8
    //   2135: iconst_3
    //   2136: iadd
    //   2137: baload
    //   2138: bipush #63
    //   2140: iand
    //   2141: ior
    //   2142: i2b
    //   2143: bastore
    //   2144: iinc #8, 4
    //   2147: iinc #9, 3
    //   2150: iload_2
    //   2151: ifne -> 2038
    //   2154: iload #9
    //   2156: aload #7
    //   2158: arraylength
    //   2159: if_icmpge -> 2198
    //   2162: aload #7
    //   2164: iload #9
    //   2166: aload #4
    //   2168: iload #8
    //   2170: baload
    //   2171: iconst_2
    //   2172: ishl
    //   2173: sipush #255
    //   2176: iand
    //   2177: aload #4
    //   2179: iload #8
    //   2181: iconst_1
    //   2182: iadd
    //   2183: baload
    //   2184: iconst_4
    //   2185: iushr
    //   2186: iconst_3
    //   2187: iand
    //   2188: ior
    //   2189: i2b
    //   2190: bastore
    //   2191: goto -> 2198
    //   2194: invokestatic a : (Ljava/lang/Throwable;)Ljava/lang/Throwable;
    //   2197: athrow
    //   2198: iinc #9, 1
    //   2201: iload #9
    //   2203: aload #7
    //   2205: arraylength
    //   2206: if_icmpge -> 2248
    //   2209: aload #7
    //   2211: iload #9
    //   2213: aload #4
    //   2215: iload #8
    //   2217: iconst_1
    //   2218: iadd
    //   2219: baload
    //   2220: iconst_4
    //   2221: ishl
    //   2222: sipush #255
    //   2225: iand
    //   2226: aload #4
    //   2228: iload #8
    //   2230: iconst_2
    //   2231: iadd
    //   2232: baload
    //   2233: iconst_2
    //   2234: iushr
    //   2235: bipush #15
    //   2237: iand
    //   2238: ior
    //   2239: i2b
    //   2240: bastore
    //   2241: goto -> 2248
    //   2244: invokestatic a : (Ljava/lang/Throwable;)Ljava/lang/Throwable;
    //   2247: athrow
    //   2248: aload #7
    //   2250: astore #5
    //   2252: sipush #-15568
    //   2255: new java/math/BigInteger
    //   2258: dup
    //   2259: aload #5
    //   2261: invokespecial <init> : ([B)V
    //   2264: invokevirtual abs : ()Ljava/math/BigInteger;
    //   2267: putstatic burp/Ztd6.ZI : Ljava/lang/Object;
    //   2270: sipush #3265
    //   2273: invokestatic a : (II)Ljava/lang/String;
    //   2276: iconst_1
    //   2277: ldc burp/Zl1q
    //   2279: invokevirtual getClassLoader : ()Ljava/lang/ClassLoader;
    //   2282: invokestatic forName : (Ljava/lang/String;ZLjava/lang/ClassLoader;)Ljava/lang/Class;
    //   2285: invokevirtual getDeclaredFields : ()[Ljava/lang/reflect/Field;
    //   2288: astore #4
    //   2290: aload #4
    //   2292: arraylength
    //   2293: istore #5
    //   2295: iconst_0
    //   2296: istore #6
    //   2298: iload #6
    //   2300: iload #5
    //   2302: if_icmpge -> 2440
    //   2305: aload #4
    //   2307: iload #6
    //   2309: aaload
    //   2310: astore #7
    //   2312: aload #7
    //   2314: invokevirtual getModifiers : ()I
    //   2317: invokestatic isStatic : (I)Z
    //   2320: ifne -> 2330
    //   2323: goto -> 2433
    //   2326: invokestatic a : (Ljava/lang/Throwable;)Ljava/lang/Throwable;
    //   2329: athrow
    //   2330: aload #7
    //   2332: invokevirtual getType : ()Ljava/lang/Class;
    //   2335: astore #8
    //   2337: aload #8
    //   2339: ifnull -> 2420
    //   2342: aload #8
    //   2344: invokevirtual isPrimitive : ()Z
    //   2347: ifne -> 2420
    //   2350: goto -> 2357
    //   2353: invokestatic a : (Ljava/lang/Throwable;)Ljava/lang/Throwable;
    //   2356: athrow
    //   2357: aload #8
    //   2359: invokevirtual getPackage : ()Ljava/lang/Package;
    //   2362: ifnull -> 2420
    //   2365: goto -> 2372
    //   2368: invokestatic a : (Ljava/lang/Throwable;)Ljava/lang/Throwable;
    //   2371: athrow
    //   2372: aload #8
    //   2374: invokevirtual getPackage : ()Ljava/lang/Package;
    //   2377: invokevirtual getName : ()Ljava/lang/String;
    //   2380: ifnull -> 2420
    //   2383: goto -> 2390
    //   2386: invokestatic a : (Ljava/lang/Throwable;)Ljava/lang/Throwable;
    //   2389: athrow
    //   2390: aload #8
    //   2392: invokevirtual getPackage : ()Ljava/lang/Package;
    //   2395: invokevirtual getName : ()Ljava/lang/String;
    //   2398: sipush #-15563
    //   2401: sipush #-29272
    //   2404: invokestatic a : (II)Ljava/lang/String;
    //   2407: invokevirtual startsWith : (Ljava/lang/String;)Z
    //   2410: ifne -> 2420
    //   2413: goto -> 2420
    //   2416: invokestatic a : (Ljava/lang/Throwable;)Ljava/lang/Throwable;
    //   2419: athrow
    //   2420: aload #7
    //   2422: iconst_1
    //   2423: invokevirtual setAccessible : (Z)V
    //   2426: aload #7
    //   2428: aconst_null
    //   2429: invokevirtual get : (Ljava/lang/Object;)Ljava/lang/Object;
    //   2432: pop
    //   2433: iinc #6, 1
    //   2436: iload_2
    //   2437: ifne -> 2298
    //   2440: sipush #-15567
    //   2443: sipush #11147
    //   2446: invokestatic a : (II)Ljava/lang/String;
    //   2449: invokestatic forName : (Ljava/lang/String;)Ljava/lang/Class;
    //   2452: invokevirtual getDeclaredMethods : ()[Ljava/lang/reflect/Method;
    //   2455: astore #4
    //   2457: aload #4
    //   2459: arraylength
    //   2460: istore #5
    //   2462: iconst_0
    //   2463: istore #6
    //   2465: iload #6
    //   2467: iload #5
    //   2469: if_icmpge -> 2602
    //   2472: aload #4
    //   2474: iload #6
    //   2476: aaload
    //   2477: astore #7
    //   2479: aload #7
    //   2481: invokevirtual getParameterTypes : ()[Ljava/lang/Class;
    //   2484: pop
    //   2485: aload #7
    //   2487: invokevirtual getModifiers : ()I
    //   2490: invokestatic isStatic : (I)Z
    //   2493: ifeq -> 2588
    //   2496: aload #7
    //   2498: invokevirtual getParameterTypes : ()[Ljava/lang/Class;
    //   2501: arraylength
    //   2502: iconst_2
    //   2503: if_icmpne -> 2588
    //   2506: goto -> 2513
    //   2509: invokestatic a : (Ljava/lang/Throwable;)Ljava/lang/Throwable;
    //   2512: athrow
    //   2513: aload #7
    //   2515: invokevirtual getReturnType : ()Ljava/lang/Class;
    //   2518: getstatic java/lang/Void.TYPE : Ljava/lang/Class;
    //   2521: invokevirtual equals : (Ljava/lang/Object;)Z
    //   2524: ifeq -> 2588
    //   2527: goto -> 2534
    //   2530: invokestatic a : (Ljava/lang/Throwable;)Ljava/lang/Throwable;
    //   2533: athrow
    //   2534: aload #7
    //   2536: iconst_1
    //   2537: invokevirtual setAccessible : (Z)V
    //   2540: aload #7
    //   2542: aconst_null
    //   2543: iconst_2
    //   2544: anewarray java/lang/Object
    //   2547: dup
    //   2548: iconst_0
    //   2549: aload_0
    //   2550: aastore
    //   2551: dup
    //   2552: iconst_1
    //   2553: aload_1
    //   2554: ifnonnull -> 2572
    //   2557: goto -> 2564
    //   2560: invokestatic a : (Ljava/lang/Throwable;)Ljava/lang/Throwable;
    //   2563: athrow
    //   2564: aload_1
    //   2565: goto -> 2579
    //   2568: invokestatic a : (Ljava/lang/Throwable;)Ljava/lang/Throwable;
    //   2571: athrow
    //   2572: aload_1
    //   2573: checkcast [B
    //   2576: invokevirtual clone : ()Ljava/lang/Object;
    //   2579: aastore
    //   2580: invokevirtual invoke : (Ljava/lang/Object;[Ljava/lang/Object;)Ljava/lang/Object;
    //   2583: pop
    //   2584: iload_2
    //   2585: ifne -> 2602
    //   2588: iinc #6, 1
    //   2591: iload_2
    //   2592: ifne -> 2465
    //   2595: goto -> 2602
    //   2598: invokestatic a : (Ljava/lang/Throwable;)Ljava/lang/Throwable;
    //   2601: athrow
    //   2602: getstatic burp/Zgd7.ZZ : Ljava/lang/Object;
    //   2605: checkcast java/math/BigInteger
    //   2608: invokevirtual toByteArray : ()[B
    //   2611: astore #4
    //   2613: bipush #32
    //   2615: newarray int
    //   2617: dup
    //   2618: iconst_0
    //   2619: ldc 943331329
    //   2621: iastore
    //   2622: dup
    //   2623: iconst_1
    //   2624: ldc 170788368
    //   2626: iastore
    //   2627: dup
    //   2628: iconst_2
    //   2629: ldc 1008414755
    //   2631: iastore
    //   2632: dup
    //   2633: iconst_3
    //   2634: ldc 187049985
    //   2636: iastore
    //   2637: dup
    //   2638: iconst_4
    //   2639: ldc 1010368540
    //   2641: iastore
    //   2642: dup
    //   2643: iconst_5
    //   2644: ldc 220604441
    //   2646: iastore
    //   2647: dup
    //   2648: bipush #6
    //   2650: ldc 940377620
    //   2652: iastore
    //   2653: dup
    //   2654: bipush #7
    //   2656: ldc 255209728
    //   2658: iastore
    //   2659: dup
    //   2660: bipush #8
    //   2662: ldc 689771012
    //   2664: iastore
    //   2665: dup
    //   2666: bipush #9
    //   2668: ldc 221709344
    //   2670: iastore
    //   2671: dup
    //   2672: bipush #10
    //   2674: ldc 957157408
    //   2676: iastore
    //   2677: dup
    //   2678: bipush #11
    //   2680: ldc 892536332
    //   2682: iastore
    //   2683: dup
    //   2684: bipush #12
    //   2686: ldc 722417666
    //   2688: iastore
    //   2689: dup
    //   2690: bipush #13
    //   2692: ldc 1026621720
    //   2694: iastore
    //   2695: dup
    //   2696: bipush #14
    //   2698: ldc 655302664
    //   2700: iastore
    //   2701: dup
    //   2702: bipush #15
    //   2704: ldc 890966315
    //   2706: iastore
    //   2707: dup
    //   2708: bipush #16
    //   2710: ldc 187632156
    //   2712: iastore
    //   2713: dup
    //   2714: bipush #17
    //   2716: ldc 874189824
    //   2718: iastore
    //   2719: dup
    //   2720: bipush #18
    //   2722: ldc 254150144
    //   2724: iastore
    //   2725: dup
    //   2726: bipush #19
    //   2728: ldc 924386310
    //   2730: iastore
    //   2731: dup
    //   2732: bipush #20
    //   2734: ldc 121057538
    //   2736: iastore
    //   2737: dup
    //   2738: bipush #21
    //   2740: ldc 840500228
    //   2742: iastore
    //   2743: dup
    //   2744: bipush #22
    //   2746: ldc 389160971
    //   2748: iastore
    //   2749: dup
    //   2750: bipush #23
    //   2752: ldc 907870729
    //   2754: iastore
    //   2755: dup
    //   2756: bipush #24
    //   2758: ldc 389426184
    //   2760: iastore
    //   2761: dup
    //   2762: bipush #25
    //   2764: ldc 973875457
    //   2766: iastore
    //   2767: dup
    //   2768: bipush #26
    //   2770: ldc 372376604
    //   2772: iastore
    //   2773: dup
    //   2774: bipush #27
    //   2776: ldc 707731490
    //   2778: iastore
    //   2779: dup
    //   2780: bipush #28
    //   2782: ldc 1043334948
    //   2784: iastore
    //   2785: dup
    //   2786: bipush #29
    //   2788: ldc 439222784
    //   2790: iastore
    //   2791: dup
    //   2792: bipush #30
    //   2794: ldc 876216579
    //   2796: iastore
    //   2797: dup
    //   2798: bipush #31
    //   2800: ldc 455999525
    //   2802: iastore
    //   2803: astore #6
    //   2805: bipush #8
    //   2807: aload #4
    //   2809: arraylength
    //   2810: bipush #8
    //   2812: irem
    //   2813: isub
    //   2814: istore #7
    //   2816: aload #4
    //   2818: arraylength
    //   2819: iload #7
    //   2821: iadd
    //   2822: newarray byte
    //   2824: astore #8
    //   2826: iconst_0
    //   2827: istore #9
    //   2829: iload #9
    //   2831: aload #4
    //   2833: arraylength
    //   2834: if_icmpge -> 2854
    //   2837: aload #8
    //   2839: iload #9
    //   2841: aload #4
    //   2843: iload #9
    //   2845: baload
    //   2846: bastore
    //   2847: iinc #9, 1
    //   2850: iload_2
    //   2851: ifne -> 2829
    //   2854: aload #4
    //   2856: arraylength
    //   2857: istore #9
    //   2859: iload #9
    //   2861: aload #8
    //   2863: arraylength
    //   2864: if_icmpge -> 2882
    //   2867: aload #8
    //   2869: iload #9
    //   2871: iload #7
    //   2873: i2b
    //   2874: bastore
    //   2875: iinc #9, 1
    //   2878: iload_2
    //   2879: ifne -> 2859
    //   2882: aload #8
    //   2884: astore #4
    //   2886: bipush #64
    //   2888: newarray int
    //   2890: dup
    //   2891: iconst_0
    //   2892: ldc 16843776
    //   2894: iastore
    //   2895: dup
    //   2896: iconst_1
    //   2897: iconst_0
    //   2898: iastore
    //   2899: dup
    //   2900: iconst_2
    //   2901: ldc 65536
    //   2903: iastore
    //   2904: dup
    //   2905: iconst_3
    //   2906: ldc 16843780
    //   2908: iastore
    //   2909: dup
    //   2910: iconst_4
    //   2911: ldc 16842756
    //   2913: iastore
    //   2914: dup
    //   2915: iconst_5
    //   2916: ldc 66564
    //   2918: iastore
    //   2919: dup
    //   2920: bipush #6
    //   2922: iconst_4
    //   2923: iastore
    //   2924: dup
    //   2925: bipush #7
    //   2927: ldc 65536
    //   2929: iastore
    //   2930: dup
    //   2931: bipush #8
    //   2933: sipush #1024
    //   2936: iastore
    //   2937: dup
    //   2938: bipush #9
    //   2940: ldc 16843776
    //   2942: iastore
    //   2943: dup
    //   2944: bipush #10
    //   2946: ldc 16843780
    //   2948: iastore
    //   2949: dup
    //   2950: bipush #11
    //   2952: sipush #1024
    //   2955: iastore
    //   2956: dup
    //   2957: bipush #12
    //   2959: ldc 16778244
    //   2961: iastore
    //   2962: dup
    //   2963: bipush #13
    //   2965: ldc 16842756
    //   2967: iastore
    //   2968: dup
    //   2969: bipush #14
    //   2971: ldc 16777216
    //   2973: iastore
    //   2974: dup
    //   2975: bipush #15
    //   2977: iconst_4
    //   2978: iastore
    //   2979: dup
    //   2980: bipush #16
    //   2982: sipush #1028
    //   2985: iastore
    //   2986: dup
    //   2987: bipush #17
    //   2989: ldc 16778240
    //   2991: iastore
    //   2992: dup
    //   2993: bipush #18
    //   2995: ldc 16778240
    //   2997: iastore
    //   2998: dup
    //   2999: bipush #19
    //   3001: ldc 66560
    //   3003: iastore
    //   3004: dup
    //   3005: bipush #20
    //   3007: ldc 66560
    //   3009: iastore
    //   3010: dup
    //   3011: bipush #21
    //   3013: ldc 16842752
    //   3015: iastore
    //   3016: dup
    //   3017: bipush #22
    //   3019: ldc 16842752
    //   3021: iastore
    //   3022: dup
    //   3023: bipush #23
    //   3025: ldc 16778244
    //   3027: iastore
    //   3028: dup
    //   3029: bipush #24
    //   3031: ldc 65540
    //   3033: iastore
    //   3034: dup
    //   3035: bipush #25
    //   3037: ldc 16777220
    //   3039: iastore
    //   3040: dup
    //   3041: bipush #26
    //   3043: ldc 16777220
    //   3045: iastore
    //   3046: dup
    //   3047: bipush #27
    //   3049: ldc 65540
    //   3051: iastore
    //   3052: dup
    //   3053: bipush #28
    //   3055: iconst_0
    //   3056: iastore
    //   3057: dup
    //   3058: bipush #29
    //   3060: sipush #1028
    //   3063: iastore
    //   3064: dup
    //   3065: bipush #30
    //   3067: ldc 66564
    //   3069: iastore
    //   3070: dup
    //   3071: bipush #31
    //   3073: ldc 16777216
    //   3075: iastore
    //   3076: dup
    //   3077: bipush #32
    //   3079: ldc 65536
    //   3081: iastore
    //   3082: dup
    //   3083: bipush #33
    //   3085: ldc 16843780
    //   3087: iastore
    //   3088: dup
    //   3089: bipush #34
    //   3091: iconst_4
    //   3092: iastore
    //   3093: dup
    //   3094: bipush #35
    //   3096: ldc 16842752
    //   3098: iastore
    //   3099: dup
    //   3100: bipush #36
    //   3102: ldc 16843776
    //   3104: iastore
    //   3105: dup
    //   3106: bipush #37
    //   3108: ldc 16777216
    //   3110: iastore
    //   3111: dup
    //   3112: bipush #38
    //   3114: ldc 16777216
    //   3116: iastore
    //   3117: dup
    //   3118: bipush #39
    //   3120: sipush #1024
    //   3123: iastore
    //   3124: dup
    //   3125: bipush #40
    //   3127: ldc 16842756
    //   3129: iastore
    //   3130: dup
    //   3131: bipush #41
    //   3133: ldc 65536
    //   3135: iastore
    //   3136: dup
    //   3137: bipush #42
    //   3139: ldc 66560
    //   3141: iastore
    //   3142: dup
    //   3143: bipush #43
    //   3145: ldc 16777220
    //   3147: iastore
    //   3148: dup
    //   3149: bipush #44
    //   3151: sipush #1024
    //   3154: iastore
    //   3155: dup
    //   3156: bipush #45
    //   3158: iconst_4
    //   3159: iastore
    //   3160: dup
    //   3161: bipush #46
    //   3163: ldc 16778244
    //   3165: iastore
    //   3166: dup
    //   3167: bipush #47
    //   3169: ldc 66564
    //   3171: iastore
    //   3172: dup
    //   3173: bipush #48
    //   3175: ldc 16843780
    //   3177: iastore
    //   3178: dup
    //   3179: bipush #49
    //   3181: ldc 65540
    //   3183: iastore
    //   3184: dup
    //   3185: bipush #50
    //   3187: ldc 16842752
    //   3189: iastore
    //   3190: dup
    //   3191: bipush #51
    //   3193: ldc 16778244
    //   3195: iastore
    //   3196: dup
    //   3197: bipush #52
    //   3199: ldc 16777220
    //   3201: iastore
    //   3202: dup
    //   3203: bipush #53
    //   3205: sipush #1028
    //   3208: iastore
    //   3209: dup
    //   3210: bipush #54
    //   3212: ldc 66564
    //   3214: iastore
    //   3215: dup
    //   3216: bipush #55
    //   3218: ldc 16843776
    //   3220: iastore
    //   3221: dup
    //   3222: bipush #56
    //   3224: sipush #1028
    //   3227: iastore
    //   3228: dup
    //   3229: bipush #57
    //   3231: ldc 16778240
    //   3233: iastore
    //   3234: dup
    //   3235: bipush #58
    //   3237: ldc 16778240
    //   3239: iastore
    //   3240: dup
    //   3241: bipush #59
    //   3243: iconst_0
    //   3244: iastore
    //   3245: dup
    //   3246: bipush #60
    //   3248: ldc 65540
    //   3250: iastore
    //   3251: dup
    //   3252: bipush #61
    //   3254: ldc 66560
    //   3256: iastore
    //   3257: dup
    //   3258: bipush #62
    //   3260: iconst_0
    //   3261: iastore
    //   3262: dup
    //   3263: bipush #63
    //   3265: ldc 16842756
    //   3267: iastore
    //   3268: astore #9
    //   3270: bipush #64
    //   3272: newarray int
    //   3274: dup
    //   3275: iconst_0
    //   3276: ldc -2146402272
    //   3278: iastore
    //   3279: dup
    //   3280: iconst_1
    //   3281: ldc -2147450880
    //   3283: iastore
    //   3284: dup
    //   3285: iconst_2
    //   3286: ldc 32768
    //   3288: iastore
    //   3289: dup
    //   3290: iconst_3
    //   3291: ldc 1081376
    //   3293: iastore
    //   3294: dup
    //   3295: iconst_4
    //   3296: ldc 1048576
    //   3298: iastore
    //   3299: dup
    //   3300: iconst_5
    //   3301: bipush #32
    //   3303: iastore
    //   3304: dup
    //   3305: bipush #6
    //   3307: ldc -2146435040
    //   3309: iastore
    //   3310: dup
    //   3311: bipush #7
    //   3313: ldc -2147450848
    //   3315: iastore
    //   3316: dup
    //   3317: bipush #8
    //   3319: ldc -2147483616
    //   3321: iastore
    //   3322: dup
    //   3323: bipush #9
    //   3325: ldc -2146402272
    //   3327: iastore
    //   3328: dup
    //   3329: bipush #10
    //   3331: ldc -2146402304
    //   3333: iastore
    //   3334: dup
    //   3335: bipush #11
    //   3337: ldc -2147483648
    //   3339: iastore
    //   3340: dup
    //   3341: bipush #12
    //   3343: ldc -2147450880
    //   3345: iastore
    //   3346: dup
    //   3347: bipush #13
    //   3349: ldc 1048576
    //   3351: iastore
    //   3352: dup
    //   3353: bipush #14
    //   3355: bipush #32
    //   3357: iastore
    //   3358: dup
    //   3359: bipush #15
    //   3361: ldc -2146435040
    //   3363: iastore
    //   3364: dup
    //   3365: bipush #16
    //   3367: ldc 1081344
    //   3369: iastore
    //   3370: dup
    //   3371: bipush #17
    //   3373: ldc 1048608
    //   3375: iastore
    //   3376: dup
    //   3377: bipush #18
    //   3379: ldc -2147450848
    //   3381: iastore
    //   3382: dup
    //   3383: bipush #19
    //   3385: iconst_0
    //   3386: iastore
    //   3387: dup
    //   3388: bipush #20
    //   3390: ldc -2147483648
    //   3392: iastore
    //   3393: dup
    //   3394: bipush #21
    //   3396: ldc 32768
    //   3398: iastore
    //   3399: dup
    //   3400: bipush #22
    //   3402: ldc 1081376
    //   3404: iastore
    //   3405: dup
    //   3406: bipush #23
    //   3408: ldc -2146435072
    //   3410: iastore
    //   3411: dup
    //   3412: bipush #24
    //   3414: ldc 1048608
    //   3416: iastore
    //   3417: dup
    //   3418: bipush #25
    //   3420: ldc -2147483616
    //   3422: iastore
    //   3423: dup
    //   3424: bipush #26
    //   3426: iconst_0
    //   3427: iastore
    //   3428: dup
    //   3429: bipush #27
    //   3431: ldc 1081344
    //   3433: iastore
    //   3434: dup
    //   3435: bipush #28
    //   3437: ldc 32800
    //   3439: iastore
    //   3440: dup
    //   3441: bipush #29
    //   3443: ldc -2146402304
    //   3445: iastore
    //   3446: dup
    //   3447: bipush #30
    //   3449: ldc -2146435072
    //   3451: iastore
    //   3452: dup
    //   3453: bipush #31
    //   3455: ldc 32800
    //   3457: iastore
    //   3458: dup
    //   3459: bipush #32
    //   3461: iconst_0
    //   3462: iastore
    //   3463: dup
    //   3464: bipush #33
    //   3466: ldc 1081376
    //   3468: iastore
    //   3469: dup
    //   3470: bipush #34
    //   3472: ldc -2146435040
    //   3474: iastore
    //   3475: dup
    //   3476: bipush #35
    //   3478: ldc 1048576
    //   3480: iastore
    //   3481: dup
    //   3482: bipush #36
    //   3484: ldc -2147450848
    //   3486: iastore
    //   3487: dup
    //   3488: bipush #37
    //   3490: ldc -2146435072
    //   3492: iastore
    //   3493: dup
    //   3494: bipush #38
    //   3496: ldc -2146402304
    //   3498: iastore
    //   3499: dup
    //   3500: bipush #39
    //   3502: ldc 32768
    //   3504: iastore
    //   3505: dup
    //   3506: bipush #40
    //   3508: ldc -2146435072
    //   3510: iastore
    //   3511: dup
    //   3512: bipush #41
    //   3514: ldc -2147450880
    //   3516: iastore
    //   3517: dup
    //   3518: bipush #42
    //   3520: bipush #32
    //   3522: iastore
    //   3523: dup
    //   3524: bipush #43
    //   3526: ldc -2146402272
    //   3528: iastore
    //   3529: dup
    //   3530: bipush #44
    //   3532: ldc 1081376
    //   3534: iastore
    //   3535: dup
    //   3536: bipush #45
    //   3538: bipush #32
    //   3540: iastore
    //   3541: dup
    //   3542: bipush #46
    //   3544: ldc 32768
    //   3546: iastore
    //   3547: dup
    //   3548: bipush #47
    //   3550: ldc -2147483648
    //   3552: iastore
    //   3553: dup
    //   3554: bipush #48
    //   3556: ldc 32800
    //   3558: iastore
    //   3559: dup
    //   3560: bipush #49
    //   3562: ldc -2146402304
    //   3564: iastore
    //   3565: dup
    //   3566: bipush #50
    //   3568: ldc 1048576
    //   3570: iastore
    //   3571: dup
    //   3572: bipush #51
    //   3574: ldc -2147483616
    //   3576: iastore
    //   3577: dup
    //   3578: bipush #52
    //   3580: ldc 1048608
    //   3582: iastore
    //   3583: dup
    //   3584: bipush #53
    //   3586: ldc -2147450848
    //   3588: iastore
    //   3589: dup
    //   3590: bipush #54
    //   3592: ldc -2147483616
    //   3594: iastore
    //   3595: dup
    //   3596: bipush #55
    //   3598: ldc 1048608
    //   3600: iastore
    //   3601: dup
    //   3602: bipush #56
    //   3604: ldc 1081344
    //   3606: iastore
    //   3607: dup
    //   3608: bipush #57
    //   3610: iconst_0
    //   3611: iastore
    //   3612: dup
    //   3613: bipush #58
    //   3615: ldc -2147450880
    //   3617: iastore
    //   3618: dup
    //   3619: bipush #59
    //   3621: ldc 32800
    //   3623: iastore
    //   3624: dup
    //   3625: bipush #60
    //   3627: ldc -2147483648
    //   3629: iastore
    //   3630: dup
    //   3631: bipush #61
    //   3633: ldc -2146435040
    //   3635: iastore
    //   3636: dup
    //   3637: bipush #62
    //   3639: ldc -2146402272
    //   3641: iastore
    //   3642: dup
    //   3643: bipush #63
    //   3645: ldc 1081344
    //   3647: iastore
    //   3648: astore #10
    //   3650: bipush #64
    //   3652: newarray int
    //   3654: dup
    //   3655: iconst_0
    //   3656: sipush #520
    //   3659: iastore
    //   3660: dup
    //   3661: iconst_1
    //   3662: ldc 134349312
    //   3664: iastore
    //   3665: dup
    //   3666: iconst_2
    //   3667: iconst_0
    //   3668: iastore
    //   3669: dup
    //   3670: iconst_3
    //   3671: ldc 134348808
    //   3673: iastore
    //   3674: dup
    //   3675: iconst_4
    //   3676: ldc 134218240
    //   3678: iastore
    //   3679: dup
    //   3680: iconst_5
    //   3681: iconst_0
    //   3682: iastore
    //   3683: dup
    //   3684: bipush #6
    //   3686: ldc 131592
    //   3688: iastore
    //   3689: dup
    //   3690: bipush #7
    //   3692: ldc 134218240
    //   3694: iastore
    //   3695: dup
    //   3696: bipush #8
    //   3698: ldc 131080
    //   3700: iastore
    //   3701: dup
    //   3702: bipush #9
    //   3704: ldc 134217736
    //   3706: iastore
    //   3707: dup
    //   3708: bipush #10
    //   3710: ldc 134217736
    //   3712: iastore
    //   3713: dup
    //   3714: bipush #11
    //   3716: ldc 131072
    //   3718: iastore
    //   3719: dup
    //   3720: bipush #12
    //   3722: ldc 134349320
    //   3724: iastore
    //   3725: dup
    //   3726: bipush #13
    //   3728: ldc 131080
    //   3730: iastore
    //   3731: dup
    //   3732: bipush #14
    //   3734: ldc 134348800
    //   3736: iastore
    //   3737: dup
    //   3738: bipush #15
    //   3740: sipush #520
    //   3743: iastore
    //   3744: dup
    //   3745: bipush #16
    //   3747: ldc 134217728
    //   3749: iastore
    //   3750: dup
    //   3751: bipush #17
    //   3753: bipush #8
    //   3755: iastore
    //   3756: dup
    //   3757: bipush #18
    //   3759: ldc 134349312
    //   3761: iastore
    //   3762: dup
    //   3763: bipush #19
    //   3765: sipush #512
    //   3768: iastore
    //   3769: dup
    //   3770: bipush #20
    //   3772: ldc 131584
    //   3774: iastore
    //   3775: dup
    //   3776: bipush #21
    //   3778: ldc 134348800
    //   3780: iastore
    //   3781: dup
    //   3782: bipush #22
    //   3784: ldc 134348808
    //   3786: iastore
    //   3787: dup
    //   3788: bipush #23
    //   3790: ldc 131592
    //   3792: iastore
    //   3793: dup
    //   3794: bipush #24
    //   3796: ldc 134218248
    //   3798: iastore
    //   3799: dup
    //   3800: bipush #25
    //   3802: ldc 131584
    //   3804: iastore
    //   3805: dup
    //   3806: bipush #26
    //   3808: ldc 131072
    //   3810: iastore
    //   3811: dup
    //   3812: bipush #27
    //   3814: ldc 134218248
    //   3816: iastore
    //   3817: dup
    //   3818: bipush #28
    //   3820: bipush #8
    //   3822: iastore
    //   3823: dup
    //   3824: bipush #29
    //   3826: ldc 134349320
    //   3828: iastore
    //   3829: dup
    //   3830: bipush #30
    //   3832: sipush #512
    //   3835: iastore
    //   3836: dup
    //   3837: bipush #31
    //   3839: ldc 134217728
    //   3841: iastore
    //   3842: dup
    //   3843: bipush #32
    //   3845: ldc 134349312
    //   3847: iastore
    //   3848: dup
    //   3849: bipush #33
    //   3851: ldc 134217728
    //   3853: iastore
    //   3854: dup
    //   3855: bipush #34
    //   3857: ldc 131080
    //   3859: iastore
    //   3860: dup
    //   3861: bipush #35
    //   3863: sipush #520
    //   3866: iastore
    //   3867: dup
    //   3868: bipush #36
    //   3870: ldc 131072
    //   3872: iastore
    //   3873: dup
    //   3874: bipush #37
    //   3876: ldc 134349312
    //   3878: iastore
    //   3879: dup
    //   3880: bipush #38
    //   3882: ldc 134218240
    //   3884: iastore
    //   3885: dup
    //   3886: bipush #39
    //   3888: iconst_0
    //   3889: iastore
    //   3890: dup
    //   3891: bipush #40
    //   3893: sipush #512
    //   3896: iastore
    //   3897: dup
    //   3898: bipush #41
    //   3900: ldc 131080
    //   3902: iastore
    //   3903: dup
    //   3904: bipush #42
    //   3906: ldc 134349320
    //   3908: iastore
    //   3909: dup
    //   3910: bipush #43
    //   3912: ldc 134218240
    //   3914: iastore
    //   3915: dup
    //   3916: bipush #44
    //   3918: ldc 134217736
    //   3920: iastore
    //   3921: dup
    //   3922: bipush #45
    //   3924: sipush #512
    //   3927: iastore
    //   3928: dup
    //   3929: bipush #46
    //   3931: iconst_0
    //   3932: iastore
    //   3933: dup
    //   3934: bipush #47
    //   3936: ldc 134348808
    //   3938: iastore
    //   3939: dup
    //   3940: bipush #48
    //   3942: ldc 134218248
    //   3944: iastore
    //   3945: dup
    //   3946: bipush #49
    //   3948: ldc 131072
    //   3950: iastore
    //   3951: dup
    //   3952: bipush #50
    //   3954: ldc 134217728
    //   3956: iastore
    //   3957: dup
    //   3958: bipush #51
    //   3960: ldc 134349320
    //   3962: iastore
    //   3963: dup
    //   3964: bipush #52
    //   3966: bipush #8
    //   3968: iastore
    //   3969: dup
    //   3970: bipush #53
    //   3972: ldc 131592
    //   3974: iastore
    //   3975: dup
    //   3976: bipush #54
    //   3978: ldc 131584
    //   3980: iastore
    //   3981: dup
    //   3982: bipush #55
    //   3984: ldc 134217736
    //   3986: iastore
    //   3987: dup
    //   3988: bipush #56
    //   3990: ldc 134348800
    //   3992: iastore
    //   3993: dup
    //   3994: bipush #57
    //   3996: ldc 134218248
    //   3998: iastore
    //   3999: dup
    //   4000: bipush #58
    //   4002: sipush #520
    //   4005: iastore
    //   4006: dup
    //   4007: bipush #59
    //   4009: ldc 134348800
    //   4011: iastore
    //   4012: dup
    //   4013: bipush #60
    //   4015: ldc 131592
    //   4017: iastore
    //   4018: dup
    //   4019: bipush #61
    //   4021: bipush #8
    //   4023: iastore
    //   4024: dup
    //   4025: bipush #62
    //   4027: ldc 134348808
    //   4029: iastore
    //   4030: dup
    //   4031: bipush #63
    //   4033: ldc 131584
    //   4035: iastore
    //   4036: astore #11
    //   4038: bipush #64
    //   4040: newarray int
    //   4042: dup
    //   4043: iconst_0
    //   4044: ldc 8396801
    //   4046: iastore
    //   4047: dup
    //   4048: iconst_1
    //   4049: sipush #8321
    //   4052: iastore
    //   4053: dup
    //   4054: iconst_2
    //   4055: sipush #8321
    //   4058: iastore
    //   4059: dup
    //   4060: iconst_3
    //   4061: sipush #128
    //   4064: iastore
    //   4065: dup
    //   4066: iconst_4
    //   4067: ldc 8396928
    //   4069: iastore
    //   4070: dup
    //   4071: iconst_5
    //   4072: ldc 8388737
    //   4074: iastore
    //   4075: dup
    //   4076: bipush #6
    //   4078: ldc 8388609
    //   4080: iastore
    //   4081: dup
    //   4082: bipush #7
    //   4084: sipush #8193
    //   4087: iastore
    //   4088: dup
    //   4089: bipush #8
    //   4091: iconst_0
    //   4092: iastore
    //   4093: dup
    //   4094: bipush #9
    //   4096: ldc 8396800
    //   4098: iastore
    //   4099: dup
    //   4100: bipush #10
    //   4102: ldc 8396800
    //   4104: iastore
    //   4105: dup
    //   4106: bipush #11
    //   4108: ldc 8396929
    //   4110: iastore
    //   4111: dup
    //   4112: bipush #12
    //   4114: sipush #129
    //   4117: iastore
    //   4118: dup
    //   4119: bipush #13
    //   4121: iconst_0
    //   4122: iastore
    //   4123: dup
    //   4124: bipush #14
    //   4126: ldc 8388736
    //   4128: iastore
    //   4129: dup
    //   4130: bipush #15
    //   4132: ldc 8388609
    //   4134: iastore
    //   4135: dup
    //   4136: bipush #16
    //   4138: iconst_1
    //   4139: iastore
    //   4140: dup
    //   4141: bipush #17
    //   4143: sipush #8192
    //   4146: iastore
    //   4147: dup
    //   4148: bipush #18
    //   4150: ldc 8388608
    //   4152: iastore
    //   4153: dup
    //   4154: bipush #19
    //   4156: ldc 8396801
    //   4158: iastore
    //   4159: dup
    //   4160: bipush #20
    //   4162: sipush #128
    //   4165: iastore
    //   4166: dup
    //   4167: bipush #21
    //   4169: ldc 8388608
    //   4171: iastore
    //   4172: dup
    //   4173: bipush #22
    //   4175: sipush #8193
    //   4178: iastore
    //   4179: dup
    //   4180: bipush #23
    //   4182: sipush #8320
    //   4185: iastore
    //   4186: dup
    //   4187: bipush #24
    //   4189: ldc 8388737
    //   4191: iastore
    //   4192: dup
    //   4193: bipush #25
    //   4195: iconst_1
    //   4196: iastore
    //   4197: dup
    //   4198: bipush #26
    //   4200: sipush #8320
    //   4203: iastore
    //   4204: dup
    //   4205: bipush #27
    //   4207: ldc 8388736
    //   4209: iastore
    //   4210: dup
    //   4211: bipush #28
    //   4213: sipush #8192
    //   4216: iastore
    //   4217: dup
    //   4218: bipush #29
    //   4220: ldc 8396928
    //   4222: iastore
    //   4223: dup
    //   4224: bipush #30
    //   4226: ldc 8396929
    //   4228: iastore
    //   4229: dup
    //   4230: bipush #31
    //   4232: sipush #129
    //   4235: iastore
    //   4236: dup
    //   4237: bipush #32
    //   4239: ldc 8388736
    //   4241: iastore
    //   4242: dup
    //   4243: bipush #33
    //   4245: ldc 8388609
    //   4247: iastore
    //   4248: dup
    //   4249: bipush #34
    //   4251: ldc 8396800
    //   4253: iastore
    //   4254: dup
    //   4255: bipush #35
    //   4257: ldc 8396929
    //   4259: iastore
    //   4260: dup
    //   4261: bipush #36
    //   4263: sipush #129
    //   4266: iastore
    //   4267: dup
    //   4268: bipush #37
    //   4270: iconst_0
    //   4271: iastore
    //   4272: dup
    //   4273: bipush #38
    //   4275: iconst_0
    //   4276: iastore
    //   4277: dup
    //   4278: bipush #39
    //   4280: ldc 8396800
    //   4282: iastore
    //   4283: dup
    //   4284: bipush #40
    //   4286: sipush #8320
    //   4289: iastore
    //   4290: dup
    //   4291: bipush #41
    //   4293: ldc 8388736
    //   4295: iastore
    //   4296: dup
    //   4297: bipush #42
    //   4299: ldc 8388737
    //   4301: iastore
    //   4302: dup
    //   4303: bipush #43
    //   4305: iconst_1
    //   4306: iastore
    //   4307: dup
    //   4308: bipush #44
    //   4310: ldc 8396801
    //   4312: iastore
    //   4313: dup
    //   4314: bipush #45
    //   4316: sipush #8321
    //   4319: iastore
    //   4320: dup
    //   4321: bipush #46
    //   4323: sipush #8321
    //   4326: iastore
    //   4327: dup
    //   4328: bipush #47
    //   4330: sipush #128
    //   4333: iastore
    //   4334: dup
    //   4335: bipush #48
    //   4337: ldc 8396929
    //   4339: iastore
    //   4340: dup
    //   4341: bipush #49
    //   4343: sipush #129
    //   4346: iastore
    //   4347: dup
    //   4348: bipush #50
    //   4350: iconst_1
    //   4351: iastore
    //   4352: dup
    //   4353: bipush #51
    //   4355: sipush #8192
    //   4358: iastore
    //   4359: dup
    //   4360: bipush #52
    //   4362: ldc 8388609
    //   4364: iastore
    //   4365: dup
    //   4366: bipush #53
    //   4368: sipush #8193
    //   4371: iastore
    //   4372: dup
    //   4373: bipush #54
    //   4375: ldc 8396928
    //   4377: iastore
    //   4378: dup
    //   4379: bipush #55
    //   4381: ldc 8388737
    //   4383: iastore
    //   4384: dup
    //   4385: bipush #56
    //   4387: sipush #8193
    //   4390: iastore
    //   4391: dup
    //   4392: bipush #57
    //   4394: sipush #8320
    //   4397: iastore
    //   4398: dup
    //   4399: bipush #58
    //   4401: ldc 8388608
    //   4403: iastore
    //   4404: dup
    //   4405: bipush #59
    //   4407: ldc 8396801
    //   4409: iastore
    //   4410: dup
    //   4411: bipush #60
    //   4413: sipush #128
    //   4416: iastore
    //   4417: dup
    //   4418: bipush #61
    //   4420: ldc 8388608
    //   4422: iastore
    //   4423: dup
    //   4424: bipush #62
    //   4426: sipush #8192
    //   4429: iastore
    //   4430: dup
    //   4431: bipush #63
    //   4433: ldc 8396928
    //   4435: iastore
    //   4436: astore #12
    //   4438: bipush #64
    //   4440: newarray int
    //   4442: dup
    //   4443: iconst_0
    //   4444: sipush #256
    //   4447: iastore
    //   4448: dup
    //   4449: iconst_1
    //   4450: ldc 34078976
    //   4452: iastore
    //   4453: dup
    //   4454: iconst_2
    //   4455: ldc 34078720
    //   4457: iastore
    //   4458: dup
    //   4459: iconst_3
    //   4460: ldc 1107296512
    //   4462: iastore
    //   4463: dup
    //   4464: iconst_4
    //   4465: ldc 524288
    //   4467: iastore
    //   4468: dup
    //   4469: iconst_5
    //   4470: sipush #256
    //   4473: iastore
    //   4474: dup
    //   4475: bipush #6
    //   4477: ldc 1073741824
    //   4479: iastore
    //   4480: dup
    //   4481: bipush #7
    //   4483: ldc 34078720
    //   4485: iastore
    //   4486: dup
    //   4487: bipush #8
    //   4489: ldc 1074266368
    //   4491: iastore
    //   4492: dup
    //   4493: bipush #9
    //   4495: ldc 524288
    //   4497: iastore
    //   4498: dup
    //   4499: bipush #10
    //   4501: ldc 33554688
    //   4503: iastore
    //   4504: dup
    //   4505: bipush #11
    //   4507: ldc 1074266368
    //   4509: iastore
    //   4510: dup
    //   4511: bipush #12
    //   4513: ldc 1107296512
    //   4515: iastore
    //   4516: dup
    //   4517: bipush #13
    //   4519: ldc 1107820544
    //   4521: iastore
    //   4522: dup
    //   4523: bipush #14
    //   4525: ldc 524544
    //   4527: iastore
    //   4528: dup
    //   4529: bipush #15
    //   4531: ldc 1073741824
    //   4533: iastore
    //   4534: dup
    //   4535: bipush #16
    //   4537: ldc 33554432
    //   4539: iastore
    //   4540: dup
    //   4541: bipush #17
    //   4543: ldc 1074266112
    //   4545: iastore
    //   4546: dup
    //   4547: bipush #18
    //   4549: ldc 1074266112
    //   4551: iastore
    //   4552: dup
    //   4553: bipush #19
    //   4555: iconst_0
    //   4556: iastore
    //   4557: dup
    //   4558: bipush #20
    //   4560: ldc 1073742080
    //   4562: iastore
    //   4563: dup
    //   4564: bipush #21
    //   4566: ldc 1107820800
    //   4568: iastore
    //   4569: dup
    //   4570: bipush #22
    //   4572: ldc 1107820800
    //   4574: iastore
    //   4575: dup
    //   4576: bipush #23
    //   4578: ldc 33554688
    //   4580: iastore
    //   4581: dup
    //   4582: bipush #24
    //   4584: ldc 1107820544
    //   4586: iastore
    //   4587: dup
    //   4588: bipush #25
    //   4590: ldc 1073742080
    //   4592: iastore
    //   4593: dup
    //   4594: bipush #26
    //   4596: iconst_0
    //   4597: iastore
    //   4598: dup
    //   4599: bipush #27
    //   4601: ldc 1107296256
    //   4603: iastore
    //   4604: dup
    //   4605: bipush #28
    //   4607: ldc 34078976
    //   4609: iastore
    //   4610: dup
    //   4611: bipush #29
    //   4613: ldc 33554432
    //   4615: iastore
    //   4616: dup
    //   4617: bipush #30
    //   4619: ldc 1107296256
    //   4621: iastore
    //   4622: dup
    //   4623: bipush #31
    //   4625: ldc 524544
    //   4627: iastore
    //   4628: dup
    //   4629: bipush #32
    //   4631: ldc 524288
    //   4633: iastore
    //   4634: dup
    //   4635: bipush #33
    //   4637: ldc 1107296512
    //   4639: iastore
    //   4640: dup
    //   4641: bipush #34
    //   4643: sipush #256
    //   4646: iastore
    //   4647: dup
    //   4648: bipush #35
    //   4650: ldc 33554432
    //   4652: iastore
    //   4653: dup
    //   4654: bipush #36
    //   4656: ldc 1073741824
    //   4658: iastore
    //   4659: dup
    //   4660: bipush #37
    //   4662: ldc 34078720
    //   4664: iastore
    //   4665: dup
    //   4666: bipush #38
    //   4668: ldc 1107296512
    //   4670: iastore
    //   4671: dup
    //   4672: bipush #39
    //   4674: ldc 1074266368
    //   4676: iastore
    //   4677: dup
    //   4678: bipush #40
    //   4680: ldc 33554688
    //   4682: iastore
    //   4683: dup
    //   4684: bipush #41
    //   4686: ldc 1073741824
    //   4688: iastore
    //   4689: dup
    //   4690: bipush #42
    //   4692: ldc 1107820544
    //   4694: iastore
    //   4695: dup
    //   4696: bipush #43
    //   4698: ldc 34078976
    //   4700: iastore
    //   4701: dup
    //   4702: bipush #44
    //   4704: ldc 1074266368
    //   4706: iastore
    //   4707: dup
    //   4708: bipush #45
    //   4710: sipush #256
    //   4713: iastore
    //   4714: dup
    //   4715: bipush #46
    //   4717: ldc 33554432
    //   4719: iastore
    //   4720: dup
    //   4721: bipush #47
    //   4723: ldc 1107820544
    //   4725: iastore
    //   4726: dup
    //   4727: bipush #48
    //   4729: ldc 1107820800
    //   4731: iastore
    //   4732: dup
    //   4733: bipush #49
    //   4735: ldc 524544
    //   4737: iastore
    //   4738: dup
    //   4739: bipush #50
    //   4741: ldc 1107296256
    //   4743: iastore
    //   4744: dup
    //   4745: bipush #51
    //   4747: ldc 1107820800
    //   4749: iastore
    //   4750: dup
    //   4751: bipush #52
    //   4753: ldc 34078720
    //   4755: iastore
    //   4756: dup
    //   4757: bipush #53
    //   4759: iconst_0
    //   4760: iastore
    //   4761: dup
    //   4762: bipush #54
    //   4764: ldc 1074266112
    //   4766: iastore
    //   4767: dup
    //   4768: bipush #55
    //   4770: ldc 1107296256
    //   4772: iastore
    //   4773: dup
    //   4774: bipush #56
    //   4776: ldc 524544
    //   4778: iastore
    //   4779: dup
    //   4780: bipush #57
    //   4782: ldc 33554688
    //   4784: iastore
    //   4785: dup
    //   4786: bipush #58
    //   4788: ldc 1073742080
    //   4790: iastore
    //   4791: dup
    //   4792: bipush #59
    //   4794: ldc 524288
    //   4796: iastore
    //   4797: dup
    //   4798: bipush #60
    //   4800: iconst_0
    //   4801: iastore
    //   4802: dup
    //   4803: bipush #61
    //   4805: ldc 1074266112
    //   4807: iastore
    //   4808: dup
    //   4809: bipush #62
    //   4811: ldc 34078976
    //   4813: iastore
    //   4814: dup
    //   4815: bipush #63
    //   4817: ldc 1073742080
    //   4819: iastore
    //   4820: astore #13
    //   4822: bipush #64
    //   4824: newarray int
    //   4826: dup
    //   4827: iconst_0
    //   4828: ldc 536870928
    //   4830: iastore
    //   4831: dup
    //   4832: iconst_1
    //   4833: ldc 541065216
    //   4835: iastore
    //   4836: dup
    //   4837: iconst_2
    //   4838: sipush #16384
    //   4841: iastore
    //   4842: dup
    //   4843: iconst_3
    //   4844: ldc 541081616
    //   4846: iastore
    //   4847: dup
    //   4848: iconst_4
    //   4849: ldc 541065216
    //   4851: iastore
    //   4852: dup
    //   4853: iconst_5
    //   4854: bipush #16
    //   4856: iastore
    //   4857: dup
    //   4858: bipush #6
    //   4860: ldc 541081616
    //   4862: iastore
    //   4863: dup
    //   4864: bipush #7
    //   4866: ldc 4194304
    //   4868: iastore
    //   4869: dup
    //   4870: bipush #8
    //   4872: ldc 536887296
    //   4874: iastore
    //   4875: dup
    //   4876: bipush #9
    //   4878: ldc 4210704
    //   4880: iastore
    //   4881: dup
    //   4882: bipush #10
    //   4884: ldc 4194304
    //   4886: iastore
    //   4887: dup
    //   4888: bipush #11
    //   4890: ldc 536870928
    //   4892: iastore
    //   4893: dup
    //   4894: bipush #12
    //   4896: ldc 4194320
    //   4898: iastore
    //   4899: dup
    //   4900: bipush #13
    //   4902: ldc 536887296
    //   4904: iastore
    //   4905: dup
    //   4906: bipush #14
    //   4908: ldc 536870912
    //   4910: iastore
    //   4911: dup
    //   4912: bipush #15
    //   4914: sipush #16400
    //   4917: iastore
    //   4918: dup
    //   4919: bipush #16
    //   4921: iconst_0
    //   4922: iastore
    //   4923: dup
    //   4924: bipush #17
    //   4926: ldc 4194320
    //   4928: iastore
    //   4929: dup
    //   4930: bipush #18
    //   4932: ldc 536887312
    //   4934: iastore
    //   4935: dup
    //   4936: bipush #19
    //   4938: sipush #16384
    //   4941: iastore
    //   4942: dup
    //   4943: bipush #20
    //   4945: ldc 4210688
    //   4947: iastore
    //   4948: dup
    //   4949: bipush #21
    //   4951: ldc 536887312
    //   4953: iastore
    //   4954: dup
    //   4955: bipush #22
    //   4957: bipush #16
    //   4959: iastore
    //   4960: dup
    //   4961: bipush #23
    //   4963: ldc 541065232
    //   4965: iastore
    //   4966: dup
    //   4967: bipush #24
    //   4969: ldc 541065232
    //   4971: iastore
    //   4972: dup
    //   4973: bipush #25
    //   4975: iconst_0
    //   4976: iastore
    //   4977: dup
    //   4978: bipush #26
    //   4980: ldc 4210704
    //   4982: iastore
    //   4983: dup
    //   4984: bipush #27
    //   4986: ldc 541081600
    //   4988: iastore
    //   4989: dup
    //   4990: bipush #28
    //   4992: sipush #16400
    //   4995: iastore
    //   4996: dup
    //   4997: bipush #29
    //   4999: ldc 4210688
    //   5001: iastore
    //   5002: dup
    //   5003: bipush #30
    //   5005: ldc 541081600
    //   5007: iastore
    //   5008: dup
    //   5009: bipush #31
    //   5011: ldc 536870912
    //   5013: iastore
    //   5014: dup
    //   5015: bipush #32
    //   5017: ldc 536887296
    //   5019: iastore
    //   5020: dup
    //   5021: bipush #33
    //   5023: bipush #16
    //   5025: iastore
    //   5026: dup
    //   5027: bipush #34
    //   5029: ldc 541065232
    //   5031: iastore
    //   5032: dup
    //   5033: bipush #35
    //   5035: ldc 4210688
    //   5037: iastore
    //   5038: dup
    //   5039: bipush #36
    //   5041: ldc 541081616
    //   5043: iastore
    //   5044: dup
    //   5045: bipush #37
    //   5047: ldc 4194304
    //   5049: iastore
    //   5050: dup
    //   5051: bipush #38
    //   5053: sipush #16400
    //   5056: iastore
    //   5057: dup
    //   5058: bipush #39
    //   5060: ldc 536870928
    //   5062: iastore
    //   5063: dup
    //   5064: bipush #40
    //   5066: ldc 4194304
    //   5068: iastore
    //   5069: dup
    //   5070: bipush #41
    //   5072: ldc 536887296
    //   5074: iastore
    //   5075: dup
    //   5076: bipush #42
    //   5078: ldc 536870912
    //   5080: iastore
    //   5081: dup
    //   5082: bipush #43
    //   5084: sipush #16400
    //   5087: iastore
    //   5088: dup
    //   5089: bipush #44
    //   5091: ldc 536870928
    //   5093: iastore
    //   5094: dup
    //   5095: bipush #45
    //   5097: ldc 541081616
    //   5099: iastore
    //   5100: dup
    //   5101: bipush #46
    //   5103: ldc 4210688
    //   5105: iastore
    //   5106: dup
    //   5107: bipush #47
    //   5109: ldc 541065216
    //   5111: iastore
    //   5112: dup
    //   5113: bipush #48
    //   5115: ldc 4210704
    //   5117: iastore
    //   5118: dup
    //   5119: bipush #49
    //   5121: ldc 541081600
    //   5123: iastore
    //   5124: dup
    //   5125: bipush #50
    //   5127: iconst_0
    //   5128: iastore
    //   5129: dup
    //   5130: bipush #51
    //   5132: ldc 541065232
    //   5134: iastore
    //   5135: dup
    //   5136: bipush #52
    //   5138: bipush #16
    //   5140: iastore
    //   5141: dup
    //   5142: bipush #53
    //   5144: sipush #16384
    //   5147: iastore
    //   5148: dup
    //   5149: bipush #54
    //   5151: ldc 541065216
    //   5153: iastore
    //   5154: dup
    //   5155: bipush #55
    //   5157: ldc 4210704
    //   5159: iastore
    //   5160: dup
    //   5161: bipush #56
    //   5163: sipush #16384
    //   5166: iastore
    //   5167: dup
    //   5168: bipush #57
    //   5170: ldc 4194320
    //   5172: iastore
    //   5173: dup
    //   5174: bipush #58
    //   5176: ldc 536887312
    //   5178: iastore
    //   5179: dup
    //   5180: bipush #59
    //   5182: iconst_0
    //   5183: iastore
    //   5184: dup
    //   5185: bipush #60
    //   5187: ldc 541081600
    //   5189: iastore
    //   5190: dup
    //   5191: bipush #61
    //   5193: ldc 536870912
    //   5195: iastore
    //   5196: dup
    //   5197: bipush #62
    //   5199: ldc 4194320
    //   5201: iastore
    //   5202: dup
    //   5203: bipush #63
    //   5205: ldc 536887312
    //   5207: iastore
    //   5208: astore #14
    //   5210: bipush #64
    //   5212: newarray int
    //   5214: dup
    //   5215: iconst_0
    //   5216: ldc 2097152
    //   5218: iastore
    //   5219: dup
    //   5220: iconst_1
    //   5221: ldc 69206018
    //   5223: iastore
    //   5224: dup
    //   5225: iconst_2
    //   5226: ldc 67110914
    //   5228: iastore
    //   5229: dup
    //   5230: iconst_3
    //   5231: iconst_0
    //   5232: iastore
    //   5233: dup
    //   5234: iconst_4
    //   5235: sipush #2048
    //   5238: iastore
    //   5239: dup
    //   5240: iconst_5
    //   5241: ldc 67110914
    //   5243: iastore
    //   5244: dup
    //   5245: bipush #6
    //   5247: ldc 2099202
    //   5249: iastore
    //   5250: dup
    //   5251: bipush #7
    //   5253: ldc 69208064
    //   5255: iastore
    //   5256: dup
    //   5257: bipush #8
    //   5259: ldc 69208066
    //   5261: iastore
    //   5262: dup
    //   5263: bipush #9
    //   5265: ldc 2097152
    //   5267: iastore
    //   5268: dup
    //   5269: bipush #10
    //   5271: iconst_0
    //   5272: iastore
    //   5273: dup
    //   5274: bipush #11
    //   5276: ldc 67108866
    //   5278: iastore
    //   5279: dup
    //   5280: bipush #12
    //   5282: iconst_2
    //   5283: iastore
    //   5284: dup
    //   5285: bipush #13
    //   5287: ldc 67108864
    //   5289: iastore
    //   5290: dup
    //   5291: bipush #14
    //   5293: ldc 69206018
    //   5295: iastore
    //   5296: dup
    //   5297: bipush #15
    //   5299: sipush #2050
    //   5302: iastore
    //   5303: dup
    //   5304: bipush #16
    //   5306: ldc 67110912
    //   5308: iastore
    //   5309: dup
    //   5310: bipush #17
    //   5312: ldc 2099202
    //   5314: iastore
    //   5315: dup
    //   5316: bipush #18
    //   5318: ldc 2097154
    //   5320: iastore
    //   5321: dup
    //   5322: bipush #19
    //   5324: ldc 67110912
    //   5326: iastore
    //   5327: dup
    //   5328: bipush #20
    //   5330: ldc 67108866
    //   5332: iastore
    //   5333: dup
    //   5334: bipush #21
    //   5336: ldc 69206016
    //   5338: iastore
    //   5339: dup
    //   5340: bipush #22
    //   5342: ldc 69208064
    //   5344: iastore
    //   5345: dup
    //   5346: bipush #23
    //   5348: ldc 2097154
    //   5350: iastore
    //   5351: dup
    //   5352: bipush #24
    //   5354: ldc 69206016
    //   5356: iastore
    //   5357: dup
    //   5358: bipush #25
    //   5360: sipush #2048
    //   5363: iastore
    //   5364: dup
    //   5365: bipush #26
    //   5367: sipush #2050
    //   5370: iastore
    //   5371: dup
    //   5372: bipush #27
    //   5374: ldc 69208066
    //   5376: iastore
    //   5377: dup
    //   5378: bipush #28
    //   5380: ldc 2099200
    //   5382: iastore
    //   5383: dup
    //   5384: bipush #29
    //   5386: iconst_2
    //   5387: iastore
    //   5388: dup
    //   5389: bipush #30
    //   5391: ldc 67108864
    //   5393: iastore
    //   5394: dup
    //   5395: bipush #31
    //   5397: ldc 2099200
    //   5399: iastore
    //   5400: dup
    //   5401: bipush #32
    //   5403: ldc 67108864
    //   5405: iastore
    //   5406: dup
    //   5407: bipush #33
    //   5409: ldc 2099200
    //   5411: iastore
    //   5412: dup
    //   5413: bipush #34
    //   5415: ldc 2097152
    //   5417: iastore
    //   5418: dup
    //   5419: bipush #35
    //   5421: ldc 67110914
    //   5423: iastore
    //   5424: dup
    //   5425: bipush #36
    //   5427: ldc 67110914
    //   5429: iastore
    //   5430: dup
    //   5431: bipush #37
    //   5433: ldc 69206018
    //   5435: iastore
    //   5436: dup
    //   5437: bipush #38
    //   5439: ldc 69206018
    //   5441: iastore
    //   5442: dup
    //   5443: bipush #39
    //   5445: iconst_2
    //   5446: iastore
    //   5447: dup
    //   5448: bipush #40
    //   5450: ldc 2097154
    //   5452: iastore
    //   5453: dup
    //   5454: bipush #41
    //   5456: ldc 67108864
    //   5458: iastore
    //   5459: dup
    //   5460: bipush #42
    //   5462: ldc 67110912
    //   5464: iastore
    //   5465: dup
    //   5466: bipush #43
    //   5468: ldc 2097152
    //   5470: iastore
    //   5471: dup
    //   5472: bipush #44
    //   5474: ldc 69208064
    //   5476: iastore
    //   5477: dup
    //   5478: bipush #45
    //   5480: sipush #2050
    //   5483: iastore
    //   5484: dup
    //   5485: bipush #46
    //   5487: ldc 2099202
    //   5489: iastore
    //   5490: dup
    //   5491: bipush #47
    //   5493: ldc 69208064
    //   5495: iastore
    //   5496: dup
    //   5497: bipush #48
    //   5499: sipush #2050
    //   5502: iastore
    //   5503: dup
    //   5504: bipush #49
    //   5506: ldc 67108866
    //   5508: iastore
    //   5509: dup
    //   5510: bipush #50
    //   5512: ldc 69208066
    //   5514: iastore
    //   5515: dup
    //   5516: bipush #51
    //   5518: ldc 69206016
    //   5520: iastore
    //   5521: dup
    //   5522: bipush #52
    //   5524: ldc 2099200
    //   5526: iastore
    //   5527: dup
    //   5528: bipush #53
    //   5530: iconst_0
    //   5531: iastore
    //   5532: dup
    //   5533: bipush #54
    //   5535: iconst_2
    //   5536: iastore
    //   5537: dup
    //   5538: bipush #55
    //   5540: ldc 69208066
    //   5542: iastore
    //   5543: dup
    //   5544: bipush #56
    //   5546: iconst_0
    //   5547: iastore
    //   5548: dup
    //   5549: bipush #57
    //   5551: ldc 2099202
    //   5553: iastore
    //   5554: dup
    //   5555: bipush #58
    //   5557: ldc 69206016
    //   5559: iastore
    //   5560: dup
    //   5561: bipush #59
    //   5563: sipush #2048
    //   5566: iastore
    //   5567: dup
    //   5568: bipush #60
    //   5570: ldc 67108866
    //   5572: iastore
    //   5573: dup
    //   5574: bipush #61
    //   5576: ldc 67110912
    //   5578: iastore
    //   5579: dup
    //   5580: bipush #62
    //   5582: sipush #2048
    //   5585: iastore
    //   5586: dup
    //   5587: bipush #63
    //   5589: ldc 2097154
    //   5591: iastore
    //   5592: astore #15
    //   5594: bipush #64
    //   5596: newarray int
    //   5598: dup
    //   5599: iconst_0
    //   5600: ldc 268439616
    //   5602: iastore
    //   5603: dup
    //   5604: iconst_1
    //   5605: sipush #4096
    //   5608: iastore
    //   5609: dup
    //   5610: iconst_2
    //   5611: ldc 262144
    //   5613: iastore
    //   5614: dup
    //   5615: iconst_3
    //   5616: ldc 268701760
    //   5618: iastore
    //   5619: dup
    //   5620: iconst_4
    //   5621: ldc 268435456
    //   5623: iastore
    //   5624: dup
    //   5625: iconst_5
    //   5626: ldc 268439616
    //   5628: iastore
    //   5629: dup
    //   5630: bipush #6
    //   5632: bipush #64
    //   5634: iastore
    //   5635: dup
    //   5636: bipush #7
    //   5638: ldc 268435456
    //   5640: iastore
    //   5641: dup
    //   5642: bipush #8
    //   5644: ldc 262208
    //   5646: iastore
    //   5647: dup
    //   5648: bipush #9
    //   5650: ldc 268697600
    //   5652: iastore
    //   5653: dup
    //   5654: bipush #10
    //   5656: ldc 268701760
    //   5658: iastore
    //   5659: dup
    //   5660: bipush #11
    //   5662: ldc 266240
    //   5664: iastore
    //   5665: dup
    //   5666: bipush #12
    //   5668: ldc 268701696
    //   5670: iastore
    //   5671: dup
    //   5672: bipush #13
    //   5674: ldc 266304
    //   5676: iastore
    //   5677: dup
    //   5678: bipush #14
    //   5680: sipush #4096
    //   5683: iastore
    //   5684: dup
    //   5685: bipush #15
    //   5687: bipush #64
    //   5689: iastore
    //   5690: dup
    //   5691: bipush #16
    //   5693: ldc 268697600
    //   5695: iastore
    //   5696: dup
    //   5697: bipush #17
    //   5699: ldc 268435520
    //   5701: iastore
    //   5702: dup
    //   5703: bipush #18
    //   5705: ldc 268439552
    //   5707: iastore
    //   5708: dup
    //   5709: bipush #19
    //   5711: sipush #4160
    //   5714: iastore
    //   5715: dup
    //   5716: bipush #20
    //   5718: ldc 266240
    //   5720: iastore
    //   5721: dup
    //   5722: bipush #21
    //   5724: ldc 262208
    //   5726: iastore
    //   5727: dup
    //   5728: bipush #22
    //   5730: ldc 268697664
    //   5732: iastore
    //   5733: dup
    //   5734: bipush #23
    //   5736: ldc 268701696
    //   5738: iastore
    //   5739: dup
    //   5740: bipush #24
    //   5742: sipush #4160
    //   5745: iastore
    //   5746: dup
    //   5747: bipush #25
    //   5749: iconst_0
    //   5750: iastore
    //   5751: dup
    //   5752: bipush #26
    //   5754: iconst_0
    //   5755: iastore
    //   5756: dup
    //   5757: bipush #27
    //   5759: ldc 268697664
    //   5761: iastore
    //   5762: dup
    //   5763: bipush #28
    //   5765: ldc 268435520
    //   5767: iastore
    //   5768: dup
    //   5769: bipush #29
    //   5771: ldc 268439552
    //   5773: iastore
    //   5774: dup
    //   5775: bipush #30
    //   5777: ldc 266304
    //   5779: iastore
    //   5780: dup
    //   5781: bipush #31
    //   5783: ldc 262144
    //   5785: iastore
    //   5786: dup
    //   5787: bipush #32
    //   5789: ldc 266304
    //   5791: iastore
    //   5792: dup
    //   5793: bipush #33
    //   5795: ldc 262144
    //   5797: iastore
    //   5798: dup
    //   5799: bipush #34
    //   5801: ldc 268701696
    //   5803: iastore
    //   5804: dup
    //   5805: bipush #35
    //   5807: sipush #4096
    //   5810: iastore
    //   5811: dup
    //   5812: bipush #36
    //   5814: bipush #64
    //   5816: iastore
    //   5817: dup
    //   5818: bipush #37
    //   5820: ldc 268697664
    //   5822: iastore
    //   5823: dup
    //   5824: bipush #38
    //   5826: sipush #4096
    //   5829: iastore
    //   5830: dup
    //   5831: bipush #39
    //   5833: ldc 266304
    //   5835: iastore
    //   5836: dup
    //   5837: bipush #40
    //   5839: ldc 268439552
    //   5841: iastore
    //   5842: dup
    //   5843: bipush #41
    //   5845: bipush #64
    //   5847: iastore
    //   5848: dup
    //   5849: bipush #42
    //   5851: ldc 268435520
    //   5853: iastore
    //   5854: dup
    //   5855: bipush #43
    //   5857: ldc 268697600
    //   5859: iastore
    //   5860: dup
    //   5861: bipush #44
    //   5863: ldc 268697664
    //   5865: iastore
    //   5866: dup
    //   5867: bipush #45
    //   5869: ldc 268435456
    //   5871: iastore
    //   5872: dup
    //   5873: bipush #46
    //   5875: ldc 262144
    //   5877: iastore
    //   5878: dup
    //   5879: bipush #47
    //   5881: ldc 268439616
    //   5883: iastore
    //   5884: dup
    //   5885: bipush #48
    //   5887: iconst_0
    //   5888: iastore
    //   5889: dup
    //   5890: bipush #49
    //   5892: ldc 268701760
    //   5894: iastore
    //   5895: dup
    //   5896: bipush #50
    //   5898: ldc 262208
    //   5900: iastore
    //   5901: dup
    //   5902: bipush #51
    //   5904: ldc 268435520
    //   5906: iastore
    //   5907: dup
    //   5908: bipush #52
    //   5910: ldc 268697600
    //   5912: iastore
    //   5913: dup
    //   5914: bipush #53
    //   5916: ldc 268439552
    //   5918: iastore
    //   5919: dup
    //   5920: bipush #54
    //   5922: ldc 268439616
    //   5924: iastore
    //   5925: dup
    //   5926: bipush #55
    //   5928: iconst_0
    //   5929: iastore
    //   5930: dup
    //   5931: bipush #56
    //   5933: ldc 268701760
    //   5935: iastore
    //   5936: dup
    //   5937: bipush #57
    //   5939: ldc 266240
    //   5941: iastore
    //   5942: dup
    //   5943: bipush #58
    //   5945: ldc 266240
    //   5947: iastore
    //   5948: dup
    //   5949: bipush #59
    //   5951: sipush #4160
    //   5954: iastore
    //   5955: dup
    //   5956: bipush #60
    //   5958: sipush #4160
    //   5961: iastore
    //   5962: dup
    //   5963: bipush #61
    //   5965: ldc 262208
    //   5967: iastore
    //   5968: dup
    //   5969: bipush #62
    //   5971: ldc 268435456
    //   5973: iastore
    //   5974: dup
    //   5975: bipush #63
    //   5977: ldc 268701696
    //   5979: iastore
    //   5980: astore #16
    //   5982: aload #4
    //   5984: arraylength
    //   5985: istore #17
    //   5987: iconst_2
    //   5988: newarray int
    //   5990: astore #18
    //   5992: iload #17
    //   5994: newarray byte
    //   5996: astore #5
    //   5998: iload #17
    //   6000: bipush #8
    //   6002: idiv
    //   6003: istore #19
    //   6005: iconst_0
    //   6006: istore #20
    //   6008: iload #20
    //   6010: iload #19
    //   6012: if_icmpge -> 6930
    //   6015: iload #20
    //   6017: bipush #8
    //   6019: imul
    //   6020: istore #21
    //   6022: iconst_0
    //   6023: istore #22
    //   6025: iload #22
    //   6027: iconst_2
    //   6028: if_icmpge -> 6117
    //   6031: aload #18
    //   6033: iload #22
    //   6035: aload #4
    //   6037: iload #21
    //   6039: iload #22
    //   6041: iconst_4
    //   6042: imul
    //   6043: iadd
    //   6044: baload
    //   6045: sipush #255
    //   6048: iand
    //   6049: bipush #24
    //   6051: ishl
    //   6052: aload #4
    //   6054: iload #21
    //   6056: iload #22
    //   6058: iconst_4
    //   6059: imul
    //   6060: iadd
    //   6061: iconst_1
    //   6062: iadd
    //   6063: baload
    //   6064: sipush #255
    //   6067: iand
    //   6068: bipush #16
    //   6070: ishl
    //   6071: ior
    //   6072: aload #4
    //   6074: iload #21
    //   6076: iload #22
    //   6078: iconst_4
    //   6079: imul
    //   6080: iadd
    //   6081: iconst_2
    //   6082: iadd
    //   6083: baload
    //   6084: sipush #255
    //   6087: iand
    //   6088: bipush #8
    //   6090: ishl
    //   6091: ior
    //   6092: aload #4
    //   6094: iload #21
    //   6096: iload #22
    //   6098: iconst_4
    //   6099: imul
    //   6100: iadd
    //   6101: iconst_3
    //   6102: iadd
    //   6103: baload
    //   6104: sipush #255
    //   6107: iand
    //   6108: ior
    //   6109: iastore
    //   6110: iinc #22, 1
    //   6113: iload_2
    //   6114: ifne -> 6025
    //   6117: iconst_0
    //   6118: istore #27
    //   6120: aload #18
    //   6122: iconst_0
    //   6123: iaload
    //   6124: istore #25
    //   6126: aload #18
    //   6128: iconst_1
    //   6129: iaload
    //   6130: istore #24
    //   6132: iload #25
    //   6134: iconst_4
    //   6135: iushr
    //   6136: iload #24
    //   6138: ixor
    //   6139: ldc 252645135
    //   6141: iand
    //   6142: istore #23
    //   6144: iload #24
    //   6146: iload #23
    //   6148: ixor
    //   6149: istore #24
    //   6151: iload #25
    //   6153: iload #23
    //   6155: iconst_4
    //   6156: ishl
    //   6157: ixor
    //   6158: istore #25
    //   6160: iload #25
    //   6162: bipush #16
    //   6164: iushr
    //   6165: iload #24
    //   6167: ixor
    //   6168: ldc 65535
    //   6170: iand
    //   6171: istore #23
    //   6173: iload #24
    //   6175: iload #23
    //   6177: ixor
    //   6178: istore #24
    //   6180: iload #25
    //   6182: iload #23
    //   6184: bipush #16
    //   6186: ishl
    //   6187: ixor
    //   6188: istore #25
    //   6190: iload #24
    //   6192: iconst_2
    //   6193: iushr
    //   6194: iload #25
    //   6196: ixor
    //   6197: ldc 858993459
    //   6199: iand
    //   6200: istore #23
    //   6202: iload #25
    //   6204: iload #23
    //   6206: ixor
    //   6207: istore #25
    //   6209: iload #24
    //   6211: iload #23
    //   6213: iconst_2
    //   6214: ishl
    //   6215: ixor
    //   6216: istore #24
    //   6218: iload #24
    //   6220: bipush #8
    //   6222: iushr
    //   6223: iload #25
    //   6225: ixor
    //   6226: ldc 16711935
    //   6228: iand
    //   6229: istore #23
    //   6231: iload #25
    //   6233: iload #23
    //   6235: ixor
    //   6236: istore #25
    //   6238: iload #24
    //   6240: iload #23
    //   6242: bipush #8
    //   6244: ishl
    //   6245: ixor
    //   6246: istore #24
    //   6248: iload #24
    //   6250: iconst_1
    //   6251: ishl
    //   6252: iload #24
    //   6254: bipush #31
    //   6256: iushr
    //   6257: iconst_1
    //   6258: iand
    //   6259: ior
    //   6260: istore #24
    //   6262: iload #25
    //   6264: iload #24
    //   6266: ixor
    //   6267: ldc -1431655766
    //   6269: iand
    //   6270: istore #23
    //   6272: iload #25
    //   6274: iload #23
    //   6276: ixor
    //   6277: istore #25
    //   6279: iload #24
    //   6281: iload #23
    //   6283: ixor
    //   6284: istore #24
    //   6286: iload #25
    //   6288: iconst_1
    //   6289: ishl
    //   6290: iload #25
    //   6292: bipush #31
    //   6294: iushr
    //   6295: iconst_1
    //   6296: iand
    //   6297: ior
    //   6298: istore #25
    //   6300: iconst_0
    //   6301: istore #26
    //   6303: iload #26
    //   6305: bipush #8
    //   6307: if_icmpge -> 6645
    //   6310: iload #24
    //   6312: bipush #28
    //   6314: ishl
    //   6315: iload #24
    //   6317: iconst_4
    //   6318: iushr
    //   6319: ior
    //   6320: istore #23
    //   6322: iload #23
    //   6324: aload #6
    //   6326: iload #27
    //   6328: iinc #27, 1
    //   6331: iaload
    //   6332: ixor
    //   6333: istore #23
    //   6335: aload #15
    //   6337: iload #23
    //   6339: bipush #63
    //   6341: iand
    //   6342: iaload
    //   6343: istore #22
    //   6345: iload #22
    //   6347: aload #13
    //   6349: iload #23
    //   6351: bipush #8
    //   6353: iushr
    //   6354: bipush #63
    //   6356: iand
    //   6357: iaload
    //   6358: ior
    //   6359: istore #22
    //   6361: iload #22
    //   6363: aload #11
    //   6365: iload #23
    //   6367: bipush #16
    //   6369: iushr
    //   6370: bipush #63
    //   6372: iand
    //   6373: iaload
    //   6374: ior
    //   6375: istore #22
    //   6377: iload #22
    //   6379: aload #9
    //   6381: iload #23
    //   6383: bipush #24
    //   6385: iushr
    //   6386: bipush #63
    //   6388: iand
    //   6389: iaload
    //   6390: ior
    //   6391: istore #22
    //   6393: iload #24
    //   6395: aload #6
    //   6397: iload #27
    //   6399: iinc #27, 1
    //   6402: iaload
    //   6403: ixor
    //   6404: istore #23
    //   6406: iload #22
    //   6408: aload #16
    //   6410: iload #23
    //   6412: bipush #63
    //   6414: iand
    //   6415: iaload
    //   6416: ior
    //   6417: istore #22
    //   6419: iload #22
    //   6421: aload #14
    //   6423: iload #23
    //   6425: bipush #8
    //   6427: iushr
    //   6428: bipush #63
    //   6430: iand
    //   6431: iaload
    //   6432: ior
    //   6433: istore #22
    //   6435: iload #22
    //   6437: aload #12
    //   6439: iload #23
    //   6441: bipush #16
    //   6443: iushr
    //   6444: bipush #63
    //   6446: iand
    //   6447: iaload
    //   6448: ior
    //   6449: istore #22
    //   6451: iload #22
    //   6453: aload #10
    //   6455: iload #23
    //   6457: bipush #24
    //   6459: iushr
    //   6460: bipush #63
    //   6462: iand
    //   6463: iaload
    //   6464: ior
    //   6465: istore #22
    //   6467: iload #25
    //   6469: iload #22
    //   6471: ixor
    //   6472: istore #25
    //   6474: iload #25
    //   6476: bipush #28
    //   6478: ishl
    //   6479: iload #25
    //   6481: iconst_4
    //   6482: iushr
    //   6483: ior
    //   6484: istore #23
    //   6486: iload #23
    //   6488: aload #6
    //   6490: iload #27
    //   6492: iinc #27, 1
    //   6495: iaload
    //   6496: ixor
    //   6497: istore #23
    //   6499: aload #15
    //   6501: iload #23
    //   6503: bipush #63
    //   6505: iand
    //   6506: iaload
    //   6507: istore #22
    //   6509: iload #22
    //   6511: aload #13
    //   6513: iload #23
    //   6515: bipush #8
    //   6517: iushr
    //   6518: bipush #63
    //   6520: iand
    //   6521: iaload
    //   6522: ior
    //   6523: istore #22
    //   6525: iload #22
    //   6527: aload #11
    //   6529: iload #23
    //   6531: bipush #16
    //   6533: iushr
    //   6534: bipush #63
    //   6536: iand
    //   6537: iaload
    //   6538: ior
    //   6539: istore #22
    //   6541: iload #22
    //   6543: aload #9
    //   6545: iload #23
    //   6547: bipush #24
    //   6549: iushr
    //   6550: bipush #63
    //   6552: iand
    //   6553: iaload
    //   6554: ior
    //   6555: istore #22
    //   6557: iload #25
    //   6559: aload #6
    //   6561: iload #27
    //   6563: iinc #27, 1
    //   6566: iaload
    //   6567: ixor
    //   6568: istore #23
    //   6570: iload #22
    //   6572: aload #16
    //   6574: iload #23
    //   6576: bipush #63
    //   6578: iand
    //   6579: iaload
    //   6580: ior
    //   6581: istore #22
    //   6583: iload #22
    //   6585: aload #14
    //   6587: iload #23
    //   6589: bipush #8
    //   6591: iushr
    //   6592: bipush #63
    //   6594: iand
    //   6595: iaload
    //   6596: ior
    //   6597: istore #22
    //   6599: iload #22
    //   6601: aload #12
    //   6603: iload #23
    //   6605: bipush #16
    //   6607: iushr
    //   6608: bipush #63
    //   6610: iand
    //   6611: iaload
    //   6612: ior
    //   6613: istore #22
    //   6615: iload #22
    //   6617: aload #10
    //   6619: iload #23
    //   6621: bipush #24
    //   6623: iushr
    //   6624: bipush #63
    //   6626: iand
    //   6627: iaload
    //   6628: ior
    //   6629: istore #22
    //   6631: iload #24
    //   6633: iload #22
    //   6635: ixor
    //   6636: istore #24
    //   6638: iinc #26, 1
    //   6641: iload_2
    //   6642: ifne -> 6303
    //   6645: iload #24
    //   6647: bipush #31
    //   6649: ishl
    //   6650: iload #24
    //   6652: iconst_1
    //   6653: iushr
    //   6654: ior
    //   6655: istore #24
    //   6657: iload #25
    //   6659: iload #24
    //   6661: ixor
    //   6662: ldc -1431655766
    //   6664: iand
    //   6665: istore #23
    //   6667: iload #25
    //   6669: iload #23
    //   6671: ixor
    //   6672: istore #25
    //   6674: iload #24
    //   6676: iload #23
    //   6678: ixor
    //   6679: istore #24
    //   6681: iload #25
    //   6683: bipush #31
    //   6685: ishl
    //   6686: iload #25
    //   6688: iconst_1
    //   6689: iushr
    //   6690: ior
    //   6691: istore #25
    //   6693: iload #25
    //   6695: bipush #8
    //   6697: iushr
    //   6698: iload #24
    //   6700: ixor
    //   6701: ldc 16711935
    //   6703: iand
    //   6704: istore #23
    //   6706: iload #24
    //   6708: iload #23
    //   6710: ixor
    //   6711: istore #24
    //   6713: iload #25
    //   6715: iload #23
    //   6717: bipush #8
    //   6719: ishl
    //   6720: ixor
    //   6721: istore #25
    //   6723: iload #25
    //   6725: iconst_2
    //   6726: iushr
    //   6727: iload #24
    //   6729: ixor
    //   6730: ldc 858993459
    //   6732: iand
    //   6733: istore #23
    //   6735: iload #24
    //   6737: iload #23
    //   6739: ixor
    //   6740: istore #24
    //   6742: iload #25
    //   6744: iload #23
    //   6746: iconst_2
    //   6747: ishl
    //   6748: ixor
    //   6749: istore #25
    //   6751: iload #24
    //   6753: bipush #16
    //   6755: iushr
    //   6756: iload #25
    //   6758: ixor
    //   6759: ldc 65535
    //   6761: iand
    //   6762: istore #23
    //   6764: iload #25
    //   6766: iload #23
    //   6768: ixor
    //   6769: istore #25
    //   6771: iload #24
    //   6773: iload #23
    //   6775: bipush #16
    //   6777: ishl
    //   6778: ixor
    //   6779: istore #24
    //   6781: iload #24
    //   6783: iconst_4
    //   6784: iushr
    //   6785: iload #25
    //   6787: ixor
    //   6788: ldc 252645135
    //   6790: iand
    //   6791: istore #23
    //   6793: iload #25
    //   6795: iload #23
    //   6797: ixor
    //   6798: istore #25
    //   6800: iload #24
    //   6802: iload #23
    //   6804: iconst_4
    //   6805: ishl
    //   6806: ixor
    //   6807: istore #24
    //   6809: aload #18
    //   6811: iconst_0
    //   6812: iload #24
    //   6814: iastore
    //   6815: aload #18
    //   6817: iconst_1
    //   6818: iload #25
    //   6820: iastore
    //   6821: iload #20
    //   6823: bipush #8
    //   6825: imul
    //   6826: istore #28
    //   6828: iconst_0
    //   6829: istore #29
    //   6831: iload #29
    //   6833: iconst_2
    //   6834: if_icmpge -> 6923
    //   6837: aload #5
    //   6839: iload #28
    //   6841: iload #29
    //   6843: iconst_4
    //   6844: imul
    //   6845: iadd
    //   6846: aload #18
    //   6848: iload #29
    //   6850: iaload
    //   6851: bipush #24
    //   6853: iushr
    //   6854: i2b
    //   6855: bastore
    //   6856: aload #5
    //   6858: iload #28
    //   6860: iload #29
    //   6862: iconst_4
    //   6863: imul
    //   6864: iadd
    //   6865: iconst_1
    //   6866: iadd
    //   6867: aload #18
    //   6869: iload #29
    //   6871: iaload
    //   6872: bipush #16
    //   6874: iushr
    //   6875: i2b
    //   6876: bastore
    //   6877: aload #5
    //   6879: iload #28
    //   6881: iload #29
    //   6883: iconst_4
    //   6884: imul
    //   6885: iadd
    //   6886: iconst_2
    //   6887: iadd
    //   6888: aload #18
    //   6890: iload #29
    //   6892: iaload
    //   6893: bipush #8
    //   6895: iushr
    //   6896: i2b
    //   6897: bastore
    //   6898: aload #5
    //   6900: iload #28
    //   6902: iload #29
    //   6904: iconst_4
    //   6905: imul
    //   6906: iadd
    //   6907: iconst_3
    //   6908: iadd
    //   6909: aload #18
    //   6911: iload #29
    //   6913: iaload
    //   6914: i2b
    //   6915: bastore
    //   6916: iinc #29, 1
    //   6919: iload_2
    //   6920: ifne -> 6831
    //   6923: iinc #20, 1
    //   6926: iload_2
    //   6927: ifne -> 6008
    //   6930: getstatic burp/Zttj.ZN : Ljava/lang/String;
    //   6933: getstatic burp/Zxrd.ZL : Ljava/lang/Object;
    //   6936: checkcast java/math/BigInteger
    //   6939: invokevirtual intValue : ()I
    //   6942: bipush #32
    //   6944: irem
    //   6945: invokestatic abs : (I)I
    //   6948: invokevirtual charAt : (I)C
    //   6951: getstatic burp/Zlc5.Z_ : Ljava/lang/String;
    //   6954: getstatic burp/Zgdt.Zb : Ljava/lang/Object;
    //   6957: checkcast java/math/BigInteger
    //   6960: invokevirtual intValue : ()I
    //   6963: bipush #32
    //   6965: irem
    //   6966: invokestatic abs : (I)I
    //   6969: invokevirtual charAt : (I)C
    //   6972: if_icmple -> 7079
    //   6975: getstatic burp/Zljx.ZD : Ljava/lang/String;
    //   6978: getstatic burp/Zgdt.Zb : Ljava/lang/Object;
    //   6981: checkcast java/math/BigInteger
    //   6984: invokevirtual intValue : ()I
    //   6987: bipush #32
    //   6989: irem
    //   6990: invokestatic abs : (I)I
    //   6993: invokevirtual charAt : (I)C
    //   6996: getstatic burp/Zmjr.Zc : Ljava/lang/String;
    //   6999: getstatic burp/Zkv2.ZC : Ljava/lang/Object;
    //   7002: checkcast java/math/BigInteger
    //   7005: invokevirtual intValue : ()I
    //   7008: bipush #32
    //   7010: irem
    //   7011: invokestatic abs : (I)I
    //   7014: invokevirtual charAt : (I)C
    //   7017: if_icmple -> 7079
    //   7020: goto -> 7027
    //   7023: invokestatic a : (Ljava/lang/Throwable;)Ljava/lang/Throwable;
    //   7026: athrow
    //   7027: getstatic burp/Ztd6.Zu : Ljava/lang/String;
    //   7030: getstatic burp/Zz0j.Zn : Ljava/lang/Object;
    //   7033: checkcast java/math/BigInteger
    //   7036: invokevirtual intValue : ()I
    //   7039: bipush #32
    //   7041: irem
    //   7042: invokestatic abs : (I)I
    //   7045: invokevirtual charAt : (I)C
    //   7048: getstatic burp/Zs9u.ZM : Ljava/lang/String;
    //   7051: getstatic burp/Zkvq.Zz : Ljava/lang/Object;
    //   7054: checkcast java/math/BigInteger
    //   7057: invokevirtual intValue : ()I
    //   7060: bipush #32
    //   7062: irem
    //   7063: invokestatic abs : (I)I
    //   7066: invokevirtual charAt : (I)C
    //   7069: if_icmpgt -> 7087
    //   7072: goto -> 7079
    //   7075: invokestatic a : (Ljava/lang/Throwable;)Ljava/lang/Throwable;
    //   7078: athrow
    //   7079: iconst_1
    //   7080: goto -> 7088
    //   7083: invokestatic a : (Ljava/lang/Throwable;)Ljava/lang/Throwable;
    //   7086: athrow
    //   7087: iconst_0
    //   7088: ireturn
    //   7089: astore_3
    //   7090: new java/lang/Exception
    //   7093: dup
    //   7094: aload_3
    //   7095: invokevirtual getMessage : ()Ljava/lang/String;
    //   7098: invokespecial <init> : (Ljava/lang/String;)V
    //   7101: athrow
    // Exception table:
    //   from	to	target	type
    //   4	7088	7089	java/lang/Throwable
    //   22	198	201	java/lang/Throwable
    //   168	235	238	java/lang/Throwable
    //   205	272	275	java/lang/Throwable
    //   242	309	312	java/lang/Throwable
    //   279	346	349	java/lang/Throwable
    //   316	383	386	java/lang/Throwable
    //   353	420	423	java/lang/Throwable
    //   390	457	460	java/lang/Throwable
    //   427	494	497	java/lang/Throwable
    //   464	531	534	java/lang/Throwable
    //   501	568	571	java/lang/Throwable
    //   538	605	608	java/lang/Throwable
    //   575	642	645	java/lang/Throwable
    //   612	679	682	java/lang/Throwable
    //   649	716	719	java/lang/Throwable
    //   686	753	756	java/lang/Throwable
    //   723	790	793	java/lang/Throwable
    //   760	827	830	java/lang/Throwable
    //   797	864	867	java/lang/Throwable
    //   834	901	904	java/lang/Throwable
    //   871	938	941	java/lang/Throwable
    //   908	975	978	java/lang/Throwable
    //   945	1012	1015	java/lang/Throwable
    //   982	1049	1052	java/lang/Throwable
    //   1019	1086	1089	java/lang/Throwable
    //   1056	1123	1126	java/lang/Throwable
    //   1093	1160	1163	java/lang/Throwable
    //   1130	1197	1200	java/lang/Throwable
    //   1167	1234	1237	java/lang/Throwable
    //   1204	1271	1274	java/lang/Throwable
    //   1241	1308	1311	java/lang/Throwable
    //   1278	1341	1344	java/lang/Throwable
    //   1394	1408	1411	java/lang/Throwable
    //   1401	1422	1425	java/lang/Throwable
    //   1415	1436	1439	java/lang/Throwable
    //   1429	1450	1453	java/lang/Throwable
    //   1443	1464	1467	java/lang/Throwable
    //   1457	1478	1481	java/lang/Throwable
    //   1471	1492	1495	java/lang/Throwable
    //   1485	1506	1509	java/lang/Throwable
    //   1499	1516	1519	java/lang/Throwable
    //   1557	1571	1574	java/lang/Throwable
    //   1564	1585	1588	java/lang/Throwable
    //   1578	1599	1602	java/lang/Throwable
    //   1592	1613	1616	java/lang/Throwable
    //   1606	1627	1630	java/lang/Throwable
    //   1620	1641	1644	java/lang/Throwable
    //   1634	1655	1658	java/lang/Throwable
    //   1648	1669	1672	java/lang/Throwable
    //   1662	1686	1689	java/lang/Throwable
    //   1755	1775	1778	java/lang/Throwable
    //   1765	1792	1795	java/lang/Throwable
    //   1782	1810	1813	java/lang/Throwable
    //   1799	1827	1830	java/lang/Throwable
    //   1817	1845	1848	java/lang/Throwable
    //   1834	1862	1865	java/lang/Throwable
    //   1852	1879	1882	java/lang/Throwable
    //   1869	1904	1907	java/lang/Throwable
    //   1886	1921	1924	java/lang/Throwable
    //   1911	1938	1941	java/lang/Throwable
    //   1928	1963	1966	java/lang/Throwable
    //   1945	1980	1983	java/lang/Throwable
    //   1970	1997	2000	java/lang/Throwable
    //   1987	2018	2021	java/lang/Throwable
    //   2154	2191	2194	java/lang/Throwable
    //   2198	2241	2244	java/lang/Throwable
    //   2312	2326	2326	java/lang/Throwable
    //   2337	2350	2353	java/lang/Throwable
    //   2342	2365	2368	java/lang/Throwable
    //   2357	2383	2386	java/lang/Throwable
    //   2372	2413	2416	java/lang/Throwable
    //   2479	2506	2509	java/lang/Throwable
    //   2496	2527	2530	java/lang/Throwable
    //   2513	2557	2560	java/lang/Throwable
    //   2534	2568	2568	java/lang/Throwable
    //   2579	2595	2598	java/lang/Throwable
    //   6930	7020	7023	java/lang/Throwable
    //   6975	7072	7075	java/lang/Throwable
    //   7027	7083	7083	java/lang/Throwable
  }
  
  static {
    // Byte code:
    //   0: bipush #8
    //   2: anewarray java/lang/String
    //   5: astore #5
    //   7: iconst_0
    //   8: istore_3
    //   9: ldc '[$<Y G+0m>w6W&Q^K'u-39o\\t~l !Meqyt2|+.r(>>9A2e1cFaW|I<|r\6r qo61Z7i'
    //   11: dup
    //   12: astore_2
    //   13: invokevirtual length : ()I
    //   16: istore #4
    //   18: bipush #9
    //   20: istore_1
    //   21: iconst_m1
    //   22: istore_0
    //   23: bipush #96
    //   25: iinc #0, 1
    //   28: aload_2
    //   29: iload_0
    //   30: dup
    //   31: iload_1
    //   32: iadd
    //   33: invokevirtual substring : (II)Ljava/lang/String;
    //   36: iconst_m1
    //   37: goto -> 143
    //   40: aload #5
    //   42: swap
    //   43: iload_3
    //   44: iinc #3, 1
    //   47: swap
    //   48: aastore
    //   49: iload_0
    //   50: iload_1
    //   51: iadd
    //   52: dup
    //   53: istore_0
    //   54: iload #4
    //   56: if_icmpge -> 68
    //   59: aload_2
    //   60: iload_0
    //   61: invokevirtual charAt : (I)C
    //   64: istore_1
    //   65: goto -> 23
    //   68: ldc 'Xe+%$\\b'
    //   70: dup
    //   71: astore_2
    //   72: invokevirtual length : ()I
    //   75: istore #4
    //   77: bipush #8
    //   79: istore_1
    //   80: iconst_m1
    //   81: istore_0
    //   82: bipush #98
    //   84: iinc #0, 1
    //   87: aload_2
    //   88: iload_0
    //   89: dup
    //   90: iload_1
    //   91: iadd
    //   92: invokevirtual substring : (II)Ljava/lang/String;
    //   95: iconst_0
    //   96: goto -> 143
    //   99: aload #5
    //   101: swap
    //   102: iload_3
    //   103: iinc #3, 1
    //   106: swap
    //   107: aastore
    //   108: iload_0
    //   109: iload_1
    //   110: iadd
    //   111: dup
    //   112: istore_0
    //   113: iload #4
    //   115: if_icmpge -> 127
    //   118: aload_2
    //   119: iload_0
    //   120: invokevirtual charAt : (I)C
    //   123: istore_1
    //   124: goto -> 82
    //   127: aload #5
    //   129: putstatic burp/Ztpa.a : [Ljava/lang/String;
    //   132: bipush #8
    //   134: anewarray java/lang/String
    //   137: putstatic burp/Ztpa.b : [Ljava/lang/String;
    //   140: goto -> 300
    //   143: dup_x2
    //   144: pop
    //   145: invokevirtual toCharArray : ()[C
    //   148: dup_x1
    //   149: arraylength
    //   150: dup_x2
    //   151: pop
    //   152: iconst_0
    //   153: istore #6
    //   155: dup2_x1
    //   156: pop2
    //   157: dup_x2
    //   158: iconst_1
    //   159: if_icmpgt -> 260
    //   162: dup2
    //   163: swap
    //   164: iload #6
    //   166: dup2_x1
    //   167: caload
    //   168: swap
    //   169: iload #6
    //   171: bipush #7
    //   173: irem
    //   174: tableswitch default -> 242, 0 -> 212, 1 -> 217, 2 -> 222, 3 -> 227, 4 -> 232, 5 -> 237
    //   212: bipush #71
    //   214: goto -> 244
    //   217: bipush #119
    //   219: goto -> 244
    //   222: bipush #55
    //   224: goto -> 244
    //   227: bipush #97
    //   229: goto -> 244
    //   232: bipush #107
    //   234: goto -> 244
    //   237: bipush #51
    //   239: goto -> 244
    //   242: bipush #82
    //   244: ixor
    //   245: ixor
    //   246: i2c
    //   247: castore
    //   248: iinc #6, 1
    //   251: dup
    //   252: ifne -> 260
    //   255: dup2
    //   256: dup_x1
    //   257: goto -> 166
    //   260: dup2_x1
    //   261: pop2
    //   262: dup_x2
    //   263: iload #6
    //   265: if_icmpgt -> 162
    //   268: pop
    //   269: new java/lang/String
    //   272: dup_x1
    //   273: swap
    //   274: invokespecial <init> : ([C)V
    //   277: invokevirtual intern : ()Ljava/lang/String;
    //   280: swap
    //   281: pop
    //   282: swap
    //   283: tableswitch default -> 40, 0 -> 99
    //   300: sipush #-15562
    //   303: sipush #21579
    //   306: invokestatic a : (II)Ljava/lang/String;
    //   309: putstatic burp/Ztpa.ZZ : Ljava/lang/String;
    //   312: new java/math/BigInteger
    //   315: dup
    //   316: iconst_1
    //   317: bipush #32
    //   319: newarray byte
    //   321: dup
    //   322: iconst_0
    //   323: bipush #45
    //   325: bastore
    //   326: dup
    //   327: iconst_1
    //   328: bipush #-49
    //   330: bastore
    //   331: dup
    //   332: iconst_2
    //   333: bipush #-126
    //   335: bastore
    //   336: dup
    //   337: iconst_3
    //   338: bipush #73
    //   340: bastore
    //   341: dup
    //   342: iconst_4
    //   343: bipush #-12
    //   345: bastore
    //   346: dup
    //   347: iconst_5
    //   348: bipush #41
    //   350: bastore
    //   351: dup
    //   352: bipush #6
    //   354: bipush #-127
    //   356: bastore
    //   357: dup
    //   358: bipush #7
    //   360: bipush #-10
    //   362: bastore
    //   363: dup
    //   364: bipush #8
    //   366: bipush #-102
    //   368: bastore
    //   369: dup
    //   370: bipush #9
    //   372: bipush #57
    //   374: bastore
    //   375: dup
    //   376: bipush #10
    //   378: bipush #119
    //   380: bastore
    //   381: dup
    //   382: bipush #11
    //   384: bipush #-10
    //   386: bastore
    //   387: dup
    //   388: bipush #12
    //   390: bipush #-15
    //   392: bastore
    //   393: dup
    //   394: bipush #13
    //   396: bipush #-51
    //   398: bastore
    //   399: dup
    //   400: bipush #14
    //   402: bipush #-25
    //   404: bastore
    //   405: dup
    //   406: bipush #15
    //   408: bipush #95
    //   410: bastore
    //   411: dup
    //   412: bipush #16
    //   414: bipush #-69
    //   416: bastore
    //   417: dup
    //   418: bipush #17
    //   420: bipush #24
    //   422: bastore
    //   423: dup
    //   424: bipush #18
    //   426: bipush #120
    //   428: bastore
    //   429: dup
    //   430: bipush #19
    //   432: bipush #-113
    //   434: bastore
    //   435: dup
    //   436: bipush #20
    //   438: bipush #75
    //   440: bastore
    //   441: dup
    //   442: bipush #21
    //   444: bipush #-60
    //   446: bastore
    //   447: dup
    //   448: bipush #22
    //   450: bipush #78
    //   452: bastore
    //   453: dup
    //   454: bipush #23
    //   456: bipush #-115
    //   458: bastore
    //   459: dup
    //   460: bipush #24
    //   462: bipush #-96
    //   464: bastore
    //   465: dup
    //   466: bipush #25
    //   468: bipush #61
    //   470: bastore
    //   471: dup
    //   472: bipush #26
    //   474: bipush #-64
    //   476: bastore
    //   477: dup
    //   478: bipush #27
    //   480: bipush #-128
    //   482: bastore
    //   483: dup
    //   484: bipush #28
    //   486: bipush #38
    //   488: bastore
    //   489: dup
    //   490: bipush #29
    //   492: bipush #-51
    //   494: bastore
    //   495: dup
    //   496: bipush #30
    //   498: iconst_4
    //   499: bastore
    //   500: dup
    //   501: bipush #31
    //   503: bipush #-113
    //   505: bastore
    //   506: invokespecial <init> : (I[B)V
    //   509: putstatic burp/Ztpa.Zv : Ljava/lang/Object;
    //   512: return
  }
  
  private static Throwable a(Throwable paramThrowable) {
    return paramThrowable;
  }
  
  private static String a(int paramInt1, int paramInt2) {
    int i = (paramInt1 ^ 0xFFFFC337) & 0xFFFF;
    if (b[i] == null) {
      char[] arrayOfChar = a[i].toCharArray();
      switch (arrayOfChar[0] & 0xFF) {
        case 0:
        
        case 1:
        
        case 2:
        
        case 3:
        
        case 4:
        
        case 5:
        
        case 6:
        
        case 7:
        
        case 8:
        
        case 9:
        
        case 10:
        
        case 11:
        
        case 12:
        
        case 13:
        
        case 14:
        
        case 15:
        
        case 16:
        
        case 17:
        
        case 18:
        
        case 19:
        
        case 20:
        
        case 21:
        
        case 22:
        
        case 23:
        
        case 24:
        
        case 25:
        
        case 26:
        
        case 27:
        
        case 28:
        
        case 29:
        
        case 30:
        
        case 31:
        
        case 32:
        
        case 33:
        
        case 34:
        
        case 35:
        
        case 36:
        
        case 37:
        
        case 38:
        
        case 39:
        
        case 40:
        
        case 41:
        
        case 42:
        
        case 43:
        
        case 44:
        
        case 45:
        
        case 46:
        
        case 47:
        
        case 48:
        
        case 49:
        
        case 50:
        
        case 51:
        
        case 52:
        
        case 53:
        
        case 54:
        
        case 55:
        
        case 56:
        
        case 57:
        
        case 58:
        
        case 59:
        
        case 60:
        
        case 61:
        
        case 62:
        
        case 63:
        
        case 64:
        
        case 65:
        
        case 66:
        
        case 67:
        
        case 68:
        
        case 69:
        
        case 70:
        
        case 71:
        
        case 72:
        
        case 73:
        
        case 74:
        
        case 75:
        
        case 76:
        
        case 77:
        
        case 78:
        
        case 79:
        
        case 80:
        
        case 81:
        
        case 82:
        
        case 83:
        
        case 84:
        
        case 85:
        
        case 86:
        
        case 87:
        
        case 88:
        
        case 89:
        
        case 90:
        
        case 91:
        
        case 92:
        
        case 93:
        
        case 94:
        
        case 95:
        
        case 96:
        
        case 97:
        
        case 98:
        
        case 99:
        
        case 100:
        
        case 101:
        
        case 102:
        
        case 103:
        
        case 104:
        
        case 105:
        
        case 106:
        
        case 107:
        
        case 108:
        
        case 109:
        
        case 110:
        
        case 111:
        
        case 112:
        
        case 113:
        
        case 114:
        
        case 115:
        
        case 116:
        
        case 117:
        
        case 118:
        
        case 119:
        
        case 120:
        
        case 121:
        
        case 122:
        
        case 123:
        
        case 124:
        
        case 125:
        
        case 126:
        
        case 127:
        
        case 128:
        
        case 129:
        
        case 130:
        
        case 131:
        
        case 132:
        
        case 133:
        
        case 134:
        
        case 135:
        
        case 136:
        
        case 137:
        
        case 138:
        
        case 139:
        
        case 140:
        
        case 141:
        
        case 142:
        
        case 143:
        
        case 144:
        
        case 145:
        
        case 146:
        
        case 147:
        
        case 148:
        
        case 149:
        
        case 150:
        
        case 151:
        
        case 152:
        
        case 153:
        
        case 154:
        
        case 155:
        
        case 156:
        
        case 157:
        
        case 158:
        
        case 159:
        
        case 160:
        
        case 161:
        
        case 162:
        
        case 163:
        
        case 164:
        
        case 165:
        
        case 166:
        
        case 167:
        
        case 168:
        
        case 169:
        
        case 170:
        
        case 171:
        
        case 172:
        
        case 173:
        
        case 174:
        
        case 175:
        
        case 176:
        
        case 177:
        
        case 178:
        
        case 179:
        
        case 180:
        
        case 181:
        
        case 182:
        
        case 183:
        
        case 184:
        
        case 185:
        
        case 186:
        
        case 187:
        
        case 188:
        
        case 189:
        
        case 190:
        
        case 191:
        
        case 192:
        
        case 193:
        
        case 194:
        
        case 195:
        
        case 196:
        
        case 197:
        
        case 198:
        
        case 199:
        
        case 200:
        
        case 201:
        
        case 202:
        
        case 203:
        
        case 204:
        
        case 205:
        
        case 206:
        
        case 207:
        
        case 208:
        
        case 209:
        
        case 210:
        
        case 211:
        
        case 212:
        
        case 213:
        
        case 214:
        
        case 215:
        
        case 216:
        
        case 217:
        
        case 218:
        
        case 219:
        
        case 220:
        
        case 221:
        
        case 222:
        
        case 223:
        
        case 224:
        
        case 225:
        
        case 226:
        
        case 227:
        
        case 228:
        
        case 229:
        
        case 230:
        
        case 231:
        
        case 232:
        
        case 233:
        
        case 234:
        
        case 235:
        
        case 236:
        
        case 237:
        
        case 238:
        
        case 239:
        
        case 240:
        
        case 241:
        
        case 242:
        
        case 243:
        
        case 244:
        
        case 245:
        
        case 246:
        
        case 247:
        
        case 248:
        
        case 249:
        
        case 250:
        
        case 251:
        
        case 252:
        
        case 253:
        
        case 254:
        
        default:
          break;
      } 
      byte b1 = 64;
      int j = (paramInt2 & 0xFF) - b1;
      if (j < 0)
        j += 256; 
      int k = ((paramInt2 & 0xFFFF) >>> 8) - b1;
      if (k < 0)
        k += 256; 
      for (byte b2 = 0; b2 < arrayOfChar.length; b2++) {
        int m = b2 % 2;
        if (m == 0) {
          arrayOfChar[b2] = (char)(arrayOfChar[b2] ^ j);
          j = ((j >>> 3 | j << 5) ^ arrayOfChar[b2]) & 0xFF;
        } else {
          arrayOfChar[b2] = (char)(arrayOfChar[b2] ^ k);
          k = ((k >>> 3 | k << 5) ^ arrayOfChar[b2]) & 0xFF;
        } 
      } 
      b[i] = (new String(arrayOfChar)).intern();
    } 
    return b[i];
  }
}


/* Location:              C:\Program Files\BurpSuitePro\burpsuite_pro.jar!\burp\Ztpa.class
 * Java compiler version: 21 (65.0)
 * JD-Core Version:       1.1.3
 */