package burp;

import java.math.BigInteger;

class Ztpz extends ClassLoader {
  static String Zu;
  
  static Object Z_;
  
  private static final String[] a;
  
  private static final String[] b;
  
  static void Zq(Object paramObject) {
    Zl_f.ZF = a(22487, -25970);
    Zl_f.ZI = new BigInteger(new byte[] { 
          1, 63, 117, 60, 114, -48, -101, -56, -124, -85, 
          -78, -32, 48, -63, 89, -66, 18, -9, 35, 109, 
          27, -39, -31, 28, 94, -120, 103, -105, 28, -113, 
          30, 72 });
    boolean bool = Zt2e.ZN();
    try {
      try {
        if (Zmlr.ZJ.charAt(Math.abs(((BigInteger)Ze5t.Zc).intValue() % 32)) > Ztpa.ZZ.charAt(Math.abs(((BigInteger)Ztid.ZL).intValue() % 32))) {
          try {
            Ztdd.Zc(Class.forName(a(22480, -26824)));
            if (!bool)
              Zkmx.Zf(Class.forName(a(22482, 23971))); 
          } catch (Throwable throwable) {
            throw a(null);
          } 
          return;
        } 
      } catch (Throwable throwable) {
        throw a(null);
      } 
      Zkmx.Zf(Class.forName(a(22482, 23971)));
    } catch (Throwable throwable) {}
  }
  
  static boolean ZX(Object[] paramArrayOfObject, Object paramObject) throws Throwable {
    // Byte code:
    //   0: invokestatic ZN : ()Z
    //   3: istore_2
    //   4: sipush #22491
    //   7: sipush #-13314
    //   10: invokestatic a : (II)Ljava/lang/String;
    //   13: invokestatic forName : (Ljava/lang/String;)Ljava/lang/Class;
    //   16: invokevirtual getDeclaredFields : ()[Ljava/lang/reflect/Field;
    //   19: astore_3
    //   20: aload_3
    //   21: arraylength
    //   22: istore #4
    //   24: iconst_0
    //   25: istore #5
    //   27: iload #5
    //   29: iload #4
    //   31: if_icmpge -> 107
    //   34: aload_3
    //   35: iload #5
    //   37: aaload
    //   38: astore #6
    //   40: aload #6
    //   42: invokevirtual getType : ()Ljava/lang/Class;
    //   45: ldc java/lang/String
    //   47: invokevirtual equals : (Ljava/lang/Object;)Z
    //   50: ifeq -> 93
    //   53: aload #6
    //   55: iconst_1
    //   56: invokevirtual setAccessible : (Z)V
    //   59: aload #6
    //   61: aconst_null
    //   62: aload #6
    //   64: aconst_null
    //   65: invokevirtual get : (Ljava/lang/Object;)Ljava/lang/Object;
    //   68: checkcast java/lang/String
    //   71: getstatic burp/Ztpz.Zu : Ljava/lang/String;
    //   74: <illegal opcode> makeConcatWithConstants : (Ljava/lang/String;Ljava/lang/String;)Ljava/lang/String;
    //   79: invokevirtual set : (Ljava/lang/Object;Ljava/lang/Object;)V
    //   82: iload_2
    //   83: ifne -> 107
    //   86: goto -> 93
    //   89: invokestatic a : (Ljava/lang/Throwable;)Ljava/lang/Throwable;
    //   92: athrow
    //   93: iinc #5, 1
    //   96: iload_2
    //   97: ifne -> 27
    //   100: goto -> 107
    //   103: invokestatic a : (Ljava/lang/Throwable;)Ljava/lang/Throwable;
    //   106: athrow
    //   107: sipush #22486
    //   110: sipush #28317
    //   113: invokestatic a : (II)Ljava/lang/String;
    //   116: iconst_1
    //   117: ldc burp/Zlqq
    //   119: invokevirtual getClassLoader : ()Ljava/lang/ClassLoader;
    //   122: invokestatic forName : (Ljava/lang/String;ZLjava/lang/ClassLoader;)Ljava/lang/Class;
    //   125: invokevirtual getDeclaredFields : ()[Ljava/lang/reflect/Field;
    //   128: astore_3
    //   129: aload_3
    //   130: arraylength
    //   131: istore #4
    //   133: iconst_0
    //   134: istore #5
    //   136: iload #5
    //   138: iload #4
    //   140: if_icmpge -> 277
    //   143: aload_3
    //   144: iload #5
    //   146: aaload
    //   147: astore #6
    //   149: aload #6
    //   151: invokevirtual getModifiers : ()I
    //   154: invokestatic isStatic : (I)Z
    //   157: ifne -> 167
    //   160: goto -> 270
    //   163: invokestatic a : (Ljava/lang/Throwable;)Ljava/lang/Throwable;
    //   166: athrow
    //   167: aload #6
    //   169: invokevirtual getType : ()Ljava/lang/Class;
    //   172: astore #7
    //   174: aload #7
    //   176: ifnull -> 257
    //   179: aload #7
    //   181: invokevirtual isPrimitive : ()Z
    //   184: ifne -> 257
    //   187: goto -> 194
    //   190: invokestatic a : (Ljava/lang/Throwable;)Ljava/lang/Throwable;
    //   193: athrow
    //   194: aload #7
    //   196: invokevirtual getPackage : ()Ljava/lang/Package;
    //   199: ifnull -> 257
    //   202: goto -> 209
    //   205: invokestatic a : (Ljava/lang/Throwable;)Ljava/lang/Throwable;
    //   208: athrow
    //   209: aload #7
    //   211: invokevirtual getPackage : ()Ljava/lang/Package;
    //   214: invokevirtual getName : ()Ljava/lang/String;
    //   217: ifnull -> 257
    //   220: goto -> 227
    //   223: invokestatic a : (Ljava/lang/Throwable;)Ljava/lang/Throwable;
    //   226: athrow
    //   227: aload #7
    //   229: invokevirtual getPackage : ()Ljava/lang/Package;
    //   232: invokevirtual getName : ()Ljava/lang/String;
    //   235: sipush #22483
    //   238: sipush #23614
    //   241: invokestatic a : (II)Ljava/lang/String;
    //   244: invokevirtual startsWith : (Ljava/lang/String;)Z
    //   247: ifne -> 257
    //   250: goto -> 257
    //   253: invokestatic a : (Ljava/lang/Throwable;)Ljava/lang/Throwable;
    //   256: athrow
    //   257: aload #6
    //   259: iconst_1
    //   260: invokevirtual setAccessible : (Z)V
    //   263: aload #6
    //   265: aconst_null
    //   266: invokevirtual get : (Ljava/lang/Object;)Ljava/lang/Object;
    //   269: pop
    //   270: iinc #5, 1
    //   273: iload_2
    //   274: ifne -> 136
    //   277: sipush #22481
    //   280: sipush #-16530
    //   283: invokestatic a : (II)Ljava/lang/String;
    //   286: invokestatic forName : (Ljava/lang/String;)Ljava/lang/Class;
    //   289: invokevirtual getDeclaredMethods : ()[Ljava/lang/reflect/Method;
    //   292: astore_3
    //   293: aload_3
    //   294: arraylength
    //   295: istore #4
    //   297: iconst_0
    //   298: istore #5
    //   300: iload #5
    //   302: iload #4
    //   304: if_icmpge -> 436
    //   307: aload_3
    //   308: iload #5
    //   310: aaload
    //   311: astore #6
    //   313: aload #6
    //   315: invokevirtual getParameterTypes : ()[Ljava/lang/Class;
    //   318: pop
    //   319: aload #6
    //   321: invokevirtual getModifiers : ()I
    //   324: invokestatic isStatic : (I)Z
    //   327: ifeq -> 422
    //   330: aload #6
    //   332: invokevirtual getParameterTypes : ()[Ljava/lang/Class;
    //   335: arraylength
    //   336: iconst_2
    //   337: if_icmpne -> 422
    //   340: goto -> 347
    //   343: invokestatic a : (Ljava/lang/Throwable;)Ljava/lang/Throwable;
    //   346: athrow
    //   347: aload #6
    //   349: invokevirtual getReturnType : ()Ljava/lang/Class;
    //   352: getstatic java/lang/Void.TYPE : Ljava/lang/Class;
    //   355: invokevirtual equals : (Ljava/lang/Object;)Z
    //   358: ifeq -> 422
    //   361: goto -> 368
    //   364: invokestatic a : (Ljava/lang/Throwable;)Ljava/lang/Throwable;
    //   367: athrow
    //   368: aload #6
    //   370: iconst_1
    //   371: invokevirtual setAccessible : (Z)V
    //   374: aload #6
    //   376: aconst_null
    //   377: iconst_2
    //   378: anewarray java/lang/Object
    //   381: dup
    //   382: iconst_0
    //   383: aload_0
    //   384: aastore
    //   385: dup
    //   386: iconst_1
    //   387: aload_1
    //   388: ifnonnull -> 406
    //   391: goto -> 398
    //   394: invokestatic a : (Ljava/lang/Throwable;)Ljava/lang/Throwable;
    //   397: athrow
    //   398: aload_1
    //   399: goto -> 413
    //   402: invokestatic a : (Ljava/lang/Throwable;)Ljava/lang/Throwable;
    //   405: athrow
    //   406: aload_1
    //   407: checkcast [B
    //   410: invokevirtual clone : ()Ljava/lang/Object;
    //   413: aastore
    //   414: invokevirtual invoke : (Ljava/lang/Object;[Ljava/lang/Object;)Ljava/lang/Object;
    //   417: pop
    //   418: iload_2
    //   419: ifne -> 436
    //   422: iinc #5, 1
    //   425: iload_2
    //   426: ifne -> 300
    //   429: goto -> 436
    //   432: invokestatic a : (Ljava/lang/Throwable;)Ljava/lang/Throwable;
    //   435: athrow
    //   436: getstatic burp/Zeqx.Zu : Ljava/lang/String;
    //   439: getstatic burp/Zgpx.ZQ : Ljava/lang/Object;
    //   442: checkcast java/math/BigInteger
    //   445: invokevirtual intValue : ()I
    //   448: bipush #32
    //   450: irem
    //   451: invokestatic abs : (I)I
    //   454: invokevirtual charAt : (I)C
    //   457: getstatic burp/Zex0.Zk : Ljava/lang/String;
    //   460: getstatic burp/Zl3j.ZY : Ljava/lang/Object;
    //   463: checkcast java/math/BigInteger
    //   466: invokevirtual intValue : ()I
    //   469: bipush #32
    //   471: irem
    //   472: invokestatic abs : (I)I
    //   475: invokevirtual charAt : (I)C
    //   478: if_icmple -> 593
    //   481: getstatic burp/Zbjx.ZA : Ljava/lang/String;
    //   484: getstatic burp/Zb87.Zb : Ljava/lang/Object;
    //   487: checkcast java/math/BigInteger
    //   490: invokevirtual intValue : ()I
    //   493: bipush #32
    //   495: irem
    //   496: invokestatic abs : (I)I
    //   499: invokevirtual charAt : (I)C
    //   502: getstatic burp/Zrnk.Zb : Ljava/lang/String;
    //   505: getstatic burp/Zlab.ZM : Ljava/lang/Object;
    //   508: checkcast java/math/BigInteger
    //   511: invokevirtual intValue : ()I
    //   514: bipush #32
    //   516: irem
    //   517: invokestatic abs : (I)I
    //   520: invokevirtual charAt : (I)C
    //   523: if_icmple -> 593
    //   526: goto -> 533
    //   529: invokestatic a : (Ljava/lang/Throwable;)Ljava/lang/Throwable;
    //   532: athrow
    //   533: getstatic burp/Zeub.ZT : Ljava/lang/String;
    //   536: getstatic burp/Zedu.ZL : Ljava/lang/Object;
    //   539: checkcast java/math/BigInteger
    //   542: invokevirtual intValue : ()I
    //   545: bipush #32
    //   547: irem
    //   548: invokestatic abs : (I)I
    //   551: invokevirtual charAt : (I)C
    //   554: getstatic burp/Zeqz.ZV : Ljava/lang/String;
    //   557: getstatic burp/Zv8d.ZN : Ljava/lang/Object;
    //   560: checkcast java/math/BigInteger
    //   563: invokevirtual intValue : ()I
    //   566: bipush #32
    //   568: irem
    //   569: invokestatic abs : (I)I
    //   572: invokevirtual charAt : (I)C
    //   575: if_icmple -> 593
    //   578: goto -> 585
    //   581: invokestatic a : (Ljava/lang/Throwable;)Ljava/lang/Throwable;
    //   584: athrow
    //   585: iconst_1
    //   586: goto -> 594
    //   589: invokestatic a : (Ljava/lang/Throwable;)Ljava/lang/Throwable;
    //   592: athrow
    //   593: iconst_0
    //   594: ireturn
    //   595: astore_3
    //   596: new java/lang/Exception
    //   599: dup
    //   600: aload_3
    //   601: invokevirtual getMessage : ()Ljava/lang/String;
    //   604: invokespecial <init> : (Ljava/lang/String;)V
    //   607: athrow
    // Exception table:
    //   from	to	target	type
    //   4	594	595	java/lang/Throwable
    //   40	86	89	java/lang/Throwable
    //   53	100	103	java/lang/Throwable
    //   149	163	163	java/lang/Throwable
    //   174	187	190	java/lang/Throwable
    //   179	202	205	java/lang/Throwable
    //   194	220	223	java/lang/Throwable
    //   209	250	253	java/lang/Throwable
    //   313	340	343	java/lang/Throwable
    //   330	361	364	java/lang/Throwable
    //   347	391	394	java/lang/Throwable
    //   368	402	402	java/lang/Throwable
    //   413	429	432	java/lang/Throwable
    //   436	526	529	java/lang/Throwable
    //   481	578	581	java/lang/Throwable
    //   533	589	589	java/lang/Throwable
  }
  
  static void Zt(Object[] paramArrayOfObject, Object paramObject) throws Throwable {}
  
  static {
    // Byte code:
    //   0: bipush #9
    //   2: anewarray java/lang/String
    //   5: astore #5
    //   7: iconst_0
    //   8: istore_3
    //   9: ldc 'Øæ\\bÀ`ñ^ $\\t»DÏo\\t\\fmså ³Tñ;}»jbÀdÅå<d'Ú<rK\\tWg/#'
    //   11: dup
    //   12: astore_2
    //   13: invokevirtual length : ()I
    //   16: istore #4
    //   18: iconst_4
    //   19: istore_1
    //   20: iconst_m1
    //   21: istore_0
    //   22: bipush #76
    //   24: iinc #0, 1
    //   27: aload_2
    //   28: iload_0
    //   29: dup
    //   30: iload_1
    //   31: iadd
    //   32: invokevirtual substring : (II)Ljava/lang/String;
    //   35: iconst_m1
    //   36: goto -> 202
    //   39: aload #5
    //   41: swap
    //   42: iload_3
    //   43: iinc #3, 1
    //   46: swap
    //   47: aastore
    //   48: iload_0
    //   49: iload_1
    //   50: iadd
    //   51: dup
    //   52: istore_0
    //   53: iload #4
    //   55: if_icmpge -> 67
    //   58: aload_2
    //   59: iload_0
    //   60: invokevirtual charAt : (I)C
    //   63: istore_1
    //   64: goto -> 22
    //   67: ldc 'Îµ6T¦¤Äõ/'\\t¶?3­1Ï½nª`\\rÍª¼ìÀC`\\fBPÍ.}ÆwÀ¼Ë2Ú¶à¬ {¨ßiËMîA&E²iE.3V¶Û¨J©lüsJ½ü-Ðô¹\\t8.WIti½ªpçÒ´\°¸Æ Æm¡²ÄøYEl+i®~{[Â6Ølg®ºfý³Ne ôÜ\\f#-ÍøMÊ{]3KLXb1K#úØå<`Äç3KUt»ãQR|úw-+®MËõÒP¡ÄÒ)fzRÌhTÑêýãlë1ûÇØéÊYÙÇâÒådoÞ;l4±FõäÌ³-D9Òâà"@@úvfsãìÝ"BpðüûùíJÕtñÎÐ1¨nH¥GIßàm9 ;:\ÄÊüÃ vOO6ð9¶Yý*CÌ\\b4UPÖQÑyýÇ/ßÄåâF½³ÂÕ³×gÛNåþ¯¬sTÉN´­åbãü]z\\rS×*Ê®©«é6¬ZÉëÙâÚæt²÷kIVT7øNòÝ¤ÂÁeÉÎë9&uÍö*Rcß]48_o$;OóäE¦®;[ËÚfSË=Ä*T^Tê¹¥î­³$<\\b2£eÕÇw{hö­ÝvxíBq8×L<×R=üãD;Ët6ØC\\tò\\t ¡2nl®ôërEÒx>z¬?zâsw">xîÌk¹³Ì×ìpêWiPq÷¦¬9<ä,4û)ñüdúÚhõ)(¦U`Ô÷©é¯ô¤­¼7Xýß,ÔÐðIèýêì"­×kô[½]Þô@\\nÛ0)À©TuÝ¦QÌAcoÉþè~ÁuÁFß~©ÇäúÐ)\³SØV®°»ÌòU¿/¼÷Ì¨2=:ú_=A\\na­4n;î<ñHCìI}³Ë\\ný@FL³¶÷ò¿Ê;Æg´\\bûÎvI.YÑ ÆØêýØº+ZC¹ÅM÷¯<­éM}ÂYæ*ð¤ã¦ÙÜÔ|5îP¹z >L _£:2\\r#bDKÈuÐv<âçjÜáPæÿàÖ*z1t\n²á×HÕZ¾Ã¤Òv'À¨*9aS>Y®ÝT vwÆÆbóSRp,üªfw8)IþeÞ­\\t`³/¿Vñ«åÇ¡á¼²\;I`UÒ¡ÏwÛDTà¸èlù»õ\\tÚY¼]Ù2 ÞmÛ>Þù$\\bajXÀr>ªÌJ6DÊì¾ÕÈïJïæF*ÐÂ)üä;ËsáJB?BÐñ0Ù¼­%xï PDïÅ]ä: .D,béØà+;]^f9ZU9ØÆÎ°ÈáÇI,4üMÎÍ&¤Üå´0ñçaß{ÚxÙ\\t!Sc×À·H¯$l÷:¤¼ V*nlh°û qv<'iÚ#$l¸=Ã¿rþæãée¸Èh>ê¨,³"Y\\nðÌ\\nVé\WuZx.Í%åsÌ÷¢*ç>y ©N²]Zîp^ýñì.½d QpLùÉ¢zÞï¯Òæ ÝløwÊí+&,RenÔv`v\\fbädñ\\t}n|«\\r"w%;ÂE\\rùòÃÉË§×<(_æ<¾á"Bøø}¯ô©KÆêÂÃ<·ìº+Xú\\nø3wÇK´Qæî¼Åðl>9¨Ø¸^=\\nK{¡úÓÉæ}!´\\bâ¹>rëû¿bõæømå%nôÊå\\bØð¼]Ù$tTîâICÌv¼gÕB³\.#éæªÂo\\tbÝÈbíZ>·ØØC\\r¸®zóz¢Æ®äî,ÙÜÌ¦ù.Zì×A³Cdyuá±t#zTËx/³kÉ¢ÿzÌAfYwHÏ#Ib°\\nì±|'ð^Z jù+ÌüT¿ÐïçkÞ°È¼µczJ¹+¤¨¥Ë=<ªXìBtê°³`ÂKü+s¼C¥Ã`3ñ¥ðô¥êØuLO×üp\Ë´_\\tÉ5²ã¹ÔAâ[ýpæõ§¦~$àvb§]'\\nûÏ2#Gi%5ø0ÞT0MIkÊ*jñùýÇªÀ®ûV¨æ>áT©%,\\nFÇZçG æ)oþ«(kTmpWt©]pêd~Øïy úþ¦òévDo+¡@Ë\\n·³ü69!Ú­©Ò%ÜxX@-KÏ¨1ÇU³KÁ2Èä ÂGkp´d¬`P Æ#,­îBP+é{×êëîìê6IhþââßæZïÅdòU«À\\tä}ZçíÐHéØ)°ô*<g4õóYê^sÄÊe¡\\tåwwL¿Y-#¤ð;À£o*{ÀÖ== ãí\\nÎ-qÆL8__ðzE|SäÑdV{±ï£é\\fë1b{\\n»i«¼¹Ý¶×i&ÞlÌïÖ~Õ]¼_µÈ*Ø½"æ·Lõ^¬*eû9"zÉ36å¸Ë4jð`Æ>ØÜ¥{¶øbÓ²TqCYpÈE±QiëßýâèK:mRy<ãsUÝ-\jaî:Í0{}I5B\ù"uãÎp©Ö£^eðNì|¬;FïírbâvßýãoîkµjDzÌMéua#ËÞ­4E|5ñE/ÏE´<¹½X, mB)7(H1Ä?ÖjÒ¨.wBöIz:ëÈù§í³¥x=gâõQîð=­ñï!#IG<?ÎxÄ½é?;åuPx´åÿà]ýrÒ¯vÚ¶.\\fòÝ0ÙÚµF<Ô%(ªOD®èógÉD l YÓú7ü·ÓjyHÂÃ¶mÍà0Ù3Î ]BSxdâÏÜ.¼§«)ôUfµÕ`1Öxn$prº.AÒwbÒôC¶ÇNÀ°éù=S~¾b"ª©\\n dÖí,îÓ¿×¼I.]Êã@ ]¦ç«ù;)/Cn i.ÄÄí<Êz"þ'âfgÒv9;±å¶2Í)znQ-b¶!QzámWñ^\\rpGsùWÐ@Óe;ðOÐÏõzY$ (Ò8µókRu]{8«~Q¨àGÁÐÃò?lã@]J\\n,ôÔhÑÌÊ;då¥ãeþ¨l="K6íZDêÿ[ØÊpæÜme\\bN³ÇÎ%¦|Åm¦Ó\\tç¹ìæ&/.Ó¨-B¨§üh^º;¤Y¦HÝ¦9q1ÏJYs^¥È¹Ùëîìú&<7-ª¤U\\byÛ8EK.I\îÙ"7 #3¡aN\\f³ ãJß§È«Ahu[~\\n®h |X¥ö~|bÙ}Â÷G+ÈxÓXßJ=Ð\\t¦lùÿc\GÑÂÎ\\néÜbeñáÝí8t;B´8ûpG=ND Î[³Dõ\\rÈ\\fEÚãÍWâJ]è«ý'ä}}ÓØe± L&~hYül[kª:Èã¦£O£¬Lh",-¾oAÙ¯7c¬cJÂ`yØcNMçWÛ}J·øw-3C>BþG(§Þ;\\n[m>°ë\\rM`·X-{Øôx@£äaæF5JÎÒçHV±ó¨øcîúúyXþSöé;÷[~s+RòE¾ ÒqËF\\ti\\rT|Ù¥ªwLZ@úêU1T(w*ò±u©H\\fÁ]Uç¬3~`Ðbüu#¢ö ç}wq2ýñ\\nÈÚd½üTþ¢ÜÊbJ\\tÈJ\\f k5S_YPïãày\\b.øO]t \\fóî­ìÙ6#(§±ÿÄ0½\\t7¯ü¦Dõ¯þLI¨ú¡AhbþÉ´dVHî¼$æÿ2YÙEñÄ¸MÎwiâôíÛnâÈ\\br(©¾³>kÊg<·7b­"; \\tvÿ(7ØN¨õùâ.c8Z]Â3#T ]Iu"ÈÅh²áÏ¤°ø¿½Î0ªÆL_­ouéèG=#õÉeÆüào®ìQ ßô gIm­¶MÐö^¼ÒL õu\\t^Ú'Ó¡Õ/3/ÏWæMïNih ¬àPÆu|;J©Ñÿ¤ñgA±W[ªX«hÿ6",kìlªYôtgÓþ]ì´¶¾m!±Ó<¨¹s\2Zd(þFõ+ur}ÛÌ*c«3Í~Ãÿ0ßòà½Æî~Ú÷\\t³³Ø\\tS]²áÂlLÞGãj©l¡w ûý¦À¿r ®÷ ÂýH$Õà'¤»\\bPAsç±°·_Ü±^eS>E®yQ¹YÅêå=O¼\\tÛÖ>^Ëºd(êXJÝ-F×õ~|C¦í P[ñzQ¸hlÖLÃâ¶Æ =M¤âÖ$G]~ üýÑg07j' 5oÛ5h<¯\\n^£&8ÕUzx=]ý2"äµ±Q»Q*ßP H©¡oªquV\\r H*\\rHI©råg½3PAÌÈX¤Fê]7!tê¬X¾KyIôE\\nP¡¶~ÐQ¹íí{ÀWbXªÅÄ¢7JýÒ¦råüÎ5òùa\\f°É¬(©Há|ý7ò_z}r[)ÃnïÅïxG<6}S¾³r7zS¶L¡Þ ×(Y]¾Ôºç¿îCdÚæB;ÈWaê0 þH%Ç-U{Lca_PK2,Âø¥SnD|¸xgw´"<·¥tâÊY!?âKòÜCºdÍWG4ÅØ ºÊ:±¯6ÝkybQðr¶ëÉ~CÓ¦w50ÝÒ/ÛJxqÇÜ§vYõ;Q±ïªh4QLÝ¸$¢k¨×C² öî§íì.íqÁÀ ñápq\\tM+[O)xÛ8í*Ðr>Ð][¬DQ°_ã¶»§¦ÏÔ840h (Á>ÐFZòÚÂlé£"Ür\\nT\\nùÑô\\rûL{.¸~õìâë#'Ur³qÿk¸VU~É\´`ÀùóÄa¨èQWµÂÁJríÛ/àT*@Õþé{Î³Ù$ed#Dy¤QYwg³· Z[s«"¡5õ¼}p?£úÉ%Ëp®ß2D©/¹çµºï/v/îÈZ¼ PÈ­cÆáA¯\êÛ´ï;/Äñ¡sMÎ<3.JäÑgæÍ®F<2×SYïVôàÚE&wB+w>bOñé°Váíçã5%ñ "Ð(Ìw ç,CFôÞlgÈ ¢Ì¬±Ë´<ÜsÇ:fµ/¡S`Á}oò'E$f60[-Vq°®ÿ\\t~MâÖ¦©ÝònÝöNØ½<ªwfhe´s«¿Çc;Gj>-Ñ³`PÖ¬/¯Ru¼äÌ*:Ä^ØkIácº®·¡êÛ·²X£¨SÈ÷îC1ãëw24xº0&d»QN´dLöÍ¥Vþ\\rMP¡½[ïv|²Ý(ð´ûºÍÞèâÃÕ¤àþNÃû·á9}BHx9ÏÍÜ¡¾U©>:ZÕÝºf¨"ðÞ:¼2§D<pE&&Äg/Þµc¼yn«öà9ÀÖüQv[ùc4 :Ñåfîý_oç8Êü\\fÃÉLËÕÚeÁpË¯¬8Ä`W`5Vã2[:AOÐÐÍpø\\r?àDÝ(·,üT$¼&É¡+Ùz<#¾¶=Ó)D¬ÍMöOnÎ½û6/uê&-ODµ+Ñplµ^±Ù ÍqcÚÁ¬N¸ÜñÄÞ6ÅÞÁ\º4u`ô¬ºïÓív«K6þw\\rÑ`=8è7)æÖ,6ÞHX=R¿bÑý·oR¼1~¡Y6»'+>ãÏÓG$#;Ä[µ&îå}:újíYËØ`´>v;Õ2ñú¨Ï×`[hÛ²Èäú\\b#Í'?1\£mUÆäçé\\t9Ïøf©£®1ø\¿¦c9ãxÓáïßëbrPæ1â7\\nâVCt8h«ÂÊî¸.Ih¡ë;í\\b9Í,L*Ã`ÃôIÐ5à>I(ñêíóþPMB¥TþÑ ¹`|:Ki`ûfG\\nD§B·, ·Q\\r¹Ø÷6B|Àî/FÖ×¢÷ÒI6SÌßV´Ø\\b¸6ñ¯bcUÐx\\n3-cH{ÇýÓ ¬þÑ$W³üFÍ/=`êQ«A E¨ªw¨òä¢Ù,t\ç!¢äz×Q'sÎçæ3º£¡ªã6§?iÊ¾Öÿb:d)¿J\'í½áæAt~í·H÷¯[k²ÉD*/îÒéM5Ó:Qþ¨­sahP4yË,tþ'VÌª¤ÅÂª¨ùÜ¤¥KÂÚAm¬âxw89ê¬^²#pcß4Ò¦g"IûÑ°;Ý"­sat:½acùA°6uýI.êÜ#H6¸$]8o\\tùSs®o!:gß\\nÂ\±Æáßúð ÂÅ2=Â*×gÃ\\fçÂ ³Ä_>ÚØ¸z?oØ\\bÇ%\\f¿ÛÄãý¢·@÷ñt|õPLn~þ¯tí`~¸ÄåWã§½½äE\\fÊü h¥,g1òzbYG*'À¼r¤j!ôpÉ¬­/$±ÈÙ<§­$*ïp(PúÕóâÑ½h·\\bçÊqðrÖUÂ\ÙFMþôÛ©b·- Yzß!?Þ\\r"é;áu äVoÒÆÙò}ÂÉ_*;>(Ûåä»³ðÿgÀoSï£#FptL£Hð|¯¹YO\\bmB·Á9}¤ÇDk}"X)/êõ­n+¯w»|Jdó *ùä0àWV3Q°0ÙêÛÄj\\fÜI,ÖµL7z?GìÍÅåèH!ÞVJ"_5ÌÈ¿®;ÜS;BÚ©à¾ü¢ô4´øÍ3}yÝcMí­9!âI©C,°fðÏª\\tsR&{ÂFµgH-Í¥ÏÀ]Á:õ>÷*±å[³>kñÿ³ñnSõ%_ájóà7êôci\\nj_Ñ¦pKïª$LR«ZþU{ÓA§E<¬îà²kL\\t ,N`M­\\r È_Cé{ü½¥$û¶ ©ÅÆ¹yhà¶¹+HÏoÀ¥îMEËyµ È ~®5¨X\\b<û6¼C.ÿµ½brïÝùþn½IËøì wM»E]¯d¼~ZéS"ºY9Mê]W[å<ÆÀ&X|®Â*ÚÃÎSAuÙÍò7@NøfÐÉû° ù¬(".\ÛÌtÝ9}J1<ä%÷Ík230¹ká[xKÎvÚ\\n?ºÓ\\t!=¨Â½Ñ³üNÖb+gMÂ5éE9æxÄ[¹0ôË/|ÃEÕÇÂÿ[ú¬²³þæï_)X¿#K×¼ÕãËU>yy¥í¼_@Ô¬Ä9ðÔ¼Aø´àJéø<, uâë´êèi54röD@%/¡*=q:&Ó1ªN 3r\\b»þs§»Ù%\\rGña ø¨¨ÆlÏ!ûÝØo¨a`¾6ªo[*Âl7½«#*rai´\\f¶¹Ðÿ­ÚK¹°Y"Õ!¤L]Èö"`&ÎeèôÏ%ngmÉùIþLäÀTô¤_\\fçõ^kØ4Í\\f\\n.ÌaÙÉ0E|ò3±ôÝÕÕJü\\f/Ô¿BjT]cïi×|°ÊÕÁ'?)¿Rt)£àèì¿k¸×Æ[Iëu¢ù^» ¶ Ô×\*)Û¶5ËÞ}ËNÉ{ýA#ñ»!uìâ«.E:!óè.öuÜôÒ@ôüÍ(ÏZdJÈ÷¡.fXçÙÀ\\r0÷¥²+í1·NßéåýÔìþ[ä+ôÂØ¶2PÚåúD@_E_¯ö]ÙÑX×]AÀ_Ô÷õ9¤ZýC23©³=¶J«Ã¿¸$Ùâ\\n­"íÝÇj½O×SnM-®ÇZñ¢XTp,ùéÜçM¨Åû×ÂÙ¬Ã<æ¿{cLÙKÝ`yÍãÈîä´xþÅ$Á{ï¸#ÃHè35`6G¢NT1¸hê8~Ì»õ_é\\b4'Ý©ft"óxNyªçÞædoúc`C6Ç J¾ò¨e)\<pÒèß¼Oß \\nR)÷nu­­@tævnâ²'-s;ê½kRTBö¦®ÝDâIâÍü3Ýûô²|2Ø+H8%þôXå[üifØá3exèªkÔ ±È0}&ëcJOJñ´ñ aû_@*38jR]B:Ý°¿®0ÿÅÌm²~­ÂÖk\\fI¬ò1nî·áo'RrFêô²Xè?ÕØÁ Äæ"Á÷Z8ÜÎ{õ¾ÒÄÙ¹"ÅÕcÏZ¦n°åoÕ;kÈkq@Ó\\béü%4±G^.?þ¼SÑ]±Ò(¬bÍf,I6ííÎFLó,á<Wºûã¼È¶XY¬åÖyï¿gjÅµX`RºÀM­ÄÑ/8}¼LÜ¸@øÿ\¼¿@²k»·µÀ¯tÚ²ê\\b[ Î¤&e<¨iÀ$³(&Ü?chêDi"G\\n<¾Õ/÷L;¹Ù¹ù\\friwa`b+ EOëjÊ×'÷ÝÏFs¾>À­eæ&É*)çÆ»H8Âçª$«ýÖoÇûüáÆÔ5Ñ_4Ø«FãÚU®\\f&nïvÅ¢~oêirê:×ÇäÒ@¹¼#ò¢Qe)2¾ÙÕ­ÏGðúúåhÎÑ¨I(G@Ò´çê³#Hlh)âó$ª:<t¾ÏBÁ£½V¶{Êv*~Á%ÒæPOb¼æÂª@K>R¸¥O_ýZV«q>iÂ;¹@uùÌ|?²K^½Lº¶ßÓ´%¦íäõK(Ìì&\\n6 ·½ßÀU\¡ð§Ö­K(]ÏcT7od¸7fxFâÌ·ï»«]¬6©ÞSKc²ã3:&vXJúD ³;ëxÿ§ 5¾´U4îÅ>@ïWpÚ¬Ô¸!Ö#ee¾Åä«¶Ùç*)÷è W1s8TRx0Mø¬Ýßä¬ïíº|lôÕ"eîy\\bA±b1Tj^n;Hn$ÆJ5¤Í_zÿîåÉÒ³ÊaÛdJàñ0#bR3×âÆï@ä+I0)ãóìØçÃ":»ÄÉt@tÞ¡!L¹\\bª¯"êr:O! #àÙÒªåF{KÃ=±fÊ<È%Ð&¢³0B0YwðBÚØÎ/?î?gÈ°²7XÃò³Ê¾§¼çTèáªØÂÚm°¾?V\\na°w0RÜ§í,ÕL÷î]xs¹$¶ÄÉ§â(_Ý|NYG9*z)@u(RÓ<uZáÞ¶ÜZµ \\tÏ¯Ì N.(X4Ib®Ñlùñ¢iàÇ[ûïç{ð³z+gràS<\\nuÔ\\nÿ']¬Öê¼cR*\\bB«{ ¼Ü²_T,u¢6YÉ{29©¸ùVAôöý%®5*yïÉ¯ñ\\tS $óà½Jåå\\bÅ¥û\\ri%¥eèîêsÇè³³ì$ôelÝGv?"ß .S8vÈÑ¯K@§*WR0õ©¾µ÷Fçé0Å.æG¢0¼QÃGYïÈê¯\\t^P³²L\\tj¼fv?î]¡½±Ûu0éüNB¾ë¦\\tó<´¬2×Hr^Xës¬­¾¸IÊO\\tÏûò\\tQ6`ÄnÛÍq87G>ììUECôPE]üu¹(-É5qzl×/ÚÜN\\tûîCâ>\²ÝI¿£yj¯,f¶Å*\\nÞ·÷¿ C*wpåFy7ÅA¤c¿±«co^w Jð«"<òÖ3-A"\\nîßñ&z3JÓ=&»àÐÕ{{86¯FqÕCä æßÔðSpoß ú1HÏ(/ã\k¯FäM:,/¿¬¼âyDË\¿£ø¦ÎRîU¢É8·q\¥Ç×x|Ãu&ÍdM%.¾\\nOÎ³íèÃº)"óLÂÛÆ/Yà\\n¨ü²Oì¾ÎÙP®óÂfôÎoyòéíF²~AQ}ú-dý b¤»i,jÎbjg¢IÑ<#\\b;¹Û 8}¢|Öõ%¹K#Á¦ø~l`«»p¨V&8~bÌ.È³ÁSÉ½gì8ÿý~´±[a#:¸1-Ñ¸»7<jÓgí,kF43·\\t3iü·uNÊËeµRqß;ÌÎåºÄÉÎä:4 k¼ V7íQmç²ºGå¥e¬w ²Ýt|ßTÑ\\tD?NKQ$)wr!3ÇÙÚÆb¬L+ë§ÜÅÃjÃÚTñöéµO%]íc¢>_2Ä×½¾aú©ì;òZúëÙ§{K®!C9¦bdE½o]ñ»#¿yòê`È¼x\\n¹ÏÃÄïû}ù£!ÖÒà u­RPÍ(>oü@s¥P=T¤èaC@b,·ÓºHæ=ç00àøÀdÀt½crè¾êtèý¾ðÂÝhãýÒS2¹I:|%÷`w72²kÀø5xÏ{Õ®ÆÜ|'\íî¹Hrrù&SNE½üù¸ÆnÈÎ]îa\\nà5`DÍ5÷Å9*Õ?æ©\\nSÂ(r0ÏJôLÕýÄ«Y·zXâCô3Êä NXZdØµ5¥¥L{¿µë <úvtg-êD÷/© rë\\rµ±®)^!ÂÎ«,çlÄ0+Ök÷æ¯)$«º\\f\\n=$iÑö§ð%t§2Ù¡²ëÊE­ì6Û|jáLBmC'ÿÒ¤q_ãâ³xï,õMCOý£ó)ÒóÈà9µë\û³¶ÁÙïkÖÕÂ/¤\[Ò±Íc¶VróÜÄçiOUr}XÌ\\bº³Ï,G¶×¾§Ák9­uÂBÑH©F£L§FD\°7¾6CZÊ¶7vÿ"ÑÞù©c:@o(_ÑáiÃÈn 4VÃýFÜà¯í×@\\t_è;Ð$ë_#â11`~l8$yèVäM¯óé#Jà}ÈèÎXÝt¨9(µ´\\r"òrëzÊ1DÜ$µZê/2'\K wù\\b ÂÑ£.u#¢ÞEå\£¨zQ÷TIÂtßÙmâ\\bk¥:i\\tT}ïyÿ¬\øÊ¡6¯Û»U¥³¶kÖOdy¢Ir?X\\r}¼ ~\\fÊ¦ÃÓfwÕ? Ã7åÁ­=ïÔz,õª2)oùr©rÁbóó! ?=¸Á5x¶àfª»ûö­¡ÈGîB òOä`¨q/>týDEÓ>úc¨DÓÞ'ï#NèÆ¡­°$Z¥ÇVAV\\fÇ5é>eêimÇ æ\\f»|¹ídLW«x .{:góWuYùÏ?É®£,BvOðWß:~2i=WëNÏ9ù\\t?}äa¾æýéi%È)¼îõéñÁTÃÖw¼ÂÛhxÇ\\t3ßãÖû$½) \ª1Ã ÓÉ¿?VÕ´õýlÈÿµ;\ïéìè\\r±Õ»Î-tý>PË»_A6ý6þéChÜAîw\ânÝ8.ñtûº]ùÄ_ÕqÓ×yêøÓÁþW,´%&î3³þâ´¡9#@aT>íùÂ[x\µ} ]3RRé\\r®7ÍÒÜMüáÔG@ú(¼+±áÍqÏÖ­ièÎMô#øg\\tzÌíD¤gSP)Ñ6Ïíæ@@)C×cæ³ý5·h¶ÏÝºÉ z°¶Ëñ¾ÎW¦×ó%tÅ^ÑÐ¶®mÁ'öÅYùÛe1÷\\f\\tyµ16Ù&Êó6°8¤«%Ö¾E-­¾àN.HyÈPB:¯³ÌsÇwá¼Ð©®Dab³Â´Öù_{k:.èÚd#âã\½¿«Í\\\nw-¾Ã]g®ÑÛI8ùæÜÆç¯Ì¯\\bA×ßµî£¿z ÷Þõ+R*jén]j08_YH*×7\\t²5Z}&­<>ò.n[ÿM.ÃÐ^an\\r\\nÄ«mg ìÅ¨á\\bÂ(ÙèìI»Ñ#$òé6+c[JbçT7{cM7Æ_<mL2ÙÒìãKDÅ^±rq®bo ´»bðÑÛ~±nJ< ùÛuÑi`m¤kÔã8×Ð¡"¬~!nËá½cPÿöE¬jØe5h¢\\rzá\\tÕ|LC4$ùNY÷5À½Z°á%iw7¥p-±çðÀ=~K£0ØÛ_ ù]Éô9Re'î\\n©³¹Ìø`MCsÜòZûW?mjõÎÆí/ÚL~p³J>S.ØEÙIìå\K¼ÜdY»§(IxÕov×q6Öî_Õ¡¹Ü`ÏaØ+ør©2ÿê?©\\ti:tªI8¡Z!]¹6¶&ÃSkþîAçX0³ðUÚ2®f¼¿¥dgóAö40c©è±>q3©oLØ·ËþÎÝ0®\%µBVº>(M>Ò_øËñ¥XûÆtTÌ¶¦§¶HÿØ\\rT+õhÅ=Zh×oaÊÁË!LíÁ²A6p/®J3¼¦~às6¤È8÷B°:&ImzÔë ©Q·¨p_\\fbEX7wwoü<A ²ä;ç@qxâGúfHÃ¯7×Ò'¹ÍNNu\\n;:Ðp#\\b2d¼Q'ÎÜ&S<º@EcXéÒR½OBí(]ÍÀËÈ¡_ÊÎåæ;ÇÌ¬æÏì'h\\n×p(Îuëý©}ËË«:µ Ï.ßÏã|Ë¼ÙIc§[\ pw{z@òZ©ò$!>\\f«^(ÝI¶_³àB\\bì\\btDaÓµÍá¤OjzÚFáWäñeWHó¹M$ïrÐè7³§ð¡Û'àíD0^¤0¼ºQå£\\re;âûÊ1¥!æúÂf6Þ¡~À0ÛàÕ ¿Ó×9*{w$i|rí^Gï²á®êVo±8Ù¯Ë&ÔE\\t>.,R`@QutÓÎ­ÝÏ¥TkÔéýá:aPlxg;æ¹uíSY¬ÉÇÐLÀ:¬e{`Ûå·VV÷ö¡?=ÍHQ1XpuAäKË6«Ò>&ZOp(é\\tÍ[y0¡R²uå^ÌãOÐæj\\núMw>BíÞò¹9¦ZZ5ÅÅ2\zzû-5|¤Í\§øéa¨VÎÈýÅx³Ñ¶\èkU*°ÛÅÃô¾êR¶Lyþ³ø&ãÛãçÓ÷¢¤z:Ihnxåz º¯ýß)¯H¡÷=ë»ö\ò~myVsäFÈ!sNo3\\rg¡jÀWÍ?\\tI£wYwãz¯çëV²âÝ½Æ¤àvíÃé$sb¡¤Ð£cÙïü÷È^>¶½J~Ý¾}éùd\\b2;Ö3ékÂ®j±Ç]Üy|RÐ  _rbôU©{XÍCÍÐTóºÔZºÜ¹3)jbárÉÃ^þ«Ï´bäÎå>Å"_g¦bµÛZ PÆx }´ÆöÊ/Ù¦7ÑúwÔi[Âmæ\\bûmÖ\\b#®u HîØSL²IÈ:éF=½Ä(Ö\ÜÐçúY^Kw¤Bîà$ãM-/û>5ÙÕ½@rôßpc¾GPÉ}K5Û%Â+U³ù¡0òyô%\\fæ\\nÀ5ÊÕm=õÉø)Vö;ÿVüzÄjñ`í&øCo·ëÚÚÐì^Nd`oØ@»Ý6À{_ßÂð´PDêÉÌAã>çÃªXûÕÓD¿S® :­h¥{Xßp®53=²ùß*²ßökÃ> i½ä»¹°¦À[nÉÝmþ¹ó-U>GÐ×M¹êÌ¶?QyZÈ\\tå²z¸9wás§½u÷C|ÜCìÌÕXDR!0ÁÊßwZ©sA3ÀÓßa{éå¦äsðÄn·óÍ}ñ1âÀÃ½4Jß¤F#>KSÖ\\rýè FúÓÖÊrRPT3ÉÎÂÓ,DÕ¹¥ÎáX­GÙ¹s.ñe¢Ò·]@·þ(]ÝóÔÔèjÜ»Ã¨ÑzéêzÊCÆ@H nÌ±1ù#¨X%Ó³S[¾,Ùõõ÷j\\rÜ\\bÁ­õyýÚ\\rþë=7à©/kn\\f1:ÏmÕÿ­Iïà\\rR6áÉÏé¶í§üf^zßË8¹\\n_ñLûy-sÙA0éå²ô§2ßÿâW£¤D£4Wyøø«´ym4Å;òieäÚÚ6sÆµ.uÚ~âéTp[H#\J|óÆÑ¾&+áFûo¡Ð^MïçÒû2n\T#¤ÁóNf8Ôóðg¬=ÉUSÁöýyx7kVÔöÜk4\\rý?\\búªèzÅ\\f¢áþÉÓ=ÌÕ.äqðï-(nçÕ®Ù1¿è.³Ö:\\te)½jbfPfí:5ú4ý: å\=úh~Æl¤¶=Ußéý·ôhMõµ_Ðói ¹»îÏ³dY8¢Çrý±'¾É\\frgøª=9÷sØ2PPÔ3® åºJ»`¬\\nðb,8|^Îø½ÏµþÁöâ.=Sì·Ì#ôµÍ¥që\\n5N!æUù<ShLâ_ëp1­F\\nd|EÑ°9µ"åär]}À¡"èG¾ÂQù³X- ºHË\\tÉGyÈâã/6RX½OQlS+ÖÚì¼gýMÉý²k!´m¬^S5ÄTH¼:Î40\ÃòDþ¼ë¸7¯ÜH{xÅþÆ­¥aU\\bT é'O3@§%)©¹)ªÑ®ñ¢âgÉKÉyý]{>ü7oÉÊiaº;If¾æN\\nå¿ñ³>0=_ä)Z[`á¸Q}phÞâMÊÍþzì{=H"±J«¦ÂO­è:ßó-ô: tm«ö\\bÍ)ìÈ^2Æ3\dpd3þ?G½rÚ6®}½¹46Ö¸å¦ÇýLÕëúÅ¯åtJ+íä\\fôm zkð £CcjcmÎíÐ}²àµ~ìMF©Ö÷eó_`C`YZþ4i0úú·¬Õm]æV"%nh ¾Äï®%³ ¢ ðiß;<_áE<°x§¯Ä±B v÷'Í.7 0eï5nX>Ù[\\t¬§Lñ¯³ÊVï·1ÐÆ6(tÑ{Á5`¾kXaR[Ñ4CÏ¸59quñhibYö1ÖH)­ ¡ýe ý4¿wCÔa?ÂIì¾W^\\nÀÞ%n¯-¿«9?çHË0ÖðÔ·ð\\båðm tËh7MÔ?O6vÎl_vTLÚæéeM³ú Gþdè]³´Ì»Ç\ßå×¨?ÃqkÚßM¢(Ít¶Í¹âêÎÁÿ¡Ó~ÛPùÄGasÒeìÅÙ(«D|'ìÜaiæ¥kÀmk½¬©N¿_y5Á9ïhOùÆ;Á'íÄ9h"ÿ}v8£ -âFèäíºv=(E©=¹MÍ¤¯¼a´°Ùu-ðÏacQ ÇÉÎ\\rîâM©²¼ö¹i(6¶Dvíd÷=#S¡bø»»â² ¶M×ý ½Sc\äÙI*-S5$Ý~\\tl­È1ë«È»ýÙcËeYdÚ÷^\\nÏ`Ü¡SQ1ÚÁtÜà0öE&?Óù-tà+Lþ¶S>(*çËöø0M^_0y¨P]vs#nkÙ>+[µ Ù5¯\aÅ\\nÇ*³óUùXTì4\\bç ^¥Mf 58íB(¸ëØ°Cþù_Ìðÿà/aÈ¿=ðÚ?õø£R r{¼^ûgí)÷ë(ÔÕ2Údðð(ðh÷YÄÄ?\\f\\bYü`ïöÞ,@s\\r<´m¼Ö\\nïá8~j edòaC¡ûÃ6ý3ÒëôûßxBXnmA^ÍÖèÖÕTíSÕTÖë\\rû¯ghfÐàØe­Æ3ç%¨cÝ7Æÿ Iã´ÐEî"è±zga}»`GQ)@j­F{ÒÛæMXÛîþÕFñÞûø»ÐM45ùyµf4æ\P¤®±gh=x¹bÅÔè@ÌBFjøõÁPIG°K¨hçI¾jx±áó3á¢|öO\\f×çìº¬ä,ÀµEökºHJW\&\\nÞ³$úcPFIµ?½»«ô-òôÏL¤¤ip¾§¡ÙzÅM/*ÏU£NÀïLyQÔl²\\t#ëñÊ*ë+\\rP'z_GÇÒpëùKLw¯\\b¾¼F`ß;»éÎ\\tÆ\´¡=i'°»ÂtFÞïÌ×¥«¨n L;;-2uUêøc©%ý34c0t(£l@ ´þ_Þì*ÞA_ãÚlºD! ÐFâé`>Iîr\\tD¦1@Àï¹?ð]&áhÝ¨ØhÀà$0bÅM©{4]g}ÍU>)\\t â\\nªu;¼z%!_Å*ª8/j,köf7Ä=§gnÝ._¯\\tqðvXlÜuQzêÓÈLaz1¶»ÏPV+4\\fòB÷l¯ÈICEÒ?ý8ÌÊchrõnK%Â«·R~B\\nÛ÷Ñ«ê>&Él3çJ >iÛ,sF[DáÚºÏx»C«RÿÉ:%ÑIô\\nqÑ=%»©.Å5íÁ¶$,ëª>rÖ5533º§s¬OD7D+ÑëçZ;»ç\\bÁ\1,\\f´°Gü~ ¸®³Iª´øG¢¬wnUÒiGXæX³Å\\n½@Cé\\b¯LðK;Ñ^¬\\nêm¤Yw_lò¤ÆÌk6iY£éúRÚÛ6\ø°oèB¿ÏôhÈU®ò¤gÏQ3<æóì]lK[&ðra@GwsWwùE ´Kõª3YÀæ`WÎííî£Ó%^ßÀXTbÑ¿¬³\\tæÙ¢VÂÐ¢[ù%ªó"·èèù)'`i\\fì´ÄfXMæ-$miÛõ¨Ç+Dð&1dl2EûLùB )¦ä¤ìBñ,:lýaæ(÷;W­©Ê:¨.k'é#g$DBÈÆ»s ¯ãþFkiu|RüK>«]oÁB$fÄq\\fÞf6n°®pëC*$ï·¨%ï9Íµd°L­×s\\bêÐÚÚ%æDµ¢ÒDß¯R|ßÞÓç'¸N2£PàûÔ¦©èFzB;ÀO/\\b1®·¶î ªXøpÿÐ«¿ÈûhÐx0y7Àdÿ«[=ê\\r ÿÁÑRm@êPP<oÐ\\næPÅi,-´VØêK¦4h±À\\bp¦«ia¸©ÄëíÏ>\\nùHû4ïJ,¿ÿgRÄ¥,óÍ>õ/¿þuÁ(}?*ÕÐdþpDvÞDÛ¥ä_æ _¥üî\\tÞ!JAZn\\bKµ¨æËªé74 æmEyàÔ6¿R\1ò§¨í±ÞËÒRà£Hyv¶æÐâü³aÇÊéÅËèú\ÂlÈ\)ªü§³ã*ecy¼®Í`@Jg2÷éB/oQÎ¡*h½`Ö}@mtÃäm.§È_4ÃF­ªº~à­±9ýØ¬g#µB¦eüÀ\\baº÷ÑÜGsb\\f~JõÛF\\rÐZ½;ø½tO[þ ¿¼ý^©hÒ5\#u¾JüÏ"J'jfòÛø7ý2!ýú­G6×jÅ}<v$LîËI§íiM­DÈñdÀæ$kôô®æXPë««{Cht°.é¼ x$Ð¹¼)?·@ÔÍWP%!û\BA»ëD'\\f\\b'{£Ý#]NæH©AThµÁ÷¬ró^ª@]eçMÕ¨Î:ÇxZ\+ºeÐÎu?nÉ»sGë¥éÐ$¼ÁùpùÀ2.ÖíâTäE¸\\r*<Ç\\rl¬OÌÏ¶âÏy,öQ¿8FÌÈÁ¬XÈ¼\\b\\bõÁTzÛíâÇo7JS¼õ\\bX9Ì|Sê§¹ÅOÌxpúsÚLÛßUâð é~÷lØ¨Fm%eªß:dG¨Dc\\n+>`êÄ\\f±Ï²ÉåêÆïVÖ>ZQ;çÃÝâJ9odB^ãX\\rrÜ2¥ýÆød)yZÝ"©ÅÞ»é^Ñµ­á¹|5¦·wÍiBòJïò,.ÙêD§¯Î§,$;Ç3u:hZ¾M1ÆêØÇT\\tËr°í²¦¦1g^B=±/QÇ³êUõ«:x5gí¯Ðt=#ú\\n`Ü5K5°½à!,pËlåáQY9òånÇ¿iwúÖÇ:Â@åNà,©NoÀ[ù¥ØëÚm\\f}ÅxåïÝ\\b&"UùÉÙÊ*9ü»ÊB$¿_EÄãâtÐG©¿ÁjÊCò}Â¥Æ>a»wu;Þ°&Ð_®ªpÇàWÒÖíüOõ¸#N½®=S½²)iyÆ\\t dC©I\\bõZ^_¤Ñ¢(\\b<;T¨æÏËL"&-Èt3¿ÿÆþÿÉk"ê¢bü5=PáÕkð>ÝNAñfý§JÉg,ûÇ]HjÒ |ãµ ¶kâ!Jûjõñ¯ØÿvC­PGMýýÉ\\t/9¥i«ú1:|f\þ!À!ßG|nF×|=¤qÖ&êGíâ¢!N^sfh ýÁ½D¨Ê¤½æ6QÇ&wÚ<E¯¨"´B3~SË" ÁöîÞnì@.)"ðà²{Ñeð)1ôÁ«.>XÒY}µ²5}\\rXÒz ¬M0.°=+ó$&O¸ªÅC4áÝ«ð Öý°oðÃ&û4AñO|yÿJ!èþYneØ¾3êè "~*ä!!i°+¾F²T²¡ªÙ*|ì]$4òYº_©D$.m\\tªKõD®×AºÇpLZVJ=èFDîMaÿ\\bæE\\f\\r§víy~è¥ì/® ¦\\bb)þíNÖó?zyË¤0V_åa+Tw]ID@ 7XáHt¥e,U¬áw§ÿ®Îi9Ü"¡ÐÇ\\b©¸ð Î¢òXÿ(Õ#ÀòâÒ14ÞÅA\\f»q¼\\f-Ú¿í/ü¸\\bP®#<:ËðÓHÇ:tå\\rºõõß÷`fz5¹Q¨;ä¸=ªû´L6(³$%&9®ýÂkf©^Ù÷ö£Ç.ZW&ÕèXfA8É¾\\nëÂQG¥áÄáÉw¡üµþ^\\t&ó*)JcbLÇ´ù-eSÑüË,D¿o\\rh¹ýè \\ngm_Ù~e®o<ïÙ­!:EEðF½ÞØ{Ì{=Ç*ÇÐáÄ¾ùêªqç~¢°})8ºSfXm¶°ë½ÇyX=7ÖWN 7úôÆHÆÃ|+²Û=Á6-C°ÛB>êäG\\t Èu8ÆÎ[ÿiì]L2ùÂ~Ä:9x\\rM't@ðzüf3{ÜÌ£î­x¿Ê9ÜÞK|H¥¦(ÌXÈÛÓV­aéiüv}\\fsA6^`Á¥[úSÓj¾D\\fü²ÿ~3°ÅûÆÂôË¾dÁ°0\\fÇLí©²^zu°c¾®ücüº\\rçÌð°µô»,yÇÜxªû\\n6ùj/­a¡$DÖÏÂ9É2 vÑH°±ÉJ¸»Ì)ÆnÝä´vì[(¶×G<ûû¸Èq×Ûícõ|5´p ï~ÕÐ$ÇÐr¦mÅ7ÐrÄÉkÂª#ôÁd±÷²8Øå¹ =;î)@s¹ËOw$± Lç]ÌXq3âRSGÖÎñc­:«ê\\táçg=aÄ¸¿hrýNz`ÀÏ\\r$Þ*GIfXx}aÖÈ"ySY=¾Ô=6âÇP U¼VÕm<rë(?AÔm;MT4½K,!"ßgy°Ê±ºz{|!\\tRÃµ«¶±ñ)&/a×8Ô4.4QËWFÓ±ýàPé±^)Ü]xåc»I Yÿ¬ÿ|êñB[½Pï?0 w.ÜL¹)[Å^Hæk%áæUÈï\\r«ìh¿t1ü'Áp6V7ç{x° õäK r\àbñ\É(¹È\\rÄÑ\\fd5±ab¼z>`Ö-f%ßVQÏ"oÌI¾E)¶Ù×Ä)yä¯ñÝEÁPõgá£!f\\nwÍé\\t18Ú1¥Còd&«\\nm¿âýlE~ìoEë+9¨gËq©Î­áÌm~ª£K pJ¹\\b²¾3%þ1¡Ö|åö(?õéKbôØ\6E¸GÓ¸Iv^YFXqô?EY¹ÆÅw^:ßIsv?ý§ÎÝo;äT^]à\\nªZ\\n\\tR£êCÏ¢ÕªaÕ½À\\rô¥ÿ®aÌLQÊf|â3^Ú!Ø{<©­¶X¸·R±DÁmàC}µ ¯^¡ár@V°FV'¸W¬ÉA.Ï¶\+ËÑ)\\r"ÿ[çTM¼ÇVG,\¹ÃÿÂpêpfY¶?2Ìu¤ÍÒo#xeÞUu´ÃWIÕ¾ÉnsùrQbì |*È\\báìV²66\\b.ªÍº\\nÃ`û¿(ÅÖ]Kz/ÞïåFAÚÛP\°VúÁmþ«ÔÀÖûÑóJ\\n58äÈ9×-\¬}\\tóÝ;}\\n\\t9Jè5È K"¸¦¬G¨o«-NÒÐ*Pï®Z\\fçkrïÙbû5<yx¬ÿy«ÓÅo\\n4·1þñò¯ä0B|ý¿lÖzmNe£Ã<Sö\\nyÞ3ÌS\\fÒ>F^3ÕòzæxK|hY»`4aøÊ®Ü|à.)8m.,(.ô¸+C{hKÌ]üßÚý`¼³`D\\nt°¹é´-Óv7$éo ý|oóÀ4V_Ën¥kZÕíÔ®T)Ý©·ûþw8tøÅþszzËx g¤7O°n©ÌähÍ\\bvVÙï¯j!¸ÑW_ùîµÓ¿rÉ¾Àõg®ïaÑ%*I÷þ·èÃ[abêoã@¬®|ôlôË;aQðaâåÀÆAøæîë].1ûÂ=ÀafÊÙÚçD8 Ùv´*DÄðÉë@3rÔ¥Ì¥ÿ¼é«1\\tþOÇaý/û%ÜLµ.üäOÕB¯ÉÙ@¸þ­½%³ÚÆlyµÌ»ã°ñÁô\\fþ¿EÌW6ªËdÈ/âhê¤uhZ¹ûð#ØZxÜµª,´&º)\\n1fØñîG^ÍC.Áu¤×?hÛa½G2ZíPÀZÆÖ;P¶2pä1z<'z¥}æ)ÉÕ®ÝJ,Fodßçãi·cÄQÿ$æh`pK]uYñV¨²Ï¢¥yT}%*ªá¶©\\rí¢BÜäa¢(Ö-Ê0ÍÛY/!½â+údàiËG°e)É4íAØà®¢­¾ÛúÖCÑÿýèqúúë}:É,ï7 ©%XH\ô³qÛÐÂ]#ÙÁÒl¼¥\\nM°!v{¬Zm;¼4 Ò½*´MYºæ¶$ªçv ?ç ÖYc/qQS-¶ò;°-+IýNäñÒ&9UÙóüí½cJ ë\\bøµï*Øåh½êôïñi\\f§hãrbÊgRµh%ûù»Z¼<úÔ=j2rLe_`9±zT.:?Î´R 3ñúQ­Ò©0Z§\\r¾`¨Ø#E¸Æýºî×ÓÔJÍ à/H6 Ó°!Y69K·%¶DæM8ÇlB$+â¿Oör¼On;ûó àÐV±³GLºx-¿cÌx=MC¼(n=¤Wb7ñ½ò@ÒuíÆèÄEýyúU S\2å¾ü¼i),í0ûvZ¹Ð'ýÎ\\na[Ñ«T|¼ËÙdÊÛÜj>ÜLÕ\ÔÖ¶'ë.=Ú8`Â$cæ¤~ûðí2£ÐèGÝÉ ýr»2©<äFYuZ¨¤;-1þ\\n[Ç'o%{· 4°%Êÿ"&ÖÞã}ØÿÆuD«n"Ý#j?7Ê#\\n¿´è2¿ÕMnaã*gs½k`ÒQ¯±Põú>ûÕJüÐl­Û2¨Ükþû²£uïZèZ¿JÌÊz²fK~Ñ´Éq%ÔüÜ+( \\bÚ`÷½õCd÷pm\\føI0Ï+¯Þg´XEe=±ægïsÂ õÌÓË{¹ò³£ºÎÒ>»÷\\nDèÏ%djÞáÉåÆ<JÕ ¥'Ïv?òYbWÑ zÊýº9HoG:ÐåÉÜSZÕp´ÚðYeæ£_zý5Yzó+ºwïáæ5©3FMCDå¦\\bÕ }»{kb¹G=o{"öË3-þLA¨ZÝêf ×¦÷ØêqöÙ¶âQ PöÈ*©ÁKNo¸ª³yäa#öNÚ'\\r¸à@¤RÉ~`óû\\r"Îß¿Â´¬OÒ4Ìèz2ègYA îä=ßq%ç\\bÜÝHÎ¯rÜ\\rýN¿(x@ZàTS[ßÛøKDñ9Uhxê!Ð!è7=©(ÒY_ûì°ÔäWºòHËxð³\?ÁèogªÕ§q Ì °Á(ÁFu£õý¯¥2õäõZáùt7§ST×¥_´YçÆ+2øÆ:ùV\\tDS\\nàrúé¿÷¤\\f;¸¼Ö½c\\rìy~0ûf¤DºÝá³vRËÛb¬>}[Ë#×µâ/5G¿wÇ\\f×ñÿÃöæg2Ç\\n>;;BO[v!Pº°ð>æÑåPOÞ¯7í Ö¥«,Z®{uºµømÉ÷»zYL¾òùjJLþLsÙþ±æ0{d!>°^<Òp@©h¡Ðð»¶F«TÃ2Àºý;G{8"K:«QÃ 'Ï£Ëj´.rG<Ç:9rhSOF_õåôYFèÚ\\rÏÎ<øZ´¦¤zËgûHi»&\\t*^ºN¦àôØ^ªoa4Ö{:cL?#îk×> U\\rÄ9Y#/AùUû@pEþ+qËNiîÅCú¸eùÿþÇÑ%8)óÁ\\rô:ipØe`r³ç½Ö¬\\nß`Z4®7FÖíÎ¹j£=8eÝW°ÏJÓ7¤3(^J'*x¼=ïYè1{?O¯,\\nÓàg (SÞ@ýÒv%¿Ý- ¨#ZZ,5Qº¸sN$!B}-låÀtmõG³0³µ©'[]°e½n¼¹Î0PEhzÔÒì§Ôé©NÇ\\b¨l&Æ>cÈAc$ýÕÐVrpJôg¶îu(¢oiYFÝ¤h§ÿ¯óÝ?=)=1gä+¯õWF²øþè»$lA®ÔJ=Qh§ÄþÆR°¨ãEB^.\\r¸r©$Õ­ýÅbî¥ á²ÐµÿÚYtµÚGqúqûÖ½àU¼ÿFË´¼Ý)o·Ôm]å/¸#Ugàh+,è}ò9.ì[ÐK·\\nðo¦ørDw-v8òÕ"çöEC¨© k}TZsaAâjÜ¼BÝ´,/NÂA?7ÙTY"|0u®í~6¿´;V¼­Y`Ô²]¸gÝæd)=Xt6"lãXh%þfR2é:î5Y8Úr+¶\\b¬ðqãÐ·4*Õy¬iªÏxÄsÖ_@_@5ªÇ>vJÔì\\ts´[|ºÉ\\fcRöÀ=ÇübÚ71z¹é\\r02°IL~=Û^Pdº² =YOp¼îÃØAé8JåÏÀ\\r\\b»±¸/å6&òð/\\rùâÂGÁlÎ«Ö?þKfà|âcyJª,ß¼ôh±î[m'A\\tçÒ3Ûïx%Â¶Ý vì-ß7HÚà=@¨B©´YUlªôè¦)|iV\\tü|°Ù.qLîãþ³«äíV²e !eÀßßuQØ{­Ùäõ\Äzá0&zÌ-­ý~zù§³I¬´¬Úó®:6c¶þWÕà8÷6W~ðÖÖ#üÄî}5\\r­"1smÔ<É3ÕñÊ@©È(ïf`3»÷¦ð`îÊ®öa¶VÊy4DÕ`àZ-Èã\\tÍ¤}éï]2Pf ZðIfw\\f¸¡]QÚé8¯P¥]ÇëJUüÝ ßÊåÌ'±`ÀtÇõ°eý¯;ÞÕ.£T`@´\\b÷ì8¨=£­+~«uIí¸`)üqºëVù13wþ¦WÊê>ICAæwËSw¥yîõPÕ©-hæG:\^À*Ø®Ú;ñ£DtÜOô|¶,t±_-h CÞÕî÷¸l1°ðÐxÙ8.3þrM6ÄÇÓ^çs; 3J-¾sJÅ´T<Ù>¡õ¢Mç­¤Ï]8 ðîk#$Ix"³¯|£:m±*ûß¨´ÀÞJ+þ15¸z :Ä/°üjâËò\P´\\râåtúÝá!oLV¯½ï[»`ôÙªä1N4\w6¢ÇøKü¸°ÙÔó\\nBt)ö»ø/#Þ½Gñßõ]î¹%K¼fnâºùÁ\\nÛ\\rÜçTÃ)a(l³u\\tZ]±"u¾÷{áÒUÉp8Ã,_©Ã»×Õ»ß¶xh©àé@adRÚb <µ0*éñÖ5»\\rñ¿ÏÝçxLepÄ?ÐÀ©ùê¯FàäØ¦6aÊ!Ùt»2ÅÇÞù¥®²Z=³@èHÏv³ÿ·y´6ifµèU%­)6ç¦-}ºtß55ÀË1oæÕ¸¨\\nÍñÁUÅWgCÂ'±*}RS3¦©=úJÏ!· c+º=>u_áÀöIÐ5Ë|,Iæ­v<¸\|FiÝÎÞéðñ0ÙU0\\b_D®DsÚKtSÛ%Î\#©+w#y² Äò\\t%L´\\b»5JkAyl²=C°WL¥}ø<Un[ò ó\\rûL[Rf:âaË¸¶ãL!°w»O x£¾Ñi§~v½NomX­WÊ0f.ÓO?ûRâ;HJ98»ÕÒSw2ÝÕ ¡õÁeQ\¾H1º×l*^JØ?üÉ8°¾ÿ8äÅ¢]k t¢\\r½ÃBÙ3~õÑÊVÍêDÐË§Ô]pK|`¢¾P-À\\b!Ö,n}Û\\r2ÿ°êã¼ÐþÆ Gñ/nkè®±r£´·øÅåe¡LÓÚ8³£Y÷èoq½e VÀ$mC­Õ÷kO"@<KÛßz¨ÇÊ91y×ø­øß­L²çZÄGhDbÓ0× pwdÅAüµoM¥Ù¸b]lV[î¬6êè^ÊYi¾ÀIøÈDDÍõÀÏ¾F|¸øà/kR{[\\r`?ÛÊ:\óÁv´UpÊyÙ@ßé;\\rÃ`ëpéºv¹ýþÍ,ÏøD·xT^~ìuiædGuñãü!-;Ûy]÷£hëþÃõ¸ô}V?É©ô ^7ÔØÅþ÷2ÈüN°òÙõºYÖå+vÄÀN"ICUXèãàk, Fê8}M^÷$ËKAÝþsÏe%ï8úÀ-Îhö½g\\t0"ÕCúYã½»Hg£t'Ô;?'r©É)ÿÇ^Þ¤áÕþ¼¡Ü>iq_"(b\\ts\\t^(RºZý_ªî5Ïg÷ÃbSûÀF¥¸å£@Jk\ã `£¢Ñ3fJ\\n\EÄóE½¶[ÀýÈR\\n(´BºÿD3_@ÝG¿]MÄ¡ÉZ`QÕïÞýl»¬|e[vd¾-!©K]cÒ,õ*aÔ_ù ²õ\\r q°­Ð¶S\zf¨E°Éá/'OÚÍ3½,bûÕ.)\\rP¢0Î\ JÇF§Õ7ÀÆu%Ód¨dcöIEªlé[ýõëóRÍDÓ²w¤ÑÑ&kå#WÏìï§÷9y¸µÀfsú£..Ô×zïjÍ|\\t8¤§þ?3»¾É¢[þåñJFe`ß8VFl;å¥¸Oû!Á±=zÝÙù¢EúNpDV¡f`B+'JýÏ£ã^º!.Ç¯o9ÐË16«Ü ¶Xsf©¼÷ß\R7s6t>©Ñ+PZ=ÚÆ\ Ñ(½øêã1AZQpØ»ÇÏ=åáâíÏ¨ZVdl~õ©:;XÀù¿IùD2.wg;9ÚÕ;Pª¦Ð¢6Lîõ´úa¡3H`MûÂ³åõOª~ab9*üÊÖõ\\nWzÖ8»KÈ=èß÷cÏD.1ªó½­ë'Á ëIÔÚ>?tª¸XÈt¦¥KøEZ\\rÛ¥ÙË\V££sEâßMmozyî£ÛHÈþ(¦ÍtOTÛqtÕN×¿úºnRA§-\\f3Æ±ÁÄ²Ê;¼]¢XOm»!{\(<£ªëwµ¨°±J})FãÍÜº7ÉZºw;-\\tÓ1ÛÚ] Ïà»cãRÁqËêÈq$LÔPá¼õ\\r§ËäÖHB\f y²ÉÚ®>röShÚèÑRnt_bðÁ¼ÛmDzæt*æUø?UfÖ³*JfIçZÕ-Átûõ¨³iêÂñ±*/ÖÜY¶Ì}v4i¹[òòÏ¾Ýë½õÑ éÏq¹>£÷Z$ ïô>.Ò£\\rJ¨\\nÀ8ZUÓ"¥ 0o\\fÍ9Äþï¾ÈLbuÓ9ìÃØÚ@k»Mñ¨òãùc¶þ}8)Êâ¦¿aè{qb&ÄtÇ%ãÛGÆQÒª µÓÿ'zÜCºó5Á§¼nêø|þ¤ùøgb2[ç yøÉûÃY`cÌÎÙJ!~Ír?¶!Îÿ?üÿ l$~®çg\\tÿá¥TXô&[o ¶-,,lÊÎ:^¾¥¯Ý1ºH\\rug·7Å`¯¹VçÏ|»Ò"Õö?H³¢oÙ|jÁ6Ý/Üª\\bÒæüÄôLSu50¶¾Vô¨µ)\\f" \\n&$û¦Ñ&N©ì0îÀoÎ»OKå?jù!ÁµBÜ¼yé2¾þx8Ùþèüní/ïG¾nN¼Ï^$"QN\\f;âuÐG¤[|ª7Sá')+½UúÏ¡Ó0lÎÖ±!_`i*OÇaîJÝ\\bJ<ô¤X3®x2¸Oü'5Pe'`¬I0Ö(©»ï¡×EÎI)NZ¦DÑ·õz-¾ãÑì+©8üñå-k=ÈåÙst²Áq*k±R­}aÑð!ÐÍ÷UY\ÍdY¦ù]o=G=5¡dÁõ³XÇòíò"­!ûÒ¼ÐÕù\\fIÂ5¸&à&mo'ß÷*ßßqÚo_ÛÎçÙ¶:#ÃÙPØHfÏ&©twüK.,«.ýd¬ê:FrØÏðÀè]GuI\õÌzÖÁÞ`ðñî¡Ã Ý >×>¼ðqjòGUá-Ôl¿Æw×AÇ>ÄEæâ°¿ÌÓôÎ±ÿËÎ·%M¤Ã¾Þd.3c¨ªÄôûAÓí;pjFQFë.óÇ§KM!OZðy¸­¥åÇh\D»%Yí\\bÄM*E m²êþÚ"ÀýÐHe>8½º9ÑÑ¦à üûélt\\nº6\\nvSÙãmOÜA³n¢íÓlèr?+ò,ècã~Ç¥Zâª7ñk þ7Þl:xhá43Oª) }2uÑ¡õi´`M4ýëtìk× »Cëtùö¹¤øßîR)zôiùí÷EÇÞô·ï¼ÒN:ýª²3{N2MÎO >E÷î@á¶EG©çò Ö×z\Z#Á#a<ÄvÅ)£â¸ýð;´§ÓfL6×átör\\f¯,kQ®XÚÿEKWýy7°@iÅgSh\WlQõÊ\\nÇ\Rg¹Z"]læà7Û­V®,é(g® ©A,Æ\\n&\\tñ"õ ®z½êß~E::)bHd]Q+àãÞe2QÒgUé@ÀãøØ §J"´àµ"z\\fZÂ\\tþgj¿:f\3gf0bÉ£R]\\bLô÷u~¥¾í%7¼³d/.ÆÝ^,Á/Ø·IÂlÙ,áÀ1>6ÝÝý_Z j²éYÿeòëë7«±¡m¡¸÷zðL$ÕL~}±ò¢Xqè>1_e°oÁ*¯â+ÁèAh{êa6LµýôÄÐoUç,éP"*×õîb}¶ëvÃøl ¬OªûÅ,>Ð¢\\rÍ×ßä÷I\£ç«|b4YRpåVÙ1T\\fHNw9§@®q`ÇÜÖÇÔæ£,å÷þ]nðaÂä¼]z]2^t3oCãóC¬©jºlãN¿½´ü0Fót^I¾ôIhªhÞÅ=W²ò@Ëï\mkz.î|I:¹gæµÜh?Ö51§õ²}!oG©@~(=_ª²~mäó 2a\\bmÓy4»¯ñ5±zfSÙx\\rïÖÊÄV×Ó!ÎOz¹¾§pÄÁG¢ú2Ö\\n·DnL'ÜéÆµÇ¨·X®ñÛOFi_my=[Ò'd[û¯idÝèÚþÃ¬YÒÒ³3~^ÄÙ±¨ÔK[A¿Òj1\§e½Ï }D¾pù3]®*èê°õ/æ2]¥âÇWaý¼Ýa.>YèÔ,`LOü¤ô¥K¯^C¹åxLÐÞèÊ+Ô;CÌ$ò°¨ÐÌäôQåtFày²§)ª\\f¢F®ó;GCùÏBZ¶26Çã|Ùt¶ôw¥;pDæF!­WCYUrRU] =!ê§¤`Ê0c\2À´%Ý@Ñt\\ra¨ä¿ìjfs]?Ôf«Â­5ùMp°ë:ÌÓ¤åÿQ3LÙ¯\\rëèÈæ~Yò dýÏäSfÙ±ï8´T^J 5_Ê=ðC&»DnQNÌ÷Ð¿V=ÅÊu¢Ä'ór½ã"ÅÿÔµ¿\\n\\b&·ßè\\f\\ndcx÷ôdYVù¼­íCv l" õÌ¤ßÖc'd7IíªøÊ"½]}s· ãÁ\\rl\\r67Jùü-DZý¸Õá qE¦27}Oþ¥&È5PøDc[1{LÚ+óNò3ÄvMîA«[IºRd{~£ðç¸#` BæX³OÅëh&óíÓïJoþøö]r¹6åÔßDXc4¯Ö~\\n·ÿdá Îå ½âa\ÌDÔ%ÙC\\b²sBC=rÞc+^¥ÿÍ\\bT£ØìjÚ ±=AzVÑ¾ËÎo:swrâfDT§<T³vª6W|V\\b,\\t,åk¢Áé­I`/WpE¢6m*°úÙ¾4êüp3s©Í¦ýò.§{Vñ1ß.[§ò9Y>`dË¾`Èb¢ø~ÞRÔ¿?0#¶´Fwº{Û 4vO½Ý0à1zôXÛ¤ð&Þ­:;3¿4¼zZÊfSGÜÿÃ|h&ù8TK¶¤5ÇÂ&Oý¿#y»+ÚHÛp6(Ãn"M¥äÍ¡gL"wqkC¿oo#[Ý ëç¸ÕÅ Ât·Ï{dÎÅx!oü^°\\fî j·½þçNÃíYnÎº¬4|pÌÒ±ë¤ü0×ôvÝ\\fwòÃçXÂög:Ûþßc)µµ¼­PÖ«Ô¡£Ì©ò0Ò!»i q¯yMïQ«,V¤Sc8.³Câ÷¡iü!Êí¶LáåùÒ9veÞq&¸±ìnöN64§QrSMËÙuû¿S¢¼è^EIãE¨·ù6ÝC;_±¡­Ï2¯é=dð³¨o0Å.ÏAÎð´(+Uã\\täWé`B%A¯/ü­Eº²ç#½l}JÌ¯GgÆÁÉ\\tÕs³1ñB×HÔmÄÊ¡ïjÄá©àßl?u_ÅÿP[ÓÄBuÏÂ;"\\f¸AÕ×mÄ?£ÐBx¥"²á.¿`Ë¸}Ó*1Ç¯Æq²ÈðïàQôÜÆ«°ÊÃáúÛó`¨O²ªò3uêb§§\\fäÛÜf[ø¿î|ZÏî1=&U²º5ûS#% ?ß¹Ëù¯Cª5MvLÆ³Y¹º«\\b4&IÛ§eËÖ<?°+"XW®ÝEä­Ìf l¦Èjl,òA3ä21¡¨Ë±÷Å,]C~ÌÇ\wû{øÏ#x+´WµWÒÿ0º3×Þ¦ñåd^NÀÿó÷jØ´×]$F@t²\\fKG\\rïñÅ?1Odº1]SjcLôÉåö}Ó£EyBwéìqÓäD5×½Í·r¡¾\\rözÙÊÔXþþ|f¤¹¹DBm£5zû\\rQjÜØsOXJ!e¢wöº[u0UõÏ¨é¹ÃjÏ)0u¦LðdÏZK¨n*3#¤@ûw8 á sà#2kIÿCÝ&cfv;ÐF£Åó½Ê`ÃnCj_UU4K!\Pèyà¯²êZc\¶¤bÑù%é¯¹ùJ³I´%?øST³Fó3Ü^§>ó¸0/1±ÝÌÂ×Å 'Ev+»RP+ä ël|jXfâ8RsDÿïÀlqÒ6Fó`æÖåÐfáp¿Gß5æÔÃnó»bëmökâ¾N£§$Ë{6Þp{ºø(.²{ om<¥!\\r"ÿ(½\\nLÓÑüF"Âlã`WÛ#}Bïøh\\fêNª¶ðùU~§áf3lY"SßIl¾ìQÏÕÉ¦É\\bë°êpÆFÌ´¯Ï¥Y.FÒÆ_Ù¯¿WYôì¢K&s£R'·ÄÁå|ï'?¦TòîD»n_$rG%éfìî=EÖXÈu×Ñ¡fè¨BYU\\bó¦åÊ\\nWsAbP7R{¹cýHQ$ÆKúE¸I»<Ã¤XÁ3Ä¼¦¬¹_@v¨Wà°=Fª8Ñ.]Ä¢\\fÒùÙ#G+I{C^FÈÚ"PëªíÏ¼ÄwáëÊ~VåÃ´¤{µÉ3õÇQA»ªãðßôp®ð¾E,yÈ´ß^ï1)7D ¿¢Axs¦U×~?à+(h¯` ©zñ£&$1fP\\t3º¼ àØ}YF¢¦XwÀö{~b¥TÅÝ´3«~E£fªÛl-MÇØi±ò2ókþ¤Wÿä&¤ÿÔ$]Lx^sv"D*¡Éòj  S©å|Ý$Q<°é¯;Ïú?KOu­ûh¡"¸ÕfÑØYçÍª¬¯Úã¸7r.\\nÞ·Cþo$ü´G]M¹~Å,¶õ9j½ê ùx*ó® w+w2©*h`\|\\bòÌhÃ×·ôáÿk|¯¨°b\\t$7EËâ©R­rñß··|>ÒüJ¹^Y7Íx´uä?¥\\nJûoÆ\\níØdWXÕ7Ê-¶ô\\b3ðÏÀ¯ÃÜ]:­¤ª*D÷T´ªH¤¥À:?(ÈR.Å$ ú=c;Oc&Aaí°khB~å|í5N\\bZ÷\\fàè òå¹ÍËâDÓlaábî,ò¸«Âö ¥ÁÂ%èÚ\øÄRLm¤Ïi}ÐúÔ_HX]ìÞ\\t¡°.LØZD|§0aáïìÞ¥&¬9KXã,@@8©c{qtggLÇO=_,Ñ:&åý]ò\\t1EÇD¯Úæº\\fu½n"ñþ6è2+J<SÓóU¾m-ìÛw"cFZ".ñ¦|#rñï¡øé³·LÑê1¾cÑsåKmÝûHD;El+L/µMäp%mÈ|:75@ÿîK¨)pÞ% w²¢oqkSõHÍ^\\fû4Ý.Iè³\\ri"3¬æ>\\r¼¦ Ty\\t×WÎÛ½ø§ DÕÊ»ëtíB÷(m/r{ÎÙTî`\=Í\\tº\\ntùººÒ«[v¦\Û¯1ô¢NÌ½}ûF/äwp\\fðût=ã\\fÈ¼W¯IñHyø!ýÂE N½\\bÕ+dæº2ÿý¸¤VTæÝÝ¹}ÑÉã2<|T2fÜÇ§¿2ád#o?Cfû¬${@£)£ëV¸Õß/ I»uìäÊ%vV'ëO\\r_~BfJ.ò )ÂoÔ){_B[@?öÝÏD`ÛlJüj0¦x³à8~ûï)\D×/ÍÅÏì*ª°LùÝz;6^/ùÃjËÉ2ÊëÛì\\fÔ(AIc{M¥  ühß2å£vkÜ:E-pA?{ Óÿ0^ùï\\nKSä!{ÅJ£sC ÜL9:¡TÍÃ××¾x¦8èy5dVk¨EÕY½bÓº¯¯9ÂGÒÂÎ¸G$¢Ê>®RAÃÂòJWëyTh\\fp\\\nó?£¸Ì^ÂÌRA@gÑ$7£'¬¾0¶X\\ttÓå|Ø,@¹zGr³í-32{OÙ3§_[o`dÏî\\f:V·T7ê³¹} kÂÿñÃ½bvâôyûÚMe(\\rv]³ý\\r¦e+\\nAá­B¿Ê)Nßº½»\\nðÕEà']qi,ëc®ÿ¦§fauÍ(IP}EAÒo§¤»¼rOI"juÌD2N§ZN) ¶öÚnk úÉ'@¢pÖ¿oâM:íFGiÃ8díwC\\bè3ê1Û*ËákÝÎÍþ *Ï¢©µ=Éþã!¾½Rolé1P!×ÐÊ¶c(9Ü][Æp&ÿfðdK=Ò=iaRtÔ´W2ð!¤+k¡LÛtî(RvÉ°õn *å 2Ê'æ~s¨FjJ6T'øªú¶ü¥;\\fÈÓ½z¯çgåÑ;O\\n¸é%\\nvË¼/Åª$F[Q»ëVnIIr(Ïä³èµvCØ2õQä \þéá¦ÒN×÷ó©]óY`ôpn/¹ ;qT§)S\\bà@M@>ô]+áÊ©ñmy<tâ9<Çlg.ìÚ{ÍÿTnÓÀ\'TØìõaþyC¥¨7|)ñv\\t?¤5å60Å.å|ê®ö.»MaNÂ5ã`eý{nøá^ÁLÑ0¯ðù g3KXI~µdXGK´ý5\\ràôCiîñ:Ð¦ã­\\nYZÝ!Æ\\nÅFäá²!Ã'u-õ}PQU¥ßeôäÒ÷2äÇi«BàVÜæ÷¹%$:£ÅHúRÃ÷ÀÖ\\t/w~í¿xqáÒ©ªñÎªÀ»#y*ÆUÉ(m!Æ±P?ûËr¢\\tv*vß\\fIÂ.(ÕW\\n\\tYB×±H<Ëÿ?ýÌ,fö0`uÇ¸°m>4Üº[Åã°Ì/NÆ ¿9§lë±a\\fnQoþ»iýc¼\\bð!Vÿä$î×8lÀ-âç\\bÎu'ûmÞá=Ng^Ò\\baÈ\\rÒNc°5dxÐá}cÓE3|ñfÖ2ºìÆÍÄb©eæl´GªL4>m|Ü¾à0òþ¿ÛÈÏ3B ûU\\f)Ó$ÄWD\x81>u¦<G Ì?Ê$\\tÏíàN4Ù5Í(ã®ö»/=¸èýâ mvÀ<?\\ný$Oþ¾©z]Ü\\fûÃXûTR*ÙÈãiÞI>ÉÅùT%óÀ«¥G1Ú§Ø¡ÍîÖÃÕ7®EÜ¸ck¾ìQèÃWI¨!»°îþOß»R§;æznÕ©!E¦Ö·;ÜU;rW^©SC7¾ëPà{kBXi9õ°7ß2É¬ò;Z1w°Æy3;>t|ÿ­\\fýªláÙNb PªWGEÖ\\nì½ÇbçÍËä)ËÙñ¢#]JpËÎÑò·¨¯LüÎÕ¾ö\w· bºñÿÎ¥ë¨(ÊÞâÅÇXsd4Ö,'àÞkÐÕjz_%Øf½íàA'¶qüTj_^ÀÁì³;g×Ih+)M\\bçÎâIJp*ÛäæDY*ñ/CGIÏLÎ¢ó ûïÛ²øI,eÅÙÛDæ\\fìÇìB×¸\\r²rÏWÒ6ù-\\tåïçOäßMæXïP]¥½\\rªû3íÎa#_§ZÔ*fã\,¿]³´WÝoéé;¨>U\\bÇ ³¦ëlþØ0Oò5¤½´*=b(:íR-óß|ó¤½ÒE¼KÐgaÝ¹.¿[ÖÕÝë@Vã{ÇB¬^ît}æ-L»×Þð¡¼%Àrñý#PLXuÍ¢[Jù.`¯#FB$+ÖîáÃN&¦Iã;7¾r¾±,T©(%=Z#ZÉ¦lù÷uÄ«ÁÔù»>DÎÜèÌ!g}^\ò.þ=«< 'u\\t 9¦s\\fËövêâ<$Ô%¨ù(NI\Ø¯õ"J:$Ü£!ð+ãÁIèËKrÊ ¦IJ5ÌsÿìH?úïÃa¹eA^ÞµÌ ÐIv¡w{wÛ{éÑMÔ5VmbFµàüÖÚ·$¿¾so¼IËâýßÅgn_ÞÒ\\tPÒ#Dë¿b)q98P{Åop~TMÑØºt,!Qñ'¢c|[B¹2+C rµ¦MÛ©¿AH\\f¯§ÊayÔú¢|äOþiý9áWer<¯ºçl,£-Uã§2UZD¢óx0b}wÊ>µ¹cE7:}f-%ÿç":+\\bcøµ@º!\\nóBÝ×Ü«uã1Qº\\nûé¢&[¬D¨~ËhÑÄdÅ<ö¼ç_]Ípá&ìaõä¤ëNÂ"ãìV¤uîÞFÐ:ÿÎ·Às¸ò®²ÝP?;¿Ö<ð\\bG¬ô<ì-\\fÃ Ç©ªÑ4§ÙyºÏÒP«k[Exò£¸3ÙbbQNâj êBwñ÷3¾uAzøø`6wk¹­(%_Ø Á2fêëÍ?Øi´Ó¹ðRkU¼¾®Ëqvò>>ïI2ì])@.inÅôt"â­xØS W·S©8N±\W/¥\=òã\\rËbUj¿0Ç¢ÒlÊxî­Sþ³M@@&_mÔ^¥3ÏVn-[VÿîÍ\ ÛÝt+k³b\\nn\\rOÏt¾$ÆÞÐq,\\tplsnúu8uïâÙnàÊú@Á¼\©ÄX'?÷ ¢hkü'î5e0N×û²75`»_¶IÍ\\t£±Mø|È0¯ãÒeSÕù<wur lº¤ïs$¡]NðYÔûJ4;uâCZxø«¨×£Ó(Ì*G«ìáÁkq³¨ð©Õ £Oþü; é!«-ÂmpßÞ:Ù5m~»o ø@r)xsXÖHOøz]GÖñ»Q÷ÛÚrD¬¶ÇUNÊJâL?F9¥ÞãéöºÉMÈO¦bEÈ?ÞòCEÍÿÅ0 ½Q@ù|CA¼ßÌ3Y\\nÝ+óÆbMVA"\\t\\nÑëiRêHÊ½!ü çíÐØëÄÂ9Q&Åùþ¹»Ø®¥dâ±D]jl± RÞ]âýÝâ*öÚþv_·¦ÐÑq2ü¼Í \\n¯5&èç<Üªf~ðËTxÒ\\f(rÃzRvÀ¬pFODLm:·08bÐ¾º\ðÜÂ¬hÃZÄÌb4üùùdÙÂ"<£Ëß>ã¥\\bÚ³7õZéæ®Ò7»ì~lf¶Ã»Ò¦ªÒñ0Ì­¬ü1D×ú¦­È3ý(ÕlÍ¢Ãol?Ö1s\\rQã~«ñèéÓÉ{e}"<¢]å\I02÷\\b.å^~°?9ÑóaDE° TA\\fãqX¤pÉ  X~9ò¼âßê_|ÃrwÔÈ»\×¾]ò±!õZHA¥[ ¯ÿFH¶$SM´ùVÁå¿'Wù9n¿NßP!9òÔáÇZ.?sÇö/owöÍcHîÉH)Ø¢S? }w²ZPc¡IÞIs¶hø`@úyàcu¾ÿñhayO_V='eÉl\\fª©gn>:öÖrÄE÷Í7NæÔësW/²*õKÙ}`´ßÆîÃ®5Rú" ¼@¨.+Dn®uîæjõ¼K¶¸7Téæmù²ãCMãg\@In\\nÁÈ]©Û3½±#Ë¹Ìßöa ¨¾¥¬Zn¥ìP81.ÁÍÅ¸·Dß)Àf×Y|pwç:q«r®Ì5!«]J( ØÀ³XdÅfQD\\tË"Ù¼M^*×hJly`ßåÈSâò0v"\\bw®U-[¾aÿØ¶Ù°·hT¢¾(¥E^,² #ô[>h±ÅSÒ\\tÔ.«4ÌYçÏ¡*bãQ÷>Ð·¤(ÜÍ¡åo\\fpéß®DÐî,q~Ãáò#3·|Îetónê4·ôÁ÷_µ¤×\\tù+N1ú"z=v:AÂaØ×$÷·õ'>â*Dx¥\\ngWò0<Ó4@û­H\\t­¥r!N;©ÔIÄ0ÆÁ®.Ã\\b/ôÙú]®ÝMÞ;99\\f?Uèº·:º?º/é!S~N{ÑçÂ¦8Á ÊÇåîZ¦u&Ü¼ß\\nµùdMý2Ä\!f,ze¡EO:m¨Öí*ïáLÌí¸¹³øÉ¼7°æ ±y¬P2sÈÌyY´`Õô<¡Ï7.,7ý¿\\f$»âÌ\\blsZúéðv93HüH«Zh÷AU|ÑaÁÂ¼ÙÔ·[{6Ü¸Nám<sAÂÌXç2Ä8æ®Ìd£?Ñì!ZÉÇUïªØ´<a¹±u\Èk$\\f¯HP1yÆÈ®ìì6°ªK\\t¶IfªÃtÊ³×olÅ=Y¯¹ê}Ä½Iî#Ä¾{ªvqï.©a/neMÒóKdÑ½GaÍ¯¾-Ã¾«OÀWz=rÉ"VÐ®'$=wÀÝéøÝ`ÞÏëiì2zOB2ó.Õ¨)ÚZH Ì-\\f*¸Ê¶Kv.vçÿHÊvßÐ2SMu/Ä_;¼i¯xòMO+Ó[w¬uRY`ôÞlê» ,o\\b-Ô@8è\w7L;ö¡h~\\tv¶\\rHÈ®´£vtnÙ~+°öu&krù0µJD1WêL®f©'âã^²VêÕ-uÃÑ\\n®·Æ-1ï'\\b`|­üMNú\aÉA-\¹ ·Ü'B¤ôùOÑî/\\f±¨OÄpÒÃ¼"@²;Ã°ì´2½.L8æàí ñ¿j£jl·(e\\f®n2^²Ívjå=ùÈ5Ta¯«ÕI:_wNë6µÆ´¯æ&.¹\\bUZ'Ðp,§\\ru°T¢)½¡ª¿®ÒÕÏÎÐÕíåoýìä.ÒÉDG¿9Ë è\\bw^ÜP©ÄâIN1æ¤­Ø\\t06ôêi}aÃZYë°±Å¥©ÂáB£Qidß¥=®*Ãk©ÀºëU¸YC4þÌ F(AÄ_cHõ}ÆÕ\\tÂjïdÃÃ>÷îk­öÈ_'Èú(Gÿ\\rT2Üìýï´\\tÎtü¦òa^ÀòoðèÜ?«»À¢®H'y¨Óý°Å"Iùª>ØÌÄ_ÃKÒz\WõlØÔOß5²nÏç:}1÷GPåh7 ½júÐ°o§u»Óþ\\fµ½QÇ÷Wî×L÷ÃqÕ_²»º^mGµöê³mX£\\fä Ö3-Ëï¢Ã½2¶³Rë@WAî'ÍðçîæYÙ>.aÓÃ\\f8¥XJ__É±ôçâ|^-rÅ}-x1­Y(Öj@\\f<Òæw·Ií\\bY¤¸\E\«Ñ¾YDèÅÚÜ§òn<mR`hWÒÈædîyP´ z\\f¶GÇLSI0ÝÛü"®ç¸C \\bô^L\\nóiû3Úcb plÒÚgbÞ\\f]WÅÓÉ6í§OØú/©C¾zð^=4ðU¬kp9Gh»K±F¥]Põ¶°6ãÍñÙeÈø(C¸"·ý_£6 ±ïÉÙ¿ l³\\b²?d¦2õxñI¶É°®ÿåTÁ×¼~¬­\\n5CûC_oM³ZáOgÇq¢Ô¦3¨°\\rBíøÛs2Oà"ÈvÙJÛMRæLóYñ ¯yâÙ\\fÏjHäi°EÓ}¤åC~(÷Q.Ç»tndÿ"Ô½>ªWxÑÍî T0êð(ÐzAÀF¢¬^´¨<yp%JRÛ·rDUçD"@'-fÛÒm?FÔwÆ½èêÛ8!Baµ(±~£´ù½¯v§å\¤ËEÂ.ÃAþ½5kú×û÷Ò h5\\n'D²I'}HÆÂ*è¨Î¬0ÿQÃ¨VdÍ´·f»½9¢» ØZAÑu*Äð:¶lZwÑþ%\ºc!2xu>\ËåE©ÞêDcÿapPL^¶ÍN¾Pà@Ïuºº§c×g¦\\tA Ø])õóÏ!l6UÖ f¥2­§õ,ÈDôêëjN6°9éáùPÇË³_*âð=Ç·}N^É°ÞÄt{ÆÖ<ØpüÉ{¼iNh×aÐ*n¶â°!1ãkû6FHKûW!ÿÁíùK½?Ïìw!>²¼jjiòªh|PÛè-dïV¡v)j(¼\\f«újËÃ1P£¹³d`yüFðé¯x)Lo%8{©ÂëÌØrF.­ýÀ@²¥( ,ß8â¨êäÏõÄs©áIC ¡þhM"ö\\n£kJ"G}£$ý:uô¦]ö^q¦h$@4«.¬óÊgU=¿Ü°\\bë×ÜßRé¢ï÷äÕLøÖïWµrÔk|S ÛÕÁlM%(¢ÉíµÄå$~SàîUýeéÕÐO¹ÉMqáÎ.àF¼æ2ÛÛ5øÜ5ríìMôç+ñÇ´µÍ¶fh:Ægy1$×}²ì2Ñô¦Òå%æÑWâñóòû·§¿dÜòeÈ-¸#mïÏ+èöÙl\\f¼@R;ëëRîr\StåîñG$3}É«#óñ'ò=üÍËqÆJt6k2¬¨¹e¿|êúu`5øîá,íß N`{#p[ÜhÐÀòÒð\\nf;!´!©ÌMþú¡ê*\\t¤Ê&A÷{+¾NÆ%ÿp79ç)¥þvÃs5<ùH%½ky0mâ|ºF1~l5(n¸»\\f÷!*>Ï^ÀZ",ÄÞéÎÍé»ÎÙbÞÜUÝ÷eXÝ{ÆÇÚÎ¯ïÛ9 îÕQ20EÍ==b;Å®ÅpØÜ.NLZGVÚ4t=vþ1/ÀÂÝ!á×TÏ!ðwÇ )à\\tÓ¯í®Høsvô¶w\\bÙbaì¶\\r¤Ñîù6Ncnð"ê±½HÿþóÏ¶ â¬v ,ùÌ#pÆk[Ité×v:WòýïA;Ö2~n!{¼½Í.>P\\rçèû\\rMi)V9rÏSÖçë}&òC/ñ-¸Õ`M<,\\t;­Ò×²;°þ¢ñâ  (F¬ÞâRC'\\füëeåÚãeL¨È&MOß£´Ré-*øV\VþWì{fë²¸^ÃeÕ±=\\bòr\\n¨:°ÛS\\n¾ùånæL3Ñ¡ÎâéµÛ ·¬Ð\\tX?ÿÑÜ?^ésT8å4¤&NÕï²µÊGY§ë.mÊ÷rkàðiNg/~b'Íâqqs°oc/CRÓF_Ý-(|ÈAúÜÁ¨ÔoÃ5}ôdvÄ'uÅÂGwLëXyô\\tr³d@ÁöæuØbµ¢QÝßd\\n+fª»ÉØ#2Ð×ïeF¼°w¬\ÇäÚæß\\fu74+ø¢ÞÞë­Êï ~R\\f|Ik\\n Ý L31ïkÌOs¾{ºwV3e{g@à&å÷3[1ö®W©7¤\H×Èü ¹÷æÉ÷H|²¿ôaþÚgÑ¾Ö3!ª-»o}Ýu+óOi¤së%a¤}º×)f5guÔ\\rÄ\\nO{h!o|)³w !Å ¨·ÌÉZ°y97'
    //   69: dup
    //   70: astore_2
    //   71: invokevirtual length : ()I
    //   74: istore #4
    //   76: sipush #32767
    //   79: istore_1
    //   80: iconst_m1
    //   81: istore_0
    //   82: iconst_5
    //   83: iinc #0, 1
    //   86: aload_2
    //   87: iload_0
    //   88: dup
    //   89: iload_1
    //   90: iadd
    //   91: invokevirtual substring : (II)Ljava/lang/String;
    //   94: iconst_0
    //   95: goto -> 202
    //   98: aload #5
    //   100: swap
    //   101: iload_3
    //   102: iinc #3, 1
    //   105: swap
    //   106: aastore
    //   107: iload_0
    //   108: iload_1
    //   109: iadd
    //   110: dup
    //   111: istore_0
    //   112: iload #4
    //   114: if_icmpge -> 126
    //   117: aload_2
    //   118: iload_0
    //   119: invokevirtual charAt : (I)C
    //   122: istore_1
    //   123: goto -> 82
    //   126: ldc '§#t¥¿\X}Ê]êw'ÇÓÝí÷fÙ¬Á¸»»e'´ÓÝåbMÜ$°ëØÇh¾}G¾8ÇìiÈi|Êx¥}­oyF_D¶WÄàySÏrï*f4"¸-=µØÛ×óF(ìgâ?Í0LKçd|$a%4Cz)¥xPVðf»ÝC4ëñÂúDKòØÈL{JîT¯gþÅSÊã¼Ûñ]:&Å}±@¸(`&veÛcû`+/ÌÔ½;1ÕÅ|}ã¥úô(¢?ÚIk(9mÑàçÙã0X|ÿTbtz\\fØU¸\\r}_ø\\bÑiUÖÝ^Äö^aJO)hùãYysó}:¥÷Ü¶Ý²íJ`Ü7ìÄ`fvªìý)¼y¤¸IÝ­ñè+åu ×Û±´uïáñòæRlkaÊÔdH\\fzM?üè9yýRpwíTpU/©»÷l`Zí@ÌI;hËÄ\]ïîºåEº¨UFß6Oò½«K®¿á9ÈrVEÿpfK\\rê1ïÚ£PãpÕÙÏJOá!ï&x_åiÇn£`û[\ê?´îO¦)±rëí~dlONBxÒáaç.ÿ¾º¯çëî,Úçhz~Ç£QzßÑÉ41<\\rbê³]µÎW3gâÚî÷OÜdLM$î©p>mÕÚåu÷ºß¶æey¿h¸lV¥ýNÇGÙç&'T´)ÝÞÎ-38äggÆÇ&9ûdææ§Bº;¬µ~mhjg5ÏÙè:@%ÄÉÛú«¾ÜY%L6!XAI¼æð©øV(¦YO¶á¾N¢ÓÓÊr¢nÅ*¨ÀuÆ¼»8HO¤¨«E@FpâXðÔ$¢v¯ä,7¼Eåß±¬âlnRo¡ÞP©Ú¹àWôÁ,WÜ¿ÜHã(»oE¸ÎNÙJ;9é¼^+c"À÷#kPhBQÀ4|>#~`]9¿HrúÆl4¢õ§BÇ)D9ó¼-U³$y£²}î»PÜ×*à²Fm®N\\tÿþÃ`¤K×îüÙ«Ôã^2ZÂB¹<íAS_À×\\r8ò¤Ò(fÓå-ì3\\tX,,¸nüJo.3¸ÒäíL´G¶ºÇë¥IzJðM >¨ìü1\\r·xR-«è¥GÙ©MÚzÜs ºÖ­¦P,Ó;ÌMîÙ u2'utTZ-KÎf Xè{ra¢Ry§Ó£}ÃGïæ¢8#_ÔìUÜÄ¸IAó¹ùÍ¡mFËWpÈp<;ØÃ¢+ç¯._/ïjÝV¼0z\ú]\\fÊ×[fÌê&Þ@ýþ]Ò¤ìð¥O-ñ¥·ª>ðëvÕ±Üf7ßÙØQ, ¿C÷ÿ0áÐÅ+¨e]ì`ªÄ|¢£ô2¸bØáºÓªtÆ=»NÎ2¨¶]mîv^ÏYn±2Î¯ZÖÜ`1¦xBÃ*&GY_\\rø(aÌbÇ0ú»èð´Añy©?Pßú)ñ\o5eöK'r¤áTÂi80ê·# [>§µ²èÈA±ÍêrÒª\\nAç²jR']kÞ³M'©·9#!>î\\t1ÄÁ-»5d^åÿ¢¾Ü^îE:\ök|î°Å)Ü´\ÕÙ¯rD\\nõôÛî«ÎäÔB#AÝv@ÏUz,êµÐé=\\bCs&ºbeOöïºõÞ³\\nÐÌ,·ÄÓËû¤¤J@»hß S 4Ý%\ÙyIs,á#ÕíË=( z·åºK#6:¶ÛÜbhÉW\\taöî§5ýqàñ×2*¹k÷´q|ïêÓì, >O)Gsî \\tümZ¾zêµà8rCÓÈû\\r!ï\´{¦â¬fîê+íhåR8jørv"f8>p=¡!æVT7¬°X°}~fä§ÂÉÂ»ìÉKÇæ8ï±òüx~,??3\*6Ù|:kE£eÉ­Ä²íFZ'K?¼âë<(Öq*÷@ü;Q§1%Bêãë¼p+3ú}dØÿ¥Ôylf¾ß³§ÚKgÀâá>îÃ3Xj×óÙçØ¢rùþÃ$aWCv?/ò$Q%nó1×`}æçA¸äÖelû>q)Ûÿ};ÎÜå$Ç¡sÞë\\nîS,>5\\f2Iì¦Ijó^ÈÙv]K+]Ïk\\rÚ¾öUFÝ©×«MG¿áJð$fÑ@§õÐÐôÀ!÷;Ü'å=_l#(Û£Q^=î-STÉCåØÎTq²O6v¸ý±2à­ °ð0v¬e·ÄÍÆ÷@1ûàc,¸Ù@À%9ë-¦a°xGXÌ\\f±Î°ÔL°\\n*ÐÄËVu#³ì,A\\rJÕÑÕéÓõÓ`ó4ÖKs/æ÷ÉÜÚ8©ð{<·Û{khÀòXq®ÓÔp @MúÁÝ\\n[-e0s¾rÖ±¸5+í§gHB'Xnöy°³:ÈÕMqRå9,çêÅºþhyë­*¬9döòºlxEçn=sbh³®0&÷nÐV¤¸tµLÎ8F÷®:pLw+åî¸À´Õ?Ìzí£2 áÚc> HmJPM\\t>xÊ<Ø¨ú\\t,¥àÐ6þc¶É¼ÄÓ¢5õ£_mÿÓ½ïÝ¶)cu@^Á¿7¨RÓl«óC2ËSaðÛØu&<b>+!çÅ&Ý(4õü¥¾ûøÀ2`R ¿=]­¯2Î*³õÑN8ZÏ C¿ºÚÿB¶ÏÞ¨TÅÄÁ9<ÂyR·>6\\f5_#Ç.\\túÏo¬ÇAÚüÍ¯½½7/}§\\b34º7"Z l×*`JN³A½ÆNÙG:mP¿«\\rð,ðæöMI?Ò¦û·8ê×åÖ1#ícÚR¢²k³$>ïiKØ&h[ Zs8¡:j0 $h¢LÎþ`LçÅmÇ5IÙ5¡×ó²g@é¶iÑµ£'Ë/ÌÁcax¿Èr¢ôkS+Ip[GhÛT$4ºvÝ%-$Ìü¨ù7¾£E3×Õ/Å£À.*ÈTÔÛ¤n8RÕ§Mõløb°¦%)Å,ÙßÝ7ä+,0.W8W}ÒÍÓ1%l;Ým~TÃÞÌ2» /ÓQóâ¬ÀcS#5(<È -|7 ^Dv8òÒ¢øhF Ç©l³ãR6×²zï$÷6¯LÔ÷÷J8Q%Þ¯è´Ö¡då¼8'ýBëiä9+ðe¡6å*Ñm"4(1Áh_ä'+õ OTaÈÁ)Ät³vîÀÊ£ã!hyF.´DÒíÂ3BÀayY¸iN¼2w\\rÉ¼Ã+ýt:pìÊJmõ)Oh!È¾B\\n©OõÊï¦DÜobÒðñ#ÐÎ±*¯½¼¬¥ÃçºeÂ9A,©ÄÑÃ@p¦w{^uOk~·8ûI0½®N"r¾¤l5/Ö=ã\\rg,¿L÷3ÆÙWº¶\Ui÷¸*7]>~|ÀJ¦Ì£ÔöC/PUrSÊ[]&àãêPú)FÐyLÒKg'êjgz¬Õ4a¦óá^è!Ñ¹ *ÕÏJÄ!Þ\\r/°½Q¹IË<+LçfsîÌâTTâülÄÇO+ÈðzËw>óCÿ\\t¦Zä+e§`QF6j}ØwÁPnOpLÒåh))>ÞQg5¡Tì¨Æa&DÊb}*XCvî!-Ä~ìY0Oûâ0õðÉ»«º¶cOwdÌåæÆ<YZÍHR'çâË§ìÃ>dÜäëÝªóÈ|dú{9"¢Í¤«qPs©êU3Ýµ:,¿YÄãv«ÙòQ#4àýÿ7ÝLÞcàýÇ:sÜ¥<Yî'.­7;apßÀsÃP/§^yó¢SW²Qñð©)tö­­¤Ý¨ LL²üY÷O k×F¿lDü'V)[ò­9ÆºP?âîÕÔVµÜ$c:wIÄýÞ´#®Ô¸õcc¹\Uí%¼@÷þ²á­O\\fGXêÂèÓRßá®-7ñj HÙù«úÿQ8Õ¢°\\tó¬ÄG»v<(Ó7ÏÇ×ïÔG(ÿ~P¬ß¥¯©^­áIélæ#F\\neâú@ Ê·hóTwX±vµ·'Î0P¾SMPP\\nîMO]"±²S+º5ÍùcKT¾±÷Uí\\r¢õ/P<ÞXÉGo/\\tþbPMA,{°8g\\n\\b \b-\\büçÉ~ÀAõ}©^9-ò¿(½19ó-Öw ýZ´êÐþ=ßÉb»øÜ2`«+)µ|+2fæ¡ÿäçà pSU?xsYÝ{\\b$ç¡øÑkÐBQ¦r\\f18ÊP@±ÆÇaÛônt)OÁ¿fcF[7ßúæ¼~*AsWgA¤åªXGúE]H³x÷Â¤"¾T¨çÙ2¶ë¤GÑ?ÏªXr£ Õ\\f]}ÁÉl¹wÓê&Ìh<³\\fõ2"}4wü8t\\r|øH äµ¤]M"LãïZùÆøÙr2¡ÈnKqhbÍôkÔàðªn¬î÷ôÊºøÑ­Ùsþõôséh8©46î0Û×dñ~`{<á,~{ùí¨i ?Ìgæ\è{Íf´üêÓÙfô75gz)E}t¼ÊéÛu=á1\\f:\Ò°-4Xxqieá&?Ô¥¶Î^-9³öÙ\\bSùz£6lç¿3´ÙïõP*p\\rüöà\V¹­Gàçºô\\tÁËäF$xàE¤88Ú·ÛtâoÍ×mù462½C­ìÄ=¨D×·Sää©ÓÛå¶ê°Ey´ØZ?42ÍsÉ[ÍÚãy¨*éÝ Îæ%¢¹[q\\b\\r9ñ9,É¼æ­î¿ü¸ýk\\f~¢¹g#qÅO'µ3³2ÇöE°ïI_I2É,WJÑ­\×Á½Ä+]ö!«Çê+Ü­Ï?3W²v<m(=9çÚÊÍ:ê&û¼\\bËu´Ù¾»ÁyµÅe3N°Ç¿ªÚ§Ç§,T³jèá:6ôí¹ìîX,\\\fÛØ\Ú\\tb<RWíÀr¶iRßé#½*tU.sL\\tQøC-Et#ã7×ÐR¸ØÌØNÙ\\fÖâéxÌaVÏÏ{u\\rÆáÈÓ)¯½ãÕ7ö)Øqâ\\tÒF;ãýx}F\\nÇrö*CÏRAg¢6Ù[vwÇ×q8ù³·%@¦j³Yýéc\\nJoPCrecüÊJÿ¤æÞªµÙö.æPv&QIs=×óâedàø¥Å$RÖg*ËóÆÑ°öÆÆBÀÂ$tXt>^\\f½j¸E>.\\r`dÍF:ÜgâUÅê-ÅG\A¨²baî´YCqH@a½¦h{Wc¡Ð?ÏùÇÒñ=`PÀ5vJ¨&ØzÞ\\r#£ÙÑóòÃu@³H|MwùÒq(~×§.ý¬&ò!´~\\bó¿¡GáÕÈË6¹QÖf»}p_÷5\\b[}IV=vÓ¨èÀ¶¨kø[Kæ¼ÖJÑ*7#®¯Íu­Y\\nXI¹Ynjï@Ò¹e1L¨ÓüB},l3äix1~a×fL¼¬âÚ»¢K½mK}±\\b/¹pîZjEJi¡ÈùâqUqá¾ó$Vqë@[óJþP)¸g$ïÁýíuü À ÅÞ]SÛºñë´In¸î¶OèBÆ1qÂ9FÃmÇ2ãî¸D®ß dëvañvÒÒ:ïwýÑ9¶\\b®ÆÈ!;9( ¨,©ÄZË±¬Þ2y=¬r_Qõ§?YÕéw¢ù$ÿäÉ¡üQÆô«¬Äpìîhná¥®¹<x3ô3V¾'æÐÑÊ¥Â%y]ræÉ5«Âì Ë& [ëD¡¢8¼sDðlûÞ`#¢Ú:Íå"Ûô­1À`ïî\\b:1<ÂTPråR©N²$)÷Æ e\\tÂQÌmmu¼;-Ç-Fá@Ø¡ÿ\\tÊ­õëm¹ùVè}M¼å!Ã Í3°_ûzàÃ`í?õ¥¨ÍûÇóvê´ÖÁHÀê·ýíÄåµò¹U¬\\b9h÷ i\f@ó¡ïdÅ)¶Nò8è. ´àKn"ÈaÉFNYü$åá\\né\\n¨¤k2{\\r×z6Áó..Ôc¡d°ÿ'B«ÂsZÅES®ÉÜ%ÿÀRÞrê)âq\\f2/ÿmhöaêè«{{:Þø,HîbäMËÇãuò¢æmdÙ¶8O;ÂÓ5\\rT58^ªE\\tÈý[íöt¹ 5»ödAûÁÚ¯Õò´÷mK­ôÑK.x\\tÏ½,ÅÃë`\\b±ÆúæOZcÉmú?üçd4ÁW\q¡¶ ~E#jifPß¢Î¼Î~©õêRå $Ú.*iE<¢R7\\fÙs°0zgÚDÌL%º0<û§Lïß·?\\bÌYª"{lþë¿­öV;:qøC[\\nþrXå¦¿õ)C?§¬öäïûF·rÔ°}eT»òìhVhM¬%NlÀPi*¦ß*aZø´J\\fù]ðØÓ</'|2Þ0àÑJ#ó¶ÎX_Î¨BÎo¤´3ë@Ý*pèt¤Öy1©Æs²µM}Óm@FN3ëÉ#ØO³ÂZÛ[Õµâlª1V\\tÜù0$2ãØØF\\tÙBCu\\f½;0çUI\\f\¦m\ÿ"áR1Îrõ-0cÑÂæ}[²@dôJ)¾uëlµJ v_5³Wc$ýÑp3eæÆ*ú¸SÜ3Ìªf[äíºÖÞ®D´Fx'0¸ªýòÓ{ñ´7[q¯Xa{ÆÕø`ú¶OXt{¬ãqy_\\nëE½ÿT¾ á¨å\\b8Xcjó)P¥\L\\rÑéhÂ(>Øïù{Ím¥ÒsãQÞÛË~¬ÏÊ XOk©óD¾Ë\\fÀEibä&¦R°¾¾Ù\\nAN\%Û²ê&ÆÃ NbD¸c®Mß_¡ÙÎU\\n6\\n;°Sû¥ÕËèßÕ\\teÔíÊë\\b-ºTÿü&ºLÁuzûrNãÅ=?ò±eÅ¾¯÷§Úu0h¾d3»NÀ¶>¤>3:1SEZI¥ÔñÖÂ¾GÓ¸X!.³X,JxN\\nÜÿj7JÝÈ²iÀ9IÊ\\nö9yUõs´¶2ÝÕ}Åø¡ÚæXÔoÂfZAgA[% #`5Ìçþ¹¯ìJ_h#½g£ØÇ«ßxPúö8¯NÍr`³ÓJa÷9¬;æ ü.\\bÒªÝìMésìYy«½|z)ÿV-O,óôtþß@2ãëúC|/¥T¦­ùSÍ;o·ªõ´?S±dî3 S&nó ¾~v%z s¨ù*.è!v\\bÀ¾Ò·°gøG#ý´Fö"éòÈÐy*lT_øyD4ÉdW)h®>X²Ý§WÓ]b¨{ÔnqðøªõJlëä(AÂ$>'vv;ZSÜôÜF=ø/U\Zò0Âý#tþèj¤ý/BAf#Ý"­Nà¸Æ\\r¨ñx.®r2ã-"ÒØ·)_05¿pá{¤DftByO\\r-´Ö¨@åÒyy"$Ä¥:ºWíä$W;vìGÆPÔpµ~"ógÂEWyÏd@¨ä÷èBUØ$õ«ÊÒ\\rõë¾~ý}ãÜ ;êS~ßÙâ+:É;ÌQÑ¥áã2¹ºKE» Ó¯`µfÆf?\\fÚ$,èp\\r\\néÔs6â\\t/Y¸j9;³ZXWw&aÀr>ëúÅLWaô¸@~94[K ¹Ãzjs4â§©VØæ·F/]|ª1rÿÆfEåØì\\nÈ]ãÞ¤DôhJÈ~)y=%¡+°E\B©æiïÿ¦07$EÑ fü"-úþ» ìÆÀFcX´Ôxë"R¨0nc¬²·1n¾m)wñBÄHyg¡$_®Éê06ò±á~lõº»¯à/ä\\f0v\\tgºÊ{fÍþ`æ+¨YrÄâ¿,X¦xõ§g×ÍLï«`ÓpLSOÒÚÄ)À»¬bïÊ9ý²ýyÑèò]r»"t7äO_û-n/Ði«@'H~¦øD_5©ÍÓäâ¶C±wDÅ%êÊC<6LeºÝdä¤!ZuBí9¾þ2sÅrl=î®¼§±üN¿éëÑäïêwÔF¼ü+ [V(92Ò)%Û²&µ:AQÆ¢=ÄÎBí³<¼ heÍ¼Ñ§%-~9skn×>rH½h|º±ß­~éÑ³£gÍ¶¹Ã +æ¾\\bc<¸d½eORLy´`9v°Ä3ð'ZìÒíü\\n[<yLça7¿By[u]<qÊ3ÖJèÏAÿ7ºyª1ì5jjìý¥Æ¾ÝÔkòCNí <ÿ°.¾Å\\râ¾åuºÙÜ-ÞÉ>v"<b4Hñµ»ä`u5g_ô}ïùpoÌØT¡/8ÐÕªSme á\\rlÂËÃÖÈÈÖáÆÚH\\t¶ÌÀÖ«}Ðõês°ä|ôï¾ìª0Ñuá 5¯ÖU=¶åµ¬åb¯PãÖ¶Ùø\\fÚzKöÖuÑuIxk°¾Þð©GeË$láolQ¡<3?²ül»Öÿ\\r^?c±á3¡h}ÿð%IKÑMÇ}TFóÌp$Þ¸m®m_}>5°{ø$ubÎ}\\t=¶e£`\\tØúÙ9Ça9oÒã¶Þ·Ó4è°%ú(l"Û«ï.¦²¸á-\\tª£ÕÖSÛÄ,!û)Ïéi÷-0ÙªbY6ÅÚq¢Ä=u'TKjc¶`A¯K³(\\fùÒ¯EèL èV>j¸®¯yCåbÕÞÇ0£2­Hï!ØpöÃÌÔÉKù·ÞH­9h½V5Ó+(kêÜlù²cù³ÓMwô*îÄråq¾,¥I¥ä¥BÑ¡óìk|è_]}ÞÀìs¡#êCªÖ\\bç¯\\rîÛÓNÄM65Í¾ëçÐûrõ:D²gPDuUÕXÕ H[òÞyÀÂnn6^\\nGd¹Nêdx£¬¤7Ö[W[ºp/\\r"ª-òÃ¹y\\bHü©=§ÿÖ£Óä´´6È#éq¿\\r;×hÊ¾\\fnÝkCøÅ^Êòíb4JJÐtc³\JÇÌ7À×°Öï\\r&¸\ÁsfØV>Ù¾Ö¡¿í`¶M¸¸,4±®;­_Ó¦ÿ]¿¶Þ3þ;|ãïÐ¨Ü/òÖe¡ØT~ÐHpt|d_mT%¨³[M×ÙÁIÙ-¾Mãw·I)X;.`ªÑ\\n<ÛÍý²;ÛÊ.8Mé´á×[ýgXKÑLÃ)fØæsM}\\tö·gä².ÒM´÷¡·ý;.T\åÞ0Òâg>\\r¯Iz`ÕBmS£\\fÃTVÌÁa mOB4¶ÑÎ})7ÉYC+\\b¿¶¥ÈAÐtª}\\nè)zîýãËéT·1o;I¿H4TX¾üéó£5ò`ëoC¼¡QéÁý>Þ)tx(5»+ïOÖSM±¬8r>è5Fba¹ÒS²ìÝë÷3ÿ×.t/Ðº:ÝûB¬ã+GwÁ>h]Rqó\\túödþïÌZG"É¦&¤Òú÷ÁA~,!H:F|åéH6SúU³J8X¢ hKÜòÀë~\\bv«J§$»)é/V×P¥¨±G%p¬|çþªê¬¾Im9HF¾ïK±LÌBpìçBp¾dö±\\f\\nÃÇJ_¥\\tï¡½ç "Úu¾ÛÄÊå<:å ôãa#ñyx¸~ Üé©ðð;müNk]zwWQgkï+êWh¡µFaµhQ71£sdôÝtÅ*Å÷/×°6½¨;U¯ªDÒ7Èñ¯¤n~Ùuã" }1_ÇQCÕæ{_ÐèÌ±\\bHÊBÅh½3gµÀo´&±iwÕ10áÌPø<iÿø¦{ìrùU.øÁ°Á7ú©ù½ýO~v7³<GvâYOX¡ÝVåÔq(1\\fªñw¨¸dÃß]Þí7ó°óKeÍùëÎÆhW®Îf#ã­±wTÏwÒòó\\bèóN F}ÎWåÖéÔ­Zâ¿@àÞ*³?yÐ»ÞO¨iiáæ>{ßÙQ`\\tÇR¶m^8µµ 0w'(*8ìõ%u÷üû>ñoI «sÄsâ5¬?ÇþÆÈÏDÂc'Ù§5¸b½o¾¦»iÅÖ7r:U{¿>rõÀ¶§(¶UêüÙZÉMÂÂúsÒ¨Y`Õ&uóÔÀkI\øDèf`ûÒÈ&,jj ÅËÃÙ4úd¦['¯ãvHþöðù}Ì5jÌµ 4·?¹r§-88ÈôJqsr÷%jH³q{ ùmÚÀZùÜ~íbD Tû¯_IØe^PMÊÑØ2¥-ëO .ÒÂ\\f'v$¹Þ.òTÊÜ{I`öÉç~¶e@bcò/ð¾v}7ø_¹TÝ­èNï4^èJeÐerÛ3^. ¹ÈëM"0°W"\\fÈ]jì9OýúÁS®Ð½\\b¤Mi®ÚÎ'ì.,G9 f§ÙÖçsæ[~hÄP§Ö(¿w¼ä  REáÆ·y ð%[®ûÂ¢DhõI¤s»üb Ó%$=/A9Mr¥úXêó7Þì·¬µò°çsá2O¼üÂGâ ÷°A[Ód¯úÊ­ÝªÃÄ(½gl¸^ÄM>³rÃ\\tµKþ=À°vËar\\n\\t¾¢äE£×1uý­qÙRh/áCoûÆBÅ¥\\t§è´&Ý¼'%'
    //   128: dup
    //   129: astore_2
    //   130: invokevirtual length : ()I
    //   133: istore #4
    //   135: sipush #8929
    //   138: istore_1
    //   139: iconst_m1
    //   140: istore_0
    //   141: bipush #74
    //   143: iinc #0, 1
    //   146: aload_2
    //   147: iload_0
    //   148: dup
    //   149: iload_1
    //   150: iadd
    //   151: invokevirtual substring : (II)Ljava/lang/String;
    //   154: iconst_1
    //   155: goto -> 202
    //   158: aload #5
    //   160: swap
    //   161: iload_3
    //   162: iinc #3, 1
    //   165: swap
    //   166: aastore
    //   167: iload_0
    //   168: iload_1
    //   169: iadd
    //   170: dup
    //   171: istore_0
    //   172: iload #4
    //   174: if_icmpge -> 186
    //   177: aload_2
    //   178: iload_0
    //   179: invokevirtual charAt : (I)C
    //   182: istore_1
    //   183: goto -> 141
    //   186: aload #5
    //   188: putstatic burp/Ztpz.a : [Ljava/lang/String;
    //   191: bipush #9
    //   193: anewarray java/lang/String
    //   196: putstatic burp/Ztpz.b : [Ljava/lang/String;
    //   199: goto -> 364
    //   202: dup_x2
    //   203: pop
    //   204: invokevirtual toCharArray : ()[C
    //   207: dup_x1
    //   208: arraylength
    //   209: dup_x2
    //   210: pop
    //   211: iconst_0
    //   212: istore #6
    //   214: dup2_x1
    //   215: pop2
    //   216: dup_x2
    //   217: iconst_1
    //   218: if_icmpgt -> 320
    //   221: dup2
    //   222: swap
    //   223: iload #6
    //   225: dup2_x1
    //   226: caload
    //   227: swap
    //   228: iload #6
    //   230: bipush #7
    //   232: irem
    //   233: tableswitch default -> 302, 0 -> 272, 1 -> 277, 2 -> 282, 3 -> 287, 4 -> 292, 5 -> 297
    //   272: bipush #123
    //   274: goto -> 304
    //   277: bipush #22
    //   279: goto -> 304
    //   282: bipush #112
    //   284: goto -> 304
    //   287: bipush #81
    //   289: goto -> 304
    //   292: bipush #84
    //   294: goto -> 304
    //   297: bipush #85
    //   299: goto -> 304
    //   302: bipush #31
    //   304: ixor
    //   305: ixor
    //   306: i2c
    //   307: castore
    //   308: iinc #6, 1
    //   311: dup
    //   312: ifne -> 320
    //   315: dup2
    //   316: dup_x1
    //   317: goto -> 225
    //   320: dup2_x1
    //   321: pop2
    //   322: dup_x2
    //   323: iload #6
    //   325: if_icmpgt -> 221
    //   328: pop
    //   329: new java/lang/String
    //   332: dup_x1
    //   333: swap
    //   334: invokespecial <init> : ([C)V
    //   337: invokevirtual intern : ()Ljava/lang/String;
    //   340: swap
    //   341: pop
    //   342: swap
    //   343: tableswitch default -> 39, 0 -> 98, 1 -> 158
    //   364: sipush #22485
    //   367: sipush #-15746
    //   370: invokestatic a : (II)Ljava/lang/String;
    //   373: putstatic burp/Ztpz.Zu : Ljava/lang/String;
    //   376: getstatic burp/Ztpz.Zu : Ljava/lang/String;
    //   379: sipush #22484
    //   382: sipush #22015
    //   385: invokestatic a : (II)Ljava/lang/String;
    //   388: <illegal opcode> makeConcatWithConstants : (Ljava/lang/String;Ljava/lang/String;)Ljava/lang/String;
    //   393: putstatic burp/Ztpz.Zu : Ljava/lang/String;
    //   396: new java/math/BigInteger
    //   399: dup
    //   400: iconst_1
    //   401: bipush #32
    //   403: newarray byte
    //   405: dup
    //   406: iconst_0
    //   407: bipush #120
    //   409: bastore
    //   410: dup
    //   411: iconst_1
    //   412: bipush #-100
    //   414: bastore
    //   415: dup
    //   416: iconst_2
    //   417: bipush #-51
    //   419: bastore
    //   420: dup
    //   421: iconst_3
    //   422: bipush #36
    //   424: bastore
    //   425: dup
    //   426: iconst_4
    //   427: bipush #-37
    //   429: bastore
    //   430: dup
    //   431: iconst_5
    //   432: bipush #33
    //   434: bastore
    //   435: dup
    //   436: bipush #6
    //   438: bipush #-55
    //   440: bastore
    //   441: dup
    //   442: bipush #7
    //   444: bipush #-83
    //   446: bastore
    //   447: dup
    //   448: bipush #8
    //   450: bipush #-7
    //   452: bastore
    //   453: dup
    //   454: bipush #9
    //   456: bipush #97
    //   458: bastore
    //   459: dup
    //   460: bipush #10
    //   462: bipush #-41
    //   464: bastore
    //   465: dup
    //   466: bipush #11
    //   468: bipush #-33
    //   470: bastore
    //   471: dup
    //   472: bipush #12
    //   474: bipush #94
    //   476: bastore
    //   477: dup
    //   478: bipush #13
    //   480: bipush #79
    //   482: bastore
    //   483: dup
    //   484: bipush #14
    //   486: bipush #-72
    //   488: bastore
    //   489: dup
    //   490: bipush #15
    //   492: bipush #101
    //   494: bastore
    //   495: dup
    //   496: bipush #16
    //   498: bipush #-8
    //   500: bastore
    //   501: dup
    //   502: bipush #17
    //   504: bipush #28
    //   506: bastore
    //   507: dup
    //   508: bipush #18
    //   510: bipush #-41
    //   512: bastore
    //   513: dup
    //   514: bipush #19
    //   516: bipush #6
    //   518: bastore
    //   519: dup
    //   520: bipush #20
    //   522: bipush #65
    //   524: bastore
    //   525: dup
    //   526: bipush #21
    //   528: bipush #84
    //   530: bastore
    //   531: dup
    //   532: bipush #22
    //   534: bipush #-11
    //   536: bastore
    //   537: dup
    //   538: bipush #23
    //   540: bipush #105
    //   542: bastore
    //   543: dup
    //   544: bipush #24
    //   546: bipush #-86
    //   548: bastore
    //   549: dup
    //   550: bipush #25
    //   552: bipush #50
    //   554: bastore
    //   555: dup
    //   556: bipush #26
    //   558: bipush #-32
    //   560: bastore
    //   561: dup
    //   562: bipush #27
    //   564: bipush #24
    //   566: bastore
    //   567: dup
    //   568: bipush #28
    //   570: bipush #118
    //   572: bastore
    //   573: dup
    //   574: bipush #29
    //   576: bipush #31
    //   578: bastore
    //   579: dup
    //   580: bipush #30
    //   582: bipush #84
    //   584: bastore
    //   585: dup
    //   586: bipush #31
    //   588: bipush #38
    //   590: bastore
    //   591: invokespecial <init> : (I[B)V
    //   594: putstatic burp/Ztpz.Z_ : Ljava/lang/Object;
    //   597: return
  }
  
  private static Throwable a(Throwable paramThrowable) {
    return paramThrowable;
  }
  
  private static String a(int paramInt1, int paramInt2) {
    int i = (paramInt1 ^ 0x57D3) & 0xFFFF;
    if (b[i] == null) {
      char[] arrayOfChar = a[i].toCharArray();
      switch (arrayOfChar[0] & 0xFF) {
        case 0:
        
        case 1:
        
        case 2:
        
        case 3:
        
        case 4:
        
        case 5:
        
        case 6:
        
        case 7:
        
        case 8:
        
        case 9:
        
        case 10:
        
        case 11:
        
        case 12:
        
        case 13:
        
        case 14:
        
        case 15:
        
        case 16:
        
        case 17:
        
        case 18:
        
        case 19:
        
        case 20:
        
        case 21:
        
        case 22:
        
        case 23:
        
        case 24:
        
        case 25:
        
        case 26:
        
        case 27:
        
        case 28:
        
        case 29:
        
        case 30:
        
        case 31:
        
        case 32:
        
        case 33:
        
        case 34:
        
        case 35:
        
        case 36:
        
        case 37:
        
        case 38:
        
        case 39:
        
        case 40:
        
        case 41:
        
        case 42:
        
        case 43:
        
        case 44:
        
        case 45:
        
        case 46:
        
        case 47:
        
        case 48:
        
        case 49:
        
        case 50:
        
        case 51:
        
        case 52:
        
        case 53:
        
        case 54:
        
        case 55:
        
        case 56:
        
        case 57:
        
        case 58:
        
        case 59:
        
        case 60:
        
        case 61:
        
        case 62:
        
        case 63:
        
        case 64:
        
        case 65:
        
        case 66:
        
        case 67:
        
        case 68:
        
        case 69:
        
        case 70:
        
        case 71:
        
        case 72:
        
        case 73:
        
        case 74:
        
        case 75:
        
        case 76:
        
        case 77:
        
        case 78:
        
        case 79:
        
        case 80:
        
        case 81:
        
        case 82:
        
        case 83:
        
        case 84:
        
        case 85:
        
        case 86:
        
        case 87:
        
        case 88:
        
        case 89:
        
        case 90:
        
        case 91:
        
        case 92:
        
        case 93:
        
        case 94:
        
        case 95:
        
        case 96:
        
        case 97:
        
        case 98:
        
        case 99:
        
        case 100:
        
        case 101:
        
        case 102:
        
        case 103:
        
        case 104:
        
        case 105:
        
        case 106:
        
        case 107:
        
        case 108:
        
        case 109:
        
        case 110:
        
        case 111:
        
        case 112:
        
        case 113:
        
        case 114:
        
        case 115:
        
        case 116:
        
        case 117:
        
        case 118:
        
        case 119:
        
        case 120:
        
        case 121:
        
        case 122:
        
        case 123:
        
        case 124:
        
        case 125:
        
        case 126:
        
        case 127:
        
        case 128:
        
        case 129:
        
        case 130:
        
        case 131:
        
        case 132:
        
        case 133:
        
        case 134:
        
        case 135:
        
        case 136:
        
        case 137:
        
        case 138:
        
        case 139:
        
        case 140:
        
        case 141:
        
        case 142:
        
        case 143:
        
        case 144:
        
        case 145:
        
        case 146:
        
        case 147:
        
        case 148:
        
        case 149:
        
        case 150:
        
        case 151:
        
        case 152:
        
        case 153:
        
        case 154:
        
        case 155:
        
        case 156:
        
        case 157:
        
        case 158:
        
        case 159:
        
        case 160:
        
        case 161:
        
        case 162:
        
        case 163:
        
        case 164:
        
        case 165:
        
        case 166:
        
        case 167:
        
        case 168:
        
        case 169:
        
        case 170:
        
        case 171:
        
        case 172:
        
        case 173:
        
        case 174:
        
        case 175:
        
        case 176:
        
        case 177:
        
        case 178:
        
        case 179:
        
        case 180:
        
        case 181:
        
        case 182:
        
        case 183:
        
        case 184:
        
        case 185:
        
        case 186:
        
        case 187:
        
        case 188:
        
        case 189:
        
        case 190:
        
        case 191:
        
        case 192:
        
        case 193:
        
        case 194:
        
        case 195:
        
        case 196:
        
        case 197:
        
        case 198:
        
        case 199:
        
        case 200:
        
        case 201:
        
        case 202:
        
        case 203:
        
        case 204:
        
        case 205:
        
        case 206:
        
        case 207:
        
        case 208:
        
        case 209:
        
        case 210:
        
        case 211:
        
        case 212:
        
        case 213:
        
        case 214:
        
        case 215:
        
        case 216:
        
        case 217:
        
        case 218:
        
        case 219:
        
        case 220:
        
        case 221:
        
        case 222:
        
        case 223:
        
        case 224:
        
        case 225:
        
        case 226:
        
        case 227:
        
        case 228:
        
        case 229:
        
        case 230:
        
        case 231:
        
        case 232:
        
        case 233:
        
        case 234:
        
        case 235:
        
        case 236:
        
        case 237:
        
        case 238:
        
        case 239:
        
        case 240:
        
        case 241:
        
        case 242:
        
        case 243:
        
        case 244:
        
        case 245:
        
        case 246:
        
        case 247:
        
        case 248:
        
        case 249:
        
        case 250:
        
        case 251:
        
        case 252:
        
        case 253:
        
        case 254:
        
        default:
          break;
      } 
      byte b1 = 61;
      int j = (paramInt2 & 0xFF) - b1;
      if (j < 0)
        j += 256; 
      int k = ((paramInt2 & 0xFFFF) >>> 8) - b1;
      if (k < 0)
        k += 256; 
      for (byte b2 = 0; b2 < arrayOfChar.length; b2++) {
        int m = b2 % 2;
        if (m == 0) {
          arrayOfChar[b2] = (char)(arrayOfChar[b2] ^ j);
          j = ((j >>> 3 | j << 5) ^ arrayOfChar[b2]) & 0xFF;
        } else {
          arrayOfChar[b2] = (char)(arrayOfChar[b2] ^ k);
          k = ((k >>> 3 | k << 5) ^ arrayOfChar[b2]) & 0xFF;
        } 
      } 
      b[i] = (new String(arrayOfChar)).intern();
    } 
    return b[i];
  }
}


/* Location:              C:\Program Files\BurpSuitePro\burpsuite_pro.jar!\burp\Ztpz.class
 * Java compiler version: 21 (65.0)
 * JD-Core Version:       1.1.3
 */