package burp;

import java.util.Arrays;
import java.util.List;
import java.util.stream.Collectors;

public class Ztwj extends Ztx1 {
  public static final List<Zlp9> Za = (List<Zlp9>)Arrays.<Zk9m>stream(Zk9m.values()).map(Zk9m::Zx).collect(Collectors.toList());
  
  public Ztwj(Ze3n paramZe3n, Zbjl paramZbjl, Zesv paramZesv, Zr_4 paramZr_4, int paramInt, Zbom paramZbom, Zbnt paramZbnt, Zey9 paramZey9) {
    // Byte code:
    //   0: aload_0
    //   1: getstatic burp/Ztwj.Za : Ljava/util/List;
    //   4: new burp/Zt46
    //   7: dup
    //   8: getstatic burp/Ztwj.Za : Ljava/util/List;
    //   11: aload_1
    //   12: aload_2
    //   13: iload #5
    //   15: aload_2
    //   16: aload_1
    //   17: aload #6
    //   19: aload #8
    //   21: <illegal opcode> Zc : (ILburp/Zbjl;Lburp/Ze3n;Lburp/Zbom;Lburp/Zey9;)Lburp/Zrbu;
    //   26: aload_3
    //   27: aload #4
    //   29: aload #7
    //   31: invokespecial <init> : (Ljava/util/List;Lburp/Ze3n;Lburp/Zbjl;Lburp/Zrbu;Lburp/Zesv;Lburp/Zr_4;Lburp/Zbnt;)V
    //   34: new burp/Zeso
    //   37: dup
    //   38: invokespecial <init> : ()V
    //   41: invokespecial <init> : (Ljava/util/List;Lburp/Zlz5;Lburp/Zmdl;)V
    //   44: return
  }
  
  private static Zzwz lambda$new$0(int paramInt, Zbjl paramZbjl, Ze3n paramZe3n, Zbom paramZbom, Zey9 paramZey9, Zxs7 paramZxs7) {
    return new Zeay(paramInt, paramZbjl, paramZe3n, paramZbom, paramZey9);
  }
}


/* Location:              C:\Program Files\BurpSuitePro\burpsuite_pro.jar!\burp\Ztwj.class
 * Java compiler version: 21 (65.0)
 * JD-Core Version:       1.1.3
 */