package burp;

import java.math.BigInteger;

class Ztwp extends ClassLoader {
  static Object Ze;
  
  static String ZK;
  
  private static final String[] a;
  
  private static final String[] b;
  
  static boolean Zk(Object[] paramArrayOfObject, Object paramObject) throws Throwable {
    // Byte code:
    //   0: invokestatic ZK : ()Z
    //   3: istore_2
    //   4: getstatic burp/Zsn4.ZQ : Ljava/lang/Object;
    //   7: checkcast java/math/BigInteger
    //   10: getstatic burp/Ztdl.Zw : Ljava/lang/Object;
    //   13: checkcast java/math/BigInteger
    //   16: invokevirtual add : (Ljava/math/BigInteger;)Ljava/math/BigInteger;
    //   19: putstatic burp/Znu.Zf : Ljava/lang/Object;
    //   22: getstatic burp/Zld5.ZX : Ljava/lang/Object;
    //   25: checkcast java/math/BigInteger
    //   28: getstatic burp/Zle9.ZI : Ljava/lang/Object;
    //   31: checkcast java/math/BigInteger
    //   34: invokevirtual add : (Ljava/math/BigInteger;)Ljava/math/BigInteger;
    //   37: putstatic burp/Zr2q.ZS : Ljava/lang/Object;
    //   40: new java/lang/StringBuilder
    //   43: dup
    //   44: invokespecial <init> : ()V
    //   47: astore_3
    //   48: iconst_0
    //   49: istore #4
    //   51: iload #4
    //   53: bipush #32
    //   55: if_icmpge -> 1391
    //   58: iload #4
    //   60: tableswitch default -> 1384, 0 -> 204, 1 -> 241, 2 -> 278, 3 -> 315, 4 -> 352, 5 -> 389, 6 -> 426, 7 -> 463, 8 -> 500, 9 -> 537, 10 -> 574, 11 -> 611, 12 -> 648, 13 -> 685, 14 -> 722, 15 -> 759, 16 -> 796, 17 -> 833, 18 -> 870, 19 -> 907, 20 -> 944, 21 -> 981, 22 -> 1018, 23 -> 1055, 24 -> 1092, 25 -> 1129, 26 -> 1166, 27 -> 1203, 28 -> 1240, 29 -> 1277, 30 -> 1314, 31 -> 1351
    //   204: aload_3
    //   205: getstatic burp/Zgsb.ZM : Ljava/lang/String;
    //   208: getstatic burp/Zsp9.ZV : Ljava/lang/Object;
    //   211: checkcast java/math/BigInteger
    //   214: invokevirtual intValue : ()I
    //   217: bipush #32
    //   219: irem
    //   220: invokestatic abs : (I)I
    //   223: invokevirtual charAt : (I)C
    //   226: invokevirtual append : (C)Ljava/lang/StringBuilder;
    //   229: pop
    //   230: iload_2
    //   231: ifeq -> 1384
    //   234: goto -> 241
    //   237: invokestatic a : (Ljava/lang/Throwable;)Ljava/lang/Throwable;
    //   240: athrow
    //   241: aload_3
    //   242: getstatic burp/Zegj.ZS : Ljava/lang/String;
    //   245: getstatic burp/Zb3r.ZI : Ljava/lang/Object;
    //   248: checkcast java/math/BigInteger
    //   251: invokevirtual intValue : ()I
    //   254: bipush #32
    //   256: irem
    //   257: invokestatic abs : (I)I
    //   260: invokevirtual charAt : (I)C
    //   263: invokevirtual append : (C)Ljava/lang/StringBuilder;
    //   266: pop
    //   267: iload_2
    //   268: ifeq -> 1384
    //   271: goto -> 278
    //   274: invokestatic a : (Ljava/lang/Throwable;)Ljava/lang/Throwable;
    //   277: athrow
    //   278: aload_3
    //   279: getstatic burp/Zmn0.Zk : Ljava/lang/String;
    //   282: getstatic burp/Zl_f.ZI : Ljava/lang/Object;
    //   285: checkcast java/math/BigInteger
    //   288: invokevirtual intValue : ()I
    //   291: bipush #32
    //   293: irem
    //   294: invokestatic abs : (I)I
    //   297: invokevirtual charAt : (I)C
    //   300: invokevirtual append : (C)Ljava/lang/StringBuilder;
    //   303: pop
    //   304: iload_2
    //   305: ifeq -> 1384
    //   308: goto -> 315
    //   311: invokestatic a : (Ljava/lang/Throwable;)Ljava/lang/Throwable;
    //   314: athrow
    //   315: aload_3
    //   316: getstatic burp/Ztq8.ZI : Ljava/lang/String;
    //   319: getstatic burp/Zr17.ZR : Ljava/lang/Object;
    //   322: checkcast java/math/BigInteger
    //   325: invokevirtual intValue : ()I
    //   328: bipush #32
    //   330: irem
    //   331: invokestatic abs : (I)I
    //   334: invokevirtual charAt : (I)C
    //   337: invokevirtual append : (C)Ljava/lang/StringBuilder;
    //   340: pop
    //   341: iload_2
    //   342: ifeq -> 1384
    //   345: goto -> 352
    //   348: invokestatic a : (Ljava/lang/Throwable;)Ljava/lang/Throwable;
    //   351: athrow
    //   352: aload_3
    //   353: getstatic burp/Zbx4.ZS : Ljava/lang/String;
    //   356: getstatic burp/Zka9.Zd : Ljava/lang/Object;
    //   359: checkcast java/math/BigInteger
    //   362: invokevirtual intValue : ()I
    //   365: bipush #32
    //   367: irem
    //   368: invokestatic abs : (I)I
    //   371: invokevirtual charAt : (I)C
    //   374: invokevirtual append : (C)Ljava/lang/StringBuilder;
    //   377: pop
    //   378: iload_2
    //   379: ifeq -> 1384
    //   382: goto -> 389
    //   385: invokestatic a : (Ljava/lang/Throwable;)Ljava/lang/Throwable;
    //   388: athrow
    //   389: aload_3
    //   390: getstatic burp/Zgrz.Zu : Ljava/lang/String;
    //   393: getstatic burp/Zl_a.ZP : Ljava/lang/Object;
    //   396: checkcast java/math/BigInteger
    //   399: invokevirtual intValue : ()I
    //   402: bipush #32
    //   404: irem
    //   405: invokestatic abs : (I)I
    //   408: invokevirtual charAt : (I)C
    //   411: invokevirtual append : (C)Ljava/lang/StringBuilder;
    //   414: pop
    //   415: iload_2
    //   416: ifeq -> 1384
    //   419: goto -> 426
    //   422: invokestatic a : (Ljava/lang/Throwable;)Ljava/lang/Throwable;
    //   425: athrow
    //   426: aload_3
    //   427: getstatic burp/Zbnz.Zp : Ljava/lang/String;
    //   430: getstatic burp/Zrom.ZF : Ljava/lang/Object;
    //   433: checkcast java/math/BigInteger
    //   436: invokevirtual intValue : ()I
    //   439: bipush #32
    //   441: irem
    //   442: invokestatic abs : (I)I
    //   445: invokevirtual charAt : (I)C
    //   448: invokevirtual append : (C)Ljava/lang/StringBuilder;
    //   451: pop
    //   452: iload_2
    //   453: ifeq -> 1384
    //   456: goto -> 463
    //   459: invokestatic a : (Ljava/lang/Throwable;)Ljava/lang/Throwable;
    //   462: athrow
    //   463: aload_3
    //   464: getstatic burp/Ze5h.Zk : Ljava/lang/String;
    //   467: getstatic burp/Zsp9.ZV : Ljava/lang/Object;
    //   470: checkcast java/math/BigInteger
    //   473: invokevirtual intValue : ()I
    //   476: bipush #32
    //   478: irem
    //   479: invokestatic abs : (I)I
    //   482: invokevirtual charAt : (I)C
    //   485: invokevirtual append : (C)Ljava/lang/StringBuilder;
    //   488: pop
    //   489: iload_2
    //   490: ifeq -> 1384
    //   493: goto -> 500
    //   496: invokestatic a : (Ljava/lang/Throwable;)Ljava/lang/Throwable;
    //   499: athrow
    //   500: aload_3
    //   501: getstatic burp/Zmtr.Zd : Ljava/lang/String;
    //   504: getstatic burp/Zl1e.Zp : Ljava/lang/Object;
    //   507: checkcast java/math/BigInteger
    //   510: invokevirtual intValue : ()I
    //   513: bipush #32
    //   515: irem
    //   516: invokestatic abs : (I)I
    //   519: invokevirtual charAt : (I)C
    //   522: invokevirtual append : (C)Ljava/lang/StringBuilder;
    //   525: pop
    //   526: iload_2
    //   527: ifeq -> 1384
    //   530: goto -> 537
    //   533: invokestatic a : (Ljava/lang/Throwable;)Ljava/lang/Throwable;
    //   536: athrow
    //   537: aload_3
    //   538: getstatic burp/Zml9.Zw : Ljava/lang/String;
    //   541: getstatic burp/Zr9u.ZX : Ljava/lang/Object;
    //   544: checkcast java/math/BigInteger
    //   547: invokevirtual intValue : ()I
    //   550: bipush #32
    //   552: irem
    //   553: invokestatic abs : (I)I
    //   556: invokevirtual charAt : (I)C
    //   559: invokevirtual append : (C)Ljava/lang/StringBuilder;
    //   562: pop
    //   563: iload_2
    //   564: ifeq -> 1384
    //   567: goto -> 574
    //   570: invokestatic a : (Ljava/lang/Throwable;)Ljava/lang/Throwable;
    //   573: athrow
    //   574: aload_3
    //   575: getstatic burp/Zv8d.Zi : Ljava/lang/String;
    //   578: getstatic burp/Zld5.ZX : Ljava/lang/Object;
    //   581: checkcast java/math/BigInteger
    //   584: invokevirtual intValue : ()I
    //   587: bipush #32
    //   589: irem
    //   590: invokestatic abs : (I)I
    //   593: invokevirtual charAt : (I)C
    //   596: invokevirtual append : (C)Ljava/lang/StringBuilder;
    //   599: pop
    //   600: iload_2
    //   601: ifeq -> 1384
    //   604: goto -> 611
    //   607: invokestatic a : (Ljava/lang/Throwable;)Ljava/lang/Throwable;
    //   610: athrow
    //   611: aload_3
    //   612: getstatic burp/Zex0.Zk : Ljava/lang/String;
    //   615: getstatic burp/Zgrz.ZX : Ljava/lang/Object;
    //   618: checkcast java/math/BigInteger
    //   621: invokevirtual intValue : ()I
    //   624: bipush #32
    //   626: irem
    //   627: invokestatic abs : (I)I
    //   630: invokevirtual charAt : (I)C
    //   633: invokevirtual append : (C)Ljava/lang/StringBuilder;
    //   636: pop
    //   637: iload_2
    //   638: ifeq -> 1384
    //   641: goto -> 648
    //   644: invokestatic a : (Ljava/lang/Throwable;)Ljava/lang/Throwable;
    //   647: athrow
    //   648: aload_3
    //   649: getstatic burp/Zt6z.ZL : Ljava/lang/String;
    //   652: getstatic burp/Zbx4.Zw : Ljava/lang/Object;
    //   655: checkcast java/math/BigInteger
    //   658: invokevirtual intValue : ()I
    //   661: bipush #32
    //   663: irem
    //   664: invokestatic abs : (I)I
    //   667: invokevirtual charAt : (I)C
    //   670: invokevirtual append : (C)Ljava/lang/StringBuilder;
    //   673: pop
    //   674: iload_2
    //   675: ifeq -> 1384
    //   678: goto -> 685
    //   681: invokestatic a : (Ljava/lang/Throwable;)Ljava/lang/Throwable;
    //   684: athrow
    //   685: aload_3
    //   686: getstatic burp/Zrip.Zy : Ljava/lang/String;
    //   689: getstatic burp/Zscz.ZN : Ljava/lang/Object;
    //   692: checkcast java/math/BigInteger
    //   695: invokevirtual intValue : ()I
    //   698: bipush #32
    //   700: irem
    //   701: invokestatic abs : (I)I
    //   704: invokevirtual charAt : (I)C
    //   707: invokevirtual append : (C)Ljava/lang/StringBuilder;
    //   710: pop
    //   711: iload_2
    //   712: ifeq -> 1384
    //   715: goto -> 722
    //   718: invokestatic a : (Ljava/lang/Throwable;)Ljava/lang/Throwable;
    //   721: athrow
    //   722: aload_3
    //   723: getstatic burp/Zeqx.Zu : Ljava/lang/String;
    //   726: getstatic burp/Zmh3.ZF : Ljava/lang/Object;
    //   729: checkcast java/math/BigInteger
    //   732: invokevirtual intValue : ()I
    //   735: bipush #32
    //   737: irem
    //   738: invokestatic abs : (I)I
    //   741: invokevirtual charAt : (I)C
    //   744: invokevirtual append : (C)Ljava/lang/StringBuilder;
    //   747: pop
    //   748: iload_2
    //   749: ifeq -> 1384
    //   752: goto -> 759
    //   755: invokestatic a : (Ljava/lang/Throwable;)Ljava/lang/Throwable;
    //   758: athrow
    //   759: aload_3
    //   760: getstatic burp/Zrl5.ZG : Ljava/lang/String;
    //   763: getstatic burp/Zg4z.ZB : Ljava/lang/Object;
    //   766: checkcast java/math/BigInteger
    //   769: invokevirtual intValue : ()I
    //   772: bipush #32
    //   774: irem
    //   775: invokestatic abs : (I)I
    //   778: invokevirtual charAt : (I)C
    //   781: invokevirtual append : (C)Ljava/lang/StringBuilder;
    //   784: pop
    //   785: iload_2
    //   786: ifeq -> 1384
    //   789: goto -> 796
    //   792: invokestatic a : (Ljava/lang/Throwable;)Ljava/lang/Throwable;
    //   795: athrow
    //   796: aload_3
    //   797: getstatic burp/Zesw.ZC : Ljava/lang/String;
    //   800: getstatic burp/Zb9q.ZI : Ljava/lang/Object;
    //   803: checkcast java/math/BigInteger
    //   806: invokevirtual intValue : ()I
    //   809: bipush #32
    //   811: irem
    //   812: invokestatic abs : (I)I
    //   815: invokevirtual charAt : (I)C
    //   818: invokevirtual append : (C)Ljava/lang/StringBuilder;
    //   821: pop
    //   822: iload_2
    //   823: ifeq -> 1384
    //   826: goto -> 833
    //   829: invokestatic a : (Ljava/lang/Throwable;)Ljava/lang/Throwable;
    //   832: athrow
    //   833: aload_3
    //   834: getstatic burp/Zg7u.ZA : Ljava/lang/String;
    //   837: getstatic burp/Zs5y.Zd : Ljava/lang/Object;
    //   840: checkcast java/math/BigInteger
    //   843: invokevirtual intValue : ()I
    //   846: bipush #32
    //   848: irem
    //   849: invokestatic abs : (I)I
    //   852: invokevirtual charAt : (I)C
    //   855: invokevirtual append : (C)Ljava/lang/StringBuilder;
    //   858: pop
    //   859: iload_2
    //   860: ifeq -> 1384
    //   863: goto -> 870
    //   866: invokestatic a : (Ljava/lang/Throwable;)Ljava/lang/Throwable;
    //   869: athrow
    //   870: aload_3
    //   871: getstatic burp/Ze4g.Zk : Ljava/lang/String;
    //   874: getstatic burp/Zmdf.ZH : Ljava/lang/Object;
    //   877: checkcast java/math/BigInteger
    //   880: invokevirtual intValue : ()I
    //   883: bipush #32
    //   885: irem
    //   886: invokestatic abs : (I)I
    //   889: invokevirtual charAt : (I)C
    //   892: invokevirtual append : (C)Ljava/lang/StringBuilder;
    //   895: pop
    //   896: iload_2
    //   897: ifeq -> 1384
    //   900: goto -> 907
    //   903: invokestatic a : (Ljava/lang/Throwable;)Ljava/lang/Throwable;
    //   906: athrow
    //   907: aload_3
    //   908: getstatic burp/Zlcc.Zw : Ljava/lang/String;
    //   911: getstatic burp/Zr36.Za : Ljava/lang/Object;
    //   914: checkcast java/math/BigInteger
    //   917: invokevirtual intValue : ()I
    //   920: bipush #32
    //   922: irem
    //   923: invokestatic abs : (I)I
    //   926: invokevirtual charAt : (I)C
    //   929: invokevirtual append : (C)Ljava/lang/StringBuilder;
    //   932: pop
    //   933: iload_2
    //   934: ifeq -> 1384
    //   937: goto -> 944
    //   940: invokestatic a : (Ljava/lang/Throwable;)Ljava/lang/Throwable;
    //   943: athrow
    //   944: aload_3
    //   945: getstatic burp/Zgpx.Z_ : Ljava/lang/String;
    //   948: getstatic burp/Zx63.ZX : Ljava/lang/Object;
    //   951: checkcast java/math/BigInteger
    //   954: invokevirtual intValue : ()I
    //   957: bipush #32
    //   959: irem
    //   960: invokestatic abs : (I)I
    //   963: invokevirtual charAt : (I)C
    //   966: invokevirtual append : (C)Ljava/lang/StringBuilder;
    //   969: pop
    //   970: iload_2
    //   971: ifeq -> 1384
    //   974: goto -> 981
    //   977: invokestatic a : (Ljava/lang/Throwable;)Ljava/lang/Throwable;
    //   980: athrow
    //   981: aload_3
    //   982: getstatic burp/Zelt.ZJ : Ljava/lang/String;
    //   985: getstatic burp/Zbl4.ZW : Ljava/lang/Object;
    //   988: checkcast java/math/BigInteger
    //   991: invokevirtual intValue : ()I
    //   994: bipush #32
    //   996: irem
    //   997: invokestatic abs : (I)I
    //   1000: invokevirtual charAt : (I)C
    //   1003: invokevirtual append : (C)Ljava/lang/StringBuilder;
    //   1006: pop
    //   1007: iload_2
    //   1008: ifeq -> 1384
    //   1011: goto -> 1018
    //   1014: invokestatic a : (Ljava/lang/Throwable;)Ljava/lang/Throwable;
    //   1017: athrow
    //   1018: aload_3
    //   1019: getstatic burp/Zbss.ZV : Ljava/lang/String;
    //   1022: getstatic burp/Zz3b.Zu : Ljava/lang/Object;
    //   1025: checkcast java/math/BigInteger
    //   1028: invokevirtual intValue : ()I
    //   1031: bipush #32
    //   1033: irem
    //   1034: invokestatic abs : (I)I
    //   1037: invokevirtual charAt : (I)C
    //   1040: invokevirtual append : (C)Ljava/lang/StringBuilder;
    //   1043: pop
    //   1044: iload_2
    //   1045: ifeq -> 1384
    //   1048: goto -> 1055
    //   1051: invokestatic a : (Ljava/lang/Throwable;)Ljava/lang/Throwable;
    //   1054: athrow
    //   1055: aload_3
    //   1056: getstatic burp/Zbnk.Zg : Ljava/lang/String;
    //   1059: getstatic burp/Zdv.Zw : Ljava/lang/Object;
    //   1062: checkcast java/math/BigInteger
    //   1065: invokevirtual intValue : ()I
    //   1068: bipush #32
    //   1070: irem
    //   1071: invokestatic abs : (I)I
    //   1074: invokevirtual charAt : (I)C
    //   1077: invokevirtual append : (C)Ljava/lang/StringBuilder;
    //   1080: pop
    //   1081: iload_2
    //   1082: ifeq -> 1384
    //   1085: goto -> 1092
    //   1088: invokestatic a : (Ljava/lang/Throwable;)Ljava/lang/Throwable;
    //   1091: athrow
    //   1092: aload_3
    //   1093: getstatic burp/Zl1e.Z_ : Ljava/lang/String;
    //   1096: getstatic burp/Zlxw.Zi : Ljava/lang/Object;
    //   1099: checkcast java/math/BigInteger
    //   1102: invokevirtual intValue : ()I
    //   1105: bipush #32
    //   1107: irem
    //   1108: invokestatic abs : (I)I
    //   1111: invokevirtual charAt : (I)C
    //   1114: invokevirtual append : (C)Ljava/lang/StringBuilder;
    //   1117: pop
    //   1118: iload_2
    //   1119: ifeq -> 1384
    //   1122: goto -> 1129
    //   1125: invokestatic a : (Ljava/lang/Throwable;)Ljava/lang/Throwable;
    //   1128: athrow
    //   1129: aload_3
    //   1130: getstatic burp/Zrb6.ZP : Ljava/lang/String;
    //   1133: getstatic burp/Zti4.Zi : Ljava/lang/Object;
    //   1136: checkcast java/math/BigInteger
    //   1139: invokevirtual intValue : ()I
    //   1142: bipush #32
    //   1144: irem
    //   1145: invokestatic abs : (I)I
    //   1148: invokevirtual charAt : (I)C
    //   1151: invokevirtual append : (C)Ljava/lang/StringBuilder;
    //   1154: pop
    //   1155: iload_2
    //   1156: ifeq -> 1384
    //   1159: goto -> 1166
    //   1162: invokestatic a : (Ljava/lang/Throwable;)Ljava/lang/Throwable;
    //   1165: athrow
    //   1166: aload_3
    //   1167: getstatic burp/Zr60.ZQ : Ljava/lang/String;
    //   1170: getstatic burp/Zm3x.ZM : Ljava/lang/Object;
    //   1173: checkcast java/math/BigInteger
    //   1176: invokevirtual intValue : ()I
    //   1179: bipush #32
    //   1181: irem
    //   1182: invokestatic abs : (I)I
    //   1185: invokevirtual charAt : (I)C
    //   1188: invokevirtual append : (C)Ljava/lang/StringBuilder;
    //   1191: pop
    //   1192: iload_2
    //   1193: ifeq -> 1384
    //   1196: goto -> 1203
    //   1199: invokestatic a : (Ljava/lang/Throwable;)Ljava/lang/Throwable;
    //   1202: athrow
    //   1203: aload_3
    //   1204: getstatic burp/Zrww.ZV : Ljava/lang/String;
    //   1207: getstatic burp/Zt8m.Zf : Ljava/lang/Object;
    //   1210: checkcast java/math/BigInteger
    //   1213: invokevirtual intValue : ()I
    //   1216: bipush #32
    //   1218: irem
    //   1219: invokestatic abs : (I)I
    //   1222: invokevirtual charAt : (I)C
    //   1225: invokevirtual append : (C)Ljava/lang/StringBuilder;
    //   1228: pop
    //   1229: iload_2
    //   1230: ifeq -> 1384
    //   1233: goto -> 1240
    //   1236: invokestatic a : (Ljava/lang/Throwable;)Ljava/lang/Throwable;
    //   1239: athrow
    //   1240: aload_3
    //   1241: getstatic burp/Zs8w.ZR : Ljava/lang/String;
    //   1244: getstatic burp/Zz91.Z_ : Ljava/lang/Object;
    //   1247: checkcast java/math/BigInteger
    //   1250: invokevirtual intValue : ()I
    //   1253: bipush #32
    //   1255: irem
    //   1256: invokestatic abs : (I)I
    //   1259: invokevirtual charAt : (I)C
    //   1262: invokevirtual append : (C)Ljava/lang/StringBuilder;
    //   1265: pop
    //   1266: iload_2
    //   1267: ifeq -> 1384
    //   1270: goto -> 1277
    //   1273: invokestatic a : (Ljava/lang/Throwable;)Ljava/lang/Throwable;
    //   1276: athrow
    //   1277: aload_3
    //   1278: getstatic burp/Ztq4.Zb : Ljava/lang/String;
    //   1281: getstatic burp/Zer1.ZL : Ljava/lang/Object;
    //   1284: checkcast java/math/BigInteger
    //   1287: invokevirtual intValue : ()I
    //   1290: bipush #32
    //   1292: irem
    //   1293: invokestatic abs : (I)I
    //   1296: invokevirtual charAt : (I)C
    //   1299: invokevirtual append : (C)Ljava/lang/StringBuilder;
    //   1302: pop
    //   1303: iload_2
    //   1304: ifeq -> 1384
    //   1307: goto -> 1314
    //   1310: invokestatic a : (Ljava/lang/Throwable;)Ljava/lang/Throwable;
    //   1313: athrow
    //   1314: aload_3
    //   1315: getstatic burp/Zti4.ZI : Ljava/lang/String;
    //   1318: getstatic burp/Zkdq.ZG : Ljava/lang/Object;
    //   1321: checkcast java/math/BigInteger
    //   1324: invokevirtual intValue : ()I
    //   1327: bipush #32
    //   1329: irem
    //   1330: invokestatic abs : (I)I
    //   1333: invokevirtual charAt : (I)C
    //   1336: invokevirtual append : (C)Ljava/lang/StringBuilder;
    //   1339: pop
    //   1340: iload_2
    //   1341: ifeq -> 1384
    //   1344: goto -> 1351
    //   1347: invokestatic a : (Ljava/lang/Throwable;)Ljava/lang/Throwable;
    //   1350: athrow
    //   1351: aload_3
    //   1352: getstatic burp/Zs5y.ZO : Ljava/lang/String;
    //   1355: getstatic burp/Ztr5.ZZ : Ljava/lang/Object;
    //   1358: checkcast java/math/BigInteger
    //   1361: invokevirtual intValue : ()I
    //   1364: bipush #32
    //   1366: irem
    //   1367: invokestatic abs : (I)I
    //   1370: invokevirtual charAt : (I)C
    //   1373: invokevirtual append : (C)Ljava/lang/StringBuilder;
    //   1376: pop
    //   1377: goto -> 1384
    //   1380: invokestatic a : (Ljava/lang/Throwable;)Ljava/lang/Throwable;
    //   1383: athrow
    //   1384: iinc #4, 1
    //   1387: iload_2
    //   1388: ifeq -> 51
    //   1391: aload_3
    //   1392: invokevirtual toString : ()Ljava/lang/String;
    //   1395: putstatic burp/Zb4d.ZS : Ljava/lang/String;
    //   1398: sipush #-30428
    //   1401: sipush #26218
    //   1404: invokestatic a : (II)Ljava/lang/String;
    //   1407: iconst_1
    //   1408: ldc burp/Ze6k
    //   1410: invokevirtual getClassLoader : ()Ljava/lang/ClassLoader;
    //   1413: invokestatic forName : (Ljava/lang/String;ZLjava/lang/ClassLoader;)Ljava/lang/Class;
    //   1416: invokevirtual getDeclaredFields : ()[Ljava/lang/reflect/Field;
    //   1419: astore #4
    //   1421: aload #4
    //   1423: arraylength
    //   1424: istore #5
    //   1426: iconst_0
    //   1427: istore #6
    //   1429: iload #6
    //   1431: iload #5
    //   1433: if_icmpge -> 1571
    //   1436: aload #4
    //   1438: iload #6
    //   1440: aaload
    //   1441: astore #7
    //   1443: aload #7
    //   1445: invokevirtual getModifiers : ()I
    //   1448: invokestatic isStatic : (I)Z
    //   1451: ifne -> 1461
    //   1454: goto -> 1564
    //   1457: invokestatic a : (Ljava/lang/Throwable;)Ljava/lang/Throwable;
    //   1460: athrow
    //   1461: aload #7
    //   1463: invokevirtual getType : ()Ljava/lang/Class;
    //   1466: astore #8
    //   1468: aload #8
    //   1470: ifnull -> 1551
    //   1473: aload #8
    //   1475: invokevirtual isPrimitive : ()Z
    //   1478: ifne -> 1551
    //   1481: goto -> 1488
    //   1484: invokestatic a : (Ljava/lang/Throwable;)Ljava/lang/Throwable;
    //   1487: athrow
    //   1488: aload #8
    //   1490: invokevirtual getPackage : ()Ljava/lang/Package;
    //   1493: ifnull -> 1551
    //   1496: goto -> 1503
    //   1499: invokestatic a : (Ljava/lang/Throwable;)Ljava/lang/Throwable;
    //   1502: athrow
    //   1503: aload #8
    //   1505: invokevirtual getPackage : ()Ljava/lang/Package;
    //   1508: invokevirtual getName : ()Ljava/lang/String;
    //   1511: ifnull -> 1551
    //   1514: goto -> 1521
    //   1517: invokestatic a : (Ljava/lang/Throwable;)Ljava/lang/Throwable;
    //   1520: athrow
    //   1521: aload #8
    //   1523: invokevirtual getPackage : ()Ljava/lang/Package;
    //   1526: invokevirtual getName : ()Ljava/lang/String;
    //   1529: sipush #-30421
    //   1532: sipush #11879
    //   1535: invokestatic a : (II)Ljava/lang/String;
    //   1538: invokevirtual startsWith : (Ljava/lang/String;)Z
    //   1541: ifne -> 1551
    //   1544: goto -> 1551
    //   1547: invokestatic a : (Ljava/lang/Throwable;)Ljava/lang/Throwable;
    //   1550: athrow
    //   1551: aload #7
    //   1553: iconst_1
    //   1554: invokevirtual setAccessible : (Z)V
    //   1557: aload #7
    //   1559: aconst_null
    //   1560: invokevirtual get : (Ljava/lang/Object;)Ljava/lang/Object;
    //   1563: pop
    //   1564: iinc #6, 1
    //   1567: iload_2
    //   1568: ifeq -> 1429
    //   1571: sipush #-30424
    //   1574: sipush #30671
    //   1577: invokestatic a : (II)Ljava/lang/String;
    //   1580: invokestatic forName : (Ljava/lang/String;)Ljava/lang/Class;
    //   1583: invokevirtual getDeclaredMethods : ()[Ljava/lang/reflect/Method;
    //   1586: astore #4
    //   1588: aload #4
    //   1590: arraylength
    //   1591: istore #5
    //   1593: iconst_0
    //   1594: istore #6
    //   1596: iload #6
    //   1598: iload #5
    //   1600: if_icmpge -> 1733
    //   1603: aload #4
    //   1605: iload #6
    //   1607: aaload
    //   1608: astore #7
    //   1610: aload #7
    //   1612: invokevirtual getParameterTypes : ()[Ljava/lang/Class;
    //   1615: pop
    //   1616: aload #7
    //   1618: invokevirtual getModifiers : ()I
    //   1621: invokestatic isStatic : (I)Z
    //   1624: ifeq -> 1719
    //   1627: aload #7
    //   1629: invokevirtual getParameterTypes : ()[Ljava/lang/Class;
    //   1632: arraylength
    //   1633: iconst_2
    //   1634: if_icmpne -> 1719
    //   1637: goto -> 1644
    //   1640: invokestatic a : (Ljava/lang/Throwable;)Ljava/lang/Throwable;
    //   1643: athrow
    //   1644: aload #7
    //   1646: invokevirtual getReturnType : ()Ljava/lang/Class;
    //   1649: getstatic java/lang/Void.TYPE : Ljava/lang/Class;
    //   1652: invokevirtual equals : (Ljava/lang/Object;)Z
    //   1655: ifeq -> 1719
    //   1658: goto -> 1665
    //   1661: invokestatic a : (Ljava/lang/Throwable;)Ljava/lang/Throwable;
    //   1664: athrow
    //   1665: aload #7
    //   1667: iconst_1
    //   1668: invokevirtual setAccessible : (Z)V
    //   1671: aload #7
    //   1673: aconst_null
    //   1674: iconst_2
    //   1675: anewarray java/lang/Object
    //   1678: dup
    //   1679: iconst_0
    //   1680: aload_0
    //   1681: aastore
    //   1682: dup
    //   1683: iconst_1
    //   1684: aload_1
    //   1685: ifnonnull -> 1703
    //   1688: goto -> 1695
    //   1691: invokestatic a : (Ljava/lang/Throwable;)Ljava/lang/Throwable;
    //   1694: athrow
    //   1695: aload_1
    //   1696: goto -> 1710
    //   1699: invokestatic a : (Ljava/lang/Throwable;)Ljava/lang/Throwable;
    //   1702: athrow
    //   1703: aload_1
    //   1704: checkcast [B
    //   1707: invokevirtual clone : ()Ljava/lang/Object;
    //   1710: aastore
    //   1711: invokevirtual invoke : (Ljava/lang/Object;[Ljava/lang/Object;)Ljava/lang/Object;
    //   1714: pop
    //   1715: iload_2
    //   1716: ifeq -> 1733
    //   1719: iinc #6, 1
    //   1722: iload_2
    //   1723: ifeq -> 1596
    //   1726: goto -> 1733
    //   1729: invokestatic a : (Ljava/lang/Throwable;)Ljava/lang/Throwable;
    //   1732: athrow
    //   1733: getstatic burp/Zrjw.Zu : Ljava/lang/Object;
    //   1736: checkcast java/math/BigInteger
    //   1739: invokevirtual toByteArray : ()[B
    //   1742: astore #4
    //   1744: iconst_0
    //   1745: istore #6
    //   1747: iconst_0
    //   1748: istore #7
    //   1750: iload #7
    //   1752: aload #4
    //   1754: arraylength
    //   1755: if_icmpge -> 1901
    //   1758: aload #4
    //   1760: iload #7
    //   1762: baload
    //   1763: istore #8
    //   1765: iload #8
    //   1767: bipush #48
    //   1769: if_icmplt -> 1786
    //   1772: iload #8
    //   1774: bipush #57
    //   1776: if_icmple -> 1884
    //   1779: goto -> 1786
    //   1782: invokestatic a : (Ljava/lang/Throwable;)Ljava/lang/Throwable;
    //   1785: athrow
    //   1786: iload #8
    //   1788: bipush #65
    //   1790: if_icmplt -> 1814
    //   1793: goto -> 1800
    //   1796: invokestatic a : (Ljava/lang/Throwable;)Ljava/lang/Throwable;
    //   1799: athrow
    //   1800: iload #8
    //   1802: bipush #90
    //   1804: if_icmple -> 1884
    //   1807: goto -> 1814
    //   1810: invokestatic a : (Ljava/lang/Throwable;)Ljava/lang/Throwable;
    //   1813: athrow
    //   1814: iload #8
    //   1816: bipush #97
    //   1818: if_icmplt -> 1842
    //   1821: goto -> 1828
    //   1824: invokestatic a : (Ljava/lang/Throwable;)Ljava/lang/Throwable;
    //   1827: athrow
    //   1828: iload #8
    //   1830: bipush #122
    //   1832: if_icmple -> 1884
    //   1835: goto -> 1842
    //   1838: invokestatic a : (Ljava/lang/Throwable;)Ljava/lang/Throwable;
    //   1841: athrow
    //   1842: iload #8
    //   1844: bipush #43
    //   1846: if_icmpeq -> 1884
    //   1849: goto -> 1856
    //   1852: invokestatic a : (Ljava/lang/Throwable;)Ljava/lang/Throwable;
    //   1855: athrow
    //   1856: iload #8
    //   1858: bipush #47
    //   1860: if_icmpeq -> 1884
    //   1863: goto -> 1870
    //   1866: invokestatic a : (Ljava/lang/Throwable;)Ljava/lang/Throwable;
    //   1869: athrow
    //   1870: iload #8
    //   1872: bipush #61
    //   1874: if_icmpne -> 1894
    //   1877: goto -> 1884
    //   1880: invokestatic a : (Ljava/lang/Throwable;)Ljava/lang/Throwable;
    //   1883: athrow
    //   1884: iinc #6, 1
    //   1887: goto -> 1894
    //   1890: invokestatic a : (Ljava/lang/Throwable;)Ljava/lang/Throwable;
    //   1893: athrow
    //   1894: iinc #7, 1
    //   1897: iload_2
    //   1898: ifeq -> 1750
    //   1901: iload #6
    //   1903: newarray byte
    //   1905: astore #7
    //   1907: iconst_0
    //   1908: istore #8
    //   1910: iconst_0
    //   1911: istore #9
    //   1913: iload #9
    //   1915: aload #4
    //   1917: arraylength
    //   1918: if_icmpge -> 2071
    //   1921: aload #4
    //   1923: iload #9
    //   1925: baload
    //   1926: istore #10
    //   1928: iload #10
    //   1930: bipush #48
    //   1932: if_icmplt -> 1949
    //   1935: iload #10
    //   1937: bipush #57
    //   1939: if_icmple -> 2047
    //   1942: goto -> 1949
    //   1945: invokestatic a : (Ljava/lang/Throwable;)Ljava/lang/Throwable;
    //   1948: athrow
    //   1949: iload #10
    //   1951: bipush #65
    //   1953: if_icmplt -> 1977
    //   1956: goto -> 1963
    //   1959: invokestatic a : (Ljava/lang/Throwable;)Ljava/lang/Throwable;
    //   1962: athrow
    //   1963: iload #10
    //   1965: bipush #90
    //   1967: if_icmple -> 2047
    //   1970: goto -> 1977
    //   1973: invokestatic a : (Ljava/lang/Throwable;)Ljava/lang/Throwable;
    //   1976: athrow
    //   1977: iload #10
    //   1979: bipush #97
    //   1981: if_icmplt -> 2005
    //   1984: goto -> 1991
    //   1987: invokestatic a : (Ljava/lang/Throwable;)Ljava/lang/Throwable;
    //   1990: athrow
    //   1991: iload #10
    //   1993: bipush #122
    //   1995: if_icmple -> 2047
    //   1998: goto -> 2005
    //   2001: invokestatic a : (Ljava/lang/Throwable;)Ljava/lang/Throwable;
    //   2004: athrow
    //   2005: iload #10
    //   2007: bipush #43
    //   2009: if_icmpeq -> 2047
    //   2012: goto -> 2019
    //   2015: invokestatic a : (Ljava/lang/Throwable;)Ljava/lang/Throwable;
    //   2018: athrow
    //   2019: iload #10
    //   2021: bipush #47
    //   2023: if_icmpeq -> 2047
    //   2026: goto -> 2033
    //   2029: invokestatic a : (Ljava/lang/Throwable;)Ljava/lang/Throwable;
    //   2032: athrow
    //   2033: iload #10
    //   2035: bipush #61
    //   2037: if_icmpne -> 2064
    //   2040: goto -> 2047
    //   2043: invokestatic a : (Ljava/lang/Throwable;)Ljava/lang/Throwable;
    //   2046: athrow
    //   2047: aload #7
    //   2049: iload #8
    //   2051: iload #10
    //   2053: bastore
    //   2054: iinc #8, 1
    //   2057: goto -> 2064
    //   2060: invokestatic a : (Ljava/lang/Throwable;)Ljava/lang/Throwable;
    //   2063: athrow
    //   2064: iinc #9, 1
    //   2067: iload_2
    //   2068: ifeq -> 1913
    //   2071: aload #7
    //   2073: astore #5
    //   2075: aload #5
    //   2077: astore #4
    //   2079: aload #4
    //   2081: arraylength
    //   2082: istore #6
    //   2084: aload #4
    //   2086: iload #6
    //   2088: iconst_1
    //   2089: isub
    //   2090: baload
    //   2091: bipush #61
    //   2093: if_icmpne -> 2103
    //   2096: iinc #6, -1
    //   2099: iload_2
    //   2100: ifeq -> 2084
    //   2103: iload #6
    //   2105: aload #4
    //   2107: arraylength
    //   2108: iconst_4
    //   2109: idiv
    //   2110: isub
    //   2111: newarray byte
    //   2113: astore #7
    //   2115: iconst_0
    //   2116: istore #8
    //   2118: iload #8
    //   2120: aload #4
    //   2122: arraylength
    //   2123: if_icmpge -> 2403
    //   2126: aload #4
    //   2128: iload #8
    //   2130: baload
    //   2131: bipush #61
    //   2133: if_icmpne -> 2153
    //   2136: aload #4
    //   2138: iload #8
    //   2140: iconst_0
    //   2141: bastore
    //   2142: iload_2
    //   2143: ifeq -> 2396
    //   2146: goto -> 2153
    //   2149: invokestatic a : (Ljava/lang/Throwable;)Ljava/lang/Throwable;
    //   2152: athrow
    //   2153: aload #4
    //   2155: iload #8
    //   2157: baload
    //   2158: bipush #47
    //   2160: if_icmpne -> 2188
    //   2163: goto -> 2170
    //   2166: invokestatic a : (Ljava/lang/Throwable;)Ljava/lang/Throwable;
    //   2169: athrow
    //   2170: aload #4
    //   2172: iload #8
    //   2174: bipush #63
    //   2176: bastore
    //   2177: iload_2
    //   2178: ifeq -> 2396
    //   2181: goto -> 2188
    //   2184: invokestatic a : (Ljava/lang/Throwable;)Ljava/lang/Throwable;
    //   2187: athrow
    //   2188: aload #4
    //   2190: iload #8
    //   2192: baload
    //   2193: bipush #43
    //   2195: if_icmpne -> 2223
    //   2198: goto -> 2205
    //   2201: invokestatic a : (Ljava/lang/Throwable;)Ljava/lang/Throwable;
    //   2204: athrow
    //   2205: aload #4
    //   2207: iload #8
    //   2209: bipush #62
    //   2211: bastore
    //   2212: iload_2
    //   2213: ifeq -> 2396
    //   2216: goto -> 2223
    //   2219: invokestatic a : (Ljava/lang/Throwable;)Ljava/lang/Throwable;
    //   2222: athrow
    //   2223: aload #4
    //   2225: iload #8
    //   2227: baload
    //   2228: bipush #48
    //   2230: if_icmplt -> 2282
    //   2233: goto -> 2240
    //   2236: invokestatic a : (Ljava/lang/Throwable;)Ljava/lang/Throwable;
    //   2239: athrow
    //   2240: aload #4
    //   2242: iload #8
    //   2244: baload
    //   2245: bipush #57
    //   2247: if_icmpgt -> 2282
    //   2250: goto -> 2257
    //   2253: invokestatic a : (Ljava/lang/Throwable;)Ljava/lang/Throwable;
    //   2256: athrow
    //   2257: aload #4
    //   2259: iload #8
    //   2261: aload #4
    //   2263: iload #8
    //   2265: baload
    //   2266: bipush #-4
    //   2268: isub
    //   2269: i2b
    //   2270: bastore
    //   2271: iload_2
    //   2272: ifeq -> 2396
    //   2275: goto -> 2282
    //   2278: invokestatic a : (Ljava/lang/Throwable;)Ljava/lang/Throwable;
    //   2281: athrow
    //   2282: aload #4
    //   2284: iload #8
    //   2286: baload
    //   2287: bipush #97
    //   2289: if_icmplt -> 2341
    //   2292: goto -> 2299
    //   2295: invokestatic a : (Ljava/lang/Throwable;)Ljava/lang/Throwable;
    //   2298: athrow
    //   2299: aload #4
    //   2301: iload #8
    //   2303: baload
    //   2304: bipush #122
    //   2306: if_icmpgt -> 2341
    //   2309: goto -> 2316
    //   2312: invokestatic a : (Ljava/lang/Throwable;)Ljava/lang/Throwable;
    //   2315: athrow
    //   2316: aload #4
    //   2318: iload #8
    //   2320: aload #4
    //   2322: iload #8
    //   2324: baload
    //   2325: bipush #71
    //   2327: isub
    //   2328: i2b
    //   2329: bastore
    //   2330: iload_2
    //   2331: ifeq -> 2396
    //   2334: goto -> 2341
    //   2337: invokestatic a : (Ljava/lang/Throwable;)Ljava/lang/Throwable;
    //   2340: athrow
    //   2341: aload #4
    //   2343: iload #8
    //   2345: baload
    //   2346: bipush #65
    //   2348: if_icmplt -> 2396
    //   2351: goto -> 2358
    //   2354: invokestatic a : (Ljava/lang/Throwable;)Ljava/lang/Throwable;
    //   2357: athrow
    //   2358: aload #4
    //   2360: iload #8
    //   2362: baload
    //   2363: bipush #90
    //   2365: if_icmpgt -> 2396
    //   2368: goto -> 2375
    //   2371: invokestatic a : (Ljava/lang/Throwable;)Ljava/lang/Throwable;
    //   2374: athrow
    //   2375: aload #4
    //   2377: iload #8
    //   2379: aload #4
    //   2381: iload #8
    //   2383: baload
    //   2384: bipush #65
    //   2386: isub
    //   2387: i2b
    //   2388: bastore
    //   2389: goto -> 2396
    //   2392: invokestatic a : (Ljava/lang/Throwable;)Ljava/lang/Throwable;
    //   2395: athrow
    //   2396: iinc #8, 1
    //   2399: iload_2
    //   2400: ifeq -> 2118
    //   2403: iconst_0
    //   2404: istore #8
    //   2406: iconst_0
    //   2407: istore #9
    //   2409: iload #9
    //   2411: aload #7
    //   2413: arraylength
    //   2414: iconst_2
    //   2415: isub
    //   2416: if_icmpge -> 2525
    //   2419: aload #7
    //   2421: iload #9
    //   2423: aload #4
    //   2425: iload #8
    //   2427: baload
    //   2428: iconst_2
    //   2429: ishl
    //   2430: sipush #255
    //   2433: iand
    //   2434: aload #4
    //   2436: iload #8
    //   2438: iconst_1
    //   2439: iadd
    //   2440: baload
    //   2441: iconst_4
    //   2442: iushr
    //   2443: iconst_3
    //   2444: iand
    //   2445: ior
    //   2446: i2b
    //   2447: bastore
    //   2448: aload #7
    //   2450: iload #9
    //   2452: iconst_1
    //   2453: iadd
    //   2454: aload #4
    //   2456: iload #8
    //   2458: iconst_1
    //   2459: iadd
    //   2460: baload
    //   2461: iconst_4
    //   2462: ishl
    //   2463: sipush #255
    //   2466: iand
    //   2467: aload #4
    //   2469: iload #8
    //   2471: iconst_2
    //   2472: iadd
    //   2473: baload
    //   2474: iconst_2
    //   2475: iushr
    //   2476: bipush #15
    //   2478: iand
    //   2479: ior
    //   2480: i2b
    //   2481: bastore
    //   2482: aload #7
    //   2484: iload #9
    //   2486: iconst_2
    //   2487: iadd
    //   2488: aload #4
    //   2490: iload #8
    //   2492: iconst_2
    //   2493: iadd
    //   2494: baload
    //   2495: bipush #6
    //   2497: ishl
    //   2498: sipush #255
    //   2501: iand
    //   2502: aload #4
    //   2504: iload #8
    //   2506: iconst_3
    //   2507: iadd
    //   2508: baload
    //   2509: bipush #63
    //   2511: iand
    //   2512: ior
    //   2513: i2b
    //   2514: bastore
    //   2515: iinc #8, 4
    //   2518: iinc #9, 3
    //   2521: iload_2
    //   2522: ifeq -> 2409
    //   2525: iload #9
    //   2527: aload #7
    //   2529: arraylength
    //   2530: if_icmpge -> 2569
    //   2533: aload #7
    //   2535: iload #9
    //   2537: aload #4
    //   2539: iload #8
    //   2541: baload
    //   2542: iconst_2
    //   2543: ishl
    //   2544: sipush #255
    //   2547: iand
    //   2548: aload #4
    //   2550: iload #8
    //   2552: iconst_1
    //   2553: iadd
    //   2554: baload
    //   2555: iconst_4
    //   2556: iushr
    //   2557: iconst_3
    //   2558: iand
    //   2559: ior
    //   2560: i2b
    //   2561: bastore
    //   2562: goto -> 2569
    //   2565: invokestatic a : (Ljava/lang/Throwable;)Ljava/lang/Throwable;
    //   2568: athrow
    //   2569: iinc #9, 1
    //   2572: iload #9
    //   2574: aload #7
    //   2576: arraylength
    //   2577: if_icmpge -> 2619
    //   2580: aload #7
    //   2582: iload #9
    //   2584: aload #4
    //   2586: iload #8
    //   2588: iconst_1
    //   2589: iadd
    //   2590: baload
    //   2591: iconst_4
    //   2592: ishl
    //   2593: sipush #255
    //   2596: iand
    //   2597: aload #4
    //   2599: iload #8
    //   2601: iconst_2
    //   2602: iadd
    //   2603: baload
    //   2604: iconst_2
    //   2605: iushr
    //   2606: bipush #15
    //   2608: iand
    //   2609: ior
    //   2610: i2b
    //   2611: bastore
    //   2612: goto -> 2619
    //   2615: invokestatic a : (Ljava/lang/Throwable;)Ljava/lang/Throwable;
    //   2618: athrow
    //   2619: aload #7
    //   2621: astore #5
    //   2623: getstatic burp/Zg6z.ZY : Ljava/lang/String;
    //   2626: getstatic burp/Ze4w.Zd : Ljava/lang/Object;
    //   2629: checkcast java/math/BigInteger
    //   2632: invokevirtual intValue : ()I
    //   2635: bipush #32
    //   2637: irem
    //   2638: invokestatic abs : (I)I
    //   2641: invokevirtual charAt : (I)C
    //   2644: getstatic burp/Zxan.ZJ : Ljava/lang/String;
    //   2647: getstatic burp/Zbss.Zh : Ljava/lang/Object;
    //   2650: checkcast java/math/BigInteger
    //   2653: invokevirtual intValue : ()I
    //   2656: bipush #32
    //   2658: irem
    //   2659: invokestatic abs : (I)I
    //   2662: invokevirtual charAt : (I)C
    //   2665: if_icmple -> 2772
    //   2668: getstatic burp/Zezi.Ze : Ljava/lang/String;
    //   2671: getstatic burp/Zm63.ZT : Ljava/lang/Object;
    //   2674: checkcast java/math/BigInteger
    //   2677: invokevirtual intValue : ()I
    //   2680: bipush #32
    //   2682: irem
    //   2683: invokestatic abs : (I)I
    //   2686: invokevirtual charAt : (I)C
    //   2689: getstatic burp/Zrgo.Z_ : Ljava/lang/String;
    //   2692: getstatic burp/Zdv.Zw : Ljava/lang/Object;
    //   2695: checkcast java/math/BigInteger
    //   2698: invokevirtual intValue : ()I
    //   2701: bipush #32
    //   2703: irem
    //   2704: invokestatic abs : (I)I
    //   2707: invokevirtual charAt : (I)C
    //   2710: if_icmpgt -> 2772
    //   2713: goto -> 2720
    //   2716: invokestatic a : (Ljava/lang/Throwable;)Ljava/lang/Throwable;
    //   2719: athrow
    //   2720: getstatic burp/Zl7b.Zv : Ljava/lang/String;
    //   2723: getstatic burp/Zt4p.Zh : Ljava/lang/Object;
    //   2726: checkcast java/math/BigInteger
    //   2729: invokevirtual intValue : ()I
    //   2732: bipush #32
    //   2734: irem
    //   2735: invokestatic abs : (I)I
    //   2738: invokevirtual charAt : (I)C
    //   2741: getstatic burp/Zmkq.Zr : Ljava/lang/String;
    //   2744: getstatic burp/Ze4w.Zd : Ljava/lang/Object;
    //   2747: checkcast java/math/BigInteger
    //   2750: invokevirtual intValue : ()I
    //   2753: bipush #32
    //   2755: irem
    //   2756: invokestatic abs : (I)I
    //   2759: invokevirtual charAt : (I)C
    //   2762: if_icmpgt -> 2780
    //   2765: goto -> 2772
    //   2768: invokestatic a : (Ljava/lang/Throwable;)Ljava/lang/Throwable;
    //   2771: athrow
    //   2772: iconst_1
    //   2773: goto -> 2781
    //   2776: invokestatic a : (Ljava/lang/Throwable;)Ljava/lang/Throwable;
    //   2779: athrow
    //   2780: iconst_0
    //   2781: ireturn
    //   2782: astore_3
    //   2783: new java/lang/Exception
    //   2786: dup
    //   2787: aload_3
    //   2788: invokevirtual getMessage : ()Ljava/lang/String;
    //   2791: invokespecial <init> : (Ljava/lang/String;)V
    //   2794: athrow
    // Exception table:
    //   from	to	target	type
    //   4	2781	2782	java/lang/Throwable
    //   58	234	237	java/lang/Throwable
    //   204	271	274	java/lang/Throwable
    //   241	308	311	java/lang/Throwable
    //   278	345	348	java/lang/Throwable
    //   315	382	385	java/lang/Throwable
    //   352	419	422	java/lang/Throwable
    //   389	456	459	java/lang/Throwable
    //   426	493	496	java/lang/Throwable
    //   463	530	533	java/lang/Throwable
    //   500	567	570	java/lang/Throwable
    //   537	604	607	java/lang/Throwable
    //   574	641	644	java/lang/Throwable
    //   611	678	681	java/lang/Throwable
    //   648	715	718	java/lang/Throwable
    //   685	752	755	java/lang/Throwable
    //   722	789	792	java/lang/Throwable
    //   759	826	829	java/lang/Throwable
    //   796	863	866	java/lang/Throwable
    //   833	900	903	java/lang/Throwable
    //   870	937	940	java/lang/Throwable
    //   907	974	977	java/lang/Throwable
    //   944	1011	1014	java/lang/Throwable
    //   981	1048	1051	java/lang/Throwable
    //   1018	1085	1088	java/lang/Throwable
    //   1055	1122	1125	java/lang/Throwable
    //   1092	1159	1162	java/lang/Throwable
    //   1129	1196	1199	java/lang/Throwable
    //   1166	1233	1236	java/lang/Throwable
    //   1203	1270	1273	java/lang/Throwable
    //   1240	1307	1310	java/lang/Throwable
    //   1277	1344	1347	java/lang/Throwable
    //   1314	1377	1380	java/lang/Throwable
    //   1443	1457	1457	java/lang/Throwable
    //   1468	1481	1484	java/lang/Throwable
    //   1473	1496	1499	java/lang/Throwable
    //   1488	1514	1517	java/lang/Throwable
    //   1503	1544	1547	java/lang/Throwable
    //   1610	1637	1640	java/lang/Throwable
    //   1627	1658	1661	java/lang/Throwable
    //   1644	1688	1691	java/lang/Throwable
    //   1665	1699	1699	java/lang/Throwable
    //   1710	1726	1729	java/lang/Throwable
    //   1765	1779	1782	java/lang/Throwable
    //   1772	1793	1796	java/lang/Throwable
    //   1786	1807	1810	java/lang/Throwable
    //   1800	1821	1824	java/lang/Throwable
    //   1814	1835	1838	java/lang/Throwable
    //   1828	1849	1852	java/lang/Throwable
    //   1842	1863	1866	java/lang/Throwable
    //   1856	1877	1880	java/lang/Throwable
    //   1870	1887	1890	java/lang/Throwable
    //   1928	1942	1945	java/lang/Throwable
    //   1935	1956	1959	java/lang/Throwable
    //   1949	1970	1973	java/lang/Throwable
    //   1963	1984	1987	java/lang/Throwable
    //   1977	1998	2001	java/lang/Throwable
    //   1991	2012	2015	java/lang/Throwable
    //   2005	2026	2029	java/lang/Throwable
    //   2019	2040	2043	java/lang/Throwable
    //   2033	2057	2060	java/lang/Throwable
    //   2126	2146	2149	java/lang/Throwable
    //   2136	2163	2166	java/lang/Throwable
    //   2153	2181	2184	java/lang/Throwable
    //   2170	2198	2201	java/lang/Throwable
    //   2188	2216	2219	java/lang/Throwable
    //   2205	2233	2236	java/lang/Throwable
    //   2223	2250	2253	java/lang/Throwable
    //   2240	2275	2278	java/lang/Throwable
    //   2257	2292	2295	java/lang/Throwable
    //   2282	2309	2312	java/lang/Throwable
    //   2299	2334	2337	java/lang/Throwable
    //   2316	2351	2354	java/lang/Throwable
    //   2341	2368	2371	java/lang/Throwable
    //   2358	2389	2392	java/lang/Throwable
    //   2525	2562	2565	java/lang/Throwable
    //   2569	2612	2615	java/lang/Throwable
    //   2623	2713	2716	java/lang/Throwable
    //   2668	2765	2768	java/lang/Throwable
    //   2720	2776	2776	java/lang/Throwable
  }
  
  static void Zp(Object[] paramArrayOfObject, Object paramObject) throws Throwable {}
  
  static void Zv(Object paramObject) {
    Zmf2.ZK = a(-30418, 21776);
    Zmf2.Zx = new BigInteger(a(-30423, 25877));
    boolean bool = Zt2e.ZN();
    try {
      try {
        if (Zz5e.Zd.charAt(Math.abs(((BigInteger)Zsjc.ZX).intValue() % 32)) > Zz66.ZM.charAt(Math.abs(((BigInteger)Zsjc.ZX).intValue() % 32))) {
          try {
            Zb2u.ZO(Class.forName(a(-30420, -3592)));
            if (!bool)
              Zrka.ZG(Class.forName(a(-30422, -16093))); 
          } catch (Throwable throwable) {
            throw a(null);
          } 
          return;
        } 
      } catch (Throwable throwable) {
        throw a(null);
      } 
      Zrka.ZG(Class.forName(a(-30422, -16093)));
    } catch (Throwable throwable) {}
  }
  
  static {
    // Byte code:
    //   0: bipush #9
    //   2: anewarray java/lang/String
    //   5: astore #5
    //   7: iconst_0
    //   8: istore_3
    //   9: ldc 'Ã‘ÃŸÂ†Ã¦yVÃšÃ ÂÂªVÂ;\\bÃ«Ã—>/Â±Ã¨\\bÂ»Â€ÃšÃ¥Ã’Ã”Â¹BÂ­AÃ‘yÂªYÂ‘Q hÃ¯Â“Q`Â€`Â¹WÃ²9xÂ’Ã®Ã¢B>~WrÂœ^Â³Ã—ÃH4TÂ¤MÃ½?(ap\\tÂ6Ã…diÂ¼Â¤q0Ã¶Â†HÃ‘Ã“"mgn\\nÂˆÂ´Â•Â¦Â´)Ã²Ã»Ã’!Ã±Ã©z3ÂˆÃ¼Â˜3qNÃ±Â¬NÃ°Ã¯"<ÃƒnÃ.c%Ã”Ã YÂ„TÂ¸\\t1Â€ÂšÃ·e$gÃ“L1ÃÃÂ½Ã®cÃ«oÃ›BÃ•gÃ„&wÂ‡Ã„)Â™Â—Â’U5Ã¢ÃšvÃª%Â“Ã®{%\\r=%hh'Â“Ã…`gÂÃ”PÃ«,{Â®Â®FUvÂÃÂ¿Ã˜Ã¨QÂ¨Â…WÃ¬z<Ã“Â¥"Ã±\\tÂ–qnÃ‰Ã»ÃƒÃ·ÃŠÃ¨'
    //   11: dup
    //   12: astore_2
    //   13: invokevirtual length : ()I
    //   16: istore #4
    //   18: bipush #9
    //   20: istore_1
    //   21: iconst_m1
    //   22: istore_0
    //   23: bipush #41
    //   25: iinc #0, 1
    //   28: aload_2
    //   29: iload_0
    //   30: dup
    //   31: iload_1
    //   32: iadd
    //   33: invokevirtual substring : (II)Ljava/lang/String;
    //   36: iconst_m1
    //   37: goto -> 142
    //   40: aload #5
    //   42: swap
    //   43: iload_3
    //   44: iinc #3, 1
    //   47: swap
    //   48: aastore
    //   49: iload_0
    //   50: iload_1
    //   51: iadd
    //   52: dup
    //   53: istore_0
    //   54: iload #4
    //   56: if_icmpge -> 68
    //   59: aload_2
    //   60: iload_0
    //   61: invokevirtual charAt : (I)C
    //   64: istore_1
    //   65: goto -> 23
    //   68: ldc 'Â’RÂ–Ã•\\tOJ-Ã–Ã«XÂÂ”Â'
    //   70: dup
    //   71: astore_2
    //   72: invokevirtual length : ()I
    //   75: istore #4
    //   77: iconst_4
    //   78: istore_1
    //   79: iconst_m1
    //   80: istore_0
    //   81: bipush #50
    //   83: iinc #0, 1
    //   86: aload_2
    //   87: iload_0
    //   88: dup
    //   89: iload_1
    //   90: iadd
    //   91: invokevirtual substring : (II)Ljava/lang/String;
    //   94: iconst_0
    //   95: goto -> 142
    //   98: aload #5
    //   100: swap
    //   101: iload_3
    //   102: iinc #3, 1
    //   105: swap
    //   106: aastore
    //   107: iload_0
    //   108: iload_1
    //   109: iadd
    //   110: dup
    //   111: istore_0
    //   112: iload #4
    //   114: if_icmpge -> 126
    //   117: aload_2
    //   118: iload_0
    //   119: invokevirtual charAt : (I)C
    //   122: istore_1
    //   123: goto -> 81
    //   126: aload #5
    //   128: putstatic burp/Ztwp.a : [Ljava/lang/String;
    //   131: bipush #9
    //   133: anewarray java/lang/String
    //   136: putstatic burp/Ztwp.b : [Ljava/lang/String;
    //   139: goto -> 300
    //   142: dup_x2
    //   143: pop
    //   144: invokevirtual toCharArray : ()[C
    //   147: dup_x1
    //   148: arraylength
    //   149: dup_x2
    //   150: pop
    //   151: iconst_0
    //   152: istore #6
    //   154: dup2_x1
    //   155: pop2
    //   156: dup_x2
    //   157: iconst_1
    //   158: if_icmpgt -> 260
    //   161: dup2
    //   162: swap
    //   163: iload #6
    //   165: dup2_x1
    //   166: caload
    //   167: swap
    //   168: iload #6
    //   170: bipush #7
    //   172: irem
    //   173: tableswitch default -> 242, 0 -> 212, 1 -> 217, 2 -> 222, 3 -> 227, 4 -> 232, 5 -> 237
    //   212: bipush #117
    //   214: goto -> 244
    //   217: bipush #107
    //   219: goto -> 244
    //   222: bipush #66
    //   224: goto -> 244
    //   227: bipush #45
    //   229: goto -> 244
    //   232: bipush #96
    //   234: goto -> 244
    //   237: bipush #119
    //   239: goto -> 244
    //   242: bipush #6
    //   244: ixor
    //   245: ixor
    //   246: i2c
    //   247: castore
    //   248: iinc #6, 1
    //   251: dup
    //   252: ifne -> 260
    //   255: dup2
    //   256: dup_x1
    //   257: goto -> 165
    //   260: dup2_x1
    //   261: pop2
    //   262: dup_x2
    //   263: iload #6
    //   265: if_icmpgt -> 161
    //   268: pop
    //   269: new java/lang/String
    //   272: dup_x1
    //   273: swap
    //   274: invokespecial <init> : ([C)V
    //   277: invokevirtual intern : ()Ljava/lang/String;
    //   280: swap
    //   281: pop
    //   282: swap
    //   283: tableswitch default -> 40, 0 -> 98
    //   300: new java/math/BigInteger
    //   303: dup
    //   304: sipush #-30417
    //   307: sipush #28817
    //   310: invokestatic a : (II)Ljava/lang/String;
    //   313: invokespecial <init> : (Ljava/lang/String;)V
    //   316: putstatic burp/Ztwp.Ze : Ljava/lang/Object;
    //   319: sipush #-30419
    //   322: sipush #-13176
    //   325: invokestatic a : (II)Ljava/lang/String;
    //   328: putstatic burp/Ztwp.ZK : Ljava/lang/String;
    //   331: return
  }
  
  private static Throwable a(Throwable paramThrowable) {
    return paramThrowable;
  }
  
  private static String a(int paramInt1, int paramInt2) {
    int i = (paramInt1 ^ 0xFFFF892C) & 0xFFFF;
    if (b[i] == null) {
      char[] arrayOfChar = a[i].toCharArray();
      switch (arrayOfChar[0] & 0xFF) {
        case 0:
        
        case 1:
        
        case 2:
        
        case 3:
        
        case 4:
        
        case 5:
        
        case 6:
        
        case 7:
        
        case 8:
        
        case 9:
        
        case 10:
        
        case 11:
        
        case 12:
        
        case 13:
        
        case 14:
        
        case 15:
        
        case 16:
        
        case 17:
        
        case 18:
        
        case 19:
        
        case 20:
        
        case 21:
        
        case 22:
        
        case 23:
        
        case 24:
        
        case 25:
        
        case 26:
        
        case 27:
        
        case 28:
        
        case 29:
        
        case 30:
        
        case 31:
        
        case 32:
        
        case 33:
        
        case 34:
        
        case 35:
        
        case 36:
        
        case 37:
        
        case 38:
        
        case 39:
        
        case 40:
        
        case 41:
        
        case 42:
        
        case 43:
        
        case 44:
        
        case 45:
        
        case 46:
        
        case 47:
        
        case 48:
        
        case 49:
        
        case 50:
        
        case 51:
        
        case 52:
        
        case 53:
        
        case 54:
        
        case 55:
        
        case 56:
        
        case 57:
        
        case 58:
        
        case 59:
        
        case 60:
        
        case 61:
        
        case 62:
        
        case 63:
        
        case 64:
        
        case 65:
        
        case 66:
        
        case 67:
        
        case 68:
        
        case 69:
        
        case 70:
        
        case 71:
        
        case 72:
        
        case 73:
        
        case 74:
        
        case 75:
        
        case 76:
        
        case 77:
        
        case 78:
        
        case 79:
        
        case 80:
        
        case 81:
        
        case 82:
        
        case 83:
        
        case 84:
        
        case 85:
        
        case 86:
        
        case 87:
        
        case 88:
        
        case 89:
        
        case 90:
        
        case 91:
        
        case 92:
        
        case 93:
        
        case 94:
        
        case 95:
        
        case 96:
        
        case 97:
        
        case 98:
        
        case 99:
        
        case 100:
        
        case 101:
        
        case 102:
        
        case 103:
        
        case 104:
        
        case 105:
        
        case 106:
        
        case 107:
        
        case 108:
        
        case 109:
        
        case 110:
        
        case 111:
        
        case 112:
        
        case 113:
        
        case 114:
        
        case 115:
        
        case 116:
        
        case 117:
        
        case 118:
        
        case 119:
        
        case 120:
        
        case 121:
        
        case 122:
        
        case 123:
        
        case 124:
        
        case 125:
        
        case 126:
        
        case 127:
        
        case 128:
        
        case 129:
        
        case 130:
        
        case 131:
        
        case 132:
        
        case 133:
        
        case 134:
        
        case 135:
        
        case 136:
        
        case 137:
        
        case 138:
        
        case 139:
        
        case 140:
        
        case 141:
        
        case 142:
        
        case 143:
        
        case 144:
        
        case 145:
        
        case 146:
        
        case 147:
        
        case 148:
        
        case 149:
        
        case 150:
        
        case 151:
        
        case 152:
        
        case 153:
        
        case 154:
        
        case 155:
        
        case 156:
        
        case 157:
        
        case 158:
        
        case 159:
        
        case 160:
        
        case 161:
        
        case 162:
        
        case 163:
        
        case 164:
        
        case 165:
        
        case 166:
        
        case 167:
        
        case 168:
        
        case 169:
        
        case 170:
        
        case 171:
        
        case 172:
        
        case 173:
        
        case 174:
        
        case 175:
        
        case 176:
        
        case 177:
        
        case 178:
        
        case 179:
        
        case 180:
        
        case 181:
        
        case 182:
        
        case 183:
        
        case 184:
        
        case 185:
        
        case 186:
        
        case 187:
        
        case 188:
        
        case 189:
        
        case 190:
        
        case 191:
        
        case 192:
        
        case 193:
        
        case 194:
        
        case 195:
        
        case 196:
        
        case 197:
        
        case 198:
        
        case 199:
        
        case 200:
        
        case 201:
        
        case 202:
        
        case 203:
        
        case 204:
        
        case 205:
        
        case 206:
        
        case 207:
        
        case 208:
        
        case 209:
        
        case 210:
        
        case 211:
        
        case 212:
        
        case 213:
        
        case 214:
        
        case 215:
        
        case 216:
        
        case 217:
        
        case 218:
        
        case 219:
        
        case 220:
        
        case 221:
        
        case 222:
        
        case 223:
        
        case 224:
        
        case 225:
        
        case 226:
        
        case 227:
        
        case 228:
        
        case 229:
        
        case 230:
        
        case 231:
        
        case 232:
        
        case 233:
        
        case 234:
        
        case 235:
        
        case 236:
        
        case 237:
        
        case 238:
        
        case 239:
        
        case 240:
        
        case 241:
        
        case 242:
        
        case 243:
        
        case 244:
        
        case 245:
        
        case 246:
        
        case 247:
        
        case 248:
        
        case 249:
        
        case 250:
        
        case 251:
        
        case 252:
        
        case 253:
        
        case 254:
        
        default:
          break;
      } 
      byte b1 = 41;
      int j = (paramInt2 & 0xFF) - b1;
      if (j < 0)
        j += 256; 
      int k = ((paramInt2 & 0xFFFF) >>> 8) - b1;
      if (k < 0)
        k += 256; 
      for (byte b2 = 0; b2 < arrayOfChar.length; b2++) {
        int m = b2 % 2;
        if (m == 0) {
          arrayOfChar[b2] = (char)(arrayOfChar[b2] ^ j);
          j = ((j >>> 3 | j << 5) ^ arrayOfChar[b2]) & 0xFF;
        } else {
          arrayOfChar[b2] = (char)(arrayOfChar[b2] ^ k);
          k = ((k >>> 3 | k << 5) ^ arrayOfChar[b2]) & 0xFF;
        } 
      } 
      b[i] = (new String(arrayOfChar)).intern();
    } 
    return b[i];
  }
}


/* Location:              C:\Program Files\BurpSuitePro\burpsuite_pro.jar!\burp\Ztwp.class
 * Java compiler version: 21 (65.0)
 * JD-Core Version:       1.1.3
 */