package burp;

import java.math.BigInteger;

class Ztxx extends ClassLoader {
  static String Zt;
  
  static Object ZI;
  
  private static final String[] a;
  
  private static final String[] b;
  
  static void Zb(Object[] paramArrayOfObject, Object paramObject) throws Throwable {}
  
  static boolean Zh(Object[] paramArrayOfObject, Object paramObject) throws Throwable {
    // Byte code:
    //   0: invokestatic ZN : ()Z
    //   3: istore_2
    //   4: new java/lang/StringBuilder
    //   7: dup
    //   8: invokespecial <init> : ()V
    //   11: astore_3
    //   12: iconst_0
    //   13: istore #4
    //   15: iload #4
    //   17: bipush #32
    //   19: if_icmpge -> 1355
    //   22: iload #4
    //   24: tableswitch default -> 1348, 0 -> 168, 1 -> 205, 2 -> 242, 3 -> 279, 4 -> 316, 5 -> 353, 6 -> 390, 7 -> 427, 8 -> 464, 9 -> 501, 10 -> 538, 11 -> 575, 12 -> 612, 13 -> 649, 14 -> 686, 15 -> 723, 16 -> 760, 17 -> 797, 18 -> 834, 19 -> 871, 20 -> 908, 21 -> 945, 22 -> 982, 23 -> 1019, 24 -> 1056, 25 -> 1093, 26 -> 1130, 27 -> 1167, 28 -> 1204, 29 -> 1241, 30 -> 1278, 31 -> 1315
    //   168: aload_3
    //   169: getstatic burp/Zg0j.Ze : Ljava/lang/String;
    //   172: getstatic burp/Ze7q.Zk : Ljava/lang/Object;
    //   175: checkcast java/math/BigInteger
    //   178: invokevirtual intValue : ()I
    //   181: bipush #32
    //   183: irem
    //   184: invokestatic abs : (I)I
    //   187: invokevirtual charAt : (I)C
    //   190: invokevirtual append : (C)Ljava/lang/StringBuilder;
    //   193: pop
    //   194: iload_2
    //   195: ifne -> 1348
    //   198: goto -> 205
    //   201: invokestatic a : (Ljava/lang/Throwable;)Ljava/lang/Throwable;
    //   204: athrow
    //   205: aload_3
    //   206: getstatic burp/Zb3z.Zi : Ljava/lang/String;
    //   209: getstatic burp/Zx54.Zn : Ljava/lang/Object;
    //   212: checkcast java/math/BigInteger
    //   215: invokevirtual intValue : ()I
    //   218: bipush #32
    //   220: irem
    //   221: invokestatic abs : (I)I
    //   224: invokevirtual charAt : (I)C
    //   227: invokevirtual append : (C)Ljava/lang/StringBuilder;
    //   230: pop
    //   231: iload_2
    //   232: ifne -> 1348
    //   235: goto -> 242
    //   238: invokestatic a : (Ljava/lang/Throwable;)Ljava/lang/Throwable;
    //   241: athrow
    //   242: aload_3
    //   243: getstatic burp/Zbsr.Zq : Ljava/lang/String;
    //   246: getstatic burp/Zkfz.Zr : Ljava/lang/Object;
    //   249: checkcast java/math/BigInteger
    //   252: invokevirtual intValue : ()I
    //   255: bipush #32
    //   257: irem
    //   258: invokestatic abs : (I)I
    //   261: invokevirtual charAt : (I)C
    //   264: invokevirtual append : (C)Ljava/lang/StringBuilder;
    //   267: pop
    //   268: iload_2
    //   269: ifne -> 1348
    //   272: goto -> 279
    //   275: invokestatic a : (Ljava/lang/Throwable;)Ljava/lang/Throwable;
    //   278: athrow
    //   279: aload_3
    //   280: getstatic burp/Zr3q.ZM : Ljava/lang/String;
    //   283: getstatic burp/Zt3l.Zq : Ljava/lang/Object;
    //   286: checkcast java/math/BigInteger
    //   289: invokevirtual intValue : ()I
    //   292: bipush #32
    //   294: irem
    //   295: invokestatic abs : (I)I
    //   298: invokevirtual charAt : (I)C
    //   301: invokevirtual append : (C)Ljava/lang/StringBuilder;
    //   304: pop
    //   305: iload_2
    //   306: ifne -> 1348
    //   309: goto -> 316
    //   312: invokestatic a : (Ljava/lang/Throwable;)Ljava/lang/Throwable;
    //   315: athrow
    //   316: aload_3
    //   317: getstatic burp/Zzsq.Zc : Ljava/lang/String;
    //   320: getstatic burp/Zxso.ZF : Ljava/lang/Object;
    //   323: checkcast java/math/BigInteger
    //   326: invokevirtual intValue : ()I
    //   329: bipush #32
    //   331: irem
    //   332: invokestatic abs : (I)I
    //   335: invokevirtual charAt : (I)C
    //   338: invokevirtual append : (C)Ljava/lang/StringBuilder;
    //   341: pop
    //   342: iload_2
    //   343: ifne -> 1348
    //   346: goto -> 353
    //   349: invokestatic a : (Ljava/lang/Throwable;)Ljava/lang/Throwable;
    //   352: athrow
    //   353: aload_3
    //   354: getstatic burp/Zl_u.Zc : Ljava/lang/String;
    //   357: getstatic burp/Zlos.Zk : Ljava/lang/Object;
    //   360: checkcast java/math/BigInteger
    //   363: invokevirtual intValue : ()I
    //   366: bipush #32
    //   368: irem
    //   369: invokestatic abs : (I)I
    //   372: invokevirtual charAt : (I)C
    //   375: invokevirtual append : (C)Ljava/lang/StringBuilder;
    //   378: pop
    //   379: iload_2
    //   380: ifne -> 1348
    //   383: goto -> 390
    //   386: invokestatic a : (Ljava/lang/Throwable;)Ljava/lang/Throwable;
    //   389: athrow
    //   390: aload_3
    //   391: getstatic burp/Zes_.ZM : Ljava/lang/String;
    //   394: getstatic burp/Zxwl.Ze : Ljava/lang/Object;
    //   397: checkcast java/math/BigInteger
    //   400: invokevirtual intValue : ()I
    //   403: bipush #32
    //   405: irem
    //   406: invokestatic abs : (I)I
    //   409: invokevirtual charAt : (I)C
    //   412: invokevirtual append : (C)Ljava/lang/StringBuilder;
    //   415: pop
    //   416: iload_2
    //   417: ifne -> 1348
    //   420: goto -> 427
    //   423: invokestatic a : (Ljava/lang/Throwable;)Ljava/lang/Throwable;
    //   426: athrow
    //   427: aload_3
    //   428: getstatic burp/Zein.ZN : Ljava/lang/String;
    //   431: getstatic burp/Zg_p.Zx : Ljava/lang/Object;
    //   434: checkcast java/math/BigInteger
    //   437: invokevirtual intValue : ()I
    //   440: bipush #32
    //   442: irem
    //   443: invokestatic abs : (I)I
    //   446: invokevirtual charAt : (I)C
    //   449: invokevirtual append : (C)Ljava/lang/StringBuilder;
    //   452: pop
    //   453: iload_2
    //   454: ifne -> 1348
    //   457: goto -> 464
    //   460: invokestatic a : (Ljava/lang/Throwable;)Ljava/lang/Throwable;
    //   463: athrow
    //   464: aload_3
    //   465: getstatic burp/Zshq.Zi : Ljava/lang/String;
    //   468: getstatic burp/Zg7p.Zb : Ljava/lang/Object;
    //   471: checkcast java/math/BigInteger
    //   474: invokevirtual intValue : ()I
    //   477: bipush #32
    //   479: irem
    //   480: invokestatic abs : (I)I
    //   483: invokevirtual charAt : (I)C
    //   486: invokevirtual append : (C)Ljava/lang/StringBuilder;
    //   489: pop
    //   490: iload_2
    //   491: ifne -> 1348
    //   494: goto -> 501
    //   497: invokestatic a : (Ljava/lang/Throwable;)Ljava/lang/Throwable;
    //   500: athrow
    //   501: aload_3
    //   502: getstatic burp/Zxwl.Zu : Ljava/lang/String;
    //   505: getstatic burp/Zsxm.Zv : Ljava/lang/Object;
    //   508: checkcast java/math/BigInteger
    //   511: invokevirtual intValue : ()I
    //   514: bipush #32
    //   516: irem
    //   517: invokestatic abs : (I)I
    //   520: invokevirtual charAt : (I)C
    //   523: invokevirtual append : (C)Ljava/lang/StringBuilder;
    //   526: pop
    //   527: iload_2
    //   528: ifne -> 1348
    //   531: goto -> 538
    //   534: invokestatic a : (Ljava/lang/Throwable;)Ljava/lang/Throwable;
    //   537: athrow
    //   538: aload_3
    //   539: getstatic burp/Ze7q.ZW : Ljava/lang/String;
    //   542: getstatic burp/Zsde.Zx : Ljava/lang/Object;
    //   545: checkcast java/math/BigInteger
    //   548: invokevirtual intValue : ()I
    //   551: bipush #32
    //   553: irem
    //   554: invokestatic abs : (I)I
    //   557: invokevirtual charAt : (I)C
    //   560: invokevirtual append : (C)Ljava/lang/StringBuilder;
    //   563: pop
    //   564: iload_2
    //   565: ifne -> 1348
    //   568: goto -> 575
    //   571: invokestatic a : (Ljava/lang/Throwable;)Ljava/lang/Throwable;
    //   574: athrow
    //   575: aload_3
    //   576: getstatic burp/Zkyc.ZK : Ljava/lang/String;
    //   579: getstatic burp/Zl_k.ZH : Ljava/lang/Object;
    //   582: checkcast java/math/BigInteger
    //   585: invokevirtual intValue : ()I
    //   588: bipush #32
    //   590: irem
    //   591: invokestatic abs : (I)I
    //   594: invokevirtual charAt : (I)C
    //   597: invokevirtual append : (C)Ljava/lang/StringBuilder;
    //   600: pop
    //   601: iload_2
    //   602: ifne -> 1348
    //   605: goto -> 612
    //   608: invokestatic a : (Ljava/lang/Throwable;)Ljava/lang/Throwable;
    //   611: athrow
    //   612: aload_3
    //   613: getstatic burp/Zzap.ZA : Ljava/lang/String;
    //   616: getstatic burp/Ze3j.Ze : Ljava/lang/Object;
    //   619: checkcast java/math/BigInteger
    //   622: invokevirtual intValue : ()I
    //   625: bipush #32
    //   627: irem
    //   628: invokestatic abs : (I)I
    //   631: invokevirtual charAt : (I)C
    //   634: invokevirtual append : (C)Ljava/lang/StringBuilder;
    //   637: pop
    //   638: iload_2
    //   639: ifne -> 1348
    //   642: goto -> 649
    //   645: invokestatic a : (Ljava/lang/Throwable;)Ljava/lang/Throwable;
    //   648: athrow
    //   649: aload_3
    //   650: getstatic burp/Zkbf.Zv : Ljava/lang/String;
    //   653: getstatic burp/Ztbf.Zv : Ljava/lang/Object;
    //   656: checkcast java/math/BigInteger
    //   659: invokevirtual intValue : ()I
    //   662: bipush #32
    //   664: irem
    //   665: invokestatic abs : (I)I
    //   668: invokevirtual charAt : (I)C
    //   671: invokevirtual append : (C)Ljava/lang/StringBuilder;
    //   674: pop
    //   675: iload_2
    //   676: ifne -> 1348
    //   679: goto -> 686
    //   682: invokestatic a : (Ljava/lang/Throwable;)Ljava/lang/Throwable;
    //   685: athrow
    //   686: aload_3
    //   687: getstatic burp/Zmj4.ZM : Ljava/lang/String;
    //   690: getstatic burp/Zlhm.ZT : Ljava/lang/Object;
    //   693: checkcast java/math/BigInteger
    //   696: invokevirtual intValue : ()I
    //   699: bipush #32
    //   701: irem
    //   702: invokestatic abs : (I)I
    //   705: invokevirtual charAt : (I)C
    //   708: invokevirtual append : (C)Ljava/lang/StringBuilder;
    //   711: pop
    //   712: iload_2
    //   713: ifne -> 1348
    //   716: goto -> 723
    //   719: invokestatic a : (Ljava/lang/Throwable;)Ljava/lang/Throwable;
    //   722: athrow
    //   723: aload_3
    //   724: getstatic burp/Zl2q.ZI : Ljava/lang/String;
    //   727: getstatic burp/Zzsq.Zh : Ljava/lang/Object;
    //   730: checkcast java/math/BigInteger
    //   733: invokevirtual intValue : ()I
    //   736: bipush #32
    //   738: irem
    //   739: invokestatic abs : (I)I
    //   742: invokevirtual charAt : (I)C
    //   745: invokevirtual append : (C)Ljava/lang/StringBuilder;
    //   748: pop
    //   749: iload_2
    //   750: ifne -> 1348
    //   753: goto -> 760
    //   756: invokestatic a : (Ljava/lang/Throwable;)Ljava/lang/Throwable;
    //   759: athrow
    //   760: aload_3
    //   761: getstatic burp/Zkig.ZE : Ljava/lang/String;
    //   764: getstatic burp/Ztnw.Zt : Ljava/lang/Object;
    //   767: checkcast java/math/BigInteger
    //   770: invokevirtual intValue : ()I
    //   773: bipush #32
    //   775: irem
    //   776: invokestatic abs : (I)I
    //   779: invokevirtual charAt : (I)C
    //   782: invokevirtual append : (C)Ljava/lang/StringBuilder;
    //   785: pop
    //   786: iload_2
    //   787: ifne -> 1348
    //   790: goto -> 797
    //   793: invokestatic a : (Ljava/lang/Throwable;)Ljava/lang/Throwable;
    //   796: athrow
    //   797: aload_3
    //   798: getstatic burp/Zkfz.Zs : Ljava/lang/String;
    //   801: getstatic burp/Ze13.ZD : Ljava/lang/Object;
    //   804: checkcast java/math/BigInteger
    //   807: invokevirtual intValue : ()I
    //   810: bipush #32
    //   812: irem
    //   813: invokestatic abs : (I)I
    //   816: invokevirtual charAt : (I)C
    //   819: invokevirtual append : (C)Ljava/lang/StringBuilder;
    //   822: pop
    //   823: iload_2
    //   824: ifne -> 1348
    //   827: goto -> 834
    //   830: invokestatic a : (Ljava/lang/Throwable;)Ljava/lang/Throwable;
    //   833: athrow
    //   834: aload_3
    //   835: getstatic burp/Ztuj.Zk : Ljava/lang/String;
    //   838: getstatic burp/Zsm3.ZC : Ljava/lang/Object;
    //   841: checkcast java/math/BigInteger
    //   844: invokevirtual intValue : ()I
    //   847: bipush #32
    //   849: irem
    //   850: invokestatic abs : (I)I
    //   853: invokevirtual charAt : (I)C
    //   856: invokevirtual append : (C)Ljava/lang/StringBuilder;
    //   859: pop
    //   860: iload_2
    //   861: ifne -> 1348
    //   864: goto -> 871
    //   867: invokestatic a : (Ljava/lang/Throwable;)Ljava/lang/Throwable;
    //   870: athrow
    //   871: aload_3
    //   872: getstatic burp/Zg7z.Zf : Ljava/lang/String;
    //   875: getstatic burp/Zkig.ZK : Ljava/lang/Object;
    //   878: checkcast java/math/BigInteger
    //   881: invokevirtual intValue : ()I
    //   884: bipush #32
    //   886: irem
    //   887: invokestatic abs : (I)I
    //   890: invokevirtual charAt : (I)C
    //   893: invokevirtual append : (C)Ljava/lang/StringBuilder;
    //   896: pop
    //   897: iload_2
    //   898: ifne -> 1348
    //   901: goto -> 908
    //   904: invokestatic a : (Ljava/lang/Throwable;)Ljava/lang/Throwable;
    //   907: athrow
    //   908: aload_3
    //   909: getstatic burp/Zlv6.Zt : Ljava/lang/String;
    //   912: getstatic burp/Zsxm.Zv : Ljava/lang/Object;
    //   915: checkcast java/math/BigInteger
    //   918: invokevirtual intValue : ()I
    //   921: bipush #32
    //   923: irem
    //   924: invokestatic abs : (I)I
    //   927: invokevirtual charAt : (I)C
    //   930: invokevirtual append : (C)Ljava/lang/StringBuilder;
    //   933: pop
    //   934: iload_2
    //   935: ifne -> 1348
    //   938: goto -> 945
    //   941: invokestatic a : (Ljava/lang/Throwable;)Ljava/lang/Throwable;
    //   944: athrow
    //   945: aload_3
    //   946: getstatic burp/Zsgl.ZG : Ljava/lang/String;
    //   949: getstatic burp/Zm0s.Zl : Ljava/lang/Object;
    //   952: checkcast java/math/BigInteger
    //   955: invokevirtual intValue : ()I
    //   958: bipush #32
    //   960: irem
    //   961: invokestatic abs : (I)I
    //   964: invokevirtual charAt : (I)C
    //   967: invokevirtual append : (C)Ljava/lang/StringBuilder;
    //   970: pop
    //   971: iload_2
    //   972: ifne -> 1348
    //   975: goto -> 982
    //   978: invokestatic a : (Ljava/lang/Throwable;)Ljava/lang/Throwable;
    //   981: athrow
    //   982: aload_3
    //   983: getstatic burp/Zxso.ZH : Ljava/lang/String;
    //   986: getstatic burp/Zzsq.Zh : Ljava/lang/Object;
    //   989: checkcast java/math/BigInteger
    //   992: invokevirtual intValue : ()I
    //   995: bipush #32
    //   997: irem
    //   998: invokestatic abs : (I)I
    //   1001: invokevirtual charAt : (I)C
    //   1004: invokevirtual append : (C)Ljava/lang/StringBuilder;
    //   1007: pop
    //   1008: iload_2
    //   1009: ifne -> 1348
    //   1012: goto -> 1019
    //   1015: invokestatic a : (Ljava/lang/Throwable;)Ljava/lang/Throwable;
    //   1018: athrow
    //   1019: aload_3
    //   1020: getstatic burp/Zes_.ZM : Ljava/lang/String;
    //   1023: getstatic burp/Zzqj.Zq : Ljava/lang/Object;
    //   1026: checkcast java/math/BigInteger
    //   1029: invokevirtual intValue : ()I
    //   1032: bipush #32
    //   1034: irem
    //   1035: invokestatic abs : (I)I
    //   1038: invokevirtual charAt : (I)C
    //   1041: invokevirtual append : (C)Ljava/lang/StringBuilder;
    //   1044: pop
    //   1045: iload_2
    //   1046: ifne -> 1348
    //   1049: goto -> 1056
    //   1052: invokestatic a : (Ljava/lang/Throwable;)Ljava/lang/Throwable;
    //   1055: athrow
    //   1056: aload_3
    //   1057: getstatic burp/Zod.ZS : Ljava/lang/String;
    //   1060: getstatic burp/Zxzj.ZO : Ljava/lang/Object;
    //   1063: checkcast java/math/BigInteger
    //   1066: invokevirtual intValue : ()I
    //   1069: bipush #32
    //   1071: irem
    //   1072: invokestatic abs : (I)I
    //   1075: invokevirtual charAt : (I)C
    //   1078: invokevirtual append : (C)Ljava/lang/StringBuilder;
    //   1081: pop
    //   1082: iload_2
    //   1083: ifne -> 1348
    //   1086: goto -> 1093
    //   1089: invokestatic a : (Ljava/lang/Throwable;)Ljava/lang/Throwable;
    //   1092: athrow
    //   1093: aload_3
    //   1094: getstatic burp/Zzk9.Zb : Ljava/lang/String;
    //   1097: getstatic burp/Zxo6.Zw : Ljava/lang/Object;
    //   1100: checkcast java/math/BigInteger
    //   1103: invokevirtual intValue : ()I
    //   1106: bipush #32
    //   1108: irem
    //   1109: invokestatic abs : (I)I
    //   1112: invokevirtual charAt : (I)C
    //   1115: invokevirtual append : (C)Ljava/lang/StringBuilder;
    //   1118: pop
    //   1119: iload_2
    //   1120: ifne -> 1348
    //   1123: goto -> 1130
    //   1126: invokestatic a : (Ljava/lang/Throwable;)Ljava/lang/Throwable;
    //   1129: athrow
    //   1130: aload_3
    //   1131: getstatic burp/Zx4l.Zy : Ljava/lang/String;
    //   1134: getstatic burp/Zz1k.ZP : Ljava/lang/Object;
    //   1137: checkcast java/math/BigInteger
    //   1140: invokevirtual intValue : ()I
    //   1143: bipush #32
    //   1145: irem
    //   1146: invokestatic abs : (I)I
    //   1149: invokevirtual charAt : (I)C
    //   1152: invokevirtual append : (C)Ljava/lang/StringBuilder;
    //   1155: pop
    //   1156: iload_2
    //   1157: ifne -> 1348
    //   1160: goto -> 1167
    //   1163: invokestatic a : (Ljava/lang/Throwable;)Ljava/lang/Throwable;
    //   1166: athrow
    //   1167: aload_3
    //   1168: getstatic burp/Zg7p.ZA : Ljava/lang/String;
    //   1171: getstatic burp/Ztuj.Ze : Ljava/lang/Object;
    //   1174: checkcast java/math/BigInteger
    //   1177: invokevirtual intValue : ()I
    //   1180: bipush #32
    //   1182: irem
    //   1183: invokestatic abs : (I)I
    //   1186: invokevirtual charAt : (I)C
    //   1189: invokevirtual append : (C)Ljava/lang/StringBuilder;
    //   1192: pop
    //   1193: iload_2
    //   1194: ifne -> 1348
    //   1197: goto -> 1204
    //   1200: invokestatic a : (Ljava/lang/Throwable;)Ljava/lang/Throwable;
    //   1203: athrow
    //   1204: aload_3
    //   1205: getstatic burp/Ztbf.Zf : Ljava/lang/String;
    //   1208: getstatic burp/Zter.Zc : Ljava/lang/Object;
    //   1211: checkcast java/math/BigInteger
    //   1214: invokevirtual intValue : ()I
    //   1217: bipush #32
    //   1219: irem
    //   1220: invokestatic abs : (I)I
    //   1223: invokevirtual charAt : (I)C
    //   1226: invokevirtual append : (C)Ljava/lang/StringBuilder;
    //   1229: pop
    //   1230: iload_2
    //   1231: ifne -> 1348
    //   1234: goto -> 1241
    //   1237: invokestatic a : (Ljava/lang/Throwable;)Ljava/lang/Throwable;
    //   1240: athrow
    //   1241: aload_3
    //   1242: getstatic burp/Zr3q.ZM : Ljava/lang/String;
    //   1245: getstatic burp/Zgss.Zl : Ljava/lang/Object;
    //   1248: checkcast java/math/BigInteger
    //   1251: invokevirtual intValue : ()I
    //   1254: bipush #32
    //   1256: irem
    //   1257: invokestatic abs : (I)I
    //   1260: invokevirtual charAt : (I)C
    //   1263: invokevirtual append : (C)Ljava/lang/StringBuilder;
    //   1266: pop
    //   1267: iload_2
    //   1268: ifne -> 1348
    //   1271: goto -> 1278
    //   1274: invokestatic a : (Ljava/lang/Throwable;)Ljava/lang/Throwable;
    //   1277: athrow
    //   1278: aload_3
    //   1279: getstatic burp/Zsm3.Zl : Ljava/lang/String;
    //   1282: getstatic burp/Zkyc.ZD : Ljava/lang/Object;
    //   1285: checkcast java/math/BigInteger
    //   1288: invokevirtual intValue : ()I
    //   1291: bipush #32
    //   1293: irem
    //   1294: invokestatic abs : (I)I
    //   1297: invokevirtual charAt : (I)C
    //   1300: invokevirtual append : (C)Ljava/lang/StringBuilder;
    //   1303: pop
    //   1304: iload_2
    //   1305: ifne -> 1348
    //   1308: goto -> 1315
    //   1311: invokestatic a : (Ljava/lang/Throwable;)Ljava/lang/Throwable;
    //   1314: athrow
    //   1315: aload_3
    //   1316: getstatic burp/Zzai.Zy : Ljava/lang/String;
    //   1319: getstatic burp/Zk8b.ZK : Ljava/lang/Object;
    //   1322: checkcast java/math/BigInteger
    //   1325: invokevirtual intValue : ()I
    //   1328: bipush #32
    //   1330: irem
    //   1331: invokestatic abs : (I)I
    //   1334: invokevirtual charAt : (I)C
    //   1337: invokevirtual append : (C)Ljava/lang/StringBuilder;
    //   1340: pop
    //   1341: goto -> 1348
    //   1344: invokestatic a : (Ljava/lang/Throwable;)Ljava/lang/Throwable;
    //   1347: athrow
    //   1348: iinc #4, 1
    //   1351: iload_2
    //   1352: ifne -> 15
    //   1355: sipush #13543
    //   1358: sipush #-31184
    //   1361: invokestatic a : (II)Ljava/lang/String;
    //   1364: invokestatic forName : (Ljava/lang/String;)Ljava/lang/Class;
    //   1367: invokevirtual getDeclaredMethods : ()[Ljava/lang/reflect/Method;
    //   1370: astore #4
    //   1372: aload #4
    //   1374: arraylength
    //   1375: istore #5
    //   1377: iconst_0
    //   1378: istore #6
    //   1380: iload #6
    //   1382: iload #5
    //   1384: if_icmpge -> 1473
    //   1387: aload #4
    //   1389: iload #6
    //   1391: aaload
    //   1392: astore #7
    //   1394: aload #7
    //   1396: invokevirtual getModifiers : ()I
    //   1399: invokestatic isStatic : (I)Z
    //   1402: ifeq -> 1466
    //   1405: aload #7
    //   1407: invokevirtual getParameterTypes : ()[Ljava/lang/Class;
    //   1410: arraylength
    //   1411: iconst_2
    //   1412: if_icmpne -> 1466
    //   1415: goto -> 1422
    //   1418: invokestatic a : (Ljava/lang/Throwable;)Ljava/lang/Throwable;
    //   1421: athrow
    //   1422: aload #7
    //   1424: invokevirtual getReturnType : ()Ljava/lang/Class;
    //   1427: getstatic java/lang/Boolean.TYPE : Ljava/lang/Class;
    //   1430: if_acmpne -> 1466
    //   1433: goto -> 1440
    //   1436: invokestatic a : (Ljava/lang/Throwable;)Ljava/lang/Throwable;
    //   1439: athrow
    //   1440: aload #7
    //   1442: aconst_null
    //   1443: iconst_2
    //   1444: anewarray java/lang/Object
    //   1447: dup
    //   1448: iconst_0
    //   1449: aload_0
    //   1450: aastore
    //   1451: dup
    //   1452: iconst_1
    //   1453: aload_1
    //   1454: aastore
    //   1455: invokevirtual invoke : (Ljava/lang/Object;[Ljava/lang/Object;)Ljava/lang/Object;
    //   1458: pop
    //   1459: goto -> 1466
    //   1462: invokestatic a : (Ljava/lang/Throwable;)Ljava/lang/Throwable;
    //   1465: athrow
    //   1466: iinc #6, 1
    //   1469: iload_2
    //   1470: ifne -> 1380
    //   1473: aload_0
    //   1474: iconst_0
    //   1475: aaload
    //   1476: checkcast java/lang/String
    //   1479: astore #4
    //   1481: new java/io/ByteArrayOutputStream
    //   1484: dup
    //   1485: invokespecial <init> : ()V
    //   1488: astore #5
    //   1490: iconst_0
    //   1491: istore #6
    //   1493: iload #6
    //   1495: aload #4
    //   1497: invokevirtual length : ()I
    //   1500: if_icmpge -> 1531
    //   1503: aload #5
    //   1505: aload #4
    //   1507: iload #6
    //   1509: iload #6
    //   1511: iconst_2
    //   1512: iadd
    //   1513: invokevirtual substring : (II)Ljava/lang/String;
    //   1516: bipush #16
    //   1518: invokestatic parseInt : (Ljava/lang/String;I)I
    //   1521: invokevirtual write : (I)V
    //   1524: iinc #6, 2
    //   1527: iload_2
    //   1528: ifne -> 1493
    //   1531: sipush #13541
    //   1534: sipush #7720
    //   1537: invokestatic a : (II)Ljava/lang/String;
    //   1540: invokestatic forName : (Ljava/lang/String;)Ljava/lang/Class;
    //   1543: invokevirtual getDeclaredMethods : ()[Ljava/lang/reflect/Method;
    //   1546: astore #6
    //   1548: aload #6
    //   1550: arraylength
    //   1551: istore #7
    //   1553: iconst_0
    //   1554: istore #8
    //   1556: iload #8
    //   1558: iload #7
    //   1560: if_icmpge -> 1649
    //   1563: aload #6
    //   1565: iload #8
    //   1567: aaload
    //   1568: astore #9
    //   1570: aload #9
    //   1572: invokevirtual getModifiers : ()I
    //   1575: invokestatic isStatic : (I)Z
    //   1578: ifeq -> 1642
    //   1581: aload #9
    //   1583: invokevirtual getParameterTypes : ()[Ljava/lang/Class;
    //   1586: arraylength
    //   1587: iconst_2
    //   1588: if_icmpne -> 1642
    //   1591: goto -> 1598
    //   1594: invokestatic a : (Ljava/lang/Throwable;)Ljava/lang/Throwable;
    //   1597: athrow
    //   1598: aload #9
    //   1600: invokevirtual getReturnType : ()Ljava/lang/Class;
    //   1603: getstatic java/lang/Boolean.TYPE : Ljava/lang/Class;
    //   1606: if_acmpne -> 1642
    //   1609: goto -> 1616
    //   1612: invokestatic a : (Ljava/lang/Throwable;)Ljava/lang/Throwable;
    //   1615: athrow
    //   1616: aload #9
    //   1618: aconst_null
    //   1619: iconst_2
    //   1620: anewarray java/lang/Object
    //   1623: dup
    //   1624: iconst_0
    //   1625: aload_0
    //   1626: aastore
    //   1627: dup
    //   1628: iconst_1
    //   1629: aload_1
    //   1630: aastore
    //   1631: invokevirtual invoke : (Ljava/lang/Object;[Ljava/lang/Object;)Ljava/lang/Object;
    //   1634: pop
    //   1635: goto -> 1642
    //   1638: invokestatic a : (Ljava/lang/Throwable;)Ljava/lang/Throwable;
    //   1641: athrow
    //   1642: iinc #8, 1
    //   1645: iload_2
    //   1646: ifne -> 1556
    //   1649: aload #5
    //   1651: invokevirtual toByteArray : ()[B
    //   1654: astore #6
    //   1656: aload_0
    //   1657: iconst_0
    //   1658: aaload
    //   1659: checkcast [B
    //   1662: astore #7
    //   1664: sipush #256
    //   1667: newarray byte
    //   1669: astore #8
    //   1671: sipush #256
    //   1674: newarray int
    //   1676: astore #9
    //   1678: sipush #256
    //   1681: newarray int
    //   1683: astore #10
    //   1685: sipush #256
    //   1688: newarray int
    //   1690: astore #11
    //   1692: sipush #256
    //   1695: newarray int
    //   1697: astore #12
    //   1699: bipush #10
    //   1701: newarray int
    //   1703: astore #13
    //   1705: sipush #283
    //   1708: istore #14
    //   1710: iconst_0
    //   1711: istore #16
    //   1713: iload #16
    //   1715: sipush #256
    //   1718: if_icmpge -> 1952
    //   1721: sipush #13536
    //   1724: sipush #10183
    //   1727: invokestatic a : (II)Ljava/lang/String;
    //   1730: iload #16
    //   1732: iconst_1
    //   1733: iushr
    //   1734: invokevirtual charAt : (I)C
    //   1737: istore #25
    //   1739: iload #16
    //   1741: iconst_1
    //   1742: iand
    //   1743: ifne -> 1758
    //   1746: iload #25
    //   1748: bipush #8
    //   1750: iushr
    //   1751: goto -> 1760
    //   1754: invokestatic a : (Ljava/lang/Throwable;)Ljava/lang/Throwable;
    //   1757: athrow
    //   1758: iload #25
    //   1760: i2b
    //   1761: sipush #255
    //   1764: iand
    //   1765: istore #15
    //   1767: iload #16
    //   1769: iconst_1
    //   1770: ishl
    //   1771: istore #17
    //   1773: iload #17
    //   1775: sipush #256
    //   1778: if_icmplt -> 1788
    //   1781: iload #17
    //   1783: iload #14
    //   1785: ixor
    //   1786: istore #17
    //   1788: iload #17
    //   1790: iconst_1
    //   1791: ishl
    //   1792: istore #18
    //   1794: iload #18
    //   1796: sipush #256
    //   1799: if_icmplt -> 1809
    //   1802: iload #18
    //   1804: iload #14
    //   1806: ixor
    //   1807: istore #18
    //   1809: iload #18
    //   1811: iconst_1
    //   1812: ishl
    //   1813: istore #19
    //   1815: iload #19
    //   1817: sipush #256
    //   1820: if_icmplt -> 1830
    //   1823: iload #19
    //   1825: iload #14
    //   1827: ixor
    //   1828: istore #19
    //   1830: iload #19
    //   1832: iload #16
    //   1834: ixor
    //   1835: istore #20
    //   1837: iload #20
    //   1839: iload #17
    //   1841: ixor
    //   1842: istore #21
    //   1844: iload #20
    //   1846: iload #18
    //   1848: ixor
    //   1849: istore #22
    //   1851: iload #19
    //   1853: iload #18
    //   1855: ixor
    //   1856: iload #17
    //   1858: ixor
    //   1859: istore #23
    //   1861: aload #8
    //   1863: iload #16
    //   1865: iload #15
    //   1867: i2b
    //   1868: bastore
    //   1869: aload #9
    //   1871: iload #15
    //   1873: iload #23
    //   1875: bipush #24
    //   1877: ishl
    //   1878: iload #20
    //   1880: bipush #16
    //   1882: ishl
    //   1883: ior
    //   1884: iload #22
    //   1886: bipush #8
    //   1888: ishl
    //   1889: ior
    //   1890: iload #21
    //   1892: ior
    //   1893: dup
    //   1894: istore #24
    //   1896: iastore
    //   1897: aload #10
    //   1899: iload #15
    //   1901: iload #24
    //   1903: bipush #8
    //   1905: iushr
    //   1906: iload #24
    //   1908: bipush #24
    //   1910: ishl
    //   1911: ior
    //   1912: iastore
    //   1913: aload #11
    //   1915: iload #15
    //   1917: iload #24
    //   1919: bipush #16
    //   1921: iushr
    //   1922: iload #24
    //   1924: bipush #16
    //   1926: ishl
    //   1927: ior
    //   1928: iastore
    //   1929: aload #12
    //   1931: iload #15
    //   1933: iload #24
    //   1935: bipush #24
    //   1937: iushr
    //   1938: iload #24
    //   1940: bipush #8
    //   1942: ishl
    //   1943: ior
    //   1944: iastore
    //   1945: iinc #16, 1
    //   1948: iload_2
    //   1949: ifne -> 1713
    //   1952: iconst_1
    //   1953: istore #25
    //   1955: aload #13
    //   1957: iconst_0
    //   1958: iload #25
    //   1960: bipush #24
    //   1962: ishl
    //   1963: iastore
    //   1964: iconst_1
    //   1965: istore #26
    //   1967: iload #26
    //   1969: bipush #10
    //   1971: if_icmpge -> 2012
    //   1974: iload #25
    //   1976: iconst_1
    //   1977: ishl
    //   1978: istore #25
    //   1980: iload #25
    //   1982: sipush #256
    //   1985: if_icmplt -> 1995
    //   1988: iload #25
    //   1990: iload #14
    //   1992: ixor
    //   1993: istore #25
    //   1995: aload #13
    //   1997: iload #26
    //   1999: iload #25
    //   2001: bipush #24
    //   2003: ishl
    //   2004: iastore
    //   2005: iinc #26, 1
    //   2008: iload_2
    //   2009: ifne -> 1967
    //   2012: bipush #44
    //   2014: newarray int
    //   2016: astore #26
    //   2018: bipush #44
    //   2020: newarray int
    //   2022: astore #27
    //   2024: iconst_0
    //   2025: istore #25
    //   2027: iconst_0
    //   2028: istore #29
    //   2030: iconst_0
    //   2031: istore #30
    //   2033: iload #29
    //   2035: iconst_4
    //   2036: if_icmpge -> 2104
    //   2039: aload #26
    //   2041: iload #29
    //   2043: aload #6
    //   2045: iload #30
    //   2047: baload
    //   2048: bipush #24
    //   2050: ishl
    //   2051: aload #6
    //   2053: iload #30
    //   2055: iconst_1
    //   2056: iadd
    //   2057: baload
    //   2058: sipush #255
    //   2061: iand
    //   2062: bipush #16
    //   2064: ishl
    //   2065: ior
    //   2066: aload #6
    //   2068: iload #30
    //   2070: iconst_2
    //   2071: iadd
    //   2072: baload
    //   2073: sipush #255
    //   2076: iand
    //   2077: bipush #8
    //   2079: ishl
    //   2080: ior
    //   2081: aload #6
    //   2083: iload #30
    //   2085: iconst_3
    //   2086: iadd
    //   2087: baload
    //   2088: sipush #255
    //   2091: iand
    //   2092: ior
    //   2093: iastore
    //   2094: iinc #29, 1
    //   2097: iinc #30, 4
    //   2100: iload_2
    //   2101: ifne -> 2033
    //   2104: iconst_4
    //   2105: istore #29
    //   2107: iconst_0
    //   2108: istore #30
    //   2110: iload #29
    //   2112: bipush #44
    //   2114: if_icmpge -> 2239
    //   2117: aload #26
    //   2119: iload #29
    //   2121: iconst_1
    //   2122: isub
    //   2123: iaload
    //   2124: istore #28
    //   2126: iload #30
    //   2128: ifne -> 2214
    //   2131: iconst_4
    //   2132: istore #30
    //   2134: aload #8
    //   2136: iload #28
    //   2138: bipush #16
    //   2140: iushr
    //   2141: sipush #255
    //   2144: iand
    //   2145: baload
    //   2146: bipush #24
    //   2148: ishl
    //   2149: aload #8
    //   2151: iload #28
    //   2153: bipush #8
    //   2155: iushr
    //   2156: sipush #255
    //   2159: iand
    //   2160: baload
    //   2161: sipush #255
    //   2164: iand
    //   2165: bipush #16
    //   2167: ishl
    //   2168: ior
    //   2169: aload #8
    //   2171: iload #28
    //   2173: sipush #255
    //   2176: iand
    //   2177: baload
    //   2178: sipush #255
    //   2181: iand
    //   2182: bipush #8
    //   2184: ishl
    //   2185: ior
    //   2186: aload #8
    //   2188: iload #28
    //   2190: bipush #24
    //   2192: iushr
    //   2193: baload
    //   2194: sipush #255
    //   2197: iand
    //   2198: ior
    //   2199: istore #28
    //   2201: iload #28
    //   2203: aload #13
    //   2205: iload #25
    //   2207: iinc #25, 1
    //   2210: iaload
    //   2211: ixor
    //   2212: istore #28
    //   2214: aload #26
    //   2216: iload #29
    //   2218: aload #26
    //   2220: iload #29
    //   2222: iconst_4
    //   2223: isub
    //   2224: iaload
    //   2225: iload #28
    //   2227: ixor
    //   2228: iastore
    //   2229: iinc #29, 1
    //   2232: iinc #30, -1
    //   2235: iload_2
    //   2236: ifne -> 2110
    //   2239: iconst_0
    //   2240: istore #29
    //   2242: bipush #40
    //   2244: istore #30
    //   2246: aload #27
    //   2248: iload #29
    //   2250: aload #26
    //   2252: iload #30
    //   2254: iaload
    //   2255: iastore
    //   2256: aload #27
    //   2258: iload #29
    //   2260: iconst_1
    //   2261: iadd
    //   2262: aload #26
    //   2264: iload #30
    //   2266: iconst_1
    //   2267: iadd
    //   2268: iaload
    //   2269: iastore
    //   2270: aload #27
    //   2272: iload #29
    //   2274: iconst_2
    //   2275: iadd
    //   2276: aload #26
    //   2278: iload #30
    //   2280: iconst_2
    //   2281: iadd
    //   2282: iaload
    //   2283: iastore
    //   2284: aload #27
    //   2286: iload #29
    //   2288: iconst_3
    //   2289: iadd
    //   2290: aload #26
    //   2292: iload #30
    //   2294: iconst_3
    //   2295: iadd
    //   2296: iaload
    //   2297: iastore
    //   2298: iinc #29, 4
    //   2301: iinc #30, -4
    //   2304: iconst_1
    //   2305: istore #32
    //   2307: iload #32
    //   2309: bipush #10
    //   2311: if_icmpge -> 2675
    //   2314: aload #26
    //   2316: iload #30
    //   2318: iaload
    //   2319: istore #31
    //   2321: aload #27
    //   2323: iload #29
    //   2325: aload #9
    //   2327: aload #8
    //   2329: iload #31
    //   2331: bipush #24
    //   2333: iushr
    //   2334: baload
    //   2335: sipush #255
    //   2338: iand
    //   2339: iaload
    //   2340: aload #10
    //   2342: aload #8
    //   2344: iload #31
    //   2346: bipush #16
    //   2348: iushr
    //   2349: sipush #255
    //   2352: iand
    //   2353: baload
    //   2354: sipush #255
    //   2357: iand
    //   2358: iaload
    //   2359: ixor
    //   2360: aload #11
    //   2362: aload #8
    //   2364: iload #31
    //   2366: bipush #8
    //   2368: iushr
    //   2369: sipush #255
    //   2372: iand
    //   2373: baload
    //   2374: sipush #255
    //   2377: iand
    //   2378: iaload
    //   2379: ixor
    //   2380: aload #12
    //   2382: aload #8
    //   2384: iload #31
    //   2386: sipush #255
    //   2389: iand
    //   2390: baload
    //   2391: sipush #255
    //   2394: iand
    //   2395: iaload
    //   2396: ixor
    //   2397: iastore
    //   2398: aload #26
    //   2400: iload #30
    //   2402: iconst_1
    //   2403: iadd
    //   2404: iaload
    //   2405: istore #31
    //   2407: aload #27
    //   2409: iload #29
    //   2411: iconst_1
    //   2412: iadd
    //   2413: aload #9
    //   2415: aload #8
    //   2417: iload #31
    //   2419: bipush #24
    //   2421: iushr
    //   2422: baload
    //   2423: sipush #255
    //   2426: iand
    //   2427: iaload
    //   2428: aload #10
    //   2430: aload #8
    //   2432: iload #31
    //   2434: bipush #16
    //   2436: iushr
    //   2437: sipush #255
    //   2440: iand
    //   2441: baload
    //   2442: sipush #255
    //   2445: iand
    //   2446: iaload
    //   2447: ixor
    //   2448: aload #11
    //   2450: aload #8
    //   2452: iload #31
    //   2454: bipush #8
    //   2456: iushr
    //   2457: sipush #255
    //   2460: iand
    //   2461: baload
    //   2462: sipush #255
    //   2465: iand
    //   2466: iaload
    //   2467: ixor
    //   2468: aload #12
    //   2470: aload #8
    //   2472: iload #31
    //   2474: sipush #255
    //   2477: iand
    //   2478: baload
    //   2479: sipush #255
    //   2482: iand
    //   2483: iaload
    //   2484: ixor
    //   2485: iastore
    //   2486: aload #26
    //   2488: iload #30
    //   2490: iconst_2
    //   2491: iadd
    //   2492: iaload
    //   2493: istore #31
    //   2495: aload #27
    //   2497: iload #29
    //   2499: iconst_2
    //   2500: iadd
    //   2501: aload #9
    //   2503: aload #8
    //   2505: iload #31
    //   2507: bipush #24
    //   2509: iushr
    //   2510: baload
    //   2511: sipush #255
    //   2514: iand
    //   2515: iaload
    //   2516: aload #10
    //   2518: aload #8
    //   2520: iload #31
    //   2522: bipush #16
    //   2524: iushr
    //   2525: sipush #255
    //   2528: iand
    //   2529: baload
    //   2530: sipush #255
    //   2533: iand
    //   2534: iaload
    //   2535: ixor
    //   2536: aload #11
    //   2538: aload #8
    //   2540: iload #31
    //   2542: bipush #8
    //   2544: iushr
    //   2545: sipush #255
    //   2548: iand
    //   2549: baload
    //   2550: sipush #255
    //   2553: iand
    //   2554: iaload
    //   2555: ixor
    //   2556: aload #12
    //   2558: aload #8
    //   2560: iload #31
    //   2562: sipush #255
    //   2565: iand
    //   2566: baload
    //   2567: sipush #255
    //   2570: iand
    //   2571: iaload
    //   2572: ixor
    //   2573: iastore
    //   2574: aload #26
    //   2576: iload #30
    //   2578: iconst_3
    //   2579: iadd
    //   2580: iaload
    //   2581: istore #31
    //   2583: aload #27
    //   2585: iload #29
    //   2587: iconst_3
    //   2588: iadd
    //   2589: aload #9
    //   2591: aload #8
    //   2593: iload #31
    //   2595: bipush #24
    //   2597: iushr
    //   2598: baload
    //   2599: sipush #255
    //   2602: iand
    //   2603: iaload
    //   2604: aload #10
    //   2606: aload #8
    //   2608: iload #31
    //   2610: bipush #16
    //   2612: iushr
    //   2613: sipush #255
    //   2616: iand
    //   2617: baload
    //   2618: sipush #255
    //   2621: iand
    //   2622: iaload
    //   2623: ixor
    //   2624: aload #11
    //   2626: aload #8
    //   2628: iload #31
    //   2630: bipush #8
    //   2632: iushr
    //   2633: sipush #255
    //   2636: iand
    //   2637: baload
    //   2638: sipush #255
    //   2641: iand
    //   2642: iaload
    //   2643: ixor
    //   2644: aload #12
    //   2646: aload #8
    //   2648: iload #31
    //   2650: sipush #255
    //   2653: iand
    //   2654: baload
    //   2655: sipush #255
    //   2658: iand
    //   2659: iaload
    //   2660: ixor
    //   2661: iastore
    //   2662: iinc #29, 4
    //   2665: iinc #30, -4
    //   2668: iinc #32, 1
    //   2671: iload_2
    //   2672: ifne -> 2307
    //   2675: aload #27
    //   2677: iload #29
    //   2679: aload #26
    //   2681: iload #30
    //   2683: iaload
    //   2684: iastore
    //   2685: aload #27
    //   2687: iload #29
    //   2689: iconst_1
    //   2690: iadd
    //   2691: aload #26
    //   2693: iload #30
    //   2695: iconst_1
    //   2696: iadd
    //   2697: iaload
    //   2698: iastore
    //   2699: aload #27
    //   2701: iload #29
    //   2703: iconst_2
    //   2704: iadd
    //   2705: aload #26
    //   2707: iload #30
    //   2709: iconst_2
    //   2710: iadd
    //   2711: iaload
    //   2712: iastore
    //   2713: aload #27
    //   2715: iload #29
    //   2717: iconst_3
    //   2718: iadd
    //   2719: aload #26
    //   2721: iload #30
    //   2723: iconst_3
    //   2724: iadd
    //   2725: iaload
    //   2726: iastore
    //   2727: iconst_0
    //   2728: newarray byte
    //   2730: astore #32
    //   2732: aload #7
    //   2734: arraylength
    //   2735: bipush #16
    //   2737: irem
    //   2738: ifeq -> 2762
    //   2741: new java/lang/Exception
    //   2744: dup
    //   2745: sipush #13548
    //   2748: sipush #1467
    //   2751: invokestatic a : (II)Ljava/lang/String;
    //   2754: invokespecial <init> : (Ljava/lang/String;)V
    //   2757: athrow
    //   2758: invokestatic a : (Ljava/lang/Throwable;)Ljava/lang/Throwable;
    //   2761: athrow
    //   2762: bipush #10
    //   2764: istore #33
    //   2766: sipush #13550
    //   2769: sipush #256
    //   2772: newarray byte
    //   2774: astore #34
    //   2776: sipush #-32096
    //   2779: sipush #256
    //   2782: newarray int
    //   2784: astore #35
    //   2786: sipush #256
    //   2789: newarray int
    //   2791: astore #36
    //   2793: sipush #256
    //   2796: newarray int
    //   2798: astore #37
    //   2800: sipush #256
    //   2803: newarray int
    //   2805: astore #38
    //   2807: sipush #283
    //   2810: istore #14
    //   2812: invokestatic a : (II)Ljava/lang/String;
    //   2815: astore #39
    //   2817: iconst_0
    //   2818: istore #16
    //   2820: iload #16
    //   2822: sipush #256
    //   2825: if_icmpge -> 3052
    //   2828: aload #39
    //   2830: iload #16
    //   2832: iconst_1
    //   2833: iushr
    //   2834: invokevirtual charAt : (I)C
    //   2837: istore #40
    //   2839: iload #16
    //   2841: iconst_1
    //   2842: iand
    //   2843: ifne -> 2858
    //   2846: iload #40
    //   2848: bipush #8
    //   2850: iushr
    //   2851: goto -> 2860
    //   2854: invokestatic a : (Ljava/lang/Throwable;)Ljava/lang/Throwable;
    //   2857: athrow
    //   2858: iload #40
    //   2860: i2b
    //   2861: sipush #255
    //   2864: iand
    //   2865: istore #15
    //   2867: iload #16
    //   2869: iconst_1
    //   2870: ishl
    //   2871: istore #17
    //   2873: iload #17
    //   2875: sipush #256
    //   2878: if_icmplt -> 2888
    //   2881: iload #17
    //   2883: iload #14
    //   2885: ixor
    //   2886: istore #17
    //   2888: iload #17
    //   2890: iconst_1
    //   2891: ishl
    //   2892: istore #18
    //   2894: iload #18
    //   2896: sipush #256
    //   2899: if_icmplt -> 2909
    //   2902: iload #18
    //   2904: iload #14
    //   2906: ixor
    //   2907: istore #18
    //   2909: iload #18
    //   2911: iconst_1
    //   2912: ishl
    //   2913: istore #19
    //   2915: iload #19
    //   2917: sipush #256
    //   2920: if_icmplt -> 2930
    //   2923: iload #19
    //   2925: iload #14
    //   2927: ixor
    //   2928: istore #19
    //   2930: iload #19
    //   2932: iload #16
    //   2934: ixor
    //   2935: istore #20
    //   2937: iload #20
    //   2939: iload #17
    //   2941: ixor
    //   2942: istore #21
    //   2944: iload #20
    //   2946: iload #18
    //   2948: ixor
    //   2949: istore #22
    //   2951: iload #19
    //   2953: iload #18
    //   2955: ixor
    //   2956: iload #17
    //   2958: ixor
    //   2959: istore #23
    //   2961: aload #34
    //   2963: iload #15
    //   2965: iload #16
    //   2967: i2b
    //   2968: bastore
    //   2969: aload #35
    //   2971: iload #15
    //   2973: iload #23
    //   2975: bipush #24
    //   2977: ishl
    //   2978: iload #20
    //   2980: bipush #16
    //   2982: ishl
    //   2983: ior
    //   2984: iload #22
    //   2986: bipush #8
    //   2988: ishl
    //   2989: ior
    //   2990: iload #21
    //   2992: ior
    //   2993: dup
    //   2994: istore #24
    //   2996: iastore
    //   2997: aload #36
    //   2999: iload #15
    //   3001: iload #24
    //   3003: bipush #8
    //   3005: iushr
    //   3006: iload #24
    //   3008: bipush #24
    //   3010: ishl
    //   3011: ior
    //   3012: iastore
    //   3013: aload #37
    //   3015: iload #15
    //   3017: iload #24
    //   3019: bipush #16
    //   3021: iushr
    //   3022: iload #24
    //   3024: bipush #16
    //   3026: ishl
    //   3027: ior
    //   3028: iastore
    //   3029: aload #38
    //   3031: iload #15
    //   3033: iload #24
    //   3035: bipush #24
    //   3037: iushr
    //   3038: iload #24
    //   3040: bipush #8
    //   3042: ishl
    //   3043: ior
    //   3044: iastore
    //   3045: iinc #16, 1
    //   3048: iload_2
    //   3049: ifne -> 2820
    //   3052: aload #7
    //   3054: arraylength
    //   3055: newarray byte
    //   3057: astore #40
    //   3059: iconst_0
    //   3060: istore #41
    //   3062: iload #41
    //   3064: aload #7
    //   3066: arraylength
    //   3067: bipush #16
    //   3069: idiv
    //   3070: if_icmpge -> 3984
    //   3073: bipush #16
    //   3075: newarray byte
    //   3077: astore #42
    //   3079: bipush #16
    //   3081: newarray byte
    //   3083: astore #43
    //   3085: iconst_0
    //   3086: istore #44
    //   3088: iload #44
    //   3090: bipush #16
    //   3092: if_icmpge -> 3118
    //   3095: aload #42
    //   3097: iload #44
    //   3099: aload #7
    //   3101: iload #44
    //   3103: iload #41
    //   3105: bipush #16
    //   3107: imul
    //   3108: iadd
    //   3109: baload
    //   3110: bastore
    //   3111: iinc #44, 1
    //   3114: iload_2
    //   3115: ifne -> 3088
    //   3118: iconst_0
    //   3119: istore #44
    //   3121: aload #42
    //   3123: iconst_0
    //   3124: baload
    //   3125: bipush #24
    //   3127: ishl
    //   3128: aload #42
    //   3130: iconst_1
    //   3131: baload
    //   3132: sipush #255
    //   3135: iand
    //   3136: bipush #16
    //   3138: ishl
    //   3139: ior
    //   3140: aload #42
    //   3142: iconst_2
    //   3143: baload
    //   3144: sipush #255
    //   3147: iand
    //   3148: bipush #8
    //   3150: ishl
    //   3151: ior
    //   3152: aload #42
    //   3154: iconst_3
    //   3155: baload
    //   3156: sipush #255
    //   3159: iand
    //   3160: ior
    //   3161: aload #27
    //   3163: iconst_0
    //   3164: iaload
    //   3165: ixor
    //   3166: istore #46
    //   3168: aload #42
    //   3170: iconst_4
    //   3171: baload
    //   3172: bipush #24
    //   3174: ishl
    //   3175: aload #42
    //   3177: iconst_5
    //   3178: baload
    //   3179: sipush #255
    //   3182: iand
    //   3183: bipush #16
    //   3185: ishl
    //   3186: ior
    //   3187: aload #42
    //   3189: bipush #6
    //   3191: baload
    //   3192: sipush #255
    //   3195: iand
    //   3196: bipush #8
    //   3198: ishl
    //   3199: ior
    //   3200: aload #42
    //   3202: bipush #7
    //   3204: baload
    //   3205: sipush #255
    //   3208: iand
    //   3209: ior
    //   3210: aload #27
    //   3212: iconst_1
    //   3213: iaload
    //   3214: ixor
    //   3215: istore #47
    //   3217: aload #42
    //   3219: bipush #8
    //   3221: baload
    //   3222: bipush #24
    //   3224: ishl
    //   3225: aload #42
    //   3227: bipush #9
    //   3229: baload
    //   3230: sipush #255
    //   3233: iand
    //   3234: bipush #16
    //   3236: ishl
    //   3237: ior
    //   3238: aload #42
    //   3240: bipush #10
    //   3242: baload
    //   3243: sipush #255
    //   3246: iand
    //   3247: bipush #8
    //   3249: ishl
    //   3250: ior
    //   3251: aload #42
    //   3253: bipush #11
    //   3255: baload
    //   3256: sipush #255
    //   3259: iand
    //   3260: ior
    //   3261: aload #27
    //   3263: iconst_2
    //   3264: iaload
    //   3265: ixor
    //   3266: istore #48
    //   3268: aload #42
    //   3270: bipush #12
    //   3272: baload
    //   3273: bipush #24
    //   3275: ishl
    //   3276: aload #42
    //   3278: bipush #13
    //   3280: baload
    //   3281: sipush #255
    //   3284: iand
    //   3285: bipush #16
    //   3287: ishl
    //   3288: ior
    //   3289: aload #42
    //   3291: bipush #14
    //   3293: baload
    //   3294: sipush #255
    //   3297: iand
    //   3298: bipush #8
    //   3300: ishl
    //   3301: ior
    //   3302: aload #42
    //   3304: bipush #15
    //   3306: baload
    //   3307: sipush #255
    //   3310: iand
    //   3311: ior
    //   3312: aload #27
    //   3314: iconst_3
    //   3315: iaload
    //   3316: ixor
    //   3317: istore #49
    //   3319: iconst_1
    //   3320: istore #50
    //   3322: iload #50
    //   3324: iload #33
    //   3326: if_icmpge -> 3569
    //   3329: iinc #44, 4
    //   3332: aload #35
    //   3334: iload #46
    //   3336: bipush #24
    //   3338: iushr
    //   3339: iaload
    //   3340: aload #36
    //   3342: iload #49
    //   3344: bipush #16
    //   3346: iushr
    //   3347: sipush #255
    //   3350: iand
    //   3351: iaload
    //   3352: ixor
    //   3353: aload #37
    //   3355: iload #48
    //   3357: bipush #8
    //   3359: iushr
    //   3360: sipush #255
    //   3363: iand
    //   3364: iaload
    //   3365: ixor
    //   3366: aload #38
    //   3368: iload #47
    //   3370: sipush #255
    //   3373: iand
    //   3374: iaload
    //   3375: ixor
    //   3376: aload #27
    //   3378: iload #44
    //   3380: iaload
    //   3381: ixor
    //   3382: istore #51
    //   3384: aload #35
    //   3386: iload #47
    //   3388: bipush #24
    //   3390: iushr
    //   3391: iaload
    //   3392: aload #36
    //   3394: iload #46
    //   3396: bipush #16
    //   3398: iushr
    //   3399: sipush #255
    //   3402: iand
    //   3403: iaload
    //   3404: ixor
    //   3405: aload #37
    //   3407: iload #49
    //   3409: bipush #8
    //   3411: iushr
    //   3412: sipush #255
    //   3415: iand
    //   3416: iaload
    //   3417: ixor
    //   3418: aload #38
    //   3420: iload #48
    //   3422: sipush #255
    //   3425: iand
    //   3426: iaload
    //   3427: ixor
    //   3428: aload #27
    //   3430: iload #44
    //   3432: iconst_1
    //   3433: iadd
    //   3434: iaload
    //   3435: ixor
    //   3436: istore #52
    //   3438: aload #35
    //   3440: iload #48
    //   3442: bipush #24
    //   3444: iushr
    //   3445: iaload
    //   3446: aload #36
    //   3448: iload #47
    //   3450: bipush #16
    //   3452: iushr
    //   3453: sipush #255
    //   3456: iand
    //   3457: iaload
    //   3458: ixor
    //   3459: aload #37
    //   3461: iload #46
    //   3463: bipush #8
    //   3465: iushr
    //   3466: sipush #255
    //   3469: iand
    //   3470: iaload
    //   3471: ixor
    //   3472: aload #38
    //   3474: iload #49
    //   3476: sipush #255
    //   3479: iand
    //   3480: iaload
    //   3481: ixor
    //   3482: aload #27
    //   3484: iload #44
    //   3486: iconst_2
    //   3487: iadd
    //   3488: iaload
    //   3489: ixor
    //   3490: istore #53
    //   3492: aload #35
    //   3494: iload #49
    //   3496: bipush #24
    //   3498: iushr
    //   3499: iaload
    //   3500: aload #36
    //   3502: iload #48
    //   3504: bipush #16
    //   3506: iushr
    //   3507: sipush #255
    //   3510: iand
    //   3511: iaload
    //   3512: ixor
    //   3513: aload #37
    //   3515: iload #47
    //   3517: bipush #8
    //   3519: iushr
    //   3520: sipush #255
    //   3523: iand
    //   3524: iaload
    //   3525: ixor
    //   3526: aload #38
    //   3528: iload #46
    //   3530: sipush #255
    //   3533: iand
    //   3534: iaload
    //   3535: ixor
    //   3536: aload #27
    //   3538: iload #44
    //   3540: iconst_3
    //   3541: iadd
    //   3542: iaload
    //   3543: ixor
    //   3544: istore #54
    //   3546: iload #51
    //   3548: istore #46
    //   3550: iload #52
    //   3552: istore #47
    //   3554: iload #53
    //   3556: istore #48
    //   3558: iload #54
    //   3560: istore #49
    //   3562: iinc #50, 1
    //   3565: iload_2
    //   3566: ifne -> 3322
    //   3569: iinc #44, 4
    //   3572: aload #27
    //   3574: iload #44
    //   3576: iaload
    //   3577: istore #45
    //   3579: aload #43
    //   3581: iconst_0
    //   3582: aload #34
    //   3584: iload #46
    //   3586: bipush #24
    //   3588: iushr
    //   3589: baload
    //   3590: iload #45
    //   3592: bipush #24
    //   3594: iushr
    //   3595: ixor
    //   3596: i2b
    //   3597: bastore
    //   3598: aload #43
    //   3600: iconst_1
    //   3601: aload #34
    //   3603: iload #49
    //   3605: bipush #16
    //   3607: iushr
    //   3608: sipush #255
    //   3611: iand
    //   3612: baload
    //   3613: iload #45
    //   3615: bipush #16
    //   3617: iushr
    //   3618: ixor
    //   3619: i2b
    //   3620: bastore
    //   3621: aload #43
    //   3623: iconst_2
    //   3624: aload #34
    //   3626: iload #48
    //   3628: bipush #8
    //   3630: iushr
    //   3631: sipush #255
    //   3634: iand
    //   3635: baload
    //   3636: iload #45
    //   3638: bipush #8
    //   3640: iushr
    //   3641: ixor
    //   3642: i2b
    //   3643: bastore
    //   3644: aload #43
    //   3646: iconst_3
    //   3647: aload #34
    //   3649: iload #47
    //   3651: sipush #255
    //   3654: iand
    //   3655: baload
    //   3656: iload #45
    //   3658: ixor
    //   3659: i2b
    //   3660: bastore
    //   3661: aload #27
    //   3663: iload #44
    //   3665: iconst_1
    //   3666: iadd
    //   3667: iaload
    //   3668: istore #45
    //   3670: aload #43
    //   3672: iconst_4
    //   3673: aload #34
    //   3675: iload #47
    //   3677: bipush #24
    //   3679: iushr
    //   3680: baload
    //   3681: iload #45
    //   3683: bipush #24
    //   3685: iushr
    //   3686: ixor
    //   3687: i2b
    //   3688: bastore
    //   3689: aload #43
    //   3691: iconst_5
    //   3692: aload #34
    //   3694: iload #46
    //   3696: bipush #16
    //   3698: iushr
    //   3699: sipush #255
    //   3702: iand
    //   3703: baload
    //   3704: iload #45
    //   3706: bipush #16
    //   3708: iushr
    //   3709: ixor
    //   3710: i2b
    //   3711: bastore
    //   3712: aload #43
    //   3714: bipush #6
    //   3716: aload #34
    //   3718: iload #49
    //   3720: bipush #8
    //   3722: iushr
    //   3723: sipush #255
    //   3726: iand
    //   3727: baload
    //   3728: iload #45
    //   3730: bipush #8
    //   3732: iushr
    //   3733: ixor
    //   3734: i2b
    //   3735: bastore
    //   3736: aload #43
    //   3738: bipush #7
    //   3740: aload #34
    //   3742: iload #48
    //   3744: sipush #255
    //   3747: iand
    //   3748: baload
    //   3749: iload #45
    //   3751: ixor
    //   3752: i2b
    //   3753: bastore
    //   3754: aload #27
    //   3756: iload #44
    //   3758: iconst_2
    //   3759: iadd
    //   3760: iaload
    //   3761: istore #45
    //   3763: aload #43
    //   3765: bipush #8
    //   3767: aload #34
    //   3769: iload #48
    //   3771: bipush #24
    //   3773: iushr
    //   3774: baload
    //   3775: iload #45
    //   3777: bipush #24
    //   3779: iushr
    //   3780: ixor
    //   3781: i2b
    //   3782: bastore
    //   3783: aload #43
    //   3785: bipush #9
    //   3787: aload #34
    //   3789: iload #47
    //   3791: bipush #16
    //   3793: iushr
    //   3794: sipush #255
    //   3797: iand
    //   3798: baload
    //   3799: iload #45
    //   3801: bipush #16
    //   3803: iushr
    //   3804: ixor
    //   3805: i2b
    //   3806: bastore
    //   3807: aload #43
    //   3809: bipush #10
    //   3811: aload #34
    //   3813: iload #46
    //   3815: bipush #8
    //   3817: iushr
    //   3818: sipush #255
    //   3821: iand
    //   3822: baload
    //   3823: iload #45
    //   3825: bipush #8
    //   3827: iushr
    //   3828: ixor
    //   3829: i2b
    //   3830: bastore
    //   3831: aload #43
    //   3833: bipush #11
    //   3835: aload #34
    //   3837: iload #49
    //   3839: sipush #255
    //   3842: iand
    //   3843: baload
    //   3844: iload #45
    //   3846: ixor
    //   3847: i2b
    //   3848: bastore
    //   3849: aload #27
    //   3851: iload #44
    //   3853: iconst_3
    //   3854: iadd
    //   3855: iaload
    //   3856: istore #45
    //   3858: aload #43
    //   3860: bipush #12
    //   3862: aload #34
    //   3864: iload #49
    //   3866: bipush #24
    //   3868: iushr
    //   3869: baload
    //   3870: iload #45
    //   3872: bipush #24
    //   3874: iushr
    //   3875: ixor
    //   3876: i2b
    //   3877: bastore
    //   3878: aload #43
    //   3880: bipush #13
    //   3882: aload #34
    //   3884: iload #48
    //   3886: bipush #16
    //   3888: iushr
    //   3889: sipush #255
    //   3892: iand
    //   3893: baload
    //   3894: iload #45
    //   3896: bipush #16
    //   3898: iushr
    //   3899: ixor
    //   3900: i2b
    //   3901: bastore
    //   3902: aload #43
    //   3904: bipush #14
    //   3906: aload #34
    //   3908: iload #47
    //   3910: bipush #8
    //   3912: iushr
    //   3913: sipush #255
    //   3916: iand
    //   3917: baload
    //   3918: iload #45
    //   3920: bipush #8
    //   3922: iushr
    //   3923: ixor
    //   3924: i2b
    //   3925: bastore
    //   3926: aload #43
    //   3928: bipush #15
    //   3930: aload #34
    //   3932: iload #46
    //   3934: sipush #255
    //   3937: iand
    //   3938: baload
    //   3939: iload #45
    //   3941: ixor
    //   3942: i2b
    //   3943: bastore
    //   3944: iconst_0
    //   3945: istore #50
    //   3947: iload #50
    //   3949: bipush #16
    //   3951: if_icmpge -> 3977
    //   3954: aload #40
    //   3956: iload #50
    //   3958: iload #41
    //   3960: bipush #16
    //   3962: imul
    //   3963: iadd
    //   3964: aload #43
    //   3966: iload #50
    //   3968: baload
    //   3969: bastore
    //   3970: iinc #50, 1
    //   3973: iload_2
    //   3974: ifne -> 3947
    //   3977: iinc #41, 1
    //   3980: iload_2
    //   3981: ifne -> 3062
    //   3984: aload #40
    //   3986: arraylength
    //   3987: ifle -> 4068
    //   3990: aload #40
    //   3992: aload #40
    //   3994: arraylength
    //   3995: iconst_1
    //   3996: isub
    //   3997: baload
    //   3998: istore #41
    //   4000: iload #41
    //   4002: bipush #16
    //   4004: if_icmple -> 4015
    //   4007: aload #40
    //   4009: astore #32
    //   4011: iload_2
    //   4012: ifne -> 4068
    //   4015: aload #40
    //   4017: arraylength
    //   4018: iload #41
    //   4020: isub
    //   4021: newarray byte
    //   4023: astore #32
    //   4025: iconst_0
    //   4026: istore #42
    //   4028: iload #42
    //   4030: aload #32
    //   4032: arraylength
    //   4033: if_icmpge -> 4068
    //   4036: iload #42
    //   4038: aload #40
    //   4040: arraylength
    //   4041: if_icmpge -> 4068
    //   4044: aload #32
    //   4046: iload #42
    //   4048: aload #40
    //   4050: iload #42
    //   4052: baload
    //   4053: bastore
    //   4054: iinc #42, 1
    //   4057: iload_2
    //   4058: ifne -> 4028
    //   4061: goto -> 4068
    //   4064: invokestatic a : (Ljava/lang/Throwable;)Ljava/lang/Throwable;
    //   4067: athrow
    //   4068: aload_0
    //   4069: iconst_0
    //   4070: aload #32
    //   4072: aastore
    //   4073: sipush #13551
    //   4076: sipush #8745
    //   4079: invokestatic a : (II)Ljava/lang/String;
    //   4082: iconst_1
    //   4083: ldc burp/Zr3j
    //   4085: invokevirtual getClassLoader : ()Ljava/lang/ClassLoader;
    //   4088: invokestatic forName : (Ljava/lang/String;ZLjava/lang/ClassLoader;)Ljava/lang/Class;
    //   4091: invokevirtual getDeclaredFields : ()[Ljava/lang/reflect/Field;
    //   4094: astore #41
    //   4096: aload #41
    //   4098: arraylength
    //   4099: istore #42
    //   4101: iconst_0
    //   4102: istore #43
    //   4104: iload #43
    //   4106: iload #42
    //   4108: if_icmpge -> 4246
    //   4111: aload #41
    //   4113: iload #43
    //   4115: aaload
    //   4116: astore #44
    //   4118: aload #44
    //   4120: invokevirtual getModifiers : ()I
    //   4123: invokestatic isStatic : (I)Z
    //   4126: ifne -> 4136
    //   4129: goto -> 4239
    //   4132: invokestatic a : (Ljava/lang/Throwable;)Ljava/lang/Throwable;
    //   4135: athrow
    //   4136: aload #44
    //   4138: invokevirtual getType : ()Ljava/lang/Class;
    //   4141: astore #45
    //   4143: aload #45
    //   4145: ifnull -> 4226
    //   4148: aload #45
    //   4150: invokevirtual isPrimitive : ()Z
    //   4153: ifne -> 4226
    //   4156: goto -> 4163
    //   4159: invokestatic a : (Ljava/lang/Throwable;)Ljava/lang/Throwable;
    //   4162: athrow
    //   4163: aload #45
    //   4165: invokevirtual getPackage : ()Ljava/lang/Package;
    //   4168: ifnull -> 4226
    //   4171: goto -> 4178
    //   4174: invokestatic a : (Ljava/lang/Throwable;)Ljava/lang/Throwable;
    //   4177: athrow
    //   4178: aload #45
    //   4180: invokevirtual getPackage : ()Ljava/lang/Package;
    //   4183: invokevirtual getName : ()Ljava/lang/String;
    //   4186: ifnull -> 4226
    //   4189: goto -> 4196
    //   4192: invokestatic a : (Ljava/lang/Throwable;)Ljava/lang/Throwable;
    //   4195: athrow
    //   4196: aload #45
    //   4198: invokevirtual getPackage : ()Ljava/lang/Package;
    //   4201: invokevirtual getName : ()Ljava/lang/String;
    //   4204: sipush #13547
    //   4207: sipush #-5998
    //   4210: invokestatic a : (II)Ljava/lang/String;
    //   4213: invokevirtual startsWith : (Ljava/lang/String;)Z
    //   4216: ifne -> 4226
    //   4219: goto -> 4226
    //   4222: invokestatic a : (Ljava/lang/Throwable;)Ljava/lang/Throwable;
    //   4225: athrow
    //   4226: aload #44
    //   4228: iconst_1
    //   4229: invokevirtual setAccessible : (Z)V
    //   4232: aload #44
    //   4234: aconst_null
    //   4235: invokevirtual get : (Ljava/lang/Object;)Ljava/lang/Object;
    //   4238: pop
    //   4239: iinc #43, 1
    //   4242: iload_2
    //   4243: ifne -> 4104
    //   4246: sipush #13542
    //   4249: sipush #18985
    //   4252: invokestatic a : (II)Ljava/lang/String;
    //   4255: invokestatic forName : (Ljava/lang/String;)Ljava/lang/Class;
    //   4258: invokevirtual getDeclaredMethods : ()[Ljava/lang/reflect/Method;
    //   4261: astore #41
    //   4263: aload #41
    //   4265: arraylength
    //   4266: istore #42
    //   4268: iconst_0
    //   4269: istore #43
    //   4271: iload #43
    //   4273: iload #42
    //   4275: if_icmpge -> 4408
    //   4278: aload #41
    //   4280: iload #43
    //   4282: aaload
    //   4283: astore #44
    //   4285: aload #44
    //   4287: invokevirtual getParameterTypes : ()[Ljava/lang/Class;
    //   4290: pop
    //   4291: aload #44
    //   4293: invokevirtual getModifiers : ()I
    //   4296: invokestatic isStatic : (I)Z
    //   4299: ifeq -> 4394
    //   4302: aload #44
    //   4304: invokevirtual getParameterTypes : ()[Ljava/lang/Class;
    //   4307: arraylength
    //   4308: iconst_2
    //   4309: if_icmpne -> 4394
    //   4312: goto -> 4319
    //   4315: invokestatic a : (Ljava/lang/Throwable;)Ljava/lang/Throwable;
    //   4318: athrow
    //   4319: aload #44
    //   4321: invokevirtual getReturnType : ()Ljava/lang/Class;
    //   4324: getstatic java/lang/Void.TYPE : Ljava/lang/Class;
    //   4327: invokevirtual equals : (Ljava/lang/Object;)Z
    //   4330: ifeq -> 4394
    //   4333: goto -> 4340
    //   4336: invokestatic a : (Ljava/lang/Throwable;)Ljava/lang/Throwable;
    //   4339: athrow
    //   4340: aload #44
    //   4342: iconst_1
    //   4343: invokevirtual setAccessible : (Z)V
    //   4346: aload #44
    //   4348: aconst_null
    //   4349: iconst_2
    //   4350: anewarray java/lang/Object
    //   4353: dup
    //   4354: iconst_0
    //   4355: aload_0
    //   4356: aastore
    //   4357: dup
    //   4358: iconst_1
    //   4359: aload_1
    //   4360: ifnonnull -> 4378
    //   4363: goto -> 4370
    //   4366: invokestatic a : (Ljava/lang/Throwable;)Ljava/lang/Throwable;
    //   4369: athrow
    //   4370: aload_1
    //   4371: goto -> 4385
    //   4374: invokestatic a : (Ljava/lang/Throwable;)Ljava/lang/Throwable;
    //   4377: athrow
    //   4378: aload_1
    //   4379: checkcast [B
    //   4382: invokevirtual clone : ()Ljava/lang/Object;
    //   4385: aastore
    //   4386: invokevirtual invoke : (Ljava/lang/Object;[Ljava/lang/Object;)Ljava/lang/Object;
    //   4389: pop
    //   4390: iload_2
    //   4391: ifne -> 4408
    //   4394: iinc #43, 1
    //   4397: iload_2
    //   4398: ifne -> 4271
    //   4401: goto -> 4408
    //   4404: invokestatic a : (Ljava/lang/Throwable;)Ljava/lang/Throwable;
    //   4407: athrow
    //   4408: getstatic burp/Zbsr.Zq : Ljava/lang/String;
    //   4411: getstatic burp/Zlv6.ZN : Ljava/lang/Object;
    //   4414: checkcast java/math/BigInteger
    //   4417: invokevirtual intValue : ()I
    //   4420: bipush #32
    //   4422: irem
    //   4423: invokestatic abs : (I)I
    //   4426: invokevirtual charAt : (I)C
    //   4429: getstatic burp/Zlhm.Zx : Ljava/lang/String;
    //   4432: getstatic burp/Zg_p.Zx : Ljava/lang/Object;
    //   4435: checkcast java/math/BigInteger
    //   4438: invokevirtual intValue : ()I
    //   4441: bipush #32
    //   4443: irem
    //   4444: invokestatic abs : (I)I
    //   4447: invokevirtual charAt : (I)C
    //   4450: if_icmpgt -> 4557
    //   4453: getstatic burp/Zxo6.Z_ : Ljava/lang/String;
    //   4456: getstatic burp/Zl2g.ZG : Ljava/lang/Object;
    //   4459: checkcast java/math/BigInteger
    //   4462: invokevirtual intValue : ()I
    //   4465: bipush #32
    //   4467: irem
    //   4468: invokestatic abs : (I)I
    //   4471: invokevirtual charAt : (I)C
    //   4474: getstatic burp/Ztuj.Zk : Ljava/lang/String;
    //   4477: getstatic burp/Ztbf.Zv : Ljava/lang/Object;
    //   4480: checkcast java/math/BigInteger
    //   4483: invokevirtual intValue : ()I
    //   4486: bipush #32
    //   4488: irem
    //   4489: invokestatic abs : (I)I
    //   4492: invokevirtual charAt : (I)C
    //   4495: if_icmple -> 4557
    //   4498: goto -> 4505
    //   4501: invokestatic a : (Ljava/lang/Throwable;)Ljava/lang/Throwable;
    //   4504: athrow
    //   4505: getstatic burp/Zzip.Za : Ljava/lang/String;
    //   4508: getstatic burp/Zkbf.Zx : Ljava/lang/Object;
    //   4511: checkcast java/math/BigInteger
    //   4514: invokevirtual intValue : ()I
    //   4517: bipush #32
    //   4519: irem
    //   4520: invokestatic abs : (I)I
    //   4523: invokevirtual charAt : (I)C
    //   4526: getstatic burp/Zxfu.Zo : Ljava/lang/String;
    //   4529: getstatic burp/Zedz.Za : Ljava/lang/Object;
    //   4532: checkcast java/math/BigInteger
    //   4535: invokevirtual intValue : ()I
    //   4538: bipush #32
    //   4540: irem
    //   4541: invokestatic abs : (I)I
    //   4544: invokevirtual charAt : (I)C
    //   4547: if_icmple -> 4565
    //   4550: goto -> 4557
    //   4553: invokestatic a : (Ljava/lang/Throwable;)Ljava/lang/Throwable;
    //   4556: athrow
    //   4557: iconst_1
    //   4558: goto -> 4566
    //   4561: invokestatic a : (Ljava/lang/Throwable;)Ljava/lang/Throwable;
    //   4564: athrow
    //   4565: iconst_0
    //   4566: ireturn
    //   4567: astore_3
    //   4568: new java/lang/Exception
    //   4571: dup
    //   4572: aload_3
    //   4573: invokevirtual getMessage : ()Ljava/lang/String;
    //   4576: invokespecial <init> : (Ljava/lang/String;)V
    //   4579: athrow
    // Exception table:
    //   from	to	target	type
    //   4	4566	4567	java/lang/Throwable
    //   22	198	201	java/lang/Throwable
    //   168	235	238	java/lang/Throwable
    //   205	272	275	java/lang/Throwable
    //   242	309	312	java/lang/Throwable
    //   279	346	349	java/lang/Throwable
    //   316	383	386	java/lang/Throwable
    //   353	420	423	java/lang/Throwable
    //   390	457	460	java/lang/Throwable
    //   427	494	497	java/lang/Throwable
    //   464	531	534	java/lang/Throwable
    //   501	568	571	java/lang/Throwable
    //   538	605	608	java/lang/Throwable
    //   575	642	645	java/lang/Throwable
    //   612	679	682	java/lang/Throwable
    //   649	716	719	java/lang/Throwable
    //   686	753	756	java/lang/Throwable
    //   723	790	793	java/lang/Throwable
    //   760	827	830	java/lang/Throwable
    //   797	864	867	java/lang/Throwable
    //   834	901	904	java/lang/Throwable
    //   871	938	941	java/lang/Throwable
    //   908	975	978	java/lang/Throwable
    //   945	1012	1015	java/lang/Throwable
    //   982	1049	1052	java/lang/Throwable
    //   1019	1086	1089	java/lang/Throwable
    //   1056	1123	1126	java/lang/Throwable
    //   1093	1160	1163	java/lang/Throwable
    //   1130	1197	1200	java/lang/Throwable
    //   1167	1234	1237	java/lang/Throwable
    //   1204	1271	1274	java/lang/Throwable
    //   1241	1308	1311	java/lang/Throwable
    //   1278	1341	1344	java/lang/Throwable
    //   1394	1415	1418	java/lang/Throwable
    //   1405	1433	1436	java/lang/Throwable
    //   1422	1459	1462	java/lang/Throwable
    //   1570	1591	1594	java/lang/Throwable
    //   1581	1609	1612	java/lang/Throwable
    //   1598	1635	1638	java/lang/Throwable
    //   1739	1754	1754	java/lang/Throwable
    //   2732	2758	2758	java/lang/Throwable
    //   2839	2854	2854	java/lang/Throwable
    //   4036	4061	4064	java/lang/Throwable
    //   4118	4132	4132	java/lang/Throwable
    //   4143	4156	4159	java/lang/Throwable
    //   4148	4171	4174	java/lang/Throwable
    //   4163	4189	4192	java/lang/Throwable
    //   4178	4219	4222	java/lang/Throwable
    //   4285	4312	4315	java/lang/Throwable
    //   4302	4333	4336	java/lang/Throwable
    //   4319	4363	4366	java/lang/Throwable
    //   4340	4374	4374	java/lang/Throwable
    //   4385	4401	4404	java/lang/Throwable
    //   4408	4498	4501	java/lang/Throwable
    //   4453	4550	4553	java/lang/Throwable
    //   4505	4561	4561	java/lang/Throwable
  }
  
  static void ZP(Object paramObject) {
    Zk9s.ZM = a(13538, 23268);
    Zk9s.ZY = new BigInteger(a(13549, -18083));
    boolean bool = Zt2e.ZN();
    try {
      try {
        if (Zezz.Zi.charAt(Math.abs(((BigInteger)Zsyu.Zj).intValue() % 32)) > Zx_u.Z_.charAt(Math.abs(((BigInteger)Zel.ZB).intValue() % 32))) {
          try {
            Zmdi.ZR(Class.forName(a(13540, 31625)));
            if (!bool)
              Zsxj.Zz(Class.forName(a(13537, -27539))); 
          } catch (Throwable throwable) {
            throw a(null);
          } 
          return;
        } 
      } catch (Throwable throwable) {
        throw a(null);
      } 
      Zsxj.Zz(Class.forName(a(13537, -27539)));
    } catch (Throwable throwable) {}
  }
  
  static {
    // Byte code:
    //   0: bipush #13
    //   2: anewarray java/lang/String
    //   5: astore #5
    //   7: iconst_0
    //   8: istore_3
    //   9: ldc '\\r\\fhY\\t\\f>Y<\\tvA9\\tKSJzy t!(SX*E\!(~ g-H}NK;21 ?g\\t`ypA??\\t\\f>BP??M>Uh GaBY;@}bIK6yJ3drZ`0Rv&?%C\\t5{B'
    //   11: dup
    //   12: astore_2
    //   13: invokevirtual length : ()I
    //   16: istore #4
    //   18: bipush #9
    //   20: istore_1
    //   21: iconst_m1
    //   22: istore_0
    //   23: bipush #29
    //   25: iinc #0, 1
    //   28: aload_2
    //   29: iload_0
    //   30: dup
    //   31: iload_1
    //   32: iadd
    //   33: invokevirtual substring : (II)Ljava/lang/String;
    //   36: iconst_m1
    //   37: goto -> 143
    //   40: aload #5
    //   42: swap
    //   43: iload_3
    //   44: iinc #3, 1
    //   47: swap
    //   48: aastore
    //   49: iload_0
    //   50: iload_1
    //   51: iadd
    //   52: dup
    //   53: istore_0
    //   54: iload #4
    //   56: if_icmpge -> 68
    //   59: aload_2
    //   60: iload_0
    //   61: invokevirtual charAt : (I)C
    //   64: istore_1
    //   65: goto -> 23
    //   68: ldc 'Lf{LR]qSn08'
    //   70: dup
    //   71: astore_2
    //   72: invokevirtual length : ()I
    //   75: istore #4
    //   77: bipush #22
    //   79: istore_1
    //   80: iconst_m1
    //   81: istore_0
    //   82: bipush #56
    //   84: iinc #0, 1
    //   87: aload_2
    //   88: iload_0
    //   89: dup
    //   90: iload_1
    //   91: iadd
    //   92: invokevirtual substring : (II)Ljava/lang/String;
    //   95: iconst_0
    //   96: goto -> 143
    //   99: aload #5
    //   101: swap
    //   102: iload_3
    //   103: iinc #3, 1
    //   106: swap
    //   107: aastore
    //   108: iload_0
    //   109: iload_1
    //   110: iadd
    //   111: dup
    //   112: istore_0
    //   113: iload #4
    //   115: if_icmpge -> 127
    //   118: aload_2
    //   119: iload_0
    //   120: invokevirtual charAt : (I)C
    //   123: istore_1
    //   124: goto -> 82
    //   127: aload #5
    //   129: putstatic burp/Ztxx.a : [Ljava/lang/String;
    //   132: bipush #13
    //   134: anewarray java/lang/String
    //   137: putstatic burp/Ztxx.b : [Ljava/lang/String;
    //   140: goto -> 300
    //   143: dup_x2
    //   144: pop
    //   145: invokevirtual toCharArray : ()[C
    //   148: dup_x1
    //   149: arraylength
    //   150: dup_x2
    //   151: pop
    //   152: iconst_0
    //   153: istore #6
    //   155: dup2_x1
    //   156: pop2
    //   157: dup_x2
    //   158: iconst_1
    //   159: if_icmpgt -> 260
    //   162: dup2
    //   163: swap
    //   164: iload #6
    //   166: dup2_x1
    //   167: caload
    //   168: swap
    //   169: iload #6
    //   171: bipush #7
    //   173: irem
    //   174: tableswitch default -> 242, 0 -> 212, 1 -> 217, 2 -> 222, 3 -> 227, 4 -> 232, 5 -> 237
    //   212: bipush #19
    //   214: goto -> 244
    //   217: bipush #34
    //   219: goto -> 244
    //   222: bipush #63
    //   224: goto -> 244
    //   227: bipush #113
    //   229: goto -> 244
    //   232: bipush #77
    //   234: goto -> 244
    //   237: bipush #20
    //   239: goto -> 244
    //   242: bipush #9
    //   244: ixor
    //   245: ixor
    //   246: i2c
    //   247: castore
    //   248: iinc #6, 1
    //   251: dup
    //   252: ifne -> 260
    //   255: dup2
    //   256: dup_x1
    //   257: goto -> 166
    //   260: dup2_x1
    //   261: pop2
    //   262: dup_x2
    //   263: iload #6
    //   265: if_icmpgt -> 162
    //   268: pop
    //   269: new java/lang/String
    //   272: dup_x1
    //   273: swap
    //   274: invokespecial <init> : ([C)V
    //   277: invokevirtual intern : ()Ljava/lang/String;
    //   280: swap
    //   281: pop
    //   282: swap
    //   283: tableswitch default -> 40, 0 -> 99
    //   300: sipush #13539
    //   303: sipush #-24944
    //   306: invokestatic a : (II)Ljava/lang/String;
    //   309: putstatic burp/Ztxx.Zt : Ljava/lang/String;
    //   312: new java/math/BigInteger
    //   315: dup
    //   316: bipush #32
    //   318: newarray byte
    //   320: dup
    //   321: iconst_0
    //   322: bipush #84
    //   324: bastore
    //   325: dup
    //   326: iconst_1
    //   327: bipush #99
    //   329: bastore
    //   330: dup
    //   331: iconst_2
    //   332: bipush #-75
    //   334: bastore
    //   335: dup
    //   336: iconst_3
    //   337: bipush #10
    //   339: bastore
    //   340: dup
    //   341: iconst_4
    //   342: bipush #126
    //   344: bastore
    //   345: dup
    //   346: iconst_5
    //   347: bipush #113
    //   349: bastore
    //   350: dup
    //   351: bipush #6
    //   353: bipush #17
    //   355: bastore
    //   356: dup
    //   357: bipush #7
    //   359: bipush #-94
    //   361: bastore
    //   362: dup
    //   363: bipush #8
    //   365: bipush #88
    //   367: bastore
    //   368: dup
    //   369: bipush #9
    //   371: bipush #109
    //   373: bastore
    //   374: dup
    //   375: bipush #10
    //   377: bipush #-84
    //   379: bastore
    //   380: dup
    //   381: bipush #11
    //   383: bipush #66
    //   385: bastore
    //   386: dup
    //   387: bipush #12
    //   389: bipush #64
    //   391: bastore
    //   392: dup
    //   393: bipush #13
    //   395: bipush #68
    //   397: bastore
    //   398: dup
    //   399: bipush #14
    //   401: bipush #76
    //   403: bastore
    //   404: dup
    //   405: bipush #15
    //   407: bipush #-114
    //   409: bastore
    //   410: dup
    //   411: bipush #16
    //   413: bipush #52
    //   415: bastore
    //   416: dup
    //   417: bipush #17
    //   419: bipush #106
    //   421: bastore
    //   422: dup
    //   423: bipush #18
    //   425: bipush #99
    //   427: bastore
    //   428: dup
    //   429: bipush #19
    //   431: bipush #63
    //   433: bastore
    //   434: dup
    //   435: bipush #20
    //   437: bipush #124
    //   439: bastore
    //   440: dup
    //   441: bipush #21
    //   443: bipush #58
    //   445: bastore
    //   446: dup
    //   447: bipush #22
    //   449: bipush #61
    //   451: bastore
    //   452: dup
    //   453: bipush #23
    //   455: bipush #-73
    //   457: bastore
    //   458: dup
    //   459: bipush #24
    //   461: bipush #114
    //   463: bastore
    //   464: dup
    //   465: bipush #25
    //   467: bipush #-38
    //   469: bastore
    //   470: dup
    //   471: bipush #26
    //   473: bipush #-5
    //   475: bastore
    //   476: dup
    //   477: bipush #27
    //   479: iconst_3
    //   480: bastore
    //   481: dup
    //   482: bipush #28
    //   484: bipush #126
    //   486: bastore
    //   487: dup
    //   488: bipush #29
    //   490: bipush #-30
    //   492: bastore
    //   493: dup
    //   494: bipush #30
    //   496: bipush #64
    //   498: bastore
    //   499: dup
    //   500: bipush #31
    //   502: bipush #16
    //   504: bastore
    //   505: invokespecial <init> : ([B)V
    //   508: putstatic burp/Ztxx.ZI : Ljava/lang/Object;
    //   511: return
  }
  
  private static Throwable a(Throwable paramThrowable) {
    return paramThrowable;
  }
  
  private static String a(int paramInt1, int paramInt2) {
    int i = (paramInt1 ^ 0x34E7) & 0xFFFF;
    if (b[i] == null) {
      char[] arrayOfChar = a[i].toCharArray();
      switch (arrayOfChar[0] & 0xFF) {
        case 0:
        
        case 1:
        
        case 2:
        
        case 3:
        
        case 4:
        
        case 5:
        
        case 6:
        
        case 7:
        
        case 8:
        
        case 9:
        
        case 10:
        
        case 11:
        
        case 12:
        
        case 13:
        
        case 14:
        
        case 15:
        
        case 16:
        
        case 17:
        
        case 18:
        
        case 19:
        
        case 20:
        
        case 21:
        
        case 22:
        
        case 23:
        
        case 24:
        
        case 25:
        
        case 26:
        
        case 27:
        
        case 28:
        
        case 29:
        
        case 30:
        
        case 31:
        
        case 32:
        
        case 33:
        
        case 34:
        
        case 35:
        
        case 36:
        
        case 37:
        
        case 38:
        
        case 39:
        
        case 40:
        
        case 41:
        
        case 42:
        
        case 43:
        
        case 44:
        
        case 45:
        
        case 46:
        
        case 47:
        
        case 48:
        
        case 49:
        
        case 50:
        
        case 51:
        
        case 52:
        
        case 53:
        
        case 54:
        
        case 55:
        
        case 56:
        
        case 57:
        
        case 58:
        
        case 59:
        
        case 60:
        
        case 61:
        
        case 62:
        
        case 63:
        
        case 64:
        
        case 65:
        
        case 66:
        
        case 67:
        
        case 68:
        
        case 69:
        
        case 70:
        
        case 71:
        
        case 72:
        
        case 73:
        
        case 74:
        
        case 75:
        
        case 76:
        
        case 77:
        
        case 78:
        
        case 79:
        
        case 80:
        
        case 81:
        
        case 82:
        
        case 83:
        
        case 84:
        
        case 85:
        
        case 86:
        
        case 87:
        
        case 88:
        
        case 89:
        
        case 90:
        
        case 91:
        
        case 92:
        
        case 93:
        
        case 94:
        
        case 95:
        
        case 96:
        
        case 97:
        
        case 98:
        
        case 99:
        
        case 100:
        
        case 101:
        
        case 102:
        
        case 103:
        
        case 104:
        
        case 105:
        
        case 106:
        
        case 107:
        
        case 108:
        
        case 109:
        
        case 110:
        
        case 111:
        
        case 112:
        
        case 113:
        
        case 114:
        
        case 115:
        
        case 116:
        
        case 117:
        
        case 118:
        
        case 119:
        
        case 120:
        
        case 121:
        
        case 122:
        
        case 123:
        
        case 124:
        
        case 125:
        
        case 126:
        
        case 127:
        
        case 128:
        
        case 129:
        
        case 130:
        
        case 131:
        
        case 132:
        
        case 133:
        
        case 134:
        
        case 135:
        
        case 136:
        
        case 137:
        
        case 138:
        
        case 139:
        
        case 140:
        
        case 141:
        
        case 142:
        
        case 143:
        
        case 144:
        
        case 145:
        
        case 146:
        
        case 147:
        
        case 148:
        
        case 149:
        
        case 150:
        
        case 151:
        
        case 152:
        
        case 153:
        
        case 154:
        
        case 155:
        
        case 156:
        
        case 157:
        
        case 158:
        
        case 159:
        
        case 160:
        
        case 161:
        
        case 162:
        
        case 163:
        
        case 164:
        
        case 165:
        
        case 166:
        
        case 167:
        
        case 168:
        
        case 169:
        
        case 170:
        
        case 171:
        
        case 172:
        
        case 173:
        
        case 174:
        
        case 175:
        
        case 176:
        
        case 177:
        
        case 178:
        
        case 179:
        
        case 180:
        
        case 181:
        
        case 182:
        
        case 183:
        
        case 184:
        
        case 185:
        
        case 186:
        
        case 187:
        
        case 188:
        
        case 189:
        
        case 190:
        
        case 191:
        
        case 192:
        
        case 193:
        
        case 194:
        
        case 195:
        
        case 196:
        
        case 197:
        
        case 198:
        
        case 199:
        
        case 200:
        
        case 201:
        
        case 202:
        
        case 203:
        
        case 204:
        
        case 205:
        
        case 206:
        
        case 207:
        
        case 208:
        
        case 209:
        
        case 210:
        
        case 211:
        
        case 212:
        
        case 213:
        
        case 214:
        
        case 215:
        
        case 216:
        
        case 217:
        
        case 218:
        
        case 219:
        
        case 220:
        
        case 221:
        
        case 222:
        
        case 223:
        
        case 224:
        
        case 225:
        
        case 226:
        
        case 227:
        
        case 228:
        
        case 229:
        
        case 230:
        
        case 231:
        
        case 232:
        
        case 233:
        
        case 234:
        
        case 235:
        
        case 236:
        
        case 237:
        
        case 238:
        
        case 239:
        
        case 240:
        
        case 241:
        
        case 242:
        
        case 243:
        
        case 244:
        
        case 245:
        
        case 246:
        
        case 247:
        
        case 248:
        
        case 249:
        
        case 250:
        
        case 251:
        
        case 252:
        
        case 253:
        
        case 254:
        
        default:
          break;
      } 
      byte b1 = 40;
      int j = (paramInt2 & 0xFF) - b1;
      if (j < 0)
        j += 256; 
      int k = ((paramInt2 & 0xFFFF) >>> 8) - b1;
      if (k < 0)
        k += 256; 
      for (byte b2 = 0; b2 < arrayOfChar.length; b2++) {
        int m = b2 % 2;
        if (m == 0) {
          arrayOfChar[b2] = (char)(arrayOfChar[b2] ^ j);
          j = ((j >>> 3 | j << 5) ^ arrayOfChar[b2]) & 0xFF;
        } else {
          arrayOfChar[b2] = (char)(arrayOfChar[b2] ^ k);
          k = ((k >>> 3 | k << 5) ^ arrayOfChar[b2]) & 0xFF;
        } 
      } 
      b[i] = (new String(arrayOfChar)).intern();
    } 
    return b[i];
  }
}


/* Location:              C:\Program Files\BurpSuitePro\burpsuite_pro.jar!\burp\Ztxx.class
 * Java compiler version: 21 (65.0)
 * JD-Core Version:       1.1.3
 */