package burp;

public class Zuo extends Zni implements Zzt9 {
  @Zzvo(0)
  private boolean ZH;
  
  @Zzvo(1)
  private boolean ZT;
  
  @Zzvo(2)
  private boolean ZJ;
  
  @Zzvo(3)
  private boolean Zt;
  
  @Zzvo(4)
  private boolean ZS;
  
  @Zzvo(5)
  private boolean ZC;
  
  @Zzvo(6)
  private boolean Zj;
  
  @Zzvo(7)
  private boolean ZO;
  
  @Zzvo(8)
  private boolean ZG;
  
  @Zzvo(9)
  private boolean Zq;
  
  @Zzvo(10)
  private boolean ZU;
  
  @Zzvo(11)
  private boolean Zi;
  
  @Zzvo(12)
  private boolean Zm;
  
  @Zzvo(13)
  private boolean Zw;
  
  @Zzvo(14)
  private boolean Zb;
  
  @Zzvo(15)
  private boolean ZV;
  
  @Zzvo(16)
  private String Zu = "";
  
  @Zzvo(17)
  private boolean Zr;
  
  @Zzvo(18)
  private boolean ZQ;
  
  @Zzvo(19)
  private boolean Z_;
  
  @Zzvo(20)
  private String Zz = "";
  
  @Zzvo(21)
  private boolean ZL;
  
  @Zzvo(22)
  private String Zk = "";
  
  @Zzvo(23)
  private boolean Zc;
  
  @Zzvo(24)
  private boolean Zn;
  
  @Zzvo(25)
  private String Zd;
  
  @Zzvo(26)
  private Zrb5 ZK;
  
  private Zzca Ze;
  
  private static final String a;
  
  public Zuo() {
    int[] arrayOfInt = Zgvt.Zw();
    this.Zd = "";
    if (Zbqc.Zwu() == null)
      Zgvt.Zg(new int[5]); 
  }
  
  public boolean Zcu() {
    return this.ZH;
  }
  
  public void Zan(boolean paramBoolean) {
    this.ZH = paramBoolean;
  }
  
  public boolean ZcE() {
    return this.ZT;
  }
  
  public void Zao(boolean paramBoolean) {
    this.ZT = paramBoolean;
  }
  
  public boolean ZcW() {
    return this.ZJ;
  }
  
  public void ZaC(boolean paramBoolean) {
    this.ZJ = paramBoolean;
  }
  
  public boolean ZcR() {
    return this.Zt;
  }
  
  public void Zal(boolean paramBoolean) {
    this.Zt = paramBoolean;
  }
  
  public boolean ZcS() {
    return this.ZS;
  }
  
  public void ZaZ(boolean paramBoolean) {
    this.ZS = paramBoolean;
  }
  
  public boolean ZcZ() {
    return this.ZC;
  }
  
  public void Zaq(boolean paramBoolean) {
    this.ZC = paramBoolean;
  }
  
  public boolean ZcH() {
    return this.Zj;
  }
  
  public void Zab(boolean paramBoolean) {
    this.Zj = paramBoolean;
  }
  
  public boolean Zc8() {
    return this.ZO;
  }
  
  public void Zai(boolean paramBoolean) {
    this.ZO = paramBoolean;
  }
  
  public boolean Zcz() {
    return this.ZG;
  }
  
  public void ZaU(boolean paramBoolean) {
    this.ZG = paramBoolean;
  }
  
  public boolean Zc4() {
    return this.Zq;
  }
  
  public void Zah(boolean paramBoolean) {
    this.Zq = paramBoolean;
  }
  
  public boolean Zcc() {
    return this.ZU;
  }
  
  public void Zas(boolean paramBoolean) {
    this.ZU = paramBoolean;
  }
  
  public boolean Zc1() {
    return this.Zi;
  }
  
  public void Zaa(boolean paramBoolean) {
    this.Zi = paramBoolean;
  }
  
  public boolean Zcm() {
    return this.Zm;
  }
  
  public void Zaw(boolean paramBoolean) {
    this.Zm = paramBoolean;
  }
  
  public boolean ZcP() {
    return this.Zw;
  }
  
  public void Za7(boolean paramBoolean) {
    this.Zw = paramBoolean;
  }
  
  public boolean ZcQ() {
    return this.Zb;
  }
  
  public void ZaR(boolean paramBoolean) {
    this.Zb = paramBoolean;
  }
  
  public String Zcs() {
    return this.Zu;
  }
  
  public void ZHv(String paramString) {
    this.Zu = paramString;
  }
  
  public boolean Zc_() {
    return this.ZV;
  }
  
  public void ZaI(boolean paramBoolean) {
    this.ZV = paramBoolean;
  }
  
  public boolean ZcO() {
    return this.Zr;
  }
  
  public void ZaG(boolean paramBoolean) {
    this.Zr = paramBoolean;
  }
  
  public boolean Zcq() {
    return this.ZQ;
  }
  
  public void ZaQ(boolean paramBoolean) {
    this.ZQ = paramBoolean;
  }
  
  public String Zcr() {
    return this.Zz;
  }
  
  public boolean Zcf() {
    return this.Z_;
  }
  
  public void Zat(boolean paramBoolean) {
    this.Z_ = paramBoolean;
  }
  
  public void ZHK(String paramString) {
    this.Zz = paramString;
  }
  
  public boolean ZcN() {
    return this.ZL;
  }
  
  public void ZaB(boolean paramBoolean) {
    this.ZL = paramBoolean;
  }
  
  public String Zcv() {
    return this.Zk;
  }
  
  public void ZHd(String paramString) {
    this.Zk = paramString;
  }
  
  public boolean ZcI() {
    return this.Zc;
  }
  
  public void ZaM(boolean paramBoolean) {
    this.Zc = paramBoolean;
  }
  
  public boolean ZcC() {
    return this.Zn;
  }
  
  public void ZaE(boolean paramBoolean) {
    this.Zn = paramBoolean;
  }
  
  public String ZcL() {
    return this.Zd;
  }
  
  public void ZHF(String paramString) {
    this.Zd = paramString;
  }
  
  public String Zcp() {
    String str = (this.ZK == null) ? "" : this.ZK.ZJ();
    return str.isEmpty() ? a : str;
  }
  
  public void ZHC(String paramString) {
    if (this.ZK == null)
      this.ZK = new Zn9(); 
    this.ZK.Ze(paramString);
  }
  
  public Zzca ZcF() {
    if (this.Ze == null)
      this.Ze = Zzca.SETTINGS; 
    return this.Ze;
  }
  
  public void ZX(Zzca paramZzca) {
    this.Ze = paramZzca;
  }
  
  public Zeu4<Zzt9> ZF() {
    return Zzt9.ZF;
  }
  
  @Zzvo(27)
  private byte Zve() {
    return ZcF().ZY();
  }
  
  static {
    // Byte code:
    //   0: bipush #127
    //   2: ldc 'b\\ttJd='
    //   4: iconst_m1
    //   5: goto -> 14
    //   8: putstatic burp/Zuo.a : Ljava/lang/String;
    //   11: goto -> 153
    //   14: dup_x2
    //   15: pop
    //   16: invokevirtual toCharArray : ()[C
    //   19: dup_x1
    //   20: arraylength
    //   21: dup_x2
    //   22: pop
    //   23: iconst_0
    //   24: istore_0
    //   25: dup2_x1
    //   26: pop2
    //   27: dup_x2
    //   28: iconst_1
    //   29: if_icmpgt -> 127
    //   32: dup2
    //   33: swap
    //   34: iload_0
    //   35: dup2_x1
    //   36: caload
    //   37: swap
    //   38: iload_0
    //   39: bipush #7
    //   41: irem
    //   42: tableswitch default -> 109, 0 -> 80, 1 -> 85, 2 -> 90, 3 -> 95, 4 -> 99, 5 -> 104
    //   80: bipush #111
    //   82: goto -> 111
    //   85: bipush #17
    //   87: goto -> 111
    //   90: bipush #20
    //   92: goto -> 111
    //   95: iconst_3
    //   96: goto -> 111
    //   99: bipush #121
    //   101: goto -> 111
    //   104: bipush #15
    //   106: goto -> 111
    //   109: bipush #21
    //   111: ixor
    //   112: ixor
    //   113: i2c
    //   114: castore
    //   115: iinc #0, 1
    //   118: dup
    //   119: ifne -> 127
    //   122: dup2
    //   123: dup_x1
    //   124: goto -> 35
    //   127: dup2_x1
    //   128: pop2
    //   129: dup_x2
    //   130: iload_0
    //   131: if_icmpgt -> 32
    //   134: pop
    //   135: new java/lang/String
    //   138: dup_x1
    //   139: swap
    //   140: invokespecial <init> : ([C)V
    //   143: invokevirtual intern : ()Ljava/lang/String;
    //   146: swap
    //   147: pop
    //   148: swap
    //   149: pop
    //   150: goto -> 8
    //   153: return
  }
}


/* Location:              C:\Program Files\BurpSuitePro\burpsuite_pro.jar!\burp\Zuo.class
 * Java compiler version: 21 (65.0)
 * JD-Core Version:       1.1.3
 */