package burp;

import java.math.BigInteger;

class Zvi extends ClassLoader {
  static String ZR;
  
  static Object Zs;
  
  private static final String[] a;
  
  private static final String[] b;
  
  static void ZZ(Object paramObject) {
    Zsqi.Zs = a(-12969, -23211);
    Zsqi.Zf = new BigInteger(a(-12965, 13494));
    boolean bool = Zt2e.ZK();
    try {
      try {
        if (Zs9x.ZY.charAt(Math.abs(((BigInteger)Zl4v.ZT).intValue() % 32)) <= Zmsl.ZP.charAt(Math.abs(((BigInteger)Zg27.ZQ).intValue() % 32))) {
          try {
            Zl8y.Zr(Class.forName(a(-12970, 2918)));
            if (bool)
              Zsuw.Zv(Class.forName(a(-12974, -2902))); 
          } catch (Throwable throwable) {
            throw a(null);
          } 
          return;
        } 
      } catch (Throwable throwable) {
        throw a(null);
      } 
      Zsuw.Zv(Class.forName(a(-12974, -2902)));
    } catch (Throwable throwable) {}
  }
  
  static void Zt(Object[] paramArrayOfObject, Object paramObject) throws Throwable {}
  
  static boolean Zc(Object[] paramArrayOfObject, Object paramObject) throws Throwable {
    // Byte code:
    //   0: invokestatic ZK : ()Z
    //   3: istore_2
    //   4: sipush #-12968
    //   7: sipush #-20821
    //   10: invokestatic a : (II)Ljava/lang/String;
    //   13: invokestatic forName : (Ljava/lang/String;)Ljava/lang/Class;
    //   16: invokestatic ZG : (Ljava/lang/Object;)V
    //   19: getstatic burp/Zsuw.ZB : Ljava/lang/Object;
    //   22: checkcast java/math/BigInteger
    //   25: invokevirtual toByteArray : ()[B
    //   28: astore_3
    //   29: bipush #64
    //   31: newarray byte
    //   33: dup
    //   34: iconst_0
    //   35: bipush #-128
    //   37: bastore
    //   38: dup
    //   39: iconst_1
    //   40: iconst_0
    //   41: bastore
    //   42: dup
    //   43: iconst_2
    //   44: iconst_0
    //   45: bastore
    //   46: dup
    //   47: iconst_3
    //   48: iconst_0
    //   49: bastore
    //   50: dup
    //   51: iconst_4
    //   52: iconst_0
    //   53: bastore
    //   54: dup
    //   55: iconst_5
    //   56: iconst_0
    //   57: bastore
    //   58: dup
    //   59: bipush #6
    //   61: iconst_0
    //   62: bastore
    //   63: dup
    //   64: bipush #7
    //   66: iconst_0
    //   67: bastore
    //   68: dup
    //   69: bipush #8
    //   71: iconst_0
    //   72: bastore
    //   73: dup
    //   74: bipush #9
    //   76: iconst_0
    //   77: bastore
    //   78: dup
    //   79: bipush #10
    //   81: iconst_0
    //   82: bastore
    //   83: dup
    //   84: bipush #11
    //   86: iconst_0
    //   87: bastore
    //   88: dup
    //   89: bipush #12
    //   91: iconst_0
    //   92: bastore
    //   93: dup
    //   94: bipush #13
    //   96: iconst_0
    //   97: bastore
    //   98: dup
    //   99: bipush #14
    //   101: iconst_0
    //   102: bastore
    //   103: dup
    //   104: bipush #15
    //   106: iconst_0
    //   107: bastore
    //   108: dup
    //   109: bipush #16
    //   111: iconst_0
    //   112: bastore
    //   113: dup
    //   114: bipush #17
    //   116: iconst_0
    //   117: bastore
    //   118: dup
    //   119: bipush #18
    //   121: iconst_0
    //   122: bastore
    //   123: dup
    //   124: bipush #19
    //   126: iconst_0
    //   127: bastore
    //   128: dup
    //   129: bipush #20
    //   131: iconst_0
    //   132: bastore
    //   133: dup
    //   134: bipush #21
    //   136: iconst_0
    //   137: bastore
    //   138: dup
    //   139: bipush #22
    //   141: iconst_0
    //   142: bastore
    //   143: dup
    //   144: bipush #23
    //   146: iconst_0
    //   147: bastore
    //   148: dup
    //   149: bipush #24
    //   151: iconst_0
    //   152: bastore
    //   153: dup
    //   154: bipush #25
    //   156: iconst_0
    //   157: bastore
    //   158: dup
    //   159: bipush #26
    //   161: iconst_0
    //   162: bastore
    //   163: dup
    //   164: bipush #27
    //   166: iconst_0
    //   167: bastore
    //   168: dup
    //   169: bipush #28
    //   171: iconst_0
    //   172: bastore
    //   173: dup
    //   174: bipush #29
    //   176: iconst_0
    //   177: bastore
    //   178: dup
    //   179: bipush #30
    //   181: iconst_0
    //   182: bastore
    //   183: dup
    //   184: bipush #31
    //   186: iconst_0
    //   187: bastore
    //   188: dup
    //   189: bipush #32
    //   191: iconst_0
    //   192: bastore
    //   193: dup
    //   194: bipush #33
    //   196: iconst_0
    //   197: bastore
    //   198: dup
    //   199: bipush #34
    //   201: iconst_0
    //   202: bastore
    //   203: dup
    //   204: bipush #35
    //   206: iconst_0
    //   207: bastore
    //   208: dup
    //   209: bipush #36
    //   211: iconst_0
    //   212: bastore
    //   213: dup
    //   214: bipush #37
    //   216: iconst_0
    //   217: bastore
    //   218: dup
    //   219: bipush #38
    //   221: iconst_0
    //   222: bastore
    //   223: dup
    //   224: bipush #39
    //   226: iconst_0
    //   227: bastore
    //   228: dup
    //   229: bipush #40
    //   231: iconst_0
    //   232: bastore
    //   233: dup
    //   234: bipush #41
    //   236: iconst_0
    //   237: bastore
    //   238: dup
    //   239: bipush #42
    //   241: iconst_0
    //   242: bastore
    //   243: dup
    //   244: bipush #43
    //   246: iconst_0
    //   247: bastore
    //   248: dup
    //   249: bipush #44
    //   251: iconst_0
    //   252: bastore
    //   253: dup
    //   254: bipush #45
    //   256: iconst_0
    //   257: bastore
    //   258: dup
    //   259: bipush #46
    //   261: iconst_0
    //   262: bastore
    //   263: dup
    //   264: bipush #47
    //   266: iconst_0
    //   267: bastore
    //   268: dup
    //   269: bipush #48
    //   271: iconst_0
    //   272: bastore
    //   273: dup
    //   274: bipush #49
    //   276: iconst_0
    //   277: bastore
    //   278: dup
    //   279: bipush #50
    //   281: iconst_0
    //   282: bastore
    //   283: dup
    //   284: bipush #51
    //   286: iconst_0
    //   287: bastore
    //   288: dup
    //   289: bipush #52
    //   291: iconst_0
    //   292: bastore
    //   293: dup
    //   294: bipush #53
    //   296: iconst_0
    //   297: bastore
    //   298: dup
    //   299: bipush #54
    //   301: iconst_0
    //   302: bastore
    //   303: dup
    //   304: bipush #55
    //   306: iconst_0
    //   307: bastore
    //   308: dup
    //   309: bipush #56
    //   311: iconst_0
    //   312: bastore
    //   313: dup
    //   314: bipush #57
    //   316: iconst_0
    //   317: bastore
    //   318: dup
    //   319: bipush #58
    //   321: iconst_0
    //   322: bastore
    //   323: dup
    //   324: bipush #59
    //   326: iconst_0
    //   327: bastore
    //   328: dup
    //   329: bipush #60
    //   331: iconst_0
    //   332: bastore
    //   333: dup
    //   334: bipush #61
    //   336: iconst_0
    //   337: bastore
    //   338: dup
    //   339: bipush #62
    //   341: iconst_0
    //   342: bastore
    //   343: dup
    //   344: bipush #63
    //   346: iconst_0
    //   347: bastore
    //   348: astore #5
    //   350: bipush #64
    //   352: newarray int
    //   354: dup
    //   355: iconst_0
    //   356: ldc 1116352408
    //   358: iastore
    //   359: dup
    //   360: iconst_1
    //   361: ldc 1899447441
    //   363: iastore
    //   364: dup
    //   365: iconst_2
    //   366: ldc -1245643825
    //   368: iastore
    //   369: dup
    //   370: iconst_3
    //   371: ldc -373957723
    //   373: iastore
    //   374: dup
    //   375: iconst_4
    //   376: ldc 961987163
    //   378: iastore
    //   379: dup
    //   380: iconst_5
    //   381: ldc 1508970993
    //   383: iastore
    //   384: dup
    //   385: bipush #6
    //   387: ldc -1841331548
    //   389: iastore
    //   390: dup
    //   391: bipush #7
    //   393: ldc -1424204075
    //   395: iastore
    //   396: dup
    //   397: bipush #8
    //   399: ldc -670586216
    //   401: iastore
    //   402: dup
    //   403: bipush #9
    //   405: ldc 310598401
    //   407: iastore
    //   408: dup
    //   409: bipush #10
    //   411: ldc 607225278
    //   413: iastore
    //   414: dup
    //   415: bipush #11
    //   417: ldc 1426881987
    //   419: iastore
    //   420: dup
    //   421: bipush #12
    //   423: ldc 1925078388
    //   425: iastore
    //   426: dup
    //   427: bipush #13
    //   429: ldc -2132889090
    //   431: iastore
    //   432: dup
    //   433: bipush #14
    //   435: ldc -1680079193
    //   437: iastore
    //   438: dup
    //   439: bipush #15
    //   441: ldc -1046744716
    //   443: iastore
    //   444: dup
    //   445: bipush #16
    //   447: ldc -459576895
    //   449: iastore
    //   450: dup
    //   451: bipush #17
    //   453: ldc -272742522
    //   455: iastore
    //   456: dup
    //   457: bipush #18
    //   459: ldc 264347078
    //   461: iastore
    //   462: dup
    //   463: bipush #19
    //   465: ldc 604807628
    //   467: iastore
    //   468: dup
    //   469: bipush #20
    //   471: ldc 770255983
    //   473: iastore
    //   474: dup
    //   475: bipush #21
    //   477: ldc 1249150122
    //   479: iastore
    //   480: dup
    //   481: bipush #22
    //   483: ldc 1555081692
    //   485: iastore
    //   486: dup
    //   487: bipush #23
    //   489: ldc 1996064986
    //   491: iastore
    //   492: dup
    //   493: bipush #24
    //   495: ldc -1740746414
    //   497: iastore
    //   498: dup
    //   499: bipush #25
    //   501: ldc -1473132947
    //   503: iastore
    //   504: dup
    //   505: bipush #26
    //   507: ldc -1341970488
    //   509: iastore
    //   510: dup
    //   511: bipush #27
    //   513: ldc -1084653625
    //   515: iastore
    //   516: dup
    //   517: bipush #28
    //   519: ldc -958395405
    //   521: iastore
    //   522: dup
    //   523: bipush #29
    //   525: ldc -710438585
    //   527: iastore
    //   528: dup
    //   529: bipush #30
    //   531: ldc 113926993
    //   533: iastore
    //   534: dup
    //   535: bipush #31
    //   537: ldc 338241895
    //   539: iastore
    //   540: dup
    //   541: bipush #32
    //   543: ldc 666307205
    //   545: iastore
    //   546: dup
    //   547: bipush #33
    //   549: ldc 773529912
    //   551: iastore
    //   552: dup
    //   553: bipush #34
    //   555: ldc 1294757372
    //   557: iastore
    //   558: dup
    //   559: bipush #35
    //   561: ldc 1396182291
    //   563: iastore
    //   564: dup
    //   565: bipush #36
    //   567: ldc 1695183700
    //   569: iastore
    //   570: dup
    //   571: bipush #37
    //   573: ldc 1986661051
    //   575: iastore
    //   576: dup
    //   577: bipush #38
    //   579: ldc -2117940946
    //   581: iastore
    //   582: dup
    //   583: bipush #39
    //   585: ldc -1838011259
    //   587: iastore
    //   588: dup
    //   589: bipush #40
    //   591: ldc -1564481375
    //   593: iastore
    //   594: dup
    //   595: bipush #41
    //   597: ldc -1474664885
    //   599: iastore
    //   600: dup
    //   601: bipush #42
    //   603: ldc -1035236496
    //   605: iastore
    //   606: dup
    //   607: bipush #43
    //   609: ldc -949202525
    //   611: iastore
    //   612: dup
    //   613: bipush #44
    //   615: ldc -778901479
    //   617: iastore
    //   618: dup
    //   619: bipush #45
    //   621: ldc -694614492
    //   623: iastore
    //   624: dup
    //   625: bipush #46
    //   627: ldc -200395387
    //   629: iastore
    //   630: dup
    //   631: bipush #47
    //   633: ldc 275423344
    //   635: iastore
    //   636: dup
    //   637: bipush #48
    //   639: ldc 430227734
    //   641: iastore
    //   642: dup
    //   643: bipush #49
    //   645: ldc 506948616
    //   647: iastore
    //   648: dup
    //   649: bipush #50
    //   651: ldc 659060556
    //   653: iastore
    //   654: dup
    //   655: bipush #51
    //   657: ldc 883997877
    //   659: iastore
    //   660: dup
    //   661: bipush #52
    //   663: ldc 958139571
    //   665: iastore
    //   666: dup
    //   667: bipush #53
    //   669: ldc 1322822218
    //   671: iastore
    //   672: dup
    //   673: bipush #54
    //   675: ldc 1537002063
    //   677: iastore
    //   678: dup
    //   679: bipush #55
    //   681: ldc 1747873779
    //   683: iastore
    //   684: dup
    //   685: bipush #56
    //   687: ldc 1955562222
    //   689: iastore
    //   690: dup
    //   691: bipush #57
    //   693: ldc 2024104815
    //   695: iastore
    //   696: dup
    //   697: bipush #58
    //   699: ldc -2067236844
    //   701: iastore
    //   702: dup
    //   703: bipush #59
    //   705: ldc -1933114872
    //   707: iastore
    //   708: dup
    //   709: bipush #60
    //   711: ldc -1866530822
    //   713: iastore
    //   714: dup
    //   715: bipush #61
    //   717: ldc -1538233109
    //   719: iastore
    //   720: dup
    //   721: bipush #62
    //   723: ldc -1090935817
    //   725: iastore
    //   726: dup
    //   727: bipush #63
    //   729: ldc -965641998
    //   731: iastore
    //   732: astore #6
    //   734: iconst_2
    //   735: newarray int
    //   737: dup
    //   738: iconst_0
    //   739: iconst_0
    //   740: iastore
    //   741: dup
    //   742: iconst_1
    //   743: iconst_0
    //   744: iastore
    //   745: astore #7
    //   747: bipush #8
    //   749: newarray int
    //   751: dup
    //   752: iconst_0
    //   753: ldc 1779033703
    //   755: iastore
    //   756: dup
    //   757: iconst_1
    //   758: ldc -1150833019
    //   760: iastore
    //   761: dup
    //   762: iconst_2
    //   763: ldc 1013904242
    //   765: iastore
    //   766: dup
    //   767: iconst_3
    //   768: ldc -1521486534
    //   770: iastore
    //   771: dup
    //   772: iconst_4
    //   773: ldc 1359893119
    //   775: iastore
    //   776: dup
    //   777: iconst_5
    //   778: ldc -1694144372
    //   780: iastore
    //   781: dup
    //   782: bipush #6
    //   784: ldc 528734635
    //   786: iastore
    //   787: dup
    //   788: bipush #7
    //   790: ldc 1541459225
    //   792: iastore
    //   793: astore #8
    //   795: bipush #64
    //   797: newarray byte
    //   799: astore #9
    //   801: bipush #64
    //   803: newarray byte
    //   805: astore #10
    //   807: aload_3
    //   808: arraylength
    //   809: istore #11
    //   811: aload #7
    //   813: iconst_0
    //   814: iaload
    //   815: bipush #63
    //   817: iand
    //   818: istore #12
    //   820: aload #7
    //   822: iconst_0
    //   823: dup2
    //   824: iaload
    //   825: iload #11
    //   827: iadd
    //   828: iastore
    //   829: aload #7
    //   831: iconst_0
    //   832: dup2
    //   833: iaload
    //   834: iconst_m1
    //   835: iand
    //   836: iastore
    //   837: aload #7
    //   839: iconst_0
    //   840: iaload
    //   841: iload #11
    //   843: if_icmpge -> 861
    //   846: aload #7
    //   848: iconst_1
    //   849: dup2
    //   850: iaload
    //   851: iconst_1
    //   852: iadd
    //   853: iastore
    //   854: goto -> 861
    //   857: invokestatic a : (Ljava/lang/Throwable;)Ljava/lang/Throwable;
    //   860: athrow
    //   861: iconst_0
    //   862: istore #13
    //   864: iload #11
    //   866: bipush #64
    //   868: if_icmplt -> 1477
    //   871: iconst_0
    //   872: istore #14
    //   874: iload #14
    //   876: bipush #64
    //   878: if_icmpge -> 900
    //   881: aload #10
    //   883: iload #14
    //   885: aload_3
    //   886: iload #13
    //   888: iload #14
    //   890: iadd
    //   891: baload
    //   892: bastore
    //   893: iinc #14, 1
    //   896: iload_2
    //   897: ifeq -> 874
    //   900: bipush #64
    //   902: newarray int
    //   904: astore #14
    //   906: bipush #8
    //   908: newarray int
    //   910: astore #15
    //   912: iconst_0
    //   913: istore #16
    //   915: iload #16
    //   917: bipush #8
    //   919: if_icmpge -> 939
    //   922: aload #15
    //   924: iload #16
    //   926: aload #8
    //   928: iload #16
    //   930: iaload
    //   931: iastore
    //   932: iinc #16, 1
    //   935: iload_2
    //   936: ifeq -> 915
    //   939: iconst_0
    //   940: istore #16
    //   942: iload #16
    //   944: bipush #64
    //   946: if_icmpge -> 1437
    //   949: iload #16
    //   951: bipush #16
    //   953: if_icmpge -> 1034
    //   956: aload #14
    //   958: iload #16
    //   960: aload #10
    //   962: iconst_4
    //   963: iload #16
    //   965: imul
    //   966: baload
    //   967: sipush #255
    //   970: iand
    //   971: bipush #24
    //   973: ishl
    //   974: aload #10
    //   976: iconst_4
    //   977: iload #16
    //   979: imul
    //   980: iconst_1
    //   981: iadd
    //   982: baload
    //   983: sipush #255
    //   986: iand
    //   987: bipush #16
    //   989: ishl
    //   990: ior
    //   991: aload #10
    //   993: iconst_4
    //   994: iload #16
    //   996: imul
    //   997: iconst_2
    //   998: iadd
    //   999: baload
    //   1000: sipush #255
    //   1003: iand
    //   1004: bipush #8
    //   1006: ishl
    //   1007: ior
    //   1008: aload #10
    //   1010: iconst_4
    //   1011: iload #16
    //   1013: imul
    //   1014: iconst_3
    //   1015: iadd
    //   1016: baload
    //   1017: sipush #255
    //   1020: iand
    //   1021: ior
    //   1022: iastore
    //   1023: iload_2
    //   1024: ifeq -> 1177
    //   1027: goto -> 1034
    //   1030: invokestatic a : (Ljava/lang/Throwable;)Ljava/lang/Throwable;
    //   1033: athrow
    //   1034: aload #14
    //   1036: iload #16
    //   1038: aload #14
    //   1040: iload #16
    //   1042: iconst_2
    //   1043: isub
    //   1044: iaload
    //   1045: bipush #17
    //   1047: iushr
    //   1048: aload #14
    //   1050: iload #16
    //   1052: iconst_2
    //   1053: isub
    //   1054: iaload
    //   1055: bipush #15
    //   1057: ishl
    //   1058: ior
    //   1059: aload #14
    //   1061: iload #16
    //   1063: iconst_2
    //   1064: isub
    //   1065: iaload
    //   1066: bipush #19
    //   1068: iushr
    //   1069: aload #14
    //   1071: iload #16
    //   1073: iconst_2
    //   1074: isub
    //   1075: iaload
    //   1076: bipush #13
    //   1078: ishl
    //   1079: ior
    //   1080: ixor
    //   1081: aload #14
    //   1083: iload #16
    //   1085: iconst_2
    //   1086: isub
    //   1087: iaload
    //   1088: bipush #10
    //   1090: iushr
    //   1091: ixor
    //   1092: aload #14
    //   1094: iload #16
    //   1096: bipush #7
    //   1098: isub
    //   1099: iaload
    //   1100: iadd
    //   1101: aload #14
    //   1103: iload #16
    //   1105: bipush #15
    //   1107: isub
    //   1108: iaload
    //   1109: bipush #7
    //   1111: iushr
    //   1112: aload #14
    //   1114: iload #16
    //   1116: bipush #15
    //   1118: isub
    //   1119: iaload
    //   1120: bipush #25
    //   1122: ishl
    //   1123: ior
    //   1124: aload #14
    //   1126: iload #16
    //   1128: bipush #15
    //   1130: isub
    //   1131: iaload
    //   1132: bipush #18
    //   1134: iushr
    //   1135: aload #14
    //   1137: iload #16
    //   1139: bipush #15
    //   1141: isub
    //   1142: iaload
    //   1143: bipush #14
    //   1145: ishl
    //   1146: ior
    //   1147: ixor
    //   1148: aload #14
    //   1150: iload #16
    //   1152: bipush #15
    //   1154: isub
    //   1155: iaload
    //   1156: iconst_3
    //   1157: iushr
    //   1158: ixor
    //   1159: iadd
    //   1160: aload #14
    //   1162: iload #16
    //   1164: bipush #16
    //   1166: isub
    //   1167: iaload
    //   1168: iadd
    //   1169: iastore
    //   1170: goto -> 1177
    //   1173: invokestatic a : (Ljava/lang/Throwable;)Ljava/lang/Throwable;
    //   1176: athrow
    //   1177: aload #15
    //   1179: bipush #7
    //   1181: iaload
    //   1182: aload #15
    //   1184: iconst_4
    //   1185: iaload
    //   1186: bipush #6
    //   1188: iushr
    //   1189: aload #15
    //   1191: iconst_4
    //   1192: iaload
    //   1193: bipush #26
    //   1195: ishl
    //   1196: ior
    //   1197: aload #15
    //   1199: iconst_4
    //   1200: iaload
    //   1201: bipush #11
    //   1203: iushr
    //   1204: aload #15
    //   1206: iconst_4
    //   1207: iaload
    //   1208: bipush #21
    //   1210: ishl
    //   1211: ior
    //   1212: ixor
    //   1213: aload #15
    //   1215: iconst_4
    //   1216: iaload
    //   1217: bipush #25
    //   1219: iushr
    //   1220: aload #15
    //   1222: iconst_4
    //   1223: iaload
    //   1224: bipush #7
    //   1226: ishl
    //   1227: ior
    //   1228: ixor
    //   1229: iadd
    //   1230: aload #15
    //   1232: bipush #6
    //   1234: iaload
    //   1235: aload #15
    //   1237: iconst_4
    //   1238: iaload
    //   1239: aload #15
    //   1241: iconst_5
    //   1242: iaload
    //   1243: aload #15
    //   1245: bipush #6
    //   1247: iaload
    //   1248: ixor
    //   1249: iand
    //   1250: ixor
    //   1251: iadd
    //   1252: aload #6
    //   1254: iload #16
    //   1256: iaload
    //   1257: iadd
    //   1258: aload #14
    //   1260: iload #16
    //   1262: iaload
    //   1263: iadd
    //   1264: istore #17
    //   1266: aload #15
    //   1268: iconst_0
    //   1269: iaload
    //   1270: iconst_2
    //   1271: iushr
    //   1272: aload #15
    //   1274: iconst_0
    //   1275: iaload
    //   1276: bipush #30
    //   1278: ishl
    //   1279: ior
    //   1280: aload #15
    //   1282: iconst_0
    //   1283: iaload
    //   1284: bipush #13
    //   1286: iushr
    //   1287: aload #15
    //   1289: iconst_0
    //   1290: iaload
    //   1291: bipush #19
    //   1293: ishl
    //   1294: ior
    //   1295: ixor
    //   1296: aload #15
    //   1298: iconst_0
    //   1299: iaload
    //   1300: bipush #22
    //   1302: iushr
    //   1303: aload #15
    //   1305: iconst_0
    //   1306: iaload
    //   1307: bipush #10
    //   1309: ishl
    //   1310: ior
    //   1311: ixor
    //   1312: aload #15
    //   1314: iconst_0
    //   1315: iaload
    //   1316: aload #15
    //   1318: iconst_1
    //   1319: iaload
    //   1320: iand
    //   1321: aload #15
    //   1323: iconst_2
    //   1324: iaload
    //   1325: aload #15
    //   1327: iconst_0
    //   1328: iaload
    //   1329: aload #15
    //   1331: iconst_1
    //   1332: iaload
    //   1333: ior
    //   1334: iand
    //   1335: ior
    //   1336: iadd
    //   1337: istore #18
    //   1339: aload #15
    //   1341: iconst_3
    //   1342: dup2
    //   1343: iaload
    //   1344: iload #17
    //   1346: iadd
    //   1347: iastore
    //   1348: aload #15
    //   1350: bipush #7
    //   1352: iload #17
    //   1354: iload #18
    //   1356: iadd
    //   1357: iastore
    //   1358: aload #15
    //   1360: bipush #7
    //   1362: iaload
    //   1363: istore #17
    //   1365: aload #15
    //   1367: bipush #7
    //   1369: aload #15
    //   1371: bipush #6
    //   1373: iaload
    //   1374: iastore
    //   1375: aload #15
    //   1377: bipush #6
    //   1379: aload #15
    //   1381: iconst_5
    //   1382: iaload
    //   1383: iastore
    //   1384: aload #15
    //   1386: iconst_5
    //   1387: aload #15
    //   1389: iconst_4
    //   1390: iaload
    //   1391: iastore
    //   1392: aload #15
    //   1394: iconst_4
    //   1395: aload #15
    //   1397: iconst_3
    //   1398: iaload
    //   1399: iastore
    //   1400: aload #15
    //   1402: iconst_3
    //   1403: aload #15
    //   1405: iconst_2
    //   1406: iaload
    //   1407: iastore
    //   1408: aload #15
    //   1410: iconst_2
    //   1411: aload #15
    //   1413: iconst_1
    //   1414: iaload
    //   1415: iastore
    //   1416: aload #15
    //   1418: iconst_1
    //   1419: aload #15
    //   1421: iconst_0
    //   1422: iaload
    //   1423: iastore
    //   1424: aload #15
    //   1426: iconst_0
    //   1427: iload #17
    //   1429: iastore
    //   1430: iinc #16, 1
    //   1433: iload_2
    //   1434: ifeq -> 942
    //   1437: iconst_0
    //   1438: istore #16
    //   1440: iload #16
    //   1442: bipush #8
    //   1444: if_icmpge -> 1467
    //   1447: aload #8
    //   1449: iload #16
    //   1451: dup2
    //   1452: iaload
    //   1453: aload #15
    //   1455: iload #16
    //   1457: iaload
    //   1458: iadd
    //   1459: iastore
    //   1460: iinc #16, 1
    //   1463: iload_2
    //   1464: ifeq -> 1440
    //   1467: iinc #13, 64
    //   1470: iinc #11, -64
    //   1473: iload_2
    //   1474: ifeq -> 864
    //   1477: iload #11
    //   1479: ifle -> 1514
    //   1482: iconst_0
    //   1483: istore #14
    //   1485: iload #14
    //   1487: iload #11
    //   1489: if_icmpge -> 1514
    //   1492: aload #9
    //   1494: iload #12
    //   1496: iload #14
    //   1498: iadd
    //   1499: aload_3
    //   1500: iload #13
    //   1502: iload #14
    //   1504: iadd
    //   1505: baload
    //   1506: bastore
    //   1507: iinc #14, 1
    //   1510: iload_2
    //   1511: ifeq -> 1485
    //   1514: aload #7
    //   1516: iconst_0
    //   1517: iaload
    //   1518: bipush #29
    //   1520: iushr
    //   1521: aload #7
    //   1523: iconst_1
    //   1524: iaload
    //   1525: iconst_3
    //   1526: ishl
    //   1527: ior
    //   1528: istore #14
    //   1530: aload #7
    //   1532: iconst_0
    //   1533: iaload
    //   1534: iconst_3
    //   1535: ishl
    //   1536: istore #15
    //   1538: aload #7
    //   1540: iconst_0
    //   1541: iaload
    //   1542: bipush #63
    //   1544: iand
    //   1545: istore #16
    //   1547: iload #16
    //   1549: bipush #56
    //   1551: if_icmpge -> 1566
    //   1554: bipush #56
    //   1556: iload #16
    //   1558: isub
    //   1559: goto -> 1571
    //   1562: invokestatic a : (Ljava/lang/Throwable;)Ljava/lang/Throwable;
    //   1565: athrow
    //   1566: bipush #120
    //   1568: iload #16
    //   1570: isub
    //   1571: istore #17
    //   1573: aload #7
    //   1575: iconst_0
    //   1576: iaload
    //   1577: bipush #63
    //   1579: iand
    //   1580: istore #12
    //   1582: bipush #64
    //   1584: iload #12
    //   1586: isub
    //   1587: istore #18
    //   1589: aload #7
    //   1591: iconst_0
    //   1592: dup2
    //   1593: iaload
    //   1594: iload #17
    //   1596: iadd
    //   1597: iastore
    //   1598: aload #7
    //   1600: iconst_0
    //   1601: dup2
    //   1602: iaload
    //   1603: iconst_m1
    //   1604: iand
    //   1605: iastore
    //   1606: aload #7
    //   1608: iconst_0
    //   1609: iaload
    //   1610: iload #17
    //   1612: if_icmpge -> 1630
    //   1615: aload #7
    //   1617: iconst_1
    //   1618: dup2
    //   1619: iaload
    //   1620: iconst_1
    //   1621: iadd
    //   1622: iastore
    //   1623: goto -> 1630
    //   1626: invokestatic a : (Ljava/lang/Throwable;)Ljava/lang/Throwable;
    //   1629: athrow
    //   1630: iconst_0
    //   1631: istore #13
    //   1633: iload #12
    //   1635: ifle -> 2266
    //   1638: iload #17
    //   1640: iload #18
    //   1642: if_icmplt -> 2266
    //   1645: goto -> 1652
    //   1648: invokestatic a : (Ljava/lang/Throwable;)Ljava/lang/Throwable;
    //   1651: athrow
    //   1652: iconst_0
    //   1653: istore #19
    //   1655: iload #19
    //   1657: iload #18
    //   1659: if_icmpge -> 1682
    //   1662: aload #9
    //   1664: iload #12
    //   1666: iload #19
    //   1668: iadd
    //   1669: aload #5
    //   1671: iload #19
    //   1673: baload
    //   1674: bastore
    //   1675: iinc #19, 1
    //   1678: iload_2
    //   1679: ifeq -> 1655
    //   1682: bipush #64
    //   1684: newarray int
    //   1686: astore #19
    //   1688: bipush #8
    //   1690: newarray int
    //   1692: astore #20
    //   1694: iconst_0
    //   1695: istore #21
    //   1697: iload #21
    //   1699: bipush #8
    //   1701: if_icmpge -> 1721
    //   1704: aload #20
    //   1706: iload #21
    //   1708: aload #8
    //   1710: iload #21
    //   1712: iaload
    //   1713: iastore
    //   1714: iinc #21, 1
    //   1717: iload_2
    //   1718: ifeq -> 1697
    //   1721: iconst_0
    //   1722: istore #21
    //   1724: iload #21
    //   1726: bipush #64
    //   1728: if_icmpge -> 2219
    //   1731: iload #21
    //   1733: bipush #16
    //   1735: if_icmpge -> 1816
    //   1738: aload #19
    //   1740: iload #21
    //   1742: aload #9
    //   1744: iconst_4
    //   1745: iload #21
    //   1747: imul
    //   1748: baload
    //   1749: sipush #255
    //   1752: iand
    //   1753: bipush #24
    //   1755: ishl
    //   1756: aload #9
    //   1758: iconst_4
    //   1759: iload #21
    //   1761: imul
    //   1762: iconst_1
    //   1763: iadd
    //   1764: baload
    //   1765: sipush #255
    //   1768: iand
    //   1769: bipush #16
    //   1771: ishl
    //   1772: ior
    //   1773: aload #9
    //   1775: iconst_4
    //   1776: iload #21
    //   1778: imul
    //   1779: iconst_2
    //   1780: iadd
    //   1781: baload
    //   1782: sipush #255
    //   1785: iand
    //   1786: bipush #8
    //   1788: ishl
    //   1789: ior
    //   1790: aload #9
    //   1792: iconst_4
    //   1793: iload #21
    //   1795: imul
    //   1796: iconst_3
    //   1797: iadd
    //   1798: baload
    //   1799: sipush #255
    //   1802: iand
    //   1803: ior
    //   1804: iastore
    //   1805: iload_2
    //   1806: ifeq -> 1959
    //   1809: goto -> 1816
    //   1812: invokestatic a : (Ljava/lang/Throwable;)Ljava/lang/Throwable;
    //   1815: athrow
    //   1816: aload #19
    //   1818: iload #21
    //   1820: aload #19
    //   1822: iload #21
    //   1824: iconst_2
    //   1825: isub
    //   1826: iaload
    //   1827: bipush #17
    //   1829: iushr
    //   1830: aload #19
    //   1832: iload #21
    //   1834: iconst_2
    //   1835: isub
    //   1836: iaload
    //   1837: bipush #15
    //   1839: ishl
    //   1840: ior
    //   1841: aload #19
    //   1843: iload #21
    //   1845: iconst_2
    //   1846: isub
    //   1847: iaload
    //   1848: bipush #19
    //   1850: iushr
    //   1851: aload #19
    //   1853: iload #21
    //   1855: iconst_2
    //   1856: isub
    //   1857: iaload
    //   1858: bipush #13
    //   1860: ishl
    //   1861: ior
    //   1862: ixor
    //   1863: aload #19
    //   1865: iload #21
    //   1867: iconst_2
    //   1868: isub
    //   1869: iaload
    //   1870: bipush #10
    //   1872: iushr
    //   1873: ixor
    //   1874: aload #19
    //   1876: iload #21
    //   1878: bipush #7
    //   1880: isub
    //   1881: iaload
    //   1882: iadd
    //   1883: aload #19
    //   1885: iload #21
    //   1887: bipush #15
    //   1889: isub
    //   1890: iaload
    //   1891: bipush #7
    //   1893: iushr
    //   1894: aload #19
    //   1896: iload #21
    //   1898: bipush #15
    //   1900: isub
    //   1901: iaload
    //   1902: bipush #25
    //   1904: ishl
    //   1905: ior
    //   1906: aload #19
    //   1908: iload #21
    //   1910: bipush #15
    //   1912: isub
    //   1913: iaload
    //   1914: bipush #18
    //   1916: iushr
    //   1917: aload #19
    //   1919: iload #21
    //   1921: bipush #15
    //   1923: isub
    //   1924: iaload
    //   1925: bipush #14
    //   1927: ishl
    //   1928: ior
    //   1929: ixor
    //   1930: aload #19
    //   1932: iload #21
    //   1934: bipush #15
    //   1936: isub
    //   1937: iaload
    //   1938: iconst_3
    //   1939: iushr
    //   1940: ixor
    //   1941: iadd
    //   1942: aload #19
    //   1944: iload #21
    //   1946: bipush #16
    //   1948: isub
    //   1949: iaload
    //   1950: iadd
    //   1951: iastore
    //   1952: goto -> 1959
    //   1955: invokestatic a : (Ljava/lang/Throwable;)Ljava/lang/Throwable;
    //   1958: athrow
    //   1959: aload #20
    //   1961: bipush #7
    //   1963: iaload
    //   1964: aload #20
    //   1966: iconst_4
    //   1967: iaload
    //   1968: bipush #6
    //   1970: iushr
    //   1971: aload #20
    //   1973: iconst_4
    //   1974: iaload
    //   1975: bipush #26
    //   1977: ishl
    //   1978: ior
    //   1979: aload #20
    //   1981: iconst_4
    //   1982: iaload
    //   1983: bipush #11
    //   1985: iushr
    //   1986: aload #20
    //   1988: iconst_4
    //   1989: iaload
    //   1990: bipush #21
    //   1992: ishl
    //   1993: ior
    //   1994: ixor
    //   1995: aload #20
    //   1997: iconst_4
    //   1998: iaload
    //   1999: bipush #25
    //   2001: iushr
    //   2002: aload #20
    //   2004: iconst_4
    //   2005: iaload
    //   2006: bipush #7
    //   2008: ishl
    //   2009: ior
    //   2010: ixor
    //   2011: iadd
    //   2012: aload #20
    //   2014: bipush #6
    //   2016: iaload
    //   2017: aload #20
    //   2019: iconst_4
    //   2020: iaload
    //   2021: aload #20
    //   2023: iconst_5
    //   2024: iaload
    //   2025: aload #20
    //   2027: bipush #6
    //   2029: iaload
    //   2030: ixor
    //   2031: iand
    //   2032: ixor
    //   2033: iadd
    //   2034: aload #6
    //   2036: iload #21
    //   2038: iaload
    //   2039: iadd
    //   2040: aload #19
    //   2042: iload #21
    //   2044: iaload
    //   2045: iadd
    //   2046: istore #22
    //   2048: aload #20
    //   2050: iconst_0
    //   2051: iaload
    //   2052: iconst_2
    //   2053: iushr
    //   2054: aload #20
    //   2056: iconst_0
    //   2057: iaload
    //   2058: bipush #30
    //   2060: ishl
    //   2061: ior
    //   2062: aload #20
    //   2064: iconst_0
    //   2065: iaload
    //   2066: bipush #13
    //   2068: iushr
    //   2069: aload #20
    //   2071: iconst_0
    //   2072: iaload
    //   2073: bipush #19
    //   2075: ishl
    //   2076: ior
    //   2077: ixor
    //   2078: aload #20
    //   2080: iconst_0
    //   2081: iaload
    //   2082: bipush #22
    //   2084: iushr
    //   2085: aload #20
    //   2087: iconst_0
    //   2088: iaload
    //   2089: bipush #10
    //   2091: ishl
    //   2092: ior
    //   2093: ixor
    //   2094: aload #20
    //   2096: iconst_0
    //   2097: iaload
    //   2098: aload #20
    //   2100: iconst_1
    //   2101: iaload
    //   2102: iand
    //   2103: aload #20
    //   2105: iconst_2
    //   2106: iaload
    //   2107: aload #20
    //   2109: iconst_0
    //   2110: iaload
    //   2111: aload #20
    //   2113: iconst_1
    //   2114: iaload
    //   2115: ior
    //   2116: iand
    //   2117: ior
    //   2118: iadd
    //   2119: istore #23
    //   2121: aload #20
    //   2123: iconst_3
    //   2124: dup2
    //   2125: iaload
    //   2126: iload #22
    //   2128: iadd
    //   2129: iastore
    //   2130: aload #20
    //   2132: bipush #7
    //   2134: iload #22
    //   2136: iload #23
    //   2138: iadd
    //   2139: iastore
    //   2140: aload #20
    //   2142: bipush #7
    //   2144: iaload
    //   2145: istore #22
    //   2147: aload #20
    //   2149: bipush #7
    //   2151: aload #20
    //   2153: bipush #6
    //   2155: iaload
    //   2156: iastore
    //   2157: aload #20
    //   2159: bipush #6
    //   2161: aload #20
    //   2163: iconst_5
    //   2164: iaload
    //   2165: iastore
    //   2166: aload #20
    //   2168: iconst_5
    //   2169: aload #20
    //   2171: iconst_4
    //   2172: iaload
    //   2173: iastore
    //   2174: aload #20
    //   2176: iconst_4
    //   2177: aload #20
    //   2179: iconst_3
    //   2180: iaload
    //   2181: iastore
    //   2182: aload #20
    //   2184: iconst_3
    //   2185: aload #20
    //   2187: iconst_2
    //   2188: iaload
    //   2189: iastore
    //   2190: aload #20
    //   2192: iconst_2
    //   2193: aload #20
    //   2195: iconst_1
    //   2196: iaload
    //   2197: iastore
    //   2198: aload #20
    //   2200: iconst_1
    //   2201: aload #20
    //   2203: iconst_0
    //   2204: iaload
    //   2205: iastore
    //   2206: aload #20
    //   2208: iconst_0
    //   2209: iload #22
    //   2211: iastore
    //   2212: iinc #21, 1
    //   2215: iload_2
    //   2216: ifeq -> 1724
    //   2219: iconst_0
    //   2220: istore #21
    //   2222: iload #21
    //   2224: bipush #8
    //   2226: if_icmpge -> 2249
    //   2229: aload #8
    //   2231: iload #21
    //   2233: dup2
    //   2234: iaload
    //   2235: aload #20
    //   2237: iload #21
    //   2239: iaload
    //   2240: iadd
    //   2241: iastore
    //   2242: iinc #21, 1
    //   2245: iload_2
    //   2246: ifeq -> 2222
    //   2249: iload #13
    //   2251: iload #18
    //   2253: iadd
    //   2254: istore #13
    //   2256: iload #17
    //   2258: iload #18
    //   2260: isub
    //   2261: istore #17
    //   2263: iconst_0
    //   2264: istore #12
    //   2266: iload #17
    //   2268: bipush #64
    //   2270: if_icmplt -> 2880
    //   2273: iconst_0
    //   2274: istore #19
    //   2276: iload #19
    //   2278: bipush #64
    //   2280: if_icmpge -> 2303
    //   2283: aload #10
    //   2285: iload #19
    //   2287: aload #5
    //   2289: iload #13
    //   2291: iload #19
    //   2293: iadd
    //   2294: baload
    //   2295: bastore
    //   2296: iinc #19, 1
    //   2299: iload_2
    //   2300: ifeq -> 2276
    //   2303: bipush #64
    //   2305: newarray int
    //   2307: astore #19
    //   2309: bipush #8
    //   2311: newarray int
    //   2313: astore #20
    //   2315: iconst_0
    //   2316: istore #21
    //   2318: iload #21
    //   2320: bipush #8
    //   2322: if_icmpge -> 2342
    //   2325: aload #20
    //   2327: iload #21
    //   2329: aload #8
    //   2331: iload #21
    //   2333: iaload
    //   2334: iastore
    //   2335: iinc #21, 1
    //   2338: iload_2
    //   2339: ifeq -> 2318
    //   2342: iconst_0
    //   2343: istore #21
    //   2345: iload #21
    //   2347: bipush #64
    //   2349: if_icmpge -> 2840
    //   2352: iload #21
    //   2354: bipush #16
    //   2356: if_icmpge -> 2437
    //   2359: aload #19
    //   2361: iload #21
    //   2363: aload #10
    //   2365: iconst_4
    //   2366: iload #21
    //   2368: imul
    //   2369: baload
    //   2370: sipush #255
    //   2373: iand
    //   2374: bipush #24
    //   2376: ishl
    //   2377: aload #10
    //   2379: iconst_4
    //   2380: iload #21
    //   2382: imul
    //   2383: iconst_1
    //   2384: iadd
    //   2385: baload
    //   2386: sipush #255
    //   2389: iand
    //   2390: bipush #16
    //   2392: ishl
    //   2393: ior
    //   2394: aload #10
    //   2396: iconst_4
    //   2397: iload #21
    //   2399: imul
    //   2400: iconst_2
    //   2401: iadd
    //   2402: baload
    //   2403: sipush #255
    //   2406: iand
    //   2407: bipush #8
    //   2409: ishl
    //   2410: ior
    //   2411: aload #10
    //   2413: iconst_4
    //   2414: iload #21
    //   2416: imul
    //   2417: iconst_3
    //   2418: iadd
    //   2419: baload
    //   2420: sipush #255
    //   2423: iand
    //   2424: ior
    //   2425: iastore
    //   2426: iload_2
    //   2427: ifeq -> 2580
    //   2430: goto -> 2437
    //   2433: invokestatic a : (Ljava/lang/Throwable;)Ljava/lang/Throwable;
    //   2436: athrow
    //   2437: aload #19
    //   2439: iload #21
    //   2441: aload #19
    //   2443: iload #21
    //   2445: iconst_2
    //   2446: isub
    //   2447: iaload
    //   2448: bipush #17
    //   2450: iushr
    //   2451: aload #19
    //   2453: iload #21
    //   2455: iconst_2
    //   2456: isub
    //   2457: iaload
    //   2458: bipush #15
    //   2460: ishl
    //   2461: ior
    //   2462: aload #19
    //   2464: iload #21
    //   2466: iconst_2
    //   2467: isub
    //   2468: iaload
    //   2469: bipush #19
    //   2471: iushr
    //   2472: aload #19
    //   2474: iload #21
    //   2476: iconst_2
    //   2477: isub
    //   2478: iaload
    //   2479: bipush #13
    //   2481: ishl
    //   2482: ior
    //   2483: ixor
    //   2484: aload #19
    //   2486: iload #21
    //   2488: iconst_2
    //   2489: isub
    //   2490: iaload
    //   2491: bipush #10
    //   2493: iushr
    //   2494: ixor
    //   2495: aload #19
    //   2497: iload #21
    //   2499: bipush #7
    //   2501: isub
    //   2502: iaload
    //   2503: iadd
    //   2504: aload #19
    //   2506: iload #21
    //   2508: bipush #15
    //   2510: isub
    //   2511: iaload
    //   2512: bipush #7
    //   2514: iushr
    //   2515: aload #19
    //   2517: iload #21
    //   2519: bipush #15
    //   2521: isub
    //   2522: iaload
    //   2523: bipush #25
    //   2525: ishl
    //   2526: ior
    //   2527: aload #19
    //   2529: iload #21
    //   2531: bipush #15
    //   2533: isub
    //   2534: iaload
    //   2535: bipush #18
    //   2537: iushr
    //   2538: aload #19
    //   2540: iload #21
    //   2542: bipush #15
    //   2544: isub
    //   2545: iaload
    //   2546: bipush #14
    //   2548: ishl
    //   2549: ior
    //   2550: ixor
    //   2551: aload #19
    //   2553: iload #21
    //   2555: bipush #15
    //   2557: isub
    //   2558: iaload
    //   2559: iconst_3
    //   2560: iushr
    //   2561: ixor
    //   2562: iadd
    //   2563: aload #19
    //   2565: iload #21
    //   2567: bipush #16
    //   2569: isub
    //   2570: iaload
    //   2571: iadd
    //   2572: iastore
    //   2573: goto -> 2580
    //   2576: invokestatic a : (Ljava/lang/Throwable;)Ljava/lang/Throwable;
    //   2579: athrow
    //   2580: aload #20
    //   2582: bipush #7
    //   2584: iaload
    //   2585: aload #20
    //   2587: iconst_4
    //   2588: iaload
    //   2589: bipush #6
    //   2591: iushr
    //   2592: aload #20
    //   2594: iconst_4
    //   2595: iaload
    //   2596: bipush #26
    //   2598: ishl
    //   2599: ior
    //   2600: aload #20
    //   2602: iconst_4
    //   2603: iaload
    //   2604: bipush #11
    //   2606: iushr
    //   2607: aload #20
    //   2609: iconst_4
    //   2610: iaload
    //   2611: bipush #21
    //   2613: ishl
    //   2614: ior
    //   2615: ixor
    //   2616: aload #20
    //   2618: iconst_4
    //   2619: iaload
    //   2620: bipush #25
    //   2622: iushr
    //   2623: aload #20
    //   2625: iconst_4
    //   2626: iaload
    //   2627: bipush #7
    //   2629: ishl
    //   2630: ior
    //   2631: ixor
    //   2632: iadd
    //   2633: aload #20
    //   2635: bipush #6
    //   2637: iaload
    //   2638: aload #20
    //   2640: iconst_4
    //   2641: iaload
    //   2642: aload #20
    //   2644: iconst_5
    //   2645: iaload
    //   2646: aload #20
    //   2648: bipush #6
    //   2650: iaload
    //   2651: ixor
    //   2652: iand
    //   2653: ixor
    //   2654: iadd
    //   2655: aload #6
    //   2657: iload #21
    //   2659: iaload
    //   2660: iadd
    //   2661: aload #19
    //   2663: iload #21
    //   2665: iaload
    //   2666: iadd
    //   2667: istore #22
    //   2669: aload #20
    //   2671: iconst_0
    //   2672: iaload
    //   2673: iconst_2
    //   2674: iushr
    //   2675: aload #20
    //   2677: iconst_0
    //   2678: iaload
    //   2679: bipush #30
    //   2681: ishl
    //   2682: ior
    //   2683: aload #20
    //   2685: iconst_0
    //   2686: iaload
    //   2687: bipush #13
    //   2689: iushr
    //   2690: aload #20
    //   2692: iconst_0
    //   2693: iaload
    //   2694: bipush #19
    //   2696: ishl
    //   2697: ior
    //   2698: ixor
    //   2699: aload #20
    //   2701: iconst_0
    //   2702: iaload
    //   2703: bipush #22
    //   2705: iushr
    //   2706: aload #20
    //   2708: iconst_0
    //   2709: iaload
    //   2710: bipush #10
    //   2712: ishl
    //   2713: ior
    //   2714: ixor
    //   2715: aload #20
    //   2717: iconst_0
    //   2718: iaload
    //   2719: aload #20
    //   2721: iconst_1
    //   2722: iaload
    //   2723: iand
    //   2724: aload #20
    //   2726: iconst_2
    //   2727: iaload
    //   2728: aload #20
    //   2730: iconst_0
    //   2731: iaload
    //   2732: aload #20
    //   2734: iconst_1
    //   2735: iaload
    //   2736: ior
    //   2737: iand
    //   2738: ior
    //   2739: iadd
    //   2740: istore #23
    //   2742: aload #20
    //   2744: iconst_3
    //   2745: dup2
    //   2746: iaload
    //   2747: iload #22
    //   2749: iadd
    //   2750: iastore
    //   2751: aload #20
    //   2753: bipush #7
    //   2755: iload #22
    //   2757: iload #23
    //   2759: iadd
    //   2760: iastore
    //   2761: aload #20
    //   2763: bipush #7
    //   2765: iaload
    //   2766: istore #22
    //   2768: aload #20
    //   2770: bipush #7
    //   2772: aload #20
    //   2774: bipush #6
    //   2776: iaload
    //   2777: iastore
    //   2778: aload #20
    //   2780: bipush #6
    //   2782: aload #20
    //   2784: iconst_5
    //   2785: iaload
    //   2786: iastore
    //   2787: aload #20
    //   2789: iconst_5
    //   2790: aload #20
    //   2792: iconst_4
    //   2793: iaload
    //   2794: iastore
    //   2795: aload #20
    //   2797: iconst_4
    //   2798: aload #20
    //   2800: iconst_3
    //   2801: iaload
    //   2802: iastore
    //   2803: aload #20
    //   2805: iconst_3
    //   2806: aload #20
    //   2808: iconst_2
    //   2809: iaload
    //   2810: iastore
    //   2811: aload #20
    //   2813: iconst_2
    //   2814: aload #20
    //   2816: iconst_1
    //   2817: iaload
    //   2818: iastore
    //   2819: aload #20
    //   2821: iconst_1
    //   2822: aload #20
    //   2824: iconst_0
    //   2825: iaload
    //   2826: iastore
    //   2827: aload #20
    //   2829: iconst_0
    //   2830: iload #22
    //   2832: iastore
    //   2833: iinc #21, 1
    //   2836: iload_2
    //   2837: ifeq -> 2345
    //   2840: iconst_0
    //   2841: istore #21
    //   2843: iload #21
    //   2845: bipush #8
    //   2847: if_icmpge -> 2870
    //   2850: aload #8
    //   2852: iload #21
    //   2854: dup2
    //   2855: iaload
    //   2856: aload #20
    //   2858: iload #21
    //   2860: iaload
    //   2861: iadd
    //   2862: iastore
    //   2863: iinc #21, 1
    //   2866: iload_2
    //   2867: ifeq -> 2843
    //   2870: iinc #13, 64
    //   2873: iinc #17, -64
    //   2876: iload_2
    //   2877: ifeq -> 2266
    //   2880: iload #17
    //   2882: ifle -> 2918
    //   2885: iconst_0
    //   2886: istore #19
    //   2888: iload #19
    //   2890: iload #17
    //   2892: if_icmpge -> 2918
    //   2895: aload #9
    //   2897: iload #12
    //   2899: iload #19
    //   2901: iadd
    //   2902: aload #5
    //   2904: iload #13
    //   2906: iload #19
    //   2908: iadd
    //   2909: baload
    //   2910: bastore
    //   2911: iinc #19, 1
    //   2914: iload_2
    //   2915: ifeq -> 2888
    //   2918: bipush #8
    //   2920: newarray byte
    //   2922: astore #19
    //   2924: aload #19
    //   2926: iconst_0
    //   2927: iload #14
    //   2929: bipush #24
    //   2931: iushr
    //   2932: i2b
    //   2933: bastore
    //   2934: aload #19
    //   2936: iconst_1
    //   2937: iload #14
    //   2939: bipush #16
    //   2941: iushr
    //   2942: i2b
    //   2943: bastore
    //   2944: aload #19
    //   2946: iconst_2
    //   2947: iload #14
    //   2949: bipush #8
    //   2951: iushr
    //   2952: i2b
    //   2953: bastore
    //   2954: aload #19
    //   2956: iconst_3
    //   2957: iload #14
    //   2959: i2b
    //   2960: bastore
    //   2961: aload #19
    //   2963: iconst_4
    //   2964: iload #15
    //   2966: bipush #24
    //   2968: iushr
    //   2969: i2b
    //   2970: bastore
    //   2971: aload #19
    //   2973: iconst_5
    //   2974: iload #15
    //   2976: bipush #16
    //   2978: iushr
    //   2979: i2b
    //   2980: bastore
    //   2981: aload #19
    //   2983: bipush #6
    //   2985: iload #15
    //   2987: bipush #8
    //   2989: iushr
    //   2990: i2b
    //   2991: bastore
    //   2992: aload #19
    //   2994: bipush #7
    //   2996: iload #15
    //   2998: i2b
    //   2999: bastore
    //   3000: bipush #8
    //   3002: istore #11
    //   3004: aload #7
    //   3006: iconst_0
    //   3007: iaload
    //   3008: bipush #63
    //   3010: iand
    //   3011: istore #12
    //   3013: bipush #64
    //   3015: iload #12
    //   3017: isub
    //   3018: istore #18
    //   3020: aload #7
    //   3022: iconst_0
    //   3023: dup2
    //   3024: iaload
    //   3025: iload #11
    //   3027: iadd
    //   3028: iastore
    //   3029: aload #7
    //   3031: iconst_0
    //   3032: dup2
    //   3033: iaload
    //   3034: iconst_m1
    //   3035: iand
    //   3036: iastore
    //   3037: aload #7
    //   3039: iconst_0
    //   3040: iaload
    //   3041: iload #11
    //   3043: if_icmpge -> 3061
    //   3046: aload #7
    //   3048: iconst_1
    //   3049: dup2
    //   3050: iaload
    //   3051: iconst_1
    //   3052: iadd
    //   3053: iastore
    //   3054: goto -> 3061
    //   3057: invokestatic a : (Ljava/lang/Throwable;)Ljava/lang/Throwable;
    //   3060: athrow
    //   3061: iload #12
    //   3063: ifle -> 3677
    //   3066: iload #11
    //   3068: iload #18
    //   3070: if_icmplt -> 3677
    //   3073: goto -> 3080
    //   3076: invokestatic a : (Ljava/lang/Throwable;)Ljava/lang/Throwable;
    //   3079: athrow
    //   3080: iconst_0
    //   3081: istore #20
    //   3083: iload #20
    //   3085: iload #18
    //   3087: if_icmpge -> 3110
    //   3090: aload #9
    //   3092: iload #12
    //   3094: iload #20
    //   3096: iadd
    //   3097: aload #19
    //   3099: iload #20
    //   3101: baload
    //   3102: bastore
    //   3103: iinc #20, 1
    //   3106: iload_2
    //   3107: ifeq -> 3083
    //   3110: bipush #64
    //   3112: newarray int
    //   3114: astore #20
    //   3116: bipush #8
    //   3118: newarray int
    //   3120: astore #21
    //   3122: iconst_0
    //   3123: istore #22
    //   3125: iload #22
    //   3127: bipush #8
    //   3129: if_icmpge -> 3149
    //   3132: aload #21
    //   3134: iload #22
    //   3136: aload #8
    //   3138: iload #22
    //   3140: iaload
    //   3141: iastore
    //   3142: iinc #22, 1
    //   3145: iload_2
    //   3146: ifeq -> 3125
    //   3149: iconst_0
    //   3150: istore #22
    //   3152: iload #22
    //   3154: bipush #64
    //   3156: if_icmpge -> 3647
    //   3159: iload #22
    //   3161: bipush #16
    //   3163: if_icmpge -> 3244
    //   3166: aload #20
    //   3168: iload #22
    //   3170: aload #9
    //   3172: iconst_4
    //   3173: iload #22
    //   3175: imul
    //   3176: baload
    //   3177: sipush #255
    //   3180: iand
    //   3181: bipush #24
    //   3183: ishl
    //   3184: aload #9
    //   3186: iconst_4
    //   3187: iload #22
    //   3189: imul
    //   3190: iconst_1
    //   3191: iadd
    //   3192: baload
    //   3193: sipush #255
    //   3196: iand
    //   3197: bipush #16
    //   3199: ishl
    //   3200: ior
    //   3201: aload #9
    //   3203: iconst_4
    //   3204: iload #22
    //   3206: imul
    //   3207: iconst_2
    //   3208: iadd
    //   3209: baload
    //   3210: sipush #255
    //   3213: iand
    //   3214: bipush #8
    //   3216: ishl
    //   3217: ior
    //   3218: aload #9
    //   3220: iconst_4
    //   3221: iload #22
    //   3223: imul
    //   3224: iconst_3
    //   3225: iadd
    //   3226: baload
    //   3227: sipush #255
    //   3230: iand
    //   3231: ior
    //   3232: iastore
    //   3233: iload_2
    //   3234: ifeq -> 3387
    //   3237: goto -> 3244
    //   3240: invokestatic a : (Ljava/lang/Throwable;)Ljava/lang/Throwable;
    //   3243: athrow
    //   3244: aload #20
    //   3246: iload #22
    //   3248: aload #20
    //   3250: iload #22
    //   3252: iconst_2
    //   3253: isub
    //   3254: iaload
    //   3255: bipush #17
    //   3257: iushr
    //   3258: aload #20
    //   3260: iload #22
    //   3262: iconst_2
    //   3263: isub
    //   3264: iaload
    //   3265: bipush #15
    //   3267: ishl
    //   3268: ior
    //   3269: aload #20
    //   3271: iload #22
    //   3273: iconst_2
    //   3274: isub
    //   3275: iaload
    //   3276: bipush #19
    //   3278: iushr
    //   3279: aload #20
    //   3281: iload #22
    //   3283: iconst_2
    //   3284: isub
    //   3285: iaload
    //   3286: bipush #13
    //   3288: ishl
    //   3289: ior
    //   3290: ixor
    //   3291: aload #20
    //   3293: iload #22
    //   3295: iconst_2
    //   3296: isub
    //   3297: iaload
    //   3298: bipush #10
    //   3300: iushr
    //   3301: ixor
    //   3302: aload #20
    //   3304: iload #22
    //   3306: bipush #7
    //   3308: isub
    //   3309: iaload
    //   3310: iadd
    //   3311: aload #20
    //   3313: iload #22
    //   3315: bipush #15
    //   3317: isub
    //   3318: iaload
    //   3319: bipush #7
    //   3321: iushr
    //   3322: aload #20
    //   3324: iload #22
    //   3326: bipush #15
    //   3328: isub
    //   3329: iaload
    //   3330: bipush #25
    //   3332: ishl
    //   3333: ior
    //   3334: aload #20
    //   3336: iload #22
    //   3338: bipush #15
    //   3340: isub
    //   3341: iaload
    //   3342: bipush #18
    //   3344: iushr
    //   3345: aload #20
    //   3347: iload #22
    //   3349: bipush #15
    //   3351: isub
    //   3352: iaload
    //   3353: bipush #14
    //   3355: ishl
    //   3356: ior
    //   3357: ixor
    //   3358: aload #20
    //   3360: iload #22
    //   3362: bipush #15
    //   3364: isub
    //   3365: iaload
    //   3366: iconst_3
    //   3367: iushr
    //   3368: ixor
    //   3369: iadd
    //   3370: aload #20
    //   3372: iload #22
    //   3374: bipush #16
    //   3376: isub
    //   3377: iaload
    //   3378: iadd
    //   3379: iastore
    //   3380: goto -> 3387
    //   3383: invokestatic a : (Ljava/lang/Throwable;)Ljava/lang/Throwable;
    //   3386: athrow
    //   3387: aload #21
    //   3389: bipush #7
    //   3391: iaload
    //   3392: aload #21
    //   3394: iconst_4
    //   3395: iaload
    //   3396: bipush #6
    //   3398: iushr
    //   3399: aload #21
    //   3401: iconst_4
    //   3402: iaload
    //   3403: bipush #26
    //   3405: ishl
    //   3406: ior
    //   3407: aload #21
    //   3409: iconst_4
    //   3410: iaload
    //   3411: bipush #11
    //   3413: iushr
    //   3414: aload #21
    //   3416: iconst_4
    //   3417: iaload
    //   3418: bipush #21
    //   3420: ishl
    //   3421: ior
    //   3422: ixor
    //   3423: aload #21
    //   3425: iconst_4
    //   3426: iaload
    //   3427: bipush #25
    //   3429: iushr
    //   3430: aload #21
    //   3432: iconst_4
    //   3433: iaload
    //   3434: bipush #7
    //   3436: ishl
    //   3437: ior
    //   3438: ixor
    //   3439: iadd
    //   3440: aload #21
    //   3442: bipush #6
    //   3444: iaload
    //   3445: aload #21
    //   3447: iconst_4
    //   3448: iaload
    //   3449: aload #21
    //   3451: iconst_5
    //   3452: iaload
    //   3453: aload #21
    //   3455: bipush #6
    //   3457: iaload
    //   3458: ixor
    //   3459: iand
    //   3460: ixor
    //   3461: iadd
    //   3462: aload #6
    //   3464: iload #22
    //   3466: iaload
    //   3467: iadd
    //   3468: aload #20
    //   3470: iload #22
    //   3472: iaload
    //   3473: iadd
    //   3474: istore #23
    //   3476: aload #21
    //   3478: iconst_0
    //   3479: iaload
    //   3480: iconst_2
    //   3481: iushr
    //   3482: aload #21
    //   3484: iconst_0
    //   3485: iaload
    //   3486: bipush #30
    //   3488: ishl
    //   3489: ior
    //   3490: aload #21
    //   3492: iconst_0
    //   3493: iaload
    //   3494: bipush #13
    //   3496: iushr
    //   3497: aload #21
    //   3499: iconst_0
    //   3500: iaload
    //   3501: bipush #19
    //   3503: ishl
    //   3504: ior
    //   3505: ixor
    //   3506: aload #21
    //   3508: iconst_0
    //   3509: iaload
    //   3510: bipush #22
    //   3512: iushr
    //   3513: aload #21
    //   3515: iconst_0
    //   3516: iaload
    //   3517: bipush #10
    //   3519: ishl
    //   3520: ior
    //   3521: ixor
    //   3522: aload #21
    //   3524: iconst_0
    //   3525: iaload
    //   3526: aload #21
    //   3528: iconst_1
    //   3529: iaload
    //   3530: iand
    //   3531: aload #21
    //   3533: iconst_2
    //   3534: iaload
    //   3535: aload #21
    //   3537: iconst_0
    //   3538: iaload
    //   3539: aload #21
    //   3541: iconst_1
    //   3542: iaload
    //   3543: ior
    //   3544: iand
    //   3545: ior
    //   3546: iadd
    //   3547: istore #24
    //   3549: aload #21
    //   3551: iconst_3
    //   3552: dup2
    //   3553: iaload
    //   3554: iload #23
    //   3556: iadd
    //   3557: iastore
    //   3558: aload #21
    //   3560: bipush #7
    //   3562: iload #23
    //   3564: iload #24
    //   3566: iadd
    //   3567: iastore
    //   3568: aload #21
    //   3570: bipush #7
    //   3572: iaload
    //   3573: istore #23
    //   3575: aload #21
    //   3577: bipush #7
    //   3579: aload #21
    //   3581: bipush #6
    //   3583: iaload
    //   3584: iastore
    //   3585: aload #21
    //   3587: bipush #6
    //   3589: aload #21
    //   3591: iconst_5
    //   3592: iaload
    //   3593: iastore
    //   3594: aload #21
    //   3596: iconst_5
    //   3597: aload #21
    //   3599: iconst_4
    //   3600: iaload
    //   3601: iastore
    //   3602: aload #21
    //   3604: iconst_4
    //   3605: aload #21
    //   3607: iconst_3
    //   3608: iaload
    //   3609: iastore
    //   3610: aload #21
    //   3612: iconst_3
    //   3613: aload #21
    //   3615: iconst_2
    //   3616: iaload
    //   3617: iastore
    //   3618: aload #21
    //   3620: iconst_2
    //   3621: aload #21
    //   3623: iconst_1
    //   3624: iaload
    //   3625: iastore
    //   3626: aload #21
    //   3628: iconst_1
    //   3629: aload #21
    //   3631: iconst_0
    //   3632: iaload
    //   3633: iastore
    //   3634: aload #21
    //   3636: iconst_0
    //   3637: iload #23
    //   3639: iastore
    //   3640: iinc #22, 1
    //   3643: iload_2
    //   3644: ifeq -> 3152
    //   3647: iconst_0
    //   3648: istore #22
    //   3650: iload #22
    //   3652: bipush #8
    //   3654: if_icmpge -> 3677
    //   3657: aload #8
    //   3659: iload #22
    //   3661: dup2
    //   3662: iaload
    //   3663: aload #21
    //   3665: iload #22
    //   3667: iaload
    //   3668: iadd
    //   3669: iastore
    //   3670: iinc #22, 1
    //   3673: iload_2
    //   3674: ifeq -> 3650
    //   3677: bipush #32
    //   3679: newarray byte
    //   3681: astore #4
    //   3683: sipush #-12971
    //   3686: aload #4
    //   3688: iconst_0
    //   3689: aload #8
    //   3691: iconst_0
    //   3692: iaload
    //   3693: bipush #24
    //   3695: iushr
    //   3696: i2b
    //   3697: bastore
    //   3698: sipush #-7958
    //   3701: aload #4
    //   3703: iconst_1
    //   3704: aload #8
    //   3706: iconst_0
    //   3707: iaload
    //   3708: bipush #16
    //   3710: iushr
    //   3711: i2b
    //   3712: bastore
    //   3713: aload #4
    //   3715: iconst_2
    //   3716: aload #8
    //   3718: iconst_0
    //   3719: iaload
    //   3720: bipush #8
    //   3722: iushr
    //   3723: i2b
    //   3724: bastore
    //   3725: aload #4
    //   3727: iconst_3
    //   3728: aload #8
    //   3730: iconst_0
    //   3731: iaload
    //   3732: i2b
    //   3733: bastore
    //   3734: aload #4
    //   3736: iconst_4
    //   3737: aload #8
    //   3739: iconst_1
    //   3740: iaload
    //   3741: bipush #24
    //   3743: iushr
    //   3744: i2b
    //   3745: bastore
    //   3746: aload #4
    //   3748: iconst_5
    //   3749: aload #8
    //   3751: iconst_1
    //   3752: iaload
    //   3753: bipush #16
    //   3755: iushr
    //   3756: i2b
    //   3757: bastore
    //   3758: aload #4
    //   3760: bipush #6
    //   3762: aload #8
    //   3764: iconst_1
    //   3765: iaload
    //   3766: bipush #8
    //   3768: iushr
    //   3769: i2b
    //   3770: bastore
    //   3771: aload #4
    //   3773: bipush #7
    //   3775: aload #8
    //   3777: iconst_1
    //   3778: iaload
    //   3779: i2b
    //   3780: bastore
    //   3781: aload #4
    //   3783: bipush #8
    //   3785: aload #8
    //   3787: iconst_2
    //   3788: iaload
    //   3789: bipush #24
    //   3791: iushr
    //   3792: i2b
    //   3793: bastore
    //   3794: aload #4
    //   3796: bipush #9
    //   3798: aload #8
    //   3800: iconst_2
    //   3801: iaload
    //   3802: bipush #16
    //   3804: iushr
    //   3805: i2b
    //   3806: bastore
    //   3807: aload #4
    //   3809: bipush #10
    //   3811: aload #8
    //   3813: iconst_2
    //   3814: iaload
    //   3815: bipush #8
    //   3817: iushr
    //   3818: i2b
    //   3819: bastore
    //   3820: aload #4
    //   3822: bipush #11
    //   3824: aload #8
    //   3826: iconst_2
    //   3827: iaload
    //   3828: i2b
    //   3829: bastore
    //   3830: aload #4
    //   3832: bipush #12
    //   3834: aload #8
    //   3836: iconst_3
    //   3837: iaload
    //   3838: bipush #24
    //   3840: iushr
    //   3841: i2b
    //   3842: bastore
    //   3843: aload #4
    //   3845: bipush #13
    //   3847: aload #8
    //   3849: iconst_3
    //   3850: iaload
    //   3851: bipush #16
    //   3853: iushr
    //   3854: i2b
    //   3855: bastore
    //   3856: aload #4
    //   3858: bipush #14
    //   3860: aload #8
    //   3862: iconst_3
    //   3863: iaload
    //   3864: bipush #8
    //   3866: iushr
    //   3867: i2b
    //   3868: bastore
    //   3869: aload #4
    //   3871: bipush #15
    //   3873: aload #8
    //   3875: iconst_3
    //   3876: iaload
    //   3877: i2b
    //   3878: bastore
    //   3879: aload #4
    //   3881: bipush #16
    //   3883: aload #8
    //   3885: iconst_4
    //   3886: iaload
    //   3887: bipush #24
    //   3889: iushr
    //   3890: i2b
    //   3891: bastore
    //   3892: aload #4
    //   3894: bipush #17
    //   3896: aload #8
    //   3898: iconst_4
    //   3899: iaload
    //   3900: bipush #16
    //   3902: iushr
    //   3903: i2b
    //   3904: bastore
    //   3905: aload #4
    //   3907: bipush #18
    //   3909: aload #8
    //   3911: iconst_4
    //   3912: iaload
    //   3913: bipush #8
    //   3915: iushr
    //   3916: i2b
    //   3917: bastore
    //   3918: aload #4
    //   3920: bipush #19
    //   3922: aload #8
    //   3924: iconst_4
    //   3925: iaload
    //   3926: i2b
    //   3927: bastore
    //   3928: aload #4
    //   3930: bipush #20
    //   3932: aload #8
    //   3934: iconst_5
    //   3935: iaload
    //   3936: bipush #24
    //   3938: iushr
    //   3939: i2b
    //   3940: bastore
    //   3941: aload #4
    //   3943: bipush #21
    //   3945: aload #8
    //   3947: iconst_5
    //   3948: iaload
    //   3949: bipush #16
    //   3951: iushr
    //   3952: i2b
    //   3953: bastore
    //   3954: aload #4
    //   3956: bipush #22
    //   3958: aload #8
    //   3960: iconst_5
    //   3961: iaload
    //   3962: bipush #8
    //   3964: iushr
    //   3965: i2b
    //   3966: bastore
    //   3967: aload #4
    //   3969: bipush #23
    //   3971: aload #8
    //   3973: iconst_5
    //   3974: iaload
    //   3975: i2b
    //   3976: bastore
    //   3977: aload #4
    //   3979: bipush #24
    //   3981: aload #8
    //   3983: bipush #6
    //   3985: iaload
    //   3986: bipush #24
    //   3988: iushr
    //   3989: i2b
    //   3990: bastore
    //   3991: aload #4
    //   3993: bipush #25
    //   3995: aload #8
    //   3997: bipush #6
    //   3999: iaload
    //   4000: bipush #16
    //   4002: iushr
    //   4003: i2b
    //   4004: bastore
    //   4005: aload #4
    //   4007: bipush #26
    //   4009: aload #8
    //   4011: bipush #6
    //   4013: iaload
    //   4014: bipush #8
    //   4016: iushr
    //   4017: i2b
    //   4018: bastore
    //   4019: aload #4
    //   4021: bipush #27
    //   4023: aload #8
    //   4025: bipush #6
    //   4027: iaload
    //   4028: i2b
    //   4029: bastore
    //   4030: aload #4
    //   4032: bipush #28
    //   4034: aload #8
    //   4036: bipush #7
    //   4038: iaload
    //   4039: bipush #24
    //   4041: iushr
    //   4042: i2b
    //   4043: bastore
    //   4044: aload #4
    //   4046: bipush #29
    //   4048: aload #8
    //   4050: bipush #7
    //   4052: iaload
    //   4053: bipush #16
    //   4055: iushr
    //   4056: i2b
    //   4057: bastore
    //   4058: aload #4
    //   4060: bipush #30
    //   4062: aload #8
    //   4064: bipush #7
    //   4066: iaload
    //   4067: bipush #8
    //   4069: iushr
    //   4070: i2b
    //   4071: bastore
    //   4072: aload #4
    //   4074: bipush #31
    //   4076: aload #8
    //   4078: bipush #7
    //   4080: iaload
    //   4081: i2b
    //   4082: bastore
    //   4083: new java/math/BigInteger
    //   4086: dup
    //   4087: aload #4
    //   4089: invokespecial <init> : ([B)V
    //   4092: invokevirtual abs : ()Ljava/math/BigInteger;
    //   4095: putstatic burp/Zeqr.ZM : Ljava/lang/Object;
    //   4098: invokestatic a : (II)Ljava/lang/String;
    //   4101: iconst_1
    //   4102: ldc burp/Zr8g
    //   4104: invokevirtual getClassLoader : ()Ljava/lang/ClassLoader;
    //   4107: invokestatic forName : (Ljava/lang/String;ZLjava/lang/ClassLoader;)Ljava/lang/Class;
    //   4110: invokevirtual getDeclaredFields : ()[Ljava/lang/reflect/Field;
    //   4113: astore_3
    //   4114: aload_3
    //   4115: arraylength
    //   4116: istore #4
    //   4118: iconst_0
    //   4119: istore #5
    //   4121: iload #5
    //   4123: iload #4
    //   4125: if_icmpge -> 4262
    //   4128: aload_3
    //   4129: iload #5
    //   4131: aaload
    //   4132: astore #6
    //   4134: aload #6
    //   4136: invokevirtual getModifiers : ()I
    //   4139: invokestatic isStatic : (I)Z
    //   4142: ifne -> 4152
    //   4145: goto -> 4255
    //   4148: invokestatic a : (Ljava/lang/Throwable;)Ljava/lang/Throwable;
    //   4151: athrow
    //   4152: aload #6
    //   4154: invokevirtual getType : ()Ljava/lang/Class;
    //   4157: astore #7
    //   4159: aload #7
    //   4161: ifnull -> 4242
    //   4164: aload #7
    //   4166: invokevirtual isPrimitive : ()Z
    //   4169: ifne -> 4242
    //   4172: goto -> 4179
    //   4175: invokestatic a : (Ljava/lang/Throwable;)Ljava/lang/Throwable;
    //   4178: athrow
    //   4179: aload #7
    //   4181: invokevirtual getPackage : ()Ljava/lang/Package;
    //   4184: ifnull -> 4242
    //   4187: goto -> 4194
    //   4190: invokestatic a : (Ljava/lang/Throwable;)Ljava/lang/Throwable;
    //   4193: athrow
    //   4194: aload #7
    //   4196: invokevirtual getPackage : ()Ljava/lang/Package;
    //   4199: invokevirtual getName : ()Ljava/lang/String;
    //   4202: ifnull -> 4242
    //   4205: goto -> 4212
    //   4208: invokestatic a : (Ljava/lang/Throwable;)Ljava/lang/Throwable;
    //   4211: athrow
    //   4212: aload #7
    //   4214: invokevirtual getPackage : ()Ljava/lang/Package;
    //   4217: invokevirtual getName : ()Ljava/lang/String;
    //   4220: sipush #-12961
    //   4223: sipush #26168
    //   4226: invokestatic a : (II)Ljava/lang/String;
    //   4229: invokevirtual startsWith : (Ljava/lang/String;)Z
    //   4232: ifne -> 4242
    //   4235: goto -> 4242
    //   4238: invokestatic a : (Ljava/lang/Throwable;)Ljava/lang/Throwable;
    //   4241: athrow
    //   4242: aload #6
    //   4244: iconst_1
    //   4245: invokevirtual setAccessible : (Z)V
    //   4248: aload #6
    //   4250: aconst_null
    //   4251: invokevirtual get : (Ljava/lang/Object;)Ljava/lang/Object;
    //   4254: pop
    //   4255: iinc #5, 1
    //   4258: iload_2
    //   4259: ifeq -> 4121
    //   4262: sipush #-12967
    //   4265: sipush #-12336
    //   4268: invokestatic a : (II)Ljava/lang/String;
    //   4271: invokestatic forName : (Ljava/lang/String;)Ljava/lang/Class;
    //   4274: invokevirtual getDeclaredMethods : ()[Ljava/lang/reflect/Method;
    //   4277: astore_3
    //   4278: aload_3
    //   4279: arraylength
    //   4280: istore #4
    //   4282: iconst_0
    //   4283: istore #5
    //   4285: iload #5
    //   4287: iload #4
    //   4289: if_icmpge -> 4400
    //   4292: aload_3
    //   4293: iload #5
    //   4295: aaload
    //   4296: astore #6
    //   4298: aload #6
    //   4300: invokevirtual getParameterTypes : ()[Ljava/lang/Class;
    //   4303: pop
    //   4304: aload #6
    //   4306: invokevirtual getModifiers : ()I
    //   4309: invokestatic isStatic : (I)Z
    //   4312: ifeq -> 4386
    //   4315: aload #6
    //   4317: invokevirtual getParameterTypes : ()[Ljava/lang/Class;
    //   4320: arraylength
    //   4321: iconst_2
    //   4322: if_icmpne -> 4386
    //   4325: goto -> 4332
    //   4328: invokestatic a : (Ljava/lang/Throwable;)Ljava/lang/Throwable;
    //   4331: athrow
    //   4332: aload #6
    //   4334: invokevirtual getReturnType : ()Ljava/lang/Class;
    //   4337: getstatic java/lang/Boolean.TYPE : Ljava/lang/Class;
    //   4340: if_acmpne -> 4386
    //   4343: goto -> 4350
    //   4346: invokestatic a : (Ljava/lang/Throwable;)Ljava/lang/Throwable;
    //   4349: athrow
    //   4350: aload #6
    //   4352: iconst_1
    //   4353: invokevirtual setAccessible : (Z)V
    //   4356: aload #6
    //   4358: aconst_null
    //   4359: iconst_2
    //   4360: anewarray java/lang/Object
    //   4363: dup
    //   4364: iconst_0
    //   4365: aload_0
    //   4366: aastore
    //   4367: dup
    //   4368: iconst_1
    //   4369: aload_1
    //   4370: aastore
    //   4371: invokevirtual invoke : (Ljava/lang/Object;[Ljava/lang/Object;)Ljava/lang/Object;
    //   4374: pop
    //   4375: iload_2
    //   4376: ifeq -> 4400
    //   4379: goto -> 4386
    //   4382: invokestatic a : (Ljava/lang/Throwable;)Ljava/lang/Throwable;
    //   4385: athrow
    //   4386: iinc #5, 1
    //   4389: iload_2
    //   4390: ifeq -> 4285
    //   4393: goto -> 4400
    //   4396: invokestatic a : (Ljava/lang/Throwable;)Ljava/lang/Throwable;
    //   4399: athrow
    //   4400: sipush #-12972
    //   4403: sipush #21930
    //   4406: invokestatic a : (II)Ljava/lang/String;
    //   4409: iconst_1
    //   4410: ldc burp/Zs5i
    //   4412: invokevirtual getClassLoader : ()Ljava/lang/ClassLoader;
    //   4415: invokestatic forName : (Ljava/lang/String;ZLjava/lang/ClassLoader;)Ljava/lang/Class;
    //   4418: invokevirtual getDeclaredFields : ()[Ljava/lang/reflect/Field;
    //   4421: astore_3
    //   4422: aload_3
    //   4423: arraylength
    //   4424: istore #4
    //   4426: iconst_0
    //   4427: istore #5
    //   4429: iload #5
    //   4431: iload #4
    //   4433: if_icmpge -> 4570
    //   4436: aload_3
    //   4437: iload #5
    //   4439: aaload
    //   4440: astore #6
    //   4442: aload #6
    //   4444: invokevirtual getModifiers : ()I
    //   4447: invokestatic isStatic : (I)Z
    //   4450: ifne -> 4460
    //   4453: goto -> 4563
    //   4456: invokestatic a : (Ljava/lang/Throwable;)Ljava/lang/Throwable;
    //   4459: athrow
    //   4460: aload #6
    //   4462: invokevirtual getType : ()Ljava/lang/Class;
    //   4465: astore #7
    //   4467: aload #7
    //   4469: ifnull -> 4550
    //   4472: aload #7
    //   4474: invokevirtual isPrimitive : ()Z
    //   4477: ifne -> 4550
    //   4480: goto -> 4487
    //   4483: invokestatic a : (Ljava/lang/Throwable;)Ljava/lang/Throwable;
    //   4486: athrow
    //   4487: aload #7
    //   4489: invokevirtual getPackage : ()Ljava/lang/Package;
    //   4492: ifnull -> 4550
    //   4495: goto -> 4502
    //   4498: invokestatic a : (Ljava/lang/Throwable;)Ljava/lang/Throwable;
    //   4501: athrow
    //   4502: aload #7
    //   4504: invokevirtual getPackage : ()Ljava/lang/Package;
    //   4507: invokevirtual getName : ()Ljava/lang/String;
    //   4510: ifnull -> 4550
    //   4513: goto -> 4520
    //   4516: invokestatic a : (Ljava/lang/Throwable;)Ljava/lang/Throwable;
    //   4519: athrow
    //   4520: aload #7
    //   4522: invokevirtual getPackage : ()Ljava/lang/Package;
    //   4525: invokevirtual getName : ()Ljava/lang/String;
    //   4528: sipush #-12964
    //   4531: sipush #-2250
    //   4534: invokestatic a : (II)Ljava/lang/String;
    //   4537: invokevirtual startsWith : (Ljava/lang/String;)Z
    //   4540: ifne -> 4550
    //   4543: goto -> 4550
    //   4546: invokestatic a : (Ljava/lang/Throwable;)Ljava/lang/Throwable;
    //   4549: athrow
    //   4550: aload #6
    //   4552: iconst_1
    //   4553: invokevirtual setAccessible : (Z)V
    //   4556: aload #6
    //   4558: aconst_null
    //   4559: invokevirtual get : (Ljava/lang/Object;)Ljava/lang/Object;
    //   4562: pop
    //   4563: iinc #5, 1
    //   4566: iload_2
    //   4567: ifeq -> 4429
    //   4570: sipush #-12963
    //   4573: sipush #15519
    //   4576: invokestatic a : (II)Ljava/lang/String;
    //   4579: invokestatic forName : (Ljava/lang/String;)Ljava/lang/Class;
    //   4582: invokevirtual getDeclaredMethods : ()[Ljava/lang/reflect/Method;
    //   4585: astore_3
    //   4586: aload_3
    //   4587: arraylength
    //   4588: istore #4
    //   4590: iconst_0
    //   4591: istore #5
    //   4593: iload #5
    //   4595: iload #4
    //   4597: if_icmpge -> 4729
    //   4600: aload_3
    //   4601: iload #5
    //   4603: aaload
    //   4604: astore #6
    //   4606: aload #6
    //   4608: invokevirtual getParameterTypes : ()[Ljava/lang/Class;
    //   4611: pop
    //   4612: aload #6
    //   4614: invokevirtual getModifiers : ()I
    //   4617: invokestatic isStatic : (I)Z
    //   4620: ifeq -> 4715
    //   4623: aload #6
    //   4625: invokevirtual getParameterTypes : ()[Ljava/lang/Class;
    //   4628: arraylength
    //   4629: iconst_2
    //   4630: if_icmpne -> 4715
    //   4633: goto -> 4640
    //   4636: invokestatic a : (Ljava/lang/Throwable;)Ljava/lang/Throwable;
    //   4639: athrow
    //   4640: aload #6
    //   4642: invokevirtual getReturnType : ()Ljava/lang/Class;
    //   4645: getstatic java/lang/Void.TYPE : Ljava/lang/Class;
    //   4648: invokevirtual equals : (Ljava/lang/Object;)Z
    //   4651: ifeq -> 4715
    //   4654: goto -> 4661
    //   4657: invokestatic a : (Ljava/lang/Throwable;)Ljava/lang/Throwable;
    //   4660: athrow
    //   4661: aload #6
    //   4663: iconst_1
    //   4664: invokevirtual setAccessible : (Z)V
    //   4667: aload #6
    //   4669: aconst_null
    //   4670: iconst_2
    //   4671: anewarray java/lang/Object
    //   4674: dup
    //   4675: iconst_0
    //   4676: aload_0
    //   4677: aastore
    //   4678: dup
    //   4679: iconst_1
    //   4680: aload_1
    //   4681: ifnonnull -> 4699
    //   4684: goto -> 4691
    //   4687: invokestatic a : (Ljava/lang/Throwable;)Ljava/lang/Throwable;
    //   4690: athrow
    //   4691: aload_1
    //   4692: goto -> 4706
    //   4695: invokestatic a : (Ljava/lang/Throwable;)Ljava/lang/Throwable;
    //   4698: athrow
    //   4699: aload_1
    //   4700: checkcast [B
    //   4703: invokevirtual clone : ()Ljava/lang/Object;
    //   4706: aastore
    //   4707: invokevirtual invoke : (Ljava/lang/Object;[Ljava/lang/Object;)Ljava/lang/Object;
    //   4710: pop
    //   4711: iload_2
    //   4712: ifeq -> 4729
    //   4715: iinc #5, 1
    //   4718: iload_2
    //   4719: ifeq -> 4593
    //   4722: goto -> 4729
    //   4725: invokestatic a : (Ljava/lang/Throwable;)Ljava/lang/Throwable;
    //   4728: athrow
    //   4729: iconst_0
    //   4730: istore_3
    //   4731: sipush #-12966
    //   4734: sipush #-25998
    //   4737: invokestatic a : (II)Ljava/lang/String;
    //   4740: iconst_1
    //   4741: ldc burp/Zgj5
    //   4743: invokevirtual getClassLoader : ()Ljava/lang/ClassLoader;
    //   4746: invokestatic forName : (Ljava/lang/String;ZLjava/lang/ClassLoader;)Ljava/lang/Class;
    //   4749: invokevirtual getDeclaredFields : ()[Ljava/lang/reflect/Field;
    //   4752: astore #4
    //   4754: aload #4
    //   4756: arraylength
    //   4757: istore #5
    //   4759: iconst_0
    //   4760: istore #6
    //   4762: iload #6
    //   4764: iload #5
    //   4766: if_icmpge -> 4904
    //   4769: aload #4
    //   4771: iload #6
    //   4773: aaload
    //   4774: astore #7
    //   4776: aload #7
    //   4778: invokevirtual getModifiers : ()I
    //   4781: invokestatic isStatic : (I)Z
    //   4784: ifne -> 4794
    //   4787: goto -> 4897
    //   4790: invokestatic a : (Ljava/lang/Throwable;)Ljava/lang/Throwable;
    //   4793: athrow
    //   4794: aload #7
    //   4796: invokevirtual getType : ()Ljava/lang/Class;
    //   4799: astore #8
    //   4801: aload #8
    //   4803: ifnull -> 4884
    //   4806: aload #8
    //   4808: invokevirtual isPrimitive : ()Z
    //   4811: ifne -> 4884
    //   4814: goto -> 4821
    //   4817: invokestatic a : (Ljava/lang/Throwable;)Ljava/lang/Throwable;
    //   4820: athrow
    //   4821: aload #8
    //   4823: invokevirtual getPackage : ()Ljava/lang/Package;
    //   4826: ifnull -> 4884
    //   4829: goto -> 4836
    //   4832: invokestatic a : (Ljava/lang/Throwable;)Ljava/lang/Throwable;
    //   4835: athrow
    //   4836: aload #8
    //   4838: invokevirtual getPackage : ()Ljava/lang/Package;
    //   4841: invokevirtual getName : ()Ljava/lang/String;
    //   4844: ifnull -> 4884
    //   4847: goto -> 4854
    //   4850: invokestatic a : (Ljava/lang/Throwable;)Ljava/lang/Throwable;
    //   4853: athrow
    //   4854: aload #8
    //   4856: invokevirtual getPackage : ()Ljava/lang/Package;
    //   4859: invokevirtual getName : ()Ljava/lang/String;
    //   4862: sipush #-12964
    //   4865: sipush #-2250
    //   4868: invokestatic a : (II)Ljava/lang/String;
    //   4871: invokevirtual startsWith : (Ljava/lang/String;)Z
    //   4874: ifne -> 4884
    //   4877: goto -> 4884
    //   4880: invokestatic a : (Ljava/lang/Throwable;)Ljava/lang/Throwable;
    //   4883: athrow
    //   4884: aload #7
    //   4886: iconst_1
    //   4887: invokevirtual setAccessible : (Z)V
    //   4890: aload #7
    //   4892: aconst_null
    //   4893: invokevirtual get : (Ljava/lang/Object;)Ljava/lang/Object;
    //   4896: pop
    //   4897: iinc #6, 1
    //   4900: iload_2
    //   4901: ifeq -> 4762
    //   4904: sipush #-12962
    //   4907: sipush #3801
    //   4910: invokestatic a : (II)Ljava/lang/String;
    //   4913: invokestatic forName : (Ljava/lang/String;)Ljava/lang/Class;
    //   4916: invokevirtual getDeclaredMethods : ()[Ljava/lang/reflect/Method;
    //   4919: astore #4
    //   4921: aload #4
    //   4923: arraylength
    //   4924: istore #5
    //   4926: iconst_0
    //   4927: istore #6
    //   4929: iload #6
    //   4931: iload #5
    //   4933: if_icmpge -> 5069
    //   4936: aload #4
    //   4938: iload #6
    //   4940: aaload
    //   4941: astore #7
    //   4943: aload #7
    //   4945: invokevirtual getParameterTypes : ()[Ljava/lang/Class;
    //   4948: pop
    //   4949: aload #7
    //   4951: invokevirtual getModifiers : ()I
    //   4954: invokestatic isStatic : (I)Z
    //   4957: ifeq -> 5055
    //   4960: aload #7
    //   4962: invokevirtual getParameterTypes : ()[Ljava/lang/Class;
    //   4965: arraylength
    //   4966: iconst_2
    //   4967: if_icmpne -> 5055
    //   4970: goto -> 4977
    //   4973: invokestatic a : (Ljava/lang/Throwable;)Ljava/lang/Throwable;
    //   4976: athrow
    //   4977: aload #7
    //   4979: invokevirtual getReturnType : ()Ljava/lang/Class;
    //   4982: getstatic java/lang/Boolean.TYPE : Ljava/lang/Class;
    //   4985: if_acmpne -> 5055
    //   4988: goto -> 4995
    //   4991: invokestatic a : (Ljava/lang/Throwable;)Ljava/lang/Throwable;
    //   4994: athrow
    //   4995: aload #7
    //   4997: iconst_1
    //   4998: invokevirtual setAccessible : (Z)V
    //   5001: aload #7
    //   5003: aconst_null
    //   5004: iconst_2
    //   5005: anewarray java/lang/Object
    //   5008: dup
    //   5009: iconst_0
    //   5010: aload_0
    //   5011: aastore
    //   5012: dup
    //   5013: iconst_1
    //   5014: aload_1
    //   5015: ifnonnull -> 5033
    //   5018: goto -> 5025
    //   5021: invokestatic a : (Ljava/lang/Throwable;)Ljava/lang/Throwable;
    //   5024: athrow
    //   5025: aload_1
    //   5026: goto -> 5040
    //   5029: invokestatic a : (Ljava/lang/Throwable;)Ljava/lang/Throwable;
    //   5032: athrow
    //   5033: aload_1
    //   5034: checkcast [B
    //   5037: invokevirtual clone : ()Ljava/lang/Object;
    //   5040: aastore
    //   5041: invokevirtual invoke : (Ljava/lang/Object;[Ljava/lang/Object;)Ljava/lang/Object;
    //   5044: checkcast java/lang/Boolean
    //   5047: invokevirtual booleanValue : ()Z
    //   5050: istore_3
    //   5051: iload_2
    //   5052: ifeq -> 5069
    //   5055: iinc #6, 1
    //   5058: iload_2
    //   5059: ifeq -> 4929
    //   5062: goto -> 5069
    //   5065: invokestatic a : (Ljava/lang/Throwable;)Ljava/lang/Throwable;
    //   5068: athrow
    //   5069: iload_3
    //   5070: ireturn
    //   5071: astore_3
    //   5072: new java/lang/Exception
    //   5075: dup
    //   5076: aload_3
    //   5077: invokevirtual getMessage : ()Ljava/lang/String;
    //   5080: invokespecial <init> : (Ljava/lang/String;)V
    //   5083: athrow
    // Exception table:
    //   from	to	target	type
    //   4	5070	5071	java/lang/Throwable
    //   820	854	857	java/lang/Throwable
    //   949	1027	1030	java/lang/Throwable
    //   956	1170	1173	java/lang/Throwable
    //   1547	1562	1562	java/lang/Throwable
    //   1589	1623	1626	java/lang/Throwable
    //   1633	1645	1648	java/lang/Throwable
    //   1731	1809	1812	java/lang/Throwable
    //   1738	1952	1955	java/lang/Throwable
    //   2352	2430	2433	java/lang/Throwable
    //   2359	2573	2576	java/lang/Throwable
    //   3020	3054	3057	java/lang/Throwable
    //   3061	3073	3076	java/lang/Throwable
    //   3159	3237	3240	java/lang/Throwable
    //   3166	3380	3383	java/lang/Throwable
    //   4134	4148	4148	java/lang/Throwable
    //   4159	4172	4175	java/lang/Throwable
    //   4164	4187	4190	java/lang/Throwable
    //   4179	4205	4208	java/lang/Throwable
    //   4194	4235	4238	java/lang/Throwable
    //   4298	4325	4328	java/lang/Throwable
    //   4315	4343	4346	java/lang/Throwable
    //   4332	4379	4382	java/lang/Throwable
    //   4350	4393	4396	java/lang/Throwable
    //   4442	4456	4456	java/lang/Throwable
    //   4467	4480	4483	java/lang/Throwable
    //   4472	4495	4498	java/lang/Throwable
    //   4487	4513	4516	java/lang/Throwable
    //   4502	4543	4546	java/lang/Throwable
    //   4606	4633	4636	java/lang/Throwable
    //   4623	4654	4657	java/lang/Throwable
    //   4640	4684	4687	java/lang/Throwable
    //   4661	4695	4695	java/lang/Throwable
    //   4706	4722	4725	java/lang/Throwable
    //   4776	4790	4790	java/lang/Throwable
    //   4801	4814	4817	java/lang/Throwable
    //   4806	4829	4832	java/lang/Throwable
    //   4821	4847	4850	java/lang/Throwable
    //   4836	4877	4880	java/lang/Throwable
    //   4943	4970	4973	java/lang/Throwable
    //   4960	4988	4991	java/lang/Throwable
    //   4977	5018	5021	java/lang/Throwable
    //   4995	5029	5029	java/lang/Throwable
    //   5051	5062	5065	java/lang/Throwable
  }
  
  static {
    // Byte code:
    //   0: bipush #14
    //   2: anewarray java/lang/String
    //   5: astore #5
    //   7: iconst_0
    //   8: istore_3
    //   9: ldc ' S\\tV#@`\\tw\L0H_[r.op UcK*rt!DjWrn(PZNkH5\\t;-\\t2U@\\tiT>  G_[Ri&C b\\tal\\tC\\t*8E\\t5xy-'
    //   11: dup
    //   12: astore_2
    //   13: invokevirtual length : ()I
    //   16: istore #4
    //   18: iconst_4
    //   19: istore_1
    //   20: iconst_m1
    //   21: istore_0
    //   22: bipush #92
    //   24: iinc #0, 1
    //   27: aload_2
    //   28: iload_0
    //   29: dup
    //   30: iload_1
    //   31: iadd
    //   32: invokevirtual substring : (II)Ljava/lang/String;
    //   35: iconst_m1
    //   36: goto -> 142
    //   39: aload #5
    //   41: swap
    //   42: iload_3
    //   43: iinc #3, 1
    //   46: swap
    //   47: aastore
    //   48: iload_0
    //   49: iload_1
    //   50: iadd
    //   51: dup
    //   52: istore_0
    //   53: iload #4
    //   55: if_icmpge -> 67
    //   58: aload_2
    //   59: iload_0
    //   60: invokevirtual charAt : (I)C
    //   63: istore_1
    //   64: goto -> 22
    //   67: ldc 'QZRJ,:X\\tS-a\\tBgjgP'
    //   69: dup
    //   70: astore_2
    //   71: invokevirtual length : ()I
    //   74: istore #4
    //   76: bipush #32
    //   78: istore_1
    //   79: iconst_m1
    //   80: istore_0
    //   81: bipush #43
    //   83: iinc #0, 1
    //   86: aload_2
    //   87: iload_0
    //   88: dup
    //   89: iload_1
    //   90: iadd
    //   91: invokevirtual substring : (II)Ljava/lang/String;
    //   94: iconst_0
    //   95: goto -> 142
    //   98: aload #5
    //   100: swap
    //   101: iload_3
    //   102: iinc #3, 1
    //   105: swap
    //   106: aastore
    //   107: iload_0
    //   108: iload_1
    //   109: iadd
    //   110: dup
    //   111: istore_0
    //   112: iload #4
    //   114: if_icmpge -> 126
    //   117: aload_2
    //   118: iload_0
    //   119: invokevirtual charAt : (I)C
    //   122: istore_1
    //   123: goto -> 81
    //   126: aload #5
    //   128: putstatic burp/Zvi.a : [Ljava/lang/String;
    //   131: bipush #14
    //   133: anewarray java/lang/String
    //   136: putstatic burp/Zvi.b : [Ljava/lang/String;
    //   139: goto -> 300
    //   142: dup_x2
    //   143: pop
    //   144: invokevirtual toCharArray : ()[C
    //   147: dup_x1
    //   148: arraylength
    //   149: dup_x2
    //   150: pop
    //   151: iconst_0
    //   152: istore #6
    //   154: dup2_x1
    //   155: pop2
    //   156: dup_x2
    //   157: iconst_1
    //   158: if_icmpgt -> 260
    //   161: dup2
    //   162: swap
    //   163: iload #6
    //   165: dup2_x1
    //   166: caload
    //   167: swap
    //   168: iload #6
    //   170: bipush #7
    //   172: irem
    //   173: tableswitch default -> 242, 0 -> 212, 1 -> 217, 2 -> 222, 3 -> 227, 4 -> 232, 5 -> 237
    //   212: bipush #122
    //   214: goto -> 244
    //   217: bipush #77
    //   219: goto -> 244
    //   222: bipush #27
    //   224: goto -> 244
    //   227: bipush #68
    //   229: goto -> 244
    //   232: bipush #68
    //   234: goto -> 244
    //   237: bipush #38
    //   239: goto -> 244
    //   242: bipush #100
    //   244: ixor
    //   245: ixor
    //   246: i2c
    //   247: castore
    //   248: iinc #6, 1
    //   251: dup
    //   252: ifne -> 260
    //   255: dup2
    //   256: dup_x1
    //   257: goto -> 165
    //   260: dup2_x1
    //   261: pop2
    //   262: dup_x2
    //   263: iload #6
    //   265: if_icmpgt -> 161
    //   268: pop
    //   269: new java/lang/String
    //   272: dup_x1
    //   273: swap
    //   274: invokespecial <init> : ([C)V
    //   277: invokevirtual intern : ()Ljava/lang/String;
    //   280: swap
    //   281: pop
    //   282: swap
    //   283: tableswitch default -> 39, 0 -> 98
    //   300: sipush #-12973
    //   303: sipush #-6592
    //   306: invokestatic a : (II)Ljava/lang/String;
    //   309: putstatic burp/Zvi.ZR : Ljava/lang/String;
    //   312: new java/math/BigInteger
    //   315: dup
    //   316: iconst_1
    //   317: bipush #32
    //   319: newarray byte
    //   321: dup
    //   322: iconst_0
    //   323: bipush #62
    //   325: bastore
    //   326: dup
    //   327: iconst_1
    //   328: bipush #105
    //   330: bastore
    //   331: dup
    //   332: iconst_2
    //   333: bipush #-31
    //   335: bastore
    //   336: dup
    //   337: iconst_3
    //   338: bipush #-94
    //   340: bastore
    //   341: dup
    //   342: iconst_4
    //   343: bipush #25
    //   345: bastore
    //   346: dup
    //   347: iconst_5
    //   348: bipush #-122
    //   350: bastore
    //   351: dup
    //   352: bipush #6
    //   354: bipush #-125
    //   356: bastore
    //   357: dup
    //   358: bipush #7
    //   360: bipush #-38
    //   362: bastore
    //   363: dup
    //   364: bipush #8
    //   366: bipush #96
    //   368: bastore
    //   369: dup
    //   370: bipush #9
    //   372: bipush #44
    //   374: bastore
    //   375: dup
    //   376: bipush #10
    //   378: bipush #-80
    //   380: bastore
    //   381: dup
    //   382: bipush #11
    //   384: bipush #127
    //   386: bastore
    //   387: dup
    //   388: bipush #12
    //   390: bipush #-38
    //   392: bastore
    //   393: dup
    //   394: bipush #13
    //   396: bipush #-78
    //   398: bastore
    //   399: dup
    //   400: bipush #14
    //   402: bipush #87
    //   404: bastore
    //   405: dup
    //   406: bipush #15
    //   408: iconst_2
    //   409: bastore
    //   410: dup
    //   411: bipush #16
    //   413: bipush #-70
    //   415: bastore
    //   416: dup
    //   417: bipush #17
    //   419: bipush #-52
    //   421: bastore
    //   422: dup
    //   423: bipush #18
    //   425: bipush #-121
    //   427: bastore
    //   428: dup
    //   429: bipush #19
    //   431: bipush #67
    //   433: bastore
    //   434: dup
    //   435: bipush #20
    //   437: bipush #118
    //   439: bastore
    //   440: dup
    //   441: bipush #21
    //   443: bipush #28
    //   445: bastore
    //   446: dup
    //   447: bipush #22
    //   449: bipush #-67
    //   451: bastore
    //   452: dup
    //   453: bipush #23
    //   455: bipush #-91
    //   457: bastore
    //   458: dup
    //   459: bipush #24
    //   461: bipush #-49
    //   463: bastore
    //   464: dup
    //   465: bipush #25
    //   467: bipush #43
    //   469: bastore
    //   470: dup
    //   471: bipush #26
    //   473: bipush #40
    //   475: bastore
    //   476: dup
    //   477: bipush #27
    //   479: bipush #86
    //   481: bastore
    //   482: dup
    //   483: bipush #28
    //   485: bipush #-97
    //   487: bastore
    //   488: dup
    //   489: bipush #29
    //   491: bipush #69
    //   493: bastore
    //   494: dup
    //   495: bipush #30
    //   497: bipush #79
    //   499: bastore
    //   500: dup
    //   501: bipush #31
    //   503: bipush #-7
    //   505: bastore
    //   506: invokespecial <init> : (I[B)V
    //   509: putstatic burp/Zvi.Zs : Ljava/lang/Object;
    //   512: return
  }
  
  private static Throwable a(Throwable paramThrowable) {
    return paramThrowable;
  }
  
  private static String a(int paramInt1, int paramInt2) {
    int i = (paramInt1 ^ 0xFFFFCD5F) & 0xFFFF;
    if (b[i] == null) {
      char[] arrayOfChar = a[i].toCharArray();
      switch (arrayOfChar[0] & 0xFF) {
        case 0:
        
        case 1:
        
        case 2:
        
        case 3:
        
        case 4:
        
        case 5:
        
        case 6:
        
        case 7:
        
        case 8:
        
        case 9:
        
        case 10:
        
        case 11:
        
        case 12:
        
        case 13:
        
        case 14:
        
        case 15:
        
        case 16:
        
        case 17:
        
        case 18:
        
        case 19:
        
        case 20:
        
        case 21:
        
        case 22:
        
        case 23:
        
        case 24:
        
        case 25:
        
        case 26:
        
        case 27:
        
        case 28:
        
        case 29:
        
        case 30:
        
        case 31:
        
        case 32:
        
        case 33:
        
        case 34:
        
        case 35:
        
        case 36:
        
        case 37:
        
        case 38:
        
        case 39:
        
        case 40:
        
        case 41:
        
        case 42:
        
        case 43:
        
        case 44:
        
        case 45:
        
        case 46:
        
        case 47:
        
        case 48:
        
        case 49:
        
        case 50:
        
        case 51:
        
        case 52:
        
        case 53:
        
        case 54:
        
        case 55:
        
        case 56:
        
        case 57:
        
        case 58:
        
        case 59:
        
        case 60:
        
        case 61:
        
        case 62:
        
        case 63:
        
        case 64:
        
        case 65:
        
        case 66:
        
        case 67:
        
        case 68:
        
        case 69:
        
        case 70:
        
        case 71:
        
        case 72:
        
        case 73:
        
        case 74:
        
        case 75:
        
        case 76:
        
        case 77:
        
        case 78:
        
        case 79:
        
        case 80:
        
        case 81:
        
        case 82:
        
        case 83:
        
        case 84:
        
        case 85:
        
        case 86:
        
        case 87:
        
        case 88:
        
        case 89:
        
        case 90:
        
        case 91:
        
        case 92:
        
        case 93:
        
        case 94:
        
        case 95:
        
        case 96:
        
        case 97:
        
        case 98:
        
        case 99:
        
        case 100:
        
        case 101:
        
        case 102:
        
        case 103:
        
        case 104:
        
        case 105:
        
        case 106:
        
        case 107:
        
        case 108:
        
        case 109:
        
        case 110:
        
        case 111:
        
        case 112:
        
        case 113:
        
        case 114:
        
        case 115:
        
        case 116:
        
        case 117:
        
        case 118:
        
        case 119:
        
        case 120:
        
        case 121:
        
        case 122:
        
        case 123:
        
        case 124:
        
        case 125:
        
        case 126:
        
        case 127:
        
        case 128:
        
        case 129:
        
        case 130:
        
        case 131:
        
        case 132:
        
        case 133:
        
        case 134:
        
        case 135:
        
        case 136:
        
        case 137:
        
        case 138:
        
        case 139:
        
        case 140:
        
        case 141:
        
        case 142:
        
        case 143:
        
        case 144:
        
        case 145:
        
        case 146:
        
        case 147:
        
        case 148:
        
        case 149:
        
        case 150:
        
        case 151:
        
        case 152:
        
        case 153:
        
        case 154:
        
        case 155:
        
        case 156:
        
        case 157:
        
        case 158:
        
        case 159:
        
        case 160:
        
        case 161:
        
        case 162:
        
        case 163:
        
        case 164:
        
        case 165:
        
        case 166:
        
        case 167:
        
        case 168:
        
        case 169:
        
        case 170:
        
        case 171:
        
        case 172:
        
        case 173:
        
        case 174:
        
        case 175:
        
        case 176:
        
        case 177:
        
        case 178:
        
        case 179:
        
        case 180:
        
        case 181:
        
        case 182:
        
        case 183:
        
        case 184:
        
        case 185:
        
        case 186:
        
        case 187:
        
        case 188:
        
        case 189:
        
        case 190:
        
        case 191:
        
        case 192:
        
        case 193:
        
        case 194:
        
        case 195:
        
        case 196:
        
        case 197:
        
        case 198:
        
        case 199:
        
        case 200:
        
        case 201:
        
        case 202:
        
        case 203:
        
        case 204:
        
        case 205:
        
        case 206:
        
        case 207:
        
        case 208:
        
        case 209:
        
        case 210:
        
        case 211:
        
        case 212:
        
        case 213:
        
        case 214:
        
        case 215:
        
        case 216:
        
        case 217:
        
        case 218:
        
        case 219:
        
        case 220:
        
        case 221:
        
        case 222:
        
        case 223:
        
        case 224:
        
        case 225:
        
        case 226:
        
        case 227:
        
        case 228:
        
        case 229:
        
        case 230:
        
        case 231:
        
        case 232:
        
        case 233:
        
        case 234:
        
        case 235:
        
        case 236:
        
        case 237:
        
        case 238:
        
        case 239:
        
        case 240:
        
        case 241:
        
        case 242:
        
        case 243:
        
        case 244:
        
        case 245:
        
        case 246:
        
        case 247:
        
        case 248:
        
        case 249:
        
        case 250:
        
        case 251:
        
        case 252:
        
        case 253:
        
        case 254:
        
        default:
          break;
      } 
      byte b1 = 31;
      int j = (paramInt2 & 0xFF) - b1;
      if (j < 0)
        j += 256; 
      int k = ((paramInt2 & 0xFFFF) >>> 8) - b1;
      if (k < 0)
        k += 256; 
      for (byte b2 = 0; b2 < arrayOfChar.length; b2++) {
        int m = b2 % 2;
        if (m == 0) {
          arrayOfChar[b2] = (char)(arrayOfChar[b2] ^ j);
          j = ((j >>> 3 | j << 5) ^ arrayOfChar[b2]) & 0xFF;
        } else {
          arrayOfChar[b2] = (char)(arrayOfChar[b2] ^ k);
          k = ((k >>> 3 | k << 5) ^ arrayOfChar[b2]) & 0xFF;
        } 
      } 
      b[i] = (new String(arrayOfChar)).intern();
    } 
    return b[i];
  }
}


/* Location:              C:\Program Files\BurpSuitePro\burpsuite_pro.jar!\burp\Zvi.class
 * Java compiler version: 21 (65.0)
 * JD-Core Version:       1.1.3
 */