package burp;

import java.math.BigInteger;

class Zx54 extends ClassLoader {
  static Object Zn;
  
  static String Zs;
  
  private static final String[] a;
  
  private static final String[] b;
  
  static void Zf(Object paramObject) {
    Zl_k.Zw = a(6533, 15473);
    Zl_k.ZH = new BigInteger(a(6530, 7169));
    boolean bool = Zt2e.ZK();
    try {
      try {
        if (Zkfz.Zs.charAt(Math.abs(((BigInteger)Zlv6.ZN).intValue() % 32)) > Zd1.ZN.charAt(Math.abs(((BigInteger)Zxzj.ZO).intValue() % 32))) {
          try {
            Zzk9.Zo(Class.forName(a(6531, 7123)));
            if (bool)
              Ztdx.ZG(Class.forName(a(6538, -14291))); 
          } catch (Throwable throwable) {
            throw a(null);
          } 
          return;
        } 
      } catch (Throwable throwable) {
        throw a(null);
      } 
      Ztdx.ZG(Class.forName(a(6538, -14291)));
    } catch (Throwable throwable) {}
  }
  
  static void Z_(Object[] paramArrayOfObject, Object paramObject) throws Throwable {}
  
  static boolean Za(Object[] paramArrayOfObject, Object paramObject) throws Throwable {
    // Byte code:
    //   0: invokestatic ZK : ()Z
    //   3: istore_2
    //   4: ldc2_w 8682522807148012
    //   7: invokestatic currentTimeMillis : ()J
    //   10: lxor
    //   11: lstore #4
    //   13: lload #4
    //   15: ldc2_w 25214903917
    //   18: lmul
    //   19: ldc2_w 11
    //   22: ladd
    //   23: ldc2_w 281474976710655
    //   26: land
    //   27: lstore #4
    //   29: lload #4
    //   31: bipush #32
    //   33: lshl
    //   34: lstore #6
    //   36: lload #4
    //   38: ldc2_w 25214903917
    //   41: lmul
    //   42: ldc2_w 11
    //   45: ladd
    //   46: ldc2_w 281474976710655
    //   49: land
    //   50: lstore #4
    //   52: lload #6
    //   54: lload #4
    //   56: ladd
    //   57: lstore #6
    //   59: bipush #16
    //   61: newarray byte
    //   63: dup
    //   64: iconst_0
    //   65: bipush #48
    //   67: bastore
    //   68: dup
    //   69: iconst_1
    //   70: bipush #49
    //   72: bastore
    //   73: dup
    //   74: iconst_2
    //   75: bipush #50
    //   77: bastore
    //   78: dup
    //   79: iconst_3
    //   80: bipush #51
    //   82: bastore
    //   83: dup
    //   84: iconst_4
    //   85: bipush #52
    //   87: bastore
    //   88: dup
    //   89: iconst_5
    //   90: bipush #53
    //   92: bastore
    //   93: dup
    //   94: bipush #6
    //   96: bipush #54
    //   98: bastore
    //   99: dup
    //   100: bipush #7
    //   102: bipush #55
    //   104: bastore
    //   105: dup
    //   106: bipush #8
    //   108: bipush #56
    //   110: bastore
    //   111: dup
    //   112: bipush #9
    //   114: bipush #57
    //   116: bastore
    //   117: dup
    //   118: bipush #10
    //   120: bipush #97
    //   122: bastore
    //   123: dup
    //   124: bipush #11
    //   126: bipush #98
    //   128: bastore
    //   129: dup
    //   130: bipush #12
    //   132: bipush #99
    //   134: bastore
    //   135: dup
    //   136: bipush #13
    //   138: bipush #100
    //   140: bastore
    //   141: dup
    //   142: bipush #14
    //   144: bipush #101
    //   146: bastore
    //   147: dup
    //   148: bipush #15
    //   150: bipush #102
    //   152: bastore
    //   153: astore #8
    //   155: bipush #64
    //   157: newarray byte
    //   159: astore #9
    //   161: bipush #64
    //   163: istore #10
    //   165: bipush #16
    //   167: istore #11
    //   169: iload #11
    //   171: iconst_1
    //   172: isub
    //   173: i2l
    //   174: lstore #12
    //   176: aload #9
    //   178: iinc #10, -1
    //   181: iload #10
    //   183: aload #8
    //   185: lload #6
    //   187: lload #12
    //   189: land
    //   190: l2i
    //   191: baload
    //   192: bastore
    //   193: lload #6
    //   195: iconst_4
    //   196: lushr
    //   197: lstore #6
    //   199: lload #6
    //   201: lconst_0
    //   202: lcmp
    //   203: ifne -> 176
    //   206: bipush #64
    //   208: iload #10
    //   210: isub
    //   211: newarray byte
    //   213: astore_3
    //   214: iconst_0
    //   215: istore #14
    //   217: iload #14
    //   219: aload_3
    //   220: arraylength
    //   221: if_icmpge -> 243
    //   224: aload_3
    //   225: iload #14
    //   227: aload #9
    //   229: iload #10
    //   231: iload #14
    //   233: iadd
    //   234: baload
    //   235: bastore
    //   236: iinc #14, 1
    //   239: iload_2
    //   240: ifeq -> 217
    //   243: aload_3
    //   244: arraylength
    //   245: bipush #10
    //   247: if_icmplt -> 13
    //   250: new java/lang/StringBuilder
    //   253: dup
    //   254: invokespecial <init> : ()V
    //   257: astore_3
    //   258: iconst_0
    //   259: istore #4
    //   261: iload #4
    //   263: bipush #32
    //   265: if_icmpge -> 1599
    //   268: iload #4
    //   270: tableswitch default -> 1592, 0 -> 412, 1 -> 449, 2 -> 486, 3 -> 523, 4 -> 560, 5 -> 597, 6 -> 634, 7 -> 671, 8 -> 708, 9 -> 745, 10 -> 782, 11 -> 819, 12 -> 856, 13 -> 893, 14 -> 930, 15 -> 967, 16 -> 1004, 17 -> 1041, 18 -> 1078, 19 -> 1115, 20 -> 1152, 21 -> 1189, 22 -> 1226, 23 -> 1263, 24 -> 1300, 25 -> 1337, 26 -> 1374, 27 -> 1411, 28 -> 1448, 29 -> 1485, 30 -> 1522, 31 -> 1559
    //   412: aload_3
    //   413: getstatic burp/Zzk9.Zb : Ljava/lang/String;
    //   416: getstatic burp/Ze3d.Ze : Ljava/lang/Object;
    //   419: checkcast java/math/BigInteger
    //   422: invokevirtual intValue : ()I
    //   425: bipush #32
    //   427: irem
    //   428: invokestatic abs : (I)I
    //   431: invokevirtual charAt : (I)C
    //   434: invokevirtual append : (C)Ljava/lang/StringBuilder;
    //   437: pop
    //   438: iload_2
    //   439: ifeq -> 1592
    //   442: goto -> 449
    //   445: invokestatic a : (Ljava/lang/Throwable;)Ljava/lang/Throwable;
    //   448: athrow
    //   449: aload_3
    //   450: getstatic burp/Zm__.Zf : Ljava/lang/String;
    //   453: getstatic burp/Zzai.Z_ : Ljava/lang/Object;
    //   456: checkcast java/math/BigInteger
    //   459: invokevirtual intValue : ()I
    //   462: bipush #32
    //   464: irem
    //   465: invokestatic abs : (I)I
    //   468: invokevirtual charAt : (I)C
    //   471: invokevirtual append : (C)Ljava/lang/StringBuilder;
    //   474: pop
    //   475: iload_2
    //   476: ifeq -> 1592
    //   479: goto -> 486
    //   482: invokestatic a : (Ljava/lang/Throwable;)Ljava/lang/Throwable;
    //   485: athrow
    //   486: aload_3
    //   487: getstatic burp/Zz1k.ZC : Ljava/lang/String;
    //   490: getstatic burp/Zgw0.ZM : Ljava/lang/Object;
    //   493: checkcast java/math/BigInteger
    //   496: invokevirtual intValue : ()I
    //   499: bipush #32
    //   501: irem
    //   502: invokestatic abs : (I)I
    //   505: invokevirtual charAt : (I)C
    //   508: invokevirtual append : (C)Ljava/lang/StringBuilder;
    //   511: pop
    //   512: iload_2
    //   513: ifeq -> 1592
    //   516: goto -> 523
    //   519: invokestatic a : (Ljava/lang/Throwable;)Ljava/lang/Throwable;
    //   522: athrow
    //   523: aload_3
    //   524: getstatic burp/Ztuj.Zk : Ljava/lang/String;
    //   527: getstatic burp/Zr3q.Zn : Ljava/lang/Object;
    //   530: checkcast java/math/BigInteger
    //   533: invokevirtual intValue : ()I
    //   536: bipush #32
    //   538: irem
    //   539: invokestatic abs : (I)I
    //   542: invokevirtual charAt : (I)C
    //   545: invokevirtual append : (C)Ljava/lang/StringBuilder;
    //   548: pop
    //   549: iload_2
    //   550: ifeq -> 1592
    //   553: goto -> 560
    //   556: invokestatic a : (Ljava/lang/Throwable;)Ljava/lang/Throwable;
    //   559: athrow
    //   560: aload_3
    //   561: getstatic burp/Zr0u.Z_ : Ljava/lang/String;
    //   564: getstatic burp/Zsxm.Zv : Ljava/lang/Object;
    //   567: checkcast java/math/BigInteger
    //   570: invokevirtual intValue : ()I
    //   573: bipush #32
    //   575: irem
    //   576: invokestatic abs : (I)I
    //   579: invokevirtual charAt : (I)C
    //   582: invokevirtual append : (C)Ljava/lang/StringBuilder;
    //   585: pop
    //   586: iload_2
    //   587: ifeq -> 1592
    //   590: goto -> 597
    //   593: invokestatic a : (Ljava/lang/Throwable;)Ljava/lang/Throwable;
    //   596: athrow
    //   597: aload_3
    //   598: getstatic burp/Zb3z.Zi : Ljava/lang/String;
    //   601: getstatic burp/Zsby.ZZ : Ljava/lang/Object;
    //   604: checkcast java/math/BigInteger
    //   607: invokevirtual intValue : ()I
    //   610: bipush #32
    //   612: irem
    //   613: invokestatic abs : (I)I
    //   616: invokevirtual charAt : (I)C
    //   619: invokevirtual append : (C)Ljava/lang/StringBuilder;
    //   622: pop
    //   623: iload_2
    //   624: ifeq -> 1592
    //   627: goto -> 634
    //   630: invokestatic a : (Ljava/lang/Throwable;)Ljava/lang/Throwable;
    //   633: athrow
    //   634: aload_3
    //   635: getstatic burp/Zt3l.Zi : Ljava/lang/String;
    //   638: getstatic burp/Zgss.Zl : Ljava/lang/Object;
    //   641: checkcast java/math/BigInteger
    //   644: invokevirtual intValue : ()I
    //   647: bipush #32
    //   649: irem
    //   650: invokestatic abs : (I)I
    //   653: invokevirtual charAt : (I)C
    //   656: invokevirtual append : (C)Ljava/lang/StringBuilder;
    //   659: pop
    //   660: iload_2
    //   661: ifeq -> 1592
    //   664: goto -> 671
    //   667: invokestatic a : (Ljava/lang/Throwable;)Ljava/lang/Throwable;
    //   670: athrow
    //   671: aload_3
    //   672: getstatic burp/Zrbp.Ze : Ljava/lang/String;
    //   675: getstatic burp/Zkyc.ZD : Ljava/lang/Object;
    //   678: checkcast java/math/BigInteger
    //   681: invokevirtual intValue : ()I
    //   684: bipush #32
    //   686: irem
    //   687: invokestatic abs : (I)I
    //   690: invokevirtual charAt : (I)C
    //   693: invokevirtual append : (C)Ljava/lang/StringBuilder;
    //   696: pop
    //   697: iload_2
    //   698: ifeq -> 1592
    //   701: goto -> 708
    //   704: invokestatic a : (Ljava/lang/Throwable;)Ljava/lang/Throwable;
    //   707: athrow
    //   708: aload_3
    //   709: getstatic burp/Zl2q.ZI : Ljava/lang/String;
    //   712: getstatic burp/Zeh9.ZY : Ljava/lang/Object;
    //   715: checkcast java/math/BigInteger
    //   718: invokevirtual intValue : ()I
    //   721: bipush #32
    //   723: irem
    //   724: invokestatic abs : (I)I
    //   727: invokevirtual charAt : (I)C
    //   730: invokevirtual append : (C)Ljava/lang/StringBuilder;
    //   733: pop
    //   734: iload_2
    //   735: ifeq -> 1592
    //   738: goto -> 745
    //   741: invokestatic a : (Ljava/lang/Throwable;)Ljava/lang/Throwable;
    //   744: athrow
    //   745: aload_3
    //   746: getstatic burp/Zl2g.ZI : Ljava/lang/String;
    //   749: getstatic burp/Zer.Zk : Ljava/lang/Object;
    //   752: checkcast java/math/BigInteger
    //   755: invokevirtual intValue : ()I
    //   758: bipush #32
    //   760: irem
    //   761: invokestatic abs : (I)I
    //   764: invokevirtual charAt : (I)C
    //   767: invokevirtual append : (C)Ljava/lang/StringBuilder;
    //   770: pop
    //   771: iload_2
    //   772: ifeq -> 1592
    //   775: goto -> 782
    //   778: invokestatic a : (Ljava/lang/Throwable;)Ljava/lang/Throwable;
    //   781: athrow
    //   782: aload_3
    //   783: getstatic burp/Zrdy.ZO : Ljava/lang/String;
    //   786: getstatic burp/Zein.Zb : Ljava/lang/Object;
    //   789: checkcast java/math/BigInteger
    //   792: invokevirtual intValue : ()I
    //   795: bipush #32
    //   797: irem
    //   798: invokestatic abs : (I)I
    //   801: invokevirtual charAt : (I)C
    //   804: invokevirtual append : (C)Ljava/lang/StringBuilder;
    //   807: pop
    //   808: iload_2
    //   809: ifeq -> 1592
    //   812: goto -> 819
    //   815: invokestatic a : (Ljava/lang/Throwable;)Ljava/lang/Throwable;
    //   818: athrow
    //   819: aload_3
    //   820: getstatic burp/Zsm3.Zl : Ljava/lang/String;
    //   823: getstatic burp/Zl88.ZK : Ljava/lang/Object;
    //   826: checkcast java/math/BigInteger
    //   829: invokevirtual intValue : ()I
    //   832: bipush #32
    //   834: irem
    //   835: invokestatic abs : (I)I
    //   838: invokevirtual charAt : (I)C
    //   841: invokevirtual append : (C)Ljava/lang/StringBuilder;
    //   844: pop
    //   845: iload_2
    //   846: ifeq -> 1592
    //   849: goto -> 856
    //   852: invokestatic a : (Ljava/lang/Throwable;)Ljava/lang/Throwable;
    //   855: athrow
    //   856: aload_3
    //   857: getstatic burp/Zb3z.Zi : Ljava/lang/String;
    //   860: getstatic burp/Zl_u.ZR : Ljava/lang/Object;
    //   863: checkcast java/math/BigInteger
    //   866: invokevirtual intValue : ()I
    //   869: bipush #32
    //   871: irem
    //   872: invokestatic abs : (I)I
    //   875: invokevirtual charAt : (I)C
    //   878: invokevirtual append : (C)Ljava/lang/StringBuilder;
    //   881: pop
    //   882: iload_2
    //   883: ifeq -> 1592
    //   886: goto -> 893
    //   889: invokestatic a : (Ljava/lang/Throwable;)Ljava/lang/Throwable;
    //   892: athrow
    //   893: aload_3
    //   894: getstatic burp/Zl88.Zd : Ljava/lang/String;
    //   897: getstatic burp/Zmj4.Zm : Ljava/lang/Object;
    //   900: checkcast java/math/BigInteger
    //   903: invokevirtual intValue : ()I
    //   906: bipush #32
    //   908: irem
    //   909: invokestatic abs : (I)I
    //   912: invokevirtual charAt : (I)C
    //   915: invokevirtual append : (C)Ljava/lang/StringBuilder;
    //   918: pop
    //   919: iload_2
    //   920: ifeq -> 1592
    //   923: goto -> 930
    //   926: invokestatic a : (Ljava/lang/Throwable;)Ljava/lang/Throwable;
    //   929: athrow
    //   930: aload_3
    //   931: getstatic burp/Ze7q.ZW : Ljava/lang/String;
    //   934: getstatic burp/Zein.Zb : Ljava/lang/Object;
    //   937: checkcast java/math/BigInteger
    //   940: invokevirtual intValue : ()I
    //   943: bipush #32
    //   945: irem
    //   946: invokestatic abs : (I)I
    //   949: invokevirtual charAt : (I)C
    //   952: invokevirtual append : (C)Ljava/lang/StringBuilder;
    //   955: pop
    //   956: iload_2
    //   957: ifeq -> 1592
    //   960: goto -> 967
    //   963: invokestatic a : (Ljava/lang/Throwable;)Ljava/lang/Throwable;
    //   966: athrow
    //   967: aload_3
    //   968: getstatic burp/Zr8h.Zk : Ljava/lang/String;
    //   971: getstatic burp/Zzsq.Zh : Ljava/lang/Object;
    //   974: checkcast java/math/BigInteger
    //   977: invokevirtual intValue : ()I
    //   980: bipush #32
    //   982: irem
    //   983: invokestatic abs : (I)I
    //   986: invokevirtual charAt : (I)C
    //   989: invokevirtual append : (C)Ljava/lang/StringBuilder;
    //   992: pop
    //   993: iload_2
    //   994: ifeq -> 1592
    //   997: goto -> 1004
    //   1000: invokestatic a : (Ljava/lang/Throwable;)Ljava/lang/Throwable;
    //   1003: athrow
    //   1004: aload_3
    //   1005: getstatic burp/Zein.ZN : Ljava/lang/String;
    //   1008: getstatic burp/Zod.ZP : Ljava/lang/Object;
    //   1011: checkcast java/math/BigInteger
    //   1014: invokevirtual intValue : ()I
    //   1017: bipush #32
    //   1019: irem
    //   1020: invokestatic abs : (I)I
    //   1023: invokevirtual charAt : (I)C
    //   1026: invokevirtual append : (C)Ljava/lang/StringBuilder;
    //   1029: pop
    //   1030: iload_2
    //   1031: ifeq -> 1592
    //   1034: goto -> 1041
    //   1037: invokestatic a : (Ljava/lang/Throwable;)Ljava/lang/Throwable;
    //   1040: athrow
    //   1041: aload_3
    //   1042: getstatic burp/Zod.ZS : Ljava/lang/String;
    //   1045: getstatic burp/Zxzj.ZO : Ljava/lang/Object;
    //   1048: checkcast java/math/BigInteger
    //   1051: invokevirtual intValue : ()I
    //   1054: bipush #32
    //   1056: irem
    //   1057: invokestatic abs : (I)I
    //   1060: invokevirtual charAt : (I)C
    //   1063: invokevirtual append : (C)Ljava/lang/StringBuilder;
    //   1066: pop
    //   1067: iload_2
    //   1068: ifeq -> 1592
    //   1071: goto -> 1078
    //   1074: invokestatic a : (Ljava/lang/Throwable;)Ljava/lang/Throwable;
    //   1077: athrow
    //   1078: aload_3
    //   1079: getstatic burp/Zlhm.Zx : Ljava/lang/String;
    //   1082: getstatic burp/Ze7q.Zk : Ljava/lang/Object;
    //   1085: checkcast java/math/BigInteger
    //   1088: invokevirtual intValue : ()I
    //   1091: bipush #32
    //   1093: irem
    //   1094: invokestatic abs : (I)I
    //   1097: invokevirtual charAt : (I)C
    //   1100: invokevirtual append : (C)Ljava/lang/StringBuilder;
    //   1103: pop
    //   1104: iload_2
    //   1105: ifeq -> 1592
    //   1108: goto -> 1115
    //   1111: invokestatic a : (Ljava/lang/Throwable;)Ljava/lang/Throwable;
    //   1114: athrow
    //   1115: aload_3
    //   1116: getstatic burp/Zkfz.Zs : Ljava/lang/String;
    //   1119: getstatic burp/Zz1k.ZP : Ljava/lang/Object;
    //   1122: checkcast java/math/BigInteger
    //   1125: invokevirtual intValue : ()I
    //   1128: bipush #32
    //   1130: irem
    //   1131: invokestatic abs : (I)I
    //   1134: invokevirtual charAt : (I)C
    //   1137: invokevirtual append : (C)Ljava/lang/StringBuilder;
    //   1140: pop
    //   1141: iload_2
    //   1142: ifeq -> 1592
    //   1145: goto -> 1152
    //   1148: invokestatic a : (Ljava/lang/Throwable;)Ljava/lang/Throwable;
    //   1151: athrow
    //   1152: aload_3
    //   1153: getstatic burp/Zg_p.ZO : Ljava/lang/String;
    //   1156: getstatic burp/Zm0s.Zl : Ljava/lang/Object;
    //   1159: checkcast java/math/BigInteger
    //   1162: invokevirtual intValue : ()I
    //   1165: bipush #32
    //   1167: irem
    //   1168: invokestatic abs : (I)I
    //   1171: invokevirtual charAt : (I)C
    //   1174: invokevirtual append : (C)Ljava/lang/StringBuilder;
    //   1177: pop
    //   1178: iload_2
    //   1179: ifeq -> 1592
    //   1182: goto -> 1189
    //   1185: invokestatic a : (Ljava/lang/Throwable;)Ljava/lang/Throwable;
    //   1188: athrow
    //   1189: aload_3
    //   1190: getstatic burp/Zgw0.ZL : Ljava/lang/String;
    //   1193: getstatic burp/Zllw.ZW : Ljava/lang/Object;
    //   1196: checkcast java/math/BigInteger
    //   1199: invokevirtual intValue : ()I
    //   1202: bipush #32
    //   1204: irem
    //   1205: invokestatic abs : (I)I
    //   1208: invokevirtual charAt : (I)C
    //   1211: invokevirtual append : (C)Ljava/lang/StringBuilder;
    //   1214: pop
    //   1215: iload_2
    //   1216: ifeq -> 1592
    //   1219: goto -> 1226
    //   1222: invokestatic a : (Ljava/lang/Throwable;)Ljava/lang/Throwable;
    //   1225: athrow
    //   1226: aload_3
    //   1227: getstatic burp/Zter.ZE : Ljava/lang/String;
    //   1230: getstatic burp/Zkbf.Zx : Ljava/lang/Object;
    //   1233: checkcast java/math/BigInteger
    //   1236: invokevirtual intValue : ()I
    //   1239: bipush #32
    //   1241: irem
    //   1242: invokestatic abs : (I)I
    //   1245: invokevirtual charAt : (I)C
    //   1248: invokevirtual append : (C)Ljava/lang/StringBuilder;
    //   1251: pop
    //   1252: iload_2
    //   1253: ifeq -> 1592
    //   1256: goto -> 1263
    //   1259: invokestatic a : (Ljava/lang/Throwable;)Ljava/lang/Throwable;
    //   1262: athrow
    //   1263: aload_3
    //   1264: getstatic burp/Zgmt.Zu : Ljava/lang/String;
    //   1267: getstatic burp/Zsgl.Zn : Ljava/lang/Object;
    //   1270: checkcast java/math/BigInteger
    //   1273: invokevirtual intValue : ()I
    //   1276: bipush #32
    //   1278: irem
    //   1279: invokestatic abs : (I)I
    //   1282: invokevirtual charAt : (I)C
    //   1285: invokevirtual append : (C)Ljava/lang/StringBuilder;
    //   1288: pop
    //   1289: iload_2
    //   1290: ifeq -> 1592
    //   1293: goto -> 1300
    //   1296: invokestatic a : (Ljava/lang/Throwable;)Ljava/lang/Throwable;
    //   1299: athrow
    //   1300: aload_3
    //   1301: getstatic burp/Zlhm.Zx : Ljava/lang/String;
    //   1304: getstatic burp/Zm__.Zz : Ljava/lang/Object;
    //   1307: checkcast java/math/BigInteger
    //   1310: invokevirtual intValue : ()I
    //   1313: bipush #32
    //   1315: irem
    //   1316: invokestatic abs : (I)I
    //   1319: invokevirtual charAt : (I)C
    //   1322: invokevirtual append : (C)Ljava/lang/StringBuilder;
    //   1325: pop
    //   1326: iload_2
    //   1327: ifeq -> 1592
    //   1330: goto -> 1337
    //   1333: invokestatic a : (Ljava/lang/Throwable;)Ljava/lang/Throwable;
    //   1336: athrow
    //   1337: aload_3
    //   1338: getstatic burp/Zsby.Zx : Ljava/lang/String;
    //   1341: getstatic burp/Zzip.ZW : Ljava/lang/Object;
    //   1344: checkcast java/math/BigInteger
    //   1347: invokevirtual intValue : ()I
    //   1350: bipush #32
    //   1352: irem
    //   1353: invokestatic abs : (I)I
    //   1356: invokevirtual charAt : (I)C
    //   1359: invokevirtual append : (C)Ljava/lang/StringBuilder;
    //   1362: pop
    //   1363: iload_2
    //   1364: ifeq -> 1592
    //   1367: goto -> 1374
    //   1370: invokestatic a : (Ljava/lang/Throwable;)Ljava/lang/Throwable;
    //   1373: athrow
    //   1374: aload_3
    //   1375: getstatic burp/Zr8h.Zk : Ljava/lang/String;
    //   1378: getstatic burp/Zsgl.Zn : Ljava/lang/Object;
    //   1381: checkcast java/math/BigInteger
    //   1384: invokevirtual intValue : ()I
    //   1387: bipush #32
    //   1389: irem
    //   1390: invokestatic abs : (I)I
    //   1393: invokevirtual charAt : (I)C
    //   1396: invokevirtual append : (C)Ljava/lang/StringBuilder;
    //   1399: pop
    //   1400: iload_2
    //   1401: ifeq -> 1592
    //   1404: goto -> 1411
    //   1407: invokestatic a : (Ljava/lang/Throwable;)Ljava/lang/Throwable;
    //   1410: athrow
    //   1411: aload_3
    //   1412: getstatic burp/Zl2q.ZI : Ljava/lang/String;
    //   1415: getstatic burp/Zk8b.ZK : Ljava/lang/Object;
    //   1418: checkcast java/math/BigInteger
    //   1421: invokevirtual intValue : ()I
    //   1424: bipush #32
    //   1426: irem
    //   1427: invokestatic abs : (I)I
    //   1430: invokevirtual charAt : (I)C
    //   1433: invokevirtual append : (C)Ljava/lang/StringBuilder;
    //   1436: pop
    //   1437: iload_2
    //   1438: ifeq -> 1592
    //   1441: goto -> 1448
    //   1444: invokestatic a : (Ljava/lang/Throwable;)Ljava/lang/Throwable;
    //   1447: athrow
    //   1448: aload_3
    //   1449: getstatic burp/Zkbm.Zb : Ljava/lang/String;
    //   1452: getstatic burp/Zl88.ZK : Ljava/lang/Object;
    //   1455: checkcast java/math/BigInteger
    //   1458: invokevirtual intValue : ()I
    //   1461: bipush #32
    //   1463: irem
    //   1464: invokestatic abs : (I)I
    //   1467: invokevirtual charAt : (I)C
    //   1470: invokevirtual append : (C)Ljava/lang/StringBuilder;
    //   1473: pop
    //   1474: iload_2
    //   1475: ifeq -> 1592
    //   1478: goto -> 1485
    //   1481: invokestatic a : (Ljava/lang/Throwable;)Ljava/lang/Throwable;
    //   1484: athrow
    //   1485: aload_3
    //   1486: getstatic burp/Zbsr.Zq : Ljava/lang/String;
    //   1489: getstatic burp/Ztuj.Ze : Ljava/lang/Object;
    //   1492: checkcast java/math/BigInteger
    //   1495: invokevirtual intValue : ()I
    //   1498: bipush #32
    //   1500: irem
    //   1501: invokestatic abs : (I)I
    //   1504: invokevirtual charAt : (I)C
    //   1507: invokevirtual append : (C)Ljava/lang/StringBuilder;
    //   1510: pop
    //   1511: iload_2
    //   1512: ifeq -> 1592
    //   1515: goto -> 1522
    //   1518: invokestatic a : (Ljava/lang/Throwable;)Ljava/lang/Throwable;
    //   1521: athrow
    //   1522: aload_3
    //   1523: getstatic burp/Zbsr.Zq : Ljava/lang/String;
    //   1526: getstatic burp/Zkmx.Zu : Ljava/lang/Object;
    //   1529: checkcast java/math/BigInteger
    //   1532: invokevirtual intValue : ()I
    //   1535: bipush #32
    //   1537: irem
    //   1538: invokestatic abs : (I)I
    //   1541: invokevirtual charAt : (I)C
    //   1544: invokevirtual append : (C)Ljava/lang/StringBuilder;
    //   1547: pop
    //   1548: iload_2
    //   1549: ifeq -> 1592
    //   1552: goto -> 1559
    //   1555: invokestatic a : (Ljava/lang/Throwable;)Ljava/lang/Throwable;
    //   1558: athrow
    //   1559: aload_3
    //   1560: getstatic burp/Zrdy.ZO : Ljava/lang/String;
    //   1563: getstatic burp/Zr8h.ZH : Ljava/lang/Object;
    //   1566: checkcast java/math/BigInteger
    //   1569: invokevirtual intValue : ()I
    //   1572: bipush #32
    //   1574: irem
    //   1575: invokestatic abs : (I)I
    //   1578: invokevirtual charAt : (I)C
    //   1581: invokevirtual append : (C)Ljava/lang/StringBuilder;
    //   1584: pop
    //   1585: goto -> 1592
    //   1588: invokestatic a : (Ljava/lang/Throwable;)Ljava/lang/Throwable;
    //   1591: athrow
    //   1592: iinc #4, 1
    //   1595: iload_2
    //   1596: ifeq -> 261
    //   1599: aload_3
    //   1600: invokevirtual toString : ()Ljava/lang/String;
    //   1603: putstatic burp/Zxyp.Z_ : Ljava/lang/String;
    //   1606: sipush #6528
    //   1609: getstatic burp/Zbsr.ZD : Ljava/lang/Object;
    //   1612: checkcast java/math/BigInteger
    //   1615: getstatic burp/Zzk9.ZK : Ljava/lang/Object;
    //   1618: checkcast java/math/BigInteger
    //   1621: invokevirtual add : (Ljava/math/BigInteger;)Ljava/math/BigInteger;
    //   1624: putstatic burp/Zg7p.Zb : Ljava/lang/Object;
    //   1627: sipush #-8228
    //   1630: invokestatic a : (II)Ljava/lang/String;
    //   1633: iconst_1
    //   1634: ldc burp/Zz6t
    //   1636: invokevirtual getClassLoader : ()Ljava/lang/ClassLoader;
    //   1639: invokestatic forName : (Ljava/lang/String;ZLjava/lang/ClassLoader;)Ljava/lang/Class;
    //   1642: invokevirtual getDeclaredFields : ()[Ljava/lang/reflect/Field;
    //   1645: astore #4
    //   1647: aload #4
    //   1649: arraylength
    //   1650: istore #5
    //   1652: iconst_0
    //   1653: istore #6
    //   1655: iload #6
    //   1657: iload #5
    //   1659: if_icmpge -> 1797
    //   1662: aload #4
    //   1664: iload #6
    //   1666: aaload
    //   1667: astore #7
    //   1669: aload #7
    //   1671: invokevirtual getModifiers : ()I
    //   1674: invokestatic isStatic : (I)Z
    //   1677: ifne -> 1687
    //   1680: goto -> 1790
    //   1683: invokestatic a : (Ljava/lang/Throwable;)Ljava/lang/Throwable;
    //   1686: athrow
    //   1687: aload #7
    //   1689: invokevirtual getType : ()Ljava/lang/Class;
    //   1692: astore #8
    //   1694: aload #8
    //   1696: ifnull -> 1777
    //   1699: aload #8
    //   1701: invokevirtual isPrimitive : ()Z
    //   1704: ifne -> 1777
    //   1707: goto -> 1714
    //   1710: invokestatic a : (Ljava/lang/Throwable;)Ljava/lang/Throwable;
    //   1713: athrow
    //   1714: aload #8
    //   1716: invokevirtual getPackage : ()Ljava/lang/Package;
    //   1719: ifnull -> 1777
    //   1722: goto -> 1729
    //   1725: invokestatic a : (Ljava/lang/Throwable;)Ljava/lang/Throwable;
    //   1728: athrow
    //   1729: aload #8
    //   1731: invokevirtual getPackage : ()Ljava/lang/Package;
    //   1734: invokevirtual getName : ()Ljava/lang/String;
    //   1737: ifnull -> 1777
    //   1740: goto -> 1747
    //   1743: invokestatic a : (Ljava/lang/Throwable;)Ljava/lang/Throwable;
    //   1746: athrow
    //   1747: aload #8
    //   1749: invokevirtual getPackage : ()Ljava/lang/Package;
    //   1752: invokevirtual getName : ()Ljava/lang/String;
    //   1755: sipush #6529
    //   1758: sipush #-18668
    //   1761: invokestatic a : (II)Ljava/lang/String;
    //   1764: invokevirtual startsWith : (Ljava/lang/String;)Z
    //   1767: ifne -> 1777
    //   1770: goto -> 1777
    //   1773: invokestatic a : (Ljava/lang/Throwable;)Ljava/lang/Throwable;
    //   1776: athrow
    //   1777: aload #7
    //   1779: iconst_1
    //   1780: invokevirtual setAccessible : (Z)V
    //   1783: aload #7
    //   1785: aconst_null
    //   1786: invokevirtual get : (Ljava/lang/Object;)Ljava/lang/Object;
    //   1789: pop
    //   1790: iinc #6, 1
    //   1793: iload_2
    //   1794: ifeq -> 1655
    //   1797: sipush #6535
    //   1800: sipush #10064
    //   1803: invokestatic a : (II)Ljava/lang/String;
    //   1806: invokestatic forName : (Ljava/lang/String;)Ljava/lang/Class;
    //   1809: invokevirtual getDeclaredMethods : ()[Ljava/lang/reflect/Method;
    //   1812: astore #4
    //   1814: aload #4
    //   1816: arraylength
    //   1817: istore #5
    //   1819: iconst_0
    //   1820: istore #6
    //   1822: iload #6
    //   1824: iload #5
    //   1826: if_icmpge -> 1959
    //   1829: aload #4
    //   1831: iload #6
    //   1833: aaload
    //   1834: astore #7
    //   1836: aload #7
    //   1838: invokevirtual getParameterTypes : ()[Ljava/lang/Class;
    //   1841: pop
    //   1842: aload #7
    //   1844: invokevirtual getModifiers : ()I
    //   1847: invokestatic isStatic : (I)Z
    //   1850: ifeq -> 1945
    //   1853: aload #7
    //   1855: invokevirtual getParameterTypes : ()[Ljava/lang/Class;
    //   1858: arraylength
    //   1859: iconst_2
    //   1860: if_icmpne -> 1945
    //   1863: goto -> 1870
    //   1866: invokestatic a : (Ljava/lang/Throwable;)Ljava/lang/Throwable;
    //   1869: athrow
    //   1870: aload #7
    //   1872: invokevirtual getReturnType : ()Ljava/lang/Class;
    //   1875: getstatic java/lang/Void.TYPE : Ljava/lang/Class;
    //   1878: invokevirtual equals : (Ljava/lang/Object;)Z
    //   1881: ifeq -> 1945
    //   1884: goto -> 1891
    //   1887: invokestatic a : (Ljava/lang/Throwable;)Ljava/lang/Throwable;
    //   1890: athrow
    //   1891: aload #7
    //   1893: iconst_1
    //   1894: invokevirtual setAccessible : (Z)V
    //   1897: aload #7
    //   1899: aconst_null
    //   1900: iconst_2
    //   1901: anewarray java/lang/Object
    //   1904: dup
    //   1905: iconst_0
    //   1906: aload_0
    //   1907: aastore
    //   1908: dup
    //   1909: iconst_1
    //   1910: aload_1
    //   1911: ifnonnull -> 1929
    //   1914: goto -> 1921
    //   1917: invokestatic a : (Ljava/lang/Throwable;)Ljava/lang/Throwable;
    //   1920: athrow
    //   1921: aload_1
    //   1922: goto -> 1936
    //   1925: invokestatic a : (Ljava/lang/Throwable;)Ljava/lang/Throwable;
    //   1928: athrow
    //   1929: aload_1
    //   1930: checkcast [B
    //   1933: invokevirtual clone : ()Ljava/lang/Object;
    //   1936: aastore
    //   1937: invokevirtual invoke : (Ljava/lang/Object;[Ljava/lang/Object;)Ljava/lang/Object;
    //   1940: pop
    //   1941: iload_2
    //   1942: ifeq -> 1959
    //   1945: iinc #6, 1
    //   1948: iload_2
    //   1949: ifeq -> 1822
    //   1952: goto -> 1959
    //   1955: invokestatic a : (Ljava/lang/Throwable;)Ljava/lang/Throwable;
    //   1958: athrow
    //   1959: getstatic burp/Zkmx.Zu : Ljava/lang/Object;
    //   1962: checkcast java/math/BigInteger
    //   1965: invokevirtual toByteArray : ()[B
    //   1968: astore #4
    //   1970: bipush #32
    //   1972: newarray int
    //   1974: dup
    //   1975: iconst_0
    //   1976: ldc 943331329
    //   1978: iastore
    //   1979: dup
    //   1980: iconst_1
    //   1981: ldc 170788368
    //   1983: iastore
    //   1984: dup
    //   1985: iconst_2
    //   1986: ldc 1008414755
    //   1988: iastore
    //   1989: dup
    //   1990: iconst_3
    //   1991: ldc 187049985
    //   1993: iastore
    //   1994: dup
    //   1995: iconst_4
    //   1996: ldc 1010368540
    //   1998: iastore
    //   1999: dup
    //   2000: iconst_5
    //   2001: ldc 220604441
    //   2003: iastore
    //   2004: dup
    //   2005: bipush #6
    //   2007: ldc 940377620
    //   2009: iastore
    //   2010: dup
    //   2011: bipush #7
    //   2013: ldc 255209728
    //   2015: iastore
    //   2016: dup
    //   2017: bipush #8
    //   2019: ldc 689771012
    //   2021: iastore
    //   2022: dup
    //   2023: bipush #9
    //   2025: ldc 221709344
    //   2027: iastore
    //   2028: dup
    //   2029: bipush #10
    //   2031: ldc 957157408
    //   2033: iastore
    //   2034: dup
    //   2035: bipush #11
    //   2037: ldc 892536332
    //   2039: iastore
    //   2040: dup
    //   2041: bipush #12
    //   2043: ldc 722417666
    //   2045: iastore
    //   2046: dup
    //   2047: bipush #13
    //   2049: ldc 1026621720
    //   2051: iastore
    //   2052: dup
    //   2053: bipush #14
    //   2055: ldc 655302664
    //   2057: iastore
    //   2058: dup
    //   2059: bipush #15
    //   2061: ldc 890966315
    //   2063: iastore
    //   2064: dup
    //   2065: bipush #16
    //   2067: ldc 187632156
    //   2069: iastore
    //   2070: dup
    //   2071: bipush #17
    //   2073: ldc 874189824
    //   2075: iastore
    //   2076: dup
    //   2077: bipush #18
    //   2079: ldc 254150144
    //   2081: iastore
    //   2082: dup
    //   2083: bipush #19
    //   2085: ldc 924386310
    //   2087: iastore
    //   2088: dup
    //   2089: bipush #20
    //   2091: ldc 121057538
    //   2093: iastore
    //   2094: dup
    //   2095: bipush #21
    //   2097: ldc 840500228
    //   2099: iastore
    //   2100: dup
    //   2101: bipush #22
    //   2103: ldc 389160971
    //   2105: iastore
    //   2106: dup
    //   2107: bipush #23
    //   2109: ldc 907870729
    //   2111: iastore
    //   2112: dup
    //   2113: bipush #24
    //   2115: ldc 389426184
    //   2117: iastore
    //   2118: dup
    //   2119: bipush #25
    //   2121: ldc 973875457
    //   2123: iastore
    //   2124: dup
    //   2125: bipush #26
    //   2127: ldc 372376604
    //   2129: iastore
    //   2130: dup
    //   2131: bipush #27
    //   2133: ldc 707731490
    //   2135: iastore
    //   2136: dup
    //   2137: bipush #28
    //   2139: ldc 1043334948
    //   2141: iastore
    //   2142: dup
    //   2143: bipush #29
    //   2145: ldc 439222784
    //   2147: iastore
    //   2148: dup
    //   2149: bipush #30
    //   2151: ldc 876216579
    //   2153: iastore
    //   2154: dup
    //   2155: bipush #31
    //   2157: ldc 455999525
    //   2159: iastore
    //   2160: astore #6
    //   2162: bipush #8
    //   2164: aload #4
    //   2166: arraylength
    //   2167: bipush #8
    //   2169: irem
    //   2170: isub
    //   2171: istore #7
    //   2173: aload #4
    //   2175: arraylength
    //   2176: iload #7
    //   2178: iadd
    //   2179: newarray byte
    //   2181: astore #8
    //   2183: iconst_0
    //   2184: istore #9
    //   2186: iload #9
    //   2188: aload #4
    //   2190: arraylength
    //   2191: if_icmpge -> 2211
    //   2194: aload #8
    //   2196: iload #9
    //   2198: aload #4
    //   2200: iload #9
    //   2202: baload
    //   2203: bastore
    //   2204: iinc #9, 1
    //   2207: iload_2
    //   2208: ifeq -> 2186
    //   2211: aload #4
    //   2213: arraylength
    //   2214: istore #9
    //   2216: iload #9
    //   2218: aload #8
    //   2220: arraylength
    //   2221: if_icmpge -> 2239
    //   2224: aload #8
    //   2226: iload #9
    //   2228: iload #7
    //   2230: i2b
    //   2231: bastore
    //   2232: iinc #9, 1
    //   2235: iload_2
    //   2236: ifeq -> 2216
    //   2239: aload #8
    //   2241: astore #4
    //   2243: bipush #64
    //   2245: newarray int
    //   2247: dup
    //   2248: iconst_0
    //   2249: ldc 16843776
    //   2251: iastore
    //   2252: dup
    //   2253: iconst_1
    //   2254: iconst_0
    //   2255: iastore
    //   2256: dup
    //   2257: iconst_2
    //   2258: ldc 65536
    //   2260: iastore
    //   2261: dup
    //   2262: iconst_3
    //   2263: ldc 16843780
    //   2265: iastore
    //   2266: dup
    //   2267: iconst_4
    //   2268: ldc 16842756
    //   2270: iastore
    //   2271: dup
    //   2272: iconst_5
    //   2273: ldc 66564
    //   2275: iastore
    //   2276: dup
    //   2277: bipush #6
    //   2279: iconst_4
    //   2280: iastore
    //   2281: dup
    //   2282: bipush #7
    //   2284: ldc 65536
    //   2286: iastore
    //   2287: dup
    //   2288: bipush #8
    //   2290: sipush #1024
    //   2293: iastore
    //   2294: dup
    //   2295: bipush #9
    //   2297: ldc 16843776
    //   2299: iastore
    //   2300: dup
    //   2301: bipush #10
    //   2303: ldc 16843780
    //   2305: iastore
    //   2306: dup
    //   2307: bipush #11
    //   2309: sipush #1024
    //   2312: iastore
    //   2313: dup
    //   2314: bipush #12
    //   2316: ldc 16778244
    //   2318: iastore
    //   2319: dup
    //   2320: bipush #13
    //   2322: ldc 16842756
    //   2324: iastore
    //   2325: dup
    //   2326: bipush #14
    //   2328: ldc 16777216
    //   2330: iastore
    //   2331: dup
    //   2332: bipush #15
    //   2334: iconst_4
    //   2335: iastore
    //   2336: dup
    //   2337: bipush #16
    //   2339: sipush #1028
    //   2342: iastore
    //   2343: dup
    //   2344: bipush #17
    //   2346: ldc 16778240
    //   2348: iastore
    //   2349: dup
    //   2350: bipush #18
    //   2352: ldc 16778240
    //   2354: iastore
    //   2355: dup
    //   2356: bipush #19
    //   2358: ldc 66560
    //   2360: iastore
    //   2361: dup
    //   2362: bipush #20
    //   2364: ldc 66560
    //   2366: iastore
    //   2367: dup
    //   2368: bipush #21
    //   2370: ldc 16842752
    //   2372: iastore
    //   2373: dup
    //   2374: bipush #22
    //   2376: ldc 16842752
    //   2378: iastore
    //   2379: dup
    //   2380: bipush #23
    //   2382: ldc 16778244
    //   2384: iastore
    //   2385: dup
    //   2386: bipush #24
    //   2388: ldc 65540
    //   2390: iastore
    //   2391: dup
    //   2392: bipush #25
    //   2394: ldc 16777220
    //   2396: iastore
    //   2397: dup
    //   2398: bipush #26
    //   2400: ldc 16777220
    //   2402: iastore
    //   2403: dup
    //   2404: bipush #27
    //   2406: ldc 65540
    //   2408: iastore
    //   2409: dup
    //   2410: bipush #28
    //   2412: iconst_0
    //   2413: iastore
    //   2414: dup
    //   2415: bipush #29
    //   2417: sipush #1028
    //   2420: iastore
    //   2421: dup
    //   2422: bipush #30
    //   2424: ldc 66564
    //   2426: iastore
    //   2427: dup
    //   2428: bipush #31
    //   2430: ldc 16777216
    //   2432: iastore
    //   2433: dup
    //   2434: bipush #32
    //   2436: ldc 65536
    //   2438: iastore
    //   2439: dup
    //   2440: bipush #33
    //   2442: ldc 16843780
    //   2444: iastore
    //   2445: dup
    //   2446: bipush #34
    //   2448: iconst_4
    //   2449: iastore
    //   2450: dup
    //   2451: bipush #35
    //   2453: ldc 16842752
    //   2455: iastore
    //   2456: dup
    //   2457: bipush #36
    //   2459: ldc 16843776
    //   2461: iastore
    //   2462: dup
    //   2463: bipush #37
    //   2465: ldc 16777216
    //   2467: iastore
    //   2468: dup
    //   2469: bipush #38
    //   2471: ldc 16777216
    //   2473: iastore
    //   2474: dup
    //   2475: bipush #39
    //   2477: sipush #1024
    //   2480: iastore
    //   2481: dup
    //   2482: bipush #40
    //   2484: ldc 16842756
    //   2486: iastore
    //   2487: dup
    //   2488: bipush #41
    //   2490: ldc 65536
    //   2492: iastore
    //   2493: dup
    //   2494: bipush #42
    //   2496: ldc 66560
    //   2498: iastore
    //   2499: dup
    //   2500: bipush #43
    //   2502: ldc 16777220
    //   2504: iastore
    //   2505: dup
    //   2506: bipush #44
    //   2508: sipush #1024
    //   2511: iastore
    //   2512: dup
    //   2513: bipush #45
    //   2515: iconst_4
    //   2516: iastore
    //   2517: dup
    //   2518: bipush #46
    //   2520: ldc 16778244
    //   2522: iastore
    //   2523: dup
    //   2524: bipush #47
    //   2526: ldc 66564
    //   2528: iastore
    //   2529: dup
    //   2530: bipush #48
    //   2532: ldc 16843780
    //   2534: iastore
    //   2535: dup
    //   2536: bipush #49
    //   2538: ldc 65540
    //   2540: iastore
    //   2541: dup
    //   2542: bipush #50
    //   2544: ldc 16842752
    //   2546: iastore
    //   2547: dup
    //   2548: bipush #51
    //   2550: ldc 16778244
    //   2552: iastore
    //   2553: dup
    //   2554: bipush #52
    //   2556: ldc 16777220
    //   2558: iastore
    //   2559: dup
    //   2560: bipush #53
    //   2562: sipush #1028
    //   2565: iastore
    //   2566: dup
    //   2567: bipush #54
    //   2569: ldc 66564
    //   2571: iastore
    //   2572: dup
    //   2573: bipush #55
    //   2575: ldc 16843776
    //   2577: iastore
    //   2578: dup
    //   2579: bipush #56
    //   2581: sipush #1028
    //   2584: iastore
    //   2585: dup
    //   2586: bipush #57
    //   2588: ldc 16778240
    //   2590: iastore
    //   2591: dup
    //   2592: bipush #58
    //   2594: ldc 16778240
    //   2596: iastore
    //   2597: dup
    //   2598: bipush #59
    //   2600: iconst_0
    //   2601: iastore
    //   2602: dup
    //   2603: bipush #60
    //   2605: ldc 65540
    //   2607: iastore
    //   2608: dup
    //   2609: bipush #61
    //   2611: ldc 66560
    //   2613: iastore
    //   2614: dup
    //   2615: bipush #62
    //   2617: iconst_0
    //   2618: iastore
    //   2619: dup
    //   2620: bipush #63
    //   2622: ldc 16842756
    //   2624: iastore
    //   2625: astore #9
    //   2627: bipush #64
    //   2629: newarray int
    //   2631: dup
    //   2632: iconst_0
    //   2633: ldc -2146402272
    //   2635: iastore
    //   2636: dup
    //   2637: iconst_1
    //   2638: ldc -2147450880
    //   2640: iastore
    //   2641: dup
    //   2642: iconst_2
    //   2643: ldc 32768
    //   2645: iastore
    //   2646: dup
    //   2647: iconst_3
    //   2648: ldc 1081376
    //   2650: iastore
    //   2651: dup
    //   2652: iconst_4
    //   2653: ldc 1048576
    //   2655: iastore
    //   2656: dup
    //   2657: iconst_5
    //   2658: bipush #32
    //   2660: iastore
    //   2661: dup
    //   2662: bipush #6
    //   2664: ldc -2146435040
    //   2666: iastore
    //   2667: dup
    //   2668: bipush #7
    //   2670: ldc -2147450848
    //   2672: iastore
    //   2673: dup
    //   2674: bipush #8
    //   2676: ldc -2147483616
    //   2678: iastore
    //   2679: dup
    //   2680: bipush #9
    //   2682: ldc -2146402272
    //   2684: iastore
    //   2685: dup
    //   2686: bipush #10
    //   2688: ldc -2146402304
    //   2690: iastore
    //   2691: dup
    //   2692: bipush #11
    //   2694: ldc -2147483648
    //   2696: iastore
    //   2697: dup
    //   2698: bipush #12
    //   2700: ldc -2147450880
    //   2702: iastore
    //   2703: dup
    //   2704: bipush #13
    //   2706: ldc 1048576
    //   2708: iastore
    //   2709: dup
    //   2710: bipush #14
    //   2712: bipush #32
    //   2714: iastore
    //   2715: dup
    //   2716: bipush #15
    //   2718: ldc -2146435040
    //   2720: iastore
    //   2721: dup
    //   2722: bipush #16
    //   2724: ldc 1081344
    //   2726: iastore
    //   2727: dup
    //   2728: bipush #17
    //   2730: ldc 1048608
    //   2732: iastore
    //   2733: dup
    //   2734: bipush #18
    //   2736: ldc -2147450848
    //   2738: iastore
    //   2739: dup
    //   2740: bipush #19
    //   2742: iconst_0
    //   2743: iastore
    //   2744: dup
    //   2745: bipush #20
    //   2747: ldc -2147483648
    //   2749: iastore
    //   2750: dup
    //   2751: bipush #21
    //   2753: ldc 32768
    //   2755: iastore
    //   2756: dup
    //   2757: bipush #22
    //   2759: ldc 1081376
    //   2761: iastore
    //   2762: dup
    //   2763: bipush #23
    //   2765: ldc -2146435072
    //   2767: iastore
    //   2768: dup
    //   2769: bipush #24
    //   2771: ldc 1048608
    //   2773: iastore
    //   2774: dup
    //   2775: bipush #25
    //   2777: ldc -2147483616
    //   2779: iastore
    //   2780: dup
    //   2781: bipush #26
    //   2783: iconst_0
    //   2784: iastore
    //   2785: dup
    //   2786: bipush #27
    //   2788: ldc 1081344
    //   2790: iastore
    //   2791: dup
    //   2792: bipush #28
    //   2794: ldc 32800
    //   2796: iastore
    //   2797: dup
    //   2798: bipush #29
    //   2800: ldc -2146402304
    //   2802: iastore
    //   2803: dup
    //   2804: bipush #30
    //   2806: ldc -2146435072
    //   2808: iastore
    //   2809: dup
    //   2810: bipush #31
    //   2812: ldc 32800
    //   2814: iastore
    //   2815: dup
    //   2816: bipush #32
    //   2818: iconst_0
    //   2819: iastore
    //   2820: dup
    //   2821: bipush #33
    //   2823: ldc 1081376
    //   2825: iastore
    //   2826: dup
    //   2827: bipush #34
    //   2829: ldc -2146435040
    //   2831: iastore
    //   2832: dup
    //   2833: bipush #35
    //   2835: ldc 1048576
    //   2837: iastore
    //   2838: dup
    //   2839: bipush #36
    //   2841: ldc -2147450848
    //   2843: iastore
    //   2844: dup
    //   2845: bipush #37
    //   2847: ldc -2146435072
    //   2849: iastore
    //   2850: dup
    //   2851: bipush #38
    //   2853: ldc -2146402304
    //   2855: iastore
    //   2856: dup
    //   2857: bipush #39
    //   2859: ldc 32768
    //   2861: iastore
    //   2862: dup
    //   2863: bipush #40
    //   2865: ldc -2146435072
    //   2867: iastore
    //   2868: dup
    //   2869: bipush #41
    //   2871: ldc -2147450880
    //   2873: iastore
    //   2874: dup
    //   2875: bipush #42
    //   2877: bipush #32
    //   2879: iastore
    //   2880: dup
    //   2881: bipush #43
    //   2883: ldc -2146402272
    //   2885: iastore
    //   2886: dup
    //   2887: bipush #44
    //   2889: ldc 1081376
    //   2891: iastore
    //   2892: dup
    //   2893: bipush #45
    //   2895: bipush #32
    //   2897: iastore
    //   2898: dup
    //   2899: bipush #46
    //   2901: ldc 32768
    //   2903: iastore
    //   2904: dup
    //   2905: bipush #47
    //   2907: ldc -2147483648
    //   2909: iastore
    //   2910: dup
    //   2911: bipush #48
    //   2913: ldc 32800
    //   2915: iastore
    //   2916: dup
    //   2917: bipush #49
    //   2919: ldc -2146402304
    //   2921: iastore
    //   2922: dup
    //   2923: bipush #50
    //   2925: ldc 1048576
    //   2927: iastore
    //   2928: dup
    //   2929: bipush #51
    //   2931: ldc -2147483616
    //   2933: iastore
    //   2934: dup
    //   2935: bipush #52
    //   2937: ldc 1048608
    //   2939: iastore
    //   2940: dup
    //   2941: bipush #53
    //   2943: ldc -2147450848
    //   2945: iastore
    //   2946: dup
    //   2947: bipush #54
    //   2949: ldc -2147483616
    //   2951: iastore
    //   2952: dup
    //   2953: bipush #55
    //   2955: ldc 1048608
    //   2957: iastore
    //   2958: dup
    //   2959: bipush #56
    //   2961: ldc 1081344
    //   2963: iastore
    //   2964: dup
    //   2965: bipush #57
    //   2967: iconst_0
    //   2968: iastore
    //   2969: dup
    //   2970: bipush #58
    //   2972: ldc -2147450880
    //   2974: iastore
    //   2975: dup
    //   2976: bipush #59
    //   2978: ldc 32800
    //   2980: iastore
    //   2981: dup
    //   2982: bipush #60
    //   2984: ldc -2147483648
    //   2986: iastore
    //   2987: dup
    //   2988: bipush #61
    //   2990: ldc -2146435040
    //   2992: iastore
    //   2993: dup
    //   2994: bipush #62
    //   2996: ldc -2146402272
    //   2998: iastore
    //   2999: dup
    //   3000: bipush #63
    //   3002: ldc 1081344
    //   3004: iastore
    //   3005: astore #10
    //   3007: bipush #64
    //   3009: newarray int
    //   3011: dup
    //   3012: iconst_0
    //   3013: sipush #520
    //   3016: iastore
    //   3017: dup
    //   3018: iconst_1
    //   3019: ldc 134349312
    //   3021: iastore
    //   3022: dup
    //   3023: iconst_2
    //   3024: iconst_0
    //   3025: iastore
    //   3026: dup
    //   3027: iconst_3
    //   3028: ldc 134348808
    //   3030: iastore
    //   3031: dup
    //   3032: iconst_4
    //   3033: ldc 134218240
    //   3035: iastore
    //   3036: dup
    //   3037: iconst_5
    //   3038: iconst_0
    //   3039: iastore
    //   3040: dup
    //   3041: bipush #6
    //   3043: ldc 131592
    //   3045: iastore
    //   3046: dup
    //   3047: bipush #7
    //   3049: ldc 134218240
    //   3051: iastore
    //   3052: dup
    //   3053: bipush #8
    //   3055: ldc 131080
    //   3057: iastore
    //   3058: dup
    //   3059: bipush #9
    //   3061: ldc 134217736
    //   3063: iastore
    //   3064: dup
    //   3065: bipush #10
    //   3067: ldc 134217736
    //   3069: iastore
    //   3070: dup
    //   3071: bipush #11
    //   3073: ldc 131072
    //   3075: iastore
    //   3076: dup
    //   3077: bipush #12
    //   3079: ldc 134349320
    //   3081: iastore
    //   3082: dup
    //   3083: bipush #13
    //   3085: ldc 131080
    //   3087: iastore
    //   3088: dup
    //   3089: bipush #14
    //   3091: ldc 134348800
    //   3093: iastore
    //   3094: dup
    //   3095: bipush #15
    //   3097: sipush #520
    //   3100: iastore
    //   3101: dup
    //   3102: bipush #16
    //   3104: ldc 134217728
    //   3106: iastore
    //   3107: dup
    //   3108: bipush #17
    //   3110: bipush #8
    //   3112: iastore
    //   3113: dup
    //   3114: bipush #18
    //   3116: ldc 134349312
    //   3118: iastore
    //   3119: dup
    //   3120: bipush #19
    //   3122: sipush #512
    //   3125: iastore
    //   3126: dup
    //   3127: bipush #20
    //   3129: ldc 131584
    //   3131: iastore
    //   3132: dup
    //   3133: bipush #21
    //   3135: ldc 134348800
    //   3137: iastore
    //   3138: dup
    //   3139: bipush #22
    //   3141: ldc 134348808
    //   3143: iastore
    //   3144: dup
    //   3145: bipush #23
    //   3147: ldc 131592
    //   3149: iastore
    //   3150: dup
    //   3151: bipush #24
    //   3153: ldc 134218248
    //   3155: iastore
    //   3156: dup
    //   3157: bipush #25
    //   3159: ldc 131584
    //   3161: iastore
    //   3162: dup
    //   3163: bipush #26
    //   3165: ldc 131072
    //   3167: iastore
    //   3168: dup
    //   3169: bipush #27
    //   3171: ldc 134218248
    //   3173: iastore
    //   3174: dup
    //   3175: bipush #28
    //   3177: bipush #8
    //   3179: iastore
    //   3180: dup
    //   3181: bipush #29
    //   3183: ldc 134349320
    //   3185: iastore
    //   3186: dup
    //   3187: bipush #30
    //   3189: sipush #512
    //   3192: iastore
    //   3193: dup
    //   3194: bipush #31
    //   3196: ldc 134217728
    //   3198: iastore
    //   3199: dup
    //   3200: bipush #32
    //   3202: ldc 134349312
    //   3204: iastore
    //   3205: dup
    //   3206: bipush #33
    //   3208: ldc 134217728
    //   3210: iastore
    //   3211: dup
    //   3212: bipush #34
    //   3214: ldc 131080
    //   3216: iastore
    //   3217: dup
    //   3218: bipush #35
    //   3220: sipush #520
    //   3223: iastore
    //   3224: dup
    //   3225: bipush #36
    //   3227: ldc 131072
    //   3229: iastore
    //   3230: dup
    //   3231: bipush #37
    //   3233: ldc 134349312
    //   3235: iastore
    //   3236: dup
    //   3237: bipush #38
    //   3239: ldc 134218240
    //   3241: iastore
    //   3242: dup
    //   3243: bipush #39
    //   3245: iconst_0
    //   3246: iastore
    //   3247: dup
    //   3248: bipush #40
    //   3250: sipush #512
    //   3253: iastore
    //   3254: dup
    //   3255: bipush #41
    //   3257: ldc 131080
    //   3259: iastore
    //   3260: dup
    //   3261: bipush #42
    //   3263: ldc 134349320
    //   3265: iastore
    //   3266: dup
    //   3267: bipush #43
    //   3269: ldc 134218240
    //   3271: iastore
    //   3272: dup
    //   3273: bipush #44
    //   3275: ldc 134217736
    //   3277: iastore
    //   3278: dup
    //   3279: bipush #45
    //   3281: sipush #512
    //   3284: iastore
    //   3285: dup
    //   3286: bipush #46
    //   3288: iconst_0
    //   3289: iastore
    //   3290: dup
    //   3291: bipush #47
    //   3293: ldc 134348808
    //   3295: iastore
    //   3296: dup
    //   3297: bipush #48
    //   3299: ldc 134218248
    //   3301: iastore
    //   3302: dup
    //   3303: bipush #49
    //   3305: ldc 131072
    //   3307: iastore
    //   3308: dup
    //   3309: bipush #50
    //   3311: ldc 134217728
    //   3313: iastore
    //   3314: dup
    //   3315: bipush #51
    //   3317: ldc 134349320
    //   3319: iastore
    //   3320: dup
    //   3321: bipush #52
    //   3323: bipush #8
    //   3325: iastore
    //   3326: dup
    //   3327: bipush #53
    //   3329: ldc 131592
    //   3331: iastore
    //   3332: dup
    //   3333: bipush #54
    //   3335: ldc 131584
    //   3337: iastore
    //   3338: dup
    //   3339: bipush #55
    //   3341: ldc 134217736
    //   3343: iastore
    //   3344: dup
    //   3345: bipush #56
    //   3347: ldc 134348800
    //   3349: iastore
    //   3350: dup
    //   3351: bipush #57
    //   3353: ldc 134218248
    //   3355: iastore
    //   3356: dup
    //   3357: bipush #58
    //   3359: sipush #520
    //   3362: iastore
    //   3363: dup
    //   3364: bipush #59
    //   3366: ldc 134348800
    //   3368: iastore
    //   3369: dup
    //   3370: bipush #60
    //   3372: ldc 131592
    //   3374: iastore
    //   3375: dup
    //   3376: bipush #61
    //   3378: bipush #8
    //   3380: iastore
    //   3381: dup
    //   3382: bipush #62
    //   3384: ldc 134348808
    //   3386: iastore
    //   3387: dup
    //   3388: bipush #63
    //   3390: ldc 131584
    //   3392: iastore
    //   3393: astore #11
    //   3395: bipush #64
    //   3397: newarray int
    //   3399: dup
    //   3400: iconst_0
    //   3401: ldc 8396801
    //   3403: iastore
    //   3404: dup
    //   3405: iconst_1
    //   3406: sipush #8321
    //   3409: iastore
    //   3410: dup
    //   3411: iconst_2
    //   3412: sipush #8321
    //   3415: iastore
    //   3416: dup
    //   3417: iconst_3
    //   3418: sipush #128
    //   3421: iastore
    //   3422: dup
    //   3423: iconst_4
    //   3424: ldc 8396928
    //   3426: iastore
    //   3427: dup
    //   3428: iconst_5
    //   3429: ldc 8388737
    //   3431: iastore
    //   3432: dup
    //   3433: bipush #6
    //   3435: ldc 8388609
    //   3437: iastore
    //   3438: dup
    //   3439: bipush #7
    //   3441: sipush #8193
    //   3444: iastore
    //   3445: dup
    //   3446: bipush #8
    //   3448: iconst_0
    //   3449: iastore
    //   3450: dup
    //   3451: bipush #9
    //   3453: ldc 8396800
    //   3455: iastore
    //   3456: dup
    //   3457: bipush #10
    //   3459: ldc 8396800
    //   3461: iastore
    //   3462: dup
    //   3463: bipush #11
    //   3465: ldc 8396929
    //   3467: iastore
    //   3468: dup
    //   3469: bipush #12
    //   3471: sipush #129
    //   3474: iastore
    //   3475: dup
    //   3476: bipush #13
    //   3478: iconst_0
    //   3479: iastore
    //   3480: dup
    //   3481: bipush #14
    //   3483: ldc 8388736
    //   3485: iastore
    //   3486: dup
    //   3487: bipush #15
    //   3489: ldc 8388609
    //   3491: iastore
    //   3492: dup
    //   3493: bipush #16
    //   3495: iconst_1
    //   3496: iastore
    //   3497: dup
    //   3498: bipush #17
    //   3500: sipush #8192
    //   3503: iastore
    //   3504: dup
    //   3505: bipush #18
    //   3507: ldc 8388608
    //   3509: iastore
    //   3510: dup
    //   3511: bipush #19
    //   3513: ldc 8396801
    //   3515: iastore
    //   3516: dup
    //   3517: bipush #20
    //   3519: sipush #128
    //   3522: iastore
    //   3523: dup
    //   3524: bipush #21
    //   3526: ldc 8388608
    //   3528: iastore
    //   3529: dup
    //   3530: bipush #22
    //   3532: sipush #8193
    //   3535: iastore
    //   3536: dup
    //   3537: bipush #23
    //   3539: sipush #8320
    //   3542: iastore
    //   3543: dup
    //   3544: bipush #24
    //   3546: ldc 8388737
    //   3548: iastore
    //   3549: dup
    //   3550: bipush #25
    //   3552: iconst_1
    //   3553: iastore
    //   3554: dup
    //   3555: bipush #26
    //   3557: sipush #8320
    //   3560: iastore
    //   3561: dup
    //   3562: bipush #27
    //   3564: ldc 8388736
    //   3566: iastore
    //   3567: dup
    //   3568: bipush #28
    //   3570: sipush #8192
    //   3573: iastore
    //   3574: dup
    //   3575: bipush #29
    //   3577: ldc 8396928
    //   3579: iastore
    //   3580: dup
    //   3581: bipush #30
    //   3583: ldc 8396929
    //   3585: iastore
    //   3586: dup
    //   3587: bipush #31
    //   3589: sipush #129
    //   3592: iastore
    //   3593: dup
    //   3594: bipush #32
    //   3596: ldc 8388736
    //   3598: iastore
    //   3599: dup
    //   3600: bipush #33
    //   3602: ldc 8388609
    //   3604: iastore
    //   3605: dup
    //   3606: bipush #34
    //   3608: ldc 8396800
    //   3610: iastore
    //   3611: dup
    //   3612: bipush #35
    //   3614: ldc 8396929
    //   3616: iastore
    //   3617: dup
    //   3618: bipush #36
    //   3620: sipush #129
    //   3623: iastore
    //   3624: dup
    //   3625: bipush #37
    //   3627: iconst_0
    //   3628: iastore
    //   3629: dup
    //   3630: bipush #38
    //   3632: iconst_0
    //   3633: iastore
    //   3634: dup
    //   3635: bipush #39
    //   3637: ldc 8396800
    //   3639: iastore
    //   3640: dup
    //   3641: bipush #40
    //   3643: sipush #8320
    //   3646: iastore
    //   3647: dup
    //   3648: bipush #41
    //   3650: ldc 8388736
    //   3652: iastore
    //   3653: dup
    //   3654: bipush #42
    //   3656: ldc 8388737
    //   3658: iastore
    //   3659: dup
    //   3660: bipush #43
    //   3662: iconst_1
    //   3663: iastore
    //   3664: dup
    //   3665: bipush #44
    //   3667: ldc 8396801
    //   3669: iastore
    //   3670: dup
    //   3671: bipush #45
    //   3673: sipush #8321
    //   3676: iastore
    //   3677: dup
    //   3678: bipush #46
    //   3680: sipush #8321
    //   3683: iastore
    //   3684: dup
    //   3685: bipush #47
    //   3687: sipush #128
    //   3690: iastore
    //   3691: dup
    //   3692: bipush #48
    //   3694: ldc 8396929
    //   3696: iastore
    //   3697: dup
    //   3698: bipush #49
    //   3700: sipush #129
    //   3703: iastore
    //   3704: dup
    //   3705: bipush #50
    //   3707: iconst_1
    //   3708: iastore
    //   3709: dup
    //   3710: bipush #51
    //   3712: sipush #8192
    //   3715: iastore
    //   3716: dup
    //   3717: bipush #52
    //   3719: ldc 8388609
    //   3721: iastore
    //   3722: dup
    //   3723: bipush #53
    //   3725: sipush #8193
    //   3728: iastore
    //   3729: dup
    //   3730: bipush #54
    //   3732: ldc 8396928
    //   3734: iastore
    //   3735: dup
    //   3736: bipush #55
    //   3738: ldc 8388737
    //   3740: iastore
    //   3741: dup
    //   3742: bipush #56
    //   3744: sipush #8193
    //   3747: iastore
    //   3748: dup
    //   3749: bipush #57
    //   3751: sipush #8320
    //   3754: iastore
    //   3755: dup
    //   3756: bipush #58
    //   3758: ldc 8388608
    //   3760: iastore
    //   3761: dup
    //   3762: bipush #59
    //   3764: ldc 8396801
    //   3766: iastore
    //   3767: dup
    //   3768: bipush #60
    //   3770: sipush #128
    //   3773: iastore
    //   3774: dup
    //   3775: bipush #61
    //   3777: ldc 8388608
    //   3779: iastore
    //   3780: dup
    //   3781: bipush #62
    //   3783: sipush #8192
    //   3786: iastore
    //   3787: dup
    //   3788: bipush #63
    //   3790: ldc 8396928
    //   3792: iastore
    //   3793: astore #12
    //   3795: bipush #64
    //   3797: newarray int
    //   3799: dup
    //   3800: iconst_0
    //   3801: sipush #256
    //   3804: iastore
    //   3805: dup
    //   3806: iconst_1
    //   3807: ldc 34078976
    //   3809: iastore
    //   3810: dup
    //   3811: iconst_2
    //   3812: ldc 34078720
    //   3814: iastore
    //   3815: dup
    //   3816: iconst_3
    //   3817: ldc 1107296512
    //   3819: iastore
    //   3820: dup
    //   3821: iconst_4
    //   3822: ldc 524288
    //   3824: iastore
    //   3825: dup
    //   3826: iconst_5
    //   3827: sipush #256
    //   3830: iastore
    //   3831: dup
    //   3832: bipush #6
    //   3834: ldc 1073741824
    //   3836: iastore
    //   3837: dup
    //   3838: bipush #7
    //   3840: ldc 34078720
    //   3842: iastore
    //   3843: dup
    //   3844: bipush #8
    //   3846: ldc 1074266368
    //   3848: iastore
    //   3849: dup
    //   3850: bipush #9
    //   3852: ldc 524288
    //   3854: iastore
    //   3855: dup
    //   3856: bipush #10
    //   3858: ldc 33554688
    //   3860: iastore
    //   3861: dup
    //   3862: bipush #11
    //   3864: ldc 1074266368
    //   3866: iastore
    //   3867: dup
    //   3868: bipush #12
    //   3870: ldc 1107296512
    //   3872: iastore
    //   3873: dup
    //   3874: bipush #13
    //   3876: ldc 1107820544
    //   3878: iastore
    //   3879: dup
    //   3880: bipush #14
    //   3882: ldc 524544
    //   3884: iastore
    //   3885: dup
    //   3886: bipush #15
    //   3888: ldc 1073741824
    //   3890: iastore
    //   3891: dup
    //   3892: bipush #16
    //   3894: ldc 33554432
    //   3896: iastore
    //   3897: dup
    //   3898: bipush #17
    //   3900: ldc 1074266112
    //   3902: iastore
    //   3903: dup
    //   3904: bipush #18
    //   3906: ldc 1074266112
    //   3908: iastore
    //   3909: dup
    //   3910: bipush #19
    //   3912: iconst_0
    //   3913: iastore
    //   3914: dup
    //   3915: bipush #20
    //   3917: ldc 1073742080
    //   3919: iastore
    //   3920: dup
    //   3921: bipush #21
    //   3923: ldc 1107820800
    //   3925: iastore
    //   3926: dup
    //   3927: bipush #22
    //   3929: ldc 1107820800
    //   3931: iastore
    //   3932: dup
    //   3933: bipush #23
    //   3935: ldc 33554688
    //   3937: iastore
    //   3938: dup
    //   3939: bipush #24
    //   3941: ldc 1107820544
    //   3943: iastore
    //   3944: dup
    //   3945: bipush #25
    //   3947: ldc 1073742080
    //   3949: iastore
    //   3950: dup
    //   3951: bipush #26
    //   3953: iconst_0
    //   3954: iastore
    //   3955: dup
    //   3956: bipush #27
    //   3958: ldc 1107296256
    //   3960: iastore
    //   3961: dup
    //   3962: bipush #28
    //   3964: ldc 34078976
    //   3966: iastore
    //   3967: dup
    //   3968: bipush #29
    //   3970: ldc 33554432
    //   3972: iastore
    //   3973: dup
    //   3974: bipush #30
    //   3976: ldc 1107296256
    //   3978: iastore
    //   3979: dup
    //   3980: bipush #31
    //   3982: ldc 524544
    //   3984: iastore
    //   3985: dup
    //   3986: bipush #32
    //   3988: ldc 524288
    //   3990: iastore
    //   3991: dup
    //   3992: bipush #33
    //   3994: ldc 1107296512
    //   3996: iastore
    //   3997: dup
    //   3998: bipush #34
    //   4000: sipush #256
    //   4003: iastore
    //   4004: dup
    //   4005: bipush #35
    //   4007: ldc 33554432
    //   4009: iastore
    //   4010: dup
    //   4011: bipush #36
    //   4013: ldc 1073741824
    //   4015: iastore
    //   4016: dup
    //   4017: bipush #37
    //   4019: ldc 34078720
    //   4021: iastore
    //   4022: dup
    //   4023: bipush #38
    //   4025: ldc 1107296512
    //   4027: iastore
    //   4028: dup
    //   4029: bipush #39
    //   4031: ldc 1074266368
    //   4033: iastore
    //   4034: dup
    //   4035: bipush #40
    //   4037: ldc 33554688
    //   4039: iastore
    //   4040: dup
    //   4041: bipush #41
    //   4043: ldc 1073741824
    //   4045: iastore
    //   4046: dup
    //   4047: bipush #42
    //   4049: ldc 1107820544
    //   4051: iastore
    //   4052: dup
    //   4053: bipush #43
    //   4055: ldc 34078976
    //   4057: iastore
    //   4058: dup
    //   4059: bipush #44
    //   4061: ldc 1074266368
    //   4063: iastore
    //   4064: dup
    //   4065: bipush #45
    //   4067: sipush #256
    //   4070: iastore
    //   4071: dup
    //   4072: bipush #46
    //   4074: ldc 33554432
    //   4076: iastore
    //   4077: dup
    //   4078: bipush #47
    //   4080: ldc 1107820544
    //   4082: iastore
    //   4083: dup
    //   4084: bipush #48
    //   4086: ldc 1107820800
    //   4088: iastore
    //   4089: dup
    //   4090: bipush #49
    //   4092: ldc 524544
    //   4094: iastore
    //   4095: dup
    //   4096: bipush #50
    //   4098: ldc 1107296256
    //   4100: iastore
    //   4101: dup
    //   4102: bipush #51
    //   4104: ldc 1107820800
    //   4106: iastore
    //   4107: dup
    //   4108: bipush #52
    //   4110: ldc 34078720
    //   4112: iastore
    //   4113: dup
    //   4114: bipush #53
    //   4116: iconst_0
    //   4117: iastore
    //   4118: dup
    //   4119: bipush #54
    //   4121: ldc 1074266112
    //   4123: iastore
    //   4124: dup
    //   4125: bipush #55
    //   4127: ldc 1107296256
    //   4129: iastore
    //   4130: dup
    //   4131: bipush #56
    //   4133: ldc 524544
    //   4135: iastore
    //   4136: dup
    //   4137: bipush #57
    //   4139: ldc 33554688
    //   4141: iastore
    //   4142: dup
    //   4143: bipush #58
    //   4145: ldc 1073742080
    //   4147: iastore
    //   4148: dup
    //   4149: bipush #59
    //   4151: ldc 524288
    //   4153: iastore
    //   4154: dup
    //   4155: bipush #60
    //   4157: iconst_0
    //   4158: iastore
    //   4159: dup
    //   4160: bipush #61
    //   4162: ldc 1074266112
    //   4164: iastore
    //   4165: dup
    //   4166: bipush #62
    //   4168: ldc 34078976
    //   4170: iastore
    //   4171: dup
    //   4172: bipush #63
    //   4174: ldc 1073742080
    //   4176: iastore
    //   4177: astore #13
    //   4179: bipush #64
    //   4181: newarray int
    //   4183: dup
    //   4184: iconst_0
    //   4185: ldc 536870928
    //   4187: iastore
    //   4188: dup
    //   4189: iconst_1
    //   4190: ldc 541065216
    //   4192: iastore
    //   4193: dup
    //   4194: iconst_2
    //   4195: sipush #16384
    //   4198: iastore
    //   4199: dup
    //   4200: iconst_3
    //   4201: ldc 541081616
    //   4203: iastore
    //   4204: dup
    //   4205: iconst_4
    //   4206: ldc 541065216
    //   4208: iastore
    //   4209: dup
    //   4210: iconst_5
    //   4211: bipush #16
    //   4213: iastore
    //   4214: dup
    //   4215: bipush #6
    //   4217: ldc 541081616
    //   4219: iastore
    //   4220: dup
    //   4221: bipush #7
    //   4223: ldc 4194304
    //   4225: iastore
    //   4226: dup
    //   4227: bipush #8
    //   4229: ldc 536887296
    //   4231: iastore
    //   4232: dup
    //   4233: bipush #9
    //   4235: ldc 4210704
    //   4237: iastore
    //   4238: dup
    //   4239: bipush #10
    //   4241: ldc 4194304
    //   4243: iastore
    //   4244: dup
    //   4245: bipush #11
    //   4247: ldc 536870928
    //   4249: iastore
    //   4250: dup
    //   4251: bipush #12
    //   4253: ldc 4194320
    //   4255: iastore
    //   4256: dup
    //   4257: bipush #13
    //   4259: ldc 536887296
    //   4261: iastore
    //   4262: dup
    //   4263: bipush #14
    //   4265: ldc 536870912
    //   4267: iastore
    //   4268: dup
    //   4269: bipush #15
    //   4271: sipush #16400
    //   4274: iastore
    //   4275: dup
    //   4276: bipush #16
    //   4278: iconst_0
    //   4279: iastore
    //   4280: dup
    //   4281: bipush #17
    //   4283: ldc 4194320
    //   4285: iastore
    //   4286: dup
    //   4287: bipush #18
    //   4289: ldc 536887312
    //   4291: iastore
    //   4292: dup
    //   4293: bipush #19
    //   4295: sipush #16384
    //   4298: iastore
    //   4299: dup
    //   4300: bipush #20
    //   4302: ldc 4210688
    //   4304: iastore
    //   4305: dup
    //   4306: bipush #21
    //   4308: ldc 536887312
    //   4310: iastore
    //   4311: dup
    //   4312: bipush #22
    //   4314: bipush #16
    //   4316: iastore
    //   4317: dup
    //   4318: bipush #23
    //   4320: ldc 541065232
    //   4322: iastore
    //   4323: dup
    //   4324: bipush #24
    //   4326: ldc 541065232
    //   4328: iastore
    //   4329: dup
    //   4330: bipush #25
    //   4332: iconst_0
    //   4333: iastore
    //   4334: dup
    //   4335: bipush #26
    //   4337: ldc 4210704
    //   4339: iastore
    //   4340: dup
    //   4341: bipush #27
    //   4343: ldc 541081600
    //   4345: iastore
    //   4346: dup
    //   4347: bipush #28
    //   4349: sipush #16400
    //   4352: iastore
    //   4353: dup
    //   4354: bipush #29
    //   4356: ldc 4210688
    //   4358: iastore
    //   4359: dup
    //   4360: bipush #30
    //   4362: ldc 541081600
    //   4364: iastore
    //   4365: dup
    //   4366: bipush #31
    //   4368: ldc 536870912
    //   4370: iastore
    //   4371: dup
    //   4372: bipush #32
    //   4374: ldc 536887296
    //   4376: iastore
    //   4377: dup
    //   4378: bipush #33
    //   4380: bipush #16
    //   4382: iastore
    //   4383: dup
    //   4384: bipush #34
    //   4386: ldc 541065232
    //   4388: iastore
    //   4389: dup
    //   4390: bipush #35
    //   4392: ldc 4210688
    //   4394: iastore
    //   4395: dup
    //   4396: bipush #36
    //   4398: ldc 541081616
    //   4400: iastore
    //   4401: dup
    //   4402: bipush #37
    //   4404: ldc 4194304
    //   4406: iastore
    //   4407: dup
    //   4408: bipush #38
    //   4410: sipush #16400
    //   4413: iastore
    //   4414: dup
    //   4415: bipush #39
    //   4417: ldc 536870928
    //   4419: iastore
    //   4420: dup
    //   4421: bipush #40
    //   4423: ldc 4194304
    //   4425: iastore
    //   4426: dup
    //   4427: bipush #41
    //   4429: ldc 536887296
    //   4431: iastore
    //   4432: dup
    //   4433: bipush #42
    //   4435: ldc 536870912
    //   4437: iastore
    //   4438: dup
    //   4439: bipush #43
    //   4441: sipush #16400
    //   4444: iastore
    //   4445: dup
    //   4446: bipush #44
    //   4448: ldc 536870928
    //   4450: iastore
    //   4451: dup
    //   4452: bipush #45
    //   4454: ldc 541081616
    //   4456: iastore
    //   4457: dup
    //   4458: bipush #46
    //   4460: ldc 4210688
    //   4462: iastore
    //   4463: dup
    //   4464: bipush #47
    //   4466: ldc 541065216
    //   4468: iastore
    //   4469: dup
    //   4470: bipush #48
    //   4472: ldc 4210704
    //   4474: iastore
    //   4475: dup
    //   4476: bipush #49
    //   4478: ldc 541081600
    //   4480: iastore
    //   4481: dup
    //   4482: bipush #50
    //   4484: iconst_0
    //   4485: iastore
    //   4486: dup
    //   4487: bipush #51
    //   4489: ldc 541065232
    //   4491: iastore
    //   4492: dup
    //   4493: bipush #52
    //   4495: bipush #16
    //   4497: iastore
    //   4498: dup
    //   4499: bipush #53
    //   4501: sipush #16384
    //   4504: iastore
    //   4505: dup
    //   4506: bipush #54
    //   4508: ldc 541065216
    //   4510: iastore
    //   4511: dup
    //   4512: bipush #55
    //   4514: ldc 4210704
    //   4516: iastore
    //   4517: dup
    //   4518: bipush #56
    //   4520: sipush #16384
    //   4523: iastore
    //   4524: dup
    //   4525: bipush #57
    //   4527: ldc 4194320
    //   4529: iastore
    //   4530: dup
    //   4531: bipush #58
    //   4533: ldc 536887312
    //   4535: iastore
    //   4536: dup
    //   4537: bipush #59
    //   4539: iconst_0
    //   4540: iastore
    //   4541: dup
    //   4542: bipush #60
    //   4544: ldc 541081600
    //   4546: iastore
    //   4547: dup
    //   4548: bipush #61
    //   4550: ldc 536870912
    //   4552: iastore
    //   4553: dup
    //   4554: bipush #62
    //   4556: ldc 4194320
    //   4558: iastore
    //   4559: dup
    //   4560: bipush #63
    //   4562: ldc 536887312
    //   4564: iastore
    //   4565: astore #14
    //   4567: bipush #64
    //   4569: newarray int
    //   4571: dup
    //   4572: iconst_0
    //   4573: ldc 2097152
    //   4575: iastore
    //   4576: dup
    //   4577: iconst_1
    //   4578: ldc 69206018
    //   4580: iastore
    //   4581: dup
    //   4582: iconst_2
    //   4583: ldc 67110914
    //   4585: iastore
    //   4586: dup
    //   4587: iconst_3
    //   4588: iconst_0
    //   4589: iastore
    //   4590: dup
    //   4591: iconst_4
    //   4592: sipush #2048
    //   4595: iastore
    //   4596: dup
    //   4597: iconst_5
    //   4598: ldc 67110914
    //   4600: iastore
    //   4601: dup
    //   4602: bipush #6
    //   4604: ldc 2099202
    //   4606: iastore
    //   4607: dup
    //   4608: bipush #7
    //   4610: ldc 69208064
    //   4612: iastore
    //   4613: dup
    //   4614: bipush #8
    //   4616: ldc 69208066
    //   4618: iastore
    //   4619: dup
    //   4620: bipush #9
    //   4622: ldc 2097152
    //   4624: iastore
    //   4625: dup
    //   4626: bipush #10
    //   4628: iconst_0
    //   4629: iastore
    //   4630: dup
    //   4631: bipush #11
    //   4633: ldc 67108866
    //   4635: iastore
    //   4636: dup
    //   4637: bipush #12
    //   4639: iconst_2
    //   4640: iastore
    //   4641: dup
    //   4642: bipush #13
    //   4644: ldc 67108864
    //   4646: iastore
    //   4647: dup
    //   4648: bipush #14
    //   4650: ldc 69206018
    //   4652: iastore
    //   4653: dup
    //   4654: bipush #15
    //   4656: sipush #2050
    //   4659: iastore
    //   4660: dup
    //   4661: bipush #16
    //   4663: ldc 67110912
    //   4665: iastore
    //   4666: dup
    //   4667: bipush #17
    //   4669: ldc 2099202
    //   4671: iastore
    //   4672: dup
    //   4673: bipush #18
    //   4675: ldc 2097154
    //   4677: iastore
    //   4678: dup
    //   4679: bipush #19
    //   4681: ldc 67110912
    //   4683: iastore
    //   4684: dup
    //   4685: bipush #20
    //   4687: ldc 67108866
    //   4689: iastore
    //   4690: dup
    //   4691: bipush #21
    //   4693: ldc 69206016
    //   4695: iastore
    //   4696: dup
    //   4697: bipush #22
    //   4699: ldc 69208064
    //   4701: iastore
    //   4702: dup
    //   4703: bipush #23
    //   4705: ldc 2097154
    //   4707: iastore
    //   4708: dup
    //   4709: bipush #24
    //   4711: ldc 69206016
    //   4713: iastore
    //   4714: dup
    //   4715: bipush #25
    //   4717: sipush #2048
    //   4720: iastore
    //   4721: dup
    //   4722: bipush #26
    //   4724: sipush #2050
    //   4727: iastore
    //   4728: dup
    //   4729: bipush #27
    //   4731: ldc 69208066
    //   4733: iastore
    //   4734: dup
    //   4735: bipush #28
    //   4737: ldc 2099200
    //   4739: iastore
    //   4740: dup
    //   4741: bipush #29
    //   4743: iconst_2
    //   4744: iastore
    //   4745: dup
    //   4746: bipush #30
    //   4748: ldc 67108864
    //   4750: iastore
    //   4751: dup
    //   4752: bipush #31
    //   4754: ldc 2099200
    //   4756: iastore
    //   4757: dup
    //   4758: bipush #32
    //   4760: ldc 67108864
    //   4762: iastore
    //   4763: dup
    //   4764: bipush #33
    //   4766: ldc 2099200
    //   4768: iastore
    //   4769: dup
    //   4770: bipush #34
    //   4772: ldc 2097152
    //   4774: iastore
    //   4775: dup
    //   4776: bipush #35
    //   4778: ldc 67110914
    //   4780: iastore
    //   4781: dup
    //   4782: bipush #36
    //   4784: ldc 67110914
    //   4786: iastore
    //   4787: dup
    //   4788: bipush #37
    //   4790: ldc 69206018
    //   4792: iastore
    //   4793: dup
    //   4794: bipush #38
    //   4796: ldc 69206018
    //   4798: iastore
    //   4799: dup
    //   4800: bipush #39
    //   4802: iconst_2
    //   4803: iastore
    //   4804: dup
    //   4805: bipush #40
    //   4807: ldc 2097154
    //   4809: iastore
    //   4810: dup
    //   4811: bipush #41
    //   4813: ldc 67108864
    //   4815: iastore
    //   4816: dup
    //   4817: bipush #42
    //   4819: ldc 67110912
    //   4821: iastore
    //   4822: dup
    //   4823: bipush #43
    //   4825: ldc 2097152
    //   4827: iastore
    //   4828: dup
    //   4829: bipush #44
    //   4831: ldc 69208064
    //   4833: iastore
    //   4834: dup
    //   4835: bipush #45
    //   4837: sipush #2050
    //   4840: iastore
    //   4841: dup
    //   4842: bipush #46
    //   4844: ldc 2099202
    //   4846: iastore
    //   4847: dup
    //   4848: bipush #47
    //   4850: ldc 69208064
    //   4852: iastore
    //   4853: dup
    //   4854: bipush #48
    //   4856: sipush #2050
    //   4859: iastore
    //   4860: dup
    //   4861: bipush #49
    //   4863: ldc 67108866
    //   4865: iastore
    //   4866: dup
    //   4867: bipush #50
    //   4869: ldc 69208066
    //   4871: iastore
    //   4872: dup
    //   4873: bipush #51
    //   4875: ldc 69206016
    //   4877: iastore
    //   4878: dup
    //   4879: bipush #52
    //   4881: ldc 2099200
    //   4883: iastore
    //   4884: dup
    //   4885: bipush #53
    //   4887: iconst_0
    //   4888: iastore
    //   4889: dup
    //   4890: bipush #54
    //   4892: iconst_2
    //   4893: iastore
    //   4894: dup
    //   4895: bipush #55
    //   4897: ldc 69208066
    //   4899: iastore
    //   4900: dup
    //   4901: bipush #56
    //   4903: iconst_0
    //   4904: iastore
    //   4905: dup
    //   4906: bipush #57
    //   4908: ldc 2099202
    //   4910: iastore
    //   4911: dup
    //   4912: bipush #58
    //   4914: ldc 69206016
    //   4916: iastore
    //   4917: dup
    //   4918: bipush #59
    //   4920: sipush #2048
    //   4923: iastore
    //   4924: dup
    //   4925: bipush #60
    //   4927: ldc 67108866
    //   4929: iastore
    //   4930: dup
    //   4931: bipush #61
    //   4933: ldc 67110912
    //   4935: iastore
    //   4936: dup
    //   4937: bipush #62
    //   4939: sipush #2048
    //   4942: iastore
    //   4943: dup
    //   4944: bipush #63
    //   4946: ldc 2097154
    //   4948: iastore
    //   4949: astore #15
    //   4951: bipush #64
    //   4953: newarray int
    //   4955: dup
    //   4956: iconst_0
    //   4957: ldc 268439616
    //   4959: iastore
    //   4960: dup
    //   4961: iconst_1
    //   4962: sipush #4096
    //   4965: iastore
    //   4966: dup
    //   4967: iconst_2
    //   4968: ldc 262144
    //   4970: iastore
    //   4971: dup
    //   4972: iconst_3
    //   4973: ldc 268701760
    //   4975: iastore
    //   4976: dup
    //   4977: iconst_4
    //   4978: ldc 268435456
    //   4980: iastore
    //   4981: dup
    //   4982: iconst_5
    //   4983: ldc 268439616
    //   4985: iastore
    //   4986: dup
    //   4987: bipush #6
    //   4989: bipush #64
    //   4991: iastore
    //   4992: dup
    //   4993: bipush #7
    //   4995: ldc 268435456
    //   4997: iastore
    //   4998: dup
    //   4999: bipush #8
    //   5001: ldc 262208
    //   5003: iastore
    //   5004: dup
    //   5005: bipush #9
    //   5007: ldc 268697600
    //   5009: iastore
    //   5010: dup
    //   5011: bipush #10
    //   5013: ldc 268701760
    //   5015: iastore
    //   5016: dup
    //   5017: bipush #11
    //   5019: ldc 266240
    //   5021: iastore
    //   5022: dup
    //   5023: bipush #12
    //   5025: ldc 268701696
    //   5027: iastore
    //   5028: dup
    //   5029: bipush #13
    //   5031: ldc 266304
    //   5033: iastore
    //   5034: dup
    //   5035: bipush #14
    //   5037: sipush #4096
    //   5040: iastore
    //   5041: dup
    //   5042: bipush #15
    //   5044: bipush #64
    //   5046: iastore
    //   5047: dup
    //   5048: bipush #16
    //   5050: ldc 268697600
    //   5052: iastore
    //   5053: dup
    //   5054: bipush #17
    //   5056: ldc 268435520
    //   5058: iastore
    //   5059: dup
    //   5060: bipush #18
    //   5062: ldc 268439552
    //   5064: iastore
    //   5065: dup
    //   5066: bipush #19
    //   5068: sipush #4160
    //   5071: iastore
    //   5072: dup
    //   5073: bipush #20
    //   5075: ldc 266240
    //   5077: iastore
    //   5078: dup
    //   5079: bipush #21
    //   5081: ldc 262208
    //   5083: iastore
    //   5084: dup
    //   5085: bipush #22
    //   5087: ldc 268697664
    //   5089: iastore
    //   5090: dup
    //   5091: bipush #23
    //   5093: ldc 268701696
    //   5095: iastore
    //   5096: dup
    //   5097: bipush #24
    //   5099: sipush #4160
    //   5102: iastore
    //   5103: dup
    //   5104: bipush #25
    //   5106: iconst_0
    //   5107: iastore
    //   5108: dup
    //   5109: bipush #26
    //   5111: iconst_0
    //   5112: iastore
    //   5113: dup
    //   5114: bipush #27
    //   5116: ldc 268697664
    //   5118: iastore
    //   5119: dup
    //   5120: bipush #28
    //   5122: ldc 268435520
    //   5124: iastore
    //   5125: dup
    //   5126: bipush #29
    //   5128: ldc 268439552
    //   5130: iastore
    //   5131: dup
    //   5132: bipush #30
    //   5134: ldc 266304
    //   5136: iastore
    //   5137: dup
    //   5138: bipush #31
    //   5140: ldc 262144
    //   5142: iastore
    //   5143: dup
    //   5144: bipush #32
    //   5146: ldc 266304
    //   5148: iastore
    //   5149: dup
    //   5150: bipush #33
    //   5152: ldc 262144
    //   5154: iastore
    //   5155: dup
    //   5156: bipush #34
    //   5158: ldc 268701696
    //   5160: iastore
    //   5161: dup
    //   5162: bipush #35
    //   5164: sipush #4096
    //   5167: iastore
    //   5168: dup
    //   5169: bipush #36
    //   5171: bipush #64
    //   5173: iastore
    //   5174: dup
    //   5175: bipush #37
    //   5177: ldc 268697664
    //   5179: iastore
    //   5180: dup
    //   5181: bipush #38
    //   5183: sipush #4096
    //   5186: iastore
    //   5187: dup
    //   5188: bipush #39
    //   5190: ldc 266304
    //   5192: iastore
    //   5193: dup
    //   5194: bipush #40
    //   5196: ldc 268439552
    //   5198: iastore
    //   5199: dup
    //   5200: bipush #41
    //   5202: bipush #64
    //   5204: iastore
    //   5205: dup
    //   5206: bipush #42
    //   5208: ldc 268435520
    //   5210: iastore
    //   5211: dup
    //   5212: bipush #43
    //   5214: ldc 268697600
    //   5216: iastore
    //   5217: dup
    //   5218: bipush #44
    //   5220: ldc 268697664
    //   5222: iastore
    //   5223: dup
    //   5224: bipush #45
    //   5226: ldc 268435456
    //   5228: iastore
    //   5229: dup
    //   5230: bipush #46
    //   5232: ldc 262144
    //   5234: iastore
    //   5235: dup
    //   5236: bipush #47
    //   5238: ldc 268439616
    //   5240: iastore
    //   5241: dup
    //   5242: bipush #48
    //   5244: iconst_0
    //   5245: iastore
    //   5246: dup
    //   5247: bipush #49
    //   5249: ldc 268701760
    //   5251: iastore
    //   5252: dup
    //   5253: bipush #50
    //   5255: ldc 262208
    //   5257: iastore
    //   5258: dup
    //   5259: bipush #51
    //   5261: ldc 268435520
    //   5263: iastore
    //   5264: dup
    //   5265: bipush #52
    //   5267: ldc 268697600
    //   5269: iastore
    //   5270: dup
    //   5271: bipush #53
    //   5273: ldc 268439552
    //   5275: iastore
    //   5276: dup
    //   5277: bipush #54
    //   5279: ldc 268439616
    //   5281: iastore
    //   5282: dup
    //   5283: bipush #55
    //   5285: iconst_0
    //   5286: iastore
    //   5287: dup
    //   5288: bipush #56
    //   5290: ldc 268701760
    //   5292: iastore
    //   5293: dup
    //   5294: bipush #57
    //   5296: ldc 266240
    //   5298: iastore
    //   5299: dup
    //   5300: bipush #58
    //   5302: ldc 266240
    //   5304: iastore
    //   5305: dup
    //   5306: bipush #59
    //   5308: sipush #4160
    //   5311: iastore
    //   5312: dup
    //   5313: bipush #60
    //   5315: sipush #4160
    //   5318: iastore
    //   5319: dup
    //   5320: bipush #61
    //   5322: ldc 262208
    //   5324: iastore
    //   5325: dup
    //   5326: bipush #62
    //   5328: ldc 268435456
    //   5330: iastore
    //   5331: dup
    //   5332: bipush #63
    //   5334: ldc 268701696
    //   5336: iastore
    //   5337: astore #16
    //   5339: aload #4
    //   5341: arraylength
    //   5342: istore #17
    //   5344: iconst_2
    //   5345: newarray int
    //   5347: astore #18
    //   5349: iload #17
    //   5351: newarray byte
    //   5353: astore #5
    //   5355: iload #17
    //   5357: bipush #8
    //   5359: idiv
    //   5360: istore #19
    //   5362: iconst_0
    //   5363: istore #20
    //   5365: iload #20
    //   5367: iload #19
    //   5369: if_icmpge -> 6287
    //   5372: iload #20
    //   5374: bipush #8
    //   5376: imul
    //   5377: istore #21
    //   5379: iconst_0
    //   5380: istore #22
    //   5382: iload #22
    //   5384: iconst_2
    //   5385: if_icmpge -> 5474
    //   5388: aload #18
    //   5390: iload #22
    //   5392: aload #4
    //   5394: iload #21
    //   5396: iload #22
    //   5398: iconst_4
    //   5399: imul
    //   5400: iadd
    //   5401: baload
    //   5402: sipush #255
    //   5405: iand
    //   5406: bipush #24
    //   5408: ishl
    //   5409: aload #4
    //   5411: iload #21
    //   5413: iload #22
    //   5415: iconst_4
    //   5416: imul
    //   5417: iadd
    //   5418: iconst_1
    //   5419: iadd
    //   5420: baload
    //   5421: sipush #255
    //   5424: iand
    //   5425: bipush #16
    //   5427: ishl
    //   5428: ior
    //   5429: aload #4
    //   5431: iload #21
    //   5433: iload #22
    //   5435: iconst_4
    //   5436: imul
    //   5437: iadd
    //   5438: iconst_2
    //   5439: iadd
    //   5440: baload
    //   5441: sipush #255
    //   5444: iand
    //   5445: bipush #8
    //   5447: ishl
    //   5448: ior
    //   5449: aload #4
    //   5451: iload #21
    //   5453: iload #22
    //   5455: iconst_4
    //   5456: imul
    //   5457: iadd
    //   5458: iconst_3
    //   5459: iadd
    //   5460: baload
    //   5461: sipush #255
    //   5464: iand
    //   5465: ior
    //   5466: iastore
    //   5467: iinc #22, 1
    //   5470: iload_2
    //   5471: ifeq -> 5382
    //   5474: iconst_0
    //   5475: istore #27
    //   5477: aload #18
    //   5479: iconst_0
    //   5480: iaload
    //   5481: istore #25
    //   5483: aload #18
    //   5485: iconst_1
    //   5486: iaload
    //   5487: istore #24
    //   5489: iload #25
    //   5491: iconst_4
    //   5492: iushr
    //   5493: iload #24
    //   5495: ixor
    //   5496: ldc 252645135
    //   5498: iand
    //   5499: istore #23
    //   5501: iload #24
    //   5503: iload #23
    //   5505: ixor
    //   5506: istore #24
    //   5508: iload #25
    //   5510: iload #23
    //   5512: iconst_4
    //   5513: ishl
    //   5514: ixor
    //   5515: istore #25
    //   5517: iload #25
    //   5519: bipush #16
    //   5521: iushr
    //   5522: iload #24
    //   5524: ixor
    //   5525: ldc 65535
    //   5527: iand
    //   5528: istore #23
    //   5530: iload #24
    //   5532: iload #23
    //   5534: ixor
    //   5535: istore #24
    //   5537: iload #25
    //   5539: iload #23
    //   5541: bipush #16
    //   5543: ishl
    //   5544: ixor
    //   5545: istore #25
    //   5547: iload #24
    //   5549: iconst_2
    //   5550: iushr
    //   5551: iload #25
    //   5553: ixor
    //   5554: ldc 858993459
    //   5556: iand
    //   5557: istore #23
    //   5559: iload #25
    //   5561: iload #23
    //   5563: ixor
    //   5564: istore #25
    //   5566: iload #24
    //   5568: iload #23
    //   5570: iconst_2
    //   5571: ishl
    //   5572: ixor
    //   5573: istore #24
    //   5575: iload #24
    //   5577: bipush #8
    //   5579: iushr
    //   5580: iload #25
    //   5582: ixor
    //   5583: ldc 16711935
    //   5585: iand
    //   5586: istore #23
    //   5588: iload #25
    //   5590: iload #23
    //   5592: ixor
    //   5593: istore #25
    //   5595: iload #24
    //   5597: iload #23
    //   5599: bipush #8
    //   5601: ishl
    //   5602: ixor
    //   5603: istore #24
    //   5605: iload #24
    //   5607: iconst_1
    //   5608: ishl
    //   5609: iload #24
    //   5611: bipush #31
    //   5613: iushr
    //   5614: iconst_1
    //   5615: iand
    //   5616: ior
    //   5617: istore #24
    //   5619: iload #25
    //   5621: iload #24
    //   5623: ixor
    //   5624: ldc -1431655766
    //   5626: iand
    //   5627: istore #23
    //   5629: iload #25
    //   5631: iload #23
    //   5633: ixor
    //   5634: istore #25
    //   5636: iload #24
    //   5638: iload #23
    //   5640: ixor
    //   5641: istore #24
    //   5643: iload #25
    //   5645: iconst_1
    //   5646: ishl
    //   5647: iload #25
    //   5649: bipush #31
    //   5651: iushr
    //   5652: iconst_1
    //   5653: iand
    //   5654: ior
    //   5655: istore #25
    //   5657: iconst_0
    //   5658: istore #26
    //   5660: iload #26
    //   5662: bipush #8
    //   5664: if_icmpge -> 6002
    //   5667: iload #24
    //   5669: bipush #28
    //   5671: ishl
    //   5672: iload #24
    //   5674: iconst_4
    //   5675: iushr
    //   5676: ior
    //   5677: istore #23
    //   5679: iload #23
    //   5681: aload #6
    //   5683: iload #27
    //   5685: iinc #27, 1
    //   5688: iaload
    //   5689: ixor
    //   5690: istore #23
    //   5692: aload #15
    //   5694: iload #23
    //   5696: bipush #63
    //   5698: iand
    //   5699: iaload
    //   5700: istore #22
    //   5702: iload #22
    //   5704: aload #13
    //   5706: iload #23
    //   5708: bipush #8
    //   5710: iushr
    //   5711: bipush #63
    //   5713: iand
    //   5714: iaload
    //   5715: ior
    //   5716: istore #22
    //   5718: iload #22
    //   5720: aload #11
    //   5722: iload #23
    //   5724: bipush #16
    //   5726: iushr
    //   5727: bipush #63
    //   5729: iand
    //   5730: iaload
    //   5731: ior
    //   5732: istore #22
    //   5734: iload #22
    //   5736: aload #9
    //   5738: iload #23
    //   5740: bipush #24
    //   5742: iushr
    //   5743: bipush #63
    //   5745: iand
    //   5746: iaload
    //   5747: ior
    //   5748: istore #22
    //   5750: iload #24
    //   5752: aload #6
    //   5754: iload #27
    //   5756: iinc #27, 1
    //   5759: iaload
    //   5760: ixor
    //   5761: istore #23
    //   5763: iload #22
    //   5765: aload #16
    //   5767: iload #23
    //   5769: bipush #63
    //   5771: iand
    //   5772: iaload
    //   5773: ior
    //   5774: istore #22
    //   5776: iload #22
    //   5778: aload #14
    //   5780: iload #23
    //   5782: bipush #8
    //   5784: iushr
    //   5785: bipush #63
    //   5787: iand
    //   5788: iaload
    //   5789: ior
    //   5790: istore #22
    //   5792: iload #22
    //   5794: aload #12
    //   5796: iload #23
    //   5798: bipush #16
    //   5800: iushr
    //   5801: bipush #63
    //   5803: iand
    //   5804: iaload
    //   5805: ior
    //   5806: istore #22
    //   5808: iload #22
    //   5810: aload #10
    //   5812: iload #23
    //   5814: bipush #24
    //   5816: iushr
    //   5817: bipush #63
    //   5819: iand
    //   5820: iaload
    //   5821: ior
    //   5822: istore #22
    //   5824: iload #25
    //   5826: iload #22
    //   5828: ixor
    //   5829: istore #25
    //   5831: iload #25
    //   5833: bipush #28
    //   5835: ishl
    //   5836: iload #25
    //   5838: iconst_4
    //   5839: iushr
    //   5840: ior
    //   5841: istore #23
    //   5843: iload #23
    //   5845: aload #6
    //   5847: iload #27
    //   5849: iinc #27, 1
    //   5852: iaload
    //   5853: ixor
    //   5854: istore #23
    //   5856: aload #15
    //   5858: iload #23
    //   5860: bipush #63
    //   5862: iand
    //   5863: iaload
    //   5864: istore #22
    //   5866: iload #22
    //   5868: aload #13
    //   5870: iload #23
    //   5872: bipush #8
    //   5874: iushr
    //   5875: bipush #63
    //   5877: iand
    //   5878: iaload
    //   5879: ior
    //   5880: istore #22
    //   5882: iload #22
    //   5884: aload #11
    //   5886: iload #23
    //   5888: bipush #16
    //   5890: iushr
    //   5891: bipush #63
    //   5893: iand
    //   5894: iaload
    //   5895: ior
    //   5896: istore #22
    //   5898: iload #22
    //   5900: aload #9
    //   5902: iload #23
    //   5904: bipush #24
    //   5906: iushr
    //   5907: bipush #63
    //   5909: iand
    //   5910: iaload
    //   5911: ior
    //   5912: istore #22
    //   5914: iload #25
    //   5916: aload #6
    //   5918: iload #27
    //   5920: iinc #27, 1
    //   5923: iaload
    //   5924: ixor
    //   5925: istore #23
    //   5927: iload #22
    //   5929: aload #16
    //   5931: iload #23
    //   5933: bipush #63
    //   5935: iand
    //   5936: iaload
    //   5937: ior
    //   5938: istore #22
    //   5940: iload #22
    //   5942: aload #14
    //   5944: iload #23
    //   5946: bipush #8
    //   5948: iushr
    //   5949: bipush #63
    //   5951: iand
    //   5952: iaload
    //   5953: ior
    //   5954: istore #22
    //   5956: iload #22
    //   5958: aload #12
    //   5960: iload #23
    //   5962: bipush #16
    //   5964: iushr
    //   5965: bipush #63
    //   5967: iand
    //   5968: iaload
    //   5969: ior
    //   5970: istore #22
    //   5972: iload #22
    //   5974: aload #10
    //   5976: iload #23
    //   5978: bipush #24
    //   5980: iushr
    //   5981: bipush #63
    //   5983: iand
    //   5984: iaload
    //   5985: ior
    //   5986: istore #22
    //   5988: iload #24
    //   5990: iload #22
    //   5992: ixor
    //   5993: istore #24
    //   5995: iinc #26, 1
    //   5998: iload_2
    //   5999: ifeq -> 5660
    //   6002: iload #24
    //   6004: bipush #31
    //   6006: ishl
    //   6007: iload #24
    //   6009: iconst_1
    //   6010: iushr
    //   6011: ior
    //   6012: istore #24
    //   6014: iload #25
    //   6016: iload #24
    //   6018: ixor
    //   6019: ldc -1431655766
    //   6021: iand
    //   6022: istore #23
    //   6024: iload #25
    //   6026: iload #23
    //   6028: ixor
    //   6029: istore #25
    //   6031: iload #24
    //   6033: iload #23
    //   6035: ixor
    //   6036: istore #24
    //   6038: iload #25
    //   6040: bipush #31
    //   6042: ishl
    //   6043: iload #25
    //   6045: iconst_1
    //   6046: iushr
    //   6047: ior
    //   6048: istore #25
    //   6050: iload #25
    //   6052: bipush #8
    //   6054: iushr
    //   6055: iload #24
    //   6057: ixor
    //   6058: ldc 16711935
    //   6060: iand
    //   6061: istore #23
    //   6063: iload #24
    //   6065: iload #23
    //   6067: ixor
    //   6068: istore #24
    //   6070: iload #25
    //   6072: iload #23
    //   6074: bipush #8
    //   6076: ishl
    //   6077: ixor
    //   6078: istore #25
    //   6080: iload #25
    //   6082: iconst_2
    //   6083: iushr
    //   6084: iload #24
    //   6086: ixor
    //   6087: ldc 858993459
    //   6089: iand
    //   6090: istore #23
    //   6092: iload #24
    //   6094: iload #23
    //   6096: ixor
    //   6097: istore #24
    //   6099: iload #25
    //   6101: iload #23
    //   6103: iconst_2
    //   6104: ishl
    //   6105: ixor
    //   6106: istore #25
    //   6108: iload #24
    //   6110: bipush #16
    //   6112: iushr
    //   6113: iload #25
    //   6115: ixor
    //   6116: ldc 65535
    //   6118: iand
    //   6119: istore #23
    //   6121: iload #25
    //   6123: iload #23
    //   6125: ixor
    //   6126: istore #25
    //   6128: iload #24
    //   6130: iload #23
    //   6132: bipush #16
    //   6134: ishl
    //   6135: ixor
    //   6136: istore #24
    //   6138: iload #24
    //   6140: iconst_4
    //   6141: iushr
    //   6142: iload #25
    //   6144: ixor
    //   6145: ldc 252645135
    //   6147: iand
    //   6148: istore #23
    //   6150: iload #25
    //   6152: iload #23
    //   6154: ixor
    //   6155: istore #25
    //   6157: iload #24
    //   6159: iload #23
    //   6161: iconst_4
    //   6162: ishl
    //   6163: ixor
    //   6164: istore #24
    //   6166: aload #18
    //   6168: iconst_0
    //   6169: iload #24
    //   6171: iastore
    //   6172: aload #18
    //   6174: iconst_1
    //   6175: iload #25
    //   6177: iastore
    //   6178: iload #20
    //   6180: bipush #8
    //   6182: imul
    //   6183: istore #28
    //   6185: iconst_0
    //   6186: istore #29
    //   6188: iload #29
    //   6190: iconst_2
    //   6191: if_icmpge -> 6280
    //   6194: aload #5
    //   6196: iload #28
    //   6198: iload #29
    //   6200: iconst_4
    //   6201: imul
    //   6202: iadd
    //   6203: aload #18
    //   6205: iload #29
    //   6207: iaload
    //   6208: bipush #24
    //   6210: iushr
    //   6211: i2b
    //   6212: bastore
    //   6213: aload #5
    //   6215: iload #28
    //   6217: iload #29
    //   6219: iconst_4
    //   6220: imul
    //   6221: iadd
    //   6222: iconst_1
    //   6223: iadd
    //   6224: aload #18
    //   6226: iload #29
    //   6228: iaload
    //   6229: bipush #16
    //   6231: iushr
    //   6232: i2b
    //   6233: bastore
    //   6234: aload #5
    //   6236: iload #28
    //   6238: iload #29
    //   6240: iconst_4
    //   6241: imul
    //   6242: iadd
    //   6243: iconst_2
    //   6244: iadd
    //   6245: aload #18
    //   6247: iload #29
    //   6249: iaload
    //   6250: bipush #8
    //   6252: iushr
    //   6253: i2b
    //   6254: bastore
    //   6255: aload #5
    //   6257: iload #28
    //   6259: iload #29
    //   6261: iconst_4
    //   6262: imul
    //   6263: iadd
    //   6264: iconst_3
    //   6265: iadd
    //   6266: aload #18
    //   6268: iload #29
    //   6270: iaload
    //   6271: i2b
    //   6272: bastore
    //   6273: iinc #29, 1
    //   6276: iload_2
    //   6277: ifeq -> 6188
    //   6280: iinc #20, 1
    //   6283: iload_2
    //   6284: ifeq -> 5365
    //   6287: getstatic burp/Zt3l.Zi : Ljava/lang/String;
    //   6290: getstatic burp/Zxo6.Zw : Ljava/lang/Object;
    //   6293: checkcast java/math/BigInteger
    //   6296: invokevirtual intValue : ()I
    //   6299: bipush #32
    //   6301: irem
    //   6302: invokestatic abs : (I)I
    //   6305: invokevirtual charAt : (I)C
    //   6308: getstatic burp/Zl88.Zd : Ljava/lang/String;
    //   6311: getstatic burp/Zk8b.ZK : Ljava/lang/Object;
    //   6314: checkcast java/math/BigInteger
    //   6317: invokevirtual intValue : ()I
    //   6320: bipush #32
    //   6322: irem
    //   6323: invokestatic abs : (I)I
    //   6326: invokevirtual charAt : (I)C
    //   6329: if_icmple -> 6444
    //   6332: getstatic burp/Ze3d.ZL : Ljava/lang/String;
    //   6335: getstatic burp/Zg7p.Zb : Ljava/lang/Object;
    //   6338: checkcast java/math/BigInteger
    //   6341: invokevirtual intValue : ()I
    //   6344: bipush #32
    //   6346: irem
    //   6347: invokestatic abs : (I)I
    //   6350: invokevirtual charAt : (I)C
    //   6353: getstatic burp/Zkbm.Zb : Ljava/lang/String;
    //   6356: getstatic burp/Zg7z.ZV : Ljava/lang/Object;
    //   6359: checkcast java/math/BigInteger
    //   6362: invokevirtual intValue : ()I
    //   6365: bipush #32
    //   6367: irem
    //   6368: invokestatic abs : (I)I
    //   6371: invokevirtual charAt : (I)C
    //   6374: if_icmpgt -> 6444
    //   6377: goto -> 6384
    //   6380: invokestatic a : (Ljava/lang/Throwable;)Ljava/lang/Throwable;
    //   6383: athrow
    //   6384: getstatic burp/Zl2q.ZI : Ljava/lang/String;
    //   6387: getstatic burp/Zzqj.Zq : Ljava/lang/Object;
    //   6390: checkcast java/math/BigInteger
    //   6393: invokevirtual intValue : ()I
    //   6396: bipush #32
    //   6398: irem
    //   6399: invokestatic abs : (I)I
    //   6402: invokevirtual charAt : (I)C
    //   6405: getstatic burp/Zsgl.ZG : Ljava/lang/String;
    //   6408: getstatic burp/Zein.Zb : Ljava/lang/Object;
    //   6411: checkcast java/math/BigInteger
    //   6414: invokevirtual intValue : ()I
    //   6417: bipush #32
    //   6419: irem
    //   6420: invokestatic abs : (I)I
    //   6423: invokevirtual charAt : (I)C
    //   6426: if_icmpgt -> 6444
    //   6429: goto -> 6436
    //   6432: invokestatic a : (Ljava/lang/Throwable;)Ljava/lang/Throwable;
    //   6435: athrow
    //   6436: iconst_1
    //   6437: goto -> 6445
    //   6440: invokestatic a : (Ljava/lang/Throwable;)Ljava/lang/Throwable;
    //   6443: athrow
    //   6444: iconst_0
    //   6445: ireturn
    //   6446: astore_3
    //   6447: new java/lang/Exception
    //   6450: dup
    //   6451: aload_3
    //   6452: invokevirtual getMessage : ()Ljava/lang/String;
    //   6455: invokespecial <init> : (Ljava/lang/String;)V
    //   6458: athrow
    // Exception table:
    //   from	to	target	type
    //   4	6445	6446	java/lang/Throwable
    //   268	442	445	java/lang/Throwable
    //   412	479	482	java/lang/Throwable
    //   449	516	519	java/lang/Throwable
    //   486	553	556	java/lang/Throwable
    //   523	590	593	java/lang/Throwable
    //   560	627	630	java/lang/Throwable
    //   597	664	667	java/lang/Throwable
    //   634	701	704	java/lang/Throwable
    //   671	738	741	java/lang/Throwable
    //   708	775	778	java/lang/Throwable
    //   745	812	815	java/lang/Throwable
    //   782	849	852	java/lang/Throwable
    //   819	886	889	java/lang/Throwable
    //   856	923	926	java/lang/Throwable
    //   893	960	963	java/lang/Throwable
    //   930	997	1000	java/lang/Throwable
    //   967	1034	1037	java/lang/Throwable
    //   1004	1071	1074	java/lang/Throwable
    //   1041	1108	1111	java/lang/Throwable
    //   1078	1145	1148	java/lang/Throwable
    //   1115	1182	1185	java/lang/Throwable
    //   1152	1219	1222	java/lang/Throwable
    //   1189	1256	1259	java/lang/Throwable
    //   1226	1293	1296	java/lang/Throwable
    //   1263	1330	1333	java/lang/Throwable
    //   1300	1367	1370	java/lang/Throwable
    //   1337	1404	1407	java/lang/Throwable
    //   1374	1441	1444	java/lang/Throwable
    //   1411	1478	1481	java/lang/Throwable
    //   1448	1515	1518	java/lang/Throwable
    //   1485	1552	1555	java/lang/Throwable
    //   1522	1585	1588	java/lang/Throwable
    //   1669	1683	1683	java/lang/Throwable
    //   1694	1707	1710	java/lang/Throwable
    //   1699	1722	1725	java/lang/Throwable
    //   1714	1740	1743	java/lang/Throwable
    //   1729	1770	1773	java/lang/Throwable
    //   1836	1863	1866	java/lang/Throwable
    //   1853	1884	1887	java/lang/Throwable
    //   1870	1914	1917	java/lang/Throwable
    //   1891	1925	1925	java/lang/Throwable
    //   1936	1952	1955	java/lang/Throwable
    //   6287	6377	6380	java/lang/Throwable
    //   6332	6429	6432	java/lang/Throwable
    //   6384	6440	6440	java/lang/Throwable
  }
  
  static {
    // Byte code:
    //   0: bipush #9
    //   2: anewarray java/lang/String
    //   5: astore #5
    //   7: iconst_0
    //   8: istore_3
    //   9: ldc 'Y7$0gi\\r.'ae}P&|.{gt0p"k\\tzCBn\\\tIt@z, b~]pFK]d8af\\tz:BIMV?gt[5)H_g{ogp4T\\bu*Q#K\='
    //   11: dup
    //   12: astore_2
    //   13: invokevirtual length : ()I
    //   16: istore #4
    //   18: bipush #76
    //   20: istore_1
    //   21: iconst_m1
    //   22: istore_0
    //   23: bipush #118
    //   25: iinc #0, 1
    //   28: aload_2
    //   29: iload_0
    //   30: dup
    //   31: iload_1
    //   32: iadd
    //   33: invokevirtual substring : (II)Ljava/lang/String;
    //   36: iconst_m1
    //   37: goto -> 143
    //   40: aload #5
    //   42: swap
    //   43: iload_3
    //   44: iinc #3, 1
    //   47: swap
    //   48: aastore
    //   49: iload_0
    //   50: iload_1
    //   51: iadd
    //   52: dup
    //   53: istore_0
    //   54: iload #4
    //   56: if_icmpge -> 68
    //   59: aload_2
    //   60: iload_0
    //   61: invokevirtual charAt : (I)C
    //   64: istore_1
    //   65: goto -> 23
    //   68: ldc '5Tf\\tFV<,6s?wxP\\t.\\n\\f'
    //   70: dup
    //   71: astore_2
    //   72: invokevirtual length : ()I
    //   75: istore #4
    //   77: bipush #32
    //   79: istore_1
    //   80: iconst_m1
    //   81: istore_0
    //   82: bipush #120
    //   84: iinc #0, 1
    //   87: aload_2
    //   88: iload_0
    //   89: dup
    //   90: iload_1
    //   91: iadd
    //   92: invokevirtual substring : (II)Ljava/lang/String;
    //   95: iconst_0
    //   96: goto -> 143
    //   99: aload #5
    //   101: swap
    //   102: iload_3
    //   103: iinc #3, 1
    //   106: swap
    //   107: aastore
    //   108: iload_0
    //   109: iload_1
    //   110: iadd
    //   111: dup
    //   112: istore_0
    //   113: iload #4
    //   115: if_icmpge -> 127
    //   118: aload_2
    //   119: iload_0
    //   120: invokevirtual charAt : (I)C
    //   123: istore_1
    //   124: goto -> 82
    //   127: aload #5
    //   129: putstatic burp/Zx54.a : [Ljava/lang/String;
    //   132: bipush #9
    //   134: anewarray java/lang/String
    //   137: putstatic burp/Zx54.b : [Ljava/lang/String;
    //   140: goto -> 300
    //   143: dup_x2
    //   144: pop
    //   145: invokevirtual toCharArray : ()[C
    //   148: dup_x1
    //   149: arraylength
    //   150: dup_x2
    //   151: pop
    //   152: iconst_0
    //   153: istore #6
    //   155: dup2_x1
    //   156: pop2
    //   157: dup_x2
    //   158: iconst_1
    //   159: if_icmpgt -> 260
    //   162: dup2
    //   163: swap
    //   164: iload #6
    //   166: dup2_x1
    //   167: caload
    //   168: swap
    //   169: iload #6
    //   171: bipush #7
    //   173: irem
    //   174: tableswitch default -> 242, 0 -> 212, 1 -> 217, 2 -> 222, 3 -> 227, 4 -> 232, 5 -> 237
    //   212: bipush #94
    //   214: goto -> 244
    //   217: bipush #74
    //   219: goto -> 244
    //   222: bipush #88
    //   224: goto -> 244
    //   227: bipush #6
    //   229: goto -> 244
    //   232: bipush #45
    //   234: goto -> 244
    //   237: bipush #124
    //   239: goto -> 244
    //   242: bipush #105
    //   244: ixor
    //   245: ixor
    //   246: i2c
    //   247: castore
    //   248: iinc #6, 1
    //   251: dup
    //   252: ifne -> 260
    //   255: dup2
    //   256: dup_x1
    //   257: goto -> 166
    //   260: dup2_x1
    //   261: pop2
    //   262: dup_x2
    //   263: iload #6
    //   265: if_icmpgt -> 162
    //   268: pop
    //   269: new java/lang/String
    //   272: dup_x1
    //   273: swap
    //   274: invokespecial <init> : ([C)V
    //   277: invokevirtual intern : ()Ljava/lang/String;
    //   280: swap
    //   281: pop
    //   282: swap
    //   283: tableswitch default -> 40, 0 -> 99
    //   300: new java/math/BigInteger
    //   303: dup
    //   304: sipush #6532
    //   307: sipush #19353
    //   310: invokestatic a : (II)Ljava/lang/String;
    //   313: invokespecial <init> : (Ljava/lang/String;)V
    //   316: putstatic burp/Zx54.Zn : Ljava/lang/Object;
    //   319: sipush #6534
    //   322: sipush #19951
    //   325: invokestatic a : (II)Ljava/lang/String;
    //   328: putstatic burp/Zx54.Zs : Ljava/lang/String;
    //   331: return
  }
  
  private static Throwable a(Throwable paramThrowable) {
    return paramThrowable;
  }
  
  private static String a(int paramInt1, int paramInt2) {
    int i = (paramInt1 ^ 0x1982) & 0xFFFF;
    if (b[i] == null) {
      char[] arrayOfChar = a[i].toCharArray();
      switch (arrayOfChar[0] & 0xFF) {
        case 0:
        
        case 1:
        
        case 2:
        
        case 3:
        
        case 4:
        
        case 5:
        
        case 6:
        
        case 7:
        
        case 8:
        
        case 9:
        
        case 10:
        
        case 11:
        
        case 12:
        
        case 13:
        
        case 14:
        
        case 15:
        
        case 16:
        
        case 17:
        
        case 18:
        
        case 19:
        
        case 20:
        
        case 21:
        
        case 22:
        
        case 23:
        
        case 24:
        
        case 25:
        
        case 26:
        
        case 27:
        
        case 28:
        
        case 29:
        
        case 30:
        
        case 31:
        
        case 32:
        
        case 33:
        
        case 34:
        
        case 35:
        
        case 36:
        
        case 37:
        
        case 38:
        
        case 39:
        
        case 40:
        
        case 41:
        
        case 42:
        
        case 43:
        
        case 44:
        
        case 45:
        
        case 46:
        
        case 47:
        
        case 48:
        
        case 49:
        
        case 50:
        
        case 51:
        
        case 52:
        
        case 53:
        
        case 54:
        
        case 55:
        
        case 56:
        
        case 57:
        
        case 58:
        
        case 59:
        
        case 60:
        
        case 61:
        
        case 62:
        
        case 63:
        
        case 64:
        
        case 65:
        
        case 66:
        
        case 67:
        
        case 68:
        
        case 69:
        
        case 70:
        
        case 71:
        
        case 72:
        
        case 73:
        
        case 74:
        
        case 75:
        
        case 76:
        
        case 77:
        
        case 78:
        
        case 79:
        
        case 80:
        
        case 81:
        
        case 82:
        
        case 83:
        
        case 84:
        
        case 85:
        
        case 86:
        
        case 87:
        
        case 88:
        
        case 89:
        
        case 90:
        
        case 91:
        
        case 92:
        
        case 93:
        
        case 94:
        
        case 95:
        
        case 96:
        
        case 97:
        
        case 98:
        
        case 99:
        
        case 100:
        
        case 101:
        
        case 102:
        
        case 103:
        
        case 104:
        
        case 105:
        
        case 106:
        
        case 107:
        
        case 108:
        
        case 109:
        
        case 110:
        
        case 111:
        
        case 112:
        
        case 113:
        
        case 114:
        
        case 115:
        
        case 116:
        
        case 117:
        
        case 118:
        
        case 119:
        
        case 120:
        
        case 121:
        
        case 122:
        
        case 123:
        
        case 124:
        
        case 125:
        
        case 126:
        
        case 127:
        
        case 128:
        
        case 129:
        
        case 130:
        
        case 131:
        
        case 132:
        
        case 133:
        
        case 134:
        
        case 135:
        
        case 136:
        
        case 137:
        
        case 138:
        
        case 139:
        
        case 140:
        
        case 141:
        
        case 142:
        
        case 143:
        
        case 144:
        
        case 145:
        
        case 146:
        
        case 147:
        
        case 148:
        
        case 149:
        
        case 150:
        
        case 151:
        
        case 152:
        
        case 153:
        
        case 154:
        
        case 155:
        
        case 156:
        
        case 157:
        
        case 158:
        
        case 159:
        
        case 160:
        
        case 161:
        
        case 162:
        
        case 163:
        
        case 164:
        
        case 165:
        
        case 166:
        
        case 167:
        
        case 168:
        
        case 169:
        
        case 170:
        
        case 171:
        
        case 172:
        
        case 173:
        
        case 174:
        
        case 175:
        
        case 176:
        
        case 177:
        
        case 178:
        
        case 179:
        
        case 180:
        
        case 181:
        
        case 182:
        
        case 183:
        
        case 184:
        
        case 185:
        
        case 186:
        
        case 187:
        
        case 188:
        
        case 189:
        
        case 190:
        
        case 191:
        
        case 192:
        
        case 193:
        
        case 194:
        
        case 195:
        
        case 196:
        
        case 197:
        
        case 198:
        
        case 199:
        
        case 200:
        
        case 201:
        
        case 202:
        
        case 203:
        
        case 204:
        
        case 205:
        
        case 206:
        
        case 207:
        
        case 208:
        
        case 209:
        
        case 210:
        
        case 211:
        
        case 212:
        
        case 213:
        
        case 214:
        
        case 215:
        
        case 216:
        
        case 217:
        
        case 218:
        
        case 219:
        
        case 220:
        
        case 221:
        
        case 222:
        
        case 223:
        
        case 224:
        
        case 225:
        
        case 226:
        
        case 227:
        
        case 228:
        
        case 229:
        
        case 230:
        
        case 231:
        
        case 232:
        
        case 233:
        
        case 234:
        
        case 235:
        
        case 236:
        
        case 237:
        
        case 238:
        
        case 239:
        
        case 240:
        
        case 241:
        
        case 242:
        
        case 243:
        
        case 244:
        
        case 245:
        
        case 246:
        
        case 247:
        
        case 248:
        
        case 249:
        
        case 250:
        
        case 251:
        
        case 252:
        
        case 253:
        
        case 254:
        
        default:
          break;
      } 
      byte b1 = 26;
      int j = (paramInt2 & 0xFF) - b1;
      if (j < 0)
        j += 256; 
      int k = ((paramInt2 & 0xFFFF) >>> 8) - b1;
      if (k < 0)
        k += 256; 
      for (byte b2 = 0; b2 < arrayOfChar.length; b2++) {
        int m = b2 % 2;
        if (m == 0) {
          arrayOfChar[b2] = (char)(arrayOfChar[b2] ^ j);
          j = ((j >>> 3 | j << 5) ^ arrayOfChar[b2]) & 0xFF;
        } else {
          arrayOfChar[b2] = (char)(arrayOfChar[b2] ^ k);
          k = ((k >>> 3 | k << 5) ^ arrayOfChar[b2]) & 0xFF;
        } 
      } 
      b[i] = (new String(arrayOfChar)).intern();
    } 
    return b[i];
  }
}


/* Location:              C:\Program Files\BurpSuitePro\burpsuite_pro.jar!\burp\Zx54.class
 * Java compiler version: 21 (65.0)
 * JD-Core Version:       1.1.3
 */