package burp;

import java.math.BigInteger;

class Zx63 extends ClassLoader {
  static String ZT;
  
  static Object ZX;
  
  private static final String[] a;
  
  private static final String[] b;
  
  static boolean Zv(Object[] paramArrayOfObject, Object paramObject) throws Throwable {
    // Byte code:
    //   0: invokestatic ZK : ()Z
    //   3: istore_2
    //   4: new java/lang/StringBuilder
    //   7: dup
    //   8: invokespecial <init> : ()V
    //   11: astore_3
    //   12: iconst_0
    //   13: istore #4
    //   15: iload #4
    //   17: bipush #32
    //   19: if_icmpge -> 1355
    //   22: iload #4
    //   24: tableswitch default -> 1348, 0 -> 168, 1 -> 205, 2 -> 242, 3 -> 279, 4 -> 316, 5 -> 353, 6 -> 390, 7 -> 427, 8 -> 464, 9 -> 501, 10 -> 538, 11 -> 575, 12 -> 612, 13 -> 649, 14 -> 686, 15 -> 723, 16 -> 760, 17 -> 797, 18 -> 834, 19 -> 871, 20 -> 908, 21 -> 945, 22 -> 982, 23 -> 1019, 24 -> 1056, 25 -> 1093, 26 -> 1130, 27 -> 1167, 28 -> 1204, 29 -> 1241, 30 -> 1278, 31 -> 1315
    //   168: aload_3
    //   169: getstatic burp/Zz4j.ZS : Ljava/lang/String;
    //   172: getstatic burp/Zr14.Zy : Ljava/lang/Object;
    //   175: checkcast java/math/BigInteger
    //   178: invokevirtual intValue : ()I
    //   181: bipush #32
    //   183: irem
    //   184: invokestatic abs : (I)I
    //   187: invokevirtual charAt : (I)C
    //   190: invokevirtual append : (C)Ljava/lang/StringBuilder;
    //   193: pop
    //   194: iload_2
    //   195: ifeq -> 1348
    //   198: goto -> 205
    //   201: invokestatic a : (Ljava/lang/Throwable;)Ljava/lang/Throwable;
    //   204: athrow
    //   205: aload_3
    //   206: getstatic burp/Zm83.Zq : Ljava/lang/String;
    //   209: getstatic burp/Zg7u.Zh : Ljava/lang/Object;
    //   212: checkcast java/math/BigInteger
    //   215: invokevirtual intValue : ()I
    //   218: bipush #32
    //   220: irem
    //   221: invokestatic abs : (I)I
    //   224: invokevirtual charAt : (I)C
    //   227: invokevirtual append : (C)Ljava/lang/StringBuilder;
    //   230: pop
    //   231: iload_2
    //   232: ifeq -> 1348
    //   235: goto -> 242
    //   238: invokestatic a : (Ljava/lang/Throwable;)Ljava/lang/Throwable;
    //   241: athrow
    //   242: aload_3
    //   243: getstatic burp/Zsn4.ZZ : Ljava/lang/String;
    //   246: getstatic burp/Ztvy.ZH : Ljava/lang/Object;
    //   249: checkcast java/math/BigInteger
    //   252: invokevirtual intValue : ()I
    //   255: bipush #32
    //   257: irem
    //   258: invokestatic abs : (I)I
    //   261: invokevirtual charAt : (I)C
    //   264: invokevirtual append : (C)Ljava/lang/StringBuilder;
    //   267: pop
    //   268: iload_2
    //   269: ifeq -> 1348
    //   272: goto -> 279
    //   275: invokestatic a : (Ljava/lang/Throwable;)Ljava/lang/Throwable;
    //   278: athrow
    //   279: aload_3
    //   280: getstatic burp/Zr6c.Zf : Ljava/lang/String;
    //   283: getstatic burp/Zry1.Zf : Ljava/lang/Object;
    //   286: checkcast java/math/BigInteger
    //   289: invokevirtual intValue : ()I
    //   292: bipush #32
    //   294: irem
    //   295: invokestatic abs : (I)I
    //   298: invokevirtual charAt : (I)C
    //   301: invokevirtual append : (C)Ljava/lang/StringBuilder;
    //   304: pop
    //   305: iload_2
    //   306: ifeq -> 1348
    //   309: goto -> 316
    //   312: invokestatic a : (Ljava/lang/Throwable;)Ljava/lang/Throwable;
    //   315: athrow
    //   316: aload_3
    //   317: getstatic burp/Zb3l.Zz : Ljava/lang/String;
    //   320: getstatic burp/Zv8l.ZL : Ljava/lang/Object;
    //   323: checkcast java/math/BigInteger
    //   326: invokevirtual intValue : ()I
    //   329: bipush #32
    //   331: irem
    //   332: invokestatic abs : (I)I
    //   335: invokevirtual charAt : (I)C
    //   338: invokevirtual append : (C)Ljava/lang/StringBuilder;
    //   341: pop
    //   342: iload_2
    //   343: ifeq -> 1348
    //   346: goto -> 353
    //   349: invokestatic a : (Ljava/lang/Throwable;)Ljava/lang/Throwable;
    //   352: athrow
    //   353: aload_3
    //   354: getstatic burp/Zeig.Zg : Ljava/lang/String;
    //   357: getstatic burp/Zly9.Zz : Ljava/lang/Object;
    //   360: checkcast java/math/BigInteger
    //   363: invokevirtual intValue : ()I
    //   366: bipush #32
    //   368: irem
    //   369: invokestatic abs : (I)I
    //   372: invokevirtual charAt : (I)C
    //   375: invokevirtual append : (C)Ljava/lang/StringBuilder;
    //   378: pop
    //   379: iload_2
    //   380: ifeq -> 1348
    //   383: goto -> 390
    //   386: invokestatic a : (Ljava/lang/Throwable;)Ljava/lang/Throwable;
    //   389: athrow
    //   390: aload_3
    //   391: getstatic burp/Zer1.ZV : Ljava/lang/String;
    //   394: getstatic burp/Zrjq.ZU : Ljava/lang/Object;
    //   397: checkcast java/math/BigInteger
    //   400: invokevirtual intValue : ()I
    //   403: bipush #32
    //   405: irem
    //   406: invokestatic abs : (I)I
    //   409: invokevirtual charAt : (I)C
    //   412: invokevirtual append : (C)Ljava/lang/StringBuilder;
    //   415: pop
    //   416: iload_2
    //   417: ifeq -> 1348
    //   420: goto -> 427
    //   423: invokestatic a : (Ljava/lang/Throwable;)Ljava/lang/Throwable;
    //   426: athrow
    //   427: aload_3
    //   428: getstatic burp/Zzc9.Zv : Ljava/lang/String;
    //   431: getstatic burp/Zej8.Zu : Ljava/lang/Object;
    //   434: checkcast java/math/BigInteger
    //   437: invokevirtual intValue : ()I
    //   440: bipush #32
    //   442: irem
    //   443: invokestatic abs : (I)I
    //   446: invokevirtual charAt : (I)C
    //   449: invokevirtual append : (C)Ljava/lang/StringBuilder;
    //   452: pop
    //   453: iload_2
    //   454: ifeq -> 1348
    //   457: goto -> 464
    //   460: invokestatic a : (Ljava/lang/Throwable;)Ljava/lang/Throwable;
    //   463: athrow
    //   464: aload_3
    //   465: getstatic burp/Zbze.ZK : Ljava/lang/String;
    //   468: getstatic burp/Zk5k.Zr : Ljava/lang/Object;
    //   471: checkcast java/math/BigInteger
    //   474: invokevirtual intValue : ()I
    //   477: bipush #32
    //   479: irem
    //   480: invokestatic abs : (I)I
    //   483: invokevirtual charAt : (I)C
    //   486: invokevirtual append : (C)Ljava/lang/StringBuilder;
    //   489: pop
    //   490: iload_2
    //   491: ifeq -> 1348
    //   494: goto -> 501
    //   497: invokestatic a : (Ljava/lang/Throwable;)Ljava/lang/Throwable;
    //   500: athrow
    //   501: aload_3
    //   502: getstatic burp/Zrfa.ZT : Ljava/lang/String;
    //   505: getstatic burp/Zkca.ZQ : Ljava/lang/Object;
    //   508: checkcast java/math/BigInteger
    //   511: invokevirtual intValue : ()I
    //   514: bipush #32
    //   516: irem
    //   517: invokestatic abs : (I)I
    //   520: invokevirtual charAt : (I)C
    //   523: invokevirtual append : (C)Ljava/lang/StringBuilder;
    //   526: pop
    //   527: iload_2
    //   528: ifeq -> 1348
    //   531: goto -> 538
    //   534: invokestatic a : (Ljava/lang/Throwable;)Ljava/lang/Throwable;
    //   537: athrow
    //   538: aload_3
    //   539: getstatic burp/Zegw.Zn : Ljava/lang/String;
    //   542: getstatic burp/Zgcg.Zi : Ljava/lang/Object;
    //   545: checkcast java/math/BigInteger
    //   548: invokevirtual intValue : ()I
    //   551: bipush #32
    //   553: irem
    //   554: invokestatic abs : (I)I
    //   557: invokevirtual charAt : (I)C
    //   560: invokevirtual append : (C)Ljava/lang/StringBuilder;
    //   563: pop
    //   564: iload_2
    //   565: ifeq -> 1348
    //   568: goto -> 575
    //   571: invokestatic a : (Ljava/lang/Throwable;)Ljava/lang/Throwable;
    //   574: athrow
    //   575: aload_3
    //   576: getstatic burp/Ze4a.Zm : Ljava/lang/String;
    //   579: getstatic burp/Zr9u.ZX : Ljava/lang/Object;
    //   582: checkcast java/math/BigInteger
    //   585: invokevirtual intValue : ()I
    //   588: bipush #32
    //   590: irem
    //   591: invokestatic abs : (I)I
    //   594: invokevirtual charAt : (I)C
    //   597: invokevirtual append : (C)Ljava/lang/StringBuilder;
    //   600: pop
    //   601: iload_2
    //   602: ifeq -> 1348
    //   605: goto -> 612
    //   608: invokestatic a : (Ljava/lang/Throwable;)Ljava/lang/Throwable;
    //   611: athrow
    //   612: aload_3
    //   613: getstatic burp/Zbze.ZK : Ljava/lang/String;
    //   616: getstatic burp/Zk5k.Zr : Ljava/lang/Object;
    //   619: checkcast java/math/BigInteger
    //   622: invokevirtual intValue : ()I
    //   625: bipush #32
    //   627: irem
    //   628: invokestatic abs : (I)I
    //   631: invokevirtual charAt : (I)C
    //   634: invokevirtual append : (C)Ljava/lang/StringBuilder;
    //   637: pop
    //   638: iload_2
    //   639: ifeq -> 1348
    //   642: goto -> 649
    //   645: invokestatic a : (Ljava/lang/Throwable;)Ljava/lang/Throwable;
    //   648: athrow
    //   649: aload_3
    //   650: getstatic burp/Zex0.Zk : Ljava/lang/String;
    //   653: getstatic burp/Zeva.Zf : Ljava/lang/Object;
    //   656: checkcast java/math/BigInteger
    //   659: invokevirtual intValue : ()I
    //   662: bipush #32
    //   664: irem
    //   665: invokestatic abs : (I)I
    //   668: invokevirtual charAt : (I)C
    //   671: invokevirtual append : (C)Ljava/lang/StringBuilder;
    //   674: pop
    //   675: iload_2
    //   676: ifeq -> 1348
    //   679: goto -> 686
    //   682: invokestatic a : (Ljava/lang/Throwable;)Ljava/lang/Throwable;
    //   685: athrow
    //   686: aload_3
    //   687: getstatic burp/Zsn3.ZS : Ljava/lang/String;
    //   690: getstatic burp/Zvh.Zb : Ljava/lang/Object;
    //   693: checkcast java/math/BigInteger
    //   696: invokevirtual intValue : ()I
    //   699: bipush #32
    //   701: irem
    //   702: invokestatic abs : (I)I
    //   705: invokevirtual charAt : (I)C
    //   708: invokevirtual append : (C)Ljava/lang/StringBuilder;
    //   711: pop
    //   712: iload_2
    //   713: ifeq -> 1348
    //   716: goto -> 723
    //   719: invokestatic a : (Ljava/lang/Throwable;)Ljava/lang/Throwable;
    //   722: athrow
    //   723: aload_3
    //   724: getstatic burp/Zmn0.Zk : Ljava/lang/String;
    //   727: getstatic burp/Znu.Zf : Ljava/lang/Object;
    //   730: checkcast java/math/BigInteger
    //   733: invokevirtual intValue : ()I
    //   736: bipush #32
    //   738: irem
    //   739: invokestatic abs : (I)I
    //   742: invokevirtual charAt : (I)C
    //   745: invokevirtual append : (C)Ljava/lang/StringBuilder;
    //   748: pop
    //   749: iload_2
    //   750: ifeq -> 1348
    //   753: goto -> 760
    //   756: invokestatic a : (Ljava/lang/Throwable;)Ljava/lang/Throwable;
    //   759: athrow
    //   760: aload_3
    //   761: getstatic burp/Zzpm.Za : Ljava/lang/String;
    //   764: getstatic burp/Zdv.Zw : Ljava/lang/Object;
    //   767: checkcast java/math/BigInteger
    //   770: invokevirtual intValue : ()I
    //   773: bipush #32
    //   775: irem
    //   776: invokestatic abs : (I)I
    //   779: invokevirtual charAt : (I)C
    //   782: invokevirtual append : (C)Ljava/lang/StringBuilder;
    //   785: pop
    //   786: iload_2
    //   787: ifeq -> 1348
    //   790: goto -> 797
    //   793: invokestatic a : (Ljava/lang/Throwable;)Ljava/lang/Throwable;
    //   796: athrow
    //   797: aload_3
    //   798: getstatic burp/Zrd2.Zj : Ljava/lang/String;
    //   801: getstatic burp/Zrtp.Zy : Ljava/lang/Object;
    //   804: checkcast java/math/BigInteger
    //   807: invokevirtual intValue : ()I
    //   810: bipush #32
    //   812: irem
    //   813: invokestatic abs : (I)I
    //   816: invokevirtual charAt : (I)C
    //   819: invokevirtual append : (C)Ljava/lang/StringBuilder;
    //   822: pop
    //   823: iload_2
    //   824: ifeq -> 1348
    //   827: goto -> 834
    //   830: invokestatic a : (Ljava/lang/Throwable;)Ljava/lang/Throwable;
    //   833: athrow
    //   834: aload_3
    //   835: getstatic burp/Zt81.ZL : Ljava/lang/String;
    //   838: getstatic burp/Zsjc.ZX : Ljava/lang/Object;
    //   841: checkcast java/math/BigInteger
    //   844: invokevirtual intValue : ()I
    //   847: bipush #32
    //   849: irem
    //   850: invokestatic abs : (I)I
    //   853: invokevirtual charAt : (I)C
    //   856: invokevirtual append : (C)Ljava/lang/StringBuilder;
    //   859: pop
    //   860: iload_2
    //   861: ifeq -> 1348
    //   864: goto -> 871
    //   867: invokestatic a : (Ljava/lang/Throwable;)Ljava/lang/Throwable;
    //   870: athrow
    //   871: aload_3
    //   872: getstatic burp/Ztnn.ZS : Ljava/lang/String;
    //   875: getstatic burp/Zrfs.ZV : Ljava/lang/Object;
    //   878: checkcast java/math/BigInteger
    //   881: invokevirtual intValue : ()I
    //   884: bipush #32
    //   886: irem
    //   887: invokestatic abs : (I)I
    //   890: invokevirtual charAt : (I)C
    //   893: invokevirtual append : (C)Ljava/lang/StringBuilder;
    //   896: pop
    //   897: iload_2
    //   898: ifeq -> 1348
    //   901: goto -> 908
    //   904: invokestatic a : (Ljava/lang/Throwable;)Ljava/lang/Throwable;
    //   907: athrow
    //   908: aload_3
    //   909: getstatic burp/Zrb6.ZP : Ljava/lang/String;
    //   912: getstatic burp/Zxp5.ZA : Ljava/lang/Object;
    //   915: checkcast java/math/BigInteger
    //   918: invokevirtual intValue : ()I
    //   921: bipush #32
    //   923: irem
    //   924: invokestatic abs : (I)I
    //   927: invokevirtual charAt : (I)C
    //   930: invokevirtual append : (C)Ljava/lang/StringBuilder;
    //   933: pop
    //   934: iload_2
    //   935: ifeq -> 1348
    //   938: goto -> 945
    //   941: invokestatic a : (Ljava/lang/Throwable;)Ljava/lang/Throwable;
    //   944: athrow
    //   945: aload_3
    //   946: getstatic burp/Zm83.Zq : Ljava/lang/String;
    //   949: getstatic burp/Zk92.Zn : Ljava/lang/Object;
    //   952: checkcast java/math/BigInteger
    //   955: invokevirtual intValue : ()I
    //   958: bipush #32
    //   960: irem
    //   961: invokestatic abs : (I)I
    //   964: invokevirtual charAt : (I)C
    //   967: invokevirtual append : (C)Ljava/lang/StringBuilder;
    //   970: pop
    //   971: iload_2
    //   972: ifeq -> 1348
    //   975: goto -> 982
    //   978: invokestatic a : (Ljava/lang/Throwable;)Ljava/lang/Throwable;
    //   981: athrow
    //   982: aload_3
    //   983: getstatic burp/Zrqi.Zu : Ljava/lang/String;
    //   986: getstatic burp/Zmf2.Zx : Ljava/lang/Object;
    //   989: checkcast java/math/BigInteger
    //   992: invokevirtual intValue : ()I
    //   995: bipush #32
    //   997: irem
    //   998: invokestatic abs : (I)I
    //   1001: invokevirtual charAt : (I)C
    //   1004: invokevirtual append : (C)Ljava/lang/StringBuilder;
    //   1007: pop
    //   1008: iload_2
    //   1009: ifeq -> 1348
    //   1012: goto -> 1019
    //   1015: invokestatic a : (Ljava/lang/Throwable;)Ljava/lang/Throwable;
    //   1018: athrow
    //   1019: aload_3
    //   1020: getstatic burp/Zg4l.Z_ : Ljava/lang/String;
    //   1023: getstatic burp/Zr36.Za : Ljava/lang/Object;
    //   1026: checkcast java/math/BigInteger
    //   1029: invokevirtual intValue : ()I
    //   1032: bipush #32
    //   1034: irem
    //   1035: invokestatic abs : (I)I
    //   1038: invokevirtual charAt : (I)C
    //   1041: invokevirtual append : (C)Ljava/lang/StringBuilder;
    //   1044: pop
    //   1045: iload_2
    //   1046: ifeq -> 1348
    //   1049: goto -> 1056
    //   1052: invokestatic a : (Ljava/lang/Throwable;)Ljava/lang/Throwable;
    //   1055: athrow
    //   1056: aload_3
    //   1057: getstatic burp/Zt81.ZL : Ljava/lang/String;
    //   1060: getstatic burp/Ze1k.ZD : Ljava/lang/Object;
    //   1063: checkcast java/math/BigInteger
    //   1066: invokevirtual intValue : ()I
    //   1069: bipush #32
    //   1071: irem
    //   1072: invokestatic abs : (I)I
    //   1075: invokevirtual charAt : (I)C
    //   1078: invokevirtual append : (C)Ljava/lang/StringBuilder;
    //   1081: pop
    //   1082: iload_2
    //   1083: ifeq -> 1348
    //   1086: goto -> 1093
    //   1089: invokestatic a : (Ljava/lang/Throwable;)Ljava/lang/Throwable;
    //   1092: athrow
    //   1093: aload_3
    //   1094: getstatic burp/Zewr.ZW : Ljava/lang/String;
    //   1097: getstatic burp/Zti7.Zw : Ljava/lang/Object;
    //   1100: checkcast java/math/BigInteger
    //   1103: invokevirtual intValue : ()I
    //   1106: bipush #32
    //   1108: irem
    //   1109: invokestatic abs : (I)I
    //   1112: invokevirtual charAt : (I)C
    //   1115: invokevirtual append : (C)Ljava/lang/StringBuilder;
    //   1118: pop
    //   1119: iload_2
    //   1120: ifeq -> 1348
    //   1123: goto -> 1130
    //   1126: invokestatic a : (Ljava/lang/Throwable;)Ljava/lang/Throwable;
    //   1129: athrow
    //   1130: aload_3
    //   1131: getstatic burp/Zeub.ZT : Ljava/lang/String;
    //   1134: getstatic burp/Zxdy.ZZ : Ljava/lang/Object;
    //   1137: checkcast java/math/BigInteger
    //   1140: invokevirtual intValue : ()I
    //   1143: bipush #32
    //   1145: irem
    //   1146: invokestatic abs : (I)I
    //   1149: invokevirtual charAt : (I)C
    //   1152: invokevirtual append : (C)Ljava/lang/StringBuilder;
    //   1155: pop
    //   1156: iload_2
    //   1157: ifeq -> 1348
    //   1160: goto -> 1167
    //   1163: invokestatic a : (Ljava/lang/Throwable;)Ljava/lang/Throwable;
    //   1166: athrow
    //   1167: aload_3
    //   1168: getstatic burp/Zlgh.Zm : Ljava/lang/String;
    //   1171: getstatic burp/Zg2u.ZI : Ljava/lang/Object;
    //   1174: checkcast java/math/BigInteger
    //   1177: invokevirtual intValue : ()I
    //   1180: bipush #32
    //   1182: irem
    //   1183: invokestatic abs : (I)I
    //   1186: invokevirtual charAt : (I)C
    //   1189: invokevirtual append : (C)Ljava/lang/StringBuilder;
    //   1192: pop
    //   1193: iload_2
    //   1194: ifeq -> 1348
    //   1197: goto -> 1204
    //   1200: invokestatic a : (Ljava/lang/Throwable;)Ljava/lang/Throwable;
    //   1203: athrow
    //   1204: aload_3
    //   1205: getstatic burp/Zbjx.ZA : Ljava/lang/String;
    //   1208: getstatic burp/Zsdl.Zx : Ljava/lang/Object;
    //   1211: checkcast java/math/BigInteger
    //   1214: invokevirtual intValue : ()I
    //   1217: bipush #32
    //   1219: irem
    //   1220: invokestatic abs : (I)I
    //   1223: invokevirtual charAt : (I)C
    //   1226: invokevirtual append : (C)Ljava/lang/StringBuilder;
    //   1229: pop
    //   1230: iload_2
    //   1231: ifeq -> 1348
    //   1234: goto -> 1241
    //   1237: invokestatic a : (Ljava/lang/Throwable;)Ljava/lang/Throwable;
    //   1240: athrow
    //   1241: aload_3
    //   1242: getstatic burp/Zz4m.ZI : Ljava/lang/String;
    //   1245: getstatic burp/Zl7b.ZK : Ljava/lang/Object;
    //   1248: checkcast java/math/BigInteger
    //   1251: invokevirtual intValue : ()I
    //   1254: bipush #32
    //   1256: irem
    //   1257: invokestatic abs : (I)I
    //   1260: invokevirtual charAt : (I)C
    //   1263: invokevirtual append : (C)Ljava/lang/StringBuilder;
    //   1266: pop
    //   1267: iload_2
    //   1268: ifeq -> 1348
    //   1271: goto -> 1278
    //   1274: invokestatic a : (Ljava/lang/Throwable;)Ljava/lang/Throwable;
    //   1277: athrow
    //   1278: aload_3
    //   1279: getstatic burp/Zm63.Zs : Ljava/lang/String;
    //   1282: getstatic burp/Zt81.ZY : Ljava/lang/Object;
    //   1285: checkcast java/math/BigInteger
    //   1288: invokevirtual intValue : ()I
    //   1291: bipush #32
    //   1293: irem
    //   1294: invokestatic abs : (I)I
    //   1297: invokevirtual charAt : (I)C
    //   1300: invokevirtual append : (C)Ljava/lang/StringBuilder;
    //   1303: pop
    //   1304: iload_2
    //   1305: ifeq -> 1348
    //   1308: goto -> 1315
    //   1311: invokestatic a : (Ljava/lang/Throwable;)Ljava/lang/Throwable;
    //   1314: athrow
    //   1315: aload_3
    //   1316: getstatic burp/Zg7e.Zg : Ljava/lang/String;
    //   1319: getstatic burp/Zs4g.ZC : Ljava/lang/Object;
    //   1322: checkcast java/math/BigInteger
    //   1325: invokevirtual intValue : ()I
    //   1328: bipush #32
    //   1330: irem
    //   1331: invokestatic abs : (I)I
    //   1334: invokevirtual charAt : (I)C
    //   1337: invokevirtual append : (C)Ljava/lang/StringBuilder;
    //   1340: pop
    //   1341: goto -> 1348
    //   1344: invokestatic a : (Ljava/lang/Throwable;)Ljava/lang/Throwable;
    //   1347: athrow
    //   1348: iinc #4, 1
    //   1351: iload_2
    //   1352: ifeq -> 15
    //   1355: aload_3
    //   1356: invokevirtual toString : ()Ljava/lang/String;
    //   1359: putstatic burp/Zb4d.ZS : Ljava/lang/String;
    //   1362: new java/lang/StringBuilder
    //   1365: dup
    //   1366: invokespecial <init> : ()V
    //   1369: astore #4
    //   1371: iconst_0
    //   1372: istore #5
    //   1374: iload #5
    //   1376: bipush #32
    //   1378: if_icmpge -> 2743
    //   1381: iload #5
    //   1383: tableswitch default -> 2736, 0 -> 1524, 1 -> 1562, 2 -> 1600, 3 -> 1638, 4 -> 1676, 5 -> 1714, 6 -> 1752, 7 -> 1790, 8 -> 1828, 9 -> 1866, 10 -> 1904, 11 -> 1942, 12 -> 1980, 13 -> 2018, 14 -> 2056, 15 -> 2094, 16 -> 2132, 17 -> 2170, 18 -> 2208, 19 -> 2246, 20 -> 2284, 21 -> 2322, 22 -> 2360, 23 -> 2398, 24 -> 2436, 25 -> 2474, 26 -> 2512, 27 -> 2550, 28 -> 2588, 29 -> 2626, 30 -> 2664, 31 -> 2702
    //   1524: aload #4
    //   1526: getstatic burp/Zrex.Za : Ljava/lang/String;
    //   1529: getstatic burp/Zrm6.Z_ : Ljava/lang/Object;
    //   1532: checkcast java/math/BigInteger
    //   1535: invokevirtual intValue : ()I
    //   1538: bipush #32
    //   1540: irem
    //   1541: invokestatic abs : (I)I
    //   1544: invokevirtual charAt : (I)C
    //   1547: invokevirtual append : (C)Ljava/lang/StringBuilder;
    //   1550: pop
    //   1551: iload_2
    //   1552: ifeq -> 2736
    //   1555: goto -> 1562
    //   1558: invokestatic a : (Ljava/lang/Throwable;)Ljava/lang/Throwable;
    //   1561: athrow
    //   1562: aload #4
    //   1564: getstatic burp/Zzh5.Zc : Ljava/lang/String;
    //   1567: getstatic burp/Znu.Zf : Ljava/lang/Object;
    //   1570: checkcast java/math/BigInteger
    //   1573: invokevirtual intValue : ()I
    //   1576: bipush #32
    //   1578: irem
    //   1579: invokestatic abs : (I)I
    //   1582: invokevirtual charAt : (I)C
    //   1585: invokevirtual append : (C)Ljava/lang/StringBuilder;
    //   1588: pop
    //   1589: iload_2
    //   1590: ifeq -> 2736
    //   1593: goto -> 1600
    //   1596: invokestatic a : (Ljava/lang/Throwable;)Ljava/lang/Throwable;
    //   1599: athrow
    //   1600: aload #4
    //   1602: getstatic burp/Ztle.ZR : Ljava/lang/String;
    //   1605: getstatic burp/Zrgo.ZJ : Ljava/lang/Object;
    //   1608: checkcast java/math/BigInteger
    //   1611: invokevirtual intValue : ()I
    //   1614: bipush #32
    //   1616: irem
    //   1617: invokestatic abs : (I)I
    //   1620: invokevirtual charAt : (I)C
    //   1623: invokevirtual append : (C)Ljava/lang/StringBuilder;
    //   1626: pop
    //   1627: iload_2
    //   1628: ifeq -> 2736
    //   1631: goto -> 1638
    //   1634: invokestatic a : (Ljava/lang/Throwable;)Ljava/lang/Throwable;
    //   1637: athrow
    //   1638: aload #4
    //   1640: getstatic burp/Ze84.Zv : Ljava/lang/String;
    //   1643: getstatic burp/Zr60.Ze : Ljava/lang/Object;
    //   1646: checkcast java/math/BigInteger
    //   1649: invokevirtual intValue : ()I
    //   1652: bipush #32
    //   1654: irem
    //   1655: invokestatic abs : (I)I
    //   1658: invokevirtual charAt : (I)C
    //   1661: invokevirtual append : (C)Ljava/lang/StringBuilder;
    //   1664: pop
    //   1665: iload_2
    //   1666: ifeq -> 2736
    //   1669: goto -> 1676
    //   1672: invokestatic a : (Ljava/lang/Throwable;)Ljava/lang/Throwable;
    //   1675: athrow
    //   1676: aload #4
    //   1678: getstatic burp/Zedu.ZD : Ljava/lang/String;
    //   1681: getstatic burp/Zmlr.Zh : Ljava/lang/Object;
    //   1684: checkcast java/math/BigInteger
    //   1687: invokevirtual intValue : ()I
    //   1690: bipush #32
    //   1692: irem
    //   1693: invokestatic abs : (I)I
    //   1696: invokevirtual charAt : (I)C
    //   1699: invokevirtual append : (C)Ljava/lang/StringBuilder;
    //   1702: pop
    //   1703: iload_2
    //   1704: ifeq -> 2736
    //   1707: goto -> 1714
    //   1710: invokestatic a : (Ljava/lang/Throwable;)Ljava/lang/Throwable;
    //   1713: athrow
    //   1714: aload #4
    //   1716: getstatic burp/Zg2u.Zy : Ljava/lang/String;
    //   1719: getstatic burp/Zsbo.ZG : Ljava/lang/Object;
    //   1722: checkcast java/math/BigInteger
    //   1725: invokevirtual intValue : ()I
    //   1728: bipush #32
    //   1730: irem
    //   1731: invokestatic abs : (I)I
    //   1734: invokevirtual charAt : (I)C
    //   1737: invokevirtual append : (C)Ljava/lang/StringBuilder;
    //   1740: pop
    //   1741: iload_2
    //   1742: ifeq -> 2736
    //   1745: goto -> 1752
    //   1748: invokestatic a : (Ljava/lang/Throwable;)Ljava/lang/Throwable;
    //   1751: athrow
    //   1752: aload #4
    //   1754: getstatic burp/Zrh_.ZU : Ljava/lang/String;
    //   1757: getstatic burp/Zzre.ZE : Ljava/lang/Object;
    //   1760: checkcast java/math/BigInteger
    //   1763: invokevirtual intValue : ()I
    //   1766: bipush #32
    //   1768: irem
    //   1769: invokestatic abs : (I)I
    //   1772: invokevirtual charAt : (I)C
    //   1775: invokevirtual append : (C)Ljava/lang/StringBuilder;
    //   1778: pop
    //   1779: iload_2
    //   1780: ifeq -> 2736
    //   1783: goto -> 1790
    //   1786: invokestatic a : (Ljava/lang/Throwable;)Ljava/lang/Throwable;
    //   1789: athrow
    //   1790: aload #4
    //   1792: getstatic burp/Zm8j.Zp : Ljava/lang/String;
    //   1795: getstatic burp/Zmll.ZU : Ljava/lang/Object;
    //   1798: checkcast java/math/BigInteger
    //   1801: invokevirtual intValue : ()I
    //   1804: bipush #32
    //   1806: irem
    //   1807: invokestatic abs : (I)I
    //   1810: invokevirtual charAt : (I)C
    //   1813: invokevirtual append : (C)Ljava/lang/StringBuilder;
    //   1816: pop
    //   1817: iload_2
    //   1818: ifeq -> 2736
    //   1821: goto -> 1828
    //   1824: invokestatic a : (Ljava/lang/Throwable;)Ljava/lang/Throwable;
    //   1827: athrow
    //   1828: aload #4
    //   1830: getstatic burp/Zmf6.Zn : Ljava/lang/String;
    //   1833: getstatic burp/Zg7u.Zh : Ljava/lang/Object;
    //   1836: checkcast java/math/BigInteger
    //   1839: invokevirtual intValue : ()I
    //   1842: bipush #32
    //   1844: irem
    //   1845: invokestatic abs : (I)I
    //   1848: invokevirtual charAt : (I)C
    //   1851: invokevirtual append : (C)Ljava/lang/StringBuilder;
    //   1854: pop
    //   1855: iload_2
    //   1856: ifeq -> 2736
    //   1859: goto -> 1866
    //   1862: invokestatic a : (Ljava/lang/Throwable;)Ljava/lang/Throwable;
    //   1865: athrow
    //   1866: aload #4
    //   1868: getstatic burp/Zkjj.ZT : Ljava/lang/String;
    //   1871: getstatic burp/Zxn9.ZN : Ljava/lang/Object;
    //   1874: checkcast java/math/BigInteger
    //   1877: invokevirtual intValue : ()I
    //   1880: bipush #32
    //   1882: irem
    //   1883: invokestatic abs : (I)I
    //   1886: invokevirtual charAt : (I)C
    //   1889: invokevirtual append : (C)Ljava/lang/StringBuilder;
    //   1892: pop
    //   1893: iload_2
    //   1894: ifeq -> 2736
    //   1897: goto -> 1904
    //   1900: invokestatic a : (Ljava/lang/Throwable;)Ljava/lang/Throwable;
    //   1903: athrow
    //   1904: aload #4
    //   1906: getstatic burp/Zr14.ZL : Ljava/lang/String;
    //   1909: getstatic burp/Zegv.ZL : Ljava/lang/Object;
    //   1912: checkcast java/math/BigInteger
    //   1915: invokevirtual intValue : ()I
    //   1918: bipush #32
    //   1920: irem
    //   1921: invokestatic abs : (I)I
    //   1924: invokevirtual charAt : (I)C
    //   1927: invokevirtual append : (C)Ljava/lang/StringBuilder;
    //   1930: pop
    //   1931: iload_2
    //   1932: ifeq -> 2736
    //   1935: goto -> 1942
    //   1938: invokestatic a : (Ljava/lang/Throwable;)Ljava/lang/Throwable;
    //   1941: athrow
    //   1942: aload #4
    //   1944: getstatic burp/Zttd.Ze : Ljava/lang/String;
    //   1947: getstatic burp/Zz7j.ZR : Ljava/lang/Object;
    //   1950: checkcast java/math/BigInteger
    //   1953: invokevirtual intValue : ()I
    //   1956: bipush #32
    //   1958: irem
    //   1959: invokestatic abs : (I)I
    //   1962: invokevirtual charAt : (I)C
    //   1965: invokevirtual append : (C)Ljava/lang/StringBuilder;
    //   1968: pop
    //   1969: iload_2
    //   1970: ifeq -> 2736
    //   1973: goto -> 1980
    //   1976: invokestatic a : (Ljava/lang/Throwable;)Ljava/lang/Throwable;
    //   1979: athrow
    //   1980: aload #4
    //   1982: getstatic burp/Zrm6.ZV : Ljava/lang/String;
    //   1985: getstatic burp/Zrt3.ZG : Ljava/lang/Object;
    //   1988: checkcast java/math/BigInteger
    //   1991: invokevirtual intValue : ()I
    //   1994: bipush #32
    //   1996: irem
    //   1997: invokestatic abs : (I)I
    //   2000: invokevirtual charAt : (I)C
    //   2003: invokevirtual append : (C)Ljava/lang/StringBuilder;
    //   2006: pop
    //   2007: iload_2
    //   2008: ifeq -> 2736
    //   2011: goto -> 2018
    //   2014: invokestatic a : (Ljava/lang/Throwable;)Ljava/lang/Throwable;
    //   2017: athrow
    //   2018: aload #4
    //   2020: getstatic burp/Zzii.Zl : Ljava/lang/String;
    //   2023: getstatic burp/Zebc.Zr : Ljava/lang/Object;
    //   2026: checkcast java/math/BigInteger
    //   2029: invokevirtual intValue : ()I
    //   2032: bipush #32
    //   2034: irem
    //   2035: invokestatic abs : (I)I
    //   2038: invokevirtual charAt : (I)C
    //   2041: invokevirtual append : (C)Ljava/lang/StringBuilder;
    //   2044: pop
    //   2045: iload_2
    //   2046: ifeq -> 2736
    //   2049: goto -> 2056
    //   2052: invokestatic a : (Ljava/lang/Throwable;)Ljava/lang/Throwable;
    //   2055: athrow
    //   2056: aload #4
    //   2058: getstatic burp/Zgk9.Zf : Ljava/lang/String;
    //   2061: getstatic burp/Zlc2.ZQ : Ljava/lang/Object;
    //   2064: checkcast java/math/BigInteger
    //   2067: invokevirtual intValue : ()I
    //   2070: bipush #32
    //   2072: irem
    //   2073: invokestatic abs : (I)I
    //   2076: invokevirtual charAt : (I)C
    //   2079: invokevirtual append : (C)Ljava/lang/StringBuilder;
    //   2082: pop
    //   2083: iload_2
    //   2084: ifeq -> 2736
    //   2087: goto -> 2094
    //   2090: invokestatic a : (Ljava/lang/Throwable;)Ljava/lang/Throwable;
    //   2093: athrow
    //   2094: aload #4
    //   2096: getstatic burp/Ztdl.ZK : Ljava/lang/String;
    //   2099: getstatic burp/Zxdy.ZZ : Ljava/lang/Object;
    //   2102: checkcast java/math/BigInteger
    //   2105: invokevirtual intValue : ()I
    //   2108: bipush #32
    //   2110: irem
    //   2111: invokestatic abs : (I)I
    //   2114: invokevirtual charAt : (I)C
    //   2117: invokevirtual append : (C)Ljava/lang/StringBuilder;
    //   2120: pop
    //   2121: iload_2
    //   2122: ifeq -> 2736
    //   2125: goto -> 2132
    //   2128: invokestatic a : (Ljava/lang/Throwable;)Ljava/lang/Throwable;
    //   2131: athrow
    //   2132: aload #4
    //   2134: getstatic burp/Zrl5.ZG : Ljava/lang/String;
    //   2137: getstatic burp/Zm69.Zg : Ljava/lang/Object;
    //   2140: checkcast java/math/BigInteger
    //   2143: invokevirtual intValue : ()I
    //   2146: bipush #32
    //   2148: irem
    //   2149: invokestatic abs : (I)I
    //   2152: invokevirtual charAt : (I)C
    //   2155: invokevirtual append : (C)Ljava/lang/StringBuilder;
    //   2158: pop
    //   2159: iload_2
    //   2160: ifeq -> 2736
    //   2163: goto -> 2170
    //   2166: invokestatic a : (Ljava/lang/Throwable;)Ljava/lang/Throwable;
    //   2169: athrow
    //   2170: aload #4
    //   2172: getstatic burp/Zkdq.ZZ : Ljava/lang/String;
    //   2175: getstatic burp/Zmli.Zh : Ljava/lang/Object;
    //   2178: checkcast java/math/BigInteger
    //   2181: invokevirtual intValue : ()I
    //   2184: bipush #32
    //   2186: irem
    //   2187: invokestatic abs : (I)I
    //   2190: invokevirtual charAt : (I)C
    //   2193: invokevirtual append : (C)Ljava/lang/StringBuilder;
    //   2196: pop
    //   2197: iload_2
    //   2198: ifeq -> 2736
    //   2201: goto -> 2208
    //   2204: invokestatic a : (Ljava/lang/Throwable;)Ljava/lang/Throwable;
    //   2207: athrow
    //   2208: aload #4
    //   2210: getstatic burp/Zrd2.Zj : Ljava/lang/String;
    //   2213: getstatic burp/Zg4l.ZI : Ljava/lang/Object;
    //   2216: checkcast java/math/BigInteger
    //   2219: invokevirtual intValue : ()I
    //   2222: bipush #32
    //   2224: irem
    //   2225: invokestatic abs : (I)I
    //   2228: invokevirtual charAt : (I)C
    //   2231: invokevirtual append : (C)Ljava/lang/StringBuilder;
    //   2234: pop
    //   2235: iload_2
    //   2236: ifeq -> 2736
    //   2239: goto -> 2246
    //   2242: invokestatic a : (Ljava/lang/Throwable;)Ljava/lang/Throwable;
    //   2245: athrow
    //   2246: aload #4
    //   2248: getstatic burp/Zti4.ZI : Ljava/lang/String;
    //   2251: getstatic burp/Zmpx.ZZ : Ljava/lang/Object;
    //   2254: checkcast java/math/BigInteger
    //   2257: invokevirtual intValue : ()I
    //   2260: bipush #32
    //   2262: irem
    //   2263: invokestatic abs : (I)I
    //   2266: invokevirtual charAt : (I)C
    //   2269: invokevirtual append : (C)Ljava/lang/StringBuilder;
    //   2272: pop
    //   2273: iload_2
    //   2274: ifeq -> 2736
    //   2277: goto -> 2284
    //   2280: invokestatic a : (Ljava/lang/Throwable;)Ljava/lang/Throwable;
    //   2283: athrow
    //   2284: aload #4
    //   2286: getstatic burp/Zkjj.ZT : Ljava/lang/String;
    //   2289: getstatic burp/Zrjw.Zu : Ljava/lang/Object;
    //   2292: checkcast java/math/BigInteger
    //   2295: invokevirtual intValue : ()I
    //   2298: bipush #32
    //   2300: irem
    //   2301: invokestatic abs : (I)I
    //   2304: invokevirtual charAt : (I)C
    //   2307: invokevirtual append : (C)Ljava/lang/StringBuilder;
    //   2310: pop
    //   2311: iload_2
    //   2312: ifeq -> 2736
    //   2315: goto -> 2322
    //   2318: invokestatic a : (Ljava/lang/Throwable;)Ljava/lang/Throwable;
    //   2321: athrow
    //   2322: aload #4
    //   2324: getstatic burp/Zb4d.ZS : Ljava/lang/String;
    //   2327: getstatic burp/Zrzg.ZA : Ljava/lang/Object;
    //   2330: checkcast java/math/BigInteger
    //   2333: invokevirtual intValue : ()I
    //   2336: bipush #32
    //   2338: irem
    //   2339: invokestatic abs : (I)I
    //   2342: invokevirtual charAt : (I)C
    //   2345: invokevirtual append : (C)Ljava/lang/StringBuilder;
    //   2348: pop
    //   2349: iload_2
    //   2350: ifeq -> 2736
    //   2353: goto -> 2360
    //   2356: invokestatic a : (Ljava/lang/Throwable;)Ljava/lang/Throwable;
    //   2359: athrow
    //   2360: aload #4
    //   2362: getstatic burp/Zxdy.Zm : Ljava/lang/String;
    //   2365: getstatic burp/Zr_x.Zd : Ljava/lang/Object;
    //   2368: checkcast java/math/BigInteger
    //   2371: invokevirtual intValue : ()I
    //   2374: bipush #32
    //   2376: irem
    //   2377: invokestatic abs : (I)I
    //   2380: invokevirtual charAt : (I)C
    //   2383: invokevirtual append : (C)Ljava/lang/StringBuilder;
    //   2386: pop
    //   2387: iload_2
    //   2388: ifeq -> 2736
    //   2391: goto -> 2398
    //   2394: invokestatic a : (Ljava/lang/Throwable;)Ljava/lang/Throwable;
    //   2397: athrow
    //   2398: aload #4
    //   2400: getstatic burp/Zbwj.ZP : Ljava/lang/String;
    //   2403: getstatic burp/Zka9.Zd : Ljava/lang/Object;
    //   2406: checkcast java/math/BigInteger
    //   2409: invokevirtual intValue : ()I
    //   2412: bipush #32
    //   2414: irem
    //   2415: invokestatic abs : (I)I
    //   2418: invokevirtual charAt : (I)C
    //   2421: invokevirtual append : (C)Ljava/lang/StringBuilder;
    //   2424: pop
    //   2425: iload_2
    //   2426: ifeq -> 2736
    //   2429: goto -> 2436
    //   2432: invokestatic a : (Ljava/lang/Throwable;)Ljava/lang/Throwable;
    //   2435: athrow
    //   2436: aload #4
    //   2438: getstatic burp/Zrov.ZU : Ljava/lang/String;
    //   2441: getstatic burp/Zsp9.ZV : Ljava/lang/Object;
    //   2444: checkcast java/math/BigInteger
    //   2447: invokevirtual intValue : ()I
    //   2450: bipush #32
    //   2452: irem
    //   2453: invokestatic abs : (I)I
    //   2456: invokevirtual charAt : (I)C
    //   2459: invokevirtual append : (C)Ljava/lang/StringBuilder;
    //   2462: pop
    //   2463: iload_2
    //   2464: ifeq -> 2736
    //   2467: goto -> 2474
    //   2470: invokestatic a : (Ljava/lang/Throwable;)Ljava/lang/Throwable;
    //   2473: athrow
    //   2474: aload #4
    //   2476: getstatic burp/Zzpm.Za : Ljava/lang/String;
    //   2479: getstatic burp/Ze1k.ZD : Ljava/lang/Object;
    //   2482: checkcast java/math/BigInteger
    //   2485: invokevirtual intValue : ()I
    //   2488: bipush #32
    //   2490: irem
    //   2491: invokestatic abs : (I)I
    //   2494: invokevirtual charAt : (I)C
    //   2497: invokevirtual append : (C)Ljava/lang/StringBuilder;
    //   2500: pop
    //   2501: iload_2
    //   2502: ifeq -> 2736
    //   2505: goto -> 2512
    //   2508: invokestatic a : (Ljava/lang/Throwable;)Ljava/lang/Throwable;
    //   2511: athrow
    //   2512: aload #4
    //   2514: getstatic burp/Zewr.ZW : Ljava/lang/String;
    //   2517: getstatic burp/Zsdl.Zx : Ljava/lang/Object;
    //   2520: checkcast java/math/BigInteger
    //   2523: invokevirtual intValue : ()I
    //   2526: bipush #32
    //   2528: irem
    //   2529: invokestatic abs : (I)I
    //   2532: invokevirtual charAt : (I)C
    //   2535: invokevirtual append : (C)Ljava/lang/StringBuilder;
    //   2538: pop
    //   2539: iload_2
    //   2540: ifeq -> 2736
    //   2543: goto -> 2550
    //   2546: invokestatic a : (Ljava/lang/Throwable;)Ljava/lang/Throwable;
    //   2549: athrow
    //   2550: aload #4
    //   2552: getstatic burp/Zzyb.Zh : Ljava/lang/String;
    //   2555: getstatic burp/Zeig.ZA : Ljava/lang/Object;
    //   2558: checkcast java/math/BigInteger
    //   2561: invokevirtual intValue : ()I
    //   2564: bipush #32
    //   2566: irem
    //   2567: invokestatic abs : (I)I
    //   2570: invokevirtual charAt : (I)C
    //   2573: invokevirtual append : (C)Ljava/lang/StringBuilder;
    //   2576: pop
    //   2577: iload_2
    //   2578: ifeq -> 2736
    //   2581: goto -> 2588
    //   2584: invokestatic a : (Ljava/lang/Throwable;)Ljava/lang/Throwable;
    //   2587: athrow
    //   2588: aload #4
    //   2590: getstatic burp/Zb4d.ZS : Ljava/lang/String;
    //   2593: getstatic burp/Zm69.Zg : Ljava/lang/Object;
    //   2596: checkcast java/math/BigInteger
    //   2599: invokevirtual intValue : ()I
    //   2602: bipush #32
    //   2604: irem
    //   2605: invokestatic abs : (I)I
    //   2608: invokevirtual charAt : (I)C
    //   2611: invokevirtual append : (C)Ljava/lang/StringBuilder;
    //   2614: pop
    //   2615: iload_2
    //   2616: ifeq -> 2736
    //   2619: goto -> 2626
    //   2622: invokestatic a : (Ljava/lang/Throwable;)Ljava/lang/Throwable;
    //   2625: athrow
    //   2626: aload #4
    //   2628: getstatic burp/Zebc.ZC : Ljava/lang/String;
    //   2631: getstatic burp/Zs5y.Zd : Ljava/lang/Object;
    //   2634: checkcast java/math/BigInteger
    //   2637: invokevirtual intValue : ()I
    //   2640: bipush #32
    //   2642: irem
    //   2643: invokestatic abs : (I)I
    //   2646: invokevirtual charAt : (I)C
    //   2649: invokevirtual append : (C)Ljava/lang/StringBuilder;
    //   2652: pop
    //   2653: iload_2
    //   2654: ifeq -> 2736
    //   2657: goto -> 2664
    //   2660: invokestatic a : (Ljava/lang/Throwable;)Ljava/lang/Throwable;
    //   2663: athrow
    //   2664: aload #4
    //   2666: getstatic burp/Zbsz.Zu : Ljava/lang/String;
    //   2669: getstatic burp/Ztbn.ZA : Ljava/lang/Object;
    //   2672: checkcast java/math/BigInteger
    //   2675: invokevirtual intValue : ()I
    //   2678: bipush #32
    //   2680: irem
    //   2681: invokestatic abs : (I)I
    //   2684: invokevirtual charAt : (I)C
    //   2687: invokevirtual append : (C)Ljava/lang/StringBuilder;
    //   2690: pop
    //   2691: iload_2
    //   2692: ifeq -> 2736
    //   2695: goto -> 2702
    //   2698: invokestatic a : (Ljava/lang/Throwable;)Ljava/lang/Throwable;
    //   2701: athrow
    //   2702: aload #4
    //   2704: getstatic burp/Zskf.ZV : Ljava/lang/String;
    //   2707: getstatic burp/Zgcg.Zi : Ljava/lang/Object;
    //   2710: checkcast java/math/BigInteger
    //   2713: invokevirtual intValue : ()I
    //   2716: bipush #32
    //   2718: irem
    //   2719: invokestatic abs : (I)I
    //   2722: invokevirtual charAt : (I)C
    //   2725: invokevirtual append : (C)Ljava/lang/StringBuilder;
    //   2728: pop
    //   2729: goto -> 2736
    //   2732: invokestatic a : (Ljava/lang/Throwable;)Ljava/lang/Throwable;
    //   2735: athrow
    //   2736: iinc #5, 1
    //   2739: iload_2
    //   2740: ifeq -> 1374
    //   2743: aload #4
    //   2745: invokevirtual toString : ()Ljava/lang/String;
    //   2748: putstatic burp/Zrip.Zy : Ljava/lang/String;
    //   2751: new java/lang/StringBuilder
    //   2754: dup
    //   2755: invokespecial <init> : ()V
    //   2758: astore #5
    //   2760: iconst_0
    //   2761: istore #6
    //   2763: iload #6
    //   2765: bipush #32
    //   2767: if_icmpge -> 4135
    //   2770: iload #6
    //   2772: tableswitch default -> 4128, 0 -> 2916, 1 -> 2954, 2 -> 2992, 3 -> 3030, 4 -> 3068, 5 -> 3106, 6 -> 3144, 7 -> 3182, 8 -> 3220, 9 -> 3258, 10 -> 3296, 11 -> 3334, 12 -> 3372, 13 -> 3410, 14 -> 3448, 15 -> 3486, 16 -> 3524, 17 -> 3562, 18 -> 3600, 19 -> 3638, 20 -> 3676, 21 -> 3714, 22 -> 3752, 23 -> 3790, 24 -> 3828, 25 -> 3866, 26 -> 3904, 27 -> 3942, 28 -> 3980, 29 -> 4018, 30 -> 4056, 31 -> 4094
    //   2916: aload #5
    //   2918: getstatic burp/Zgrz.Zu : Ljava/lang/String;
    //   2921: getstatic burp/Zk9q.ZH : Ljava/lang/Object;
    //   2924: checkcast java/math/BigInteger
    //   2927: invokevirtual intValue : ()I
    //   2930: bipush #32
    //   2932: irem
    //   2933: invokestatic abs : (I)I
    //   2936: invokevirtual charAt : (I)C
    //   2939: invokevirtual append : (C)Ljava/lang/StringBuilder;
    //   2942: pop
    //   2943: iload_2
    //   2944: ifeq -> 4128
    //   2947: goto -> 2954
    //   2950: invokestatic a : (Ljava/lang/Throwable;)Ljava/lang/Throwable;
    //   2953: athrow
    //   2954: aload #5
    //   2956: getstatic burp/Zs5y.ZO : Ljava/lang/String;
    //   2959: getstatic burp/Zxln.ZJ : Ljava/lang/Object;
    //   2962: checkcast java/math/BigInteger
    //   2965: invokevirtual intValue : ()I
    //   2968: bipush #32
    //   2970: irem
    //   2971: invokestatic abs : (I)I
    //   2974: invokevirtual charAt : (I)C
    //   2977: invokevirtual append : (C)Ljava/lang/StringBuilder;
    //   2980: pop
    //   2981: iload_2
    //   2982: ifeq -> 4128
    //   2985: goto -> 2992
    //   2988: invokestatic a : (Ljava/lang/Throwable;)Ljava/lang/Throwable;
    //   2991: athrow
    //   2992: aload #5
    //   2994: getstatic burp/Zm7v.ZX : Ljava/lang/String;
    //   2997: getstatic burp/Zmt_.Zl : Ljava/lang/Object;
    //   3000: checkcast java/math/BigInteger
    //   3003: invokevirtual intValue : ()I
    //   3006: bipush #32
    //   3008: irem
    //   3009: invokestatic abs : (I)I
    //   3012: invokevirtual charAt : (I)C
    //   3015: invokevirtual append : (C)Ljava/lang/StringBuilder;
    //   3018: pop
    //   3019: iload_2
    //   3020: ifeq -> 4128
    //   3023: goto -> 3030
    //   3026: invokestatic a : (Ljava/lang/Throwable;)Ljava/lang/Throwable;
    //   3029: athrow
    //   3030: aload #5
    //   3032: getstatic burp/Zb6m.ZR : Ljava/lang/String;
    //   3035: getstatic burp/Zdv.Zw : Ljava/lang/Object;
    //   3038: checkcast java/math/BigInteger
    //   3041: invokevirtual intValue : ()I
    //   3044: bipush #32
    //   3046: irem
    //   3047: invokestatic abs : (I)I
    //   3050: invokevirtual charAt : (I)C
    //   3053: invokevirtual append : (C)Ljava/lang/StringBuilder;
    //   3056: pop
    //   3057: iload_2
    //   3058: ifeq -> 4128
    //   3061: goto -> 3068
    //   3064: invokestatic a : (Ljava/lang/Throwable;)Ljava/lang/Throwable;
    //   3067: athrow
    //   3068: aload #5
    //   3070: getstatic burp/Zl7b.Zv : Ljava/lang/String;
    //   3073: getstatic burp/Zxp1.ZP : Ljava/lang/Object;
    //   3076: checkcast java/math/BigInteger
    //   3079: invokevirtual intValue : ()I
    //   3082: bipush #32
    //   3084: irem
    //   3085: invokestatic abs : (I)I
    //   3088: invokevirtual charAt : (I)C
    //   3091: invokevirtual append : (C)Ljava/lang/StringBuilder;
    //   3094: pop
    //   3095: iload_2
    //   3096: ifeq -> 4128
    //   3099: goto -> 3106
    //   3102: invokestatic a : (Ljava/lang/Throwable;)Ljava/lang/Throwable;
    //   3105: athrow
    //   3106: aload #5
    //   3108: getstatic burp/Ztlo.Zs : Ljava/lang/String;
    //   3111: getstatic burp/Zld9.ZF : Ljava/lang/Object;
    //   3114: checkcast java/math/BigInteger
    //   3117: invokevirtual intValue : ()I
    //   3120: bipush #32
    //   3122: irem
    //   3123: invokestatic abs : (I)I
    //   3126: invokevirtual charAt : (I)C
    //   3129: invokevirtual append : (C)Ljava/lang/StringBuilder;
    //   3132: pop
    //   3133: iload_2
    //   3134: ifeq -> 4128
    //   3137: goto -> 3144
    //   3140: invokestatic a : (Ljava/lang/Throwable;)Ljava/lang/Throwable;
    //   3143: athrow
    //   3144: aload #5
    //   3146: getstatic burp/Zelt.ZJ : Ljava/lang/String;
    //   3149: getstatic burp/Zb2u.ZY : Ljava/lang/Object;
    //   3152: checkcast java/math/BigInteger
    //   3155: invokevirtual intValue : ()I
    //   3158: bipush #32
    //   3160: irem
    //   3161: invokestatic abs : (I)I
    //   3164: invokevirtual charAt : (I)C
    //   3167: invokevirtual append : (C)Ljava/lang/StringBuilder;
    //   3170: pop
    //   3171: iload_2
    //   3172: ifeq -> 4128
    //   3175: goto -> 3182
    //   3178: invokestatic a : (Ljava/lang/Throwable;)Ljava/lang/Throwable;
    //   3181: athrow
    //   3182: aload #5
    //   3184: getstatic burp/Zex0.Zk : Ljava/lang/String;
    //   3187: getstatic burp/Zrjq.ZU : Ljava/lang/Object;
    //   3190: checkcast java/math/BigInteger
    //   3193: invokevirtual intValue : ()I
    //   3196: bipush #32
    //   3198: irem
    //   3199: invokestatic abs : (I)I
    //   3202: invokevirtual charAt : (I)C
    //   3205: invokevirtual append : (C)Ljava/lang/StringBuilder;
    //   3208: pop
    //   3209: iload_2
    //   3210: ifeq -> 4128
    //   3213: goto -> 3220
    //   3216: invokestatic a : (Ljava/lang/Throwable;)Ljava/lang/Throwable;
    //   3219: athrow
    //   3220: aload #5
    //   3222: getstatic burp/Ze84.Zv : Ljava/lang/String;
    //   3225: getstatic burp/Zz41.Zv : Ljava/lang/Object;
    //   3228: checkcast java/math/BigInteger
    //   3231: invokevirtual intValue : ()I
    //   3234: bipush #32
    //   3236: irem
    //   3237: invokestatic abs : (I)I
    //   3240: invokevirtual charAt : (I)C
    //   3243: invokevirtual append : (C)Ljava/lang/StringBuilder;
    //   3246: pop
    //   3247: iload_2
    //   3248: ifeq -> 4128
    //   3251: goto -> 3258
    //   3254: invokestatic a : (Ljava/lang/Throwable;)Ljava/lang/Throwable;
    //   3257: athrow
    //   3258: aload #5
    //   3260: getstatic burp/Zgio.ZS : Ljava/lang/String;
    //   3263: getstatic burp/Zejz.ZF : Ljava/lang/Object;
    //   3266: checkcast java/math/BigInteger
    //   3269: invokevirtual intValue : ()I
    //   3272: bipush #32
    //   3274: irem
    //   3275: invokestatic abs : (I)I
    //   3278: invokevirtual charAt : (I)C
    //   3281: invokevirtual append : (C)Ljava/lang/StringBuilder;
    //   3284: pop
    //   3285: iload_2
    //   3286: ifeq -> 4128
    //   3289: goto -> 3296
    //   3292: invokestatic a : (Ljava/lang/Throwable;)Ljava/lang/Throwable;
    //   3295: athrow
    //   3296: aload #5
    //   3298: getstatic burp/Zsbo.Zg : Ljava/lang/String;
    //   3301: getstatic burp/Zbl4.ZW : Ljava/lang/Object;
    //   3304: checkcast java/math/BigInteger
    //   3307: invokevirtual intValue : ()I
    //   3310: bipush #32
    //   3312: irem
    //   3313: invokestatic abs : (I)I
    //   3316: invokevirtual charAt : (I)C
    //   3319: invokevirtual append : (C)Ljava/lang/StringBuilder;
    //   3322: pop
    //   3323: iload_2
    //   3324: ifeq -> 4128
    //   3327: goto -> 3334
    //   3330: invokestatic a : (Ljava/lang/Throwable;)Ljava/lang/Throwable;
    //   3333: athrow
    //   3334: aload #5
    //   3336: getstatic burp/Zt6z.ZL : Ljava/lang/String;
    //   3339: getstatic burp/Ztq8.Zm : Ljava/lang/Object;
    //   3342: checkcast java/math/BigInteger
    //   3345: invokevirtual intValue : ()I
    //   3348: bipush #32
    //   3350: irem
    //   3351: invokestatic abs : (I)I
    //   3354: invokevirtual charAt : (I)C
    //   3357: invokevirtual append : (C)Ljava/lang/StringBuilder;
    //   3360: pop
    //   3361: iload_2
    //   3362: ifeq -> 4128
    //   3365: goto -> 3372
    //   3368: invokestatic a : (Ljava/lang/Throwable;)Ljava/lang/Throwable;
    //   3371: athrow
    //   3372: aload #5
    //   3374: getstatic burp/Zzpm.Za : Ljava/lang/String;
    //   3377: getstatic burp/Zscz.ZN : Ljava/lang/Object;
    //   3380: checkcast java/math/BigInteger
    //   3383: invokevirtual intValue : ()I
    //   3386: bipush #32
    //   3388: irem
    //   3389: invokestatic abs : (I)I
    //   3392: invokevirtual charAt : (I)C
    //   3395: invokevirtual append : (C)Ljava/lang/StringBuilder;
    //   3398: pop
    //   3399: iload_2
    //   3400: ifeq -> 4128
    //   3403: goto -> 3410
    //   3406: invokestatic a : (Ljava/lang/Throwable;)Ljava/lang/Throwable;
    //   3409: athrow
    //   3410: aload #5
    //   3412: getstatic burp/Zrn4.ZY : Ljava/lang/String;
    //   3415: getstatic burp/Zb87.Zb : Ljava/lang/Object;
    //   3418: checkcast java/math/BigInteger
    //   3421: invokevirtual intValue : ()I
    //   3424: bipush #32
    //   3426: irem
    //   3427: invokestatic abs : (I)I
    //   3430: invokevirtual charAt : (I)C
    //   3433: invokevirtual append : (C)Ljava/lang/StringBuilder;
    //   3436: pop
    //   3437: iload_2
    //   3438: ifeq -> 4128
    //   3441: goto -> 3448
    //   3444: invokestatic a : (Ljava/lang/Throwable;)Ljava/lang/Throwable;
    //   3447: athrow
    //   3448: aload #5
    //   3450: getstatic burp/Ztl6.Zb : Ljava/lang/String;
    //   3453: getstatic burp/Ze1k.ZD : Ljava/lang/Object;
    //   3456: checkcast java/math/BigInteger
    //   3459: invokevirtual intValue : ()I
    //   3462: bipush #32
    //   3464: irem
    //   3465: invokestatic abs : (I)I
    //   3468: invokevirtual charAt : (I)C
    //   3471: invokevirtual append : (C)Ljava/lang/StringBuilder;
    //   3474: pop
    //   3475: iload_2
    //   3476: ifeq -> 4128
    //   3479: goto -> 3486
    //   3482: invokestatic a : (Ljava/lang/Throwable;)Ljava/lang/Throwable;
    //   3485: athrow
    //   3486: aload #5
    //   3488: getstatic burp/Zmkq.Zr : Ljava/lang/String;
    //   3491: getstatic burp/Zvob.ZX : Ljava/lang/Object;
    //   3494: checkcast java/math/BigInteger
    //   3497: invokevirtual intValue : ()I
    //   3500: bipush #32
    //   3502: irem
    //   3503: invokestatic abs : (I)I
    //   3506: invokevirtual charAt : (I)C
    //   3509: invokevirtual append : (C)Ljava/lang/StringBuilder;
    //   3512: pop
    //   3513: iload_2
    //   3514: ifeq -> 4128
    //   3517: goto -> 3524
    //   3520: invokestatic a : (Ljava/lang/Throwable;)Ljava/lang/Throwable;
    //   3523: athrow
    //   3524: aload #5
    //   3526: getstatic burp/Zxy6.ZR : Ljava/lang/String;
    //   3529: getstatic burp/Zezi.ZQ : Ljava/lang/Object;
    //   3532: checkcast java/math/BigInteger
    //   3535: invokevirtual intValue : ()I
    //   3538: bipush #32
    //   3540: irem
    //   3541: invokestatic abs : (I)I
    //   3544: invokevirtual charAt : (I)C
    //   3547: invokevirtual append : (C)Ljava/lang/StringBuilder;
    //   3550: pop
    //   3551: iload_2
    //   3552: ifeq -> 4128
    //   3555: goto -> 3562
    //   3558: invokestatic a : (Ljava/lang/Throwable;)Ljava/lang/Throwable;
    //   3561: athrow
    //   3562: aload #5
    //   3564: getstatic burp/Zso.ZL : Ljava/lang/String;
    //   3567: getstatic burp/Zg7e.Zr : Ljava/lang/Object;
    //   3570: checkcast java/math/BigInteger
    //   3573: invokevirtual intValue : ()I
    //   3576: bipush #32
    //   3578: irem
    //   3579: invokestatic abs : (I)I
    //   3582: invokevirtual charAt : (I)C
    //   3585: invokevirtual append : (C)Ljava/lang/StringBuilder;
    //   3588: pop
    //   3589: iload_2
    //   3590: ifeq -> 4128
    //   3593: goto -> 3600
    //   3596: invokestatic a : (Ljava/lang/Throwable;)Ljava/lang/Throwable;
    //   3599: athrow
    //   3600: aload #5
    //   3602: getstatic burp/Zzk_.ZX : Ljava/lang/String;
    //   3605: getstatic burp/Zea.ZO : Ljava/lang/Object;
    //   3608: checkcast java/math/BigInteger
    //   3611: invokevirtual intValue : ()I
    //   3614: bipush #32
    //   3616: irem
    //   3617: invokestatic abs : (I)I
    //   3620: invokevirtual charAt : (I)C
    //   3623: invokevirtual append : (C)Ljava/lang/StringBuilder;
    //   3626: pop
    //   3627: iload_2
    //   3628: ifeq -> 4128
    //   3631: goto -> 3638
    //   3634: invokestatic a : (Ljava/lang/Throwable;)Ljava/lang/Throwable;
    //   3637: athrow
    //   3638: aload #5
    //   3640: getstatic burp/Zzk_.ZX : Ljava/lang/String;
    //   3643: getstatic burp/Zrwp.Zk : Ljava/lang/Object;
    //   3646: checkcast java/math/BigInteger
    //   3649: invokevirtual intValue : ()I
    //   3652: bipush #32
    //   3654: irem
    //   3655: invokestatic abs : (I)I
    //   3658: invokevirtual charAt : (I)C
    //   3661: invokevirtual append : (C)Ljava/lang/StringBuilder;
    //   3664: pop
    //   3665: iload_2
    //   3666: ifeq -> 4128
    //   3669: goto -> 3676
    //   3672: invokestatic a : (Ljava/lang/Throwable;)Ljava/lang/Throwable;
    //   3675: athrow
    //   3676: aload #5
    //   3678: getstatic burp/Zegw.Zn : Ljava/lang/String;
    //   3681: getstatic burp/Ze4a.ZP : Ljava/lang/Object;
    //   3684: checkcast java/math/BigInteger
    //   3687: invokevirtual intValue : ()I
    //   3690: bipush #32
    //   3692: irem
    //   3693: invokestatic abs : (I)I
    //   3696: invokevirtual charAt : (I)C
    //   3699: invokevirtual append : (C)Ljava/lang/StringBuilder;
    //   3702: pop
    //   3703: iload_2
    //   3704: ifeq -> 4128
    //   3707: goto -> 3714
    //   3710: invokestatic a : (Ljava/lang/Throwable;)Ljava/lang/Throwable;
    //   3713: athrow
    //   3714: aload #5
    //   3716: getstatic burp/Zkdq.ZZ : Ljava/lang/String;
    //   3719: getstatic burp/Zbx5.ZL : Ljava/lang/Object;
    //   3722: checkcast java/math/BigInteger
    //   3725: invokevirtual intValue : ()I
    //   3728: bipush #32
    //   3730: irem
    //   3731: invokestatic abs : (I)I
    //   3734: invokevirtual charAt : (I)C
    //   3737: invokevirtual append : (C)Ljava/lang/StringBuilder;
    //   3740: pop
    //   3741: iload_2
    //   3742: ifeq -> 4128
    //   3745: goto -> 3752
    //   3748: invokestatic a : (Ljava/lang/Throwable;)Ljava/lang/Throwable;
    //   3751: athrow
    //   3752: aload #5
    //   3754: getstatic burp/Zkjj.ZT : Ljava/lang/String;
    //   3757: getstatic burp/Zs1k.Ze : Ljava/lang/Object;
    //   3760: checkcast java/math/BigInteger
    //   3763: invokevirtual intValue : ()I
    //   3766: bipush #32
    //   3768: irem
    //   3769: invokestatic abs : (I)I
    //   3772: invokevirtual charAt : (I)C
    //   3775: invokevirtual append : (C)Ljava/lang/StringBuilder;
    //   3778: pop
    //   3779: iload_2
    //   3780: ifeq -> 4128
    //   3783: goto -> 3790
    //   3786: invokestatic a : (Ljava/lang/Throwable;)Ljava/lang/Throwable;
    //   3789: athrow
    //   3790: aload #5
    //   3792: getstatic burp/Zbjx.ZA : Ljava/lang/String;
    //   3795: getstatic burp/Zr02.ZB : Ljava/lang/Object;
    //   3798: checkcast java/math/BigInteger
    //   3801: invokevirtual intValue : ()I
    //   3804: bipush #32
    //   3806: irem
    //   3807: invokestatic abs : (I)I
    //   3810: invokevirtual charAt : (I)C
    //   3813: invokevirtual append : (C)Ljava/lang/StringBuilder;
    //   3816: pop
    //   3817: iload_2
    //   3818: ifeq -> 4128
    //   3821: goto -> 3828
    //   3824: invokestatic a : (Ljava/lang/Throwable;)Ljava/lang/Throwable;
    //   3827: athrow
    //   3828: aload #5
    //   3830: getstatic burp/Zm63.Zs : Ljava/lang/String;
    //   3833: getstatic burp/Zk1.Z_ : Ljava/lang/Object;
    //   3836: checkcast java/math/BigInteger
    //   3839: invokevirtual intValue : ()I
    //   3842: bipush #32
    //   3844: irem
    //   3845: invokestatic abs : (I)I
    //   3848: invokevirtual charAt : (I)C
    //   3851: invokevirtual append : (C)Ljava/lang/StringBuilder;
    //   3854: pop
    //   3855: iload_2
    //   3856: ifeq -> 4128
    //   3859: goto -> 3866
    //   3862: invokestatic a : (Ljava/lang/Throwable;)Ljava/lang/Throwable;
    //   3865: athrow
    //   3866: aload #5
    //   3868: getstatic burp/Zb3r.Zo : Ljava/lang/String;
    //   3871: getstatic burp/Zrye.Zx : Ljava/lang/Object;
    //   3874: checkcast java/math/BigInteger
    //   3877: invokevirtual intValue : ()I
    //   3880: bipush #32
    //   3882: irem
    //   3883: invokestatic abs : (I)I
    //   3886: invokevirtual charAt : (I)C
    //   3889: invokevirtual append : (C)Ljava/lang/StringBuilder;
    //   3892: pop
    //   3893: iload_2
    //   3894: ifeq -> 4128
    //   3897: goto -> 3904
    //   3900: invokestatic a : (Ljava/lang/Throwable;)Ljava/lang/Throwable;
    //   3903: athrow
    //   3904: aload #5
    //   3906: getstatic burp/Zrt3.Zu : Ljava/lang/String;
    //   3909: getstatic burp/Zejz.ZF : Ljava/lang/Object;
    //   3912: checkcast java/math/BigInteger
    //   3915: invokevirtual intValue : ()I
    //   3918: bipush #32
    //   3920: irem
    //   3921: invokestatic abs : (I)I
    //   3924: invokevirtual charAt : (I)C
    //   3927: invokevirtual append : (C)Ljava/lang/StringBuilder;
    //   3930: pop
    //   3931: iload_2
    //   3932: ifeq -> 4128
    //   3935: goto -> 3942
    //   3938: invokestatic a : (Ljava/lang/Throwable;)Ljava/lang/Throwable;
    //   3941: athrow
    //   3942: aload #5
    //   3944: getstatic burp/Zb3l.Zz : Ljava/lang/String;
    //   3947: getstatic burp/Ztle.ZP : Ljava/lang/Object;
    //   3950: checkcast java/math/BigInteger
    //   3953: invokevirtual intValue : ()I
    //   3956: bipush #32
    //   3958: irem
    //   3959: invokestatic abs : (I)I
    //   3962: invokevirtual charAt : (I)C
    //   3965: invokevirtual append : (C)Ljava/lang/StringBuilder;
    //   3968: pop
    //   3969: iload_2
    //   3970: ifeq -> 4128
    //   3973: goto -> 3980
    //   3976: invokestatic a : (Ljava/lang/Throwable;)Ljava/lang/Throwable;
    //   3979: athrow
    //   3980: aload #5
    //   3982: getstatic burp/Zg0q.Ze : Ljava/lang/String;
    //   3985: getstatic burp/Zly9.Zz : Ljava/lang/Object;
    //   3988: checkcast java/math/BigInteger
    //   3991: invokevirtual intValue : ()I
    //   3994: bipush #32
    //   3996: irem
    //   3997: invokestatic abs : (I)I
    //   4000: invokevirtual charAt : (I)C
    //   4003: invokevirtual append : (C)Ljava/lang/StringBuilder;
    //   4006: pop
    //   4007: iload_2
    //   4008: ifeq -> 4128
    //   4011: goto -> 4018
    //   4014: invokestatic a : (Ljava/lang/Throwable;)Ljava/lang/Throwable;
    //   4017: athrow
    //   4018: aload #5
    //   4020: getstatic burp/Zsbv.Zr : Ljava/lang/String;
    //   4023: getstatic burp/Ztvg.ZO : Ljava/lang/Object;
    //   4026: checkcast java/math/BigInteger
    //   4029: invokevirtual intValue : ()I
    //   4032: bipush #32
    //   4034: irem
    //   4035: invokestatic abs : (I)I
    //   4038: invokevirtual charAt : (I)C
    //   4041: invokevirtual append : (C)Ljava/lang/StringBuilder;
    //   4044: pop
    //   4045: iload_2
    //   4046: ifeq -> 4128
    //   4049: goto -> 4056
    //   4052: invokestatic a : (Ljava/lang/Throwable;)Ljava/lang/Throwable;
    //   4055: athrow
    //   4056: aload #5
    //   4058: getstatic burp/Zzn6.Za : Ljava/lang/String;
    //   4061: getstatic burp/Zr_x.Zd : Ljava/lang/Object;
    //   4064: checkcast java/math/BigInteger
    //   4067: invokevirtual intValue : ()I
    //   4070: bipush #32
    //   4072: irem
    //   4073: invokestatic abs : (I)I
    //   4076: invokevirtual charAt : (I)C
    //   4079: invokevirtual append : (C)Ljava/lang/StringBuilder;
    //   4082: pop
    //   4083: iload_2
    //   4084: ifeq -> 4128
    //   4087: goto -> 4094
    //   4090: invokestatic a : (Ljava/lang/Throwable;)Ljava/lang/Throwable;
    //   4093: athrow
    //   4094: aload #5
    //   4096: getstatic burp/Zsp9.ZA : Ljava/lang/String;
    //   4099: getstatic burp/Zzna.ZD : Ljava/lang/Object;
    //   4102: checkcast java/math/BigInteger
    //   4105: invokevirtual intValue : ()I
    //   4108: bipush #32
    //   4110: irem
    //   4111: invokestatic abs : (I)I
    //   4114: invokevirtual charAt : (I)C
    //   4117: invokevirtual append : (C)Ljava/lang/StringBuilder;
    //   4120: pop
    //   4121: goto -> 4128
    //   4124: invokestatic a : (Ljava/lang/Throwable;)Ljava/lang/Throwable;
    //   4127: athrow
    //   4128: iinc #6, 1
    //   4131: iload_2
    //   4132: ifeq -> 2763
    //   4135: aload #5
    //   4137: invokevirtual toString : ()Ljava/lang/String;
    //   4140: putstatic burp/Zmc_.Zb : Ljava/lang/String;
    //   4143: sipush #12995
    //   4146: sipush #10364
    //   4149: invokestatic a : (II)Ljava/lang/String;
    //   4152: iconst_1
    //   4153: ldc burp/Zlsg
    //   4155: invokevirtual getClassLoader : ()Ljava/lang/ClassLoader;
    //   4158: invokestatic forName : (Ljava/lang/String;ZLjava/lang/ClassLoader;)Ljava/lang/Class;
    //   4161: invokevirtual getDeclaredFields : ()[Ljava/lang/reflect/Field;
    //   4164: astore #6
    //   4166: aload #6
    //   4168: arraylength
    //   4169: istore #7
    //   4171: iconst_0
    //   4172: istore #8
    //   4174: iload #8
    //   4176: iload #7
    //   4178: if_icmpge -> 4316
    //   4181: aload #6
    //   4183: iload #8
    //   4185: aaload
    //   4186: astore #9
    //   4188: aload #9
    //   4190: invokevirtual getModifiers : ()I
    //   4193: invokestatic isStatic : (I)Z
    //   4196: ifne -> 4206
    //   4199: goto -> 4309
    //   4202: invokestatic a : (Ljava/lang/Throwable;)Ljava/lang/Throwable;
    //   4205: athrow
    //   4206: aload #9
    //   4208: invokevirtual getType : ()Ljava/lang/Class;
    //   4211: astore #10
    //   4213: aload #10
    //   4215: ifnull -> 4296
    //   4218: aload #10
    //   4220: invokevirtual isPrimitive : ()Z
    //   4223: ifne -> 4296
    //   4226: goto -> 4233
    //   4229: invokestatic a : (Ljava/lang/Throwable;)Ljava/lang/Throwable;
    //   4232: athrow
    //   4233: aload #10
    //   4235: invokevirtual getPackage : ()Ljava/lang/Package;
    //   4238: ifnull -> 4296
    //   4241: goto -> 4248
    //   4244: invokestatic a : (Ljava/lang/Throwable;)Ljava/lang/Throwable;
    //   4247: athrow
    //   4248: aload #10
    //   4250: invokevirtual getPackage : ()Ljava/lang/Package;
    //   4253: invokevirtual getName : ()Ljava/lang/String;
    //   4256: ifnull -> 4296
    //   4259: goto -> 4266
    //   4262: invokestatic a : (Ljava/lang/Throwable;)Ljava/lang/Throwable;
    //   4265: athrow
    //   4266: aload #10
    //   4268: invokevirtual getPackage : ()Ljava/lang/Package;
    //   4271: invokevirtual getName : ()Ljava/lang/String;
    //   4274: sipush #13023
    //   4277: sipush #22250
    //   4280: invokestatic a : (II)Ljava/lang/String;
    //   4283: invokevirtual startsWith : (Ljava/lang/String;)Z
    //   4286: ifne -> 4296
    //   4289: goto -> 4296
    //   4292: invokestatic a : (Ljava/lang/Throwable;)Ljava/lang/Throwable;
    //   4295: athrow
    //   4296: aload #9
    //   4298: iconst_1
    //   4299: invokevirtual setAccessible : (Z)V
    //   4302: aload #9
    //   4304: aconst_null
    //   4305: invokevirtual get : (Ljava/lang/Object;)Ljava/lang/Object;
    //   4308: pop
    //   4309: iinc #8, 1
    //   4312: iload_2
    //   4313: ifeq -> 4174
    //   4316: sipush #12998
    //   4319: sipush #2844
    //   4322: invokestatic a : (II)Ljava/lang/String;
    //   4325: invokestatic forName : (Ljava/lang/String;)Ljava/lang/Class;
    //   4328: invokevirtual getDeclaredMethods : ()[Ljava/lang/reflect/Method;
    //   4331: astore #6
    //   4333: aload #6
    //   4335: arraylength
    //   4336: istore #7
    //   4338: iconst_0
    //   4339: istore #8
    //   4341: iload #8
    //   4343: iload #7
    //   4345: if_icmpge -> 4478
    //   4348: aload #6
    //   4350: iload #8
    //   4352: aaload
    //   4353: astore #9
    //   4355: aload #9
    //   4357: invokevirtual getParameterTypes : ()[Ljava/lang/Class;
    //   4360: pop
    //   4361: aload #9
    //   4363: invokevirtual getModifiers : ()I
    //   4366: invokestatic isStatic : (I)Z
    //   4369: ifeq -> 4464
    //   4372: aload #9
    //   4374: invokevirtual getParameterTypes : ()[Ljava/lang/Class;
    //   4377: arraylength
    //   4378: iconst_2
    //   4379: if_icmpne -> 4464
    //   4382: goto -> 4389
    //   4385: invokestatic a : (Ljava/lang/Throwable;)Ljava/lang/Throwable;
    //   4388: athrow
    //   4389: aload #9
    //   4391: invokevirtual getReturnType : ()Ljava/lang/Class;
    //   4394: getstatic java/lang/Void.TYPE : Ljava/lang/Class;
    //   4397: invokevirtual equals : (Ljava/lang/Object;)Z
    //   4400: ifeq -> 4464
    //   4403: goto -> 4410
    //   4406: invokestatic a : (Ljava/lang/Throwable;)Ljava/lang/Throwable;
    //   4409: athrow
    //   4410: aload #9
    //   4412: iconst_1
    //   4413: invokevirtual setAccessible : (Z)V
    //   4416: aload #9
    //   4418: aconst_null
    //   4419: iconst_2
    //   4420: anewarray java/lang/Object
    //   4423: dup
    //   4424: iconst_0
    //   4425: aload_0
    //   4426: aastore
    //   4427: dup
    //   4428: iconst_1
    //   4429: aload_1
    //   4430: ifnonnull -> 4448
    //   4433: goto -> 4440
    //   4436: invokestatic a : (Ljava/lang/Throwable;)Ljava/lang/Throwable;
    //   4439: athrow
    //   4440: aload_1
    //   4441: goto -> 4455
    //   4444: invokestatic a : (Ljava/lang/Throwable;)Ljava/lang/Throwable;
    //   4447: athrow
    //   4448: aload_1
    //   4449: checkcast [B
    //   4452: invokevirtual clone : ()Ljava/lang/Object;
    //   4455: aastore
    //   4456: invokevirtual invoke : (Ljava/lang/Object;[Ljava/lang/Object;)Ljava/lang/Object;
    //   4459: pop
    //   4460: iload_2
    //   4461: ifeq -> 4478
    //   4464: iinc #8, 1
    //   4467: iload_2
    //   4468: ifeq -> 4341
    //   4471: goto -> 4478
    //   4474: invokestatic a : (Ljava/lang/Throwable;)Ljava/lang/Throwable;
    //   4477: athrow
    //   4478: new java/io/ByteArrayOutputStream
    //   4481: dup
    //   4482: invokespecial <init> : ()V
    //   4485: astore #6
    //   4487: getstatic burp/Zbwj.ZP : Ljava/lang/String;
    //   4490: astore #7
    //   4492: iconst_0
    //   4493: istore #8
    //   4495: iload #8
    //   4497: aload #7
    //   4499: invokevirtual length : ()I
    //   4502: if_icmpge -> 4533
    //   4505: aload #6
    //   4507: aload #7
    //   4509: iload #8
    //   4511: iload #8
    //   4513: iconst_2
    //   4514: iadd
    //   4515: invokevirtual substring : (II)Ljava/lang/String;
    //   4518: bipush #16
    //   4520: invokestatic parseInt : (Ljava/lang/String;I)I
    //   4523: invokevirtual write : (I)V
    //   4526: iinc #8, 2
    //   4529: iload_2
    //   4530: ifeq -> 4495
    //   4533: aload #6
    //   4535: invokevirtual toByteArray : ()[B
    //   4538: astore #8
    //   4540: getstatic burp/Zs8w.ZW : Ljava/lang/Object;
    //   4543: checkcast java/math/BigInteger
    //   4546: invokevirtual toByteArray : ()[B
    //   4549: astore #9
    //   4551: sipush #256
    //   4554: newarray byte
    //   4556: astore #11
    //   4558: sipush #256
    //   4561: newarray int
    //   4563: astore #12
    //   4565: sipush #256
    //   4568: newarray int
    //   4570: astore #13
    //   4572: sipush #256
    //   4575: newarray int
    //   4577: astore #14
    //   4579: sipush #256
    //   4582: newarray int
    //   4584: astore #15
    //   4586: bipush #10
    //   4588: newarray int
    //   4590: astore #16
    //   4592: sipush #283
    //   4595: istore #17
    //   4597: iconst_0
    //   4598: istore #19
    //   4600: iload #19
    //   4602: sipush #256
    //   4605: if_icmpge -> 4839
    //   4608: sipush #13011
    //   4611: sipush #-31115
    //   4614: invokestatic a : (II)Ljava/lang/String;
    //   4617: iload #19
    //   4619: iconst_1
    //   4620: iushr
    //   4621: invokevirtual charAt : (I)C
    //   4624: istore #28
    //   4626: iload #19
    //   4628: iconst_1
    //   4629: iand
    //   4630: ifne -> 4645
    //   4633: iload #28
    //   4635: bipush #8
    //   4637: iushr
    //   4638: goto -> 4647
    //   4641: invokestatic a : (Ljava/lang/Throwable;)Ljava/lang/Throwable;
    //   4644: athrow
    //   4645: iload #28
    //   4647: i2b
    //   4648: sipush #255
    //   4651: iand
    //   4652: istore #18
    //   4654: iload #19
    //   4656: iconst_1
    //   4657: ishl
    //   4658: istore #20
    //   4660: iload #20
    //   4662: sipush #256
    //   4665: if_icmplt -> 4675
    //   4668: iload #20
    //   4670: iload #17
    //   4672: ixor
    //   4673: istore #20
    //   4675: iload #20
    //   4677: iconst_1
    //   4678: ishl
    //   4679: istore #21
    //   4681: iload #21
    //   4683: sipush #256
    //   4686: if_icmplt -> 4696
    //   4689: iload #21
    //   4691: iload #17
    //   4693: ixor
    //   4694: istore #21
    //   4696: iload #21
    //   4698: iconst_1
    //   4699: ishl
    //   4700: istore #22
    //   4702: iload #22
    //   4704: sipush #256
    //   4707: if_icmplt -> 4717
    //   4710: iload #22
    //   4712: iload #17
    //   4714: ixor
    //   4715: istore #22
    //   4717: iload #22
    //   4719: iload #19
    //   4721: ixor
    //   4722: istore #23
    //   4724: iload #23
    //   4726: iload #20
    //   4728: ixor
    //   4729: istore #24
    //   4731: iload #23
    //   4733: iload #21
    //   4735: ixor
    //   4736: istore #25
    //   4738: iload #22
    //   4740: iload #21
    //   4742: ixor
    //   4743: iload #20
    //   4745: ixor
    //   4746: istore #26
    //   4748: aload #11
    //   4750: iload #19
    //   4752: iload #18
    //   4754: i2b
    //   4755: bastore
    //   4756: aload #12
    //   4758: iload #18
    //   4760: iload #26
    //   4762: bipush #24
    //   4764: ishl
    //   4765: iload #23
    //   4767: bipush #16
    //   4769: ishl
    //   4770: ior
    //   4771: iload #25
    //   4773: bipush #8
    //   4775: ishl
    //   4776: ior
    //   4777: iload #24
    //   4779: ior
    //   4780: dup
    //   4781: istore #27
    //   4783: iastore
    //   4784: aload #13
    //   4786: iload #18
    //   4788: iload #27
    //   4790: bipush #8
    //   4792: iushr
    //   4793: iload #27
    //   4795: bipush #24
    //   4797: ishl
    //   4798: ior
    //   4799: iastore
    //   4800: aload #14
    //   4802: iload #18
    //   4804: iload #27
    //   4806: bipush #16
    //   4808: iushr
    //   4809: iload #27
    //   4811: bipush #16
    //   4813: ishl
    //   4814: ior
    //   4815: iastore
    //   4816: aload #15
    //   4818: iload #18
    //   4820: iload #27
    //   4822: bipush #24
    //   4824: iushr
    //   4825: iload #27
    //   4827: bipush #8
    //   4829: ishl
    //   4830: ior
    //   4831: iastore
    //   4832: iinc #19, 1
    //   4835: iload_2
    //   4836: ifeq -> 4600
    //   4839: iconst_1
    //   4840: istore #28
    //   4842: aload #16
    //   4844: iconst_0
    //   4845: iload #28
    //   4847: bipush #24
    //   4849: ishl
    //   4850: iastore
    //   4851: iconst_1
    //   4852: istore #29
    //   4854: iload #29
    //   4856: bipush #10
    //   4858: if_icmpge -> 4899
    //   4861: iload #28
    //   4863: iconst_1
    //   4864: ishl
    //   4865: istore #28
    //   4867: iload #28
    //   4869: sipush #256
    //   4872: if_icmplt -> 4882
    //   4875: iload #28
    //   4877: iload #17
    //   4879: ixor
    //   4880: istore #28
    //   4882: aload #16
    //   4884: iload #29
    //   4886: iload #28
    //   4888: bipush #24
    //   4890: ishl
    //   4891: iastore
    //   4892: iinc #29, 1
    //   4895: iload_2
    //   4896: ifeq -> 4854
    //   4899: iconst_4
    //   4900: istore #29
    //   4902: iload #29
    //   4904: bipush #6
    //   4906: iadd
    //   4907: istore #30
    //   4909: iconst_4
    //   4910: iload #30
    //   4912: iconst_1
    //   4913: iadd
    //   4914: imul
    //   4915: istore #31
    //   4917: iload #31
    //   4919: newarray int
    //   4921: astore #32
    //   4923: iload #31
    //   4925: newarray int
    //   4927: astore #33
    //   4929: iconst_0
    //   4930: istore #28
    //   4932: iconst_0
    //   4933: istore #35
    //   4935: iconst_0
    //   4936: istore #36
    //   4938: iload #35
    //   4940: iload #29
    //   4942: if_icmpge -> 5010
    //   4945: aload #32
    //   4947: iload #35
    //   4949: aload #8
    //   4951: iload #36
    //   4953: baload
    //   4954: bipush #24
    //   4956: ishl
    //   4957: aload #8
    //   4959: iload #36
    //   4961: iconst_1
    //   4962: iadd
    //   4963: baload
    //   4964: sipush #255
    //   4967: iand
    //   4968: bipush #16
    //   4970: ishl
    //   4971: ior
    //   4972: aload #8
    //   4974: iload #36
    //   4976: iconst_2
    //   4977: iadd
    //   4978: baload
    //   4979: sipush #255
    //   4982: iand
    //   4983: bipush #8
    //   4985: ishl
    //   4986: ior
    //   4987: aload #8
    //   4989: iload #36
    //   4991: iconst_3
    //   4992: iadd
    //   4993: baload
    //   4994: sipush #255
    //   4997: iand
    //   4998: ior
    //   4999: iastore
    //   5000: iinc #35, 1
    //   5003: iinc #36, 4
    //   5006: iload_2
    //   5007: ifeq -> 4938
    //   5010: iload #29
    //   5012: istore #35
    //   5014: iconst_0
    //   5015: istore #36
    //   5017: iload #35
    //   5019: iload #31
    //   5021: if_icmpge -> 5148
    //   5024: aload #32
    //   5026: iload #35
    //   5028: iconst_1
    //   5029: isub
    //   5030: iaload
    //   5031: istore #34
    //   5033: iload #36
    //   5035: ifne -> 5122
    //   5038: iload #29
    //   5040: istore #36
    //   5042: aload #11
    //   5044: iload #34
    //   5046: bipush #16
    //   5048: iushr
    //   5049: sipush #255
    //   5052: iand
    //   5053: baload
    //   5054: bipush #24
    //   5056: ishl
    //   5057: aload #11
    //   5059: iload #34
    //   5061: bipush #8
    //   5063: iushr
    //   5064: sipush #255
    //   5067: iand
    //   5068: baload
    //   5069: sipush #255
    //   5072: iand
    //   5073: bipush #16
    //   5075: ishl
    //   5076: ior
    //   5077: aload #11
    //   5079: iload #34
    //   5081: sipush #255
    //   5084: iand
    //   5085: baload
    //   5086: sipush #255
    //   5089: iand
    //   5090: bipush #8
    //   5092: ishl
    //   5093: ior
    //   5094: aload #11
    //   5096: iload #34
    //   5098: bipush #24
    //   5100: iushr
    //   5101: baload
    //   5102: sipush #255
    //   5105: iand
    //   5106: ior
    //   5107: istore #34
    //   5109: iload #34
    //   5111: aload #16
    //   5113: iload #28
    //   5115: iinc #28, 1
    //   5118: iaload
    //   5119: ixor
    //   5120: istore #34
    //   5122: aload #32
    //   5124: iload #35
    //   5126: aload #32
    //   5128: iload #35
    //   5130: iload #29
    //   5132: isub
    //   5133: iaload
    //   5134: iload #34
    //   5136: ixor
    //   5137: iastore
    //   5138: iinc #35, 1
    //   5141: iinc #36, -1
    //   5144: iload_2
    //   5145: ifeq -> 5017
    //   5148: iconst_0
    //   5149: istore #35
    //   5151: iconst_4
    //   5152: iload #30
    //   5154: imul
    //   5155: istore #36
    //   5157: aload #33
    //   5159: iload #35
    //   5161: aload #32
    //   5163: iload #36
    //   5165: iaload
    //   5166: iastore
    //   5167: aload #33
    //   5169: iload #35
    //   5171: iconst_1
    //   5172: iadd
    //   5173: aload #32
    //   5175: iload #36
    //   5177: iconst_1
    //   5178: iadd
    //   5179: iaload
    //   5180: iastore
    //   5181: aload #33
    //   5183: iload #35
    //   5185: iconst_2
    //   5186: iadd
    //   5187: aload #32
    //   5189: iload #36
    //   5191: iconst_2
    //   5192: iadd
    //   5193: iaload
    //   5194: iastore
    //   5195: aload #33
    //   5197: iload #35
    //   5199: iconst_3
    //   5200: iadd
    //   5201: aload #32
    //   5203: iload #36
    //   5205: iconst_3
    //   5206: iadd
    //   5207: iaload
    //   5208: iastore
    //   5209: iinc #35, 4
    //   5212: iinc #36, -4
    //   5215: iconst_1
    //   5216: istore #38
    //   5218: iload #38
    //   5220: iload #30
    //   5222: if_icmpge -> 5586
    //   5225: aload #32
    //   5227: iload #36
    //   5229: iaload
    //   5230: istore #37
    //   5232: aload #33
    //   5234: iload #35
    //   5236: aload #12
    //   5238: aload #11
    //   5240: iload #37
    //   5242: bipush #24
    //   5244: iushr
    //   5245: baload
    //   5246: sipush #255
    //   5249: iand
    //   5250: iaload
    //   5251: aload #13
    //   5253: aload #11
    //   5255: iload #37
    //   5257: bipush #16
    //   5259: iushr
    //   5260: sipush #255
    //   5263: iand
    //   5264: baload
    //   5265: sipush #255
    //   5268: iand
    //   5269: iaload
    //   5270: ixor
    //   5271: aload #14
    //   5273: aload #11
    //   5275: iload #37
    //   5277: bipush #8
    //   5279: iushr
    //   5280: sipush #255
    //   5283: iand
    //   5284: baload
    //   5285: sipush #255
    //   5288: iand
    //   5289: iaload
    //   5290: ixor
    //   5291: aload #15
    //   5293: aload #11
    //   5295: iload #37
    //   5297: sipush #255
    //   5300: iand
    //   5301: baload
    //   5302: sipush #255
    //   5305: iand
    //   5306: iaload
    //   5307: ixor
    //   5308: iastore
    //   5309: aload #32
    //   5311: iload #36
    //   5313: iconst_1
    //   5314: iadd
    //   5315: iaload
    //   5316: istore #37
    //   5318: aload #33
    //   5320: iload #35
    //   5322: iconst_1
    //   5323: iadd
    //   5324: aload #12
    //   5326: aload #11
    //   5328: iload #37
    //   5330: bipush #24
    //   5332: iushr
    //   5333: baload
    //   5334: sipush #255
    //   5337: iand
    //   5338: iaload
    //   5339: aload #13
    //   5341: aload #11
    //   5343: iload #37
    //   5345: bipush #16
    //   5347: iushr
    //   5348: sipush #255
    //   5351: iand
    //   5352: baload
    //   5353: sipush #255
    //   5356: iand
    //   5357: iaload
    //   5358: ixor
    //   5359: aload #14
    //   5361: aload #11
    //   5363: iload #37
    //   5365: bipush #8
    //   5367: iushr
    //   5368: sipush #255
    //   5371: iand
    //   5372: baload
    //   5373: sipush #255
    //   5376: iand
    //   5377: iaload
    //   5378: ixor
    //   5379: aload #15
    //   5381: aload #11
    //   5383: iload #37
    //   5385: sipush #255
    //   5388: iand
    //   5389: baload
    //   5390: sipush #255
    //   5393: iand
    //   5394: iaload
    //   5395: ixor
    //   5396: iastore
    //   5397: aload #32
    //   5399: iload #36
    //   5401: iconst_2
    //   5402: iadd
    //   5403: iaload
    //   5404: istore #37
    //   5406: aload #33
    //   5408: iload #35
    //   5410: iconst_2
    //   5411: iadd
    //   5412: aload #12
    //   5414: aload #11
    //   5416: iload #37
    //   5418: bipush #24
    //   5420: iushr
    //   5421: baload
    //   5422: sipush #255
    //   5425: iand
    //   5426: iaload
    //   5427: aload #13
    //   5429: aload #11
    //   5431: iload #37
    //   5433: bipush #16
    //   5435: iushr
    //   5436: sipush #255
    //   5439: iand
    //   5440: baload
    //   5441: sipush #255
    //   5444: iand
    //   5445: iaload
    //   5446: ixor
    //   5447: aload #14
    //   5449: aload #11
    //   5451: iload #37
    //   5453: bipush #8
    //   5455: iushr
    //   5456: sipush #255
    //   5459: iand
    //   5460: baload
    //   5461: sipush #255
    //   5464: iand
    //   5465: iaload
    //   5466: ixor
    //   5467: aload #15
    //   5469: aload #11
    //   5471: iload #37
    //   5473: sipush #255
    //   5476: iand
    //   5477: baload
    //   5478: sipush #255
    //   5481: iand
    //   5482: iaload
    //   5483: ixor
    //   5484: iastore
    //   5485: aload #32
    //   5487: iload #36
    //   5489: iconst_3
    //   5490: iadd
    //   5491: iaload
    //   5492: istore #37
    //   5494: aload #33
    //   5496: iload #35
    //   5498: iconst_3
    //   5499: iadd
    //   5500: aload #12
    //   5502: aload #11
    //   5504: iload #37
    //   5506: bipush #24
    //   5508: iushr
    //   5509: baload
    //   5510: sipush #255
    //   5513: iand
    //   5514: iaload
    //   5515: aload #13
    //   5517: aload #11
    //   5519: iload #37
    //   5521: bipush #16
    //   5523: iushr
    //   5524: sipush #255
    //   5527: iand
    //   5528: baload
    //   5529: sipush #255
    //   5532: iand
    //   5533: iaload
    //   5534: ixor
    //   5535: aload #14
    //   5537: aload #11
    //   5539: iload #37
    //   5541: bipush #8
    //   5543: iushr
    //   5544: sipush #255
    //   5547: iand
    //   5548: baload
    //   5549: sipush #255
    //   5552: iand
    //   5553: iaload
    //   5554: ixor
    //   5555: aload #15
    //   5557: aload #11
    //   5559: iload #37
    //   5561: sipush #255
    //   5564: iand
    //   5565: baload
    //   5566: sipush #255
    //   5569: iand
    //   5570: iaload
    //   5571: ixor
    //   5572: iastore
    //   5573: iinc #35, 4
    //   5576: iinc #36, -4
    //   5579: iinc #38, 1
    //   5582: iload_2
    //   5583: ifeq -> 5218
    //   5586: aload #33
    //   5588: iload #35
    //   5590: aload #32
    //   5592: iload #36
    //   5594: iaload
    //   5595: iastore
    //   5596: aload #33
    //   5598: iload #35
    //   5600: iconst_1
    //   5601: iadd
    //   5602: aload #32
    //   5604: iload #36
    //   5606: iconst_1
    //   5607: iadd
    //   5608: iaload
    //   5609: iastore
    //   5610: aload #33
    //   5612: iload #35
    //   5614: iconst_2
    //   5615: iadd
    //   5616: aload #32
    //   5618: iload #36
    //   5620: iconst_2
    //   5621: iadd
    //   5622: iaload
    //   5623: iastore
    //   5624: aload #33
    //   5626: iload #35
    //   5628: iconst_3
    //   5629: iadd
    //   5630: aload #32
    //   5632: iload #36
    //   5634: iconst_3
    //   5635: iadd
    //   5636: iaload
    //   5637: iastore
    //   5638: iconst_0
    //   5639: newarray byte
    //   5641: astore #38
    //   5643: aload #9
    //   5645: arraylength
    //   5646: bipush #16
    //   5648: irem
    //   5649: ifeq -> 5673
    //   5652: new java/lang/Exception
    //   5655: dup
    //   5656: sipush #13015
    //   5659: sipush #21332
    //   5662: invokestatic a : (II)Ljava/lang/String;
    //   5665: invokespecial <init> : (Ljava/lang/String;)V
    //   5668: athrow
    //   5669: invokestatic a : (Ljava/lang/Throwable;)Ljava/lang/Throwable;
    //   5672: athrow
    //   5673: bipush #10
    //   5675: istore #39
    //   5677: sipush #12996
    //   5680: sipush #256
    //   5683: newarray byte
    //   5685: astore #40
    //   5687: sipush #-3450
    //   5690: sipush #256
    //   5693: newarray int
    //   5695: astore #41
    //   5697: sipush #256
    //   5700: newarray int
    //   5702: astore #42
    //   5704: sipush #256
    //   5707: newarray int
    //   5709: astore #43
    //   5711: sipush #256
    //   5714: newarray int
    //   5716: astore #44
    //   5718: sipush #283
    //   5721: istore #17
    //   5723: invokestatic a : (II)Ljava/lang/String;
    //   5726: astore #45
    //   5728: iconst_0
    //   5729: istore #19
    //   5731: iload #19
    //   5733: sipush #256
    //   5736: if_icmpge -> 5963
    //   5739: aload #45
    //   5741: iload #19
    //   5743: iconst_1
    //   5744: iushr
    //   5745: invokevirtual charAt : (I)C
    //   5748: istore #46
    //   5750: iload #19
    //   5752: iconst_1
    //   5753: iand
    //   5754: ifne -> 5769
    //   5757: iload #46
    //   5759: bipush #8
    //   5761: iushr
    //   5762: goto -> 5771
    //   5765: invokestatic a : (Ljava/lang/Throwable;)Ljava/lang/Throwable;
    //   5768: athrow
    //   5769: iload #46
    //   5771: i2b
    //   5772: sipush #255
    //   5775: iand
    //   5776: istore #18
    //   5778: iload #19
    //   5780: iconst_1
    //   5781: ishl
    //   5782: istore #20
    //   5784: iload #20
    //   5786: sipush #256
    //   5789: if_icmplt -> 5799
    //   5792: iload #20
    //   5794: iload #17
    //   5796: ixor
    //   5797: istore #20
    //   5799: iload #20
    //   5801: iconst_1
    //   5802: ishl
    //   5803: istore #21
    //   5805: iload #21
    //   5807: sipush #256
    //   5810: if_icmplt -> 5820
    //   5813: iload #21
    //   5815: iload #17
    //   5817: ixor
    //   5818: istore #21
    //   5820: iload #21
    //   5822: iconst_1
    //   5823: ishl
    //   5824: istore #22
    //   5826: iload #22
    //   5828: sipush #256
    //   5831: if_icmplt -> 5841
    //   5834: iload #22
    //   5836: iload #17
    //   5838: ixor
    //   5839: istore #22
    //   5841: iload #22
    //   5843: iload #19
    //   5845: ixor
    //   5846: istore #23
    //   5848: iload #23
    //   5850: iload #20
    //   5852: ixor
    //   5853: istore #24
    //   5855: iload #23
    //   5857: iload #21
    //   5859: ixor
    //   5860: istore #25
    //   5862: iload #22
    //   5864: iload #21
    //   5866: ixor
    //   5867: iload #20
    //   5869: ixor
    //   5870: istore #26
    //   5872: aload #40
    //   5874: iload #18
    //   5876: iload #19
    //   5878: i2b
    //   5879: bastore
    //   5880: aload #41
    //   5882: iload #18
    //   5884: iload #26
    //   5886: bipush #24
    //   5888: ishl
    //   5889: iload #23
    //   5891: bipush #16
    //   5893: ishl
    //   5894: ior
    //   5895: iload #25
    //   5897: bipush #8
    //   5899: ishl
    //   5900: ior
    //   5901: iload #24
    //   5903: ior
    //   5904: dup
    //   5905: istore #27
    //   5907: iastore
    //   5908: aload #42
    //   5910: iload #18
    //   5912: iload #27
    //   5914: bipush #8
    //   5916: iushr
    //   5917: iload #27
    //   5919: bipush #24
    //   5921: ishl
    //   5922: ior
    //   5923: iastore
    //   5924: aload #43
    //   5926: iload #18
    //   5928: iload #27
    //   5930: bipush #16
    //   5932: iushr
    //   5933: iload #27
    //   5935: bipush #16
    //   5937: ishl
    //   5938: ior
    //   5939: iastore
    //   5940: aload #44
    //   5942: iload #18
    //   5944: iload #27
    //   5946: bipush #24
    //   5948: iushr
    //   5949: iload #27
    //   5951: bipush #8
    //   5953: ishl
    //   5954: ior
    //   5955: iastore
    //   5956: iinc #19, 1
    //   5959: iload_2
    //   5960: ifeq -> 5731
    //   5963: aload #9
    //   5965: arraylength
    //   5966: newarray byte
    //   5968: astore #46
    //   5970: iconst_0
    //   5971: istore #47
    //   5973: iload #47
    //   5975: aload #9
    //   5977: arraylength
    //   5978: bipush #16
    //   5980: idiv
    //   5981: if_icmpge -> 6895
    //   5984: bipush #16
    //   5986: newarray byte
    //   5988: astore #48
    //   5990: bipush #16
    //   5992: newarray byte
    //   5994: astore #49
    //   5996: iconst_0
    //   5997: istore #50
    //   5999: iload #50
    //   6001: bipush #16
    //   6003: if_icmpge -> 6029
    //   6006: aload #48
    //   6008: iload #50
    //   6010: aload #9
    //   6012: iload #50
    //   6014: iload #47
    //   6016: bipush #16
    //   6018: imul
    //   6019: iadd
    //   6020: baload
    //   6021: bastore
    //   6022: iinc #50, 1
    //   6025: iload_2
    //   6026: ifeq -> 5999
    //   6029: iconst_0
    //   6030: istore #50
    //   6032: aload #48
    //   6034: iconst_0
    //   6035: baload
    //   6036: bipush #24
    //   6038: ishl
    //   6039: aload #48
    //   6041: iconst_1
    //   6042: baload
    //   6043: sipush #255
    //   6046: iand
    //   6047: bipush #16
    //   6049: ishl
    //   6050: ior
    //   6051: aload #48
    //   6053: iconst_2
    //   6054: baload
    //   6055: sipush #255
    //   6058: iand
    //   6059: bipush #8
    //   6061: ishl
    //   6062: ior
    //   6063: aload #48
    //   6065: iconst_3
    //   6066: baload
    //   6067: sipush #255
    //   6070: iand
    //   6071: ior
    //   6072: aload #33
    //   6074: iconst_0
    //   6075: iaload
    //   6076: ixor
    //   6077: istore #52
    //   6079: aload #48
    //   6081: iconst_4
    //   6082: baload
    //   6083: bipush #24
    //   6085: ishl
    //   6086: aload #48
    //   6088: iconst_5
    //   6089: baload
    //   6090: sipush #255
    //   6093: iand
    //   6094: bipush #16
    //   6096: ishl
    //   6097: ior
    //   6098: aload #48
    //   6100: bipush #6
    //   6102: baload
    //   6103: sipush #255
    //   6106: iand
    //   6107: bipush #8
    //   6109: ishl
    //   6110: ior
    //   6111: aload #48
    //   6113: bipush #7
    //   6115: baload
    //   6116: sipush #255
    //   6119: iand
    //   6120: ior
    //   6121: aload #33
    //   6123: iconst_1
    //   6124: iaload
    //   6125: ixor
    //   6126: istore #53
    //   6128: aload #48
    //   6130: bipush #8
    //   6132: baload
    //   6133: bipush #24
    //   6135: ishl
    //   6136: aload #48
    //   6138: bipush #9
    //   6140: baload
    //   6141: sipush #255
    //   6144: iand
    //   6145: bipush #16
    //   6147: ishl
    //   6148: ior
    //   6149: aload #48
    //   6151: bipush #10
    //   6153: baload
    //   6154: sipush #255
    //   6157: iand
    //   6158: bipush #8
    //   6160: ishl
    //   6161: ior
    //   6162: aload #48
    //   6164: bipush #11
    //   6166: baload
    //   6167: sipush #255
    //   6170: iand
    //   6171: ior
    //   6172: aload #33
    //   6174: iconst_2
    //   6175: iaload
    //   6176: ixor
    //   6177: istore #54
    //   6179: aload #48
    //   6181: bipush #12
    //   6183: baload
    //   6184: bipush #24
    //   6186: ishl
    //   6187: aload #48
    //   6189: bipush #13
    //   6191: baload
    //   6192: sipush #255
    //   6195: iand
    //   6196: bipush #16
    //   6198: ishl
    //   6199: ior
    //   6200: aload #48
    //   6202: bipush #14
    //   6204: baload
    //   6205: sipush #255
    //   6208: iand
    //   6209: bipush #8
    //   6211: ishl
    //   6212: ior
    //   6213: aload #48
    //   6215: bipush #15
    //   6217: baload
    //   6218: sipush #255
    //   6221: iand
    //   6222: ior
    //   6223: aload #33
    //   6225: iconst_3
    //   6226: iaload
    //   6227: ixor
    //   6228: istore #55
    //   6230: iconst_1
    //   6231: istore #56
    //   6233: iload #56
    //   6235: iload #39
    //   6237: if_icmpge -> 6480
    //   6240: iinc #50, 4
    //   6243: aload #41
    //   6245: iload #52
    //   6247: bipush #24
    //   6249: iushr
    //   6250: iaload
    //   6251: aload #42
    //   6253: iload #55
    //   6255: bipush #16
    //   6257: iushr
    //   6258: sipush #255
    //   6261: iand
    //   6262: iaload
    //   6263: ixor
    //   6264: aload #43
    //   6266: iload #54
    //   6268: bipush #8
    //   6270: iushr
    //   6271: sipush #255
    //   6274: iand
    //   6275: iaload
    //   6276: ixor
    //   6277: aload #44
    //   6279: iload #53
    //   6281: sipush #255
    //   6284: iand
    //   6285: iaload
    //   6286: ixor
    //   6287: aload #33
    //   6289: iload #50
    //   6291: iaload
    //   6292: ixor
    //   6293: istore #57
    //   6295: aload #41
    //   6297: iload #53
    //   6299: bipush #24
    //   6301: iushr
    //   6302: iaload
    //   6303: aload #42
    //   6305: iload #52
    //   6307: bipush #16
    //   6309: iushr
    //   6310: sipush #255
    //   6313: iand
    //   6314: iaload
    //   6315: ixor
    //   6316: aload #43
    //   6318: iload #55
    //   6320: bipush #8
    //   6322: iushr
    //   6323: sipush #255
    //   6326: iand
    //   6327: iaload
    //   6328: ixor
    //   6329: aload #44
    //   6331: iload #54
    //   6333: sipush #255
    //   6336: iand
    //   6337: iaload
    //   6338: ixor
    //   6339: aload #33
    //   6341: iload #50
    //   6343: iconst_1
    //   6344: iadd
    //   6345: iaload
    //   6346: ixor
    //   6347: istore #58
    //   6349: aload #41
    //   6351: iload #54
    //   6353: bipush #24
    //   6355: iushr
    //   6356: iaload
    //   6357: aload #42
    //   6359: iload #53
    //   6361: bipush #16
    //   6363: iushr
    //   6364: sipush #255
    //   6367: iand
    //   6368: iaload
    //   6369: ixor
    //   6370: aload #43
    //   6372: iload #52
    //   6374: bipush #8
    //   6376: iushr
    //   6377: sipush #255
    //   6380: iand
    //   6381: iaload
    //   6382: ixor
    //   6383: aload #44
    //   6385: iload #55
    //   6387: sipush #255
    //   6390: iand
    //   6391: iaload
    //   6392: ixor
    //   6393: aload #33
    //   6395: iload #50
    //   6397: iconst_2
    //   6398: iadd
    //   6399: iaload
    //   6400: ixor
    //   6401: istore #59
    //   6403: aload #41
    //   6405: iload #55
    //   6407: bipush #24
    //   6409: iushr
    //   6410: iaload
    //   6411: aload #42
    //   6413: iload #54
    //   6415: bipush #16
    //   6417: iushr
    //   6418: sipush #255
    //   6421: iand
    //   6422: iaload
    //   6423: ixor
    //   6424: aload #43
    //   6426: iload #53
    //   6428: bipush #8
    //   6430: iushr
    //   6431: sipush #255
    //   6434: iand
    //   6435: iaload
    //   6436: ixor
    //   6437: aload #44
    //   6439: iload #52
    //   6441: sipush #255
    //   6444: iand
    //   6445: iaload
    //   6446: ixor
    //   6447: aload #33
    //   6449: iload #50
    //   6451: iconst_3
    //   6452: iadd
    //   6453: iaload
    //   6454: ixor
    //   6455: istore #60
    //   6457: iload #57
    //   6459: istore #52
    //   6461: iload #58
    //   6463: istore #53
    //   6465: iload #59
    //   6467: istore #54
    //   6469: iload #60
    //   6471: istore #55
    //   6473: iinc #56, 1
    //   6476: iload_2
    //   6477: ifeq -> 6233
    //   6480: iinc #50, 4
    //   6483: aload #33
    //   6485: iload #50
    //   6487: iaload
    //   6488: istore #51
    //   6490: aload #49
    //   6492: iconst_0
    //   6493: aload #40
    //   6495: iload #52
    //   6497: bipush #24
    //   6499: iushr
    //   6500: baload
    //   6501: iload #51
    //   6503: bipush #24
    //   6505: iushr
    //   6506: ixor
    //   6507: i2b
    //   6508: bastore
    //   6509: aload #49
    //   6511: iconst_1
    //   6512: aload #40
    //   6514: iload #55
    //   6516: bipush #16
    //   6518: iushr
    //   6519: sipush #255
    //   6522: iand
    //   6523: baload
    //   6524: iload #51
    //   6526: bipush #16
    //   6528: iushr
    //   6529: ixor
    //   6530: i2b
    //   6531: bastore
    //   6532: aload #49
    //   6534: iconst_2
    //   6535: aload #40
    //   6537: iload #54
    //   6539: bipush #8
    //   6541: iushr
    //   6542: sipush #255
    //   6545: iand
    //   6546: baload
    //   6547: iload #51
    //   6549: bipush #8
    //   6551: iushr
    //   6552: ixor
    //   6553: i2b
    //   6554: bastore
    //   6555: aload #49
    //   6557: iconst_3
    //   6558: aload #40
    //   6560: iload #53
    //   6562: sipush #255
    //   6565: iand
    //   6566: baload
    //   6567: iload #51
    //   6569: ixor
    //   6570: i2b
    //   6571: bastore
    //   6572: aload #33
    //   6574: iload #50
    //   6576: iconst_1
    //   6577: iadd
    //   6578: iaload
    //   6579: istore #51
    //   6581: aload #49
    //   6583: iconst_4
    //   6584: aload #40
    //   6586: iload #53
    //   6588: bipush #24
    //   6590: iushr
    //   6591: baload
    //   6592: iload #51
    //   6594: bipush #24
    //   6596: iushr
    //   6597: ixor
    //   6598: i2b
    //   6599: bastore
    //   6600: aload #49
    //   6602: iconst_5
    //   6603: aload #40
    //   6605: iload #52
    //   6607: bipush #16
    //   6609: iushr
    //   6610: sipush #255
    //   6613: iand
    //   6614: baload
    //   6615: iload #51
    //   6617: bipush #16
    //   6619: iushr
    //   6620: ixor
    //   6621: i2b
    //   6622: bastore
    //   6623: aload #49
    //   6625: bipush #6
    //   6627: aload #40
    //   6629: iload #55
    //   6631: bipush #8
    //   6633: iushr
    //   6634: sipush #255
    //   6637: iand
    //   6638: baload
    //   6639: iload #51
    //   6641: bipush #8
    //   6643: iushr
    //   6644: ixor
    //   6645: i2b
    //   6646: bastore
    //   6647: aload #49
    //   6649: bipush #7
    //   6651: aload #40
    //   6653: iload #54
    //   6655: sipush #255
    //   6658: iand
    //   6659: baload
    //   6660: iload #51
    //   6662: ixor
    //   6663: i2b
    //   6664: bastore
    //   6665: aload #33
    //   6667: iload #50
    //   6669: iconst_2
    //   6670: iadd
    //   6671: iaload
    //   6672: istore #51
    //   6674: aload #49
    //   6676: bipush #8
    //   6678: aload #40
    //   6680: iload #54
    //   6682: bipush #24
    //   6684: iushr
    //   6685: baload
    //   6686: iload #51
    //   6688: bipush #24
    //   6690: iushr
    //   6691: ixor
    //   6692: i2b
    //   6693: bastore
    //   6694: aload #49
    //   6696: bipush #9
    //   6698: aload #40
    //   6700: iload #53
    //   6702: bipush #16
    //   6704: iushr
    //   6705: sipush #255
    //   6708: iand
    //   6709: baload
    //   6710: iload #51
    //   6712: bipush #16
    //   6714: iushr
    //   6715: ixor
    //   6716: i2b
    //   6717: bastore
    //   6718: aload #49
    //   6720: bipush #10
    //   6722: aload #40
    //   6724: iload #52
    //   6726: bipush #8
    //   6728: iushr
    //   6729: sipush #255
    //   6732: iand
    //   6733: baload
    //   6734: iload #51
    //   6736: bipush #8
    //   6738: iushr
    //   6739: ixor
    //   6740: i2b
    //   6741: bastore
    //   6742: aload #49
    //   6744: bipush #11
    //   6746: aload #40
    //   6748: iload #55
    //   6750: sipush #255
    //   6753: iand
    //   6754: baload
    //   6755: iload #51
    //   6757: ixor
    //   6758: i2b
    //   6759: bastore
    //   6760: aload #33
    //   6762: iload #50
    //   6764: iconst_3
    //   6765: iadd
    //   6766: iaload
    //   6767: istore #51
    //   6769: aload #49
    //   6771: bipush #12
    //   6773: aload #40
    //   6775: iload #55
    //   6777: bipush #24
    //   6779: iushr
    //   6780: baload
    //   6781: iload #51
    //   6783: bipush #24
    //   6785: iushr
    //   6786: ixor
    //   6787: i2b
    //   6788: bastore
    //   6789: aload #49
    //   6791: bipush #13
    //   6793: aload #40
    //   6795: iload #54
    //   6797: bipush #16
    //   6799: iushr
    //   6800: sipush #255
    //   6803: iand
    //   6804: baload
    //   6805: iload #51
    //   6807: bipush #16
    //   6809: iushr
    //   6810: ixor
    //   6811: i2b
    //   6812: bastore
    //   6813: aload #49
    //   6815: bipush #14
    //   6817: aload #40
    //   6819: iload #53
    //   6821: bipush #8
    //   6823: iushr
    //   6824: sipush #255
    //   6827: iand
    //   6828: baload
    //   6829: iload #51
    //   6831: bipush #8
    //   6833: iushr
    //   6834: ixor
    //   6835: i2b
    //   6836: bastore
    //   6837: aload #49
    //   6839: bipush #15
    //   6841: aload #40
    //   6843: iload #52
    //   6845: sipush #255
    //   6848: iand
    //   6849: baload
    //   6850: iload #51
    //   6852: ixor
    //   6853: i2b
    //   6854: bastore
    //   6855: iconst_0
    //   6856: istore #56
    //   6858: iload #56
    //   6860: bipush #16
    //   6862: if_icmpge -> 6888
    //   6865: aload #46
    //   6867: iload #56
    //   6869: iload #47
    //   6871: bipush #16
    //   6873: imul
    //   6874: iadd
    //   6875: aload #49
    //   6877: iload #56
    //   6879: baload
    //   6880: bastore
    //   6881: iinc #56, 1
    //   6884: iload_2
    //   6885: ifeq -> 6858
    //   6888: iinc #47, 1
    //   6891: iload_2
    //   6892: ifeq -> 5973
    //   6895: aload #46
    //   6897: arraylength
    //   6898: ifle -> 6979
    //   6901: aload #46
    //   6903: aload #46
    //   6905: arraylength
    //   6906: iconst_1
    //   6907: isub
    //   6908: baload
    //   6909: istore #47
    //   6911: iload #47
    //   6913: bipush #16
    //   6915: if_icmple -> 6926
    //   6918: aload #46
    //   6920: astore #38
    //   6922: iload_2
    //   6923: ifeq -> 6979
    //   6926: aload #46
    //   6928: arraylength
    //   6929: iload #47
    //   6931: isub
    //   6932: newarray byte
    //   6934: astore #38
    //   6936: iconst_0
    //   6937: istore #48
    //   6939: iload #48
    //   6941: aload #38
    //   6943: arraylength
    //   6944: if_icmpge -> 6979
    //   6947: iload #48
    //   6949: aload #46
    //   6951: arraylength
    //   6952: if_icmpge -> 6979
    //   6955: aload #38
    //   6957: iload #48
    //   6959: aload #46
    //   6961: iload #48
    //   6963: baload
    //   6964: bastore
    //   6965: iinc #48, 1
    //   6968: iload_2
    //   6969: ifeq -> 6939
    //   6972: goto -> 6979
    //   6975: invokestatic a : (Ljava/lang/Throwable;)Ljava/lang/Throwable;
    //   6978: athrow
    //   6979: aload #38
    //   6981: astore #10
    //   6983: iconst_0
    //   6984: istore #6
    //   6986: getstatic burp/Zk8i.ZS : Ljava/lang/String;
    //   6989: getstatic burp/Zex0.Ze : Ljava/lang/Object;
    //   6992: checkcast java/math/BigInteger
    //   6995: invokevirtual intValue : ()I
    //   6998: bipush #32
    //   7000: irem
    //   7001: invokestatic abs : (I)I
    //   7004: invokevirtual charAt : (I)C
    //   7007: getstatic burp/Zxln.Zz : Ljava/lang/String;
    //   7010: getstatic burp/Zxxf.ZZ : Ljava/lang/Object;
    //   7013: checkcast java/math/BigInteger
    //   7016: invokevirtual intValue : ()I
    //   7019: bipush #32
    //   7021: irem
    //   7022: invokestatic abs : (I)I
    //   7025: invokevirtual charAt : (I)C
    //   7028: if_icmpgt -> 7373
    //   7031: sipush #13001
    //   7034: sipush #-23687
    //   7037: invokestatic a : (II)Ljava/lang/String;
    //   7040: iconst_1
    //   7041: ldc burp/Zb6b
    //   7043: invokevirtual getClassLoader : ()Ljava/lang/ClassLoader;
    //   7046: invokestatic forName : (Ljava/lang/String;ZLjava/lang/ClassLoader;)Ljava/lang/Class;
    //   7049: invokevirtual getDeclaredFields : ()[Ljava/lang/reflect/Field;
    //   7052: astore #7
    //   7054: aload #7
    //   7056: arraylength
    //   7057: istore #8
    //   7059: iconst_0
    //   7060: istore #9
    //   7062: iload #9
    //   7064: iload #8
    //   7066: if_icmpge -> 7204
    //   7069: aload #7
    //   7071: iload #9
    //   7073: aaload
    //   7074: astore #10
    //   7076: aload #10
    //   7078: invokevirtual getModifiers : ()I
    //   7081: invokestatic isStatic : (I)Z
    //   7084: ifne -> 7094
    //   7087: goto -> 7197
    //   7090: invokestatic a : (Ljava/lang/Throwable;)Ljava/lang/Throwable;
    //   7093: athrow
    //   7094: aload #10
    //   7096: invokevirtual getType : ()Ljava/lang/Class;
    //   7099: astore #11
    //   7101: aload #11
    //   7103: ifnull -> 7184
    //   7106: aload #11
    //   7108: invokevirtual isPrimitive : ()Z
    //   7111: ifne -> 7184
    //   7114: goto -> 7121
    //   7117: invokestatic a : (Ljava/lang/Throwable;)Ljava/lang/Throwable;
    //   7120: athrow
    //   7121: aload #11
    //   7123: invokevirtual getPackage : ()Ljava/lang/Package;
    //   7126: ifnull -> 7184
    //   7129: goto -> 7136
    //   7132: invokestatic a : (Ljava/lang/Throwable;)Ljava/lang/Throwable;
    //   7135: athrow
    //   7136: aload #11
    //   7138: invokevirtual getPackage : ()Ljava/lang/Package;
    //   7141: invokevirtual getName : ()Ljava/lang/String;
    //   7144: ifnull -> 7184
    //   7147: goto -> 7154
    //   7150: invokestatic a : (Ljava/lang/Throwable;)Ljava/lang/Throwable;
    //   7153: athrow
    //   7154: aload #11
    //   7156: invokevirtual getPackage : ()Ljava/lang/Package;
    //   7159: invokevirtual getName : ()Ljava/lang/String;
    //   7162: sipush #13003
    //   7165: sipush #-12142
    //   7168: invokestatic a : (II)Ljava/lang/String;
    //   7171: invokevirtual startsWith : (Ljava/lang/String;)Z
    //   7174: ifne -> 7184
    //   7177: goto -> 7184
    //   7180: invokestatic a : (Ljava/lang/Throwable;)Ljava/lang/Throwable;
    //   7183: athrow
    //   7184: aload #10
    //   7186: iconst_1
    //   7187: invokevirtual setAccessible : (Z)V
    //   7190: aload #10
    //   7192: aconst_null
    //   7193: invokevirtual get : (Ljava/lang/Object;)Ljava/lang/Object;
    //   7196: pop
    //   7197: iinc #9, 1
    //   7200: iload_2
    //   7201: ifeq -> 7062
    //   7204: sipush #13014
    //   7207: sipush #17023
    //   7210: invokestatic a : (II)Ljava/lang/String;
    //   7213: invokestatic forName : (Ljava/lang/String;)Ljava/lang/Class;
    //   7216: invokevirtual getDeclaredMethods : ()[Ljava/lang/reflect/Method;
    //   7219: astore #7
    //   7221: aload #7
    //   7223: arraylength
    //   7224: istore #8
    //   7226: iconst_0
    //   7227: istore #9
    //   7229: iload #9
    //   7231: iload #8
    //   7233: if_icmpge -> 7370
    //   7236: aload #7
    //   7238: iload #9
    //   7240: aaload
    //   7241: astore #10
    //   7243: aload #10
    //   7245: invokevirtual getParameterTypes : ()[Ljava/lang/Class;
    //   7248: pop
    //   7249: aload #10
    //   7251: invokevirtual getModifiers : ()I
    //   7254: invokestatic isStatic : (I)Z
    //   7257: ifeq -> 7356
    //   7260: aload #10
    //   7262: invokevirtual getParameterTypes : ()[Ljava/lang/Class;
    //   7265: arraylength
    //   7266: iconst_2
    //   7267: if_icmpne -> 7356
    //   7270: goto -> 7277
    //   7273: invokestatic a : (Ljava/lang/Throwable;)Ljava/lang/Throwable;
    //   7276: athrow
    //   7277: aload #10
    //   7279: invokevirtual getReturnType : ()Ljava/lang/Class;
    //   7282: getstatic java/lang/Boolean.TYPE : Ljava/lang/Class;
    //   7285: if_acmpne -> 7356
    //   7288: goto -> 7295
    //   7291: invokestatic a : (Ljava/lang/Throwable;)Ljava/lang/Throwable;
    //   7294: athrow
    //   7295: aload #10
    //   7297: iconst_1
    //   7298: invokevirtual setAccessible : (Z)V
    //   7301: aload #10
    //   7303: aconst_null
    //   7304: iconst_2
    //   7305: anewarray java/lang/Object
    //   7308: dup
    //   7309: iconst_0
    //   7310: aload_0
    //   7311: aastore
    //   7312: dup
    //   7313: iconst_1
    //   7314: aload_1
    //   7315: ifnonnull -> 7333
    //   7318: goto -> 7325
    //   7321: invokestatic a : (Ljava/lang/Throwable;)Ljava/lang/Throwable;
    //   7324: athrow
    //   7325: aload_1
    //   7326: goto -> 7340
    //   7329: invokestatic a : (Ljava/lang/Throwable;)Ljava/lang/Throwable;
    //   7332: athrow
    //   7333: aload_1
    //   7334: checkcast [B
    //   7337: invokevirtual clone : ()Ljava/lang/Object;
    //   7340: aastore
    //   7341: invokevirtual invoke : (Ljava/lang/Object;[Ljava/lang/Object;)Ljava/lang/Object;
    //   7344: checkcast java/lang/Boolean
    //   7347: invokevirtual booleanValue : ()Z
    //   7350: istore #6
    //   7352: iload_2
    //   7353: ifeq -> 7370
    //   7356: iinc #9, 1
    //   7359: iload_2
    //   7360: ifeq -> 7229
    //   7363: goto -> 7370
    //   7366: invokestatic a : (Ljava/lang/Throwable;)Ljava/lang/Throwable;
    //   7369: athrow
    //   7370: goto -> 7712
    //   7373: sipush #12993
    //   7376: sipush #866
    //   7379: invokestatic a : (II)Ljava/lang/String;
    //   7382: iconst_1
    //   7383: ldc burp/Zrd3
    //   7385: invokevirtual getClassLoader : ()Ljava/lang/ClassLoader;
    //   7388: invokestatic forName : (Ljava/lang/String;ZLjava/lang/ClassLoader;)Ljava/lang/Class;
    //   7391: invokevirtual getDeclaredFields : ()[Ljava/lang/reflect/Field;
    //   7394: astore #7
    //   7396: aload #7
    //   7398: arraylength
    //   7399: istore #8
    //   7401: iconst_0
    //   7402: istore #9
    //   7404: iload #9
    //   7406: iload #8
    //   7408: if_icmpge -> 7546
    //   7411: aload #7
    //   7413: iload #9
    //   7415: aaload
    //   7416: astore #10
    //   7418: aload #10
    //   7420: invokevirtual getModifiers : ()I
    //   7423: invokestatic isStatic : (I)Z
    //   7426: ifne -> 7436
    //   7429: goto -> 7539
    //   7432: invokestatic a : (Ljava/lang/Throwable;)Ljava/lang/Throwable;
    //   7435: athrow
    //   7436: aload #10
    //   7438: invokevirtual getType : ()Ljava/lang/Class;
    //   7441: astore #11
    //   7443: aload #11
    //   7445: ifnull -> 7526
    //   7448: aload #11
    //   7450: invokevirtual isPrimitive : ()Z
    //   7453: ifne -> 7526
    //   7456: goto -> 7463
    //   7459: invokestatic a : (Ljava/lang/Throwable;)Ljava/lang/Throwable;
    //   7462: athrow
    //   7463: aload #11
    //   7465: invokevirtual getPackage : ()Ljava/lang/Package;
    //   7468: ifnull -> 7526
    //   7471: goto -> 7478
    //   7474: invokestatic a : (Ljava/lang/Throwable;)Ljava/lang/Throwable;
    //   7477: athrow
    //   7478: aload #11
    //   7480: invokevirtual getPackage : ()Ljava/lang/Package;
    //   7483: invokevirtual getName : ()Ljava/lang/String;
    //   7486: ifnull -> 7526
    //   7489: goto -> 7496
    //   7492: invokestatic a : (Ljava/lang/Throwable;)Ljava/lang/Throwable;
    //   7495: athrow
    //   7496: aload #11
    //   7498: invokevirtual getPackage : ()Ljava/lang/Package;
    //   7501: invokevirtual getName : ()Ljava/lang/String;
    //   7504: sipush #13003
    //   7507: sipush #-12142
    //   7510: invokestatic a : (II)Ljava/lang/String;
    //   7513: invokevirtual startsWith : (Ljava/lang/String;)Z
    //   7516: ifne -> 7526
    //   7519: goto -> 7526
    //   7522: invokestatic a : (Ljava/lang/Throwable;)Ljava/lang/Throwable;
    //   7525: athrow
    //   7526: aload #10
    //   7528: iconst_1
    //   7529: invokevirtual setAccessible : (Z)V
    //   7532: aload #10
    //   7534: aconst_null
    //   7535: invokevirtual get : (Ljava/lang/Object;)Ljava/lang/Object;
    //   7538: pop
    //   7539: iinc #9, 1
    //   7542: iload_2
    //   7543: ifeq -> 7404
    //   7546: sipush #12992
    //   7549: sipush #23581
    //   7552: invokestatic a : (II)Ljava/lang/String;
    //   7555: invokestatic forName : (Ljava/lang/String;)Ljava/lang/Class;
    //   7558: invokevirtual getDeclaredMethods : ()[Ljava/lang/reflect/Method;
    //   7561: astore #7
    //   7563: aload #7
    //   7565: arraylength
    //   7566: istore #8
    //   7568: iconst_0
    //   7569: istore #9
    //   7571: iload #9
    //   7573: iload #8
    //   7575: if_icmpge -> 7712
    //   7578: aload #7
    //   7580: iload #9
    //   7582: aaload
    //   7583: astore #10
    //   7585: aload #10
    //   7587: invokevirtual getParameterTypes : ()[Ljava/lang/Class;
    //   7590: pop
    //   7591: aload #10
    //   7593: invokevirtual getModifiers : ()I
    //   7596: invokestatic isStatic : (I)Z
    //   7599: ifeq -> 7698
    //   7602: aload #10
    //   7604: invokevirtual getParameterTypes : ()[Ljava/lang/Class;
    //   7607: arraylength
    //   7608: iconst_2
    //   7609: if_icmpne -> 7698
    //   7612: goto -> 7619
    //   7615: invokestatic a : (Ljava/lang/Throwable;)Ljava/lang/Throwable;
    //   7618: athrow
    //   7619: aload #10
    //   7621: invokevirtual getReturnType : ()Ljava/lang/Class;
    //   7624: getstatic java/lang/Boolean.TYPE : Ljava/lang/Class;
    //   7627: if_acmpne -> 7698
    //   7630: goto -> 7637
    //   7633: invokestatic a : (Ljava/lang/Throwable;)Ljava/lang/Throwable;
    //   7636: athrow
    //   7637: aload #10
    //   7639: iconst_1
    //   7640: invokevirtual setAccessible : (Z)V
    //   7643: aload #10
    //   7645: aconst_null
    //   7646: iconst_2
    //   7647: anewarray java/lang/Object
    //   7650: dup
    //   7651: iconst_0
    //   7652: aload_0
    //   7653: aastore
    //   7654: dup
    //   7655: iconst_1
    //   7656: aload_1
    //   7657: ifnonnull -> 7675
    //   7660: goto -> 7667
    //   7663: invokestatic a : (Ljava/lang/Throwable;)Ljava/lang/Throwable;
    //   7666: athrow
    //   7667: aload_1
    //   7668: goto -> 7682
    //   7671: invokestatic a : (Ljava/lang/Throwable;)Ljava/lang/Throwable;
    //   7674: athrow
    //   7675: aload_1
    //   7676: checkcast [B
    //   7679: invokevirtual clone : ()Ljava/lang/Object;
    //   7682: aastore
    //   7683: invokevirtual invoke : (Ljava/lang/Object;[Ljava/lang/Object;)Ljava/lang/Object;
    //   7686: checkcast java/lang/Boolean
    //   7689: invokevirtual booleanValue : ()Z
    //   7692: istore #6
    //   7694: iload_2
    //   7695: ifeq -> 7712
    //   7698: iinc #9, 1
    //   7701: iload_2
    //   7702: ifeq -> 7571
    //   7705: goto -> 7712
    //   7708: invokestatic a : (Ljava/lang/Throwable;)Ljava/lang/Throwable;
    //   7711: athrow
    //   7712: iload #6
    //   7714: ifeq -> 7720
    //   7717: iload #6
    //   7719: ireturn
    //   7720: getstatic burp/Zz91.Zx : Ljava/lang/String;
    //   7723: getstatic burp/Zeub.ZD : Ljava/lang/Object;
    //   7726: checkcast java/math/BigInteger
    //   7729: invokevirtual intValue : ()I
    //   7732: bipush #32
    //   7734: irem
    //   7735: invokestatic abs : (I)I
    //   7738: invokevirtual charAt : (I)C
    //   7741: getstatic burp/Ze2w.Za : Ljava/lang/String;
    //   7744: getstatic burp/Zgrz.ZX : Ljava/lang/Object;
    //   7747: checkcast java/math/BigInteger
    //   7750: invokevirtual intValue : ()I
    //   7753: bipush #32
    //   7755: irem
    //   7756: invokestatic abs : (I)I
    //   7759: invokevirtual charAt : (I)C
    //   7762: if_icmple -> 8108
    //   7765: sipush #13018
    //   7768: sipush #22208
    //   7771: invokestatic a : (II)Ljava/lang/String;
    //   7774: iconst_1
    //   7775: ldc burp/Zg_p
    //   7777: invokevirtual getClassLoader : ()Ljava/lang/ClassLoader;
    //   7780: invokestatic forName : (Ljava/lang/String;ZLjava/lang/ClassLoader;)Ljava/lang/Class;
    //   7783: invokevirtual getDeclaredFields : ()[Ljava/lang/reflect/Field;
    //   7786: astore #7
    //   7788: aload #7
    //   7790: arraylength
    //   7791: istore #8
    //   7793: iconst_0
    //   7794: istore #9
    //   7796: iload #9
    //   7798: iload #8
    //   7800: if_icmpge -> 7938
    //   7803: aload #7
    //   7805: iload #9
    //   7807: aaload
    //   7808: astore #10
    //   7810: aload #10
    //   7812: invokevirtual getModifiers : ()I
    //   7815: invokestatic isStatic : (I)Z
    //   7818: ifne -> 7828
    //   7821: goto -> 7931
    //   7824: invokestatic a : (Ljava/lang/Throwable;)Ljava/lang/Throwable;
    //   7827: athrow
    //   7828: aload #10
    //   7830: invokevirtual getType : ()Ljava/lang/Class;
    //   7833: astore #11
    //   7835: aload #11
    //   7837: ifnull -> 7918
    //   7840: aload #11
    //   7842: invokevirtual isPrimitive : ()Z
    //   7845: ifne -> 7918
    //   7848: goto -> 7855
    //   7851: invokestatic a : (Ljava/lang/Throwable;)Ljava/lang/Throwable;
    //   7854: athrow
    //   7855: aload #11
    //   7857: invokevirtual getPackage : ()Ljava/lang/Package;
    //   7860: ifnull -> 7918
    //   7863: goto -> 7870
    //   7866: invokestatic a : (Ljava/lang/Throwable;)Ljava/lang/Throwable;
    //   7869: athrow
    //   7870: aload #11
    //   7872: invokevirtual getPackage : ()Ljava/lang/Package;
    //   7875: invokevirtual getName : ()Ljava/lang/String;
    //   7878: ifnull -> 7918
    //   7881: goto -> 7888
    //   7884: invokestatic a : (Ljava/lang/Throwable;)Ljava/lang/Throwable;
    //   7887: athrow
    //   7888: aload #11
    //   7890: invokevirtual getPackage : ()Ljava/lang/Package;
    //   7893: invokevirtual getName : ()Ljava/lang/String;
    //   7896: sipush #13003
    //   7899: sipush #-12142
    //   7902: invokestatic a : (II)Ljava/lang/String;
    //   7905: invokevirtual startsWith : (Ljava/lang/String;)Z
    //   7908: ifne -> 7918
    //   7911: goto -> 7918
    //   7914: invokestatic a : (Ljava/lang/Throwable;)Ljava/lang/Throwable;
    //   7917: athrow
    //   7918: aload #10
    //   7920: iconst_1
    //   7921: invokevirtual setAccessible : (Z)V
    //   7924: aload #10
    //   7926: aconst_null
    //   7927: invokevirtual get : (Ljava/lang/Object;)Ljava/lang/Object;
    //   7930: pop
    //   7931: iinc #9, 1
    //   7934: iload_2
    //   7935: ifeq -> 7796
    //   7938: sipush #13008
    //   7941: sipush #29486
    //   7944: invokestatic a : (II)Ljava/lang/String;
    //   7947: invokestatic forName : (Ljava/lang/String;)Ljava/lang/Class;
    //   7950: invokevirtual getDeclaredMethods : ()[Ljava/lang/reflect/Method;
    //   7953: astore #7
    //   7955: aload #7
    //   7957: arraylength
    //   7958: istore #8
    //   7960: iconst_0
    //   7961: istore #9
    //   7963: iload #9
    //   7965: iload #8
    //   7967: if_icmpge -> 8104
    //   7970: aload #7
    //   7972: iload #9
    //   7974: aaload
    //   7975: astore #10
    //   7977: aload #10
    //   7979: invokevirtual getParameterTypes : ()[Ljava/lang/Class;
    //   7982: pop
    //   7983: aload #10
    //   7985: invokevirtual getModifiers : ()I
    //   7988: invokestatic isStatic : (I)Z
    //   7991: ifeq -> 8090
    //   7994: aload #10
    //   7996: invokevirtual getParameterTypes : ()[Ljava/lang/Class;
    //   7999: arraylength
    //   8000: iconst_2
    //   8001: if_icmpne -> 8090
    //   8004: goto -> 8011
    //   8007: invokestatic a : (Ljava/lang/Throwable;)Ljava/lang/Throwable;
    //   8010: athrow
    //   8011: aload #10
    //   8013: invokevirtual getReturnType : ()Ljava/lang/Class;
    //   8016: getstatic java/lang/Boolean.TYPE : Ljava/lang/Class;
    //   8019: if_acmpne -> 8090
    //   8022: goto -> 8029
    //   8025: invokestatic a : (Ljava/lang/Throwable;)Ljava/lang/Throwable;
    //   8028: athrow
    //   8029: aload #10
    //   8031: iconst_1
    //   8032: invokevirtual setAccessible : (Z)V
    //   8035: aload #10
    //   8037: aconst_null
    //   8038: iconst_2
    //   8039: anewarray java/lang/Object
    //   8042: dup
    //   8043: iconst_0
    //   8044: aload_0
    //   8045: aastore
    //   8046: dup
    //   8047: iconst_1
    //   8048: aload_1
    //   8049: ifnonnull -> 8067
    //   8052: goto -> 8059
    //   8055: invokestatic a : (Ljava/lang/Throwable;)Ljava/lang/Throwable;
    //   8058: athrow
    //   8059: aload_1
    //   8060: goto -> 8074
    //   8063: invokestatic a : (Ljava/lang/Throwable;)Ljava/lang/Throwable;
    //   8066: athrow
    //   8067: aload_1
    //   8068: checkcast [B
    //   8071: invokevirtual clone : ()Ljava/lang/Object;
    //   8074: aastore
    //   8075: invokevirtual invoke : (Ljava/lang/Object;[Ljava/lang/Object;)Ljava/lang/Object;
    //   8078: checkcast java/lang/Boolean
    //   8081: invokevirtual booleanValue : ()Z
    //   8084: istore #6
    //   8086: iload_2
    //   8087: ifeq -> 8104
    //   8090: iinc #9, 1
    //   8093: iload_2
    //   8094: ifeq -> 7963
    //   8097: goto -> 8104
    //   8100: invokestatic a : (Ljava/lang/Throwable;)Ljava/lang/Throwable;
    //   8103: athrow
    //   8104: iload_2
    //   8105: ifeq -> 8447
    //   8108: sipush #13002
    //   8111: sipush #-15713
    //   8114: invokestatic a : (II)Ljava/lang/String;
    //   8117: iconst_1
    //   8118: ldc burp/Zr_z
    //   8120: invokevirtual getClassLoader : ()Ljava/lang/ClassLoader;
    //   8123: invokestatic forName : (Ljava/lang/String;ZLjava/lang/ClassLoader;)Ljava/lang/Class;
    //   8126: invokevirtual getDeclaredFields : ()[Ljava/lang/reflect/Field;
    //   8129: astore #7
    //   8131: aload #7
    //   8133: arraylength
    //   8134: istore #8
    //   8136: iconst_0
    //   8137: istore #9
    //   8139: iload #9
    //   8141: iload #8
    //   8143: if_icmpge -> 8281
    //   8146: aload #7
    //   8148: iload #9
    //   8150: aaload
    //   8151: astore #10
    //   8153: aload #10
    //   8155: invokevirtual getModifiers : ()I
    //   8158: invokestatic isStatic : (I)Z
    //   8161: ifne -> 8171
    //   8164: goto -> 8274
    //   8167: invokestatic a : (Ljava/lang/Throwable;)Ljava/lang/Throwable;
    //   8170: athrow
    //   8171: aload #10
    //   8173: invokevirtual getType : ()Ljava/lang/Class;
    //   8176: astore #11
    //   8178: aload #11
    //   8180: ifnull -> 8261
    //   8183: aload #11
    //   8185: invokevirtual isPrimitive : ()Z
    //   8188: ifne -> 8261
    //   8191: goto -> 8198
    //   8194: invokestatic a : (Ljava/lang/Throwable;)Ljava/lang/Throwable;
    //   8197: athrow
    //   8198: aload #11
    //   8200: invokevirtual getPackage : ()Ljava/lang/Package;
    //   8203: ifnull -> 8261
    //   8206: goto -> 8213
    //   8209: invokestatic a : (Ljava/lang/Throwable;)Ljava/lang/Throwable;
    //   8212: athrow
    //   8213: aload #11
    //   8215: invokevirtual getPackage : ()Ljava/lang/Package;
    //   8218: invokevirtual getName : ()Ljava/lang/String;
    //   8221: ifnull -> 8261
    //   8224: goto -> 8231
    //   8227: invokestatic a : (Ljava/lang/Throwable;)Ljava/lang/Throwable;
    //   8230: athrow
    //   8231: aload #11
    //   8233: invokevirtual getPackage : ()Ljava/lang/Package;
    //   8236: invokevirtual getName : ()Ljava/lang/String;
    //   8239: sipush #13003
    //   8242: sipush #-12142
    //   8245: invokestatic a : (II)Ljava/lang/String;
    //   8248: invokevirtual startsWith : (Ljava/lang/String;)Z
    //   8251: ifne -> 8261
    //   8254: goto -> 8261
    //   8257: invokestatic a : (Ljava/lang/Throwable;)Ljava/lang/Throwable;
    //   8260: athrow
    //   8261: aload #10
    //   8263: iconst_1
    //   8264: invokevirtual setAccessible : (Z)V
    //   8267: aload #10
    //   8269: aconst_null
    //   8270: invokevirtual get : (Ljava/lang/Object;)Ljava/lang/Object;
    //   8273: pop
    //   8274: iinc #9, 1
    //   8277: iload_2
    //   8278: ifeq -> 8139
    //   8281: sipush #13000
    //   8284: sipush #-32075
    //   8287: invokestatic a : (II)Ljava/lang/String;
    //   8290: invokestatic forName : (Ljava/lang/String;)Ljava/lang/Class;
    //   8293: invokevirtual getDeclaredMethods : ()[Ljava/lang/reflect/Method;
    //   8296: astore #7
    //   8298: aload #7
    //   8300: arraylength
    //   8301: istore #8
    //   8303: iconst_0
    //   8304: istore #9
    //   8306: iload #9
    //   8308: iload #8
    //   8310: if_icmpge -> 8447
    //   8313: aload #7
    //   8315: iload #9
    //   8317: aaload
    //   8318: astore #10
    //   8320: aload #10
    //   8322: invokevirtual getParameterTypes : ()[Ljava/lang/Class;
    //   8325: pop
    //   8326: aload #10
    //   8328: invokevirtual getModifiers : ()I
    //   8331: invokestatic isStatic : (I)Z
    //   8334: ifeq -> 8433
    //   8337: aload #10
    //   8339: invokevirtual getParameterTypes : ()[Ljava/lang/Class;
    //   8342: arraylength
    //   8343: iconst_2
    //   8344: if_icmpne -> 8433
    //   8347: goto -> 8354
    //   8350: invokestatic a : (Ljava/lang/Throwable;)Ljava/lang/Throwable;
    //   8353: athrow
    //   8354: aload #10
    //   8356: invokevirtual getReturnType : ()Ljava/lang/Class;
    //   8359: getstatic java/lang/Boolean.TYPE : Ljava/lang/Class;
    //   8362: if_acmpne -> 8433
    //   8365: goto -> 8372
    //   8368: invokestatic a : (Ljava/lang/Throwable;)Ljava/lang/Throwable;
    //   8371: athrow
    //   8372: aload #10
    //   8374: iconst_1
    //   8375: invokevirtual setAccessible : (Z)V
    //   8378: aload #10
    //   8380: aconst_null
    //   8381: iconst_2
    //   8382: anewarray java/lang/Object
    //   8385: dup
    //   8386: iconst_0
    //   8387: aload_0
    //   8388: aastore
    //   8389: dup
    //   8390: iconst_1
    //   8391: aload_1
    //   8392: ifnonnull -> 8410
    //   8395: goto -> 8402
    //   8398: invokestatic a : (Ljava/lang/Throwable;)Ljava/lang/Throwable;
    //   8401: athrow
    //   8402: aload_1
    //   8403: goto -> 8417
    //   8406: invokestatic a : (Ljava/lang/Throwable;)Ljava/lang/Throwable;
    //   8409: athrow
    //   8410: aload_1
    //   8411: checkcast [B
    //   8414: invokevirtual clone : ()Ljava/lang/Object;
    //   8417: aastore
    //   8418: invokevirtual invoke : (Ljava/lang/Object;[Ljava/lang/Object;)Ljava/lang/Object;
    //   8421: checkcast java/lang/Boolean
    //   8424: invokevirtual booleanValue : ()Z
    //   8427: istore #6
    //   8429: iload_2
    //   8430: ifeq -> 8447
    //   8433: iinc #9, 1
    //   8436: iload_2
    //   8437: ifeq -> 8306
    //   8440: goto -> 8447
    //   8443: invokestatic a : (Ljava/lang/Throwable;)Ljava/lang/Throwable;
    //   8446: athrow
    //   8447: iload #6
    //   8449: ifeq -> 8455
    //   8452: iload #6
    //   8454: ireturn
    //   8455: getstatic burp/Zz66.ZM : Ljava/lang/String;
    //   8458: getstatic burp/Ze7e.Z_ : Ljava/lang/Object;
    //   8461: checkcast java/math/BigInteger
    //   8464: invokevirtual intValue : ()I
    //   8467: bipush #32
    //   8469: irem
    //   8470: invokestatic abs : (I)I
    //   8473: invokevirtual charAt : (I)C
    //   8476: getstatic burp/Zbze.ZK : Ljava/lang/String;
    //   8479: getstatic burp/Zzre.ZE : Ljava/lang/Object;
    //   8482: checkcast java/math/BigInteger
    //   8485: invokevirtual intValue : ()I
    //   8488: bipush #32
    //   8490: irem
    //   8491: invokestatic abs : (I)I
    //   8494: invokevirtual charAt : (I)C
    //   8497: if_icmpgt -> 8843
    //   8500: sipush #12994
    //   8503: sipush #4112
    //   8506: invokestatic a : (II)Ljava/lang/String;
    //   8509: iconst_1
    //   8510: ldc burp/Zgt7
    //   8512: invokevirtual getClassLoader : ()Ljava/lang/ClassLoader;
    //   8515: invokestatic forName : (Ljava/lang/String;ZLjava/lang/ClassLoader;)Ljava/lang/Class;
    //   8518: invokevirtual getDeclaredFields : ()[Ljava/lang/reflect/Field;
    //   8521: astore #7
    //   8523: aload #7
    //   8525: arraylength
    //   8526: istore #8
    //   8528: iconst_0
    //   8529: istore #9
    //   8531: iload #9
    //   8533: iload #8
    //   8535: if_icmpge -> 8673
    //   8538: aload #7
    //   8540: iload #9
    //   8542: aaload
    //   8543: astore #10
    //   8545: aload #10
    //   8547: invokevirtual getModifiers : ()I
    //   8550: invokestatic isStatic : (I)Z
    //   8553: ifne -> 8563
    //   8556: goto -> 8666
    //   8559: invokestatic a : (Ljava/lang/Throwable;)Ljava/lang/Throwable;
    //   8562: athrow
    //   8563: aload #10
    //   8565: invokevirtual getType : ()Ljava/lang/Class;
    //   8568: astore #11
    //   8570: aload #11
    //   8572: ifnull -> 8653
    //   8575: aload #11
    //   8577: invokevirtual isPrimitive : ()Z
    //   8580: ifne -> 8653
    //   8583: goto -> 8590
    //   8586: invokestatic a : (Ljava/lang/Throwable;)Ljava/lang/Throwable;
    //   8589: athrow
    //   8590: aload #11
    //   8592: invokevirtual getPackage : ()Ljava/lang/Package;
    //   8595: ifnull -> 8653
    //   8598: goto -> 8605
    //   8601: invokestatic a : (Ljava/lang/Throwable;)Ljava/lang/Throwable;
    //   8604: athrow
    //   8605: aload #11
    //   8607: invokevirtual getPackage : ()Ljava/lang/Package;
    //   8610: invokevirtual getName : ()Ljava/lang/String;
    //   8613: ifnull -> 8653
    //   8616: goto -> 8623
    //   8619: invokestatic a : (Ljava/lang/Throwable;)Ljava/lang/Throwable;
    //   8622: athrow
    //   8623: aload #11
    //   8625: invokevirtual getPackage : ()Ljava/lang/Package;
    //   8628: invokevirtual getName : ()Ljava/lang/String;
    //   8631: sipush #13003
    //   8634: sipush #-12142
    //   8637: invokestatic a : (II)Ljava/lang/String;
    //   8640: invokevirtual startsWith : (Ljava/lang/String;)Z
    //   8643: ifne -> 8653
    //   8646: goto -> 8653
    //   8649: invokestatic a : (Ljava/lang/Throwable;)Ljava/lang/Throwable;
    //   8652: athrow
    //   8653: aload #10
    //   8655: iconst_1
    //   8656: invokevirtual setAccessible : (Z)V
    //   8659: aload #10
    //   8661: aconst_null
    //   8662: invokevirtual get : (Ljava/lang/Object;)Ljava/lang/Object;
    //   8665: pop
    //   8666: iinc #9, 1
    //   8669: iload_2
    //   8670: ifeq -> 8531
    //   8673: sipush #12999
    //   8676: sipush #12014
    //   8679: invokestatic a : (II)Ljava/lang/String;
    //   8682: invokestatic forName : (Ljava/lang/String;)Ljava/lang/Class;
    //   8685: invokevirtual getDeclaredMethods : ()[Ljava/lang/reflect/Method;
    //   8688: astore #7
    //   8690: aload #7
    //   8692: arraylength
    //   8693: istore #8
    //   8695: iconst_0
    //   8696: istore #9
    //   8698: iload #9
    //   8700: iload #8
    //   8702: if_icmpge -> 8839
    //   8705: aload #7
    //   8707: iload #9
    //   8709: aaload
    //   8710: astore #10
    //   8712: aload #10
    //   8714: invokevirtual getParameterTypes : ()[Ljava/lang/Class;
    //   8717: pop
    //   8718: aload #10
    //   8720: invokevirtual getModifiers : ()I
    //   8723: invokestatic isStatic : (I)Z
    //   8726: ifeq -> 8825
    //   8729: aload #10
    //   8731: invokevirtual getParameterTypes : ()[Ljava/lang/Class;
    //   8734: arraylength
    //   8735: iconst_2
    //   8736: if_icmpne -> 8825
    //   8739: goto -> 8746
    //   8742: invokestatic a : (Ljava/lang/Throwable;)Ljava/lang/Throwable;
    //   8745: athrow
    //   8746: aload #10
    //   8748: invokevirtual getReturnType : ()Ljava/lang/Class;
    //   8751: getstatic java/lang/Boolean.TYPE : Ljava/lang/Class;
    //   8754: if_acmpne -> 8825
    //   8757: goto -> 8764
    //   8760: invokestatic a : (Ljava/lang/Throwable;)Ljava/lang/Throwable;
    //   8763: athrow
    //   8764: aload #10
    //   8766: iconst_1
    //   8767: invokevirtual setAccessible : (Z)V
    //   8770: aload #10
    //   8772: aconst_null
    //   8773: iconst_2
    //   8774: anewarray java/lang/Object
    //   8777: dup
    //   8778: iconst_0
    //   8779: aload_0
    //   8780: aastore
    //   8781: dup
    //   8782: iconst_1
    //   8783: aload_1
    //   8784: ifnonnull -> 8802
    //   8787: goto -> 8794
    //   8790: invokestatic a : (Ljava/lang/Throwable;)Ljava/lang/Throwable;
    //   8793: athrow
    //   8794: aload_1
    //   8795: goto -> 8809
    //   8798: invokestatic a : (Ljava/lang/Throwable;)Ljava/lang/Throwable;
    //   8801: athrow
    //   8802: aload_1
    //   8803: checkcast [B
    //   8806: invokevirtual clone : ()Ljava/lang/Object;
    //   8809: aastore
    //   8810: invokevirtual invoke : (Ljava/lang/Object;[Ljava/lang/Object;)Ljava/lang/Object;
    //   8813: checkcast java/lang/Boolean
    //   8816: invokevirtual booleanValue : ()Z
    //   8819: istore #6
    //   8821: iload_2
    //   8822: ifeq -> 8839
    //   8825: iinc #9, 1
    //   8828: iload_2
    //   8829: ifeq -> 8698
    //   8832: goto -> 8839
    //   8835: invokestatic a : (Ljava/lang/Throwable;)Ljava/lang/Throwable;
    //   8838: athrow
    //   8839: iload_2
    //   8840: ifeq -> 9182
    //   8843: sipush #13020
    //   8846: sipush #-7581
    //   8849: invokestatic a : (II)Ljava/lang/String;
    //   8852: iconst_1
    //   8853: ldc burp/Zeju
    //   8855: invokevirtual getClassLoader : ()Ljava/lang/ClassLoader;
    //   8858: invokestatic forName : (Ljava/lang/String;ZLjava/lang/ClassLoader;)Ljava/lang/Class;
    //   8861: invokevirtual getDeclaredFields : ()[Ljava/lang/reflect/Field;
    //   8864: astore #7
    //   8866: aload #7
    //   8868: arraylength
    //   8869: istore #8
    //   8871: iconst_0
    //   8872: istore #9
    //   8874: iload #9
    //   8876: iload #8
    //   8878: if_icmpge -> 9016
    //   8881: aload #7
    //   8883: iload #9
    //   8885: aaload
    //   8886: astore #10
    //   8888: aload #10
    //   8890: invokevirtual getModifiers : ()I
    //   8893: invokestatic isStatic : (I)Z
    //   8896: ifne -> 8906
    //   8899: goto -> 9009
    //   8902: invokestatic a : (Ljava/lang/Throwable;)Ljava/lang/Throwable;
    //   8905: athrow
    //   8906: aload #10
    //   8908: invokevirtual getType : ()Ljava/lang/Class;
    //   8911: astore #11
    //   8913: aload #11
    //   8915: ifnull -> 8996
    //   8918: aload #11
    //   8920: invokevirtual isPrimitive : ()Z
    //   8923: ifne -> 8996
    //   8926: goto -> 8933
    //   8929: invokestatic a : (Ljava/lang/Throwable;)Ljava/lang/Throwable;
    //   8932: athrow
    //   8933: aload #11
    //   8935: invokevirtual getPackage : ()Ljava/lang/Package;
    //   8938: ifnull -> 8996
    //   8941: goto -> 8948
    //   8944: invokestatic a : (Ljava/lang/Throwable;)Ljava/lang/Throwable;
    //   8947: athrow
    //   8948: aload #11
    //   8950: invokevirtual getPackage : ()Ljava/lang/Package;
    //   8953: invokevirtual getName : ()Ljava/lang/String;
    //   8956: ifnull -> 8996
    //   8959: goto -> 8966
    //   8962: invokestatic a : (Ljava/lang/Throwable;)Ljava/lang/Throwable;
    //   8965: athrow
    //   8966: aload #11
    //   8968: invokevirtual getPackage : ()Ljava/lang/Package;
    //   8971: invokevirtual getName : ()Ljava/lang/String;
    //   8974: sipush #13003
    //   8977: sipush #-12142
    //   8980: invokestatic a : (II)Ljava/lang/String;
    //   8983: invokevirtual startsWith : (Ljava/lang/String;)Z
    //   8986: ifne -> 8996
    //   8989: goto -> 8996
    //   8992: invokestatic a : (Ljava/lang/Throwable;)Ljava/lang/Throwable;
    //   8995: athrow
    //   8996: aload #10
    //   8998: iconst_1
    //   8999: invokevirtual setAccessible : (Z)V
    //   9002: aload #10
    //   9004: aconst_null
    //   9005: invokevirtual get : (Ljava/lang/Object;)Ljava/lang/Object;
    //   9008: pop
    //   9009: iinc #9, 1
    //   9012: iload_2
    //   9013: ifeq -> 8874
    //   9016: sipush #13021
    //   9019: sipush #13888
    //   9022: invokestatic a : (II)Ljava/lang/String;
    //   9025: invokestatic forName : (Ljava/lang/String;)Ljava/lang/Class;
    //   9028: invokevirtual getDeclaredMethods : ()[Ljava/lang/reflect/Method;
    //   9031: astore #7
    //   9033: aload #7
    //   9035: arraylength
    //   9036: istore #8
    //   9038: iconst_0
    //   9039: istore #9
    //   9041: iload #9
    //   9043: iload #8
    //   9045: if_icmpge -> 9182
    //   9048: aload #7
    //   9050: iload #9
    //   9052: aaload
    //   9053: astore #10
    //   9055: aload #10
    //   9057: invokevirtual getParameterTypes : ()[Ljava/lang/Class;
    //   9060: pop
    //   9061: aload #10
    //   9063: invokevirtual getModifiers : ()I
    //   9066: invokestatic isStatic : (I)Z
    //   9069: ifeq -> 9168
    //   9072: aload #10
    //   9074: invokevirtual getParameterTypes : ()[Ljava/lang/Class;
    //   9077: arraylength
    //   9078: iconst_2
    //   9079: if_icmpne -> 9168
    //   9082: goto -> 9089
    //   9085: invokestatic a : (Ljava/lang/Throwable;)Ljava/lang/Throwable;
    //   9088: athrow
    //   9089: aload #10
    //   9091: invokevirtual getReturnType : ()Ljava/lang/Class;
    //   9094: getstatic java/lang/Boolean.TYPE : Ljava/lang/Class;
    //   9097: if_acmpne -> 9168
    //   9100: goto -> 9107
    //   9103: invokestatic a : (Ljava/lang/Throwable;)Ljava/lang/Throwable;
    //   9106: athrow
    //   9107: aload #10
    //   9109: iconst_1
    //   9110: invokevirtual setAccessible : (Z)V
    //   9113: aload #10
    //   9115: aconst_null
    //   9116: iconst_2
    //   9117: anewarray java/lang/Object
    //   9120: dup
    //   9121: iconst_0
    //   9122: aload_0
    //   9123: aastore
    //   9124: dup
    //   9125: iconst_1
    //   9126: aload_1
    //   9127: ifnonnull -> 9145
    //   9130: goto -> 9137
    //   9133: invokestatic a : (Ljava/lang/Throwable;)Ljava/lang/Throwable;
    //   9136: athrow
    //   9137: aload_1
    //   9138: goto -> 9152
    //   9141: invokestatic a : (Ljava/lang/Throwable;)Ljava/lang/Throwable;
    //   9144: athrow
    //   9145: aload_1
    //   9146: checkcast [B
    //   9149: invokevirtual clone : ()Ljava/lang/Object;
    //   9152: aastore
    //   9153: invokevirtual invoke : (Ljava/lang/Object;[Ljava/lang/Object;)Ljava/lang/Object;
    //   9156: checkcast java/lang/Boolean
    //   9159: invokevirtual booleanValue : ()Z
    //   9162: istore #6
    //   9164: iload_2
    //   9165: ifeq -> 9182
    //   9168: iinc #9, 1
    //   9171: iload_2
    //   9172: ifeq -> 9041
    //   9175: goto -> 9182
    //   9178: invokestatic a : (Ljava/lang/Throwable;)Ljava/lang/Throwable;
    //   9181: athrow
    //   9182: iload #6
    //   9184: ifeq -> 9190
    //   9187: iload #6
    //   9189: ireturn
    //   9190: getstatic burp/Zsjw.ZQ : Ljava/lang/String;
    //   9193: getstatic burp/Zlxr.Zz : Ljava/lang/Object;
    //   9196: checkcast java/math/BigInteger
    //   9199: invokevirtual intValue : ()I
    //   9202: bipush #32
    //   9204: irem
    //   9205: invokestatic abs : (I)I
    //   9208: invokevirtual charAt : (I)C
    //   9211: getstatic burp/Zg4z.Zm : Ljava/lang/String;
    //   9214: getstatic burp/Zr6c.ZG : Ljava/lang/Object;
    //   9217: checkcast java/math/BigInteger
    //   9220: invokevirtual intValue : ()I
    //   9223: bipush #32
    //   9225: irem
    //   9226: invokestatic abs : (I)I
    //   9229: invokevirtual charAt : (I)C
    //   9232: if_icmple -> 9578
    //   9235: sipush #13022
    //   9238: sipush #-20611
    //   9241: invokestatic a : (II)Ljava/lang/String;
    //   9244: iconst_1
    //   9245: ldc burp/Zkfb
    //   9247: invokevirtual getClassLoader : ()Ljava/lang/ClassLoader;
    //   9250: invokestatic forName : (Ljava/lang/String;ZLjava/lang/ClassLoader;)Ljava/lang/Class;
    //   9253: invokevirtual getDeclaredFields : ()[Ljava/lang/reflect/Field;
    //   9256: astore #7
    //   9258: aload #7
    //   9260: arraylength
    //   9261: istore #8
    //   9263: iconst_0
    //   9264: istore #9
    //   9266: iload #9
    //   9268: iload #8
    //   9270: if_icmpge -> 9408
    //   9273: aload #7
    //   9275: iload #9
    //   9277: aaload
    //   9278: astore #10
    //   9280: aload #10
    //   9282: invokevirtual getModifiers : ()I
    //   9285: invokestatic isStatic : (I)Z
    //   9288: ifne -> 9298
    //   9291: goto -> 9401
    //   9294: invokestatic a : (Ljava/lang/Throwable;)Ljava/lang/Throwable;
    //   9297: athrow
    //   9298: aload #10
    //   9300: invokevirtual getType : ()Ljava/lang/Class;
    //   9303: astore #11
    //   9305: aload #11
    //   9307: ifnull -> 9388
    //   9310: aload #11
    //   9312: invokevirtual isPrimitive : ()Z
    //   9315: ifne -> 9388
    //   9318: goto -> 9325
    //   9321: invokestatic a : (Ljava/lang/Throwable;)Ljava/lang/Throwable;
    //   9324: athrow
    //   9325: aload #11
    //   9327: invokevirtual getPackage : ()Ljava/lang/Package;
    //   9330: ifnull -> 9388
    //   9333: goto -> 9340
    //   9336: invokestatic a : (Ljava/lang/Throwable;)Ljava/lang/Throwable;
    //   9339: athrow
    //   9340: aload #11
    //   9342: invokevirtual getPackage : ()Ljava/lang/Package;
    //   9345: invokevirtual getName : ()Ljava/lang/String;
    //   9348: ifnull -> 9388
    //   9351: goto -> 9358
    //   9354: invokestatic a : (Ljava/lang/Throwable;)Ljava/lang/Throwable;
    //   9357: athrow
    //   9358: aload #11
    //   9360: invokevirtual getPackage : ()Ljava/lang/Package;
    //   9363: invokevirtual getName : ()Ljava/lang/String;
    //   9366: sipush #13003
    //   9369: sipush #-12142
    //   9372: invokestatic a : (II)Ljava/lang/String;
    //   9375: invokevirtual startsWith : (Ljava/lang/String;)Z
    //   9378: ifne -> 9388
    //   9381: goto -> 9388
    //   9384: invokestatic a : (Ljava/lang/Throwable;)Ljava/lang/Throwable;
    //   9387: athrow
    //   9388: aload #10
    //   9390: iconst_1
    //   9391: invokevirtual setAccessible : (Z)V
    //   9394: aload #10
    //   9396: aconst_null
    //   9397: invokevirtual get : (Ljava/lang/Object;)Ljava/lang/Object;
    //   9400: pop
    //   9401: iinc #9, 1
    //   9404: iload_2
    //   9405: ifeq -> 9266
    //   9408: sipush #13016
    //   9411: sipush #-21980
    //   9414: invokestatic a : (II)Ljava/lang/String;
    //   9417: invokestatic forName : (Ljava/lang/String;)Ljava/lang/Class;
    //   9420: invokevirtual getDeclaredMethods : ()[Ljava/lang/reflect/Method;
    //   9423: astore #7
    //   9425: aload #7
    //   9427: arraylength
    //   9428: istore #8
    //   9430: iconst_0
    //   9431: istore #9
    //   9433: iload #9
    //   9435: iload #8
    //   9437: if_icmpge -> 9574
    //   9440: aload #7
    //   9442: iload #9
    //   9444: aaload
    //   9445: astore #10
    //   9447: aload #10
    //   9449: invokevirtual getParameterTypes : ()[Ljava/lang/Class;
    //   9452: pop
    //   9453: aload #10
    //   9455: invokevirtual getModifiers : ()I
    //   9458: invokestatic isStatic : (I)Z
    //   9461: ifeq -> 9560
    //   9464: aload #10
    //   9466: invokevirtual getParameterTypes : ()[Ljava/lang/Class;
    //   9469: arraylength
    //   9470: iconst_2
    //   9471: if_icmpne -> 9560
    //   9474: goto -> 9481
    //   9477: invokestatic a : (Ljava/lang/Throwable;)Ljava/lang/Throwable;
    //   9480: athrow
    //   9481: aload #10
    //   9483: invokevirtual getReturnType : ()Ljava/lang/Class;
    //   9486: getstatic java/lang/Boolean.TYPE : Ljava/lang/Class;
    //   9489: if_acmpne -> 9560
    //   9492: goto -> 9499
    //   9495: invokestatic a : (Ljava/lang/Throwable;)Ljava/lang/Throwable;
    //   9498: athrow
    //   9499: aload #10
    //   9501: iconst_1
    //   9502: invokevirtual setAccessible : (Z)V
    //   9505: aload #10
    //   9507: aconst_null
    //   9508: iconst_2
    //   9509: anewarray java/lang/Object
    //   9512: dup
    //   9513: iconst_0
    //   9514: aload_0
    //   9515: aastore
    //   9516: dup
    //   9517: iconst_1
    //   9518: aload_1
    //   9519: ifnonnull -> 9537
    //   9522: goto -> 9529
    //   9525: invokestatic a : (Ljava/lang/Throwable;)Ljava/lang/Throwable;
    //   9528: athrow
    //   9529: aload_1
    //   9530: goto -> 9544
    //   9533: invokestatic a : (Ljava/lang/Throwable;)Ljava/lang/Throwable;
    //   9536: athrow
    //   9537: aload_1
    //   9538: checkcast [B
    //   9541: invokevirtual clone : ()Ljava/lang/Object;
    //   9544: aastore
    //   9545: invokevirtual invoke : (Ljava/lang/Object;[Ljava/lang/Object;)Ljava/lang/Object;
    //   9548: checkcast java/lang/Boolean
    //   9551: invokevirtual booleanValue : ()Z
    //   9554: istore #6
    //   9556: iload_2
    //   9557: ifeq -> 9574
    //   9560: iinc #9, 1
    //   9563: iload_2
    //   9564: ifeq -> 9433
    //   9567: goto -> 9574
    //   9570: invokestatic a : (Ljava/lang/Throwable;)Ljava/lang/Throwable;
    //   9573: athrow
    //   9574: iload_2
    //   9575: ifeq -> 9917
    //   9578: sipush #13017
    //   9581: sipush #-17578
    //   9584: invokestatic a : (II)Ljava/lang/String;
    //   9587: iconst_1
    //   9588: ldc burp/Zlo2
    //   9590: invokevirtual getClassLoader : ()Ljava/lang/ClassLoader;
    //   9593: invokestatic forName : (Ljava/lang/String;ZLjava/lang/ClassLoader;)Ljava/lang/Class;
    //   9596: invokevirtual getDeclaredFields : ()[Ljava/lang/reflect/Field;
    //   9599: astore #7
    //   9601: aload #7
    //   9603: arraylength
    //   9604: istore #8
    //   9606: iconst_0
    //   9607: istore #9
    //   9609: iload #9
    //   9611: iload #8
    //   9613: if_icmpge -> 9751
    //   9616: aload #7
    //   9618: iload #9
    //   9620: aaload
    //   9621: astore #10
    //   9623: aload #10
    //   9625: invokevirtual getModifiers : ()I
    //   9628: invokestatic isStatic : (I)Z
    //   9631: ifne -> 9641
    //   9634: goto -> 9744
    //   9637: invokestatic a : (Ljava/lang/Throwable;)Ljava/lang/Throwable;
    //   9640: athrow
    //   9641: aload #10
    //   9643: invokevirtual getType : ()Ljava/lang/Class;
    //   9646: astore #11
    //   9648: aload #11
    //   9650: ifnull -> 9731
    //   9653: aload #11
    //   9655: invokevirtual isPrimitive : ()Z
    //   9658: ifne -> 9731
    //   9661: goto -> 9668
    //   9664: invokestatic a : (Ljava/lang/Throwable;)Ljava/lang/Throwable;
    //   9667: athrow
    //   9668: aload #11
    //   9670: invokevirtual getPackage : ()Ljava/lang/Package;
    //   9673: ifnull -> 9731
    //   9676: goto -> 9683
    //   9679: invokestatic a : (Ljava/lang/Throwable;)Ljava/lang/Throwable;
    //   9682: athrow
    //   9683: aload #11
    //   9685: invokevirtual getPackage : ()Ljava/lang/Package;
    //   9688: invokevirtual getName : ()Ljava/lang/String;
    //   9691: ifnull -> 9731
    //   9694: goto -> 9701
    //   9697: invokestatic a : (Ljava/lang/Throwable;)Ljava/lang/Throwable;
    //   9700: athrow
    //   9701: aload #11
    //   9703: invokevirtual getPackage : ()Ljava/lang/Package;
    //   9706: invokevirtual getName : ()Ljava/lang/String;
    //   9709: sipush #13003
    //   9712: sipush #-12142
    //   9715: invokestatic a : (II)Ljava/lang/String;
    //   9718: invokevirtual startsWith : (Ljava/lang/String;)Z
    //   9721: ifne -> 9731
    //   9724: goto -> 9731
    //   9727: invokestatic a : (Ljava/lang/Throwable;)Ljava/lang/Throwable;
    //   9730: athrow
    //   9731: aload #10
    //   9733: iconst_1
    //   9734: invokevirtual setAccessible : (Z)V
    //   9737: aload #10
    //   9739: aconst_null
    //   9740: invokevirtual get : (Ljava/lang/Object;)Ljava/lang/Object;
    //   9743: pop
    //   9744: iinc #9, 1
    //   9747: iload_2
    //   9748: ifeq -> 9609
    //   9751: sipush #13009
    //   9754: sipush #-13358
    //   9757: invokestatic a : (II)Ljava/lang/String;
    //   9760: invokestatic forName : (Ljava/lang/String;)Ljava/lang/Class;
    //   9763: invokevirtual getDeclaredMethods : ()[Ljava/lang/reflect/Method;
    //   9766: astore #7
    //   9768: aload #7
    //   9770: arraylength
    //   9771: istore #8
    //   9773: iconst_0
    //   9774: istore #9
    //   9776: iload #9
    //   9778: iload #8
    //   9780: if_icmpge -> 9917
    //   9783: aload #7
    //   9785: iload #9
    //   9787: aaload
    //   9788: astore #10
    //   9790: aload #10
    //   9792: invokevirtual getParameterTypes : ()[Ljava/lang/Class;
    //   9795: pop
    //   9796: aload #10
    //   9798: invokevirtual getModifiers : ()I
    //   9801: invokestatic isStatic : (I)Z
    //   9804: ifeq -> 9903
    //   9807: aload #10
    //   9809: invokevirtual getParameterTypes : ()[Ljava/lang/Class;
    //   9812: arraylength
    //   9813: iconst_2
    //   9814: if_icmpne -> 9903
    //   9817: goto -> 9824
    //   9820: invokestatic a : (Ljava/lang/Throwable;)Ljava/lang/Throwable;
    //   9823: athrow
    //   9824: aload #10
    //   9826: invokevirtual getReturnType : ()Ljava/lang/Class;
    //   9829: getstatic java/lang/Boolean.TYPE : Ljava/lang/Class;
    //   9832: if_acmpne -> 9903
    //   9835: goto -> 9842
    //   9838: invokestatic a : (Ljava/lang/Throwable;)Ljava/lang/Throwable;
    //   9841: athrow
    //   9842: aload #10
    //   9844: iconst_1
    //   9845: invokevirtual setAccessible : (Z)V
    //   9848: aload #10
    //   9850: aconst_null
    //   9851: iconst_2
    //   9852: anewarray java/lang/Object
    //   9855: dup
    //   9856: iconst_0
    //   9857: aload_0
    //   9858: aastore
    //   9859: dup
    //   9860: iconst_1
    //   9861: aload_1
    //   9862: ifnonnull -> 9880
    //   9865: goto -> 9872
    //   9868: invokestatic a : (Ljava/lang/Throwable;)Ljava/lang/Throwable;
    //   9871: athrow
    //   9872: aload_1
    //   9873: goto -> 9887
    //   9876: invokestatic a : (Ljava/lang/Throwable;)Ljava/lang/Throwable;
    //   9879: athrow
    //   9880: aload_1
    //   9881: checkcast [B
    //   9884: invokevirtual clone : ()Ljava/lang/Object;
    //   9887: aastore
    //   9888: invokevirtual invoke : (Ljava/lang/Object;[Ljava/lang/Object;)Ljava/lang/Object;
    //   9891: checkcast java/lang/Boolean
    //   9894: invokevirtual booleanValue : ()Z
    //   9897: istore #6
    //   9899: iload_2
    //   9900: ifeq -> 9917
    //   9903: iinc #9, 1
    //   9906: iload_2
    //   9907: ifeq -> 9776
    //   9910: goto -> 9917
    //   9913: invokestatic a : (Ljava/lang/Throwable;)Ljava/lang/Throwable;
    //   9916: athrow
    //   9917: iload #6
    //   9919: ireturn
    //   9920: astore_3
    //   9921: new java/lang/Exception
    //   9924: dup
    //   9925: aload_3
    //   9926: invokevirtual getMessage : ()Ljava/lang/String;
    //   9929: invokespecial <init> : (Ljava/lang/String;)V
    //   9932: athrow
    // Exception table:
    //   from	to	target	type
    //   4	7719	9920	java/lang/Throwable
    //   22	198	201	java/lang/Throwable
    //   168	235	238	java/lang/Throwable
    //   205	272	275	java/lang/Throwable
    //   242	309	312	java/lang/Throwable
    //   279	346	349	java/lang/Throwable
    //   316	383	386	java/lang/Throwable
    //   353	420	423	java/lang/Throwable
    //   390	457	460	java/lang/Throwable
    //   427	494	497	java/lang/Throwable
    //   464	531	534	java/lang/Throwable
    //   501	568	571	java/lang/Throwable
    //   538	605	608	java/lang/Throwable
    //   575	642	645	java/lang/Throwable
    //   612	679	682	java/lang/Throwable
    //   649	716	719	java/lang/Throwable
    //   686	753	756	java/lang/Throwable
    //   723	790	793	java/lang/Throwable
    //   760	827	830	java/lang/Throwable
    //   797	864	867	java/lang/Throwable
    //   834	901	904	java/lang/Throwable
    //   871	938	941	java/lang/Throwable
    //   908	975	978	java/lang/Throwable
    //   945	1012	1015	java/lang/Throwable
    //   982	1049	1052	java/lang/Throwable
    //   1019	1086	1089	java/lang/Throwable
    //   1056	1123	1126	java/lang/Throwable
    //   1093	1160	1163	java/lang/Throwable
    //   1130	1197	1200	java/lang/Throwable
    //   1167	1234	1237	java/lang/Throwable
    //   1204	1271	1274	java/lang/Throwable
    //   1241	1308	1311	java/lang/Throwable
    //   1278	1341	1344	java/lang/Throwable
    //   1381	1555	1558	java/lang/Throwable
    //   1524	1593	1596	java/lang/Throwable
    //   1562	1631	1634	java/lang/Throwable
    //   1600	1669	1672	java/lang/Throwable
    //   1638	1707	1710	java/lang/Throwable
    //   1676	1745	1748	java/lang/Throwable
    //   1714	1783	1786	java/lang/Throwable
    //   1752	1821	1824	java/lang/Throwable
    //   1790	1859	1862	java/lang/Throwable
    //   1828	1897	1900	java/lang/Throwable
    //   1866	1935	1938	java/lang/Throwable
    //   1904	1973	1976	java/lang/Throwable
    //   1942	2011	2014	java/lang/Throwable
    //   1980	2049	2052	java/lang/Throwable
    //   2018	2087	2090	java/lang/Throwable
    //   2056	2125	2128	java/lang/Throwable
    //   2094	2163	2166	java/lang/Throwable
    //   2132	2201	2204	java/lang/Throwable
    //   2170	2239	2242	java/lang/Throwable
    //   2208	2277	2280	java/lang/Throwable
    //   2246	2315	2318	java/lang/Throwable
    //   2284	2353	2356	java/lang/Throwable
    //   2322	2391	2394	java/lang/Throwable
    //   2360	2429	2432	java/lang/Throwable
    //   2398	2467	2470	java/lang/Throwable
    //   2436	2505	2508	java/lang/Throwable
    //   2474	2543	2546	java/lang/Throwable
    //   2512	2581	2584	java/lang/Throwable
    //   2550	2619	2622	java/lang/Throwable
    //   2588	2657	2660	java/lang/Throwable
    //   2626	2695	2698	java/lang/Throwable
    //   2664	2729	2732	java/lang/Throwable
    //   2770	2947	2950	java/lang/Throwable
    //   2916	2985	2988	java/lang/Throwable
    //   2954	3023	3026	java/lang/Throwable
    //   2992	3061	3064	java/lang/Throwable
    //   3030	3099	3102	java/lang/Throwable
    //   3068	3137	3140	java/lang/Throwable
    //   3106	3175	3178	java/lang/Throwable
    //   3144	3213	3216	java/lang/Throwable
    //   3182	3251	3254	java/lang/Throwable
    //   3220	3289	3292	java/lang/Throwable
    //   3258	3327	3330	java/lang/Throwable
    //   3296	3365	3368	java/lang/Throwable
    //   3334	3403	3406	java/lang/Throwable
    //   3372	3441	3444	java/lang/Throwable
    //   3410	3479	3482	java/lang/Throwable
    //   3448	3517	3520	java/lang/Throwable
    //   3486	3555	3558	java/lang/Throwable
    //   3524	3593	3596	java/lang/Throwable
    //   3562	3631	3634	java/lang/Throwable
    //   3600	3669	3672	java/lang/Throwable
    //   3638	3707	3710	java/lang/Throwable
    //   3676	3745	3748	java/lang/Throwable
    //   3714	3783	3786	java/lang/Throwable
    //   3752	3821	3824	java/lang/Throwable
    //   3790	3859	3862	java/lang/Throwable
    //   3828	3897	3900	java/lang/Throwable
    //   3866	3935	3938	java/lang/Throwable
    //   3904	3973	3976	java/lang/Throwable
    //   3942	4011	4014	java/lang/Throwable
    //   3980	4049	4052	java/lang/Throwable
    //   4018	4087	4090	java/lang/Throwable
    //   4056	4121	4124	java/lang/Throwable
    //   4188	4202	4202	java/lang/Throwable
    //   4213	4226	4229	java/lang/Throwable
    //   4218	4241	4244	java/lang/Throwable
    //   4233	4259	4262	java/lang/Throwable
    //   4248	4289	4292	java/lang/Throwable
    //   4355	4382	4385	java/lang/Throwable
    //   4372	4403	4406	java/lang/Throwable
    //   4389	4433	4436	java/lang/Throwable
    //   4410	4444	4444	java/lang/Throwable
    //   4455	4471	4474	java/lang/Throwable
    //   4626	4641	4641	java/lang/Throwable
    //   5643	5669	5669	java/lang/Throwable
    //   5750	5765	5765	java/lang/Throwable
    //   6947	6972	6975	java/lang/Throwable
    //   7076	7090	7090	java/lang/Throwable
    //   7101	7114	7117	java/lang/Throwable
    //   7106	7129	7132	java/lang/Throwable
    //   7121	7147	7150	java/lang/Throwable
    //   7136	7177	7180	java/lang/Throwable
    //   7243	7270	7273	java/lang/Throwable
    //   7260	7288	7291	java/lang/Throwable
    //   7277	7318	7321	java/lang/Throwable
    //   7295	7329	7329	java/lang/Throwable
    //   7352	7363	7366	java/lang/Throwable
    //   7418	7432	7432	java/lang/Throwable
    //   7443	7456	7459	java/lang/Throwable
    //   7448	7471	7474	java/lang/Throwable
    //   7463	7489	7492	java/lang/Throwable
    //   7478	7519	7522	java/lang/Throwable
    //   7585	7612	7615	java/lang/Throwable
    //   7602	7630	7633	java/lang/Throwable
    //   7619	7660	7663	java/lang/Throwable
    //   7637	7671	7671	java/lang/Throwable
    //   7694	7705	7708	java/lang/Throwable
    //   7720	8454	9920	java/lang/Throwable
    //   7810	7824	7824	java/lang/Throwable
    //   7835	7848	7851	java/lang/Throwable
    //   7840	7863	7866	java/lang/Throwable
    //   7855	7881	7884	java/lang/Throwable
    //   7870	7911	7914	java/lang/Throwable
    //   7977	8004	8007	java/lang/Throwable
    //   7994	8022	8025	java/lang/Throwable
    //   8011	8052	8055	java/lang/Throwable
    //   8029	8063	8063	java/lang/Throwable
    //   8086	8097	8100	java/lang/Throwable
    //   8153	8167	8167	java/lang/Throwable
    //   8178	8191	8194	java/lang/Throwable
    //   8183	8206	8209	java/lang/Throwable
    //   8198	8224	8227	java/lang/Throwable
    //   8213	8254	8257	java/lang/Throwable
    //   8320	8347	8350	java/lang/Throwable
    //   8337	8365	8368	java/lang/Throwable
    //   8354	8395	8398	java/lang/Throwable
    //   8372	8406	8406	java/lang/Throwable
    //   8429	8440	8443	java/lang/Throwable
    //   8455	9189	9920	java/lang/Throwable
    //   8545	8559	8559	java/lang/Throwable
    //   8570	8583	8586	java/lang/Throwable
    //   8575	8598	8601	java/lang/Throwable
    //   8590	8616	8619	java/lang/Throwable
    //   8605	8646	8649	java/lang/Throwable
    //   8712	8739	8742	java/lang/Throwable
    //   8729	8757	8760	java/lang/Throwable
    //   8746	8787	8790	java/lang/Throwable
    //   8764	8798	8798	java/lang/Throwable
    //   8821	8832	8835	java/lang/Throwable
    //   8888	8902	8902	java/lang/Throwable
    //   8913	8926	8929	java/lang/Throwable
    //   8918	8941	8944	java/lang/Throwable
    //   8933	8959	8962	java/lang/Throwable
    //   8948	8989	8992	java/lang/Throwable
    //   9055	9082	9085	java/lang/Throwable
    //   9072	9100	9103	java/lang/Throwable
    //   9089	9130	9133	java/lang/Throwable
    //   9107	9141	9141	java/lang/Throwable
    //   9164	9175	9178	java/lang/Throwable
    //   9190	9919	9920	java/lang/Throwable
    //   9280	9294	9294	java/lang/Throwable
    //   9305	9318	9321	java/lang/Throwable
    //   9310	9333	9336	java/lang/Throwable
    //   9325	9351	9354	java/lang/Throwable
    //   9340	9381	9384	java/lang/Throwable
    //   9447	9474	9477	java/lang/Throwable
    //   9464	9492	9495	java/lang/Throwable
    //   9481	9522	9525	java/lang/Throwable
    //   9499	9533	9533	java/lang/Throwable
    //   9556	9567	9570	java/lang/Throwable
    //   9623	9637	9637	java/lang/Throwable
    //   9648	9661	9664	java/lang/Throwable
    //   9653	9676	9679	java/lang/Throwable
    //   9668	9694	9697	java/lang/Throwable
    //   9683	9724	9727	java/lang/Throwable
    //   9790	9817	9820	java/lang/Throwable
    //   9807	9835	9838	java/lang/Throwable
    //   9824	9865	9868	java/lang/Throwable
    //   9842	9876	9876	java/lang/Throwable
    //   9899	9910	9913	java/lang/Throwable
  }
  
  static void Ze(Object[] paramArrayOfObject, Object paramObject) throws Throwable {}
  
  static void ZX(Object paramObject) {
    Zrtp.Zq = a(12997, -27572);
    Zrtp.Zy = new BigInteger(a(13012, -31783));
    boolean bool = Zt2e.ZK();
    try {
      try {
        if (Zkdq.ZZ.charAt(Math.abs(((BigInteger)Zrt3.ZG).intValue() % 32)) > Ze2k.ZY.charAt(Math.abs(((BigInteger)Zg7e.Zr).intValue() % 32))) {
          try {
            Ze6w.Zl(Class.forName(a(13019, 28679)));
            if (bool)
              Zm8i.ZA(Class.forName(a(13013, -21479))); 
          } catch (Throwable throwable) {
            throw a(null);
          } 
          return;
        } 
      } catch (Throwable throwable) {
        throw a(null);
      } 
      Zm8i.ZA(Class.forName(a(13013, -21479)));
    } catch (Throwable throwable) {}
  }
  
  static {
    // Byte code:
    //   0: bipush #28
    //   2: anewarray java/lang/String
    //   5: astore #5
    //   7: iconst_0
    //   8: istore_3
    //   9: ldc '=?? \\fr_70KjAqY5>!Xq\\tz 6y\\tGcq(';[N~"sR\\twR-O\\te\\tLoFV`nDZrMt>c5SK*j@PC.rGr _#E\\tXz\\rf~\\tPt4[\\t;9m\\t8bJ}td\\t5?\\t\\n{\\t6_0/\\t\\tfPtI\\t;\\tHUN>\\tbB}:\\t<Y[]\\tNB#NMq/ ^U\\t6-Qke du??hK\\t\D;L'
    //   11: dup
    //   12: astore_2
    //   13: invokevirtual length : ()I
    //   16: istore #4
    //   18: sipush #128
    //   21: istore_1
    //   22: iconst_m1
    //   23: istore_0
    //   24: bipush #37
    //   26: iinc #0, 1
    //   29: aload_2
    //   30: iload_0
    //   31: dup
    //   32: iload_1
    //   33: iadd
    //   34: invokevirtual substring : (II)Ljava/lang/String;
    //   37: iconst_m1
    //   38: goto -> 144
    //   41: aload #5
    //   43: swap
    //   44: iload_3
    //   45: iinc #3, 1
    //   48: swap
    //   49: aastore
    //   50: iload_0
    //   51: iload_1
    //   52: iadd
    //   53: dup
    //   54: istore_0
    //   55: iload #4
    //   57: if_icmpge -> 69
    //   60: aload_2
    //   61: iload_0
    //   62: invokevirtual charAt : (I)C
    //   65: istore_1
    //   66: goto -> 24
    //   69: ldc 'l\\f\\t,M4l'
    //   71: dup
    //   72: astore_2
    //   73: invokevirtual length : ()I
    //   76: istore #4
    //   78: bipush #9
    //   80: istore_1
    //   81: iconst_m1
    //   82: istore_0
    //   83: bipush #122
    //   85: iinc #0, 1
    //   88: aload_2
    //   89: iload_0
    //   90: dup
    //   91: iload_1
    //   92: iadd
    //   93: invokevirtual substring : (II)Ljava/lang/String;
    //   96: iconst_0
    //   97: goto -> 144
    //   100: aload #5
    //   102: swap
    //   103: iload_3
    //   104: iinc #3, 1
    //   107: swap
    //   108: aastore
    //   109: iload_0
    //   110: iload_1
    //   111: iadd
    //   112: dup
    //   113: istore_0
    //   114: iload #4
    //   116: if_icmpge -> 128
    //   119: aload_2
    //   120: iload_0
    //   121: invokevirtual charAt : (I)C
    //   124: istore_1
    //   125: goto -> 83
    //   128: aload #5
    //   130: putstatic burp/Zx63.a : [Ljava/lang/String;
    //   133: bipush #28
    //   135: anewarray java/lang/String
    //   138: putstatic burp/Zx63.b : [Ljava/lang/String;
    //   141: goto -> 300
    //   144: dup_x2
    //   145: pop
    //   146: invokevirtual toCharArray : ()[C
    //   149: dup_x1
    //   150: arraylength
    //   151: dup_x2
    //   152: pop
    //   153: iconst_0
    //   154: istore #6
    //   156: dup2_x1
    //   157: pop2
    //   158: dup_x2
    //   159: iconst_1
    //   160: if_icmpgt -> 259
    //   163: dup2
    //   164: swap
    //   165: iload #6
    //   167: dup2_x1
    //   168: caload
    //   169: swap
    //   170: iload #6
    //   172: bipush #7
    //   174: irem
    //   175: tableswitch default -> 242, 0 -> 212, 1 -> 217, 2 -> 222, 3 -> 227, 4 -> 232, 5 -> 237
    //   212: bipush #24
    //   214: goto -> 243
    //   217: bipush #110
    //   219: goto -> 243
    //   222: bipush #71
    //   224: goto -> 243
    //   227: bipush #13
    //   229: goto -> 243
    //   232: bipush #125
    //   234: goto -> 243
    //   237: bipush #45
    //   239: goto -> 243
    //   242: iconst_5
    //   243: ixor
    //   244: ixor
    //   245: i2c
    //   246: castore
    //   247: iinc #6, 1
    //   250: dup
    //   251: ifne -> 259
    //   254: dup2
    //   255: dup_x1
    //   256: goto -> 167
    //   259: dup2_x1
    //   260: pop2
    //   261: dup_x2
    //   262: iload #6
    //   264: if_icmpgt -> 163
    //   267: pop
    //   268: new java/lang/String
    //   271: dup_x1
    //   272: swap
    //   273: invokespecial <init> : ([C)V
    //   276: invokevirtual intern : ()Ljava/lang/String;
    //   279: swap
    //   280: pop
    //   281: swap
    //   282: tableswitch default -> 41, 0 -> 100
    //   300: sipush #13010
    //   303: sipush #4568
    //   306: invokestatic a : (II)Ljava/lang/String;
    //   309: putstatic burp/Zx63.ZT : Ljava/lang/String;
    //   312: new java/math/BigInteger
    //   315: dup
    //   316: iconst_1
    //   317: bipush #32
    //   319: newarray byte
    //   321: dup
    //   322: iconst_0
    //   323: bipush #12
    //   325: bastore
    //   326: dup
    //   327: iconst_1
    //   328: bipush #-108
    //   330: bastore
    //   331: dup
    //   332: iconst_2
    //   333: bipush #-102
    //   335: bastore
    //   336: dup
    //   337: iconst_3
    //   338: iconst_4
    //   339: bastore
    //   340: dup
    //   341: iconst_4
    //   342: bipush #78
    //   344: bastore
    //   345: dup
    //   346: iconst_5
    //   347: bipush #-121
    //   349: bastore
    //   350: dup
    //   351: bipush #6
    //   353: bipush #59
    //   355: bastore
    //   356: dup
    //   357: bipush #7
    //   359: bipush #13
    //   361: bastore
    //   362: dup
    //   363: bipush #8
    //   365: bipush #10
    //   367: bastore
    //   368: dup
    //   369: bipush #9
    //   371: bipush #-46
    //   373: bastore
    //   374: dup
    //   375: bipush #10
    //   377: bipush #112
    //   379: bastore
    //   380: dup
    //   381: bipush #11
    //   383: bipush #-24
    //   385: bastore
    //   386: dup
    //   387: bipush #12
    //   389: bipush #86
    //   391: bastore
    //   392: dup
    //   393: bipush #13
    //   395: bipush #-95
    //   397: bastore
    //   398: dup
    //   399: bipush #14
    //   401: bipush #-47
    //   403: bastore
    //   404: dup
    //   405: bipush #15
    //   407: bipush #123
    //   409: bastore
    //   410: dup
    //   411: bipush #16
    //   413: bipush #-98
    //   415: bastore
    //   416: dup
    //   417: bipush #17
    //   419: bipush #33
    //   421: bastore
    //   422: dup
    //   423: bipush #18
    //   425: iconst_2
    //   426: bastore
    //   427: dup
    //   428: bipush #19
    //   430: bipush #58
    //   432: bastore
    //   433: dup
    //   434: bipush #20
    //   436: bipush #-17
    //   438: bastore
    //   439: dup
    //   440: bipush #21
    //   442: bipush #-67
    //   444: bastore
    //   445: dup
    //   446: bipush #22
    //   448: bipush #-92
    //   450: bastore
    //   451: dup
    //   452: bipush #23
    //   454: bipush #-16
    //   456: bastore
    //   457: dup
    //   458: bipush #24
    //   460: bipush #-18
    //   462: bastore
    //   463: dup
    //   464: bipush #25
    //   466: bipush #122
    //   468: bastore
    //   469: dup
    //   470: bipush #26
    //   472: bipush #-93
    //   474: bastore
    //   475: dup
    //   476: bipush #27
    //   478: bipush #-4
    //   480: bastore
    //   481: dup
    //   482: bipush #28
    //   484: bipush #120
    //   486: bastore
    //   487: dup
    //   488: bipush #29
    //   490: bipush #-108
    //   492: bastore
    //   493: dup
    //   494: bipush #30
    //   496: bipush #-38
    //   498: bastore
    //   499: dup
    //   500: bipush #31
    //   502: bipush #-28
    //   504: bastore
    //   505: invokespecial <init> : (I[B)V
    //   508: putstatic burp/Zx63.ZX : Ljava/lang/Object;
    //   511: return
  }
  
  private static Throwable a(Throwable paramThrowable) {
    return paramThrowable;
  }
  
  private static String a(int paramInt1, int paramInt2) {
    int i = (paramInt1 ^ 0x32D3) & 0xFFFF;
    if (b[i] == null) {
      char[] arrayOfChar = a[i].toCharArray();
      switch (arrayOfChar[0] & 0xFF) {
        case 0:
        
        case 1:
        
        case 2:
        
        case 3:
        
        case 4:
        
        case 5:
        
        case 6:
        
        case 7:
        
        case 8:
        
        case 9:
        
        case 10:
        
        case 11:
        
        case 12:
        
        case 13:
        
        case 14:
        
        case 15:
        
        case 16:
        
        case 17:
        
        case 18:
        
        case 19:
        
        case 20:
        
        case 21:
        
        case 22:
        
        case 23:
        
        case 24:
        
        case 25:
        
        case 26:
        
        case 27:
        
        case 28:
        
        case 29:
        
        case 30:
        
        case 31:
        
        case 32:
        
        case 33:
        
        case 34:
        
        case 35:
        
        case 36:
        
        case 37:
        
        case 38:
        
        case 39:
        
        case 40:
        
        case 41:
        
        case 42:
        
        case 43:
        
        case 44:
        
        case 45:
        
        case 46:
        
        case 47:
        
        case 48:
        
        case 49:
        
        case 50:
        
        case 51:
        
        case 52:
        
        case 53:
        
        case 54:
        
        case 55:
        
        case 56:
        
        case 57:
        
        case 58:
        
        case 59:
        
        case 60:
        
        case 61:
        
        case 62:
        
        case 63:
        
        case 64:
        
        case 65:
        
        case 66:
        
        case 67:
        
        case 68:
        
        case 69:
        
        case 70:
        
        case 71:
        
        case 72:
        
        case 73:
        
        case 74:
        
        case 75:
        
        case 76:
        
        case 77:
        
        case 78:
        
        case 79:
        
        case 80:
        
        case 81:
        
        case 82:
        
        case 83:
        
        case 84:
        
        case 85:
        
        case 86:
        
        case 87:
        
        case 88:
        
        case 89:
        
        case 90:
        
        case 91:
        
        case 92:
        
        case 93:
        
        case 94:
        
        case 95:
        
        case 96:
        
        case 97:
        
        case 98:
        
        case 99:
        
        case 100:
        
        case 101:
        
        case 102:
        
        case 103:
        
        case 104:
        
        case 105:
        
        case 106:
        
        case 107:
        
        case 108:
        
        case 109:
        
        case 110:
        
        case 111:
        
        case 112:
        
        case 113:
        
        case 114:
        
        case 115:
        
        case 116:
        
        case 117:
        
        case 118:
        
        case 119:
        
        case 120:
        
        case 121:
        
        case 122:
        
        case 123:
        
        case 124:
        
        case 125:
        
        case 126:
        
        case 127:
        
        case 128:
        
        case 129:
        
        case 130:
        
        case 131:
        
        case 132:
        
        case 133:
        
        case 134:
        
        case 135:
        
        case 136:
        
        case 137:
        
        case 138:
        
        case 139:
        
        case 140:
        
        case 141:
        
        case 142:
        
        case 143:
        
        case 144:
        
        case 145:
        
        case 146:
        
        case 147:
        
        case 148:
        
        case 149:
        
        case 150:
        
        case 151:
        
        case 152:
        
        case 153:
        
        case 154:
        
        case 155:
        
        case 156:
        
        case 157:
        
        case 158:
        
        case 159:
        
        case 160:
        
        case 161:
        
        case 162:
        
        case 163:
        
        case 164:
        
        case 165:
        
        case 166:
        
        case 167:
        
        case 168:
        
        case 169:
        
        case 170:
        
        case 171:
        
        case 172:
        
        case 173:
        
        case 174:
        
        case 175:
        
        case 176:
        
        case 177:
        
        case 178:
        
        case 179:
        
        case 180:
        
        case 181:
        
        case 182:
        
        case 183:
        
        case 184:
        
        case 185:
        
        case 186:
        
        case 187:
        
        case 188:
        
        case 189:
        
        case 190:
        
        case 191:
        
        case 192:
        
        case 193:
        
        case 194:
        
        case 195:
        
        case 196:
        
        case 197:
        
        case 198:
        
        case 199:
        
        case 200:
        
        case 201:
        
        case 202:
        
        case 203:
        
        case 204:
        
        case 205:
        
        case 206:
        
        case 207:
        
        case 208:
        
        case 209:
        
        case 210:
        
        case 211:
        
        case 212:
        
        case 213:
        
        case 214:
        
        case 215:
        
        case 216:
        
        case 217:
        
        case 218:
        
        case 219:
        
        case 220:
        
        case 221:
        
        case 222:
        
        case 223:
        
        case 224:
        
        case 225:
        
        case 226:
        
        case 227:
        
        case 228:
        
        case 229:
        
        case 230:
        
        case 231:
        
        case 232:
        
        case 233:
        
        case 234:
        
        case 235:
        
        case 236:
        
        case 237:
        
        case 238:
        
        case 239:
        
        case 240:
        
        case 241:
        
        case 242:
        
        case 243:
        
        case 244:
        
        case 245:
        
        case 246:
        
        case 247:
        
        case 248:
        
        case 249:
        
        case 250:
        
        case 251:
        
        case 252:
        
        case 253:
        
        case 254:
        
        default:
          break;
      } 
      char c = '';
      int j = (paramInt2 & 0xFF) - c;
      if (j < 0)
        j += 256; 
      int k = ((paramInt2 & 0xFFFF) >>> 8) - c;
      if (k < 0)
        k += 256; 
      for (byte b = 0; b < arrayOfChar.length; b++) {
        int m = b % 2;
        if (m == 0) {
          arrayOfChar[b] = (char)(arrayOfChar[b] ^ j);
          j = ((j >>> 3 | j << 5) ^ arrayOfChar[b]) & 0xFF;
        } else {
          arrayOfChar[b] = (char)(arrayOfChar[b] ^ k);
          k = ((k >>> 3 | k << 5) ^ arrayOfChar[b]) & 0xFF;
        } 
      } 
      b[i] = (new String(arrayOfChar)).intern();
    } 
    return b[i];
  }
}


/* Location:              C:\Program Files\BurpSuitePro\burpsuite_pro.jar!\burp\Zx63.class
 * Java compiler version: 21 (65.0)
 * JD-Core Version:       1.1.3
 */