package burp;

public class Zx8e {
  public static final Zmv7 Zr = new Zs9_();
  
  public static Zmv7 ZB(Zsug paramZsug, Zskh paramZskh) {
    // Byte code:
    //   0: invokestatic ZF : ()[Lburp/Zbqc;
    //   3: astore_2
    //   4: aload_0
    //   5: invokeinterface Zt : ()Z
    //   10: ifeq -> 27
    //   13: new burp/Zrx8
    //   16: dup
    //   17: aload_0
    //   18: aload_1
    //   19: invokespecial <init> : (Lburp/Zsug;Lburp/Zskh;)V
    //   22: astore_3
    //   23: aload_2
    //   24: ifnull -> 31
    //   27: getstatic burp/Zx8e.Zr : Lburp/Zmv7;
    //   30: astore_3
    //   31: new burp/Zmob
    //   34: dup
    //   35: aload_1
    //   36: aload_3
    //   37: invokespecial <init> : (Lburp/Zskh;Lburp/Zmv7;)V
    //   40: invokestatic Zwu : ()[Lburp/Zbqc;
    //   43: ifnonnull -> 53
    //   46: iconst_1
    //   47: anewarray burp/Zbqc
    //   50: invokestatic Zh : ([Lburp/Zbqc;)V
    //   53: areturn
  }
}


/* Location:              C:\Program Files\BurpSuitePro\burpsuite_pro.jar!\burp\Zx8e.class
 * Java compiler version: 21 (65.0)
 * JD-Core Version:       1.1.3
 */