package burp;

import java.math.BigInteger;

class Zx_b extends ClassLoader {
  static String ZD;
  
  static Object ZX;
  
  private static final String[] a;
  
  private static final String[] b;
  
  static void ZD(Object paramObject) {
    Zvi.ZR = a(-727, 30169);
    Zvi.Zs = new BigInteger(a(-711, 19188));
    boolean bool = Zt2e.ZN();
    try {
      try {
        if (Zelz.ZK.charAt(Math.abs(((BigInteger)Zlh2.Zc).intValue() % 32)) <= Zk8g.ZH.charAt(Math.abs(((BigInteger)Zsqi.Zf).intValue() % 32))) {
          try {
            Zkff.ZL(Class.forName(a(-707, -2905)));
            if (!bool)
              Zblj.Zi(Class.forName(a(-716, -7608))); 
          } catch (Throwable throwable) {
            throw a(null);
          } 
          return;
        } 
      } catch (Throwable throwable) {
        throw a(null);
      } 
      Zblj.Zi(Class.forName(a(-716, -7608)));
    } catch (Throwable throwable) {}
  }
  
  static void Zb(Object[] paramArrayOfObject, Object paramObject) throws Throwable {}
  
  static boolean Zm(Object[] paramArrayOfObject, Object paramObject) throws Throwable {
    // Byte code:
    //   0: invokestatic ZK : ()Z
    //   3: istore_2
    //   4: new java/lang/StringBuilder
    //   7: dup
    //   8: invokespecial <init> : ()V
    //   11: astore_3
    //   12: iconst_0
    //   13: istore #4
    //   15: iload #4
    //   17: bipush #32
    //   19: if_icmpge -> 1355
    //   22: iload #4
    //   24: tableswitch default -> 1348, 0 -> 168, 1 -> 205, 2 -> 242, 3 -> 279, 4 -> 316, 5 -> 353, 6 -> 390, 7 -> 427, 8 -> 464, 9 -> 501, 10 -> 538, 11 -> 575, 12 -> 612, 13 -> 649, 14 -> 686, 15 -> 723, 16 -> 760, 17 -> 797, 18 -> 834, 19 -> 871, 20 -> 908, 21 -> 945, 22 -> 982, 23 -> 1019, 24 -> 1056, 25 -> 1093, 26 -> 1130, 27 -> 1167, 28 -> 1204, 29 -> 1241, 30 -> 1278, 31 -> 1315
    //   168: aload_3
    //   169: getstatic burp/Zt7w.Zi : Ljava/lang/String;
    //   172: getstatic burp/Zxxd.Zn : Ljava/lang/Object;
    //   175: checkcast java/math/BigInteger
    //   178: invokevirtual intValue : ()I
    //   181: bipush #32
    //   183: irem
    //   184: invokestatic abs : (I)I
    //   187: invokevirtual charAt : (I)C
    //   190: invokevirtual append : (C)Ljava/lang/StringBuilder;
    //   193: pop
    //   194: iload_2
    //   195: ifeq -> 1348
    //   198: goto -> 205
    //   201: invokestatic a : (Ljava/lang/Throwable;)Ljava/lang/Throwable;
    //   204: athrow
    //   205: aload_3
    //   206: getstatic burp/Ze40.Zr : Ljava/lang/String;
    //   209: getstatic burp/Zlbr.Zp : Ljava/lang/Object;
    //   212: checkcast java/math/BigInteger
    //   215: invokevirtual intValue : ()I
    //   218: bipush #32
    //   220: irem
    //   221: invokestatic abs : (I)I
    //   224: invokevirtual charAt : (I)C
    //   227: invokevirtual append : (C)Ljava/lang/StringBuilder;
    //   230: pop
    //   231: iload_2
    //   232: ifeq -> 1348
    //   235: goto -> 242
    //   238: invokestatic a : (Ljava/lang/Throwable;)Ljava/lang/Throwable;
    //   241: athrow
    //   242: aload_3
    //   243: getstatic burp/Zem6.Zp : Ljava/lang/String;
    //   246: getstatic burp/Zty2.Zl : Ljava/lang/Object;
    //   249: checkcast java/math/BigInteger
    //   252: invokevirtual intValue : ()I
    //   255: bipush #32
    //   257: irem
    //   258: invokestatic abs : (I)I
    //   261: invokevirtual charAt : (I)C
    //   264: invokevirtual append : (C)Ljava/lang/StringBuilder;
    //   267: pop
    //   268: iload_2
    //   269: ifeq -> 1348
    //   272: goto -> 279
    //   275: invokestatic a : (Ljava/lang/Throwable;)Ljava/lang/Throwable;
    //   278: athrow
    //   279: aload_3
    //   280: getstatic burp/Zevf.ZL : Ljava/lang/String;
    //   283: getstatic burp/Zkff.Zr : Ljava/lang/Object;
    //   286: checkcast java/math/BigInteger
    //   289: invokevirtual intValue : ()I
    //   292: bipush #32
    //   294: irem
    //   295: invokestatic abs : (I)I
    //   298: invokevirtual charAt : (I)C
    //   301: invokevirtual append : (C)Ljava/lang/StringBuilder;
    //   304: pop
    //   305: iload_2
    //   306: ifeq -> 1348
    //   309: goto -> 316
    //   312: invokestatic a : (Ljava/lang/Throwable;)Ljava/lang/Throwable;
    //   315: athrow
    //   316: aload_3
    //   317: getstatic burp/Ztvp.ZZ : Ljava/lang/String;
    //   320: getstatic burp/Zt7w.ZF : Ljava/lang/Object;
    //   323: checkcast java/math/BigInteger
    //   326: invokevirtual intValue : ()I
    //   329: bipush #32
    //   331: irem
    //   332: invokestatic abs : (I)I
    //   335: invokevirtual charAt : (I)C
    //   338: invokevirtual append : (C)Ljava/lang/StringBuilder;
    //   341: pop
    //   342: iload_2
    //   343: ifeq -> 1348
    //   346: goto -> 353
    //   349: invokestatic a : (Ljava/lang/Throwable;)Ljava/lang/Throwable;
    //   352: athrow
    //   353: aload_3
    //   354: getstatic burp/Zec_.Zv : Ljava/lang/String;
    //   357: getstatic burp/Zvi.Zs : Ljava/lang/Object;
    //   360: checkcast java/math/BigInteger
    //   363: invokevirtual intValue : ()I
    //   366: bipush #32
    //   368: irem
    //   369: invokestatic abs : (I)I
    //   372: invokevirtual charAt : (I)C
    //   375: invokevirtual append : (C)Ljava/lang/StringBuilder;
    //   378: pop
    //   379: iload_2
    //   380: ifeq -> 1348
    //   383: goto -> 390
    //   386: invokestatic a : (Ljava/lang/Throwable;)Ljava/lang/Throwable;
    //   389: athrow
    //   390: aload_3
    //   391: getstatic burp/Zgfm.ZE : Ljava/lang/String;
    //   394: getstatic burp/Zm1l.Za : Ljava/lang/Object;
    //   397: checkcast java/math/BigInteger
    //   400: invokevirtual intValue : ()I
    //   403: bipush #32
    //   405: irem
    //   406: invokestatic abs : (I)I
    //   409: invokevirtual charAt : (I)C
    //   412: invokevirtual append : (C)Ljava/lang/StringBuilder;
    //   415: pop
    //   416: iload_2
    //   417: ifeq -> 1348
    //   420: goto -> 427
    //   423: invokestatic a : (Ljava/lang/Throwable;)Ljava/lang/Throwable;
    //   426: athrow
    //   427: aload_3
    //   428: getstatic burp/Zsdn.Zf : Ljava/lang/String;
    //   431: getstatic burp/Zsdn.ZE : Ljava/lang/Object;
    //   434: checkcast java/math/BigInteger
    //   437: invokevirtual intValue : ()I
    //   440: bipush #32
    //   442: irem
    //   443: invokestatic abs : (I)I
    //   446: invokevirtual charAt : (I)C
    //   449: invokevirtual append : (C)Ljava/lang/StringBuilder;
    //   452: pop
    //   453: iload_2
    //   454: ifeq -> 1348
    //   457: goto -> 464
    //   460: invokestatic a : (Ljava/lang/Throwable;)Ljava/lang/Throwable;
    //   463: athrow
    //   464: aload_3
    //   465: getstatic burp/Ztfr.Zo : Ljava/lang/String;
    //   468: getstatic burp/Zelz.Z_ : Ljava/lang/Object;
    //   471: checkcast java/math/BigInteger
    //   474: invokevirtual intValue : ()I
    //   477: bipush #32
    //   479: irem
    //   480: invokestatic abs : (I)I
    //   483: invokevirtual charAt : (I)C
    //   486: invokevirtual append : (C)Ljava/lang/StringBuilder;
    //   489: pop
    //   490: iload_2
    //   491: ifeq -> 1348
    //   494: goto -> 501
    //   497: invokestatic a : (Ljava/lang/Throwable;)Ljava/lang/Throwable;
    //   500: athrow
    //   501: aload_3
    //   502: getstatic burp/Zmsl.ZP : Ljava/lang/String;
    //   505: getstatic burp/Zry9.Zw : Ljava/lang/Object;
    //   508: checkcast java/math/BigInteger
    //   511: invokevirtual intValue : ()I
    //   514: bipush #32
    //   516: irem
    //   517: invokestatic abs : (I)I
    //   520: invokevirtual charAt : (I)C
    //   523: invokevirtual append : (C)Ljava/lang/StringBuilder;
    //   526: pop
    //   527: iload_2
    //   528: ifeq -> 1348
    //   531: goto -> 538
    //   534: invokestatic a : (Ljava/lang/Throwable;)Ljava/lang/Throwable;
    //   537: athrow
    //   538: aload_3
    //   539: getstatic burp/Zlbr.Zr : Ljava/lang/String;
    //   542: getstatic burp/Zb9m.ZK : Ljava/lang/Object;
    //   545: checkcast java/math/BigInteger
    //   548: invokevirtual intValue : ()I
    //   551: bipush #32
    //   553: irem
    //   554: invokestatic abs : (I)I
    //   557: invokevirtual charAt : (I)C
    //   560: invokevirtual append : (C)Ljava/lang/StringBuilder;
    //   563: pop
    //   564: iload_2
    //   565: ifeq -> 1348
    //   568: goto -> 575
    //   571: invokestatic a : (Ljava/lang/Throwable;)Ljava/lang/Throwable;
    //   574: athrow
    //   575: aload_3
    //   576: getstatic burp/Zsdn.Zf : Ljava/lang/String;
    //   579: getstatic burp/Zm_w.ZW : Ljava/lang/Object;
    //   582: checkcast java/math/BigInteger
    //   585: invokevirtual intValue : ()I
    //   588: bipush #32
    //   590: irem
    //   591: invokestatic abs : (I)I
    //   594: invokevirtual charAt : (I)C
    //   597: invokevirtual append : (C)Ljava/lang/StringBuilder;
    //   600: pop
    //   601: iload_2
    //   602: ifeq -> 1348
    //   605: goto -> 612
    //   608: invokestatic a : (Ljava/lang/Throwable;)Ljava/lang/Throwable;
    //   611: athrow
    //   612: aload_3
    //   613: getstatic burp/Zz16.ZA : Ljava/lang/String;
    //   616: getstatic burp/Ze3z.Zf : Ljava/lang/Object;
    //   619: checkcast java/math/BigInteger
    //   622: invokevirtual intValue : ()I
    //   625: bipush #32
    //   627: irem
    //   628: invokestatic abs : (I)I
    //   631: invokevirtual charAt : (I)C
    //   634: invokevirtual append : (C)Ljava/lang/StringBuilder;
    //   637: pop
    //   638: iload_2
    //   639: ifeq -> 1348
    //   642: goto -> 649
    //   645: invokestatic a : (Ljava/lang/Throwable;)Ljava/lang/Throwable;
    //   648: athrow
    //   649: aload_3
    //   650: getstatic burp/Ztvp.ZZ : Ljava/lang/String;
    //   653: getstatic burp/Zmy3.Zx : Ljava/lang/Object;
    //   656: checkcast java/math/BigInteger
    //   659: invokevirtual intValue : ()I
    //   662: bipush #32
    //   664: irem
    //   665: invokestatic abs : (I)I
    //   668: invokevirtual charAt : (I)C
    //   671: invokevirtual append : (C)Ljava/lang/StringBuilder;
    //   674: pop
    //   675: iload_2
    //   676: ifeq -> 1348
    //   679: goto -> 686
    //   682: invokestatic a : (Ljava/lang/Throwable;)Ljava/lang/Throwable;
    //   685: athrow
    //   686: aload_3
    //   687: getstatic burp/Zgde.Zr : Ljava/lang/String;
    //   690: getstatic burp/Zsuw.ZB : Ljava/lang/Object;
    //   693: checkcast java/math/BigInteger
    //   696: invokevirtual intValue : ()I
    //   699: bipush #32
    //   701: irem
    //   702: invokestatic abs : (I)I
    //   705: invokevirtual charAt : (I)C
    //   708: invokevirtual append : (C)Ljava/lang/StringBuilder;
    //   711: pop
    //   712: iload_2
    //   713: ifeq -> 1348
    //   716: goto -> 723
    //   719: invokestatic a : (Ljava/lang/Throwable;)Ljava/lang/Throwable;
    //   722: athrow
    //   723: aload_3
    //   724: getstatic burp/Zz16.ZA : Ljava/lang/String;
    //   727: getstatic burp/Zrcu.Zs : Ljava/lang/Object;
    //   730: checkcast java/math/BigInteger
    //   733: invokevirtual intValue : ()I
    //   736: bipush #32
    //   738: irem
    //   739: invokestatic abs : (I)I
    //   742: invokevirtual charAt : (I)C
    //   745: invokevirtual append : (C)Ljava/lang/StringBuilder;
    //   748: pop
    //   749: iload_2
    //   750: ifeq -> 1348
    //   753: goto -> 760
    //   756: invokestatic a : (Ljava/lang/Throwable;)Ljava/lang/Throwable;
    //   759: athrow
    //   760: aload_3
    //   761: getstatic burp/Zsqi.Zs : Ljava/lang/String;
    //   764: getstatic burp/Zx58.ZE : Ljava/lang/Object;
    //   767: checkcast java/math/BigInteger
    //   770: invokevirtual intValue : ()I
    //   773: bipush #32
    //   775: irem
    //   776: invokestatic abs : (I)I
    //   779: invokevirtual charAt : (I)C
    //   782: invokevirtual append : (C)Ljava/lang/StringBuilder;
    //   785: pop
    //   786: iload_2
    //   787: ifeq -> 1348
    //   790: goto -> 797
    //   793: invokestatic a : (Ljava/lang/Throwable;)Ljava/lang/Throwable;
    //   796: athrow
    //   797: aload_3
    //   798: getstatic burp/Zl1n.ZZ : Ljava/lang/String;
    //   801: getstatic burp/Zl6e.Zo : Ljava/lang/Object;
    //   804: checkcast java/math/BigInteger
    //   807: invokevirtual intValue : ()I
    //   810: bipush #32
    //   812: irem
    //   813: invokestatic abs : (I)I
    //   816: invokevirtual charAt : (I)C
    //   819: invokevirtual append : (C)Ljava/lang/StringBuilder;
    //   822: pop
    //   823: iload_2
    //   824: ifeq -> 1348
    //   827: goto -> 834
    //   830: invokestatic a : (Ljava/lang/Throwable;)Ljava/lang/Throwable;
    //   833: athrow
    //   834: aload_3
    //   835: getstatic burp/Zb6e.ZR : Ljava/lang/String;
    //   838: getstatic burp/Zk5y.ZL : Ljava/lang/Object;
    //   841: checkcast java/math/BigInteger
    //   844: invokevirtual intValue : ()I
    //   847: bipush #32
    //   849: irem
    //   850: invokestatic abs : (I)I
    //   853: invokevirtual charAt : (I)C
    //   856: invokevirtual append : (C)Ljava/lang/StringBuilder;
    //   859: pop
    //   860: iload_2
    //   861: ifeq -> 1348
    //   864: goto -> 871
    //   867: invokestatic a : (Ljava/lang/Throwable;)Ljava/lang/Throwable;
    //   870: athrow
    //   871: aload_3
    //   872: getstatic burp/Zb6e.ZR : Ljava/lang/String;
    //   875: getstatic burp/Zec0.Zg : Ljava/lang/Object;
    //   878: checkcast java/math/BigInteger
    //   881: invokevirtual intValue : ()I
    //   884: bipush #32
    //   886: irem
    //   887: invokestatic abs : (I)I
    //   890: invokevirtual charAt : (I)C
    //   893: invokevirtual append : (C)Ljava/lang/StringBuilder;
    //   896: pop
    //   897: iload_2
    //   898: ifeq -> 1348
    //   901: goto -> 908
    //   904: invokestatic a : (Ljava/lang/Throwable;)Ljava/lang/Throwable;
    //   907: athrow
    //   908: aload_3
    //   909: getstatic burp/Zs15.Zs : Ljava/lang/String;
    //   912: getstatic burp/Zvi.Zs : Ljava/lang/Object;
    //   915: checkcast java/math/BigInteger
    //   918: invokevirtual intValue : ()I
    //   921: bipush #32
    //   923: irem
    //   924: invokestatic abs : (I)I
    //   927: invokevirtual charAt : (I)C
    //   930: invokevirtual append : (C)Ljava/lang/StringBuilder;
    //   933: pop
    //   934: iload_2
    //   935: ifeq -> 1348
    //   938: goto -> 945
    //   941: invokestatic a : (Ljava/lang/Throwable;)Ljava/lang/Throwable;
    //   944: athrow
    //   945: aload_3
    //   946: getstatic burp/Zelz.ZK : Ljava/lang/String;
    //   949: getstatic burp/Zex5.Zb : Ljava/lang/Object;
    //   952: checkcast java/math/BigInteger
    //   955: invokevirtual intValue : ()I
    //   958: bipush #32
    //   960: irem
    //   961: invokestatic abs : (I)I
    //   964: invokevirtual charAt : (I)C
    //   967: invokevirtual append : (C)Ljava/lang/StringBuilder;
    //   970: pop
    //   971: iload_2
    //   972: ifeq -> 1348
    //   975: goto -> 982
    //   978: invokestatic a : (Ljava/lang/Throwable;)Ljava/lang/Throwable;
    //   981: athrow
    //   982: aload_3
    //   983: getstatic burp/Zl4v.ZD : Ljava/lang/String;
    //   986: getstatic burp/Zs15.Zk : Ljava/lang/Object;
    //   989: checkcast java/math/BigInteger
    //   992: invokevirtual intValue : ()I
    //   995: bipush #32
    //   997: irem
    //   998: invokestatic abs : (I)I
    //   1001: invokevirtual charAt : (I)C
    //   1004: invokevirtual append : (C)Ljava/lang/StringBuilder;
    //   1007: pop
    //   1008: iload_2
    //   1009: ifeq -> 1348
    //   1012: goto -> 1019
    //   1015: invokestatic a : (Ljava/lang/Throwable;)Ljava/lang/Throwable;
    //   1018: athrow
    //   1019: aload_3
    //   1020: getstatic burp/Zb6e.ZR : Ljava/lang/String;
    //   1023: getstatic burp/Zm_w.ZW : Ljava/lang/Object;
    //   1026: checkcast java/math/BigInteger
    //   1029: invokevirtual intValue : ()I
    //   1032: bipush #32
    //   1034: irem
    //   1035: invokestatic abs : (I)I
    //   1038: invokevirtual charAt : (I)C
    //   1041: invokevirtual append : (C)Ljava/lang/StringBuilder;
    //   1044: pop
    //   1045: iload_2
    //   1046: ifeq -> 1348
    //   1049: goto -> 1056
    //   1052: invokestatic a : (Ljava/lang/Throwable;)Ljava/lang/Throwable;
    //   1055: athrow
    //   1056: aload_3
    //   1057: getstatic burp/Zty4.Zu : Ljava/lang/String;
    //   1060: getstatic burp/Zg2z.ZU : Ljava/lang/Object;
    //   1063: checkcast java/math/BigInteger
    //   1066: invokevirtual intValue : ()I
    //   1069: bipush #32
    //   1071: irem
    //   1072: invokestatic abs : (I)I
    //   1075: invokevirtual charAt : (I)C
    //   1078: invokevirtual append : (C)Ljava/lang/StringBuilder;
    //   1081: pop
    //   1082: iload_2
    //   1083: ifeq -> 1348
    //   1086: goto -> 1093
    //   1089: invokestatic a : (Ljava/lang/Throwable;)Ljava/lang/Throwable;
    //   1092: athrow
    //   1093: aload_3
    //   1094: getstatic burp/Zt7w.Zi : Ljava/lang/String;
    //   1097: getstatic burp/Zrfl.Z_ : Ljava/lang/Object;
    //   1100: checkcast java/math/BigInteger
    //   1103: invokevirtual intValue : ()I
    //   1106: bipush #32
    //   1108: irem
    //   1109: invokestatic abs : (I)I
    //   1112: invokevirtual charAt : (I)C
    //   1115: invokevirtual append : (C)Ljava/lang/StringBuilder;
    //   1118: pop
    //   1119: iload_2
    //   1120: ifeq -> 1348
    //   1123: goto -> 1130
    //   1126: invokestatic a : (Ljava/lang/Throwable;)Ljava/lang/Throwable;
    //   1129: athrow
    //   1130: aload_3
    //   1131: getstatic burp/Zmpc.ZT : Ljava/lang/String;
    //   1134: getstatic burp/Zm1l.Za : Ljava/lang/Object;
    //   1137: checkcast java/math/BigInteger
    //   1140: invokevirtual intValue : ()I
    //   1143: bipush #32
    //   1145: irem
    //   1146: invokestatic abs : (I)I
    //   1149: invokevirtual charAt : (I)C
    //   1152: invokevirtual append : (C)Ljava/lang/StringBuilder;
    //   1155: pop
    //   1156: iload_2
    //   1157: ifeq -> 1348
    //   1160: goto -> 1167
    //   1163: invokestatic a : (Ljava/lang/Throwable;)Ljava/lang/Throwable;
    //   1166: athrow
    //   1167: aload_3
    //   1168: getstatic burp/Zmpc.ZT : Ljava/lang/String;
    //   1171: getstatic burp/Zvi.Zs : Ljava/lang/Object;
    //   1174: checkcast java/math/BigInteger
    //   1177: invokevirtual intValue : ()I
    //   1180: bipush #32
    //   1182: irem
    //   1183: invokestatic abs : (I)I
    //   1186: invokevirtual charAt : (I)C
    //   1189: invokevirtual append : (C)Ljava/lang/StringBuilder;
    //   1192: pop
    //   1193: iload_2
    //   1194: ifeq -> 1348
    //   1197: goto -> 1204
    //   1200: invokestatic a : (Ljava/lang/Throwable;)Ljava/lang/Throwable;
    //   1203: athrow
    //   1204: aload_3
    //   1205: getstatic burp/Zk8g.ZH : Ljava/lang/String;
    //   1208: getstatic burp/Zm81.Zy : Ljava/lang/Object;
    //   1211: checkcast java/math/BigInteger
    //   1214: invokevirtual intValue : ()I
    //   1217: bipush #32
    //   1219: irem
    //   1220: invokestatic abs : (I)I
    //   1223: invokevirtual charAt : (I)C
    //   1226: invokevirtual append : (C)Ljava/lang/StringBuilder;
    //   1229: pop
    //   1230: iload_2
    //   1231: ifeq -> 1348
    //   1234: goto -> 1241
    //   1237: invokestatic a : (Ljava/lang/Throwable;)Ljava/lang/Throwable;
    //   1240: athrow
    //   1241: aload_3
    //   1242: getstatic burp/Zztx.Zg : Ljava/lang/String;
    //   1245: getstatic burp/Zty2.Zl : Ljava/lang/Object;
    //   1248: checkcast java/math/BigInteger
    //   1251: invokevirtual intValue : ()I
    //   1254: bipush #32
    //   1256: irem
    //   1257: invokestatic abs : (I)I
    //   1260: invokevirtual charAt : (I)C
    //   1263: invokevirtual append : (C)Ljava/lang/StringBuilder;
    //   1266: pop
    //   1267: iload_2
    //   1268: ifeq -> 1348
    //   1271: goto -> 1278
    //   1274: invokestatic a : (Ljava/lang/Throwable;)Ljava/lang/Throwable;
    //   1277: athrow
    //   1278: aload_3
    //   1279: getstatic burp/Zs15.Zs : Ljava/lang/String;
    //   1282: getstatic burp/Zboa.Zh : Ljava/lang/Object;
    //   1285: checkcast java/math/BigInteger
    //   1288: invokevirtual intValue : ()I
    //   1291: bipush #32
    //   1293: irem
    //   1294: invokestatic abs : (I)I
    //   1297: invokevirtual charAt : (I)C
    //   1300: invokevirtual append : (C)Ljava/lang/StringBuilder;
    //   1303: pop
    //   1304: iload_2
    //   1305: ifeq -> 1348
    //   1308: goto -> 1315
    //   1311: invokestatic a : (Ljava/lang/Throwable;)Ljava/lang/Throwable;
    //   1314: athrow
    //   1315: aload_3
    //   1316: getstatic burp/Zec_.Zv : Ljava/lang/String;
    //   1319: getstatic burp/Zx58.ZE : Ljava/lang/Object;
    //   1322: checkcast java/math/BigInteger
    //   1325: invokevirtual intValue : ()I
    //   1328: bipush #32
    //   1330: irem
    //   1331: invokestatic abs : (I)I
    //   1334: invokevirtual charAt : (I)C
    //   1337: invokevirtual append : (C)Ljava/lang/StringBuilder;
    //   1340: pop
    //   1341: goto -> 1348
    //   1344: invokestatic a : (Ljava/lang/Throwable;)Ljava/lang/Throwable;
    //   1347: athrow
    //   1348: iinc #4, 1
    //   1351: iload_2
    //   1352: ifeq -> 15
    //   1355: aload_3
    //   1356: invokevirtual toString : ()Ljava/lang/String;
    //   1359: putstatic burp/Zec0.Zk : Ljava/lang/String;
    //   1362: getstatic burp/Zlh2.Zc : Ljava/lang/Object;
    //   1365: checkcast java/math/BigInteger
    //   1368: getstatic burp/Zt7w.ZF : Ljava/lang/Object;
    //   1371: checkcast java/math/BigInteger
    //   1374: invokevirtual subtract : (Ljava/math/BigInteger;)Ljava/math/BigInteger;
    //   1377: putstatic burp/Zl5d.Za : Ljava/lang/Object;
    //   1380: new java/lang/StringBuilder
    //   1383: dup
    //   1384: invokespecial <init> : ()V
    //   1387: astore #4
    //   1389: iconst_0
    //   1390: istore #5
    //   1392: iload #5
    //   1394: bipush #32
    //   1396: if_icmpge -> 2763
    //   1399: iload #5
    //   1401: tableswitch default -> 2756, 0 -> 1544, 1 -> 1582, 2 -> 1620, 3 -> 1658, 4 -> 1696, 5 -> 1734, 6 -> 1772, 7 -> 1810, 8 -> 1848, 9 -> 1886, 10 -> 1924, 11 -> 1962, 12 -> 2000, 13 -> 2038, 14 -> 2076, 15 -> 2114, 16 -> 2152, 17 -> 2190, 18 -> 2228, 19 -> 2266, 20 -> 2304, 21 -> 2342, 22 -> 2380, 23 -> 2418, 24 -> 2456, 25 -> 2494, 26 -> 2532, 27 -> 2570, 28 -> 2608, 29 -> 2646, 30 -> 2684, 31 -> 2722
    //   1544: aload #4
    //   1546: getstatic burp/Zsk4.ZH : Ljava/lang/String;
    //   1549: getstatic burp/Zrw7.ZV : Ljava/lang/Object;
    //   1552: checkcast java/math/BigInteger
    //   1555: invokevirtual intValue : ()I
    //   1558: bipush #32
    //   1560: irem
    //   1561: invokestatic abs : (I)I
    //   1564: invokevirtual charAt : (I)C
    //   1567: invokevirtual append : (C)Ljava/lang/StringBuilder;
    //   1570: pop
    //   1571: iload_2
    //   1572: ifeq -> 2756
    //   1575: goto -> 1582
    //   1578: invokestatic a : (Ljava/lang/Throwable;)Ljava/lang/Throwable;
    //   1581: athrow
    //   1582: aload #4
    //   1584: getstatic burp/Zx58.Zs : Ljava/lang/String;
    //   1587: getstatic burp/Zty2.Zl : Ljava/lang/Object;
    //   1590: checkcast java/math/BigInteger
    //   1593: invokevirtual intValue : ()I
    //   1596: bipush #32
    //   1598: irem
    //   1599: invokestatic abs : (I)I
    //   1602: invokevirtual charAt : (I)C
    //   1605: invokevirtual append : (C)Ljava/lang/StringBuilder;
    //   1608: pop
    //   1609: iload_2
    //   1610: ifeq -> 2756
    //   1613: goto -> 1620
    //   1616: invokestatic a : (Ljava/lang/Throwable;)Ljava/lang/Throwable;
    //   1619: athrow
    //   1620: aload #4
    //   1622: getstatic burp/Zsqi.Zs : Ljava/lang/String;
    //   1625: getstatic burp/Ze40.ZO : Ljava/lang/Object;
    //   1628: checkcast java/math/BigInteger
    //   1631: invokevirtual intValue : ()I
    //   1634: bipush #32
    //   1636: irem
    //   1637: invokestatic abs : (I)I
    //   1640: invokevirtual charAt : (I)C
    //   1643: invokevirtual append : (C)Ljava/lang/StringBuilder;
    //   1646: pop
    //   1647: iload_2
    //   1648: ifeq -> 2756
    //   1651: goto -> 1658
    //   1654: invokestatic a : (Ljava/lang/Throwable;)Ljava/lang/Throwable;
    //   1657: athrow
    //   1658: aload #4
    //   1660: getstatic burp/Zboa.Zq : Ljava/lang/String;
    //   1663: getstatic burp/Zlxh.ZU : Ljava/lang/Object;
    //   1666: checkcast java/math/BigInteger
    //   1669: invokevirtual intValue : ()I
    //   1672: bipush #32
    //   1674: irem
    //   1675: invokestatic abs : (I)I
    //   1678: invokevirtual charAt : (I)C
    //   1681: invokevirtual append : (C)Ljava/lang/StringBuilder;
    //   1684: pop
    //   1685: iload_2
    //   1686: ifeq -> 2756
    //   1689: goto -> 1696
    //   1692: invokestatic a : (Ljava/lang/Throwable;)Ljava/lang/Throwable;
    //   1695: athrow
    //   1696: aload #4
    //   1698: getstatic burp/Ztfr.Zo : Ljava/lang/String;
    //   1701: getstatic burp/Zl1n.ZM : Ljava/lang/Object;
    //   1704: checkcast java/math/BigInteger
    //   1707: invokevirtual intValue : ()I
    //   1710: bipush #32
    //   1712: irem
    //   1713: invokestatic abs : (I)I
    //   1716: invokevirtual charAt : (I)C
    //   1719: invokevirtual append : (C)Ljava/lang/StringBuilder;
    //   1722: pop
    //   1723: iload_2
    //   1724: ifeq -> 2756
    //   1727: goto -> 1734
    //   1730: invokestatic a : (Ljava/lang/Throwable;)Ljava/lang/Throwable;
    //   1733: athrow
    //   1734: aload #4
    //   1736: getstatic burp/Zty2.ZR : Ljava/lang/String;
    //   1739: getstatic burp/Zx58.ZE : Ljava/lang/Object;
    //   1742: checkcast java/math/BigInteger
    //   1745: invokevirtual intValue : ()I
    //   1748: bipush #32
    //   1750: irem
    //   1751: invokestatic abs : (I)I
    //   1754: invokevirtual charAt : (I)C
    //   1757: invokevirtual append : (C)Ljava/lang/StringBuilder;
    //   1760: pop
    //   1761: iload_2
    //   1762: ifeq -> 2756
    //   1765: goto -> 1772
    //   1768: invokestatic a : (Ljava/lang/Throwable;)Ljava/lang/Throwable;
    //   1771: athrow
    //   1772: aload #4
    //   1774: getstatic burp/Ze6k.ZM : Ljava/lang/String;
    //   1777: getstatic burp/Zl1q.Zh : Ljava/lang/Object;
    //   1780: checkcast java/math/BigInteger
    //   1783: invokevirtual intValue : ()I
    //   1786: bipush #32
    //   1788: irem
    //   1789: invokestatic abs : (I)I
    //   1792: invokevirtual charAt : (I)C
    //   1795: invokevirtual append : (C)Ljava/lang/StringBuilder;
    //   1798: pop
    //   1799: iload_2
    //   1800: ifeq -> 2756
    //   1803: goto -> 1810
    //   1806: invokestatic a : (Ljava/lang/Throwable;)Ljava/lang/Throwable;
    //   1809: athrow
    //   1810: aload #4
    //   1812: getstatic burp/Zlfi.Zg : Ljava/lang/String;
    //   1815: getstatic burp/Zlxh.ZU : Ljava/lang/Object;
    //   1818: checkcast java/math/BigInteger
    //   1821: invokevirtual intValue : ()I
    //   1824: bipush #32
    //   1826: irem
    //   1827: invokestatic abs : (I)I
    //   1830: invokevirtual charAt : (I)C
    //   1833: invokevirtual append : (C)Ljava/lang/StringBuilder;
    //   1836: pop
    //   1837: iload_2
    //   1838: ifeq -> 2756
    //   1841: goto -> 1848
    //   1844: invokestatic a : (Ljava/lang/Throwable;)Ljava/lang/Throwable;
    //   1847: athrow
    //   1848: aload #4
    //   1850: getstatic burp/Zsx6.ZJ : Ljava/lang/String;
    //   1853: getstatic burp/Zrw7.ZV : Ljava/lang/Object;
    //   1856: checkcast java/math/BigInteger
    //   1859: invokevirtual intValue : ()I
    //   1862: bipush #32
    //   1864: irem
    //   1865: invokestatic abs : (I)I
    //   1868: invokevirtual charAt : (I)C
    //   1871: invokevirtual append : (C)Ljava/lang/StringBuilder;
    //   1874: pop
    //   1875: iload_2
    //   1876: ifeq -> 2756
    //   1879: goto -> 1886
    //   1882: invokestatic a : (Ljava/lang/Throwable;)Ljava/lang/Throwable;
    //   1885: athrow
    //   1886: aload #4
    //   1888: getstatic burp/Ztvp.ZZ : Ljava/lang/String;
    //   1891: getstatic burp/Ze6k.Zs : Ljava/lang/Object;
    //   1894: checkcast java/math/BigInteger
    //   1897: invokevirtual intValue : ()I
    //   1900: bipush #32
    //   1902: irem
    //   1903: invokestatic abs : (I)I
    //   1906: invokevirtual charAt : (I)C
    //   1909: invokevirtual append : (C)Ljava/lang/StringBuilder;
    //   1912: pop
    //   1913: iload_2
    //   1914: ifeq -> 2756
    //   1917: goto -> 1924
    //   1920: invokestatic a : (Ljava/lang/Throwable;)Ljava/lang/Throwable;
    //   1923: athrow
    //   1924: aload #4
    //   1926: getstatic burp/Zec0.Zk : Ljava/lang/String;
    //   1929: getstatic burp/Zl4v.ZT : Ljava/lang/Object;
    //   1932: checkcast java/math/BigInteger
    //   1935: invokevirtual intValue : ()I
    //   1938: bipush #32
    //   1940: irem
    //   1941: invokestatic abs : (I)I
    //   1944: invokevirtual charAt : (I)C
    //   1947: invokevirtual append : (C)Ljava/lang/StringBuilder;
    //   1950: pop
    //   1951: iload_2
    //   1952: ifeq -> 2756
    //   1955: goto -> 1962
    //   1958: invokestatic a : (Ljava/lang/Throwable;)Ljava/lang/Throwable;
    //   1961: athrow
    //   1962: aload #4
    //   1964: getstatic burp/Zsk4.ZH : Ljava/lang/String;
    //   1967: getstatic burp/Zg7j.Zr : Ljava/lang/Object;
    //   1970: checkcast java/math/BigInteger
    //   1973: invokevirtual intValue : ()I
    //   1976: bipush #32
    //   1978: irem
    //   1979: invokestatic abs : (I)I
    //   1982: invokevirtual charAt : (I)C
    //   1985: invokevirtual append : (C)Ljava/lang/StringBuilder;
    //   1988: pop
    //   1989: iload_2
    //   1990: ifeq -> 2756
    //   1993: goto -> 2000
    //   1996: invokestatic a : (Ljava/lang/Throwable;)Ljava/lang/Throwable;
    //   1999: athrow
    //   2000: aload #4
    //   2002: getstatic burp/Zl4v.ZD : Ljava/lang/String;
    //   2005: getstatic burp/Zvi.Zs : Ljava/lang/Object;
    //   2008: checkcast java/math/BigInteger
    //   2011: invokevirtual intValue : ()I
    //   2014: bipush #32
    //   2016: irem
    //   2017: invokestatic abs : (I)I
    //   2020: invokevirtual charAt : (I)C
    //   2023: invokevirtual append : (C)Ljava/lang/StringBuilder;
    //   2026: pop
    //   2027: iload_2
    //   2028: ifeq -> 2756
    //   2031: goto -> 2038
    //   2034: invokestatic a : (Ljava/lang/Throwable;)Ljava/lang/Throwable;
    //   2037: athrow
    //   2038: aload #4
    //   2040: getstatic burp/Zeqr.Zb : Ljava/lang/String;
    //   2043: getstatic burp/Zg7j.Zr : Ljava/lang/Object;
    //   2046: checkcast java/math/BigInteger
    //   2049: invokevirtual intValue : ()I
    //   2052: bipush #32
    //   2054: irem
    //   2055: invokestatic abs : (I)I
    //   2058: invokevirtual charAt : (I)C
    //   2061: invokevirtual append : (C)Ljava/lang/StringBuilder;
    //   2064: pop
    //   2065: iload_2
    //   2066: ifeq -> 2756
    //   2069: goto -> 2076
    //   2072: invokestatic a : (Ljava/lang/Throwable;)Ljava/lang/Throwable;
    //   2075: athrow
    //   2076: aload #4
    //   2078: getstatic burp/Zx_b.ZD : Ljava/lang/String;
    //   2081: getstatic burp/Zsuw.ZB : Ljava/lang/Object;
    //   2084: checkcast java/math/BigInteger
    //   2087: invokevirtual intValue : ()I
    //   2090: bipush #32
    //   2092: irem
    //   2093: invokestatic abs : (I)I
    //   2096: invokevirtual charAt : (I)C
    //   2099: invokevirtual append : (C)Ljava/lang/StringBuilder;
    //   2102: pop
    //   2103: iload_2
    //   2104: ifeq -> 2756
    //   2107: goto -> 2114
    //   2110: invokestatic a : (Ljava/lang/Throwable;)Ljava/lang/Throwable;
    //   2113: athrow
    //   2114: aload #4
    //   2116: getstatic burp/Zz16.ZA : Ljava/lang/String;
    //   2119: getstatic burp/Zrw7.ZV : Ljava/lang/Object;
    //   2122: checkcast java/math/BigInteger
    //   2125: invokevirtual intValue : ()I
    //   2128: bipush #32
    //   2130: irem
    //   2131: invokestatic abs : (I)I
    //   2134: invokevirtual charAt : (I)C
    //   2137: invokevirtual append : (C)Ljava/lang/StringBuilder;
    //   2140: pop
    //   2141: iload_2
    //   2142: ifeq -> 2756
    //   2145: goto -> 2152
    //   2148: invokestatic a : (Ljava/lang/Throwable;)Ljava/lang/Throwable;
    //   2151: athrow
    //   2152: aload #4
    //   2154: getstatic burp/Zxof.Zs : Ljava/lang/String;
    //   2157: getstatic burp/Zxxd.Zn : Ljava/lang/Object;
    //   2160: checkcast java/math/BigInteger
    //   2163: invokevirtual intValue : ()I
    //   2166: bipush #32
    //   2168: irem
    //   2169: invokestatic abs : (I)I
    //   2172: invokevirtual charAt : (I)C
    //   2175: invokevirtual append : (C)Ljava/lang/StringBuilder;
    //   2178: pop
    //   2179: iload_2
    //   2180: ifeq -> 2756
    //   2183: goto -> 2190
    //   2186: invokestatic a : (Ljava/lang/Throwable;)Ljava/lang/Throwable;
    //   2189: athrow
    //   2190: aload #4
    //   2192: getstatic burp/Zrcx.ZW : Ljava/lang/String;
    //   2195: getstatic burp/Ze6k.Zs : Ljava/lang/Object;
    //   2198: checkcast java/math/BigInteger
    //   2201: invokevirtual intValue : ()I
    //   2204: bipush #32
    //   2206: irem
    //   2207: invokestatic abs : (I)I
    //   2210: invokevirtual charAt : (I)C
    //   2213: invokevirtual append : (C)Ljava/lang/StringBuilder;
    //   2216: pop
    //   2217: iload_2
    //   2218: ifeq -> 2756
    //   2221: goto -> 2228
    //   2224: invokestatic a : (Ljava/lang/Throwable;)Ljava/lang/Throwable;
    //   2227: athrow
    //   2228: aload #4
    //   2230: getstatic burp/Zlfi.Zg : Ljava/lang/String;
    //   2233: getstatic burp/Zmd.ZU : Ljava/lang/Object;
    //   2236: checkcast java/math/BigInteger
    //   2239: invokevirtual intValue : ()I
    //   2242: bipush #32
    //   2244: irem
    //   2245: invokestatic abs : (I)I
    //   2248: invokevirtual charAt : (I)C
    //   2251: invokevirtual append : (C)Ljava/lang/StringBuilder;
    //   2254: pop
    //   2255: iload_2
    //   2256: ifeq -> 2756
    //   2259: goto -> 2266
    //   2262: invokestatic a : (Ljava/lang/Throwable;)Ljava/lang/Throwable;
    //   2265: athrow
    //   2266: aload #4
    //   2268: getstatic burp/Zsuw.ZK : Ljava/lang/String;
    //   2271: getstatic burp/Zm_w.ZW : Ljava/lang/Object;
    //   2274: checkcast java/math/BigInteger
    //   2277: invokevirtual intValue : ()I
    //   2280: bipush #32
    //   2282: irem
    //   2283: invokestatic abs : (I)I
    //   2286: invokevirtual charAt : (I)C
    //   2289: invokevirtual append : (C)Ljava/lang/StringBuilder;
    //   2292: pop
    //   2293: iload_2
    //   2294: ifeq -> 2756
    //   2297: goto -> 2304
    //   2300: invokestatic a : (Ljava/lang/Throwable;)Ljava/lang/Throwable;
    //   2303: athrow
    //   2304: aload #4
    //   2306: getstatic burp/Zx_u.Z_ : Ljava/lang/String;
    //   2309: getstatic burp/Zg27.ZQ : Ljava/lang/Object;
    //   2312: checkcast java/math/BigInteger
    //   2315: invokevirtual intValue : ()I
    //   2318: bipush #32
    //   2320: irem
    //   2321: invokestatic abs : (I)I
    //   2324: invokevirtual charAt : (I)C
    //   2327: invokevirtual append : (C)Ljava/lang/StringBuilder;
    //   2330: pop
    //   2331: iload_2
    //   2332: ifeq -> 2756
    //   2335: goto -> 2342
    //   2338: invokestatic a : (Ljava/lang/Throwable;)Ljava/lang/Throwable;
    //   2341: athrow
    //   2342: aload #4
    //   2344: getstatic burp/Zmir.ZI : Ljava/lang/String;
    //   2347: getstatic burp/Zz16.ZK : Ljava/lang/Object;
    //   2350: checkcast java/math/BigInteger
    //   2353: invokevirtual intValue : ()I
    //   2356: bipush #32
    //   2358: irem
    //   2359: invokestatic abs : (I)I
    //   2362: invokevirtual charAt : (I)C
    //   2365: invokevirtual append : (C)Ljava/lang/StringBuilder;
    //   2368: pop
    //   2369: iload_2
    //   2370: ifeq -> 2756
    //   2373: goto -> 2380
    //   2376: invokestatic a : (Ljava/lang/Throwable;)Ljava/lang/Throwable;
    //   2379: athrow
    //   2380: aload #4
    //   2382: getstatic burp/Zl4v.ZD : Ljava/lang/String;
    //   2385: getstatic burp/Ztfr.Zr : Ljava/lang/Object;
    //   2388: checkcast java/math/BigInteger
    //   2391: invokevirtual intValue : ()I
    //   2394: bipush #32
    //   2396: irem
    //   2397: invokestatic abs : (I)I
    //   2400: invokevirtual charAt : (I)C
    //   2403: invokevirtual append : (C)Ljava/lang/StringBuilder;
    //   2406: pop
    //   2407: iload_2
    //   2408: ifeq -> 2756
    //   2411: goto -> 2418
    //   2414: invokestatic a : (Ljava/lang/Throwable;)Ljava/lang/Throwable;
    //   2417: athrow
    //   2418: aload #4
    //   2420: getstatic burp/Zsk4.ZH : Ljava/lang/String;
    //   2423: getstatic burp/Zlh2.Zc : Ljava/lang/Object;
    //   2426: checkcast java/math/BigInteger
    //   2429: invokevirtual intValue : ()I
    //   2432: bipush #32
    //   2434: irem
    //   2435: invokestatic abs : (I)I
    //   2438: invokevirtual charAt : (I)C
    //   2441: invokevirtual append : (C)Ljava/lang/StringBuilder;
    //   2444: pop
    //   2445: iload_2
    //   2446: ifeq -> 2756
    //   2449: goto -> 2456
    //   2452: invokestatic a : (Ljava/lang/Throwable;)Ljava/lang/Throwable;
    //   2455: athrow
    //   2456: aload #4
    //   2458: getstatic burp/Ze3z.Zv : Ljava/lang/String;
    //   2461: getstatic burp/Zsmn.Zq : Ljava/lang/Object;
    //   2464: checkcast java/math/BigInteger
    //   2467: invokevirtual intValue : ()I
    //   2470: bipush #32
    //   2472: irem
    //   2473: invokestatic abs : (I)I
    //   2476: invokevirtual charAt : (I)C
    //   2479: invokevirtual append : (C)Ljava/lang/StringBuilder;
    //   2482: pop
    //   2483: iload_2
    //   2484: ifeq -> 2756
    //   2487: goto -> 2494
    //   2490: invokestatic a : (Ljava/lang/Throwable;)Ljava/lang/Throwable;
    //   2493: athrow
    //   2494: aload #4
    //   2496: getstatic burp/Zx58.Zs : Ljava/lang/String;
    //   2499: getstatic burp/Zec0.Zg : Ljava/lang/Object;
    //   2502: checkcast java/math/BigInteger
    //   2505: invokevirtual intValue : ()I
    //   2508: bipush #32
    //   2510: irem
    //   2511: invokestatic abs : (I)I
    //   2514: invokevirtual charAt : (I)C
    //   2517: invokevirtual append : (C)Ljava/lang/StringBuilder;
    //   2520: pop
    //   2521: iload_2
    //   2522: ifeq -> 2756
    //   2525: goto -> 2532
    //   2528: invokestatic a : (Ljava/lang/Throwable;)Ljava/lang/Throwable;
    //   2531: athrow
    //   2532: aload #4
    //   2534: getstatic burp/Zlum.ZW : Ljava/lang/String;
    //   2537: getstatic burp/Zlpu.ZE : Ljava/lang/Object;
    //   2540: checkcast java/math/BigInteger
    //   2543: invokevirtual intValue : ()I
    //   2546: bipush #32
    //   2548: irem
    //   2549: invokestatic abs : (I)I
    //   2552: invokevirtual charAt : (I)C
    //   2555: invokevirtual append : (C)Ljava/lang/StringBuilder;
    //   2558: pop
    //   2559: iload_2
    //   2560: ifeq -> 2756
    //   2563: goto -> 2570
    //   2566: invokestatic a : (Ljava/lang/Throwable;)Ljava/lang/Throwable;
    //   2569: athrow
    //   2570: aload #4
    //   2572: getstatic burp/Zszz.Zg : Ljava/lang/String;
    //   2575: getstatic burp/Ztzw.Zk : Ljava/lang/Object;
    //   2578: checkcast java/math/BigInteger
    //   2581: invokevirtual intValue : ()I
    //   2584: bipush #32
    //   2586: irem
    //   2587: invokestatic abs : (I)I
    //   2590: invokevirtual charAt : (I)C
    //   2593: invokevirtual append : (C)Ljava/lang/StringBuilder;
    //   2596: pop
    //   2597: iload_2
    //   2598: ifeq -> 2756
    //   2601: goto -> 2608
    //   2604: invokestatic a : (Ljava/lang/Throwable;)Ljava/lang/Throwable;
    //   2607: athrow
    //   2608: aload #4
    //   2610: getstatic burp/Zk8g.ZH : Ljava/lang/String;
    //   2613: getstatic burp/Zg27.ZQ : Ljava/lang/Object;
    //   2616: checkcast java/math/BigInteger
    //   2619: invokevirtual intValue : ()I
    //   2622: bipush #32
    //   2624: irem
    //   2625: invokestatic abs : (I)I
    //   2628: invokevirtual charAt : (I)C
    //   2631: invokevirtual append : (C)Ljava/lang/StringBuilder;
    //   2634: pop
    //   2635: iload_2
    //   2636: ifeq -> 2756
    //   2639: goto -> 2646
    //   2642: invokestatic a : (Ljava/lang/Throwable;)Ljava/lang/Throwable;
    //   2645: athrow
    //   2646: aload #4
    //   2648: getstatic burp/Zb6e.ZR : Ljava/lang/String;
    //   2651: getstatic burp/Zg7j.Zr : Ljava/lang/Object;
    //   2654: checkcast java/math/BigInteger
    //   2657: invokevirtual intValue : ()I
    //   2660: bipush #32
    //   2662: irem
    //   2663: invokestatic abs : (I)I
    //   2666: invokevirtual charAt : (I)C
    //   2669: invokevirtual append : (C)Ljava/lang/StringBuilder;
    //   2672: pop
    //   2673: iload_2
    //   2674: ifeq -> 2756
    //   2677: goto -> 2684
    //   2680: invokestatic a : (Ljava/lang/Throwable;)Ljava/lang/Throwable;
    //   2683: athrow
    //   2684: aload #4
    //   2686: getstatic burp/Zm81.ZY : Ljava/lang/String;
    //   2689: getstatic burp/Zgr4.ZL : Ljava/lang/Object;
    //   2692: checkcast java/math/BigInteger
    //   2695: invokevirtual intValue : ()I
    //   2698: bipush #32
    //   2700: irem
    //   2701: invokestatic abs : (I)I
    //   2704: invokevirtual charAt : (I)C
    //   2707: invokevirtual append : (C)Ljava/lang/StringBuilder;
    //   2710: pop
    //   2711: iload_2
    //   2712: ifeq -> 2756
    //   2715: goto -> 2722
    //   2718: invokestatic a : (Ljava/lang/Throwable;)Ljava/lang/Throwable;
    //   2721: athrow
    //   2722: aload #4
    //   2724: getstatic burp/Zxjm.ZG : Ljava/lang/String;
    //   2727: getstatic burp/Zx58.ZE : Ljava/lang/Object;
    //   2730: checkcast java/math/BigInteger
    //   2733: invokevirtual intValue : ()I
    //   2736: bipush #32
    //   2738: irem
    //   2739: invokestatic abs : (I)I
    //   2742: invokevirtual charAt : (I)C
    //   2745: invokevirtual append : (C)Ljava/lang/StringBuilder;
    //   2748: pop
    //   2749: goto -> 2756
    //   2752: invokestatic a : (Ljava/lang/Throwable;)Ljava/lang/Throwable;
    //   2755: athrow
    //   2756: iinc #5, 1
    //   2759: iload_2
    //   2760: ifeq -> 1392
    //   2763: aload #4
    //   2765: invokevirtual toString : ()Ljava/lang/String;
    //   2768: putstatic burp/Zgfm.ZE : Ljava/lang/String;
    //   2771: sipush #-712
    //   2774: sipush #19764
    //   2777: invokestatic a : (II)Ljava/lang/String;
    //   2780: iconst_1
    //   2781: ldc burp/Zsk4
    //   2783: invokevirtual getClassLoader : ()Ljava/lang/ClassLoader;
    //   2786: invokestatic forName : (Ljava/lang/String;ZLjava/lang/ClassLoader;)Ljava/lang/Class;
    //   2789: invokevirtual getDeclaredFields : ()[Ljava/lang/reflect/Field;
    //   2792: astore #5
    //   2794: aload #5
    //   2796: arraylength
    //   2797: istore #6
    //   2799: iconst_0
    //   2800: istore #7
    //   2802: iload #7
    //   2804: iload #6
    //   2806: if_icmpge -> 2944
    //   2809: aload #5
    //   2811: iload #7
    //   2813: aaload
    //   2814: astore #8
    //   2816: aload #8
    //   2818: invokevirtual getModifiers : ()I
    //   2821: invokestatic isStatic : (I)Z
    //   2824: ifne -> 2834
    //   2827: goto -> 2937
    //   2830: invokestatic a : (Ljava/lang/Throwable;)Ljava/lang/Throwable;
    //   2833: athrow
    //   2834: aload #8
    //   2836: invokevirtual getType : ()Ljava/lang/Class;
    //   2839: astore #9
    //   2841: aload #9
    //   2843: ifnull -> 2924
    //   2846: aload #9
    //   2848: invokevirtual isPrimitive : ()Z
    //   2851: ifne -> 2924
    //   2854: goto -> 2861
    //   2857: invokestatic a : (Ljava/lang/Throwable;)Ljava/lang/Throwable;
    //   2860: athrow
    //   2861: aload #9
    //   2863: invokevirtual getPackage : ()Ljava/lang/Package;
    //   2866: ifnull -> 2924
    //   2869: goto -> 2876
    //   2872: invokestatic a : (Ljava/lang/Throwable;)Ljava/lang/Throwable;
    //   2875: athrow
    //   2876: aload #9
    //   2878: invokevirtual getPackage : ()Ljava/lang/Package;
    //   2881: invokevirtual getName : ()Ljava/lang/String;
    //   2884: ifnull -> 2924
    //   2887: goto -> 2894
    //   2890: invokestatic a : (Ljava/lang/Throwable;)Ljava/lang/Throwable;
    //   2893: athrow
    //   2894: aload #9
    //   2896: invokevirtual getPackage : ()Ljava/lang/Package;
    //   2899: invokevirtual getName : ()Ljava/lang/String;
    //   2902: sipush #-714
    //   2905: sipush #-24540
    //   2908: invokestatic a : (II)Ljava/lang/String;
    //   2911: invokevirtual startsWith : (Ljava/lang/String;)Z
    //   2914: ifne -> 2924
    //   2917: goto -> 2924
    //   2920: invokestatic a : (Ljava/lang/Throwable;)Ljava/lang/Throwable;
    //   2923: athrow
    //   2924: aload #8
    //   2926: iconst_1
    //   2927: invokevirtual setAccessible : (Z)V
    //   2930: aload #8
    //   2932: aconst_null
    //   2933: invokevirtual get : (Ljava/lang/Object;)Ljava/lang/Object;
    //   2936: pop
    //   2937: iinc #7, 1
    //   2940: iload_2
    //   2941: ifeq -> 2802
    //   2944: sipush #-717
    //   2947: sipush #-26960
    //   2950: invokestatic a : (II)Ljava/lang/String;
    //   2953: invokestatic forName : (Ljava/lang/String;)Ljava/lang/Class;
    //   2956: invokevirtual getDeclaredMethods : ()[Ljava/lang/reflect/Method;
    //   2959: astore #5
    //   2961: aload #5
    //   2963: arraylength
    //   2964: istore #6
    //   2966: iconst_0
    //   2967: istore #7
    //   2969: iload #7
    //   2971: iload #6
    //   2973: if_icmpge -> 3106
    //   2976: aload #5
    //   2978: iload #7
    //   2980: aaload
    //   2981: astore #8
    //   2983: aload #8
    //   2985: invokevirtual getParameterTypes : ()[Ljava/lang/Class;
    //   2988: pop
    //   2989: aload #8
    //   2991: invokevirtual getModifiers : ()I
    //   2994: invokestatic isStatic : (I)Z
    //   2997: ifeq -> 3092
    //   3000: aload #8
    //   3002: invokevirtual getParameterTypes : ()[Ljava/lang/Class;
    //   3005: arraylength
    //   3006: iconst_2
    //   3007: if_icmpne -> 3092
    //   3010: goto -> 3017
    //   3013: invokestatic a : (Ljava/lang/Throwable;)Ljava/lang/Throwable;
    //   3016: athrow
    //   3017: aload #8
    //   3019: invokevirtual getReturnType : ()Ljava/lang/Class;
    //   3022: getstatic java/lang/Void.TYPE : Ljava/lang/Class;
    //   3025: invokevirtual equals : (Ljava/lang/Object;)Z
    //   3028: ifeq -> 3092
    //   3031: goto -> 3038
    //   3034: invokestatic a : (Ljava/lang/Throwable;)Ljava/lang/Throwable;
    //   3037: athrow
    //   3038: aload #8
    //   3040: iconst_1
    //   3041: invokevirtual setAccessible : (Z)V
    //   3044: aload #8
    //   3046: aconst_null
    //   3047: iconst_2
    //   3048: anewarray java/lang/Object
    //   3051: dup
    //   3052: iconst_0
    //   3053: aload_0
    //   3054: aastore
    //   3055: dup
    //   3056: iconst_1
    //   3057: aload_1
    //   3058: ifnonnull -> 3076
    //   3061: goto -> 3068
    //   3064: invokestatic a : (Ljava/lang/Throwable;)Ljava/lang/Throwable;
    //   3067: athrow
    //   3068: aload_1
    //   3069: goto -> 3083
    //   3072: invokestatic a : (Ljava/lang/Throwable;)Ljava/lang/Throwable;
    //   3075: athrow
    //   3076: aload_1
    //   3077: checkcast [B
    //   3080: invokevirtual clone : ()Ljava/lang/Object;
    //   3083: aastore
    //   3084: invokevirtual invoke : (Ljava/lang/Object;[Ljava/lang/Object;)Ljava/lang/Object;
    //   3087: pop
    //   3088: iload_2
    //   3089: ifeq -> 3106
    //   3092: iinc #7, 1
    //   3095: iload_2
    //   3096: ifeq -> 2969
    //   3099: goto -> 3106
    //   3102: invokestatic a : (Ljava/lang/Throwable;)Ljava/lang/Throwable;
    //   3105: athrow
    //   3106: iconst_0
    //   3107: istore #5
    //   3109: getstatic burp/Zem6.Zp : Ljava/lang/String;
    //   3112: getstatic burp/Zegk.ZR : Ljava/lang/Object;
    //   3115: checkcast java/math/BigInteger
    //   3118: invokevirtual intValue : ()I
    //   3121: bipush #32
    //   3123: irem
    //   3124: invokestatic abs : (I)I
    //   3127: invokevirtual charAt : (I)C
    //   3130: getstatic burp/Zl4v.ZD : Ljava/lang/String;
    //   3133: getstatic burp/Zm4k.Zm : Ljava/lang/Object;
    //   3136: checkcast java/math/BigInteger
    //   3139: invokevirtual intValue : ()I
    //   3142: bipush #32
    //   3144: irem
    //   3145: invokestatic abs : (I)I
    //   3148: invokevirtual charAt : (I)C
    //   3151: if_icmple -> 3496
    //   3154: sipush #-705
    //   3157: sipush #-22594
    //   3160: invokestatic a : (II)Ljava/lang/String;
    //   3163: iconst_1
    //   3164: ldc burp/Zep8
    //   3166: invokevirtual getClassLoader : ()Ljava/lang/ClassLoader;
    //   3169: invokestatic forName : (Ljava/lang/String;ZLjava/lang/ClassLoader;)Ljava/lang/Class;
    //   3172: invokevirtual getDeclaredFields : ()[Ljava/lang/reflect/Field;
    //   3175: astore #6
    //   3177: aload #6
    //   3179: arraylength
    //   3180: istore #7
    //   3182: iconst_0
    //   3183: istore #8
    //   3185: iload #8
    //   3187: iload #7
    //   3189: if_icmpge -> 3327
    //   3192: aload #6
    //   3194: iload #8
    //   3196: aaload
    //   3197: astore #9
    //   3199: aload #9
    //   3201: invokevirtual getModifiers : ()I
    //   3204: invokestatic isStatic : (I)Z
    //   3207: ifne -> 3217
    //   3210: goto -> 3320
    //   3213: invokestatic a : (Ljava/lang/Throwable;)Ljava/lang/Throwable;
    //   3216: athrow
    //   3217: aload #9
    //   3219: invokevirtual getType : ()Ljava/lang/Class;
    //   3222: astore #10
    //   3224: aload #10
    //   3226: ifnull -> 3307
    //   3229: aload #10
    //   3231: invokevirtual isPrimitive : ()Z
    //   3234: ifne -> 3307
    //   3237: goto -> 3244
    //   3240: invokestatic a : (Ljava/lang/Throwable;)Ljava/lang/Throwable;
    //   3243: athrow
    //   3244: aload #10
    //   3246: invokevirtual getPackage : ()Ljava/lang/Package;
    //   3249: ifnull -> 3307
    //   3252: goto -> 3259
    //   3255: invokestatic a : (Ljava/lang/Throwable;)Ljava/lang/Throwable;
    //   3258: athrow
    //   3259: aload #10
    //   3261: invokevirtual getPackage : ()Ljava/lang/Package;
    //   3264: invokevirtual getName : ()Ljava/lang/String;
    //   3267: ifnull -> 3307
    //   3270: goto -> 3277
    //   3273: invokestatic a : (Ljava/lang/Throwable;)Ljava/lang/Throwable;
    //   3276: athrow
    //   3277: aload #10
    //   3279: invokevirtual getPackage : ()Ljava/lang/Package;
    //   3282: invokevirtual getName : ()Ljava/lang/String;
    //   3285: sipush #-733
    //   3288: sipush #18525
    //   3291: invokestatic a : (II)Ljava/lang/String;
    //   3294: invokevirtual startsWith : (Ljava/lang/String;)Z
    //   3297: ifne -> 3307
    //   3300: goto -> 3307
    //   3303: invokestatic a : (Ljava/lang/Throwable;)Ljava/lang/Throwable;
    //   3306: athrow
    //   3307: aload #9
    //   3309: iconst_1
    //   3310: invokevirtual setAccessible : (Z)V
    //   3313: aload #9
    //   3315: aconst_null
    //   3316: invokevirtual get : (Ljava/lang/Object;)Ljava/lang/Object;
    //   3319: pop
    //   3320: iinc #8, 1
    //   3323: iload_2
    //   3324: ifeq -> 3185
    //   3327: sipush #-713
    //   3330: sipush #-807
    //   3333: invokestatic a : (II)Ljava/lang/String;
    //   3336: invokestatic forName : (Ljava/lang/String;)Ljava/lang/Class;
    //   3339: invokevirtual getDeclaredMethods : ()[Ljava/lang/reflect/Method;
    //   3342: astore #6
    //   3344: aload #6
    //   3346: arraylength
    //   3347: istore #7
    //   3349: iconst_0
    //   3350: istore #8
    //   3352: iload #8
    //   3354: iload #7
    //   3356: if_icmpge -> 3493
    //   3359: aload #6
    //   3361: iload #8
    //   3363: aaload
    //   3364: astore #9
    //   3366: aload #9
    //   3368: invokevirtual getParameterTypes : ()[Ljava/lang/Class;
    //   3371: pop
    //   3372: aload #9
    //   3374: invokevirtual getModifiers : ()I
    //   3377: invokestatic isStatic : (I)Z
    //   3380: ifeq -> 3479
    //   3383: aload #9
    //   3385: invokevirtual getParameterTypes : ()[Ljava/lang/Class;
    //   3388: arraylength
    //   3389: iconst_2
    //   3390: if_icmpne -> 3479
    //   3393: goto -> 3400
    //   3396: invokestatic a : (Ljava/lang/Throwable;)Ljava/lang/Throwable;
    //   3399: athrow
    //   3400: aload #9
    //   3402: invokevirtual getReturnType : ()Ljava/lang/Class;
    //   3405: getstatic java/lang/Boolean.TYPE : Ljava/lang/Class;
    //   3408: if_acmpne -> 3479
    //   3411: goto -> 3418
    //   3414: invokestatic a : (Ljava/lang/Throwable;)Ljava/lang/Throwable;
    //   3417: athrow
    //   3418: aload #9
    //   3420: iconst_1
    //   3421: invokevirtual setAccessible : (Z)V
    //   3424: aload #9
    //   3426: aconst_null
    //   3427: iconst_2
    //   3428: anewarray java/lang/Object
    //   3431: dup
    //   3432: iconst_0
    //   3433: aload_0
    //   3434: aastore
    //   3435: dup
    //   3436: iconst_1
    //   3437: aload_1
    //   3438: ifnonnull -> 3456
    //   3441: goto -> 3448
    //   3444: invokestatic a : (Ljava/lang/Throwable;)Ljava/lang/Throwable;
    //   3447: athrow
    //   3448: aload_1
    //   3449: goto -> 3463
    //   3452: invokestatic a : (Ljava/lang/Throwable;)Ljava/lang/Throwable;
    //   3455: athrow
    //   3456: aload_1
    //   3457: checkcast [B
    //   3460: invokevirtual clone : ()Ljava/lang/Object;
    //   3463: aastore
    //   3464: invokevirtual invoke : (Ljava/lang/Object;[Ljava/lang/Object;)Ljava/lang/Object;
    //   3467: checkcast java/lang/Boolean
    //   3470: invokevirtual booleanValue : ()Z
    //   3473: istore #5
    //   3475: iload_2
    //   3476: ifeq -> 3493
    //   3479: iinc #8, 1
    //   3482: iload_2
    //   3483: ifeq -> 3352
    //   3486: goto -> 3493
    //   3489: invokestatic a : (Ljava/lang/Throwable;)Ljava/lang/Throwable;
    //   3492: athrow
    //   3493: goto -> 3835
    //   3496: sipush #-719
    //   3499: sipush #-6670
    //   3502: invokestatic a : (II)Ljava/lang/String;
    //   3505: iconst_1
    //   3506: ldc burp/Zxf8
    //   3508: invokevirtual getClassLoader : ()Ljava/lang/ClassLoader;
    //   3511: invokestatic forName : (Ljava/lang/String;ZLjava/lang/ClassLoader;)Ljava/lang/Class;
    //   3514: invokevirtual getDeclaredFields : ()[Ljava/lang/reflect/Field;
    //   3517: astore #6
    //   3519: aload #6
    //   3521: arraylength
    //   3522: istore #7
    //   3524: iconst_0
    //   3525: istore #8
    //   3527: iload #8
    //   3529: iload #7
    //   3531: if_icmpge -> 3669
    //   3534: aload #6
    //   3536: iload #8
    //   3538: aaload
    //   3539: astore #9
    //   3541: aload #9
    //   3543: invokevirtual getModifiers : ()I
    //   3546: invokestatic isStatic : (I)Z
    //   3549: ifne -> 3559
    //   3552: goto -> 3662
    //   3555: invokestatic a : (Ljava/lang/Throwable;)Ljava/lang/Throwable;
    //   3558: athrow
    //   3559: aload #9
    //   3561: invokevirtual getType : ()Ljava/lang/Class;
    //   3564: astore #10
    //   3566: aload #10
    //   3568: ifnull -> 3649
    //   3571: aload #10
    //   3573: invokevirtual isPrimitive : ()Z
    //   3576: ifne -> 3649
    //   3579: goto -> 3586
    //   3582: invokestatic a : (Ljava/lang/Throwable;)Ljava/lang/Throwable;
    //   3585: athrow
    //   3586: aload #10
    //   3588: invokevirtual getPackage : ()Ljava/lang/Package;
    //   3591: ifnull -> 3649
    //   3594: goto -> 3601
    //   3597: invokestatic a : (Ljava/lang/Throwable;)Ljava/lang/Throwable;
    //   3600: athrow
    //   3601: aload #10
    //   3603: invokevirtual getPackage : ()Ljava/lang/Package;
    //   3606: invokevirtual getName : ()Ljava/lang/String;
    //   3609: ifnull -> 3649
    //   3612: goto -> 3619
    //   3615: invokestatic a : (Ljava/lang/Throwable;)Ljava/lang/Throwable;
    //   3618: athrow
    //   3619: aload #10
    //   3621: invokevirtual getPackage : ()Ljava/lang/Package;
    //   3624: invokevirtual getName : ()Ljava/lang/String;
    //   3627: sipush #-733
    //   3630: sipush #18525
    //   3633: invokestatic a : (II)Ljava/lang/String;
    //   3636: invokevirtual startsWith : (Ljava/lang/String;)Z
    //   3639: ifne -> 3649
    //   3642: goto -> 3649
    //   3645: invokestatic a : (Ljava/lang/Throwable;)Ljava/lang/Throwable;
    //   3648: athrow
    //   3649: aload #9
    //   3651: iconst_1
    //   3652: invokevirtual setAccessible : (Z)V
    //   3655: aload #9
    //   3657: aconst_null
    //   3658: invokevirtual get : (Ljava/lang/Object;)Ljava/lang/Object;
    //   3661: pop
    //   3662: iinc #8, 1
    //   3665: iload_2
    //   3666: ifeq -> 3527
    //   3669: sipush #-729
    //   3672: sipush #7804
    //   3675: invokestatic a : (II)Ljava/lang/String;
    //   3678: invokestatic forName : (Ljava/lang/String;)Ljava/lang/Class;
    //   3681: invokevirtual getDeclaredMethods : ()[Ljava/lang/reflect/Method;
    //   3684: astore #6
    //   3686: aload #6
    //   3688: arraylength
    //   3689: istore #7
    //   3691: iconst_0
    //   3692: istore #8
    //   3694: iload #8
    //   3696: iload #7
    //   3698: if_icmpge -> 3835
    //   3701: aload #6
    //   3703: iload #8
    //   3705: aaload
    //   3706: astore #9
    //   3708: aload #9
    //   3710: invokevirtual getParameterTypes : ()[Ljava/lang/Class;
    //   3713: pop
    //   3714: aload #9
    //   3716: invokevirtual getModifiers : ()I
    //   3719: invokestatic isStatic : (I)Z
    //   3722: ifeq -> 3821
    //   3725: aload #9
    //   3727: invokevirtual getParameterTypes : ()[Ljava/lang/Class;
    //   3730: arraylength
    //   3731: iconst_2
    //   3732: if_icmpne -> 3821
    //   3735: goto -> 3742
    //   3738: invokestatic a : (Ljava/lang/Throwable;)Ljava/lang/Throwable;
    //   3741: athrow
    //   3742: aload #9
    //   3744: invokevirtual getReturnType : ()Ljava/lang/Class;
    //   3747: getstatic java/lang/Boolean.TYPE : Ljava/lang/Class;
    //   3750: if_acmpne -> 3821
    //   3753: goto -> 3760
    //   3756: invokestatic a : (Ljava/lang/Throwable;)Ljava/lang/Throwable;
    //   3759: athrow
    //   3760: aload #9
    //   3762: iconst_1
    //   3763: invokevirtual setAccessible : (Z)V
    //   3766: aload #9
    //   3768: aconst_null
    //   3769: iconst_2
    //   3770: anewarray java/lang/Object
    //   3773: dup
    //   3774: iconst_0
    //   3775: aload_0
    //   3776: aastore
    //   3777: dup
    //   3778: iconst_1
    //   3779: aload_1
    //   3780: ifnonnull -> 3798
    //   3783: goto -> 3790
    //   3786: invokestatic a : (Ljava/lang/Throwable;)Ljava/lang/Throwable;
    //   3789: athrow
    //   3790: aload_1
    //   3791: goto -> 3805
    //   3794: invokestatic a : (Ljava/lang/Throwable;)Ljava/lang/Throwable;
    //   3797: athrow
    //   3798: aload_1
    //   3799: checkcast [B
    //   3802: invokevirtual clone : ()Ljava/lang/Object;
    //   3805: aastore
    //   3806: invokevirtual invoke : (Ljava/lang/Object;[Ljava/lang/Object;)Ljava/lang/Object;
    //   3809: checkcast java/lang/Boolean
    //   3812: invokevirtual booleanValue : ()Z
    //   3815: istore #5
    //   3817: iload_2
    //   3818: ifeq -> 3835
    //   3821: iinc #8, 1
    //   3824: iload_2
    //   3825: ifeq -> 3694
    //   3828: goto -> 3835
    //   3831: invokestatic a : (Ljava/lang/Throwable;)Ljava/lang/Throwable;
    //   3834: athrow
    //   3835: iload #5
    //   3837: ifeq -> 3843
    //   3840: iload #5
    //   3842: ireturn
    //   3843: getstatic burp/Zsyu.ZJ : Ljava/lang/String;
    //   3846: getstatic burp/Zsbd.Zh : Ljava/lang/Object;
    //   3849: checkcast java/math/BigInteger
    //   3852: invokevirtual intValue : ()I
    //   3855: bipush #32
    //   3857: irem
    //   3858: invokestatic abs : (I)I
    //   3861: invokevirtual charAt : (I)C
    //   3864: getstatic burp/Zelz.ZK : Ljava/lang/String;
    //   3867: getstatic burp/Zeoi.ZE : Ljava/lang/Object;
    //   3870: checkcast java/math/BigInteger
    //   3873: invokevirtual intValue : ()I
    //   3876: bipush #32
    //   3878: irem
    //   3879: invokestatic abs : (I)I
    //   3882: invokevirtual charAt : (I)C
    //   3885: if_icmple -> 4231
    //   3888: sipush #-735
    //   3891: sipush #-10110
    //   3894: invokestatic a : (II)Ljava/lang/String;
    //   3897: iconst_1
    //   3898: ldc burp/Ztgv
    //   3900: invokevirtual getClassLoader : ()Ljava/lang/ClassLoader;
    //   3903: invokestatic forName : (Ljava/lang/String;ZLjava/lang/ClassLoader;)Ljava/lang/Class;
    //   3906: invokevirtual getDeclaredFields : ()[Ljava/lang/reflect/Field;
    //   3909: astore #6
    //   3911: aload #6
    //   3913: arraylength
    //   3914: istore #7
    //   3916: iconst_0
    //   3917: istore #8
    //   3919: iload #8
    //   3921: iload #7
    //   3923: if_icmpge -> 4061
    //   3926: aload #6
    //   3928: iload #8
    //   3930: aaload
    //   3931: astore #9
    //   3933: aload #9
    //   3935: invokevirtual getModifiers : ()I
    //   3938: invokestatic isStatic : (I)Z
    //   3941: ifne -> 3951
    //   3944: goto -> 4054
    //   3947: invokestatic a : (Ljava/lang/Throwable;)Ljava/lang/Throwable;
    //   3950: athrow
    //   3951: aload #9
    //   3953: invokevirtual getType : ()Ljava/lang/Class;
    //   3956: astore #10
    //   3958: aload #10
    //   3960: ifnull -> 4041
    //   3963: aload #10
    //   3965: invokevirtual isPrimitive : ()Z
    //   3968: ifne -> 4041
    //   3971: goto -> 3978
    //   3974: invokestatic a : (Ljava/lang/Throwable;)Ljava/lang/Throwable;
    //   3977: athrow
    //   3978: aload #10
    //   3980: invokevirtual getPackage : ()Ljava/lang/Package;
    //   3983: ifnull -> 4041
    //   3986: goto -> 3993
    //   3989: invokestatic a : (Ljava/lang/Throwable;)Ljava/lang/Throwable;
    //   3992: athrow
    //   3993: aload #10
    //   3995: invokevirtual getPackage : ()Ljava/lang/Package;
    //   3998: invokevirtual getName : ()Ljava/lang/String;
    //   4001: ifnull -> 4041
    //   4004: goto -> 4011
    //   4007: invokestatic a : (Ljava/lang/Throwable;)Ljava/lang/Throwable;
    //   4010: athrow
    //   4011: aload #10
    //   4013: invokevirtual getPackage : ()Ljava/lang/Package;
    //   4016: invokevirtual getName : ()Ljava/lang/String;
    //   4019: sipush #-733
    //   4022: sipush #18525
    //   4025: invokestatic a : (II)Ljava/lang/String;
    //   4028: invokevirtual startsWith : (Ljava/lang/String;)Z
    //   4031: ifne -> 4041
    //   4034: goto -> 4041
    //   4037: invokestatic a : (Ljava/lang/Throwable;)Ljava/lang/Throwable;
    //   4040: athrow
    //   4041: aload #9
    //   4043: iconst_1
    //   4044: invokevirtual setAccessible : (Z)V
    //   4047: aload #9
    //   4049: aconst_null
    //   4050: invokevirtual get : (Ljava/lang/Object;)Ljava/lang/Object;
    //   4053: pop
    //   4054: iinc #8, 1
    //   4057: iload_2
    //   4058: ifeq -> 3919
    //   4061: sipush #-732
    //   4064: sipush #-18374
    //   4067: invokestatic a : (II)Ljava/lang/String;
    //   4070: invokestatic forName : (Ljava/lang/String;)Ljava/lang/Class;
    //   4073: invokevirtual getDeclaredMethods : ()[Ljava/lang/reflect/Method;
    //   4076: astore #6
    //   4078: aload #6
    //   4080: arraylength
    //   4081: istore #7
    //   4083: iconst_0
    //   4084: istore #8
    //   4086: iload #8
    //   4088: iload #7
    //   4090: if_icmpge -> 4227
    //   4093: aload #6
    //   4095: iload #8
    //   4097: aaload
    //   4098: astore #9
    //   4100: aload #9
    //   4102: invokevirtual getParameterTypes : ()[Ljava/lang/Class;
    //   4105: pop
    //   4106: aload #9
    //   4108: invokevirtual getModifiers : ()I
    //   4111: invokestatic isStatic : (I)Z
    //   4114: ifeq -> 4213
    //   4117: aload #9
    //   4119: invokevirtual getParameterTypes : ()[Ljava/lang/Class;
    //   4122: arraylength
    //   4123: iconst_2
    //   4124: if_icmpne -> 4213
    //   4127: goto -> 4134
    //   4130: invokestatic a : (Ljava/lang/Throwable;)Ljava/lang/Throwable;
    //   4133: athrow
    //   4134: aload #9
    //   4136: invokevirtual getReturnType : ()Ljava/lang/Class;
    //   4139: getstatic java/lang/Boolean.TYPE : Ljava/lang/Class;
    //   4142: if_acmpne -> 4213
    //   4145: goto -> 4152
    //   4148: invokestatic a : (Ljava/lang/Throwable;)Ljava/lang/Throwable;
    //   4151: athrow
    //   4152: aload #9
    //   4154: iconst_1
    //   4155: invokevirtual setAccessible : (Z)V
    //   4158: aload #9
    //   4160: aconst_null
    //   4161: iconst_2
    //   4162: anewarray java/lang/Object
    //   4165: dup
    //   4166: iconst_0
    //   4167: aload_0
    //   4168: aastore
    //   4169: dup
    //   4170: iconst_1
    //   4171: aload_1
    //   4172: ifnonnull -> 4190
    //   4175: goto -> 4182
    //   4178: invokestatic a : (Ljava/lang/Throwable;)Ljava/lang/Throwable;
    //   4181: athrow
    //   4182: aload_1
    //   4183: goto -> 4197
    //   4186: invokestatic a : (Ljava/lang/Throwable;)Ljava/lang/Throwable;
    //   4189: athrow
    //   4190: aload_1
    //   4191: checkcast [B
    //   4194: invokevirtual clone : ()Ljava/lang/Object;
    //   4197: aastore
    //   4198: invokevirtual invoke : (Ljava/lang/Object;[Ljava/lang/Object;)Ljava/lang/Object;
    //   4201: checkcast java/lang/Boolean
    //   4204: invokevirtual booleanValue : ()Z
    //   4207: istore #5
    //   4209: iload_2
    //   4210: ifeq -> 4227
    //   4213: iinc #8, 1
    //   4216: iload_2
    //   4217: ifeq -> 4086
    //   4220: goto -> 4227
    //   4223: invokestatic a : (Ljava/lang/Throwable;)Ljava/lang/Throwable;
    //   4226: athrow
    //   4227: iload_2
    //   4228: ifeq -> 4570
    //   4231: sipush #-709
    //   4234: sipush #-23030
    //   4237: invokestatic a : (II)Ljava/lang/String;
    //   4240: iconst_1
    //   4241: ldc burp/Zm4k
    //   4243: invokevirtual getClassLoader : ()Ljava/lang/ClassLoader;
    //   4246: invokestatic forName : (Ljava/lang/String;ZLjava/lang/ClassLoader;)Ljava/lang/Class;
    //   4249: invokevirtual getDeclaredFields : ()[Ljava/lang/reflect/Field;
    //   4252: astore #6
    //   4254: aload #6
    //   4256: arraylength
    //   4257: istore #7
    //   4259: iconst_0
    //   4260: istore #8
    //   4262: iload #8
    //   4264: iload #7
    //   4266: if_icmpge -> 4404
    //   4269: aload #6
    //   4271: iload #8
    //   4273: aaload
    //   4274: astore #9
    //   4276: aload #9
    //   4278: invokevirtual getModifiers : ()I
    //   4281: invokestatic isStatic : (I)Z
    //   4284: ifne -> 4294
    //   4287: goto -> 4397
    //   4290: invokestatic a : (Ljava/lang/Throwable;)Ljava/lang/Throwable;
    //   4293: athrow
    //   4294: aload #9
    //   4296: invokevirtual getType : ()Ljava/lang/Class;
    //   4299: astore #10
    //   4301: aload #10
    //   4303: ifnull -> 4384
    //   4306: aload #10
    //   4308: invokevirtual isPrimitive : ()Z
    //   4311: ifne -> 4384
    //   4314: goto -> 4321
    //   4317: invokestatic a : (Ljava/lang/Throwable;)Ljava/lang/Throwable;
    //   4320: athrow
    //   4321: aload #10
    //   4323: invokevirtual getPackage : ()Ljava/lang/Package;
    //   4326: ifnull -> 4384
    //   4329: goto -> 4336
    //   4332: invokestatic a : (Ljava/lang/Throwable;)Ljava/lang/Throwable;
    //   4335: athrow
    //   4336: aload #10
    //   4338: invokevirtual getPackage : ()Ljava/lang/Package;
    //   4341: invokevirtual getName : ()Ljava/lang/String;
    //   4344: ifnull -> 4384
    //   4347: goto -> 4354
    //   4350: invokestatic a : (Ljava/lang/Throwable;)Ljava/lang/Throwable;
    //   4353: athrow
    //   4354: aload #10
    //   4356: invokevirtual getPackage : ()Ljava/lang/Package;
    //   4359: invokevirtual getName : ()Ljava/lang/String;
    //   4362: sipush #-733
    //   4365: sipush #18525
    //   4368: invokestatic a : (II)Ljava/lang/String;
    //   4371: invokevirtual startsWith : (Ljava/lang/String;)Z
    //   4374: ifne -> 4384
    //   4377: goto -> 4384
    //   4380: invokestatic a : (Ljava/lang/Throwable;)Ljava/lang/Throwable;
    //   4383: athrow
    //   4384: aload #9
    //   4386: iconst_1
    //   4387: invokevirtual setAccessible : (Z)V
    //   4390: aload #9
    //   4392: aconst_null
    //   4393: invokevirtual get : (Ljava/lang/Object;)Ljava/lang/Object;
    //   4396: pop
    //   4397: iinc #8, 1
    //   4400: iload_2
    //   4401: ifeq -> 4262
    //   4404: sipush #-731
    //   4407: sipush #24288
    //   4410: invokestatic a : (II)Ljava/lang/String;
    //   4413: invokestatic forName : (Ljava/lang/String;)Ljava/lang/Class;
    //   4416: invokevirtual getDeclaredMethods : ()[Ljava/lang/reflect/Method;
    //   4419: astore #6
    //   4421: aload #6
    //   4423: arraylength
    //   4424: istore #7
    //   4426: iconst_0
    //   4427: istore #8
    //   4429: iload #8
    //   4431: iload #7
    //   4433: if_icmpge -> 4570
    //   4436: aload #6
    //   4438: iload #8
    //   4440: aaload
    //   4441: astore #9
    //   4443: aload #9
    //   4445: invokevirtual getParameterTypes : ()[Ljava/lang/Class;
    //   4448: pop
    //   4449: aload #9
    //   4451: invokevirtual getModifiers : ()I
    //   4454: invokestatic isStatic : (I)Z
    //   4457: ifeq -> 4556
    //   4460: aload #9
    //   4462: invokevirtual getParameterTypes : ()[Ljava/lang/Class;
    //   4465: arraylength
    //   4466: iconst_2
    //   4467: if_icmpne -> 4556
    //   4470: goto -> 4477
    //   4473: invokestatic a : (Ljava/lang/Throwable;)Ljava/lang/Throwable;
    //   4476: athrow
    //   4477: aload #9
    //   4479: invokevirtual getReturnType : ()Ljava/lang/Class;
    //   4482: getstatic java/lang/Boolean.TYPE : Ljava/lang/Class;
    //   4485: if_acmpne -> 4556
    //   4488: goto -> 4495
    //   4491: invokestatic a : (Ljava/lang/Throwable;)Ljava/lang/Throwable;
    //   4494: athrow
    //   4495: aload #9
    //   4497: iconst_1
    //   4498: invokevirtual setAccessible : (Z)V
    //   4501: aload #9
    //   4503: aconst_null
    //   4504: iconst_2
    //   4505: anewarray java/lang/Object
    //   4508: dup
    //   4509: iconst_0
    //   4510: aload_0
    //   4511: aastore
    //   4512: dup
    //   4513: iconst_1
    //   4514: aload_1
    //   4515: ifnonnull -> 4533
    //   4518: goto -> 4525
    //   4521: invokestatic a : (Ljava/lang/Throwable;)Ljava/lang/Throwable;
    //   4524: athrow
    //   4525: aload_1
    //   4526: goto -> 4540
    //   4529: invokestatic a : (Ljava/lang/Throwable;)Ljava/lang/Throwable;
    //   4532: athrow
    //   4533: aload_1
    //   4534: checkcast [B
    //   4537: invokevirtual clone : ()Ljava/lang/Object;
    //   4540: aastore
    //   4541: invokevirtual invoke : (Ljava/lang/Object;[Ljava/lang/Object;)Ljava/lang/Object;
    //   4544: checkcast java/lang/Boolean
    //   4547: invokevirtual booleanValue : ()Z
    //   4550: istore #5
    //   4552: iload_2
    //   4553: ifeq -> 4570
    //   4556: iinc #8, 1
    //   4559: iload_2
    //   4560: ifeq -> 4429
    //   4563: goto -> 4570
    //   4566: invokestatic a : (Ljava/lang/Throwable;)Ljava/lang/Throwable;
    //   4569: athrow
    //   4570: iload #5
    //   4572: ifeq -> 4578
    //   4575: iload #5
    //   4577: ireturn
    //   4578: getstatic burp/Zz16.ZA : Ljava/lang/String;
    //   4581: getstatic burp/Ze6k.Zs : Ljava/lang/Object;
    //   4584: checkcast java/math/BigInteger
    //   4587: invokevirtual intValue : ()I
    //   4590: bipush #32
    //   4592: irem
    //   4593: invokestatic abs : (I)I
    //   4596: invokevirtual charAt : (I)C
    //   4599: getstatic burp/Zegk.Ze : Ljava/lang/String;
    //   4602: getstatic burp/Zl1q.Zh : Ljava/lang/Object;
    //   4605: checkcast java/math/BigInteger
    //   4608: invokevirtual intValue : ()I
    //   4611: bipush #32
    //   4613: irem
    //   4614: invokestatic abs : (I)I
    //   4617: invokevirtual charAt : (I)C
    //   4620: if_icmpgt -> 4966
    //   4623: sipush #-706
    //   4626: sipush #-10301
    //   4629: invokestatic a : (II)Ljava/lang/String;
    //   4632: iconst_1
    //   4633: ldc burp/Zsts
    //   4635: invokevirtual getClassLoader : ()Ljava/lang/ClassLoader;
    //   4638: invokestatic forName : (Ljava/lang/String;ZLjava/lang/ClassLoader;)Ljava/lang/Class;
    //   4641: invokevirtual getDeclaredFields : ()[Ljava/lang/reflect/Field;
    //   4644: astore #6
    //   4646: aload #6
    //   4648: arraylength
    //   4649: istore #7
    //   4651: iconst_0
    //   4652: istore #8
    //   4654: iload #8
    //   4656: iload #7
    //   4658: if_icmpge -> 4796
    //   4661: aload #6
    //   4663: iload #8
    //   4665: aaload
    //   4666: astore #9
    //   4668: aload #9
    //   4670: invokevirtual getModifiers : ()I
    //   4673: invokestatic isStatic : (I)Z
    //   4676: ifne -> 4686
    //   4679: goto -> 4789
    //   4682: invokestatic a : (Ljava/lang/Throwable;)Ljava/lang/Throwable;
    //   4685: athrow
    //   4686: aload #9
    //   4688: invokevirtual getType : ()Ljava/lang/Class;
    //   4691: astore #10
    //   4693: aload #10
    //   4695: ifnull -> 4776
    //   4698: aload #10
    //   4700: invokevirtual isPrimitive : ()Z
    //   4703: ifne -> 4776
    //   4706: goto -> 4713
    //   4709: invokestatic a : (Ljava/lang/Throwable;)Ljava/lang/Throwable;
    //   4712: athrow
    //   4713: aload #10
    //   4715: invokevirtual getPackage : ()Ljava/lang/Package;
    //   4718: ifnull -> 4776
    //   4721: goto -> 4728
    //   4724: invokestatic a : (Ljava/lang/Throwable;)Ljava/lang/Throwable;
    //   4727: athrow
    //   4728: aload #10
    //   4730: invokevirtual getPackage : ()Ljava/lang/Package;
    //   4733: invokevirtual getName : ()Ljava/lang/String;
    //   4736: ifnull -> 4776
    //   4739: goto -> 4746
    //   4742: invokestatic a : (Ljava/lang/Throwable;)Ljava/lang/Throwable;
    //   4745: athrow
    //   4746: aload #10
    //   4748: invokevirtual getPackage : ()Ljava/lang/Package;
    //   4751: invokevirtual getName : ()Ljava/lang/String;
    //   4754: sipush #-733
    //   4757: sipush #18525
    //   4760: invokestatic a : (II)Ljava/lang/String;
    //   4763: invokevirtual startsWith : (Ljava/lang/String;)Z
    //   4766: ifne -> 4776
    //   4769: goto -> 4776
    //   4772: invokestatic a : (Ljava/lang/Throwable;)Ljava/lang/Throwable;
    //   4775: athrow
    //   4776: aload #9
    //   4778: iconst_1
    //   4779: invokevirtual setAccessible : (Z)V
    //   4782: aload #9
    //   4784: aconst_null
    //   4785: invokevirtual get : (Ljava/lang/Object;)Ljava/lang/Object;
    //   4788: pop
    //   4789: iinc #8, 1
    //   4792: iload_2
    //   4793: ifeq -> 4654
    //   4796: sipush #-715
    //   4799: sipush #7481
    //   4802: invokestatic a : (II)Ljava/lang/String;
    //   4805: invokestatic forName : (Ljava/lang/String;)Ljava/lang/Class;
    //   4808: invokevirtual getDeclaredMethods : ()[Ljava/lang/reflect/Method;
    //   4811: astore #6
    //   4813: aload #6
    //   4815: arraylength
    //   4816: istore #7
    //   4818: iconst_0
    //   4819: istore #8
    //   4821: iload #8
    //   4823: iload #7
    //   4825: if_icmpge -> 4962
    //   4828: aload #6
    //   4830: iload #8
    //   4832: aaload
    //   4833: astore #9
    //   4835: aload #9
    //   4837: invokevirtual getParameterTypes : ()[Ljava/lang/Class;
    //   4840: pop
    //   4841: aload #9
    //   4843: invokevirtual getModifiers : ()I
    //   4846: invokestatic isStatic : (I)Z
    //   4849: ifeq -> 4948
    //   4852: aload #9
    //   4854: invokevirtual getParameterTypes : ()[Ljava/lang/Class;
    //   4857: arraylength
    //   4858: iconst_2
    //   4859: if_icmpne -> 4948
    //   4862: goto -> 4869
    //   4865: invokestatic a : (Ljava/lang/Throwable;)Ljava/lang/Throwable;
    //   4868: athrow
    //   4869: aload #9
    //   4871: invokevirtual getReturnType : ()Ljava/lang/Class;
    //   4874: getstatic java/lang/Boolean.TYPE : Ljava/lang/Class;
    //   4877: if_acmpne -> 4948
    //   4880: goto -> 4887
    //   4883: invokestatic a : (Ljava/lang/Throwable;)Ljava/lang/Throwable;
    //   4886: athrow
    //   4887: aload #9
    //   4889: iconst_1
    //   4890: invokevirtual setAccessible : (Z)V
    //   4893: aload #9
    //   4895: aconst_null
    //   4896: iconst_2
    //   4897: anewarray java/lang/Object
    //   4900: dup
    //   4901: iconst_0
    //   4902: aload_0
    //   4903: aastore
    //   4904: dup
    //   4905: iconst_1
    //   4906: aload_1
    //   4907: ifnonnull -> 4925
    //   4910: goto -> 4917
    //   4913: invokestatic a : (Ljava/lang/Throwable;)Ljava/lang/Throwable;
    //   4916: athrow
    //   4917: aload_1
    //   4918: goto -> 4932
    //   4921: invokestatic a : (Ljava/lang/Throwable;)Ljava/lang/Throwable;
    //   4924: athrow
    //   4925: aload_1
    //   4926: checkcast [B
    //   4929: invokevirtual clone : ()Ljava/lang/Object;
    //   4932: aastore
    //   4933: invokevirtual invoke : (Ljava/lang/Object;[Ljava/lang/Object;)Ljava/lang/Object;
    //   4936: checkcast java/lang/Boolean
    //   4939: invokevirtual booleanValue : ()Z
    //   4942: istore #5
    //   4944: iload_2
    //   4945: ifeq -> 4962
    //   4948: iinc #8, 1
    //   4951: iload_2
    //   4952: ifeq -> 4821
    //   4955: goto -> 4962
    //   4958: invokestatic a : (Ljava/lang/Throwable;)Ljava/lang/Throwable;
    //   4961: athrow
    //   4962: iload_2
    //   4963: ifeq -> 5305
    //   4966: sipush #-708
    //   4969: sipush #-19582
    //   4972: invokestatic a : (II)Ljava/lang/String;
    //   4975: iconst_1
    //   4976: ldc burp/Zsgj
    //   4978: invokevirtual getClassLoader : ()Ljava/lang/ClassLoader;
    //   4981: invokestatic forName : (Ljava/lang/String;ZLjava/lang/ClassLoader;)Ljava/lang/Class;
    //   4984: invokevirtual getDeclaredFields : ()[Ljava/lang/reflect/Field;
    //   4987: astore #6
    //   4989: aload #6
    //   4991: arraylength
    //   4992: istore #7
    //   4994: iconst_0
    //   4995: istore #8
    //   4997: iload #8
    //   4999: iload #7
    //   5001: if_icmpge -> 5139
    //   5004: aload #6
    //   5006: iload #8
    //   5008: aaload
    //   5009: astore #9
    //   5011: aload #9
    //   5013: invokevirtual getModifiers : ()I
    //   5016: invokestatic isStatic : (I)Z
    //   5019: ifne -> 5029
    //   5022: goto -> 5132
    //   5025: invokestatic a : (Ljava/lang/Throwable;)Ljava/lang/Throwable;
    //   5028: athrow
    //   5029: aload #9
    //   5031: invokevirtual getType : ()Ljava/lang/Class;
    //   5034: astore #10
    //   5036: aload #10
    //   5038: ifnull -> 5119
    //   5041: aload #10
    //   5043: invokevirtual isPrimitive : ()Z
    //   5046: ifne -> 5119
    //   5049: goto -> 5056
    //   5052: invokestatic a : (Ljava/lang/Throwable;)Ljava/lang/Throwable;
    //   5055: athrow
    //   5056: aload #10
    //   5058: invokevirtual getPackage : ()Ljava/lang/Package;
    //   5061: ifnull -> 5119
    //   5064: goto -> 5071
    //   5067: invokestatic a : (Ljava/lang/Throwable;)Ljava/lang/Throwable;
    //   5070: athrow
    //   5071: aload #10
    //   5073: invokevirtual getPackage : ()Ljava/lang/Package;
    //   5076: invokevirtual getName : ()Ljava/lang/String;
    //   5079: ifnull -> 5119
    //   5082: goto -> 5089
    //   5085: invokestatic a : (Ljava/lang/Throwable;)Ljava/lang/Throwable;
    //   5088: athrow
    //   5089: aload #10
    //   5091: invokevirtual getPackage : ()Ljava/lang/Package;
    //   5094: invokevirtual getName : ()Ljava/lang/String;
    //   5097: sipush #-733
    //   5100: sipush #18525
    //   5103: invokestatic a : (II)Ljava/lang/String;
    //   5106: invokevirtual startsWith : (Ljava/lang/String;)Z
    //   5109: ifne -> 5119
    //   5112: goto -> 5119
    //   5115: invokestatic a : (Ljava/lang/Throwable;)Ljava/lang/Throwable;
    //   5118: athrow
    //   5119: aload #9
    //   5121: iconst_1
    //   5122: invokevirtual setAccessible : (Z)V
    //   5125: aload #9
    //   5127: aconst_null
    //   5128: invokevirtual get : (Ljava/lang/Object;)Ljava/lang/Object;
    //   5131: pop
    //   5132: iinc #8, 1
    //   5135: iload_2
    //   5136: ifeq -> 4997
    //   5139: sipush #-728
    //   5142: sipush #31801
    //   5145: invokestatic a : (II)Ljava/lang/String;
    //   5148: invokestatic forName : (Ljava/lang/String;)Ljava/lang/Class;
    //   5151: invokevirtual getDeclaredMethods : ()[Ljava/lang/reflect/Method;
    //   5154: astore #6
    //   5156: aload #6
    //   5158: arraylength
    //   5159: istore #7
    //   5161: iconst_0
    //   5162: istore #8
    //   5164: iload #8
    //   5166: iload #7
    //   5168: if_icmpge -> 5305
    //   5171: aload #6
    //   5173: iload #8
    //   5175: aaload
    //   5176: astore #9
    //   5178: aload #9
    //   5180: invokevirtual getParameterTypes : ()[Ljava/lang/Class;
    //   5183: pop
    //   5184: aload #9
    //   5186: invokevirtual getModifiers : ()I
    //   5189: invokestatic isStatic : (I)Z
    //   5192: ifeq -> 5291
    //   5195: aload #9
    //   5197: invokevirtual getParameterTypes : ()[Ljava/lang/Class;
    //   5200: arraylength
    //   5201: iconst_2
    //   5202: if_icmpne -> 5291
    //   5205: goto -> 5212
    //   5208: invokestatic a : (Ljava/lang/Throwable;)Ljava/lang/Throwable;
    //   5211: athrow
    //   5212: aload #9
    //   5214: invokevirtual getReturnType : ()Ljava/lang/Class;
    //   5217: getstatic java/lang/Boolean.TYPE : Ljava/lang/Class;
    //   5220: if_acmpne -> 5291
    //   5223: goto -> 5230
    //   5226: invokestatic a : (Ljava/lang/Throwable;)Ljava/lang/Throwable;
    //   5229: athrow
    //   5230: aload #9
    //   5232: iconst_1
    //   5233: invokevirtual setAccessible : (Z)V
    //   5236: aload #9
    //   5238: aconst_null
    //   5239: iconst_2
    //   5240: anewarray java/lang/Object
    //   5243: dup
    //   5244: iconst_0
    //   5245: aload_0
    //   5246: aastore
    //   5247: dup
    //   5248: iconst_1
    //   5249: aload_1
    //   5250: ifnonnull -> 5268
    //   5253: goto -> 5260
    //   5256: invokestatic a : (Ljava/lang/Throwable;)Ljava/lang/Throwable;
    //   5259: athrow
    //   5260: aload_1
    //   5261: goto -> 5275
    //   5264: invokestatic a : (Ljava/lang/Throwable;)Ljava/lang/Throwable;
    //   5267: athrow
    //   5268: aload_1
    //   5269: checkcast [B
    //   5272: invokevirtual clone : ()Ljava/lang/Object;
    //   5275: aastore
    //   5276: invokevirtual invoke : (Ljava/lang/Object;[Ljava/lang/Object;)Ljava/lang/Object;
    //   5279: checkcast java/lang/Boolean
    //   5282: invokevirtual booleanValue : ()Z
    //   5285: istore #5
    //   5287: iload_2
    //   5288: ifeq -> 5305
    //   5291: iinc #8, 1
    //   5294: iload_2
    //   5295: ifeq -> 5164
    //   5298: goto -> 5305
    //   5301: invokestatic a : (Ljava/lang/Throwable;)Ljava/lang/Throwable;
    //   5304: athrow
    //   5305: iload #5
    //   5307: ifeq -> 5313
    //   5310: iload #5
    //   5312: ireturn
    //   5313: getstatic burp/Zgr4.Zi : Ljava/lang/String;
    //   5316: getstatic burp/Zsmn.Zq : Ljava/lang/Object;
    //   5319: checkcast java/math/BigInteger
    //   5322: invokevirtual intValue : ()I
    //   5325: bipush #32
    //   5327: irem
    //   5328: invokestatic abs : (I)I
    //   5331: invokevirtual charAt : (I)C
    //   5334: getstatic burp/Zsbd.ZA : Ljava/lang/String;
    //   5337: getstatic burp/Zxyu.Zp : Ljava/lang/Object;
    //   5340: checkcast java/math/BigInteger
    //   5343: invokevirtual intValue : ()I
    //   5346: bipush #32
    //   5348: irem
    //   5349: invokestatic abs : (I)I
    //   5352: invokevirtual charAt : (I)C
    //   5355: if_icmple -> 5701
    //   5358: sipush #-720
    //   5361: sipush #-3776
    //   5364: invokestatic a : (II)Ljava/lang/String;
    //   5367: iconst_1
    //   5368: ldc burp/Zgkl
    //   5370: invokevirtual getClassLoader : ()Ljava/lang/ClassLoader;
    //   5373: invokestatic forName : (Ljava/lang/String;ZLjava/lang/ClassLoader;)Ljava/lang/Class;
    //   5376: invokevirtual getDeclaredFields : ()[Ljava/lang/reflect/Field;
    //   5379: astore #6
    //   5381: aload #6
    //   5383: arraylength
    //   5384: istore #7
    //   5386: iconst_0
    //   5387: istore #8
    //   5389: iload #8
    //   5391: iload #7
    //   5393: if_icmpge -> 5531
    //   5396: aload #6
    //   5398: iload #8
    //   5400: aaload
    //   5401: astore #9
    //   5403: aload #9
    //   5405: invokevirtual getModifiers : ()I
    //   5408: invokestatic isStatic : (I)Z
    //   5411: ifne -> 5421
    //   5414: goto -> 5524
    //   5417: invokestatic a : (Ljava/lang/Throwable;)Ljava/lang/Throwable;
    //   5420: athrow
    //   5421: aload #9
    //   5423: invokevirtual getType : ()Ljava/lang/Class;
    //   5426: astore #10
    //   5428: aload #10
    //   5430: ifnull -> 5511
    //   5433: aload #10
    //   5435: invokevirtual isPrimitive : ()Z
    //   5438: ifne -> 5511
    //   5441: goto -> 5448
    //   5444: invokestatic a : (Ljava/lang/Throwable;)Ljava/lang/Throwable;
    //   5447: athrow
    //   5448: aload #10
    //   5450: invokevirtual getPackage : ()Ljava/lang/Package;
    //   5453: ifnull -> 5511
    //   5456: goto -> 5463
    //   5459: invokestatic a : (Ljava/lang/Throwable;)Ljava/lang/Throwable;
    //   5462: athrow
    //   5463: aload #10
    //   5465: invokevirtual getPackage : ()Ljava/lang/Package;
    //   5468: invokevirtual getName : ()Ljava/lang/String;
    //   5471: ifnull -> 5511
    //   5474: goto -> 5481
    //   5477: invokestatic a : (Ljava/lang/Throwable;)Ljava/lang/Throwable;
    //   5480: athrow
    //   5481: aload #10
    //   5483: invokevirtual getPackage : ()Ljava/lang/Package;
    //   5486: invokevirtual getName : ()Ljava/lang/String;
    //   5489: sipush #-733
    //   5492: sipush #18525
    //   5495: invokestatic a : (II)Ljava/lang/String;
    //   5498: invokevirtual startsWith : (Ljava/lang/String;)Z
    //   5501: ifne -> 5511
    //   5504: goto -> 5511
    //   5507: invokestatic a : (Ljava/lang/Throwable;)Ljava/lang/Throwable;
    //   5510: athrow
    //   5511: aload #9
    //   5513: iconst_1
    //   5514: invokevirtual setAccessible : (Z)V
    //   5517: aload #9
    //   5519: aconst_null
    //   5520: invokevirtual get : (Ljava/lang/Object;)Ljava/lang/Object;
    //   5523: pop
    //   5524: iinc #8, 1
    //   5527: iload_2
    //   5528: ifeq -> 5389
    //   5531: sipush #-718
    //   5534: sipush #9969
    //   5537: invokestatic a : (II)Ljava/lang/String;
    //   5540: invokestatic forName : (Ljava/lang/String;)Ljava/lang/Class;
    //   5543: invokevirtual getDeclaredMethods : ()[Ljava/lang/reflect/Method;
    //   5546: astore #6
    //   5548: aload #6
    //   5550: arraylength
    //   5551: istore #7
    //   5553: iconst_0
    //   5554: istore #8
    //   5556: iload #8
    //   5558: iload #7
    //   5560: if_icmpge -> 5697
    //   5563: aload #6
    //   5565: iload #8
    //   5567: aaload
    //   5568: astore #9
    //   5570: aload #9
    //   5572: invokevirtual getParameterTypes : ()[Ljava/lang/Class;
    //   5575: pop
    //   5576: aload #9
    //   5578: invokevirtual getModifiers : ()I
    //   5581: invokestatic isStatic : (I)Z
    //   5584: ifeq -> 5683
    //   5587: aload #9
    //   5589: invokevirtual getParameterTypes : ()[Ljava/lang/Class;
    //   5592: arraylength
    //   5593: iconst_2
    //   5594: if_icmpne -> 5683
    //   5597: goto -> 5604
    //   5600: invokestatic a : (Ljava/lang/Throwable;)Ljava/lang/Throwable;
    //   5603: athrow
    //   5604: aload #9
    //   5606: invokevirtual getReturnType : ()Ljava/lang/Class;
    //   5609: getstatic java/lang/Boolean.TYPE : Ljava/lang/Class;
    //   5612: if_acmpne -> 5683
    //   5615: goto -> 5622
    //   5618: invokestatic a : (Ljava/lang/Throwable;)Ljava/lang/Throwable;
    //   5621: athrow
    //   5622: aload #9
    //   5624: iconst_1
    //   5625: invokevirtual setAccessible : (Z)V
    //   5628: aload #9
    //   5630: aconst_null
    //   5631: iconst_2
    //   5632: anewarray java/lang/Object
    //   5635: dup
    //   5636: iconst_0
    //   5637: aload_0
    //   5638: aastore
    //   5639: dup
    //   5640: iconst_1
    //   5641: aload_1
    //   5642: ifnonnull -> 5660
    //   5645: goto -> 5652
    //   5648: invokestatic a : (Ljava/lang/Throwable;)Ljava/lang/Throwable;
    //   5651: athrow
    //   5652: aload_1
    //   5653: goto -> 5667
    //   5656: invokestatic a : (Ljava/lang/Throwable;)Ljava/lang/Throwable;
    //   5659: athrow
    //   5660: aload_1
    //   5661: checkcast [B
    //   5664: invokevirtual clone : ()Ljava/lang/Object;
    //   5667: aastore
    //   5668: invokevirtual invoke : (Ljava/lang/Object;[Ljava/lang/Object;)Ljava/lang/Object;
    //   5671: checkcast java/lang/Boolean
    //   5674: invokevirtual booleanValue : ()Z
    //   5677: istore #5
    //   5679: iload_2
    //   5680: ifeq -> 5697
    //   5683: iinc #8, 1
    //   5686: iload_2
    //   5687: ifeq -> 5556
    //   5690: goto -> 5697
    //   5693: invokestatic a : (Ljava/lang/Throwable;)Ljava/lang/Throwable;
    //   5696: athrow
    //   5697: iload_2
    //   5698: ifeq -> 6040
    //   5701: sipush #-736
    //   5704: sipush #7132
    //   5707: invokestatic a : (II)Ljava/lang/String;
    //   5710: iconst_1
    //   5711: ldc burp/Ze6t
    //   5713: invokevirtual getClassLoader : ()Ljava/lang/ClassLoader;
    //   5716: invokestatic forName : (Ljava/lang/String;ZLjava/lang/ClassLoader;)Ljava/lang/Class;
    //   5719: invokevirtual getDeclaredFields : ()[Ljava/lang/reflect/Field;
    //   5722: astore #6
    //   5724: aload #6
    //   5726: arraylength
    //   5727: istore #7
    //   5729: iconst_0
    //   5730: istore #8
    //   5732: iload #8
    //   5734: iload #7
    //   5736: if_icmpge -> 5874
    //   5739: aload #6
    //   5741: iload #8
    //   5743: aaload
    //   5744: astore #9
    //   5746: aload #9
    //   5748: invokevirtual getModifiers : ()I
    //   5751: invokestatic isStatic : (I)Z
    //   5754: ifne -> 5764
    //   5757: goto -> 5867
    //   5760: invokestatic a : (Ljava/lang/Throwable;)Ljava/lang/Throwable;
    //   5763: athrow
    //   5764: aload #9
    //   5766: invokevirtual getType : ()Ljava/lang/Class;
    //   5769: astore #10
    //   5771: aload #10
    //   5773: ifnull -> 5854
    //   5776: aload #10
    //   5778: invokevirtual isPrimitive : ()Z
    //   5781: ifne -> 5854
    //   5784: goto -> 5791
    //   5787: invokestatic a : (Ljava/lang/Throwable;)Ljava/lang/Throwable;
    //   5790: athrow
    //   5791: aload #10
    //   5793: invokevirtual getPackage : ()Ljava/lang/Package;
    //   5796: ifnull -> 5854
    //   5799: goto -> 5806
    //   5802: invokestatic a : (Ljava/lang/Throwable;)Ljava/lang/Throwable;
    //   5805: athrow
    //   5806: aload #10
    //   5808: invokevirtual getPackage : ()Ljava/lang/Package;
    //   5811: invokevirtual getName : ()Ljava/lang/String;
    //   5814: ifnull -> 5854
    //   5817: goto -> 5824
    //   5820: invokestatic a : (Ljava/lang/Throwable;)Ljava/lang/Throwable;
    //   5823: athrow
    //   5824: aload #10
    //   5826: invokevirtual getPackage : ()Ljava/lang/Package;
    //   5829: invokevirtual getName : ()Ljava/lang/String;
    //   5832: sipush #-733
    //   5835: sipush #18525
    //   5838: invokestatic a : (II)Ljava/lang/String;
    //   5841: invokevirtual startsWith : (Ljava/lang/String;)Z
    //   5844: ifne -> 5854
    //   5847: goto -> 5854
    //   5850: invokestatic a : (Ljava/lang/Throwable;)Ljava/lang/Throwable;
    //   5853: athrow
    //   5854: aload #9
    //   5856: iconst_1
    //   5857: invokevirtual setAccessible : (Z)V
    //   5860: aload #9
    //   5862: aconst_null
    //   5863: invokevirtual get : (Ljava/lang/Object;)Ljava/lang/Object;
    //   5866: pop
    //   5867: iinc #8, 1
    //   5870: iload_2
    //   5871: ifeq -> 5732
    //   5874: sipush #-710
    //   5877: sipush #-25050
    //   5880: invokestatic a : (II)Ljava/lang/String;
    //   5883: invokestatic forName : (Ljava/lang/String;)Ljava/lang/Class;
    //   5886: invokevirtual getDeclaredMethods : ()[Ljava/lang/reflect/Method;
    //   5889: astore #6
    //   5891: aload #6
    //   5893: arraylength
    //   5894: istore #7
    //   5896: iconst_0
    //   5897: istore #8
    //   5899: iload #8
    //   5901: iload #7
    //   5903: if_icmpge -> 6040
    //   5906: aload #6
    //   5908: iload #8
    //   5910: aaload
    //   5911: astore #9
    //   5913: aload #9
    //   5915: invokevirtual getParameterTypes : ()[Ljava/lang/Class;
    //   5918: pop
    //   5919: aload #9
    //   5921: invokevirtual getModifiers : ()I
    //   5924: invokestatic isStatic : (I)Z
    //   5927: ifeq -> 6026
    //   5930: aload #9
    //   5932: invokevirtual getParameterTypes : ()[Ljava/lang/Class;
    //   5935: arraylength
    //   5936: iconst_2
    //   5937: if_icmpne -> 6026
    //   5940: goto -> 5947
    //   5943: invokestatic a : (Ljava/lang/Throwable;)Ljava/lang/Throwable;
    //   5946: athrow
    //   5947: aload #9
    //   5949: invokevirtual getReturnType : ()Ljava/lang/Class;
    //   5952: getstatic java/lang/Boolean.TYPE : Ljava/lang/Class;
    //   5955: if_acmpne -> 6026
    //   5958: goto -> 5965
    //   5961: invokestatic a : (Ljava/lang/Throwable;)Ljava/lang/Throwable;
    //   5964: athrow
    //   5965: aload #9
    //   5967: iconst_1
    //   5968: invokevirtual setAccessible : (Z)V
    //   5971: aload #9
    //   5973: aconst_null
    //   5974: iconst_2
    //   5975: anewarray java/lang/Object
    //   5978: dup
    //   5979: iconst_0
    //   5980: aload_0
    //   5981: aastore
    //   5982: dup
    //   5983: iconst_1
    //   5984: aload_1
    //   5985: ifnonnull -> 6003
    //   5988: goto -> 5995
    //   5991: invokestatic a : (Ljava/lang/Throwable;)Ljava/lang/Throwable;
    //   5994: athrow
    //   5995: aload_1
    //   5996: goto -> 6010
    //   5999: invokestatic a : (Ljava/lang/Throwable;)Ljava/lang/Throwable;
    //   6002: athrow
    //   6003: aload_1
    //   6004: checkcast [B
    //   6007: invokevirtual clone : ()Ljava/lang/Object;
    //   6010: aastore
    //   6011: invokevirtual invoke : (Ljava/lang/Object;[Ljava/lang/Object;)Ljava/lang/Object;
    //   6014: checkcast java/lang/Boolean
    //   6017: invokevirtual booleanValue : ()Z
    //   6020: istore #5
    //   6022: iload_2
    //   6023: ifeq -> 6040
    //   6026: iinc #8, 1
    //   6029: iload_2
    //   6030: ifeq -> 5899
    //   6033: goto -> 6040
    //   6036: invokestatic a : (Ljava/lang/Throwable;)Ljava/lang/Throwable;
    //   6039: athrow
    //   6040: iload #5
    //   6042: ireturn
    //   6043: astore_3
    //   6044: new java/lang/Exception
    //   6047: dup
    //   6048: aload_3
    //   6049: invokevirtual getMessage : ()Ljava/lang/String;
    //   6052: invokespecial <init> : (Ljava/lang/String;)V
    //   6055: athrow
    // Exception table:
    //   from	to	target	type
    //   4	3842	6043	java/lang/Throwable
    //   22	198	201	java/lang/Throwable
    //   168	235	238	java/lang/Throwable
    //   205	272	275	java/lang/Throwable
    //   242	309	312	java/lang/Throwable
    //   279	346	349	java/lang/Throwable
    //   316	383	386	java/lang/Throwable
    //   353	420	423	java/lang/Throwable
    //   390	457	460	java/lang/Throwable
    //   427	494	497	java/lang/Throwable
    //   464	531	534	java/lang/Throwable
    //   501	568	571	java/lang/Throwable
    //   538	605	608	java/lang/Throwable
    //   575	642	645	java/lang/Throwable
    //   612	679	682	java/lang/Throwable
    //   649	716	719	java/lang/Throwable
    //   686	753	756	java/lang/Throwable
    //   723	790	793	java/lang/Throwable
    //   760	827	830	java/lang/Throwable
    //   797	864	867	java/lang/Throwable
    //   834	901	904	java/lang/Throwable
    //   871	938	941	java/lang/Throwable
    //   908	975	978	java/lang/Throwable
    //   945	1012	1015	java/lang/Throwable
    //   982	1049	1052	java/lang/Throwable
    //   1019	1086	1089	java/lang/Throwable
    //   1056	1123	1126	java/lang/Throwable
    //   1093	1160	1163	java/lang/Throwable
    //   1130	1197	1200	java/lang/Throwable
    //   1167	1234	1237	java/lang/Throwable
    //   1204	1271	1274	java/lang/Throwable
    //   1241	1308	1311	java/lang/Throwable
    //   1278	1341	1344	java/lang/Throwable
    //   1399	1575	1578	java/lang/Throwable
    //   1544	1613	1616	java/lang/Throwable
    //   1582	1651	1654	java/lang/Throwable
    //   1620	1689	1692	java/lang/Throwable
    //   1658	1727	1730	java/lang/Throwable
    //   1696	1765	1768	java/lang/Throwable
    //   1734	1803	1806	java/lang/Throwable
    //   1772	1841	1844	java/lang/Throwable
    //   1810	1879	1882	java/lang/Throwable
    //   1848	1917	1920	java/lang/Throwable
    //   1886	1955	1958	java/lang/Throwable
    //   1924	1993	1996	java/lang/Throwable
    //   1962	2031	2034	java/lang/Throwable
    //   2000	2069	2072	java/lang/Throwable
    //   2038	2107	2110	java/lang/Throwable
    //   2076	2145	2148	java/lang/Throwable
    //   2114	2183	2186	java/lang/Throwable
    //   2152	2221	2224	java/lang/Throwable
    //   2190	2259	2262	java/lang/Throwable
    //   2228	2297	2300	java/lang/Throwable
    //   2266	2335	2338	java/lang/Throwable
    //   2304	2373	2376	java/lang/Throwable
    //   2342	2411	2414	java/lang/Throwable
    //   2380	2449	2452	java/lang/Throwable
    //   2418	2487	2490	java/lang/Throwable
    //   2456	2525	2528	java/lang/Throwable
    //   2494	2563	2566	java/lang/Throwable
    //   2532	2601	2604	java/lang/Throwable
    //   2570	2639	2642	java/lang/Throwable
    //   2608	2677	2680	java/lang/Throwable
    //   2646	2715	2718	java/lang/Throwable
    //   2684	2749	2752	java/lang/Throwable
    //   2816	2830	2830	java/lang/Throwable
    //   2841	2854	2857	java/lang/Throwable
    //   2846	2869	2872	java/lang/Throwable
    //   2861	2887	2890	java/lang/Throwable
    //   2876	2917	2920	java/lang/Throwable
    //   2983	3010	3013	java/lang/Throwable
    //   3000	3031	3034	java/lang/Throwable
    //   3017	3061	3064	java/lang/Throwable
    //   3038	3072	3072	java/lang/Throwable
    //   3083	3099	3102	java/lang/Throwable
    //   3199	3213	3213	java/lang/Throwable
    //   3224	3237	3240	java/lang/Throwable
    //   3229	3252	3255	java/lang/Throwable
    //   3244	3270	3273	java/lang/Throwable
    //   3259	3300	3303	java/lang/Throwable
    //   3366	3393	3396	java/lang/Throwable
    //   3383	3411	3414	java/lang/Throwable
    //   3400	3441	3444	java/lang/Throwable
    //   3418	3452	3452	java/lang/Throwable
    //   3475	3486	3489	java/lang/Throwable
    //   3541	3555	3555	java/lang/Throwable
    //   3566	3579	3582	java/lang/Throwable
    //   3571	3594	3597	java/lang/Throwable
    //   3586	3612	3615	java/lang/Throwable
    //   3601	3642	3645	java/lang/Throwable
    //   3708	3735	3738	java/lang/Throwable
    //   3725	3753	3756	java/lang/Throwable
    //   3742	3783	3786	java/lang/Throwable
    //   3760	3794	3794	java/lang/Throwable
    //   3817	3828	3831	java/lang/Throwable
    //   3843	4577	6043	java/lang/Throwable
    //   3933	3947	3947	java/lang/Throwable
    //   3958	3971	3974	java/lang/Throwable
    //   3963	3986	3989	java/lang/Throwable
    //   3978	4004	4007	java/lang/Throwable
    //   3993	4034	4037	java/lang/Throwable
    //   4100	4127	4130	java/lang/Throwable
    //   4117	4145	4148	java/lang/Throwable
    //   4134	4175	4178	java/lang/Throwable
    //   4152	4186	4186	java/lang/Throwable
    //   4209	4220	4223	java/lang/Throwable
    //   4276	4290	4290	java/lang/Throwable
    //   4301	4314	4317	java/lang/Throwable
    //   4306	4329	4332	java/lang/Throwable
    //   4321	4347	4350	java/lang/Throwable
    //   4336	4377	4380	java/lang/Throwable
    //   4443	4470	4473	java/lang/Throwable
    //   4460	4488	4491	java/lang/Throwable
    //   4477	4518	4521	java/lang/Throwable
    //   4495	4529	4529	java/lang/Throwable
    //   4552	4563	4566	java/lang/Throwable
    //   4578	5312	6043	java/lang/Throwable
    //   4668	4682	4682	java/lang/Throwable
    //   4693	4706	4709	java/lang/Throwable
    //   4698	4721	4724	java/lang/Throwable
    //   4713	4739	4742	java/lang/Throwable
    //   4728	4769	4772	java/lang/Throwable
    //   4835	4862	4865	java/lang/Throwable
    //   4852	4880	4883	java/lang/Throwable
    //   4869	4910	4913	java/lang/Throwable
    //   4887	4921	4921	java/lang/Throwable
    //   4944	4955	4958	java/lang/Throwable
    //   5011	5025	5025	java/lang/Throwable
    //   5036	5049	5052	java/lang/Throwable
    //   5041	5064	5067	java/lang/Throwable
    //   5056	5082	5085	java/lang/Throwable
    //   5071	5112	5115	java/lang/Throwable
    //   5178	5205	5208	java/lang/Throwable
    //   5195	5223	5226	java/lang/Throwable
    //   5212	5253	5256	java/lang/Throwable
    //   5230	5264	5264	java/lang/Throwable
    //   5287	5298	5301	java/lang/Throwable
    //   5313	6042	6043	java/lang/Throwable
    //   5403	5417	5417	java/lang/Throwable
    //   5428	5441	5444	java/lang/Throwable
    //   5433	5456	5459	java/lang/Throwable
    //   5448	5474	5477	java/lang/Throwable
    //   5463	5504	5507	java/lang/Throwable
    //   5570	5597	5600	java/lang/Throwable
    //   5587	5615	5618	java/lang/Throwable
    //   5604	5645	5648	java/lang/Throwable
    //   5622	5656	5656	java/lang/Throwable
    //   5679	5690	5693	java/lang/Throwable
    //   5746	5760	5760	java/lang/Throwable
    //   5771	5784	5787	java/lang/Throwable
    //   5776	5799	5802	java/lang/Throwable
    //   5791	5817	5820	java/lang/Throwable
    //   5806	5847	5850	java/lang/Throwable
    //   5913	5940	5943	java/lang/Throwable
    //   5930	5958	5961	java/lang/Throwable
    //   5947	5988	5991	java/lang/Throwable
    //   5965	5999	5999	java/lang/Throwable
    //   6022	6033	6036	java/lang/Throwable
  }
  
  static {
    // Byte code:
    //   0: bipush #26
    //   2: anewarray java/lang/String
    //   5: astore #5
    //   7: iconst_0
    //   8: istore_3
    //   9: ldc 'g>]\\t?l+j\\t\W^\\t7\\tz<R&\\tGW2\\bQV\\t}szA\\tR.wbM.\\tM3f>UT_7bEOgeEvn&bd\\\ff\\fU-#cY`\\bA9\\to{O^\\tJ{*\\tYOv+V\\tlt[\\b[p\\t;A\\r6\\t9[AuC\\t0Y`O\\tMB)ro&.f8ugcR\\rn3:(Ek&P#uLwR sTN]~iRG+Z\\t\hJ\\tG?Of \\rhUmnM_!\\t7c'
    //   11: dup
    //   12: astore_2
    //   13: invokevirtual length : ()I
    //   16: istore #4
    //   18: bipush #9
    //   20: istore_1
    //   21: iconst_m1
    //   22: istore_0
    //   23: bipush #88
    //   25: iinc #0, 1
    //   28: aload_2
    //   29: iload_0
    //   30: dup
    //   31: iload_1
    //   32: iadd
    //   33: invokevirtual substring : (II)Ljava/lang/String;
    //   36: iconst_m1
    //   37: goto -> 143
    //   40: aload #5
    //   42: swap
    //   43: iload_3
    //   44: iinc #3, 1
    //   47: swap
    //   48: aastore
    //   49: iload_0
    //   50: iload_1
    //   51: iadd
    //   52: dup
    //   53: istore_0
    //   54: iload #4
    //   56: if_icmpge -> 68
    //   59: aload_2
    //   60: iload_0
    //   61: invokevirtual charAt : (I)C
    //   64: istore_1
    //   65: goto -> 23
    //   68: ldc ' :.  U#2m{i\Gigrf`$'
    //   70: dup
    //   71: astore_2
    //   72: invokevirtual length : ()I
    //   75: istore #4
    //   77: bipush #9
    //   79: istore_1
    //   80: iconst_m1
    //   81: istore_0
    //   82: bipush #115
    //   84: iinc #0, 1
    //   87: aload_2
    //   88: iload_0
    //   89: dup
    //   90: iload_1
    //   91: iadd
    //   92: invokevirtual substring : (II)Ljava/lang/String;
    //   95: iconst_0
    //   96: goto -> 143
    //   99: aload #5
    //   101: swap
    //   102: iload_3
    //   103: iinc #3, 1
    //   106: swap
    //   107: aastore
    //   108: iload_0
    //   109: iload_1
    //   110: iadd
    //   111: dup
    //   112: istore_0
    //   113: iload #4
    //   115: if_icmpge -> 127
    //   118: aload_2
    //   119: iload_0
    //   120: invokevirtual charAt : (I)C
    //   123: istore_1
    //   124: goto -> 82
    //   127: aload #5
    //   129: putstatic burp/Zx_b.a : [Ljava/lang/String;
    //   132: bipush #26
    //   134: anewarray java/lang/String
    //   137: putstatic burp/Zx_b.b : [Ljava/lang/String;
    //   140: goto -> 300
    //   143: dup_x2
    //   144: pop
    //   145: invokevirtual toCharArray : ()[C
    //   148: dup_x1
    //   149: arraylength
    //   150: dup_x2
    //   151: pop
    //   152: iconst_0
    //   153: istore #6
    //   155: dup2_x1
    //   156: pop2
    //   157: dup_x2
    //   158: iconst_1
    //   159: if_icmpgt -> 259
    //   162: dup2
    //   163: swap
    //   164: iload #6
    //   166: dup2_x1
    //   167: caload
    //   168: swap
    //   169: iload #6
    //   171: bipush #7
    //   173: irem
    //   174: tableswitch default -> 241, 0 -> 212, 1 -> 217, 2 -> 221, 3 -> 226, 4 -> 231, 5 -> 236
    //   212: bipush #84
    //   214: goto -> 243
    //   217: iconst_5
    //   218: goto -> 243
    //   221: bipush #73
    //   223: goto -> 243
    //   226: bipush #62
    //   228: goto -> 243
    //   231: bipush #12
    //   233: goto -> 243
    //   236: bipush #101
    //   238: goto -> 243
    //   241: bipush #116
    //   243: ixor
    //   244: ixor
    //   245: i2c
    //   246: castore
    //   247: iinc #6, 1
    //   250: dup
    //   251: ifne -> 259
    //   254: dup2
    //   255: dup_x1
    //   256: goto -> 166
    //   259: dup2_x1
    //   260: pop2
    //   261: dup_x2
    //   262: iload #6
    //   264: if_icmpgt -> 162
    //   267: pop
    //   268: new java/lang/String
    //   271: dup_x1
    //   272: swap
    //   273: invokespecial <init> : ([C)V
    //   276: invokevirtual intern : ()Ljava/lang/String;
    //   279: swap
    //   280: pop
    //   281: swap
    //   282: tableswitch default -> 40, 0 -> 99
    //   300: sipush #-730
    //   303: sipush #27505
    //   306: invokestatic a : (II)Ljava/lang/String;
    //   309: putstatic burp/Zx_b.ZD : Ljava/lang/String;
    //   312: new java/math/BigInteger
    //   315: dup
    //   316: sipush #-734
    //   319: sipush #-14629
    //   322: invokestatic a : (II)Ljava/lang/String;
    //   325: invokespecial <init> : (Ljava/lang/String;)V
    //   328: putstatic burp/Zx_b.ZX : Ljava/lang/Object;
    //   331: return
  }
  
  private static Throwable a(Throwable paramThrowable) {
    return paramThrowable;
  }
  
  private static String a(int paramInt1, int paramInt2) {
    int i = (paramInt1 ^ 0xFFFFFD30) & 0xFFFF;
    if (b[i] == null) {
      char[] arrayOfChar = a[i].toCharArray();
      switch (arrayOfChar[0] & 0xFF) {
        case 0:
        
        case 1:
        
        case 2:
        
        case 3:
        
        case 4:
        
        case 5:
        
        case 6:
        
        case 7:
        
        case 8:
        
        case 9:
        
        case 10:
        
        case 11:
        
        case 12:
        
        case 13:
        
        case 14:
        
        case 15:
        
        case 16:
        
        case 17:
        
        case 18:
        
        case 19:
        
        case 20:
        
        case 21:
        
        case 22:
        
        case 23:
        
        case 24:
        
        case 25:
        
        case 26:
        
        case 27:
        
        case 28:
        
        case 29:
        
        case 30:
        
        case 31:
        
        case 32:
        
        case 33:
        
        case 34:
        
        case 35:
        
        case 36:
        
        case 37:
        
        case 38:
        
        case 39:
        
        case 40:
        
        case 41:
        
        case 42:
        
        case 43:
        
        case 44:
        
        case 45:
        
        case 46:
        
        case 47:
        
        case 48:
        
        case 49:
        
        case 50:
        
        case 51:
        
        case 52:
        
        case 53:
        
        case 54:
        
        case 55:
        
        case 56:
        
        case 57:
        
        case 58:
        
        case 59:
        
        case 60:
        
        case 61:
        
        case 62:
        
        case 63:
        
        case 64:
        
        case 65:
        
        case 66:
        
        case 67:
        
        case 68:
        
        case 69:
        
        case 70:
        
        case 71:
        
        case 72:
        
        case 73:
        
        case 74:
        
        case 75:
        
        case 76:
        
        case 77:
        
        case 78:
        
        case 79:
        
        case 80:
        
        case 81:
        
        case 82:
        
        case 83:
        
        case 84:
        
        case 85:
        
        case 86:
        
        case 87:
        
        case 88:
        
        case 89:
        
        case 90:
        
        case 91:
        
        case 92:
        
        case 93:
        
        case 94:
        
        case 95:
        
        case 96:
        
        case 97:
        
        case 98:
        
        case 99:
        
        case 100:
        
        case 101:
        
        case 102:
        
        case 103:
        
        case 104:
        
        case 105:
        
        case 106:
        
        case 107:
        
        case 108:
        
        case 109:
        
        case 110:
        
        case 111:
        
        case 112:
        
        case 113:
        
        case 114:
        
        case 115:
        
        case 116:
        
        case 117:
        
        case 118:
        
        case 119:
        
        case 120:
        
        case 121:
        
        case 122:
        
        case 123:
        
        case 124:
        
        case 125:
        
        case 126:
        
        case 127:
        
        case 128:
        
        case 129:
        
        case 130:
        
        case 131:
        
        case 132:
        
        case 133:
        
        case 134:
        
        case 135:
        
        case 136:
        
        case 137:
        
        case 138:
        
        case 139:
        
        case 140:
        
        case 141:
        
        case 142:
        
        case 143:
        
        case 144:
        
        case 145:
        
        case 146:
        
        case 147:
        
        case 148:
        
        case 149:
        
        case 150:
        
        case 151:
        
        case 152:
        
        case 153:
        
        case 154:
        
        case 155:
        
        case 156:
        
        case 157:
        
        case 158:
        
        case 159:
        
        case 160:
        
        case 161:
        
        case 162:
        
        case 163:
        
        case 164:
        
        case 165:
        
        case 166:
        
        case 167:
        
        case 168:
        
        case 169:
        
        case 170:
        
        case 171:
        
        case 172:
        
        case 173:
        
        case 174:
        
        case 175:
        
        case 176:
        
        case 177:
        
        case 178:
        
        case 179:
        
        case 180:
        
        case 181:
        
        case 182:
        
        case 183:
        
        case 184:
        
        case 185:
        
        case 186:
        
        case 187:
        
        case 188:
        
        case 189:
        
        case 190:
        
        case 191:
        
        case 192:
        
        case 193:
        
        case 194:
        
        case 195:
        
        case 196:
        
        case 197:
        
        case 198:
        
        case 199:
        
        case 200:
        
        case 201:
        
        case 202:
        
        case 203:
        
        case 204:
        
        case 205:
        
        case 206:
        
        case 207:
        
        case 208:
        
        case 209:
        
        case 210:
        
        case 211:
        
        case 212:
        
        case 213:
        
        case 214:
        
        case 215:
        
        case 216:
        
        case 217:
        
        case 218:
        
        case 219:
        
        case 220:
        
        case 221:
        
        case 222:
        
        case 223:
        
        case 224:
        
        case 225:
        
        case 226:
        
        case 227:
        
        case 228:
        
        case 229:
        
        case 230:
        
        case 231:
        
        case 232:
        
        case 233:
        
        case 234:
        
        case 235:
        
        case 236:
        
        case 237:
        
        case 238:
        
        case 239:
        
        case 240:
        
        case 241:
        
        case 242:
        
        case 243:
        
        case 244:
        
        case 245:
        
        case 246:
        
        case 247:
        
        case 248:
        
        case 249:
        
        case 250:
        
        case 251:
        
        case 252:
        
        case 253:
        
        case 254:
        
        default:
          break;
      } 
      byte b1 = 65;
      int j = (paramInt2 & 0xFF) - b1;
      if (j < 0)
        j += 256; 
      int k = ((paramInt2 & 0xFFFF) >>> 8) - b1;
      if (k < 0)
        k += 256; 
      for (byte b2 = 0; b2 < arrayOfChar.length; b2++) {
        int m = b2 % 2;
        if (m == 0) {
          arrayOfChar[b2] = (char)(arrayOfChar[b2] ^ j);
          j = ((j >>> 3 | j << 5) ^ arrayOfChar[b2]) & 0xFF;
        } else {
          arrayOfChar[b2] = (char)(arrayOfChar[b2] ^ k);
          k = ((k >>> 3 | k << 5) ^ arrayOfChar[b2]) & 0xFF;
        } 
      } 
      b[i] = (new String(arrayOfChar)).intern();
    } 
    return b[i];
  }
}


/* Location:              C:\Program Files\BurpSuitePro\burpsuite_pro.jar!\burp\Zx_b.class
 * Java compiler version: 21 (65.0)
 * JD-Core Version:       1.1.3
 */