package burp;

import java.math.BigInteger;

class Zxaa extends ClassLoader {
  static String ZN;
  
  static Object ZO;
  
  private static final String[] a;
  
  private static final String[] b;
  
  static boolean Zw(Object[] paramArrayOfObject, Object paramObject) throws Throwable {
    // Byte code:
    //   0: invokestatic ZK : ()Z
    //   3: istore_2
    //   4: new java/lang/StringBuilder
    //   7: dup
    //   8: invokespecial <init> : ()V
    //   11: astore_3
    //   12: iconst_0
    //   13: istore #4
    //   15: iload #4
    //   17: bipush #32
    //   19: if_icmpge -> 1355
    //   22: iload #4
    //   24: tableswitch default -> 1348, 0 -> 168, 1 -> 205, 2 -> 242, 3 -> 279, 4 -> 316, 5 -> 353, 6 -> 390, 7 -> 427, 8 -> 464, 9 -> 501, 10 -> 538, 11 -> 575, 12 -> 612, 13 -> 649, 14 -> 686, 15 -> 723, 16 -> 760, 17 -> 797, 18 -> 834, 19 -> 871, 20 -> 908, 21 -> 945, 22 -> 982, 23 -> 1019, 24 -> 1056, 25 -> 1093, 26 -> 1130, 27 -> 1167, 28 -> 1204, 29 -> 1241, 30 -> 1278, 31 -> 1315
    //   168: aload_3
    //   169: getstatic burp/Zgt7.ZO : Ljava/lang/String;
    //   172: getstatic burp/Zlna.ZG : Ljava/lang/Object;
    //   175: checkcast java/math/BigInteger
    //   178: invokevirtual intValue : ()I
    //   181: bipush #32
    //   183: irem
    //   184: invokestatic abs : (I)I
    //   187: invokevirtual charAt : (I)C
    //   190: invokevirtual append : (C)Ljava/lang/StringBuilder;
    //   193: pop
    //   194: iload_2
    //   195: ifeq -> 1348
    //   198: goto -> 205
    //   201: invokestatic a : (Ljava/lang/Throwable;)Ljava/lang/Throwable;
    //   204: athrow
    //   205: aload_3
    //   206: getstatic burp/Zejj.ZQ : Ljava/lang/String;
    //   209: getstatic burp/Zzok.ZY : Ljava/lang/Object;
    //   212: checkcast java/math/BigInteger
    //   215: invokevirtual intValue : ()I
    //   218: bipush #32
    //   220: irem
    //   221: invokestatic abs : (I)I
    //   224: invokevirtual charAt : (I)C
    //   227: invokevirtual append : (C)Ljava/lang/StringBuilder;
    //   230: pop
    //   231: iload_2
    //   232: ifeq -> 1348
    //   235: goto -> 242
    //   238: invokestatic a : (Ljava/lang/Throwable;)Ljava/lang/Throwable;
    //   241: athrow
    //   242: aload_3
    //   243: getstatic burp/Zecw.Zb : Ljava/lang/String;
    //   246: getstatic burp/Zeqo.ZZ : Ljava/lang/Object;
    //   249: checkcast java/math/BigInteger
    //   252: invokevirtual intValue : ()I
    //   255: bipush #32
    //   257: irem
    //   258: invokestatic abs : (I)I
    //   261: invokevirtual charAt : (I)C
    //   264: invokevirtual append : (C)Ljava/lang/StringBuilder;
    //   267: pop
    //   268: iload_2
    //   269: ifeq -> 1348
    //   272: goto -> 279
    //   275: invokestatic a : (Ljava/lang/Throwable;)Ljava/lang/Throwable;
    //   278: athrow
    //   279: aload_3
    //   280: getstatic burp/Zecw.Zb : Ljava/lang/String;
    //   283: getstatic burp/Zr9b.ZF : Ljava/lang/Object;
    //   286: checkcast java/math/BigInteger
    //   289: invokevirtual intValue : ()I
    //   292: bipush #32
    //   294: irem
    //   295: invokestatic abs : (I)I
    //   298: invokevirtual charAt : (I)C
    //   301: invokevirtual append : (C)Ljava/lang/StringBuilder;
    //   304: pop
    //   305: iload_2
    //   306: ifeq -> 1348
    //   309: goto -> 316
    //   312: invokestatic a : (Ljava/lang/Throwable;)Ljava/lang/Throwable;
    //   315: athrow
    //   316: aload_3
    //   317: getstatic burp/Zkf9.ZS : Ljava/lang/String;
    //   320: getstatic burp/Zmlu.Zi : Ljava/lang/Object;
    //   323: checkcast java/math/BigInteger
    //   326: invokevirtual intValue : ()I
    //   329: bipush #32
    //   331: irem
    //   332: invokestatic abs : (I)I
    //   335: invokevirtual charAt : (I)C
    //   338: invokevirtual append : (C)Ljava/lang/StringBuilder;
    //   341: pop
    //   342: iload_2
    //   343: ifeq -> 1348
    //   346: goto -> 353
    //   349: invokestatic a : (Ljava/lang/Throwable;)Ljava/lang/Throwable;
    //   352: athrow
    //   353: aload_3
    //   354: getstatic burp/Zr9b.ZC : Ljava/lang/String;
    //   357: getstatic burp/Zkfa.Zw : Ljava/lang/Object;
    //   360: checkcast java/math/BigInteger
    //   363: invokevirtual intValue : ()I
    //   366: bipush #32
    //   368: irem
    //   369: invokestatic abs : (I)I
    //   372: invokevirtual charAt : (I)C
    //   375: invokevirtual append : (C)Ljava/lang/StringBuilder;
    //   378: pop
    //   379: iload_2
    //   380: ifeq -> 1348
    //   383: goto -> 390
    //   386: invokestatic a : (Ljava/lang/Throwable;)Ljava/lang/Throwable;
    //   389: athrow
    //   390: aload_3
    //   391: getstatic burp/Zzrb.ZA : Ljava/lang/String;
    //   394: getstatic burp/Zsf3.ZH : Ljava/lang/Object;
    //   397: checkcast java/math/BigInteger
    //   400: invokevirtual intValue : ()I
    //   403: bipush #32
    //   405: irem
    //   406: invokestatic abs : (I)I
    //   409: invokevirtual charAt : (I)C
    //   412: invokevirtual append : (C)Ljava/lang/StringBuilder;
    //   415: pop
    //   416: iload_2
    //   417: ifeq -> 1348
    //   420: goto -> 427
    //   423: invokestatic a : (Ljava/lang/Throwable;)Ljava/lang/Throwable;
    //   426: athrow
    //   427: aload_3
    //   428: getstatic burp/Zzou.ZN : Ljava/lang/String;
    //   431: getstatic burp/Zlav.Zp : Ljava/lang/Object;
    //   434: checkcast java/math/BigInteger
    //   437: invokevirtual intValue : ()I
    //   440: bipush #32
    //   442: irem
    //   443: invokestatic abs : (I)I
    //   446: invokevirtual charAt : (I)C
    //   449: invokevirtual append : (C)Ljava/lang/StringBuilder;
    //   452: pop
    //   453: iload_2
    //   454: ifeq -> 1348
    //   457: goto -> 464
    //   460: invokestatic a : (Ljava/lang/Throwable;)Ljava/lang/Throwable;
    //   463: athrow
    //   464: aload_3
    //   465: getstatic burp/Zrs0.Zt : Ljava/lang/String;
    //   468: getstatic burp/Zzs9.ZO : Ljava/lang/Object;
    //   471: checkcast java/math/BigInteger
    //   474: invokevirtual intValue : ()I
    //   477: bipush #32
    //   479: irem
    //   480: invokestatic abs : (I)I
    //   483: invokevirtual charAt : (I)C
    //   486: invokevirtual append : (C)Ljava/lang/StringBuilder;
    //   489: pop
    //   490: iload_2
    //   491: ifeq -> 1348
    //   494: goto -> 501
    //   497: invokestatic a : (Ljava/lang/Throwable;)Ljava/lang/Throwable;
    //   500: athrow
    //   501: aload_3
    //   502: getstatic burp/Zsf3.Zb : Ljava/lang/String;
    //   505: getstatic burp/Zl8y.ZD : Ljava/lang/Object;
    //   508: checkcast java/math/BigInteger
    //   511: invokevirtual intValue : ()I
    //   514: bipush #32
    //   516: irem
    //   517: invokestatic abs : (I)I
    //   520: invokevirtual charAt : (I)C
    //   523: invokevirtual append : (C)Ljava/lang/StringBuilder;
    //   526: pop
    //   527: iload_2
    //   528: ifeq -> 1348
    //   531: goto -> 538
    //   534: invokestatic a : (Ljava/lang/Throwable;)Ljava/lang/Throwable;
    //   537: athrow
    //   538: aload_3
    //   539: getstatic burp/Zro5.ZY : Ljava/lang/String;
    //   542: getstatic burp/Zmji.ZB : Ljava/lang/Object;
    //   545: checkcast java/math/BigInteger
    //   548: invokevirtual intValue : ()I
    //   551: bipush #32
    //   553: irem
    //   554: invokestatic abs : (I)I
    //   557: invokevirtual charAt : (I)C
    //   560: invokevirtual append : (C)Ljava/lang/StringBuilder;
    //   563: pop
    //   564: iload_2
    //   565: ifeq -> 1348
    //   568: goto -> 575
    //   571: invokestatic a : (Ljava/lang/Throwable;)Ljava/lang/Throwable;
    //   574: athrow
    //   575: aload_3
    //   576: getstatic burp/Zrs0.Zt : Ljava/lang/String;
    //   579: getstatic burp/Zefm.ZP : Ljava/lang/Object;
    //   582: checkcast java/math/BigInteger
    //   585: invokevirtual intValue : ()I
    //   588: bipush #32
    //   590: irem
    //   591: invokestatic abs : (I)I
    //   594: invokevirtual charAt : (I)C
    //   597: invokevirtual append : (C)Ljava/lang/StringBuilder;
    //   600: pop
    //   601: iload_2
    //   602: ifeq -> 1348
    //   605: goto -> 612
    //   608: invokestatic a : (Ljava/lang/Throwable;)Ljava/lang/Throwable;
    //   611: athrow
    //   612: aload_3
    //   613: getstatic burp/Zr5k.Zq : Ljava/lang/String;
    //   616: getstatic burp/Ztys.Zs : Ljava/lang/Object;
    //   619: checkcast java/math/BigInteger
    //   622: invokevirtual intValue : ()I
    //   625: bipush #32
    //   627: irem
    //   628: invokestatic abs : (I)I
    //   631: invokevirtual charAt : (I)C
    //   634: invokevirtual append : (C)Ljava/lang/StringBuilder;
    //   637: pop
    //   638: iload_2
    //   639: ifeq -> 1348
    //   642: goto -> 649
    //   645: invokestatic a : (Ljava/lang/Throwable;)Ljava/lang/Throwable;
    //   648: athrow
    //   649: aload_3
    //   650: getstatic burp/Zejj.ZQ : Ljava/lang/String;
    //   653: getstatic burp/Zkfa.Zw : Ljava/lang/Object;
    //   656: checkcast java/math/BigInteger
    //   659: invokevirtual intValue : ()I
    //   662: bipush #32
    //   664: irem
    //   665: invokestatic abs : (I)I
    //   668: invokevirtual charAt : (I)C
    //   671: invokevirtual append : (C)Ljava/lang/StringBuilder;
    //   674: pop
    //   675: iload_2
    //   676: ifeq -> 1348
    //   679: goto -> 686
    //   682: invokestatic a : (Ljava/lang/Throwable;)Ljava/lang/Throwable;
    //   685: athrow
    //   686: aload_3
    //   687: getstatic burp/Zmzh.Zm : Ljava/lang/String;
    //   690: getstatic burp/Zx_x.Zi : Ljava/lang/Object;
    //   693: checkcast java/math/BigInteger
    //   696: invokevirtual intValue : ()I
    //   699: bipush #32
    //   701: irem
    //   702: invokestatic abs : (I)I
    //   705: invokevirtual charAt : (I)C
    //   708: invokevirtual append : (C)Ljava/lang/StringBuilder;
    //   711: pop
    //   712: iload_2
    //   713: ifeq -> 1348
    //   716: goto -> 723
    //   719: invokestatic a : (Ljava/lang/Throwable;)Ljava/lang/Throwable;
    //   722: athrow
    //   723: aload_3
    //   724: getstatic burp/Zr5k.Zq : Ljava/lang/String;
    //   727: getstatic burp/Zgwu.ZD : Ljava/lang/Object;
    //   730: checkcast java/math/BigInteger
    //   733: invokevirtual intValue : ()I
    //   736: bipush #32
    //   738: irem
    //   739: invokestatic abs : (I)I
    //   742: invokevirtual charAt : (I)C
    //   745: invokevirtual append : (C)Ljava/lang/StringBuilder;
    //   748: pop
    //   749: iload_2
    //   750: ifeq -> 1348
    //   753: goto -> 760
    //   756: invokestatic a : (Ljava/lang/Throwable;)Ljava/lang/Throwable;
    //   759: athrow
    //   760: aload_3
    //   761: getstatic burp/Zxpb.ZQ : Ljava/lang/String;
    //   764: getstatic burp/Zb20.Zq : Ljava/lang/Object;
    //   767: checkcast java/math/BigInteger
    //   770: invokevirtual intValue : ()I
    //   773: bipush #32
    //   775: irem
    //   776: invokestatic abs : (I)I
    //   779: invokevirtual charAt : (I)C
    //   782: invokevirtual append : (C)Ljava/lang/StringBuilder;
    //   785: pop
    //   786: iload_2
    //   787: ifeq -> 1348
    //   790: goto -> 797
    //   793: invokestatic a : (Ljava/lang/Throwable;)Ljava/lang/Throwable;
    //   796: athrow
    //   797: aload_3
    //   798: getstatic burp/Zzpu.Zq : Ljava/lang/String;
    //   801: getstatic burp/Zmji.ZB : Ljava/lang/Object;
    //   804: checkcast java/math/BigInteger
    //   807: invokevirtual intValue : ()I
    //   810: bipush #32
    //   812: irem
    //   813: invokestatic abs : (I)I
    //   816: invokevirtual charAt : (I)C
    //   819: invokevirtual append : (C)Ljava/lang/StringBuilder;
    //   822: pop
    //   823: iload_2
    //   824: ifeq -> 1348
    //   827: goto -> 834
    //   830: invokestatic a : (Ljava/lang/Throwable;)Ljava/lang/Throwable;
    //   833: athrow
    //   834: aload_3
    //   835: getstatic burp/Zm8i.Z_ : Ljava/lang/String;
    //   838: getstatic burp/Zlpn.ZU : Ljava/lang/Object;
    //   841: checkcast java/math/BigInteger
    //   844: invokevirtual intValue : ()I
    //   847: bipush #32
    //   849: irem
    //   850: invokestatic abs : (I)I
    //   853: invokevirtual charAt : (I)C
    //   856: invokevirtual append : (C)Ljava/lang/StringBuilder;
    //   859: pop
    //   860: iload_2
    //   861: ifeq -> 1348
    //   864: goto -> 871
    //   867: invokestatic a : (Ljava/lang/Throwable;)Ljava/lang/Throwable;
    //   870: athrow
    //   871: aload_3
    //   872: getstatic burp/Zkfa.Zy : Ljava/lang/String;
    //   875: getstatic burp/Zzok.ZY : Ljava/lang/Object;
    //   878: checkcast java/math/BigInteger
    //   881: invokevirtual intValue : ()I
    //   884: bipush #32
    //   886: irem
    //   887: invokestatic abs : (I)I
    //   890: invokevirtual charAt : (I)C
    //   893: invokevirtual append : (C)Ljava/lang/StringBuilder;
    //   896: pop
    //   897: iload_2
    //   898: ifeq -> 1348
    //   901: goto -> 908
    //   904: invokestatic a : (Ljava/lang/Throwable;)Ljava/lang/Throwable;
    //   907: athrow
    //   908: aload_3
    //   909: getstatic burp/Zss6.ZN : Ljava/lang/String;
    //   912: getstatic burp/Zb0z.ZQ : Ljava/lang/Object;
    //   915: checkcast java/math/BigInteger
    //   918: invokevirtual intValue : ()I
    //   921: bipush #32
    //   923: irem
    //   924: invokestatic abs : (I)I
    //   927: invokevirtual charAt : (I)C
    //   930: invokevirtual append : (C)Ljava/lang/StringBuilder;
    //   933: pop
    //   934: iload_2
    //   935: ifeq -> 1348
    //   938: goto -> 945
    //   941: invokestatic a : (Ljava/lang/Throwable;)Ljava/lang/Throwable;
    //   944: athrow
    //   945: aload_3
    //   946: getstatic burp/Zmt7.Zl : Ljava/lang/String;
    //   949: getstatic burp/Zrpy.ZG : Ljava/lang/Object;
    //   952: checkcast java/math/BigInteger
    //   955: invokevirtual intValue : ()I
    //   958: bipush #32
    //   960: irem
    //   961: invokestatic abs : (I)I
    //   964: invokevirtual charAt : (I)C
    //   967: invokevirtual append : (C)Ljava/lang/StringBuilder;
    //   970: pop
    //   971: iload_2
    //   972: ifeq -> 1348
    //   975: goto -> 982
    //   978: invokestatic a : (Ljava/lang/Throwable;)Ljava/lang/Throwable;
    //   981: athrow
    //   982: aload_3
    //   983: getstatic burp/Zxtc.Zo : Ljava/lang/String;
    //   986: getstatic burp/Zbp_.Zi : Ljava/lang/Object;
    //   989: checkcast java/math/BigInteger
    //   992: invokevirtual intValue : ()I
    //   995: bipush #32
    //   997: irem
    //   998: invokestatic abs : (I)I
    //   1001: invokevirtual charAt : (I)C
    //   1004: invokevirtual append : (C)Ljava/lang/StringBuilder;
    //   1007: pop
    //   1008: iload_2
    //   1009: ifeq -> 1348
    //   1012: goto -> 1019
    //   1015: invokestatic a : (Ljava/lang/Throwable;)Ljava/lang/Throwable;
    //   1018: athrow
    //   1019: aload_3
    //   1020: getstatic burp/Zkfa.Zy : Ljava/lang/String;
    //   1023: getstatic burp/Zscs.Zg : Ljava/lang/Object;
    //   1026: checkcast java/math/BigInteger
    //   1029: invokevirtual intValue : ()I
    //   1032: bipush #32
    //   1034: irem
    //   1035: invokestatic abs : (I)I
    //   1038: invokevirtual charAt : (I)C
    //   1041: invokevirtual append : (C)Ljava/lang/StringBuilder;
    //   1044: pop
    //   1045: iload_2
    //   1046: ifeq -> 1348
    //   1049: goto -> 1056
    //   1052: invokestatic a : (Ljava/lang/Throwable;)Ljava/lang/Throwable;
    //   1055: athrow
    //   1056: aload_3
    //   1057: getstatic burp/Zrpy.Zr : Ljava/lang/String;
    //   1060: getstatic burp/Zkco.Zg : Ljava/lang/Object;
    //   1063: checkcast java/math/BigInteger
    //   1066: invokevirtual intValue : ()I
    //   1069: bipush #32
    //   1071: irem
    //   1072: invokestatic abs : (I)I
    //   1075: invokevirtual charAt : (I)C
    //   1078: invokevirtual append : (C)Ljava/lang/StringBuilder;
    //   1081: pop
    //   1082: iload_2
    //   1083: ifeq -> 1348
    //   1086: goto -> 1093
    //   1089: invokestatic a : (Ljava/lang/Throwable;)Ljava/lang/Throwable;
    //   1092: athrow
    //   1093: aload_3
    //   1094: getstatic burp/Zrpy.Zr : Ljava/lang/String;
    //   1097: getstatic burp/Zscs.Zg : Ljava/lang/Object;
    //   1100: checkcast java/math/BigInteger
    //   1103: invokevirtual intValue : ()I
    //   1106: bipush #32
    //   1108: irem
    //   1109: invokestatic abs : (I)I
    //   1112: invokevirtual charAt : (I)C
    //   1115: invokevirtual append : (C)Ljava/lang/StringBuilder;
    //   1118: pop
    //   1119: iload_2
    //   1120: ifeq -> 1348
    //   1123: goto -> 1130
    //   1126: invokestatic a : (Ljava/lang/Throwable;)Ljava/lang/Throwable;
    //   1129: athrow
    //   1130: aload_3
    //   1131: getstatic burp/Zz35.ZH : Ljava/lang/String;
    //   1134: getstatic burp/Zecw.ZE : Ljava/lang/Object;
    //   1137: checkcast java/math/BigInteger
    //   1140: invokevirtual intValue : ()I
    //   1143: bipush #32
    //   1145: irem
    //   1146: invokestatic abs : (I)I
    //   1149: invokevirtual charAt : (I)C
    //   1152: invokevirtual append : (C)Ljava/lang/StringBuilder;
    //   1155: pop
    //   1156: iload_2
    //   1157: ifeq -> 1348
    //   1160: goto -> 1167
    //   1163: invokestatic a : (Ljava/lang/Throwable;)Ljava/lang/Throwable;
    //   1166: athrow
    //   1167: aload_3
    //   1168: getstatic burp/Zrml.Zt : Ljava/lang/String;
    //   1171: getstatic burp/Zlnq.ZO : Ljava/lang/Object;
    //   1174: checkcast java/math/BigInteger
    //   1177: invokevirtual intValue : ()I
    //   1180: bipush #32
    //   1182: irem
    //   1183: invokestatic abs : (I)I
    //   1186: invokevirtual charAt : (I)C
    //   1189: invokevirtual append : (C)Ljava/lang/StringBuilder;
    //   1192: pop
    //   1193: iload_2
    //   1194: ifeq -> 1348
    //   1197: goto -> 1204
    //   1200: invokestatic a : (Ljava/lang/Throwable;)Ljava/lang/Throwable;
    //   1203: athrow
    //   1204: aload_3
    //   1205: getstatic burp/Zzxv.Z_ : Ljava/lang/String;
    //   1208: getstatic burp/Zx8t.ZA : Ljava/lang/Object;
    //   1211: checkcast java/math/BigInteger
    //   1214: invokevirtual intValue : ()I
    //   1217: bipush #32
    //   1219: irem
    //   1220: invokestatic abs : (I)I
    //   1223: invokevirtual charAt : (I)C
    //   1226: invokevirtual append : (C)Ljava/lang/StringBuilder;
    //   1229: pop
    //   1230: iload_2
    //   1231: ifeq -> 1348
    //   1234: goto -> 1241
    //   1237: invokestatic a : (Ljava/lang/Throwable;)Ljava/lang/Throwable;
    //   1240: athrow
    //   1241: aload_3
    //   1242: getstatic burp/Zss6.ZN : Ljava/lang/String;
    //   1245: getstatic burp/Zldt.ZS : Ljava/lang/Object;
    //   1248: checkcast java/math/BigInteger
    //   1251: invokevirtual intValue : ()I
    //   1254: bipush #32
    //   1256: irem
    //   1257: invokestatic abs : (I)I
    //   1260: invokevirtual charAt : (I)C
    //   1263: invokevirtual append : (C)Ljava/lang/StringBuilder;
    //   1266: pop
    //   1267: iload_2
    //   1268: ifeq -> 1348
    //   1271: goto -> 1278
    //   1274: invokestatic a : (Ljava/lang/Throwable;)Ljava/lang/Throwable;
    //   1277: athrow
    //   1278: aload_3
    //   1279: getstatic burp/Zgkn.ZV : Ljava/lang/String;
    //   1282: getstatic burp/Ze_l.ZX : Ljava/lang/Object;
    //   1285: checkcast java/math/BigInteger
    //   1288: invokevirtual intValue : ()I
    //   1291: bipush #32
    //   1293: irem
    //   1294: invokestatic abs : (I)I
    //   1297: invokevirtual charAt : (I)C
    //   1300: invokevirtual append : (C)Ljava/lang/StringBuilder;
    //   1303: pop
    //   1304: iload_2
    //   1305: ifeq -> 1348
    //   1308: goto -> 1315
    //   1311: invokestatic a : (Ljava/lang/Throwable;)Ljava/lang/Throwable;
    //   1314: athrow
    //   1315: aload_3
    //   1316: getstatic burp/Ztd3.ZC : Ljava/lang/String;
    //   1319: getstatic burp/Zmzh.Zk : Ljava/lang/Object;
    //   1322: checkcast java/math/BigInteger
    //   1325: invokevirtual intValue : ()I
    //   1328: bipush #32
    //   1330: irem
    //   1331: invokestatic abs : (I)I
    //   1334: invokevirtual charAt : (I)C
    //   1337: invokevirtual append : (C)Ljava/lang/StringBuilder;
    //   1340: pop
    //   1341: goto -> 1348
    //   1344: invokestatic a : (Ljava/lang/Throwable;)Ljava/lang/Throwable;
    //   1347: athrow
    //   1348: iinc #4, 1
    //   1351: iload_2
    //   1352: ifeq -> 15
    //   1355: sipush #24847
    //   1358: sipush #7377
    //   1361: invokestatic a : (II)Ljava/lang/String;
    //   1364: invokestatic forName : (Ljava/lang/String;)Ljava/lang/Class;
    //   1367: invokevirtual getDeclaredMethods : ()[Ljava/lang/reflect/Method;
    //   1370: astore #4
    //   1372: aload #4
    //   1374: arraylength
    //   1375: istore #5
    //   1377: iconst_0
    //   1378: istore #6
    //   1380: iload #6
    //   1382: iload #5
    //   1384: if_icmpge -> 1472
    //   1387: aload #4
    //   1389: iload #6
    //   1391: aaload
    //   1392: astore #7
    //   1394: aload #7
    //   1396: invokevirtual getModifiers : ()I
    //   1399: invokestatic isStatic : (I)Z
    //   1402: ifeq -> 1465
    //   1405: aload #7
    //   1407: invokevirtual getParameterTypes : ()[Ljava/lang/Class;
    //   1410: arraylength
    //   1411: iconst_2
    //   1412: if_icmpne -> 1465
    //   1415: goto -> 1422
    //   1418: invokestatic a : (Ljava/lang/Throwable;)Ljava/lang/Throwable;
    //   1421: athrow
    //   1422: aload #7
    //   1424: invokevirtual getReturnType : ()Ljava/lang/Class;
    //   1427: getstatic java/lang/Boolean.TYPE : Ljava/lang/Class;
    //   1430: if_acmpne -> 1465
    //   1433: goto -> 1440
    //   1436: invokestatic a : (Ljava/lang/Throwable;)Ljava/lang/Throwable;
    //   1439: athrow
    //   1440: aload #7
    //   1442: aconst_null
    //   1443: iconst_2
    //   1444: anewarray java/lang/Object
    //   1447: dup
    //   1448: iconst_0
    //   1449: aload_0
    //   1450: aastore
    //   1451: dup
    //   1452: iconst_1
    //   1453: aload_1
    //   1454: aastore
    //   1455: invokevirtual invoke : (Ljava/lang/Object;[Ljava/lang/Object;)Ljava/lang/Object;
    //   1458: checkcast java/lang/Boolean
    //   1461: invokevirtual booleanValue : ()Z
    //   1464: ireturn
    //   1465: iinc #6, 1
    //   1468: iload_2
    //   1469: ifeq -> 1380
    //   1472: sipush #24844
    //   1475: sipush #-26648
    //   1478: invokestatic a : (II)Ljava/lang/String;
    //   1481: iconst_1
    //   1482: ldc burp/Zegw
    //   1484: invokevirtual getClassLoader : ()Ljava/lang/ClassLoader;
    //   1487: invokestatic forName : (Ljava/lang/String;ZLjava/lang/ClassLoader;)Ljava/lang/Class;
    //   1490: invokevirtual getDeclaredFields : ()[Ljava/lang/reflect/Field;
    //   1493: astore #4
    //   1495: aload #4
    //   1497: arraylength
    //   1498: istore #5
    //   1500: iconst_0
    //   1501: istore #6
    //   1503: iload #6
    //   1505: iload #5
    //   1507: if_icmpge -> 1645
    //   1510: aload #4
    //   1512: iload #6
    //   1514: aaload
    //   1515: astore #7
    //   1517: aload #7
    //   1519: invokevirtual getModifiers : ()I
    //   1522: invokestatic isStatic : (I)Z
    //   1525: ifne -> 1535
    //   1528: goto -> 1638
    //   1531: invokestatic a : (Ljava/lang/Throwable;)Ljava/lang/Throwable;
    //   1534: athrow
    //   1535: aload #7
    //   1537: invokevirtual getType : ()Ljava/lang/Class;
    //   1540: astore #8
    //   1542: aload #8
    //   1544: ifnull -> 1625
    //   1547: aload #8
    //   1549: invokevirtual isPrimitive : ()Z
    //   1552: ifne -> 1625
    //   1555: goto -> 1562
    //   1558: invokestatic a : (Ljava/lang/Throwable;)Ljava/lang/Throwable;
    //   1561: athrow
    //   1562: aload #8
    //   1564: invokevirtual getPackage : ()Ljava/lang/Package;
    //   1567: ifnull -> 1625
    //   1570: goto -> 1577
    //   1573: invokestatic a : (Ljava/lang/Throwable;)Ljava/lang/Throwable;
    //   1576: athrow
    //   1577: aload #8
    //   1579: invokevirtual getPackage : ()Ljava/lang/Package;
    //   1582: invokevirtual getName : ()Ljava/lang/String;
    //   1585: ifnull -> 1625
    //   1588: goto -> 1595
    //   1591: invokestatic a : (Ljava/lang/Throwable;)Ljava/lang/Throwable;
    //   1594: athrow
    //   1595: aload #8
    //   1597: invokevirtual getPackage : ()Ljava/lang/Package;
    //   1600: invokevirtual getName : ()Ljava/lang/String;
    //   1603: sipush #24840
    //   1606: sipush #3680
    //   1609: invokestatic a : (II)Ljava/lang/String;
    //   1612: invokevirtual startsWith : (Ljava/lang/String;)Z
    //   1615: ifne -> 1625
    //   1618: goto -> 1625
    //   1621: invokestatic a : (Ljava/lang/Throwable;)Ljava/lang/Throwable;
    //   1624: athrow
    //   1625: aload #7
    //   1627: iconst_1
    //   1628: invokevirtual setAccessible : (Z)V
    //   1631: aload #7
    //   1633: aconst_null
    //   1634: invokevirtual get : (Ljava/lang/Object;)Ljava/lang/Object;
    //   1637: pop
    //   1638: iinc #6, 1
    //   1641: iload_2
    //   1642: ifeq -> 1503
    //   1645: sipush #24846
    //   1648: sipush #-10922
    //   1651: invokestatic a : (II)Ljava/lang/String;
    //   1654: invokestatic forName : (Ljava/lang/String;)Ljava/lang/Class;
    //   1657: invokevirtual getDeclaredMethods : ()[Ljava/lang/reflect/Method;
    //   1660: astore #4
    //   1662: aload #4
    //   1664: arraylength
    //   1665: istore #5
    //   1667: iconst_0
    //   1668: istore #6
    //   1670: iload #6
    //   1672: iload #5
    //   1674: if_icmpge -> 1807
    //   1677: aload #4
    //   1679: iload #6
    //   1681: aaload
    //   1682: astore #7
    //   1684: aload #7
    //   1686: invokevirtual getParameterTypes : ()[Ljava/lang/Class;
    //   1689: pop
    //   1690: aload #7
    //   1692: invokevirtual getModifiers : ()I
    //   1695: invokestatic isStatic : (I)Z
    //   1698: ifeq -> 1793
    //   1701: aload #7
    //   1703: invokevirtual getParameterTypes : ()[Ljava/lang/Class;
    //   1706: arraylength
    //   1707: iconst_2
    //   1708: if_icmpne -> 1793
    //   1711: goto -> 1718
    //   1714: invokestatic a : (Ljava/lang/Throwable;)Ljava/lang/Throwable;
    //   1717: athrow
    //   1718: aload #7
    //   1720: invokevirtual getReturnType : ()Ljava/lang/Class;
    //   1723: getstatic java/lang/Void.TYPE : Ljava/lang/Class;
    //   1726: invokevirtual equals : (Ljava/lang/Object;)Z
    //   1729: ifeq -> 1793
    //   1732: goto -> 1739
    //   1735: invokestatic a : (Ljava/lang/Throwable;)Ljava/lang/Throwable;
    //   1738: athrow
    //   1739: aload #7
    //   1741: iconst_1
    //   1742: invokevirtual setAccessible : (Z)V
    //   1745: aload #7
    //   1747: aconst_null
    //   1748: iconst_2
    //   1749: anewarray java/lang/Object
    //   1752: dup
    //   1753: iconst_0
    //   1754: aload_0
    //   1755: aastore
    //   1756: dup
    //   1757: iconst_1
    //   1758: aload_1
    //   1759: ifnonnull -> 1777
    //   1762: goto -> 1769
    //   1765: invokestatic a : (Ljava/lang/Throwable;)Ljava/lang/Throwable;
    //   1768: athrow
    //   1769: aload_1
    //   1770: goto -> 1784
    //   1773: invokestatic a : (Ljava/lang/Throwable;)Ljava/lang/Throwable;
    //   1776: athrow
    //   1777: aload_1
    //   1778: checkcast [B
    //   1781: invokevirtual clone : ()Ljava/lang/Object;
    //   1784: aastore
    //   1785: invokevirtual invoke : (Ljava/lang/Object;[Ljava/lang/Object;)Ljava/lang/Object;
    //   1788: pop
    //   1789: iload_2
    //   1790: ifeq -> 1807
    //   1793: iinc #6, 1
    //   1796: iload_2
    //   1797: ifeq -> 1670
    //   1800: goto -> 1807
    //   1803: invokestatic a : (Ljava/lang/Throwable;)Ljava/lang/Throwable;
    //   1806: athrow
    //   1807: getstatic burp/Zmji.Zs : Ljava/lang/String;
    //   1810: getstatic burp/Ztys.Zs : Ljava/lang/Object;
    //   1813: checkcast java/math/BigInteger
    //   1816: invokevirtual intValue : ()I
    //   1819: bipush #32
    //   1821: irem
    //   1822: invokestatic abs : (I)I
    //   1825: invokevirtual charAt : (I)C
    //   1828: getstatic burp/Zzh0.ZK : Ljava/lang/String;
    //   1831: getstatic burp/Zb9h.Zm : Ljava/lang/Object;
    //   1834: checkcast java/math/BigInteger
    //   1837: invokevirtual intValue : ()I
    //   1840: bipush #32
    //   1842: irem
    //   1843: invokestatic abs : (I)I
    //   1846: invokevirtual charAt : (I)C
    //   1849: if_icmpgt -> 1956
    //   1852: getstatic burp/Zzpu.Zq : Ljava/lang/String;
    //   1855: getstatic burp/Zmji.ZB : Ljava/lang/Object;
    //   1858: checkcast java/math/BigInteger
    //   1861: invokevirtual intValue : ()I
    //   1864: bipush #32
    //   1866: irem
    //   1867: invokestatic abs : (I)I
    //   1870: invokevirtual charAt : (I)C
    //   1873: getstatic burp/Zzrb.ZA : Ljava/lang/String;
    //   1876: getstatic burp/Zxtc.ZF : Ljava/lang/Object;
    //   1879: checkcast java/math/BigInteger
    //   1882: invokevirtual intValue : ()I
    //   1885: bipush #32
    //   1887: irem
    //   1888: invokestatic abs : (I)I
    //   1891: invokevirtual charAt : (I)C
    //   1894: if_icmple -> 1956
    //   1897: goto -> 1904
    //   1900: invokestatic a : (Ljava/lang/Throwable;)Ljava/lang/Throwable;
    //   1903: athrow
    //   1904: getstatic burp/Zbzc.ZL : Ljava/lang/String;
    //   1907: getstatic burp/Zme.Zd : Ljava/lang/Object;
    //   1910: checkcast java/math/BigInteger
    //   1913: invokevirtual intValue : ()I
    //   1916: bipush #32
    //   1918: irem
    //   1919: invokestatic abs : (I)I
    //   1922: invokevirtual charAt : (I)C
    //   1925: getstatic burp/Zldt.Zj : Ljava/lang/String;
    //   1928: getstatic burp/Zzs9.ZO : Ljava/lang/Object;
    //   1931: checkcast java/math/BigInteger
    //   1934: invokevirtual intValue : ()I
    //   1937: bipush #32
    //   1939: irem
    //   1940: invokestatic abs : (I)I
    //   1943: invokevirtual charAt : (I)C
    //   1946: if_icmpgt -> 1964
    //   1949: goto -> 1956
    //   1952: invokestatic a : (Ljava/lang/Throwable;)Ljava/lang/Throwable;
    //   1955: athrow
    //   1956: iconst_1
    //   1957: goto -> 1965
    //   1960: invokestatic a : (Ljava/lang/Throwable;)Ljava/lang/Throwable;
    //   1963: athrow
    //   1964: iconst_0
    //   1965: ireturn
    //   1966: astore_3
    //   1967: new java/lang/Exception
    //   1970: dup
    //   1971: aload_3
    //   1972: invokevirtual getMessage : ()Ljava/lang/String;
    //   1975: invokespecial <init> : (Ljava/lang/String;)V
    //   1978: athrow
    // Exception table:
    //   from	to	target	type
    //   4	1464	1966	java/lang/Throwable
    //   22	198	201	java/lang/Throwable
    //   168	235	238	java/lang/Throwable
    //   205	272	275	java/lang/Throwable
    //   242	309	312	java/lang/Throwable
    //   279	346	349	java/lang/Throwable
    //   316	383	386	java/lang/Throwable
    //   353	420	423	java/lang/Throwable
    //   390	457	460	java/lang/Throwable
    //   427	494	497	java/lang/Throwable
    //   464	531	534	java/lang/Throwable
    //   501	568	571	java/lang/Throwable
    //   538	605	608	java/lang/Throwable
    //   575	642	645	java/lang/Throwable
    //   612	679	682	java/lang/Throwable
    //   649	716	719	java/lang/Throwable
    //   686	753	756	java/lang/Throwable
    //   723	790	793	java/lang/Throwable
    //   760	827	830	java/lang/Throwable
    //   797	864	867	java/lang/Throwable
    //   834	901	904	java/lang/Throwable
    //   871	938	941	java/lang/Throwable
    //   908	975	978	java/lang/Throwable
    //   945	1012	1015	java/lang/Throwable
    //   982	1049	1052	java/lang/Throwable
    //   1019	1086	1089	java/lang/Throwable
    //   1056	1123	1126	java/lang/Throwable
    //   1093	1160	1163	java/lang/Throwable
    //   1130	1197	1200	java/lang/Throwable
    //   1167	1234	1237	java/lang/Throwable
    //   1204	1271	1274	java/lang/Throwable
    //   1241	1308	1311	java/lang/Throwable
    //   1278	1341	1344	java/lang/Throwable
    //   1394	1415	1418	java/lang/Throwable
    //   1405	1433	1436	java/lang/Throwable
    //   1465	1965	1966	java/lang/Throwable
    //   1517	1531	1531	java/lang/Throwable
    //   1542	1555	1558	java/lang/Throwable
    //   1547	1570	1573	java/lang/Throwable
    //   1562	1588	1591	java/lang/Throwable
    //   1577	1618	1621	java/lang/Throwable
    //   1684	1711	1714	java/lang/Throwable
    //   1701	1732	1735	java/lang/Throwable
    //   1718	1762	1765	java/lang/Throwable
    //   1739	1773	1773	java/lang/Throwable
    //   1784	1800	1803	java/lang/Throwable
    //   1807	1897	1900	java/lang/Throwable
    //   1852	1949	1952	java/lang/Throwable
    //   1904	1960	1960	java/lang/Throwable
  }
  
  static void Zo(Object paramObject) {
    Zgwu.Zd = a(24843, -26925);
    Zgwu.ZD = new BigInteger(1, new byte[] { 
          74, -97, 105, -72, 20, -81, 73, -28, 103, 12, 
          94, 34, 110, -77, 18, -119, 46, -100, -103, 45, 
          42, 16, -69, -100, 7, -56, -85, 1, -110, 119, 
          63, -10 });
    boolean bool = Zt2e.ZN();
    try {
      try {
        if (Zrof.ZE.charAt(Math.abs(((BigInteger)Zecm.ZJ).intValue() % 32)) <= Zlna.Zo.charAt(Math.abs(((BigInteger)Zmy4.ZB).intValue() % 32))) {
          try {
            Ztpg.Zx(Class.forName(a(24842, -29369)));
            if (!bool)
              Zlwi.ZE(Class.forName(a(24845, 6791))); 
          } catch (Throwable throwable) {
            throw a(null);
          } 
          return;
        } 
      } catch (Throwable throwable) {
        throw a(null);
      } 
      Zlwi.ZE(Class.forName(a(24845, 6791)));
    } catch (Throwable throwable) {}
  }
  
  static void Zs(Object[] paramArrayOfObject, Object paramObject) throws Throwable {}
  
  static {
    // Byte code:
    //   0: bipush #8
    //   2: anewarray java/lang/String
    //   5: astore #5
    //   7: iconst_0
    //   8: istore_3
    //   9: ldc 'ÃÃ°Ã„Â©Ã•Â´Ã´:Â½~AUÂ‘ÂÃºÃÃ¨Ã¬ÂÃ¨ÃŽÃÃ¢=Ã¸;Â±Ã¬Â‹Ã Â”+ÃÂ™ Ã—Â”Ã£ÃÂ©Ã¬Ã¾Ã“>]ÃžÃ¯Â‹Â’q).Â…[Â¢ÃŒW7ÂŒ{Ã¸Ã†Â­Â±Â•\\tÂˆBÃ•Ã´7ÂŸ\\tÃ¿!Â¬Ã˜\\bÂÂºLÃ¢\\t|Â€ÃœÃ¬{Ã•Ãƒ'
    //   11: dup
    //   12: astore_2
    //   13: invokevirtual length : ()I
    //   16: istore #4
    //   18: bipush #32
    //   20: istore_1
    //   21: iconst_m1
    //   22: istore_0
    //   23: bipush #117
    //   25: iinc #0, 1
    //   28: aload_2
    //   29: iload_0
    //   30: dup
    //   31: iload_1
    //   32: iadd
    //   33: invokevirtual substring : (II)Ljava/lang/String;
    //   36: iconst_m1
    //   37: goto -> 143
    //   40: aload #5
    //   42: swap
    //   43: iload_3
    //   44: iinc #3, 1
    //   47: swap
    //   48: aastore
    //   49: iload_0
    //   50: iload_1
    //   51: iadd
    //   52: dup
    //   53: istore_0
    //   54: iload #4
    //   56: if_icmpge -> 68
    //   59: aload_2
    //   60: iload_0
    //   61: invokevirtual charAt : (I)C
    //   64: istore_1
    //   65: goto -> 23
    //   68: ldc '/)\\rbÂ‡aÃ 2\\f\\t>Ã²/ÃƒxÃŽ'
    //   70: dup
    //   71: astore_2
    //   72: invokevirtual length : ()I
    //   75: istore #4
    //   77: bipush #9
    //   79: istore_1
    //   80: iconst_m1
    //   81: istore_0
    //   82: bipush #73
    //   84: iinc #0, 1
    //   87: aload_2
    //   88: iload_0
    //   89: dup
    //   90: iload_1
    //   91: iadd
    //   92: invokevirtual substring : (II)Ljava/lang/String;
    //   95: iconst_0
    //   96: goto -> 143
    //   99: aload #5
    //   101: swap
    //   102: iload_3
    //   103: iinc #3, 1
    //   106: swap
    //   107: aastore
    //   108: iload_0
    //   109: iload_1
    //   110: iadd
    //   111: dup
    //   112: istore_0
    //   113: iload #4
    //   115: if_icmpge -> 127
    //   118: aload_2
    //   119: iload_0
    //   120: invokevirtual charAt : (I)C
    //   123: istore_1
    //   124: goto -> 82
    //   127: aload #5
    //   129: putstatic burp/Zxaa.a : [Ljava/lang/String;
    //   132: bipush #8
    //   134: anewarray java/lang/String
    //   137: putstatic burp/Zxaa.b : [Ljava/lang/String;
    //   140: goto -> 300
    //   143: dup_x2
    //   144: pop
    //   145: invokevirtual toCharArray : ()[C
    //   148: dup_x1
    //   149: arraylength
    //   150: dup_x2
    //   151: pop
    //   152: iconst_0
    //   153: istore #6
    //   155: dup2_x1
    //   156: pop2
    //   157: dup_x2
    //   158: iconst_1
    //   159: if_icmpgt -> 259
    //   162: dup2
    //   163: swap
    //   164: iload #6
    //   166: dup2_x1
    //   167: caload
    //   168: swap
    //   169: iload #6
    //   171: bipush #7
    //   173: irem
    //   174: tableswitch default -> 241, 0 -> 212, 1 -> 217, 2 -> 222, 3 -> 227, 4 -> 232, 5 -> 237
    //   212: bipush #36
    //   214: goto -> 243
    //   217: bipush #126
    //   219: goto -> 243
    //   222: bipush #80
    //   224: goto -> 243
    //   227: bipush #67
    //   229: goto -> 243
    //   232: bipush #94
    //   234: goto -> 243
    //   237: iconst_1
    //   238: goto -> 243
    //   241: bipush #34
    //   243: ixor
    //   244: ixor
    //   245: i2c
    //   246: castore
    //   247: iinc #6, 1
    //   250: dup
    //   251: ifne -> 259
    //   254: dup2
    //   255: dup_x1
    //   256: goto -> 166
    //   259: dup2_x1
    //   260: pop2
    //   261: dup_x2
    //   262: iload #6
    //   264: if_icmpgt -> 162
    //   267: pop
    //   268: new java/lang/String
    //   271: dup_x1
    //   272: swap
    //   273: invokespecial <init> : ([C)V
    //   276: invokevirtual intern : ()Ljava/lang/String;
    //   279: swap
    //   280: pop
    //   281: swap
    //   282: tableswitch default -> 40, 0 -> 99
    //   300: sipush #24841
    //   303: sipush #6879
    //   306: invokestatic a : (II)Ljava/lang/String;
    //   309: putstatic burp/Zxaa.ZN : Ljava/lang/String;
    //   312: new java/math/BigInteger
    //   315: dup
    //   316: iconst_1
    //   317: bipush #32
    //   319: newarray byte
    //   321: dup
    //   322: iconst_0
    //   323: bipush #15
    //   325: bastore
    //   326: dup
    //   327: iconst_1
    //   328: bipush #-118
    //   330: bastore
    //   331: dup
    //   332: iconst_2
    //   333: bipush #-64
    //   335: bastore
    //   336: dup
    //   337: iconst_3
    //   338: bipush #-104
    //   340: bastore
    //   341: dup
    //   342: iconst_4
    //   343: bipush #97
    //   345: bastore
    //   346: dup
    //   347: iconst_5
    //   348: bipush #18
    //   350: bastore
    //   351: dup
    //   352: bipush #6
    //   354: bipush #18
    //   356: bastore
    //   357: dup
    //   358: bipush #7
    //   360: bipush #-52
    //   362: bastore
    //   363: dup
    //   364: bipush #8
    //   366: bipush #120
    //   368: bastore
    //   369: dup
    //   370: bipush #9
    //   372: bipush #18
    //   374: bastore
    //   375: dup
    //   376: bipush #10
    //   378: bipush #93
    //   380: bastore
    //   381: dup
    //   382: bipush #11
    //   384: bipush #-78
    //   386: bastore
    //   387: dup
    //   388: bipush #12
    //   390: bipush #-25
    //   392: bastore
    //   393: dup
    //   394: bipush #13
    //   396: bipush #-122
    //   398: bastore
    //   399: dup
    //   400: bipush #14
    //   402: bipush #-32
    //   404: bastore
    //   405: dup
    //   406: bipush #15
    //   408: bipush #67
    //   410: bastore
    //   411: dup
    //   412: bipush #16
    //   414: bipush #73
    //   416: bastore
    //   417: dup
    //   418: bipush #17
    //   420: bipush #-47
    //   422: bastore
    //   423: dup
    //   424: bipush #18
    //   426: bipush #-91
    //   428: bastore
    //   429: dup
    //   430: bipush #19
    //   432: bipush #-93
    //   434: bastore
    //   435: dup
    //   436: bipush #20
    //   438: bipush #-103
    //   440: bastore
    //   441: dup
    //   442: bipush #21
    //   444: bipush #9
    //   446: bastore
    //   447: dup
    //   448: bipush #22
    //   450: bipush #-126
    //   452: bastore
    //   453: dup
    //   454: bipush #23
    //   456: bipush #77
    //   458: bastore
    //   459: dup
    //   460: bipush #24
    //   462: bipush #-104
    //   464: bastore
    //   465: dup
    //   466: bipush #25
    //   468: bipush #-88
    //   470: bastore
    //   471: dup
    //   472: bipush #26
    //   474: bipush #84
    //   476: bastore
    //   477: dup
    //   478: bipush #27
    //   480: bipush #100
    //   482: bastore
    //   483: dup
    //   484: bipush #28
    //   486: bipush #62
    //   488: bastore
    //   489: dup
    //   490: bipush #29
    //   492: bipush #-123
    //   494: bastore
    //   495: dup
    //   496: bipush #30
    //   498: bipush #70
    //   500: bastore
    //   501: dup
    //   502: bipush #31
    //   504: bipush #-22
    //   506: bastore
    //   507: invokespecial <init> : (I[B)V
    //   510: putstatic burp/Zxaa.ZO : Ljava/lang/Object;
    //   513: return
  }
  
  private static Throwable a(Throwable paramThrowable) {
    return paramThrowable;
  }
  
  private static String a(int paramInt1, int paramInt2) {
    int i = (paramInt1 ^ 0x6109) & 0xFFFF;
    if (b[i] == null) {
      char[] arrayOfChar = a[i].toCharArray();
      switch (arrayOfChar[0] & 0xFF) {
        case 0:
        
        case 1:
        
        case 2:
        
        case 3:
        
        case 4:
        
        case 5:
        
        case 6:
        
        case 7:
        
        case 8:
        
        case 9:
        
        case 10:
        
        case 11:
        
        case 12:
        
        case 13:
        
        case 14:
        
        case 15:
        
        case 16:
        
        case 17:
        
        case 18:
        
        case 19:
        
        case 20:
        
        case 21:
        
        case 22:
        
        case 23:
        
        case 24:
        
        case 25:
        
        case 26:
        
        case 27:
        
        case 28:
        
        case 29:
        
        case 30:
        
        case 31:
        
        case 32:
        
        case 33:
        
        case 34:
        
        case 35:
        
        case 36:
        
        case 37:
        
        case 38:
        
        case 39:
        
        case 40:
        
        case 41:
        
        case 42:
        
        case 43:
        
        case 44:
        
        case 45:
        
        case 46:
        
        case 47:
        
        case 48:
        
        case 49:
        
        case 50:
        
        case 51:
        
        case 52:
        
        case 53:
        
        case 54:
        
        case 55:
        
        case 56:
        
        case 57:
        
        case 58:
        
        case 59:
        
        case 60:
        
        case 61:
        
        case 62:
        
        case 63:
        
        case 64:
        
        case 65:
        
        case 66:
        
        case 67:
        
        case 68:
        
        case 69:
        
        case 70:
        
        case 71:
        
        case 72:
        
        case 73:
        
        case 74:
        
        case 75:
        
        case 76:
        
        case 77:
        
        case 78:
        
        case 79:
        
        case 80:
        
        case 81:
        
        case 82:
        
        case 83:
        
        case 84:
        
        case 85:
        
        case 86:
        
        case 87:
        
        case 88:
        
        case 89:
        
        case 90:
        
        case 91:
        
        case 92:
        
        case 93:
        
        case 94:
        
        case 95:
        
        case 96:
        
        case 97:
        
        case 98:
        
        case 99:
        
        case 100:
        
        case 101:
        
        case 102:
        
        case 103:
        
        case 104:
        
        case 105:
        
        case 106:
        
        case 107:
        
        case 108:
        
        case 109:
        
        case 110:
        
        case 111:
        
        case 112:
        
        case 113:
        
        case 114:
        
        case 115:
        
        case 116:
        
        case 117:
        
        case 118:
        
        case 119:
        
        case 120:
        
        case 121:
        
        case 122:
        
        case 123:
        
        case 124:
        
        case 125:
        
        case 126:
        
        case 127:
        
        case 128:
        
        case 129:
        
        case 130:
        
        case 131:
        
        case 132:
        
        case 133:
        
        case 134:
        
        case 135:
        
        case 136:
        
        case 137:
        
        case 138:
        
        case 139:
        
        case 140:
        
        case 141:
        
        case 142:
        
        case 143:
        
        case 144:
        
        case 145:
        
        case 146:
        
        case 147:
        
        case 148:
        
        case 149:
        
        case 150:
        
        case 151:
        
        case 152:
        
        case 153:
        
        case 154:
        
        case 155:
        
        case 156:
        
        case 157:
        
        case 158:
        
        case 159:
        
        case 160:
        
        case 161:
        
        case 162:
        
        case 163:
        
        case 164:
        
        case 165:
        
        case 166:
        
        case 167:
        
        case 168:
        
        case 169:
        
        case 170:
        
        case 171:
        
        case 172:
        
        case 173:
        
        case 174:
        
        case 175:
        
        case 176:
        
        case 177:
        
        case 178:
        
        case 179:
        
        case 180:
        
        case 181:
        
        case 182:
        
        case 183:
        
        case 184:
        
        case 185:
        
        case 186:
        
        case 187:
        
        case 188:
        
        case 189:
        
        case 190:
        
        case 191:
        
        case 192:
        
        case 193:
        
        case 194:
        
        case 195:
        
        case 196:
        
        case 197:
        
        case 198:
        
        case 199:
        
        case 200:
        
        case 201:
        
        case 202:
        
        case 203:
        
        case 204:
        
        case 205:
        
        case 206:
        
        case 207:
        
        case 208:
        
        case 209:
        
        case 210:
        
        case 211:
        
        case 212:
        
        case 213:
        
        case 214:
        
        case 215:
        
        case 216:
        
        case 217:
        
        case 218:
        
        case 219:
        
        case 220:
        
        case 221:
        
        case 222:
        
        case 223:
        
        case 224:
        
        case 225:
        
        case 226:
        
        case 227:
        
        case 228:
        
        case 229:
        
        case 230:
        
        case 231:
        
        case 232:
        
        case 233:
        
        case 234:
        
        case 235:
        
        case 236:
        
        case 237:
        
        case 238:
        
        case 239:
        
        case 240:
        
        case 241:
        
        case 242:
        
        case 243:
        
        case 244:
        
        case 245:
        
        case 246:
        
        case 247:
        
        case 248:
        
        case 249:
        
        case 250:
        
        case 251:
        
        case 252:
        
        case 253:
        
        case 254:
        
        default:
          break;
      } 
      char c = 'Â¼';
      int j = (paramInt2 & 0xFF) - c;
      if (j < 0)
        j += 256; 
      int k = ((paramInt2 & 0xFFFF) >>> 8) - c;
      if (k < 0)
        k += 256; 
      for (byte b = 0; b < arrayOfChar.length; b++) {
        int m = b % 2;
        if (m == 0) {
          arrayOfChar[b] = (char)(arrayOfChar[b] ^ j);
          j = ((j >>> 3 | j << 5) ^ arrayOfChar[b]) & 0xFF;
        } else {
          arrayOfChar[b] = (char)(arrayOfChar[b] ^ k);
          k = ((k >>> 3 | k << 5) ^ arrayOfChar[b]) & 0xFF;
        } 
      } 
      b[i] = (new String(arrayOfChar)).intern();
    } 
    return b[i];
  }
}


/* Location:              C:\Program Files\BurpSuitePro\burpsuite_pro.jar!\burp\Zxaa.class
 * Java compiler version: 21 (65.0)
 * JD-Core Version:       1.1.3
 */