package burp;

import java.math.BigInteger;

class Zxc0 extends ClassLoader {
  static String Zh;
  
  static Object Zl;
  
  private static final String[] a;
  
  private static final String[] b;
  
  static void Zn(Object[] paramArrayOfObject, Object paramObject) throws Throwable {}
  
  static void Zt(Object paramObject) {
    Zt5t.ZK = a(-14207, 28470);
    Zt5t.Za = new BigInteger(a(-14196, -30489));
    boolean bool = Zt2e.ZK();
    try {
      try {
        if (Zzhx.ZV.charAt(Math.abs(((BigInteger)Zz4j.Zu).intValue() % 32)) <= Zxxf.Zw.charAt(Math.abs(((BigInteger)Zsjc.ZX).intValue() % 32))) {
          try {
            Zx4w.Zi(Class.forName(a(-14197, 6609)));
            if (bool)
              Ze2k.ZU(Class.forName(a(-14203, 9069))); 
          } catch (Throwable throwable) {
            throw a(null);
          } 
          return;
        } 
      } catch (Throwable throwable) {
        throw a(null);
      } 
      Ze2k.ZU(Class.forName(a(-14203, 9069)));
    } catch (Throwable throwable) {}
  }
  
  static boolean Zp(Object[] paramArrayOfObject, Object paramObject) throws Throwable {
    // Byte code:
    //   0: invokestatic ZK : ()Z
    //   3: istore_2
    //   4: getstatic burp/Zl1e.Zp : Ljava/lang/Object;
    //   7: checkcast java/math/BigInteger
    //   10: invokevirtual toByteArray : ()[B
    //   13: astore_3
    //   14: aload_3
    //   15: arraylength
    //   16: iconst_2
    //   17: iadd
    //   18: newarray byte
    //   20: astore #5
    //   22: iconst_0
    //   23: istore #6
    //   25: iload #6
    //   27: aload_3
    //   28: arraylength
    //   29: if_icmpge -> 48
    //   32: aload #5
    //   34: iload #6
    //   36: aload_3
    //   37: iload #6
    //   39: baload
    //   40: bastore
    //   41: iinc #6, 1
    //   44: iload_2
    //   45: ifeq -> 25
    //   48: aload #5
    //   50: arraylength
    //   51: iconst_3
    //   52: idiv
    //   53: iconst_4
    //   54: imul
    //   55: newarray byte
    //   57: astore #4
    //   59: iconst_0
    //   60: istore #6
    //   62: iconst_0
    //   63: istore #7
    //   65: iload #6
    //   67: aload_3
    //   68: arraylength
    //   69: if_icmpge -> 180
    //   72: aload #4
    //   74: iload #7
    //   76: aload #5
    //   78: iload #6
    //   80: baload
    //   81: iconst_2
    //   82: iushr
    //   83: bipush #63
    //   85: iand
    //   86: i2b
    //   87: bastore
    //   88: aload #4
    //   90: iload #7
    //   92: iconst_1
    //   93: iadd
    //   94: aload #5
    //   96: iload #6
    //   98: iconst_1
    //   99: iadd
    //   100: baload
    //   101: iconst_4
    //   102: iushr
    //   103: bipush #15
    //   105: iand
    //   106: aload #5
    //   108: iload #6
    //   110: baload
    //   111: iconst_4
    //   112: ishl
    //   113: bipush #63
    //   115: iand
    //   116: ior
    //   117: i2b
    //   118: bastore
    //   119: aload #4
    //   121: iload #7
    //   123: iconst_2
    //   124: iadd
    //   125: aload #5
    //   127: iload #6
    //   129: iconst_2
    //   130: iadd
    //   131: baload
    //   132: bipush #6
    //   134: iushr
    //   135: iconst_3
    //   136: iand
    //   137: aload #5
    //   139: iload #6
    //   141: iconst_1
    //   142: iadd
    //   143: baload
    //   144: iconst_2
    //   145: ishl
    //   146: bipush #63
    //   148: iand
    //   149: ior
    //   150: i2b
    //   151: bastore
    //   152: aload #4
    //   154: iload #7
    //   156: iconst_3
    //   157: iadd
    //   158: aload #5
    //   160: iload #6
    //   162: iconst_2
    //   163: iadd
    //   164: baload
    //   165: bipush #63
    //   167: iand
    //   168: i2b
    //   169: bastore
    //   170: iinc #6, 3
    //   173: iinc #7, 4
    //   176: iload_2
    //   177: ifeq -> 65
    //   180: iconst_0
    //   181: istore #6
    //   183: iload #6
    //   185: aload #4
    //   187: arraylength
    //   188: if_icmpge -> 372
    //   191: aload #4
    //   193: iload #6
    //   195: baload
    //   196: bipush #26
    //   198: if_icmpge -> 226
    //   201: aload #4
    //   203: iload #6
    //   205: aload #4
    //   207: iload #6
    //   209: baload
    //   210: bipush #65
    //   212: iadd
    //   213: i2b
    //   214: bastore
    //   215: iload_2
    //   216: ifeq -> 365
    //   219: goto -> 226
    //   222: invokestatic a : (Ljava/lang/Throwable;)Ljava/lang/Throwable;
    //   225: athrow
    //   226: aload #4
    //   228: iload #6
    //   230: baload
    //   231: bipush #52
    //   233: if_icmpge -> 271
    //   236: goto -> 243
    //   239: invokestatic a : (Ljava/lang/Throwable;)Ljava/lang/Throwable;
    //   242: athrow
    //   243: aload #4
    //   245: iload #6
    //   247: aload #4
    //   249: iload #6
    //   251: baload
    //   252: bipush #97
    //   254: iadd
    //   255: bipush #26
    //   257: isub
    //   258: i2b
    //   259: bastore
    //   260: iload_2
    //   261: ifeq -> 365
    //   264: goto -> 271
    //   267: invokestatic a : (Ljava/lang/Throwable;)Ljava/lang/Throwable;
    //   270: athrow
    //   271: aload #4
    //   273: iload #6
    //   275: baload
    //   276: bipush #62
    //   278: if_icmpge -> 316
    //   281: goto -> 288
    //   284: invokestatic a : (Ljava/lang/Throwable;)Ljava/lang/Throwable;
    //   287: athrow
    //   288: aload #4
    //   290: iload #6
    //   292: aload #4
    //   294: iload #6
    //   296: baload
    //   297: bipush #48
    //   299: iadd
    //   300: bipush #52
    //   302: isub
    //   303: i2b
    //   304: bastore
    //   305: iload_2
    //   306: ifeq -> 365
    //   309: goto -> 316
    //   312: invokestatic a : (Ljava/lang/Throwable;)Ljava/lang/Throwable;
    //   315: athrow
    //   316: aload #4
    //   318: iload #6
    //   320: baload
    //   321: bipush #63
    //   323: if_icmpge -> 351
    //   326: goto -> 333
    //   329: invokestatic a : (Ljava/lang/Throwable;)Ljava/lang/Throwable;
    //   332: athrow
    //   333: aload #4
    //   335: iload #6
    //   337: bipush #43
    //   339: bastore
    //   340: iload_2
    //   341: ifeq -> 365
    //   344: goto -> 351
    //   347: invokestatic a : (Ljava/lang/Throwable;)Ljava/lang/Throwable;
    //   350: athrow
    //   351: aload #4
    //   353: iload #6
    //   355: bipush #47
    //   357: bastore
    //   358: goto -> 365
    //   361: invokestatic a : (Ljava/lang/Throwable;)Ljava/lang/Throwable;
    //   364: athrow
    //   365: iinc #6, 1
    //   368: iload_2
    //   369: ifeq -> 183
    //   372: aload #4
    //   374: arraylength
    //   375: iconst_1
    //   376: isub
    //   377: istore #6
    //   379: iload #6
    //   381: aload_3
    //   382: arraylength
    //   383: iconst_4
    //   384: imul
    //   385: iconst_3
    //   386: idiv
    //   387: if_icmple -> 404
    //   390: aload #4
    //   392: iload #6
    //   394: bipush #61
    //   396: bastore
    //   397: iinc #6, -1
    //   400: iload_2
    //   401: ifeq -> 379
    //   404: new java/math/BigInteger
    //   407: dup
    //   408: aload #4
    //   410: invokespecial <init> : ([B)V
    //   413: invokevirtual abs : ()Ljava/math/BigInteger;
    //   416: putstatic burp/Zk8f.ZG : Ljava/lang/Object;
    //   419: getstatic burp/Zt6z.Zl : Ljava/lang/Object;
    //   422: checkcast java/math/BigInteger
    //   425: invokevirtual toByteArray : ()[B
    //   428: astore_3
    //   429: new java/lang/StringBuilder
    //   432: dup
    //   433: invokespecial <init> : ()V
    //   436: astore #5
    //   438: aload #5
    //   440: sipush #-14195
    //   443: sipush #-18545
    //   446: invokestatic a : (II)Ljava/lang/String;
    //   449: invokevirtual append : (Ljava/lang/String;)Ljava/lang/StringBuilder;
    //   452: pop
    //   453: aload_3
    //   454: astore #6
    //   456: aload #6
    //   458: arraylength
    //   459: istore #7
    //   461: iconst_0
    //   462: istore #8
    //   464: iload #8
    //   466: iload #7
    //   468: if_icmpge -> 494
    //   471: aload #6
    //   473: iload #8
    //   475: baload
    //   476: istore #9
    //   478: aload #5
    //   480: iload #9
    //   482: i2c
    //   483: invokevirtual append : (C)Ljava/lang/StringBuilder;
    //   486: pop
    //   487: iinc #8, 1
    //   490: iload_2
    //   491: ifeq -> 464
    //   494: aload #5
    //   496: sipush #-14198
    //   499: sipush #16934
    //   502: invokestatic a : (II)Ljava/lang/String;
    //   505: ldc ''
    //   507: invokestatic getProperty : (Ljava/lang/String;Ljava/lang/String;)Ljava/lang/String;
    //   510: invokevirtual toLowerCase : ()Ljava/lang/String;
    //   513: invokevirtual append : (Ljava/lang/String;)Ljava/lang/StringBuilder;
    //   516: pop
    //   517: aload #5
    //   519: sipush #-14201
    //   522: sipush #8958
    //   525: invokestatic a : (II)Ljava/lang/String;
    //   528: ldc ''
    //   530: invokestatic getProperty : (Ljava/lang/String;Ljava/lang/String;)Ljava/lang/String;
    //   533: invokevirtual toLowerCase : ()Ljava/lang/String;
    //   536: invokevirtual append : (Ljava/lang/String;)Ljava/lang/StringBuilder;
    //   539: pop
    //   540: aload #5
    //   542: invokevirtual toString : ()Ljava/lang/String;
    //   545: invokevirtual getBytes : ()[B
    //   548: astore #4
    //   550: aload #4
    //   552: astore_3
    //   553: aload_3
    //   554: arraylength
    //   555: bipush #8
    //   557: iadd
    //   558: bipush #6
    //   560: ishr
    //   561: iconst_1
    //   562: iadd
    //   563: bipush #16
    //   565: imul
    //   566: newarray int
    //   568: astore #5
    //   570: iconst_0
    //   571: istore #6
    //   573: iload #6
    //   575: aload_3
    //   576: arraylength
    //   577: if_icmpge -> 620
    //   580: aload_3
    //   581: iload #6
    //   583: baload
    //   584: sipush #255
    //   587: iand
    //   588: istore #7
    //   590: aload #5
    //   592: iload #6
    //   594: iconst_2
    //   595: ishr
    //   596: dup2
    //   597: iaload
    //   598: iload #7
    //   600: bipush #24
    //   602: iload #6
    //   604: iconst_4
    //   605: irem
    //   606: bipush #8
    //   608: imul
    //   609: isub
    //   610: ishl
    //   611: ior
    //   612: iastore
    //   613: iinc #6, 1
    //   616: iload_2
    //   617: ifeq -> 573
    //   620: aload #5
    //   622: iload #6
    //   624: iconst_2
    //   625: ishr
    //   626: dup2
    //   627: iaload
    //   628: sipush #128
    //   631: bipush #24
    //   633: iload #6
    //   635: iconst_4
    //   636: irem
    //   637: bipush #8
    //   639: imul
    //   640: isub
    //   641: ishl
    //   642: ior
    //   643: iastore
    //   644: aload #5
    //   646: aload #5
    //   648: arraylength
    //   649: iconst_1
    //   650: isub
    //   651: aload_3
    //   652: arraylength
    //   653: bipush #8
    //   655: imul
    //   656: iastore
    //   657: bipush #80
    //   659: newarray int
    //   661: astore #7
    //   663: ldc 1732584193
    //   665: istore #8
    //   667: ldc -271733879
    //   669: istore #9
    //   671: ldc -1732584194
    //   673: istore #10
    //   675: ldc 271733878
    //   677: istore #11
    //   679: ldc -1009589776
    //   681: istore #12
    //   683: iconst_0
    //   684: istore #6
    //   686: iload #6
    //   688: aload #5
    //   690: arraylength
    //   691: if_icmpge -> 1013
    //   694: iload #8
    //   696: istore #13
    //   698: iload #9
    //   700: istore #14
    //   702: iload #10
    //   704: istore #15
    //   706: iload #11
    //   708: istore #16
    //   710: iload #12
    //   712: istore #17
    //   714: iconst_0
    //   715: istore #18
    //   717: iload #18
    //   719: bipush #80
    //   721: if_icmpge -> 971
    //   724: iload #18
    //   726: bipush #16
    //   728: if_icmpge -> 755
    //   731: aload #7
    //   733: iload #18
    //   735: aload #5
    //   737: iload #6
    //   739: iload #18
    //   741: iadd
    //   742: iaload
    //   743: iastore
    //   744: iload_2
    //   745: ifeq -> 810
    //   748: goto -> 755
    //   751: invokestatic a : (Ljava/lang/Throwable;)Ljava/lang/Throwable;
    //   754: athrow
    //   755: aload #7
    //   757: iload #18
    //   759: iconst_3
    //   760: isub
    //   761: iaload
    //   762: aload #7
    //   764: iload #18
    //   766: bipush #8
    //   768: isub
    //   769: iaload
    //   770: ixor
    //   771: aload #7
    //   773: iload #18
    //   775: bipush #14
    //   777: isub
    //   778: iaload
    //   779: ixor
    //   780: aload #7
    //   782: iload #18
    //   784: bipush #16
    //   786: isub
    //   787: iaload
    //   788: ixor
    //   789: istore #19
    //   791: iload #19
    //   793: iconst_1
    //   794: ishl
    //   795: iload #19
    //   797: bipush #31
    //   799: iushr
    //   800: ior
    //   801: istore #20
    //   803: aload #7
    //   805: iload #18
    //   807: iload #20
    //   809: iastore
    //   810: iload #8
    //   812: iconst_5
    //   813: ishl
    //   814: iload #8
    //   816: bipush #27
    //   818: iushr
    //   819: ior
    //   820: istore #19
    //   822: iload #19
    //   824: iload #12
    //   826: iadd
    //   827: aload #7
    //   829: iload #18
    //   831: iaload
    //   832: iadd
    //   833: iload #18
    //   835: bipush #20
    //   837: if_icmpge -> 863
    //   840: ldc 1518500249
    //   842: iload #9
    //   844: iload #10
    //   846: iand
    //   847: iload #9
    //   849: iconst_m1
    //   850: ixor
    //   851: iload #11
    //   853: iand
    //   854: ior
    //   855: iadd
    //   856: goto -> 933
    //   859: invokestatic a : (Ljava/lang/Throwable;)Ljava/lang/Throwable;
    //   862: athrow
    //   863: iload #18
    //   865: bipush #40
    //   867: if_icmpge -> 888
    //   870: ldc 1859775393
    //   872: iload #9
    //   874: iload #10
    //   876: ixor
    //   877: iload #11
    //   879: ixor
    //   880: iadd
    //   881: goto -> 933
    //   884: invokestatic a : (Ljava/lang/Throwable;)Ljava/lang/Throwable;
    //   887: athrow
    //   888: iload #18
    //   890: bipush #60
    //   892: if_icmpge -> 922
    //   895: ldc -1894007588
    //   897: iload #9
    //   899: iload #10
    //   901: iand
    //   902: iload #9
    //   904: iload #11
    //   906: iand
    //   907: ior
    //   908: iload #10
    //   910: iload #11
    //   912: iand
    //   913: ior
    //   914: iadd
    //   915: goto -> 933
    //   918: invokestatic a : (Ljava/lang/Throwable;)Ljava/lang/Throwable;
    //   921: athrow
    //   922: ldc -899497514
    //   924: iload #9
    //   926: iload #10
    //   928: ixor
    //   929: iload #11
    //   931: ixor
    //   932: iadd
    //   933: iadd
    //   934: istore #20
    //   936: iload #11
    //   938: istore #12
    //   940: iload #10
    //   942: istore #11
    //   944: iload #9
    //   946: bipush #30
    //   948: ishl
    //   949: iload #9
    //   951: iconst_2
    //   952: iushr
    //   953: ior
    //   954: istore #10
    //   956: iload #8
    //   958: istore #9
    //   960: iload #20
    //   962: istore #8
    //   964: iinc #18, 1
    //   967: iload_2
    //   968: ifeq -> 717
    //   971: iload #8
    //   973: iload #13
    //   975: iadd
    //   976: istore #8
    //   978: iload #9
    //   980: iload #14
    //   982: iadd
    //   983: istore #9
    //   985: iload #10
    //   987: iload #15
    //   989: iadd
    //   990: istore #10
    //   992: iload #11
    //   994: iload #16
    //   996: iadd
    //   997: istore #11
    //   999: iload #12
    //   1001: iload #17
    //   1003: iadd
    //   1004: istore #12
    //   1006: iinc #6, 16
    //   1009: iload_2
    //   1010: ifeq -> 686
    //   1013: iconst_5
    //   1014: newarray int
    //   1016: dup
    //   1017: iconst_0
    //   1018: iload #8
    //   1020: iastore
    //   1021: dup
    //   1022: iconst_1
    //   1023: iload #9
    //   1025: iastore
    //   1026: dup
    //   1027: iconst_2
    //   1028: iload #10
    //   1030: iastore
    //   1031: dup
    //   1032: iconst_3
    //   1033: iload #11
    //   1035: iastore
    //   1036: dup
    //   1037: iconst_4
    //   1038: iload #12
    //   1040: iastore
    //   1041: astore #13
    //   1043: bipush #20
    //   1045: newarray byte
    //   1047: astore #14
    //   1049: iconst_0
    //   1050: istore #15
    //   1052: iload #15
    //   1054: bipush #20
    //   1056: if_icmpge -> 1097
    //   1059: aload #13
    //   1061: iload #15
    //   1063: iconst_4
    //   1064: idiv
    //   1065: iaload
    //   1066: istore #16
    //   1068: iconst_3
    //   1069: iload #15
    //   1071: iconst_4
    //   1072: irem
    //   1073: isub
    //   1074: bipush #8
    //   1076: imul
    //   1077: istore #17
    //   1079: aload #14
    //   1081: iload #15
    //   1083: iload #16
    //   1085: iload #17
    //   1087: iushr
    //   1088: i2b
    //   1089: bastore
    //   1090: iinc #15, 1
    //   1093: iload_2
    //   1094: ifeq -> 1052
    //   1097: aload #14
    //   1099: astore #4
    //   1101: new java/lang/StringBuilder
    //   1104: dup
    //   1105: invokespecial <init> : ()V
    //   1108: astore_3
    //   1109: iconst_0
    //   1110: istore #4
    //   1112: iload #4
    //   1114: bipush #32
    //   1116: if_icmpge -> 2451
    //   1119: iload #4
    //   1121: tableswitch default -> 2444, 0 -> 1264, 1 -> 1301, 2 -> 1338, 3 -> 1375, 4 -> 1412, 5 -> 1449, 6 -> 1486, 7 -> 1523, 8 -> 1560, 9 -> 1597, 10 -> 1634, 11 -> 1671, 12 -> 1708, 13 -> 1745, 14 -> 1782, 15 -> 1819, 16 -> 1856, 17 -> 1893, 18 -> 1930, 19 -> 1967, 20 -> 2004, 21 -> 2041, 22 -> 2078, 23 -> 2115, 24 -> 2152, 25 -> 2189, 26 -> 2226, 27 -> 2263, 28 -> 2300, 29 -> 2337, 30 -> 2374, 31 -> 2411
    //   1264: aload_3
    //   1265: getstatic burp/Zlid.ZU : Ljava/lang/String;
    //   1268: getstatic burp/Zrp2.Zw : Ljava/lang/Object;
    //   1271: checkcast java/math/BigInteger
    //   1274: invokevirtual intValue : ()I
    //   1277: bipush #32
    //   1279: irem
    //   1280: invokestatic abs : (I)I
    //   1283: invokevirtual charAt : (I)C
    //   1286: invokevirtual append : (C)Ljava/lang/StringBuilder;
    //   1289: pop
    //   1290: iload_2
    //   1291: ifeq -> 2444
    //   1294: goto -> 1301
    //   1297: invokestatic a : (Ljava/lang/Throwable;)Ljava/lang/Throwable;
    //   1300: athrow
    //   1301: aload_3
    //   1302: getstatic burp/Zea.Zj : Ljava/lang/String;
    //   1305: getstatic burp/Zmll.ZU : Ljava/lang/Object;
    //   1308: checkcast java/math/BigInteger
    //   1311: invokevirtual intValue : ()I
    //   1314: bipush #32
    //   1316: irem
    //   1317: invokestatic abs : (I)I
    //   1320: invokevirtual charAt : (I)C
    //   1323: invokevirtual append : (C)Ljava/lang/StringBuilder;
    //   1326: pop
    //   1327: iload_2
    //   1328: ifeq -> 2444
    //   1331: goto -> 1338
    //   1334: invokestatic a : (Ljava/lang/Throwable;)Ljava/lang/Throwable;
    //   1337: athrow
    //   1338: aload_3
    //   1339: getstatic burp/Ztr5.ZY : Ljava/lang/String;
    //   1342: getstatic burp/Zti7.Zw : Ljava/lang/Object;
    //   1345: checkcast java/math/BigInteger
    //   1348: invokevirtual intValue : ()I
    //   1351: bipush #32
    //   1353: irem
    //   1354: invokestatic abs : (I)I
    //   1357: invokevirtual charAt : (I)C
    //   1360: invokevirtual append : (C)Ljava/lang/StringBuilder;
    //   1363: pop
    //   1364: iload_2
    //   1365: ifeq -> 2444
    //   1368: goto -> 1375
    //   1371: invokestatic a : (Ljava/lang/Throwable;)Ljava/lang/Throwable;
    //   1374: athrow
    //   1375: aload_3
    //   1376: getstatic burp/Zzna.Zi : Ljava/lang/String;
    //   1379: getstatic burp/Zbw5.ZR : Ljava/lang/Object;
    //   1382: checkcast java/math/BigInteger
    //   1385: invokevirtual intValue : ()I
    //   1388: bipush #32
    //   1390: irem
    //   1391: invokestatic abs : (I)I
    //   1394: invokevirtual charAt : (I)C
    //   1397: invokevirtual append : (C)Ljava/lang/StringBuilder;
    //   1400: pop
    //   1401: iload_2
    //   1402: ifeq -> 2444
    //   1405: goto -> 1412
    //   1408: invokestatic a : (Ljava/lang/Throwable;)Ljava/lang/Throwable;
    //   1411: athrow
    //   1412: aload_3
    //   1413: getstatic burp/Zm69.ZE : Ljava/lang/String;
    //   1416: getstatic burp/Zgis.ZV : Ljava/lang/Object;
    //   1419: checkcast java/math/BigInteger
    //   1422: invokevirtual intValue : ()I
    //   1425: bipush #32
    //   1427: irem
    //   1428: invokestatic abs : (I)I
    //   1431: invokevirtual charAt : (I)C
    //   1434: invokevirtual append : (C)Ljava/lang/StringBuilder;
    //   1437: pop
    //   1438: iload_2
    //   1439: ifeq -> 2444
    //   1442: goto -> 1449
    //   1445: invokestatic a : (Ljava/lang/Throwable;)Ljava/lang/Throwable;
    //   1448: athrow
    //   1449: aload_3
    //   1450: getstatic burp/Zeub.ZT : Ljava/lang/String;
    //   1453: getstatic burp/Zex0.Ze : Ljava/lang/Object;
    //   1456: checkcast java/math/BigInteger
    //   1459: invokevirtual intValue : ()I
    //   1462: bipush #32
    //   1464: irem
    //   1465: invokestatic abs : (I)I
    //   1468: invokevirtual charAt : (I)C
    //   1471: invokevirtual append : (C)Ljava/lang/StringBuilder;
    //   1474: pop
    //   1475: iload_2
    //   1476: ifeq -> 2444
    //   1479: goto -> 1486
    //   1482: invokestatic a : (Ljava/lang/Throwable;)Ljava/lang/Throwable;
    //   1485: athrow
    //   1486: aload_3
    //   1487: getstatic burp/Zek4.Zo : Ljava/lang/String;
    //   1490: getstatic burp/Zmn0.Zo : Ljava/lang/Object;
    //   1493: checkcast java/math/BigInteger
    //   1496: invokevirtual intValue : ()I
    //   1499: bipush #32
    //   1501: irem
    //   1502: invokestatic abs : (I)I
    //   1505: invokevirtual charAt : (I)C
    //   1508: invokevirtual append : (C)Ljava/lang/StringBuilder;
    //   1511: pop
    //   1512: iload_2
    //   1513: ifeq -> 2444
    //   1516: goto -> 1523
    //   1519: invokestatic a : (Ljava/lang/Throwable;)Ljava/lang/Throwable;
    //   1522: athrow
    //   1523: aload_3
    //   1524: getstatic burp/Zbze.ZK : Ljava/lang/String;
    //   1527: getstatic burp/Zry1.Zf : Ljava/lang/Object;
    //   1530: checkcast java/math/BigInteger
    //   1533: invokevirtual intValue : ()I
    //   1536: bipush #32
    //   1538: irem
    //   1539: invokestatic abs : (I)I
    //   1542: invokevirtual charAt : (I)C
    //   1545: invokevirtual append : (C)Ljava/lang/StringBuilder;
    //   1548: pop
    //   1549: iload_2
    //   1550: ifeq -> 2444
    //   1553: goto -> 1560
    //   1556: invokestatic a : (Ljava/lang/Throwable;)Ljava/lang/Throwable;
    //   1559: athrow
    //   1560: aload_3
    //   1561: getstatic burp/Zti7.Zc : Ljava/lang/String;
    //   1564: getstatic burp/Ztq4.ZA : Ljava/lang/Object;
    //   1567: checkcast java/math/BigInteger
    //   1570: invokevirtual intValue : ()I
    //   1573: bipush #32
    //   1575: irem
    //   1576: invokestatic abs : (I)I
    //   1579: invokevirtual charAt : (I)C
    //   1582: invokevirtual append : (C)Ljava/lang/StringBuilder;
    //   1585: pop
    //   1586: iload_2
    //   1587: ifeq -> 2444
    //   1590: goto -> 1597
    //   1593: invokestatic a : (Ljava/lang/Throwable;)Ljava/lang/Throwable;
    //   1596: athrow
    //   1597: aload_3
    //   1598: getstatic burp/Zedu.ZD : Ljava/lang/String;
    //   1601: getstatic burp/Zgeq.ZT : Ljava/lang/Object;
    //   1604: checkcast java/math/BigInteger
    //   1607: invokevirtual intValue : ()I
    //   1610: bipush #32
    //   1612: irem
    //   1613: invokestatic abs : (I)I
    //   1616: invokevirtual charAt : (I)C
    //   1619: invokevirtual append : (C)Ljava/lang/StringBuilder;
    //   1622: pop
    //   1623: iload_2
    //   1624: ifeq -> 2444
    //   1627: goto -> 1634
    //   1630: invokestatic a : (Ljava/lang/Throwable;)Ljava/lang/Throwable;
    //   1633: athrow
    //   1634: aload_3
    //   1635: getstatic burp/Ze84.Zv : Ljava/lang/String;
    //   1638: getstatic burp/Zt5t.Za : Ljava/lang/Object;
    //   1641: checkcast java/math/BigInteger
    //   1644: invokevirtual intValue : ()I
    //   1647: bipush #32
    //   1649: irem
    //   1650: invokestatic abs : (I)I
    //   1653: invokevirtual charAt : (I)C
    //   1656: invokevirtual append : (C)Ljava/lang/StringBuilder;
    //   1659: pop
    //   1660: iload_2
    //   1661: ifeq -> 2444
    //   1664: goto -> 1671
    //   1667: invokestatic a : (Ljava/lang/Throwable;)Ljava/lang/Throwable;
    //   1670: athrow
    //   1671: aload_3
    //   1672: getstatic burp/Ze6w.ZY : Ljava/lang/String;
    //   1675: getstatic burp/Zlxw.Zi : Ljava/lang/Object;
    //   1678: checkcast java/math/BigInteger
    //   1681: invokevirtual intValue : ()I
    //   1684: bipush #32
    //   1686: irem
    //   1687: invokestatic abs : (I)I
    //   1690: invokevirtual charAt : (I)C
    //   1693: invokevirtual append : (C)Ljava/lang/StringBuilder;
    //   1696: pop
    //   1697: iload_2
    //   1698: ifeq -> 2444
    //   1701: goto -> 1708
    //   1704: invokestatic a : (Ljava/lang/Throwable;)Ljava/lang/Throwable;
    //   1707: athrow
    //   1708: aload_3
    //   1709: getstatic burp/Zlwj.ZQ : Ljava/lang/String;
    //   1712: getstatic burp/Zz4j.Zu : Ljava/lang/Object;
    //   1715: checkcast java/math/BigInteger
    //   1718: invokevirtual intValue : ()I
    //   1721: bipush #32
    //   1723: irem
    //   1724: invokestatic abs : (I)I
    //   1727: invokevirtual charAt : (I)C
    //   1730: invokevirtual append : (C)Ljava/lang/StringBuilder;
    //   1733: pop
    //   1734: iload_2
    //   1735: ifeq -> 2444
    //   1738: goto -> 1745
    //   1741: invokestatic a : (Ljava/lang/Throwable;)Ljava/lang/Throwable;
    //   1744: athrow
    //   1745: aload_3
    //   1746: getstatic burp/Zz4m.ZI : Ljava/lang/String;
    //   1749: getstatic burp/Zedq.Zy : Ljava/lang/Object;
    //   1752: checkcast java/math/BigInteger
    //   1755: invokevirtual intValue : ()I
    //   1758: bipush #32
    //   1760: irem
    //   1761: invokestatic abs : (I)I
    //   1764: invokevirtual charAt : (I)C
    //   1767: invokevirtual append : (C)Ljava/lang/StringBuilder;
    //   1770: pop
    //   1771: iload_2
    //   1772: ifeq -> 2444
    //   1775: goto -> 1782
    //   1778: invokestatic a : (Ljava/lang/Throwable;)Ljava/lang/Throwable;
    //   1781: athrow
    //   1782: aload_3
    //   1783: getstatic burp/Zbss.ZV : Ljava/lang/String;
    //   1786: getstatic burp/Zzht.Zb : Ljava/lang/Object;
    //   1789: checkcast java/math/BigInteger
    //   1792: invokevirtual intValue : ()I
    //   1795: bipush #32
    //   1797: irem
    //   1798: invokestatic abs : (I)I
    //   1801: invokevirtual charAt : (I)C
    //   1804: invokevirtual append : (C)Ljava/lang/StringBuilder;
    //   1807: pop
    //   1808: iload_2
    //   1809: ifeq -> 2444
    //   1812: goto -> 1819
    //   1815: invokestatic a : (Ljava/lang/Throwable;)Ljava/lang/Throwable;
    //   1818: athrow
    //   1819: aload_3
    //   1820: getstatic burp/Zb4d.ZS : Ljava/lang/String;
    //   1823: getstatic burp/Zs1d.Zo : Ljava/lang/Object;
    //   1826: checkcast java/math/BigInteger
    //   1829: invokevirtual intValue : ()I
    //   1832: bipush #32
    //   1834: irem
    //   1835: invokestatic abs : (I)I
    //   1838: invokevirtual charAt : (I)C
    //   1841: invokevirtual append : (C)Ljava/lang/StringBuilder;
    //   1844: pop
    //   1845: iload_2
    //   1846: ifeq -> 2444
    //   1849: goto -> 1856
    //   1852: invokestatic a : (Ljava/lang/Throwable;)Ljava/lang/Throwable;
    //   1855: athrow
    //   1856: aload_3
    //   1857: getstatic burp/Zsvd.ZB : Ljava/lang/String;
    //   1860: getstatic burp/Zegj.ZT : Ljava/lang/Object;
    //   1863: checkcast java/math/BigInteger
    //   1866: invokevirtual intValue : ()I
    //   1869: bipush #32
    //   1871: irem
    //   1872: invokestatic abs : (I)I
    //   1875: invokevirtual charAt : (I)C
    //   1878: invokevirtual append : (C)Ljava/lang/StringBuilder;
    //   1881: pop
    //   1882: iload_2
    //   1883: ifeq -> 2444
    //   1886: goto -> 1893
    //   1889: invokestatic a : (Ljava/lang/Throwable;)Ljava/lang/Throwable;
    //   1892: athrow
    //   1893: aload_3
    //   1894: getstatic burp/Zmlr.ZJ : Ljava/lang/String;
    //   1897: getstatic burp/Zr36.Za : Ljava/lang/Object;
    //   1900: checkcast java/math/BigInteger
    //   1903: invokevirtual intValue : ()I
    //   1906: bipush #32
    //   1908: irem
    //   1909: invokestatic abs : (I)I
    //   1912: invokevirtual charAt : (I)C
    //   1915: invokevirtual append : (C)Ljava/lang/StringBuilder;
    //   1918: pop
    //   1919: iload_2
    //   1920: ifeq -> 2444
    //   1923: goto -> 1930
    //   1926: invokestatic a : (Ljava/lang/Throwable;)Ljava/lang/Throwable;
    //   1929: athrow
    //   1930: aload_3
    //   1931: getstatic burp/Zeub.ZT : Ljava/lang/String;
    //   1934: getstatic burp/Zsn3.Zy : Ljava/lang/Object;
    //   1937: checkcast java/math/BigInteger
    //   1940: invokevirtual intValue : ()I
    //   1943: bipush #32
    //   1945: irem
    //   1946: invokestatic abs : (I)I
    //   1949: invokevirtual charAt : (I)C
    //   1952: invokevirtual append : (C)Ljava/lang/StringBuilder;
    //   1955: pop
    //   1956: iload_2
    //   1957: ifeq -> 2444
    //   1960: goto -> 1967
    //   1963: invokestatic a : (Ljava/lang/Throwable;)Ljava/lang/Throwable;
    //   1966: athrow
    //   1967: aload_3
    //   1968: getstatic burp/Zlbd.Zq : Ljava/lang/String;
    //   1971: getstatic burp/Zs8w.ZW : Ljava/lang/Object;
    //   1974: checkcast java/math/BigInteger
    //   1977: invokevirtual intValue : ()I
    //   1980: bipush #32
    //   1982: irem
    //   1983: invokestatic abs : (I)I
    //   1986: invokevirtual charAt : (I)C
    //   1989: invokevirtual append : (C)Ljava/lang/StringBuilder;
    //   1992: pop
    //   1993: iload_2
    //   1994: ifeq -> 2444
    //   1997: goto -> 2004
    //   2000: invokestatic a : (Ljava/lang/Throwable;)Ljava/lang/Throwable;
    //   2003: athrow
    //   2004: aload_3
    //   2005: getstatic burp/Zzr8.ZY : Ljava/lang/String;
    //   2008: getstatic burp/Zx5w.Zo : Ljava/lang/Object;
    //   2011: checkcast java/math/BigInteger
    //   2014: invokevirtual intValue : ()I
    //   2017: bipush #32
    //   2019: irem
    //   2020: invokestatic abs : (I)I
    //   2023: invokevirtual charAt : (I)C
    //   2026: invokevirtual append : (C)Ljava/lang/StringBuilder;
    //   2029: pop
    //   2030: iload_2
    //   2031: ifeq -> 2444
    //   2034: goto -> 2041
    //   2037: invokestatic a : (Ljava/lang/Throwable;)Ljava/lang/Throwable;
    //   2040: athrow
    //   2041: aload_3
    //   2042: getstatic burp/Zql.Zf : Ljava/lang/String;
    //   2045: getstatic burp/Ztq4.ZA : Ljava/lang/Object;
    //   2048: checkcast java/math/BigInteger
    //   2051: invokevirtual intValue : ()I
    //   2054: bipush #32
    //   2056: irem
    //   2057: invokestatic abs : (I)I
    //   2060: invokevirtual charAt : (I)C
    //   2063: invokevirtual append : (C)Ljava/lang/StringBuilder;
    //   2066: pop
    //   2067: iload_2
    //   2068: ifeq -> 2444
    //   2071: goto -> 2078
    //   2074: invokestatic a : (Ljava/lang/Throwable;)Ljava/lang/Throwable;
    //   2077: athrow
    //   2078: aload_3
    //   2079: getstatic burp/Zxt7.Zi : Ljava/lang/String;
    //   2082: getstatic burp/Zg0q.Zf : Ljava/lang/Object;
    //   2085: checkcast java/math/BigInteger
    //   2088: invokevirtual intValue : ()I
    //   2091: bipush #32
    //   2093: irem
    //   2094: invokestatic abs : (I)I
    //   2097: invokevirtual charAt : (I)C
    //   2100: invokevirtual append : (C)Ljava/lang/StringBuilder;
    //   2103: pop
    //   2104: iload_2
    //   2105: ifeq -> 2444
    //   2108: goto -> 2115
    //   2111: invokestatic a : (Ljava/lang/Throwable;)Ljava/lang/Throwable;
    //   2114: athrow
    //   2115: aload_3
    //   2116: getstatic burp/Zrd3.Z_ : Ljava/lang/String;
    //   2119: getstatic burp/Zti4.Zi : Ljava/lang/Object;
    //   2122: checkcast java/math/BigInteger
    //   2125: invokevirtual intValue : ()I
    //   2128: bipush #32
    //   2130: irem
    //   2131: invokestatic abs : (I)I
    //   2134: invokevirtual charAt : (I)C
    //   2137: invokevirtual append : (C)Ljava/lang/StringBuilder;
    //   2140: pop
    //   2141: iload_2
    //   2142: ifeq -> 2444
    //   2145: goto -> 2152
    //   2148: invokestatic a : (Ljava/lang/Throwable;)Ljava/lang/Throwable;
    //   2151: athrow
    //   2152: aload_3
    //   2153: getstatic burp/Zm69.ZE : Ljava/lang/String;
    //   2156: getstatic burp/Zlwj.ZE : Ljava/lang/Object;
    //   2159: checkcast java/math/BigInteger
    //   2162: invokevirtual intValue : ()I
    //   2165: bipush #32
    //   2167: irem
    //   2168: invokestatic abs : (I)I
    //   2171: invokevirtual charAt : (I)C
    //   2174: invokevirtual append : (C)Ljava/lang/StringBuilder;
    //   2177: pop
    //   2178: iload_2
    //   2179: ifeq -> 2444
    //   2182: goto -> 2189
    //   2185: invokestatic a : (Ljava/lang/Throwable;)Ljava/lang/Throwable;
    //   2188: athrow
    //   2189: aload_3
    //   2190: getstatic burp/Zxp1.Zg : Ljava/lang/String;
    //   2193: getstatic burp/Zlgh.Zd : Ljava/lang/Object;
    //   2196: checkcast java/math/BigInteger
    //   2199: invokevirtual intValue : ()I
    //   2202: bipush #32
    //   2204: irem
    //   2205: invokestatic abs : (I)I
    //   2208: invokevirtual charAt : (I)C
    //   2211: invokevirtual append : (C)Ljava/lang/StringBuilder;
    //   2214: pop
    //   2215: iload_2
    //   2216: ifeq -> 2444
    //   2219: goto -> 2226
    //   2222: invokestatic a : (Ljava/lang/Throwable;)Ljava/lang/Throwable;
    //   2225: athrow
    //   2226: aload_3
    //   2227: getstatic burp/Zmlr.ZJ : Ljava/lang/String;
    //   2230: getstatic burp/Zzac.ZH : Ljava/lang/Object;
    //   2233: checkcast java/math/BigInteger
    //   2236: invokevirtual intValue : ()I
    //   2239: bipush #32
    //   2241: irem
    //   2242: invokestatic abs : (I)I
    //   2245: invokevirtual charAt : (I)C
    //   2248: invokevirtual append : (C)Ljava/lang/StringBuilder;
    //   2251: pop
    //   2252: iload_2
    //   2253: ifeq -> 2444
    //   2256: goto -> 2263
    //   2259: invokestatic a : (Ljava/lang/Throwable;)Ljava/lang/Throwable;
    //   2262: athrow
    //   2263: aload_3
    //   2264: getstatic burp/Zbl4.Ze : Ljava/lang/String;
    //   2267: getstatic burp/Zm69.Zg : Ljava/lang/Object;
    //   2270: checkcast java/math/BigInteger
    //   2273: invokevirtual intValue : ()I
    //   2276: bipush #32
    //   2278: irem
    //   2279: invokestatic abs : (I)I
    //   2282: invokevirtual charAt : (I)C
    //   2285: invokevirtual append : (C)Ljava/lang/StringBuilder;
    //   2288: pop
    //   2289: iload_2
    //   2290: ifeq -> 2444
    //   2293: goto -> 2300
    //   2296: invokestatic a : (Ljava/lang/Throwable;)Ljava/lang/Throwable;
    //   2299: athrow
    //   2300: aload_3
    //   2301: getstatic burp/Zsn3.ZS : Ljava/lang/String;
    //   2304: getstatic burp/Zg7e.Zr : Ljava/lang/Object;
    //   2307: checkcast java/math/BigInteger
    //   2310: invokevirtual intValue : ()I
    //   2313: bipush #32
    //   2315: irem
    //   2316: invokestatic abs : (I)I
    //   2319: invokevirtual charAt : (I)C
    //   2322: invokevirtual append : (C)Ljava/lang/StringBuilder;
    //   2325: pop
    //   2326: iload_2
    //   2327: ifeq -> 2444
    //   2330: goto -> 2337
    //   2333: invokestatic a : (Ljava/lang/Throwable;)Ljava/lang/Throwable;
    //   2336: athrow
    //   2337: aload_3
    //   2338: getstatic burp/Ztgv.ZC : Ljava/lang/String;
    //   2341: getstatic burp/Zr17.ZR : Ljava/lang/Object;
    //   2344: checkcast java/math/BigInteger
    //   2347: invokevirtual intValue : ()I
    //   2350: bipush #32
    //   2352: irem
    //   2353: invokestatic abs : (I)I
    //   2356: invokevirtual charAt : (I)C
    //   2359: invokevirtual append : (C)Ljava/lang/StringBuilder;
    //   2362: pop
    //   2363: iload_2
    //   2364: ifeq -> 2444
    //   2367: goto -> 2374
    //   2370: invokestatic a : (Ljava/lang/Throwable;)Ljava/lang/Throwable;
    //   2373: athrow
    //   2374: aload_3
    //   2375: getstatic burp/Zr2q.ZA : Ljava/lang/String;
    //   2378: getstatic burp/Zrom.ZF : Ljava/lang/Object;
    //   2381: checkcast java/math/BigInteger
    //   2384: invokevirtual intValue : ()I
    //   2387: bipush #32
    //   2389: irem
    //   2390: invokestatic abs : (I)I
    //   2393: invokevirtual charAt : (I)C
    //   2396: invokevirtual append : (C)Ljava/lang/StringBuilder;
    //   2399: pop
    //   2400: iload_2
    //   2401: ifeq -> 2444
    //   2404: goto -> 2411
    //   2407: invokestatic a : (Ljava/lang/Throwable;)Ljava/lang/Throwable;
    //   2410: athrow
    //   2411: aload_3
    //   2412: getstatic burp/Zrzg.ZX : Ljava/lang/String;
    //   2415: getstatic burp/Zenr.ZA : Ljava/lang/Object;
    //   2418: checkcast java/math/BigInteger
    //   2421: invokevirtual intValue : ()I
    //   2424: bipush #32
    //   2426: irem
    //   2427: invokestatic abs : (I)I
    //   2430: invokevirtual charAt : (I)C
    //   2433: invokevirtual append : (C)Ljava/lang/StringBuilder;
    //   2436: pop
    //   2437: goto -> 2444
    //   2440: invokestatic a : (Ljava/lang/Throwable;)Ljava/lang/Throwable;
    //   2443: athrow
    //   2444: iinc #4, 1
    //   2447: iload_2
    //   2448: ifeq -> 1112
    //   2451: aload_3
    //   2452: invokevirtual toString : ()Ljava/lang/String;
    //   2455: putstatic burp/Zrle.ZG : Ljava/lang/String;
    //   2458: sipush #-14204
    //   2461: sipush #-16421
    //   2464: invokestatic a : (II)Ljava/lang/String;
    //   2467: iconst_1
    //   2468: ldc burp/Zefn
    //   2470: invokevirtual getClassLoader : ()Ljava/lang/ClassLoader;
    //   2473: invokestatic forName : (Ljava/lang/String;ZLjava/lang/ClassLoader;)Ljava/lang/Class;
    //   2476: invokevirtual getDeclaredFields : ()[Ljava/lang/reflect/Field;
    //   2479: astore #4
    //   2481: aload #4
    //   2483: arraylength
    //   2484: istore #5
    //   2486: iconst_0
    //   2487: istore #6
    //   2489: iload #6
    //   2491: iload #5
    //   2493: if_icmpge -> 2631
    //   2496: aload #4
    //   2498: iload #6
    //   2500: aaload
    //   2501: astore #7
    //   2503: aload #7
    //   2505: invokevirtual getModifiers : ()I
    //   2508: invokestatic isStatic : (I)Z
    //   2511: ifne -> 2521
    //   2514: goto -> 2624
    //   2517: invokestatic a : (Ljava/lang/Throwable;)Ljava/lang/Throwable;
    //   2520: athrow
    //   2521: aload #7
    //   2523: invokevirtual getType : ()Ljava/lang/Class;
    //   2526: astore #8
    //   2528: aload #8
    //   2530: ifnull -> 2611
    //   2533: aload #8
    //   2535: invokevirtual isPrimitive : ()Z
    //   2538: ifne -> 2611
    //   2541: goto -> 2548
    //   2544: invokestatic a : (Ljava/lang/Throwable;)Ljava/lang/Throwable;
    //   2547: athrow
    //   2548: aload #8
    //   2550: invokevirtual getPackage : ()Ljava/lang/Package;
    //   2553: ifnull -> 2611
    //   2556: goto -> 2563
    //   2559: invokestatic a : (Ljava/lang/Throwable;)Ljava/lang/Throwable;
    //   2562: athrow
    //   2563: aload #8
    //   2565: invokevirtual getPackage : ()Ljava/lang/Package;
    //   2568: invokevirtual getName : ()Ljava/lang/String;
    //   2571: ifnull -> 2611
    //   2574: goto -> 2581
    //   2577: invokestatic a : (Ljava/lang/Throwable;)Ljava/lang/Throwable;
    //   2580: athrow
    //   2581: aload #8
    //   2583: invokevirtual getPackage : ()Ljava/lang/Package;
    //   2586: invokevirtual getName : ()Ljava/lang/String;
    //   2589: sipush #-14208
    //   2592: sipush #-31742
    //   2595: invokestatic a : (II)Ljava/lang/String;
    //   2598: invokevirtual startsWith : (Ljava/lang/String;)Z
    //   2601: ifne -> 2611
    //   2604: goto -> 2611
    //   2607: invokestatic a : (Ljava/lang/Throwable;)Ljava/lang/Throwable;
    //   2610: athrow
    //   2611: aload #7
    //   2613: iconst_1
    //   2614: invokevirtual setAccessible : (Z)V
    //   2617: aload #7
    //   2619: aconst_null
    //   2620: invokevirtual get : (Ljava/lang/Object;)Ljava/lang/Object;
    //   2623: pop
    //   2624: iinc #6, 1
    //   2627: iload_2
    //   2628: ifeq -> 2489
    //   2631: sipush #-14200
    //   2634: sipush #-30469
    //   2637: invokestatic a : (II)Ljava/lang/String;
    //   2640: invokestatic forName : (Ljava/lang/String;)Ljava/lang/Class;
    //   2643: invokevirtual getDeclaredMethods : ()[Ljava/lang/reflect/Method;
    //   2646: astore #4
    //   2648: aload #4
    //   2650: arraylength
    //   2651: istore #5
    //   2653: iconst_0
    //   2654: istore #6
    //   2656: iload #6
    //   2658: iload #5
    //   2660: if_icmpge -> 2793
    //   2663: aload #4
    //   2665: iload #6
    //   2667: aaload
    //   2668: astore #7
    //   2670: aload #7
    //   2672: invokevirtual getParameterTypes : ()[Ljava/lang/Class;
    //   2675: pop
    //   2676: aload #7
    //   2678: invokevirtual getModifiers : ()I
    //   2681: invokestatic isStatic : (I)Z
    //   2684: ifeq -> 2779
    //   2687: aload #7
    //   2689: invokevirtual getParameterTypes : ()[Ljava/lang/Class;
    //   2692: arraylength
    //   2693: iconst_2
    //   2694: if_icmpne -> 2779
    //   2697: goto -> 2704
    //   2700: invokestatic a : (Ljava/lang/Throwable;)Ljava/lang/Throwable;
    //   2703: athrow
    //   2704: aload #7
    //   2706: invokevirtual getReturnType : ()Ljava/lang/Class;
    //   2709: getstatic java/lang/Void.TYPE : Ljava/lang/Class;
    //   2712: invokevirtual equals : (Ljava/lang/Object;)Z
    //   2715: ifeq -> 2779
    //   2718: goto -> 2725
    //   2721: invokestatic a : (Ljava/lang/Throwable;)Ljava/lang/Throwable;
    //   2724: athrow
    //   2725: aload #7
    //   2727: iconst_1
    //   2728: invokevirtual setAccessible : (Z)V
    //   2731: aload #7
    //   2733: aconst_null
    //   2734: iconst_2
    //   2735: anewarray java/lang/Object
    //   2738: dup
    //   2739: iconst_0
    //   2740: aload_0
    //   2741: aastore
    //   2742: dup
    //   2743: iconst_1
    //   2744: aload_1
    //   2745: ifnonnull -> 2763
    //   2748: goto -> 2755
    //   2751: invokestatic a : (Ljava/lang/Throwable;)Ljava/lang/Throwable;
    //   2754: athrow
    //   2755: aload_1
    //   2756: goto -> 2770
    //   2759: invokestatic a : (Ljava/lang/Throwable;)Ljava/lang/Throwable;
    //   2762: athrow
    //   2763: aload_1
    //   2764: checkcast [B
    //   2767: invokevirtual clone : ()Ljava/lang/Object;
    //   2770: aastore
    //   2771: invokevirtual invoke : (Ljava/lang/Object;[Ljava/lang/Object;)Ljava/lang/Object;
    //   2774: pop
    //   2775: iload_2
    //   2776: ifeq -> 2793
    //   2779: iinc #6, 1
    //   2782: iload_2
    //   2783: ifeq -> 2656
    //   2786: goto -> 2793
    //   2789: invokestatic a : (Ljava/lang/Throwable;)Ljava/lang/Throwable;
    //   2792: athrow
    //   2793: new java/io/ByteArrayOutputStream
    //   2796: dup
    //   2797: invokespecial <init> : ()V
    //   2800: astore #4
    //   2802: sipush #-14199
    //   2805: aload #4
    //   2807: sipush #202
    //   2810: invokevirtual write : (I)V
    //   2813: sipush #1251
    //   2816: aload #4
    //   2818: sipush #254
    //   2821: invokevirtual write : (I)V
    //   2824: aload #4
    //   2826: sipush #186
    //   2829: invokevirtual write : (I)V
    //   2832: aload #4
    //   2834: sipush #190
    //   2837: invokevirtual write : (I)V
    //   2840: aload #4
    //   2842: iconst_0
    //   2843: invokevirtual write : (I)V
    //   2846: aload #4
    //   2848: iconst_1
    //   2849: invokevirtual write : (I)V
    //   2852: aload #4
    //   2854: iconst_0
    //   2855: invokevirtual write : (I)V
    //   2858: aload #4
    //   2860: bipush #50
    //   2862: invokevirtual write : (I)V
    //   2865: aload #4
    //   2867: getstatic burp/Zk7f.Za : Ljava/lang/Object;
    //   2870: checkcast java/math/BigInteger
    //   2873: invokevirtual toByteArray : ()[B
    //   2876: invokevirtual write : ([B)V
    //   2879: aload #4
    //   2881: getstatic burp/Zl50.ZV : Ljava/lang/Object;
    //   2884: checkcast java/math/BigInteger
    //   2887: invokevirtual toByteArray : ()[B
    //   2890: invokevirtual write : ([B)V
    //   2893: aload #4
    //   2895: getstatic burp/Zke7.Zj : Ljava/lang/Object;
    //   2898: checkcast java/math/BigInteger
    //   2901: invokevirtual toByteArray : ()[B
    //   2904: invokevirtual write : ([B)V
    //   2907: aload #4
    //   2909: invokevirtual toByteArray : ()[B
    //   2912: astore #5
    //   2914: aconst_null
    //   2915: astore #6
    //   2917: invokestatic a : (II)Ljava/lang/String;
    //   2920: invokestatic forName : (Ljava/lang/String;)Ljava/lang/Class;
    //   2923: invokevirtual getDeclaredMethods : ()[Ljava/lang/reflect/Method;
    //   2926: astore #7
    //   2928: aload #7
    //   2930: arraylength
    //   2931: istore #8
    //   2933: iconst_0
    //   2934: istore #9
    //   2936: iload #9
    //   2938: iload #8
    //   2940: if_icmpge -> 3068
    //   2943: aload #7
    //   2945: iload #9
    //   2947: aaload
    //   2948: astore #10
    //   2950: aload #10
    //   2952: invokevirtual getName : ()Ljava/lang/String;
    //   2955: sipush #-14193
    //   2958: sipush #-4760
    //   2961: invokestatic a : (II)Ljava/lang/String;
    //   2964: invokevirtual equals : (Ljava/lang/Object;)Z
    //   2967: ifeq -> 3061
    //   2970: aload #10
    //   2972: invokevirtual getParameterTypes : ()[Ljava/lang/Class;
    //   2975: astore #11
    //   2977: aload #11
    //   2979: arraylength
    //   2980: iconst_4
    //   2981: if_icmpeq -> 2991
    //   2984: goto -> 3061
    //   2987: invokestatic a : (Ljava/lang/Throwable;)Ljava/lang/Throwable;
    //   2990: athrow
    //   2991: aload #11
    //   2993: iconst_0
    //   2994: aaload
    //   2995: ldc java/lang/String
    //   2997: if_acmpeq -> 3007
    //   3000: goto -> 3061
    //   3003: invokestatic a : (Ljava/lang/Throwable;)Ljava/lang/Throwable;
    //   3006: athrow
    //   3007: aload #11
    //   3009: iconst_1
    //   3010: aaload
    //   3011: ldc [B
    //   3013: if_acmpeq -> 3023
    //   3016: goto -> 3061
    //   3019: invokestatic a : (Ljava/lang/Throwable;)Ljava/lang/Throwable;
    //   3022: athrow
    //   3023: aload #11
    //   3025: iconst_2
    //   3026: aaload
    //   3027: getstatic java/lang/Integer.TYPE : Ljava/lang/Class;
    //   3030: if_acmpeq -> 3040
    //   3033: goto -> 3061
    //   3036: invokestatic a : (Ljava/lang/Throwable;)Ljava/lang/Throwable;
    //   3039: athrow
    //   3040: aload #11
    //   3042: iconst_3
    //   3043: aaload
    //   3044: getstatic java/lang/Integer.TYPE : Ljava/lang/Class;
    //   3047: if_acmpeq -> 3057
    //   3050: goto -> 3061
    //   3053: invokestatic a : (Ljava/lang/Throwable;)Ljava/lang/Throwable;
    //   3056: athrow
    //   3057: aload #10
    //   3059: astore #6
    //   3061: iinc #9, 1
    //   3064: iload_2
    //   3065: ifeq -> 2936
    //   3068: aload #6
    //   3070: iconst_1
    //   3071: invokevirtual setAccessible : (Z)V
    //   3074: ldc burp/Zx4y
    //   3076: iconst_0
    //   3077: anewarray java/lang/Class
    //   3080: invokevirtual getDeclaredConstructor : ([Ljava/lang/Class;)Ljava/lang/reflect/Constructor;
    //   3083: astore #7
    //   3085: aload #7
    //   3087: iconst_1
    //   3088: invokevirtual setAccessible : (Z)V
    //   3091: aload #6
    //   3093: aload #7
    //   3095: iconst_0
    //   3096: anewarray java/lang/Object
    //   3099: invokevirtual newInstance : ([Ljava/lang/Object;)Ljava/lang/Object;
    //   3102: iconst_4
    //   3103: anewarray java/lang/Object
    //   3106: dup
    //   3107: iconst_0
    //   3108: sipush #-14202
    //   3111: sipush #17175
    //   3114: invokestatic a : (II)Ljava/lang/String;
    //   3117: aastore
    //   3118: dup
    //   3119: iconst_1
    //   3120: aload #5
    //   3122: aastore
    //   3123: dup
    //   3124: iconst_2
    //   3125: iconst_0
    //   3126: invokestatic valueOf : (I)Ljava/lang/Integer;
    //   3129: aastore
    //   3130: dup
    //   3131: iconst_3
    //   3132: aload #5
    //   3134: arraylength
    //   3135: invokestatic valueOf : (I)Ljava/lang/Integer;
    //   3138: aastore
    //   3139: invokevirtual invoke : (Ljava/lang/Object;[Ljava/lang/Object;)Ljava/lang/Object;
    //   3142: pop
    //   3143: goto -> 3148
    //   3146: astore #4
    //   3148: getstatic burp/Zlcc.Zw : Ljava/lang/String;
    //   3151: getstatic burp/Zrnt.Zh : Ljava/lang/Object;
    //   3154: checkcast java/math/BigInteger
    //   3157: invokevirtual intValue : ()I
    //   3160: bipush #32
    //   3162: irem
    //   3163: invokestatic abs : (I)I
    //   3166: invokevirtual charAt : (I)C
    //   3169: getstatic burp/Zzgb.ZT : Ljava/lang/String;
    //   3172: getstatic burp/Zrh_.Zb : Ljava/lang/Object;
    //   3175: checkcast java/math/BigInteger
    //   3178: invokevirtual intValue : ()I
    //   3181: bipush #32
    //   3183: irem
    //   3184: invokestatic abs : (I)I
    //   3187: invokevirtual charAt : (I)C
    //   3190: if_icmple -> 3297
    //   3193: getstatic burp/Zz66.ZM : Ljava/lang/String;
    //   3196: getstatic burp/Zsp9.ZV : Ljava/lang/Object;
    //   3199: checkcast java/math/BigInteger
    //   3202: invokevirtual intValue : ()I
    //   3205: bipush #32
    //   3207: irem
    //   3208: invokestatic abs : (I)I
    //   3211: invokevirtual charAt : (I)C
    //   3214: getstatic burp/Zbx4.ZS : Ljava/lang/String;
    //   3217: getstatic burp/Zlid.Zx : Ljava/lang/Object;
    //   3220: checkcast java/math/BigInteger
    //   3223: invokevirtual intValue : ()I
    //   3226: bipush #32
    //   3228: irem
    //   3229: invokestatic abs : (I)I
    //   3232: invokevirtual charAt : (I)C
    //   3235: if_icmpgt -> 3297
    //   3238: goto -> 3245
    //   3241: invokestatic a : (Ljava/lang/Throwable;)Ljava/lang/Throwable;
    //   3244: athrow
    //   3245: getstatic burp/Ze4a.Zm : Ljava/lang/String;
    //   3248: getstatic burp/Ze1k.ZD : Ljava/lang/Object;
    //   3251: checkcast java/math/BigInteger
    //   3254: invokevirtual intValue : ()I
    //   3257: bipush #32
    //   3259: irem
    //   3260: invokestatic abs : (I)I
    //   3263: invokevirtual charAt : (I)C
    //   3266: getstatic burp/Zzh5.Zc : Ljava/lang/String;
    //   3269: getstatic burp/Zm_u.Zf : Ljava/lang/Object;
    //   3272: checkcast java/math/BigInteger
    //   3275: invokevirtual intValue : ()I
    //   3278: bipush #32
    //   3280: irem
    //   3281: invokestatic abs : (I)I
    //   3284: invokevirtual charAt : (I)C
    //   3287: if_icmpgt -> 3305
    //   3290: goto -> 3297
    //   3293: invokestatic a : (Ljava/lang/Throwable;)Ljava/lang/Throwable;
    //   3296: athrow
    //   3297: iconst_1
    //   3298: goto -> 3306
    //   3301: invokestatic a : (Ljava/lang/Throwable;)Ljava/lang/Throwable;
    //   3304: athrow
    //   3305: iconst_0
    //   3306: ireturn
    //   3307: astore_3
    //   3308: new java/lang/Exception
    //   3311: dup
    //   3312: aload_3
    //   3313: invokevirtual getMessage : ()Ljava/lang/String;
    //   3316: invokespecial <init> : (Ljava/lang/String;)V
    //   3319: athrow
    // Exception table:
    //   from	to	target	type
    //   4	3306	3307	java/lang/Throwable
    //   191	219	222	java/lang/Throwable
    //   201	236	239	java/lang/Throwable
    //   226	264	267	java/lang/Throwable
    //   243	281	284	java/lang/Throwable
    //   271	309	312	java/lang/Throwable
    //   288	326	329	java/lang/Throwable
    //   316	344	347	java/lang/Throwable
    //   333	358	361	java/lang/Throwable
    //   724	748	751	java/lang/Throwable
    //   822	859	859	java/lang/Throwable
    //   863	884	884	java/lang/Throwable
    //   888	918	918	java/lang/Throwable
    //   1119	1294	1297	java/lang/Throwable
    //   1264	1331	1334	java/lang/Throwable
    //   1301	1368	1371	java/lang/Throwable
    //   1338	1405	1408	java/lang/Throwable
    //   1375	1442	1445	java/lang/Throwable
    //   1412	1479	1482	java/lang/Throwable
    //   1449	1516	1519	java/lang/Throwable
    //   1486	1553	1556	java/lang/Throwable
    //   1523	1590	1593	java/lang/Throwable
    //   1560	1627	1630	java/lang/Throwable
    //   1597	1664	1667	java/lang/Throwable
    //   1634	1701	1704	java/lang/Throwable
    //   1671	1738	1741	java/lang/Throwable
    //   1708	1775	1778	java/lang/Throwable
    //   1745	1812	1815	java/lang/Throwable
    //   1782	1849	1852	java/lang/Throwable
    //   1819	1886	1889	java/lang/Throwable
    //   1856	1923	1926	java/lang/Throwable
    //   1893	1960	1963	java/lang/Throwable
    //   1930	1997	2000	java/lang/Throwable
    //   1967	2034	2037	java/lang/Throwable
    //   2004	2071	2074	java/lang/Throwable
    //   2041	2108	2111	java/lang/Throwable
    //   2078	2145	2148	java/lang/Throwable
    //   2115	2182	2185	java/lang/Throwable
    //   2152	2219	2222	java/lang/Throwable
    //   2189	2256	2259	java/lang/Throwable
    //   2226	2293	2296	java/lang/Throwable
    //   2263	2330	2333	java/lang/Throwable
    //   2300	2367	2370	java/lang/Throwable
    //   2337	2404	2407	java/lang/Throwable
    //   2374	2437	2440	java/lang/Throwable
    //   2503	2517	2517	java/lang/Throwable
    //   2528	2541	2544	java/lang/Throwable
    //   2533	2556	2559	java/lang/Throwable
    //   2548	2574	2577	java/lang/Throwable
    //   2563	2604	2607	java/lang/Throwable
    //   2670	2697	2700	java/lang/Throwable
    //   2687	2718	2721	java/lang/Throwable
    //   2704	2748	2751	java/lang/Throwable
    //   2725	2759	2759	java/lang/Throwable
    //   2770	2786	2789	java/lang/Throwable
    //   2793	3143	3146	java/lang/Throwable
    //   2977	2987	2987	java/lang/Throwable
    //   2991	3003	3003	java/lang/Throwable
    //   3007	3019	3019	java/lang/Throwable
    //   3023	3036	3036	java/lang/Throwable
    //   3040	3053	3053	java/lang/Throwable
    //   3148	3238	3241	java/lang/Throwable
    //   3193	3290	3293	java/lang/Throwable
    //   3245	3301	3301	java/lang/Throwable
  }
  
  static {
    // Byte code:
    //   0: bipush #14
    //   2: anewarray java/lang/String
    //   5: astore #5
    //   7: iconst_0
    //   8: istore_3
    //   9: ldc '3jg#*?v-|C?DE7u::'4)qS:H !b/ YMg!Dn 8$\7zg= .(w@=K)N/vvntE\\rI\\tn#b\\t'=JF;rD.5\\tt\\n#%c\\tDZ2O0\\tvM"A\\byq&k\\tBHfAs'
    //   11: dup
    //   12: astore_2
    //   13: invokevirtual length : ()I
    //   16: istore #4
    //   18: bipush #77
    //   20: istore_1
    //   21: iconst_m1
    //   22: istore_0
    //   23: bipush #23
    //   25: iinc #0, 1
    //   28: aload_2
    //   29: iload_0
    //   30: dup
    //   31: iload_1
    //   32: iadd
    //   33: invokevirtual substring : (II)Ljava/lang/String;
    //   36: iconst_m1
    //   37: goto -> 142
    //   40: aload #5
    //   42: swap
    //   43: iload_3
    //   44: iinc #3, 1
    //   47: swap
    //   48: aastore
    //   49: iload_0
    //   50: iload_1
    //   51: iadd
    //   52: dup
    //   53: istore_0
    //   54: iload #4
    //   56: if_icmpge -> 68
    //   59: aload_2
    //   60: iload_0
    //   61: invokevirtual charAt : (I)C
    //   64: istore_1
    //   65: goto -> 23
    //   68: ldc '%n 98w\\boa"iZ'
    //   70: dup
    //   71: astore_2
    //   72: invokevirtual length : ()I
    //   75: istore #4
    //   77: iconst_4
    //   78: istore_1
    //   79: iconst_m1
    //   80: istore_0
    //   81: bipush #122
    //   83: iinc #0, 1
    //   86: aload_2
    //   87: iload_0
    //   88: dup
    //   89: iload_1
    //   90: iadd
    //   91: invokevirtual substring : (II)Ljava/lang/String;
    //   94: iconst_0
    //   95: goto -> 142
    //   98: aload #5
    //   100: swap
    //   101: iload_3
    //   102: iinc #3, 1
    //   105: swap
    //   106: aastore
    //   107: iload_0
    //   108: iload_1
    //   109: iadd
    //   110: dup
    //   111: istore_0
    //   112: iload #4
    //   114: if_icmpge -> 126
    //   117: aload_2
    //   118: iload_0
    //   119: invokevirtual charAt : (I)C
    //   122: istore_1
    //   123: goto -> 81
    //   126: aload #5
    //   128: putstatic burp/Zxc0.a : [Ljava/lang/String;
    //   131: bipush #14
    //   133: anewarray java/lang/String
    //   136: putstatic burp/Zxc0.b : [Ljava/lang/String;
    //   139: goto -> 300
    //   142: dup_x2
    //   143: pop
    //   144: invokevirtual toCharArray : ()[C
    //   147: dup_x1
    //   148: arraylength
    //   149: dup_x2
    //   150: pop
    //   151: iconst_0
    //   152: istore #6
    //   154: dup2_x1
    //   155: pop2
    //   156: dup_x2
    //   157: iconst_1
    //   158: if_icmpgt -> 260
    //   161: dup2
    //   162: swap
    //   163: iload #6
    //   165: dup2_x1
    //   166: caload
    //   167: swap
    //   168: iload #6
    //   170: bipush #7
    //   172: irem
    //   173: tableswitch default -> 242, 0 -> 212, 1 -> 217, 2 -> 222, 3 -> 227, 4 -> 232, 5 -> 237
    //   212: bipush #70
    //   214: goto -> 244
    //   217: bipush #99
    //   219: goto -> 244
    //   222: bipush #107
    //   224: goto -> 244
    //   227: bipush #108
    //   229: goto -> 244
    //   232: bipush #16
    //   234: goto -> 244
    //   237: bipush #49
    //   239: goto -> 244
    //   242: bipush #18
    //   244: ixor
    //   245: ixor
    //   246: i2c
    //   247: castore
    //   248: iinc #6, 1
    //   251: dup
    //   252: ifne -> 260
    //   255: dup2
    //   256: dup_x1
    //   257: goto -> 165
    //   260: dup2_x1
    //   261: pop2
    //   262: dup_x2
    //   263: iload #6
    //   265: if_icmpgt -> 161
    //   268: pop
    //   269: new java/lang/String
    //   272: dup_x1
    //   273: swap
    //   274: invokespecial <init> : ([C)V
    //   277: invokevirtual intern : ()Ljava/lang/String;
    //   280: swap
    //   281: pop
    //   282: swap
    //   283: tableswitch default -> 40, 0 -> 98
    //   300: sipush #-14194
    //   303: sipush #18283
    //   306: invokestatic a : (II)Ljava/lang/String;
    //   309: putstatic burp/Zxc0.Zh : Ljava/lang/String;
    //   312: new java/math/BigInteger
    //   315: dup
    //   316: iconst_1
    //   317: bipush #32
    //   319: newarray byte
    //   321: dup
    //   322: iconst_0
    //   323: bipush #95
    //   325: bastore
    //   326: dup
    //   327: iconst_1
    //   328: bipush #-10
    //   330: bastore
    //   331: dup
    //   332: iconst_2
    //   333: bipush #-123
    //   335: bastore
    //   336: dup
    //   337: iconst_3
    //   338: bipush #94
    //   340: bastore
    //   341: dup
    //   342: iconst_4
    //   343: bipush #-76
    //   345: bastore
    //   346: dup
    //   347: iconst_5
    //   348: bipush #-37
    //   350: bastore
    //   351: dup
    //   352: bipush #6
    //   354: bipush #-39
    //   356: bastore
    //   357: dup
    //   358: bipush #7
    //   360: bipush #-12
    //   362: bastore
    //   363: dup
    //   364: bipush #8
    //   366: bipush #108
    //   368: bastore
    //   369: dup
    //   370: bipush #9
    //   372: bipush #-110
    //   374: bastore
    //   375: dup
    //   376: bipush #10
    //   378: bipush #32
    //   380: bastore
    //   381: dup
    //   382: bipush #11
    //   384: bipush #99
    //   386: bastore
    //   387: dup
    //   388: bipush #12
    //   390: bipush #71
    //   392: bastore
    //   393: dup
    //   394: bipush #13
    //   396: bipush #-112
    //   398: bastore
    //   399: dup
    //   400: bipush #14
    //   402: bipush #16
    //   404: bastore
    //   405: dup
    //   406: bipush #15
    //   408: bipush #125
    //   410: bastore
    //   411: dup
    //   412: bipush #16
    //   414: bipush #20
    //   416: bastore
    //   417: dup
    //   418: bipush #17
    //   420: bipush #-41
    //   422: bastore
    //   423: dup
    //   424: bipush #18
    //   426: bipush #7
    //   428: bastore
    //   429: dup
    //   430: bipush #19
    //   432: bipush #-98
    //   434: bastore
    //   435: dup
    //   436: bipush #20
    //   438: bipush #31
    //   440: bastore
    //   441: dup
    //   442: bipush #21
    //   444: bipush #-60
    //   446: bastore
    //   447: dup
    //   448: bipush #22
    //   450: bipush #-63
    //   452: bastore
    //   453: dup
    //   454: bipush #23
    //   456: bipush #64
    //   458: bastore
    //   459: dup
    //   460: bipush #24
    //   462: bipush #-123
    //   464: bastore
    //   465: dup
    //   466: bipush #25
    //   468: bipush #117
    //   470: bastore
    //   471: dup
    //   472: bipush #26
    //   474: bipush #-29
    //   476: bastore
    //   477: dup
    //   478: bipush #27
    //   480: bipush #123
    //   482: bastore
    //   483: dup
    //   484: bipush #28
    //   486: bipush #-83
    //   488: bastore
    //   489: dup
    //   490: bipush #29
    //   492: bipush #56
    //   494: bastore
    //   495: dup
    //   496: bipush #30
    //   498: bipush #74
    //   500: bastore
    //   501: dup
    //   502: bipush #31
    //   504: bipush #-9
    //   506: bastore
    //   507: invokespecial <init> : (I[B)V
    //   510: putstatic burp/Zxc0.Zl : Ljava/lang/Object;
    //   513: return
  }
  
  private static Throwable a(Throwable paramThrowable) {
    return paramThrowable;
  }
  
  private static String a(int paramInt1, int paramInt2) {
    int i = (paramInt1 ^ 0xFFFFC88C) & 0xFFFF;
    if (b[i] == null) {
      char[] arrayOfChar = a[i].toCharArray();
      switch (arrayOfChar[0] & 0xFF) {
        case 0:
        
        case 1:
        
        case 2:
        
        case 3:
        
        case 4:
        
        case 5:
        
        case 6:
        
        case 7:
        
        case 8:
        
        case 9:
        
        case 10:
        
        case 11:
        
        case 12:
        
        case 13:
        
        case 14:
        
        case 15:
        
        case 16:
        
        case 17:
        
        case 18:
        
        case 19:
        
        case 20:
        
        case 21:
        
        case 22:
        
        case 23:
        
        case 24:
        
        case 25:
        
        case 26:
        
        case 27:
        
        case 28:
        
        case 29:
        
        case 30:
        
        case 31:
        
        case 32:
        
        case 33:
        
        case 34:
        
        case 35:
        
        case 36:
        
        case 37:
        
        case 38:
        
        case 39:
        
        case 40:
        
        case 41:
        
        case 42:
        
        case 43:
        
        case 44:
        
        case 45:
        
        case 46:
        
        case 47:
        
        case 48:
        
        case 49:
        
        case 50:
        
        case 51:
        
        case 52:
        
        case 53:
        
        case 54:
        
        case 55:
        
        case 56:
        
        case 57:
        
        case 58:
        
        case 59:
        
        case 60:
        
        case 61:
        
        case 62:
        
        case 63:
        
        case 64:
        
        case 65:
        
        case 66:
        
        case 67:
        
        case 68:
        
        case 69:
        
        case 70:
        
        case 71:
        
        case 72:
        
        case 73:
        
        case 74:
        
        case 75:
        
        case 76:
        
        case 77:
        
        case 78:
        
        case 79:
        
        case 80:
        
        case 81:
        
        case 82:
        
        case 83:
        
        case 84:
        
        case 85:
        
        case 86:
        
        case 87:
        
        case 88:
        
        case 89:
        
        case 90:
        
        case 91:
        
        case 92:
        
        case 93:
        
        case 94:
        
        case 95:
        
        case 96:
        
        case 97:
        
        case 98:
        
        case 99:
        
        case 100:
        
        case 101:
        
        case 102:
        
        case 103:
        
        case 104:
        
        case 105:
        
        case 106:
        
        case 107:
        
        case 108:
        
        case 109:
        
        case 110:
        
        case 111:
        
        case 112:
        
        case 113:
        
        case 114:
        
        case 115:
        
        case 116:
        
        case 117:
        
        case 118:
        
        case 119:
        
        case 120:
        
        case 121:
        
        case 122:
        
        case 123:
        
        case 124:
        
        case 125:
        
        case 126:
        
        case 127:
        
        case 128:
        
        case 129:
        
        case 130:
        
        case 131:
        
        case 132:
        
        case 133:
        
        case 134:
        
        case 135:
        
        case 136:
        
        case 137:
        
        case 138:
        
        case 139:
        
        case 140:
        
        case 141:
        
        case 142:
        
        case 143:
        
        case 144:
        
        case 145:
        
        case 146:
        
        case 147:
        
        case 148:
        
        case 149:
        
        case 150:
        
        case 151:
        
        case 152:
        
        case 153:
        
        case 154:
        
        case 155:
        
        case 156:
        
        case 157:
        
        case 158:
        
        case 159:
        
        case 160:
        
        case 161:
        
        case 162:
        
        case 163:
        
        case 164:
        
        case 165:
        
        case 166:
        
        case 167:
        
        case 168:
        
        case 169:
        
        case 170:
        
        case 171:
        
        case 172:
        
        case 173:
        
        case 174:
        
        case 175:
        
        case 176:
        
        case 177:
        
        case 178:
        
        case 179:
        
        case 180:
        
        case 181:
        
        case 182:
        
        case 183:
        
        case 184:
        
        case 185:
        
        case 186:
        
        case 187:
        
        case 188:
        
        case 189:
        
        case 190:
        
        case 191:
        
        case 192:
        
        case 193:
        
        case 194:
        
        case 195:
        
        case 196:
        
        case 197:
        
        case 198:
        
        case 199:
        
        case 200:
        
        case 201:
        
        case 202:
        
        case 203:
        
        case 204:
        
        case 205:
        
        case 206:
        
        case 207:
        
        case 208:
        
        case 209:
        
        case 210:
        
        case 211:
        
        case 212:
        
        case 213:
        
        case 214:
        
        case 215:
        
        case 216:
        
        case 217:
        
        case 218:
        
        case 219:
        
        case 220:
        
        case 221:
        
        case 222:
        
        case 223:
        
        case 224:
        
        case 225:
        
        case 226:
        
        case 227:
        
        case 228:
        
        case 229:
        
        case 230:
        
        case 231:
        
        case 232:
        
        case 233:
        
        case 234:
        
        case 235:
        
        case 236:
        
        case 237:
        
        case 238:
        
        case 239:
        
        case 240:
        
        case 241:
        
        case 242:
        
        case 243:
        
        case 244:
        
        case 245:
        
        case 246:
        
        case 247:
        
        case 248:
        
        case 249:
        
        case 250:
        
        case 251:
        
        case 252:
        
        case 253:
        
        case 254:
        
        default:
          break;
      } 
      byte b1 = 84;
      int j = (paramInt2 & 0xFF) - b1;
      if (j < 0)
        j += 256; 
      int k = ((paramInt2 & 0xFFFF) >>> 8) - b1;
      if (k < 0)
        k += 256; 
      for (byte b2 = 0; b2 < arrayOfChar.length; b2++) {
        int m = b2 % 2;
        if (m == 0) {
          arrayOfChar[b2] = (char)(arrayOfChar[b2] ^ j);
          j = ((j >>> 3 | j << 5) ^ arrayOfChar[b2]) & 0xFF;
        } else {
          arrayOfChar[b2] = (char)(arrayOfChar[b2] ^ k);
          k = ((k >>> 3 | k << 5) ^ arrayOfChar[b2]) & 0xFF;
        } 
      } 
      b[i] = (new String(arrayOfChar)).intern();
    } 
    return b[i];
  }
}


/* Location:              C:\Program Files\BurpSuitePro\burpsuite_pro.jar!\burp\Zxc0.class
 * Java compiler version: 21 (65.0)
 * JD-Core Version:       1.1.3
 */