package burp;

import java.math.BigInteger;

class Zxdw extends ClassLoader {
  static Object ZN;
  
  static String Zk;
  
  private static final String[] a;
  
  private static final String[] b;
  
  static boolean Zd(Object[] paramArrayOfObject, Object paramObject) throws Throwable {
    // Byte code:
    //   0: invokestatic ZK : ()Z
    //   3: istore_2
    //   4: new java/lang/StringBuilder
    //   7: dup
    //   8: invokespecial <init> : ()V
    //   11: astore_3
    //   12: iconst_0
    //   13: istore #4
    //   15: iload #4
    //   17: bipush #32
    //   19: if_icmpge -> 1251
    //   22: iload #4
    //   24: tableswitch default -> 1247, 0 -> 168, 1 -> 201, 2 -> 234, 3 -> 267, 4 -> 300, 5 -> 333, 6 -> 367, 7 -> 401, 8 -> 435, 9 -> 469, 10 -> 503, 11 -> 537, 12 -> 571, 13 -> 605, 14 -> 639, 15 -> 673, 16 -> 707, 17 -> 741, 18 -> 775, 19 -> 809, 20 -> 843, 21 -> 877, 22 -> 911, 23 -> 945, 24 -> 979, 25 -> 1013, 26 -> 1047, 27 -> 1081, 28 -> 1115, 29 -> 1149, 30 -> 1183, 31 -> 1217
    //   168: aload_3
    //   169: getstatic burp/Zxo7.Zl : Ljava/lang/String;
    //   172: getstatic burp/Zlem.ZI : Ljava/lang/Object;
    //   175: checkcast java/math/BigInteger
    //   178: invokevirtual intValue : ()I
    //   181: bipush #32
    //   183: irem
    //   184: invokestatic abs : (I)I
    //   187: invokevirtual charAt : (I)C
    //   190: invokevirtual append : (C)Ljava/lang/StringBuilder;
    //   193: pop
    //   194: iconst_1
    //   195: istore #4
    //   197: iload_2
    //   198: ifeq -> 1247
    //   201: aload_3
    //   202: getstatic burp/Ze_t.ZZ : Ljava/lang/String;
    //   205: getstatic burp/Zt98.Zz : Ljava/lang/Object;
    //   208: checkcast java/math/BigInteger
    //   211: invokevirtual intValue : ()I
    //   214: bipush #32
    //   216: irem
    //   217: invokestatic abs : (I)I
    //   220: invokevirtual charAt : (I)C
    //   223: invokevirtual append : (C)Ljava/lang/StringBuilder;
    //   226: pop
    //   227: iconst_2
    //   228: istore #4
    //   230: iload_2
    //   231: ifeq -> 1247
    //   234: aload_3
    //   235: getstatic burp/Zz2e.ZS : Ljava/lang/String;
    //   238: getstatic burp/Zm7x.Zv : Ljava/lang/Object;
    //   241: checkcast java/math/BigInteger
    //   244: invokevirtual intValue : ()I
    //   247: bipush #32
    //   249: irem
    //   250: invokestatic abs : (I)I
    //   253: invokevirtual charAt : (I)C
    //   256: invokevirtual append : (C)Ljava/lang/StringBuilder;
    //   259: pop
    //   260: iconst_3
    //   261: istore #4
    //   263: iload_2
    //   264: ifeq -> 1247
    //   267: aload_3
    //   268: getstatic burp/Zr1z.ZB : Ljava/lang/String;
    //   271: getstatic burp/Zlck.Zr : Ljava/lang/Object;
    //   274: checkcast java/math/BigInteger
    //   277: invokevirtual intValue : ()I
    //   280: bipush #32
    //   282: irem
    //   283: invokestatic abs : (I)I
    //   286: invokevirtual charAt : (I)C
    //   289: invokevirtual append : (C)Ljava/lang/StringBuilder;
    //   292: pop
    //   293: iconst_4
    //   294: istore #4
    //   296: iload_2
    //   297: ifeq -> 1247
    //   300: aload_3
    //   301: getstatic burp/Zztk.Zf : Ljava/lang/String;
    //   304: getstatic burp/Zb4a.ZJ : Ljava/lang/Object;
    //   307: checkcast java/math/BigInteger
    //   310: invokevirtual intValue : ()I
    //   313: bipush #32
    //   315: irem
    //   316: invokestatic abs : (I)I
    //   319: invokevirtual charAt : (I)C
    //   322: invokevirtual append : (C)Ljava/lang/StringBuilder;
    //   325: pop
    //   326: iconst_5
    //   327: istore #4
    //   329: iload_2
    //   330: ifeq -> 1247
    //   333: aload_3
    //   334: getstatic burp/Ze5t.ZX : Ljava/lang/String;
    //   337: getstatic burp/Zmj8.Zz : Ljava/lang/Object;
    //   340: checkcast java/math/BigInteger
    //   343: invokevirtual intValue : ()I
    //   346: bipush #32
    //   348: irem
    //   349: invokestatic abs : (I)I
    //   352: invokevirtual charAt : (I)C
    //   355: invokevirtual append : (C)Ljava/lang/StringBuilder;
    //   358: pop
    //   359: bipush #6
    //   361: istore #4
    //   363: iload_2
    //   364: ifeq -> 1247
    //   367: aload_3
    //   368: getstatic burp/Zmhi.ZQ : Ljava/lang/String;
    //   371: getstatic burp/Zrof.ZB : Ljava/lang/Object;
    //   374: checkcast java/math/BigInteger
    //   377: invokevirtual intValue : ()I
    //   380: bipush #32
    //   382: irem
    //   383: invokestatic abs : (I)I
    //   386: invokevirtual charAt : (I)C
    //   389: invokevirtual append : (C)Ljava/lang/StringBuilder;
    //   392: pop
    //   393: bipush #7
    //   395: istore #4
    //   397: iload_2
    //   398: ifeq -> 1247
    //   401: aload_3
    //   402: getstatic burp/Ztlz.ZE : Ljava/lang/String;
    //   405: getstatic burp/Zzyr.Za : Ljava/lang/Object;
    //   408: checkcast java/math/BigInteger
    //   411: invokevirtual intValue : ()I
    //   414: bipush #32
    //   416: irem
    //   417: invokestatic abs : (I)I
    //   420: invokevirtual charAt : (I)C
    //   423: invokevirtual append : (C)Ljava/lang/StringBuilder;
    //   426: pop
    //   427: bipush #8
    //   429: istore #4
    //   431: iload_2
    //   432: ifeq -> 1247
    //   435: aload_3
    //   436: getstatic burp/Ze8i.ZM : Ljava/lang/String;
    //   439: getstatic burp/Zlh8.Zm : Ljava/lang/Object;
    //   442: checkcast java/math/BigInteger
    //   445: invokevirtual intValue : ()I
    //   448: bipush #32
    //   450: irem
    //   451: invokestatic abs : (I)I
    //   454: invokevirtual charAt : (I)C
    //   457: invokevirtual append : (C)Ljava/lang/StringBuilder;
    //   460: pop
    //   461: bipush #9
    //   463: istore #4
    //   465: iload_2
    //   466: ifeq -> 1247
    //   469: aload_3
    //   470: getstatic burp/Zsf7.ZS : Ljava/lang/String;
    //   473: getstatic burp/Zrva.ZE : Ljava/lang/Object;
    //   476: checkcast java/math/BigInteger
    //   479: invokevirtual intValue : ()I
    //   482: bipush #32
    //   484: irem
    //   485: invokestatic abs : (I)I
    //   488: invokevirtual charAt : (I)C
    //   491: invokevirtual append : (C)Ljava/lang/StringBuilder;
    //   494: pop
    //   495: bipush #10
    //   497: istore #4
    //   499: iload_2
    //   500: ifeq -> 1247
    //   503: aload_3
    //   504: getstatic burp/Zgva.ZV : Ljava/lang/String;
    //   507: getstatic burp/Ztlz.ZW : Ljava/lang/Object;
    //   510: checkcast java/math/BigInteger
    //   513: invokevirtual intValue : ()I
    //   516: bipush #32
    //   518: irem
    //   519: invokestatic abs : (I)I
    //   522: invokevirtual charAt : (I)C
    //   525: invokevirtual append : (C)Ljava/lang/StringBuilder;
    //   528: pop
    //   529: bipush #11
    //   531: istore #4
    //   533: iload_2
    //   534: ifeq -> 1247
    //   537: aload_3
    //   538: getstatic burp/Ze5t.ZX : Ljava/lang/String;
    //   541: getstatic burp/Zl8f.ZA : Ljava/lang/Object;
    //   544: checkcast java/math/BigInteger
    //   547: invokevirtual intValue : ()I
    //   550: bipush #32
    //   552: irem
    //   553: invokestatic abs : (I)I
    //   556: invokevirtual charAt : (I)C
    //   559: invokevirtual append : (C)Ljava/lang/StringBuilder;
    //   562: pop
    //   563: bipush #12
    //   565: istore #4
    //   567: iload_2
    //   568: ifeq -> 1247
    //   571: aload_3
    //   572: getstatic burp/Zl8f.ZK : Ljava/lang/String;
    //   575: getstatic burp/Ze8m.Zm : Ljava/lang/Object;
    //   578: checkcast java/math/BigInteger
    //   581: invokevirtual intValue : ()I
    //   584: bipush #32
    //   586: irem
    //   587: invokestatic abs : (I)I
    //   590: invokevirtual charAt : (I)C
    //   593: invokevirtual append : (C)Ljava/lang/StringBuilder;
    //   596: pop
    //   597: bipush #13
    //   599: istore #4
    //   601: iload_2
    //   602: ifeq -> 1247
    //   605: aload_3
    //   606: getstatic burp/Zv8c.ZO : Ljava/lang/String;
    //   609: getstatic burp/Zlrm.ZM : Ljava/lang/Object;
    //   612: checkcast java/math/BigInteger
    //   615: invokevirtual intValue : ()I
    //   618: bipush #32
    //   620: irem
    //   621: invokestatic abs : (I)I
    //   624: invokevirtual charAt : (I)C
    //   627: invokevirtual append : (C)Ljava/lang/StringBuilder;
    //   630: pop
    //   631: bipush #14
    //   633: istore #4
    //   635: iload_2
    //   636: ifeq -> 1247
    //   639: aload_3
    //   640: getstatic burp/Zzr5.Zg : Ljava/lang/String;
    //   643: getstatic burp/Zke7.Zj : Ljava/lang/Object;
    //   646: checkcast java/math/BigInteger
    //   649: invokevirtual intValue : ()I
    //   652: bipush #32
    //   654: irem
    //   655: invokestatic abs : (I)I
    //   658: invokevirtual charAt : (I)C
    //   661: invokevirtual append : (C)Ljava/lang/StringBuilder;
    //   664: pop
    //   665: bipush #15
    //   667: istore #4
    //   669: iload_2
    //   670: ifeq -> 1247
    //   673: aload_3
    //   674: getstatic burp/Zm6h.Za : Ljava/lang/String;
    //   677: getstatic burp/Zz6t.ZA : Ljava/lang/Object;
    //   680: checkcast java/math/BigInteger
    //   683: invokevirtual intValue : ()I
    //   686: bipush #32
    //   688: irem
    //   689: invokestatic abs : (I)I
    //   692: invokevirtual charAt : (I)C
    //   695: invokevirtual append : (C)Ljava/lang/StringBuilder;
    //   698: pop
    //   699: bipush #16
    //   701: istore #4
    //   703: iload_2
    //   704: ifeq -> 1247
    //   707: aload_3
    //   708: getstatic burp/Zrof.ZE : Ljava/lang/String;
    //   711: getstatic burp/Zlem.ZI : Ljava/lang/Object;
    //   714: checkcast java/math/BigInteger
    //   717: invokevirtual intValue : ()I
    //   720: bipush #32
    //   722: irem
    //   723: invokestatic abs : (I)I
    //   726: invokevirtual charAt : (I)C
    //   729: invokevirtual append : (C)Ljava/lang/StringBuilder;
    //   732: pop
    //   733: bipush #17
    //   735: istore #4
    //   737: iload_2
    //   738: ifeq -> 1247
    //   741: aload_3
    //   742: getstatic burp/Zk7e.ZP : Ljava/lang/String;
    //   745: getstatic burp/Zkb_.ZG : Ljava/lang/Object;
    //   748: checkcast java/math/BigInteger
    //   751: invokevirtual intValue : ()I
    //   754: bipush #32
    //   756: irem
    //   757: invokestatic abs : (I)I
    //   760: invokevirtual charAt : (I)C
    //   763: invokevirtual append : (C)Ljava/lang/StringBuilder;
    //   766: pop
    //   767: bipush #18
    //   769: istore #4
    //   771: iload_2
    //   772: ifeq -> 1247
    //   775: aload_3
    //   776: getstatic burp/Zr1z.ZB : Ljava/lang/String;
    //   779: getstatic burp/Zr1z.Zi : Ljava/lang/Object;
    //   782: checkcast java/math/BigInteger
    //   785: invokevirtual intValue : ()I
    //   788: bipush #32
    //   790: irem
    //   791: invokestatic abs : (I)I
    //   794: invokevirtual charAt : (I)C
    //   797: invokevirtual append : (C)Ljava/lang/StringBuilder;
    //   800: pop
    //   801: bipush #19
    //   803: istore #4
    //   805: iload_2
    //   806: ifeq -> 1247
    //   809: aload_3
    //   810: getstatic burp/Zb8y.Zn : Ljava/lang/String;
    //   813: getstatic burp/Zkc8.ZW : Ljava/lang/Object;
    //   816: checkcast java/math/BigInteger
    //   819: invokevirtual intValue : ()I
    //   822: bipush #32
    //   824: irem
    //   825: invokestatic abs : (I)I
    //   828: invokevirtual charAt : (I)C
    //   831: invokevirtual append : (C)Ljava/lang/StringBuilder;
    //   834: pop
    //   835: bipush #20
    //   837: istore #4
    //   839: iload_2
    //   840: ifeq -> 1247
    //   843: aload_3
    //   844: getstatic burp/Zs83.ZG : Ljava/lang/String;
    //   847: getstatic burp/Zlnm.Zn : Ljava/lang/Object;
    //   850: checkcast java/math/BigInteger
    //   853: invokevirtual intValue : ()I
    //   856: bipush #32
    //   858: irem
    //   859: invokestatic abs : (I)I
    //   862: invokevirtual charAt : (I)C
    //   865: invokevirtual append : (C)Ljava/lang/StringBuilder;
    //   868: pop
    //   869: bipush #21
    //   871: istore #4
    //   873: iload_2
    //   874: ifeq -> 1247
    //   877: aload_3
    //   878: getstatic burp/Zkjr.Zg : Ljava/lang/String;
    //   881: getstatic burp/Ze54.Zx : Ljava/lang/Object;
    //   884: checkcast java/math/BigInteger
    //   887: invokevirtual intValue : ()I
    //   890: bipush #32
    //   892: irem
    //   893: invokestatic abs : (I)I
    //   896: invokevirtual charAt : (I)C
    //   899: invokevirtual append : (C)Ljava/lang/StringBuilder;
    //   902: pop
    //   903: bipush #22
    //   905: istore #4
    //   907: iload_2
    //   908: ifeq -> 1247
    //   911: aload_3
    //   912: getstatic burp/Zzoi.ZR : Ljava/lang/String;
    //   915: getstatic burp/Zex.ZO : Ljava/lang/Object;
    //   918: checkcast java/math/BigInteger
    //   921: invokevirtual intValue : ()I
    //   924: bipush #32
    //   926: irem
    //   927: invokestatic abs : (I)I
    //   930: invokevirtual charAt : (I)C
    //   933: invokevirtual append : (C)Ljava/lang/StringBuilder;
    //   936: pop
    //   937: bipush #23
    //   939: istore #4
    //   941: iload_2
    //   942: ifeq -> 1247
    //   945: aload_3
    //   946: getstatic burp/Ze8m.Zx : Ljava/lang/String;
    //   949: getstatic burp/Ze54.Zx : Ljava/lang/Object;
    //   952: checkcast java/math/BigInteger
    //   955: invokevirtual intValue : ()I
    //   958: bipush #32
    //   960: irem
    //   961: invokestatic abs : (I)I
    //   964: invokevirtual charAt : (I)C
    //   967: invokevirtual append : (C)Ljava/lang/StringBuilder;
    //   970: pop
    //   971: bipush #24
    //   973: istore #4
    //   975: iload_2
    //   976: ifeq -> 1247
    //   979: aload_3
    //   980: getstatic burp/Zg_5.ZG : Ljava/lang/String;
    //   983: getstatic burp/Zxe.Zg : Ljava/lang/Object;
    //   986: checkcast java/math/BigInteger
    //   989: invokevirtual intValue : ()I
    //   992: bipush #32
    //   994: irem
    //   995: invokestatic abs : (I)I
    //   998: invokevirtual charAt : (I)C
    //   1001: invokevirtual append : (C)Ljava/lang/StringBuilder;
    //   1004: pop
    //   1005: bipush #25
    //   1007: istore #4
    //   1009: iload_2
    //   1010: ifeq -> 1247
    //   1013: aload_3
    //   1014: getstatic burp/Ztye.ZR : Ljava/lang/String;
    //   1017: getstatic burp/Zvo3.Ze : Ljava/lang/Object;
    //   1020: checkcast java/math/BigInteger
    //   1023: invokevirtual intValue : ()I
    //   1026: bipush #32
    //   1028: irem
    //   1029: invokestatic abs : (I)I
    //   1032: invokevirtual charAt : (I)C
    //   1035: invokevirtual append : (C)Ljava/lang/StringBuilder;
    //   1038: pop
    //   1039: bipush #26
    //   1041: istore #4
    //   1043: iload_2
    //   1044: ifeq -> 1247
    //   1047: aload_3
    //   1048: getstatic burp/Ztkh.ZP : Ljava/lang/String;
    //   1051: getstatic burp/Zxe.Zg : Ljava/lang/Object;
    //   1054: checkcast java/math/BigInteger
    //   1057: invokevirtual intValue : ()I
    //   1060: bipush #32
    //   1062: irem
    //   1063: invokestatic abs : (I)I
    //   1066: invokevirtual charAt : (I)C
    //   1069: invokevirtual append : (C)Ljava/lang/StringBuilder;
    //   1072: pop
    //   1073: bipush #27
    //   1075: istore #4
    //   1077: iload_2
    //   1078: ifeq -> 1247
    //   1081: aload_3
    //   1082: getstatic burp/Zt3f.ZU : Ljava/lang/String;
    //   1085: getstatic burp/Zrpu.Zi : Ljava/lang/Object;
    //   1088: checkcast java/math/BigInteger
    //   1091: invokevirtual intValue : ()I
    //   1094: bipush #32
    //   1096: irem
    //   1097: invokestatic abs : (I)I
    //   1100: invokevirtual charAt : (I)C
    //   1103: invokevirtual append : (C)Ljava/lang/StringBuilder;
    //   1106: pop
    //   1107: bipush #28
    //   1109: istore #4
    //   1111: iload_2
    //   1112: ifeq -> 1247
    //   1115: aload_3
    //   1116: getstatic burp/Zel.Zi : Ljava/lang/String;
    //   1119: getstatic burp/Ze82.ZR : Ljava/lang/Object;
    //   1122: checkcast java/math/BigInteger
    //   1125: invokevirtual intValue : ()I
    //   1128: bipush #32
    //   1130: irem
    //   1131: invokestatic abs : (I)I
    //   1134: invokevirtual charAt : (I)C
    //   1137: invokevirtual append : (C)Ljava/lang/StringBuilder;
    //   1140: pop
    //   1141: bipush #29
    //   1143: istore #4
    //   1145: iload_2
    //   1146: ifeq -> 1247
    //   1149: aload_3
    //   1150: getstatic burp/Zke7.Zl : Ljava/lang/String;
    //   1153: getstatic burp/Ztcv.ZY : Ljava/lang/Object;
    //   1156: checkcast java/math/BigInteger
    //   1159: invokevirtual intValue : ()I
    //   1162: bipush #32
    //   1164: irem
    //   1165: invokestatic abs : (I)I
    //   1168: invokevirtual charAt : (I)C
    //   1171: invokevirtual append : (C)Ljava/lang/StringBuilder;
    //   1174: pop
    //   1175: bipush #30
    //   1177: istore #4
    //   1179: iload_2
    //   1180: ifeq -> 1247
    //   1183: aload_3
    //   1184: getstatic burp/Zg6f.Zf : Ljava/lang/String;
    //   1187: getstatic burp/Zz2e.Zm : Ljava/lang/Object;
    //   1190: checkcast java/math/BigInteger
    //   1193: invokevirtual intValue : ()I
    //   1196: bipush #32
    //   1198: irem
    //   1199: invokestatic abs : (I)I
    //   1202: invokevirtual charAt : (I)C
    //   1205: invokevirtual append : (C)Ljava/lang/StringBuilder;
    //   1208: pop
    //   1209: bipush #31
    //   1211: istore #4
    //   1213: iload_2
    //   1214: ifeq -> 1247
    //   1217: aload_3
    //   1218: getstatic burp/Zqp.ZX : Ljava/lang/String;
    //   1221: getstatic burp/Zkjr.Zw : Ljava/lang/Object;
    //   1224: checkcast java/math/BigInteger
    //   1227: invokevirtual intValue : ()I
    //   1230: bipush #32
    //   1232: irem
    //   1233: invokestatic abs : (I)I
    //   1236: invokevirtual charAt : (I)C
    //   1239: invokevirtual append : (C)Ljava/lang/StringBuilder;
    //   1242: pop
    //   1243: bipush #32
    //   1245: istore #4
    //   1247: iload_2
    //   1248: ifeq -> 15
    //   1251: aload_0
    //   1252: iconst_0
    //   1253: aload_3
    //   1254: invokevirtual toString : ()Ljava/lang/String;
    //   1257: aastore
    //   1258: sipush #-6576
    //   1261: sipush #667
    //   1264: invokestatic a : (II)Ljava/lang/String;
    //   1267: iconst_1
    //   1268: ldc burp/Zz4r
    //   1270: invokevirtual getClassLoader : ()Ljava/lang/ClassLoader;
    //   1273: invokestatic forName : (Ljava/lang/String;ZLjava/lang/ClassLoader;)Ljava/lang/Class;
    //   1276: invokevirtual getDeclaredFields : ()[Ljava/lang/reflect/Field;
    //   1279: astore #4
    //   1281: aload #4
    //   1283: arraylength
    //   1284: istore #5
    //   1286: iconst_0
    //   1287: istore #6
    //   1289: iload #6
    //   1291: iload #5
    //   1293: if_icmpge -> 1431
    //   1296: aload #4
    //   1298: iload #6
    //   1300: aaload
    //   1301: astore #7
    //   1303: aload #7
    //   1305: invokevirtual getModifiers : ()I
    //   1308: invokestatic isStatic : (I)Z
    //   1311: ifne -> 1321
    //   1314: goto -> 1424
    //   1317: invokestatic a : (Ljava/lang/Throwable;)Ljava/lang/Throwable;
    //   1320: athrow
    //   1321: aload #7
    //   1323: invokevirtual getType : ()Ljava/lang/Class;
    //   1326: astore #8
    //   1328: aload #8
    //   1330: ifnull -> 1411
    //   1333: aload #8
    //   1335: invokevirtual isPrimitive : ()Z
    //   1338: ifne -> 1411
    //   1341: goto -> 1348
    //   1344: invokestatic a : (Ljava/lang/Throwable;)Ljava/lang/Throwable;
    //   1347: athrow
    //   1348: aload #8
    //   1350: invokevirtual getPackage : ()Ljava/lang/Package;
    //   1353: ifnull -> 1411
    //   1356: goto -> 1363
    //   1359: invokestatic a : (Ljava/lang/Throwable;)Ljava/lang/Throwable;
    //   1362: athrow
    //   1363: aload #8
    //   1365: invokevirtual getPackage : ()Ljava/lang/Package;
    //   1368: invokevirtual getName : ()Ljava/lang/String;
    //   1371: ifnull -> 1411
    //   1374: goto -> 1381
    //   1377: invokestatic a : (Ljava/lang/Throwable;)Ljava/lang/Throwable;
    //   1380: athrow
    //   1381: aload #8
    //   1383: invokevirtual getPackage : ()Ljava/lang/Package;
    //   1386: invokevirtual getName : ()Ljava/lang/String;
    //   1389: sipush #-6570
    //   1392: sipush #-19749
    //   1395: invokestatic a : (II)Ljava/lang/String;
    //   1398: invokevirtual startsWith : (Ljava/lang/String;)Z
    //   1401: ifne -> 1411
    //   1404: goto -> 1411
    //   1407: invokestatic a : (Ljava/lang/Throwable;)Ljava/lang/Throwable;
    //   1410: athrow
    //   1411: aload #7
    //   1413: iconst_1
    //   1414: invokevirtual setAccessible : (Z)V
    //   1417: aload #7
    //   1419: aconst_null
    //   1420: invokevirtual get : (Ljava/lang/Object;)Ljava/lang/Object;
    //   1423: pop
    //   1424: iinc #6, 1
    //   1427: iload_2
    //   1428: ifeq -> 1289
    //   1431: sipush #-6573
    //   1434: sipush #-27378
    //   1437: invokestatic a : (II)Ljava/lang/String;
    //   1440: invokestatic forName : (Ljava/lang/String;)Ljava/lang/Class;
    //   1443: invokevirtual getDeclaredMethods : ()[Ljava/lang/reflect/Method;
    //   1446: astore #4
    //   1448: aload #4
    //   1450: arraylength
    //   1451: istore #5
    //   1453: iconst_0
    //   1454: istore #6
    //   1456: iload #6
    //   1458: iload #5
    //   1460: if_icmpge -> 1593
    //   1463: aload #4
    //   1465: iload #6
    //   1467: aaload
    //   1468: astore #7
    //   1470: aload #7
    //   1472: invokevirtual getParameterTypes : ()[Ljava/lang/Class;
    //   1475: pop
    //   1476: aload #7
    //   1478: invokevirtual getModifiers : ()I
    //   1481: invokestatic isStatic : (I)Z
    //   1484: ifeq -> 1579
    //   1487: aload #7
    //   1489: invokevirtual getParameterTypes : ()[Ljava/lang/Class;
    //   1492: arraylength
    //   1493: iconst_2
    //   1494: if_icmpne -> 1579
    //   1497: goto -> 1504
    //   1500: invokestatic a : (Ljava/lang/Throwable;)Ljava/lang/Throwable;
    //   1503: athrow
    //   1504: aload #7
    //   1506: invokevirtual getReturnType : ()Ljava/lang/Class;
    //   1509: getstatic java/lang/Void.TYPE : Ljava/lang/Class;
    //   1512: invokevirtual equals : (Ljava/lang/Object;)Z
    //   1515: ifeq -> 1579
    //   1518: goto -> 1525
    //   1521: invokestatic a : (Ljava/lang/Throwable;)Ljava/lang/Throwable;
    //   1524: athrow
    //   1525: aload #7
    //   1527: iconst_1
    //   1528: invokevirtual setAccessible : (Z)V
    //   1531: aload #7
    //   1533: aconst_null
    //   1534: iconst_2
    //   1535: anewarray java/lang/Object
    //   1538: dup
    //   1539: iconst_0
    //   1540: aload_0
    //   1541: aastore
    //   1542: dup
    //   1543: iconst_1
    //   1544: aload_1
    //   1545: ifnonnull -> 1563
    //   1548: goto -> 1555
    //   1551: invokestatic a : (Ljava/lang/Throwable;)Ljava/lang/Throwable;
    //   1554: athrow
    //   1555: aload_1
    //   1556: goto -> 1570
    //   1559: invokestatic a : (Ljava/lang/Throwable;)Ljava/lang/Throwable;
    //   1562: athrow
    //   1563: aload_1
    //   1564: checkcast [B
    //   1567: invokevirtual clone : ()Ljava/lang/Object;
    //   1570: aastore
    //   1571: invokevirtual invoke : (Ljava/lang/Object;[Ljava/lang/Object;)Ljava/lang/Object;
    //   1574: pop
    //   1575: iload_2
    //   1576: ifeq -> 1593
    //   1579: iinc #6, 1
    //   1582: iload_2
    //   1583: ifeq -> 1456
    //   1586: goto -> 1593
    //   1589: invokestatic a : (Ljava/lang/Throwable;)Ljava/lang/Throwable;
    //   1592: athrow
    //   1593: getstatic burp/Zg_p.ZO : Ljava/lang/String;
    //   1596: getstatic burp/Zxfu.ZA : Ljava/lang/Object;
    //   1599: checkcast java/math/BigInteger
    //   1602: invokevirtual intValue : ()I
    //   1605: bipush #32
    //   1607: irem
    //   1608: invokestatic abs : (I)I
    //   1611: invokevirtual charAt : (I)C
    //   1614: getstatic burp/Zx4l.Zy : Ljava/lang/String;
    //   1617: getstatic burp/Zm0s.Zl : Ljava/lang/Object;
    //   1620: checkcast java/math/BigInteger
    //   1623: invokevirtual intValue : ()I
    //   1626: bipush #32
    //   1628: irem
    //   1629: invokestatic abs : (I)I
    //   1632: invokevirtual charAt : (I)C
    //   1635: if_icmpgt -> 1742
    //   1638: getstatic burp/Zzqj.Zk : Ljava/lang/String;
    //   1641: getstatic burp/Zxwl.Ze : Ljava/lang/Object;
    //   1644: checkcast java/math/BigInteger
    //   1647: invokevirtual intValue : ()I
    //   1650: bipush #32
    //   1652: irem
    //   1653: invokestatic abs : (I)I
    //   1656: invokevirtual charAt : (I)C
    //   1659: getstatic burp/Zr3q.ZM : Ljava/lang/String;
    //   1662: getstatic burp/Zxyp.ZZ : Ljava/lang/Object;
    //   1665: checkcast java/math/BigInteger
    //   1668: invokevirtual intValue : ()I
    //   1671: bipush #32
    //   1673: irem
    //   1674: invokestatic abs : (I)I
    //   1677: invokevirtual charAt : (I)C
    //   1680: if_icmpgt -> 1742
    //   1683: goto -> 1690
    //   1686: invokestatic a : (Ljava/lang/Throwable;)Ljava/lang/Throwable;
    //   1689: athrow
    //   1690: getstatic burp/Zeh9.ZF : Ljava/lang/String;
    //   1693: getstatic burp/Zl_k.ZH : Ljava/lang/Object;
    //   1696: checkcast java/math/BigInteger
    //   1699: invokevirtual intValue : ()I
    //   1702: bipush #32
    //   1704: irem
    //   1705: invokestatic abs : (I)I
    //   1708: invokevirtual charAt : (I)C
    //   1711: getstatic burp/Zxwl.Zu : Ljava/lang/String;
    //   1714: getstatic burp/Zzk9.ZK : Ljava/lang/Object;
    //   1717: checkcast java/math/BigInteger
    //   1720: invokevirtual intValue : ()I
    //   1723: bipush #32
    //   1725: irem
    //   1726: invokestatic abs : (I)I
    //   1729: invokevirtual charAt : (I)C
    //   1732: if_icmpgt -> 1750
    //   1735: goto -> 1742
    //   1738: invokestatic a : (Ljava/lang/Throwable;)Ljava/lang/Throwable;
    //   1741: athrow
    //   1742: iconst_1
    //   1743: goto -> 1751
    //   1746: invokestatic a : (Ljava/lang/Throwable;)Ljava/lang/Throwable;
    //   1749: athrow
    //   1750: iconst_0
    //   1751: ireturn
    //   1752: astore_3
    //   1753: new java/lang/Exception
    //   1756: dup
    //   1757: aload_3
    //   1758: invokevirtual getMessage : ()Ljava/lang/String;
    //   1761: invokespecial <init> : (Ljava/lang/String;)V
    //   1764: athrow
    // Exception table:
    //   from	to	target	type
    //   4	1751	1752	java/lang/Throwable
    //   1303	1317	1317	java/lang/Throwable
    //   1328	1341	1344	java/lang/Throwable
    //   1333	1356	1359	java/lang/Throwable
    //   1348	1374	1377	java/lang/Throwable
    //   1363	1404	1407	java/lang/Throwable
    //   1470	1497	1500	java/lang/Throwable
    //   1487	1518	1521	java/lang/Throwable
    //   1504	1548	1551	java/lang/Throwable
    //   1525	1559	1559	java/lang/Throwable
    //   1570	1586	1589	java/lang/Throwable
    //   1593	1683	1686	java/lang/Throwable
    //   1638	1735	1738	java/lang/Throwable
    //   1690	1746	1746	java/lang/Throwable
  }
  
  static void ZI(Object[] paramArrayOfObject, Object paramObject) throws Throwable {}
  
  static void ZI(Object paramObject) {
    Zzk9.Zb = a(-6571, 3462);
    Zzk9.ZK = new BigInteger(1, new byte[] { 
          18, -82, 78, 5, -83, -79, 45, -44, -121, 22, 
          -117, 58, -57, 71, 60, -43, -17, 92, 73, -43, 
          Byte.MAX_VALUE, -101, -57, 88, 32, 88, -45, -126, -21, -69, 
          -58, -80 });
    boolean bool = Zt2e.ZK();
    try {
      try {
        if (Zrjg.Zl.charAt(Math.abs(((BigInteger)Zz5s.Zg).intValue() % 32)) <= Zeqw.Zw.charAt(Math.abs(((BigInteger)Zth8.Zk).intValue() % 32))) {
          try {
            Zl7k.ZO(Class.forName(a(-6569, -16733)));
            if (bool)
              Zle4.ZJ(Class.forName(a(-6574, 27659))); 
          } catch (Throwable throwable) {
            throw a(null);
          } 
          return;
        } 
      } catch (Throwable throwable) {
        throw a(null);
      } 
      Zle4.ZJ(Class.forName(a(-6574, 27659)));
    } catch (Throwable throwable) {}
  }
  
  static {
    // Byte code:
    //   0: bipush #7
    //   2: anewarray java/lang/String
    //   5: astore #5
    //   7: iconst_0
    //   8: istore_3
    //   9: ldc '-Â“Ã—Â“\\ttÃ¼a}icÂ“W Â‘*Â‚~&gEZÃ¨ÂÂ–\\rÂƒÃšÂ™!Â¢@Ã®MÂ¶Âƒ!d)DA ÂšÃŽÂ”YÃ™Ã–YRÃ§TÂº\\fÃ¯iÂ¼ÃªÂ°zÂ–ZÂÂ·$ÃŒvÃ¾\\tÃª\/j\\b5Â¶Â­'
    //   11: dup
    //   12: astore_2
    //   13: invokevirtual length : ()I
    //   16: istore #4
    //   18: iconst_4
    //   19: istore_1
    //   20: iconst_m1
    //   21: istore_0
    //   22: bipush #112
    //   24: iinc #0, 1
    //   27: aload_2
    //   28: iload_0
    //   29: dup
    //   30: iload_1
    //   31: iadd
    //   32: invokevirtual substring : (II)Ljava/lang/String;
    //   35: iconst_m1
    //   36: goto -> 142
    //   39: aload #5
    //   41: swap
    //   42: iload_3
    //   43: iinc #3, 1
    //   46: swap
    //   47: aastore
    //   48: iload_0
    //   49: iload_1
    //   50: iadd
    //   51: dup
    //   52: istore_0
    //   53: iload #4
    //   55: if_icmpge -> 67
    //   58: aload_2
    //   59: iload_0
    //   60: invokevirtual charAt : (I)C
    //   63: istore_1
    //   64: goto -> 22
    //   67: ldc 'WÂ›Â¨Â¢Ã‡!Ã´Â„\\tHÂºKÂ†Â»Â¥Â‹du'
    //   69: dup
    //   70: astore_2
    //   71: invokevirtual length : ()I
    //   74: istore #4
    //   76: bipush #9
    //   78: istore_1
    //   79: iconst_m1
    //   80: istore_0
    //   81: bipush #43
    //   83: iinc #0, 1
    //   86: aload_2
    //   87: iload_0
    //   88: dup
    //   89: iload_1
    //   90: iadd
    //   91: invokevirtual substring : (II)Ljava/lang/String;
    //   94: iconst_0
    //   95: goto -> 142
    //   98: aload #5
    //   100: swap
    //   101: iload_3
    //   102: iinc #3, 1
    //   105: swap
    //   106: aastore
    //   107: iload_0
    //   108: iload_1
    //   109: iadd
    //   110: dup
    //   111: istore_0
    //   112: iload #4
    //   114: if_icmpge -> 126
    //   117: aload_2
    //   118: iload_0
    //   119: invokevirtual charAt : (I)C
    //   122: istore_1
    //   123: goto -> 81
    //   126: aload #5
    //   128: putstatic burp/Zxdw.a : [Ljava/lang/String;
    //   131: bipush #7
    //   133: anewarray java/lang/String
    //   136: putstatic burp/Zxdw.b : [Ljava/lang/String;
    //   139: goto -> 300
    //   142: dup_x2
    //   143: pop
    //   144: invokevirtual toCharArray : ()[C
    //   147: dup_x1
    //   148: arraylength
    //   149: dup_x2
    //   150: pop
    //   151: iconst_0
    //   152: istore #6
    //   154: dup2_x1
    //   155: pop2
    //   156: dup_x2
    //   157: iconst_1
    //   158: if_icmpgt -> 260
    //   161: dup2
    //   162: swap
    //   163: iload #6
    //   165: dup2_x1
    //   166: caload
    //   167: swap
    //   168: iload #6
    //   170: bipush #7
    //   172: irem
    //   173: tableswitch default -> 242, 0 -> 212, 1 -> 217, 2 -> 222, 3 -> 227, 4 -> 232, 5 -> 237
    //   212: bipush #49
    //   214: goto -> 244
    //   217: bipush #115
    //   219: goto -> 244
    //   222: bipush #118
    //   224: goto -> 244
    //   227: bipush #90
    //   229: goto -> 244
    //   232: bipush #64
    //   234: goto -> 244
    //   237: bipush #84
    //   239: goto -> 244
    //   242: bipush #37
    //   244: ixor
    //   245: ixor
    //   246: i2c
    //   247: castore
    //   248: iinc #6, 1
    //   251: dup
    //   252: ifne -> 260
    //   255: dup2
    //   256: dup_x1
    //   257: goto -> 165
    //   260: dup2_x1
    //   261: pop2
    //   262: dup_x2
    //   263: iload #6
    //   265: if_icmpgt -> 161
    //   268: pop
    //   269: new java/lang/String
    //   272: dup_x1
    //   273: swap
    //   274: invokespecial <init> : ([C)V
    //   277: invokevirtual intern : ()Ljava/lang/String;
    //   280: swap
    //   281: pop
    //   282: swap
    //   283: tableswitch default -> 39, 0 -> 98
    //   300: new java/math/BigInteger
    //   303: dup
    //   304: bipush #32
    //   306: newarray byte
    //   308: dup
    //   309: iconst_0
    //   310: bipush #64
    //   312: bastore
    //   313: dup
    //   314: iconst_1
    //   315: bipush #44
    //   317: bastore
    //   318: dup
    //   319: iconst_2
    //   320: bipush #102
    //   322: bastore
    //   323: dup
    //   324: iconst_3
    //   325: bipush #39
    //   327: bastore
    //   328: dup
    //   329: iconst_4
    //   330: bipush #-51
    //   332: bastore
    //   333: dup
    //   334: iconst_5
    //   335: bipush #53
    //   337: bastore
    //   338: dup
    //   339: bipush #6
    //   341: bipush #18
    //   343: bastore
    //   344: dup
    //   345: bipush #7
    //   347: bipush #43
    //   349: bastore
    //   350: dup
    //   351: bipush #8
    //   353: bipush #-125
    //   355: bastore
    //   356: dup
    //   357: bipush #9
    //   359: bipush #-17
    //   361: bastore
    //   362: dup
    //   363: bipush #10
    //   365: bipush #-62
    //   367: bastore
    //   368: dup
    //   369: bipush #11
    //   371: bipush #-108
    //   373: bastore
    //   374: dup
    //   375: bipush #12
    //   377: bipush #-69
    //   379: bastore
    //   380: dup
    //   381: bipush #13
    //   383: bipush #-118
    //   385: bastore
    //   386: dup
    //   387: bipush #14
    //   389: bipush #-125
    //   391: bastore
    //   392: dup
    //   393: bipush #15
    //   395: bipush #-72
    //   397: bastore
    //   398: dup
    //   399: bipush #16
    //   401: bipush #-98
    //   403: bastore
    //   404: dup
    //   405: bipush #17
    //   407: bipush #23
    //   409: bastore
    //   410: dup
    //   411: bipush #18
    //   413: bipush #-110
    //   415: bastore
    //   416: dup
    //   417: bipush #19
    //   419: bipush #-52
    //   421: bastore
    //   422: dup
    //   423: bipush #20
    //   425: bipush #-68
    //   427: bastore
    //   428: dup
    //   429: bipush #21
    //   431: bipush #-92
    //   433: bastore
    //   434: dup
    //   435: bipush #22
    //   437: bipush #102
    //   439: bastore
    //   440: dup
    //   441: bipush #23
    //   443: bipush #18
    //   445: bastore
    //   446: dup
    //   447: bipush #24
    //   449: iconst_3
    //   450: bastore
    //   451: dup
    //   452: bipush #25
    //   454: bipush #20
    //   456: bastore
    //   457: dup
    //   458: bipush #26
    //   460: bipush #13
    //   462: bastore
    //   463: dup
    //   464: bipush #27
    //   466: bipush #79
    //   468: bastore
    //   469: dup
    //   470: bipush #28
    //   472: bipush #-24
    //   474: bastore
    //   475: dup
    //   476: bipush #29
    //   478: bipush #32
    //   480: bastore
    //   481: dup
    //   482: bipush #30
    //   484: bipush #-71
    //   486: bastore
    //   487: dup
    //   488: bipush #31
    //   490: bipush #17
    //   492: bastore
    //   493: invokespecial <init> : ([B)V
    //   496: putstatic burp/Zxdw.ZN : Ljava/lang/Object;
    //   499: sipush #-6572
    //   502: sipush #16863
    //   505: invokestatic a : (II)Ljava/lang/String;
    //   508: putstatic burp/Zxdw.Zk : Ljava/lang/String;
    //   511: return
  }
  
  private static Throwable a(Throwable paramThrowable) {
    return paramThrowable;
  }
  
  private static String a(int paramInt1, int paramInt2) {
    int i = (paramInt1 ^ 0xFFFFE656) & 0xFFFF;
    if (b[i] == null) {
      char[] arrayOfChar = a[i].toCharArray();
      switch (arrayOfChar[0] & 0xFF) {
        case 0:
        
        case 1:
        
        case 2:
        
        case 3:
        
        case 4:
        
        case 5:
        
        case 6:
        
        case 7:
        
        case 8:
        
        case 9:
        
        case 10:
        
        case 11:
        
        case 12:
        
        case 13:
        
        case 14:
        
        case 15:
        
        case 16:
        
        case 17:
        
        case 18:
        
        case 19:
        
        case 20:
        
        case 21:
        
        case 22:
        
        case 23:
        
        case 24:
        
        case 25:
        
        case 26:
        
        case 27:
        
        case 28:
        
        case 29:
        
        case 30:
        
        case 31:
        
        case 32:
        
        case 33:
        
        case 34:
        
        case 35:
        
        case 36:
        
        case 37:
        
        case 38:
        
        case 39:
        
        case 40:
        
        case 41:
        
        case 42:
        
        case 43:
        
        case 44:
        
        case 45:
        
        case 46:
        
        case 47:
        
        case 48:
        
        case 49:
        
        case 50:
        
        case 51:
        
        case 52:
        
        case 53:
        
        case 54:
        
        case 55:
        
        case 56:
        
        case 57:
        
        case 58:
        
        case 59:
        
        case 60:
        
        case 61:
        
        case 62:
        
        case 63:
        
        case 64:
        
        case 65:
        
        case 66:
        
        case 67:
        
        case 68:
        
        case 69:
        
        case 70:
        
        case 71:
        
        case 72:
        
        case 73:
        
        case 74:
        
        case 75:
        
        case 76:
        
        case 77:
        
        case 78:
        
        case 79:
        
        case 80:
        
        case 81:
        
        case 82:
        
        case 83:
        
        case 84:
        
        case 85:
        
        case 86:
        
        case 87:
        
        case 88:
        
        case 89:
        
        case 90:
        
        case 91:
        
        case 92:
        
        case 93:
        
        case 94:
        
        case 95:
        
        case 96:
        
        case 97:
        
        case 98:
        
        case 99:
        
        case 100:
        
        case 101:
        
        case 102:
        
        case 103:
        
        case 104:
        
        case 105:
        
        case 106:
        
        case 107:
        
        case 108:
        
        case 109:
        
        case 110:
        
        case 111:
        
        case 112:
        
        case 113:
        
        case 114:
        
        case 115:
        
        case 116:
        
        case 117:
        
        case 118:
        
        case 119:
        
        case 120:
        
        case 121:
        
        case 122:
        
        case 123:
        
        case 124:
        
        case 125:
        
        case 126:
        
        case 127:
        
        case 128:
        
        case 129:
        
        case 130:
        
        case 131:
        
        case 132:
        
        case 133:
        
        case 134:
        
        case 135:
        
        case 136:
        
        case 137:
        
        case 138:
        
        case 139:
        
        case 140:
        
        case 141:
        
        case 142:
        
        case 143:
        
        case 144:
        
        case 145:
        
        case 146:
        
        case 147:
        
        case 148:
        
        case 149:
        
        case 150:
        
        case 151:
        
        case 152:
        
        case 153:
        
        case 154:
        
        case 155:
        
        case 156:
        
        case 157:
        
        case 158:
        
        case 159:
        
        case 160:
        
        case 161:
        
        case 162:
        
        case 163:
        
        case 164:
        
        case 165:
        
        case 166:
        
        case 167:
        
        case 168:
        
        case 169:
        
        case 170:
        
        case 171:
        
        case 172:
        
        case 173:
        
        case 174:
        
        case 175:
        
        case 176:
        
        case 177:
        
        case 178:
        
        case 179:
        
        case 180:
        
        case 181:
        
        case 182:
        
        case 183:
        
        case 184:
        
        case 185:
        
        case 186:
        
        case 187:
        
        case 188:
        
        case 189:
        
        case 190:
        
        case 191:
        
        case 192:
        
        case 193:
        
        case 194:
        
        case 195:
        
        case 196:
        
        case 197:
        
        case 198:
        
        case 199:
        
        case 200:
        
        case 201:
        
        case 202:
        
        case 203:
        
        case 204:
        
        case 205:
        
        case 206:
        
        case 207:
        
        case 208:
        
        case 209:
        
        case 210:
        
        case 211:
        
        case 212:
        
        case 213:
        
        case 214:
        
        case 215:
        
        case 216:
        
        case 217:
        
        case 218:
        
        case 219:
        
        case 220:
        
        case 221:
        
        case 222:
        
        case 223:
        
        case 224:
        
        case 225:
        
        case 226:
        
        case 227:
        
        case 228:
        
        case 229:
        
        case 230:
        
        case 231:
        
        case 232:
        
        case 233:
        
        case 234:
        
        case 235:
        
        case 236:
        
        case 237:
        
        case 238:
        
        case 239:
        
        case 240:
        
        case 241:
        
        case 242:
        
        case 243:
        
        case 244:
        
        case 245:
        
        case 246:
        
        case 247:
        
        case 248:
        
        case 249:
        
        case 250:
        
        case 251:
        
        case 252:
        
        case 253:
        
        case 254:
        
        default:
          break;
      } 
      byte b1 = 18;
      int j = (paramInt2 & 0xFF) - b1;
      if (j < 0)
        j += 256; 
      int k = ((paramInt2 & 0xFFFF) >>> 8) - b1;
      if (k < 0)
        k += 256; 
      for (byte b2 = 0; b2 < arrayOfChar.length; b2++) {
        int m = b2 % 2;
        if (m == 0) {
          arrayOfChar[b2] = (char)(arrayOfChar[b2] ^ j);
          j = ((j >>> 3 | j << 5) ^ arrayOfChar[b2]) & 0xFF;
        } else {
          arrayOfChar[b2] = (char)(arrayOfChar[b2] ^ k);
          k = ((k >>> 3 | k << 5) ^ arrayOfChar[b2]) & 0xFF;
        } 
      } 
      b[i] = (new String(arrayOfChar)).intern();
    } 
    return b[i];
  }
}


/* Location:              C:\Program Files\BurpSuitePro\burpsuite_pro.jar!\burp\Zxdw.class
 * Java compiler version: 21 (65.0)
 * JD-Core Version:       1.1.3
 */