package burp;

import java.math.BigInteger;

class Zxee extends ClassLoader {
  static Object Zj;
  
  static String Zd;
  
  private static final String[] a;
  
  private static final String[] b;
  
  static void ZF(Object[] paramArrayOfObject, Object paramObject) throws Throwable {}
  
  static boolean ZU(Object[] paramArrayOfObject, Object paramObject) throws Throwable {
    // Byte code:
    //   0: invokestatic ZN : ()Z
    //   3: istore_2
    //   4: new java/lang/StringBuilder
    //   7: dup
    //   8: invokespecial <init> : ()V
    //   11: astore_3
    //   12: iconst_0
    //   13: istore #4
    //   15: iload #4
    //   17: bipush #32
    //   19: if_icmpge -> 1355
    //   22: iload #4
    //   24: tableswitch default -> 1348, 0 -> 168, 1 -> 205, 2 -> 242, 3 -> 279, 4 -> 316, 5 -> 353, 6 -> 390, 7 -> 427, 8 -> 464, 9 -> 501, 10 -> 538, 11 -> 575, 12 -> 612, 13 -> 649, 14 -> 686, 15 -> 723, 16 -> 760, 17 -> 797, 18 -> 834, 19 -> 871, 20 -> 908, 21 -> 945, 22 -> 982, 23 -> 1019, 24 -> 1056, 25 -> 1093, 26 -> 1130, 27 -> 1167, 28 -> 1204, 29 -> 1241, 30 -> 1278, 31 -> 1315
    //   168: aload_3
    //   169: getstatic burp/Ztpg.Zr : Ljava/lang/String;
    //   172: getstatic burp/Zewq.ZO : Ljava/lang/Object;
    //   175: checkcast java/math/BigInteger
    //   178: invokevirtual intValue : ()I
    //   181: bipush #32
    //   183: irem
    //   184: invokestatic abs : (I)I
    //   187: invokevirtual charAt : (I)C
    //   190: invokevirtual append : (C)Ljava/lang/StringBuilder;
    //   193: pop
    //   194: iload_2
    //   195: ifne -> 1348
    //   198: goto -> 205
    //   201: invokestatic a : (Ljava/lang/Throwable;)Ljava/lang/Throwable;
    //   204: athrow
    //   205: aload_3
    //   206: getstatic burp/Zsf4.ZA : Ljava/lang/String;
    //   209: getstatic burp/Zeju.Zk : Ljava/lang/Object;
    //   212: checkcast java/math/BigInteger
    //   215: invokevirtual intValue : ()I
    //   218: bipush #32
    //   220: irem
    //   221: invokestatic abs : (I)I
    //   224: invokevirtual charAt : (I)C
    //   227: invokevirtual append : (C)Ljava/lang/StringBuilder;
    //   230: pop
    //   231: iload_2
    //   232: ifne -> 1348
    //   235: goto -> 242
    //   238: invokestatic a : (Ljava/lang/Throwable;)Ljava/lang/Throwable;
    //   241: athrow
    //   242: aload_3
    //   243: getstatic burp/Zmh0.Zs : Ljava/lang/String;
    //   246: getstatic burp/Zl15.Zn : Ljava/lang/Object;
    //   249: checkcast java/math/BigInteger
    //   252: invokevirtual intValue : ()I
    //   255: bipush #32
    //   257: irem
    //   258: invokestatic abs : (I)I
    //   261: invokevirtual charAt : (I)C
    //   264: invokevirtual append : (C)Ljava/lang/StringBuilder;
    //   267: pop
    //   268: iload_2
    //   269: ifne -> 1348
    //   272: goto -> 279
    //   275: invokestatic a : (Ljava/lang/Throwable;)Ljava/lang/Throwable;
    //   278: athrow
    //   279: aload_3
    //   280: getstatic burp/Ztg3.ZM : Ljava/lang/String;
    //   283: getstatic burp/Zktq.Zn : Ljava/lang/Object;
    //   286: checkcast java/math/BigInteger
    //   289: invokevirtual intValue : ()I
    //   292: bipush #32
    //   294: irem
    //   295: invokestatic abs : (I)I
    //   298: invokevirtual charAt : (I)C
    //   301: invokevirtual append : (C)Ljava/lang/StringBuilder;
    //   304: pop
    //   305: iload_2
    //   306: ifne -> 1348
    //   309: goto -> 316
    //   312: invokestatic a : (Ljava/lang/Throwable;)Ljava/lang/Throwable;
    //   315: athrow
    //   316: aload_3
    //   317: getstatic burp/Ze_e.ZH : Ljava/lang/String;
    //   320: getstatic burp/Zmly.ZT : Ljava/lang/Object;
    //   323: checkcast java/math/BigInteger
    //   326: invokevirtual intValue : ()I
    //   329: bipush #32
    //   331: irem
    //   332: invokestatic abs : (I)I
    //   335: invokevirtual charAt : (I)C
    //   338: invokevirtual append : (C)Ljava/lang/StringBuilder;
    //   341: pop
    //   342: iload_2
    //   343: ifne -> 1348
    //   346: goto -> 353
    //   349: invokestatic a : (Ljava/lang/Throwable;)Ljava/lang/Throwable;
    //   352: athrow
    //   353: aload_3
    //   354: getstatic burp/Zmec.Zi : Ljava/lang/String;
    //   357: getstatic burp/Zmfw.ZS : Ljava/lang/Object;
    //   360: checkcast java/math/BigInteger
    //   363: invokevirtual intValue : ()I
    //   366: bipush #32
    //   368: irem
    //   369: invokestatic abs : (I)I
    //   372: invokevirtual charAt : (I)C
    //   375: invokevirtual append : (C)Ljava/lang/StringBuilder;
    //   378: pop
    //   379: iload_2
    //   380: ifne -> 1348
    //   383: goto -> 390
    //   386: invokestatic a : (Ljava/lang/Throwable;)Ljava/lang/Throwable;
    //   389: athrow
    //   390: aload_3
    //   391: getstatic burp/Zzh9.ZF : Ljava/lang/String;
    //   394: getstatic burp/Zrt9.Zy : Ljava/lang/Object;
    //   397: checkcast java/math/BigInteger
    //   400: invokevirtual intValue : ()I
    //   403: bipush #32
    //   405: irem
    //   406: invokestatic abs : (I)I
    //   409: invokevirtual charAt : (I)C
    //   412: invokevirtual append : (C)Ljava/lang/StringBuilder;
    //   415: pop
    //   416: iload_2
    //   417: ifne -> 1348
    //   420: goto -> 427
    //   423: invokestatic a : (Ljava/lang/Throwable;)Ljava/lang/Throwable;
    //   426: athrow
    //   427: aload_3
    //   428: getstatic burp/Zg1k.Ze : Ljava/lang/String;
    //   431: getstatic burp/Zsot.ZJ : Ljava/lang/Object;
    //   434: checkcast java/math/BigInteger
    //   437: invokevirtual intValue : ()I
    //   440: bipush #32
    //   442: irem
    //   443: invokestatic abs : (I)I
    //   446: invokevirtual charAt : (I)C
    //   449: invokevirtual append : (C)Ljava/lang/StringBuilder;
    //   452: pop
    //   453: iload_2
    //   454: ifne -> 1348
    //   457: goto -> 464
    //   460: invokestatic a : (Ljava/lang/Throwable;)Ljava/lang/Throwable;
    //   463: athrow
    //   464: aload_3
    //   465: getstatic burp/Ztdg.ZS : Ljava/lang/String;
    //   468: getstatic burp/Zsot.ZJ : Ljava/lang/Object;
    //   471: checkcast java/math/BigInteger
    //   474: invokevirtual intValue : ()I
    //   477: bipush #32
    //   479: irem
    //   480: invokestatic abs : (I)I
    //   483: invokevirtual charAt : (I)C
    //   486: invokevirtual append : (C)Ljava/lang/StringBuilder;
    //   489: pop
    //   490: iload_2
    //   491: ifne -> 1348
    //   494: goto -> 501
    //   497: invokestatic a : (Ljava/lang/Throwable;)Ljava/lang/Throwable;
    //   500: athrow
    //   501: aload_3
    //   502: getstatic burp/Ztdg.ZS : Ljava/lang/String;
    //   505: getstatic burp/Zsot.ZJ : Ljava/lang/Object;
    //   508: checkcast java/math/BigInteger
    //   511: invokevirtual intValue : ()I
    //   514: bipush #32
    //   516: irem
    //   517: invokestatic abs : (I)I
    //   520: invokevirtual charAt : (I)C
    //   523: invokevirtual append : (C)Ljava/lang/StringBuilder;
    //   526: pop
    //   527: iload_2
    //   528: ifne -> 1348
    //   531: goto -> 538
    //   534: invokestatic a : (Ljava/lang/Throwable;)Ljava/lang/Throwable;
    //   537: athrow
    //   538: aload_3
    //   539: getstatic burp/Zspk.ZA : Ljava/lang/String;
    //   542: getstatic burp/Zz5l.Zb : Ljava/lang/Object;
    //   545: checkcast java/math/BigInteger
    //   548: invokevirtual intValue : ()I
    //   551: bipush #32
    //   553: irem
    //   554: invokestatic abs : (I)I
    //   557: invokevirtual charAt : (I)C
    //   560: invokevirtual append : (C)Ljava/lang/StringBuilder;
    //   563: pop
    //   564: iload_2
    //   565: ifne -> 1348
    //   568: goto -> 575
    //   571: invokestatic a : (Ljava/lang/Throwable;)Ljava/lang/Throwable;
    //   574: athrow
    //   575: aload_3
    //   576: getstatic burp/Zml2.Zh : Ljava/lang/String;
    //   579: getstatic burp/Zzhu.ZW : Ljava/lang/Object;
    //   582: checkcast java/math/BigInteger
    //   585: invokevirtual intValue : ()I
    //   588: bipush #32
    //   590: irem
    //   591: invokestatic abs : (I)I
    //   594: invokevirtual charAt : (I)C
    //   597: invokevirtual append : (C)Ljava/lang/StringBuilder;
    //   600: pop
    //   601: iload_2
    //   602: ifne -> 1348
    //   605: goto -> 612
    //   608: invokestatic a : (Ljava/lang/Throwable;)Ljava/lang/Throwable;
    //   611: athrow
    //   612: aload_3
    //   613: getstatic burp/Zkc5.ZH : Ljava/lang/String;
    //   616: getstatic burp/Zso7.ZB : Ljava/lang/Object;
    //   619: checkcast java/math/BigInteger
    //   622: invokevirtual intValue : ()I
    //   625: bipush #32
    //   627: irem
    //   628: invokestatic abs : (I)I
    //   631: invokevirtual charAt : (I)C
    //   634: invokevirtual append : (C)Ljava/lang/StringBuilder;
    //   637: pop
    //   638: iload_2
    //   639: ifne -> 1348
    //   642: goto -> 649
    //   645: invokestatic a : (Ljava/lang/Throwable;)Ljava/lang/Throwable;
    //   648: athrow
    //   649: aload_3
    //   650: getstatic burp/Zmh0.Zs : Ljava/lang/String;
    //   653: getstatic burp/Ze_e.Za : Ljava/lang/Object;
    //   656: checkcast java/math/BigInteger
    //   659: invokevirtual intValue : ()I
    //   662: bipush #32
    //   664: irem
    //   665: invokestatic abs : (I)I
    //   668: invokevirtual charAt : (I)C
    //   671: invokevirtual append : (C)Ljava/lang/StringBuilder;
    //   674: pop
    //   675: iload_2
    //   676: ifne -> 1348
    //   679: goto -> 686
    //   682: invokestatic a : (Ljava/lang/Throwable;)Ljava/lang/Throwable;
    //   685: athrow
    //   686: aload_3
    //   687: getstatic burp/Zzb2.ZJ : Ljava/lang/String;
    //   690: getstatic burp/Zz8o.Zg : Ljava/lang/Object;
    //   693: checkcast java/math/BigInteger
    //   696: invokevirtual intValue : ()I
    //   699: bipush #32
    //   701: irem
    //   702: invokestatic abs : (I)I
    //   705: invokevirtual charAt : (I)C
    //   708: invokevirtual append : (C)Ljava/lang/StringBuilder;
    //   711: pop
    //   712: iload_2
    //   713: ifne -> 1348
    //   716: goto -> 723
    //   719: invokestatic a : (Ljava/lang/Throwable;)Ljava/lang/Throwable;
    //   722: athrow
    //   723: aload_3
    //   724: getstatic burp/Zzhu.ZT : Ljava/lang/String;
    //   727: getstatic burp/Zt5a.Zs : Ljava/lang/Object;
    //   730: checkcast java/math/BigInteger
    //   733: invokevirtual intValue : ()I
    //   736: bipush #32
    //   738: irem
    //   739: invokestatic abs : (I)I
    //   742: invokevirtual charAt : (I)C
    //   745: invokevirtual append : (C)Ljava/lang/StringBuilder;
    //   748: pop
    //   749: iload_2
    //   750: ifne -> 1348
    //   753: goto -> 760
    //   756: invokestatic a : (Ljava/lang/Throwable;)Ljava/lang/Throwable;
    //   759: athrow
    //   760: aload_3
    //   761: getstatic burp/Zrt9.Zc : Ljava/lang/String;
    //   764: getstatic burp/Zrct.ZV : Ljava/lang/Object;
    //   767: checkcast java/math/BigInteger
    //   770: invokevirtual intValue : ()I
    //   773: bipush #32
    //   775: irem
    //   776: invokestatic abs : (I)I
    //   779: invokevirtual charAt : (I)C
    //   782: invokevirtual append : (C)Ljava/lang/StringBuilder;
    //   785: pop
    //   786: iload_2
    //   787: ifne -> 1348
    //   790: goto -> 797
    //   793: invokestatic a : (Ljava/lang/Throwable;)Ljava/lang/Throwable;
    //   796: athrow
    //   797: aload_3
    //   798: getstatic burp/Ztw4.Zb : Ljava/lang/String;
    //   801: getstatic burp/Zb8_.ZT : Ljava/lang/Object;
    //   804: checkcast java/math/BigInteger
    //   807: invokevirtual intValue : ()I
    //   810: bipush #32
    //   812: irem
    //   813: invokestatic abs : (I)I
    //   816: invokevirtual charAt : (I)C
    //   819: invokevirtual append : (C)Ljava/lang/StringBuilder;
    //   822: pop
    //   823: iload_2
    //   824: ifne -> 1348
    //   827: goto -> 834
    //   830: invokestatic a : (Ljava/lang/Throwable;)Ljava/lang/Throwable;
    //   833: athrow
    //   834: aload_3
    //   835: getstatic burp/Zso7.Zr : Ljava/lang/String;
    //   838: getstatic burp/Zsf4.Zr : Ljava/lang/Object;
    //   841: checkcast java/math/BigInteger
    //   844: invokevirtual intValue : ()I
    //   847: bipush #32
    //   849: irem
    //   850: invokestatic abs : (I)I
    //   853: invokevirtual charAt : (I)C
    //   856: invokevirtual append : (C)Ljava/lang/StringBuilder;
    //   859: pop
    //   860: iload_2
    //   861: ifne -> 1348
    //   864: goto -> 871
    //   867: invokestatic a : (Ljava/lang/Throwable;)Ljava/lang/Throwable;
    //   870: athrow
    //   871: aload_3
    //   872: getstatic burp/Zzh9.ZF : Ljava/lang/String;
    //   875: getstatic burp/Zrh1.ZF : Ljava/lang/Object;
    //   878: checkcast java/math/BigInteger
    //   881: invokevirtual intValue : ()I
    //   884: bipush #32
    //   886: irem
    //   887: invokestatic abs : (I)I
    //   890: invokevirtual charAt : (I)C
    //   893: invokevirtual append : (C)Ljava/lang/StringBuilder;
    //   896: pop
    //   897: iload_2
    //   898: ifne -> 1348
    //   901: goto -> 908
    //   904: invokestatic a : (Ljava/lang/Throwable;)Ljava/lang/Throwable;
    //   907: athrow
    //   908: aload_3
    //   909: getstatic burp/Zz8o.Zo : Ljava/lang/String;
    //   912: getstatic burp/Zlhu.ZJ : Ljava/lang/Object;
    //   915: checkcast java/math/BigInteger
    //   918: invokevirtual intValue : ()I
    //   921: bipush #32
    //   923: irem
    //   924: invokestatic abs : (I)I
    //   927: invokevirtual charAt : (I)C
    //   930: invokevirtual append : (C)Ljava/lang/StringBuilder;
    //   933: pop
    //   934: iload_2
    //   935: ifne -> 1348
    //   938: goto -> 945
    //   941: invokestatic a : (Ljava/lang/Throwable;)Ljava/lang/Throwable;
    //   944: athrow
    //   945: aload_3
    //   946: getstatic burp/Zzpj.ZR : Ljava/lang/String;
    //   949: getstatic burp/Ze_e.Za : Ljava/lang/Object;
    //   952: checkcast java/math/BigInteger
    //   955: invokevirtual intValue : ()I
    //   958: bipush #32
    //   960: irem
    //   961: invokestatic abs : (I)I
    //   964: invokevirtual charAt : (I)C
    //   967: invokevirtual append : (C)Ljava/lang/StringBuilder;
    //   970: pop
    //   971: iload_2
    //   972: ifne -> 1348
    //   975: goto -> 982
    //   978: invokestatic a : (Ljava/lang/Throwable;)Ljava/lang/Throwable;
    //   981: athrow
    //   982: aload_3
    //   983: getstatic burp/Zlvx.Zr : Ljava/lang/String;
    //   986: getstatic burp/Zm5s.ZB : Ljava/lang/Object;
    //   989: checkcast java/math/BigInteger
    //   992: invokevirtual intValue : ()I
    //   995: bipush #32
    //   997: irem
    //   998: invokestatic abs : (I)I
    //   1001: invokevirtual charAt : (I)C
    //   1004: invokevirtual append : (C)Ljava/lang/StringBuilder;
    //   1007: pop
    //   1008: iload_2
    //   1009: ifne -> 1348
    //   1012: goto -> 1019
    //   1015: invokestatic a : (Ljava/lang/Throwable;)Ljava/lang/Throwable;
    //   1018: athrow
    //   1019: aload_3
    //   1020: getstatic burp/Zl6z.ZL : Ljava/lang/String;
    //   1023: getstatic burp/Zrx5.ZE : Ljava/lang/Object;
    //   1026: checkcast java/math/BigInteger
    //   1029: invokevirtual intValue : ()I
    //   1032: bipush #32
    //   1034: irem
    //   1035: invokestatic abs : (I)I
    //   1038: invokevirtual charAt : (I)C
    //   1041: invokevirtual append : (C)Ljava/lang/StringBuilder;
    //   1044: pop
    //   1045: iload_2
    //   1046: ifne -> 1348
    //   1049: goto -> 1056
    //   1052: invokestatic a : (Ljava/lang/Throwable;)Ljava/lang/Throwable;
    //   1055: athrow
    //   1056: aload_3
    //   1057: getstatic burp/Zro_.Zz : Ljava/lang/String;
    //   1060: getstatic burp/Ze9.Zu : Ljava/lang/Object;
    //   1063: checkcast java/math/BigInteger
    //   1066: invokevirtual intValue : ()I
    //   1069: bipush #32
    //   1071: irem
    //   1072: invokestatic abs : (I)I
    //   1075: invokevirtual charAt : (I)C
    //   1078: invokevirtual append : (C)Ljava/lang/StringBuilder;
    //   1081: pop
    //   1082: iload_2
    //   1083: ifne -> 1348
    //   1086: goto -> 1093
    //   1089: invokestatic a : (Ljava/lang/Throwable;)Ljava/lang/Throwable;
    //   1092: athrow
    //   1093: aload_3
    //   1094: getstatic burp/Zefn.Ze : Ljava/lang/String;
    //   1097: getstatic burp/Zrct.ZV : Ljava/lang/Object;
    //   1100: checkcast java/math/BigInteger
    //   1103: invokevirtual intValue : ()I
    //   1106: bipush #32
    //   1108: irem
    //   1109: invokestatic abs : (I)I
    //   1112: invokevirtual charAt : (I)C
    //   1115: invokevirtual append : (C)Ljava/lang/StringBuilder;
    //   1118: pop
    //   1119: iload_2
    //   1120: ifne -> 1348
    //   1123: goto -> 1130
    //   1126: invokestatic a : (Ljava/lang/Throwable;)Ljava/lang/Throwable;
    //   1129: athrow
    //   1130: aload_3
    //   1131: getstatic burp/Zl6z.ZL : Ljava/lang/String;
    //   1134: getstatic burp/Zktq.Zn : Ljava/lang/Object;
    //   1137: checkcast java/math/BigInteger
    //   1140: invokevirtual intValue : ()I
    //   1143: bipush #32
    //   1145: irem
    //   1146: invokestatic abs : (I)I
    //   1149: invokevirtual charAt : (I)C
    //   1152: invokevirtual append : (C)Ljava/lang/StringBuilder;
    //   1155: pop
    //   1156: iload_2
    //   1157: ifne -> 1348
    //   1160: goto -> 1167
    //   1163: invokestatic a : (Ljava/lang/Throwable;)Ljava/lang/Throwable;
    //   1166: athrow
    //   1167: aload_3
    //   1168: getstatic burp/Zg3m.Za : Ljava/lang/String;
    //   1171: getstatic burp/Zz5l.Zb : Ljava/lang/Object;
    //   1174: checkcast java/math/BigInteger
    //   1177: invokevirtual intValue : ()I
    //   1180: bipush #32
    //   1182: irem
    //   1183: invokestatic abs : (I)I
    //   1186: invokevirtual charAt : (I)C
    //   1189: invokevirtual append : (C)Ljava/lang/StringBuilder;
    //   1192: pop
    //   1193: iload_2
    //   1194: ifne -> 1348
    //   1197: goto -> 1204
    //   1200: invokestatic a : (Ljava/lang/Throwable;)Ljava/lang/Throwable;
    //   1203: athrow
    //   1204: aload_3
    //   1205: getstatic burp/Zso7.Zr : Ljava/lang/String;
    //   1208: getstatic burp/Zewq.ZO : Ljava/lang/Object;
    //   1211: checkcast java/math/BigInteger
    //   1214: invokevirtual intValue : ()I
    //   1217: bipush #32
    //   1219: irem
    //   1220: invokestatic abs : (I)I
    //   1223: invokevirtual charAt : (I)C
    //   1226: invokevirtual append : (C)Ljava/lang/StringBuilder;
    //   1229: pop
    //   1230: iload_2
    //   1231: ifne -> 1348
    //   1234: goto -> 1241
    //   1237: invokestatic a : (Ljava/lang/Throwable;)Ljava/lang/Throwable;
    //   1240: athrow
    //   1241: aload_3
    //   1242: getstatic burp/Zeju.ZR : Ljava/lang/String;
    //   1245: getstatic burp/Zevc.Zm : Ljava/lang/Object;
    //   1248: checkcast java/math/BigInteger
    //   1251: invokevirtual intValue : ()I
    //   1254: bipush #32
    //   1256: irem
    //   1257: invokestatic abs : (I)I
    //   1260: invokevirtual charAt : (I)C
    //   1263: invokevirtual append : (C)Ljava/lang/StringBuilder;
    //   1266: pop
    //   1267: iload_2
    //   1268: ifne -> 1348
    //   1271: goto -> 1278
    //   1274: invokestatic a : (Ljava/lang/Throwable;)Ljava/lang/Throwable;
    //   1277: athrow
    //   1278: aload_3
    //   1279: getstatic burp/Zzh9.ZF : Ljava/lang/String;
    //   1282: getstatic burp/Zl6z.Zt : Ljava/lang/Object;
    //   1285: checkcast java/math/BigInteger
    //   1288: invokevirtual intValue : ()I
    //   1291: bipush #32
    //   1293: irem
    //   1294: invokestatic abs : (I)I
    //   1297: invokevirtual charAt : (I)C
    //   1300: invokevirtual append : (C)Ljava/lang/StringBuilder;
    //   1303: pop
    //   1304: iload_2
    //   1305: ifne -> 1348
    //   1308: goto -> 1315
    //   1311: invokestatic a : (Ljava/lang/Throwable;)Ljava/lang/Throwable;
    //   1314: athrow
    //   1315: aload_3
    //   1316: getstatic burp/Zlhu.ZC : Ljava/lang/String;
    //   1319: getstatic burp/Zeju.Zk : Ljava/lang/Object;
    //   1322: checkcast java/math/BigInteger
    //   1325: invokevirtual intValue : ()I
    //   1328: bipush #32
    //   1330: irem
    //   1331: invokestatic abs : (I)I
    //   1334: invokevirtual charAt : (I)C
    //   1337: invokevirtual append : (C)Ljava/lang/StringBuilder;
    //   1340: pop
    //   1341: goto -> 1348
    //   1344: invokestatic a : (Ljava/lang/Throwable;)Ljava/lang/Throwable;
    //   1347: athrow
    //   1348: iinc #4, 1
    //   1351: iload_2
    //   1352: ifne -> 15
    //   1355: aload_3
    //   1356: invokevirtual toString : ()Ljava/lang/String;
    //   1359: putstatic burp/Zmvk.Z_ : Ljava/lang/String;
    //   1362: sipush #14316
    //   1365: sipush #866
    //   1368: invokestatic a : (II)Ljava/lang/String;
    //   1371: iconst_1
    //   1372: ldc burp/Zlsw
    //   1374: invokevirtual getClassLoader : ()Ljava/lang/ClassLoader;
    //   1377: invokestatic forName : (Ljava/lang/String;ZLjava/lang/ClassLoader;)Ljava/lang/Class;
    //   1380: invokevirtual getDeclaredFields : ()[Ljava/lang/reflect/Field;
    //   1383: astore #4
    //   1385: aload #4
    //   1387: arraylength
    //   1388: istore #5
    //   1390: iconst_0
    //   1391: istore #6
    //   1393: iload #6
    //   1395: iload #5
    //   1397: if_icmpge -> 1535
    //   1400: aload #4
    //   1402: iload #6
    //   1404: aaload
    //   1405: astore #7
    //   1407: aload #7
    //   1409: invokevirtual getModifiers : ()I
    //   1412: invokestatic isStatic : (I)Z
    //   1415: ifne -> 1425
    //   1418: goto -> 1528
    //   1421: invokestatic a : (Ljava/lang/Throwable;)Ljava/lang/Throwable;
    //   1424: athrow
    //   1425: aload #7
    //   1427: invokevirtual getType : ()Ljava/lang/Class;
    //   1430: astore #8
    //   1432: aload #8
    //   1434: ifnull -> 1515
    //   1437: aload #8
    //   1439: invokevirtual isPrimitive : ()Z
    //   1442: ifne -> 1515
    //   1445: goto -> 1452
    //   1448: invokestatic a : (Ljava/lang/Throwable;)Ljava/lang/Throwable;
    //   1451: athrow
    //   1452: aload #8
    //   1454: invokevirtual getPackage : ()Ljava/lang/Package;
    //   1457: ifnull -> 1515
    //   1460: goto -> 1467
    //   1463: invokestatic a : (Ljava/lang/Throwable;)Ljava/lang/Throwable;
    //   1466: athrow
    //   1467: aload #8
    //   1469: invokevirtual getPackage : ()Ljava/lang/Package;
    //   1472: invokevirtual getName : ()Ljava/lang/String;
    //   1475: ifnull -> 1515
    //   1478: goto -> 1485
    //   1481: invokestatic a : (Ljava/lang/Throwable;)Ljava/lang/Throwable;
    //   1484: athrow
    //   1485: aload #8
    //   1487: invokevirtual getPackage : ()Ljava/lang/Package;
    //   1490: invokevirtual getName : ()Ljava/lang/String;
    //   1493: sipush #14315
    //   1496: sipush #-20899
    //   1499: invokestatic a : (II)Ljava/lang/String;
    //   1502: invokevirtual startsWith : (Ljava/lang/String;)Z
    //   1505: ifne -> 1515
    //   1508: goto -> 1515
    //   1511: invokestatic a : (Ljava/lang/Throwable;)Ljava/lang/Throwable;
    //   1514: athrow
    //   1515: aload #7
    //   1517: iconst_1
    //   1518: invokevirtual setAccessible : (Z)V
    //   1521: aload #7
    //   1523: aconst_null
    //   1524: invokevirtual get : (Ljava/lang/Object;)Ljava/lang/Object;
    //   1527: pop
    //   1528: iinc #6, 1
    //   1531: iload_2
    //   1532: ifne -> 1393
    //   1535: sipush #14312
    //   1538: sipush #23766
    //   1541: invokestatic a : (II)Ljava/lang/String;
    //   1544: invokestatic forName : (Ljava/lang/String;)Ljava/lang/Class;
    //   1547: invokevirtual getDeclaredMethods : ()[Ljava/lang/reflect/Method;
    //   1550: astore #4
    //   1552: aload #4
    //   1554: arraylength
    //   1555: istore #5
    //   1557: iconst_0
    //   1558: istore #6
    //   1560: iload #6
    //   1562: iload #5
    //   1564: if_icmpge -> 1697
    //   1567: aload #4
    //   1569: iload #6
    //   1571: aaload
    //   1572: astore #7
    //   1574: aload #7
    //   1576: invokevirtual getParameterTypes : ()[Ljava/lang/Class;
    //   1579: pop
    //   1580: aload #7
    //   1582: invokevirtual getModifiers : ()I
    //   1585: invokestatic isStatic : (I)Z
    //   1588: ifeq -> 1683
    //   1591: aload #7
    //   1593: invokevirtual getParameterTypes : ()[Ljava/lang/Class;
    //   1596: arraylength
    //   1597: iconst_2
    //   1598: if_icmpne -> 1683
    //   1601: goto -> 1608
    //   1604: invokestatic a : (Ljava/lang/Throwable;)Ljava/lang/Throwable;
    //   1607: athrow
    //   1608: aload #7
    //   1610: invokevirtual getReturnType : ()Ljava/lang/Class;
    //   1613: getstatic java/lang/Void.TYPE : Ljava/lang/Class;
    //   1616: invokevirtual equals : (Ljava/lang/Object;)Z
    //   1619: ifeq -> 1683
    //   1622: goto -> 1629
    //   1625: invokestatic a : (Ljava/lang/Throwable;)Ljava/lang/Throwable;
    //   1628: athrow
    //   1629: aload #7
    //   1631: iconst_1
    //   1632: invokevirtual setAccessible : (Z)V
    //   1635: aload #7
    //   1637: aconst_null
    //   1638: iconst_2
    //   1639: anewarray java/lang/Object
    //   1642: dup
    //   1643: iconst_0
    //   1644: aload_0
    //   1645: aastore
    //   1646: dup
    //   1647: iconst_1
    //   1648: aload_1
    //   1649: ifnonnull -> 1667
    //   1652: goto -> 1659
    //   1655: invokestatic a : (Ljava/lang/Throwable;)Ljava/lang/Throwable;
    //   1658: athrow
    //   1659: aload_1
    //   1660: goto -> 1674
    //   1663: invokestatic a : (Ljava/lang/Throwable;)Ljava/lang/Throwable;
    //   1666: athrow
    //   1667: aload_1
    //   1668: checkcast [B
    //   1671: invokevirtual clone : ()Ljava/lang/Object;
    //   1674: aastore
    //   1675: invokevirtual invoke : (Ljava/lang/Object;[Ljava/lang/Object;)Ljava/lang/Object;
    //   1678: pop
    //   1679: iload_2
    //   1680: ifne -> 1697
    //   1683: iinc #6, 1
    //   1686: iload_2
    //   1687: ifne -> 1560
    //   1690: goto -> 1697
    //   1693: invokestatic a : (Ljava/lang/Throwable;)Ljava/lang/Throwable;
    //   1696: athrow
    //   1697: getstatic burp/Zefn.ZJ : Ljava/lang/Object;
    //   1700: checkcast java/math/BigInteger
    //   1703: invokevirtual toByteArray : ()[B
    //   1706: astore #4
    //   1708: iconst_0
    //   1709: istore #6
    //   1711: iconst_0
    //   1712: istore #7
    //   1714: iload #7
    //   1716: aload #4
    //   1718: arraylength
    //   1719: if_icmpge -> 1865
    //   1722: aload #4
    //   1724: iload #7
    //   1726: baload
    //   1727: istore #8
    //   1729: iload #8
    //   1731: bipush #48
    //   1733: if_icmplt -> 1750
    //   1736: iload #8
    //   1738: bipush #57
    //   1740: if_icmple -> 1848
    //   1743: goto -> 1750
    //   1746: invokestatic a : (Ljava/lang/Throwable;)Ljava/lang/Throwable;
    //   1749: athrow
    //   1750: iload #8
    //   1752: bipush #65
    //   1754: if_icmplt -> 1778
    //   1757: goto -> 1764
    //   1760: invokestatic a : (Ljava/lang/Throwable;)Ljava/lang/Throwable;
    //   1763: athrow
    //   1764: iload #8
    //   1766: bipush #90
    //   1768: if_icmple -> 1848
    //   1771: goto -> 1778
    //   1774: invokestatic a : (Ljava/lang/Throwable;)Ljava/lang/Throwable;
    //   1777: athrow
    //   1778: iload #8
    //   1780: bipush #97
    //   1782: if_icmplt -> 1806
    //   1785: goto -> 1792
    //   1788: invokestatic a : (Ljava/lang/Throwable;)Ljava/lang/Throwable;
    //   1791: athrow
    //   1792: iload #8
    //   1794: bipush #122
    //   1796: if_icmple -> 1848
    //   1799: goto -> 1806
    //   1802: invokestatic a : (Ljava/lang/Throwable;)Ljava/lang/Throwable;
    //   1805: athrow
    //   1806: iload #8
    //   1808: bipush #43
    //   1810: if_icmpeq -> 1848
    //   1813: goto -> 1820
    //   1816: invokestatic a : (Ljava/lang/Throwable;)Ljava/lang/Throwable;
    //   1819: athrow
    //   1820: iload #8
    //   1822: bipush #47
    //   1824: if_icmpeq -> 1848
    //   1827: goto -> 1834
    //   1830: invokestatic a : (Ljava/lang/Throwable;)Ljava/lang/Throwable;
    //   1833: athrow
    //   1834: iload #8
    //   1836: bipush #61
    //   1838: if_icmpne -> 1858
    //   1841: goto -> 1848
    //   1844: invokestatic a : (Ljava/lang/Throwable;)Ljava/lang/Throwable;
    //   1847: athrow
    //   1848: iinc #6, 1
    //   1851: goto -> 1858
    //   1854: invokestatic a : (Ljava/lang/Throwable;)Ljava/lang/Throwable;
    //   1857: athrow
    //   1858: iinc #7, 1
    //   1861: iload_2
    //   1862: ifne -> 1714
    //   1865: iload #6
    //   1867: newarray byte
    //   1869: astore #7
    //   1871: iconst_0
    //   1872: istore #8
    //   1874: iconst_0
    //   1875: istore #9
    //   1877: iload #9
    //   1879: aload #4
    //   1881: arraylength
    //   1882: if_icmpge -> 2035
    //   1885: aload #4
    //   1887: iload #9
    //   1889: baload
    //   1890: istore #10
    //   1892: iload #10
    //   1894: bipush #48
    //   1896: if_icmplt -> 1913
    //   1899: iload #10
    //   1901: bipush #57
    //   1903: if_icmple -> 2011
    //   1906: goto -> 1913
    //   1909: invokestatic a : (Ljava/lang/Throwable;)Ljava/lang/Throwable;
    //   1912: athrow
    //   1913: iload #10
    //   1915: bipush #65
    //   1917: if_icmplt -> 1941
    //   1920: goto -> 1927
    //   1923: invokestatic a : (Ljava/lang/Throwable;)Ljava/lang/Throwable;
    //   1926: athrow
    //   1927: iload #10
    //   1929: bipush #90
    //   1931: if_icmple -> 2011
    //   1934: goto -> 1941
    //   1937: invokestatic a : (Ljava/lang/Throwable;)Ljava/lang/Throwable;
    //   1940: athrow
    //   1941: iload #10
    //   1943: bipush #97
    //   1945: if_icmplt -> 1969
    //   1948: goto -> 1955
    //   1951: invokestatic a : (Ljava/lang/Throwable;)Ljava/lang/Throwable;
    //   1954: athrow
    //   1955: iload #10
    //   1957: bipush #122
    //   1959: if_icmple -> 2011
    //   1962: goto -> 1969
    //   1965: invokestatic a : (Ljava/lang/Throwable;)Ljava/lang/Throwable;
    //   1968: athrow
    //   1969: iload #10
    //   1971: bipush #43
    //   1973: if_icmpeq -> 2011
    //   1976: goto -> 1983
    //   1979: invokestatic a : (Ljava/lang/Throwable;)Ljava/lang/Throwable;
    //   1982: athrow
    //   1983: iload #10
    //   1985: bipush #47
    //   1987: if_icmpeq -> 2011
    //   1990: goto -> 1997
    //   1993: invokestatic a : (Ljava/lang/Throwable;)Ljava/lang/Throwable;
    //   1996: athrow
    //   1997: iload #10
    //   1999: bipush #61
    //   2001: if_icmpne -> 2028
    //   2004: goto -> 2011
    //   2007: invokestatic a : (Ljava/lang/Throwable;)Ljava/lang/Throwable;
    //   2010: athrow
    //   2011: aload #7
    //   2013: iload #8
    //   2015: iload #10
    //   2017: bastore
    //   2018: iinc #8, 1
    //   2021: goto -> 2028
    //   2024: invokestatic a : (Ljava/lang/Throwable;)Ljava/lang/Throwable;
    //   2027: athrow
    //   2028: iinc #9, 1
    //   2031: iload_2
    //   2032: ifne -> 1877
    //   2035: aload #7
    //   2037: astore #5
    //   2039: aload #5
    //   2041: astore #4
    //   2043: aload #4
    //   2045: arraylength
    //   2046: istore #6
    //   2048: aload #4
    //   2050: iload #6
    //   2052: iconst_1
    //   2053: isub
    //   2054: baload
    //   2055: bipush #61
    //   2057: if_icmpne -> 2067
    //   2060: iinc #6, -1
    //   2063: iload_2
    //   2064: ifne -> 2048
    //   2067: iload #6
    //   2069: aload #4
    //   2071: arraylength
    //   2072: iconst_4
    //   2073: idiv
    //   2074: isub
    //   2075: newarray byte
    //   2077: astore #7
    //   2079: iconst_0
    //   2080: istore #8
    //   2082: iload #8
    //   2084: aload #4
    //   2086: arraylength
    //   2087: if_icmpge -> 2367
    //   2090: aload #4
    //   2092: iload #8
    //   2094: baload
    //   2095: bipush #61
    //   2097: if_icmpne -> 2117
    //   2100: aload #4
    //   2102: iload #8
    //   2104: iconst_0
    //   2105: bastore
    //   2106: iload_2
    //   2107: ifne -> 2360
    //   2110: goto -> 2117
    //   2113: invokestatic a : (Ljava/lang/Throwable;)Ljava/lang/Throwable;
    //   2116: athrow
    //   2117: aload #4
    //   2119: iload #8
    //   2121: baload
    //   2122: bipush #47
    //   2124: if_icmpne -> 2152
    //   2127: goto -> 2134
    //   2130: invokestatic a : (Ljava/lang/Throwable;)Ljava/lang/Throwable;
    //   2133: athrow
    //   2134: aload #4
    //   2136: iload #8
    //   2138: bipush #63
    //   2140: bastore
    //   2141: iload_2
    //   2142: ifne -> 2360
    //   2145: goto -> 2152
    //   2148: invokestatic a : (Ljava/lang/Throwable;)Ljava/lang/Throwable;
    //   2151: athrow
    //   2152: aload #4
    //   2154: iload #8
    //   2156: baload
    //   2157: bipush #43
    //   2159: if_icmpne -> 2187
    //   2162: goto -> 2169
    //   2165: invokestatic a : (Ljava/lang/Throwable;)Ljava/lang/Throwable;
    //   2168: athrow
    //   2169: aload #4
    //   2171: iload #8
    //   2173: bipush #62
    //   2175: bastore
    //   2176: iload_2
    //   2177: ifne -> 2360
    //   2180: goto -> 2187
    //   2183: invokestatic a : (Ljava/lang/Throwable;)Ljava/lang/Throwable;
    //   2186: athrow
    //   2187: aload #4
    //   2189: iload #8
    //   2191: baload
    //   2192: bipush #48
    //   2194: if_icmplt -> 2246
    //   2197: goto -> 2204
    //   2200: invokestatic a : (Ljava/lang/Throwable;)Ljava/lang/Throwable;
    //   2203: athrow
    //   2204: aload #4
    //   2206: iload #8
    //   2208: baload
    //   2209: bipush #57
    //   2211: if_icmpgt -> 2246
    //   2214: goto -> 2221
    //   2217: invokestatic a : (Ljava/lang/Throwable;)Ljava/lang/Throwable;
    //   2220: athrow
    //   2221: aload #4
    //   2223: iload #8
    //   2225: aload #4
    //   2227: iload #8
    //   2229: baload
    //   2230: bipush #-4
    //   2232: isub
    //   2233: i2b
    //   2234: bastore
    //   2235: iload_2
    //   2236: ifne -> 2360
    //   2239: goto -> 2246
    //   2242: invokestatic a : (Ljava/lang/Throwable;)Ljava/lang/Throwable;
    //   2245: athrow
    //   2246: aload #4
    //   2248: iload #8
    //   2250: baload
    //   2251: bipush #97
    //   2253: if_icmplt -> 2305
    //   2256: goto -> 2263
    //   2259: invokestatic a : (Ljava/lang/Throwable;)Ljava/lang/Throwable;
    //   2262: athrow
    //   2263: aload #4
    //   2265: iload #8
    //   2267: baload
    //   2268: bipush #122
    //   2270: if_icmpgt -> 2305
    //   2273: goto -> 2280
    //   2276: invokestatic a : (Ljava/lang/Throwable;)Ljava/lang/Throwable;
    //   2279: athrow
    //   2280: aload #4
    //   2282: iload #8
    //   2284: aload #4
    //   2286: iload #8
    //   2288: baload
    //   2289: bipush #71
    //   2291: isub
    //   2292: i2b
    //   2293: bastore
    //   2294: iload_2
    //   2295: ifne -> 2360
    //   2298: goto -> 2305
    //   2301: invokestatic a : (Ljava/lang/Throwable;)Ljava/lang/Throwable;
    //   2304: athrow
    //   2305: aload #4
    //   2307: iload #8
    //   2309: baload
    //   2310: bipush #65
    //   2312: if_icmplt -> 2360
    //   2315: goto -> 2322
    //   2318: invokestatic a : (Ljava/lang/Throwable;)Ljava/lang/Throwable;
    //   2321: athrow
    //   2322: aload #4
    //   2324: iload #8
    //   2326: baload
    //   2327: bipush #90
    //   2329: if_icmpgt -> 2360
    //   2332: goto -> 2339
    //   2335: invokestatic a : (Ljava/lang/Throwable;)Ljava/lang/Throwable;
    //   2338: athrow
    //   2339: aload #4
    //   2341: iload #8
    //   2343: aload #4
    //   2345: iload #8
    //   2347: baload
    //   2348: bipush #65
    //   2350: isub
    //   2351: i2b
    //   2352: bastore
    //   2353: goto -> 2360
    //   2356: invokestatic a : (Ljava/lang/Throwable;)Ljava/lang/Throwable;
    //   2359: athrow
    //   2360: iinc #8, 1
    //   2363: iload_2
    //   2364: ifne -> 2082
    //   2367: iconst_0
    //   2368: istore #8
    //   2370: iconst_0
    //   2371: istore #9
    //   2373: iload #9
    //   2375: aload #7
    //   2377: arraylength
    //   2378: iconst_2
    //   2379: isub
    //   2380: if_icmpge -> 2489
    //   2383: aload #7
    //   2385: iload #9
    //   2387: aload #4
    //   2389: iload #8
    //   2391: baload
    //   2392: iconst_2
    //   2393: ishl
    //   2394: sipush #255
    //   2397: iand
    //   2398: aload #4
    //   2400: iload #8
    //   2402: iconst_1
    //   2403: iadd
    //   2404: baload
    //   2405: iconst_4
    //   2406: iushr
    //   2407: iconst_3
    //   2408: iand
    //   2409: ior
    //   2410: i2b
    //   2411: bastore
    //   2412: aload #7
    //   2414: iload #9
    //   2416: iconst_1
    //   2417: iadd
    //   2418: aload #4
    //   2420: iload #8
    //   2422: iconst_1
    //   2423: iadd
    //   2424: baload
    //   2425: iconst_4
    //   2426: ishl
    //   2427: sipush #255
    //   2430: iand
    //   2431: aload #4
    //   2433: iload #8
    //   2435: iconst_2
    //   2436: iadd
    //   2437: baload
    //   2438: iconst_2
    //   2439: iushr
    //   2440: bipush #15
    //   2442: iand
    //   2443: ior
    //   2444: i2b
    //   2445: bastore
    //   2446: aload #7
    //   2448: iload #9
    //   2450: iconst_2
    //   2451: iadd
    //   2452: aload #4
    //   2454: iload #8
    //   2456: iconst_2
    //   2457: iadd
    //   2458: baload
    //   2459: bipush #6
    //   2461: ishl
    //   2462: sipush #255
    //   2465: iand
    //   2466: aload #4
    //   2468: iload #8
    //   2470: iconst_3
    //   2471: iadd
    //   2472: baload
    //   2473: bipush #63
    //   2475: iand
    //   2476: ior
    //   2477: i2b
    //   2478: bastore
    //   2479: iinc #8, 4
    //   2482: iinc #9, 3
    //   2485: iload_2
    //   2486: ifne -> 2373
    //   2489: iload #9
    //   2491: aload #7
    //   2493: arraylength
    //   2494: if_icmpge -> 2533
    //   2497: aload #7
    //   2499: iload #9
    //   2501: aload #4
    //   2503: iload #8
    //   2505: baload
    //   2506: iconst_2
    //   2507: ishl
    //   2508: sipush #255
    //   2511: iand
    //   2512: aload #4
    //   2514: iload #8
    //   2516: iconst_1
    //   2517: iadd
    //   2518: baload
    //   2519: iconst_4
    //   2520: iushr
    //   2521: iconst_3
    //   2522: iand
    //   2523: ior
    //   2524: i2b
    //   2525: bastore
    //   2526: goto -> 2533
    //   2529: invokestatic a : (Ljava/lang/Throwable;)Ljava/lang/Throwable;
    //   2532: athrow
    //   2533: iinc #9, 1
    //   2536: iload #9
    //   2538: aload #7
    //   2540: arraylength
    //   2541: if_icmpge -> 2583
    //   2544: aload #7
    //   2546: iload #9
    //   2548: aload #4
    //   2550: iload #8
    //   2552: iconst_1
    //   2553: iadd
    //   2554: baload
    //   2555: iconst_4
    //   2556: ishl
    //   2557: sipush #255
    //   2560: iand
    //   2561: aload #4
    //   2563: iload #8
    //   2565: iconst_2
    //   2566: iadd
    //   2567: baload
    //   2568: iconst_2
    //   2569: iushr
    //   2570: bipush #15
    //   2572: iand
    //   2573: ior
    //   2574: i2b
    //   2575: bastore
    //   2576: goto -> 2583
    //   2579: invokestatic a : (Ljava/lang/Throwable;)Ljava/lang/Throwable;
    //   2582: athrow
    //   2583: aload #7
    //   2585: astore #5
    //   2587: getstatic burp/Zmh0.Zs : Ljava/lang/String;
    //   2590: getstatic burp/Zeju.Zk : Ljava/lang/Object;
    //   2593: checkcast java/math/BigInteger
    //   2596: invokevirtual intValue : ()I
    //   2599: bipush #32
    //   2601: irem
    //   2602: invokestatic abs : (I)I
    //   2605: invokevirtual charAt : (I)C
    //   2608: getstatic burp/Zeju.ZR : Ljava/lang/String;
    //   2611: getstatic burp/Zmvk.ZK : Ljava/lang/Object;
    //   2614: checkcast java/math/BigInteger
    //   2617: invokevirtual intValue : ()I
    //   2620: bipush #32
    //   2622: irem
    //   2623: invokestatic abs : (I)I
    //   2626: invokevirtual charAt : (I)C
    //   2629: if_icmpgt -> 2736
    //   2632: getstatic burp/Zrp3.Zf : Ljava/lang/String;
    //   2635: getstatic burp/Zlzs.ZL : Ljava/lang/Object;
    //   2638: checkcast java/math/BigInteger
    //   2641: invokevirtual intValue : ()I
    //   2644: bipush #32
    //   2646: irem
    //   2647: invokestatic abs : (I)I
    //   2650: invokevirtual charAt : (I)C
    //   2653: getstatic burp/Zmfw.ZV : Ljava/lang/String;
    //   2656: getstatic burp/Zza3.Zb : Ljava/lang/Object;
    //   2659: checkcast java/math/BigInteger
    //   2662: invokevirtual intValue : ()I
    //   2665: bipush #32
    //   2667: irem
    //   2668: invokestatic abs : (I)I
    //   2671: invokevirtual charAt : (I)C
    //   2674: if_icmpgt -> 2736
    //   2677: goto -> 2684
    //   2680: invokestatic a : (Ljava/lang/Throwable;)Ljava/lang/Throwable;
    //   2683: athrow
    //   2684: getstatic burp/Zms1.ZZ : Ljava/lang/String;
    //   2687: getstatic burp/Zeqw.ZV : Ljava/lang/Object;
    //   2690: checkcast java/math/BigInteger
    //   2693: invokevirtual intValue : ()I
    //   2696: bipush #32
    //   2698: irem
    //   2699: invokestatic abs : (I)I
    //   2702: invokevirtual charAt : (I)C
    //   2705: getstatic burp/Zeju.ZR : Ljava/lang/String;
    //   2708: getstatic burp/Zl6z.Zt : Ljava/lang/Object;
    //   2711: checkcast java/math/BigInteger
    //   2714: invokevirtual intValue : ()I
    //   2717: bipush #32
    //   2719: irem
    //   2720: invokestatic abs : (I)I
    //   2723: invokevirtual charAt : (I)C
    //   2726: if_icmple -> 2744
    //   2729: goto -> 2736
    //   2732: invokestatic a : (Ljava/lang/Throwable;)Ljava/lang/Throwable;
    //   2735: athrow
    //   2736: iconst_1
    //   2737: goto -> 2745
    //   2740: invokestatic a : (Ljava/lang/Throwable;)Ljava/lang/Throwable;
    //   2743: athrow
    //   2744: iconst_0
    //   2745: ireturn
    //   2746: astore_3
    //   2747: new java/lang/Exception
    //   2750: dup
    //   2751: aload_3
    //   2752: invokevirtual getMessage : ()Ljava/lang/String;
    //   2755: invokespecial <init> : (Ljava/lang/String;)V
    //   2758: athrow
    // Exception table:
    //   from	to	target	type
    //   4	2745	2746	java/lang/Throwable
    //   22	198	201	java/lang/Throwable
    //   168	235	238	java/lang/Throwable
    //   205	272	275	java/lang/Throwable
    //   242	309	312	java/lang/Throwable
    //   279	346	349	java/lang/Throwable
    //   316	383	386	java/lang/Throwable
    //   353	420	423	java/lang/Throwable
    //   390	457	460	java/lang/Throwable
    //   427	494	497	java/lang/Throwable
    //   464	531	534	java/lang/Throwable
    //   501	568	571	java/lang/Throwable
    //   538	605	608	java/lang/Throwable
    //   575	642	645	java/lang/Throwable
    //   612	679	682	java/lang/Throwable
    //   649	716	719	java/lang/Throwable
    //   686	753	756	java/lang/Throwable
    //   723	790	793	java/lang/Throwable
    //   760	827	830	java/lang/Throwable
    //   797	864	867	java/lang/Throwable
    //   834	901	904	java/lang/Throwable
    //   871	938	941	java/lang/Throwable
    //   908	975	978	java/lang/Throwable
    //   945	1012	1015	java/lang/Throwable
    //   982	1049	1052	java/lang/Throwable
    //   1019	1086	1089	java/lang/Throwable
    //   1056	1123	1126	java/lang/Throwable
    //   1093	1160	1163	java/lang/Throwable
    //   1130	1197	1200	java/lang/Throwable
    //   1167	1234	1237	java/lang/Throwable
    //   1204	1271	1274	java/lang/Throwable
    //   1241	1308	1311	java/lang/Throwable
    //   1278	1341	1344	java/lang/Throwable
    //   1407	1421	1421	java/lang/Throwable
    //   1432	1445	1448	java/lang/Throwable
    //   1437	1460	1463	java/lang/Throwable
    //   1452	1478	1481	java/lang/Throwable
    //   1467	1508	1511	java/lang/Throwable
    //   1574	1601	1604	java/lang/Throwable
    //   1591	1622	1625	java/lang/Throwable
    //   1608	1652	1655	java/lang/Throwable
    //   1629	1663	1663	java/lang/Throwable
    //   1674	1690	1693	java/lang/Throwable
    //   1729	1743	1746	java/lang/Throwable
    //   1736	1757	1760	java/lang/Throwable
    //   1750	1771	1774	java/lang/Throwable
    //   1764	1785	1788	java/lang/Throwable
    //   1778	1799	1802	java/lang/Throwable
    //   1792	1813	1816	java/lang/Throwable
    //   1806	1827	1830	java/lang/Throwable
    //   1820	1841	1844	java/lang/Throwable
    //   1834	1851	1854	java/lang/Throwable
    //   1892	1906	1909	java/lang/Throwable
    //   1899	1920	1923	java/lang/Throwable
    //   1913	1934	1937	java/lang/Throwable
    //   1927	1948	1951	java/lang/Throwable
    //   1941	1962	1965	java/lang/Throwable
    //   1955	1976	1979	java/lang/Throwable
    //   1969	1990	1993	java/lang/Throwable
    //   1983	2004	2007	java/lang/Throwable
    //   1997	2021	2024	java/lang/Throwable
    //   2090	2110	2113	java/lang/Throwable
    //   2100	2127	2130	java/lang/Throwable
    //   2117	2145	2148	java/lang/Throwable
    //   2134	2162	2165	java/lang/Throwable
    //   2152	2180	2183	java/lang/Throwable
    //   2169	2197	2200	java/lang/Throwable
    //   2187	2214	2217	java/lang/Throwable
    //   2204	2239	2242	java/lang/Throwable
    //   2221	2256	2259	java/lang/Throwable
    //   2246	2273	2276	java/lang/Throwable
    //   2263	2298	2301	java/lang/Throwable
    //   2280	2315	2318	java/lang/Throwable
    //   2305	2332	2335	java/lang/Throwable
    //   2322	2353	2356	java/lang/Throwable
    //   2489	2526	2529	java/lang/Throwable
    //   2533	2576	2579	java/lang/Throwable
    //   2587	2677	2680	java/lang/Throwable
    //   2632	2729	2732	java/lang/Throwable
    //   2684	2740	2740	java/lang/Throwable
  }
  
  static void Ze(Object paramObject) {
    Zs56.ZW = a(14319, 17557);
    Zs56.ZC = new BigInteger(a(14314, -12698));
    boolean bool = Zt2e.ZN();
    try {
      try {
        if (Zenq.ZG.charAt(Math.abs(((BigInteger)Ze9.Zu).intValue() % 32)) > Zmh0.Zs.charAt(Math.abs(((BigInteger)Zrp3.Zd).intValue() % 32))) {
          try {
            Zg1k.ZQ(Class.forName(a(14310, -25262)));
            if (!bool)
              Zge1.Zh(Class.forName(a(14317, 15331))); 
          } catch (Throwable throwable) {
            throw a(null);
          } 
          return;
        } 
      } catch (Throwable throwable) {
        throw a(null);
      } 
      Zge1.Zh(Class.forName(a(14317, 15331)));
    } catch (Throwable throwable) {}
  }
  
  static {
    // Byte code:
    //   0: bipush #9
    //   2: anewarray java/lang/String
    //   5: astore #5
    //   7: iconst_0
    //   8: istore_3
    //   9: ldc 'cÃ³Ã»\\ni:`7Â¹ÃÂ‡7WUÂ¼Â•Â£Â¾Ã˜Ã‡ÃgÃ¥Ã•gm85Â—*Â•Ã•ÃŒÂ¢BÃ€"Ã·Ã¶Â¥Ã4$RÃ¿Â”Â‰ _ÃƒÃ´ Ã…0`Âª.Â¿Ã™Ã¼Â˜mÃ‡P $Â—Â¿Ã«Ã¤cÂªÃ¶Ã¦Â’Ã¿\Ã‚Â“FcÃ“Â¹ÂY)Ã£ÃÂ Â¢RÃ9Â²\\tÂ˜ÂÂœiÂŸ\\tÂ‡Ã†mFd2gÂ¼MÂ™KQrÃ´Â¹Ã¦Â…pTÂºÃ¬Â´ÃÃ±Ã°xÂ½<_Ã€Â˜AÂ1dÃ„Ã§Â¢Â‹=Ã…ÂœÃŸÃ‚Â‚KÂˆÃ¤Ã—#.Â¶Ã›Ã©vÃ³Ã¸Â¤gnÂ¤kGÂÃŸÂ¢Â¦Ã„>Ãº:H3Ã¿Â†\\\tÂ¢Â¿ÃŠ>Â£[[Â›'
    //   11: dup
    //   12: astore_2
    //   13: invokevirtual length : ()I
    //   16: istore #4
    //   18: bipush #77
    //   20: istore_1
    //   21: iconst_m1
    //   22: istore_0
    //   23: bipush #56
    //   25: iinc #0, 1
    //   28: aload_2
    //   29: iload_0
    //   30: dup
    //   31: iload_1
    //   32: iadd
    //   33: invokevirtual substring : (II)Ljava/lang/String;
    //   36: iconst_m1
    //   37: goto -> 143
    //   40: aload #5
    //   42: swap
    //   43: iload_3
    //   44: iinc #3, 1
    //   47: swap
    //   48: aastore
    //   49: iload_0
    //   50: iload_1
    //   51: iadd
    //   52: dup
    //   53: istore_0
    //   54: iload #4
    //   56: if_icmpge -> 68
    //   59: aload_2
    //   60: iload_0
    //   61: invokevirtual charAt : (I)C
    //   64: istore_1
    //   65: goto -> 23
    //   68: ldc '4ÃƒÃ¤HÃ˜)?GÃ—Â¤Ã™Â†)0oÂƒÃ¯Ã¦ÂµÂ†=Â”4ÃÂ†Â¤c\\tC?Ã‰EÃŒn9Â‡Â '
    //   70: dup
    //   71: astore_2
    //   72: invokevirtual length : ()I
    //   75: istore #4
    //   77: bipush #32
    //   79: istore_1
    //   80: iconst_m1
    //   81: istore_0
    //   82: bipush #74
    //   84: iinc #0, 1
    //   87: aload_2
    //   88: iload_0
    //   89: dup
    //   90: iload_1
    //   91: iadd
    //   92: invokevirtual substring : (II)Ljava/lang/String;
    //   95: iconst_0
    //   96: goto -> 143
    //   99: aload #5
    //   101: swap
    //   102: iload_3
    //   103: iinc #3, 1
    //   106: swap
    //   107: aastore
    //   108: iload_0
    //   109: iload_1
    //   110: iadd
    //   111: dup
    //   112: istore_0
    //   113: iload #4
    //   115: if_icmpge -> 127
    //   118: aload_2
    //   119: iload_0
    //   120: invokevirtual charAt : (I)C
    //   123: istore_1
    //   124: goto -> 82
    //   127: aload #5
    //   129: putstatic burp/Zxee.a : [Ljava/lang/String;
    //   132: bipush #9
    //   134: anewarray java/lang/String
    //   137: putstatic burp/Zxee.b : [Ljava/lang/String;
    //   140: goto -> 300
    //   143: dup_x2
    //   144: pop
    //   145: invokevirtual toCharArray : ()[C
    //   148: dup_x1
    //   149: arraylength
    //   150: dup_x2
    //   151: pop
    //   152: iconst_0
    //   153: istore #6
    //   155: dup2_x1
    //   156: pop2
    //   157: dup_x2
    //   158: iconst_1
    //   159: if_icmpgt -> 260
    //   162: dup2
    //   163: swap
    //   164: iload #6
    //   166: dup2_x1
    //   167: caload
    //   168: swap
    //   169: iload #6
    //   171: bipush #7
    //   173: irem
    //   174: tableswitch default -> 242, 0 -> 212, 1 -> 217, 2 -> 222, 3 -> 227, 4 -> 232, 5 -> 237
    //   212: bipush #68
    //   214: goto -> 244
    //   217: bipush #122
    //   219: goto -> 244
    //   222: bipush #118
    //   224: goto -> 244
    //   227: bipush #69
    //   229: goto -> 244
    //   232: bipush #42
    //   234: goto -> 244
    //   237: bipush #73
    //   239: goto -> 244
    //   242: bipush #96
    //   244: ixor
    //   245: ixor
    //   246: i2c
    //   247: castore
    //   248: iinc #6, 1
    //   251: dup
    //   252: ifne -> 260
    //   255: dup2
    //   256: dup_x1
    //   257: goto -> 166
    //   260: dup2_x1
    //   261: pop2
    //   262: dup_x2
    //   263: iload #6
    //   265: if_icmpgt -> 162
    //   268: pop
    //   269: new java/lang/String
    //   272: dup_x1
    //   273: swap
    //   274: invokespecial <init> : ([C)V
    //   277: invokevirtual intern : ()Ljava/lang/String;
    //   280: swap
    //   281: pop
    //   282: swap
    //   283: tableswitch default -> 40, 0 -> 99
    //   300: new java/math/BigInteger
    //   303: dup
    //   304: sipush #14318
    //   307: sipush #-23921
    //   310: invokestatic a : (II)Ljava/lang/String;
    //   313: invokespecial <init> : (Ljava/lang/String;)V
    //   316: putstatic burp/Zxee.Zj : Ljava/lang/Object;
    //   319: sipush #14313
    //   322: sipush #-3394
    //   325: invokestatic a : (II)Ljava/lang/String;
    //   328: putstatic burp/Zxee.Zd : Ljava/lang/String;
    //   331: return
  }
  
  private static Throwable a(Throwable paramThrowable) {
    return paramThrowable;
  }
  
  private static String a(int paramInt1, int paramInt2) {
    int i = (paramInt1 ^ 0x37EE) & 0xFFFF;
    if (b[i] == null) {
      char[] arrayOfChar = a[i].toCharArray();
      switch (arrayOfChar[0] & 0xFF) {
        case 0:
        
        case 1:
        
        case 2:
        
        case 3:
        
        case 4:
        
        case 5:
        
        case 6:
        
        case 7:
        
        case 8:
        
        case 9:
        
        case 10:
        
        case 11:
        
        case 12:
        
        case 13:
        
        case 14:
        
        case 15:
        
        case 16:
        
        case 17:
        
        case 18:
        
        case 19:
        
        case 20:
        
        case 21:
        
        case 22:
        
        case 23:
        
        case 24:
        
        case 25:
        
        case 26:
        
        case 27:
        
        case 28:
        
        case 29:
        
        case 30:
        
        case 31:
        
        case 32:
        
        case 33:
        
        case 34:
        
        case 35:
        
        case 36:
        
        case 37:
        
        case 38:
        
        case 39:
        
        case 40:
        
        case 41:
        
        case 42:
        
        case 43:
        
        case 44:
        
        case 45:
        
        case 46:
        
        case 47:
        
        case 48:
        
        case 49:
        
        case 50:
        
        case 51:
        
        case 52:
        
        case 53:
        
        case 54:
        
        case 55:
        
        case 56:
        
        case 57:
        
        case 58:
        
        case 59:
        
        case 60:
        
        case 61:
        
        case 62:
        
        case 63:
        
        case 64:
        
        case 65:
        
        case 66:
        
        case 67:
        
        case 68:
        
        case 69:
        
        case 70:
        
        case 71:
        
        case 72:
        
        case 73:
        
        case 74:
        
        case 75:
        
        case 76:
        
        case 77:
        
        case 78:
        
        case 79:
        
        case 80:
        
        case 81:
        
        case 82:
        
        case 83:
        
        case 84:
        
        case 85:
        
        case 86:
        
        case 87:
        
        case 88:
        
        case 89:
        
        case 90:
        
        case 91:
        
        case 92:
        
        case 93:
        
        case 94:
        
        case 95:
        
        case 96:
        
        case 97:
        
        case 98:
        
        case 99:
        
        case 100:
        
        case 101:
        
        case 102:
        
        case 103:
        
        case 104:
        
        case 105:
        
        case 106:
        
        case 107:
        
        case 108:
        
        case 109:
        
        case 110:
        
        case 111:
        
        case 112:
        
        case 113:
        
        case 114:
        
        case 115:
        
        case 116:
        
        case 117:
        
        case 118:
        
        case 119:
        
        case 120:
        
        case 121:
        
        case 122:
        
        case 123:
        
        case 124:
        
        case 125:
        
        case 126:
        
        case 127:
        
        case 128:
        
        case 129:
        
        case 130:
        
        case 131:
        
        case 132:
        
        case 133:
        
        case 134:
        
        case 135:
        
        case 136:
        
        case 137:
        
        case 138:
        
        case 139:
        
        case 140:
        
        case 141:
        
        case 142:
        
        case 143:
        
        case 144:
        
        case 145:
        
        case 146:
        
        case 147:
        
        case 148:
        
        case 149:
        
        case 150:
        
        case 151:
        
        case 152:
        
        case 153:
        
        case 154:
        
        case 155:
        
        case 156:
        
        case 157:
        
        case 158:
        
        case 159:
        
        case 160:
        
        case 161:
        
        case 162:
        
        case 163:
        
        case 164:
        
        case 165:
        
        case 166:
        
        case 167:
        
        case 168:
        
        case 169:
        
        case 170:
        
        case 171:
        
        case 172:
        
        case 173:
        
        case 174:
        
        case 175:
        
        case 176:
        
        case 177:
        
        case 178:
        
        case 179:
        
        case 180:
        
        case 181:
        
        case 182:
        
        case 183:
        
        case 184:
        
        case 185:
        
        case 186:
        
        case 187:
        
        case 188:
        
        case 189:
        
        case 190:
        
        case 191:
        
        case 192:
        
        case 193:
        
        case 194:
        
        case 195:
        
        case 196:
        
        case 197:
        
        case 198:
        
        case 199:
        
        case 200:
        
        case 201:
        
        case 202:
        
        case 203:
        
        case 204:
        
        case 205:
        
        case 206:
        
        case 207:
        
        case 208:
        
        case 209:
        
        case 210:
        
        case 211:
        
        case 212:
        
        case 213:
        
        case 214:
        
        case 215:
        
        case 216:
        
        case 217:
        
        case 218:
        
        case 219:
        
        case 220:
        
        case 221:
        
        case 222:
        
        case 223:
        
        case 224:
        
        case 225:
        
        case 226:
        
        case 227:
        
        case 228:
        
        case 229:
        
        case 230:
        
        case 231:
        
        case 232:
        
        case 233:
        
        case 234:
        
        case 235:
        
        case 236:
        
        case 237:
        
        case 238:
        
        case 239:
        
        case 240:
        
        case 241:
        
        case 242:
        
        case 243:
        
        case 244:
        
        case 245:
        
        case 246:
        
        case 247:
        
        case 248:
        
        case 249:
        
        case 250:
        
        case 251:
        
        case 252:
        
        case 253:
        
        case 254:
        
        default:
          break;
      } 
      char c = 'Ã';
      int j = (paramInt2 & 0xFF) - c;
      if (j < 0)
        j += 256; 
      int k = ((paramInt2 & 0xFFFF) >>> 8) - c;
      if (k < 0)
        k += 256; 
      for (byte b = 0; b < arrayOfChar.length; b++) {
        int m = b % 2;
        if (m == 0) {
          arrayOfChar[b] = (char)(arrayOfChar[b] ^ j);
          j = ((j >>> 3 | j << 5) ^ arrayOfChar[b]) & 0xFF;
        } else {
          arrayOfChar[b] = (char)(arrayOfChar[b] ^ k);
          k = ((k >>> 3 | k << 5) ^ arrayOfChar[b]) & 0xFF;
        } 
      } 
      b[i] = (new String(arrayOfChar)).intern();
    } 
    return b[i];
  }
}


/* Location:              C:\Program Files\BurpSuitePro\burpsuite_pro.jar!\burp\Zxee.class
 * Java compiler version: 21 (65.0)
 * JD-Core Version:       1.1.3
 */