package burp;

import java.math.BigInteger;

class Zxg7 extends ClassLoader {
  static Object Zy;
  
  static String Zi;
  
  private static final String[] a;
  
  private static final String[] b;
  
  static void Zh(Object[] paramArrayOfObject, Object paramObject) throws Throwable {}
  
  static boolean ZH(Object[] paramArrayOfObject, Object paramObject) throws Throwable {
    // Byte code:
    //   0: invokestatic ZN : ()Z
    //   3: istore_2
    //   4: getstatic burp/Zgnp.Zm : Ljava/lang/Object;
    //   7: checkcast java/math/BigInteger
    //   10: getstatic burp/Zt5j.Zn : Ljava/lang/Object;
    //   13: checkcast java/math/BigInteger
    //   16: invokevirtual add : (Ljava/math/BigInteger;)Ljava/math/BigInteger;
    //   19: putstatic burp/Zrjg.ZG : Ljava/lang/Object;
    //   22: new java/lang/StringBuilder
    //   25: dup
    //   26: invokespecial <init> : ()V
    //   29: astore_3
    //   30: iconst_0
    //   31: istore #4
    //   33: iload #4
    //   35: bipush #32
    //   37: if_icmpge -> 1371
    //   40: iload #4
    //   42: tableswitch default -> 1364, 0 -> 184, 1 -> 221, 2 -> 258, 3 -> 295, 4 -> 332, 5 -> 369, 6 -> 406, 7 -> 443, 8 -> 480, 9 -> 517, 10 -> 554, 11 -> 591, 12 -> 628, 13 -> 665, 14 -> 702, 15 -> 739, 16 -> 776, 17 -> 813, 18 -> 850, 19 -> 887, 20 -> 924, 21 -> 961, 22 -> 998, 23 -> 1035, 24 -> 1072, 25 -> 1109, 26 -> 1146, 27 -> 1183, 28 -> 1220, 29 -> 1257, 30 -> 1294, 31 -> 1331
    //   184: aload_3
    //   185: getstatic burp/Zs0_.ZH : Ljava/lang/String;
    //   188: getstatic burp/Ze64.ZW : Ljava/lang/Object;
    //   191: checkcast java/math/BigInteger
    //   194: invokevirtual intValue : ()I
    //   197: bipush #32
    //   199: irem
    //   200: invokestatic abs : (I)I
    //   203: invokevirtual charAt : (I)C
    //   206: invokevirtual append : (C)Ljava/lang/StringBuilder;
    //   209: pop
    //   210: iload_2
    //   211: ifne -> 1364
    //   214: goto -> 221
    //   217: invokestatic a : (Ljava/lang/Throwable;)Ljava/lang/Throwable;
    //   220: athrow
    //   221: aload_3
    //   222: getstatic burp/Zrpu.Zy : Ljava/lang/String;
    //   225: getstatic burp/Zrjg.ZG : Ljava/lang/Object;
    //   228: checkcast java/math/BigInteger
    //   231: invokevirtual intValue : ()I
    //   234: bipush #32
    //   236: irem
    //   237: invokestatic abs : (I)I
    //   240: invokevirtual charAt : (I)C
    //   243: invokevirtual append : (C)Ljava/lang/StringBuilder;
    //   246: pop
    //   247: iload_2
    //   248: ifne -> 1364
    //   251: goto -> 258
    //   254: invokestatic a : (Ljava/lang/Throwable;)Ljava/lang/Throwable;
    //   257: athrow
    //   258: aload_3
    //   259: getstatic burp/Zlhq.Zl : Ljava/lang/String;
    //   262: getstatic burp/Ztcv.ZY : Ljava/lang/Object;
    //   265: checkcast java/math/BigInteger
    //   268: invokevirtual intValue : ()I
    //   271: bipush #32
    //   273: irem
    //   274: invokestatic abs : (I)I
    //   277: invokevirtual charAt : (I)C
    //   280: invokevirtual append : (C)Ljava/lang/StringBuilder;
    //   283: pop
    //   284: iload_2
    //   285: ifne -> 1364
    //   288: goto -> 295
    //   291: invokestatic a : (Ljava/lang/Throwable;)Ljava/lang/Throwable;
    //   294: athrow
    //   295: aload_3
    //   296: getstatic burp/Zgpp.Zm : Ljava/lang/String;
    //   299: getstatic burp/Zlrm.ZM : Ljava/lang/Object;
    //   302: checkcast java/math/BigInteger
    //   305: invokevirtual intValue : ()I
    //   308: bipush #32
    //   310: irem
    //   311: invokestatic abs : (I)I
    //   314: invokevirtual charAt : (I)C
    //   317: invokevirtual append : (C)Ljava/lang/StringBuilder;
    //   320: pop
    //   321: iload_2
    //   322: ifne -> 1364
    //   325: goto -> 332
    //   328: invokestatic a : (Ljava/lang/Throwable;)Ljava/lang/Throwable;
    //   331: athrow
    //   332: aload_3
    //   333: getstatic burp/Zera.Zn : Ljava/lang/String;
    //   336: getstatic burp/Zltz.Zg : Ljava/lang/Object;
    //   339: checkcast java/math/BigInteger
    //   342: invokevirtual intValue : ()I
    //   345: bipush #32
    //   347: irem
    //   348: invokestatic abs : (I)I
    //   351: invokevirtual charAt : (I)C
    //   354: invokevirtual append : (C)Ljava/lang/StringBuilder;
    //   357: pop
    //   358: iload_2
    //   359: ifne -> 1364
    //   362: goto -> 369
    //   365: invokestatic a : (Ljava/lang/Throwable;)Ljava/lang/Throwable;
    //   368: athrow
    //   369: aload_3
    //   370: getstatic burp/Zlr.ZO : Ljava/lang/String;
    //   373: getstatic burp/Zltz.Zg : Ljava/lang/Object;
    //   376: checkcast java/math/BigInteger
    //   379: invokevirtual intValue : ()I
    //   382: bipush #32
    //   384: irem
    //   385: invokestatic abs : (I)I
    //   388: invokevirtual charAt : (I)C
    //   391: invokevirtual append : (C)Ljava/lang/StringBuilder;
    //   394: pop
    //   395: iload_2
    //   396: ifne -> 1364
    //   399: goto -> 406
    //   402: invokestatic a : (Ljava/lang/Throwable;)Ljava/lang/Throwable;
    //   405: athrow
    //   406: aload_3
    //   407: getstatic burp/Zxe.ZD : Ljava/lang/String;
    //   410: getstatic burp/Zkb_.ZG : Ljava/lang/Object;
    //   413: checkcast java/math/BigInteger
    //   416: invokevirtual intValue : ()I
    //   419: bipush #32
    //   421: irem
    //   422: invokestatic abs : (I)I
    //   425: invokevirtual charAt : (I)C
    //   428: invokevirtual append : (C)Ljava/lang/StringBuilder;
    //   431: pop
    //   432: iload_2
    //   433: ifne -> 1364
    //   436: goto -> 443
    //   439: invokestatic a : (Ljava/lang/Throwable;)Ljava/lang/Throwable;
    //   442: athrow
    //   443: aload_3
    //   444: getstatic burp/Zs75.Zn : Ljava/lang/String;
    //   447: getstatic burp/Zkm0.ZI : Ljava/lang/Object;
    //   450: checkcast java/math/BigInteger
    //   453: invokevirtual intValue : ()I
    //   456: bipush #32
    //   458: irem
    //   459: invokestatic abs : (I)I
    //   462: invokevirtual charAt : (I)C
    //   465: invokevirtual append : (C)Ljava/lang/StringBuilder;
    //   468: pop
    //   469: iload_2
    //   470: ifne -> 1364
    //   473: goto -> 480
    //   476: invokestatic a : (Ljava/lang/Throwable;)Ljava/lang/Throwable;
    //   479: athrow
    //   480: aload_3
    //   481: getstatic burp/Zera.Zn : Ljava/lang/String;
    //   484: getstatic burp/Zkll.Zl : Ljava/lang/Object;
    //   487: checkcast java/math/BigInteger
    //   490: invokevirtual intValue : ()I
    //   493: bipush #32
    //   495: irem
    //   496: invokestatic abs : (I)I
    //   499: invokevirtual charAt : (I)C
    //   502: invokevirtual append : (C)Ljava/lang/StringBuilder;
    //   505: pop
    //   506: iload_2
    //   507: ifne -> 1364
    //   510: goto -> 517
    //   513: invokestatic a : (Ljava/lang/Throwable;)Ljava/lang/Throwable;
    //   516: athrow
    //   517: aload_3
    //   518: getstatic burp/Zgqi.Zv : Ljava/lang/String;
    //   521: getstatic burp/Zs_v.Zs : Ljava/lang/Object;
    //   524: checkcast java/math/BigInteger
    //   527: invokevirtual intValue : ()I
    //   530: bipush #32
    //   532: irem
    //   533: invokestatic abs : (I)I
    //   536: invokevirtual charAt : (I)C
    //   539: invokevirtual append : (C)Ljava/lang/StringBuilder;
    //   542: pop
    //   543: iload_2
    //   544: ifne -> 1364
    //   547: goto -> 554
    //   550: invokestatic a : (Ljava/lang/Throwable;)Ljava/lang/Throwable;
    //   553: athrow
    //   554: aload_3
    //   555: getstatic burp/Zl8f.ZK : Ljava/lang/String;
    //   558: getstatic burp/Zb4a.ZJ : Ljava/lang/Object;
    //   561: checkcast java/math/BigInteger
    //   564: invokevirtual intValue : ()I
    //   567: bipush #32
    //   569: irem
    //   570: invokestatic abs : (I)I
    //   573: invokevirtual charAt : (I)C
    //   576: invokevirtual append : (C)Ljava/lang/StringBuilder;
    //   579: pop
    //   580: iload_2
    //   581: ifne -> 1364
    //   584: goto -> 591
    //   587: invokestatic a : (Ljava/lang/Throwable;)Ljava/lang/Throwable;
    //   590: athrow
    //   591: aload_3
    //   592: getstatic burp/Zxg7.Zi : Ljava/lang/String;
    //   595: getstatic burp/Zm3p.Zz : Ljava/lang/Object;
    //   598: checkcast java/math/BigInteger
    //   601: invokevirtual intValue : ()I
    //   604: bipush #32
    //   606: irem
    //   607: invokestatic abs : (I)I
    //   610: invokevirtual charAt : (I)C
    //   613: invokevirtual append : (C)Ljava/lang/StringBuilder;
    //   616: pop
    //   617: iload_2
    //   618: ifne -> 1364
    //   621: goto -> 628
    //   624: invokestatic a : (Ljava/lang/Throwable;)Ljava/lang/Throwable;
    //   627: athrow
    //   628: aload_3
    //   629: getstatic burp/Ze69.ZA : Ljava/lang/String;
    //   632: getstatic burp/Zlx5.Zp : Ljava/lang/Object;
    //   635: checkcast java/math/BigInteger
    //   638: invokevirtual intValue : ()I
    //   641: bipush #32
    //   643: irem
    //   644: invokestatic abs : (I)I
    //   647: invokevirtual charAt : (I)C
    //   650: invokevirtual append : (C)Ljava/lang/StringBuilder;
    //   653: pop
    //   654: iload_2
    //   655: ifne -> 1364
    //   658: goto -> 665
    //   661: invokestatic a : (Ljava/lang/Throwable;)Ljava/lang/Throwable;
    //   664: athrow
    //   665: aload_3
    //   666: getstatic burp/Zlvb.Zs : Ljava/lang/String;
    //   669: getstatic burp/Zm8v.ZU : Ljava/lang/Object;
    //   672: checkcast java/math/BigInteger
    //   675: invokevirtual intValue : ()I
    //   678: bipush #32
    //   680: irem
    //   681: invokestatic abs : (I)I
    //   684: invokevirtual charAt : (I)C
    //   687: invokevirtual append : (C)Ljava/lang/StringBuilder;
    //   690: pop
    //   691: iload_2
    //   692: ifne -> 1364
    //   695: goto -> 702
    //   698: invokestatic a : (Ljava/lang/Throwable;)Ljava/lang/Throwable;
    //   701: athrow
    //   702: aload_3
    //   703: getstatic burp/Zsqy.Zo : Ljava/lang/String;
    //   706: getstatic burp/Zzgh.ZV : Ljava/lang/Object;
    //   709: checkcast java/math/BigInteger
    //   712: invokevirtual intValue : ()I
    //   715: bipush #32
    //   717: irem
    //   718: invokestatic abs : (I)I
    //   721: invokevirtual charAt : (I)C
    //   724: invokevirtual append : (C)Ljava/lang/StringBuilder;
    //   727: pop
    //   728: iload_2
    //   729: ifne -> 1364
    //   732: goto -> 739
    //   735: invokestatic a : (Ljava/lang/Throwable;)Ljava/lang/Throwable;
    //   738: athrow
    //   739: aload_3
    //   740: getstatic burp/Zmyg.ZE : Ljava/lang/String;
    //   743: getstatic burp/Zefo.ZW : Ljava/lang/Object;
    //   746: checkcast java/math/BigInteger
    //   749: invokevirtual intValue : ()I
    //   752: bipush #32
    //   754: irem
    //   755: invokestatic abs : (I)I
    //   758: invokevirtual charAt : (I)C
    //   761: invokevirtual append : (C)Ljava/lang/StringBuilder;
    //   764: pop
    //   765: iload_2
    //   766: ifne -> 1364
    //   769: goto -> 776
    //   772: invokestatic a : (Ljava/lang/Throwable;)Ljava/lang/Throwable;
    //   775: athrow
    //   776: aload_3
    //   777: getstatic burp/Zl8f.ZK : Ljava/lang/String;
    //   780: getstatic burp/Zs8y.ZG : Ljava/lang/Object;
    //   783: checkcast java/math/BigInteger
    //   786: invokevirtual intValue : ()I
    //   789: bipush #32
    //   791: irem
    //   792: invokestatic abs : (I)I
    //   795: invokevirtual charAt : (I)C
    //   798: invokevirtual append : (C)Ljava/lang/StringBuilder;
    //   801: pop
    //   802: iload_2
    //   803: ifne -> 1364
    //   806: goto -> 813
    //   809: invokestatic a : (Ljava/lang/Throwable;)Ljava/lang/Throwable;
    //   812: athrow
    //   813: aload_3
    //   814: getstatic burp/Zix.Zp : Ljava/lang/String;
    //   817: getstatic burp/Zgpp.Zt : Ljava/lang/Object;
    //   820: checkcast java/math/BigInteger
    //   823: invokevirtual intValue : ()I
    //   826: bipush #32
    //   828: irem
    //   829: invokestatic abs : (I)I
    //   832: invokevirtual charAt : (I)C
    //   835: invokevirtual append : (C)Ljava/lang/StringBuilder;
    //   838: pop
    //   839: iload_2
    //   840: ifne -> 1364
    //   843: goto -> 850
    //   846: invokestatic a : (Ljava/lang/Throwable;)Ljava/lang/Throwable;
    //   849: athrow
    //   850: aload_3
    //   851: getstatic burp/Zsbt.ZX : Ljava/lang/String;
    //   854: getstatic burp/Zsbt.Zl : Ljava/lang/Object;
    //   857: checkcast java/math/BigInteger
    //   860: invokevirtual intValue : ()I
    //   863: bipush #32
    //   865: irem
    //   866: invokestatic abs : (I)I
    //   869: invokevirtual charAt : (I)C
    //   872: invokevirtual append : (C)Ljava/lang/StringBuilder;
    //   875: pop
    //   876: iload_2
    //   877: ifne -> 1364
    //   880: goto -> 887
    //   883: invokestatic a : (Ljava/lang/Throwable;)Ljava/lang/Throwable;
    //   886: athrow
    //   887: aload_3
    //   888: getstatic burp/Zztn.ZY : Ljava/lang/String;
    //   891: getstatic burp/Zlx5.Zp : Ljava/lang/Object;
    //   894: checkcast java/math/BigInteger
    //   897: invokevirtual intValue : ()I
    //   900: bipush #32
    //   902: irem
    //   903: invokestatic abs : (I)I
    //   906: invokevirtual charAt : (I)C
    //   909: invokevirtual append : (C)Ljava/lang/StringBuilder;
    //   912: pop
    //   913: iload_2
    //   914: ifne -> 1364
    //   917: goto -> 924
    //   920: invokestatic a : (Ljava/lang/Throwable;)Ljava/lang/Throwable;
    //   923: athrow
    //   924: aload_3
    //   925: getstatic burp/Zlf0.ZS : Ljava/lang/String;
    //   928: getstatic burp/Zz20.ZN : Ljava/lang/Object;
    //   931: checkcast java/math/BigInteger
    //   934: invokevirtual intValue : ()I
    //   937: bipush #32
    //   939: irem
    //   940: invokestatic abs : (I)I
    //   943: invokevirtual charAt : (I)C
    //   946: invokevirtual append : (C)Ljava/lang/StringBuilder;
    //   949: pop
    //   950: iload_2
    //   951: ifne -> 1364
    //   954: goto -> 961
    //   957: invokestatic a : (Ljava/lang/Throwable;)Ljava/lang/Throwable;
    //   960: athrow
    //   961: aload_3
    //   962: getstatic burp/Zr1z.ZB : Ljava/lang/String;
    //   965: getstatic burp/Ze69.ZH : Ljava/lang/Object;
    //   968: checkcast java/math/BigInteger
    //   971: invokevirtual intValue : ()I
    //   974: bipush #32
    //   976: irem
    //   977: invokestatic abs : (I)I
    //   980: invokevirtual charAt : (I)C
    //   983: invokevirtual append : (C)Ljava/lang/StringBuilder;
    //   986: pop
    //   987: iload_2
    //   988: ifne -> 1364
    //   991: goto -> 998
    //   994: invokestatic a : (Ljava/lang/Throwable;)Ljava/lang/Throwable;
    //   997: athrow
    //   998: aload_3
    //   999: getstatic burp/Zsxo.ZW : Ljava/lang/String;
    //   1002: getstatic burp/Zlf0.ZC : Ljava/lang/Object;
    //   1005: checkcast java/math/BigInteger
    //   1008: invokevirtual intValue : ()I
    //   1011: bipush #32
    //   1013: irem
    //   1014: invokestatic abs : (I)I
    //   1017: invokevirtual charAt : (I)C
    //   1020: invokevirtual append : (C)Ljava/lang/StringBuilder;
    //   1023: pop
    //   1024: iload_2
    //   1025: ifne -> 1364
    //   1028: goto -> 1035
    //   1031: invokestatic a : (Ljava/lang/Throwable;)Ljava/lang/Throwable;
    //   1034: athrow
    //   1035: aload_3
    //   1036: getstatic burp/Zxo7.Zl : Ljava/lang/String;
    //   1039: getstatic burp/Zsbt.Zl : Ljava/lang/Object;
    //   1042: checkcast java/math/BigInteger
    //   1045: invokevirtual intValue : ()I
    //   1048: bipush #32
    //   1050: irem
    //   1051: invokestatic abs : (I)I
    //   1054: invokevirtual charAt : (I)C
    //   1057: invokevirtual append : (C)Ljava/lang/StringBuilder;
    //   1060: pop
    //   1061: iload_2
    //   1062: ifne -> 1364
    //   1065: goto -> 1072
    //   1068: invokestatic a : (Ljava/lang/Throwable;)Ljava/lang/Throwable;
    //   1071: athrow
    //   1072: aload_3
    //   1073: getstatic burp/Zs8s.Za : Ljava/lang/String;
    //   1076: getstatic burp/Zevr.ZG : Ljava/lang/Object;
    //   1079: checkcast java/math/BigInteger
    //   1082: invokevirtual intValue : ()I
    //   1085: bipush #32
    //   1087: irem
    //   1088: invokestatic abs : (I)I
    //   1091: invokevirtual charAt : (I)C
    //   1094: invokevirtual append : (C)Ljava/lang/StringBuilder;
    //   1097: pop
    //   1098: iload_2
    //   1099: ifne -> 1364
    //   1102: goto -> 1109
    //   1105: invokestatic a : (Ljava/lang/Throwable;)Ljava/lang/Throwable;
    //   1108: athrow
    //   1109: aload_3
    //   1110: getstatic burp/Zkb_.ZR : Ljava/lang/String;
    //   1113: getstatic burp/Zg_5.ZA : Ljava/lang/Object;
    //   1116: checkcast java/math/BigInteger
    //   1119: invokevirtual intValue : ()I
    //   1122: bipush #32
    //   1124: irem
    //   1125: invokestatic abs : (I)I
    //   1128: invokevirtual charAt : (I)C
    //   1131: invokevirtual append : (C)Ljava/lang/StringBuilder;
    //   1134: pop
    //   1135: iload_2
    //   1136: ifne -> 1364
    //   1139: goto -> 1146
    //   1142: invokestatic a : (Ljava/lang/Throwable;)Ljava/lang/Throwable;
    //   1145: athrow
    //   1146: aload_3
    //   1147: getstatic burp/Zt98.Zh : Ljava/lang/String;
    //   1150: getstatic burp/Ze8m.Zm : Ljava/lang/Object;
    //   1153: checkcast java/math/BigInteger
    //   1156: invokevirtual intValue : ()I
    //   1159: bipush #32
    //   1161: irem
    //   1162: invokestatic abs : (I)I
    //   1165: invokevirtual charAt : (I)C
    //   1168: invokevirtual append : (C)Ljava/lang/StringBuilder;
    //   1171: pop
    //   1172: iload_2
    //   1173: ifne -> 1364
    //   1176: goto -> 1183
    //   1179: invokestatic a : (Ljava/lang/Throwable;)Ljava/lang/Throwable;
    //   1182: athrow
    //   1183: aload_3
    //   1184: getstatic burp/Ze_t.ZZ : Ljava/lang/String;
    //   1187: getstatic burp/Zrhp.Zw : Ljava/lang/Object;
    //   1190: checkcast java/math/BigInteger
    //   1193: invokevirtual intValue : ()I
    //   1196: bipush #32
    //   1198: irem
    //   1199: invokestatic abs : (I)I
    //   1202: invokevirtual charAt : (I)C
    //   1205: invokevirtual append : (C)Ljava/lang/StringBuilder;
    //   1208: pop
    //   1209: iload_2
    //   1210: ifne -> 1364
    //   1213: goto -> 1220
    //   1216: invokestatic a : (Ljava/lang/Throwable;)Ljava/lang/Throwable;
    //   1219: athrow
    //   1220: aload_3
    //   1221: getstatic burp/Zsxh.Z_ : Ljava/lang/String;
    //   1224: getstatic burp/Zef0.ZX : Ljava/lang/Object;
    //   1227: checkcast java/math/BigInteger
    //   1230: invokevirtual intValue : ()I
    //   1233: bipush #32
    //   1235: irem
    //   1236: invokestatic abs : (I)I
    //   1239: invokevirtual charAt : (I)C
    //   1242: invokevirtual append : (C)Ljava/lang/StringBuilder;
    //   1245: pop
    //   1246: iload_2
    //   1247: ifne -> 1364
    //   1250: goto -> 1257
    //   1253: invokestatic a : (Ljava/lang/Throwable;)Ljava/lang/Throwable;
    //   1256: athrow
    //   1257: aload_3
    //   1258: getstatic burp/Zkc8.Za : Ljava/lang/String;
    //   1261: getstatic burp/Zs8s.ZG : Ljava/lang/Object;
    //   1264: checkcast java/math/BigInteger
    //   1267: invokevirtual intValue : ()I
    //   1270: bipush #32
    //   1272: irem
    //   1273: invokestatic abs : (I)I
    //   1276: invokevirtual charAt : (I)C
    //   1279: invokevirtual append : (C)Ljava/lang/StringBuilder;
    //   1282: pop
    //   1283: iload_2
    //   1284: ifne -> 1364
    //   1287: goto -> 1294
    //   1290: invokestatic a : (Ljava/lang/Throwable;)Ljava/lang/Throwable;
    //   1293: athrow
    //   1294: aload_3
    //   1295: getstatic burp/Ze5t.ZX : Ljava/lang/String;
    //   1298: getstatic burp/Zk12.Zh : Ljava/lang/Object;
    //   1301: checkcast java/math/BigInteger
    //   1304: invokevirtual intValue : ()I
    //   1307: bipush #32
    //   1309: irem
    //   1310: invokestatic abs : (I)I
    //   1313: invokevirtual charAt : (I)C
    //   1316: invokevirtual append : (C)Ljava/lang/StringBuilder;
    //   1319: pop
    //   1320: iload_2
    //   1321: ifne -> 1364
    //   1324: goto -> 1331
    //   1327: invokestatic a : (Ljava/lang/Throwable;)Ljava/lang/Throwable;
    //   1330: athrow
    //   1331: aload_3
    //   1332: getstatic burp/Zre5.ZR : Ljava/lang/String;
    //   1335: getstatic burp/Zl8f.ZA : Ljava/lang/Object;
    //   1338: checkcast java/math/BigInteger
    //   1341: invokevirtual intValue : ()I
    //   1344: bipush #32
    //   1346: irem
    //   1347: invokestatic abs : (I)I
    //   1350: invokevirtual charAt : (I)C
    //   1353: invokevirtual append : (C)Ljava/lang/StringBuilder;
    //   1356: pop
    //   1357: goto -> 1364
    //   1360: invokestatic a : (Ljava/lang/Throwable;)Ljava/lang/Throwable;
    //   1363: athrow
    //   1364: iinc #4, 1
    //   1367: iload_2
    //   1368: ifne -> 33
    //   1371: aload_3
    //   1372: invokevirtual toString : ()Ljava/lang/String;
    //   1375: putstatic burp/Zk12.Zu : Ljava/lang/String;
    //   1378: ldc2_w 8682522807148012
    //   1381: invokestatic currentTimeMillis : ()J
    //   1384: lxor
    //   1385: lstore #5
    //   1387: lload #5
    //   1389: ldc2_w 25214903917
    //   1392: lmul
    //   1393: ldc2_w 11
    //   1396: ladd
    //   1397: ldc2_w 281474976710655
    //   1400: land
    //   1401: lstore #5
    //   1403: lload #5
    //   1405: bipush #32
    //   1407: lshl
    //   1408: lstore #7
    //   1410: lload #5
    //   1412: ldc2_w 25214903917
    //   1415: lmul
    //   1416: ldc2_w 11
    //   1419: ladd
    //   1420: ldc2_w 281474976710655
    //   1423: land
    //   1424: lstore #5
    //   1426: lload #7
    //   1428: lload #5
    //   1430: ladd
    //   1431: lstore #7
    //   1433: bipush #16
    //   1435: newarray byte
    //   1437: dup
    //   1438: iconst_0
    //   1439: bipush #48
    //   1441: bastore
    //   1442: dup
    //   1443: iconst_1
    //   1444: bipush #49
    //   1446: bastore
    //   1447: dup
    //   1448: iconst_2
    //   1449: bipush #50
    //   1451: bastore
    //   1452: dup
    //   1453: iconst_3
    //   1454: bipush #51
    //   1456: bastore
    //   1457: dup
    //   1458: iconst_4
    //   1459: bipush #52
    //   1461: bastore
    //   1462: dup
    //   1463: iconst_5
    //   1464: bipush #53
    //   1466: bastore
    //   1467: dup
    //   1468: bipush #6
    //   1470: bipush #54
    //   1472: bastore
    //   1473: dup
    //   1474: bipush #7
    //   1476: bipush #55
    //   1478: bastore
    //   1479: dup
    //   1480: bipush #8
    //   1482: bipush #56
    //   1484: bastore
    //   1485: dup
    //   1486: bipush #9
    //   1488: bipush #57
    //   1490: bastore
    //   1491: dup
    //   1492: bipush #10
    //   1494: bipush #97
    //   1496: bastore
    //   1497: dup
    //   1498: bipush #11
    //   1500: bipush #98
    //   1502: bastore
    //   1503: dup
    //   1504: bipush #12
    //   1506: bipush #99
    //   1508: bastore
    //   1509: dup
    //   1510: bipush #13
    //   1512: bipush #100
    //   1514: bastore
    //   1515: dup
    //   1516: bipush #14
    //   1518: bipush #101
    //   1520: bastore
    //   1521: dup
    //   1522: bipush #15
    //   1524: bipush #102
    //   1526: bastore
    //   1527: astore #9
    //   1529: bipush #64
    //   1531: newarray byte
    //   1533: astore #10
    //   1535: bipush #64
    //   1537: istore #11
    //   1539: bipush #16
    //   1541: istore #12
    //   1543: iload #12
    //   1545: iconst_1
    //   1546: isub
    //   1547: i2l
    //   1548: lstore #13
    //   1550: aload #10
    //   1552: iinc #11, -1
    //   1555: iload #11
    //   1557: aload #9
    //   1559: lload #7
    //   1561: lload #13
    //   1563: land
    //   1564: l2i
    //   1565: baload
    //   1566: bastore
    //   1567: lload #7
    //   1569: iconst_4
    //   1570: lushr
    //   1571: lstore #7
    //   1573: lload #7
    //   1575: lconst_0
    //   1576: lcmp
    //   1577: ifne -> 1550
    //   1580: bipush #64
    //   1582: iload #11
    //   1584: isub
    //   1585: newarray byte
    //   1587: astore #4
    //   1589: iconst_0
    //   1590: istore #15
    //   1592: iload #15
    //   1594: aload #4
    //   1596: arraylength
    //   1597: if_icmpge -> 1620
    //   1600: aload #4
    //   1602: iload #15
    //   1604: aload #10
    //   1606: iload #11
    //   1608: iload #15
    //   1610: iadd
    //   1611: baload
    //   1612: bastore
    //   1613: iinc #15, 1
    //   1616: iload_2
    //   1617: ifne -> 1592
    //   1620: aload #4
    //   1622: arraylength
    //   1623: bipush #10
    //   1625: if_icmplt -> 1387
    //   1628: sipush #27463
    //   1631: sipush #10050
    //   1634: invokestatic a : (II)Ljava/lang/String;
    //   1637: iconst_1
    //   1638: ldc burp/Zm__
    //   1640: invokevirtual getClassLoader : ()Ljava/lang/ClassLoader;
    //   1643: invokestatic forName : (Ljava/lang/String;ZLjava/lang/ClassLoader;)Ljava/lang/Class;
    //   1646: invokevirtual getDeclaredFields : ()[Ljava/lang/reflect/Field;
    //   1649: astore #4
    //   1651: aload #4
    //   1653: arraylength
    //   1654: istore #5
    //   1656: iconst_0
    //   1657: istore #6
    //   1659: iload #6
    //   1661: iload #5
    //   1663: if_icmpge -> 1801
    //   1666: aload #4
    //   1668: iload #6
    //   1670: aaload
    //   1671: astore #7
    //   1673: aload #7
    //   1675: invokevirtual getModifiers : ()I
    //   1678: invokestatic isStatic : (I)Z
    //   1681: ifne -> 1691
    //   1684: goto -> 1794
    //   1687: invokestatic a : (Ljava/lang/Throwable;)Ljava/lang/Throwable;
    //   1690: athrow
    //   1691: aload #7
    //   1693: invokevirtual getType : ()Ljava/lang/Class;
    //   1696: astore #8
    //   1698: aload #8
    //   1700: ifnull -> 1781
    //   1703: aload #8
    //   1705: invokevirtual isPrimitive : ()Z
    //   1708: ifne -> 1781
    //   1711: goto -> 1718
    //   1714: invokestatic a : (Ljava/lang/Throwable;)Ljava/lang/Throwable;
    //   1717: athrow
    //   1718: aload #8
    //   1720: invokevirtual getPackage : ()Ljava/lang/Package;
    //   1723: ifnull -> 1781
    //   1726: goto -> 1733
    //   1729: invokestatic a : (Ljava/lang/Throwable;)Ljava/lang/Throwable;
    //   1732: athrow
    //   1733: aload #8
    //   1735: invokevirtual getPackage : ()Ljava/lang/Package;
    //   1738: invokevirtual getName : ()Ljava/lang/String;
    //   1741: ifnull -> 1781
    //   1744: goto -> 1751
    //   1747: invokestatic a : (Ljava/lang/Throwable;)Ljava/lang/Throwable;
    //   1750: athrow
    //   1751: aload #8
    //   1753: invokevirtual getPackage : ()Ljava/lang/Package;
    //   1756: invokevirtual getName : ()Ljava/lang/String;
    //   1759: sipush #27461
    //   1762: sipush #-10907
    //   1765: invokestatic a : (II)Ljava/lang/String;
    //   1768: invokevirtual startsWith : (Ljava/lang/String;)Z
    //   1771: ifne -> 1781
    //   1774: goto -> 1781
    //   1777: invokestatic a : (Ljava/lang/Throwable;)Ljava/lang/Throwable;
    //   1780: athrow
    //   1781: aload #7
    //   1783: iconst_1
    //   1784: invokevirtual setAccessible : (Z)V
    //   1787: aload #7
    //   1789: aconst_null
    //   1790: invokevirtual get : (Ljava/lang/Object;)Ljava/lang/Object;
    //   1793: pop
    //   1794: iinc #6, 1
    //   1797: iload_2
    //   1798: ifne -> 1659
    //   1801: sipush #27458
    //   1804: sipush #-32520
    //   1807: invokestatic a : (II)Ljava/lang/String;
    //   1810: invokestatic forName : (Ljava/lang/String;)Ljava/lang/Class;
    //   1813: invokevirtual getDeclaredMethods : ()[Ljava/lang/reflect/Method;
    //   1816: astore #4
    //   1818: aload #4
    //   1820: arraylength
    //   1821: istore #5
    //   1823: iconst_0
    //   1824: istore #6
    //   1826: iload #6
    //   1828: iload #5
    //   1830: if_icmpge -> 1963
    //   1833: aload #4
    //   1835: iload #6
    //   1837: aaload
    //   1838: astore #7
    //   1840: aload #7
    //   1842: invokevirtual getParameterTypes : ()[Ljava/lang/Class;
    //   1845: pop
    //   1846: aload #7
    //   1848: invokevirtual getModifiers : ()I
    //   1851: invokestatic isStatic : (I)Z
    //   1854: ifeq -> 1949
    //   1857: aload #7
    //   1859: invokevirtual getParameterTypes : ()[Ljava/lang/Class;
    //   1862: arraylength
    //   1863: iconst_2
    //   1864: if_icmpne -> 1949
    //   1867: goto -> 1874
    //   1870: invokestatic a : (Ljava/lang/Throwable;)Ljava/lang/Throwable;
    //   1873: athrow
    //   1874: aload #7
    //   1876: invokevirtual getReturnType : ()Ljava/lang/Class;
    //   1879: getstatic java/lang/Void.TYPE : Ljava/lang/Class;
    //   1882: invokevirtual equals : (Ljava/lang/Object;)Z
    //   1885: ifeq -> 1949
    //   1888: goto -> 1895
    //   1891: invokestatic a : (Ljava/lang/Throwable;)Ljava/lang/Throwable;
    //   1894: athrow
    //   1895: aload #7
    //   1897: iconst_1
    //   1898: invokevirtual setAccessible : (Z)V
    //   1901: aload #7
    //   1903: aconst_null
    //   1904: iconst_2
    //   1905: anewarray java/lang/Object
    //   1908: dup
    //   1909: iconst_0
    //   1910: aload_0
    //   1911: aastore
    //   1912: dup
    //   1913: iconst_1
    //   1914: aload_1
    //   1915: ifnonnull -> 1933
    //   1918: goto -> 1925
    //   1921: invokestatic a : (Ljava/lang/Throwable;)Ljava/lang/Throwable;
    //   1924: athrow
    //   1925: aload_1
    //   1926: goto -> 1940
    //   1929: invokestatic a : (Ljava/lang/Throwable;)Ljava/lang/Throwable;
    //   1932: athrow
    //   1933: aload_1
    //   1934: checkcast [B
    //   1937: invokevirtual clone : ()Ljava/lang/Object;
    //   1940: aastore
    //   1941: invokevirtual invoke : (Ljava/lang/Object;[Ljava/lang/Object;)Ljava/lang/Object;
    //   1944: pop
    //   1945: iload_2
    //   1946: ifne -> 1963
    //   1949: iinc #6, 1
    //   1952: iload_2
    //   1953: ifne -> 1826
    //   1956: goto -> 1963
    //   1959: invokestatic a : (Ljava/lang/Throwable;)Ljava/lang/Throwable;
    //   1962: athrow
    //   1963: getstatic burp/Ztj5.Zt : Ljava/lang/String;
    //   1966: getstatic burp/Zeb7.ZJ : Ljava/lang/Object;
    //   1969: checkcast java/math/BigInteger
    //   1972: invokevirtual intValue : ()I
    //   1975: bipush #32
    //   1977: irem
    //   1978: invokestatic abs : (I)I
    //   1981: invokevirtual charAt : (I)C
    //   1984: getstatic burp/Zeuc.Zp : Ljava/lang/String;
    //   1987: getstatic burp/Zex.ZO : Ljava/lang/Object;
    //   1990: checkcast java/math/BigInteger
    //   1993: invokevirtual intValue : ()I
    //   1996: bipush #32
    //   1998: irem
    //   1999: invokestatic abs : (I)I
    //   2002: invokevirtual charAt : (I)C
    //   2005: if_icmpgt -> 2112
    //   2008: getstatic burp/Zex.Zn : Ljava/lang/String;
    //   2011: getstatic burp/Zgpp.Zt : Ljava/lang/Object;
    //   2014: checkcast java/math/BigInteger
    //   2017: invokevirtual intValue : ()I
    //   2020: bipush #32
    //   2022: irem
    //   2023: invokestatic abs : (I)I
    //   2026: invokevirtual charAt : (I)C
    //   2029: getstatic burp/Ze54.ZU : Ljava/lang/String;
    //   2032: getstatic burp/Zlrm.ZM : Ljava/lang/Object;
    //   2035: checkcast java/math/BigInteger
    //   2038: invokevirtual intValue : ()I
    //   2041: bipush #32
    //   2043: irem
    //   2044: invokestatic abs : (I)I
    //   2047: invokevirtual charAt : (I)C
    //   2050: if_icmple -> 2112
    //   2053: goto -> 2060
    //   2056: invokestatic a : (Ljava/lang/Throwable;)Ljava/lang/Throwable;
    //   2059: athrow
    //   2060: getstatic burp/Zlh8.ZY : Ljava/lang/String;
    //   2063: getstatic burp/Zxn5.Zd : Ljava/lang/Object;
    //   2066: checkcast java/math/BigInteger
    //   2069: invokevirtual intValue : ()I
    //   2072: bipush #32
    //   2074: irem
    //   2075: invokestatic abs : (I)I
    //   2078: invokevirtual charAt : (I)C
    //   2081: getstatic burp/Ze69.ZA : Ljava/lang/String;
    //   2084: getstatic burp/Zk7e.ZW : Ljava/lang/Object;
    //   2087: checkcast java/math/BigInteger
    //   2090: invokevirtual intValue : ()I
    //   2093: bipush #32
    //   2095: irem
    //   2096: invokestatic abs : (I)I
    //   2099: invokevirtual charAt : (I)C
    //   2102: if_icmple -> 2120
    //   2105: goto -> 2112
    //   2108: invokestatic a : (Ljava/lang/Throwable;)Ljava/lang/Throwable;
    //   2111: athrow
    //   2112: iconst_1
    //   2113: goto -> 2121
    //   2116: invokestatic a : (Ljava/lang/Throwable;)Ljava/lang/Throwable;
    //   2119: athrow
    //   2120: iconst_0
    //   2121: ireturn
    //   2122: astore_3
    //   2123: new java/lang/Exception
    //   2126: dup
    //   2127: aload_3
    //   2128: invokevirtual getMessage : ()Ljava/lang/String;
    //   2131: invokespecial <init> : (Ljava/lang/String;)V
    //   2134: athrow
    // Exception table:
    //   from	to	target	type
    //   4	2121	2122	java/lang/Throwable
    //   40	214	217	java/lang/Throwable
    //   184	251	254	java/lang/Throwable
    //   221	288	291	java/lang/Throwable
    //   258	325	328	java/lang/Throwable
    //   295	362	365	java/lang/Throwable
    //   332	399	402	java/lang/Throwable
    //   369	436	439	java/lang/Throwable
    //   406	473	476	java/lang/Throwable
    //   443	510	513	java/lang/Throwable
    //   480	547	550	java/lang/Throwable
    //   517	584	587	java/lang/Throwable
    //   554	621	624	java/lang/Throwable
    //   591	658	661	java/lang/Throwable
    //   628	695	698	java/lang/Throwable
    //   665	732	735	java/lang/Throwable
    //   702	769	772	java/lang/Throwable
    //   739	806	809	java/lang/Throwable
    //   776	843	846	java/lang/Throwable
    //   813	880	883	java/lang/Throwable
    //   850	917	920	java/lang/Throwable
    //   887	954	957	java/lang/Throwable
    //   924	991	994	java/lang/Throwable
    //   961	1028	1031	java/lang/Throwable
    //   998	1065	1068	java/lang/Throwable
    //   1035	1102	1105	java/lang/Throwable
    //   1072	1139	1142	java/lang/Throwable
    //   1109	1176	1179	java/lang/Throwable
    //   1146	1213	1216	java/lang/Throwable
    //   1183	1250	1253	java/lang/Throwable
    //   1220	1287	1290	java/lang/Throwable
    //   1257	1324	1327	java/lang/Throwable
    //   1294	1357	1360	java/lang/Throwable
    //   1673	1687	1687	java/lang/Throwable
    //   1698	1711	1714	java/lang/Throwable
    //   1703	1726	1729	java/lang/Throwable
    //   1718	1744	1747	java/lang/Throwable
    //   1733	1774	1777	java/lang/Throwable
    //   1840	1867	1870	java/lang/Throwable
    //   1857	1888	1891	java/lang/Throwable
    //   1874	1918	1921	java/lang/Throwable
    //   1895	1929	1929	java/lang/Throwable
    //   1940	1956	1959	java/lang/Throwable
    //   1963	2053	2056	java/lang/Throwable
    //   2008	2105	2108	java/lang/Throwable
    //   2060	2116	2116	java/lang/Throwable
  }
  
  static void Zm(Object paramObject) {
    Zt9_.Zf = a(27457, 10778);
    Zt9_.ZN = new BigInteger(a(27456, 538));
    boolean bool = Zt2e.ZK();
    try {
      try {
        if (Zkll.ZX.charAt(Math.abs(((BigInteger)Zztk.Za).intValue() % 32)) > Zrcy.Zq.charAt(Math.abs(((BigInteger)Zt5j.Zn).intValue() % 32))) {
          try {
            Ze69.Zh(Class.forName(a(27462, 8072)));
            if (bool)
              Ztkh.Zh(Class.forName(a(27459, -10747))); 
          } catch (Throwable throwable) {
            throw a(null);
          } 
          return;
        } 
      } catch (Throwable throwable) {
        throw a(null);
      } 
      Ztkh.Zh(Class.forName(a(27459, -10747)));
    } catch (Throwable throwable) {}
  }
  
  static {
    // Byte code:
    //   0: bipush #8
    //   2: anewarray java/lang/String
    //   5: astore #5
    //   7: iconst_0
    //   8: istore_3
    //   9: ldc 'Ã½9]FÃ›Ã¢\\tÃ²rÂ¼rz.Â€ ÂºÃ–Â“(>CÃ˜LÃ¢^Ã«ÃºÂ‹ÃÂº,ÃuÃ‡'Ã©'[Ã»\\nÃ¿Â‰Ã“Â2Â¯Â¤Ã‰\\tÂ•pP2Ã§&3s\\tÂ”Â¨p)Ã£EÂ½$r'
    //   11: dup
    //   12: astore_2
    //   13: invokevirtual length : ()I
    //   16: istore #4
    //   18: bipush #9
    //   20: istore_1
    //   21: iconst_m1
    //   22: istore_0
    //   23: bipush #12
    //   25: iinc #0, 1
    //   28: aload_2
    //   29: iload_0
    //   30: dup
    //   31: iload_1
    //   32: iadd
    //   33: invokevirtual substring : (II)Ljava/lang/String;
    //   36: iconst_m1
    //   37: goto -> 143
    //   40: aload #5
    //   42: swap
    //   43: iload_3
    //   44: iinc #3, 1
    //   47: swap
    //   48: aastore
    //   49: iload_0
    //   50: iload_1
    //   51: iadd
    //   52: dup
    //   53: istore_0
    //   54: iload #4
    //   56: if_icmpge -> 68
    //   59: aload_2
    //   60: iload_0
    //   61: invokevirtual charAt : (I)C
    //   64: istore_1
    //   65: goto -> 23
    //   68: ldc 'ÂŸÃžÂ“Ã¿Â²IÃ»eÂÂ¨Âž7nÃ­Ã¡/zÂ¡AÃŠÂ©|gÃ‡G0>Â£Ã…Â«Ã™ NrÃªÃ€Â¾A<GÃ»Â«Ã¶ÂœWÂ¶Â°ÂœÂ™LÂŠ"mÃªÂ‚&ÃžÃŒ`[FEÃ“/^Ã§Â…- Â¾Ã•Â¿ÃšBSjvÃÂ„Â½D*Â»EÂ›Ã“IÃ˜,Ã¸Â“P"*K\\tÃˆOÂŽ'
    //   70: dup
    //   71: astore_2
    //   72: invokevirtual length : ()I
    //   75: istore #4
    //   77: bipush #77
    //   79: istore_1
    //   80: iconst_m1
    //   81: istore_0
    //   82: bipush #89
    //   84: iinc #0, 1
    //   87: aload_2
    //   88: iload_0
    //   89: dup
    //   90: iload_1
    //   91: iadd
    //   92: invokevirtual substring : (II)Ljava/lang/String;
    //   95: iconst_0
    //   96: goto -> 143
    //   99: aload #5
    //   101: swap
    //   102: iload_3
    //   103: iinc #3, 1
    //   106: swap
    //   107: aastore
    //   108: iload_0
    //   109: iload_1
    //   110: iadd
    //   111: dup
    //   112: istore_0
    //   113: iload #4
    //   115: if_icmpge -> 127
    //   118: aload_2
    //   119: iload_0
    //   120: invokevirtual charAt : (I)C
    //   123: istore_1
    //   124: goto -> 82
    //   127: aload #5
    //   129: putstatic burp/Zxg7.a : [Ljava/lang/String;
    //   132: bipush #8
    //   134: anewarray java/lang/String
    //   137: putstatic burp/Zxg7.b : [Ljava/lang/String;
    //   140: goto -> 300
    //   143: dup_x2
    //   144: pop
    //   145: invokevirtual toCharArray : ()[C
    //   148: dup_x1
    //   149: arraylength
    //   150: dup_x2
    //   151: pop
    //   152: iconst_0
    //   153: istore #6
    //   155: dup2_x1
    //   156: pop2
    //   157: dup_x2
    //   158: iconst_1
    //   159: if_icmpgt -> 259
    //   162: dup2
    //   163: swap
    //   164: iload #6
    //   166: dup2_x1
    //   167: caload
    //   168: swap
    //   169: iload #6
    //   171: bipush #7
    //   173: irem
    //   174: tableswitch default -> 241, 0 -> 212, 1 -> 217, 2 -> 222, 3 -> 227, 4 -> 232, 5 -> 237
    //   212: bipush #24
    //   214: goto -> 243
    //   217: bipush #98
    //   219: goto -> 243
    //   222: bipush #48
    //   224: goto -> 243
    //   227: bipush #86
    //   229: goto -> 243
    //   232: bipush #116
    //   234: goto -> 243
    //   237: iconst_3
    //   238: goto -> 243
    //   241: bipush #83
    //   243: ixor
    //   244: ixor
    //   245: i2c
    //   246: castore
    //   247: iinc #6, 1
    //   250: dup
    //   251: ifne -> 259
    //   254: dup2
    //   255: dup_x1
    //   256: goto -> 166
    //   259: dup2_x1
    //   260: pop2
    //   261: dup_x2
    //   262: iload #6
    //   264: if_icmpgt -> 162
    //   267: pop
    //   268: new java/lang/String
    //   271: dup_x1
    //   272: swap
    //   273: invokespecial <init> : ([C)V
    //   276: invokevirtual intern : ()Ljava/lang/String;
    //   279: swap
    //   280: pop
    //   281: swap
    //   282: tableswitch default -> 40, 0 -> 99
    //   300: new java/math/BigInteger
    //   303: dup
    //   304: iconst_1
    //   305: bipush #32
    //   307: newarray byte
    //   309: dup
    //   310: iconst_0
    //   311: bipush #27
    //   313: bastore
    //   314: dup
    //   315: iconst_1
    //   316: bipush #-120
    //   318: bastore
    //   319: dup
    //   320: iconst_2
    //   321: bipush #-11
    //   323: bastore
    //   324: dup
    //   325: iconst_3
    //   326: bipush #-105
    //   328: bastore
    //   329: dup
    //   330: iconst_4
    //   331: bipush #35
    //   333: bastore
    //   334: dup
    //   335: iconst_5
    //   336: bipush #-18
    //   338: bastore
    //   339: dup
    //   340: bipush #6
    //   342: bipush #36
    //   344: bastore
    //   345: dup
    //   346: bipush #7
    //   348: bipush #-49
    //   350: bastore
    //   351: dup
    //   352: bipush #8
    //   354: bipush #-97
    //   356: bastore
    //   357: dup
    //   358: bipush #9
    //   360: bipush #22
    //   362: bastore
    //   363: dup
    //   364: bipush #10
    //   366: bipush #-28
    //   368: bastore
    //   369: dup
    //   370: bipush #11
    //   372: bipush #122
    //   374: bastore
    //   375: dup
    //   376: bipush #12
    //   378: bipush #58
    //   380: bastore
    //   381: dup
    //   382: bipush #13
    //   384: iconst_3
    //   385: bastore
    //   386: dup
    //   387: bipush #14
    //   389: bipush #-2
    //   391: bastore
    //   392: dup
    //   393: bipush #15
    //   395: bipush #-35
    //   397: bastore
    //   398: dup
    //   399: bipush #16
    //   401: bipush #56
    //   403: bastore
    //   404: dup
    //   405: bipush #17
    //   407: bipush #25
    //   409: bastore
    //   410: dup
    //   411: bipush #18
    //   413: bipush #26
    //   415: bastore
    //   416: dup
    //   417: bipush #19
    //   419: bipush #87
    //   421: bastore
    //   422: dup
    //   423: bipush #20
    //   425: iconst_4
    //   426: bastore
    //   427: dup
    //   428: bipush #21
    //   430: bipush #52
    //   432: bastore
    //   433: dup
    //   434: bipush #22
    //   436: bipush #-62
    //   438: bastore
    //   439: dup
    //   440: bipush #23
    //   442: bipush #-66
    //   444: bastore
    //   445: dup
    //   446: bipush #24
    //   448: bipush #-22
    //   450: bastore
    //   451: dup
    //   452: bipush #25
    //   454: bipush #81
    //   456: bastore
    //   457: dup
    //   458: bipush #26
    //   460: bipush #44
    //   462: bastore
    //   463: dup
    //   464: bipush #27
    //   466: bipush #126
    //   468: bastore
    //   469: dup
    //   470: bipush #28
    //   472: bipush #-60
    //   474: bastore
    //   475: dup
    //   476: bipush #29
    //   478: bipush #-62
    //   480: bastore
    //   481: dup
    //   482: bipush #30
    //   484: bipush #-107
    //   486: bastore
    //   487: dup
    //   488: bipush #31
    //   490: bipush #99
    //   492: bastore
    //   493: invokespecial <init> : (I[B)V
    //   496: putstatic burp/Zxg7.Zy : Ljava/lang/Object;
    //   499: sipush #27460
    //   502: sipush #-27175
    //   505: invokestatic a : (II)Ljava/lang/String;
    //   508: putstatic burp/Zxg7.Zi : Ljava/lang/String;
    //   511: return
  }
  
  private static Throwable a(Throwable paramThrowable) {
    return paramThrowable;
  }
  
  private static String a(int paramInt1, int paramInt2) {
    int i = (paramInt1 ^ 0x6B46) & 0xFFFF;
    if (b[i] == null) {
      char[] arrayOfChar = a[i].toCharArray();
      switch (arrayOfChar[0] & 0xFF) {
        case 0:
        
        case 1:
        
        case 2:
        
        case 3:
        
        case 4:
        
        case 5:
        
        case 6:
        
        case 7:
        
        case 8:
        
        case 9:
        
        case 10:
        
        case 11:
        
        case 12:
        
        case 13:
        
        case 14:
        
        case 15:
        
        case 16:
        
        case 17:
        
        case 18:
        
        case 19:
        
        case 20:
        
        case 21:
        
        case 22:
        
        case 23:
        
        case 24:
        
        case 25:
        
        case 26:
        
        case 27:
        
        case 28:
        
        case 29:
        
        case 30:
        
        case 31:
        
        case 32:
        
        case 33:
        
        case 34:
        
        case 35:
        
        case 36:
        
        case 37:
        
        case 38:
        
        case 39:
        
        case 40:
        
        case 41:
        
        case 42:
        
        case 43:
        
        case 44:
        
        case 45:
        
        case 46:
        
        case 47:
        
        case 48:
        
        case 49:
        
        case 50:
        
        case 51:
        
        case 52:
        
        case 53:
        
        case 54:
        
        case 55:
        
        case 56:
        
        case 57:
        
        case 58:
        
        case 59:
        
        case 60:
        
        case 61:
        
        case 62:
        
        case 63:
        
        case 64:
        
        case 65:
        
        case 66:
        
        case 67:
        
        case 68:
        
        case 69:
        
        case 70:
        
        case 71:
        
        case 72:
        
        case 73:
        
        case 74:
        
        case 75:
        
        case 76:
        
        case 77:
        
        case 78:
        
        case 79:
        
        case 80:
        
        case 81:
        
        case 82:
        
        case 83:
        
        case 84:
        
        case 85:
        
        case 86:
        
        case 87:
        
        case 88:
        
        case 89:
        
        case 90:
        
        case 91:
        
        case 92:
        
        case 93:
        
        case 94:
        
        case 95:
        
        case 96:
        
        case 97:
        
        case 98:
        
        case 99:
        
        case 100:
        
        case 101:
        
        case 102:
        
        case 103:
        
        case 104:
        
        case 105:
        
        case 106:
        
        case 107:
        
        case 108:
        
        case 109:
        
        case 110:
        
        case 111:
        
        case 112:
        
        case 113:
        
        case 114:
        
        case 115:
        
        case 116:
        
        case 117:
        
        case 118:
        
        case 119:
        
        case 120:
        
        case 121:
        
        case 122:
        
        case 123:
        
        case 124:
        
        case 125:
        
        case 126:
        
        case 127:
        
        case 128:
        
        case 129:
        
        case 130:
        
        case 131:
        
        case 132:
        
        case 133:
        
        case 134:
        
        case 135:
        
        case 136:
        
        case 137:
        
        case 138:
        
        case 139:
        
        case 140:
        
        case 141:
        
        case 142:
        
        case 143:
        
        case 144:
        
        case 145:
        
        case 146:
        
        case 147:
        
        case 148:
        
        case 149:
        
        case 150:
        
        case 151:
        
        case 152:
        
        case 153:
        
        case 154:
        
        case 155:
        
        case 156:
        
        case 157:
        
        case 158:
        
        case 159:
        
        case 160:
        
        case 161:
        
        case 162:
        
        case 163:
        
        case 164:
        
        case 165:
        
        case 166:
        
        case 167:
        
        case 168:
        
        case 169:
        
        case 170:
        
        case 171:
        
        case 172:
        
        case 173:
        
        case 174:
        
        case 175:
        
        case 176:
        
        case 177:
        
        case 178:
        
        case 179:
        
        case 180:
        
        case 181:
        
        case 182:
        
        case 183:
        
        case 184:
        
        case 185:
        
        case 186:
        
        case 187:
        
        case 188:
        
        case 189:
        
        case 190:
        
        case 191:
        
        case 192:
        
        case 193:
        
        case 194:
        
        case 195:
        
        case 196:
        
        case 197:
        
        case 198:
        
        case 199:
        
        case 200:
        
        case 201:
        
        case 202:
        
        case 203:
        
        case 204:
        
        case 205:
        
        case 206:
        
        case 207:
        
        case 208:
        
        case 209:
        
        case 210:
        
        case 211:
        
        case 212:
        
        case 213:
        
        case 214:
        
        case 215:
        
        case 216:
        
        case 217:
        
        case 218:
        
        case 219:
        
        case 220:
        
        case 221:
        
        case 222:
        
        case 223:
        
        case 224:
        
        case 225:
        
        case 226:
        
        case 227:
        
        case 228:
        
        case 229:
        
        case 230:
        
        case 231:
        
        case 232:
        
        case 233:
        
        case 234:
        
        case 235:
        
        case 236:
        
        case 237:
        
        case 238:
        
        case 239:
        
        case 240:
        
        case 241:
        
        case 242:
        
        case 243:
        
        case 244:
        
        case 245:
        
        case 246:
        
        case 247:
        
        case 248:
        
        case 249:
        
        case 250:
        
        case 251:
        
        case 252:
        
        case 253:
        
        case 254:
        
        default:
          break;
      } 
      byte b1 = 84;
      int j = (paramInt2 & 0xFF) - b1;
      if (j < 0)
        j += 256; 
      int k = ((paramInt2 & 0xFFFF) >>> 8) - b1;
      if (k < 0)
        k += 256; 
      for (byte b2 = 0; b2 < arrayOfChar.length; b2++) {
        int m = b2 % 2;
        if (m == 0) {
          arrayOfChar[b2] = (char)(arrayOfChar[b2] ^ j);
          j = ((j >>> 3 | j << 5) ^ arrayOfChar[b2]) & 0xFF;
        } else {
          arrayOfChar[b2] = (char)(arrayOfChar[b2] ^ k);
          k = ((k >>> 3 | k << 5) ^ arrayOfChar[b2]) & 0xFF;
        } 
      } 
      b[i] = (new String(arrayOfChar)).intern();
    } 
    return b[i];
  }
}


/* Location:              C:\Program Files\BurpSuitePro\burpsuite_pro.jar!\burp\Zxg7.class
 * Java compiler version: 21 (65.0)
 * JD-Core Version:       1.1.3
 */