package burp;

public class Zxhy extends Zxsr implements Zgzp {
  private static final String a;
  
  Zxhy(Zkit paramZkit, long paramLong) {
    super(paramZkit, paramLong);
  }
  
  public int Z_G() {
    return this.Za.Zx(this, Zk0e.Ze);
  }
  
  public void Zk0(int paramInt) {
    this.Za.ZM(this, Zk0e.Ze, paramInt);
  }
  
  public boolean Z_L() {
    return this.Za.Zi(this, Zk0e.ZE);
  }
  
  public void ZPC(boolean paramBoolean) {
    this.Za.ZH(this, Zk0e.ZE, paramBoolean);
  }
  
  public boolean Z_j() {
    return this.Za.Zi(this, Zk0e.Zo);
  }
  
  public void ZPZ(boolean paramBoolean) {
    this.Za.ZH(this, Zk0e.Zo, paramBoolean);
  }
  
  public boolean Z_K() {
    return this.Za.Zi(this, Zk0e.Zp);
  }
  
  public void ZPK(boolean paramBoolean) {
    this.Za.ZH(this, Zk0e.Zp, paramBoolean);
  }
  
  public boolean Z_e() {
    return this.Za.Zi(this, Zk0e.ZC);
  }
  
  public void ZP2(boolean paramBoolean) {
    this.Za.ZH(this, Zk0e.ZC, paramBoolean);
  }
  
  public boolean Z_q() {
    return this.Za.Zi(this, Zk0e.Zq);
  }
  
  public void ZPe(boolean paramBoolean) {
    this.Za.ZH(this, Zk0e.Zq, paramBoolean);
  }
  
  public boolean Z_r() {
    return this.Za.Zi(this, Zk0e.ZZ);
  }
  
  public void ZPP(boolean paramBoolean) {
    this.Za.ZH(this, Zk0e.ZZ, paramBoolean);
  }
  
  public boolean Z_Y() {
    return this.Za.Zi(this, Zk0e.ZB);
  }
  
  public void ZPn(boolean paramBoolean) {
    this.Za.ZH(this, Zk0e.ZB, paramBoolean);
  }
  
  public boolean Z_w() {
    return this.Za.Zi(this, Zk0e.Zx);
  }
  
  public void ZPs(boolean paramBoolean) {
    this.Za.ZH(this, Zk0e.Zx, paramBoolean);
  }
  
  public boolean Z_S() {
    return this.Za.Zi(this, Zk0e.ZM);
  }
  
  public void ZPH(boolean paramBoolean) {
    this.Za.ZH(this, Zk0e.ZM, paramBoolean);
  }
  
  public boolean Z_J() {
    return this.Za.Zi(this, Zk0e.ZO);
  }
  
  public void ZPh(boolean paramBoolean) {
    this.Za.ZH(this, Zk0e.ZO, paramBoolean);
  }
  
  public boolean Z_t() {
    return this.Za.Zi(this, Zk0e.Zz);
  }
  
  public void ZPM(boolean paramBoolean) {
    this.Za.ZH(this, Zk0e.Zz, paramBoolean);
  }
  
  public boolean Z_b() {
    return this.Za.Zi(this, Zk0e.Zr);
  }
  
  public void ZP4(boolean paramBoolean) {
    this.Za.ZH(this, Zk0e.Zr, paramBoolean);
  }
  
  public boolean Z_P() {
    return this.Za.Zi(this, Zk0e.Zt);
  }
  
  public void ZPq(boolean paramBoolean) {
    this.Za.ZH(this, Zk0e.Zt, paramBoolean);
  }
  
  public boolean Z_u() {
    return this.Za.Zi(this, Zk0e.Zw);
  }
  
  public void ZP7(boolean paramBoolean) {
    this.Za.ZH(this, Zk0e.Zw, paramBoolean);
  }
  
  public boolean Z_4() {
    return this.Za.Zi(this, Zk0e.ZG);
  }
  
  public void ZP5(boolean paramBoolean) {
    this.Za.ZH(this, Zk0e.ZG, paramBoolean);
  }
  
  public boolean Zv(Zeew paramZeew) {
    return ((Zsqo)this.Za.<Zsqo>ZA(this, Zk0e.Zv)).ZV(Zg0k.ZR(paramZeew));
  }
  
  public void Zc(Zeew paramZeew, boolean paramBoolean) {
    ((Zsqo)this.Za.<Zsqo>ZA(this, Zk0e.Zv)).ZC(Zg0k.ZR(paramZeew), paramBoolean);
  }
  
  public String Zbo() {
    return this.Za.ZJ(this, Zk0e.ZF);
  }
  
  public void ZP4(String paramString) {
    this.Za.Zn(this, Zk0e.ZF, paramString);
  }
  
  public boolean ZbK() {
    return this.Za.Zi(this, Zk0e.Zu);
  }
  
  public void ZPr(boolean paramBoolean) {
    this.Za.ZH(this, Zk0e.Zu, paramBoolean);
  }
  
  public boolean Zbz() {
    return this.Za.Zi(this, Zk0e.ZY);
  }
  
  public void ZPW(boolean paramBoolean) {
    this.Za.ZH(this, Zk0e.ZY, paramBoolean);
  }
  
  public boolean Zb1() {
    return this.Za.Zi(this, Zk0e.ZN);
  }
  
  public void ZP8(boolean paramBoolean) {
    this.Za.ZH(this, Zk0e.ZN, paramBoolean);
  }
  
  public boolean Z_T() {
    return this.Za.Zi(this, Zk0e.ZV);
  }
  
  public void ZPB(boolean paramBoolean) {
    this.Za.ZH(this, Zk0e.ZV, paramBoolean);
  }
  
  public int Z_Q() {
    return this.Za.Zx(this, Zk0e.Zn);
  }
  
  public void Zkh(int paramInt) {
    this.Za.ZM(this, Zk0e.Zn, paramInt);
  }
  
  public int Z_E() {
    return this.Za.Zx(this, Zk0e.ZR);
  }
  
  public void Zkm(int paramInt) {
    this.Za.ZM(this, Zk0e.ZR, paramInt);
  }
  
  public boolean Z_g() {
    return this.Za.Zi(this, Zk0e.Zf);
  }
  
  public void ZPc(boolean paramBoolean) {
    this.Za.ZH(this, Zk0e.Zf, paramBoolean);
  }
  
  public int Z_l() {
    return this.Za.Zx(this, Zk0e.ZX);
  }
  
  public String Z_W() {
    boolean bool = Zsju.ZGq();
    Zrb5 zrb5 = this.Za.<Zrb5>ZJ(this, Zk0e.Zk);
    String str = (zrb5 == null) ? "" : zrb5.ZJ();
    if (Zbqc.Zwu() == null)
      Zsju.ZaA(!bool); 
    return str.isEmpty() ? a : str;
  }
  
  public void ZiY(String paramString) {
    Zrb5 zrb5 = this.Za.<Zrb5>ZJ(this, Zk0e.Zk);
    if (zrb5 == null) {
      zrb5 = this.Za.<Zrb5>ZH(new Zrjk());
      this.Za.Zq(this, Zk0e.Zk, zrb5);
    } 
    zrb5.Ze(paramString);
  }
  
  public Zzca Z_D() {
    byte b = this.Za.ZL(this, Zk0e.ZA);
    return Zzca.Zy(b);
  }
  
  public void Zr(Zzca paramZzca) {
    byte b = (paramZzca == null) ? Zzca.SETTINGS.ZY() : paramZzca.ZY();
    this.Za.Zc(this, Zk0e.ZA, b);
  }
  
  public Zeu4<Zgzp> ZF() {
    return Zgzp.ZF;
  }
  
  static {
    // Byte code:
    //   0: bipush #29
    //   2: ldc '>+dM|8<e]5'
    //   4: iconst_m1
    //   5: goto -> 14
    //   8: putstatic burp/Zxhy.a : Ljava/lang/String;
    //   11: goto -> 154
    //   14: dup_x2
    //   15: pop
    //   16: invokevirtual toCharArray : ()[C
    //   19: dup_x1
    //   20: arraylength
    //   21: dup_x2
    //   22: pop
    //   23: iconst_0
    //   24: istore_0
    //   25: dup2_x1
    //   26: pop2
    //   27: dup_x2
    //   28: iconst_1
    //   29: if_icmpgt -> 128
    //   32: dup2
    //   33: swap
    //   34: iload_0
    //   35: dup2_x1
    //   36: caload
    //   37: swap
    //   38: iload_0
    //   39: bipush #7
    //   41: irem
    //   42: tableswitch default -> 110, 0 -> 80, 1 -> 85, 2 -> 90, 3 -> 95, 4 -> 100, 5 -> 105
    //   80: bipush #81
    //   82: goto -> 112
    //   85: bipush #83
    //   87: goto -> 112
    //   90: bipush #13
    //   92: goto -> 112
    //   95: bipush #37
    //   97: goto -> 112
    //   100: bipush #19
    //   102: goto -> 112
    //   105: bipush #108
    //   107: goto -> 112
    //   110: bipush #43
    //   112: ixor
    //   113: ixor
    //   114: i2c
    //   115: castore
    //   116: iinc #0, 1
    //   119: dup
    //   120: ifne -> 128
    //   123: dup2
    //   124: dup_x1
    //   125: goto -> 35
    //   128: dup2_x1
    //   129: pop2
    //   130: dup_x2
    //   131: iload_0
    //   132: if_icmpgt -> 32
    //   135: pop
    //   136: new java/lang/String
    //   139: dup_x1
    //   140: swap
    //   141: invokespecial <init> : ([C)V
    //   144: invokevirtual intern : ()Ljava/lang/String;
    //   147: swap
    //   148: pop
    //   149: swap
    //   150: pop
    //   151: goto -> 8
    //   154: return
  }
}


/* Location:              C:\Program Files\BurpSuitePro\burpsuite_pro.jar!\burp\Zxhy.class
 * Java compiler version: 21 (65.0)
 * JD-Core Version:       1.1.3
 */