package burp;

import java.math.BigInteger;

class Zxjw extends ClassLoader {
  static String Zv;
  
  static Object ZU;
  
  private static final String[] a;
  
  private static final String[] b;
  
  static void ZX(Object[] paramArrayOfObject, Object paramObject) throws Throwable {}
  
  static void ZK(Object paramObject) {
    Ze_b.ZX = a(667, -5283);
    Ze_b.Zp = new BigInteger(a(658, -14363));
    boolean bool = Zt2e.ZN();
    try {
      try {
        if (Zdm.ZJ.charAt(Math.abs(((BigInteger)Zct.ZW).intValue() % 32)) > Zb29.Zf.charAt(Math.abs(((BigInteger)Zgwh.Zl).intValue() % 32))) {
          try {
            Zeoa.ZS(Class.forName(a(666, -8269)));
            if (!bool)
              Zr4k.Zt(Class.forName(a(663, -20726))); 
          } catch (Throwable throwable) {
            throw a(null);
          } 
          return;
        } 
      } catch (Throwable throwable) {
        throw a(null);
      } 
      Zr4k.Zt(Class.forName(a(663, -20726)));
    } catch (Throwable throwable) {}
  }
  
  static boolean Zj(Object[] paramArrayOfObject, Object paramObject) throws Throwable {
    // Byte code:
    //   0: invokestatic ZK : ()Z
    //   3: istore_2
    //   4: getstatic burp/Zgds.Z_ : Ljava/lang/Object;
    //   7: checkcast java/math/BigInteger
    //   10: getstatic burp/Zer.Zk : Ljava/lang/Object;
    //   13: checkcast java/math/BigInteger
    //   16: invokevirtual add : (Ljava/math/BigInteger;)Ljava/math/BigInteger;
    //   19: putstatic burp/Zxee.Zj : Ljava/lang/Object;
    //   22: getstatic burp/Zct.ZW : Ljava/lang/Object;
    //   25: checkcast java/math/BigInteger
    //   28: invokevirtual toByteArray : ()[B
    //   31: astore_3
    //   32: new java/lang/StringBuilder
    //   35: dup
    //   36: invokespecial <init> : ()V
    //   39: astore #5
    //   41: aload #5
    //   43: sipush #669
    //   46: sipush #-27043
    //   49: invokestatic a : (II)Ljava/lang/String;
    //   52: invokevirtual append : (Ljava/lang/String;)Ljava/lang/StringBuilder;
    //   55: pop
    //   56: aload_3
    //   57: astore #6
    //   59: aload #6
    //   61: arraylength
    //   62: istore #7
    //   64: iconst_0
    //   65: istore #8
    //   67: iload #8
    //   69: iload #7
    //   71: if_icmpge -> 97
    //   74: aload #6
    //   76: iload #8
    //   78: baload
    //   79: istore #9
    //   81: aload #5
    //   83: iload #9
    //   85: i2c
    //   86: invokevirtual append : (C)Ljava/lang/StringBuilder;
    //   89: pop
    //   90: iinc #8, 1
    //   93: iload_2
    //   94: ifeq -> 67
    //   97: aload #5
    //   99: sipush #659
    //   102: sipush #12361
    //   105: invokestatic a : (II)Ljava/lang/String;
    //   108: ldc ''
    //   110: invokestatic getProperty : (Ljava/lang/String;Ljava/lang/String;)Ljava/lang/String;
    //   113: invokevirtual toLowerCase : ()Ljava/lang/String;
    //   116: invokevirtual append : (Ljava/lang/String;)Ljava/lang/StringBuilder;
    //   119: pop
    //   120: aload #5
    //   122: sipush #670
    //   125: sipush #-9208
    //   128: invokestatic a : (II)Ljava/lang/String;
    //   131: ldc ''
    //   133: invokestatic getProperty : (Ljava/lang/String;Ljava/lang/String;)Ljava/lang/String;
    //   136: invokevirtual toLowerCase : ()Ljava/lang/String;
    //   139: invokevirtual append : (Ljava/lang/String;)Ljava/lang/StringBuilder;
    //   142: pop
    //   143: aload #5
    //   145: invokevirtual toString : ()Ljava/lang/String;
    //   148: invokevirtual getBytes : ()[B
    //   151: astore #4
    //   153: aload #4
    //   155: astore_3
    //   156: aload_3
    //   157: arraylength
    //   158: bipush #8
    //   160: iadd
    //   161: bipush #6
    //   163: ishr
    //   164: iconst_1
    //   165: iadd
    //   166: bipush #16
    //   168: imul
    //   169: newarray int
    //   171: astore #5
    //   173: iconst_0
    //   174: istore #6
    //   176: iload #6
    //   178: aload_3
    //   179: arraylength
    //   180: if_icmpge -> 223
    //   183: aload_3
    //   184: iload #6
    //   186: baload
    //   187: sipush #255
    //   190: iand
    //   191: istore #7
    //   193: aload #5
    //   195: iload #6
    //   197: iconst_2
    //   198: ishr
    //   199: dup2
    //   200: iaload
    //   201: iload #7
    //   203: bipush #24
    //   205: iload #6
    //   207: iconst_4
    //   208: irem
    //   209: bipush #8
    //   211: imul
    //   212: isub
    //   213: ishl
    //   214: ior
    //   215: iastore
    //   216: iinc #6, 1
    //   219: iload_2
    //   220: ifeq -> 176
    //   223: aload #5
    //   225: iload #6
    //   227: iconst_2
    //   228: ishr
    //   229: dup2
    //   230: iaload
    //   231: sipush #128
    //   234: bipush #24
    //   236: iload #6
    //   238: iconst_4
    //   239: irem
    //   240: bipush #8
    //   242: imul
    //   243: isub
    //   244: ishl
    //   245: ior
    //   246: iastore
    //   247: aload #5
    //   249: aload #5
    //   251: arraylength
    //   252: iconst_1
    //   253: isub
    //   254: aload_3
    //   255: arraylength
    //   256: bipush #8
    //   258: imul
    //   259: iastore
    //   260: bipush #80
    //   262: newarray int
    //   264: astore #7
    //   266: ldc 1732584193
    //   268: istore #8
    //   270: ldc -271733879
    //   272: istore #9
    //   274: ldc -1732584194
    //   276: istore #10
    //   278: ldc 271733878
    //   280: istore #11
    //   282: ldc -1009589776
    //   284: istore #12
    //   286: iconst_0
    //   287: istore #6
    //   289: iload #6
    //   291: aload #5
    //   293: arraylength
    //   294: if_icmpge -> 616
    //   297: iload #8
    //   299: istore #13
    //   301: iload #9
    //   303: istore #14
    //   305: iload #10
    //   307: istore #15
    //   309: iload #11
    //   311: istore #16
    //   313: iload #12
    //   315: istore #17
    //   317: iconst_0
    //   318: istore #18
    //   320: iload #18
    //   322: bipush #80
    //   324: if_icmpge -> 574
    //   327: iload #18
    //   329: bipush #16
    //   331: if_icmpge -> 358
    //   334: aload #7
    //   336: iload #18
    //   338: aload #5
    //   340: iload #6
    //   342: iload #18
    //   344: iadd
    //   345: iaload
    //   346: iastore
    //   347: iload_2
    //   348: ifeq -> 413
    //   351: goto -> 358
    //   354: invokestatic a : (Ljava/lang/Throwable;)Ljava/lang/Throwable;
    //   357: athrow
    //   358: aload #7
    //   360: iload #18
    //   362: iconst_3
    //   363: isub
    //   364: iaload
    //   365: aload #7
    //   367: iload #18
    //   369: bipush #8
    //   371: isub
    //   372: iaload
    //   373: ixor
    //   374: aload #7
    //   376: iload #18
    //   378: bipush #14
    //   380: isub
    //   381: iaload
    //   382: ixor
    //   383: aload #7
    //   385: iload #18
    //   387: bipush #16
    //   389: isub
    //   390: iaload
    //   391: ixor
    //   392: istore #19
    //   394: iload #19
    //   396: iconst_1
    //   397: ishl
    //   398: iload #19
    //   400: bipush #31
    //   402: iushr
    //   403: ior
    //   404: istore #20
    //   406: aload #7
    //   408: iload #18
    //   410: iload #20
    //   412: iastore
    //   413: iload #8
    //   415: iconst_5
    //   416: ishl
    //   417: iload #8
    //   419: bipush #27
    //   421: iushr
    //   422: ior
    //   423: istore #19
    //   425: iload #19
    //   427: iload #12
    //   429: iadd
    //   430: aload #7
    //   432: iload #18
    //   434: iaload
    //   435: iadd
    //   436: iload #18
    //   438: bipush #20
    //   440: if_icmpge -> 466
    //   443: ldc 1518500249
    //   445: iload #9
    //   447: iload #10
    //   449: iand
    //   450: iload #9
    //   452: iconst_m1
    //   453: ixor
    //   454: iload #11
    //   456: iand
    //   457: ior
    //   458: iadd
    //   459: goto -> 536
    //   462: invokestatic a : (Ljava/lang/Throwable;)Ljava/lang/Throwable;
    //   465: athrow
    //   466: iload #18
    //   468: bipush #40
    //   470: if_icmpge -> 491
    //   473: ldc 1859775393
    //   475: iload #9
    //   477: iload #10
    //   479: ixor
    //   480: iload #11
    //   482: ixor
    //   483: iadd
    //   484: goto -> 536
    //   487: invokestatic a : (Ljava/lang/Throwable;)Ljava/lang/Throwable;
    //   490: athrow
    //   491: iload #18
    //   493: bipush #60
    //   495: if_icmpge -> 525
    //   498: ldc -1894007588
    //   500: iload #9
    //   502: iload #10
    //   504: iand
    //   505: iload #9
    //   507: iload #11
    //   509: iand
    //   510: ior
    //   511: iload #10
    //   513: iload #11
    //   515: iand
    //   516: ior
    //   517: iadd
    //   518: goto -> 536
    //   521: invokestatic a : (Ljava/lang/Throwable;)Ljava/lang/Throwable;
    //   524: athrow
    //   525: ldc -899497514
    //   527: iload #9
    //   529: iload #10
    //   531: ixor
    //   532: iload #11
    //   534: ixor
    //   535: iadd
    //   536: iadd
    //   537: istore #20
    //   539: iload #11
    //   541: istore #12
    //   543: iload #10
    //   545: istore #11
    //   547: iload #9
    //   549: bipush #30
    //   551: ishl
    //   552: iload #9
    //   554: iconst_2
    //   555: iushr
    //   556: ior
    //   557: istore #10
    //   559: iload #8
    //   561: istore #9
    //   563: iload #20
    //   565: istore #8
    //   567: iinc #18, 1
    //   570: iload_2
    //   571: ifeq -> 320
    //   574: iload #8
    //   576: iload #13
    //   578: iadd
    //   579: istore #8
    //   581: iload #9
    //   583: iload #14
    //   585: iadd
    //   586: istore #9
    //   588: iload #10
    //   590: iload #15
    //   592: iadd
    //   593: istore #10
    //   595: iload #11
    //   597: iload #16
    //   599: iadd
    //   600: istore #11
    //   602: iload #12
    //   604: iload #17
    //   606: iadd
    //   607: istore #12
    //   609: iinc #6, 16
    //   612: iload_2
    //   613: ifeq -> 289
    //   616: iconst_5
    //   617: newarray int
    //   619: dup
    //   620: iconst_0
    //   621: iload #8
    //   623: iastore
    //   624: dup
    //   625: iconst_1
    //   626: iload #9
    //   628: iastore
    //   629: dup
    //   630: iconst_2
    //   631: iload #10
    //   633: iastore
    //   634: dup
    //   635: iconst_3
    //   636: iload #11
    //   638: iastore
    //   639: dup
    //   640: iconst_4
    //   641: iload #12
    //   643: iastore
    //   644: astore #13
    //   646: bipush #20
    //   648: newarray byte
    //   650: astore #14
    //   652: iconst_0
    //   653: istore #15
    //   655: iload #15
    //   657: bipush #20
    //   659: if_icmpge -> 700
    //   662: aload #13
    //   664: iload #15
    //   666: iconst_4
    //   667: idiv
    //   668: iaload
    //   669: istore #16
    //   671: iconst_3
    //   672: iload #15
    //   674: iconst_4
    //   675: irem
    //   676: isub
    //   677: bipush #8
    //   679: imul
    //   680: istore #17
    //   682: aload #14
    //   684: iload #15
    //   686: iload #16
    //   688: iload #17
    //   690: iushr
    //   691: i2b
    //   692: bastore
    //   693: iinc #15, 1
    //   696: iload_2
    //   697: ifeq -> 655
    //   700: aload #14
    //   702: astore #4
    //   704: new java/io/ByteArrayOutputStream
    //   707: dup
    //   708: invokespecial <init> : ()V
    //   711: astore_3
    //   712: getstatic burp/Zttq.ZO : Ljava/lang/String;
    //   715: astore #4
    //   717: iconst_0
    //   718: istore #5
    //   720: iload #5
    //   722: aload #4
    //   724: invokevirtual length : ()I
    //   727: if_icmpge -> 757
    //   730: aload_3
    //   731: aload #4
    //   733: iload #5
    //   735: iload #5
    //   737: iconst_2
    //   738: iadd
    //   739: invokevirtual substring : (II)Ljava/lang/String;
    //   742: bipush #16
    //   744: invokestatic parseInt : (Ljava/lang/String;I)I
    //   747: invokevirtual write : (I)V
    //   750: iinc #5, 2
    //   753: iload_2
    //   754: ifeq -> 720
    //   757: aload_3
    //   758: invokevirtual toByteArray : ()[B
    //   761: astore #5
    //   763: getstatic burp/Zl3l.Zv : Ljava/lang/Object;
    //   766: checkcast java/math/BigInteger
    //   769: invokevirtual toByteArray : ()[B
    //   772: astore #6
    //   774: sipush #256
    //   777: newarray byte
    //   779: astore #8
    //   781: sipush #256
    //   784: newarray int
    //   786: astore #9
    //   788: sipush #256
    //   791: newarray int
    //   793: astore #10
    //   795: sipush #256
    //   798: newarray int
    //   800: astore #11
    //   802: sipush #256
    //   805: newarray int
    //   807: astore #12
    //   809: bipush #10
    //   811: newarray int
    //   813: astore #13
    //   815: sipush #283
    //   818: istore #14
    //   820: iconst_0
    //   821: istore #16
    //   823: iload #16
    //   825: sipush #256
    //   828: if_icmpge -> 1062
    //   831: sipush #671
    //   834: sipush #-1360
    //   837: invokestatic a : (II)Ljava/lang/String;
    //   840: iload #16
    //   842: iconst_1
    //   843: iushr
    //   844: invokevirtual charAt : (I)C
    //   847: istore #25
    //   849: iload #16
    //   851: iconst_1
    //   852: iand
    //   853: ifne -> 868
    //   856: iload #25
    //   858: bipush #8
    //   860: iushr
    //   861: goto -> 870
    //   864: invokestatic a : (Ljava/lang/Throwable;)Ljava/lang/Throwable;
    //   867: athrow
    //   868: iload #25
    //   870: i2b
    //   871: sipush #255
    //   874: iand
    //   875: istore #15
    //   877: iload #16
    //   879: iconst_1
    //   880: ishl
    //   881: istore #17
    //   883: iload #17
    //   885: sipush #256
    //   888: if_icmplt -> 898
    //   891: iload #17
    //   893: iload #14
    //   895: ixor
    //   896: istore #17
    //   898: iload #17
    //   900: iconst_1
    //   901: ishl
    //   902: istore #18
    //   904: iload #18
    //   906: sipush #256
    //   909: if_icmplt -> 919
    //   912: iload #18
    //   914: iload #14
    //   916: ixor
    //   917: istore #18
    //   919: iload #18
    //   921: iconst_1
    //   922: ishl
    //   923: istore #19
    //   925: iload #19
    //   927: sipush #256
    //   930: if_icmplt -> 940
    //   933: iload #19
    //   935: iload #14
    //   937: ixor
    //   938: istore #19
    //   940: iload #19
    //   942: iload #16
    //   944: ixor
    //   945: istore #20
    //   947: iload #20
    //   949: iload #17
    //   951: ixor
    //   952: istore #21
    //   954: iload #20
    //   956: iload #18
    //   958: ixor
    //   959: istore #22
    //   961: iload #19
    //   963: iload #18
    //   965: ixor
    //   966: iload #17
    //   968: ixor
    //   969: istore #23
    //   971: aload #8
    //   973: iload #16
    //   975: iload #15
    //   977: i2b
    //   978: bastore
    //   979: aload #9
    //   981: iload #15
    //   983: iload #23
    //   985: bipush #24
    //   987: ishl
    //   988: iload #20
    //   990: bipush #16
    //   992: ishl
    //   993: ior
    //   994: iload #22
    //   996: bipush #8
    //   998: ishl
    //   999: ior
    //   1000: iload #21
    //   1002: ior
    //   1003: dup
    //   1004: istore #24
    //   1006: iastore
    //   1007: aload #10
    //   1009: iload #15
    //   1011: iload #24
    //   1013: bipush #8
    //   1015: iushr
    //   1016: iload #24
    //   1018: bipush #24
    //   1020: ishl
    //   1021: ior
    //   1022: iastore
    //   1023: aload #11
    //   1025: iload #15
    //   1027: iload #24
    //   1029: bipush #16
    //   1031: iushr
    //   1032: iload #24
    //   1034: bipush #16
    //   1036: ishl
    //   1037: ior
    //   1038: iastore
    //   1039: aload #12
    //   1041: iload #15
    //   1043: iload #24
    //   1045: bipush #24
    //   1047: iushr
    //   1048: iload #24
    //   1050: bipush #8
    //   1052: ishl
    //   1053: ior
    //   1054: iastore
    //   1055: iinc #16, 1
    //   1058: iload_2
    //   1059: ifeq -> 823
    //   1062: iconst_1
    //   1063: istore #25
    //   1065: aload #13
    //   1067: iconst_0
    //   1068: iload #25
    //   1070: bipush #24
    //   1072: ishl
    //   1073: iastore
    //   1074: iconst_1
    //   1075: istore #26
    //   1077: iload #26
    //   1079: bipush #10
    //   1081: if_icmpge -> 1122
    //   1084: iload #25
    //   1086: iconst_1
    //   1087: ishl
    //   1088: istore #25
    //   1090: iload #25
    //   1092: sipush #256
    //   1095: if_icmplt -> 1105
    //   1098: iload #25
    //   1100: iload #14
    //   1102: ixor
    //   1103: istore #25
    //   1105: aload #13
    //   1107: iload #26
    //   1109: iload #25
    //   1111: bipush #24
    //   1113: ishl
    //   1114: iastore
    //   1115: iinc #26, 1
    //   1118: iload_2
    //   1119: ifeq -> 1077
    //   1122: iconst_4
    //   1123: istore #26
    //   1125: iload #26
    //   1127: bipush #6
    //   1129: iadd
    //   1130: istore #27
    //   1132: iconst_4
    //   1133: iload #27
    //   1135: iconst_1
    //   1136: iadd
    //   1137: imul
    //   1138: istore #28
    //   1140: iload #28
    //   1142: newarray int
    //   1144: astore #29
    //   1146: iload #28
    //   1148: newarray int
    //   1150: astore #30
    //   1152: iconst_0
    //   1153: istore #25
    //   1155: iconst_0
    //   1156: istore #32
    //   1158: iconst_0
    //   1159: istore #33
    //   1161: iload #32
    //   1163: iload #26
    //   1165: if_icmpge -> 1233
    //   1168: aload #29
    //   1170: iload #32
    //   1172: aload #5
    //   1174: iload #33
    //   1176: baload
    //   1177: bipush #24
    //   1179: ishl
    //   1180: aload #5
    //   1182: iload #33
    //   1184: iconst_1
    //   1185: iadd
    //   1186: baload
    //   1187: sipush #255
    //   1190: iand
    //   1191: bipush #16
    //   1193: ishl
    //   1194: ior
    //   1195: aload #5
    //   1197: iload #33
    //   1199: iconst_2
    //   1200: iadd
    //   1201: baload
    //   1202: sipush #255
    //   1205: iand
    //   1206: bipush #8
    //   1208: ishl
    //   1209: ior
    //   1210: aload #5
    //   1212: iload #33
    //   1214: iconst_3
    //   1215: iadd
    //   1216: baload
    //   1217: sipush #255
    //   1220: iand
    //   1221: ior
    //   1222: iastore
    //   1223: iinc #32, 1
    //   1226: iinc #33, 4
    //   1229: iload_2
    //   1230: ifeq -> 1161
    //   1233: iload #26
    //   1235: istore #32
    //   1237: iconst_0
    //   1238: istore #33
    //   1240: iload #32
    //   1242: iload #28
    //   1244: if_icmpge -> 1371
    //   1247: aload #29
    //   1249: iload #32
    //   1251: iconst_1
    //   1252: isub
    //   1253: iaload
    //   1254: istore #31
    //   1256: iload #33
    //   1258: ifne -> 1345
    //   1261: iload #26
    //   1263: istore #33
    //   1265: aload #8
    //   1267: iload #31
    //   1269: bipush #16
    //   1271: iushr
    //   1272: sipush #255
    //   1275: iand
    //   1276: baload
    //   1277: bipush #24
    //   1279: ishl
    //   1280: aload #8
    //   1282: iload #31
    //   1284: bipush #8
    //   1286: iushr
    //   1287: sipush #255
    //   1290: iand
    //   1291: baload
    //   1292: sipush #255
    //   1295: iand
    //   1296: bipush #16
    //   1298: ishl
    //   1299: ior
    //   1300: aload #8
    //   1302: iload #31
    //   1304: sipush #255
    //   1307: iand
    //   1308: baload
    //   1309: sipush #255
    //   1312: iand
    //   1313: bipush #8
    //   1315: ishl
    //   1316: ior
    //   1317: aload #8
    //   1319: iload #31
    //   1321: bipush #24
    //   1323: iushr
    //   1324: baload
    //   1325: sipush #255
    //   1328: iand
    //   1329: ior
    //   1330: istore #31
    //   1332: iload #31
    //   1334: aload #13
    //   1336: iload #25
    //   1338: iinc #25, 1
    //   1341: iaload
    //   1342: ixor
    //   1343: istore #31
    //   1345: aload #29
    //   1347: iload #32
    //   1349: aload #29
    //   1351: iload #32
    //   1353: iload #26
    //   1355: isub
    //   1356: iaload
    //   1357: iload #31
    //   1359: ixor
    //   1360: iastore
    //   1361: iinc #32, 1
    //   1364: iinc #33, -1
    //   1367: iload_2
    //   1368: ifeq -> 1240
    //   1371: iconst_0
    //   1372: istore #32
    //   1374: iconst_4
    //   1375: iload #27
    //   1377: imul
    //   1378: istore #33
    //   1380: aload #30
    //   1382: iload #32
    //   1384: aload #29
    //   1386: iload #33
    //   1388: iaload
    //   1389: iastore
    //   1390: aload #30
    //   1392: iload #32
    //   1394: iconst_1
    //   1395: iadd
    //   1396: aload #29
    //   1398: iload #33
    //   1400: iconst_1
    //   1401: iadd
    //   1402: iaload
    //   1403: iastore
    //   1404: aload #30
    //   1406: iload #32
    //   1408: iconst_2
    //   1409: iadd
    //   1410: aload #29
    //   1412: iload #33
    //   1414: iconst_2
    //   1415: iadd
    //   1416: iaload
    //   1417: iastore
    //   1418: aload #30
    //   1420: iload #32
    //   1422: iconst_3
    //   1423: iadd
    //   1424: aload #29
    //   1426: iload #33
    //   1428: iconst_3
    //   1429: iadd
    //   1430: iaload
    //   1431: iastore
    //   1432: iinc #32, 4
    //   1435: iinc #33, -4
    //   1438: iconst_1
    //   1439: istore #35
    //   1441: iload #35
    //   1443: iload #27
    //   1445: if_icmpge -> 1809
    //   1448: aload #29
    //   1450: iload #33
    //   1452: iaload
    //   1453: istore #34
    //   1455: aload #30
    //   1457: iload #32
    //   1459: aload #9
    //   1461: aload #8
    //   1463: iload #34
    //   1465: bipush #24
    //   1467: iushr
    //   1468: baload
    //   1469: sipush #255
    //   1472: iand
    //   1473: iaload
    //   1474: aload #10
    //   1476: aload #8
    //   1478: iload #34
    //   1480: bipush #16
    //   1482: iushr
    //   1483: sipush #255
    //   1486: iand
    //   1487: baload
    //   1488: sipush #255
    //   1491: iand
    //   1492: iaload
    //   1493: ixor
    //   1494: aload #11
    //   1496: aload #8
    //   1498: iload #34
    //   1500: bipush #8
    //   1502: iushr
    //   1503: sipush #255
    //   1506: iand
    //   1507: baload
    //   1508: sipush #255
    //   1511: iand
    //   1512: iaload
    //   1513: ixor
    //   1514: aload #12
    //   1516: aload #8
    //   1518: iload #34
    //   1520: sipush #255
    //   1523: iand
    //   1524: baload
    //   1525: sipush #255
    //   1528: iand
    //   1529: iaload
    //   1530: ixor
    //   1531: iastore
    //   1532: aload #29
    //   1534: iload #33
    //   1536: iconst_1
    //   1537: iadd
    //   1538: iaload
    //   1539: istore #34
    //   1541: aload #30
    //   1543: iload #32
    //   1545: iconst_1
    //   1546: iadd
    //   1547: aload #9
    //   1549: aload #8
    //   1551: iload #34
    //   1553: bipush #24
    //   1555: iushr
    //   1556: baload
    //   1557: sipush #255
    //   1560: iand
    //   1561: iaload
    //   1562: aload #10
    //   1564: aload #8
    //   1566: iload #34
    //   1568: bipush #16
    //   1570: iushr
    //   1571: sipush #255
    //   1574: iand
    //   1575: baload
    //   1576: sipush #255
    //   1579: iand
    //   1580: iaload
    //   1581: ixor
    //   1582: aload #11
    //   1584: aload #8
    //   1586: iload #34
    //   1588: bipush #8
    //   1590: iushr
    //   1591: sipush #255
    //   1594: iand
    //   1595: baload
    //   1596: sipush #255
    //   1599: iand
    //   1600: iaload
    //   1601: ixor
    //   1602: aload #12
    //   1604: aload #8
    //   1606: iload #34
    //   1608: sipush #255
    //   1611: iand
    //   1612: baload
    //   1613: sipush #255
    //   1616: iand
    //   1617: iaload
    //   1618: ixor
    //   1619: iastore
    //   1620: aload #29
    //   1622: iload #33
    //   1624: iconst_2
    //   1625: iadd
    //   1626: iaload
    //   1627: istore #34
    //   1629: aload #30
    //   1631: iload #32
    //   1633: iconst_2
    //   1634: iadd
    //   1635: aload #9
    //   1637: aload #8
    //   1639: iload #34
    //   1641: bipush #24
    //   1643: iushr
    //   1644: baload
    //   1645: sipush #255
    //   1648: iand
    //   1649: iaload
    //   1650: aload #10
    //   1652: aload #8
    //   1654: iload #34
    //   1656: bipush #16
    //   1658: iushr
    //   1659: sipush #255
    //   1662: iand
    //   1663: baload
    //   1664: sipush #255
    //   1667: iand
    //   1668: iaload
    //   1669: ixor
    //   1670: aload #11
    //   1672: aload #8
    //   1674: iload #34
    //   1676: bipush #8
    //   1678: iushr
    //   1679: sipush #255
    //   1682: iand
    //   1683: baload
    //   1684: sipush #255
    //   1687: iand
    //   1688: iaload
    //   1689: ixor
    //   1690: aload #12
    //   1692: aload #8
    //   1694: iload #34
    //   1696: sipush #255
    //   1699: iand
    //   1700: baload
    //   1701: sipush #255
    //   1704: iand
    //   1705: iaload
    //   1706: ixor
    //   1707: iastore
    //   1708: aload #29
    //   1710: iload #33
    //   1712: iconst_3
    //   1713: iadd
    //   1714: iaload
    //   1715: istore #34
    //   1717: aload #30
    //   1719: iload #32
    //   1721: iconst_3
    //   1722: iadd
    //   1723: aload #9
    //   1725: aload #8
    //   1727: iload #34
    //   1729: bipush #24
    //   1731: iushr
    //   1732: baload
    //   1733: sipush #255
    //   1736: iand
    //   1737: iaload
    //   1738: aload #10
    //   1740: aload #8
    //   1742: iload #34
    //   1744: bipush #16
    //   1746: iushr
    //   1747: sipush #255
    //   1750: iand
    //   1751: baload
    //   1752: sipush #255
    //   1755: iand
    //   1756: iaload
    //   1757: ixor
    //   1758: aload #11
    //   1760: aload #8
    //   1762: iload #34
    //   1764: bipush #8
    //   1766: iushr
    //   1767: sipush #255
    //   1770: iand
    //   1771: baload
    //   1772: sipush #255
    //   1775: iand
    //   1776: iaload
    //   1777: ixor
    //   1778: aload #12
    //   1780: aload #8
    //   1782: iload #34
    //   1784: sipush #255
    //   1787: iand
    //   1788: baload
    //   1789: sipush #255
    //   1792: iand
    //   1793: iaload
    //   1794: ixor
    //   1795: iastore
    //   1796: iinc #32, 4
    //   1799: iinc #33, -4
    //   1802: iinc #35, 1
    //   1805: iload_2
    //   1806: ifeq -> 1441
    //   1809: aload #30
    //   1811: iload #32
    //   1813: aload #29
    //   1815: iload #33
    //   1817: iaload
    //   1818: iastore
    //   1819: aload #30
    //   1821: iload #32
    //   1823: iconst_1
    //   1824: iadd
    //   1825: aload #29
    //   1827: iload #33
    //   1829: iconst_1
    //   1830: iadd
    //   1831: iaload
    //   1832: iastore
    //   1833: aload #30
    //   1835: iload #32
    //   1837: iconst_2
    //   1838: iadd
    //   1839: aload #29
    //   1841: iload #33
    //   1843: iconst_2
    //   1844: iadd
    //   1845: iaload
    //   1846: iastore
    //   1847: aload #30
    //   1849: iload #32
    //   1851: iconst_3
    //   1852: iadd
    //   1853: aload #29
    //   1855: iload #33
    //   1857: iconst_3
    //   1858: iadd
    //   1859: iaload
    //   1860: iastore
    //   1861: iconst_0
    //   1862: newarray byte
    //   1864: astore #35
    //   1866: aload #6
    //   1868: arraylength
    //   1869: bipush #16
    //   1871: irem
    //   1872: ifeq -> 1896
    //   1875: new java/lang/Exception
    //   1878: dup
    //   1879: sipush #668
    //   1882: sipush #10479
    //   1885: invokestatic a : (II)Ljava/lang/String;
    //   1888: invokespecial <init> : (Ljava/lang/String;)V
    //   1891: athrow
    //   1892: invokestatic a : (Ljava/lang/Throwable;)Ljava/lang/Throwable;
    //   1895: athrow
    //   1896: bipush #10
    //   1898: istore #36
    //   1900: sipush #665
    //   1903: sipush #256
    //   1906: newarray byte
    //   1908: astore #37
    //   1910: sipush #-22433
    //   1913: sipush #256
    //   1916: newarray int
    //   1918: astore #38
    //   1920: sipush #256
    //   1923: newarray int
    //   1925: astore #39
    //   1927: sipush #256
    //   1930: newarray int
    //   1932: astore #40
    //   1934: sipush #256
    //   1937: newarray int
    //   1939: astore #41
    //   1941: sipush #283
    //   1944: istore #14
    //   1946: invokestatic a : (II)Ljava/lang/String;
    //   1949: astore #42
    //   1951: iconst_0
    //   1952: istore #16
    //   1954: iload #16
    //   1956: sipush #256
    //   1959: if_icmpge -> 2186
    //   1962: aload #42
    //   1964: iload #16
    //   1966: iconst_1
    //   1967: iushr
    //   1968: invokevirtual charAt : (I)C
    //   1971: istore #43
    //   1973: iload #16
    //   1975: iconst_1
    //   1976: iand
    //   1977: ifne -> 1992
    //   1980: iload #43
    //   1982: bipush #8
    //   1984: iushr
    //   1985: goto -> 1994
    //   1988: invokestatic a : (Ljava/lang/Throwable;)Ljava/lang/Throwable;
    //   1991: athrow
    //   1992: iload #43
    //   1994: i2b
    //   1995: sipush #255
    //   1998: iand
    //   1999: istore #15
    //   2001: iload #16
    //   2003: iconst_1
    //   2004: ishl
    //   2005: istore #17
    //   2007: iload #17
    //   2009: sipush #256
    //   2012: if_icmplt -> 2022
    //   2015: iload #17
    //   2017: iload #14
    //   2019: ixor
    //   2020: istore #17
    //   2022: iload #17
    //   2024: iconst_1
    //   2025: ishl
    //   2026: istore #18
    //   2028: iload #18
    //   2030: sipush #256
    //   2033: if_icmplt -> 2043
    //   2036: iload #18
    //   2038: iload #14
    //   2040: ixor
    //   2041: istore #18
    //   2043: iload #18
    //   2045: iconst_1
    //   2046: ishl
    //   2047: istore #19
    //   2049: iload #19
    //   2051: sipush #256
    //   2054: if_icmplt -> 2064
    //   2057: iload #19
    //   2059: iload #14
    //   2061: ixor
    //   2062: istore #19
    //   2064: iload #19
    //   2066: iload #16
    //   2068: ixor
    //   2069: istore #20
    //   2071: iload #20
    //   2073: iload #17
    //   2075: ixor
    //   2076: istore #21
    //   2078: iload #20
    //   2080: iload #18
    //   2082: ixor
    //   2083: istore #22
    //   2085: iload #19
    //   2087: iload #18
    //   2089: ixor
    //   2090: iload #17
    //   2092: ixor
    //   2093: istore #23
    //   2095: aload #37
    //   2097: iload #15
    //   2099: iload #16
    //   2101: i2b
    //   2102: bastore
    //   2103: aload #38
    //   2105: iload #15
    //   2107: iload #23
    //   2109: bipush #24
    //   2111: ishl
    //   2112: iload #20
    //   2114: bipush #16
    //   2116: ishl
    //   2117: ior
    //   2118: iload #22
    //   2120: bipush #8
    //   2122: ishl
    //   2123: ior
    //   2124: iload #21
    //   2126: ior
    //   2127: dup
    //   2128: istore #24
    //   2130: iastore
    //   2131: aload #39
    //   2133: iload #15
    //   2135: iload #24
    //   2137: bipush #8
    //   2139: iushr
    //   2140: iload #24
    //   2142: bipush #24
    //   2144: ishl
    //   2145: ior
    //   2146: iastore
    //   2147: aload #40
    //   2149: iload #15
    //   2151: iload #24
    //   2153: bipush #16
    //   2155: iushr
    //   2156: iload #24
    //   2158: bipush #16
    //   2160: ishl
    //   2161: ior
    //   2162: iastore
    //   2163: aload #41
    //   2165: iload #15
    //   2167: iload #24
    //   2169: bipush #24
    //   2171: iushr
    //   2172: iload #24
    //   2174: bipush #8
    //   2176: ishl
    //   2177: ior
    //   2178: iastore
    //   2179: iinc #16, 1
    //   2182: iload_2
    //   2183: ifeq -> 1954
    //   2186: aload #6
    //   2188: arraylength
    //   2189: newarray byte
    //   2191: astore #43
    //   2193: iconst_0
    //   2194: istore #44
    //   2196: iload #44
    //   2198: aload #6
    //   2200: arraylength
    //   2201: bipush #16
    //   2203: idiv
    //   2204: if_icmpge -> 3118
    //   2207: bipush #16
    //   2209: newarray byte
    //   2211: astore #45
    //   2213: bipush #16
    //   2215: newarray byte
    //   2217: astore #46
    //   2219: iconst_0
    //   2220: istore #47
    //   2222: iload #47
    //   2224: bipush #16
    //   2226: if_icmpge -> 2252
    //   2229: aload #45
    //   2231: iload #47
    //   2233: aload #6
    //   2235: iload #47
    //   2237: iload #44
    //   2239: bipush #16
    //   2241: imul
    //   2242: iadd
    //   2243: baload
    //   2244: bastore
    //   2245: iinc #47, 1
    //   2248: iload_2
    //   2249: ifeq -> 2222
    //   2252: iconst_0
    //   2253: istore #47
    //   2255: aload #45
    //   2257: iconst_0
    //   2258: baload
    //   2259: bipush #24
    //   2261: ishl
    //   2262: aload #45
    //   2264: iconst_1
    //   2265: baload
    //   2266: sipush #255
    //   2269: iand
    //   2270: bipush #16
    //   2272: ishl
    //   2273: ior
    //   2274: aload #45
    //   2276: iconst_2
    //   2277: baload
    //   2278: sipush #255
    //   2281: iand
    //   2282: bipush #8
    //   2284: ishl
    //   2285: ior
    //   2286: aload #45
    //   2288: iconst_3
    //   2289: baload
    //   2290: sipush #255
    //   2293: iand
    //   2294: ior
    //   2295: aload #30
    //   2297: iconst_0
    //   2298: iaload
    //   2299: ixor
    //   2300: istore #49
    //   2302: aload #45
    //   2304: iconst_4
    //   2305: baload
    //   2306: bipush #24
    //   2308: ishl
    //   2309: aload #45
    //   2311: iconst_5
    //   2312: baload
    //   2313: sipush #255
    //   2316: iand
    //   2317: bipush #16
    //   2319: ishl
    //   2320: ior
    //   2321: aload #45
    //   2323: bipush #6
    //   2325: baload
    //   2326: sipush #255
    //   2329: iand
    //   2330: bipush #8
    //   2332: ishl
    //   2333: ior
    //   2334: aload #45
    //   2336: bipush #7
    //   2338: baload
    //   2339: sipush #255
    //   2342: iand
    //   2343: ior
    //   2344: aload #30
    //   2346: iconst_1
    //   2347: iaload
    //   2348: ixor
    //   2349: istore #50
    //   2351: aload #45
    //   2353: bipush #8
    //   2355: baload
    //   2356: bipush #24
    //   2358: ishl
    //   2359: aload #45
    //   2361: bipush #9
    //   2363: baload
    //   2364: sipush #255
    //   2367: iand
    //   2368: bipush #16
    //   2370: ishl
    //   2371: ior
    //   2372: aload #45
    //   2374: bipush #10
    //   2376: baload
    //   2377: sipush #255
    //   2380: iand
    //   2381: bipush #8
    //   2383: ishl
    //   2384: ior
    //   2385: aload #45
    //   2387: bipush #11
    //   2389: baload
    //   2390: sipush #255
    //   2393: iand
    //   2394: ior
    //   2395: aload #30
    //   2397: iconst_2
    //   2398: iaload
    //   2399: ixor
    //   2400: istore #51
    //   2402: aload #45
    //   2404: bipush #12
    //   2406: baload
    //   2407: bipush #24
    //   2409: ishl
    //   2410: aload #45
    //   2412: bipush #13
    //   2414: baload
    //   2415: sipush #255
    //   2418: iand
    //   2419: bipush #16
    //   2421: ishl
    //   2422: ior
    //   2423: aload #45
    //   2425: bipush #14
    //   2427: baload
    //   2428: sipush #255
    //   2431: iand
    //   2432: bipush #8
    //   2434: ishl
    //   2435: ior
    //   2436: aload #45
    //   2438: bipush #15
    //   2440: baload
    //   2441: sipush #255
    //   2444: iand
    //   2445: ior
    //   2446: aload #30
    //   2448: iconst_3
    //   2449: iaload
    //   2450: ixor
    //   2451: istore #52
    //   2453: iconst_1
    //   2454: istore #53
    //   2456: iload #53
    //   2458: iload #36
    //   2460: if_icmpge -> 2703
    //   2463: iinc #47, 4
    //   2466: aload #38
    //   2468: iload #49
    //   2470: bipush #24
    //   2472: iushr
    //   2473: iaload
    //   2474: aload #39
    //   2476: iload #52
    //   2478: bipush #16
    //   2480: iushr
    //   2481: sipush #255
    //   2484: iand
    //   2485: iaload
    //   2486: ixor
    //   2487: aload #40
    //   2489: iload #51
    //   2491: bipush #8
    //   2493: iushr
    //   2494: sipush #255
    //   2497: iand
    //   2498: iaload
    //   2499: ixor
    //   2500: aload #41
    //   2502: iload #50
    //   2504: sipush #255
    //   2507: iand
    //   2508: iaload
    //   2509: ixor
    //   2510: aload #30
    //   2512: iload #47
    //   2514: iaload
    //   2515: ixor
    //   2516: istore #54
    //   2518: aload #38
    //   2520: iload #50
    //   2522: bipush #24
    //   2524: iushr
    //   2525: iaload
    //   2526: aload #39
    //   2528: iload #49
    //   2530: bipush #16
    //   2532: iushr
    //   2533: sipush #255
    //   2536: iand
    //   2537: iaload
    //   2538: ixor
    //   2539: aload #40
    //   2541: iload #52
    //   2543: bipush #8
    //   2545: iushr
    //   2546: sipush #255
    //   2549: iand
    //   2550: iaload
    //   2551: ixor
    //   2552: aload #41
    //   2554: iload #51
    //   2556: sipush #255
    //   2559: iand
    //   2560: iaload
    //   2561: ixor
    //   2562: aload #30
    //   2564: iload #47
    //   2566: iconst_1
    //   2567: iadd
    //   2568: iaload
    //   2569: ixor
    //   2570: istore #55
    //   2572: aload #38
    //   2574: iload #51
    //   2576: bipush #24
    //   2578: iushr
    //   2579: iaload
    //   2580: aload #39
    //   2582: iload #50
    //   2584: bipush #16
    //   2586: iushr
    //   2587: sipush #255
    //   2590: iand
    //   2591: iaload
    //   2592: ixor
    //   2593: aload #40
    //   2595: iload #49
    //   2597: bipush #8
    //   2599: iushr
    //   2600: sipush #255
    //   2603: iand
    //   2604: iaload
    //   2605: ixor
    //   2606: aload #41
    //   2608: iload #52
    //   2610: sipush #255
    //   2613: iand
    //   2614: iaload
    //   2615: ixor
    //   2616: aload #30
    //   2618: iload #47
    //   2620: iconst_2
    //   2621: iadd
    //   2622: iaload
    //   2623: ixor
    //   2624: istore #56
    //   2626: aload #38
    //   2628: iload #52
    //   2630: bipush #24
    //   2632: iushr
    //   2633: iaload
    //   2634: aload #39
    //   2636: iload #51
    //   2638: bipush #16
    //   2640: iushr
    //   2641: sipush #255
    //   2644: iand
    //   2645: iaload
    //   2646: ixor
    //   2647: aload #40
    //   2649: iload #50
    //   2651: bipush #8
    //   2653: iushr
    //   2654: sipush #255
    //   2657: iand
    //   2658: iaload
    //   2659: ixor
    //   2660: aload #41
    //   2662: iload #49
    //   2664: sipush #255
    //   2667: iand
    //   2668: iaload
    //   2669: ixor
    //   2670: aload #30
    //   2672: iload #47
    //   2674: iconst_3
    //   2675: iadd
    //   2676: iaload
    //   2677: ixor
    //   2678: istore #57
    //   2680: iload #54
    //   2682: istore #49
    //   2684: iload #55
    //   2686: istore #50
    //   2688: iload #56
    //   2690: istore #51
    //   2692: iload #57
    //   2694: istore #52
    //   2696: iinc #53, 1
    //   2699: iload_2
    //   2700: ifeq -> 2456
    //   2703: iinc #47, 4
    //   2706: aload #30
    //   2708: iload #47
    //   2710: iaload
    //   2711: istore #48
    //   2713: aload #46
    //   2715: iconst_0
    //   2716: aload #37
    //   2718: iload #49
    //   2720: bipush #24
    //   2722: iushr
    //   2723: baload
    //   2724: iload #48
    //   2726: bipush #24
    //   2728: iushr
    //   2729: ixor
    //   2730: i2b
    //   2731: bastore
    //   2732: aload #46
    //   2734: iconst_1
    //   2735: aload #37
    //   2737: iload #52
    //   2739: bipush #16
    //   2741: iushr
    //   2742: sipush #255
    //   2745: iand
    //   2746: baload
    //   2747: iload #48
    //   2749: bipush #16
    //   2751: iushr
    //   2752: ixor
    //   2753: i2b
    //   2754: bastore
    //   2755: aload #46
    //   2757: iconst_2
    //   2758: aload #37
    //   2760: iload #51
    //   2762: bipush #8
    //   2764: iushr
    //   2765: sipush #255
    //   2768: iand
    //   2769: baload
    //   2770: iload #48
    //   2772: bipush #8
    //   2774: iushr
    //   2775: ixor
    //   2776: i2b
    //   2777: bastore
    //   2778: aload #46
    //   2780: iconst_3
    //   2781: aload #37
    //   2783: iload #50
    //   2785: sipush #255
    //   2788: iand
    //   2789: baload
    //   2790: iload #48
    //   2792: ixor
    //   2793: i2b
    //   2794: bastore
    //   2795: aload #30
    //   2797: iload #47
    //   2799: iconst_1
    //   2800: iadd
    //   2801: iaload
    //   2802: istore #48
    //   2804: aload #46
    //   2806: iconst_4
    //   2807: aload #37
    //   2809: iload #50
    //   2811: bipush #24
    //   2813: iushr
    //   2814: baload
    //   2815: iload #48
    //   2817: bipush #24
    //   2819: iushr
    //   2820: ixor
    //   2821: i2b
    //   2822: bastore
    //   2823: aload #46
    //   2825: iconst_5
    //   2826: aload #37
    //   2828: iload #49
    //   2830: bipush #16
    //   2832: iushr
    //   2833: sipush #255
    //   2836: iand
    //   2837: baload
    //   2838: iload #48
    //   2840: bipush #16
    //   2842: iushr
    //   2843: ixor
    //   2844: i2b
    //   2845: bastore
    //   2846: aload #46
    //   2848: bipush #6
    //   2850: aload #37
    //   2852: iload #52
    //   2854: bipush #8
    //   2856: iushr
    //   2857: sipush #255
    //   2860: iand
    //   2861: baload
    //   2862: iload #48
    //   2864: bipush #8
    //   2866: iushr
    //   2867: ixor
    //   2868: i2b
    //   2869: bastore
    //   2870: aload #46
    //   2872: bipush #7
    //   2874: aload #37
    //   2876: iload #51
    //   2878: sipush #255
    //   2881: iand
    //   2882: baload
    //   2883: iload #48
    //   2885: ixor
    //   2886: i2b
    //   2887: bastore
    //   2888: aload #30
    //   2890: iload #47
    //   2892: iconst_2
    //   2893: iadd
    //   2894: iaload
    //   2895: istore #48
    //   2897: aload #46
    //   2899: bipush #8
    //   2901: aload #37
    //   2903: iload #51
    //   2905: bipush #24
    //   2907: iushr
    //   2908: baload
    //   2909: iload #48
    //   2911: bipush #24
    //   2913: iushr
    //   2914: ixor
    //   2915: i2b
    //   2916: bastore
    //   2917: aload #46
    //   2919: bipush #9
    //   2921: aload #37
    //   2923: iload #50
    //   2925: bipush #16
    //   2927: iushr
    //   2928: sipush #255
    //   2931: iand
    //   2932: baload
    //   2933: iload #48
    //   2935: bipush #16
    //   2937: iushr
    //   2938: ixor
    //   2939: i2b
    //   2940: bastore
    //   2941: aload #46
    //   2943: bipush #10
    //   2945: aload #37
    //   2947: iload #49
    //   2949: bipush #8
    //   2951: iushr
    //   2952: sipush #255
    //   2955: iand
    //   2956: baload
    //   2957: iload #48
    //   2959: bipush #8
    //   2961: iushr
    //   2962: ixor
    //   2963: i2b
    //   2964: bastore
    //   2965: aload #46
    //   2967: bipush #11
    //   2969: aload #37
    //   2971: iload #52
    //   2973: sipush #255
    //   2976: iand
    //   2977: baload
    //   2978: iload #48
    //   2980: ixor
    //   2981: i2b
    //   2982: bastore
    //   2983: aload #30
    //   2985: iload #47
    //   2987: iconst_3
    //   2988: iadd
    //   2989: iaload
    //   2990: istore #48
    //   2992: aload #46
    //   2994: bipush #12
    //   2996: aload #37
    //   2998: iload #52
    //   3000: bipush #24
    //   3002: iushr
    //   3003: baload
    //   3004: iload #48
    //   3006: bipush #24
    //   3008: iushr
    //   3009: ixor
    //   3010: i2b
    //   3011: bastore
    //   3012: aload #46
    //   3014: bipush #13
    //   3016: aload #37
    //   3018: iload #51
    //   3020: bipush #16
    //   3022: iushr
    //   3023: sipush #255
    //   3026: iand
    //   3027: baload
    //   3028: iload #48
    //   3030: bipush #16
    //   3032: iushr
    //   3033: ixor
    //   3034: i2b
    //   3035: bastore
    //   3036: aload #46
    //   3038: bipush #14
    //   3040: aload #37
    //   3042: iload #50
    //   3044: bipush #8
    //   3046: iushr
    //   3047: sipush #255
    //   3050: iand
    //   3051: baload
    //   3052: iload #48
    //   3054: bipush #8
    //   3056: iushr
    //   3057: ixor
    //   3058: i2b
    //   3059: bastore
    //   3060: aload #46
    //   3062: bipush #15
    //   3064: aload #37
    //   3066: iload #49
    //   3068: sipush #255
    //   3071: iand
    //   3072: baload
    //   3073: iload #48
    //   3075: ixor
    //   3076: i2b
    //   3077: bastore
    //   3078: iconst_0
    //   3079: istore #53
    //   3081: iload #53
    //   3083: bipush #16
    //   3085: if_icmpge -> 3111
    //   3088: aload #43
    //   3090: iload #53
    //   3092: iload #44
    //   3094: bipush #16
    //   3096: imul
    //   3097: iadd
    //   3098: aload #46
    //   3100: iload #53
    //   3102: baload
    //   3103: bastore
    //   3104: iinc #53, 1
    //   3107: iload_2
    //   3108: ifeq -> 3081
    //   3111: iinc #44, 1
    //   3114: iload_2
    //   3115: ifeq -> 2196
    //   3118: aload #43
    //   3120: arraylength
    //   3121: ifle -> 3202
    //   3124: aload #43
    //   3126: aload #43
    //   3128: arraylength
    //   3129: iconst_1
    //   3130: isub
    //   3131: baload
    //   3132: istore #44
    //   3134: iload #44
    //   3136: bipush #16
    //   3138: if_icmple -> 3149
    //   3141: aload #43
    //   3143: astore #35
    //   3145: iload_2
    //   3146: ifeq -> 3202
    //   3149: aload #43
    //   3151: arraylength
    //   3152: iload #44
    //   3154: isub
    //   3155: newarray byte
    //   3157: astore #35
    //   3159: iconst_0
    //   3160: istore #45
    //   3162: iload #45
    //   3164: aload #35
    //   3166: arraylength
    //   3167: if_icmpge -> 3202
    //   3170: iload #45
    //   3172: aload #43
    //   3174: arraylength
    //   3175: if_icmpge -> 3202
    //   3178: aload #35
    //   3180: iload #45
    //   3182: aload #43
    //   3184: iload #45
    //   3186: baload
    //   3187: bastore
    //   3188: iinc #45, 1
    //   3191: iload_2
    //   3192: ifeq -> 3162
    //   3195: goto -> 3202
    //   3198: invokestatic a : (Ljava/lang/Throwable;)Ljava/lang/Throwable;
    //   3201: athrow
    //   3202: aload #35
    //   3204: astore #7
    //   3206: sipush #661
    //   3209: new java/math/BigInteger
    //   3212: dup
    //   3213: aload #7
    //   3215: invokespecial <init> : ([B)V
    //   3218: invokevirtual abs : ()Ljava/math/BigInteger;
    //   3221: putstatic burp/Zle4.Zh : Ljava/lang/Object;
    //   3224: sipush #-7297
    //   3227: invokestatic a : (II)Ljava/lang/String;
    //   3230: iconst_1
    //   3231: ldc burp/Zb14
    //   3233: invokevirtual getClassLoader : ()Ljava/lang/ClassLoader;
    //   3236: invokestatic forName : (Ljava/lang/String;ZLjava/lang/ClassLoader;)Ljava/lang/Class;
    //   3239: invokevirtual getDeclaredFields : ()[Ljava/lang/reflect/Field;
    //   3242: astore_3
    //   3243: aload_3
    //   3244: arraylength
    //   3245: istore #4
    //   3247: iconst_0
    //   3248: istore #5
    //   3250: iload #5
    //   3252: iload #4
    //   3254: if_icmpge -> 3391
    //   3257: aload_3
    //   3258: iload #5
    //   3260: aaload
    //   3261: astore #6
    //   3263: aload #6
    //   3265: invokevirtual getModifiers : ()I
    //   3268: invokestatic isStatic : (I)Z
    //   3271: ifne -> 3281
    //   3274: goto -> 3384
    //   3277: invokestatic a : (Ljava/lang/Throwable;)Ljava/lang/Throwable;
    //   3280: athrow
    //   3281: aload #6
    //   3283: invokevirtual getType : ()Ljava/lang/Class;
    //   3286: astore #7
    //   3288: aload #7
    //   3290: ifnull -> 3371
    //   3293: aload #7
    //   3295: invokevirtual isPrimitive : ()Z
    //   3298: ifne -> 3371
    //   3301: goto -> 3308
    //   3304: invokestatic a : (Ljava/lang/Throwable;)Ljava/lang/Throwable;
    //   3307: athrow
    //   3308: aload #7
    //   3310: invokevirtual getPackage : ()Ljava/lang/Package;
    //   3313: ifnull -> 3371
    //   3316: goto -> 3323
    //   3319: invokestatic a : (Ljava/lang/Throwable;)Ljava/lang/Throwable;
    //   3322: athrow
    //   3323: aload #7
    //   3325: invokevirtual getPackage : ()Ljava/lang/Package;
    //   3328: invokevirtual getName : ()Ljava/lang/String;
    //   3331: ifnull -> 3371
    //   3334: goto -> 3341
    //   3337: invokestatic a : (Ljava/lang/Throwable;)Ljava/lang/Throwable;
    //   3340: athrow
    //   3341: aload #7
    //   3343: invokevirtual getPackage : ()Ljava/lang/Package;
    //   3346: invokevirtual getName : ()Ljava/lang/String;
    //   3349: sipush #656
    //   3352: sipush #24409
    //   3355: invokestatic a : (II)Ljava/lang/String;
    //   3358: invokevirtual startsWith : (Ljava/lang/String;)Z
    //   3361: ifne -> 3371
    //   3364: goto -> 3371
    //   3367: invokestatic a : (Ljava/lang/Throwable;)Ljava/lang/Throwable;
    //   3370: athrow
    //   3371: aload #6
    //   3373: iconst_1
    //   3374: invokevirtual setAccessible : (Z)V
    //   3377: aload #6
    //   3379: aconst_null
    //   3380: invokevirtual get : (Ljava/lang/Object;)Ljava/lang/Object;
    //   3383: pop
    //   3384: iinc #5, 1
    //   3387: iload_2
    //   3388: ifeq -> 3250
    //   3391: sipush #662
    //   3394: sipush #-30713
    //   3397: invokestatic a : (II)Ljava/lang/String;
    //   3400: invokestatic forName : (Ljava/lang/String;)Ljava/lang/Class;
    //   3403: invokevirtual getDeclaredMethods : ()[Ljava/lang/reflect/Method;
    //   3406: astore_3
    //   3407: aload_3
    //   3408: arraylength
    //   3409: istore #4
    //   3411: iconst_0
    //   3412: istore #5
    //   3414: iload #5
    //   3416: iload #4
    //   3418: if_icmpge -> 3547
    //   3421: aload_3
    //   3422: iload #5
    //   3424: aaload
    //   3425: astore #6
    //   3427: aload #6
    //   3429: invokevirtual getParameterTypes : ()[Ljava/lang/Class;
    //   3432: pop
    //   3433: aload #6
    //   3435: invokevirtual getModifiers : ()I
    //   3438: invokestatic isStatic : (I)Z
    //   3441: ifeq -> 3533
    //   3444: aload #6
    //   3446: invokevirtual getParameterTypes : ()[Ljava/lang/Class;
    //   3449: arraylength
    //   3450: iconst_2
    //   3451: if_icmpne -> 3533
    //   3454: goto -> 3461
    //   3457: invokestatic a : (Ljava/lang/Throwable;)Ljava/lang/Throwable;
    //   3460: athrow
    //   3461: aload #6
    //   3463: invokevirtual getReturnType : ()Ljava/lang/Class;
    //   3466: getstatic java/lang/Boolean.TYPE : Ljava/lang/Class;
    //   3469: if_acmpne -> 3533
    //   3472: goto -> 3479
    //   3475: invokestatic a : (Ljava/lang/Throwable;)Ljava/lang/Throwable;
    //   3478: athrow
    //   3479: aload #6
    //   3481: iconst_1
    //   3482: invokevirtual setAccessible : (Z)V
    //   3485: aload #6
    //   3487: aconst_null
    //   3488: iconst_2
    //   3489: anewarray java/lang/Object
    //   3492: dup
    //   3493: iconst_0
    //   3494: aload_0
    //   3495: aastore
    //   3496: dup
    //   3497: iconst_1
    //   3498: aload_1
    //   3499: ifnonnull -> 3517
    //   3502: goto -> 3509
    //   3505: invokestatic a : (Ljava/lang/Throwable;)Ljava/lang/Throwable;
    //   3508: athrow
    //   3509: aload_1
    //   3510: goto -> 3524
    //   3513: invokestatic a : (Ljava/lang/Throwable;)Ljava/lang/Throwable;
    //   3516: athrow
    //   3517: aload_1
    //   3518: checkcast [B
    //   3521: invokevirtual clone : ()Ljava/lang/Object;
    //   3524: aastore
    //   3525: invokevirtual invoke : (Ljava/lang/Object;[Ljava/lang/Object;)Ljava/lang/Object;
    //   3528: pop
    //   3529: iload_2
    //   3530: ifeq -> 3547
    //   3533: iinc #5, 1
    //   3536: iload_2
    //   3537: ifeq -> 3414
    //   3540: goto -> 3547
    //   3543: invokestatic a : (Ljava/lang/Throwable;)Ljava/lang/Throwable;
    //   3546: athrow
    //   3547: sipush #647
    //   3550: sipush #24289
    //   3553: invokestatic a : (II)Ljava/lang/String;
    //   3556: iconst_1
    //   3557: ldc burp/Zlw8
    //   3559: invokevirtual getClassLoader : ()Ljava/lang/ClassLoader;
    //   3562: invokestatic forName : (Ljava/lang/String;ZLjava/lang/ClassLoader;)Ljava/lang/Class;
    //   3565: invokevirtual getDeclaredFields : ()[Ljava/lang/reflect/Field;
    //   3568: astore_3
    //   3569: aload_3
    //   3570: arraylength
    //   3571: istore #4
    //   3573: iconst_0
    //   3574: istore #5
    //   3576: iload #5
    //   3578: iload #4
    //   3580: if_icmpge -> 3717
    //   3583: aload_3
    //   3584: iload #5
    //   3586: aaload
    //   3587: astore #6
    //   3589: aload #6
    //   3591: invokevirtual getModifiers : ()I
    //   3594: invokestatic isStatic : (I)Z
    //   3597: ifne -> 3607
    //   3600: goto -> 3710
    //   3603: invokestatic a : (Ljava/lang/Throwable;)Ljava/lang/Throwable;
    //   3606: athrow
    //   3607: aload #6
    //   3609: invokevirtual getType : ()Ljava/lang/Class;
    //   3612: astore #7
    //   3614: aload #7
    //   3616: ifnull -> 3697
    //   3619: aload #7
    //   3621: invokevirtual isPrimitive : ()Z
    //   3624: ifne -> 3697
    //   3627: goto -> 3634
    //   3630: invokestatic a : (Ljava/lang/Throwable;)Ljava/lang/Throwable;
    //   3633: athrow
    //   3634: aload #7
    //   3636: invokevirtual getPackage : ()Ljava/lang/Package;
    //   3639: ifnull -> 3697
    //   3642: goto -> 3649
    //   3645: invokestatic a : (Ljava/lang/Throwable;)Ljava/lang/Throwable;
    //   3648: athrow
    //   3649: aload #7
    //   3651: invokevirtual getPackage : ()Ljava/lang/Package;
    //   3654: invokevirtual getName : ()Ljava/lang/String;
    //   3657: ifnull -> 3697
    //   3660: goto -> 3667
    //   3663: invokestatic a : (Ljava/lang/Throwable;)Ljava/lang/Throwable;
    //   3666: athrow
    //   3667: aload #7
    //   3669: invokevirtual getPackage : ()Ljava/lang/Package;
    //   3672: invokevirtual getName : ()Ljava/lang/String;
    //   3675: sipush #657
    //   3678: sipush #-28825
    //   3681: invokestatic a : (II)Ljava/lang/String;
    //   3684: invokevirtual startsWith : (Ljava/lang/String;)Z
    //   3687: ifne -> 3697
    //   3690: goto -> 3697
    //   3693: invokestatic a : (Ljava/lang/Throwable;)Ljava/lang/Throwable;
    //   3696: athrow
    //   3697: aload #6
    //   3699: iconst_1
    //   3700: invokevirtual setAccessible : (Z)V
    //   3703: aload #6
    //   3705: aconst_null
    //   3706: invokevirtual get : (Ljava/lang/Object;)Ljava/lang/Object;
    //   3709: pop
    //   3710: iinc #5, 1
    //   3713: iload_2
    //   3714: ifeq -> 3576
    //   3717: sipush #660
    //   3720: sipush #6201
    //   3723: invokestatic a : (II)Ljava/lang/String;
    //   3726: invokestatic forName : (Ljava/lang/String;)Ljava/lang/Class;
    //   3729: invokevirtual getDeclaredMethods : ()[Ljava/lang/reflect/Method;
    //   3732: astore_3
    //   3733: aload_3
    //   3734: arraylength
    //   3735: istore #4
    //   3737: iconst_0
    //   3738: istore #5
    //   3740: iload #5
    //   3742: iload #4
    //   3744: if_icmpge -> 3876
    //   3747: aload_3
    //   3748: iload #5
    //   3750: aaload
    //   3751: astore #6
    //   3753: aload #6
    //   3755: invokevirtual getParameterTypes : ()[Ljava/lang/Class;
    //   3758: pop
    //   3759: aload #6
    //   3761: invokevirtual getModifiers : ()I
    //   3764: invokestatic isStatic : (I)Z
    //   3767: ifeq -> 3862
    //   3770: aload #6
    //   3772: invokevirtual getParameterTypes : ()[Ljava/lang/Class;
    //   3775: arraylength
    //   3776: iconst_2
    //   3777: if_icmpne -> 3862
    //   3780: goto -> 3787
    //   3783: invokestatic a : (Ljava/lang/Throwable;)Ljava/lang/Throwable;
    //   3786: athrow
    //   3787: aload #6
    //   3789: invokevirtual getReturnType : ()Ljava/lang/Class;
    //   3792: getstatic java/lang/Void.TYPE : Ljava/lang/Class;
    //   3795: invokevirtual equals : (Ljava/lang/Object;)Z
    //   3798: ifeq -> 3862
    //   3801: goto -> 3808
    //   3804: invokestatic a : (Ljava/lang/Throwable;)Ljava/lang/Throwable;
    //   3807: athrow
    //   3808: aload #6
    //   3810: iconst_1
    //   3811: invokevirtual setAccessible : (Z)V
    //   3814: aload #6
    //   3816: aconst_null
    //   3817: iconst_2
    //   3818: anewarray java/lang/Object
    //   3821: dup
    //   3822: iconst_0
    //   3823: aload_0
    //   3824: aastore
    //   3825: dup
    //   3826: iconst_1
    //   3827: aload_1
    //   3828: ifnonnull -> 3846
    //   3831: goto -> 3838
    //   3834: invokestatic a : (Ljava/lang/Throwable;)Ljava/lang/Throwable;
    //   3837: athrow
    //   3838: aload_1
    //   3839: goto -> 3853
    //   3842: invokestatic a : (Ljava/lang/Throwable;)Ljava/lang/Throwable;
    //   3845: athrow
    //   3846: aload_1
    //   3847: checkcast [B
    //   3850: invokevirtual clone : ()Ljava/lang/Object;
    //   3853: aastore
    //   3854: invokevirtual invoke : (Ljava/lang/Object;[Ljava/lang/Object;)Ljava/lang/Object;
    //   3857: pop
    //   3858: iload_2
    //   3859: ifeq -> 3876
    //   3862: iinc #5, 1
    //   3865: iload_2
    //   3866: ifeq -> 3740
    //   3869: goto -> 3876
    //   3872: invokestatic a : (Ljava/lang/Throwable;)Ljava/lang/Throwable;
    //   3875: athrow
    //   3876: getstatic burp/Zkqx.Ze : Ljava/lang/String;
    //   3879: getstatic burp/Zkmx.Zu : Ljava/lang/Object;
    //   3882: checkcast java/math/BigInteger
    //   3885: invokevirtual intValue : ()I
    //   3888: bipush #32
    //   3890: irem
    //   3891: invokestatic abs : (I)I
    //   3894: invokevirtual charAt : (I)C
    //   3897: getstatic burp/Zl_9.ZP : Ljava/lang/String;
    //   3900: getstatic burp/Zrcu.Zs : Ljava/lang/Object;
    //   3903: checkcast java/math/BigInteger
    //   3906: invokevirtual intValue : ()I
    //   3909: bipush #32
    //   3911: irem
    //   3912: invokestatic abs : (I)I
    //   3915: invokevirtual charAt : (I)C
    //   3918: if_icmple -> 4025
    //   3921: getstatic burp/Zter.ZE : Ljava/lang/String;
    //   3924: getstatic burp/Zsxo.Za : Ljava/lang/Object;
    //   3927: checkcast java/math/BigInteger
    //   3930: invokevirtual intValue : ()I
    //   3933: bipush #32
    //   3935: irem
    //   3936: invokestatic abs : (I)I
    //   3939: invokevirtual charAt : (I)C
    //   3942: getstatic burp/Zr4z.Zw : Ljava/lang/String;
    //   3945: getstatic burp/Zl8f.ZA : Ljava/lang/Object;
    //   3948: checkcast java/math/BigInteger
    //   3951: invokevirtual intValue : ()I
    //   3954: bipush #32
    //   3956: irem
    //   3957: invokestatic abs : (I)I
    //   3960: invokevirtual charAt : (I)C
    //   3963: if_icmple -> 4025
    //   3966: goto -> 3973
    //   3969: invokestatic a : (Ljava/lang/Throwable;)Ljava/lang/Throwable;
    //   3972: athrow
    //   3973: getstatic burp/Zgre.Zj : Ljava/lang/String;
    //   3976: getstatic burp/Zl2t.ZS : Ljava/lang/Object;
    //   3979: checkcast java/math/BigInteger
    //   3982: invokevirtual intValue : ()I
    //   3985: bipush #32
    //   3987: irem
    //   3988: invokestatic abs : (I)I
    //   3991: invokevirtual charAt : (I)C
    //   3994: getstatic burp/Zsdn.Zf : Ljava/lang/String;
    //   3997: getstatic burp/Zzmo.ZI : Ljava/lang/Object;
    //   4000: checkcast java/math/BigInteger
    //   4003: invokevirtual intValue : ()I
    //   4006: bipush #32
    //   4008: irem
    //   4009: invokestatic abs : (I)I
    //   4012: invokevirtual charAt : (I)C
    //   4015: if_icmpgt -> 4033
    //   4018: goto -> 4025
    //   4021: invokestatic a : (Ljava/lang/Throwable;)Ljava/lang/Throwable;
    //   4024: athrow
    //   4025: iconst_1
    //   4026: goto -> 4034
    //   4029: invokestatic a : (Ljava/lang/Throwable;)Ljava/lang/Throwable;
    //   4032: athrow
    //   4033: iconst_0
    //   4034: ireturn
    //   4035: astore_3
    //   4036: new java/lang/Exception
    //   4039: dup
    //   4040: aload_3
    //   4041: invokevirtual getMessage : ()Ljava/lang/String;
    //   4044: invokespecial <init> : (Ljava/lang/String;)V
    //   4047: athrow
    // Exception table:
    //   from	to	target	type
    //   4	4034	4035	java/lang/Throwable
    //   327	351	354	java/lang/Throwable
    //   425	462	462	java/lang/Throwable
    //   466	487	487	java/lang/Throwable
    //   491	521	521	java/lang/Throwable
    //   849	864	864	java/lang/Throwable
    //   1866	1892	1892	java/lang/Throwable
    //   1973	1988	1988	java/lang/Throwable
    //   3170	3195	3198	java/lang/Throwable
    //   3263	3277	3277	java/lang/Throwable
    //   3288	3301	3304	java/lang/Throwable
    //   3293	3316	3319	java/lang/Throwable
    //   3308	3334	3337	java/lang/Throwable
    //   3323	3364	3367	java/lang/Throwable
    //   3427	3454	3457	java/lang/Throwable
    //   3444	3472	3475	java/lang/Throwable
    //   3461	3502	3505	java/lang/Throwable
    //   3479	3513	3513	java/lang/Throwable
    //   3524	3540	3543	java/lang/Throwable
    //   3589	3603	3603	java/lang/Throwable
    //   3614	3627	3630	java/lang/Throwable
    //   3619	3642	3645	java/lang/Throwable
    //   3634	3660	3663	java/lang/Throwable
    //   3649	3690	3693	java/lang/Throwable
    //   3753	3780	3783	java/lang/Throwable
    //   3770	3801	3804	java/lang/Throwable
    //   3787	3831	3834	java/lang/Throwable
    //   3808	3842	3842	java/lang/Throwable
    //   3853	3869	3872	java/lang/Throwable
    //   3876	3966	3969	java/lang/Throwable
    //   3921	4018	4021	java/lang/Throwable
    //   3973	4029	4029	java/lang/Throwable
  }
  
  static {
    // Byte code:
    //   0: bipush #17
    //   2: anewarray java/lang/String
    //   5: astore #5
    //   7: iconst_0
    //   8: istore_3
    //   9: ldc '%(aT\\t @MH{\\tT8R\\r+\\tI,\\fhFRM7QBS6\\tR@MEiRx}8b3`|&\Fn8HtCfV;??\\t(BN !B^dli=3IOZ H\\nnc2U<Q^X 1!q(5r36BGe 9\\t0Cu!f??'
    //   11: dup
    //   12: astore_2
    //   13: invokevirtual length : ()I
    //   16: istore #4
    //   18: bipush #9
    //   20: istore_1
    //   21: iconst_m1
    //   22: istore_0
    //   23: bipush #55
    //   25: iinc #0, 1
    //   28: aload_2
    //   29: iload_0
    //   30: dup
    //   31: iload_1
    //   32: iadd
    //   33: invokevirtual substring : (II)Ljava/lang/String;
    //   36: iconst_m1
    //   37: goto -> 143
    //   40: aload #5
    //   42: swap
    //   43: iload_3
    //   44: iinc #3, 1
    //   47: swap
    //   48: aastore
    //   49: iload_0
    //   50: iload_1
    //   51: iadd
    //   52: dup
    //   53: istore_0
    //   54: iload #4
    //   56: if_icmpge -> 68
    //   59: aload_2
    //   60: iload_0
    //   61: invokevirtual charAt : (I)C
    //   64: istore_1
    //   65: goto -> 23
    //   68: ldc '7^\\rN#<PvXikq;\\nQ\\tC~}}'
    //   70: dup
    //   71: astore_2
    //   72: invokevirtual length : ()I
    //   75: istore #4
    //   77: bipush #32
    //   79: istore_1
    //   80: iconst_m1
    //   81: istore_0
    //   82: bipush #55
    //   84: iinc #0, 1
    //   87: aload_2
    //   88: iload_0
    //   89: dup
    //   90: iload_1
    //   91: iadd
    //   92: invokevirtual substring : (II)Ljava/lang/String;
    //   95: iconst_0
    //   96: goto -> 143
    //   99: aload #5
    //   101: swap
    //   102: iload_3
    //   103: iinc #3, 1
    //   106: swap
    //   107: aastore
    //   108: iload_0
    //   109: iload_1
    //   110: iadd
    //   111: dup
    //   112: istore_0
    //   113: iload #4
    //   115: if_icmpge -> 127
    //   118: aload_2
    //   119: iload_0
    //   120: invokevirtual charAt : (I)C
    //   123: istore_1
    //   124: goto -> 82
    //   127: aload #5
    //   129: putstatic burp/Zxjw.a : [Ljava/lang/String;
    //   132: bipush #17
    //   134: anewarray java/lang/String
    //   137: putstatic burp/Zxjw.b : [Ljava/lang/String;
    //   140: goto -> 300
    //   143: dup_x2
    //   144: pop
    //   145: invokevirtual toCharArray : ()[C
    //   148: dup_x1
    //   149: arraylength
    //   150: dup_x2
    //   151: pop
    //   152: iconst_0
    //   153: istore #6
    //   155: dup2_x1
    //   156: pop2
    //   157: dup_x2
    //   158: iconst_1
    //   159: if_icmpgt -> 260
    //   162: dup2
    //   163: swap
    //   164: iload #6
    //   166: dup2_x1
    //   167: caload
    //   168: swap
    //   169: iload #6
    //   171: bipush #7
    //   173: irem
    //   174: tableswitch default -> 242, 0 -> 212, 1 -> 217, 2 -> 222, 3 -> 227, 4 -> 232, 5 -> 237
    //   212: bipush #6
    //   214: goto -> 244
    //   217: bipush #32
    //   219: goto -> 244
    //   222: bipush #91
    //   224: goto -> 244
    //   227: bipush #123
    //   229: goto -> 244
    //   232: bipush #26
    //   234: goto -> 244
    //   237: bipush #119
    //   239: goto -> 244
    //   242: bipush #30
    //   244: ixor
    //   245: ixor
    //   246: i2c
    //   247: castore
    //   248: iinc #6, 1
    //   251: dup
    //   252: ifne -> 260
    //   255: dup2
    //   256: dup_x1
    //   257: goto -> 166
    //   260: dup2_x1
    //   261: pop2
    //   262: dup_x2
    //   263: iload #6
    //   265: if_icmpgt -> 162
    //   268: pop
    //   269: new java/lang/String
    //   272: dup_x1
    //   273: swap
    //   274: invokespecial <init> : ([C)V
    //   277: invokevirtual intern : ()Ljava/lang/String;
    //   280: swap
    //   281: pop
    //   282: swap
    //   283: tableswitch default -> 40, 0 -> 99
    //   300: sipush #664
    //   303: sipush #2221
    //   306: invokestatic a : (II)Ljava/lang/String;
    //   309: putstatic burp/Zxjw.Zv : Ljava/lang/String;
    //   312: new java/math/BigInteger
    //   315: dup
    //   316: bipush #32
    //   318: newarray byte
    //   320: dup
    //   321: iconst_0
    //   322: bipush #82
    //   324: bastore
    //   325: dup
    //   326: iconst_1
    //   327: bipush #18
    //   329: bastore
    //   330: dup
    //   331: iconst_2
    //   332: bipush #120
    //   334: bastore
    //   335: dup
    //   336: iconst_3
    //   337: bipush #-9
    //   339: bastore
    //   340: dup
    //   341: iconst_4
    //   342: bipush #-64
    //   344: bastore
    //   345: dup
    //   346: iconst_5
    //   347: bipush #-57
    //   349: bastore
    //   350: dup
    //   351: bipush #6
    //   353: bipush #59
    //   355: bastore
    //   356: dup
    //   357: bipush #7
    //   359: bipush #87
    //   361: bastore
    //   362: dup
    //   363: bipush #8
    //   365: bipush #95
    //   367: bastore
    //   368: dup
    //   369: bipush #9
    //   371: bipush #127
    //   373: bastore
    //   374: dup
    //   375: bipush #10
    //   377: bipush #-8
    //   379: bastore
    //   380: dup
    //   381: bipush #11
    //   383: bipush #62
    //   385: bastore
    //   386: dup
    //   387: bipush #12
    //   389: bipush #-78
    //   391: bastore
    //   392: dup
    //   393: bipush #13
    //   395: bipush #-116
    //   397: bastore
    //   398: dup
    //   399: bipush #14
    //   401: bipush #61
    //   403: bastore
    //   404: dup
    //   405: bipush #15
    //   407: bipush #-51
    //   409: bastore
    //   410: dup
    //   411: bipush #16
    //   413: bipush #-49
    //   415: bastore
    //   416: dup
    //   417: bipush #17
    //   419: bipush #93
    //   421: bastore
    //   422: dup
    //   423: bipush #18
    //   425: bipush #-70
    //   427: bastore
    //   428: dup
    //   429: bipush #19
    //   431: bipush #-59
    //   433: bastore
    //   434: dup
    //   435: bipush #20
    //   437: bipush #109
    //   439: bastore
    //   440: dup
    //   441: bipush #21
    //   443: bipush #53
    //   445: bastore
    //   446: dup
    //   447: bipush #22
    //   449: bipush #126
    //   451: bastore
    //   452: dup
    //   453: bipush #23
    //   455: bipush #-107
    //   457: bastore
    //   458: dup
    //   459: bipush #24
    //   461: bipush #-116
    //   463: bastore
    //   464: dup
    //   465: bipush #25
    //   467: bipush #-121
    //   469: bastore
    //   470: dup
    //   471: bipush #26
    //   473: bipush #-123
    //   475: bastore
    //   476: dup
    //   477: bipush #27
    //   479: bipush #-106
    //   481: bastore
    //   482: dup
    //   483: bipush #28
    //   485: bipush #78
    //   487: bastore
    //   488: dup
    //   489: bipush #29
    //   491: bipush #73
    //   493: bastore
    //   494: dup
    //   495: bipush #30
    //   497: bipush #-41
    //   499: bastore
    //   500: dup
    //   501: bipush #31
    //   503: bipush #120
    //   505: bastore
    //   506: invokespecial <init> : ([B)V
    //   509: putstatic burp/Zxjw.ZU : Ljava/lang/Object;
    //   512: return
  }
  
  private static Throwable a(Throwable paramThrowable) {
    return paramThrowable;
  }
  
  private static String a(int paramInt1, int paramInt2) {
    int i = (paramInt1 ^ 0x297) & 0xFFFF;
    if (b[i] == null) {
      char[] arrayOfChar = a[i].toCharArray();
      switch (arrayOfChar[0] & 0xFF) {
        case 0:
        
        case 1:
        
        case 2:
        
        case 3:
        
        case 4:
        
        case 5:
        
        case 6:
        
        case 7:
        
        case 8:
        
        case 9:
        
        case 10:
        
        case 11:
        
        case 12:
        
        case 13:
        
        case 14:
        
        case 15:
        
        case 16:
        
        case 17:
        
        case 18:
        
        case 19:
        
        case 20:
        
        case 21:
        
        case 22:
        
        case 23:
        
        case 24:
        
        case 25:
        
        case 26:
        
        case 27:
        
        case 28:
        
        case 29:
        
        case 30:
        
        case 31:
        
        case 32:
        
        case 33:
        
        case 34:
        
        case 35:
        
        case 36:
        
        case 37:
        
        case 38:
        
        case 39:
        
        case 40:
        
        case 41:
        
        case 42:
        
        case 43:
        
        case 44:
        
        case 45:
        
        case 46:
        
        case 47:
        
        case 48:
        
        case 49:
        
        case 50:
        
        case 51:
        
        case 52:
        
        case 53:
        
        case 54:
        
        case 55:
        
        case 56:
        
        case 57:
        
        case 58:
        
        case 59:
        
        case 60:
        
        case 61:
        
        case 62:
        
        case 63:
        
        case 64:
        
        case 65:
        
        case 66:
        
        case 67:
        
        case 68:
        
        case 69:
        
        case 70:
        
        case 71:
        
        case 72:
        
        case 73:
        
        case 74:
        
        case 75:
        
        case 76:
        
        case 77:
        
        case 78:
        
        case 79:
        
        case 80:
        
        case 81:
        
        case 82:
        
        case 83:
        
        case 84:
        
        case 85:
        
        case 86:
        
        case 87:
        
        case 88:
        
        case 89:
        
        case 90:
        
        case 91:
        
        case 92:
        
        case 93:
        
        case 94:
        
        case 95:
        
        case 96:
        
        case 97:
        
        case 98:
        
        case 99:
        
        case 100:
        
        case 101:
        
        case 102:
        
        case 103:
        
        case 104:
        
        case 105:
        
        case 106:
        
        case 107:
        
        case 108:
        
        case 109:
        
        case 110:
        
        case 111:
        
        case 112:
        
        case 113:
        
        case 114:
        
        case 115:
        
        case 116:
        
        case 117:
        
        case 118:
        
        case 119:
        
        case 120:
        
        case 121:
        
        case 122:
        
        case 123:
        
        case 124:
        
        case 125:
        
        case 126:
        
        case 127:
        
        case 128:
        
        case 129:
        
        case 130:
        
        case 131:
        
        case 132:
        
        case 133:
        
        case 134:
        
        case 135:
        
        case 136:
        
        case 137:
        
        case 138:
        
        case 139:
        
        case 140:
        
        case 141:
        
        case 142:
        
        case 143:
        
        case 144:
        
        case 145:
        
        case 146:
        
        case 147:
        
        case 148:
        
        case 149:
        
        case 150:
        
        case 151:
        
        case 152:
        
        case 153:
        
        case 154:
        
        case 155:
        
        case 156:
        
        case 157:
        
        case 158:
        
        case 159:
        
        case 160:
        
        case 161:
        
        case 162:
        
        case 163:
        
        case 164:
        
        case 165:
        
        case 166:
        
        case 167:
        
        case 168:
        
        case 169:
        
        case 170:
        
        case 171:
        
        case 172:
        
        case 173:
        
        case 174:
        
        case 175:
        
        case 176:
        
        case 177:
        
        case 178:
        
        case 179:
        
        case 180:
        
        case 181:
        
        case 182:
        
        case 183:
        
        case 184:
        
        case 185:
        
        case 186:
        
        case 187:
        
        case 188:
        
        case 189:
        
        case 190:
        
        case 191:
        
        case 192:
        
        case 193:
        
        case 194:
        
        case 195:
        
        case 196:
        
        case 197:
        
        case 198:
        
        case 199:
        
        case 200:
        
        case 201:
        
        case 202:
        
        case 203:
        
        case 204:
        
        case 205:
        
        case 206:
        
        case 207:
        
        case 208:
        
        case 209:
        
        case 210:
        
        case 211:
        
        case 212:
        
        case 213:
        
        case 214:
        
        case 215:
        
        case 216:
        
        case 217:
        
        case 218:
        
        case 219:
        
        case 220:
        
        case 221:
        
        case 222:
        
        case 223:
        
        case 224:
        
        case 225:
        
        case 226:
        
        case 227:
        
        case 228:
        
        case 229:
        
        case 230:
        
        case 231:
        
        case 232:
        
        case 233:
        
        case 234:
        
        case 235:
        
        case 236:
        
        case 237:
        
        case 238:
        
        case 239:
        
        case 240:
        
        case 241:
        
        case 242:
        
        case 243:
        
        case 244:
        
        case 245:
        
        case 246:
        
        case 247:
        
        case 248:
        
        case 249:
        
        case 250:
        
        case 251:
        
        case 252:
        
        case 253:
        
        case 254:
        
        default:
          break;
      } 
      char c = '';
      int j = (paramInt2 & 0xFF) - c;
      if (j < 0)
        j += 256; 
      int k = ((paramInt2 & 0xFFFF) >>> 8) - c;
      if (k < 0)
        k += 256; 
      for (byte b = 0; b < arrayOfChar.length; b++) {
        int m = b % 2;
        if (m == 0) {
          arrayOfChar[b] = (char)(arrayOfChar[b] ^ j);
          j = ((j >>> 3 | j << 5) ^ arrayOfChar[b]) & 0xFF;
        } else {
          arrayOfChar[b] = (char)(arrayOfChar[b] ^ k);
          k = ((k >>> 3 | k << 5) ^ arrayOfChar[b]) & 0xFF;
        } 
      } 
      b[i] = (new String(arrayOfChar)).intern();
    } 
    return b[i];
  }
}


/* Location:              C:\Program Files\BurpSuitePro\burpsuite_pro.jar!\burp\Zxjw.class
 * Java compiler version: 21 (65.0)
 * JD-Core Version:       1.1.3
 */