package burp;

import java.math.BigInteger;

class Zxn4 extends ClassLoader {
  static String ZQ;
  
  static Object Zx;
  
  private static final String[] a;
  
  private static final String[] b;
  
  static boolean Zi(Object[] paramArrayOfObject, Object paramObject) throws Throwable {
    // Byte code:
    //   0: invokestatic ZK : ()Z
    //   3: istore_2
    //   4: new java/lang/StringBuilder
    //   7: dup
    //   8: invokespecial <init> : ()V
    //   11: astore_3
    //   12: iconst_0
    //   13: istore #4
    //   15: iload #4
    //   17: bipush #32
    //   19: if_icmpge -> 1355
    //   22: iload #4
    //   24: tableswitch default -> 1348, 0 -> 168, 1 -> 205, 2 -> 242, 3 -> 279, 4 -> 316, 5 -> 353, 6 -> 390, 7 -> 427, 8 -> 464, 9 -> 501, 10 -> 538, 11 -> 575, 12 -> 612, 13 -> 649, 14 -> 686, 15 -> 723, 16 -> 760, 17 -> 797, 18 -> 834, 19 -> 871, 20 -> 908, 21 -> 945, 22 -> 982, 23 -> 1019, 24 -> 1056, 25 -> 1093, 26 -> 1130, 27 -> 1167, 28 -> 1204, 29 -> 1241, 30 -> 1278, 31 -> 1315
    //   168: aload_3
    //   169: getstatic burp/Ztvg.ZZ : Ljava/lang/String;
    //   172: getstatic burp/Zr17.ZR : Ljava/lang/Object;
    //   175: checkcast java/math/BigInteger
    //   178: invokevirtual intValue : ()I
    //   181: bipush #32
    //   183: irem
    //   184: invokestatic abs : (I)I
    //   187: invokevirtual charAt : (I)C
    //   190: invokevirtual append : (C)Ljava/lang/StringBuilder;
    //   193: pop
    //   194: iload_2
    //   195: ifeq -> 1348
    //   198: goto -> 205
    //   201: invokestatic a : (Ljava/lang/Throwable;)Ljava/lang/Throwable;
    //   204: athrow
    //   205: aload_3
    //   206: getstatic burp/Zl7b.Zv : Ljava/lang/String;
    //   209: getstatic burp/Zxzv.Zg : Ljava/lang/Object;
    //   212: checkcast java/math/BigInteger
    //   215: invokevirtual intValue : ()I
    //   218: bipush #32
    //   220: irem
    //   221: invokestatic abs : (I)I
    //   224: invokevirtual charAt : (I)C
    //   227: invokevirtual append : (C)Ljava/lang/StringBuilder;
    //   230: pop
    //   231: iload_2
    //   232: ifeq -> 1348
    //   235: goto -> 242
    //   238: invokestatic a : (Ljava/lang/Throwable;)Ljava/lang/Throwable;
    //   241: athrow
    //   242: aload_3
    //   243: getstatic burp/Zea9.Zd : Ljava/lang/String;
    //   246: getstatic burp/Ztq2.Zj : Ljava/lang/Object;
    //   249: checkcast java/math/BigInteger
    //   252: invokevirtual intValue : ()I
    //   255: bipush #32
    //   257: irem
    //   258: invokestatic abs : (I)I
    //   261: invokevirtual charAt : (I)C
    //   264: invokevirtual append : (C)Ljava/lang/StringBuilder;
    //   267: pop
    //   268: iload_2
    //   269: ifeq -> 1348
    //   272: goto -> 279
    //   275: invokestatic a : (Ljava/lang/Throwable;)Ljava/lang/Throwable;
    //   278: athrow
    //   279: aload_3
    //   280: getstatic burp/Zkkl.Zh : Ljava/lang/String;
    //   283: getstatic burp/Zsfj.ZL : Ljava/lang/Object;
    //   286: checkcast java/math/BigInteger
    //   289: invokevirtual intValue : ()I
    //   292: bipush #32
    //   294: irem
    //   295: invokestatic abs : (I)I
    //   298: invokevirtual charAt : (I)C
    //   301: invokevirtual append : (C)Ljava/lang/StringBuilder;
    //   304: pop
    //   305: iload_2
    //   306: ifeq -> 1348
    //   309: goto -> 316
    //   312: invokestatic a : (Ljava/lang/Throwable;)Ljava/lang/Throwable;
    //   315: athrow
    //   316: aload_3
    //   317: getstatic burp/Zt85.ZR : Ljava/lang/String;
    //   320: getstatic burp/Zg61.Zp : Ljava/lang/Object;
    //   323: checkcast java/math/BigInteger
    //   326: invokevirtual intValue : ()I
    //   329: bipush #32
    //   331: irem
    //   332: invokestatic abs : (I)I
    //   335: invokevirtual charAt : (I)C
    //   338: invokevirtual append : (C)Ljava/lang/StringBuilder;
    //   341: pop
    //   342: iload_2
    //   343: ifeq -> 1348
    //   346: goto -> 353
    //   349: invokestatic a : (Ljava/lang/Throwable;)Ljava/lang/Throwable;
    //   352: athrow
    //   353: aload_3
    //   354: getstatic burp/Zzhx.ZV : Ljava/lang/String;
    //   357: getstatic burp/Zscf.ZG : Ljava/lang/Object;
    //   360: checkcast java/math/BigInteger
    //   363: invokevirtual intValue : ()I
    //   366: bipush #32
    //   368: irem
    //   369: invokestatic abs : (I)I
    //   372: invokevirtual charAt : (I)C
    //   375: invokevirtual append : (C)Ljava/lang/StringBuilder;
    //   378: pop
    //   379: iload_2
    //   380: ifeq -> 1348
    //   383: goto -> 390
    //   386: invokestatic a : (Ljava/lang/Throwable;)Ljava/lang/Throwable;
    //   389: athrow
    //   390: aload_3
    //   391: getstatic burp/Zlg2.ZL : Ljava/lang/String;
    //   394: getstatic burp/Zmf6.ZD : Ljava/lang/Object;
    //   397: checkcast java/math/BigInteger
    //   400: invokevirtual intValue : ()I
    //   403: bipush #32
    //   405: irem
    //   406: invokestatic abs : (I)I
    //   409: invokevirtual charAt : (I)C
    //   412: invokevirtual append : (C)Ljava/lang/StringBuilder;
    //   415: pop
    //   416: iload_2
    //   417: ifeq -> 1348
    //   420: goto -> 427
    //   423: invokestatic a : (Ljava/lang/Throwable;)Ljava/lang/Throwable;
    //   426: athrow
    //   427: aload_3
    //   428: getstatic burp/Zejz.Zd : Ljava/lang/String;
    //   431: getstatic burp/Zsdl.Zx : Ljava/lang/Object;
    //   434: checkcast java/math/BigInteger
    //   437: invokevirtual intValue : ()I
    //   440: bipush #32
    //   442: irem
    //   443: invokestatic abs : (I)I
    //   446: invokevirtual charAt : (I)C
    //   449: invokevirtual append : (C)Ljava/lang/StringBuilder;
    //   452: pop
    //   453: iload_2
    //   454: ifeq -> 1348
    //   457: goto -> 464
    //   460: invokestatic a : (Ljava/lang/Throwable;)Ljava/lang/Throwable;
    //   463: athrow
    //   464: aload_3
    //   465: getstatic burp/Zsp9.ZA : Ljava/lang/String;
    //   468: getstatic burp/Zl1e.Zp : Ljava/lang/Object;
    //   471: checkcast java/math/BigInteger
    //   474: invokevirtual intValue : ()I
    //   477: bipush #32
    //   479: irem
    //   480: invokestatic abs : (I)I
    //   483: invokevirtual charAt : (I)C
    //   486: invokevirtual append : (C)Ljava/lang/StringBuilder;
    //   489: pop
    //   490: iload_2
    //   491: ifeq -> 1348
    //   494: goto -> 501
    //   497: invokestatic a : (Ljava/lang/Throwable;)Ljava/lang/Throwable;
    //   500: athrow
    //   501: aload_3
    //   502: getstatic burp/Zb3l.Zz : Ljava/lang/String;
    //   505: getstatic burp/Zlsg.ZD : Ljava/lang/Object;
    //   508: checkcast java/math/BigInteger
    //   511: invokevirtual intValue : ()I
    //   514: bipush #32
    //   516: irem
    //   517: invokestatic abs : (I)I
    //   520: invokevirtual charAt : (I)C
    //   523: invokevirtual append : (C)Ljava/lang/StringBuilder;
    //   526: pop
    //   527: iload_2
    //   528: ifeq -> 1348
    //   531: goto -> 538
    //   534: invokestatic a : (Ljava/lang/Throwable;)Ljava/lang/Throwable;
    //   537: athrow
    //   538: aload_3
    //   539: getstatic burp/Zgtx.ZN : Ljava/lang/String;
    //   542: getstatic burp/Zst7.ZI : Ljava/lang/Object;
    //   545: checkcast java/math/BigInteger
    //   548: invokevirtual intValue : ()I
    //   551: bipush #32
    //   553: irem
    //   554: invokestatic abs : (I)I
    //   557: invokevirtual charAt : (I)C
    //   560: invokevirtual append : (C)Ljava/lang/StringBuilder;
    //   563: pop
    //   564: iload_2
    //   565: ifeq -> 1348
    //   568: goto -> 575
    //   571: invokestatic a : (Ljava/lang/Throwable;)Ljava/lang/Throwable;
    //   574: athrow
    //   575: aload_3
    //   576: getstatic burp/Zer1.ZV : Ljava/lang/String;
    //   579: getstatic burp/Zmzj.Zm : Ljava/lang/Object;
    //   582: checkcast java/math/BigInteger
    //   585: invokevirtual intValue : ()I
    //   588: bipush #32
    //   590: irem
    //   591: invokestatic abs : (I)I
    //   594: invokevirtual charAt : (I)C
    //   597: invokevirtual append : (C)Ljava/lang/StringBuilder;
    //   600: pop
    //   601: iload_2
    //   602: ifeq -> 1348
    //   605: goto -> 612
    //   608: invokestatic a : (Ljava/lang/Throwable;)Ljava/lang/Throwable;
    //   611: athrow
    //   612: aload_3
    //   613: getstatic burp/Zr14.ZL : Ljava/lang/String;
    //   616: getstatic burp/Zlgh.Zd : Ljava/lang/Object;
    //   619: checkcast java/math/BigInteger
    //   622: invokevirtual intValue : ()I
    //   625: bipush #32
    //   627: irem
    //   628: invokestatic abs : (I)I
    //   631: invokevirtual charAt : (I)C
    //   634: invokevirtual append : (C)Ljava/lang/StringBuilder;
    //   637: pop
    //   638: iload_2
    //   639: ifeq -> 1348
    //   642: goto -> 649
    //   645: invokestatic a : (Ljava/lang/Throwable;)Ljava/lang/Throwable;
    //   648: athrow
    //   649: aload_3
    //   650: getstatic burp/Zscz.ZJ : Ljava/lang/String;
    //   653: getstatic burp/Zeqx.Zh : Ljava/lang/Object;
    //   656: checkcast java/math/BigInteger
    //   659: invokevirtual intValue : ()I
    //   662: bipush #32
    //   664: irem
    //   665: invokestatic abs : (I)I
    //   668: invokevirtual charAt : (I)C
    //   671: invokevirtual append : (C)Ljava/lang/StringBuilder;
    //   674: pop
    //   675: iload_2
    //   676: ifeq -> 1348
    //   679: goto -> 686
    //   682: invokestatic a : (Ljava/lang/Throwable;)Ljava/lang/Throwable;
    //   685: athrow
    //   686: aload_3
    //   687: getstatic burp/Zsjw.ZQ : Ljava/lang/String;
    //   690: getstatic burp/Zmkq.Zg : Ljava/lang/Object;
    //   693: checkcast java/math/BigInteger
    //   696: invokevirtual intValue : ()I
    //   699: bipush #32
    //   701: irem
    //   702: invokestatic abs : (I)I
    //   705: invokevirtual charAt : (I)C
    //   708: invokevirtual append : (C)Ljava/lang/StringBuilder;
    //   711: pop
    //   712: iload_2
    //   713: ifeq -> 1348
    //   716: goto -> 723
    //   719: invokestatic a : (Ljava/lang/Throwable;)Ljava/lang/Throwable;
    //   722: athrow
    //   723: aload_3
    //   724: getstatic burp/Zrnt.Zy : Ljava/lang/String;
    //   727: getstatic burp/Zst7.ZI : Ljava/lang/Object;
    //   730: checkcast java/math/BigInteger
    //   733: invokevirtual intValue : ()I
    //   736: bipush #32
    //   738: irem
    //   739: invokestatic abs : (I)I
    //   742: invokevirtual charAt : (I)C
    //   745: invokevirtual append : (C)Ljava/lang/StringBuilder;
    //   748: pop
    //   749: iload_2
    //   750: ifeq -> 1348
    //   753: goto -> 760
    //   756: invokestatic a : (Ljava/lang/Throwable;)Ljava/lang/Throwable;
    //   759: athrow
    //   760: aload_3
    //   761: getstatic burp/Zzc9.Zv : Ljava/lang/String;
    //   764: getstatic burp/Zgcg.Zi : Ljava/lang/Object;
    //   767: checkcast java/math/BigInteger
    //   770: invokevirtual intValue : ()I
    //   773: bipush #32
    //   775: irem
    //   776: invokestatic abs : (I)I
    //   779: invokevirtual charAt : (I)C
    //   782: invokevirtual append : (C)Ljava/lang/StringBuilder;
    //   785: pop
    //   786: iload_2
    //   787: ifeq -> 1348
    //   790: goto -> 797
    //   793: invokestatic a : (Ljava/lang/Throwable;)Ljava/lang/Throwable;
    //   796: athrow
    //   797: aload_3
    //   798: getstatic burp/Zmhq.Zy : Ljava/lang/String;
    //   801: getstatic burp/Zrl5.ZI : Ljava/lang/Object;
    //   804: checkcast java/math/BigInteger
    //   807: invokevirtual intValue : ()I
    //   810: bipush #32
    //   812: irem
    //   813: invokestatic abs : (I)I
    //   816: invokevirtual charAt : (I)C
    //   819: invokevirtual append : (C)Ljava/lang/StringBuilder;
    //   822: pop
    //   823: iload_2
    //   824: ifeq -> 1348
    //   827: goto -> 834
    //   830: invokestatic a : (Ljava/lang/Throwable;)Ljava/lang/Throwable;
    //   833: athrow
    //   834: aload_3
    //   835: getstatic burp/Zbwj.ZP : Ljava/lang/String;
    //   838: getstatic burp/Zti4.Zi : Ljava/lang/Object;
    //   841: checkcast java/math/BigInteger
    //   844: invokevirtual intValue : ()I
    //   847: bipush #32
    //   849: irem
    //   850: invokestatic abs : (I)I
    //   853: invokevirtual charAt : (I)C
    //   856: invokevirtual append : (C)Ljava/lang/StringBuilder;
    //   859: pop
    //   860: iload_2
    //   861: ifeq -> 1348
    //   864: goto -> 871
    //   867: invokestatic a : (Ljava/lang/Throwable;)Ljava/lang/Throwable;
    //   870: athrow
    //   871: aload_3
    //   872: getstatic burp/Zg4l.Z_ : Ljava/lang/String;
    //   875: getstatic burp/Zzht.Zb : Ljava/lang/Object;
    //   878: checkcast java/math/BigInteger
    //   881: invokevirtual intValue : ()I
    //   884: bipush #32
    //   886: irem
    //   887: invokestatic abs : (I)I
    //   890: invokevirtual charAt : (I)C
    //   893: invokevirtual append : (C)Ljava/lang/StringBuilder;
    //   896: pop
    //   897: iload_2
    //   898: ifeq -> 1348
    //   901: goto -> 908
    //   904: invokestatic a : (Ljava/lang/Throwable;)Ljava/lang/Throwable;
    //   907: athrow
    //   908: aload_3
    //   909: getstatic burp/Zs_m.Zt : Ljava/lang/String;
    //   912: getstatic burp/Zz4m.Zo : Ljava/lang/Object;
    //   915: checkcast java/math/BigInteger
    //   918: invokevirtual intValue : ()I
    //   921: bipush #32
    //   923: irem
    //   924: invokestatic abs : (I)I
    //   927: invokevirtual charAt : (I)C
    //   930: invokevirtual append : (C)Ljava/lang/StringBuilder;
    //   933: pop
    //   934: iload_2
    //   935: ifeq -> 1348
    //   938: goto -> 945
    //   941: invokestatic a : (Ljava/lang/Throwable;)Ljava/lang/Throwable;
    //   944: athrow
    //   945: aload_3
    //   946: getstatic burp/Zg7e.Zg : Ljava/lang/String;
    //   949: getstatic burp/Zxp1.ZP : Ljava/lang/Object;
    //   952: checkcast java/math/BigInteger
    //   955: invokevirtual intValue : ()I
    //   958: bipush #32
    //   960: irem
    //   961: invokestatic abs : (I)I
    //   964: invokevirtual charAt : (I)C
    //   967: invokevirtual append : (C)Ljava/lang/StringBuilder;
    //   970: pop
    //   971: iload_2
    //   972: ifeq -> 1348
    //   975: goto -> 982
    //   978: invokestatic a : (Ljava/lang/Throwable;)Ljava/lang/Throwable;
    //   981: athrow
    //   982: aload_3
    //   983: getstatic burp/Zlf7.ZM : Ljava/lang/String;
    //   986: getstatic burp/Zm1d.ZS : Ljava/lang/Object;
    //   989: checkcast java/math/BigInteger
    //   992: invokevirtual intValue : ()I
    //   995: bipush #32
    //   997: irem
    //   998: invokestatic abs : (I)I
    //   1001: invokevirtual charAt : (I)C
    //   1004: invokevirtual append : (C)Ljava/lang/StringBuilder;
    //   1007: pop
    //   1008: iload_2
    //   1009: ifeq -> 1348
    //   1012: goto -> 1019
    //   1015: invokestatic a : (Ljava/lang/Throwable;)Ljava/lang/Throwable;
    //   1018: athrow
    //   1019: aload_3
    //   1020: getstatic burp/Zegj.ZS : Ljava/lang/String;
    //   1023: getstatic burp/Zmf2.Zx : Ljava/lang/Object;
    //   1026: checkcast java/math/BigInteger
    //   1029: invokevirtual intValue : ()I
    //   1032: bipush #32
    //   1034: irem
    //   1035: invokestatic abs : (I)I
    //   1038: invokevirtual charAt : (I)C
    //   1041: invokevirtual append : (C)Ljava/lang/StringBuilder;
    //   1044: pop
    //   1045: iload_2
    //   1046: ifeq -> 1348
    //   1049: goto -> 1056
    //   1052: invokestatic a : (Ljava/lang/Throwable;)Ljava/lang/Throwable;
    //   1055: athrow
    //   1056: aload_3
    //   1057: getstatic burp/Zxp1.Zg : Ljava/lang/String;
    //   1060: getstatic burp/Zsbv.Zl : Ljava/lang/Object;
    //   1063: checkcast java/math/BigInteger
    //   1066: invokevirtual intValue : ()I
    //   1069: bipush #32
    //   1071: irem
    //   1072: invokestatic abs : (I)I
    //   1075: invokevirtual charAt : (I)C
    //   1078: invokevirtual append : (C)Ljava/lang/StringBuilder;
    //   1081: pop
    //   1082: iload_2
    //   1083: ifeq -> 1348
    //   1086: goto -> 1093
    //   1089: invokestatic a : (Ljava/lang/Throwable;)Ljava/lang/Throwable;
    //   1092: athrow
    //   1093: aload_3
    //   1094: getstatic burp/Zst7.Zi : Ljava/lang/String;
    //   1097: getstatic burp/Zmhq.ZK : Ljava/lang/Object;
    //   1100: checkcast java/math/BigInteger
    //   1103: invokevirtual intValue : ()I
    //   1106: bipush #32
    //   1108: irem
    //   1109: invokestatic abs : (I)I
    //   1112: invokevirtual charAt : (I)C
    //   1115: invokevirtual append : (C)Ljava/lang/StringBuilder;
    //   1118: pop
    //   1119: iload_2
    //   1120: ifeq -> 1348
    //   1123: goto -> 1130
    //   1126: invokestatic a : (Ljava/lang/Throwable;)Ljava/lang/Throwable;
    //   1129: athrow
    //   1130: aload_3
    //   1131: getstatic burp/Zrwp.ZS : Ljava/lang/String;
    //   1134: getstatic burp/Zr02.ZB : Ljava/lang/Object;
    //   1137: checkcast java/math/BigInteger
    //   1140: invokevirtual intValue : ()I
    //   1143: bipush #32
    //   1145: irem
    //   1146: invokestatic abs : (I)I
    //   1149: invokevirtual charAt : (I)C
    //   1152: invokevirtual append : (C)Ljava/lang/StringBuilder;
    //   1155: pop
    //   1156: iload_2
    //   1157: ifeq -> 1348
    //   1160: goto -> 1167
    //   1163: invokestatic a : (Ljava/lang/Throwable;)Ljava/lang/Throwable;
    //   1166: athrow
    //   1167: aload_3
    //   1168: getstatic burp/Zbnk.Zg : Ljava/lang/String;
    //   1171: getstatic burp/Zm1d.ZS : Ljava/lang/Object;
    //   1174: checkcast java/math/BigInteger
    //   1177: invokevirtual intValue : ()I
    //   1180: bipush #32
    //   1182: irem
    //   1183: invokestatic abs : (I)I
    //   1186: invokevirtual charAt : (I)C
    //   1189: invokevirtual append : (C)Ljava/lang/StringBuilder;
    //   1192: pop
    //   1193: iload_2
    //   1194: ifeq -> 1348
    //   1197: goto -> 1204
    //   1200: invokestatic a : (Ljava/lang/Throwable;)Ljava/lang/Throwable;
    //   1203: athrow
    //   1204: aload_3
    //   1205: getstatic burp/Zkjj.ZT : Ljava/lang/String;
    //   1208: getstatic burp/Ztr5.ZZ : Ljava/lang/Object;
    //   1211: checkcast java/math/BigInteger
    //   1214: invokevirtual intValue : ()I
    //   1217: bipush #32
    //   1219: irem
    //   1220: invokestatic abs : (I)I
    //   1223: invokevirtual charAt : (I)C
    //   1226: invokevirtual append : (C)Ljava/lang/StringBuilder;
    //   1229: pop
    //   1230: iload_2
    //   1231: ifeq -> 1348
    //   1234: goto -> 1241
    //   1237: invokestatic a : (Ljava/lang/Throwable;)Ljava/lang/Throwable;
    //   1240: athrow
    //   1241: aload_3
    //   1242: getstatic burp/Zbss.ZV : Ljava/lang/String;
    //   1245: getstatic burp/Zllk.Zi : Ljava/lang/Object;
    //   1248: checkcast java/math/BigInteger
    //   1251: invokevirtual intValue : ()I
    //   1254: bipush #32
    //   1256: irem
    //   1257: invokestatic abs : (I)I
    //   1260: invokevirtual charAt : (I)C
    //   1263: invokevirtual append : (C)Ljava/lang/StringBuilder;
    //   1266: pop
    //   1267: iload_2
    //   1268: ifeq -> 1348
    //   1271: goto -> 1278
    //   1274: invokestatic a : (Ljava/lang/Throwable;)Ljava/lang/Throwable;
    //   1277: athrow
    //   1278: aload_3
    //   1279: getstatic burp/Zzpm.Za : Ljava/lang/String;
    //   1282: getstatic burp/Zkf6.ZS : Ljava/lang/Object;
    //   1285: checkcast java/math/BigInteger
    //   1288: invokevirtual intValue : ()I
    //   1291: bipush #32
    //   1293: irem
    //   1294: invokestatic abs : (I)I
    //   1297: invokevirtual charAt : (I)C
    //   1300: invokevirtual append : (C)Ljava/lang/StringBuilder;
    //   1303: pop
    //   1304: iload_2
    //   1305: ifeq -> 1348
    //   1308: goto -> 1315
    //   1311: invokestatic a : (Ljava/lang/Throwable;)Ljava/lang/Throwable;
    //   1314: athrow
    //   1315: aload_3
    //   1316: getstatic burp/Ze4a.Zm : Ljava/lang/String;
    //   1319: getstatic burp/Ze2w.ZA : Ljava/lang/Object;
    //   1322: checkcast java/math/BigInteger
    //   1325: invokevirtual intValue : ()I
    //   1328: bipush #32
    //   1330: irem
    //   1331: invokestatic abs : (I)I
    //   1334: invokevirtual charAt : (I)C
    //   1337: invokevirtual append : (C)Ljava/lang/StringBuilder;
    //   1340: pop
    //   1341: goto -> 1348
    //   1344: invokestatic a : (Ljava/lang/Throwable;)Ljava/lang/Throwable;
    //   1347: athrow
    //   1348: iinc #4, 1
    //   1351: iload_2
    //   1352: ifeq -> 15
    //   1355: aload_3
    //   1356: invokevirtual toString : ()Ljava/lang/String;
    //   1359: putstatic burp/Zrww.ZV : Ljava/lang/String;
    //   1362: new java/io/ByteArrayOutputStream
    //   1365: dup
    //   1366: invokespecial <init> : ()V
    //   1369: astore #4
    //   1371: getstatic burp/Ze2k.ZY : Ljava/lang/String;
    //   1374: astore #5
    //   1376: iconst_0
    //   1377: istore #6
    //   1379: iload #6
    //   1381: aload #5
    //   1383: invokevirtual length : ()I
    //   1386: if_icmpge -> 1417
    //   1389: aload #4
    //   1391: aload #5
    //   1393: iload #6
    //   1395: iload #6
    //   1397: iconst_2
    //   1398: iadd
    //   1399: invokevirtual substring : (II)Ljava/lang/String;
    //   1402: bipush #16
    //   1404: invokestatic parseInt : (Ljava/lang/String;I)I
    //   1407: invokevirtual write : (I)V
    //   1410: iinc #6, 2
    //   1413: iload_2
    //   1414: ifeq -> 1379
    //   1417: aload #4
    //   1419: invokevirtual toByteArray : ()[B
    //   1422: astore #6
    //   1424: getstatic burp/Zxci.Zx : Ljava/lang/Object;
    //   1427: checkcast java/math/BigInteger
    //   1430: invokevirtual toByteArray : ()[B
    //   1433: astore #7
    //   1435: sipush #256
    //   1438: newarray byte
    //   1440: astore #9
    //   1442: sipush #256
    //   1445: newarray int
    //   1447: astore #10
    //   1449: sipush #256
    //   1452: newarray int
    //   1454: astore #11
    //   1456: sipush #256
    //   1459: newarray int
    //   1461: astore #12
    //   1463: sipush #256
    //   1466: newarray int
    //   1468: astore #13
    //   1470: bipush #10
    //   1472: newarray int
    //   1474: astore #14
    //   1476: sipush #283
    //   1479: istore #15
    //   1481: iconst_0
    //   1482: istore #17
    //   1484: iload #17
    //   1486: sipush #256
    //   1489: if_icmpge -> 1723
    //   1492: sipush #10768
    //   1495: sipush #-29537
    //   1498: invokestatic a : (II)Ljava/lang/String;
    //   1501: iload #17
    //   1503: iconst_1
    //   1504: iushr
    //   1505: invokevirtual charAt : (I)C
    //   1508: istore #26
    //   1510: iload #17
    //   1512: iconst_1
    //   1513: iand
    //   1514: ifne -> 1529
    //   1517: iload #26
    //   1519: bipush #8
    //   1521: iushr
    //   1522: goto -> 1531
    //   1525: invokestatic a : (Ljava/lang/Throwable;)Ljava/lang/Throwable;
    //   1528: athrow
    //   1529: iload #26
    //   1531: i2b
    //   1532: sipush #255
    //   1535: iand
    //   1536: istore #16
    //   1538: iload #17
    //   1540: iconst_1
    //   1541: ishl
    //   1542: istore #18
    //   1544: iload #18
    //   1546: sipush #256
    //   1549: if_icmplt -> 1559
    //   1552: iload #18
    //   1554: iload #15
    //   1556: ixor
    //   1557: istore #18
    //   1559: iload #18
    //   1561: iconst_1
    //   1562: ishl
    //   1563: istore #19
    //   1565: iload #19
    //   1567: sipush #256
    //   1570: if_icmplt -> 1580
    //   1573: iload #19
    //   1575: iload #15
    //   1577: ixor
    //   1578: istore #19
    //   1580: iload #19
    //   1582: iconst_1
    //   1583: ishl
    //   1584: istore #20
    //   1586: iload #20
    //   1588: sipush #256
    //   1591: if_icmplt -> 1601
    //   1594: iload #20
    //   1596: iload #15
    //   1598: ixor
    //   1599: istore #20
    //   1601: iload #20
    //   1603: iload #17
    //   1605: ixor
    //   1606: istore #21
    //   1608: iload #21
    //   1610: iload #18
    //   1612: ixor
    //   1613: istore #22
    //   1615: iload #21
    //   1617: iload #19
    //   1619: ixor
    //   1620: istore #23
    //   1622: iload #20
    //   1624: iload #19
    //   1626: ixor
    //   1627: iload #18
    //   1629: ixor
    //   1630: istore #24
    //   1632: aload #9
    //   1634: iload #17
    //   1636: iload #16
    //   1638: i2b
    //   1639: bastore
    //   1640: aload #10
    //   1642: iload #16
    //   1644: iload #24
    //   1646: bipush #24
    //   1648: ishl
    //   1649: iload #21
    //   1651: bipush #16
    //   1653: ishl
    //   1654: ior
    //   1655: iload #23
    //   1657: bipush #8
    //   1659: ishl
    //   1660: ior
    //   1661: iload #22
    //   1663: ior
    //   1664: dup
    //   1665: istore #25
    //   1667: iastore
    //   1668: aload #11
    //   1670: iload #16
    //   1672: iload #25
    //   1674: bipush #8
    //   1676: iushr
    //   1677: iload #25
    //   1679: bipush #24
    //   1681: ishl
    //   1682: ior
    //   1683: iastore
    //   1684: aload #12
    //   1686: iload #16
    //   1688: iload #25
    //   1690: bipush #16
    //   1692: iushr
    //   1693: iload #25
    //   1695: bipush #16
    //   1697: ishl
    //   1698: ior
    //   1699: iastore
    //   1700: aload #13
    //   1702: iload #16
    //   1704: iload #25
    //   1706: bipush #24
    //   1708: iushr
    //   1709: iload #25
    //   1711: bipush #8
    //   1713: ishl
    //   1714: ior
    //   1715: iastore
    //   1716: iinc #17, 1
    //   1719: iload_2
    //   1720: ifeq -> 1484
    //   1723: iconst_1
    //   1724: istore #26
    //   1726: aload #14
    //   1728: iconst_0
    //   1729: iload #26
    //   1731: bipush #24
    //   1733: ishl
    //   1734: iastore
    //   1735: iconst_1
    //   1736: istore #27
    //   1738: iload #27
    //   1740: bipush #10
    //   1742: if_icmpge -> 1783
    //   1745: iload #26
    //   1747: iconst_1
    //   1748: ishl
    //   1749: istore #26
    //   1751: iload #26
    //   1753: sipush #256
    //   1756: if_icmplt -> 1766
    //   1759: iload #26
    //   1761: iload #15
    //   1763: ixor
    //   1764: istore #26
    //   1766: aload #14
    //   1768: iload #27
    //   1770: iload #26
    //   1772: bipush #24
    //   1774: ishl
    //   1775: iastore
    //   1776: iinc #27, 1
    //   1779: iload_2
    //   1780: ifeq -> 1738
    //   1783: iconst_4
    //   1784: istore #27
    //   1786: iload #27
    //   1788: bipush #6
    //   1790: iadd
    //   1791: istore #28
    //   1793: iconst_4
    //   1794: iload #28
    //   1796: iconst_1
    //   1797: iadd
    //   1798: imul
    //   1799: istore #29
    //   1801: iload #29
    //   1803: newarray int
    //   1805: astore #30
    //   1807: iload #29
    //   1809: newarray int
    //   1811: astore #31
    //   1813: iconst_0
    //   1814: istore #26
    //   1816: iconst_0
    //   1817: istore #33
    //   1819: iconst_0
    //   1820: istore #34
    //   1822: iload #33
    //   1824: iload #27
    //   1826: if_icmpge -> 1894
    //   1829: aload #30
    //   1831: iload #33
    //   1833: aload #6
    //   1835: iload #34
    //   1837: baload
    //   1838: bipush #24
    //   1840: ishl
    //   1841: aload #6
    //   1843: iload #34
    //   1845: iconst_1
    //   1846: iadd
    //   1847: baload
    //   1848: sipush #255
    //   1851: iand
    //   1852: bipush #16
    //   1854: ishl
    //   1855: ior
    //   1856: aload #6
    //   1858: iload #34
    //   1860: iconst_2
    //   1861: iadd
    //   1862: baload
    //   1863: sipush #255
    //   1866: iand
    //   1867: bipush #8
    //   1869: ishl
    //   1870: ior
    //   1871: aload #6
    //   1873: iload #34
    //   1875: iconst_3
    //   1876: iadd
    //   1877: baload
    //   1878: sipush #255
    //   1881: iand
    //   1882: ior
    //   1883: iastore
    //   1884: iinc #33, 1
    //   1887: iinc #34, 4
    //   1890: iload_2
    //   1891: ifeq -> 1822
    //   1894: iload #27
    //   1896: istore #33
    //   1898: iconst_0
    //   1899: istore #34
    //   1901: iload #33
    //   1903: iload #29
    //   1905: if_icmpge -> 2032
    //   1908: aload #30
    //   1910: iload #33
    //   1912: iconst_1
    //   1913: isub
    //   1914: iaload
    //   1915: istore #32
    //   1917: iload #34
    //   1919: ifne -> 2006
    //   1922: iload #27
    //   1924: istore #34
    //   1926: aload #9
    //   1928: iload #32
    //   1930: bipush #16
    //   1932: iushr
    //   1933: sipush #255
    //   1936: iand
    //   1937: baload
    //   1938: bipush #24
    //   1940: ishl
    //   1941: aload #9
    //   1943: iload #32
    //   1945: bipush #8
    //   1947: iushr
    //   1948: sipush #255
    //   1951: iand
    //   1952: baload
    //   1953: sipush #255
    //   1956: iand
    //   1957: bipush #16
    //   1959: ishl
    //   1960: ior
    //   1961: aload #9
    //   1963: iload #32
    //   1965: sipush #255
    //   1968: iand
    //   1969: baload
    //   1970: sipush #255
    //   1973: iand
    //   1974: bipush #8
    //   1976: ishl
    //   1977: ior
    //   1978: aload #9
    //   1980: iload #32
    //   1982: bipush #24
    //   1984: iushr
    //   1985: baload
    //   1986: sipush #255
    //   1989: iand
    //   1990: ior
    //   1991: istore #32
    //   1993: iload #32
    //   1995: aload #14
    //   1997: iload #26
    //   1999: iinc #26, 1
    //   2002: iaload
    //   2003: ixor
    //   2004: istore #32
    //   2006: aload #30
    //   2008: iload #33
    //   2010: aload #30
    //   2012: iload #33
    //   2014: iload #27
    //   2016: isub
    //   2017: iaload
    //   2018: iload #32
    //   2020: ixor
    //   2021: iastore
    //   2022: iinc #33, 1
    //   2025: iinc #34, -1
    //   2028: iload_2
    //   2029: ifeq -> 1901
    //   2032: iconst_0
    //   2033: istore #33
    //   2035: iconst_4
    //   2036: iload #28
    //   2038: imul
    //   2039: istore #34
    //   2041: aload #31
    //   2043: iload #33
    //   2045: aload #30
    //   2047: iload #34
    //   2049: iaload
    //   2050: iastore
    //   2051: aload #31
    //   2053: iload #33
    //   2055: iconst_1
    //   2056: iadd
    //   2057: aload #30
    //   2059: iload #34
    //   2061: iconst_1
    //   2062: iadd
    //   2063: iaload
    //   2064: iastore
    //   2065: aload #31
    //   2067: iload #33
    //   2069: iconst_2
    //   2070: iadd
    //   2071: aload #30
    //   2073: iload #34
    //   2075: iconst_2
    //   2076: iadd
    //   2077: iaload
    //   2078: iastore
    //   2079: aload #31
    //   2081: iload #33
    //   2083: iconst_3
    //   2084: iadd
    //   2085: aload #30
    //   2087: iload #34
    //   2089: iconst_3
    //   2090: iadd
    //   2091: iaload
    //   2092: iastore
    //   2093: iinc #33, 4
    //   2096: iinc #34, -4
    //   2099: iconst_1
    //   2100: istore #36
    //   2102: iload #36
    //   2104: iload #28
    //   2106: if_icmpge -> 2470
    //   2109: aload #30
    //   2111: iload #34
    //   2113: iaload
    //   2114: istore #35
    //   2116: aload #31
    //   2118: iload #33
    //   2120: aload #10
    //   2122: aload #9
    //   2124: iload #35
    //   2126: bipush #24
    //   2128: iushr
    //   2129: baload
    //   2130: sipush #255
    //   2133: iand
    //   2134: iaload
    //   2135: aload #11
    //   2137: aload #9
    //   2139: iload #35
    //   2141: bipush #16
    //   2143: iushr
    //   2144: sipush #255
    //   2147: iand
    //   2148: baload
    //   2149: sipush #255
    //   2152: iand
    //   2153: iaload
    //   2154: ixor
    //   2155: aload #12
    //   2157: aload #9
    //   2159: iload #35
    //   2161: bipush #8
    //   2163: iushr
    //   2164: sipush #255
    //   2167: iand
    //   2168: baload
    //   2169: sipush #255
    //   2172: iand
    //   2173: iaload
    //   2174: ixor
    //   2175: aload #13
    //   2177: aload #9
    //   2179: iload #35
    //   2181: sipush #255
    //   2184: iand
    //   2185: baload
    //   2186: sipush #255
    //   2189: iand
    //   2190: iaload
    //   2191: ixor
    //   2192: iastore
    //   2193: aload #30
    //   2195: iload #34
    //   2197: iconst_1
    //   2198: iadd
    //   2199: iaload
    //   2200: istore #35
    //   2202: aload #31
    //   2204: iload #33
    //   2206: iconst_1
    //   2207: iadd
    //   2208: aload #10
    //   2210: aload #9
    //   2212: iload #35
    //   2214: bipush #24
    //   2216: iushr
    //   2217: baload
    //   2218: sipush #255
    //   2221: iand
    //   2222: iaload
    //   2223: aload #11
    //   2225: aload #9
    //   2227: iload #35
    //   2229: bipush #16
    //   2231: iushr
    //   2232: sipush #255
    //   2235: iand
    //   2236: baload
    //   2237: sipush #255
    //   2240: iand
    //   2241: iaload
    //   2242: ixor
    //   2243: aload #12
    //   2245: aload #9
    //   2247: iload #35
    //   2249: bipush #8
    //   2251: iushr
    //   2252: sipush #255
    //   2255: iand
    //   2256: baload
    //   2257: sipush #255
    //   2260: iand
    //   2261: iaload
    //   2262: ixor
    //   2263: aload #13
    //   2265: aload #9
    //   2267: iload #35
    //   2269: sipush #255
    //   2272: iand
    //   2273: baload
    //   2274: sipush #255
    //   2277: iand
    //   2278: iaload
    //   2279: ixor
    //   2280: iastore
    //   2281: aload #30
    //   2283: iload #34
    //   2285: iconst_2
    //   2286: iadd
    //   2287: iaload
    //   2288: istore #35
    //   2290: aload #31
    //   2292: iload #33
    //   2294: iconst_2
    //   2295: iadd
    //   2296: aload #10
    //   2298: aload #9
    //   2300: iload #35
    //   2302: bipush #24
    //   2304: iushr
    //   2305: baload
    //   2306: sipush #255
    //   2309: iand
    //   2310: iaload
    //   2311: aload #11
    //   2313: aload #9
    //   2315: iload #35
    //   2317: bipush #16
    //   2319: iushr
    //   2320: sipush #255
    //   2323: iand
    //   2324: baload
    //   2325: sipush #255
    //   2328: iand
    //   2329: iaload
    //   2330: ixor
    //   2331: aload #12
    //   2333: aload #9
    //   2335: iload #35
    //   2337: bipush #8
    //   2339: iushr
    //   2340: sipush #255
    //   2343: iand
    //   2344: baload
    //   2345: sipush #255
    //   2348: iand
    //   2349: iaload
    //   2350: ixor
    //   2351: aload #13
    //   2353: aload #9
    //   2355: iload #35
    //   2357: sipush #255
    //   2360: iand
    //   2361: baload
    //   2362: sipush #255
    //   2365: iand
    //   2366: iaload
    //   2367: ixor
    //   2368: iastore
    //   2369: aload #30
    //   2371: iload #34
    //   2373: iconst_3
    //   2374: iadd
    //   2375: iaload
    //   2376: istore #35
    //   2378: aload #31
    //   2380: iload #33
    //   2382: iconst_3
    //   2383: iadd
    //   2384: aload #10
    //   2386: aload #9
    //   2388: iload #35
    //   2390: bipush #24
    //   2392: iushr
    //   2393: baload
    //   2394: sipush #255
    //   2397: iand
    //   2398: iaload
    //   2399: aload #11
    //   2401: aload #9
    //   2403: iload #35
    //   2405: bipush #16
    //   2407: iushr
    //   2408: sipush #255
    //   2411: iand
    //   2412: baload
    //   2413: sipush #255
    //   2416: iand
    //   2417: iaload
    //   2418: ixor
    //   2419: aload #12
    //   2421: aload #9
    //   2423: iload #35
    //   2425: bipush #8
    //   2427: iushr
    //   2428: sipush #255
    //   2431: iand
    //   2432: baload
    //   2433: sipush #255
    //   2436: iand
    //   2437: iaload
    //   2438: ixor
    //   2439: aload #13
    //   2441: aload #9
    //   2443: iload #35
    //   2445: sipush #255
    //   2448: iand
    //   2449: baload
    //   2450: sipush #255
    //   2453: iand
    //   2454: iaload
    //   2455: ixor
    //   2456: iastore
    //   2457: iinc #33, 4
    //   2460: iinc #34, -4
    //   2463: iinc #36, 1
    //   2466: iload_2
    //   2467: ifeq -> 2102
    //   2470: aload #31
    //   2472: iload #33
    //   2474: aload #30
    //   2476: iload #34
    //   2478: iaload
    //   2479: iastore
    //   2480: aload #31
    //   2482: iload #33
    //   2484: iconst_1
    //   2485: iadd
    //   2486: aload #30
    //   2488: iload #34
    //   2490: iconst_1
    //   2491: iadd
    //   2492: iaload
    //   2493: iastore
    //   2494: aload #31
    //   2496: iload #33
    //   2498: iconst_2
    //   2499: iadd
    //   2500: aload #30
    //   2502: iload #34
    //   2504: iconst_2
    //   2505: iadd
    //   2506: iaload
    //   2507: iastore
    //   2508: aload #31
    //   2510: iload #33
    //   2512: iconst_3
    //   2513: iadd
    //   2514: aload #30
    //   2516: iload #34
    //   2518: iconst_3
    //   2519: iadd
    //   2520: iaload
    //   2521: iastore
    //   2522: iconst_0
    //   2523: newarray byte
    //   2525: astore #36
    //   2527: aload #7
    //   2529: arraylength
    //   2530: bipush #16
    //   2532: irem
    //   2533: ifeq -> 2557
    //   2536: new java/lang/Exception
    //   2539: dup
    //   2540: sipush #10769
    //   2543: sipush #24573
    //   2546: invokestatic a : (II)Ljava/lang/String;
    //   2549: invokespecial <init> : (Ljava/lang/String;)V
    //   2552: athrow
    //   2553: invokestatic a : (Ljava/lang/Throwable;)Ljava/lang/Throwable;
    //   2556: athrow
    //   2557: bipush #10
    //   2559: istore #37
    //   2561: sipush #10760
    //   2564: sipush #256
    //   2567: newarray byte
    //   2569: astore #38
    //   2571: sipush #29855
    //   2574: sipush #256
    //   2577: newarray int
    //   2579: astore #39
    //   2581: sipush #256
    //   2584: newarray int
    //   2586: astore #40
    //   2588: sipush #256
    //   2591: newarray int
    //   2593: astore #41
    //   2595: sipush #256
    //   2598: newarray int
    //   2600: astore #42
    //   2602: sipush #283
    //   2605: istore #15
    //   2607: invokestatic a : (II)Ljava/lang/String;
    //   2610: astore #43
    //   2612: iconst_0
    //   2613: istore #17
    //   2615: iload #17
    //   2617: sipush #256
    //   2620: if_icmpge -> 2847
    //   2623: aload #43
    //   2625: iload #17
    //   2627: iconst_1
    //   2628: iushr
    //   2629: invokevirtual charAt : (I)C
    //   2632: istore #44
    //   2634: iload #17
    //   2636: iconst_1
    //   2637: iand
    //   2638: ifne -> 2653
    //   2641: iload #44
    //   2643: bipush #8
    //   2645: iushr
    //   2646: goto -> 2655
    //   2649: invokestatic a : (Ljava/lang/Throwable;)Ljava/lang/Throwable;
    //   2652: athrow
    //   2653: iload #44
    //   2655: i2b
    //   2656: sipush #255
    //   2659: iand
    //   2660: istore #16
    //   2662: iload #17
    //   2664: iconst_1
    //   2665: ishl
    //   2666: istore #18
    //   2668: iload #18
    //   2670: sipush #256
    //   2673: if_icmplt -> 2683
    //   2676: iload #18
    //   2678: iload #15
    //   2680: ixor
    //   2681: istore #18
    //   2683: iload #18
    //   2685: iconst_1
    //   2686: ishl
    //   2687: istore #19
    //   2689: iload #19
    //   2691: sipush #256
    //   2694: if_icmplt -> 2704
    //   2697: iload #19
    //   2699: iload #15
    //   2701: ixor
    //   2702: istore #19
    //   2704: iload #19
    //   2706: iconst_1
    //   2707: ishl
    //   2708: istore #20
    //   2710: iload #20
    //   2712: sipush #256
    //   2715: if_icmplt -> 2725
    //   2718: iload #20
    //   2720: iload #15
    //   2722: ixor
    //   2723: istore #20
    //   2725: iload #20
    //   2727: iload #17
    //   2729: ixor
    //   2730: istore #21
    //   2732: iload #21
    //   2734: iload #18
    //   2736: ixor
    //   2737: istore #22
    //   2739: iload #21
    //   2741: iload #19
    //   2743: ixor
    //   2744: istore #23
    //   2746: iload #20
    //   2748: iload #19
    //   2750: ixor
    //   2751: iload #18
    //   2753: ixor
    //   2754: istore #24
    //   2756: aload #38
    //   2758: iload #16
    //   2760: iload #17
    //   2762: i2b
    //   2763: bastore
    //   2764: aload #39
    //   2766: iload #16
    //   2768: iload #24
    //   2770: bipush #24
    //   2772: ishl
    //   2773: iload #21
    //   2775: bipush #16
    //   2777: ishl
    //   2778: ior
    //   2779: iload #23
    //   2781: bipush #8
    //   2783: ishl
    //   2784: ior
    //   2785: iload #22
    //   2787: ior
    //   2788: dup
    //   2789: istore #25
    //   2791: iastore
    //   2792: aload #40
    //   2794: iload #16
    //   2796: iload #25
    //   2798: bipush #8
    //   2800: iushr
    //   2801: iload #25
    //   2803: bipush #24
    //   2805: ishl
    //   2806: ior
    //   2807: iastore
    //   2808: aload #41
    //   2810: iload #16
    //   2812: iload #25
    //   2814: bipush #16
    //   2816: iushr
    //   2817: iload #25
    //   2819: bipush #16
    //   2821: ishl
    //   2822: ior
    //   2823: iastore
    //   2824: aload #42
    //   2826: iload #16
    //   2828: iload #25
    //   2830: bipush #24
    //   2832: iushr
    //   2833: iload #25
    //   2835: bipush #8
    //   2837: ishl
    //   2838: ior
    //   2839: iastore
    //   2840: iinc #17, 1
    //   2843: iload_2
    //   2844: ifeq -> 2615
    //   2847: aload #7
    //   2849: arraylength
    //   2850: newarray byte
    //   2852: astore #44
    //   2854: iconst_0
    //   2855: istore #45
    //   2857: iload #45
    //   2859: aload #7
    //   2861: arraylength
    //   2862: bipush #16
    //   2864: idiv
    //   2865: if_icmpge -> 3779
    //   2868: bipush #16
    //   2870: newarray byte
    //   2872: astore #46
    //   2874: bipush #16
    //   2876: newarray byte
    //   2878: astore #47
    //   2880: iconst_0
    //   2881: istore #48
    //   2883: iload #48
    //   2885: bipush #16
    //   2887: if_icmpge -> 2913
    //   2890: aload #46
    //   2892: iload #48
    //   2894: aload #7
    //   2896: iload #48
    //   2898: iload #45
    //   2900: bipush #16
    //   2902: imul
    //   2903: iadd
    //   2904: baload
    //   2905: bastore
    //   2906: iinc #48, 1
    //   2909: iload_2
    //   2910: ifeq -> 2883
    //   2913: iconst_0
    //   2914: istore #48
    //   2916: aload #46
    //   2918: iconst_0
    //   2919: baload
    //   2920: bipush #24
    //   2922: ishl
    //   2923: aload #46
    //   2925: iconst_1
    //   2926: baload
    //   2927: sipush #255
    //   2930: iand
    //   2931: bipush #16
    //   2933: ishl
    //   2934: ior
    //   2935: aload #46
    //   2937: iconst_2
    //   2938: baload
    //   2939: sipush #255
    //   2942: iand
    //   2943: bipush #8
    //   2945: ishl
    //   2946: ior
    //   2947: aload #46
    //   2949: iconst_3
    //   2950: baload
    //   2951: sipush #255
    //   2954: iand
    //   2955: ior
    //   2956: aload #31
    //   2958: iconst_0
    //   2959: iaload
    //   2960: ixor
    //   2961: istore #50
    //   2963: aload #46
    //   2965: iconst_4
    //   2966: baload
    //   2967: bipush #24
    //   2969: ishl
    //   2970: aload #46
    //   2972: iconst_5
    //   2973: baload
    //   2974: sipush #255
    //   2977: iand
    //   2978: bipush #16
    //   2980: ishl
    //   2981: ior
    //   2982: aload #46
    //   2984: bipush #6
    //   2986: baload
    //   2987: sipush #255
    //   2990: iand
    //   2991: bipush #8
    //   2993: ishl
    //   2994: ior
    //   2995: aload #46
    //   2997: bipush #7
    //   2999: baload
    //   3000: sipush #255
    //   3003: iand
    //   3004: ior
    //   3005: aload #31
    //   3007: iconst_1
    //   3008: iaload
    //   3009: ixor
    //   3010: istore #51
    //   3012: aload #46
    //   3014: bipush #8
    //   3016: baload
    //   3017: bipush #24
    //   3019: ishl
    //   3020: aload #46
    //   3022: bipush #9
    //   3024: baload
    //   3025: sipush #255
    //   3028: iand
    //   3029: bipush #16
    //   3031: ishl
    //   3032: ior
    //   3033: aload #46
    //   3035: bipush #10
    //   3037: baload
    //   3038: sipush #255
    //   3041: iand
    //   3042: bipush #8
    //   3044: ishl
    //   3045: ior
    //   3046: aload #46
    //   3048: bipush #11
    //   3050: baload
    //   3051: sipush #255
    //   3054: iand
    //   3055: ior
    //   3056: aload #31
    //   3058: iconst_2
    //   3059: iaload
    //   3060: ixor
    //   3061: istore #52
    //   3063: aload #46
    //   3065: bipush #12
    //   3067: baload
    //   3068: bipush #24
    //   3070: ishl
    //   3071: aload #46
    //   3073: bipush #13
    //   3075: baload
    //   3076: sipush #255
    //   3079: iand
    //   3080: bipush #16
    //   3082: ishl
    //   3083: ior
    //   3084: aload #46
    //   3086: bipush #14
    //   3088: baload
    //   3089: sipush #255
    //   3092: iand
    //   3093: bipush #8
    //   3095: ishl
    //   3096: ior
    //   3097: aload #46
    //   3099: bipush #15
    //   3101: baload
    //   3102: sipush #255
    //   3105: iand
    //   3106: ior
    //   3107: aload #31
    //   3109: iconst_3
    //   3110: iaload
    //   3111: ixor
    //   3112: istore #53
    //   3114: iconst_1
    //   3115: istore #54
    //   3117: iload #54
    //   3119: iload #37
    //   3121: if_icmpge -> 3364
    //   3124: iinc #48, 4
    //   3127: aload #39
    //   3129: iload #50
    //   3131: bipush #24
    //   3133: iushr
    //   3134: iaload
    //   3135: aload #40
    //   3137: iload #53
    //   3139: bipush #16
    //   3141: iushr
    //   3142: sipush #255
    //   3145: iand
    //   3146: iaload
    //   3147: ixor
    //   3148: aload #41
    //   3150: iload #52
    //   3152: bipush #8
    //   3154: iushr
    //   3155: sipush #255
    //   3158: iand
    //   3159: iaload
    //   3160: ixor
    //   3161: aload #42
    //   3163: iload #51
    //   3165: sipush #255
    //   3168: iand
    //   3169: iaload
    //   3170: ixor
    //   3171: aload #31
    //   3173: iload #48
    //   3175: iaload
    //   3176: ixor
    //   3177: istore #55
    //   3179: aload #39
    //   3181: iload #51
    //   3183: bipush #24
    //   3185: iushr
    //   3186: iaload
    //   3187: aload #40
    //   3189: iload #50
    //   3191: bipush #16
    //   3193: iushr
    //   3194: sipush #255
    //   3197: iand
    //   3198: iaload
    //   3199: ixor
    //   3200: aload #41
    //   3202: iload #53
    //   3204: bipush #8
    //   3206: iushr
    //   3207: sipush #255
    //   3210: iand
    //   3211: iaload
    //   3212: ixor
    //   3213: aload #42
    //   3215: iload #52
    //   3217: sipush #255
    //   3220: iand
    //   3221: iaload
    //   3222: ixor
    //   3223: aload #31
    //   3225: iload #48
    //   3227: iconst_1
    //   3228: iadd
    //   3229: iaload
    //   3230: ixor
    //   3231: istore #56
    //   3233: aload #39
    //   3235: iload #52
    //   3237: bipush #24
    //   3239: iushr
    //   3240: iaload
    //   3241: aload #40
    //   3243: iload #51
    //   3245: bipush #16
    //   3247: iushr
    //   3248: sipush #255
    //   3251: iand
    //   3252: iaload
    //   3253: ixor
    //   3254: aload #41
    //   3256: iload #50
    //   3258: bipush #8
    //   3260: iushr
    //   3261: sipush #255
    //   3264: iand
    //   3265: iaload
    //   3266: ixor
    //   3267: aload #42
    //   3269: iload #53
    //   3271: sipush #255
    //   3274: iand
    //   3275: iaload
    //   3276: ixor
    //   3277: aload #31
    //   3279: iload #48
    //   3281: iconst_2
    //   3282: iadd
    //   3283: iaload
    //   3284: ixor
    //   3285: istore #57
    //   3287: aload #39
    //   3289: iload #53
    //   3291: bipush #24
    //   3293: iushr
    //   3294: iaload
    //   3295: aload #40
    //   3297: iload #52
    //   3299: bipush #16
    //   3301: iushr
    //   3302: sipush #255
    //   3305: iand
    //   3306: iaload
    //   3307: ixor
    //   3308: aload #41
    //   3310: iload #51
    //   3312: bipush #8
    //   3314: iushr
    //   3315: sipush #255
    //   3318: iand
    //   3319: iaload
    //   3320: ixor
    //   3321: aload #42
    //   3323: iload #50
    //   3325: sipush #255
    //   3328: iand
    //   3329: iaload
    //   3330: ixor
    //   3331: aload #31
    //   3333: iload #48
    //   3335: iconst_3
    //   3336: iadd
    //   3337: iaload
    //   3338: ixor
    //   3339: istore #58
    //   3341: iload #55
    //   3343: istore #50
    //   3345: iload #56
    //   3347: istore #51
    //   3349: iload #57
    //   3351: istore #52
    //   3353: iload #58
    //   3355: istore #53
    //   3357: iinc #54, 1
    //   3360: iload_2
    //   3361: ifeq -> 3117
    //   3364: iinc #48, 4
    //   3367: aload #31
    //   3369: iload #48
    //   3371: iaload
    //   3372: istore #49
    //   3374: aload #47
    //   3376: iconst_0
    //   3377: aload #38
    //   3379: iload #50
    //   3381: bipush #24
    //   3383: iushr
    //   3384: baload
    //   3385: iload #49
    //   3387: bipush #24
    //   3389: iushr
    //   3390: ixor
    //   3391: i2b
    //   3392: bastore
    //   3393: aload #47
    //   3395: iconst_1
    //   3396: aload #38
    //   3398: iload #53
    //   3400: bipush #16
    //   3402: iushr
    //   3403: sipush #255
    //   3406: iand
    //   3407: baload
    //   3408: iload #49
    //   3410: bipush #16
    //   3412: iushr
    //   3413: ixor
    //   3414: i2b
    //   3415: bastore
    //   3416: aload #47
    //   3418: iconst_2
    //   3419: aload #38
    //   3421: iload #52
    //   3423: bipush #8
    //   3425: iushr
    //   3426: sipush #255
    //   3429: iand
    //   3430: baload
    //   3431: iload #49
    //   3433: bipush #8
    //   3435: iushr
    //   3436: ixor
    //   3437: i2b
    //   3438: bastore
    //   3439: aload #47
    //   3441: iconst_3
    //   3442: aload #38
    //   3444: iload #51
    //   3446: sipush #255
    //   3449: iand
    //   3450: baload
    //   3451: iload #49
    //   3453: ixor
    //   3454: i2b
    //   3455: bastore
    //   3456: aload #31
    //   3458: iload #48
    //   3460: iconst_1
    //   3461: iadd
    //   3462: iaload
    //   3463: istore #49
    //   3465: aload #47
    //   3467: iconst_4
    //   3468: aload #38
    //   3470: iload #51
    //   3472: bipush #24
    //   3474: iushr
    //   3475: baload
    //   3476: iload #49
    //   3478: bipush #24
    //   3480: iushr
    //   3481: ixor
    //   3482: i2b
    //   3483: bastore
    //   3484: aload #47
    //   3486: iconst_5
    //   3487: aload #38
    //   3489: iload #50
    //   3491: bipush #16
    //   3493: iushr
    //   3494: sipush #255
    //   3497: iand
    //   3498: baload
    //   3499: iload #49
    //   3501: bipush #16
    //   3503: iushr
    //   3504: ixor
    //   3505: i2b
    //   3506: bastore
    //   3507: aload #47
    //   3509: bipush #6
    //   3511: aload #38
    //   3513: iload #53
    //   3515: bipush #8
    //   3517: iushr
    //   3518: sipush #255
    //   3521: iand
    //   3522: baload
    //   3523: iload #49
    //   3525: bipush #8
    //   3527: iushr
    //   3528: ixor
    //   3529: i2b
    //   3530: bastore
    //   3531: aload #47
    //   3533: bipush #7
    //   3535: aload #38
    //   3537: iload #52
    //   3539: sipush #255
    //   3542: iand
    //   3543: baload
    //   3544: iload #49
    //   3546: ixor
    //   3547: i2b
    //   3548: bastore
    //   3549: aload #31
    //   3551: iload #48
    //   3553: iconst_2
    //   3554: iadd
    //   3555: iaload
    //   3556: istore #49
    //   3558: aload #47
    //   3560: bipush #8
    //   3562: aload #38
    //   3564: iload #52
    //   3566: bipush #24
    //   3568: iushr
    //   3569: baload
    //   3570: iload #49
    //   3572: bipush #24
    //   3574: iushr
    //   3575: ixor
    //   3576: i2b
    //   3577: bastore
    //   3578: aload #47
    //   3580: bipush #9
    //   3582: aload #38
    //   3584: iload #51
    //   3586: bipush #16
    //   3588: iushr
    //   3589: sipush #255
    //   3592: iand
    //   3593: baload
    //   3594: iload #49
    //   3596: bipush #16
    //   3598: iushr
    //   3599: ixor
    //   3600: i2b
    //   3601: bastore
    //   3602: aload #47
    //   3604: bipush #10
    //   3606: aload #38
    //   3608: iload #50
    //   3610: bipush #8
    //   3612: iushr
    //   3613: sipush #255
    //   3616: iand
    //   3617: baload
    //   3618: iload #49
    //   3620: bipush #8
    //   3622: iushr
    //   3623: ixor
    //   3624: i2b
    //   3625: bastore
    //   3626: aload #47
    //   3628: bipush #11
    //   3630: aload #38
    //   3632: iload #53
    //   3634: sipush #255
    //   3637: iand
    //   3638: baload
    //   3639: iload #49
    //   3641: ixor
    //   3642: i2b
    //   3643: bastore
    //   3644: aload #31
    //   3646: iload #48
    //   3648: iconst_3
    //   3649: iadd
    //   3650: iaload
    //   3651: istore #49
    //   3653: aload #47
    //   3655: bipush #12
    //   3657: aload #38
    //   3659: iload #53
    //   3661: bipush #24
    //   3663: iushr
    //   3664: baload
    //   3665: iload #49
    //   3667: bipush #24
    //   3669: iushr
    //   3670: ixor
    //   3671: i2b
    //   3672: bastore
    //   3673: aload #47
    //   3675: bipush #13
    //   3677: aload #38
    //   3679: iload #52
    //   3681: bipush #16
    //   3683: iushr
    //   3684: sipush #255
    //   3687: iand
    //   3688: baload
    //   3689: iload #49
    //   3691: bipush #16
    //   3693: iushr
    //   3694: ixor
    //   3695: i2b
    //   3696: bastore
    //   3697: aload #47
    //   3699: bipush #14
    //   3701: aload #38
    //   3703: iload #51
    //   3705: bipush #8
    //   3707: iushr
    //   3708: sipush #255
    //   3711: iand
    //   3712: baload
    //   3713: iload #49
    //   3715: bipush #8
    //   3717: iushr
    //   3718: ixor
    //   3719: i2b
    //   3720: bastore
    //   3721: aload #47
    //   3723: bipush #15
    //   3725: aload #38
    //   3727: iload #50
    //   3729: sipush #255
    //   3732: iand
    //   3733: baload
    //   3734: iload #49
    //   3736: ixor
    //   3737: i2b
    //   3738: bastore
    //   3739: iconst_0
    //   3740: istore #54
    //   3742: iload #54
    //   3744: bipush #16
    //   3746: if_icmpge -> 3772
    //   3749: aload #44
    //   3751: iload #54
    //   3753: iload #45
    //   3755: bipush #16
    //   3757: imul
    //   3758: iadd
    //   3759: aload #47
    //   3761: iload #54
    //   3763: baload
    //   3764: bastore
    //   3765: iinc #54, 1
    //   3768: iload_2
    //   3769: ifeq -> 3742
    //   3772: iinc #45, 1
    //   3775: iload_2
    //   3776: ifeq -> 2857
    //   3779: aload #44
    //   3781: arraylength
    //   3782: ifle -> 3863
    //   3785: aload #44
    //   3787: aload #44
    //   3789: arraylength
    //   3790: iconst_1
    //   3791: isub
    //   3792: baload
    //   3793: istore #45
    //   3795: iload #45
    //   3797: bipush #16
    //   3799: if_icmple -> 3810
    //   3802: aload #44
    //   3804: astore #36
    //   3806: iload_2
    //   3807: ifeq -> 3863
    //   3810: aload #44
    //   3812: arraylength
    //   3813: iload #45
    //   3815: isub
    //   3816: newarray byte
    //   3818: astore #36
    //   3820: iconst_0
    //   3821: istore #46
    //   3823: iload #46
    //   3825: aload #36
    //   3827: arraylength
    //   3828: if_icmpge -> 3863
    //   3831: iload #46
    //   3833: aload #44
    //   3835: arraylength
    //   3836: if_icmpge -> 3863
    //   3839: aload #36
    //   3841: iload #46
    //   3843: aload #44
    //   3845: iload #46
    //   3847: baload
    //   3848: bastore
    //   3849: iinc #46, 1
    //   3852: iload_2
    //   3853: ifeq -> 3823
    //   3856: goto -> 3863
    //   3859: invokestatic a : (Ljava/lang/Throwable;)Ljava/lang/Throwable;
    //   3862: athrow
    //   3863: aload #36
    //   3865: astore #8
    //   3867: sipush #10758
    //   3870: new java/math/BigInteger
    //   3873: dup
    //   3874: aload #8
    //   3876: invokespecial <init> : ([B)V
    //   3879: invokevirtual abs : ()Ljava/math/BigInteger;
    //   3882: putstatic burp/Zm0d.Zz : Ljava/lang/Object;
    //   3885: sipush #-29178
    //   3888: getstatic burp/Zrye.Zx : Ljava/lang/Object;
    //   3891: checkcast java/math/BigInteger
    //   3894: getstatic burp/Zgtx.Z_ : Ljava/lang/Object;
    //   3897: checkcast java/math/BigInteger
    //   3900: invokevirtual add : (Ljava/math/BigInteger;)Ljava/math/BigInteger;
    //   3903: putstatic burp/Zzii.ZO : Ljava/lang/Object;
    //   3906: invokestatic a : (II)Ljava/lang/String;
    //   3909: iconst_1
    //   3910: ldc burp/Zd1
    //   3912: invokevirtual getClassLoader : ()Ljava/lang/ClassLoader;
    //   3915: invokestatic forName : (Ljava/lang/String;ZLjava/lang/ClassLoader;)Ljava/lang/Class;
    //   3918: invokevirtual getDeclaredFields : ()[Ljava/lang/reflect/Field;
    //   3921: astore #4
    //   3923: aload #4
    //   3925: arraylength
    //   3926: istore #5
    //   3928: iconst_0
    //   3929: istore #6
    //   3931: iload #6
    //   3933: iload #5
    //   3935: if_icmpge -> 4073
    //   3938: aload #4
    //   3940: iload #6
    //   3942: aaload
    //   3943: astore #7
    //   3945: aload #7
    //   3947: invokevirtual getModifiers : ()I
    //   3950: invokestatic isStatic : (I)Z
    //   3953: ifne -> 3963
    //   3956: goto -> 4066
    //   3959: invokestatic a : (Ljava/lang/Throwable;)Ljava/lang/Throwable;
    //   3962: athrow
    //   3963: aload #7
    //   3965: invokevirtual getType : ()Ljava/lang/Class;
    //   3968: astore #8
    //   3970: aload #8
    //   3972: ifnull -> 4053
    //   3975: aload #8
    //   3977: invokevirtual isPrimitive : ()Z
    //   3980: ifne -> 4053
    //   3983: goto -> 3990
    //   3986: invokestatic a : (Ljava/lang/Throwable;)Ljava/lang/Throwable;
    //   3989: athrow
    //   3990: aload #8
    //   3992: invokevirtual getPackage : ()Ljava/lang/Package;
    //   3995: ifnull -> 4053
    //   3998: goto -> 4005
    //   4001: invokestatic a : (Ljava/lang/Throwable;)Ljava/lang/Throwable;
    //   4004: athrow
    //   4005: aload #8
    //   4007: invokevirtual getPackage : ()Ljava/lang/Package;
    //   4010: invokevirtual getName : ()Ljava/lang/String;
    //   4013: ifnull -> 4053
    //   4016: goto -> 4023
    //   4019: invokestatic a : (Ljava/lang/Throwable;)Ljava/lang/Throwable;
    //   4022: athrow
    //   4023: aload #8
    //   4025: invokevirtual getPackage : ()Ljava/lang/Package;
    //   4028: invokevirtual getName : ()Ljava/lang/String;
    //   4031: sipush #10777
    //   4034: sipush #10707
    //   4037: invokestatic a : (II)Ljava/lang/String;
    //   4040: invokevirtual startsWith : (Ljava/lang/String;)Z
    //   4043: ifne -> 4053
    //   4046: goto -> 4053
    //   4049: invokestatic a : (Ljava/lang/Throwable;)Ljava/lang/Throwable;
    //   4052: athrow
    //   4053: aload #7
    //   4055: iconst_1
    //   4056: invokevirtual setAccessible : (Z)V
    //   4059: aload #7
    //   4061: aconst_null
    //   4062: invokevirtual get : (Ljava/lang/Object;)Ljava/lang/Object;
    //   4065: pop
    //   4066: iinc #6, 1
    //   4069: iload_2
    //   4070: ifeq -> 3931
    //   4073: sipush #10755
    //   4076: sipush #19241
    //   4079: invokestatic a : (II)Ljava/lang/String;
    //   4082: invokestatic forName : (Ljava/lang/String;)Ljava/lang/Class;
    //   4085: invokevirtual getDeclaredMethods : ()[Ljava/lang/reflect/Method;
    //   4088: astore #4
    //   4090: aload #4
    //   4092: arraylength
    //   4093: istore #5
    //   4095: iconst_0
    //   4096: istore #6
    //   4098: iload #6
    //   4100: iload #5
    //   4102: if_icmpge -> 4235
    //   4105: aload #4
    //   4107: iload #6
    //   4109: aaload
    //   4110: astore #7
    //   4112: aload #7
    //   4114: invokevirtual getParameterTypes : ()[Ljava/lang/Class;
    //   4117: pop
    //   4118: aload #7
    //   4120: invokevirtual getModifiers : ()I
    //   4123: invokestatic isStatic : (I)Z
    //   4126: ifeq -> 4221
    //   4129: aload #7
    //   4131: invokevirtual getParameterTypes : ()[Ljava/lang/Class;
    //   4134: arraylength
    //   4135: iconst_2
    //   4136: if_icmpne -> 4221
    //   4139: goto -> 4146
    //   4142: invokestatic a : (Ljava/lang/Throwable;)Ljava/lang/Throwable;
    //   4145: athrow
    //   4146: aload #7
    //   4148: invokevirtual getReturnType : ()Ljava/lang/Class;
    //   4151: getstatic java/lang/Void.TYPE : Ljava/lang/Class;
    //   4154: invokevirtual equals : (Ljava/lang/Object;)Z
    //   4157: ifeq -> 4221
    //   4160: goto -> 4167
    //   4163: invokestatic a : (Ljava/lang/Throwable;)Ljava/lang/Throwable;
    //   4166: athrow
    //   4167: aload #7
    //   4169: iconst_1
    //   4170: invokevirtual setAccessible : (Z)V
    //   4173: aload #7
    //   4175: aconst_null
    //   4176: iconst_2
    //   4177: anewarray java/lang/Object
    //   4180: dup
    //   4181: iconst_0
    //   4182: aload_0
    //   4183: aastore
    //   4184: dup
    //   4185: iconst_1
    //   4186: aload_1
    //   4187: ifnonnull -> 4205
    //   4190: goto -> 4197
    //   4193: invokestatic a : (Ljava/lang/Throwable;)Ljava/lang/Throwable;
    //   4196: athrow
    //   4197: aload_1
    //   4198: goto -> 4212
    //   4201: invokestatic a : (Ljava/lang/Throwable;)Ljava/lang/Throwable;
    //   4204: athrow
    //   4205: aload_1
    //   4206: checkcast [B
    //   4209: invokevirtual clone : ()Ljava/lang/Object;
    //   4212: aastore
    //   4213: invokevirtual invoke : (Ljava/lang/Object;[Ljava/lang/Object;)Ljava/lang/Object;
    //   4216: pop
    //   4217: iload_2
    //   4218: ifeq -> 4235
    //   4221: iinc #6, 1
    //   4224: iload_2
    //   4225: ifeq -> 4098
    //   4228: goto -> 4235
    //   4231: invokestatic a : (Ljava/lang/Throwable;)Ljava/lang/Throwable;
    //   4234: athrow
    //   4235: getstatic burp/Zg1l.Zg : Ljava/lang/Object;
    //   4238: checkcast java/math/BigInteger
    //   4241: invokevirtual intValue : ()I
    //   4244: i2l
    //   4245: invokestatic currentTimeMillis : ()J
    //   4248: ladd
    //   4249: getstatic burp/Zbl4.ZW : Ljava/lang/Object;
    //   4252: checkcast java/math/BigInteger
    //   4255: invokevirtual intValue : ()I
    //   4258: i2l
    //   4259: lcmp
    //   4260: ifge -> 4598
    //   4263: sipush #10781
    //   4266: sipush #7056
    //   4269: invokestatic a : (II)Ljava/lang/String;
    //   4272: iconst_1
    //   4273: ldc burp/Zxfu
    //   4275: invokevirtual getClassLoader : ()Ljava/lang/ClassLoader;
    //   4278: invokestatic forName : (Ljava/lang/String;ZLjava/lang/ClassLoader;)Ljava/lang/Class;
    //   4281: invokevirtual getDeclaredFields : ()[Ljava/lang/reflect/Field;
    //   4284: astore #4
    //   4286: aload #4
    //   4288: arraylength
    //   4289: istore #5
    //   4291: iconst_0
    //   4292: istore #6
    //   4294: iload #6
    //   4296: iload #5
    //   4298: if_icmpge -> 4436
    //   4301: aload #4
    //   4303: iload #6
    //   4305: aaload
    //   4306: astore #7
    //   4308: aload #7
    //   4310: invokevirtual getModifiers : ()I
    //   4313: invokestatic isStatic : (I)Z
    //   4316: ifne -> 4326
    //   4319: goto -> 4429
    //   4322: invokestatic a : (Ljava/lang/Throwable;)Ljava/lang/Throwable;
    //   4325: athrow
    //   4326: aload #7
    //   4328: invokevirtual getType : ()Ljava/lang/Class;
    //   4331: astore #8
    //   4333: aload #8
    //   4335: ifnull -> 4416
    //   4338: aload #8
    //   4340: invokevirtual isPrimitive : ()Z
    //   4343: ifne -> 4416
    //   4346: goto -> 4353
    //   4349: invokestatic a : (Ljava/lang/Throwable;)Ljava/lang/Throwable;
    //   4352: athrow
    //   4353: aload #8
    //   4355: invokevirtual getPackage : ()Ljava/lang/Package;
    //   4358: ifnull -> 4416
    //   4361: goto -> 4368
    //   4364: invokestatic a : (Ljava/lang/Throwable;)Ljava/lang/Throwable;
    //   4367: athrow
    //   4368: aload #8
    //   4370: invokevirtual getPackage : ()Ljava/lang/Package;
    //   4373: invokevirtual getName : ()Ljava/lang/String;
    //   4376: ifnull -> 4416
    //   4379: goto -> 4386
    //   4382: invokestatic a : (Ljava/lang/Throwable;)Ljava/lang/Throwable;
    //   4385: athrow
    //   4386: aload #8
    //   4388: invokevirtual getPackage : ()Ljava/lang/Package;
    //   4391: invokevirtual getName : ()Ljava/lang/String;
    //   4394: sipush #10761
    //   4397: sipush #-27140
    //   4400: invokestatic a : (II)Ljava/lang/String;
    //   4403: invokevirtual startsWith : (Ljava/lang/String;)Z
    //   4406: ifne -> 4416
    //   4409: goto -> 4416
    //   4412: invokestatic a : (Ljava/lang/Throwable;)Ljava/lang/Throwable;
    //   4415: athrow
    //   4416: aload #7
    //   4418: iconst_1
    //   4419: invokevirtual setAccessible : (Z)V
    //   4422: aload #7
    //   4424: aconst_null
    //   4425: invokevirtual get : (Ljava/lang/Object;)Ljava/lang/Object;
    //   4428: pop
    //   4429: iinc #6, 1
    //   4432: iload_2
    //   4433: ifeq -> 4294
    //   4436: sipush #10776
    //   4439: sipush #-21210
    //   4442: invokestatic a : (II)Ljava/lang/String;
    //   4445: invokestatic forName : (Ljava/lang/String;)Ljava/lang/Class;
    //   4448: invokevirtual getDeclaredMethods : ()[Ljava/lang/reflect/Method;
    //   4451: astore #4
    //   4453: aload #4
    //   4455: arraylength
    //   4456: istore #5
    //   4458: iconst_0
    //   4459: istore #6
    //   4461: iload #6
    //   4463: iload #5
    //   4465: if_icmpge -> 4598
    //   4468: aload #4
    //   4470: iload #6
    //   4472: aaload
    //   4473: astore #7
    //   4475: aload #7
    //   4477: invokevirtual getParameterTypes : ()[Ljava/lang/Class;
    //   4480: pop
    //   4481: aload #7
    //   4483: invokevirtual getModifiers : ()I
    //   4486: invokestatic isStatic : (I)Z
    //   4489: ifeq -> 4584
    //   4492: aload #7
    //   4494: invokevirtual getParameterTypes : ()[Ljava/lang/Class;
    //   4497: arraylength
    //   4498: iconst_2
    //   4499: if_icmpne -> 4584
    //   4502: goto -> 4509
    //   4505: invokestatic a : (Ljava/lang/Throwable;)Ljava/lang/Throwable;
    //   4508: athrow
    //   4509: aload #7
    //   4511: invokevirtual getReturnType : ()Ljava/lang/Class;
    //   4514: getstatic java/lang/Void.TYPE : Ljava/lang/Class;
    //   4517: invokevirtual equals : (Ljava/lang/Object;)Z
    //   4520: ifeq -> 4584
    //   4523: goto -> 4530
    //   4526: invokestatic a : (Ljava/lang/Throwable;)Ljava/lang/Throwable;
    //   4529: athrow
    //   4530: aload #7
    //   4532: iconst_1
    //   4533: invokevirtual setAccessible : (Z)V
    //   4536: aload #7
    //   4538: aconst_null
    //   4539: iconst_2
    //   4540: anewarray java/lang/Object
    //   4543: dup
    //   4544: iconst_0
    //   4545: aload_0
    //   4546: aastore
    //   4547: dup
    //   4548: iconst_1
    //   4549: aload_1
    //   4550: ifnonnull -> 4568
    //   4553: goto -> 4560
    //   4556: invokestatic a : (Ljava/lang/Throwable;)Ljava/lang/Throwable;
    //   4559: athrow
    //   4560: aload_1
    //   4561: goto -> 4575
    //   4564: invokestatic a : (Ljava/lang/Throwable;)Ljava/lang/Throwable;
    //   4567: athrow
    //   4568: aload_1
    //   4569: checkcast [B
    //   4572: invokevirtual clone : ()Ljava/lang/Object;
    //   4575: aastore
    //   4576: invokevirtual invoke : (Ljava/lang/Object;[Ljava/lang/Object;)Ljava/lang/Object;
    //   4579: pop
    //   4580: iload_2
    //   4581: ifeq -> 4598
    //   4584: iinc #6, 1
    //   4587: iload_2
    //   4588: ifeq -> 4461
    //   4591: goto -> 4598
    //   4594: invokestatic a : (Ljava/lang/Throwable;)Ljava/lang/Throwable;
    //   4597: athrow
    //   4598: getstatic burp/Zm3x.ZM : Ljava/lang/Object;
    //   4601: checkcast java/math/BigInteger
    //   4604: invokevirtual toByteArray : ()[B
    //   4607: astore #4
    //   4609: bipush #64
    //   4611: newarray byte
    //   4613: dup
    //   4614: iconst_0
    //   4615: bipush #-128
    //   4617: bastore
    //   4618: dup
    //   4619: iconst_1
    //   4620: iconst_0
    //   4621: bastore
    //   4622: dup
    //   4623: iconst_2
    //   4624: iconst_0
    //   4625: bastore
    //   4626: dup
    //   4627: iconst_3
    //   4628: iconst_0
    //   4629: bastore
    //   4630: dup
    //   4631: iconst_4
    //   4632: iconst_0
    //   4633: bastore
    //   4634: dup
    //   4635: iconst_5
    //   4636: iconst_0
    //   4637: bastore
    //   4638: dup
    //   4639: bipush #6
    //   4641: iconst_0
    //   4642: bastore
    //   4643: dup
    //   4644: bipush #7
    //   4646: iconst_0
    //   4647: bastore
    //   4648: dup
    //   4649: bipush #8
    //   4651: iconst_0
    //   4652: bastore
    //   4653: dup
    //   4654: bipush #9
    //   4656: iconst_0
    //   4657: bastore
    //   4658: dup
    //   4659: bipush #10
    //   4661: iconst_0
    //   4662: bastore
    //   4663: dup
    //   4664: bipush #11
    //   4666: iconst_0
    //   4667: bastore
    //   4668: dup
    //   4669: bipush #12
    //   4671: iconst_0
    //   4672: bastore
    //   4673: dup
    //   4674: bipush #13
    //   4676: iconst_0
    //   4677: bastore
    //   4678: dup
    //   4679: bipush #14
    //   4681: iconst_0
    //   4682: bastore
    //   4683: dup
    //   4684: bipush #15
    //   4686: iconst_0
    //   4687: bastore
    //   4688: dup
    //   4689: bipush #16
    //   4691: iconst_0
    //   4692: bastore
    //   4693: dup
    //   4694: bipush #17
    //   4696: iconst_0
    //   4697: bastore
    //   4698: dup
    //   4699: bipush #18
    //   4701: iconst_0
    //   4702: bastore
    //   4703: dup
    //   4704: bipush #19
    //   4706: iconst_0
    //   4707: bastore
    //   4708: dup
    //   4709: bipush #20
    //   4711: iconst_0
    //   4712: bastore
    //   4713: dup
    //   4714: bipush #21
    //   4716: iconst_0
    //   4717: bastore
    //   4718: dup
    //   4719: bipush #22
    //   4721: iconst_0
    //   4722: bastore
    //   4723: dup
    //   4724: bipush #23
    //   4726: iconst_0
    //   4727: bastore
    //   4728: dup
    //   4729: bipush #24
    //   4731: iconst_0
    //   4732: bastore
    //   4733: dup
    //   4734: bipush #25
    //   4736: iconst_0
    //   4737: bastore
    //   4738: dup
    //   4739: bipush #26
    //   4741: iconst_0
    //   4742: bastore
    //   4743: dup
    //   4744: bipush #27
    //   4746: iconst_0
    //   4747: bastore
    //   4748: dup
    //   4749: bipush #28
    //   4751: iconst_0
    //   4752: bastore
    //   4753: dup
    //   4754: bipush #29
    //   4756: iconst_0
    //   4757: bastore
    //   4758: dup
    //   4759: bipush #30
    //   4761: iconst_0
    //   4762: bastore
    //   4763: dup
    //   4764: bipush #31
    //   4766: iconst_0
    //   4767: bastore
    //   4768: dup
    //   4769: bipush #32
    //   4771: iconst_0
    //   4772: bastore
    //   4773: dup
    //   4774: bipush #33
    //   4776: iconst_0
    //   4777: bastore
    //   4778: dup
    //   4779: bipush #34
    //   4781: iconst_0
    //   4782: bastore
    //   4783: dup
    //   4784: bipush #35
    //   4786: iconst_0
    //   4787: bastore
    //   4788: dup
    //   4789: bipush #36
    //   4791: iconst_0
    //   4792: bastore
    //   4793: dup
    //   4794: bipush #37
    //   4796: iconst_0
    //   4797: bastore
    //   4798: dup
    //   4799: bipush #38
    //   4801: iconst_0
    //   4802: bastore
    //   4803: dup
    //   4804: bipush #39
    //   4806: iconst_0
    //   4807: bastore
    //   4808: dup
    //   4809: bipush #40
    //   4811: iconst_0
    //   4812: bastore
    //   4813: dup
    //   4814: bipush #41
    //   4816: iconst_0
    //   4817: bastore
    //   4818: dup
    //   4819: bipush #42
    //   4821: iconst_0
    //   4822: bastore
    //   4823: dup
    //   4824: bipush #43
    //   4826: iconst_0
    //   4827: bastore
    //   4828: dup
    //   4829: bipush #44
    //   4831: iconst_0
    //   4832: bastore
    //   4833: dup
    //   4834: bipush #45
    //   4836: iconst_0
    //   4837: bastore
    //   4838: dup
    //   4839: bipush #46
    //   4841: iconst_0
    //   4842: bastore
    //   4843: dup
    //   4844: bipush #47
    //   4846: iconst_0
    //   4847: bastore
    //   4848: dup
    //   4849: bipush #48
    //   4851: iconst_0
    //   4852: bastore
    //   4853: dup
    //   4854: bipush #49
    //   4856: iconst_0
    //   4857: bastore
    //   4858: dup
    //   4859: bipush #50
    //   4861: iconst_0
    //   4862: bastore
    //   4863: dup
    //   4864: bipush #51
    //   4866: iconst_0
    //   4867: bastore
    //   4868: dup
    //   4869: bipush #52
    //   4871: iconst_0
    //   4872: bastore
    //   4873: dup
    //   4874: bipush #53
    //   4876: iconst_0
    //   4877: bastore
    //   4878: dup
    //   4879: bipush #54
    //   4881: iconst_0
    //   4882: bastore
    //   4883: dup
    //   4884: bipush #55
    //   4886: iconst_0
    //   4887: bastore
    //   4888: dup
    //   4889: bipush #56
    //   4891: iconst_0
    //   4892: bastore
    //   4893: dup
    //   4894: bipush #57
    //   4896: iconst_0
    //   4897: bastore
    //   4898: dup
    //   4899: bipush #58
    //   4901: iconst_0
    //   4902: bastore
    //   4903: dup
    //   4904: bipush #59
    //   4906: iconst_0
    //   4907: bastore
    //   4908: dup
    //   4909: bipush #60
    //   4911: iconst_0
    //   4912: bastore
    //   4913: dup
    //   4914: bipush #61
    //   4916: iconst_0
    //   4917: bastore
    //   4918: dup
    //   4919: bipush #62
    //   4921: iconst_0
    //   4922: bastore
    //   4923: dup
    //   4924: bipush #63
    //   4926: iconst_0
    //   4927: bastore
    //   4928: astore #6
    //   4930: bipush #64
    //   4932: newarray int
    //   4934: dup
    //   4935: iconst_0
    //   4936: ldc 1116352408
    //   4938: iastore
    //   4939: dup
    //   4940: iconst_1
    //   4941: ldc 1899447441
    //   4943: iastore
    //   4944: dup
    //   4945: iconst_2
    //   4946: ldc -1245643825
    //   4948: iastore
    //   4949: dup
    //   4950: iconst_3
    //   4951: ldc -373957723
    //   4953: iastore
    //   4954: dup
    //   4955: iconst_4
    //   4956: ldc 961987163
    //   4958: iastore
    //   4959: dup
    //   4960: iconst_5
    //   4961: ldc 1508970993
    //   4963: iastore
    //   4964: dup
    //   4965: bipush #6
    //   4967: ldc -1841331548
    //   4969: iastore
    //   4970: dup
    //   4971: bipush #7
    //   4973: ldc -1424204075
    //   4975: iastore
    //   4976: dup
    //   4977: bipush #8
    //   4979: ldc -670586216
    //   4981: iastore
    //   4982: dup
    //   4983: bipush #9
    //   4985: ldc 310598401
    //   4987: iastore
    //   4988: dup
    //   4989: bipush #10
    //   4991: ldc 607225278
    //   4993: iastore
    //   4994: dup
    //   4995: bipush #11
    //   4997: ldc 1426881987
    //   4999: iastore
    //   5000: dup
    //   5001: bipush #12
    //   5003: ldc 1925078388
    //   5005: iastore
    //   5006: dup
    //   5007: bipush #13
    //   5009: ldc -2132889090
    //   5011: iastore
    //   5012: dup
    //   5013: bipush #14
    //   5015: ldc -1680079193
    //   5017: iastore
    //   5018: dup
    //   5019: bipush #15
    //   5021: ldc -1046744716
    //   5023: iastore
    //   5024: dup
    //   5025: bipush #16
    //   5027: ldc -459576895
    //   5029: iastore
    //   5030: dup
    //   5031: bipush #17
    //   5033: ldc -272742522
    //   5035: iastore
    //   5036: dup
    //   5037: bipush #18
    //   5039: ldc 264347078
    //   5041: iastore
    //   5042: dup
    //   5043: bipush #19
    //   5045: ldc 604807628
    //   5047: iastore
    //   5048: dup
    //   5049: bipush #20
    //   5051: ldc 770255983
    //   5053: iastore
    //   5054: dup
    //   5055: bipush #21
    //   5057: ldc 1249150122
    //   5059: iastore
    //   5060: dup
    //   5061: bipush #22
    //   5063: ldc 1555081692
    //   5065: iastore
    //   5066: dup
    //   5067: bipush #23
    //   5069: ldc 1996064986
    //   5071: iastore
    //   5072: dup
    //   5073: bipush #24
    //   5075: ldc -1740746414
    //   5077: iastore
    //   5078: dup
    //   5079: bipush #25
    //   5081: ldc -1473132947
    //   5083: iastore
    //   5084: dup
    //   5085: bipush #26
    //   5087: ldc -1341970488
    //   5089: iastore
    //   5090: dup
    //   5091: bipush #27
    //   5093: ldc -1084653625
    //   5095: iastore
    //   5096: dup
    //   5097: bipush #28
    //   5099: ldc -958395405
    //   5101: iastore
    //   5102: dup
    //   5103: bipush #29
    //   5105: ldc -710438585
    //   5107: iastore
    //   5108: dup
    //   5109: bipush #30
    //   5111: ldc 113926993
    //   5113: iastore
    //   5114: dup
    //   5115: bipush #31
    //   5117: ldc 338241895
    //   5119: iastore
    //   5120: dup
    //   5121: bipush #32
    //   5123: ldc 666307205
    //   5125: iastore
    //   5126: dup
    //   5127: bipush #33
    //   5129: ldc 773529912
    //   5131: iastore
    //   5132: dup
    //   5133: bipush #34
    //   5135: ldc 1294757372
    //   5137: iastore
    //   5138: dup
    //   5139: bipush #35
    //   5141: ldc 1396182291
    //   5143: iastore
    //   5144: dup
    //   5145: bipush #36
    //   5147: ldc 1695183700
    //   5149: iastore
    //   5150: dup
    //   5151: bipush #37
    //   5153: ldc 1986661051
    //   5155: iastore
    //   5156: dup
    //   5157: bipush #38
    //   5159: ldc -2117940946
    //   5161: iastore
    //   5162: dup
    //   5163: bipush #39
    //   5165: ldc -1838011259
    //   5167: iastore
    //   5168: dup
    //   5169: bipush #40
    //   5171: ldc -1564481375
    //   5173: iastore
    //   5174: dup
    //   5175: bipush #41
    //   5177: ldc -1474664885
    //   5179: iastore
    //   5180: dup
    //   5181: bipush #42
    //   5183: ldc -1035236496
    //   5185: iastore
    //   5186: dup
    //   5187: bipush #43
    //   5189: ldc -949202525
    //   5191: iastore
    //   5192: dup
    //   5193: bipush #44
    //   5195: ldc -778901479
    //   5197: iastore
    //   5198: dup
    //   5199: bipush #45
    //   5201: ldc -694614492
    //   5203: iastore
    //   5204: dup
    //   5205: bipush #46
    //   5207: ldc -200395387
    //   5209: iastore
    //   5210: dup
    //   5211: bipush #47
    //   5213: ldc 275423344
    //   5215: iastore
    //   5216: dup
    //   5217: bipush #48
    //   5219: ldc 430227734
    //   5221: iastore
    //   5222: dup
    //   5223: bipush #49
    //   5225: ldc 506948616
    //   5227: iastore
    //   5228: dup
    //   5229: bipush #50
    //   5231: ldc 659060556
    //   5233: iastore
    //   5234: dup
    //   5235: bipush #51
    //   5237: ldc 883997877
    //   5239: iastore
    //   5240: dup
    //   5241: bipush #52
    //   5243: ldc 958139571
    //   5245: iastore
    //   5246: dup
    //   5247: bipush #53
    //   5249: ldc 1322822218
    //   5251: iastore
    //   5252: dup
    //   5253: bipush #54
    //   5255: ldc 1537002063
    //   5257: iastore
    //   5258: dup
    //   5259: bipush #55
    //   5261: ldc 1747873779
    //   5263: iastore
    //   5264: dup
    //   5265: bipush #56
    //   5267: ldc 1955562222
    //   5269: iastore
    //   5270: dup
    //   5271: bipush #57
    //   5273: ldc 2024104815
    //   5275: iastore
    //   5276: dup
    //   5277: bipush #58
    //   5279: ldc -2067236844
    //   5281: iastore
    //   5282: dup
    //   5283: bipush #59
    //   5285: ldc -1933114872
    //   5287: iastore
    //   5288: dup
    //   5289: bipush #60
    //   5291: ldc -1866530822
    //   5293: iastore
    //   5294: dup
    //   5295: bipush #61
    //   5297: ldc -1538233109
    //   5299: iastore
    //   5300: dup
    //   5301: bipush #62
    //   5303: ldc -1090935817
    //   5305: iastore
    //   5306: dup
    //   5307: bipush #63
    //   5309: ldc -965641998
    //   5311: iastore
    //   5312: astore #7
    //   5314: iconst_2
    //   5315: newarray int
    //   5317: dup
    //   5318: iconst_0
    //   5319: iconst_0
    //   5320: iastore
    //   5321: dup
    //   5322: iconst_1
    //   5323: iconst_0
    //   5324: iastore
    //   5325: astore #8
    //   5327: bipush #8
    //   5329: newarray int
    //   5331: dup
    //   5332: iconst_0
    //   5333: ldc 1779033703
    //   5335: iastore
    //   5336: dup
    //   5337: iconst_1
    //   5338: ldc -1150833019
    //   5340: iastore
    //   5341: dup
    //   5342: iconst_2
    //   5343: ldc 1013904242
    //   5345: iastore
    //   5346: dup
    //   5347: iconst_3
    //   5348: ldc -1521486534
    //   5350: iastore
    //   5351: dup
    //   5352: iconst_4
    //   5353: ldc 1359893119
    //   5355: iastore
    //   5356: dup
    //   5357: iconst_5
    //   5358: ldc -1694144372
    //   5360: iastore
    //   5361: dup
    //   5362: bipush #6
    //   5364: ldc 528734635
    //   5366: iastore
    //   5367: dup
    //   5368: bipush #7
    //   5370: ldc 1541459225
    //   5372: iastore
    //   5373: astore #9
    //   5375: bipush #64
    //   5377: newarray byte
    //   5379: astore #10
    //   5381: bipush #64
    //   5383: newarray byte
    //   5385: astore #11
    //   5387: aload #4
    //   5389: arraylength
    //   5390: istore #12
    //   5392: aload #8
    //   5394: iconst_0
    //   5395: iaload
    //   5396: bipush #63
    //   5398: iand
    //   5399: istore #13
    //   5401: aload #8
    //   5403: iconst_0
    //   5404: dup2
    //   5405: iaload
    //   5406: iload #12
    //   5408: iadd
    //   5409: iastore
    //   5410: aload #8
    //   5412: iconst_0
    //   5413: dup2
    //   5414: iaload
    //   5415: iconst_m1
    //   5416: iand
    //   5417: iastore
    //   5418: aload #8
    //   5420: iconst_0
    //   5421: iaload
    //   5422: iload #12
    //   5424: if_icmpge -> 5442
    //   5427: aload #8
    //   5429: iconst_1
    //   5430: dup2
    //   5431: iaload
    //   5432: iconst_1
    //   5433: iadd
    //   5434: iastore
    //   5435: goto -> 5442
    //   5438: invokestatic a : (Ljava/lang/Throwable;)Ljava/lang/Throwable;
    //   5441: athrow
    //   5442: iconst_0
    //   5443: istore #14
    //   5445: iload #12
    //   5447: bipush #64
    //   5449: if_icmplt -> 6059
    //   5452: iconst_0
    //   5453: istore #15
    //   5455: iload #15
    //   5457: bipush #64
    //   5459: if_icmpge -> 5482
    //   5462: aload #11
    //   5464: iload #15
    //   5466: aload #4
    //   5468: iload #14
    //   5470: iload #15
    //   5472: iadd
    //   5473: baload
    //   5474: bastore
    //   5475: iinc #15, 1
    //   5478: iload_2
    //   5479: ifeq -> 5455
    //   5482: bipush #64
    //   5484: newarray int
    //   5486: astore #15
    //   5488: bipush #8
    //   5490: newarray int
    //   5492: astore #16
    //   5494: iconst_0
    //   5495: istore #17
    //   5497: iload #17
    //   5499: bipush #8
    //   5501: if_icmpge -> 5521
    //   5504: aload #16
    //   5506: iload #17
    //   5508: aload #9
    //   5510: iload #17
    //   5512: iaload
    //   5513: iastore
    //   5514: iinc #17, 1
    //   5517: iload_2
    //   5518: ifeq -> 5497
    //   5521: iconst_0
    //   5522: istore #17
    //   5524: iload #17
    //   5526: bipush #64
    //   5528: if_icmpge -> 6019
    //   5531: iload #17
    //   5533: bipush #16
    //   5535: if_icmpge -> 5616
    //   5538: aload #15
    //   5540: iload #17
    //   5542: aload #11
    //   5544: iconst_4
    //   5545: iload #17
    //   5547: imul
    //   5548: baload
    //   5549: sipush #255
    //   5552: iand
    //   5553: bipush #24
    //   5555: ishl
    //   5556: aload #11
    //   5558: iconst_4
    //   5559: iload #17
    //   5561: imul
    //   5562: iconst_1
    //   5563: iadd
    //   5564: baload
    //   5565: sipush #255
    //   5568: iand
    //   5569: bipush #16
    //   5571: ishl
    //   5572: ior
    //   5573: aload #11
    //   5575: iconst_4
    //   5576: iload #17
    //   5578: imul
    //   5579: iconst_2
    //   5580: iadd
    //   5581: baload
    //   5582: sipush #255
    //   5585: iand
    //   5586: bipush #8
    //   5588: ishl
    //   5589: ior
    //   5590: aload #11
    //   5592: iconst_4
    //   5593: iload #17
    //   5595: imul
    //   5596: iconst_3
    //   5597: iadd
    //   5598: baload
    //   5599: sipush #255
    //   5602: iand
    //   5603: ior
    //   5604: iastore
    //   5605: iload_2
    //   5606: ifeq -> 5759
    //   5609: goto -> 5616
    //   5612: invokestatic a : (Ljava/lang/Throwable;)Ljava/lang/Throwable;
    //   5615: athrow
    //   5616: aload #15
    //   5618: iload #17
    //   5620: aload #15
    //   5622: iload #17
    //   5624: iconst_2
    //   5625: isub
    //   5626: iaload
    //   5627: bipush #17
    //   5629: iushr
    //   5630: aload #15
    //   5632: iload #17
    //   5634: iconst_2
    //   5635: isub
    //   5636: iaload
    //   5637: bipush #15
    //   5639: ishl
    //   5640: ior
    //   5641: aload #15
    //   5643: iload #17
    //   5645: iconst_2
    //   5646: isub
    //   5647: iaload
    //   5648: bipush #19
    //   5650: iushr
    //   5651: aload #15
    //   5653: iload #17
    //   5655: iconst_2
    //   5656: isub
    //   5657: iaload
    //   5658: bipush #13
    //   5660: ishl
    //   5661: ior
    //   5662: ixor
    //   5663: aload #15
    //   5665: iload #17
    //   5667: iconst_2
    //   5668: isub
    //   5669: iaload
    //   5670: bipush #10
    //   5672: iushr
    //   5673: ixor
    //   5674: aload #15
    //   5676: iload #17
    //   5678: bipush #7
    //   5680: isub
    //   5681: iaload
    //   5682: iadd
    //   5683: aload #15
    //   5685: iload #17
    //   5687: bipush #15
    //   5689: isub
    //   5690: iaload
    //   5691: bipush #7
    //   5693: iushr
    //   5694: aload #15
    //   5696: iload #17
    //   5698: bipush #15
    //   5700: isub
    //   5701: iaload
    //   5702: bipush #25
    //   5704: ishl
    //   5705: ior
    //   5706: aload #15
    //   5708: iload #17
    //   5710: bipush #15
    //   5712: isub
    //   5713: iaload
    //   5714: bipush #18
    //   5716: iushr
    //   5717: aload #15
    //   5719: iload #17
    //   5721: bipush #15
    //   5723: isub
    //   5724: iaload
    //   5725: bipush #14
    //   5727: ishl
    //   5728: ior
    //   5729: ixor
    //   5730: aload #15
    //   5732: iload #17
    //   5734: bipush #15
    //   5736: isub
    //   5737: iaload
    //   5738: iconst_3
    //   5739: iushr
    //   5740: ixor
    //   5741: iadd
    //   5742: aload #15
    //   5744: iload #17
    //   5746: bipush #16
    //   5748: isub
    //   5749: iaload
    //   5750: iadd
    //   5751: iastore
    //   5752: goto -> 5759
    //   5755: invokestatic a : (Ljava/lang/Throwable;)Ljava/lang/Throwable;
    //   5758: athrow
    //   5759: aload #16
    //   5761: bipush #7
    //   5763: iaload
    //   5764: aload #16
    //   5766: iconst_4
    //   5767: iaload
    //   5768: bipush #6
    //   5770: iushr
    //   5771: aload #16
    //   5773: iconst_4
    //   5774: iaload
    //   5775: bipush #26
    //   5777: ishl
    //   5778: ior
    //   5779: aload #16
    //   5781: iconst_4
    //   5782: iaload
    //   5783: bipush #11
    //   5785: iushr
    //   5786: aload #16
    //   5788: iconst_4
    //   5789: iaload
    //   5790: bipush #21
    //   5792: ishl
    //   5793: ior
    //   5794: ixor
    //   5795: aload #16
    //   5797: iconst_4
    //   5798: iaload
    //   5799: bipush #25
    //   5801: iushr
    //   5802: aload #16
    //   5804: iconst_4
    //   5805: iaload
    //   5806: bipush #7
    //   5808: ishl
    //   5809: ior
    //   5810: ixor
    //   5811: iadd
    //   5812: aload #16
    //   5814: bipush #6
    //   5816: iaload
    //   5817: aload #16
    //   5819: iconst_4
    //   5820: iaload
    //   5821: aload #16
    //   5823: iconst_5
    //   5824: iaload
    //   5825: aload #16
    //   5827: bipush #6
    //   5829: iaload
    //   5830: ixor
    //   5831: iand
    //   5832: ixor
    //   5833: iadd
    //   5834: aload #7
    //   5836: iload #17
    //   5838: iaload
    //   5839: iadd
    //   5840: aload #15
    //   5842: iload #17
    //   5844: iaload
    //   5845: iadd
    //   5846: istore #18
    //   5848: aload #16
    //   5850: iconst_0
    //   5851: iaload
    //   5852: iconst_2
    //   5853: iushr
    //   5854: aload #16
    //   5856: iconst_0
    //   5857: iaload
    //   5858: bipush #30
    //   5860: ishl
    //   5861: ior
    //   5862: aload #16
    //   5864: iconst_0
    //   5865: iaload
    //   5866: bipush #13
    //   5868: iushr
    //   5869: aload #16
    //   5871: iconst_0
    //   5872: iaload
    //   5873: bipush #19
    //   5875: ishl
    //   5876: ior
    //   5877: ixor
    //   5878: aload #16
    //   5880: iconst_0
    //   5881: iaload
    //   5882: bipush #22
    //   5884: iushr
    //   5885: aload #16
    //   5887: iconst_0
    //   5888: iaload
    //   5889: bipush #10
    //   5891: ishl
    //   5892: ior
    //   5893: ixor
    //   5894: aload #16
    //   5896: iconst_0
    //   5897: iaload
    //   5898: aload #16
    //   5900: iconst_1
    //   5901: iaload
    //   5902: iand
    //   5903: aload #16
    //   5905: iconst_2
    //   5906: iaload
    //   5907: aload #16
    //   5909: iconst_0
    //   5910: iaload
    //   5911: aload #16
    //   5913: iconst_1
    //   5914: iaload
    //   5915: ior
    //   5916: iand
    //   5917: ior
    //   5918: iadd
    //   5919: istore #19
    //   5921: aload #16
    //   5923: iconst_3
    //   5924: dup2
    //   5925: iaload
    //   5926: iload #18
    //   5928: iadd
    //   5929: iastore
    //   5930: aload #16
    //   5932: bipush #7
    //   5934: iload #18
    //   5936: iload #19
    //   5938: iadd
    //   5939: iastore
    //   5940: aload #16
    //   5942: bipush #7
    //   5944: iaload
    //   5945: istore #18
    //   5947: aload #16
    //   5949: bipush #7
    //   5951: aload #16
    //   5953: bipush #6
    //   5955: iaload
    //   5956: iastore
    //   5957: aload #16
    //   5959: bipush #6
    //   5961: aload #16
    //   5963: iconst_5
    //   5964: iaload
    //   5965: iastore
    //   5966: aload #16
    //   5968: iconst_5
    //   5969: aload #16
    //   5971: iconst_4
    //   5972: iaload
    //   5973: iastore
    //   5974: aload #16
    //   5976: iconst_4
    //   5977: aload #16
    //   5979: iconst_3
    //   5980: iaload
    //   5981: iastore
    //   5982: aload #16
    //   5984: iconst_3
    //   5985: aload #16
    //   5987: iconst_2
    //   5988: iaload
    //   5989: iastore
    //   5990: aload #16
    //   5992: iconst_2
    //   5993: aload #16
    //   5995: iconst_1
    //   5996: iaload
    //   5997: iastore
    //   5998: aload #16
    //   6000: iconst_1
    //   6001: aload #16
    //   6003: iconst_0
    //   6004: iaload
    //   6005: iastore
    //   6006: aload #16
    //   6008: iconst_0
    //   6009: iload #18
    //   6011: iastore
    //   6012: iinc #17, 1
    //   6015: iload_2
    //   6016: ifeq -> 5524
    //   6019: iconst_0
    //   6020: istore #17
    //   6022: iload #17
    //   6024: bipush #8
    //   6026: if_icmpge -> 6049
    //   6029: aload #9
    //   6031: iload #17
    //   6033: dup2
    //   6034: iaload
    //   6035: aload #16
    //   6037: iload #17
    //   6039: iaload
    //   6040: iadd
    //   6041: iastore
    //   6042: iinc #17, 1
    //   6045: iload_2
    //   6046: ifeq -> 6022
    //   6049: iinc #14, 64
    //   6052: iinc #12, -64
    //   6055: iload_2
    //   6056: ifeq -> 5445
    //   6059: iload #12
    //   6061: ifle -> 6097
    //   6064: iconst_0
    //   6065: istore #15
    //   6067: iload #15
    //   6069: iload #12
    //   6071: if_icmpge -> 6097
    //   6074: aload #10
    //   6076: iload #13
    //   6078: iload #15
    //   6080: iadd
    //   6081: aload #4
    //   6083: iload #14
    //   6085: iload #15
    //   6087: iadd
    //   6088: baload
    //   6089: bastore
    //   6090: iinc #15, 1
    //   6093: iload_2
    //   6094: ifeq -> 6067
    //   6097: aload #8
    //   6099: iconst_0
    //   6100: iaload
    //   6101: bipush #29
    //   6103: iushr
    //   6104: aload #8
    //   6106: iconst_1
    //   6107: iaload
    //   6108: iconst_3
    //   6109: ishl
    //   6110: ior
    //   6111: istore #15
    //   6113: aload #8
    //   6115: iconst_0
    //   6116: iaload
    //   6117: iconst_3
    //   6118: ishl
    //   6119: istore #16
    //   6121: aload #8
    //   6123: iconst_0
    //   6124: iaload
    //   6125: bipush #63
    //   6127: iand
    //   6128: istore #17
    //   6130: iload #17
    //   6132: bipush #56
    //   6134: if_icmpge -> 6149
    //   6137: bipush #56
    //   6139: iload #17
    //   6141: isub
    //   6142: goto -> 6154
    //   6145: invokestatic a : (Ljava/lang/Throwable;)Ljava/lang/Throwable;
    //   6148: athrow
    //   6149: bipush #120
    //   6151: iload #17
    //   6153: isub
    //   6154: istore #18
    //   6156: aload #8
    //   6158: iconst_0
    //   6159: iaload
    //   6160: bipush #63
    //   6162: iand
    //   6163: istore #13
    //   6165: bipush #64
    //   6167: iload #13
    //   6169: isub
    //   6170: istore #19
    //   6172: aload #8
    //   6174: iconst_0
    //   6175: dup2
    //   6176: iaload
    //   6177: iload #18
    //   6179: iadd
    //   6180: iastore
    //   6181: aload #8
    //   6183: iconst_0
    //   6184: dup2
    //   6185: iaload
    //   6186: iconst_m1
    //   6187: iand
    //   6188: iastore
    //   6189: aload #8
    //   6191: iconst_0
    //   6192: iaload
    //   6193: iload #18
    //   6195: if_icmpge -> 6213
    //   6198: aload #8
    //   6200: iconst_1
    //   6201: dup2
    //   6202: iaload
    //   6203: iconst_1
    //   6204: iadd
    //   6205: iastore
    //   6206: goto -> 6213
    //   6209: invokestatic a : (Ljava/lang/Throwable;)Ljava/lang/Throwable;
    //   6212: athrow
    //   6213: iconst_0
    //   6214: istore #14
    //   6216: iload #13
    //   6218: ifle -> 6849
    //   6221: iload #18
    //   6223: iload #19
    //   6225: if_icmplt -> 6849
    //   6228: goto -> 6235
    //   6231: invokestatic a : (Ljava/lang/Throwable;)Ljava/lang/Throwable;
    //   6234: athrow
    //   6235: iconst_0
    //   6236: istore #20
    //   6238: iload #20
    //   6240: iload #19
    //   6242: if_icmpge -> 6265
    //   6245: aload #10
    //   6247: iload #13
    //   6249: iload #20
    //   6251: iadd
    //   6252: aload #6
    //   6254: iload #20
    //   6256: baload
    //   6257: bastore
    //   6258: iinc #20, 1
    //   6261: iload_2
    //   6262: ifeq -> 6238
    //   6265: bipush #64
    //   6267: newarray int
    //   6269: astore #20
    //   6271: bipush #8
    //   6273: newarray int
    //   6275: astore #21
    //   6277: iconst_0
    //   6278: istore #22
    //   6280: iload #22
    //   6282: bipush #8
    //   6284: if_icmpge -> 6304
    //   6287: aload #21
    //   6289: iload #22
    //   6291: aload #9
    //   6293: iload #22
    //   6295: iaload
    //   6296: iastore
    //   6297: iinc #22, 1
    //   6300: iload_2
    //   6301: ifeq -> 6280
    //   6304: iconst_0
    //   6305: istore #22
    //   6307: iload #22
    //   6309: bipush #64
    //   6311: if_icmpge -> 6802
    //   6314: iload #22
    //   6316: bipush #16
    //   6318: if_icmpge -> 6399
    //   6321: aload #20
    //   6323: iload #22
    //   6325: aload #10
    //   6327: iconst_4
    //   6328: iload #22
    //   6330: imul
    //   6331: baload
    //   6332: sipush #255
    //   6335: iand
    //   6336: bipush #24
    //   6338: ishl
    //   6339: aload #10
    //   6341: iconst_4
    //   6342: iload #22
    //   6344: imul
    //   6345: iconst_1
    //   6346: iadd
    //   6347: baload
    //   6348: sipush #255
    //   6351: iand
    //   6352: bipush #16
    //   6354: ishl
    //   6355: ior
    //   6356: aload #10
    //   6358: iconst_4
    //   6359: iload #22
    //   6361: imul
    //   6362: iconst_2
    //   6363: iadd
    //   6364: baload
    //   6365: sipush #255
    //   6368: iand
    //   6369: bipush #8
    //   6371: ishl
    //   6372: ior
    //   6373: aload #10
    //   6375: iconst_4
    //   6376: iload #22
    //   6378: imul
    //   6379: iconst_3
    //   6380: iadd
    //   6381: baload
    //   6382: sipush #255
    //   6385: iand
    //   6386: ior
    //   6387: iastore
    //   6388: iload_2
    //   6389: ifeq -> 6542
    //   6392: goto -> 6399
    //   6395: invokestatic a : (Ljava/lang/Throwable;)Ljava/lang/Throwable;
    //   6398: athrow
    //   6399: aload #20
    //   6401: iload #22
    //   6403: aload #20
    //   6405: iload #22
    //   6407: iconst_2
    //   6408: isub
    //   6409: iaload
    //   6410: bipush #17
    //   6412: iushr
    //   6413: aload #20
    //   6415: iload #22
    //   6417: iconst_2
    //   6418: isub
    //   6419: iaload
    //   6420: bipush #15
    //   6422: ishl
    //   6423: ior
    //   6424: aload #20
    //   6426: iload #22
    //   6428: iconst_2
    //   6429: isub
    //   6430: iaload
    //   6431: bipush #19
    //   6433: iushr
    //   6434: aload #20
    //   6436: iload #22
    //   6438: iconst_2
    //   6439: isub
    //   6440: iaload
    //   6441: bipush #13
    //   6443: ishl
    //   6444: ior
    //   6445: ixor
    //   6446: aload #20
    //   6448: iload #22
    //   6450: iconst_2
    //   6451: isub
    //   6452: iaload
    //   6453: bipush #10
    //   6455: iushr
    //   6456: ixor
    //   6457: aload #20
    //   6459: iload #22
    //   6461: bipush #7
    //   6463: isub
    //   6464: iaload
    //   6465: iadd
    //   6466: aload #20
    //   6468: iload #22
    //   6470: bipush #15
    //   6472: isub
    //   6473: iaload
    //   6474: bipush #7
    //   6476: iushr
    //   6477: aload #20
    //   6479: iload #22
    //   6481: bipush #15
    //   6483: isub
    //   6484: iaload
    //   6485: bipush #25
    //   6487: ishl
    //   6488: ior
    //   6489: aload #20
    //   6491: iload #22
    //   6493: bipush #15
    //   6495: isub
    //   6496: iaload
    //   6497: bipush #18
    //   6499: iushr
    //   6500: aload #20
    //   6502: iload #22
    //   6504: bipush #15
    //   6506: isub
    //   6507: iaload
    //   6508: bipush #14
    //   6510: ishl
    //   6511: ior
    //   6512: ixor
    //   6513: aload #20
    //   6515: iload #22
    //   6517: bipush #15
    //   6519: isub
    //   6520: iaload
    //   6521: iconst_3
    //   6522: iushr
    //   6523: ixor
    //   6524: iadd
    //   6525: aload #20
    //   6527: iload #22
    //   6529: bipush #16
    //   6531: isub
    //   6532: iaload
    //   6533: iadd
    //   6534: iastore
    //   6535: goto -> 6542
    //   6538: invokestatic a : (Ljava/lang/Throwable;)Ljava/lang/Throwable;
    //   6541: athrow
    //   6542: aload #21
    //   6544: bipush #7
    //   6546: iaload
    //   6547: aload #21
    //   6549: iconst_4
    //   6550: iaload
    //   6551: bipush #6
    //   6553: iushr
    //   6554: aload #21
    //   6556: iconst_4
    //   6557: iaload
    //   6558: bipush #26
    //   6560: ishl
    //   6561: ior
    //   6562: aload #21
    //   6564: iconst_4
    //   6565: iaload
    //   6566: bipush #11
    //   6568: iushr
    //   6569: aload #21
    //   6571: iconst_4
    //   6572: iaload
    //   6573: bipush #21
    //   6575: ishl
    //   6576: ior
    //   6577: ixor
    //   6578: aload #21
    //   6580: iconst_4
    //   6581: iaload
    //   6582: bipush #25
    //   6584: iushr
    //   6585: aload #21
    //   6587: iconst_4
    //   6588: iaload
    //   6589: bipush #7
    //   6591: ishl
    //   6592: ior
    //   6593: ixor
    //   6594: iadd
    //   6595: aload #21
    //   6597: bipush #6
    //   6599: iaload
    //   6600: aload #21
    //   6602: iconst_4
    //   6603: iaload
    //   6604: aload #21
    //   6606: iconst_5
    //   6607: iaload
    //   6608: aload #21
    //   6610: bipush #6
    //   6612: iaload
    //   6613: ixor
    //   6614: iand
    //   6615: ixor
    //   6616: iadd
    //   6617: aload #7
    //   6619: iload #22
    //   6621: iaload
    //   6622: iadd
    //   6623: aload #20
    //   6625: iload #22
    //   6627: iaload
    //   6628: iadd
    //   6629: istore #23
    //   6631: aload #21
    //   6633: iconst_0
    //   6634: iaload
    //   6635: iconst_2
    //   6636: iushr
    //   6637: aload #21
    //   6639: iconst_0
    //   6640: iaload
    //   6641: bipush #30
    //   6643: ishl
    //   6644: ior
    //   6645: aload #21
    //   6647: iconst_0
    //   6648: iaload
    //   6649: bipush #13
    //   6651: iushr
    //   6652: aload #21
    //   6654: iconst_0
    //   6655: iaload
    //   6656: bipush #19
    //   6658: ishl
    //   6659: ior
    //   6660: ixor
    //   6661: aload #21
    //   6663: iconst_0
    //   6664: iaload
    //   6665: bipush #22
    //   6667: iushr
    //   6668: aload #21
    //   6670: iconst_0
    //   6671: iaload
    //   6672: bipush #10
    //   6674: ishl
    //   6675: ior
    //   6676: ixor
    //   6677: aload #21
    //   6679: iconst_0
    //   6680: iaload
    //   6681: aload #21
    //   6683: iconst_1
    //   6684: iaload
    //   6685: iand
    //   6686: aload #21
    //   6688: iconst_2
    //   6689: iaload
    //   6690: aload #21
    //   6692: iconst_0
    //   6693: iaload
    //   6694: aload #21
    //   6696: iconst_1
    //   6697: iaload
    //   6698: ior
    //   6699: iand
    //   6700: ior
    //   6701: iadd
    //   6702: istore #24
    //   6704: aload #21
    //   6706: iconst_3
    //   6707: dup2
    //   6708: iaload
    //   6709: iload #23
    //   6711: iadd
    //   6712: iastore
    //   6713: aload #21
    //   6715: bipush #7
    //   6717: iload #23
    //   6719: iload #24
    //   6721: iadd
    //   6722: iastore
    //   6723: aload #21
    //   6725: bipush #7
    //   6727: iaload
    //   6728: istore #23
    //   6730: aload #21
    //   6732: bipush #7
    //   6734: aload #21
    //   6736: bipush #6
    //   6738: iaload
    //   6739: iastore
    //   6740: aload #21
    //   6742: bipush #6
    //   6744: aload #21
    //   6746: iconst_5
    //   6747: iaload
    //   6748: iastore
    //   6749: aload #21
    //   6751: iconst_5
    //   6752: aload #21
    //   6754: iconst_4
    //   6755: iaload
    //   6756: iastore
    //   6757: aload #21
    //   6759: iconst_4
    //   6760: aload #21
    //   6762: iconst_3
    //   6763: iaload
    //   6764: iastore
    //   6765: aload #21
    //   6767: iconst_3
    //   6768: aload #21
    //   6770: iconst_2
    //   6771: iaload
    //   6772: iastore
    //   6773: aload #21
    //   6775: iconst_2
    //   6776: aload #21
    //   6778: iconst_1
    //   6779: iaload
    //   6780: iastore
    //   6781: aload #21
    //   6783: iconst_1
    //   6784: aload #21
    //   6786: iconst_0
    //   6787: iaload
    //   6788: iastore
    //   6789: aload #21
    //   6791: iconst_0
    //   6792: iload #23
    //   6794: iastore
    //   6795: iinc #22, 1
    //   6798: iload_2
    //   6799: ifeq -> 6307
    //   6802: iconst_0
    //   6803: istore #22
    //   6805: iload #22
    //   6807: bipush #8
    //   6809: if_icmpge -> 6832
    //   6812: aload #9
    //   6814: iload #22
    //   6816: dup2
    //   6817: iaload
    //   6818: aload #21
    //   6820: iload #22
    //   6822: iaload
    //   6823: iadd
    //   6824: iastore
    //   6825: iinc #22, 1
    //   6828: iload_2
    //   6829: ifeq -> 6805
    //   6832: iload #14
    //   6834: iload #19
    //   6836: iadd
    //   6837: istore #14
    //   6839: iload #18
    //   6841: iload #19
    //   6843: isub
    //   6844: istore #18
    //   6846: iconst_0
    //   6847: istore #13
    //   6849: iload #18
    //   6851: bipush #64
    //   6853: if_icmplt -> 7463
    //   6856: iconst_0
    //   6857: istore #20
    //   6859: iload #20
    //   6861: bipush #64
    //   6863: if_icmpge -> 6886
    //   6866: aload #11
    //   6868: iload #20
    //   6870: aload #6
    //   6872: iload #14
    //   6874: iload #20
    //   6876: iadd
    //   6877: baload
    //   6878: bastore
    //   6879: iinc #20, 1
    //   6882: iload_2
    //   6883: ifeq -> 6859
    //   6886: bipush #64
    //   6888: newarray int
    //   6890: astore #20
    //   6892: bipush #8
    //   6894: newarray int
    //   6896: astore #21
    //   6898: iconst_0
    //   6899: istore #22
    //   6901: iload #22
    //   6903: bipush #8
    //   6905: if_icmpge -> 6925
    //   6908: aload #21
    //   6910: iload #22
    //   6912: aload #9
    //   6914: iload #22
    //   6916: iaload
    //   6917: iastore
    //   6918: iinc #22, 1
    //   6921: iload_2
    //   6922: ifeq -> 6901
    //   6925: iconst_0
    //   6926: istore #22
    //   6928: iload #22
    //   6930: bipush #64
    //   6932: if_icmpge -> 7423
    //   6935: iload #22
    //   6937: bipush #16
    //   6939: if_icmpge -> 7020
    //   6942: aload #20
    //   6944: iload #22
    //   6946: aload #11
    //   6948: iconst_4
    //   6949: iload #22
    //   6951: imul
    //   6952: baload
    //   6953: sipush #255
    //   6956: iand
    //   6957: bipush #24
    //   6959: ishl
    //   6960: aload #11
    //   6962: iconst_4
    //   6963: iload #22
    //   6965: imul
    //   6966: iconst_1
    //   6967: iadd
    //   6968: baload
    //   6969: sipush #255
    //   6972: iand
    //   6973: bipush #16
    //   6975: ishl
    //   6976: ior
    //   6977: aload #11
    //   6979: iconst_4
    //   6980: iload #22
    //   6982: imul
    //   6983: iconst_2
    //   6984: iadd
    //   6985: baload
    //   6986: sipush #255
    //   6989: iand
    //   6990: bipush #8
    //   6992: ishl
    //   6993: ior
    //   6994: aload #11
    //   6996: iconst_4
    //   6997: iload #22
    //   6999: imul
    //   7000: iconst_3
    //   7001: iadd
    //   7002: baload
    //   7003: sipush #255
    //   7006: iand
    //   7007: ior
    //   7008: iastore
    //   7009: iload_2
    //   7010: ifeq -> 7163
    //   7013: goto -> 7020
    //   7016: invokestatic a : (Ljava/lang/Throwable;)Ljava/lang/Throwable;
    //   7019: athrow
    //   7020: aload #20
    //   7022: iload #22
    //   7024: aload #20
    //   7026: iload #22
    //   7028: iconst_2
    //   7029: isub
    //   7030: iaload
    //   7031: bipush #17
    //   7033: iushr
    //   7034: aload #20
    //   7036: iload #22
    //   7038: iconst_2
    //   7039: isub
    //   7040: iaload
    //   7041: bipush #15
    //   7043: ishl
    //   7044: ior
    //   7045: aload #20
    //   7047: iload #22
    //   7049: iconst_2
    //   7050: isub
    //   7051: iaload
    //   7052: bipush #19
    //   7054: iushr
    //   7055: aload #20
    //   7057: iload #22
    //   7059: iconst_2
    //   7060: isub
    //   7061: iaload
    //   7062: bipush #13
    //   7064: ishl
    //   7065: ior
    //   7066: ixor
    //   7067: aload #20
    //   7069: iload #22
    //   7071: iconst_2
    //   7072: isub
    //   7073: iaload
    //   7074: bipush #10
    //   7076: iushr
    //   7077: ixor
    //   7078: aload #20
    //   7080: iload #22
    //   7082: bipush #7
    //   7084: isub
    //   7085: iaload
    //   7086: iadd
    //   7087: aload #20
    //   7089: iload #22
    //   7091: bipush #15
    //   7093: isub
    //   7094: iaload
    //   7095: bipush #7
    //   7097: iushr
    //   7098: aload #20
    //   7100: iload #22
    //   7102: bipush #15
    //   7104: isub
    //   7105: iaload
    //   7106: bipush #25
    //   7108: ishl
    //   7109: ior
    //   7110: aload #20
    //   7112: iload #22
    //   7114: bipush #15
    //   7116: isub
    //   7117: iaload
    //   7118: bipush #18
    //   7120: iushr
    //   7121: aload #20
    //   7123: iload #22
    //   7125: bipush #15
    //   7127: isub
    //   7128: iaload
    //   7129: bipush #14
    //   7131: ishl
    //   7132: ior
    //   7133: ixor
    //   7134: aload #20
    //   7136: iload #22
    //   7138: bipush #15
    //   7140: isub
    //   7141: iaload
    //   7142: iconst_3
    //   7143: iushr
    //   7144: ixor
    //   7145: iadd
    //   7146: aload #20
    //   7148: iload #22
    //   7150: bipush #16
    //   7152: isub
    //   7153: iaload
    //   7154: iadd
    //   7155: iastore
    //   7156: goto -> 7163
    //   7159: invokestatic a : (Ljava/lang/Throwable;)Ljava/lang/Throwable;
    //   7162: athrow
    //   7163: aload #21
    //   7165: bipush #7
    //   7167: iaload
    //   7168: aload #21
    //   7170: iconst_4
    //   7171: iaload
    //   7172: bipush #6
    //   7174: iushr
    //   7175: aload #21
    //   7177: iconst_4
    //   7178: iaload
    //   7179: bipush #26
    //   7181: ishl
    //   7182: ior
    //   7183: aload #21
    //   7185: iconst_4
    //   7186: iaload
    //   7187: bipush #11
    //   7189: iushr
    //   7190: aload #21
    //   7192: iconst_4
    //   7193: iaload
    //   7194: bipush #21
    //   7196: ishl
    //   7197: ior
    //   7198: ixor
    //   7199: aload #21
    //   7201: iconst_4
    //   7202: iaload
    //   7203: bipush #25
    //   7205: iushr
    //   7206: aload #21
    //   7208: iconst_4
    //   7209: iaload
    //   7210: bipush #7
    //   7212: ishl
    //   7213: ior
    //   7214: ixor
    //   7215: iadd
    //   7216: aload #21
    //   7218: bipush #6
    //   7220: iaload
    //   7221: aload #21
    //   7223: iconst_4
    //   7224: iaload
    //   7225: aload #21
    //   7227: iconst_5
    //   7228: iaload
    //   7229: aload #21
    //   7231: bipush #6
    //   7233: iaload
    //   7234: ixor
    //   7235: iand
    //   7236: ixor
    //   7237: iadd
    //   7238: aload #7
    //   7240: iload #22
    //   7242: iaload
    //   7243: iadd
    //   7244: aload #20
    //   7246: iload #22
    //   7248: iaload
    //   7249: iadd
    //   7250: istore #23
    //   7252: aload #21
    //   7254: iconst_0
    //   7255: iaload
    //   7256: iconst_2
    //   7257: iushr
    //   7258: aload #21
    //   7260: iconst_0
    //   7261: iaload
    //   7262: bipush #30
    //   7264: ishl
    //   7265: ior
    //   7266: aload #21
    //   7268: iconst_0
    //   7269: iaload
    //   7270: bipush #13
    //   7272: iushr
    //   7273: aload #21
    //   7275: iconst_0
    //   7276: iaload
    //   7277: bipush #19
    //   7279: ishl
    //   7280: ior
    //   7281: ixor
    //   7282: aload #21
    //   7284: iconst_0
    //   7285: iaload
    //   7286: bipush #22
    //   7288: iushr
    //   7289: aload #21
    //   7291: iconst_0
    //   7292: iaload
    //   7293: bipush #10
    //   7295: ishl
    //   7296: ior
    //   7297: ixor
    //   7298: aload #21
    //   7300: iconst_0
    //   7301: iaload
    //   7302: aload #21
    //   7304: iconst_1
    //   7305: iaload
    //   7306: iand
    //   7307: aload #21
    //   7309: iconst_2
    //   7310: iaload
    //   7311: aload #21
    //   7313: iconst_0
    //   7314: iaload
    //   7315: aload #21
    //   7317: iconst_1
    //   7318: iaload
    //   7319: ior
    //   7320: iand
    //   7321: ior
    //   7322: iadd
    //   7323: istore #24
    //   7325: aload #21
    //   7327: iconst_3
    //   7328: dup2
    //   7329: iaload
    //   7330: iload #23
    //   7332: iadd
    //   7333: iastore
    //   7334: aload #21
    //   7336: bipush #7
    //   7338: iload #23
    //   7340: iload #24
    //   7342: iadd
    //   7343: iastore
    //   7344: aload #21
    //   7346: bipush #7
    //   7348: iaload
    //   7349: istore #23
    //   7351: aload #21
    //   7353: bipush #7
    //   7355: aload #21
    //   7357: bipush #6
    //   7359: iaload
    //   7360: iastore
    //   7361: aload #21
    //   7363: bipush #6
    //   7365: aload #21
    //   7367: iconst_5
    //   7368: iaload
    //   7369: iastore
    //   7370: aload #21
    //   7372: iconst_5
    //   7373: aload #21
    //   7375: iconst_4
    //   7376: iaload
    //   7377: iastore
    //   7378: aload #21
    //   7380: iconst_4
    //   7381: aload #21
    //   7383: iconst_3
    //   7384: iaload
    //   7385: iastore
    //   7386: aload #21
    //   7388: iconst_3
    //   7389: aload #21
    //   7391: iconst_2
    //   7392: iaload
    //   7393: iastore
    //   7394: aload #21
    //   7396: iconst_2
    //   7397: aload #21
    //   7399: iconst_1
    //   7400: iaload
    //   7401: iastore
    //   7402: aload #21
    //   7404: iconst_1
    //   7405: aload #21
    //   7407: iconst_0
    //   7408: iaload
    //   7409: iastore
    //   7410: aload #21
    //   7412: iconst_0
    //   7413: iload #23
    //   7415: iastore
    //   7416: iinc #22, 1
    //   7419: iload_2
    //   7420: ifeq -> 6928
    //   7423: iconst_0
    //   7424: istore #22
    //   7426: iload #22
    //   7428: bipush #8
    //   7430: if_icmpge -> 7453
    //   7433: aload #9
    //   7435: iload #22
    //   7437: dup2
    //   7438: iaload
    //   7439: aload #21
    //   7441: iload #22
    //   7443: iaload
    //   7444: iadd
    //   7445: iastore
    //   7446: iinc #22, 1
    //   7449: iload_2
    //   7450: ifeq -> 7426
    //   7453: iinc #14, 64
    //   7456: iinc #18, -64
    //   7459: iload_2
    //   7460: ifeq -> 6849
    //   7463: iload #18
    //   7465: ifle -> 7501
    //   7468: iconst_0
    //   7469: istore #20
    //   7471: iload #20
    //   7473: iload #18
    //   7475: if_icmpge -> 7501
    //   7478: aload #10
    //   7480: iload #13
    //   7482: iload #20
    //   7484: iadd
    //   7485: aload #6
    //   7487: iload #14
    //   7489: iload #20
    //   7491: iadd
    //   7492: baload
    //   7493: bastore
    //   7494: iinc #20, 1
    //   7497: iload_2
    //   7498: ifeq -> 7471
    //   7501: bipush #8
    //   7503: newarray byte
    //   7505: astore #20
    //   7507: aload #20
    //   7509: iconst_0
    //   7510: iload #15
    //   7512: bipush #24
    //   7514: iushr
    //   7515: i2b
    //   7516: bastore
    //   7517: aload #20
    //   7519: iconst_1
    //   7520: iload #15
    //   7522: bipush #16
    //   7524: iushr
    //   7525: i2b
    //   7526: bastore
    //   7527: aload #20
    //   7529: iconst_2
    //   7530: iload #15
    //   7532: bipush #8
    //   7534: iushr
    //   7535: i2b
    //   7536: bastore
    //   7537: aload #20
    //   7539: iconst_3
    //   7540: iload #15
    //   7542: i2b
    //   7543: bastore
    //   7544: aload #20
    //   7546: iconst_4
    //   7547: iload #16
    //   7549: bipush #24
    //   7551: iushr
    //   7552: i2b
    //   7553: bastore
    //   7554: aload #20
    //   7556: iconst_5
    //   7557: iload #16
    //   7559: bipush #16
    //   7561: iushr
    //   7562: i2b
    //   7563: bastore
    //   7564: aload #20
    //   7566: bipush #6
    //   7568: iload #16
    //   7570: bipush #8
    //   7572: iushr
    //   7573: i2b
    //   7574: bastore
    //   7575: aload #20
    //   7577: bipush #7
    //   7579: iload #16
    //   7581: i2b
    //   7582: bastore
    //   7583: bipush #8
    //   7585: istore #12
    //   7587: aload #8
    //   7589: iconst_0
    //   7590: iaload
    //   7591: bipush #63
    //   7593: iand
    //   7594: istore #13
    //   7596: bipush #64
    //   7598: iload #13
    //   7600: isub
    //   7601: istore #19
    //   7603: aload #8
    //   7605: iconst_0
    //   7606: dup2
    //   7607: iaload
    //   7608: iload #12
    //   7610: iadd
    //   7611: iastore
    //   7612: aload #8
    //   7614: iconst_0
    //   7615: dup2
    //   7616: iaload
    //   7617: iconst_m1
    //   7618: iand
    //   7619: iastore
    //   7620: aload #8
    //   7622: iconst_0
    //   7623: iaload
    //   7624: iload #12
    //   7626: if_icmpge -> 7644
    //   7629: aload #8
    //   7631: iconst_1
    //   7632: dup2
    //   7633: iaload
    //   7634: iconst_1
    //   7635: iadd
    //   7636: iastore
    //   7637: goto -> 7644
    //   7640: invokestatic a : (Ljava/lang/Throwable;)Ljava/lang/Throwable;
    //   7643: athrow
    //   7644: iload #13
    //   7646: ifle -> 8260
    //   7649: iload #12
    //   7651: iload #19
    //   7653: if_icmplt -> 8260
    //   7656: goto -> 7663
    //   7659: invokestatic a : (Ljava/lang/Throwable;)Ljava/lang/Throwable;
    //   7662: athrow
    //   7663: iconst_0
    //   7664: istore #21
    //   7666: iload #21
    //   7668: iload #19
    //   7670: if_icmpge -> 7693
    //   7673: aload #10
    //   7675: iload #13
    //   7677: iload #21
    //   7679: iadd
    //   7680: aload #20
    //   7682: iload #21
    //   7684: baload
    //   7685: bastore
    //   7686: iinc #21, 1
    //   7689: iload_2
    //   7690: ifeq -> 7666
    //   7693: bipush #64
    //   7695: newarray int
    //   7697: astore #21
    //   7699: bipush #8
    //   7701: newarray int
    //   7703: astore #22
    //   7705: iconst_0
    //   7706: istore #23
    //   7708: iload #23
    //   7710: bipush #8
    //   7712: if_icmpge -> 7732
    //   7715: aload #22
    //   7717: iload #23
    //   7719: aload #9
    //   7721: iload #23
    //   7723: iaload
    //   7724: iastore
    //   7725: iinc #23, 1
    //   7728: iload_2
    //   7729: ifeq -> 7708
    //   7732: iconst_0
    //   7733: istore #23
    //   7735: iload #23
    //   7737: bipush #64
    //   7739: if_icmpge -> 8230
    //   7742: iload #23
    //   7744: bipush #16
    //   7746: if_icmpge -> 7827
    //   7749: aload #21
    //   7751: iload #23
    //   7753: aload #10
    //   7755: iconst_4
    //   7756: iload #23
    //   7758: imul
    //   7759: baload
    //   7760: sipush #255
    //   7763: iand
    //   7764: bipush #24
    //   7766: ishl
    //   7767: aload #10
    //   7769: iconst_4
    //   7770: iload #23
    //   7772: imul
    //   7773: iconst_1
    //   7774: iadd
    //   7775: baload
    //   7776: sipush #255
    //   7779: iand
    //   7780: bipush #16
    //   7782: ishl
    //   7783: ior
    //   7784: aload #10
    //   7786: iconst_4
    //   7787: iload #23
    //   7789: imul
    //   7790: iconst_2
    //   7791: iadd
    //   7792: baload
    //   7793: sipush #255
    //   7796: iand
    //   7797: bipush #8
    //   7799: ishl
    //   7800: ior
    //   7801: aload #10
    //   7803: iconst_4
    //   7804: iload #23
    //   7806: imul
    //   7807: iconst_3
    //   7808: iadd
    //   7809: baload
    //   7810: sipush #255
    //   7813: iand
    //   7814: ior
    //   7815: iastore
    //   7816: iload_2
    //   7817: ifeq -> 7970
    //   7820: goto -> 7827
    //   7823: invokestatic a : (Ljava/lang/Throwable;)Ljava/lang/Throwable;
    //   7826: athrow
    //   7827: aload #21
    //   7829: iload #23
    //   7831: aload #21
    //   7833: iload #23
    //   7835: iconst_2
    //   7836: isub
    //   7837: iaload
    //   7838: bipush #17
    //   7840: iushr
    //   7841: aload #21
    //   7843: iload #23
    //   7845: iconst_2
    //   7846: isub
    //   7847: iaload
    //   7848: bipush #15
    //   7850: ishl
    //   7851: ior
    //   7852: aload #21
    //   7854: iload #23
    //   7856: iconst_2
    //   7857: isub
    //   7858: iaload
    //   7859: bipush #19
    //   7861: iushr
    //   7862: aload #21
    //   7864: iload #23
    //   7866: iconst_2
    //   7867: isub
    //   7868: iaload
    //   7869: bipush #13
    //   7871: ishl
    //   7872: ior
    //   7873: ixor
    //   7874: aload #21
    //   7876: iload #23
    //   7878: iconst_2
    //   7879: isub
    //   7880: iaload
    //   7881: bipush #10
    //   7883: iushr
    //   7884: ixor
    //   7885: aload #21
    //   7887: iload #23
    //   7889: bipush #7
    //   7891: isub
    //   7892: iaload
    //   7893: iadd
    //   7894: aload #21
    //   7896: iload #23
    //   7898: bipush #15
    //   7900: isub
    //   7901: iaload
    //   7902: bipush #7
    //   7904: iushr
    //   7905: aload #21
    //   7907: iload #23
    //   7909: bipush #15
    //   7911: isub
    //   7912: iaload
    //   7913: bipush #25
    //   7915: ishl
    //   7916: ior
    //   7917: aload #21
    //   7919: iload #23
    //   7921: bipush #15
    //   7923: isub
    //   7924: iaload
    //   7925: bipush #18
    //   7927: iushr
    //   7928: aload #21
    //   7930: iload #23
    //   7932: bipush #15
    //   7934: isub
    //   7935: iaload
    //   7936: bipush #14
    //   7938: ishl
    //   7939: ior
    //   7940: ixor
    //   7941: aload #21
    //   7943: iload #23
    //   7945: bipush #15
    //   7947: isub
    //   7948: iaload
    //   7949: iconst_3
    //   7950: iushr
    //   7951: ixor
    //   7952: iadd
    //   7953: aload #21
    //   7955: iload #23
    //   7957: bipush #16
    //   7959: isub
    //   7960: iaload
    //   7961: iadd
    //   7962: iastore
    //   7963: goto -> 7970
    //   7966: invokestatic a : (Ljava/lang/Throwable;)Ljava/lang/Throwable;
    //   7969: athrow
    //   7970: aload #22
    //   7972: bipush #7
    //   7974: iaload
    //   7975: aload #22
    //   7977: iconst_4
    //   7978: iaload
    //   7979: bipush #6
    //   7981: iushr
    //   7982: aload #22
    //   7984: iconst_4
    //   7985: iaload
    //   7986: bipush #26
    //   7988: ishl
    //   7989: ior
    //   7990: aload #22
    //   7992: iconst_4
    //   7993: iaload
    //   7994: bipush #11
    //   7996: iushr
    //   7997: aload #22
    //   7999: iconst_4
    //   8000: iaload
    //   8001: bipush #21
    //   8003: ishl
    //   8004: ior
    //   8005: ixor
    //   8006: aload #22
    //   8008: iconst_4
    //   8009: iaload
    //   8010: bipush #25
    //   8012: iushr
    //   8013: aload #22
    //   8015: iconst_4
    //   8016: iaload
    //   8017: bipush #7
    //   8019: ishl
    //   8020: ior
    //   8021: ixor
    //   8022: iadd
    //   8023: aload #22
    //   8025: bipush #6
    //   8027: iaload
    //   8028: aload #22
    //   8030: iconst_4
    //   8031: iaload
    //   8032: aload #22
    //   8034: iconst_5
    //   8035: iaload
    //   8036: aload #22
    //   8038: bipush #6
    //   8040: iaload
    //   8041: ixor
    //   8042: iand
    //   8043: ixor
    //   8044: iadd
    //   8045: aload #7
    //   8047: iload #23
    //   8049: iaload
    //   8050: iadd
    //   8051: aload #21
    //   8053: iload #23
    //   8055: iaload
    //   8056: iadd
    //   8057: istore #24
    //   8059: aload #22
    //   8061: iconst_0
    //   8062: iaload
    //   8063: iconst_2
    //   8064: iushr
    //   8065: aload #22
    //   8067: iconst_0
    //   8068: iaload
    //   8069: bipush #30
    //   8071: ishl
    //   8072: ior
    //   8073: aload #22
    //   8075: iconst_0
    //   8076: iaload
    //   8077: bipush #13
    //   8079: iushr
    //   8080: aload #22
    //   8082: iconst_0
    //   8083: iaload
    //   8084: bipush #19
    //   8086: ishl
    //   8087: ior
    //   8088: ixor
    //   8089: aload #22
    //   8091: iconst_0
    //   8092: iaload
    //   8093: bipush #22
    //   8095: iushr
    //   8096: aload #22
    //   8098: iconst_0
    //   8099: iaload
    //   8100: bipush #10
    //   8102: ishl
    //   8103: ior
    //   8104: ixor
    //   8105: aload #22
    //   8107: iconst_0
    //   8108: iaload
    //   8109: aload #22
    //   8111: iconst_1
    //   8112: iaload
    //   8113: iand
    //   8114: aload #22
    //   8116: iconst_2
    //   8117: iaload
    //   8118: aload #22
    //   8120: iconst_0
    //   8121: iaload
    //   8122: aload #22
    //   8124: iconst_1
    //   8125: iaload
    //   8126: ior
    //   8127: iand
    //   8128: ior
    //   8129: iadd
    //   8130: istore #25
    //   8132: aload #22
    //   8134: iconst_3
    //   8135: dup2
    //   8136: iaload
    //   8137: iload #24
    //   8139: iadd
    //   8140: iastore
    //   8141: aload #22
    //   8143: bipush #7
    //   8145: iload #24
    //   8147: iload #25
    //   8149: iadd
    //   8150: iastore
    //   8151: aload #22
    //   8153: bipush #7
    //   8155: iaload
    //   8156: istore #24
    //   8158: aload #22
    //   8160: bipush #7
    //   8162: aload #22
    //   8164: bipush #6
    //   8166: iaload
    //   8167: iastore
    //   8168: aload #22
    //   8170: bipush #6
    //   8172: aload #22
    //   8174: iconst_5
    //   8175: iaload
    //   8176: iastore
    //   8177: aload #22
    //   8179: iconst_5
    //   8180: aload #22
    //   8182: iconst_4
    //   8183: iaload
    //   8184: iastore
    //   8185: aload #22
    //   8187: iconst_4
    //   8188: aload #22
    //   8190: iconst_3
    //   8191: iaload
    //   8192: iastore
    //   8193: aload #22
    //   8195: iconst_3
    //   8196: aload #22
    //   8198: iconst_2
    //   8199: iaload
    //   8200: iastore
    //   8201: aload #22
    //   8203: iconst_2
    //   8204: aload #22
    //   8206: iconst_1
    //   8207: iaload
    //   8208: iastore
    //   8209: aload #22
    //   8211: iconst_1
    //   8212: aload #22
    //   8214: iconst_0
    //   8215: iaload
    //   8216: iastore
    //   8217: aload #22
    //   8219: iconst_0
    //   8220: iload #24
    //   8222: iastore
    //   8223: iinc #23, 1
    //   8226: iload_2
    //   8227: ifeq -> 7735
    //   8230: iconst_0
    //   8231: istore #23
    //   8233: iload #23
    //   8235: bipush #8
    //   8237: if_icmpge -> 8260
    //   8240: aload #9
    //   8242: iload #23
    //   8244: dup2
    //   8245: iaload
    //   8246: aload #22
    //   8248: iload #23
    //   8250: iaload
    //   8251: iadd
    //   8252: iastore
    //   8253: iinc #23, 1
    //   8256: iload_2
    //   8257: ifeq -> 8233
    //   8260: bipush #32
    //   8262: newarray byte
    //   8264: astore #5
    //   8266: aload #5
    //   8268: iconst_0
    //   8269: aload #9
    //   8271: iconst_0
    //   8272: iaload
    //   8273: bipush #24
    //   8275: iushr
    //   8276: i2b
    //   8277: bastore
    //   8278: aload #5
    //   8280: iconst_1
    //   8281: aload #9
    //   8283: iconst_0
    //   8284: iaload
    //   8285: bipush #16
    //   8287: iushr
    //   8288: i2b
    //   8289: bastore
    //   8290: aload #5
    //   8292: iconst_2
    //   8293: aload #9
    //   8295: iconst_0
    //   8296: iaload
    //   8297: bipush #8
    //   8299: iushr
    //   8300: i2b
    //   8301: bastore
    //   8302: aload #5
    //   8304: iconst_3
    //   8305: aload #9
    //   8307: iconst_0
    //   8308: iaload
    //   8309: i2b
    //   8310: bastore
    //   8311: aload #5
    //   8313: iconst_4
    //   8314: aload #9
    //   8316: iconst_1
    //   8317: iaload
    //   8318: bipush #24
    //   8320: iushr
    //   8321: i2b
    //   8322: bastore
    //   8323: aload #5
    //   8325: iconst_5
    //   8326: aload #9
    //   8328: iconst_1
    //   8329: iaload
    //   8330: bipush #16
    //   8332: iushr
    //   8333: i2b
    //   8334: bastore
    //   8335: aload #5
    //   8337: bipush #6
    //   8339: aload #9
    //   8341: iconst_1
    //   8342: iaload
    //   8343: bipush #8
    //   8345: iushr
    //   8346: i2b
    //   8347: bastore
    //   8348: aload #5
    //   8350: bipush #7
    //   8352: aload #9
    //   8354: iconst_1
    //   8355: iaload
    //   8356: i2b
    //   8357: bastore
    //   8358: aload #5
    //   8360: bipush #8
    //   8362: aload #9
    //   8364: iconst_2
    //   8365: iaload
    //   8366: bipush #24
    //   8368: iushr
    //   8369: i2b
    //   8370: bastore
    //   8371: aload #5
    //   8373: bipush #9
    //   8375: aload #9
    //   8377: iconst_2
    //   8378: iaload
    //   8379: bipush #16
    //   8381: iushr
    //   8382: i2b
    //   8383: bastore
    //   8384: aload #5
    //   8386: bipush #10
    //   8388: aload #9
    //   8390: iconst_2
    //   8391: iaload
    //   8392: bipush #8
    //   8394: iushr
    //   8395: i2b
    //   8396: bastore
    //   8397: aload #5
    //   8399: bipush #11
    //   8401: aload #9
    //   8403: iconst_2
    //   8404: iaload
    //   8405: i2b
    //   8406: bastore
    //   8407: aload #5
    //   8409: bipush #12
    //   8411: aload #9
    //   8413: iconst_3
    //   8414: iaload
    //   8415: bipush #24
    //   8417: iushr
    //   8418: i2b
    //   8419: bastore
    //   8420: aload #5
    //   8422: bipush #13
    //   8424: aload #9
    //   8426: iconst_3
    //   8427: iaload
    //   8428: bipush #16
    //   8430: iushr
    //   8431: i2b
    //   8432: bastore
    //   8433: aload #5
    //   8435: bipush #14
    //   8437: aload #9
    //   8439: iconst_3
    //   8440: iaload
    //   8441: bipush #8
    //   8443: iushr
    //   8444: i2b
    //   8445: bastore
    //   8446: aload #5
    //   8448: bipush #15
    //   8450: aload #9
    //   8452: iconst_3
    //   8453: iaload
    //   8454: i2b
    //   8455: bastore
    //   8456: aload #5
    //   8458: bipush #16
    //   8460: aload #9
    //   8462: iconst_4
    //   8463: iaload
    //   8464: bipush #24
    //   8466: iushr
    //   8467: i2b
    //   8468: bastore
    //   8469: aload #5
    //   8471: bipush #17
    //   8473: aload #9
    //   8475: iconst_4
    //   8476: iaload
    //   8477: bipush #16
    //   8479: iushr
    //   8480: i2b
    //   8481: bastore
    //   8482: aload #5
    //   8484: bipush #18
    //   8486: aload #9
    //   8488: iconst_4
    //   8489: iaload
    //   8490: bipush #8
    //   8492: iushr
    //   8493: i2b
    //   8494: bastore
    //   8495: aload #5
    //   8497: bipush #19
    //   8499: aload #9
    //   8501: iconst_4
    //   8502: iaload
    //   8503: i2b
    //   8504: bastore
    //   8505: aload #5
    //   8507: bipush #20
    //   8509: aload #9
    //   8511: iconst_5
    //   8512: iaload
    //   8513: bipush #24
    //   8515: iushr
    //   8516: i2b
    //   8517: bastore
    //   8518: aload #5
    //   8520: bipush #21
    //   8522: aload #9
    //   8524: iconst_5
    //   8525: iaload
    //   8526: bipush #16
    //   8528: iushr
    //   8529: i2b
    //   8530: bastore
    //   8531: aload #5
    //   8533: bipush #22
    //   8535: aload #9
    //   8537: iconst_5
    //   8538: iaload
    //   8539: bipush #8
    //   8541: iushr
    //   8542: i2b
    //   8543: bastore
    //   8544: aload #5
    //   8546: bipush #23
    //   8548: aload #9
    //   8550: iconst_5
    //   8551: iaload
    //   8552: i2b
    //   8553: bastore
    //   8554: aload #5
    //   8556: bipush #24
    //   8558: aload #9
    //   8560: bipush #6
    //   8562: iaload
    //   8563: bipush #24
    //   8565: iushr
    //   8566: i2b
    //   8567: bastore
    //   8568: aload #5
    //   8570: bipush #25
    //   8572: aload #9
    //   8574: bipush #6
    //   8576: iaload
    //   8577: bipush #16
    //   8579: iushr
    //   8580: i2b
    //   8581: bastore
    //   8582: aload #5
    //   8584: bipush #26
    //   8586: aload #9
    //   8588: bipush #6
    //   8590: iaload
    //   8591: bipush #8
    //   8593: iushr
    //   8594: i2b
    //   8595: bastore
    //   8596: aload #5
    //   8598: bipush #27
    //   8600: aload #9
    //   8602: bipush #6
    //   8604: iaload
    //   8605: i2b
    //   8606: bastore
    //   8607: aload #5
    //   8609: bipush #28
    //   8611: aload #9
    //   8613: bipush #7
    //   8615: iaload
    //   8616: bipush #24
    //   8618: iushr
    //   8619: i2b
    //   8620: bastore
    //   8621: aload #5
    //   8623: bipush #29
    //   8625: aload #9
    //   8627: bipush #7
    //   8629: iaload
    //   8630: bipush #16
    //   8632: iushr
    //   8633: i2b
    //   8634: bastore
    //   8635: aload #5
    //   8637: bipush #30
    //   8639: aload #9
    //   8641: bipush #7
    //   8643: iaload
    //   8644: bipush #8
    //   8646: iushr
    //   8647: i2b
    //   8648: bastore
    //   8649: aload #5
    //   8651: bipush #31
    //   8653: aload #9
    //   8655: bipush #7
    //   8657: iaload
    //   8658: i2b
    //   8659: bastore
    //   8660: iconst_0
    //   8661: istore #4
    //   8663: getstatic burp/Zrfa.ZT : Ljava/lang/String;
    //   8666: getstatic burp/Zzi_.Zf : Ljava/lang/Object;
    //   8669: checkcast java/math/BigInteger
    //   8672: invokevirtual intValue : ()I
    //   8675: bipush #32
    //   8677: irem
    //   8678: invokestatic abs : (I)I
    //   8681: invokevirtual charAt : (I)C
    //   8684: getstatic burp/Ztr5.ZY : Ljava/lang/String;
    //   8687: getstatic burp/Zku9.Zp : Ljava/lang/Object;
    //   8690: checkcast java/math/BigInteger
    //   8693: invokevirtual intValue : ()I
    //   8696: bipush #32
    //   8698: irem
    //   8699: invokestatic abs : (I)I
    //   8702: invokevirtual charAt : (I)C
    //   8705: if_icmple -> 9050
    //   8708: sipush #10767
    //   8711: sipush #10456
    //   8714: invokestatic a : (II)Ljava/lang/String;
    //   8717: iconst_1
    //   8718: ldc burp/Zrka
    //   8720: invokevirtual getClassLoader : ()Ljava/lang/ClassLoader;
    //   8723: invokestatic forName : (Ljava/lang/String;ZLjava/lang/ClassLoader;)Ljava/lang/Class;
    //   8726: invokevirtual getDeclaredFields : ()[Ljava/lang/reflect/Field;
    //   8729: astore #5
    //   8731: aload #5
    //   8733: arraylength
    //   8734: istore #6
    //   8736: iconst_0
    //   8737: istore #7
    //   8739: iload #7
    //   8741: iload #6
    //   8743: if_icmpge -> 8881
    //   8746: aload #5
    //   8748: iload #7
    //   8750: aaload
    //   8751: astore #8
    //   8753: aload #8
    //   8755: invokevirtual getModifiers : ()I
    //   8758: invokestatic isStatic : (I)Z
    //   8761: ifne -> 8771
    //   8764: goto -> 8874
    //   8767: invokestatic a : (Ljava/lang/Throwable;)Ljava/lang/Throwable;
    //   8770: athrow
    //   8771: aload #8
    //   8773: invokevirtual getType : ()Ljava/lang/Class;
    //   8776: astore #9
    //   8778: aload #9
    //   8780: ifnull -> 8861
    //   8783: aload #9
    //   8785: invokevirtual isPrimitive : ()Z
    //   8788: ifne -> 8861
    //   8791: goto -> 8798
    //   8794: invokestatic a : (Ljava/lang/Throwable;)Ljava/lang/Throwable;
    //   8797: athrow
    //   8798: aload #9
    //   8800: invokevirtual getPackage : ()Ljava/lang/Package;
    //   8803: ifnull -> 8861
    //   8806: goto -> 8813
    //   8809: invokestatic a : (Ljava/lang/Throwable;)Ljava/lang/Throwable;
    //   8812: athrow
    //   8813: aload #9
    //   8815: invokevirtual getPackage : ()Ljava/lang/Package;
    //   8818: invokevirtual getName : ()Ljava/lang/String;
    //   8821: ifnull -> 8861
    //   8824: goto -> 8831
    //   8827: invokestatic a : (Ljava/lang/Throwable;)Ljava/lang/Throwable;
    //   8830: athrow
    //   8831: aload #9
    //   8833: invokevirtual getPackage : ()Ljava/lang/Package;
    //   8836: invokevirtual getName : ()Ljava/lang/String;
    //   8839: sipush #10761
    //   8842: sipush #-27140
    //   8845: invokestatic a : (II)Ljava/lang/String;
    //   8848: invokevirtual startsWith : (Ljava/lang/String;)Z
    //   8851: ifne -> 8861
    //   8854: goto -> 8861
    //   8857: invokestatic a : (Ljava/lang/Throwable;)Ljava/lang/Throwable;
    //   8860: athrow
    //   8861: aload #8
    //   8863: iconst_1
    //   8864: invokevirtual setAccessible : (Z)V
    //   8867: aload #8
    //   8869: aconst_null
    //   8870: invokevirtual get : (Ljava/lang/Object;)Ljava/lang/Object;
    //   8873: pop
    //   8874: iinc #7, 1
    //   8877: iload_2
    //   8878: ifeq -> 8739
    //   8881: sipush #10780
    //   8884: sipush #-29073
    //   8887: invokestatic a : (II)Ljava/lang/String;
    //   8890: invokestatic forName : (Ljava/lang/String;)Ljava/lang/Class;
    //   8893: invokevirtual getDeclaredMethods : ()[Ljava/lang/reflect/Method;
    //   8896: astore #5
    //   8898: aload #5
    //   8900: arraylength
    //   8901: istore #6
    //   8903: iconst_0
    //   8904: istore #7
    //   8906: iload #7
    //   8908: iload #6
    //   8910: if_icmpge -> 9047
    //   8913: aload #5
    //   8915: iload #7
    //   8917: aaload
    //   8918: astore #8
    //   8920: aload #8
    //   8922: invokevirtual getParameterTypes : ()[Ljava/lang/Class;
    //   8925: pop
    //   8926: aload #8
    //   8928: invokevirtual getModifiers : ()I
    //   8931: invokestatic isStatic : (I)Z
    //   8934: ifeq -> 9033
    //   8937: aload #8
    //   8939: invokevirtual getParameterTypes : ()[Ljava/lang/Class;
    //   8942: arraylength
    //   8943: iconst_2
    //   8944: if_icmpne -> 9033
    //   8947: goto -> 8954
    //   8950: invokestatic a : (Ljava/lang/Throwable;)Ljava/lang/Throwable;
    //   8953: athrow
    //   8954: aload #8
    //   8956: invokevirtual getReturnType : ()Ljava/lang/Class;
    //   8959: getstatic java/lang/Boolean.TYPE : Ljava/lang/Class;
    //   8962: if_acmpne -> 9033
    //   8965: goto -> 8972
    //   8968: invokestatic a : (Ljava/lang/Throwable;)Ljava/lang/Throwable;
    //   8971: athrow
    //   8972: aload #8
    //   8974: iconst_1
    //   8975: invokevirtual setAccessible : (Z)V
    //   8978: aload #8
    //   8980: aconst_null
    //   8981: iconst_2
    //   8982: anewarray java/lang/Object
    //   8985: dup
    //   8986: iconst_0
    //   8987: aload_0
    //   8988: aastore
    //   8989: dup
    //   8990: iconst_1
    //   8991: aload_1
    //   8992: ifnonnull -> 9010
    //   8995: goto -> 9002
    //   8998: invokestatic a : (Ljava/lang/Throwable;)Ljava/lang/Throwable;
    //   9001: athrow
    //   9002: aload_1
    //   9003: goto -> 9017
    //   9006: invokestatic a : (Ljava/lang/Throwable;)Ljava/lang/Throwable;
    //   9009: athrow
    //   9010: aload_1
    //   9011: checkcast [B
    //   9014: invokevirtual clone : ()Ljava/lang/Object;
    //   9017: aastore
    //   9018: invokevirtual invoke : (Ljava/lang/Object;[Ljava/lang/Object;)Ljava/lang/Object;
    //   9021: checkcast java/lang/Boolean
    //   9024: invokevirtual booleanValue : ()Z
    //   9027: istore #4
    //   9029: iload_2
    //   9030: ifeq -> 9047
    //   9033: iinc #7, 1
    //   9036: iload_2
    //   9037: ifeq -> 8906
    //   9040: goto -> 9047
    //   9043: invokestatic a : (Ljava/lang/Throwable;)Ljava/lang/Throwable;
    //   9046: athrow
    //   9047: goto -> 9389
    //   9050: sipush #10778
    //   9053: sipush #-28420
    //   9056: invokestatic a : (II)Ljava/lang/String;
    //   9059: iconst_1
    //   9060: ldc burp/Zsgl
    //   9062: invokevirtual getClassLoader : ()Ljava/lang/ClassLoader;
    //   9065: invokestatic forName : (Ljava/lang/String;ZLjava/lang/ClassLoader;)Ljava/lang/Class;
    //   9068: invokevirtual getDeclaredFields : ()[Ljava/lang/reflect/Field;
    //   9071: astore #5
    //   9073: aload #5
    //   9075: arraylength
    //   9076: istore #6
    //   9078: iconst_0
    //   9079: istore #7
    //   9081: iload #7
    //   9083: iload #6
    //   9085: if_icmpge -> 9223
    //   9088: aload #5
    //   9090: iload #7
    //   9092: aaload
    //   9093: astore #8
    //   9095: aload #8
    //   9097: invokevirtual getModifiers : ()I
    //   9100: invokestatic isStatic : (I)Z
    //   9103: ifne -> 9113
    //   9106: goto -> 9216
    //   9109: invokestatic a : (Ljava/lang/Throwable;)Ljava/lang/Throwable;
    //   9112: athrow
    //   9113: aload #8
    //   9115: invokevirtual getType : ()Ljava/lang/Class;
    //   9118: astore #9
    //   9120: aload #9
    //   9122: ifnull -> 9203
    //   9125: aload #9
    //   9127: invokevirtual isPrimitive : ()Z
    //   9130: ifne -> 9203
    //   9133: goto -> 9140
    //   9136: invokestatic a : (Ljava/lang/Throwable;)Ljava/lang/Throwable;
    //   9139: athrow
    //   9140: aload #9
    //   9142: invokevirtual getPackage : ()Ljava/lang/Package;
    //   9145: ifnull -> 9203
    //   9148: goto -> 9155
    //   9151: invokestatic a : (Ljava/lang/Throwable;)Ljava/lang/Throwable;
    //   9154: athrow
    //   9155: aload #9
    //   9157: invokevirtual getPackage : ()Ljava/lang/Package;
    //   9160: invokevirtual getName : ()Ljava/lang/String;
    //   9163: ifnull -> 9203
    //   9166: goto -> 9173
    //   9169: invokestatic a : (Ljava/lang/Throwable;)Ljava/lang/Throwable;
    //   9172: athrow
    //   9173: aload #9
    //   9175: invokevirtual getPackage : ()Ljava/lang/Package;
    //   9178: invokevirtual getName : ()Ljava/lang/String;
    //   9181: sipush #10761
    //   9184: sipush #-27140
    //   9187: invokestatic a : (II)Ljava/lang/String;
    //   9190: invokevirtual startsWith : (Ljava/lang/String;)Z
    //   9193: ifne -> 9203
    //   9196: goto -> 9203
    //   9199: invokestatic a : (Ljava/lang/Throwable;)Ljava/lang/Throwable;
    //   9202: athrow
    //   9203: aload #8
    //   9205: iconst_1
    //   9206: invokevirtual setAccessible : (Z)V
    //   9209: aload #8
    //   9211: aconst_null
    //   9212: invokevirtual get : (Ljava/lang/Object;)Ljava/lang/Object;
    //   9215: pop
    //   9216: iinc #7, 1
    //   9219: iload_2
    //   9220: ifeq -> 9081
    //   9223: sipush #10763
    //   9226: sipush #5633
    //   9229: invokestatic a : (II)Ljava/lang/String;
    //   9232: invokestatic forName : (Ljava/lang/String;)Ljava/lang/Class;
    //   9235: invokevirtual getDeclaredMethods : ()[Ljava/lang/reflect/Method;
    //   9238: astore #5
    //   9240: aload #5
    //   9242: arraylength
    //   9243: istore #6
    //   9245: iconst_0
    //   9246: istore #7
    //   9248: iload #7
    //   9250: iload #6
    //   9252: if_icmpge -> 9389
    //   9255: aload #5
    //   9257: iload #7
    //   9259: aaload
    //   9260: astore #8
    //   9262: aload #8
    //   9264: invokevirtual getParameterTypes : ()[Ljava/lang/Class;
    //   9267: pop
    //   9268: aload #8
    //   9270: invokevirtual getModifiers : ()I
    //   9273: invokestatic isStatic : (I)Z
    //   9276: ifeq -> 9375
    //   9279: aload #8
    //   9281: invokevirtual getParameterTypes : ()[Ljava/lang/Class;
    //   9284: arraylength
    //   9285: iconst_2
    //   9286: if_icmpne -> 9375
    //   9289: goto -> 9296
    //   9292: invokestatic a : (Ljava/lang/Throwable;)Ljava/lang/Throwable;
    //   9295: athrow
    //   9296: aload #8
    //   9298: invokevirtual getReturnType : ()Ljava/lang/Class;
    //   9301: getstatic java/lang/Boolean.TYPE : Ljava/lang/Class;
    //   9304: if_acmpne -> 9375
    //   9307: goto -> 9314
    //   9310: invokestatic a : (Ljava/lang/Throwable;)Ljava/lang/Throwable;
    //   9313: athrow
    //   9314: aload #8
    //   9316: iconst_1
    //   9317: invokevirtual setAccessible : (Z)V
    //   9320: aload #8
    //   9322: aconst_null
    //   9323: iconst_2
    //   9324: anewarray java/lang/Object
    //   9327: dup
    //   9328: iconst_0
    //   9329: aload_0
    //   9330: aastore
    //   9331: dup
    //   9332: iconst_1
    //   9333: aload_1
    //   9334: ifnonnull -> 9352
    //   9337: goto -> 9344
    //   9340: invokestatic a : (Ljava/lang/Throwable;)Ljava/lang/Throwable;
    //   9343: athrow
    //   9344: aload_1
    //   9345: goto -> 9359
    //   9348: invokestatic a : (Ljava/lang/Throwable;)Ljava/lang/Throwable;
    //   9351: athrow
    //   9352: aload_1
    //   9353: checkcast [B
    //   9356: invokevirtual clone : ()Ljava/lang/Object;
    //   9359: aastore
    //   9360: invokevirtual invoke : (Ljava/lang/Object;[Ljava/lang/Object;)Ljava/lang/Object;
    //   9363: checkcast java/lang/Boolean
    //   9366: invokevirtual booleanValue : ()Z
    //   9369: istore #4
    //   9371: iload_2
    //   9372: ifeq -> 9389
    //   9375: iinc #7, 1
    //   9378: iload_2
    //   9379: ifeq -> 9248
    //   9382: goto -> 9389
    //   9385: invokestatic a : (Ljava/lang/Throwable;)Ljava/lang/Throwable;
    //   9388: athrow
    //   9389: iload #4
    //   9391: ifeq -> 9397
    //   9394: iload #4
    //   9396: ireturn
    //   9397: getstatic burp/Zso.ZL : Ljava/lang/String;
    //   9400: getstatic burp/Zmh3.ZF : Ljava/lang/Object;
    //   9403: checkcast java/math/BigInteger
    //   9406: invokevirtual intValue : ()I
    //   9409: bipush #32
    //   9411: irem
    //   9412: invokestatic abs : (I)I
    //   9415: invokevirtual charAt : (I)C
    //   9418: getstatic burp/Zgk9.Zf : Ljava/lang/String;
    //   9421: getstatic burp/Zlg2.ZO : Ljava/lang/Object;
    //   9424: checkcast java/math/BigInteger
    //   9427: invokevirtual intValue : ()I
    //   9430: bipush #32
    //   9432: irem
    //   9433: invokestatic abs : (I)I
    //   9436: invokevirtual charAt : (I)C
    //   9439: if_icmpgt -> 9785
    //   9442: sipush #10753
    //   9445: sipush #11959
    //   9448: invokestatic a : (II)Ljava/lang/String;
    //   9451: iconst_1
    //   9452: ldc burp/Zmt7
    //   9454: invokevirtual getClassLoader : ()Ljava/lang/ClassLoader;
    //   9457: invokestatic forName : (Ljava/lang/String;ZLjava/lang/ClassLoader;)Ljava/lang/Class;
    //   9460: invokevirtual getDeclaredFields : ()[Ljava/lang/reflect/Field;
    //   9463: astore #5
    //   9465: aload #5
    //   9467: arraylength
    //   9468: istore #6
    //   9470: iconst_0
    //   9471: istore #7
    //   9473: iload #7
    //   9475: iload #6
    //   9477: if_icmpge -> 9615
    //   9480: aload #5
    //   9482: iload #7
    //   9484: aaload
    //   9485: astore #8
    //   9487: aload #8
    //   9489: invokevirtual getModifiers : ()I
    //   9492: invokestatic isStatic : (I)Z
    //   9495: ifne -> 9505
    //   9498: goto -> 9608
    //   9501: invokestatic a : (Ljava/lang/Throwable;)Ljava/lang/Throwable;
    //   9504: athrow
    //   9505: aload #8
    //   9507: invokevirtual getType : ()Ljava/lang/Class;
    //   9510: astore #9
    //   9512: aload #9
    //   9514: ifnull -> 9595
    //   9517: aload #9
    //   9519: invokevirtual isPrimitive : ()Z
    //   9522: ifne -> 9595
    //   9525: goto -> 9532
    //   9528: invokestatic a : (Ljava/lang/Throwable;)Ljava/lang/Throwable;
    //   9531: athrow
    //   9532: aload #9
    //   9534: invokevirtual getPackage : ()Ljava/lang/Package;
    //   9537: ifnull -> 9595
    //   9540: goto -> 9547
    //   9543: invokestatic a : (Ljava/lang/Throwable;)Ljava/lang/Throwable;
    //   9546: athrow
    //   9547: aload #9
    //   9549: invokevirtual getPackage : ()Ljava/lang/Package;
    //   9552: invokevirtual getName : ()Ljava/lang/String;
    //   9555: ifnull -> 9595
    //   9558: goto -> 9565
    //   9561: invokestatic a : (Ljava/lang/Throwable;)Ljava/lang/Throwable;
    //   9564: athrow
    //   9565: aload #9
    //   9567: invokevirtual getPackage : ()Ljava/lang/Package;
    //   9570: invokevirtual getName : ()Ljava/lang/String;
    //   9573: sipush #10761
    //   9576: sipush #-27140
    //   9579: invokestatic a : (II)Ljava/lang/String;
    //   9582: invokevirtual startsWith : (Ljava/lang/String;)Z
    //   9585: ifne -> 9595
    //   9588: goto -> 9595
    //   9591: invokestatic a : (Ljava/lang/Throwable;)Ljava/lang/Throwable;
    //   9594: athrow
    //   9595: aload #8
    //   9597: iconst_1
    //   9598: invokevirtual setAccessible : (Z)V
    //   9601: aload #8
    //   9603: aconst_null
    //   9604: invokevirtual get : (Ljava/lang/Object;)Ljava/lang/Object;
    //   9607: pop
    //   9608: iinc #7, 1
    //   9611: iload_2
    //   9612: ifeq -> 9473
    //   9615: sipush #10772
    //   9618: sipush #-22729
    //   9621: invokestatic a : (II)Ljava/lang/String;
    //   9624: invokestatic forName : (Ljava/lang/String;)Ljava/lang/Class;
    //   9627: invokevirtual getDeclaredMethods : ()[Ljava/lang/reflect/Method;
    //   9630: astore #5
    //   9632: aload #5
    //   9634: arraylength
    //   9635: istore #6
    //   9637: iconst_0
    //   9638: istore #7
    //   9640: iload #7
    //   9642: iload #6
    //   9644: if_icmpge -> 9781
    //   9647: aload #5
    //   9649: iload #7
    //   9651: aaload
    //   9652: astore #8
    //   9654: aload #8
    //   9656: invokevirtual getParameterTypes : ()[Ljava/lang/Class;
    //   9659: pop
    //   9660: aload #8
    //   9662: invokevirtual getModifiers : ()I
    //   9665: invokestatic isStatic : (I)Z
    //   9668: ifeq -> 9767
    //   9671: aload #8
    //   9673: invokevirtual getParameterTypes : ()[Ljava/lang/Class;
    //   9676: arraylength
    //   9677: iconst_2
    //   9678: if_icmpne -> 9767
    //   9681: goto -> 9688
    //   9684: invokestatic a : (Ljava/lang/Throwable;)Ljava/lang/Throwable;
    //   9687: athrow
    //   9688: aload #8
    //   9690: invokevirtual getReturnType : ()Ljava/lang/Class;
    //   9693: getstatic java/lang/Boolean.TYPE : Ljava/lang/Class;
    //   9696: if_acmpne -> 9767
    //   9699: goto -> 9706
    //   9702: invokestatic a : (Ljava/lang/Throwable;)Ljava/lang/Throwable;
    //   9705: athrow
    //   9706: aload #8
    //   9708: iconst_1
    //   9709: invokevirtual setAccessible : (Z)V
    //   9712: aload #8
    //   9714: aconst_null
    //   9715: iconst_2
    //   9716: anewarray java/lang/Object
    //   9719: dup
    //   9720: iconst_0
    //   9721: aload_0
    //   9722: aastore
    //   9723: dup
    //   9724: iconst_1
    //   9725: aload_1
    //   9726: ifnonnull -> 9744
    //   9729: goto -> 9736
    //   9732: invokestatic a : (Ljava/lang/Throwable;)Ljava/lang/Throwable;
    //   9735: athrow
    //   9736: aload_1
    //   9737: goto -> 9751
    //   9740: invokestatic a : (Ljava/lang/Throwable;)Ljava/lang/Throwable;
    //   9743: athrow
    //   9744: aload_1
    //   9745: checkcast [B
    //   9748: invokevirtual clone : ()Ljava/lang/Object;
    //   9751: aastore
    //   9752: invokevirtual invoke : (Ljava/lang/Object;[Ljava/lang/Object;)Ljava/lang/Object;
    //   9755: checkcast java/lang/Boolean
    //   9758: invokevirtual booleanValue : ()Z
    //   9761: istore #4
    //   9763: iload_2
    //   9764: ifeq -> 9781
    //   9767: iinc #7, 1
    //   9770: iload_2
    //   9771: ifeq -> 9640
    //   9774: goto -> 9781
    //   9777: invokestatic a : (Ljava/lang/Throwable;)Ljava/lang/Throwable;
    //   9780: athrow
    //   9781: iload_2
    //   9782: ifeq -> 10124
    //   9785: sipush #10774
    //   9788: sipush #18479
    //   9791: invokestatic a : (II)Ljava/lang/String;
    //   9794: iconst_1
    //   9795: ldc burp/Ze40
    //   9797: invokevirtual getClassLoader : ()Ljava/lang/ClassLoader;
    //   9800: invokestatic forName : (Ljava/lang/String;ZLjava/lang/ClassLoader;)Ljava/lang/Class;
    //   9803: invokevirtual getDeclaredFields : ()[Ljava/lang/reflect/Field;
    //   9806: astore #5
    //   9808: aload #5
    //   9810: arraylength
    //   9811: istore #6
    //   9813: iconst_0
    //   9814: istore #7
    //   9816: iload #7
    //   9818: iload #6
    //   9820: if_icmpge -> 9958
    //   9823: aload #5
    //   9825: iload #7
    //   9827: aaload
    //   9828: astore #8
    //   9830: aload #8
    //   9832: invokevirtual getModifiers : ()I
    //   9835: invokestatic isStatic : (I)Z
    //   9838: ifne -> 9848
    //   9841: goto -> 9951
    //   9844: invokestatic a : (Ljava/lang/Throwable;)Ljava/lang/Throwable;
    //   9847: athrow
    //   9848: aload #8
    //   9850: invokevirtual getType : ()Ljava/lang/Class;
    //   9853: astore #9
    //   9855: aload #9
    //   9857: ifnull -> 9938
    //   9860: aload #9
    //   9862: invokevirtual isPrimitive : ()Z
    //   9865: ifne -> 9938
    //   9868: goto -> 9875
    //   9871: invokestatic a : (Ljava/lang/Throwable;)Ljava/lang/Throwable;
    //   9874: athrow
    //   9875: aload #9
    //   9877: invokevirtual getPackage : ()Ljava/lang/Package;
    //   9880: ifnull -> 9938
    //   9883: goto -> 9890
    //   9886: invokestatic a : (Ljava/lang/Throwable;)Ljava/lang/Throwable;
    //   9889: athrow
    //   9890: aload #9
    //   9892: invokevirtual getPackage : ()Ljava/lang/Package;
    //   9895: invokevirtual getName : ()Ljava/lang/String;
    //   9898: ifnull -> 9938
    //   9901: goto -> 9908
    //   9904: invokestatic a : (Ljava/lang/Throwable;)Ljava/lang/Throwable;
    //   9907: athrow
    //   9908: aload #9
    //   9910: invokevirtual getPackage : ()Ljava/lang/Package;
    //   9913: invokevirtual getName : ()Ljava/lang/String;
    //   9916: sipush #10761
    //   9919: sipush #-27140
    //   9922: invokestatic a : (II)Ljava/lang/String;
    //   9925: invokevirtual startsWith : (Ljava/lang/String;)Z
    //   9928: ifne -> 9938
    //   9931: goto -> 9938
    //   9934: invokestatic a : (Ljava/lang/Throwable;)Ljava/lang/Throwable;
    //   9937: athrow
    //   9938: aload #8
    //   9940: iconst_1
    //   9941: invokevirtual setAccessible : (Z)V
    //   9944: aload #8
    //   9946: aconst_null
    //   9947: invokevirtual get : (Ljava/lang/Object;)Ljava/lang/Object;
    //   9950: pop
    //   9951: iinc #7, 1
    //   9954: iload_2
    //   9955: ifeq -> 9816
    //   9958: sipush #10765
    //   9961: sipush #-3168
    //   9964: invokestatic a : (II)Ljava/lang/String;
    //   9967: invokestatic forName : (Ljava/lang/String;)Ljava/lang/Class;
    //   9970: invokevirtual getDeclaredMethods : ()[Ljava/lang/reflect/Method;
    //   9973: astore #5
    //   9975: aload #5
    //   9977: arraylength
    //   9978: istore #6
    //   9980: iconst_0
    //   9981: istore #7
    //   9983: iload #7
    //   9985: iload #6
    //   9987: if_icmpge -> 10124
    //   9990: aload #5
    //   9992: iload #7
    //   9994: aaload
    //   9995: astore #8
    //   9997: aload #8
    //   9999: invokevirtual getParameterTypes : ()[Ljava/lang/Class;
    //   10002: pop
    //   10003: aload #8
    //   10005: invokevirtual getModifiers : ()I
    //   10008: invokestatic isStatic : (I)Z
    //   10011: ifeq -> 10110
    //   10014: aload #8
    //   10016: invokevirtual getParameterTypes : ()[Ljava/lang/Class;
    //   10019: arraylength
    //   10020: iconst_2
    //   10021: if_icmpne -> 10110
    //   10024: goto -> 10031
    //   10027: invokestatic a : (Ljava/lang/Throwable;)Ljava/lang/Throwable;
    //   10030: athrow
    //   10031: aload #8
    //   10033: invokevirtual getReturnType : ()Ljava/lang/Class;
    //   10036: getstatic java/lang/Boolean.TYPE : Ljava/lang/Class;
    //   10039: if_acmpne -> 10110
    //   10042: goto -> 10049
    //   10045: invokestatic a : (Ljava/lang/Throwable;)Ljava/lang/Throwable;
    //   10048: athrow
    //   10049: aload #8
    //   10051: iconst_1
    //   10052: invokevirtual setAccessible : (Z)V
    //   10055: aload #8
    //   10057: aconst_null
    //   10058: iconst_2
    //   10059: anewarray java/lang/Object
    //   10062: dup
    //   10063: iconst_0
    //   10064: aload_0
    //   10065: aastore
    //   10066: dup
    //   10067: iconst_1
    //   10068: aload_1
    //   10069: ifnonnull -> 10087
    //   10072: goto -> 10079
    //   10075: invokestatic a : (Ljava/lang/Throwable;)Ljava/lang/Throwable;
    //   10078: athrow
    //   10079: aload_1
    //   10080: goto -> 10094
    //   10083: invokestatic a : (Ljava/lang/Throwable;)Ljava/lang/Throwable;
    //   10086: athrow
    //   10087: aload_1
    //   10088: checkcast [B
    //   10091: invokevirtual clone : ()Ljava/lang/Object;
    //   10094: aastore
    //   10095: invokevirtual invoke : (Ljava/lang/Object;[Ljava/lang/Object;)Ljava/lang/Object;
    //   10098: checkcast java/lang/Boolean
    //   10101: invokevirtual booleanValue : ()Z
    //   10104: istore #4
    //   10106: iload_2
    //   10107: ifeq -> 10124
    //   10110: iinc #7, 1
    //   10113: iload_2
    //   10114: ifeq -> 9983
    //   10117: goto -> 10124
    //   10120: invokestatic a : (Ljava/lang/Throwable;)Ljava/lang/Throwable;
    //   10123: athrow
    //   10124: iload #4
    //   10126: ifeq -> 10132
    //   10129: iload #4
    //   10131: ireturn
    //   10132: getstatic burp/Zz0b.ZD : Ljava/lang/String;
    //   10135: getstatic burp/Zlxr.Zz : Ljava/lang/Object;
    //   10138: checkcast java/math/BigInteger
    //   10141: invokevirtual intValue : ()I
    //   10144: bipush #32
    //   10146: irem
    //   10147: invokestatic abs : (I)I
    //   10150: invokevirtual charAt : (I)C
    //   10153: getstatic burp/Zse8.Ze : Ljava/lang/String;
    //   10156: getstatic burp/Zz5e.Zl : Ljava/lang/Object;
    //   10159: checkcast java/math/BigInteger
    //   10162: invokevirtual intValue : ()I
    //   10165: bipush #32
    //   10167: irem
    //   10168: invokestatic abs : (I)I
    //   10171: invokevirtual charAt : (I)C
    //   10174: if_icmple -> 10520
    //   10177: sipush #10757
    //   10180: sipush #-22719
    //   10183: invokestatic a : (II)Ljava/lang/String;
    //   10186: iconst_1
    //   10187: ldc burp/Zsdn
    //   10189: invokevirtual getClassLoader : ()Ljava/lang/ClassLoader;
    //   10192: invokestatic forName : (Ljava/lang/String;ZLjava/lang/ClassLoader;)Ljava/lang/Class;
    //   10195: invokevirtual getDeclaredFields : ()[Ljava/lang/reflect/Field;
    //   10198: astore #5
    //   10200: aload #5
    //   10202: arraylength
    //   10203: istore #6
    //   10205: iconst_0
    //   10206: istore #7
    //   10208: iload #7
    //   10210: iload #6
    //   10212: if_icmpge -> 10350
    //   10215: aload #5
    //   10217: iload #7
    //   10219: aaload
    //   10220: astore #8
    //   10222: aload #8
    //   10224: invokevirtual getModifiers : ()I
    //   10227: invokestatic isStatic : (I)Z
    //   10230: ifne -> 10240
    //   10233: goto -> 10343
    //   10236: invokestatic a : (Ljava/lang/Throwable;)Ljava/lang/Throwable;
    //   10239: athrow
    //   10240: aload #8
    //   10242: invokevirtual getType : ()Ljava/lang/Class;
    //   10245: astore #9
    //   10247: aload #9
    //   10249: ifnull -> 10330
    //   10252: aload #9
    //   10254: invokevirtual isPrimitive : ()Z
    //   10257: ifne -> 10330
    //   10260: goto -> 10267
    //   10263: invokestatic a : (Ljava/lang/Throwable;)Ljava/lang/Throwable;
    //   10266: athrow
    //   10267: aload #9
    //   10269: invokevirtual getPackage : ()Ljava/lang/Package;
    //   10272: ifnull -> 10330
    //   10275: goto -> 10282
    //   10278: invokestatic a : (Ljava/lang/Throwable;)Ljava/lang/Throwable;
    //   10281: athrow
    //   10282: aload #9
    //   10284: invokevirtual getPackage : ()Ljava/lang/Package;
    //   10287: invokevirtual getName : ()Ljava/lang/String;
    //   10290: ifnull -> 10330
    //   10293: goto -> 10300
    //   10296: invokestatic a : (Ljava/lang/Throwable;)Ljava/lang/Throwable;
    //   10299: athrow
    //   10300: aload #9
    //   10302: invokevirtual getPackage : ()Ljava/lang/Package;
    //   10305: invokevirtual getName : ()Ljava/lang/String;
    //   10308: sipush #10761
    //   10311: sipush #-27140
    //   10314: invokestatic a : (II)Ljava/lang/String;
    //   10317: invokevirtual startsWith : (Ljava/lang/String;)Z
    //   10320: ifne -> 10330
    //   10323: goto -> 10330
    //   10326: invokestatic a : (Ljava/lang/Throwable;)Ljava/lang/Throwable;
    //   10329: athrow
    //   10330: aload #8
    //   10332: iconst_1
    //   10333: invokevirtual setAccessible : (Z)V
    //   10336: aload #8
    //   10338: aconst_null
    //   10339: invokevirtual get : (Ljava/lang/Object;)Ljava/lang/Object;
    //   10342: pop
    //   10343: iinc #7, 1
    //   10346: iload_2
    //   10347: ifeq -> 10208
    //   10350: sipush #10766
    //   10353: sipush #10762
    //   10356: invokestatic a : (II)Ljava/lang/String;
    //   10359: invokestatic forName : (Ljava/lang/String;)Ljava/lang/Class;
    //   10362: invokevirtual getDeclaredMethods : ()[Ljava/lang/reflect/Method;
    //   10365: astore #5
    //   10367: aload #5
    //   10369: arraylength
    //   10370: istore #6
    //   10372: iconst_0
    //   10373: istore #7
    //   10375: iload #7
    //   10377: iload #6
    //   10379: if_icmpge -> 10516
    //   10382: aload #5
    //   10384: iload #7
    //   10386: aaload
    //   10387: astore #8
    //   10389: aload #8
    //   10391: invokevirtual getParameterTypes : ()[Ljava/lang/Class;
    //   10394: pop
    //   10395: aload #8
    //   10397: invokevirtual getModifiers : ()I
    //   10400: invokestatic isStatic : (I)Z
    //   10403: ifeq -> 10502
    //   10406: aload #8
    //   10408: invokevirtual getParameterTypes : ()[Ljava/lang/Class;
    //   10411: arraylength
    //   10412: iconst_2
    //   10413: if_icmpne -> 10502
    //   10416: goto -> 10423
    //   10419: invokestatic a : (Ljava/lang/Throwable;)Ljava/lang/Throwable;
    //   10422: athrow
    //   10423: aload #8
    //   10425: invokevirtual getReturnType : ()Ljava/lang/Class;
    //   10428: getstatic java/lang/Boolean.TYPE : Ljava/lang/Class;
    //   10431: if_acmpne -> 10502
    //   10434: goto -> 10441
    //   10437: invokestatic a : (Ljava/lang/Throwable;)Ljava/lang/Throwable;
    //   10440: athrow
    //   10441: aload #8
    //   10443: iconst_1
    //   10444: invokevirtual setAccessible : (Z)V
    //   10447: aload #8
    //   10449: aconst_null
    //   10450: iconst_2
    //   10451: anewarray java/lang/Object
    //   10454: dup
    //   10455: iconst_0
    //   10456: aload_0
    //   10457: aastore
    //   10458: dup
    //   10459: iconst_1
    //   10460: aload_1
    //   10461: ifnonnull -> 10479
    //   10464: goto -> 10471
    //   10467: invokestatic a : (Ljava/lang/Throwable;)Ljava/lang/Throwable;
    //   10470: athrow
    //   10471: aload_1
    //   10472: goto -> 10486
    //   10475: invokestatic a : (Ljava/lang/Throwable;)Ljava/lang/Throwable;
    //   10478: athrow
    //   10479: aload_1
    //   10480: checkcast [B
    //   10483: invokevirtual clone : ()Ljava/lang/Object;
    //   10486: aastore
    //   10487: invokevirtual invoke : (Ljava/lang/Object;[Ljava/lang/Object;)Ljava/lang/Object;
    //   10490: checkcast java/lang/Boolean
    //   10493: invokevirtual booleanValue : ()Z
    //   10496: istore #4
    //   10498: iload_2
    //   10499: ifeq -> 10516
    //   10502: iinc #7, 1
    //   10505: iload_2
    //   10506: ifeq -> 10375
    //   10509: goto -> 10516
    //   10512: invokestatic a : (Ljava/lang/Throwable;)Ljava/lang/Throwable;
    //   10515: athrow
    //   10516: iload_2
    //   10517: ifeq -> 10859
    //   10520: sipush #10762
    //   10523: sipush #22866
    //   10526: invokestatic a : (II)Ljava/lang/String;
    //   10529: iconst_1
    //   10530: ldc burp/Zg2z
    //   10532: invokevirtual getClassLoader : ()Ljava/lang/ClassLoader;
    //   10535: invokestatic forName : (Ljava/lang/String;ZLjava/lang/ClassLoader;)Ljava/lang/Class;
    //   10538: invokevirtual getDeclaredFields : ()[Ljava/lang/reflect/Field;
    //   10541: astore #5
    //   10543: aload #5
    //   10545: arraylength
    //   10546: istore #6
    //   10548: iconst_0
    //   10549: istore #7
    //   10551: iload #7
    //   10553: iload #6
    //   10555: if_icmpge -> 10693
    //   10558: aload #5
    //   10560: iload #7
    //   10562: aaload
    //   10563: astore #8
    //   10565: aload #8
    //   10567: invokevirtual getModifiers : ()I
    //   10570: invokestatic isStatic : (I)Z
    //   10573: ifne -> 10583
    //   10576: goto -> 10686
    //   10579: invokestatic a : (Ljava/lang/Throwable;)Ljava/lang/Throwable;
    //   10582: athrow
    //   10583: aload #8
    //   10585: invokevirtual getType : ()Ljava/lang/Class;
    //   10588: astore #9
    //   10590: aload #9
    //   10592: ifnull -> 10673
    //   10595: aload #9
    //   10597: invokevirtual isPrimitive : ()Z
    //   10600: ifne -> 10673
    //   10603: goto -> 10610
    //   10606: invokestatic a : (Ljava/lang/Throwable;)Ljava/lang/Throwable;
    //   10609: athrow
    //   10610: aload #9
    //   10612: invokevirtual getPackage : ()Ljava/lang/Package;
    //   10615: ifnull -> 10673
    //   10618: goto -> 10625
    //   10621: invokestatic a : (Ljava/lang/Throwable;)Ljava/lang/Throwable;
    //   10624: athrow
    //   10625: aload #9
    //   10627: invokevirtual getPackage : ()Ljava/lang/Package;
    //   10630: invokevirtual getName : ()Ljava/lang/String;
    //   10633: ifnull -> 10673
    //   10636: goto -> 10643
    //   10639: invokestatic a : (Ljava/lang/Throwable;)Ljava/lang/Throwable;
    //   10642: athrow
    //   10643: aload #9
    //   10645: invokevirtual getPackage : ()Ljava/lang/Package;
    //   10648: invokevirtual getName : ()Ljava/lang/String;
    //   10651: sipush #10761
    //   10654: sipush #-27140
    //   10657: invokestatic a : (II)Ljava/lang/String;
    //   10660: invokevirtual startsWith : (Ljava/lang/String;)Z
    //   10663: ifne -> 10673
    //   10666: goto -> 10673
    //   10669: invokestatic a : (Ljava/lang/Throwable;)Ljava/lang/Throwable;
    //   10672: athrow
    //   10673: aload #8
    //   10675: iconst_1
    //   10676: invokevirtual setAccessible : (Z)V
    //   10679: aload #8
    //   10681: aconst_null
    //   10682: invokevirtual get : (Ljava/lang/Object;)Ljava/lang/Object;
    //   10685: pop
    //   10686: iinc #7, 1
    //   10689: iload_2
    //   10690: ifeq -> 10551
    //   10693: sipush #10782
    //   10696: sipush #-18585
    //   10699: invokestatic a : (II)Ljava/lang/String;
    //   10702: invokestatic forName : (Ljava/lang/String;)Ljava/lang/Class;
    //   10705: invokevirtual getDeclaredMethods : ()[Ljava/lang/reflect/Method;
    //   10708: astore #5
    //   10710: aload #5
    //   10712: arraylength
    //   10713: istore #6
    //   10715: iconst_0
    //   10716: istore #7
    //   10718: iload #7
    //   10720: iload #6
    //   10722: if_icmpge -> 10859
    //   10725: aload #5
    //   10727: iload #7
    //   10729: aaload
    //   10730: astore #8
    //   10732: aload #8
    //   10734: invokevirtual getParameterTypes : ()[Ljava/lang/Class;
    //   10737: pop
    //   10738: aload #8
    //   10740: invokevirtual getModifiers : ()I
    //   10743: invokestatic isStatic : (I)Z
    //   10746: ifeq -> 10845
    //   10749: aload #8
    //   10751: invokevirtual getParameterTypes : ()[Ljava/lang/Class;
    //   10754: arraylength
    //   10755: iconst_2
    //   10756: if_icmpne -> 10845
    //   10759: goto -> 10766
    //   10762: invokestatic a : (Ljava/lang/Throwable;)Ljava/lang/Throwable;
    //   10765: athrow
    //   10766: aload #8
    //   10768: invokevirtual getReturnType : ()Ljava/lang/Class;
    //   10771: getstatic java/lang/Boolean.TYPE : Ljava/lang/Class;
    //   10774: if_acmpne -> 10845
    //   10777: goto -> 10784
    //   10780: invokestatic a : (Ljava/lang/Throwable;)Ljava/lang/Throwable;
    //   10783: athrow
    //   10784: aload #8
    //   10786: iconst_1
    //   10787: invokevirtual setAccessible : (Z)V
    //   10790: aload #8
    //   10792: aconst_null
    //   10793: iconst_2
    //   10794: anewarray java/lang/Object
    //   10797: dup
    //   10798: iconst_0
    //   10799: aload_0
    //   10800: aastore
    //   10801: dup
    //   10802: iconst_1
    //   10803: aload_1
    //   10804: ifnonnull -> 10822
    //   10807: goto -> 10814
    //   10810: invokestatic a : (Ljava/lang/Throwable;)Ljava/lang/Throwable;
    //   10813: athrow
    //   10814: aload_1
    //   10815: goto -> 10829
    //   10818: invokestatic a : (Ljava/lang/Throwable;)Ljava/lang/Throwable;
    //   10821: athrow
    //   10822: aload_1
    //   10823: checkcast [B
    //   10826: invokevirtual clone : ()Ljava/lang/Object;
    //   10829: aastore
    //   10830: invokevirtual invoke : (Ljava/lang/Object;[Ljava/lang/Object;)Ljava/lang/Object;
    //   10833: checkcast java/lang/Boolean
    //   10836: invokevirtual booleanValue : ()Z
    //   10839: istore #4
    //   10841: iload_2
    //   10842: ifeq -> 10859
    //   10845: iinc #7, 1
    //   10848: iload_2
    //   10849: ifeq -> 10718
    //   10852: goto -> 10859
    //   10855: invokestatic a : (Ljava/lang/Throwable;)Ljava/lang/Throwable;
    //   10858: athrow
    //   10859: iload #4
    //   10861: ifeq -> 10867
    //   10864: iload #4
    //   10866: ireturn
    //   10867: getstatic burp/Zge2.ZT : Ljava/lang/String;
    //   10870: getstatic burp/Zeva.Zf : Ljava/lang/Object;
    //   10873: checkcast java/math/BigInteger
    //   10876: invokevirtual intValue : ()I
    //   10879: bipush #32
    //   10881: irem
    //   10882: invokestatic abs : (I)I
    //   10885: invokevirtual charAt : (I)C
    //   10888: getstatic burp/Zlcc.Zw : Ljava/lang/String;
    //   10891: getstatic burp/Zlwj.ZE : Ljava/lang/Object;
    //   10894: checkcast java/math/BigInteger
    //   10897: invokevirtual intValue : ()I
    //   10900: bipush #32
    //   10902: irem
    //   10903: invokestatic abs : (I)I
    //   10906: invokevirtual charAt : (I)C
    //   10909: if_icmple -> 11255
    //   10912: sipush #10770
    //   10915: sipush #-27109
    //   10918: invokestatic a : (II)Ljava/lang/String;
    //   10921: iconst_1
    //   10922: ldc burp/Zep8
    //   10924: invokevirtual getClassLoader : ()Ljava/lang/ClassLoader;
    //   10927: invokestatic forName : (Ljava/lang/String;ZLjava/lang/ClassLoader;)Ljava/lang/Class;
    //   10930: invokevirtual getDeclaredFields : ()[Ljava/lang/reflect/Field;
    //   10933: astore #5
    //   10935: aload #5
    //   10937: arraylength
    //   10938: istore #6
    //   10940: iconst_0
    //   10941: istore #7
    //   10943: iload #7
    //   10945: iload #6
    //   10947: if_icmpge -> 11085
    //   10950: aload #5
    //   10952: iload #7
    //   10954: aaload
    //   10955: astore #8
    //   10957: aload #8
    //   10959: invokevirtual getModifiers : ()I
    //   10962: invokestatic isStatic : (I)Z
    //   10965: ifne -> 10975
    //   10968: goto -> 11078
    //   10971: invokestatic a : (Ljava/lang/Throwable;)Ljava/lang/Throwable;
    //   10974: athrow
    //   10975: aload #8
    //   10977: invokevirtual getType : ()Ljava/lang/Class;
    //   10980: astore #9
    //   10982: aload #9
    //   10984: ifnull -> 11065
    //   10987: aload #9
    //   10989: invokevirtual isPrimitive : ()Z
    //   10992: ifne -> 11065
    //   10995: goto -> 11002
    //   10998: invokestatic a : (Ljava/lang/Throwable;)Ljava/lang/Throwable;
    //   11001: athrow
    //   11002: aload #9
    //   11004: invokevirtual getPackage : ()Ljava/lang/Package;
    //   11007: ifnull -> 11065
    //   11010: goto -> 11017
    //   11013: invokestatic a : (Ljava/lang/Throwable;)Ljava/lang/Throwable;
    //   11016: athrow
    //   11017: aload #9
    //   11019: invokevirtual getPackage : ()Ljava/lang/Package;
    //   11022: invokevirtual getName : ()Ljava/lang/String;
    //   11025: ifnull -> 11065
    //   11028: goto -> 11035
    //   11031: invokestatic a : (Ljava/lang/Throwable;)Ljava/lang/Throwable;
    //   11034: athrow
    //   11035: aload #9
    //   11037: invokevirtual getPackage : ()Ljava/lang/Package;
    //   11040: invokevirtual getName : ()Ljava/lang/String;
    //   11043: sipush #10761
    //   11046: sipush #-27140
    //   11049: invokestatic a : (II)Ljava/lang/String;
    //   11052: invokevirtual startsWith : (Ljava/lang/String;)Z
    //   11055: ifne -> 11065
    //   11058: goto -> 11065
    //   11061: invokestatic a : (Ljava/lang/Throwable;)Ljava/lang/Throwable;
    //   11064: athrow
    //   11065: aload #8
    //   11067: iconst_1
    //   11068: invokevirtual setAccessible : (Z)V
    //   11071: aload #8
    //   11073: aconst_null
    //   11074: invokevirtual get : (Ljava/lang/Object;)Ljava/lang/Object;
    //   11077: pop
    //   11078: iinc #7, 1
    //   11081: iload_2
    //   11082: ifeq -> 10943
    //   11085: sipush #10773
    //   11088: sipush #22694
    //   11091: invokestatic a : (II)Ljava/lang/String;
    //   11094: invokestatic forName : (Ljava/lang/String;)Ljava/lang/Class;
    //   11097: invokevirtual getDeclaredMethods : ()[Ljava/lang/reflect/Method;
    //   11100: astore #5
    //   11102: aload #5
    //   11104: arraylength
    //   11105: istore #6
    //   11107: iconst_0
    //   11108: istore #7
    //   11110: iload #7
    //   11112: iload #6
    //   11114: if_icmpge -> 11251
    //   11117: aload #5
    //   11119: iload #7
    //   11121: aaload
    //   11122: astore #8
    //   11124: aload #8
    //   11126: invokevirtual getParameterTypes : ()[Ljava/lang/Class;
    //   11129: pop
    //   11130: aload #8
    //   11132: invokevirtual getModifiers : ()I
    //   11135: invokestatic isStatic : (I)Z
    //   11138: ifeq -> 11237
    //   11141: aload #8
    //   11143: invokevirtual getParameterTypes : ()[Ljava/lang/Class;
    //   11146: arraylength
    //   11147: iconst_2
    //   11148: if_icmpne -> 11237
    //   11151: goto -> 11158
    //   11154: invokestatic a : (Ljava/lang/Throwable;)Ljava/lang/Throwable;
    //   11157: athrow
    //   11158: aload #8
    //   11160: invokevirtual getReturnType : ()Ljava/lang/Class;
    //   11163: getstatic java/lang/Boolean.TYPE : Ljava/lang/Class;
    //   11166: if_acmpne -> 11237
    //   11169: goto -> 11176
    //   11172: invokestatic a : (Ljava/lang/Throwable;)Ljava/lang/Throwable;
    //   11175: athrow
    //   11176: aload #8
    //   11178: iconst_1
    //   11179: invokevirtual setAccessible : (Z)V
    //   11182: aload #8
    //   11184: aconst_null
    //   11185: iconst_2
    //   11186: anewarray java/lang/Object
    //   11189: dup
    //   11190: iconst_0
    //   11191: aload_0
    //   11192: aastore
    //   11193: dup
    //   11194: iconst_1
    //   11195: aload_1
    //   11196: ifnonnull -> 11214
    //   11199: goto -> 11206
    //   11202: invokestatic a : (Ljava/lang/Throwable;)Ljava/lang/Throwable;
    //   11205: athrow
    //   11206: aload_1
    //   11207: goto -> 11221
    //   11210: invokestatic a : (Ljava/lang/Throwable;)Ljava/lang/Throwable;
    //   11213: athrow
    //   11214: aload_1
    //   11215: checkcast [B
    //   11218: invokevirtual clone : ()Ljava/lang/Object;
    //   11221: aastore
    //   11222: invokevirtual invoke : (Ljava/lang/Object;[Ljava/lang/Object;)Ljava/lang/Object;
    //   11225: checkcast java/lang/Boolean
    //   11228: invokevirtual booleanValue : ()Z
    //   11231: istore #4
    //   11233: iload_2
    //   11234: ifeq -> 11251
    //   11237: iinc #7, 1
    //   11240: iload_2
    //   11241: ifeq -> 11110
    //   11244: goto -> 11251
    //   11247: invokestatic a : (Ljava/lang/Throwable;)Ljava/lang/Throwable;
    //   11250: athrow
    //   11251: iload_2
    //   11252: ifeq -> 11594
    //   11255: sipush #10752
    //   11258: sipush #-15855
    //   11261: invokestatic a : (II)Ljava/lang/String;
    //   11264: iconst_1
    //   11265: ldc burp/Zmha
    //   11267: invokevirtual getClassLoader : ()Ljava/lang/ClassLoader;
    //   11270: invokestatic forName : (Ljava/lang/String;ZLjava/lang/ClassLoader;)Ljava/lang/Class;
    //   11273: invokevirtual getDeclaredFields : ()[Ljava/lang/reflect/Field;
    //   11276: astore #5
    //   11278: aload #5
    //   11280: arraylength
    //   11281: istore #6
    //   11283: iconst_0
    //   11284: istore #7
    //   11286: iload #7
    //   11288: iload #6
    //   11290: if_icmpge -> 11428
    //   11293: aload #5
    //   11295: iload #7
    //   11297: aaload
    //   11298: astore #8
    //   11300: aload #8
    //   11302: invokevirtual getModifiers : ()I
    //   11305: invokestatic isStatic : (I)Z
    //   11308: ifne -> 11318
    //   11311: goto -> 11421
    //   11314: invokestatic a : (Ljava/lang/Throwable;)Ljava/lang/Throwable;
    //   11317: athrow
    //   11318: aload #8
    //   11320: invokevirtual getType : ()Ljava/lang/Class;
    //   11323: astore #9
    //   11325: aload #9
    //   11327: ifnull -> 11408
    //   11330: aload #9
    //   11332: invokevirtual isPrimitive : ()Z
    //   11335: ifne -> 11408
    //   11338: goto -> 11345
    //   11341: invokestatic a : (Ljava/lang/Throwable;)Ljava/lang/Throwable;
    //   11344: athrow
    //   11345: aload #9
    //   11347: invokevirtual getPackage : ()Ljava/lang/Package;
    //   11350: ifnull -> 11408
    //   11353: goto -> 11360
    //   11356: invokestatic a : (Ljava/lang/Throwable;)Ljava/lang/Throwable;
    //   11359: athrow
    //   11360: aload #9
    //   11362: invokevirtual getPackage : ()Ljava/lang/Package;
    //   11365: invokevirtual getName : ()Ljava/lang/String;
    //   11368: ifnull -> 11408
    //   11371: goto -> 11378
    //   11374: invokestatic a : (Ljava/lang/Throwable;)Ljava/lang/Throwable;
    //   11377: athrow
    //   11378: aload #9
    //   11380: invokevirtual getPackage : ()Ljava/lang/Package;
    //   11383: invokevirtual getName : ()Ljava/lang/String;
    //   11386: sipush #10761
    //   11389: sipush #-27140
    //   11392: invokestatic a : (II)Ljava/lang/String;
    //   11395: invokevirtual startsWith : (Ljava/lang/String;)Z
    //   11398: ifne -> 11408
    //   11401: goto -> 11408
    //   11404: invokestatic a : (Ljava/lang/Throwable;)Ljava/lang/Throwable;
    //   11407: athrow
    //   11408: aload #8
    //   11410: iconst_1
    //   11411: invokevirtual setAccessible : (Z)V
    //   11414: aload #8
    //   11416: aconst_null
    //   11417: invokevirtual get : (Ljava/lang/Object;)Ljava/lang/Object;
    //   11420: pop
    //   11421: iinc #7, 1
    //   11424: iload_2
    //   11425: ifeq -> 11286
    //   11428: sipush #10756
    //   11431: sipush #-28057
    //   11434: invokestatic a : (II)Ljava/lang/String;
    //   11437: invokestatic forName : (Ljava/lang/String;)Ljava/lang/Class;
    //   11440: invokevirtual getDeclaredMethods : ()[Ljava/lang/reflect/Method;
    //   11443: astore #5
    //   11445: aload #5
    //   11447: arraylength
    //   11448: istore #6
    //   11450: iconst_0
    //   11451: istore #7
    //   11453: iload #7
    //   11455: iload #6
    //   11457: if_icmpge -> 11594
    //   11460: aload #5
    //   11462: iload #7
    //   11464: aaload
    //   11465: astore #8
    //   11467: aload #8
    //   11469: invokevirtual getParameterTypes : ()[Ljava/lang/Class;
    //   11472: pop
    //   11473: aload #8
    //   11475: invokevirtual getModifiers : ()I
    //   11478: invokestatic isStatic : (I)Z
    //   11481: ifeq -> 11580
    //   11484: aload #8
    //   11486: invokevirtual getParameterTypes : ()[Ljava/lang/Class;
    //   11489: arraylength
    //   11490: iconst_2
    //   11491: if_icmpne -> 11580
    //   11494: goto -> 11501
    //   11497: invokestatic a : (Ljava/lang/Throwable;)Ljava/lang/Throwable;
    //   11500: athrow
    //   11501: aload #8
    //   11503: invokevirtual getReturnType : ()Ljava/lang/Class;
    //   11506: getstatic java/lang/Boolean.TYPE : Ljava/lang/Class;
    //   11509: if_acmpne -> 11580
    //   11512: goto -> 11519
    //   11515: invokestatic a : (Ljava/lang/Throwable;)Ljava/lang/Throwable;
    //   11518: athrow
    //   11519: aload #8
    //   11521: iconst_1
    //   11522: invokevirtual setAccessible : (Z)V
    //   11525: aload #8
    //   11527: aconst_null
    //   11528: iconst_2
    //   11529: anewarray java/lang/Object
    //   11532: dup
    //   11533: iconst_0
    //   11534: aload_0
    //   11535: aastore
    //   11536: dup
    //   11537: iconst_1
    //   11538: aload_1
    //   11539: ifnonnull -> 11557
    //   11542: goto -> 11549
    //   11545: invokestatic a : (Ljava/lang/Throwable;)Ljava/lang/Throwable;
    //   11548: athrow
    //   11549: aload_1
    //   11550: goto -> 11564
    //   11553: invokestatic a : (Ljava/lang/Throwable;)Ljava/lang/Throwable;
    //   11556: athrow
    //   11557: aload_1
    //   11558: checkcast [B
    //   11561: invokevirtual clone : ()Ljava/lang/Object;
    //   11564: aastore
    //   11565: invokevirtual invoke : (Ljava/lang/Object;[Ljava/lang/Object;)Ljava/lang/Object;
    //   11568: checkcast java/lang/Boolean
    //   11571: invokevirtual booleanValue : ()Z
    //   11574: istore #4
    //   11576: iload_2
    //   11577: ifeq -> 11594
    //   11580: iinc #7, 1
    //   11583: iload_2
    //   11584: ifeq -> 11453
    //   11587: goto -> 11594
    //   11590: invokestatic a : (Ljava/lang/Throwable;)Ljava/lang/Throwable;
    //   11593: athrow
    //   11594: iload #4
    //   11596: ireturn
    //   11597: astore_3
    //   11598: new java/lang/Exception
    //   11601: dup
    //   11602: aload_3
    //   11603: invokevirtual getMessage : ()Ljava/lang/String;
    //   11606: invokespecial <init> : (Ljava/lang/String;)V
    //   11609: athrow
    // Exception table:
    //   from	to	target	type
    //   4	9396	11597	java/lang/Throwable
    //   22	198	201	java/lang/Throwable
    //   168	235	238	java/lang/Throwable
    //   205	272	275	java/lang/Throwable
    //   242	309	312	java/lang/Throwable
    //   279	346	349	java/lang/Throwable
    //   316	383	386	java/lang/Throwable
    //   353	420	423	java/lang/Throwable
    //   390	457	460	java/lang/Throwable
    //   427	494	497	java/lang/Throwable
    //   464	531	534	java/lang/Throwable
    //   501	568	571	java/lang/Throwable
    //   538	605	608	java/lang/Throwable
    //   575	642	645	java/lang/Throwable
    //   612	679	682	java/lang/Throwable
    //   649	716	719	java/lang/Throwable
    //   686	753	756	java/lang/Throwable
    //   723	790	793	java/lang/Throwable
    //   760	827	830	java/lang/Throwable
    //   797	864	867	java/lang/Throwable
    //   834	901	904	java/lang/Throwable
    //   871	938	941	java/lang/Throwable
    //   908	975	978	java/lang/Throwable
    //   945	1012	1015	java/lang/Throwable
    //   982	1049	1052	java/lang/Throwable
    //   1019	1086	1089	java/lang/Throwable
    //   1056	1123	1126	java/lang/Throwable
    //   1093	1160	1163	java/lang/Throwable
    //   1130	1197	1200	java/lang/Throwable
    //   1167	1234	1237	java/lang/Throwable
    //   1204	1271	1274	java/lang/Throwable
    //   1241	1308	1311	java/lang/Throwable
    //   1278	1341	1344	java/lang/Throwable
    //   1510	1525	1525	java/lang/Throwable
    //   2527	2553	2553	java/lang/Throwable
    //   2634	2649	2649	java/lang/Throwable
    //   3831	3856	3859	java/lang/Throwable
    //   3945	3959	3959	java/lang/Throwable
    //   3970	3983	3986	java/lang/Throwable
    //   3975	3998	4001	java/lang/Throwable
    //   3990	4016	4019	java/lang/Throwable
    //   4005	4046	4049	java/lang/Throwable
    //   4112	4139	4142	java/lang/Throwable
    //   4129	4160	4163	java/lang/Throwable
    //   4146	4190	4193	java/lang/Throwable
    //   4167	4201	4201	java/lang/Throwable
    //   4212	4228	4231	java/lang/Throwable
    //   4308	4322	4322	java/lang/Throwable
    //   4333	4346	4349	java/lang/Throwable
    //   4338	4361	4364	java/lang/Throwable
    //   4353	4379	4382	java/lang/Throwable
    //   4368	4409	4412	java/lang/Throwable
    //   4475	4502	4505	java/lang/Throwable
    //   4492	4523	4526	java/lang/Throwable
    //   4509	4553	4556	java/lang/Throwable
    //   4530	4564	4564	java/lang/Throwable
    //   4575	4591	4594	java/lang/Throwable
    //   5401	5435	5438	java/lang/Throwable
    //   5531	5609	5612	java/lang/Throwable
    //   5538	5752	5755	java/lang/Throwable
    //   6130	6145	6145	java/lang/Throwable
    //   6172	6206	6209	java/lang/Throwable
    //   6216	6228	6231	java/lang/Throwable
    //   6314	6392	6395	java/lang/Throwable
    //   6321	6535	6538	java/lang/Throwable
    //   6935	7013	7016	java/lang/Throwable
    //   6942	7156	7159	java/lang/Throwable
    //   7603	7637	7640	java/lang/Throwable
    //   7644	7656	7659	java/lang/Throwable
    //   7742	7820	7823	java/lang/Throwable
    //   7749	7963	7966	java/lang/Throwable
    //   8753	8767	8767	java/lang/Throwable
    //   8778	8791	8794	java/lang/Throwable
    //   8783	8806	8809	java/lang/Throwable
    //   8798	8824	8827	java/lang/Throwable
    //   8813	8854	8857	java/lang/Throwable
    //   8920	8947	8950	java/lang/Throwable
    //   8937	8965	8968	java/lang/Throwable
    //   8954	8995	8998	java/lang/Throwable
    //   8972	9006	9006	java/lang/Throwable
    //   9029	9040	9043	java/lang/Throwable
    //   9095	9109	9109	java/lang/Throwable
    //   9120	9133	9136	java/lang/Throwable
    //   9125	9148	9151	java/lang/Throwable
    //   9140	9166	9169	java/lang/Throwable
    //   9155	9196	9199	java/lang/Throwable
    //   9262	9289	9292	java/lang/Throwable
    //   9279	9307	9310	java/lang/Throwable
    //   9296	9337	9340	java/lang/Throwable
    //   9314	9348	9348	java/lang/Throwable
    //   9371	9382	9385	java/lang/Throwable
    //   9397	10131	11597	java/lang/Throwable
    //   9487	9501	9501	java/lang/Throwable
    //   9512	9525	9528	java/lang/Throwable
    //   9517	9540	9543	java/lang/Throwable
    //   9532	9558	9561	java/lang/Throwable
    //   9547	9588	9591	java/lang/Throwable
    //   9654	9681	9684	java/lang/Throwable
    //   9671	9699	9702	java/lang/Throwable
    //   9688	9729	9732	java/lang/Throwable
    //   9706	9740	9740	java/lang/Throwable
    //   9763	9774	9777	java/lang/Throwable
    //   9830	9844	9844	java/lang/Throwable
    //   9855	9868	9871	java/lang/Throwable
    //   9860	9883	9886	java/lang/Throwable
    //   9875	9901	9904	java/lang/Throwable
    //   9890	9931	9934	java/lang/Throwable
    //   9997	10024	10027	java/lang/Throwable
    //   10014	10042	10045	java/lang/Throwable
    //   10031	10072	10075	java/lang/Throwable
    //   10049	10083	10083	java/lang/Throwable
    //   10106	10117	10120	java/lang/Throwable
    //   10132	10866	11597	java/lang/Throwable
    //   10222	10236	10236	java/lang/Throwable
    //   10247	10260	10263	java/lang/Throwable
    //   10252	10275	10278	java/lang/Throwable
    //   10267	10293	10296	java/lang/Throwable
    //   10282	10323	10326	java/lang/Throwable
    //   10389	10416	10419	java/lang/Throwable
    //   10406	10434	10437	java/lang/Throwable
    //   10423	10464	10467	java/lang/Throwable
    //   10441	10475	10475	java/lang/Throwable
    //   10498	10509	10512	java/lang/Throwable
    //   10565	10579	10579	java/lang/Throwable
    //   10590	10603	10606	java/lang/Throwable
    //   10595	10618	10621	java/lang/Throwable
    //   10610	10636	10639	java/lang/Throwable
    //   10625	10666	10669	java/lang/Throwable
    //   10732	10759	10762	java/lang/Throwable
    //   10749	10777	10780	java/lang/Throwable
    //   10766	10807	10810	java/lang/Throwable
    //   10784	10818	10818	java/lang/Throwable
    //   10841	10852	10855	java/lang/Throwable
    //   10867	11596	11597	java/lang/Throwable
    //   10957	10971	10971	java/lang/Throwable
    //   10982	10995	10998	java/lang/Throwable
    //   10987	11010	11013	java/lang/Throwable
    //   11002	11028	11031	java/lang/Throwable
    //   11017	11058	11061	java/lang/Throwable
    //   11124	11151	11154	java/lang/Throwable
    //   11141	11169	11172	java/lang/Throwable
    //   11158	11199	11202	java/lang/Throwable
    //   11176	11210	11210	java/lang/Throwable
    //   11233	11244	11247	java/lang/Throwable
    //   11300	11314	11314	java/lang/Throwable
    //   11325	11338	11341	java/lang/Throwable
    //   11330	11353	11356	java/lang/Throwable
    //   11345	11371	11374	java/lang/Throwable
    //   11360	11401	11404	java/lang/Throwable
    //   11467	11494	11497	java/lang/Throwable
    //   11484	11512	11515	java/lang/Throwable
    //   11501	11542	11545	java/lang/Throwable
    //   11519	11553	11553	java/lang/Throwable
    //   11576	11587	11590	java/lang/Throwable
  }
  
  static void ZD(Object paramObject) {
    Zbow.Zr = a(10754, -20891);
    Zbow.ZS = new BigInteger(a(10779, -6607));
    boolean bool = Zt2e.ZK();
    try {
      try {
        if (Zzc9.Zv.charAt(Math.abs(((BigInteger)Zrw0.ZC).intValue() % 32)) > Zrd3.Z_.charAt(Math.abs(((BigInteger)Zscz.ZN).intValue() % 32))) {
          try {
            Zmha.ZY(Class.forName(a(10783, 22455)));
            if (bool)
              Zrb6.ZV(Class.forName(a(10759, 23563))); 
          } catch (Throwable throwable) {
            throw a(null);
          } 
          return;
        } 
      } catch (Throwable throwable) {
        throw a(null);
      } 
      Zrb6.ZV(Class.forName(a(10759, 23563)));
    } catch (Throwable throwable) {}
  }
  
  static void Zp(Object[] paramArrayOfObject, Object paramObject) throws Throwable {}
  
  static {
    // Byte code:
    //   0: bipush #31
    //   2: anewarray java/lang/String
    //   5: astore #5
    //   7: iconst_0
    //   8: istore_3
    //   9: ldc 'd.2,EwjJ6(nk*4w<6w_XGv\\t{w7\\tji\\t21.\\t${D4??Apv\\tq-v`O\\tI'q`HA\\ts#6\\tC\\bhOa)\\t[3(X\\tT\\\tkdmy}\\t?23wY 1 =VsxNNf]~r;\\tU$C\\tfT\\tWs\\t&sL\\t^<B-\\tbMh\\r\\b1&^CFM`sgH7!_k)>?}f^+Ag=[<fhMLoavzhBUtN\\tXsSn$xR\\tBH\\tU'HB ;YF\[4 H4??'
    //   11: dup
    //   12: astore_2
    //   13: invokevirtual length : ()I
    //   16: istore #4
    //   18: bipush #77
    //   20: istore_1
    //   21: iconst_m1
    //   22: istore_0
    //   23: bipush #117
    //   25: iinc #0, 1
    //   28: aload_2
    //   29: iload_0
    //   30: dup
    //   31: iload_1
    //   32: iadd
    //   33: invokevirtual substring : (II)Ljava/lang/String;
    //   36: iconst_m1
    //   37: goto -> 143
    //   40: aload #5
    //   42: swap
    //   43: iload_3
    //   44: iinc #3, 1
    //   47: swap
    //   48: aastore
    //   49: iload_0
    //   50: iload_1
    //   51: iadd
    //   52: dup
    //   53: istore_0
    //   54: iload #4
    //   56: if_icmpge -> 68
    //   59: aload_2
    //   60: iload_0
    //   61: invokevirtual charAt : (I)C
    //   64: istore_1
    //   65: goto -> 23
    //   68: ldc 'T\\nD\\r=K\\t#O"u'
    //   70: dup
    //   71: astore_2
    //   72: invokevirtual length : ()I
    //   75: istore #4
    //   77: bipush #19
    //   79: istore_1
    //   80: iconst_m1
    //   81: istore_0
    //   82: bipush #54
    //   84: iinc #0, 1
    //   87: aload_2
    //   88: iload_0
    //   89: dup
    //   90: iload_1
    //   91: iadd
    //   92: invokevirtual substring : (II)Ljava/lang/String;
    //   95: iconst_0
    //   96: goto -> 143
    //   99: aload #5
    //   101: swap
    //   102: iload_3
    //   103: iinc #3, 1
    //   106: swap
    //   107: aastore
    //   108: iload_0
    //   109: iload_1
    //   110: iadd
    //   111: dup
    //   112: istore_0
    //   113: iload #4
    //   115: if_icmpge -> 127
    //   118: aload_2
    //   119: iload_0
    //   120: invokevirtual charAt : (I)C
    //   123: istore_1
    //   124: goto -> 82
    //   127: aload #5
    //   129: putstatic burp/Zxn4.a : [Ljava/lang/String;
    //   132: bipush #31
    //   134: anewarray java/lang/String
    //   137: putstatic burp/Zxn4.b : [Ljava/lang/String;
    //   140: goto -> 300
    //   143: dup_x2
    //   144: pop
    //   145: invokevirtual toCharArray : ()[C
    //   148: dup_x1
    //   149: arraylength
    //   150: dup_x2
    //   151: pop
    //   152: iconst_0
    //   153: istore #6
    //   155: dup2_x1
    //   156: pop2
    //   157: dup_x2
    //   158: iconst_1
    //   159: if_icmpgt -> 259
    //   162: dup2
    //   163: swap
    //   164: iload #6
    //   166: dup2_x1
    //   167: caload
    //   168: swap
    //   169: iload #6
    //   171: bipush #7
    //   173: irem
    //   174: tableswitch default -> 241, 0 -> 212, 1 -> 217, 2 -> 221, 3 -> 226, 4 -> 231, 5 -> 236
    //   212: bipush #78
    //   214: goto -> 243
    //   217: iconst_2
    //   218: goto -> 243
    //   221: bipush #22
    //   223: goto -> 243
    //   226: bipush #48
    //   228: goto -> 243
    //   231: bipush #69
    //   233: goto -> 243
    //   236: bipush #45
    //   238: goto -> 243
    //   241: bipush #125
    //   243: ixor
    //   244: ixor
    //   245: i2c
    //   246: castore
    //   247: iinc #6, 1
    //   250: dup
    //   251: ifne -> 259
    //   254: dup2
    //   255: dup_x1
    //   256: goto -> 166
    //   259: dup2_x1
    //   260: pop2
    //   261: dup_x2
    //   262: iload #6
    //   264: if_icmpgt -> 162
    //   267: pop
    //   268: new java/lang/String
    //   271: dup_x1
    //   272: swap
    //   273: invokespecial <init> : ([C)V
    //   276: invokevirtual intern : ()Ljava/lang/String;
    //   279: swap
    //   280: pop
    //   281: swap
    //   282: tableswitch default -> 40, 0 -> 99
    //   300: sipush #10775
    //   303: sipush #14763
    //   306: invokestatic a : (II)Ljava/lang/String;
    //   309: putstatic burp/Zxn4.ZQ : Ljava/lang/String;
    //   312: new java/math/BigInteger
    //   315: dup
    //   316: sipush #10764
    //   319: sipush #11820
    //   322: invokestatic a : (II)Ljava/lang/String;
    //   325: invokespecial <init> : (Ljava/lang/String;)V
    //   328: putstatic burp/Zxn4.Zx : Ljava/lang/Object;
    //   331: return
  }
  
  private static Throwable a(Throwable paramThrowable) {
    return paramThrowable;
  }
  
  private static String a(int paramInt1, int paramInt2) {
    int i = (paramInt1 ^ 0x2A0C) & 0xFFFF;
    if (b[i] == null) {
      char[] arrayOfChar = a[i].toCharArray();
      switch (arrayOfChar[0] & 0xFF) {
        case 0:
        
        case 1:
        
        case 2:
        
        case 3:
        
        case 4:
        
        case 5:
        
        case 6:
        
        case 7:
        
        case 8:
        
        case 9:
        
        case 10:
        
        case 11:
        
        case 12:
        
        case 13:
        
        case 14:
        
        case 15:
        
        case 16:
        
        case 17:
        
        case 18:
        
        case 19:
        
        case 20:
        
        case 21:
        
        case 22:
        
        case 23:
        
        case 24:
        
        case 25:
        
        case 26:
        
        case 27:
        
        case 28:
        
        case 29:
        
        case 30:
        
        case 31:
        
        case 32:
        
        case 33:
        
        case 34:
        
        case 35:
        
        case 36:
        
        case 37:
        
        case 38:
        
        case 39:
        
        case 40:
        
        case 41:
        
        case 42:
        
        case 43:
        
        case 44:
        
        case 45:
        
        case 46:
        
        case 47:
        
        case 48:
        
        case 49:
        
        case 50:
        
        case 51:
        
        case 52:
        
        case 53:
        
        case 54:
        
        case 55:
        
        case 56:
        
        case 57:
        
        case 58:
        
        case 59:
        
        case 60:
        
        case 61:
        
        case 62:
        
        case 63:
        
        case 64:
        
        case 65:
        
        case 66:
        
        case 67:
        
        case 68:
        
        case 69:
        
        case 70:
        
        case 71:
        
        case 72:
        
        case 73:
        
        case 74:
        
        case 75:
        
        case 76:
        
        case 77:
        
        case 78:
        
        case 79:
        
        case 80:
        
        case 81:
        
        case 82:
        
        case 83:
        
        case 84:
        
        case 85:
        
        case 86:
        
        case 87:
        
        case 88:
        
        case 89:
        
        case 90:
        
        case 91:
        
        case 92:
        
        case 93:
        
        case 94:
        
        case 95:
        
        case 96:
        
        case 97:
        
        case 98:
        
        case 99:
        
        case 100:
        
        case 101:
        
        case 102:
        
        case 103:
        
        case 104:
        
        case 105:
        
        case 106:
        
        case 107:
        
        case 108:
        
        case 109:
        
        case 110:
        
        case 111:
        
        case 112:
        
        case 113:
        
        case 114:
        
        case 115:
        
        case 116:
        
        case 117:
        
        case 118:
        
        case 119:
        
        case 120:
        
        case 121:
        
        case 122:
        
        case 123:
        
        case 124:
        
        case 125:
        
        case 126:
        
        case 127:
        
        case 128:
        
        case 129:
        
        case 130:
        
        case 131:
        
        case 132:
        
        case 133:
        
        case 134:
        
        case 135:
        
        case 136:
        
        case 137:
        
        case 138:
        
        case 139:
        
        case 140:
        
        case 141:
        
        case 142:
        
        case 143:
        
        case 144:
        
        case 145:
        
        case 146:
        
        case 147:
        
        case 148:
        
        case 149:
        
        case 150:
        
        case 151:
        
        case 152:
        
        case 153:
        
        case 154:
        
        case 155:
        
        case 156:
        
        case 157:
        
        case 158:
        
        case 159:
        
        case 160:
        
        case 161:
        
        case 162:
        
        case 163:
        
        case 164:
        
        case 165:
        
        case 166:
        
        case 167:
        
        case 168:
        
        case 169:
        
        case 170:
        
        case 171:
        
        case 172:
        
        case 173:
        
        case 174:
        
        case 175:
        
        case 176:
        
        case 177:
        
        case 178:
        
        case 179:
        
        case 180:
        
        case 181:
        
        case 182:
        
        case 183:
        
        case 184:
        
        case 185:
        
        case 186:
        
        case 187:
        
        case 188:
        
        case 189:
        
        case 190:
        
        case 191:
        
        case 192:
        
        case 193:
        
        case 194:
        
        case 195:
        
        case 196:
        
        case 197:
        
        case 198:
        
        case 199:
        
        case 200:
        
        case 201:
        
        case 202:
        
        case 203:
        
        case 204:
        
        case 205:
        
        case 206:
        
        case 207:
        
        case 208:
        
        case 209:
        
        case 210:
        
        case 211:
        
        case 212:
        
        case 213:
        
        case 214:
        
        case 215:
        
        case 216:
        
        case 217:
        
        case 218:
        
        case 219:
        
        case 220:
        
        case 221:
        
        case 222:
        
        case 223:
        
        case 224:
        
        case 225:
        
        case 226:
        
        case 227:
        
        case 228:
        
        case 229:
        
        case 230:
        
        case 231:
        
        case 232:
        
        case 233:
        
        case 234:
        
        case 235:
        
        case 236:
        
        case 237:
        
        case 238:
        
        case 239:
        
        case 240:
        
        case 241:
        
        case 242:
        
        case 243:
        
        case 244:
        
        case 245:
        
        case 246:
        
        case 247:
        
        case 248:
        
        case 249:
        
        case 250:
        
        case 251:
        
        case 252:
        
        case 253:
        
        case 254:
        
        default:
          break;
      } 
      char c = '';
      int j = (paramInt2 & 0xFF) - c;
      if (j < 0)
        j += 256; 
      int k = ((paramInt2 & 0xFFFF) >>> 8) - c;
      if (k < 0)
        k += 256; 
      for (byte b = 0; b < arrayOfChar.length; b++) {
        int m = b % 2;
        if (m == 0) {
          arrayOfChar[b] = (char)(arrayOfChar[b] ^ j);
          j = ((j >>> 3 | j << 5) ^ arrayOfChar[b]) & 0xFF;
        } else {
          arrayOfChar[b] = (char)(arrayOfChar[b] ^ k);
          k = ((k >>> 3 | k << 5) ^ arrayOfChar[b]) & 0xFF;
        } 
      } 
      b[i] = (new String(arrayOfChar)).intern();
    } 
    return b[i];
  }
}


/* Location:              C:\Program Files\BurpSuitePro\burpsuite_pro.jar!\burp\Zxn4.class
 * Java compiler version: 21 (65.0)
 * JD-Core Version:       1.1.3
 */