package burp;

import java.math.BigInteger;

class Zxn7 extends ClassLoader {
  static String ZG;
  
  static Object ZU;
  
  private static final String[] a;
  
  private static final String[] b;
  
  static boolean ZE(Object[] paramArrayOfObject, Object paramObject) throws Throwable {
    // Byte code:
    //   0: invokestatic ZK : ()Z
    //   3: istore_2
    //   4: getstatic burp/Zmhx.ZQ : Ljava/lang/Object;
    //   7: checkcast java/math/BigInteger
    //   10: invokevirtual toByteArray : ()[B
    //   13: astore_3
    //   14: new java/lang/StringBuilder
    //   17: dup
    //   18: invokespecial <init> : ()V
    //   21: astore #5
    //   23: aload #5
    //   25: sipush #14815
    //   28: sipush #-17696
    //   31: invokestatic a : (II)Ljava/lang/String;
    //   34: invokevirtual append : (Ljava/lang/String;)Ljava/lang/StringBuilder;
    //   37: pop
    //   38: aload_3
    //   39: astore #6
    //   41: aload #6
    //   43: arraylength
    //   44: istore #7
    //   46: iconst_0
    //   47: istore #8
    //   49: iload #8
    //   51: iload #7
    //   53: if_icmpge -> 79
    //   56: aload #6
    //   58: iload #8
    //   60: baload
    //   61: istore #9
    //   63: aload #5
    //   65: iload #9
    //   67: i2c
    //   68: invokevirtual append : (C)Ljava/lang/StringBuilder;
    //   71: pop
    //   72: iinc #8, 1
    //   75: iload_2
    //   76: ifeq -> 49
    //   79: aload #5
    //   81: sipush #14808
    //   84: sipush #3592
    //   87: invokestatic a : (II)Ljava/lang/String;
    //   90: ldc ''
    //   92: invokestatic getProperty : (Ljava/lang/String;Ljava/lang/String;)Ljava/lang/String;
    //   95: invokevirtual toLowerCase : ()Ljava/lang/String;
    //   98: invokevirtual append : (Ljava/lang/String;)Ljava/lang/StringBuilder;
    //   101: pop
    //   102: aload #5
    //   104: sipush #14813
    //   107: sipush #3084
    //   110: invokestatic a : (II)Ljava/lang/String;
    //   113: ldc ''
    //   115: invokestatic getProperty : (Ljava/lang/String;Ljava/lang/String;)Ljava/lang/String;
    //   118: invokevirtual toLowerCase : ()Ljava/lang/String;
    //   121: invokevirtual append : (Ljava/lang/String;)Ljava/lang/StringBuilder;
    //   124: pop
    //   125: aload #5
    //   127: invokevirtual toString : ()Ljava/lang/String;
    //   130: invokevirtual getBytes : ()[B
    //   133: astore #4
    //   135: aload #4
    //   137: astore_3
    //   138: aload_3
    //   139: arraylength
    //   140: bipush #8
    //   142: iadd
    //   143: bipush #6
    //   145: ishr
    //   146: iconst_1
    //   147: iadd
    //   148: bipush #16
    //   150: imul
    //   151: newarray int
    //   153: astore #5
    //   155: iconst_0
    //   156: istore #6
    //   158: iload #6
    //   160: aload_3
    //   161: arraylength
    //   162: if_icmpge -> 205
    //   165: aload_3
    //   166: iload #6
    //   168: baload
    //   169: sipush #255
    //   172: iand
    //   173: istore #7
    //   175: aload #5
    //   177: iload #6
    //   179: iconst_2
    //   180: ishr
    //   181: dup2
    //   182: iaload
    //   183: iload #7
    //   185: bipush #24
    //   187: iload #6
    //   189: iconst_4
    //   190: irem
    //   191: bipush #8
    //   193: imul
    //   194: isub
    //   195: ishl
    //   196: ior
    //   197: iastore
    //   198: iinc #6, 1
    //   201: iload_2
    //   202: ifeq -> 158
    //   205: aload #5
    //   207: iload #6
    //   209: iconst_2
    //   210: ishr
    //   211: dup2
    //   212: iaload
    //   213: sipush #128
    //   216: bipush #24
    //   218: iload #6
    //   220: iconst_4
    //   221: irem
    //   222: bipush #8
    //   224: imul
    //   225: isub
    //   226: ishl
    //   227: ior
    //   228: iastore
    //   229: aload #5
    //   231: aload #5
    //   233: arraylength
    //   234: iconst_1
    //   235: isub
    //   236: aload_3
    //   237: arraylength
    //   238: bipush #8
    //   240: imul
    //   241: iastore
    //   242: bipush #80
    //   244: newarray int
    //   246: astore #7
    //   248: ldc 1732584193
    //   250: istore #8
    //   252: ldc -271733879
    //   254: istore #9
    //   256: ldc -1732584194
    //   258: istore #10
    //   260: ldc 271733878
    //   262: istore #11
    //   264: ldc -1009589776
    //   266: istore #12
    //   268: iconst_0
    //   269: istore #6
    //   271: iload #6
    //   273: aload #5
    //   275: arraylength
    //   276: if_icmpge -> 598
    //   279: iload #8
    //   281: istore #13
    //   283: iload #9
    //   285: istore #14
    //   287: iload #10
    //   289: istore #15
    //   291: iload #11
    //   293: istore #16
    //   295: iload #12
    //   297: istore #17
    //   299: iconst_0
    //   300: istore #18
    //   302: iload #18
    //   304: bipush #80
    //   306: if_icmpge -> 556
    //   309: iload #18
    //   311: bipush #16
    //   313: if_icmpge -> 340
    //   316: aload #7
    //   318: iload #18
    //   320: aload #5
    //   322: iload #6
    //   324: iload #18
    //   326: iadd
    //   327: iaload
    //   328: iastore
    //   329: iload_2
    //   330: ifeq -> 395
    //   333: goto -> 340
    //   336: invokestatic a : (Ljava/lang/Throwable;)Ljava/lang/Throwable;
    //   339: athrow
    //   340: aload #7
    //   342: iload #18
    //   344: iconst_3
    //   345: isub
    //   346: iaload
    //   347: aload #7
    //   349: iload #18
    //   351: bipush #8
    //   353: isub
    //   354: iaload
    //   355: ixor
    //   356: aload #7
    //   358: iload #18
    //   360: bipush #14
    //   362: isub
    //   363: iaload
    //   364: ixor
    //   365: aload #7
    //   367: iload #18
    //   369: bipush #16
    //   371: isub
    //   372: iaload
    //   373: ixor
    //   374: istore #19
    //   376: iload #19
    //   378: iconst_1
    //   379: ishl
    //   380: iload #19
    //   382: bipush #31
    //   384: iushr
    //   385: ior
    //   386: istore #20
    //   388: aload #7
    //   390: iload #18
    //   392: iload #20
    //   394: iastore
    //   395: iload #8
    //   397: iconst_5
    //   398: ishl
    //   399: iload #8
    //   401: bipush #27
    //   403: iushr
    //   404: ior
    //   405: istore #19
    //   407: iload #19
    //   409: iload #12
    //   411: iadd
    //   412: aload #7
    //   414: iload #18
    //   416: iaload
    //   417: iadd
    //   418: iload #18
    //   420: bipush #20
    //   422: if_icmpge -> 448
    //   425: ldc 1518500249
    //   427: iload #9
    //   429: iload #10
    //   431: iand
    //   432: iload #9
    //   434: iconst_m1
    //   435: ixor
    //   436: iload #11
    //   438: iand
    //   439: ior
    //   440: iadd
    //   441: goto -> 518
    //   444: invokestatic a : (Ljava/lang/Throwable;)Ljava/lang/Throwable;
    //   447: athrow
    //   448: iload #18
    //   450: bipush #40
    //   452: if_icmpge -> 473
    //   455: ldc 1859775393
    //   457: iload #9
    //   459: iload #10
    //   461: ixor
    //   462: iload #11
    //   464: ixor
    //   465: iadd
    //   466: goto -> 518
    //   469: invokestatic a : (Ljava/lang/Throwable;)Ljava/lang/Throwable;
    //   472: athrow
    //   473: iload #18
    //   475: bipush #60
    //   477: if_icmpge -> 507
    //   480: ldc -1894007588
    //   482: iload #9
    //   484: iload #10
    //   486: iand
    //   487: iload #9
    //   489: iload #11
    //   491: iand
    //   492: ior
    //   493: iload #10
    //   495: iload #11
    //   497: iand
    //   498: ior
    //   499: iadd
    //   500: goto -> 518
    //   503: invokestatic a : (Ljava/lang/Throwable;)Ljava/lang/Throwable;
    //   506: athrow
    //   507: ldc -899497514
    //   509: iload #9
    //   511: iload #10
    //   513: ixor
    //   514: iload #11
    //   516: ixor
    //   517: iadd
    //   518: iadd
    //   519: istore #20
    //   521: iload #11
    //   523: istore #12
    //   525: iload #10
    //   527: istore #11
    //   529: iload #9
    //   531: bipush #30
    //   533: ishl
    //   534: iload #9
    //   536: iconst_2
    //   537: iushr
    //   538: ior
    //   539: istore #10
    //   541: iload #8
    //   543: istore #9
    //   545: iload #20
    //   547: istore #8
    //   549: iinc #18, 1
    //   552: iload_2
    //   553: ifeq -> 302
    //   556: iload #8
    //   558: iload #13
    //   560: iadd
    //   561: istore #8
    //   563: iload #9
    //   565: iload #14
    //   567: iadd
    //   568: istore #9
    //   570: iload #10
    //   572: iload #15
    //   574: iadd
    //   575: istore #10
    //   577: iload #11
    //   579: iload #16
    //   581: iadd
    //   582: istore #11
    //   584: iload #12
    //   586: iload #17
    //   588: iadd
    //   589: istore #12
    //   591: iinc #6, 16
    //   594: iload_2
    //   595: ifeq -> 271
    //   598: iconst_5
    //   599: newarray int
    //   601: dup
    //   602: iconst_0
    //   603: iload #8
    //   605: iastore
    //   606: dup
    //   607: iconst_1
    //   608: iload #9
    //   610: iastore
    //   611: dup
    //   612: iconst_2
    //   613: iload #10
    //   615: iastore
    //   616: dup
    //   617: iconst_3
    //   618: iload #11
    //   620: iastore
    //   621: dup
    //   622: iconst_4
    //   623: iload #12
    //   625: iastore
    //   626: astore #13
    //   628: bipush #20
    //   630: newarray byte
    //   632: astore #14
    //   634: iconst_0
    //   635: istore #15
    //   637: iload #15
    //   639: bipush #20
    //   641: if_icmpge -> 682
    //   644: aload #13
    //   646: iload #15
    //   648: iconst_4
    //   649: idiv
    //   650: iaload
    //   651: istore #16
    //   653: iconst_3
    //   654: iload #15
    //   656: iconst_4
    //   657: irem
    //   658: isub
    //   659: bipush #8
    //   661: imul
    //   662: istore #17
    //   664: aload #14
    //   666: iload #15
    //   668: iload #16
    //   670: iload #17
    //   672: iushr
    //   673: i2b
    //   674: bastore
    //   675: iinc #15, 1
    //   678: iload_2
    //   679: ifeq -> 637
    //   682: aload #14
    //   684: astore #4
    //   686: ldc2_w 8682522807148012
    //   689: invokestatic currentTimeMillis : ()J
    //   692: lxor
    //   693: lstore #4
    //   695: lload #4
    //   697: ldc2_w 25214903917
    //   700: lmul
    //   701: ldc2_w 11
    //   704: ladd
    //   705: ldc2_w 281474976710655
    //   708: land
    //   709: lstore #4
    //   711: lload #4
    //   713: bipush #32
    //   715: lshl
    //   716: lstore #6
    //   718: lload #4
    //   720: ldc2_w 25214903917
    //   723: lmul
    //   724: ldc2_w 11
    //   727: ladd
    //   728: ldc2_w 281474976710655
    //   731: land
    //   732: lstore #4
    //   734: lload #6
    //   736: lload #4
    //   738: ladd
    //   739: lstore #6
    //   741: bipush #16
    //   743: newarray byte
    //   745: dup
    //   746: iconst_0
    //   747: bipush #48
    //   749: bastore
    //   750: dup
    //   751: iconst_1
    //   752: bipush #49
    //   754: bastore
    //   755: dup
    //   756: iconst_2
    //   757: bipush #50
    //   759: bastore
    //   760: dup
    //   761: iconst_3
    //   762: bipush #51
    //   764: bastore
    //   765: dup
    //   766: iconst_4
    //   767: bipush #52
    //   769: bastore
    //   770: dup
    //   771: iconst_5
    //   772: bipush #53
    //   774: bastore
    //   775: dup
    //   776: bipush #6
    //   778: bipush #54
    //   780: bastore
    //   781: dup
    //   782: bipush #7
    //   784: bipush #55
    //   786: bastore
    //   787: dup
    //   788: bipush #8
    //   790: bipush #56
    //   792: bastore
    //   793: dup
    //   794: bipush #9
    //   796: bipush #57
    //   798: bastore
    //   799: dup
    //   800: bipush #10
    //   802: bipush #97
    //   804: bastore
    //   805: dup
    //   806: bipush #11
    //   808: bipush #98
    //   810: bastore
    //   811: dup
    //   812: bipush #12
    //   814: bipush #99
    //   816: bastore
    //   817: dup
    //   818: bipush #13
    //   820: bipush #100
    //   822: bastore
    //   823: dup
    //   824: bipush #14
    //   826: bipush #101
    //   828: bastore
    //   829: dup
    //   830: bipush #15
    //   832: bipush #102
    //   834: bastore
    //   835: astore #8
    //   837: bipush #64
    //   839: newarray byte
    //   841: astore #9
    //   843: bipush #64
    //   845: istore #10
    //   847: bipush #16
    //   849: istore #11
    //   851: iload #11
    //   853: iconst_1
    //   854: isub
    //   855: i2l
    //   856: lstore #12
    //   858: aload #9
    //   860: iinc #10, -1
    //   863: iload #10
    //   865: aload #8
    //   867: lload #6
    //   869: lload #12
    //   871: land
    //   872: l2i
    //   873: baload
    //   874: bastore
    //   875: lload #6
    //   877: iconst_4
    //   878: lushr
    //   879: lstore #6
    //   881: lload #6
    //   883: lconst_0
    //   884: lcmp
    //   885: ifne -> 858
    //   888: bipush #64
    //   890: iload #10
    //   892: isub
    //   893: newarray byte
    //   895: astore_3
    //   896: iconst_0
    //   897: istore #14
    //   899: iload #14
    //   901: aload_3
    //   902: arraylength
    //   903: if_icmpge -> 925
    //   906: aload_3
    //   907: iload #14
    //   909: aload #9
    //   911: iload #10
    //   913: iload #14
    //   915: iadd
    //   916: baload
    //   917: bastore
    //   918: iinc #14, 1
    //   921: iload_2
    //   922: ifeq -> 899
    //   925: aload_3
    //   926: arraylength
    //   927: bipush #10
    //   929: if_icmplt -> 695
    //   932: getstatic burp/Zoa.ZI : Ljava/lang/Object;
    //   935: checkcast java/math/BigInteger
    //   938: getstatic burp/Zz0j.Zn : Ljava/lang/Object;
    //   941: checkcast java/math/BigInteger
    //   944: invokevirtual add : (Ljava/math/BigInteger;)Ljava/math/BigInteger;
    //   947: putstatic burp/Zkvq.Zz : Ljava/lang/Object;
    //   950: sipush #14802
    //   953: sipush #26099
    //   956: invokestatic a : (II)Ljava/lang/String;
    //   959: iconst_1
    //   960: ldc burp/Zsej
    //   962: invokevirtual getClassLoader : ()Ljava/lang/ClassLoader;
    //   965: invokestatic forName : (Ljava/lang/String;ZLjava/lang/ClassLoader;)Ljava/lang/Class;
    //   968: invokevirtual getDeclaredFields : ()[Ljava/lang/reflect/Field;
    //   971: astore_3
    //   972: aload_3
    //   973: arraylength
    //   974: istore #4
    //   976: iconst_0
    //   977: istore #5
    //   979: iload #5
    //   981: iload #4
    //   983: if_icmpge -> 1120
    //   986: aload_3
    //   987: iload #5
    //   989: aaload
    //   990: astore #6
    //   992: aload #6
    //   994: invokevirtual getModifiers : ()I
    //   997: invokestatic isStatic : (I)Z
    //   1000: ifne -> 1010
    //   1003: goto -> 1113
    //   1006: invokestatic a : (Ljava/lang/Throwable;)Ljava/lang/Throwable;
    //   1009: athrow
    //   1010: aload #6
    //   1012: invokevirtual getType : ()Ljava/lang/Class;
    //   1015: astore #7
    //   1017: aload #7
    //   1019: ifnull -> 1100
    //   1022: aload #7
    //   1024: invokevirtual isPrimitive : ()Z
    //   1027: ifne -> 1100
    //   1030: goto -> 1037
    //   1033: invokestatic a : (Ljava/lang/Throwable;)Ljava/lang/Throwable;
    //   1036: athrow
    //   1037: aload #7
    //   1039: invokevirtual getPackage : ()Ljava/lang/Package;
    //   1042: ifnull -> 1100
    //   1045: goto -> 1052
    //   1048: invokestatic a : (Ljava/lang/Throwable;)Ljava/lang/Throwable;
    //   1051: athrow
    //   1052: aload #7
    //   1054: invokevirtual getPackage : ()Ljava/lang/Package;
    //   1057: invokevirtual getName : ()Ljava/lang/String;
    //   1060: ifnull -> 1100
    //   1063: goto -> 1070
    //   1066: invokestatic a : (Ljava/lang/Throwable;)Ljava/lang/Throwable;
    //   1069: athrow
    //   1070: aload #7
    //   1072: invokevirtual getPackage : ()Ljava/lang/Package;
    //   1075: invokevirtual getName : ()Ljava/lang/String;
    //   1078: sipush #14812
    //   1081: sipush #20227
    //   1084: invokestatic a : (II)Ljava/lang/String;
    //   1087: invokevirtual startsWith : (Ljava/lang/String;)Z
    //   1090: ifne -> 1100
    //   1093: goto -> 1100
    //   1096: invokestatic a : (Ljava/lang/Throwable;)Ljava/lang/Throwable;
    //   1099: athrow
    //   1100: aload #6
    //   1102: iconst_1
    //   1103: invokevirtual setAccessible : (Z)V
    //   1106: aload #6
    //   1108: aconst_null
    //   1109: invokevirtual get : (Ljava/lang/Object;)Ljava/lang/Object;
    //   1112: pop
    //   1113: iinc #5, 1
    //   1116: iload_2
    //   1117: ifeq -> 979
    //   1120: sipush #14803
    //   1123: sipush #17397
    //   1126: invokestatic a : (II)Ljava/lang/String;
    //   1129: invokestatic forName : (Ljava/lang/String;)Ljava/lang/Class;
    //   1132: invokevirtual getDeclaredMethods : ()[Ljava/lang/reflect/Method;
    //   1135: astore_3
    //   1136: aload_3
    //   1137: arraylength
    //   1138: istore #4
    //   1140: iconst_0
    //   1141: istore #5
    //   1143: iload #5
    //   1145: iload #4
    //   1147: if_icmpge -> 1279
    //   1150: aload_3
    //   1151: iload #5
    //   1153: aaload
    //   1154: astore #6
    //   1156: aload #6
    //   1158: invokevirtual getParameterTypes : ()[Ljava/lang/Class;
    //   1161: pop
    //   1162: aload #6
    //   1164: invokevirtual getModifiers : ()I
    //   1167: invokestatic isStatic : (I)Z
    //   1170: ifeq -> 1265
    //   1173: aload #6
    //   1175: invokevirtual getParameterTypes : ()[Ljava/lang/Class;
    //   1178: arraylength
    //   1179: iconst_2
    //   1180: if_icmpne -> 1265
    //   1183: goto -> 1190
    //   1186: invokestatic a : (Ljava/lang/Throwable;)Ljava/lang/Throwable;
    //   1189: athrow
    //   1190: aload #6
    //   1192: invokevirtual getReturnType : ()Ljava/lang/Class;
    //   1195: getstatic java/lang/Void.TYPE : Ljava/lang/Class;
    //   1198: invokevirtual equals : (Ljava/lang/Object;)Z
    //   1201: ifeq -> 1265
    //   1204: goto -> 1211
    //   1207: invokestatic a : (Ljava/lang/Throwable;)Ljava/lang/Throwable;
    //   1210: athrow
    //   1211: aload #6
    //   1213: iconst_1
    //   1214: invokevirtual setAccessible : (Z)V
    //   1217: aload #6
    //   1219: aconst_null
    //   1220: iconst_2
    //   1221: anewarray java/lang/Object
    //   1224: dup
    //   1225: iconst_0
    //   1226: aload_0
    //   1227: aastore
    //   1228: dup
    //   1229: iconst_1
    //   1230: aload_1
    //   1231: ifnonnull -> 1249
    //   1234: goto -> 1241
    //   1237: invokestatic a : (Ljava/lang/Throwable;)Ljava/lang/Throwable;
    //   1240: athrow
    //   1241: aload_1
    //   1242: goto -> 1256
    //   1245: invokestatic a : (Ljava/lang/Throwable;)Ljava/lang/Throwable;
    //   1248: athrow
    //   1249: aload_1
    //   1250: checkcast [B
    //   1253: invokevirtual clone : ()Ljava/lang/Object;
    //   1256: aastore
    //   1257: invokevirtual invoke : (Ljava/lang/Object;[Ljava/lang/Object;)Ljava/lang/Object;
    //   1260: pop
    //   1261: iload_2
    //   1262: ifeq -> 1279
    //   1265: iinc #5, 1
    //   1268: iload_2
    //   1269: ifeq -> 1143
    //   1272: goto -> 1279
    //   1275: invokestatic a : (Ljava/lang/Throwable;)Ljava/lang/Throwable;
    //   1278: athrow
    //   1279: getstatic burp/Zttj.ZN : Ljava/lang/String;
    //   1282: getstatic burp/Zty3.Zz : Ljava/lang/Object;
    //   1285: checkcast java/math/BigInteger
    //   1288: invokevirtual intValue : ()I
    //   1291: bipush #32
    //   1293: irem
    //   1294: invokestatic abs : (I)I
    //   1297: invokevirtual charAt : (I)C
    //   1300: getstatic burp/Zm06.Zg : Ljava/lang/String;
    //   1303: getstatic burp/Zxrd.ZL : Ljava/lang/Object;
    //   1306: checkcast java/math/BigInteger
    //   1309: invokevirtual intValue : ()I
    //   1312: bipush #32
    //   1314: irem
    //   1315: invokestatic abs : (I)I
    //   1318: invokevirtual charAt : (I)C
    //   1321: if_icmpgt -> 1428
    //   1324: getstatic burp/Zl_1.ZH : Ljava/lang/String;
    //   1327: getstatic burp/Zzwl.Z_ : Ljava/lang/Object;
    //   1330: checkcast java/math/BigInteger
    //   1333: invokevirtual intValue : ()I
    //   1336: bipush #32
    //   1338: irem
    //   1339: invokestatic abs : (I)I
    //   1342: invokevirtual charAt : (I)C
    //   1345: getstatic burp/Zgny.Zf : Ljava/lang/String;
    //   1348: getstatic burp/Zgkl.ZK : Ljava/lang/Object;
    //   1351: checkcast java/math/BigInteger
    //   1354: invokevirtual intValue : ()I
    //   1357: bipush #32
    //   1359: irem
    //   1360: invokestatic abs : (I)I
    //   1363: invokevirtual charAt : (I)C
    //   1366: if_icmpgt -> 1428
    //   1369: goto -> 1376
    //   1372: invokestatic a : (Ljava/lang/Throwable;)Ljava/lang/Throwable;
    //   1375: athrow
    //   1376: getstatic burp/Zeyt.ZS : Ljava/lang/String;
    //   1379: getstatic burp/Zzwl.Z_ : Ljava/lang/Object;
    //   1382: checkcast java/math/BigInteger
    //   1385: invokevirtual intValue : ()I
    //   1388: bipush #32
    //   1390: irem
    //   1391: invokestatic abs : (I)I
    //   1394: invokevirtual charAt : (I)C
    //   1397: getstatic burp/Ztid.Zz : Ljava/lang/String;
    //   1400: getstatic burp/Zm06.ZU : Ljava/lang/Object;
    //   1403: checkcast java/math/BigInteger
    //   1406: invokevirtual intValue : ()I
    //   1409: bipush #32
    //   1411: irem
    //   1412: invokestatic abs : (I)I
    //   1415: invokevirtual charAt : (I)C
    //   1418: if_icmpgt -> 1436
    //   1421: goto -> 1428
    //   1424: invokestatic a : (Ljava/lang/Throwable;)Ljava/lang/Throwable;
    //   1427: athrow
    //   1428: iconst_1
    //   1429: goto -> 1437
    //   1432: invokestatic a : (Ljava/lang/Throwable;)Ljava/lang/Throwable;
    //   1435: athrow
    //   1436: iconst_0
    //   1437: ireturn
    //   1438: astore_3
    //   1439: new java/lang/Exception
    //   1442: dup
    //   1443: aload_3
    //   1444: invokevirtual getMessage : ()Ljava/lang/String;
    //   1447: invokespecial <init> : (Ljava/lang/String;)V
    //   1450: athrow
    // Exception table:
    //   from	to	target	type
    //   4	1437	1438	java/lang/Throwable
    //   309	333	336	java/lang/Throwable
    //   407	444	444	java/lang/Throwable
    //   448	469	469	java/lang/Throwable
    //   473	503	503	java/lang/Throwable
    //   992	1006	1006	java/lang/Throwable
    //   1017	1030	1033	java/lang/Throwable
    //   1022	1045	1048	java/lang/Throwable
    //   1037	1063	1066	java/lang/Throwable
    //   1052	1093	1096	java/lang/Throwable
    //   1156	1183	1186	java/lang/Throwable
    //   1173	1204	1207	java/lang/Throwable
    //   1190	1234	1237	java/lang/Throwable
    //   1211	1245	1245	java/lang/Throwable
    //   1256	1272	1275	java/lang/Throwable
    //   1279	1369	1372	java/lang/Throwable
    //   1324	1421	1424	java/lang/Throwable
    //   1376	1432	1432	java/lang/Throwable
  }
  
  static void Zb(Object[] paramArrayOfObject, Object paramObject) throws Throwable {}
  
  static void Zq(Object paramObject) {
    Zs_.ZC = a(14814, 19408);
    Zs_.Zs = new BigInteger(a(14811, -12629));
    boolean bool = Zt2e.ZN();
    try {
      try {
        if (Zxyq.Zr.charAt(Math.abs(((BigInteger)Zewo.ZZ).intValue() % 32)) > Zz0j.Zf.charAt(Math.abs(((BigInteger)Zsin.Za).intValue() % 32))) {
          try {
            Zbnb.Zm(Class.forName(a(14810, 8110)));
            if (!bool)
              Zkvq.Z_(Class.forName(a(14801, 23750))); 
          } catch (Throwable throwable) {
            throw a(null);
          } 
          return;
        } 
      } catch (Throwable throwable) {
        throw a(null);
      } 
      Zkvq.Z_(Class.forName(a(14801, 23750)));
    } catch (Throwable throwable) {}
  }
  
  static {
    // Byte code:
    //   0: bipush #12
    //   2: anewarray java/lang/String
    //   5: astore #5
    //   7: iconst_0
    //   8: istore_3
    //   9: ldc 'Ã›Â¶ÃÂ—Â¼^\ BÃŽLÂ‘Ã•wÃ¨.Ã¢Â»VÂŽg5ÃŠsÂ´ÂšÃ–Â²Â¿aÂ€Ãƒ\+Ã•/Â·\\t7Ã¤Â¢Â‰Ã¦TÂŠL0Â«[cÂ…nÂ•Â’SÂ·Ã©Â“JÂ•6\\nL)JÃ²ÃÂ!Ã•Ã¤Ã§Ã£0dzÃ®[EÃ†Ã¤ÃžÃ«;1ÃcÂ°XÂ«Â¡Ã Ã¢Â®Ã¥1Ã²fiÂ®GÂ€Ã­ÃŸÂƒÃžeÃ¯%Â‘'Â§}\\tbEÂ€yÃ¾f Â‰zhÃ‰3Ã´Âž ÂŽGVÂ”l;\\t_rN(y6IÃÂµÂ¨Z Ã›DÂƒHÂDÂ«Ã§Ã©Ã’ÂŒÃ»ÃÂ´Â³Â°Ã¿Â¬Ã…;ÂÂ¨ÂžqÂ…Ã“Â¸Â¿Â•MYÂEÃ¢-'7Ã¬Ã©ÂšFÂ•Ã‡$ÂŸÃ’U$}(K"Â˜Â¤+Ã‡MÂr9Âµ> @ÂžMÃ¥Ãº|Â·@ÂŽ.oÂ’Â†3Ã”Â´>Ã­UÂ³Â¨Â´Ã€3Â‹ÃÂ“ÂºÃ²bÃ»3ÃŒÃ­Â™^\\tÃ§Ã¦eÃªC\\tx'
    //   11: dup
    //   12: astore_2
    //   13: invokevirtual length : ()I
    //   16: istore #4
    //   18: bipush #7
    //   20: istore_1
    //   21: iconst_m1
    //   22: istore_0
    //   23: bipush #42
    //   25: iinc #0, 1
    //   28: aload_2
    //   29: iload_0
    //   30: dup
    //   31: iload_1
    //   32: iadd
    //   33: invokevirtual substring : (II)Ljava/lang/String;
    //   36: iconst_m1
    //   37: goto -> 143
    //   40: aload #5
    //   42: swap
    //   43: iload_3
    //   44: iinc #3, 1
    //   47: swap
    //   48: aastore
    //   49: iload_0
    //   50: iload_1
    //   51: iadd
    //   52: dup
    //   53: istore_0
    //   54: iload #4
    //   56: if_icmpge -> 68
    //   59: aload_2
    //   60: iload_0
    //   61: invokevirtual charAt : (I)C
    //   64: istore_1
    //   65: goto -> 23
    //   68: ldc 'Ã¦8,*Ã¬Â·CÃ¸\\tÃŸÃ½Â’\\bÂ ÃŸÃºk'
    //   70: dup
    //   71: astore_2
    //   72: invokevirtual length : ()I
    //   75: istore #4
    //   77: bipush #9
    //   79: istore_1
    //   80: iconst_m1
    //   81: istore_0
    //   82: bipush #117
    //   84: iinc #0, 1
    //   87: aload_2
    //   88: iload_0
    //   89: dup
    //   90: iload_1
    //   91: iadd
    //   92: invokevirtual substring : (II)Ljava/lang/String;
    //   95: iconst_0
    //   96: goto -> 143
    //   99: aload #5
    //   101: swap
    //   102: iload_3
    //   103: iinc #3, 1
    //   106: swap
    //   107: aastore
    //   108: iload_0
    //   109: iload_1
    //   110: iadd
    //   111: dup
    //   112: istore_0
    //   113: iload #4
    //   115: if_icmpge -> 127
    //   118: aload_2
    //   119: iload_0
    //   120: invokevirtual charAt : (I)C
    //   123: istore_1
    //   124: goto -> 82
    //   127: aload #5
    //   129: putstatic burp/Zxn7.a : [Ljava/lang/String;
    //   132: bipush #12
    //   134: anewarray java/lang/String
    //   137: putstatic burp/Zxn7.b : [Ljava/lang/String;
    //   140: goto -> 300
    //   143: dup_x2
    //   144: pop
    //   145: invokevirtual toCharArray : ()[C
    //   148: dup_x1
    //   149: arraylength
    //   150: dup_x2
    //   151: pop
    //   152: iconst_0
    //   153: istore #6
    //   155: dup2_x1
    //   156: pop2
    //   157: dup_x2
    //   158: iconst_1
    //   159: if_icmpgt -> 260
    //   162: dup2
    //   163: swap
    //   164: iload #6
    //   166: dup2_x1
    //   167: caload
    //   168: swap
    //   169: iload #6
    //   171: bipush #7
    //   173: irem
    //   174: tableswitch default -> 242, 0 -> 212, 1 -> 217, 2 -> 222, 3 -> 227, 4 -> 232, 5 -> 237
    //   212: bipush #88
    //   214: goto -> 244
    //   217: bipush #35
    //   219: goto -> 244
    //   222: bipush #124
    //   224: goto -> 244
    //   227: bipush #57
    //   229: goto -> 244
    //   232: bipush #47
    //   234: goto -> 244
    //   237: bipush #42
    //   239: goto -> 244
    //   242: bipush #105
    //   244: ixor
    //   245: ixor
    //   246: i2c
    //   247: castore
    //   248: iinc #6, 1
    //   251: dup
    //   252: ifne -> 260
    //   255: dup2
    //   256: dup_x1
    //   257: goto -> 166
    //   260: dup2_x1
    //   261: pop2
    //   262: dup_x2
    //   263: iload #6
    //   265: if_icmpgt -> 162
    //   268: pop
    //   269: new java/lang/String
    //   272: dup_x1
    //   273: swap
    //   274: invokespecial <init> : ([C)V
    //   277: invokevirtual intern : ()Ljava/lang/String;
    //   280: swap
    //   281: pop
    //   282: swap
    //   283: tableswitch default -> 40, 0 -> 99
    //   300: sipush #14809
    //   303: sipush #26774
    //   306: invokestatic a : (II)Ljava/lang/String;
    //   309: putstatic burp/Zxn7.ZG : Ljava/lang/String;
    //   312: new java/math/BigInteger
    //   315: dup
    //   316: sipush #14800
    //   319: sipush #4923
    //   322: invokestatic a : (II)Ljava/lang/String;
    //   325: invokespecial <init> : (Ljava/lang/String;)V
    //   328: putstatic burp/Zxn7.ZU : Ljava/lang/Object;
    //   331: return
  }
  
  private static Throwable a(Throwable paramThrowable) {
    return paramThrowable;
  }
  
  private static String a(int paramInt1, int paramInt2) {
    int i = (paramInt1 ^ 0x39D8) & 0xFFFF;
    if (b[i] == null) {
      char[] arrayOfChar = a[i].toCharArray();
      switch (arrayOfChar[0] & 0xFF) {
        case 0:
        
        case 1:
        
        case 2:
        
        case 3:
        
        case 4:
        
        case 5:
        
        case 6:
        
        case 7:
        
        case 8:
        
        case 9:
        
        case 10:
        
        case 11:
        
        case 12:
        
        case 13:
        
        case 14:
        
        case 15:
        
        case 16:
        
        case 17:
        
        case 18:
        
        case 19:
        
        case 20:
        
        case 21:
        
        case 22:
        
        case 23:
        
        case 24:
        
        case 25:
        
        case 26:
        
        case 27:
        
        case 28:
        
        case 29:
        
        case 30:
        
        case 31:
        
        case 32:
        
        case 33:
        
        case 34:
        
        case 35:
        
        case 36:
        
        case 37:
        
        case 38:
        
        case 39:
        
        case 40:
        
        case 41:
        
        case 42:
        
        case 43:
        
        case 44:
        
        case 45:
        
        case 46:
        
        case 47:
        
        case 48:
        
        case 49:
        
        case 50:
        
        case 51:
        
        case 52:
        
        case 53:
        
        case 54:
        
        case 55:
        
        case 56:
        
        case 57:
        
        case 58:
        
        case 59:
        
        case 60:
        
        case 61:
        
        case 62:
        
        case 63:
        
        case 64:
        
        case 65:
        
        case 66:
        
        case 67:
        
        case 68:
        
        case 69:
        
        case 70:
        
        case 71:
        
        case 72:
        
        case 73:
        
        case 74:
        
        case 75:
        
        case 76:
        
        case 77:
        
        case 78:
        
        case 79:
        
        case 80:
        
        case 81:
        
        case 82:
        
        case 83:
        
        case 84:
        
        case 85:
        
        case 86:
        
        case 87:
        
        case 88:
        
        case 89:
        
        case 90:
        
        case 91:
        
        case 92:
        
        case 93:
        
        case 94:
        
        case 95:
        
        case 96:
        
        case 97:
        
        case 98:
        
        case 99:
        
        case 100:
        
        case 101:
        
        case 102:
        
        case 103:
        
        case 104:
        
        case 105:
        
        case 106:
        
        case 107:
        
        case 108:
        
        case 109:
        
        case 110:
        
        case 111:
        
        case 112:
        
        case 113:
        
        case 114:
        
        case 115:
        
        case 116:
        
        case 117:
        
        case 118:
        
        case 119:
        
        case 120:
        
        case 121:
        
        case 122:
        
        case 123:
        
        case 124:
        
        case 125:
        
        case 126:
        
        case 127:
        
        case 128:
        
        case 129:
        
        case 130:
        
        case 131:
        
        case 132:
        
        case 133:
        
        case 134:
        
        case 135:
        
        case 136:
        
        case 137:
        
        case 138:
        
        case 139:
        
        case 140:
        
        case 141:
        
        case 142:
        
        case 143:
        
        case 144:
        
        case 145:
        
        case 146:
        
        case 147:
        
        case 148:
        
        case 149:
        
        case 150:
        
        case 151:
        
        case 152:
        
        case 153:
        
        case 154:
        
        case 155:
        
        case 156:
        
        case 157:
        
        case 158:
        
        case 159:
        
        case 160:
        
        case 161:
        
        case 162:
        
        case 163:
        
        case 164:
        
        case 165:
        
        case 166:
        
        case 167:
        
        case 168:
        
        case 169:
        
        case 170:
        
        case 171:
        
        case 172:
        
        case 173:
        
        case 174:
        
        case 175:
        
        case 176:
        
        case 177:
        
        case 178:
        
        case 179:
        
        case 180:
        
        case 181:
        
        case 182:
        
        case 183:
        
        case 184:
        
        case 185:
        
        case 186:
        
        case 187:
        
        case 188:
        
        case 189:
        
        case 190:
        
        case 191:
        
        case 192:
        
        case 193:
        
        case 194:
        
        case 195:
        
        case 196:
        
        case 197:
        
        case 198:
        
        case 199:
        
        case 200:
        
        case 201:
        
        case 202:
        
        case 203:
        
        case 204:
        
        case 205:
        
        case 206:
        
        case 207:
        
        case 208:
        
        case 209:
        
        case 210:
        
        case 211:
        
        case 212:
        
        case 213:
        
        case 214:
        
        case 215:
        
        case 216:
        
        case 217:
        
        case 218:
        
        case 219:
        
        case 220:
        
        case 221:
        
        case 222:
        
        case 223:
        
        case 224:
        
        case 225:
        
        case 226:
        
        case 227:
        
        case 228:
        
        case 229:
        
        case 230:
        
        case 231:
        
        case 232:
        
        case 233:
        
        case 234:
        
        case 235:
        
        case 236:
        
        case 237:
        
        case 238:
        
        case 239:
        
        case 240:
        
        case 241:
        
        case 242:
        
        case 243:
        
        case 244:
        
        case 245:
        
        case 246:
        
        case 247:
        
        case 248:
        
        case 249:
        
        case 250:
        
        case 251:
        
        case 252:
        
        case 253:
        
        case 254:
        
        default:
          break;
      } 
      byte b1 = 32;
      int j = (paramInt2 & 0xFF) - b1;
      if (j < 0)
        j += 256; 
      int k = ((paramInt2 & 0xFFFF) >>> 8) - b1;
      if (k < 0)
        k += 256; 
      for (byte b2 = 0; b2 < arrayOfChar.length; b2++) {
        int m = b2 % 2;
        if (m == 0) {
          arrayOfChar[b2] = (char)(arrayOfChar[b2] ^ j);
          j = ((j >>> 3 | j << 5) ^ arrayOfChar[b2]) & 0xFF;
        } else {
          arrayOfChar[b2] = (char)(arrayOfChar[b2] ^ k);
          k = ((k >>> 3 | k << 5) ^ arrayOfChar[b2]) & 0xFF;
        } 
      } 
      b[i] = (new String(arrayOfChar)).intern();
    } 
    return b[i];
  }
}


/* Location:              C:\Program Files\BurpSuitePro\burpsuite_pro.jar!\burp\Zxn7.class
 * Java compiler version: 21 (65.0)
 * JD-Core Version:       1.1.3
 */