package burp;

import java.math.BigInteger;

class Zxoa extends ClassLoader {
  static Object Zr;
  
  static String Z_;
  
  private static final String[] a;
  
  private static final String[] b;
  
  static void ZK(Object[] paramArrayOfObject, Object paramObject) throws Throwable {}
  
  static void Ze(Object paramObject) {
    Zm06.Zg = a(9306, -3004);
    Zm06.ZU = new BigInteger(a(9305, -21691));
    boolean bool = Zt2e.ZK();
    try {
      try {
        if (Zgny.Zf.charAt(Math.abs(((BigInteger)Zs0b.ZI).intValue() % 32)) <= Ztd6.Zu.charAt(Math.abs(((BigInteger)Zs_.Zs).intValue() % 32))) {
          try {
            Zgqp.Zl(Class.forName(a(9300, -10654)));
            if (bool)
              Zxrd.ZY(Class.forName(a(9299, -28689))); 
          } catch (Throwable throwable) {
            throw a(null);
          } 
          return;
        } 
      } catch (Throwable throwable) {
        throw a(null);
      } 
      Zxrd.ZY(Class.forName(a(9299, -28689)));
    } catch (Throwable throwable) {}
  }
  
  static boolean Zm(Object[] paramArrayOfObject, Object paramObject) throws Throwable {
    // Byte code:
    //   0: invokestatic ZK : ()Z
    //   3: istore_2
    //   4: new java/lang/StringBuilder
    //   7: dup
    //   8: invokespecial <init> : ()V
    //   11: astore_3
    //   12: iconst_0
    //   13: istore #4
    //   15: iload #4
    //   17: bipush #32
    //   19: if_icmpge -> 1355
    //   22: iload #4
    //   24: tableswitch default -> 1348, 0 -> 168, 1 -> 205, 2 -> 242, 3 -> 279, 4 -> 316, 5 -> 353, 6 -> 390, 7 -> 427, 8 -> 464, 9 -> 501, 10 -> 538, 11 -> 575, 12 -> 612, 13 -> 649, 14 -> 686, 15 -> 723, 16 -> 760, 17 -> 797, 18 -> 834, 19 -> 871, 20 -> 908, 21 -> 945, 22 -> 982, 23 -> 1019, 24 -> 1056, 25 -> 1093, 26 -> 1130, 27 -> 1167, 28 -> 1204, 29 -> 1241, 30 -> 1278, 31 -> 1315
    //   168: aload_3
    //   169: getstatic burp/Ze5f.Zt : Ljava/lang/String;
    //   172: getstatic burp/Zgmo.Zo : Ljava/lang/Object;
    //   175: checkcast java/math/BigInteger
    //   178: invokevirtual intValue : ()I
    //   181: bipush #32
    //   183: irem
    //   184: invokestatic abs : (I)I
    //   187: invokevirtual charAt : (I)C
    //   190: invokevirtual append : (C)Ljava/lang/StringBuilder;
    //   193: pop
    //   194: iload_2
    //   195: ifeq -> 1348
    //   198: goto -> 205
    //   201: invokestatic a : (Ljava/lang/Throwable;)Ljava/lang/Throwable;
    //   204: athrow
    //   205: aload_3
    //   206: getstatic burp/Zli5.Zq : Ljava/lang/String;
    //   209: getstatic burp/Zb8y.ZI : Ljava/lang/Object;
    //   212: checkcast java/math/BigInteger
    //   215: invokevirtual intValue : ()I
    //   218: bipush #32
    //   220: irem
    //   221: invokestatic abs : (I)I
    //   224: invokevirtual charAt : (I)C
    //   227: invokevirtual append : (C)Ljava/lang/StringBuilder;
    //   230: pop
    //   231: iload_2
    //   232: ifeq -> 1348
    //   235: goto -> 242
    //   238: invokestatic a : (Ljava/lang/Throwable;)Ljava/lang/Throwable;
    //   241: athrow
    //   242: aload_3
    //   243: getstatic burp/Ztbf.Zf : Ljava/lang/String;
    //   246: getstatic burp/Zlr2.Zq : Ljava/lang/Object;
    //   249: checkcast java/math/BigInteger
    //   252: invokevirtual intValue : ()I
    //   255: bipush #32
    //   257: irem
    //   258: invokestatic abs : (I)I
    //   261: invokevirtual charAt : (I)C
    //   264: invokevirtual append : (C)Ljava/lang/StringBuilder;
    //   267: pop
    //   268: iload_2
    //   269: ifeq -> 1348
    //   272: goto -> 279
    //   275: invokestatic a : (Ljava/lang/Throwable;)Ljava/lang/Throwable;
    //   278: athrow
    //   279: aload_3
    //   280: getstatic burp/Zrh1.Zg : Ljava/lang/String;
    //   283: getstatic burp/Zeoi.ZE : Ljava/lang/Object;
    //   286: checkcast java/math/BigInteger
    //   289: invokevirtual intValue : ()I
    //   292: bipush #32
    //   294: irem
    //   295: invokestatic abs : (I)I
    //   298: invokevirtual charAt : (I)C
    //   301: invokevirtual append : (C)Ljava/lang/StringBuilder;
    //   304: pop
    //   305: iload_2
    //   306: ifeq -> 1348
    //   309: goto -> 316
    //   312: invokestatic a : (Ljava/lang/Throwable;)Ljava/lang/Throwable;
    //   315: athrow
    //   316: aload_3
    //   317: getstatic burp/Zmze.ZO : Ljava/lang/String;
    //   320: getstatic burp/Zkk2.Zq : Ljava/lang/Object;
    //   323: checkcast java/math/BigInteger
    //   326: invokevirtual intValue : ()I
    //   329: bipush #32
    //   331: irem
    //   332: invokestatic abs : (I)I
    //   335: invokevirtual charAt : (I)C
    //   338: invokevirtual append : (C)Ljava/lang/StringBuilder;
    //   341: pop
    //   342: iload_2
    //   343: ifeq -> 1348
    //   346: goto -> 353
    //   349: invokestatic a : (Ljava/lang/Throwable;)Ljava/lang/Throwable;
    //   352: athrow
    //   353: aload_3
    //   354: getstatic burp/Zbf9.Zp : Ljava/lang/String;
    //   357: getstatic burp/Zt5b.Zc : Ljava/lang/Object;
    //   360: checkcast java/math/BigInteger
    //   363: invokevirtual intValue : ()I
    //   366: bipush #32
    //   368: irem
    //   369: invokestatic abs : (I)I
    //   372: invokevirtual charAt : (I)C
    //   375: invokevirtual append : (C)Ljava/lang/StringBuilder;
    //   378: pop
    //   379: iload_2
    //   380: ifeq -> 1348
    //   383: goto -> 390
    //   386: invokestatic a : (Ljava/lang/Throwable;)Ljava/lang/Throwable;
    //   389: athrow
    //   390: aload_3
    //   391: getstatic burp/Zm52.Ze : Ljava/lang/String;
    //   394: getstatic burp/Zzri.ZG : Ljava/lang/Object;
    //   397: checkcast java/math/BigInteger
    //   400: invokevirtual intValue : ()I
    //   403: bipush #32
    //   405: irem
    //   406: invokestatic abs : (I)I
    //   409: invokevirtual charAt : (I)C
    //   412: invokevirtual append : (C)Ljava/lang/StringBuilder;
    //   415: pop
    //   416: iload_2
    //   417: ifeq -> 1348
    //   420: goto -> 427
    //   423: invokestatic a : (Ljava/lang/Throwable;)Ljava/lang/Throwable;
    //   426: athrow
    //   427: aload_3
    //   428: getstatic burp/Zlxm.Zv : Ljava/lang/String;
    //   431: getstatic burp/Zm5p.Ze : Ljava/lang/Object;
    //   434: checkcast java/math/BigInteger
    //   437: invokevirtual intValue : ()I
    //   440: bipush #32
    //   442: irem
    //   443: invokestatic abs : (I)I
    //   446: invokevirtual charAt : (I)C
    //   449: invokevirtual append : (C)Ljava/lang/StringBuilder;
    //   452: pop
    //   453: iload_2
    //   454: ifeq -> 1348
    //   457: goto -> 464
    //   460: invokestatic a : (Ljava/lang/Throwable;)Ljava/lang/Throwable;
    //   463: athrow
    //   464: aload_3
    //   465: getstatic burp/Zzou.ZN : Ljava/lang/String;
    //   468: getstatic burp/Zdk.Zy : Ljava/lang/Object;
    //   471: checkcast java/math/BigInteger
    //   474: invokevirtual intValue : ()I
    //   477: bipush #32
    //   479: irem
    //   480: invokestatic abs : (I)I
    //   483: invokevirtual charAt : (I)C
    //   486: invokevirtual append : (C)Ljava/lang/StringBuilder;
    //   489: pop
    //   490: iload_2
    //   491: ifeq -> 1348
    //   494: goto -> 501
    //   497: invokestatic a : (Ljava/lang/Throwable;)Ljava/lang/Throwable;
    //   500: athrow
    //   501: aload_3
    //   502: getstatic burp/Zmcb.Zl : Ljava/lang/String;
    //   505: getstatic burp/Zsdn.ZE : Ljava/lang/Object;
    //   508: checkcast java/math/BigInteger
    //   511: invokevirtual intValue : ()I
    //   514: bipush #32
    //   516: irem
    //   517: invokestatic abs : (I)I
    //   520: invokevirtual charAt : (I)C
    //   523: invokevirtual append : (C)Ljava/lang/StringBuilder;
    //   526: pop
    //   527: iload_2
    //   528: ifeq -> 1348
    //   531: goto -> 538
    //   534: invokestatic a : (Ljava/lang/Throwable;)Ljava/lang/Throwable;
    //   537: athrow
    //   538: aload_3
    //   539: getstatic burp/Zevc.ZF : Ljava/lang/String;
    //   542: getstatic burp/Zk8g.Zb : Ljava/lang/Object;
    //   545: checkcast java/math/BigInteger
    //   548: invokevirtual intValue : ()I
    //   551: bipush #32
    //   553: irem
    //   554: invokestatic abs : (I)I
    //   557: invokevirtual charAt : (I)C
    //   560: invokevirtual append : (C)Ljava/lang/StringBuilder;
    //   563: pop
    //   564: iload_2
    //   565: ifeq -> 1348
    //   568: goto -> 575
    //   571: invokestatic a : (Ljava/lang/Throwable;)Ljava/lang/Throwable;
    //   574: athrow
    //   575: aload_3
    //   576: getstatic burp/Zb29.Zf : Ljava/lang/String;
    //   579: getstatic burp/Zk7w.ZF : Ljava/lang/Object;
    //   582: checkcast java/math/BigInteger
    //   585: invokevirtual intValue : ()I
    //   588: bipush #32
    //   590: irem
    //   591: invokestatic abs : (I)I
    //   594: invokevirtual charAt : (I)C
    //   597: invokevirtual append : (C)Ljava/lang/StringBuilder;
    //   600: pop
    //   601: iload_2
    //   602: ifeq -> 1348
    //   605: goto -> 612
    //   608: invokestatic a : (Ljava/lang/Throwable;)Ljava/lang/Throwable;
    //   611: athrow
    //   612: aload_3
    //   613: getstatic burp/Zt3l.Zi : Ljava/lang/String;
    //   616: getstatic burp/Zsq5.ZF : Ljava/lang/Object;
    //   619: checkcast java/math/BigInteger
    //   622: invokevirtual intValue : ()I
    //   625: bipush #32
    //   627: irem
    //   628: invokestatic abs : (I)I
    //   631: invokevirtual charAt : (I)C
    //   634: invokevirtual append : (C)Ljava/lang/StringBuilder;
    //   637: pop
    //   638: iload_2
    //   639: ifeq -> 1348
    //   642: goto -> 649
    //   645: invokestatic a : (Ljava/lang/Throwable;)Ljava/lang/Throwable;
    //   648: athrow
    //   649: aload_3
    //   650: getstatic burp/Zgvf.ZM : Ljava/lang/String;
    //   653: getstatic burp/Zzc7.ZG : Ljava/lang/Object;
    //   656: checkcast java/math/BigInteger
    //   659: invokevirtual intValue : ()I
    //   662: bipush #32
    //   664: irem
    //   665: invokestatic abs : (I)I
    //   668: invokevirtual charAt : (I)C
    //   671: invokevirtual append : (C)Ljava/lang/StringBuilder;
    //   674: pop
    //   675: iload_2
    //   676: ifeq -> 1348
    //   679: goto -> 686
    //   682: invokestatic a : (Ljava/lang/Throwable;)Ljava/lang/Throwable;
    //   685: athrow
    //   686: aload_3
    //   687: getstatic burp/Zbsr.Zq : Ljava/lang/String;
    //   690: getstatic burp/Ztw4.ZF : Ljava/lang/Object;
    //   693: checkcast java/math/BigInteger
    //   696: invokevirtual intValue : ()I
    //   699: bipush #32
    //   701: irem
    //   702: invokestatic abs : (I)I
    //   705: invokevirtual charAt : (I)C
    //   708: invokevirtual append : (C)Ljava/lang/StringBuilder;
    //   711: pop
    //   712: iload_2
    //   713: ifeq -> 1348
    //   716: goto -> 723
    //   719: invokestatic a : (Ljava/lang/Throwable;)Ljava/lang/Throwable;
    //   722: athrow
    //   723: aload_3
    //   724: getstatic burp/Zb6a.ZY : Ljava/lang/String;
    //   727: getstatic burp/Znp.ZJ : Ljava/lang/Object;
    //   730: checkcast java/math/BigInteger
    //   733: invokevirtual intValue : ()I
    //   736: bipush #32
    //   738: irem
    //   739: invokestatic abs : (I)I
    //   742: invokevirtual charAt : (I)C
    //   745: invokevirtual append : (C)Ljava/lang/StringBuilder;
    //   748: pop
    //   749: iload_2
    //   750: ifeq -> 1348
    //   753: goto -> 760
    //   756: invokestatic a : (Ljava/lang/Throwable;)Ljava/lang/Throwable;
    //   759: athrow
    //   760: aload_3
    //   761: getstatic burp/Zb8y.Zn : Ljava/lang/String;
    //   764: getstatic burp/Zelz.Z_ : Ljava/lang/Object;
    //   767: checkcast java/math/BigInteger
    //   770: invokevirtual intValue : ()I
    //   773: bipush #32
    //   775: irem
    //   776: invokestatic abs : (I)I
    //   779: invokevirtual charAt : (I)C
    //   782: invokevirtual append : (C)Ljava/lang/StringBuilder;
    //   785: pop
    //   786: iload_2
    //   787: ifeq -> 1348
    //   790: goto -> 797
    //   793: invokestatic a : (Ljava/lang/Throwable;)Ljava/lang/Throwable;
    //   796: athrow
    //   797: aload_3
    //   798: getstatic burp/Zgqp.ZA : Ljava/lang/String;
    //   801: getstatic burp/Zz75.ZX : Ljava/lang/Object;
    //   804: checkcast java/math/BigInteger
    //   807: invokevirtual intValue : ()I
    //   810: bipush #32
    //   812: irem
    //   813: invokestatic abs : (I)I
    //   816: invokevirtual charAt : (I)C
    //   819: invokevirtual append : (C)Ljava/lang/StringBuilder;
    //   822: pop
    //   823: iload_2
    //   824: ifeq -> 1348
    //   827: goto -> 834
    //   830: invokestatic a : (Ljava/lang/Throwable;)Ljava/lang/Throwable;
    //   833: athrow
    //   834: aload_3
    //   835: getstatic burp/Zbu6.ZQ : Ljava/lang/String;
    //   838: getstatic burp/Zl5d.Za : Ljava/lang/Object;
    //   841: checkcast java/math/BigInteger
    //   844: invokevirtual intValue : ()I
    //   847: bipush #32
    //   849: irem
    //   850: invokestatic abs : (I)I
    //   853: invokevirtual charAt : (I)C
    //   856: invokevirtual append : (C)Ljava/lang/StringBuilder;
    //   859: pop
    //   860: iload_2
    //   861: ifeq -> 1348
    //   864: goto -> 871
    //   867: invokestatic a : (Ljava/lang/Throwable;)Ljava/lang/Throwable;
    //   870: athrow
    //   871: aload_3
    //   872: getstatic burp/Zejg.ZP : Ljava/lang/String;
    //   875: getstatic burp/Zrxm.ZL : Ljava/lang/Object;
    //   878: checkcast java/math/BigInteger
    //   881: invokevirtual intValue : ()I
    //   884: bipush #32
    //   886: irem
    //   887: invokestatic abs : (I)I
    //   890: invokevirtual charAt : (I)C
    //   893: invokevirtual append : (C)Ljava/lang/StringBuilder;
    //   896: pop
    //   897: iload_2
    //   898: ifeq -> 1348
    //   901: goto -> 908
    //   904: invokestatic a : (Ljava/lang/Throwable;)Ljava/lang/Throwable;
    //   907: athrow
    //   908: aload_3
    //   909: getstatic burp/Zegk.Ze : Ljava/lang/String;
    //   912: getstatic burp/Zegv.ZL : Ljava/lang/Object;
    //   915: checkcast java/math/BigInteger
    //   918: invokevirtual intValue : ()I
    //   921: bipush #32
    //   923: irem
    //   924: invokestatic abs : (I)I
    //   927: invokevirtual charAt : (I)C
    //   930: invokevirtual append : (C)Ljava/lang/StringBuilder;
    //   933: pop
    //   934: iload_2
    //   935: ifeq -> 1348
    //   938: goto -> 945
    //   941: invokestatic a : (Ljava/lang/Throwable;)Ljava/lang/Throwable;
    //   944: athrow
    //   945: aload_3
    //   946: getstatic burp/Zxl5.Zq : Ljava/lang/String;
    //   949: getstatic burp/Zl8l.ZJ : Ljava/lang/Object;
    //   952: checkcast java/math/BigInteger
    //   955: invokevirtual intValue : ()I
    //   958: bipush #32
    //   960: irem
    //   961: invokestatic abs : (I)I
    //   964: invokevirtual charAt : (I)C
    //   967: invokevirtual append : (C)Ljava/lang/StringBuilder;
    //   970: pop
    //   971: iload_2
    //   972: ifeq -> 1348
    //   975: goto -> 982
    //   978: invokestatic a : (Ljava/lang/Throwable;)Ljava/lang/Throwable;
    //   981: athrow
    //   982: aload_3
    //   983: getstatic burp/Zzgh.Zn : Ljava/lang/String;
    //   986: getstatic burp/Zl1u.Zq : Ljava/lang/Object;
    //   989: checkcast java/math/BigInteger
    //   992: invokevirtual intValue : ()I
    //   995: bipush #32
    //   997: irem
    //   998: invokestatic abs : (I)I
    //   1001: invokevirtual charAt : (I)C
    //   1004: invokevirtual append : (C)Ljava/lang/StringBuilder;
    //   1007: pop
    //   1008: iload_2
    //   1009: ifeq -> 1348
    //   1012: goto -> 1019
    //   1015: invokestatic a : (Ljava/lang/Throwable;)Ljava/lang/Throwable;
    //   1018: athrow
    //   1019: aload_3
    //   1020: getstatic burp/Ze3t.ZG : Ljava/lang/String;
    //   1023: getstatic burp/Zt7k.Zc : Ljava/lang/Object;
    //   1026: checkcast java/math/BigInteger
    //   1029: invokevirtual intValue : ()I
    //   1032: bipush #32
    //   1034: irem
    //   1035: invokestatic abs : (I)I
    //   1038: invokevirtual charAt : (I)C
    //   1041: invokevirtual append : (C)Ljava/lang/StringBuilder;
    //   1044: pop
    //   1045: iload_2
    //   1046: ifeq -> 1348
    //   1049: goto -> 1056
    //   1052: invokestatic a : (Ljava/lang/Throwable;)Ljava/lang/Throwable;
    //   1055: athrow
    //   1056: aload_3
    //   1057: getstatic burp/Zr1t.Ze : Ljava/lang/String;
    //   1060: getstatic burp/Zrnw.ZN : Ljava/lang/Object;
    //   1063: checkcast java/math/BigInteger
    //   1066: invokevirtual intValue : ()I
    //   1069: bipush #32
    //   1071: irem
    //   1072: invokestatic abs : (I)I
    //   1075: invokevirtual charAt : (I)C
    //   1078: invokevirtual append : (C)Ljava/lang/StringBuilder;
    //   1081: pop
    //   1082: iload_2
    //   1083: ifeq -> 1348
    //   1086: goto -> 1093
    //   1089: invokestatic a : (Ljava/lang/Throwable;)Ljava/lang/Throwable;
    //   1092: athrow
    //   1093: aload_3
    //   1094: getstatic burp/Zl55.Zp : Ljava/lang/String;
    //   1097: getstatic burp/Zsf4.Zr : Ljava/lang/Object;
    //   1100: checkcast java/math/BigInteger
    //   1103: invokevirtual intValue : ()I
    //   1106: bipush #32
    //   1108: irem
    //   1109: invokestatic abs : (I)I
    //   1112: invokevirtual charAt : (I)C
    //   1115: invokevirtual append : (C)Ljava/lang/StringBuilder;
    //   1118: pop
    //   1119: iload_2
    //   1120: ifeq -> 1348
    //   1123: goto -> 1130
    //   1126: invokestatic a : (Ljava/lang/Throwable;)Ljava/lang/Throwable;
    //   1129: athrow
    //   1130: aload_3
    //   1131: getstatic burp/Zl_9.ZP : Ljava/lang/String;
    //   1134: getstatic burp/Zl8i.ZY : Ljava/lang/Object;
    //   1137: checkcast java/math/BigInteger
    //   1140: invokevirtual intValue : ()I
    //   1143: bipush #32
    //   1145: irem
    //   1146: invokestatic abs : (I)I
    //   1149: invokevirtual charAt : (I)C
    //   1152: invokevirtual append : (C)Ljava/lang/StringBuilder;
    //   1155: pop
    //   1156: iload_2
    //   1157: ifeq -> 1348
    //   1160: goto -> 1167
    //   1163: invokestatic a : (Ljava/lang/Throwable;)Ljava/lang/Throwable;
    //   1166: athrow
    //   1167: aload_3
    //   1168: getstatic burp/Ztpa.ZZ : Ljava/lang/String;
    //   1171: getstatic burp/Zg5.Zs : Ljava/lang/Object;
    //   1174: checkcast java/math/BigInteger
    //   1177: invokevirtual intValue : ()I
    //   1180: bipush #32
    //   1182: irem
    //   1183: invokestatic abs : (I)I
    //   1186: invokevirtual charAt : (I)C
    //   1189: invokevirtual append : (C)Ljava/lang/StringBuilder;
    //   1192: pop
    //   1193: iload_2
    //   1194: ifeq -> 1348
    //   1197: goto -> 1204
    //   1200: invokestatic a : (Ljava/lang/Throwable;)Ljava/lang/Throwable;
    //   1203: athrow
    //   1204: aload_3
    //   1205: getstatic burp/Zzna.Zi : Ljava/lang/String;
    //   1208: getstatic burp/Zl1z.ZV : Ljava/lang/Object;
    //   1211: checkcast java/math/BigInteger
    //   1214: invokevirtual intValue : ()I
    //   1217: bipush #32
    //   1219: irem
    //   1220: invokestatic abs : (I)I
    //   1223: invokevirtual charAt : (I)C
    //   1226: invokevirtual append : (C)Ljava/lang/StringBuilder;
    //   1229: pop
    //   1230: iload_2
    //   1231: ifeq -> 1348
    //   1234: goto -> 1241
    //   1237: invokestatic a : (Ljava/lang/Throwable;)Ljava/lang/Throwable;
    //   1240: athrow
    //   1241: aload_3
    //   1242: getstatic burp/Zzlg.Zw : Ljava/lang/String;
    //   1245: getstatic burp/Zmsl.ZB : Ljava/lang/Object;
    //   1248: checkcast java/math/BigInteger
    //   1251: invokevirtual intValue : ()I
    //   1254: bipush #32
    //   1256: irem
    //   1257: invokestatic abs : (I)I
    //   1260: invokevirtual charAt : (I)C
    //   1263: invokevirtual append : (C)Ljava/lang/StringBuilder;
    //   1266: pop
    //   1267: iload_2
    //   1268: ifeq -> 1348
    //   1271: goto -> 1278
    //   1274: invokestatic a : (Ljava/lang/Throwable;)Ljava/lang/Throwable;
    //   1277: athrow
    //   1278: aload_3
    //   1279: getstatic burp/Zsf7.ZS : Ljava/lang/String;
    //   1282: getstatic burp/Zsgj.ZK : Ljava/lang/Object;
    //   1285: checkcast java/math/BigInteger
    //   1288: invokevirtual intValue : ()I
    //   1291: bipush #32
    //   1293: irem
    //   1294: invokestatic abs : (I)I
    //   1297: invokevirtual charAt : (I)C
    //   1300: invokevirtual append : (C)Ljava/lang/StringBuilder;
    //   1303: pop
    //   1304: iload_2
    //   1305: ifeq -> 1348
    //   1308: goto -> 1315
    //   1311: invokestatic a : (Ljava/lang/Throwable;)Ljava/lang/Throwable;
    //   1314: athrow
    //   1315: aload_3
    //   1316: getstatic burp/Zktq.Zc : Ljava/lang/String;
    //   1319: getstatic burp/Zgta.ZF : Ljava/lang/Object;
    //   1322: checkcast java/math/BigInteger
    //   1325: invokevirtual intValue : ()I
    //   1328: bipush #32
    //   1330: irem
    //   1331: invokestatic abs : (I)I
    //   1334: invokevirtual charAt : (I)C
    //   1337: invokevirtual append : (C)Ljava/lang/StringBuilder;
    //   1340: pop
    //   1341: goto -> 1348
    //   1344: invokestatic a : (Ljava/lang/Throwable;)Ljava/lang/Throwable;
    //   1347: athrow
    //   1348: iinc #4, 1
    //   1351: iload_2
    //   1352: ifeq -> 15
    //   1355: aload_3
    //   1356: invokevirtual toString : ()Ljava/lang/String;
    //   1359: putstatic burp/Zxyq.Zr : Ljava/lang/String;
    //   1362: getstatic burp/Zzc7.ZG : Ljava/lang/Object;
    //   1365: checkcast java/math/BigInteger
    //   1368: invokevirtual toByteArray : ()[B
    //   1371: astore #4
    //   1373: aload #4
    //   1375: arraylength
    //   1376: iconst_2
    //   1377: iadd
    //   1378: newarray byte
    //   1380: astore #6
    //   1382: iconst_0
    //   1383: istore #7
    //   1385: iload #7
    //   1387: aload #4
    //   1389: arraylength
    //   1390: if_icmpge -> 1410
    //   1393: aload #6
    //   1395: iload #7
    //   1397: aload #4
    //   1399: iload #7
    //   1401: baload
    //   1402: bastore
    //   1403: iinc #7, 1
    //   1406: iload_2
    //   1407: ifeq -> 1385
    //   1410: aload #6
    //   1412: arraylength
    //   1413: iconst_3
    //   1414: idiv
    //   1415: iconst_4
    //   1416: imul
    //   1417: newarray byte
    //   1419: astore #5
    //   1421: iconst_0
    //   1422: istore #7
    //   1424: iconst_0
    //   1425: istore #8
    //   1427: iload #7
    //   1429: aload #4
    //   1431: arraylength
    //   1432: if_icmpge -> 1543
    //   1435: aload #5
    //   1437: iload #8
    //   1439: aload #6
    //   1441: iload #7
    //   1443: baload
    //   1444: iconst_2
    //   1445: iushr
    //   1446: bipush #63
    //   1448: iand
    //   1449: i2b
    //   1450: bastore
    //   1451: aload #5
    //   1453: iload #8
    //   1455: iconst_1
    //   1456: iadd
    //   1457: aload #6
    //   1459: iload #7
    //   1461: iconst_1
    //   1462: iadd
    //   1463: baload
    //   1464: iconst_4
    //   1465: iushr
    //   1466: bipush #15
    //   1468: iand
    //   1469: aload #6
    //   1471: iload #7
    //   1473: baload
    //   1474: iconst_4
    //   1475: ishl
    //   1476: bipush #63
    //   1478: iand
    //   1479: ior
    //   1480: i2b
    //   1481: bastore
    //   1482: aload #5
    //   1484: iload #8
    //   1486: iconst_2
    //   1487: iadd
    //   1488: aload #6
    //   1490: iload #7
    //   1492: iconst_2
    //   1493: iadd
    //   1494: baload
    //   1495: bipush #6
    //   1497: iushr
    //   1498: iconst_3
    //   1499: iand
    //   1500: aload #6
    //   1502: iload #7
    //   1504: iconst_1
    //   1505: iadd
    //   1506: baload
    //   1507: iconst_2
    //   1508: ishl
    //   1509: bipush #63
    //   1511: iand
    //   1512: ior
    //   1513: i2b
    //   1514: bastore
    //   1515: aload #5
    //   1517: iload #8
    //   1519: iconst_3
    //   1520: iadd
    //   1521: aload #6
    //   1523: iload #7
    //   1525: iconst_2
    //   1526: iadd
    //   1527: baload
    //   1528: bipush #63
    //   1530: iand
    //   1531: i2b
    //   1532: bastore
    //   1533: iinc #7, 3
    //   1536: iinc #8, 4
    //   1539: iload_2
    //   1540: ifeq -> 1427
    //   1543: iconst_0
    //   1544: istore #7
    //   1546: iload #7
    //   1548: aload #5
    //   1550: arraylength
    //   1551: if_icmpge -> 1735
    //   1554: aload #5
    //   1556: iload #7
    //   1558: baload
    //   1559: bipush #26
    //   1561: if_icmpge -> 1589
    //   1564: aload #5
    //   1566: iload #7
    //   1568: aload #5
    //   1570: iload #7
    //   1572: baload
    //   1573: bipush #65
    //   1575: iadd
    //   1576: i2b
    //   1577: bastore
    //   1578: iload_2
    //   1579: ifeq -> 1728
    //   1582: goto -> 1589
    //   1585: invokestatic a : (Ljava/lang/Throwable;)Ljava/lang/Throwable;
    //   1588: athrow
    //   1589: aload #5
    //   1591: iload #7
    //   1593: baload
    //   1594: bipush #52
    //   1596: if_icmpge -> 1634
    //   1599: goto -> 1606
    //   1602: invokestatic a : (Ljava/lang/Throwable;)Ljava/lang/Throwable;
    //   1605: athrow
    //   1606: aload #5
    //   1608: iload #7
    //   1610: aload #5
    //   1612: iload #7
    //   1614: baload
    //   1615: bipush #97
    //   1617: iadd
    //   1618: bipush #26
    //   1620: isub
    //   1621: i2b
    //   1622: bastore
    //   1623: iload_2
    //   1624: ifeq -> 1728
    //   1627: goto -> 1634
    //   1630: invokestatic a : (Ljava/lang/Throwable;)Ljava/lang/Throwable;
    //   1633: athrow
    //   1634: aload #5
    //   1636: iload #7
    //   1638: baload
    //   1639: bipush #62
    //   1641: if_icmpge -> 1679
    //   1644: goto -> 1651
    //   1647: invokestatic a : (Ljava/lang/Throwable;)Ljava/lang/Throwable;
    //   1650: athrow
    //   1651: aload #5
    //   1653: iload #7
    //   1655: aload #5
    //   1657: iload #7
    //   1659: baload
    //   1660: bipush #48
    //   1662: iadd
    //   1663: bipush #52
    //   1665: isub
    //   1666: i2b
    //   1667: bastore
    //   1668: iload_2
    //   1669: ifeq -> 1728
    //   1672: goto -> 1679
    //   1675: invokestatic a : (Ljava/lang/Throwable;)Ljava/lang/Throwable;
    //   1678: athrow
    //   1679: aload #5
    //   1681: iload #7
    //   1683: baload
    //   1684: bipush #63
    //   1686: if_icmpge -> 1714
    //   1689: goto -> 1696
    //   1692: invokestatic a : (Ljava/lang/Throwable;)Ljava/lang/Throwable;
    //   1695: athrow
    //   1696: aload #5
    //   1698: iload #7
    //   1700: bipush #43
    //   1702: bastore
    //   1703: iload_2
    //   1704: ifeq -> 1728
    //   1707: goto -> 1714
    //   1710: invokestatic a : (Ljava/lang/Throwable;)Ljava/lang/Throwable;
    //   1713: athrow
    //   1714: aload #5
    //   1716: iload #7
    //   1718: bipush #47
    //   1720: bastore
    //   1721: goto -> 1728
    //   1724: invokestatic a : (Ljava/lang/Throwable;)Ljava/lang/Throwable;
    //   1727: athrow
    //   1728: iinc #7, 1
    //   1731: iload_2
    //   1732: ifeq -> 1546
    //   1735: aload #5
    //   1737: arraylength
    //   1738: iconst_1
    //   1739: isub
    //   1740: istore #7
    //   1742: iload #7
    //   1744: aload #4
    //   1746: arraylength
    //   1747: iconst_4
    //   1748: imul
    //   1749: iconst_3
    //   1750: idiv
    //   1751: if_icmple -> 1768
    //   1754: aload #5
    //   1756: iload #7
    //   1758: bipush #61
    //   1760: bastore
    //   1761: iinc #7, -1
    //   1764: iload_2
    //   1765: ifeq -> 1742
    //   1768: new java/math/BigInteger
    //   1771: dup
    //   1772: aload #5
    //   1774: invokespecial <init> : ([B)V
    //   1777: invokevirtual abs : ()Ljava/math/BigInteger;
    //   1780: putstatic burp/Ztpa.Zv : Ljava/lang/Object;
    //   1783: getstatic burp/Zr8g.ZF : Ljava/lang/Object;
    //   1786: checkcast java/math/BigInteger
    //   1789: invokevirtual toByteArray : ()[B
    //   1792: astore #4
    //   1794: aload #4
    //   1796: arraylength
    //   1797: iconst_2
    //   1798: iadd
    //   1799: newarray byte
    //   1801: astore #6
    //   1803: iconst_0
    //   1804: istore #7
    //   1806: iload #7
    //   1808: aload #4
    //   1810: arraylength
    //   1811: if_icmpge -> 1831
    //   1814: aload #6
    //   1816: iload #7
    //   1818: aload #4
    //   1820: iload #7
    //   1822: baload
    //   1823: bastore
    //   1824: iinc #7, 1
    //   1827: iload_2
    //   1828: ifeq -> 1806
    //   1831: aload #6
    //   1833: arraylength
    //   1834: iconst_3
    //   1835: idiv
    //   1836: iconst_4
    //   1837: imul
    //   1838: newarray byte
    //   1840: astore #5
    //   1842: iconst_0
    //   1843: istore #7
    //   1845: iconst_0
    //   1846: istore #8
    //   1848: iload #7
    //   1850: aload #4
    //   1852: arraylength
    //   1853: if_icmpge -> 1964
    //   1856: aload #5
    //   1858: iload #8
    //   1860: aload #6
    //   1862: iload #7
    //   1864: baload
    //   1865: iconst_2
    //   1866: iushr
    //   1867: bipush #63
    //   1869: iand
    //   1870: i2b
    //   1871: bastore
    //   1872: aload #5
    //   1874: iload #8
    //   1876: iconst_1
    //   1877: iadd
    //   1878: aload #6
    //   1880: iload #7
    //   1882: iconst_1
    //   1883: iadd
    //   1884: baload
    //   1885: iconst_4
    //   1886: iushr
    //   1887: bipush #15
    //   1889: iand
    //   1890: aload #6
    //   1892: iload #7
    //   1894: baload
    //   1895: iconst_4
    //   1896: ishl
    //   1897: bipush #63
    //   1899: iand
    //   1900: ior
    //   1901: i2b
    //   1902: bastore
    //   1903: aload #5
    //   1905: iload #8
    //   1907: iconst_2
    //   1908: iadd
    //   1909: aload #6
    //   1911: iload #7
    //   1913: iconst_2
    //   1914: iadd
    //   1915: baload
    //   1916: bipush #6
    //   1918: iushr
    //   1919: iconst_3
    //   1920: iand
    //   1921: aload #6
    //   1923: iload #7
    //   1925: iconst_1
    //   1926: iadd
    //   1927: baload
    //   1928: iconst_2
    //   1929: ishl
    //   1930: bipush #63
    //   1932: iand
    //   1933: ior
    //   1934: i2b
    //   1935: bastore
    //   1936: aload #5
    //   1938: iload #8
    //   1940: iconst_3
    //   1941: iadd
    //   1942: aload #6
    //   1944: iload #7
    //   1946: iconst_2
    //   1947: iadd
    //   1948: baload
    //   1949: bipush #63
    //   1951: iand
    //   1952: i2b
    //   1953: bastore
    //   1954: iinc #7, 3
    //   1957: iinc #8, 4
    //   1960: iload_2
    //   1961: ifeq -> 1848
    //   1964: iconst_0
    //   1965: istore #7
    //   1967: iload #7
    //   1969: aload #5
    //   1971: arraylength
    //   1972: if_icmpge -> 2156
    //   1975: aload #5
    //   1977: iload #7
    //   1979: baload
    //   1980: bipush #26
    //   1982: if_icmpge -> 2010
    //   1985: aload #5
    //   1987: iload #7
    //   1989: aload #5
    //   1991: iload #7
    //   1993: baload
    //   1994: bipush #65
    //   1996: iadd
    //   1997: i2b
    //   1998: bastore
    //   1999: iload_2
    //   2000: ifeq -> 2149
    //   2003: goto -> 2010
    //   2006: invokestatic a : (Ljava/lang/Throwable;)Ljava/lang/Throwable;
    //   2009: athrow
    //   2010: aload #5
    //   2012: iload #7
    //   2014: baload
    //   2015: bipush #52
    //   2017: if_icmpge -> 2055
    //   2020: goto -> 2027
    //   2023: invokestatic a : (Ljava/lang/Throwable;)Ljava/lang/Throwable;
    //   2026: athrow
    //   2027: aload #5
    //   2029: iload #7
    //   2031: aload #5
    //   2033: iload #7
    //   2035: baload
    //   2036: bipush #97
    //   2038: iadd
    //   2039: bipush #26
    //   2041: isub
    //   2042: i2b
    //   2043: bastore
    //   2044: iload_2
    //   2045: ifeq -> 2149
    //   2048: goto -> 2055
    //   2051: invokestatic a : (Ljava/lang/Throwable;)Ljava/lang/Throwable;
    //   2054: athrow
    //   2055: aload #5
    //   2057: iload #7
    //   2059: baload
    //   2060: bipush #62
    //   2062: if_icmpge -> 2100
    //   2065: goto -> 2072
    //   2068: invokestatic a : (Ljava/lang/Throwable;)Ljava/lang/Throwable;
    //   2071: athrow
    //   2072: aload #5
    //   2074: iload #7
    //   2076: aload #5
    //   2078: iload #7
    //   2080: baload
    //   2081: bipush #48
    //   2083: iadd
    //   2084: bipush #52
    //   2086: isub
    //   2087: i2b
    //   2088: bastore
    //   2089: iload_2
    //   2090: ifeq -> 2149
    //   2093: goto -> 2100
    //   2096: invokestatic a : (Ljava/lang/Throwable;)Ljava/lang/Throwable;
    //   2099: athrow
    //   2100: aload #5
    //   2102: iload #7
    //   2104: baload
    //   2105: bipush #63
    //   2107: if_icmpge -> 2135
    //   2110: goto -> 2117
    //   2113: invokestatic a : (Ljava/lang/Throwable;)Ljava/lang/Throwable;
    //   2116: athrow
    //   2117: aload #5
    //   2119: iload #7
    //   2121: bipush #43
    //   2123: bastore
    //   2124: iload_2
    //   2125: ifeq -> 2149
    //   2128: goto -> 2135
    //   2131: invokestatic a : (Ljava/lang/Throwable;)Ljava/lang/Throwable;
    //   2134: athrow
    //   2135: aload #5
    //   2137: iload #7
    //   2139: bipush #47
    //   2141: bastore
    //   2142: goto -> 2149
    //   2145: invokestatic a : (Ljava/lang/Throwable;)Ljava/lang/Throwable;
    //   2148: athrow
    //   2149: iinc #7, 1
    //   2152: iload_2
    //   2153: ifeq -> 1967
    //   2156: aload #5
    //   2158: arraylength
    //   2159: iconst_1
    //   2160: isub
    //   2161: istore #7
    //   2163: iload #7
    //   2165: aload #4
    //   2167: arraylength
    //   2168: iconst_4
    //   2169: imul
    //   2170: iconst_3
    //   2171: idiv
    //   2172: if_icmple -> 2189
    //   2175: aload #5
    //   2177: iload #7
    //   2179: bipush #61
    //   2181: bastore
    //   2182: iinc #7, -1
    //   2185: iload_2
    //   2186: ifeq -> 2163
    //   2189: new java/math/BigInteger
    //   2192: dup
    //   2193: aload #5
    //   2195: invokespecial <init> : ([B)V
    //   2198: invokevirtual abs : ()Ljava/math/BigInteger;
    //   2201: putstatic burp/Zzwl.Z_ : Ljava/lang/Object;
    //   2204: sipush #9307
    //   2207: sipush #-5100
    //   2210: invokestatic a : (II)Ljava/lang/String;
    //   2213: iconst_1
    //   2214: ldc burp/Zgqi
    //   2216: invokevirtual getClassLoader : ()Ljava/lang/ClassLoader;
    //   2219: invokestatic forName : (Ljava/lang/String;ZLjava/lang/ClassLoader;)Ljava/lang/Class;
    //   2222: invokevirtual getDeclaredFields : ()[Ljava/lang/reflect/Field;
    //   2225: astore #4
    //   2227: aload #4
    //   2229: arraylength
    //   2230: istore #5
    //   2232: iconst_0
    //   2233: istore #6
    //   2235: iload #6
    //   2237: iload #5
    //   2239: if_icmpge -> 2377
    //   2242: aload #4
    //   2244: iload #6
    //   2246: aaload
    //   2247: astore #7
    //   2249: aload #7
    //   2251: invokevirtual getModifiers : ()I
    //   2254: invokestatic isStatic : (I)Z
    //   2257: ifne -> 2267
    //   2260: goto -> 2370
    //   2263: invokestatic a : (Ljava/lang/Throwable;)Ljava/lang/Throwable;
    //   2266: athrow
    //   2267: aload #7
    //   2269: invokevirtual getType : ()Ljava/lang/Class;
    //   2272: astore #8
    //   2274: aload #8
    //   2276: ifnull -> 2357
    //   2279: aload #8
    //   2281: invokevirtual isPrimitive : ()Z
    //   2284: ifne -> 2357
    //   2287: goto -> 2294
    //   2290: invokestatic a : (Ljava/lang/Throwable;)Ljava/lang/Throwable;
    //   2293: athrow
    //   2294: aload #8
    //   2296: invokevirtual getPackage : ()Ljava/lang/Package;
    //   2299: ifnull -> 2357
    //   2302: goto -> 2309
    //   2305: invokestatic a : (Ljava/lang/Throwable;)Ljava/lang/Throwable;
    //   2308: athrow
    //   2309: aload #8
    //   2311: invokevirtual getPackage : ()Ljava/lang/Package;
    //   2314: invokevirtual getName : ()Ljava/lang/String;
    //   2317: ifnull -> 2357
    //   2320: goto -> 2327
    //   2323: invokestatic a : (Ljava/lang/Throwable;)Ljava/lang/Throwable;
    //   2326: athrow
    //   2327: aload #8
    //   2329: invokevirtual getPackage : ()Ljava/lang/Package;
    //   2332: invokevirtual getName : ()Ljava/lang/String;
    //   2335: sipush #9297
    //   2338: sipush #-6386
    //   2341: invokestatic a : (II)Ljava/lang/String;
    //   2344: invokevirtual startsWith : (Ljava/lang/String;)Z
    //   2347: ifne -> 2357
    //   2350: goto -> 2357
    //   2353: invokestatic a : (Ljava/lang/Throwable;)Ljava/lang/Throwable;
    //   2356: athrow
    //   2357: aload #7
    //   2359: iconst_1
    //   2360: invokevirtual setAccessible : (Z)V
    //   2363: aload #7
    //   2365: aconst_null
    //   2366: invokevirtual get : (Ljava/lang/Object;)Ljava/lang/Object;
    //   2369: pop
    //   2370: iinc #6, 1
    //   2373: iload_2
    //   2374: ifeq -> 2235
    //   2377: sipush #9298
    //   2380: sipush #30100
    //   2383: invokestatic a : (II)Ljava/lang/String;
    //   2386: invokestatic forName : (Ljava/lang/String;)Ljava/lang/Class;
    //   2389: invokevirtual getDeclaredMethods : ()[Ljava/lang/reflect/Method;
    //   2392: astore #4
    //   2394: aload #4
    //   2396: arraylength
    //   2397: istore #5
    //   2399: iconst_0
    //   2400: istore #6
    //   2402: iload #6
    //   2404: iload #5
    //   2406: if_icmpge -> 2518
    //   2409: aload #4
    //   2411: iload #6
    //   2413: aaload
    //   2414: astore #7
    //   2416: aload #7
    //   2418: invokevirtual getParameterTypes : ()[Ljava/lang/Class;
    //   2421: pop
    //   2422: aload #7
    //   2424: invokevirtual getModifiers : ()I
    //   2427: invokestatic isStatic : (I)Z
    //   2430: ifeq -> 2504
    //   2433: aload #7
    //   2435: invokevirtual getParameterTypes : ()[Ljava/lang/Class;
    //   2438: arraylength
    //   2439: iconst_2
    //   2440: if_icmpne -> 2504
    //   2443: goto -> 2450
    //   2446: invokestatic a : (Ljava/lang/Throwable;)Ljava/lang/Throwable;
    //   2449: athrow
    //   2450: aload #7
    //   2452: invokevirtual getReturnType : ()Ljava/lang/Class;
    //   2455: getstatic java/lang/Boolean.TYPE : Ljava/lang/Class;
    //   2458: if_acmpne -> 2504
    //   2461: goto -> 2468
    //   2464: invokestatic a : (Ljava/lang/Throwable;)Ljava/lang/Throwable;
    //   2467: athrow
    //   2468: aload #7
    //   2470: iconst_1
    //   2471: invokevirtual setAccessible : (Z)V
    //   2474: aload #7
    //   2476: aconst_null
    //   2477: iconst_2
    //   2478: anewarray java/lang/Object
    //   2481: dup
    //   2482: iconst_0
    //   2483: aload_0
    //   2484: aastore
    //   2485: dup
    //   2486: iconst_1
    //   2487: aload_1
    //   2488: aastore
    //   2489: invokevirtual invoke : (Ljava/lang/Object;[Ljava/lang/Object;)Ljava/lang/Object;
    //   2492: pop
    //   2493: iload_2
    //   2494: ifeq -> 2518
    //   2497: goto -> 2504
    //   2500: invokestatic a : (Ljava/lang/Throwable;)Ljava/lang/Throwable;
    //   2503: athrow
    //   2504: iinc #6, 1
    //   2507: iload_2
    //   2508: ifeq -> 2402
    //   2511: goto -> 2518
    //   2514: invokestatic a : (Ljava/lang/Throwable;)Ljava/lang/Throwable;
    //   2517: athrow
    //   2518: sipush #9296
    //   2521: sipush #-908
    //   2524: invokestatic a : (II)Ljava/lang/String;
    //   2527: iconst_1
    //   2528: ldc burp/Zljx
    //   2530: invokevirtual getClassLoader : ()Ljava/lang/ClassLoader;
    //   2533: invokestatic forName : (Ljava/lang/String;ZLjava/lang/ClassLoader;)Ljava/lang/Class;
    //   2536: invokevirtual getDeclaredFields : ()[Ljava/lang/reflect/Field;
    //   2539: astore #4
    //   2541: aload #4
    //   2543: arraylength
    //   2544: istore #5
    //   2546: iconst_0
    //   2547: istore #6
    //   2549: iload #6
    //   2551: iload #5
    //   2553: if_icmpge -> 2691
    //   2556: aload #4
    //   2558: iload #6
    //   2560: aaload
    //   2561: astore #7
    //   2563: aload #7
    //   2565: invokevirtual getModifiers : ()I
    //   2568: invokestatic isStatic : (I)Z
    //   2571: ifne -> 2581
    //   2574: goto -> 2684
    //   2577: invokestatic a : (Ljava/lang/Throwable;)Ljava/lang/Throwable;
    //   2580: athrow
    //   2581: aload #7
    //   2583: invokevirtual getType : ()Ljava/lang/Class;
    //   2586: astore #8
    //   2588: aload #8
    //   2590: ifnull -> 2671
    //   2593: aload #8
    //   2595: invokevirtual isPrimitive : ()Z
    //   2598: ifne -> 2671
    //   2601: goto -> 2608
    //   2604: invokestatic a : (Ljava/lang/Throwable;)Ljava/lang/Throwable;
    //   2607: athrow
    //   2608: aload #8
    //   2610: invokevirtual getPackage : ()Ljava/lang/Package;
    //   2613: ifnull -> 2671
    //   2616: goto -> 2623
    //   2619: invokestatic a : (Ljava/lang/Throwable;)Ljava/lang/Throwable;
    //   2622: athrow
    //   2623: aload #8
    //   2625: invokevirtual getPackage : ()Ljava/lang/Package;
    //   2628: invokevirtual getName : ()Ljava/lang/String;
    //   2631: ifnull -> 2671
    //   2634: goto -> 2641
    //   2637: invokestatic a : (Ljava/lang/Throwable;)Ljava/lang/Throwable;
    //   2640: athrow
    //   2641: aload #8
    //   2643: invokevirtual getPackage : ()Ljava/lang/Package;
    //   2646: invokevirtual getName : ()Ljava/lang/String;
    //   2649: sipush #9311
    //   2652: sipush #11842
    //   2655: invokestatic a : (II)Ljava/lang/String;
    //   2658: invokevirtual startsWith : (Ljava/lang/String;)Z
    //   2661: ifne -> 2671
    //   2664: goto -> 2671
    //   2667: invokestatic a : (Ljava/lang/Throwable;)Ljava/lang/Throwable;
    //   2670: athrow
    //   2671: aload #7
    //   2673: iconst_1
    //   2674: invokevirtual setAccessible : (Z)V
    //   2677: aload #7
    //   2679: aconst_null
    //   2680: invokevirtual get : (Ljava/lang/Object;)Ljava/lang/Object;
    //   2683: pop
    //   2684: iinc #6, 1
    //   2687: iload_2
    //   2688: ifeq -> 2549
    //   2691: sipush #9304
    //   2694: sipush #5549
    //   2697: invokestatic a : (II)Ljava/lang/String;
    //   2700: invokestatic forName : (Ljava/lang/String;)Ljava/lang/Class;
    //   2703: invokevirtual getDeclaredMethods : ()[Ljava/lang/reflect/Method;
    //   2706: astore #4
    //   2708: aload #4
    //   2710: arraylength
    //   2711: istore #5
    //   2713: iconst_0
    //   2714: istore #6
    //   2716: iload #6
    //   2718: iload #5
    //   2720: if_icmpge -> 2853
    //   2723: aload #4
    //   2725: iload #6
    //   2727: aaload
    //   2728: astore #7
    //   2730: aload #7
    //   2732: invokevirtual getParameterTypes : ()[Ljava/lang/Class;
    //   2735: pop
    //   2736: aload #7
    //   2738: invokevirtual getModifiers : ()I
    //   2741: invokestatic isStatic : (I)Z
    //   2744: ifeq -> 2839
    //   2747: aload #7
    //   2749: invokevirtual getParameterTypes : ()[Ljava/lang/Class;
    //   2752: arraylength
    //   2753: iconst_2
    //   2754: if_icmpne -> 2839
    //   2757: goto -> 2764
    //   2760: invokestatic a : (Ljava/lang/Throwable;)Ljava/lang/Throwable;
    //   2763: athrow
    //   2764: aload #7
    //   2766: invokevirtual getReturnType : ()Ljava/lang/Class;
    //   2769: getstatic java/lang/Void.TYPE : Ljava/lang/Class;
    //   2772: invokevirtual equals : (Ljava/lang/Object;)Z
    //   2775: ifeq -> 2839
    //   2778: goto -> 2785
    //   2781: invokestatic a : (Ljava/lang/Throwable;)Ljava/lang/Throwable;
    //   2784: athrow
    //   2785: aload #7
    //   2787: iconst_1
    //   2788: invokevirtual setAccessible : (Z)V
    //   2791: aload #7
    //   2793: aconst_null
    //   2794: iconst_2
    //   2795: anewarray java/lang/Object
    //   2798: dup
    //   2799: iconst_0
    //   2800: aload_0
    //   2801: aastore
    //   2802: dup
    //   2803: iconst_1
    //   2804: aload_1
    //   2805: ifnonnull -> 2823
    //   2808: goto -> 2815
    //   2811: invokestatic a : (Ljava/lang/Throwable;)Ljava/lang/Throwable;
    //   2814: athrow
    //   2815: aload_1
    //   2816: goto -> 2830
    //   2819: invokestatic a : (Ljava/lang/Throwable;)Ljava/lang/Throwable;
    //   2822: athrow
    //   2823: aload_1
    //   2824: checkcast [B
    //   2827: invokevirtual clone : ()Ljava/lang/Object;
    //   2830: aastore
    //   2831: invokevirtual invoke : (Ljava/lang/Object;[Ljava/lang/Object;)Ljava/lang/Object;
    //   2834: pop
    //   2835: iload_2
    //   2836: ifeq -> 2853
    //   2839: iinc #6, 1
    //   2842: iload_2
    //   2843: ifeq -> 2716
    //   2846: goto -> 2853
    //   2849: invokestatic a : (Ljava/lang/Throwable;)Ljava/lang/Throwable;
    //   2852: athrow
    //   2853: iconst_0
    //   2854: istore #4
    //   2856: sipush #9310
    //   2859: sipush #-5615
    //   2862: invokestatic a : (II)Ljava/lang/String;
    //   2865: iconst_1
    //   2866: ldc burp/Zxk9
    //   2868: invokevirtual getClassLoader : ()Ljava/lang/ClassLoader;
    //   2871: invokestatic forName : (Ljava/lang/String;ZLjava/lang/ClassLoader;)Ljava/lang/Class;
    //   2874: invokevirtual getDeclaredFields : ()[Ljava/lang/reflect/Field;
    //   2877: astore #5
    //   2879: aload #5
    //   2881: arraylength
    //   2882: istore #6
    //   2884: iconst_0
    //   2885: istore #7
    //   2887: iload #7
    //   2889: iload #6
    //   2891: if_icmpge -> 3029
    //   2894: aload #5
    //   2896: iload #7
    //   2898: aaload
    //   2899: astore #8
    //   2901: aload #8
    //   2903: invokevirtual getModifiers : ()I
    //   2906: invokestatic isStatic : (I)Z
    //   2909: ifne -> 2919
    //   2912: goto -> 3022
    //   2915: invokestatic a : (Ljava/lang/Throwable;)Ljava/lang/Throwable;
    //   2918: athrow
    //   2919: aload #8
    //   2921: invokevirtual getType : ()Ljava/lang/Class;
    //   2924: astore #9
    //   2926: aload #9
    //   2928: ifnull -> 3009
    //   2931: aload #9
    //   2933: invokevirtual isPrimitive : ()Z
    //   2936: ifne -> 3009
    //   2939: goto -> 2946
    //   2942: invokestatic a : (Ljava/lang/Throwable;)Ljava/lang/Throwable;
    //   2945: athrow
    //   2946: aload #9
    //   2948: invokevirtual getPackage : ()Ljava/lang/Package;
    //   2951: ifnull -> 3009
    //   2954: goto -> 2961
    //   2957: invokestatic a : (Ljava/lang/Throwable;)Ljava/lang/Throwable;
    //   2960: athrow
    //   2961: aload #9
    //   2963: invokevirtual getPackage : ()Ljava/lang/Package;
    //   2966: invokevirtual getName : ()Ljava/lang/String;
    //   2969: ifnull -> 3009
    //   2972: goto -> 2979
    //   2975: invokestatic a : (Ljava/lang/Throwable;)Ljava/lang/Throwable;
    //   2978: athrow
    //   2979: aload #9
    //   2981: invokevirtual getPackage : ()Ljava/lang/Package;
    //   2984: invokevirtual getName : ()Ljava/lang/String;
    //   2987: sipush #9311
    //   2990: sipush #11842
    //   2993: invokestatic a : (II)Ljava/lang/String;
    //   2996: invokevirtual startsWith : (Ljava/lang/String;)Z
    //   2999: ifne -> 3009
    //   3002: goto -> 3009
    //   3005: invokestatic a : (Ljava/lang/Throwable;)Ljava/lang/Throwable;
    //   3008: athrow
    //   3009: aload #8
    //   3011: iconst_1
    //   3012: invokevirtual setAccessible : (Z)V
    //   3015: aload #8
    //   3017: aconst_null
    //   3018: invokevirtual get : (Ljava/lang/Object;)Ljava/lang/Object;
    //   3021: pop
    //   3022: iinc #7, 1
    //   3025: iload_2
    //   3026: ifeq -> 2887
    //   3029: sipush #9309
    //   3032: sipush #32079
    //   3035: invokestatic a : (II)Ljava/lang/String;
    //   3038: invokestatic forName : (Ljava/lang/String;)Ljava/lang/Class;
    //   3041: invokevirtual getDeclaredMethods : ()[Ljava/lang/reflect/Method;
    //   3044: astore #5
    //   3046: aload #5
    //   3048: arraylength
    //   3049: istore #6
    //   3051: iconst_0
    //   3052: istore #7
    //   3054: iload #7
    //   3056: iload #6
    //   3058: if_icmpge -> 3195
    //   3061: aload #5
    //   3063: iload #7
    //   3065: aaload
    //   3066: astore #8
    //   3068: aload #8
    //   3070: invokevirtual getParameterTypes : ()[Ljava/lang/Class;
    //   3073: pop
    //   3074: aload #8
    //   3076: invokevirtual getModifiers : ()I
    //   3079: invokestatic isStatic : (I)Z
    //   3082: ifeq -> 3181
    //   3085: aload #8
    //   3087: invokevirtual getParameterTypes : ()[Ljava/lang/Class;
    //   3090: arraylength
    //   3091: iconst_2
    //   3092: if_icmpne -> 3181
    //   3095: goto -> 3102
    //   3098: invokestatic a : (Ljava/lang/Throwable;)Ljava/lang/Throwable;
    //   3101: athrow
    //   3102: aload #8
    //   3104: invokevirtual getReturnType : ()Ljava/lang/Class;
    //   3107: getstatic java/lang/Boolean.TYPE : Ljava/lang/Class;
    //   3110: if_acmpne -> 3181
    //   3113: goto -> 3120
    //   3116: invokestatic a : (Ljava/lang/Throwable;)Ljava/lang/Throwable;
    //   3119: athrow
    //   3120: aload #8
    //   3122: iconst_1
    //   3123: invokevirtual setAccessible : (Z)V
    //   3126: aload #8
    //   3128: aconst_null
    //   3129: iconst_2
    //   3130: anewarray java/lang/Object
    //   3133: dup
    //   3134: iconst_0
    //   3135: aload_0
    //   3136: aastore
    //   3137: dup
    //   3138: iconst_1
    //   3139: aload_1
    //   3140: ifnonnull -> 3158
    //   3143: goto -> 3150
    //   3146: invokestatic a : (Ljava/lang/Throwable;)Ljava/lang/Throwable;
    //   3149: athrow
    //   3150: aload_1
    //   3151: goto -> 3165
    //   3154: invokestatic a : (Ljava/lang/Throwable;)Ljava/lang/Throwable;
    //   3157: athrow
    //   3158: aload_1
    //   3159: checkcast [B
    //   3162: invokevirtual clone : ()Ljava/lang/Object;
    //   3165: aastore
    //   3166: invokevirtual invoke : (Ljava/lang/Object;[Ljava/lang/Object;)Ljava/lang/Object;
    //   3169: checkcast java/lang/Boolean
    //   3172: invokevirtual booleanValue : ()Z
    //   3175: istore #4
    //   3177: iload_2
    //   3178: ifeq -> 3195
    //   3181: iinc #7, 1
    //   3184: iload_2
    //   3185: ifeq -> 3054
    //   3188: goto -> 3195
    //   3191: invokestatic a : (Ljava/lang/Throwable;)Ljava/lang/Throwable;
    //   3194: athrow
    //   3195: iload #4
    //   3197: ireturn
    //   3198: astore_3
    //   3199: new java/lang/Exception
    //   3202: dup
    //   3203: aload_3
    //   3204: invokevirtual getMessage : ()Ljava/lang/String;
    //   3207: invokespecial <init> : (Ljava/lang/String;)V
    //   3210: athrow
    // Exception table:
    //   from	to	target	type
    //   4	3197	3198	java/lang/Throwable
    //   22	198	201	java/lang/Throwable
    //   168	235	238	java/lang/Throwable
    //   205	272	275	java/lang/Throwable
    //   242	309	312	java/lang/Throwable
    //   279	346	349	java/lang/Throwable
    //   316	383	386	java/lang/Throwable
    //   353	420	423	java/lang/Throwable
    //   390	457	460	java/lang/Throwable
    //   427	494	497	java/lang/Throwable
    //   464	531	534	java/lang/Throwable
    //   501	568	571	java/lang/Throwable
    //   538	605	608	java/lang/Throwable
    //   575	642	645	java/lang/Throwable
    //   612	679	682	java/lang/Throwable
    //   649	716	719	java/lang/Throwable
    //   686	753	756	java/lang/Throwable
    //   723	790	793	java/lang/Throwable
    //   760	827	830	java/lang/Throwable
    //   797	864	867	java/lang/Throwable
    //   834	901	904	java/lang/Throwable
    //   871	938	941	java/lang/Throwable
    //   908	975	978	java/lang/Throwable
    //   945	1012	1015	java/lang/Throwable
    //   982	1049	1052	java/lang/Throwable
    //   1019	1086	1089	java/lang/Throwable
    //   1056	1123	1126	java/lang/Throwable
    //   1093	1160	1163	java/lang/Throwable
    //   1130	1197	1200	java/lang/Throwable
    //   1167	1234	1237	java/lang/Throwable
    //   1204	1271	1274	java/lang/Throwable
    //   1241	1308	1311	java/lang/Throwable
    //   1278	1341	1344	java/lang/Throwable
    //   1554	1582	1585	java/lang/Throwable
    //   1564	1599	1602	java/lang/Throwable
    //   1589	1627	1630	java/lang/Throwable
    //   1606	1644	1647	java/lang/Throwable
    //   1634	1672	1675	java/lang/Throwable
    //   1651	1689	1692	java/lang/Throwable
    //   1679	1707	1710	java/lang/Throwable
    //   1696	1721	1724	java/lang/Throwable
    //   1975	2003	2006	java/lang/Throwable
    //   1985	2020	2023	java/lang/Throwable
    //   2010	2048	2051	java/lang/Throwable
    //   2027	2065	2068	java/lang/Throwable
    //   2055	2093	2096	java/lang/Throwable
    //   2072	2110	2113	java/lang/Throwable
    //   2100	2128	2131	java/lang/Throwable
    //   2117	2142	2145	java/lang/Throwable
    //   2249	2263	2263	java/lang/Throwable
    //   2274	2287	2290	java/lang/Throwable
    //   2279	2302	2305	java/lang/Throwable
    //   2294	2320	2323	java/lang/Throwable
    //   2309	2350	2353	java/lang/Throwable
    //   2416	2443	2446	java/lang/Throwable
    //   2433	2461	2464	java/lang/Throwable
    //   2450	2497	2500	java/lang/Throwable
    //   2468	2511	2514	java/lang/Throwable
    //   2563	2577	2577	java/lang/Throwable
    //   2588	2601	2604	java/lang/Throwable
    //   2593	2616	2619	java/lang/Throwable
    //   2608	2634	2637	java/lang/Throwable
    //   2623	2664	2667	java/lang/Throwable
    //   2730	2757	2760	java/lang/Throwable
    //   2747	2778	2781	java/lang/Throwable
    //   2764	2808	2811	java/lang/Throwable
    //   2785	2819	2819	java/lang/Throwable
    //   2830	2846	2849	java/lang/Throwable
    //   2901	2915	2915	java/lang/Throwable
    //   2926	2939	2942	java/lang/Throwable
    //   2931	2954	2957	java/lang/Throwable
    //   2946	2972	2975	java/lang/Throwable
    //   2961	3002	3005	java/lang/Throwable
    //   3068	3095	3098	java/lang/Throwable
    //   3085	3113	3116	java/lang/Throwable
    //   3102	3143	3146	java/lang/Throwable
    //   3120	3154	3154	java/lang/Throwable
    //   3177	3188	3191	java/lang/Throwable
  }
  
  static {
    // Byte code:
    //   0: bipush #13
    //   2: anewarray java/lang/String
    //   5: astore #5
    //   7: iconst_0
    //   8: istore_3
    //   9: ldc '0^VkUqMoN!!O!Lq:Z 3WL\\r>GMFu1,%' RG?s</2;?q[^f\\t2X4@ /x;9-0K(eQLC\\n\\t$WI2\\t;T?+x!8\\t}2Y>od\\tn'
    //   11: dup
    //   12: astore_2
    //   13: invokevirtual length : ()I
    //   16: istore #4
    //   18: bipush #9
    //   20: istore_1
    //   21: iconst_m1
    //   22: istore_0
    //   23: bipush #68
    //   25: iinc #0, 1
    //   28: aload_2
    //   29: iload_0
    //   30: dup
    //   31: iload_1
    //   32: iadd
    //   33: invokevirtual substring : (II)Ljava/lang/String;
    //   36: iconst_m1
    //   37: goto -> 143
    //   40: aload #5
    //   42: swap
    //   43: iload_3
    //   44: iinc #3, 1
    //   47: swap
    //   48: aastore
    //   49: iload_0
    //   50: iload_1
    //   51: iadd
    //   52: dup
    //   53: istore_0
    //   54: iload #4
    //   56: if_icmpge -> 68
    //   59: aload_2
    //   60: iload_0
    //   61: invokevirtual charAt : (I)C
    //   64: istore_1
    //   65: goto -> 23
    //   68: ldc '`6hs4_\\t/k'
    //   70: dup
    //   71: astore_2
    //   72: invokevirtual length : ()I
    //   75: istore #4
    //   77: bipush #9
    //   79: istore_1
    //   80: iconst_m1
    //   81: istore_0
    //   82: bipush #54
    //   84: iinc #0, 1
    //   87: aload_2
    //   88: iload_0
    //   89: dup
    //   90: iload_1
    //   91: iadd
    //   92: invokevirtual substring : (II)Ljava/lang/String;
    //   95: iconst_0
    //   96: goto -> 143
    //   99: aload #5
    //   101: swap
    //   102: iload_3
    //   103: iinc #3, 1
    //   106: swap
    //   107: aastore
    //   108: iload_0
    //   109: iload_1
    //   110: iadd
    //   111: dup
    //   112: istore_0
    //   113: iload #4
    //   115: if_icmpge -> 127
    //   118: aload_2
    //   119: iload_0
    //   120: invokevirtual charAt : (I)C
    //   123: istore_1
    //   124: goto -> 82
    //   127: aload #5
    //   129: putstatic burp/Zxoa.a : [Ljava/lang/String;
    //   132: bipush #13
    //   134: anewarray java/lang/String
    //   137: putstatic burp/Zxoa.b : [Ljava/lang/String;
    //   140: goto -> 300
    //   143: dup_x2
    //   144: pop
    //   145: invokevirtual toCharArray : ()[C
    //   148: dup_x1
    //   149: arraylength
    //   150: dup_x2
    //   151: pop
    //   152: iconst_0
    //   153: istore #6
    //   155: dup2_x1
    //   156: pop2
    //   157: dup_x2
    //   158: iconst_1
    //   159: if_icmpgt -> 260
    //   162: dup2
    //   163: swap
    //   164: iload #6
    //   166: dup2_x1
    //   167: caload
    //   168: swap
    //   169: iload #6
    //   171: bipush #7
    //   173: irem
    //   174: tableswitch default -> 242, 0 -> 212, 1 -> 217, 2 -> 222, 3 -> 227, 4 -> 232, 5 -> 237
    //   212: bipush #95
    //   214: goto -> 244
    //   217: bipush #126
    //   219: goto -> 244
    //   222: bipush #35
    //   224: goto -> 244
    //   227: bipush #33
    //   229: goto -> 244
    //   232: bipush #118
    //   234: goto -> 244
    //   237: bipush #109
    //   239: goto -> 244
    //   242: bipush #57
    //   244: ixor
    //   245: ixor
    //   246: i2c
    //   247: castore
    //   248: iinc #6, 1
    //   251: dup
    //   252: ifne -> 260
    //   255: dup2
    //   256: dup_x1
    //   257: goto -> 166
    //   260: dup2_x1
    //   261: pop2
    //   262: dup_x2
    //   263: iload #6
    //   265: if_icmpgt -> 162
    //   268: pop
    //   269: new java/lang/String
    //   272: dup_x1
    //   273: swap
    //   274: invokespecial <init> : ([C)V
    //   277: invokevirtual intern : ()Ljava/lang/String;
    //   280: swap
    //   281: pop
    //   282: swap
    //   283: tableswitch default -> 40, 0 -> 99
    //   300: new java/math/BigInteger
    //   303: dup
    //   304: iconst_1
    //   305: bipush #32
    //   307: newarray byte
    //   309: dup
    //   310: iconst_0
    //   311: bipush #94
    //   313: bastore
    //   314: dup
    //   315: iconst_1
    //   316: bipush #38
    //   318: bastore
    //   319: dup
    //   320: iconst_2
    //   321: bipush #-91
    //   323: bastore
    //   324: dup
    //   325: iconst_3
    //   326: bipush #-63
    //   328: bastore
    //   329: dup
    //   330: iconst_4
    //   331: bipush #-24
    //   333: bastore
    //   334: dup
    //   335: iconst_5
    //   336: bipush #124
    //   338: bastore
    //   339: dup
    //   340: bipush #6
    //   342: bipush #10
    //   344: bastore
    //   345: dup
    //   346: bipush #7
    //   348: bipush #42
    //   350: bastore
    //   351: dup
    //   352: bipush #8
    //   354: bipush #-70
    //   356: bastore
    //   357: dup
    //   358: bipush #9
    //   360: bipush #121
    //   362: bastore
    //   363: dup
    //   364: bipush #10
    //   366: bipush #22
    //   368: bastore
    //   369: dup
    //   370: bipush #11
    //   372: bipush #-48
    //   374: bastore
    //   375: dup
    //   376: bipush #12
    //   378: bipush #104
    //   380: bastore
    //   381: dup
    //   382: bipush #13
    //   384: bipush #33
    //   386: bastore
    //   387: dup
    //   388: bipush #14
    //   390: bipush #-74
    //   392: bastore
    //   393: dup
    //   394: bipush #15
    //   396: bipush #-25
    //   398: bastore
    //   399: dup
    //   400: bipush #16
    //   402: bipush #121
    //   404: bastore
    //   405: dup
    //   406: bipush #17
    //   408: bipush #9
    //   410: bastore
    //   411: dup
    //   412: bipush #18
    //   414: bipush #105
    //   416: bastore
    //   417: dup
    //   418: bipush #19
    //   420: bipush #87
    //   422: bastore
    //   423: dup
    //   424: bipush #20
    //   426: bipush #-5
    //   428: bastore
    //   429: dup
    //   430: bipush #21
    //   432: bipush #97
    //   434: bastore
    //   435: dup
    //   436: bipush #22
    //   438: bipush #-21
    //   440: bastore
    //   441: dup
    //   442: bipush #23
    //   444: bipush #90
    //   446: bastore
    //   447: dup
    //   448: bipush #24
    //   450: bipush #26
    //   452: bastore
    //   453: dup
    //   454: bipush #25
    //   456: bipush #-7
    //   458: bastore
    //   459: dup
    //   460: bipush #26
    //   462: bipush #38
    //   464: bastore
    //   465: dup
    //   466: bipush #27
    //   468: bipush #-54
    //   470: bastore
    //   471: dup
    //   472: bipush #28
    //   474: bipush #7
    //   476: bastore
    //   477: dup
    //   478: bipush #29
    //   480: bipush #-28
    //   482: bastore
    //   483: dup
    //   484: bipush #30
    //   486: bipush #-90
    //   488: bastore
    //   489: dup
    //   490: bipush #31
    //   492: bipush #23
    //   494: bastore
    //   495: invokespecial <init> : (I[B)V
    //   498: putstatic burp/Zxoa.Zr : Ljava/lang/Object;
    //   501: sipush #9308
    //   504: sipush #11487
    //   507: invokestatic a : (II)Ljava/lang/String;
    //   510: putstatic burp/Zxoa.Z_ : Ljava/lang/String;
    //   513: return
  }
  
  private static Throwable a(Throwable paramThrowable) {
    return paramThrowable;
  }
  
  private static String a(int paramInt1, int paramInt2) {
    int i = (paramInt1 ^ 0x2458) & 0xFFFF;
    if (b[i] == null) {
      char[] arrayOfChar = a[i].toCharArray();
      switch (arrayOfChar[0] & 0xFF) {
        case 0:
        
        case 1:
        
        case 2:
        
        case 3:
        
        case 4:
        
        case 5:
        
        case 6:
        
        case 7:
        
        case 8:
        
        case 9:
        
        case 10:
        
        case 11:
        
        case 12:
        
        case 13:
        
        case 14:
        
        case 15:
        
        case 16:
        
        case 17:
        
        case 18:
        
        case 19:
        
        case 20:
        
        case 21:
        
        case 22:
        
        case 23:
        
        case 24:
        
        case 25:
        
        case 26:
        
        case 27:
        
        case 28:
        
        case 29:
        
        case 30:
        
        case 31:
        
        case 32:
        
        case 33:
        
        case 34:
        
        case 35:
        
        case 36:
        
        case 37:
        
        case 38:
        
        case 39:
        
        case 40:
        
        case 41:
        
        case 42:
        
        case 43:
        
        case 44:
        
        case 45:
        
        case 46:
        
        case 47:
        
        case 48:
        
        case 49:
        
        case 50:
        
        case 51:
        
        case 52:
        
        case 53:
        
        case 54:
        
        case 55:
        
        case 56:
        
        case 57:
        
        case 58:
        
        case 59:
        
        case 60:
        
        case 61:
        
        case 62:
        
        case 63:
        
        case 64:
        
        case 65:
        
        case 66:
        
        case 67:
        
        case 68:
        
        case 69:
        
        case 70:
        
        case 71:
        
        case 72:
        
        case 73:
        
        case 74:
        
        case 75:
        
        case 76:
        
        case 77:
        
        case 78:
        
        case 79:
        
        case 80:
        
        case 81:
        
        case 82:
        
        case 83:
        
        case 84:
        
        case 85:
        
        case 86:
        
        case 87:
        
        case 88:
        
        case 89:
        
        case 90:
        
        case 91:
        
        case 92:
        
        case 93:
        
        case 94:
        
        case 95:
        
        case 96:
        
        case 97:
        
        case 98:
        
        case 99:
        
        case 100:
        
        case 101:
        
        case 102:
        
        case 103:
        
        case 104:
        
        case 105:
        
        case 106:
        
        case 107:
        
        case 108:
        
        case 109:
        
        case 110:
        
        case 111:
        
        case 112:
        
        case 113:
        
        case 114:
        
        case 115:
        
        case 116:
        
        case 117:
        
        case 118:
        
        case 119:
        
        case 120:
        
        case 121:
        
        case 122:
        
        case 123:
        
        case 124:
        
        case 125:
        
        case 126:
        
        case 127:
        
        case 128:
        
        case 129:
        
        case 130:
        
        case 131:
        
        case 132:
        
        case 133:
        
        case 134:
        
        case 135:
        
        case 136:
        
        case 137:
        
        case 138:
        
        case 139:
        
        case 140:
        
        case 141:
        
        case 142:
        
        case 143:
        
        case 144:
        
        case 145:
        
        case 146:
        
        case 147:
        
        case 148:
        
        case 149:
        
        case 150:
        
        case 151:
        
        case 152:
        
        case 153:
        
        case 154:
        
        case 155:
        
        case 156:
        
        case 157:
        
        case 158:
        
        case 159:
        
        case 160:
        
        case 161:
        
        case 162:
        
        case 163:
        
        case 164:
        
        case 165:
        
        case 166:
        
        case 167:
        
        case 168:
        
        case 169:
        
        case 170:
        
        case 171:
        
        case 172:
        
        case 173:
        
        case 174:
        
        case 175:
        
        case 176:
        
        case 177:
        
        case 178:
        
        case 179:
        
        case 180:
        
        case 181:
        
        case 182:
        
        case 183:
        
        case 184:
        
        case 185:
        
        case 186:
        
        case 187:
        
        case 188:
        
        case 189:
        
        case 190:
        
        case 191:
        
        case 192:
        
        case 193:
        
        case 194:
        
        case 195:
        
        case 196:
        
        case 197:
        
        case 198:
        
        case 199:
        
        case 200:
        
        case 201:
        
        case 202:
        
        case 203:
        
        case 204:
        
        case 205:
        
        case 206:
        
        case 207:
        
        case 208:
        
        case 209:
        
        case 210:
        
        case 211:
        
        case 212:
        
        case 213:
        
        case 214:
        
        case 215:
        
        case 216:
        
        case 217:
        
        case 218:
        
        case 219:
        
        case 220:
        
        case 221:
        
        case 222:
        
        case 223:
        
        case 224:
        
        case 225:
        
        case 226:
        
        case 227:
        
        case 228:
        
        case 229:
        
        case 230:
        
        case 231:
        
        case 232:
        
        case 233:
        
        case 234:
        
        case 235:
        
        case 236:
        
        case 237:
        
        case 238:
        
        case 239:
        
        case 240:
        
        case 241:
        
        case 242:
        
        case 243:
        
        case 244:
        
        case 245:
        
        case 246:
        
        case 247:
        
        case 248:
        
        case 249:
        
        case 250:
        
        case 251:
        
        case 252:
        
        case 253:
        
        case 254:
        
        default:
          break;
      } 
      byte b1 = 50;
      int j = (paramInt2 & 0xFF) - b1;
      if (j < 0)
        j += 256; 
      int k = ((paramInt2 & 0xFFFF) >>> 8) - b1;
      if (k < 0)
        k += 256; 
      for (byte b2 = 0; b2 < arrayOfChar.length; b2++) {
        int m = b2 % 2;
        if (m == 0) {
          arrayOfChar[b2] = (char)(arrayOfChar[b2] ^ j);
          j = ((j >>> 3 | j << 5) ^ arrayOfChar[b2]) & 0xFF;
        } else {
          arrayOfChar[b2] = (char)(arrayOfChar[b2] ^ k);
          k = ((k >>> 3 | k << 5) ^ arrayOfChar[b2]) & 0xFF;
        } 
      } 
      b[i] = (new String(arrayOfChar)).intern();
    } 
    return b[i];
  }
}


/* Location:              C:\Program Files\BurpSuitePro\burpsuite_pro.jar!\burp\Zxoa.class
 * Java compiler version: 21 (65.0)
 * JD-Core Version:       1.1.3
 */