package burp;

import java.math.BigInteger;

class Zxof extends ClassLoader {
  static Object Zi;
  
  static String Zs;
  
  private static final String[] a;
  
  private static final String[] b;
  
  static void ZY(Object paramObject) {
    Zegk.Ze = a(26612, -16429);
    Zegk.ZR = new BigInteger(a(26608, 24780));
    boolean bool = Zt2e.ZN();
    try {
      try {
        if (Zgr4.Zi.charAt(Math.abs(((BigInteger)Zegk.ZR).intValue() % 32)) > Zmsl.ZP.charAt(Math.abs(((BigInteger)Zx_b.ZX).intValue() % 32))) {
          try {
            Zrw7.ZT(Class.forName(a(26615, 21847)));
            if (!bool)
              Zs_3.ZI(Class.forName(a(26609, -729))); 
          } catch (Throwable throwable) {
            throw a(null);
          } 
          return;
        } 
      } catch (Throwable throwable) {
        throw a(null);
      } 
      Zs_3.ZI(Class.forName(a(26609, -729)));
    } catch (Throwable throwable) {}
  }
  
  static void Zj(Object[] paramArrayOfObject, Object paramObject) throws Throwable {}
  
  static boolean ZI(Object[] paramArrayOfObject, Object paramObject) throws Throwable {
    // Byte code:
    //   0: invokestatic ZK : ()Z
    //   3: istore_2
    //   4: ldc2_w 8682522807148012
    //   7: invokestatic currentTimeMillis : ()J
    //   10: lxor
    //   11: lstore #4
    //   13: lload #4
    //   15: ldc2_w 25214903917
    //   18: lmul
    //   19: ldc2_w 11
    //   22: ladd
    //   23: ldc2_w 281474976710655
    //   26: land
    //   27: lstore #4
    //   29: lload #4
    //   31: bipush #32
    //   33: lshl
    //   34: lstore #6
    //   36: lload #4
    //   38: ldc2_w 25214903917
    //   41: lmul
    //   42: ldc2_w 11
    //   45: ladd
    //   46: ldc2_w 281474976710655
    //   49: land
    //   50: lstore #4
    //   52: lload #6
    //   54: lload #4
    //   56: ladd
    //   57: lstore #6
    //   59: bipush #16
    //   61: newarray byte
    //   63: dup
    //   64: iconst_0
    //   65: bipush #48
    //   67: bastore
    //   68: dup
    //   69: iconst_1
    //   70: bipush #49
    //   72: bastore
    //   73: dup
    //   74: iconst_2
    //   75: bipush #50
    //   77: bastore
    //   78: dup
    //   79: iconst_3
    //   80: bipush #51
    //   82: bastore
    //   83: dup
    //   84: iconst_4
    //   85: bipush #52
    //   87: bastore
    //   88: dup
    //   89: iconst_5
    //   90: bipush #53
    //   92: bastore
    //   93: dup
    //   94: bipush #6
    //   96: bipush #54
    //   98: bastore
    //   99: dup
    //   100: bipush #7
    //   102: bipush #55
    //   104: bastore
    //   105: dup
    //   106: bipush #8
    //   108: bipush #56
    //   110: bastore
    //   111: dup
    //   112: bipush #9
    //   114: bipush #57
    //   116: bastore
    //   117: dup
    //   118: bipush #10
    //   120: bipush #97
    //   122: bastore
    //   123: dup
    //   124: bipush #11
    //   126: bipush #98
    //   128: bastore
    //   129: dup
    //   130: bipush #12
    //   132: bipush #99
    //   134: bastore
    //   135: dup
    //   136: bipush #13
    //   138: bipush #100
    //   140: bastore
    //   141: dup
    //   142: bipush #14
    //   144: bipush #101
    //   146: bastore
    //   147: dup
    //   148: bipush #15
    //   150: bipush #102
    //   152: bastore
    //   153: astore #8
    //   155: bipush #64
    //   157: newarray byte
    //   159: astore #9
    //   161: bipush #64
    //   163: istore #10
    //   165: bipush #16
    //   167: istore #11
    //   169: iload #11
    //   171: iconst_1
    //   172: isub
    //   173: i2l
    //   174: lstore #12
    //   176: aload #9
    //   178: iinc #10, -1
    //   181: iload #10
    //   183: aload #8
    //   185: lload #6
    //   187: lload #12
    //   189: land
    //   190: l2i
    //   191: baload
    //   192: bastore
    //   193: lload #6
    //   195: iconst_4
    //   196: lushr
    //   197: lstore #6
    //   199: lload #6
    //   201: lconst_0
    //   202: lcmp
    //   203: ifne -> 176
    //   206: bipush #64
    //   208: iload #10
    //   210: isub
    //   211: newarray byte
    //   213: astore_3
    //   214: iconst_0
    //   215: istore #14
    //   217: iload #14
    //   219: aload_3
    //   220: arraylength
    //   221: if_icmpge -> 243
    //   224: aload_3
    //   225: iload #14
    //   227: aload #9
    //   229: iload #10
    //   231: iload #14
    //   233: iadd
    //   234: baload
    //   235: bastore
    //   236: iinc #14, 1
    //   239: iload_2
    //   240: ifeq -> 217
    //   243: aload_3
    //   244: arraylength
    //   245: bipush #10
    //   247: if_icmplt -> 13
    //   250: getstatic burp/Zmcq.Zh : Ljava/lang/Object;
    //   253: checkcast java/math/BigInteger
    //   256: getstatic burp/Zeuz.Zp : Ljava/lang/Object;
    //   259: checkcast java/math/BigInteger
    //   262: invokevirtual add : (Ljava/math/BigInteger;)Ljava/math/BigInteger;
    //   265: putstatic burp/Zmpv.ZI : Ljava/lang/Object;
    //   268: getstatic burp/Zsk4.Ze : Ljava/lang/Object;
    //   271: checkcast java/math/BigInteger
    //   274: invokevirtual toByteArray : ()[B
    //   277: astore_3
    //   278: bipush #32
    //   280: newarray int
    //   282: dup
    //   283: iconst_0
    //   284: ldc 943331329
    //   286: iastore
    //   287: dup
    //   288: iconst_1
    //   289: ldc 170788368
    //   291: iastore
    //   292: dup
    //   293: iconst_2
    //   294: ldc 1008414755
    //   296: iastore
    //   297: dup
    //   298: iconst_3
    //   299: ldc 187049985
    //   301: iastore
    //   302: dup
    //   303: iconst_4
    //   304: ldc 1010368540
    //   306: iastore
    //   307: dup
    //   308: iconst_5
    //   309: ldc 220604441
    //   311: iastore
    //   312: dup
    //   313: bipush #6
    //   315: ldc 940377620
    //   317: iastore
    //   318: dup
    //   319: bipush #7
    //   321: ldc 255209728
    //   323: iastore
    //   324: dup
    //   325: bipush #8
    //   327: ldc 689771012
    //   329: iastore
    //   330: dup
    //   331: bipush #9
    //   333: ldc 221709344
    //   335: iastore
    //   336: dup
    //   337: bipush #10
    //   339: ldc 957157408
    //   341: iastore
    //   342: dup
    //   343: bipush #11
    //   345: ldc 892536332
    //   347: iastore
    //   348: dup
    //   349: bipush #12
    //   351: ldc 722417666
    //   353: iastore
    //   354: dup
    //   355: bipush #13
    //   357: ldc 1026621720
    //   359: iastore
    //   360: dup
    //   361: bipush #14
    //   363: ldc 655302664
    //   365: iastore
    //   366: dup
    //   367: bipush #15
    //   369: ldc 890966315
    //   371: iastore
    //   372: dup
    //   373: bipush #16
    //   375: ldc 187632156
    //   377: iastore
    //   378: dup
    //   379: bipush #17
    //   381: ldc 874189824
    //   383: iastore
    //   384: dup
    //   385: bipush #18
    //   387: ldc 254150144
    //   389: iastore
    //   390: dup
    //   391: bipush #19
    //   393: ldc 924386310
    //   395: iastore
    //   396: dup
    //   397: bipush #20
    //   399: ldc 121057538
    //   401: iastore
    //   402: dup
    //   403: bipush #21
    //   405: ldc 840500228
    //   407: iastore
    //   408: dup
    //   409: bipush #22
    //   411: ldc 389160971
    //   413: iastore
    //   414: dup
    //   415: bipush #23
    //   417: ldc 907870729
    //   419: iastore
    //   420: dup
    //   421: bipush #24
    //   423: ldc 389426184
    //   425: iastore
    //   426: dup
    //   427: bipush #25
    //   429: ldc 973875457
    //   431: iastore
    //   432: dup
    //   433: bipush #26
    //   435: ldc 372376604
    //   437: iastore
    //   438: dup
    //   439: bipush #27
    //   441: ldc 707731490
    //   443: iastore
    //   444: dup
    //   445: bipush #28
    //   447: ldc 1043334948
    //   449: iastore
    //   450: dup
    //   451: bipush #29
    //   453: ldc 439222784
    //   455: iastore
    //   456: dup
    //   457: bipush #30
    //   459: ldc 876216579
    //   461: iastore
    //   462: dup
    //   463: bipush #31
    //   465: ldc 455999525
    //   467: iastore
    //   468: astore #5
    //   470: bipush #8
    //   472: aload_3
    //   473: arraylength
    //   474: bipush #8
    //   476: irem
    //   477: isub
    //   478: istore #6
    //   480: aload_3
    //   481: arraylength
    //   482: iload #6
    //   484: iadd
    //   485: newarray byte
    //   487: astore #7
    //   489: iconst_0
    //   490: istore #8
    //   492: iload #8
    //   494: aload_3
    //   495: arraylength
    //   496: if_icmpge -> 515
    //   499: aload #7
    //   501: iload #8
    //   503: aload_3
    //   504: iload #8
    //   506: baload
    //   507: bastore
    //   508: iinc #8, 1
    //   511: iload_2
    //   512: ifeq -> 492
    //   515: aload_3
    //   516: arraylength
    //   517: istore #8
    //   519: iload #8
    //   521: aload #7
    //   523: arraylength
    //   524: if_icmpge -> 542
    //   527: aload #7
    //   529: iload #8
    //   531: iload #6
    //   533: i2b
    //   534: bastore
    //   535: iinc #8, 1
    //   538: iload_2
    //   539: ifeq -> 519
    //   542: aload #7
    //   544: astore_3
    //   545: bipush #64
    //   547: newarray int
    //   549: dup
    //   550: iconst_0
    //   551: ldc 16843776
    //   553: iastore
    //   554: dup
    //   555: iconst_1
    //   556: iconst_0
    //   557: iastore
    //   558: dup
    //   559: iconst_2
    //   560: ldc 65536
    //   562: iastore
    //   563: dup
    //   564: iconst_3
    //   565: ldc 16843780
    //   567: iastore
    //   568: dup
    //   569: iconst_4
    //   570: ldc 16842756
    //   572: iastore
    //   573: dup
    //   574: iconst_5
    //   575: ldc 66564
    //   577: iastore
    //   578: dup
    //   579: bipush #6
    //   581: iconst_4
    //   582: iastore
    //   583: dup
    //   584: bipush #7
    //   586: ldc 65536
    //   588: iastore
    //   589: dup
    //   590: bipush #8
    //   592: sipush #1024
    //   595: iastore
    //   596: dup
    //   597: bipush #9
    //   599: ldc 16843776
    //   601: iastore
    //   602: dup
    //   603: bipush #10
    //   605: ldc 16843780
    //   607: iastore
    //   608: dup
    //   609: bipush #11
    //   611: sipush #1024
    //   614: iastore
    //   615: dup
    //   616: bipush #12
    //   618: ldc 16778244
    //   620: iastore
    //   621: dup
    //   622: bipush #13
    //   624: ldc 16842756
    //   626: iastore
    //   627: dup
    //   628: bipush #14
    //   630: ldc 16777216
    //   632: iastore
    //   633: dup
    //   634: bipush #15
    //   636: iconst_4
    //   637: iastore
    //   638: dup
    //   639: bipush #16
    //   641: sipush #1028
    //   644: iastore
    //   645: dup
    //   646: bipush #17
    //   648: ldc 16778240
    //   650: iastore
    //   651: dup
    //   652: bipush #18
    //   654: ldc 16778240
    //   656: iastore
    //   657: dup
    //   658: bipush #19
    //   660: ldc 66560
    //   662: iastore
    //   663: dup
    //   664: bipush #20
    //   666: ldc 66560
    //   668: iastore
    //   669: dup
    //   670: bipush #21
    //   672: ldc 16842752
    //   674: iastore
    //   675: dup
    //   676: bipush #22
    //   678: ldc 16842752
    //   680: iastore
    //   681: dup
    //   682: bipush #23
    //   684: ldc 16778244
    //   686: iastore
    //   687: dup
    //   688: bipush #24
    //   690: ldc 65540
    //   692: iastore
    //   693: dup
    //   694: bipush #25
    //   696: ldc 16777220
    //   698: iastore
    //   699: dup
    //   700: bipush #26
    //   702: ldc 16777220
    //   704: iastore
    //   705: dup
    //   706: bipush #27
    //   708: ldc 65540
    //   710: iastore
    //   711: dup
    //   712: bipush #28
    //   714: iconst_0
    //   715: iastore
    //   716: dup
    //   717: bipush #29
    //   719: sipush #1028
    //   722: iastore
    //   723: dup
    //   724: bipush #30
    //   726: ldc 66564
    //   728: iastore
    //   729: dup
    //   730: bipush #31
    //   732: ldc 16777216
    //   734: iastore
    //   735: dup
    //   736: bipush #32
    //   738: ldc 65536
    //   740: iastore
    //   741: dup
    //   742: bipush #33
    //   744: ldc 16843780
    //   746: iastore
    //   747: dup
    //   748: bipush #34
    //   750: iconst_4
    //   751: iastore
    //   752: dup
    //   753: bipush #35
    //   755: ldc 16842752
    //   757: iastore
    //   758: dup
    //   759: bipush #36
    //   761: ldc 16843776
    //   763: iastore
    //   764: dup
    //   765: bipush #37
    //   767: ldc 16777216
    //   769: iastore
    //   770: dup
    //   771: bipush #38
    //   773: ldc 16777216
    //   775: iastore
    //   776: dup
    //   777: bipush #39
    //   779: sipush #1024
    //   782: iastore
    //   783: dup
    //   784: bipush #40
    //   786: ldc 16842756
    //   788: iastore
    //   789: dup
    //   790: bipush #41
    //   792: ldc 65536
    //   794: iastore
    //   795: dup
    //   796: bipush #42
    //   798: ldc 66560
    //   800: iastore
    //   801: dup
    //   802: bipush #43
    //   804: ldc 16777220
    //   806: iastore
    //   807: dup
    //   808: bipush #44
    //   810: sipush #1024
    //   813: iastore
    //   814: dup
    //   815: bipush #45
    //   817: iconst_4
    //   818: iastore
    //   819: dup
    //   820: bipush #46
    //   822: ldc 16778244
    //   824: iastore
    //   825: dup
    //   826: bipush #47
    //   828: ldc 66564
    //   830: iastore
    //   831: dup
    //   832: bipush #48
    //   834: ldc 16843780
    //   836: iastore
    //   837: dup
    //   838: bipush #49
    //   840: ldc 65540
    //   842: iastore
    //   843: dup
    //   844: bipush #50
    //   846: ldc 16842752
    //   848: iastore
    //   849: dup
    //   850: bipush #51
    //   852: ldc 16778244
    //   854: iastore
    //   855: dup
    //   856: bipush #52
    //   858: ldc 16777220
    //   860: iastore
    //   861: dup
    //   862: bipush #53
    //   864: sipush #1028
    //   867: iastore
    //   868: dup
    //   869: bipush #54
    //   871: ldc 66564
    //   873: iastore
    //   874: dup
    //   875: bipush #55
    //   877: ldc 16843776
    //   879: iastore
    //   880: dup
    //   881: bipush #56
    //   883: sipush #1028
    //   886: iastore
    //   887: dup
    //   888: bipush #57
    //   890: ldc 16778240
    //   892: iastore
    //   893: dup
    //   894: bipush #58
    //   896: ldc 16778240
    //   898: iastore
    //   899: dup
    //   900: bipush #59
    //   902: iconst_0
    //   903: iastore
    //   904: dup
    //   905: bipush #60
    //   907: ldc 65540
    //   909: iastore
    //   910: dup
    //   911: bipush #61
    //   913: ldc 66560
    //   915: iastore
    //   916: dup
    //   917: bipush #62
    //   919: iconst_0
    //   920: iastore
    //   921: dup
    //   922: bipush #63
    //   924: ldc 16842756
    //   926: iastore
    //   927: astore #8
    //   929: bipush #64
    //   931: newarray int
    //   933: dup
    //   934: iconst_0
    //   935: ldc -2146402272
    //   937: iastore
    //   938: dup
    //   939: iconst_1
    //   940: ldc -2147450880
    //   942: iastore
    //   943: dup
    //   944: iconst_2
    //   945: ldc 32768
    //   947: iastore
    //   948: dup
    //   949: iconst_3
    //   950: ldc 1081376
    //   952: iastore
    //   953: dup
    //   954: iconst_4
    //   955: ldc 1048576
    //   957: iastore
    //   958: dup
    //   959: iconst_5
    //   960: bipush #32
    //   962: iastore
    //   963: dup
    //   964: bipush #6
    //   966: ldc -2146435040
    //   968: iastore
    //   969: dup
    //   970: bipush #7
    //   972: ldc -2147450848
    //   974: iastore
    //   975: dup
    //   976: bipush #8
    //   978: ldc -2147483616
    //   980: iastore
    //   981: dup
    //   982: bipush #9
    //   984: ldc -2146402272
    //   986: iastore
    //   987: dup
    //   988: bipush #10
    //   990: ldc -2146402304
    //   992: iastore
    //   993: dup
    //   994: bipush #11
    //   996: ldc -2147483648
    //   998: iastore
    //   999: dup
    //   1000: bipush #12
    //   1002: ldc -2147450880
    //   1004: iastore
    //   1005: dup
    //   1006: bipush #13
    //   1008: ldc 1048576
    //   1010: iastore
    //   1011: dup
    //   1012: bipush #14
    //   1014: bipush #32
    //   1016: iastore
    //   1017: dup
    //   1018: bipush #15
    //   1020: ldc -2146435040
    //   1022: iastore
    //   1023: dup
    //   1024: bipush #16
    //   1026: ldc 1081344
    //   1028: iastore
    //   1029: dup
    //   1030: bipush #17
    //   1032: ldc 1048608
    //   1034: iastore
    //   1035: dup
    //   1036: bipush #18
    //   1038: ldc -2147450848
    //   1040: iastore
    //   1041: dup
    //   1042: bipush #19
    //   1044: iconst_0
    //   1045: iastore
    //   1046: dup
    //   1047: bipush #20
    //   1049: ldc -2147483648
    //   1051: iastore
    //   1052: dup
    //   1053: bipush #21
    //   1055: ldc 32768
    //   1057: iastore
    //   1058: dup
    //   1059: bipush #22
    //   1061: ldc 1081376
    //   1063: iastore
    //   1064: dup
    //   1065: bipush #23
    //   1067: ldc -2146435072
    //   1069: iastore
    //   1070: dup
    //   1071: bipush #24
    //   1073: ldc 1048608
    //   1075: iastore
    //   1076: dup
    //   1077: bipush #25
    //   1079: ldc -2147483616
    //   1081: iastore
    //   1082: dup
    //   1083: bipush #26
    //   1085: iconst_0
    //   1086: iastore
    //   1087: dup
    //   1088: bipush #27
    //   1090: ldc 1081344
    //   1092: iastore
    //   1093: dup
    //   1094: bipush #28
    //   1096: ldc 32800
    //   1098: iastore
    //   1099: dup
    //   1100: bipush #29
    //   1102: ldc -2146402304
    //   1104: iastore
    //   1105: dup
    //   1106: bipush #30
    //   1108: ldc -2146435072
    //   1110: iastore
    //   1111: dup
    //   1112: bipush #31
    //   1114: ldc 32800
    //   1116: iastore
    //   1117: dup
    //   1118: bipush #32
    //   1120: iconst_0
    //   1121: iastore
    //   1122: dup
    //   1123: bipush #33
    //   1125: ldc 1081376
    //   1127: iastore
    //   1128: dup
    //   1129: bipush #34
    //   1131: ldc -2146435040
    //   1133: iastore
    //   1134: dup
    //   1135: bipush #35
    //   1137: ldc 1048576
    //   1139: iastore
    //   1140: dup
    //   1141: bipush #36
    //   1143: ldc -2147450848
    //   1145: iastore
    //   1146: dup
    //   1147: bipush #37
    //   1149: ldc -2146435072
    //   1151: iastore
    //   1152: dup
    //   1153: bipush #38
    //   1155: ldc -2146402304
    //   1157: iastore
    //   1158: dup
    //   1159: bipush #39
    //   1161: ldc 32768
    //   1163: iastore
    //   1164: dup
    //   1165: bipush #40
    //   1167: ldc -2146435072
    //   1169: iastore
    //   1170: dup
    //   1171: bipush #41
    //   1173: ldc -2147450880
    //   1175: iastore
    //   1176: dup
    //   1177: bipush #42
    //   1179: bipush #32
    //   1181: iastore
    //   1182: dup
    //   1183: bipush #43
    //   1185: ldc -2146402272
    //   1187: iastore
    //   1188: dup
    //   1189: bipush #44
    //   1191: ldc 1081376
    //   1193: iastore
    //   1194: dup
    //   1195: bipush #45
    //   1197: bipush #32
    //   1199: iastore
    //   1200: dup
    //   1201: bipush #46
    //   1203: ldc 32768
    //   1205: iastore
    //   1206: dup
    //   1207: bipush #47
    //   1209: ldc -2147483648
    //   1211: iastore
    //   1212: dup
    //   1213: bipush #48
    //   1215: ldc 32800
    //   1217: iastore
    //   1218: dup
    //   1219: bipush #49
    //   1221: ldc -2146402304
    //   1223: iastore
    //   1224: dup
    //   1225: bipush #50
    //   1227: ldc 1048576
    //   1229: iastore
    //   1230: dup
    //   1231: bipush #51
    //   1233: ldc -2147483616
    //   1235: iastore
    //   1236: dup
    //   1237: bipush #52
    //   1239: ldc 1048608
    //   1241: iastore
    //   1242: dup
    //   1243: bipush #53
    //   1245: ldc -2147450848
    //   1247: iastore
    //   1248: dup
    //   1249: bipush #54
    //   1251: ldc -2147483616
    //   1253: iastore
    //   1254: dup
    //   1255: bipush #55
    //   1257: ldc 1048608
    //   1259: iastore
    //   1260: dup
    //   1261: bipush #56
    //   1263: ldc 1081344
    //   1265: iastore
    //   1266: dup
    //   1267: bipush #57
    //   1269: iconst_0
    //   1270: iastore
    //   1271: dup
    //   1272: bipush #58
    //   1274: ldc -2147450880
    //   1276: iastore
    //   1277: dup
    //   1278: bipush #59
    //   1280: ldc 32800
    //   1282: iastore
    //   1283: dup
    //   1284: bipush #60
    //   1286: ldc -2147483648
    //   1288: iastore
    //   1289: dup
    //   1290: bipush #61
    //   1292: ldc -2146435040
    //   1294: iastore
    //   1295: dup
    //   1296: bipush #62
    //   1298: ldc -2146402272
    //   1300: iastore
    //   1301: dup
    //   1302: bipush #63
    //   1304: ldc 1081344
    //   1306: iastore
    //   1307: astore #9
    //   1309: bipush #64
    //   1311: newarray int
    //   1313: dup
    //   1314: iconst_0
    //   1315: sipush #520
    //   1318: iastore
    //   1319: dup
    //   1320: iconst_1
    //   1321: ldc 134349312
    //   1323: iastore
    //   1324: dup
    //   1325: iconst_2
    //   1326: iconst_0
    //   1327: iastore
    //   1328: dup
    //   1329: iconst_3
    //   1330: ldc 134348808
    //   1332: iastore
    //   1333: dup
    //   1334: iconst_4
    //   1335: ldc 134218240
    //   1337: iastore
    //   1338: dup
    //   1339: iconst_5
    //   1340: iconst_0
    //   1341: iastore
    //   1342: dup
    //   1343: bipush #6
    //   1345: ldc 131592
    //   1347: iastore
    //   1348: dup
    //   1349: bipush #7
    //   1351: ldc 134218240
    //   1353: iastore
    //   1354: dup
    //   1355: bipush #8
    //   1357: ldc 131080
    //   1359: iastore
    //   1360: dup
    //   1361: bipush #9
    //   1363: ldc 134217736
    //   1365: iastore
    //   1366: dup
    //   1367: bipush #10
    //   1369: ldc 134217736
    //   1371: iastore
    //   1372: dup
    //   1373: bipush #11
    //   1375: ldc 131072
    //   1377: iastore
    //   1378: dup
    //   1379: bipush #12
    //   1381: ldc 134349320
    //   1383: iastore
    //   1384: dup
    //   1385: bipush #13
    //   1387: ldc 131080
    //   1389: iastore
    //   1390: dup
    //   1391: bipush #14
    //   1393: ldc 134348800
    //   1395: iastore
    //   1396: dup
    //   1397: bipush #15
    //   1399: sipush #520
    //   1402: iastore
    //   1403: dup
    //   1404: bipush #16
    //   1406: ldc 134217728
    //   1408: iastore
    //   1409: dup
    //   1410: bipush #17
    //   1412: bipush #8
    //   1414: iastore
    //   1415: dup
    //   1416: bipush #18
    //   1418: ldc 134349312
    //   1420: iastore
    //   1421: dup
    //   1422: bipush #19
    //   1424: sipush #512
    //   1427: iastore
    //   1428: dup
    //   1429: bipush #20
    //   1431: ldc 131584
    //   1433: iastore
    //   1434: dup
    //   1435: bipush #21
    //   1437: ldc 134348800
    //   1439: iastore
    //   1440: dup
    //   1441: bipush #22
    //   1443: ldc 134348808
    //   1445: iastore
    //   1446: dup
    //   1447: bipush #23
    //   1449: ldc 131592
    //   1451: iastore
    //   1452: dup
    //   1453: bipush #24
    //   1455: ldc 134218248
    //   1457: iastore
    //   1458: dup
    //   1459: bipush #25
    //   1461: ldc 131584
    //   1463: iastore
    //   1464: dup
    //   1465: bipush #26
    //   1467: ldc 131072
    //   1469: iastore
    //   1470: dup
    //   1471: bipush #27
    //   1473: ldc 134218248
    //   1475: iastore
    //   1476: dup
    //   1477: bipush #28
    //   1479: bipush #8
    //   1481: iastore
    //   1482: dup
    //   1483: bipush #29
    //   1485: ldc 134349320
    //   1487: iastore
    //   1488: dup
    //   1489: bipush #30
    //   1491: sipush #512
    //   1494: iastore
    //   1495: dup
    //   1496: bipush #31
    //   1498: ldc 134217728
    //   1500: iastore
    //   1501: dup
    //   1502: bipush #32
    //   1504: ldc 134349312
    //   1506: iastore
    //   1507: dup
    //   1508: bipush #33
    //   1510: ldc 134217728
    //   1512: iastore
    //   1513: dup
    //   1514: bipush #34
    //   1516: ldc 131080
    //   1518: iastore
    //   1519: dup
    //   1520: bipush #35
    //   1522: sipush #520
    //   1525: iastore
    //   1526: dup
    //   1527: bipush #36
    //   1529: ldc 131072
    //   1531: iastore
    //   1532: dup
    //   1533: bipush #37
    //   1535: ldc 134349312
    //   1537: iastore
    //   1538: dup
    //   1539: bipush #38
    //   1541: ldc 134218240
    //   1543: iastore
    //   1544: dup
    //   1545: bipush #39
    //   1547: iconst_0
    //   1548: iastore
    //   1549: dup
    //   1550: bipush #40
    //   1552: sipush #512
    //   1555: iastore
    //   1556: dup
    //   1557: bipush #41
    //   1559: ldc 131080
    //   1561: iastore
    //   1562: dup
    //   1563: bipush #42
    //   1565: ldc 134349320
    //   1567: iastore
    //   1568: dup
    //   1569: bipush #43
    //   1571: ldc 134218240
    //   1573: iastore
    //   1574: dup
    //   1575: bipush #44
    //   1577: ldc 134217736
    //   1579: iastore
    //   1580: dup
    //   1581: bipush #45
    //   1583: sipush #512
    //   1586: iastore
    //   1587: dup
    //   1588: bipush #46
    //   1590: iconst_0
    //   1591: iastore
    //   1592: dup
    //   1593: bipush #47
    //   1595: ldc 134348808
    //   1597: iastore
    //   1598: dup
    //   1599: bipush #48
    //   1601: ldc 134218248
    //   1603: iastore
    //   1604: dup
    //   1605: bipush #49
    //   1607: ldc 131072
    //   1609: iastore
    //   1610: dup
    //   1611: bipush #50
    //   1613: ldc 134217728
    //   1615: iastore
    //   1616: dup
    //   1617: bipush #51
    //   1619: ldc 134349320
    //   1621: iastore
    //   1622: dup
    //   1623: bipush #52
    //   1625: bipush #8
    //   1627: iastore
    //   1628: dup
    //   1629: bipush #53
    //   1631: ldc 131592
    //   1633: iastore
    //   1634: dup
    //   1635: bipush #54
    //   1637: ldc 131584
    //   1639: iastore
    //   1640: dup
    //   1641: bipush #55
    //   1643: ldc 134217736
    //   1645: iastore
    //   1646: dup
    //   1647: bipush #56
    //   1649: ldc 134348800
    //   1651: iastore
    //   1652: dup
    //   1653: bipush #57
    //   1655: ldc 134218248
    //   1657: iastore
    //   1658: dup
    //   1659: bipush #58
    //   1661: sipush #520
    //   1664: iastore
    //   1665: dup
    //   1666: bipush #59
    //   1668: ldc 134348800
    //   1670: iastore
    //   1671: dup
    //   1672: bipush #60
    //   1674: ldc 131592
    //   1676: iastore
    //   1677: dup
    //   1678: bipush #61
    //   1680: bipush #8
    //   1682: iastore
    //   1683: dup
    //   1684: bipush #62
    //   1686: ldc 134348808
    //   1688: iastore
    //   1689: dup
    //   1690: bipush #63
    //   1692: ldc 131584
    //   1694: iastore
    //   1695: astore #10
    //   1697: bipush #64
    //   1699: newarray int
    //   1701: dup
    //   1702: iconst_0
    //   1703: ldc 8396801
    //   1705: iastore
    //   1706: dup
    //   1707: iconst_1
    //   1708: sipush #8321
    //   1711: iastore
    //   1712: dup
    //   1713: iconst_2
    //   1714: sipush #8321
    //   1717: iastore
    //   1718: dup
    //   1719: iconst_3
    //   1720: sipush #128
    //   1723: iastore
    //   1724: dup
    //   1725: iconst_4
    //   1726: ldc 8396928
    //   1728: iastore
    //   1729: dup
    //   1730: iconst_5
    //   1731: ldc 8388737
    //   1733: iastore
    //   1734: dup
    //   1735: bipush #6
    //   1737: ldc 8388609
    //   1739: iastore
    //   1740: dup
    //   1741: bipush #7
    //   1743: sipush #8193
    //   1746: iastore
    //   1747: dup
    //   1748: bipush #8
    //   1750: iconst_0
    //   1751: iastore
    //   1752: dup
    //   1753: bipush #9
    //   1755: ldc 8396800
    //   1757: iastore
    //   1758: dup
    //   1759: bipush #10
    //   1761: ldc 8396800
    //   1763: iastore
    //   1764: dup
    //   1765: bipush #11
    //   1767: ldc 8396929
    //   1769: iastore
    //   1770: dup
    //   1771: bipush #12
    //   1773: sipush #129
    //   1776: iastore
    //   1777: dup
    //   1778: bipush #13
    //   1780: iconst_0
    //   1781: iastore
    //   1782: dup
    //   1783: bipush #14
    //   1785: ldc 8388736
    //   1787: iastore
    //   1788: dup
    //   1789: bipush #15
    //   1791: ldc 8388609
    //   1793: iastore
    //   1794: dup
    //   1795: bipush #16
    //   1797: iconst_1
    //   1798: iastore
    //   1799: dup
    //   1800: bipush #17
    //   1802: sipush #8192
    //   1805: iastore
    //   1806: dup
    //   1807: bipush #18
    //   1809: ldc 8388608
    //   1811: iastore
    //   1812: dup
    //   1813: bipush #19
    //   1815: ldc 8396801
    //   1817: iastore
    //   1818: dup
    //   1819: bipush #20
    //   1821: sipush #128
    //   1824: iastore
    //   1825: dup
    //   1826: bipush #21
    //   1828: ldc 8388608
    //   1830: iastore
    //   1831: dup
    //   1832: bipush #22
    //   1834: sipush #8193
    //   1837: iastore
    //   1838: dup
    //   1839: bipush #23
    //   1841: sipush #8320
    //   1844: iastore
    //   1845: dup
    //   1846: bipush #24
    //   1848: ldc 8388737
    //   1850: iastore
    //   1851: dup
    //   1852: bipush #25
    //   1854: iconst_1
    //   1855: iastore
    //   1856: dup
    //   1857: bipush #26
    //   1859: sipush #8320
    //   1862: iastore
    //   1863: dup
    //   1864: bipush #27
    //   1866: ldc 8388736
    //   1868: iastore
    //   1869: dup
    //   1870: bipush #28
    //   1872: sipush #8192
    //   1875: iastore
    //   1876: dup
    //   1877: bipush #29
    //   1879: ldc 8396928
    //   1881: iastore
    //   1882: dup
    //   1883: bipush #30
    //   1885: ldc 8396929
    //   1887: iastore
    //   1888: dup
    //   1889: bipush #31
    //   1891: sipush #129
    //   1894: iastore
    //   1895: dup
    //   1896: bipush #32
    //   1898: ldc 8388736
    //   1900: iastore
    //   1901: dup
    //   1902: bipush #33
    //   1904: ldc 8388609
    //   1906: iastore
    //   1907: dup
    //   1908: bipush #34
    //   1910: ldc 8396800
    //   1912: iastore
    //   1913: dup
    //   1914: bipush #35
    //   1916: ldc 8396929
    //   1918: iastore
    //   1919: dup
    //   1920: bipush #36
    //   1922: sipush #129
    //   1925: iastore
    //   1926: dup
    //   1927: bipush #37
    //   1929: iconst_0
    //   1930: iastore
    //   1931: dup
    //   1932: bipush #38
    //   1934: iconst_0
    //   1935: iastore
    //   1936: dup
    //   1937: bipush #39
    //   1939: ldc 8396800
    //   1941: iastore
    //   1942: dup
    //   1943: bipush #40
    //   1945: sipush #8320
    //   1948: iastore
    //   1949: dup
    //   1950: bipush #41
    //   1952: ldc 8388736
    //   1954: iastore
    //   1955: dup
    //   1956: bipush #42
    //   1958: ldc 8388737
    //   1960: iastore
    //   1961: dup
    //   1962: bipush #43
    //   1964: iconst_1
    //   1965: iastore
    //   1966: dup
    //   1967: bipush #44
    //   1969: ldc 8396801
    //   1971: iastore
    //   1972: dup
    //   1973: bipush #45
    //   1975: sipush #8321
    //   1978: iastore
    //   1979: dup
    //   1980: bipush #46
    //   1982: sipush #8321
    //   1985: iastore
    //   1986: dup
    //   1987: bipush #47
    //   1989: sipush #128
    //   1992: iastore
    //   1993: dup
    //   1994: bipush #48
    //   1996: ldc 8396929
    //   1998: iastore
    //   1999: dup
    //   2000: bipush #49
    //   2002: sipush #129
    //   2005: iastore
    //   2006: dup
    //   2007: bipush #50
    //   2009: iconst_1
    //   2010: iastore
    //   2011: dup
    //   2012: bipush #51
    //   2014: sipush #8192
    //   2017: iastore
    //   2018: dup
    //   2019: bipush #52
    //   2021: ldc 8388609
    //   2023: iastore
    //   2024: dup
    //   2025: bipush #53
    //   2027: sipush #8193
    //   2030: iastore
    //   2031: dup
    //   2032: bipush #54
    //   2034: ldc 8396928
    //   2036: iastore
    //   2037: dup
    //   2038: bipush #55
    //   2040: ldc 8388737
    //   2042: iastore
    //   2043: dup
    //   2044: bipush #56
    //   2046: sipush #8193
    //   2049: iastore
    //   2050: dup
    //   2051: bipush #57
    //   2053: sipush #8320
    //   2056: iastore
    //   2057: dup
    //   2058: bipush #58
    //   2060: ldc 8388608
    //   2062: iastore
    //   2063: dup
    //   2064: bipush #59
    //   2066: ldc 8396801
    //   2068: iastore
    //   2069: dup
    //   2070: bipush #60
    //   2072: sipush #128
    //   2075: iastore
    //   2076: dup
    //   2077: bipush #61
    //   2079: ldc 8388608
    //   2081: iastore
    //   2082: dup
    //   2083: bipush #62
    //   2085: sipush #8192
    //   2088: iastore
    //   2089: dup
    //   2090: bipush #63
    //   2092: ldc 8396928
    //   2094: iastore
    //   2095: astore #11
    //   2097: bipush #64
    //   2099: newarray int
    //   2101: dup
    //   2102: iconst_0
    //   2103: sipush #256
    //   2106: iastore
    //   2107: dup
    //   2108: iconst_1
    //   2109: ldc 34078976
    //   2111: iastore
    //   2112: dup
    //   2113: iconst_2
    //   2114: ldc 34078720
    //   2116: iastore
    //   2117: dup
    //   2118: iconst_3
    //   2119: ldc 1107296512
    //   2121: iastore
    //   2122: dup
    //   2123: iconst_4
    //   2124: ldc 524288
    //   2126: iastore
    //   2127: dup
    //   2128: iconst_5
    //   2129: sipush #256
    //   2132: iastore
    //   2133: dup
    //   2134: bipush #6
    //   2136: ldc 1073741824
    //   2138: iastore
    //   2139: dup
    //   2140: bipush #7
    //   2142: ldc 34078720
    //   2144: iastore
    //   2145: dup
    //   2146: bipush #8
    //   2148: ldc 1074266368
    //   2150: iastore
    //   2151: dup
    //   2152: bipush #9
    //   2154: ldc 524288
    //   2156: iastore
    //   2157: dup
    //   2158: bipush #10
    //   2160: ldc 33554688
    //   2162: iastore
    //   2163: dup
    //   2164: bipush #11
    //   2166: ldc 1074266368
    //   2168: iastore
    //   2169: dup
    //   2170: bipush #12
    //   2172: ldc 1107296512
    //   2174: iastore
    //   2175: dup
    //   2176: bipush #13
    //   2178: ldc 1107820544
    //   2180: iastore
    //   2181: dup
    //   2182: bipush #14
    //   2184: ldc 524544
    //   2186: iastore
    //   2187: dup
    //   2188: bipush #15
    //   2190: ldc 1073741824
    //   2192: iastore
    //   2193: dup
    //   2194: bipush #16
    //   2196: ldc 33554432
    //   2198: iastore
    //   2199: dup
    //   2200: bipush #17
    //   2202: ldc 1074266112
    //   2204: iastore
    //   2205: dup
    //   2206: bipush #18
    //   2208: ldc 1074266112
    //   2210: iastore
    //   2211: dup
    //   2212: bipush #19
    //   2214: iconst_0
    //   2215: iastore
    //   2216: dup
    //   2217: bipush #20
    //   2219: ldc 1073742080
    //   2221: iastore
    //   2222: dup
    //   2223: bipush #21
    //   2225: ldc 1107820800
    //   2227: iastore
    //   2228: dup
    //   2229: bipush #22
    //   2231: ldc 1107820800
    //   2233: iastore
    //   2234: dup
    //   2235: bipush #23
    //   2237: ldc 33554688
    //   2239: iastore
    //   2240: dup
    //   2241: bipush #24
    //   2243: ldc 1107820544
    //   2245: iastore
    //   2246: dup
    //   2247: bipush #25
    //   2249: ldc 1073742080
    //   2251: iastore
    //   2252: dup
    //   2253: bipush #26
    //   2255: iconst_0
    //   2256: iastore
    //   2257: dup
    //   2258: bipush #27
    //   2260: ldc 1107296256
    //   2262: iastore
    //   2263: dup
    //   2264: bipush #28
    //   2266: ldc 34078976
    //   2268: iastore
    //   2269: dup
    //   2270: bipush #29
    //   2272: ldc 33554432
    //   2274: iastore
    //   2275: dup
    //   2276: bipush #30
    //   2278: ldc 1107296256
    //   2280: iastore
    //   2281: dup
    //   2282: bipush #31
    //   2284: ldc 524544
    //   2286: iastore
    //   2287: dup
    //   2288: bipush #32
    //   2290: ldc 524288
    //   2292: iastore
    //   2293: dup
    //   2294: bipush #33
    //   2296: ldc 1107296512
    //   2298: iastore
    //   2299: dup
    //   2300: bipush #34
    //   2302: sipush #256
    //   2305: iastore
    //   2306: dup
    //   2307: bipush #35
    //   2309: ldc 33554432
    //   2311: iastore
    //   2312: dup
    //   2313: bipush #36
    //   2315: ldc 1073741824
    //   2317: iastore
    //   2318: dup
    //   2319: bipush #37
    //   2321: ldc 34078720
    //   2323: iastore
    //   2324: dup
    //   2325: bipush #38
    //   2327: ldc 1107296512
    //   2329: iastore
    //   2330: dup
    //   2331: bipush #39
    //   2333: ldc 1074266368
    //   2335: iastore
    //   2336: dup
    //   2337: bipush #40
    //   2339: ldc 33554688
    //   2341: iastore
    //   2342: dup
    //   2343: bipush #41
    //   2345: ldc 1073741824
    //   2347: iastore
    //   2348: dup
    //   2349: bipush #42
    //   2351: ldc 1107820544
    //   2353: iastore
    //   2354: dup
    //   2355: bipush #43
    //   2357: ldc 34078976
    //   2359: iastore
    //   2360: dup
    //   2361: bipush #44
    //   2363: ldc 1074266368
    //   2365: iastore
    //   2366: dup
    //   2367: bipush #45
    //   2369: sipush #256
    //   2372: iastore
    //   2373: dup
    //   2374: bipush #46
    //   2376: ldc 33554432
    //   2378: iastore
    //   2379: dup
    //   2380: bipush #47
    //   2382: ldc 1107820544
    //   2384: iastore
    //   2385: dup
    //   2386: bipush #48
    //   2388: ldc 1107820800
    //   2390: iastore
    //   2391: dup
    //   2392: bipush #49
    //   2394: ldc 524544
    //   2396: iastore
    //   2397: dup
    //   2398: bipush #50
    //   2400: ldc 1107296256
    //   2402: iastore
    //   2403: dup
    //   2404: bipush #51
    //   2406: ldc 1107820800
    //   2408: iastore
    //   2409: dup
    //   2410: bipush #52
    //   2412: ldc 34078720
    //   2414: iastore
    //   2415: dup
    //   2416: bipush #53
    //   2418: iconst_0
    //   2419: iastore
    //   2420: dup
    //   2421: bipush #54
    //   2423: ldc 1074266112
    //   2425: iastore
    //   2426: dup
    //   2427: bipush #55
    //   2429: ldc 1107296256
    //   2431: iastore
    //   2432: dup
    //   2433: bipush #56
    //   2435: ldc 524544
    //   2437: iastore
    //   2438: dup
    //   2439: bipush #57
    //   2441: ldc 33554688
    //   2443: iastore
    //   2444: dup
    //   2445: bipush #58
    //   2447: ldc 1073742080
    //   2449: iastore
    //   2450: dup
    //   2451: bipush #59
    //   2453: ldc 524288
    //   2455: iastore
    //   2456: dup
    //   2457: bipush #60
    //   2459: iconst_0
    //   2460: iastore
    //   2461: dup
    //   2462: bipush #61
    //   2464: ldc 1074266112
    //   2466: iastore
    //   2467: dup
    //   2468: bipush #62
    //   2470: ldc 34078976
    //   2472: iastore
    //   2473: dup
    //   2474: bipush #63
    //   2476: ldc 1073742080
    //   2478: iastore
    //   2479: astore #12
    //   2481: bipush #64
    //   2483: newarray int
    //   2485: dup
    //   2486: iconst_0
    //   2487: ldc 536870928
    //   2489: iastore
    //   2490: dup
    //   2491: iconst_1
    //   2492: ldc 541065216
    //   2494: iastore
    //   2495: dup
    //   2496: iconst_2
    //   2497: sipush #16384
    //   2500: iastore
    //   2501: dup
    //   2502: iconst_3
    //   2503: ldc 541081616
    //   2505: iastore
    //   2506: dup
    //   2507: iconst_4
    //   2508: ldc 541065216
    //   2510: iastore
    //   2511: dup
    //   2512: iconst_5
    //   2513: bipush #16
    //   2515: iastore
    //   2516: dup
    //   2517: bipush #6
    //   2519: ldc 541081616
    //   2521: iastore
    //   2522: dup
    //   2523: bipush #7
    //   2525: ldc 4194304
    //   2527: iastore
    //   2528: dup
    //   2529: bipush #8
    //   2531: ldc 536887296
    //   2533: iastore
    //   2534: dup
    //   2535: bipush #9
    //   2537: ldc 4210704
    //   2539: iastore
    //   2540: dup
    //   2541: bipush #10
    //   2543: ldc 4194304
    //   2545: iastore
    //   2546: dup
    //   2547: bipush #11
    //   2549: ldc 536870928
    //   2551: iastore
    //   2552: dup
    //   2553: bipush #12
    //   2555: ldc 4194320
    //   2557: iastore
    //   2558: dup
    //   2559: bipush #13
    //   2561: ldc 536887296
    //   2563: iastore
    //   2564: dup
    //   2565: bipush #14
    //   2567: ldc 536870912
    //   2569: iastore
    //   2570: dup
    //   2571: bipush #15
    //   2573: sipush #16400
    //   2576: iastore
    //   2577: dup
    //   2578: bipush #16
    //   2580: iconst_0
    //   2581: iastore
    //   2582: dup
    //   2583: bipush #17
    //   2585: ldc 4194320
    //   2587: iastore
    //   2588: dup
    //   2589: bipush #18
    //   2591: ldc 536887312
    //   2593: iastore
    //   2594: dup
    //   2595: bipush #19
    //   2597: sipush #16384
    //   2600: iastore
    //   2601: dup
    //   2602: bipush #20
    //   2604: ldc 4210688
    //   2606: iastore
    //   2607: dup
    //   2608: bipush #21
    //   2610: ldc 536887312
    //   2612: iastore
    //   2613: dup
    //   2614: bipush #22
    //   2616: bipush #16
    //   2618: iastore
    //   2619: dup
    //   2620: bipush #23
    //   2622: ldc 541065232
    //   2624: iastore
    //   2625: dup
    //   2626: bipush #24
    //   2628: ldc 541065232
    //   2630: iastore
    //   2631: dup
    //   2632: bipush #25
    //   2634: iconst_0
    //   2635: iastore
    //   2636: dup
    //   2637: bipush #26
    //   2639: ldc 4210704
    //   2641: iastore
    //   2642: dup
    //   2643: bipush #27
    //   2645: ldc 541081600
    //   2647: iastore
    //   2648: dup
    //   2649: bipush #28
    //   2651: sipush #16400
    //   2654: iastore
    //   2655: dup
    //   2656: bipush #29
    //   2658: ldc 4210688
    //   2660: iastore
    //   2661: dup
    //   2662: bipush #30
    //   2664: ldc 541081600
    //   2666: iastore
    //   2667: dup
    //   2668: bipush #31
    //   2670: ldc 536870912
    //   2672: iastore
    //   2673: dup
    //   2674: bipush #32
    //   2676: ldc 536887296
    //   2678: iastore
    //   2679: dup
    //   2680: bipush #33
    //   2682: bipush #16
    //   2684: iastore
    //   2685: dup
    //   2686: bipush #34
    //   2688: ldc 541065232
    //   2690: iastore
    //   2691: dup
    //   2692: bipush #35
    //   2694: ldc 4210688
    //   2696: iastore
    //   2697: dup
    //   2698: bipush #36
    //   2700: ldc 541081616
    //   2702: iastore
    //   2703: dup
    //   2704: bipush #37
    //   2706: ldc 4194304
    //   2708: iastore
    //   2709: dup
    //   2710: bipush #38
    //   2712: sipush #16400
    //   2715: iastore
    //   2716: dup
    //   2717: bipush #39
    //   2719: ldc 536870928
    //   2721: iastore
    //   2722: dup
    //   2723: bipush #40
    //   2725: ldc 4194304
    //   2727: iastore
    //   2728: dup
    //   2729: bipush #41
    //   2731: ldc 536887296
    //   2733: iastore
    //   2734: dup
    //   2735: bipush #42
    //   2737: ldc 536870912
    //   2739: iastore
    //   2740: dup
    //   2741: bipush #43
    //   2743: sipush #16400
    //   2746: iastore
    //   2747: dup
    //   2748: bipush #44
    //   2750: ldc 536870928
    //   2752: iastore
    //   2753: dup
    //   2754: bipush #45
    //   2756: ldc 541081616
    //   2758: iastore
    //   2759: dup
    //   2760: bipush #46
    //   2762: ldc 4210688
    //   2764: iastore
    //   2765: dup
    //   2766: bipush #47
    //   2768: ldc 541065216
    //   2770: iastore
    //   2771: dup
    //   2772: bipush #48
    //   2774: ldc 4210704
    //   2776: iastore
    //   2777: dup
    //   2778: bipush #49
    //   2780: ldc 541081600
    //   2782: iastore
    //   2783: dup
    //   2784: bipush #50
    //   2786: iconst_0
    //   2787: iastore
    //   2788: dup
    //   2789: bipush #51
    //   2791: ldc 541065232
    //   2793: iastore
    //   2794: dup
    //   2795: bipush #52
    //   2797: bipush #16
    //   2799: iastore
    //   2800: dup
    //   2801: bipush #53
    //   2803: sipush #16384
    //   2806: iastore
    //   2807: dup
    //   2808: bipush #54
    //   2810: ldc 541065216
    //   2812: iastore
    //   2813: dup
    //   2814: bipush #55
    //   2816: ldc 4210704
    //   2818: iastore
    //   2819: dup
    //   2820: bipush #56
    //   2822: sipush #16384
    //   2825: iastore
    //   2826: dup
    //   2827: bipush #57
    //   2829: ldc 4194320
    //   2831: iastore
    //   2832: dup
    //   2833: bipush #58
    //   2835: ldc 536887312
    //   2837: iastore
    //   2838: dup
    //   2839: bipush #59
    //   2841: iconst_0
    //   2842: iastore
    //   2843: dup
    //   2844: bipush #60
    //   2846: ldc 541081600
    //   2848: iastore
    //   2849: dup
    //   2850: bipush #61
    //   2852: ldc 536870912
    //   2854: iastore
    //   2855: dup
    //   2856: bipush #62
    //   2858: ldc 4194320
    //   2860: iastore
    //   2861: dup
    //   2862: bipush #63
    //   2864: ldc 536887312
    //   2866: iastore
    //   2867: astore #13
    //   2869: bipush #64
    //   2871: newarray int
    //   2873: dup
    //   2874: iconst_0
    //   2875: ldc 2097152
    //   2877: iastore
    //   2878: dup
    //   2879: iconst_1
    //   2880: ldc 69206018
    //   2882: iastore
    //   2883: dup
    //   2884: iconst_2
    //   2885: ldc 67110914
    //   2887: iastore
    //   2888: dup
    //   2889: iconst_3
    //   2890: iconst_0
    //   2891: iastore
    //   2892: dup
    //   2893: iconst_4
    //   2894: sipush #2048
    //   2897: iastore
    //   2898: dup
    //   2899: iconst_5
    //   2900: ldc 67110914
    //   2902: iastore
    //   2903: dup
    //   2904: bipush #6
    //   2906: ldc 2099202
    //   2908: iastore
    //   2909: dup
    //   2910: bipush #7
    //   2912: ldc 69208064
    //   2914: iastore
    //   2915: dup
    //   2916: bipush #8
    //   2918: ldc 69208066
    //   2920: iastore
    //   2921: dup
    //   2922: bipush #9
    //   2924: ldc 2097152
    //   2926: iastore
    //   2927: dup
    //   2928: bipush #10
    //   2930: iconst_0
    //   2931: iastore
    //   2932: dup
    //   2933: bipush #11
    //   2935: ldc 67108866
    //   2937: iastore
    //   2938: dup
    //   2939: bipush #12
    //   2941: iconst_2
    //   2942: iastore
    //   2943: dup
    //   2944: bipush #13
    //   2946: ldc 67108864
    //   2948: iastore
    //   2949: dup
    //   2950: bipush #14
    //   2952: ldc 69206018
    //   2954: iastore
    //   2955: dup
    //   2956: bipush #15
    //   2958: sipush #2050
    //   2961: iastore
    //   2962: dup
    //   2963: bipush #16
    //   2965: ldc 67110912
    //   2967: iastore
    //   2968: dup
    //   2969: bipush #17
    //   2971: ldc 2099202
    //   2973: iastore
    //   2974: dup
    //   2975: bipush #18
    //   2977: ldc 2097154
    //   2979: iastore
    //   2980: dup
    //   2981: bipush #19
    //   2983: ldc 67110912
    //   2985: iastore
    //   2986: dup
    //   2987: bipush #20
    //   2989: ldc 67108866
    //   2991: iastore
    //   2992: dup
    //   2993: bipush #21
    //   2995: ldc 69206016
    //   2997: iastore
    //   2998: dup
    //   2999: bipush #22
    //   3001: ldc 69208064
    //   3003: iastore
    //   3004: dup
    //   3005: bipush #23
    //   3007: ldc 2097154
    //   3009: iastore
    //   3010: dup
    //   3011: bipush #24
    //   3013: ldc 69206016
    //   3015: iastore
    //   3016: dup
    //   3017: bipush #25
    //   3019: sipush #2048
    //   3022: iastore
    //   3023: dup
    //   3024: bipush #26
    //   3026: sipush #2050
    //   3029: iastore
    //   3030: dup
    //   3031: bipush #27
    //   3033: ldc 69208066
    //   3035: iastore
    //   3036: dup
    //   3037: bipush #28
    //   3039: ldc 2099200
    //   3041: iastore
    //   3042: dup
    //   3043: bipush #29
    //   3045: iconst_2
    //   3046: iastore
    //   3047: dup
    //   3048: bipush #30
    //   3050: ldc 67108864
    //   3052: iastore
    //   3053: dup
    //   3054: bipush #31
    //   3056: ldc 2099200
    //   3058: iastore
    //   3059: dup
    //   3060: bipush #32
    //   3062: ldc 67108864
    //   3064: iastore
    //   3065: dup
    //   3066: bipush #33
    //   3068: ldc 2099200
    //   3070: iastore
    //   3071: dup
    //   3072: bipush #34
    //   3074: ldc 2097152
    //   3076: iastore
    //   3077: dup
    //   3078: bipush #35
    //   3080: ldc 67110914
    //   3082: iastore
    //   3083: dup
    //   3084: bipush #36
    //   3086: ldc 67110914
    //   3088: iastore
    //   3089: dup
    //   3090: bipush #37
    //   3092: ldc 69206018
    //   3094: iastore
    //   3095: dup
    //   3096: bipush #38
    //   3098: ldc 69206018
    //   3100: iastore
    //   3101: dup
    //   3102: bipush #39
    //   3104: iconst_2
    //   3105: iastore
    //   3106: dup
    //   3107: bipush #40
    //   3109: ldc 2097154
    //   3111: iastore
    //   3112: dup
    //   3113: bipush #41
    //   3115: ldc 67108864
    //   3117: iastore
    //   3118: dup
    //   3119: bipush #42
    //   3121: ldc 67110912
    //   3123: iastore
    //   3124: dup
    //   3125: bipush #43
    //   3127: ldc 2097152
    //   3129: iastore
    //   3130: dup
    //   3131: bipush #44
    //   3133: ldc 69208064
    //   3135: iastore
    //   3136: dup
    //   3137: bipush #45
    //   3139: sipush #2050
    //   3142: iastore
    //   3143: dup
    //   3144: bipush #46
    //   3146: ldc 2099202
    //   3148: iastore
    //   3149: dup
    //   3150: bipush #47
    //   3152: ldc 69208064
    //   3154: iastore
    //   3155: dup
    //   3156: bipush #48
    //   3158: sipush #2050
    //   3161: iastore
    //   3162: dup
    //   3163: bipush #49
    //   3165: ldc 67108866
    //   3167: iastore
    //   3168: dup
    //   3169: bipush #50
    //   3171: ldc 69208066
    //   3173: iastore
    //   3174: dup
    //   3175: bipush #51
    //   3177: ldc 69206016
    //   3179: iastore
    //   3180: dup
    //   3181: bipush #52
    //   3183: ldc 2099200
    //   3185: iastore
    //   3186: dup
    //   3187: bipush #53
    //   3189: iconst_0
    //   3190: iastore
    //   3191: dup
    //   3192: bipush #54
    //   3194: iconst_2
    //   3195: iastore
    //   3196: dup
    //   3197: bipush #55
    //   3199: ldc 69208066
    //   3201: iastore
    //   3202: dup
    //   3203: bipush #56
    //   3205: iconst_0
    //   3206: iastore
    //   3207: dup
    //   3208: bipush #57
    //   3210: ldc 2099202
    //   3212: iastore
    //   3213: dup
    //   3214: bipush #58
    //   3216: ldc 69206016
    //   3218: iastore
    //   3219: dup
    //   3220: bipush #59
    //   3222: sipush #2048
    //   3225: iastore
    //   3226: dup
    //   3227: bipush #60
    //   3229: ldc 67108866
    //   3231: iastore
    //   3232: dup
    //   3233: bipush #61
    //   3235: ldc 67110912
    //   3237: iastore
    //   3238: dup
    //   3239: bipush #62
    //   3241: sipush #2048
    //   3244: iastore
    //   3245: dup
    //   3246: bipush #63
    //   3248: ldc 2097154
    //   3250: iastore
    //   3251: astore #14
    //   3253: bipush #64
    //   3255: newarray int
    //   3257: dup
    //   3258: iconst_0
    //   3259: ldc 268439616
    //   3261: iastore
    //   3262: dup
    //   3263: iconst_1
    //   3264: sipush #4096
    //   3267: iastore
    //   3268: dup
    //   3269: iconst_2
    //   3270: ldc 262144
    //   3272: iastore
    //   3273: dup
    //   3274: iconst_3
    //   3275: ldc 268701760
    //   3277: iastore
    //   3278: dup
    //   3279: iconst_4
    //   3280: ldc 268435456
    //   3282: iastore
    //   3283: dup
    //   3284: iconst_5
    //   3285: ldc 268439616
    //   3287: iastore
    //   3288: dup
    //   3289: bipush #6
    //   3291: bipush #64
    //   3293: iastore
    //   3294: dup
    //   3295: bipush #7
    //   3297: ldc 268435456
    //   3299: iastore
    //   3300: dup
    //   3301: bipush #8
    //   3303: ldc 262208
    //   3305: iastore
    //   3306: dup
    //   3307: bipush #9
    //   3309: ldc 268697600
    //   3311: iastore
    //   3312: dup
    //   3313: bipush #10
    //   3315: ldc 268701760
    //   3317: iastore
    //   3318: dup
    //   3319: bipush #11
    //   3321: ldc 266240
    //   3323: iastore
    //   3324: dup
    //   3325: bipush #12
    //   3327: ldc 268701696
    //   3329: iastore
    //   3330: dup
    //   3331: bipush #13
    //   3333: ldc 266304
    //   3335: iastore
    //   3336: dup
    //   3337: bipush #14
    //   3339: sipush #4096
    //   3342: iastore
    //   3343: dup
    //   3344: bipush #15
    //   3346: bipush #64
    //   3348: iastore
    //   3349: dup
    //   3350: bipush #16
    //   3352: ldc 268697600
    //   3354: iastore
    //   3355: dup
    //   3356: bipush #17
    //   3358: ldc 268435520
    //   3360: iastore
    //   3361: dup
    //   3362: bipush #18
    //   3364: ldc 268439552
    //   3366: iastore
    //   3367: dup
    //   3368: bipush #19
    //   3370: sipush #4160
    //   3373: iastore
    //   3374: dup
    //   3375: bipush #20
    //   3377: ldc 266240
    //   3379: iastore
    //   3380: dup
    //   3381: bipush #21
    //   3383: ldc 262208
    //   3385: iastore
    //   3386: dup
    //   3387: bipush #22
    //   3389: ldc 268697664
    //   3391: iastore
    //   3392: dup
    //   3393: bipush #23
    //   3395: ldc 268701696
    //   3397: iastore
    //   3398: dup
    //   3399: bipush #24
    //   3401: sipush #4160
    //   3404: iastore
    //   3405: dup
    //   3406: bipush #25
    //   3408: iconst_0
    //   3409: iastore
    //   3410: dup
    //   3411: bipush #26
    //   3413: iconst_0
    //   3414: iastore
    //   3415: dup
    //   3416: bipush #27
    //   3418: ldc 268697664
    //   3420: iastore
    //   3421: dup
    //   3422: bipush #28
    //   3424: ldc 268435520
    //   3426: iastore
    //   3427: dup
    //   3428: bipush #29
    //   3430: ldc 268439552
    //   3432: iastore
    //   3433: dup
    //   3434: bipush #30
    //   3436: ldc 266304
    //   3438: iastore
    //   3439: dup
    //   3440: bipush #31
    //   3442: ldc 262144
    //   3444: iastore
    //   3445: dup
    //   3446: bipush #32
    //   3448: ldc 266304
    //   3450: iastore
    //   3451: dup
    //   3452: bipush #33
    //   3454: ldc 262144
    //   3456: iastore
    //   3457: dup
    //   3458: bipush #34
    //   3460: ldc 268701696
    //   3462: iastore
    //   3463: dup
    //   3464: bipush #35
    //   3466: sipush #4096
    //   3469: iastore
    //   3470: dup
    //   3471: bipush #36
    //   3473: bipush #64
    //   3475: iastore
    //   3476: dup
    //   3477: bipush #37
    //   3479: ldc 268697664
    //   3481: iastore
    //   3482: dup
    //   3483: bipush #38
    //   3485: sipush #4096
    //   3488: iastore
    //   3489: dup
    //   3490: bipush #39
    //   3492: ldc 266304
    //   3494: iastore
    //   3495: dup
    //   3496: bipush #40
    //   3498: ldc 268439552
    //   3500: iastore
    //   3501: dup
    //   3502: bipush #41
    //   3504: bipush #64
    //   3506: iastore
    //   3507: dup
    //   3508: bipush #42
    //   3510: ldc 268435520
    //   3512: iastore
    //   3513: dup
    //   3514: bipush #43
    //   3516: ldc 268697600
    //   3518: iastore
    //   3519: dup
    //   3520: bipush #44
    //   3522: ldc 268697664
    //   3524: iastore
    //   3525: dup
    //   3526: bipush #45
    //   3528: ldc 268435456
    //   3530: iastore
    //   3531: dup
    //   3532: bipush #46
    //   3534: ldc 262144
    //   3536: iastore
    //   3537: dup
    //   3538: bipush #47
    //   3540: ldc 268439616
    //   3542: iastore
    //   3543: dup
    //   3544: bipush #48
    //   3546: iconst_0
    //   3547: iastore
    //   3548: dup
    //   3549: bipush #49
    //   3551: ldc 268701760
    //   3553: iastore
    //   3554: dup
    //   3555: bipush #50
    //   3557: ldc 262208
    //   3559: iastore
    //   3560: dup
    //   3561: bipush #51
    //   3563: ldc 268435520
    //   3565: iastore
    //   3566: dup
    //   3567: bipush #52
    //   3569: ldc 268697600
    //   3571: iastore
    //   3572: dup
    //   3573: bipush #53
    //   3575: ldc 268439552
    //   3577: iastore
    //   3578: dup
    //   3579: bipush #54
    //   3581: ldc 268439616
    //   3583: iastore
    //   3584: dup
    //   3585: bipush #55
    //   3587: iconst_0
    //   3588: iastore
    //   3589: dup
    //   3590: bipush #56
    //   3592: ldc 268701760
    //   3594: iastore
    //   3595: dup
    //   3596: bipush #57
    //   3598: ldc 266240
    //   3600: iastore
    //   3601: dup
    //   3602: bipush #58
    //   3604: ldc 266240
    //   3606: iastore
    //   3607: dup
    //   3608: bipush #59
    //   3610: sipush #4160
    //   3613: iastore
    //   3614: dup
    //   3615: bipush #60
    //   3617: sipush #4160
    //   3620: iastore
    //   3621: dup
    //   3622: bipush #61
    //   3624: ldc 262208
    //   3626: iastore
    //   3627: dup
    //   3628: bipush #62
    //   3630: ldc 268435456
    //   3632: iastore
    //   3633: dup
    //   3634: bipush #63
    //   3636: ldc 268701696
    //   3638: iastore
    //   3639: astore #15
    //   3641: aload_3
    //   3642: arraylength
    //   3643: istore #16
    //   3645: iconst_2
    //   3646: newarray int
    //   3648: astore #17
    //   3650: iload #16
    //   3652: newarray byte
    //   3654: astore #4
    //   3656: iload #16
    //   3658: bipush #8
    //   3660: idiv
    //   3661: istore #18
    //   3663: iconst_0
    //   3664: istore #19
    //   3666: iload #19
    //   3668: iload #18
    //   3670: if_icmpge -> 4584
    //   3673: iload #19
    //   3675: bipush #8
    //   3677: imul
    //   3678: istore #20
    //   3680: iconst_0
    //   3681: istore #21
    //   3683: iload #21
    //   3685: iconst_2
    //   3686: if_icmpge -> 3771
    //   3689: aload #17
    //   3691: iload #21
    //   3693: aload_3
    //   3694: iload #20
    //   3696: iload #21
    //   3698: iconst_4
    //   3699: imul
    //   3700: iadd
    //   3701: baload
    //   3702: sipush #255
    //   3705: iand
    //   3706: bipush #24
    //   3708: ishl
    //   3709: aload_3
    //   3710: iload #20
    //   3712: iload #21
    //   3714: iconst_4
    //   3715: imul
    //   3716: iadd
    //   3717: iconst_1
    //   3718: iadd
    //   3719: baload
    //   3720: sipush #255
    //   3723: iand
    //   3724: bipush #16
    //   3726: ishl
    //   3727: ior
    //   3728: aload_3
    //   3729: iload #20
    //   3731: iload #21
    //   3733: iconst_4
    //   3734: imul
    //   3735: iadd
    //   3736: iconst_2
    //   3737: iadd
    //   3738: baload
    //   3739: sipush #255
    //   3742: iand
    //   3743: bipush #8
    //   3745: ishl
    //   3746: ior
    //   3747: aload_3
    //   3748: iload #20
    //   3750: iload #21
    //   3752: iconst_4
    //   3753: imul
    //   3754: iadd
    //   3755: iconst_3
    //   3756: iadd
    //   3757: baload
    //   3758: sipush #255
    //   3761: iand
    //   3762: ior
    //   3763: iastore
    //   3764: iinc #21, 1
    //   3767: iload_2
    //   3768: ifeq -> 3683
    //   3771: iconst_0
    //   3772: istore #26
    //   3774: aload #17
    //   3776: iconst_0
    //   3777: iaload
    //   3778: istore #24
    //   3780: aload #17
    //   3782: iconst_1
    //   3783: iaload
    //   3784: istore #23
    //   3786: iload #24
    //   3788: iconst_4
    //   3789: iushr
    //   3790: iload #23
    //   3792: ixor
    //   3793: ldc 252645135
    //   3795: iand
    //   3796: istore #22
    //   3798: iload #23
    //   3800: iload #22
    //   3802: ixor
    //   3803: istore #23
    //   3805: iload #24
    //   3807: iload #22
    //   3809: iconst_4
    //   3810: ishl
    //   3811: ixor
    //   3812: istore #24
    //   3814: iload #24
    //   3816: bipush #16
    //   3818: iushr
    //   3819: iload #23
    //   3821: ixor
    //   3822: ldc 65535
    //   3824: iand
    //   3825: istore #22
    //   3827: iload #23
    //   3829: iload #22
    //   3831: ixor
    //   3832: istore #23
    //   3834: iload #24
    //   3836: iload #22
    //   3838: bipush #16
    //   3840: ishl
    //   3841: ixor
    //   3842: istore #24
    //   3844: iload #23
    //   3846: iconst_2
    //   3847: iushr
    //   3848: iload #24
    //   3850: ixor
    //   3851: ldc 858993459
    //   3853: iand
    //   3854: istore #22
    //   3856: iload #24
    //   3858: iload #22
    //   3860: ixor
    //   3861: istore #24
    //   3863: iload #23
    //   3865: iload #22
    //   3867: iconst_2
    //   3868: ishl
    //   3869: ixor
    //   3870: istore #23
    //   3872: iload #23
    //   3874: bipush #8
    //   3876: iushr
    //   3877: iload #24
    //   3879: ixor
    //   3880: ldc 16711935
    //   3882: iand
    //   3883: istore #22
    //   3885: iload #24
    //   3887: iload #22
    //   3889: ixor
    //   3890: istore #24
    //   3892: iload #23
    //   3894: iload #22
    //   3896: bipush #8
    //   3898: ishl
    //   3899: ixor
    //   3900: istore #23
    //   3902: iload #23
    //   3904: iconst_1
    //   3905: ishl
    //   3906: iload #23
    //   3908: bipush #31
    //   3910: iushr
    //   3911: iconst_1
    //   3912: iand
    //   3913: ior
    //   3914: istore #23
    //   3916: iload #24
    //   3918: iload #23
    //   3920: ixor
    //   3921: ldc -1431655766
    //   3923: iand
    //   3924: istore #22
    //   3926: iload #24
    //   3928: iload #22
    //   3930: ixor
    //   3931: istore #24
    //   3933: iload #23
    //   3935: iload #22
    //   3937: ixor
    //   3938: istore #23
    //   3940: iload #24
    //   3942: iconst_1
    //   3943: ishl
    //   3944: iload #24
    //   3946: bipush #31
    //   3948: iushr
    //   3949: iconst_1
    //   3950: iand
    //   3951: ior
    //   3952: istore #24
    //   3954: iconst_0
    //   3955: istore #25
    //   3957: iload #25
    //   3959: bipush #8
    //   3961: if_icmpge -> 4299
    //   3964: iload #23
    //   3966: bipush #28
    //   3968: ishl
    //   3969: iload #23
    //   3971: iconst_4
    //   3972: iushr
    //   3973: ior
    //   3974: istore #22
    //   3976: iload #22
    //   3978: aload #5
    //   3980: iload #26
    //   3982: iinc #26, 1
    //   3985: iaload
    //   3986: ixor
    //   3987: istore #22
    //   3989: aload #14
    //   3991: iload #22
    //   3993: bipush #63
    //   3995: iand
    //   3996: iaload
    //   3997: istore #21
    //   3999: iload #21
    //   4001: aload #12
    //   4003: iload #22
    //   4005: bipush #8
    //   4007: iushr
    //   4008: bipush #63
    //   4010: iand
    //   4011: iaload
    //   4012: ior
    //   4013: istore #21
    //   4015: iload #21
    //   4017: aload #10
    //   4019: iload #22
    //   4021: bipush #16
    //   4023: iushr
    //   4024: bipush #63
    //   4026: iand
    //   4027: iaload
    //   4028: ior
    //   4029: istore #21
    //   4031: iload #21
    //   4033: aload #8
    //   4035: iload #22
    //   4037: bipush #24
    //   4039: iushr
    //   4040: bipush #63
    //   4042: iand
    //   4043: iaload
    //   4044: ior
    //   4045: istore #21
    //   4047: iload #23
    //   4049: aload #5
    //   4051: iload #26
    //   4053: iinc #26, 1
    //   4056: iaload
    //   4057: ixor
    //   4058: istore #22
    //   4060: iload #21
    //   4062: aload #15
    //   4064: iload #22
    //   4066: bipush #63
    //   4068: iand
    //   4069: iaload
    //   4070: ior
    //   4071: istore #21
    //   4073: iload #21
    //   4075: aload #13
    //   4077: iload #22
    //   4079: bipush #8
    //   4081: iushr
    //   4082: bipush #63
    //   4084: iand
    //   4085: iaload
    //   4086: ior
    //   4087: istore #21
    //   4089: iload #21
    //   4091: aload #11
    //   4093: iload #22
    //   4095: bipush #16
    //   4097: iushr
    //   4098: bipush #63
    //   4100: iand
    //   4101: iaload
    //   4102: ior
    //   4103: istore #21
    //   4105: iload #21
    //   4107: aload #9
    //   4109: iload #22
    //   4111: bipush #24
    //   4113: iushr
    //   4114: bipush #63
    //   4116: iand
    //   4117: iaload
    //   4118: ior
    //   4119: istore #21
    //   4121: iload #24
    //   4123: iload #21
    //   4125: ixor
    //   4126: istore #24
    //   4128: iload #24
    //   4130: bipush #28
    //   4132: ishl
    //   4133: iload #24
    //   4135: iconst_4
    //   4136: iushr
    //   4137: ior
    //   4138: istore #22
    //   4140: iload #22
    //   4142: aload #5
    //   4144: iload #26
    //   4146: iinc #26, 1
    //   4149: iaload
    //   4150: ixor
    //   4151: istore #22
    //   4153: aload #14
    //   4155: iload #22
    //   4157: bipush #63
    //   4159: iand
    //   4160: iaload
    //   4161: istore #21
    //   4163: iload #21
    //   4165: aload #12
    //   4167: iload #22
    //   4169: bipush #8
    //   4171: iushr
    //   4172: bipush #63
    //   4174: iand
    //   4175: iaload
    //   4176: ior
    //   4177: istore #21
    //   4179: iload #21
    //   4181: aload #10
    //   4183: iload #22
    //   4185: bipush #16
    //   4187: iushr
    //   4188: bipush #63
    //   4190: iand
    //   4191: iaload
    //   4192: ior
    //   4193: istore #21
    //   4195: iload #21
    //   4197: aload #8
    //   4199: iload #22
    //   4201: bipush #24
    //   4203: iushr
    //   4204: bipush #63
    //   4206: iand
    //   4207: iaload
    //   4208: ior
    //   4209: istore #21
    //   4211: iload #24
    //   4213: aload #5
    //   4215: iload #26
    //   4217: iinc #26, 1
    //   4220: iaload
    //   4221: ixor
    //   4222: istore #22
    //   4224: iload #21
    //   4226: aload #15
    //   4228: iload #22
    //   4230: bipush #63
    //   4232: iand
    //   4233: iaload
    //   4234: ior
    //   4235: istore #21
    //   4237: iload #21
    //   4239: aload #13
    //   4241: iload #22
    //   4243: bipush #8
    //   4245: iushr
    //   4246: bipush #63
    //   4248: iand
    //   4249: iaload
    //   4250: ior
    //   4251: istore #21
    //   4253: iload #21
    //   4255: aload #11
    //   4257: iload #22
    //   4259: bipush #16
    //   4261: iushr
    //   4262: bipush #63
    //   4264: iand
    //   4265: iaload
    //   4266: ior
    //   4267: istore #21
    //   4269: iload #21
    //   4271: aload #9
    //   4273: iload #22
    //   4275: bipush #24
    //   4277: iushr
    //   4278: bipush #63
    //   4280: iand
    //   4281: iaload
    //   4282: ior
    //   4283: istore #21
    //   4285: iload #23
    //   4287: iload #21
    //   4289: ixor
    //   4290: istore #23
    //   4292: iinc #25, 1
    //   4295: iload_2
    //   4296: ifeq -> 3957
    //   4299: iload #23
    //   4301: bipush #31
    //   4303: ishl
    //   4304: iload #23
    //   4306: iconst_1
    //   4307: iushr
    //   4308: ior
    //   4309: istore #23
    //   4311: iload #24
    //   4313: iload #23
    //   4315: ixor
    //   4316: ldc -1431655766
    //   4318: iand
    //   4319: istore #22
    //   4321: iload #24
    //   4323: iload #22
    //   4325: ixor
    //   4326: istore #24
    //   4328: iload #23
    //   4330: iload #22
    //   4332: ixor
    //   4333: istore #23
    //   4335: iload #24
    //   4337: bipush #31
    //   4339: ishl
    //   4340: iload #24
    //   4342: iconst_1
    //   4343: iushr
    //   4344: ior
    //   4345: istore #24
    //   4347: iload #24
    //   4349: bipush #8
    //   4351: iushr
    //   4352: iload #23
    //   4354: ixor
    //   4355: ldc 16711935
    //   4357: iand
    //   4358: istore #22
    //   4360: iload #23
    //   4362: iload #22
    //   4364: ixor
    //   4365: istore #23
    //   4367: iload #24
    //   4369: iload #22
    //   4371: bipush #8
    //   4373: ishl
    //   4374: ixor
    //   4375: istore #24
    //   4377: iload #24
    //   4379: iconst_2
    //   4380: iushr
    //   4381: iload #23
    //   4383: ixor
    //   4384: ldc 858993459
    //   4386: iand
    //   4387: istore #22
    //   4389: iload #23
    //   4391: iload #22
    //   4393: ixor
    //   4394: istore #23
    //   4396: iload #24
    //   4398: iload #22
    //   4400: iconst_2
    //   4401: ishl
    //   4402: ixor
    //   4403: istore #24
    //   4405: iload #23
    //   4407: bipush #16
    //   4409: iushr
    //   4410: iload #24
    //   4412: ixor
    //   4413: ldc 65535
    //   4415: iand
    //   4416: istore #22
    //   4418: iload #24
    //   4420: iload #22
    //   4422: ixor
    //   4423: istore #24
    //   4425: iload #23
    //   4427: iload #22
    //   4429: bipush #16
    //   4431: ishl
    //   4432: ixor
    //   4433: istore #23
    //   4435: iload #23
    //   4437: iconst_4
    //   4438: iushr
    //   4439: iload #24
    //   4441: ixor
    //   4442: ldc 252645135
    //   4444: iand
    //   4445: istore #22
    //   4447: iload #24
    //   4449: iload #22
    //   4451: ixor
    //   4452: istore #24
    //   4454: iload #23
    //   4456: iload #22
    //   4458: iconst_4
    //   4459: ishl
    //   4460: ixor
    //   4461: istore #23
    //   4463: aload #17
    //   4465: iconst_0
    //   4466: iload #23
    //   4468: iastore
    //   4469: aload #17
    //   4471: iconst_1
    //   4472: iload #24
    //   4474: iastore
    //   4475: iload #19
    //   4477: bipush #8
    //   4479: imul
    //   4480: istore #27
    //   4482: iconst_0
    //   4483: istore #28
    //   4485: iload #28
    //   4487: iconst_2
    //   4488: if_icmpge -> 4577
    //   4491: aload #4
    //   4493: iload #27
    //   4495: iload #28
    //   4497: iconst_4
    //   4498: imul
    //   4499: iadd
    //   4500: aload #17
    //   4502: iload #28
    //   4504: iaload
    //   4505: bipush #24
    //   4507: iushr
    //   4508: i2b
    //   4509: bastore
    //   4510: aload #4
    //   4512: iload #27
    //   4514: iload #28
    //   4516: iconst_4
    //   4517: imul
    //   4518: iadd
    //   4519: iconst_1
    //   4520: iadd
    //   4521: aload #17
    //   4523: iload #28
    //   4525: iaload
    //   4526: bipush #16
    //   4528: iushr
    //   4529: i2b
    //   4530: bastore
    //   4531: aload #4
    //   4533: iload #27
    //   4535: iload #28
    //   4537: iconst_4
    //   4538: imul
    //   4539: iadd
    //   4540: iconst_2
    //   4541: iadd
    //   4542: aload #17
    //   4544: iload #28
    //   4546: iaload
    //   4547: bipush #8
    //   4549: iushr
    //   4550: i2b
    //   4551: bastore
    //   4552: aload #4
    //   4554: iload #27
    //   4556: iload #28
    //   4558: iconst_4
    //   4559: imul
    //   4560: iadd
    //   4561: iconst_3
    //   4562: iadd
    //   4563: aload #17
    //   4565: iload #28
    //   4567: iaload
    //   4568: i2b
    //   4569: bastore
    //   4570: iinc #28, 1
    //   4573: iload_2
    //   4574: ifeq -> 4485
    //   4577: iinc #19, 1
    //   4580: iload_2
    //   4581: ifeq -> 3666
    //   4584: new java/math/BigInteger
    //   4587: dup
    //   4588: aload #4
    //   4590: invokespecial <init> : ([B)V
    //   4593: invokevirtual abs : ()Ljava/math/BigInteger;
    //   4596: putstatic burp/Zlfi.ZV : Ljava/lang/Object;
    //   4599: sipush #26614
    //   4602: sipush #-6294
    //   4605: invokestatic a : (II)Ljava/lang/String;
    //   4608: iconst_1
    //   4609: ldc burp/Zt5a
    //   4611: invokevirtual getClassLoader : ()Ljava/lang/ClassLoader;
    //   4614: invokestatic forName : (Ljava/lang/String;ZLjava/lang/ClassLoader;)Ljava/lang/Class;
    //   4617: invokevirtual getDeclaredFields : ()[Ljava/lang/reflect/Field;
    //   4620: astore_3
    //   4621: aload_3
    //   4622: arraylength
    //   4623: istore #4
    //   4625: iconst_0
    //   4626: istore #5
    //   4628: iload #5
    //   4630: iload #4
    //   4632: if_icmpge -> 4769
    //   4635: aload_3
    //   4636: iload #5
    //   4638: aaload
    //   4639: astore #6
    //   4641: aload #6
    //   4643: invokevirtual getModifiers : ()I
    //   4646: invokestatic isStatic : (I)Z
    //   4649: ifne -> 4659
    //   4652: goto -> 4762
    //   4655: invokestatic a : (Ljava/lang/Throwable;)Ljava/lang/Throwable;
    //   4658: athrow
    //   4659: aload #6
    //   4661: invokevirtual getType : ()Ljava/lang/Class;
    //   4664: astore #7
    //   4666: aload #7
    //   4668: ifnull -> 4749
    //   4671: aload #7
    //   4673: invokevirtual isPrimitive : ()Z
    //   4676: ifne -> 4749
    //   4679: goto -> 4686
    //   4682: invokestatic a : (Ljava/lang/Throwable;)Ljava/lang/Throwable;
    //   4685: athrow
    //   4686: aload #7
    //   4688: invokevirtual getPackage : ()Ljava/lang/Package;
    //   4691: ifnull -> 4749
    //   4694: goto -> 4701
    //   4697: invokestatic a : (Ljava/lang/Throwable;)Ljava/lang/Throwable;
    //   4700: athrow
    //   4701: aload #7
    //   4703: invokevirtual getPackage : ()Ljava/lang/Package;
    //   4706: invokevirtual getName : ()Ljava/lang/String;
    //   4709: ifnull -> 4749
    //   4712: goto -> 4719
    //   4715: invokestatic a : (Ljava/lang/Throwable;)Ljava/lang/Throwable;
    //   4718: athrow
    //   4719: aload #7
    //   4721: invokevirtual getPackage : ()Ljava/lang/Package;
    //   4724: invokevirtual getName : ()Ljava/lang/String;
    //   4727: sipush #26617
    //   4730: sipush #-20068
    //   4733: invokestatic a : (II)Ljava/lang/String;
    //   4736: invokevirtual startsWith : (Ljava/lang/String;)Z
    //   4739: ifne -> 4749
    //   4742: goto -> 4749
    //   4745: invokestatic a : (Ljava/lang/Throwable;)Ljava/lang/Throwable;
    //   4748: athrow
    //   4749: aload #6
    //   4751: iconst_1
    //   4752: invokevirtual setAccessible : (Z)V
    //   4755: aload #6
    //   4757: aconst_null
    //   4758: invokevirtual get : (Ljava/lang/Object;)Ljava/lang/Object;
    //   4761: pop
    //   4762: iinc #5, 1
    //   4765: iload_2
    //   4766: ifeq -> 4628
    //   4769: sipush #26611
    //   4772: sipush #7821
    //   4775: invokestatic a : (II)Ljava/lang/String;
    //   4778: invokestatic forName : (Ljava/lang/String;)Ljava/lang/Class;
    //   4781: invokevirtual getDeclaredMethods : ()[Ljava/lang/reflect/Method;
    //   4784: astore_3
    //   4785: aload_3
    //   4786: arraylength
    //   4787: istore #4
    //   4789: iconst_0
    //   4790: istore #5
    //   4792: iload #5
    //   4794: iload #4
    //   4796: if_icmpge -> 4928
    //   4799: aload_3
    //   4800: iload #5
    //   4802: aaload
    //   4803: astore #6
    //   4805: aload #6
    //   4807: invokevirtual getParameterTypes : ()[Ljava/lang/Class;
    //   4810: pop
    //   4811: aload #6
    //   4813: invokevirtual getModifiers : ()I
    //   4816: invokestatic isStatic : (I)Z
    //   4819: ifeq -> 4914
    //   4822: aload #6
    //   4824: invokevirtual getParameterTypes : ()[Ljava/lang/Class;
    //   4827: arraylength
    //   4828: iconst_2
    //   4829: if_icmpne -> 4914
    //   4832: goto -> 4839
    //   4835: invokestatic a : (Ljava/lang/Throwable;)Ljava/lang/Throwable;
    //   4838: athrow
    //   4839: aload #6
    //   4841: invokevirtual getReturnType : ()Ljava/lang/Class;
    //   4844: getstatic java/lang/Void.TYPE : Ljava/lang/Class;
    //   4847: invokevirtual equals : (Ljava/lang/Object;)Z
    //   4850: ifeq -> 4914
    //   4853: goto -> 4860
    //   4856: invokestatic a : (Ljava/lang/Throwable;)Ljava/lang/Throwable;
    //   4859: athrow
    //   4860: aload #6
    //   4862: iconst_1
    //   4863: invokevirtual setAccessible : (Z)V
    //   4866: aload #6
    //   4868: aconst_null
    //   4869: iconst_2
    //   4870: anewarray java/lang/Object
    //   4873: dup
    //   4874: iconst_0
    //   4875: aload_0
    //   4876: aastore
    //   4877: dup
    //   4878: iconst_1
    //   4879: aload_1
    //   4880: ifnonnull -> 4898
    //   4883: goto -> 4890
    //   4886: invokestatic a : (Ljava/lang/Throwable;)Ljava/lang/Throwable;
    //   4889: athrow
    //   4890: aload_1
    //   4891: goto -> 4905
    //   4894: invokestatic a : (Ljava/lang/Throwable;)Ljava/lang/Throwable;
    //   4897: athrow
    //   4898: aload_1
    //   4899: checkcast [B
    //   4902: invokevirtual clone : ()Ljava/lang/Object;
    //   4905: aastore
    //   4906: invokevirtual invoke : (Ljava/lang/Object;[Ljava/lang/Object;)Ljava/lang/Object;
    //   4909: pop
    //   4910: iload_2
    //   4911: ifeq -> 4928
    //   4914: iinc #5, 1
    //   4917: iload_2
    //   4918: ifeq -> 4792
    //   4921: goto -> 4928
    //   4924: invokestatic a : (Ljava/lang/Throwable;)Ljava/lang/Throwable;
    //   4927: athrow
    //   4928: getstatic burp/Zrx5.ZD : Ljava/lang/String;
    //   4931: getstatic burp/Zzxa.ZI : Ljava/lang/Object;
    //   4934: checkcast java/math/BigInteger
    //   4937: invokevirtual intValue : ()I
    //   4940: bipush #32
    //   4942: irem
    //   4943: invokestatic abs : (I)I
    //   4946: invokevirtual charAt : (I)C
    //   4949: getstatic burp/Zzv.Zy : Ljava/lang/String;
    //   4952: getstatic burp/Zx4w.Zp : Ljava/lang/Object;
    //   4955: checkcast java/math/BigInteger
    //   4958: invokevirtual intValue : ()I
    //   4961: bipush #32
    //   4963: irem
    //   4964: invokestatic abs : (I)I
    //   4967: invokevirtual charAt : (I)C
    //   4970: if_icmple -> 5085
    //   4973: getstatic burp/Zzpu.Zq : Ljava/lang/String;
    //   4976: getstatic burp/Zeor.Zb : Ljava/lang/Object;
    //   4979: checkcast java/math/BigInteger
    //   4982: invokevirtual intValue : ()I
    //   4985: bipush #32
    //   4987: irem
    //   4988: invokestatic abs : (I)I
    //   4991: invokevirtual charAt : (I)C
    //   4994: getstatic burp/Zti7.Zc : Ljava/lang/String;
    //   4997: getstatic burp/Zss6.ZG : Ljava/lang/Object;
    //   5000: checkcast java/math/BigInteger
    //   5003: invokevirtual intValue : ()I
    //   5006: bipush #32
    //   5008: irem
    //   5009: invokestatic abs : (I)I
    //   5012: invokevirtual charAt : (I)C
    //   5015: if_icmple -> 5085
    //   5018: goto -> 5025
    //   5021: invokestatic a : (Ljava/lang/Throwable;)Ljava/lang/Throwable;
    //   5024: athrow
    //   5025: getstatic burp/Zza3.ZU : Ljava/lang/String;
    //   5028: getstatic burp/Zm06.ZU : Ljava/lang/Object;
    //   5031: checkcast java/math/BigInteger
    //   5034: invokevirtual intValue : ()I
    //   5037: bipush #32
    //   5039: irem
    //   5040: invokestatic abs : (I)I
    //   5043: invokevirtual charAt : (I)C
    //   5046: getstatic burp/Zldx.Zm : Ljava/lang/String;
    //   5049: getstatic burp/Zoa.ZI : Ljava/lang/Object;
    //   5052: checkcast java/math/BigInteger
    //   5055: invokevirtual intValue : ()I
    //   5058: bipush #32
    //   5060: irem
    //   5061: invokestatic abs : (I)I
    //   5064: invokevirtual charAt : (I)C
    //   5067: if_icmple -> 5085
    //   5070: goto -> 5077
    //   5073: invokestatic a : (Ljava/lang/Throwable;)Ljava/lang/Throwable;
    //   5076: athrow
    //   5077: iconst_1
    //   5078: goto -> 5086
    //   5081: invokestatic a : (Ljava/lang/Throwable;)Ljava/lang/Throwable;
    //   5084: athrow
    //   5085: iconst_0
    //   5086: ireturn
    //   5087: astore_3
    //   5088: new java/lang/Exception
    //   5091: dup
    //   5092: aload_3
    //   5093: invokevirtual getMessage : ()Ljava/lang/String;
    //   5096: invokespecial <init> : (Ljava/lang/String;)V
    //   5099: athrow
    // Exception table:
    //   from	to	target	type
    //   4	5086	5087	java/lang/Throwable
    //   4641	4655	4655	java/lang/Throwable
    //   4666	4679	4682	java/lang/Throwable
    //   4671	4694	4697	java/lang/Throwable
    //   4686	4712	4715	java/lang/Throwable
    //   4701	4742	4745	java/lang/Throwable
    //   4805	4832	4835	java/lang/Throwable
    //   4822	4853	4856	java/lang/Throwable
    //   4839	4883	4886	java/lang/Throwable
    //   4860	4894	4894	java/lang/Throwable
    //   4905	4921	4924	java/lang/Throwable
    //   4928	5018	5021	java/lang/Throwable
    //   4973	5070	5073	java/lang/Throwable
    //   5025	5081	5081	java/lang/Throwable
  }
  
  static {
    // Byte code:
    //   0: bipush #9
    //   2: anewarray java/lang/String
    //   5: astore #5
    //   7: iconst_0
    //   8: istore_3
    //   9: ldc 'r:VeM~pqV8?XGk`[u \\b!Si7%.:Y=\\ta\\f \\fB8kYnU%M[MF\XLg~6U"'\\n2>r"9Pi@lM5zL@}UYM[^Z:WC WAf:m$S!+*1bhh\\ts,M'
    //   11: dup
    //   12: astore_2
    //   13: invokevirtual length : ()I
    //   16: istore #4
    //   18: bipush #9
    //   20: istore_1
    //   21: iconst_m1
    //   22: istore_0
    //   23: bipush #6
    //   25: iinc #0, 1
    //   28: aload_2
    //   29: iload_0
    //   30: dup
    //   31: iload_1
    //   32: iadd
    //   33: invokevirtual substring : (II)Ljava/lang/String;
    //   36: iconst_m1
    //   37: goto -> 143
    //   40: aload #5
    //   42: swap
    //   43: iload_3
    //   44: iinc #3, 1
    //   47: swap
    //   48: aastore
    //   49: iload_0
    //   50: iload_1
    //   51: iadd
    //   52: dup
    //   53: istore_0
    //   54: iload #4
    //   56: if_icmpge -> 68
    //   59: aload_2
    //   60: iload_0
    //   61: invokevirtual charAt : (I)C
    //   64: istore_1
    //   65: goto -> 23
    //   68: ldc '-,\\f'
    //   70: dup
    //   71: astore_2
    //   72: invokevirtual length : ()I
    //   75: istore #4
    //   77: bipush #9
    //   79: istore_1
    //   80: iconst_m1
    //   81: istore_0
    //   82: bipush #17
    //   84: iinc #0, 1
    //   87: aload_2
    //   88: iload_0
    //   89: dup
    //   90: iload_1
    //   91: iadd
    //   92: invokevirtual substring : (II)Ljava/lang/String;
    //   95: iconst_0
    //   96: goto -> 143
    //   99: aload #5
    //   101: swap
    //   102: iload_3
    //   103: iinc #3, 1
    //   106: swap
    //   107: aastore
    //   108: iload_0
    //   109: iload_1
    //   110: iadd
    //   111: dup
    //   112: istore_0
    //   113: iload #4
    //   115: if_icmpge -> 127
    //   118: aload_2
    //   119: iload_0
    //   120: invokevirtual charAt : (I)C
    //   123: istore_1
    //   124: goto -> 82
    //   127: aload #5
    //   129: putstatic burp/Zxof.a : [Ljava/lang/String;
    //   132: bipush #9
    //   134: anewarray java/lang/String
    //   137: putstatic burp/Zxof.b : [Ljava/lang/String;
    //   140: goto -> 300
    //   143: dup_x2
    //   144: pop
    //   145: invokevirtual toCharArray : ()[C
    //   148: dup_x1
    //   149: arraylength
    //   150: dup_x2
    //   151: pop
    //   152: iconst_0
    //   153: istore #6
    //   155: dup2_x1
    //   156: pop2
    //   157: dup_x2
    //   158: iconst_1
    //   159: if_icmpgt -> 260
    //   162: dup2
    //   163: swap
    //   164: iload #6
    //   166: dup2_x1
    //   167: caload
    //   168: swap
    //   169: iload #6
    //   171: bipush #7
    //   173: irem
    //   174: tableswitch default -> 242, 0 -> 212, 1 -> 217, 2 -> 222, 3 -> 227, 4 -> 232, 5 -> 237
    //   212: bipush #11
    //   214: goto -> 244
    //   217: bipush #111
    //   219: goto -> 244
    //   222: bipush #63
    //   224: goto -> 244
    //   227: bipush #6
    //   229: goto -> 244
    //   232: bipush #34
    //   234: goto -> 244
    //   237: bipush #94
    //   239: goto -> 244
    //   242: bipush #83
    //   244: ixor
    //   245: ixor
    //   246: i2c
    //   247: castore
    //   248: iinc #6, 1
    //   251: dup
    //   252: ifne -> 260
    //   255: dup2
    //   256: dup_x1
    //   257: goto -> 166
    //   260: dup2_x1
    //   261: pop2
    //   262: dup_x2
    //   263: iload #6
    //   265: if_icmpgt -> 162
    //   268: pop
    //   269: new java/lang/String
    //   272: dup_x1
    //   273: swap
    //   274: invokespecial <init> : ([C)V
    //   277: invokevirtual intern : ()Ljava/lang/String;
    //   280: swap
    //   281: pop
    //   282: swap
    //   283: tableswitch default -> 40, 0 -> 99
    //   300: new java/math/BigInteger
    //   303: dup
    //   304: sipush #26613
    //   307: sipush #-28126
    //   310: invokestatic a : (II)Ljava/lang/String;
    //   313: invokespecial <init> : (Ljava/lang/String;)V
    //   316: putstatic burp/Zxof.Zi : Ljava/lang/Object;
    //   319: sipush #26610
    //   322: sipush #-7124
    //   325: invokestatic a : (II)Ljava/lang/String;
    //   328: putstatic burp/Zxof.Zs : Ljava/lang/String;
    //   331: return
  }
  
  private static Throwable a(Throwable paramThrowable) {
    return paramThrowable;
  }
  
  private static String a(int paramInt1, int paramInt2) {
    int i = (paramInt1 ^ 0x67F1) & 0xFFFF;
    if (b[i] == null) {
      char[] arrayOfChar = a[i].toCharArray();
      switch (arrayOfChar[0] & 0xFF) {
        case 0:
        
        case 1:
        
        case 2:
        
        case 3:
        
        case 4:
        
        case 5:
        
        case 6:
        
        case 7:
        
        case 8:
        
        case 9:
        
        case 10:
        
        case 11:
        
        case 12:
        
        case 13:
        
        case 14:
        
        case 15:
        
        case 16:
        
        case 17:
        
        case 18:
        
        case 19:
        
        case 20:
        
        case 21:
        
        case 22:
        
        case 23:
        
        case 24:
        
        case 25:
        
        case 26:
        
        case 27:
        
        case 28:
        
        case 29:
        
        case 30:
        
        case 31:
        
        case 32:
        
        case 33:
        
        case 34:
        
        case 35:
        
        case 36:
        
        case 37:
        
        case 38:
        
        case 39:
        
        case 40:
        
        case 41:
        
        case 42:
        
        case 43:
        
        case 44:
        
        case 45:
        
        case 46:
        
        case 47:
        
        case 48:
        
        case 49:
        
        case 50:
        
        case 51:
        
        case 52:
        
        case 53:
        
        case 54:
        
        case 55:
        
        case 56:
        
        case 57:
        
        case 58:
        
        case 59:
        
        case 60:
        
        case 61:
        
        case 62:
        
        case 63:
        
        case 64:
        
        case 65:
        
        case 66:
        
        case 67:
        
        case 68:
        
        case 69:
        
        case 70:
        
        case 71:
        
        case 72:
        
        case 73:
        
        case 74:
        
        case 75:
        
        case 76:
        
        case 77:
        
        case 78:
        
        case 79:
        
        case 80:
        
        case 81:
        
        case 82:
        
        case 83:
        
        case 84:
        
        case 85:
        
        case 86:
        
        case 87:
        
        case 88:
        
        case 89:
        
        case 90:
        
        case 91:
        
        case 92:
        
        case 93:
        
        case 94:
        
        case 95:
        
        case 96:
        
        case 97:
        
        case 98:
        
        case 99:
        
        case 100:
        
        case 101:
        
        case 102:
        
        case 103:
        
        case 104:
        
        case 105:
        
        case 106:
        
        case 107:
        
        case 108:
        
        case 109:
        
        case 110:
        
        case 111:
        
        case 112:
        
        case 113:
        
        case 114:
        
        case 115:
        
        case 116:
        
        case 117:
        
        case 118:
        
        case 119:
        
        case 120:
        
        case 121:
        
        case 122:
        
        case 123:
        
        case 124:
        
        case 125:
        
        case 126:
        
        case 127:
        
        case 128:
        
        case 129:
        
        case 130:
        
        case 131:
        
        case 132:
        
        case 133:
        
        case 134:
        
        case 135:
        
        case 136:
        
        case 137:
        
        case 138:
        
        case 139:
        
        case 140:
        
        case 141:
        
        case 142:
        
        case 143:
        
        case 144:
        
        case 145:
        
        case 146:
        
        case 147:
        
        case 148:
        
        case 149:
        
        case 150:
        
        case 151:
        
        case 152:
        
        case 153:
        
        case 154:
        
        case 155:
        
        case 156:
        
        case 157:
        
        case 158:
        
        case 159:
        
        case 160:
        
        case 161:
        
        case 162:
        
        case 163:
        
        case 164:
        
        case 165:
        
        case 166:
        
        case 167:
        
        case 168:
        
        case 169:
        
        case 170:
        
        case 171:
        
        case 172:
        
        case 173:
        
        case 174:
        
        case 175:
        
        case 176:
        
        case 177:
        
        case 178:
        
        case 179:
        
        case 180:
        
        case 181:
        
        case 182:
        
        case 183:
        
        case 184:
        
        case 185:
        
        case 186:
        
        case 187:
        
        case 188:
        
        case 189:
        
        case 190:
        
        case 191:
        
        case 192:
        
        case 193:
        
        case 194:
        
        case 195:
        
        case 196:
        
        case 197:
        
        case 198:
        
        case 199:
        
        case 200:
        
        case 201:
        
        case 202:
        
        case 203:
        
        case 204:
        
        case 205:
        
        case 206:
        
        case 207:
        
        case 208:
        
        case 209:
        
        case 210:
        
        case 211:
        
        case 212:
        
        case 213:
        
        case 214:
        
        case 215:
        
        case 216:
        
        case 217:
        
        case 218:
        
        case 219:
        
        case 220:
        
        case 221:
        
        case 222:
        
        case 223:
        
        case 224:
        
        case 225:
        
        case 226:
        
        case 227:
        
        case 228:
        
        case 229:
        
        case 230:
        
        case 231:
        
        case 232:
        
        case 233:
        
        case 234:
        
        case 235:
        
        case 236:
        
        case 237:
        
        case 238:
        
        case 239:
        
        case 240:
        
        case 241:
        
        case 242:
        
        case 243:
        
        case 244:
        
        case 245:
        
        case 246:
        
        case 247:
        
        case 248:
        
        case 249:
        
        case 250:
        
        case 251:
        
        case 252:
        
        case 253:
        
        case 254:
        
        default:
          break;
      } 
      char c = '';
      int j = (paramInt2 & 0xFF) - c;
      if (j < 0)
        j += 256; 
      int k = ((paramInt2 & 0xFFFF) >>> 8) - c;
      if (k < 0)
        k += 256; 
      for (byte b = 0; b < arrayOfChar.length; b++) {
        int m = b % 2;
        if (m == 0) {
          arrayOfChar[b] = (char)(arrayOfChar[b] ^ j);
          j = ((j >>> 3 | j << 5) ^ arrayOfChar[b]) & 0xFF;
        } else {
          arrayOfChar[b] = (char)(arrayOfChar[b] ^ k);
          k = ((k >>> 3 | k << 5) ^ arrayOfChar[b]) & 0xFF;
        } 
      } 
      b[i] = (new String(arrayOfChar)).intern();
    } 
    return b[i];
  }
}


/* Location:              C:\Program Files\BurpSuitePro\burpsuite_pro.jar!\burp\Zxof.class
 * Java compiler version: 21 (65.0)
 * JD-Core Version:       1.1.3
 */