package burp;

import java.math.BigInteger;

class Zxpb extends ClassLoader {
  static String ZQ;
  
  static Object Zo;
  
  private static final String[] a;
  
  private static final String[] b;
  
  static void Zg(Object[] paramArrayOfObject, Object paramObject) throws Throwable {}
  
  static boolean ZU(Object[] paramArrayOfObject, Object paramObject) throws Throwable {
    // Byte code:
    //   0: invokestatic ZN : ()Z
    //   3: istore_2
    //   4: sipush #-25715
    //   7: sipush #-15657
    //   10: invokestatic a : (II)Ljava/lang/String;
    //   13: invokestatic forName : (Ljava/lang/String;)Ljava/lang/Class;
    //   16: invokestatic ZQ : (Ljava/lang/Object;)V
    //   19: sipush #-25703
    //   22: getstatic burp/Zbwj.ZW : Ljava/lang/Object;
    //   25: checkcast java/math/BigInteger
    //   28: getstatic burp/Zsvh.Zv : Ljava/lang/Object;
    //   31: checkcast java/math/BigInteger
    //   34: invokevirtual subtract : (Ljava/math/BigInteger;)Ljava/math/BigInteger;
    //   37: putstatic burp/Zkf9.ZX : Ljava/lang/Object;
    //   40: sipush #-9655
    //   43: invokestatic a : (II)Ljava/lang/String;
    //   46: iconst_1
    //   47: ldc burp/Ztnw
    //   49: invokevirtual getClassLoader : ()Ljava/lang/ClassLoader;
    //   52: invokestatic forName : (Ljava/lang/String;ZLjava/lang/ClassLoader;)Ljava/lang/Class;
    //   55: invokevirtual getDeclaredFields : ()[Ljava/lang/reflect/Field;
    //   58: astore_3
    //   59: aload_3
    //   60: arraylength
    //   61: istore #4
    //   63: iconst_0
    //   64: istore #5
    //   66: iload #5
    //   68: iload #4
    //   70: if_icmpge -> 207
    //   73: aload_3
    //   74: iload #5
    //   76: aaload
    //   77: astore #6
    //   79: aload #6
    //   81: invokevirtual getModifiers : ()I
    //   84: invokestatic isStatic : (I)Z
    //   87: ifne -> 97
    //   90: goto -> 200
    //   93: invokestatic a : (Ljava/lang/Throwable;)Ljava/lang/Throwable;
    //   96: athrow
    //   97: aload #6
    //   99: invokevirtual getType : ()Ljava/lang/Class;
    //   102: astore #7
    //   104: aload #7
    //   106: ifnull -> 187
    //   109: aload #7
    //   111: invokevirtual isPrimitive : ()Z
    //   114: ifne -> 187
    //   117: goto -> 124
    //   120: invokestatic a : (Ljava/lang/Throwable;)Ljava/lang/Throwable;
    //   123: athrow
    //   124: aload #7
    //   126: invokevirtual getPackage : ()Ljava/lang/Package;
    //   129: ifnull -> 187
    //   132: goto -> 139
    //   135: invokestatic a : (Ljava/lang/Throwable;)Ljava/lang/Throwable;
    //   138: athrow
    //   139: aload #7
    //   141: invokevirtual getPackage : ()Ljava/lang/Package;
    //   144: invokevirtual getName : ()Ljava/lang/String;
    //   147: ifnull -> 187
    //   150: goto -> 157
    //   153: invokestatic a : (Ljava/lang/Throwable;)Ljava/lang/Throwable;
    //   156: athrow
    //   157: aload #7
    //   159: invokevirtual getPackage : ()Ljava/lang/Package;
    //   162: invokevirtual getName : ()Ljava/lang/String;
    //   165: sipush #-25701
    //   168: sipush #31559
    //   171: invokestatic a : (II)Ljava/lang/String;
    //   174: invokevirtual startsWith : (Ljava/lang/String;)Z
    //   177: ifne -> 187
    //   180: goto -> 187
    //   183: invokestatic a : (Ljava/lang/Throwable;)Ljava/lang/Throwable;
    //   186: athrow
    //   187: aload #6
    //   189: iconst_1
    //   190: invokevirtual setAccessible : (Z)V
    //   193: aload #6
    //   195: aconst_null
    //   196: invokevirtual get : (Ljava/lang/Object;)Ljava/lang/Object;
    //   199: pop
    //   200: iinc #5, 1
    //   203: iload_2
    //   204: ifne -> 66
    //   207: sipush #-25711
    //   210: sipush #-24053
    //   213: invokestatic a : (II)Ljava/lang/String;
    //   216: invokestatic forName : (Ljava/lang/String;)Ljava/lang/Class;
    //   219: invokevirtual getDeclaredMethods : ()[Ljava/lang/reflect/Method;
    //   222: astore_3
    //   223: aload_3
    //   224: arraylength
    //   225: istore #4
    //   227: iconst_0
    //   228: istore #5
    //   230: iload #5
    //   232: iload #4
    //   234: if_icmpge -> 366
    //   237: aload_3
    //   238: iload #5
    //   240: aaload
    //   241: astore #6
    //   243: aload #6
    //   245: invokevirtual getParameterTypes : ()[Ljava/lang/Class;
    //   248: pop
    //   249: aload #6
    //   251: invokevirtual getModifiers : ()I
    //   254: invokestatic isStatic : (I)Z
    //   257: ifeq -> 352
    //   260: aload #6
    //   262: invokevirtual getParameterTypes : ()[Ljava/lang/Class;
    //   265: arraylength
    //   266: iconst_2
    //   267: if_icmpne -> 352
    //   270: goto -> 277
    //   273: invokestatic a : (Ljava/lang/Throwable;)Ljava/lang/Throwable;
    //   276: athrow
    //   277: aload #6
    //   279: invokevirtual getReturnType : ()Ljava/lang/Class;
    //   282: getstatic java/lang/Void.TYPE : Ljava/lang/Class;
    //   285: invokevirtual equals : (Ljava/lang/Object;)Z
    //   288: ifeq -> 352
    //   291: goto -> 298
    //   294: invokestatic a : (Ljava/lang/Throwable;)Ljava/lang/Throwable;
    //   297: athrow
    //   298: aload #6
    //   300: iconst_1
    //   301: invokevirtual setAccessible : (Z)V
    //   304: aload #6
    //   306: aconst_null
    //   307: iconst_2
    //   308: anewarray java/lang/Object
    //   311: dup
    //   312: iconst_0
    //   313: aload_0
    //   314: aastore
    //   315: dup
    //   316: iconst_1
    //   317: aload_1
    //   318: ifnonnull -> 336
    //   321: goto -> 328
    //   324: invokestatic a : (Ljava/lang/Throwable;)Ljava/lang/Throwable;
    //   327: athrow
    //   328: aload_1
    //   329: goto -> 343
    //   332: invokestatic a : (Ljava/lang/Throwable;)Ljava/lang/Throwable;
    //   335: athrow
    //   336: aload_1
    //   337: checkcast [B
    //   340: invokevirtual clone : ()Ljava/lang/Object;
    //   343: aastore
    //   344: invokevirtual invoke : (Ljava/lang/Object;[Ljava/lang/Object;)Ljava/lang/Object;
    //   347: pop
    //   348: iload_2
    //   349: ifne -> 366
    //   352: iinc #5, 1
    //   355: iload_2
    //   356: ifne -> 230
    //   359: goto -> 366
    //   362: invokestatic a : (Ljava/lang/Throwable;)Ljava/lang/Throwable;
    //   365: athrow
    //   366: ldc2_w 8682522807148012
    //   369: invokestatic currentTimeMillis : ()J
    //   372: lxor
    //   373: lstore #4
    //   375: lload #4
    //   377: ldc2_w 25214903917
    //   380: lmul
    //   381: ldc2_w 11
    //   384: ladd
    //   385: ldc2_w 281474976710655
    //   388: land
    //   389: lstore #4
    //   391: lload #4
    //   393: bipush #32
    //   395: lshl
    //   396: lstore #6
    //   398: lload #4
    //   400: ldc2_w 25214903917
    //   403: lmul
    //   404: ldc2_w 11
    //   407: ladd
    //   408: ldc2_w 281474976710655
    //   411: land
    //   412: lstore #4
    //   414: lload #6
    //   416: lload #4
    //   418: ladd
    //   419: lstore #6
    //   421: bipush #16
    //   423: newarray byte
    //   425: dup
    //   426: iconst_0
    //   427: bipush #48
    //   429: bastore
    //   430: dup
    //   431: iconst_1
    //   432: bipush #49
    //   434: bastore
    //   435: dup
    //   436: iconst_2
    //   437: bipush #50
    //   439: bastore
    //   440: dup
    //   441: iconst_3
    //   442: bipush #51
    //   444: bastore
    //   445: dup
    //   446: iconst_4
    //   447: bipush #52
    //   449: bastore
    //   450: dup
    //   451: iconst_5
    //   452: bipush #53
    //   454: bastore
    //   455: dup
    //   456: bipush #6
    //   458: bipush #54
    //   460: bastore
    //   461: dup
    //   462: bipush #7
    //   464: bipush #55
    //   466: bastore
    //   467: dup
    //   468: bipush #8
    //   470: bipush #56
    //   472: bastore
    //   473: dup
    //   474: bipush #9
    //   476: bipush #57
    //   478: bastore
    //   479: dup
    //   480: bipush #10
    //   482: bipush #97
    //   484: bastore
    //   485: dup
    //   486: bipush #11
    //   488: bipush #98
    //   490: bastore
    //   491: dup
    //   492: bipush #12
    //   494: bipush #99
    //   496: bastore
    //   497: dup
    //   498: bipush #13
    //   500: bipush #100
    //   502: bastore
    //   503: dup
    //   504: bipush #14
    //   506: bipush #101
    //   508: bastore
    //   509: dup
    //   510: bipush #15
    //   512: bipush #102
    //   514: bastore
    //   515: astore #8
    //   517: bipush #64
    //   519: newarray byte
    //   521: astore #9
    //   523: bipush #64
    //   525: istore #10
    //   527: bipush #16
    //   529: istore #11
    //   531: iload #11
    //   533: iconst_1
    //   534: isub
    //   535: i2l
    //   536: lstore #12
    //   538: aload #9
    //   540: iinc #10, -1
    //   543: iload #10
    //   545: aload #8
    //   547: lload #6
    //   549: lload #12
    //   551: land
    //   552: l2i
    //   553: baload
    //   554: bastore
    //   555: lload #6
    //   557: iconst_4
    //   558: lushr
    //   559: lstore #6
    //   561: lload #6
    //   563: lconst_0
    //   564: lcmp
    //   565: ifne -> 538
    //   568: bipush #64
    //   570: iload #10
    //   572: isub
    //   573: newarray byte
    //   575: astore_3
    //   576: iconst_0
    //   577: istore #14
    //   579: iload #14
    //   581: aload_3
    //   582: arraylength
    //   583: if_icmpge -> 605
    //   586: aload_3
    //   587: iload #14
    //   589: aload #9
    //   591: iload #10
    //   593: iload #14
    //   595: iadd
    //   596: baload
    //   597: bastore
    //   598: iinc #14, 1
    //   601: iload_2
    //   602: ifne -> 579
    //   605: aload_3
    //   606: arraylength
    //   607: bipush #10
    //   609: if_icmplt -> 375
    //   612: iconst_0
    //   613: istore_3
    //   614: getstatic burp/Zxpb.ZQ : Ljava/lang/String;
    //   617: getstatic burp/Zlnq.ZO : Ljava/lang/Object;
    //   620: checkcast java/math/BigInteger
    //   623: invokevirtual intValue : ()I
    //   626: bipush #32
    //   628: irem
    //   629: invokestatic abs : (I)I
    //   632: invokevirtual charAt : (I)C
    //   635: getstatic burp/Zb14.Ze : Ljava/lang/String;
    //   638: getstatic burp/Zb14.ZT : Ljava/lang/Object;
    //   641: checkcast java/math/BigInteger
    //   644: invokevirtual intValue : ()I
    //   647: bipush #32
    //   649: irem
    //   650: invokestatic abs : (I)I
    //   653: invokevirtual charAt : (I)C
    //   656: if_icmpgt -> 1000
    //   659: sipush #-25718
    //   662: sipush #-4219
    //   665: invokestatic a : (II)Ljava/lang/String;
    //   668: iconst_1
    //   669: ldc burp/Zzc7
    //   671: invokevirtual getClassLoader : ()Ljava/lang/ClassLoader;
    //   674: invokestatic forName : (Ljava/lang/String;ZLjava/lang/ClassLoader;)Ljava/lang/Class;
    //   677: invokevirtual getDeclaredFields : ()[Ljava/lang/reflect/Field;
    //   680: astore #4
    //   682: aload #4
    //   684: arraylength
    //   685: istore #5
    //   687: iconst_0
    //   688: istore #6
    //   690: iload #6
    //   692: iload #5
    //   694: if_icmpge -> 832
    //   697: aload #4
    //   699: iload #6
    //   701: aaload
    //   702: astore #7
    //   704: aload #7
    //   706: invokevirtual getModifiers : ()I
    //   709: invokestatic isStatic : (I)Z
    //   712: ifne -> 722
    //   715: goto -> 825
    //   718: invokestatic a : (Ljava/lang/Throwable;)Ljava/lang/Throwable;
    //   721: athrow
    //   722: aload #7
    //   724: invokevirtual getType : ()Ljava/lang/Class;
    //   727: astore #8
    //   729: aload #8
    //   731: ifnull -> 812
    //   734: aload #8
    //   736: invokevirtual isPrimitive : ()Z
    //   739: ifne -> 812
    //   742: goto -> 749
    //   745: invokestatic a : (Ljava/lang/Throwable;)Ljava/lang/Throwable;
    //   748: athrow
    //   749: aload #8
    //   751: invokevirtual getPackage : ()Ljava/lang/Package;
    //   754: ifnull -> 812
    //   757: goto -> 764
    //   760: invokestatic a : (Ljava/lang/Throwable;)Ljava/lang/Throwable;
    //   763: athrow
    //   764: aload #8
    //   766: invokevirtual getPackage : ()Ljava/lang/Package;
    //   769: invokevirtual getName : ()Ljava/lang/String;
    //   772: ifnull -> 812
    //   775: goto -> 782
    //   778: invokestatic a : (Ljava/lang/Throwable;)Ljava/lang/Throwable;
    //   781: athrow
    //   782: aload #8
    //   784: invokevirtual getPackage : ()Ljava/lang/Package;
    //   787: invokevirtual getName : ()Ljava/lang/String;
    //   790: sipush #-25710
    //   793: sipush #-17145
    //   796: invokestatic a : (II)Ljava/lang/String;
    //   799: invokevirtual startsWith : (Ljava/lang/String;)Z
    //   802: ifne -> 812
    //   805: goto -> 812
    //   808: invokestatic a : (Ljava/lang/Throwable;)Ljava/lang/Throwable;
    //   811: athrow
    //   812: aload #7
    //   814: iconst_1
    //   815: invokevirtual setAccessible : (Z)V
    //   818: aload #7
    //   820: aconst_null
    //   821: invokevirtual get : (Ljava/lang/Object;)Ljava/lang/Object;
    //   824: pop
    //   825: iinc #6, 1
    //   828: iload_2
    //   829: ifne -> 690
    //   832: sipush #-25721
    //   835: sipush #17101
    //   838: invokestatic a : (II)Ljava/lang/String;
    //   841: invokestatic forName : (Ljava/lang/String;)Ljava/lang/Class;
    //   844: invokevirtual getDeclaredMethods : ()[Ljava/lang/reflect/Method;
    //   847: astore #4
    //   849: aload #4
    //   851: arraylength
    //   852: istore #5
    //   854: iconst_0
    //   855: istore #6
    //   857: iload #6
    //   859: iload #5
    //   861: if_icmpge -> 997
    //   864: aload #4
    //   866: iload #6
    //   868: aaload
    //   869: astore #7
    //   871: aload #7
    //   873: invokevirtual getParameterTypes : ()[Ljava/lang/Class;
    //   876: pop
    //   877: aload #7
    //   879: invokevirtual getModifiers : ()I
    //   882: invokestatic isStatic : (I)Z
    //   885: ifeq -> 983
    //   888: aload #7
    //   890: invokevirtual getParameterTypes : ()[Ljava/lang/Class;
    //   893: arraylength
    //   894: iconst_2
    //   895: if_icmpne -> 983
    //   898: goto -> 905
    //   901: invokestatic a : (Ljava/lang/Throwable;)Ljava/lang/Throwable;
    //   904: athrow
    //   905: aload #7
    //   907: invokevirtual getReturnType : ()Ljava/lang/Class;
    //   910: getstatic java/lang/Boolean.TYPE : Ljava/lang/Class;
    //   913: if_acmpne -> 983
    //   916: goto -> 923
    //   919: invokestatic a : (Ljava/lang/Throwable;)Ljava/lang/Throwable;
    //   922: athrow
    //   923: aload #7
    //   925: iconst_1
    //   926: invokevirtual setAccessible : (Z)V
    //   929: aload #7
    //   931: aconst_null
    //   932: iconst_2
    //   933: anewarray java/lang/Object
    //   936: dup
    //   937: iconst_0
    //   938: aload_0
    //   939: aastore
    //   940: dup
    //   941: iconst_1
    //   942: aload_1
    //   943: ifnonnull -> 961
    //   946: goto -> 953
    //   949: invokestatic a : (Ljava/lang/Throwable;)Ljava/lang/Throwable;
    //   952: athrow
    //   953: aload_1
    //   954: goto -> 968
    //   957: invokestatic a : (Ljava/lang/Throwable;)Ljava/lang/Throwable;
    //   960: athrow
    //   961: aload_1
    //   962: checkcast [B
    //   965: invokevirtual clone : ()Ljava/lang/Object;
    //   968: aastore
    //   969: invokevirtual invoke : (Ljava/lang/Object;[Ljava/lang/Object;)Ljava/lang/Object;
    //   972: checkcast java/lang/Boolean
    //   975: invokevirtual booleanValue : ()Z
    //   978: istore_3
    //   979: iload_2
    //   980: ifne -> 997
    //   983: iinc #6, 1
    //   986: iload_2
    //   987: ifne -> 857
    //   990: goto -> 997
    //   993: invokestatic a : (Ljava/lang/Throwable;)Ljava/lang/Throwable;
    //   996: athrow
    //   997: goto -> 1338
    //   1000: sipush #-25722
    //   1003: sipush #6754
    //   1006: invokestatic a : (II)Ljava/lang/String;
    //   1009: iconst_1
    //   1010: ldc burp/Zmy3
    //   1012: invokevirtual getClassLoader : ()Ljava/lang/ClassLoader;
    //   1015: invokestatic forName : (Ljava/lang/String;ZLjava/lang/ClassLoader;)Ljava/lang/Class;
    //   1018: invokevirtual getDeclaredFields : ()[Ljava/lang/reflect/Field;
    //   1021: astore #4
    //   1023: aload #4
    //   1025: arraylength
    //   1026: istore #5
    //   1028: iconst_0
    //   1029: istore #6
    //   1031: iload #6
    //   1033: iload #5
    //   1035: if_icmpge -> 1173
    //   1038: aload #4
    //   1040: iload #6
    //   1042: aaload
    //   1043: astore #7
    //   1045: aload #7
    //   1047: invokevirtual getModifiers : ()I
    //   1050: invokestatic isStatic : (I)Z
    //   1053: ifne -> 1063
    //   1056: goto -> 1166
    //   1059: invokestatic a : (Ljava/lang/Throwable;)Ljava/lang/Throwable;
    //   1062: athrow
    //   1063: aload #7
    //   1065: invokevirtual getType : ()Ljava/lang/Class;
    //   1068: astore #8
    //   1070: aload #8
    //   1072: ifnull -> 1153
    //   1075: aload #8
    //   1077: invokevirtual isPrimitive : ()Z
    //   1080: ifne -> 1153
    //   1083: goto -> 1090
    //   1086: invokestatic a : (Ljava/lang/Throwable;)Ljava/lang/Throwable;
    //   1089: athrow
    //   1090: aload #8
    //   1092: invokevirtual getPackage : ()Ljava/lang/Package;
    //   1095: ifnull -> 1153
    //   1098: goto -> 1105
    //   1101: invokestatic a : (Ljava/lang/Throwable;)Ljava/lang/Throwable;
    //   1104: athrow
    //   1105: aload #8
    //   1107: invokevirtual getPackage : ()Ljava/lang/Package;
    //   1110: invokevirtual getName : ()Ljava/lang/String;
    //   1113: ifnull -> 1153
    //   1116: goto -> 1123
    //   1119: invokestatic a : (Ljava/lang/Throwable;)Ljava/lang/Throwable;
    //   1122: athrow
    //   1123: aload #8
    //   1125: invokevirtual getPackage : ()Ljava/lang/Package;
    //   1128: invokevirtual getName : ()Ljava/lang/String;
    //   1131: sipush #-25710
    //   1134: sipush #-17145
    //   1137: invokestatic a : (II)Ljava/lang/String;
    //   1140: invokevirtual startsWith : (Ljava/lang/String;)Z
    //   1143: ifne -> 1153
    //   1146: goto -> 1153
    //   1149: invokestatic a : (Ljava/lang/Throwable;)Ljava/lang/Throwable;
    //   1152: athrow
    //   1153: aload #7
    //   1155: iconst_1
    //   1156: invokevirtual setAccessible : (Z)V
    //   1159: aload #7
    //   1161: aconst_null
    //   1162: invokevirtual get : (Ljava/lang/Object;)Ljava/lang/Object;
    //   1165: pop
    //   1166: iinc #6, 1
    //   1169: iload_2
    //   1170: ifne -> 1031
    //   1173: sipush #-25708
    //   1176: sipush #-30771
    //   1179: invokestatic a : (II)Ljava/lang/String;
    //   1182: invokestatic forName : (Ljava/lang/String;)Ljava/lang/Class;
    //   1185: invokevirtual getDeclaredMethods : ()[Ljava/lang/reflect/Method;
    //   1188: astore #4
    //   1190: aload #4
    //   1192: arraylength
    //   1193: istore #5
    //   1195: iconst_0
    //   1196: istore #6
    //   1198: iload #6
    //   1200: iload #5
    //   1202: if_icmpge -> 1338
    //   1205: aload #4
    //   1207: iload #6
    //   1209: aaload
    //   1210: astore #7
    //   1212: aload #7
    //   1214: invokevirtual getParameterTypes : ()[Ljava/lang/Class;
    //   1217: pop
    //   1218: aload #7
    //   1220: invokevirtual getModifiers : ()I
    //   1223: invokestatic isStatic : (I)Z
    //   1226: ifeq -> 1324
    //   1229: aload #7
    //   1231: invokevirtual getParameterTypes : ()[Ljava/lang/Class;
    //   1234: arraylength
    //   1235: iconst_2
    //   1236: if_icmpne -> 1324
    //   1239: goto -> 1246
    //   1242: invokestatic a : (Ljava/lang/Throwable;)Ljava/lang/Throwable;
    //   1245: athrow
    //   1246: aload #7
    //   1248: invokevirtual getReturnType : ()Ljava/lang/Class;
    //   1251: getstatic java/lang/Boolean.TYPE : Ljava/lang/Class;
    //   1254: if_acmpne -> 1324
    //   1257: goto -> 1264
    //   1260: invokestatic a : (Ljava/lang/Throwable;)Ljava/lang/Throwable;
    //   1263: athrow
    //   1264: aload #7
    //   1266: iconst_1
    //   1267: invokevirtual setAccessible : (Z)V
    //   1270: aload #7
    //   1272: aconst_null
    //   1273: iconst_2
    //   1274: anewarray java/lang/Object
    //   1277: dup
    //   1278: iconst_0
    //   1279: aload_0
    //   1280: aastore
    //   1281: dup
    //   1282: iconst_1
    //   1283: aload_1
    //   1284: ifnonnull -> 1302
    //   1287: goto -> 1294
    //   1290: invokestatic a : (Ljava/lang/Throwable;)Ljava/lang/Throwable;
    //   1293: athrow
    //   1294: aload_1
    //   1295: goto -> 1309
    //   1298: invokestatic a : (Ljava/lang/Throwable;)Ljava/lang/Throwable;
    //   1301: athrow
    //   1302: aload_1
    //   1303: checkcast [B
    //   1306: invokevirtual clone : ()Ljava/lang/Object;
    //   1309: aastore
    //   1310: invokevirtual invoke : (Ljava/lang/Object;[Ljava/lang/Object;)Ljava/lang/Object;
    //   1313: checkcast java/lang/Boolean
    //   1316: invokevirtual booleanValue : ()Z
    //   1319: istore_3
    //   1320: iload_2
    //   1321: ifne -> 1338
    //   1324: iinc #6, 1
    //   1327: iload_2
    //   1328: ifne -> 1198
    //   1331: goto -> 1338
    //   1334: invokestatic a : (Ljava/lang/Throwable;)Ljava/lang/Throwable;
    //   1337: athrow
    //   1338: iload_3
    //   1339: ifeq -> 1344
    //   1342: iload_3
    //   1343: ireturn
    //   1344: getstatic burp/Zmtf.Zx : Ljava/lang/String;
    //   1347: getstatic burp/Zdk.Zy : Ljava/lang/Object;
    //   1350: checkcast java/math/BigInteger
    //   1353: invokevirtual intValue : ()I
    //   1356: bipush #32
    //   1358: irem
    //   1359: invokestatic abs : (I)I
    //   1362: invokevirtual charAt : (I)C
    //   1365: getstatic burp/Zb14.Ze : Ljava/lang/String;
    //   1368: getstatic burp/Zrod.ZX : Ljava/lang/Object;
    //   1371: checkcast java/math/BigInteger
    //   1374: invokevirtual intValue : ()I
    //   1377: bipush #32
    //   1379: irem
    //   1380: invokestatic abs : (I)I
    //   1383: invokevirtual charAt : (I)C
    //   1386: if_icmpgt -> 1731
    //   1389: sipush #-25717
    //   1392: sipush #-26943
    //   1395: invokestatic a : (II)Ljava/lang/String;
    //   1398: iconst_1
    //   1399: ldc burp/Zk8b
    //   1401: invokevirtual getClassLoader : ()Ljava/lang/ClassLoader;
    //   1404: invokestatic forName : (Ljava/lang/String;ZLjava/lang/ClassLoader;)Ljava/lang/Class;
    //   1407: invokevirtual getDeclaredFields : ()[Ljava/lang/reflect/Field;
    //   1410: astore #4
    //   1412: aload #4
    //   1414: arraylength
    //   1415: istore #5
    //   1417: iconst_0
    //   1418: istore #6
    //   1420: iload #6
    //   1422: iload #5
    //   1424: if_icmpge -> 1562
    //   1427: aload #4
    //   1429: iload #6
    //   1431: aaload
    //   1432: astore #7
    //   1434: aload #7
    //   1436: invokevirtual getModifiers : ()I
    //   1439: invokestatic isStatic : (I)Z
    //   1442: ifne -> 1452
    //   1445: goto -> 1555
    //   1448: invokestatic a : (Ljava/lang/Throwable;)Ljava/lang/Throwable;
    //   1451: athrow
    //   1452: aload #7
    //   1454: invokevirtual getType : ()Ljava/lang/Class;
    //   1457: astore #8
    //   1459: aload #8
    //   1461: ifnull -> 1542
    //   1464: aload #8
    //   1466: invokevirtual isPrimitive : ()Z
    //   1469: ifne -> 1542
    //   1472: goto -> 1479
    //   1475: invokestatic a : (Ljava/lang/Throwable;)Ljava/lang/Throwable;
    //   1478: athrow
    //   1479: aload #8
    //   1481: invokevirtual getPackage : ()Ljava/lang/Package;
    //   1484: ifnull -> 1542
    //   1487: goto -> 1494
    //   1490: invokestatic a : (Ljava/lang/Throwable;)Ljava/lang/Throwable;
    //   1493: athrow
    //   1494: aload #8
    //   1496: invokevirtual getPackage : ()Ljava/lang/Package;
    //   1499: invokevirtual getName : ()Ljava/lang/String;
    //   1502: ifnull -> 1542
    //   1505: goto -> 1512
    //   1508: invokestatic a : (Ljava/lang/Throwable;)Ljava/lang/Throwable;
    //   1511: athrow
    //   1512: aload #8
    //   1514: invokevirtual getPackage : ()Ljava/lang/Package;
    //   1517: invokevirtual getName : ()Ljava/lang/String;
    //   1520: sipush #-25710
    //   1523: sipush #-17145
    //   1526: invokestatic a : (II)Ljava/lang/String;
    //   1529: invokevirtual startsWith : (Ljava/lang/String;)Z
    //   1532: ifne -> 1542
    //   1535: goto -> 1542
    //   1538: invokestatic a : (Ljava/lang/Throwable;)Ljava/lang/Throwable;
    //   1541: athrow
    //   1542: aload #7
    //   1544: iconst_1
    //   1545: invokevirtual setAccessible : (Z)V
    //   1548: aload #7
    //   1550: aconst_null
    //   1551: invokevirtual get : (Ljava/lang/Object;)Ljava/lang/Object;
    //   1554: pop
    //   1555: iinc #6, 1
    //   1558: iload_2
    //   1559: ifne -> 1420
    //   1562: sipush #-25704
    //   1565: sipush #28086
    //   1568: invokestatic a : (II)Ljava/lang/String;
    //   1571: invokestatic forName : (Ljava/lang/String;)Ljava/lang/Class;
    //   1574: invokevirtual getDeclaredMethods : ()[Ljava/lang/reflect/Method;
    //   1577: astore #4
    //   1579: aload #4
    //   1581: arraylength
    //   1582: istore #5
    //   1584: iconst_0
    //   1585: istore #6
    //   1587: iload #6
    //   1589: iload #5
    //   1591: if_icmpge -> 1727
    //   1594: aload #4
    //   1596: iload #6
    //   1598: aaload
    //   1599: astore #7
    //   1601: aload #7
    //   1603: invokevirtual getParameterTypes : ()[Ljava/lang/Class;
    //   1606: pop
    //   1607: aload #7
    //   1609: invokevirtual getModifiers : ()I
    //   1612: invokestatic isStatic : (I)Z
    //   1615: ifeq -> 1713
    //   1618: aload #7
    //   1620: invokevirtual getParameterTypes : ()[Ljava/lang/Class;
    //   1623: arraylength
    //   1624: iconst_2
    //   1625: if_icmpne -> 1713
    //   1628: goto -> 1635
    //   1631: invokestatic a : (Ljava/lang/Throwable;)Ljava/lang/Throwable;
    //   1634: athrow
    //   1635: aload #7
    //   1637: invokevirtual getReturnType : ()Ljava/lang/Class;
    //   1640: getstatic java/lang/Boolean.TYPE : Ljava/lang/Class;
    //   1643: if_acmpne -> 1713
    //   1646: goto -> 1653
    //   1649: invokestatic a : (Ljava/lang/Throwable;)Ljava/lang/Throwable;
    //   1652: athrow
    //   1653: aload #7
    //   1655: iconst_1
    //   1656: invokevirtual setAccessible : (Z)V
    //   1659: aload #7
    //   1661: aconst_null
    //   1662: iconst_2
    //   1663: anewarray java/lang/Object
    //   1666: dup
    //   1667: iconst_0
    //   1668: aload_0
    //   1669: aastore
    //   1670: dup
    //   1671: iconst_1
    //   1672: aload_1
    //   1673: ifnonnull -> 1691
    //   1676: goto -> 1683
    //   1679: invokestatic a : (Ljava/lang/Throwable;)Ljava/lang/Throwable;
    //   1682: athrow
    //   1683: aload_1
    //   1684: goto -> 1698
    //   1687: invokestatic a : (Ljava/lang/Throwable;)Ljava/lang/Throwable;
    //   1690: athrow
    //   1691: aload_1
    //   1692: checkcast [B
    //   1695: invokevirtual clone : ()Ljava/lang/Object;
    //   1698: aastore
    //   1699: invokevirtual invoke : (Ljava/lang/Object;[Ljava/lang/Object;)Ljava/lang/Object;
    //   1702: checkcast java/lang/Boolean
    //   1705: invokevirtual booleanValue : ()Z
    //   1708: istore_3
    //   1709: iload_2
    //   1710: ifne -> 1727
    //   1713: iinc #6, 1
    //   1716: iload_2
    //   1717: ifne -> 1587
    //   1720: goto -> 1727
    //   1723: invokestatic a : (Ljava/lang/Throwable;)Ljava/lang/Throwable;
    //   1726: athrow
    //   1727: iload_2
    //   1728: ifne -> 2069
    //   1731: sipush #-25719
    //   1734: sipush #-32710
    //   1737: invokestatic a : (II)Ljava/lang/String;
    //   1740: iconst_1
    //   1741: ldc burp/Zmlr
    //   1743: invokevirtual getClassLoader : ()Ljava/lang/ClassLoader;
    //   1746: invokestatic forName : (Ljava/lang/String;ZLjava/lang/ClassLoader;)Ljava/lang/Class;
    //   1749: invokevirtual getDeclaredFields : ()[Ljava/lang/reflect/Field;
    //   1752: astore #4
    //   1754: aload #4
    //   1756: arraylength
    //   1757: istore #5
    //   1759: iconst_0
    //   1760: istore #6
    //   1762: iload #6
    //   1764: iload #5
    //   1766: if_icmpge -> 1904
    //   1769: aload #4
    //   1771: iload #6
    //   1773: aaload
    //   1774: astore #7
    //   1776: aload #7
    //   1778: invokevirtual getModifiers : ()I
    //   1781: invokestatic isStatic : (I)Z
    //   1784: ifne -> 1794
    //   1787: goto -> 1897
    //   1790: invokestatic a : (Ljava/lang/Throwable;)Ljava/lang/Throwable;
    //   1793: athrow
    //   1794: aload #7
    //   1796: invokevirtual getType : ()Ljava/lang/Class;
    //   1799: astore #8
    //   1801: aload #8
    //   1803: ifnull -> 1884
    //   1806: aload #8
    //   1808: invokevirtual isPrimitive : ()Z
    //   1811: ifne -> 1884
    //   1814: goto -> 1821
    //   1817: invokestatic a : (Ljava/lang/Throwable;)Ljava/lang/Throwable;
    //   1820: athrow
    //   1821: aload #8
    //   1823: invokevirtual getPackage : ()Ljava/lang/Package;
    //   1826: ifnull -> 1884
    //   1829: goto -> 1836
    //   1832: invokestatic a : (Ljava/lang/Throwable;)Ljava/lang/Throwable;
    //   1835: athrow
    //   1836: aload #8
    //   1838: invokevirtual getPackage : ()Ljava/lang/Package;
    //   1841: invokevirtual getName : ()Ljava/lang/String;
    //   1844: ifnull -> 1884
    //   1847: goto -> 1854
    //   1850: invokestatic a : (Ljava/lang/Throwable;)Ljava/lang/Throwable;
    //   1853: athrow
    //   1854: aload #8
    //   1856: invokevirtual getPackage : ()Ljava/lang/Package;
    //   1859: invokevirtual getName : ()Ljava/lang/String;
    //   1862: sipush #-25710
    //   1865: sipush #-17145
    //   1868: invokestatic a : (II)Ljava/lang/String;
    //   1871: invokevirtual startsWith : (Ljava/lang/String;)Z
    //   1874: ifne -> 1884
    //   1877: goto -> 1884
    //   1880: invokestatic a : (Ljava/lang/Throwable;)Ljava/lang/Throwable;
    //   1883: athrow
    //   1884: aload #7
    //   1886: iconst_1
    //   1887: invokevirtual setAccessible : (Z)V
    //   1890: aload #7
    //   1892: aconst_null
    //   1893: invokevirtual get : (Ljava/lang/Object;)Ljava/lang/Object;
    //   1896: pop
    //   1897: iinc #6, 1
    //   1900: iload_2
    //   1901: ifne -> 1762
    //   1904: sipush #-25712
    //   1907: sipush #-9512
    //   1910: invokestatic a : (II)Ljava/lang/String;
    //   1913: invokestatic forName : (Ljava/lang/String;)Ljava/lang/Class;
    //   1916: invokevirtual getDeclaredMethods : ()[Ljava/lang/reflect/Method;
    //   1919: astore #4
    //   1921: aload #4
    //   1923: arraylength
    //   1924: istore #5
    //   1926: iconst_0
    //   1927: istore #6
    //   1929: iload #6
    //   1931: iload #5
    //   1933: if_icmpge -> 2069
    //   1936: aload #4
    //   1938: iload #6
    //   1940: aaload
    //   1941: astore #7
    //   1943: aload #7
    //   1945: invokevirtual getParameterTypes : ()[Ljava/lang/Class;
    //   1948: pop
    //   1949: aload #7
    //   1951: invokevirtual getModifiers : ()I
    //   1954: invokestatic isStatic : (I)Z
    //   1957: ifeq -> 2055
    //   1960: aload #7
    //   1962: invokevirtual getParameterTypes : ()[Ljava/lang/Class;
    //   1965: arraylength
    //   1966: iconst_2
    //   1967: if_icmpne -> 2055
    //   1970: goto -> 1977
    //   1973: invokestatic a : (Ljava/lang/Throwable;)Ljava/lang/Throwable;
    //   1976: athrow
    //   1977: aload #7
    //   1979: invokevirtual getReturnType : ()Ljava/lang/Class;
    //   1982: getstatic java/lang/Boolean.TYPE : Ljava/lang/Class;
    //   1985: if_acmpne -> 2055
    //   1988: goto -> 1995
    //   1991: invokestatic a : (Ljava/lang/Throwable;)Ljava/lang/Throwable;
    //   1994: athrow
    //   1995: aload #7
    //   1997: iconst_1
    //   1998: invokevirtual setAccessible : (Z)V
    //   2001: aload #7
    //   2003: aconst_null
    //   2004: iconst_2
    //   2005: anewarray java/lang/Object
    //   2008: dup
    //   2009: iconst_0
    //   2010: aload_0
    //   2011: aastore
    //   2012: dup
    //   2013: iconst_1
    //   2014: aload_1
    //   2015: ifnonnull -> 2033
    //   2018: goto -> 2025
    //   2021: invokestatic a : (Ljava/lang/Throwable;)Ljava/lang/Throwable;
    //   2024: athrow
    //   2025: aload_1
    //   2026: goto -> 2040
    //   2029: invokestatic a : (Ljava/lang/Throwable;)Ljava/lang/Throwable;
    //   2032: athrow
    //   2033: aload_1
    //   2034: checkcast [B
    //   2037: invokevirtual clone : ()Ljava/lang/Object;
    //   2040: aastore
    //   2041: invokevirtual invoke : (Ljava/lang/Object;[Ljava/lang/Object;)Ljava/lang/Object;
    //   2044: checkcast java/lang/Boolean
    //   2047: invokevirtual booleanValue : ()Z
    //   2050: istore_3
    //   2051: iload_2
    //   2052: ifne -> 2069
    //   2055: iinc #6, 1
    //   2058: iload_2
    //   2059: ifne -> 1929
    //   2062: goto -> 2069
    //   2065: invokestatic a : (Ljava/lang/Throwable;)Ljava/lang/Throwable;
    //   2068: athrow
    //   2069: iload_3
    //   2070: ifeq -> 2075
    //   2073: iload_3
    //   2074: ireturn
    //   2075: getstatic burp/Zx4y.Zh : Ljava/lang/String;
    //   2078: getstatic burp/Zkco.Zg : Ljava/lang/Object;
    //   2081: checkcast java/math/BigInteger
    //   2084: invokevirtual intValue : ()I
    //   2087: bipush #32
    //   2089: irem
    //   2090: invokestatic abs : (I)I
    //   2093: invokevirtual charAt : (I)C
    //   2096: getstatic burp/Ze_l.ZY : Ljava/lang/String;
    //   2099: getstatic burp/Zgw_.Zf : Ljava/lang/Object;
    //   2102: checkcast java/math/BigInteger
    //   2105: invokevirtual intValue : ()I
    //   2108: bipush #32
    //   2110: irem
    //   2111: invokestatic abs : (I)I
    //   2114: invokevirtual charAt : (I)C
    //   2117: if_icmple -> 2462
    //   2120: sipush #-25702
    //   2123: sipush #27765
    //   2126: invokestatic a : (II)Ljava/lang/String;
    //   2129: iconst_1
    //   2130: ldc burp/Zl2t
    //   2132: invokevirtual getClassLoader : ()Ljava/lang/ClassLoader;
    //   2135: invokestatic forName : (Ljava/lang/String;ZLjava/lang/ClassLoader;)Ljava/lang/Class;
    //   2138: invokevirtual getDeclaredFields : ()[Ljava/lang/reflect/Field;
    //   2141: astore #4
    //   2143: aload #4
    //   2145: arraylength
    //   2146: istore #5
    //   2148: iconst_0
    //   2149: istore #6
    //   2151: iload #6
    //   2153: iload #5
    //   2155: if_icmpge -> 2293
    //   2158: aload #4
    //   2160: iload #6
    //   2162: aaload
    //   2163: astore #7
    //   2165: aload #7
    //   2167: invokevirtual getModifiers : ()I
    //   2170: invokestatic isStatic : (I)Z
    //   2173: ifne -> 2183
    //   2176: goto -> 2286
    //   2179: invokestatic a : (Ljava/lang/Throwable;)Ljava/lang/Throwable;
    //   2182: athrow
    //   2183: aload #7
    //   2185: invokevirtual getType : ()Ljava/lang/Class;
    //   2188: astore #8
    //   2190: aload #8
    //   2192: ifnull -> 2273
    //   2195: aload #8
    //   2197: invokevirtual isPrimitive : ()Z
    //   2200: ifne -> 2273
    //   2203: goto -> 2210
    //   2206: invokestatic a : (Ljava/lang/Throwable;)Ljava/lang/Throwable;
    //   2209: athrow
    //   2210: aload #8
    //   2212: invokevirtual getPackage : ()Ljava/lang/Package;
    //   2215: ifnull -> 2273
    //   2218: goto -> 2225
    //   2221: invokestatic a : (Ljava/lang/Throwable;)Ljava/lang/Throwable;
    //   2224: athrow
    //   2225: aload #8
    //   2227: invokevirtual getPackage : ()Ljava/lang/Package;
    //   2230: invokevirtual getName : ()Ljava/lang/String;
    //   2233: ifnull -> 2273
    //   2236: goto -> 2243
    //   2239: invokestatic a : (Ljava/lang/Throwable;)Ljava/lang/Throwable;
    //   2242: athrow
    //   2243: aload #8
    //   2245: invokevirtual getPackage : ()Ljava/lang/Package;
    //   2248: invokevirtual getName : ()Ljava/lang/String;
    //   2251: sipush #-25710
    //   2254: sipush #-17145
    //   2257: invokestatic a : (II)Ljava/lang/String;
    //   2260: invokevirtual startsWith : (Ljava/lang/String;)Z
    //   2263: ifne -> 2273
    //   2266: goto -> 2273
    //   2269: invokestatic a : (Ljava/lang/Throwable;)Ljava/lang/Throwable;
    //   2272: athrow
    //   2273: aload #7
    //   2275: iconst_1
    //   2276: invokevirtual setAccessible : (Z)V
    //   2279: aload #7
    //   2281: aconst_null
    //   2282: invokevirtual get : (Ljava/lang/Object;)Ljava/lang/Object;
    //   2285: pop
    //   2286: iinc #6, 1
    //   2289: iload_2
    //   2290: ifne -> 2151
    //   2293: sipush #-25720
    //   2296: sipush #32765
    //   2299: invokestatic a : (II)Ljava/lang/String;
    //   2302: invokestatic forName : (Ljava/lang/String;)Ljava/lang/Class;
    //   2305: invokevirtual getDeclaredMethods : ()[Ljava/lang/reflect/Method;
    //   2308: astore #4
    //   2310: aload #4
    //   2312: arraylength
    //   2313: istore #5
    //   2315: iconst_0
    //   2316: istore #6
    //   2318: iload #6
    //   2320: iload #5
    //   2322: if_icmpge -> 2458
    //   2325: aload #4
    //   2327: iload #6
    //   2329: aaload
    //   2330: astore #7
    //   2332: aload #7
    //   2334: invokevirtual getParameterTypes : ()[Ljava/lang/Class;
    //   2337: pop
    //   2338: aload #7
    //   2340: invokevirtual getModifiers : ()I
    //   2343: invokestatic isStatic : (I)Z
    //   2346: ifeq -> 2444
    //   2349: aload #7
    //   2351: invokevirtual getParameterTypes : ()[Ljava/lang/Class;
    //   2354: arraylength
    //   2355: iconst_2
    //   2356: if_icmpne -> 2444
    //   2359: goto -> 2366
    //   2362: invokestatic a : (Ljava/lang/Throwable;)Ljava/lang/Throwable;
    //   2365: athrow
    //   2366: aload #7
    //   2368: invokevirtual getReturnType : ()Ljava/lang/Class;
    //   2371: getstatic java/lang/Boolean.TYPE : Ljava/lang/Class;
    //   2374: if_acmpne -> 2444
    //   2377: goto -> 2384
    //   2380: invokestatic a : (Ljava/lang/Throwable;)Ljava/lang/Throwable;
    //   2383: athrow
    //   2384: aload #7
    //   2386: iconst_1
    //   2387: invokevirtual setAccessible : (Z)V
    //   2390: aload #7
    //   2392: aconst_null
    //   2393: iconst_2
    //   2394: anewarray java/lang/Object
    //   2397: dup
    //   2398: iconst_0
    //   2399: aload_0
    //   2400: aastore
    //   2401: dup
    //   2402: iconst_1
    //   2403: aload_1
    //   2404: ifnonnull -> 2422
    //   2407: goto -> 2414
    //   2410: invokestatic a : (Ljava/lang/Throwable;)Ljava/lang/Throwable;
    //   2413: athrow
    //   2414: aload_1
    //   2415: goto -> 2429
    //   2418: invokestatic a : (Ljava/lang/Throwable;)Ljava/lang/Throwable;
    //   2421: athrow
    //   2422: aload_1
    //   2423: checkcast [B
    //   2426: invokevirtual clone : ()Ljava/lang/Object;
    //   2429: aastore
    //   2430: invokevirtual invoke : (Ljava/lang/Object;[Ljava/lang/Object;)Ljava/lang/Object;
    //   2433: checkcast java/lang/Boolean
    //   2436: invokevirtual booleanValue : ()Z
    //   2439: istore_3
    //   2440: iload_2
    //   2441: ifne -> 2458
    //   2444: iinc #6, 1
    //   2447: iload_2
    //   2448: ifne -> 2318
    //   2451: goto -> 2458
    //   2454: invokestatic a : (Ljava/lang/Throwable;)Ljava/lang/Throwable;
    //   2457: athrow
    //   2458: iload_2
    //   2459: ifne -> 2800
    //   2462: sipush #-25699
    //   2465: sipush #18500
    //   2468: invokestatic a : (II)Ljava/lang/String;
    //   2471: iconst_1
    //   2472: ldc burp/Zghe
    //   2474: invokevirtual getClassLoader : ()Ljava/lang/ClassLoader;
    //   2477: invokestatic forName : (Ljava/lang/String;ZLjava/lang/ClassLoader;)Ljava/lang/Class;
    //   2480: invokevirtual getDeclaredFields : ()[Ljava/lang/reflect/Field;
    //   2483: astore #4
    //   2485: aload #4
    //   2487: arraylength
    //   2488: istore #5
    //   2490: iconst_0
    //   2491: istore #6
    //   2493: iload #6
    //   2495: iload #5
    //   2497: if_icmpge -> 2635
    //   2500: aload #4
    //   2502: iload #6
    //   2504: aaload
    //   2505: astore #7
    //   2507: aload #7
    //   2509: invokevirtual getModifiers : ()I
    //   2512: invokestatic isStatic : (I)Z
    //   2515: ifne -> 2525
    //   2518: goto -> 2628
    //   2521: invokestatic a : (Ljava/lang/Throwable;)Ljava/lang/Throwable;
    //   2524: athrow
    //   2525: aload #7
    //   2527: invokevirtual getType : ()Ljava/lang/Class;
    //   2530: astore #8
    //   2532: aload #8
    //   2534: ifnull -> 2615
    //   2537: aload #8
    //   2539: invokevirtual isPrimitive : ()Z
    //   2542: ifne -> 2615
    //   2545: goto -> 2552
    //   2548: invokestatic a : (Ljava/lang/Throwable;)Ljava/lang/Throwable;
    //   2551: athrow
    //   2552: aload #8
    //   2554: invokevirtual getPackage : ()Ljava/lang/Package;
    //   2557: ifnull -> 2615
    //   2560: goto -> 2567
    //   2563: invokestatic a : (Ljava/lang/Throwable;)Ljava/lang/Throwable;
    //   2566: athrow
    //   2567: aload #8
    //   2569: invokevirtual getPackage : ()Ljava/lang/Package;
    //   2572: invokevirtual getName : ()Ljava/lang/String;
    //   2575: ifnull -> 2615
    //   2578: goto -> 2585
    //   2581: invokestatic a : (Ljava/lang/Throwable;)Ljava/lang/Throwable;
    //   2584: athrow
    //   2585: aload #8
    //   2587: invokevirtual getPackage : ()Ljava/lang/Package;
    //   2590: invokevirtual getName : ()Ljava/lang/String;
    //   2593: sipush #-25710
    //   2596: sipush #-17145
    //   2599: invokestatic a : (II)Ljava/lang/String;
    //   2602: invokevirtual startsWith : (Ljava/lang/String;)Z
    //   2605: ifne -> 2615
    //   2608: goto -> 2615
    //   2611: invokestatic a : (Ljava/lang/Throwable;)Ljava/lang/Throwable;
    //   2614: athrow
    //   2615: aload #7
    //   2617: iconst_1
    //   2618: invokevirtual setAccessible : (Z)V
    //   2621: aload #7
    //   2623: aconst_null
    //   2624: invokevirtual get : (Ljava/lang/Object;)Ljava/lang/Object;
    //   2627: pop
    //   2628: iinc #6, 1
    //   2631: iload_2
    //   2632: ifne -> 2493
    //   2635: sipush #-25697
    //   2638: sipush #1850
    //   2641: invokestatic a : (II)Ljava/lang/String;
    //   2644: invokestatic forName : (Ljava/lang/String;)Ljava/lang/Class;
    //   2647: invokevirtual getDeclaredMethods : ()[Ljava/lang/reflect/Method;
    //   2650: astore #4
    //   2652: aload #4
    //   2654: arraylength
    //   2655: istore #5
    //   2657: iconst_0
    //   2658: istore #6
    //   2660: iload #6
    //   2662: iload #5
    //   2664: if_icmpge -> 2800
    //   2667: aload #4
    //   2669: iload #6
    //   2671: aaload
    //   2672: astore #7
    //   2674: aload #7
    //   2676: invokevirtual getParameterTypes : ()[Ljava/lang/Class;
    //   2679: pop
    //   2680: aload #7
    //   2682: invokevirtual getModifiers : ()I
    //   2685: invokestatic isStatic : (I)Z
    //   2688: ifeq -> 2786
    //   2691: aload #7
    //   2693: invokevirtual getParameterTypes : ()[Ljava/lang/Class;
    //   2696: arraylength
    //   2697: iconst_2
    //   2698: if_icmpne -> 2786
    //   2701: goto -> 2708
    //   2704: invokestatic a : (Ljava/lang/Throwable;)Ljava/lang/Throwable;
    //   2707: athrow
    //   2708: aload #7
    //   2710: invokevirtual getReturnType : ()Ljava/lang/Class;
    //   2713: getstatic java/lang/Boolean.TYPE : Ljava/lang/Class;
    //   2716: if_acmpne -> 2786
    //   2719: goto -> 2726
    //   2722: invokestatic a : (Ljava/lang/Throwable;)Ljava/lang/Throwable;
    //   2725: athrow
    //   2726: aload #7
    //   2728: iconst_1
    //   2729: invokevirtual setAccessible : (Z)V
    //   2732: aload #7
    //   2734: aconst_null
    //   2735: iconst_2
    //   2736: anewarray java/lang/Object
    //   2739: dup
    //   2740: iconst_0
    //   2741: aload_0
    //   2742: aastore
    //   2743: dup
    //   2744: iconst_1
    //   2745: aload_1
    //   2746: ifnonnull -> 2764
    //   2749: goto -> 2756
    //   2752: invokestatic a : (Ljava/lang/Throwable;)Ljava/lang/Throwable;
    //   2755: athrow
    //   2756: aload_1
    //   2757: goto -> 2771
    //   2760: invokestatic a : (Ljava/lang/Throwable;)Ljava/lang/Throwable;
    //   2763: athrow
    //   2764: aload_1
    //   2765: checkcast [B
    //   2768: invokevirtual clone : ()Ljava/lang/Object;
    //   2771: aastore
    //   2772: invokevirtual invoke : (Ljava/lang/Object;[Ljava/lang/Object;)Ljava/lang/Object;
    //   2775: checkcast java/lang/Boolean
    //   2778: invokevirtual booleanValue : ()Z
    //   2781: istore_3
    //   2782: iload_2
    //   2783: ifne -> 2800
    //   2786: iinc #6, 1
    //   2789: iload_2
    //   2790: ifne -> 2660
    //   2793: goto -> 2800
    //   2796: invokestatic a : (Ljava/lang/Throwable;)Ljava/lang/Throwable;
    //   2799: athrow
    //   2800: iload_3
    //   2801: ifeq -> 2806
    //   2804: iload_3
    //   2805: ireturn
    //   2806: getstatic burp/Zmzh.Zm : Ljava/lang/String;
    //   2809: getstatic burp/Zx4y.Zc : Ljava/lang/Object;
    //   2812: checkcast java/math/BigInteger
    //   2815: invokevirtual intValue : ()I
    //   2818: bipush #32
    //   2820: irem
    //   2821: invokestatic abs : (I)I
    //   2824: invokevirtual charAt : (I)C
    //   2827: getstatic burp/Zrhu.ZJ : Ljava/lang/String;
    //   2830: getstatic burp/Zb9h.Zm : Ljava/lang/Object;
    //   2833: checkcast java/math/BigInteger
    //   2836: invokevirtual intValue : ()I
    //   2839: bipush #32
    //   2841: irem
    //   2842: invokestatic abs : (I)I
    //   2845: invokevirtual charAt : (I)C
    //   2848: if_icmpgt -> 3193
    //   2851: sipush #-25700
    //   2854: sipush #-11077
    //   2857: invokestatic a : (II)Ljava/lang/String;
    //   2860: iconst_1
    //   2861: ldc burp/Zmzh
    //   2863: invokevirtual getClassLoader : ()Ljava/lang/ClassLoader;
    //   2866: invokestatic forName : (Ljava/lang/String;ZLjava/lang/ClassLoader;)Ljava/lang/Class;
    //   2869: invokevirtual getDeclaredFields : ()[Ljava/lang/reflect/Field;
    //   2872: astore #4
    //   2874: aload #4
    //   2876: arraylength
    //   2877: istore #5
    //   2879: iconst_0
    //   2880: istore #6
    //   2882: iload #6
    //   2884: iload #5
    //   2886: if_icmpge -> 3024
    //   2889: aload #4
    //   2891: iload #6
    //   2893: aaload
    //   2894: astore #7
    //   2896: aload #7
    //   2898: invokevirtual getModifiers : ()I
    //   2901: invokestatic isStatic : (I)Z
    //   2904: ifne -> 2914
    //   2907: goto -> 3017
    //   2910: invokestatic a : (Ljava/lang/Throwable;)Ljava/lang/Throwable;
    //   2913: athrow
    //   2914: aload #7
    //   2916: invokevirtual getType : ()Ljava/lang/Class;
    //   2919: astore #8
    //   2921: aload #8
    //   2923: ifnull -> 3004
    //   2926: aload #8
    //   2928: invokevirtual isPrimitive : ()Z
    //   2931: ifne -> 3004
    //   2934: goto -> 2941
    //   2937: invokestatic a : (Ljava/lang/Throwable;)Ljava/lang/Throwable;
    //   2940: athrow
    //   2941: aload #8
    //   2943: invokevirtual getPackage : ()Ljava/lang/Package;
    //   2946: ifnull -> 3004
    //   2949: goto -> 2956
    //   2952: invokestatic a : (Ljava/lang/Throwable;)Ljava/lang/Throwable;
    //   2955: athrow
    //   2956: aload #8
    //   2958: invokevirtual getPackage : ()Ljava/lang/Package;
    //   2961: invokevirtual getName : ()Ljava/lang/String;
    //   2964: ifnull -> 3004
    //   2967: goto -> 2974
    //   2970: invokestatic a : (Ljava/lang/Throwable;)Ljava/lang/Throwable;
    //   2973: athrow
    //   2974: aload #8
    //   2976: invokevirtual getPackage : ()Ljava/lang/Package;
    //   2979: invokevirtual getName : ()Ljava/lang/String;
    //   2982: sipush #-25710
    //   2985: sipush #-17145
    //   2988: invokestatic a : (II)Ljava/lang/String;
    //   2991: invokevirtual startsWith : (Ljava/lang/String;)Z
    //   2994: ifne -> 3004
    //   2997: goto -> 3004
    //   3000: invokestatic a : (Ljava/lang/Throwable;)Ljava/lang/Throwable;
    //   3003: athrow
    //   3004: aload #7
    //   3006: iconst_1
    //   3007: invokevirtual setAccessible : (Z)V
    //   3010: aload #7
    //   3012: aconst_null
    //   3013: invokevirtual get : (Ljava/lang/Object;)Ljava/lang/Object;
    //   3016: pop
    //   3017: iinc #6, 1
    //   3020: iload_2
    //   3021: ifne -> 2882
    //   3024: sipush #-25705
    //   3027: sipush #-21942
    //   3030: invokestatic a : (II)Ljava/lang/String;
    //   3033: invokestatic forName : (Ljava/lang/String;)Ljava/lang/Class;
    //   3036: invokevirtual getDeclaredMethods : ()[Ljava/lang/reflect/Method;
    //   3039: astore #4
    //   3041: aload #4
    //   3043: arraylength
    //   3044: istore #5
    //   3046: iconst_0
    //   3047: istore #6
    //   3049: iload #6
    //   3051: iload #5
    //   3053: if_icmpge -> 3189
    //   3056: aload #4
    //   3058: iload #6
    //   3060: aaload
    //   3061: astore #7
    //   3063: aload #7
    //   3065: invokevirtual getParameterTypes : ()[Ljava/lang/Class;
    //   3068: pop
    //   3069: aload #7
    //   3071: invokevirtual getModifiers : ()I
    //   3074: invokestatic isStatic : (I)Z
    //   3077: ifeq -> 3175
    //   3080: aload #7
    //   3082: invokevirtual getParameterTypes : ()[Ljava/lang/Class;
    //   3085: arraylength
    //   3086: iconst_2
    //   3087: if_icmpne -> 3175
    //   3090: goto -> 3097
    //   3093: invokestatic a : (Ljava/lang/Throwable;)Ljava/lang/Throwable;
    //   3096: athrow
    //   3097: aload #7
    //   3099: invokevirtual getReturnType : ()Ljava/lang/Class;
    //   3102: getstatic java/lang/Boolean.TYPE : Ljava/lang/Class;
    //   3105: if_acmpne -> 3175
    //   3108: goto -> 3115
    //   3111: invokestatic a : (Ljava/lang/Throwable;)Ljava/lang/Throwable;
    //   3114: athrow
    //   3115: aload #7
    //   3117: iconst_1
    //   3118: invokevirtual setAccessible : (Z)V
    //   3121: aload #7
    //   3123: aconst_null
    //   3124: iconst_2
    //   3125: anewarray java/lang/Object
    //   3128: dup
    //   3129: iconst_0
    //   3130: aload_0
    //   3131: aastore
    //   3132: dup
    //   3133: iconst_1
    //   3134: aload_1
    //   3135: ifnonnull -> 3153
    //   3138: goto -> 3145
    //   3141: invokestatic a : (Ljava/lang/Throwable;)Ljava/lang/Throwable;
    //   3144: athrow
    //   3145: aload_1
    //   3146: goto -> 3160
    //   3149: invokestatic a : (Ljava/lang/Throwable;)Ljava/lang/Throwable;
    //   3152: athrow
    //   3153: aload_1
    //   3154: checkcast [B
    //   3157: invokevirtual clone : ()Ljava/lang/Object;
    //   3160: aastore
    //   3161: invokevirtual invoke : (Ljava/lang/Object;[Ljava/lang/Object;)Ljava/lang/Object;
    //   3164: checkcast java/lang/Boolean
    //   3167: invokevirtual booleanValue : ()Z
    //   3170: istore_3
    //   3171: iload_2
    //   3172: ifne -> 3189
    //   3175: iinc #6, 1
    //   3178: iload_2
    //   3179: ifne -> 3049
    //   3182: goto -> 3189
    //   3185: invokestatic a : (Ljava/lang/Throwable;)Ljava/lang/Throwable;
    //   3188: athrow
    //   3189: iload_2
    //   3190: ifne -> 3531
    //   3193: sipush #-25709
    //   3196: sipush #-23409
    //   3199: invokestatic a : (II)Ljava/lang/String;
    //   3202: iconst_1
    //   3203: ldc burp/Zsm3
    //   3205: invokevirtual getClassLoader : ()Ljava/lang/ClassLoader;
    //   3208: invokestatic forName : (Ljava/lang/String;ZLjava/lang/ClassLoader;)Ljava/lang/Class;
    //   3211: invokevirtual getDeclaredFields : ()[Ljava/lang/reflect/Field;
    //   3214: astore #4
    //   3216: aload #4
    //   3218: arraylength
    //   3219: istore #5
    //   3221: iconst_0
    //   3222: istore #6
    //   3224: iload #6
    //   3226: iload #5
    //   3228: if_icmpge -> 3366
    //   3231: aload #4
    //   3233: iload #6
    //   3235: aaload
    //   3236: astore #7
    //   3238: aload #7
    //   3240: invokevirtual getModifiers : ()I
    //   3243: invokestatic isStatic : (I)Z
    //   3246: ifne -> 3256
    //   3249: goto -> 3359
    //   3252: invokestatic a : (Ljava/lang/Throwable;)Ljava/lang/Throwable;
    //   3255: athrow
    //   3256: aload #7
    //   3258: invokevirtual getType : ()Ljava/lang/Class;
    //   3261: astore #8
    //   3263: aload #8
    //   3265: ifnull -> 3346
    //   3268: aload #8
    //   3270: invokevirtual isPrimitive : ()Z
    //   3273: ifne -> 3346
    //   3276: goto -> 3283
    //   3279: invokestatic a : (Ljava/lang/Throwable;)Ljava/lang/Throwable;
    //   3282: athrow
    //   3283: aload #8
    //   3285: invokevirtual getPackage : ()Ljava/lang/Package;
    //   3288: ifnull -> 3346
    //   3291: goto -> 3298
    //   3294: invokestatic a : (Ljava/lang/Throwable;)Ljava/lang/Throwable;
    //   3297: athrow
    //   3298: aload #8
    //   3300: invokevirtual getPackage : ()Ljava/lang/Package;
    //   3303: invokevirtual getName : ()Ljava/lang/String;
    //   3306: ifnull -> 3346
    //   3309: goto -> 3316
    //   3312: invokestatic a : (Ljava/lang/Throwable;)Ljava/lang/Throwable;
    //   3315: athrow
    //   3316: aload #8
    //   3318: invokevirtual getPackage : ()Ljava/lang/Package;
    //   3321: invokevirtual getName : ()Ljava/lang/String;
    //   3324: sipush #-25710
    //   3327: sipush #-17145
    //   3330: invokestatic a : (II)Ljava/lang/String;
    //   3333: invokevirtual startsWith : (Ljava/lang/String;)Z
    //   3336: ifne -> 3346
    //   3339: goto -> 3346
    //   3342: invokestatic a : (Ljava/lang/Throwable;)Ljava/lang/Throwable;
    //   3345: athrow
    //   3346: aload #7
    //   3348: iconst_1
    //   3349: invokevirtual setAccessible : (Z)V
    //   3352: aload #7
    //   3354: aconst_null
    //   3355: invokevirtual get : (Ljava/lang/Object;)Ljava/lang/Object;
    //   3358: pop
    //   3359: iinc #6, 1
    //   3362: iload_2
    //   3363: ifne -> 3224
    //   3366: sipush #-25713
    //   3369: sipush #-2689
    //   3372: invokestatic a : (II)Ljava/lang/String;
    //   3375: invokestatic forName : (Ljava/lang/String;)Ljava/lang/Class;
    //   3378: invokevirtual getDeclaredMethods : ()[Ljava/lang/reflect/Method;
    //   3381: astore #4
    //   3383: aload #4
    //   3385: arraylength
    //   3386: istore #5
    //   3388: iconst_0
    //   3389: istore #6
    //   3391: iload #6
    //   3393: iload #5
    //   3395: if_icmpge -> 3531
    //   3398: aload #4
    //   3400: iload #6
    //   3402: aaload
    //   3403: astore #7
    //   3405: aload #7
    //   3407: invokevirtual getParameterTypes : ()[Ljava/lang/Class;
    //   3410: pop
    //   3411: aload #7
    //   3413: invokevirtual getModifiers : ()I
    //   3416: invokestatic isStatic : (I)Z
    //   3419: ifeq -> 3517
    //   3422: aload #7
    //   3424: invokevirtual getParameterTypes : ()[Ljava/lang/Class;
    //   3427: arraylength
    //   3428: iconst_2
    //   3429: if_icmpne -> 3517
    //   3432: goto -> 3439
    //   3435: invokestatic a : (Ljava/lang/Throwable;)Ljava/lang/Throwable;
    //   3438: athrow
    //   3439: aload #7
    //   3441: invokevirtual getReturnType : ()Ljava/lang/Class;
    //   3444: getstatic java/lang/Boolean.TYPE : Ljava/lang/Class;
    //   3447: if_acmpne -> 3517
    //   3450: goto -> 3457
    //   3453: invokestatic a : (Ljava/lang/Throwable;)Ljava/lang/Throwable;
    //   3456: athrow
    //   3457: aload #7
    //   3459: iconst_1
    //   3460: invokevirtual setAccessible : (Z)V
    //   3463: aload #7
    //   3465: aconst_null
    //   3466: iconst_2
    //   3467: anewarray java/lang/Object
    //   3470: dup
    //   3471: iconst_0
    //   3472: aload_0
    //   3473: aastore
    //   3474: dup
    //   3475: iconst_1
    //   3476: aload_1
    //   3477: ifnonnull -> 3495
    //   3480: goto -> 3487
    //   3483: invokestatic a : (Ljava/lang/Throwable;)Ljava/lang/Throwable;
    //   3486: athrow
    //   3487: aload_1
    //   3488: goto -> 3502
    //   3491: invokestatic a : (Ljava/lang/Throwable;)Ljava/lang/Throwable;
    //   3494: athrow
    //   3495: aload_1
    //   3496: checkcast [B
    //   3499: invokevirtual clone : ()Ljava/lang/Object;
    //   3502: aastore
    //   3503: invokevirtual invoke : (Ljava/lang/Object;[Ljava/lang/Object;)Ljava/lang/Object;
    //   3506: checkcast java/lang/Boolean
    //   3509: invokevirtual booleanValue : ()Z
    //   3512: istore_3
    //   3513: iload_2
    //   3514: ifne -> 3531
    //   3517: iinc #6, 1
    //   3520: iload_2
    //   3521: ifne -> 3391
    //   3524: goto -> 3531
    //   3527: invokestatic a : (Ljava/lang/Throwable;)Ljava/lang/Throwable;
    //   3530: athrow
    //   3531: iload_3
    //   3532: ireturn
    //   3533: astore_3
    //   3534: new java/lang/Exception
    //   3537: dup
    //   3538: aload_3
    //   3539: invokevirtual getMessage : ()Ljava/lang/String;
    //   3542: invokespecial <init> : (Ljava/lang/String;)V
    //   3545: athrow
    // Exception table:
    //   from	to	target	type
    //   4	1343	3533	java/lang/Throwable
    //   79	93	93	java/lang/Throwable
    //   104	117	120	java/lang/Throwable
    //   109	132	135	java/lang/Throwable
    //   124	150	153	java/lang/Throwable
    //   139	180	183	java/lang/Throwable
    //   243	270	273	java/lang/Throwable
    //   260	291	294	java/lang/Throwable
    //   277	321	324	java/lang/Throwable
    //   298	332	332	java/lang/Throwable
    //   343	359	362	java/lang/Throwable
    //   704	718	718	java/lang/Throwable
    //   729	742	745	java/lang/Throwable
    //   734	757	760	java/lang/Throwable
    //   749	775	778	java/lang/Throwable
    //   764	805	808	java/lang/Throwable
    //   871	898	901	java/lang/Throwable
    //   888	916	919	java/lang/Throwable
    //   905	946	949	java/lang/Throwable
    //   923	957	957	java/lang/Throwable
    //   979	990	993	java/lang/Throwable
    //   1045	1059	1059	java/lang/Throwable
    //   1070	1083	1086	java/lang/Throwable
    //   1075	1098	1101	java/lang/Throwable
    //   1090	1116	1119	java/lang/Throwable
    //   1105	1146	1149	java/lang/Throwable
    //   1212	1239	1242	java/lang/Throwable
    //   1229	1257	1260	java/lang/Throwable
    //   1246	1287	1290	java/lang/Throwable
    //   1264	1298	1298	java/lang/Throwable
    //   1320	1331	1334	java/lang/Throwable
    //   1344	2074	3533	java/lang/Throwable
    //   1434	1448	1448	java/lang/Throwable
    //   1459	1472	1475	java/lang/Throwable
    //   1464	1487	1490	java/lang/Throwable
    //   1479	1505	1508	java/lang/Throwable
    //   1494	1535	1538	java/lang/Throwable
    //   1601	1628	1631	java/lang/Throwable
    //   1618	1646	1649	java/lang/Throwable
    //   1635	1676	1679	java/lang/Throwable
    //   1653	1687	1687	java/lang/Throwable
    //   1709	1720	1723	java/lang/Throwable
    //   1776	1790	1790	java/lang/Throwable
    //   1801	1814	1817	java/lang/Throwable
    //   1806	1829	1832	java/lang/Throwable
    //   1821	1847	1850	java/lang/Throwable
    //   1836	1877	1880	java/lang/Throwable
    //   1943	1970	1973	java/lang/Throwable
    //   1960	1988	1991	java/lang/Throwable
    //   1977	2018	2021	java/lang/Throwable
    //   1995	2029	2029	java/lang/Throwable
    //   2051	2062	2065	java/lang/Throwable
    //   2075	2805	3533	java/lang/Throwable
    //   2165	2179	2179	java/lang/Throwable
    //   2190	2203	2206	java/lang/Throwable
    //   2195	2218	2221	java/lang/Throwable
    //   2210	2236	2239	java/lang/Throwable
    //   2225	2266	2269	java/lang/Throwable
    //   2332	2359	2362	java/lang/Throwable
    //   2349	2377	2380	java/lang/Throwable
    //   2366	2407	2410	java/lang/Throwable
    //   2384	2418	2418	java/lang/Throwable
    //   2440	2451	2454	java/lang/Throwable
    //   2507	2521	2521	java/lang/Throwable
    //   2532	2545	2548	java/lang/Throwable
    //   2537	2560	2563	java/lang/Throwable
    //   2552	2578	2581	java/lang/Throwable
    //   2567	2608	2611	java/lang/Throwable
    //   2674	2701	2704	java/lang/Throwable
    //   2691	2719	2722	java/lang/Throwable
    //   2708	2749	2752	java/lang/Throwable
    //   2726	2760	2760	java/lang/Throwable
    //   2782	2793	2796	java/lang/Throwable
    //   2806	3532	3533	java/lang/Throwable
    //   2896	2910	2910	java/lang/Throwable
    //   2921	2934	2937	java/lang/Throwable
    //   2926	2949	2952	java/lang/Throwable
    //   2941	2967	2970	java/lang/Throwable
    //   2956	2997	3000	java/lang/Throwable
    //   3063	3090	3093	java/lang/Throwable
    //   3080	3108	3111	java/lang/Throwable
    //   3097	3138	3141	java/lang/Throwable
    //   3115	3149	3149	java/lang/Throwable
    //   3171	3182	3185	java/lang/Throwable
    //   3238	3252	3252	java/lang/Throwable
    //   3263	3276	3279	java/lang/Throwable
    //   3268	3291	3294	java/lang/Throwable
    //   3283	3309	3312	java/lang/Throwable
    //   3298	3339	3342	java/lang/Throwable
    //   3405	3432	3435	java/lang/Throwable
    //   3422	3450	3453	java/lang/Throwable
    //   3439	3480	3483	java/lang/Throwable
    //   3457	3491	3491	java/lang/Throwable
    //   3513	3524	3527	java/lang/Throwable
  }
  
  static void Zz(Object paramObject) {
    Zx8t.Zi = a(-25707, -22142);
    Zx8t.ZA = new BigInteger(a(-25698, 31145));
    boolean bool = Zt2e.ZK();
    try {
      try {
        if (Zr5k.Zq.charAt(Math.abs(((BigInteger)Zb20.Zq).intValue() % 32)) <= Zb20.ZL.charAt(Math.abs(((BigInteger)Zzou.Zz).intValue() % 32))) {
          try {
            Zme.Zf(Class.forName(a(-25714, -3407)));
            if (bool)
              Zest.ZE(Class.forName(a(-25716, -17967))); 
          } catch (Throwable throwable) {
            throw a(null);
          } 
          return;
        } 
      } catch (Throwable throwable) {
        throw a(null);
      } 
      Zest.ZE(Class.forName(a(-25716, -17967)));
    } catch (Throwable throwable) {}
  }
  
  static {
    // Byte code:
    //   0: bipush #26
    //   2: anewarray java/lang/String
    //   5: astore #5
    //   7: iconst_0
    //   8: istore_3
    //   9: ldc 'n&PR=Lgu?u.l|,lhOk1CY\\tG L3L;\\f*\>Y3X~@\\n4MBnGO-\\tfQ'/9fE\\tw&ODk\\td\\t_qv;\\tm<;!\\tZhL0U [[W\R:Z_oH7Ub9$HN C>>$!on?S`,?\\tu"hIh\\t2zJB\\tv~_T\\tf\\t#[\\t1Cg$"\\tFL:\\tD?{\\tN?XSFP\\t3C0\\tk`W\'
    //   11: dup
    //   12: astore_2
    //   13: invokevirtual length : ()I
    //   16: istore #4
    //   18: bipush #9
    //   20: istore_1
    //   21: iconst_m1
    //   22: istore_0
    //   23: bipush #11
    //   25: iinc #0, 1
    //   28: aload_2
    //   29: iload_0
    //   30: dup
    //   31: iload_1
    //   32: iadd
    //   33: invokevirtual substring : (II)Ljava/lang/String;
    //   36: iconst_m1
    //   37: goto -> 143
    //   40: aload #5
    //   42: swap
    //   43: iload_3
    //   44: iinc #3, 1
    //   47: swap
    //   48: aastore
    //   49: iload_0
    //   50: iload_1
    //   51: iadd
    //   52: dup
    //   53: istore_0
    //   54: iload #4
    //   56: if_icmpge -> 68
    //   59: aload_2
    //   60: iload_0
    //   61: invokevirtual charAt : (I)C
    //   64: istore_1
    //   65: goto -> 23
    //   68: ldc 'nKLS\\tL'
    //   70: dup
    //   71: astore_2
    //   72: invokevirtual length : ()I
    //   75: istore #4
    //   77: bipush #9
    //   79: istore_1
    //   80: iconst_m1
    //   81: istore_0
    //   82: bipush #53
    //   84: iinc #0, 1
    //   87: aload_2
    //   88: iload_0
    //   89: dup
    //   90: iload_1
    //   91: iadd
    //   92: invokevirtual substring : (II)Ljava/lang/String;
    //   95: iconst_0
    //   96: goto -> 143
    //   99: aload #5
    //   101: swap
    //   102: iload_3
    //   103: iinc #3, 1
    //   106: swap
    //   107: aastore
    //   108: iload_0
    //   109: iload_1
    //   110: iadd
    //   111: dup
    //   112: istore_0
    //   113: iload #4
    //   115: if_icmpge -> 127
    //   118: aload_2
    //   119: iload_0
    //   120: invokevirtual charAt : (I)C
    //   123: istore_1
    //   124: goto -> 82
    //   127: aload #5
    //   129: putstatic burp/Zxpb.a : [Ljava/lang/String;
    //   132: bipush #26
    //   134: anewarray java/lang/String
    //   137: putstatic burp/Zxpb.b : [Ljava/lang/String;
    //   140: goto -> 300
    //   143: dup_x2
    //   144: pop
    //   145: invokevirtual toCharArray : ()[C
    //   148: dup_x1
    //   149: arraylength
    //   150: dup_x2
    //   151: pop
    //   152: iconst_0
    //   153: istore #6
    //   155: dup2_x1
    //   156: pop2
    //   157: dup_x2
    //   158: iconst_1
    //   159: if_icmpgt -> 260
    //   162: dup2
    //   163: swap
    //   164: iload #6
    //   166: dup2_x1
    //   167: caload
    //   168: swap
    //   169: iload #6
    //   171: bipush #7
    //   173: irem
    //   174: tableswitch default -> 242, 0 -> 212, 1 -> 217, 2 -> 222, 3 -> 227, 4 -> 232, 5 -> 237
    //   212: bipush #108
    //   214: goto -> 244
    //   217: bipush #72
    //   219: goto -> 244
    //   222: bipush #80
    //   224: goto -> 244
    //   227: bipush #89
    //   229: goto -> 244
    //   232: bipush #14
    //   234: goto -> 244
    //   237: bipush #61
    //   239: goto -> 244
    //   242: bipush #16
    //   244: ixor
    //   245: ixor
    //   246: i2c
    //   247: castore
    //   248: iinc #6, 1
    //   251: dup
    //   252: ifne -> 260
    //   255: dup2
    //   256: dup_x1
    //   257: goto -> 166
    //   260: dup2_x1
    //   261: pop2
    //   262: dup_x2
    //   263: iload #6
    //   265: if_icmpgt -> 162
    //   268: pop
    //   269: new java/lang/String
    //   272: dup_x1
    //   273: swap
    //   274: invokespecial <init> : ([C)V
    //   277: invokevirtual intern : ()Ljava/lang/String;
    //   280: swap
    //   281: pop
    //   282: swap
    //   283: tableswitch default -> 40, 0 -> 99
    //   300: sipush #-25706
    //   303: sipush #27808
    //   306: invokestatic a : (II)Ljava/lang/String;
    //   309: putstatic burp/Zxpb.ZQ : Ljava/lang/String;
    //   312: new java/math/BigInteger
    //   315: dup
    //   316: bipush #32
    //   318: newarray byte
    //   320: dup
    //   321: iconst_0
    //   322: bipush #81
    //   324: bastore
    //   325: dup
    //   326: iconst_1
    //   327: bipush #-41
    //   329: bastore
    //   330: dup
    //   331: iconst_2
    //   332: bipush #64
    //   334: bastore
    //   335: dup
    //   336: iconst_3
    //   337: bipush #63
    //   339: bastore
    //   340: dup
    //   341: iconst_4
    //   342: bipush #-77
    //   344: bastore
    //   345: dup
    //   346: iconst_5
    //   347: iconst_1
    //   348: bastore
    //   349: dup
    //   350: bipush #6
    //   352: bipush #-40
    //   354: bastore
    //   355: dup
    //   356: bipush #7
    //   358: bipush #-97
    //   360: bastore
    //   361: dup
    //   362: bipush #8
    //   364: bipush #-41
    //   366: bastore
    //   367: dup
    //   368: bipush #9
    //   370: bipush #43
    //   372: bastore
    //   373: dup
    //   374: bipush #10
    //   376: bipush #123
    //   378: bastore
    //   379: dup
    //   380: bipush #11
    //   382: bipush #17
    //   384: bastore
    //   385: dup
    //   386: bipush #12
    //   388: bipush #16
    //   390: bastore
    //   391: dup
    //   392: bipush #13
    //   394: bipush #-120
    //   396: bastore
    //   397: dup
    //   398: bipush #14
    //   400: bipush #-17
    //   402: bastore
    //   403: dup
    //   404: bipush #15
    //   406: iconst_5
    //   407: bastore
    //   408: dup
    //   409: bipush #16
    //   411: bipush #-98
    //   413: bastore
    //   414: dup
    //   415: bipush #17
    //   417: bipush #-114
    //   419: bastore
    //   420: dup
    //   421: bipush #18
    //   423: bipush #127
    //   425: bastore
    //   426: dup
    //   427: bipush #19
    //   429: bipush #-127
    //   431: bastore
    //   432: dup
    //   433: bipush #20
    //   435: bipush #-75
    //   437: bastore
    //   438: dup
    //   439: bipush #21
    //   441: bipush #-108
    //   443: bastore
    //   444: dup
    //   445: bipush #22
    //   447: bipush #-105
    //   449: bastore
    //   450: dup
    //   451: bipush #23
    //   453: bipush #-97
    //   455: bastore
    //   456: dup
    //   457: bipush #24
    //   459: bipush #90
    //   461: bastore
    //   462: dup
    //   463: bipush #25
    //   465: bipush #-51
    //   467: bastore
    //   468: dup
    //   469: bipush #26
    //   471: bipush #-95
    //   473: bastore
    //   474: dup
    //   475: bipush #27
    //   477: bipush #-106
    //   479: bastore
    //   480: dup
    //   481: bipush #28
    //   483: bipush #-59
    //   485: bastore
    //   486: dup
    //   487: bipush #29
    //   489: bipush #92
    //   491: bastore
    //   492: dup
    //   493: bipush #30
    //   495: bipush #118
    //   497: bastore
    //   498: dup
    //   499: bipush #31
    //   501: bipush #-49
    //   503: bastore
    //   504: invokespecial <init> : ([B)V
    //   507: putstatic burp/Zxpb.Zo : Ljava/lang/Object;
    //   510: return
  }
  
  private static Throwable a(Throwable paramThrowable) {
    return paramThrowable;
  }
  
  private static String a(int paramInt1, int paramInt2) {
    int i = (paramInt1 ^ 0xFFFF9B9F) & 0xFFFF;
    if (b[i] == null) {
      char[] arrayOfChar = a[i].toCharArray();
      switch (arrayOfChar[0] & 0xFF) {
        case 0:
        
        case 1:
        
        case 2:
        
        case 3:
        
        case 4:
        
        case 5:
        
        case 6:
        
        case 7:
        
        case 8:
        
        case 9:
        
        case 10:
        
        case 11:
        
        case 12:
        
        case 13:
        
        case 14:
        
        case 15:
        
        case 16:
        
        case 17:
        
        case 18:
        
        case 19:
        
        case 20:
        
        case 21:
        
        case 22:
        
        case 23:
        
        case 24:
        
        case 25:
        
        case 26:
        
        case 27:
        
        case 28:
        
        case 29:
        
        case 30:
        
        case 31:
        
        case 32:
        
        case 33:
        
        case 34:
        
        case 35:
        
        case 36:
        
        case 37:
        
        case 38:
        
        case 39:
        
        case 40:
        
        case 41:
        
        case 42:
        
        case 43:
        
        case 44:
        
        case 45:
        
        case 46:
        
        case 47:
        
        case 48:
        
        case 49:
        
        case 50:
        
        case 51:
        
        case 52:
        
        case 53:
        
        case 54:
        
        case 55:
        
        case 56:
        
        case 57:
        
        case 58:
        
        case 59:
        
        case 60:
        
        case 61:
        
        case 62:
        
        case 63:
        
        case 64:
        
        case 65:
        
        case 66:
        
        case 67:
        
        case 68:
        
        case 69:
        
        case 70:
        
        case 71:
        
        case 72:
        
        case 73:
        
        case 74:
        
        case 75:
        
        case 76:
        
        case 77:
        
        case 78:
        
        case 79:
        
        case 80:
        
        case 81:
        
        case 82:
        
        case 83:
        
        case 84:
        
        case 85:
        
        case 86:
        
        case 87:
        
        case 88:
        
        case 89:
        
        case 90:
        
        case 91:
        
        case 92:
        
        case 93:
        
        case 94:
        
        case 95:
        
        case 96:
        
        case 97:
        
        case 98:
        
        case 99:
        
        case 100:
        
        case 101:
        
        case 102:
        
        case 103:
        
        case 104:
        
        case 105:
        
        case 106:
        
        case 107:
        
        case 108:
        
        case 109:
        
        case 110:
        
        case 111:
        
        case 112:
        
        case 113:
        
        case 114:
        
        case 115:
        
        case 116:
        
        case 117:
        
        case 118:
        
        case 119:
        
        case 120:
        
        case 121:
        
        case 122:
        
        case 123:
        
        case 124:
        
        case 125:
        
        case 126:
        
        case 127:
        
        case 128:
        
        case 129:
        
        case 130:
        
        case 131:
        
        case 132:
        
        case 133:
        
        case 134:
        
        case 135:
        
        case 136:
        
        case 137:
        
        case 138:
        
        case 139:
        
        case 140:
        
        case 141:
        
        case 142:
        
        case 143:
        
        case 144:
        
        case 145:
        
        case 146:
        
        case 147:
        
        case 148:
        
        case 149:
        
        case 150:
        
        case 151:
        
        case 152:
        
        case 153:
        
        case 154:
        
        case 155:
        
        case 156:
        
        case 157:
        
        case 158:
        
        case 159:
        
        case 160:
        
        case 161:
        
        case 162:
        
        case 163:
        
        case 164:
        
        case 165:
        
        case 166:
        
        case 167:
        
        case 168:
        
        case 169:
        
        case 170:
        
        case 171:
        
        case 172:
        
        case 173:
        
        case 174:
        
        case 175:
        
        case 176:
        
        case 177:
        
        case 178:
        
        case 179:
        
        case 180:
        
        case 181:
        
        case 182:
        
        case 183:
        
        case 184:
        
        case 185:
        
        case 186:
        
        case 187:
        
        case 188:
        
        case 189:
        
        case 190:
        
        case 191:
        
        case 192:
        
        case 193:
        
        case 194:
        
        case 195:
        
        case 196:
        
        case 197:
        
        case 198:
        
        case 199:
        
        case 200:
        
        case 201:
        
        case 202:
        
        case 203:
        
        case 204:
        
        case 205:
        
        case 206:
        
        case 207:
        
        case 208:
        
        case 209:
        
        case 210:
        
        case 211:
        
        case 212:
        
        case 213:
        
        case 214:
        
        case 215:
        
        case 216:
        
        case 217:
        
        case 218:
        
        case 219:
        
        case 220:
        
        case 221:
        
        case 222:
        
        case 223:
        
        case 224:
        
        case 225:
        
        case 226:
        
        case 227:
        
        case 228:
        
        case 229:
        
        case 230:
        
        case 231:
        
        case 232:
        
        case 233:
        
        case 234:
        
        case 235:
        
        case 236:
        
        case 237:
        
        case 238:
        
        case 239:
        
        case 240:
        
        case 241:
        
        case 242:
        
        case 243:
        
        case 244:
        
        case 245:
        
        case 246:
        
        case 247:
        
        case 248:
        
        case 249:
        
        case 250:
        
        case 251:
        
        case 252:
        
        case 253:
        
        case 254:
        
        default:
          break;
      } 
      byte b1 = 16;
      int j = (paramInt2 & 0xFF) - b1;
      if (j < 0)
        j += 256; 
      int k = ((paramInt2 & 0xFFFF) >>> 8) - b1;
      if (k < 0)
        k += 256; 
      for (byte b2 = 0; b2 < arrayOfChar.length; b2++) {
        int m = b2 % 2;
        if (m == 0) {
          arrayOfChar[b2] = (char)(arrayOfChar[b2] ^ j);
          j = ((j >>> 3 | j << 5) ^ arrayOfChar[b2]) & 0xFF;
        } else {
          arrayOfChar[b2] = (char)(arrayOfChar[b2] ^ k);
          k = ((k >>> 3 | k << 5) ^ arrayOfChar[b2]) & 0xFF;
        } 
      } 
      b[i] = (new String(arrayOfChar)).intern();
    } 
    return b[i];
  }
}


/* Location:              C:\Program Files\BurpSuitePro\burpsuite_pro.jar!\burp\Zxpb.class
 * Java compiler version: 21 (65.0)
 * JD-Core Version:       1.1.3
 */