package burp;

import java.math.BigInteger;

class Zxsb extends ClassLoader {
  static Object ZN;
  
  static String Zh;
  
  private static final String[] a;
  
  private static final String[] b;
  
  static boolean ZW(Object[] paramArrayOfObject, Object paramObject) throws Throwable {
    // Byte code:
    //   0: invokestatic ZK : ()Z
    //   3: istore_2
    //   4: new java/lang/StringBuilder
    //   7: dup
    //   8: invokespecial <init> : ()V
    //   11: astore_3
    //   12: iconst_0
    //   13: istore #4
    //   15: iload #4
    //   17: bipush #32
    //   19: if_icmpge -> 1355
    //   22: iload #4
    //   24: tableswitch default -> 1348, 0 -> 168, 1 -> 205, 2 -> 242, 3 -> 279, 4 -> 316, 5 -> 353, 6 -> 390, 7 -> 427, 8 -> 464, 9 -> 501, 10 -> 538, 11 -> 575, 12 -> 612, 13 -> 649, 14 -> 686, 15 -> 723, 16 -> 760, 17 -> 797, 18 -> 834, 19 -> 871, 20 -> 908, 21 -> 945, 22 -> 982, 23 -> 1019, 24 -> 1056, 25 -> 1093, 26 -> 1130, 27 -> 1167, 28 -> 1204, 29 -> 1241, 30 -> 1278, 31 -> 1315
    //   168: aload_3
    //   169: getstatic burp/Zls_.Zn : Ljava/lang/String;
    //   172: getstatic burp/Zezz.Zu : Ljava/lang/Object;
    //   175: checkcast java/math/BigInteger
    //   178: invokevirtual intValue : ()I
    //   181: bipush #32
    //   183: irem
    //   184: invokestatic abs : (I)I
    //   187: invokevirtual charAt : (I)C
    //   190: invokevirtual append : (C)Ljava/lang/StringBuilder;
    //   193: pop
    //   194: iload_2
    //   195: ifeq -> 1348
    //   198: goto -> 205
    //   201: invokestatic a : (Ljava/lang/Throwable;)Ljava/lang/Throwable;
    //   204: athrow
    //   205: aload_3
    //   206: getstatic burp/Zs59.Zc : Ljava/lang/String;
    //   209: getstatic burp/Ztes.ZX : Ljava/lang/Object;
    //   212: checkcast java/math/BigInteger
    //   215: invokevirtual intValue : ()I
    //   218: bipush #32
    //   220: irem
    //   221: invokestatic abs : (I)I
    //   224: invokevirtual charAt : (I)C
    //   227: invokevirtual append : (C)Ljava/lang/StringBuilder;
    //   230: pop
    //   231: iload_2
    //   232: ifeq -> 1348
    //   235: goto -> 242
    //   238: invokestatic a : (Ljava/lang/Throwable;)Ljava/lang/Throwable;
    //   241: athrow
    //   242: aload_3
    //   243: getstatic burp/Zltb.ZO : Ljava/lang/String;
    //   246: getstatic burp/Zb3p.Zx : Ljava/lang/Object;
    //   249: checkcast java/math/BigInteger
    //   252: invokevirtual intValue : ()I
    //   255: bipush #32
    //   257: irem
    //   258: invokestatic abs : (I)I
    //   261: invokevirtual charAt : (I)C
    //   264: invokevirtual append : (C)Ljava/lang/StringBuilder;
    //   267: pop
    //   268: iload_2
    //   269: ifeq -> 1348
    //   272: goto -> 279
    //   275: invokestatic a : (Ljava/lang/Throwable;)Ljava/lang/Throwable;
    //   278: athrow
    //   279: aload_3
    //   280: getstatic burp/Zs36.Zr : Ljava/lang/String;
    //   283: getstatic burp/Zb3p.Zx : Ljava/lang/Object;
    //   286: checkcast java/math/BigInteger
    //   289: invokevirtual intValue : ()I
    //   292: bipush #32
    //   294: irem
    //   295: invokestatic abs : (I)I
    //   298: invokevirtual charAt : (I)C
    //   301: invokevirtual append : (C)Ljava/lang/StringBuilder;
    //   304: pop
    //   305: iload_2
    //   306: ifeq -> 1348
    //   309: goto -> 316
    //   312: invokestatic a : (Ljava/lang/Throwable;)Ljava/lang/Throwable;
    //   315: athrow
    //   316: aload_3
    //   317: getstatic burp/Zz9p.ZC : Ljava/lang/String;
    //   320: getstatic burp/Zgdt.Zb : Ljava/lang/Object;
    //   323: checkcast java/math/BigInteger
    //   326: invokevirtual intValue : ()I
    //   329: bipush #32
    //   331: irem
    //   332: invokestatic abs : (I)I
    //   335: invokevirtual charAt : (I)C
    //   338: invokevirtual append : (C)Ljava/lang/StringBuilder;
    //   341: pop
    //   342: iload_2
    //   343: ifeq -> 1348
    //   346: goto -> 353
    //   349: invokestatic a : (Ljava/lang/Throwable;)Ljava/lang/Throwable;
    //   352: athrow
    //   353: aload_3
    //   354: getstatic burp/Zlno.ZM : Ljava/lang/String;
    //   357: getstatic burp/Zzv.Zu : Ljava/lang/Object;
    //   360: checkcast java/math/BigInteger
    //   363: invokevirtual intValue : ()I
    //   366: bipush #32
    //   368: irem
    //   369: invokestatic abs : (I)I
    //   372: invokevirtual charAt : (I)C
    //   375: invokevirtual append : (C)Ljava/lang/StringBuilder;
    //   378: pop
    //   379: iload_2
    //   380: ifeq -> 1348
    //   383: goto -> 390
    //   386: invokestatic a : (Ljava/lang/Throwable;)Ljava/lang/Throwable;
    //   389: athrow
    //   390: aload_3
    //   391: getstatic burp/Zxn7.ZG : Ljava/lang/String;
    //   394: getstatic burp/Zmiy.Zi : Ljava/lang/Object;
    //   397: checkcast java/math/BigInteger
    //   400: invokevirtual intValue : ()I
    //   403: bipush #32
    //   405: irem
    //   406: invokestatic abs : (I)I
    //   409: invokevirtual charAt : (I)C
    //   412: invokevirtual append : (C)Ljava/lang/StringBuilder;
    //   415: pop
    //   416: iload_2
    //   417: ifeq -> 1348
    //   420: goto -> 427
    //   423: invokestatic a : (Ljava/lang/Throwable;)Ljava/lang/Throwable;
    //   426: athrow
    //   427: aload_3
    //   428: getstatic burp/Zxn7.ZG : Ljava/lang/String;
    //   431: getstatic burp/Zl_9.ZM : Ljava/lang/Object;
    //   434: checkcast java/math/BigInteger
    //   437: invokevirtual intValue : ()I
    //   440: bipush #32
    //   442: irem
    //   443: invokestatic abs : (I)I
    //   446: invokevirtual charAt : (I)C
    //   449: invokevirtual append : (C)Ljava/lang/StringBuilder;
    //   452: pop
    //   453: iload_2
    //   454: ifeq -> 1348
    //   457: goto -> 464
    //   460: invokestatic a : (Ljava/lang/Throwable;)Ljava/lang/Throwable;
    //   463: athrow
    //   464: aload_3
    //   465: getstatic burp/Zlyf.ZU : Ljava/lang/String;
    //   468: getstatic burp/Zkvq.Zz : Ljava/lang/Object;
    //   471: checkcast java/math/BigInteger
    //   474: invokevirtual intValue : ()I
    //   477: bipush #32
    //   479: irem
    //   480: invokestatic abs : (I)I
    //   483: invokevirtual charAt : (I)C
    //   486: invokevirtual append : (C)Ljava/lang/StringBuilder;
    //   489: pop
    //   490: iload_2
    //   491: ifeq -> 1348
    //   494: goto -> 501
    //   497: invokestatic a : (Ljava/lang/Throwable;)Ljava/lang/Throwable;
    //   500: athrow
    //   501: aload_3
    //   502: getstatic burp/Ze3t.ZG : Ljava/lang/String;
    //   505: getstatic burp/Zgdj.ZT : Ljava/lang/Object;
    //   508: checkcast java/math/BigInteger
    //   511: invokevirtual intValue : ()I
    //   514: bipush #32
    //   516: irem
    //   517: invokestatic abs : (I)I
    //   520: invokevirtual charAt : (I)C
    //   523: invokevirtual append : (C)Ljava/lang/StringBuilder;
    //   526: pop
    //   527: iload_2
    //   528: ifeq -> 1348
    //   531: goto -> 538
    //   534: invokestatic a : (Ljava/lang/Throwable;)Ljava/lang/Throwable;
    //   537: athrow
    //   538: aload_3
    //   539: getstatic burp/Zb3p.ZX : Ljava/lang/String;
    //   542: getstatic burp/Zs_.Zs : Ljava/lang/Object;
    //   545: checkcast java/math/BigInteger
    //   548: invokevirtual intValue : ()I
    //   551: bipush #32
    //   553: irem
    //   554: invokestatic abs : (I)I
    //   557: invokevirtual charAt : (I)C
    //   560: invokevirtual append : (C)Ljava/lang/StringBuilder;
    //   563: pop
    //   564: iload_2
    //   565: ifeq -> 1348
    //   568: goto -> 575
    //   571: invokestatic a : (Ljava/lang/Throwable;)Ljava/lang/Throwable;
    //   574: athrow
    //   575: aload_3
    //   576: getstatic burp/Zls_.Zn : Ljava/lang/String;
    //   579: getstatic burp/Zsej.ZT : Ljava/lang/Object;
    //   582: checkcast java/math/BigInteger
    //   585: invokevirtual intValue : ()I
    //   588: bipush #32
    //   590: irem
    //   591: invokestatic abs : (I)I
    //   594: invokevirtual charAt : (I)C
    //   597: invokevirtual append : (C)Ljava/lang/StringBuilder;
    //   600: pop
    //   601: iload_2
    //   602: ifeq -> 1348
    //   605: goto -> 612
    //   608: invokestatic a : (Ljava/lang/Throwable;)Ljava/lang/Throwable;
    //   611: athrow
    //   612: aload_3
    //   613: getstatic burp/Zs0b.ZT : Ljava/lang/String;
    //   616: getstatic burp/Zz58.ZD : Ljava/lang/Object;
    //   619: checkcast java/math/BigInteger
    //   622: invokevirtual intValue : ()I
    //   625: bipush #32
    //   627: irem
    //   628: invokestatic abs : (I)I
    //   631: invokevirtual charAt : (I)C
    //   634: invokevirtual append : (C)Ljava/lang/StringBuilder;
    //   637: pop
    //   638: iload_2
    //   639: ifeq -> 1348
    //   642: goto -> 649
    //   645: invokestatic a : (Ljava/lang/Throwable;)Ljava/lang/Throwable;
    //   648: athrow
    //   649: aload_3
    //   650: getstatic burp/Zoa.ZF : Ljava/lang/String;
    //   653: getstatic burp/Zljx.ZZ : Ljava/lang/Object;
    //   656: checkcast java/math/BigInteger
    //   659: invokevirtual intValue : ()I
    //   662: bipush #32
    //   664: irem
    //   665: invokestatic abs : (I)I
    //   668: invokevirtual charAt : (I)C
    //   671: invokevirtual append : (C)Ljava/lang/StringBuilder;
    //   674: pop
    //   675: iload_2
    //   676: ifeq -> 1348
    //   679: goto -> 686
    //   682: invokestatic a : (Ljava/lang/Throwable;)Ljava/lang/Throwable;
    //   685: athrow
    //   686: aload_3
    //   687: getstatic burp/Zsej.Zd : Ljava/lang/String;
    //   690: getstatic burp/Zsgj.ZK : Ljava/lang/Object;
    //   693: checkcast java/math/BigInteger
    //   696: invokevirtual intValue : ()I
    //   699: bipush #32
    //   701: irem
    //   702: invokestatic abs : (I)I
    //   705: invokevirtual charAt : (I)C
    //   708: invokevirtual append : (C)Ljava/lang/StringBuilder;
    //   711: pop
    //   712: iload_2
    //   713: ifeq -> 1348
    //   716: goto -> 723
    //   719: invokestatic a : (Ljava/lang/Throwable;)Ljava/lang/Throwable;
    //   722: athrow
    //   723: aload_3
    //   724: getstatic burp/Zei_.ZZ : Ljava/lang/String;
    //   727: getstatic burp/Zxnm.ZW : Ljava/lang/Object;
    //   730: checkcast java/math/BigInteger
    //   733: invokevirtual intValue : ()I
    //   736: bipush #32
    //   738: irem
    //   739: invokestatic abs : (I)I
    //   742: invokevirtual charAt : (I)C
    //   745: invokevirtual append : (C)Ljava/lang/StringBuilder;
    //   748: pop
    //   749: iload_2
    //   750: ifeq -> 1348
    //   753: goto -> 760
    //   756: invokestatic a : (Ljava/lang/Throwable;)Ljava/lang/Throwable;
    //   759: athrow
    //   760: aload_3
    //   761: getstatic burp/Zls_.Zn : Ljava/lang/String;
    //   764: getstatic burp/Zty5.Zf : Ljava/lang/Object;
    //   767: checkcast java/math/BigInteger
    //   770: invokevirtual intValue : ()I
    //   773: bipush #32
    //   775: irem
    //   776: invokestatic abs : (I)I
    //   779: invokevirtual charAt : (I)C
    //   782: invokevirtual append : (C)Ljava/lang/StringBuilder;
    //   785: pop
    //   786: iload_2
    //   787: ifeq -> 1348
    //   790: goto -> 797
    //   793: invokestatic a : (Ljava/lang/Throwable;)Ljava/lang/Throwable;
    //   796: athrow
    //   797: aload_3
    //   798: getstatic burp/Zmjr.Zc : Ljava/lang/String;
    //   801: getstatic burp/Zs33.ZT : Ljava/lang/Object;
    //   804: checkcast java/math/BigInteger
    //   807: invokevirtual intValue : ()I
    //   810: bipush #32
    //   812: irem
    //   813: invokestatic abs : (I)I
    //   816: invokevirtual charAt : (I)C
    //   819: invokevirtual append : (C)Ljava/lang/StringBuilder;
    //   822: pop
    //   823: iload_2
    //   824: ifeq -> 1348
    //   827: goto -> 834
    //   830: invokestatic a : (Ljava/lang/Throwable;)Ljava/lang/Throwable;
    //   833: athrow
    //   834: aload_3
    //   835: getstatic burp/Ztid.Zz : Ljava/lang/String;
    //   838: getstatic burp/Zs6g.Zq : Ljava/lang/Object;
    //   841: checkcast java/math/BigInteger
    //   844: invokevirtual intValue : ()I
    //   847: bipush #32
    //   849: irem
    //   850: invokestatic abs : (I)I
    //   853: invokevirtual charAt : (I)C
    //   856: invokevirtual append : (C)Ljava/lang/StringBuilder;
    //   859: pop
    //   860: iload_2
    //   861: ifeq -> 1348
    //   864: goto -> 871
    //   867: invokestatic a : (Ljava/lang/Throwable;)Ljava/lang/Throwable;
    //   870: athrow
    //   871: aload_3
    //   872: getstatic burp/Zgwq.ZV : Ljava/lang/String;
    //   875: getstatic burp/Zz67.ZE : Ljava/lang/Object;
    //   878: checkcast java/math/BigInteger
    //   881: invokevirtual intValue : ()I
    //   884: bipush #32
    //   886: irem
    //   887: invokestatic abs : (I)I
    //   890: invokevirtual charAt : (I)C
    //   893: invokevirtual append : (C)Ljava/lang/StringBuilder;
    //   896: pop
    //   897: iload_2
    //   898: ifeq -> 1348
    //   901: goto -> 908
    //   904: invokestatic a : (Ljava/lang/Throwable;)Ljava/lang/Throwable;
    //   907: athrow
    //   908: aload_3
    //   909: getstatic burp/Zs9u.ZM : Ljava/lang/String;
    //   912: getstatic burp/Zgdj.ZT : Ljava/lang/Object;
    //   915: checkcast java/math/BigInteger
    //   918: invokevirtual intValue : ()I
    //   921: bipush #32
    //   923: irem
    //   924: invokestatic abs : (I)I
    //   927: invokevirtual charAt : (I)C
    //   930: invokevirtual append : (C)Ljava/lang/StringBuilder;
    //   933: pop
    //   934: iload_2
    //   935: ifeq -> 1348
    //   938: goto -> 945
    //   941: invokestatic a : (Ljava/lang/Throwable;)Ljava/lang/Throwable;
    //   944: athrow
    //   945: aload_3
    //   946: getstatic burp/Zmt6.Zx : Ljava/lang/String;
    //   949: getstatic burp/Zg97.Zc : Ljava/lang/Object;
    //   952: checkcast java/math/BigInteger
    //   955: invokevirtual intValue : ()I
    //   958: bipush #32
    //   960: irem
    //   961: invokestatic abs : (I)I
    //   964: invokevirtual charAt : (I)C
    //   967: invokevirtual append : (C)Ljava/lang/StringBuilder;
    //   970: pop
    //   971: iload_2
    //   972: ifeq -> 1348
    //   975: goto -> 982
    //   978: invokestatic a : (Ljava/lang/Throwable;)Ljava/lang/Throwable;
    //   981: athrow
    //   982: aload_3
    //   983: getstatic burp/Zlc5.Z_ : Ljava/lang/String;
    //   986: getstatic burp/Zsin.Za : Ljava/lang/Object;
    //   989: checkcast java/math/BigInteger
    //   992: invokevirtual intValue : ()I
    //   995: bipush #32
    //   997: irem
    //   998: invokestatic abs : (I)I
    //   1001: invokevirtual charAt : (I)C
    //   1004: invokevirtual append : (C)Ljava/lang/StringBuilder;
    //   1007: pop
    //   1008: iload_2
    //   1009: ifeq -> 1348
    //   1012: goto -> 1019
    //   1015: invokestatic a : (Ljava/lang/Throwable;)Ljava/lang/Throwable;
    //   1018: athrow
    //   1019: aload_3
    //   1020: getstatic burp/Zei_.ZZ : Ljava/lang/String;
    //   1023: getstatic burp/Zgdj.ZT : Ljava/lang/Object;
    //   1026: checkcast java/math/BigInteger
    //   1029: invokevirtual intValue : ()I
    //   1032: bipush #32
    //   1034: irem
    //   1035: invokestatic abs : (I)I
    //   1038: invokevirtual charAt : (I)C
    //   1041: invokevirtual append : (C)Ljava/lang/StringBuilder;
    //   1044: pop
    //   1045: iload_2
    //   1046: ifeq -> 1348
    //   1049: goto -> 1056
    //   1052: invokestatic a : (Ljava/lang/Throwable;)Ljava/lang/Throwable;
    //   1055: athrow
    //   1056: aload_3
    //   1057: getstatic burp/Zb9k.Za : Ljava/lang/String;
    //   1060: getstatic burp/Zmhx.ZQ : Ljava/lang/Object;
    //   1063: checkcast java/math/BigInteger
    //   1066: invokevirtual intValue : ()I
    //   1069: bipush #32
    //   1071: irem
    //   1072: invokestatic abs : (I)I
    //   1075: invokevirtual charAt : (I)C
    //   1078: invokevirtual append : (C)Ljava/lang/StringBuilder;
    //   1081: pop
    //   1082: iload_2
    //   1083: ifeq -> 1348
    //   1086: goto -> 1093
    //   1089: invokestatic a : (Ljava/lang/Throwable;)Ljava/lang/Throwable;
    //   1092: athrow
    //   1093: aload_3
    //   1094: getstatic burp/Zbxp.ZS : Ljava/lang/String;
    //   1097: getstatic burp/Zsej.ZT : Ljava/lang/Object;
    //   1100: checkcast java/math/BigInteger
    //   1103: invokevirtual intValue : ()I
    //   1106: bipush #32
    //   1108: irem
    //   1109: invokestatic abs : (I)I
    //   1112: invokevirtual charAt : (I)C
    //   1115: invokevirtual append : (C)Ljava/lang/StringBuilder;
    //   1118: pop
    //   1119: iload_2
    //   1120: ifeq -> 1348
    //   1123: goto -> 1130
    //   1126: invokestatic a : (Ljava/lang/Throwable;)Ljava/lang/Throwable;
    //   1129: athrow
    //   1130: aload_3
    //   1131: getstatic burp/Zz9p.ZC : Ljava/lang/String;
    //   1134: getstatic burp/Zbxp.ZW : Ljava/lang/Object;
    //   1137: checkcast java/math/BigInteger
    //   1140: invokevirtual intValue : ()I
    //   1143: bipush #32
    //   1145: irem
    //   1146: invokestatic abs : (I)I
    //   1149: invokevirtual charAt : (I)C
    //   1152: invokevirtual append : (C)Ljava/lang/StringBuilder;
    //   1155: pop
    //   1156: iload_2
    //   1157: ifeq -> 1348
    //   1160: goto -> 1167
    //   1163: invokestatic a : (Ljava/lang/Throwable;)Ljava/lang/Throwable;
    //   1166: athrow
    //   1167: aload_3
    //   1168: getstatic burp/Zs36.Zr : Ljava/lang/String;
    //   1171: getstatic burp/Zg97.Zc : Ljava/lang/Object;
    //   1174: checkcast java/math/BigInteger
    //   1177: invokevirtual intValue : ()I
    //   1180: bipush #32
    //   1182: irem
    //   1183: invokestatic abs : (I)I
    //   1186: invokevirtual charAt : (I)C
    //   1189: invokevirtual append : (C)Ljava/lang/StringBuilder;
    //   1192: pop
    //   1193: iload_2
    //   1194: ifeq -> 1348
    //   1197: goto -> 1204
    //   1200: invokestatic a : (Ljava/lang/Throwable;)Ljava/lang/Throwable;
    //   1203: athrow
    //   1204: aload_3
    //   1205: getstatic burp/Zxyq.Zr : Ljava/lang/String;
    //   1208: getstatic burp/Ztd6.ZI : Ljava/lang/Object;
    //   1211: checkcast java/math/BigInteger
    //   1214: invokevirtual intValue : ()I
    //   1217: bipush #32
    //   1219: irem
    //   1220: invokestatic abs : (I)I
    //   1223: invokevirtual charAt : (I)C
    //   1226: invokevirtual append : (C)Ljava/lang/StringBuilder;
    //   1229: pop
    //   1230: iload_2
    //   1231: ifeq -> 1348
    //   1234: goto -> 1241
    //   1237: invokestatic a : (Ljava/lang/Throwable;)Ljava/lang/Throwable;
    //   1240: athrow
    //   1241: aload_3
    //   1242: getstatic burp/Zgd7.Zs : Ljava/lang/String;
    //   1245: getstatic burp/Zgwq.Ze : Ljava/lang/Object;
    //   1248: checkcast java/math/BigInteger
    //   1251: invokevirtual intValue : ()I
    //   1254: bipush #32
    //   1256: irem
    //   1257: invokestatic abs : (I)I
    //   1260: invokevirtual charAt : (I)C
    //   1263: invokevirtual append : (C)Ljava/lang/StringBuilder;
    //   1266: pop
    //   1267: iload_2
    //   1268: ifeq -> 1348
    //   1271: goto -> 1278
    //   1274: invokestatic a : (Ljava/lang/Throwable;)Ljava/lang/Throwable;
    //   1277: athrow
    //   1278: aload_3
    //   1279: getstatic burp/Zxnm.Zw : Ljava/lang/String;
    //   1282: getstatic burp/Ztid.ZL : Ljava/lang/Object;
    //   1285: checkcast java/math/BigInteger
    //   1288: invokevirtual intValue : ()I
    //   1291: bipush #32
    //   1293: irem
    //   1294: invokestatic abs : (I)I
    //   1297: invokevirtual charAt : (I)C
    //   1300: invokevirtual append : (C)Ljava/lang/StringBuilder;
    //   1303: pop
    //   1304: iload_2
    //   1305: ifeq -> 1348
    //   1308: goto -> 1315
    //   1311: invokestatic a : (Ljava/lang/Throwable;)Ljava/lang/Throwable;
    //   1314: athrow
    //   1315: aload_3
    //   1316: getstatic burp/Zmjr.Zc : Ljava/lang/String;
    //   1319: getstatic burp/Zl_9.ZM : Ljava/lang/Object;
    //   1322: checkcast java/math/BigInteger
    //   1325: invokevirtual intValue : ()I
    //   1328: bipush #32
    //   1330: irem
    //   1331: invokestatic abs : (I)I
    //   1334: invokevirtual charAt : (I)C
    //   1337: invokevirtual append : (C)Ljava/lang/StringBuilder;
    //   1340: pop
    //   1341: goto -> 1348
    //   1344: invokestatic a : (Ljava/lang/Throwable;)Ljava/lang/Throwable;
    //   1347: athrow
    //   1348: iinc #4, 1
    //   1351: iload_2
    //   1352: ifeq -> 15
    //   1355: aload_3
    //   1356: invokevirtual toString : ()Ljava/lang/String;
    //   1359: putstatic burp/Zzc7.ZN : Ljava/lang/String;
    //   1362: ldc2_w 8682522807148012
    //   1365: invokestatic currentTimeMillis : ()J
    //   1368: lxor
    //   1369: lstore #5
    //   1371: lload #5
    //   1373: ldc2_w 25214903917
    //   1376: lmul
    //   1377: ldc2_w 11
    //   1380: ladd
    //   1381: ldc2_w 281474976710655
    //   1384: land
    //   1385: lstore #5
    //   1387: lload #5
    //   1389: bipush #32
    //   1391: lshl
    //   1392: lstore #7
    //   1394: lload #5
    //   1396: ldc2_w 25214903917
    //   1399: lmul
    //   1400: ldc2_w 11
    //   1403: ladd
    //   1404: ldc2_w 281474976710655
    //   1407: land
    //   1408: lstore #5
    //   1410: lload #7
    //   1412: lload #5
    //   1414: ladd
    //   1415: lstore #7
    //   1417: bipush #16
    //   1419: newarray byte
    //   1421: dup
    //   1422: iconst_0
    //   1423: bipush #48
    //   1425: bastore
    //   1426: dup
    //   1427: iconst_1
    //   1428: bipush #49
    //   1430: bastore
    //   1431: dup
    //   1432: iconst_2
    //   1433: bipush #50
    //   1435: bastore
    //   1436: dup
    //   1437: iconst_3
    //   1438: bipush #51
    //   1440: bastore
    //   1441: dup
    //   1442: iconst_4
    //   1443: bipush #52
    //   1445: bastore
    //   1446: dup
    //   1447: iconst_5
    //   1448: bipush #53
    //   1450: bastore
    //   1451: dup
    //   1452: bipush #6
    //   1454: bipush #54
    //   1456: bastore
    //   1457: dup
    //   1458: bipush #7
    //   1460: bipush #55
    //   1462: bastore
    //   1463: dup
    //   1464: bipush #8
    //   1466: bipush #56
    //   1468: bastore
    //   1469: dup
    //   1470: bipush #9
    //   1472: bipush #57
    //   1474: bastore
    //   1475: dup
    //   1476: bipush #10
    //   1478: bipush #97
    //   1480: bastore
    //   1481: dup
    //   1482: bipush #11
    //   1484: bipush #98
    //   1486: bastore
    //   1487: dup
    //   1488: bipush #12
    //   1490: bipush #99
    //   1492: bastore
    //   1493: dup
    //   1494: bipush #13
    //   1496: bipush #100
    //   1498: bastore
    //   1499: dup
    //   1500: bipush #14
    //   1502: bipush #101
    //   1504: bastore
    //   1505: dup
    //   1506: bipush #15
    //   1508: bipush #102
    //   1510: bastore
    //   1511: astore #9
    //   1513: bipush #64
    //   1515: newarray byte
    //   1517: astore #10
    //   1519: bipush #64
    //   1521: istore #11
    //   1523: bipush #16
    //   1525: istore #12
    //   1527: iload #12
    //   1529: iconst_1
    //   1530: isub
    //   1531: i2l
    //   1532: lstore #13
    //   1534: aload #10
    //   1536: iinc #11, -1
    //   1539: iload #11
    //   1541: aload #9
    //   1543: lload #7
    //   1545: lload #13
    //   1547: land
    //   1548: l2i
    //   1549: baload
    //   1550: bastore
    //   1551: lload #7
    //   1553: iconst_4
    //   1554: lushr
    //   1555: lstore #7
    //   1557: lload #7
    //   1559: lconst_0
    //   1560: lcmp
    //   1561: ifne -> 1534
    //   1564: bipush #64
    //   1566: iload #11
    //   1568: isub
    //   1569: newarray byte
    //   1571: astore #4
    //   1573: iconst_0
    //   1574: istore #15
    //   1576: iload #15
    //   1578: aload #4
    //   1580: arraylength
    //   1581: if_icmpge -> 1604
    //   1584: aload #4
    //   1586: iload #15
    //   1588: aload #10
    //   1590: iload #11
    //   1592: iload #15
    //   1594: iadd
    //   1595: baload
    //   1596: bastore
    //   1597: iinc #15, 1
    //   1600: iload_2
    //   1601: ifeq -> 1576
    //   1604: aload #4
    //   1606: arraylength
    //   1607: bipush #10
    //   1609: if_icmplt -> 1371
    //   1612: new java/io/ByteArrayOutputStream
    //   1615: dup
    //   1616: invokespecial <init> : ()V
    //   1619: astore #4
    //   1621: getstatic burp/Zly0.ZE : Ljava/lang/String;
    //   1624: astore #5
    //   1626: iconst_0
    //   1627: istore #6
    //   1629: iload #6
    //   1631: aload #5
    //   1633: invokevirtual length : ()I
    //   1636: if_icmpge -> 1667
    //   1639: aload #4
    //   1641: aload #5
    //   1643: iload #6
    //   1645: iload #6
    //   1647: iconst_2
    //   1648: iadd
    //   1649: invokevirtual substring : (II)Ljava/lang/String;
    //   1652: bipush #16
    //   1654: invokestatic parseInt : (Ljava/lang/String;I)I
    //   1657: invokevirtual write : (I)V
    //   1660: iinc #6, 2
    //   1663: iload_2
    //   1664: ifeq -> 1629
    //   1667: aload #4
    //   1669: invokevirtual toByteArray : ()[B
    //   1672: astore #6
    //   1674: getstatic burp/Zr_k.Zx : Ljava/lang/Object;
    //   1677: checkcast java/math/BigInteger
    //   1680: invokevirtual toByteArray : ()[B
    //   1683: astore #7
    //   1685: sipush #256
    //   1688: newarray byte
    //   1690: astore #9
    //   1692: sipush #256
    //   1695: newarray int
    //   1697: astore #10
    //   1699: sipush #256
    //   1702: newarray int
    //   1704: astore #11
    //   1706: sipush #256
    //   1709: newarray int
    //   1711: astore #12
    //   1713: sipush #256
    //   1716: newarray int
    //   1718: astore #13
    //   1720: bipush #10
    //   1722: newarray int
    //   1724: astore #14
    //   1726: sipush #283
    //   1729: istore #15
    //   1731: iconst_0
    //   1732: istore #17
    //   1734: iload #17
    //   1736: sipush #256
    //   1739: if_icmpge -> 1973
    //   1742: sipush #28804
    //   1745: sipush #19234
    //   1748: invokestatic a : (II)Ljava/lang/String;
    //   1751: iload #17
    //   1753: iconst_1
    //   1754: iushr
    //   1755: invokevirtual charAt : (I)C
    //   1758: istore #26
    //   1760: iload #17
    //   1762: iconst_1
    //   1763: iand
    //   1764: ifne -> 1779
    //   1767: iload #26
    //   1769: bipush #8
    //   1771: iushr
    //   1772: goto -> 1781
    //   1775: invokestatic a : (Ljava/lang/Throwable;)Ljava/lang/Throwable;
    //   1778: athrow
    //   1779: iload #26
    //   1781: i2b
    //   1782: sipush #255
    //   1785: iand
    //   1786: istore #16
    //   1788: iload #17
    //   1790: iconst_1
    //   1791: ishl
    //   1792: istore #18
    //   1794: iload #18
    //   1796: sipush #256
    //   1799: if_icmplt -> 1809
    //   1802: iload #18
    //   1804: iload #15
    //   1806: ixor
    //   1807: istore #18
    //   1809: iload #18
    //   1811: iconst_1
    //   1812: ishl
    //   1813: istore #19
    //   1815: iload #19
    //   1817: sipush #256
    //   1820: if_icmplt -> 1830
    //   1823: iload #19
    //   1825: iload #15
    //   1827: ixor
    //   1828: istore #19
    //   1830: iload #19
    //   1832: iconst_1
    //   1833: ishl
    //   1834: istore #20
    //   1836: iload #20
    //   1838: sipush #256
    //   1841: if_icmplt -> 1851
    //   1844: iload #20
    //   1846: iload #15
    //   1848: ixor
    //   1849: istore #20
    //   1851: iload #20
    //   1853: iload #17
    //   1855: ixor
    //   1856: istore #21
    //   1858: iload #21
    //   1860: iload #18
    //   1862: ixor
    //   1863: istore #22
    //   1865: iload #21
    //   1867: iload #19
    //   1869: ixor
    //   1870: istore #23
    //   1872: iload #20
    //   1874: iload #19
    //   1876: ixor
    //   1877: iload #18
    //   1879: ixor
    //   1880: istore #24
    //   1882: aload #9
    //   1884: iload #17
    //   1886: iload #16
    //   1888: i2b
    //   1889: bastore
    //   1890: aload #10
    //   1892: iload #16
    //   1894: iload #24
    //   1896: bipush #24
    //   1898: ishl
    //   1899: iload #21
    //   1901: bipush #16
    //   1903: ishl
    //   1904: ior
    //   1905: iload #23
    //   1907: bipush #8
    //   1909: ishl
    //   1910: ior
    //   1911: iload #22
    //   1913: ior
    //   1914: dup
    //   1915: istore #25
    //   1917: iastore
    //   1918: aload #11
    //   1920: iload #16
    //   1922: iload #25
    //   1924: bipush #8
    //   1926: iushr
    //   1927: iload #25
    //   1929: bipush #24
    //   1931: ishl
    //   1932: ior
    //   1933: iastore
    //   1934: aload #12
    //   1936: iload #16
    //   1938: iload #25
    //   1940: bipush #16
    //   1942: iushr
    //   1943: iload #25
    //   1945: bipush #16
    //   1947: ishl
    //   1948: ior
    //   1949: iastore
    //   1950: aload #13
    //   1952: iload #16
    //   1954: iload #25
    //   1956: bipush #24
    //   1958: iushr
    //   1959: iload #25
    //   1961: bipush #8
    //   1963: ishl
    //   1964: ior
    //   1965: iastore
    //   1966: iinc #17, 1
    //   1969: iload_2
    //   1970: ifeq -> 1734
    //   1973: iconst_1
    //   1974: istore #26
    //   1976: aload #14
    //   1978: iconst_0
    //   1979: iload #26
    //   1981: bipush #24
    //   1983: ishl
    //   1984: iastore
    //   1985: iconst_1
    //   1986: istore #27
    //   1988: iload #27
    //   1990: bipush #10
    //   1992: if_icmpge -> 2033
    //   1995: iload #26
    //   1997: iconst_1
    //   1998: ishl
    //   1999: istore #26
    //   2001: iload #26
    //   2003: sipush #256
    //   2006: if_icmplt -> 2016
    //   2009: iload #26
    //   2011: iload #15
    //   2013: ixor
    //   2014: istore #26
    //   2016: aload #14
    //   2018: iload #27
    //   2020: iload #26
    //   2022: bipush #24
    //   2024: ishl
    //   2025: iastore
    //   2026: iinc #27, 1
    //   2029: iload_2
    //   2030: ifeq -> 1988
    //   2033: iconst_4
    //   2034: istore #27
    //   2036: iload #27
    //   2038: bipush #6
    //   2040: iadd
    //   2041: istore #28
    //   2043: iconst_4
    //   2044: iload #28
    //   2046: iconst_1
    //   2047: iadd
    //   2048: imul
    //   2049: istore #29
    //   2051: iload #29
    //   2053: newarray int
    //   2055: astore #30
    //   2057: iload #29
    //   2059: newarray int
    //   2061: astore #31
    //   2063: iconst_0
    //   2064: istore #26
    //   2066: iconst_0
    //   2067: istore #33
    //   2069: iconst_0
    //   2070: istore #34
    //   2072: iload #33
    //   2074: iload #27
    //   2076: if_icmpge -> 2144
    //   2079: aload #30
    //   2081: iload #33
    //   2083: aload #6
    //   2085: iload #34
    //   2087: baload
    //   2088: bipush #24
    //   2090: ishl
    //   2091: aload #6
    //   2093: iload #34
    //   2095: iconst_1
    //   2096: iadd
    //   2097: baload
    //   2098: sipush #255
    //   2101: iand
    //   2102: bipush #16
    //   2104: ishl
    //   2105: ior
    //   2106: aload #6
    //   2108: iload #34
    //   2110: iconst_2
    //   2111: iadd
    //   2112: baload
    //   2113: sipush #255
    //   2116: iand
    //   2117: bipush #8
    //   2119: ishl
    //   2120: ior
    //   2121: aload #6
    //   2123: iload #34
    //   2125: iconst_3
    //   2126: iadd
    //   2127: baload
    //   2128: sipush #255
    //   2131: iand
    //   2132: ior
    //   2133: iastore
    //   2134: iinc #33, 1
    //   2137: iinc #34, 4
    //   2140: iload_2
    //   2141: ifeq -> 2072
    //   2144: iload #27
    //   2146: istore #33
    //   2148: iconst_0
    //   2149: istore #34
    //   2151: iload #33
    //   2153: iload #29
    //   2155: if_icmpge -> 2282
    //   2158: aload #30
    //   2160: iload #33
    //   2162: iconst_1
    //   2163: isub
    //   2164: iaload
    //   2165: istore #32
    //   2167: iload #34
    //   2169: ifne -> 2256
    //   2172: iload #27
    //   2174: istore #34
    //   2176: aload #9
    //   2178: iload #32
    //   2180: bipush #16
    //   2182: iushr
    //   2183: sipush #255
    //   2186: iand
    //   2187: baload
    //   2188: bipush #24
    //   2190: ishl
    //   2191: aload #9
    //   2193: iload #32
    //   2195: bipush #8
    //   2197: iushr
    //   2198: sipush #255
    //   2201: iand
    //   2202: baload
    //   2203: sipush #255
    //   2206: iand
    //   2207: bipush #16
    //   2209: ishl
    //   2210: ior
    //   2211: aload #9
    //   2213: iload #32
    //   2215: sipush #255
    //   2218: iand
    //   2219: baload
    //   2220: sipush #255
    //   2223: iand
    //   2224: bipush #8
    //   2226: ishl
    //   2227: ior
    //   2228: aload #9
    //   2230: iload #32
    //   2232: bipush #24
    //   2234: iushr
    //   2235: baload
    //   2236: sipush #255
    //   2239: iand
    //   2240: ior
    //   2241: istore #32
    //   2243: iload #32
    //   2245: aload #14
    //   2247: iload #26
    //   2249: iinc #26, 1
    //   2252: iaload
    //   2253: ixor
    //   2254: istore #32
    //   2256: aload #30
    //   2258: iload #33
    //   2260: aload #30
    //   2262: iload #33
    //   2264: iload #27
    //   2266: isub
    //   2267: iaload
    //   2268: iload #32
    //   2270: ixor
    //   2271: iastore
    //   2272: iinc #33, 1
    //   2275: iinc #34, -1
    //   2278: iload_2
    //   2279: ifeq -> 2151
    //   2282: iconst_0
    //   2283: istore #33
    //   2285: iconst_4
    //   2286: iload #28
    //   2288: imul
    //   2289: istore #34
    //   2291: aload #31
    //   2293: iload #33
    //   2295: aload #30
    //   2297: iload #34
    //   2299: iaload
    //   2300: iastore
    //   2301: aload #31
    //   2303: iload #33
    //   2305: iconst_1
    //   2306: iadd
    //   2307: aload #30
    //   2309: iload #34
    //   2311: iconst_1
    //   2312: iadd
    //   2313: iaload
    //   2314: iastore
    //   2315: aload #31
    //   2317: iload #33
    //   2319: iconst_2
    //   2320: iadd
    //   2321: aload #30
    //   2323: iload #34
    //   2325: iconst_2
    //   2326: iadd
    //   2327: iaload
    //   2328: iastore
    //   2329: aload #31
    //   2331: iload #33
    //   2333: iconst_3
    //   2334: iadd
    //   2335: aload #30
    //   2337: iload #34
    //   2339: iconst_3
    //   2340: iadd
    //   2341: iaload
    //   2342: iastore
    //   2343: iinc #33, 4
    //   2346: iinc #34, -4
    //   2349: iconst_1
    //   2350: istore #36
    //   2352: iload #36
    //   2354: iload #28
    //   2356: if_icmpge -> 2720
    //   2359: aload #30
    //   2361: iload #34
    //   2363: iaload
    //   2364: istore #35
    //   2366: aload #31
    //   2368: iload #33
    //   2370: aload #10
    //   2372: aload #9
    //   2374: iload #35
    //   2376: bipush #24
    //   2378: iushr
    //   2379: baload
    //   2380: sipush #255
    //   2383: iand
    //   2384: iaload
    //   2385: aload #11
    //   2387: aload #9
    //   2389: iload #35
    //   2391: bipush #16
    //   2393: iushr
    //   2394: sipush #255
    //   2397: iand
    //   2398: baload
    //   2399: sipush #255
    //   2402: iand
    //   2403: iaload
    //   2404: ixor
    //   2405: aload #12
    //   2407: aload #9
    //   2409: iload #35
    //   2411: bipush #8
    //   2413: iushr
    //   2414: sipush #255
    //   2417: iand
    //   2418: baload
    //   2419: sipush #255
    //   2422: iand
    //   2423: iaload
    //   2424: ixor
    //   2425: aload #13
    //   2427: aload #9
    //   2429: iload #35
    //   2431: sipush #255
    //   2434: iand
    //   2435: baload
    //   2436: sipush #255
    //   2439: iand
    //   2440: iaload
    //   2441: ixor
    //   2442: iastore
    //   2443: aload #30
    //   2445: iload #34
    //   2447: iconst_1
    //   2448: iadd
    //   2449: iaload
    //   2450: istore #35
    //   2452: aload #31
    //   2454: iload #33
    //   2456: iconst_1
    //   2457: iadd
    //   2458: aload #10
    //   2460: aload #9
    //   2462: iload #35
    //   2464: bipush #24
    //   2466: iushr
    //   2467: baload
    //   2468: sipush #255
    //   2471: iand
    //   2472: iaload
    //   2473: aload #11
    //   2475: aload #9
    //   2477: iload #35
    //   2479: bipush #16
    //   2481: iushr
    //   2482: sipush #255
    //   2485: iand
    //   2486: baload
    //   2487: sipush #255
    //   2490: iand
    //   2491: iaload
    //   2492: ixor
    //   2493: aload #12
    //   2495: aload #9
    //   2497: iload #35
    //   2499: bipush #8
    //   2501: iushr
    //   2502: sipush #255
    //   2505: iand
    //   2506: baload
    //   2507: sipush #255
    //   2510: iand
    //   2511: iaload
    //   2512: ixor
    //   2513: aload #13
    //   2515: aload #9
    //   2517: iload #35
    //   2519: sipush #255
    //   2522: iand
    //   2523: baload
    //   2524: sipush #255
    //   2527: iand
    //   2528: iaload
    //   2529: ixor
    //   2530: iastore
    //   2531: aload #30
    //   2533: iload #34
    //   2535: iconst_2
    //   2536: iadd
    //   2537: iaload
    //   2538: istore #35
    //   2540: aload #31
    //   2542: iload #33
    //   2544: iconst_2
    //   2545: iadd
    //   2546: aload #10
    //   2548: aload #9
    //   2550: iload #35
    //   2552: bipush #24
    //   2554: iushr
    //   2555: baload
    //   2556: sipush #255
    //   2559: iand
    //   2560: iaload
    //   2561: aload #11
    //   2563: aload #9
    //   2565: iload #35
    //   2567: bipush #16
    //   2569: iushr
    //   2570: sipush #255
    //   2573: iand
    //   2574: baload
    //   2575: sipush #255
    //   2578: iand
    //   2579: iaload
    //   2580: ixor
    //   2581: aload #12
    //   2583: aload #9
    //   2585: iload #35
    //   2587: bipush #8
    //   2589: iushr
    //   2590: sipush #255
    //   2593: iand
    //   2594: baload
    //   2595: sipush #255
    //   2598: iand
    //   2599: iaload
    //   2600: ixor
    //   2601: aload #13
    //   2603: aload #9
    //   2605: iload #35
    //   2607: sipush #255
    //   2610: iand
    //   2611: baload
    //   2612: sipush #255
    //   2615: iand
    //   2616: iaload
    //   2617: ixor
    //   2618: iastore
    //   2619: aload #30
    //   2621: iload #34
    //   2623: iconst_3
    //   2624: iadd
    //   2625: iaload
    //   2626: istore #35
    //   2628: aload #31
    //   2630: iload #33
    //   2632: iconst_3
    //   2633: iadd
    //   2634: aload #10
    //   2636: aload #9
    //   2638: iload #35
    //   2640: bipush #24
    //   2642: iushr
    //   2643: baload
    //   2644: sipush #255
    //   2647: iand
    //   2648: iaload
    //   2649: aload #11
    //   2651: aload #9
    //   2653: iload #35
    //   2655: bipush #16
    //   2657: iushr
    //   2658: sipush #255
    //   2661: iand
    //   2662: baload
    //   2663: sipush #255
    //   2666: iand
    //   2667: iaload
    //   2668: ixor
    //   2669: aload #12
    //   2671: aload #9
    //   2673: iload #35
    //   2675: bipush #8
    //   2677: iushr
    //   2678: sipush #255
    //   2681: iand
    //   2682: baload
    //   2683: sipush #255
    //   2686: iand
    //   2687: iaload
    //   2688: ixor
    //   2689: aload #13
    //   2691: aload #9
    //   2693: iload #35
    //   2695: sipush #255
    //   2698: iand
    //   2699: baload
    //   2700: sipush #255
    //   2703: iand
    //   2704: iaload
    //   2705: ixor
    //   2706: iastore
    //   2707: iinc #33, 4
    //   2710: iinc #34, -4
    //   2713: iinc #36, 1
    //   2716: iload_2
    //   2717: ifeq -> 2352
    //   2720: aload #31
    //   2722: iload #33
    //   2724: aload #30
    //   2726: iload #34
    //   2728: iaload
    //   2729: iastore
    //   2730: aload #31
    //   2732: iload #33
    //   2734: iconst_1
    //   2735: iadd
    //   2736: aload #30
    //   2738: iload #34
    //   2740: iconst_1
    //   2741: iadd
    //   2742: iaload
    //   2743: iastore
    //   2744: aload #31
    //   2746: iload #33
    //   2748: iconst_2
    //   2749: iadd
    //   2750: aload #30
    //   2752: iload #34
    //   2754: iconst_2
    //   2755: iadd
    //   2756: iaload
    //   2757: iastore
    //   2758: aload #31
    //   2760: iload #33
    //   2762: iconst_3
    //   2763: iadd
    //   2764: aload #30
    //   2766: iload #34
    //   2768: iconst_3
    //   2769: iadd
    //   2770: iaload
    //   2771: iastore
    //   2772: iconst_0
    //   2773: newarray byte
    //   2775: astore #36
    //   2777: aload #7
    //   2779: arraylength
    //   2780: bipush #16
    //   2782: irem
    //   2783: ifeq -> 2807
    //   2786: new java/lang/Exception
    //   2789: dup
    //   2790: sipush #28802
    //   2793: sipush #-20900
    //   2796: invokestatic a : (II)Ljava/lang/String;
    //   2799: invokespecial <init> : (Ljava/lang/String;)V
    //   2802: athrow
    //   2803: invokestatic a : (Ljava/lang/Throwable;)Ljava/lang/Throwable;
    //   2806: athrow
    //   2807: bipush #10
    //   2809: istore #37
    //   2811: sipush #28801
    //   2814: sipush #256
    //   2817: newarray byte
    //   2819: astore #38
    //   2821: sipush #-9737
    //   2824: sipush #256
    //   2827: newarray int
    //   2829: astore #39
    //   2831: sipush #256
    //   2834: newarray int
    //   2836: astore #40
    //   2838: sipush #256
    //   2841: newarray int
    //   2843: astore #41
    //   2845: sipush #256
    //   2848: newarray int
    //   2850: astore #42
    //   2852: sipush #283
    //   2855: istore #15
    //   2857: invokestatic a : (II)Ljava/lang/String;
    //   2860: astore #43
    //   2862: iconst_0
    //   2863: istore #17
    //   2865: iload #17
    //   2867: sipush #256
    //   2870: if_icmpge -> 3097
    //   2873: aload #43
    //   2875: iload #17
    //   2877: iconst_1
    //   2878: iushr
    //   2879: invokevirtual charAt : (I)C
    //   2882: istore #44
    //   2884: iload #17
    //   2886: iconst_1
    //   2887: iand
    //   2888: ifne -> 2903
    //   2891: iload #44
    //   2893: bipush #8
    //   2895: iushr
    //   2896: goto -> 2905
    //   2899: invokestatic a : (Ljava/lang/Throwable;)Ljava/lang/Throwable;
    //   2902: athrow
    //   2903: iload #44
    //   2905: i2b
    //   2906: sipush #255
    //   2909: iand
    //   2910: istore #16
    //   2912: iload #17
    //   2914: iconst_1
    //   2915: ishl
    //   2916: istore #18
    //   2918: iload #18
    //   2920: sipush #256
    //   2923: if_icmplt -> 2933
    //   2926: iload #18
    //   2928: iload #15
    //   2930: ixor
    //   2931: istore #18
    //   2933: iload #18
    //   2935: iconst_1
    //   2936: ishl
    //   2937: istore #19
    //   2939: iload #19
    //   2941: sipush #256
    //   2944: if_icmplt -> 2954
    //   2947: iload #19
    //   2949: iload #15
    //   2951: ixor
    //   2952: istore #19
    //   2954: iload #19
    //   2956: iconst_1
    //   2957: ishl
    //   2958: istore #20
    //   2960: iload #20
    //   2962: sipush #256
    //   2965: if_icmplt -> 2975
    //   2968: iload #20
    //   2970: iload #15
    //   2972: ixor
    //   2973: istore #20
    //   2975: iload #20
    //   2977: iload #17
    //   2979: ixor
    //   2980: istore #21
    //   2982: iload #21
    //   2984: iload #18
    //   2986: ixor
    //   2987: istore #22
    //   2989: iload #21
    //   2991: iload #19
    //   2993: ixor
    //   2994: istore #23
    //   2996: iload #20
    //   2998: iload #19
    //   3000: ixor
    //   3001: iload #18
    //   3003: ixor
    //   3004: istore #24
    //   3006: aload #38
    //   3008: iload #16
    //   3010: iload #17
    //   3012: i2b
    //   3013: bastore
    //   3014: aload #39
    //   3016: iload #16
    //   3018: iload #24
    //   3020: bipush #24
    //   3022: ishl
    //   3023: iload #21
    //   3025: bipush #16
    //   3027: ishl
    //   3028: ior
    //   3029: iload #23
    //   3031: bipush #8
    //   3033: ishl
    //   3034: ior
    //   3035: iload #22
    //   3037: ior
    //   3038: dup
    //   3039: istore #25
    //   3041: iastore
    //   3042: aload #40
    //   3044: iload #16
    //   3046: iload #25
    //   3048: bipush #8
    //   3050: iushr
    //   3051: iload #25
    //   3053: bipush #24
    //   3055: ishl
    //   3056: ior
    //   3057: iastore
    //   3058: aload #41
    //   3060: iload #16
    //   3062: iload #25
    //   3064: bipush #16
    //   3066: iushr
    //   3067: iload #25
    //   3069: bipush #16
    //   3071: ishl
    //   3072: ior
    //   3073: iastore
    //   3074: aload #42
    //   3076: iload #16
    //   3078: iload #25
    //   3080: bipush #24
    //   3082: iushr
    //   3083: iload #25
    //   3085: bipush #8
    //   3087: ishl
    //   3088: ior
    //   3089: iastore
    //   3090: iinc #17, 1
    //   3093: iload_2
    //   3094: ifeq -> 2865
    //   3097: aload #7
    //   3099: arraylength
    //   3100: newarray byte
    //   3102: astore #44
    //   3104: iconst_0
    //   3105: istore #45
    //   3107: iload #45
    //   3109: aload #7
    //   3111: arraylength
    //   3112: bipush #16
    //   3114: idiv
    //   3115: if_icmpge -> 4029
    //   3118: bipush #16
    //   3120: newarray byte
    //   3122: astore #46
    //   3124: bipush #16
    //   3126: newarray byte
    //   3128: astore #47
    //   3130: iconst_0
    //   3131: istore #48
    //   3133: iload #48
    //   3135: bipush #16
    //   3137: if_icmpge -> 3163
    //   3140: aload #46
    //   3142: iload #48
    //   3144: aload #7
    //   3146: iload #48
    //   3148: iload #45
    //   3150: bipush #16
    //   3152: imul
    //   3153: iadd
    //   3154: baload
    //   3155: bastore
    //   3156: iinc #48, 1
    //   3159: iload_2
    //   3160: ifeq -> 3133
    //   3163: iconst_0
    //   3164: istore #48
    //   3166: aload #46
    //   3168: iconst_0
    //   3169: baload
    //   3170: bipush #24
    //   3172: ishl
    //   3173: aload #46
    //   3175: iconst_1
    //   3176: baload
    //   3177: sipush #255
    //   3180: iand
    //   3181: bipush #16
    //   3183: ishl
    //   3184: ior
    //   3185: aload #46
    //   3187: iconst_2
    //   3188: baload
    //   3189: sipush #255
    //   3192: iand
    //   3193: bipush #8
    //   3195: ishl
    //   3196: ior
    //   3197: aload #46
    //   3199: iconst_3
    //   3200: baload
    //   3201: sipush #255
    //   3204: iand
    //   3205: ior
    //   3206: aload #31
    //   3208: iconst_0
    //   3209: iaload
    //   3210: ixor
    //   3211: istore #50
    //   3213: aload #46
    //   3215: iconst_4
    //   3216: baload
    //   3217: bipush #24
    //   3219: ishl
    //   3220: aload #46
    //   3222: iconst_5
    //   3223: baload
    //   3224: sipush #255
    //   3227: iand
    //   3228: bipush #16
    //   3230: ishl
    //   3231: ior
    //   3232: aload #46
    //   3234: bipush #6
    //   3236: baload
    //   3237: sipush #255
    //   3240: iand
    //   3241: bipush #8
    //   3243: ishl
    //   3244: ior
    //   3245: aload #46
    //   3247: bipush #7
    //   3249: baload
    //   3250: sipush #255
    //   3253: iand
    //   3254: ior
    //   3255: aload #31
    //   3257: iconst_1
    //   3258: iaload
    //   3259: ixor
    //   3260: istore #51
    //   3262: aload #46
    //   3264: bipush #8
    //   3266: baload
    //   3267: bipush #24
    //   3269: ishl
    //   3270: aload #46
    //   3272: bipush #9
    //   3274: baload
    //   3275: sipush #255
    //   3278: iand
    //   3279: bipush #16
    //   3281: ishl
    //   3282: ior
    //   3283: aload #46
    //   3285: bipush #10
    //   3287: baload
    //   3288: sipush #255
    //   3291: iand
    //   3292: bipush #8
    //   3294: ishl
    //   3295: ior
    //   3296: aload #46
    //   3298: bipush #11
    //   3300: baload
    //   3301: sipush #255
    //   3304: iand
    //   3305: ior
    //   3306: aload #31
    //   3308: iconst_2
    //   3309: iaload
    //   3310: ixor
    //   3311: istore #52
    //   3313: aload #46
    //   3315: bipush #12
    //   3317: baload
    //   3318: bipush #24
    //   3320: ishl
    //   3321: aload #46
    //   3323: bipush #13
    //   3325: baload
    //   3326: sipush #255
    //   3329: iand
    //   3330: bipush #16
    //   3332: ishl
    //   3333: ior
    //   3334: aload #46
    //   3336: bipush #14
    //   3338: baload
    //   3339: sipush #255
    //   3342: iand
    //   3343: bipush #8
    //   3345: ishl
    //   3346: ior
    //   3347: aload #46
    //   3349: bipush #15
    //   3351: baload
    //   3352: sipush #255
    //   3355: iand
    //   3356: ior
    //   3357: aload #31
    //   3359: iconst_3
    //   3360: iaload
    //   3361: ixor
    //   3362: istore #53
    //   3364: iconst_1
    //   3365: istore #54
    //   3367: iload #54
    //   3369: iload #37
    //   3371: if_icmpge -> 3614
    //   3374: iinc #48, 4
    //   3377: aload #39
    //   3379: iload #50
    //   3381: bipush #24
    //   3383: iushr
    //   3384: iaload
    //   3385: aload #40
    //   3387: iload #53
    //   3389: bipush #16
    //   3391: iushr
    //   3392: sipush #255
    //   3395: iand
    //   3396: iaload
    //   3397: ixor
    //   3398: aload #41
    //   3400: iload #52
    //   3402: bipush #8
    //   3404: iushr
    //   3405: sipush #255
    //   3408: iand
    //   3409: iaload
    //   3410: ixor
    //   3411: aload #42
    //   3413: iload #51
    //   3415: sipush #255
    //   3418: iand
    //   3419: iaload
    //   3420: ixor
    //   3421: aload #31
    //   3423: iload #48
    //   3425: iaload
    //   3426: ixor
    //   3427: istore #55
    //   3429: aload #39
    //   3431: iload #51
    //   3433: bipush #24
    //   3435: iushr
    //   3436: iaload
    //   3437: aload #40
    //   3439: iload #50
    //   3441: bipush #16
    //   3443: iushr
    //   3444: sipush #255
    //   3447: iand
    //   3448: iaload
    //   3449: ixor
    //   3450: aload #41
    //   3452: iload #53
    //   3454: bipush #8
    //   3456: iushr
    //   3457: sipush #255
    //   3460: iand
    //   3461: iaload
    //   3462: ixor
    //   3463: aload #42
    //   3465: iload #52
    //   3467: sipush #255
    //   3470: iand
    //   3471: iaload
    //   3472: ixor
    //   3473: aload #31
    //   3475: iload #48
    //   3477: iconst_1
    //   3478: iadd
    //   3479: iaload
    //   3480: ixor
    //   3481: istore #56
    //   3483: aload #39
    //   3485: iload #52
    //   3487: bipush #24
    //   3489: iushr
    //   3490: iaload
    //   3491: aload #40
    //   3493: iload #51
    //   3495: bipush #16
    //   3497: iushr
    //   3498: sipush #255
    //   3501: iand
    //   3502: iaload
    //   3503: ixor
    //   3504: aload #41
    //   3506: iload #50
    //   3508: bipush #8
    //   3510: iushr
    //   3511: sipush #255
    //   3514: iand
    //   3515: iaload
    //   3516: ixor
    //   3517: aload #42
    //   3519: iload #53
    //   3521: sipush #255
    //   3524: iand
    //   3525: iaload
    //   3526: ixor
    //   3527: aload #31
    //   3529: iload #48
    //   3531: iconst_2
    //   3532: iadd
    //   3533: iaload
    //   3534: ixor
    //   3535: istore #57
    //   3537: aload #39
    //   3539: iload #53
    //   3541: bipush #24
    //   3543: iushr
    //   3544: iaload
    //   3545: aload #40
    //   3547: iload #52
    //   3549: bipush #16
    //   3551: iushr
    //   3552: sipush #255
    //   3555: iand
    //   3556: iaload
    //   3557: ixor
    //   3558: aload #41
    //   3560: iload #51
    //   3562: bipush #8
    //   3564: iushr
    //   3565: sipush #255
    //   3568: iand
    //   3569: iaload
    //   3570: ixor
    //   3571: aload #42
    //   3573: iload #50
    //   3575: sipush #255
    //   3578: iand
    //   3579: iaload
    //   3580: ixor
    //   3581: aload #31
    //   3583: iload #48
    //   3585: iconst_3
    //   3586: iadd
    //   3587: iaload
    //   3588: ixor
    //   3589: istore #58
    //   3591: iload #55
    //   3593: istore #50
    //   3595: iload #56
    //   3597: istore #51
    //   3599: iload #57
    //   3601: istore #52
    //   3603: iload #58
    //   3605: istore #53
    //   3607: iinc #54, 1
    //   3610: iload_2
    //   3611: ifeq -> 3367
    //   3614: iinc #48, 4
    //   3617: aload #31
    //   3619: iload #48
    //   3621: iaload
    //   3622: istore #49
    //   3624: aload #47
    //   3626: iconst_0
    //   3627: aload #38
    //   3629: iload #50
    //   3631: bipush #24
    //   3633: iushr
    //   3634: baload
    //   3635: iload #49
    //   3637: bipush #24
    //   3639: iushr
    //   3640: ixor
    //   3641: i2b
    //   3642: bastore
    //   3643: aload #47
    //   3645: iconst_1
    //   3646: aload #38
    //   3648: iload #53
    //   3650: bipush #16
    //   3652: iushr
    //   3653: sipush #255
    //   3656: iand
    //   3657: baload
    //   3658: iload #49
    //   3660: bipush #16
    //   3662: iushr
    //   3663: ixor
    //   3664: i2b
    //   3665: bastore
    //   3666: aload #47
    //   3668: iconst_2
    //   3669: aload #38
    //   3671: iload #52
    //   3673: bipush #8
    //   3675: iushr
    //   3676: sipush #255
    //   3679: iand
    //   3680: baload
    //   3681: iload #49
    //   3683: bipush #8
    //   3685: iushr
    //   3686: ixor
    //   3687: i2b
    //   3688: bastore
    //   3689: aload #47
    //   3691: iconst_3
    //   3692: aload #38
    //   3694: iload #51
    //   3696: sipush #255
    //   3699: iand
    //   3700: baload
    //   3701: iload #49
    //   3703: ixor
    //   3704: i2b
    //   3705: bastore
    //   3706: aload #31
    //   3708: iload #48
    //   3710: iconst_1
    //   3711: iadd
    //   3712: iaload
    //   3713: istore #49
    //   3715: aload #47
    //   3717: iconst_4
    //   3718: aload #38
    //   3720: iload #51
    //   3722: bipush #24
    //   3724: iushr
    //   3725: baload
    //   3726: iload #49
    //   3728: bipush #24
    //   3730: iushr
    //   3731: ixor
    //   3732: i2b
    //   3733: bastore
    //   3734: aload #47
    //   3736: iconst_5
    //   3737: aload #38
    //   3739: iload #50
    //   3741: bipush #16
    //   3743: iushr
    //   3744: sipush #255
    //   3747: iand
    //   3748: baload
    //   3749: iload #49
    //   3751: bipush #16
    //   3753: iushr
    //   3754: ixor
    //   3755: i2b
    //   3756: bastore
    //   3757: aload #47
    //   3759: bipush #6
    //   3761: aload #38
    //   3763: iload #53
    //   3765: bipush #8
    //   3767: iushr
    //   3768: sipush #255
    //   3771: iand
    //   3772: baload
    //   3773: iload #49
    //   3775: bipush #8
    //   3777: iushr
    //   3778: ixor
    //   3779: i2b
    //   3780: bastore
    //   3781: aload #47
    //   3783: bipush #7
    //   3785: aload #38
    //   3787: iload #52
    //   3789: sipush #255
    //   3792: iand
    //   3793: baload
    //   3794: iload #49
    //   3796: ixor
    //   3797: i2b
    //   3798: bastore
    //   3799: aload #31
    //   3801: iload #48
    //   3803: iconst_2
    //   3804: iadd
    //   3805: iaload
    //   3806: istore #49
    //   3808: aload #47
    //   3810: bipush #8
    //   3812: aload #38
    //   3814: iload #52
    //   3816: bipush #24
    //   3818: iushr
    //   3819: baload
    //   3820: iload #49
    //   3822: bipush #24
    //   3824: iushr
    //   3825: ixor
    //   3826: i2b
    //   3827: bastore
    //   3828: aload #47
    //   3830: bipush #9
    //   3832: aload #38
    //   3834: iload #51
    //   3836: bipush #16
    //   3838: iushr
    //   3839: sipush #255
    //   3842: iand
    //   3843: baload
    //   3844: iload #49
    //   3846: bipush #16
    //   3848: iushr
    //   3849: ixor
    //   3850: i2b
    //   3851: bastore
    //   3852: aload #47
    //   3854: bipush #10
    //   3856: aload #38
    //   3858: iload #50
    //   3860: bipush #8
    //   3862: iushr
    //   3863: sipush #255
    //   3866: iand
    //   3867: baload
    //   3868: iload #49
    //   3870: bipush #8
    //   3872: iushr
    //   3873: ixor
    //   3874: i2b
    //   3875: bastore
    //   3876: aload #47
    //   3878: bipush #11
    //   3880: aload #38
    //   3882: iload #53
    //   3884: sipush #255
    //   3887: iand
    //   3888: baload
    //   3889: iload #49
    //   3891: ixor
    //   3892: i2b
    //   3893: bastore
    //   3894: aload #31
    //   3896: iload #48
    //   3898: iconst_3
    //   3899: iadd
    //   3900: iaload
    //   3901: istore #49
    //   3903: aload #47
    //   3905: bipush #12
    //   3907: aload #38
    //   3909: iload #53
    //   3911: bipush #24
    //   3913: iushr
    //   3914: baload
    //   3915: iload #49
    //   3917: bipush #24
    //   3919: iushr
    //   3920: ixor
    //   3921: i2b
    //   3922: bastore
    //   3923: aload #47
    //   3925: bipush #13
    //   3927: aload #38
    //   3929: iload #52
    //   3931: bipush #16
    //   3933: iushr
    //   3934: sipush #255
    //   3937: iand
    //   3938: baload
    //   3939: iload #49
    //   3941: bipush #16
    //   3943: iushr
    //   3944: ixor
    //   3945: i2b
    //   3946: bastore
    //   3947: aload #47
    //   3949: bipush #14
    //   3951: aload #38
    //   3953: iload #51
    //   3955: bipush #8
    //   3957: iushr
    //   3958: sipush #255
    //   3961: iand
    //   3962: baload
    //   3963: iload #49
    //   3965: bipush #8
    //   3967: iushr
    //   3968: ixor
    //   3969: i2b
    //   3970: bastore
    //   3971: aload #47
    //   3973: bipush #15
    //   3975: aload #38
    //   3977: iload #50
    //   3979: sipush #255
    //   3982: iand
    //   3983: baload
    //   3984: iload #49
    //   3986: ixor
    //   3987: i2b
    //   3988: bastore
    //   3989: iconst_0
    //   3990: istore #54
    //   3992: iload #54
    //   3994: bipush #16
    //   3996: if_icmpge -> 4022
    //   3999: aload #44
    //   4001: iload #54
    //   4003: iload #45
    //   4005: bipush #16
    //   4007: imul
    //   4008: iadd
    //   4009: aload #47
    //   4011: iload #54
    //   4013: baload
    //   4014: bastore
    //   4015: iinc #54, 1
    //   4018: iload_2
    //   4019: ifeq -> 3992
    //   4022: iinc #45, 1
    //   4025: iload_2
    //   4026: ifeq -> 3107
    //   4029: aload #44
    //   4031: arraylength
    //   4032: ifle -> 4113
    //   4035: aload #44
    //   4037: aload #44
    //   4039: arraylength
    //   4040: iconst_1
    //   4041: isub
    //   4042: baload
    //   4043: istore #45
    //   4045: iload #45
    //   4047: bipush #16
    //   4049: if_icmple -> 4060
    //   4052: aload #44
    //   4054: astore #36
    //   4056: iload_2
    //   4057: ifeq -> 4113
    //   4060: aload #44
    //   4062: arraylength
    //   4063: iload #45
    //   4065: isub
    //   4066: newarray byte
    //   4068: astore #36
    //   4070: iconst_0
    //   4071: istore #46
    //   4073: iload #46
    //   4075: aload #36
    //   4077: arraylength
    //   4078: if_icmpge -> 4113
    //   4081: iload #46
    //   4083: aload #44
    //   4085: arraylength
    //   4086: if_icmpge -> 4113
    //   4089: aload #36
    //   4091: iload #46
    //   4093: aload #44
    //   4095: iload #46
    //   4097: baload
    //   4098: bastore
    //   4099: iinc #46, 1
    //   4102: iload_2
    //   4103: ifeq -> 4073
    //   4106: goto -> 4113
    //   4109: invokestatic a : (Ljava/lang/Throwable;)Ljava/lang/Throwable;
    //   4112: athrow
    //   4113: aload #36
    //   4115: astore #8
    //   4117: sipush #28807
    //   4120: new java/math/BigInteger
    //   4123: dup
    //   4124: aload #8
    //   4126: invokespecial <init> : ([B)V
    //   4129: invokevirtual abs : ()Ljava/math/BigInteger;
    //   4132: putstatic burp/Zgdj.ZT : Ljava/lang/Object;
    //   4135: sipush #-12067
    //   4138: invokestatic a : (II)Ljava/lang/String;
    //   4141: iconst_1
    //   4142: ldc burp/Zzip
    //   4144: invokevirtual getClassLoader : ()Ljava/lang/ClassLoader;
    //   4147: invokestatic forName : (Ljava/lang/String;ZLjava/lang/ClassLoader;)Ljava/lang/Class;
    //   4150: invokevirtual getDeclaredFields : ()[Ljava/lang/reflect/Field;
    //   4153: astore #4
    //   4155: aload #4
    //   4157: arraylength
    //   4158: istore #5
    //   4160: iconst_0
    //   4161: istore #6
    //   4163: iload #6
    //   4165: iload #5
    //   4167: if_icmpge -> 4305
    //   4170: aload #4
    //   4172: iload #6
    //   4174: aaload
    //   4175: astore #7
    //   4177: aload #7
    //   4179: invokevirtual getModifiers : ()I
    //   4182: invokestatic isStatic : (I)Z
    //   4185: ifne -> 4195
    //   4188: goto -> 4298
    //   4191: invokestatic a : (Ljava/lang/Throwable;)Ljava/lang/Throwable;
    //   4194: athrow
    //   4195: aload #7
    //   4197: invokevirtual getType : ()Ljava/lang/Class;
    //   4200: astore #8
    //   4202: aload #8
    //   4204: ifnull -> 4285
    //   4207: aload #8
    //   4209: invokevirtual isPrimitive : ()Z
    //   4212: ifne -> 4285
    //   4215: goto -> 4222
    //   4218: invokestatic a : (Ljava/lang/Throwable;)Ljava/lang/Throwable;
    //   4221: athrow
    //   4222: aload #8
    //   4224: invokevirtual getPackage : ()Ljava/lang/Package;
    //   4227: ifnull -> 4285
    //   4230: goto -> 4237
    //   4233: invokestatic a : (Ljava/lang/Throwable;)Ljava/lang/Throwable;
    //   4236: athrow
    //   4237: aload #8
    //   4239: invokevirtual getPackage : ()Ljava/lang/Package;
    //   4242: invokevirtual getName : ()Ljava/lang/String;
    //   4245: ifnull -> 4285
    //   4248: goto -> 4255
    //   4251: invokestatic a : (Ljava/lang/Throwable;)Ljava/lang/Throwable;
    //   4254: athrow
    //   4255: aload #8
    //   4257: invokevirtual getPackage : ()Ljava/lang/Package;
    //   4260: invokevirtual getName : ()Ljava/lang/String;
    //   4263: sipush #28800
    //   4266: sipush #24347
    //   4269: invokestatic a : (II)Ljava/lang/String;
    //   4272: invokevirtual startsWith : (Ljava/lang/String;)Z
    //   4275: ifne -> 4285
    //   4278: goto -> 4285
    //   4281: invokestatic a : (Ljava/lang/Throwable;)Ljava/lang/Throwable;
    //   4284: athrow
    //   4285: aload #7
    //   4287: iconst_1
    //   4288: invokevirtual setAccessible : (Z)V
    //   4291: aload #7
    //   4293: aconst_null
    //   4294: invokevirtual get : (Ljava/lang/Object;)Ljava/lang/Object;
    //   4297: pop
    //   4298: iinc #6, 1
    //   4301: iload_2
    //   4302: ifeq -> 4163
    //   4305: sipush #28806
    //   4308: sipush #-21119
    //   4311: invokestatic a : (II)Ljava/lang/String;
    //   4314: invokestatic forName : (Ljava/lang/String;)Ljava/lang/Class;
    //   4317: invokevirtual getDeclaredMethods : ()[Ljava/lang/reflect/Method;
    //   4320: astore #4
    //   4322: aload #4
    //   4324: arraylength
    //   4325: istore #5
    //   4327: iconst_0
    //   4328: istore #6
    //   4330: iload #6
    //   4332: iload #5
    //   4334: if_icmpge -> 4467
    //   4337: aload #4
    //   4339: iload #6
    //   4341: aaload
    //   4342: astore #7
    //   4344: aload #7
    //   4346: invokevirtual getParameterTypes : ()[Ljava/lang/Class;
    //   4349: pop
    //   4350: aload #7
    //   4352: invokevirtual getModifiers : ()I
    //   4355: invokestatic isStatic : (I)Z
    //   4358: ifeq -> 4453
    //   4361: aload #7
    //   4363: invokevirtual getParameterTypes : ()[Ljava/lang/Class;
    //   4366: arraylength
    //   4367: iconst_2
    //   4368: if_icmpne -> 4453
    //   4371: goto -> 4378
    //   4374: invokestatic a : (Ljava/lang/Throwable;)Ljava/lang/Throwable;
    //   4377: athrow
    //   4378: aload #7
    //   4380: invokevirtual getReturnType : ()Ljava/lang/Class;
    //   4383: getstatic java/lang/Void.TYPE : Ljava/lang/Class;
    //   4386: invokevirtual equals : (Ljava/lang/Object;)Z
    //   4389: ifeq -> 4453
    //   4392: goto -> 4399
    //   4395: invokestatic a : (Ljava/lang/Throwable;)Ljava/lang/Throwable;
    //   4398: athrow
    //   4399: aload #7
    //   4401: iconst_1
    //   4402: invokevirtual setAccessible : (Z)V
    //   4405: aload #7
    //   4407: aconst_null
    //   4408: iconst_2
    //   4409: anewarray java/lang/Object
    //   4412: dup
    //   4413: iconst_0
    //   4414: aload_0
    //   4415: aastore
    //   4416: dup
    //   4417: iconst_1
    //   4418: aload_1
    //   4419: ifnonnull -> 4437
    //   4422: goto -> 4429
    //   4425: invokestatic a : (Ljava/lang/Throwable;)Ljava/lang/Throwable;
    //   4428: athrow
    //   4429: aload_1
    //   4430: goto -> 4444
    //   4433: invokestatic a : (Ljava/lang/Throwable;)Ljava/lang/Throwable;
    //   4436: athrow
    //   4437: aload_1
    //   4438: checkcast [B
    //   4441: invokevirtual clone : ()Ljava/lang/Object;
    //   4444: aastore
    //   4445: invokevirtual invoke : (Ljava/lang/Object;[Ljava/lang/Object;)Ljava/lang/Object;
    //   4448: pop
    //   4449: iload_2
    //   4450: ifeq -> 4467
    //   4453: iinc #6, 1
    //   4456: iload_2
    //   4457: ifeq -> 4330
    //   4460: goto -> 4467
    //   4463: invokestatic a : (Ljava/lang/Throwable;)Ljava/lang/Throwable;
    //   4466: athrow
    //   4467: getstatic burp/Zty5.Zf : Ljava/lang/Object;
    //   4470: checkcast java/math/BigInteger
    //   4473: invokevirtual toByteArray : ()[B
    //   4476: astore #4
    //   4478: bipush #64
    //   4480: newarray byte
    //   4482: dup
    //   4483: iconst_0
    //   4484: bipush #-128
    //   4486: bastore
    //   4487: dup
    //   4488: iconst_1
    //   4489: iconst_0
    //   4490: bastore
    //   4491: dup
    //   4492: iconst_2
    //   4493: iconst_0
    //   4494: bastore
    //   4495: dup
    //   4496: iconst_3
    //   4497: iconst_0
    //   4498: bastore
    //   4499: dup
    //   4500: iconst_4
    //   4501: iconst_0
    //   4502: bastore
    //   4503: dup
    //   4504: iconst_5
    //   4505: iconst_0
    //   4506: bastore
    //   4507: dup
    //   4508: bipush #6
    //   4510: iconst_0
    //   4511: bastore
    //   4512: dup
    //   4513: bipush #7
    //   4515: iconst_0
    //   4516: bastore
    //   4517: dup
    //   4518: bipush #8
    //   4520: iconst_0
    //   4521: bastore
    //   4522: dup
    //   4523: bipush #9
    //   4525: iconst_0
    //   4526: bastore
    //   4527: dup
    //   4528: bipush #10
    //   4530: iconst_0
    //   4531: bastore
    //   4532: dup
    //   4533: bipush #11
    //   4535: iconst_0
    //   4536: bastore
    //   4537: dup
    //   4538: bipush #12
    //   4540: iconst_0
    //   4541: bastore
    //   4542: dup
    //   4543: bipush #13
    //   4545: iconst_0
    //   4546: bastore
    //   4547: dup
    //   4548: bipush #14
    //   4550: iconst_0
    //   4551: bastore
    //   4552: dup
    //   4553: bipush #15
    //   4555: iconst_0
    //   4556: bastore
    //   4557: dup
    //   4558: bipush #16
    //   4560: iconst_0
    //   4561: bastore
    //   4562: dup
    //   4563: bipush #17
    //   4565: iconst_0
    //   4566: bastore
    //   4567: dup
    //   4568: bipush #18
    //   4570: iconst_0
    //   4571: bastore
    //   4572: dup
    //   4573: bipush #19
    //   4575: iconst_0
    //   4576: bastore
    //   4577: dup
    //   4578: bipush #20
    //   4580: iconst_0
    //   4581: bastore
    //   4582: dup
    //   4583: bipush #21
    //   4585: iconst_0
    //   4586: bastore
    //   4587: dup
    //   4588: bipush #22
    //   4590: iconst_0
    //   4591: bastore
    //   4592: dup
    //   4593: bipush #23
    //   4595: iconst_0
    //   4596: bastore
    //   4597: dup
    //   4598: bipush #24
    //   4600: iconst_0
    //   4601: bastore
    //   4602: dup
    //   4603: bipush #25
    //   4605: iconst_0
    //   4606: bastore
    //   4607: dup
    //   4608: bipush #26
    //   4610: iconst_0
    //   4611: bastore
    //   4612: dup
    //   4613: bipush #27
    //   4615: iconst_0
    //   4616: bastore
    //   4617: dup
    //   4618: bipush #28
    //   4620: iconst_0
    //   4621: bastore
    //   4622: dup
    //   4623: bipush #29
    //   4625: iconst_0
    //   4626: bastore
    //   4627: dup
    //   4628: bipush #30
    //   4630: iconst_0
    //   4631: bastore
    //   4632: dup
    //   4633: bipush #31
    //   4635: iconst_0
    //   4636: bastore
    //   4637: dup
    //   4638: bipush #32
    //   4640: iconst_0
    //   4641: bastore
    //   4642: dup
    //   4643: bipush #33
    //   4645: iconst_0
    //   4646: bastore
    //   4647: dup
    //   4648: bipush #34
    //   4650: iconst_0
    //   4651: bastore
    //   4652: dup
    //   4653: bipush #35
    //   4655: iconst_0
    //   4656: bastore
    //   4657: dup
    //   4658: bipush #36
    //   4660: iconst_0
    //   4661: bastore
    //   4662: dup
    //   4663: bipush #37
    //   4665: iconst_0
    //   4666: bastore
    //   4667: dup
    //   4668: bipush #38
    //   4670: iconst_0
    //   4671: bastore
    //   4672: dup
    //   4673: bipush #39
    //   4675: iconst_0
    //   4676: bastore
    //   4677: dup
    //   4678: bipush #40
    //   4680: iconst_0
    //   4681: bastore
    //   4682: dup
    //   4683: bipush #41
    //   4685: iconst_0
    //   4686: bastore
    //   4687: dup
    //   4688: bipush #42
    //   4690: iconst_0
    //   4691: bastore
    //   4692: dup
    //   4693: bipush #43
    //   4695: iconst_0
    //   4696: bastore
    //   4697: dup
    //   4698: bipush #44
    //   4700: iconst_0
    //   4701: bastore
    //   4702: dup
    //   4703: bipush #45
    //   4705: iconst_0
    //   4706: bastore
    //   4707: dup
    //   4708: bipush #46
    //   4710: iconst_0
    //   4711: bastore
    //   4712: dup
    //   4713: bipush #47
    //   4715: iconst_0
    //   4716: bastore
    //   4717: dup
    //   4718: bipush #48
    //   4720: iconst_0
    //   4721: bastore
    //   4722: dup
    //   4723: bipush #49
    //   4725: iconst_0
    //   4726: bastore
    //   4727: dup
    //   4728: bipush #50
    //   4730: iconst_0
    //   4731: bastore
    //   4732: dup
    //   4733: bipush #51
    //   4735: iconst_0
    //   4736: bastore
    //   4737: dup
    //   4738: bipush #52
    //   4740: iconst_0
    //   4741: bastore
    //   4742: dup
    //   4743: bipush #53
    //   4745: iconst_0
    //   4746: bastore
    //   4747: dup
    //   4748: bipush #54
    //   4750: iconst_0
    //   4751: bastore
    //   4752: dup
    //   4753: bipush #55
    //   4755: iconst_0
    //   4756: bastore
    //   4757: dup
    //   4758: bipush #56
    //   4760: iconst_0
    //   4761: bastore
    //   4762: dup
    //   4763: bipush #57
    //   4765: iconst_0
    //   4766: bastore
    //   4767: dup
    //   4768: bipush #58
    //   4770: iconst_0
    //   4771: bastore
    //   4772: dup
    //   4773: bipush #59
    //   4775: iconst_0
    //   4776: bastore
    //   4777: dup
    //   4778: bipush #60
    //   4780: iconst_0
    //   4781: bastore
    //   4782: dup
    //   4783: bipush #61
    //   4785: iconst_0
    //   4786: bastore
    //   4787: dup
    //   4788: bipush #62
    //   4790: iconst_0
    //   4791: bastore
    //   4792: dup
    //   4793: bipush #63
    //   4795: iconst_0
    //   4796: bastore
    //   4797: astore #6
    //   4799: bipush #64
    //   4801: newarray int
    //   4803: dup
    //   4804: iconst_0
    //   4805: ldc 1116352408
    //   4807: iastore
    //   4808: dup
    //   4809: iconst_1
    //   4810: ldc 1899447441
    //   4812: iastore
    //   4813: dup
    //   4814: iconst_2
    //   4815: ldc -1245643825
    //   4817: iastore
    //   4818: dup
    //   4819: iconst_3
    //   4820: ldc -373957723
    //   4822: iastore
    //   4823: dup
    //   4824: iconst_4
    //   4825: ldc 961987163
    //   4827: iastore
    //   4828: dup
    //   4829: iconst_5
    //   4830: ldc 1508970993
    //   4832: iastore
    //   4833: dup
    //   4834: bipush #6
    //   4836: ldc -1841331548
    //   4838: iastore
    //   4839: dup
    //   4840: bipush #7
    //   4842: ldc -1424204075
    //   4844: iastore
    //   4845: dup
    //   4846: bipush #8
    //   4848: ldc -670586216
    //   4850: iastore
    //   4851: dup
    //   4852: bipush #9
    //   4854: ldc 310598401
    //   4856: iastore
    //   4857: dup
    //   4858: bipush #10
    //   4860: ldc 607225278
    //   4862: iastore
    //   4863: dup
    //   4864: bipush #11
    //   4866: ldc 1426881987
    //   4868: iastore
    //   4869: dup
    //   4870: bipush #12
    //   4872: ldc 1925078388
    //   4874: iastore
    //   4875: dup
    //   4876: bipush #13
    //   4878: ldc -2132889090
    //   4880: iastore
    //   4881: dup
    //   4882: bipush #14
    //   4884: ldc -1680079193
    //   4886: iastore
    //   4887: dup
    //   4888: bipush #15
    //   4890: ldc -1046744716
    //   4892: iastore
    //   4893: dup
    //   4894: bipush #16
    //   4896: ldc -459576895
    //   4898: iastore
    //   4899: dup
    //   4900: bipush #17
    //   4902: ldc -272742522
    //   4904: iastore
    //   4905: dup
    //   4906: bipush #18
    //   4908: ldc 264347078
    //   4910: iastore
    //   4911: dup
    //   4912: bipush #19
    //   4914: ldc 604807628
    //   4916: iastore
    //   4917: dup
    //   4918: bipush #20
    //   4920: ldc 770255983
    //   4922: iastore
    //   4923: dup
    //   4924: bipush #21
    //   4926: ldc 1249150122
    //   4928: iastore
    //   4929: dup
    //   4930: bipush #22
    //   4932: ldc 1555081692
    //   4934: iastore
    //   4935: dup
    //   4936: bipush #23
    //   4938: ldc 1996064986
    //   4940: iastore
    //   4941: dup
    //   4942: bipush #24
    //   4944: ldc -1740746414
    //   4946: iastore
    //   4947: dup
    //   4948: bipush #25
    //   4950: ldc -1473132947
    //   4952: iastore
    //   4953: dup
    //   4954: bipush #26
    //   4956: ldc -1341970488
    //   4958: iastore
    //   4959: dup
    //   4960: bipush #27
    //   4962: ldc -1084653625
    //   4964: iastore
    //   4965: dup
    //   4966: bipush #28
    //   4968: ldc -958395405
    //   4970: iastore
    //   4971: dup
    //   4972: bipush #29
    //   4974: ldc -710438585
    //   4976: iastore
    //   4977: dup
    //   4978: bipush #30
    //   4980: ldc 113926993
    //   4982: iastore
    //   4983: dup
    //   4984: bipush #31
    //   4986: ldc 338241895
    //   4988: iastore
    //   4989: dup
    //   4990: bipush #32
    //   4992: ldc 666307205
    //   4994: iastore
    //   4995: dup
    //   4996: bipush #33
    //   4998: ldc 773529912
    //   5000: iastore
    //   5001: dup
    //   5002: bipush #34
    //   5004: ldc 1294757372
    //   5006: iastore
    //   5007: dup
    //   5008: bipush #35
    //   5010: ldc 1396182291
    //   5012: iastore
    //   5013: dup
    //   5014: bipush #36
    //   5016: ldc 1695183700
    //   5018: iastore
    //   5019: dup
    //   5020: bipush #37
    //   5022: ldc 1986661051
    //   5024: iastore
    //   5025: dup
    //   5026: bipush #38
    //   5028: ldc -2117940946
    //   5030: iastore
    //   5031: dup
    //   5032: bipush #39
    //   5034: ldc -1838011259
    //   5036: iastore
    //   5037: dup
    //   5038: bipush #40
    //   5040: ldc -1564481375
    //   5042: iastore
    //   5043: dup
    //   5044: bipush #41
    //   5046: ldc -1474664885
    //   5048: iastore
    //   5049: dup
    //   5050: bipush #42
    //   5052: ldc -1035236496
    //   5054: iastore
    //   5055: dup
    //   5056: bipush #43
    //   5058: ldc -949202525
    //   5060: iastore
    //   5061: dup
    //   5062: bipush #44
    //   5064: ldc -778901479
    //   5066: iastore
    //   5067: dup
    //   5068: bipush #45
    //   5070: ldc -694614492
    //   5072: iastore
    //   5073: dup
    //   5074: bipush #46
    //   5076: ldc -200395387
    //   5078: iastore
    //   5079: dup
    //   5080: bipush #47
    //   5082: ldc 275423344
    //   5084: iastore
    //   5085: dup
    //   5086: bipush #48
    //   5088: ldc 430227734
    //   5090: iastore
    //   5091: dup
    //   5092: bipush #49
    //   5094: ldc 506948616
    //   5096: iastore
    //   5097: dup
    //   5098: bipush #50
    //   5100: ldc 659060556
    //   5102: iastore
    //   5103: dup
    //   5104: bipush #51
    //   5106: ldc 883997877
    //   5108: iastore
    //   5109: dup
    //   5110: bipush #52
    //   5112: ldc 958139571
    //   5114: iastore
    //   5115: dup
    //   5116: bipush #53
    //   5118: ldc 1322822218
    //   5120: iastore
    //   5121: dup
    //   5122: bipush #54
    //   5124: ldc 1537002063
    //   5126: iastore
    //   5127: dup
    //   5128: bipush #55
    //   5130: ldc 1747873779
    //   5132: iastore
    //   5133: dup
    //   5134: bipush #56
    //   5136: ldc 1955562222
    //   5138: iastore
    //   5139: dup
    //   5140: bipush #57
    //   5142: ldc 2024104815
    //   5144: iastore
    //   5145: dup
    //   5146: bipush #58
    //   5148: ldc -2067236844
    //   5150: iastore
    //   5151: dup
    //   5152: bipush #59
    //   5154: ldc -1933114872
    //   5156: iastore
    //   5157: dup
    //   5158: bipush #60
    //   5160: ldc -1866530822
    //   5162: iastore
    //   5163: dup
    //   5164: bipush #61
    //   5166: ldc -1538233109
    //   5168: iastore
    //   5169: dup
    //   5170: bipush #62
    //   5172: ldc -1090935817
    //   5174: iastore
    //   5175: dup
    //   5176: bipush #63
    //   5178: ldc -965641998
    //   5180: iastore
    //   5181: astore #7
    //   5183: iconst_2
    //   5184: newarray int
    //   5186: dup
    //   5187: iconst_0
    //   5188: iconst_0
    //   5189: iastore
    //   5190: dup
    //   5191: iconst_1
    //   5192: iconst_0
    //   5193: iastore
    //   5194: astore #8
    //   5196: bipush #8
    //   5198: newarray int
    //   5200: dup
    //   5201: iconst_0
    //   5202: ldc 1779033703
    //   5204: iastore
    //   5205: dup
    //   5206: iconst_1
    //   5207: ldc -1150833019
    //   5209: iastore
    //   5210: dup
    //   5211: iconst_2
    //   5212: ldc 1013904242
    //   5214: iastore
    //   5215: dup
    //   5216: iconst_3
    //   5217: ldc -1521486534
    //   5219: iastore
    //   5220: dup
    //   5221: iconst_4
    //   5222: ldc 1359893119
    //   5224: iastore
    //   5225: dup
    //   5226: iconst_5
    //   5227: ldc -1694144372
    //   5229: iastore
    //   5230: dup
    //   5231: bipush #6
    //   5233: ldc 528734635
    //   5235: iastore
    //   5236: dup
    //   5237: bipush #7
    //   5239: ldc 1541459225
    //   5241: iastore
    //   5242: astore #9
    //   5244: bipush #64
    //   5246: newarray byte
    //   5248: astore #10
    //   5250: bipush #64
    //   5252: newarray byte
    //   5254: astore #11
    //   5256: aload #4
    //   5258: arraylength
    //   5259: istore #12
    //   5261: aload #8
    //   5263: iconst_0
    //   5264: iaload
    //   5265: bipush #63
    //   5267: iand
    //   5268: istore #13
    //   5270: aload #8
    //   5272: iconst_0
    //   5273: dup2
    //   5274: iaload
    //   5275: iload #12
    //   5277: iadd
    //   5278: iastore
    //   5279: aload #8
    //   5281: iconst_0
    //   5282: dup2
    //   5283: iaload
    //   5284: iconst_m1
    //   5285: iand
    //   5286: iastore
    //   5287: aload #8
    //   5289: iconst_0
    //   5290: iaload
    //   5291: iload #12
    //   5293: if_icmpge -> 5311
    //   5296: aload #8
    //   5298: iconst_1
    //   5299: dup2
    //   5300: iaload
    //   5301: iconst_1
    //   5302: iadd
    //   5303: iastore
    //   5304: goto -> 5311
    //   5307: invokestatic a : (Ljava/lang/Throwable;)Ljava/lang/Throwable;
    //   5310: athrow
    //   5311: iconst_0
    //   5312: istore #14
    //   5314: iload #12
    //   5316: bipush #64
    //   5318: if_icmplt -> 5928
    //   5321: iconst_0
    //   5322: istore #15
    //   5324: iload #15
    //   5326: bipush #64
    //   5328: if_icmpge -> 5351
    //   5331: aload #11
    //   5333: iload #15
    //   5335: aload #4
    //   5337: iload #14
    //   5339: iload #15
    //   5341: iadd
    //   5342: baload
    //   5343: bastore
    //   5344: iinc #15, 1
    //   5347: iload_2
    //   5348: ifeq -> 5324
    //   5351: bipush #64
    //   5353: newarray int
    //   5355: astore #15
    //   5357: bipush #8
    //   5359: newarray int
    //   5361: astore #16
    //   5363: iconst_0
    //   5364: istore #17
    //   5366: iload #17
    //   5368: bipush #8
    //   5370: if_icmpge -> 5390
    //   5373: aload #16
    //   5375: iload #17
    //   5377: aload #9
    //   5379: iload #17
    //   5381: iaload
    //   5382: iastore
    //   5383: iinc #17, 1
    //   5386: iload_2
    //   5387: ifeq -> 5366
    //   5390: iconst_0
    //   5391: istore #17
    //   5393: iload #17
    //   5395: bipush #64
    //   5397: if_icmpge -> 5888
    //   5400: iload #17
    //   5402: bipush #16
    //   5404: if_icmpge -> 5485
    //   5407: aload #15
    //   5409: iload #17
    //   5411: aload #11
    //   5413: iconst_4
    //   5414: iload #17
    //   5416: imul
    //   5417: baload
    //   5418: sipush #255
    //   5421: iand
    //   5422: bipush #24
    //   5424: ishl
    //   5425: aload #11
    //   5427: iconst_4
    //   5428: iload #17
    //   5430: imul
    //   5431: iconst_1
    //   5432: iadd
    //   5433: baload
    //   5434: sipush #255
    //   5437: iand
    //   5438: bipush #16
    //   5440: ishl
    //   5441: ior
    //   5442: aload #11
    //   5444: iconst_4
    //   5445: iload #17
    //   5447: imul
    //   5448: iconst_2
    //   5449: iadd
    //   5450: baload
    //   5451: sipush #255
    //   5454: iand
    //   5455: bipush #8
    //   5457: ishl
    //   5458: ior
    //   5459: aload #11
    //   5461: iconst_4
    //   5462: iload #17
    //   5464: imul
    //   5465: iconst_3
    //   5466: iadd
    //   5467: baload
    //   5468: sipush #255
    //   5471: iand
    //   5472: ior
    //   5473: iastore
    //   5474: iload_2
    //   5475: ifeq -> 5628
    //   5478: goto -> 5485
    //   5481: invokestatic a : (Ljava/lang/Throwable;)Ljava/lang/Throwable;
    //   5484: athrow
    //   5485: aload #15
    //   5487: iload #17
    //   5489: aload #15
    //   5491: iload #17
    //   5493: iconst_2
    //   5494: isub
    //   5495: iaload
    //   5496: bipush #17
    //   5498: iushr
    //   5499: aload #15
    //   5501: iload #17
    //   5503: iconst_2
    //   5504: isub
    //   5505: iaload
    //   5506: bipush #15
    //   5508: ishl
    //   5509: ior
    //   5510: aload #15
    //   5512: iload #17
    //   5514: iconst_2
    //   5515: isub
    //   5516: iaload
    //   5517: bipush #19
    //   5519: iushr
    //   5520: aload #15
    //   5522: iload #17
    //   5524: iconst_2
    //   5525: isub
    //   5526: iaload
    //   5527: bipush #13
    //   5529: ishl
    //   5530: ior
    //   5531: ixor
    //   5532: aload #15
    //   5534: iload #17
    //   5536: iconst_2
    //   5537: isub
    //   5538: iaload
    //   5539: bipush #10
    //   5541: iushr
    //   5542: ixor
    //   5543: aload #15
    //   5545: iload #17
    //   5547: bipush #7
    //   5549: isub
    //   5550: iaload
    //   5551: iadd
    //   5552: aload #15
    //   5554: iload #17
    //   5556: bipush #15
    //   5558: isub
    //   5559: iaload
    //   5560: bipush #7
    //   5562: iushr
    //   5563: aload #15
    //   5565: iload #17
    //   5567: bipush #15
    //   5569: isub
    //   5570: iaload
    //   5571: bipush #25
    //   5573: ishl
    //   5574: ior
    //   5575: aload #15
    //   5577: iload #17
    //   5579: bipush #15
    //   5581: isub
    //   5582: iaload
    //   5583: bipush #18
    //   5585: iushr
    //   5586: aload #15
    //   5588: iload #17
    //   5590: bipush #15
    //   5592: isub
    //   5593: iaload
    //   5594: bipush #14
    //   5596: ishl
    //   5597: ior
    //   5598: ixor
    //   5599: aload #15
    //   5601: iload #17
    //   5603: bipush #15
    //   5605: isub
    //   5606: iaload
    //   5607: iconst_3
    //   5608: iushr
    //   5609: ixor
    //   5610: iadd
    //   5611: aload #15
    //   5613: iload #17
    //   5615: bipush #16
    //   5617: isub
    //   5618: iaload
    //   5619: iadd
    //   5620: iastore
    //   5621: goto -> 5628
    //   5624: invokestatic a : (Ljava/lang/Throwable;)Ljava/lang/Throwable;
    //   5627: athrow
    //   5628: aload #16
    //   5630: bipush #7
    //   5632: iaload
    //   5633: aload #16
    //   5635: iconst_4
    //   5636: iaload
    //   5637: bipush #6
    //   5639: iushr
    //   5640: aload #16
    //   5642: iconst_4
    //   5643: iaload
    //   5644: bipush #26
    //   5646: ishl
    //   5647: ior
    //   5648: aload #16
    //   5650: iconst_4
    //   5651: iaload
    //   5652: bipush #11
    //   5654: iushr
    //   5655: aload #16
    //   5657: iconst_4
    //   5658: iaload
    //   5659: bipush #21
    //   5661: ishl
    //   5662: ior
    //   5663: ixor
    //   5664: aload #16
    //   5666: iconst_4
    //   5667: iaload
    //   5668: bipush #25
    //   5670: iushr
    //   5671: aload #16
    //   5673: iconst_4
    //   5674: iaload
    //   5675: bipush #7
    //   5677: ishl
    //   5678: ior
    //   5679: ixor
    //   5680: iadd
    //   5681: aload #16
    //   5683: bipush #6
    //   5685: iaload
    //   5686: aload #16
    //   5688: iconst_4
    //   5689: iaload
    //   5690: aload #16
    //   5692: iconst_5
    //   5693: iaload
    //   5694: aload #16
    //   5696: bipush #6
    //   5698: iaload
    //   5699: ixor
    //   5700: iand
    //   5701: ixor
    //   5702: iadd
    //   5703: aload #7
    //   5705: iload #17
    //   5707: iaload
    //   5708: iadd
    //   5709: aload #15
    //   5711: iload #17
    //   5713: iaload
    //   5714: iadd
    //   5715: istore #18
    //   5717: aload #16
    //   5719: iconst_0
    //   5720: iaload
    //   5721: iconst_2
    //   5722: iushr
    //   5723: aload #16
    //   5725: iconst_0
    //   5726: iaload
    //   5727: bipush #30
    //   5729: ishl
    //   5730: ior
    //   5731: aload #16
    //   5733: iconst_0
    //   5734: iaload
    //   5735: bipush #13
    //   5737: iushr
    //   5738: aload #16
    //   5740: iconst_0
    //   5741: iaload
    //   5742: bipush #19
    //   5744: ishl
    //   5745: ior
    //   5746: ixor
    //   5747: aload #16
    //   5749: iconst_0
    //   5750: iaload
    //   5751: bipush #22
    //   5753: iushr
    //   5754: aload #16
    //   5756: iconst_0
    //   5757: iaload
    //   5758: bipush #10
    //   5760: ishl
    //   5761: ior
    //   5762: ixor
    //   5763: aload #16
    //   5765: iconst_0
    //   5766: iaload
    //   5767: aload #16
    //   5769: iconst_1
    //   5770: iaload
    //   5771: iand
    //   5772: aload #16
    //   5774: iconst_2
    //   5775: iaload
    //   5776: aload #16
    //   5778: iconst_0
    //   5779: iaload
    //   5780: aload #16
    //   5782: iconst_1
    //   5783: iaload
    //   5784: ior
    //   5785: iand
    //   5786: ior
    //   5787: iadd
    //   5788: istore #19
    //   5790: aload #16
    //   5792: iconst_3
    //   5793: dup2
    //   5794: iaload
    //   5795: iload #18
    //   5797: iadd
    //   5798: iastore
    //   5799: aload #16
    //   5801: bipush #7
    //   5803: iload #18
    //   5805: iload #19
    //   5807: iadd
    //   5808: iastore
    //   5809: aload #16
    //   5811: bipush #7
    //   5813: iaload
    //   5814: istore #18
    //   5816: aload #16
    //   5818: bipush #7
    //   5820: aload #16
    //   5822: bipush #6
    //   5824: iaload
    //   5825: iastore
    //   5826: aload #16
    //   5828: bipush #6
    //   5830: aload #16
    //   5832: iconst_5
    //   5833: iaload
    //   5834: iastore
    //   5835: aload #16
    //   5837: iconst_5
    //   5838: aload #16
    //   5840: iconst_4
    //   5841: iaload
    //   5842: iastore
    //   5843: aload #16
    //   5845: iconst_4
    //   5846: aload #16
    //   5848: iconst_3
    //   5849: iaload
    //   5850: iastore
    //   5851: aload #16
    //   5853: iconst_3
    //   5854: aload #16
    //   5856: iconst_2
    //   5857: iaload
    //   5858: iastore
    //   5859: aload #16
    //   5861: iconst_2
    //   5862: aload #16
    //   5864: iconst_1
    //   5865: iaload
    //   5866: iastore
    //   5867: aload #16
    //   5869: iconst_1
    //   5870: aload #16
    //   5872: iconst_0
    //   5873: iaload
    //   5874: iastore
    //   5875: aload #16
    //   5877: iconst_0
    //   5878: iload #18
    //   5880: iastore
    //   5881: iinc #17, 1
    //   5884: iload_2
    //   5885: ifeq -> 5393
    //   5888: iconst_0
    //   5889: istore #17
    //   5891: iload #17
    //   5893: bipush #8
    //   5895: if_icmpge -> 5918
    //   5898: aload #9
    //   5900: iload #17
    //   5902: dup2
    //   5903: iaload
    //   5904: aload #16
    //   5906: iload #17
    //   5908: iaload
    //   5909: iadd
    //   5910: iastore
    //   5911: iinc #17, 1
    //   5914: iload_2
    //   5915: ifeq -> 5891
    //   5918: iinc #14, 64
    //   5921: iinc #12, -64
    //   5924: iload_2
    //   5925: ifeq -> 5314
    //   5928: iload #12
    //   5930: ifle -> 5966
    //   5933: iconst_0
    //   5934: istore #15
    //   5936: iload #15
    //   5938: iload #12
    //   5940: if_icmpge -> 5966
    //   5943: aload #10
    //   5945: iload #13
    //   5947: iload #15
    //   5949: iadd
    //   5950: aload #4
    //   5952: iload #14
    //   5954: iload #15
    //   5956: iadd
    //   5957: baload
    //   5958: bastore
    //   5959: iinc #15, 1
    //   5962: iload_2
    //   5963: ifeq -> 5936
    //   5966: aload #8
    //   5968: iconst_0
    //   5969: iaload
    //   5970: bipush #29
    //   5972: iushr
    //   5973: aload #8
    //   5975: iconst_1
    //   5976: iaload
    //   5977: iconst_3
    //   5978: ishl
    //   5979: ior
    //   5980: istore #15
    //   5982: aload #8
    //   5984: iconst_0
    //   5985: iaload
    //   5986: iconst_3
    //   5987: ishl
    //   5988: istore #16
    //   5990: aload #8
    //   5992: iconst_0
    //   5993: iaload
    //   5994: bipush #63
    //   5996: iand
    //   5997: istore #17
    //   5999: iload #17
    //   6001: bipush #56
    //   6003: if_icmpge -> 6018
    //   6006: bipush #56
    //   6008: iload #17
    //   6010: isub
    //   6011: goto -> 6023
    //   6014: invokestatic a : (Ljava/lang/Throwable;)Ljava/lang/Throwable;
    //   6017: athrow
    //   6018: bipush #120
    //   6020: iload #17
    //   6022: isub
    //   6023: istore #18
    //   6025: aload #8
    //   6027: iconst_0
    //   6028: iaload
    //   6029: bipush #63
    //   6031: iand
    //   6032: istore #13
    //   6034: bipush #64
    //   6036: iload #13
    //   6038: isub
    //   6039: istore #19
    //   6041: aload #8
    //   6043: iconst_0
    //   6044: dup2
    //   6045: iaload
    //   6046: iload #18
    //   6048: iadd
    //   6049: iastore
    //   6050: aload #8
    //   6052: iconst_0
    //   6053: dup2
    //   6054: iaload
    //   6055: iconst_m1
    //   6056: iand
    //   6057: iastore
    //   6058: aload #8
    //   6060: iconst_0
    //   6061: iaload
    //   6062: iload #18
    //   6064: if_icmpge -> 6082
    //   6067: aload #8
    //   6069: iconst_1
    //   6070: dup2
    //   6071: iaload
    //   6072: iconst_1
    //   6073: iadd
    //   6074: iastore
    //   6075: goto -> 6082
    //   6078: invokestatic a : (Ljava/lang/Throwable;)Ljava/lang/Throwable;
    //   6081: athrow
    //   6082: iconst_0
    //   6083: istore #14
    //   6085: iload #13
    //   6087: ifle -> 6718
    //   6090: iload #18
    //   6092: iload #19
    //   6094: if_icmplt -> 6718
    //   6097: goto -> 6104
    //   6100: invokestatic a : (Ljava/lang/Throwable;)Ljava/lang/Throwable;
    //   6103: athrow
    //   6104: iconst_0
    //   6105: istore #20
    //   6107: iload #20
    //   6109: iload #19
    //   6111: if_icmpge -> 6134
    //   6114: aload #10
    //   6116: iload #13
    //   6118: iload #20
    //   6120: iadd
    //   6121: aload #6
    //   6123: iload #20
    //   6125: baload
    //   6126: bastore
    //   6127: iinc #20, 1
    //   6130: iload_2
    //   6131: ifeq -> 6107
    //   6134: bipush #64
    //   6136: newarray int
    //   6138: astore #20
    //   6140: bipush #8
    //   6142: newarray int
    //   6144: astore #21
    //   6146: iconst_0
    //   6147: istore #22
    //   6149: iload #22
    //   6151: bipush #8
    //   6153: if_icmpge -> 6173
    //   6156: aload #21
    //   6158: iload #22
    //   6160: aload #9
    //   6162: iload #22
    //   6164: iaload
    //   6165: iastore
    //   6166: iinc #22, 1
    //   6169: iload_2
    //   6170: ifeq -> 6149
    //   6173: iconst_0
    //   6174: istore #22
    //   6176: iload #22
    //   6178: bipush #64
    //   6180: if_icmpge -> 6671
    //   6183: iload #22
    //   6185: bipush #16
    //   6187: if_icmpge -> 6268
    //   6190: aload #20
    //   6192: iload #22
    //   6194: aload #10
    //   6196: iconst_4
    //   6197: iload #22
    //   6199: imul
    //   6200: baload
    //   6201: sipush #255
    //   6204: iand
    //   6205: bipush #24
    //   6207: ishl
    //   6208: aload #10
    //   6210: iconst_4
    //   6211: iload #22
    //   6213: imul
    //   6214: iconst_1
    //   6215: iadd
    //   6216: baload
    //   6217: sipush #255
    //   6220: iand
    //   6221: bipush #16
    //   6223: ishl
    //   6224: ior
    //   6225: aload #10
    //   6227: iconst_4
    //   6228: iload #22
    //   6230: imul
    //   6231: iconst_2
    //   6232: iadd
    //   6233: baload
    //   6234: sipush #255
    //   6237: iand
    //   6238: bipush #8
    //   6240: ishl
    //   6241: ior
    //   6242: aload #10
    //   6244: iconst_4
    //   6245: iload #22
    //   6247: imul
    //   6248: iconst_3
    //   6249: iadd
    //   6250: baload
    //   6251: sipush #255
    //   6254: iand
    //   6255: ior
    //   6256: iastore
    //   6257: iload_2
    //   6258: ifeq -> 6411
    //   6261: goto -> 6268
    //   6264: invokestatic a : (Ljava/lang/Throwable;)Ljava/lang/Throwable;
    //   6267: athrow
    //   6268: aload #20
    //   6270: iload #22
    //   6272: aload #20
    //   6274: iload #22
    //   6276: iconst_2
    //   6277: isub
    //   6278: iaload
    //   6279: bipush #17
    //   6281: iushr
    //   6282: aload #20
    //   6284: iload #22
    //   6286: iconst_2
    //   6287: isub
    //   6288: iaload
    //   6289: bipush #15
    //   6291: ishl
    //   6292: ior
    //   6293: aload #20
    //   6295: iload #22
    //   6297: iconst_2
    //   6298: isub
    //   6299: iaload
    //   6300: bipush #19
    //   6302: iushr
    //   6303: aload #20
    //   6305: iload #22
    //   6307: iconst_2
    //   6308: isub
    //   6309: iaload
    //   6310: bipush #13
    //   6312: ishl
    //   6313: ior
    //   6314: ixor
    //   6315: aload #20
    //   6317: iload #22
    //   6319: iconst_2
    //   6320: isub
    //   6321: iaload
    //   6322: bipush #10
    //   6324: iushr
    //   6325: ixor
    //   6326: aload #20
    //   6328: iload #22
    //   6330: bipush #7
    //   6332: isub
    //   6333: iaload
    //   6334: iadd
    //   6335: aload #20
    //   6337: iload #22
    //   6339: bipush #15
    //   6341: isub
    //   6342: iaload
    //   6343: bipush #7
    //   6345: iushr
    //   6346: aload #20
    //   6348: iload #22
    //   6350: bipush #15
    //   6352: isub
    //   6353: iaload
    //   6354: bipush #25
    //   6356: ishl
    //   6357: ior
    //   6358: aload #20
    //   6360: iload #22
    //   6362: bipush #15
    //   6364: isub
    //   6365: iaload
    //   6366: bipush #18
    //   6368: iushr
    //   6369: aload #20
    //   6371: iload #22
    //   6373: bipush #15
    //   6375: isub
    //   6376: iaload
    //   6377: bipush #14
    //   6379: ishl
    //   6380: ior
    //   6381: ixor
    //   6382: aload #20
    //   6384: iload #22
    //   6386: bipush #15
    //   6388: isub
    //   6389: iaload
    //   6390: iconst_3
    //   6391: iushr
    //   6392: ixor
    //   6393: iadd
    //   6394: aload #20
    //   6396: iload #22
    //   6398: bipush #16
    //   6400: isub
    //   6401: iaload
    //   6402: iadd
    //   6403: iastore
    //   6404: goto -> 6411
    //   6407: invokestatic a : (Ljava/lang/Throwable;)Ljava/lang/Throwable;
    //   6410: athrow
    //   6411: aload #21
    //   6413: bipush #7
    //   6415: iaload
    //   6416: aload #21
    //   6418: iconst_4
    //   6419: iaload
    //   6420: bipush #6
    //   6422: iushr
    //   6423: aload #21
    //   6425: iconst_4
    //   6426: iaload
    //   6427: bipush #26
    //   6429: ishl
    //   6430: ior
    //   6431: aload #21
    //   6433: iconst_4
    //   6434: iaload
    //   6435: bipush #11
    //   6437: iushr
    //   6438: aload #21
    //   6440: iconst_4
    //   6441: iaload
    //   6442: bipush #21
    //   6444: ishl
    //   6445: ior
    //   6446: ixor
    //   6447: aload #21
    //   6449: iconst_4
    //   6450: iaload
    //   6451: bipush #25
    //   6453: iushr
    //   6454: aload #21
    //   6456: iconst_4
    //   6457: iaload
    //   6458: bipush #7
    //   6460: ishl
    //   6461: ior
    //   6462: ixor
    //   6463: iadd
    //   6464: aload #21
    //   6466: bipush #6
    //   6468: iaload
    //   6469: aload #21
    //   6471: iconst_4
    //   6472: iaload
    //   6473: aload #21
    //   6475: iconst_5
    //   6476: iaload
    //   6477: aload #21
    //   6479: bipush #6
    //   6481: iaload
    //   6482: ixor
    //   6483: iand
    //   6484: ixor
    //   6485: iadd
    //   6486: aload #7
    //   6488: iload #22
    //   6490: iaload
    //   6491: iadd
    //   6492: aload #20
    //   6494: iload #22
    //   6496: iaload
    //   6497: iadd
    //   6498: istore #23
    //   6500: aload #21
    //   6502: iconst_0
    //   6503: iaload
    //   6504: iconst_2
    //   6505: iushr
    //   6506: aload #21
    //   6508: iconst_0
    //   6509: iaload
    //   6510: bipush #30
    //   6512: ishl
    //   6513: ior
    //   6514: aload #21
    //   6516: iconst_0
    //   6517: iaload
    //   6518: bipush #13
    //   6520: iushr
    //   6521: aload #21
    //   6523: iconst_0
    //   6524: iaload
    //   6525: bipush #19
    //   6527: ishl
    //   6528: ior
    //   6529: ixor
    //   6530: aload #21
    //   6532: iconst_0
    //   6533: iaload
    //   6534: bipush #22
    //   6536: iushr
    //   6537: aload #21
    //   6539: iconst_0
    //   6540: iaload
    //   6541: bipush #10
    //   6543: ishl
    //   6544: ior
    //   6545: ixor
    //   6546: aload #21
    //   6548: iconst_0
    //   6549: iaload
    //   6550: aload #21
    //   6552: iconst_1
    //   6553: iaload
    //   6554: iand
    //   6555: aload #21
    //   6557: iconst_2
    //   6558: iaload
    //   6559: aload #21
    //   6561: iconst_0
    //   6562: iaload
    //   6563: aload #21
    //   6565: iconst_1
    //   6566: iaload
    //   6567: ior
    //   6568: iand
    //   6569: ior
    //   6570: iadd
    //   6571: istore #24
    //   6573: aload #21
    //   6575: iconst_3
    //   6576: dup2
    //   6577: iaload
    //   6578: iload #23
    //   6580: iadd
    //   6581: iastore
    //   6582: aload #21
    //   6584: bipush #7
    //   6586: iload #23
    //   6588: iload #24
    //   6590: iadd
    //   6591: iastore
    //   6592: aload #21
    //   6594: bipush #7
    //   6596: iaload
    //   6597: istore #23
    //   6599: aload #21
    //   6601: bipush #7
    //   6603: aload #21
    //   6605: bipush #6
    //   6607: iaload
    //   6608: iastore
    //   6609: aload #21
    //   6611: bipush #6
    //   6613: aload #21
    //   6615: iconst_5
    //   6616: iaload
    //   6617: iastore
    //   6618: aload #21
    //   6620: iconst_5
    //   6621: aload #21
    //   6623: iconst_4
    //   6624: iaload
    //   6625: iastore
    //   6626: aload #21
    //   6628: iconst_4
    //   6629: aload #21
    //   6631: iconst_3
    //   6632: iaload
    //   6633: iastore
    //   6634: aload #21
    //   6636: iconst_3
    //   6637: aload #21
    //   6639: iconst_2
    //   6640: iaload
    //   6641: iastore
    //   6642: aload #21
    //   6644: iconst_2
    //   6645: aload #21
    //   6647: iconst_1
    //   6648: iaload
    //   6649: iastore
    //   6650: aload #21
    //   6652: iconst_1
    //   6653: aload #21
    //   6655: iconst_0
    //   6656: iaload
    //   6657: iastore
    //   6658: aload #21
    //   6660: iconst_0
    //   6661: iload #23
    //   6663: iastore
    //   6664: iinc #22, 1
    //   6667: iload_2
    //   6668: ifeq -> 6176
    //   6671: iconst_0
    //   6672: istore #22
    //   6674: iload #22
    //   6676: bipush #8
    //   6678: if_icmpge -> 6701
    //   6681: aload #9
    //   6683: iload #22
    //   6685: dup2
    //   6686: iaload
    //   6687: aload #21
    //   6689: iload #22
    //   6691: iaload
    //   6692: iadd
    //   6693: iastore
    //   6694: iinc #22, 1
    //   6697: iload_2
    //   6698: ifeq -> 6674
    //   6701: iload #14
    //   6703: iload #19
    //   6705: iadd
    //   6706: istore #14
    //   6708: iload #18
    //   6710: iload #19
    //   6712: isub
    //   6713: istore #18
    //   6715: iconst_0
    //   6716: istore #13
    //   6718: iload #18
    //   6720: bipush #64
    //   6722: if_icmplt -> 7332
    //   6725: iconst_0
    //   6726: istore #20
    //   6728: iload #20
    //   6730: bipush #64
    //   6732: if_icmpge -> 6755
    //   6735: aload #11
    //   6737: iload #20
    //   6739: aload #6
    //   6741: iload #14
    //   6743: iload #20
    //   6745: iadd
    //   6746: baload
    //   6747: bastore
    //   6748: iinc #20, 1
    //   6751: iload_2
    //   6752: ifeq -> 6728
    //   6755: bipush #64
    //   6757: newarray int
    //   6759: astore #20
    //   6761: bipush #8
    //   6763: newarray int
    //   6765: astore #21
    //   6767: iconst_0
    //   6768: istore #22
    //   6770: iload #22
    //   6772: bipush #8
    //   6774: if_icmpge -> 6794
    //   6777: aload #21
    //   6779: iload #22
    //   6781: aload #9
    //   6783: iload #22
    //   6785: iaload
    //   6786: iastore
    //   6787: iinc #22, 1
    //   6790: iload_2
    //   6791: ifeq -> 6770
    //   6794: iconst_0
    //   6795: istore #22
    //   6797: iload #22
    //   6799: bipush #64
    //   6801: if_icmpge -> 7292
    //   6804: iload #22
    //   6806: bipush #16
    //   6808: if_icmpge -> 6889
    //   6811: aload #20
    //   6813: iload #22
    //   6815: aload #11
    //   6817: iconst_4
    //   6818: iload #22
    //   6820: imul
    //   6821: baload
    //   6822: sipush #255
    //   6825: iand
    //   6826: bipush #24
    //   6828: ishl
    //   6829: aload #11
    //   6831: iconst_4
    //   6832: iload #22
    //   6834: imul
    //   6835: iconst_1
    //   6836: iadd
    //   6837: baload
    //   6838: sipush #255
    //   6841: iand
    //   6842: bipush #16
    //   6844: ishl
    //   6845: ior
    //   6846: aload #11
    //   6848: iconst_4
    //   6849: iload #22
    //   6851: imul
    //   6852: iconst_2
    //   6853: iadd
    //   6854: baload
    //   6855: sipush #255
    //   6858: iand
    //   6859: bipush #8
    //   6861: ishl
    //   6862: ior
    //   6863: aload #11
    //   6865: iconst_4
    //   6866: iload #22
    //   6868: imul
    //   6869: iconst_3
    //   6870: iadd
    //   6871: baload
    //   6872: sipush #255
    //   6875: iand
    //   6876: ior
    //   6877: iastore
    //   6878: iload_2
    //   6879: ifeq -> 7032
    //   6882: goto -> 6889
    //   6885: invokestatic a : (Ljava/lang/Throwable;)Ljava/lang/Throwable;
    //   6888: athrow
    //   6889: aload #20
    //   6891: iload #22
    //   6893: aload #20
    //   6895: iload #22
    //   6897: iconst_2
    //   6898: isub
    //   6899: iaload
    //   6900: bipush #17
    //   6902: iushr
    //   6903: aload #20
    //   6905: iload #22
    //   6907: iconst_2
    //   6908: isub
    //   6909: iaload
    //   6910: bipush #15
    //   6912: ishl
    //   6913: ior
    //   6914: aload #20
    //   6916: iload #22
    //   6918: iconst_2
    //   6919: isub
    //   6920: iaload
    //   6921: bipush #19
    //   6923: iushr
    //   6924: aload #20
    //   6926: iload #22
    //   6928: iconst_2
    //   6929: isub
    //   6930: iaload
    //   6931: bipush #13
    //   6933: ishl
    //   6934: ior
    //   6935: ixor
    //   6936: aload #20
    //   6938: iload #22
    //   6940: iconst_2
    //   6941: isub
    //   6942: iaload
    //   6943: bipush #10
    //   6945: iushr
    //   6946: ixor
    //   6947: aload #20
    //   6949: iload #22
    //   6951: bipush #7
    //   6953: isub
    //   6954: iaload
    //   6955: iadd
    //   6956: aload #20
    //   6958: iload #22
    //   6960: bipush #15
    //   6962: isub
    //   6963: iaload
    //   6964: bipush #7
    //   6966: iushr
    //   6967: aload #20
    //   6969: iload #22
    //   6971: bipush #15
    //   6973: isub
    //   6974: iaload
    //   6975: bipush #25
    //   6977: ishl
    //   6978: ior
    //   6979: aload #20
    //   6981: iload #22
    //   6983: bipush #15
    //   6985: isub
    //   6986: iaload
    //   6987: bipush #18
    //   6989: iushr
    //   6990: aload #20
    //   6992: iload #22
    //   6994: bipush #15
    //   6996: isub
    //   6997: iaload
    //   6998: bipush #14
    //   7000: ishl
    //   7001: ior
    //   7002: ixor
    //   7003: aload #20
    //   7005: iload #22
    //   7007: bipush #15
    //   7009: isub
    //   7010: iaload
    //   7011: iconst_3
    //   7012: iushr
    //   7013: ixor
    //   7014: iadd
    //   7015: aload #20
    //   7017: iload #22
    //   7019: bipush #16
    //   7021: isub
    //   7022: iaload
    //   7023: iadd
    //   7024: iastore
    //   7025: goto -> 7032
    //   7028: invokestatic a : (Ljava/lang/Throwable;)Ljava/lang/Throwable;
    //   7031: athrow
    //   7032: aload #21
    //   7034: bipush #7
    //   7036: iaload
    //   7037: aload #21
    //   7039: iconst_4
    //   7040: iaload
    //   7041: bipush #6
    //   7043: iushr
    //   7044: aload #21
    //   7046: iconst_4
    //   7047: iaload
    //   7048: bipush #26
    //   7050: ishl
    //   7051: ior
    //   7052: aload #21
    //   7054: iconst_4
    //   7055: iaload
    //   7056: bipush #11
    //   7058: iushr
    //   7059: aload #21
    //   7061: iconst_4
    //   7062: iaload
    //   7063: bipush #21
    //   7065: ishl
    //   7066: ior
    //   7067: ixor
    //   7068: aload #21
    //   7070: iconst_4
    //   7071: iaload
    //   7072: bipush #25
    //   7074: iushr
    //   7075: aload #21
    //   7077: iconst_4
    //   7078: iaload
    //   7079: bipush #7
    //   7081: ishl
    //   7082: ior
    //   7083: ixor
    //   7084: iadd
    //   7085: aload #21
    //   7087: bipush #6
    //   7089: iaload
    //   7090: aload #21
    //   7092: iconst_4
    //   7093: iaload
    //   7094: aload #21
    //   7096: iconst_5
    //   7097: iaload
    //   7098: aload #21
    //   7100: bipush #6
    //   7102: iaload
    //   7103: ixor
    //   7104: iand
    //   7105: ixor
    //   7106: iadd
    //   7107: aload #7
    //   7109: iload #22
    //   7111: iaload
    //   7112: iadd
    //   7113: aload #20
    //   7115: iload #22
    //   7117: iaload
    //   7118: iadd
    //   7119: istore #23
    //   7121: aload #21
    //   7123: iconst_0
    //   7124: iaload
    //   7125: iconst_2
    //   7126: iushr
    //   7127: aload #21
    //   7129: iconst_0
    //   7130: iaload
    //   7131: bipush #30
    //   7133: ishl
    //   7134: ior
    //   7135: aload #21
    //   7137: iconst_0
    //   7138: iaload
    //   7139: bipush #13
    //   7141: iushr
    //   7142: aload #21
    //   7144: iconst_0
    //   7145: iaload
    //   7146: bipush #19
    //   7148: ishl
    //   7149: ior
    //   7150: ixor
    //   7151: aload #21
    //   7153: iconst_0
    //   7154: iaload
    //   7155: bipush #22
    //   7157: iushr
    //   7158: aload #21
    //   7160: iconst_0
    //   7161: iaload
    //   7162: bipush #10
    //   7164: ishl
    //   7165: ior
    //   7166: ixor
    //   7167: aload #21
    //   7169: iconst_0
    //   7170: iaload
    //   7171: aload #21
    //   7173: iconst_1
    //   7174: iaload
    //   7175: iand
    //   7176: aload #21
    //   7178: iconst_2
    //   7179: iaload
    //   7180: aload #21
    //   7182: iconst_0
    //   7183: iaload
    //   7184: aload #21
    //   7186: iconst_1
    //   7187: iaload
    //   7188: ior
    //   7189: iand
    //   7190: ior
    //   7191: iadd
    //   7192: istore #24
    //   7194: aload #21
    //   7196: iconst_3
    //   7197: dup2
    //   7198: iaload
    //   7199: iload #23
    //   7201: iadd
    //   7202: iastore
    //   7203: aload #21
    //   7205: bipush #7
    //   7207: iload #23
    //   7209: iload #24
    //   7211: iadd
    //   7212: iastore
    //   7213: aload #21
    //   7215: bipush #7
    //   7217: iaload
    //   7218: istore #23
    //   7220: aload #21
    //   7222: bipush #7
    //   7224: aload #21
    //   7226: bipush #6
    //   7228: iaload
    //   7229: iastore
    //   7230: aload #21
    //   7232: bipush #6
    //   7234: aload #21
    //   7236: iconst_5
    //   7237: iaload
    //   7238: iastore
    //   7239: aload #21
    //   7241: iconst_5
    //   7242: aload #21
    //   7244: iconst_4
    //   7245: iaload
    //   7246: iastore
    //   7247: aload #21
    //   7249: iconst_4
    //   7250: aload #21
    //   7252: iconst_3
    //   7253: iaload
    //   7254: iastore
    //   7255: aload #21
    //   7257: iconst_3
    //   7258: aload #21
    //   7260: iconst_2
    //   7261: iaload
    //   7262: iastore
    //   7263: aload #21
    //   7265: iconst_2
    //   7266: aload #21
    //   7268: iconst_1
    //   7269: iaload
    //   7270: iastore
    //   7271: aload #21
    //   7273: iconst_1
    //   7274: aload #21
    //   7276: iconst_0
    //   7277: iaload
    //   7278: iastore
    //   7279: aload #21
    //   7281: iconst_0
    //   7282: iload #23
    //   7284: iastore
    //   7285: iinc #22, 1
    //   7288: iload_2
    //   7289: ifeq -> 6797
    //   7292: iconst_0
    //   7293: istore #22
    //   7295: iload #22
    //   7297: bipush #8
    //   7299: if_icmpge -> 7322
    //   7302: aload #9
    //   7304: iload #22
    //   7306: dup2
    //   7307: iaload
    //   7308: aload #21
    //   7310: iload #22
    //   7312: iaload
    //   7313: iadd
    //   7314: iastore
    //   7315: iinc #22, 1
    //   7318: iload_2
    //   7319: ifeq -> 7295
    //   7322: iinc #14, 64
    //   7325: iinc #18, -64
    //   7328: iload_2
    //   7329: ifeq -> 6718
    //   7332: iload #18
    //   7334: ifle -> 7370
    //   7337: iconst_0
    //   7338: istore #20
    //   7340: iload #20
    //   7342: iload #18
    //   7344: if_icmpge -> 7370
    //   7347: aload #10
    //   7349: iload #13
    //   7351: iload #20
    //   7353: iadd
    //   7354: aload #6
    //   7356: iload #14
    //   7358: iload #20
    //   7360: iadd
    //   7361: baload
    //   7362: bastore
    //   7363: iinc #20, 1
    //   7366: iload_2
    //   7367: ifeq -> 7340
    //   7370: bipush #8
    //   7372: newarray byte
    //   7374: astore #20
    //   7376: aload #20
    //   7378: iconst_0
    //   7379: iload #15
    //   7381: bipush #24
    //   7383: iushr
    //   7384: i2b
    //   7385: bastore
    //   7386: aload #20
    //   7388: iconst_1
    //   7389: iload #15
    //   7391: bipush #16
    //   7393: iushr
    //   7394: i2b
    //   7395: bastore
    //   7396: aload #20
    //   7398: iconst_2
    //   7399: iload #15
    //   7401: bipush #8
    //   7403: iushr
    //   7404: i2b
    //   7405: bastore
    //   7406: aload #20
    //   7408: iconst_3
    //   7409: iload #15
    //   7411: i2b
    //   7412: bastore
    //   7413: aload #20
    //   7415: iconst_4
    //   7416: iload #16
    //   7418: bipush #24
    //   7420: iushr
    //   7421: i2b
    //   7422: bastore
    //   7423: aload #20
    //   7425: iconst_5
    //   7426: iload #16
    //   7428: bipush #16
    //   7430: iushr
    //   7431: i2b
    //   7432: bastore
    //   7433: aload #20
    //   7435: bipush #6
    //   7437: iload #16
    //   7439: bipush #8
    //   7441: iushr
    //   7442: i2b
    //   7443: bastore
    //   7444: aload #20
    //   7446: bipush #7
    //   7448: iload #16
    //   7450: i2b
    //   7451: bastore
    //   7452: bipush #8
    //   7454: istore #12
    //   7456: aload #8
    //   7458: iconst_0
    //   7459: iaload
    //   7460: bipush #63
    //   7462: iand
    //   7463: istore #13
    //   7465: bipush #64
    //   7467: iload #13
    //   7469: isub
    //   7470: istore #19
    //   7472: aload #8
    //   7474: iconst_0
    //   7475: dup2
    //   7476: iaload
    //   7477: iload #12
    //   7479: iadd
    //   7480: iastore
    //   7481: aload #8
    //   7483: iconst_0
    //   7484: dup2
    //   7485: iaload
    //   7486: iconst_m1
    //   7487: iand
    //   7488: iastore
    //   7489: aload #8
    //   7491: iconst_0
    //   7492: iaload
    //   7493: iload #12
    //   7495: if_icmpge -> 7513
    //   7498: aload #8
    //   7500: iconst_1
    //   7501: dup2
    //   7502: iaload
    //   7503: iconst_1
    //   7504: iadd
    //   7505: iastore
    //   7506: goto -> 7513
    //   7509: invokestatic a : (Ljava/lang/Throwable;)Ljava/lang/Throwable;
    //   7512: athrow
    //   7513: iload #13
    //   7515: ifle -> 8129
    //   7518: iload #12
    //   7520: iload #19
    //   7522: if_icmplt -> 8129
    //   7525: goto -> 7532
    //   7528: invokestatic a : (Ljava/lang/Throwable;)Ljava/lang/Throwable;
    //   7531: athrow
    //   7532: iconst_0
    //   7533: istore #21
    //   7535: iload #21
    //   7537: iload #19
    //   7539: if_icmpge -> 7562
    //   7542: aload #10
    //   7544: iload #13
    //   7546: iload #21
    //   7548: iadd
    //   7549: aload #20
    //   7551: iload #21
    //   7553: baload
    //   7554: bastore
    //   7555: iinc #21, 1
    //   7558: iload_2
    //   7559: ifeq -> 7535
    //   7562: bipush #64
    //   7564: newarray int
    //   7566: astore #21
    //   7568: bipush #8
    //   7570: newarray int
    //   7572: astore #22
    //   7574: iconst_0
    //   7575: istore #23
    //   7577: iload #23
    //   7579: bipush #8
    //   7581: if_icmpge -> 7601
    //   7584: aload #22
    //   7586: iload #23
    //   7588: aload #9
    //   7590: iload #23
    //   7592: iaload
    //   7593: iastore
    //   7594: iinc #23, 1
    //   7597: iload_2
    //   7598: ifeq -> 7577
    //   7601: iconst_0
    //   7602: istore #23
    //   7604: iload #23
    //   7606: bipush #64
    //   7608: if_icmpge -> 8099
    //   7611: iload #23
    //   7613: bipush #16
    //   7615: if_icmpge -> 7696
    //   7618: aload #21
    //   7620: iload #23
    //   7622: aload #10
    //   7624: iconst_4
    //   7625: iload #23
    //   7627: imul
    //   7628: baload
    //   7629: sipush #255
    //   7632: iand
    //   7633: bipush #24
    //   7635: ishl
    //   7636: aload #10
    //   7638: iconst_4
    //   7639: iload #23
    //   7641: imul
    //   7642: iconst_1
    //   7643: iadd
    //   7644: baload
    //   7645: sipush #255
    //   7648: iand
    //   7649: bipush #16
    //   7651: ishl
    //   7652: ior
    //   7653: aload #10
    //   7655: iconst_4
    //   7656: iload #23
    //   7658: imul
    //   7659: iconst_2
    //   7660: iadd
    //   7661: baload
    //   7662: sipush #255
    //   7665: iand
    //   7666: bipush #8
    //   7668: ishl
    //   7669: ior
    //   7670: aload #10
    //   7672: iconst_4
    //   7673: iload #23
    //   7675: imul
    //   7676: iconst_3
    //   7677: iadd
    //   7678: baload
    //   7679: sipush #255
    //   7682: iand
    //   7683: ior
    //   7684: iastore
    //   7685: iload_2
    //   7686: ifeq -> 7839
    //   7689: goto -> 7696
    //   7692: invokestatic a : (Ljava/lang/Throwable;)Ljava/lang/Throwable;
    //   7695: athrow
    //   7696: aload #21
    //   7698: iload #23
    //   7700: aload #21
    //   7702: iload #23
    //   7704: iconst_2
    //   7705: isub
    //   7706: iaload
    //   7707: bipush #17
    //   7709: iushr
    //   7710: aload #21
    //   7712: iload #23
    //   7714: iconst_2
    //   7715: isub
    //   7716: iaload
    //   7717: bipush #15
    //   7719: ishl
    //   7720: ior
    //   7721: aload #21
    //   7723: iload #23
    //   7725: iconst_2
    //   7726: isub
    //   7727: iaload
    //   7728: bipush #19
    //   7730: iushr
    //   7731: aload #21
    //   7733: iload #23
    //   7735: iconst_2
    //   7736: isub
    //   7737: iaload
    //   7738: bipush #13
    //   7740: ishl
    //   7741: ior
    //   7742: ixor
    //   7743: aload #21
    //   7745: iload #23
    //   7747: iconst_2
    //   7748: isub
    //   7749: iaload
    //   7750: bipush #10
    //   7752: iushr
    //   7753: ixor
    //   7754: aload #21
    //   7756: iload #23
    //   7758: bipush #7
    //   7760: isub
    //   7761: iaload
    //   7762: iadd
    //   7763: aload #21
    //   7765: iload #23
    //   7767: bipush #15
    //   7769: isub
    //   7770: iaload
    //   7771: bipush #7
    //   7773: iushr
    //   7774: aload #21
    //   7776: iload #23
    //   7778: bipush #15
    //   7780: isub
    //   7781: iaload
    //   7782: bipush #25
    //   7784: ishl
    //   7785: ior
    //   7786: aload #21
    //   7788: iload #23
    //   7790: bipush #15
    //   7792: isub
    //   7793: iaload
    //   7794: bipush #18
    //   7796: iushr
    //   7797: aload #21
    //   7799: iload #23
    //   7801: bipush #15
    //   7803: isub
    //   7804: iaload
    //   7805: bipush #14
    //   7807: ishl
    //   7808: ior
    //   7809: ixor
    //   7810: aload #21
    //   7812: iload #23
    //   7814: bipush #15
    //   7816: isub
    //   7817: iaload
    //   7818: iconst_3
    //   7819: iushr
    //   7820: ixor
    //   7821: iadd
    //   7822: aload #21
    //   7824: iload #23
    //   7826: bipush #16
    //   7828: isub
    //   7829: iaload
    //   7830: iadd
    //   7831: iastore
    //   7832: goto -> 7839
    //   7835: invokestatic a : (Ljava/lang/Throwable;)Ljava/lang/Throwable;
    //   7838: athrow
    //   7839: aload #22
    //   7841: bipush #7
    //   7843: iaload
    //   7844: aload #22
    //   7846: iconst_4
    //   7847: iaload
    //   7848: bipush #6
    //   7850: iushr
    //   7851: aload #22
    //   7853: iconst_4
    //   7854: iaload
    //   7855: bipush #26
    //   7857: ishl
    //   7858: ior
    //   7859: aload #22
    //   7861: iconst_4
    //   7862: iaload
    //   7863: bipush #11
    //   7865: iushr
    //   7866: aload #22
    //   7868: iconst_4
    //   7869: iaload
    //   7870: bipush #21
    //   7872: ishl
    //   7873: ior
    //   7874: ixor
    //   7875: aload #22
    //   7877: iconst_4
    //   7878: iaload
    //   7879: bipush #25
    //   7881: iushr
    //   7882: aload #22
    //   7884: iconst_4
    //   7885: iaload
    //   7886: bipush #7
    //   7888: ishl
    //   7889: ior
    //   7890: ixor
    //   7891: iadd
    //   7892: aload #22
    //   7894: bipush #6
    //   7896: iaload
    //   7897: aload #22
    //   7899: iconst_4
    //   7900: iaload
    //   7901: aload #22
    //   7903: iconst_5
    //   7904: iaload
    //   7905: aload #22
    //   7907: bipush #6
    //   7909: iaload
    //   7910: ixor
    //   7911: iand
    //   7912: ixor
    //   7913: iadd
    //   7914: aload #7
    //   7916: iload #23
    //   7918: iaload
    //   7919: iadd
    //   7920: aload #21
    //   7922: iload #23
    //   7924: iaload
    //   7925: iadd
    //   7926: istore #24
    //   7928: aload #22
    //   7930: iconst_0
    //   7931: iaload
    //   7932: iconst_2
    //   7933: iushr
    //   7934: aload #22
    //   7936: iconst_0
    //   7937: iaload
    //   7938: bipush #30
    //   7940: ishl
    //   7941: ior
    //   7942: aload #22
    //   7944: iconst_0
    //   7945: iaload
    //   7946: bipush #13
    //   7948: iushr
    //   7949: aload #22
    //   7951: iconst_0
    //   7952: iaload
    //   7953: bipush #19
    //   7955: ishl
    //   7956: ior
    //   7957: ixor
    //   7958: aload #22
    //   7960: iconst_0
    //   7961: iaload
    //   7962: bipush #22
    //   7964: iushr
    //   7965: aload #22
    //   7967: iconst_0
    //   7968: iaload
    //   7969: bipush #10
    //   7971: ishl
    //   7972: ior
    //   7973: ixor
    //   7974: aload #22
    //   7976: iconst_0
    //   7977: iaload
    //   7978: aload #22
    //   7980: iconst_1
    //   7981: iaload
    //   7982: iand
    //   7983: aload #22
    //   7985: iconst_2
    //   7986: iaload
    //   7987: aload #22
    //   7989: iconst_0
    //   7990: iaload
    //   7991: aload #22
    //   7993: iconst_1
    //   7994: iaload
    //   7995: ior
    //   7996: iand
    //   7997: ior
    //   7998: iadd
    //   7999: istore #25
    //   8001: aload #22
    //   8003: iconst_3
    //   8004: dup2
    //   8005: iaload
    //   8006: iload #24
    //   8008: iadd
    //   8009: iastore
    //   8010: aload #22
    //   8012: bipush #7
    //   8014: iload #24
    //   8016: iload #25
    //   8018: iadd
    //   8019: iastore
    //   8020: aload #22
    //   8022: bipush #7
    //   8024: iaload
    //   8025: istore #24
    //   8027: aload #22
    //   8029: bipush #7
    //   8031: aload #22
    //   8033: bipush #6
    //   8035: iaload
    //   8036: iastore
    //   8037: aload #22
    //   8039: bipush #6
    //   8041: aload #22
    //   8043: iconst_5
    //   8044: iaload
    //   8045: iastore
    //   8046: aload #22
    //   8048: iconst_5
    //   8049: aload #22
    //   8051: iconst_4
    //   8052: iaload
    //   8053: iastore
    //   8054: aload #22
    //   8056: iconst_4
    //   8057: aload #22
    //   8059: iconst_3
    //   8060: iaload
    //   8061: iastore
    //   8062: aload #22
    //   8064: iconst_3
    //   8065: aload #22
    //   8067: iconst_2
    //   8068: iaload
    //   8069: iastore
    //   8070: aload #22
    //   8072: iconst_2
    //   8073: aload #22
    //   8075: iconst_1
    //   8076: iaload
    //   8077: iastore
    //   8078: aload #22
    //   8080: iconst_1
    //   8081: aload #22
    //   8083: iconst_0
    //   8084: iaload
    //   8085: iastore
    //   8086: aload #22
    //   8088: iconst_0
    //   8089: iload #24
    //   8091: iastore
    //   8092: iinc #23, 1
    //   8095: iload_2
    //   8096: ifeq -> 7604
    //   8099: iconst_0
    //   8100: istore #23
    //   8102: iload #23
    //   8104: bipush #8
    //   8106: if_icmpge -> 8129
    //   8109: aload #9
    //   8111: iload #23
    //   8113: dup2
    //   8114: iaload
    //   8115: aload #22
    //   8117: iload #23
    //   8119: iaload
    //   8120: iadd
    //   8121: iastore
    //   8122: iinc #23, 1
    //   8125: iload_2
    //   8126: ifeq -> 8102
    //   8129: bipush #32
    //   8131: newarray byte
    //   8133: astore #5
    //   8135: aload #5
    //   8137: iconst_0
    //   8138: aload #9
    //   8140: iconst_0
    //   8141: iaload
    //   8142: bipush #24
    //   8144: iushr
    //   8145: i2b
    //   8146: bastore
    //   8147: aload #5
    //   8149: iconst_1
    //   8150: aload #9
    //   8152: iconst_0
    //   8153: iaload
    //   8154: bipush #16
    //   8156: iushr
    //   8157: i2b
    //   8158: bastore
    //   8159: aload #5
    //   8161: iconst_2
    //   8162: aload #9
    //   8164: iconst_0
    //   8165: iaload
    //   8166: bipush #8
    //   8168: iushr
    //   8169: i2b
    //   8170: bastore
    //   8171: aload #5
    //   8173: iconst_3
    //   8174: aload #9
    //   8176: iconst_0
    //   8177: iaload
    //   8178: i2b
    //   8179: bastore
    //   8180: aload #5
    //   8182: iconst_4
    //   8183: aload #9
    //   8185: iconst_1
    //   8186: iaload
    //   8187: bipush #24
    //   8189: iushr
    //   8190: i2b
    //   8191: bastore
    //   8192: aload #5
    //   8194: iconst_5
    //   8195: aload #9
    //   8197: iconst_1
    //   8198: iaload
    //   8199: bipush #16
    //   8201: iushr
    //   8202: i2b
    //   8203: bastore
    //   8204: aload #5
    //   8206: bipush #6
    //   8208: aload #9
    //   8210: iconst_1
    //   8211: iaload
    //   8212: bipush #8
    //   8214: iushr
    //   8215: i2b
    //   8216: bastore
    //   8217: aload #5
    //   8219: bipush #7
    //   8221: aload #9
    //   8223: iconst_1
    //   8224: iaload
    //   8225: i2b
    //   8226: bastore
    //   8227: aload #5
    //   8229: bipush #8
    //   8231: aload #9
    //   8233: iconst_2
    //   8234: iaload
    //   8235: bipush #24
    //   8237: iushr
    //   8238: i2b
    //   8239: bastore
    //   8240: aload #5
    //   8242: bipush #9
    //   8244: aload #9
    //   8246: iconst_2
    //   8247: iaload
    //   8248: bipush #16
    //   8250: iushr
    //   8251: i2b
    //   8252: bastore
    //   8253: aload #5
    //   8255: bipush #10
    //   8257: aload #9
    //   8259: iconst_2
    //   8260: iaload
    //   8261: bipush #8
    //   8263: iushr
    //   8264: i2b
    //   8265: bastore
    //   8266: aload #5
    //   8268: bipush #11
    //   8270: aload #9
    //   8272: iconst_2
    //   8273: iaload
    //   8274: i2b
    //   8275: bastore
    //   8276: aload #5
    //   8278: bipush #12
    //   8280: aload #9
    //   8282: iconst_3
    //   8283: iaload
    //   8284: bipush #24
    //   8286: iushr
    //   8287: i2b
    //   8288: bastore
    //   8289: aload #5
    //   8291: bipush #13
    //   8293: aload #9
    //   8295: iconst_3
    //   8296: iaload
    //   8297: bipush #16
    //   8299: iushr
    //   8300: i2b
    //   8301: bastore
    //   8302: aload #5
    //   8304: bipush #14
    //   8306: aload #9
    //   8308: iconst_3
    //   8309: iaload
    //   8310: bipush #8
    //   8312: iushr
    //   8313: i2b
    //   8314: bastore
    //   8315: aload #5
    //   8317: bipush #15
    //   8319: aload #9
    //   8321: iconst_3
    //   8322: iaload
    //   8323: i2b
    //   8324: bastore
    //   8325: aload #5
    //   8327: bipush #16
    //   8329: aload #9
    //   8331: iconst_4
    //   8332: iaload
    //   8333: bipush #24
    //   8335: iushr
    //   8336: i2b
    //   8337: bastore
    //   8338: aload #5
    //   8340: bipush #17
    //   8342: aload #9
    //   8344: iconst_4
    //   8345: iaload
    //   8346: bipush #16
    //   8348: iushr
    //   8349: i2b
    //   8350: bastore
    //   8351: aload #5
    //   8353: bipush #18
    //   8355: aload #9
    //   8357: iconst_4
    //   8358: iaload
    //   8359: bipush #8
    //   8361: iushr
    //   8362: i2b
    //   8363: bastore
    //   8364: aload #5
    //   8366: bipush #19
    //   8368: aload #9
    //   8370: iconst_4
    //   8371: iaload
    //   8372: i2b
    //   8373: bastore
    //   8374: aload #5
    //   8376: bipush #20
    //   8378: aload #9
    //   8380: iconst_5
    //   8381: iaload
    //   8382: bipush #24
    //   8384: iushr
    //   8385: i2b
    //   8386: bastore
    //   8387: aload #5
    //   8389: bipush #21
    //   8391: aload #9
    //   8393: iconst_5
    //   8394: iaload
    //   8395: bipush #16
    //   8397: iushr
    //   8398: i2b
    //   8399: bastore
    //   8400: aload #5
    //   8402: bipush #22
    //   8404: aload #9
    //   8406: iconst_5
    //   8407: iaload
    //   8408: bipush #8
    //   8410: iushr
    //   8411: i2b
    //   8412: bastore
    //   8413: aload #5
    //   8415: bipush #23
    //   8417: aload #9
    //   8419: iconst_5
    //   8420: iaload
    //   8421: i2b
    //   8422: bastore
    //   8423: aload #5
    //   8425: bipush #24
    //   8427: aload #9
    //   8429: bipush #6
    //   8431: iaload
    //   8432: bipush #24
    //   8434: iushr
    //   8435: i2b
    //   8436: bastore
    //   8437: aload #5
    //   8439: bipush #25
    //   8441: aload #9
    //   8443: bipush #6
    //   8445: iaload
    //   8446: bipush #16
    //   8448: iushr
    //   8449: i2b
    //   8450: bastore
    //   8451: aload #5
    //   8453: bipush #26
    //   8455: aload #9
    //   8457: bipush #6
    //   8459: iaload
    //   8460: bipush #8
    //   8462: iushr
    //   8463: i2b
    //   8464: bastore
    //   8465: aload #5
    //   8467: bipush #27
    //   8469: aload #9
    //   8471: bipush #6
    //   8473: iaload
    //   8474: i2b
    //   8475: bastore
    //   8476: aload #5
    //   8478: bipush #28
    //   8480: aload #9
    //   8482: bipush #7
    //   8484: iaload
    //   8485: bipush #24
    //   8487: iushr
    //   8488: i2b
    //   8489: bastore
    //   8490: aload #5
    //   8492: bipush #29
    //   8494: aload #9
    //   8496: bipush #7
    //   8498: iaload
    //   8499: bipush #16
    //   8501: iushr
    //   8502: i2b
    //   8503: bastore
    //   8504: aload #5
    //   8506: bipush #30
    //   8508: aload #9
    //   8510: bipush #7
    //   8512: iaload
    //   8513: bipush #8
    //   8515: iushr
    //   8516: i2b
    //   8517: bastore
    //   8518: aload #5
    //   8520: bipush #31
    //   8522: aload #9
    //   8524: bipush #7
    //   8526: iaload
    //   8527: i2b
    //   8528: bastore
    //   8529: getstatic burp/Zbxp.ZS : Ljava/lang/String;
    //   8532: getstatic burp/Zz67.ZE : Ljava/lang/Object;
    //   8535: checkcast java/math/BigInteger
    //   8538: invokevirtual intValue : ()I
    //   8541: bipush #32
    //   8543: irem
    //   8544: invokestatic abs : (I)I
    //   8547: invokevirtual charAt : (I)C
    //   8550: getstatic burp/Zkvr.Zm : Ljava/lang/String;
    //   8553: getstatic burp/Zzwl.Z_ : Ljava/lang/Object;
    //   8556: checkcast java/math/BigInteger
    //   8559: invokevirtual intValue : ()I
    //   8562: bipush #32
    //   8564: irem
    //   8565: invokestatic abs : (I)I
    //   8568: invokevirtual charAt : (I)C
    //   8571: if_icmpgt -> 8678
    //   8574: getstatic burp/Zgwq.ZV : Ljava/lang/String;
    //   8577: getstatic burp/Zzy5.ZG : Ljava/lang/Object;
    //   8580: checkcast java/math/BigInteger
    //   8583: invokevirtual intValue : ()I
    //   8586: bipush #32
    //   8588: irem
    //   8589: invokestatic abs : (I)I
    //   8592: invokevirtual charAt : (I)C
    //   8595: getstatic burp/Zxyq.Zr : Ljava/lang/String;
    //   8598: getstatic burp/Zttj.ZF : Ljava/lang/Object;
    //   8601: checkcast java/math/BigInteger
    //   8604: invokevirtual intValue : ()I
    //   8607: bipush #32
    //   8609: irem
    //   8610: invokestatic abs : (I)I
    //   8613: invokevirtual charAt : (I)C
    //   8616: if_icmpgt -> 8678
    //   8619: goto -> 8626
    //   8622: invokestatic a : (Ljava/lang/Throwable;)Ljava/lang/Throwable;
    //   8625: athrow
    //   8626: getstatic burp/Ze3t.ZG : Ljava/lang/String;
    //   8629: getstatic burp/Zty5.Zf : Ljava/lang/Object;
    //   8632: checkcast java/math/BigInteger
    //   8635: invokevirtual intValue : ()I
    //   8638: bipush #32
    //   8640: irem
    //   8641: invokestatic abs : (I)I
    //   8644: invokevirtual charAt : (I)C
    //   8647: getstatic burp/Zxd0.Zc : Ljava/lang/String;
    //   8650: getstatic burp/Zz58.ZD : Ljava/lang/Object;
    //   8653: checkcast java/math/BigInteger
    //   8656: invokevirtual intValue : ()I
    //   8659: bipush #32
    //   8661: irem
    //   8662: invokestatic abs : (I)I
    //   8665: invokevirtual charAt : (I)C
    //   8668: if_icmple -> 8686
    //   8671: goto -> 8678
    //   8674: invokestatic a : (Ljava/lang/Throwable;)Ljava/lang/Throwable;
    //   8677: athrow
    //   8678: iconst_1
    //   8679: goto -> 8687
    //   8682: invokestatic a : (Ljava/lang/Throwable;)Ljava/lang/Throwable;
    //   8685: athrow
    //   8686: iconst_0
    //   8687: ireturn
    //   8688: astore_3
    //   8689: new java/lang/Exception
    //   8692: dup
    //   8693: aload_3
    //   8694: invokevirtual getMessage : ()Ljava/lang/String;
    //   8697: invokespecial <init> : (Ljava/lang/String;)V
    //   8700: athrow
    // Exception table:
    //   from	to	target	type
    //   4	8687	8688	java/lang/Throwable
    //   22	198	201	java/lang/Throwable
    //   168	235	238	java/lang/Throwable
    //   205	272	275	java/lang/Throwable
    //   242	309	312	java/lang/Throwable
    //   279	346	349	java/lang/Throwable
    //   316	383	386	java/lang/Throwable
    //   353	420	423	java/lang/Throwable
    //   390	457	460	java/lang/Throwable
    //   427	494	497	java/lang/Throwable
    //   464	531	534	java/lang/Throwable
    //   501	568	571	java/lang/Throwable
    //   538	605	608	java/lang/Throwable
    //   575	642	645	java/lang/Throwable
    //   612	679	682	java/lang/Throwable
    //   649	716	719	java/lang/Throwable
    //   686	753	756	java/lang/Throwable
    //   723	790	793	java/lang/Throwable
    //   760	827	830	java/lang/Throwable
    //   797	864	867	java/lang/Throwable
    //   834	901	904	java/lang/Throwable
    //   871	938	941	java/lang/Throwable
    //   908	975	978	java/lang/Throwable
    //   945	1012	1015	java/lang/Throwable
    //   982	1049	1052	java/lang/Throwable
    //   1019	1086	1089	java/lang/Throwable
    //   1056	1123	1126	java/lang/Throwable
    //   1093	1160	1163	java/lang/Throwable
    //   1130	1197	1200	java/lang/Throwable
    //   1167	1234	1237	java/lang/Throwable
    //   1204	1271	1274	java/lang/Throwable
    //   1241	1308	1311	java/lang/Throwable
    //   1278	1341	1344	java/lang/Throwable
    //   1760	1775	1775	java/lang/Throwable
    //   2777	2803	2803	java/lang/Throwable
    //   2884	2899	2899	java/lang/Throwable
    //   4081	4106	4109	java/lang/Throwable
    //   4177	4191	4191	java/lang/Throwable
    //   4202	4215	4218	java/lang/Throwable
    //   4207	4230	4233	java/lang/Throwable
    //   4222	4248	4251	java/lang/Throwable
    //   4237	4278	4281	java/lang/Throwable
    //   4344	4371	4374	java/lang/Throwable
    //   4361	4392	4395	java/lang/Throwable
    //   4378	4422	4425	java/lang/Throwable
    //   4399	4433	4433	java/lang/Throwable
    //   4444	4460	4463	java/lang/Throwable
    //   5270	5304	5307	java/lang/Throwable
    //   5400	5478	5481	java/lang/Throwable
    //   5407	5621	5624	java/lang/Throwable
    //   5999	6014	6014	java/lang/Throwable
    //   6041	6075	6078	java/lang/Throwable
    //   6085	6097	6100	java/lang/Throwable
    //   6183	6261	6264	java/lang/Throwable
    //   6190	6404	6407	java/lang/Throwable
    //   6804	6882	6885	java/lang/Throwable
    //   6811	7025	7028	java/lang/Throwable
    //   7472	7506	7509	java/lang/Throwable
    //   7513	7525	7528	java/lang/Throwable
    //   7611	7689	7692	java/lang/Throwable
    //   7618	7832	7835	java/lang/Throwable
    //   8135	8619	8622	java/lang/Throwable
    //   8574	8671	8674	java/lang/Throwable
    //   8626	8682	8682	java/lang/Throwable
  }
  
  static void Zz(Object paramObject) {
    Zljx.ZD = a(28803, 30968);
    Zljx.ZZ = new BigInteger(a(28805, 8841));
    boolean bool = Zt2e.ZK();
    try {
      try {
        if (Zkvr.Zm.charAt(Math.abs(((BigInteger)Zlno.ZU).intValue() % 32)) <= Zs36.Zr.charAt(Math.abs(((BigInteger)Zty3.Zz).intValue() % 32))) {
          try {
            Zrva.ZO(Class.forName(a(28813, -5240)));
            if (bool)
              Zs33.ZG(Class.forName(a(28815, -4855))); 
          } catch (Throwable throwable) {
            throw a(null);
          } 
          return;
        } 
      } catch (Throwable throwable) {
        throw a(null);
      } 
      Zs33.ZG(Class.forName(a(28815, -4855)));
    } catch (Throwable throwable) {}
  }
  
  static void Zt(Object[] paramArrayOfObject, Object paramObject) throws Throwable {}
  
  static {
    // Byte code:
    //   0: bipush #11
    //   2: anewarray java/lang/String
    //   5: astore #5
    //   7: iconst_0
    //   8: istore_3
    //   9: ldc '{=tG)ncoXb44't mqwkZKQ~a9LUI[j8[=??\\t_6-\\tK,U"\??> G9ouB\C{D/EgVsA|m\\t9b1'
    //   11: dup
    //   12: astore_2
    //   13: invokevirtual length : ()I
    //   16: istore #4
    //   18: bipush #77
    //   20: istore_1
    //   21: iconst_m1
    //   22: istore_0
    //   23: bipush #13
    //   25: iinc #0, 1
    //   28: aload_2
    //   29: iload_0
    //   30: dup
    //   31: iload_1
    //   32: iadd
    //   33: invokevirtual substring : (II)Ljava/lang/String;
    //   36: iconst_m1
    //   37: goto -> 143
    //   40: aload #5
    //   42: swap
    //   43: iload_3
    //   44: iinc #3, 1
    //   47: swap
    //   48: aastore
    //   49: iload_0
    //   50: iload_1
    //   51: iadd
    //   52: dup
    //   53: istore_0
    //   54: iload #4
    //   56: if_icmpge -> 68
    //   59: aload_2
    //   60: iload_0
    //   61: invokevirtual charAt : (I)C
    //   64: istore_1
    //   65: goto -> 23
    //   68: ldc 'xc!,alm83'\\t^=\\te`)0'
    //   70: dup
    //   71: astore_2
    //   72: invokevirtual length : ()I
    //   75: istore #4
    //   77: bipush #32
    //   79: istore_1
    //   80: iconst_m1
    //   81: istore_0
    //   82: bipush #61
    //   84: iinc #0, 1
    //   87: aload_2
    //   88: iload_0
    //   89: dup
    //   90: iload_1
    //   91: iadd
    //   92: invokevirtual substring : (II)Ljava/lang/String;
    //   95: iconst_0
    //   96: goto -> 143
    //   99: aload #5
    //   101: swap
    //   102: iload_3
    //   103: iinc #3, 1
    //   106: swap
    //   107: aastore
    //   108: iload_0
    //   109: iload_1
    //   110: iadd
    //   111: dup
    //   112: istore_0
    //   113: iload #4
    //   115: if_icmpge -> 127
    //   118: aload_2
    //   119: iload_0
    //   120: invokevirtual charAt : (I)C
    //   123: istore_1
    //   124: goto -> 82
    //   127: aload #5
    //   129: putstatic burp/Zxsb.a : [Ljava/lang/String;
    //   132: bipush #11
    //   134: anewarray java/lang/String
    //   137: putstatic burp/Zxsb.b : [Ljava/lang/String;
    //   140: goto -> 300
    //   143: dup_x2
    //   144: pop
    //   145: invokevirtual toCharArray : ()[C
    //   148: dup_x1
    //   149: arraylength
    //   150: dup_x2
    //   151: pop
    //   152: iconst_0
    //   153: istore #6
    //   155: dup2_x1
    //   156: pop2
    //   157: dup_x2
    //   158: iconst_1
    //   159: if_icmpgt -> 259
    //   162: dup2
    //   163: swap
    //   164: iload #6
    //   166: dup2_x1
    //   167: caload
    //   168: swap
    //   169: iload #6
    //   171: bipush #7
    //   173: irem
    //   174: tableswitch default -> 242, 0 -> 212, 1 -> 217, 2 -> 222, 3 -> 227, 4 -> 232, 5 -> 237
    //   212: bipush #47
    //   214: goto -> 243
    //   217: bipush #92
    //   219: goto -> 243
    //   222: bipush #80
    //   224: goto -> 243
    //   227: bipush #103
    //   229: goto -> 243
    //   232: bipush #100
    //   234: goto -> 243
    //   237: bipush #119
    //   239: goto -> 243
    //   242: iconst_5
    //   243: ixor
    //   244: ixor
    //   245: i2c
    //   246: castore
    //   247: iinc #6, 1
    //   250: dup
    //   251: ifne -> 259
    //   254: dup2
    //   255: dup_x1
    //   256: goto -> 166
    //   259: dup2_x1
    //   260: pop2
    //   261: dup_x2
    //   262: iload #6
    //   264: if_icmpgt -> 162
    //   267: pop
    //   268: new java/lang/String
    //   271: dup_x1
    //   272: swap
    //   273: invokespecial <init> : ([C)V
    //   276: invokevirtual intern : ()Ljava/lang/String;
    //   279: swap
    //   280: pop
    //   281: swap
    //   282: tableswitch default -> 40, 0 -> 99
    //   300: new java/math/BigInteger
    //   303: dup
    //   304: bipush #32
    //   306: newarray byte
    //   308: dup
    //   309: iconst_0
    //   310: bipush #28
    //   312: bastore
    //   313: dup
    //   314: iconst_1
    //   315: bipush #-95
    //   317: bastore
    //   318: dup
    //   319: iconst_2
    //   320: bipush #-102
    //   322: bastore
    //   323: dup
    //   324: iconst_3
    //   325: bipush #110
    //   327: bastore
    //   328: dup
    //   329: iconst_4
    //   330: bipush #107
    //   332: bastore
    //   333: dup
    //   334: iconst_5
    //   335: bipush #-74
    //   337: bastore
    //   338: dup
    //   339: bipush #6
    //   341: bipush #-46
    //   343: bastore
    //   344: dup
    //   345: bipush #7
    //   347: bipush #92
    //   349: bastore
    //   350: dup
    //   351: bipush #8
    //   353: bipush #88
    //   355: bastore
    //   356: dup
    //   357: bipush #9
    //   359: bipush #-106
    //   361: bastore
    //   362: dup
    //   363: bipush #10
    //   365: bipush #101
    //   367: bastore
    //   368: dup
    //   369: bipush #11
    //   371: iconst_0
    //   372: bastore
    //   373: dup
    //   374: bipush #12
    //   376: bipush #-95
    //   378: bastore
    //   379: dup
    //   380: bipush #13
    //   382: bipush #80
    //   384: bastore
    //   385: dup
    //   386: bipush #14
    //   388: bipush #58
    //   390: bastore
    //   391: dup
    //   392: bipush #15
    //   394: bipush #-28
    //   396: bastore
    //   397: dup
    //   398: bipush #16
    //   400: bipush #10
    //   402: bastore
    //   403: dup
    //   404: bipush #17
    //   406: bipush #-13
    //   408: bastore
    //   409: dup
    //   410: bipush #18
    //   412: bipush #53
    //   414: bastore
    //   415: dup
    //   416: bipush #19
    //   418: bipush #48
    //   420: bastore
    //   421: dup
    //   422: bipush #20
    //   424: bipush #-104
    //   426: bastore
    //   427: dup
    //   428: bipush #21
    //   430: bipush #68
    //   432: bastore
    //   433: dup
    //   434: bipush #22
    //   436: bipush #-109
    //   438: bastore
    //   439: dup
    //   440: bipush #23
    //   442: bipush #25
    //   444: bastore
    //   445: dup
    //   446: bipush #24
    //   448: bipush #28
    //   450: bastore
    //   451: dup
    //   452: bipush #25
    //   454: bipush #124
    //   456: bastore
    //   457: dup
    //   458: bipush #26
    //   460: bipush #-113
    //   462: bastore
    //   463: dup
    //   464: bipush #27
    //   466: bipush #74
    //   468: bastore
    //   469: dup
    //   470: bipush #28
    //   472: bipush #89
    //   474: bastore
    //   475: dup
    //   476: bipush #29
    //   478: bipush #-70
    //   480: bastore
    //   481: dup
    //   482: bipush #30
    //   484: bipush #-32
    //   486: bastore
    //   487: dup
    //   488: bipush #31
    //   490: bipush #26
    //   492: bastore
    //   493: invokespecial <init> : ([B)V
    //   496: putstatic burp/Zxsb.ZN : Ljava/lang/Object;
    //   499: sipush #28812
    //   502: sipush #12073
    //   505: invokestatic a : (II)Ljava/lang/String;
    //   508: putstatic burp/Zxsb.Zh : Ljava/lang/String;
    //   511: return
  }
  
  private static Throwable a(Throwable paramThrowable) {
    return paramThrowable;
  }
  
  private static String a(int paramInt1, int paramInt2) {
    int i = (paramInt1 ^ 0x7085) & 0xFFFF;
    if (b[i] == null) {
      char[] arrayOfChar = a[i].toCharArray();
      switch (arrayOfChar[0] & 0xFF) {
        case 0:
        
        case 1:
        
        case 2:
        
        case 3:
        
        case 4:
        
        case 5:
        
        case 6:
        
        case 7:
        
        case 8:
        
        case 9:
        
        case 10:
        
        case 11:
        
        case 12:
        
        case 13:
        
        case 14:
        
        case 15:
        
        case 16:
        
        case 17:
        
        case 18:
        
        case 19:
        
        case 20:
        
        case 21:
        
        case 22:
        
        case 23:
        
        case 24:
        
        case 25:
        
        case 26:
        
        case 27:
        
        case 28:
        
        case 29:
        
        case 30:
        
        case 31:
        
        case 32:
        
        case 33:
        
        case 34:
        
        case 35:
        
        case 36:
        
        case 37:
        
        case 38:
        
        case 39:
        
        case 40:
        
        case 41:
        
        case 42:
        
        case 43:
        
        case 44:
        
        case 45:
        
        case 46:
        
        case 47:
        
        case 48:
        
        case 49:
        
        case 50:
        
        case 51:
        
        case 52:
        
        case 53:
        
        case 54:
        
        case 55:
        
        case 56:
        
        case 57:
        
        case 58:
        
        case 59:
        
        case 60:
        
        case 61:
        
        case 62:
        
        case 63:
        
        case 64:
        
        case 65:
        
        case 66:
        
        case 67:
        
        case 68:
        
        case 69:
        
        case 70:
        
        case 71:
        
        case 72:
        
        case 73:
        
        case 74:
        
        case 75:
        
        case 76:
        
        case 77:
        
        case 78:
        
        case 79:
        
        case 80:
        
        case 81:
        
        case 82:
        
        case 83:
        
        case 84:
        
        case 85:
        
        case 86:
        
        case 87:
        
        case 88:
        
        case 89:
        
        case 90:
        
        case 91:
        
        case 92:
        
        case 93:
        
        case 94:
        
        case 95:
        
        case 96:
        
        case 97:
        
        case 98:
        
        case 99:
        
        case 100:
        
        case 101:
        
        case 102:
        
        case 103:
        
        case 104:
        
        case 105:
        
        case 106:
        
        case 107:
        
        case 108:
        
        case 109:
        
        case 110:
        
        case 111:
        
        case 112:
        
        case 113:
        
        case 114:
        
        case 115:
        
        case 116:
        
        case 117:
        
        case 118:
        
        case 119:
        
        case 120:
        
        case 121:
        
        case 122:
        
        case 123:
        
        case 124:
        
        case 125:
        
        case 126:
        
        case 127:
        
        case 128:
        
        case 129:
        
        case 130:
        
        case 131:
        
        case 132:
        
        case 133:
        
        case 134:
        
        case 135:
        
        case 136:
        
        case 137:
        
        case 138:
        
        case 139:
        
        case 140:
        
        case 141:
        
        case 142:
        
        case 143:
        
        case 144:
        
        case 145:
        
        case 146:
        
        case 147:
        
        case 148:
        
        case 149:
        
        case 150:
        
        case 151:
        
        case 152:
        
        case 153:
        
        case 154:
        
        case 155:
        
        case 156:
        
        case 157:
        
        case 158:
        
        case 159:
        
        case 160:
        
        case 161:
        
        case 162:
        
        case 163:
        
        case 164:
        
        case 165:
        
        case 166:
        
        case 167:
        
        case 168:
        
        case 169:
        
        case 170:
        
        case 171:
        
        case 172:
        
        case 173:
        
        case 174:
        
        case 175:
        
        case 176:
        
        case 177:
        
        case 178:
        
        case 179:
        
        case 180:
        
        case 181:
        
        case 182:
        
        case 183:
        
        case 184:
        
        case 185:
        
        case 186:
        
        case 187:
        
        case 188:
        
        case 189:
        
        case 190:
        
        case 191:
        
        case 192:
        
        case 193:
        
        case 194:
        
        case 195:
        
        case 196:
        
        case 197:
        
        case 198:
        
        case 199:
        
        case 200:
        
        case 201:
        
        case 202:
        
        case 203:
        
        case 204:
        
        case 205:
        
        case 206:
        
        case 207:
        
        case 208:
        
        case 209:
        
        case 210:
        
        case 211:
        
        case 212:
        
        case 213:
        
        case 214:
        
        case 215:
        
        case 216:
        
        case 217:
        
        case 218:
        
        case 219:
        
        case 220:
        
        case 221:
        
        case 222:
        
        case 223:
        
        case 224:
        
        case 225:
        
        case 226:
        
        case 227:
        
        case 228:
        
        case 229:
        
        case 230:
        
        case 231:
        
        case 232:
        
        case 233:
        
        case 234:
        
        case 235:
        
        case 236:
        
        case 237:
        
        case 238:
        
        case 239:
        
        case 240:
        
        case 241:
        
        case 242:
        
        case 243:
        
        case 244:
        
        case 245:
        
        case 246:
        
        case 247:
        
        case 248:
        
        case 249:
        
        case 250:
        
        case 251:
        
        case 252:
        
        case 253:
        
        case 254:
        
        default:
          break;
      } 
      char c = '';
      int j = (paramInt2 & 0xFF) - c;
      if (j < 0)
        j += 256; 
      int k = ((paramInt2 & 0xFFFF) >>> 8) - c;
      if (k < 0)
        k += 256; 
      for (byte b = 0; b < arrayOfChar.length; b++) {
        int m = b % 2;
        if (m == 0) {
          arrayOfChar[b] = (char)(arrayOfChar[b] ^ j);
          j = ((j >>> 3 | j << 5) ^ arrayOfChar[b]) & 0xFF;
        } else {
          arrayOfChar[b] = (char)(arrayOfChar[b] ^ k);
          k = ((k >>> 3 | k << 5) ^ arrayOfChar[b]) & 0xFF;
        } 
      } 
      b[i] = (new String(arrayOfChar)).intern();
    } 
    return b[i];
  }
}


/* Location:              C:\Program Files\BurpSuitePro\burpsuite_pro.jar!\burp\Zxsb.class
 * Java compiler version: 21 (65.0)
 * JD-Core Version:       1.1.3
 */