package burp;

import java.math.BigInteger;

class Zxso extends ClassLoader {
  static Object ZF;
  
  static String ZH;
  
  private static final String[] a;
  
  private static final String[] b;
  
  static void ZT(Object paramObject) {
    Zsm3.Zl = a(-20084, 24473);
    Zsm3.ZC = new BigInteger(a(-20082, -7699));
    boolean bool = Zt2e.ZN();
    try {
      try {
        if (Zm__.Zf.charAt(Math.abs(((BigInteger)Ztbf.Zv).intValue() % 32)) <= Zxzd.ZM.charAt(Math.abs(((BigInteger)Zm__.Zz).intValue() % 32))) {
          try {
            Zr0u.ZU(Class.forName(a(-20068, -8093)));
            if (!bool)
              Zbo7.Zv(Class.forName(a(-20089, -8161))); 
          } catch (Throwable throwable) {
            throw a(null);
          } 
          return;
        } 
      } catch (Throwable throwable) {
        throw a(null);
      } 
      Zbo7.Zv(Class.forName(a(-20089, -8161)));
    } catch (Throwable throwable) {}
  }
  
  static boolean ZX(Object[] paramArrayOfObject, Object paramObject) throws Throwable {
    // Byte code:
    //   0: invokestatic ZK : ()Z
    //   3: istore_2
    //   4: new java/lang/StringBuilder
    //   7: dup
    //   8: invokespecial <init> : ()V
    //   11: astore_3
    //   12: iconst_0
    //   13: istore #4
    //   15: iload #4
    //   17: bipush #32
    //   19: if_icmpge -> 1355
    //   22: iload #4
    //   24: tableswitch default -> 1348, 0 -> 168, 1 -> 205, 2 -> 242, 3 -> 279, 4 -> 316, 5 -> 353, 6 -> 390, 7 -> 427, 8 -> 464, 9 -> 501, 10 -> 538, 11 -> 575, 12 -> 612, 13 -> 649, 14 -> 686, 15 -> 723, 16 -> 760, 17 -> 797, 18 -> 834, 19 -> 871, 20 -> 908, 21 -> 945, 22 -> 982, 23 -> 1019, 24 -> 1056, 25 -> 1093, 26 -> 1130, 27 -> 1167, 28 -> 1204, 29 -> 1241, 30 -> 1278, 31 -> 1315
    //   168: aload_3
    //   169: getstatic burp/Ztuj.Zk : Ljava/lang/String;
    //   172: getstatic burp/Zxzd.ZD : Ljava/lang/Object;
    //   175: checkcast java/math/BigInteger
    //   178: invokevirtual intValue : ()I
    //   181: bipush #32
    //   183: irem
    //   184: invokestatic abs : (I)I
    //   187: invokevirtual charAt : (I)C
    //   190: invokevirtual append : (C)Ljava/lang/StringBuilder;
    //   193: pop
    //   194: iload_2
    //   195: ifeq -> 1348
    //   198: goto -> 205
    //   201: invokestatic a : (Ljava/lang/Throwable;)Ljava/lang/Throwable;
    //   204: athrow
    //   205: aload_3
    //   206: getstatic burp/Zx4l.Zy : Ljava/lang/String;
    //   209: getstatic burp/Zrdy.Zt : Ljava/lang/Object;
    //   212: checkcast java/math/BigInteger
    //   215: invokevirtual intValue : ()I
    //   218: bipush #32
    //   220: irem
    //   221: invokestatic abs : (I)I
    //   224: invokevirtual charAt : (I)C
    //   227: invokevirtual append : (C)Ljava/lang/StringBuilder;
    //   230: pop
    //   231: iload_2
    //   232: ifeq -> 1348
    //   235: goto -> 242
    //   238: invokestatic a : (Ljava/lang/Throwable;)Ljava/lang/Throwable;
    //   241: athrow
    //   242: aload_3
    //   243: getstatic burp/Zt4g.Zj : Ljava/lang/String;
    //   246: getstatic burp/Zxo6.Zw : Ljava/lang/Object;
    //   249: checkcast java/math/BigInteger
    //   252: invokevirtual intValue : ()I
    //   255: bipush #32
    //   257: irem
    //   258: invokestatic abs : (I)I
    //   261: invokevirtual charAt : (I)C
    //   264: invokevirtual append : (C)Ljava/lang/StringBuilder;
    //   267: pop
    //   268: iload_2
    //   269: ifeq -> 1348
    //   272: goto -> 279
    //   275: invokestatic a : (Ljava/lang/Throwable;)Ljava/lang/Throwable;
    //   278: athrow
    //   279: aload_3
    //   280: getstatic burp/Zzip.Za : Ljava/lang/String;
    //   283: getstatic burp/Zzai.Z_ : Ljava/lang/Object;
    //   286: checkcast java/math/BigInteger
    //   289: invokevirtual intValue : ()I
    //   292: bipush #32
    //   294: irem
    //   295: invokestatic abs : (I)I
    //   298: invokevirtual charAt : (I)C
    //   301: invokevirtual append : (C)Ljava/lang/StringBuilder;
    //   304: pop
    //   305: iload_2
    //   306: ifeq -> 1348
    //   309: goto -> 316
    //   312: invokestatic a : (Ljava/lang/Throwable;)Ljava/lang/Throwable;
    //   315: athrow
    //   316: aload_3
    //   317: getstatic burp/Zlos.Zp : Ljava/lang/String;
    //   320: getstatic burp/Zod.ZP : Ljava/lang/Object;
    //   323: checkcast java/math/BigInteger
    //   326: invokevirtual intValue : ()I
    //   329: bipush #32
    //   331: irem
    //   332: invokestatic abs : (I)I
    //   335: invokevirtual charAt : (I)C
    //   338: invokevirtual append : (C)Ljava/lang/StringBuilder;
    //   341: pop
    //   342: iload_2
    //   343: ifeq -> 1348
    //   346: goto -> 353
    //   349: invokestatic a : (Ljava/lang/Throwable;)Ljava/lang/Throwable;
    //   352: athrow
    //   353: aload_3
    //   354: getstatic burp/Zeh9.ZF : Ljava/lang/String;
    //   357: getstatic burp/Zzai.Z_ : Ljava/lang/Object;
    //   360: checkcast java/math/BigInteger
    //   363: invokevirtual intValue : ()I
    //   366: bipush #32
    //   368: irem
    //   369: invokestatic abs : (I)I
    //   372: invokevirtual charAt : (I)C
    //   375: invokevirtual append : (C)Ljava/lang/StringBuilder;
    //   378: pop
    //   379: iload_2
    //   380: ifeq -> 1348
    //   383: goto -> 390
    //   386: invokestatic a : (Ljava/lang/Throwable;)Ljava/lang/Throwable;
    //   389: athrow
    //   390: aload_3
    //   391: getstatic burp/Zer.Zp : Ljava/lang/String;
    //   394: getstatic burp/Zk9s.ZY : Ljava/lang/Object;
    //   397: checkcast java/math/BigInteger
    //   400: invokevirtual intValue : ()I
    //   403: bipush #32
    //   405: irem
    //   406: invokestatic abs : (I)I
    //   409: invokevirtual charAt : (I)C
    //   412: invokevirtual append : (C)Ljava/lang/StringBuilder;
    //   415: pop
    //   416: iload_2
    //   417: ifeq -> 1348
    //   420: goto -> 427
    //   423: invokestatic a : (Ljava/lang/Throwable;)Ljava/lang/Throwable;
    //   426: athrow
    //   427: aload_3
    //   428: getstatic burp/Zk8b.ZT : Ljava/lang/String;
    //   431: getstatic burp/Zl2g.ZG : Ljava/lang/Object;
    //   434: checkcast java/math/BigInteger
    //   437: invokevirtual intValue : ()I
    //   440: bipush #32
    //   442: irem
    //   443: invokestatic abs : (I)I
    //   446: invokevirtual charAt : (I)C
    //   449: invokevirtual append : (C)Ljava/lang/StringBuilder;
    //   452: pop
    //   453: iload_2
    //   454: ifeq -> 1348
    //   457: goto -> 464
    //   460: invokestatic a : (Ljava/lang/Throwable;)Ljava/lang/Throwable;
    //   463: athrow
    //   464: aload_3
    //   465: getstatic burp/Zsby.Zx : Ljava/lang/String;
    //   468: getstatic burp/Zlhm.ZT : Ljava/lang/Object;
    //   471: checkcast java/math/BigInteger
    //   474: invokevirtual intValue : ()I
    //   477: bipush #32
    //   479: irem
    //   480: invokestatic abs : (I)I
    //   483: invokevirtual charAt : (I)C
    //   486: invokevirtual append : (C)Ljava/lang/StringBuilder;
    //   489: pop
    //   490: iload_2
    //   491: ifeq -> 1348
    //   494: goto -> 501
    //   497: invokestatic a : (Ljava/lang/Throwable;)Ljava/lang/Throwable;
    //   500: athrow
    //   501: aload_3
    //   502: getstatic burp/Zr0g.Zf : Ljava/lang/String;
    //   505: getstatic burp/Zx54.Zn : Ljava/lang/Object;
    //   508: checkcast java/math/BigInteger
    //   511: invokevirtual intValue : ()I
    //   514: bipush #32
    //   516: irem
    //   517: invokestatic abs : (I)I
    //   520: invokevirtual charAt : (I)C
    //   523: invokevirtual append : (C)Ljava/lang/StringBuilder;
    //   526: pop
    //   527: iload_2
    //   528: ifeq -> 1348
    //   531: goto -> 538
    //   534: invokestatic a : (Ljava/lang/Throwable;)Ljava/lang/Throwable;
    //   537: athrow
    //   538: aload_3
    //   539: getstatic burp/Zm__.Zf : Ljava/lang/String;
    //   542: getstatic burp/Zgss.Zl : Ljava/lang/Object;
    //   545: checkcast java/math/BigInteger
    //   548: invokevirtual intValue : ()I
    //   551: bipush #32
    //   553: irem
    //   554: invokestatic abs : (I)I
    //   557: invokevirtual charAt : (I)C
    //   560: invokevirtual append : (C)Ljava/lang/StringBuilder;
    //   563: pop
    //   564: iload_2
    //   565: ifeq -> 1348
    //   568: goto -> 575
    //   571: invokestatic a : (Ljava/lang/Throwable;)Ljava/lang/Throwable;
    //   574: athrow
    //   575: aload_3
    //   576: getstatic burp/Zllw.Zg : Ljava/lang/String;
    //   579: getstatic burp/Zk8b.ZK : Ljava/lang/Object;
    //   582: checkcast java/math/BigInteger
    //   585: invokevirtual intValue : ()I
    //   588: bipush #32
    //   590: irem
    //   591: invokestatic abs : (I)I
    //   594: invokevirtual charAt : (I)C
    //   597: invokevirtual append : (C)Ljava/lang/StringBuilder;
    //   600: pop
    //   601: iload_2
    //   602: ifeq -> 1348
    //   605: goto -> 612
    //   608: invokestatic a : (Ljava/lang/Throwable;)Ljava/lang/Throwable;
    //   611: athrow
    //   612: aload_3
    //   613: getstatic burp/Zsm3.Zl : Ljava/lang/String;
    //   616: getstatic burp/Ztnw.Zt : Ljava/lang/Object;
    //   619: checkcast java/math/BigInteger
    //   622: invokevirtual intValue : ()I
    //   625: bipush #32
    //   627: irem
    //   628: invokestatic abs : (I)I
    //   631: invokevirtual charAt : (I)C
    //   634: invokevirtual append : (C)Ljava/lang/StringBuilder;
    //   637: pop
    //   638: iload_2
    //   639: ifeq -> 1348
    //   642: goto -> 649
    //   645: invokestatic a : (Ljava/lang/Throwable;)Ljava/lang/Throwable;
    //   648: athrow
    //   649: aload_3
    //   650: getstatic burp/Ze3j.ZI : Ljava/lang/String;
    //   653: getstatic burp/Zl2q.Zg : Ljava/lang/Object;
    //   656: checkcast java/math/BigInteger
    //   659: invokevirtual intValue : ()I
    //   662: bipush #32
    //   664: irem
    //   665: invokestatic abs : (I)I
    //   668: invokevirtual charAt : (I)C
    //   671: invokevirtual append : (C)Ljava/lang/StringBuilder;
    //   674: pop
    //   675: iload_2
    //   676: ifeq -> 1348
    //   679: goto -> 686
    //   682: invokestatic a : (Ljava/lang/Throwable;)Ljava/lang/Throwable;
    //   685: athrow
    //   686: aload_3
    //   687: getstatic burp/Zg0j.Ze : Ljava/lang/String;
    //   690: getstatic burp/Zzsq.Zh : Ljava/lang/Object;
    //   693: checkcast java/math/BigInteger
    //   696: invokevirtual intValue : ()I
    //   699: bipush #32
    //   701: irem
    //   702: invokestatic abs : (I)I
    //   705: invokevirtual charAt : (I)C
    //   708: invokevirtual append : (C)Ljava/lang/StringBuilder;
    //   711: pop
    //   712: iload_2
    //   713: ifeq -> 1348
    //   716: goto -> 723
    //   719: invokestatic a : (Ljava/lang/Throwable;)Ljava/lang/Throwable;
    //   722: athrow
    //   723: aload_3
    //   724: getstatic burp/Zg0j.Ze : Ljava/lang/String;
    //   727: getstatic burp/Zkyc.ZD : Ljava/lang/Object;
    //   730: checkcast java/math/BigInteger
    //   733: invokevirtual intValue : ()I
    //   736: bipush #32
    //   738: irem
    //   739: invokestatic abs : (I)I
    //   742: invokevirtual charAt : (I)C
    //   745: invokevirtual append : (C)Ljava/lang/StringBuilder;
    //   748: pop
    //   749: iload_2
    //   750: ifeq -> 1348
    //   753: goto -> 760
    //   756: invokestatic a : (Ljava/lang/Throwable;)Ljava/lang/Throwable;
    //   759: athrow
    //   760: aload_3
    //   761: getstatic burp/Zlv6.Zt : Ljava/lang/String;
    //   764: getstatic burp/Zer.Zk : Ljava/lang/Object;
    //   767: checkcast java/math/BigInteger
    //   770: invokevirtual intValue : ()I
    //   773: bipush #32
    //   775: irem
    //   776: invokestatic abs : (I)I
    //   779: invokevirtual charAt : (I)C
    //   782: invokevirtual append : (C)Ljava/lang/StringBuilder;
    //   785: pop
    //   786: iload_2
    //   787: ifeq -> 1348
    //   790: goto -> 797
    //   793: invokestatic a : (Ljava/lang/Throwable;)Ljava/lang/Throwable;
    //   796: athrow
    //   797: aload_3
    //   798: getstatic burp/Zsde.Zi : Ljava/lang/String;
    //   801: getstatic burp/Zzai.Z_ : Ljava/lang/Object;
    //   804: checkcast java/math/BigInteger
    //   807: invokevirtual intValue : ()I
    //   810: bipush #32
    //   812: irem
    //   813: invokestatic abs : (I)I
    //   816: invokevirtual charAt : (I)C
    //   819: invokevirtual append : (C)Ljava/lang/StringBuilder;
    //   822: pop
    //   823: iload_2
    //   824: ifeq -> 1348
    //   827: goto -> 834
    //   830: invokestatic a : (Ljava/lang/Throwable;)Ljava/lang/Throwable;
    //   833: athrow
    //   834: aload_3
    //   835: getstatic burp/Zrdy.ZO : Ljava/lang/String;
    //   838: getstatic burp/Zg_p.Zx : Ljava/lang/Object;
    //   841: checkcast java/math/BigInteger
    //   844: invokevirtual intValue : ()I
    //   847: bipush #32
    //   849: irem
    //   850: invokestatic abs : (I)I
    //   853: invokevirtual charAt : (I)C
    //   856: invokevirtual append : (C)Ljava/lang/StringBuilder;
    //   859: pop
    //   860: iload_2
    //   861: ifeq -> 1348
    //   864: goto -> 871
    //   867: invokestatic a : (Ljava/lang/Throwable;)Ljava/lang/Throwable;
    //   870: athrow
    //   871: aload_3
    //   872: getstatic burp/Zzsq.Zc : Ljava/lang/String;
    //   875: getstatic burp/Zz1k.ZP : Ljava/lang/Object;
    //   878: checkcast java/math/BigInteger
    //   881: invokevirtual intValue : ()I
    //   884: bipush #32
    //   886: irem
    //   887: invokestatic abs : (I)I
    //   890: invokevirtual charAt : (I)C
    //   893: invokevirtual append : (C)Ljava/lang/StringBuilder;
    //   896: pop
    //   897: iload_2
    //   898: ifeq -> 1348
    //   901: goto -> 908
    //   904: invokestatic a : (Ljava/lang/Throwable;)Ljava/lang/Throwable;
    //   907: athrow
    //   908: aload_3
    //   909: getstatic burp/Zd1.ZN : Ljava/lang/String;
    //   912: getstatic burp/Zg7p.Zb : Ljava/lang/Object;
    //   915: checkcast java/math/BigInteger
    //   918: invokevirtual intValue : ()I
    //   921: bipush #32
    //   923: irem
    //   924: invokestatic abs : (I)I
    //   927: invokevirtual charAt : (I)C
    //   930: invokevirtual append : (C)Ljava/lang/StringBuilder;
    //   933: pop
    //   934: iload_2
    //   935: ifeq -> 1348
    //   938: goto -> 945
    //   941: invokestatic a : (Ljava/lang/Throwable;)Ljava/lang/Throwable;
    //   944: athrow
    //   945: aload_3
    //   946: getstatic burp/Zgmt.Zu : Ljava/lang/String;
    //   949: getstatic burp/Zk8b.ZK : Ljava/lang/Object;
    //   952: checkcast java/math/BigInteger
    //   955: invokevirtual intValue : ()I
    //   958: bipush #32
    //   960: irem
    //   961: invokestatic abs : (I)I
    //   964: invokevirtual charAt : (I)C
    //   967: invokevirtual append : (C)Ljava/lang/StringBuilder;
    //   970: pop
    //   971: iload_2
    //   972: ifeq -> 1348
    //   975: goto -> 982
    //   978: invokestatic a : (Ljava/lang/Throwable;)Ljava/lang/Throwable;
    //   981: athrow
    //   982: aload_3
    //   983: getstatic burp/Zter.ZE : Ljava/lang/String;
    //   986: getstatic burp/Zbsr.ZD : Ljava/lang/Object;
    //   989: checkcast java/math/BigInteger
    //   992: invokevirtual intValue : ()I
    //   995: bipush #32
    //   997: irem
    //   998: invokestatic abs : (I)I
    //   1001: invokevirtual charAt : (I)C
    //   1004: invokevirtual append : (C)Ljava/lang/StringBuilder;
    //   1007: pop
    //   1008: iload_2
    //   1009: ifeq -> 1348
    //   1012: goto -> 1019
    //   1015: invokestatic a : (Ljava/lang/Throwable;)Ljava/lang/Throwable;
    //   1018: athrow
    //   1019: aload_3
    //   1020: getstatic burp/Zg_p.ZO : Ljava/lang/String;
    //   1023: getstatic burp/Zzip.ZW : Ljava/lang/Object;
    //   1026: checkcast java/math/BigInteger
    //   1029: invokevirtual intValue : ()I
    //   1032: bipush #32
    //   1034: irem
    //   1035: invokestatic abs : (I)I
    //   1038: invokevirtual charAt : (I)C
    //   1041: invokevirtual append : (C)Ljava/lang/StringBuilder;
    //   1044: pop
    //   1045: iload_2
    //   1046: ifeq -> 1348
    //   1049: goto -> 1056
    //   1052: invokestatic a : (Ljava/lang/Throwable;)Ljava/lang/Throwable;
    //   1055: athrow
    //   1056: aload_3
    //   1057: getstatic burp/Zkbm.Zb : Ljava/lang/String;
    //   1060: getstatic burp/Zxo6.Zw : Ljava/lang/Object;
    //   1063: checkcast java/math/BigInteger
    //   1066: invokevirtual intValue : ()I
    //   1069: bipush #32
    //   1071: irem
    //   1072: invokestatic abs : (I)I
    //   1075: invokevirtual charAt : (I)C
    //   1078: invokevirtual append : (C)Ljava/lang/StringBuilder;
    //   1081: pop
    //   1082: iload_2
    //   1083: ifeq -> 1348
    //   1086: goto -> 1093
    //   1089: invokestatic a : (Ljava/lang/Throwable;)Ljava/lang/Throwable;
    //   1092: athrow
    //   1093: aload_3
    //   1094: getstatic burp/Zr0g.Zf : Ljava/lang/String;
    //   1097: getstatic burp/Zlos.Zk : Ljava/lang/Object;
    //   1100: checkcast java/math/BigInteger
    //   1103: invokevirtual intValue : ()I
    //   1106: bipush #32
    //   1108: irem
    //   1109: invokestatic abs : (I)I
    //   1112: invokevirtual charAt : (I)C
    //   1115: invokevirtual append : (C)Ljava/lang/StringBuilder;
    //   1118: pop
    //   1119: iload_2
    //   1120: ifeq -> 1348
    //   1123: goto -> 1130
    //   1126: invokestatic a : (Ljava/lang/Throwable;)Ljava/lang/Throwable;
    //   1129: athrow
    //   1130: aload_3
    //   1131: getstatic burp/Zzap.ZA : Ljava/lang/String;
    //   1134: getstatic burp/Zllw.ZW : Ljava/lang/Object;
    //   1137: checkcast java/math/BigInteger
    //   1140: invokevirtual intValue : ()I
    //   1143: bipush #32
    //   1145: irem
    //   1146: invokestatic abs : (I)I
    //   1149: invokevirtual charAt : (I)C
    //   1152: invokevirtual append : (C)Ljava/lang/StringBuilder;
    //   1155: pop
    //   1156: iload_2
    //   1157: ifeq -> 1348
    //   1160: goto -> 1167
    //   1163: invokestatic a : (Ljava/lang/Throwable;)Ljava/lang/Throwable;
    //   1166: athrow
    //   1167: aload_3
    //   1168: getstatic burp/Zzai.Zy : Ljava/lang/String;
    //   1171: getstatic burp/Zsby.ZZ : Ljava/lang/Object;
    //   1174: checkcast java/math/BigInteger
    //   1177: invokevirtual intValue : ()I
    //   1180: bipush #32
    //   1182: irem
    //   1183: invokestatic abs : (I)I
    //   1186: invokevirtual charAt : (I)C
    //   1189: invokevirtual append : (C)Ljava/lang/StringBuilder;
    //   1192: pop
    //   1193: iload_2
    //   1194: ifeq -> 1348
    //   1197: goto -> 1204
    //   1200: invokestatic a : (Ljava/lang/Throwable;)Ljava/lang/Throwable;
    //   1203: athrow
    //   1204: aload_3
    //   1205: getstatic burp/Zod.ZS : Ljava/lang/String;
    //   1208: getstatic burp/Zllw.ZW : Ljava/lang/Object;
    //   1211: checkcast java/math/BigInteger
    //   1214: invokevirtual intValue : ()I
    //   1217: bipush #32
    //   1219: irem
    //   1220: invokestatic abs : (I)I
    //   1223: invokevirtual charAt : (I)C
    //   1226: invokevirtual append : (C)Ljava/lang/StringBuilder;
    //   1229: pop
    //   1230: iload_2
    //   1231: ifeq -> 1348
    //   1234: goto -> 1241
    //   1237: invokestatic a : (Ljava/lang/Throwable;)Ljava/lang/Throwable;
    //   1240: athrow
    //   1241: aload_3
    //   1242: getstatic burp/Zk9s.ZM : Ljava/lang/String;
    //   1245: getstatic burp/Zsgl.Zn : Ljava/lang/Object;
    //   1248: checkcast java/math/BigInteger
    //   1251: invokevirtual intValue : ()I
    //   1254: bipush #32
    //   1256: irem
    //   1257: invokestatic abs : (I)I
    //   1260: invokevirtual charAt : (I)C
    //   1263: invokevirtual append : (C)Ljava/lang/StringBuilder;
    //   1266: pop
    //   1267: iload_2
    //   1268: ifeq -> 1348
    //   1271: goto -> 1278
    //   1274: invokestatic a : (Ljava/lang/Throwable;)Ljava/lang/Throwable;
    //   1277: athrow
    //   1278: aload_3
    //   1279: getstatic burp/Zsby.Zx : Ljava/lang/String;
    //   1282: getstatic burp/Ztbf.Zv : Ljava/lang/Object;
    //   1285: checkcast java/math/BigInteger
    //   1288: invokevirtual intValue : ()I
    //   1291: bipush #32
    //   1293: irem
    //   1294: invokestatic abs : (I)I
    //   1297: invokevirtual charAt : (I)C
    //   1300: invokevirtual append : (C)Ljava/lang/StringBuilder;
    //   1303: pop
    //   1304: iload_2
    //   1305: ifeq -> 1348
    //   1308: goto -> 1315
    //   1311: invokestatic a : (Ljava/lang/Throwable;)Ljava/lang/Throwable;
    //   1314: athrow
    //   1315: aload_3
    //   1316: getstatic burp/Zsxj.Zp : Ljava/lang/String;
    //   1319: getstatic burp/Zk8b.ZK : Ljava/lang/Object;
    //   1322: checkcast java/math/BigInteger
    //   1325: invokevirtual intValue : ()I
    //   1328: bipush #32
    //   1330: irem
    //   1331: invokestatic abs : (I)I
    //   1334: invokevirtual charAt : (I)C
    //   1337: invokevirtual append : (C)Ljava/lang/StringBuilder;
    //   1340: pop
    //   1341: goto -> 1348
    //   1344: invokestatic a : (Ljava/lang/Throwable;)Ljava/lang/Throwable;
    //   1347: athrow
    //   1348: iinc #4, 1
    //   1351: iload_2
    //   1352: ifeq -> 15
    //   1355: aload_3
    //   1356: invokevirtual toString : ()Ljava/lang/String;
    //   1359: putstatic burp/Zzk9.Zb : Ljava/lang/String;
    //   1362: new java/lang/StringBuilder
    //   1365: dup
    //   1366: invokespecial <init> : ()V
    //   1369: astore #4
    //   1371: iconst_0
    //   1372: istore #5
    //   1374: iload #5
    //   1376: bipush #32
    //   1378: if_icmpge -> 2743
    //   1381: iload #5
    //   1383: tableswitch default -> 2736, 0 -> 1524, 1 -> 1562, 2 -> 1600, 3 -> 1638, 4 -> 1676, 5 -> 1714, 6 -> 1752, 7 -> 1790, 8 -> 1828, 9 -> 1866, 10 -> 1904, 11 -> 1942, 12 -> 1980, 13 -> 2018, 14 -> 2056, 15 -> 2094, 16 -> 2132, 17 -> 2170, 18 -> 2208, 19 -> 2246, 20 -> 2284, 21 -> 2322, 22 -> 2360, 23 -> 2398, 24 -> 2436, 25 -> 2474, 26 -> 2512, 27 -> 2550, 28 -> 2588, 29 -> 2626, 30 -> 2664, 31 -> 2702
    //   1524: aload #4
    //   1526: getstatic burp/Ze7q.ZW : Ljava/lang/String;
    //   1529: getstatic burp/Zl_k.ZH : Ljava/lang/Object;
    //   1532: checkcast java/math/BigInteger
    //   1535: invokevirtual intValue : ()I
    //   1538: bipush #32
    //   1540: irem
    //   1541: invokestatic abs : (I)I
    //   1544: invokevirtual charAt : (I)C
    //   1547: invokevirtual append : (C)Ljava/lang/StringBuilder;
    //   1550: pop
    //   1551: iload_2
    //   1552: ifeq -> 2736
    //   1555: goto -> 1562
    //   1558: invokestatic a : (Ljava/lang/Throwable;)Ljava/lang/Throwable;
    //   1561: athrow
    //   1562: aload #4
    //   1564: getstatic burp/Zm0s.Zm : Ljava/lang/String;
    //   1567: getstatic burp/Zxk9.ZI : Ljava/lang/Object;
    //   1570: checkcast java/math/BigInteger
    //   1573: invokevirtual intValue : ()I
    //   1576: bipush #32
    //   1578: irem
    //   1579: invokestatic abs : (I)I
    //   1582: invokevirtual charAt : (I)C
    //   1585: invokevirtual append : (C)Ljava/lang/StringBuilder;
    //   1588: pop
    //   1589: iload_2
    //   1590: ifeq -> 2736
    //   1593: goto -> 1600
    //   1596: invokestatic a : (Ljava/lang/Throwable;)Ljava/lang/Throwable;
    //   1599: athrow
    //   1600: aload #4
    //   1602: getstatic burp/Zkbf.Zv : Ljava/lang/String;
    //   1605: getstatic burp/Zx54.Zn : Ljava/lang/Object;
    //   1608: checkcast java/math/BigInteger
    //   1611: invokevirtual intValue : ()I
    //   1614: bipush #32
    //   1616: irem
    //   1617: invokestatic abs : (I)I
    //   1620: invokevirtual charAt : (I)C
    //   1623: invokevirtual append : (C)Ljava/lang/StringBuilder;
    //   1626: pop
    //   1627: iload_2
    //   1628: ifeq -> 2736
    //   1631: goto -> 1638
    //   1634: invokestatic a : (Ljava/lang/Throwable;)Ljava/lang/Throwable;
    //   1637: athrow
    //   1638: aload #4
    //   1640: getstatic burp/Zsxj.Zp : Ljava/lang/String;
    //   1643: getstatic burp/Zlos.Zk : Ljava/lang/Object;
    //   1646: checkcast java/math/BigInteger
    //   1649: invokevirtual intValue : ()I
    //   1652: bipush #32
    //   1654: irem
    //   1655: invokestatic abs : (I)I
    //   1658: invokevirtual charAt : (I)C
    //   1661: invokevirtual append : (C)Ljava/lang/StringBuilder;
    //   1664: pop
    //   1665: iload_2
    //   1666: ifeq -> 2736
    //   1669: goto -> 1676
    //   1672: invokestatic a : (Ljava/lang/Throwable;)Ljava/lang/Throwable;
    //   1675: athrow
    //   1676: aload #4
    //   1678: getstatic burp/Zt3l.Zi : Ljava/lang/String;
    //   1681: getstatic burp/Zgw0.ZM : Ljava/lang/Object;
    //   1684: checkcast java/math/BigInteger
    //   1687: invokevirtual intValue : ()I
    //   1690: bipush #32
    //   1692: irem
    //   1693: invokestatic abs : (I)I
    //   1696: invokevirtual charAt : (I)C
    //   1699: invokevirtual append : (C)Ljava/lang/StringBuilder;
    //   1702: pop
    //   1703: iload_2
    //   1704: ifeq -> 2736
    //   1707: goto -> 1714
    //   1710: invokestatic a : (Ljava/lang/Throwable;)Ljava/lang/Throwable;
    //   1713: athrow
    //   1714: aload #4
    //   1716: getstatic burp/Zod.ZS : Ljava/lang/String;
    //   1719: getstatic burp/Zsxm.Zv : Ljava/lang/Object;
    //   1722: checkcast java/math/BigInteger
    //   1725: invokevirtual intValue : ()I
    //   1728: bipush #32
    //   1730: irem
    //   1731: invokestatic abs : (I)I
    //   1734: invokevirtual charAt : (I)C
    //   1737: invokevirtual append : (C)Ljava/lang/StringBuilder;
    //   1740: pop
    //   1741: iload_2
    //   1742: ifeq -> 2736
    //   1745: goto -> 1752
    //   1748: invokestatic a : (Ljava/lang/Throwable;)Ljava/lang/Throwable;
    //   1751: athrow
    //   1752: aload #4
    //   1754: getstatic burp/Zkfz.Zs : Ljava/lang/String;
    //   1757: getstatic burp/Zkmx.Zu : Ljava/lang/Object;
    //   1760: checkcast java/math/BigInteger
    //   1763: invokevirtual intValue : ()I
    //   1766: bipush #32
    //   1768: irem
    //   1769: invokestatic abs : (I)I
    //   1772: invokevirtual charAt : (I)C
    //   1775: invokevirtual append : (C)Ljava/lang/StringBuilder;
    //   1778: pop
    //   1779: iload_2
    //   1780: ifeq -> 2736
    //   1783: goto -> 1790
    //   1786: invokestatic a : (Ljava/lang/Throwable;)Ljava/lang/Throwable;
    //   1789: athrow
    //   1790: aload #4
    //   1792: getstatic burp/Zl88.Zd : Ljava/lang/String;
    //   1795: getstatic burp/Ze7q.Zk : Ljava/lang/Object;
    //   1798: checkcast java/math/BigInteger
    //   1801: invokevirtual intValue : ()I
    //   1804: bipush #32
    //   1806: irem
    //   1807: invokestatic abs : (I)I
    //   1810: invokevirtual charAt : (I)C
    //   1813: invokevirtual append : (C)Ljava/lang/StringBuilder;
    //   1816: pop
    //   1817: iload_2
    //   1818: ifeq -> 2736
    //   1821: goto -> 1828
    //   1824: invokestatic a : (Ljava/lang/Throwable;)Ljava/lang/Throwable;
    //   1827: athrow
    //   1828: aload #4
    //   1830: getstatic burp/Zsde.Zi : Ljava/lang/String;
    //   1833: getstatic burp/Zod.ZP : Ljava/lang/Object;
    //   1836: checkcast java/math/BigInteger
    //   1839: invokevirtual intValue : ()I
    //   1842: bipush #32
    //   1844: irem
    //   1845: invokestatic abs : (I)I
    //   1848: invokevirtual charAt : (I)C
    //   1851: invokevirtual append : (C)Ljava/lang/StringBuilder;
    //   1854: pop
    //   1855: iload_2
    //   1856: ifeq -> 2736
    //   1859: goto -> 1866
    //   1862: invokestatic a : (Ljava/lang/Throwable;)Ljava/lang/Throwable;
    //   1865: athrow
    //   1866: aload #4
    //   1868: getstatic burp/Zkfz.Zs : Ljava/lang/String;
    //   1871: getstatic burp/Zbo7.Zl : Ljava/lang/Object;
    //   1874: checkcast java/math/BigInteger
    //   1877: invokevirtual intValue : ()I
    //   1880: bipush #32
    //   1882: irem
    //   1883: invokestatic abs : (I)I
    //   1886: invokevirtual charAt : (I)C
    //   1889: invokevirtual append : (C)Ljava/lang/StringBuilder;
    //   1892: pop
    //   1893: iload_2
    //   1894: ifeq -> 2736
    //   1897: goto -> 1904
    //   1900: invokestatic a : (Ljava/lang/Throwable;)Ljava/lang/Throwable;
    //   1903: athrow
    //   1904: aload #4
    //   1906: getstatic burp/Zl_u.Zc : Ljava/lang/String;
    //   1909: getstatic burp/Zg7z.ZV : Ljava/lang/Object;
    //   1912: checkcast java/math/BigInteger
    //   1915: invokevirtual intValue : ()I
    //   1918: bipush #32
    //   1920: irem
    //   1921: invokestatic abs : (I)I
    //   1924: invokevirtual charAt : (I)C
    //   1927: invokevirtual append : (C)Ljava/lang/StringBuilder;
    //   1930: pop
    //   1931: iload_2
    //   1932: ifeq -> 2736
    //   1935: goto -> 1942
    //   1938: invokestatic a : (Ljava/lang/Throwable;)Ljava/lang/Throwable;
    //   1941: athrow
    //   1942: aload #4
    //   1944: getstatic burp/Zm__.Zf : Ljava/lang/String;
    //   1947: getstatic burp/Zl2g.ZG : Ljava/lang/Object;
    //   1950: checkcast java/math/BigInteger
    //   1953: invokevirtual intValue : ()I
    //   1956: bipush #32
    //   1958: irem
    //   1959: invokestatic abs : (I)I
    //   1962: invokevirtual charAt : (I)C
    //   1965: invokevirtual append : (C)Ljava/lang/StringBuilder;
    //   1968: pop
    //   1969: iload_2
    //   1970: ifeq -> 2736
    //   1973: goto -> 1980
    //   1976: invokestatic a : (Ljava/lang/Throwable;)Ljava/lang/Throwable;
    //   1979: athrow
    //   1980: aload #4
    //   1982: getstatic burp/Zkfz.Zs : Ljava/lang/String;
    //   1985: getstatic burp/Zg99.ZZ : Ljava/lang/Object;
    //   1988: checkcast java/math/BigInteger
    //   1991: invokevirtual intValue : ()I
    //   1994: bipush #32
    //   1996: irem
    //   1997: invokestatic abs : (I)I
    //   2000: invokevirtual charAt : (I)C
    //   2003: invokevirtual append : (C)Ljava/lang/StringBuilder;
    //   2006: pop
    //   2007: iload_2
    //   2008: ifeq -> 2736
    //   2011: goto -> 2018
    //   2014: invokestatic a : (Ljava/lang/Throwable;)Ljava/lang/Throwable;
    //   2017: athrow
    //   2018: aload #4
    //   2020: getstatic burp/Zl2q.ZI : Ljava/lang/String;
    //   2023: getstatic burp/Zsxm.Zv : Ljava/lang/Object;
    //   2026: checkcast java/math/BigInteger
    //   2029: invokevirtual intValue : ()I
    //   2032: bipush #32
    //   2034: irem
    //   2035: invokestatic abs : (I)I
    //   2038: invokevirtual charAt : (I)C
    //   2041: invokevirtual append : (C)Ljava/lang/StringBuilder;
    //   2044: pop
    //   2045: iload_2
    //   2046: ifeq -> 2736
    //   2049: goto -> 2056
    //   2052: invokestatic a : (Ljava/lang/Throwable;)Ljava/lang/Throwable;
    //   2055: athrow
    //   2056: aload #4
    //   2058: getstatic burp/Zg0j.Ze : Ljava/lang/String;
    //   2061: getstatic burp/Ze13.ZD : Ljava/lang/Object;
    //   2064: checkcast java/math/BigInteger
    //   2067: invokevirtual intValue : ()I
    //   2070: bipush #32
    //   2072: irem
    //   2073: invokestatic abs : (I)I
    //   2076: invokevirtual charAt : (I)C
    //   2079: invokevirtual append : (C)Ljava/lang/StringBuilder;
    //   2082: pop
    //   2083: iload_2
    //   2084: ifeq -> 2736
    //   2087: goto -> 2094
    //   2090: invokestatic a : (Ljava/lang/Throwable;)Ljava/lang/Throwable;
    //   2093: athrow
    //   2094: aload #4
    //   2096: getstatic burp/Zxfu.Zo : Ljava/lang/String;
    //   2099: getstatic burp/Zzk9.ZK : Ljava/lang/Object;
    //   2102: checkcast java/math/BigInteger
    //   2105: invokevirtual intValue : ()I
    //   2108: bipush #32
    //   2110: irem
    //   2111: invokestatic abs : (I)I
    //   2114: invokevirtual charAt : (I)C
    //   2117: invokevirtual append : (C)Ljava/lang/StringBuilder;
    //   2120: pop
    //   2121: iload_2
    //   2122: ifeq -> 2736
    //   2125: goto -> 2132
    //   2128: invokestatic a : (Ljava/lang/Throwable;)Ljava/lang/Throwable;
    //   2131: athrow
    //   2132: aload #4
    //   2134: getstatic burp/Zgmt.Zu : Ljava/lang/String;
    //   2137: getstatic burp/Zehi.Zb : Ljava/lang/Object;
    //   2140: checkcast java/math/BigInteger
    //   2143: invokevirtual intValue : ()I
    //   2146: bipush #32
    //   2148: irem
    //   2149: invokestatic abs : (I)I
    //   2152: invokevirtual charAt : (I)C
    //   2155: invokevirtual append : (C)Ljava/lang/StringBuilder;
    //   2158: pop
    //   2159: iload_2
    //   2160: ifeq -> 2736
    //   2163: goto -> 2170
    //   2166: invokestatic a : (Ljava/lang/Throwable;)Ljava/lang/Throwable;
    //   2169: athrow
    //   2170: aload #4
    //   2172: getstatic burp/Zsde.Zi : Ljava/lang/String;
    //   2175: getstatic burp/Zb2s.Ze : Ljava/lang/Object;
    //   2178: checkcast java/math/BigInteger
    //   2181: invokevirtual intValue : ()I
    //   2184: bipush #32
    //   2186: irem
    //   2187: invokestatic abs : (I)I
    //   2190: invokevirtual charAt : (I)C
    //   2193: invokevirtual append : (C)Ljava/lang/StringBuilder;
    //   2196: pop
    //   2197: iload_2
    //   2198: ifeq -> 2736
    //   2201: goto -> 2208
    //   2204: invokestatic a : (Ljava/lang/Throwable;)Ljava/lang/Throwable;
    //   2207: athrow
    //   2208: aload #4
    //   2210: getstatic burp/Zxl5.Zq : Ljava/lang/String;
    //   2213: getstatic burp/Zr3q.Zn : Ljava/lang/Object;
    //   2216: checkcast java/math/BigInteger
    //   2219: invokevirtual intValue : ()I
    //   2222: bipush #32
    //   2224: irem
    //   2225: invokestatic abs : (I)I
    //   2228: invokevirtual charAt : (I)C
    //   2231: invokevirtual append : (C)Ljava/lang/StringBuilder;
    //   2234: pop
    //   2235: iload_2
    //   2236: ifeq -> 2736
    //   2239: goto -> 2246
    //   2242: invokestatic a : (Ljava/lang/Throwable;)Ljava/lang/Throwable;
    //   2245: athrow
    //   2246: aload #4
    //   2248: getstatic burp/Ztnw.Zr : Ljava/lang/String;
    //   2251: getstatic burp/Zk9s.ZY : Ljava/lang/Object;
    //   2254: checkcast java/math/BigInteger
    //   2257: invokevirtual intValue : ()I
    //   2260: bipush #32
    //   2262: irem
    //   2263: invokestatic abs : (I)I
    //   2266: invokevirtual charAt : (I)C
    //   2269: invokevirtual append : (C)Ljava/lang/StringBuilder;
    //   2272: pop
    //   2273: iload_2
    //   2274: ifeq -> 2736
    //   2277: goto -> 2284
    //   2280: invokestatic a : (Ljava/lang/Throwable;)Ljava/lang/Throwable;
    //   2283: athrow
    //   2284: aload #4
    //   2286: getstatic burp/Zt3l.Zi : Ljava/lang/String;
    //   2289: getstatic burp/Zbsr.ZD : Ljava/lang/Object;
    //   2292: checkcast java/math/BigInteger
    //   2295: invokevirtual intValue : ()I
    //   2298: bipush #32
    //   2300: irem
    //   2301: invokestatic abs : (I)I
    //   2304: invokevirtual charAt : (I)C
    //   2307: invokevirtual append : (C)Ljava/lang/StringBuilder;
    //   2310: pop
    //   2311: iload_2
    //   2312: ifeq -> 2736
    //   2315: goto -> 2322
    //   2318: invokestatic a : (Ljava/lang/Throwable;)Ljava/lang/Throwable;
    //   2321: athrow
    //   2322: aload #4
    //   2324: getstatic burp/Zkmx.Zg : Ljava/lang/String;
    //   2327: getstatic burp/Zlhm.ZT : Ljava/lang/Object;
    //   2330: checkcast java/math/BigInteger
    //   2333: invokevirtual intValue : ()I
    //   2336: bipush #32
    //   2338: irem
    //   2339: invokestatic abs : (I)I
    //   2342: invokevirtual charAt : (I)C
    //   2345: invokevirtual append : (C)Ljava/lang/StringBuilder;
    //   2348: pop
    //   2349: iload_2
    //   2350: ifeq -> 2736
    //   2353: goto -> 2360
    //   2356: invokestatic a : (Ljava/lang/Throwable;)Ljava/lang/Throwable;
    //   2359: athrow
    //   2360: aload #4
    //   2362: getstatic burp/Zgmt.Zu : Ljava/lang/String;
    //   2365: getstatic burp/Zr8h.ZH : Ljava/lang/Object;
    //   2368: checkcast java/math/BigInteger
    //   2371: invokevirtual intValue : ()I
    //   2374: bipush #32
    //   2376: irem
    //   2377: invokestatic abs : (I)I
    //   2380: invokevirtual charAt : (I)C
    //   2383: invokevirtual append : (C)Ljava/lang/StringBuilder;
    //   2386: pop
    //   2387: iload_2
    //   2388: ifeq -> 2736
    //   2391: goto -> 2398
    //   2394: invokestatic a : (Ljava/lang/Throwable;)Ljava/lang/Throwable;
    //   2397: athrow
    //   2398: aload #4
    //   2400: getstatic burp/Zlv6.Zt : Ljava/lang/String;
    //   2403: getstatic burp/Zt3l.Zq : Ljava/lang/Object;
    //   2406: checkcast java/math/BigInteger
    //   2409: invokevirtual intValue : ()I
    //   2412: bipush #32
    //   2414: irem
    //   2415: invokestatic abs : (I)I
    //   2418: invokevirtual charAt : (I)C
    //   2421: invokevirtual append : (C)Ljava/lang/StringBuilder;
    //   2424: pop
    //   2425: iload_2
    //   2426: ifeq -> 2736
    //   2429: goto -> 2436
    //   2432: invokestatic a : (Ljava/lang/Throwable;)Ljava/lang/Throwable;
    //   2435: athrow
    //   2436: aload #4
    //   2438: getstatic burp/Zxso.ZH : Ljava/lang/String;
    //   2441: getstatic burp/Zxfu.ZA : Ljava/lang/Object;
    //   2444: checkcast java/math/BigInteger
    //   2447: invokevirtual intValue : ()I
    //   2450: bipush #32
    //   2452: irem
    //   2453: invokestatic abs : (I)I
    //   2456: invokevirtual charAt : (I)C
    //   2459: invokevirtual append : (C)Ljava/lang/StringBuilder;
    //   2462: pop
    //   2463: iload_2
    //   2464: ifeq -> 2736
    //   2467: goto -> 2474
    //   2470: invokestatic a : (Ljava/lang/Throwable;)Ljava/lang/Throwable;
    //   2473: athrow
    //   2474: aload #4
    //   2476: getstatic burp/Zr0u.Z_ : Ljava/lang/String;
    //   2479: getstatic burp/Zm0s.Zl : Ljava/lang/Object;
    //   2482: checkcast java/math/BigInteger
    //   2485: invokevirtual intValue : ()I
    //   2488: bipush #32
    //   2490: irem
    //   2491: invokestatic abs : (I)I
    //   2494: invokevirtual charAt : (I)C
    //   2497: invokevirtual append : (C)Ljava/lang/StringBuilder;
    //   2500: pop
    //   2501: iload_2
    //   2502: ifeq -> 2736
    //   2505: goto -> 2512
    //   2508: invokestatic a : (Ljava/lang/Throwable;)Ljava/lang/Throwable;
    //   2511: athrow
    //   2512: aload #4
    //   2514: getstatic burp/Zzk9.Zb : Ljava/lang/String;
    //   2517: getstatic burp/Zl88.ZK : Ljava/lang/Object;
    //   2520: checkcast java/math/BigInteger
    //   2523: invokevirtual intValue : ()I
    //   2526: bipush #32
    //   2528: irem
    //   2529: invokestatic abs : (I)I
    //   2532: invokevirtual charAt : (I)C
    //   2535: invokevirtual append : (C)Ljava/lang/StringBuilder;
    //   2538: pop
    //   2539: iload_2
    //   2540: ifeq -> 2736
    //   2543: goto -> 2550
    //   2546: invokestatic a : (Ljava/lang/Throwable;)Ljava/lang/Throwable;
    //   2549: athrow
    //   2550: aload #4
    //   2552: getstatic burp/Zes_.ZM : Ljava/lang/String;
    //   2555: getstatic burp/Zxzd.ZD : Ljava/lang/Object;
    //   2558: checkcast java/math/BigInteger
    //   2561: invokevirtual intValue : ()I
    //   2564: bipush #32
    //   2566: irem
    //   2567: invokestatic abs : (I)I
    //   2570: invokevirtual charAt : (I)C
    //   2573: invokevirtual append : (C)Ljava/lang/StringBuilder;
    //   2576: pop
    //   2577: iload_2
    //   2578: ifeq -> 2736
    //   2581: goto -> 2588
    //   2584: invokestatic a : (Ljava/lang/Throwable;)Ljava/lang/Throwable;
    //   2587: athrow
    //   2588: aload #4
    //   2590: getstatic burp/Zkmx.Zg : Ljava/lang/String;
    //   2593: getstatic burp/Ztnw.Zt : Ljava/lang/Object;
    //   2596: checkcast java/math/BigInteger
    //   2599: invokevirtual intValue : ()I
    //   2602: bipush #32
    //   2604: irem
    //   2605: invokestatic abs : (I)I
    //   2608: invokevirtual charAt : (I)C
    //   2611: invokevirtual append : (C)Ljava/lang/StringBuilder;
    //   2614: pop
    //   2615: iload_2
    //   2616: ifeq -> 2736
    //   2619: goto -> 2626
    //   2622: invokestatic a : (Ljava/lang/Throwable;)Ljava/lang/Throwable;
    //   2625: athrow
    //   2626: aload #4
    //   2628: getstatic burp/Zlhm.Zx : Ljava/lang/String;
    //   2631: getstatic burp/Ze3d.Ze : Ljava/lang/Object;
    //   2634: checkcast java/math/BigInteger
    //   2637: invokevirtual intValue : ()I
    //   2640: bipush #32
    //   2642: irem
    //   2643: invokestatic abs : (I)I
    //   2646: invokevirtual charAt : (I)C
    //   2649: invokevirtual append : (C)Ljava/lang/StringBuilder;
    //   2652: pop
    //   2653: iload_2
    //   2654: ifeq -> 2736
    //   2657: goto -> 2664
    //   2660: invokestatic a : (Ljava/lang/Throwable;)Ljava/lang/Throwable;
    //   2663: athrow
    //   2664: aload #4
    //   2666: getstatic burp/Zgmt.Zu : Ljava/lang/String;
    //   2669: getstatic burp/Zlv6.ZN : Ljava/lang/Object;
    //   2672: checkcast java/math/BigInteger
    //   2675: invokevirtual intValue : ()I
    //   2678: bipush #32
    //   2680: irem
    //   2681: invokestatic abs : (I)I
    //   2684: invokevirtual charAt : (I)C
    //   2687: invokevirtual append : (C)Ljava/lang/StringBuilder;
    //   2690: pop
    //   2691: iload_2
    //   2692: ifeq -> 2736
    //   2695: goto -> 2702
    //   2698: invokestatic a : (Ljava/lang/Throwable;)Ljava/lang/Throwable;
    //   2701: athrow
    //   2702: aload #4
    //   2704: getstatic burp/Zb8v.Zo : Ljava/lang/String;
    //   2707: getstatic burp/Zkyc.ZD : Ljava/lang/Object;
    //   2710: checkcast java/math/BigInteger
    //   2713: invokevirtual intValue : ()I
    //   2716: bipush #32
    //   2718: irem
    //   2719: invokestatic abs : (I)I
    //   2722: invokevirtual charAt : (I)C
    //   2725: invokevirtual append : (C)Ljava/lang/StringBuilder;
    //   2728: pop
    //   2729: goto -> 2736
    //   2732: invokestatic a : (Ljava/lang/Throwable;)Ljava/lang/Throwable;
    //   2735: athrow
    //   2736: iinc #5, 1
    //   2739: iload_2
    //   2740: ifeq -> 1374
    //   2743: aload #4
    //   2745: invokevirtual toString : ()Ljava/lang/String;
    //   2748: putstatic burp/Zl_u.Zc : Ljava/lang/String;
    //   2751: sipush #-20087
    //   2754: getstatic burp/Zsxj.Zi : Ljava/lang/Object;
    //   2757: checkcast java/math/BigInteger
    //   2760: getstatic burp/Zbp.ZD : Ljava/lang/Object;
    //   2763: checkcast java/math/BigInteger
    //   2766: invokevirtual subtract : (Ljava/math/BigInteger;)Ljava/math/BigInteger;
    //   2769: putstatic burp/Zsby.ZZ : Ljava/lang/Object;
    //   2772: sipush #8458
    //   2775: invokestatic a : (II)Ljava/lang/String;
    //   2778: iconst_1
    //   2779: ldc burp/Zlo0
    //   2781: invokevirtual getClassLoader : ()Ljava/lang/ClassLoader;
    //   2784: invokestatic forName : (Ljava/lang/String;ZLjava/lang/ClassLoader;)Ljava/lang/Class;
    //   2787: invokevirtual getDeclaredFields : ()[Ljava/lang/reflect/Field;
    //   2790: astore #5
    //   2792: aload #5
    //   2794: arraylength
    //   2795: istore #6
    //   2797: iconst_0
    //   2798: istore #7
    //   2800: iload #7
    //   2802: iload #6
    //   2804: if_icmpge -> 2942
    //   2807: aload #5
    //   2809: iload #7
    //   2811: aaload
    //   2812: astore #8
    //   2814: aload #8
    //   2816: invokevirtual getModifiers : ()I
    //   2819: invokestatic isStatic : (I)Z
    //   2822: ifne -> 2832
    //   2825: goto -> 2935
    //   2828: invokestatic a : (Ljava/lang/Throwable;)Ljava/lang/Throwable;
    //   2831: athrow
    //   2832: aload #8
    //   2834: invokevirtual getType : ()Ljava/lang/Class;
    //   2837: astore #9
    //   2839: aload #9
    //   2841: ifnull -> 2922
    //   2844: aload #9
    //   2846: invokevirtual isPrimitive : ()Z
    //   2849: ifne -> 2922
    //   2852: goto -> 2859
    //   2855: invokestatic a : (Ljava/lang/Throwable;)Ljava/lang/Throwable;
    //   2858: athrow
    //   2859: aload #9
    //   2861: invokevirtual getPackage : ()Ljava/lang/Package;
    //   2864: ifnull -> 2922
    //   2867: goto -> 2874
    //   2870: invokestatic a : (Ljava/lang/Throwable;)Ljava/lang/Throwable;
    //   2873: athrow
    //   2874: aload #9
    //   2876: invokevirtual getPackage : ()Ljava/lang/Package;
    //   2879: invokevirtual getName : ()Ljava/lang/String;
    //   2882: ifnull -> 2922
    //   2885: goto -> 2892
    //   2888: invokestatic a : (Ljava/lang/Throwable;)Ljava/lang/Throwable;
    //   2891: athrow
    //   2892: aload #9
    //   2894: invokevirtual getPackage : ()Ljava/lang/Package;
    //   2897: invokevirtual getName : ()Ljava/lang/String;
    //   2900: sipush #-20088
    //   2903: sipush #-330
    //   2906: invokestatic a : (II)Ljava/lang/String;
    //   2909: invokevirtual startsWith : (Ljava/lang/String;)Z
    //   2912: ifne -> 2922
    //   2915: goto -> 2922
    //   2918: invokestatic a : (Ljava/lang/Throwable;)Ljava/lang/Throwable;
    //   2921: athrow
    //   2922: aload #8
    //   2924: iconst_1
    //   2925: invokevirtual setAccessible : (Z)V
    //   2928: aload #8
    //   2930: aconst_null
    //   2931: invokevirtual get : (Ljava/lang/Object;)Ljava/lang/Object;
    //   2934: pop
    //   2935: iinc #7, 1
    //   2938: iload_2
    //   2939: ifeq -> 2800
    //   2942: sipush #-20081
    //   2945: sipush #12532
    //   2948: invokestatic a : (II)Ljava/lang/String;
    //   2951: invokestatic forName : (Ljava/lang/String;)Ljava/lang/Class;
    //   2954: invokevirtual getDeclaredMethods : ()[Ljava/lang/reflect/Method;
    //   2957: astore #5
    //   2959: aload #5
    //   2961: arraylength
    //   2962: istore #6
    //   2964: iconst_0
    //   2965: istore #7
    //   2967: iload #7
    //   2969: iload #6
    //   2971: if_icmpge -> 3104
    //   2974: aload #5
    //   2976: iload #7
    //   2978: aaload
    //   2979: astore #8
    //   2981: aload #8
    //   2983: invokevirtual getParameterTypes : ()[Ljava/lang/Class;
    //   2986: pop
    //   2987: aload #8
    //   2989: invokevirtual getModifiers : ()I
    //   2992: invokestatic isStatic : (I)Z
    //   2995: ifeq -> 3090
    //   2998: aload #8
    //   3000: invokevirtual getParameterTypes : ()[Ljava/lang/Class;
    //   3003: arraylength
    //   3004: iconst_2
    //   3005: if_icmpne -> 3090
    //   3008: goto -> 3015
    //   3011: invokestatic a : (Ljava/lang/Throwable;)Ljava/lang/Throwable;
    //   3014: athrow
    //   3015: aload #8
    //   3017: invokevirtual getReturnType : ()Ljava/lang/Class;
    //   3020: getstatic java/lang/Void.TYPE : Ljava/lang/Class;
    //   3023: invokevirtual equals : (Ljava/lang/Object;)Z
    //   3026: ifeq -> 3090
    //   3029: goto -> 3036
    //   3032: invokestatic a : (Ljava/lang/Throwable;)Ljava/lang/Throwable;
    //   3035: athrow
    //   3036: aload #8
    //   3038: iconst_1
    //   3039: invokevirtual setAccessible : (Z)V
    //   3042: aload #8
    //   3044: aconst_null
    //   3045: iconst_2
    //   3046: anewarray java/lang/Object
    //   3049: dup
    //   3050: iconst_0
    //   3051: aload_0
    //   3052: aastore
    //   3053: dup
    //   3054: iconst_1
    //   3055: aload_1
    //   3056: ifnonnull -> 3074
    //   3059: goto -> 3066
    //   3062: invokestatic a : (Ljava/lang/Throwable;)Ljava/lang/Throwable;
    //   3065: athrow
    //   3066: aload_1
    //   3067: goto -> 3081
    //   3070: invokestatic a : (Ljava/lang/Throwable;)Ljava/lang/Throwable;
    //   3073: athrow
    //   3074: aload_1
    //   3075: checkcast [B
    //   3078: invokevirtual clone : ()Ljava/lang/Object;
    //   3081: aastore
    //   3082: invokevirtual invoke : (Ljava/lang/Object;[Ljava/lang/Object;)Ljava/lang/Object;
    //   3085: pop
    //   3086: iload_2
    //   3087: ifeq -> 3104
    //   3090: iinc #7, 1
    //   3093: iload_2
    //   3094: ifeq -> 2967
    //   3097: goto -> 3104
    //   3100: invokestatic a : (Ljava/lang/Throwable;)Ljava/lang/Throwable;
    //   3103: athrow
    //   3104: iconst_0
    //   3105: istore #5
    //   3107: getstatic burp/Zr3q.ZM : Ljava/lang/String;
    //   3110: getstatic burp/Zod.ZP : Ljava/lang/Object;
    //   3113: checkcast java/math/BigInteger
    //   3116: invokevirtual intValue : ()I
    //   3119: bipush #32
    //   3121: irem
    //   3122: invokestatic abs : (I)I
    //   3125: invokevirtual charAt : (I)C
    //   3128: getstatic burp/Zgss.Zc : Ljava/lang/String;
    //   3131: getstatic burp/Zxk9.ZI : Ljava/lang/Object;
    //   3134: checkcast java/math/BigInteger
    //   3137: invokevirtual intValue : ()I
    //   3140: bipush #32
    //   3142: irem
    //   3143: invokestatic abs : (I)I
    //   3146: invokevirtual charAt : (I)C
    //   3149: if_icmpgt -> 3494
    //   3152: sipush #-20065
    //   3155: sipush #-10403
    //   3158: invokestatic a : (II)Ljava/lang/String;
    //   3161: iconst_1
    //   3162: ldc burp/Zszm
    //   3164: invokevirtual getClassLoader : ()Ljava/lang/ClassLoader;
    //   3167: invokestatic forName : (Ljava/lang/String;ZLjava/lang/ClassLoader;)Ljava/lang/Class;
    //   3170: invokevirtual getDeclaredFields : ()[Ljava/lang/reflect/Field;
    //   3173: astore #6
    //   3175: aload #6
    //   3177: arraylength
    //   3178: istore #7
    //   3180: iconst_0
    //   3181: istore #8
    //   3183: iload #8
    //   3185: iload #7
    //   3187: if_icmpge -> 3325
    //   3190: aload #6
    //   3192: iload #8
    //   3194: aaload
    //   3195: astore #9
    //   3197: aload #9
    //   3199: invokevirtual getModifiers : ()I
    //   3202: invokestatic isStatic : (I)Z
    //   3205: ifne -> 3215
    //   3208: goto -> 3318
    //   3211: invokestatic a : (Ljava/lang/Throwable;)Ljava/lang/Throwable;
    //   3214: athrow
    //   3215: aload #9
    //   3217: invokevirtual getType : ()Ljava/lang/Class;
    //   3220: astore #10
    //   3222: aload #10
    //   3224: ifnull -> 3305
    //   3227: aload #10
    //   3229: invokevirtual isPrimitive : ()Z
    //   3232: ifne -> 3305
    //   3235: goto -> 3242
    //   3238: invokestatic a : (Ljava/lang/Throwable;)Ljava/lang/Throwable;
    //   3241: athrow
    //   3242: aload #10
    //   3244: invokevirtual getPackage : ()Ljava/lang/Package;
    //   3247: ifnull -> 3305
    //   3250: goto -> 3257
    //   3253: invokestatic a : (Ljava/lang/Throwable;)Ljava/lang/Throwable;
    //   3256: athrow
    //   3257: aload #10
    //   3259: invokevirtual getPackage : ()Ljava/lang/Package;
    //   3262: invokevirtual getName : ()Ljava/lang/String;
    //   3265: ifnull -> 3305
    //   3268: goto -> 3275
    //   3271: invokestatic a : (Ljava/lang/Throwable;)Ljava/lang/Throwable;
    //   3274: athrow
    //   3275: aload #10
    //   3277: invokevirtual getPackage : ()Ljava/lang/Package;
    //   3280: invokevirtual getName : ()Ljava/lang/String;
    //   3283: sipush #-20085
    //   3286: sipush #612
    //   3289: invokestatic a : (II)Ljava/lang/String;
    //   3292: invokevirtual startsWith : (Ljava/lang/String;)Z
    //   3295: ifne -> 3305
    //   3298: goto -> 3305
    //   3301: invokestatic a : (Ljava/lang/Throwable;)Ljava/lang/Throwable;
    //   3304: athrow
    //   3305: aload #9
    //   3307: iconst_1
    //   3308: invokevirtual setAccessible : (Z)V
    //   3311: aload #9
    //   3313: aconst_null
    //   3314: invokevirtual get : (Ljava/lang/Object;)Ljava/lang/Object;
    //   3317: pop
    //   3318: iinc #8, 1
    //   3321: iload_2
    //   3322: ifeq -> 3183
    //   3325: sipush #-20091
    //   3328: sipush #6692
    //   3331: invokestatic a : (II)Ljava/lang/String;
    //   3334: invokestatic forName : (Ljava/lang/String;)Ljava/lang/Class;
    //   3337: invokevirtual getDeclaredMethods : ()[Ljava/lang/reflect/Method;
    //   3340: astore #6
    //   3342: aload #6
    //   3344: arraylength
    //   3345: istore #7
    //   3347: iconst_0
    //   3348: istore #8
    //   3350: iload #8
    //   3352: iload #7
    //   3354: if_icmpge -> 3491
    //   3357: aload #6
    //   3359: iload #8
    //   3361: aaload
    //   3362: astore #9
    //   3364: aload #9
    //   3366: invokevirtual getParameterTypes : ()[Ljava/lang/Class;
    //   3369: pop
    //   3370: aload #9
    //   3372: invokevirtual getModifiers : ()I
    //   3375: invokestatic isStatic : (I)Z
    //   3378: ifeq -> 3477
    //   3381: aload #9
    //   3383: invokevirtual getParameterTypes : ()[Ljava/lang/Class;
    //   3386: arraylength
    //   3387: iconst_2
    //   3388: if_icmpne -> 3477
    //   3391: goto -> 3398
    //   3394: invokestatic a : (Ljava/lang/Throwable;)Ljava/lang/Throwable;
    //   3397: athrow
    //   3398: aload #9
    //   3400: invokevirtual getReturnType : ()Ljava/lang/Class;
    //   3403: getstatic java/lang/Boolean.TYPE : Ljava/lang/Class;
    //   3406: if_acmpne -> 3477
    //   3409: goto -> 3416
    //   3412: invokestatic a : (Ljava/lang/Throwable;)Ljava/lang/Throwable;
    //   3415: athrow
    //   3416: aload #9
    //   3418: iconst_1
    //   3419: invokevirtual setAccessible : (Z)V
    //   3422: aload #9
    //   3424: aconst_null
    //   3425: iconst_2
    //   3426: anewarray java/lang/Object
    //   3429: dup
    //   3430: iconst_0
    //   3431: aload_0
    //   3432: aastore
    //   3433: dup
    //   3434: iconst_1
    //   3435: aload_1
    //   3436: ifnonnull -> 3454
    //   3439: goto -> 3446
    //   3442: invokestatic a : (Ljava/lang/Throwable;)Ljava/lang/Throwable;
    //   3445: athrow
    //   3446: aload_1
    //   3447: goto -> 3461
    //   3450: invokestatic a : (Ljava/lang/Throwable;)Ljava/lang/Throwable;
    //   3453: athrow
    //   3454: aload_1
    //   3455: checkcast [B
    //   3458: invokevirtual clone : ()Ljava/lang/Object;
    //   3461: aastore
    //   3462: invokevirtual invoke : (Ljava/lang/Object;[Ljava/lang/Object;)Ljava/lang/Object;
    //   3465: checkcast java/lang/Boolean
    //   3468: invokevirtual booleanValue : ()Z
    //   3471: istore #5
    //   3473: iload_2
    //   3474: ifeq -> 3491
    //   3477: iinc #8, 1
    //   3480: iload_2
    //   3481: ifeq -> 3350
    //   3484: goto -> 3491
    //   3487: invokestatic a : (Ljava/lang/Throwable;)Ljava/lang/Throwable;
    //   3490: athrow
    //   3491: goto -> 3833
    //   3494: sipush #-20094
    //   3497: sipush #25700
    //   3500: invokestatic a : (II)Ljava/lang/String;
    //   3503: iconst_1
    //   3504: ldc burp/Zro5
    //   3506: invokevirtual getClassLoader : ()Ljava/lang/ClassLoader;
    //   3509: invokestatic forName : (Ljava/lang/String;ZLjava/lang/ClassLoader;)Ljava/lang/Class;
    //   3512: invokevirtual getDeclaredFields : ()[Ljava/lang/reflect/Field;
    //   3515: astore #6
    //   3517: aload #6
    //   3519: arraylength
    //   3520: istore #7
    //   3522: iconst_0
    //   3523: istore #8
    //   3525: iload #8
    //   3527: iload #7
    //   3529: if_icmpge -> 3667
    //   3532: aload #6
    //   3534: iload #8
    //   3536: aaload
    //   3537: astore #9
    //   3539: aload #9
    //   3541: invokevirtual getModifiers : ()I
    //   3544: invokestatic isStatic : (I)Z
    //   3547: ifne -> 3557
    //   3550: goto -> 3660
    //   3553: invokestatic a : (Ljava/lang/Throwable;)Ljava/lang/Throwable;
    //   3556: athrow
    //   3557: aload #9
    //   3559: invokevirtual getType : ()Ljava/lang/Class;
    //   3562: astore #10
    //   3564: aload #10
    //   3566: ifnull -> 3647
    //   3569: aload #10
    //   3571: invokevirtual isPrimitive : ()Z
    //   3574: ifne -> 3647
    //   3577: goto -> 3584
    //   3580: invokestatic a : (Ljava/lang/Throwable;)Ljava/lang/Throwable;
    //   3583: athrow
    //   3584: aload #10
    //   3586: invokevirtual getPackage : ()Ljava/lang/Package;
    //   3589: ifnull -> 3647
    //   3592: goto -> 3599
    //   3595: invokestatic a : (Ljava/lang/Throwable;)Ljava/lang/Throwable;
    //   3598: athrow
    //   3599: aload #10
    //   3601: invokevirtual getPackage : ()Ljava/lang/Package;
    //   3604: invokevirtual getName : ()Ljava/lang/String;
    //   3607: ifnull -> 3647
    //   3610: goto -> 3617
    //   3613: invokestatic a : (Ljava/lang/Throwable;)Ljava/lang/Throwable;
    //   3616: athrow
    //   3617: aload #10
    //   3619: invokevirtual getPackage : ()Ljava/lang/Package;
    //   3622: invokevirtual getName : ()Ljava/lang/String;
    //   3625: sipush #-20085
    //   3628: sipush #612
    //   3631: invokestatic a : (II)Ljava/lang/String;
    //   3634: invokevirtual startsWith : (Ljava/lang/String;)Z
    //   3637: ifne -> 3647
    //   3640: goto -> 3647
    //   3643: invokestatic a : (Ljava/lang/Throwable;)Ljava/lang/Throwable;
    //   3646: athrow
    //   3647: aload #9
    //   3649: iconst_1
    //   3650: invokevirtual setAccessible : (Z)V
    //   3653: aload #9
    //   3655: aconst_null
    //   3656: invokevirtual get : (Ljava/lang/Object;)Ljava/lang/Object;
    //   3659: pop
    //   3660: iinc #8, 1
    //   3663: iload_2
    //   3664: ifeq -> 3525
    //   3667: sipush #-20090
    //   3670: sipush #12301
    //   3673: invokestatic a : (II)Ljava/lang/String;
    //   3676: invokestatic forName : (Ljava/lang/String;)Ljava/lang/Class;
    //   3679: invokevirtual getDeclaredMethods : ()[Ljava/lang/reflect/Method;
    //   3682: astore #6
    //   3684: aload #6
    //   3686: arraylength
    //   3687: istore #7
    //   3689: iconst_0
    //   3690: istore #8
    //   3692: iload #8
    //   3694: iload #7
    //   3696: if_icmpge -> 3833
    //   3699: aload #6
    //   3701: iload #8
    //   3703: aaload
    //   3704: astore #9
    //   3706: aload #9
    //   3708: invokevirtual getParameterTypes : ()[Ljava/lang/Class;
    //   3711: pop
    //   3712: aload #9
    //   3714: invokevirtual getModifiers : ()I
    //   3717: invokestatic isStatic : (I)Z
    //   3720: ifeq -> 3819
    //   3723: aload #9
    //   3725: invokevirtual getParameterTypes : ()[Ljava/lang/Class;
    //   3728: arraylength
    //   3729: iconst_2
    //   3730: if_icmpne -> 3819
    //   3733: goto -> 3740
    //   3736: invokestatic a : (Ljava/lang/Throwable;)Ljava/lang/Throwable;
    //   3739: athrow
    //   3740: aload #9
    //   3742: invokevirtual getReturnType : ()Ljava/lang/Class;
    //   3745: getstatic java/lang/Boolean.TYPE : Ljava/lang/Class;
    //   3748: if_acmpne -> 3819
    //   3751: goto -> 3758
    //   3754: invokestatic a : (Ljava/lang/Throwable;)Ljava/lang/Throwable;
    //   3757: athrow
    //   3758: aload #9
    //   3760: iconst_1
    //   3761: invokevirtual setAccessible : (Z)V
    //   3764: aload #9
    //   3766: aconst_null
    //   3767: iconst_2
    //   3768: anewarray java/lang/Object
    //   3771: dup
    //   3772: iconst_0
    //   3773: aload_0
    //   3774: aastore
    //   3775: dup
    //   3776: iconst_1
    //   3777: aload_1
    //   3778: ifnonnull -> 3796
    //   3781: goto -> 3788
    //   3784: invokestatic a : (Ljava/lang/Throwable;)Ljava/lang/Throwable;
    //   3787: athrow
    //   3788: aload_1
    //   3789: goto -> 3803
    //   3792: invokestatic a : (Ljava/lang/Throwable;)Ljava/lang/Throwable;
    //   3795: athrow
    //   3796: aload_1
    //   3797: checkcast [B
    //   3800: invokevirtual clone : ()Ljava/lang/Object;
    //   3803: aastore
    //   3804: invokevirtual invoke : (Ljava/lang/Object;[Ljava/lang/Object;)Ljava/lang/Object;
    //   3807: checkcast java/lang/Boolean
    //   3810: invokevirtual booleanValue : ()Z
    //   3813: istore #5
    //   3815: iload_2
    //   3816: ifeq -> 3833
    //   3819: iinc #8, 1
    //   3822: iload_2
    //   3823: ifeq -> 3692
    //   3826: goto -> 3833
    //   3829: invokestatic a : (Ljava/lang/Throwable;)Ljava/lang/Throwable;
    //   3832: athrow
    //   3833: iload #5
    //   3835: ifeq -> 3841
    //   3838: iload #5
    //   3840: ireturn
    //   3841: getstatic burp/Zsxj.Zp : Ljava/lang/String;
    //   3844: getstatic burp/Zxl5.Zh : Ljava/lang/Object;
    //   3847: checkcast java/math/BigInteger
    //   3850: invokevirtual intValue : ()I
    //   3853: bipush #32
    //   3855: irem
    //   3856: invokestatic abs : (I)I
    //   3859: invokevirtual charAt : (I)C
    //   3862: getstatic burp/Zl88.Zd : Ljava/lang/String;
    //   3865: getstatic burp/Zb2s.Ze : Ljava/lang/Object;
    //   3868: checkcast java/math/BigInteger
    //   3871: invokevirtual intValue : ()I
    //   3874: bipush #32
    //   3876: irem
    //   3877: invokestatic abs : (I)I
    //   3880: invokevirtual charAt : (I)C
    //   3883: if_icmpgt -> 4229
    //   3886: sipush #-20095
    //   3889: sipush #-14817
    //   3892: invokestatic a : (II)Ljava/lang/String;
    //   3895: iconst_1
    //   3896: ldc burp/Zera
    //   3898: invokevirtual getClassLoader : ()Ljava/lang/ClassLoader;
    //   3901: invokestatic forName : (Ljava/lang/String;ZLjava/lang/ClassLoader;)Ljava/lang/Class;
    //   3904: invokevirtual getDeclaredFields : ()[Ljava/lang/reflect/Field;
    //   3907: astore #6
    //   3909: aload #6
    //   3911: arraylength
    //   3912: istore #7
    //   3914: iconst_0
    //   3915: istore #8
    //   3917: iload #8
    //   3919: iload #7
    //   3921: if_icmpge -> 4059
    //   3924: aload #6
    //   3926: iload #8
    //   3928: aaload
    //   3929: astore #9
    //   3931: aload #9
    //   3933: invokevirtual getModifiers : ()I
    //   3936: invokestatic isStatic : (I)Z
    //   3939: ifne -> 3949
    //   3942: goto -> 4052
    //   3945: invokestatic a : (Ljava/lang/Throwable;)Ljava/lang/Throwable;
    //   3948: athrow
    //   3949: aload #9
    //   3951: invokevirtual getType : ()Ljava/lang/Class;
    //   3954: astore #10
    //   3956: aload #10
    //   3958: ifnull -> 4039
    //   3961: aload #10
    //   3963: invokevirtual isPrimitive : ()Z
    //   3966: ifne -> 4039
    //   3969: goto -> 3976
    //   3972: invokestatic a : (Ljava/lang/Throwable;)Ljava/lang/Throwable;
    //   3975: athrow
    //   3976: aload #10
    //   3978: invokevirtual getPackage : ()Ljava/lang/Package;
    //   3981: ifnull -> 4039
    //   3984: goto -> 3991
    //   3987: invokestatic a : (Ljava/lang/Throwable;)Ljava/lang/Throwable;
    //   3990: athrow
    //   3991: aload #10
    //   3993: invokevirtual getPackage : ()Ljava/lang/Package;
    //   3996: invokevirtual getName : ()Ljava/lang/String;
    //   3999: ifnull -> 4039
    //   4002: goto -> 4009
    //   4005: invokestatic a : (Ljava/lang/Throwable;)Ljava/lang/Throwable;
    //   4008: athrow
    //   4009: aload #10
    //   4011: invokevirtual getPackage : ()Ljava/lang/Package;
    //   4014: invokevirtual getName : ()Ljava/lang/String;
    //   4017: sipush #-20085
    //   4020: sipush #612
    //   4023: invokestatic a : (II)Ljava/lang/String;
    //   4026: invokevirtual startsWith : (Ljava/lang/String;)Z
    //   4029: ifne -> 4039
    //   4032: goto -> 4039
    //   4035: invokestatic a : (Ljava/lang/Throwable;)Ljava/lang/Throwable;
    //   4038: athrow
    //   4039: aload #9
    //   4041: iconst_1
    //   4042: invokevirtual setAccessible : (Z)V
    //   4045: aload #9
    //   4047: aconst_null
    //   4048: invokevirtual get : (Ljava/lang/Object;)Ljava/lang/Object;
    //   4051: pop
    //   4052: iinc #8, 1
    //   4055: iload_2
    //   4056: ifeq -> 3917
    //   4059: sipush #-20083
    //   4062: sipush #-30550
    //   4065: invokestatic a : (II)Ljava/lang/String;
    //   4068: invokestatic forName : (Ljava/lang/String;)Ljava/lang/Class;
    //   4071: invokevirtual getDeclaredMethods : ()[Ljava/lang/reflect/Method;
    //   4074: astore #6
    //   4076: aload #6
    //   4078: arraylength
    //   4079: istore #7
    //   4081: iconst_0
    //   4082: istore #8
    //   4084: iload #8
    //   4086: iload #7
    //   4088: if_icmpge -> 4225
    //   4091: aload #6
    //   4093: iload #8
    //   4095: aaload
    //   4096: astore #9
    //   4098: aload #9
    //   4100: invokevirtual getParameterTypes : ()[Ljava/lang/Class;
    //   4103: pop
    //   4104: aload #9
    //   4106: invokevirtual getModifiers : ()I
    //   4109: invokestatic isStatic : (I)Z
    //   4112: ifeq -> 4211
    //   4115: aload #9
    //   4117: invokevirtual getParameterTypes : ()[Ljava/lang/Class;
    //   4120: arraylength
    //   4121: iconst_2
    //   4122: if_icmpne -> 4211
    //   4125: goto -> 4132
    //   4128: invokestatic a : (Ljava/lang/Throwable;)Ljava/lang/Throwable;
    //   4131: athrow
    //   4132: aload #9
    //   4134: invokevirtual getReturnType : ()Ljava/lang/Class;
    //   4137: getstatic java/lang/Boolean.TYPE : Ljava/lang/Class;
    //   4140: if_acmpne -> 4211
    //   4143: goto -> 4150
    //   4146: invokestatic a : (Ljava/lang/Throwable;)Ljava/lang/Throwable;
    //   4149: athrow
    //   4150: aload #9
    //   4152: iconst_1
    //   4153: invokevirtual setAccessible : (Z)V
    //   4156: aload #9
    //   4158: aconst_null
    //   4159: iconst_2
    //   4160: anewarray java/lang/Object
    //   4163: dup
    //   4164: iconst_0
    //   4165: aload_0
    //   4166: aastore
    //   4167: dup
    //   4168: iconst_1
    //   4169: aload_1
    //   4170: ifnonnull -> 4188
    //   4173: goto -> 4180
    //   4176: invokestatic a : (Ljava/lang/Throwable;)Ljava/lang/Throwable;
    //   4179: athrow
    //   4180: aload_1
    //   4181: goto -> 4195
    //   4184: invokestatic a : (Ljava/lang/Throwable;)Ljava/lang/Throwable;
    //   4187: athrow
    //   4188: aload_1
    //   4189: checkcast [B
    //   4192: invokevirtual clone : ()Ljava/lang/Object;
    //   4195: aastore
    //   4196: invokevirtual invoke : (Ljava/lang/Object;[Ljava/lang/Object;)Ljava/lang/Object;
    //   4199: checkcast java/lang/Boolean
    //   4202: invokevirtual booleanValue : ()Z
    //   4205: istore #5
    //   4207: iload_2
    //   4208: ifeq -> 4225
    //   4211: iinc #8, 1
    //   4214: iload_2
    //   4215: ifeq -> 4084
    //   4218: goto -> 4225
    //   4221: invokestatic a : (Ljava/lang/Throwable;)Ljava/lang/Throwable;
    //   4224: athrow
    //   4225: iload_2
    //   4226: ifeq -> 4568
    //   4229: sipush #-20067
    //   4232: sipush #-28314
    //   4235: invokestatic a : (II)Ljava/lang/String;
    //   4238: iconst_1
    //   4239: ldc burp/Zz67
    //   4241: invokevirtual getClassLoader : ()Ljava/lang/ClassLoader;
    //   4244: invokestatic forName : (Ljava/lang/String;ZLjava/lang/ClassLoader;)Ljava/lang/Class;
    //   4247: invokevirtual getDeclaredFields : ()[Ljava/lang/reflect/Field;
    //   4250: astore #6
    //   4252: aload #6
    //   4254: arraylength
    //   4255: istore #7
    //   4257: iconst_0
    //   4258: istore #8
    //   4260: iload #8
    //   4262: iload #7
    //   4264: if_icmpge -> 4402
    //   4267: aload #6
    //   4269: iload #8
    //   4271: aaload
    //   4272: astore #9
    //   4274: aload #9
    //   4276: invokevirtual getModifiers : ()I
    //   4279: invokestatic isStatic : (I)Z
    //   4282: ifne -> 4292
    //   4285: goto -> 4395
    //   4288: invokestatic a : (Ljava/lang/Throwable;)Ljava/lang/Throwable;
    //   4291: athrow
    //   4292: aload #9
    //   4294: invokevirtual getType : ()Ljava/lang/Class;
    //   4297: astore #10
    //   4299: aload #10
    //   4301: ifnull -> 4382
    //   4304: aload #10
    //   4306: invokevirtual isPrimitive : ()Z
    //   4309: ifne -> 4382
    //   4312: goto -> 4319
    //   4315: invokestatic a : (Ljava/lang/Throwable;)Ljava/lang/Throwable;
    //   4318: athrow
    //   4319: aload #10
    //   4321: invokevirtual getPackage : ()Ljava/lang/Package;
    //   4324: ifnull -> 4382
    //   4327: goto -> 4334
    //   4330: invokestatic a : (Ljava/lang/Throwable;)Ljava/lang/Throwable;
    //   4333: athrow
    //   4334: aload #10
    //   4336: invokevirtual getPackage : ()Ljava/lang/Package;
    //   4339: invokevirtual getName : ()Ljava/lang/String;
    //   4342: ifnull -> 4382
    //   4345: goto -> 4352
    //   4348: invokestatic a : (Ljava/lang/Throwable;)Ljava/lang/Throwable;
    //   4351: athrow
    //   4352: aload #10
    //   4354: invokevirtual getPackage : ()Ljava/lang/Package;
    //   4357: invokevirtual getName : ()Ljava/lang/String;
    //   4360: sipush #-20085
    //   4363: sipush #612
    //   4366: invokestatic a : (II)Ljava/lang/String;
    //   4369: invokevirtual startsWith : (Ljava/lang/String;)Z
    //   4372: ifne -> 4382
    //   4375: goto -> 4382
    //   4378: invokestatic a : (Ljava/lang/Throwable;)Ljava/lang/Throwable;
    //   4381: athrow
    //   4382: aload #9
    //   4384: iconst_1
    //   4385: invokevirtual setAccessible : (Z)V
    //   4388: aload #9
    //   4390: aconst_null
    //   4391: invokevirtual get : (Ljava/lang/Object;)Ljava/lang/Object;
    //   4394: pop
    //   4395: iinc #8, 1
    //   4398: iload_2
    //   4399: ifeq -> 4260
    //   4402: sipush #-20093
    //   4405: sipush #3869
    //   4408: invokestatic a : (II)Ljava/lang/String;
    //   4411: invokestatic forName : (Ljava/lang/String;)Ljava/lang/Class;
    //   4414: invokevirtual getDeclaredMethods : ()[Ljava/lang/reflect/Method;
    //   4417: astore #6
    //   4419: aload #6
    //   4421: arraylength
    //   4422: istore #7
    //   4424: iconst_0
    //   4425: istore #8
    //   4427: iload #8
    //   4429: iload #7
    //   4431: if_icmpge -> 4568
    //   4434: aload #6
    //   4436: iload #8
    //   4438: aaload
    //   4439: astore #9
    //   4441: aload #9
    //   4443: invokevirtual getParameterTypes : ()[Ljava/lang/Class;
    //   4446: pop
    //   4447: aload #9
    //   4449: invokevirtual getModifiers : ()I
    //   4452: invokestatic isStatic : (I)Z
    //   4455: ifeq -> 4554
    //   4458: aload #9
    //   4460: invokevirtual getParameterTypes : ()[Ljava/lang/Class;
    //   4463: arraylength
    //   4464: iconst_2
    //   4465: if_icmpne -> 4554
    //   4468: goto -> 4475
    //   4471: invokestatic a : (Ljava/lang/Throwable;)Ljava/lang/Throwable;
    //   4474: athrow
    //   4475: aload #9
    //   4477: invokevirtual getReturnType : ()Ljava/lang/Class;
    //   4480: getstatic java/lang/Boolean.TYPE : Ljava/lang/Class;
    //   4483: if_acmpne -> 4554
    //   4486: goto -> 4493
    //   4489: invokestatic a : (Ljava/lang/Throwable;)Ljava/lang/Throwable;
    //   4492: athrow
    //   4493: aload #9
    //   4495: iconst_1
    //   4496: invokevirtual setAccessible : (Z)V
    //   4499: aload #9
    //   4501: aconst_null
    //   4502: iconst_2
    //   4503: anewarray java/lang/Object
    //   4506: dup
    //   4507: iconst_0
    //   4508: aload_0
    //   4509: aastore
    //   4510: dup
    //   4511: iconst_1
    //   4512: aload_1
    //   4513: ifnonnull -> 4531
    //   4516: goto -> 4523
    //   4519: invokestatic a : (Ljava/lang/Throwable;)Ljava/lang/Throwable;
    //   4522: athrow
    //   4523: aload_1
    //   4524: goto -> 4538
    //   4527: invokestatic a : (Ljava/lang/Throwable;)Ljava/lang/Throwable;
    //   4530: athrow
    //   4531: aload_1
    //   4532: checkcast [B
    //   4535: invokevirtual clone : ()Ljava/lang/Object;
    //   4538: aastore
    //   4539: invokevirtual invoke : (Ljava/lang/Object;[Ljava/lang/Object;)Ljava/lang/Object;
    //   4542: checkcast java/lang/Boolean
    //   4545: invokevirtual booleanValue : ()Z
    //   4548: istore #5
    //   4550: iload_2
    //   4551: ifeq -> 4568
    //   4554: iinc #8, 1
    //   4557: iload_2
    //   4558: ifeq -> 4427
    //   4561: goto -> 4568
    //   4564: invokestatic a : (Ljava/lang/Throwable;)Ljava/lang/Throwable;
    //   4567: athrow
    //   4568: iload #5
    //   4570: ifeq -> 4576
    //   4573: iload #5
    //   4575: ireturn
    //   4576: getstatic burp/Zl_u.Zc : Ljava/lang/String;
    //   4579: getstatic burp/Zxyp.ZZ : Ljava/lang/Object;
    //   4582: checkcast java/math/BigInteger
    //   4585: invokevirtual intValue : ()I
    //   4588: bipush #32
    //   4590: irem
    //   4591: invokestatic abs : (I)I
    //   4594: invokevirtual charAt : (I)C
    //   4597: getstatic burp/Ztuj.Zk : Ljava/lang/String;
    //   4600: getstatic burp/Zg_p.Zx : Ljava/lang/Object;
    //   4603: checkcast java/math/BigInteger
    //   4606: invokevirtual intValue : ()I
    //   4609: bipush #32
    //   4611: irem
    //   4612: invokestatic abs : (I)I
    //   4615: invokevirtual charAt : (I)C
    //   4618: if_icmpgt -> 4964
    //   4621: sipush #-20096
    //   4624: sipush #16560
    //   4627: invokestatic a : (II)Ljava/lang/String;
    //   4630: iconst_1
    //   4631: ldc burp/Zb2p
    //   4633: invokevirtual getClassLoader : ()Ljava/lang/ClassLoader;
    //   4636: invokestatic forName : (Ljava/lang/String;ZLjava/lang/ClassLoader;)Ljava/lang/Class;
    //   4639: invokevirtual getDeclaredFields : ()[Ljava/lang/reflect/Field;
    //   4642: astore #6
    //   4644: aload #6
    //   4646: arraylength
    //   4647: istore #7
    //   4649: iconst_0
    //   4650: istore #8
    //   4652: iload #8
    //   4654: iload #7
    //   4656: if_icmpge -> 4794
    //   4659: aload #6
    //   4661: iload #8
    //   4663: aaload
    //   4664: astore #9
    //   4666: aload #9
    //   4668: invokevirtual getModifiers : ()I
    //   4671: invokestatic isStatic : (I)Z
    //   4674: ifne -> 4684
    //   4677: goto -> 4787
    //   4680: invokestatic a : (Ljava/lang/Throwable;)Ljava/lang/Throwable;
    //   4683: athrow
    //   4684: aload #9
    //   4686: invokevirtual getType : ()Ljava/lang/Class;
    //   4689: astore #10
    //   4691: aload #10
    //   4693: ifnull -> 4774
    //   4696: aload #10
    //   4698: invokevirtual isPrimitive : ()Z
    //   4701: ifne -> 4774
    //   4704: goto -> 4711
    //   4707: invokestatic a : (Ljava/lang/Throwable;)Ljava/lang/Throwable;
    //   4710: athrow
    //   4711: aload #10
    //   4713: invokevirtual getPackage : ()Ljava/lang/Package;
    //   4716: ifnull -> 4774
    //   4719: goto -> 4726
    //   4722: invokestatic a : (Ljava/lang/Throwable;)Ljava/lang/Throwable;
    //   4725: athrow
    //   4726: aload #10
    //   4728: invokevirtual getPackage : ()Ljava/lang/Package;
    //   4731: invokevirtual getName : ()Ljava/lang/String;
    //   4734: ifnull -> 4774
    //   4737: goto -> 4744
    //   4740: invokestatic a : (Ljava/lang/Throwable;)Ljava/lang/Throwable;
    //   4743: athrow
    //   4744: aload #10
    //   4746: invokevirtual getPackage : ()Ljava/lang/Package;
    //   4749: invokevirtual getName : ()Ljava/lang/String;
    //   4752: sipush #-20085
    //   4755: sipush #612
    //   4758: invokestatic a : (II)Ljava/lang/String;
    //   4761: invokevirtual startsWith : (Ljava/lang/String;)Z
    //   4764: ifne -> 4774
    //   4767: goto -> 4774
    //   4770: invokestatic a : (Ljava/lang/Throwable;)Ljava/lang/Throwable;
    //   4773: athrow
    //   4774: aload #9
    //   4776: iconst_1
    //   4777: invokevirtual setAccessible : (Z)V
    //   4780: aload #9
    //   4782: aconst_null
    //   4783: invokevirtual get : (Ljava/lang/Object;)Ljava/lang/Object;
    //   4786: pop
    //   4787: iinc #8, 1
    //   4790: iload_2
    //   4791: ifeq -> 4652
    //   4794: sipush #-20086
    //   4797: sipush #-22701
    //   4800: invokestatic a : (II)Ljava/lang/String;
    //   4803: invokestatic forName : (Ljava/lang/String;)Ljava/lang/Class;
    //   4806: invokevirtual getDeclaredMethods : ()[Ljava/lang/reflect/Method;
    //   4809: astore #6
    //   4811: aload #6
    //   4813: arraylength
    //   4814: istore #7
    //   4816: iconst_0
    //   4817: istore #8
    //   4819: iload #8
    //   4821: iload #7
    //   4823: if_icmpge -> 4960
    //   4826: aload #6
    //   4828: iload #8
    //   4830: aaload
    //   4831: astore #9
    //   4833: aload #9
    //   4835: invokevirtual getParameterTypes : ()[Ljava/lang/Class;
    //   4838: pop
    //   4839: aload #9
    //   4841: invokevirtual getModifiers : ()I
    //   4844: invokestatic isStatic : (I)Z
    //   4847: ifeq -> 4946
    //   4850: aload #9
    //   4852: invokevirtual getParameterTypes : ()[Ljava/lang/Class;
    //   4855: arraylength
    //   4856: iconst_2
    //   4857: if_icmpne -> 4946
    //   4860: goto -> 4867
    //   4863: invokestatic a : (Ljava/lang/Throwable;)Ljava/lang/Throwable;
    //   4866: athrow
    //   4867: aload #9
    //   4869: invokevirtual getReturnType : ()Ljava/lang/Class;
    //   4872: getstatic java/lang/Boolean.TYPE : Ljava/lang/Class;
    //   4875: if_acmpne -> 4946
    //   4878: goto -> 4885
    //   4881: invokestatic a : (Ljava/lang/Throwable;)Ljava/lang/Throwable;
    //   4884: athrow
    //   4885: aload #9
    //   4887: iconst_1
    //   4888: invokevirtual setAccessible : (Z)V
    //   4891: aload #9
    //   4893: aconst_null
    //   4894: iconst_2
    //   4895: anewarray java/lang/Object
    //   4898: dup
    //   4899: iconst_0
    //   4900: aload_0
    //   4901: aastore
    //   4902: dup
    //   4903: iconst_1
    //   4904: aload_1
    //   4905: ifnonnull -> 4923
    //   4908: goto -> 4915
    //   4911: invokestatic a : (Ljava/lang/Throwable;)Ljava/lang/Throwable;
    //   4914: athrow
    //   4915: aload_1
    //   4916: goto -> 4930
    //   4919: invokestatic a : (Ljava/lang/Throwable;)Ljava/lang/Throwable;
    //   4922: athrow
    //   4923: aload_1
    //   4924: checkcast [B
    //   4927: invokevirtual clone : ()Ljava/lang/Object;
    //   4930: aastore
    //   4931: invokevirtual invoke : (Ljava/lang/Object;[Ljava/lang/Object;)Ljava/lang/Object;
    //   4934: checkcast java/lang/Boolean
    //   4937: invokevirtual booleanValue : ()Z
    //   4940: istore #5
    //   4942: iload_2
    //   4943: ifeq -> 4960
    //   4946: iinc #8, 1
    //   4949: iload_2
    //   4950: ifeq -> 4819
    //   4953: goto -> 4960
    //   4956: invokestatic a : (Ljava/lang/Throwable;)Ljava/lang/Throwable;
    //   4959: athrow
    //   4960: iload_2
    //   4961: ifeq -> 5303
    //   4964: sipush #-20081
    //   4967: sipush #12532
    //   4970: invokestatic a : (II)Ljava/lang/String;
    //   4973: iconst_1
    //   4974: ldc burp/Zebu
    //   4976: invokevirtual getClassLoader : ()Ljava/lang/ClassLoader;
    //   4979: invokestatic forName : (Ljava/lang/String;ZLjava/lang/ClassLoader;)Ljava/lang/Class;
    //   4982: invokevirtual getDeclaredFields : ()[Ljava/lang/reflect/Field;
    //   4985: astore #6
    //   4987: aload #6
    //   4989: arraylength
    //   4990: istore #7
    //   4992: iconst_0
    //   4993: istore #8
    //   4995: iload #8
    //   4997: iload #7
    //   4999: if_icmpge -> 5137
    //   5002: aload #6
    //   5004: iload #8
    //   5006: aaload
    //   5007: astore #9
    //   5009: aload #9
    //   5011: invokevirtual getModifiers : ()I
    //   5014: invokestatic isStatic : (I)Z
    //   5017: ifne -> 5027
    //   5020: goto -> 5130
    //   5023: invokestatic a : (Ljava/lang/Throwable;)Ljava/lang/Throwable;
    //   5026: athrow
    //   5027: aload #9
    //   5029: invokevirtual getType : ()Ljava/lang/Class;
    //   5032: astore #10
    //   5034: aload #10
    //   5036: ifnull -> 5117
    //   5039: aload #10
    //   5041: invokevirtual isPrimitive : ()Z
    //   5044: ifne -> 5117
    //   5047: goto -> 5054
    //   5050: invokestatic a : (Ljava/lang/Throwable;)Ljava/lang/Throwable;
    //   5053: athrow
    //   5054: aload #10
    //   5056: invokevirtual getPackage : ()Ljava/lang/Package;
    //   5059: ifnull -> 5117
    //   5062: goto -> 5069
    //   5065: invokestatic a : (Ljava/lang/Throwable;)Ljava/lang/Throwable;
    //   5068: athrow
    //   5069: aload #10
    //   5071: invokevirtual getPackage : ()Ljava/lang/Package;
    //   5074: invokevirtual getName : ()Ljava/lang/String;
    //   5077: ifnull -> 5117
    //   5080: goto -> 5087
    //   5083: invokestatic a : (Ljava/lang/Throwable;)Ljava/lang/Throwable;
    //   5086: athrow
    //   5087: aload #10
    //   5089: invokevirtual getPackage : ()Ljava/lang/Package;
    //   5092: invokevirtual getName : ()Ljava/lang/String;
    //   5095: sipush #-20085
    //   5098: sipush #612
    //   5101: invokestatic a : (II)Ljava/lang/String;
    //   5104: invokevirtual startsWith : (Ljava/lang/String;)Z
    //   5107: ifne -> 5117
    //   5110: goto -> 5117
    //   5113: invokestatic a : (Ljava/lang/Throwable;)Ljava/lang/Throwable;
    //   5116: athrow
    //   5117: aload #9
    //   5119: iconst_1
    //   5120: invokevirtual setAccessible : (Z)V
    //   5123: aload #9
    //   5125: aconst_null
    //   5126: invokevirtual get : (Ljava/lang/Object;)Ljava/lang/Object;
    //   5129: pop
    //   5130: iinc #8, 1
    //   5133: iload_2
    //   5134: ifeq -> 4995
    //   5137: sipush #-20081
    //   5140: sipush #12532
    //   5143: invokestatic a : (II)Ljava/lang/String;
    //   5146: invokestatic forName : (Ljava/lang/String;)Ljava/lang/Class;
    //   5149: invokevirtual getDeclaredMethods : ()[Ljava/lang/reflect/Method;
    //   5152: astore #6
    //   5154: aload #6
    //   5156: arraylength
    //   5157: istore #7
    //   5159: iconst_0
    //   5160: istore #8
    //   5162: iload #8
    //   5164: iload #7
    //   5166: if_icmpge -> 5303
    //   5169: aload #6
    //   5171: iload #8
    //   5173: aaload
    //   5174: astore #9
    //   5176: aload #9
    //   5178: invokevirtual getParameterTypes : ()[Ljava/lang/Class;
    //   5181: pop
    //   5182: aload #9
    //   5184: invokevirtual getModifiers : ()I
    //   5187: invokestatic isStatic : (I)Z
    //   5190: ifeq -> 5289
    //   5193: aload #9
    //   5195: invokevirtual getParameterTypes : ()[Ljava/lang/Class;
    //   5198: arraylength
    //   5199: iconst_2
    //   5200: if_icmpne -> 5289
    //   5203: goto -> 5210
    //   5206: invokestatic a : (Ljava/lang/Throwable;)Ljava/lang/Throwable;
    //   5209: athrow
    //   5210: aload #9
    //   5212: invokevirtual getReturnType : ()Ljava/lang/Class;
    //   5215: getstatic java/lang/Boolean.TYPE : Ljava/lang/Class;
    //   5218: if_acmpne -> 5289
    //   5221: goto -> 5228
    //   5224: invokestatic a : (Ljava/lang/Throwable;)Ljava/lang/Throwable;
    //   5227: athrow
    //   5228: aload #9
    //   5230: iconst_1
    //   5231: invokevirtual setAccessible : (Z)V
    //   5234: aload #9
    //   5236: aconst_null
    //   5237: iconst_2
    //   5238: anewarray java/lang/Object
    //   5241: dup
    //   5242: iconst_0
    //   5243: aload_0
    //   5244: aastore
    //   5245: dup
    //   5246: iconst_1
    //   5247: aload_1
    //   5248: ifnonnull -> 5266
    //   5251: goto -> 5258
    //   5254: invokestatic a : (Ljava/lang/Throwable;)Ljava/lang/Throwable;
    //   5257: athrow
    //   5258: aload_1
    //   5259: goto -> 5273
    //   5262: invokestatic a : (Ljava/lang/Throwable;)Ljava/lang/Throwable;
    //   5265: athrow
    //   5266: aload_1
    //   5267: checkcast [B
    //   5270: invokevirtual clone : ()Ljava/lang/Object;
    //   5273: aastore
    //   5274: invokevirtual invoke : (Ljava/lang/Object;[Ljava/lang/Object;)Ljava/lang/Object;
    //   5277: checkcast java/lang/Boolean
    //   5280: invokevirtual booleanValue : ()Z
    //   5283: istore #5
    //   5285: iload_2
    //   5286: ifeq -> 5303
    //   5289: iinc #8, 1
    //   5292: iload_2
    //   5293: ifeq -> 5162
    //   5296: goto -> 5303
    //   5299: invokestatic a : (Ljava/lang/Throwable;)Ljava/lang/Throwable;
    //   5302: athrow
    //   5303: iload #5
    //   5305: ifeq -> 5311
    //   5308: iload #5
    //   5310: ireturn
    //   5311: getstatic burp/Zm__.Zf : Ljava/lang/String;
    //   5314: getstatic burp/Zt3l.Zq : Ljava/lang/Object;
    //   5317: checkcast java/math/BigInteger
    //   5320: invokevirtual intValue : ()I
    //   5323: bipush #32
    //   5325: irem
    //   5326: invokestatic abs : (I)I
    //   5329: invokevirtual charAt : (I)C
    //   5332: getstatic burp/Zeh9.ZF : Ljava/lang/String;
    //   5335: getstatic burp/Zes_.ZJ : Ljava/lang/Object;
    //   5338: checkcast java/math/BigInteger
    //   5341: invokevirtual intValue : ()I
    //   5344: bipush #32
    //   5346: irem
    //   5347: invokestatic abs : (I)I
    //   5350: invokevirtual charAt : (I)C
    //   5353: if_icmple -> 5699
    //   5356: sipush #-20070
    //   5359: sipush #17128
    //   5362: invokestatic a : (II)Ljava/lang/String;
    //   5365: iconst_1
    //   5366: ldc burp/Zt5a
    //   5368: invokevirtual getClassLoader : ()Ljava/lang/ClassLoader;
    //   5371: invokestatic forName : (Ljava/lang/String;ZLjava/lang/ClassLoader;)Ljava/lang/Class;
    //   5374: invokevirtual getDeclaredFields : ()[Ljava/lang/reflect/Field;
    //   5377: astore #6
    //   5379: aload #6
    //   5381: arraylength
    //   5382: istore #7
    //   5384: iconst_0
    //   5385: istore #8
    //   5387: iload #8
    //   5389: iload #7
    //   5391: if_icmpge -> 5529
    //   5394: aload #6
    //   5396: iload #8
    //   5398: aaload
    //   5399: astore #9
    //   5401: aload #9
    //   5403: invokevirtual getModifiers : ()I
    //   5406: invokestatic isStatic : (I)Z
    //   5409: ifne -> 5419
    //   5412: goto -> 5522
    //   5415: invokestatic a : (Ljava/lang/Throwable;)Ljava/lang/Throwable;
    //   5418: athrow
    //   5419: aload #9
    //   5421: invokevirtual getType : ()Ljava/lang/Class;
    //   5424: astore #10
    //   5426: aload #10
    //   5428: ifnull -> 5509
    //   5431: aload #10
    //   5433: invokevirtual isPrimitive : ()Z
    //   5436: ifne -> 5509
    //   5439: goto -> 5446
    //   5442: invokestatic a : (Ljava/lang/Throwable;)Ljava/lang/Throwable;
    //   5445: athrow
    //   5446: aload #10
    //   5448: invokevirtual getPackage : ()Ljava/lang/Package;
    //   5451: ifnull -> 5509
    //   5454: goto -> 5461
    //   5457: invokestatic a : (Ljava/lang/Throwable;)Ljava/lang/Throwable;
    //   5460: athrow
    //   5461: aload #10
    //   5463: invokevirtual getPackage : ()Ljava/lang/Package;
    //   5466: invokevirtual getName : ()Ljava/lang/String;
    //   5469: ifnull -> 5509
    //   5472: goto -> 5479
    //   5475: invokestatic a : (Ljava/lang/Throwable;)Ljava/lang/Throwable;
    //   5478: athrow
    //   5479: aload #10
    //   5481: invokevirtual getPackage : ()Ljava/lang/Package;
    //   5484: invokevirtual getName : ()Ljava/lang/String;
    //   5487: sipush #-20085
    //   5490: sipush #612
    //   5493: invokestatic a : (II)Ljava/lang/String;
    //   5496: invokevirtual startsWith : (Ljava/lang/String;)Z
    //   5499: ifne -> 5509
    //   5502: goto -> 5509
    //   5505: invokestatic a : (Ljava/lang/Throwable;)Ljava/lang/Throwable;
    //   5508: athrow
    //   5509: aload #9
    //   5511: iconst_1
    //   5512: invokevirtual setAccessible : (Z)V
    //   5515: aload #9
    //   5517: aconst_null
    //   5518: invokevirtual get : (Ljava/lang/Object;)Ljava/lang/Object;
    //   5521: pop
    //   5522: iinc #8, 1
    //   5525: iload_2
    //   5526: ifeq -> 5387
    //   5529: sipush #-20092
    //   5532: sipush #146
    //   5535: invokestatic a : (II)Ljava/lang/String;
    //   5538: invokestatic forName : (Ljava/lang/String;)Ljava/lang/Class;
    //   5541: invokevirtual getDeclaredMethods : ()[Ljava/lang/reflect/Method;
    //   5544: astore #6
    //   5546: aload #6
    //   5548: arraylength
    //   5549: istore #7
    //   5551: iconst_0
    //   5552: istore #8
    //   5554: iload #8
    //   5556: iload #7
    //   5558: if_icmpge -> 5695
    //   5561: aload #6
    //   5563: iload #8
    //   5565: aaload
    //   5566: astore #9
    //   5568: aload #9
    //   5570: invokevirtual getParameterTypes : ()[Ljava/lang/Class;
    //   5573: pop
    //   5574: aload #9
    //   5576: invokevirtual getModifiers : ()I
    //   5579: invokestatic isStatic : (I)Z
    //   5582: ifeq -> 5681
    //   5585: aload #9
    //   5587: invokevirtual getParameterTypes : ()[Ljava/lang/Class;
    //   5590: arraylength
    //   5591: iconst_2
    //   5592: if_icmpne -> 5681
    //   5595: goto -> 5602
    //   5598: invokestatic a : (Ljava/lang/Throwable;)Ljava/lang/Throwable;
    //   5601: athrow
    //   5602: aload #9
    //   5604: invokevirtual getReturnType : ()Ljava/lang/Class;
    //   5607: getstatic java/lang/Boolean.TYPE : Ljava/lang/Class;
    //   5610: if_acmpne -> 5681
    //   5613: goto -> 5620
    //   5616: invokestatic a : (Ljava/lang/Throwable;)Ljava/lang/Throwable;
    //   5619: athrow
    //   5620: aload #9
    //   5622: iconst_1
    //   5623: invokevirtual setAccessible : (Z)V
    //   5626: aload #9
    //   5628: aconst_null
    //   5629: iconst_2
    //   5630: anewarray java/lang/Object
    //   5633: dup
    //   5634: iconst_0
    //   5635: aload_0
    //   5636: aastore
    //   5637: dup
    //   5638: iconst_1
    //   5639: aload_1
    //   5640: ifnonnull -> 5658
    //   5643: goto -> 5650
    //   5646: invokestatic a : (Ljava/lang/Throwable;)Ljava/lang/Throwable;
    //   5649: athrow
    //   5650: aload_1
    //   5651: goto -> 5665
    //   5654: invokestatic a : (Ljava/lang/Throwable;)Ljava/lang/Throwable;
    //   5657: athrow
    //   5658: aload_1
    //   5659: checkcast [B
    //   5662: invokevirtual clone : ()Ljava/lang/Object;
    //   5665: aastore
    //   5666: invokevirtual invoke : (Ljava/lang/Object;[Ljava/lang/Object;)Ljava/lang/Object;
    //   5669: checkcast java/lang/Boolean
    //   5672: invokevirtual booleanValue : ()Z
    //   5675: istore #5
    //   5677: iload_2
    //   5678: ifeq -> 5695
    //   5681: iinc #8, 1
    //   5684: iload_2
    //   5685: ifeq -> 5554
    //   5688: goto -> 5695
    //   5691: invokestatic a : (Ljava/lang/Throwable;)Ljava/lang/Throwable;
    //   5694: athrow
    //   5695: iload_2
    //   5696: ifeq -> 6038
    //   5699: sipush #-20071
    //   5702: sipush #3060
    //   5705: invokestatic a : (II)Ljava/lang/String;
    //   5708: iconst_1
    //   5709: ldc burp/Zb8v
    //   5711: invokevirtual getClassLoader : ()Ljava/lang/ClassLoader;
    //   5714: invokestatic forName : (Ljava/lang/String;ZLjava/lang/ClassLoader;)Ljava/lang/Class;
    //   5717: invokevirtual getDeclaredFields : ()[Ljava/lang/reflect/Field;
    //   5720: astore #6
    //   5722: aload #6
    //   5724: arraylength
    //   5725: istore #7
    //   5727: iconst_0
    //   5728: istore #8
    //   5730: iload #8
    //   5732: iload #7
    //   5734: if_icmpge -> 5872
    //   5737: aload #6
    //   5739: iload #8
    //   5741: aaload
    //   5742: astore #9
    //   5744: aload #9
    //   5746: invokevirtual getModifiers : ()I
    //   5749: invokestatic isStatic : (I)Z
    //   5752: ifne -> 5762
    //   5755: goto -> 5865
    //   5758: invokestatic a : (Ljava/lang/Throwable;)Ljava/lang/Throwable;
    //   5761: athrow
    //   5762: aload #9
    //   5764: invokevirtual getType : ()Ljava/lang/Class;
    //   5767: astore #10
    //   5769: aload #10
    //   5771: ifnull -> 5852
    //   5774: aload #10
    //   5776: invokevirtual isPrimitive : ()Z
    //   5779: ifne -> 5852
    //   5782: goto -> 5789
    //   5785: invokestatic a : (Ljava/lang/Throwable;)Ljava/lang/Throwable;
    //   5788: athrow
    //   5789: aload #10
    //   5791: invokevirtual getPackage : ()Ljava/lang/Package;
    //   5794: ifnull -> 5852
    //   5797: goto -> 5804
    //   5800: invokestatic a : (Ljava/lang/Throwable;)Ljava/lang/Throwable;
    //   5803: athrow
    //   5804: aload #10
    //   5806: invokevirtual getPackage : ()Ljava/lang/Package;
    //   5809: invokevirtual getName : ()Ljava/lang/String;
    //   5812: ifnull -> 5852
    //   5815: goto -> 5822
    //   5818: invokestatic a : (Ljava/lang/Throwable;)Ljava/lang/Throwable;
    //   5821: athrow
    //   5822: aload #10
    //   5824: invokevirtual getPackage : ()Ljava/lang/Package;
    //   5827: invokevirtual getName : ()Ljava/lang/String;
    //   5830: sipush #-20085
    //   5833: sipush #612
    //   5836: invokestatic a : (II)Ljava/lang/String;
    //   5839: invokevirtual startsWith : (Ljava/lang/String;)Z
    //   5842: ifne -> 5852
    //   5845: goto -> 5852
    //   5848: invokestatic a : (Ljava/lang/Throwable;)Ljava/lang/Throwable;
    //   5851: athrow
    //   5852: aload #9
    //   5854: iconst_1
    //   5855: invokevirtual setAccessible : (Z)V
    //   5858: aload #9
    //   5860: aconst_null
    //   5861: invokevirtual get : (Ljava/lang/Object;)Ljava/lang/Object;
    //   5864: pop
    //   5865: iinc #8, 1
    //   5868: iload_2
    //   5869: ifeq -> 5730
    //   5872: sipush #-20071
    //   5875: sipush #3060
    //   5878: invokestatic a : (II)Ljava/lang/String;
    //   5881: invokestatic forName : (Ljava/lang/String;)Ljava/lang/Class;
    //   5884: invokevirtual getDeclaredMethods : ()[Ljava/lang/reflect/Method;
    //   5887: astore #6
    //   5889: aload #6
    //   5891: arraylength
    //   5892: istore #7
    //   5894: iconst_0
    //   5895: istore #8
    //   5897: iload #8
    //   5899: iload #7
    //   5901: if_icmpge -> 6038
    //   5904: aload #6
    //   5906: iload #8
    //   5908: aaload
    //   5909: astore #9
    //   5911: aload #9
    //   5913: invokevirtual getParameterTypes : ()[Ljava/lang/Class;
    //   5916: pop
    //   5917: aload #9
    //   5919: invokevirtual getModifiers : ()I
    //   5922: invokestatic isStatic : (I)Z
    //   5925: ifeq -> 6024
    //   5928: aload #9
    //   5930: invokevirtual getParameterTypes : ()[Ljava/lang/Class;
    //   5933: arraylength
    //   5934: iconst_2
    //   5935: if_icmpne -> 6024
    //   5938: goto -> 5945
    //   5941: invokestatic a : (Ljava/lang/Throwable;)Ljava/lang/Throwable;
    //   5944: athrow
    //   5945: aload #9
    //   5947: invokevirtual getReturnType : ()Ljava/lang/Class;
    //   5950: getstatic java/lang/Boolean.TYPE : Ljava/lang/Class;
    //   5953: if_acmpne -> 6024
    //   5956: goto -> 5963
    //   5959: invokestatic a : (Ljava/lang/Throwable;)Ljava/lang/Throwable;
    //   5962: athrow
    //   5963: aload #9
    //   5965: iconst_1
    //   5966: invokevirtual setAccessible : (Z)V
    //   5969: aload #9
    //   5971: aconst_null
    //   5972: iconst_2
    //   5973: anewarray java/lang/Object
    //   5976: dup
    //   5977: iconst_0
    //   5978: aload_0
    //   5979: aastore
    //   5980: dup
    //   5981: iconst_1
    //   5982: aload_1
    //   5983: ifnonnull -> 6001
    //   5986: goto -> 5993
    //   5989: invokestatic a : (Ljava/lang/Throwable;)Ljava/lang/Throwable;
    //   5992: athrow
    //   5993: aload_1
    //   5994: goto -> 6008
    //   5997: invokestatic a : (Ljava/lang/Throwable;)Ljava/lang/Throwable;
    //   6000: athrow
    //   6001: aload_1
    //   6002: checkcast [B
    //   6005: invokevirtual clone : ()Ljava/lang/Object;
    //   6008: aastore
    //   6009: invokevirtual invoke : (Ljava/lang/Object;[Ljava/lang/Object;)Ljava/lang/Object;
    //   6012: checkcast java/lang/Boolean
    //   6015: invokevirtual booleanValue : ()Z
    //   6018: istore #5
    //   6020: iload_2
    //   6021: ifeq -> 6038
    //   6024: iinc #8, 1
    //   6027: iload_2
    //   6028: ifeq -> 5897
    //   6031: goto -> 6038
    //   6034: invokestatic a : (Ljava/lang/Throwable;)Ljava/lang/Throwable;
    //   6037: athrow
    //   6038: iload #5
    //   6040: ireturn
    //   6041: astore_3
    //   6042: new java/lang/Exception
    //   6045: dup
    //   6046: aload_3
    //   6047: invokevirtual getMessage : ()Ljava/lang/String;
    //   6050: invokespecial <init> : (Ljava/lang/String;)V
    //   6053: athrow
    // Exception table:
    //   from	to	target	type
    //   4	3840	6041	java/lang/Throwable
    //   22	198	201	java/lang/Throwable
    //   168	235	238	java/lang/Throwable
    //   205	272	275	java/lang/Throwable
    //   242	309	312	java/lang/Throwable
    //   279	346	349	java/lang/Throwable
    //   316	383	386	java/lang/Throwable
    //   353	420	423	java/lang/Throwable
    //   390	457	460	java/lang/Throwable
    //   427	494	497	java/lang/Throwable
    //   464	531	534	java/lang/Throwable
    //   501	568	571	java/lang/Throwable
    //   538	605	608	java/lang/Throwable
    //   575	642	645	java/lang/Throwable
    //   612	679	682	java/lang/Throwable
    //   649	716	719	java/lang/Throwable
    //   686	753	756	java/lang/Throwable
    //   723	790	793	java/lang/Throwable
    //   760	827	830	java/lang/Throwable
    //   797	864	867	java/lang/Throwable
    //   834	901	904	java/lang/Throwable
    //   871	938	941	java/lang/Throwable
    //   908	975	978	java/lang/Throwable
    //   945	1012	1015	java/lang/Throwable
    //   982	1049	1052	java/lang/Throwable
    //   1019	1086	1089	java/lang/Throwable
    //   1056	1123	1126	java/lang/Throwable
    //   1093	1160	1163	java/lang/Throwable
    //   1130	1197	1200	java/lang/Throwable
    //   1167	1234	1237	java/lang/Throwable
    //   1204	1271	1274	java/lang/Throwable
    //   1241	1308	1311	java/lang/Throwable
    //   1278	1341	1344	java/lang/Throwable
    //   1381	1555	1558	java/lang/Throwable
    //   1524	1593	1596	java/lang/Throwable
    //   1562	1631	1634	java/lang/Throwable
    //   1600	1669	1672	java/lang/Throwable
    //   1638	1707	1710	java/lang/Throwable
    //   1676	1745	1748	java/lang/Throwable
    //   1714	1783	1786	java/lang/Throwable
    //   1752	1821	1824	java/lang/Throwable
    //   1790	1859	1862	java/lang/Throwable
    //   1828	1897	1900	java/lang/Throwable
    //   1866	1935	1938	java/lang/Throwable
    //   1904	1973	1976	java/lang/Throwable
    //   1942	2011	2014	java/lang/Throwable
    //   1980	2049	2052	java/lang/Throwable
    //   2018	2087	2090	java/lang/Throwable
    //   2056	2125	2128	java/lang/Throwable
    //   2094	2163	2166	java/lang/Throwable
    //   2132	2201	2204	java/lang/Throwable
    //   2170	2239	2242	java/lang/Throwable
    //   2208	2277	2280	java/lang/Throwable
    //   2246	2315	2318	java/lang/Throwable
    //   2284	2353	2356	java/lang/Throwable
    //   2322	2391	2394	java/lang/Throwable
    //   2360	2429	2432	java/lang/Throwable
    //   2398	2467	2470	java/lang/Throwable
    //   2436	2505	2508	java/lang/Throwable
    //   2474	2543	2546	java/lang/Throwable
    //   2512	2581	2584	java/lang/Throwable
    //   2550	2619	2622	java/lang/Throwable
    //   2588	2657	2660	java/lang/Throwable
    //   2626	2695	2698	java/lang/Throwable
    //   2664	2729	2732	java/lang/Throwable
    //   2814	2828	2828	java/lang/Throwable
    //   2839	2852	2855	java/lang/Throwable
    //   2844	2867	2870	java/lang/Throwable
    //   2859	2885	2888	java/lang/Throwable
    //   2874	2915	2918	java/lang/Throwable
    //   2981	3008	3011	java/lang/Throwable
    //   2998	3029	3032	java/lang/Throwable
    //   3015	3059	3062	java/lang/Throwable
    //   3036	3070	3070	java/lang/Throwable
    //   3081	3097	3100	java/lang/Throwable
    //   3197	3211	3211	java/lang/Throwable
    //   3222	3235	3238	java/lang/Throwable
    //   3227	3250	3253	java/lang/Throwable
    //   3242	3268	3271	java/lang/Throwable
    //   3257	3298	3301	java/lang/Throwable
    //   3364	3391	3394	java/lang/Throwable
    //   3381	3409	3412	java/lang/Throwable
    //   3398	3439	3442	java/lang/Throwable
    //   3416	3450	3450	java/lang/Throwable
    //   3473	3484	3487	java/lang/Throwable
    //   3539	3553	3553	java/lang/Throwable
    //   3564	3577	3580	java/lang/Throwable
    //   3569	3592	3595	java/lang/Throwable
    //   3584	3610	3613	java/lang/Throwable
    //   3599	3640	3643	java/lang/Throwable
    //   3706	3733	3736	java/lang/Throwable
    //   3723	3751	3754	java/lang/Throwable
    //   3740	3781	3784	java/lang/Throwable
    //   3758	3792	3792	java/lang/Throwable
    //   3815	3826	3829	java/lang/Throwable
    //   3841	4575	6041	java/lang/Throwable
    //   3931	3945	3945	java/lang/Throwable
    //   3956	3969	3972	java/lang/Throwable
    //   3961	3984	3987	java/lang/Throwable
    //   3976	4002	4005	java/lang/Throwable
    //   3991	4032	4035	java/lang/Throwable
    //   4098	4125	4128	java/lang/Throwable
    //   4115	4143	4146	java/lang/Throwable
    //   4132	4173	4176	java/lang/Throwable
    //   4150	4184	4184	java/lang/Throwable
    //   4207	4218	4221	java/lang/Throwable
    //   4274	4288	4288	java/lang/Throwable
    //   4299	4312	4315	java/lang/Throwable
    //   4304	4327	4330	java/lang/Throwable
    //   4319	4345	4348	java/lang/Throwable
    //   4334	4375	4378	java/lang/Throwable
    //   4441	4468	4471	java/lang/Throwable
    //   4458	4486	4489	java/lang/Throwable
    //   4475	4516	4519	java/lang/Throwable
    //   4493	4527	4527	java/lang/Throwable
    //   4550	4561	4564	java/lang/Throwable
    //   4576	5310	6041	java/lang/Throwable
    //   4666	4680	4680	java/lang/Throwable
    //   4691	4704	4707	java/lang/Throwable
    //   4696	4719	4722	java/lang/Throwable
    //   4711	4737	4740	java/lang/Throwable
    //   4726	4767	4770	java/lang/Throwable
    //   4833	4860	4863	java/lang/Throwable
    //   4850	4878	4881	java/lang/Throwable
    //   4867	4908	4911	java/lang/Throwable
    //   4885	4919	4919	java/lang/Throwable
    //   4942	4953	4956	java/lang/Throwable
    //   5009	5023	5023	java/lang/Throwable
    //   5034	5047	5050	java/lang/Throwable
    //   5039	5062	5065	java/lang/Throwable
    //   5054	5080	5083	java/lang/Throwable
    //   5069	5110	5113	java/lang/Throwable
    //   5176	5203	5206	java/lang/Throwable
    //   5193	5221	5224	java/lang/Throwable
    //   5210	5251	5254	java/lang/Throwable
    //   5228	5262	5262	java/lang/Throwable
    //   5285	5296	5299	java/lang/Throwable
    //   5311	6040	6041	java/lang/Throwable
    //   5401	5415	5415	java/lang/Throwable
    //   5426	5439	5442	java/lang/Throwable
    //   5431	5454	5457	java/lang/Throwable
    //   5446	5472	5475	java/lang/Throwable
    //   5461	5502	5505	java/lang/Throwable
    //   5568	5595	5598	java/lang/Throwable
    //   5585	5613	5616	java/lang/Throwable
    //   5602	5643	5646	java/lang/Throwable
    //   5620	5654	5654	java/lang/Throwable
    //   5677	5688	5691	java/lang/Throwable
    //   5744	5758	5758	java/lang/Throwable
    //   5769	5782	5785	java/lang/Throwable
    //   5774	5797	5800	java/lang/Throwable
    //   5789	5815	5818	java/lang/Throwable
    //   5804	5845	5848	java/lang/Throwable
    //   5911	5938	5941	java/lang/Throwable
    //   5928	5956	5959	java/lang/Throwable
    //   5945	5986	5989	java/lang/Throwable
    //   5963	5997	5997	java/lang/Throwable
    //   6020	6031	6034	java/lang/Throwable
  }
  
  static void Zq(Object[] paramArrayOfObject, Object paramObject) throws Throwable {}
  
  static {
    // Byte code:
    //   0: bipush #23
    //   2: anewarray java/lang/String
    //   5: astore #5
    //   7: iconst_0
    //   8: istore_3
    //   9: ldc '2\\b<#Mhad_9@\\rH;~I&wv\\b-J^H#9n e:\\t^En$ #UF\\byB9,\\t-+(e/\\tQd\\t\\n)8II\\t& Z[\\t{e!Z-l\\tz1\\tgZ5%fk\\tMF\\r\\tul;F\\t\\fX\\t#*!;\\tr\\tuL#-\\tS6z)g):kva@|%L!f.p>3{M2Unn\\tL\\b?%'\\tZ;$N o(-29\\b](Z3y'
    //   11: dup
    //   12: astore_2
    //   13: invokevirtual length : ()I
    //   16: istore #4
    //   18: bipush #9
    //   20: istore_1
    //   21: iconst_m1
    //   22: istore_0
    //   23: bipush #46
    //   25: iinc #0, 1
    //   28: aload_2
    //   29: iload_0
    //   30: dup
    //   31: iload_1
    //   32: iadd
    //   33: invokevirtual substring : (II)Ljava/lang/String;
    //   36: iconst_m1
    //   37: goto -> 143
    //   40: aload #5
    //   42: swap
    //   43: iload_3
    //   44: iinc #3, 1
    //   47: swap
    //   48: aastore
    //   49: iload_0
    //   50: iload_1
    //   51: iadd
    //   52: dup
    //   53: istore_0
    //   54: iload #4
    //   56: if_icmpge -> 68
    //   59: aload_2
    //   60: iload_0
    //   61: invokevirtual charAt : (I)C
    //   64: istore_1
    //   65: goto -> 23
    //   68: ldc '%f=k\\fX\\tn~Th#ls'
    //   70: dup
    //   71: astore_2
    //   72: invokevirtual length : ()I
    //   75: istore #4
    //   77: bipush #9
    //   79: istore_1
    //   80: iconst_m1
    //   81: istore_0
    //   82: bipush #114
    //   84: iinc #0, 1
    //   87: aload_2
    //   88: iload_0
    //   89: dup
    //   90: iload_1
    //   91: iadd
    //   92: invokevirtual substring : (II)Ljava/lang/String;
    //   95: iconst_0
    //   96: goto -> 143
    //   99: aload #5
    //   101: swap
    //   102: iload_3
    //   103: iinc #3, 1
    //   106: swap
    //   107: aastore
    //   108: iload_0
    //   109: iload_1
    //   110: iadd
    //   111: dup
    //   112: istore_0
    //   113: iload #4
    //   115: if_icmpge -> 127
    //   118: aload_2
    //   119: iload_0
    //   120: invokevirtual charAt : (I)C
    //   123: istore_1
    //   124: goto -> 82
    //   127: aload #5
    //   129: putstatic burp/Zxso.a : [Ljava/lang/String;
    //   132: bipush #23
    //   134: anewarray java/lang/String
    //   137: putstatic burp/Zxso.b : [Ljava/lang/String;
    //   140: goto -> 300
    //   143: dup_x2
    //   144: pop
    //   145: invokevirtual toCharArray : ()[C
    //   148: dup_x1
    //   149: arraylength
    //   150: dup_x2
    //   151: pop
    //   152: iconst_0
    //   153: istore #6
    //   155: dup2_x1
    //   156: pop2
    //   157: dup_x2
    //   158: iconst_1
    //   159: if_icmpgt -> 260
    //   162: dup2
    //   163: swap
    //   164: iload #6
    //   166: dup2_x1
    //   167: caload
    //   168: swap
    //   169: iload #6
    //   171: bipush #7
    //   173: irem
    //   174: tableswitch default -> 242, 0 -> 212, 1 -> 217, 2 -> 222, 3 -> 227, 4 -> 232, 5 -> 237
    //   212: bipush #37
    //   214: goto -> 244
    //   217: bipush #11
    //   219: goto -> 244
    //   222: bipush #93
    //   224: goto -> 244
    //   227: bipush #81
    //   229: goto -> 244
    //   232: bipush #44
    //   234: goto -> 244
    //   237: bipush #83
    //   239: goto -> 244
    //   242: bipush #61
    //   244: ixor
    //   245: ixor
    //   246: i2c
    //   247: castore
    //   248: iinc #6, 1
    //   251: dup
    //   252: ifne -> 260
    //   255: dup2
    //   256: dup_x1
    //   257: goto -> 166
    //   260: dup2_x1
    //   261: pop2
    //   262: dup_x2
    //   263: iload #6
    //   265: if_icmpgt -> 162
    //   268: pop
    //   269: new java/lang/String
    //   272: dup_x1
    //   273: swap
    //   274: invokespecial <init> : ([C)V
    //   277: invokevirtual intern : ()Ljava/lang/String;
    //   280: swap
    //   281: pop
    //   282: swap
    //   283: tableswitch default -> 40, 0 -> 99
    //   300: new java/math/BigInteger
    //   303: dup
    //   304: sipush #-20066
    //   307: sipush #23047
    //   310: invokestatic a : (II)Ljava/lang/String;
    //   313: invokespecial <init> : (Ljava/lang/String;)V
    //   316: putstatic burp/Zxso.ZF : Ljava/lang/Object;
    //   319: sipush #-20069
    //   322: sipush #-12845
    //   325: invokestatic a : (II)Ljava/lang/String;
    //   328: putstatic burp/Zxso.ZH : Ljava/lang/String;
    //   331: return
  }
  
  private static Throwable a(Throwable paramThrowable) {
    return paramThrowable;
  }
  
  private static String a(int paramInt1, int paramInt2) {
    int i = (paramInt1 ^ 0xFFFFB18F) & 0xFFFF;
    if (b[i] == null) {
      char[] arrayOfChar = a[i].toCharArray();
      switch (arrayOfChar[0] & 0xFF) {
        case 0:
        
        case 1:
        
        case 2:
        
        case 3:
        
        case 4:
        
        case 5:
        
        case 6:
        
        case 7:
        
        case 8:
        
        case 9:
        
        case 10:
        
        case 11:
        
        case 12:
        
        case 13:
        
        case 14:
        
        case 15:
        
        case 16:
        
        case 17:
        
        case 18:
        
        case 19:
        
        case 20:
        
        case 21:
        
        case 22:
        
        case 23:
        
        case 24:
        
        case 25:
        
        case 26:
        
        case 27:
        
        case 28:
        
        case 29:
        
        case 30:
        
        case 31:
        
        case 32:
        
        case 33:
        
        case 34:
        
        case 35:
        
        case 36:
        
        case 37:
        
        case 38:
        
        case 39:
        
        case 40:
        
        case 41:
        
        case 42:
        
        case 43:
        
        case 44:
        
        case 45:
        
        case 46:
        
        case 47:
        
        case 48:
        
        case 49:
        
        case 50:
        
        case 51:
        
        case 52:
        
        case 53:
        
        case 54:
        
        case 55:
        
        case 56:
        
        case 57:
        
        case 58:
        
        case 59:
        
        case 60:
        
        case 61:
        
        case 62:
        
        case 63:
        
        case 64:
        
        case 65:
        
        case 66:
        
        case 67:
        
        case 68:
        
        case 69:
        
        case 70:
        
        case 71:
        
        case 72:
        
        case 73:
        
        case 74:
        
        case 75:
        
        case 76:
        
        case 77:
        
        case 78:
        
        case 79:
        
        case 80:
        
        case 81:
        
        case 82:
        
        case 83:
        
        case 84:
        
        case 85:
        
        case 86:
        
        case 87:
        
        case 88:
        
        case 89:
        
        case 90:
        
        case 91:
        
        case 92:
        
        case 93:
        
        case 94:
        
        case 95:
        
        case 96:
        
        case 97:
        
        case 98:
        
        case 99:
        
        case 100:
        
        case 101:
        
        case 102:
        
        case 103:
        
        case 104:
        
        case 105:
        
        case 106:
        
        case 107:
        
        case 108:
        
        case 109:
        
        case 110:
        
        case 111:
        
        case 112:
        
        case 113:
        
        case 114:
        
        case 115:
        
        case 116:
        
        case 117:
        
        case 118:
        
        case 119:
        
        case 120:
        
        case 121:
        
        case 122:
        
        case 123:
        
        case 124:
        
        case 125:
        
        case 126:
        
        case 127:
        
        case 128:
        
        case 129:
        
        case 130:
        
        case 131:
        
        case 132:
        
        case 133:
        
        case 134:
        
        case 135:
        
        case 136:
        
        case 137:
        
        case 138:
        
        case 139:
        
        case 140:
        
        case 141:
        
        case 142:
        
        case 143:
        
        case 144:
        
        case 145:
        
        case 146:
        
        case 147:
        
        case 148:
        
        case 149:
        
        case 150:
        
        case 151:
        
        case 152:
        
        case 153:
        
        case 154:
        
        case 155:
        
        case 156:
        
        case 157:
        
        case 158:
        
        case 159:
        
        case 160:
        
        case 161:
        
        case 162:
        
        case 163:
        
        case 164:
        
        case 165:
        
        case 166:
        
        case 167:
        
        case 168:
        
        case 169:
        
        case 170:
        
        case 171:
        
        case 172:
        
        case 173:
        
        case 174:
        
        case 175:
        
        case 176:
        
        case 177:
        
        case 178:
        
        case 179:
        
        case 180:
        
        case 181:
        
        case 182:
        
        case 183:
        
        case 184:
        
        case 185:
        
        case 186:
        
        case 187:
        
        case 188:
        
        case 189:
        
        case 190:
        
        case 191:
        
        case 192:
        
        case 193:
        
        case 194:
        
        case 195:
        
        case 196:
        
        case 197:
        
        case 198:
        
        case 199:
        
        case 200:
        
        case 201:
        
        case 202:
        
        case 203:
        
        case 204:
        
        case 205:
        
        case 206:
        
        case 207:
        
        case 208:
        
        case 209:
        
        case 210:
        
        case 211:
        
        case 212:
        
        case 213:
        
        case 214:
        
        case 215:
        
        case 216:
        
        case 217:
        
        case 218:
        
        case 219:
        
        case 220:
        
        case 221:
        
        case 222:
        
        case 223:
        
        case 224:
        
        case 225:
        
        case 226:
        
        case 227:
        
        case 228:
        
        case 229:
        
        case 230:
        
        case 231:
        
        case 232:
        
        case 233:
        
        case 234:
        
        case 235:
        
        case 236:
        
        case 237:
        
        case 238:
        
        case 239:
        
        case 240:
        
        case 241:
        
        case 242:
        
        case 243:
        
        case 244:
        
        case 245:
        
        case 246:
        
        case 247:
        
        case 248:
        
        case 249:
        
        case 250:
        
        case 251:
        
        case 252:
        
        case 253:
        
        case 254:
        
        default:
          break;
      } 
      byte b1 = 76;
      int j = (paramInt2 & 0xFF) - b1;
      if (j < 0)
        j += 256; 
      int k = ((paramInt2 & 0xFFFF) >>> 8) - b1;
      if (k < 0)
        k += 256; 
      for (byte b2 = 0; b2 < arrayOfChar.length; b2++) {
        int m = b2 % 2;
        if (m == 0) {
          arrayOfChar[b2] = (char)(arrayOfChar[b2] ^ j);
          j = ((j >>> 3 | j << 5) ^ arrayOfChar[b2]) & 0xFF;
        } else {
          arrayOfChar[b2] = (char)(arrayOfChar[b2] ^ k);
          k = ((k >>> 3 | k << 5) ^ arrayOfChar[b2]) & 0xFF;
        } 
      } 
      b[i] = (new String(arrayOfChar)).intern();
    } 
    return b[i];
  }
}


/* Location:              C:\Program Files\BurpSuitePro\burpsuite_pro.jar!\burp\Zxso.class
 * Java compiler version: 21 (65.0)
 * JD-Core Version:       1.1.3
 */