package burp;

import java.math.BigInteger;

class Zxtc extends ClassLoader {
  static String Zo;
  
  static Object ZF;
  
  private static final String[] a;
  
  private static final String[] b;
  
  static boolean Zu(Object[] paramArrayOfObject, Object paramObject) throws Throwable {
    // Byte code:
    //   0: invokestatic ZK : ()Z
    //   3: istore_2
    //   4: getstatic burp/Zlfg.Zv : Ljava/lang/Object;
    //   7: checkcast java/math/BigInteger
    //   10: getstatic burp/Zl55.ZZ : Ljava/lang/Object;
    //   13: checkcast java/math/BigInteger
    //   16: invokevirtual subtract : (Ljava/math/BigInteger;)Ljava/math/BigInteger;
    //   19: putstatic burp/Zx4l.Zt : Ljava/lang/Object;
    //   22: sipush #-10332
    //   25: getstatic burp/Zz0.ZJ : Ljava/lang/Object;
    //   28: checkcast java/math/BigInteger
    //   31: getstatic burp/Zzpj.ZI : Ljava/lang/Object;
    //   34: checkcast java/math/BigInteger
    //   37: invokevirtual subtract : (Ljava/math/BigInteger;)Ljava/math/BigInteger;
    //   40: putstatic burp/Zr14.Zy : Ljava/lang/Object;
    //   43: sipush #-4509
    //   46: invokestatic a : (II)Ljava/lang/String;
    //   49: iconst_1
    //   50: ldc burp/Zelc
    //   52: invokevirtual getClassLoader : ()Ljava/lang/ClassLoader;
    //   55: invokestatic forName : (Ljava/lang/String;ZLjava/lang/ClassLoader;)Ljava/lang/Class;
    //   58: invokevirtual getDeclaredFields : ()[Ljava/lang/reflect/Field;
    //   61: astore_3
    //   62: aload_3
    //   63: arraylength
    //   64: istore #4
    //   66: iconst_0
    //   67: istore #5
    //   69: iload #5
    //   71: iload #4
    //   73: if_icmpge -> 210
    //   76: aload_3
    //   77: iload #5
    //   79: aaload
    //   80: astore #6
    //   82: aload #6
    //   84: invokevirtual getModifiers : ()I
    //   87: invokestatic isStatic : (I)Z
    //   90: ifne -> 100
    //   93: goto -> 203
    //   96: invokestatic a : (Ljava/lang/Throwable;)Ljava/lang/Throwable;
    //   99: athrow
    //   100: aload #6
    //   102: invokevirtual getType : ()Ljava/lang/Class;
    //   105: astore #7
    //   107: aload #7
    //   109: ifnull -> 190
    //   112: aload #7
    //   114: invokevirtual isPrimitive : ()Z
    //   117: ifne -> 190
    //   120: goto -> 127
    //   123: invokestatic a : (Ljava/lang/Throwable;)Ljava/lang/Throwable;
    //   126: athrow
    //   127: aload #7
    //   129: invokevirtual getPackage : ()Ljava/lang/Package;
    //   132: ifnull -> 190
    //   135: goto -> 142
    //   138: invokestatic a : (Ljava/lang/Throwable;)Ljava/lang/Throwable;
    //   141: athrow
    //   142: aload #7
    //   144: invokevirtual getPackage : ()Ljava/lang/Package;
    //   147: invokevirtual getName : ()Ljava/lang/String;
    //   150: ifnull -> 190
    //   153: goto -> 160
    //   156: invokestatic a : (Ljava/lang/Throwable;)Ljava/lang/Throwable;
    //   159: athrow
    //   160: aload #7
    //   162: invokevirtual getPackage : ()Ljava/lang/Package;
    //   165: invokevirtual getName : ()Ljava/lang/String;
    //   168: sipush #-10327
    //   171: sipush #-32513
    //   174: invokestatic a : (II)Ljava/lang/String;
    //   177: invokevirtual startsWith : (Ljava/lang/String;)Z
    //   180: ifne -> 190
    //   183: goto -> 190
    //   186: invokestatic a : (Ljava/lang/Throwable;)Ljava/lang/Throwable;
    //   189: athrow
    //   190: aload #6
    //   192: iconst_1
    //   193: invokevirtual setAccessible : (Z)V
    //   196: aload #6
    //   198: aconst_null
    //   199: invokevirtual get : (Ljava/lang/Object;)Ljava/lang/Object;
    //   202: pop
    //   203: iinc #5, 1
    //   206: iload_2
    //   207: ifeq -> 69
    //   210: sipush #-10323
    //   213: sipush #16750
    //   216: invokestatic a : (II)Ljava/lang/String;
    //   219: invokestatic forName : (Ljava/lang/String;)Ljava/lang/Class;
    //   222: invokevirtual getDeclaredMethods : ()[Ljava/lang/reflect/Method;
    //   225: astore_3
    //   226: aload_3
    //   227: arraylength
    //   228: istore #4
    //   230: iconst_0
    //   231: istore #5
    //   233: iload #5
    //   235: iload #4
    //   237: if_icmpge -> 348
    //   240: aload_3
    //   241: iload #5
    //   243: aaload
    //   244: astore #6
    //   246: aload #6
    //   248: invokevirtual getParameterTypes : ()[Ljava/lang/Class;
    //   251: pop
    //   252: aload #6
    //   254: invokevirtual getModifiers : ()I
    //   257: invokestatic isStatic : (I)Z
    //   260: ifeq -> 334
    //   263: aload #6
    //   265: invokevirtual getParameterTypes : ()[Ljava/lang/Class;
    //   268: arraylength
    //   269: iconst_2
    //   270: if_icmpne -> 334
    //   273: goto -> 280
    //   276: invokestatic a : (Ljava/lang/Throwable;)Ljava/lang/Throwable;
    //   279: athrow
    //   280: aload #6
    //   282: invokevirtual getReturnType : ()Ljava/lang/Class;
    //   285: getstatic java/lang/Boolean.TYPE : Ljava/lang/Class;
    //   288: if_acmpne -> 334
    //   291: goto -> 298
    //   294: invokestatic a : (Ljava/lang/Throwable;)Ljava/lang/Throwable;
    //   297: athrow
    //   298: aload #6
    //   300: iconst_1
    //   301: invokevirtual setAccessible : (Z)V
    //   304: aload #6
    //   306: aconst_null
    //   307: iconst_2
    //   308: anewarray java/lang/Object
    //   311: dup
    //   312: iconst_0
    //   313: aload_0
    //   314: aastore
    //   315: dup
    //   316: iconst_1
    //   317: aload_1
    //   318: aastore
    //   319: invokevirtual invoke : (Ljava/lang/Object;[Ljava/lang/Object;)Ljava/lang/Object;
    //   322: pop
    //   323: iload_2
    //   324: ifeq -> 348
    //   327: goto -> 334
    //   330: invokestatic a : (Ljava/lang/Throwable;)Ljava/lang/Throwable;
    //   333: athrow
    //   334: iinc #5, 1
    //   337: iload_2
    //   338: ifeq -> 233
    //   341: goto -> 348
    //   344: invokestatic a : (Ljava/lang/Throwable;)Ljava/lang/Throwable;
    //   347: athrow
    //   348: sipush #-10325
    //   351: sipush #-300
    //   354: invokestatic a : (II)Ljava/lang/String;
    //   357: iconst_1
    //   358: ldc burp/Zg1l
    //   360: invokevirtual getClassLoader : ()Ljava/lang/ClassLoader;
    //   363: invokestatic forName : (Ljava/lang/String;ZLjava/lang/ClassLoader;)Ljava/lang/Class;
    //   366: invokevirtual getDeclaredFields : ()[Ljava/lang/reflect/Field;
    //   369: astore_3
    //   370: aload_3
    //   371: arraylength
    //   372: istore #4
    //   374: iconst_0
    //   375: istore #5
    //   377: iload #5
    //   379: iload #4
    //   381: if_icmpge -> 518
    //   384: aload_3
    //   385: iload #5
    //   387: aaload
    //   388: astore #6
    //   390: aload #6
    //   392: invokevirtual getModifiers : ()I
    //   395: invokestatic isStatic : (I)Z
    //   398: ifne -> 408
    //   401: goto -> 511
    //   404: invokestatic a : (Ljava/lang/Throwable;)Ljava/lang/Throwable;
    //   407: athrow
    //   408: aload #6
    //   410: invokevirtual getType : ()Ljava/lang/Class;
    //   413: astore #7
    //   415: aload #7
    //   417: ifnull -> 498
    //   420: aload #7
    //   422: invokevirtual isPrimitive : ()Z
    //   425: ifne -> 498
    //   428: goto -> 435
    //   431: invokestatic a : (Ljava/lang/Throwable;)Ljava/lang/Throwable;
    //   434: athrow
    //   435: aload #7
    //   437: invokevirtual getPackage : ()Ljava/lang/Package;
    //   440: ifnull -> 498
    //   443: goto -> 450
    //   446: invokestatic a : (Ljava/lang/Throwable;)Ljava/lang/Throwable;
    //   449: athrow
    //   450: aload #7
    //   452: invokevirtual getPackage : ()Ljava/lang/Package;
    //   455: invokevirtual getName : ()Ljava/lang/String;
    //   458: ifnull -> 498
    //   461: goto -> 468
    //   464: invokestatic a : (Ljava/lang/Throwable;)Ljava/lang/Throwable;
    //   467: athrow
    //   468: aload #7
    //   470: invokevirtual getPackage : ()Ljava/lang/Package;
    //   473: invokevirtual getName : ()Ljava/lang/String;
    //   476: sipush #-10333
    //   479: sipush #-11347
    //   482: invokestatic a : (II)Ljava/lang/String;
    //   485: invokevirtual startsWith : (Ljava/lang/String;)Z
    //   488: ifne -> 498
    //   491: goto -> 498
    //   494: invokestatic a : (Ljava/lang/Throwable;)Ljava/lang/Throwable;
    //   497: athrow
    //   498: aload #6
    //   500: iconst_1
    //   501: invokevirtual setAccessible : (Z)V
    //   504: aload #6
    //   506: aconst_null
    //   507: invokevirtual get : (Ljava/lang/Object;)Ljava/lang/Object;
    //   510: pop
    //   511: iinc #5, 1
    //   514: iload_2
    //   515: ifeq -> 377
    //   518: sipush #-10321
    //   521: sipush #-6517
    //   524: invokestatic a : (II)Ljava/lang/String;
    //   527: invokestatic forName : (Ljava/lang/String;)Ljava/lang/Class;
    //   530: invokevirtual getDeclaredMethods : ()[Ljava/lang/reflect/Method;
    //   533: astore_3
    //   534: aload_3
    //   535: arraylength
    //   536: istore #4
    //   538: iconst_0
    //   539: istore #5
    //   541: iload #5
    //   543: iload #4
    //   545: if_icmpge -> 674
    //   548: aload_3
    //   549: iload #5
    //   551: aaload
    //   552: astore #6
    //   554: aload #6
    //   556: invokevirtual getParameterTypes : ()[Ljava/lang/Class;
    //   559: pop
    //   560: aload #6
    //   562: invokevirtual getModifiers : ()I
    //   565: invokestatic isStatic : (I)Z
    //   568: ifeq -> 660
    //   571: aload #6
    //   573: invokevirtual getParameterTypes : ()[Ljava/lang/Class;
    //   576: arraylength
    //   577: iconst_2
    //   578: if_icmpne -> 660
    //   581: goto -> 588
    //   584: invokestatic a : (Ljava/lang/Throwable;)Ljava/lang/Throwable;
    //   587: athrow
    //   588: aload #6
    //   590: invokevirtual getReturnType : ()Ljava/lang/Class;
    //   593: getstatic java/lang/Boolean.TYPE : Ljava/lang/Class;
    //   596: if_acmpne -> 660
    //   599: goto -> 606
    //   602: invokestatic a : (Ljava/lang/Throwable;)Ljava/lang/Throwable;
    //   605: athrow
    //   606: aload #6
    //   608: iconst_1
    //   609: invokevirtual setAccessible : (Z)V
    //   612: aload #6
    //   614: aconst_null
    //   615: iconst_2
    //   616: anewarray java/lang/Object
    //   619: dup
    //   620: iconst_0
    //   621: aload_0
    //   622: aastore
    //   623: dup
    //   624: iconst_1
    //   625: aload_1
    //   626: ifnonnull -> 644
    //   629: goto -> 636
    //   632: invokestatic a : (Ljava/lang/Throwable;)Ljava/lang/Throwable;
    //   635: athrow
    //   636: aload_1
    //   637: goto -> 651
    //   640: invokestatic a : (Ljava/lang/Throwable;)Ljava/lang/Throwable;
    //   643: athrow
    //   644: aload_1
    //   645: checkcast [B
    //   648: invokevirtual clone : ()Ljava/lang/Object;
    //   651: aastore
    //   652: invokevirtual invoke : (Ljava/lang/Object;[Ljava/lang/Object;)Ljava/lang/Object;
    //   655: pop
    //   656: iload_2
    //   657: ifeq -> 674
    //   660: iinc #5, 1
    //   663: iload_2
    //   664: ifeq -> 541
    //   667: goto -> 674
    //   670: invokestatic a : (Ljava/lang/Throwable;)Ljava/lang/Throwable;
    //   673: athrow
    //   674: sipush #-10335
    //   677: sipush #7871
    //   680: invokestatic a : (II)Ljava/lang/String;
    //   683: iconst_1
    //   684: ldc burp/Zb38
    //   686: invokevirtual getClassLoader : ()Ljava/lang/ClassLoader;
    //   689: invokestatic forName : (Ljava/lang/String;ZLjava/lang/ClassLoader;)Ljava/lang/Class;
    //   692: invokevirtual getDeclaredFields : ()[Ljava/lang/reflect/Field;
    //   695: astore_3
    //   696: aload_3
    //   697: arraylength
    //   698: istore #4
    //   700: iconst_0
    //   701: istore #5
    //   703: iload #5
    //   705: iload #4
    //   707: if_icmpge -> 844
    //   710: aload_3
    //   711: iload #5
    //   713: aaload
    //   714: astore #6
    //   716: aload #6
    //   718: invokevirtual getModifiers : ()I
    //   721: invokestatic isStatic : (I)Z
    //   724: ifne -> 734
    //   727: goto -> 837
    //   730: invokestatic a : (Ljava/lang/Throwable;)Ljava/lang/Throwable;
    //   733: athrow
    //   734: aload #6
    //   736: invokevirtual getType : ()Ljava/lang/Class;
    //   739: astore #7
    //   741: aload #7
    //   743: ifnull -> 824
    //   746: aload #7
    //   748: invokevirtual isPrimitive : ()Z
    //   751: ifne -> 824
    //   754: goto -> 761
    //   757: invokestatic a : (Ljava/lang/Throwable;)Ljava/lang/Throwable;
    //   760: athrow
    //   761: aload #7
    //   763: invokevirtual getPackage : ()Ljava/lang/Package;
    //   766: ifnull -> 824
    //   769: goto -> 776
    //   772: invokestatic a : (Ljava/lang/Throwable;)Ljava/lang/Throwable;
    //   775: athrow
    //   776: aload #7
    //   778: invokevirtual getPackage : ()Ljava/lang/Package;
    //   781: invokevirtual getName : ()Ljava/lang/String;
    //   784: ifnull -> 824
    //   787: goto -> 794
    //   790: invokestatic a : (Ljava/lang/Throwable;)Ljava/lang/Throwable;
    //   793: athrow
    //   794: aload #7
    //   796: invokevirtual getPackage : ()Ljava/lang/Package;
    //   799: invokevirtual getName : ()Ljava/lang/String;
    //   802: sipush #-10333
    //   805: sipush #-11347
    //   808: invokestatic a : (II)Ljava/lang/String;
    //   811: invokevirtual startsWith : (Ljava/lang/String;)Z
    //   814: ifne -> 824
    //   817: goto -> 824
    //   820: invokestatic a : (Ljava/lang/Throwable;)Ljava/lang/Throwable;
    //   823: athrow
    //   824: aload #6
    //   826: iconst_1
    //   827: invokevirtual setAccessible : (Z)V
    //   830: aload #6
    //   832: aconst_null
    //   833: invokevirtual get : (Ljava/lang/Object;)Ljava/lang/Object;
    //   836: pop
    //   837: iinc #5, 1
    //   840: iload_2
    //   841: ifeq -> 703
    //   844: sipush #-10329
    //   847: sipush #1978
    //   850: invokestatic a : (II)Ljava/lang/String;
    //   853: invokestatic forName : (Ljava/lang/String;)Ljava/lang/Class;
    //   856: invokevirtual getDeclaredMethods : ()[Ljava/lang/reflect/Method;
    //   859: astore_3
    //   860: aload_3
    //   861: arraylength
    //   862: istore #4
    //   864: iconst_0
    //   865: istore #5
    //   867: iload #5
    //   869: iload #4
    //   871: if_icmpge -> 1003
    //   874: aload_3
    //   875: iload #5
    //   877: aaload
    //   878: astore #6
    //   880: aload #6
    //   882: invokevirtual getParameterTypes : ()[Ljava/lang/Class;
    //   885: pop
    //   886: aload #6
    //   888: invokevirtual getModifiers : ()I
    //   891: invokestatic isStatic : (I)Z
    //   894: ifeq -> 989
    //   897: aload #6
    //   899: invokevirtual getParameterTypes : ()[Ljava/lang/Class;
    //   902: arraylength
    //   903: iconst_2
    //   904: if_icmpne -> 989
    //   907: goto -> 914
    //   910: invokestatic a : (Ljava/lang/Throwable;)Ljava/lang/Throwable;
    //   913: athrow
    //   914: aload #6
    //   916: invokevirtual getReturnType : ()Ljava/lang/Class;
    //   919: getstatic java/lang/Void.TYPE : Ljava/lang/Class;
    //   922: invokevirtual equals : (Ljava/lang/Object;)Z
    //   925: ifeq -> 989
    //   928: goto -> 935
    //   931: invokestatic a : (Ljava/lang/Throwable;)Ljava/lang/Throwable;
    //   934: athrow
    //   935: aload #6
    //   937: iconst_1
    //   938: invokevirtual setAccessible : (Z)V
    //   941: aload #6
    //   943: aconst_null
    //   944: iconst_2
    //   945: anewarray java/lang/Object
    //   948: dup
    //   949: iconst_0
    //   950: aload_0
    //   951: aastore
    //   952: dup
    //   953: iconst_1
    //   954: aload_1
    //   955: ifnonnull -> 973
    //   958: goto -> 965
    //   961: invokestatic a : (Ljava/lang/Throwable;)Ljava/lang/Throwable;
    //   964: athrow
    //   965: aload_1
    //   966: goto -> 980
    //   969: invokestatic a : (Ljava/lang/Throwable;)Ljava/lang/Throwable;
    //   972: athrow
    //   973: aload_1
    //   974: checkcast [B
    //   977: invokevirtual clone : ()Ljava/lang/Object;
    //   980: aastore
    //   981: invokevirtual invoke : (Ljava/lang/Object;[Ljava/lang/Object;)Ljava/lang/Object;
    //   984: pop
    //   985: iload_2
    //   986: ifeq -> 1003
    //   989: iinc #5, 1
    //   992: iload_2
    //   993: ifeq -> 867
    //   996: goto -> 1003
    //   999: invokestatic a : (Ljava/lang/Throwable;)Ljava/lang/Throwable;
    //   1002: athrow
    //   1003: new java/io/ByteArrayOutputStream
    //   1006: dup
    //   1007: invokespecial <init> : ()V
    //   1010: astore_3
    //   1011: getstatic burp/Zb2k.Zu : Ljava/lang/String;
    //   1014: astore #4
    //   1016: iconst_0
    //   1017: istore #5
    //   1019: iload #5
    //   1021: aload #4
    //   1023: invokevirtual length : ()I
    //   1026: if_icmpge -> 1056
    //   1029: aload_3
    //   1030: aload #4
    //   1032: iload #5
    //   1034: iload #5
    //   1036: iconst_2
    //   1037: iadd
    //   1038: invokevirtual substring : (II)Ljava/lang/String;
    //   1041: bipush #16
    //   1043: invokestatic parseInt : (Ljava/lang/String;I)I
    //   1046: invokevirtual write : (I)V
    //   1049: iinc #5, 2
    //   1052: iload_2
    //   1053: ifeq -> 1019
    //   1056: aload_3
    //   1057: invokevirtual toByteArray : ()[B
    //   1060: astore #5
    //   1062: getstatic burp/Zlav.Zp : Ljava/lang/Object;
    //   1065: checkcast java/math/BigInteger
    //   1068: invokevirtual toByteArray : ()[B
    //   1071: astore #6
    //   1073: sipush #256
    //   1076: newarray byte
    //   1078: astore #8
    //   1080: sipush #256
    //   1083: newarray int
    //   1085: astore #9
    //   1087: sipush #256
    //   1090: newarray int
    //   1092: astore #10
    //   1094: sipush #256
    //   1097: newarray int
    //   1099: astore #11
    //   1101: sipush #256
    //   1104: newarray int
    //   1106: astore #12
    //   1108: bipush #10
    //   1110: newarray int
    //   1112: astore #13
    //   1114: sipush #283
    //   1117: istore #14
    //   1119: iconst_0
    //   1120: istore #16
    //   1122: iload #16
    //   1124: sipush #256
    //   1127: if_icmpge -> 1361
    //   1130: sipush #-10322
    //   1133: sipush #-30799
    //   1136: invokestatic a : (II)Ljava/lang/String;
    //   1139: iload #16
    //   1141: iconst_1
    //   1142: iushr
    //   1143: invokevirtual charAt : (I)C
    //   1146: istore #25
    //   1148: iload #16
    //   1150: iconst_1
    //   1151: iand
    //   1152: ifne -> 1167
    //   1155: iload #25
    //   1157: bipush #8
    //   1159: iushr
    //   1160: goto -> 1169
    //   1163: invokestatic a : (Ljava/lang/Throwable;)Ljava/lang/Throwable;
    //   1166: athrow
    //   1167: iload #25
    //   1169: i2b
    //   1170: sipush #255
    //   1173: iand
    //   1174: istore #15
    //   1176: iload #16
    //   1178: iconst_1
    //   1179: ishl
    //   1180: istore #17
    //   1182: iload #17
    //   1184: sipush #256
    //   1187: if_icmplt -> 1197
    //   1190: iload #17
    //   1192: iload #14
    //   1194: ixor
    //   1195: istore #17
    //   1197: iload #17
    //   1199: iconst_1
    //   1200: ishl
    //   1201: istore #18
    //   1203: iload #18
    //   1205: sipush #256
    //   1208: if_icmplt -> 1218
    //   1211: iload #18
    //   1213: iload #14
    //   1215: ixor
    //   1216: istore #18
    //   1218: iload #18
    //   1220: iconst_1
    //   1221: ishl
    //   1222: istore #19
    //   1224: iload #19
    //   1226: sipush #256
    //   1229: if_icmplt -> 1239
    //   1232: iload #19
    //   1234: iload #14
    //   1236: ixor
    //   1237: istore #19
    //   1239: iload #19
    //   1241: iload #16
    //   1243: ixor
    //   1244: istore #20
    //   1246: iload #20
    //   1248: iload #17
    //   1250: ixor
    //   1251: istore #21
    //   1253: iload #20
    //   1255: iload #18
    //   1257: ixor
    //   1258: istore #22
    //   1260: iload #19
    //   1262: iload #18
    //   1264: ixor
    //   1265: iload #17
    //   1267: ixor
    //   1268: istore #23
    //   1270: aload #8
    //   1272: iload #16
    //   1274: iload #15
    //   1276: i2b
    //   1277: bastore
    //   1278: aload #9
    //   1280: iload #15
    //   1282: iload #23
    //   1284: bipush #24
    //   1286: ishl
    //   1287: iload #20
    //   1289: bipush #16
    //   1291: ishl
    //   1292: ior
    //   1293: iload #22
    //   1295: bipush #8
    //   1297: ishl
    //   1298: ior
    //   1299: iload #21
    //   1301: ior
    //   1302: dup
    //   1303: istore #24
    //   1305: iastore
    //   1306: aload #10
    //   1308: iload #15
    //   1310: iload #24
    //   1312: bipush #8
    //   1314: iushr
    //   1315: iload #24
    //   1317: bipush #24
    //   1319: ishl
    //   1320: ior
    //   1321: iastore
    //   1322: aload #11
    //   1324: iload #15
    //   1326: iload #24
    //   1328: bipush #16
    //   1330: iushr
    //   1331: iload #24
    //   1333: bipush #16
    //   1335: ishl
    //   1336: ior
    //   1337: iastore
    //   1338: aload #12
    //   1340: iload #15
    //   1342: iload #24
    //   1344: bipush #24
    //   1346: iushr
    //   1347: iload #24
    //   1349: bipush #8
    //   1351: ishl
    //   1352: ior
    //   1353: iastore
    //   1354: iinc #16, 1
    //   1357: iload_2
    //   1358: ifeq -> 1122
    //   1361: iconst_1
    //   1362: istore #25
    //   1364: aload #13
    //   1366: iconst_0
    //   1367: iload #25
    //   1369: bipush #24
    //   1371: ishl
    //   1372: iastore
    //   1373: iconst_1
    //   1374: istore #26
    //   1376: iload #26
    //   1378: bipush #10
    //   1380: if_icmpge -> 1421
    //   1383: iload #25
    //   1385: iconst_1
    //   1386: ishl
    //   1387: istore #25
    //   1389: iload #25
    //   1391: sipush #256
    //   1394: if_icmplt -> 1404
    //   1397: iload #25
    //   1399: iload #14
    //   1401: ixor
    //   1402: istore #25
    //   1404: aload #13
    //   1406: iload #26
    //   1408: iload #25
    //   1410: bipush #24
    //   1412: ishl
    //   1413: iastore
    //   1414: iinc #26, 1
    //   1417: iload_2
    //   1418: ifeq -> 1376
    //   1421: iconst_4
    //   1422: istore #26
    //   1424: iload #26
    //   1426: bipush #6
    //   1428: iadd
    //   1429: istore #27
    //   1431: iconst_4
    //   1432: iload #27
    //   1434: iconst_1
    //   1435: iadd
    //   1436: imul
    //   1437: istore #28
    //   1439: iload #28
    //   1441: newarray int
    //   1443: astore #29
    //   1445: iload #28
    //   1447: newarray int
    //   1449: astore #30
    //   1451: iconst_0
    //   1452: istore #25
    //   1454: iconst_0
    //   1455: istore #32
    //   1457: iconst_0
    //   1458: istore #33
    //   1460: iload #32
    //   1462: iload #26
    //   1464: if_icmpge -> 1532
    //   1467: aload #29
    //   1469: iload #32
    //   1471: aload #5
    //   1473: iload #33
    //   1475: baload
    //   1476: bipush #24
    //   1478: ishl
    //   1479: aload #5
    //   1481: iload #33
    //   1483: iconst_1
    //   1484: iadd
    //   1485: baload
    //   1486: sipush #255
    //   1489: iand
    //   1490: bipush #16
    //   1492: ishl
    //   1493: ior
    //   1494: aload #5
    //   1496: iload #33
    //   1498: iconst_2
    //   1499: iadd
    //   1500: baload
    //   1501: sipush #255
    //   1504: iand
    //   1505: bipush #8
    //   1507: ishl
    //   1508: ior
    //   1509: aload #5
    //   1511: iload #33
    //   1513: iconst_3
    //   1514: iadd
    //   1515: baload
    //   1516: sipush #255
    //   1519: iand
    //   1520: ior
    //   1521: iastore
    //   1522: iinc #32, 1
    //   1525: iinc #33, 4
    //   1528: iload_2
    //   1529: ifeq -> 1460
    //   1532: iload #26
    //   1534: istore #32
    //   1536: iconst_0
    //   1537: istore #33
    //   1539: iload #32
    //   1541: iload #28
    //   1543: if_icmpge -> 1670
    //   1546: aload #29
    //   1548: iload #32
    //   1550: iconst_1
    //   1551: isub
    //   1552: iaload
    //   1553: istore #31
    //   1555: iload #33
    //   1557: ifne -> 1644
    //   1560: iload #26
    //   1562: istore #33
    //   1564: aload #8
    //   1566: iload #31
    //   1568: bipush #16
    //   1570: iushr
    //   1571: sipush #255
    //   1574: iand
    //   1575: baload
    //   1576: bipush #24
    //   1578: ishl
    //   1579: aload #8
    //   1581: iload #31
    //   1583: bipush #8
    //   1585: iushr
    //   1586: sipush #255
    //   1589: iand
    //   1590: baload
    //   1591: sipush #255
    //   1594: iand
    //   1595: bipush #16
    //   1597: ishl
    //   1598: ior
    //   1599: aload #8
    //   1601: iload #31
    //   1603: sipush #255
    //   1606: iand
    //   1607: baload
    //   1608: sipush #255
    //   1611: iand
    //   1612: bipush #8
    //   1614: ishl
    //   1615: ior
    //   1616: aload #8
    //   1618: iload #31
    //   1620: bipush #24
    //   1622: iushr
    //   1623: baload
    //   1624: sipush #255
    //   1627: iand
    //   1628: ior
    //   1629: istore #31
    //   1631: iload #31
    //   1633: aload #13
    //   1635: iload #25
    //   1637: iinc #25, 1
    //   1640: iaload
    //   1641: ixor
    //   1642: istore #31
    //   1644: aload #29
    //   1646: iload #32
    //   1648: aload #29
    //   1650: iload #32
    //   1652: iload #26
    //   1654: isub
    //   1655: iaload
    //   1656: iload #31
    //   1658: ixor
    //   1659: iastore
    //   1660: iinc #32, 1
    //   1663: iinc #33, -1
    //   1666: iload_2
    //   1667: ifeq -> 1539
    //   1670: iconst_0
    //   1671: istore #32
    //   1673: iconst_4
    //   1674: iload #27
    //   1676: imul
    //   1677: istore #33
    //   1679: aload #30
    //   1681: iload #32
    //   1683: aload #29
    //   1685: iload #33
    //   1687: iaload
    //   1688: iastore
    //   1689: aload #30
    //   1691: iload #32
    //   1693: iconst_1
    //   1694: iadd
    //   1695: aload #29
    //   1697: iload #33
    //   1699: iconst_1
    //   1700: iadd
    //   1701: iaload
    //   1702: iastore
    //   1703: aload #30
    //   1705: iload #32
    //   1707: iconst_2
    //   1708: iadd
    //   1709: aload #29
    //   1711: iload #33
    //   1713: iconst_2
    //   1714: iadd
    //   1715: iaload
    //   1716: iastore
    //   1717: aload #30
    //   1719: iload #32
    //   1721: iconst_3
    //   1722: iadd
    //   1723: aload #29
    //   1725: iload #33
    //   1727: iconst_3
    //   1728: iadd
    //   1729: iaload
    //   1730: iastore
    //   1731: iinc #32, 4
    //   1734: iinc #33, -4
    //   1737: iconst_1
    //   1738: istore #35
    //   1740: iload #35
    //   1742: iload #27
    //   1744: if_icmpge -> 2108
    //   1747: aload #29
    //   1749: iload #33
    //   1751: iaload
    //   1752: istore #34
    //   1754: aload #30
    //   1756: iload #32
    //   1758: aload #9
    //   1760: aload #8
    //   1762: iload #34
    //   1764: bipush #24
    //   1766: iushr
    //   1767: baload
    //   1768: sipush #255
    //   1771: iand
    //   1772: iaload
    //   1773: aload #10
    //   1775: aload #8
    //   1777: iload #34
    //   1779: bipush #16
    //   1781: iushr
    //   1782: sipush #255
    //   1785: iand
    //   1786: baload
    //   1787: sipush #255
    //   1790: iand
    //   1791: iaload
    //   1792: ixor
    //   1793: aload #11
    //   1795: aload #8
    //   1797: iload #34
    //   1799: bipush #8
    //   1801: iushr
    //   1802: sipush #255
    //   1805: iand
    //   1806: baload
    //   1807: sipush #255
    //   1810: iand
    //   1811: iaload
    //   1812: ixor
    //   1813: aload #12
    //   1815: aload #8
    //   1817: iload #34
    //   1819: sipush #255
    //   1822: iand
    //   1823: baload
    //   1824: sipush #255
    //   1827: iand
    //   1828: iaload
    //   1829: ixor
    //   1830: iastore
    //   1831: aload #29
    //   1833: iload #33
    //   1835: iconst_1
    //   1836: iadd
    //   1837: iaload
    //   1838: istore #34
    //   1840: aload #30
    //   1842: iload #32
    //   1844: iconst_1
    //   1845: iadd
    //   1846: aload #9
    //   1848: aload #8
    //   1850: iload #34
    //   1852: bipush #24
    //   1854: iushr
    //   1855: baload
    //   1856: sipush #255
    //   1859: iand
    //   1860: iaload
    //   1861: aload #10
    //   1863: aload #8
    //   1865: iload #34
    //   1867: bipush #16
    //   1869: iushr
    //   1870: sipush #255
    //   1873: iand
    //   1874: baload
    //   1875: sipush #255
    //   1878: iand
    //   1879: iaload
    //   1880: ixor
    //   1881: aload #11
    //   1883: aload #8
    //   1885: iload #34
    //   1887: bipush #8
    //   1889: iushr
    //   1890: sipush #255
    //   1893: iand
    //   1894: baload
    //   1895: sipush #255
    //   1898: iand
    //   1899: iaload
    //   1900: ixor
    //   1901: aload #12
    //   1903: aload #8
    //   1905: iload #34
    //   1907: sipush #255
    //   1910: iand
    //   1911: baload
    //   1912: sipush #255
    //   1915: iand
    //   1916: iaload
    //   1917: ixor
    //   1918: iastore
    //   1919: aload #29
    //   1921: iload #33
    //   1923: iconst_2
    //   1924: iadd
    //   1925: iaload
    //   1926: istore #34
    //   1928: aload #30
    //   1930: iload #32
    //   1932: iconst_2
    //   1933: iadd
    //   1934: aload #9
    //   1936: aload #8
    //   1938: iload #34
    //   1940: bipush #24
    //   1942: iushr
    //   1943: baload
    //   1944: sipush #255
    //   1947: iand
    //   1948: iaload
    //   1949: aload #10
    //   1951: aload #8
    //   1953: iload #34
    //   1955: bipush #16
    //   1957: iushr
    //   1958: sipush #255
    //   1961: iand
    //   1962: baload
    //   1963: sipush #255
    //   1966: iand
    //   1967: iaload
    //   1968: ixor
    //   1969: aload #11
    //   1971: aload #8
    //   1973: iload #34
    //   1975: bipush #8
    //   1977: iushr
    //   1978: sipush #255
    //   1981: iand
    //   1982: baload
    //   1983: sipush #255
    //   1986: iand
    //   1987: iaload
    //   1988: ixor
    //   1989: aload #12
    //   1991: aload #8
    //   1993: iload #34
    //   1995: sipush #255
    //   1998: iand
    //   1999: baload
    //   2000: sipush #255
    //   2003: iand
    //   2004: iaload
    //   2005: ixor
    //   2006: iastore
    //   2007: aload #29
    //   2009: iload #33
    //   2011: iconst_3
    //   2012: iadd
    //   2013: iaload
    //   2014: istore #34
    //   2016: aload #30
    //   2018: iload #32
    //   2020: iconst_3
    //   2021: iadd
    //   2022: aload #9
    //   2024: aload #8
    //   2026: iload #34
    //   2028: bipush #24
    //   2030: iushr
    //   2031: baload
    //   2032: sipush #255
    //   2035: iand
    //   2036: iaload
    //   2037: aload #10
    //   2039: aload #8
    //   2041: iload #34
    //   2043: bipush #16
    //   2045: iushr
    //   2046: sipush #255
    //   2049: iand
    //   2050: baload
    //   2051: sipush #255
    //   2054: iand
    //   2055: iaload
    //   2056: ixor
    //   2057: aload #11
    //   2059: aload #8
    //   2061: iload #34
    //   2063: bipush #8
    //   2065: iushr
    //   2066: sipush #255
    //   2069: iand
    //   2070: baload
    //   2071: sipush #255
    //   2074: iand
    //   2075: iaload
    //   2076: ixor
    //   2077: aload #12
    //   2079: aload #8
    //   2081: iload #34
    //   2083: sipush #255
    //   2086: iand
    //   2087: baload
    //   2088: sipush #255
    //   2091: iand
    //   2092: iaload
    //   2093: ixor
    //   2094: iastore
    //   2095: iinc #32, 4
    //   2098: iinc #33, -4
    //   2101: iinc #35, 1
    //   2104: iload_2
    //   2105: ifeq -> 1740
    //   2108: aload #30
    //   2110: iload #32
    //   2112: aload #29
    //   2114: iload #33
    //   2116: iaload
    //   2117: iastore
    //   2118: aload #30
    //   2120: iload #32
    //   2122: iconst_1
    //   2123: iadd
    //   2124: aload #29
    //   2126: iload #33
    //   2128: iconst_1
    //   2129: iadd
    //   2130: iaload
    //   2131: iastore
    //   2132: aload #30
    //   2134: iload #32
    //   2136: iconst_2
    //   2137: iadd
    //   2138: aload #29
    //   2140: iload #33
    //   2142: iconst_2
    //   2143: iadd
    //   2144: iaload
    //   2145: iastore
    //   2146: aload #30
    //   2148: iload #32
    //   2150: iconst_3
    //   2151: iadd
    //   2152: aload #29
    //   2154: iload #33
    //   2156: iconst_3
    //   2157: iadd
    //   2158: iaload
    //   2159: iastore
    //   2160: iconst_0
    //   2161: newarray byte
    //   2163: astore #35
    //   2165: aload #6
    //   2167: arraylength
    //   2168: bipush #16
    //   2170: irem
    //   2171: ifeq -> 2195
    //   2174: new java/lang/Exception
    //   2177: dup
    //   2178: sipush #-10336
    //   2181: sipush #5674
    //   2184: invokestatic a : (II)Ljava/lang/String;
    //   2187: invokespecial <init> : (Ljava/lang/String;)V
    //   2190: athrow
    //   2191: invokestatic a : (Ljava/lang/Throwable;)Ljava/lang/Throwable;
    //   2194: athrow
    //   2195: bipush #10
    //   2197: istore #36
    //   2199: sipush #-10326
    //   2202: sipush #256
    //   2205: newarray byte
    //   2207: astore #37
    //   2209: sipush #22908
    //   2212: sipush #256
    //   2215: newarray int
    //   2217: astore #38
    //   2219: sipush #256
    //   2222: newarray int
    //   2224: astore #39
    //   2226: sipush #256
    //   2229: newarray int
    //   2231: astore #40
    //   2233: sipush #256
    //   2236: newarray int
    //   2238: astore #41
    //   2240: sipush #283
    //   2243: istore #14
    //   2245: invokestatic a : (II)Ljava/lang/String;
    //   2248: astore #42
    //   2250: iconst_0
    //   2251: istore #16
    //   2253: iload #16
    //   2255: sipush #256
    //   2258: if_icmpge -> 2485
    //   2261: aload #42
    //   2263: iload #16
    //   2265: iconst_1
    //   2266: iushr
    //   2267: invokevirtual charAt : (I)C
    //   2270: istore #43
    //   2272: iload #16
    //   2274: iconst_1
    //   2275: iand
    //   2276: ifne -> 2291
    //   2279: iload #43
    //   2281: bipush #8
    //   2283: iushr
    //   2284: goto -> 2293
    //   2287: invokestatic a : (Ljava/lang/Throwable;)Ljava/lang/Throwable;
    //   2290: athrow
    //   2291: iload #43
    //   2293: i2b
    //   2294: sipush #255
    //   2297: iand
    //   2298: istore #15
    //   2300: iload #16
    //   2302: iconst_1
    //   2303: ishl
    //   2304: istore #17
    //   2306: iload #17
    //   2308: sipush #256
    //   2311: if_icmplt -> 2321
    //   2314: iload #17
    //   2316: iload #14
    //   2318: ixor
    //   2319: istore #17
    //   2321: iload #17
    //   2323: iconst_1
    //   2324: ishl
    //   2325: istore #18
    //   2327: iload #18
    //   2329: sipush #256
    //   2332: if_icmplt -> 2342
    //   2335: iload #18
    //   2337: iload #14
    //   2339: ixor
    //   2340: istore #18
    //   2342: iload #18
    //   2344: iconst_1
    //   2345: ishl
    //   2346: istore #19
    //   2348: iload #19
    //   2350: sipush #256
    //   2353: if_icmplt -> 2363
    //   2356: iload #19
    //   2358: iload #14
    //   2360: ixor
    //   2361: istore #19
    //   2363: iload #19
    //   2365: iload #16
    //   2367: ixor
    //   2368: istore #20
    //   2370: iload #20
    //   2372: iload #17
    //   2374: ixor
    //   2375: istore #21
    //   2377: iload #20
    //   2379: iload #18
    //   2381: ixor
    //   2382: istore #22
    //   2384: iload #19
    //   2386: iload #18
    //   2388: ixor
    //   2389: iload #17
    //   2391: ixor
    //   2392: istore #23
    //   2394: aload #37
    //   2396: iload #15
    //   2398: iload #16
    //   2400: i2b
    //   2401: bastore
    //   2402: aload #38
    //   2404: iload #15
    //   2406: iload #23
    //   2408: bipush #24
    //   2410: ishl
    //   2411: iload #20
    //   2413: bipush #16
    //   2415: ishl
    //   2416: ior
    //   2417: iload #22
    //   2419: bipush #8
    //   2421: ishl
    //   2422: ior
    //   2423: iload #21
    //   2425: ior
    //   2426: dup
    //   2427: istore #24
    //   2429: iastore
    //   2430: aload #39
    //   2432: iload #15
    //   2434: iload #24
    //   2436: bipush #8
    //   2438: iushr
    //   2439: iload #24
    //   2441: bipush #24
    //   2443: ishl
    //   2444: ior
    //   2445: iastore
    //   2446: aload #40
    //   2448: iload #15
    //   2450: iload #24
    //   2452: bipush #16
    //   2454: iushr
    //   2455: iload #24
    //   2457: bipush #16
    //   2459: ishl
    //   2460: ior
    //   2461: iastore
    //   2462: aload #41
    //   2464: iload #15
    //   2466: iload #24
    //   2468: bipush #24
    //   2470: iushr
    //   2471: iload #24
    //   2473: bipush #8
    //   2475: ishl
    //   2476: ior
    //   2477: iastore
    //   2478: iinc #16, 1
    //   2481: iload_2
    //   2482: ifeq -> 2253
    //   2485: aload #6
    //   2487: arraylength
    //   2488: newarray byte
    //   2490: astore #43
    //   2492: iconst_0
    //   2493: istore #44
    //   2495: iload #44
    //   2497: aload #6
    //   2499: arraylength
    //   2500: bipush #16
    //   2502: idiv
    //   2503: if_icmpge -> 3417
    //   2506: bipush #16
    //   2508: newarray byte
    //   2510: astore #45
    //   2512: bipush #16
    //   2514: newarray byte
    //   2516: astore #46
    //   2518: iconst_0
    //   2519: istore #47
    //   2521: iload #47
    //   2523: bipush #16
    //   2525: if_icmpge -> 2551
    //   2528: aload #45
    //   2530: iload #47
    //   2532: aload #6
    //   2534: iload #47
    //   2536: iload #44
    //   2538: bipush #16
    //   2540: imul
    //   2541: iadd
    //   2542: baload
    //   2543: bastore
    //   2544: iinc #47, 1
    //   2547: iload_2
    //   2548: ifeq -> 2521
    //   2551: iconst_0
    //   2552: istore #47
    //   2554: aload #45
    //   2556: iconst_0
    //   2557: baload
    //   2558: bipush #24
    //   2560: ishl
    //   2561: aload #45
    //   2563: iconst_1
    //   2564: baload
    //   2565: sipush #255
    //   2568: iand
    //   2569: bipush #16
    //   2571: ishl
    //   2572: ior
    //   2573: aload #45
    //   2575: iconst_2
    //   2576: baload
    //   2577: sipush #255
    //   2580: iand
    //   2581: bipush #8
    //   2583: ishl
    //   2584: ior
    //   2585: aload #45
    //   2587: iconst_3
    //   2588: baload
    //   2589: sipush #255
    //   2592: iand
    //   2593: ior
    //   2594: aload #30
    //   2596: iconst_0
    //   2597: iaload
    //   2598: ixor
    //   2599: istore #49
    //   2601: aload #45
    //   2603: iconst_4
    //   2604: baload
    //   2605: bipush #24
    //   2607: ishl
    //   2608: aload #45
    //   2610: iconst_5
    //   2611: baload
    //   2612: sipush #255
    //   2615: iand
    //   2616: bipush #16
    //   2618: ishl
    //   2619: ior
    //   2620: aload #45
    //   2622: bipush #6
    //   2624: baload
    //   2625: sipush #255
    //   2628: iand
    //   2629: bipush #8
    //   2631: ishl
    //   2632: ior
    //   2633: aload #45
    //   2635: bipush #7
    //   2637: baload
    //   2638: sipush #255
    //   2641: iand
    //   2642: ior
    //   2643: aload #30
    //   2645: iconst_1
    //   2646: iaload
    //   2647: ixor
    //   2648: istore #50
    //   2650: aload #45
    //   2652: bipush #8
    //   2654: baload
    //   2655: bipush #24
    //   2657: ishl
    //   2658: aload #45
    //   2660: bipush #9
    //   2662: baload
    //   2663: sipush #255
    //   2666: iand
    //   2667: bipush #16
    //   2669: ishl
    //   2670: ior
    //   2671: aload #45
    //   2673: bipush #10
    //   2675: baload
    //   2676: sipush #255
    //   2679: iand
    //   2680: bipush #8
    //   2682: ishl
    //   2683: ior
    //   2684: aload #45
    //   2686: bipush #11
    //   2688: baload
    //   2689: sipush #255
    //   2692: iand
    //   2693: ior
    //   2694: aload #30
    //   2696: iconst_2
    //   2697: iaload
    //   2698: ixor
    //   2699: istore #51
    //   2701: aload #45
    //   2703: bipush #12
    //   2705: baload
    //   2706: bipush #24
    //   2708: ishl
    //   2709: aload #45
    //   2711: bipush #13
    //   2713: baload
    //   2714: sipush #255
    //   2717: iand
    //   2718: bipush #16
    //   2720: ishl
    //   2721: ior
    //   2722: aload #45
    //   2724: bipush #14
    //   2726: baload
    //   2727: sipush #255
    //   2730: iand
    //   2731: bipush #8
    //   2733: ishl
    //   2734: ior
    //   2735: aload #45
    //   2737: bipush #15
    //   2739: baload
    //   2740: sipush #255
    //   2743: iand
    //   2744: ior
    //   2745: aload #30
    //   2747: iconst_3
    //   2748: iaload
    //   2749: ixor
    //   2750: istore #52
    //   2752: iconst_1
    //   2753: istore #53
    //   2755: iload #53
    //   2757: iload #36
    //   2759: if_icmpge -> 3002
    //   2762: iinc #47, 4
    //   2765: aload #38
    //   2767: iload #49
    //   2769: bipush #24
    //   2771: iushr
    //   2772: iaload
    //   2773: aload #39
    //   2775: iload #52
    //   2777: bipush #16
    //   2779: iushr
    //   2780: sipush #255
    //   2783: iand
    //   2784: iaload
    //   2785: ixor
    //   2786: aload #40
    //   2788: iload #51
    //   2790: bipush #8
    //   2792: iushr
    //   2793: sipush #255
    //   2796: iand
    //   2797: iaload
    //   2798: ixor
    //   2799: aload #41
    //   2801: iload #50
    //   2803: sipush #255
    //   2806: iand
    //   2807: iaload
    //   2808: ixor
    //   2809: aload #30
    //   2811: iload #47
    //   2813: iaload
    //   2814: ixor
    //   2815: istore #54
    //   2817: aload #38
    //   2819: iload #50
    //   2821: bipush #24
    //   2823: iushr
    //   2824: iaload
    //   2825: aload #39
    //   2827: iload #49
    //   2829: bipush #16
    //   2831: iushr
    //   2832: sipush #255
    //   2835: iand
    //   2836: iaload
    //   2837: ixor
    //   2838: aload #40
    //   2840: iload #52
    //   2842: bipush #8
    //   2844: iushr
    //   2845: sipush #255
    //   2848: iand
    //   2849: iaload
    //   2850: ixor
    //   2851: aload #41
    //   2853: iload #51
    //   2855: sipush #255
    //   2858: iand
    //   2859: iaload
    //   2860: ixor
    //   2861: aload #30
    //   2863: iload #47
    //   2865: iconst_1
    //   2866: iadd
    //   2867: iaload
    //   2868: ixor
    //   2869: istore #55
    //   2871: aload #38
    //   2873: iload #51
    //   2875: bipush #24
    //   2877: iushr
    //   2878: iaload
    //   2879: aload #39
    //   2881: iload #50
    //   2883: bipush #16
    //   2885: iushr
    //   2886: sipush #255
    //   2889: iand
    //   2890: iaload
    //   2891: ixor
    //   2892: aload #40
    //   2894: iload #49
    //   2896: bipush #8
    //   2898: iushr
    //   2899: sipush #255
    //   2902: iand
    //   2903: iaload
    //   2904: ixor
    //   2905: aload #41
    //   2907: iload #52
    //   2909: sipush #255
    //   2912: iand
    //   2913: iaload
    //   2914: ixor
    //   2915: aload #30
    //   2917: iload #47
    //   2919: iconst_2
    //   2920: iadd
    //   2921: iaload
    //   2922: ixor
    //   2923: istore #56
    //   2925: aload #38
    //   2927: iload #52
    //   2929: bipush #24
    //   2931: iushr
    //   2932: iaload
    //   2933: aload #39
    //   2935: iload #51
    //   2937: bipush #16
    //   2939: iushr
    //   2940: sipush #255
    //   2943: iand
    //   2944: iaload
    //   2945: ixor
    //   2946: aload #40
    //   2948: iload #50
    //   2950: bipush #8
    //   2952: iushr
    //   2953: sipush #255
    //   2956: iand
    //   2957: iaload
    //   2958: ixor
    //   2959: aload #41
    //   2961: iload #49
    //   2963: sipush #255
    //   2966: iand
    //   2967: iaload
    //   2968: ixor
    //   2969: aload #30
    //   2971: iload #47
    //   2973: iconst_3
    //   2974: iadd
    //   2975: iaload
    //   2976: ixor
    //   2977: istore #57
    //   2979: iload #54
    //   2981: istore #49
    //   2983: iload #55
    //   2985: istore #50
    //   2987: iload #56
    //   2989: istore #51
    //   2991: iload #57
    //   2993: istore #52
    //   2995: iinc #53, 1
    //   2998: iload_2
    //   2999: ifeq -> 2755
    //   3002: iinc #47, 4
    //   3005: aload #30
    //   3007: iload #47
    //   3009: iaload
    //   3010: istore #48
    //   3012: aload #46
    //   3014: iconst_0
    //   3015: aload #37
    //   3017: iload #49
    //   3019: bipush #24
    //   3021: iushr
    //   3022: baload
    //   3023: iload #48
    //   3025: bipush #24
    //   3027: iushr
    //   3028: ixor
    //   3029: i2b
    //   3030: bastore
    //   3031: aload #46
    //   3033: iconst_1
    //   3034: aload #37
    //   3036: iload #52
    //   3038: bipush #16
    //   3040: iushr
    //   3041: sipush #255
    //   3044: iand
    //   3045: baload
    //   3046: iload #48
    //   3048: bipush #16
    //   3050: iushr
    //   3051: ixor
    //   3052: i2b
    //   3053: bastore
    //   3054: aload #46
    //   3056: iconst_2
    //   3057: aload #37
    //   3059: iload #51
    //   3061: bipush #8
    //   3063: iushr
    //   3064: sipush #255
    //   3067: iand
    //   3068: baload
    //   3069: iload #48
    //   3071: bipush #8
    //   3073: iushr
    //   3074: ixor
    //   3075: i2b
    //   3076: bastore
    //   3077: aload #46
    //   3079: iconst_3
    //   3080: aload #37
    //   3082: iload #50
    //   3084: sipush #255
    //   3087: iand
    //   3088: baload
    //   3089: iload #48
    //   3091: ixor
    //   3092: i2b
    //   3093: bastore
    //   3094: aload #30
    //   3096: iload #47
    //   3098: iconst_1
    //   3099: iadd
    //   3100: iaload
    //   3101: istore #48
    //   3103: aload #46
    //   3105: iconst_4
    //   3106: aload #37
    //   3108: iload #50
    //   3110: bipush #24
    //   3112: iushr
    //   3113: baload
    //   3114: iload #48
    //   3116: bipush #24
    //   3118: iushr
    //   3119: ixor
    //   3120: i2b
    //   3121: bastore
    //   3122: aload #46
    //   3124: iconst_5
    //   3125: aload #37
    //   3127: iload #49
    //   3129: bipush #16
    //   3131: iushr
    //   3132: sipush #255
    //   3135: iand
    //   3136: baload
    //   3137: iload #48
    //   3139: bipush #16
    //   3141: iushr
    //   3142: ixor
    //   3143: i2b
    //   3144: bastore
    //   3145: aload #46
    //   3147: bipush #6
    //   3149: aload #37
    //   3151: iload #52
    //   3153: bipush #8
    //   3155: iushr
    //   3156: sipush #255
    //   3159: iand
    //   3160: baload
    //   3161: iload #48
    //   3163: bipush #8
    //   3165: iushr
    //   3166: ixor
    //   3167: i2b
    //   3168: bastore
    //   3169: aload #46
    //   3171: bipush #7
    //   3173: aload #37
    //   3175: iload #51
    //   3177: sipush #255
    //   3180: iand
    //   3181: baload
    //   3182: iload #48
    //   3184: ixor
    //   3185: i2b
    //   3186: bastore
    //   3187: aload #30
    //   3189: iload #47
    //   3191: iconst_2
    //   3192: iadd
    //   3193: iaload
    //   3194: istore #48
    //   3196: aload #46
    //   3198: bipush #8
    //   3200: aload #37
    //   3202: iload #51
    //   3204: bipush #24
    //   3206: iushr
    //   3207: baload
    //   3208: iload #48
    //   3210: bipush #24
    //   3212: iushr
    //   3213: ixor
    //   3214: i2b
    //   3215: bastore
    //   3216: aload #46
    //   3218: bipush #9
    //   3220: aload #37
    //   3222: iload #50
    //   3224: bipush #16
    //   3226: iushr
    //   3227: sipush #255
    //   3230: iand
    //   3231: baload
    //   3232: iload #48
    //   3234: bipush #16
    //   3236: iushr
    //   3237: ixor
    //   3238: i2b
    //   3239: bastore
    //   3240: aload #46
    //   3242: bipush #10
    //   3244: aload #37
    //   3246: iload #49
    //   3248: bipush #8
    //   3250: iushr
    //   3251: sipush #255
    //   3254: iand
    //   3255: baload
    //   3256: iload #48
    //   3258: bipush #8
    //   3260: iushr
    //   3261: ixor
    //   3262: i2b
    //   3263: bastore
    //   3264: aload #46
    //   3266: bipush #11
    //   3268: aload #37
    //   3270: iload #52
    //   3272: sipush #255
    //   3275: iand
    //   3276: baload
    //   3277: iload #48
    //   3279: ixor
    //   3280: i2b
    //   3281: bastore
    //   3282: aload #30
    //   3284: iload #47
    //   3286: iconst_3
    //   3287: iadd
    //   3288: iaload
    //   3289: istore #48
    //   3291: aload #46
    //   3293: bipush #12
    //   3295: aload #37
    //   3297: iload #52
    //   3299: bipush #24
    //   3301: iushr
    //   3302: baload
    //   3303: iload #48
    //   3305: bipush #24
    //   3307: iushr
    //   3308: ixor
    //   3309: i2b
    //   3310: bastore
    //   3311: aload #46
    //   3313: bipush #13
    //   3315: aload #37
    //   3317: iload #51
    //   3319: bipush #16
    //   3321: iushr
    //   3322: sipush #255
    //   3325: iand
    //   3326: baload
    //   3327: iload #48
    //   3329: bipush #16
    //   3331: iushr
    //   3332: ixor
    //   3333: i2b
    //   3334: bastore
    //   3335: aload #46
    //   3337: bipush #14
    //   3339: aload #37
    //   3341: iload #50
    //   3343: bipush #8
    //   3345: iushr
    //   3346: sipush #255
    //   3349: iand
    //   3350: baload
    //   3351: iload #48
    //   3353: bipush #8
    //   3355: iushr
    //   3356: ixor
    //   3357: i2b
    //   3358: bastore
    //   3359: aload #46
    //   3361: bipush #15
    //   3363: aload #37
    //   3365: iload #49
    //   3367: sipush #255
    //   3370: iand
    //   3371: baload
    //   3372: iload #48
    //   3374: ixor
    //   3375: i2b
    //   3376: bastore
    //   3377: iconst_0
    //   3378: istore #53
    //   3380: iload #53
    //   3382: bipush #16
    //   3384: if_icmpge -> 3410
    //   3387: aload #43
    //   3389: iload #53
    //   3391: iload #44
    //   3393: bipush #16
    //   3395: imul
    //   3396: iadd
    //   3397: aload #46
    //   3399: iload #53
    //   3401: baload
    //   3402: bastore
    //   3403: iinc #53, 1
    //   3406: iload_2
    //   3407: ifeq -> 3380
    //   3410: iinc #44, 1
    //   3413: iload_2
    //   3414: ifeq -> 2495
    //   3417: aload #43
    //   3419: arraylength
    //   3420: ifle -> 3501
    //   3423: aload #43
    //   3425: aload #43
    //   3427: arraylength
    //   3428: iconst_1
    //   3429: isub
    //   3430: baload
    //   3431: istore #44
    //   3433: iload #44
    //   3435: bipush #16
    //   3437: if_icmple -> 3448
    //   3440: aload #43
    //   3442: astore #35
    //   3444: iload_2
    //   3445: ifeq -> 3501
    //   3448: aload #43
    //   3450: arraylength
    //   3451: iload #44
    //   3453: isub
    //   3454: newarray byte
    //   3456: astore #35
    //   3458: iconst_0
    //   3459: istore #45
    //   3461: iload #45
    //   3463: aload #35
    //   3465: arraylength
    //   3466: if_icmpge -> 3501
    //   3469: iload #45
    //   3471: aload #43
    //   3473: arraylength
    //   3474: if_icmpge -> 3501
    //   3477: aload #35
    //   3479: iload #45
    //   3481: aload #43
    //   3483: iload #45
    //   3485: baload
    //   3486: bastore
    //   3487: iinc #45, 1
    //   3490: iload_2
    //   3491: ifeq -> 3461
    //   3494: goto -> 3501
    //   3497: invokestatic a : (Ljava/lang/Throwable;)Ljava/lang/Throwable;
    //   3500: athrow
    //   3501: aload #35
    //   3503: astore #7
    //   3505: getstatic burp/Zgqp.ZA : Ljava/lang/String;
    //   3508: getstatic burp/Zxe.Zg : Ljava/lang/Object;
    //   3511: checkcast java/math/BigInteger
    //   3514: invokevirtual intValue : ()I
    //   3517: bipush #32
    //   3519: irem
    //   3520: invokestatic abs : (I)I
    //   3523: invokevirtual charAt : (I)C
    //   3526: getstatic burp/Zr5k.Zq : Ljava/lang/String;
    //   3529: getstatic burp/Zxd0.Za : Ljava/lang/Object;
    //   3532: checkcast java/math/BigInteger
    //   3535: invokevirtual intValue : ()I
    //   3538: bipush #32
    //   3540: irem
    //   3541: invokestatic abs : (I)I
    //   3544: invokevirtual charAt : (I)C
    //   3547: if_icmpgt -> 3654
    //   3550: getstatic burp/Zmlu.ZF : Ljava/lang/String;
    //   3553: getstatic burp/Zgss.Zl : Ljava/lang/Object;
    //   3556: checkcast java/math/BigInteger
    //   3559: invokevirtual intValue : ()I
    //   3562: bipush #32
    //   3564: irem
    //   3565: invokestatic abs : (I)I
    //   3568: invokevirtual charAt : (I)C
    //   3571: getstatic burp/Zk7o.Zb : Ljava/lang/String;
    //   3574: getstatic burp/Zlos.Zk : Ljava/lang/Object;
    //   3577: checkcast java/math/BigInteger
    //   3580: invokevirtual intValue : ()I
    //   3583: bipush #32
    //   3585: irem
    //   3586: invokestatic abs : (I)I
    //   3589: invokevirtual charAt : (I)C
    //   3592: if_icmpgt -> 3654
    //   3595: goto -> 3602
    //   3598: invokestatic a : (Ljava/lang/Throwable;)Ljava/lang/Throwable;
    //   3601: athrow
    //   3602: getstatic burp/Zkby.Zf : Ljava/lang/String;
    //   3605: getstatic burp/Zmhx.ZQ : Ljava/lang/Object;
    //   3608: checkcast java/math/BigInteger
    //   3611: invokevirtual intValue : ()I
    //   3614: bipush #32
    //   3616: irem
    //   3617: invokestatic abs : (I)I
    //   3620: invokevirtual charAt : (I)C
    //   3623: getstatic burp/Zm__.Zf : Ljava/lang/String;
    //   3626: getstatic burp/Zeuz.Zp : Ljava/lang/Object;
    //   3629: checkcast java/math/BigInteger
    //   3632: invokevirtual intValue : ()I
    //   3635: bipush #32
    //   3637: irem
    //   3638: invokestatic abs : (I)I
    //   3641: invokevirtual charAt : (I)C
    //   3644: if_icmpgt -> 3662
    //   3647: goto -> 3654
    //   3650: invokestatic a : (Ljava/lang/Throwable;)Ljava/lang/Throwable;
    //   3653: athrow
    //   3654: iconst_1
    //   3655: goto -> 3663
    //   3658: invokestatic a : (Ljava/lang/Throwable;)Ljava/lang/Throwable;
    //   3661: athrow
    //   3662: iconst_0
    //   3663: ireturn
    //   3664: astore_3
    //   3665: new java/lang/Exception
    //   3668: dup
    //   3669: aload_3
    //   3670: invokevirtual getMessage : ()Ljava/lang/String;
    //   3673: invokespecial <init> : (Ljava/lang/String;)V
    //   3676: athrow
    // Exception table:
    //   from	to	target	type
    //   4	3663	3664	java/lang/Throwable
    //   82	96	96	java/lang/Throwable
    //   107	120	123	java/lang/Throwable
    //   112	135	138	java/lang/Throwable
    //   127	153	156	java/lang/Throwable
    //   142	183	186	java/lang/Throwable
    //   246	273	276	java/lang/Throwable
    //   263	291	294	java/lang/Throwable
    //   280	327	330	java/lang/Throwable
    //   298	341	344	java/lang/Throwable
    //   390	404	404	java/lang/Throwable
    //   415	428	431	java/lang/Throwable
    //   420	443	446	java/lang/Throwable
    //   435	461	464	java/lang/Throwable
    //   450	491	494	java/lang/Throwable
    //   554	581	584	java/lang/Throwable
    //   571	599	602	java/lang/Throwable
    //   588	629	632	java/lang/Throwable
    //   606	640	640	java/lang/Throwable
    //   651	667	670	java/lang/Throwable
    //   716	730	730	java/lang/Throwable
    //   741	754	757	java/lang/Throwable
    //   746	769	772	java/lang/Throwable
    //   761	787	790	java/lang/Throwable
    //   776	817	820	java/lang/Throwable
    //   880	907	910	java/lang/Throwable
    //   897	928	931	java/lang/Throwable
    //   914	958	961	java/lang/Throwable
    //   935	969	969	java/lang/Throwable
    //   980	996	999	java/lang/Throwable
    //   1148	1163	1163	java/lang/Throwable
    //   2165	2191	2191	java/lang/Throwable
    //   2272	2287	2287	java/lang/Throwable
    //   3469	3494	3497	java/lang/Throwable
    //   3505	3595	3598	java/lang/Throwable
    //   3550	3647	3650	java/lang/Throwable
    //   3602	3658	3658	java/lang/Throwable
  }
  
  static void ZD(Object paramObject) {
    Zrd4.Zg = a(-10334, -6472);
    Zrd4.Ze = new BigInteger(a(-10330, 21268));
    boolean bool = Zt2e.ZK();
    try {
      try {
        if (Zrd4.Zg.charAt(Math.abs(((BigInteger)Zgwu.ZD).intValue() % 32)) <= Zr5k.Zq.charAt(Math.abs(((BigInteger)Zx8t.ZA).intValue() % 32))) {
          try {
            Zzs9.Zw(Class.forName(a(-10331, -25386)));
            if (bool)
              Zlo4.Zr(Class.forName(a(-10328, 3510))); 
          } catch (Throwable throwable) {
            throw a(null);
          } 
          return;
        } 
      } catch (Throwable throwable) {
        throw a(null);
      } 
      Zlo4.Zr(Class.forName(a(-10328, 3510)));
    } catch (Throwable throwable) {}
  }
  
  static void Zm(Object[] paramArrayOfObject, Object paramObject) throws Throwable {}
  
  static {
    // Byte code:
    //   0: bipush #16
    //   2: anewarray java/lang/String
    //   5: astore #5
    //   7: iconst_0
    //   8: istore_3
    //   9: ldc '1O:4tiG\\t-U\A/ L9qR=AoH\\t5_gfD\\tn34\\n&2LE\\nl~?L5r`Rn\\r 9#@{ !9g)+nLi\\t\\nm-\\t}VZFg/89e??\\tePU&] M)7F#Byu:x-/\\tf'1W'
    //   11: dup
    //   12: astore_2
    //   13: invokevirtual length : ()I
    //   16: istore #4
    //   18: bipush #19
    //   20: istore_1
    //   21: iconst_m1
    //   22: istore_0
    //   23: bipush #110
    //   25: iinc #0, 1
    //   28: aload_2
    //   29: iload_0
    //   30: dup
    //   31: iload_1
    //   32: iadd
    //   33: invokevirtual substring : (II)Ljava/lang/String;
    //   36: iconst_m1
    //   37: goto -> 144
    //   40: aload #5
    //   42: swap
    //   43: iload_3
    //   44: iinc #3, 1
    //   47: swap
    //   48: aastore
    //   49: iload_0
    //   50: iload_1
    //   51: iadd
    //   52: dup
    //   53: istore_0
    //   54: iload #4
    //   56: if_icmpge -> 68
    //   59: aload_2
    //   60: iload_0
    //   61: invokevirtual charAt : (I)C
    //   64: istore_1
    //   65: goto -> 23
    //   68: ldc '??\\t\\t;"'
    //   70: dup
    //   71: astore_2
    //   72: invokevirtual length : ()I
    //   75: istore #4
    //   77: sipush #128
    //   80: istore_1
    //   81: iconst_m1
    //   82: istore_0
    //   83: bipush #22
    //   85: iinc #0, 1
    //   88: aload_2
    //   89: iload_0
    //   90: dup
    //   91: iload_1
    //   92: iadd
    //   93: invokevirtual substring : (II)Ljava/lang/String;
    //   96: iconst_0
    //   97: goto -> 144
    //   100: aload #5
    //   102: swap
    //   103: iload_3
    //   104: iinc #3, 1
    //   107: swap
    //   108: aastore
    //   109: iload_0
    //   110: iload_1
    //   111: iadd
    //   112: dup
    //   113: istore_0
    //   114: iload #4
    //   116: if_icmpge -> 128
    //   119: aload_2
    //   120: iload_0
    //   121: invokevirtual charAt : (I)C
    //   124: istore_1
    //   125: goto -> 83
    //   128: aload #5
    //   130: putstatic burp/Zxtc.a : [Ljava/lang/String;
    //   133: bipush #16
    //   135: anewarray java/lang/String
    //   138: putstatic burp/Zxtc.b : [Ljava/lang/String;
    //   141: goto -> 300
    //   144: dup_x2
    //   145: pop
    //   146: invokevirtual toCharArray : ()[C
    //   149: dup_x1
    //   150: arraylength
    //   151: dup_x2
    //   152: pop
    //   153: iconst_0
    //   154: istore #6
    //   156: dup2_x1
    //   157: pop2
    //   158: dup_x2
    //   159: iconst_1
    //   160: if_icmpgt -> 260
    //   163: dup2
    //   164: swap
    //   165: iload #6
    //   167: dup2_x1
    //   168: caload
    //   169: swap
    //   170: iload #6
    //   172: bipush #7
    //   174: irem
    //   175: tableswitch default -> 242, 0 -> 212, 1 -> 217, 2 -> 222, 3 -> 227, 4 -> 232, 5 -> 237
    //   212: bipush #43
    //   214: goto -> 244
    //   217: bipush #39
    //   219: goto -> 244
    //   222: bipush #99
    //   224: goto -> 244
    //   227: bipush #7
    //   229: goto -> 244
    //   232: bipush #81
    //   234: goto -> 244
    //   237: bipush #75
    //   239: goto -> 244
    //   242: bipush #105
    //   244: ixor
    //   245: ixor
    //   246: i2c
    //   247: castore
    //   248: iinc #6, 1
    //   251: dup
    //   252: ifne -> 260
    //   255: dup2
    //   256: dup_x1
    //   257: goto -> 167
    //   260: dup2_x1
    //   261: pop2
    //   262: dup_x2
    //   263: iload #6
    //   265: if_icmpgt -> 163
    //   268: pop
    //   269: new java/lang/String
    //   272: dup_x1
    //   273: swap
    //   274: invokespecial <init> : ([C)V
    //   277: invokevirtual intern : ()Ljava/lang/String;
    //   280: swap
    //   281: pop
    //   282: swap
    //   283: tableswitch default -> 40, 0 -> 100
    //   300: sipush #-10324
    //   303: sipush #-23787
    //   306: invokestatic a : (II)Ljava/lang/String;
    //   309: putstatic burp/Zxtc.Zo : Ljava/lang/String;
    //   312: new java/math/BigInteger
    //   315: dup
    //   316: iconst_1
    //   317: bipush #32
    //   319: newarray byte
    //   321: dup
    //   322: iconst_0
    //   323: bipush #103
    //   325: bastore
    //   326: dup
    //   327: iconst_1
    //   328: bipush #51
    //   330: bastore
    //   331: dup
    //   332: iconst_2
    //   333: bipush #-48
    //   335: bastore
    //   336: dup
    //   337: iconst_3
    //   338: bipush #8
    //   340: bastore
    //   341: dup
    //   342: iconst_4
    //   343: bipush #20
    //   345: bastore
    //   346: dup
    //   347: iconst_5
    //   348: bipush #97
    //   350: bastore
    //   351: dup
    //   352: bipush #6
    //   354: bipush #-69
    //   356: bastore
    //   357: dup
    //   358: bipush #7
    //   360: bipush #-34
    //   362: bastore
    //   363: dup
    //   364: bipush #8
    //   366: bipush #-105
    //   368: bastore
    //   369: dup
    //   370: bipush #9
    //   372: bipush #-120
    //   374: bastore
    //   375: dup
    //   376: bipush #10
    //   378: bipush #-93
    //   380: bastore
    //   381: dup
    //   382: bipush #11
    //   384: bipush #83
    //   386: bastore
    //   387: dup
    //   388: bipush #12
    //   390: bipush #24
    //   392: bastore
    //   393: dup
    //   394: bipush #13
    //   396: bipush #-64
    //   398: bastore
    //   399: dup
    //   400: bipush #14
    //   402: bipush #78
    //   404: bastore
    //   405: dup
    //   406: bipush #15
    //   408: bipush #29
    //   410: bastore
    //   411: dup
    //   412: bipush #16
    //   414: bipush #-37
    //   416: bastore
    //   417: dup
    //   418: bipush #17
    //   420: bipush #-115
    //   422: bastore
    //   423: dup
    //   424: bipush #18
    //   426: bipush #-24
    //   428: bastore
    //   429: dup
    //   430: bipush #19
    //   432: iconst_1
    //   433: bastore
    //   434: dup
    //   435: bipush #20
    //   437: bipush #-76
    //   439: bastore
    //   440: dup
    //   441: bipush #21
    //   443: bipush #-105
    //   445: bastore
    //   446: dup
    //   447: bipush #22
    //   449: bipush #21
    //   451: bastore
    //   452: dup
    //   453: bipush #23
    //   455: iconst_3
    //   456: bastore
    //   457: dup
    //   458: bipush #24
    //   460: bipush #45
    //   462: bastore
    //   463: dup
    //   464: bipush #25
    //   466: bipush #-77
    //   468: bastore
    //   469: dup
    //   470: bipush #26
    //   472: bipush #62
    //   474: bastore
    //   475: dup
    //   476: bipush #27
    //   478: bipush #39
    //   480: bastore
    //   481: dup
    //   482: bipush #28
    //   484: bipush #-6
    //   486: bastore
    //   487: dup
    //   488: bipush #29
    //   490: bipush #50
    //   492: bastore
    //   493: dup
    //   494: bipush #30
    //   496: bipush #-97
    //   498: bastore
    //   499: dup
    //   500: bipush #31
    //   502: bipush #18
    //   504: bastore
    //   505: invokespecial <init> : (I[B)V
    //   508: putstatic burp/Zxtc.ZF : Ljava/lang/Object;
    //   511: return
  }
  
  private static Throwable a(Throwable paramThrowable) {
    return paramThrowable;
  }
  
  private static String a(int paramInt1, int paramInt2) {
    int i = (paramInt1 ^ 0xFFFFD7A0) & 0xFFFF;
    if (b[i] == null) {
      char[] arrayOfChar = a[i].toCharArray();
      switch (arrayOfChar[0] & 0xFF) {
        case 0:
        
        case 1:
        
        case 2:
        
        case 3:
        
        case 4:
        
        case 5:
        
        case 6:
        
        case 7:
        
        case 8:
        
        case 9:
        
        case 10:
        
        case 11:
        
        case 12:
        
        case 13:
        
        case 14:
        
        case 15:
        
        case 16:
        
        case 17:
        
        case 18:
        
        case 19:
        
        case 20:
        
        case 21:
        
        case 22:
        
        case 23:
        
        case 24:
        
        case 25:
        
        case 26:
        
        case 27:
        
        case 28:
        
        case 29:
        
        case 30:
        
        case 31:
        
        case 32:
        
        case 33:
        
        case 34:
        
        case 35:
        
        case 36:
        
        case 37:
        
        case 38:
        
        case 39:
        
        case 40:
        
        case 41:
        
        case 42:
        
        case 43:
        
        case 44:
        
        case 45:
        
        case 46:
        
        case 47:
        
        case 48:
        
        case 49:
        
        case 50:
        
        case 51:
        
        case 52:
        
        case 53:
        
        case 54:
        
        case 55:
        
        case 56:
        
        case 57:
        
        case 58:
        
        case 59:
        
        case 60:
        
        case 61:
        
        case 62:
        
        case 63:
        
        case 64:
        
        case 65:
        
        case 66:
        
        case 67:
        
        case 68:
        
        case 69:
        
        case 70:
        
        case 71:
        
        case 72:
        
        case 73:
        
        case 74:
        
        case 75:
        
        case 76:
        
        case 77:
        
        case 78:
        
        case 79:
        
        case 80:
        
        case 81:
        
        case 82:
        
        case 83:
        
        case 84:
        
        case 85:
        
        case 86:
        
        case 87:
        
        case 88:
        
        case 89:
        
        case 90:
        
        case 91:
        
        case 92:
        
        case 93:
        
        case 94:
        
        case 95:
        
        case 96:
        
        case 97:
        
        case 98:
        
        case 99:
        
        case 100:
        
        case 101:
        
        case 102:
        
        case 103:
        
        case 104:
        
        case 105:
        
        case 106:
        
        case 107:
        
        case 108:
        
        case 109:
        
        case 110:
        
        case 111:
        
        case 112:
        
        case 113:
        
        case 114:
        
        case 115:
        
        case 116:
        
        case 117:
        
        case 118:
        
        case 119:
        
        case 120:
        
        case 121:
        
        case 122:
        
        case 123:
        
        case 124:
        
        case 125:
        
        case 126:
        
        case 127:
        
        case 128:
        
        case 129:
        
        case 130:
        
        case 131:
        
        case 132:
        
        case 133:
        
        case 134:
        
        case 135:
        
        case 136:
        
        case 137:
        
        case 138:
        
        case 139:
        
        case 140:
        
        case 141:
        
        case 142:
        
        case 143:
        
        case 144:
        
        case 145:
        
        case 146:
        
        case 147:
        
        case 148:
        
        case 149:
        
        case 150:
        
        case 151:
        
        case 152:
        
        case 153:
        
        case 154:
        
        case 155:
        
        case 156:
        
        case 157:
        
        case 158:
        
        case 159:
        
        case 160:
        
        case 161:
        
        case 162:
        
        case 163:
        
        case 164:
        
        case 165:
        
        case 166:
        
        case 167:
        
        case 168:
        
        case 169:
        
        case 170:
        
        case 171:
        
        case 172:
        
        case 173:
        
        case 174:
        
        case 175:
        
        case 176:
        
        case 177:
        
        case 178:
        
        case 179:
        
        case 180:
        
        case 181:
        
        case 182:
        
        case 183:
        
        case 184:
        
        case 185:
        
        case 186:
        
        case 187:
        
        case 188:
        
        case 189:
        
        case 190:
        
        case 191:
        
        case 192:
        
        case 193:
        
        case 194:
        
        case 195:
        
        case 196:
        
        case 197:
        
        case 198:
        
        case 199:
        
        case 200:
        
        case 201:
        
        case 202:
        
        case 203:
        
        case 204:
        
        case 205:
        
        case 206:
        
        case 207:
        
        case 208:
        
        case 209:
        
        case 210:
        
        case 211:
        
        case 212:
        
        case 213:
        
        case 214:
        
        case 215:
        
        case 216:
        
        case 217:
        
        case 218:
        
        case 219:
        
        case 220:
        
        case 221:
        
        case 222:
        
        case 223:
        
        case 224:
        
        case 225:
        
        case 226:
        
        case 227:
        
        case 228:
        
        case 229:
        
        case 230:
        
        case 231:
        
        case 232:
        
        case 233:
        
        case 234:
        
        case 235:
        
        case 236:
        
        case 237:
        
        case 238:
        
        case 239:
        
        case 240:
        
        case 241:
        
        case 242:
        
        case 243:
        
        case 244:
        
        case 245:
        
        case 246:
        
        case 247:
        
        case 248:
        
        case 249:
        
        case 250:
        
        case 251:
        
        case 252:
        
        case 253:
        
        case 254:
        
        default:
          break;
      } 
      byte b1 = 39;
      int j = (paramInt2 & 0xFF) - b1;
      if (j < 0)
        j += 256; 
      int k = ((paramInt2 & 0xFFFF) >>> 8) - b1;
      if (k < 0)
        k += 256; 
      for (byte b2 = 0; b2 < arrayOfChar.length; b2++) {
        int m = b2 % 2;
        if (m == 0) {
          arrayOfChar[b2] = (char)(arrayOfChar[b2] ^ j);
          j = ((j >>> 3 | j << 5) ^ arrayOfChar[b2]) & 0xFF;
        } else {
          arrayOfChar[b2] = (char)(arrayOfChar[b2] ^ k);
          k = ((k >>> 3 | k << 5) ^ arrayOfChar[b2]) & 0xFF;
        } 
      } 
      b[i] = (new String(arrayOfChar)).intern();
    } 
    return b[i];
  }
}


/* Location:              C:\Program Files\BurpSuitePro\burpsuite_pro.jar!\burp\Zxtc.class
 * Java compiler version: 21 (65.0)
 * JD-Core Version:       1.1.3
 */