package burp;

import java.util.Objects;

class Zxv_ extends Zxsr implements Zzt9 {
  private static final String a;
  
  Zxv_(Zkit paramZkit, long paramLong) {
    super(paramZkit, paramLong);
  }
  
  public Zeu4<Zzt9> ZF() {
    return Zzt9.ZF;
  }
  
  public boolean Zcu() {
    return this.Za.Zi(this, Zkp8.ZQ);
  }
  
  public void Zan(boolean paramBoolean) {
    this.Za.ZH(this, Zkp8.ZQ, paramBoolean);
  }
  
  public boolean ZcE() {
    return this.Za.Zi(this, Zkp8.ZD);
  }
  
  public void Zao(boolean paramBoolean) {
    this.Za.ZH(this, Zkp8.ZD, paramBoolean);
  }
  
  public boolean ZcW() {
    return this.Za.Zi(this, Zkp8.Zb);
  }
  
  public void ZaC(boolean paramBoolean) {
    this.Za.ZH(this, Zkp8.Zb, paramBoolean);
  }
  
  public boolean ZcR() {
    return this.Za.Zi(this, Zkp8.ZX);
  }
  
  public void Zal(boolean paramBoolean) {
    this.Za.ZH(this, Zkp8.ZX, paramBoolean);
  }
  
  public boolean ZcS() {
    return this.Za.Zi(this, Zkp8.Zx);
  }
  
  public void ZaZ(boolean paramBoolean) {
    this.Za.ZH(this, Zkp8.Zx, paramBoolean);
  }
  
  public boolean ZcZ() {
    return this.Za.Zi(this, Zkp8.ZW);
  }
  
  public void Zaq(boolean paramBoolean) {
    this.Za.ZH(this, Zkp8.ZW, paramBoolean);
  }
  
  public boolean ZcH() {
    return this.Za.Zi(this, Zkp8.Zw);
  }
  
  public void Zab(boolean paramBoolean) {
    this.Za.ZH(this, Zkp8.Zw, paramBoolean);
  }
  
  public boolean Zc8() {
    return this.Za.Zi(this, Zkp8.Zm);
  }
  
  public void Zai(boolean paramBoolean) {
    this.Za.ZH(this, Zkp8.Zm, paramBoolean);
  }
  
  public boolean Zcz() {
    return this.Za.Zi(this, Zkp8.Zc);
  }
  
  public void ZaU(boolean paramBoolean) {
    this.Za.ZH(this, Zkp8.Zc, paramBoolean);
  }
  
  public boolean Zc4() {
    return this.Za.Zi(this, Zkp8.Zd);
  }
  
  public void Zah(boolean paramBoolean) {
    this.Za.ZH(this, Zkp8.Zd, paramBoolean);
  }
  
  public boolean Zcc() {
    return this.Za.Zi(this, Zkp8.ZO);
  }
  
  public void Zas(boolean paramBoolean) {
    this.Za.ZH(this, Zkp8.ZO, paramBoolean);
  }
  
  public boolean Zc1() {
    return this.Za.Zi(this, Zkp8.Ze);
  }
  
  public void Zaa(boolean paramBoolean) {
    this.Za.ZH(this, Zkp8.Ze, paramBoolean);
  }
  
  public boolean Zcm() {
    return this.Za.Zi(this, Zkp8.ZR);
  }
  
  public void Zaw(boolean paramBoolean) {
    this.Za.ZH(this, Zkp8.ZR, paramBoolean);
  }
  
  public boolean ZcP() {
    return this.Za.Zi(this, Zkp8.ZC);
  }
  
  public void Za7(boolean paramBoolean) {
    this.Za.ZH(this, Zkp8.ZC, paramBoolean);
  }
  
  public boolean ZcQ() {
    return this.Za.Zi(this, Zkp8.ZY);
  }
  
  public void ZaR(boolean paramBoolean) {
    this.Za.ZH(this, Zkp8.ZY, paramBoolean);
  }
  
  public String Zcs() {
    String str = this.Za.ZJ(this, Zkp8.Zp);
    return Objects.<String>requireNonNullElse(str, "");
  }
  
  public void ZHv(String paramString) {
    this.Za.Zn(this, Zkp8.Zp, paramString);
  }
  
  public boolean Zc_() {
    return this.Za.Zi(this, Zkp8.ZB);
  }
  
  public void ZaI(boolean paramBoolean) {
    this.Za.ZH(this, Zkp8.ZB, paramBoolean);
  }
  
  public boolean ZcO() {
    return this.Za.Zi(this, Zkp8.ZP);
  }
  
  public void ZaG(boolean paramBoolean) {
    this.Za.ZH(this, Zkp8.ZP, paramBoolean);
  }
  
  public boolean Zcq() {
    return this.Za.Zi(this, Zkp8.Za);
  }
  
  public void ZaQ(boolean paramBoolean) {
    this.Za.ZH(this, Zkp8.Za, paramBoolean);
  }
  
  public String Zcr() {
    String str = this.Za.ZJ(this, Zkp8.ZZ);
    return Objects.<String>requireNonNullElse(str, "");
  }
  
  public boolean Zcf() {
    return this.Za.Zi(this, Zkp8.ZE);
  }
  
  public void Zat(boolean paramBoolean) {
    this.Za.ZH(this, Zkp8.ZE, paramBoolean);
  }
  
  public void ZHK(String paramString) {
    this.Za.Zn(this, Zkp8.ZZ, paramString);
  }
  
  public boolean ZcN() {
    return this.Za.Zi(this, Zkp8.ZU);
  }
  
  public void ZaB(boolean paramBoolean) {
    this.Za.ZH(this, Zkp8.ZU, paramBoolean);
  }
  
  public String Zcv() {
    String str = this.Za.ZJ(this, Zkp8.ZV);
    return Objects.<String>requireNonNullElse(str, "");
  }
  
  public void ZHd(String paramString) {
    this.Za.Zn(this, Zkp8.ZV, paramString);
  }
  
  public boolean ZcI() {
    return this.Za.Zi(this, Zkp8.ZK);
  }
  
  public void ZaM(boolean paramBoolean) {
    this.Za.ZH(this, Zkp8.ZK, paramBoolean);
  }
  
  public boolean ZcC() {
    return this.Za.Zi(this, Zkp8.Zv);
  }
  
  public void ZaE(boolean paramBoolean) {
    this.Za.ZH(this, Zkp8.Zv, paramBoolean);
  }
  
  public String ZcL() {
    String str = this.Za.ZJ(this, Zkp8.ZF);
    return Objects.<String>requireNonNullElse(str, "");
  }
  
  public void ZHF(String paramString) {
    this.Za.Zn(this, Zkp8.ZF, paramString);
  }
  
  public String Zcp() {
    int[] arrayOfInt = Zgvt.Zw();
    Zrb5 zrb5 = this.Za.<Zrb5>ZJ(this, Zkp8.Zt);
    String str = (zrb5 == null) ? "" : zrb5.ZJ();
    if (arrayOfInt == null)
      Zbqc.Zr(new Zbqc[1]); 
    return str.isEmpty() ? a : str;
  }
  
  public void ZHC(String paramString) {
    Zrb5 zrb5 = this.Za.<Zrb5>ZJ(this, Zkp8.Zt);
    if (zrb5 == null) {
      zrb5 = this.Za.<Zrb5>ZH(new Zrjk());
      this.Za.Zq(this, Zkp8.Zt, zrb5);
    } 
    zrb5.Ze(paramString);
  }
  
  public Zzca ZcF() {
    byte b = this.Za.ZL(this, Zkp8.Zl);
    return Zzca.Zy(b);
  }
  
  public void ZX(Zzca paramZzca) {
    byte b = (paramZzca == null) ? Zzca.SETTINGS.ZY() : paramZzca.ZY();
    this.Za.Zc(this, Zkp8.Zl, b);
  }
  
  static {
    // Byte code:
    //   0: bipush #110
    //   2: ldc '9\iqg;k?Kha.'
    //   4: iconst_m1
    //   5: goto -> 14
    //   8: putstatic burp/Zxv_.a : Ljava/lang/String;
    //   11: goto -> 154
    //   14: dup_x2
    //   15: pop
    //   16: invokevirtual toCharArray : ()[C
    //   19: dup_x1
    //   20: arraylength
    //   21: dup_x2
    //   22: pop
    //   23: iconst_0
    //   24: istore_0
    //   25: dup2_x1
    //   26: pop2
    //   27: dup_x2
    //   28: iconst_1
    //   29: if_icmpgt -> 128
    //   32: dup2
    //   33: swap
    //   34: iload_0
    //   35: dup2_x1
    //   36: caload
    //   37: swap
    //   38: iload_0
    //   39: bipush #7
    //   41: irem
    //   42: tableswitch default -> 110, 0 -> 80, 1 -> 85, 2 -> 90, 3 -> 95, 4 -> 100, 5 -> 105
    //   80: bipush #37
    //   82: goto -> 112
    //   85: bipush #87
    //   87: goto -> 112
    //   90: bipush #115
    //   92: goto -> 112
    //   95: bipush #106
    //   97: goto -> 112
    //   100: bipush #123
    //   102: goto -> 112
    //   105: bipush #59
    //   107: goto -> 112
    //   110: bipush #37
    //   112: ixor
    //   113: ixor
    //   114: i2c
    //   115: castore
    //   116: iinc #0, 1
    //   119: dup
    //   120: ifne -> 128
    //   123: dup2
    //   124: dup_x1
    //   125: goto -> 35
    //   128: dup2_x1
    //   129: pop2
    //   130: dup_x2
    //   131: iload_0
    //   132: if_icmpgt -> 32
    //   135: pop
    //   136: new java/lang/String
    //   139: dup_x1
    //   140: swap
    //   141: invokespecial <init> : ([C)V
    //   144: invokevirtual intern : ()Ljava/lang/String;
    //   147: swap
    //   148: pop
    //   149: swap
    //   150: pop
    //   151: goto -> 8
    //   154: return
  }
}


/* Location:              C:\Program Files\BurpSuitePro\burpsuite_pro.jar!\burp\Zxv_.class
 * Java compiler version: 21 (65.0)
 * JD-Core Version:       1.1.3
 */