package burp;

import java.math.BigInteger;

class Zxxt extends ClassLoader {
  static String ZA;
  
  static Object ZX;
  
  private static final String[] a;
  
  private static final String[] b;
  
  static void ZP(Object paramObject) {
    Zg6z.ZY = a(-27046, -2659);
    Zg6z.ZS = new BigInteger(a(-27048, 24435));
    boolean bool = Zt2e.ZN();
    try {
      try {
        if (Zxn9.ZU.charAt(Math.abs(((BigInteger)Zlhu.ZJ).intValue() % 32)) > Zkvq.Zg.charAt(Math.abs(((BigInteger)Zlp8.Zu).intValue() % 32))) {
          try {
            Zluk.Zh(Class.forName(a(-27041, 23615)));
            if (!bool)
              Ze_0.ZG(Class.forName(a(-27047, -30351))); 
          } catch (Throwable throwable) {
            throw a(null);
          } 
          return;
        } 
      } catch (Throwable throwable) {
        throw a(null);
      } 
      Ze_0.ZG(Class.forName(a(-27047, -30351)));
    } catch (Throwable throwable) {}
  }
  
  static void ZU(Object[] paramArrayOfObject, Object paramObject) throws Throwable {}
  
  static boolean Zb(Object[] paramArrayOfObject, Object paramObject) throws Throwable {
    // Byte code:
    //   0: invokestatic ZK : ()Z
    //   3: istore_2
    //   4: new java/lang/StringBuilder
    //   7: dup
    //   8: invokespecial <init> : ()V
    //   11: astore_3
    //   12: iconst_0
    //   13: istore #4
    //   15: iload #4
    //   17: bipush #32
    //   19: if_icmpge -> 1355
    //   22: iload #4
    //   24: tableswitch default -> 1348, 0 -> 168, 1 -> 205, 2 -> 242, 3 -> 279, 4 -> 316, 5 -> 353, 6 -> 390, 7 -> 427, 8 -> 464, 9 -> 501, 10 -> 538, 11 -> 575, 12 -> 612, 13 -> 649, 14 -> 686, 15 -> 723, 16 -> 760, 17 -> 797, 18 -> 834, 19 -> 871, 20 -> 908, 21 -> 945, 22 -> 982, 23 -> 1019, 24 -> 1056, 25 -> 1093, 26 -> 1130, 27 -> 1167, 28 -> 1204, 29 -> 1241, 30 -> 1278, 31 -> 1315
    //   168: aload_3
    //   169: getstatic burp/Zk1.Zg : Ljava/lang/String;
    //   172: getstatic burp/Zbze.ZM : Ljava/lang/Object;
    //   175: checkcast java/math/BigInteger
    //   178: invokevirtual intValue : ()I
    //   181: bipush #32
    //   183: irem
    //   184: invokestatic abs : (I)I
    //   187: invokevirtual charAt : (I)C
    //   190: invokevirtual append : (C)Ljava/lang/StringBuilder;
    //   193: pop
    //   194: iload_2
    //   195: ifeq -> 1348
    //   198: goto -> 205
    //   201: invokestatic a : (Ljava/lang/Throwable;)Ljava/lang/Throwable;
    //   204: athrow
    //   205: aload_3
    //   206: getstatic burp/Zej8.ZP : Ljava/lang/String;
    //   209: getstatic burp/Zkhf.ZU : Ljava/lang/Object;
    //   212: checkcast java/math/BigInteger
    //   215: invokevirtual intValue : ()I
    //   218: bipush #32
    //   220: irem
    //   221: invokestatic abs : (I)I
    //   224: invokevirtual charAt : (I)C
    //   227: invokevirtual append : (C)Ljava/lang/StringBuilder;
    //   230: pop
    //   231: iload_2
    //   232: ifeq -> 1348
    //   235: goto -> 242
    //   238: invokestatic a : (Ljava/lang/Throwable;)Ljava/lang/Throwable;
    //   241: athrow
    //   242: aload_3
    //   243: getstatic burp/Zg0q.Ze : Ljava/lang/String;
    //   246: getstatic burp/Zkkl.ZE : Ljava/lang/Object;
    //   249: checkcast java/math/BigInteger
    //   252: invokevirtual intValue : ()I
    //   255: bipush #32
    //   257: irem
    //   258: invokestatic abs : (I)I
    //   261: invokevirtual charAt : (I)C
    //   264: invokevirtual append : (C)Ljava/lang/StringBuilder;
    //   267: pop
    //   268: iload_2
    //   269: ifeq -> 1348
    //   272: goto -> 279
    //   275: invokestatic a : (Ljava/lang/Throwable;)Ljava/lang/Throwable;
    //   278: athrow
    //   279: aload_3
    //   280: getstatic burp/Ztnn.ZS : Ljava/lang/String;
    //   283: getstatic burp/Zbsz.ZP : Ljava/lang/Object;
    //   286: checkcast java/math/BigInteger
    //   289: invokevirtual intValue : ()I
    //   292: bipush #32
    //   294: irem
    //   295: invokestatic abs : (I)I
    //   298: invokevirtual charAt : (I)C
    //   301: invokevirtual append : (C)Ljava/lang/StringBuilder;
    //   304: pop
    //   305: iload_2
    //   306: ifeq -> 1348
    //   309: goto -> 316
    //   312: invokestatic a : (Ljava/lang/Throwable;)Ljava/lang/Throwable;
    //   315: athrow
    //   316: aload_3
    //   317: getstatic burp/Zexl.Zs : Ljava/lang/String;
    //   320: getstatic burp/Zlwm.Ze : Ljava/lang/Object;
    //   323: checkcast java/math/BigInteger
    //   326: invokevirtual intValue : ()I
    //   329: bipush #32
    //   331: irem
    //   332: invokestatic abs : (I)I
    //   335: invokevirtual charAt : (I)C
    //   338: invokevirtual append : (C)Ljava/lang/StringBuilder;
    //   341: pop
    //   342: iload_2
    //   343: ifeq -> 1348
    //   346: goto -> 353
    //   349: invokestatic a : (Ljava/lang/Throwable;)Ljava/lang/Throwable;
    //   352: athrow
    //   353: aload_3
    //   354: getstatic burp/Zx63.ZT : Ljava/lang/String;
    //   357: getstatic burp/Ztdl.Zw : Ljava/lang/Object;
    //   360: checkcast java/math/BigInteger
    //   363: invokevirtual intValue : ()I
    //   366: bipush #32
    //   368: irem
    //   369: invokestatic abs : (I)I
    //   372: invokevirtual charAt : (I)C
    //   375: invokevirtual append : (C)Ljava/lang/StringBuilder;
    //   378: pop
    //   379: iload_2
    //   380: ifeq -> 1348
    //   383: goto -> 390
    //   386: invokestatic a : (Ljava/lang/Throwable;)Ljava/lang/Throwable;
    //   389: athrow
    //   390: aload_3
    //   391: getstatic burp/Zb3l.Zz : Ljava/lang/String;
    //   394: getstatic burp/Zz4a.ZB : Ljava/lang/Object;
    //   397: checkcast java/math/BigInteger
    //   400: invokevirtual intValue : ()I
    //   403: bipush #32
    //   405: irem
    //   406: invokestatic abs : (I)I
    //   409: invokevirtual charAt : (I)C
    //   412: invokevirtual append : (C)Ljava/lang/StringBuilder;
    //   415: pop
    //   416: iload_2
    //   417: ifeq -> 1348
    //   420: goto -> 427
    //   423: invokestatic a : (Ljava/lang/Throwable;)Ljava/lang/Throwable;
    //   426: athrow
    //   427: aload_3
    //   428: getstatic burp/Zzna.Zi : Ljava/lang/String;
    //   431: getstatic burp/Zenr.ZA : Ljava/lang/Object;
    //   434: checkcast java/math/BigInteger
    //   437: invokevirtual intValue : ()I
    //   440: bipush #32
    //   442: irem
    //   443: invokestatic abs : (I)I
    //   446: invokevirtual charAt : (I)C
    //   449: invokevirtual append : (C)Ljava/lang/StringBuilder;
    //   452: pop
    //   453: iload_2
    //   454: ifeq -> 1348
    //   457: goto -> 464
    //   460: invokestatic a : (Ljava/lang/Throwable;)Ljava/lang/Throwable;
    //   463: athrow
    //   464: aload_3
    //   465: getstatic burp/Zmkq.Zr : Ljava/lang/String;
    //   468: getstatic burp/Zz3b.Zu : Ljava/lang/Object;
    //   471: checkcast java/math/BigInteger
    //   474: invokevirtual intValue : ()I
    //   477: bipush #32
    //   479: irem
    //   480: invokestatic abs : (I)I
    //   483: invokevirtual charAt : (I)C
    //   486: invokevirtual append : (C)Ljava/lang/StringBuilder;
    //   489: pop
    //   490: iload_2
    //   491: ifeq -> 1348
    //   494: goto -> 501
    //   497: invokestatic a : (Ljava/lang/Throwable;)Ljava/lang/Throwable;
    //   500: athrow
    //   501: aload_3
    //   502: getstatic burp/Zr02.ZG : Ljava/lang/String;
    //   505: getstatic burp/Zr2q.ZS : Ljava/lang/Object;
    //   508: checkcast java/math/BigInteger
    //   511: invokevirtual intValue : ()I
    //   514: bipush #32
    //   516: irem
    //   517: invokestatic abs : (I)I
    //   520: invokevirtual charAt : (I)C
    //   523: invokevirtual append : (C)Ljava/lang/StringBuilder;
    //   526: pop
    //   527: iload_2
    //   528: ifeq -> 1348
    //   531: goto -> 538
    //   534: invokestatic a : (Ljava/lang/Throwable;)Ljava/lang/Throwable;
    //   537: athrow
    //   538: aload_3
    //   539: getstatic burp/Zm_u.Zi : Ljava/lang/String;
    //   542: getstatic burp/Zxxh.Za : Ljava/lang/Object;
    //   545: checkcast java/math/BigInteger
    //   548: invokevirtual intValue : ()I
    //   551: bipush #32
    //   553: irem
    //   554: invokestatic abs : (I)I
    //   557: invokevirtual charAt : (I)C
    //   560: invokevirtual append : (C)Ljava/lang/StringBuilder;
    //   563: pop
    //   564: iload_2
    //   565: ifeq -> 1348
    //   568: goto -> 575
    //   571: invokestatic a : (Ljava/lang/Throwable;)Ljava/lang/Throwable;
    //   574: athrow
    //   575: aload_3
    //   576: getstatic burp/Ztvg.ZZ : Ljava/lang/String;
    //   579: getstatic burp/Zld5.ZX : Ljava/lang/Object;
    //   582: checkcast java/math/BigInteger
    //   585: invokevirtual intValue : ()I
    //   588: bipush #32
    //   590: irem
    //   591: invokestatic abs : (I)I
    //   594: invokevirtual charAt : (I)C
    //   597: invokevirtual append : (C)Ljava/lang/StringBuilder;
    //   600: pop
    //   601: iload_2
    //   602: ifeq -> 1348
    //   605: goto -> 612
    //   608: invokestatic a : (Ljava/lang/Throwable;)Ljava/lang/Throwable;
    //   611: athrow
    //   612: aload_3
    //   613: getstatic burp/Zk5k.Zx : Ljava/lang/String;
    //   616: getstatic burp/Zb6m.ZQ : Ljava/lang/Object;
    //   619: checkcast java/math/BigInteger
    //   622: invokevirtual intValue : ()I
    //   625: bipush #32
    //   627: irem
    //   628: invokestatic abs : (I)I
    //   631: invokevirtual charAt : (I)C
    //   634: invokevirtual append : (C)Ljava/lang/StringBuilder;
    //   637: pop
    //   638: iload_2
    //   639: ifeq -> 1348
    //   642: goto -> 649
    //   645: invokestatic a : (Ljava/lang/Throwable;)Ljava/lang/Throwable;
    //   648: athrow
    //   649: aload_3
    //   650: getstatic burp/Zr1h.ZS : Ljava/lang/String;
    //   653: getstatic burp/Zse8.Zn : Ljava/lang/Object;
    //   656: checkcast java/math/BigInteger
    //   659: invokevirtual intValue : ()I
    //   662: bipush #32
    //   664: irem
    //   665: invokestatic abs : (I)I
    //   668: invokevirtual charAt : (I)C
    //   671: invokevirtual append : (C)Ljava/lang/StringBuilder;
    //   674: pop
    //   675: iload_2
    //   676: ifeq -> 1348
    //   679: goto -> 686
    //   682: invokestatic a : (Ljava/lang/Throwable;)Ljava/lang/Throwable;
    //   685: athrow
    //   686: aload_3
    //   687: getstatic burp/Zzah.Zs : Ljava/lang/String;
    //   690: getstatic burp/Zlcc.ZP : Ljava/lang/Object;
    //   693: checkcast java/math/BigInteger
    //   696: invokevirtual intValue : ()I
    //   699: bipush #32
    //   701: irem
    //   702: invokestatic abs : (I)I
    //   705: invokevirtual charAt : (I)C
    //   708: invokevirtual append : (C)Ljava/lang/StringBuilder;
    //   711: pop
    //   712: iload_2
    //   713: ifeq -> 1348
    //   716: goto -> 723
    //   719: invokestatic a : (Ljava/lang/Throwable;)Ljava/lang/Throwable;
    //   722: athrow
    //   723: aload_3
    //   724: getstatic burp/Zt85.ZR : Ljava/lang/String;
    //   727: getstatic burp/Zm1d.ZS : Ljava/lang/Object;
    //   730: checkcast java/math/BigInteger
    //   733: invokevirtual intValue : ()I
    //   736: bipush #32
    //   738: irem
    //   739: invokestatic abs : (I)I
    //   742: invokevirtual charAt : (I)C
    //   745: invokevirtual append : (C)Ljava/lang/StringBuilder;
    //   748: pop
    //   749: iload_2
    //   750: ifeq -> 1348
    //   753: goto -> 760
    //   756: invokestatic a : (Ljava/lang/Throwable;)Ljava/lang/Throwable;
    //   759: athrow
    //   760: aload_3
    //   761: getstatic burp/Zr14.ZL : Ljava/lang/String;
    //   764: getstatic burp/Zd9.Zr : Ljava/lang/Object;
    //   767: checkcast java/math/BigInteger
    //   770: invokevirtual intValue : ()I
    //   773: bipush #32
    //   775: irem
    //   776: invokestatic abs : (I)I
    //   779: invokevirtual charAt : (I)C
    //   782: invokevirtual append : (C)Ljava/lang/StringBuilder;
    //   785: pop
    //   786: iload_2
    //   787: ifeq -> 1348
    //   790: goto -> 797
    //   793: invokestatic a : (Ljava/lang/Throwable;)Ljava/lang/Throwable;
    //   796: athrow
    //   797: aload_3
    //   798: getstatic burp/Zsp9.ZA : Ljava/lang/String;
    //   801: getstatic burp/Zg2u.ZI : Ljava/lang/Object;
    //   804: checkcast java/math/BigInteger
    //   807: invokevirtual intValue : ()I
    //   810: bipush #32
    //   812: irem
    //   813: invokestatic abs : (I)I
    //   816: invokevirtual charAt : (I)C
    //   819: invokevirtual append : (C)Ljava/lang/StringBuilder;
    //   822: pop
    //   823: iload_2
    //   824: ifeq -> 1348
    //   827: goto -> 834
    //   830: invokestatic a : (Ljava/lang/Throwable;)Ljava/lang/Throwable;
    //   833: athrow
    //   834: aload_3
    //   835: getstatic burp/Zmdf.Zo : Ljava/lang/String;
    //   838: getstatic burp/Zrgo.ZJ : Ljava/lang/Object;
    //   841: checkcast java/math/BigInteger
    //   844: invokevirtual intValue : ()I
    //   847: bipush #32
    //   849: irem
    //   850: invokestatic abs : (I)I
    //   853: invokevirtual charAt : (I)C
    //   856: invokevirtual append : (C)Ljava/lang/StringBuilder;
    //   859: pop
    //   860: iload_2
    //   861: ifeq -> 1348
    //   864: goto -> 871
    //   867: invokestatic a : (Ljava/lang/Throwable;)Ljava/lang/Throwable;
    //   870: athrow
    //   871: aload_3
    //   872: getstatic burp/Zb0q.Zr : Ljava/lang/String;
    //   875: getstatic burp/Zxju.ZN : Ljava/lang/Object;
    //   878: checkcast java/math/BigInteger
    //   881: invokevirtual intValue : ()I
    //   884: bipush #32
    //   886: irem
    //   887: invokestatic abs : (I)I
    //   890: invokevirtual charAt : (I)C
    //   893: invokevirtual append : (C)Ljava/lang/StringBuilder;
    //   896: pop
    //   897: iload_2
    //   898: ifeq -> 1348
    //   901: goto -> 908
    //   904: invokestatic a : (Ljava/lang/Throwable;)Ljava/lang/Throwable;
    //   907: athrow
    //   908: aload_3
    //   909: getstatic burp/Ze1k.ZI : Ljava/lang/String;
    //   912: getstatic burp/Zs1k.Ze : Ljava/lang/Object;
    //   915: checkcast java/math/BigInteger
    //   918: invokevirtual intValue : ()I
    //   921: bipush #32
    //   923: irem
    //   924: invokestatic abs : (I)I
    //   927: invokevirtual charAt : (I)C
    //   930: invokevirtual append : (C)Ljava/lang/StringBuilder;
    //   933: pop
    //   934: iload_2
    //   935: ifeq -> 1348
    //   938: goto -> 945
    //   941: invokestatic a : (Ljava/lang/Throwable;)Ljava/lang/Throwable;
    //   944: athrow
    //   945: aload_3
    //   946: getstatic burp/Zbze.ZK : Ljava/lang/String;
    //   949: getstatic burp/Zrzg.ZA : Ljava/lang/Object;
    //   952: checkcast java/math/BigInteger
    //   955: invokevirtual intValue : ()I
    //   958: bipush #32
    //   960: irem
    //   961: invokestatic abs : (I)I
    //   964: invokevirtual charAt : (I)C
    //   967: invokevirtual append : (C)Ljava/lang/StringBuilder;
    //   970: pop
    //   971: iload_2
    //   972: ifeq -> 1348
    //   975: goto -> 982
    //   978: invokestatic a : (Ljava/lang/Throwable;)Ljava/lang/Throwable;
    //   981: athrow
    //   982: aload_3
    //   983: getstatic burp/Zr02.ZG : Ljava/lang/String;
    //   986: getstatic burp/Zlwc.ZG : Ljava/lang/Object;
    //   989: checkcast java/math/BigInteger
    //   992: invokevirtual intValue : ()I
    //   995: bipush #32
    //   997: irem
    //   998: invokestatic abs : (I)I
    //   1001: invokevirtual charAt : (I)C
    //   1004: invokevirtual append : (C)Ljava/lang/StringBuilder;
    //   1007: pop
    //   1008: iload_2
    //   1009: ifeq -> 1348
    //   1012: goto -> 1019
    //   1015: invokestatic a : (Ljava/lang/Throwable;)Ljava/lang/Throwable;
    //   1018: athrow
    //   1019: aload_3
    //   1020: getstatic burp/Zmc_.Zb : Ljava/lang/String;
    //   1023: getstatic burp/Zer1.ZL : Ljava/lang/Object;
    //   1026: checkcast java/math/BigInteger
    //   1029: invokevirtual intValue : ()I
    //   1032: bipush #32
    //   1034: irem
    //   1035: invokestatic abs : (I)I
    //   1038: invokevirtual charAt : (I)C
    //   1041: invokevirtual append : (C)Ljava/lang/StringBuilder;
    //   1044: pop
    //   1045: iload_2
    //   1046: ifeq -> 1348
    //   1049: goto -> 1056
    //   1052: invokestatic a : (Ljava/lang/Throwable;)Ljava/lang/Throwable;
    //   1055: athrow
    //   1056: aload_3
    //   1057: getstatic burp/Zm69.ZE : Ljava/lang/String;
    //   1060: getstatic burp/Zs1k.Ze : Ljava/lang/Object;
    //   1063: checkcast java/math/BigInteger
    //   1066: invokevirtual intValue : ()I
    //   1069: bipush #32
    //   1071: irem
    //   1072: invokestatic abs : (I)I
    //   1075: invokevirtual charAt : (I)C
    //   1078: invokevirtual append : (C)Ljava/lang/StringBuilder;
    //   1081: pop
    //   1082: iload_2
    //   1083: ifeq -> 1348
    //   1086: goto -> 1093
    //   1089: invokestatic a : (Ljava/lang/Throwable;)Ljava/lang/Throwable;
    //   1092: athrow
    //   1093: aload_3
    //   1094: getstatic burp/Zku9.Zl : Ljava/lang/String;
    //   1097: getstatic burp/Ze4g.Zz : Ljava/lang/Object;
    //   1100: checkcast java/math/BigInteger
    //   1103: invokevirtual intValue : ()I
    //   1106: bipush #32
    //   1108: irem
    //   1109: invokestatic abs : (I)I
    //   1112: invokevirtual charAt : (I)C
    //   1115: invokevirtual append : (C)Ljava/lang/StringBuilder;
    //   1118: pop
    //   1119: iload_2
    //   1120: ifeq -> 1348
    //   1123: goto -> 1130
    //   1126: invokestatic a : (Ljava/lang/Throwable;)Ljava/lang/Throwable;
    //   1129: athrow
    //   1130: aload_3
    //   1131: getstatic burp/Zb9q.Zk : Ljava/lang/String;
    //   1134: getstatic burp/Zm83.Zl : Ljava/lang/Object;
    //   1137: checkcast java/math/BigInteger
    //   1140: invokevirtual intValue : ()I
    //   1143: bipush #32
    //   1145: irem
    //   1146: invokestatic abs : (I)I
    //   1149: invokevirtual charAt : (I)C
    //   1152: invokevirtual append : (C)Ljava/lang/StringBuilder;
    //   1155: pop
    //   1156: iload_2
    //   1157: ifeq -> 1348
    //   1160: goto -> 1167
    //   1163: invokestatic a : (Ljava/lang/Throwable;)Ljava/lang/Throwable;
    //   1166: athrow
    //   1167: aload_3
    //   1168: getstatic burp/Zk8i.ZS : Ljava/lang/String;
    //   1171: getstatic burp/Zz0y.Zp : Ljava/lang/Object;
    //   1174: checkcast java/math/BigInteger
    //   1177: invokevirtual intValue : ()I
    //   1180: bipush #32
    //   1182: irem
    //   1183: invokestatic abs : (I)I
    //   1186: invokevirtual charAt : (I)C
    //   1189: invokevirtual append : (C)Ljava/lang/StringBuilder;
    //   1192: pop
    //   1193: iload_2
    //   1194: ifeq -> 1348
    //   1197: goto -> 1204
    //   1200: invokestatic a : (Ljava/lang/Throwable;)Ljava/lang/Throwable;
    //   1203: athrow
    //   1204: aload_3
    //   1205: getstatic burp/Zzah.Zs : Ljava/lang/String;
    //   1208: getstatic burp/Zz5e.Zl : Ljava/lang/Object;
    //   1211: checkcast java/math/BigInteger
    //   1214: invokevirtual intValue : ()I
    //   1217: bipush #32
    //   1219: irem
    //   1220: invokestatic abs : (I)I
    //   1223: invokevirtual charAt : (I)C
    //   1226: invokevirtual append : (C)Ljava/lang/StringBuilder;
    //   1229: pop
    //   1230: iload_2
    //   1231: ifeq -> 1348
    //   1234: goto -> 1241
    //   1237: invokestatic a : (Ljava/lang/Throwable;)Ljava/lang/Throwable;
    //   1240: athrow
    //   1241: aload_3
    //   1242: getstatic burp/Zeub.ZT : Ljava/lang/String;
    //   1245: getstatic burp/Zvob.ZX : Ljava/lang/Object;
    //   1248: checkcast java/math/BigInteger
    //   1251: invokevirtual intValue : ()I
    //   1254: bipush #32
    //   1256: irem
    //   1257: invokestatic abs : (I)I
    //   1260: invokevirtual charAt : (I)C
    //   1263: invokevirtual append : (C)Ljava/lang/StringBuilder;
    //   1266: pop
    //   1267: iload_2
    //   1268: ifeq -> 1348
    //   1271: goto -> 1278
    //   1274: invokestatic a : (Ljava/lang/Throwable;)Ljava/lang/Throwable;
    //   1277: athrow
    //   1278: aload_3
    //   1279: getstatic burp/Zlc2.Zz : Ljava/lang/String;
    //   1282: getstatic burp/Zrym.Zk : Ljava/lang/Object;
    //   1285: checkcast java/math/BigInteger
    //   1288: invokevirtual intValue : ()I
    //   1291: bipush #32
    //   1293: irem
    //   1294: invokestatic abs : (I)I
    //   1297: invokevirtual charAt : (I)C
    //   1300: invokevirtual append : (C)Ljava/lang/StringBuilder;
    //   1303: pop
    //   1304: iload_2
    //   1305: ifeq -> 1348
    //   1308: goto -> 1315
    //   1311: invokestatic a : (Ljava/lang/Throwable;)Ljava/lang/Throwable;
    //   1314: athrow
    //   1315: aload_3
    //   1316: getstatic burp/Zmyk.Zx : Ljava/lang/String;
    //   1319: getstatic burp/Zd9.Zr : Ljava/lang/Object;
    //   1322: checkcast java/math/BigInteger
    //   1325: invokevirtual intValue : ()I
    //   1328: bipush #32
    //   1330: irem
    //   1331: invokestatic abs : (I)I
    //   1334: invokevirtual charAt : (I)C
    //   1337: invokevirtual append : (C)Ljava/lang/StringBuilder;
    //   1340: pop
    //   1341: goto -> 1348
    //   1344: invokestatic a : (Ljava/lang/Throwable;)Ljava/lang/Throwable;
    //   1347: athrow
    //   1348: iinc #4, 1
    //   1351: iload_2
    //   1352: ifeq -> 15
    //   1355: sipush #-27044
    //   1358: sipush #11113
    //   1361: invokestatic a : (II)Ljava/lang/String;
    //   1364: invokestatic forName : (Ljava/lang/String;)Ljava/lang/Class;
    //   1367: invokevirtual getDeclaredFields : ()[Ljava/lang/reflect/Field;
    //   1370: astore #4
    //   1372: aload #4
    //   1374: arraylength
    //   1375: istore #5
    //   1377: iconst_0
    //   1378: istore #6
    //   1380: iload #6
    //   1382: iload #5
    //   1384: if_icmpge -> 1461
    //   1387: aload #4
    //   1389: iload #6
    //   1391: aaload
    //   1392: astore #7
    //   1394: aload #7
    //   1396: invokevirtual getType : ()Ljava/lang/Class;
    //   1399: ldc java/lang/String
    //   1401: invokevirtual equals : (Ljava/lang/Object;)Z
    //   1404: ifeq -> 1447
    //   1407: aload #7
    //   1409: iconst_1
    //   1410: invokevirtual setAccessible : (Z)V
    //   1413: aload #7
    //   1415: aconst_null
    //   1416: aload #7
    //   1418: aconst_null
    //   1419: invokevirtual get : (Ljava/lang/Object;)Ljava/lang/Object;
    //   1422: checkcast java/lang/String
    //   1425: getstatic burp/Zxxt.ZA : Ljava/lang/String;
    //   1428: <illegal opcode> makeConcatWithConstants : (Ljava/lang/String;Ljava/lang/String;)Ljava/lang/String;
    //   1433: invokevirtual set : (Ljava/lang/Object;Ljava/lang/Object;)V
    //   1436: iload_2
    //   1437: ifeq -> 1461
    //   1440: goto -> 1447
    //   1443: invokestatic a : (Ljava/lang/Throwable;)Ljava/lang/Throwable;
    //   1446: athrow
    //   1447: iinc #6, 1
    //   1450: iload_2
    //   1451: ifeq -> 1380
    //   1454: goto -> 1461
    //   1457: invokestatic a : (Ljava/lang/Throwable;)Ljava/lang/Throwable;
    //   1460: athrow
    //   1461: sipush #-27045
    //   1464: sipush #-8220
    //   1467: invokestatic a : (II)Ljava/lang/String;
    //   1470: iconst_1
    //   1471: ldc burp/Zzv
    //   1473: invokevirtual getClassLoader : ()Ljava/lang/ClassLoader;
    //   1476: invokestatic forName : (Ljava/lang/String;ZLjava/lang/ClassLoader;)Ljava/lang/Class;
    //   1479: invokevirtual getDeclaredFields : ()[Ljava/lang/reflect/Field;
    //   1482: astore #4
    //   1484: aload #4
    //   1486: arraylength
    //   1487: istore #5
    //   1489: iconst_0
    //   1490: istore #6
    //   1492: iload #6
    //   1494: iload #5
    //   1496: if_icmpge -> 1634
    //   1499: aload #4
    //   1501: iload #6
    //   1503: aaload
    //   1504: astore #7
    //   1506: aload #7
    //   1508: invokevirtual getModifiers : ()I
    //   1511: invokestatic isStatic : (I)Z
    //   1514: ifne -> 1524
    //   1517: goto -> 1627
    //   1520: invokestatic a : (Ljava/lang/Throwable;)Ljava/lang/Throwable;
    //   1523: athrow
    //   1524: aload #7
    //   1526: invokevirtual getType : ()Ljava/lang/Class;
    //   1529: astore #8
    //   1531: aload #8
    //   1533: ifnull -> 1614
    //   1536: aload #8
    //   1538: invokevirtual isPrimitive : ()Z
    //   1541: ifne -> 1614
    //   1544: goto -> 1551
    //   1547: invokestatic a : (Ljava/lang/Throwable;)Ljava/lang/Throwable;
    //   1550: athrow
    //   1551: aload #8
    //   1553: invokevirtual getPackage : ()Ljava/lang/Package;
    //   1556: ifnull -> 1614
    //   1559: goto -> 1566
    //   1562: invokestatic a : (Ljava/lang/Throwable;)Ljava/lang/Throwable;
    //   1565: athrow
    //   1566: aload #8
    //   1568: invokevirtual getPackage : ()Ljava/lang/Package;
    //   1571: invokevirtual getName : ()Ljava/lang/String;
    //   1574: ifnull -> 1614
    //   1577: goto -> 1584
    //   1580: invokestatic a : (Ljava/lang/Throwable;)Ljava/lang/Throwable;
    //   1583: athrow
    //   1584: aload #8
    //   1586: invokevirtual getPackage : ()Ljava/lang/Package;
    //   1589: invokevirtual getName : ()Ljava/lang/String;
    //   1592: sipush #-27042
    //   1595: sipush #-2413
    //   1598: invokestatic a : (II)Ljava/lang/String;
    //   1601: invokevirtual startsWith : (Ljava/lang/String;)Z
    //   1604: ifne -> 1614
    //   1607: goto -> 1614
    //   1610: invokestatic a : (Ljava/lang/Throwable;)Ljava/lang/Throwable;
    //   1613: athrow
    //   1614: aload #7
    //   1616: iconst_1
    //   1617: invokevirtual setAccessible : (Z)V
    //   1620: aload #7
    //   1622: aconst_null
    //   1623: invokevirtual get : (Ljava/lang/Object;)Ljava/lang/Object;
    //   1626: pop
    //   1627: iinc #6, 1
    //   1630: iload_2
    //   1631: ifeq -> 1492
    //   1634: sipush #-27056
    //   1637: sipush #17176
    //   1640: invokestatic a : (II)Ljava/lang/String;
    //   1643: invokestatic forName : (Ljava/lang/String;)Ljava/lang/Class;
    //   1646: invokevirtual getDeclaredMethods : ()[Ljava/lang/reflect/Method;
    //   1649: astore #4
    //   1651: aload #4
    //   1653: arraylength
    //   1654: istore #5
    //   1656: iconst_0
    //   1657: istore #6
    //   1659: iload #6
    //   1661: iload #5
    //   1663: if_icmpge -> 1796
    //   1666: aload #4
    //   1668: iload #6
    //   1670: aaload
    //   1671: astore #7
    //   1673: aload #7
    //   1675: invokevirtual getParameterTypes : ()[Ljava/lang/Class;
    //   1678: pop
    //   1679: aload #7
    //   1681: invokevirtual getModifiers : ()I
    //   1684: invokestatic isStatic : (I)Z
    //   1687: ifeq -> 1782
    //   1690: aload #7
    //   1692: invokevirtual getParameterTypes : ()[Ljava/lang/Class;
    //   1695: arraylength
    //   1696: iconst_2
    //   1697: if_icmpne -> 1782
    //   1700: goto -> 1707
    //   1703: invokestatic a : (Ljava/lang/Throwable;)Ljava/lang/Throwable;
    //   1706: athrow
    //   1707: aload #7
    //   1709: invokevirtual getReturnType : ()Ljava/lang/Class;
    //   1712: getstatic java/lang/Void.TYPE : Ljava/lang/Class;
    //   1715: invokevirtual equals : (Ljava/lang/Object;)Z
    //   1718: ifeq -> 1782
    //   1721: goto -> 1728
    //   1724: invokestatic a : (Ljava/lang/Throwable;)Ljava/lang/Throwable;
    //   1727: athrow
    //   1728: aload #7
    //   1730: iconst_1
    //   1731: invokevirtual setAccessible : (Z)V
    //   1734: aload #7
    //   1736: aconst_null
    //   1737: iconst_2
    //   1738: anewarray java/lang/Object
    //   1741: dup
    //   1742: iconst_0
    //   1743: aload_0
    //   1744: aastore
    //   1745: dup
    //   1746: iconst_1
    //   1747: aload_1
    //   1748: ifnonnull -> 1766
    //   1751: goto -> 1758
    //   1754: invokestatic a : (Ljava/lang/Throwable;)Ljava/lang/Throwable;
    //   1757: athrow
    //   1758: aload_1
    //   1759: goto -> 1773
    //   1762: invokestatic a : (Ljava/lang/Throwable;)Ljava/lang/Throwable;
    //   1765: athrow
    //   1766: aload_1
    //   1767: checkcast [B
    //   1770: invokevirtual clone : ()Ljava/lang/Object;
    //   1773: aastore
    //   1774: invokevirtual invoke : (Ljava/lang/Object;[Ljava/lang/Object;)Ljava/lang/Object;
    //   1777: pop
    //   1778: iload_2
    //   1779: ifeq -> 1796
    //   1782: iinc #6, 1
    //   1785: iload_2
    //   1786: ifeq -> 1659
    //   1789: goto -> 1796
    //   1792: invokestatic a : (Ljava/lang/Throwable;)Ljava/lang/Throwable;
    //   1795: athrow
    //   1796: getstatic burp/Zlid.ZU : Ljava/lang/String;
    //   1799: getstatic burp/Zb2u.ZY : Ljava/lang/Object;
    //   1802: checkcast java/math/BigInteger
    //   1805: invokevirtual intValue : ()I
    //   1808: bipush #32
    //   1810: irem
    //   1811: invokestatic abs : (I)I
    //   1814: invokevirtual charAt : (I)C
    //   1817: getstatic burp/Zsdl.ZJ : Ljava/lang/String;
    //   1820: getstatic burp/Zlw8.ZA : Ljava/lang/Object;
    //   1823: checkcast java/math/BigInteger
    //   1826: invokevirtual intValue : ()I
    //   1829: bipush #32
    //   1831: irem
    //   1832: invokestatic abs : (I)I
    //   1835: invokevirtual charAt : (I)C
    //   1838: if_icmpgt -> 1945
    //   1841: getstatic burp/Zesw.ZC : Ljava/lang/String;
    //   1844: getstatic burp/Zthx.ZH : Ljava/lang/Object;
    //   1847: checkcast java/math/BigInteger
    //   1850: invokevirtual intValue : ()I
    //   1853: bipush #32
    //   1855: irem
    //   1856: invokestatic abs : (I)I
    //   1859: invokevirtual charAt : (I)C
    //   1862: getstatic burp/Zmt_.ZH : Ljava/lang/String;
    //   1865: getstatic burp/Zrp2.Zw : Ljava/lang/Object;
    //   1868: checkcast java/math/BigInteger
    //   1871: invokevirtual intValue : ()I
    //   1874: bipush #32
    //   1876: irem
    //   1877: invokestatic abs : (I)I
    //   1880: invokevirtual charAt : (I)C
    //   1883: if_icmpgt -> 1945
    //   1886: goto -> 1893
    //   1889: invokestatic a : (Ljava/lang/Throwable;)Ljava/lang/Throwable;
    //   1892: athrow
    //   1893: getstatic burp/Zmtr.Zd : Ljava/lang/String;
    //   1896: getstatic burp/Zeig.ZA : Ljava/lang/Object;
    //   1899: checkcast java/math/BigInteger
    //   1902: invokevirtual intValue : ()I
    //   1905: bipush #32
    //   1907: irem
    //   1908: invokestatic abs : (I)I
    //   1911: invokevirtual charAt : (I)C
    //   1914: getstatic burp/Zrwp.ZS : Ljava/lang/String;
    //   1917: getstatic burp/Zlsg.ZD : Ljava/lang/Object;
    //   1920: checkcast java/math/BigInteger
    //   1923: invokevirtual intValue : ()I
    //   1926: bipush #32
    //   1928: irem
    //   1929: invokestatic abs : (I)I
    //   1932: invokevirtual charAt : (I)C
    //   1935: if_icmpgt -> 1953
    //   1938: goto -> 1945
    //   1941: invokestatic a : (Ljava/lang/Throwable;)Ljava/lang/Throwable;
    //   1944: athrow
    //   1945: iconst_1
    //   1946: goto -> 1954
    //   1949: invokestatic a : (Ljava/lang/Throwable;)Ljava/lang/Throwable;
    //   1952: athrow
    //   1953: iconst_0
    //   1954: ireturn
    //   1955: astore_3
    //   1956: new java/lang/Exception
    //   1959: dup
    //   1960: aload_3
    //   1961: invokevirtual getMessage : ()Ljava/lang/String;
    //   1964: invokespecial <init> : (Ljava/lang/String;)V
    //   1967: athrow
    // Exception table:
    //   from	to	target	type
    //   4	1954	1955	java/lang/Throwable
    //   22	198	201	java/lang/Throwable
    //   168	235	238	java/lang/Throwable
    //   205	272	275	java/lang/Throwable
    //   242	309	312	java/lang/Throwable
    //   279	346	349	java/lang/Throwable
    //   316	383	386	java/lang/Throwable
    //   353	420	423	java/lang/Throwable
    //   390	457	460	java/lang/Throwable
    //   427	494	497	java/lang/Throwable
    //   464	531	534	java/lang/Throwable
    //   501	568	571	java/lang/Throwable
    //   538	605	608	java/lang/Throwable
    //   575	642	645	java/lang/Throwable
    //   612	679	682	java/lang/Throwable
    //   649	716	719	java/lang/Throwable
    //   686	753	756	java/lang/Throwable
    //   723	790	793	java/lang/Throwable
    //   760	827	830	java/lang/Throwable
    //   797	864	867	java/lang/Throwable
    //   834	901	904	java/lang/Throwable
    //   871	938	941	java/lang/Throwable
    //   908	975	978	java/lang/Throwable
    //   945	1012	1015	java/lang/Throwable
    //   982	1049	1052	java/lang/Throwable
    //   1019	1086	1089	java/lang/Throwable
    //   1056	1123	1126	java/lang/Throwable
    //   1093	1160	1163	java/lang/Throwable
    //   1130	1197	1200	java/lang/Throwable
    //   1167	1234	1237	java/lang/Throwable
    //   1204	1271	1274	java/lang/Throwable
    //   1241	1308	1311	java/lang/Throwable
    //   1278	1341	1344	java/lang/Throwable
    //   1394	1440	1443	java/lang/Throwable
    //   1407	1454	1457	java/lang/Throwable
    //   1506	1520	1520	java/lang/Throwable
    //   1531	1544	1547	java/lang/Throwable
    //   1536	1559	1562	java/lang/Throwable
    //   1551	1577	1580	java/lang/Throwable
    //   1566	1607	1610	java/lang/Throwable
    //   1673	1700	1703	java/lang/Throwable
    //   1690	1721	1724	java/lang/Throwable
    //   1707	1751	1754	java/lang/Throwable
    //   1728	1762	1762	java/lang/Throwable
    //   1773	1789	1792	java/lang/Throwable
    //   1796	1886	1889	java/lang/Throwable
    //   1841	1938	1941	java/lang/Throwable
    //   1893	1949	1949	java/lang/Throwable
  }
  
  static {
    // Byte code:
    //   0: bipush #10
    //   2: anewarray java/lang/String
    //   5: astore #5
    //   7: iconst_0
    //   8: istore_3
    //   9: ldc 'Â„Ã’!Â©ÂµQÂœÂ±Â—"Ã€ÃÂ»Â•Ã¤Â±Â¬Ã¬Â ÃšÂƒÃ¯B1Â‚Ã¤HQÃ¹Ã¿ÃÂ”Ã³{o\\bEÃ¾m,uÂ¡ÂªÂ£WÃ…,c\\fÃ¹CÃ§W\\fÃ¥Ã§,2Ã•Ã›Ã¯ÂÂ›Ã£Â·Â¦*aÃ©Â£\\tÂ¿Ã±{nimxpÂ² Ã³Â­ ÃƒÃ»SPqÃ–%aÂ’ÃÂ£Ã‚fÃ¥Ã¨Â‘EÂ¯Â§kwVÃ¸7\\tÃ‹Â¨ÃµEÂ¸\\bHÃÃ¤\\tÂ¾OÂ‡Ã¯PÂ Ã–Â³'
    //   11: dup
    //   12: astore_2
    //   13: invokevirtual length : ()I
    //   16: istore #4
    //   18: bipush #77
    //   20: istore_1
    //   21: iconst_m1
    //   22: istore_0
    //   23: bipush #93
    //   25: iinc #0, 1
    //   28: aload_2
    //   29: iload_0
    //   30: dup
    //   31: iload_1
    //   32: iadd
    //   33: invokevirtual substring : (II)Ljava/lang/String;
    //   36: iconst_m1
    //   37: goto -> 202
    //   40: aload #5
    //   42: swap
    //   43: iload_3
    //   44: iinc #3, 1
    //   47: swap
    //   48: aastore
    //   49: iload_0
    //   50: iload_1
    //   51: iadd
    //   52: dup
    //   53: istore_0
    //   54: iload #4
    //   56: if_icmpge -> 68
    //   59: aload_2
    //   60: iload_0
    //   61: invokevirtual charAt : (I)C
    //   64: istore_1
    //   65: goto -> 23
    //   68: ldc 'Ã·Ã½Â™Â£Ã“:Ã°dÃ˜Â¸Â±Â°ÂÃÃ·\\nÃ“Ã2-YÂ±"Ã¦YÂ–ÃˆÃšÂ‘Âv6Â¿Ã±Ã€@XfXzÂŒÂ‚:Ã¦Â…Ã¼ÂˆÂšBbÃ¦QÃ®ZÂ¼DÃ¬mwÂštÃ½Â€^Ã› ~Ã_Â Ã«Â˜Âº1]Â³Â´Â˜ÃšÃ¯Ã—RÃ¡Ãj Ãy}jÃ¤@Â¹QÃ!Ã°8s.-ÂÂˆoÂ«Ã\Â†=Â‚R>Ã›Ã¦Ã“Ã‘yÂ¤nL1\\nCÃ‹Â€ÂŒÂ’+ÃˆTÃ‰]Â¥Ã\\bi[Ã«Ãƒ}Â´uGÂ£Â¨"Â¨Q]ÂÂ¸VvVÂ®Âœ@Â´ÂªÂ¥Â«Ã Â­Ã¦=Ã­Â¡Ã¶Â­acLÂ¿p^Â”Â¿t}5Ã®!Â²Â¨Â¸sÃ¦GÃ‚Â°-+Ã£kÃ­Ã—Â¿>ÃƒN_f sÂÂ‰TÂ»Ã‚0Â£lÃ¨Â¹Ã¦Ã¸Â³Ã‡,iÂ¸Â³dÃ¿Ã—L>rÂ·ÃŸ\\rÂ§'F<Ã¿R}ÃÃ¢ÃƒÂ¨ÂŸrÃ’Ã­Â“?Ã‰EgÃ›Â’LÂ–Ã¬Â¶,Â¯Ã‘Â¢Â¾Ã¸Ã¿Â±ÃˆÃº@:\gÃµÂ±A4ZÃ·Â»Â.Ã¦WÂ¬Âº@pk-zÂ‚:6Â³;Ã¢73ÂpÃ‹8[&Â¡Ã™\\bÂ©Â˜Â®Ã¨ÂŒÂ¸ÂÂ‹Â·aÃˆÃ›Ã™`Ã:ÂŸPÂ Ã”Ã¥U'ÃŒÃ®Ã¹kCFÃ¨*Ã¯Ã†ÃœÂ©ÂˆuÃ”Â§ÂYÂ„aÂ¶Ã»`Â¬Ã¨= Ã¾Ã±Ã’Â­T\\fcÃ¨Â“aÂºÂ™Ã¤Ã€Â½Â¦x!%02Â„=Ã‰l`Â¹f4sG|dÂ˜ÃuÃ¢Â’VYÂ•Ã¿'Ã¾$-2dpOÂƒÂ‡Ã—UÃ U}Ã£#Â™9}+ÃŸÂÃ‘L;@kh@yÃ·:Ã‘Ã›:Ã¢:Â©d\\bÂ®'BlÂ”Ã—Â¤oÂ£ÂƒÃ±8YÂ‘Ã©CÃµÃ³`qÃ„ÃªÂ¿Â&fÃ•Ã”Ã´ÂÃ—Ã™Â¬"Ã»Â™(Â‚VÃ«ÂŒ%ÂÂ£K}ÂœÃ¤]iÂ²/Â¡Âƒ\\ti<~Â¸Â‚Ã³;Â„{<9ÂÂ™nÃ†Â‹ÂŸA*ZÃ…\gÂŸÃ¨ÂµiÂƒÂ¶Â“Â¬yÃ±26Â’Ã»Â‘dÃ•Ã¤SÂ“Ã‚yfrÃxÃ›3[ÂÃ´Ã\Â“Ã¹ÂsÂ¨4Ã‰Ã¬p$QvÃ©xÃ¶ÂGÃ—r*ÃqÃ¤uÂš-Ã‹Â¯ÂÂ‹PNÂ›W'Â‹Ã½Ã¾Ã£ÃÂˆÂš5XGÂ“Â‰v#?!Â…ÃÃ¤Ã¦ÂˆÂ„Ã‚ÂÃ¢ÃŸ"2Â±XÃ¿ÃœrÂª}VÃ—5UÂ¿Â«|p=gÂ“Ã°Â“uÃ€Â“~lxÂ¸VnOBÃ›8Â¼^Ã‰6`Ã‚XcÃº{Â‘qÂ…ÃÂÂ£Ã§FÂ¶%Â¦ÃÃ¾EÃ€\r\Ãˆ[uÃ‡Â‹YÃœÂ£jÃŒÂ·Ã³Ã_Â¤AÃ‹Â0#+ÃÃ¯Â¨Ã¨Ã¸}Ã³Ã±S\\bÃŒÃ£Ã™GÃ§Â³Â·Ã½Ã¡\\nOÃƒÂ‰Ã¤Ã­Â¹ÂŒ.DÃ°Â«hÃ†ZÃ¼Ã¶e%&=ÂŸÂÂ¸ÃÃ½* FÂªÂ„qÂ¢Â¥\\fÃ‡ÃÃ¤ÃÂ’$Q^4Â¨Â…Â•~Â½Ã…}[Ã‰Âƒ\\nAÃÃÃ‰*Ã½ÂºÃ°ÂºÂƒ~ÃŒAÂ«;Ã¤Â˜Â”<Ã¤+WÃ„Â~pÂ…Ã¤Ã©Â³Â¼Ã—\Ã¾~\ÂÂ‰Ã½Â—Â¥Â›hÂ¬`Ã‡^*Â©Ã•Ã¾\\bqÃ°-Â~qLfÃ´Ã—vgÃ°Â¿3ÂÃ¶W`Ã¬Â Ã½?Â„WÃ²vÃ£TjwÂ´ÃªÃ±/Ã»Â„Ã³Ã¶Â³*Â½"Ã¯Ã—ÂŠÃ›hV]Ã¨Â“XÃ¿&ÃRQdÂ®Ã­Ã¨!\\bgÃX+:ÂÃˆ&.Â…Â‡Ã…ÂªÃšpYAÃ±Â„Â¶@lÃ²Ã´6Ã…Â¶aÂˆÃ‘[Ã§dÂ”Â–ÂÃ¾Ã–Â†Â€(<ÃŸÂ Â£Ã‚Â­ÃÃŒ0Â½Ã¥Â›Â™Ã«.c&ÃºÃ¼;Ã0eÂ›#Â¬-ÃºsXvÂ³OÃ°oÃˆ6V:ÃµZ>Â¿Â”ÃƒÂ‰\ÃÂŠÂ› Ã©lÂŒRÂšyaÂ@j-2[Â™Ã²3ÃšÃ³Ã†BÃ·1Â³KC[KZ\\rÂ˜Â‰Â»X!5ÃÃ¡Ã¿ÃÂ–o1+xsÂ¼_iÃ‘Ã‚Ã„UÂ°Ã¼Zu\\bÃ2Ã°Ã·pFÃ³Ã™5ÃÃ©ÂŠÂ™Ã†Ã§VÂƒÃ¯lÂ ÃƒÃ—4pÃ†ÂˆÂ„Ã³ÂÃ¿Â…Â—PÂ…Z*>Â— 1ÂˆÃ°Ã€Ã‰xeÃ³ÂµÂ“\\rÂ°sÃoÃŒ*Â’t2{hK;BÂ‰'Ã¤XÃÃ¤ÂeemÂÂ»Â™(DÃ’6Ã¹8Âº*ÃÃ½Ã•\\tÃ†^Ã‘9|UÂŒÂ€ÃÂ4Ã³Ã Â™Â lÂ˜^GÃ¯Â®NZÂ®C.Â»ÂœÃ˜Â–Â­Âº1Â•ÃšDÂ•ÂºÂ‹ÃŠ,Â‚Â»Â¤}Â½Ã¶Â¢g}Â§Â¾Â‘.ÃEwÂ«'aÃ³Ã¿Ã°Â‹Ã“Â˜$8/(Â¡Â™Â¯Â‹cÃ·Â¬&BÂŸ}Â½Â°Ã£Ã¡Â®Ã;AÃ†TK<}ÃEÃ™Ãƒ<@@VÂ½Â”Ãº!ÂŠÃµ+Â‰{Âµ~Â™Ã’4iA=Ã¶Â©Â”1Ã˜ÂÃ—\\fÃ”Â±Ã½Ik\\bsu'}ÃÃºÃ­Ã8Ã°`smÃ‚Â‹Â®dÃ¹jjBÂ”9Ã­U7*JÂ°Ã©ÃÃAÂ°.pÂ˜!Ã¬Â˜gFRÂ£Â°dÃ­UÂœ6Ã Ã›ÂšÂ‘*ÂœVÃ˜ÂSÂŒ#EÃ²Ã'ÂŸm>P3ÃÃ‰OÃ¼Ã·Â“ÃÃ¸EÃ¥.KÂ¾rÂ¯Ã…Ã§0:SÃˆ0Â‹ÃœOÃÂzÃ‡BVÂ\\bÂ¢Â¦}^Ã¤KtÃ WÃƒÂ¨Â€Ã Ã’D.[Ã²jÂ–Âm$gÂ TÃÂ¶ÃdÂ–)Ã¿ÂÃ…Â§Â„Â FNÃ¸Ã’Ã…rÃ‰LÂ“Â”g.YÃˆÂ“ÃÃšÂ­)Â§\\rÂ¤rÃ Ã<Â—ÃÃ‚PGÃ©Â“71ÂˆÂ¿Âƒq'ÃµwÂ®\\rÃ¨Â‘Ã“Â·eÂ©Â¼LÃÂª8Â“SdÂ”rÂœÃ¨ÂŸ.-Â»Ã­{Â1Â¡Ã”XÃ«h5EÃ‰Y~m,"Ã©LÂ½\\fÃ­Ã¡Â‰Ã§Â®zxÃ€?LÂŸÂ¬ROrKA]UÂ:b^Â®|OÃ°ÂºnÃ‹$Ã¾6Â¼&+Q:Ãœ;Â³ÂµÂ¢[Â¬/Â¡(`YÂ¬wÃªiÂ¿Â¢q\\nÂ§_P#Â…ÂœÂ…Ã«Â³[HaÃŠRhrA1+ÂƒgÃ¥\\nÂ…jc3Â ]Â„Ã¼ÃŠÃ¬Ã’1;z:ÃBÃ¢zFÃ”ÂIÂˆÂ€3e#TÂ¥Ã¼1C fZÂ‰Ã˜Â‰XÃ§U~Â¦|ÃVÂªÃ˜{tKÂˆs/EÂ¾ÃÂ‰Âµ3Â¯?ÂµÂ“ÂÃgÂ¤Ã°cÃ rl[Â’Â§cIXÂ‹Ã„8Ã¼Â¢ntÂ^Â²Â½Â™YÂ­ÃŸÃ¢Â_}Ã¾ZÃ¼ÂÃÃ˜Â‹`Â6Ãœ"f\YÃ«Ã’Ã‰|Â˜DÂÂŠÂeÂ¸Â‰\\tÃª4Ã—IÂ¬Ã'Â™Â£~Â¦Â¾Ã–Â¬Â–jnh|HÃ¾Ã¸Ãµ\Ã#Ã½Â¨JÃ“Â…nÂ Â¿Â±:3Â¼g3Â¿Ã›V>Ã…Â¨Â›oÃ€Â Â˜<Â¹ÃMeÃ¥yÂ°wÃ¿0Ã«Âº7Â¯#Â…ÃÂ¯[Ã¿PÃ£1Â†Â‡Ãµf1rsHhÂ›AÂ¥Â‚Âg)pÂ²Ã¥MUiÃ¬Ã²GÃ‘mÃ¨Ã¦f9ÃªVt?Â‡Â§$Â¡Â¯GeÂ‹<ÂŸ:ÂºÃ™ÂµlMÂŒÂ‘Â¤Ã±Â\\nÃŒÂÂ° ^Â‚3Â…Ã¿}LÂ‹Â»Ã².#>Â³Â¡Pz)E!Ã®ÂƒÃ§Â‰ÂºÂ®oÂÃ¨;s;Â‰Ã´ÂlaÂ¶2ÂšqÂ´xÃ«KÃ‰:Â–{Ã‡OÂ¹`Â¡Â¾cÃ‚Ã¾ÂšÃ™YÃ”F>gÂ”1Â»Ã¸w:rgVÃ€7ÂƒÃ®\\n[%wÂ©JÂ®Â¡ÃºÃšÂ‹ÂZÃ•ÂÃ Â§/Â“ÂÂ5ÃŠ\Ã˜\\fÃˆ~8ÃœY\ÃÃ˜Ã¨Â¶Â‹Ã’XÃ¸ÂfÃ©Ã‘Â“Â¸OÃ«Ã¯OÃ¾Ã˜Ã‹Âš/Ã¯tqyÃ›\\tÂŒÃŒaÂ·Ã±Ã‚Ã…Â£aIÂ¹Ã“Ã†VdÂ§ÂˆÂ]ÃˆxÃŠÂ“ÂÃ¨vÃŠrÂJÃWÃ•4Z|ÂŠc*Âˆ" (YÃ±Â¯?Ã¦zbjÂµÃ¢Â—Ã´Â®NyfÃšZ@Ã‘MVÂ­Â¨LhÂ§Ã¬(Ã„Ã™Ã®)Â„Â—'Ã Ã³LhÃ²Â¬Ã€Â˜JÂÂ½ÃÂ¼Â…q2VeÃ›ÂˆÂŠÃ‰E'ÃœHj^Â¼Ãƒ,ÂŒÂ“TÃ¤Âœ\\nÃ“\\f1Â?TXÃ\zÂˆ mÂ¢Â¤Ã¬CpÃ£Ãs\\ryÂ¥Â¡TÂ…ÃŠ]n:Ã˜Ã¯Â¨Â­Ã¬ÃŒÂ“EÂµÃ£:b Ã‘9Ã“5Ij6ÂšÂ«Ã¡Ã¶-Â¶Ã—Â™Ã Â’UVx?Ã¥%Â—8Â³Ã»\\rS>Ã¢n3Ã“ÃœÂ´<xmCÃ„,Ã‘Â¬Â»ÃªwÂˆ|Ã»"\\rÃ‹ÂˆÂ°\\rÂ±Ã‚Â¾MÂ«vÃµÂŒ(Ã¹zÃ£.Â²2Âª Â¬,ÃÂŸÃ™Â¬Â…Â¶Ã†Ã¦ÂÃ¿j%4dÂÂ£Ã·Ã•ÃƒÃ¤Ã­*?xÂšÃŸ`Âšca\Ã‹Â´$ÂÃ¥ÂˆÂ\\tÃ°Â ÃŠÂ—ÂœÃÃ¨9Ã¤ÂÃ“Â†Ã™Ã‚D3xÃ˜iaÃ™Â¥"Ã‡Â¾] |BÃ¶\\nÃŒÂ¥Ã¼Ã§Ã¤4Ã¶01H0Ã‹|Â½Ã–Ã°W ÂƒbÃŸÃ­Ã¬bÃšBÂˆN;!W0Ã„Â¸Ã£Ã«A.Â«'Â¡Ã˜}Ã®hÂ¹[dhÂš2bÂ¡vÂ¨4TrWÂ¦9Ã¿Ã›Ã€Ã´Ã¾Ã€fXÂ­X5Â©Â¯Â“Ã¹Ã¼ÂŒÂ´Â–RIT"l3Q@fnx\\belDuTÃ“ÃºÂ†dÃ¨ZfÂ‘Ã›Â Ã•W_ÃŸÃ²Â\p&Â¾Â›ÃºÃ´Â¶iÂbÂ–s*ÂŠ8Â©Ã‘Â‚Ã‡>ÂÃšÃƒÃ§K {YÂ­"Â„Â &H&Ã—1LÃ¬BÃ¦Â´Â¿JÂ‚}AÂ‹\\bÃ˜ÂÃ±Â·OÃªÂ¢Â‰Â\oÂ¤ÂƒRÃÂ³Â„Ã¹yÂˆÂ´Â\\rÂ¾Â±Â¥}ÃœÂ…gÃ’ÃƒcÃ¼Â–Ã®0}$Ã‡oÃ¤Ã®ÃˆÃ·f:muÂ²IÃ°rÃJlÂ™=ÃµNÂŸ6=]Ã»TÂ¾Ã¶Â¢Ã²ÂŸÃ¯Ã°\\fÃ„G/Â±Tt7)\\fÃ­Ã¨Â‰ÃŸÃ%5Â‚Â¨U!Ã¢Ã™#.Ã¥ÃŒMPÃ–Â«Â‘Â´ZÃPÃ­Â™ÂÂŠÃ8^/GFÃ _Ã®Ã³FÃÂ°i\\nÂ–Ã¹[GÃ‡Ãª.9Ã¿XÂœ\\t\\f~Ã‘Ã±ÃÃÃ¬Ã‚}Ã©Â‹ÂŠwÂ¦Â¥~Ã‰eÂxÃ£ÂºMm)SÃ¥Ã]ÂÃˆ3\\bÂ©Ã’}Â™k?:emU(J)"ÃªÂ­Ã¹zDÃ‰Ã½Ã¸ÂÂ£Â€Â¡EÃˆ5Ã©Â§XÃ±+dÂ´Ã¿S\\b#ÃºÃ¹]IÂŠÃ’ÂºÂªÂ´1ÂšÃÂ«ÃÂ²Â¡Ã¬Ã8/ÃªR"ÃXÃ•Ã’ÂŠÃ‰\\rÂ·YÃ”pÃZÂ„,'P,ÃƒÂ–Ã‘Â£BN(Ã¾Ã£\Ã´MIeÃœÂµÂ˜sQlÂ°oÃˆÃ¡1Â’EÃ¢Â±Â¹Ã©RZGC\\rM\\fÂ­Ã½Â¬:Â¥Â®GM*ÃÃ®0ÂŒÂƒÃ‚ÂˆKÂ½Ã“AÂŠLBOrÃ—Â°Ã®Ã‚\\t\\tÃ Ã¾Ã¢Â®ÂˆÃ¯AiÃ“!Â¤TÃ§Â…zÃ’K$ }Â”%Â‹qÃ•rÂºÂšÂ”rÂnrpÂ±?8Ã±ÂºhÃ‹Ã©pÃ¢[\\tÃŒV&AÃ©\\tÃ·Ã·)PÃÃ¬Ã Ã¸Ã´OÂ¾+Ã–Ã­Ã‚Â›Ã¬Ã Ã¾Ã¸Ã¨Ã¨Ã¨ÃÃœ\\tÃ½+\\buÂ³Â Ã»ÂÃºÃ•ÂˆB c)kÃ–Ã¾`Â¹vÂ„Â±Ã°Â‘Â»ÂŒÂ©Ã°bÃ‰jÃµÂ¢4TÃ”Ã½Â™Â…sÂ§Ã¤Ã€Â¨Â¸Â‡Â²Â«Ã‰9{*Â‹ÂÃ˜ÂÂ]ÃŠÃ–Â‘YÂ±#Ã°ZÂ2[ÃÃ¡G?Â¤Â¿NÂ—lÃ«Â™ÂŠÃ >iÂ“Ã«Ã½ÂƒÃ´Ã¡OÃµbiyÃ¯'Ã—Ã—:Ã«Â‹Â„KÂÃ™\\nÂ¹_ÃÃÂ€ Ã›*Ã©NlzÃÃ\\tRÃ‰;\CqÂ™i*Ã±T#\\rÃ¨Â‹xZ?ÃšÃœÂ¾Â»ÂŒRÂ›Ã¤@m9ÃœÃ®ÂƒÂºÃ¶Â¬Ã‹ÂœSÃ±`Ã”ÃbBÃ¡Ã B8Ã¸Ã¼?Â—Â‹EÂŸÂ¯#cÂ›Â¨Ã¨GÂ«0Â‹Ã£JÃ°gÂŠ\\bÃ¥l'ÂºÃ2Â«<ÃŒÃÂƒ<wjÂµdÂ´]B)sA\\bVÃ¡7gÂ…Â».]ÂÃ‹Ã¥ÃÂšEÃ¥#Ã³Ã6Â»Â„Â£mLÃ²4Ã­ÂµÂ·ÃÂw%Â­Â”jÃ¡vÂ¹^4&Â’Â¤Ã„IÃ¥oÃ¤Â£Ã‡Ã¢p%Ãš|Ã‹\\rÂ¿Â‹Â‚/Ã·WÃªLÂ‰ÃŒÂ£Ã¡Â¹Â¦Â€*Â—gÂ‘f0Â¨Â­Â¯eÂ©TÂÃ¹Â•%Â»:h1#<ÂŠÂÂÃ–Â”ÃÂµY}Ã²dÂ£Â­Ã¼Â¡]^Ã“YÃœÃ¢Ã´NvÃ­Â¯ÂÃ³Ã¢T\Ã—Ã–Ã²7Â¿ÃœE[ÃˆÂ¹*@,Ã£|x\\rÃšÂ‹/ÂŸÂ«Ã´Â°Â‘ZÂ¿P63nÂ¥Â¸Â˜Ã—VÂ;!Â›A7ÂŸÂ¿5ÂÃº9Â¾ÃµÃŸÂ´Ã°ÃÂÂ‰1J{yÂ½Ã–_UÃ Ã¶*tLÂ¾-Â«ÃŸ,Ã»Â”Ãª0dÂ¾QT|Ã°Â°*Â€C}ÂˆÃ”jÂŒÃ³Ã‚|5VlpÃµÃ‰Ã¨Â Ã›ÂŠÂ—/Ã·ÂˆÂ‚ÃšÃ•ÂºNÃÂ‰hzLPÂŸ&Â¶=?Â‰Ã­Ã…iWhÃ²Â˜Ã‹\\tG=ÃœÂtÂÂ˜Â°Ã›7(@nÂ‡kÃ«Â†Ã¸ÃŸÂ-}Ã•nÃ¤ÃŸÂÂ³Â·Ã\\r@Â¿Ã°wÂ¥Ã•UÂ‡Â Â®Y71`Ã—GJÃ·7YÃÂ†_Â¦Â±ÃŒÃ¾ÃŸXÂšHvÂ·Ã¯Ã‘Ã±ÃÂ¸Â¿Ã¢Ã£&PÂÂ¹<Ã›Ã£Ã¢Ã‹Ã”Ãˆ#Ã´~\\bÂœPÂ—Â–Ã“~+~1\\tDiÂ‹Â¿ÃšlÃ™Ã“Â‰ÂŠZ3KÂºÃ“P%:qÃr)C1Ã‚Ã£M>cX=-Ã‘Ã¾Ã±ÃoÃ´Ã·hÂ²B.lÃ ppnÂ†;Â€]J#ÂªzNÂ›Â¤Â<Â°Â£jÃƒÂ¦ÃmÂ‚Ã¥ÂŸÃ·Â—.:9ÂŒÂBÃ•ÃšÂ¾[ÂŸGÂ¥Â¿]nÃ¯Â zÃ‡Â”1@MXÃ£\\rÂ±F;BÂ›Â’Â¼Â£Âˆ4<Ã–E<^Â„:<ÃŸÂ³Â—Ã¯rÂ”BÃšÃ¤Â¸Ã‘Â°Ãƒ?I.zHÃ¬ÃºNÂšÂCHÃ©EÂ€zÃªÃ²Â¶ÃŠÃ”Ã‘Â¨,jÂ…VÂŸÃ¸Â•g_Â½9Ã«ÃˆÃ‰ÂÂ™ÃµÂ›Ã Ã«Â¾2Â®Ã­ÃŒÂÃŒÃºÂ©Ã¼NT&Ã¿\\buÂ+ZeÃ«0SÃ´3Â­  ~Â»L/gÃšÃ‡Â²Ã‘VÂ¸Ã¡ÂÂƒ\\nTÂ‡ÂÃ¤_Â¾Â¦Ã„Â¾Ã©Â¿ÂÂ¿|nÃ‡fNfÃ„Â®Â²Ã­bfÂºsÃ»Â¶DL9Ã¢Ã¿Ã•cÂ B5=\\bX;Ã°Ã“>Â—ÂÂ²Z\\b Â¦1Ã®aÃˆÃ¾;ÃœÂ¤$rtÂ¤Ã¯=Â´Â…ÃŠÂ­ÃqÂ¸KBÂŒx Ã¨cXÂ—ZÂ«L"Ã’Ã\\nÃ–Ã–Â«@[\\rÂÂ¢%cuzÃŒÂƒÃ§Ã€Ã•Â•\\tÂ‡Ã¶ÂˆÃˆBÂ….Ã™Ã´]Â“W]^TÃ“DÂµÂƒÂ‚Ã¡ÂœÃ³ Â‹Ã§'\\f|Ã£Â‘OÂ®\\nÃ´Â±QRÂ¦Ã`Â·Â­p|Â„Â€02(\\nÂœv2,Â²Â®``Ã®7Ã¤>ÃŸ6Â˜TXÂ“mÃ–|Â„Ã¤Â›Ã“`GI|iÃƒfvÃ‘eTÃªsÃARÂ…Â6ÂŠÃŸÂ¤ÃºÃ…Ã¥bCÂ—Â–qÃ¯\Ã¢Â·Ã§Ã‘ÂƒÃµ*uÂ•Â°Ã«IÂ„ÂšeÃ·uÂ”Â„Â£ÂºÂ®IJÃ \\bÂªÂˆNÃ(Ã¸Â“Ã‡\\nwÃ­Â”"a^Â“Ã»Â±Ã‰PeÂŒÃ°DÂšÂ¸Ã¯aÃ¹\\nwÃ Â¿$Ã¸Ã–,]ÂšÂZ!\\rÃªÃ¼M!Ã±ÃÂˆÃ§4ÃŒ"ÃÃ¼Â¬xÂ¶Ã§Â±v)Â‡Â†Ã‡Ã½n\\bÃœ#rÂ¿Â³qÃºÃ±^DBÃšÃªÃŸuÃ©Â™ÂƒÂ™ QÃ»MsÃ‡Ã”5Ã¦C)!Ã‡-{PBFÂ„Ã»ÃµQÃŒJÂ‹uÂ,Â¦Ã›sÃ§&Â¿yhÃ£y?Ã½Ãœ)kÂ¦@Â¬ÂÃÃ“Ã¯ÃµÃ¦Â¶*}YÃ4uÂ­Ã„Ã¥pÂ•ÂeÂ†Â‚Â¥aÃ´Ã‘ÂŸr}7Âº?uCÂ“Ã·Ã—Ã©5\\rÂŒÂ”/Â-Ã¿>KÂ›"Ã‡Ã£WÃ¾c\\fWÃ²b Â:~VÂ¢hÂÃ¦Â¤fÃ¢Ã—Â·Â®ÂxÃ“ÂŒÂ¾oÃeÂ~Â™ÂŸYÃ°Ã€SÂ¦L.n`Â§ÃoVU(}Âƒ\\tÃ½ÃÃ¯Â½ÃœÃ†ÃcÂ‡Ã˜Ã‡Â»Ã¬Â—Âªd]]Vy+Ã†hÂÃ²\\nÃ Â\\fj\Ã¾ÂŸÂ’$TÃ®2Ã«!y/ÂƒÃºÂ ÃÃ®ÂªÃ¡UÃƒPWÃ¤Â½mr,Ã‚Q6Â¾Ã¤ÃŸÂ®ÂÃ£Ã¬Â¥]KN.GÃªÂ¡Ã¦Â¥?vÃ·Ã€Ã¡Â®ÂÃƒEÂš=Â¦%Ã«Â¦Ã”jÃ¬\\b*Â½\\rÂ¬Ã•Â¼bHÃŒpÃ´8deÂ¾Â›Â·FÂˆuzdI7Â–ÂÂˆÂÃ’Ã™Â§DÂ“Ã®ÃÂÂµ%Ã€ÃˆÂ‡~Â»Ã‡vÂsÃ°~Âµ>gÃ«Ã‡LÃ‡ Â¡,}mÂÂ½Â¡Ã›ÃµL^ÂŒÂ€Ã˜Ã¢Ã»Â¥Â’Â—{Ã•Â¹Â‰?79Â¿Ã¸R4Ã¶Ã¿ÂueÃ˜Â­ÂšÃ§bsX\\bÃ­Ã®D-gÃ¬ÂA${DÃ¨?\\b%p9]ÃºÂ²#Â¹6Â±MZ>9Â¸Â¯##GÃ Ã¬BÂ ÂºÃ£!Ã¾Â‹AÃNÃ´Ã¶Ã ÃÃºyR=RÂ Â²ÃÂ©ÃŒÂ£Â„6Ã¡Â‰ujÂ‘+Ãš]3ÂŸÂ¤Â´]ÃŒÂÂ©AÂŸÂ‡3Ã•#ÃŸO+LÂšÂ‡Âº]Ã¸)Ã›Ã´fÃ™NÃ®Â“;`JÃ¯Ã±XÂœÃ¼Â£Âº Â¥`Ã‚+Ã¨LÂ†Ã¤Ã¿Â2Ã”Ã–{e<uÂ»Ã¥Â‘Â”yÂ™Ã²iRÃ£f%{lkÂ‹tÃÃµ#Â›Ãœ?Â¶}~Ã–WÂ¼Â ÂªOÃ›'UÃšÃs/Ã’-MeE`:pÃ¦!ÃÃ¬Ã®Â­^Â¨Â¶-RÂÃ³ÂªÂÂ«Ã :yÂ†Â™Ã¸Ã’>Ã€;ÃºJ`Ã“uÂ ÂˆÂ¢Â‹\\nÃª~Â,Ã©ÂŸ%Ã¯XuÃ„Ã‡Â€Ã³Ã«2Ã¥iÃ°ÃªÃŠÂƒ&?Ã•ÃƒÂ‚ÂƒÂ¢ÃÃtÂƒ+XÃŒFÃ¿81ÂˆÃ’SÂ¡Ã‰QÃ´Â“]Â³y|PÃºÃ¿?Â“-ÃµÂ¨Ã‹SÃ‚Ã£sÂµÃ–8ÂªÃ“Â—PÃ„v"uJHÃ¢Â½JÃœÂÂ™Â’Â°Â‚Ã¦ÃÂÃªÃµ<Â ÂƒÂ‹HaWÂ®Ã£VvÃƒÃ d*ÂÃ¾Ã‰Â !Â¶Ã’Â§uÃ®Â•Â“Â’Ã–%Â†3s.ÂŒÃ°TKÃ\\fÂ‚RN{jÂ¨Ã‹\\rÂ·Â‡Â›Â‰1fwÃÂ¦Ã¯+Â¿!Â«YÂ“ÂšÂŸVÂ½4Ã€Â„Â¥G)Ã”UÃªÃ§Â¥yÂ•Ãš^0Ã‚Ã¨Ã¼eÂ·qÃ¡?NÃœÂ™iWÃ¬Ã88Ã©'p^o8Â¡ ÃÂ¶Ã¡Ã¢Â¸]VÂ¯6ÂªÃ¦Â˜]{Â’|Â¼Ã®Â‚Ã°soÂ˜t)\\rÃ Ã‘j\\bmÂˆÂ‹Â–Â¾Â¸U[~e`pÂ³nRgMGÃ„Ã²ÂŸÃ“ÃÃŒÂƒÂ•Â‹Â·Ã¥UQ[[Ã³:ÃˆdB+ÂµÃ†XÂ–ÃŠ\vÃŠÂÃ±Â…Â‰Ã¤7Â‰Â¡+ÂšÃ»\\rÂ½i4Â¬ÃŸÃ¯Â°Ã½zÃ¡2Â—Ã²Â Ã°#)WÂ°Â’Â±Â¯eÂ¾)Ã‰v`j,gJÃ¢UÂµÃ‘ÂKÂÂƒÂ Ã”aEÂƒÂ“Â¶ÃºÃ†Âœ$Ã—)bÃ¬ÃÂ‹&Â‹ÂHÃ…RÂ¼KmÂ‡Ã–Ã›ÃªÂšÂ±4^@Ã Ã³sÂµÂ’ÂªÂ¯Ã„ÂI+Â£l&xB\\r\Ã¨fÃ†Z<OZHYCÃ§5Ã®Ã¸Â˜Â½:Ã‰OÃ‡ÂªÃ¹ÂÂ¤r*Ã \\b/{$'>?VfÃ¨Ã²jÂ³=]Ã½jsÂ²iÃ¾Â¾Â¶Ã’ÂÃ“8Ã¥Ã°@Â™.\\tÂš1ÂƒÂ¢2K~Â¦Ât7:Ã”ÂÂƒ[Ã²ÂŒÂˆÂ›Â·]Ã¦Ã‰[\\nÃ¾jÃºÂ›x}Ã…Â›Â¹;7Ã´Â¶Â…Â¼Â³Â»vÃšÂŸÃ¤gEÂ¦NÂ‚}]ROÃ¹Ã¼Ã…ÂºÂƒÃ…lÂ\\bÃqÃÃ‰Â´~Ã£Ã¥Â»Â¢ÂªÃ§,Ã®Ã†b^ÂŠÂ½ÃÂ©Â¬Ã¿Â‘BÂ—ÃmÃ–ÂÂ†Â³f:zÂŠiÂ–Ã¬Â†Ã¢Â‘Ã€ Ã¢IÃ¥Â¥Ã°Â¼Âœ7v3Â‡8ÂœÃ¼ÂŒÂ‚Ã®Ã¬Hx Â¡0Â‰Â¶ÂÂ°Ã‘Ã¨Â³Ã¯<Â—Â¶Â—*H= Â¦^<(Â¥$IÂŒÃ¿Â‰Ã•~ÂÃ´{ÃºÃ²'kÂÃÃ¼Ã‚6* Ã€&IÂ¶ÃŒÂ¼ÃzgÂ–5#\\fÂ¦fÂ[ÂŠPÂ‹AÃ—Â¼Â‰Ã±* @D\\tW\\rfiÂ˜iÃº ÂˆÂ¶Â³Â¿Â¦^Â¶yÂXFÂ¶+-Ã9Ã–Ã¨Â§tÂ‰Â°Â‰ Â vÃˆ{Ã·+Â¦kÂ~Â’Ã¤ÂœÃ¹Ã½EÂ™Ã¥ÂÂ‘Â§ÂŠÃ¡lÂ•YÂ–NSÃ¬8dÃ»Â½VdM&ÃÂ€6Ã³Ã—dÃ–Ã‚ÂÃ¦|+b*\\t}ÂŒÃ°4Ã¤Â”qÃºÂ‡i!S0Ã®Ã©Ãª:4Ã€Ã¬Â¦5Ã¿zÃ‘h[?1Ã€Ã˜Â«v2ÃÃ·Â™Â#ÃœÃ¤ÂºZZÂ¥Â„Ãº4YÂ·Ã¡VÂ‚Â«Ã¡ÃŠÃVÂ¬crÃ¶Â§jXÃªÃ¹\\tÃ™DlmÂ¥"Â‹dgÂŒBÃ¹Ã¦ÂªÃµÃ’g9ÃxHÂÃªÃ®jÂƒÂ®`tÃœÂ“ÂŠÂ™Â±7Ã‰3ÃˆÃ—h.Â¶Â‘Ã¹Ã‰Â–sÂ„a>Â¸Â¹Ã·Â›Â¸TÂ²Ã“ÃRÃ–Ã´q3jnÃ’?/Ã†Â¢$Â«X<Â•eÂ¶y Ã³4#ÂƒkÃµÃ¦ Ã®zÃ½Â›Â»u8Ã‹Â¨Ã Ã·ÃŠyÂ‰Ã–Ã¼Ã­\\b<a7EÂ¾Ã’Ã±Ã£xÂ½ÃšÃ¨EÃ†Â›Â¦>EÃ5ÂšÂ¥Ã‘Â·ÂÂ„p]Â¬Â‹Ã‰uÂ‰Ã¤Â”W3Â®Â“Â£Â¶Ã©ÂŸÂ³Â§gÃµÂ·$+Â‘1\\n"Â¬FÂ¬Â¸`Ã‰O7=MÃ°Â¸lÂŸdD-Â¦ÂÃ‚ÂšÂ‘Ã«CSÃ½Â“Ã³Ã½Q^Â°\:ÂÂŒÂƒÂ²ÂˆIÂ½:Â¾h;eSÂ£Ã‡Ãª:Â…[Â»Â®]ÃˆC.]5ÃÃ Â’Ã¹AÃƒI}Â¤Ã¹Ã¬Â­BIÃ‘Â›ÃŒuHÃ•Ã 0Ã£ÂÃ•r>Ã‘^eÂŠÃµNFÃ¢>^@Â¬ÂŠÂ‹Ãµ+rJ2n\\rÂ©ÂÂ¤0Â´Â¯Â_8JÂ‘HÃ‘\\rÃŠÃ­0 Â›Â–3uÃ«Ã¸I:ÂºÂ³qÃ‡Ã£nÃ«Â² IzÃ˜Âµ.0+Ã›Â”\\bÃ½Ã§Ã¨Â§TÃŒÃ½EÃ°Ã›Ã…:Â›ÂšCÂŠÃÃµÂ´pkfÂ´|4mÂ|Ã«Â»Â¢Ã“Â¤Ã‡Ãœ_Â±Ã²Ã‚ .5ÂŒÂ¸Â¶>ÂˆÃ¥Â¥Ã´Ã‘/Ã]rÃ„Â©\\nÂ›ÂºAOÂ™ÃºÃ³ÃÂŸÂ«ft4@ObÂœÂ¹d0qÃƒÂ€Âµ\\n\\nÃ—Ã§fÃ8Â‡$I0Â»3MÃ›Ã¹Ã¢ÃƒÃ«Ã\\nuW_pj!ÃÃœÂ Ã FBkÃ«Âˆ"Â˜Â Ã³ÂŸÂ¹rÂcGÂ•nÃ½6Â„9Ã»Ã½Â¯Â½8ÂŒÃ‡Ã›KÃ„!Â™bÃ·ÃŸÃ™Â‹R'Â”KÂ—Â‹S Ãº+Â¼Ã¶Â•3Â‡Ã˜wÂ“?Â¶9Ã¦oq.bjdÂ´F@F`Â§VÃ‰\Ã¹Â‘,ÂªÂµGÂœÃ¢PbÂ\\fÃ’Â¡Ã˜VÃ¼"RÃºhÂ…D*oÃ¡)Â„Â¯Ã¼Â´yÂ¤Â£Ã˜+2Â®lÂºq<Ã‘ÃaW/ÂMÃ¬M$UÃ— \\tÃ­Â¶\\tÃ˜=\\nÃ¯kÃ»Ã½ÂœWÂ‰ÂbhÂÃš;Ã¾fÃ‹Ã \\rÂ…}Â‹'#&Â—nJÂ¹qÃ¤^ÃÂ€Ã¦ÂÃ¥Â‡Ã§ÃµÃ¿j\\bÃMxÂ¤ÃŸ\\bÂ¼ÂœtÃ®Â´nÂ‡ÃšSÃ¢Ã¼6Ã·Ã™(CMR&[ÃˆÃÃŠxÃ«ÂÃ¼Ã¹Â°&Â®7_\\nÃªÂ VÂŒ\\rdÃ·Â­\\fÃ•Ã¤Â¯-ÃœÂ¦Ã–Ã¨Ã°Â™Â©ÃªaÂ‰O0 Ã–Ã«\\rÂˆÃ®5Â¨Ã™ÂÂ‹Ã‘ÂºnsÂ±ÃœÂÂŒUJ>uÃ›U+ Ls]Ã¸P7"G.5,Ã§xVÃ•snÃ´ÃŠlÂŸ'Ã¾Â¥FÂ¥Â¡Ev|2Â¦kfHÃ»oÂºjÃ»Â·\\bbVaÃ¬>ÃÃ®Â˜Â¶ÂªTÃ‚GÃ†Ã¢Â®ÂŸÂDÂ³lUÃ!mÃ‚Â¾Â‚Ã¦ÂUÃÃ¾jÂˆÂši3Ã¶qIÃ•Â¿yDÃ¼sÂ¾!Â“Â”\\nUÂ¡XWÂ‚ÃµÃÃ€\\rÂ¯Ã†KA:CÃ‘`+Ã¼CBFÂ².Ã¹J/Ã¥Ã£ÂºÃ¶RÂ…rÂ 1ÃŠÃ–Â±Â±'7MÂ´/hUnÃŒÃªJ >Ã´W~%GTxÃÂ±mÃ€=q0Â¦]=Â²ÃÃ¥9@Ã´@Ã¨iO"ÂuÂÂ£Â¦&Â¨Âª9'ÃœÃ”ÃµÂtÃŒÂÃ«Â‹Â­^Â›Â…R.Ã³Â¡Â‹FÂ·Ã±Ã¿Ã«Âµq:)WÂ“d6Ã‹Ã Ã’Ã¹Â‰Â¿ÃkÃ’Â˜Â $Â”ÂºÃ„0%Ã½9Ã¢Ã’77ÃºÃˆEÃ´Ã§!2Â‘,Â’Ã™<gÃ²9Â‰Â¸)Ã­pPÃŒÃ¢l9JÂ¢4Âš1mÂµÃ”\\fÂ‰ÂŠt^Ã›Â¯Â¨OM ÂtÂ²ÃœhiÃŠÂµÂ±Â¬Ã›Â†ÃÂŸÂ°Ã¨Â†fA7Ã ~ZÃœÃŸÃ½PÂ¶Ã›Ã‹Ã‚Ã—9Â¦Ã™6ÃƒS#|0Ã”FÂÃ—ÂlÃŸC~qÃ¥ÂÂ±VRÃ²Â•Ã¡Â±Âœ\\f/Ã )E_Ã°RÃ¿MÂÂDRÃ‹Ã«nÂ¸Ã‡Ã¯Ã”Ã‘Â‘Â‘*S0XÃ¨ÂŸÃ†\\fÃ«?Ã¼Â¼Ã‡B=Ã‡Â†Ã˜=Ã™ÂªSÂ»KÃ¶]Â”Ã”ÂºOÃ•Â¤\\fÃˆcÃ‡Â™\\fYÂ¬Ã Ã®Ã Â¾Ã€Â¢,EÂ¡ÂˆÂÂŸYÂµZÂª ÂÃ•]Ã¥Â„Ã’VÃ«3ÃÃ©Ã‘ÂŠÂ¡[?ÃªÂ°/]ÂÂ¯Ã§Â—Ã“Ã‹Ã¾ÂƒÂ®Â’)%MOÂµÃ„HÂ²vÂ’o`Ã²Ã«Ã¸&Ã€Ã€LUÂuÂÂ?HÂ»Â¾\ÃªÃ·(Ã’ÃÃ«ÃšÂ•IÃ”Ã¯-Â¤Ã–?A(Â7]Ã©Ã‚\\tÂšÃÂ7Â—Ã¨Ã]uÃ£SO*ÃLF]Ã¸Ã”Â¾Ã‘RÂšQgÂ¹ÃÂÃ¥Â¸?Ã¯DÃµLÃ»Ãœ:I.Â¼yWoÃ¨;y]PVÂÂƒ,/Ã•Ã›NÂŠÃ¼jhÂ©)Ãv,Â…V2Ã¾DÃ™Â©gÂ›8AÂ²lÂ£sÂ´Ã«ÃÃˆÃ˜Â›\\nÂ¼Â’ÃŸÂ‘?ÂµFaGÃ•\8Ã¢+7ÂªÃ±.ECÃZÃ¼Â§#Ã…Â±Â½GÃDÂ—Ã¡Ã³Y{R`ÂÂ‡ÂºCÂ !\\bCXÃ±\\tÃƒÂªÂƒÂ¾Â€4tÂŠxÂ©Ã›Ã²Ã¤Â•9Â¥ÃŠ&Ã´Ã˜ÂÃ‚"Ã‹MQÂ€qTzÃ•Â§oÂ„ÃÂƒÂ‘J[OÂ¢ÃÂ²XÃÃ\\futÂ·Â3Ã³dÃ¤nB5Â°5Â¸Ã…Â§Â¡Ã«GÃ¥KEÂ‡m]Â©-ÂÂ¸Â¼Â’Â§Â»Ã¯"Â•Ã¯ÂºÂ¬Ã’Ã†+\\bÂ­{CÂŸ\\fÃ GEs]ÂÂ¿Ã†#Â‰Â¥Ã®JÂ¬ÂÂ¯Ã£aÂ‡ .tÂ¶ÂPR4Â¬hÃ”Â‡Âƒ%Ã”Ã¸ÂšÂœÂ¾ÃºZ2?Ã³Â³CÃ•Ã•(,ÂÃ„ÃÃ Ã¦EoÃ‘Ã›XÂ¢Â¾)Ã‹Ã¯(B\\bÂ”qÃ†\\tÃ£Â•\\nÃ³&HÃŠÂ…\\f5UÃ›Â’ÂÂ 9EÃ²Ã¶sÃ„ÃÃ„Ã¸,H&.FÂ°\\\nMÃ¼\Â¬Ã¢Â°Ã¶dÂ»Ã•SÂ¯Â„~ÃƒÃ¢nÂ·ÃÂ§Â–Ã—Ã‘Ã‰ÃºÃ‚Ã¬ÃÃºÃ´Â¯Ã»ÂÃ»Ã˜ÂÂ¡(Ã¼Â¬\\tÃ“Ã˜Ã³7Â–PÂ’S5Â’Â¹Ã·Âq6ÃµÃ—Ã¾'ÂÂ²!dÃ­&Â·@bÂ’Â™yÂ¨gDÃ”Ã‡i1ÃEÂ…Â»gÃ Ã³AUÂ²1Â³Â´VÂ•Ã±Ã…Â²\s ÂÂ–ÂÂ»ÂÃšQe!=,Ã“Âœ(,Ã£7`Â€sÂ“Ã\\tÂµ7bÃ–1Â+Ã‡ÃŒÂÃ­5VÂ¥Ã£Â‡ÂÂœOÂ›)Â‘ÃY<Ã…Ã±Ã‡Ã’ÃƒOÂ»Â¡`'KÃ—Â¿4'Â4,ÂœÂ´Ã˜ÃŠ|!+8ÃYÃ† a/3Â ÂÃ¹ÃƒÃ¹JÂ·Ã¨!Â¿ÂˆÃœxÂ™Ã•RÃ€yÃŸÃwoÂºÃ½BÃ¤Â©RÃ“tÃÃ²Â¶Ã¦Â·ÂÂ“^]*ÂŸÂ¢1Ã‰yÂ¾Â§OQÂ¦Â°xÂÃŸveO6{Ã©Â’Â”ÃœÃ…Â‡\\tÂšÃ‹]Â¨L[lÃ—Â®9Â¬AÂ Â“Ã¹xÃ½Lk Â *~ÃºÃ¬Â”Ã‡Ã£Â–=ÂºÂŒ^P>Ã¿Ã„LÃ”%Â™\\n*!Â\v`ÃÃ¢fKÂ­Lkq0qÃÂ®Â‚ÃÂ¢Ã \\fHÂ£OÂ³zZÂ†ÂˆÂŸ<^z6/Â°I\\tÂšÂ£Ã¤Ã´[Â…SÂÂ´DÃYDÃƒjkÃ2Ã³t2Ã­rÂ£Â‡yÃ„Ã–uÃ°ÂSL0Ã˜Ã´Â¥Â¶LÂ¸5*Â Ã¤ÂÃÃƒAIÂ˜Ã½4Ã·JK`ÂˆÂ“Â·ÃÃ Ãµ^nÃJÂ‹Â ÂˆH`&">"Ã¼Ã¹Â‡Â—Âƒ\\bÃ¶~ÃŸ*e"ÃˆYcÃ‹!Â—".Ã˜Â‚Ã¶Â¹Â§|(Â²MWÂ‡Ã­Ã†Â—?Ã—]J"iÃ­]Ã„ÂµÃ®Ã•Â’Â¨Ã¢Ã±Ã(Â‹BÃ¡Â©Ã•Âª\\f[ÂZ4qÂ®Â†Ã¿aiÂ—VÃ¼ÂÂÂ¿r$g,Â–Â‡Ã”ÃÃ‰Ã¦\\bÂcÃ¯&Ã¿ÂÃ‰9ÃÂ‡Ã’ÂÂ¬gÂ«Ã‰,Ã¬YÃ–ÃˆÃ™_dtW$Â‘mÃˆ\\tÂ¡Ã·Ã³Ã”/Ã“Ã¯Ã´0Ã”a=Ã§Â›Ã›\\fÂ«2Â¼ÂµÂªÃ•Ã…Ã¢Ã0ErVÂ‘Ã Â¾GÂ‚\9Ã¢3Ã–Ã¥vÂ—nÂ±8Ã¬hdÃ®ÃÃ¸.Âº=ÂŸÃ9Ã†9Â±/uÂ¸Â…Ã‹Ã™Ã¢Ã´Â©Ã·Â‚Ã.Ã¼}Ã‡0ÃÂ»@h#Â“Ã­Â¦AÃ‡Â¦Â•Ã½Â±kumrÃœ]Ã®Â¥Ã’.ÃšÂ›WÃ§D Â…TÃƒÃ±#0Â¬Â©>Â¡Â4Ã¡sj6=ÂŒÂ„]Â¡ÂƒÃ¤Ã–Â²Ã­\Â…Â¼Â«z9duÃŒGÂ¤ÃœÃÂ°Â¼x,ÂœfÃ£Ã”/ÃŠ65XÃ»Ã—ÂŒÃ¤Â³,eÂ£Â€kÂ…uÂ­Âˆ&Ã‹Ã˜}P0#8Ã‚Â‘HÂ ÃÃ˜Â»Ã¿WÃ®^xÃ°WÂÂ<Ã¾E{pÂ´Â».Ã°Ã¿lÃÃ¿J\PÃºÃ\\bOsÃ¥\\rÂ™Ã“ÃˆÃ›Ã¨\\f\\tÃŠhZ@xI5<bÃµÃ3Â˜?Â«HÃ…Â½6\Ã¿LÂ¡@Â‘Â‚Â¬Ã†MÃ¸EwaÂœ9ÂÃ¥Ã¢Ã¡7Â».;h5ÂÂ•? Ã¾ÂŒaDXÂ®K\\nÃ½Ã–nÃ¨Â‰|Ã“E`1Ã‘ÃµÂ™Ã Ã¡\\bLÂÂ„(Â·ClP=_Ã–ÂƒÂ’DÂ´-Ãˆ=b_Â‘IrRÃ‡ZÂ·ÂÂ¥Â…{\\f\\tNÂ£ÂzÃ³Â‚Â€Â’EÂ¢ÃŠc<ÃªÃ¿mÃ«X,DÂ¯ÃšÂ¹0Â€ÃXÃwjÂÃ±Ã±eÂe5oÂ lÂ£Ã£Ã¥Ã˜\\nÃ„Ã¶Â¨Ã¼LÂ¡Ã´ÃÃ€,ÃŸÃ°?Ã®Â–Â­~Â´Â¨YÂ¶0ÂÂ©Â‚bÃ·Ã”ÃƒÂ„sAp3Â¾bÃ³oÃŠÂ¤ÃÃ‹Ã‡HÃµB4Ã·wÃÃ¯}Ã´Â¤ÃŒ3sÂ¬ÃDK\\b#bÃƒÂ²9Ã‡0Ã¤LÂÂ—ÃÂ´Ã˜3ÃÃ±Â¿X\\rÂ¶OIRÃ”Ã ÂÂ¯ÃÂ¼ÂˆÃ·wÃ•mzÂ‡Â˜Ã–Â”Ã•Ã)Ã‰\\fÃ³tÃ¢ÂœÂ—ÃjÂ§Ã Â j3Â‡:Â Ã‚Â•Ã·Ã¨Â‹Â€Â½n\\bI&Â±Ã³Â§ÂªÃ°(Â»WÂºÃ²%ÃœÂ¸{XDÃ´ÂŠ'`EÂÂ·QGM/pÂ´hTÃ§xÂ.Â­Â”ÂÂŠÃ¥Ã·Ã¨Ã™Âœ(~ÃƒÂ­u,eÃ˜Â¿Ã¼+jIY\\b<Â•Âš]Ã¼ÃˆÂÃ²Â Â·ÂÂ±Ã‰ÂJÃÂgÃ¼pÂ›)Â‚(AÃ¹HÂ´IÂ£Ã‰Ã¬ Â¡SÃ®Â„xÂ—Â¶5wIÃ³wÃ’Ã’Ã›Â†IÂ³HÂŸT\Ã±(Ã³0!Â¿MÃ®Â·Â¦Ã›Â¢Ã…!Â»Â±Â¬ÃŠDÂ¯Â¸ÃŠtÃ½FnÂ¥+aÂ»ulUwjgÂ´MNÃ–_Ã§Â\\tÂ­Ã¬Â„Ãº4Ã…Ã˜Â±BLÂ“LÃ\\tÃ¯1$Ã¤ZFÂ¦Â–ÃˆRÃ¯ÃªÃ `uÂœÃ¾Â·Â  YÃ—Â’M8ÃOÃŒ,Â„Â¸Ã¡Â¶GÃ‰$Ã‹Ã•)Ã¢\\tÂ†ExZÂ®ÂŒ3Â‘Â‘Ã±Â­\\nÂŠ@Ã£\\rÂ’Ã·GAN\\taÃ—Â†Â™Â”pÃ™5"ÂµÂŸÃ½Mv\%Â›Ã‘|Ã‚Ã¹"Â¯:Â†ÃÂ¶Ã®Ãº@Â‹ÃÂšÃ¸ÃµÃÃ“Â—Â€Ã¤-Ã˜0Â‚Ã“Â‡'TÂŸÂºÂ¬Â‡C^Ã®xÂÂWÃ¾Ã›*Â¡Â«ÃhÂ«dÃˆÂˆÃ½Ã¦Â²Q^@Ã§Â°7Ã„Ã€ÃŒÂ¼\\tÃGÃÃ—c<Â»Ã¸ÃPKÃ­Ã¸ÂÃ”\\bÂ¹Â)\\bÃ_Ã‹Ã©m[ÃœÂ‚Ã¢@Â‡Â Ã…Â£Ã–Ã£&\ÂŠgÃ¨&Ã›\\bÃ‚nÃ¸Â§$Ã™ÂœHÃ `ÂšÂšS ÂƒÂŒÂšiÂ‚ÃƒAboÂšÂ–NÂµÂ¿:Â¨Ã°Ã’ÂƒÂ±ÂŒÂ‘hcÂ•Ã²B~Hu@Â§VÂºÃJÂ·Ã¿ÂªÂ¥)Â¡Ã®Â¾'Â»ÃŠÂ˜ÃÂ´Ã‚Â¦Â™"Â•q:ÃƒÃ¸Ã¬Ã€Â’0G&\\fiQnÂ‚Â’yqc5ÂµÂ³}Â±ÂºIÂ˜2Â³0ÂPÃ£H<Ã„Â˜Ã—Ã£$Â¾Â’^a ''Ã‘/zÂ±V\\nÂ¦ IX|Â£6`ÂŒ[Ã‹ÂÂ–Â·Ã¬Ã¨Ã¥ÃˆÃ‘ÃœÃƒÂ‹vÃ±SÃ¥Â¢oÂ¬ÃŠÂ¿ÃšÃ“VÂ­S:Â„lÃ¶NÃ£/Â£.vCÃ¦IjÃTÂ\\nVÂƒUHÂ¿\\nÃ—Â´ÃŠÂƒÂˆÂ‚Â#?>)sk,<Â”Â¬Â¯Â±fÂ§qÃ„Â•\Â™WWÃ‹Â•Â Â“>4Â“ÂœÂ’tÂŸ-Â«Â¨Â¬Â¿/Ã§wÃ‚Â¨uÂ‰hÃˆ,Â—5oÃŸÂÂœÂ¦ÃŸpcPÃ•ÃzÃˆbÃ‚Ã˜\\n\\bbÂ‰VÃXÂŸÂ³ZÃ±ÃÂ“1|Â·Ã¯jÃ¡Â2yÂ¯Â¼\\nÃšÃ¡Ã¹Â¶d&ÃŸÃ¤UÂ”Ãn Â™\\fNÂÃ‹ÂˆYÂªxÃº'ÂKpvÃ·Ã…KÃ¡Â½Â—Ã´!Â»BÂÂÂŠfÂ¦Â¬=OE\\ryÃ¡MÃ£ÃŒ\\rÃ¦Ã)Ã¢Â°dwQÃUÃ¥ÂŠ\zedÂg|ÂÃ‡b4zÂ‘Â€Â†w}Â‰Ã«TÂšÃ°Ã‰Ã±Ã„ÃÃ´quÃªÃœ9Â€_Ã«Â‘Â¥Â¹RÃ’Â Â„ÂºÃŠÂ}FÂ’ÂÃ\\rtÂ°ÃšÃ¦Ma-Â“Ã“EYÃ©/PÂ‰Â¢Ã¨&cÂ¾Ã€KÂ”Â¾fÂµÃ¢26ÃšÂ¶Ã¿ÃœÃ¼\\t1Ãª\Ã€ÂŒ0ÃªySÃ…Â¶|uÂˆ8Jj?ÂµÃ™{\#)XÂ¨Â”Ã½Â‚aÃ”Â´Â‹BÂ§vÂÂŒtÂ„Ã°Â‘ÂšfÃˆÃÂ½Ãš?EÃ‹ÃˆÂ‡%4tÂ¡Â™ ÂŠÃ¬jÂƒ\\tuQÃ·1Ã½Ã *_'%Ã¢Â+Ã•ÂÂ­h5<Ã¾ÃŠÂ¨{Â«<ÂHL;&oÂ†;MfÃ–}\\nr 8LTÂ§ÃƒÂ–Â›Ã¤Â§ÂÃŠÃµOÂ·tÂ­KÂ»ivÃœÃ‚L,Â—[Â«Ã¶Â¡oÃ…Ã¾Ã¾;JXÂ˜Ã©ÂœS#Ã‡Ã[\\rÂˆÂ^i-ÂªÂ¢V(Ã³Ã›Â«Ã¨p)!Â€Â™Ã¬AÃ¦Ã@Ã»TÂ¤o*4Ã®wÃ\ÂÃœÂ¥Ã¬Ã†Â Â³|Â®;ozÂwÂŸÃ‚Ã¸Ã‹5r@YÂ§Â™wÃƒPkG`Ã-AÃµ$ÃgWÂµÃ ^Â®Â½ÃµÃ»Â±Ã±%SÂ«;ÃŒÂ“*kÃŠÃ‘}Â£*Â§Ã»ÃÂ¸w_EyÂ¾Ã¢RÂ'Ã’Â’93C 8ywÃ±Ã°w._Ã¨+8ÂÃ°Â“ÃŠ;\\tÃ¶_ÂÂŠLDÂŠ#P2Â‰Â¦ÃŸÃ›Ã¡Ã²Â²}Â°&Â‚Ã—Â’Ã˜vÂÃÃ–tÂ¾V(Â¦TnÃ¸Â’Ã–uÃ¥ÃQÂ¼ Ã†Â³Â‰Ã¸Â®uÃ–1OSÃ›Pu\Â»Â²Ã“XÂ¯Â Â‡<ÂÃ‘Ã”Â‰jÃ·Â Ã´Ã¶Â·ZwÂSÃ²Â”Ã½Â®Â±ÂºÂ¬Â—Â¶Â =[WÃœÃ¼Ã£3Â…Â—7 aÃª}Â¯v\pÂ¬B-Â$Ã¡NV!AÂ‹Ã VÂ³rÃ§eÃ„ÂÃ[ÃX=\\f.IZ}Â·YÃÃºÃ–Â†ÂŒÃ¼v)u|JxÃ§ÂŒdÂ™Ã›Â¶]Â²FÂµÃ¶Â¼Ã®Ã”Â´NÂ«ÂŸÂÃ‰PNÂ +fÃŸÂ©mYÃ“to4Ã5Ã¿Ã²Â–Â¯Â”Ã…\\fÃ¿\\bÃ•Â®Ã²d!3iÃ©Â‘KÃºÂ¡Â¤rÃŸÃ™ÂÂ®eÂ "KÂ Y(\\t$cÃŸÃ„Ã¿bÂ³aÂ½Ã‘Ã Ã’Ã©ÃšÂ„WÃ‚Ã¡ÂŒÂ‹Â‰sÃ˜YÃ§l\\bk2Ã³\\nEl\\fjTnÃ½Â‚"Ã˜ÂªÂ¡N<Â¢Ã‡ÃºÃ°?ÂœO@X\\fÃ¡tJÃ¥:Â¥{Â@Ã°Ã¦Ã‚Ã‡;Ã¼Â«uÂ‘40ÃšÂ²ÂŒ0FÂ‡Ã’Â™Ã”xÂœÃœv*NrÃ¥Â±'Â£ÂLÂ­xcÃ³ÃªÂ€\\fnLÂÂ²Âš\\fqtlÂCuaÃ¡Â®Â®fÃ”ÃÃ€ÃÂ \\tÃÃ›\\tiÂ¶lÃŸu\\n^Ã†Ã™Â›ÃÃ…ÃŒÃ„Â¬_}_Ã‡Ã•Ã‰Â8Â¸ÂŠG{\\rbÂiÂ”Ã«ÂŒÃ…vbZÂ£Â‡Â¢ÃšÂƒÂ½[ÂŸÃŸÃ­Â¶Ã Â¿Ã®Â¶ÂÂ®Â›ÃœÂ‰Â¡'Ã®Â¯Ã‘Â›Â•Ã†4Â©Â½CÃ»nÃ•~ÃœÃšÂ¼0Ã¢^ÃsÃºÃªIÃ†o-9G=2Â¬VÃƒÂ¿ÃÂ­*Ã˜^@Â§WÂ¨Ã„Ã„ÃŸÃ³{: Ã„Ã¦Â›\\bvÃ‡ÃÂ¼ÂƒÂ»6Â¿Ã™Â´ÂÂ»hÃÃ¯Â’Ã….Â”ÃŠ\\nÃ˜[8odÃÃÃ¡\2*Â­}\Â«Ã€n)Ã¾Â¬Â¶n(Ã‡gÃt~Ã¯Â§2Ã€ÃÃ®-*Ã“IÃ‹_Ã‹)Y*rÃŸÃ‰jÂ‚#4Â¡A6Ã‚rÃ¼+AÂŒ3ÃƒÂœ@mÃœÃ½ÃŒ*Â9a/eÂt \Â‡Ã¾Â·tÃÃŠÃ Â–Ã¢ÃŒ:Â–?=Ã¬[Ã•l@Ã‰Â¿Ã¶Ã…&ESÃ¿QÂ©2Ã™Ã¥Â?Â‘Â¼ÂÂ˜oÂ¤'$^OÂ±ÃˆHKÃ-'Â¡ÃˆÃÃ‘Ã½OÃº=RikpgUÃ‚Ã½oÃqÂÂ—I\\tE(\\bÂœ'+ÃÃ™Ã¹Ã¦Â¥YiYDÂªÃ·Â†Â³Ã·ÃhÂ‘2t-Â„Ã©Â¬aÂ˜Â±Â±/Â0P%PDL4Â³ÂbK-Â€'Ã«Q2Ã¿Ã¨Ã›ÂÃ±mÂ¿Ã…Eq!DÃ¤ÂªÂ³\\nÂ(Ã¸oOÃ¢T?Â¡ÃŠ^Ã†Ã“!Ã¬Ã²Â‡Â£ÂºXÃ­\\bMCÂ½qÃ€ÂŠ0cÃ’4%XÂ·ÃƒÃ€Â©Â­V1Ã˜(Â©Â®Ã®ÂŸÂ·Â¼Ã‚ÂªÂ–Ã°VÃ–Â\\rÃ¾ÃªwÃ¼Ã\\bÂ¦Â”AÃšÂŒÂÂ£Ã¯Ã¤-qÃ§Ã¢Â¿oÃ—ÂˆÂ Ã³Â‡Â—Ã¢Ã´ÂœsÃŸÃŒÃ€jYÃˆÂºF&Ã«ÂˆFvÂƒ=Ã¬Â¢Â…ÂªHTÂ§3@Ã²:Â¨\\r1knÂ®RAÃ¢4Ã²ZÃŒ+5Ã‰PB=Ã±\\bÃ…ÂÃ Ã®>RÂ…N|Â”Â–Â·Â¿Â¸xÂ¤\\fjÂÃ·Ã =ÃœÃ‹Â‘\\tÂ¥pÂ•ÂŸÃ†mÃ¨qe6tÃ¦93Â²;59ÂÃ•=Â›X"Ã®Ãº}j;Â‰Ã‡W.Â€F<wÂ‚Â‚Ã”v TÃŒÂ¦Ã¢HÂ’Â”ÂºÃ®@r-ÂŠYJÂ§\\bÃÃ¶#Â’Ã¸\\fi \\rHÂ˜ÃÃ¨Ã„ÃÃ“Â®TÂ½ÃÃ¸cW6Ã´Ã²Ã¤Â–ÃŠÂ•\\rR!CÂ€"Ã½ÃƒÂ LÂ½Ã‚UÃ›Â½Âš,\\t Ã¯9@^ÂŸÂÃƒÃ‹\\nÃÂ°ÃÃ­ÂµVÃœÂœÂ¡QÃ—Â€\\ffpÂ€Â¨Ã‹Ã–Â²Â™Ã§Ã¿NÃÂ²Sm\\t89@Â¼ 3YÂ«Ã®*'UÃ‘ÃŸÃ¿RRNÃ­ÂšÂ†ÃYÃ¡ÃÃ˜Ã©ZÂ¯Â¾=Ã‚ÂœÂ©Â¿'ÃºÃ»Âƒ Ã’Ã¼ÃÃ‹Â€K}mÂ¨Â¤Ã™ÃˆÂÃºÂ¾Â§ÃºÃ•Ã‘Â™FÂ¿Ã Â®,]Ã)\\rÂœÂªÂ«I _3FÃ¨i$ÃŸ$ÃbÂƒÃ ?Ã’Â• Ã—Ã®Ã…9%Ã ÃŸÃ“Ã˜`Ã†Ã”Â®PÃ—Ã¤Âš=Â¦0ÃÃ†ÂnÂ²)WL7Ã·ÂÂ|Ã¬Â¼Ã¢ÃºwÂ¹H7Â£~Â›ÂÃ·ÂšÃÃ«Â†Â«Â—Ã³Ã‹*&'BÂ·Â‘Ã4vÃ’Â¼Â«Â‡Ã²\\rÂŒMÃ¨Ã«mÂ‰Ã¸:Â§Ã¯Â¥Â©Â­Â™4Ã‚aÃœÃ…Ã¨CÂ‘t,Â}Ã5E!8Â¬Ã­-ÂÂ—Â…Â–Ã„};\\th2\\bÂ<,BÂÂ“ÂŠÃ±Ã‰CÃ»Â¥ÃªÃ©TÃ¨Â›J ÂÂƒrÃ“GÃ³[Ã•Ete|Ã¹OÃ¸Ã­Ã—ÃÃ¡5pYÃ™Ã&Ã‘Ã¾JÃ¸m`zÃºÃªÃ¼D FÃÃ’Â„\\n]Â£Ã¡Â£Â€Ã”pcÂˆÂ‹6Ã¯Â¦Ã»Ã¨ÃÂ¤ÃºÂŠ<ÂšnÃ€7jÂUÂ¡ Â¸%5Ã“Ã¦\\bÂ†ÂºÃ{?Ã½ÃšÂ¾Â‹]-dU-ZSÃ»ÃÃ¨ÃŠÂŠ\\fÂÂªÃ¾Â‡ÃœÂ†0ÃƒÃˆMÃ«zÂ¶hÃ¶Ã˜Ã³ÃœÂ—ÃŒÂµÂ½Â˜.BÂ³Â“ÃÃÂ€Ã†4Ã§Â€~Ã›Ã§Ã¢Â±cTÂ¹Â¡Â¢ @<"$QÂŠ_Â—o]Â˜Ã­TÃ²lÂ²U1ÃŠ3g0zÃªÂ‰Â¸&Ã”ÃÃ³Â¼3H|Â­Â°yC5yÃ¨cv~Â—Ã‰yÃ˜ÃµDÃ±;Ã“@Â¦ÃˆÃ¯Â›Ã \\nÂvÃšÂÃ‹Ã‘wÃ”Ã®?Ã±Âº:ÂŸÂµÂ Ã€VÃµ/Ã•Â—TeÂªÃÂŠÃ¥;Â±Â–ÃˆVÃ‘Â¸Ã‚Â±p<ÃÃƒ"ÃÂ”Ã¸Â§>RÂ¶&4Â»RÂÃŸÂ‘ÃšÂ¼Â¯Ã¢Â„<Ã¸Ã¯Ã­Â´pMÂ¾N`#$Ã»'Â‹dCÃ¤\\fÃ„ÃºCMÂ—Ã–ÂºÂ¶M8Ã¥Ã‘MRÃ¼ÂªJÃ­Â7Ã–Ã¢Ã‚Ã²VÃ26j2Â±gÂ¾Â™="Â€kÂZÂ¶Ã¦Ã¸Ã´ Â¹Â°Ã”cÂ‡Â¦^Ã¶ÂŸÃŠÃ°\\r]'$ÂÃ¤>c[0ÂƒÂ±Â®Â£JU!^Ã©ZÃ½QrÂ¹FÂºKÂ¤Ãˆw>-ÂœÂŒÃ¶ÂºÂ¡*ÃÂ¨Â¢Ã”Âˆ\\b,EÂˆ/Ã‰cÃ™H\\fÂ¥Â„Ã¦Ã¢\\b5U V"bÂ³Â•ÂšÃ¾\\rÂ§Ã®Ã•>PfÃ‡Ã”ÂˆÂ´Â¢ÂÃ¼%Ã¨Â¿Ã~\\b!Â£Â#Â© |Ã”g$Â©Â¢ÃŸW7Â¾pÂª@Âš*QÂ /ÃŠNÃ°6Ã[ÂSqÃ¤5Ã›P4FÃ£Ã˜ÂÂ™Ã Ã ]IÃÃ´Ã‘jÃƒ)ÃŸÂ–FÃ£!Ã„{Â´\\nvmaÂ›Ã®lRÂ¾Â¯Ã v@+TÃ–_Â›v,Ã«Â¼[Â‚Ã’VÃ¾zck[Â’[&&Ã´Ã¶Ã¤Ã¼YÃ’{-Ã€ANÂ¤{ÂªxÃ®Â˜Â¤IÂ£Â°5ÃµÃÂ„Â„Â„ÃˆÃ‡Ã‚Â•)Ã€Ãœ7Ã’Ã†Ã‚tKÂ¡\\nQ\\tÃÂ°,ÂºÂ”Â…Â·SÃ¬dÂ™`YReUÂ¯Â˜XÃ®ÃºSNtÃºÃ°$Ã„Ã‚0HÃ©3]Â—uÂ³V'9Â‘UÂÃ§%ÃÃ˜Â¨:QÃœÃ¬dÃ„Â³Âˆm!pV=GÃ¹PÂÃ§3ltN=\\tcÃUÂ‡UÂ”Ã Ã­Â˜ LÃ‘]mÃ‡Â½Â·Ki=Ã›Ã—KÃ€Ã‡%ÃÃ–Ã¨Ã·8Â‰Â¥Â‰Ã‡Â³ZÃŠu\\tÃ«Â´Ã™Ã²Â¢Â™Ã”Â‹Â‰Ã‡<Ã£Â©P~Â¼ÂšsÂ™V\\bAaÂ‘Ã–=l=IJÃÃŸÃ¢Ã¯Ã‚|tÂ³Ã‘ÃƒÂ¬Â„Ã¬ÂÃ©~\\tÂ Â¸Ã·&Ã¶Â‹Â JÃ…uÃ˜Ã—hÂ‹Â¬]oÂ‹Ã„HÂµÃ·\\tÂ“Â«fÃ¨Â„gEÂ°JÃ…Â·Ã­Ã±fDÂ¦ÃªÂ½Ã‡ÂJ$!Â¥KÂ¬vÃÃ¤Ã·Â½Â¬Ã†Ã¿\Ã“GÃ¨Ã„Â´ÃªÃ€}ÃšsÃ±dOÃAmÂ²Â°\\r%Â‘Â´Ã¦Ã‚Ã¸5SÂ¹Ã‚Ã±Â¬Ã·"Ã–Ã¿Ã§Ã·Ã Ã¶Ã€"}Â¥/Â¬Ã„~Â¾$ÂªÃ”Ã‘Â™ÃpÃ™Â´2>Â‹Ã·+RÃ¹!5ÂºÃŸ7wÂµxyb`3*Ã´Â¬ÂªmÂŸÃÃ·Ã!:wÃ JÃ‚-TÂ©4Ã—.Ã–lRÂ­Ã²Â²n'Â§Â£ÃÂ©Ã©/d%ÃÂª\%gÂ¸Â´aBÃ•^Ã‡I6#Â½Ã£\\rhLÂšm]Ã¯Âºdyp9MÂAÂ‚Ã‡dXÃ˜ÂœlÃ’AÃ“MÃ¤Â‹GhÂ”ÃŒDÃ‚]FÂÂ‰wÃ´Ã·Â»Ã‘JÃ‹Â».TÃ„ÂÃª&Â¬5rÃŒ`[h2Ã¿Ã¼Â¾ÃŸÂ¥ ÃÃ±0VÃ¯GÃ«ÃˆÃ½ÃÂµÂ‰=Â¦dÂ‹Â­Â¿Ã¤ Ã“o6Âº]Â²Ã·:5Ã­Ã¤Â–%Âº^Â‹Â·r$Â“:eÂ¿Â˜\\bÃ´Ã¾Â¿Ãƒh0?Ã GÃ§ÂkDÂ©0Q;ZÂ ,Â4Â¾\Ã§!ÂpRqÂŸÂ¤3dÂ„Ã¿Â¨Ã:~Â½ÃÃ+Â›Â©Ã½]Â«}Â²Â®sÃ¼Â”Ã©vÃ˜Ã®Ã¤ÃˆQÂµ6f3Ã±Ã¾Ã¢Â°9Â¬|ÂºÂ»Ã“!\\tÂÂ¬Â¯ÂªDÃ‚Â˜ÂÂ”ÃN&ÂªÃÃÂ›7Ã›Ã¿Ãœ@Ã½Ã ÃšÂ›)ÂŠ<Â\\tÃŒ<ÂƒÃ»sÃ±Ã¢Qg0uÃ®Ã¥Â»KzÂ’EÃ³Â5Â¿ÂˆNU8A`Â¹Â°1DÃÂ£Â–Â#JÃŒvÂ½IÃº-ÃÃ­Ã°Ã°"\\fÃ†Â¬ÂŠÃ…AÂ»Â¡4Ã‚>Ã¶vÃ¤Â¹Â¡ÃŸÂœÂ´G Âƒ+Â˜Â¦Ã¼ <A3sÃ€$*L^)^Ã¬ÂªÂŸ1Ã^Â Â¾wÃ£ÃŒÃ 4Â‚Ã˜q+6Â“\\fXGÂÃÃ‰Ã³Ã¦uÂ¬1Ã›pDg\\nÃªnÃ¨mÂœÃ–tÂ¸1|1Ã´qdÂ½oÃ€Ã¢Â¨Â—9ÃSxÂ‡tÃ¸Ã‚=GÂVnÂ7ÃÃˆCÂ…1Â”4Â£hYÂ Â€^Â•BÂÂ©fEÃ°Â‡=\\bÂš~\\t_Â™j,ÂŠÃµdÂˆÂ¨Â¢Â”Â¨Ã‘xÂÃ¿Ã‰Ã™Â§Ã°ÂºNÂ¸ÂµÃ†Â2Ã¡fÂ¾YHGgÃƒwÂ”Ã¹Â¡pÃÂ‘ÂŸÂ’Ã²Â’Â‚Â»\\t"Ã”Ã‡Â€Ã»\\f|Â§M!Ã†Ã‰ÃœÃ¿Ã“Ã«{\\r=Ã¸qÃ¤'6;.Â›ÃµQÂÃ²ÃŠÃ¦Â¢Â¤Â”ÂŸÃ¯Â¶MÃ–ÂˆÃºÃ“ÂÃÂ‡ÃÂ©Ã°9?Ã¿Â¿ÂƒÂ]KCxHÃ½TÂ…~mÂ¼Â‡C-LÃ™Â¶KRRÂ¯SÃ”Âº>ÂÂ¼Â”Â´qM0ÂyzÃÂÂ!:Ã€YXwÂ†iÃ¥Â£RXÃ«)Â¸ÂšÂ¤\\bÂ¡C'Ã‘Â‰Ã69Â¯Ã´HtÂ“Â«Â­Â¬`]{Â¯RZÂ—Â­Â·Ã¦ÃšyÃ°p)ÂˆÂÂÂ”Ãª|Ã’Â™_dÂ—uÃ»Ã«\\tmÃ”jTÃ‡Ã’ÂºÃ¹ÂŠÃ„ÃÂŠÂªCÂ¦.8Â‰Ã§Ã¶\KÃ‡Ã¬bÃ¥nÃ¸Ã‰CÂ·WyA}*@Â?Â­\\nÃ¸ 2}Â¥Ã´Ã®ÂªÂ¼ Â£ÂŠ]GÃ§8Ã´Â¨Ã²Ã›96Â®Ã¯GÂ—Â¾SgÂ±Â½ÂµÂ²Ã*Â«Â–ÃŠN\Ã»Ã¡Â¸Â…J#0"Ã‡eÂÂ‡cÃ£Ã­k-Â¿`Ã¨ÃÃ½Â¹Ã Â»ÂšwÂ%Ã´BÃ´Â…ÃÃ­Ã +Ã­IÂ­\\tÂ¾QHd_Â³Â‚Ã´VÂ±Â–nÂ©*WÃºÃ«iÃƒÂ”ÂšÂ°WZÃ¨JÂ‚Â¯Â´Ã¥Ã²LÃ‹UÃœtÃ˜Â‡ÃÃ«Â‚Ã—SÃ€Â£Â…AÃ’Â¹Ã‡Ã¸Â©Ã­Ã™D[ÂªXÂSLCÃ¼Â®9Â‹ÃºÃ›[oabÃ\\tZ%[eÃ’ÃªÃ¼B6Â½ Rr+Â¼Â½n!Ã JÃ·Â©<Â„Â¨#Â¾dÂ‘Ã°Ã©FÂ»Ã¸Â­Â¿w[Ã“|ÃœÂ¨0Ã¿Â„Â®'Ã‘*4^jtÂ¬|Ã™`Â»dÂ¹D/ZbÃ´\\t]HÂ¨Ã§Ã£TÃr0FÂ½Â¢ÂºÃµÂ¯7Ã¾yÃ“Ã“CÃwUÂ”ÂˆÃ°*Ã—st\\rKÃ¤TÂ”xÃ´{Â½ÂˆÂ€Ã©Ã’ÂÂš\\tq|Ã½2Â§Ã¶\\b@.ÃŸÃ”ÃƒÃ»Â„Â‘Â²Â ÂŒ(`Ã•Ã¼ÂJÃŠ\\rÃŸÃ˜Â¯\\tÂ—KÃµÂ¦Ã†Â¨Ã¤ÃŒÃÃ‰Ã´<Â¹Â„Ã»Ã”I:Ã¢JÃ—mP]iÃ¿Ã£Ã’uÂ›(Ã¦2y;Â‰ÂŒÂ¾YÃ½Â±ÂœÃ°Ã›Â†Ã³BÂ½{1BÃ°MaÃ€o( STQOÂ½Â­Â³Ã©zÃ£Â²Ã“ejiÂš_`<vÃˆ$8/_Ã–Ã˜Ã·Ã™Â¨Ã¹Ã‘QXÂ³Ã¦DÃƒÂº#7;MI1Â¾ÃŒÂ˜\\r8Â¬;ÃƒÂ¶Â“Â²yÂ¦Ã‡Â”Ã¼Â€Â–ZÂƒÃªoÂ®Â§ÃÃ¨Ã«I^Â‚EEÃ§Â¯Â“Â¾\\bvMÂ¤qÃÃ¸Â‰Ã†+sÃ®)3Ã™Â²}sÃ¢0Ã¡Ã¥Ã–DÃ¬S#Â•Ã¬ÂqÂ¸ÃŠÃ¾cÂ¿*Â¶zÂ»/Ã®Ã³]iÃ¥ÃpÃº`Ã¹@ÂÃA.deÃÂ†Ã‰ÂÂ­iÃ›\\rÂ‹EÂ’Ã¨ÃµÃŠa2]ÂƒÃ† Â¥Â¯kvÂ±3Â›DÃ†Âœ,ÃŸ6Â¼Ã¥Ãœ3wÃ‰lÃ˜?Â©Â‚RÂÃƒ,Ã«Â‹[4Ã¶8@3cÂ¾g+MfÂ˜7HlÃ„sÃ‚Â‡Ã…;Â—0ÃŒ;Â“yi;IÂ‹*Â’\\bÃœAÂ·Â…Â Â¼\Ã§Ã¿Ã°Â‹JÃ´Ã‹SÂšdÃ‰|Ã•kÂ·>Âƒ\\rÃª3wÃ‰Â¶Â¯Ãª^RÂÃÂ¯Z44ÂŒ$Â¿Ã¹ÂÂ»ÃˆÂ›Â²,VÃªÃªÂÂ=@Ã—ÂµÃŸ\2\ Â³ÃÂÃº^Ã‡Â¹=_xÂ¯_Â{Ã®Â«Ã¯Ã¹]0Ã¾ÂŸÃˆ Â‘w3Ã¦I Â„P%Â‘p4u44Ã¢SÂ¶Â¨Ã®Ã”Â…UÃ€zAÃ®Â‚Â„ÃªÂ•S1Â]-Â¹2ÂˆfaÃ°$Â°rC\\bX]\\f'IÃ¦~\\t\\rÃ€V:Ã–Ã™;Ã°ÂÃÃŸÂ”Â§-ÂŒÂ“Ã”Ã¢`b$Â„Â›ÃƒmYÃ¿{Ã„Â¨M$Ã‰vUÂ‚Ã”Ã“n$Â‡#Â¿Â¼Â¨pÃ²(Ã‰Ã´\\bÂ¯VÃ‰Â»;\\tÃ²Â¦ÃŒÂ¢UÂÃµÂ«Ã†mÂŒS=PÂ«7Ã§Â¬Â«g%Ã«$ÂÃ³Â¸Ã¡C98"!Â¿&Â¶ÃJgÂ‘@Â€ÂƒpÂ4Ã…ÃÃ¢Â’2ÃÂ»Â’Ã‚sÂ¯HÃ‰&V_[Ã¨Ã°0UÂ»ÂÂºx"zÂ»ÃˆÃ˜U\\nÃ½Ã§Â‘Ã„ÃÃ§tÂ³Â§Ã€T_Ã”\\b6ÃœÂ‹hÃ±Â¨Ã¢Â¦ÃŠ|ÃÃ½Ã¦ÃÃÂ¿Ã¹ÂˆÂªÂŒgKÃ¢Â¤#Ã‘gÂœÂ©ÂÂ¬ÂŒGÃ·-dÃ”ÃŒÃª#p\\rÃ¿ÂŸÃ¼5ÂŠ2pUFÃ¿Ã‹ÂœÂ½Ã—Ã»Ã”ÂÂÃ³Ã¥Â¤teÃ™ÃªÂ©Âˆ\\bÃ®Ã’ÃÃ²Â¶\\rÃ§Ã‘Â¡Ã¼ÂµjeÃ™XÂ§BGVÂŒÂ·bl8dÂˆÂ‹Ã±Ã«Ã’ Ã¦Ã'Ã™iÃ‚0Â†;HÃµÃ“Â‹ÂŒÃŒdÃƒÂ !Hw[p#GÃ®Â³!Ã‚Â‹d%Ãº\\bÃ‡Â£Ã§Â‡Â†\\tÂ„Ã•Â·Ã¦Ã¡8Ã¿ÃŸFÃ”j5e6ÃTEq}dÃ 21 Ã·{Â€FÂŸÂ˜Ã³Ã„Ã»jIÂ«o"gÃ‰Â¸*,'Â¥a:\\n|Â†Â²:TÂ¼Â±ÃºsÂ 9Â‰Ã¥Â<Ãƒ[{lVÂÃ¤ÃŸÂ¹zÃÃ¤Ã°fsÂ¥-Ã¼Ã™/Ã³.}Â³Ã§Ã‡3M PÂ¹ÃˆÃ¸Ãœ,Â«Ã™KÃ–]Ãº\\n\\frNDNÃ¤ÂÂ–Ã¨ÂMÃ¨ÃƒÂ§Â±ÂŠÂÂ¯ÃŒÃ²;-Â¾Âˆcm Â…@Ã‹Â‘Ã‡Ã¥Ã¯Ã5ÃœÃµMÃµ-Â°2CCÂ³RoÂ³Ã’ZÂ½:*oQÂ´Â³9?Ã©Ud!Â†Ã‹Ã‚Â‰MÂ°Ã›<RÂ•Â½ÃšÂŠÃ–Ã»)Â„Y%J6Ã°Â“CÂ„Ã‰Ã´X[&Â—Â¿ÂÂÃ†Ã©Ã‡Ã»Â‡l-Ã©MfÂ­Ã—lÂ„Â¥Ã€Â“\\bÃ<wÃˆÃŸÃ½uÂ¨Ã«uÃÃKIÂ„RwÂ‘Ã¯<Â¨Ã‚}Â­ÃÂ‡8Â¼ÂZcÂÂƒÃ„Â§ÂÃ›LNÂ™%Ã§Âµ5r=rÂ‹2ÃšÃ‰i!&Ã”(rbÃ—Ã½Ã–Â¼tÃ–Â¯&Â¥Ã¬Â•Ã…ÃœÃ€ÂµP\ZÃ›`WÂŸÃMvtÃ¢ÃŒÃ®Ã³A\\bBÂ“"Ã¼Â¬Ã»-Ã·Ã†ÂaÂÃ›Â½Â¬_Â ÃºÃºÃ²vÃŠMÂ¯Â•TÂ(fÃ‚ÂµÃ†Â¨Ã•>vÂ¼ aÃTÂ™%Â¡Â½Â²*`@83Ã¸xÃ²Ã« Â‡6Â¥\\nÃ¾ÃX6~ÃµOÃ¯Ã‘w\\tmÃƒnÃ¼Ã½TÃ‘gTÂ‰*vÃ£ÂºawPÃ®ÂwÂ Ã’Ã®ÃºÃ¨Â»BÂˆ%\\t'ÂŒwÃ‚Ã™Â©Â§Ã MBSMAÂ‰bÂ°Â½L3tFÃ“pÂ¼~Â‡Ã¼ÃŠ[Â¤:ÂŠÂ„Ã¥7ea2=ÃŒ RH'4Â—Ã˜Ã€Ã¼ÃšÂ¹Â¡NÃÃœÃÂ«qÂ„Ã¾\\\r>HÃºB%Ã¦Ã¸OÂ¬Â‚ÂÃµÃÃ²ÃŠ\\rÃºÂ·Â•Ã‚]Â“-PÂ¢e[Ã§Âº}O }ÂÃ³BÂ¯ÂˆÂ²Ã°ÂƒBÂÂ˜Ã¹tÂ‡.Ã‹Â­-ÃƒÂ—Ã«Ã¸\\rÂ‰Â 2Â‹6LÃ¹ÃÃ³ÃÂ¹:_Ã€R|wÂ‰Ã³ÃŸÂ‡|Ã}#ÃµÂ˜^3Â±..Â„CÃ«]Â¶Â¡*"Ã‰Â„SÃ‰Ã…HÂ¬Ã«ÃºÂ¹Â«$DÂ†8ÂÃb7Â¾Ã«\\tÃµÂš<yauÃƒ6qIÃ³'rÃ¶dÂ”ÂbÃ¤Ã†?Â4Â„Ã¶Â±Â³ÂÂ¦Â›{}Â¯Ã­wÃ¦Ã€ÃŸÃ‚EÂ’Ã9o>Â§Â¶Ã©\\fZmÃ™Â\\nÂ’|ÃŒÂ‘ÃÂ¨Â‰Â +Â“Â¾\\txÂˆrÃ‚@.Ã‚ /7\)Â—I-PÂ§?(Â·Â Â«ÂÂ©6wA\\txÂ¼Â¡Â§rÃ)ÂˆkÃ™Â [\\r} Ã­Â¶Â°Ã„ÂˆÂ¶ÂšÂ²Â¾Ã©b_u5ÂŒ%Ã®[%Â§Ã°Â·;Â»Â¼^@Â§Â¬Ã†Â¤Ã³` H)SÃ°\\nnÂ¹Â”mÂºÂ‚q *ÃŒÃ¦Â½Â‡Ã‹ÂÂ¬ÃÃ‹ÃªaÂ™;{'Ã–63Ã²Ã½Ã•Â±ÃÃ°}Â±ÃšpAeÃ„3ÃqÃ¨N\\bÃ·WhÃ‹%nÂ¸ÃÂ·Â€Â›Â˜Â½Ã•Ã‰6Â¹ÃµUÃ“]Â‚-xÃ¿fQÃ´Ã¨Y\\fÃµÂ§Â¦Â‡CÂ¿YÃŒ$Â­Â¦Ã‚ÃˆÂ”$Ã»!ÂˆÂº\\rÂ¢ÂCYn'Ã¤\\fÂ Â±yMÂ®CVÂ¦Â·RtÂ¥kÃŒÃe\\rÃƒ$Ã‹Ã•"\\fÂ¢\Ã•ÃŠÂŠÂ `Ã™Ã–nCÂ¼Ã¦!=tBAÂ•ÃŸÃ· #LÂœzÃ¤vÂŒ#ÂŸ%Ã…Â‹c3~Â£aÃ¾Â‰%Ã–Âª>ÂªÃ‡Ã‹ZyÃ·Ã„Ã¾%G;)^/Ã¥ÃŠÃÂŸlÂ¬Â°Ã©Â‹G%Â‰Ã²Ã¤Ã¨Ã¸ÃšÂ²^Ã–Ã³HR2Ã’aE]Â³Â«?Ãºv?ÂÃÂ¯_Â¾Â½Â±ÂÃ¡ÂªÂ›)rÂ¦Â†F{ÃzÃ¾a2ÂƒrRÂÂ‘|Âµ)JQsk#|}Ã”NF}Ã¤ZÂ”SÃªÃ“Ã›xi/8+Â¦_ÃÂÂÂ¶Y%NÂ¥MÂŸLÂŠÂ¬Ã˜Ã Â´ÃŒse\\rPjÂªÂ!Ã¢ÃŒÂ¨LÂÃ™ÂÂ®Â•ÃÃ¿ÃÂÂ™Â¤\\rÃ2Ã©%Ã‡Â³mÃ‚Â­hf\\n}Â¤Â´sÃ»Ã„Â‚!ÂŠ&Â—ÃµÂºÃ‚wÂ«RÃ´OKÂ„Ãš[Âˆ8ÂˆA( G,PÂÃš'JÃ¾}H=VÂ¡Â§Â‰zÃ™+Â¶7"Â…4\\tÃ™Ã–W\\rÂ”Q|`"Ã˜Ã½Â‚Ã±Â‰;Ã¶Â°3Â³x{$Â£Ã¿ÂºiMl7ÃµÃ„\\n;Ã‡ÃºÃZÃ­pBÂ¥Ã¦ÃŠ&k#ÂŒÂ‹Ã¶,Â«<O'Â¸ÃœÂÂ¨0Ã·Ã…zÂˆÂ„}ÂÃŠÂ«yY'ÂœBÃ§UÃœÃ–Â›^Ã™ÂºÃÂ‘TwÂ­Ã¥QÃ£Ã•Â¢Â¡Ã¹Â§lÃƒ|Ã¤Z%^Ã©Â°u"Â€`VÃ¦7Ã¼Â»'\\nVÃŸÃšÃˆaÃÃ‘Ãª$Â0RÂ¦x`hÂ‹Â“`Ã¸Â«Ã”gÂ˜Â‰.BÂ›zÂ”ÂÂ´KÃ¯FÃ»wVÃÂ¡*Ã¤Â‰NÂ„ Â­OÃ¾Â„Â»ÃŒÃ¤*Ã·QÂ¶Ã¯Â±peÂ­Âºc Â§Â†Ã–Ã—ÂµÃµ2Ã¹Ã‡'WÂ—,Â®vÃ‡ -XEÃ›CÃ#!\\fpÃ·<mÂÃ'ÂºÃ§ÃˆÂ¼^Ã´:RÂœ5Â¼*Ã‚nHÂ©43Â›ÂˆÂŠÂ–Â·Â“IÂˆsÃ­Ã†Ã°)dmÂ”Ã¬Ã¦Â·Ã¼LÃ™Â¥ÂŸmÂ\TÃ¬Â¥<Ã¥ÃÃ¯Ã¿.\\tÃŒÂ·bÃ±"Ã¸Ã›Ã‘Âƒ5ÃŠÂ´ÂšÂ¼jsXQ]Ã!]ÂµÂ’Ã®qÃ½Ãµj<Â”Ã¾ÂŸ Ã¾eÂ„^ÂŒÃºÂ‹bLR-$^3Ã°y5aÃ­Â½T/#Ã¿4ÂªÃ•NÂ§Â™Ã‰ÂŸÂ¤Ã„a"Â¾ÂŠÂŠÂ£Â–ÂºlÂƒÃ¾&|yjÃ¦ÃƒazÃ‡-eÃ¤ÃµÃ¡ÂµbÃ›$Ã¥Â“ÂaÃ·xÃÂƒÃ{ÃÃ¾kÂ«Â¢YOÂ·Â¸jÃ^`\\bÃºÃ”Â®)IÂ«ÃÂµpBm8XugyÂ‘Â­xÃ›HÃ¦Ã Â‚!ÃÃ½=xpÃ¢Â«BxcÃƒÂ¶tÃŒÃÂÃ‚ÂŸÃŠÃªÃŸÃ€ÃÂÂ˜N\\r$EÃºRmÂ­Ã]Â“+ÃµkÃ‹Ã”C:9Â­Ãœ6yÂ«ÂÂ¾|:Ã¡"Â§dÃ˜Â„Â¬6Ã¡Ã›ÂƒdÃšÃ½Â¾yXj,FaÂ—Ã“ÂŸbpÃ¡ÂoÂ„\\fV8Â”Ã½Ã™Ã„Ã»Ã¢QZÂ†ÃŸÃ°Â¦Â¦Â©fÂ«ÃœFÂ¡\\fÃ‰Ã'Ã™PÂºÂªeÃ¡Ã‹Â»Ã§fvkÂ¢ÂŠi"svÂ‰\\f{Â›@uÂ·Â‡Ã†Â›)Â£Ã©Â¦Âˆ=,Ã¬ÃÃ°Â½B$Ã»Ã¯kÂµÂ¨kY|x,O)FÃÂÃ¶HRÃ‹:Ã–Â¼Â§XÂ¨Ã¸Ã„ÃŸÃŸ.%3OQÂ€xvyÃ¼Â¼Â•Ã§$Ã½Â‡ Â°CÂšW\\n&ÂšÂ»Ã’m2Ã¸mÃ‰Ãœ?Â†\\t)Â¦ÃƒÂ•Ã‡HÂ¢ÃµÃ¼Ã³nÂ…Â˜Ã±Â•EÂ‡cÃºÃ„JÂÃªkCÃ¾Ã²Â¾Â¸Â¶Ã¹^0Â…Ã˜Â’Â‡MÂ¬Â£tPÃ‘qÂ‰HÃš9.i^Ã®Ã†]Â´5ÃÂ‹\\fÂ›Â‚WÃ¤ÂmÂ©Â¿nÂ£Ã›ÃªÂ Â¥Ã±Ã­^Â¨1cÃÂ‹Ã’SÂ”Â—AÂ¥Ã‰Ã§ÂÂ·@Ã†e//ÃŸÃŠWÂÂˆ ~Ã¬Ã²2Â‹Ã³>DÃ˜vÃ¥Ã¤7Â‘_Â±wS\\bÂ+Â¼Ã¥.ÂnÃ„Â˜tÃÂºÃ·RÃ„\\bÂ¿_Ã˜NÂ»YÃ«Ã£Â½Ã–PÂ°Â”&Â€:/zÂ…Â—Â²ÃŸMEPPÃÂ±oÂ…Â§Â¢rL mÂ½Â©#)Ã™\\fÃ¬Ã­9ÂÃš64ÃŠÃ¬RÂ½xbo<\$\\bÂ«M6Â»Â¤sXÃ/Ã¢Â™<Ã¦[Â‚XHÃÂ±ÂƒJB4Â¤VÂ ÂªÂ·@Ã¸}Ã™+Â”Ã”EÃ•NVVÂÃÂ¢Ã›AE~>#Â7,Ã¶%Ã¥Ã‰4Ã·@^{Ã¯.?Ã±ÂŠÃ‰Â©Â¿Â­ÃŠaWÂ«Ã)?Ã¿h-<ÂÂˆÃ§3Â‹zÂ½rÃÃ«,Ã£Â™20ÃµCÃ¯Ã»nV%Ã¶Â”Â³Ã©Ã·Ã—}4Ã’ Ã˜K0"~Ã¤3(\\tÂ€Â’A\\tÂ™iÃ°Ã°ÂŸ_ÃƒIÂÃ³Â¤Ã§Ã¥Â•ÃÂ³X&Ã® \mÃVÂ†8KÃ®6vÃÂÃ•Â°ÂŒ9Je&Â´8j4@Â„t?Âys/Ã’Z|Ã“Â»;}IÂ€XP-EÃº2Ã›Â°ÂšÂ Ã•@Ã›^Â®}Â±hÂ›\\bÃ³9Ã¬Â¦Ã¹Ã³ MÃ±Ã¹ÂˆBÂ¬SÃµ9Â—;t,Ã˜Ã£<Â«?Ã’Â›[Ã°Â£ÂŒÃŸÂ„Ã®9l`Â°Ã‰Ã§/Â¸*ÂÃ£Ã®\\bÃ§@Â±CÃ‘ÂÃ›ÃÃ\\fÂ±Â™NÂŠÂÃ°Ãª\\f}Â”a3>Ã˜Â¨|Ã½|ÃšÂÃŸÂ¬G&Ã­Â„ÂƒÃ€ÃÃ¾Â˜Ã›Â‹bÃ¥dIÂ“Ã’cÃ®5ÃÂµ RBy%J\\t:Â¤$Ã¨;Ã˜QÂ°OÂÂºÂ„\+iÂ³Â„Ã–z\9Ã™Â¦Â¢AÃ“ÂÃ–Â«Â¾ÂOÂ¸TÃ‰EÂªÃ¡%Ã™Ã´) ,#Ã¨Â«?Ã‰6p}?Â…Ã Â¾cÂ’ÃºÃ©Ã«Â7Ãƒ``BÃ¨Ãµ*\\b(Â´i2wÃˆvOÂ¤Ã¢Â´nCÂ­MÃ˜\\nÂ´iÂ¹at>Ã¬ÃƒQÃ› Â½dbP9ZÃ£\4Ã‹ÃºK"Â…Â”Â„Ã²3KhÃ‹Ã–Â•ÂœÃµÃœXwÂ”Â«Â…&ÃÃ‘$laÂ„Ã‰Â‡%Ã 'Ã­lsKÃ\\rÃƒlÂºÂ¹:Ã€Â¿ÂÃŸÂ‰Â’ÂŸjÃ‡ÃŠÃ“#kÂºKO~\\fÃ¾ÂºÃc8Â¯^ÂœndSÂ$7gÂ·Â—Ã°Ã¾77ÃšÃ–6Â¡GÃk$Â€Ã;Â²Ã¶jÂŒÃˆ"HÂ¸Â«Ã”Â¨TSs[Â£Â±!Â¯UÂœÃ›Â’ÂšÂ¶ÂÃŒ\\fÃŒzDpÃ»Ã§ WÃ‘ÃºÃ—QÂ»XXId1OÂˆc":Â‚Â ^Ã°4aÂÂ‹ÃŒÃšÂšÃ¹YSÃ€LWÃ–p^\ Â“Â¶Ã´Â‚Ã¿*v!\\tÂ‰$Â±Â¼Â¤Â»Â¯Ã¯Ã’Ã¢iÂ©}ÂƒÃ’xÂ€pq'2b\\rÃ‡d/4BÃºIÃœÃ¡\\tÂ—4Ã§/MÃ†DÃ¨MÃ¬Â‹NÂªÃ’fÂ¦Â¸Ã®VÂÃ›gÂ‰ÃÂŸÂ®ÃŸ Ã³:Â†Ã¦Ã‹ÃYÃŒÃ¥8Â†,Ã´ÃªÃ¹ÂµÃŒÃ“Â˜Ã¾<6,lÃƒÂ¾ÃªÃgÃ’Â¼]j1Ã›Â‹Â·Â‡ÂºÂ“fÂ«Â©*(Â†%Â \lÂÃŒYÃŸÃ“Â³ÂqÃ©Â¤Ã“SÃ|ÂÂ¾Ã¶Âœ0Ã£\{~Ã˜x%tÂµÃ\0Ã¾Â‚Ã³ÃˆÂ¬AÂŠÂ¥|ÃE\\rÃ¹ ÃŸÂ·CÃÃ£Â’3Â}Â¼Ã®Â®*O\\tuÃ˜N;Â…^d0Ã³Ã‹5ÃÂˆÃ‘VuÃ¦XÃ‚?"/Â¢Â´BÂŸÃ¬Â¹pÂ°xzÃ†{Â¾bÃ€Ã­ÃF@Â’Â­f^WvÂ“Y)Ã¼6Ã“ÃÂ±Â‡`Ã†Ã§Â²ÂªlÂ—nX;}Â–h\Ã„Ã¤FÂ¥Ã·Ã‘2ÂˆijdvÃ¯[Ã¥,'Â­@Ã¨Ã…Ã˜Ã§Ã¡Ã†ÂÃ¦Ã„1Â"Â‹Â‘Â+Ã¨Ã¨Â”'t ÃAIÃÃ¡Â®$ÃŒÂ–Â”ÃNÃ¦Âª\\nÃ‹Ã†-Ã£Â—Ã¶%Ã—hÂ¦Â¹7xÂ­ÃÃ7ÃºÂšÃ“{#_Ã¬Â #Ã¤Ã‹%rÂœRÃ†<Ã¯*sÃ¤WnJÃ«Â¯Ã:8\\bÃ‰scÂ‚Â„HJÂ”ÂÃ©Ã™Ã£ÂµÂ¶Â´8Ã¶Â¦+C~Â¨Â«Â£tÂ‘Â).2Â‰ rÃ¢fÃ‚Â„>Ã¿ÂˆÃ“Â–Â¶Â”ÂŠGÂ¶%fÂ¯KÃ‡Ã¤ÂŸÃ’Â¿_;Ã”Ã·5Ã™eÃ­UJI'7Ã„5Â·Ã³^Ã°ÃªÂNGXÃ Ã†Â;\\rÃ­DÃÃ•Ã„N)ZÃˆÂ—Ã–&Ã¦ÂƒÂ®ÃƒÂ“x)6ÂˆÂ³3Â»Â9Ã†Â”Ã½Â–Â¶wÃšGÃ i@@ÂŠÂrÂ½9Ã¦Â‰Âœ*Ã‡GÃ¨Ã©]wÂŠhÃ¶ZÂ•IÂ¬MÃŠÂÂ¸Y?GÂ¨Ã¡?GÃSÃ“ÂŠÂ¤,Â„NcTÃ“`Â Ã´Ã‰Ã…,Ã¯Â¢ÂÃ”ÂÂ¥uWÃ£Ã²Â”Â‰Â¢3\\fÂÃ>Â?Â¾ÃˆÃ·Â†Ã•Ã„Ã¤Â¦Ã¶"Ã®Â˜Â’1&Ãª~OÃ†Â«Ã€Â¼Â€{Ã‹ÂªÃ³tÂ´Â˜^Ã–guKÂ±qnZÃ»!KÂ-Ã¶Â—Ã¤Â¾Â«^92&Ã©ÃŸc, Â»\\bÃˆÂ²-Â‚Ã§ÃŒ2Â¾)Ã˜$Ã·Ã»:Â$Â‘4YÂ¤ÂÃ£7[l'%Ã’ÃšÃ Â¯ÃªÂ¶OÂ®Â¦ÃªÂ‚Â¹Â¼Ãˆs TÂ‹ÃŒÂ•ÂˆI+Ã½Â†Â 'mÃ¬ÃÂ¶ÃŠÂ½ÂÂŸÃ¶Ã—Ã±Ã¹Ã´PÂ»Ã¢Ã—9Â”Ã¶vÃÂƒÂ±RÃ—VfÃ¶Â½sÃ”iYrÂªÂšmÃ…ÂÃ©dbÃ‹}PÃ¥t"XuÂŠ|Ã­O1ZsZ\\baÃ¾Ã¨Ã°}J[Â¶].O9FÃŸÂ†EÃ°Ã¬MÃƒ[Â¸Â>Ã¦Ã¹Â¹CÂ³ÂƒÃÃˆ&Ã ÂµÂºÂ…Ã¿Ã½LÂ¤$Ãƒ\\bbQÃ½Ã¾Ã²6<Ã²Â¶Â¬Â¿Ã¦:Â†&kÂšÃ•Â˜|V6a4;Â§ÃÂªÃ¥Ã´MÃ•Â¼Ã‡$Ã—)[Â¦b#GÃ„Ã ÂÂ£1\ÃŠ}Â¸ÂƒÂŒ'sÂŸÃ”Â•Ã†\\fm~}Ã— KÂ»xJ1Â–AÃÃŸÂ“+Â‰Ãª$\8DÂŒÂ–Ã!QÃ3ÂºÃ¶ÂˆÃÂ¯\\\rÂ›ÂÂ£Â«Ã‹\\r*ÂšÂeÃ‹Â’Ã«pOÃ£EÃ©Ã’\\bÂÂ²Ã‘ ÂŸÂ¼Ã¾I@2Ã¶Â²ÃªeXÃ ÂŒNhÃºÂ›Ã¬IbÃ­ÂÃ§\\ryÂ°0+Â¾dÃÃ¶]Â”Ã’b8ÃŒÂºÂB)xÂ¡%Â´wÃ™u"Â†#Â¹\\f\Ãœ0Â³ÂƒCÂ´Â€Â±z%Â¢AÂ·_Â»Â‚ÃÃ¦~<ÂÂ¨Â¤Ã€`ÂÃ¬Ã±Ã¤&Â¾4Eo,ÃœÂ«Ã±ÂšÂ«xÃªqBxÂ¢Ã²?Â«;Â³7|UÃ±PcÃ²Ã¥S.Ã²Ã‚CÂÂ—yÃ•ÃÃ¦Âƒ\\rÂ°\\t\\fW\Â²HvÃ±&G}Â§Ã?Ã½Ã„Â”ÃŒÂ‚Â©R-ÂmÃŸ+Ã• 6F\\tFÂ²iÂ»4ÂˆeFÃšÂšÂ˜]Ã¸HÃª<Â¹#Ã¾oÃˆÃ›\\fÃŒJ\\noÃ» ~ÃÃŸÃÃ¤Ã‚Ã½9Ã™Â«NtgÃ»ZÃ¼Â\Â‘Â¶Â›EÂ²Ã®Â”+ÂÂ”EE-Ã£Ã³Ã}$Â‘Ã¦Ã»Ã™RÂ°KVoÃ¾Ã¥Ã½Â¼Ã–=Â¡BÃ¼Ã†PÃÂŒmÃ°(Ãƒ4Kr GÂ­IÂ¼Ã¼AÂƒDYÂº4uÂµÂ¾ÃW {Ã»m\\tÂUGÂ•YtÃ‰GPzÃ½Â³Â…Â‹+Â°ÃÂ„OÃ‹]3ÂŸÂª;+-\\rÃ­Â„77K<Ã§ÂºÂ•Â™iÃ¢Ã¦ÂÃÃ¥Â Ã«nÂ¿Â±Â˜Ã°Ã¾Â…N}BÂ´aÃ¸c\\fÂÃÂ—Ã§\\tI Ã±ÃÂºÂ¿Ã¤.DÃ©ZÃ™n*oÂ·ÂÃ’ÃRWÃ‹/ÃŠÂŒ>Â¹bÃ†Ãc*xÃƒY"Â»Â¸ÃŠ:Â•LÃ¸Â»Â¿@%Ã²\\bÂš1QÃ6!;$CmÃ¡o-x.0Ã\\ncÂ z~Ã™Ã•Â¨bÃºÃ‘Â«i{Â&Â 6Â¹ZÂ°Ã–gÃ²XB@VÂ§Â¶"ÃŠÃ‚Ã–mÂŠK.<ÃÂ°Ã½Â•Â‡#Ã´CÃ—Ã¯Ã˜z[LÃ¥NÃµÃ¥z'rÃEÃ¢Ã£Â˜42HÃ¨F~Â¢Ã•OlÂ“Âc:*@Ã‚Â(Â”_Ã€s)Ã£Ã—c1BÂ¡Â»TÂÂ‚Ã“vYXKÂŸÂ—Ã²ÂƒÂ†M\\nÂ]R%bÂ `DÃ£ÂÃ¼Ã¸Ã”ÃŸÃ™Ã¹=sÃƒÂ¥Ã…Â¶ÃÃ¥Ã¾)iLÂ¼Â°_Ã£Â¨3ieÃ¨Â¾Â²F$uÃ€MbÂ«XÃ›Ã‘Â•9ÃŠ1Ã”Ã¥Ã“Ã—ÂÂ¤Ã¨Â¨{Â“RÃºÂÂšxÂ‚Ã©Â¤Â¾ÂA\\bÃÂ¼Ã±mJnÂŸs8Â³Â0Â½zÃ‹Â‹nCÂ¿ÂˆÂ²Â®\\nÂ°Â¤KÃŒÃšdTÂ¡\\nÃ¾+bzÂ‡g\\bÃ™XÂ‰KÂ½!Ã»xxÃ†%6Â€Ãƒo[Âª;Â®Ã–s6Â˜ #zÃÂ™jÂ´XÂ°Â»Ã¤Â¯Â¹8Ã‹0Â¡Ã‚Â‡Â…Ã¦ÂÃ›-ÃºÂ´vÃ¬ÂµÂ˜hÂŠ3#xÂ„DÃ¯Â¤rÃFÃ¥Ã‰e~9Â‹ÃµyÃš+Â‹t3Â¿=)Ã°?lmÃ±ybTÂ©EÃ¨Ã•wÃƒÂ£DÃ¶Â¥u%ÃÂ¢Ã¹ÃŠÃ—<pÃ˜Ã½Â…uÂ´BÃ™Ã¸Â—Ã³/7Ã§<LmÃ†Ã®*5nÃ™ÂÃ­Ã¾;Â™6Â»QÃŠ/ÃÃŠÂ¬Â°fÂ½rÂ ÂºÃ¾bÃÂÃ›Ã˜Ã­Â­Ã©Ã ÂºvÂ¬Ã¿p2?Ã¾Ã„\\tÂ®Â¶ÃÂ•Ã¸ylÂ·ZÃ¨7Â‡Ã«Ã¢xÂ¤~6\Â–Ã¾{)Ã½Â§OÂ’Ã±iZÂ¸Â¶]\\nyÃ­ÂÃŸÃƒJ#ÃœÃ¹ÂaÂµ Ã°Â˜Z7mÂ±fÃ“ÂšNÂ±Âº\ÂœHÂ²ÃœÃ‰|JÃ–Â»Â—Â¾Â„Âµ\\rÃŠuÂÂ«hqÃ™Ã¶ÃŸ6Ã¯Ã£Â®Ã™Â¶Ã„ÃµÃ“gÃNÂ§Ãƒg]ÂÂ¨Ã¥PÃ¬Â¥Â°v]ÂÃ¯ÂÂ£Ã&%7Â Ã»Ã€Â…Â¢Â·DÃ™Ã‡Â¸Ã…ÃJÂ­;wUÂ…Ã³ÃšÂ„Ã¸,Â‰P+Â¢ÃŠÂµIÂ•/Â‘Ã¬Ã”Â´Â²`@FM+Â‚Â™6Ã¹Ã…Â¤ÂÃ‹Â¨Ã©wÂ”ÂÃ ÂPÂ‰HÃ Kl#+4\\tÃ‰Ã¼M7fÃ€M6Ã´]Ã†nÃ¥5ÂµSÂºÃÃ¬Â’ÂÂ‚Â¹Â… Â¹Ã½Ã†a!:ÃªÃªÃ™Ã“=Â–Ã¡ÃŸÃ½KV=7>Â™E6Ã–A\Â‡QÂ¸Ã·Ã¶Ã«>\\tÂ¸ÂœÂxNÃ¦rÂœÃÂˆÂ´VYÃµÃš9Ã˜Ã¼Ã›L%Â¬eIÂ DÃ·ÃÂ¤;Ã°ÂˆÃ¬Â‚ÃŒÂ¼Â½dÂª@Â¦Â£Ã±ÂÃ‹Â¸Ã«\\fÂ®[Â‘Ã¨QAqg~Â_Âª.ÂÂƒHks7Âƒ\\bÃªÂ®ÂˆÃÂ€Ã£ÂÂ¹Ã¬} tÂºÃ²Â©Â‰Ã­y1ÃªÂ¢x_7Â²Ã¢Â¡.Ã“QuLÂÂ«Âª`ÃˆÃ½MÂ­Â»Ã¹p_Ã‹Â«Ã’Ã¿Ã†~0Ã›Â§ÂÂ‘Â‘;ÃÂ©I/ÂÂ«Â¬Â¾ÂšÂ€hÃœ>\\bQÃ¯|xf\\nÂ†ÂÂ˜;mÃ›Â•NÂ™Â¸K:Â•AÂ”Ã¥Â›Ã¦?FÃ±KÂ¹jzL;\\nÃ¤Ã»Â—Ã«Ã¹Ã¹Â'GÂ•}Ã«p\\btfÂ‰9BÃ¦TcÂŒr) Ã¢ÃÂ†Â©ICÃXFÃ•Â“Â‰Âº+1zÃ²Â›ÃªIÂ‘oLÂ¢Â³ÂªÂ›Â˜HÃ½Â‡Â’Â§'iEÃ„ÂªSooÂˆ67Ãª|Â€Ã²Ã¦Ã•Ã¾ÂšÃÃ˜Ã¼Â®Â£PÂ•sÂŸ\\f:ZÃ…;Ã‚jeÂÂ“3iÃ!Ã«[Â‹)Â·YbR ZS"Ã‰Â‚Ã­\\bcdÃ“Â£+Ã‚Ã¶QÃ°Ãˆ)Ã¦Â¨Ã¢w ÂÂŠ]>Ã€ÃºÂ˜ÃˆÂšÂŠÃ‰ÂŠjj}RÂŠG\\nswÃ–Ã½ÂºT~Â¤Â¶Â…ÂµÃ¼"Ãœ\\fÂ±\\t;ÃˆPÃnÂ·`,Â€ÃÂ½ÃšVÂ¾Ã‡Ã“"Â¶IÂ§Â¾Â¹Â§&Â«ÂƒSÂœ\\fÃŒ3MeÃ„Ã®Ã³Ã…tuÃÂ…mÂsÂ”Ã¶E.rÃ²[Ã‡Ã“bÃ»Â¹)}Ã¢RfI5Â›wÂ‚-ECKÂ¤ÂœÂ»U>Â¼Â¤Â¥ÂÃ«GÃ•ÃšÂ˜Â˜Â¸Ã¤Â’O0ÂŸ0Â¢Ã¹ÃŸÃ dsÂ#Â‡Â¿mÃ§Ã³qvDÂ¾1Â›Â€_Â¾NÃ±aÂ­ÃœÃŸÃ¿Â•ÂnÃškÃ¥_fÃ´kÃ™Â¶Â)!PÂ«ÃLZÂ›Â¦ÃÂ—Â7zÂ·\\t(Ã ]EÃˆÂ¼Â‡ÃÃ°Ã½Â¡Ã³)&Â³ÂŒÃ…Ã¯DÂ”|ÃÃ®Â·Ã”Ã¶?Ã·DX\\bKKÃ¦dÃ¼ÂˆÂœÃ¢9ÃÂ‡ÃªÃ°TÃ‘/GÂ»ÃÃ_Ã„Â³ÃÂ·Â›vÂÂ”Ã–Ã»Â£I3tG]cÃšyÂÂ„Â¶Â¥9ZÂ¢Ã¬gÂ…ZÂ—Ã»Â¼QÃ9Ã“Â¬`Ã‰~Ã˜jj/mÂœeÃµÃ”Â¢Â¶jÂ…Â„Ã¼Â·ÂÃ¦Â…$aÂ¬NÂµÂ±n#Ã¾Â½hÃ›3Â¦,)Â›80Â„WÃ©\\f;Â©*Ã²8ÃœÂ‚\\fÃÂ˜Â¹Â‘Â¯Âµ!;H.Vt*IL,Ã€Â¾Ã¾Ã—Â¥DÂºÂ\\fÂ–Â]Ã Ã¶dÃ²yÃ±oÃ›Ã£JjÂœÂŠÃ£Â„#Âµ]ÂÂ¾Â«Ã‘Ã‘ÂŠÂ†uÃ§QÃŒÃ’ÃºÃºÂ«ÂªÃª?[r\\r_1Ã¯;Â¶\\rÃ»Ã…*Ã¨SÂÂ¬=?Â‰QSÂ›\Ã¥ÂšÃƒLbÃ°=Ã¦Ã‘ %rOSÃ§EÂnÂ»6M^gÃ˜Â¦+Gx@Ã‚Â§_ÂšPJ Â€kÂŸÂ‚ZÃ˜ÃºÂºÂ¼ÃˆÂªÂ‰ÂÃ\\t*Â„^uÃ²Â‚Â«[6vKNÂ€ÂŒÂ¦)Ã°ÃÂ­Â 2Ã VHÃ>6Ã»Ã–Â Ã—9Â®ÂÃ‰ÃoÂ‘ÃzÂ½Ã Â¤VÂ¢mÃ¤Â˜Â¹Â¥8Ã”ÃÃÃ¿Ã•1[ÂÃ\\nÂ¢Â®N'Â­|ÃŒÃ†ÃÃ¹Â‰v\\fÂ·Â Â‡Â¼Â‰cÃ§Ã˜Ã |Â¢Ã¥Â Â‚taÃºFzoÂ´Ã·Â®ÃÂ…)'ÃÃ…Ã½Â›HÃ¹ÃœÃ·ÂºÂ›#Ã‚YÂ¢[Ãš!'Ã‹ÃŒtÃ¾ÃÃ²Â…ÃÂŸÂ‘NdÂ›ÃšCÃŠÂ½Â‘Ã©w Ã¿Ã•XÃ”/Â«rÂ€@hNÂ¢]UXÃ¿ÂµÂŸLÂ"Ã Ã®Â¶ÃªÃ¢Â“Â±Ã‘RÃ™pfftÃ“Y9Ã™ÃkÂ´Â¼Ã¬ÃµÂŒÃƒiÃŠÃ•?Â—UgÂ¾Â hVÃ‘Â'Ã¿cvÂ›Â¹bÂ¡Â´k"Â±Ã’xÃ­Ã Â”ÃˆÃÃÂ£Ã¼ÂšÂ•yÃœÂ¼WK)Â²Ã†Â®Â±Ã¹cÂšQÂ¹ÂŒÃ¾fÂ·Ã‘Â—BÃ¼ÂÃ¿Âª+ÂŠ *Ã¡Ã¬Ã°Â¹`Ã¡fÂ»Â¶LÃ®1Â¹ÃƒÂÃ­~Ã·Â“)Â¤AdÂ¹UÃ–ÃeÃšÃ‹;eÂnKÃ¶ÃÂº,Ã°ÃÃ®ÂŒÃ¥Â­V5Ã‰/Ã¾Ã°zÃ²Ã´@(hÃ§wT6J\\nÂ:Â»Â£l#IzsÃÃ†VzÃ‹1tÃ˜ÃÂ¥Ã³ÂoÃ®EnYÂŠlÃ¬"7l|ÃªCÃ‹ÃšÃ–Ã›}oÂ¼ÃÃ™Ã¨WÃˆ9]wÂ Â¦5QÂ¶ÂªÂ•ÂoÃƒSÂ:EÃ´Â‰tÂˆ>p[Â¥Â´ 8O2ÃB\\nÂDÃ·[ÂIÃ‘Â qÂ¤LÂ°Â°Â½Â¼/ÃÂ]Â²Âƒ2<nÃÃ¦Ã£:e}~JÂªOÃ¤1Â˜Â¼spcÂš5NÃµÂ¾Â ;Ã–ÂJÂ‘Ãµ2\\nÃš~ÃœÃ…Ã©ÂªAA!Â©j\\rÂ’Ã´Ã¥ÃªÃ€|hÂ£j-ÂƒÃ¶Â¡GÂŠÃœÃ€ÃÃ€Â¹ÃŒÂ©xXÃ«\Âˆ$ÃŠÃnÃ‹JÂ¹\\nÂ…Â¬Â‡Â‹uXÂª7ÃšÂ¿Â£3Â·KÃ†JÂµ)Ã­\Â¿#Â¸%ÂÃ™cÂ¶6Ã¶hÃ‘9ÂÃŒPÂ“sÂ³4Ã{R50?$Â¤\\tÃ½\\tÂ¥Ã·ÂªÂ—7eÃ”ÂˆÂ‘Â¢*Ã‚ X/kÃ˜,ÂÂ¹UÃ£Ã«Â¼Ã–EÂˆÃ®EÂ¾Ã¬Â”\\nX^Ã©Ã›zÃ½Ã‡9Â­F/ÃŒÃ¯ÃµÂ®Ã—ÂÃ­Z(Ã•6ÃªÂÂ¾ÃºwkÃ“Ã…ÃµÃ Â°:TÃÂ«Â¡ÃPÂ„tovZXÂœÂ‚Ã¬Â·Ã¼Ã”Â½0qÃ­tÂšÃ¿Ã§0_;'5ÃÃ‹80Â±=ÃµÃª>UÂˆÃ³Ã±Ã±Â­cÂ…Â›ÃªÂ’Ã¶Ã¢Â+ÃÂ¤Ã·TÃ—Â€/RÃÂ¿Ã«ÃºYÂŸÂ—t_ÃŒhÃ¼Ã²Â¤nÃ¦`CDQÃ¯Â¬]VÂšÂ©\\fÂ«Â¬sl9Ã•Â‡/LÂ‡PÃ´ÃµÃ’vÂ•K3=Â´Â°Ã‚Â­Â‹ÃÂºÂ©$Â§Ãsg)Ã‘I9Ã†4+Â·ÂuÃ•\\r0ÂÂ­Â¥^ÃªbÂ„Ã¹Â»Â‰(Ã´Ã•ÂƒÃ¹Z\\bS`I0Â¥yÂ´Ã‰bjjÃ©Ã£vaÃ…\Ã®Ã¤Ã²"Ã·Ã«Ã¹0Â†zÃ·nÂƒÃ£Ã­nÃ®Ã¨{Ãš|6Â“Ã‡lÃ·Â¸\\tÂµÂ›ÃŠÂŒÂ´;ÃªÂ‡tÂÂ‡q'ZÂ¬l`gÃ¯}[ÂÂ”Â‘ÃÂµ>Ã¥w~ZIWYÂ§Ã³MÂ²Ã€#=2Â¨Â§Â‹Â‰FÂ…ÃEÂ©bÂ™Â¯Â”ÂªÃ‰Ã…Ã­QÂ°`NÃ©T=58+'U|Ã¡{Ã‰Â'MÂœÂ»Â‡Â±Â rlÂ¡Â‹FÃµLÂ»GÂ¤?ÂµÂÃª~Ã¯Â•Âš*ÃÃ‹QQÂ‹Âˆ?Ã #+RÃ+Â‘>IaoÃ„Ã³sÂ´)Â–Â¨Â¨nk#Ã­xÂ¬@Â«Ã¤NÃ•Ã©`Ã®ÂŸ9Â²0JfKÃ­^P\\t :Ã¡0wwÃ´Â’G"~ÂªÂ }ÃµÂˆÂÃ´ÂšÂ‡NÃ±lÂ“Ã´eÂ€cÂ£w7Ã–\\tÂ¨Â½| ÃgÂ¦Â‡QmJÃ•Ã„Â¯ÃÂƒÂ‚Ã”P*ÃÂ¯!X^Ã¸Ã‹Ã·Ã¡ÂšÂªÂ½Â¶Â¡saÃ¶Ã¸SÂ¨}?Ã•TÂ¥ÂÃ¢ÃÃ’Â˜ÃŸÃ¶ÂTÂ‹ÃˆlÃ»MÂ±Ã›Ã¦R\\fÃªÂ‡UÃº_gXÃ­Â UTGÂ“[&Ã‹Â„QÃsÃ¿#Ã¿iÂhhÃ±mÃ€P}Â…`Â¸Â”ÂxÂ§Â“Ã¯Ã¯ÃŠÂ»9Ã®;Ã¤jÂˆÂ’3TvÃ—\\b Â­WÂ•ÂÃ‘rÃŸÃšÃ˜ÃœÃ¼Ã ÃÃ¥Ã‚`Ã‰Ã’Â“P`wÂµqÂˆFqÃhÂ”CÃ¹Â®Â¢Â¡ ÂªÃ¯ÃÂ—Â±Â›SÃ¸ÃšÂ.Â«\\tvÂŸÂÂ¥\\nÂ‡Ã…Â·QÃ‘Ã³vp;9Â…MÂÂJÃ Ã¹Ã§ÂµÃ–Â—*Ã—Ã„Ã§Ã§ÃGÃ¹0Â¦Ã˜(Ã¦BÃ•uOhÂºÂ³O`wDÂºÂ›2Â¢Â’Âª&yÃ’Ã¡Ã»Ãª&VÂ“_Ã¡Â¬Â¹Â‡Â¿{JÃ˜Ã—ÂÂ©Ã¢Ã§"}Ã¥Ã©Â SÂ±Â¡Â«Ã³,CÂ J=Â©Â·ÂˆÂ™Ã˜bÃ´;oÂDÂ–ÂŒElÃ‚Ã†Â‘zÃÃ°-Ã—kÃ«qHwÂ²Ã«\\fzÂ˜Â¥ÃŠ'Ã°Ã‚Ã„Ã‚tÂ…ÃŸ\\rÂ°wÃ»Ã—Ã¬0{ÃƒÂ¶mwÂÂ¶Ã”Ã·Ã£Ãœg}ÃQgÃ´Â·TÂ”MYÂ¨Â°Â­iÃµÂ¤&Ã¢Ã´Ã½Â®ÂƒÂŸÃ±\\fÃ¿Ã¦siÃ„;Â’M\\tÂ§ÃŒÂ¶ÃÂ‰ÂÂµÂ¸.Ã”YdÃŸÂÂ‰YÂ­Ã†Â¸:Ã˜Â’Â¶Â±Â™Ã£4a|Â°8Ã£Â«mÂ›QÃ.Ã¾Ã•ÂµÂ«Â„ÂÂHÂ‘B/ÂŠÃœÂ”i+Âš+Ã¾Ã"\\nLÃ¹ÃˆÃ¦Ã›Â†ÂÃ´Ã—Ã·ÃÃ¦kdÃ†\\bÂÃ‹Â¼{Â‚Ã#ÃŠi?.\Ã–Âƒ?{Ã¹Â«ÃEÂ€\\r%Â¬Â†\\fÃ‚Â»Â›RÃ›"Ã¨AjÃ½\\bÃªÂšÂ.Ã­GÂÂ‘ÂºÂ¿Ã BÃ¶Â¿Â‘t|4ÃŸÃÂ—Â‹ÂÂÃŸÃ¹"ÃkÃ£Â·Â¦\\t|!lÃ‘{mÃÂ¾OÂ¶<ÂŠÂ‰Y'"1ÃƒxkBÃšÃµ]NÃ²Â¢Â‹Ã\Â•Ã´Â­/Â‡\\bÂªÃÂ™Ã¨8Ã¢@GÂ¾"AÃ¹ÂªÂ¢>Ã½XUNÂ‚Â¸>Â¨Ã«Ã¶Ã•Â¬ÃµÂš$ÃÂvÃˆÃ»Ã–Ã¿ÃÃ Ã‚Ã©Â§ÂŠÃ’{)Â‰9K~jÃƒÂ´RGVÃ¸m#{_ Â e\\bÂ‹0`Ã€ÃÂµÃ‘Â¾!'lRÂÃ¢Ã¬Ã½Â°s\\fkÃ¬Ã‰Â§Ã´Â„Ã½UÂ§Ã¯kÃ•ÂiMÃˆÃŒÃ˜Â¬ÂÂ’Â¸Z)duÂ¸Ã³?ÃšÂÃ„Â±ÂÃÃ°\\fÂ—N\\bk*Â’(Ã¿Ã¾Â¯Ã€`Â¼hSÃˆÂ±ÂŸÂÂ…Ã·jÂ¿Â‡Â§oÃ£Â½Â¦Ã¼qÃ™Ã¿9DÂ¬Â“ÂÂ6Ã²\\rÃ:2?Ã¦Â—waÂ¢Â¿Ã‚@Â½xÂŒDHÂ¡Ã£ÂÂ°EÂƒÂŠ[bÃ”#Â½\\tÂ€Â»Ã…[Ã¢Â¤Â’3Z(Ã¬Ã¨Ã¾ÂŒB:3vÃ°t3`Ã·Ã`3Â…KÃ¼VÂ®y<9Â¤Ã¿Ã¹;ÂšÂ›ÂÃ»Ã›Ã‚Ã»Â—Ã­Â‘ÂÂ­Â¥Ã¹yÃªÂ¼UJ{Ã§Â†ÃÃ¢ÃÃ¿\\n\\ncÃ°!Ã¼WÃ£Ã›Â«ÃšnÂ¡2KSÃ™3Â¤f?b-vÃœÂ¤Â»\\nÃ· Â–+Ã³6Ã›Âƒ!.2mÂ’UÃ¹>Fb|#YÃ–AÂ©Â†Ã«&4c_Â¸I\\fwÃ¤Â»Â«ÂcÃ¥Ã¾WÂÂ½Â¡RÂ²'aÂ´9Ã¦Ã‹50ÃŸwÂ¨Ã¨Â•Â­FÂ,ÂˆÂºÂÃ£Â‡ÃœÃ­{D6aÃ—Â®Ã¦Ã•D(]5Â²Ã¨Â…Â®PLÂ±Ã”Ã°Ã«Â°+c^Ã°Â‚ÃºÃLvÃ¥Â™Â7OkÂ½t;Ã‡*Â´ggÃªÃ¯oÂ·Ã‡Â°Â½Ã«zÂ±Ã‘SÃI`Ã¦oÃƒx>;f;&\;Â’ÂŒ\{ÂŒMÂ”M7Ã-Â„@Â¦Â¤TdÂ”j]Ã„Ã¦8Ã¨nÃ¥ÃŠÃ£ÃˆÃ½1ÂƒHÃœ6Â…tÂ½Ã¨Â¶Â°*ÃšÂ¸ÂÂ¾\\f|ÃŒÃÃ°Ã»Â¥Â›NÃ¢Ã¢Ã³1ÃÂ‹Â¡fÂ¬1Ã¾DÃ£fÂ·Ã°Â­LÃ¯Ã»Ã‚Â¥eÃ™Ã¤Ã´ÂŸÂ±4Ã¾Ã®Ã©ÂÂ™Ã§Â‡SÃ{Ã«@\\b\\r/Ã‘Ã³cÃ–Ã†Ã¸f-GÃ«bF\\rÂ›Â™Ã¶cÂÃ¸DÃ®\Â¯Ã B"Ã®7TÃ§Â¬WÃcdÃ²ÃšÂ5UBÃ’\\nÂÂ“Ã¼GÃŒ8ÂCÃ»Â¶Ã‰"1`Â¡FÃ™NÃµÃ™Ã‡xÂ‰ÃÂ‡Ã©Â´Ã˜Â½}ÂÃ†VÃÃ’Ã·.Ã¢Ã±@ÂšÃ–ÂÃ¼Ã¿Ã¥ÂŸÂŒÃD(ÂŒAÃ‰Ã»z%Â˜hÃ¡CÃK\\b\Âˆz"Â£{p[Â’Ã©+QQ\\fÂ†<UÃ¶Ã½ÂšÂŒÂ¶Â–Â­Ã»z"'GÂ¡Ã®gÂ¸Â­Â‰3Â‰J}LÃ°YÃnÂ™i\Ã¥8DSÃ¸Ã‰*Â“3Â¡Â»ÂœÂ—Ã­\\bÂ«}Â²{ÂŠF[ÃºÃÂ¾Â¬5KÂ˜Ã¿Ã¤Ã®=Ã½ VÂ‰PÃ‘%Â«[Â¡ÃˆÃ°ÃˆzÂ–<cÂšÃ¼*,iÂ…rÂÂÃŠ5y\\fÂ¡:r>Ã–Â¦Ã€ MÂ²[5Â®BY@ÃÃ›]Â›1Ã§Â–*Ã°pÂ–lÃKws\\tNÃ©IÃ·Â¤ÂŒÃ›Â‰[Ã¾_Â½Â»Ã¥\\t1XdO[Â²Ã‹aÂ‡Ã¾ÃƒÂÂ¬Ã•Ã…Ã›Ã€WÃ£Ã¡Â»tÃ¨Â§\\nutJMÂ“(Ã”9nÃ€Â­Ã³ÃŠÃ€Ã lÂ¦Â»AÃ¸Â‰Â«Â§@Â³F{_ÃŠÃšÃ·UÃÃ¾/~Ã—Â¦Ã·ÂªÂ8Â¹Ã“Ã†tÃ¨-iUÃ£\Â¢Â¶\\nÂ€Ã«Ã¸Z~Ã²Ã—2ÂˆÃÃ£ÃÂ„_Â’OÂ–Ã¶Ã±Â†\\bÃ¬jÃ¤Â·+ÃŒ\\\nÃ½Ã¬wBÃ©Ã®cÃ® Ã Ã›9Ã¥Â†Â‹Ã†Ã½ÃŠÃ·_r[(N,Ã´\\nÃ³)UÃ„Ã¤Ã­Â Ã†XEÃ…Ã’I\\tÃ•Ã–CÃ›Ã·Ã³Ã©Â¨ZÃ†ÃŸ8Â•Ã­Ã¹Â—RÃ«B/&iÃ¤1Â±vÂÂ¶Ã¬~~(Ã² Ã¿OÃ­Â‘Ã»Â¹Â³Ã¬Â³Â¯QÂ– ÂŸÂ”ÂŠle)Â˜Â¾Ã»Ã€Ã Ã©Ã¦|nÂ¼ÂÃ¼Â„&Â•HÂ¯Ã\xÂÃœ*ÂŸÂ²Â€K?Ã°EÃ…Ã”Â‘?\\fiÂ°Ã¸m`Ã¦;+$>ÃºÃŸLÂ°Ã–8Ã´ÂŒÂ©wÃ¼ÂŸÂŒÃ‹Â”Ã¾Â±Â¤:Â¶tÂ•Â‹ÃœÃ‡ÃÂ†Ã®mX_\\bÃ€Â’Â§Â¶Â’Ã‚mX}[ÂŸÂ¾Â¼Ã£aÂ˜Â¬T7Ã§ÃŒfÂ²Ã¢?Ã’OÂšDÃ+Ã˜Ã—Â–Â›Ã¹?Ã›M>ÂÂ»LÂš{ÃŒÃ‚Ã˜HvÃ”dÂ·Ã§Â¡Â´Ã”Y5.G{Â¿Ã€Ã¥SÂ­Ã¨ÃƒÂ¯\\nÂ“<Â‡Â¤ÂšÂ°Ã‰Ã¨Âš\FÃÃ¨Ã´*R"rÃ¤ÃÂ¡IÃ®8,@Â•*Ã©^Â£Â Â©~,Ã·Ã°qHÃ¹Â½_jÂ¬OÂ©]Â„ÂœÃ¦?GAÂ”Z~Â™Â•Ã›*Ã–\\nÃŒ57Ã“Â‰}DÃ­!$%9Ã™ÂÃ˜Bv/Ã¿,Â‘Â³BÂ›=Ã‚\\fÃ¦Ã‚wmmÃœ>Ã£Ã¶Â€Ã’*.\\tMuÂ¨lÂ€Ã­2Ã—YK\\bÃ‘%VÂ§,ÂPÃˆ-Ã ÂÃƒÂ‚Â£Â¹Â—uÂ¨Â½v)ÂºT7Â’Â­GÂ«v-Â¤[YE ÂÃ¤%9RÂ¾gu}Â§0Â¼Â«Qx{+Ã†EÂ¡Â¥'Ã­Â¯Â¹m;Â™ÂƒW0Â“Â‰'Ã¶-Â¡Ãµ)Ã‹ÃŸL(0tÃÂ`Â„Â¡ÂµÂ³"OÂ°Ã‹Ã’Ã€`aoqsk^cÃ•Ã€ÂµÃ©\Â²Ã˜]iÃ²ÂƒUÃ ÂµÃ³Ã±Ã±Ã˜_Â‚Ã¡Ã–Ã¿JÂŒÂ¹(ÂºIÂ¥Ã®QHx-Ã˜C/Â¤xÂ¾Â»d\\fK"ÂšÂˆ7Â.ÂÂ‘Ã®Â“Â²HÃªÃ¤Ã»\\r{Â¤ÂšOÃ€Â•Â¢7[ÂµÃ /$Ã§Â¼Â™Â”<joÃºÃ¹:Ã’2ÃÂ±Â›Â–a\\bÃ©YZjcÂ·ÃÂ)Ã³Ã˜yPÃ£ÃˆÂ§qv%Â“CÂ†cEbÂµ\ÂŒÂŠÂ£Ã™=Â»)9mÃªKkÃ¢yLÂˆÃ§Â˜ÂÃ­Â³qVl5(Â¯Â¬Â¹CrÃ¨Â¾Ã„Â—\\nÃÂ¢!cÃƒÃ™Â¾2ÃÂ§AÂšÃœÃ½Âº)v\\tT]\\bÂ‚Â±nBÃ¦Ã²Ã˜\Â½Ã¾@Â¯Ã„ÃÂœUÂ‹Â5)ÂÃ£ÃÃ¥Â”\\nAÃ”Ã Â‡\\nÂ™ÂŒcDÂ’$ÃÂ¹Âd%Ã‹Ã•QÂ£'Â¹-<Â‘dÂ™l/Ã‹2Ã®$CÃ—VÂˆÃ·Ã¼Â­Ã´Ã¹*ztÂ¢ xAyÃ’Ã—Ã³Ã¶Ã†0Ã Â¦y|Â©Â®QOÂ—ÂÃœ'Ã Â°uÂ•t{,ÃµÂµÃŸÂ¥Ã²Ã®Â¯K2yÂ*P~Â›oÃ¶w%^9.Ã¾Â©uÃ†Ã½ÃªQl6Ã”?ÂŒqÃ¢Â¬ÃªÃŸYx#Â«Â½Ã€OÂ„Â‘Â‡_Â´qÃ¤P`Â‰Â‘DÂ”Â \Ãƒ^HÂ»Â¦xÃ€hNÃŒÂ’Ã†WUÃ€Â„Â„s~XoÃ¥`g*Âœ\\fÂ•Â»Â™mÃ‰Â€e& Â©Ã²ÂªÂ¾ÂBVÃ­cÂ¬Ã»w8Â½[A,$DÂ‡,ÃˆÂ¿z%PÃ‘ÂœÂ“rÂ¸NÂªÃUÂ±ÂsÃ‘Â•ÂŠÃ¾{\\tÃÃ‰Ã”Z^Â“ÂœPÃ°tKd$Â¾Ã¾dÂ’\\rzpTj"Ã®ÃµÃ³WÃ±ÃºÂŠSbJ3xÃ¬Â‹Ã¹ÂŸÂ“Â¿Ã—ÂµÃ£Ã­Ã°Â¿)X4Â Ã‰3dÃ±Â™Ã€Ã¼Ã…<ÃˆKÂ‹EÃ˜ÃšM{kÂ³Ã‡|ÃŸL!vÂ¾Ã“ÂŒIÂ¡9Ã s8$-Â•ÂºÂ‘Â·Ã»AÂ“xÃ¦rÃ¡F Ã€Ã˜Ã¤~ÃÃ…4Â Â§Ã¿Ã’'Ã’`YÃ¦hÂ·ÃR%Â‡Â”Âª>Ã‰Â¬3oÃ”Â¶Â ylPÂ«Â˜Âœ'k.ÃÃ–Ã§9Â¯Â€QÃNÃ•Ã…Z(gÂ¬dÂµ4Â±Â¶GÂ¼Â¯{LkÂ™d)Ã•Ã¥Ã·Ã›Â©Â„E|Â´Ã—Ã .Ã¥Ã“ÃÂ³Â‰ gÃ‡ ekÃ¸ÃÃ¶]ÃÃ©Â¤OhÃ¿NV!Â™Ã‹Ã™~Ã¨jcÂÃ¥U"ÂˆÂŸ\\b\\rÂ˜Â¯Ã…Â®mÃ‹Â‡8Â¿AÃ¬1Â¸\\t*ÃÂ·MÂƒ8Ã´Ã¬Â—lÂ´ÃÂ¸;s>ÂœÂ—ÂÂRÂ£Â‘Ã‡(ÂÃ¬ÂŸÂ‹Ã“Ã±Â¢ÂÃ™Â¹ÂŸÂŒf7|MÂ®gÂ„ÃŸ\\fÂ·Ã–m?Ã±Â‹ÃšÃµ"Â•Ã½ÃšEÂ‡Ã”Ã³HÂ£Â·cX>Ã¬8Â¼\\b+sgÂ¾ÂŒwjÂ–ÃšÂ„ÂŸ(Â—9ÂŒÃ„9Ã¸Â¾LÂ¼Â›Â¯ Ã:Ã®Ã¤OtP\\nÃ^ÂˆÂ”Â‰A/\\n`sÃ…%e8UaÃ§Ã…ÂÃ˜Â¬"Ã¬aÂ fÃ†Ã½:Â˜Â”NÃ¥j+f>Ã¢)?^Â½'Â˜Ã¡FGÂŠ5Q9Ã£ÂŒÃ€AÂ‡Ã™Ã¡`Â˜FoU*ÃºÂ¬ÃŠjÂf\\bsQÃÃÃˆ'Â¾Ã°Â›nÃÃ‚^:Ãº=Ã¹Â¤#?;!Â ÃšG4Â€ÃªÂŒhÂµÃ¡Â‹ÂÃ¥sLÃ… Â¼w2"Â¿ xVÃ«Ã³Â†Â­/Â–|Â‚tÃ¥+Â‡Ã»z$ÃˆXTÃ°Â¶F+Ã‰FÃ°Ã²{S0ZÃ‹Â±`ÂÃŸÃ¨_>ÃÃ xÂ¤Â³Os8U2ÃºÂ‚Ãª`3Â­M#Â¹Ã“5/ÂºÃ¸Â–ÂŸÂ¥Ã«-ÃŸÃÃ¼iÃ›yÃ Â‰Â­ÃƒUÃFBÃ†eÃˆÂ€ÃŒÃÃ¿Ã¶Â•Ã·Ã‰Â…ÃœÂŸÂ·Â¡Ã¿Â¯WÃÂ¦lÂÂ ÂgÂ¦Â‹Ã³}Â¨Â²}7Â‡iÂŠ]ÂŸÃ±ÂÂ¤Â“JÂ¼RÂ\\n Ã…Â¡-oÂ”\`eÃ\\bÃ4Â¡Ã²`Â…NÃÂŠ:Ã‹Ã‚Ã‰Ã§Âª\\fvÃ¼Â¨Â—*Ã¾Â‰Â¬Ã¹Â„\\nÃ¡ÂÃšÃÃ¢Â£\\n(Ã…Â›wÃºÂ“Â¸Qb\\tÂœÃ•%Ã€Â¨K? Ã¼Â‡ÂÂ 'Ã«Â½-9ÂX1Ã¹:Â¶Ã“ Ã¹Â§ÂœhÂ¾-hKÃ˜-ÃºoÃ•O S-Ã¹Ãˆ^ÃŒ7ÃÂ N_Â†Ã…0Ã¼Â—|Ã‘Â“kÂ­Â¨Ã§W~rKÂ’Â‡2Ã­ÂºÂuÃ‡"9}Y2Â6rÂƒÃ¯vÃ®%Ã¯Ã“Â™Ã…LcIÂ•U948Ã‘Â±j-ge\\b)hÃ®#RÃ§Ã·d|Ã¥Â™Â‡!`@Ã¢\Â¨u6sÃ·Fs<RÂ¡=Ã´Ã€ÃœÃ˜w3Âº,VÂ~Ã¥Ã—Ã–f{Ã”Ã¥`Ã¡Â¥Ã±1ZÂ¹Ã¤q\\b<_Ã€ÃÂ£({Â¶ÂˆÃ®9Ã†"Ã¨Â»CQÂX$eÂ®Â“ÃÂ‘.Â LÃBx;2oÂœLfrYCÂ¶Ã§Â£dÃ»Ã–Ã‰e"Ã‹Ã–drqHÂ„WÂ +q:ÃÃ„Â¢Ã¢'sÂ”ZÂ­:1UÂ˜Ã¯RÃ’Â±Â•Â¿deÃ¥Â­yÃ«Ã¦Â®Ã›@Â´lALdÃ´Ã„OÂ‰Â®ÃÂ´A[BuÃÃ†Â£UÃšÃ lÂœÂÂ£+N^mÂ›Ã•Ã‡Ã·Â°ÂŠÂ†Ã”@QÂ·Â²|FÂ–ÃŸÃŸsÂŠmÃ„Ã‡Ã§"Ã£IÃŸÃ°Ã•ÃfÂ‡sLc`Â¯LÃ™ÂˆÂ¶ÃœÃ€Â”Ã°|gÂ°ÃšÂ¦mÃ°FÃ§Ã¬Â®Â¸Ã¸ÃoMÂ·aÃ‹LÃ€Ã¶Ã¬ÃxÂ›QÂ’&Ã”Ã¬Ã€ÃÂ¶Â€Ã£Ã¥,Ã´Â…+Ã†^Â¬B(Â¬Â¼Â‚61Â&Ã• 0RtÃ©9~BÂ‘j8iÂ·Â†Ã¸Ã”Ã™GÂ•Ã¹Â…ÃˆÃ²SÃ™Ã³KOÃ¡Ã¹ÂªÃª!*R}Ã˜Ã|Â»-=ÂÃ»Â…S{Â§ÃŸo7Â™ÂŒ.w90kI:_Â†ZÃ›Â¢uDÃªÂÂÂ²KÃ¡ÂŸÂªÂŸÂŠÃœ0 ÃšÃ³\\fÃ†Â’Ã±@ÂÃÂ‚ZÂ‚Ã·ÂrÂ¡%Â_Ã„Ã‚ÃŒÂ¬fÂ£4ÂzÃ«Â³Ã¸Ã›ÂVÃ¸Ã¥64LÂ½Ãš>Ã¤ ÃƒÂ˜ZQÃ„aÂ·Ã“Â–ÂT)Â‰\\bÂ»Â¼ÃYÃ wÃ‡Â“,(@0Qxt,Â»Ã¸ÃŒÂ­Â“Ã•;ÃÃ¹RIÂ„1ÃŸyÃ€Ã».Â¸Â§ Â‹4Ã—ÃOÃ§Â€Â{Â‡Ã‘eIÃ„Ã›ÃœÃ§Ã®`#PÂ½ÂºsÂ—ÃÃ¹Â‰{\ÂšÂ±c  Ã»GÂ·ÂŒwÂ“jWÃ’ÃŠ-'Ã–2ÂµÃÂ·OÃÂ‘Ã…5ÂƒÃ§sÃÂ¶Â“oÂ›Â°Ã¯Â•ErzAJÃ†Â´\\bÂ¢Â­qGÂ¼Â¢Ã‚Â·Â¨Ã³DyÂªQÂ’ÃŒ+QÃ–XvÃÃ¾VÃÂ’1Â‹ÂšÃªÂ«L<Â´Ã£Â’Ã“Â£ÂºfÂÃ†Â“Â¼Ã‚Ãƒ(ÃœsÃ¼ÃÂÃ¦ÂŠÃ—ÃÃ²Â‚ÃÂŸOÃOlÂ¬ÂÃ¨ÂÃ’ÂŠÂ„Ã›ÃªGÃ“mfCÂ“EÃ¤Â‹Â²2ÂŠÂ·Ã”ÂÃŠÃ†ÂœÂ¶ÃÃ©%Ã™Â™Ã‚Â Ã‡ÃªÃ Ã‰D5ÃºÃ“@Ã• v{Ã›TÃ™Â¼Ã±HÂ’Ã»Â·Â„Â´tÂ˜Ã¯+RÃ£aÂ§Ã¸ÃÃ»'/Â¶Ã˜Ã¬=g@ÂªXÃŒ|Â‡MÃšSÃ¯ÂJÃ½Ã±Â‘Â‰Ã¬N7:Â…ÃµÂ°Â¼Ã®Â³Â¦"Ã€Ã…`3 xÂ”\Ã•Ã;Ã¨_Ã—Ã€Ãš0^Ã³Â¡5VtÃ`Ã„Â©.nÃŒ@$GÂX`Ã€BmMfÃˆÃ®Â¿Â™\\tÂ°_8Ã¸%ÃªÃ\Â©yÃ³]8ÂŸ?;Ã¤u4Â°k4SÃ’,rB~Â†Ã•Ã­mÂ¢Â–Â½IÃ´Â—Ã˜Ã”Ã„Â–Â—=Ã’"ViÂ¾Ã‡\\fÃ˜Â²~Â²ÂŸÃ ÃÂª'XÂ¬:Â”+rGÂ†Ã´ÂƒÂœ`Â©Ã¿\\f&ÃœÂŸ'ÂˆÃ©[ewÂŒÂ¸Â‘Â¨Â­Â˜Â•#*/Â±Ã”fÃ»Ãk=Ã§Â¢ÃÃ—ÃÂˆÃ›,Â€lÃƒZY1wÃ«\'Ã¬|Âˆ\\bÂ°Â£XÂ…ÃÂ‡ÃZÂ˜#HUÂ‡Â«Â¶ÂÃˆXÃ“sÃ…:5=ÃÃ™UÂ»Â¶fÂ™Ã²ÃŸeÂ²ÂŒÂŒBÂ¬Â‚<0Â…'Â‡\\t2]Â„ÃœÃ›Ãªa!ÃµTHÂ°Ã™sÃ‡VÂ’Ã­cXÂ€4Ã¼Â‡XÂ¢YÃ—Â­^Â«Ã†Â›Â›ÂˆCÃŒÂ»ÃÃ«Â²Ãª>*ÂÃ 4ÂÃ¦HQlÃµÃ”ÂšÃˆsÃºÂ„F=Â²TVbR(ÃœÃ«xkÂª8ÃÃ“4ÃÂ‘Â“HÃÂ¼Ã¸Â´AMÃ¤ÃÃ¨1gdÃ±Â…HÃ¿Ã‡Â(Â˜Ã•Â³DÂ¬2ÂŸÂ³Ã‹Ã…xÃ§"]Â‘Ã¿Â’Â¿zÂ¦ÂbÂ…Ãš3>?Â§\\tF<Ã¢TÂª\\tÃ‹Ã¥O!%Ã¢Ã…\ÂÂ†$Â¦Ã§Ã„Â¡KÃ†ÃÃ™Ã´lÂ¾ÃºÂ´ÂsGMoNÂ–Â˜+\\bÂ¹ÂÃ©Â¸7Â“Ã›(Ã¤;Ã´Â—Â¦^ÂšÂ Â•Â‰Ã†eÃ®Âº7Â€Â¶]Â¨ÃQÂŠÂ¡Ã¡ÂµIÃÃ¥ÃšÂ¸Ã±Â“yÂ›Ã†ÂˆÃˆ]{Ã—Â•DÃœs4Â»gkNÂªÂÂ´Â„v_Ã¢DÂ¢ÃˆÂœ>Â£G6<}Ã­L!Âel"^nÂ¹*cÂ’8ÂCÃ—Ã¶pÂ¼Ã±}Ã³\\n_Â¸Ã„ÂÂ›Â¦?6Â€Ã¢ÂŠ,?Ã³ÂˆÃ£Â¨Ã…Y*Â©rÃ’Â²ÃƒÂ¯ÂŸ>KYÂ»Ã´sÂ®Ã§TdYÂ—\\tÃ•Â•&Â¸bÃ¡sÃ®Ã™?Â®ÃÂªÂ§mÃ¿Ã¸/96/TÂÃ˜ )Â‚Ã¡Ã¢Z:yÃ·NÃºÂ—Ã¿Ã®Â‘AÃ‘ÃÃ‹Âº2Ã—y.oÃ¼Ã‘=XÂ¥gÃ”Ã´dÃÂ¦uÂÃ€E:\\t/@Â½}aÃ—gÃƒ\\t^TÂ·Ã±\\teÃ™Â¨Ã‡TÂ¶Â½QI8Â”Â’Â‹`Ã¸YÂºZÃ‰lqÂ¦RÃ¾190Y7Ã½Â‰o3&zÂ”Â¿Ã©ÂÂªÂˆdÂ†Ã›Ã”\\nÂ“#Ã€{Ã«%vÂ¸Ã¾CÃ¼ÃƒmmÃ¾3Â”3ÃÂ½Ã´dÂ­ÂŒÂ¬Â¡L."N'Âœ0Ã•#Ã·:CÂ¤Â‚7ÃÃ©ÂƒÂ¿Ã¸Ã•Ã³ÂšÃ«ikÃ¢&Ã°Â¾~NÃ™I,gi Ã¯j[Ã„Ã©Ã‹+5Ã…Ã§Â’ÂŒ9ÃÂ¯ÃŠÂºbÃ°Â›ÃIÃ†DÂˆÃµÂºaÃ”Ã°_AÂ—< ÂšÃ½ÂÃ¬Ã°~Qg_CiÂ‰ÂŸÂƒÂ–\\fk|Ã¾ÂÃ¹uÂ¢ÂEbÃƒÂ”s^Â©Ã¥6Â=Ãª-Â[HÂ‚Â”Â›Â½$FNÂ“ÃƒlcÂ™\\bÃŸ\\rÂÃ¡Â\\bÃ€"\\fÃ²ÃµRÃŠÃœAVÃ‹Ã„6Ã9WÃƒÃ§+Â‰Â¯Â«g_CÂ³Ã¾Â®Ã€J\\riÃ¿O>Â–ÃpÂ—sÂ•ÃªhÂ±Â¦iÃ”BÂºÂˆÂ‹Â¥|Ã¿?ÃšOÃ¼HE1vÃ‘Ã¯TeÃ¸iwÃ²Âª/QÃºÃ®mÂ¿Â©H:\ÃÂœ\\brbFc4ÃÃ’ÂºuÂ„zÂ–4`hVÃ§\\b5ÃºÂ‘Ã½ÂoKLÃƒÃÃ‚V`0w9Ã¼Â° SskReÃ¤ZÃ‰\\rLÃ¸wbÃ‹N.Â´ÂÂ—Ã“ÂˆÂ›ÃšÂ•Â˜]<Ã·8Â†1Â•CÃƒÃ­jw\\tP~Â¡}ÂºÂ»8ÃjÂ‘ÃBÃ–Ã³Â‰Ã¿Ã6%ÃÂÃ´Â€Â³pÂŸÂ¡Ã¥z;h"ÂºkÃ‡Â¥hÃ‘Â±Â‰Âƒv?fÂÃµÃ†ÂœÃ˜Ã”Â¢)Ã´vÂ¥Ã–Â¦pÂ°Ã¬Ã·Ã¨Ã‹Â‘Â„>8Ã¥ÂŠÂ¬BÃ¦7GÂ†.Â\\nÂºlÂ‡Ãº\\nÂ¶pÂ—DÃ‰\Â¢Â„Â}FÃ’'Â‡ÂŸÂ€Â•Â…3Ã¹]Ã“Â­IÃˆmÃºÃ°Â»Ã«Ã+yÂ‡BÂ¤TÂƒÃÂ~V\\fÃÃ¬Ã€PÂ˜%Ã´Ã \\bÂœDÃ¿#&/Ã¬ÂˆÃ¸Â¬Ã‘UÂ¿Â¼;MÂ°HÃšÂ’Â¹Â”Â±YÃ£Â†qÃ¸ÃÃ¥Ã¯Â‡av&Ãš\\rxÂ½(Ã¸dÂµÂ•Â¡Â³Ã­Ã‹Ã†mÂƒÃ$Â³Â”Ã€ÃiÃº}o{Â®:Ã¹Â¡Ã¹Ãº;AiÃ»Â’y6ÂšÂ½Ã–Ã¶Â§#ÃµOÃ—Ã©tÃ¶L#`z<Â©ÃÃŸ7QÂ§mÂ{iÂ¿Â™rÂ³OÃ”WÂ²ÂbÂ’Â‡Ã˜ÃŠ*yÂ‘x3{Ã¦Â…Â³d`Â·EÃ¶Â“1<AÂ·!Ãˆz+Ã¯jÂ–*ÂŒÃŒÃ¹g4cÂ›GPÃ—?ÂœÃ¬sÂ¦lÂŸÃ¸jbÃºÂ†Ã¬o56Â„qÃºÂŸGKuWÂ–U^ÃÂŸÂ¦Ã¥I>Â¡$Â²ÃŒÃ˜Ã“OÂ‡BÃ“\\tÂ˜ Â¿ÃªÃ Ã‚mÂ­ÂÃ·+ÂµÃ‡@Â%|Â€pÃÂ”]4yÂ—Â¯Ã®Â¬Â°Ã¤ÃªÃ¥Â¥hEOÃ‰Â¢\\nÃ±Ã“-Ãµ:Ã±FrNÃ•Ã–Âµ8KÃƒi6Ã“{AÃ»Ã±cÃ—oÃ¼0nU-\\rÂ±-6Â´Â—iÃ®`Ã»dÂÂ¼Â±Âµ#M9Â RUÃ§QzÃ­S#Ã€S?~ ^Ã¾RÃ£$|Â¯ÂƒÂŸÂ“<qÃ¿;$Ã„Ã…Â™LÂ¬Ã‘Ã‰i@S IlÃ´Ã­Â¿Ã•KÃ¤?ÂÂ´Ã–Â¦GÂ›Â¸Â†Zg6Â˜&1Â¾:Ã¸.Ã®Â¼ÃšJÂ‘w-Â›Ã‚Ã—2d\ÂºP`ÂºÂ‰T5ÂÂ»Â†Ã€ÂªÂ·Â&Â¾:Â²#N>PÂ¬Ã·QÂš\\rzÃ‚CJ7ÂÂ¨Ã­5QÃµuLÃ‡%Ã¸%?"\\tÂ˜ Â¢MÃ°A85%ÂŠÂÃ‘Â¼Ã¡Â…ÂºÂŸÂŠÂ²%nÂ³ÂÃ»%ÃÃ¯R*Âƒ\\fFc Â—Âµ'Â¥Ã“Ã“JÂ´EÂ³\\rÂºYoÂ`Ya9.aÂ°g>ÃƒÂ¦JÃ¥E1Â¢HEhÃ›|Ã¾!Ã©Q{Ã’Â”(ÃŠ>|V/\\tÂ\\fÂ‹Â¿Â¸ÂcÂ€<ÂƒÂ°Ã¸ÃˆÂ¾NÂ•R|:Ât\\rÂŸÃ¾_Ã¥Â‡Ã’ÃÃ„RhÃ3bÃ°Ã®ÃœÂ \\tÂD2j}#Ã¿ÃN"ÂC\\nÃ<ÂgAÃ€9Ã¾Â§ÃbÂ±ÃªVÃ›Â\\nÃšÂ¼ÂÂÃ–Â…LQÂ™3Â¯Â˜7Â²fÃ›ÂƒÃ™Ã”Ã–FÂ Â–Ã¼Ã€w^ÃºRÃ zÃ„vÂ¬gÂ»Ã‚ÃÃ‚Ã¡Ã¨ooOÃ€^aÂ§Â§ÃÂ¹iÂQÂ’aÂ½kÂªWnÂ›Â…ÃƒÃˆÂµÃ¥ZÂ›~[!Â¤Â«uDÂ‡ÂÃÂÃ²FÂ½Ã¥KÂ¥9AQ7Â£\\rÃ…Ã’70Â TÃˆ*zÂ”ÃšÃµ6`Âš(Ã h\ÂÂ—ÃŸÂ¦ Â¬wÂ®Â´HIjÃ¸Ã…8Â±eÃ“ÂÂ•7Â¯Â¢\\t|bÃˆÃ¶6+xÂ‡M$6BÂ¼D11;Â§Ã–Ã¾Â€Ã·Ã¡9Â‘ÂªÃ¨9Ã‰ZÃ¿Ã¶PuÂÂšÃ¢ÃŒÃ‡wÃHÂ“iÂ¾Ã›%-Ã°5)OÃ™Ã¾Â•8Ã…Â¯;Ã‡Ã»VÃ‘Â“Â‰Ã¬Ã·3oKKÂ¼NÂ´Â·Ã¶qvÃ2aÃ‹_?iÃ¯Ã³ÃÂŠÂ¥|oÃ·[Ã»Ã¼Ã¼Ã‚Ã¢wÂ‰:Â£iÂˆNÃ®ÂŒÂ€ÃˆÂ‚\\tAÂ RÂºÃ—Ã¾9ÃÃ·Â¢Ã‰<Ã\81g=Ã¸\\bKÂ½Â›ÃƒÂ‰Z{ÃhÃ€tÃ¢ÃŸÂ¦kVÃÂ”Ã—Âˆo\\fÃ¿Â»m)s ÃµÃFÂ¾Â¡lÃ“ Ã¬#Â¤7ÂxÂ’Â«Ã…Ã¿Â‘Â¶oÂ¶Ã¥Ã¿Â€~/*Â·\\bÂa^+ÂÃÂ†ÂŠQ1\\rmÃ¸Xl\\n{EwÂ·qTÃ”Ã8Â™,3Â‡Ã‹Â•)Â»Â·]$<=ÂŒÂ¿|Â³ÂšUÃ¹ÂŠKÂ„Â½Ã¥UF}Ãµ\\bMÃ¤RÃ†WBWÃŸÂ¾ÂºÃ“|Â†Ã™\\fÃ‘Â´Â—ÂŒÃ­ÃœjBÃ·\\fÂŸÃº%Ã…Âº.Â¯ÃœkÂ•>FÃŒIÃ£R^.Â‰ÃƒÃ½Ã„Â¾Ã—Ã±c\\fÃ‘Ã¶Â“mÂ¤Â®GÂ–\\f\\fÃÃ‹Ã§Ã¶Ã…Ã¨ÃµÃ°Ãˆ9Â‹ÃªU5.Â•ÃÂ¶&6Â®&ÃªsNÃ†Ã¯Â¾.\\r<Ã¡z:>Ã‰Ã±Â˜WÃ–Ã½WÂ¤Ã‹ÂˆÃŠÃ»ÃœL!ÂÃ£ÃŸÂ˜Ã…Ã¬Ã‚ÂŠ%FCÃ¼\\tÃ’I#aXÂ n8Â¡Â†Â¸Ã®Â~|Ã­Ã¬Ã¹AÂ‚5Â¤-Â°Ã‘AÃ¨Â›kÂƒÂ®Ã¸SÃªÂ¯6Ã¡.;yÃÂ¶~QQÃŸ)Â¼Â¢zÃ™}%Ã§Â‰Ã—Ãœ5\\fÂ›Â¤'eMÂ¾ÃºÃhÃ¶Ã•ÃÃ³Ã…\\fÃ©Â—dÂ¡%!5p;Ã±Ã™Â¨SÃ¼Ã²Ã&ÂÂ¸ÂµÃ•Â«Â¨J>\\tÂ©)ÂÂ¶XÃÂ²Â½LÂÃšÂ„ÃÃºÃŸÂ“Ã§<)Ã°aÃ¶^Â¶Ã™Â°Â‹Ã¼ÃªÃ©%Â•ÂœÂ·Â’rÂ½Ã‘Â·_D<Ã·"nÃ®Ã¡Â¹Ã£Âˆ]#Ã—\\nÂ…Â”Ã¹@?&Â–Ã°Ã‹$Â‰Â¼Â¿g&+{aZgÃƒ`K`D)Ã›Ã›HÂµrÃ˜Ã“?HÃsÃ²Ã›Â½d8Â¿ZÂgCÃ€ÂÂ€Ã”Ã…]Ãˆ~FÃªÃ±{+Ã–c~ÃœsÂ¿Y\\brxÂŸÃ² Â¾Ã²CÂ¯wwÂ‰^ÃÂºQk\\nÂ°P_0ÃšÂ°Â¯Ã¯bÂÃ½,XWÃ²ÃŸ'Ã”ÂvÃƒEZÂluÃµÃšÃ¸oWGÃ¯Ã»{tÂ°?v#Tt/\\tÂ¡KpÃÃ¦Â‚4bÂ—EÂ´\\bÂ”Ã§Â§9% Â”FÂ¸Ã†Ã—uC*fv[[ÃŠÃƒÂ›ÃˆHÂ„o$ÃÃ®ÃƒbÃ«xK$ÂÃ…*ÃƒeÃ§xÃ™TÃˆbÃ¢Ã‹Ã«Ã©ÂˆÃ“Ã—ÂˆÃ¨Ã´Â£Ã¹s&{Â ÃŸ7Ã§tÃ—Â“Â¦[Ã´Ã§Â³KK$ÂŸÃ¥RÂ»ÂÂ¼Â†Ã½Ã„Â›u3Â†Â°r]Ã²\\nÂ²S3'Â®Â£%Â¥ÂÂ†Â˜Ã·AÃ¯Â²gÂšÂ‘+ÂÃ!AwÃ>Â€Â’Â¾ÂÂÃ²zÂ›Â…@Â”lÃœ\\tÃˆwÃÂ”Â«ÂKXPdÂ¯ÂˆÂ±Â™NÂˆÃšIÃ¬yÃÂšÃ…4Ã‹ÂŠ1Â¨Â«Ã³=Â—7jqr!Ã·CÃ¼Ã¿Ã¾lÃ’|Ã°)Â®Ã¹\Ã£ÂœÂ¹ÃŒC?uÃ˜\\rÃ»DTÂ‘ÂÂ§$Â¿Ã®Â±MÃ‡Ã˜Ã¡Â²\\tÂS`uÃºÃ—"Ã©mwÃ\&fmÂ°-mÂ¼Ã«Â¸BÃ¬Â¬Â„hÃ³Â’Ã—\\bÃ›ÂœmÂ¾ÃdÃ¹Ã–ÂµÃ dÂ«2Â½*ÂÃ„k4WÃ½Ã’QYdÃÂ‹Ã›Ã‰wÂ³V-Ã´Ã¯ cI^\\t-/Â‰Ã’Ã¸Â¦.zÂoKÂ¸Â›sUÂšÂ“ÃŠÃƒÂ‚zÃ£PÃƒÂ—^DÃ¾Â¦<ujÂ’eÂˆ iUÂ¦Â“]ÃÂŠÃ§[ÂBÂ–Â˜Â®ÃQM^ÂÃºÂ’Qc<RBÂ3ÂœÃÂºxÃ–7lÂœÃ„Ã¬ÂŸrÂ™Âº/^ÂªeÃ¼Ã‹Ã¬Â·Â£!\\r[Â³P=ÂµÂ„Â³Â¡Ã¥Â˜Â­zÂ€Â”Ãº\Âˆ@~Â‘#Ãu./\\rdÃ£Â³:Ã¨+,Ã«\\bÂ¿hyÃ–T\\tAÂŒPNCÃ³Â·Ã–Ã‚:\\bÂÂ­ÃœÃÂŠ7"Ã„Â¯Z*zbÃ§,Ã­ÃÃ¡!eÃ–ÃVÂšÃ’Â‘AÂ½ÂšÃªÃtxÂ‡Â•!WÂ©5ÃÂ‘I\\bVPÂ‡ÃJÃŠ@-Â’Ã‰Â”ÃšhÃ°Â´DÃÂ¶ÂÃ¥>Â—g5XÃ™ÃŸÂ™ÃAÂ…WÃ±ÃÂ•Ã Â _G%Ã¶ÃÃ”,ÂÃ·Ã¯Ã¦Ã¾v\'#Â°G9Ã¬Â¡Ã¼Ã®$$Â‘IavdÃ·Â¿}<Ã©ÃƒÂ“Â”Ã¦ÃÂ·Ã•rQÃ°G\\bÃ‡Â¾\\fÂ‡Â­0Ã­ÃÂ–Ã®Â½Â‚ÂoÃ Ã¿\\nÃ¿Q3!eÃ§Â»xGÂÃƒ|ÃˆAÂÂ­-Â\\tl<Â¢Â¿AÃÃ+Ãš8Â‚yÂ Ã’=Ã«Â¿:Ã¤Â¿\2kÂ¾uÂšÃ·RÂ¾Ã±\\fÃ®tÂ¸Â°Â¦\ÃÃ‡Ã…Â¦Â»qÃÂ¸\ #Ã¢ÂŸlÂ­Â´X@65Â·ÂºÂ¼ÂŠ6=Ã±ÃºÃ‘cÂŸÂ—Ã¶Â¬wÃ½]Â»Âª[Â‘[Â¹wCÂ§Â½Ã•pÂ•\\fÃ¥^(Â·Â¢67Â›}Â…b1Ã´Â¬Ã¹Â¦Â¾Ãƒ\\rÃ¾&ÃŠÂ¥;r5HLÂ½Â­HÃ³Â£3CÃ·Ã¾r|uÃ‘&Â©V/bÃ€9:Ãª(ÃÂ¼VÃŸ_Â°Â‚Ã8tÃÃ‹$Ãƒ*Â¹!NYÂ›Â²Â‡Ã–Ã¿Ã…ÃŠIÂ˜KÃ‘8wÂ°Ã“Â»Â’Ã³`i'<ÂŠÂ›I=kkÂ‰Ug*Ã•Ã—Â·Â˜iMÂ‡Âª@FÂ®3}<Â·Ã¡Ã¯oDBNY#ÃºÃ›Â… 9ÂŒÂ½CÃ¥9Â¤\\fÂ¼ Â´ÃÂ—I6Ã¢Ã¡}Ã«Â·_iÃ¯Â…ÂŒLÂ’ÃˆÃ?p.oÃ…Â®pÃ­ÂctqGÂ¸Ã«kVF]Ã—Â€Ã²xeÃ—y~LtÂ9Â¨Ã¡Ã¦cÂªÃ©Â—ÂˆÃ±\/Â©Ã…dQÂ¶9ÂœKÃY~U}dJÃ³Â«ÂÂ®Ã¤Â¬6Â´Ã“Â¸Ã¥a@Â¼aÂ·Â©*IÂ¬(Â›Â­uÂÂ“Â‹+Â¸Â›tÃŸÃ¯Â¾ÃµÃ‘jÃ—KJÂ€Ã‘uy[Ã£wgÃ–Â¿ÂšÃ“ÃSÃ¶GÃ¼SÂˆ9&KC#Â¾ÂŠ|5Ã¸Â±Ã°EÃÂšÃ‚ÃÂ– Â¶Â–?%(_hdÃ˜Â•ÂšJ5Âº!ÂµÂÂ•>Â‚$KÂ°ÂÂºÂÂ„\\fÃ«LÃ™ÂªÂ·dÂ \\nÂ‹ÂÂÂ‰Â­s%Ã„K*Ã¯qÃ»ÃˆPIÂ§Ã§tÃ­["ÂÂ¹C|.Â•b<Â—Â›Â‹nÃŒÂÃ›Ã¹ÂÃ°EÃ¸ÃºfÃ¿Â«lÃ¼Ã­Ã¿:Â‡KÂ¯Ã¹Â›Ã•ÂºÂ™2dÃŸÃ˜{Â² \Ã¼ÂÂrÂ–2Ã±Â²&Â–Ã brhÃ Â¡Ãœ~)HF)Ã„Ã®pdÃ¦Â½Â­cÂŒ;dyÂ’Ã£qPX#x;\\fiÂ–-ÂºÂ6fÃ‹Â…XTÂ²Â•X=XKMRÃ‡4Â±F\\r?Ã¼ÃŠÃ§ Â‰'QÂ‚9`Ã€2A'9Ã“Â†9F[~Â©Ã„+Â²Ã¤\\nÂ£ÃÃ±Â¡Â# ZÃ¾ hÃ¤Ã¬VÂ¾'ÂÂÂ£ÂŒeÂ±\\rÂ¶6\\t%!Ã©Â«Â ÃºÃ¼Ã§iÂ•Â±P'Ã–:ÃœÃ0W1Ã¬Â°Ã£=Â¬hÃ3Ã±WÂÂ‡Â¹Ã¦ÂŸRÂ§#Â˜Â¯b5Ã²DRÃ¥` EÂ¼Â¥@Â–Â®Â¢ÃªÃ…Ã®#Â›Ã¦Â¾\\nÂ‘,Â“Â§Ã¿Ã¼Â¬N\\r.kÃ€\\fK]-Â¹ÃšÂªlÂ¶ÂºB#oÃ®?ÂÃ°Â¨Ã‡gRÃ°Ã» uÃ•Âµ)Ã™Ã¸Â³OÂ‡Ã•ÂÃ•)|ÃºÂ½nÂ¹{Â¦#Ã‚Ã¼Ã¥DÂŸ7$=Â¹c/Ã€1Ã©eÂ½"UÃ\\tIÃ«~Ã‚\\rÂÂ¯ÃƒO{+Â³SÂ„Â¡\\fÂ»Ã½Â‡Y~Â‘YÃxEÂƒyjÃ†PÃ®Ã› Ã¾Â¢Â¡Â´ÂÂ¸Â½Ã¹Ã¢uZÂ­"Ã»Ã™Ã©Â²Â˜ÂªNÂ]&LÃ¸Ã‹8bÂ±Ã Â€60\\t'T1.A\\nÂ²Z\\fÃ¢Ã…Â‘Â—w\\rÃ®=Ã³Â­kÃÃµOÃ±Â…ÂŠÂ™G\Ã©Ã˜5/Z.LÂ·ÃÃ—tÂ†ÂºlÂ™Â—Ã©ÃƒÃ‰Ã»ÂˆÂ€ÃÃ«Ã‘Â²Ã¶Ã³Ã‡saÂ Ã¾Ã„ÂˆUÃ²4Ã¹Â£Ã§Q/Â§Â¼Ã«ÂTPÂ‚SÃ³(ÃˆÂ›Ã¼'Ã—ÂƒÂ…Â‡Â­"Â…Ã·%Ã¡ C7Ã§Ã•Â¡Ã‚Â­Â¬ÃµpÂ°? 2Ã‡6-Â™Â€\\n6TÂŒK!Ã• ÂÃ¿ÂÃ(Âk>nÂ¾ÂŠ\\bn5QÃ³\\rÃ°Ã½ÂjÃ™Â•VÃµÃœIÂÃƒÂ˜_Ã‘lÃ£ ÃªKÂ˜ÂœgÂ‘Ã½PÂ¥ÂµaÂ·L9Ã°iÂ“+SÃ¹ÂÃ»;ÃÃº<\\fÂº#YÂ‘ÃÂŒÃ´Ã€\\fÃ…OÃ•Ã½`kÃ¿*Ã˜Â¯Â£ÃWÂÂŒÃ‘|Â‹Aq0rÂ€Ã¹pÃ¼Â |5Â°Â…Â£oÂ§Â‰jAÃ£bÃ“Ã‚Â›tÂÂ­\\tÃ¤Y"?xÃ¦Â¸Â­Ã²Ãœ96;Ã‡Ã®pFÃÂ¶Â˜fcÃ(Ã«uÃ¹Â¨f:ÂÃ¦JÃ”Ã™Ã¡Hd>Â\Ã„Ã•{Oq(Â­Ã¬Ã­dÂÃ’BÃˆÃ‡~Â·=Â¼Ã–Â˜Â‹~XÂ¬fÃ“CvÂ¯Ã­Â¤8Sl nIG?Ã®Âš0ÃŠÂ°ÂŠqdÂœyÂ Ã°7KÂ‡Ã¡|>Â€Â‹WÂ‹:LÂ¢TÃ™DÃ±Ã»xhÂ”oÃ¬Ã›`hmP zy~ÂŸÂ©0Â—Ã¥LÂÃÃ„Ã¡~kÂ±;ÂµÃšÂ™Ã€ÃµÂ¢CÂ’aÂœÃ™ÂŸ;ÂŠAqWÃ¾zZ>OÃ¢Ãµ|Â­Ã¦Ã‘Ã³a<1Ã›QÂŸÂ•XlÃ„Ã•IÃŸÂ¦Â¤2r7Ã—Ãœ~\\rYÃ¨1Ã™:ZbÂ”Ã™Ã¢Ã«Â$Ã‰Â¥Â¿Â‘Ã€*\\nSK[\\fQÂ¤Ã8Ã«Â‡X<"hÂ’Ã€Â¯Ã¬Â†Â›Â¬ Ã¯jÂ†&Ã±Ã¾ÂªwM(Ã–Ã—Ã»h#8ÂÃ¥Â»Ã…Â™ÃÂµÂ€vs`kÃ¬UÃµÂ¶ÂÂ·Ã—Ã›Ã£R2\\nÂ†ÂYeÂ½Ã§Â˜\\rSi&9Ã¯ÂªÃ.Ã….(qÃ„!.7ÃÃ®]Â…$uÃ‘Â¬LsÂ„WÃ¼?sÃ‡Ã¹Âª1Â„e|ÂƒÂ\\tdÂ…sÃÂš $Ã–Â¸Ã’ÃªÂ¯=Ã\\nOÃ·ÃšpÂ¥ÃˆeÃ¨Â®ÃÃ‡Ã“Ã»Ã¨>Ã¥?Ã†Ã·Â©QÃ–Â¹Â“ÃUÃªB3>MÂ¿Ã‰dÃ¨ÃÃ¯/Ã¼XÂŸÃƒlÂµÃ¤#Ã¨+kÂ¨Ã‘ÂSÃ 3ÃmÂ±Ã§goÃ”Ã¼ÃˆÂ€ÃhÃ´1Ã«Ã·ÃÃÃ…Â¥{Ã›Â¼Â˜Â´Ãƒ>7EÂ„Ã½ÃªÂ®\\tÂ˜1z/U7Ã¡^Â¡Ã±PS\\bÂ‘vyÂ§Â£bÃ§Â‡YÃ‰SÃ¨+Â“ÃÂ±Ã‹qÃ¦ÃÂšÃ¬Â‰ÃŠÂ‘Â›~zÃÂ°!.Â¼Â¼Hb<Ã°Ã±Â§:Â½Ã­Â”Ã»Ã°ÃÂ¡Ãƒ7#ha&Ã©Ã•ÂfÃ†Ã¡LÂºj6BÂÂ¬Â¯Â’Â—Â•ÂˆÂšÃ·/Ã Â”=ÃµÂ«-Ã›Â±%Ã›Â»Â½ÂˆÂºÂ¹ÃŠÂÂ³Ã‹Â‰Ã€Ã”Ã©Â¶vÂˆÃ¾Â¥#Â£N+Ã‘Ãq8Â’ÃÂ¾ÂÂš\\t0!ÃÂ¤sÂÃ¸Ã—NÃ’Â@Ã¨Ã–Â«ÂÂ°2ÃˆN'Ã„ÃºÂ™VÃ¤Ã£Ã¸ÂŒÃ™Ãµ-Ã¥Ã‚%Ã‚rQÂœÂ•Ã›ÂŸ'Ã°`&Â²Ã„@NÂ›GÃ½ÂÃ¹Âµ!^Â³Âˆ>BjÂ¼Â¼Ã½w Ã½rÃ›Ã”Ã®\\fÂŠÃÃ Ã™Â¢-Ã¾Ã¡4Ã·Â¤bÂ‚Â‡C]I]_Ã¬Ã‹Â°Â¸Ã¼NÃ7>Ã“Ã¬Ã¦FÂ€HÂ¨Â³Ã»Ã™=?MAeÃlÂ¾ORÃ¯Ã¬ÃNÃudÃ‡#wÂ±s<Ã®vÃ“a<Ã­Â”rÂ¹Ã±ÂoÃ©Ã²Â£Ã»Â]LÃ¨Â‘Â¤Â­ ÃšÂ£Ã©ÂÃ¬ÃºÂ±4Ã¹Â½Â›kEsÃ¬ÂŠ$Â¨ÃÂ—Â¼Â‹Â²ÂŒH*Âfa{K>RÂ›v*Ã ?Â†25k~CHÂ£Ã•ÃªÃ™ÃÂ¤6Â¦Ã…ÂœÂ¥?ÃÃÃŒ.bÂ‹T%ÃŒtÃ´"eÂµÃ§-Ã‰Â­Ã–Ã\\rÂ‹Â†Ã¥Â£Ã”Ã¹.Â¡Ã¶Ã£Â”$Â’Ã³Â®Â—Ã¹ÂµRÃ‹Ã…\\rÂ´Â€Ã9ÂÃ—ÃœqÂ¸IMÂ£ ÂˆÃ‘Ã¦ZÃ€$6|ÂµÃ³Â†Ãº,Ã¸TÂ€c/_UÂ”Ã™ÂŒf]ÃÂ‡Â¡Ã’|Â¢Â‡IÂ™Ã¿CÃ¯Â£Ã»Ã¨%ÂŠÂ°kdÃƒ.\\n\\t"Ã„`Â¨5Ã¤Ã§$$fÃ»Ã³Ã¯Â²ÂyÂ¿dÃ¥ÂµÂ¼aÃ£6KÃ±Y4Â‘Ã¾7Â¬gtÃ£Â“?Â†iÂŸ1Ã«,lÂ·YÂ³,Ã‚Â¿k( wÃšÃ–R.TÂÂ€i\\fÂ¤Ã©\\rcÂš Ã˜Â…ÂŠÂ´tÃšÃ˜Ã¬ÂÂ¡uÂ˜Â Ã¨Â¢Ã”W\\feÃ¸Â§Ã„B$:\\rU Ã»Â¡Âƒ5YNÃ¸%Ã¹1>kx^^ÂšUÂ‡Â½ÃœGÂ¯Ã˜Â¯Â·iÂ'-ÂÃ…?LÂ¼Â³XDÂ®<\\bÂ’Â†aÃ¬ÃdÃ¿RÂÂ°Â¿ÃµÃˆÂ¼ÃŒÂ¦\\rÂÂœÂ//Ã§Â„ÂœIfÂŒÂ‰/ÃÃ±;ÂŸÂ™dÃ¯Â¬ÂŸÂ¢Â‚bnÃ†Â‹ÂÂ±Ã­ÃšÂ•Â®Â“ÃÃ˜Ã¨Â£W\\rÃ±Â‚ÂŒcOÃ¸uÂ£BÃ¬OÃ–ÃƒÃ»^Â„\\f\\t;Â–]Ã£ F2{Ã­AÂ¦Â‰BBÂ‰,Â²Ã—&ÃŒÃ²ÂŒÂ»ÃºnqÂšiÃÃ¶3Ã´ÃŠÂ…Ã™ÃµÃÃ†Â­Â˜Ã”AÃ¼Â®Â¡Ã“ÂS\\tÂ¥ {Ãœ#B.1Ã˜n;Â°4H'Â˜kJb{ÃÂ¥Â“Â‘Â•ÂºnfÃ8ÃŠ\\bIf#Ã•mÂrÃ«\\tÂ”Â2^iÂ„ÃÂ“1nÂ‹Ã€:Ã†Â£Ãº'Â¡,R RÂ†Â„\\tÂšÃŠÃ Ã¦Ã PÃ§ vÃ¤7ÂŠÂ¾@ÂŒiKÃ°R Â»Ã°\Â˜Â¬ÃÂ±Ã”5 Âœ\Â…Â¸Ã´Ã–NcÃ¾ÂœvÂ¥Ãˆ^ÂÂÂ“[aA?Ã¨ÂƒÃ¸Â–ueÃ—Ã’ÃgÃœ+qÂ­Ã¦IÂÂ‡Â•Ã—Â¾J?jÂ…Ã‹\\nÂˆÂ–sÃ¿AÃšÃ’Â®g*kÂ Ã’cÃ‘WÂ†Ã³yÂ­TtÂ“0Ã¼JÃ$TÃ­Â‹Ã‰qOÂ´y\1Ã ^uÂ¹Ã¾Ã£Â¦U^$ÃƒÂ’Â€#Ã¬&Ã°lÂ´*Â¦ÂÃº.Â–Ã–pÃ°Ã¹xÂÃ¦qÂUÂ”Ã²Â±nGlÂµÂ€ÂÂ \5Ã†ÃºÃ³ÃªÃ‘>pYÃƒ"Â–Ã›r<ÂmÂŸÂµÃ²%Ã‘Ã“ÃÃŒÃ«Ã‡rÂ¼\\ft pÃ¤Â¦pÂŒ Â¼Â»Â«Â½Âš\\bzz4ÂªÂ©yg&ÃœÂ”LÂ¨Ã…Â€Ã¼=Ã”Ã½Ã…Â³nÃ˜jF,Ã \\nf1|.Ã¥|ÃzÂ‹H1rc)ÃÂ‡Â Ãœ%*VÂ«Ã‘ÂºÂ•i"@Â‰zÂ´Ã¿)Ã›sÃ”MÃ§ÃÃ´Ã†Â’!Â«HÃ²</K5Ã¹Ã„|Ã¦DXÃ„KÃ¥ÂÂŸÂ¤ÃÃ‘Â§ÃuF,Ã„Ã–Â²Â³MÃ±Â¹nÃ¡2e"Ãº;ÃzdÂ·bVÃiZÂ±fs,Â»Ã¹AgÂšÃœd9ÂÃ« 5EÂ«T-ÃŒÃ“Ã’5tFÃŠYÂº\\bKPÂ¶ÃÂ„Â»Ã¯Ã†!6DÃ›tHÂ¬":ÃÃ²Â«Ã¿0^ Ã˜Ã«)\\nAÃ¾W*yhÃˆÂ´Â‡Â‰Â§Â‡Â¤Ã«Â¾Â½32ÂÃxÃjDÃ•lJÃ›#@_{'ÂÂ°Ã„Ã¨Â»Ã€F0EÃ²Â”xÃ¥ÃÂ§Â¿4Â®7ÂŸÂµ Â¦Â°#]`Â³Â†ÂŒx|(BÂ€,Â*Â·Ã‘Ã¤dÃ›Â·Ã€Ã„+Âµ_OÃ°Â±Ã¤1cxJÃº;Ãˆ\\t3} knÂŠÂšC U\\fp Ã»Ã¿ÃªÃ²pÂ€)eÃÂ¼Ã€ÃÂ®ÃÂ§KÃ©Â¥Ãƒ~JÂ‘yÃ³J!ÂªÂ§NÂÂºÃ¾Â¦%,Â›Ã´Ã·ÂŒ@Ã”IÂµÃ’yÃ“Ã¹Ã¨VÃÃ“Ã•?vÃ [Ã“Â­ Ã¹ywÃ¾Ã´Ã‹Â€Â‘vS(%ÃŒhCÃƒ&fÃŸ6Â¥Ã‘ÂªÃ’Â˜H#Ã Â‰O'4wÃ‘Ã™qÃ´NLÃ˜0Ã«HÂšÃŒÂ­Â‹ÃšÂ²XÂ·6ÃdÂ–Ã²Â‚Â½PÃ›)ÃºÂ¯u:Â±Â•Ã¿Ã˜}Ã°Ã³iÂšÃƒÂ©Ã—Ã‘Â¸Â°\\bÃ«zÂ¢^-Ã‡ÃAÂ£Â¿G3Â–Ã£:bÃÃ£Ã²ÃXÃ¬ÃªÂ¾Ã²HÃH:Â¢JÃˆÂœÃ³ÃšÂ²ÃÂ—Â£Â™ÂŠ&UÂ¬l$ÂÂ‡ÂšÂšÂ…Ã—Â£ÃµÂ«$Â¨cjÂ§\\nÂ©Â‰]ÃŒu@Ã¬Â³xÃ„/Â®0i%Â°Ã7YÂ‚ÃšÃ£x(Ã¯Â£@Â©ztÂ¿sM!Â Â¸RÂ@c5{TÃ®Â«Ãµ6Ã¤\\nÂº:+ÃÂ‘&Â¢Ã³Ã«?Â¥Â~bqCÂ…X~l<}lÃŒÃšÃŸÂ¶ÂÃ©/\\rÃ»ÃÂ²Â¸YJIÂ’$ÂŒÃ½Q?Ã‚Ã¶oÂ°nz_Â”Â¬Ãº xÃ´Ã¬Â„ÃƒÂ¦Ã°Ã…Â¥Ã´Â½ÃœÂšÂ•+`7\\bÂ«Ã›6ÃÂ“Ã/\\tÂ˜Ã¨O(<ÃˆB_Â‡ÂŠO\\nÃ‚]ÂiÂFÃµÂ¬)ÂƒÃ¥Ã¤NÃ¢1Â™,!Â¯Â¶DDÃ´Â°aÃ‚Â»LÂ½ÂÂÃOÂœÃ±OÂ·*Â¹Ã¬ÂÂºnÂ°ÃÂŒÂ¯ZUÃ‘)gYMÂ’Ã‚Â£afÃ Â…%Â Â¹Â«\\f#Â˜ÃŸÃ´Â³YrÃ®Â¸ÂÂ²NBÂ’<]^Ã‘Â¶ JÃ†o/Â’kÃƒ},Â«~?Â‡ÂºÃº\\b7Â‡;*Âœ%$gÂ™Ã˜Â˜MÃ£\\rÂÂŠÃ»Â³ÃÃ¡Ã’IÃ˜Ã™Â¢hÃ¶Â˜$[Ã®Â¨Ã½Ã®6v6Â”Ã¶Ã¾Â»Ã¶Â‘Â°ÃŸ=Â±Ã¢Ã…Â¤QÂº>Â¾PÃ¡VÂ±Â•Â‘T(A6Â·\\tGpÃ£y1S+Â¸<Â­Â…ÂœÂ›Ã¦Â^Ã»Â”\\ruÃ‰wÂ€$Â¹>Ã§Âº'e?BiÃµÂ¿Ã»t}KÂŠÂ‘wÂ–Ã¢Ã»SjÂ¢Â®ÂŠÃ¯[Â‹-w7_Â¼Ã«Â¦'\\rÃ‡"QÂ…Ã¬Â»Ã¬{R;{Ã§Â³_rÂ³D,Â°~QÃ´Â’.Ã­\\tjÂ±'Ã»\\ff\\rJ&Ã¶Â•Â‘:zDPÂµU,Ã¾\\f|cÂ¥Ã§Â¹ÂŒÃ€ÃŒÂ‹ÃƒÂ¬Â³kÂÂ‰Ã¤qÂ­ÃºÃ¹EaÃ­Ã›Ã©Â©ÃÃµÂ©[Â·PÂ¤/3EÃ‚=tÂŒxÂ¥6ÂŸÃ—Ã¢'{Â°e;Ã®Â¡&A9Âš]ae#Â‘T-Â«ÃœtN*(wÂ“p)Â”FÂ­Ã„Â¡!Â;Â¯Ã„Â±0Y|Ã<Â¡,Ã‚Ã¯yHgXÂœÂ½Ã¦!t\\bÂ¬'Â°R{RÃ„ÂºÂ‰ÃªPÃ¦g?Â¹Ã¿Ã¦ÃµÂŸÃ„Â¬qÂ½Ã¨Â¾Â°Â'
    //   70: dup
    //   71: astore_2
    //   72: invokevirtual length : ()I
    //   75: istore #4
    //   77: sipush #32767
    //   80: istore_1
    //   81: iconst_m1
    //   82: istore_0
    //   83: bipush #90
    //   85: iinc #0, 1
    //   88: aload_2
    //   89: iload_0
    //   90: dup
    //   91: iload_1
    //   92: iadd
    //   93: invokevirtual substring : (II)Ljava/lang/String;
    //   96: iconst_0
    //   97: goto -> 202
    //   100: aload #5
    //   102: swap
    //   103: iload_3
    //   104: iinc #3, 1
    //   107: swap
    //   108: aastore
    //   109: iload_0
    //   110: iload_1
    //   111: iadd
    //   112: dup
    //   113: istore_0
    //   114: iload #4
    //   116: if_icmpge -> 128
    //   119: aload_2
    //   120: iload_0
    //   121: invokevirtual charAt : (I)C
    //   124: istore_1
    //   125: goto -> 83
    //   128: ldc 'XÂ£Âš9\\t\\rF0Â…\\rÃ²&Â”\\t|GÂ¥Ã˜\\tYÃ³Ã›â‹¡]kÂ‘:|\\nÃ’xÃ¶YTÂš)_q9Ã³_eÂ¥YÃ¯6ÃÂ‘Â°Ã‹Â©n-WPÂ‡\\rÂ¿Ã«Ã½Ã-Â“Ã¾Ã¦Ãk-}hSd)Ã—xÂ…Ã¢ÃŒÃ„Â¶QnWc+Ã©Ã„Â½Â©'Â¬Â¼,Ã–Â²Ã…Â¥Â™Ã¬|Â‹Â†Â…ÃˆÂÂ¼Â…$I4Ã¤!ÂµÃœÃCud)ÂŒÂ”Â€Â™Ã®Ã¸ÃªÃ¥Â«ÃšÂ…Â¹\\f3Ã£Ã·ÂœÂ€:Ã :ÃŠÂ«ÂƒÃ‹ÃªNx>Ã²Âˆ;ZÃ…\~Ã§NOÃ“Âƒ9Â…ÂƒÂ¤kÂ¿%Â†?MNÃœÂ¶o~WÂ·Â—Â›Ã´Ã¨ Ã¡bÃ©Â”:Ã„4Âœ;ÂªÂ±ÃÃhCÃ¥Ã†jsÃ‡Ã„%Ã–Ã¬?W2jhxÂ‹Ã®Â¢ÂŒÃ´Ã¬Â‹vÃ£Ã„1ÂÃ™Â·\\tÂ›Ã›Ã›ÂŒsÃ³_Â™czÃ°ÂfoÃ¾ezÂ2Ã’GoÂ€wÂŒSÃªÂ¯ÃˆÃ 5tÃ¡tXTÃ­Ã¸Ã§c;]Ã·rlÃ„Â«Â¶Ã•jÂ½%C]Â€JÃ®=Â…$0ÂªÃ…ÃªÂ¼VV7Ã¬ÂzPc@Ã™Ã²Ã‘nÃÃŸw2\\nÃ­ÂªÂ°ÃˆÃÃqYÂ«/Ãƒ(ÃIÂ´D/XÃƒÂ½Ã›dt3Â”"Â¾AÃ¾ÃƒÂ’SÂNÂ¨wV`Ã…}Ã–7}g7oÂÃ¾\\nrVvÂ¦>1Ã•\\n\\n<;_ÂÃ®&p\\ta\QfÂ–S6Ã°Â–ÂœÃ”Ã‚Âœ8[Â…Ã\\fifÃ¿ÂŸÃ‘Â²Ã¤Â£3?$Ã¾Ã€ng^Ã’_Â‡^oÂœÂ‰Â˜Ã¸G*Ã·ÂÂ¢W(CwÂ€Ã™\\bÂ…*kÃÂ¹3Ã›Â£*Â¸Ã½K9ÂŠÂ¾;lÂªÂŸ.jÂÂ‚LDPÂ€DFÂ³Ã¹Â¢Ã¥Â›tDÃ£8Â@Â¥Ã«[RgÃÂµlÂ“ymKÂ˜Â€oÂ¥sQÃ¥' Â¿hÃ¾Â¦&*QÃ–o\\fÂ[ÂÃ«Ã³Â‰ÃŠxÂ¬Ã¯.L,Â½Â’LÂ¸Ã¼Ã¯YÂŒÃ¹Â‡ÃˆÂ™(Ã™Ã”eÂ‡Â˜/Â€)\\rw\\nÂ†Â°yÃƒÃÃ¢Ã Ã£NÃ¹ÃMÂˆÂ½gÃ«ÃÃ¼ÂªÂ›Â°Ã¢Ã½)kÃ«Â†r5qqÂ¥ÂªÂ”Â³@ÂƒÃ™u!Ã£Ã®Ã¥Ã¶7Â¥ÃŸ1Â¶mÃŠÂ¾Ãµ8N'UÂ›mdJ5ÂƒÂ´Â˜AÃ¶G|\\fDvÂ¡ÂŸ(=Ã½Ã†Â›ÃŒÂŒ:Â­4Ã‰Ã”Â6Ã¸Ã‘Ã¦V94Ã–Â‰/wA"0_{OmÂ‡Ã®Â¬Â„seÂÂ¿E7Ã¬ÃÂÂ¦mÃ‘ÃÂP{jÂ¶Â•KEÂƒZÃ‚Ã‹*ÂŒR'Ã<VjÂ¼Ã”Ã¯uÂÂ¨Â²Â³RÂŒ9&)7xt#JJÃ’Ã—Ã„TNÂ‡ÂƒÃ¹-Â¦8> Ã€Â²Â“Ã¼wOÃ‹Â¾QfÃšW$BÃ˜ Â†!ÃœXÂ—{(BsÂ¯Â”aÃ¶sj=\\rÂ‹$^Ã©WÃŸÂ¨*Â†Ã±+Â±Ã`Ã‡RÂšÃ»1Â™Â›$Ã·VÃ“Âœ$YQ%.)ÂƒÃ¬Âºw*Â¯Ã¢ÃšÂ¥ÃÂ–ÃÃ‹BÂ˜ÂµÂÃ„H#Â…ÃªÃ»Ã§>4oÃˆÂÃŒÃŒY?.ÃŠc&qoNÃ²Ã¡Â¼ÂµK$ÃªÂÂ£Â“Â¶N{Ã»Âµ2a9"gSÂ·Ã‘eÂ´}JÂ’)Ã”Â¢Ã´Ã©Â«Â…Â¬D!ÃŒÃŒ!Â†Â‘Ã¨Â‚BÂ‰ÃŸÂ¹Q[Ã·Ã—/Ã‰5Ã·Ã­Â¨Â‹3Â´Â»\\bÃ«sÃŸÃgÂ/*OezÂ¦KJÃ°\\f_Â¥eÃ®@Â‹Â’ÂœÂµgÃœ~chÃ¦Ã˜Ã¿+Â»Â»Ãˆ\\rÂœÂ«ÃÃ£Y\\bi\\fÃ®Â³kyÃ‘ÂÂª\\b q Ã‘Â—g@Ã“Â…Ã¶Ã°Â•I[Ã´}?:-,ÂŒÃ¦ÃµÃ‰Ã°\\nÂšVÃ…Ã³Ã»,Â¿Â´JEÃ™CÂ¥:ÃœM!5Â‰Â£ÃÃºÂ Â–Â`ADnÃ¿ÂŒÂªÃ©Â¼Ã«EÂ¤KÃÂ©Ã¼ÃŸÃ¨ÂÃÃ’\\n)ÂÃ¸Â (ÃœÂ«nÃœq+uÂ´Ã²Â­PÂºÃƒOÃÃ…qÂ–Ã)Â—Â‹_ÃÃ™Â€uYÃƒÂ¿ÂšCM/WÂ‹5Ã†Â‡ÃÃ·Ã¥6wÃ wÃª~Â¬]Â1;$FÃÂifÂ›uÂ›6ÂÃ°Ã¨Ã€Â¼Â\\rÃ¼Â‡;9Â…]Â‘Â´ÃªK\\bÂ§Â›Â­ÂœAÃ½Ã—0FÂ»}kÂ¹\\bÂˆÃ¬Â¸Ã¸$Â³Ã¨`!Ã‰Â„Ã“ÃŠÂ»ÃÃ­ÂœÃ§Ã’9mctaÂŒPCÂªÃ»Â½Ã®ÃŠ\\fÃ™jÂ‘Â»MÃ‚bÂ™Â¹Ã½Ã¯2pÂ¤ÂÃ‹Â¾1ÃŸÂ«DÃ\\t'Ã—7Ã¨ Ã—Â“{\\tXÃ›ÂŒÃ©QÃ¬Â›)Ã¥k)lÃ©,v7Ã·ÃÂ…ÂƒzsÂ„YÂ°Â„u=Ã¨\!ÃŸÃœÃ¥\\fÂ€EÂ¦ÂªÂµFÂ™MÃ™Â¾Ãl5XÂ‡Â³eÂ”Â•Ã†Ã‚Ã´Âƒ7nÃ£7Â¾Ã¹Â‘.ÃˆÂ‚{5TezxÂšÂ„Ã©LÂˆ,qÃ»Â†N2Â…:ÃœoÂ´Â¡\\b\\tVÃÂ°~ÃµÃœ~JÃ€Ã£TÃ»xÃ›zÃ•Â«iÂ“QÃƒÂ†Ã¤\\rÂ±Ã£kÃºÂ–&Ã Â¬MzFÂƒZgÂÃ“;Â¢NuÃ¼Ã“Ãƒ|Ã¶Oe^GDÃ Â„Â¶Â® ÃšÃ²Â¹Ãœt'Ã•RzÂ¥{Ã¯Â¯Ã³Ã«\oÂ‚rÂ«0Ã´CAÂ¦ÃƒÂ½[Ã„?\Â­Ã’Ã¼Ã˜ÃŠÂ¦lFDÂ¼q(-Â€Ãœg>ZÂºÂ¤TÃ€Â»vB\\bCÃ…]Ã½ÂvbÂ§Â–Ã¡R3ÂµÃ¢qÂ•ZÂ£Â—Ã£HÃ­Â£Â˜vÂ˜Ã‚Â©Ã‡ÂÂ®nÂªÃ¼Â¡Ã¼Â˜[U|Âˆ\\n5Ã´Â‘ÃŠÃ©fÃ¢pÂ¿Â¼:=ÃŸ!RÂ¢B[T/s<Â½ÂƒÂ—Â«IÂ…Ã–Ãœ\\nqÂ…Y1Ã­ÃcZÃ'Â·ÂÂ“Â†ÂzNÃ‚Â‰Ã’ÂªÃ€kÂ…Ã˜#(Â°Â™ÃuÂÃÂ²sÂ¿Ã›nÃ­-ÃÂ‚ÃœÃ c5Â¡ÃœNfÃ©Ã·, Â¸Ã€GÂ£bvÃ­ÂŠÃÃ¦Ã”QÃ¡0hÂ¢Â£ÃVWÃ¥pÂ²Â²Â²0.Ã™tÃœÂ‚Ã’ÃŠÂ‘Â³Ãµ\\bÃ©xÃ¢7Pn\\rÂ²ÃºTÂ¦NQ1Ã•Â¨)>Ã}'aÃ´8\\rW Ãµ6ÃŠÃ³Â¦Ã¸Ã›`\Ã‡BÃ¶Ã›-,Ã¾vÃ°Ã¢Ã¸ÃŠÃŒÂ‘|ÃªFÂ·IÂŒJÃºLÂ§>.Â’Ã’Â¾Ã«:ÃƒÂ‹|OÂ‡Â¸P>ZÂ¯TÂ®:qQÂªÂšÃ‡Ã¡'LÂ¹ÃÂ¯Â‹IÂœÂ²ÂˆÂ‘QGÃœFÃ›eÃ»Â”Ã¹Ã·Â•{Ã¼Ãµ~Ã‚ÂƒÃ­Â™.Ã•AdÃ®Â–Ã’pÃˆÂ—;Ãƒa1q\\fvÂ©ÃÃªÃ±6*Ã„Ãm)Ã™^Â‚ÃÂ°Ã¦ÂºÂÂ¦Â©&Ã›Â¸Ã—Â·ÂÃ°UÃ‰ÂœÃˆ#Ã‘>Ã·Ã¯QsÂ‘QÃ©?Â¥Ã NÃ‚Â¦Â§Â¥ÂšÃ¡Â¸SMÂ±Ã¸9JÃ‘pÃ¢Â°rzÂ®&Ã·Ã‘Â™4ÂšrÃ½h!ÂsVÂ­Ã©gs\\nÃŸÂ¥Â®Â™mHKuÃœÃšÃÃ±Ã…Â»Â•/ÂœÃ¸ÂÃ‚`%Ã”Ã™ Ã‚peÂ½zÂ‰.Ã¶/cT;Ã?Ã„ÃªQÃ¹Â–]#Ã€Ã—Âµ^Â.&ÂšAD\\b9Â°Ã¤Â‰Â³.ÂˆÃ£Â´ÃÂ¬Â•ÂˆÂ³#Â‘W7S<Â—Ã€%Ã°Ã‹QÂ”Ã®[Â¨/Â—^\\tÃŠ[bÃ¯0AÂ¸ÂœmÃ»6)LxÂ¦Ã³OÃ¼JtDÃ•bÃŠjÂ½Â¼ÃškÃ–Ã¯ÃÃ—Â‘Â–ÂŒÃ¸Ã#kÃ‡YAÂ¾8}RQQqgÂ™Âƒ!ÃªÂŸÂ²HÂ„+ÃˆÃœÂ—;Â²Â­Â¯VÃ™ÂµÃ”Ã¦Â•\\fÂÂ–:m\\nÂ­Â•#/xÂ•zÃ¢Ã“Â–Ã­RÃˆÂ©RuÂÂ¢Â·}YÂÂ°_Ã­Ã·ÂŒWÃ²Â°Ã‰{aÂ˜]Ã Ã¬Â»ÂÂ„\Â™G\\rS=Ã—6ngÃ›ÃÃ„ÃŸ3Â‹ÂœÃ’8PÃÃ»qÂ¸Ã¡Â³KÂ¤\\rÃ©oj4Ã­0Ã»Ã–WÃ•Ã¨AÃ¨Ã”l;Â¥'ÂšÃ—Â«%oÃ±Â !ÂƒÃ«Â¤Ã—Ã—oÃ–Ã»|fÃ²Ã®yÂ“Ã…(Â—-Ã»ÃƒkÂŸÃ¨Ã°ÂSSsuÂ¯\\n?Ã·Ã¯ÃƒÂ´Ã„iF Ã”ÃÂ¬Â¾EÂ™Ã¡Â¤FfÂ‘PÂšÂ‹Ã£Ã¯ÃÂ˜WÂ±7Ã¶Â 8WÂ¤ÂjÃBÃ˜!ÂdÃŒy0^YÂ—Â¸0ÂˆÃ¿Ã¤Ã½ÂÃ²?ÃÃ°Â·sÃ»Â¶%>Â„Ã¸2Ã„ÃÂ‹kq:Â¼Â¬MÂ’TÂ¡oÃ™ÃŒÂ©Ã¡Ã„Â›Â…}AÃ€ÃœÃ¿q?Ã•/ÃˆVcÂ¾Ã˜e,Â°:Ã®Â»Â¨0ÃŠÃ¶Ã³UzRyÃ–Â­NÂ°Â–Ã¥Â\\nÃ¾Ã¹Ã• Ã«Ã†Ã‚YÃ¦Â¦Â‰Ã´\\rmM\\rhÃ–{Ã”;AÃ³Â·KyÃ®WÂ ÂšqÃÂšFÃœÃ…_Ã©cÃƒÃ™ÂšÃ¥Ã­Â¾lÃ«\\tÂ¶ÂÃ¿ÂÃ4UÂ\\bÃ–Ã“s,\\tBÂ£Ã¡Â›ÂÃ¸Ã¢Ã¼Â«Â¨FÃ¤Â…Â‘Ã‡Ã½NÂªuxÃƒÂ—[=P`Â¥2\\bÃ¿ÃŠÃ¨-Ã‹ÃµÃƒÂ¼+a'8&][Ã¹Â½]Â„ÃƒÂ†Ã»Â°Â¸Â³nVÃ¾Â’VÃ˜Â€)Ã£Â…wÃœÃ“q[Ã‘rÃ»Â»Ã‘BÂ¦Â©Ã»45Ã¡Â¹Â¡Â³Ã«Ã¤xTAÂ…PX.Ã§Ã‡Â“Ã¿yÃÂoaUÂÃ´Â‘Â¬Â«Â—pÂÂ™O8Ã´Â«Â®8Ã£MÃ¬Â˜ÃºÂœÂ’Ã¯ÂœfÂ§Â»ÂÃ·Â©Ã‹Ã—ÃÂ”xÂœ(,Â†Â¤9iÃ¿C}Â…QQqÃÂ›wÂ®Â‹Ã•ÃpSÃ„Ã´ÂŸÂ›^M?1Ã¡ÂnÃ¼ÂŸXÃ¿Â¨AÂºÃ®yÂ®Ã˜e8Ã°8Ã³WÃ§Ãº]Ã¶V>HÃ©ÂˆÃ—RdaÃ¾=Ã¢%Â¨XÂ¹Â”-Ã´UC,Â˜WÂ¦yvÂ±ÂœÃµÂ½OÃ¸4Â”G|ÂœuÂ­ÂšfÃ¬]<ÃŸgAÂ‡ÃšÂ’uÂ·KÃ¡ÂŸÃ¯Â´Â‚Ã¶ÂœÂ½xÃ†Â¸XÃŸÂ¼wÃš,Â@Ã¶Â³Â£ÂvÂ¿Â–\\ntÃÃ‹AÃ€;&6K~Â¸pÂ¹Ã¿4  Â…~Â­_:]Ã¶@Â’ÂƒÃ®b=Ã“^Ãª! Ã¸Â¥Ã«Ã‹+60$Ã®Â­`Ã‘Â›AeÃ¡;Ã¯ÃÂ„eÂ€U&Â¨Â¡Ã•Ã¬s8Â‘#c7iÃŒJ*Â‹ÃœzC7Â¬Ã¸\\nÃµYÃ†Ã¢Ã±Ã§Â‘}ÂÂ¬ÃÂaÃ¾Â»ÂBÃ¡0Â»Ã–UEÂ°~$Ã¹%AÂ•Ã¡Â¾tÃ˜Ã›Â¡dÃ€GÃ´Ã‡Â£r[Ã«Â´Â¾J8\\nÃ»5Â¥xy\\nÃ¥Ã3Â©Ã¦Ã­Ã£\\nÃ–ÃŒÂÂ‡]Â†Ã£Ã½U)Ã‡Â¦XhÂ˜Â€BÂ—Â¦PyÃ´2ÃŠ+Ã‘fÃ¯Â®3Â‰gi9Â´Â¸$\\tÃ¯.Â«.]Â²Â£Â¢ÂŠBÃÃ¬ÂŒxhPÂšIT"Ã¾Â¯;<Ã£\Â¢+3Ã·EJÃ¸Â‰Â…Â¹vMÂ³Â tÂ¿Â‡xxYÂ¸'ÃŸbpÂ¿Ã›JÂ—ÃÃÂ†Ãš-*tÃ—o0ÃŠÂÂ¶Ãœ\\b? r\\bYÂ‰Ã§U7eÃšÂ…XÃ˜zÂ´Ã–Â²}YÃ‡Â‡dÃ¤Â”ZÂ¾eÂ«Â—ÃÂ°Ã ;;^Â»MÃ“Â‘!Ã˜Ã„Ã°.IÃƒÃ‘uMM;Â¡ÂƒÂ½/Ã–Â‘#Â§Â5Â…\\r]Ã‹Ã¡=Ã£Â§Â¦AÂ´Ã“>r*ÂÃ²=Â«ng=\\f4[Ã—CÂ›RÂ Â¤ÂEÃ‚BÃ‚Â´Â²1{*ÃµlVÃ«Ã¿O9ÃÂ®qGÂ€Ã¶IÂª*CÃ seÂ‰0Â«Ã€ÃºÃ‡{\bsÂ¨Â Ã¹EhvÂ˜ÂÂÃ·Â‹Ã³Â•LÂ´Ã™IÂ»ÃÂ•Â«Â˜p`Ã²Ã©ÃŒÂ§xK0Â¿ÂŒÂ¹Â¬ÃoÂŒÃ˜Ã—Ã–ÂšÃ™MÃÃ¼Â˜fÃuÂÃ«hÃ—Â¸Â±sGK&Â¼iÃ7\\n\\nÂTQÃ²Â™$Â¼Â‘34Â¬Y\\fÂº\\tÂ‘vÃ°$Â”Â¢!Â¡WÂ®Â½Â»ÃƒÃ·ÂƒÃ¶Ã‚Ã¦Â•mY-ÂµÂ—ÂŒÂ¦cÂ˜ÂÂ›Ã›Ã~ Ã¸?Ã‡Ã‡OÂ§eÃÂÂ«Â·vÂÂ’Â¨Â‘Ã“Ã®T]Â¼1|R[Ã‰Â°ÃŒ\\nÂ»Ã´y^1<WÂ±Â›Ã­ÂªÃ¾'ÂÃ‹'3U(ÂÂ°JÃˆ7CÂÃ¤Â lÃ‰1Âº@ÂŸoÂ¸r.ÃÂ¿sWÃ¬Ã”"Ã˜Ã†ÂÂ¿$?ÂÂ²Â•Ãº`Ã¬hÃ®Ã‘ÂÃÃ„ÂÃ„Ã“P4Ã0FÂ½p#Â¢$&ÃƒÃ¹-Ã‹BÃÃÃ·Ã°s*Â®ÃDÃ‹nÃ¢Ã¯Ãº_Ã»ÃŒGyÃ†Ã¬Â®Ãº ÃšÃ¤WCÂ½Â³Ã‘ÂƒÂ–Â£wÂÃ”Ã„Ã“}ÂyÂ³6Ã‰Â>Â¸Ã–Â½Â¯Â‚ÃªÂ›ÂµS(\Â¥Â²'WÂ—Ã¡ÂÃ”Ã³yÂ¿:Ã±Ã·Ã§JÃ¸NÃ°Ã®Ã…ÂÂŠÃ¶Â˜XÃ¶#zsGeÂ¦Â–ÃµÃˆÂ“Â™,Ã½@Z -Ã¿HzÂ³Â¸mÂ=>Â¹Â‚Ã‰ Ã¡4Â®u*ÃaÃ¾ÂˆÃ™JÃ®Â¬fÂ\HfÃ´LcMcÂ¹ÃŠÃ¦v1Â¥:ÂPmÃ©NcÂ¿vÂ²Â»1SÂ™\\r9'ÃŒÂ‹y|(ÂšÃ´Â¦lIÃ¹Â„Ã¦Ã°E1CÃ»Dm, ÃÂ´Ã°BÂÃ›Ã€BÂšÃ¦_,Vyxl_zÂ¬<Ã‘Ã£Ã“^lÂ´@Ã´2Ã„Â´\\bcÂ’Ã—Ã…8)ÃˆlÂ•Â†Â„{Ã½Â’5Ã±SÃÃ´Ã¦Ã…Â¿zÂŒÃ¢PÂ€Â \\rdÂ®(Ã©:Ã‰7;Ã£Ã¦cÂ±Âš#Ã¤Â¦9Â¥\\nÃ¿KÃ‘Ã¢Â¡+AÂ¦Ã±Ã¹Â¡Â‚Â‘ÂyÃµÃ·Â­CÃ¼8Ã‘vÃœÂ¹~cÃŠÂ¤V]aÂ“YMÂ¡ÃšÃ€8Ã·Ã‚Â®h="yÃ²btTÃÂ§Â Ã²ÃÂ U\\tÂ˜:Ã›UÂ„*IÂ§Ã§Ã’Â¬Ã–2Â«S=iÃº[GÃ†{QYÂ‰ÃƒÂ’z,<hÂŸÂ·Â‚?Â‹ÃœÃ·ÂŒ\\tCcÃÂÂ¡ÃlÃ‰\Ã‚jÃ’:Â¼Â§HÃ–1ÂºÃ£M1!KÃ¡Ã¥Â‡Â=<Â—cp&Ã¸Âœ[LYÃ™-ÂºÂ§Â—Â°Â¾Âª Ã§Ãœ]ÂƒÃÃŒÃ~ÃÃÃ¬Ã•cÂ…Ãš<ry+s`jÂ´Ã‡Â‡Ã¨MÂÂ´\\tÂ‘ÃÂ–JfÂºÃ·}Â—Ã»jiÃ’Â±Ã™$Ã³bÃ†iÃÃÃ’MÂ–Â¨GÂ·@|S!5ÂŒÃ‹YÂ·Ã¾mSÃ†<Ã„Ã»gÂ¹/Ã¢^HÃ­Ã¨$Ã¥Â²Â¬HÃµÃ±p.Â’Ã¨)Ã½Â¶Ã‹gÂ…Ã…Â¯Ã›Ã™Ã«ÂŒÂ°GÂ‰\\rÂ±cÂ²gzÃª3YÃÂ¯Ã–Â<4Â¢^[sÂ’ZlÂ¸8ooÂ¤|bs&Ã Ã„poÂµÂ´ÃˆÂœd{5Â¾Ã¢ÃªÃ“Ã›ÂµFÂ¤Â†CÂšÂ¿$hT}Â‰pM2MÂ´Â Â£Â³Ã´\\rÂ¨ÂÃ…ÂœÂ¤BF,w"}L! Â´PÃƒÂÂ¸Ã¾7nYWÂ±dÂšÂ’lÃ¤qÃŒgÂ¾}Ã² Â¡ÂµÃ°s\Ã•ÃµVÃŸvÃ´Ã Â†ÃÃ¿Ã°Â¶Ã¸mÂÃ®Â²5ÃGÂ™~Â–iÂ }]Ã•Ã›Ã¹Â‚Â¯\\f}AyÂ”wÂ±Â”rÃÂ¥ÂŒÃ­Â†ÃšÂÃ´cAÃ¡Â²ÃÃ›SeÂ’ÃÃˆÃÂ”dÃ¾Ã°Ã·DTÂ“rÃ·Ã‘Ã·Â›Â¹uzÃ±Ã•5Ãª=Â¹`Ã½Â©h\\fÂÂ¨ÃŠodaÂ²EÂsÃ­Â´Ã§yÃ¡Â\\tOÂ¼MÂÂ¥)Â½Â¨ÂÃ‹Ã¹WÂ¥Â‚n,Ã¹Ã»Ã¨Ã¼Ã¹.Â„p{Ã’2TÂ¢Â´G_BÂ„Ã‰?Âª1Ã¾Â‰L \\taY%^/9g]ÃªÂÂÃ¤\\nÃ˜-:Â¢$Â‡vM2Ã¿eÂ¤;\G, ÂŠÃ¡Â­Â§Â²ÃalÃÂ¡uqÃ”Ã§ÂšÂ”Ã—Â¥Â’ÂSÃŒÃÂÂ®4ÃÂ¨Â.Â¸Ã€{KÃ¨GÂºÃ—\\f>Ã¸ÂŸ$Ã¿Ã’\\nÂ¿4pÃtÂ†g"fE7ÂÃ™MÂ— bÃÂƒd^Ã•JÂ–ÃªÂˆÃ«0Ã—Â‚&<fQÃ±ÃÃÂ¾Â}JÂ”vÂÂ¯sbÃ‘ÂÃ›mÃ¦\\nÃ«Â˜SÂ«!ÂNÃ¼ÂŒ\\bÂ³Ã®RÂ–Ã‚^Ã“\\fÂ›Ã´>=Â¢LÃ•Ã­ÃFÂÃµ\\rÃˆÂ¸ÂµÃ²GtdÂœÂ£jÃ¹ÃTÃ²#gÃ›Ã¨ÂŠÂ·Â§ÂÃ 1Ã…Â!ÂµEÂÃªAwÂ˜np\\fÃ¢KYeGz\\tÃ Â·=5'|1'$ÂœSÂ¼Ã¿IÃ¾Ã²9ÂTÃ¯Ã¯Ã¼Â™Â¤qa\ndÃ˜Ã…BÂ²ÃœÃ‚;Â¥gÃŸÂ«rÃ­Â‘ÂšÃ‚Â½7K5\\bÃº?Â¸ÂÂ–Ã„:Ã ÂœÃ¹Ãˆ;<{ÃÃŒÃšEWÃŸÃ´Ã’~Ã£+Â…Ã½Ã¥'MÃ›MÃ’9<Â³sÂ±llXH>hÂº6Ã¯NÂœZÂ…:Ccd[Â°Â¹Â™Â™ÂÂ²ÃÃ½Âˆ5Â«Ã€Â¶Â½Â©Ã‹Â[ÃEOÂ°Ã©>Ã¼;bVÃ¯Â®Ã±Ã†Â‡ÃƒÃƒ6\\nÂÂ±ÂÃ–Ã®mVÃZ{Ã¶Â•HÃ¯HÂŠ<TÃ›ÂºÃ°;Ã¨Â¾Ã Q~<^(\\nÃfX87q`Âª)Ã’uÃ—ÂŸÃ†]Ã¿\\bÂ²Ã„Â®uMÂˆÃ¨3d{Ã˜Z[B2uÃ„Q%Ã®0Ã‘Â¶GÃIÃ½LÃ·c7BÂ²ÃƒÂˆÃ…Ã”qÂ´ÃÂ‰;Ã¹$ÂšÃ§0Â‡):;Ã‘Â¯Ã©KÂ Ã¡Â·Â„\\bÂ‡/Ã¿EV0Ã Â¬GÃ¼ÂÃŒXÃ…Â½Â¼^_Â€ÃŸ&Ã¹ÃÂ¿^Â”Ã{Â–VeÂ¶<Ãµ@Ã½Ã´Ã¢Ã•yÃ Ã½Ã…CuÂŸGÃ·`ÂÃ­ÃŠÃ«Ã™Ã»ÂºÂ†Â‹&Â§Ã°b!Â†ÂŠÂ‹Ã—Ã«Ã«:teÂ6(IÂ¨ÂƒÂšÂ¨,3~Ã½ÂÂ‘Ã´Ã›PÃ§=?Ã«\ÃµÃ¿.Â¶Â¯@Â˜ÃŸÂ³Ã­Â¡Â½Â¾Ã³hÃƒÂ­Ã«pÃÃ§{Ã¬Ã£2Â¢Â«//O%7Â¸Â–Ã­ÃœÂ‚ÂˆnÂ¶Â³2ÃŠÂ”;wÂƒ>^Ã“^yÂ±Ã‹Ã¼ÃÂŸÂ¤wÂ¼Ã‘MÃ‘6YÂÃ¾Â¢Â¦Ã¸PU\\t\\b:Ã™Â·ÃƒÃ“\\ncDOÃ‰Ã›wÂÂ±Ã¦Ã‚$\\rOÂ›Âœ\\nXÂ¸Â¤Â»Ã¢a}Â„qÃ¬Â€gdÃ³Â¤Ã¢Ã Ã³l'>LÂ‹<Â©ÂƒPÃœÂ…[ÃÃ†MÂ´ÂŒgÃˆLZÂ¿ÂºÂ·Â±=Ã‘%ÃÃaÃ”Ã¦$Â‰Ã¼Â‹Â…BXÂ˜Â¸Ã»sÃ­Ã¤Â›Ã®ÂŠÃ¥sÂ°$KÃ‚5Â°CÃ±ÃÂÂ¯Ã“NLÃÂ \\tÃ‰Ã»Â¨Ã¿R}Â”Ã¤Ã†/hi,|Ã“NÂvÂ¶Ã²=7b~cÃœ{cÂƒÂ¢Ãª\\rÂ²UÃ™Â–EÂ‡'LY<7Â‘ÂƒÂÂ)Ã¬Ã¡1P06+Ã…ÂÃ¢bÂ›tÂ«Â£Â€Â¬ÂšÂ£Ã¼Â”t&8UÃ¯\\tP;*Ã‚Ã°\\tÂ¹Ã¡Â«Â´Â¸qÂ”U_9RÂ—ÃŠÃ»Â­kO2?Ã¡+hÃ©Âµ*Â©Ã”Â½ÂÃšÃ€DÂ¾ \\b 2gDÂ°ZÃÂƒÂ¦Ã“\\ryÃ­foÃ¾Â0'aÃ­ Ã’_ÂÂŸ>|L/ÃŸ'iÃ¬ÂÂªÃ²CÂ®xjÂ¹CMÂ ;ÂŠÃ…ÃÂ™Ã²6Ã¡Â•ÂÂ¤-Â¬Â›ÂUjQÃŠXÃªÂ‡{Ã“Â¢xÃ­Â‰srÃDCCÃ­ÃÂ¢\\rÂ™Â¦ÂŠÂ¦ÂšÃª\Ã…]Â¬qÂ«Â–/A.DuxÃŠÃÂ’Ã'E)Ã™LDÂŠÂµÂ¾ÃƒÂŒÂ¾wQÂ€ RaÂ–ÂŒÃ”Â¥Ã´%Ã¥ÂÂ Â¨ Ã‚~Â›Â€Â…Ã´HnE,tÃ·Â´Ã¬3T!t Â†Â™\\nÃ‚ÃÂ¹_ÂˆÂ‘ÃƒÃ”Â¬Â¹{zU3\\fÃ“UÂÃ¢Â°Â±eÃŸÃ„\\na\\fÂqÃÂ»1ÂµKyÃ¢Â¢Ã@ÃœP3o,Ã¾%laÂbHÃ‰ÂÃ¿\\nÂ‚TÃ¬Âª$Â¶Â¯Ã¿;Âª-LÃ…Â€Ã¬Â¹Ã¼Ã·Ã¶OÂ®YÃÂ—}Â¤r.ÃƒÂŠÃ£zRZÃ°Ã­\\nÂµÂŸÂ°Ã·jSÂÂ¸Â‰ÃÂ€Ã¥Ã°Â”2?Â¤Ã¼Â²Ã‘ÂŒcÂ»QÃ°Ã Ã€Ã£-VB'ÂŠÂ¢Ã–4Ã†Â›ÂCUEÂ€Â™q%Ã›A_Â”ÃšÂ­Â”Ã©nÂ©ÂŒ(CÂÂÃ©94ÃŒL|)]Ã¤\\rÃ¶Â¿Ã‹Â¦Â¶B@!rÃ®Â¶]ÂœZmÃ©UÃ‡aÂ½Ã’pÂ±Ã·Ã´ÂwÃ§e\\nÃ³Y/Â¸WÂ Ã¼Â«Ã¬Ã·%Â“Ã Â‡Ã°nÂ¥Ã‡v6Ã”Â±HÃ¦Ã½Â¶ÂºÂ“2ÃnÃ¶Ã¹Ã™Â–?Ã™mÂ“Â£Â Ã»i{Â•.Ã—Ãª<5Â­Â§\\fG5Ã¯sÃ—-Ã­Ã¬y6Â¯ouÂUÃ»Ãª4Ã­ÃŸaJÃ”ÂœYÂ„Â–Ã–Â©tÂ«+Â¡Ã r)ÃµÂ‰BÂ›ZÂŒÂªÃ¬Ã¾ÃÃ¼ÂªÃÃˆÃ‚Â¼Â¨Ã©"Ã·Â•ÂˆWÂ¶ÂªrjEÃ¢Â§oÂÂ—3QÂ½Â‡Â§Â•Â’Ã§dOrÂ†7qÂTÂ¨Ã“Ã™ÃÃ³Â·Â¯ÃªfÃ³Ã‰Â’Ã—-qPÂ­Â‹ÃÃ§Ã‰)ÂpqdÃÂµÃ†ÃŠÃ—zÂ–A/AÃ–ZÂ´Ã°ÂÂ¥Ã¾]5Â· qÂƒ3Â¶RUÂ°sÃ¹ÃÂŸ!72&Ã ;Ã©Âš EÂ•eÃb&Â²Â­\%gÂ³Ã‚GÂ4ÂŠÂ‚w_6Â‡Ã¾GÃ°SÃ¿Ã—Â”iÂ–ÃÂ²yOPÂ•ÂkGÂ°Ã•Ã˜rwÂ’Â¡rÃ–;ÂŠÃˆLÃ†Â¿ÂŒ\\tÂ¬-lÂªÃ™Â¶Ã¤Ã ÃƒÂŸIÃ,TÂ–Ã‘Ã—Â‹Ã‹Ã±cZ_Ã–4hÂ„Ã²b%ÃfÃ„JÂ¿Â©ÂŠÃ‰xtÂ¥]ÂŠÂ†Ã¾CeÃ¿0~Â’pKÃ¿eÃºÃÃÂœÂ¹${v7Â¹Ã–ÃŸ{Ã…-}Ã„1J"Â†kÂ‘Â·Ã‡Ã›Â¼Ã¡Ã«Â„Ã°Ã¾ÃŸiÃŸÃ½;8b}Â¸4"Â­~T@uÃLÃ…Â›6UÃš s)Â¼*ÂŸÃ½Ã¨Âº Ã¤bÃ‘+Ã‚AÃÂœY9#ÂÃ6SJÂƒvÃ¨)]Ã´Â¦\\nÃ’'Â Ã•Â¿ÂœÃ¨ÂˆÂÂ±ÃÃ›Â‘Ã†Ã¶Ã°2Ã w9FÂ^Â‹Â¹Ã­Ã»0Â²Ã€`L)Â¨DÂšÂ‚,Â¼xÃ…Âˆc>ÂšÂ©Ã²Â±Â¼Ã…0Â–:)WÃÃ™Ã²Â…ÃƒaÂ‚0ÂÃ¼Â¯ÂÃƒGÂ¸Ãœ|Â¶ÃK1Â®&BÃ†Ã¬Ã¤Ã€Ã³<ÃªvÃˆ;[Â«Â­2Â¶RÃŒÃ½&Â¿5Ã‰RÃ¦Ã°PÂ´Ã8Ã¿Ã“Ã¿9Ã°ÂµÂEÂ±Ã¼{P+ ÂÃ©Â­}q8-3ÃªÃ£Ã£'Ã½\\r.lÃ°Â±Â¬Â©Ã¤Ã„Â¹jÃ5ÂÂ>XÃ•Â«"ÃÂ—Â«ÂºDÃYÃ‡9Â—[Â­]HÃ¢Â®\O1Â¤Â½V-Ã§Â¤{Â´Â¾Ã‹S_Â¨JÂŸm(ÂˆÃ’+Â…wÂ½6Â™uÂ™Ã…Â·ÂŠfÃ£JÂ“Â°#Ã­ÃˆÃ„ÃšÂ‘pÂ—Â1Ã–!]T\\r2ÂÃ Ã¯UÃÂ»=XÃœÃ“MÂ‰Â‘jeÂªÂ„HÂ­CÃHÃ´|Â•*Â³Ã’Â–h3Ã…ÃŸMÃ«c#Ã¿=ÂºÂqÂ…ÂŸÃHVÂ™Â¿&VÂ­Âƒe\\fÃƒÃŠgbAÃ“Ã¨Ã4-Ã—Â bÃ‰Ã©ÂŸÃ¤Â‰RÂ Â…ÃÂÂ’,Â‹Â›Â·u/%)Â¸9ÃªeÂŒÂµisÃ§"Âª]Â–ÂÃ¿(L"Ã‚ÃdÂµUPÂ†Ã©1Â½jÂ²ÃÂÂ¦bÂ„~Ã#Â†PdÃŒpÂ§Ã©jÃ‚qvOÃ°Ã¬Ã¸ÃÃ²2Ã„Â‚]ÂšÃ£Ã§Ã caÃ‘;Â¹Ã™Â…Ã¯?Ã›H_'AÂ Â»Â½'Â…Ã³Ã‹aÃ«Ã—Â„Â¬Ã¨Ã¥Â¦vÃ›IÃÃºÃÂ™!Â¦Ã»Ã¯Â½Ã‡H\\nÃ€Ã¢Â ,ÃµÂ‡Â³&Ã‡Ã™Ã®Ã¯,'ÂÃ¦Â‘_iÂœÂ\\fÃÂ¨Ã­ÂŠXcÃ¼>Â©HYiÃ“Â¯Ã£ÂšÃ¹Â»Â¬Â³Ã‰Ã¤67Â‰Ã·Ãš;cÂ¬Â¨yÂ¤Ã„WÃ‚ÃºIÃœÃ–3Ã”k/Â¬Â°UÂ‘>-Â¡Â‰RÂ€Â»RÂ‡eÂœÃ¢+Ã`iÂ±8Ã¡Ã¼mÂ¹Â«Ã‚ Ã„Â¼Â˜Â˜jÂ¹Â›8vÂ¸ÃŸÃ­wÂ kÂ¿Ã»\\fÂ©QÃÃ«Ã»ÃŠ}Â©)Ã—2ÃªÃˆhÂ•ÃšÂ¸Â›Â¬Â„ÃƒdÃ½Ã~Â¥ÃºÃ¼Ã‹8Ã­;ÂŒQKÃÃ¯[Â“Ã‘Y:eÂ˜%ÃœÂ¸Â¿ÂµÃ°-Ã¬Â†Â²ÃÂÂµhFzÂ£Ã?Ã…Â¢0$7Â±Ã¾Â¤Â… Â•^eÃ­Â»BÃÃœEÃ‰Ã–Ã¨XÂ¨Ã´Â¸Â³u,Ã‰-]ÃŒsAUÂÃ¬L0Â¥Ã•Ã]Â¦)Â„ÃÃ²ÃCÂ°Â±5GtÃ»CÃ£jWÂŸr)ÃŒvÃƒFÃ¾MÂ’?Â–Ã€bÂ¨Â¬Ã¹>Â¼Ã›kÂ©Ã®ÃÂÂºÃŒ:Ã¾Â¤%Ã¬Ã†Ã Ã¶kHÃÂ¬ÂÂ/Ã³Â‚bÂªÃŒmÃ\\ffdÂ¹EÂ*Ã„JÃÃ³Â¦ÂŠÂ½ÃŒÂŠ~Ã‡;ÃÂˆÂ˜Ã­MÃ·Ã¯ 0ÃŒÃ»(_ÃÃ¤Ãœ\\fgÃ®p\\nÃ¦Â¿;FÃ·`hdÃ`Â¡0@VÃœÂ†Â›Â¬~f*,Ã†.>Â¡Â›Â¸uÃ²"OÃ¦Â©Ã Ã« ÂqÃ‚Â±Ã³Ã¼HGÂˆÂº&Xi!Â¦ÃŒ7iÃ•Â¼ÃÂ‚Ã Â <_ÃœÃ²-Ã»Â–lÃ¦Â”ÃzÂ„Â®Â'Ã E#Ã—3Ã©H[Ã¶)Ã³\\n)\\bÃ†|Ã–e-Ã”~Â´kÃ˜fÃ»&Z3ÂœÃˆÃIÃºÃ¡Ã³Ã¬Â¤/jÂ°Â¤Â¦XÂ‰AÃ¾Ã·"Â–HÂ³Â´Âªa[q$Ã¡Â¯Ã„Ã xÂ‘Ã Â±Â¯Â˜.Ã™Â†Ã¶SÃ¡Ã²Â¿PÃ›DÂJÂ«Ã²Ã¥PxÂÃ„Âœ\\bL\ÂˆkÃ“Â§ÃÃ¾wÃ5Ã­ÂŸÂ’ÃÂ‰Â§Â¿Â¿m\\fuÃšÃ‘Ã/iÂ°Ã¨LÃÂ­Ã¶^Fdk Â§oÃ›ÃŸÃŸDÂ€Â‚Â¼\\rÃ•Â„/Ã0Â´Ã±ÃÃ ÂÃˆÃºÂ–KPÂ²Â˜SÂ³ÃB'Ã¨Â†ÂŒÂÂÂ‰.Ã—ÃšÂ¡ÂÃGjÂ»]eÂ“5Â€KÃ…Â„ÂºÃ¢ÂƒÃ²lwÃ¾ÂÂ€&vÂ¥8DFXmBÃ§0TS.Â†Â´;Ã 8fÃ¥Ã«Â½Â‘Â„Â\\tÂ»Â‹ÂÂ²'\\t5ÃrrÃšÂ¦Ã–gÃ¦ÂˆÂ›Â„QzDÃÂ”Â+?EyÂ›Ã•Ã«;Ã¹wÃwÃ™Â‚Ã¹Ã”ÃZÃÂÃ¿FyÂ‹Ã–N1Ã©Ã¾gÃœ{Â³Ã½Â¯=.Ãµ(Ã³Ã¯Ã°iÂ–Ã¼itYZÂ¨Â3ÃˆÂ;Do\Ã³|Â¹ÂÂŒÂŠÃ’#KÂ—#C*OÃ°Ã€<"Â°=Ã %Ã¬y!Â¬B]/Ã z%ÃÃS=SÂld2ÃÃ„MCÃ§,>Ã±Â’Â¹Ã¾Ã¥Â–\xÃ¸Ã“RÂÂœÂ…Ã…Â²pÃ…ÂµÃ†\\r`5Ã‡Ã¢|.ÃˆÃ¸LÃ«nÃ”Hw@Ã€3rÂ¦Ã…EnÃ«BgoJOÃ­ÃÂ…N!ÃÃ§Â¯Â› Ã¶Ã Ã’Ãƒ\\rÂ£Ã“AAÃÂ«|ÂÂµÃ¤Ã¿yÃ¹&Ã‹OCfÂ³Ã—ÃœÂÂ®Ã®5Ã£8JÂ§pgÂŸÃªÂ‘ÂµÃ“UÂ»Â˜ÂºAÃ§Ã±ÂˆÂ¸Ã¸Ã¥Ã„c?Â­ÂsÃ¨Ã¦5xÂ±]mÂ­Â—Â”Ã¨Â¿ÂÂ©}ÂµPL"Ã¯Â¿rÂ¸Ã™MÂ±9Â»92Ã™6Ã£Ã¶Ã®]}!ÃŒ ÃÂ¤ÃÃnvÂ‹^ÂŠ&Â¬DbpmOÂ½OfÃ†!Â³8C5Ã¡E\\nÂŸ)r7Âƒ!EÂ›ÃyÃ„Â€x!Âq&ÃœYÃ¯FÂ¦HÃ¸N0"Ã›hiÂÂ¬Â°ÃˆÂ¶2Ã—Ã“Ã#ÂºÃŠ[ÂÂ¬Ã¦innÂ:Ã´4ÃšÃ¢Â²~@Â°Ã…tÂ‚Ã”Â¢\\nÂ¡Ã’ÂÃ9HÃ¨@Â‘Ã‹Ã­Â„73ÂˆÃ¼Ã­Ã„ÃZÂ Ã¦Ã• flhÂ±2Ã‚6ZÃƒÃŠÃ¦1*3&Ã¦aÂ­Ã¾*.STb;WÂ¤3Ã¬ÂªÃ—Â˜w"Ã‘Ã®Ã•\\bcÂ¸Ã„Ã†Â“W&ÃšÃ™ÃÃ]ÃƒÃ¹Ã„bhh:Â³Â†Â§1!Â™Â¢7wÃ©Â°ÃƒÂÃ¥Â¿Ã¡IVÂ®Âª4Ã¨1Ã©Ã†Ã¼9Â€Ã›4JRpÃ…Ã›Â²>Ã¬PVÂ Â°Ãˆ1Ã«ÃŒÂ¼Â·Ã Ã“Ã‡mVÂ“wÂŒÃ«VÂ¦Ã†Â»Ã—Ã§TÃ®Ã›Ã¾Ã†[Ã‚lÃ¾CÂÂµ1ÂœÃ˜\\tDÃÂ½cÂ„Â‚Ã€@Â”Ã’Ã½Ã˜Â–Ã³Â´@Â¤Â¤Â¾Â†7nÂ­Â³Â‰iÃ¨Â¡8Â‚Ãˆ)ÃƒMÂ€C7ÂŸu[!Ã¹Ãšr\\tÂ¾Â‰HÂ§Â‡iÂ]Ã…Â­,Ã¢UÂ¦fÂ€Â‚Ã™_]jÃƒÂ•JÂ„{yÃ·Â³ZÂ±Â¹Ã§YiÃ¬Â Â¦x,ÃšYÃªÃ‡ÃÂÂ¨b}Â±HÃƒu\\fÂÂ¸Â¾Ã°ÂÂ·1Ã‡Â§Ã¡Ã°mÃŸWÃmPuÃ6Â†Â™Ã–4gx/Ã¾Z>Â¿-Ã°Â‰kÃ„Ã¡w]Ãœ"&Ã¶Ã‡Ã¼Ã¡ÂÂ‰4eQÂ•lÃÃˆÃ¸Â±k8Â¹Ã²Â¬ÃŒ4RÃ²Â±Ã¢$Â¸Â•'0Â¡Â¨CÂ•Ã©6)Â¼Ãƒ|ÃKÂ¯Â¨FÃÃ¨Ã" 4;Â„Ã§2Ã’Â¸;Â´hcÂ“Ã–CÃ¿PdÃ¡Ã•ÃœHÃ¨ÂªW&ÃœÃ½Ã²=B_gs1~Â¾Â]QuÂ–MÃ½Ã[ Ã±iÃ¡Ã­Ã½}$Ã€Â£ÂŸÂ·w-Â’Ã€vÃƒ9;jK9zÃŒÂ†R.Ã”fÃ± bÃ£^bÂ¾Â™Ã€Â¡ÂœÃ—Ã­Â€ÃÂ‰Ã‰;Ã¢Ã¬RÂ•ÂƒÃ¨5Ã›Â„bÂ¢Â‰^,CÂµÃ‘ÂŒ]Ã›Â¡Â«CÂ¡CÃ¨a+-Â‹Ã‘Q0Ã¬>M#Ã§KfrwÂ¼7`UÂ \\rt_Â¸ÂœS#ÂœFÂ¤Ây>t\\tÃ 7PÃ¥Â‚Ã®Â’Ã†_Ã€{Ã˜fÂ’Ã³_Ã…|Â¼3\Ã•Ã„=Ã„Â·Â—Â¶zoÃoÂ»<Â˜x.\\bÂ¦Â–Ã½r0Ã™zÃÃ–Ã¾Ã¬Ãº$Â‰ÃµÃ¼ÂŠNÂ…]YÂ˜ÂŒÃŸÂºÃ¶Ã•.Ã¼uÂÂ˜CÂ†]Ã²ÂŠ>Ã“ÂˆÂ‡oUÂ­Ã¬d3Ã£ÃÂ¯*Ã¹Ã£ÂˆÂ‰Â‰#Â¶ÃÂxÂ Â‡Â¾/;Zf9Ã¿Y"Q\\nssÂ¶\6Â¦Ã¾3ÂƒÂ¢t[p9Â¬H-ÃÂªÂ‡Â¯FÂ ÂªÃ´Â—+VÂ€nNÂƒÂ«Ã‡t5-Â”\0Ã«Ã¢Âƒ9YÂMÂ‘Ã_Ã°Â´Â‡Ã³Ã…Ãµ$Ã²Ã¿Â¯=Â¹9Â¼ÂsÃ²Âœ;Â’ÂºÂÃ·Â²lÃ„=fÂ°lÂ®Ã”UÂ«wÃ½Â¯p A\\bÂ¸zÃ³1Â‹C5ÂªÃ”Â¬ÂÂ”Ã˜Ã¹%Â–8bÂ”4#ÃªOÃÂšÃ›ÃŸÃ¢Ã¼ Â¿tÃ…8Ã»Ã­Â†0ÂºÂ°ÃœÃ‡ÃA%\\nÃ›g:Ã‰?Â²1Â‘Â¹;Ã”ÃŒÂªzC9qÃ\\nÂ“Ã‰Â‚al#&}"Â¤Âš*%ÂƒÃªÃºÃ¿ÃkÂ©\\tÃ¨\ ÂœÂÂ«$Ã¾`Â…\\ruÃ–Ã‰_Â—Â·XÃ³ÂŠÃ™_ `Â€\\bÂÂ„tÃÃ•Ã‰^Ã·Â©<9ÃºÃ‘Â¢ÂÂÃ›Â£#Â±sÂÃ©\\nÂ˜D~Ã—Ã›(p9Ã¬IzÃ¨Â…<qÂˆÂÃPÂÂ»WgÃ3eÂ€Â¨Ã‘Ã­Â¦ÃÂÂ¹Ã±Â¢PÂ¡8ÃƒÃ­Ã°Ã†Ã…Ã™Â¶f\\fÂ¸Ã¹Ãµ]Ã¸Â¡Â¶Â¬Ãš\\bÂ“Ã€Â€Ãf.Â‹Ã¨ÂÂ¨FÃÃ»yÂÃ•"Â‹Â¹u{Ã‰Â‹Â–Ã¯KÂ¦ÃŠEÃ ?_Ã™iÃ $Â¼y}hÂ¢Ã™ÃÃ¤Â’Ã‹Â¢uÃ‡Ã¾Ã©_Â±ÂTH:+Â±Ã¬Â²bÂ­ÂCRÂ·Ã´Â¬<};ÂºÃ‚(Â¢9Ã¶3BÃÃœÂ¦ÃÂ§Â”Ã€/6f$Â“dÂ¥PQ8Ã­ÃºÂ¶Ã˜m?8Ã§NÃ¤eKÂ°lvÂ†Ã»NÃ™{Z&ÂzÃ #ÂÃ¶$Âª#Â·IÂµÂŸÃ®JVÂ&[Â¬[xÃ€ÂIÃ¶Ãº)*vÂŠMxqÃ|Ã '
    //   130: dup
    //   131: astore_2
    //   132: invokevirtual length : ()I
    //   135: istore #4
    //   137: iconst_4
    //   138: istore_1
    //   139: iconst_m1
    //   140: istore_0
    //   141: bipush #46
    //   143: iinc #0, 1
    //   146: aload_2
    //   147: iload_0
    //   148: dup
    //   149: iload_1
    //   150: iadd
    //   151: invokevirtual substring : (II)Ljava/lang/String;
    //   154: iconst_1
    //   155: goto -> 202
    //   158: aload #5
    //   160: swap
    //   161: iload_3
    //   162: iinc #3, 1
    //   165: swap
    //   166: aastore
    //   167: iload_0
    //   168: iload_1
    //   169: iadd
    //   170: dup
    //   171: istore_0
    //   172: iload #4
    //   174: if_icmpge -> 186
    //   177: aload_2
    //   178: iload_0
    //   179: invokevirtual charAt : (I)C
    //   182: istore_1
    //   183: goto -> 141
    //   186: aload #5
    //   188: putstatic burp/Zxxt.a : [Ljava/lang/String;
    //   191: bipush #10
    //   193: anewarray java/lang/String
    //   196: putstatic burp/Zxxt.b : [Ljava/lang/String;
    //   199: goto -> 364
    //   202: dup_x2
    //   203: pop
    //   204: invokevirtual toCharArray : ()[C
    //   207: dup_x1
    //   208: arraylength
    //   209: dup_x2
    //   210: pop
    //   211: iconst_0
    //   212: istore #6
    //   214: dup2_x1
    //   215: pop2
    //   216: dup_x2
    //   217: iconst_1
    //   218: if_icmpgt -> 320
    //   221: dup2
    //   222: swap
    //   223: iload #6
    //   225: dup2_x1
    //   226: caload
    //   227: swap
    //   228: iload #6
    //   230: bipush #7
    //   232: irem
    //   233: tableswitch default -> 302, 0 -> 272, 1 -> 277, 2 -> 282, 3 -> 287, 4 -> 292, 5 -> 297
    //   272: bipush #11
    //   274: goto -> 304
    //   277: bipush #122
    //   279: goto -> 304
    //   282: bipush #71
    //   284: goto -> 304
    //   287: bipush #66
    //   289: goto -> 304
    //   292: bipush #10
    //   294: goto -> 304
    //   297: bipush #58
    //   299: goto -> 304
    //   302: bipush #123
    //   304: ixor
    //   305: ixor
    //   306: i2c
    //   307: castore
    //   308: iinc #6, 1
    //   311: dup
    //   312: ifne -> 320
    //   315: dup2
    //   316: dup_x1
    //   317: goto -> 225
    //   320: dup2_x1
    //   321: pop2
    //   322: dup_x2
    //   323: iload #6
    //   325: if_icmpgt -> 221
    //   328: pop
    //   329: new java/lang/String
    //   332: dup_x1
    //   333: swap
    //   334: invokespecial <init> : ([C)V
    //   337: invokevirtual intern : ()Ljava/lang/String;
    //   340: swap
    //   341: pop
    //   342: swap
    //   343: tableswitch default -> 40, 0 -> 100, 1 -> 158
    //   364: sipush #-27043
    //   367: sipush #19444
    //   370: invokestatic a : (II)Ljava/lang/String;
    //   373: putstatic burp/Zxxt.ZA : Ljava/lang/String;
    //   376: getstatic burp/Zxxt.ZA : Ljava/lang/String;
    //   379: sipush #-27055
    //   382: sipush #-10863
    //   385: invokestatic a : (II)Ljava/lang/String;
    //   388: <illegal opcode> makeConcatWithConstants : (Ljava/lang/String;Ljava/lang/String;)Ljava/lang/String;
    //   393: putstatic burp/Zxxt.ZA : Ljava/lang/String;
    //   396: new java/math/BigInteger
    //   399: dup
    //   400: iconst_1
    //   401: bipush #32
    //   403: newarray byte
    //   405: dup
    //   406: iconst_0
    //   407: bipush #43
    //   409: bastore
    //   410: dup
    //   411: iconst_1
    //   412: bipush #50
    //   414: bastore
    //   415: dup
    //   416: iconst_2
    //   417: bipush #57
    //   419: bastore
    //   420: dup
    //   421: iconst_3
    //   422: bipush #62
    //   424: bastore
    //   425: dup
    //   426: iconst_4
    //   427: bipush #41
    //   429: bastore
    //   430: dup
    //   431: iconst_5
    //   432: bipush #-77
    //   434: bastore
    //   435: dup
    //   436: bipush #6
    //   438: bipush #-90
    //   440: bastore
    //   441: dup
    //   442: bipush #7
    //   444: iconst_0
    //   445: bastore
    //   446: dup
    //   447: bipush #8
    //   449: bipush #39
    //   451: bastore
    //   452: dup
    //   453: bipush #9
    //   455: bipush #-111
    //   457: bastore
    //   458: dup
    //   459: bipush #10
    //   461: bipush #23
    //   463: bastore
    //   464: dup
    //   465: bipush #11
    //   467: bipush #-124
    //   469: bastore
    //   470: dup
    //   471: bipush #12
    //   473: bipush #96
    //   475: bastore
    //   476: dup
    //   477: bipush #13
    //   479: bipush #-92
    //   481: bastore
    //   482: dup
    //   483: bipush #14
    //   485: bipush #42
    //   487: bastore
    //   488: dup
    //   489: bipush #15
    //   491: bipush #76
    //   493: bastore
    //   494: dup
    //   495: bipush #16
    //   497: bipush #-47
    //   499: bastore
    //   500: dup
    //   501: bipush #17
    //   503: bipush #125
    //   505: bastore
    //   506: dup
    //   507: bipush #18
    //   509: bipush #-9
    //   511: bastore
    //   512: dup
    //   513: bipush #19
    //   515: bipush #120
    //   517: bastore
    //   518: dup
    //   519: bipush #20
    //   521: bipush #12
    //   523: bastore
    //   524: dup
    //   525: bipush #21
    //   527: bipush #91
    //   529: bastore
    //   530: dup
    //   531: bipush #22
    //   533: bipush #-14
    //   535: bastore
    //   536: dup
    //   537: bipush #23
    //   539: bipush #35
    //   541: bastore
    //   542: dup
    //   543: bipush #24
    //   545: bipush #103
    //   547: bastore
    //   548: dup
    //   549: bipush #25
    //   551: bipush #-14
    //   553: bastore
    //   554: dup
    //   555: bipush #26
    //   557: bipush #70
    //   559: bastore
    //   560: dup
    //   561: bipush #27
    //   563: bipush #29
    //   565: bastore
    //   566: dup
    //   567: bipush #28
    //   569: bipush #41
    //   571: bastore
    //   572: dup
    //   573: bipush #29
    //   575: bipush #-109
    //   577: bastore
    //   578: dup
    //   579: bipush #30
    //   581: bipush #-50
    //   583: bastore
    //   584: dup
    //   585: bipush #31
    //   587: bipush #-47
    //   589: bastore
    //   590: invokespecial <init> : (I[B)V
    //   593: putstatic burp/Zxxt.ZX : Ljava/lang/Object;
    //   596: return
  }
  
  private static Throwable a(Throwable paramThrowable) {
    return paramThrowable;
  }
  
  private static String a(int paramInt1, int paramInt2) {
    int i = (paramInt1 ^ 0xFFFF9658) & 0xFFFF;
    if (b[i] == null) {
      char[] arrayOfChar = a[i].toCharArray();
      switch (arrayOfChar[0] & 0xFF) {
        case 0:
        
        case 1:
        
        case 2:
        
        case 3:
        
        case 4:
        
        case 5:
        
        case 6:
        
        case 7:
        
        case 8:
        
        case 9:
        
        case 10:
        
        case 11:
        
        case 12:
        
        case 13:
        
        case 14:
        
        case 15:
        
        case 16:
        
        case 17:
        
        case 18:
        
        case 19:
        
        case 20:
        
        case 21:
        
        case 22:
        
        case 23:
        
        case 24:
        
        case 25:
        
        case 26:
        
        case 27:
        
        case 28:
        
        case 29:
        
        case 30:
        
        case 31:
        
        case 32:
        
        case 33:
        
        case 34:
        
        case 35:
        
        case 36:
        
        case 37:
        
        case 38:
        
        case 39:
        
        case 40:
        
        case 41:
        
        case 42:
        
        case 43:
        
        case 44:
        
        case 45:
        
        case 46:
        
        case 47:
        
        case 48:
        
        case 49:
        
        case 50:
        
        case 51:
        
        case 52:
        
        case 53:
        
        case 54:
        
        case 55:
        
        case 56:
        
        case 57:
        
        case 58:
        
        case 59:
        
        case 60:
        
        case 61:
        
        case 62:
        
        case 63:
        
        case 64:
        
        case 65:
        
        case 66:
        
        case 67:
        
        case 68:
        
        case 69:
        
        case 70:
        
        case 71:
        
        case 72:
        
        case 73:
        
        case 74:
        
        case 75:
        
        case 76:
        
        case 77:
        
        case 78:
        
        case 79:
        
        case 80:
        
        case 81:
        
        case 82:
        
        case 83:
        
        case 84:
        
        case 85:
        
        case 86:
        
        case 87:
        
        case 88:
        
        case 89:
        
        case 90:
        
        case 91:
        
        case 92:
        
        case 93:
        
        case 94:
        
        case 95:
        
        case 96:
        
        case 97:
        
        case 98:
        
        case 99:
        
        case 100:
        
        case 101:
        
        case 102:
        
        case 103:
        
        case 104:
        
        case 105:
        
        case 106:
        
        case 107:
        
        case 108:
        
        case 109:
        
        case 110:
        
        case 111:
        
        case 112:
        
        case 113:
        
        case 114:
        
        case 115:
        
        case 116:
        
        case 117:
        
        case 118:
        
        case 119:
        
        case 120:
        
        case 121:
        
        case 122:
        
        case 123:
        
        case 124:
        
        case 125:
        
        case 126:
        
        case 127:
        
        case 128:
        
        case 129:
        
        case 130:
        
        case 131:
        
        case 132:
        
        case 133:
        
        case 134:
        
        case 135:
        
        case 136:
        
        case 137:
        
        case 138:
        
        case 139:
        
        case 140:
        
        case 141:
        
        case 142:
        
        case 143:
        
        case 144:
        
        case 145:
        
        case 146:
        
        case 147:
        
        case 148:
        
        case 149:
        
        case 150:
        
        case 151:
        
        case 152:
        
        case 153:
        
        case 154:
        
        case 155:
        
        case 156:
        
        case 157:
        
        case 158:
        
        case 159:
        
        case 160:
        
        case 161:
        
        case 162:
        
        case 163:
        
        case 164:
        
        case 165:
        
        case 166:
        
        case 167:
        
        case 168:
        
        case 169:
        
        case 170:
        
        case 171:
        
        case 172:
        
        case 173:
        
        case 174:
        
        case 175:
        
        case 176:
        
        case 177:
        
        case 178:
        
        case 179:
        
        case 180:
        
        case 181:
        
        case 182:
        
        case 183:
        
        case 184:
        
        case 185:
        
        case 186:
        
        case 187:
        
        case 188:
        
        case 189:
        
        case 190:
        
        case 191:
        
        case 192:
        
        case 193:
        
        case 194:
        
        case 195:
        
        case 196:
        
        case 197:
        
        case 198:
        
        case 199:
        
        case 200:
        
        case 201:
        
        case 202:
        
        case 203:
        
        case 204:
        
        case 205:
        
        case 206:
        
        case 207:
        
        case 208:
        
        case 209:
        
        case 210:
        
        case 211:
        
        case 212:
        
        case 213:
        
        case 214:
        
        case 215:
        
        case 216:
        
        case 217:
        
        case 218:
        
        case 219:
        
        case 220:
        
        case 221:
        
        case 222:
        
        case 223:
        
        case 224:
        
        case 225:
        
        case 226:
        
        case 227:
        
        case 228:
        
        case 229:
        
        case 230:
        
        case 231:
        
        case 232:
        
        case 233:
        
        case 234:
        
        case 235:
        
        case 236:
        
        case 237:
        
        case 238:
        
        case 239:
        
        case 240:
        
        case 241:
        
        case 242:
        
        case 243:
        
        case 244:
        
        case 245:
        
        case 246:
        
        case 247:
        
        case 248:
        
        case 249:
        
        case 250:
        
        case 251:
        
        case 252:
        
        case 253:
        
        case 254:
        
        default:
          break;
      } 
      char c = 'Â‘';
      int j = (paramInt2 & 0xFF) - c;
      if (j < 0)
        j += 256; 
      int k = ((paramInt2 & 0xFFFF) >>> 8) - c;
      if (k < 0)
        k += 256; 
      for (byte b = 0; b < arrayOfChar.length; b++) {
        int m = b % 2;
        if (m == 0) {
          arrayOfChar[b] = (char)(arrayOfChar[b] ^ j);
          j = ((j >>> 3 | j << 5) ^ arrayOfChar[b]) & 0xFF;
        } else {
          arrayOfChar[b] = (char)(arrayOfChar[b] ^ k);
          k = ((k >>> 3 | k << 5) ^ arrayOfChar[b]) & 0xFF;
        } 
      } 
      b[i] = (new String(arrayOfChar)).intern();
    } 
    return b[i];
  }
}


/* Location:              C:\Program Files\BurpSuitePro\burpsuite_pro.jar!\burp\Zxxt.class
 * Java compiler version: 21 (65.0)
 * JD-Core Version:       1.1.3
 */