package burp;

import java.math.BigInteger;

class Zxyu extends ClassLoader {
  static Object Zp;
  
  static String ZM;
  
  private static final String[] a;
  
  private static final String[] b;
  
  static boolean Zx(Object[] paramArrayOfObject, Object paramObject) throws Throwable {
    // Byte code:
    //   0: invokestatic ZK : ()Z
    //   3: istore_2
    //   4: getstatic burp/Ze7y.Zh : Ljava/lang/Object;
    //   7: checkcast java/math/BigInteger
    //   10: invokevirtual toByteArray : ()[B
    //   13: astore_3
    //   14: iconst_0
    //   15: istore #5
    //   17: iconst_0
    //   18: istore #6
    //   20: iload #6
    //   22: aload_3
    //   23: arraylength
    //   24: if_icmpge -> 169
    //   27: aload_3
    //   28: iload #6
    //   30: baload
    //   31: istore #7
    //   33: iload #7
    //   35: bipush #48
    //   37: if_icmplt -> 54
    //   40: iload #7
    //   42: bipush #57
    //   44: if_icmple -> 152
    //   47: goto -> 54
    //   50: invokestatic a : (Ljava/lang/Throwable;)Ljava/lang/Throwable;
    //   53: athrow
    //   54: iload #7
    //   56: bipush #65
    //   58: if_icmplt -> 82
    //   61: goto -> 68
    //   64: invokestatic a : (Ljava/lang/Throwable;)Ljava/lang/Throwable;
    //   67: athrow
    //   68: iload #7
    //   70: bipush #90
    //   72: if_icmple -> 152
    //   75: goto -> 82
    //   78: invokestatic a : (Ljava/lang/Throwable;)Ljava/lang/Throwable;
    //   81: athrow
    //   82: iload #7
    //   84: bipush #97
    //   86: if_icmplt -> 110
    //   89: goto -> 96
    //   92: invokestatic a : (Ljava/lang/Throwable;)Ljava/lang/Throwable;
    //   95: athrow
    //   96: iload #7
    //   98: bipush #122
    //   100: if_icmple -> 152
    //   103: goto -> 110
    //   106: invokestatic a : (Ljava/lang/Throwable;)Ljava/lang/Throwable;
    //   109: athrow
    //   110: iload #7
    //   112: bipush #43
    //   114: if_icmpeq -> 152
    //   117: goto -> 124
    //   120: invokestatic a : (Ljava/lang/Throwable;)Ljava/lang/Throwable;
    //   123: athrow
    //   124: iload #7
    //   126: bipush #47
    //   128: if_icmpeq -> 152
    //   131: goto -> 138
    //   134: invokestatic a : (Ljava/lang/Throwable;)Ljava/lang/Throwable;
    //   137: athrow
    //   138: iload #7
    //   140: bipush #61
    //   142: if_icmpne -> 162
    //   145: goto -> 152
    //   148: invokestatic a : (Ljava/lang/Throwable;)Ljava/lang/Throwable;
    //   151: athrow
    //   152: iinc #5, 1
    //   155: goto -> 162
    //   158: invokestatic a : (Ljava/lang/Throwable;)Ljava/lang/Throwable;
    //   161: athrow
    //   162: iinc #6, 1
    //   165: iload_2
    //   166: ifeq -> 20
    //   169: iload #5
    //   171: newarray byte
    //   173: astore #6
    //   175: iconst_0
    //   176: istore #7
    //   178: iconst_0
    //   179: istore #8
    //   181: iload #8
    //   183: aload_3
    //   184: arraylength
    //   185: if_icmpge -> 337
    //   188: aload_3
    //   189: iload #8
    //   191: baload
    //   192: istore #9
    //   194: iload #9
    //   196: bipush #48
    //   198: if_icmplt -> 215
    //   201: iload #9
    //   203: bipush #57
    //   205: if_icmple -> 313
    //   208: goto -> 215
    //   211: invokestatic a : (Ljava/lang/Throwable;)Ljava/lang/Throwable;
    //   214: athrow
    //   215: iload #9
    //   217: bipush #65
    //   219: if_icmplt -> 243
    //   222: goto -> 229
    //   225: invokestatic a : (Ljava/lang/Throwable;)Ljava/lang/Throwable;
    //   228: athrow
    //   229: iload #9
    //   231: bipush #90
    //   233: if_icmple -> 313
    //   236: goto -> 243
    //   239: invokestatic a : (Ljava/lang/Throwable;)Ljava/lang/Throwable;
    //   242: athrow
    //   243: iload #9
    //   245: bipush #97
    //   247: if_icmplt -> 271
    //   250: goto -> 257
    //   253: invokestatic a : (Ljava/lang/Throwable;)Ljava/lang/Throwable;
    //   256: athrow
    //   257: iload #9
    //   259: bipush #122
    //   261: if_icmple -> 313
    //   264: goto -> 271
    //   267: invokestatic a : (Ljava/lang/Throwable;)Ljava/lang/Throwable;
    //   270: athrow
    //   271: iload #9
    //   273: bipush #43
    //   275: if_icmpeq -> 313
    //   278: goto -> 285
    //   281: invokestatic a : (Ljava/lang/Throwable;)Ljava/lang/Throwable;
    //   284: athrow
    //   285: iload #9
    //   287: bipush #47
    //   289: if_icmpeq -> 313
    //   292: goto -> 299
    //   295: invokestatic a : (Ljava/lang/Throwable;)Ljava/lang/Throwable;
    //   298: athrow
    //   299: iload #9
    //   301: bipush #61
    //   303: if_icmpne -> 330
    //   306: goto -> 313
    //   309: invokestatic a : (Ljava/lang/Throwable;)Ljava/lang/Throwable;
    //   312: athrow
    //   313: aload #6
    //   315: iload #7
    //   317: iload #9
    //   319: bastore
    //   320: iinc #7, 1
    //   323: goto -> 330
    //   326: invokestatic a : (Ljava/lang/Throwable;)Ljava/lang/Throwable;
    //   329: athrow
    //   330: iinc #8, 1
    //   333: iload_2
    //   334: ifeq -> 181
    //   337: aload #6
    //   339: astore #4
    //   341: aload #4
    //   343: astore_3
    //   344: aload_3
    //   345: arraylength
    //   346: istore #5
    //   348: aload_3
    //   349: iload #5
    //   351: iconst_1
    //   352: isub
    //   353: baload
    //   354: bipush #61
    //   356: if_icmpne -> 366
    //   359: iinc #5, -1
    //   362: iload_2
    //   363: ifeq -> 348
    //   366: iload #5
    //   368: aload_3
    //   369: arraylength
    //   370: iconst_4
    //   371: idiv
    //   372: isub
    //   373: newarray byte
    //   375: astore #6
    //   377: iconst_0
    //   378: istore #7
    //   380: iload #7
    //   382: aload_3
    //   383: arraylength
    //   384: if_icmpge -> 646
    //   387: aload_3
    //   388: iload #7
    //   390: baload
    //   391: bipush #61
    //   393: if_icmpne -> 412
    //   396: aload_3
    //   397: iload #7
    //   399: iconst_0
    //   400: bastore
    //   401: iload_2
    //   402: ifeq -> 639
    //   405: goto -> 412
    //   408: invokestatic a : (Ljava/lang/Throwable;)Ljava/lang/Throwable;
    //   411: athrow
    //   412: aload_3
    //   413: iload #7
    //   415: baload
    //   416: bipush #47
    //   418: if_icmpne -> 445
    //   421: goto -> 428
    //   424: invokestatic a : (Ljava/lang/Throwable;)Ljava/lang/Throwable;
    //   427: athrow
    //   428: aload_3
    //   429: iload #7
    //   431: bipush #63
    //   433: bastore
    //   434: iload_2
    //   435: ifeq -> 639
    //   438: goto -> 445
    //   441: invokestatic a : (Ljava/lang/Throwable;)Ljava/lang/Throwable;
    //   444: athrow
    //   445: aload_3
    //   446: iload #7
    //   448: baload
    //   449: bipush #43
    //   451: if_icmpne -> 478
    //   454: goto -> 461
    //   457: invokestatic a : (Ljava/lang/Throwable;)Ljava/lang/Throwable;
    //   460: athrow
    //   461: aload_3
    //   462: iload #7
    //   464: bipush #62
    //   466: bastore
    //   467: iload_2
    //   468: ifeq -> 639
    //   471: goto -> 478
    //   474: invokestatic a : (Ljava/lang/Throwable;)Ljava/lang/Throwable;
    //   477: athrow
    //   478: aload_3
    //   479: iload #7
    //   481: baload
    //   482: bipush #48
    //   484: if_icmplt -> 533
    //   487: goto -> 494
    //   490: invokestatic a : (Ljava/lang/Throwable;)Ljava/lang/Throwable;
    //   493: athrow
    //   494: aload_3
    //   495: iload #7
    //   497: baload
    //   498: bipush #57
    //   500: if_icmpgt -> 533
    //   503: goto -> 510
    //   506: invokestatic a : (Ljava/lang/Throwable;)Ljava/lang/Throwable;
    //   509: athrow
    //   510: aload_3
    //   511: iload #7
    //   513: aload_3
    //   514: iload #7
    //   516: baload
    //   517: bipush #-4
    //   519: isub
    //   520: i2b
    //   521: bastore
    //   522: iload_2
    //   523: ifeq -> 639
    //   526: goto -> 533
    //   529: invokestatic a : (Ljava/lang/Throwable;)Ljava/lang/Throwable;
    //   532: athrow
    //   533: aload_3
    //   534: iload #7
    //   536: baload
    //   537: bipush #97
    //   539: if_icmplt -> 588
    //   542: goto -> 549
    //   545: invokestatic a : (Ljava/lang/Throwable;)Ljava/lang/Throwable;
    //   548: athrow
    //   549: aload_3
    //   550: iload #7
    //   552: baload
    //   553: bipush #122
    //   555: if_icmpgt -> 588
    //   558: goto -> 565
    //   561: invokestatic a : (Ljava/lang/Throwable;)Ljava/lang/Throwable;
    //   564: athrow
    //   565: aload_3
    //   566: iload #7
    //   568: aload_3
    //   569: iload #7
    //   571: baload
    //   572: bipush #71
    //   574: isub
    //   575: i2b
    //   576: bastore
    //   577: iload_2
    //   578: ifeq -> 639
    //   581: goto -> 588
    //   584: invokestatic a : (Ljava/lang/Throwable;)Ljava/lang/Throwable;
    //   587: athrow
    //   588: aload_3
    //   589: iload #7
    //   591: baload
    //   592: bipush #65
    //   594: if_icmplt -> 639
    //   597: goto -> 604
    //   600: invokestatic a : (Ljava/lang/Throwable;)Ljava/lang/Throwable;
    //   603: athrow
    //   604: aload_3
    //   605: iload #7
    //   607: baload
    //   608: bipush #90
    //   610: if_icmpgt -> 639
    //   613: goto -> 620
    //   616: invokestatic a : (Ljava/lang/Throwable;)Ljava/lang/Throwable;
    //   619: athrow
    //   620: aload_3
    //   621: iload #7
    //   623: aload_3
    //   624: iload #7
    //   626: baload
    //   627: bipush #65
    //   629: isub
    //   630: i2b
    //   631: bastore
    //   632: goto -> 639
    //   635: invokestatic a : (Ljava/lang/Throwable;)Ljava/lang/Throwable;
    //   638: athrow
    //   639: iinc #7, 1
    //   642: iload_2
    //   643: ifeq -> 380
    //   646: iconst_0
    //   647: istore #7
    //   649: iconst_0
    //   650: istore #8
    //   652: iload #8
    //   654: aload #6
    //   656: arraylength
    //   657: iconst_2
    //   658: isub
    //   659: if_icmpge -> 762
    //   662: aload #6
    //   664: iload #8
    //   666: aload_3
    //   667: iload #7
    //   669: baload
    //   670: iconst_2
    //   671: ishl
    //   672: sipush #255
    //   675: iand
    //   676: aload_3
    //   677: iload #7
    //   679: iconst_1
    //   680: iadd
    //   681: baload
    //   682: iconst_4
    //   683: iushr
    //   684: iconst_3
    //   685: iand
    //   686: ior
    //   687: i2b
    //   688: bastore
    //   689: aload #6
    //   691: iload #8
    //   693: iconst_1
    //   694: iadd
    //   695: aload_3
    //   696: iload #7
    //   698: iconst_1
    //   699: iadd
    //   700: baload
    //   701: iconst_4
    //   702: ishl
    //   703: sipush #255
    //   706: iand
    //   707: aload_3
    //   708: iload #7
    //   710: iconst_2
    //   711: iadd
    //   712: baload
    //   713: iconst_2
    //   714: iushr
    //   715: bipush #15
    //   717: iand
    //   718: ior
    //   719: i2b
    //   720: bastore
    //   721: aload #6
    //   723: iload #8
    //   725: iconst_2
    //   726: iadd
    //   727: aload_3
    //   728: iload #7
    //   730: iconst_2
    //   731: iadd
    //   732: baload
    //   733: bipush #6
    //   735: ishl
    //   736: sipush #255
    //   739: iand
    //   740: aload_3
    //   741: iload #7
    //   743: iconst_3
    //   744: iadd
    //   745: baload
    //   746: bipush #63
    //   748: iand
    //   749: ior
    //   750: i2b
    //   751: bastore
    //   752: iinc #7, 4
    //   755: iinc #8, 3
    //   758: iload_2
    //   759: ifeq -> 652
    //   762: iload #8
    //   764: aload #6
    //   766: arraylength
    //   767: if_icmpge -> 804
    //   770: aload #6
    //   772: iload #8
    //   774: aload_3
    //   775: iload #7
    //   777: baload
    //   778: iconst_2
    //   779: ishl
    //   780: sipush #255
    //   783: iand
    //   784: aload_3
    //   785: iload #7
    //   787: iconst_1
    //   788: iadd
    //   789: baload
    //   790: iconst_4
    //   791: iushr
    //   792: iconst_3
    //   793: iand
    //   794: ior
    //   795: i2b
    //   796: bastore
    //   797: goto -> 804
    //   800: invokestatic a : (Ljava/lang/Throwable;)Ljava/lang/Throwable;
    //   803: athrow
    //   804: iinc #8, 1
    //   807: iload #8
    //   809: aload #6
    //   811: arraylength
    //   812: if_icmpge -> 852
    //   815: aload #6
    //   817: iload #8
    //   819: aload_3
    //   820: iload #7
    //   822: iconst_1
    //   823: iadd
    //   824: baload
    //   825: iconst_4
    //   826: ishl
    //   827: sipush #255
    //   830: iand
    //   831: aload_3
    //   832: iload #7
    //   834: iconst_2
    //   835: iadd
    //   836: baload
    //   837: iconst_2
    //   838: iushr
    //   839: bipush #15
    //   841: iand
    //   842: ior
    //   843: i2b
    //   844: bastore
    //   845: goto -> 852
    //   848: invokestatic a : (Ljava/lang/Throwable;)Ljava/lang/Throwable;
    //   851: athrow
    //   852: aload #6
    //   854: astore #4
    //   856: sipush #21705
    //   859: new java/math/BigInteger
    //   862: dup
    //   863: aload #4
    //   865: invokespecial <init> : ([B)V
    //   868: invokevirtual abs : ()Ljava/math/BigInteger;
    //   871: putstatic burp/Zszz.ZG : Ljava/lang/Object;
    //   874: sipush #23171
    //   877: getstatic burp/Zt7w.ZF : Ljava/lang/Object;
    //   880: checkcast java/math/BigInteger
    //   883: getstatic burp/Zd8.Zs : Ljava/lang/Object;
    //   886: checkcast java/math/BigInteger
    //   889: invokevirtual subtract : (Ljava/math/BigInteger;)Ljava/math/BigInteger;
    //   892: putstatic burp/Ztvp.Zy : Ljava/lang/Object;
    //   895: getstatic burp/Zsqi.Zf : Ljava/lang/Object;
    //   898: checkcast java/math/BigInteger
    //   901: getstatic burp/Zrw7.ZV : Ljava/lang/Object;
    //   904: checkcast java/math/BigInteger
    //   907: invokevirtual add : (Ljava/math/BigInteger;)Ljava/math/BigInteger;
    //   910: putstatic burp/Zrcu.Zs : Ljava/lang/Object;
    //   913: invokestatic a : (II)Ljava/lang/String;
    //   916: iconst_1
    //   917: ldc burp/Zl50
    //   919: invokevirtual getClassLoader : ()Ljava/lang/ClassLoader;
    //   922: invokestatic forName : (Ljava/lang/String;ZLjava/lang/ClassLoader;)Ljava/lang/Class;
    //   925: invokevirtual getDeclaredFields : ()[Ljava/lang/reflect/Field;
    //   928: astore_3
    //   929: aload_3
    //   930: arraylength
    //   931: istore #4
    //   933: iconst_0
    //   934: istore #5
    //   936: iload #5
    //   938: iload #4
    //   940: if_icmpge -> 1077
    //   943: aload_3
    //   944: iload #5
    //   946: aaload
    //   947: astore #6
    //   949: aload #6
    //   951: invokevirtual getModifiers : ()I
    //   954: invokestatic isStatic : (I)Z
    //   957: ifne -> 967
    //   960: goto -> 1070
    //   963: invokestatic a : (Ljava/lang/Throwable;)Ljava/lang/Throwable;
    //   966: athrow
    //   967: aload #6
    //   969: invokevirtual getType : ()Ljava/lang/Class;
    //   972: astore #7
    //   974: aload #7
    //   976: ifnull -> 1057
    //   979: aload #7
    //   981: invokevirtual isPrimitive : ()Z
    //   984: ifne -> 1057
    //   987: goto -> 994
    //   990: invokestatic a : (Ljava/lang/Throwable;)Ljava/lang/Throwable;
    //   993: athrow
    //   994: aload #7
    //   996: invokevirtual getPackage : ()Ljava/lang/Package;
    //   999: ifnull -> 1057
    //   1002: goto -> 1009
    //   1005: invokestatic a : (Ljava/lang/Throwable;)Ljava/lang/Throwable;
    //   1008: athrow
    //   1009: aload #7
    //   1011: invokevirtual getPackage : ()Ljava/lang/Package;
    //   1014: invokevirtual getName : ()Ljava/lang/String;
    //   1017: ifnull -> 1057
    //   1020: goto -> 1027
    //   1023: invokestatic a : (Ljava/lang/Throwable;)Ljava/lang/Throwable;
    //   1026: athrow
    //   1027: aload #7
    //   1029: invokevirtual getPackage : ()Ljava/lang/Package;
    //   1032: invokevirtual getName : ()Ljava/lang/String;
    //   1035: sipush #21707
    //   1038: sipush #9234
    //   1041: invokestatic a : (II)Ljava/lang/String;
    //   1044: invokevirtual startsWith : (Ljava/lang/String;)Z
    //   1047: ifne -> 1057
    //   1050: goto -> 1057
    //   1053: invokestatic a : (Ljava/lang/Throwable;)Ljava/lang/Throwable;
    //   1056: athrow
    //   1057: aload #6
    //   1059: iconst_1
    //   1060: invokevirtual setAccessible : (Z)V
    //   1063: aload #6
    //   1065: aconst_null
    //   1066: invokevirtual get : (Ljava/lang/Object;)Ljava/lang/Object;
    //   1069: pop
    //   1070: iinc #5, 1
    //   1073: iload_2
    //   1074: ifeq -> 936
    //   1077: sipush #21704
    //   1080: sipush #6930
    //   1083: invokestatic a : (II)Ljava/lang/String;
    //   1086: invokestatic forName : (Ljava/lang/String;)Ljava/lang/Class;
    //   1089: invokevirtual getDeclaredMethods : ()[Ljava/lang/reflect/Method;
    //   1092: astore_3
    //   1093: aload_3
    //   1094: arraylength
    //   1095: istore #4
    //   1097: iconst_0
    //   1098: istore #5
    //   1100: iload #5
    //   1102: iload #4
    //   1104: if_icmpge -> 1236
    //   1107: aload_3
    //   1108: iload #5
    //   1110: aaload
    //   1111: astore #6
    //   1113: aload #6
    //   1115: invokevirtual getParameterTypes : ()[Ljava/lang/Class;
    //   1118: pop
    //   1119: aload #6
    //   1121: invokevirtual getModifiers : ()I
    //   1124: invokestatic isStatic : (I)Z
    //   1127: ifeq -> 1222
    //   1130: aload #6
    //   1132: invokevirtual getParameterTypes : ()[Ljava/lang/Class;
    //   1135: arraylength
    //   1136: iconst_2
    //   1137: if_icmpne -> 1222
    //   1140: goto -> 1147
    //   1143: invokestatic a : (Ljava/lang/Throwable;)Ljava/lang/Throwable;
    //   1146: athrow
    //   1147: aload #6
    //   1149: invokevirtual getReturnType : ()Ljava/lang/Class;
    //   1152: getstatic java/lang/Void.TYPE : Ljava/lang/Class;
    //   1155: invokevirtual equals : (Ljava/lang/Object;)Z
    //   1158: ifeq -> 1222
    //   1161: goto -> 1168
    //   1164: invokestatic a : (Ljava/lang/Throwable;)Ljava/lang/Throwable;
    //   1167: athrow
    //   1168: aload #6
    //   1170: iconst_1
    //   1171: invokevirtual setAccessible : (Z)V
    //   1174: aload #6
    //   1176: aconst_null
    //   1177: iconst_2
    //   1178: anewarray java/lang/Object
    //   1181: dup
    //   1182: iconst_0
    //   1183: aload_0
    //   1184: aastore
    //   1185: dup
    //   1186: iconst_1
    //   1187: aload_1
    //   1188: ifnonnull -> 1206
    //   1191: goto -> 1198
    //   1194: invokestatic a : (Ljava/lang/Throwable;)Ljava/lang/Throwable;
    //   1197: athrow
    //   1198: aload_1
    //   1199: goto -> 1213
    //   1202: invokestatic a : (Ljava/lang/Throwable;)Ljava/lang/Throwable;
    //   1205: athrow
    //   1206: aload_1
    //   1207: checkcast [B
    //   1210: invokevirtual clone : ()Ljava/lang/Object;
    //   1213: aastore
    //   1214: invokevirtual invoke : (Ljava/lang/Object;[Ljava/lang/Object;)Ljava/lang/Object;
    //   1217: pop
    //   1218: iload_2
    //   1219: ifeq -> 1236
    //   1222: iinc #5, 1
    //   1225: iload_2
    //   1226: ifeq -> 1100
    //   1229: goto -> 1236
    //   1232: invokestatic a : (Ljava/lang/Throwable;)Ljava/lang/Throwable;
    //   1235: athrow
    //   1236: getstatic burp/Zelz.Z_ : Ljava/lang/Object;
    //   1239: checkcast java/math/BigInteger
    //   1242: invokevirtual intValue : ()I
    //   1245: i2l
    //   1246: invokestatic currentTimeMillis : ()J
    //   1249: ladd
    //   1250: getstatic burp/Zm1l.Za : Ljava/lang/Object;
    //   1253: checkcast java/math/BigInteger
    //   1256: invokevirtual intValue : ()I
    //   1259: i2l
    //   1260: lcmp
    //   1261: ifge -> 1593
    //   1264: sipush #21711
    //   1267: sipush #22962
    //   1270: invokestatic a : (II)Ljava/lang/String;
    //   1273: iconst_1
    //   1274: ldc burp/Zr3q
    //   1276: invokevirtual getClassLoader : ()Ljava/lang/ClassLoader;
    //   1279: invokestatic forName : (Ljava/lang/String;ZLjava/lang/ClassLoader;)Ljava/lang/Class;
    //   1282: invokevirtual getDeclaredFields : ()[Ljava/lang/reflect/Field;
    //   1285: astore_3
    //   1286: aload_3
    //   1287: arraylength
    //   1288: istore #4
    //   1290: iconst_0
    //   1291: istore #5
    //   1293: iload #5
    //   1295: iload #4
    //   1297: if_icmpge -> 1434
    //   1300: aload_3
    //   1301: iload #5
    //   1303: aaload
    //   1304: astore #6
    //   1306: aload #6
    //   1308: invokevirtual getModifiers : ()I
    //   1311: invokestatic isStatic : (I)Z
    //   1314: ifne -> 1324
    //   1317: goto -> 1427
    //   1320: invokestatic a : (Ljava/lang/Throwable;)Ljava/lang/Throwable;
    //   1323: athrow
    //   1324: aload #6
    //   1326: invokevirtual getType : ()Ljava/lang/Class;
    //   1329: astore #7
    //   1331: aload #7
    //   1333: ifnull -> 1414
    //   1336: aload #7
    //   1338: invokevirtual isPrimitive : ()Z
    //   1341: ifne -> 1414
    //   1344: goto -> 1351
    //   1347: invokestatic a : (Ljava/lang/Throwable;)Ljava/lang/Throwable;
    //   1350: athrow
    //   1351: aload #7
    //   1353: invokevirtual getPackage : ()Ljava/lang/Package;
    //   1356: ifnull -> 1414
    //   1359: goto -> 1366
    //   1362: invokestatic a : (Ljava/lang/Throwable;)Ljava/lang/Throwable;
    //   1365: athrow
    //   1366: aload #7
    //   1368: invokevirtual getPackage : ()Ljava/lang/Package;
    //   1371: invokevirtual getName : ()Ljava/lang/String;
    //   1374: ifnull -> 1414
    //   1377: goto -> 1384
    //   1380: invokestatic a : (Ljava/lang/Throwable;)Ljava/lang/Throwable;
    //   1383: athrow
    //   1384: aload #7
    //   1386: invokevirtual getPackage : ()Ljava/lang/Package;
    //   1389: invokevirtual getName : ()Ljava/lang/String;
    //   1392: sipush #21710
    //   1395: sipush #8636
    //   1398: invokestatic a : (II)Ljava/lang/String;
    //   1401: invokevirtual startsWith : (Ljava/lang/String;)Z
    //   1404: ifne -> 1414
    //   1407: goto -> 1414
    //   1410: invokestatic a : (Ljava/lang/Throwable;)Ljava/lang/Throwable;
    //   1413: athrow
    //   1414: aload #6
    //   1416: iconst_1
    //   1417: invokevirtual setAccessible : (Z)V
    //   1420: aload #6
    //   1422: aconst_null
    //   1423: invokevirtual get : (Ljava/lang/Object;)Ljava/lang/Object;
    //   1426: pop
    //   1427: iinc #5, 1
    //   1430: iload_2
    //   1431: ifeq -> 1293
    //   1434: sipush #21709
    //   1437: sipush #-29916
    //   1440: invokestatic a : (II)Ljava/lang/String;
    //   1443: invokestatic forName : (Ljava/lang/String;)Ljava/lang/Class;
    //   1446: invokevirtual getDeclaredMethods : ()[Ljava/lang/reflect/Method;
    //   1449: astore_3
    //   1450: aload_3
    //   1451: arraylength
    //   1452: istore #4
    //   1454: iconst_0
    //   1455: istore #5
    //   1457: iload #5
    //   1459: iload #4
    //   1461: if_icmpge -> 1593
    //   1464: aload_3
    //   1465: iload #5
    //   1467: aaload
    //   1468: astore #6
    //   1470: aload #6
    //   1472: invokevirtual getParameterTypes : ()[Ljava/lang/Class;
    //   1475: pop
    //   1476: aload #6
    //   1478: invokevirtual getModifiers : ()I
    //   1481: invokestatic isStatic : (I)Z
    //   1484: ifeq -> 1579
    //   1487: aload #6
    //   1489: invokevirtual getParameterTypes : ()[Ljava/lang/Class;
    //   1492: arraylength
    //   1493: iconst_2
    //   1494: if_icmpne -> 1579
    //   1497: goto -> 1504
    //   1500: invokestatic a : (Ljava/lang/Throwable;)Ljava/lang/Throwable;
    //   1503: athrow
    //   1504: aload #6
    //   1506: invokevirtual getReturnType : ()Ljava/lang/Class;
    //   1509: getstatic java/lang/Void.TYPE : Ljava/lang/Class;
    //   1512: invokevirtual equals : (Ljava/lang/Object;)Z
    //   1515: ifeq -> 1579
    //   1518: goto -> 1525
    //   1521: invokestatic a : (Ljava/lang/Throwable;)Ljava/lang/Throwable;
    //   1524: athrow
    //   1525: aload #6
    //   1527: iconst_1
    //   1528: invokevirtual setAccessible : (Z)V
    //   1531: aload #6
    //   1533: aconst_null
    //   1534: iconst_2
    //   1535: anewarray java/lang/Object
    //   1538: dup
    //   1539: iconst_0
    //   1540: aload_0
    //   1541: aastore
    //   1542: dup
    //   1543: iconst_1
    //   1544: aload_1
    //   1545: ifnonnull -> 1563
    //   1548: goto -> 1555
    //   1551: invokestatic a : (Ljava/lang/Throwable;)Ljava/lang/Throwable;
    //   1554: athrow
    //   1555: aload_1
    //   1556: goto -> 1570
    //   1559: invokestatic a : (Ljava/lang/Throwable;)Ljava/lang/Throwable;
    //   1562: athrow
    //   1563: aload_1
    //   1564: checkcast [B
    //   1567: invokevirtual clone : ()Ljava/lang/Object;
    //   1570: aastore
    //   1571: invokevirtual invoke : (Ljava/lang/Object;[Ljava/lang/Object;)Ljava/lang/Object;
    //   1574: pop
    //   1575: iload_2
    //   1576: ifeq -> 1593
    //   1579: iinc #5, 1
    //   1582: iload_2
    //   1583: ifeq -> 1457
    //   1586: goto -> 1593
    //   1589: invokestatic a : (Ljava/lang/Throwable;)Ljava/lang/Throwable;
    //   1592: athrow
    //   1593: getstatic burp/Zs9x.ZY : Ljava/lang/String;
    //   1596: getstatic burp/Zs15.Zk : Ljava/lang/Object;
    //   1599: checkcast java/math/BigInteger
    //   1602: invokevirtual intValue : ()I
    //   1605: bipush #32
    //   1607: irem
    //   1608: invokestatic abs : (I)I
    //   1611: invokevirtual charAt : (I)C
    //   1614: getstatic burp/Zl4v.ZD : Ljava/lang/String;
    //   1617: getstatic burp/Zmsl.ZB : Ljava/lang/Object;
    //   1620: checkcast java/math/BigInteger
    //   1623: invokevirtual intValue : ()I
    //   1626: bipush #32
    //   1628: irem
    //   1629: invokestatic abs : (I)I
    //   1632: invokevirtual charAt : (I)C
    //   1635: if_icmple -> 1742
    //   1638: getstatic burp/Zsk4.ZH : Ljava/lang/String;
    //   1641: getstatic burp/Zlfi.ZV : Ljava/lang/Object;
    //   1644: checkcast java/math/BigInteger
    //   1647: invokevirtual intValue : ()I
    //   1650: bipush #32
    //   1652: irem
    //   1653: invokestatic abs : (I)I
    //   1656: invokevirtual charAt : (I)C
    //   1659: getstatic burp/Zm_w.ZA : Ljava/lang/String;
    //   1662: getstatic burp/Ze3z.Zf : Ljava/lang/Object;
    //   1665: checkcast java/math/BigInteger
    //   1668: invokevirtual intValue : ()I
    //   1671: bipush #32
    //   1673: irem
    //   1674: invokestatic abs : (I)I
    //   1677: invokevirtual charAt : (I)C
    //   1680: if_icmple -> 1742
    //   1683: goto -> 1690
    //   1686: invokestatic a : (Ljava/lang/Throwable;)Ljava/lang/Throwable;
    //   1689: athrow
    //   1690: getstatic burp/Ztzw.Zi : Ljava/lang/String;
    //   1693: getstatic burp/Zszz.ZG : Ljava/lang/Object;
    //   1696: checkcast java/math/BigInteger
    //   1699: invokevirtual intValue : ()I
    //   1702: bipush #32
    //   1704: irem
    //   1705: invokestatic abs : (I)I
    //   1708: invokevirtual charAt : (I)C
    //   1711: getstatic burp/Zm81.ZY : Ljava/lang/String;
    //   1714: getstatic burp/Zeqr.ZM : Ljava/lang/Object;
    //   1717: checkcast java/math/BigInteger
    //   1720: invokevirtual intValue : ()I
    //   1723: bipush #32
    //   1725: irem
    //   1726: invokestatic abs : (I)I
    //   1729: invokevirtual charAt : (I)C
    //   1732: if_icmple -> 1750
    //   1735: goto -> 1742
    //   1738: invokestatic a : (Ljava/lang/Throwable;)Ljava/lang/Throwable;
    //   1741: athrow
    //   1742: iconst_1
    //   1743: goto -> 1751
    //   1746: invokestatic a : (Ljava/lang/Throwable;)Ljava/lang/Throwable;
    //   1749: athrow
    //   1750: iconst_0
    //   1751: ireturn
    //   1752: astore_3
    //   1753: new java/lang/Exception
    //   1756: dup
    //   1757: aload_3
    //   1758: invokevirtual getMessage : ()Ljava/lang/String;
    //   1761: invokespecial <init> : (Ljava/lang/String;)V
    //   1764: athrow
    // Exception table:
    //   from	to	target	type
    //   4	1751	1752	java/lang/Throwable
    //   33	47	50	java/lang/Throwable
    //   40	61	64	java/lang/Throwable
    //   54	75	78	java/lang/Throwable
    //   68	89	92	java/lang/Throwable
    //   82	103	106	java/lang/Throwable
    //   96	117	120	java/lang/Throwable
    //   110	131	134	java/lang/Throwable
    //   124	145	148	java/lang/Throwable
    //   138	155	158	java/lang/Throwable
    //   194	208	211	java/lang/Throwable
    //   201	222	225	java/lang/Throwable
    //   215	236	239	java/lang/Throwable
    //   229	250	253	java/lang/Throwable
    //   243	264	267	java/lang/Throwable
    //   257	278	281	java/lang/Throwable
    //   271	292	295	java/lang/Throwable
    //   285	306	309	java/lang/Throwable
    //   299	323	326	java/lang/Throwable
    //   387	405	408	java/lang/Throwable
    //   396	421	424	java/lang/Throwable
    //   412	438	441	java/lang/Throwable
    //   428	454	457	java/lang/Throwable
    //   445	471	474	java/lang/Throwable
    //   461	487	490	java/lang/Throwable
    //   478	503	506	java/lang/Throwable
    //   494	526	529	java/lang/Throwable
    //   510	542	545	java/lang/Throwable
    //   533	558	561	java/lang/Throwable
    //   549	581	584	java/lang/Throwable
    //   565	597	600	java/lang/Throwable
    //   588	613	616	java/lang/Throwable
    //   604	632	635	java/lang/Throwable
    //   762	797	800	java/lang/Throwable
    //   804	845	848	java/lang/Throwable
    //   949	963	963	java/lang/Throwable
    //   974	987	990	java/lang/Throwable
    //   979	1002	1005	java/lang/Throwable
    //   994	1020	1023	java/lang/Throwable
    //   1009	1050	1053	java/lang/Throwable
    //   1113	1140	1143	java/lang/Throwable
    //   1130	1161	1164	java/lang/Throwable
    //   1147	1191	1194	java/lang/Throwable
    //   1168	1202	1202	java/lang/Throwable
    //   1213	1229	1232	java/lang/Throwable
    //   1306	1320	1320	java/lang/Throwable
    //   1331	1344	1347	java/lang/Throwable
    //   1336	1359	1362	java/lang/Throwable
    //   1351	1377	1380	java/lang/Throwable
    //   1366	1407	1410	java/lang/Throwable
    //   1470	1497	1500	java/lang/Throwable
    //   1487	1518	1521	java/lang/Throwable
    //   1504	1548	1551	java/lang/Throwable
    //   1525	1559	1559	java/lang/Throwable
    //   1570	1586	1589	java/lang/Throwable
    //   1593	1683	1686	java/lang/Throwable
    //   1638	1735	1738	java/lang/Throwable
    //   1690	1746	1746	java/lang/Throwable
  }
  
  static void Zz(Object[] paramArrayOfObject, Object paramObject) throws Throwable {}
  
  static void Zh(Object paramObject) {
    Zd0.Zi = a(21696, 2717);
    Zd0.ZT = new BigInteger(a(21706, 31197));
    boolean bool = Zt2e.ZK();
    try {
      try {
        if (Zxjm.ZG.charAt(Math.abs(((BigInteger)Zgr4.ZL).intValue() % 32)) <= Zm4k.ZW.charAt(Math.abs(((BigInteger)Zmsl.ZB).intValue() % 32))) {
          try {
            Zrt9.Zn(Class.forName(a(21699, -11162)));
            if (bool)
              Zszz.ZG(Class.forName(a(21708, 25452))); 
          } catch (Throwable throwable) {
            throw a(null);
          } 
          return;
        } 
      } catch (Throwable throwable) {
        throw a(null);
      } 
      Zszz.ZG(Class.forName(a(21708, 25452)));
    } catch (Throwable throwable) {}
  }
  
  static {
    // Byte code:
    //   0: bipush #11
    //   2: anewarray java/lang/String
    //   5: astore #5
    //   7: iconst_0
    //   8: istore_3
    //   9: ldc 'PÂœÂž\\fÃ¤ÂšÃ‚"Âˆ\\tÃŽ8m3yM+rÂœ|A)+Â“uÂ§Â³k@]Ã—Ã”ÃÃ€Ã¹\c:Ã’9ÂœÃŽ FPÂ¾Â´Ã½Â¼OÂ®Â”Ã…ÂŒ2Ã¹]LÂ;1YKF=V}^JÂ‰\\tP|Ã¯ÃÃ§ Ã¡WÂ¤\\tÂÂTrÂÃ·Â©yÃ¦69Â„\\tÃ“ÂŸÂŸÂ±Ã©Â(Â¡Â“\\tÂ–Â”7ÃÃ¼Â£Â‚{Ã–\\tzÂ ÂªVOsÃ¼>\\t Ã™ÃžÂˆ`Ã¬ÂŸYÂ Â¸FÂ¬KÃ‡Â› ZÂ¨Ã”ÂºmV$VÃÂ˜SÂ…R'
    //   11: dup
    //   12: astore_2
    //   13: invokevirtual length : ()I
    //   16: istore #4
    //   18: bipush #77
    //   20: istore_1
    //   21: iconst_m1
    //   22: istore_0
    //   23: bipush #10
    //   25: iinc #0, 1
    //   28: aload_2
    //   29: iload_0
    //   30: dup
    //   31: iload_1
    //   32: iadd
    //   33: invokevirtual substring : (II)Ljava/lang/String;
    //   36: iconst_m1
    //   37: goto -> 143
    //   40: aload #5
    //   42: swap
    //   43: iload_3
    //   44: iinc #3, 1
    //   47: swap
    //   48: aastore
    //   49: iload_0
    //   50: iload_1
    //   51: iadd
    //   52: dup
    //   53: istore_0
    //   54: iload #4
    //   56: if_icmpge -> 68
    //   59: aload_2
    //   60: iload_0
    //   61: invokevirtual charAt : (I)C
    //   64: istore_1
    //   65: goto -> 23
    //   68: ldc '\\fÂ‹Ã“Â„Ã—ÂžOfe Â»mÃ³RÃ†%Â®Ã»8Â¬ÃƒGÂ«\\r5Ã¢Â›ÃŽÂ‘Â—Ã¾Â’Â°~sOXÂ•Ã¼x'
    //   70: dup
    //   71: astore_2
    //   72: invokevirtual length : ()I
    //   75: istore #4
    //   77: bipush #9
    //   79: istore_1
    //   80: iconst_m1
    //   81: istore_0
    //   82: bipush #31
    //   84: iinc #0, 1
    //   87: aload_2
    //   88: iload_0
    //   89: dup
    //   90: iload_1
    //   91: iadd
    //   92: invokevirtual substring : (II)Ljava/lang/String;
    //   95: iconst_0
    //   96: goto -> 143
    //   99: aload #5
    //   101: swap
    //   102: iload_3
    //   103: iinc #3, 1
    //   106: swap
    //   107: aastore
    //   108: iload_0
    //   109: iload_1
    //   110: iadd
    //   111: dup
    //   112: istore_0
    //   113: iload #4
    //   115: if_icmpge -> 127
    //   118: aload_2
    //   119: iload_0
    //   120: invokevirtual charAt : (I)C
    //   123: istore_1
    //   124: goto -> 82
    //   127: aload #5
    //   129: putstatic burp/Zxyu.a : [Ljava/lang/String;
    //   132: bipush #11
    //   134: anewarray java/lang/String
    //   137: putstatic burp/Zxyu.b : [Ljava/lang/String;
    //   140: goto -> 300
    //   143: dup_x2
    //   144: pop
    //   145: invokevirtual toCharArray : ()[C
    //   148: dup_x1
    //   149: arraylength
    //   150: dup_x2
    //   151: pop
    //   152: iconst_0
    //   153: istore #6
    //   155: dup2_x1
    //   156: pop2
    //   157: dup_x2
    //   158: iconst_1
    //   159: if_icmpgt -> 260
    //   162: dup2
    //   163: swap
    //   164: iload #6
    //   166: dup2_x1
    //   167: caload
    //   168: swap
    //   169: iload #6
    //   171: bipush #7
    //   173: irem
    //   174: tableswitch default -> 242, 0 -> 212, 1 -> 217, 2 -> 222, 3 -> 227, 4 -> 232, 5 -> 237
    //   212: bipush #86
    //   214: goto -> 244
    //   217: bipush #116
    //   219: goto -> 244
    //   222: bipush #56
    //   224: goto -> 244
    //   227: bipush #44
    //   229: goto -> 244
    //   232: bipush #68
    //   234: goto -> 244
    //   237: bipush #83
    //   239: goto -> 244
    //   242: bipush #88
    //   244: ixor
    //   245: ixor
    //   246: i2c
    //   247: castore
    //   248: iinc #6, 1
    //   251: dup
    //   252: ifne -> 260
    //   255: dup2
    //   256: dup_x1
    //   257: goto -> 166
    //   260: dup2_x1
    //   261: pop2
    //   262: dup_x2
    //   263: iload #6
    //   265: if_icmpgt -> 162
    //   268: pop
    //   269: new java/lang/String
    //   272: dup_x1
    //   273: swap
    //   274: invokespecial <init> : ([C)V
    //   277: invokevirtual intern : ()Ljava/lang/String;
    //   280: swap
    //   281: pop
    //   282: swap
    //   283: tableswitch default -> 40, 0 -> 99
    //   300: new java/math/BigInteger
    //   303: dup
    //   304: iconst_1
    //   305: bipush #32
    //   307: newarray byte
    //   309: dup
    //   310: iconst_0
    //   311: bipush #59
    //   313: bastore
    //   314: dup
    //   315: iconst_1
    //   316: bipush #26
    //   318: bastore
    //   319: dup
    //   320: iconst_2
    //   321: bipush #-122
    //   323: bastore
    //   324: dup
    //   325: iconst_3
    //   326: bipush #-78
    //   328: bastore
    //   329: dup
    //   330: iconst_4
    //   331: bipush #-37
    //   333: bastore
    //   334: dup
    //   335: iconst_5
    //   336: bipush #14
    //   338: bastore
    //   339: dup
    //   340: bipush #6
    //   342: bipush #-56
    //   344: bastore
    //   345: dup
    //   346: bipush #7
    //   348: bipush #-36
    //   350: bastore
    //   351: dup
    //   352: bipush #8
    //   354: bipush #96
    //   356: bastore
    //   357: dup
    //   358: bipush #9
    //   360: bipush #65
    //   362: bastore
    //   363: dup
    //   364: bipush #10
    //   366: bipush #-111
    //   368: bastore
    //   369: dup
    //   370: bipush #11
    //   372: bipush #95
    //   374: bastore
    //   375: dup
    //   376: bipush #12
    //   378: bipush #39
    //   380: bastore
    //   381: dup
    //   382: bipush #13
    //   384: bipush #-23
    //   386: bastore
    //   387: dup
    //   388: bipush #14
    //   390: bipush #-109
    //   392: bastore
    //   393: dup
    //   394: bipush #15
    //   396: bipush #-82
    //   398: bastore
    //   399: dup
    //   400: bipush #16
    //   402: bipush #-78
    //   404: bastore
    //   405: dup
    //   406: bipush #17
    //   408: bipush #43
    //   410: bastore
    //   411: dup
    //   412: bipush #18
    //   414: bipush #69
    //   416: bastore
    //   417: dup
    //   418: bipush #19
    //   420: bipush #84
    //   422: bastore
    //   423: dup
    //   424: bipush #20
    //   426: bipush #125
    //   428: bastore
    //   429: dup
    //   430: bipush #21
    //   432: bipush #-28
    //   434: bastore
    //   435: dup
    //   436: bipush #22
    //   438: bipush #-49
    //   440: bastore
    //   441: dup
    //   442: bipush #23
    //   444: bipush #126
    //   446: bastore
    //   447: dup
    //   448: bipush #24
    //   450: bipush #71
    //   452: bastore
    //   453: dup
    //   454: bipush #25
    //   456: iconst_5
    //   457: bastore
    //   458: dup
    //   459: bipush #26
    //   461: bipush #69
    //   463: bastore
    //   464: dup
    //   465: bipush #27
    //   467: bipush #64
    //   469: bastore
    //   470: dup
    //   471: bipush #28
    //   473: bipush #61
    //   475: bastore
    //   476: dup
    //   477: bipush #29
    //   479: bipush #-22
    //   481: bastore
    //   482: dup
    //   483: bipush #30
    //   485: bipush #-61
    //   487: bastore
    //   488: dup
    //   489: bipush #31
    //   491: bipush #-92
    //   493: bastore
    //   494: invokespecial <init> : (I[B)V
    //   497: putstatic burp/Zxyu.Zp : Ljava/lang/Object;
    //   500: sipush #21698
    //   503: sipush #29600
    //   506: invokestatic a : (II)Ljava/lang/String;
    //   509: putstatic burp/Zxyu.ZM : Ljava/lang/String;
    //   512: return
  }
  
  private static Throwable a(Throwable paramThrowable) {
    return paramThrowable;
  }
  
  private static String a(int paramInt1, int paramInt2) {
    int i = (paramInt1 ^ 0x54CA) & 0xFFFF;
    if (b[i] == null) {
      char[] arrayOfChar = a[i].toCharArray();
      switch (arrayOfChar[0] & 0xFF) {
        case 0:
        
        case 1:
        
        case 2:
        
        case 3:
        
        case 4:
        
        case 5:
        
        case 6:
        
        case 7:
        
        case 8:
        
        case 9:
        
        case 10:
        
        case 11:
        
        case 12:
        
        case 13:
        
        case 14:
        
        case 15:
        
        case 16:
        
        case 17:
        
        case 18:
        
        case 19:
        
        case 20:
        
        case 21:
        
        case 22:
        
        case 23:
        
        case 24:
        
        case 25:
        
        case 26:
        
        case 27:
        
        case 28:
        
        case 29:
        
        case 30:
        
        case 31:
        
        case 32:
        
        case 33:
        
        case 34:
        
        case 35:
        
        case 36:
        
        case 37:
        
        case 38:
        
        case 39:
        
        case 40:
        
        case 41:
        
        case 42:
        
        case 43:
        
        case 44:
        
        case 45:
        
        case 46:
        
        case 47:
        
        case 48:
        
        case 49:
        
        case 50:
        
        case 51:
        
        case 52:
        
        case 53:
        
        case 54:
        
        case 55:
        
        case 56:
        
        case 57:
        
        case 58:
        
        case 59:
        
        case 60:
        
        case 61:
        
        case 62:
        
        case 63:
        
        case 64:
        
        case 65:
        
        case 66:
        
        case 67:
        
        case 68:
        
        case 69:
        
        case 70:
        
        case 71:
        
        case 72:
        
        case 73:
        
        case 74:
        
        case 75:
        
        case 76:
        
        case 77:
        
        case 78:
        
        case 79:
        
        case 80:
        
        case 81:
        
        case 82:
        
        case 83:
        
        case 84:
        
        case 85:
        
        case 86:
        
        case 87:
        
        case 88:
        
        case 89:
        
        case 90:
        
        case 91:
        
        case 92:
        
        case 93:
        
        case 94:
        
        case 95:
        
        case 96:
        
        case 97:
        
        case 98:
        
        case 99:
        
        case 100:
        
        case 101:
        
        case 102:
        
        case 103:
        
        case 104:
        
        case 105:
        
        case 106:
        
        case 107:
        
        case 108:
        
        case 109:
        
        case 110:
        
        case 111:
        
        case 112:
        
        case 113:
        
        case 114:
        
        case 115:
        
        case 116:
        
        case 117:
        
        case 118:
        
        case 119:
        
        case 120:
        
        case 121:
        
        case 122:
        
        case 123:
        
        case 124:
        
        case 125:
        
        case 126:
        
        case 127:
        
        case 128:
        
        case 129:
        
        case 130:
        
        case 131:
        
        case 132:
        
        case 133:
        
        case 134:
        
        case 135:
        
        case 136:
        
        case 137:
        
        case 138:
        
        case 139:
        
        case 140:
        
        case 141:
        
        case 142:
        
        case 143:
        
        case 144:
        
        case 145:
        
        case 146:
        
        case 147:
        
        case 148:
        
        case 149:
        
        case 150:
        
        case 151:
        
        case 152:
        
        case 153:
        
        case 154:
        
        case 155:
        
        case 156:
        
        case 157:
        
        case 158:
        
        case 159:
        
        case 160:
        
        case 161:
        
        case 162:
        
        case 163:
        
        case 164:
        
        case 165:
        
        case 166:
        
        case 167:
        
        case 168:
        
        case 169:
        
        case 170:
        
        case 171:
        
        case 172:
        
        case 173:
        
        case 174:
        
        case 175:
        
        case 176:
        
        case 177:
        
        case 178:
        
        case 179:
        
        case 180:
        
        case 181:
        
        case 182:
        
        case 183:
        
        case 184:
        
        case 185:
        
        case 186:
        
        case 187:
        
        case 188:
        
        case 189:
        
        case 190:
        
        case 191:
        
        case 192:
        
        case 193:
        
        case 194:
        
        case 195:
        
        case 196:
        
        case 197:
        
        case 198:
        
        case 199:
        
        case 200:
        
        case 201:
        
        case 202:
        
        case 203:
        
        case 204:
        
        case 205:
        
        case 206:
        
        case 207:
        
        case 208:
        
        case 209:
        
        case 210:
        
        case 211:
        
        case 212:
        
        case 213:
        
        case 214:
        
        case 215:
        
        case 216:
        
        case 217:
        
        case 218:
        
        case 219:
        
        case 220:
        
        case 221:
        
        case 222:
        
        case 223:
        
        case 224:
        
        case 225:
        
        case 226:
        
        case 227:
        
        case 228:
        
        case 229:
        
        case 230:
        
        case 231:
        
        case 232:
        
        case 233:
        
        case 234:
        
        case 235:
        
        case 236:
        
        case 237:
        
        case 238:
        
        case 239:
        
        case 240:
        
        case 241:
        
        case 242:
        
        case 243:
        
        case 244:
        
        case 245:
        
        case 246:
        
        case 247:
        
        case 248:
        
        case 249:
        
        case 250:
        
        case 251:
        
        case 252:
        
        case 253:
        
        case 254:
        
        default:
          break;
      } 
      byte b1 = 64;
      int j = (paramInt2 & 0xFF) - b1;
      if (j < 0)
        j += 256; 
      int k = ((paramInt2 & 0xFFFF) >>> 8) - b1;
      if (k < 0)
        k += 256; 
      for (byte b2 = 0; b2 < arrayOfChar.length; b2++) {
        int m = b2 % 2;
        if (m == 0) {
          arrayOfChar[b2] = (char)(arrayOfChar[b2] ^ j);
          j = ((j >>> 3 | j << 5) ^ arrayOfChar[b2]) & 0xFF;
        } else {
          arrayOfChar[b2] = (char)(arrayOfChar[b2] ^ k);
          k = ((k >>> 3 | k << 5) ^ arrayOfChar[b2]) & 0xFF;
        } 
      } 
      b[i] = (new String(arrayOfChar)).intern();
    } 
    return b[i];
  }
}


/* Location:              C:\Program Files\BurpSuitePro\burpsuite_pro.jar!\burp\Zxyu.class
 * Java compiler version: 21 (65.0)
 * JD-Core Version:       1.1.3
 */