package burp;

import java.math.BigInteger;

class Zxzd extends ClassLoader {
  static Object ZD;
  
  static String ZM;
  
  private static final String[] a;
  
  private static final String[] b;
  
  static boolean ZX(Object[] paramArrayOfObject, Object paramObject) throws Throwable {
    // Byte code:
    //   0: invokestatic ZK : ()Z
    //   3: istore_2
    //   4: getstatic burp/Zb8v.ZA : Ljava/lang/Object;
    //   7: checkcast java/math/BigInteger
    //   10: getstatic burp/Zx4l.Zt : Ljava/lang/Object;
    //   13: checkcast java/math/BigInteger
    //   16: invokevirtual add : (Ljava/math/BigInteger;)Ljava/math/BigInteger;
    //   19: putstatic burp/Zg0j.ZV : Ljava/lang/Object;
    //   22: getstatic burp/Zlos.Zk : Ljava/lang/Object;
    //   25: checkcast java/math/BigInteger
    //   28: invokevirtual toByteArray : ()[B
    //   31: astore_3
    //   32: aload_3
    //   33: arraylength
    //   34: bipush #8
    //   36: iadd
    //   37: bipush #6
    //   39: ishr
    //   40: iconst_1
    //   41: iadd
    //   42: bipush #16
    //   44: imul
    //   45: newarray int
    //   47: astore #5
    //   49: iconst_0
    //   50: istore #6
    //   52: iload #6
    //   54: aload_3
    //   55: arraylength
    //   56: if_icmpge -> 99
    //   59: aload_3
    //   60: iload #6
    //   62: baload
    //   63: sipush #255
    //   66: iand
    //   67: istore #7
    //   69: aload #5
    //   71: iload #6
    //   73: iconst_2
    //   74: ishr
    //   75: dup2
    //   76: iaload
    //   77: iload #7
    //   79: bipush #24
    //   81: iload #6
    //   83: iconst_4
    //   84: irem
    //   85: bipush #8
    //   87: imul
    //   88: isub
    //   89: ishl
    //   90: ior
    //   91: iastore
    //   92: iinc #6, 1
    //   95: iload_2
    //   96: ifeq -> 52
    //   99: aload #5
    //   101: iload #6
    //   103: iconst_2
    //   104: ishr
    //   105: dup2
    //   106: iaload
    //   107: sipush #128
    //   110: bipush #24
    //   112: iload #6
    //   114: iconst_4
    //   115: irem
    //   116: bipush #8
    //   118: imul
    //   119: isub
    //   120: ishl
    //   121: ior
    //   122: iastore
    //   123: aload #5
    //   125: aload #5
    //   127: arraylength
    //   128: iconst_1
    //   129: isub
    //   130: aload_3
    //   131: arraylength
    //   132: bipush #8
    //   134: imul
    //   135: iastore
    //   136: bipush #80
    //   138: newarray int
    //   140: astore #7
    //   142: ldc 1732584193
    //   144: istore #8
    //   146: ldc -271733879
    //   148: istore #9
    //   150: ldc -1732584194
    //   152: istore #10
    //   154: ldc 271733878
    //   156: istore #11
    //   158: ldc -1009589776
    //   160: istore #12
    //   162: iconst_0
    //   163: istore #6
    //   165: iload #6
    //   167: aload #5
    //   169: arraylength
    //   170: if_icmpge -> 492
    //   173: iload #8
    //   175: istore #13
    //   177: iload #9
    //   179: istore #14
    //   181: iload #10
    //   183: istore #15
    //   185: iload #11
    //   187: istore #16
    //   189: iload #12
    //   191: istore #17
    //   193: iconst_0
    //   194: istore #18
    //   196: iload #18
    //   198: bipush #80
    //   200: if_icmpge -> 450
    //   203: iload #18
    //   205: bipush #16
    //   207: if_icmpge -> 234
    //   210: aload #7
    //   212: iload #18
    //   214: aload #5
    //   216: iload #6
    //   218: iload #18
    //   220: iadd
    //   221: iaload
    //   222: iastore
    //   223: iload_2
    //   224: ifeq -> 289
    //   227: goto -> 234
    //   230: invokestatic a : (Ljava/lang/Throwable;)Ljava/lang/Throwable;
    //   233: athrow
    //   234: aload #7
    //   236: iload #18
    //   238: iconst_3
    //   239: isub
    //   240: iaload
    //   241: aload #7
    //   243: iload #18
    //   245: bipush #8
    //   247: isub
    //   248: iaload
    //   249: ixor
    //   250: aload #7
    //   252: iload #18
    //   254: bipush #14
    //   256: isub
    //   257: iaload
    //   258: ixor
    //   259: aload #7
    //   261: iload #18
    //   263: bipush #16
    //   265: isub
    //   266: iaload
    //   267: ixor
    //   268: istore #19
    //   270: iload #19
    //   272: iconst_1
    //   273: ishl
    //   274: iload #19
    //   276: bipush #31
    //   278: iushr
    //   279: ior
    //   280: istore #20
    //   282: aload #7
    //   284: iload #18
    //   286: iload #20
    //   288: iastore
    //   289: iload #8
    //   291: iconst_5
    //   292: ishl
    //   293: iload #8
    //   295: bipush #27
    //   297: iushr
    //   298: ior
    //   299: istore #19
    //   301: iload #19
    //   303: iload #12
    //   305: iadd
    //   306: aload #7
    //   308: iload #18
    //   310: iaload
    //   311: iadd
    //   312: iload #18
    //   314: bipush #20
    //   316: if_icmpge -> 342
    //   319: ldc 1518500249
    //   321: iload #9
    //   323: iload #10
    //   325: iand
    //   326: iload #9
    //   328: iconst_m1
    //   329: ixor
    //   330: iload #11
    //   332: iand
    //   333: ior
    //   334: iadd
    //   335: goto -> 412
    //   338: invokestatic a : (Ljava/lang/Throwable;)Ljava/lang/Throwable;
    //   341: athrow
    //   342: iload #18
    //   344: bipush #40
    //   346: if_icmpge -> 367
    //   349: ldc 1859775393
    //   351: iload #9
    //   353: iload #10
    //   355: ixor
    //   356: iload #11
    //   358: ixor
    //   359: iadd
    //   360: goto -> 412
    //   363: invokestatic a : (Ljava/lang/Throwable;)Ljava/lang/Throwable;
    //   366: athrow
    //   367: iload #18
    //   369: bipush #60
    //   371: if_icmpge -> 401
    //   374: ldc -1894007588
    //   376: iload #9
    //   378: iload #10
    //   380: iand
    //   381: iload #9
    //   383: iload #11
    //   385: iand
    //   386: ior
    //   387: iload #10
    //   389: iload #11
    //   391: iand
    //   392: ior
    //   393: iadd
    //   394: goto -> 412
    //   397: invokestatic a : (Ljava/lang/Throwable;)Ljava/lang/Throwable;
    //   400: athrow
    //   401: ldc -899497514
    //   403: iload #9
    //   405: iload #10
    //   407: ixor
    //   408: iload #11
    //   410: ixor
    //   411: iadd
    //   412: iadd
    //   413: istore #20
    //   415: iload #11
    //   417: istore #12
    //   419: iload #10
    //   421: istore #11
    //   423: iload #9
    //   425: bipush #30
    //   427: ishl
    //   428: iload #9
    //   430: iconst_2
    //   431: iushr
    //   432: ior
    //   433: istore #10
    //   435: iload #8
    //   437: istore #9
    //   439: iload #20
    //   441: istore #8
    //   443: iinc #18, 1
    //   446: iload_2
    //   447: ifeq -> 196
    //   450: iload #8
    //   452: iload #13
    //   454: iadd
    //   455: istore #8
    //   457: iload #9
    //   459: iload #14
    //   461: iadd
    //   462: istore #9
    //   464: iload #10
    //   466: iload #15
    //   468: iadd
    //   469: istore #10
    //   471: iload #11
    //   473: iload #16
    //   475: iadd
    //   476: istore #11
    //   478: iload #12
    //   480: iload #17
    //   482: iadd
    //   483: istore #12
    //   485: iinc #6, 16
    //   488: iload_2
    //   489: ifeq -> 165
    //   492: iconst_5
    //   493: newarray int
    //   495: dup
    //   496: iconst_0
    //   497: iload #8
    //   499: iastore
    //   500: dup
    //   501: iconst_1
    //   502: iload #9
    //   504: iastore
    //   505: dup
    //   506: iconst_2
    //   507: iload #10
    //   509: iastore
    //   510: dup
    //   511: iconst_3
    //   512: iload #11
    //   514: iastore
    //   515: dup
    //   516: iconst_4
    //   517: iload #12
    //   519: iastore
    //   520: astore #13
    //   522: bipush #20
    //   524: newarray byte
    //   526: astore #14
    //   528: iconst_0
    //   529: istore #15
    //   531: iload #15
    //   533: bipush #20
    //   535: if_icmpge -> 576
    //   538: aload #13
    //   540: iload #15
    //   542: iconst_4
    //   543: idiv
    //   544: iaload
    //   545: istore #16
    //   547: iconst_3
    //   548: iload #15
    //   550: iconst_4
    //   551: irem
    //   552: isub
    //   553: bipush #8
    //   555: imul
    //   556: istore #17
    //   558: aload #14
    //   560: iload #15
    //   562: iload #16
    //   564: iload #17
    //   566: iushr
    //   567: i2b
    //   568: bastore
    //   569: iinc #15, 1
    //   572: iload_2
    //   573: ifeq -> 531
    //   576: aload #14
    //   578: astore #4
    //   580: new java/math/BigInteger
    //   583: dup
    //   584: aload #4
    //   586: invokespecial <init> : ([B)V
    //   589: invokevirtual abs : ()Ljava/math/BigInteger;
    //   592: putstatic burp/Zsgl.Zn : Ljava/lang/Object;
    //   595: new java/io/ByteArrayOutputStream
    //   598: dup
    //   599: invokespecial <init> : ()V
    //   602: astore_3
    //   603: getstatic burp/Zr3q.ZM : Ljava/lang/String;
    //   606: astore #4
    //   608: iconst_0
    //   609: istore #5
    //   611: iload #5
    //   613: aload #4
    //   615: invokevirtual length : ()I
    //   618: if_icmpge -> 648
    //   621: aload_3
    //   622: aload #4
    //   624: iload #5
    //   626: iload #5
    //   628: iconst_2
    //   629: iadd
    //   630: invokevirtual substring : (II)Ljava/lang/String;
    //   633: bipush #16
    //   635: invokestatic parseInt : (Ljava/lang/String;I)I
    //   638: invokevirtual write : (I)V
    //   641: iinc #5, 2
    //   644: iload_2
    //   645: ifeq -> 611
    //   648: aload_3
    //   649: invokevirtual toByteArray : ()[B
    //   652: astore #5
    //   654: getstatic burp/Zedz.Za : Ljava/lang/Object;
    //   657: checkcast java/math/BigInteger
    //   660: invokevirtual toByteArray : ()[B
    //   663: astore #6
    //   665: sipush #256
    //   668: newarray byte
    //   670: astore #8
    //   672: sipush #256
    //   675: newarray int
    //   677: astore #9
    //   679: sipush #256
    //   682: newarray int
    //   684: astore #10
    //   686: sipush #256
    //   689: newarray int
    //   691: astore #11
    //   693: sipush #256
    //   696: newarray int
    //   698: astore #12
    //   700: bipush #10
    //   702: newarray int
    //   704: astore #13
    //   706: sipush #283
    //   709: istore #14
    //   711: iconst_0
    //   712: istore #16
    //   714: iload #16
    //   716: sipush #256
    //   719: if_icmpge -> 953
    //   722: sipush #-17877
    //   725: sipush #31211
    //   728: invokestatic a : (II)Ljava/lang/String;
    //   731: iload #16
    //   733: iconst_1
    //   734: iushr
    //   735: invokevirtual charAt : (I)C
    //   738: istore #25
    //   740: iload #16
    //   742: iconst_1
    //   743: iand
    //   744: ifne -> 759
    //   747: iload #25
    //   749: bipush #8
    //   751: iushr
    //   752: goto -> 761
    //   755: invokestatic a : (Ljava/lang/Throwable;)Ljava/lang/Throwable;
    //   758: athrow
    //   759: iload #25
    //   761: i2b
    //   762: sipush #255
    //   765: iand
    //   766: istore #15
    //   768: iload #16
    //   770: iconst_1
    //   771: ishl
    //   772: istore #17
    //   774: iload #17
    //   776: sipush #256
    //   779: if_icmplt -> 789
    //   782: iload #17
    //   784: iload #14
    //   786: ixor
    //   787: istore #17
    //   789: iload #17
    //   791: iconst_1
    //   792: ishl
    //   793: istore #18
    //   795: iload #18
    //   797: sipush #256
    //   800: if_icmplt -> 810
    //   803: iload #18
    //   805: iload #14
    //   807: ixor
    //   808: istore #18
    //   810: iload #18
    //   812: iconst_1
    //   813: ishl
    //   814: istore #19
    //   816: iload #19
    //   818: sipush #256
    //   821: if_icmplt -> 831
    //   824: iload #19
    //   826: iload #14
    //   828: ixor
    //   829: istore #19
    //   831: iload #19
    //   833: iload #16
    //   835: ixor
    //   836: istore #20
    //   838: iload #20
    //   840: iload #17
    //   842: ixor
    //   843: istore #21
    //   845: iload #20
    //   847: iload #18
    //   849: ixor
    //   850: istore #22
    //   852: iload #19
    //   854: iload #18
    //   856: ixor
    //   857: iload #17
    //   859: ixor
    //   860: istore #23
    //   862: aload #8
    //   864: iload #16
    //   866: iload #15
    //   868: i2b
    //   869: bastore
    //   870: aload #9
    //   872: iload #15
    //   874: iload #23
    //   876: bipush #24
    //   878: ishl
    //   879: iload #20
    //   881: bipush #16
    //   883: ishl
    //   884: ior
    //   885: iload #22
    //   887: bipush #8
    //   889: ishl
    //   890: ior
    //   891: iload #21
    //   893: ior
    //   894: dup
    //   895: istore #24
    //   897: iastore
    //   898: aload #10
    //   900: iload #15
    //   902: iload #24
    //   904: bipush #8
    //   906: iushr
    //   907: iload #24
    //   909: bipush #24
    //   911: ishl
    //   912: ior
    //   913: iastore
    //   914: aload #11
    //   916: iload #15
    //   918: iload #24
    //   920: bipush #16
    //   922: iushr
    //   923: iload #24
    //   925: bipush #16
    //   927: ishl
    //   928: ior
    //   929: iastore
    //   930: aload #12
    //   932: iload #15
    //   934: iload #24
    //   936: bipush #24
    //   938: iushr
    //   939: iload #24
    //   941: bipush #8
    //   943: ishl
    //   944: ior
    //   945: iastore
    //   946: iinc #16, 1
    //   949: iload_2
    //   950: ifeq -> 714
    //   953: iconst_1
    //   954: istore #25
    //   956: aload #13
    //   958: iconst_0
    //   959: iload #25
    //   961: bipush #24
    //   963: ishl
    //   964: iastore
    //   965: iconst_1
    //   966: istore #26
    //   968: iload #26
    //   970: bipush #10
    //   972: if_icmpge -> 1013
    //   975: iload #25
    //   977: iconst_1
    //   978: ishl
    //   979: istore #25
    //   981: iload #25
    //   983: sipush #256
    //   986: if_icmplt -> 996
    //   989: iload #25
    //   991: iload #14
    //   993: ixor
    //   994: istore #25
    //   996: aload #13
    //   998: iload #26
    //   1000: iload #25
    //   1002: bipush #24
    //   1004: ishl
    //   1005: iastore
    //   1006: iinc #26, 1
    //   1009: iload_2
    //   1010: ifeq -> 968
    //   1013: iconst_4
    //   1014: istore #26
    //   1016: iload #26
    //   1018: bipush #6
    //   1020: iadd
    //   1021: istore #27
    //   1023: iconst_4
    //   1024: iload #27
    //   1026: iconst_1
    //   1027: iadd
    //   1028: imul
    //   1029: istore #28
    //   1031: iload #28
    //   1033: newarray int
    //   1035: astore #29
    //   1037: iload #28
    //   1039: newarray int
    //   1041: astore #30
    //   1043: iconst_0
    //   1044: istore #25
    //   1046: iconst_0
    //   1047: istore #32
    //   1049: iconst_0
    //   1050: istore #33
    //   1052: iload #32
    //   1054: iload #26
    //   1056: if_icmpge -> 1124
    //   1059: aload #29
    //   1061: iload #32
    //   1063: aload #5
    //   1065: iload #33
    //   1067: baload
    //   1068: bipush #24
    //   1070: ishl
    //   1071: aload #5
    //   1073: iload #33
    //   1075: iconst_1
    //   1076: iadd
    //   1077: baload
    //   1078: sipush #255
    //   1081: iand
    //   1082: bipush #16
    //   1084: ishl
    //   1085: ior
    //   1086: aload #5
    //   1088: iload #33
    //   1090: iconst_2
    //   1091: iadd
    //   1092: baload
    //   1093: sipush #255
    //   1096: iand
    //   1097: bipush #8
    //   1099: ishl
    //   1100: ior
    //   1101: aload #5
    //   1103: iload #33
    //   1105: iconst_3
    //   1106: iadd
    //   1107: baload
    //   1108: sipush #255
    //   1111: iand
    //   1112: ior
    //   1113: iastore
    //   1114: iinc #32, 1
    //   1117: iinc #33, 4
    //   1120: iload_2
    //   1121: ifeq -> 1052
    //   1124: iload #26
    //   1126: istore #32
    //   1128: iconst_0
    //   1129: istore #33
    //   1131: iload #32
    //   1133: iload #28
    //   1135: if_icmpge -> 1262
    //   1138: aload #29
    //   1140: iload #32
    //   1142: iconst_1
    //   1143: isub
    //   1144: iaload
    //   1145: istore #31
    //   1147: iload #33
    //   1149: ifne -> 1236
    //   1152: iload #26
    //   1154: istore #33
    //   1156: aload #8
    //   1158: iload #31
    //   1160: bipush #16
    //   1162: iushr
    //   1163: sipush #255
    //   1166: iand
    //   1167: baload
    //   1168: bipush #24
    //   1170: ishl
    //   1171: aload #8
    //   1173: iload #31
    //   1175: bipush #8
    //   1177: iushr
    //   1178: sipush #255
    //   1181: iand
    //   1182: baload
    //   1183: sipush #255
    //   1186: iand
    //   1187: bipush #16
    //   1189: ishl
    //   1190: ior
    //   1191: aload #8
    //   1193: iload #31
    //   1195: sipush #255
    //   1198: iand
    //   1199: baload
    //   1200: sipush #255
    //   1203: iand
    //   1204: bipush #8
    //   1206: ishl
    //   1207: ior
    //   1208: aload #8
    //   1210: iload #31
    //   1212: bipush #24
    //   1214: iushr
    //   1215: baload
    //   1216: sipush #255
    //   1219: iand
    //   1220: ior
    //   1221: istore #31
    //   1223: iload #31
    //   1225: aload #13
    //   1227: iload #25
    //   1229: iinc #25, 1
    //   1232: iaload
    //   1233: ixor
    //   1234: istore #31
    //   1236: aload #29
    //   1238: iload #32
    //   1240: aload #29
    //   1242: iload #32
    //   1244: iload #26
    //   1246: isub
    //   1247: iaload
    //   1248: iload #31
    //   1250: ixor
    //   1251: iastore
    //   1252: iinc #32, 1
    //   1255: iinc #33, -1
    //   1258: iload_2
    //   1259: ifeq -> 1131
    //   1262: iconst_0
    //   1263: istore #32
    //   1265: iconst_4
    //   1266: iload #27
    //   1268: imul
    //   1269: istore #33
    //   1271: aload #30
    //   1273: iload #32
    //   1275: aload #29
    //   1277: iload #33
    //   1279: iaload
    //   1280: iastore
    //   1281: aload #30
    //   1283: iload #32
    //   1285: iconst_1
    //   1286: iadd
    //   1287: aload #29
    //   1289: iload #33
    //   1291: iconst_1
    //   1292: iadd
    //   1293: iaload
    //   1294: iastore
    //   1295: aload #30
    //   1297: iload #32
    //   1299: iconst_2
    //   1300: iadd
    //   1301: aload #29
    //   1303: iload #33
    //   1305: iconst_2
    //   1306: iadd
    //   1307: iaload
    //   1308: iastore
    //   1309: aload #30
    //   1311: iload #32
    //   1313: iconst_3
    //   1314: iadd
    //   1315: aload #29
    //   1317: iload #33
    //   1319: iconst_3
    //   1320: iadd
    //   1321: iaload
    //   1322: iastore
    //   1323: iinc #32, 4
    //   1326: iinc #33, -4
    //   1329: iconst_1
    //   1330: istore #35
    //   1332: iload #35
    //   1334: iload #27
    //   1336: if_icmpge -> 1700
    //   1339: aload #29
    //   1341: iload #33
    //   1343: iaload
    //   1344: istore #34
    //   1346: aload #30
    //   1348: iload #32
    //   1350: aload #9
    //   1352: aload #8
    //   1354: iload #34
    //   1356: bipush #24
    //   1358: iushr
    //   1359: baload
    //   1360: sipush #255
    //   1363: iand
    //   1364: iaload
    //   1365: aload #10
    //   1367: aload #8
    //   1369: iload #34
    //   1371: bipush #16
    //   1373: iushr
    //   1374: sipush #255
    //   1377: iand
    //   1378: baload
    //   1379: sipush #255
    //   1382: iand
    //   1383: iaload
    //   1384: ixor
    //   1385: aload #11
    //   1387: aload #8
    //   1389: iload #34
    //   1391: bipush #8
    //   1393: iushr
    //   1394: sipush #255
    //   1397: iand
    //   1398: baload
    //   1399: sipush #255
    //   1402: iand
    //   1403: iaload
    //   1404: ixor
    //   1405: aload #12
    //   1407: aload #8
    //   1409: iload #34
    //   1411: sipush #255
    //   1414: iand
    //   1415: baload
    //   1416: sipush #255
    //   1419: iand
    //   1420: iaload
    //   1421: ixor
    //   1422: iastore
    //   1423: aload #29
    //   1425: iload #33
    //   1427: iconst_1
    //   1428: iadd
    //   1429: iaload
    //   1430: istore #34
    //   1432: aload #30
    //   1434: iload #32
    //   1436: iconst_1
    //   1437: iadd
    //   1438: aload #9
    //   1440: aload #8
    //   1442: iload #34
    //   1444: bipush #24
    //   1446: iushr
    //   1447: baload
    //   1448: sipush #255
    //   1451: iand
    //   1452: iaload
    //   1453: aload #10
    //   1455: aload #8
    //   1457: iload #34
    //   1459: bipush #16
    //   1461: iushr
    //   1462: sipush #255
    //   1465: iand
    //   1466: baload
    //   1467: sipush #255
    //   1470: iand
    //   1471: iaload
    //   1472: ixor
    //   1473: aload #11
    //   1475: aload #8
    //   1477: iload #34
    //   1479: bipush #8
    //   1481: iushr
    //   1482: sipush #255
    //   1485: iand
    //   1486: baload
    //   1487: sipush #255
    //   1490: iand
    //   1491: iaload
    //   1492: ixor
    //   1493: aload #12
    //   1495: aload #8
    //   1497: iload #34
    //   1499: sipush #255
    //   1502: iand
    //   1503: baload
    //   1504: sipush #255
    //   1507: iand
    //   1508: iaload
    //   1509: ixor
    //   1510: iastore
    //   1511: aload #29
    //   1513: iload #33
    //   1515: iconst_2
    //   1516: iadd
    //   1517: iaload
    //   1518: istore #34
    //   1520: aload #30
    //   1522: iload #32
    //   1524: iconst_2
    //   1525: iadd
    //   1526: aload #9
    //   1528: aload #8
    //   1530: iload #34
    //   1532: bipush #24
    //   1534: iushr
    //   1535: baload
    //   1536: sipush #255
    //   1539: iand
    //   1540: iaload
    //   1541: aload #10
    //   1543: aload #8
    //   1545: iload #34
    //   1547: bipush #16
    //   1549: iushr
    //   1550: sipush #255
    //   1553: iand
    //   1554: baload
    //   1555: sipush #255
    //   1558: iand
    //   1559: iaload
    //   1560: ixor
    //   1561: aload #11
    //   1563: aload #8
    //   1565: iload #34
    //   1567: bipush #8
    //   1569: iushr
    //   1570: sipush #255
    //   1573: iand
    //   1574: baload
    //   1575: sipush #255
    //   1578: iand
    //   1579: iaload
    //   1580: ixor
    //   1581: aload #12
    //   1583: aload #8
    //   1585: iload #34
    //   1587: sipush #255
    //   1590: iand
    //   1591: baload
    //   1592: sipush #255
    //   1595: iand
    //   1596: iaload
    //   1597: ixor
    //   1598: iastore
    //   1599: aload #29
    //   1601: iload #33
    //   1603: iconst_3
    //   1604: iadd
    //   1605: iaload
    //   1606: istore #34
    //   1608: aload #30
    //   1610: iload #32
    //   1612: iconst_3
    //   1613: iadd
    //   1614: aload #9
    //   1616: aload #8
    //   1618: iload #34
    //   1620: bipush #24
    //   1622: iushr
    //   1623: baload
    //   1624: sipush #255
    //   1627: iand
    //   1628: iaload
    //   1629: aload #10
    //   1631: aload #8
    //   1633: iload #34
    //   1635: bipush #16
    //   1637: iushr
    //   1638: sipush #255
    //   1641: iand
    //   1642: baload
    //   1643: sipush #255
    //   1646: iand
    //   1647: iaload
    //   1648: ixor
    //   1649: aload #11
    //   1651: aload #8
    //   1653: iload #34
    //   1655: bipush #8
    //   1657: iushr
    //   1658: sipush #255
    //   1661: iand
    //   1662: baload
    //   1663: sipush #255
    //   1666: iand
    //   1667: iaload
    //   1668: ixor
    //   1669: aload #12
    //   1671: aload #8
    //   1673: iload #34
    //   1675: sipush #255
    //   1678: iand
    //   1679: baload
    //   1680: sipush #255
    //   1683: iand
    //   1684: iaload
    //   1685: ixor
    //   1686: iastore
    //   1687: iinc #32, 4
    //   1690: iinc #33, -4
    //   1693: iinc #35, 1
    //   1696: iload_2
    //   1697: ifeq -> 1332
    //   1700: aload #30
    //   1702: iload #32
    //   1704: aload #29
    //   1706: iload #33
    //   1708: iaload
    //   1709: iastore
    //   1710: aload #30
    //   1712: iload #32
    //   1714: iconst_1
    //   1715: iadd
    //   1716: aload #29
    //   1718: iload #33
    //   1720: iconst_1
    //   1721: iadd
    //   1722: iaload
    //   1723: iastore
    //   1724: aload #30
    //   1726: iload #32
    //   1728: iconst_2
    //   1729: iadd
    //   1730: aload #29
    //   1732: iload #33
    //   1734: iconst_2
    //   1735: iadd
    //   1736: iaload
    //   1737: iastore
    //   1738: aload #30
    //   1740: iload #32
    //   1742: iconst_3
    //   1743: iadd
    //   1744: aload #29
    //   1746: iload #33
    //   1748: iconst_3
    //   1749: iadd
    //   1750: iaload
    //   1751: iastore
    //   1752: iconst_0
    //   1753: newarray byte
    //   1755: astore #35
    //   1757: aload #6
    //   1759: arraylength
    //   1760: bipush #16
    //   1762: irem
    //   1763: ifeq -> 1787
    //   1766: new java/lang/Exception
    //   1769: dup
    //   1770: sipush #-17879
    //   1773: sipush #23489
    //   1776: invokestatic a : (II)Ljava/lang/String;
    //   1779: invokespecial <init> : (Ljava/lang/String;)V
    //   1782: athrow
    //   1783: invokestatic a : (Ljava/lang/Throwable;)Ljava/lang/Throwable;
    //   1786: athrow
    //   1787: bipush #10
    //   1789: istore #36
    //   1791: sipush #-17874
    //   1794: sipush #256
    //   1797: newarray byte
    //   1799: astore #37
    //   1801: sipush #28768
    //   1804: sipush #256
    //   1807: newarray int
    //   1809: astore #38
    //   1811: sipush #256
    //   1814: newarray int
    //   1816: astore #39
    //   1818: sipush #256
    //   1821: newarray int
    //   1823: astore #40
    //   1825: sipush #256
    //   1828: newarray int
    //   1830: astore #41
    //   1832: sipush #283
    //   1835: istore #14
    //   1837: invokestatic a : (II)Ljava/lang/String;
    //   1840: astore #42
    //   1842: iconst_0
    //   1843: istore #16
    //   1845: iload #16
    //   1847: sipush #256
    //   1850: if_icmpge -> 2077
    //   1853: aload #42
    //   1855: iload #16
    //   1857: iconst_1
    //   1858: iushr
    //   1859: invokevirtual charAt : (I)C
    //   1862: istore #43
    //   1864: iload #16
    //   1866: iconst_1
    //   1867: iand
    //   1868: ifne -> 1883
    //   1871: iload #43
    //   1873: bipush #8
    //   1875: iushr
    //   1876: goto -> 1885
    //   1879: invokestatic a : (Ljava/lang/Throwable;)Ljava/lang/Throwable;
    //   1882: athrow
    //   1883: iload #43
    //   1885: i2b
    //   1886: sipush #255
    //   1889: iand
    //   1890: istore #15
    //   1892: iload #16
    //   1894: iconst_1
    //   1895: ishl
    //   1896: istore #17
    //   1898: iload #17
    //   1900: sipush #256
    //   1903: if_icmplt -> 1913
    //   1906: iload #17
    //   1908: iload #14
    //   1910: ixor
    //   1911: istore #17
    //   1913: iload #17
    //   1915: iconst_1
    //   1916: ishl
    //   1917: istore #18
    //   1919: iload #18
    //   1921: sipush #256
    //   1924: if_icmplt -> 1934
    //   1927: iload #18
    //   1929: iload #14
    //   1931: ixor
    //   1932: istore #18
    //   1934: iload #18
    //   1936: iconst_1
    //   1937: ishl
    //   1938: istore #19
    //   1940: iload #19
    //   1942: sipush #256
    //   1945: if_icmplt -> 1955
    //   1948: iload #19
    //   1950: iload #14
    //   1952: ixor
    //   1953: istore #19
    //   1955: iload #19
    //   1957: iload #16
    //   1959: ixor
    //   1960: istore #20
    //   1962: iload #20
    //   1964: iload #17
    //   1966: ixor
    //   1967: istore #21
    //   1969: iload #20
    //   1971: iload #18
    //   1973: ixor
    //   1974: istore #22
    //   1976: iload #19
    //   1978: iload #18
    //   1980: ixor
    //   1981: iload #17
    //   1983: ixor
    //   1984: istore #23
    //   1986: aload #37
    //   1988: iload #15
    //   1990: iload #16
    //   1992: i2b
    //   1993: bastore
    //   1994: aload #38
    //   1996: iload #15
    //   1998: iload #23
    //   2000: bipush #24
    //   2002: ishl
    //   2003: iload #20
    //   2005: bipush #16
    //   2007: ishl
    //   2008: ior
    //   2009: iload #22
    //   2011: bipush #8
    //   2013: ishl
    //   2014: ior
    //   2015: iload #21
    //   2017: ior
    //   2018: dup
    //   2019: istore #24
    //   2021: iastore
    //   2022: aload #39
    //   2024: iload #15
    //   2026: iload #24
    //   2028: bipush #8
    //   2030: iushr
    //   2031: iload #24
    //   2033: bipush #24
    //   2035: ishl
    //   2036: ior
    //   2037: iastore
    //   2038: aload #40
    //   2040: iload #15
    //   2042: iload #24
    //   2044: bipush #16
    //   2046: iushr
    //   2047: iload #24
    //   2049: bipush #16
    //   2051: ishl
    //   2052: ior
    //   2053: iastore
    //   2054: aload #41
    //   2056: iload #15
    //   2058: iload #24
    //   2060: bipush #24
    //   2062: iushr
    //   2063: iload #24
    //   2065: bipush #8
    //   2067: ishl
    //   2068: ior
    //   2069: iastore
    //   2070: iinc #16, 1
    //   2073: iload_2
    //   2074: ifeq -> 1845
    //   2077: aload #6
    //   2079: arraylength
    //   2080: newarray byte
    //   2082: astore #43
    //   2084: iconst_0
    //   2085: istore #44
    //   2087: iload #44
    //   2089: aload #6
    //   2091: arraylength
    //   2092: bipush #16
    //   2094: idiv
    //   2095: if_icmpge -> 3009
    //   2098: bipush #16
    //   2100: newarray byte
    //   2102: astore #45
    //   2104: bipush #16
    //   2106: newarray byte
    //   2108: astore #46
    //   2110: iconst_0
    //   2111: istore #47
    //   2113: iload #47
    //   2115: bipush #16
    //   2117: if_icmpge -> 2143
    //   2120: aload #45
    //   2122: iload #47
    //   2124: aload #6
    //   2126: iload #47
    //   2128: iload #44
    //   2130: bipush #16
    //   2132: imul
    //   2133: iadd
    //   2134: baload
    //   2135: bastore
    //   2136: iinc #47, 1
    //   2139: iload_2
    //   2140: ifeq -> 2113
    //   2143: iconst_0
    //   2144: istore #47
    //   2146: aload #45
    //   2148: iconst_0
    //   2149: baload
    //   2150: bipush #24
    //   2152: ishl
    //   2153: aload #45
    //   2155: iconst_1
    //   2156: baload
    //   2157: sipush #255
    //   2160: iand
    //   2161: bipush #16
    //   2163: ishl
    //   2164: ior
    //   2165: aload #45
    //   2167: iconst_2
    //   2168: baload
    //   2169: sipush #255
    //   2172: iand
    //   2173: bipush #8
    //   2175: ishl
    //   2176: ior
    //   2177: aload #45
    //   2179: iconst_3
    //   2180: baload
    //   2181: sipush #255
    //   2184: iand
    //   2185: ior
    //   2186: aload #30
    //   2188: iconst_0
    //   2189: iaload
    //   2190: ixor
    //   2191: istore #49
    //   2193: aload #45
    //   2195: iconst_4
    //   2196: baload
    //   2197: bipush #24
    //   2199: ishl
    //   2200: aload #45
    //   2202: iconst_5
    //   2203: baload
    //   2204: sipush #255
    //   2207: iand
    //   2208: bipush #16
    //   2210: ishl
    //   2211: ior
    //   2212: aload #45
    //   2214: bipush #6
    //   2216: baload
    //   2217: sipush #255
    //   2220: iand
    //   2221: bipush #8
    //   2223: ishl
    //   2224: ior
    //   2225: aload #45
    //   2227: bipush #7
    //   2229: baload
    //   2230: sipush #255
    //   2233: iand
    //   2234: ior
    //   2235: aload #30
    //   2237: iconst_1
    //   2238: iaload
    //   2239: ixor
    //   2240: istore #50
    //   2242: aload #45
    //   2244: bipush #8
    //   2246: baload
    //   2247: bipush #24
    //   2249: ishl
    //   2250: aload #45
    //   2252: bipush #9
    //   2254: baload
    //   2255: sipush #255
    //   2258: iand
    //   2259: bipush #16
    //   2261: ishl
    //   2262: ior
    //   2263: aload #45
    //   2265: bipush #10
    //   2267: baload
    //   2268: sipush #255
    //   2271: iand
    //   2272: bipush #8
    //   2274: ishl
    //   2275: ior
    //   2276: aload #45
    //   2278: bipush #11
    //   2280: baload
    //   2281: sipush #255
    //   2284: iand
    //   2285: ior
    //   2286: aload #30
    //   2288: iconst_2
    //   2289: iaload
    //   2290: ixor
    //   2291: istore #51
    //   2293: aload #45
    //   2295: bipush #12
    //   2297: baload
    //   2298: bipush #24
    //   2300: ishl
    //   2301: aload #45
    //   2303: bipush #13
    //   2305: baload
    //   2306: sipush #255
    //   2309: iand
    //   2310: bipush #16
    //   2312: ishl
    //   2313: ior
    //   2314: aload #45
    //   2316: bipush #14
    //   2318: baload
    //   2319: sipush #255
    //   2322: iand
    //   2323: bipush #8
    //   2325: ishl
    //   2326: ior
    //   2327: aload #45
    //   2329: bipush #15
    //   2331: baload
    //   2332: sipush #255
    //   2335: iand
    //   2336: ior
    //   2337: aload #30
    //   2339: iconst_3
    //   2340: iaload
    //   2341: ixor
    //   2342: istore #52
    //   2344: iconst_1
    //   2345: istore #53
    //   2347: iload #53
    //   2349: iload #36
    //   2351: if_icmpge -> 2594
    //   2354: iinc #47, 4
    //   2357: aload #38
    //   2359: iload #49
    //   2361: bipush #24
    //   2363: iushr
    //   2364: iaload
    //   2365: aload #39
    //   2367: iload #52
    //   2369: bipush #16
    //   2371: iushr
    //   2372: sipush #255
    //   2375: iand
    //   2376: iaload
    //   2377: ixor
    //   2378: aload #40
    //   2380: iload #51
    //   2382: bipush #8
    //   2384: iushr
    //   2385: sipush #255
    //   2388: iand
    //   2389: iaload
    //   2390: ixor
    //   2391: aload #41
    //   2393: iload #50
    //   2395: sipush #255
    //   2398: iand
    //   2399: iaload
    //   2400: ixor
    //   2401: aload #30
    //   2403: iload #47
    //   2405: iaload
    //   2406: ixor
    //   2407: istore #54
    //   2409: aload #38
    //   2411: iload #50
    //   2413: bipush #24
    //   2415: iushr
    //   2416: iaload
    //   2417: aload #39
    //   2419: iload #49
    //   2421: bipush #16
    //   2423: iushr
    //   2424: sipush #255
    //   2427: iand
    //   2428: iaload
    //   2429: ixor
    //   2430: aload #40
    //   2432: iload #52
    //   2434: bipush #8
    //   2436: iushr
    //   2437: sipush #255
    //   2440: iand
    //   2441: iaload
    //   2442: ixor
    //   2443: aload #41
    //   2445: iload #51
    //   2447: sipush #255
    //   2450: iand
    //   2451: iaload
    //   2452: ixor
    //   2453: aload #30
    //   2455: iload #47
    //   2457: iconst_1
    //   2458: iadd
    //   2459: iaload
    //   2460: ixor
    //   2461: istore #55
    //   2463: aload #38
    //   2465: iload #51
    //   2467: bipush #24
    //   2469: iushr
    //   2470: iaload
    //   2471: aload #39
    //   2473: iload #50
    //   2475: bipush #16
    //   2477: iushr
    //   2478: sipush #255
    //   2481: iand
    //   2482: iaload
    //   2483: ixor
    //   2484: aload #40
    //   2486: iload #49
    //   2488: bipush #8
    //   2490: iushr
    //   2491: sipush #255
    //   2494: iand
    //   2495: iaload
    //   2496: ixor
    //   2497: aload #41
    //   2499: iload #52
    //   2501: sipush #255
    //   2504: iand
    //   2505: iaload
    //   2506: ixor
    //   2507: aload #30
    //   2509: iload #47
    //   2511: iconst_2
    //   2512: iadd
    //   2513: iaload
    //   2514: ixor
    //   2515: istore #56
    //   2517: aload #38
    //   2519: iload #52
    //   2521: bipush #24
    //   2523: iushr
    //   2524: iaload
    //   2525: aload #39
    //   2527: iload #51
    //   2529: bipush #16
    //   2531: iushr
    //   2532: sipush #255
    //   2535: iand
    //   2536: iaload
    //   2537: ixor
    //   2538: aload #40
    //   2540: iload #50
    //   2542: bipush #8
    //   2544: iushr
    //   2545: sipush #255
    //   2548: iand
    //   2549: iaload
    //   2550: ixor
    //   2551: aload #41
    //   2553: iload #49
    //   2555: sipush #255
    //   2558: iand
    //   2559: iaload
    //   2560: ixor
    //   2561: aload #30
    //   2563: iload #47
    //   2565: iconst_3
    //   2566: iadd
    //   2567: iaload
    //   2568: ixor
    //   2569: istore #57
    //   2571: iload #54
    //   2573: istore #49
    //   2575: iload #55
    //   2577: istore #50
    //   2579: iload #56
    //   2581: istore #51
    //   2583: iload #57
    //   2585: istore #52
    //   2587: iinc #53, 1
    //   2590: iload_2
    //   2591: ifeq -> 2347
    //   2594: iinc #47, 4
    //   2597: aload #30
    //   2599: iload #47
    //   2601: iaload
    //   2602: istore #48
    //   2604: aload #46
    //   2606: iconst_0
    //   2607: aload #37
    //   2609: iload #49
    //   2611: bipush #24
    //   2613: iushr
    //   2614: baload
    //   2615: iload #48
    //   2617: bipush #24
    //   2619: iushr
    //   2620: ixor
    //   2621: i2b
    //   2622: bastore
    //   2623: aload #46
    //   2625: iconst_1
    //   2626: aload #37
    //   2628: iload #52
    //   2630: bipush #16
    //   2632: iushr
    //   2633: sipush #255
    //   2636: iand
    //   2637: baload
    //   2638: iload #48
    //   2640: bipush #16
    //   2642: iushr
    //   2643: ixor
    //   2644: i2b
    //   2645: bastore
    //   2646: aload #46
    //   2648: iconst_2
    //   2649: aload #37
    //   2651: iload #51
    //   2653: bipush #8
    //   2655: iushr
    //   2656: sipush #255
    //   2659: iand
    //   2660: baload
    //   2661: iload #48
    //   2663: bipush #8
    //   2665: iushr
    //   2666: ixor
    //   2667: i2b
    //   2668: bastore
    //   2669: aload #46
    //   2671: iconst_3
    //   2672: aload #37
    //   2674: iload #50
    //   2676: sipush #255
    //   2679: iand
    //   2680: baload
    //   2681: iload #48
    //   2683: ixor
    //   2684: i2b
    //   2685: bastore
    //   2686: aload #30
    //   2688: iload #47
    //   2690: iconst_1
    //   2691: iadd
    //   2692: iaload
    //   2693: istore #48
    //   2695: aload #46
    //   2697: iconst_4
    //   2698: aload #37
    //   2700: iload #50
    //   2702: bipush #24
    //   2704: iushr
    //   2705: baload
    //   2706: iload #48
    //   2708: bipush #24
    //   2710: iushr
    //   2711: ixor
    //   2712: i2b
    //   2713: bastore
    //   2714: aload #46
    //   2716: iconst_5
    //   2717: aload #37
    //   2719: iload #49
    //   2721: bipush #16
    //   2723: iushr
    //   2724: sipush #255
    //   2727: iand
    //   2728: baload
    //   2729: iload #48
    //   2731: bipush #16
    //   2733: iushr
    //   2734: ixor
    //   2735: i2b
    //   2736: bastore
    //   2737: aload #46
    //   2739: bipush #6
    //   2741: aload #37
    //   2743: iload #52
    //   2745: bipush #8
    //   2747: iushr
    //   2748: sipush #255
    //   2751: iand
    //   2752: baload
    //   2753: iload #48
    //   2755: bipush #8
    //   2757: iushr
    //   2758: ixor
    //   2759: i2b
    //   2760: bastore
    //   2761: aload #46
    //   2763: bipush #7
    //   2765: aload #37
    //   2767: iload #51
    //   2769: sipush #255
    //   2772: iand
    //   2773: baload
    //   2774: iload #48
    //   2776: ixor
    //   2777: i2b
    //   2778: bastore
    //   2779: aload #30
    //   2781: iload #47
    //   2783: iconst_2
    //   2784: iadd
    //   2785: iaload
    //   2786: istore #48
    //   2788: aload #46
    //   2790: bipush #8
    //   2792: aload #37
    //   2794: iload #51
    //   2796: bipush #24
    //   2798: iushr
    //   2799: baload
    //   2800: iload #48
    //   2802: bipush #24
    //   2804: iushr
    //   2805: ixor
    //   2806: i2b
    //   2807: bastore
    //   2808: aload #46
    //   2810: bipush #9
    //   2812: aload #37
    //   2814: iload #50
    //   2816: bipush #16
    //   2818: iushr
    //   2819: sipush #255
    //   2822: iand
    //   2823: baload
    //   2824: iload #48
    //   2826: bipush #16
    //   2828: iushr
    //   2829: ixor
    //   2830: i2b
    //   2831: bastore
    //   2832: aload #46
    //   2834: bipush #10
    //   2836: aload #37
    //   2838: iload #49
    //   2840: bipush #8
    //   2842: iushr
    //   2843: sipush #255
    //   2846: iand
    //   2847: baload
    //   2848: iload #48
    //   2850: bipush #8
    //   2852: iushr
    //   2853: ixor
    //   2854: i2b
    //   2855: bastore
    //   2856: aload #46
    //   2858: bipush #11
    //   2860: aload #37
    //   2862: iload #52
    //   2864: sipush #255
    //   2867: iand
    //   2868: baload
    //   2869: iload #48
    //   2871: ixor
    //   2872: i2b
    //   2873: bastore
    //   2874: aload #30
    //   2876: iload #47
    //   2878: iconst_3
    //   2879: iadd
    //   2880: iaload
    //   2881: istore #48
    //   2883: aload #46
    //   2885: bipush #12
    //   2887: aload #37
    //   2889: iload #52
    //   2891: bipush #24
    //   2893: iushr
    //   2894: baload
    //   2895: iload #48
    //   2897: bipush #24
    //   2899: iushr
    //   2900: ixor
    //   2901: i2b
    //   2902: bastore
    //   2903: aload #46
    //   2905: bipush #13
    //   2907: aload #37
    //   2909: iload #51
    //   2911: bipush #16
    //   2913: iushr
    //   2914: sipush #255
    //   2917: iand
    //   2918: baload
    //   2919: iload #48
    //   2921: bipush #16
    //   2923: iushr
    //   2924: ixor
    //   2925: i2b
    //   2926: bastore
    //   2927: aload #46
    //   2929: bipush #14
    //   2931: aload #37
    //   2933: iload #50
    //   2935: bipush #8
    //   2937: iushr
    //   2938: sipush #255
    //   2941: iand
    //   2942: baload
    //   2943: iload #48
    //   2945: bipush #8
    //   2947: iushr
    //   2948: ixor
    //   2949: i2b
    //   2950: bastore
    //   2951: aload #46
    //   2953: bipush #15
    //   2955: aload #37
    //   2957: iload #49
    //   2959: sipush #255
    //   2962: iand
    //   2963: baload
    //   2964: iload #48
    //   2966: ixor
    //   2967: i2b
    //   2968: bastore
    //   2969: iconst_0
    //   2970: istore #53
    //   2972: iload #53
    //   2974: bipush #16
    //   2976: if_icmpge -> 3002
    //   2979: aload #43
    //   2981: iload #53
    //   2983: iload #44
    //   2985: bipush #16
    //   2987: imul
    //   2988: iadd
    //   2989: aload #46
    //   2991: iload #53
    //   2993: baload
    //   2994: bastore
    //   2995: iinc #53, 1
    //   2998: iload_2
    //   2999: ifeq -> 2972
    //   3002: iinc #44, 1
    //   3005: iload_2
    //   3006: ifeq -> 2087
    //   3009: aload #43
    //   3011: arraylength
    //   3012: ifle -> 3093
    //   3015: aload #43
    //   3017: aload #43
    //   3019: arraylength
    //   3020: iconst_1
    //   3021: isub
    //   3022: baload
    //   3023: istore #44
    //   3025: iload #44
    //   3027: bipush #16
    //   3029: if_icmple -> 3040
    //   3032: aload #43
    //   3034: astore #35
    //   3036: iload_2
    //   3037: ifeq -> 3093
    //   3040: aload #43
    //   3042: arraylength
    //   3043: iload #44
    //   3045: isub
    //   3046: newarray byte
    //   3048: astore #35
    //   3050: iconst_0
    //   3051: istore #45
    //   3053: iload #45
    //   3055: aload #35
    //   3057: arraylength
    //   3058: if_icmpge -> 3093
    //   3061: iload #45
    //   3063: aload #43
    //   3065: arraylength
    //   3066: if_icmpge -> 3093
    //   3069: aload #35
    //   3071: iload #45
    //   3073: aload #43
    //   3075: iload #45
    //   3077: baload
    //   3078: bastore
    //   3079: iinc #45, 1
    //   3082: iload_2
    //   3083: ifeq -> 3053
    //   3086: goto -> 3093
    //   3089: invokestatic a : (Ljava/lang/Throwable;)Ljava/lang/Throwable;
    //   3092: athrow
    //   3093: aload #35
    //   3095: astore #7
    //   3097: sipush #-17875
    //   3100: new java/math/BigInteger
    //   3103: dup
    //   3104: aload #7
    //   3106: invokespecial <init> : ([B)V
    //   3109: invokevirtual abs : ()Ljava/math/BigInteger;
    //   3112: putstatic burp/Zm__.Zz : Ljava/lang/Object;
    //   3115: sipush #-27043
    //   3118: invokestatic a : (II)Ljava/lang/String;
    //   3121: iconst_1
    //   3122: ldc burp/Zzv
    //   3124: invokevirtual getClassLoader : ()Ljava/lang/ClassLoader;
    //   3127: invokestatic forName : (Ljava/lang/String;ZLjava/lang/ClassLoader;)Ljava/lang/Class;
    //   3130: invokevirtual getDeclaredFields : ()[Ljava/lang/reflect/Field;
    //   3133: astore_3
    //   3134: aload_3
    //   3135: arraylength
    //   3136: istore #4
    //   3138: iconst_0
    //   3139: istore #5
    //   3141: iload #5
    //   3143: iload #4
    //   3145: if_icmpge -> 3282
    //   3148: aload_3
    //   3149: iload #5
    //   3151: aaload
    //   3152: astore #6
    //   3154: aload #6
    //   3156: invokevirtual getModifiers : ()I
    //   3159: invokestatic isStatic : (I)Z
    //   3162: ifne -> 3172
    //   3165: goto -> 3275
    //   3168: invokestatic a : (Ljava/lang/Throwable;)Ljava/lang/Throwable;
    //   3171: athrow
    //   3172: aload #6
    //   3174: invokevirtual getType : ()Ljava/lang/Class;
    //   3177: astore #7
    //   3179: aload #7
    //   3181: ifnull -> 3262
    //   3184: aload #7
    //   3186: invokevirtual isPrimitive : ()Z
    //   3189: ifne -> 3262
    //   3192: goto -> 3199
    //   3195: invokestatic a : (Ljava/lang/Throwable;)Ljava/lang/Throwable;
    //   3198: athrow
    //   3199: aload #7
    //   3201: invokevirtual getPackage : ()Ljava/lang/Package;
    //   3204: ifnull -> 3262
    //   3207: goto -> 3214
    //   3210: invokestatic a : (Ljava/lang/Throwable;)Ljava/lang/Throwable;
    //   3213: athrow
    //   3214: aload #7
    //   3216: invokevirtual getPackage : ()Ljava/lang/Package;
    //   3219: invokevirtual getName : ()Ljava/lang/String;
    //   3222: ifnull -> 3262
    //   3225: goto -> 3232
    //   3228: invokestatic a : (Ljava/lang/Throwable;)Ljava/lang/Throwable;
    //   3231: athrow
    //   3232: aload #7
    //   3234: invokevirtual getPackage : ()Ljava/lang/Package;
    //   3237: invokevirtual getName : ()Ljava/lang/String;
    //   3240: sipush #-17880
    //   3243: sipush #-30137
    //   3246: invokestatic a : (II)Ljava/lang/String;
    //   3249: invokevirtual startsWith : (Ljava/lang/String;)Z
    //   3252: ifne -> 3262
    //   3255: goto -> 3262
    //   3258: invokestatic a : (Ljava/lang/Throwable;)Ljava/lang/Throwable;
    //   3261: athrow
    //   3262: aload #6
    //   3264: iconst_1
    //   3265: invokevirtual setAccessible : (Z)V
    //   3268: aload #6
    //   3270: aconst_null
    //   3271: invokevirtual get : (Ljava/lang/Object;)Ljava/lang/Object;
    //   3274: pop
    //   3275: iinc #5, 1
    //   3278: iload_2
    //   3279: ifeq -> 3141
    //   3282: sipush #-17873
    //   3285: sipush #-1607
    //   3288: invokestatic a : (II)Ljava/lang/String;
    //   3291: invokestatic forName : (Ljava/lang/String;)Ljava/lang/Class;
    //   3294: invokevirtual getDeclaredMethods : ()[Ljava/lang/reflect/Method;
    //   3297: astore_3
    //   3298: aload_3
    //   3299: arraylength
    //   3300: istore #4
    //   3302: iconst_0
    //   3303: istore #5
    //   3305: iload #5
    //   3307: iload #4
    //   3309: if_icmpge -> 3441
    //   3312: aload_3
    //   3313: iload #5
    //   3315: aaload
    //   3316: astore #6
    //   3318: aload #6
    //   3320: invokevirtual getParameterTypes : ()[Ljava/lang/Class;
    //   3323: pop
    //   3324: aload #6
    //   3326: invokevirtual getModifiers : ()I
    //   3329: invokestatic isStatic : (I)Z
    //   3332: ifeq -> 3427
    //   3335: aload #6
    //   3337: invokevirtual getParameterTypes : ()[Ljava/lang/Class;
    //   3340: arraylength
    //   3341: iconst_2
    //   3342: if_icmpne -> 3427
    //   3345: goto -> 3352
    //   3348: invokestatic a : (Ljava/lang/Throwable;)Ljava/lang/Throwable;
    //   3351: athrow
    //   3352: aload #6
    //   3354: invokevirtual getReturnType : ()Ljava/lang/Class;
    //   3357: getstatic java/lang/Void.TYPE : Ljava/lang/Class;
    //   3360: invokevirtual equals : (Ljava/lang/Object;)Z
    //   3363: ifeq -> 3427
    //   3366: goto -> 3373
    //   3369: invokestatic a : (Ljava/lang/Throwable;)Ljava/lang/Throwable;
    //   3372: athrow
    //   3373: aload #6
    //   3375: iconst_1
    //   3376: invokevirtual setAccessible : (Z)V
    //   3379: aload #6
    //   3381: aconst_null
    //   3382: iconst_2
    //   3383: anewarray java/lang/Object
    //   3386: dup
    //   3387: iconst_0
    //   3388: aload_0
    //   3389: aastore
    //   3390: dup
    //   3391: iconst_1
    //   3392: aload_1
    //   3393: ifnonnull -> 3411
    //   3396: goto -> 3403
    //   3399: invokestatic a : (Ljava/lang/Throwable;)Ljava/lang/Throwable;
    //   3402: athrow
    //   3403: aload_1
    //   3404: goto -> 3418
    //   3407: invokestatic a : (Ljava/lang/Throwable;)Ljava/lang/Throwable;
    //   3410: athrow
    //   3411: aload_1
    //   3412: checkcast [B
    //   3415: invokevirtual clone : ()Ljava/lang/Object;
    //   3418: aastore
    //   3419: invokevirtual invoke : (Ljava/lang/Object;[Ljava/lang/Object;)Ljava/lang/Object;
    //   3422: pop
    //   3423: iload_2
    //   3424: ifeq -> 3441
    //   3427: iinc #5, 1
    //   3430: iload_2
    //   3431: ifeq -> 3305
    //   3434: goto -> 3441
    //   3437: invokestatic a : (Ljava/lang/Throwable;)Ljava/lang/Throwable;
    //   3440: athrow
    //   3441: getstatic burp/Zehi.Zi : Ljava/lang/String;
    //   3444: getstatic burp/Zzai.Z_ : Ljava/lang/Object;
    //   3447: checkcast java/math/BigInteger
    //   3450: invokevirtual intValue : ()I
    //   3453: bipush #32
    //   3455: irem
    //   3456: invokestatic abs : (I)I
    //   3459: invokevirtual charAt : (I)C
    //   3462: getstatic burp/Zod.ZS : Ljava/lang/String;
    //   3465: getstatic burp/Zxfu.ZA : Ljava/lang/Object;
    //   3468: checkcast java/math/BigInteger
    //   3471: invokevirtual intValue : ()I
    //   3474: bipush #32
    //   3476: irem
    //   3477: invokestatic abs : (I)I
    //   3480: invokevirtual charAt : (I)C
    //   3483: if_icmple -> 3598
    //   3486: getstatic burp/Ztbf.Zf : Ljava/lang/String;
    //   3489: getstatic burp/Zedz.Za : Ljava/lang/Object;
    //   3492: checkcast java/math/BigInteger
    //   3495: invokevirtual intValue : ()I
    //   3498: bipush #32
    //   3500: irem
    //   3501: invokestatic abs : (I)I
    //   3504: invokevirtual charAt : (I)C
    //   3507: getstatic burp/Zb3z.Zi : Ljava/lang/String;
    //   3510: getstatic burp/Zrbp.Z_ : Ljava/lang/Object;
    //   3513: checkcast java/math/BigInteger
    //   3516: invokevirtual intValue : ()I
    //   3519: bipush #32
    //   3521: irem
    //   3522: invokestatic abs : (I)I
    //   3525: invokevirtual charAt : (I)C
    //   3528: if_icmpgt -> 3598
    //   3531: goto -> 3538
    //   3534: invokestatic a : (Ljava/lang/Throwable;)Ljava/lang/Throwable;
    //   3537: athrow
    //   3538: getstatic burp/Zl2g.ZI : Ljava/lang/String;
    //   3541: getstatic burp/Zxzd.ZD : Ljava/lang/Object;
    //   3544: checkcast java/math/BigInteger
    //   3547: invokevirtual intValue : ()I
    //   3550: bipush #32
    //   3552: irem
    //   3553: invokestatic abs : (I)I
    //   3556: invokevirtual charAt : (I)C
    //   3559: getstatic burp/Zxso.ZH : Ljava/lang/String;
    //   3562: getstatic burp/Zr0u.ZB : Ljava/lang/Object;
    //   3565: checkcast java/math/BigInteger
    //   3568: invokevirtual intValue : ()I
    //   3571: bipush #32
    //   3573: irem
    //   3574: invokestatic abs : (I)I
    //   3577: invokevirtual charAt : (I)C
    //   3580: if_icmpgt -> 3598
    //   3583: goto -> 3590
    //   3586: invokestatic a : (Ljava/lang/Throwable;)Ljava/lang/Throwable;
    //   3589: athrow
    //   3590: iconst_1
    //   3591: goto -> 3599
    //   3594: invokestatic a : (Ljava/lang/Throwable;)Ljava/lang/Throwable;
    //   3597: athrow
    //   3598: iconst_0
    //   3599: ireturn
    //   3600: astore_3
    //   3601: new java/lang/Exception
    //   3604: dup
    //   3605: aload_3
    //   3606: invokevirtual getMessage : ()Ljava/lang/String;
    //   3609: invokespecial <init> : (Ljava/lang/String;)V
    //   3612: athrow
    // Exception table:
    //   from	to	target	type
    //   4	3599	3600	java/lang/Throwable
    //   203	227	230	java/lang/Throwable
    //   301	338	338	java/lang/Throwable
    //   342	363	363	java/lang/Throwable
    //   367	397	397	java/lang/Throwable
    //   740	755	755	java/lang/Throwable
    //   1757	1783	1783	java/lang/Throwable
    //   1864	1879	1879	java/lang/Throwable
    //   3061	3086	3089	java/lang/Throwable
    //   3154	3168	3168	java/lang/Throwable
    //   3179	3192	3195	java/lang/Throwable
    //   3184	3207	3210	java/lang/Throwable
    //   3199	3225	3228	java/lang/Throwable
    //   3214	3255	3258	java/lang/Throwable
    //   3318	3345	3348	java/lang/Throwable
    //   3335	3366	3369	java/lang/Throwable
    //   3352	3396	3399	java/lang/Throwable
    //   3373	3407	3407	java/lang/Throwable
    //   3418	3434	3437	java/lang/Throwable
    //   3441	3531	3534	java/lang/Throwable
    //   3486	3583	3586	java/lang/Throwable
    //   3538	3594	3594	java/lang/Throwable
  }
  
  static void Zo(Object[] paramArrayOfObject, Object paramObject) throws Throwable {}
  
  static void Zy(Object paramObject) {
    Zsde.Zi = a(-17876, 27827);
    Zsde.Zx = new BigInteger(a(-17878, 4672));
    boolean bool = Zt2e.ZN();
    try {
      try {
        if (Zlv6.Zt.charAt(Math.abs(((BigInteger)Zrbp.Z_).intValue() % 32)) > Zgmt.Zu.charAt(Math.abs(((BigInteger)Zgw0.ZM).intValue() % 32))) {
          try {
            Zkfz.ZP(Class.forName(a(-17881, 3287)));
            if (!bool)
              Zzi_.ZJ(Class.forName(a(-17883, 7055))); 
          } catch (Throwable throwable) {
            throw a(null);
          } 
          return;
        } 
      } catch (Throwable throwable) {
        throw a(null);
      } 
      Zzi_.ZJ(Class.forName(a(-17883, 7055)));
    } catch (Throwable throwable) {}
  }
  
  static {
    // Byte code:
    //   0: bipush #11
    //   2: anewarray java/lang/String
    //   5: astore #5
    //   7: iconst_0
    //   8: istore_3
    //   9: ldc 'xo(^ :6*q<yi[J&$Z/.p\\t=KK)7??\\foT`81\\n??M-'G",S%\\nhZauKm|z@c\\f\\t! f)>PI(]A1\\t;\\t/z%'
    //   11: dup
    //   12: astore_2
    //   13: invokevirtual length : ()I
    //   16: istore #4
    //   18: bipush #9
    //   20: istore_1
    //   21: iconst_m1
    //   22: istore_0
    //   23: bipush #49
    //   25: iinc #0, 1
    //   28: aload_2
    //   29: iload_0
    //   30: dup
    //   31: iload_1
    //   32: iadd
    //   33: invokevirtual substring : (II)Ljava/lang/String;
    //   36: iconst_m1
    //   37: goto -> 143
    //   40: aload #5
    //   42: swap
    //   43: iload_3
    //   44: iinc #3, 1
    //   47: swap
    //   48: aastore
    //   49: iload_0
    //   50: iload_1
    //   51: iadd
    //   52: dup
    //   53: istore_0
    //   54: iload #4
    //   56: if_icmpge -> 68
    //   59: aload_2
    //   60: iload_0
    //   61: invokevirtual charAt : (I)C
    //   64: istore_1
    //   65: goto -> 23
    //   68: ldc 'gJUih.,*/`y\\tpWP'
    //   70: dup
    //   71: astore_2
    //   72: invokevirtual length : ()I
    //   75: istore #4
    //   77: bipush #32
    //   79: istore_1
    //   80: iconst_m1
    //   81: istore_0
    //   82: bipush #94
    //   84: iinc #0, 1
    //   87: aload_2
    //   88: iload_0
    //   89: dup
    //   90: iload_1
    //   91: iadd
    //   92: invokevirtual substring : (II)Ljava/lang/String;
    //   95: iconst_0
    //   96: goto -> 143
    //   99: aload #5
    //   101: swap
    //   102: iload_3
    //   103: iinc #3, 1
    //   106: swap
    //   107: aastore
    //   108: iload_0
    //   109: iload_1
    //   110: iadd
    //   111: dup
    //   112: istore_0
    //   113: iload #4
    //   115: if_icmpge -> 127
    //   118: aload_2
    //   119: iload_0
    //   120: invokevirtual charAt : (I)C
    //   123: istore_1
    //   124: goto -> 82
    //   127: aload #5
    //   129: putstatic burp/Zxzd.a : [Ljava/lang/String;
    //   132: bipush #11
    //   134: anewarray java/lang/String
    //   137: putstatic burp/Zxzd.b : [Ljava/lang/String;
    //   140: goto -> 300
    //   143: dup_x2
    //   144: pop
    //   145: invokevirtual toCharArray : ()[C
    //   148: dup_x1
    //   149: arraylength
    //   150: dup_x2
    //   151: pop
    //   152: iconst_0
    //   153: istore #6
    //   155: dup2_x1
    //   156: pop2
    //   157: dup_x2
    //   158: iconst_1
    //   159: if_icmpgt -> 258
    //   162: dup2
    //   163: swap
    //   164: iload #6
    //   166: dup2_x1
    //   167: caload
    //   168: swap
    //   169: iload #6
    //   171: bipush #7
    //   173: irem
    //   174: tableswitch default -> 240, 0 -> 212, 1 -> 216, 2 -> 221, 3 -> 226, 4 -> 230, 5 -> 235
    //   212: iconst_5
    //   213: goto -> 242
    //   216: bipush #17
    //   218: goto -> 242
    //   221: bipush #106
    //   223: goto -> 242
    //   226: iconst_1
    //   227: goto -> 242
    //   230: bipush #111
    //   232: goto -> 242
    //   235: bipush #121
    //   237: goto -> 242
    //   240: bipush #47
    //   242: ixor
    //   243: ixor
    //   244: i2c
    //   245: castore
    //   246: iinc #6, 1
    //   249: dup
    //   250: ifne -> 258
    //   253: dup2
    //   254: dup_x1
    //   255: goto -> 166
    //   258: dup2_x1
    //   259: pop2
    //   260: dup_x2
    //   261: iload #6
    //   263: if_icmpgt -> 162
    //   266: pop
    //   267: new java/lang/String
    //   270: dup_x1
    //   271: swap
    //   272: invokespecial <init> : ([C)V
    //   275: invokevirtual intern : ()Ljava/lang/String;
    //   278: swap
    //   279: pop
    //   280: swap
    //   281: tableswitch default -> 40, 0 -> 99
    //   300: new java/math/BigInteger
    //   303: dup
    //   304: bipush #32
    //   306: newarray byte
    //   308: dup
    //   309: iconst_0
    //   310: bipush #55
    //   312: bastore
    //   313: dup
    //   314: iconst_1
    //   315: bipush #69
    //   317: bastore
    //   318: dup
    //   319: iconst_2
    //   320: bipush #-71
    //   322: bastore
    //   323: dup
    //   324: iconst_3
    //   325: bipush #-86
    //   327: bastore
    //   328: dup
    //   329: iconst_4
    //   330: bipush #37
    //   332: bastore
    //   333: dup
    //   334: iconst_5
    //   335: bipush #-35
    //   337: bastore
    //   338: dup
    //   339: bipush #6
    //   341: bipush #-113
    //   343: bastore
    //   344: dup
    //   345: bipush #7
    //   347: bipush #10
    //   349: bastore
    //   350: dup
    //   351: bipush #8
    //   353: bipush #31
    //   355: bastore
    //   356: dup
    //   357: bipush #9
    //   359: bipush #-101
    //   361: bastore
    //   362: dup
    //   363: bipush #10
    //   365: bipush #100
    //   367: bastore
    //   368: dup
    //   369: bipush #11
    //   371: bipush #-65
    //   373: bastore
    //   374: dup
    //   375: bipush #12
    //   377: bipush #72
    //   379: bastore
    //   380: dup
    //   381: bipush #13
    //   383: bipush #-92
    //   385: bastore
    //   386: dup
    //   387: bipush #14
    //   389: bipush #-106
    //   391: bastore
    //   392: dup
    //   393: bipush #15
    //   395: bipush #-24
    //   397: bastore
    //   398: dup
    //   399: bipush #16
    //   401: bipush #-28
    //   403: bastore
    //   404: dup
    //   405: bipush #17
    //   407: bipush #-59
    //   409: bastore
    //   410: dup
    //   411: bipush #18
    //   413: bipush #-24
    //   415: bastore
    //   416: dup
    //   417: bipush #19
    //   419: bipush #26
    //   421: bastore
    //   422: dup
    //   423: bipush #20
    //   425: bipush #55
    //   427: bastore
    //   428: dup
    //   429: bipush #21
    //   431: bipush #-81
    //   433: bastore
    //   434: dup
    //   435: bipush #22
    //   437: bipush #77
    //   439: bastore
    //   440: dup
    //   441: bipush #23
    //   443: bipush #48
    //   445: bastore
    //   446: dup
    //   447: bipush #24
    //   449: bipush #115
    //   451: bastore
    //   452: dup
    //   453: bipush #25
    //   455: bipush #-12
    //   457: bastore
    //   458: dup
    //   459: bipush #26
    //   461: bipush #-114
    //   463: bastore
    //   464: dup
    //   465: bipush #27
    //   467: bipush #-122
    //   469: bastore
    //   470: dup
    //   471: bipush #28
    //   473: bipush #30
    //   475: bastore
    //   476: dup
    //   477: bipush #29
    //   479: bipush #-30
    //   481: bastore
    //   482: dup
    //   483: bipush #30
    //   485: bipush #-68
    //   487: bastore
    //   488: dup
    //   489: bipush #31
    //   491: bipush #-55
    //   493: bastore
    //   494: invokespecial <init> : ([B)V
    //   497: putstatic burp/Zxzd.ZD : Ljava/lang/Object;
    //   500: sipush #-17884
    //   503: sipush #16667
    //   506: invokestatic a : (II)Ljava/lang/String;
    //   509: putstatic burp/Zxzd.ZM : Ljava/lang/String;
    //   512: return
  }
  
  private static Throwable a(Throwable paramThrowable) {
    return paramThrowable;
  }
  
  private static String a(int paramInt1, int paramInt2) {
    int i = (paramInt1 ^ 0xFFFFBA2D) & 0xFFFF;
    if (b[i] == null) {
      char[] arrayOfChar = a[i].toCharArray();
      switch (arrayOfChar[0] & 0xFF) {
        case 0:
        
        case 1:
        
        case 2:
        
        case 3:
        
        case 4:
        
        case 5:
        
        case 6:
        
        case 7:
        
        case 8:
        
        case 9:
        
        case 10:
        
        case 11:
        
        case 12:
        
        case 13:
        
        case 14:
        
        case 15:
        
        case 16:
        
        case 17:
        
        case 18:
        
        case 19:
        
        case 20:
        
        case 21:
        
        case 22:
        
        case 23:
        
        case 24:
        
        case 25:
        
        case 26:
        
        case 27:
        
        case 28:
        
        case 29:
        
        case 30:
        
        case 31:
        
        case 32:
        
        case 33:
        
        case 34:
        
        case 35:
        
        case 36:
        
        case 37:
        
        case 38:
        
        case 39:
        
        case 40:
        
        case 41:
        
        case 42:
        
        case 43:
        
        case 44:
        
        case 45:
        
        case 46:
        
        case 47:
        
        case 48:
        
        case 49:
        
        case 50:
        
        case 51:
        
        case 52:
        
        case 53:
        
        case 54:
        
        case 55:
        
        case 56:
        
        case 57:
        
        case 58:
        
        case 59:
        
        case 60:
        
        case 61:
        
        case 62:
        
        case 63:
        
        case 64:
        
        case 65:
        
        case 66:
        
        case 67:
        
        case 68:
        
        case 69:
        
        case 70:
        
        case 71:
        
        case 72:
        
        case 73:
        
        case 74:
        
        case 75:
        
        case 76:
        
        case 77:
        
        case 78:
        
        case 79:
        
        case 80:
        
        case 81:
        
        case 82:
        
        case 83:
        
        case 84:
        
        case 85:
        
        case 86:
        
        case 87:
        
        case 88:
        
        case 89:
        
        case 90:
        
        case 91:
        
        case 92:
        
        case 93:
        
        case 94:
        
        case 95:
        
        case 96:
        
        case 97:
        
        case 98:
        
        case 99:
        
        case 100:
        
        case 101:
        
        case 102:
        
        case 103:
        
        case 104:
        
        case 105:
        
        case 106:
        
        case 107:
        
        case 108:
        
        case 109:
        
        case 110:
        
        case 111:
        
        case 112:
        
        case 113:
        
        case 114:
        
        case 115:
        
        case 116:
        
        case 117:
        
        case 118:
        
        case 119:
        
        case 120:
        
        case 121:
        
        case 122:
        
        case 123:
        
        case 124:
        
        case 125:
        
        case 126:
        
        case 127:
        
        case 128:
        
        case 129:
        
        case 130:
        
        case 131:
        
        case 132:
        
        case 133:
        
        case 134:
        
        case 135:
        
        case 136:
        
        case 137:
        
        case 138:
        
        case 139:
        
        case 140:
        
        case 141:
        
        case 142:
        
        case 143:
        
        case 144:
        
        case 145:
        
        case 146:
        
        case 147:
        
        case 148:
        
        case 149:
        
        case 150:
        
        case 151:
        
        case 152:
        
        case 153:
        
        case 154:
        
        case 155:
        
        case 156:
        
        case 157:
        
        case 158:
        
        case 159:
        
        case 160:
        
        case 161:
        
        case 162:
        
        case 163:
        
        case 164:
        
        case 165:
        
        case 166:
        
        case 167:
        
        case 168:
        
        case 169:
        
        case 170:
        
        case 171:
        
        case 172:
        
        case 173:
        
        case 174:
        
        case 175:
        
        case 176:
        
        case 177:
        
        case 178:
        
        case 179:
        
        case 180:
        
        case 181:
        
        case 182:
        
        case 183:
        
        case 184:
        
        case 185:
        
        case 186:
        
        case 187:
        
        case 188:
        
        case 189:
        
        case 190:
        
        case 191:
        
        case 192:
        
        case 193:
        
        case 194:
        
        case 195:
        
        case 196:
        
        case 197:
        
        case 198:
        
        case 199:
        
        case 200:
        
        case 201:
        
        case 202:
        
        case 203:
        
        case 204:
        
        case 205:
        
        case 206:
        
        case 207:
        
        case 208:
        
        case 209:
        
        case 210:
        
        case 211:
        
        case 212:
        
        case 213:
        
        case 214:
        
        case 215:
        
        case 216:
        
        case 217:
        
        case 218:
        
        case 219:
        
        case 220:
        
        case 221:
        
        case 222:
        
        case 223:
        
        case 224:
        
        case 225:
        
        case 226:
        
        case 227:
        
        case 228:
        
        case 229:
        
        case 230:
        
        case 231:
        
        case 232:
        
        case 233:
        
        case 234:
        
        case 235:
        
        case 236:
        
        case 237:
        
        case 238:
        
        case 239:
        
        case 240:
        
        case 241:
        
        case 242:
        
        case 243:
        
        case 244:
        
        case 245:
        
        case 246:
        
        case 247:
        
        case 248:
        
        case 249:
        
        case 250:
        
        case 251:
        
        case 252:
        
        case 253:
        
        case 254:
        
        default:
          break;
      } 
      char c = '';
      int j = (paramInt2 & 0xFF) - c;
      if (j < 0)
        j += 256; 
      int k = ((paramInt2 & 0xFFFF) >>> 8) - c;
      if (k < 0)
        k += 256; 
      for (byte b = 0; b < arrayOfChar.length; b++) {
        int m = b % 2;
        if (m == 0) {
          arrayOfChar[b] = (char)(arrayOfChar[b] ^ j);
          j = ((j >>> 3 | j << 5) ^ arrayOfChar[b]) & 0xFF;
        } else {
          arrayOfChar[b] = (char)(arrayOfChar[b] ^ k);
          k = ((k >>> 3 | k << 5) ^ arrayOfChar[b]) & 0xFF;
        } 
      } 
      b[i] = (new String(arrayOfChar)).intern();
    } 
    return b[i];
  }
}


/* Location:              C:\Program Files\BurpSuitePro\burpsuite_pro.jar!\burp\Zxzd.class
 * Java compiler version: 21 (65.0)
 * JD-Core Version:       1.1.3
 */