package burp;

import java.math.BigInteger;

class Zxzp extends ClassLoader {
  static Object Zh;
  
  static String ZH;
  
  private static final String[] a;
  
  private static final String[] b;
  
  static boolean Zr(Object[] paramArrayOfObject, Object paramObject) throws Throwable {
    // Byte code:
    //   0: invokestatic ZK : ()Z
    //   3: istore_2
    //   4: getstatic burp/Zb2p.ZQ : Ljava/lang/Object;
    //   7: checkcast java/math/BigInteger
    //   10: invokevirtual toByteArray : ()[B
    //   13: astore_3
    //   14: iconst_0
    //   15: istore #5
    //   17: iconst_0
    //   18: istore #6
    //   20: iload #6
    //   22: aload_3
    //   23: arraylength
    //   24: if_icmpge -> 169
    //   27: aload_3
    //   28: iload #6
    //   30: baload
    //   31: istore #7
    //   33: iload #7
    //   35: bipush #48
    //   37: if_icmplt -> 54
    //   40: iload #7
    //   42: bipush #57
    //   44: if_icmple -> 152
    //   47: goto -> 54
    //   50: invokestatic a : (Ljava/lang/Throwable;)Ljava/lang/Throwable;
    //   53: athrow
    //   54: iload #7
    //   56: bipush #65
    //   58: if_icmplt -> 82
    //   61: goto -> 68
    //   64: invokestatic a : (Ljava/lang/Throwable;)Ljava/lang/Throwable;
    //   67: athrow
    //   68: iload #7
    //   70: bipush #90
    //   72: if_icmple -> 152
    //   75: goto -> 82
    //   78: invokestatic a : (Ljava/lang/Throwable;)Ljava/lang/Throwable;
    //   81: athrow
    //   82: iload #7
    //   84: bipush #97
    //   86: if_icmplt -> 110
    //   89: goto -> 96
    //   92: invokestatic a : (Ljava/lang/Throwable;)Ljava/lang/Throwable;
    //   95: athrow
    //   96: iload #7
    //   98: bipush #122
    //   100: if_icmple -> 152
    //   103: goto -> 110
    //   106: invokestatic a : (Ljava/lang/Throwable;)Ljava/lang/Throwable;
    //   109: athrow
    //   110: iload #7
    //   112: bipush #43
    //   114: if_icmpeq -> 152
    //   117: goto -> 124
    //   120: invokestatic a : (Ljava/lang/Throwable;)Ljava/lang/Throwable;
    //   123: athrow
    //   124: iload #7
    //   126: bipush #47
    //   128: if_icmpeq -> 152
    //   131: goto -> 138
    //   134: invokestatic a : (Ljava/lang/Throwable;)Ljava/lang/Throwable;
    //   137: athrow
    //   138: iload #7
    //   140: bipush #61
    //   142: if_icmpne -> 162
    //   145: goto -> 152
    //   148: invokestatic a : (Ljava/lang/Throwable;)Ljava/lang/Throwable;
    //   151: athrow
    //   152: iinc #5, 1
    //   155: goto -> 162
    //   158: invokestatic a : (Ljava/lang/Throwable;)Ljava/lang/Throwable;
    //   161: athrow
    //   162: iinc #6, 1
    //   165: iload_2
    //   166: ifeq -> 20
    //   169: iload #5
    //   171: newarray byte
    //   173: astore #6
    //   175: iconst_0
    //   176: istore #7
    //   178: iconst_0
    //   179: istore #8
    //   181: iload #8
    //   183: aload_3
    //   184: arraylength
    //   185: if_icmpge -> 337
    //   188: aload_3
    //   189: iload #8
    //   191: baload
    //   192: istore #9
    //   194: iload #9
    //   196: bipush #48
    //   198: if_icmplt -> 215
    //   201: iload #9
    //   203: bipush #57
    //   205: if_icmple -> 313
    //   208: goto -> 215
    //   211: invokestatic a : (Ljava/lang/Throwable;)Ljava/lang/Throwable;
    //   214: athrow
    //   215: iload #9
    //   217: bipush #65
    //   219: if_icmplt -> 243
    //   222: goto -> 229
    //   225: invokestatic a : (Ljava/lang/Throwable;)Ljava/lang/Throwable;
    //   228: athrow
    //   229: iload #9
    //   231: bipush #90
    //   233: if_icmple -> 313
    //   236: goto -> 243
    //   239: invokestatic a : (Ljava/lang/Throwable;)Ljava/lang/Throwable;
    //   242: athrow
    //   243: iload #9
    //   245: bipush #97
    //   247: if_icmplt -> 271
    //   250: goto -> 257
    //   253: invokestatic a : (Ljava/lang/Throwable;)Ljava/lang/Throwable;
    //   256: athrow
    //   257: iload #9
    //   259: bipush #122
    //   261: if_icmple -> 313
    //   264: goto -> 271
    //   267: invokestatic a : (Ljava/lang/Throwable;)Ljava/lang/Throwable;
    //   270: athrow
    //   271: iload #9
    //   273: bipush #43
    //   275: if_icmpeq -> 313
    //   278: goto -> 285
    //   281: invokestatic a : (Ljava/lang/Throwable;)Ljava/lang/Throwable;
    //   284: athrow
    //   285: iload #9
    //   287: bipush #47
    //   289: if_icmpeq -> 313
    //   292: goto -> 299
    //   295: invokestatic a : (Ljava/lang/Throwable;)Ljava/lang/Throwable;
    //   298: athrow
    //   299: iload #9
    //   301: bipush #61
    //   303: if_icmpne -> 330
    //   306: goto -> 313
    //   309: invokestatic a : (Ljava/lang/Throwable;)Ljava/lang/Throwable;
    //   312: athrow
    //   313: aload #6
    //   315: iload #7
    //   317: iload #9
    //   319: bastore
    //   320: iinc #7, 1
    //   323: goto -> 330
    //   326: invokestatic a : (Ljava/lang/Throwable;)Ljava/lang/Throwable;
    //   329: athrow
    //   330: iinc #8, 1
    //   333: iload_2
    //   334: ifeq -> 181
    //   337: aload #6
    //   339: astore #4
    //   341: aload #4
    //   343: astore_3
    //   344: aload_3
    //   345: arraylength
    //   346: istore #5
    //   348: aload_3
    //   349: iload #5
    //   351: iconst_1
    //   352: isub
    //   353: baload
    //   354: bipush #61
    //   356: if_icmpne -> 366
    //   359: iinc #5, -1
    //   362: iload_2
    //   363: ifeq -> 348
    //   366: iload #5
    //   368: aload_3
    //   369: arraylength
    //   370: iconst_4
    //   371: idiv
    //   372: isub
    //   373: newarray byte
    //   375: astore #6
    //   377: iconst_0
    //   378: istore #7
    //   380: iload #7
    //   382: aload_3
    //   383: arraylength
    //   384: if_icmpge -> 646
    //   387: aload_3
    //   388: iload #7
    //   390: baload
    //   391: bipush #61
    //   393: if_icmpne -> 412
    //   396: aload_3
    //   397: iload #7
    //   399: iconst_0
    //   400: bastore
    //   401: iload_2
    //   402: ifeq -> 639
    //   405: goto -> 412
    //   408: invokestatic a : (Ljava/lang/Throwable;)Ljava/lang/Throwable;
    //   411: athrow
    //   412: aload_3
    //   413: iload #7
    //   415: baload
    //   416: bipush #47
    //   418: if_icmpne -> 445
    //   421: goto -> 428
    //   424: invokestatic a : (Ljava/lang/Throwable;)Ljava/lang/Throwable;
    //   427: athrow
    //   428: aload_3
    //   429: iload #7
    //   431: bipush #63
    //   433: bastore
    //   434: iload_2
    //   435: ifeq -> 639
    //   438: goto -> 445
    //   441: invokestatic a : (Ljava/lang/Throwable;)Ljava/lang/Throwable;
    //   444: athrow
    //   445: aload_3
    //   446: iload #7
    //   448: baload
    //   449: bipush #43
    //   451: if_icmpne -> 478
    //   454: goto -> 461
    //   457: invokestatic a : (Ljava/lang/Throwable;)Ljava/lang/Throwable;
    //   460: athrow
    //   461: aload_3
    //   462: iload #7
    //   464: bipush #62
    //   466: bastore
    //   467: iload_2
    //   468: ifeq -> 639
    //   471: goto -> 478
    //   474: invokestatic a : (Ljava/lang/Throwable;)Ljava/lang/Throwable;
    //   477: athrow
    //   478: aload_3
    //   479: iload #7
    //   481: baload
    //   482: bipush #48
    //   484: if_icmplt -> 533
    //   487: goto -> 494
    //   490: invokestatic a : (Ljava/lang/Throwable;)Ljava/lang/Throwable;
    //   493: athrow
    //   494: aload_3
    //   495: iload #7
    //   497: baload
    //   498: bipush #57
    //   500: if_icmpgt -> 533
    //   503: goto -> 510
    //   506: invokestatic a : (Ljava/lang/Throwable;)Ljava/lang/Throwable;
    //   509: athrow
    //   510: aload_3
    //   511: iload #7
    //   513: aload_3
    //   514: iload #7
    //   516: baload
    //   517: bipush #-4
    //   519: isub
    //   520: i2b
    //   521: bastore
    //   522: iload_2
    //   523: ifeq -> 639
    //   526: goto -> 533
    //   529: invokestatic a : (Ljava/lang/Throwable;)Ljava/lang/Throwable;
    //   532: athrow
    //   533: aload_3
    //   534: iload #7
    //   536: baload
    //   537: bipush #97
    //   539: if_icmplt -> 588
    //   542: goto -> 549
    //   545: invokestatic a : (Ljava/lang/Throwable;)Ljava/lang/Throwable;
    //   548: athrow
    //   549: aload_3
    //   550: iload #7
    //   552: baload
    //   553: bipush #122
    //   555: if_icmpgt -> 588
    //   558: goto -> 565
    //   561: invokestatic a : (Ljava/lang/Throwable;)Ljava/lang/Throwable;
    //   564: athrow
    //   565: aload_3
    //   566: iload #7
    //   568: aload_3
    //   569: iload #7
    //   571: baload
    //   572: bipush #71
    //   574: isub
    //   575: i2b
    //   576: bastore
    //   577: iload_2
    //   578: ifeq -> 639
    //   581: goto -> 588
    //   584: invokestatic a : (Ljava/lang/Throwable;)Ljava/lang/Throwable;
    //   587: athrow
    //   588: aload_3
    //   589: iload #7
    //   591: baload
    //   592: bipush #65
    //   594: if_icmplt -> 639
    //   597: goto -> 604
    //   600: invokestatic a : (Ljava/lang/Throwable;)Ljava/lang/Throwable;
    //   603: athrow
    //   604: aload_3
    //   605: iload #7
    //   607: baload
    //   608: bipush #90
    //   610: if_icmpgt -> 639
    //   613: goto -> 620
    //   616: invokestatic a : (Ljava/lang/Throwable;)Ljava/lang/Throwable;
    //   619: athrow
    //   620: aload_3
    //   621: iload #7
    //   623: aload_3
    //   624: iload #7
    //   626: baload
    //   627: bipush #65
    //   629: isub
    //   630: i2b
    //   631: bastore
    //   632: goto -> 639
    //   635: invokestatic a : (Ljava/lang/Throwable;)Ljava/lang/Throwable;
    //   638: athrow
    //   639: iinc #7, 1
    //   642: iload_2
    //   643: ifeq -> 380
    //   646: iconst_0
    //   647: istore #7
    //   649: iconst_0
    //   650: istore #8
    //   652: iload #8
    //   654: aload #6
    //   656: arraylength
    //   657: iconst_2
    //   658: isub
    //   659: if_icmpge -> 762
    //   662: aload #6
    //   664: iload #8
    //   666: aload_3
    //   667: iload #7
    //   669: baload
    //   670: iconst_2
    //   671: ishl
    //   672: sipush #255
    //   675: iand
    //   676: aload_3
    //   677: iload #7
    //   679: iconst_1
    //   680: iadd
    //   681: baload
    //   682: iconst_4
    //   683: iushr
    //   684: iconst_3
    //   685: iand
    //   686: ior
    //   687: i2b
    //   688: bastore
    //   689: aload #6
    //   691: iload #8
    //   693: iconst_1
    //   694: iadd
    //   695: aload_3
    //   696: iload #7
    //   698: iconst_1
    //   699: iadd
    //   700: baload
    //   701: iconst_4
    //   702: ishl
    //   703: sipush #255
    //   706: iand
    //   707: aload_3
    //   708: iload #7
    //   710: iconst_2
    //   711: iadd
    //   712: baload
    //   713: iconst_2
    //   714: iushr
    //   715: bipush #15
    //   717: iand
    //   718: ior
    //   719: i2b
    //   720: bastore
    //   721: aload #6
    //   723: iload #8
    //   725: iconst_2
    //   726: iadd
    //   727: aload_3
    //   728: iload #7
    //   730: iconst_2
    //   731: iadd
    //   732: baload
    //   733: bipush #6
    //   735: ishl
    //   736: sipush #255
    //   739: iand
    //   740: aload_3
    //   741: iload #7
    //   743: iconst_3
    //   744: iadd
    //   745: baload
    //   746: bipush #63
    //   748: iand
    //   749: ior
    //   750: i2b
    //   751: bastore
    //   752: iinc #7, 4
    //   755: iinc #8, 3
    //   758: iload_2
    //   759: ifeq -> 652
    //   762: iload #8
    //   764: aload #6
    //   766: arraylength
    //   767: if_icmpge -> 804
    //   770: aload #6
    //   772: iload #8
    //   774: aload_3
    //   775: iload #7
    //   777: baload
    //   778: iconst_2
    //   779: ishl
    //   780: sipush #255
    //   783: iand
    //   784: aload_3
    //   785: iload #7
    //   787: iconst_1
    //   788: iadd
    //   789: baload
    //   790: iconst_4
    //   791: iushr
    //   792: iconst_3
    //   793: iand
    //   794: ior
    //   795: i2b
    //   796: bastore
    //   797: goto -> 804
    //   800: invokestatic a : (Ljava/lang/Throwable;)Ljava/lang/Throwable;
    //   803: athrow
    //   804: iinc #8, 1
    //   807: iload #8
    //   809: aload #6
    //   811: arraylength
    //   812: if_icmpge -> 852
    //   815: aload #6
    //   817: iload #8
    //   819: aload_3
    //   820: iload #7
    //   822: iconst_1
    //   823: iadd
    //   824: baload
    //   825: iconst_4
    //   826: ishl
    //   827: sipush #255
    //   830: iand
    //   831: aload_3
    //   832: iload #7
    //   834: iconst_2
    //   835: iadd
    //   836: baload
    //   837: iconst_2
    //   838: iushr
    //   839: bipush #15
    //   841: iand
    //   842: ior
    //   843: i2b
    //   844: bastore
    //   845: goto -> 852
    //   848: invokestatic a : (Ljava/lang/Throwable;)Ljava/lang/Throwable;
    //   851: athrow
    //   852: aload #6
    //   854: astore #4
    //   856: sipush #-8739
    //   859: new java/math/BigInteger
    //   862: dup
    //   863: aload #4
    //   865: invokespecial <init> : ([B)V
    //   868: invokevirtual abs : ()Ljava/math/BigInteger;
    //   871: putstatic burp/Zle6.ZM : Ljava/lang/Object;
    //   874: sipush #-1502
    //   877: getstatic burp/Zb6e.ZD : Ljava/lang/Object;
    //   880: checkcast java/math/BigInteger
    //   883: getstatic burp/Zlqm.Zw : Ljava/lang/Object;
    //   886: checkcast java/math/BigInteger
    //   889: invokevirtual subtract : (Ljava/math/BigInteger;)Ljava/math/BigInteger;
    //   892: putstatic burp/Zg0j.ZV : Ljava/lang/Object;
    //   895: invokestatic a : (II)Ljava/lang/String;
    //   898: iconst_1
    //   899: ldc burp/Zb29
    //   901: invokevirtual getClassLoader : ()Ljava/lang/ClassLoader;
    //   904: invokestatic forName : (Ljava/lang/String;ZLjava/lang/ClassLoader;)Ljava/lang/Class;
    //   907: invokevirtual getDeclaredFields : ()[Ljava/lang/reflect/Field;
    //   910: astore_3
    //   911: aload_3
    //   912: arraylength
    //   913: istore #4
    //   915: iconst_0
    //   916: istore #5
    //   918: iload #5
    //   920: iload #4
    //   922: if_icmpge -> 1059
    //   925: aload_3
    //   926: iload #5
    //   928: aaload
    //   929: astore #6
    //   931: aload #6
    //   933: invokevirtual getModifiers : ()I
    //   936: invokestatic isStatic : (I)Z
    //   939: ifne -> 949
    //   942: goto -> 1052
    //   945: invokestatic a : (Ljava/lang/Throwable;)Ljava/lang/Throwable;
    //   948: athrow
    //   949: aload #6
    //   951: invokevirtual getType : ()Ljava/lang/Class;
    //   954: astore #7
    //   956: aload #7
    //   958: ifnull -> 1039
    //   961: aload #7
    //   963: invokevirtual isPrimitive : ()Z
    //   966: ifne -> 1039
    //   969: goto -> 976
    //   972: invokestatic a : (Ljava/lang/Throwable;)Ljava/lang/Throwable;
    //   975: athrow
    //   976: aload #7
    //   978: invokevirtual getPackage : ()Ljava/lang/Package;
    //   981: ifnull -> 1039
    //   984: goto -> 991
    //   987: invokestatic a : (Ljava/lang/Throwable;)Ljava/lang/Throwable;
    //   990: athrow
    //   991: aload #7
    //   993: invokevirtual getPackage : ()Ljava/lang/Package;
    //   996: invokevirtual getName : ()Ljava/lang/String;
    //   999: ifnull -> 1039
    //   1002: goto -> 1009
    //   1005: invokestatic a : (Ljava/lang/Throwable;)Ljava/lang/Throwable;
    //   1008: athrow
    //   1009: aload #7
    //   1011: invokevirtual getPackage : ()Ljava/lang/Package;
    //   1014: invokevirtual getName : ()Ljava/lang/String;
    //   1017: sipush #-8741
    //   1020: sipush #-15370
    //   1023: invokestatic a : (II)Ljava/lang/String;
    //   1026: invokevirtual startsWith : (Ljava/lang/String;)Z
    //   1029: ifne -> 1039
    //   1032: goto -> 1039
    //   1035: invokestatic a : (Ljava/lang/Throwable;)Ljava/lang/Throwable;
    //   1038: athrow
    //   1039: aload #6
    //   1041: iconst_1
    //   1042: invokevirtual setAccessible : (Z)V
    //   1045: aload #6
    //   1047: aconst_null
    //   1048: invokevirtual get : (Ljava/lang/Object;)Ljava/lang/Object;
    //   1051: pop
    //   1052: iinc #5, 1
    //   1055: iload_2
    //   1056: ifeq -> 918
    //   1059: sipush #-8744
    //   1062: sipush #28861
    //   1065: invokestatic a : (II)Ljava/lang/String;
    //   1068: invokestatic forName : (Ljava/lang/String;)Ljava/lang/Class;
    //   1071: invokevirtual getDeclaredMethods : ()[Ljava/lang/reflect/Method;
    //   1074: astore_3
    //   1075: aload_3
    //   1076: arraylength
    //   1077: istore #4
    //   1079: iconst_0
    //   1080: istore #5
    //   1082: iload #5
    //   1084: iload #4
    //   1086: if_icmpge -> 1218
    //   1089: aload_3
    //   1090: iload #5
    //   1092: aaload
    //   1093: astore #6
    //   1095: aload #6
    //   1097: invokevirtual getParameterTypes : ()[Ljava/lang/Class;
    //   1100: pop
    //   1101: aload #6
    //   1103: invokevirtual getModifiers : ()I
    //   1106: invokestatic isStatic : (I)Z
    //   1109: ifeq -> 1204
    //   1112: aload #6
    //   1114: invokevirtual getParameterTypes : ()[Ljava/lang/Class;
    //   1117: arraylength
    //   1118: iconst_2
    //   1119: if_icmpne -> 1204
    //   1122: goto -> 1129
    //   1125: invokestatic a : (Ljava/lang/Throwable;)Ljava/lang/Throwable;
    //   1128: athrow
    //   1129: aload #6
    //   1131: invokevirtual getReturnType : ()Ljava/lang/Class;
    //   1134: getstatic java/lang/Void.TYPE : Ljava/lang/Class;
    //   1137: invokevirtual equals : (Ljava/lang/Object;)Z
    //   1140: ifeq -> 1204
    //   1143: goto -> 1150
    //   1146: invokestatic a : (Ljava/lang/Throwable;)Ljava/lang/Throwable;
    //   1149: athrow
    //   1150: aload #6
    //   1152: iconst_1
    //   1153: invokevirtual setAccessible : (Z)V
    //   1156: aload #6
    //   1158: aconst_null
    //   1159: iconst_2
    //   1160: anewarray java/lang/Object
    //   1163: dup
    //   1164: iconst_0
    //   1165: aload_0
    //   1166: aastore
    //   1167: dup
    //   1168: iconst_1
    //   1169: aload_1
    //   1170: ifnonnull -> 1188
    //   1173: goto -> 1180
    //   1176: invokestatic a : (Ljava/lang/Throwable;)Ljava/lang/Throwable;
    //   1179: athrow
    //   1180: aload_1
    //   1181: goto -> 1195
    //   1184: invokestatic a : (Ljava/lang/Throwable;)Ljava/lang/Throwable;
    //   1187: athrow
    //   1188: aload_1
    //   1189: checkcast [B
    //   1192: invokevirtual clone : ()Ljava/lang/Object;
    //   1195: aastore
    //   1196: invokevirtual invoke : (Ljava/lang/Object;[Ljava/lang/Object;)Ljava/lang/Object;
    //   1199: pop
    //   1200: iload_2
    //   1201: ifeq -> 1218
    //   1204: iinc #5, 1
    //   1207: iload_2
    //   1208: ifeq -> 1082
    //   1211: goto -> 1218
    //   1214: invokestatic a : (Ljava/lang/Throwable;)Ljava/lang/Throwable;
    //   1217: athrow
    //   1218: getstatic burp/Zgre.ZD : Ljava/lang/Object;
    //   1221: checkcast java/math/BigInteger
    //   1224: invokevirtual toByteArray : ()[B
    //   1227: astore_3
    //   1228: bipush #64
    //   1230: newarray byte
    //   1232: dup
    //   1233: iconst_0
    //   1234: bipush #-128
    //   1236: bastore
    //   1237: dup
    //   1238: iconst_1
    //   1239: iconst_0
    //   1240: bastore
    //   1241: dup
    //   1242: iconst_2
    //   1243: iconst_0
    //   1244: bastore
    //   1245: dup
    //   1246: iconst_3
    //   1247: iconst_0
    //   1248: bastore
    //   1249: dup
    //   1250: iconst_4
    //   1251: iconst_0
    //   1252: bastore
    //   1253: dup
    //   1254: iconst_5
    //   1255: iconst_0
    //   1256: bastore
    //   1257: dup
    //   1258: bipush #6
    //   1260: iconst_0
    //   1261: bastore
    //   1262: dup
    //   1263: bipush #7
    //   1265: iconst_0
    //   1266: bastore
    //   1267: dup
    //   1268: bipush #8
    //   1270: iconst_0
    //   1271: bastore
    //   1272: dup
    //   1273: bipush #9
    //   1275: iconst_0
    //   1276: bastore
    //   1277: dup
    //   1278: bipush #10
    //   1280: iconst_0
    //   1281: bastore
    //   1282: dup
    //   1283: bipush #11
    //   1285: iconst_0
    //   1286: bastore
    //   1287: dup
    //   1288: bipush #12
    //   1290: iconst_0
    //   1291: bastore
    //   1292: dup
    //   1293: bipush #13
    //   1295: iconst_0
    //   1296: bastore
    //   1297: dup
    //   1298: bipush #14
    //   1300: iconst_0
    //   1301: bastore
    //   1302: dup
    //   1303: bipush #15
    //   1305: iconst_0
    //   1306: bastore
    //   1307: dup
    //   1308: bipush #16
    //   1310: iconst_0
    //   1311: bastore
    //   1312: dup
    //   1313: bipush #17
    //   1315: iconst_0
    //   1316: bastore
    //   1317: dup
    //   1318: bipush #18
    //   1320: iconst_0
    //   1321: bastore
    //   1322: dup
    //   1323: bipush #19
    //   1325: iconst_0
    //   1326: bastore
    //   1327: dup
    //   1328: bipush #20
    //   1330: iconst_0
    //   1331: bastore
    //   1332: dup
    //   1333: bipush #21
    //   1335: iconst_0
    //   1336: bastore
    //   1337: dup
    //   1338: bipush #22
    //   1340: iconst_0
    //   1341: bastore
    //   1342: dup
    //   1343: bipush #23
    //   1345: iconst_0
    //   1346: bastore
    //   1347: dup
    //   1348: bipush #24
    //   1350: iconst_0
    //   1351: bastore
    //   1352: dup
    //   1353: bipush #25
    //   1355: iconst_0
    //   1356: bastore
    //   1357: dup
    //   1358: bipush #26
    //   1360: iconst_0
    //   1361: bastore
    //   1362: dup
    //   1363: bipush #27
    //   1365: iconst_0
    //   1366: bastore
    //   1367: dup
    //   1368: bipush #28
    //   1370: iconst_0
    //   1371: bastore
    //   1372: dup
    //   1373: bipush #29
    //   1375: iconst_0
    //   1376: bastore
    //   1377: dup
    //   1378: bipush #30
    //   1380: iconst_0
    //   1381: bastore
    //   1382: dup
    //   1383: bipush #31
    //   1385: iconst_0
    //   1386: bastore
    //   1387: dup
    //   1388: bipush #32
    //   1390: iconst_0
    //   1391: bastore
    //   1392: dup
    //   1393: bipush #33
    //   1395: iconst_0
    //   1396: bastore
    //   1397: dup
    //   1398: bipush #34
    //   1400: iconst_0
    //   1401: bastore
    //   1402: dup
    //   1403: bipush #35
    //   1405: iconst_0
    //   1406: bastore
    //   1407: dup
    //   1408: bipush #36
    //   1410: iconst_0
    //   1411: bastore
    //   1412: dup
    //   1413: bipush #37
    //   1415: iconst_0
    //   1416: bastore
    //   1417: dup
    //   1418: bipush #38
    //   1420: iconst_0
    //   1421: bastore
    //   1422: dup
    //   1423: bipush #39
    //   1425: iconst_0
    //   1426: bastore
    //   1427: dup
    //   1428: bipush #40
    //   1430: iconst_0
    //   1431: bastore
    //   1432: dup
    //   1433: bipush #41
    //   1435: iconst_0
    //   1436: bastore
    //   1437: dup
    //   1438: bipush #42
    //   1440: iconst_0
    //   1441: bastore
    //   1442: dup
    //   1443: bipush #43
    //   1445: iconst_0
    //   1446: bastore
    //   1447: dup
    //   1448: bipush #44
    //   1450: iconst_0
    //   1451: bastore
    //   1452: dup
    //   1453: bipush #45
    //   1455: iconst_0
    //   1456: bastore
    //   1457: dup
    //   1458: bipush #46
    //   1460: iconst_0
    //   1461: bastore
    //   1462: dup
    //   1463: bipush #47
    //   1465: iconst_0
    //   1466: bastore
    //   1467: dup
    //   1468: bipush #48
    //   1470: iconst_0
    //   1471: bastore
    //   1472: dup
    //   1473: bipush #49
    //   1475: iconst_0
    //   1476: bastore
    //   1477: dup
    //   1478: bipush #50
    //   1480: iconst_0
    //   1481: bastore
    //   1482: dup
    //   1483: bipush #51
    //   1485: iconst_0
    //   1486: bastore
    //   1487: dup
    //   1488: bipush #52
    //   1490: iconst_0
    //   1491: bastore
    //   1492: dup
    //   1493: bipush #53
    //   1495: iconst_0
    //   1496: bastore
    //   1497: dup
    //   1498: bipush #54
    //   1500: iconst_0
    //   1501: bastore
    //   1502: dup
    //   1503: bipush #55
    //   1505: iconst_0
    //   1506: bastore
    //   1507: dup
    //   1508: bipush #56
    //   1510: iconst_0
    //   1511: bastore
    //   1512: dup
    //   1513: bipush #57
    //   1515: iconst_0
    //   1516: bastore
    //   1517: dup
    //   1518: bipush #58
    //   1520: iconst_0
    //   1521: bastore
    //   1522: dup
    //   1523: bipush #59
    //   1525: iconst_0
    //   1526: bastore
    //   1527: dup
    //   1528: bipush #60
    //   1530: iconst_0
    //   1531: bastore
    //   1532: dup
    //   1533: bipush #61
    //   1535: iconst_0
    //   1536: bastore
    //   1537: dup
    //   1538: bipush #62
    //   1540: iconst_0
    //   1541: bastore
    //   1542: dup
    //   1543: bipush #63
    //   1545: iconst_0
    //   1546: bastore
    //   1547: astore #5
    //   1549: bipush #64
    //   1551: newarray int
    //   1553: dup
    //   1554: iconst_0
    //   1555: ldc 1116352408
    //   1557: iastore
    //   1558: dup
    //   1559: iconst_1
    //   1560: ldc 1899447441
    //   1562: iastore
    //   1563: dup
    //   1564: iconst_2
    //   1565: ldc -1245643825
    //   1567: iastore
    //   1568: dup
    //   1569: iconst_3
    //   1570: ldc -373957723
    //   1572: iastore
    //   1573: dup
    //   1574: iconst_4
    //   1575: ldc 961987163
    //   1577: iastore
    //   1578: dup
    //   1579: iconst_5
    //   1580: ldc 1508970993
    //   1582: iastore
    //   1583: dup
    //   1584: bipush #6
    //   1586: ldc -1841331548
    //   1588: iastore
    //   1589: dup
    //   1590: bipush #7
    //   1592: ldc -1424204075
    //   1594: iastore
    //   1595: dup
    //   1596: bipush #8
    //   1598: ldc -670586216
    //   1600: iastore
    //   1601: dup
    //   1602: bipush #9
    //   1604: ldc 310598401
    //   1606: iastore
    //   1607: dup
    //   1608: bipush #10
    //   1610: ldc 607225278
    //   1612: iastore
    //   1613: dup
    //   1614: bipush #11
    //   1616: ldc 1426881987
    //   1618: iastore
    //   1619: dup
    //   1620: bipush #12
    //   1622: ldc 1925078388
    //   1624: iastore
    //   1625: dup
    //   1626: bipush #13
    //   1628: ldc -2132889090
    //   1630: iastore
    //   1631: dup
    //   1632: bipush #14
    //   1634: ldc -1680079193
    //   1636: iastore
    //   1637: dup
    //   1638: bipush #15
    //   1640: ldc -1046744716
    //   1642: iastore
    //   1643: dup
    //   1644: bipush #16
    //   1646: ldc -459576895
    //   1648: iastore
    //   1649: dup
    //   1650: bipush #17
    //   1652: ldc -272742522
    //   1654: iastore
    //   1655: dup
    //   1656: bipush #18
    //   1658: ldc 264347078
    //   1660: iastore
    //   1661: dup
    //   1662: bipush #19
    //   1664: ldc 604807628
    //   1666: iastore
    //   1667: dup
    //   1668: bipush #20
    //   1670: ldc 770255983
    //   1672: iastore
    //   1673: dup
    //   1674: bipush #21
    //   1676: ldc 1249150122
    //   1678: iastore
    //   1679: dup
    //   1680: bipush #22
    //   1682: ldc 1555081692
    //   1684: iastore
    //   1685: dup
    //   1686: bipush #23
    //   1688: ldc 1996064986
    //   1690: iastore
    //   1691: dup
    //   1692: bipush #24
    //   1694: ldc -1740746414
    //   1696: iastore
    //   1697: dup
    //   1698: bipush #25
    //   1700: ldc -1473132947
    //   1702: iastore
    //   1703: dup
    //   1704: bipush #26
    //   1706: ldc -1341970488
    //   1708: iastore
    //   1709: dup
    //   1710: bipush #27
    //   1712: ldc -1084653625
    //   1714: iastore
    //   1715: dup
    //   1716: bipush #28
    //   1718: ldc -958395405
    //   1720: iastore
    //   1721: dup
    //   1722: bipush #29
    //   1724: ldc -710438585
    //   1726: iastore
    //   1727: dup
    //   1728: bipush #30
    //   1730: ldc 113926993
    //   1732: iastore
    //   1733: dup
    //   1734: bipush #31
    //   1736: ldc 338241895
    //   1738: iastore
    //   1739: dup
    //   1740: bipush #32
    //   1742: ldc 666307205
    //   1744: iastore
    //   1745: dup
    //   1746: bipush #33
    //   1748: ldc 773529912
    //   1750: iastore
    //   1751: dup
    //   1752: bipush #34
    //   1754: ldc 1294757372
    //   1756: iastore
    //   1757: dup
    //   1758: bipush #35
    //   1760: ldc 1396182291
    //   1762: iastore
    //   1763: dup
    //   1764: bipush #36
    //   1766: ldc 1695183700
    //   1768: iastore
    //   1769: dup
    //   1770: bipush #37
    //   1772: ldc 1986661051
    //   1774: iastore
    //   1775: dup
    //   1776: bipush #38
    //   1778: ldc -2117940946
    //   1780: iastore
    //   1781: dup
    //   1782: bipush #39
    //   1784: ldc -1838011259
    //   1786: iastore
    //   1787: dup
    //   1788: bipush #40
    //   1790: ldc -1564481375
    //   1792: iastore
    //   1793: dup
    //   1794: bipush #41
    //   1796: ldc -1474664885
    //   1798: iastore
    //   1799: dup
    //   1800: bipush #42
    //   1802: ldc -1035236496
    //   1804: iastore
    //   1805: dup
    //   1806: bipush #43
    //   1808: ldc -949202525
    //   1810: iastore
    //   1811: dup
    //   1812: bipush #44
    //   1814: ldc -778901479
    //   1816: iastore
    //   1817: dup
    //   1818: bipush #45
    //   1820: ldc -694614492
    //   1822: iastore
    //   1823: dup
    //   1824: bipush #46
    //   1826: ldc -200395387
    //   1828: iastore
    //   1829: dup
    //   1830: bipush #47
    //   1832: ldc 275423344
    //   1834: iastore
    //   1835: dup
    //   1836: bipush #48
    //   1838: ldc 430227734
    //   1840: iastore
    //   1841: dup
    //   1842: bipush #49
    //   1844: ldc 506948616
    //   1846: iastore
    //   1847: dup
    //   1848: bipush #50
    //   1850: ldc 659060556
    //   1852: iastore
    //   1853: dup
    //   1854: bipush #51
    //   1856: ldc 883997877
    //   1858: iastore
    //   1859: dup
    //   1860: bipush #52
    //   1862: ldc 958139571
    //   1864: iastore
    //   1865: dup
    //   1866: bipush #53
    //   1868: ldc 1322822218
    //   1870: iastore
    //   1871: dup
    //   1872: bipush #54
    //   1874: ldc 1537002063
    //   1876: iastore
    //   1877: dup
    //   1878: bipush #55
    //   1880: ldc 1747873779
    //   1882: iastore
    //   1883: dup
    //   1884: bipush #56
    //   1886: ldc 1955562222
    //   1888: iastore
    //   1889: dup
    //   1890: bipush #57
    //   1892: ldc 2024104815
    //   1894: iastore
    //   1895: dup
    //   1896: bipush #58
    //   1898: ldc -2067236844
    //   1900: iastore
    //   1901: dup
    //   1902: bipush #59
    //   1904: ldc -1933114872
    //   1906: iastore
    //   1907: dup
    //   1908: bipush #60
    //   1910: ldc -1866530822
    //   1912: iastore
    //   1913: dup
    //   1914: bipush #61
    //   1916: ldc -1538233109
    //   1918: iastore
    //   1919: dup
    //   1920: bipush #62
    //   1922: ldc -1090935817
    //   1924: iastore
    //   1925: dup
    //   1926: bipush #63
    //   1928: ldc -965641998
    //   1930: iastore
    //   1931: astore #6
    //   1933: iconst_2
    //   1934: newarray int
    //   1936: dup
    //   1937: iconst_0
    //   1938: iconst_0
    //   1939: iastore
    //   1940: dup
    //   1941: iconst_1
    //   1942: iconst_0
    //   1943: iastore
    //   1944: astore #7
    //   1946: bipush #8
    //   1948: newarray int
    //   1950: dup
    //   1951: iconst_0
    //   1952: ldc 1779033703
    //   1954: iastore
    //   1955: dup
    //   1956: iconst_1
    //   1957: ldc -1150833019
    //   1959: iastore
    //   1960: dup
    //   1961: iconst_2
    //   1962: ldc 1013904242
    //   1964: iastore
    //   1965: dup
    //   1966: iconst_3
    //   1967: ldc -1521486534
    //   1969: iastore
    //   1970: dup
    //   1971: iconst_4
    //   1972: ldc 1359893119
    //   1974: iastore
    //   1975: dup
    //   1976: iconst_5
    //   1977: ldc -1694144372
    //   1979: iastore
    //   1980: dup
    //   1981: bipush #6
    //   1983: ldc 528734635
    //   1985: iastore
    //   1986: dup
    //   1987: bipush #7
    //   1989: ldc 1541459225
    //   1991: iastore
    //   1992: astore #8
    //   1994: bipush #64
    //   1996: newarray byte
    //   1998: astore #9
    //   2000: bipush #64
    //   2002: newarray byte
    //   2004: astore #10
    //   2006: aload_3
    //   2007: arraylength
    //   2008: istore #11
    //   2010: aload #7
    //   2012: iconst_0
    //   2013: iaload
    //   2014: bipush #63
    //   2016: iand
    //   2017: istore #12
    //   2019: aload #7
    //   2021: iconst_0
    //   2022: dup2
    //   2023: iaload
    //   2024: iload #11
    //   2026: iadd
    //   2027: iastore
    //   2028: aload #7
    //   2030: iconst_0
    //   2031: dup2
    //   2032: iaload
    //   2033: iconst_m1
    //   2034: iand
    //   2035: iastore
    //   2036: aload #7
    //   2038: iconst_0
    //   2039: iaload
    //   2040: iload #11
    //   2042: if_icmpge -> 2060
    //   2045: aload #7
    //   2047: iconst_1
    //   2048: dup2
    //   2049: iaload
    //   2050: iconst_1
    //   2051: iadd
    //   2052: iastore
    //   2053: goto -> 2060
    //   2056: invokestatic a : (Ljava/lang/Throwable;)Ljava/lang/Throwable;
    //   2059: athrow
    //   2060: iconst_0
    //   2061: istore #13
    //   2063: iload #11
    //   2065: bipush #64
    //   2067: if_icmplt -> 2676
    //   2070: iconst_0
    //   2071: istore #14
    //   2073: iload #14
    //   2075: bipush #64
    //   2077: if_icmpge -> 2099
    //   2080: aload #10
    //   2082: iload #14
    //   2084: aload_3
    //   2085: iload #13
    //   2087: iload #14
    //   2089: iadd
    //   2090: baload
    //   2091: bastore
    //   2092: iinc #14, 1
    //   2095: iload_2
    //   2096: ifeq -> 2073
    //   2099: bipush #64
    //   2101: newarray int
    //   2103: astore #14
    //   2105: bipush #8
    //   2107: newarray int
    //   2109: astore #15
    //   2111: iconst_0
    //   2112: istore #16
    //   2114: iload #16
    //   2116: bipush #8
    //   2118: if_icmpge -> 2138
    //   2121: aload #15
    //   2123: iload #16
    //   2125: aload #8
    //   2127: iload #16
    //   2129: iaload
    //   2130: iastore
    //   2131: iinc #16, 1
    //   2134: iload_2
    //   2135: ifeq -> 2114
    //   2138: iconst_0
    //   2139: istore #16
    //   2141: iload #16
    //   2143: bipush #64
    //   2145: if_icmpge -> 2636
    //   2148: iload #16
    //   2150: bipush #16
    //   2152: if_icmpge -> 2233
    //   2155: aload #14
    //   2157: iload #16
    //   2159: aload #10
    //   2161: iconst_4
    //   2162: iload #16
    //   2164: imul
    //   2165: baload
    //   2166: sipush #255
    //   2169: iand
    //   2170: bipush #24
    //   2172: ishl
    //   2173: aload #10
    //   2175: iconst_4
    //   2176: iload #16
    //   2178: imul
    //   2179: iconst_1
    //   2180: iadd
    //   2181: baload
    //   2182: sipush #255
    //   2185: iand
    //   2186: bipush #16
    //   2188: ishl
    //   2189: ior
    //   2190: aload #10
    //   2192: iconst_4
    //   2193: iload #16
    //   2195: imul
    //   2196: iconst_2
    //   2197: iadd
    //   2198: baload
    //   2199: sipush #255
    //   2202: iand
    //   2203: bipush #8
    //   2205: ishl
    //   2206: ior
    //   2207: aload #10
    //   2209: iconst_4
    //   2210: iload #16
    //   2212: imul
    //   2213: iconst_3
    //   2214: iadd
    //   2215: baload
    //   2216: sipush #255
    //   2219: iand
    //   2220: ior
    //   2221: iastore
    //   2222: iload_2
    //   2223: ifeq -> 2376
    //   2226: goto -> 2233
    //   2229: invokestatic a : (Ljava/lang/Throwable;)Ljava/lang/Throwable;
    //   2232: athrow
    //   2233: aload #14
    //   2235: iload #16
    //   2237: aload #14
    //   2239: iload #16
    //   2241: iconst_2
    //   2242: isub
    //   2243: iaload
    //   2244: bipush #17
    //   2246: iushr
    //   2247: aload #14
    //   2249: iload #16
    //   2251: iconst_2
    //   2252: isub
    //   2253: iaload
    //   2254: bipush #15
    //   2256: ishl
    //   2257: ior
    //   2258: aload #14
    //   2260: iload #16
    //   2262: iconst_2
    //   2263: isub
    //   2264: iaload
    //   2265: bipush #19
    //   2267: iushr
    //   2268: aload #14
    //   2270: iload #16
    //   2272: iconst_2
    //   2273: isub
    //   2274: iaload
    //   2275: bipush #13
    //   2277: ishl
    //   2278: ior
    //   2279: ixor
    //   2280: aload #14
    //   2282: iload #16
    //   2284: iconst_2
    //   2285: isub
    //   2286: iaload
    //   2287: bipush #10
    //   2289: iushr
    //   2290: ixor
    //   2291: aload #14
    //   2293: iload #16
    //   2295: bipush #7
    //   2297: isub
    //   2298: iaload
    //   2299: iadd
    //   2300: aload #14
    //   2302: iload #16
    //   2304: bipush #15
    //   2306: isub
    //   2307: iaload
    //   2308: bipush #7
    //   2310: iushr
    //   2311: aload #14
    //   2313: iload #16
    //   2315: bipush #15
    //   2317: isub
    //   2318: iaload
    //   2319: bipush #25
    //   2321: ishl
    //   2322: ior
    //   2323: aload #14
    //   2325: iload #16
    //   2327: bipush #15
    //   2329: isub
    //   2330: iaload
    //   2331: bipush #18
    //   2333: iushr
    //   2334: aload #14
    //   2336: iload #16
    //   2338: bipush #15
    //   2340: isub
    //   2341: iaload
    //   2342: bipush #14
    //   2344: ishl
    //   2345: ior
    //   2346: ixor
    //   2347: aload #14
    //   2349: iload #16
    //   2351: bipush #15
    //   2353: isub
    //   2354: iaload
    //   2355: iconst_3
    //   2356: iushr
    //   2357: ixor
    //   2358: iadd
    //   2359: aload #14
    //   2361: iload #16
    //   2363: bipush #16
    //   2365: isub
    //   2366: iaload
    //   2367: iadd
    //   2368: iastore
    //   2369: goto -> 2376
    //   2372: invokestatic a : (Ljava/lang/Throwable;)Ljava/lang/Throwable;
    //   2375: athrow
    //   2376: aload #15
    //   2378: bipush #7
    //   2380: iaload
    //   2381: aload #15
    //   2383: iconst_4
    //   2384: iaload
    //   2385: bipush #6
    //   2387: iushr
    //   2388: aload #15
    //   2390: iconst_4
    //   2391: iaload
    //   2392: bipush #26
    //   2394: ishl
    //   2395: ior
    //   2396: aload #15
    //   2398: iconst_4
    //   2399: iaload
    //   2400: bipush #11
    //   2402: iushr
    //   2403: aload #15
    //   2405: iconst_4
    //   2406: iaload
    //   2407: bipush #21
    //   2409: ishl
    //   2410: ior
    //   2411: ixor
    //   2412: aload #15
    //   2414: iconst_4
    //   2415: iaload
    //   2416: bipush #25
    //   2418: iushr
    //   2419: aload #15
    //   2421: iconst_4
    //   2422: iaload
    //   2423: bipush #7
    //   2425: ishl
    //   2426: ior
    //   2427: ixor
    //   2428: iadd
    //   2429: aload #15
    //   2431: bipush #6
    //   2433: iaload
    //   2434: aload #15
    //   2436: iconst_4
    //   2437: iaload
    //   2438: aload #15
    //   2440: iconst_5
    //   2441: iaload
    //   2442: aload #15
    //   2444: bipush #6
    //   2446: iaload
    //   2447: ixor
    //   2448: iand
    //   2449: ixor
    //   2450: iadd
    //   2451: aload #6
    //   2453: iload #16
    //   2455: iaload
    //   2456: iadd
    //   2457: aload #14
    //   2459: iload #16
    //   2461: iaload
    //   2462: iadd
    //   2463: istore #17
    //   2465: aload #15
    //   2467: iconst_0
    //   2468: iaload
    //   2469: iconst_2
    //   2470: iushr
    //   2471: aload #15
    //   2473: iconst_0
    //   2474: iaload
    //   2475: bipush #30
    //   2477: ishl
    //   2478: ior
    //   2479: aload #15
    //   2481: iconst_0
    //   2482: iaload
    //   2483: bipush #13
    //   2485: iushr
    //   2486: aload #15
    //   2488: iconst_0
    //   2489: iaload
    //   2490: bipush #19
    //   2492: ishl
    //   2493: ior
    //   2494: ixor
    //   2495: aload #15
    //   2497: iconst_0
    //   2498: iaload
    //   2499: bipush #22
    //   2501: iushr
    //   2502: aload #15
    //   2504: iconst_0
    //   2505: iaload
    //   2506: bipush #10
    //   2508: ishl
    //   2509: ior
    //   2510: ixor
    //   2511: aload #15
    //   2513: iconst_0
    //   2514: iaload
    //   2515: aload #15
    //   2517: iconst_1
    //   2518: iaload
    //   2519: iand
    //   2520: aload #15
    //   2522: iconst_2
    //   2523: iaload
    //   2524: aload #15
    //   2526: iconst_0
    //   2527: iaload
    //   2528: aload #15
    //   2530: iconst_1
    //   2531: iaload
    //   2532: ior
    //   2533: iand
    //   2534: ior
    //   2535: iadd
    //   2536: istore #18
    //   2538: aload #15
    //   2540: iconst_3
    //   2541: dup2
    //   2542: iaload
    //   2543: iload #17
    //   2545: iadd
    //   2546: iastore
    //   2547: aload #15
    //   2549: bipush #7
    //   2551: iload #17
    //   2553: iload #18
    //   2555: iadd
    //   2556: iastore
    //   2557: aload #15
    //   2559: bipush #7
    //   2561: iaload
    //   2562: istore #17
    //   2564: aload #15
    //   2566: bipush #7
    //   2568: aload #15
    //   2570: bipush #6
    //   2572: iaload
    //   2573: iastore
    //   2574: aload #15
    //   2576: bipush #6
    //   2578: aload #15
    //   2580: iconst_5
    //   2581: iaload
    //   2582: iastore
    //   2583: aload #15
    //   2585: iconst_5
    //   2586: aload #15
    //   2588: iconst_4
    //   2589: iaload
    //   2590: iastore
    //   2591: aload #15
    //   2593: iconst_4
    //   2594: aload #15
    //   2596: iconst_3
    //   2597: iaload
    //   2598: iastore
    //   2599: aload #15
    //   2601: iconst_3
    //   2602: aload #15
    //   2604: iconst_2
    //   2605: iaload
    //   2606: iastore
    //   2607: aload #15
    //   2609: iconst_2
    //   2610: aload #15
    //   2612: iconst_1
    //   2613: iaload
    //   2614: iastore
    //   2615: aload #15
    //   2617: iconst_1
    //   2618: aload #15
    //   2620: iconst_0
    //   2621: iaload
    //   2622: iastore
    //   2623: aload #15
    //   2625: iconst_0
    //   2626: iload #17
    //   2628: iastore
    //   2629: iinc #16, 1
    //   2632: iload_2
    //   2633: ifeq -> 2141
    //   2636: iconst_0
    //   2637: istore #16
    //   2639: iload #16
    //   2641: bipush #8
    //   2643: if_icmpge -> 2666
    //   2646: aload #8
    //   2648: iload #16
    //   2650: dup2
    //   2651: iaload
    //   2652: aload #15
    //   2654: iload #16
    //   2656: iaload
    //   2657: iadd
    //   2658: iastore
    //   2659: iinc #16, 1
    //   2662: iload_2
    //   2663: ifeq -> 2639
    //   2666: iinc #13, 64
    //   2669: iinc #11, -64
    //   2672: iload_2
    //   2673: ifeq -> 2063
    //   2676: iload #11
    //   2678: ifle -> 2713
    //   2681: iconst_0
    //   2682: istore #14
    //   2684: iload #14
    //   2686: iload #11
    //   2688: if_icmpge -> 2713
    //   2691: aload #9
    //   2693: iload #12
    //   2695: iload #14
    //   2697: iadd
    //   2698: aload_3
    //   2699: iload #13
    //   2701: iload #14
    //   2703: iadd
    //   2704: baload
    //   2705: bastore
    //   2706: iinc #14, 1
    //   2709: iload_2
    //   2710: ifeq -> 2684
    //   2713: aload #7
    //   2715: iconst_0
    //   2716: iaload
    //   2717: bipush #29
    //   2719: iushr
    //   2720: aload #7
    //   2722: iconst_1
    //   2723: iaload
    //   2724: iconst_3
    //   2725: ishl
    //   2726: ior
    //   2727: istore #14
    //   2729: aload #7
    //   2731: iconst_0
    //   2732: iaload
    //   2733: iconst_3
    //   2734: ishl
    //   2735: istore #15
    //   2737: aload #7
    //   2739: iconst_0
    //   2740: iaload
    //   2741: bipush #63
    //   2743: iand
    //   2744: istore #16
    //   2746: iload #16
    //   2748: bipush #56
    //   2750: if_icmpge -> 2765
    //   2753: bipush #56
    //   2755: iload #16
    //   2757: isub
    //   2758: goto -> 2770
    //   2761: invokestatic a : (Ljava/lang/Throwable;)Ljava/lang/Throwable;
    //   2764: athrow
    //   2765: bipush #120
    //   2767: iload #16
    //   2769: isub
    //   2770: istore #17
    //   2772: aload #7
    //   2774: iconst_0
    //   2775: iaload
    //   2776: bipush #63
    //   2778: iand
    //   2779: istore #12
    //   2781: bipush #64
    //   2783: iload #12
    //   2785: isub
    //   2786: istore #18
    //   2788: aload #7
    //   2790: iconst_0
    //   2791: dup2
    //   2792: iaload
    //   2793: iload #17
    //   2795: iadd
    //   2796: iastore
    //   2797: aload #7
    //   2799: iconst_0
    //   2800: dup2
    //   2801: iaload
    //   2802: iconst_m1
    //   2803: iand
    //   2804: iastore
    //   2805: aload #7
    //   2807: iconst_0
    //   2808: iaload
    //   2809: iload #17
    //   2811: if_icmpge -> 2829
    //   2814: aload #7
    //   2816: iconst_1
    //   2817: dup2
    //   2818: iaload
    //   2819: iconst_1
    //   2820: iadd
    //   2821: iastore
    //   2822: goto -> 2829
    //   2825: invokestatic a : (Ljava/lang/Throwable;)Ljava/lang/Throwable;
    //   2828: athrow
    //   2829: iconst_0
    //   2830: istore #13
    //   2832: iload #12
    //   2834: ifle -> 3465
    //   2837: iload #17
    //   2839: iload #18
    //   2841: if_icmplt -> 3465
    //   2844: goto -> 2851
    //   2847: invokestatic a : (Ljava/lang/Throwable;)Ljava/lang/Throwable;
    //   2850: athrow
    //   2851: iconst_0
    //   2852: istore #19
    //   2854: iload #19
    //   2856: iload #18
    //   2858: if_icmpge -> 2881
    //   2861: aload #9
    //   2863: iload #12
    //   2865: iload #19
    //   2867: iadd
    //   2868: aload #5
    //   2870: iload #19
    //   2872: baload
    //   2873: bastore
    //   2874: iinc #19, 1
    //   2877: iload_2
    //   2878: ifeq -> 2854
    //   2881: bipush #64
    //   2883: newarray int
    //   2885: astore #19
    //   2887: bipush #8
    //   2889: newarray int
    //   2891: astore #20
    //   2893: iconst_0
    //   2894: istore #21
    //   2896: iload #21
    //   2898: bipush #8
    //   2900: if_icmpge -> 2920
    //   2903: aload #20
    //   2905: iload #21
    //   2907: aload #8
    //   2909: iload #21
    //   2911: iaload
    //   2912: iastore
    //   2913: iinc #21, 1
    //   2916: iload_2
    //   2917: ifeq -> 2896
    //   2920: iconst_0
    //   2921: istore #21
    //   2923: iload #21
    //   2925: bipush #64
    //   2927: if_icmpge -> 3418
    //   2930: iload #21
    //   2932: bipush #16
    //   2934: if_icmpge -> 3015
    //   2937: aload #19
    //   2939: iload #21
    //   2941: aload #9
    //   2943: iconst_4
    //   2944: iload #21
    //   2946: imul
    //   2947: baload
    //   2948: sipush #255
    //   2951: iand
    //   2952: bipush #24
    //   2954: ishl
    //   2955: aload #9
    //   2957: iconst_4
    //   2958: iload #21
    //   2960: imul
    //   2961: iconst_1
    //   2962: iadd
    //   2963: baload
    //   2964: sipush #255
    //   2967: iand
    //   2968: bipush #16
    //   2970: ishl
    //   2971: ior
    //   2972: aload #9
    //   2974: iconst_4
    //   2975: iload #21
    //   2977: imul
    //   2978: iconst_2
    //   2979: iadd
    //   2980: baload
    //   2981: sipush #255
    //   2984: iand
    //   2985: bipush #8
    //   2987: ishl
    //   2988: ior
    //   2989: aload #9
    //   2991: iconst_4
    //   2992: iload #21
    //   2994: imul
    //   2995: iconst_3
    //   2996: iadd
    //   2997: baload
    //   2998: sipush #255
    //   3001: iand
    //   3002: ior
    //   3003: iastore
    //   3004: iload_2
    //   3005: ifeq -> 3158
    //   3008: goto -> 3015
    //   3011: invokestatic a : (Ljava/lang/Throwable;)Ljava/lang/Throwable;
    //   3014: athrow
    //   3015: aload #19
    //   3017: iload #21
    //   3019: aload #19
    //   3021: iload #21
    //   3023: iconst_2
    //   3024: isub
    //   3025: iaload
    //   3026: bipush #17
    //   3028: iushr
    //   3029: aload #19
    //   3031: iload #21
    //   3033: iconst_2
    //   3034: isub
    //   3035: iaload
    //   3036: bipush #15
    //   3038: ishl
    //   3039: ior
    //   3040: aload #19
    //   3042: iload #21
    //   3044: iconst_2
    //   3045: isub
    //   3046: iaload
    //   3047: bipush #19
    //   3049: iushr
    //   3050: aload #19
    //   3052: iload #21
    //   3054: iconst_2
    //   3055: isub
    //   3056: iaload
    //   3057: bipush #13
    //   3059: ishl
    //   3060: ior
    //   3061: ixor
    //   3062: aload #19
    //   3064: iload #21
    //   3066: iconst_2
    //   3067: isub
    //   3068: iaload
    //   3069: bipush #10
    //   3071: iushr
    //   3072: ixor
    //   3073: aload #19
    //   3075: iload #21
    //   3077: bipush #7
    //   3079: isub
    //   3080: iaload
    //   3081: iadd
    //   3082: aload #19
    //   3084: iload #21
    //   3086: bipush #15
    //   3088: isub
    //   3089: iaload
    //   3090: bipush #7
    //   3092: iushr
    //   3093: aload #19
    //   3095: iload #21
    //   3097: bipush #15
    //   3099: isub
    //   3100: iaload
    //   3101: bipush #25
    //   3103: ishl
    //   3104: ior
    //   3105: aload #19
    //   3107: iload #21
    //   3109: bipush #15
    //   3111: isub
    //   3112: iaload
    //   3113: bipush #18
    //   3115: iushr
    //   3116: aload #19
    //   3118: iload #21
    //   3120: bipush #15
    //   3122: isub
    //   3123: iaload
    //   3124: bipush #14
    //   3126: ishl
    //   3127: ior
    //   3128: ixor
    //   3129: aload #19
    //   3131: iload #21
    //   3133: bipush #15
    //   3135: isub
    //   3136: iaload
    //   3137: iconst_3
    //   3138: iushr
    //   3139: ixor
    //   3140: iadd
    //   3141: aload #19
    //   3143: iload #21
    //   3145: bipush #16
    //   3147: isub
    //   3148: iaload
    //   3149: iadd
    //   3150: iastore
    //   3151: goto -> 3158
    //   3154: invokestatic a : (Ljava/lang/Throwable;)Ljava/lang/Throwable;
    //   3157: athrow
    //   3158: aload #20
    //   3160: bipush #7
    //   3162: iaload
    //   3163: aload #20
    //   3165: iconst_4
    //   3166: iaload
    //   3167: bipush #6
    //   3169: iushr
    //   3170: aload #20
    //   3172: iconst_4
    //   3173: iaload
    //   3174: bipush #26
    //   3176: ishl
    //   3177: ior
    //   3178: aload #20
    //   3180: iconst_4
    //   3181: iaload
    //   3182: bipush #11
    //   3184: iushr
    //   3185: aload #20
    //   3187: iconst_4
    //   3188: iaload
    //   3189: bipush #21
    //   3191: ishl
    //   3192: ior
    //   3193: ixor
    //   3194: aload #20
    //   3196: iconst_4
    //   3197: iaload
    //   3198: bipush #25
    //   3200: iushr
    //   3201: aload #20
    //   3203: iconst_4
    //   3204: iaload
    //   3205: bipush #7
    //   3207: ishl
    //   3208: ior
    //   3209: ixor
    //   3210: iadd
    //   3211: aload #20
    //   3213: bipush #6
    //   3215: iaload
    //   3216: aload #20
    //   3218: iconst_4
    //   3219: iaload
    //   3220: aload #20
    //   3222: iconst_5
    //   3223: iaload
    //   3224: aload #20
    //   3226: bipush #6
    //   3228: iaload
    //   3229: ixor
    //   3230: iand
    //   3231: ixor
    //   3232: iadd
    //   3233: aload #6
    //   3235: iload #21
    //   3237: iaload
    //   3238: iadd
    //   3239: aload #19
    //   3241: iload #21
    //   3243: iaload
    //   3244: iadd
    //   3245: istore #22
    //   3247: aload #20
    //   3249: iconst_0
    //   3250: iaload
    //   3251: iconst_2
    //   3252: iushr
    //   3253: aload #20
    //   3255: iconst_0
    //   3256: iaload
    //   3257: bipush #30
    //   3259: ishl
    //   3260: ior
    //   3261: aload #20
    //   3263: iconst_0
    //   3264: iaload
    //   3265: bipush #13
    //   3267: iushr
    //   3268: aload #20
    //   3270: iconst_0
    //   3271: iaload
    //   3272: bipush #19
    //   3274: ishl
    //   3275: ior
    //   3276: ixor
    //   3277: aload #20
    //   3279: iconst_0
    //   3280: iaload
    //   3281: bipush #22
    //   3283: iushr
    //   3284: aload #20
    //   3286: iconst_0
    //   3287: iaload
    //   3288: bipush #10
    //   3290: ishl
    //   3291: ior
    //   3292: ixor
    //   3293: aload #20
    //   3295: iconst_0
    //   3296: iaload
    //   3297: aload #20
    //   3299: iconst_1
    //   3300: iaload
    //   3301: iand
    //   3302: aload #20
    //   3304: iconst_2
    //   3305: iaload
    //   3306: aload #20
    //   3308: iconst_0
    //   3309: iaload
    //   3310: aload #20
    //   3312: iconst_1
    //   3313: iaload
    //   3314: ior
    //   3315: iand
    //   3316: ior
    //   3317: iadd
    //   3318: istore #23
    //   3320: aload #20
    //   3322: iconst_3
    //   3323: dup2
    //   3324: iaload
    //   3325: iload #22
    //   3327: iadd
    //   3328: iastore
    //   3329: aload #20
    //   3331: bipush #7
    //   3333: iload #22
    //   3335: iload #23
    //   3337: iadd
    //   3338: iastore
    //   3339: aload #20
    //   3341: bipush #7
    //   3343: iaload
    //   3344: istore #22
    //   3346: aload #20
    //   3348: bipush #7
    //   3350: aload #20
    //   3352: bipush #6
    //   3354: iaload
    //   3355: iastore
    //   3356: aload #20
    //   3358: bipush #6
    //   3360: aload #20
    //   3362: iconst_5
    //   3363: iaload
    //   3364: iastore
    //   3365: aload #20
    //   3367: iconst_5
    //   3368: aload #20
    //   3370: iconst_4
    //   3371: iaload
    //   3372: iastore
    //   3373: aload #20
    //   3375: iconst_4
    //   3376: aload #20
    //   3378: iconst_3
    //   3379: iaload
    //   3380: iastore
    //   3381: aload #20
    //   3383: iconst_3
    //   3384: aload #20
    //   3386: iconst_2
    //   3387: iaload
    //   3388: iastore
    //   3389: aload #20
    //   3391: iconst_2
    //   3392: aload #20
    //   3394: iconst_1
    //   3395: iaload
    //   3396: iastore
    //   3397: aload #20
    //   3399: iconst_1
    //   3400: aload #20
    //   3402: iconst_0
    //   3403: iaload
    //   3404: iastore
    //   3405: aload #20
    //   3407: iconst_0
    //   3408: iload #22
    //   3410: iastore
    //   3411: iinc #21, 1
    //   3414: iload_2
    //   3415: ifeq -> 2923
    //   3418: iconst_0
    //   3419: istore #21
    //   3421: iload #21
    //   3423: bipush #8
    //   3425: if_icmpge -> 3448
    //   3428: aload #8
    //   3430: iload #21
    //   3432: dup2
    //   3433: iaload
    //   3434: aload #20
    //   3436: iload #21
    //   3438: iaload
    //   3439: iadd
    //   3440: iastore
    //   3441: iinc #21, 1
    //   3444: iload_2
    //   3445: ifeq -> 3421
    //   3448: iload #13
    //   3450: iload #18
    //   3452: iadd
    //   3453: istore #13
    //   3455: iload #17
    //   3457: iload #18
    //   3459: isub
    //   3460: istore #17
    //   3462: iconst_0
    //   3463: istore #12
    //   3465: iload #17
    //   3467: bipush #64
    //   3469: if_icmplt -> 4079
    //   3472: iconst_0
    //   3473: istore #19
    //   3475: iload #19
    //   3477: bipush #64
    //   3479: if_icmpge -> 3502
    //   3482: aload #10
    //   3484: iload #19
    //   3486: aload #5
    //   3488: iload #13
    //   3490: iload #19
    //   3492: iadd
    //   3493: baload
    //   3494: bastore
    //   3495: iinc #19, 1
    //   3498: iload_2
    //   3499: ifeq -> 3475
    //   3502: bipush #64
    //   3504: newarray int
    //   3506: astore #19
    //   3508: bipush #8
    //   3510: newarray int
    //   3512: astore #20
    //   3514: iconst_0
    //   3515: istore #21
    //   3517: iload #21
    //   3519: bipush #8
    //   3521: if_icmpge -> 3541
    //   3524: aload #20
    //   3526: iload #21
    //   3528: aload #8
    //   3530: iload #21
    //   3532: iaload
    //   3533: iastore
    //   3534: iinc #21, 1
    //   3537: iload_2
    //   3538: ifeq -> 3517
    //   3541: iconst_0
    //   3542: istore #21
    //   3544: iload #21
    //   3546: bipush #64
    //   3548: if_icmpge -> 4039
    //   3551: iload #21
    //   3553: bipush #16
    //   3555: if_icmpge -> 3636
    //   3558: aload #19
    //   3560: iload #21
    //   3562: aload #10
    //   3564: iconst_4
    //   3565: iload #21
    //   3567: imul
    //   3568: baload
    //   3569: sipush #255
    //   3572: iand
    //   3573: bipush #24
    //   3575: ishl
    //   3576: aload #10
    //   3578: iconst_4
    //   3579: iload #21
    //   3581: imul
    //   3582: iconst_1
    //   3583: iadd
    //   3584: baload
    //   3585: sipush #255
    //   3588: iand
    //   3589: bipush #16
    //   3591: ishl
    //   3592: ior
    //   3593: aload #10
    //   3595: iconst_4
    //   3596: iload #21
    //   3598: imul
    //   3599: iconst_2
    //   3600: iadd
    //   3601: baload
    //   3602: sipush #255
    //   3605: iand
    //   3606: bipush #8
    //   3608: ishl
    //   3609: ior
    //   3610: aload #10
    //   3612: iconst_4
    //   3613: iload #21
    //   3615: imul
    //   3616: iconst_3
    //   3617: iadd
    //   3618: baload
    //   3619: sipush #255
    //   3622: iand
    //   3623: ior
    //   3624: iastore
    //   3625: iload_2
    //   3626: ifeq -> 3779
    //   3629: goto -> 3636
    //   3632: invokestatic a : (Ljava/lang/Throwable;)Ljava/lang/Throwable;
    //   3635: athrow
    //   3636: aload #19
    //   3638: iload #21
    //   3640: aload #19
    //   3642: iload #21
    //   3644: iconst_2
    //   3645: isub
    //   3646: iaload
    //   3647: bipush #17
    //   3649: iushr
    //   3650: aload #19
    //   3652: iload #21
    //   3654: iconst_2
    //   3655: isub
    //   3656: iaload
    //   3657: bipush #15
    //   3659: ishl
    //   3660: ior
    //   3661: aload #19
    //   3663: iload #21
    //   3665: iconst_2
    //   3666: isub
    //   3667: iaload
    //   3668: bipush #19
    //   3670: iushr
    //   3671: aload #19
    //   3673: iload #21
    //   3675: iconst_2
    //   3676: isub
    //   3677: iaload
    //   3678: bipush #13
    //   3680: ishl
    //   3681: ior
    //   3682: ixor
    //   3683: aload #19
    //   3685: iload #21
    //   3687: iconst_2
    //   3688: isub
    //   3689: iaload
    //   3690: bipush #10
    //   3692: iushr
    //   3693: ixor
    //   3694: aload #19
    //   3696: iload #21
    //   3698: bipush #7
    //   3700: isub
    //   3701: iaload
    //   3702: iadd
    //   3703: aload #19
    //   3705: iload #21
    //   3707: bipush #15
    //   3709: isub
    //   3710: iaload
    //   3711: bipush #7
    //   3713: iushr
    //   3714: aload #19
    //   3716: iload #21
    //   3718: bipush #15
    //   3720: isub
    //   3721: iaload
    //   3722: bipush #25
    //   3724: ishl
    //   3725: ior
    //   3726: aload #19
    //   3728: iload #21
    //   3730: bipush #15
    //   3732: isub
    //   3733: iaload
    //   3734: bipush #18
    //   3736: iushr
    //   3737: aload #19
    //   3739: iload #21
    //   3741: bipush #15
    //   3743: isub
    //   3744: iaload
    //   3745: bipush #14
    //   3747: ishl
    //   3748: ior
    //   3749: ixor
    //   3750: aload #19
    //   3752: iload #21
    //   3754: bipush #15
    //   3756: isub
    //   3757: iaload
    //   3758: iconst_3
    //   3759: iushr
    //   3760: ixor
    //   3761: iadd
    //   3762: aload #19
    //   3764: iload #21
    //   3766: bipush #16
    //   3768: isub
    //   3769: iaload
    //   3770: iadd
    //   3771: iastore
    //   3772: goto -> 3779
    //   3775: invokestatic a : (Ljava/lang/Throwable;)Ljava/lang/Throwable;
    //   3778: athrow
    //   3779: aload #20
    //   3781: bipush #7
    //   3783: iaload
    //   3784: aload #20
    //   3786: iconst_4
    //   3787: iaload
    //   3788: bipush #6
    //   3790: iushr
    //   3791: aload #20
    //   3793: iconst_4
    //   3794: iaload
    //   3795: bipush #26
    //   3797: ishl
    //   3798: ior
    //   3799: aload #20
    //   3801: iconst_4
    //   3802: iaload
    //   3803: bipush #11
    //   3805: iushr
    //   3806: aload #20
    //   3808: iconst_4
    //   3809: iaload
    //   3810: bipush #21
    //   3812: ishl
    //   3813: ior
    //   3814: ixor
    //   3815: aload #20
    //   3817: iconst_4
    //   3818: iaload
    //   3819: bipush #25
    //   3821: iushr
    //   3822: aload #20
    //   3824: iconst_4
    //   3825: iaload
    //   3826: bipush #7
    //   3828: ishl
    //   3829: ior
    //   3830: ixor
    //   3831: iadd
    //   3832: aload #20
    //   3834: bipush #6
    //   3836: iaload
    //   3837: aload #20
    //   3839: iconst_4
    //   3840: iaload
    //   3841: aload #20
    //   3843: iconst_5
    //   3844: iaload
    //   3845: aload #20
    //   3847: bipush #6
    //   3849: iaload
    //   3850: ixor
    //   3851: iand
    //   3852: ixor
    //   3853: iadd
    //   3854: aload #6
    //   3856: iload #21
    //   3858: iaload
    //   3859: iadd
    //   3860: aload #19
    //   3862: iload #21
    //   3864: iaload
    //   3865: iadd
    //   3866: istore #22
    //   3868: aload #20
    //   3870: iconst_0
    //   3871: iaload
    //   3872: iconst_2
    //   3873: iushr
    //   3874: aload #20
    //   3876: iconst_0
    //   3877: iaload
    //   3878: bipush #30
    //   3880: ishl
    //   3881: ior
    //   3882: aload #20
    //   3884: iconst_0
    //   3885: iaload
    //   3886: bipush #13
    //   3888: iushr
    //   3889: aload #20
    //   3891: iconst_0
    //   3892: iaload
    //   3893: bipush #19
    //   3895: ishl
    //   3896: ior
    //   3897: ixor
    //   3898: aload #20
    //   3900: iconst_0
    //   3901: iaload
    //   3902: bipush #22
    //   3904: iushr
    //   3905: aload #20
    //   3907: iconst_0
    //   3908: iaload
    //   3909: bipush #10
    //   3911: ishl
    //   3912: ior
    //   3913: ixor
    //   3914: aload #20
    //   3916: iconst_0
    //   3917: iaload
    //   3918: aload #20
    //   3920: iconst_1
    //   3921: iaload
    //   3922: iand
    //   3923: aload #20
    //   3925: iconst_2
    //   3926: iaload
    //   3927: aload #20
    //   3929: iconst_0
    //   3930: iaload
    //   3931: aload #20
    //   3933: iconst_1
    //   3934: iaload
    //   3935: ior
    //   3936: iand
    //   3937: ior
    //   3938: iadd
    //   3939: istore #23
    //   3941: aload #20
    //   3943: iconst_3
    //   3944: dup2
    //   3945: iaload
    //   3946: iload #22
    //   3948: iadd
    //   3949: iastore
    //   3950: aload #20
    //   3952: bipush #7
    //   3954: iload #22
    //   3956: iload #23
    //   3958: iadd
    //   3959: iastore
    //   3960: aload #20
    //   3962: bipush #7
    //   3964: iaload
    //   3965: istore #22
    //   3967: aload #20
    //   3969: bipush #7
    //   3971: aload #20
    //   3973: bipush #6
    //   3975: iaload
    //   3976: iastore
    //   3977: aload #20
    //   3979: bipush #6
    //   3981: aload #20
    //   3983: iconst_5
    //   3984: iaload
    //   3985: iastore
    //   3986: aload #20
    //   3988: iconst_5
    //   3989: aload #20
    //   3991: iconst_4
    //   3992: iaload
    //   3993: iastore
    //   3994: aload #20
    //   3996: iconst_4
    //   3997: aload #20
    //   3999: iconst_3
    //   4000: iaload
    //   4001: iastore
    //   4002: aload #20
    //   4004: iconst_3
    //   4005: aload #20
    //   4007: iconst_2
    //   4008: iaload
    //   4009: iastore
    //   4010: aload #20
    //   4012: iconst_2
    //   4013: aload #20
    //   4015: iconst_1
    //   4016: iaload
    //   4017: iastore
    //   4018: aload #20
    //   4020: iconst_1
    //   4021: aload #20
    //   4023: iconst_0
    //   4024: iaload
    //   4025: iastore
    //   4026: aload #20
    //   4028: iconst_0
    //   4029: iload #22
    //   4031: iastore
    //   4032: iinc #21, 1
    //   4035: iload_2
    //   4036: ifeq -> 3544
    //   4039: iconst_0
    //   4040: istore #21
    //   4042: iload #21
    //   4044: bipush #8
    //   4046: if_icmpge -> 4069
    //   4049: aload #8
    //   4051: iload #21
    //   4053: dup2
    //   4054: iaload
    //   4055: aload #20
    //   4057: iload #21
    //   4059: iaload
    //   4060: iadd
    //   4061: iastore
    //   4062: iinc #21, 1
    //   4065: iload_2
    //   4066: ifeq -> 4042
    //   4069: iinc #13, 64
    //   4072: iinc #17, -64
    //   4075: iload_2
    //   4076: ifeq -> 3465
    //   4079: iload #17
    //   4081: ifle -> 4117
    //   4084: iconst_0
    //   4085: istore #19
    //   4087: iload #19
    //   4089: iload #17
    //   4091: if_icmpge -> 4117
    //   4094: aload #9
    //   4096: iload #12
    //   4098: iload #19
    //   4100: iadd
    //   4101: aload #5
    //   4103: iload #13
    //   4105: iload #19
    //   4107: iadd
    //   4108: baload
    //   4109: bastore
    //   4110: iinc #19, 1
    //   4113: iload_2
    //   4114: ifeq -> 4087
    //   4117: bipush #8
    //   4119: newarray byte
    //   4121: astore #19
    //   4123: aload #19
    //   4125: iconst_0
    //   4126: iload #14
    //   4128: bipush #24
    //   4130: iushr
    //   4131: i2b
    //   4132: bastore
    //   4133: aload #19
    //   4135: iconst_1
    //   4136: iload #14
    //   4138: bipush #16
    //   4140: iushr
    //   4141: i2b
    //   4142: bastore
    //   4143: aload #19
    //   4145: iconst_2
    //   4146: iload #14
    //   4148: bipush #8
    //   4150: iushr
    //   4151: i2b
    //   4152: bastore
    //   4153: aload #19
    //   4155: iconst_3
    //   4156: iload #14
    //   4158: i2b
    //   4159: bastore
    //   4160: aload #19
    //   4162: iconst_4
    //   4163: iload #15
    //   4165: bipush #24
    //   4167: iushr
    //   4168: i2b
    //   4169: bastore
    //   4170: aload #19
    //   4172: iconst_5
    //   4173: iload #15
    //   4175: bipush #16
    //   4177: iushr
    //   4178: i2b
    //   4179: bastore
    //   4180: aload #19
    //   4182: bipush #6
    //   4184: iload #15
    //   4186: bipush #8
    //   4188: iushr
    //   4189: i2b
    //   4190: bastore
    //   4191: aload #19
    //   4193: bipush #7
    //   4195: iload #15
    //   4197: i2b
    //   4198: bastore
    //   4199: bipush #8
    //   4201: istore #11
    //   4203: aload #7
    //   4205: iconst_0
    //   4206: iaload
    //   4207: bipush #63
    //   4209: iand
    //   4210: istore #12
    //   4212: bipush #64
    //   4214: iload #12
    //   4216: isub
    //   4217: istore #18
    //   4219: aload #7
    //   4221: iconst_0
    //   4222: dup2
    //   4223: iaload
    //   4224: iload #11
    //   4226: iadd
    //   4227: iastore
    //   4228: aload #7
    //   4230: iconst_0
    //   4231: dup2
    //   4232: iaload
    //   4233: iconst_m1
    //   4234: iand
    //   4235: iastore
    //   4236: aload #7
    //   4238: iconst_0
    //   4239: iaload
    //   4240: iload #11
    //   4242: if_icmpge -> 4260
    //   4245: aload #7
    //   4247: iconst_1
    //   4248: dup2
    //   4249: iaload
    //   4250: iconst_1
    //   4251: iadd
    //   4252: iastore
    //   4253: goto -> 4260
    //   4256: invokestatic a : (Ljava/lang/Throwable;)Ljava/lang/Throwable;
    //   4259: athrow
    //   4260: iload #12
    //   4262: ifle -> 4876
    //   4265: iload #11
    //   4267: iload #18
    //   4269: if_icmplt -> 4876
    //   4272: goto -> 4279
    //   4275: invokestatic a : (Ljava/lang/Throwable;)Ljava/lang/Throwable;
    //   4278: athrow
    //   4279: iconst_0
    //   4280: istore #20
    //   4282: iload #20
    //   4284: iload #18
    //   4286: if_icmpge -> 4309
    //   4289: aload #9
    //   4291: iload #12
    //   4293: iload #20
    //   4295: iadd
    //   4296: aload #19
    //   4298: iload #20
    //   4300: baload
    //   4301: bastore
    //   4302: iinc #20, 1
    //   4305: iload_2
    //   4306: ifeq -> 4282
    //   4309: bipush #64
    //   4311: newarray int
    //   4313: astore #20
    //   4315: bipush #8
    //   4317: newarray int
    //   4319: astore #21
    //   4321: iconst_0
    //   4322: istore #22
    //   4324: iload #22
    //   4326: bipush #8
    //   4328: if_icmpge -> 4348
    //   4331: aload #21
    //   4333: iload #22
    //   4335: aload #8
    //   4337: iload #22
    //   4339: iaload
    //   4340: iastore
    //   4341: iinc #22, 1
    //   4344: iload_2
    //   4345: ifeq -> 4324
    //   4348: iconst_0
    //   4349: istore #22
    //   4351: iload #22
    //   4353: bipush #64
    //   4355: if_icmpge -> 4846
    //   4358: iload #22
    //   4360: bipush #16
    //   4362: if_icmpge -> 4443
    //   4365: aload #20
    //   4367: iload #22
    //   4369: aload #9
    //   4371: iconst_4
    //   4372: iload #22
    //   4374: imul
    //   4375: baload
    //   4376: sipush #255
    //   4379: iand
    //   4380: bipush #24
    //   4382: ishl
    //   4383: aload #9
    //   4385: iconst_4
    //   4386: iload #22
    //   4388: imul
    //   4389: iconst_1
    //   4390: iadd
    //   4391: baload
    //   4392: sipush #255
    //   4395: iand
    //   4396: bipush #16
    //   4398: ishl
    //   4399: ior
    //   4400: aload #9
    //   4402: iconst_4
    //   4403: iload #22
    //   4405: imul
    //   4406: iconst_2
    //   4407: iadd
    //   4408: baload
    //   4409: sipush #255
    //   4412: iand
    //   4413: bipush #8
    //   4415: ishl
    //   4416: ior
    //   4417: aload #9
    //   4419: iconst_4
    //   4420: iload #22
    //   4422: imul
    //   4423: iconst_3
    //   4424: iadd
    //   4425: baload
    //   4426: sipush #255
    //   4429: iand
    //   4430: ior
    //   4431: iastore
    //   4432: iload_2
    //   4433: ifeq -> 4586
    //   4436: goto -> 4443
    //   4439: invokestatic a : (Ljava/lang/Throwable;)Ljava/lang/Throwable;
    //   4442: athrow
    //   4443: aload #20
    //   4445: iload #22
    //   4447: aload #20
    //   4449: iload #22
    //   4451: iconst_2
    //   4452: isub
    //   4453: iaload
    //   4454: bipush #17
    //   4456: iushr
    //   4457: aload #20
    //   4459: iload #22
    //   4461: iconst_2
    //   4462: isub
    //   4463: iaload
    //   4464: bipush #15
    //   4466: ishl
    //   4467: ior
    //   4468: aload #20
    //   4470: iload #22
    //   4472: iconst_2
    //   4473: isub
    //   4474: iaload
    //   4475: bipush #19
    //   4477: iushr
    //   4478: aload #20
    //   4480: iload #22
    //   4482: iconst_2
    //   4483: isub
    //   4484: iaload
    //   4485: bipush #13
    //   4487: ishl
    //   4488: ior
    //   4489: ixor
    //   4490: aload #20
    //   4492: iload #22
    //   4494: iconst_2
    //   4495: isub
    //   4496: iaload
    //   4497: bipush #10
    //   4499: iushr
    //   4500: ixor
    //   4501: aload #20
    //   4503: iload #22
    //   4505: bipush #7
    //   4507: isub
    //   4508: iaload
    //   4509: iadd
    //   4510: aload #20
    //   4512: iload #22
    //   4514: bipush #15
    //   4516: isub
    //   4517: iaload
    //   4518: bipush #7
    //   4520: iushr
    //   4521: aload #20
    //   4523: iload #22
    //   4525: bipush #15
    //   4527: isub
    //   4528: iaload
    //   4529: bipush #25
    //   4531: ishl
    //   4532: ior
    //   4533: aload #20
    //   4535: iload #22
    //   4537: bipush #15
    //   4539: isub
    //   4540: iaload
    //   4541: bipush #18
    //   4543: iushr
    //   4544: aload #20
    //   4546: iload #22
    //   4548: bipush #15
    //   4550: isub
    //   4551: iaload
    //   4552: bipush #14
    //   4554: ishl
    //   4555: ior
    //   4556: ixor
    //   4557: aload #20
    //   4559: iload #22
    //   4561: bipush #15
    //   4563: isub
    //   4564: iaload
    //   4565: iconst_3
    //   4566: iushr
    //   4567: ixor
    //   4568: iadd
    //   4569: aload #20
    //   4571: iload #22
    //   4573: bipush #16
    //   4575: isub
    //   4576: iaload
    //   4577: iadd
    //   4578: iastore
    //   4579: goto -> 4586
    //   4582: invokestatic a : (Ljava/lang/Throwable;)Ljava/lang/Throwable;
    //   4585: athrow
    //   4586: aload #21
    //   4588: bipush #7
    //   4590: iaload
    //   4591: aload #21
    //   4593: iconst_4
    //   4594: iaload
    //   4595: bipush #6
    //   4597: iushr
    //   4598: aload #21
    //   4600: iconst_4
    //   4601: iaload
    //   4602: bipush #26
    //   4604: ishl
    //   4605: ior
    //   4606: aload #21
    //   4608: iconst_4
    //   4609: iaload
    //   4610: bipush #11
    //   4612: iushr
    //   4613: aload #21
    //   4615: iconst_4
    //   4616: iaload
    //   4617: bipush #21
    //   4619: ishl
    //   4620: ior
    //   4621: ixor
    //   4622: aload #21
    //   4624: iconst_4
    //   4625: iaload
    //   4626: bipush #25
    //   4628: iushr
    //   4629: aload #21
    //   4631: iconst_4
    //   4632: iaload
    //   4633: bipush #7
    //   4635: ishl
    //   4636: ior
    //   4637: ixor
    //   4638: iadd
    //   4639: aload #21
    //   4641: bipush #6
    //   4643: iaload
    //   4644: aload #21
    //   4646: iconst_4
    //   4647: iaload
    //   4648: aload #21
    //   4650: iconst_5
    //   4651: iaload
    //   4652: aload #21
    //   4654: bipush #6
    //   4656: iaload
    //   4657: ixor
    //   4658: iand
    //   4659: ixor
    //   4660: iadd
    //   4661: aload #6
    //   4663: iload #22
    //   4665: iaload
    //   4666: iadd
    //   4667: aload #20
    //   4669: iload #22
    //   4671: iaload
    //   4672: iadd
    //   4673: istore #23
    //   4675: aload #21
    //   4677: iconst_0
    //   4678: iaload
    //   4679: iconst_2
    //   4680: iushr
    //   4681: aload #21
    //   4683: iconst_0
    //   4684: iaload
    //   4685: bipush #30
    //   4687: ishl
    //   4688: ior
    //   4689: aload #21
    //   4691: iconst_0
    //   4692: iaload
    //   4693: bipush #13
    //   4695: iushr
    //   4696: aload #21
    //   4698: iconst_0
    //   4699: iaload
    //   4700: bipush #19
    //   4702: ishl
    //   4703: ior
    //   4704: ixor
    //   4705: aload #21
    //   4707: iconst_0
    //   4708: iaload
    //   4709: bipush #22
    //   4711: iushr
    //   4712: aload #21
    //   4714: iconst_0
    //   4715: iaload
    //   4716: bipush #10
    //   4718: ishl
    //   4719: ior
    //   4720: ixor
    //   4721: aload #21
    //   4723: iconst_0
    //   4724: iaload
    //   4725: aload #21
    //   4727: iconst_1
    //   4728: iaload
    //   4729: iand
    //   4730: aload #21
    //   4732: iconst_2
    //   4733: iaload
    //   4734: aload #21
    //   4736: iconst_0
    //   4737: iaload
    //   4738: aload #21
    //   4740: iconst_1
    //   4741: iaload
    //   4742: ior
    //   4743: iand
    //   4744: ior
    //   4745: iadd
    //   4746: istore #24
    //   4748: aload #21
    //   4750: iconst_3
    //   4751: dup2
    //   4752: iaload
    //   4753: iload #23
    //   4755: iadd
    //   4756: iastore
    //   4757: aload #21
    //   4759: bipush #7
    //   4761: iload #23
    //   4763: iload #24
    //   4765: iadd
    //   4766: iastore
    //   4767: aload #21
    //   4769: bipush #7
    //   4771: iaload
    //   4772: istore #23
    //   4774: aload #21
    //   4776: bipush #7
    //   4778: aload #21
    //   4780: bipush #6
    //   4782: iaload
    //   4783: iastore
    //   4784: aload #21
    //   4786: bipush #6
    //   4788: aload #21
    //   4790: iconst_5
    //   4791: iaload
    //   4792: iastore
    //   4793: aload #21
    //   4795: iconst_5
    //   4796: aload #21
    //   4798: iconst_4
    //   4799: iaload
    //   4800: iastore
    //   4801: aload #21
    //   4803: iconst_4
    //   4804: aload #21
    //   4806: iconst_3
    //   4807: iaload
    //   4808: iastore
    //   4809: aload #21
    //   4811: iconst_3
    //   4812: aload #21
    //   4814: iconst_2
    //   4815: iaload
    //   4816: iastore
    //   4817: aload #21
    //   4819: iconst_2
    //   4820: aload #21
    //   4822: iconst_1
    //   4823: iaload
    //   4824: iastore
    //   4825: aload #21
    //   4827: iconst_1
    //   4828: aload #21
    //   4830: iconst_0
    //   4831: iaload
    //   4832: iastore
    //   4833: aload #21
    //   4835: iconst_0
    //   4836: iload #23
    //   4838: iastore
    //   4839: iinc #22, 1
    //   4842: iload_2
    //   4843: ifeq -> 4351
    //   4846: iconst_0
    //   4847: istore #22
    //   4849: iload #22
    //   4851: bipush #8
    //   4853: if_icmpge -> 4876
    //   4856: aload #8
    //   4858: iload #22
    //   4860: dup2
    //   4861: iaload
    //   4862: aload #21
    //   4864: iload #22
    //   4866: iaload
    //   4867: iadd
    //   4868: iastore
    //   4869: iinc #22, 1
    //   4872: iload_2
    //   4873: ifeq -> 4849
    //   4876: bipush #32
    //   4878: newarray byte
    //   4880: astore #4
    //   4882: aload #4
    //   4884: iconst_0
    //   4885: aload #8
    //   4887: iconst_0
    //   4888: iaload
    //   4889: bipush #24
    //   4891: iushr
    //   4892: i2b
    //   4893: bastore
    //   4894: aload #4
    //   4896: iconst_1
    //   4897: aload #8
    //   4899: iconst_0
    //   4900: iaload
    //   4901: bipush #16
    //   4903: iushr
    //   4904: i2b
    //   4905: bastore
    //   4906: aload #4
    //   4908: iconst_2
    //   4909: aload #8
    //   4911: iconst_0
    //   4912: iaload
    //   4913: bipush #8
    //   4915: iushr
    //   4916: i2b
    //   4917: bastore
    //   4918: aload #4
    //   4920: iconst_3
    //   4921: aload #8
    //   4923: iconst_0
    //   4924: iaload
    //   4925: i2b
    //   4926: bastore
    //   4927: aload #4
    //   4929: iconst_4
    //   4930: aload #8
    //   4932: iconst_1
    //   4933: iaload
    //   4934: bipush #24
    //   4936: iushr
    //   4937: i2b
    //   4938: bastore
    //   4939: aload #4
    //   4941: iconst_5
    //   4942: aload #8
    //   4944: iconst_1
    //   4945: iaload
    //   4946: bipush #16
    //   4948: iushr
    //   4949: i2b
    //   4950: bastore
    //   4951: aload #4
    //   4953: bipush #6
    //   4955: aload #8
    //   4957: iconst_1
    //   4958: iaload
    //   4959: bipush #8
    //   4961: iushr
    //   4962: i2b
    //   4963: bastore
    //   4964: aload #4
    //   4966: bipush #7
    //   4968: aload #8
    //   4970: iconst_1
    //   4971: iaload
    //   4972: i2b
    //   4973: bastore
    //   4974: aload #4
    //   4976: bipush #8
    //   4978: aload #8
    //   4980: iconst_2
    //   4981: iaload
    //   4982: bipush #24
    //   4984: iushr
    //   4985: i2b
    //   4986: bastore
    //   4987: aload #4
    //   4989: bipush #9
    //   4991: aload #8
    //   4993: iconst_2
    //   4994: iaload
    //   4995: bipush #16
    //   4997: iushr
    //   4998: i2b
    //   4999: bastore
    //   5000: aload #4
    //   5002: bipush #10
    //   5004: aload #8
    //   5006: iconst_2
    //   5007: iaload
    //   5008: bipush #8
    //   5010: iushr
    //   5011: i2b
    //   5012: bastore
    //   5013: aload #4
    //   5015: bipush #11
    //   5017: aload #8
    //   5019: iconst_2
    //   5020: iaload
    //   5021: i2b
    //   5022: bastore
    //   5023: aload #4
    //   5025: bipush #12
    //   5027: aload #8
    //   5029: iconst_3
    //   5030: iaload
    //   5031: bipush #24
    //   5033: iushr
    //   5034: i2b
    //   5035: bastore
    //   5036: aload #4
    //   5038: bipush #13
    //   5040: aload #8
    //   5042: iconst_3
    //   5043: iaload
    //   5044: bipush #16
    //   5046: iushr
    //   5047: i2b
    //   5048: bastore
    //   5049: aload #4
    //   5051: bipush #14
    //   5053: aload #8
    //   5055: iconst_3
    //   5056: iaload
    //   5057: bipush #8
    //   5059: iushr
    //   5060: i2b
    //   5061: bastore
    //   5062: aload #4
    //   5064: bipush #15
    //   5066: aload #8
    //   5068: iconst_3
    //   5069: iaload
    //   5070: i2b
    //   5071: bastore
    //   5072: aload #4
    //   5074: bipush #16
    //   5076: aload #8
    //   5078: iconst_4
    //   5079: iaload
    //   5080: bipush #24
    //   5082: iushr
    //   5083: i2b
    //   5084: bastore
    //   5085: aload #4
    //   5087: bipush #17
    //   5089: aload #8
    //   5091: iconst_4
    //   5092: iaload
    //   5093: bipush #16
    //   5095: iushr
    //   5096: i2b
    //   5097: bastore
    //   5098: aload #4
    //   5100: bipush #18
    //   5102: aload #8
    //   5104: iconst_4
    //   5105: iaload
    //   5106: bipush #8
    //   5108: iushr
    //   5109: i2b
    //   5110: bastore
    //   5111: aload #4
    //   5113: bipush #19
    //   5115: aload #8
    //   5117: iconst_4
    //   5118: iaload
    //   5119: i2b
    //   5120: bastore
    //   5121: aload #4
    //   5123: bipush #20
    //   5125: aload #8
    //   5127: iconst_5
    //   5128: iaload
    //   5129: bipush #24
    //   5131: iushr
    //   5132: i2b
    //   5133: bastore
    //   5134: aload #4
    //   5136: bipush #21
    //   5138: aload #8
    //   5140: iconst_5
    //   5141: iaload
    //   5142: bipush #16
    //   5144: iushr
    //   5145: i2b
    //   5146: bastore
    //   5147: aload #4
    //   5149: bipush #22
    //   5151: aload #8
    //   5153: iconst_5
    //   5154: iaload
    //   5155: bipush #8
    //   5157: iushr
    //   5158: i2b
    //   5159: bastore
    //   5160: aload #4
    //   5162: bipush #23
    //   5164: aload #8
    //   5166: iconst_5
    //   5167: iaload
    //   5168: i2b
    //   5169: bastore
    //   5170: aload #4
    //   5172: bipush #24
    //   5174: aload #8
    //   5176: bipush #6
    //   5178: iaload
    //   5179: bipush #24
    //   5181: iushr
    //   5182: i2b
    //   5183: bastore
    //   5184: aload #4
    //   5186: bipush #25
    //   5188: aload #8
    //   5190: bipush #6
    //   5192: iaload
    //   5193: bipush #16
    //   5195: iushr
    //   5196: i2b
    //   5197: bastore
    //   5198: aload #4
    //   5200: bipush #26
    //   5202: aload #8
    //   5204: bipush #6
    //   5206: iaload
    //   5207: bipush #8
    //   5209: iushr
    //   5210: i2b
    //   5211: bastore
    //   5212: aload #4
    //   5214: bipush #27
    //   5216: aload #8
    //   5218: bipush #6
    //   5220: iaload
    //   5221: i2b
    //   5222: bastore
    //   5223: aload #4
    //   5225: bipush #28
    //   5227: aload #8
    //   5229: bipush #7
    //   5231: iaload
    //   5232: bipush #24
    //   5234: iushr
    //   5235: i2b
    //   5236: bastore
    //   5237: aload #4
    //   5239: bipush #29
    //   5241: aload #8
    //   5243: bipush #7
    //   5245: iaload
    //   5246: bipush #16
    //   5248: iushr
    //   5249: i2b
    //   5250: bastore
    //   5251: aload #4
    //   5253: bipush #30
    //   5255: aload #8
    //   5257: bipush #7
    //   5259: iaload
    //   5260: bipush #8
    //   5262: iushr
    //   5263: i2b
    //   5264: bastore
    //   5265: aload #4
    //   5267: bipush #31
    //   5269: aload #8
    //   5271: bipush #7
    //   5273: iaload
    //   5274: i2b
    //   5275: bastore
    //   5276: getstatic burp/Zbo2.Zr : Ljava/lang/String;
    //   5279: getstatic burp/Zgco.Zx : Ljava/lang/Object;
    //   5282: checkcast java/math/BigInteger
    //   5285: invokevirtual intValue : ()I
    //   5288: bipush #32
    //   5290: irem
    //   5291: invokestatic abs : (I)I
    //   5294: invokevirtual charAt : (I)C
    //   5297: getstatic burp/Zkig.ZE : Ljava/lang/String;
    //   5300: getstatic burp/Zgfq.Za : Ljava/lang/Object;
    //   5303: checkcast java/math/BigInteger
    //   5306: invokevirtual intValue : ()I
    //   5309: bipush #32
    //   5311: irem
    //   5312: invokestatic abs : (I)I
    //   5315: invokevirtual charAt : (I)C
    //   5318: if_icmple -> 5425
    //   5321: getstatic burp/Ztuj.Zk : Ljava/lang/String;
    //   5324: getstatic burp/Zlhy.ZN : Ljava/lang/Object;
    //   5327: checkcast java/math/BigInteger
    //   5330: invokevirtual intValue : ()I
    //   5333: bipush #32
    //   5335: irem
    //   5336: invokestatic abs : (I)I
    //   5339: invokevirtual charAt : (I)C
    //   5342: getstatic burp/Ztnw.Zr : Ljava/lang/String;
    //   5345: getstatic burp/Ze57.ZR : Ljava/lang/Object;
    //   5348: checkcast java/math/BigInteger
    //   5351: invokevirtual intValue : ()I
    //   5354: bipush #32
    //   5356: irem
    //   5357: invokestatic abs : (I)I
    //   5360: invokevirtual charAt : (I)C
    //   5363: if_icmpgt -> 5425
    //   5366: goto -> 5373
    //   5369: invokestatic a : (Ljava/lang/Throwable;)Ljava/lang/Throwable;
    //   5372: athrow
    //   5373: getstatic burp/Zgb9.Zk : Ljava/lang/String;
    //   5376: getstatic burp/Zrbp.Z_ : Ljava/lang/Object;
    //   5379: checkcast java/math/BigInteger
    //   5382: invokevirtual intValue : ()I
    //   5385: bipush #32
    //   5387: irem
    //   5388: invokestatic abs : (I)I
    //   5391: invokevirtual charAt : (I)C
    //   5394: getstatic burp/Zxtc.Zo : Ljava/lang/String;
    //   5397: getstatic burp/Zxn9.ZN : Ljava/lang/Object;
    //   5400: checkcast java/math/BigInteger
    //   5403: invokevirtual intValue : ()I
    //   5406: bipush #32
    //   5408: irem
    //   5409: invokestatic abs : (I)I
    //   5412: invokevirtual charAt : (I)C
    //   5415: if_icmpgt -> 5433
    //   5418: goto -> 5425
    //   5421: invokestatic a : (Ljava/lang/Throwable;)Ljava/lang/Throwable;
    //   5424: athrow
    //   5425: iconst_1
    //   5426: goto -> 5434
    //   5429: invokestatic a : (Ljava/lang/Throwable;)Ljava/lang/Throwable;
    //   5432: athrow
    //   5433: iconst_0
    //   5434: ireturn
    //   5435: astore_3
    //   5436: new java/lang/Exception
    //   5439: dup
    //   5440: aload_3
    //   5441: invokevirtual getMessage : ()Ljava/lang/String;
    //   5444: invokespecial <init> : (Ljava/lang/String;)V
    //   5447: athrow
    // Exception table:
    //   from	to	target	type
    //   4	5434	5435	java/lang/Throwable
    //   33	47	50	java/lang/Throwable
    //   40	61	64	java/lang/Throwable
    //   54	75	78	java/lang/Throwable
    //   68	89	92	java/lang/Throwable
    //   82	103	106	java/lang/Throwable
    //   96	117	120	java/lang/Throwable
    //   110	131	134	java/lang/Throwable
    //   124	145	148	java/lang/Throwable
    //   138	155	158	java/lang/Throwable
    //   194	208	211	java/lang/Throwable
    //   201	222	225	java/lang/Throwable
    //   215	236	239	java/lang/Throwable
    //   229	250	253	java/lang/Throwable
    //   243	264	267	java/lang/Throwable
    //   257	278	281	java/lang/Throwable
    //   271	292	295	java/lang/Throwable
    //   285	306	309	java/lang/Throwable
    //   299	323	326	java/lang/Throwable
    //   387	405	408	java/lang/Throwable
    //   396	421	424	java/lang/Throwable
    //   412	438	441	java/lang/Throwable
    //   428	454	457	java/lang/Throwable
    //   445	471	474	java/lang/Throwable
    //   461	487	490	java/lang/Throwable
    //   478	503	506	java/lang/Throwable
    //   494	526	529	java/lang/Throwable
    //   510	542	545	java/lang/Throwable
    //   533	558	561	java/lang/Throwable
    //   549	581	584	java/lang/Throwable
    //   565	597	600	java/lang/Throwable
    //   588	613	616	java/lang/Throwable
    //   604	632	635	java/lang/Throwable
    //   762	797	800	java/lang/Throwable
    //   804	845	848	java/lang/Throwable
    //   931	945	945	java/lang/Throwable
    //   956	969	972	java/lang/Throwable
    //   961	984	987	java/lang/Throwable
    //   976	1002	1005	java/lang/Throwable
    //   991	1032	1035	java/lang/Throwable
    //   1095	1122	1125	java/lang/Throwable
    //   1112	1143	1146	java/lang/Throwable
    //   1129	1173	1176	java/lang/Throwable
    //   1150	1184	1184	java/lang/Throwable
    //   1195	1211	1214	java/lang/Throwable
    //   2019	2053	2056	java/lang/Throwable
    //   2148	2226	2229	java/lang/Throwable
    //   2155	2369	2372	java/lang/Throwable
    //   2746	2761	2761	java/lang/Throwable
    //   2788	2822	2825	java/lang/Throwable
    //   2832	2844	2847	java/lang/Throwable
    //   2930	3008	3011	java/lang/Throwable
    //   2937	3151	3154	java/lang/Throwable
    //   3551	3629	3632	java/lang/Throwable
    //   3558	3772	3775	java/lang/Throwable
    //   4219	4253	4256	java/lang/Throwable
    //   4260	4272	4275	java/lang/Throwable
    //   4358	4436	4439	java/lang/Throwable
    //   4365	4579	4582	java/lang/Throwable
    //   4882	5366	5369	java/lang/Throwable
    //   5321	5418	5421	java/lang/Throwable
    //   5373	5429	5429	java/lang/Throwable
  }
  
  static void Zw(Object paramObject) {
    Ze4x.Zk = a(-8742, -3346);
    Ze4x.Zp = new BigInteger(a(-8740, 29299));
    boolean bool = Zt2e.ZN();
    try {
      try {
        if (Zgds.ZA.charAt(Math.abs(((BigInteger)Ze_0.ZY).intValue() % 32)) > Zt5b.ZV.charAt(Math.abs(((BigInteger)Zk88.ZX).intValue() % 32))) {
          try {
            Zsqi.Zi(Class.forName(a(-8737, -25353)));
            if (!bool)
              Zll8.Zr(Class.forName(a(-8751, -4826))); 
          } catch (Throwable throwable) {
            throw a(null);
          } 
          return;
        } 
      } catch (Throwable throwable) {
        throw a(null);
      } 
      Zll8.Zr(Class.forName(a(-8751, -4826)));
    } catch (Throwable throwable) {}
  }
  
  static void Zk(Object[] paramArrayOfObject, Object paramObject) throws Throwable {}
  
  static {
    // Byte code:
    //   0: bipush #9
    //   2: anewarray java/lang/String
    //   5: astore #5
    //   7: iconst_0
    //   8: istore_3
    //   9: ldc '):Xq/{K"HjfXGqV<S${yM$\)u9c@LHC$)}BO?>NtJ\\tW\\nPg@[  =\\fS\\rv\\bke\\brqL<1)\\tGv$.K M9DHrHuC~1`\\b"-P;uc(Ad)7}Ek]\\t*w"'
    //   11: dup
    //   12: astore_2
    //   13: invokevirtual length : ()I
    //   16: istore #4
    //   18: bipush #77
    //   20: istore_1
    //   21: iconst_m1
    //   22: istore_0
    //   23: bipush #117
    //   25: iinc #0, 1
    //   28: aload_2
    //   29: iload_0
    //   30: dup
    //   31: iload_1
    //   32: iadd
    //   33: invokevirtual substring : (II)Ljava/lang/String;
    //   36: iconst_m1
    //   37: goto -> 143
    //   40: aload #5
    //   42: swap
    //   43: iload_3
    //   44: iinc #3, 1
    //   47: swap
    //   48: aastore
    //   49: iload_0
    //   50: iload_1
    //   51: iadd
    //   52: dup
    //   53: istore_0
    //   54: iload #4
    //   56: if_icmpge -> 68
    //   59: aload_2
    //   60: iload_0
    //   61: invokevirtual charAt : (I)C
    //   64: istore_1
    //   65: goto -> 23
    //   68: ldc 'j2Y1:BJT,Zf'JA\\t(~rW'
    //   70: dup
    //   71: astore_2
    //   72: invokevirtual length : ()I
    //   75: istore #4
    //   77: bipush #32
    //   79: istore_1
    //   80: iconst_m1
    //   81: istore_0
    //   82: bipush #44
    //   84: iinc #0, 1
    //   87: aload_2
    //   88: iload_0
    //   89: dup
    //   90: iload_1
    //   91: iadd
    //   92: invokevirtual substring : (II)Ljava/lang/String;
    //   95: iconst_0
    //   96: goto -> 143
    //   99: aload #5
    //   101: swap
    //   102: iload_3
    //   103: iinc #3, 1
    //   106: swap
    //   107: aastore
    //   108: iload_0
    //   109: iload_1
    //   110: iadd
    //   111: dup
    //   112: istore_0
    //   113: iload #4
    //   115: if_icmpge -> 127
    //   118: aload_2
    //   119: iload_0
    //   120: invokevirtual charAt : (I)C
    //   123: istore_1
    //   124: goto -> 82
    //   127: aload #5
    //   129: putstatic burp/Zxzp.a : [Ljava/lang/String;
    //   132: bipush #9
    //   134: anewarray java/lang/String
    //   137: putstatic burp/Zxzp.b : [Ljava/lang/String;
    //   140: goto -> 300
    //   143: dup_x2
    //   144: pop
    //   145: invokevirtual toCharArray : ()[C
    //   148: dup_x1
    //   149: arraylength
    //   150: dup_x2
    //   151: pop
    //   152: iconst_0
    //   153: istore #6
    //   155: dup2_x1
    //   156: pop2
    //   157: dup_x2
    //   158: iconst_1
    //   159: if_icmpgt -> 260
    //   162: dup2
    //   163: swap
    //   164: iload #6
    //   166: dup2_x1
    //   167: caload
    //   168: swap
    //   169: iload #6
    //   171: bipush #7
    //   173: irem
    //   174: tableswitch default -> 242, 0 -> 212, 1 -> 217, 2 -> 222, 3 -> 227, 4 -> 232, 5 -> 237
    //   212: bipush #16
    //   214: goto -> 244
    //   217: bipush #110
    //   219: goto -> 244
    //   222: bipush #73
    //   224: goto -> 244
    //   227: bipush #93
    //   229: goto -> 244
    //   232: bipush #47
    //   234: goto -> 244
    //   237: bipush #114
    //   239: goto -> 244
    //   242: bipush #77
    //   244: ixor
    //   245: ixor
    //   246: i2c
    //   247: castore
    //   248: iinc #6, 1
    //   251: dup
    //   252: ifne -> 260
    //   255: dup2
    //   256: dup_x1
    //   257: goto -> 166
    //   260: dup2_x1
    //   261: pop2
    //   262: dup_x2
    //   263: iload #6
    //   265: if_icmpgt -> 162
    //   268: pop
    //   269: new java/lang/String
    //   272: dup_x1
    //   273: swap
    //   274: invokespecial <init> : ([C)V
    //   277: invokevirtual intern : ()Ljava/lang/String;
    //   280: swap
    //   281: pop
    //   282: swap
    //   283: tableswitch default -> 40, 0 -> 99
    //   300: new java/math/BigInteger
    //   303: dup
    //   304: sipush #-8743
    //   307: sipush #-827
    //   310: invokestatic a : (II)Ljava/lang/String;
    //   313: invokespecial <init> : (Ljava/lang/String;)V
    //   316: putstatic burp/Zxzp.Zh : Ljava/lang/Object;
    //   319: sipush #-8738
    //   322: sipush #20270
    //   325: invokestatic a : (II)Ljava/lang/String;
    //   328: putstatic burp/Zxzp.ZH : Ljava/lang/String;
    //   331: return
  }
  
  private static Throwable a(Throwable paramThrowable) {
    return paramThrowable;
  }
  
  private static String a(int paramInt1, int paramInt2) {
    int i = (paramInt1 ^ 0xFFFFDDD9) & 0xFFFF;
    if (b[i] == null) {
      char[] arrayOfChar = a[i].toCharArray();
      switch (arrayOfChar[0] & 0xFF) {
        case 0:
        
        case 1:
        
        case 2:
        
        case 3:
        
        case 4:
        
        case 5:
        
        case 6:
        
        case 7:
        
        case 8:
        
        case 9:
        
        case 10:
        
        case 11:
        
        case 12:
        
        case 13:
        
        case 14:
        
        case 15:
        
        case 16:
        
        case 17:
        
        case 18:
        
        case 19:
        
        case 20:
        
        case 21:
        
        case 22:
        
        case 23:
        
        case 24:
        
        case 25:
        
        case 26:
        
        case 27:
        
        case 28:
        
        case 29:
        
        case 30:
        
        case 31:
        
        case 32:
        
        case 33:
        
        case 34:
        
        case 35:
        
        case 36:
        
        case 37:
        
        case 38:
        
        case 39:
        
        case 40:
        
        case 41:
        
        case 42:
        
        case 43:
        
        case 44:
        
        case 45:
        
        case 46:
        
        case 47:
        
        case 48:
        
        case 49:
        
        case 50:
        
        case 51:
        
        case 52:
        
        case 53:
        
        case 54:
        
        case 55:
        
        case 56:
        
        case 57:
        
        case 58:
        
        case 59:
        
        case 60:
        
        case 61:
        
        case 62:
        
        case 63:
        
        case 64:
        
        case 65:
        
        case 66:
        
        case 67:
        
        case 68:
        
        case 69:
        
        case 70:
        
        case 71:
        
        case 72:
        
        case 73:
        
        case 74:
        
        case 75:
        
        case 76:
        
        case 77:
        
        case 78:
        
        case 79:
        
        case 80:
        
        case 81:
        
        case 82:
        
        case 83:
        
        case 84:
        
        case 85:
        
        case 86:
        
        case 87:
        
        case 88:
        
        case 89:
        
        case 90:
        
        case 91:
        
        case 92:
        
        case 93:
        
        case 94:
        
        case 95:
        
        case 96:
        
        case 97:
        
        case 98:
        
        case 99:
        
        case 100:
        
        case 101:
        
        case 102:
        
        case 103:
        
        case 104:
        
        case 105:
        
        case 106:
        
        case 107:
        
        case 108:
        
        case 109:
        
        case 110:
        
        case 111:
        
        case 112:
        
        case 113:
        
        case 114:
        
        case 115:
        
        case 116:
        
        case 117:
        
        case 118:
        
        case 119:
        
        case 120:
        
        case 121:
        
        case 122:
        
        case 123:
        
        case 124:
        
        case 125:
        
        case 126:
        
        case 127:
        
        case 128:
        
        case 129:
        
        case 130:
        
        case 131:
        
        case 132:
        
        case 133:
        
        case 134:
        
        case 135:
        
        case 136:
        
        case 137:
        
        case 138:
        
        case 139:
        
        case 140:
        
        case 141:
        
        case 142:
        
        case 143:
        
        case 144:
        
        case 145:
        
        case 146:
        
        case 147:
        
        case 148:
        
        case 149:
        
        case 150:
        
        case 151:
        
        case 152:
        
        case 153:
        
        case 154:
        
        case 155:
        
        case 156:
        
        case 157:
        
        case 158:
        
        case 159:
        
        case 160:
        
        case 161:
        
        case 162:
        
        case 163:
        
        case 164:
        
        case 165:
        
        case 166:
        
        case 167:
        
        case 168:
        
        case 169:
        
        case 170:
        
        case 171:
        
        case 172:
        
        case 173:
        
        case 174:
        
        case 175:
        
        case 176:
        
        case 177:
        
        case 178:
        
        case 179:
        
        case 180:
        
        case 181:
        
        case 182:
        
        case 183:
        
        case 184:
        
        case 185:
        
        case 186:
        
        case 187:
        
        case 188:
        
        case 189:
        
        case 190:
        
        case 191:
        
        case 192:
        
        case 193:
        
        case 194:
        
        case 195:
        
        case 196:
        
        case 197:
        
        case 198:
        
        case 199:
        
        case 200:
        
        case 201:
        
        case 202:
        
        case 203:
        
        case 204:
        
        case 205:
        
        case 206:
        
        case 207:
        
        case 208:
        
        case 209:
        
        case 210:
        
        case 211:
        
        case 212:
        
        case 213:
        
        case 214:
        
        case 215:
        
        case 216:
        
        case 217:
        
        case 218:
        
        case 219:
        
        case 220:
        
        case 221:
        
        case 222:
        
        case 223:
        
        case 224:
        
        case 225:
        
        case 226:
        
        case 227:
        
        case 228:
        
        case 229:
        
        case 230:
        
        case 231:
        
        case 232:
        
        case 233:
        
        case 234:
        
        case 235:
        
        case 236:
        
        case 237:
        
        case 238:
        
        case 239:
        
        case 240:
        
        case 241:
        
        case 242:
        
        case 243:
        
        case 244:
        
        case 245:
        
        case 246:
        
        case 247:
        
        case 248:
        
        case 249:
        
        case 250:
        
        case 251:
        
        case 252:
        
        case 253:
        
        case 254:
        
        default:
          break;
      } 
      char c = '';
      int j = (paramInt2 & 0xFF) - c;
      if (j < 0)
        j += 256; 
      int k = ((paramInt2 & 0xFFFF) >>> 8) - c;
      if (k < 0)
        k += 256; 
      for (byte b = 0; b < arrayOfChar.length; b++) {
        int m = b % 2;
        if (m == 0) {
          arrayOfChar[b] = (char)(arrayOfChar[b] ^ j);
          j = ((j >>> 3 | j << 5) ^ arrayOfChar[b]) & 0xFF;
        } else {
          arrayOfChar[b] = (char)(arrayOfChar[b] ^ k);
          k = ((k >>> 3 | k << 5) ^ arrayOfChar[b]) & 0xFF;
        } 
      } 
      b[i] = (new String(arrayOfChar)).intern();
    } 
    return b[i];
  }
}


/* Location:              C:\Program Files\BurpSuitePro\burpsuite_pro.jar!\burp\Zxzp.class
 * Java compiler version: 21 (65.0)
 * JD-Core Version:       1.1.3
 */