package burp;

import java.math.BigInteger;

class Zz0b extends ClassLoader {
  static Object ZT;
  
  static String ZD;
  
  private static final String[] a;
  
  private static final String[] b;
  
  static void Zt(Object paramObject) {
    Zedq.Zj = a(-7564, 10654);
    Zedq.Zy = new BigInteger(a(-7573, 1523));
    boolean bool = Zt2e.ZK();
    try {
      try {
        if (Zscz.ZJ.charAt(Math.abs(((BigInteger)Zeqx.Zh).intValue() % 32)) <= Zk8f.ZV.charAt(Math.abs(((BigInteger)Zrqi.Zb).intValue() % 32))) {
          try {
            Zsxm.Zq(Class.forName(a(-7568, -7441)));
            if (bool)
              Zt5t.ZP(Class.forName(a(-7553, -30623))); 
          } catch (Throwable throwable) {
            throw a(null);
          } 
          return;
        } 
      } catch (Throwable throwable) {
        throw a(null);
      } 
      Zt5t.ZP(Class.forName(a(-7553, -30623)));
    } catch (Throwable throwable) {}
  }
  
  static boolean ZB(Object[] paramArrayOfObject, Object paramObject) throws Throwable {
    // Byte code:
    //   0: invokestatic ZN : ()Z
    //   3: istore_2
    //   4: new java/lang/StringBuilder
    //   7: dup
    //   8: invokespecial <init> : ()V
    //   11: astore_3
    //   12: iconst_0
    //   13: istore #4
    //   15: iload #4
    //   17: bipush #32
    //   19: if_icmpge -> 1355
    //   22: iload #4
    //   24: tableswitch default -> 1348, 0 -> 168, 1 -> 205, 2 -> 242, 3 -> 279, 4 -> 316, 5 -> 353, 6 -> 390, 7 -> 427, 8 -> 464, 9 -> 501, 10 -> 538, 11 -> 575, 12 -> 612, 13 -> 649, 14 -> 686, 15 -> 723, 16 -> 760, 17 -> 797, 18 -> 834, 19 -> 871, 20 -> 908, 21 -> 945, 22 -> 982, 23 -> 1019, 24 -> 1056, 25 -> 1093, 26 -> 1130, 27 -> 1167, 28 -> 1204, 29 -> 1241, 30 -> 1278, 31 -> 1315
    //   168: aload_3
    //   169: getstatic burp/Ztvy.Zk : Ljava/lang/String;
    //   172: getstatic burp/Zmn0.Zo : Ljava/lang/Object;
    //   175: checkcast java/math/BigInteger
    //   178: invokevirtual intValue : ()I
    //   181: bipush #32
    //   183: irem
    //   184: invokestatic abs : (I)I
    //   187: invokevirtual charAt : (I)C
    //   190: invokevirtual append : (C)Ljava/lang/StringBuilder;
    //   193: pop
    //   194: iload_2
    //   195: ifne -> 1348
    //   198: goto -> 205
    //   201: invokestatic a : (Ljava/lang/Throwable;)Ljava/lang/Throwable;
    //   204: athrow
    //   205: aload_3
    //   206: getstatic burp/Zrd2.Zj : Ljava/lang/String;
    //   209: getstatic burp/Zlw8.ZA : Ljava/lang/Object;
    //   212: checkcast java/math/BigInteger
    //   215: invokevirtual intValue : ()I
    //   218: bipush #32
    //   220: irem
    //   221: invokestatic abs : (I)I
    //   224: invokevirtual charAt : (I)C
    //   227: invokevirtual append : (C)Ljava/lang/StringBuilder;
    //   230: pop
    //   231: iload_2
    //   232: ifne -> 1348
    //   235: goto -> 242
    //   238: invokestatic a : (Ljava/lang/Throwable;)Ljava/lang/Throwable;
    //   241: athrow
    //   242: aload_3
    //   243: getstatic burp/Zlxr.ZS : Ljava/lang/String;
    //   246: getstatic burp/Zzmc.Zg : Ljava/lang/Object;
    //   249: checkcast java/math/BigInteger
    //   252: invokevirtual intValue : ()I
    //   255: bipush #32
    //   257: irem
    //   258: invokestatic abs : (I)I
    //   261: invokevirtual charAt : (I)C
    //   264: invokevirtual append : (C)Ljava/lang/StringBuilder;
    //   267: pop
    //   268: iload_2
    //   269: ifne -> 1348
    //   272: goto -> 279
    //   275: invokestatic a : (Ljava/lang/Throwable;)Ljava/lang/Throwable;
    //   278: athrow
    //   279: aload_3
    //   280: getstatic burp/Zlwc.ZM : Ljava/lang/String;
    //   283: getstatic burp/Zewr.Zw : Ljava/lang/Object;
    //   286: checkcast java/math/BigInteger
    //   289: invokevirtual intValue : ()I
    //   292: bipush #32
    //   294: irem
    //   295: invokestatic abs : (I)I
    //   298: invokevirtual charAt : (I)C
    //   301: invokevirtual append : (C)Ljava/lang/StringBuilder;
    //   304: pop
    //   305: iload_2
    //   306: ifne -> 1348
    //   309: goto -> 316
    //   312: invokestatic a : (Ljava/lang/Throwable;)Ljava/lang/Throwable;
    //   315: athrow
    //   316: aload_3
    //   317: getstatic burp/Zmz.Zp : Ljava/lang/String;
    //   320: getstatic burp/Zz41.Zv : Ljava/lang/Object;
    //   323: checkcast java/math/BigInteger
    //   326: invokevirtual intValue : ()I
    //   329: bipush #32
    //   331: irem
    //   332: invokestatic abs : (I)I
    //   335: invokevirtual charAt : (I)C
    //   338: invokevirtual append : (C)Ljava/lang/StringBuilder;
    //   341: pop
    //   342: iload_2
    //   343: ifne -> 1348
    //   346: goto -> 353
    //   349: invokestatic a : (Ljava/lang/Throwable;)Ljava/lang/Throwable;
    //   352: athrow
    //   353: aload_3
    //   354: getstatic burp/Zr_x.ZF : Ljava/lang/String;
    //   357: getstatic burp/Zepy.Ze : Ljava/lang/Object;
    //   360: checkcast java/math/BigInteger
    //   363: invokevirtual intValue : ()I
    //   366: bipush #32
    //   368: irem
    //   369: invokestatic abs : (I)I
    //   372: invokevirtual charAt : (I)C
    //   375: invokevirtual append : (C)Ljava/lang/StringBuilder;
    //   378: pop
    //   379: iload_2
    //   380: ifne -> 1348
    //   383: goto -> 390
    //   386: invokestatic a : (Ljava/lang/Throwable;)Ljava/lang/Throwable;
    //   389: athrow
    //   390: aload_3
    //   391: getstatic burp/Zedq.Zj : Ljava/lang/String;
    //   394: getstatic burp/Zgsy.ZC : Ljava/lang/Object;
    //   397: checkcast java/math/BigInteger
    //   400: invokevirtual intValue : ()I
    //   403: bipush #32
    //   405: irem
    //   406: invokestatic abs : (I)I
    //   409: invokevirtual charAt : (I)C
    //   412: invokevirtual append : (C)Ljava/lang/StringBuilder;
    //   415: pop
    //   416: iload_2
    //   417: ifne -> 1348
    //   420: goto -> 427
    //   423: invokestatic a : (Ljava/lang/Throwable;)Ljava/lang/Throwable;
    //   426: athrow
    //   427: aload_3
    //   428: getstatic burp/Zm0d.ZV : Ljava/lang/String;
    //   431: getstatic burp/Zrw0.ZC : Ljava/lang/Object;
    //   434: checkcast java/math/BigInteger
    //   437: invokevirtual intValue : ()I
    //   440: bipush #32
    //   442: irem
    //   443: invokestatic abs : (I)I
    //   446: invokevirtual charAt : (I)C
    //   449: invokevirtual append : (C)Ljava/lang/StringBuilder;
    //   452: pop
    //   453: iload_2
    //   454: ifne -> 1348
    //   457: goto -> 464
    //   460: invokestatic a : (Ljava/lang/Throwable;)Ljava/lang/Throwable;
    //   463: athrow
    //   464: aload_3
    //   465: getstatic burp/Zbx5.Zz : Ljava/lang/String;
    //   468: getstatic burp/Ztgv.Zg : Ljava/lang/Object;
    //   471: checkcast java/math/BigInteger
    //   474: invokevirtual intValue : ()I
    //   477: bipush #32
    //   479: irem
    //   480: invokestatic abs : (I)I
    //   483: invokevirtual charAt : (I)C
    //   486: invokevirtual append : (C)Ljava/lang/StringBuilder;
    //   489: pop
    //   490: iload_2
    //   491: ifne -> 1348
    //   494: goto -> 501
    //   497: invokestatic a : (Ljava/lang/Throwable;)Ljava/lang/Throwable;
    //   500: athrow
    //   501: aload_3
    //   502: getstatic burp/Zm63.Zs : Ljava/lang/String;
    //   505: getstatic burp/Zr2q.ZS : Ljava/lang/Object;
    //   508: checkcast java/math/BigInteger
    //   511: invokevirtual intValue : ()I
    //   514: bipush #32
    //   516: irem
    //   517: invokestatic abs : (I)I
    //   520: invokevirtual charAt : (I)C
    //   523: invokevirtual append : (C)Ljava/lang/StringBuilder;
    //   526: pop
    //   527: iload_2
    //   528: ifne -> 1348
    //   531: goto -> 538
    //   534: invokestatic a : (Ljava/lang/Throwable;)Ljava/lang/Throwable;
    //   537: athrow
    //   538: aload_3
    //   539: getstatic burp/Zexl.Zs : Ljava/lang/String;
    //   542: getstatic burp/Zesw.ZB : Ljava/lang/Object;
    //   545: checkcast java/math/BigInteger
    //   548: invokevirtual intValue : ()I
    //   551: bipush #32
    //   553: irem
    //   554: invokestatic abs : (I)I
    //   557: invokevirtual charAt : (I)C
    //   560: invokevirtual append : (C)Ljava/lang/StringBuilder;
    //   563: pop
    //   564: iload_2
    //   565: ifne -> 1348
    //   568: goto -> 575
    //   571: invokestatic a : (Ljava/lang/Throwable;)Ljava/lang/Throwable;
    //   574: athrow
    //   575: aload_3
    //   576: getstatic burp/Zbw5.ZC : Ljava/lang/String;
    //   579: getstatic burp/Zrle.Zl : Ljava/lang/Object;
    //   582: checkcast java/math/BigInteger
    //   585: invokevirtual intValue : ()I
    //   588: bipush #32
    //   590: irem
    //   591: invokestatic abs : (I)I
    //   594: invokevirtual charAt : (I)C
    //   597: invokevirtual append : (C)Ljava/lang/StringBuilder;
    //   600: pop
    //   601: iload_2
    //   602: ifne -> 1348
    //   605: goto -> 612
    //   608: invokestatic a : (Ljava/lang/Throwable;)Ljava/lang/Throwable;
    //   611: athrow
    //   612: aload_3
    //   613: getstatic burp/Zlwm.Zj : Ljava/lang/String;
    //   616: getstatic burp/Ze6w.Ze : Ljava/lang/Object;
    //   619: checkcast java/math/BigInteger
    //   622: invokevirtual intValue : ()I
    //   625: bipush #32
    //   627: irem
    //   628: invokestatic abs : (I)I
    //   631: invokevirtual charAt : (I)C
    //   634: invokevirtual append : (C)Ljava/lang/StringBuilder;
    //   637: pop
    //   638: iload_2
    //   639: ifne -> 1348
    //   642: goto -> 649
    //   645: invokestatic a : (Ljava/lang/Throwable;)Ljava/lang/Throwable;
    //   648: athrow
    //   649: aload_3
    //   650: getstatic burp/Zxn9.ZU : Ljava/lang/String;
    //   653: getstatic burp/Zetf.Zs : Ljava/lang/Object;
    //   656: checkcast java/math/BigInteger
    //   659: invokevirtual intValue : ()I
    //   662: bipush #32
    //   664: irem
    //   665: invokestatic abs : (I)I
    //   668: invokevirtual charAt : (I)C
    //   671: invokevirtual append : (C)Ljava/lang/StringBuilder;
    //   674: pop
    //   675: iload_2
    //   676: ifne -> 1348
    //   679: goto -> 686
    //   682: invokestatic a : (Ljava/lang/Throwable;)Ljava/lang/Throwable;
    //   685: athrow
    //   686: aload_3
    //   687: getstatic burp/Zzna.Zi : Ljava/lang/String;
    //   690: getstatic burp/Zxn9.ZN : Ljava/lang/Object;
    //   693: checkcast java/math/BigInteger
    //   696: invokevirtual intValue : ()I
    //   699: bipush #32
    //   701: irem
    //   702: invokestatic abs : (I)I
    //   705: invokevirtual charAt : (I)C
    //   708: invokevirtual append : (C)Ljava/lang/StringBuilder;
    //   711: pop
    //   712: iload_2
    //   713: ifne -> 1348
    //   716: goto -> 723
    //   719: invokestatic a : (Ljava/lang/Throwable;)Ljava/lang/Throwable;
    //   722: athrow
    //   723: aload_3
    //   724: getstatic burp/Znu.ZF : Ljava/lang/String;
    //   727: getstatic burp/Ztq2.Zj : Ljava/lang/Object;
    //   730: checkcast java/math/BigInteger
    //   733: invokevirtual intValue : ()I
    //   736: bipush #32
    //   738: irem
    //   739: invokestatic abs : (I)I
    //   742: invokevirtual charAt : (I)C
    //   745: invokevirtual append : (C)Ljava/lang/StringBuilder;
    //   748: pop
    //   749: iload_2
    //   750: ifne -> 1348
    //   753: goto -> 760
    //   756: invokestatic a : (Ljava/lang/Throwable;)Ljava/lang/Throwable;
    //   759: athrow
    //   760: aload_3
    //   761: getstatic burp/Zk5k.Zx : Ljava/lang/String;
    //   764: getstatic burp/Zgtx.Z_ : Ljava/lang/Object;
    //   767: checkcast java/math/BigInteger
    //   770: invokevirtual intValue : ()I
    //   773: bipush #32
    //   775: irem
    //   776: invokestatic abs : (I)I
    //   779: invokevirtual charAt : (I)C
    //   782: invokevirtual append : (C)Ljava/lang/StringBuilder;
    //   785: pop
    //   786: iload_2
    //   787: ifne -> 1348
    //   790: goto -> 797
    //   793: invokestatic a : (Ljava/lang/Throwable;)Ljava/lang/Throwable;
    //   796: athrow
    //   797: aload_3
    //   798: getstatic burp/Zlt1.ZA : Ljava/lang/String;
    //   801: getstatic burp/Zr36.Za : Ljava/lang/Object;
    //   804: checkcast java/math/BigInteger
    //   807: invokevirtual intValue : ()I
    //   810: bipush #32
    //   812: irem
    //   813: invokestatic abs : (I)I
    //   816: invokevirtual charAt : (I)C
    //   819: invokevirtual append : (C)Ljava/lang/StringBuilder;
    //   822: pop
    //   823: iload_2
    //   824: ifne -> 1348
    //   827: goto -> 834
    //   830: invokestatic a : (Ljava/lang/Throwable;)Ljava/lang/Throwable;
    //   833: athrow
    //   834: aload_3
    //   835: getstatic burp/Zx5w.Zq : Ljava/lang/String;
    //   838: getstatic burp/Zmc_.Zj : Ljava/lang/Object;
    //   841: checkcast java/math/BigInteger
    //   844: invokevirtual intValue : ()I
    //   847: bipush #32
    //   849: irem
    //   850: invokestatic abs : (I)I
    //   853: invokevirtual charAt : (I)C
    //   856: invokevirtual append : (C)Ljava/lang/StringBuilder;
    //   859: pop
    //   860: iload_2
    //   861: ifne -> 1348
    //   864: goto -> 871
    //   867: invokestatic a : (Ljava/lang/Throwable;)Ljava/lang/Throwable;
    //   870: athrow
    //   871: aload_3
    //   872: getstatic burp/Zlxr.ZS : Ljava/lang/String;
    //   875: getstatic burp/Zz3b.Zu : Ljava/lang/Object;
    //   878: checkcast java/math/BigInteger
    //   881: invokevirtual intValue : ()I
    //   884: bipush #32
    //   886: irem
    //   887: invokestatic abs : (I)I
    //   890: invokevirtual charAt : (I)C
    //   893: invokevirtual append : (C)Ljava/lang/StringBuilder;
    //   896: pop
    //   897: iload_2
    //   898: ifne -> 1348
    //   901: goto -> 908
    //   904: invokestatic a : (Ljava/lang/Throwable;)Ljava/lang/Throwable;
    //   907: athrow
    //   908: aload_3
    //   909: getstatic burp/Zepy.Zg : Ljava/lang/String;
    //   912: getstatic burp/Zb87.Zb : Ljava/lang/Object;
    //   915: checkcast java/math/BigInteger
    //   918: invokevirtual intValue : ()I
    //   921: bipush #32
    //   923: irem
    //   924: invokestatic abs : (I)I
    //   927: invokevirtual charAt : (I)C
    //   930: invokevirtual append : (C)Ljava/lang/StringBuilder;
    //   933: pop
    //   934: iload_2
    //   935: ifne -> 1348
    //   938: goto -> 945
    //   941: invokestatic a : (Ljava/lang/Throwable;)Ljava/lang/Throwable;
    //   944: athrow
    //   945: aload_3
    //   946: getstatic burp/Zlc2.Zz : Ljava/lang/String;
    //   949: getstatic burp/Znu.Zf : Ljava/lang/Object;
    //   952: checkcast java/math/BigInteger
    //   955: invokevirtual intValue : ()I
    //   958: bipush #32
    //   960: irem
    //   961: invokestatic abs : (I)I
    //   964: invokevirtual charAt : (I)C
    //   967: invokevirtual append : (C)Ljava/lang/StringBuilder;
    //   970: pop
    //   971: iload_2
    //   972: ifne -> 1348
    //   975: goto -> 982
    //   978: invokestatic a : (Ljava/lang/Throwable;)Ljava/lang/Throwable;
    //   981: athrow
    //   982: aload_3
    //   983: getstatic burp/Zge9.Zp : Ljava/lang/String;
    //   986: getstatic burp/Zzna.ZD : Ljava/lang/Object;
    //   989: checkcast java/math/BigInteger
    //   992: invokevirtual intValue : ()I
    //   995: bipush #32
    //   997: irem
    //   998: invokestatic abs : (I)I
    //   1001: invokevirtual charAt : (I)C
    //   1004: invokevirtual append : (C)Ljava/lang/StringBuilder;
    //   1007: pop
    //   1008: iload_2
    //   1009: ifne -> 1348
    //   1012: goto -> 1019
    //   1015: invokestatic a : (Ljava/lang/Throwable;)Ljava/lang/Throwable;
    //   1018: athrow
    //   1019: aload_3
    //   1020: getstatic burp/Zb2u.ZM : Ljava/lang/String;
    //   1023: getstatic burp/Zg61.Zp : Ljava/lang/Object;
    //   1026: checkcast java/math/BigInteger
    //   1029: invokevirtual intValue : ()I
    //   1032: bipush #32
    //   1034: irem
    //   1035: invokestatic abs : (I)I
    //   1038: invokevirtual charAt : (I)C
    //   1041: invokevirtual append : (C)Ljava/lang/StringBuilder;
    //   1044: pop
    //   1045: iload_2
    //   1046: ifne -> 1348
    //   1049: goto -> 1056
    //   1052: invokestatic a : (Ljava/lang/Throwable;)Ljava/lang/Throwable;
    //   1055: athrow
    //   1056: aload_3
    //   1057: getstatic burp/Zrb6.ZP : Ljava/lang/String;
    //   1060: getstatic burp/Zex0.Ze : Ljava/lang/Object;
    //   1063: checkcast java/math/BigInteger
    //   1066: invokevirtual intValue : ()I
    //   1069: bipush #32
    //   1071: irem
    //   1072: invokestatic abs : (I)I
    //   1075: invokevirtual charAt : (I)C
    //   1078: invokevirtual append : (C)Ljava/lang/StringBuilder;
    //   1081: pop
    //   1082: iload_2
    //   1083: ifne -> 1348
    //   1086: goto -> 1093
    //   1089: invokestatic a : (Ljava/lang/Throwable;)Ljava/lang/Throwable;
    //   1092: athrow
    //   1093: aload_3
    //   1094: getstatic burp/Zz91.Zx : Ljava/lang/String;
    //   1097: getstatic burp/Zv8d.ZN : Ljava/lang/Object;
    //   1100: checkcast java/math/BigInteger
    //   1103: invokevirtual intValue : ()I
    //   1106: bipush #32
    //   1108: irem
    //   1109: invokestatic abs : (I)I
    //   1112: invokevirtual charAt : (I)C
    //   1115: invokevirtual append : (C)Ljava/lang/StringBuilder;
    //   1118: pop
    //   1119: iload_2
    //   1120: ifne -> 1348
    //   1123: goto -> 1130
    //   1126: invokestatic a : (Ljava/lang/Throwable;)Ljava/lang/Throwable;
    //   1129: athrow
    //   1130: aload_3
    //   1131: getstatic burp/Zlo0.ZD : Ljava/lang/String;
    //   1134: getstatic burp/Zg0f.Zm : Ljava/lang/Object;
    //   1137: checkcast java/math/BigInteger
    //   1140: invokevirtual intValue : ()I
    //   1143: bipush #32
    //   1145: irem
    //   1146: invokestatic abs : (I)I
    //   1149: invokevirtual charAt : (I)C
    //   1152: invokevirtual append : (C)Ljava/lang/StringBuilder;
    //   1155: pop
    //   1156: iload_2
    //   1157: ifne -> 1348
    //   1160: goto -> 1167
    //   1163: invokestatic a : (Ljava/lang/Throwable;)Ljava/lang/Throwable;
    //   1166: athrow
    //   1167: aload_3
    //   1168: getstatic burp/Zxn9.ZU : Ljava/lang/String;
    //   1171: getstatic burp/Zsvd.Zk : Ljava/lang/Object;
    //   1174: checkcast java/math/BigInteger
    //   1177: invokevirtual intValue : ()I
    //   1180: bipush #32
    //   1182: irem
    //   1183: invokestatic abs : (I)I
    //   1186: invokevirtual charAt : (I)C
    //   1189: invokevirtual append : (C)Ljava/lang/StringBuilder;
    //   1192: pop
    //   1193: iload_2
    //   1194: ifne -> 1348
    //   1197: goto -> 1204
    //   1200: invokestatic a : (Ljava/lang/Throwable;)Ljava/lang/Throwable;
    //   1203: athrow
    //   1204: aload_3
    //   1205: getstatic burp/Zgio.ZS : Ljava/lang/String;
    //   1208: getstatic burp/Zos.ZB : Ljava/lang/Object;
    //   1211: checkcast java/math/BigInteger
    //   1214: invokevirtual intValue : ()I
    //   1217: bipush #32
    //   1219: irem
    //   1220: invokestatic abs : (I)I
    //   1223: invokevirtual charAt : (I)C
    //   1226: invokevirtual append : (C)Ljava/lang/StringBuilder;
    //   1229: pop
    //   1230: iload_2
    //   1231: ifne -> 1348
    //   1234: goto -> 1241
    //   1237: invokestatic a : (Ljava/lang/Throwable;)Ljava/lang/Throwable;
    //   1240: athrow
    //   1241: aload_3
    //   1242: getstatic burp/Zsp9.ZA : Ljava/lang/String;
    //   1245: getstatic burp/Zz66.ZQ : Ljava/lang/Object;
    //   1248: checkcast java/math/BigInteger
    //   1251: invokevirtual intValue : ()I
    //   1254: bipush #32
    //   1256: irem
    //   1257: invokestatic abs : (I)I
    //   1260: invokevirtual charAt : (I)C
    //   1263: invokevirtual append : (C)Ljava/lang/StringBuilder;
    //   1266: pop
    //   1267: iload_2
    //   1268: ifne -> 1348
    //   1271: goto -> 1278
    //   1274: invokestatic a : (Ljava/lang/Throwable;)Ljava/lang/Throwable;
    //   1277: athrow
    //   1278: aload_3
    //   1279: getstatic burp/Zs5y.ZO : Ljava/lang/String;
    //   1282: getstatic burp/Zegj.ZT : Ljava/lang/Object;
    //   1285: checkcast java/math/BigInteger
    //   1288: invokevirtual intValue : ()I
    //   1291: bipush #32
    //   1293: irem
    //   1294: invokestatic abs : (I)I
    //   1297: invokevirtual charAt : (I)C
    //   1300: invokevirtual append : (C)Ljava/lang/StringBuilder;
    //   1303: pop
    //   1304: iload_2
    //   1305: ifne -> 1348
    //   1308: goto -> 1315
    //   1311: invokestatic a : (Ljava/lang/Throwable;)Ljava/lang/Throwable;
    //   1314: athrow
    //   1315: aload_3
    //   1316: getstatic burp/Ztl6.Zb : Ljava/lang/String;
    //   1319: getstatic burp/Ze7e.Z_ : Ljava/lang/Object;
    //   1322: checkcast java/math/BigInteger
    //   1325: invokevirtual intValue : ()I
    //   1328: bipush #32
    //   1330: irem
    //   1331: invokestatic abs : (I)I
    //   1334: invokevirtual charAt : (I)C
    //   1337: invokevirtual append : (C)Ljava/lang/StringBuilder;
    //   1340: pop
    //   1341: goto -> 1348
    //   1344: invokestatic a : (Ljava/lang/Throwable;)Ljava/lang/Throwable;
    //   1347: athrow
    //   1348: iinc #4, 1
    //   1351: iload_2
    //   1352: ifne -> 15
    //   1355: aload_3
    //   1356: invokevirtual toString : ()Ljava/lang/String;
    //   1359: putstatic burp/Zkdx.Ze : Ljava/lang/String;
    //   1362: new java/lang/StringBuilder
    //   1365: dup
    //   1366: invokespecial <init> : ()V
    //   1369: astore #4
    //   1371: iconst_0
    //   1372: istore #5
    //   1374: iload #5
    //   1376: bipush #32
    //   1378: if_icmpge -> 2743
    //   1381: iload #5
    //   1383: tableswitch default -> 2736, 0 -> 1524, 1 -> 1562, 2 -> 1600, 3 -> 1638, 4 -> 1676, 5 -> 1714, 6 -> 1752, 7 -> 1790, 8 -> 1828, 9 -> 1866, 10 -> 1904, 11 -> 1942, 12 -> 1980, 13 -> 2018, 14 -> 2056, 15 -> 2094, 16 -> 2132, 17 -> 2170, 18 -> 2208, 19 -> 2246, 20 -> 2284, 21 -> 2322, 22 -> 2360, 23 -> 2398, 24 -> 2436, 25 -> 2474, 26 -> 2512, 27 -> 2550, 28 -> 2588, 29 -> 2626, 30 -> 2664, 31 -> 2702
    //   1524: aload #4
    //   1526: getstatic burp/Zlxw.ZC : Ljava/lang/String;
    //   1529: getstatic burp/Zkca.ZQ : Ljava/lang/Object;
    //   1532: checkcast java/math/BigInteger
    //   1535: invokevirtual intValue : ()I
    //   1538: bipush #32
    //   1540: irem
    //   1541: invokestatic abs : (I)I
    //   1544: invokevirtual charAt : (I)C
    //   1547: invokevirtual append : (C)Ljava/lang/StringBuilder;
    //   1550: pop
    //   1551: iload_2
    //   1552: ifne -> 2736
    //   1555: goto -> 1562
    //   1558: invokestatic a : (Ljava/lang/Throwable;)Ljava/lang/Throwable;
    //   1561: athrow
    //   1562: aload #4
    //   1564: getstatic burp/Zmpx.ZC : Ljava/lang/String;
    //   1567: getstatic burp/Zld9.ZF : Ljava/lang/Object;
    //   1570: checkcast java/math/BigInteger
    //   1573: invokevirtual intValue : ()I
    //   1576: bipush #32
    //   1578: irem
    //   1579: invokestatic abs : (I)I
    //   1582: invokevirtual charAt : (I)C
    //   1585: invokevirtual append : (C)Ljava/lang/StringBuilder;
    //   1588: pop
    //   1589: iload_2
    //   1590: ifne -> 2736
    //   1593: goto -> 1600
    //   1596: invokestatic a : (Ljava/lang/Throwable;)Ljava/lang/Throwable;
    //   1599: athrow
    //   1600: aload #4
    //   1602: getstatic burp/Zk92.Zc : Ljava/lang/String;
    //   1605: getstatic burp/Zl_f.ZI : Ljava/lang/Object;
    //   1608: checkcast java/math/BigInteger
    //   1611: invokevirtual intValue : ()I
    //   1614: bipush #32
    //   1616: irem
    //   1617: invokestatic abs : (I)I
    //   1620: invokevirtual charAt : (I)C
    //   1623: invokevirtual append : (C)Ljava/lang/StringBuilder;
    //   1626: pop
    //   1627: iload_2
    //   1628: ifne -> 2736
    //   1631: goto -> 1638
    //   1634: invokestatic a : (Ljava/lang/Throwable;)Ljava/lang/Throwable;
    //   1637: athrow
    //   1638: aload #4
    //   1640: getstatic burp/Zgis.Zh : Ljava/lang/String;
    //   1643: getstatic burp/Zlxw.Zi : Ljava/lang/Object;
    //   1646: checkcast java/math/BigInteger
    //   1649: invokevirtual intValue : ()I
    //   1652: bipush #32
    //   1654: irem
    //   1655: invokestatic abs : (I)I
    //   1658: invokevirtual charAt : (I)C
    //   1661: invokevirtual append : (C)Ljava/lang/StringBuilder;
    //   1664: pop
    //   1665: iload_2
    //   1666: ifne -> 2736
    //   1669: goto -> 1676
    //   1672: invokestatic a : (Ljava/lang/Throwable;)Ljava/lang/Throwable;
    //   1675: athrow
    //   1676: aload #4
    //   1678: getstatic burp/Zlg2.ZL : Ljava/lang/String;
    //   1681: getstatic burp/Zkkl.ZE : Ljava/lang/Object;
    //   1684: checkcast java/math/BigInteger
    //   1687: invokevirtual intValue : ()I
    //   1690: bipush #32
    //   1692: irem
    //   1693: invokestatic abs : (I)I
    //   1696: invokevirtual charAt : (I)C
    //   1699: invokevirtual append : (C)Ljava/lang/StringBuilder;
    //   1702: pop
    //   1703: iload_2
    //   1704: ifne -> 2736
    //   1707: goto -> 1714
    //   1710: invokestatic a : (Ljava/lang/Throwable;)Ljava/lang/Throwable;
    //   1713: athrow
    //   1714: aload #4
    //   1716: getstatic burp/Zbze.ZK : Ljava/lang/String;
    //   1719: getstatic burp/Zbun.ZH : Ljava/lang/Object;
    //   1722: checkcast java/math/BigInteger
    //   1725: invokevirtual intValue : ()I
    //   1728: bipush #32
    //   1730: irem
    //   1731: invokestatic abs : (I)I
    //   1734: invokevirtual charAt : (I)C
    //   1737: invokevirtual append : (C)Ljava/lang/StringBuilder;
    //   1740: pop
    //   1741: iload_2
    //   1742: ifne -> 2736
    //   1745: goto -> 1752
    //   1748: invokestatic a : (Ljava/lang/Throwable;)Ljava/lang/Throwable;
    //   1751: athrow
    //   1752: aload #4
    //   1754: getstatic burp/Zz41.Zc : Ljava/lang/String;
    //   1757: getstatic burp/Zsbv.Zl : Ljava/lang/Object;
    //   1760: checkcast java/math/BigInteger
    //   1763: invokevirtual intValue : ()I
    //   1766: bipush #32
    //   1768: irem
    //   1769: invokestatic abs : (I)I
    //   1772: invokevirtual charAt : (I)C
    //   1775: invokevirtual append : (C)Ljava/lang/StringBuilder;
    //   1778: pop
    //   1779: iload_2
    //   1780: ifne -> 2736
    //   1783: goto -> 1790
    //   1786: invokestatic a : (Ljava/lang/Throwable;)Ljava/lang/Throwable;
    //   1789: athrow
    //   1790: aload #4
    //   1792: getstatic burp/Zr6c.Zf : Ljava/lang/String;
    //   1795: getstatic burp/Zxan.ZX : Ljava/lang/Object;
    //   1798: checkcast java/math/BigInteger
    //   1801: invokevirtual intValue : ()I
    //   1804: bipush #32
    //   1806: irem
    //   1807: invokestatic abs : (I)I
    //   1810: invokevirtual charAt : (I)C
    //   1813: invokevirtual append : (C)Ljava/lang/StringBuilder;
    //   1816: pop
    //   1817: iload_2
    //   1818: ifne -> 2736
    //   1821: goto -> 1828
    //   1824: invokestatic a : (Ljava/lang/Throwable;)Ljava/lang/Throwable;
    //   1827: athrow
    //   1828: aload #4
    //   1830: getstatic burp/Zt4p.ZL : Ljava/lang/String;
    //   1833: getstatic burp/Zz41.Zv : Ljava/lang/Object;
    //   1836: checkcast java/math/BigInteger
    //   1839: invokevirtual intValue : ()I
    //   1842: bipush #32
    //   1844: irem
    //   1845: invokestatic abs : (I)I
    //   1848: invokevirtual charAt : (I)C
    //   1851: invokevirtual append : (C)Ljava/lang/StringBuilder;
    //   1854: pop
    //   1855: iload_2
    //   1856: ifne -> 2736
    //   1859: goto -> 1866
    //   1862: invokestatic a : (Ljava/lang/Throwable;)Ljava/lang/Throwable;
    //   1865: athrow
    //   1866: aload #4
    //   1868: getstatic burp/Zt6z.ZL : Ljava/lang/String;
    //   1871: getstatic burp/Zm8j.Zj : Ljava/lang/Object;
    //   1874: checkcast java/math/BigInteger
    //   1877: invokevirtual intValue : ()I
    //   1880: bipush #32
    //   1882: irem
    //   1883: invokestatic abs : (I)I
    //   1886: invokevirtual charAt : (I)C
    //   1889: invokevirtual append : (C)Ljava/lang/StringBuilder;
    //   1892: pop
    //   1893: iload_2
    //   1894: ifne -> 2736
    //   1897: goto -> 1904
    //   1900: invokestatic a : (Ljava/lang/Throwable;)Ljava/lang/Throwable;
    //   1903: athrow
    //   1904: aload #4
    //   1906: getstatic burp/Zb2n.Za : Ljava/lang/String;
    //   1909: getstatic burp/Zrjw.Zu : Ljava/lang/Object;
    //   1912: checkcast java/math/BigInteger
    //   1915: invokevirtual intValue : ()I
    //   1918: bipush #32
    //   1920: irem
    //   1921: invokestatic abs : (I)I
    //   1924: invokevirtual charAt : (I)C
    //   1927: invokevirtual append : (C)Ljava/lang/StringBuilder;
    //   1930: pop
    //   1931: iload_2
    //   1932: ifne -> 2736
    //   1935: goto -> 1942
    //   1938: invokestatic a : (Ljava/lang/Throwable;)Ljava/lang/Throwable;
    //   1941: athrow
    //   1942: aload #4
    //   1944: getstatic burp/Zelt.ZJ : Ljava/lang/String;
    //   1947: getstatic burp/Zlwj.ZE : Ljava/lang/Object;
    //   1950: checkcast java/math/BigInteger
    //   1953: invokevirtual intValue : ()I
    //   1956: bipush #32
    //   1958: irem
    //   1959: invokestatic abs : (I)I
    //   1962: invokevirtual charAt : (I)C
    //   1965: invokevirtual append : (C)Ljava/lang/StringBuilder;
    //   1968: pop
    //   1969: iload_2
    //   1970: ifne -> 2736
    //   1973: goto -> 1980
    //   1976: invokestatic a : (Ljava/lang/Throwable;)Ljava/lang/Throwable;
    //   1979: athrow
    //   1980: aload #4
    //   1982: getstatic burp/Zlc2.Zz : Ljava/lang/String;
    //   1985: getstatic burp/Zx4u.Zn : Ljava/lang/Object;
    //   1988: checkcast java/math/BigInteger
    //   1991: invokevirtual intValue : ()I
    //   1994: bipush #32
    //   1996: irem
    //   1997: invokestatic abs : (I)I
    //   2000: invokevirtual charAt : (I)C
    //   2003: invokevirtual append : (C)Ljava/lang/StringBuilder;
    //   2006: pop
    //   2007: iload_2
    //   2008: ifne -> 2736
    //   2011: goto -> 2018
    //   2014: invokestatic a : (Ljava/lang/Throwable;)Ljava/lang/Throwable;
    //   2017: athrow
    //   2018: aload #4
    //   2020: getstatic burp/Zrkd.ZL : Ljava/lang/String;
    //   2023: getstatic burp/Zr36.Za : Ljava/lang/Object;
    //   2026: checkcast java/math/BigInteger
    //   2029: invokevirtual intValue : ()I
    //   2032: bipush #32
    //   2034: irem
    //   2035: invokestatic abs : (I)I
    //   2038: invokevirtual charAt : (I)C
    //   2041: invokevirtual append : (C)Ljava/lang/StringBuilder;
    //   2044: pop
    //   2045: iload_2
    //   2046: ifne -> 2736
    //   2049: goto -> 2056
    //   2052: invokestatic a : (Ljava/lang/Throwable;)Ljava/lang/Throwable;
    //   2055: athrow
    //   2056: aload #4
    //   2058: getstatic burp/Zbsz.Zu : Ljava/lang/String;
    //   2061: getstatic burp/Zkca.ZQ : Ljava/lang/Object;
    //   2064: checkcast java/math/BigInteger
    //   2067: invokevirtual intValue : ()I
    //   2070: bipush #32
    //   2072: irem
    //   2073: invokestatic abs : (I)I
    //   2076: invokevirtual charAt : (I)C
    //   2079: invokevirtual append : (C)Ljava/lang/StringBuilder;
    //   2082: pop
    //   2083: iload_2
    //   2084: ifne -> 2736
    //   2087: goto -> 2094
    //   2090: invokestatic a : (Ljava/lang/Throwable;)Ljava/lang/Throwable;
    //   2093: athrow
    //   2094: aload #4
    //   2096: getstatic burp/Zea9.Zd : Ljava/lang/String;
    //   2099: getstatic burp/Ze2w.ZA : Ljava/lang/Object;
    //   2102: checkcast java/math/BigInteger
    //   2105: invokevirtual intValue : ()I
    //   2108: bipush #32
    //   2110: irem
    //   2111: invokestatic abs : (I)I
    //   2114: invokevirtual charAt : (I)C
    //   2117: invokevirtual append : (C)Ljava/lang/StringBuilder;
    //   2120: pop
    //   2121: iload_2
    //   2122: ifne -> 2736
    //   2125: goto -> 2132
    //   2128: invokestatic a : (Ljava/lang/Throwable;)Ljava/lang/Throwable;
    //   2131: athrow
    //   2132: aload #4
    //   2134: getstatic burp/Zrqi.Zu : Ljava/lang/String;
    //   2137: getstatic burp/Zlt1.ZH : Ljava/lang/Object;
    //   2140: checkcast java/math/BigInteger
    //   2143: invokevirtual intValue : ()I
    //   2146: bipush #32
    //   2148: irem
    //   2149: invokestatic abs : (I)I
    //   2152: invokevirtual charAt : (I)C
    //   2155: invokevirtual append : (C)Ljava/lang/StringBuilder;
    //   2158: pop
    //   2159: iload_2
    //   2160: ifne -> 2736
    //   2163: goto -> 2170
    //   2166: invokestatic a : (Ljava/lang/Throwable;)Ljava/lang/Throwable;
    //   2169: athrow
    //   2170: aload #4
    //   2172: getstatic burp/Znu.ZF : Ljava/lang/String;
    //   2175: getstatic burp/Zti4.Zi : Ljava/lang/Object;
    //   2178: checkcast java/math/BigInteger
    //   2181: invokevirtual intValue : ()I
    //   2184: bipush #32
    //   2186: irem
    //   2187: invokestatic abs : (I)I
    //   2190: invokevirtual charAt : (I)C
    //   2193: invokevirtual append : (C)Ljava/lang/StringBuilder;
    //   2196: pop
    //   2197: iload_2
    //   2198: ifne -> 2736
    //   2201: goto -> 2208
    //   2204: invokestatic a : (Ljava/lang/Throwable;)Ljava/lang/Throwable;
    //   2207: athrow
    //   2208: aload #4
    //   2210: getstatic burp/Zzmc.Zr : Ljava/lang/String;
    //   2213: getstatic burp/Zz4j.Zu : Ljava/lang/Object;
    //   2216: checkcast java/math/BigInteger
    //   2219: invokevirtual intValue : ()I
    //   2222: bipush #32
    //   2224: irem
    //   2225: invokestatic abs : (I)I
    //   2228: invokevirtual charAt : (I)C
    //   2231: invokevirtual append : (C)Ljava/lang/StringBuilder;
    //   2234: pop
    //   2235: iload_2
    //   2236: ifne -> 2736
    //   2239: goto -> 2246
    //   2242: invokestatic a : (Ljava/lang/Throwable;)Ljava/lang/Throwable;
    //   2245: athrow
    //   2246: aload #4
    //   2248: getstatic burp/Zg7u.ZA : Ljava/lang/String;
    //   2251: getstatic burp/Zzr8.ZC : Ljava/lang/Object;
    //   2254: checkcast java/math/BigInteger
    //   2257: invokevirtual intValue : ()I
    //   2260: bipush #32
    //   2262: irem
    //   2263: invokestatic abs : (I)I
    //   2266: invokevirtual charAt : (I)C
    //   2269: invokevirtual append : (C)Ljava/lang/StringBuilder;
    //   2272: pop
    //   2273: iload_2
    //   2274: ifne -> 2736
    //   2277: goto -> 2284
    //   2280: invokestatic a : (Ljava/lang/Throwable;)Ljava/lang/Throwable;
    //   2283: athrow
    //   2284: aload #4
    //   2286: getstatic burp/Ztq8.ZI : Ljava/lang/String;
    //   2289: getstatic burp/Zmf2.Zx : Ljava/lang/Object;
    //   2292: checkcast java/math/BigInteger
    //   2295: invokevirtual intValue : ()I
    //   2298: bipush #32
    //   2300: irem
    //   2301: invokestatic abs : (I)I
    //   2304: invokevirtual charAt : (I)C
    //   2307: invokevirtual append : (C)Ljava/lang/StringBuilder;
    //   2310: pop
    //   2311: iload_2
    //   2312: ifne -> 2736
    //   2315: goto -> 2322
    //   2318: invokestatic a : (Ljava/lang/Throwable;)Ljava/lang/Throwable;
    //   2321: athrow
    //   2322: aload #4
    //   2324: getstatic burp/Zr9u.Zc : Ljava/lang/String;
    //   2327: getstatic burp/Zos.ZB : Ljava/lang/Object;
    //   2330: checkcast java/math/BigInteger
    //   2333: invokevirtual intValue : ()I
    //   2336: bipush #32
    //   2338: irem
    //   2339: invokestatic abs : (I)I
    //   2342: invokevirtual charAt : (I)C
    //   2345: invokevirtual append : (C)Ljava/lang/StringBuilder;
    //   2348: pop
    //   2349: iload_2
    //   2350: ifne -> 2736
    //   2353: goto -> 2360
    //   2356: invokestatic a : (Ljava/lang/Throwable;)Ljava/lang/Throwable;
    //   2359: athrow
    //   2360: aload #4
    //   2362: getstatic burp/Zm69.ZE : Ljava/lang/String;
    //   2365: getstatic burp/Zt6z.Zl : Ljava/lang/Object;
    //   2368: checkcast java/math/BigInteger
    //   2371: invokevirtual intValue : ()I
    //   2374: bipush #32
    //   2376: irem
    //   2377: invokestatic abs : (I)I
    //   2380: invokevirtual charAt : (I)C
    //   2383: invokevirtual append : (C)Ljava/lang/StringBuilder;
    //   2386: pop
    //   2387: iload_2
    //   2388: ifne -> 2736
    //   2391: goto -> 2398
    //   2394: invokestatic a : (Ljava/lang/Throwable;)Ljava/lang/Throwable;
    //   2397: athrow
    //   2398: aload #4
    //   2400: getstatic burp/Zsjc.ZO : Ljava/lang/String;
    //   2403: getstatic burp/Ztwp.Ze : Ljava/lang/Object;
    //   2406: checkcast java/math/BigInteger
    //   2409: invokevirtual intValue : ()I
    //   2412: bipush #32
    //   2414: irem
    //   2415: invokestatic abs : (I)I
    //   2418: invokevirtual charAt : (I)C
    //   2421: invokevirtual append : (C)Ljava/lang/StringBuilder;
    //   2424: pop
    //   2425: iload_2
    //   2426: ifne -> 2736
    //   2429: goto -> 2436
    //   2432: invokestatic a : (Ljava/lang/Throwable;)Ljava/lang/Throwable;
    //   2435: athrow
    //   2436: aload #4
    //   2438: getstatic burp/Zegv.ZA : Ljava/lang/String;
    //   2441: getstatic burp/Zmtr.Zv : Ljava/lang/Object;
    //   2444: checkcast java/math/BigInteger
    //   2447: invokevirtual intValue : ()I
    //   2450: bipush #32
    //   2452: irem
    //   2453: invokestatic abs : (I)I
    //   2456: invokevirtual charAt : (I)C
    //   2459: invokevirtual append : (C)Ljava/lang/StringBuilder;
    //   2462: pop
    //   2463: iload_2
    //   2464: ifne -> 2736
    //   2467: goto -> 2474
    //   2470: invokestatic a : (Ljava/lang/Throwable;)Ljava/lang/Throwable;
    //   2473: athrow
    //   2474: aload #4
    //   2476: getstatic burp/Zxdy.Zm : Ljava/lang/String;
    //   2479: getstatic burp/Zg4z.ZB : Ljava/lang/Object;
    //   2482: checkcast java/math/BigInteger
    //   2485: invokevirtual intValue : ()I
    //   2488: bipush #32
    //   2490: irem
    //   2491: invokestatic abs : (I)I
    //   2494: invokevirtual charAt : (I)C
    //   2497: invokevirtual append : (C)Ljava/lang/StringBuilder;
    //   2500: pop
    //   2501: iload_2
    //   2502: ifne -> 2736
    //   2505: goto -> 2512
    //   2508: invokestatic a : (Ljava/lang/Throwable;)Ljava/lang/Throwable;
    //   2511: athrow
    //   2512: aload #4
    //   2514: getstatic burp/Zeqz.ZV : Ljava/lang/String;
    //   2517: getstatic burp/Zzh5.ZG : Ljava/lang/Object;
    //   2520: checkcast java/math/BigInteger
    //   2523: invokevirtual intValue : ()I
    //   2526: bipush #32
    //   2528: irem
    //   2529: invokestatic abs : (I)I
    //   2532: invokevirtual charAt : (I)C
    //   2535: invokevirtual append : (C)Ljava/lang/StringBuilder;
    //   2538: pop
    //   2539: iload_2
    //   2540: ifne -> 2736
    //   2543: goto -> 2550
    //   2546: invokestatic a : (Ljava/lang/Throwable;)Ljava/lang/Throwable;
    //   2549: athrow
    //   2550: aload #4
    //   2552: getstatic burp/Zzh5.Zc : Ljava/lang/String;
    //   2555: getstatic burp/Zm1d.ZS : Ljava/lang/Object;
    //   2558: checkcast java/math/BigInteger
    //   2561: invokevirtual intValue : ()I
    //   2564: bipush #32
    //   2566: irem
    //   2567: invokestatic abs : (I)I
    //   2570: invokevirtual charAt : (I)C
    //   2573: invokevirtual append : (C)Ljava/lang/StringBuilder;
    //   2576: pop
    //   2577: iload_2
    //   2578: ifne -> 2736
    //   2581: goto -> 2588
    //   2584: invokestatic a : (Ljava/lang/Throwable;)Ljava/lang/Throwable;
    //   2587: athrow
    //   2588: aload #4
    //   2590: getstatic burp/Zxan.ZJ : Ljava/lang/String;
    //   2593: getstatic burp/Zz0f.ZL : Ljava/lang/Object;
    //   2596: checkcast java/math/BigInteger
    //   2599: invokevirtual intValue : ()I
    //   2602: bipush #32
    //   2604: irem
    //   2605: invokestatic abs : (I)I
    //   2608: invokevirtual charAt : (I)C
    //   2611: invokevirtual append : (C)Ljava/lang/StringBuilder;
    //   2614: pop
    //   2615: iload_2
    //   2616: ifne -> 2736
    //   2619: goto -> 2626
    //   2622: invokestatic a : (Ljava/lang/Throwable;)Ljava/lang/Throwable;
    //   2625: athrow
    //   2626: aload #4
    //   2628: getstatic burp/Zs3m.Zl : Ljava/lang/String;
    //   2631: getstatic burp/Zt9f.Zl : Ljava/lang/Object;
    //   2634: checkcast java/math/BigInteger
    //   2637: invokevirtual intValue : ()I
    //   2640: bipush #32
    //   2642: irem
    //   2643: invokestatic abs : (I)I
    //   2646: invokevirtual charAt : (I)C
    //   2649: invokevirtual append : (C)Ljava/lang/StringBuilder;
    //   2652: pop
    //   2653: iload_2
    //   2654: ifne -> 2736
    //   2657: goto -> 2664
    //   2660: invokestatic a : (Ljava/lang/Throwable;)Ljava/lang/Throwable;
    //   2663: athrow
    //   2664: aload #4
    //   2666: getstatic burp/Zbnz.Zp : Ljava/lang/String;
    //   2669: getstatic burp/Zl7x.Za : Ljava/lang/Object;
    //   2672: checkcast java/math/BigInteger
    //   2675: invokevirtual intValue : ()I
    //   2678: bipush #32
    //   2680: irem
    //   2681: invokestatic abs : (I)I
    //   2684: invokevirtual charAt : (I)C
    //   2687: invokevirtual append : (C)Ljava/lang/StringBuilder;
    //   2690: pop
    //   2691: iload_2
    //   2692: ifne -> 2736
    //   2695: goto -> 2702
    //   2698: invokestatic a : (Ljava/lang/Throwable;)Ljava/lang/Throwable;
    //   2701: athrow
    //   2702: aload #4
    //   2704: getstatic burp/Zma0.ZP : Ljava/lang/String;
    //   2707: getstatic burp/Zgio.ZP : Ljava/lang/Object;
    //   2710: checkcast java/math/BigInteger
    //   2713: invokevirtual intValue : ()I
    //   2716: bipush #32
    //   2718: irem
    //   2719: invokestatic abs : (I)I
    //   2722: invokevirtual charAt : (I)C
    //   2725: invokevirtual append : (C)Ljava/lang/StringBuilder;
    //   2728: pop
    //   2729: goto -> 2736
    //   2732: invokestatic a : (Ljava/lang/Throwable;)Ljava/lang/Throwable;
    //   2735: athrow
    //   2736: iinc #5, 1
    //   2739: iload_2
    //   2740: ifne -> 1374
    //   2743: aload #4
    //   2745: invokevirtual toString : ()Ljava/lang/String;
    //   2748: putstatic burp/Zm_u.Zi : Ljava/lang/String;
    //   2751: sipush #-7584
    //   2754: sipush #9168
    //   2757: invokestatic a : (II)Ljava/lang/String;
    //   2760: iconst_1
    //   2761: ldc burp/Ztc2
    //   2763: invokevirtual getClassLoader : ()Ljava/lang/ClassLoader;
    //   2766: invokestatic forName : (Ljava/lang/String;ZLjava/lang/ClassLoader;)Ljava/lang/Class;
    //   2769: invokevirtual getDeclaredFields : ()[Ljava/lang/reflect/Field;
    //   2772: astore #5
    //   2774: aload #5
    //   2776: arraylength
    //   2777: istore #6
    //   2779: iconst_0
    //   2780: istore #7
    //   2782: iload #7
    //   2784: iload #6
    //   2786: if_icmpge -> 2924
    //   2789: aload #5
    //   2791: iload #7
    //   2793: aaload
    //   2794: astore #8
    //   2796: aload #8
    //   2798: invokevirtual getModifiers : ()I
    //   2801: invokestatic isStatic : (I)Z
    //   2804: ifne -> 2814
    //   2807: goto -> 2917
    //   2810: invokestatic a : (Ljava/lang/Throwable;)Ljava/lang/Throwable;
    //   2813: athrow
    //   2814: aload #8
    //   2816: invokevirtual getType : ()Ljava/lang/Class;
    //   2819: astore #9
    //   2821: aload #9
    //   2823: ifnull -> 2904
    //   2826: aload #9
    //   2828: invokevirtual isPrimitive : ()Z
    //   2831: ifne -> 2904
    //   2834: goto -> 2841
    //   2837: invokestatic a : (Ljava/lang/Throwable;)Ljava/lang/Throwable;
    //   2840: athrow
    //   2841: aload #9
    //   2843: invokevirtual getPackage : ()Ljava/lang/Package;
    //   2846: ifnull -> 2904
    //   2849: goto -> 2856
    //   2852: invokestatic a : (Ljava/lang/Throwable;)Ljava/lang/Throwable;
    //   2855: athrow
    //   2856: aload #9
    //   2858: invokevirtual getPackage : ()Ljava/lang/Package;
    //   2861: invokevirtual getName : ()Ljava/lang/String;
    //   2864: ifnull -> 2904
    //   2867: goto -> 2874
    //   2870: invokestatic a : (Ljava/lang/Throwable;)Ljava/lang/Throwable;
    //   2873: athrow
    //   2874: aload #9
    //   2876: invokevirtual getPackage : ()Ljava/lang/Package;
    //   2879: invokevirtual getName : ()Ljava/lang/String;
    //   2882: sipush #-7583
    //   2885: sipush #19399
    //   2888: invokestatic a : (II)Ljava/lang/String;
    //   2891: invokevirtual startsWith : (Ljava/lang/String;)Z
    //   2894: ifne -> 2904
    //   2897: goto -> 2904
    //   2900: invokestatic a : (Ljava/lang/Throwable;)Ljava/lang/Throwable;
    //   2903: athrow
    //   2904: aload #8
    //   2906: iconst_1
    //   2907: invokevirtual setAccessible : (Z)V
    //   2910: aload #8
    //   2912: aconst_null
    //   2913: invokevirtual get : (Ljava/lang/Object;)Ljava/lang/Object;
    //   2916: pop
    //   2917: iinc #7, 1
    //   2920: iload_2
    //   2921: ifne -> 2782
    //   2924: sipush #-7572
    //   2927: sipush #-20061
    //   2930: invokestatic a : (II)Ljava/lang/String;
    //   2933: invokestatic forName : (Ljava/lang/String;)Ljava/lang/Class;
    //   2936: invokevirtual getDeclaredMethods : ()[Ljava/lang/reflect/Method;
    //   2939: astore #5
    //   2941: aload #5
    //   2943: arraylength
    //   2944: istore #6
    //   2946: iconst_0
    //   2947: istore #7
    //   2949: iload #7
    //   2951: iload #6
    //   2953: if_icmpge -> 3086
    //   2956: aload #5
    //   2958: iload #7
    //   2960: aaload
    //   2961: astore #8
    //   2963: aload #8
    //   2965: invokevirtual getParameterTypes : ()[Ljava/lang/Class;
    //   2968: pop
    //   2969: aload #8
    //   2971: invokevirtual getModifiers : ()I
    //   2974: invokestatic isStatic : (I)Z
    //   2977: ifeq -> 3072
    //   2980: aload #8
    //   2982: invokevirtual getParameterTypes : ()[Ljava/lang/Class;
    //   2985: arraylength
    //   2986: iconst_2
    //   2987: if_icmpne -> 3072
    //   2990: goto -> 2997
    //   2993: invokestatic a : (Ljava/lang/Throwable;)Ljava/lang/Throwable;
    //   2996: athrow
    //   2997: aload #8
    //   2999: invokevirtual getReturnType : ()Ljava/lang/Class;
    //   3002: getstatic java/lang/Void.TYPE : Ljava/lang/Class;
    //   3005: invokevirtual equals : (Ljava/lang/Object;)Z
    //   3008: ifeq -> 3072
    //   3011: goto -> 3018
    //   3014: invokestatic a : (Ljava/lang/Throwable;)Ljava/lang/Throwable;
    //   3017: athrow
    //   3018: aload #8
    //   3020: iconst_1
    //   3021: invokevirtual setAccessible : (Z)V
    //   3024: aload #8
    //   3026: aconst_null
    //   3027: iconst_2
    //   3028: anewarray java/lang/Object
    //   3031: dup
    //   3032: iconst_0
    //   3033: aload_0
    //   3034: aastore
    //   3035: dup
    //   3036: iconst_1
    //   3037: aload_1
    //   3038: ifnonnull -> 3056
    //   3041: goto -> 3048
    //   3044: invokestatic a : (Ljava/lang/Throwable;)Ljava/lang/Throwable;
    //   3047: athrow
    //   3048: aload_1
    //   3049: goto -> 3063
    //   3052: invokestatic a : (Ljava/lang/Throwable;)Ljava/lang/Throwable;
    //   3055: athrow
    //   3056: aload_1
    //   3057: checkcast [B
    //   3060: invokevirtual clone : ()Ljava/lang/Object;
    //   3063: aastore
    //   3064: invokevirtual invoke : (Ljava/lang/Object;[Ljava/lang/Object;)Ljava/lang/Object;
    //   3067: pop
    //   3068: iload_2
    //   3069: ifne -> 3086
    //   3072: iinc #7, 1
    //   3075: iload_2
    //   3076: ifne -> 2949
    //   3079: goto -> 3086
    //   3082: invokestatic a : (Ljava/lang/Throwable;)Ljava/lang/Throwable;
    //   3085: athrow
    //   3086: iconst_0
    //   3087: istore #5
    //   3089: getstatic burp/Zql.Zf : Ljava/lang/String;
    //   3092: getstatic burp/Zvob.ZX : Ljava/lang/Object;
    //   3095: checkcast java/math/BigInteger
    //   3098: invokevirtual intValue : ()I
    //   3101: bipush #32
    //   3103: irem
    //   3104: invokestatic abs : (I)I
    //   3107: invokevirtual charAt : (I)C
    //   3110: getstatic burp/Zld5.ZO : Ljava/lang/String;
    //   3113: getstatic burp/Zlwc.ZG : Ljava/lang/Object;
    //   3116: checkcast java/math/BigInteger
    //   3119: invokevirtual intValue : ()I
    //   3122: bipush #32
    //   3124: irem
    //   3125: invokestatic abs : (I)I
    //   3128: invokevirtual charAt : (I)C
    //   3131: if_icmpgt -> 3476
    //   3134: sipush #-7574
    //   3137: sipush #23187
    //   3140: invokestatic a : (II)Ljava/lang/String;
    //   3143: iconst_1
    //   3144: ldc burp/Zsts
    //   3146: invokevirtual getClassLoader : ()Ljava/lang/ClassLoader;
    //   3149: invokestatic forName : (Ljava/lang/String;ZLjava/lang/ClassLoader;)Ljava/lang/Class;
    //   3152: invokevirtual getDeclaredFields : ()[Ljava/lang/reflect/Field;
    //   3155: astore #6
    //   3157: aload #6
    //   3159: arraylength
    //   3160: istore #7
    //   3162: iconst_0
    //   3163: istore #8
    //   3165: iload #8
    //   3167: iload #7
    //   3169: if_icmpge -> 3307
    //   3172: aload #6
    //   3174: iload #8
    //   3176: aaload
    //   3177: astore #9
    //   3179: aload #9
    //   3181: invokevirtual getModifiers : ()I
    //   3184: invokestatic isStatic : (I)Z
    //   3187: ifne -> 3197
    //   3190: goto -> 3300
    //   3193: invokestatic a : (Ljava/lang/Throwable;)Ljava/lang/Throwable;
    //   3196: athrow
    //   3197: aload #9
    //   3199: invokevirtual getType : ()Ljava/lang/Class;
    //   3202: astore #10
    //   3204: aload #10
    //   3206: ifnull -> 3287
    //   3209: aload #10
    //   3211: invokevirtual isPrimitive : ()Z
    //   3214: ifne -> 3287
    //   3217: goto -> 3224
    //   3220: invokestatic a : (Ljava/lang/Throwable;)Ljava/lang/Throwable;
    //   3223: athrow
    //   3224: aload #10
    //   3226: invokevirtual getPackage : ()Ljava/lang/Package;
    //   3229: ifnull -> 3287
    //   3232: goto -> 3239
    //   3235: invokestatic a : (Ljava/lang/Throwable;)Ljava/lang/Throwable;
    //   3238: athrow
    //   3239: aload #10
    //   3241: invokevirtual getPackage : ()Ljava/lang/Package;
    //   3244: invokevirtual getName : ()Ljava/lang/String;
    //   3247: ifnull -> 3287
    //   3250: goto -> 3257
    //   3253: invokestatic a : (Ljava/lang/Throwable;)Ljava/lang/Throwable;
    //   3256: athrow
    //   3257: aload #10
    //   3259: invokevirtual getPackage : ()Ljava/lang/Package;
    //   3262: invokevirtual getName : ()Ljava/lang/String;
    //   3265: sipush #-7562
    //   3268: sipush #17029
    //   3271: invokestatic a : (II)Ljava/lang/String;
    //   3274: invokevirtual startsWith : (Ljava/lang/String;)Z
    //   3277: ifne -> 3287
    //   3280: goto -> 3287
    //   3283: invokestatic a : (Ljava/lang/Throwable;)Ljava/lang/Throwable;
    //   3286: athrow
    //   3287: aload #9
    //   3289: iconst_1
    //   3290: invokevirtual setAccessible : (Z)V
    //   3293: aload #9
    //   3295: aconst_null
    //   3296: invokevirtual get : (Ljava/lang/Object;)Ljava/lang/Object;
    //   3299: pop
    //   3300: iinc #8, 1
    //   3303: iload_2
    //   3304: ifne -> 3165
    //   3307: sipush #-7563
    //   3310: sipush #-30625
    //   3313: invokestatic a : (II)Ljava/lang/String;
    //   3316: invokestatic forName : (Ljava/lang/String;)Ljava/lang/Class;
    //   3319: invokevirtual getDeclaredMethods : ()[Ljava/lang/reflect/Method;
    //   3322: astore #6
    //   3324: aload #6
    //   3326: arraylength
    //   3327: istore #7
    //   3329: iconst_0
    //   3330: istore #8
    //   3332: iload #8
    //   3334: iload #7
    //   3336: if_icmpge -> 3473
    //   3339: aload #6
    //   3341: iload #8
    //   3343: aaload
    //   3344: astore #9
    //   3346: aload #9
    //   3348: invokevirtual getParameterTypes : ()[Ljava/lang/Class;
    //   3351: pop
    //   3352: aload #9
    //   3354: invokevirtual getModifiers : ()I
    //   3357: invokestatic isStatic : (I)Z
    //   3360: ifeq -> 3459
    //   3363: aload #9
    //   3365: invokevirtual getParameterTypes : ()[Ljava/lang/Class;
    //   3368: arraylength
    //   3369: iconst_2
    //   3370: if_icmpne -> 3459
    //   3373: goto -> 3380
    //   3376: invokestatic a : (Ljava/lang/Throwable;)Ljava/lang/Throwable;
    //   3379: athrow
    //   3380: aload #9
    //   3382: invokevirtual getReturnType : ()Ljava/lang/Class;
    //   3385: getstatic java/lang/Boolean.TYPE : Ljava/lang/Class;
    //   3388: if_acmpne -> 3459
    //   3391: goto -> 3398
    //   3394: invokestatic a : (Ljava/lang/Throwable;)Ljava/lang/Throwable;
    //   3397: athrow
    //   3398: aload #9
    //   3400: iconst_1
    //   3401: invokevirtual setAccessible : (Z)V
    //   3404: aload #9
    //   3406: aconst_null
    //   3407: iconst_2
    //   3408: anewarray java/lang/Object
    //   3411: dup
    //   3412: iconst_0
    //   3413: aload_0
    //   3414: aastore
    //   3415: dup
    //   3416: iconst_1
    //   3417: aload_1
    //   3418: ifnonnull -> 3436
    //   3421: goto -> 3428
    //   3424: invokestatic a : (Ljava/lang/Throwable;)Ljava/lang/Throwable;
    //   3427: athrow
    //   3428: aload_1
    //   3429: goto -> 3443
    //   3432: invokestatic a : (Ljava/lang/Throwable;)Ljava/lang/Throwable;
    //   3435: athrow
    //   3436: aload_1
    //   3437: checkcast [B
    //   3440: invokevirtual clone : ()Ljava/lang/Object;
    //   3443: aastore
    //   3444: invokevirtual invoke : (Ljava/lang/Object;[Ljava/lang/Object;)Ljava/lang/Object;
    //   3447: checkcast java/lang/Boolean
    //   3450: invokevirtual booleanValue : ()Z
    //   3453: istore #5
    //   3455: iload_2
    //   3456: ifne -> 3473
    //   3459: iinc #8, 1
    //   3462: iload_2
    //   3463: ifne -> 3332
    //   3466: goto -> 3473
    //   3469: invokestatic a : (Ljava/lang/Throwable;)Ljava/lang/Throwable;
    //   3472: athrow
    //   3473: goto -> 3815
    //   3476: sipush #-7577
    //   3479: sipush #-20425
    //   3482: invokestatic a : (II)Ljava/lang/String;
    //   3485: iconst_1
    //   3486: ldc burp/Ztt0
    //   3488: invokevirtual getClassLoader : ()Ljava/lang/ClassLoader;
    //   3491: invokestatic forName : (Ljava/lang/String;ZLjava/lang/ClassLoader;)Ljava/lang/Class;
    //   3494: invokevirtual getDeclaredFields : ()[Ljava/lang/reflect/Field;
    //   3497: astore #6
    //   3499: aload #6
    //   3501: arraylength
    //   3502: istore #7
    //   3504: iconst_0
    //   3505: istore #8
    //   3507: iload #8
    //   3509: iload #7
    //   3511: if_icmpge -> 3649
    //   3514: aload #6
    //   3516: iload #8
    //   3518: aaload
    //   3519: astore #9
    //   3521: aload #9
    //   3523: invokevirtual getModifiers : ()I
    //   3526: invokestatic isStatic : (I)Z
    //   3529: ifne -> 3539
    //   3532: goto -> 3642
    //   3535: invokestatic a : (Ljava/lang/Throwable;)Ljava/lang/Throwable;
    //   3538: athrow
    //   3539: aload #9
    //   3541: invokevirtual getType : ()Ljava/lang/Class;
    //   3544: astore #10
    //   3546: aload #10
    //   3548: ifnull -> 3629
    //   3551: aload #10
    //   3553: invokevirtual isPrimitive : ()Z
    //   3556: ifne -> 3629
    //   3559: goto -> 3566
    //   3562: invokestatic a : (Ljava/lang/Throwable;)Ljava/lang/Throwable;
    //   3565: athrow
    //   3566: aload #10
    //   3568: invokevirtual getPackage : ()Ljava/lang/Package;
    //   3571: ifnull -> 3629
    //   3574: goto -> 3581
    //   3577: invokestatic a : (Ljava/lang/Throwable;)Ljava/lang/Throwable;
    //   3580: athrow
    //   3581: aload #10
    //   3583: invokevirtual getPackage : ()Ljava/lang/Package;
    //   3586: invokevirtual getName : ()Ljava/lang/String;
    //   3589: ifnull -> 3629
    //   3592: goto -> 3599
    //   3595: invokestatic a : (Ljava/lang/Throwable;)Ljava/lang/Throwable;
    //   3598: athrow
    //   3599: aload #10
    //   3601: invokevirtual getPackage : ()Ljava/lang/Package;
    //   3604: invokevirtual getName : ()Ljava/lang/String;
    //   3607: sipush #-7562
    //   3610: sipush #17029
    //   3613: invokestatic a : (II)Ljava/lang/String;
    //   3616: invokevirtual startsWith : (Ljava/lang/String;)Z
    //   3619: ifne -> 3629
    //   3622: goto -> 3629
    //   3625: invokestatic a : (Ljava/lang/Throwable;)Ljava/lang/Throwable;
    //   3628: athrow
    //   3629: aload #9
    //   3631: iconst_1
    //   3632: invokevirtual setAccessible : (Z)V
    //   3635: aload #9
    //   3637: aconst_null
    //   3638: invokevirtual get : (Ljava/lang/Object;)Ljava/lang/Object;
    //   3641: pop
    //   3642: iinc #8, 1
    //   3645: iload_2
    //   3646: ifne -> 3507
    //   3649: sipush #-7579
    //   3652: sipush #-27338
    //   3655: invokestatic a : (II)Ljava/lang/String;
    //   3658: invokestatic forName : (Ljava/lang/String;)Ljava/lang/Class;
    //   3661: invokevirtual getDeclaredMethods : ()[Ljava/lang/reflect/Method;
    //   3664: astore #6
    //   3666: aload #6
    //   3668: arraylength
    //   3669: istore #7
    //   3671: iconst_0
    //   3672: istore #8
    //   3674: iload #8
    //   3676: iload #7
    //   3678: if_icmpge -> 3815
    //   3681: aload #6
    //   3683: iload #8
    //   3685: aaload
    //   3686: astore #9
    //   3688: aload #9
    //   3690: invokevirtual getParameterTypes : ()[Ljava/lang/Class;
    //   3693: pop
    //   3694: aload #9
    //   3696: invokevirtual getModifiers : ()I
    //   3699: invokestatic isStatic : (I)Z
    //   3702: ifeq -> 3801
    //   3705: aload #9
    //   3707: invokevirtual getParameterTypes : ()[Ljava/lang/Class;
    //   3710: arraylength
    //   3711: iconst_2
    //   3712: if_icmpne -> 3801
    //   3715: goto -> 3722
    //   3718: invokestatic a : (Ljava/lang/Throwable;)Ljava/lang/Throwable;
    //   3721: athrow
    //   3722: aload #9
    //   3724: invokevirtual getReturnType : ()Ljava/lang/Class;
    //   3727: getstatic java/lang/Boolean.TYPE : Ljava/lang/Class;
    //   3730: if_acmpne -> 3801
    //   3733: goto -> 3740
    //   3736: invokestatic a : (Ljava/lang/Throwable;)Ljava/lang/Throwable;
    //   3739: athrow
    //   3740: aload #9
    //   3742: iconst_1
    //   3743: invokevirtual setAccessible : (Z)V
    //   3746: aload #9
    //   3748: aconst_null
    //   3749: iconst_2
    //   3750: anewarray java/lang/Object
    //   3753: dup
    //   3754: iconst_0
    //   3755: aload_0
    //   3756: aastore
    //   3757: dup
    //   3758: iconst_1
    //   3759: aload_1
    //   3760: ifnonnull -> 3778
    //   3763: goto -> 3770
    //   3766: invokestatic a : (Ljava/lang/Throwable;)Ljava/lang/Throwable;
    //   3769: athrow
    //   3770: aload_1
    //   3771: goto -> 3785
    //   3774: invokestatic a : (Ljava/lang/Throwable;)Ljava/lang/Throwable;
    //   3777: athrow
    //   3778: aload_1
    //   3779: checkcast [B
    //   3782: invokevirtual clone : ()Ljava/lang/Object;
    //   3785: aastore
    //   3786: invokevirtual invoke : (Ljava/lang/Object;[Ljava/lang/Object;)Ljava/lang/Object;
    //   3789: checkcast java/lang/Boolean
    //   3792: invokevirtual booleanValue : ()Z
    //   3795: istore #5
    //   3797: iload_2
    //   3798: ifne -> 3815
    //   3801: iinc #8, 1
    //   3804: iload_2
    //   3805: ifne -> 3674
    //   3808: goto -> 3815
    //   3811: invokestatic a : (Ljava/lang/Throwable;)Ljava/lang/Throwable;
    //   3814: athrow
    //   3815: iload #5
    //   3817: ifeq -> 3823
    //   3820: iload #5
    //   3822: ireturn
    //   3823: getstatic burp/Zepy.Zg : Ljava/lang/String;
    //   3826: getstatic burp/Zlxr.Zz : Ljava/lang/Object;
    //   3829: checkcast java/math/BigInteger
    //   3832: invokevirtual intValue : ()I
    //   3835: bipush #32
    //   3837: irem
    //   3838: invokestatic abs : (I)I
    //   3841: invokevirtual charAt : (I)C
    //   3844: getstatic burp/Zt85.ZR : Ljava/lang/String;
    //   3847: getstatic burp/Zgpx.ZQ : Ljava/lang/Object;
    //   3850: checkcast java/math/BigInteger
    //   3853: invokevirtual intValue : ()I
    //   3856: bipush #32
    //   3858: irem
    //   3859: invokestatic abs : (I)I
    //   3862: invokevirtual charAt : (I)C
    //   3865: if_icmple -> 4211
    //   3868: sipush #-7569
    //   3871: sipush #4997
    //   3874: invokestatic a : (II)Ljava/lang/String;
    //   3877: iconst_1
    //   3878: ldc burp/Zzou
    //   3880: invokevirtual getClassLoader : ()Ljava/lang/ClassLoader;
    //   3883: invokestatic forName : (Ljava/lang/String;ZLjava/lang/ClassLoader;)Ljava/lang/Class;
    //   3886: invokevirtual getDeclaredFields : ()[Ljava/lang/reflect/Field;
    //   3889: astore #6
    //   3891: aload #6
    //   3893: arraylength
    //   3894: istore #7
    //   3896: iconst_0
    //   3897: istore #8
    //   3899: iload #8
    //   3901: iload #7
    //   3903: if_icmpge -> 4041
    //   3906: aload #6
    //   3908: iload #8
    //   3910: aaload
    //   3911: astore #9
    //   3913: aload #9
    //   3915: invokevirtual getModifiers : ()I
    //   3918: invokestatic isStatic : (I)Z
    //   3921: ifne -> 3931
    //   3924: goto -> 4034
    //   3927: invokestatic a : (Ljava/lang/Throwable;)Ljava/lang/Throwable;
    //   3930: athrow
    //   3931: aload #9
    //   3933: invokevirtual getType : ()Ljava/lang/Class;
    //   3936: astore #10
    //   3938: aload #10
    //   3940: ifnull -> 4021
    //   3943: aload #10
    //   3945: invokevirtual isPrimitive : ()Z
    //   3948: ifne -> 4021
    //   3951: goto -> 3958
    //   3954: invokestatic a : (Ljava/lang/Throwable;)Ljava/lang/Throwable;
    //   3957: athrow
    //   3958: aload #10
    //   3960: invokevirtual getPackage : ()Ljava/lang/Package;
    //   3963: ifnull -> 4021
    //   3966: goto -> 3973
    //   3969: invokestatic a : (Ljava/lang/Throwable;)Ljava/lang/Throwable;
    //   3972: athrow
    //   3973: aload #10
    //   3975: invokevirtual getPackage : ()Ljava/lang/Package;
    //   3978: invokevirtual getName : ()Ljava/lang/String;
    //   3981: ifnull -> 4021
    //   3984: goto -> 3991
    //   3987: invokestatic a : (Ljava/lang/Throwable;)Ljava/lang/Throwable;
    //   3990: athrow
    //   3991: aload #10
    //   3993: invokevirtual getPackage : ()Ljava/lang/Package;
    //   3996: invokevirtual getName : ()Ljava/lang/String;
    //   3999: sipush #-7562
    //   4002: sipush #17029
    //   4005: invokestatic a : (II)Ljava/lang/String;
    //   4008: invokevirtual startsWith : (Ljava/lang/String;)Z
    //   4011: ifne -> 4021
    //   4014: goto -> 4021
    //   4017: invokestatic a : (Ljava/lang/Throwable;)Ljava/lang/Throwable;
    //   4020: athrow
    //   4021: aload #9
    //   4023: iconst_1
    //   4024: invokevirtual setAccessible : (Z)V
    //   4027: aload #9
    //   4029: aconst_null
    //   4030: invokevirtual get : (Ljava/lang/Object;)Ljava/lang/Object;
    //   4033: pop
    //   4034: iinc #8, 1
    //   4037: iload_2
    //   4038: ifne -> 3899
    //   4041: sipush #-7567
    //   4044: sipush #-26951
    //   4047: invokestatic a : (II)Ljava/lang/String;
    //   4050: invokestatic forName : (Ljava/lang/String;)Ljava/lang/Class;
    //   4053: invokevirtual getDeclaredMethods : ()[Ljava/lang/reflect/Method;
    //   4056: astore #6
    //   4058: aload #6
    //   4060: arraylength
    //   4061: istore #7
    //   4063: iconst_0
    //   4064: istore #8
    //   4066: iload #8
    //   4068: iload #7
    //   4070: if_icmpge -> 4207
    //   4073: aload #6
    //   4075: iload #8
    //   4077: aaload
    //   4078: astore #9
    //   4080: aload #9
    //   4082: invokevirtual getParameterTypes : ()[Ljava/lang/Class;
    //   4085: pop
    //   4086: aload #9
    //   4088: invokevirtual getModifiers : ()I
    //   4091: invokestatic isStatic : (I)Z
    //   4094: ifeq -> 4193
    //   4097: aload #9
    //   4099: invokevirtual getParameterTypes : ()[Ljava/lang/Class;
    //   4102: arraylength
    //   4103: iconst_2
    //   4104: if_icmpne -> 4193
    //   4107: goto -> 4114
    //   4110: invokestatic a : (Ljava/lang/Throwable;)Ljava/lang/Throwable;
    //   4113: athrow
    //   4114: aload #9
    //   4116: invokevirtual getReturnType : ()Ljava/lang/Class;
    //   4119: getstatic java/lang/Boolean.TYPE : Ljava/lang/Class;
    //   4122: if_acmpne -> 4193
    //   4125: goto -> 4132
    //   4128: invokestatic a : (Ljava/lang/Throwable;)Ljava/lang/Throwable;
    //   4131: athrow
    //   4132: aload #9
    //   4134: iconst_1
    //   4135: invokevirtual setAccessible : (Z)V
    //   4138: aload #9
    //   4140: aconst_null
    //   4141: iconst_2
    //   4142: anewarray java/lang/Object
    //   4145: dup
    //   4146: iconst_0
    //   4147: aload_0
    //   4148: aastore
    //   4149: dup
    //   4150: iconst_1
    //   4151: aload_1
    //   4152: ifnonnull -> 4170
    //   4155: goto -> 4162
    //   4158: invokestatic a : (Ljava/lang/Throwable;)Ljava/lang/Throwable;
    //   4161: athrow
    //   4162: aload_1
    //   4163: goto -> 4177
    //   4166: invokestatic a : (Ljava/lang/Throwable;)Ljava/lang/Throwable;
    //   4169: athrow
    //   4170: aload_1
    //   4171: checkcast [B
    //   4174: invokevirtual clone : ()Ljava/lang/Object;
    //   4177: aastore
    //   4178: invokevirtual invoke : (Ljava/lang/Object;[Ljava/lang/Object;)Ljava/lang/Object;
    //   4181: checkcast java/lang/Boolean
    //   4184: invokevirtual booleanValue : ()Z
    //   4187: istore #5
    //   4189: iload_2
    //   4190: ifne -> 4207
    //   4193: iinc #8, 1
    //   4196: iload_2
    //   4197: ifne -> 4066
    //   4200: goto -> 4207
    //   4203: invokestatic a : (Ljava/lang/Throwable;)Ljava/lang/Throwable;
    //   4206: athrow
    //   4207: iload_2
    //   4208: ifne -> 4550
    //   4211: sipush #-7581
    //   4214: sipush #-30481
    //   4217: invokestatic a : (II)Ljava/lang/String;
    //   4220: iconst_1
    //   4221: ldc burp/Zgjs
    //   4223: invokevirtual getClassLoader : ()Ljava/lang/ClassLoader;
    //   4226: invokestatic forName : (Ljava/lang/String;ZLjava/lang/ClassLoader;)Ljava/lang/Class;
    //   4229: invokevirtual getDeclaredFields : ()[Ljava/lang/reflect/Field;
    //   4232: astore #6
    //   4234: aload #6
    //   4236: arraylength
    //   4237: istore #7
    //   4239: iconst_0
    //   4240: istore #8
    //   4242: iload #8
    //   4244: iload #7
    //   4246: if_icmpge -> 4384
    //   4249: aload #6
    //   4251: iload #8
    //   4253: aaload
    //   4254: astore #9
    //   4256: aload #9
    //   4258: invokevirtual getModifiers : ()I
    //   4261: invokestatic isStatic : (I)Z
    //   4264: ifne -> 4274
    //   4267: goto -> 4377
    //   4270: invokestatic a : (Ljava/lang/Throwable;)Ljava/lang/Throwable;
    //   4273: athrow
    //   4274: aload #9
    //   4276: invokevirtual getType : ()Ljava/lang/Class;
    //   4279: astore #10
    //   4281: aload #10
    //   4283: ifnull -> 4364
    //   4286: aload #10
    //   4288: invokevirtual isPrimitive : ()Z
    //   4291: ifne -> 4364
    //   4294: goto -> 4301
    //   4297: invokestatic a : (Ljava/lang/Throwable;)Ljava/lang/Throwable;
    //   4300: athrow
    //   4301: aload #10
    //   4303: invokevirtual getPackage : ()Ljava/lang/Package;
    //   4306: ifnull -> 4364
    //   4309: goto -> 4316
    //   4312: invokestatic a : (Ljava/lang/Throwable;)Ljava/lang/Throwable;
    //   4315: athrow
    //   4316: aload #10
    //   4318: invokevirtual getPackage : ()Ljava/lang/Package;
    //   4321: invokevirtual getName : ()Ljava/lang/String;
    //   4324: ifnull -> 4364
    //   4327: goto -> 4334
    //   4330: invokestatic a : (Ljava/lang/Throwable;)Ljava/lang/Throwable;
    //   4333: athrow
    //   4334: aload #10
    //   4336: invokevirtual getPackage : ()Ljava/lang/Package;
    //   4339: invokevirtual getName : ()Ljava/lang/String;
    //   4342: sipush #-7562
    //   4345: sipush #17029
    //   4348: invokestatic a : (II)Ljava/lang/String;
    //   4351: invokevirtual startsWith : (Ljava/lang/String;)Z
    //   4354: ifne -> 4364
    //   4357: goto -> 4364
    //   4360: invokestatic a : (Ljava/lang/Throwable;)Ljava/lang/Throwable;
    //   4363: athrow
    //   4364: aload #9
    //   4366: iconst_1
    //   4367: invokevirtual setAccessible : (Z)V
    //   4370: aload #9
    //   4372: aconst_null
    //   4373: invokevirtual get : (Ljava/lang/Object;)Ljava/lang/Object;
    //   4376: pop
    //   4377: iinc #8, 1
    //   4380: iload_2
    //   4381: ifne -> 4242
    //   4384: sipush #-7575
    //   4387: sipush #-4013
    //   4390: invokestatic a : (II)Ljava/lang/String;
    //   4393: invokestatic forName : (Ljava/lang/String;)Ljava/lang/Class;
    //   4396: invokevirtual getDeclaredMethods : ()[Ljava/lang/reflect/Method;
    //   4399: astore #6
    //   4401: aload #6
    //   4403: arraylength
    //   4404: istore #7
    //   4406: iconst_0
    //   4407: istore #8
    //   4409: iload #8
    //   4411: iload #7
    //   4413: if_icmpge -> 4550
    //   4416: aload #6
    //   4418: iload #8
    //   4420: aaload
    //   4421: astore #9
    //   4423: aload #9
    //   4425: invokevirtual getParameterTypes : ()[Ljava/lang/Class;
    //   4428: pop
    //   4429: aload #9
    //   4431: invokevirtual getModifiers : ()I
    //   4434: invokestatic isStatic : (I)Z
    //   4437: ifeq -> 4536
    //   4440: aload #9
    //   4442: invokevirtual getParameterTypes : ()[Ljava/lang/Class;
    //   4445: arraylength
    //   4446: iconst_2
    //   4447: if_icmpne -> 4536
    //   4450: goto -> 4457
    //   4453: invokestatic a : (Ljava/lang/Throwable;)Ljava/lang/Throwable;
    //   4456: athrow
    //   4457: aload #9
    //   4459: invokevirtual getReturnType : ()Ljava/lang/Class;
    //   4462: getstatic java/lang/Boolean.TYPE : Ljava/lang/Class;
    //   4465: if_acmpne -> 4536
    //   4468: goto -> 4475
    //   4471: invokestatic a : (Ljava/lang/Throwable;)Ljava/lang/Throwable;
    //   4474: athrow
    //   4475: aload #9
    //   4477: iconst_1
    //   4478: invokevirtual setAccessible : (Z)V
    //   4481: aload #9
    //   4483: aconst_null
    //   4484: iconst_2
    //   4485: anewarray java/lang/Object
    //   4488: dup
    //   4489: iconst_0
    //   4490: aload_0
    //   4491: aastore
    //   4492: dup
    //   4493: iconst_1
    //   4494: aload_1
    //   4495: ifnonnull -> 4513
    //   4498: goto -> 4505
    //   4501: invokestatic a : (Ljava/lang/Throwable;)Ljava/lang/Throwable;
    //   4504: athrow
    //   4505: aload_1
    //   4506: goto -> 4520
    //   4509: invokestatic a : (Ljava/lang/Throwable;)Ljava/lang/Throwable;
    //   4512: athrow
    //   4513: aload_1
    //   4514: checkcast [B
    //   4517: invokevirtual clone : ()Ljava/lang/Object;
    //   4520: aastore
    //   4521: invokevirtual invoke : (Ljava/lang/Object;[Ljava/lang/Object;)Ljava/lang/Object;
    //   4524: checkcast java/lang/Boolean
    //   4527: invokevirtual booleanValue : ()Z
    //   4530: istore #5
    //   4532: iload_2
    //   4533: ifne -> 4550
    //   4536: iinc #8, 1
    //   4539: iload_2
    //   4540: ifne -> 4409
    //   4543: goto -> 4550
    //   4546: invokestatic a : (Ljava/lang/Throwable;)Ljava/lang/Throwable;
    //   4549: athrow
    //   4550: iload #5
    //   4552: ifeq -> 4558
    //   4555: iload #5
    //   4557: ireturn
    //   4558: getstatic burp/Zz66.ZM : Ljava/lang/String;
    //   4561: getstatic burp/Zzc9.ZZ : Ljava/lang/Object;
    //   4564: checkcast java/math/BigInteger
    //   4567: invokevirtual intValue : ()I
    //   4570: bipush #32
    //   4572: irem
    //   4573: invokestatic abs : (I)I
    //   4576: invokevirtual charAt : (I)C
    //   4579: getstatic burp/Zdv.Zz : Ljava/lang/String;
    //   4582: getstatic burp/Zb3d.Zw : Ljava/lang/Object;
    //   4585: checkcast java/math/BigInteger
    //   4588: invokevirtual intValue : ()I
    //   4591: bipush #32
    //   4593: irem
    //   4594: invokestatic abs : (I)I
    //   4597: invokevirtual charAt : (I)C
    //   4600: if_icmple -> 4946
    //   4603: sipush #-7580
    //   4606: sipush #-550
    //   4609: invokestatic a : (II)Ljava/lang/String;
    //   4612: iconst_1
    //   4613: ldc burp/Ztex
    //   4615: invokevirtual getClassLoader : ()Ljava/lang/ClassLoader;
    //   4618: invokestatic forName : (Ljava/lang/String;ZLjava/lang/ClassLoader;)Ljava/lang/Class;
    //   4621: invokevirtual getDeclaredFields : ()[Ljava/lang/reflect/Field;
    //   4624: astore #6
    //   4626: aload #6
    //   4628: arraylength
    //   4629: istore #7
    //   4631: iconst_0
    //   4632: istore #8
    //   4634: iload #8
    //   4636: iload #7
    //   4638: if_icmpge -> 4776
    //   4641: aload #6
    //   4643: iload #8
    //   4645: aaload
    //   4646: astore #9
    //   4648: aload #9
    //   4650: invokevirtual getModifiers : ()I
    //   4653: invokestatic isStatic : (I)Z
    //   4656: ifne -> 4666
    //   4659: goto -> 4769
    //   4662: invokestatic a : (Ljava/lang/Throwable;)Ljava/lang/Throwable;
    //   4665: athrow
    //   4666: aload #9
    //   4668: invokevirtual getType : ()Ljava/lang/Class;
    //   4671: astore #10
    //   4673: aload #10
    //   4675: ifnull -> 4756
    //   4678: aload #10
    //   4680: invokevirtual isPrimitive : ()Z
    //   4683: ifne -> 4756
    //   4686: goto -> 4693
    //   4689: invokestatic a : (Ljava/lang/Throwable;)Ljava/lang/Throwable;
    //   4692: athrow
    //   4693: aload #10
    //   4695: invokevirtual getPackage : ()Ljava/lang/Package;
    //   4698: ifnull -> 4756
    //   4701: goto -> 4708
    //   4704: invokestatic a : (Ljava/lang/Throwable;)Ljava/lang/Throwable;
    //   4707: athrow
    //   4708: aload #10
    //   4710: invokevirtual getPackage : ()Ljava/lang/Package;
    //   4713: invokevirtual getName : ()Ljava/lang/String;
    //   4716: ifnull -> 4756
    //   4719: goto -> 4726
    //   4722: invokestatic a : (Ljava/lang/Throwable;)Ljava/lang/Throwable;
    //   4725: athrow
    //   4726: aload #10
    //   4728: invokevirtual getPackage : ()Ljava/lang/Package;
    //   4731: invokevirtual getName : ()Ljava/lang/String;
    //   4734: sipush #-7562
    //   4737: sipush #17029
    //   4740: invokestatic a : (II)Ljava/lang/String;
    //   4743: invokevirtual startsWith : (Ljava/lang/String;)Z
    //   4746: ifne -> 4756
    //   4749: goto -> 4756
    //   4752: invokestatic a : (Ljava/lang/Throwable;)Ljava/lang/Throwable;
    //   4755: athrow
    //   4756: aload #9
    //   4758: iconst_1
    //   4759: invokevirtual setAccessible : (Z)V
    //   4762: aload #9
    //   4764: aconst_null
    //   4765: invokevirtual get : (Ljava/lang/Object;)Ljava/lang/Object;
    //   4768: pop
    //   4769: iinc #8, 1
    //   4772: iload_2
    //   4773: ifne -> 4634
    //   4776: sipush #-7565
    //   4779: sipush #-27379
    //   4782: invokestatic a : (II)Ljava/lang/String;
    //   4785: invokestatic forName : (Ljava/lang/String;)Ljava/lang/Class;
    //   4788: invokevirtual getDeclaredMethods : ()[Ljava/lang/reflect/Method;
    //   4791: astore #6
    //   4793: aload #6
    //   4795: arraylength
    //   4796: istore #7
    //   4798: iconst_0
    //   4799: istore #8
    //   4801: iload #8
    //   4803: iload #7
    //   4805: if_icmpge -> 4942
    //   4808: aload #6
    //   4810: iload #8
    //   4812: aaload
    //   4813: astore #9
    //   4815: aload #9
    //   4817: invokevirtual getParameterTypes : ()[Ljava/lang/Class;
    //   4820: pop
    //   4821: aload #9
    //   4823: invokevirtual getModifiers : ()I
    //   4826: invokestatic isStatic : (I)Z
    //   4829: ifeq -> 4928
    //   4832: aload #9
    //   4834: invokevirtual getParameterTypes : ()[Ljava/lang/Class;
    //   4837: arraylength
    //   4838: iconst_2
    //   4839: if_icmpne -> 4928
    //   4842: goto -> 4849
    //   4845: invokestatic a : (Ljava/lang/Throwable;)Ljava/lang/Throwable;
    //   4848: athrow
    //   4849: aload #9
    //   4851: invokevirtual getReturnType : ()Ljava/lang/Class;
    //   4854: getstatic java/lang/Boolean.TYPE : Ljava/lang/Class;
    //   4857: if_acmpne -> 4928
    //   4860: goto -> 4867
    //   4863: invokestatic a : (Ljava/lang/Throwable;)Ljava/lang/Throwable;
    //   4866: athrow
    //   4867: aload #9
    //   4869: iconst_1
    //   4870: invokevirtual setAccessible : (Z)V
    //   4873: aload #9
    //   4875: aconst_null
    //   4876: iconst_2
    //   4877: anewarray java/lang/Object
    //   4880: dup
    //   4881: iconst_0
    //   4882: aload_0
    //   4883: aastore
    //   4884: dup
    //   4885: iconst_1
    //   4886: aload_1
    //   4887: ifnonnull -> 4905
    //   4890: goto -> 4897
    //   4893: invokestatic a : (Ljava/lang/Throwable;)Ljava/lang/Throwable;
    //   4896: athrow
    //   4897: aload_1
    //   4898: goto -> 4912
    //   4901: invokestatic a : (Ljava/lang/Throwable;)Ljava/lang/Throwable;
    //   4904: athrow
    //   4905: aload_1
    //   4906: checkcast [B
    //   4909: invokevirtual clone : ()Ljava/lang/Object;
    //   4912: aastore
    //   4913: invokevirtual invoke : (Ljava/lang/Object;[Ljava/lang/Object;)Ljava/lang/Object;
    //   4916: checkcast java/lang/Boolean
    //   4919: invokevirtual booleanValue : ()Z
    //   4922: istore #5
    //   4924: iload_2
    //   4925: ifne -> 4942
    //   4928: iinc #8, 1
    //   4931: iload_2
    //   4932: ifne -> 4801
    //   4935: goto -> 4942
    //   4938: invokestatic a : (Ljava/lang/Throwable;)Ljava/lang/Throwable;
    //   4941: athrow
    //   4942: iload_2
    //   4943: ifne -> 5284
    //   4946: sipush #-7576
    //   4949: sipush #-12516
    //   4952: invokestatic a : (II)Ljava/lang/String;
    //   4955: iconst_1
    //   4956: ldc burp/Zxxf
    //   4958: invokevirtual getClassLoader : ()Ljava/lang/ClassLoader;
    //   4961: invokestatic forName : (Ljava/lang/String;ZLjava/lang/ClassLoader;)Ljava/lang/Class;
    //   4964: invokevirtual getDeclaredFields : ()[Ljava/lang/reflect/Field;
    //   4967: astore #6
    //   4969: aload #6
    //   4971: arraylength
    //   4972: istore #7
    //   4974: iconst_0
    //   4975: istore #8
    //   4977: iload #8
    //   4979: iload #7
    //   4981: if_icmpge -> 5119
    //   4984: aload #6
    //   4986: iload #8
    //   4988: aaload
    //   4989: astore #9
    //   4991: aload #9
    //   4993: invokevirtual getModifiers : ()I
    //   4996: invokestatic isStatic : (I)Z
    //   4999: ifne -> 5009
    //   5002: goto -> 5112
    //   5005: invokestatic a : (Ljava/lang/Throwable;)Ljava/lang/Throwable;
    //   5008: athrow
    //   5009: aload #9
    //   5011: invokevirtual getType : ()Ljava/lang/Class;
    //   5014: astore #10
    //   5016: aload #10
    //   5018: ifnull -> 5099
    //   5021: aload #10
    //   5023: invokevirtual isPrimitive : ()Z
    //   5026: ifne -> 5099
    //   5029: goto -> 5036
    //   5032: invokestatic a : (Ljava/lang/Throwable;)Ljava/lang/Throwable;
    //   5035: athrow
    //   5036: aload #10
    //   5038: invokevirtual getPackage : ()Ljava/lang/Package;
    //   5041: ifnull -> 5099
    //   5044: goto -> 5051
    //   5047: invokestatic a : (Ljava/lang/Throwable;)Ljava/lang/Throwable;
    //   5050: athrow
    //   5051: aload #10
    //   5053: invokevirtual getPackage : ()Ljava/lang/Package;
    //   5056: invokevirtual getName : ()Ljava/lang/String;
    //   5059: ifnull -> 5099
    //   5062: goto -> 5069
    //   5065: invokestatic a : (Ljava/lang/Throwable;)Ljava/lang/Throwable;
    //   5068: athrow
    //   5069: aload #10
    //   5071: invokevirtual getPackage : ()Ljava/lang/Package;
    //   5074: invokevirtual getName : ()Ljava/lang/String;
    //   5077: sipush #-7562
    //   5080: sipush #17029
    //   5083: invokestatic a : (II)Ljava/lang/String;
    //   5086: invokevirtual startsWith : (Ljava/lang/String;)Z
    //   5089: ifne -> 5099
    //   5092: goto -> 5099
    //   5095: invokestatic a : (Ljava/lang/Throwable;)Ljava/lang/Throwable;
    //   5098: athrow
    //   5099: aload #9
    //   5101: iconst_1
    //   5102: invokevirtual setAccessible : (Z)V
    //   5105: aload #9
    //   5107: aconst_null
    //   5108: invokevirtual get : (Ljava/lang/Object;)Ljava/lang/Object;
    //   5111: pop
    //   5112: iinc #8, 1
    //   5115: iload_2
    //   5116: ifne -> 4977
    //   5119: sipush #-7582
    //   5122: bipush #28
    //   5124: invokestatic a : (II)Ljava/lang/String;
    //   5127: invokestatic forName : (Ljava/lang/String;)Ljava/lang/Class;
    //   5130: invokevirtual getDeclaredMethods : ()[Ljava/lang/reflect/Method;
    //   5133: astore #6
    //   5135: aload #6
    //   5137: arraylength
    //   5138: istore #7
    //   5140: iconst_0
    //   5141: istore #8
    //   5143: iload #8
    //   5145: iload #7
    //   5147: if_icmpge -> 5284
    //   5150: aload #6
    //   5152: iload #8
    //   5154: aaload
    //   5155: astore #9
    //   5157: aload #9
    //   5159: invokevirtual getParameterTypes : ()[Ljava/lang/Class;
    //   5162: pop
    //   5163: aload #9
    //   5165: invokevirtual getModifiers : ()I
    //   5168: invokestatic isStatic : (I)Z
    //   5171: ifeq -> 5270
    //   5174: aload #9
    //   5176: invokevirtual getParameterTypes : ()[Ljava/lang/Class;
    //   5179: arraylength
    //   5180: iconst_2
    //   5181: if_icmpne -> 5270
    //   5184: goto -> 5191
    //   5187: invokestatic a : (Ljava/lang/Throwable;)Ljava/lang/Throwable;
    //   5190: athrow
    //   5191: aload #9
    //   5193: invokevirtual getReturnType : ()Ljava/lang/Class;
    //   5196: getstatic java/lang/Boolean.TYPE : Ljava/lang/Class;
    //   5199: if_acmpne -> 5270
    //   5202: goto -> 5209
    //   5205: invokestatic a : (Ljava/lang/Throwable;)Ljava/lang/Throwable;
    //   5208: athrow
    //   5209: aload #9
    //   5211: iconst_1
    //   5212: invokevirtual setAccessible : (Z)V
    //   5215: aload #9
    //   5217: aconst_null
    //   5218: iconst_2
    //   5219: anewarray java/lang/Object
    //   5222: dup
    //   5223: iconst_0
    //   5224: aload_0
    //   5225: aastore
    //   5226: dup
    //   5227: iconst_1
    //   5228: aload_1
    //   5229: ifnonnull -> 5247
    //   5232: goto -> 5239
    //   5235: invokestatic a : (Ljava/lang/Throwable;)Ljava/lang/Throwable;
    //   5238: athrow
    //   5239: aload_1
    //   5240: goto -> 5254
    //   5243: invokestatic a : (Ljava/lang/Throwable;)Ljava/lang/Throwable;
    //   5246: athrow
    //   5247: aload_1
    //   5248: checkcast [B
    //   5251: invokevirtual clone : ()Ljava/lang/Object;
    //   5254: aastore
    //   5255: invokevirtual invoke : (Ljava/lang/Object;[Ljava/lang/Object;)Ljava/lang/Object;
    //   5258: checkcast java/lang/Boolean
    //   5261: invokevirtual booleanValue : ()Z
    //   5264: istore #5
    //   5266: iload_2
    //   5267: ifne -> 5284
    //   5270: iinc #8, 1
    //   5273: iload_2
    //   5274: ifne -> 5143
    //   5277: goto -> 5284
    //   5280: invokestatic a : (Ljava/lang/Throwable;)Ljava/lang/Throwable;
    //   5283: athrow
    //   5284: iload #5
    //   5286: ifeq -> 5292
    //   5289: iload #5
    //   5291: ireturn
    //   5292: getstatic burp/Zz5e.Zd : Ljava/lang/String;
    //   5295: getstatic burp/Zrye.Zx : Ljava/lang/Object;
    //   5298: checkcast java/math/BigInteger
    //   5301: invokevirtual intValue : ()I
    //   5304: bipush #32
    //   5306: irem
    //   5307: invokestatic abs : (I)I
    //   5310: invokevirtual charAt : (I)C
    //   5313: getstatic burp/Zsn9.Zp : Ljava/lang/String;
    //   5316: getstatic burp/Zxdy.ZZ : Ljava/lang/Object;
    //   5319: checkcast java/math/BigInteger
    //   5322: invokevirtual intValue : ()I
    //   5325: bipush #32
    //   5327: irem
    //   5328: invokestatic abs : (I)I
    //   5331: invokevirtual charAt : (I)C
    //   5334: if_icmpgt -> 5680
    //   5337: sipush #-7571
    //   5340: sipush #532
    //   5343: invokestatic a : (II)Ljava/lang/String;
    //   5346: iconst_1
    //   5347: ldc burp/Zs0h
    //   5349: invokevirtual getClassLoader : ()Ljava/lang/ClassLoader;
    //   5352: invokestatic forName : (Ljava/lang/String;ZLjava/lang/ClassLoader;)Ljava/lang/Class;
    //   5355: invokevirtual getDeclaredFields : ()[Ljava/lang/reflect/Field;
    //   5358: astore #6
    //   5360: aload #6
    //   5362: arraylength
    //   5363: istore #7
    //   5365: iconst_0
    //   5366: istore #8
    //   5368: iload #8
    //   5370: iload #7
    //   5372: if_icmpge -> 5510
    //   5375: aload #6
    //   5377: iload #8
    //   5379: aaload
    //   5380: astore #9
    //   5382: aload #9
    //   5384: invokevirtual getModifiers : ()I
    //   5387: invokestatic isStatic : (I)Z
    //   5390: ifne -> 5400
    //   5393: goto -> 5503
    //   5396: invokestatic a : (Ljava/lang/Throwable;)Ljava/lang/Throwable;
    //   5399: athrow
    //   5400: aload #9
    //   5402: invokevirtual getType : ()Ljava/lang/Class;
    //   5405: astore #10
    //   5407: aload #10
    //   5409: ifnull -> 5490
    //   5412: aload #10
    //   5414: invokevirtual isPrimitive : ()Z
    //   5417: ifne -> 5490
    //   5420: goto -> 5427
    //   5423: invokestatic a : (Ljava/lang/Throwable;)Ljava/lang/Throwable;
    //   5426: athrow
    //   5427: aload #10
    //   5429: invokevirtual getPackage : ()Ljava/lang/Package;
    //   5432: ifnull -> 5490
    //   5435: goto -> 5442
    //   5438: invokestatic a : (Ljava/lang/Throwable;)Ljava/lang/Throwable;
    //   5441: athrow
    //   5442: aload #10
    //   5444: invokevirtual getPackage : ()Ljava/lang/Package;
    //   5447: invokevirtual getName : ()Ljava/lang/String;
    //   5450: ifnull -> 5490
    //   5453: goto -> 5460
    //   5456: invokestatic a : (Ljava/lang/Throwable;)Ljava/lang/Throwable;
    //   5459: athrow
    //   5460: aload #10
    //   5462: invokevirtual getPackage : ()Ljava/lang/Package;
    //   5465: invokevirtual getName : ()Ljava/lang/String;
    //   5468: sipush #-7562
    //   5471: sipush #17029
    //   5474: invokestatic a : (II)Ljava/lang/String;
    //   5477: invokevirtual startsWith : (Ljava/lang/String;)Z
    //   5480: ifne -> 5490
    //   5483: goto -> 5490
    //   5486: invokestatic a : (Ljava/lang/Throwable;)Ljava/lang/Throwable;
    //   5489: athrow
    //   5490: aload #9
    //   5492: iconst_1
    //   5493: invokevirtual setAccessible : (Z)V
    //   5496: aload #9
    //   5498: aconst_null
    //   5499: invokevirtual get : (Ljava/lang/Object;)Ljava/lang/Object;
    //   5502: pop
    //   5503: iinc #8, 1
    //   5506: iload_2
    //   5507: ifne -> 5368
    //   5510: sipush #-7570
    //   5513: sipush #-25570
    //   5516: invokestatic a : (II)Ljava/lang/String;
    //   5519: invokestatic forName : (Ljava/lang/String;)Ljava/lang/Class;
    //   5522: invokevirtual getDeclaredMethods : ()[Ljava/lang/reflect/Method;
    //   5525: astore #6
    //   5527: aload #6
    //   5529: arraylength
    //   5530: istore #7
    //   5532: iconst_0
    //   5533: istore #8
    //   5535: iload #8
    //   5537: iload #7
    //   5539: if_icmpge -> 5676
    //   5542: aload #6
    //   5544: iload #8
    //   5546: aaload
    //   5547: astore #9
    //   5549: aload #9
    //   5551: invokevirtual getParameterTypes : ()[Ljava/lang/Class;
    //   5554: pop
    //   5555: aload #9
    //   5557: invokevirtual getModifiers : ()I
    //   5560: invokestatic isStatic : (I)Z
    //   5563: ifeq -> 5662
    //   5566: aload #9
    //   5568: invokevirtual getParameterTypes : ()[Ljava/lang/Class;
    //   5571: arraylength
    //   5572: iconst_2
    //   5573: if_icmpne -> 5662
    //   5576: goto -> 5583
    //   5579: invokestatic a : (Ljava/lang/Throwable;)Ljava/lang/Throwable;
    //   5582: athrow
    //   5583: aload #9
    //   5585: invokevirtual getReturnType : ()Ljava/lang/Class;
    //   5588: getstatic java/lang/Boolean.TYPE : Ljava/lang/Class;
    //   5591: if_acmpne -> 5662
    //   5594: goto -> 5601
    //   5597: invokestatic a : (Ljava/lang/Throwable;)Ljava/lang/Throwable;
    //   5600: athrow
    //   5601: aload #9
    //   5603: iconst_1
    //   5604: invokevirtual setAccessible : (Z)V
    //   5607: aload #9
    //   5609: aconst_null
    //   5610: iconst_2
    //   5611: anewarray java/lang/Object
    //   5614: dup
    //   5615: iconst_0
    //   5616: aload_0
    //   5617: aastore
    //   5618: dup
    //   5619: iconst_1
    //   5620: aload_1
    //   5621: ifnonnull -> 5639
    //   5624: goto -> 5631
    //   5627: invokestatic a : (Ljava/lang/Throwable;)Ljava/lang/Throwable;
    //   5630: athrow
    //   5631: aload_1
    //   5632: goto -> 5646
    //   5635: invokestatic a : (Ljava/lang/Throwable;)Ljava/lang/Throwable;
    //   5638: athrow
    //   5639: aload_1
    //   5640: checkcast [B
    //   5643: invokevirtual clone : ()Ljava/lang/Object;
    //   5646: aastore
    //   5647: invokevirtual invoke : (Ljava/lang/Object;[Ljava/lang/Object;)Ljava/lang/Object;
    //   5650: checkcast java/lang/Boolean
    //   5653: invokevirtual booleanValue : ()Z
    //   5656: istore #5
    //   5658: iload_2
    //   5659: ifne -> 5676
    //   5662: iinc #8, 1
    //   5665: iload_2
    //   5666: ifne -> 5535
    //   5669: goto -> 5676
    //   5672: invokestatic a : (Ljava/lang/Throwable;)Ljava/lang/Throwable;
    //   5675: athrow
    //   5676: iload_2
    //   5677: ifne -> 6019
    //   5680: sipush #-7561
    //   5683: sipush #23684
    //   5686: invokestatic a : (II)Ljava/lang/String;
    //   5689: iconst_1
    //   5690: ldc burp/Zrj3
    //   5692: invokevirtual getClassLoader : ()Ljava/lang/ClassLoader;
    //   5695: invokestatic forName : (Ljava/lang/String;ZLjava/lang/ClassLoader;)Ljava/lang/Class;
    //   5698: invokevirtual getDeclaredFields : ()[Ljava/lang/reflect/Field;
    //   5701: astore #6
    //   5703: aload #6
    //   5705: arraylength
    //   5706: istore #7
    //   5708: iconst_0
    //   5709: istore #8
    //   5711: iload #8
    //   5713: iload #7
    //   5715: if_icmpge -> 5853
    //   5718: aload #6
    //   5720: iload #8
    //   5722: aaload
    //   5723: astore #9
    //   5725: aload #9
    //   5727: invokevirtual getModifiers : ()I
    //   5730: invokestatic isStatic : (I)Z
    //   5733: ifne -> 5743
    //   5736: goto -> 5846
    //   5739: invokestatic a : (Ljava/lang/Throwable;)Ljava/lang/Throwable;
    //   5742: athrow
    //   5743: aload #9
    //   5745: invokevirtual getType : ()Ljava/lang/Class;
    //   5748: astore #10
    //   5750: aload #10
    //   5752: ifnull -> 5833
    //   5755: aload #10
    //   5757: invokevirtual isPrimitive : ()Z
    //   5760: ifne -> 5833
    //   5763: goto -> 5770
    //   5766: invokestatic a : (Ljava/lang/Throwable;)Ljava/lang/Throwable;
    //   5769: athrow
    //   5770: aload #10
    //   5772: invokevirtual getPackage : ()Ljava/lang/Package;
    //   5775: ifnull -> 5833
    //   5778: goto -> 5785
    //   5781: invokestatic a : (Ljava/lang/Throwable;)Ljava/lang/Throwable;
    //   5784: athrow
    //   5785: aload #10
    //   5787: invokevirtual getPackage : ()Ljava/lang/Package;
    //   5790: invokevirtual getName : ()Ljava/lang/String;
    //   5793: ifnull -> 5833
    //   5796: goto -> 5803
    //   5799: invokestatic a : (Ljava/lang/Throwable;)Ljava/lang/Throwable;
    //   5802: athrow
    //   5803: aload #10
    //   5805: invokevirtual getPackage : ()Ljava/lang/Package;
    //   5808: invokevirtual getName : ()Ljava/lang/String;
    //   5811: sipush #-7562
    //   5814: sipush #17029
    //   5817: invokestatic a : (II)Ljava/lang/String;
    //   5820: invokevirtual startsWith : (Ljava/lang/String;)Z
    //   5823: ifne -> 5833
    //   5826: goto -> 5833
    //   5829: invokestatic a : (Ljava/lang/Throwable;)Ljava/lang/Throwable;
    //   5832: athrow
    //   5833: aload #9
    //   5835: iconst_1
    //   5836: invokevirtual setAccessible : (Z)V
    //   5839: aload #9
    //   5841: aconst_null
    //   5842: invokevirtual get : (Ljava/lang/Object;)Ljava/lang/Object;
    //   5845: pop
    //   5846: iinc #8, 1
    //   5849: iload_2
    //   5850: ifne -> 5711
    //   5853: sipush #-7578
    //   5856: sipush #-2035
    //   5859: invokestatic a : (II)Ljava/lang/String;
    //   5862: invokestatic forName : (Ljava/lang/String;)Ljava/lang/Class;
    //   5865: invokevirtual getDeclaredMethods : ()[Ljava/lang/reflect/Method;
    //   5868: astore #6
    //   5870: aload #6
    //   5872: arraylength
    //   5873: istore #7
    //   5875: iconst_0
    //   5876: istore #8
    //   5878: iload #8
    //   5880: iload #7
    //   5882: if_icmpge -> 6019
    //   5885: aload #6
    //   5887: iload #8
    //   5889: aaload
    //   5890: astore #9
    //   5892: aload #9
    //   5894: invokevirtual getParameterTypes : ()[Ljava/lang/Class;
    //   5897: pop
    //   5898: aload #9
    //   5900: invokevirtual getModifiers : ()I
    //   5903: invokestatic isStatic : (I)Z
    //   5906: ifeq -> 6005
    //   5909: aload #9
    //   5911: invokevirtual getParameterTypes : ()[Ljava/lang/Class;
    //   5914: arraylength
    //   5915: iconst_2
    //   5916: if_icmpne -> 6005
    //   5919: goto -> 5926
    //   5922: invokestatic a : (Ljava/lang/Throwable;)Ljava/lang/Throwable;
    //   5925: athrow
    //   5926: aload #9
    //   5928: invokevirtual getReturnType : ()Ljava/lang/Class;
    //   5931: getstatic java/lang/Boolean.TYPE : Ljava/lang/Class;
    //   5934: if_acmpne -> 6005
    //   5937: goto -> 5944
    //   5940: invokestatic a : (Ljava/lang/Throwable;)Ljava/lang/Throwable;
    //   5943: athrow
    //   5944: aload #9
    //   5946: iconst_1
    //   5947: invokevirtual setAccessible : (Z)V
    //   5950: aload #9
    //   5952: aconst_null
    //   5953: iconst_2
    //   5954: anewarray java/lang/Object
    //   5957: dup
    //   5958: iconst_0
    //   5959: aload_0
    //   5960: aastore
    //   5961: dup
    //   5962: iconst_1
    //   5963: aload_1
    //   5964: ifnonnull -> 5982
    //   5967: goto -> 5974
    //   5970: invokestatic a : (Ljava/lang/Throwable;)Ljava/lang/Throwable;
    //   5973: athrow
    //   5974: aload_1
    //   5975: goto -> 5989
    //   5978: invokestatic a : (Ljava/lang/Throwable;)Ljava/lang/Throwable;
    //   5981: athrow
    //   5982: aload_1
    //   5983: checkcast [B
    //   5986: invokevirtual clone : ()Ljava/lang/Object;
    //   5989: aastore
    //   5990: invokevirtual invoke : (Ljava/lang/Object;[Ljava/lang/Object;)Ljava/lang/Object;
    //   5993: checkcast java/lang/Boolean
    //   5996: invokevirtual booleanValue : ()Z
    //   5999: istore #5
    //   6001: iload_2
    //   6002: ifne -> 6019
    //   6005: iinc #8, 1
    //   6008: iload_2
    //   6009: ifne -> 5878
    //   6012: goto -> 6019
    //   6015: invokestatic a : (Ljava/lang/Throwable;)Ljava/lang/Throwable;
    //   6018: athrow
    //   6019: iload #5
    //   6021: ireturn
    //   6022: astore_3
    //   6023: new java/lang/Exception
    //   6026: dup
    //   6027: aload_3
    //   6028: invokevirtual getMessage : ()Ljava/lang/String;
    //   6031: invokespecial <init> : (Ljava/lang/String;)V
    //   6034: athrow
    // Exception table:
    //   from	to	target	type
    //   4	3822	6022	java/lang/Throwable
    //   22	198	201	java/lang/Throwable
    //   168	235	238	java/lang/Throwable
    //   205	272	275	java/lang/Throwable
    //   242	309	312	java/lang/Throwable
    //   279	346	349	java/lang/Throwable
    //   316	383	386	java/lang/Throwable
    //   353	420	423	java/lang/Throwable
    //   390	457	460	java/lang/Throwable
    //   427	494	497	java/lang/Throwable
    //   464	531	534	java/lang/Throwable
    //   501	568	571	java/lang/Throwable
    //   538	605	608	java/lang/Throwable
    //   575	642	645	java/lang/Throwable
    //   612	679	682	java/lang/Throwable
    //   649	716	719	java/lang/Throwable
    //   686	753	756	java/lang/Throwable
    //   723	790	793	java/lang/Throwable
    //   760	827	830	java/lang/Throwable
    //   797	864	867	java/lang/Throwable
    //   834	901	904	java/lang/Throwable
    //   871	938	941	java/lang/Throwable
    //   908	975	978	java/lang/Throwable
    //   945	1012	1015	java/lang/Throwable
    //   982	1049	1052	java/lang/Throwable
    //   1019	1086	1089	java/lang/Throwable
    //   1056	1123	1126	java/lang/Throwable
    //   1093	1160	1163	java/lang/Throwable
    //   1130	1197	1200	java/lang/Throwable
    //   1167	1234	1237	java/lang/Throwable
    //   1204	1271	1274	java/lang/Throwable
    //   1241	1308	1311	java/lang/Throwable
    //   1278	1341	1344	java/lang/Throwable
    //   1381	1555	1558	java/lang/Throwable
    //   1524	1593	1596	java/lang/Throwable
    //   1562	1631	1634	java/lang/Throwable
    //   1600	1669	1672	java/lang/Throwable
    //   1638	1707	1710	java/lang/Throwable
    //   1676	1745	1748	java/lang/Throwable
    //   1714	1783	1786	java/lang/Throwable
    //   1752	1821	1824	java/lang/Throwable
    //   1790	1859	1862	java/lang/Throwable
    //   1828	1897	1900	java/lang/Throwable
    //   1866	1935	1938	java/lang/Throwable
    //   1904	1973	1976	java/lang/Throwable
    //   1942	2011	2014	java/lang/Throwable
    //   1980	2049	2052	java/lang/Throwable
    //   2018	2087	2090	java/lang/Throwable
    //   2056	2125	2128	java/lang/Throwable
    //   2094	2163	2166	java/lang/Throwable
    //   2132	2201	2204	java/lang/Throwable
    //   2170	2239	2242	java/lang/Throwable
    //   2208	2277	2280	java/lang/Throwable
    //   2246	2315	2318	java/lang/Throwable
    //   2284	2353	2356	java/lang/Throwable
    //   2322	2391	2394	java/lang/Throwable
    //   2360	2429	2432	java/lang/Throwable
    //   2398	2467	2470	java/lang/Throwable
    //   2436	2505	2508	java/lang/Throwable
    //   2474	2543	2546	java/lang/Throwable
    //   2512	2581	2584	java/lang/Throwable
    //   2550	2619	2622	java/lang/Throwable
    //   2588	2657	2660	java/lang/Throwable
    //   2626	2695	2698	java/lang/Throwable
    //   2664	2729	2732	java/lang/Throwable
    //   2796	2810	2810	java/lang/Throwable
    //   2821	2834	2837	java/lang/Throwable
    //   2826	2849	2852	java/lang/Throwable
    //   2841	2867	2870	java/lang/Throwable
    //   2856	2897	2900	java/lang/Throwable
    //   2963	2990	2993	java/lang/Throwable
    //   2980	3011	3014	java/lang/Throwable
    //   2997	3041	3044	java/lang/Throwable
    //   3018	3052	3052	java/lang/Throwable
    //   3063	3079	3082	java/lang/Throwable
    //   3179	3193	3193	java/lang/Throwable
    //   3204	3217	3220	java/lang/Throwable
    //   3209	3232	3235	java/lang/Throwable
    //   3224	3250	3253	java/lang/Throwable
    //   3239	3280	3283	java/lang/Throwable
    //   3346	3373	3376	java/lang/Throwable
    //   3363	3391	3394	java/lang/Throwable
    //   3380	3421	3424	java/lang/Throwable
    //   3398	3432	3432	java/lang/Throwable
    //   3455	3466	3469	java/lang/Throwable
    //   3521	3535	3535	java/lang/Throwable
    //   3546	3559	3562	java/lang/Throwable
    //   3551	3574	3577	java/lang/Throwable
    //   3566	3592	3595	java/lang/Throwable
    //   3581	3622	3625	java/lang/Throwable
    //   3688	3715	3718	java/lang/Throwable
    //   3705	3733	3736	java/lang/Throwable
    //   3722	3763	3766	java/lang/Throwable
    //   3740	3774	3774	java/lang/Throwable
    //   3797	3808	3811	java/lang/Throwable
    //   3823	4557	6022	java/lang/Throwable
    //   3913	3927	3927	java/lang/Throwable
    //   3938	3951	3954	java/lang/Throwable
    //   3943	3966	3969	java/lang/Throwable
    //   3958	3984	3987	java/lang/Throwable
    //   3973	4014	4017	java/lang/Throwable
    //   4080	4107	4110	java/lang/Throwable
    //   4097	4125	4128	java/lang/Throwable
    //   4114	4155	4158	java/lang/Throwable
    //   4132	4166	4166	java/lang/Throwable
    //   4189	4200	4203	java/lang/Throwable
    //   4256	4270	4270	java/lang/Throwable
    //   4281	4294	4297	java/lang/Throwable
    //   4286	4309	4312	java/lang/Throwable
    //   4301	4327	4330	java/lang/Throwable
    //   4316	4357	4360	java/lang/Throwable
    //   4423	4450	4453	java/lang/Throwable
    //   4440	4468	4471	java/lang/Throwable
    //   4457	4498	4501	java/lang/Throwable
    //   4475	4509	4509	java/lang/Throwable
    //   4532	4543	4546	java/lang/Throwable
    //   4558	5291	6022	java/lang/Throwable
    //   4648	4662	4662	java/lang/Throwable
    //   4673	4686	4689	java/lang/Throwable
    //   4678	4701	4704	java/lang/Throwable
    //   4693	4719	4722	java/lang/Throwable
    //   4708	4749	4752	java/lang/Throwable
    //   4815	4842	4845	java/lang/Throwable
    //   4832	4860	4863	java/lang/Throwable
    //   4849	4890	4893	java/lang/Throwable
    //   4867	4901	4901	java/lang/Throwable
    //   4924	4935	4938	java/lang/Throwable
    //   4991	5005	5005	java/lang/Throwable
    //   5016	5029	5032	java/lang/Throwable
    //   5021	5044	5047	java/lang/Throwable
    //   5036	5062	5065	java/lang/Throwable
    //   5051	5092	5095	java/lang/Throwable
    //   5157	5184	5187	java/lang/Throwable
    //   5174	5202	5205	java/lang/Throwable
    //   5191	5232	5235	java/lang/Throwable
    //   5209	5243	5243	java/lang/Throwable
    //   5266	5277	5280	java/lang/Throwable
    //   5292	6021	6022	java/lang/Throwable
    //   5382	5396	5396	java/lang/Throwable
    //   5407	5420	5423	java/lang/Throwable
    //   5412	5435	5438	java/lang/Throwable
    //   5427	5453	5456	java/lang/Throwable
    //   5442	5483	5486	java/lang/Throwable
    //   5549	5576	5579	java/lang/Throwable
    //   5566	5594	5597	java/lang/Throwable
    //   5583	5624	5627	java/lang/Throwable
    //   5601	5635	5635	java/lang/Throwable
    //   5658	5669	5672	java/lang/Throwable
    //   5725	5739	5739	java/lang/Throwable
    //   5750	5763	5766	java/lang/Throwable
    //   5755	5778	5781	java/lang/Throwable
    //   5770	5796	5799	java/lang/Throwable
    //   5785	5826	5829	java/lang/Throwable
    //   5892	5919	5922	java/lang/Throwable
    //   5909	5937	5940	java/lang/Throwable
    //   5926	5967	5970	java/lang/Throwable
    //   5944	5978	5978	java/lang/Throwable
    //   6001	6012	6015	java/lang/Throwable
  }
  
  static void ZG(Object[] paramArrayOfObject, Object paramObject) throws Throwable {}
  
  static {
    // Byte code:
    //   0: bipush #25
    //   2: anewarray java/lang/String
    //   5: astore #5
    //   7: iconst_0
    //   8: istore_3
    //   9: ldc 'Nh}\\tH`\\tR$yVH\\tyiA\\twKV\\t,i+W)K\\t$u>\\tssL5c\\tS\\tL1P\\\tmV#\\tKLVif70x`lPPaZI u:JuP6t$SGze\\t'\\n\\t|guP\\t,x\\th)c7\\nK(:)\\twD4& qW:'|Q-\\byrqi{ioOt\\tt\\n oOC[M- tOkP~XX&\\t}Yp['
    //   11: dup
    //   12: astore_2
    //   13: invokevirtual length : ()I
    //   16: istore #4
    //   18: bipush #9
    //   20: istore_1
    //   21: iconst_m1
    //   22: istore_0
    //   23: bipush #42
    //   25: iinc #0, 1
    //   28: aload_2
    //   29: iload_0
    //   30: dup
    //   31: iload_1
    //   32: iadd
    //   33: invokevirtual substring : (II)Ljava/lang/String;
    //   36: iconst_m1
    //   37: goto -> 143
    //   40: aload #5
    //   42: swap
    //   43: iload_3
    //   44: iinc #3, 1
    //   47: swap
    //   48: aastore
    //   49: iload_0
    //   50: iload_1
    //   51: iadd
    //   52: dup
    //   53: istore_0
    //   54: iload #4
    //   56: if_icmpge -> 68
    //   59: aload_2
    //   60: iload_0
    //   61: invokevirtual charAt : (I)C
    //   64: istore_1
    //   65: goto -> 23
    //   68: ldc '^8i_d\\tKM'
    //   70: dup
    //   71: astore_2
    //   72: invokevirtual length : ()I
    //   75: istore #4
    //   77: bipush #9
    //   79: istore_1
    //   80: iconst_m1
    //   81: istore_0
    //   82: bipush #89
    //   84: iinc #0, 1
    //   87: aload_2
    //   88: iload_0
    //   89: dup
    //   90: iload_1
    //   91: iadd
    //   92: invokevirtual substring : (II)Ljava/lang/String;
    //   95: iconst_0
    //   96: goto -> 143
    //   99: aload #5
    //   101: swap
    //   102: iload_3
    //   103: iinc #3, 1
    //   106: swap
    //   107: aastore
    //   108: iload_0
    //   109: iload_1
    //   110: iadd
    //   111: dup
    //   112: istore_0
    //   113: iload #4
    //   115: if_icmpge -> 127
    //   118: aload_2
    //   119: iload_0
    //   120: invokevirtual charAt : (I)C
    //   123: istore_1
    //   124: goto -> 82
    //   127: aload #5
    //   129: putstatic burp/Zz0b.a : [Ljava/lang/String;
    //   132: bipush #25
    //   134: anewarray java/lang/String
    //   137: putstatic burp/Zz0b.b : [Ljava/lang/String;
    //   140: goto -> 300
    //   143: dup_x2
    //   144: pop
    //   145: invokevirtual toCharArray : ()[C
    //   148: dup_x1
    //   149: arraylength
    //   150: dup_x2
    //   151: pop
    //   152: iconst_0
    //   153: istore #6
    //   155: dup2_x1
    //   156: pop2
    //   157: dup_x2
    //   158: iconst_1
    //   159: if_icmpgt -> 260
    //   162: dup2
    //   163: swap
    //   164: iload #6
    //   166: dup2_x1
    //   167: caload
    //   168: swap
    //   169: iload #6
    //   171: bipush #7
    //   173: irem
    //   174: tableswitch default -> 242, 0 -> 212, 1 -> 217, 2 -> 222, 3 -> 227, 4 -> 232, 5 -> 237
    //   212: bipush #123
    //   214: goto -> 244
    //   217: bipush #69
    //   219: goto -> 244
    //   222: bipush #50
    //   224: goto -> 244
    //   227: bipush #78
    //   229: goto -> 244
    //   232: bipush #96
    //   234: goto -> 244
    //   237: bipush #104
    //   239: goto -> 244
    //   242: bipush #64
    //   244: ixor
    //   245: ixor
    //   246: i2c
    //   247: castore
    //   248: iinc #6, 1
    //   251: dup
    //   252: ifne -> 260
    //   255: dup2
    //   256: dup_x1
    //   257: goto -> 166
    //   260: dup2_x1
    //   261: pop2
    //   262: dup_x2
    //   263: iload #6
    //   265: if_icmpgt -> 162
    //   268: pop
    //   269: new java/lang/String
    //   272: dup_x1
    //   273: swap
    //   274: invokespecial <init> : ([C)V
    //   277: invokevirtual intern : ()Ljava/lang/String;
    //   280: swap
    //   281: pop
    //   282: swap
    //   283: tableswitch default -> 40, 0 -> 99
    //   300: new java/math/BigInteger
    //   303: dup
    //   304: iconst_1
    //   305: bipush #32
    //   307: newarray byte
    //   309: dup
    //   310: iconst_0
    //   311: bipush #11
    //   313: bastore
    //   314: dup
    //   315: iconst_1
    //   316: bipush #-64
    //   318: bastore
    //   319: dup
    //   320: iconst_2
    //   321: bipush #10
    //   323: bastore
    //   324: dup
    //   325: iconst_3
    //   326: bipush #-68
    //   328: bastore
    //   329: dup
    //   330: iconst_4
    //   331: bipush #42
    //   333: bastore
    //   334: dup
    //   335: iconst_5
    //   336: bipush #-94
    //   338: bastore
    //   339: dup
    //   340: bipush #6
    //   342: bipush #103
    //   344: bastore
    //   345: dup
    //   346: bipush #7
    //   348: iconst_2
    //   349: bastore
    //   350: dup
    //   351: bipush #8
    //   353: bipush #-79
    //   355: bastore
    //   356: dup
    //   357: bipush #9
    //   359: bipush #-117
    //   361: bastore
    //   362: dup
    //   363: bipush #10
    //   365: bipush #-122
    //   367: bastore
    //   368: dup
    //   369: bipush #11
    //   371: bipush #100
    //   373: bastore
    //   374: dup
    //   375: bipush #12
    //   377: bipush #74
    //   379: bastore
    //   380: dup
    //   381: bipush #13
    //   383: bipush #91
    //   385: bastore
    //   386: dup
    //   387: bipush #14
    //   389: bipush #-72
    //   391: bastore
    //   392: dup
    //   393: bipush #15
    //   395: bipush #-59
    //   397: bastore
    //   398: dup
    //   399: bipush #16
    //   401: bipush #30
    //   403: bastore
    //   404: dup
    //   405: bipush #17
    //   407: bipush #71
    //   409: bastore
    //   410: dup
    //   411: bipush #18
    //   413: bipush #-121
    //   415: bastore
    //   416: dup
    //   417: bipush #19
    //   419: bipush #-120
    //   421: bastore
    //   422: dup
    //   423: bipush #20
    //   425: bipush #21
    //   427: bastore
    //   428: dup
    //   429: bipush #21
    //   431: bipush #107
    //   433: bastore
    //   434: dup
    //   435: bipush #22
    //   437: bipush #-80
    //   439: bastore
    //   440: dup
    //   441: bipush #23
    //   443: bipush #121
    //   445: bastore
    //   446: dup
    //   447: bipush #24
    //   449: bipush #-32
    //   451: bastore
    //   452: dup
    //   453: bipush #25
    //   455: bipush #114
    //   457: bastore
    //   458: dup
    //   459: bipush #26
    //   461: bipush #-92
    //   463: bastore
    //   464: dup
    //   465: bipush #27
    //   467: bipush #-44
    //   469: bastore
    //   470: dup
    //   471: bipush #28
    //   473: bipush #36
    //   475: bastore
    //   476: dup
    //   477: bipush #29
    //   479: bipush #-84
    //   481: bastore
    //   482: dup
    //   483: bipush #30
    //   485: bipush #48
    //   487: bastore
    //   488: dup
    //   489: bipush #31
    //   491: bipush #-20
    //   493: bastore
    //   494: invokespecial <init> : (I[B)V
    //   497: putstatic burp/Zz0b.ZT : Ljava/lang/Object;
    //   500: sipush #-7566
    //   503: sipush #14456
    //   506: invokestatic a : (II)Ljava/lang/String;
    //   509: putstatic burp/Zz0b.ZD : Ljava/lang/String;
    //   512: return
  }
  
  private static Throwable a(Throwable paramThrowable) {
    return paramThrowable;
  }
  
  private static String a(int paramInt1, int paramInt2) {
    int i = (paramInt1 ^ 0xFFFFE267) & 0xFFFF;
    if (b[i] == null) {
      char[] arrayOfChar = a[i].toCharArray();
      switch (arrayOfChar[0] & 0xFF) {
        case 0:
        
        case 1:
        
        case 2:
        
        case 3:
        
        case 4:
        
        case 5:
        
        case 6:
        
        case 7:
        
        case 8:
        
        case 9:
        
        case 10:
        
        case 11:
        
        case 12:
        
        case 13:
        
        case 14:
        
        case 15:
        
        case 16:
        
        case 17:
        
        case 18:
        
        case 19:
        
        case 20:
        
        case 21:
        
        case 22:
        
        case 23:
        
        case 24:
        
        case 25:
        
        case 26:
        
        case 27:
        
        case 28:
        
        case 29:
        
        case 30:
        
        case 31:
        
        case 32:
        
        case 33:
        
        case 34:
        
        case 35:
        
        case 36:
        
        case 37:
        
        case 38:
        
        case 39:
        
        case 40:
        
        case 41:
        
        case 42:
        
        case 43:
        
        case 44:
        
        case 45:
        
        case 46:
        
        case 47:
        
        case 48:
        
        case 49:
        
        case 50:
        
        case 51:
        
        case 52:
        
        case 53:
        
        case 54:
        
        case 55:
        
        case 56:
        
        case 57:
        
        case 58:
        
        case 59:
        
        case 60:
        
        case 61:
        
        case 62:
        
        case 63:
        
        case 64:
        
        case 65:
        
        case 66:
        
        case 67:
        
        case 68:
        
        case 69:
        
        case 70:
        
        case 71:
        
        case 72:
        
        case 73:
        
        case 74:
        
        case 75:
        
        case 76:
        
        case 77:
        
        case 78:
        
        case 79:
        
        case 80:
        
        case 81:
        
        case 82:
        
        case 83:
        
        case 84:
        
        case 85:
        
        case 86:
        
        case 87:
        
        case 88:
        
        case 89:
        
        case 90:
        
        case 91:
        
        case 92:
        
        case 93:
        
        case 94:
        
        case 95:
        
        case 96:
        
        case 97:
        
        case 98:
        
        case 99:
        
        case 100:
        
        case 101:
        
        case 102:
        
        case 103:
        
        case 104:
        
        case 105:
        
        case 106:
        
        case 107:
        
        case 108:
        
        case 109:
        
        case 110:
        
        case 111:
        
        case 112:
        
        case 113:
        
        case 114:
        
        case 115:
        
        case 116:
        
        case 117:
        
        case 118:
        
        case 119:
        
        case 120:
        
        case 121:
        
        case 122:
        
        case 123:
        
        case 124:
        
        case 125:
        
        case 126:
        
        case 127:
        
        case 128:
        
        case 129:
        
        case 130:
        
        case 131:
        
        case 132:
        
        case 133:
        
        case 134:
        
        case 135:
        
        case 136:
        
        case 137:
        
        case 138:
        
        case 139:
        
        case 140:
        
        case 141:
        
        case 142:
        
        case 143:
        
        case 144:
        
        case 145:
        
        case 146:
        
        case 147:
        
        case 148:
        
        case 149:
        
        case 150:
        
        case 151:
        
        case 152:
        
        case 153:
        
        case 154:
        
        case 155:
        
        case 156:
        
        case 157:
        
        case 158:
        
        case 159:
        
        case 160:
        
        case 161:
        
        case 162:
        
        case 163:
        
        case 164:
        
        case 165:
        
        case 166:
        
        case 167:
        
        case 168:
        
        case 169:
        
        case 170:
        
        case 171:
        
        case 172:
        
        case 173:
        
        case 174:
        
        case 175:
        
        case 176:
        
        case 177:
        
        case 178:
        
        case 179:
        
        case 180:
        
        case 181:
        
        case 182:
        
        case 183:
        
        case 184:
        
        case 185:
        
        case 186:
        
        case 187:
        
        case 188:
        
        case 189:
        
        case 190:
        
        case 191:
        
        case 192:
        
        case 193:
        
        case 194:
        
        case 195:
        
        case 196:
        
        case 197:
        
        case 198:
        
        case 199:
        
        case 200:
        
        case 201:
        
        case 202:
        
        case 203:
        
        case 204:
        
        case 205:
        
        case 206:
        
        case 207:
        
        case 208:
        
        case 209:
        
        case 210:
        
        case 211:
        
        case 212:
        
        case 213:
        
        case 214:
        
        case 215:
        
        case 216:
        
        case 217:
        
        case 218:
        
        case 219:
        
        case 220:
        
        case 221:
        
        case 222:
        
        case 223:
        
        case 224:
        
        case 225:
        
        case 226:
        
        case 227:
        
        case 228:
        
        case 229:
        
        case 230:
        
        case 231:
        
        case 232:
        
        case 233:
        
        case 234:
        
        case 235:
        
        case 236:
        
        case 237:
        
        case 238:
        
        case 239:
        
        case 240:
        
        case 241:
        
        case 242:
        
        case 243:
        
        case 244:
        
        case 245:
        
        case 246:
        
        case 247:
        
        case 248:
        
        case 249:
        
        case 250:
        
        case 251:
        
        case 252:
        
        case 253:
        
        case 254:
        
        default:
          break;
      } 
      char c = '';
      int j = (paramInt2 & 0xFF) - c;
      if (j < 0)
        j += 256; 
      int k = ((paramInt2 & 0xFFFF) >>> 8) - c;
      if (k < 0)
        k += 256; 
      for (byte b = 0; b < arrayOfChar.length; b++) {
        int m = b % 2;
        if (m == 0) {
          arrayOfChar[b] = (char)(arrayOfChar[b] ^ j);
          j = ((j >>> 3 | j << 5) ^ arrayOfChar[b]) & 0xFF;
        } else {
          arrayOfChar[b] = (char)(arrayOfChar[b] ^ k);
          k = ((k >>> 3 | k << 5) ^ arrayOfChar[b]) & 0xFF;
        } 
      } 
      b[i] = (new String(arrayOfChar)).intern();
    } 
    return b[i];
  }
}


/* Location:              C:\Program Files\BurpSuitePro\burpsuite_pro.jar!\burp\Zz0b.class
 * Java compiler version: 21 (65.0)
 * JD-Core Version:       1.1.3
 */