package burp;

import java.math.BigInteger;

class Zz0w extends ClassLoader {
  static String ZO;
  
  static Object ZF;
  
  private static final String[] a;
  
  private static final String[] b;
  
  static void ZK(Object[] paramArrayOfObject, Object paramObject) throws Throwable {}
  
  static boolean Zc(Object[] paramArrayOfObject, Object paramObject) throws Throwable {
    // Byte code:
    //   0: invokestatic ZN : ()Z
    //   3: istore_2
    //   4: getstatic burp/Zsxo.Za : Ljava/lang/Object;
    //   7: checkcast java/math/BigInteger
    //   10: invokevirtual toByteArray : ()[B
    //   13: astore_3
    //   14: bipush #32
    //   16: newarray int
    //   18: dup
    //   19: iconst_0
    //   20: ldc 943331329
    //   22: iastore
    //   23: dup
    //   24: iconst_1
    //   25: ldc 170788368
    //   27: iastore
    //   28: dup
    //   29: iconst_2
    //   30: ldc 1008414755
    //   32: iastore
    //   33: dup
    //   34: iconst_3
    //   35: ldc 187049985
    //   37: iastore
    //   38: dup
    //   39: iconst_4
    //   40: ldc 1010368540
    //   42: iastore
    //   43: dup
    //   44: iconst_5
    //   45: ldc 220604441
    //   47: iastore
    //   48: dup
    //   49: bipush #6
    //   51: ldc 940377620
    //   53: iastore
    //   54: dup
    //   55: bipush #7
    //   57: ldc 255209728
    //   59: iastore
    //   60: dup
    //   61: bipush #8
    //   63: ldc 689771012
    //   65: iastore
    //   66: dup
    //   67: bipush #9
    //   69: ldc 221709344
    //   71: iastore
    //   72: dup
    //   73: bipush #10
    //   75: ldc 957157408
    //   77: iastore
    //   78: dup
    //   79: bipush #11
    //   81: ldc 892536332
    //   83: iastore
    //   84: dup
    //   85: bipush #12
    //   87: ldc 722417666
    //   89: iastore
    //   90: dup
    //   91: bipush #13
    //   93: ldc 1026621720
    //   95: iastore
    //   96: dup
    //   97: bipush #14
    //   99: ldc 655302664
    //   101: iastore
    //   102: dup
    //   103: bipush #15
    //   105: ldc 890966315
    //   107: iastore
    //   108: dup
    //   109: bipush #16
    //   111: ldc 187632156
    //   113: iastore
    //   114: dup
    //   115: bipush #17
    //   117: ldc 874189824
    //   119: iastore
    //   120: dup
    //   121: bipush #18
    //   123: ldc 254150144
    //   125: iastore
    //   126: dup
    //   127: bipush #19
    //   129: ldc 924386310
    //   131: iastore
    //   132: dup
    //   133: bipush #20
    //   135: ldc 121057538
    //   137: iastore
    //   138: dup
    //   139: bipush #21
    //   141: ldc 840500228
    //   143: iastore
    //   144: dup
    //   145: bipush #22
    //   147: ldc 389160971
    //   149: iastore
    //   150: dup
    //   151: bipush #23
    //   153: ldc 907870729
    //   155: iastore
    //   156: dup
    //   157: bipush #24
    //   159: ldc 389426184
    //   161: iastore
    //   162: dup
    //   163: bipush #25
    //   165: ldc 973875457
    //   167: iastore
    //   168: dup
    //   169: bipush #26
    //   171: ldc 372376604
    //   173: iastore
    //   174: dup
    //   175: bipush #27
    //   177: ldc 707731490
    //   179: iastore
    //   180: dup
    //   181: bipush #28
    //   183: ldc 1043334948
    //   185: iastore
    //   186: dup
    //   187: bipush #29
    //   189: ldc 439222784
    //   191: iastore
    //   192: dup
    //   193: bipush #30
    //   195: ldc 876216579
    //   197: iastore
    //   198: dup
    //   199: bipush #31
    //   201: ldc 455999525
    //   203: iastore
    //   204: astore #5
    //   206: bipush #8
    //   208: aload_3
    //   209: arraylength
    //   210: bipush #8
    //   212: irem
    //   213: isub
    //   214: istore #6
    //   216: aload_3
    //   217: arraylength
    //   218: iload #6
    //   220: iadd
    //   221: newarray byte
    //   223: astore #7
    //   225: iconst_0
    //   226: istore #8
    //   228: iload #8
    //   230: aload_3
    //   231: arraylength
    //   232: if_icmpge -> 258
    //   235: aload #7
    //   237: iload #8
    //   239: aload_3
    //   240: iload #8
    //   242: baload
    //   243: bastore
    //   244: iinc #8, 1
    //   247: iload_2
    //   248: ifne -> 228
    //   251: iconst_2
    //   252: anewarray burp/Zbqc
    //   255: invokestatic Zr : ([Lburp/Zbqc;)V
    //   258: aload_3
    //   259: arraylength
    //   260: istore #8
    //   262: iload #8
    //   264: aload #7
    //   266: arraylength
    //   267: if_icmpge -> 285
    //   270: aload #7
    //   272: iload #8
    //   274: iload #6
    //   276: i2b
    //   277: bastore
    //   278: iinc #8, 1
    //   281: iload_2
    //   282: ifne -> 262
    //   285: aload #7
    //   287: astore_3
    //   288: bipush #64
    //   290: newarray int
    //   292: dup
    //   293: iconst_0
    //   294: ldc 16843776
    //   296: iastore
    //   297: dup
    //   298: iconst_1
    //   299: iconst_0
    //   300: iastore
    //   301: dup
    //   302: iconst_2
    //   303: ldc 65536
    //   305: iastore
    //   306: dup
    //   307: iconst_3
    //   308: ldc 16843780
    //   310: iastore
    //   311: dup
    //   312: iconst_4
    //   313: ldc 16842756
    //   315: iastore
    //   316: dup
    //   317: iconst_5
    //   318: ldc 66564
    //   320: iastore
    //   321: dup
    //   322: bipush #6
    //   324: iconst_4
    //   325: iastore
    //   326: dup
    //   327: bipush #7
    //   329: ldc 65536
    //   331: iastore
    //   332: dup
    //   333: bipush #8
    //   335: sipush #1024
    //   338: iastore
    //   339: dup
    //   340: bipush #9
    //   342: ldc 16843776
    //   344: iastore
    //   345: dup
    //   346: bipush #10
    //   348: ldc 16843780
    //   350: iastore
    //   351: dup
    //   352: bipush #11
    //   354: sipush #1024
    //   357: iastore
    //   358: dup
    //   359: bipush #12
    //   361: ldc 16778244
    //   363: iastore
    //   364: dup
    //   365: bipush #13
    //   367: ldc 16842756
    //   369: iastore
    //   370: dup
    //   371: bipush #14
    //   373: ldc 16777216
    //   375: iastore
    //   376: dup
    //   377: bipush #15
    //   379: iconst_4
    //   380: iastore
    //   381: dup
    //   382: bipush #16
    //   384: sipush #1028
    //   387: iastore
    //   388: dup
    //   389: bipush #17
    //   391: ldc 16778240
    //   393: iastore
    //   394: dup
    //   395: bipush #18
    //   397: ldc 16778240
    //   399: iastore
    //   400: dup
    //   401: bipush #19
    //   403: ldc 66560
    //   405: iastore
    //   406: dup
    //   407: bipush #20
    //   409: ldc 66560
    //   411: iastore
    //   412: dup
    //   413: bipush #21
    //   415: ldc 16842752
    //   417: iastore
    //   418: dup
    //   419: bipush #22
    //   421: ldc 16842752
    //   423: iastore
    //   424: dup
    //   425: bipush #23
    //   427: ldc 16778244
    //   429: iastore
    //   430: dup
    //   431: bipush #24
    //   433: ldc 65540
    //   435: iastore
    //   436: dup
    //   437: bipush #25
    //   439: ldc 16777220
    //   441: iastore
    //   442: dup
    //   443: bipush #26
    //   445: ldc 16777220
    //   447: iastore
    //   448: dup
    //   449: bipush #27
    //   451: ldc 65540
    //   453: iastore
    //   454: dup
    //   455: bipush #28
    //   457: iconst_0
    //   458: iastore
    //   459: dup
    //   460: bipush #29
    //   462: sipush #1028
    //   465: iastore
    //   466: dup
    //   467: bipush #30
    //   469: ldc 66564
    //   471: iastore
    //   472: dup
    //   473: bipush #31
    //   475: ldc 16777216
    //   477: iastore
    //   478: dup
    //   479: bipush #32
    //   481: ldc 65536
    //   483: iastore
    //   484: dup
    //   485: bipush #33
    //   487: ldc 16843780
    //   489: iastore
    //   490: dup
    //   491: bipush #34
    //   493: iconst_4
    //   494: iastore
    //   495: dup
    //   496: bipush #35
    //   498: ldc 16842752
    //   500: iastore
    //   501: dup
    //   502: bipush #36
    //   504: ldc 16843776
    //   506: iastore
    //   507: dup
    //   508: bipush #37
    //   510: ldc 16777216
    //   512: iastore
    //   513: dup
    //   514: bipush #38
    //   516: ldc 16777216
    //   518: iastore
    //   519: dup
    //   520: bipush #39
    //   522: sipush #1024
    //   525: iastore
    //   526: dup
    //   527: bipush #40
    //   529: ldc 16842756
    //   531: iastore
    //   532: dup
    //   533: bipush #41
    //   535: ldc 65536
    //   537: iastore
    //   538: dup
    //   539: bipush #42
    //   541: ldc 66560
    //   543: iastore
    //   544: dup
    //   545: bipush #43
    //   547: ldc 16777220
    //   549: iastore
    //   550: dup
    //   551: bipush #44
    //   553: sipush #1024
    //   556: iastore
    //   557: dup
    //   558: bipush #45
    //   560: iconst_4
    //   561: iastore
    //   562: dup
    //   563: bipush #46
    //   565: ldc 16778244
    //   567: iastore
    //   568: dup
    //   569: bipush #47
    //   571: ldc 66564
    //   573: iastore
    //   574: dup
    //   575: bipush #48
    //   577: ldc 16843780
    //   579: iastore
    //   580: dup
    //   581: bipush #49
    //   583: ldc 65540
    //   585: iastore
    //   586: dup
    //   587: bipush #50
    //   589: ldc 16842752
    //   591: iastore
    //   592: dup
    //   593: bipush #51
    //   595: ldc 16778244
    //   597: iastore
    //   598: dup
    //   599: bipush #52
    //   601: ldc 16777220
    //   603: iastore
    //   604: dup
    //   605: bipush #53
    //   607: sipush #1028
    //   610: iastore
    //   611: dup
    //   612: bipush #54
    //   614: ldc 66564
    //   616: iastore
    //   617: dup
    //   618: bipush #55
    //   620: ldc 16843776
    //   622: iastore
    //   623: dup
    //   624: bipush #56
    //   626: sipush #1028
    //   629: iastore
    //   630: dup
    //   631: bipush #57
    //   633: ldc 16778240
    //   635: iastore
    //   636: dup
    //   637: bipush #58
    //   639: ldc 16778240
    //   641: iastore
    //   642: dup
    //   643: bipush #59
    //   645: iconst_0
    //   646: iastore
    //   647: dup
    //   648: bipush #60
    //   650: ldc 65540
    //   652: iastore
    //   653: dup
    //   654: bipush #61
    //   656: ldc 66560
    //   658: iastore
    //   659: dup
    //   660: bipush #62
    //   662: iconst_0
    //   663: iastore
    //   664: dup
    //   665: bipush #63
    //   667: ldc 16842756
    //   669: iastore
    //   670: astore #8
    //   672: bipush #64
    //   674: newarray int
    //   676: dup
    //   677: iconst_0
    //   678: ldc -2146402272
    //   680: iastore
    //   681: dup
    //   682: iconst_1
    //   683: ldc -2147450880
    //   685: iastore
    //   686: dup
    //   687: iconst_2
    //   688: ldc 32768
    //   690: iastore
    //   691: dup
    //   692: iconst_3
    //   693: ldc 1081376
    //   695: iastore
    //   696: dup
    //   697: iconst_4
    //   698: ldc 1048576
    //   700: iastore
    //   701: dup
    //   702: iconst_5
    //   703: bipush #32
    //   705: iastore
    //   706: dup
    //   707: bipush #6
    //   709: ldc -2146435040
    //   711: iastore
    //   712: dup
    //   713: bipush #7
    //   715: ldc -2147450848
    //   717: iastore
    //   718: dup
    //   719: bipush #8
    //   721: ldc -2147483616
    //   723: iastore
    //   724: dup
    //   725: bipush #9
    //   727: ldc -2146402272
    //   729: iastore
    //   730: dup
    //   731: bipush #10
    //   733: ldc -2146402304
    //   735: iastore
    //   736: dup
    //   737: bipush #11
    //   739: ldc -2147483648
    //   741: iastore
    //   742: dup
    //   743: bipush #12
    //   745: ldc -2147450880
    //   747: iastore
    //   748: dup
    //   749: bipush #13
    //   751: ldc 1048576
    //   753: iastore
    //   754: dup
    //   755: bipush #14
    //   757: bipush #32
    //   759: iastore
    //   760: dup
    //   761: bipush #15
    //   763: ldc -2146435040
    //   765: iastore
    //   766: dup
    //   767: bipush #16
    //   769: ldc 1081344
    //   771: iastore
    //   772: dup
    //   773: bipush #17
    //   775: ldc 1048608
    //   777: iastore
    //   778: dup
    //   779: bipush #18
    //   781: ldc -2147450848
    //   783: iastore
    //   784: dup
    //   785: bipush #19
    //   787: iconst_0
    //   788: iastore
    //   789: dup
    //   790: bipush #20
    //   792: ldc -2147483648
    //   794: iastore
    //   795: dup
    //   796: bipush #21
    //   798: ldc 32768
    //   800: iastore
    //   801: dup
    //   802: bipush #22
    //   804: ldc 1081376
    //   806: iastore
    //   807: dup
    //   808: bipush #23
    //   810: ldc -2146435072
    //   812: iastore
    //   813: dup
    //   814: bipush #24
    //   816: ldc 1048608
    //   818: iastore
    //   819: dup
    //   820: bipush #25
    //   822: ldc -2147483616
    //   824: iastore
    //   825: dup
    //   826: bipush #26
    //   828: iconst_0
    //   829: iastore
    //   830: dup
    //   831: bipush #27
    //   833: ldc 1081344
    //   835: iastore
    //   836: dup
    //   837: bipush #28
    //   839: ldc 32800
    //   841: iastore
    //   842: dup
    //   843: bipush #29
    //   845: ldc -2146402304
    //   847: iastore
    //   848: dup
    //   849: bipush #30
    //   851: ldc -2146435072
    //   853: iastore
    //   854: dup
    //   855: bipush #31
    //   857: ldc 32800
    //   859: iastore
    //   860: dup
    //   861: bipush #32
    //   863: iconst_0
    //   864: iastore
    //   865: dup
    //   866: bipush #33
    //   868: ldc 1081376
    //   870: iastore
    //   871: dup
    //   872: bipush #34
    //   874: ldc -2146435040
    //   876: iastore
    //   877: dup
    //   878: bipush #35
    //   880: ldc 1048576
    //   882: iastore
    //   883: dup
    //   884: bipush #36
    //   886: ldc -2147450848
    //   888: iastore
    //   889: dup
    //   890: bipush #37
    //   892: ldc -2146435072
    //   894: iastore
    //   895: dup
    //   896: bipush #38
    //   898: ldc -2146402304
    //   900: iastore
    //   901: dup
    //   902: bipush #39
    //   904: ldc 32768
    //   906: iastore
    //   907: dup
    //   908: bipush #40
    //   910: ldc -2146435072
    //   912: iastore
    //   913: dup
    //   914: bipush #41
    //   916: ldc -2147450880
    //   918: iastore
    //   919: dup
    //   920: bipush #42
    //   922: bipush #32
    //   924: iastore
    //   925: dup
    //   926: bipush #43
    //   928: ldc -2146402272
    //   930: iastore
    //   931: dup
    //   932: bipush #44
    //   934: ldc 1081376
    //   936: iastore
    //   937: dup
    //   938: bipush #45
    //   940: bipush #32
    //   942: iastore
    //   943: dup
    //   944: bipush #46
    //   946: ldc 32768
    //   948: iastore
    //   949: dup
    //   950: bipush #47
    //   952: ldc -2147483648
    //   954: iastore
    //   955: dup
    //   956: bipush #48
    //   958: ldc 32800
    //   960: iastore
    //   961: dup
    //   962: bipush #49
    //   964: ldc -2146402304
    //   966: iastore
    //   967: dup
    //   968: bipush #50
    //   970: ldc 1048576
    //   972: iastore
    //   973: dup
    //   974: bipush #51
    //   976: ldc -2147483616
    //   978: iastore
    //   979: dup
    //   980: bipush #52
    //   982: ldc 1048608
    //   984: iastore
    //   985: dup
    //   986: bipush #53
    //   988: ldc -2147450848
    //   990: iastore
    //   991: dup
    //   992: bipush #54
    //   994: ldc -2147483616
    //   996: iastore
    //   997: dup
    //   998: bipush #55
    //   1000: ldc 1048608
    //   1002: iastore
    //   1003: dup
    //   1004: bipush #56
    //   1006: ldc 1081344
    //   1008: iastore
    //   1009: dup
    //   1010: bipush #57
    //   1012: iconst_0
    //   1013: iastore
    //   1014: dup
    //   1015: bipush #58
    //   1017: ldc -2147450880
    //   1019: iastore
    //   1020: dup
    //   1021: bipush #59
    //   1023: ldc 32800
    //   1025: iastore
    //   1026: dup
    //   1027: bipush #60
    //   1029: ldc -2147483648
    //   1031: iastore
    //   1032: dup
    //   1033: bipush #61
    //   1035: ldc -2146435040
    //   1037: iastore
    //   1038: dup
    //   1039: bipush #62
    //   1041: ldc -2146402272
    //   1043: iastore
    //   1044: dup
    //   1045: bipush #63
    //   1047: ldc 1081344
    //   1049: iastore
    //   1050: astore #9
    //   1052: bipush #64
    //   1054: newarray int
    //   1056: dup
    //   1057: iconst_0
    //   1058: sipush #520
    //   1061: iastore
    //   1062: dup
    //   1063: iconst_1
    //   1064: ldc 134349312
    //   1066: iastore
    //   1067: dup
    //   1068: iconst_2
    //   1069: iconst_0
    //   1070: iastore
    //   1071: dup
    //   1072: iconst_3
    //   1073: ldc 134348808
    //   1075: iastore
    //   1076: dup
    //   1077: iconst_4
    //   1078: ldc 134218240
    //   1080: iastore
    //   1081: dup
    //   1082: iconst_5
    //   1083: iconst_0
    //   1084: iastore
    //   1085: dup
    //   1086: bipush #6
    //   1088: ldc 131592
    //   1090: iastore
    //   1091: dup
    //   1092: bipush #7
    //   1094: ldc 134218240
    //   1096: iastore
    //   1097: dup
    //   1098: bipush #8
    //   1100: ldc 131080
    //   1102: iastore
    //   1103: dup
    //   1104: bipush #9
    //   1106: ldc 134217736
    //   1108: iastore
    //   1109: dup
    //   1110: bipush #10
    //   1112: ldc 134217736
    //   1114: iastore
    //   1115: dup
    //   1116: bipush #11
    //   1118: ldc 131072
    //   1120: iastore
    //   1121: dup
    //   1122: bipush #12
    //   1124: ldc 134349320
    //   1126: iastore
    //   1127: dup
    //   1128: bipush #13
    //   1130: ldc 131080
    //   1132: iastore
    //   1133: dup
    //   1134: bipush #14
    //   1136: ldc 134348800
    //   1138: iastore
    //   1139: dup
    //   1140: bipush #15
    //   1142: sipush #520
    //   1145: iastore
    //   1146: dup
    //   1147: bipush #16
    //   1149: ldc 134217728
    //   1151: iastore
    //   1152: dup
    //   1153: bipush #17
    //   1155: bipush #8
    //   1157: iastore
    //   1158: dup
    //   1159: bipush #18
    //   1161: ldc 134349312
    //   1163: iastore
    //   1164: dup
    //   1165: bipush #19
    //   1167: sipush #512
    //   1170: iastore
    //   1171: dup
    //   1172: bipush #20
    //   1174: ldc 131584
    //   1176: iastore
    //   1177: dup
    //   1178: bipush #21
    //   1180: ldc 134348800
    //   1182: iastore
    //   1183: dup
    //   1184: bipush #22
    //   1186: ldc 134348808
    //   1188: iastore
    //   1189: dup
    //   1190: bipush #23
    //   1192: ldc 131592
    //   1194: iastore
    //   1195: dup
    //   1196: bipush #24
    //   1198: ldc 134218248
    //   1200: iastore
    //   1201: dup
    //   1202: bipush #25
    //   1204: ldc 131584
    //   1206: iastore
    //   1207: dup
    //   1208: bipush #26
    //   1210: ldc 131072
    //   1212: iastore
    //   1213: dup
    //   1214: bipush #27
    //   1216: ldc 134218248
    //   1218: iastore
    //   1219: dup
    //   1220: bipush #28
    //   1222: bipush #8
    //   1224: iastore
    //   1225: dup
    //   1226: bipush #29
    //   1228: ldc 134349320
    //   1230: iastore
    //   1231: dup
    //   1232: bipush #30
    //   1234: sipush #512
    //   1237: iastore
    //   1238: dup
    //   1239: bipush #31
    //   1241: ldc 134217728
    //   1243: iastore
    //   1244: dup
    //   1245: bipush #32
    //   1247: ldc 134349312
    //   1249: iastore
    //   1250: dup
    //   1251: bipush #33
    //   1253: ldc 134217728
    //   1255: iastore
    //   1256: dup
    //   1257: bipush #34
    //   1259: ldc 131080
    //   1261: iastore
    //   1262: dup
    //   1263: bipush #35
    //   1265: sipush #520
    //   1268: iastore
    //   1269: dup
    //   1270: bipush #36
    //   1272: ldc 131072
    //   1274: iastore
    //   1275: dup
    //   1276: bipush #37
    //   1278: ldc 134349312
    //   1280: iastore
    //   1281: dup
    //   1282: bipush #38
    //   1284: ldc 134218240
    //   1286: iastore
    //   1287: dup
    //   1288: bipush #39
    //   1290: iconst_0
    //   1291: iastore
    //   1292: dup
    //   1293: bipush #40
    //   1295: sipush #512
    //   1298: iastore
    //   1299: dup
    //   1300: bipush #41
    //   1302: ldc 131080
    //   1304: iastore
    //   1305: dup
    //   1306: bipush #42
    //   1308: ldc 134349320
    //   1310: iastore
    //   1311: dup
    //   1312: bipush #43
    //   1314: ldc 134218240
    //   1316: iastore
    //   1317: dup
    //   1318: bipush #44
    //   1320: ldc 134217736
    //   1322: iastore
    //   1323: dup
    //   1324: bipush #45
    //   1326: sipush #512
    //   1329: iastore
    //   1330: dup
    //   1331: bipush #46
    //   1333: iconst_0
    //   1334: iastore
    //   1335: dup
    //   1336: bipush #47
    //   1338: ldc 134348808
    //   1340: iastore
    //   1341: dup
    //   1342: bipush #48
    //   1344: ldc 134218248
    //   1346: iastore
    //   1347: dup
    //   1348: bipush #49
    //   1350: ldc 131072
    //   1352: iastore
    //   1353: dup
    //   1354: bipush #50
    //   1356: ldc 134217728
    //   1358: iastore
    //   1359: dup
    //   1360: bipush #51
    //   1362: ldc 134349320
    //   1364: iastore
    //   1365: dup
    //   1366: bipush #52
    //   1368: bipush #8
    //   1370: iastore
    //   1371: dup
    //   1372: bipush #53
    //   1374: ldc 131592
    //   1376: iastore
    //   1377: dup
    //   1378: bipush #54
    //   1380: ldc 131584
    //   1382: iastore
    //   1383: dup
    //   1384: bipush #55
    //   1386: ldc 134217736
    //   1388: iastore
    //   1389: dup
    //   1390: bipush #56
    //   1392: ldc 134348800
    //   1394: iastore
    //   1395: dup
    //   1396: bipush #57
    //   1398: ldc 134218248
    //   1400: iastore
    //   1401: dup
    //   1402: bipush #58
    //   1404: sipush #520
    //   1407: iastore
    //   1408: dup
    //   1409: bipush #59
    //   1411: ldc 134348800
    //   1413: iastore
    //   1414: dup
    //   1415: bipush #60
    //   1417: ldc 131592
    //   1419: iastore
    //   1420: dup
    //   1421: bipush #61
    //   1423: bipush #8
    //   1425: iastore
    //   1426: dup
    //   1427: bipush #62
    //   1429: ldc 134348808
    //   1431: iastore
    //   1432: dup
    //   1433: bipush #63
    //   1435: ldc 131584
    //   1437: iastore
    //   1438: astore #10
    //   1440: bipush #64
    //   1442: newarray int
    //   1444: dup
    //   1445: iconst_0
    //   1446: ldc 8396801
    //   1448: iastore
    //   1449: dup
    //   1450: iconst_1
    //   1451: sipush #8321
    //   1454: iastore
    //   1455: dup
    //   1456: iconst_2
    //   1457: sipush #8321
    //   1460: iastore
    //   1461: dup
    //   1462: iconst_3
    //   1463: sipush #128
    //   1466: iastore
    //   1467: dup
    //   1468: iconst_4
    //   1469: ldc 8396928
    //   1471: iastore
    //   1472: dup
    //   1473: iconst_5
    //   1474: ldc 8388737
    //   1476: iastore
    //   1477: dup
    //   1478: bipush #6
    //   1480: ldc 8388609
    //   1482: iastore
    //   1483: dup
    //   1484: bipush #7
    //   1486: sipush #8193
    //   1489: iastore
    //   1490: dup
    //   1491: bipush #8
    //   1493: iconst_0
    //   1494: iastore
    //   1495: dup
    //   1496: bipush #9
    //   1498: ldc 8396800
    //   1500: iastore
    //   1501: dup
    //   1502: bipush #10
    //   1504: ldc 8396800
    //   1506: iastore
    //   1507: dup
    //   1508: bipush #11
    //   1510: ldc 8396929
    //   1512: iastore
    //   1513: dup
    //   1514: bipush #12
    //   1516: sipush #129
    //   1519: iastore
    //   1520: dup
    //   1521: bipush #13
    //   1523: iconst_0
    //   1524: iastore
    //   1525: dup
    //   1526: bipush #14
    //   1528: ldc 8388736
    //   1530: iastore
    //   1531: dup
    //   1532: bipush #15
    //   1534: ldc 8388609
    //   1536: iastore
    //   1537: dup
    //   1538: bipush #16
    //   1540: iconst_1
    //   1541: iastore
    //   1542: dup
    //   1543: bipush #17
    //   1545: sipush #8192
    //   1548: iastore
    //   1549: dup
    //   1550: bipush #18
    //   1552: ldc 8388608
    //   1554: iastore
    //   1555: dup
    //   1556: bipush #19
    //   1558: ldc 8396801
    //   1560: iastore
    //   1561: dup
    //   1562: bipush #20
    //   1564: sipush #128
    //   1567: iastore
    //   1568: dup
    //   1569: bipush #21
    //   1571: ldc 8388608
    //   1573: iastore
    //   1574: dup
    //   1575: bipush #22
    //   1577: sipush #8193
    //   1580: iastore
    //   1581: dup
    //   1582: bipush #23
    //   1584: sipush #8320
    //   1587: iastore
    //   1588: dup
    //   1589: bipush #24
    //   1591: ldc 8388737
    //   1593: iastore
    //   1594: dup
    //   1595: bipush #25
    //   1597: iconst_1
    //   1598: iastore
    //   1599: dup
    //   1600: bipush #26
    //   1602: sipush #8320
    //   1605: iastore
    //   1606: dup
    //   1607: bipush #27
    //   1609: ldc 8388736
    //   1611: iastore
    //   1612: dup
    //   1613: bipush #28
    //   1615: sipush #8192
    //   1618: iastore
    //   1619: dup
    //   1620: bipush #29
    //   1622: ldc 8396928
    //   1624: iastore
    //   1625: dup
    //   1626: bipush #30
    //   1628: ldc 8396929
    //   1630: iastore
    //   1631: dup
    //   1632: bipush #31
    //   1634: sipush #129
    //   1637: iastore
    //   1638: dup
    //   1639: bipush #32
    //   1641: ldc 8388736
    //   1643: iastore
    //   1644: dup
    //   1645: bipush #33
    //   1647: ldc 8388609
    //   1649: iastore
    //   1650: dup
    //   1651: bipush #34
    //   1653: ldc 8396800
    //   1655: iastore
    //   1656: dup
    //   1657: bipush #35
    //   1659: ldc 8396929
    //   1661: iastore
    //   1662: dup
    //   1663: bipush #36
    //   1665: sipush #129
    //   1668: iastore
    //   1669: dup
    //   1670: bipush #37
    //   1672: iconst_0
    //   1673: iastore
    //   1674: dup
    //   1675: bipush #38
    //   1677: iconst_0
    //   1678: iastore
    //   1679: dup
    //   1680: bipush #39
    //   1682: ldc 8396800
    //   1684: iastore
    //   1685: dup
    //   1686: bipush #40
    //   1688: sipush #8320
    //   1691: iastore
    //   1692: dup
    //   1693: bipush #41
    //   1695: ldc 8388736
    //   1697: iastore
    //   1698: dup
    //   1699: bipush #42
    //   1701: ldc 8388737
    //   1703: iastore
    //   1704: dup
    //   1705: bipush #43
    //   1707: iconst_1
    //   1708: iastore
    //   1709: dup
    //   1710: bipush #44
    //   1712: ldc 8396801
    //   1714: iastore
    //   1715: dup
    //   1716: bipush #45
    //   1718: sipush #8321
    //   1721: iastore
    //   1722: dup
    //   1723: bipush #46
    //   1725: sipush #8321
    //   1728: iastore
    //   1729: dup
    //   1730: bipush #47
    //   1732: sipush #128
    //   1735: iastore
    //   1736: dup
    //   1737: bipush #48
    //   1739: ldc 8396929
    //   1741: iastore
    //   1742: dup
    //   1743: bipush #49
    //   1745: sipush #129
    //   1748: iastore
    //   1749: dup
    //   1750: bipush #50
    //   1752: iconst_1
    //   1753: iastore
    //   1754: dup
    //   1755: bipush #51
    //   1757: sipush #8192
    //   1760: iastore
    //   1761: dup
    //   1762: bipush #52
    //   1764: ldc 8388609
    //   1766: iastore
    //   1767: dup
    //   1768: bipush #53
    //   1770: sipush #8193
    //   1773: iastore
    //   1774: dup
    //   1775: bipush #54
    //   1777: ldc 8396928
    //   1779: iastore
    //   1780: dup
    //   1781: bipush #55
    //   1783: ldc 8388737
    //   1785: iastore
    //   1786: dup
    //   1787: bipush #56
    //   1789: sipush #8193
    //   1792: iastore
    //   1793: dup
    //   1794: bipush #57
    //   1796: sipush #8320
    //   1799: iastore
    //   1800: dup
    //   1801: bipush #58
    //   1803: ldc 8388608
    //   1805: iastore
    //   1806: dup
    //   1807: bipush #59
    //   1809: ldc 8396801
    //   1811: iastore
    //   1812: dup
    //   1813: bipush #60
    //   1815: sipush #128
    //   1818: iastore
    //   1819: dup
    //   1820: bipush #61
    //   1822: ldc 8388608
    //   1824: iastore
    //   1825: dup
    //   1826: bipush #62
    //   1828: sipush #8192
    //   1831: iastore
    //   1832: dup
    //   1833: bipush #63
    //   1835: ldc 8396928
    //   1837: iastore
    //   1838: astore #11
    //   1840: bipush #64
    //   1842: newarray int
    //   1844: dup
    //   1845: iconst_0
    //   1846: sipush #256
    //   1849: iastore
    //   1850: dup
    //   1851: iconst_1
    //   1852: ldc 34078976
    //   1854: iastore
    //   1855: dup
    //   1856: iconst_2
    //   1857: ldc 34078720
    //   1859: iastore
    //   1860: dup
    //   1861: iconst_3
    //   1862: ldc 1107296512
    //   1864: iastore
    //   1865: dup
    //   1866: iconst_4
    //   1867: ldc 524288
    //   1869: iastore
    //   1870: dup
    //   1871: iconst_5
    //   1872: sipush #256
    //   1875: iastore
    //   1876: dup
    //   1877: bipush #6
    //   1879: ldc 1073741824
    //   1881: iastore
    //   1882: dup
    //   1883: bipush #7
    //   1885: ldc 34078720
    //   1887: iastore
    //   1888: dup
    //   1889: bipush #8
    //   1891: ldc 1074266368
    //   1893: iastore
    //   1894: dup
    //   1895: bipush #9
    //   1897: ldc 524288
    //   1899: iastore
    //   1900: dup
    //   1901: bipush #10
    //   1903: ldc 33554688
    //   1905: iastore
    //   1906: dup
    //   1907: bipush #11
    //   1909: ldc 1074266368
    //   1911: iastore
    //   1912: dup
    //   1913: bipush #12
    //   1915: ldc 1107296512
    //   1917: iastore
    //   1918: dup
    //   1919: bipush #13
    //   1921: ldc 1107820544
    //   1923: iastore
    //   1924: dup
    //   1925: bipush #14
    //   1927: ldc 524544
    //   1929: iastore
    //   1930: dup
    //   1931: bipush #15
    //   1933: ldc 1073741824
    //   1935: iastore
    //   1936: dup
    //   1937: bipush #16
    //   1939: ldc 33554432
    //   1941: iastore
    //   1942: dup
    //   1943: bipush #17
    //   1945: ldc 1074266112
    //   1947: iastore
    //   1948: dup
    //   1949: bipush #18
    //   1951: ldc 1074266112
    //   1953: iastore
    //   1954: dup
    //   1955: bipush #19
    //   1957: iconst_0
    //   1958: iastore
    //   1959: dup
    //   1960: bipush #20
    //   1962: ldc 1073742080
    //   1964: iastore
    //   1965: dup
    //   1966: bipush #21
    //   1968: ldc 1107820800
    //   1970: iastore
    //   1971: dup
    //   1972: bipush #22
    //   1974: ldc 1107820800
    //   1976: iastore
    //   1977: dup
    //   1978: bipush #23
    //   1980: ldc 33554688
    //   1982: iastore
    //   1983: dup
    //   1984: bipush #24
    //   1986: ldc 1107820544
    //   1988: iastore
    //   1989: dup
    //   1990: bipush #25
    //   1992: ldc 1073742080
    //   1994: iastore
    //   1995: dup
    //   1996: bipush #26
    //   1998: iconst_0
    //   1999: iastore
    //   2000: dup
    //   2001: bipush #27
    //   2003: ldc 1107296256
    //   2005: iastore
    //   2006: dup
    //   2007: bipush #28
    //   2009: ldc 34078976
    //   2011: iastore
    //   2012: dup
    //   2013: bipush #29
    //   2015: ldc 33554432
    //   2017: iastore
    //   2018: dup
    //   2019: bipush #30
    //   2021: ldc 1107296256
    //   2023: iastore
    //   2024: dup
    //   2025: bipush #31
    //   2027: ldc 524544
    //   2029: iastore
    //   2030: dup
    //   2031: bipush #32
    //   2033: ldc 524288
    //   2035: iastore
    //   2036: dup
    //   2037: bipush #33
    //   2039: ldc 1107296512
    //   2041: iastore
    //   2042: dup
    //   2043: bipush #34
    //   2045: sipush #256
    //   2048: iastore
    //   2049: dup
    //   2050: bipush #35
    //   2052: ldc 33554432
    //   2054: iastore
    //   2055: dup
    //   2056: bipush #36
    //   2058: ldc 1073741824
    //   2060: iastore
    //   2061: dup
    //   2062: bipush #37
    //   2064: ldc 34078720
    //   2066: iastore
    //   2067: dup
    //   2068: bipush #38
    //   2070: ldc 1107296512
    //   2072: iastore
    //   2073: dup
    //   2074: bipush #39
    //   2076: ldc 1074266368
    //   2078: iastore
    //   2079: dup
    //   2080: bipush #40
    //   2082: ldc 33554688
    //   2084: iastore
    //   2085: dup
    //   2086: bipush #41
    //   2088: ldc 1073741824
    //   2090: iastore
    //   2091: dup
    //   2092: bipush #42
    //   2094: ldc 1107820544
    //   2096: iastore
    //   2097: dup
    //   2098: bipush #43
    //   2100: ldc 34078976
    //   2102: iastore
    //   2103: dup
    //   2104: bipush #44
    //   2106: ldc 1074266368
    //   2108: iastore
    //   2109: dup
    //   2110: bipush #45
    //   2112: sipush #256
    //   2115: iastore
    //   2116: dup
    //   2117: bipush #46
    //   2119: ldc 33554432
    //   2121: iastore
    //   2122: dup
    //   2123: bipush #47
    //   2125: ldc 1107820544
    //   2127: iastore
    //   2128: dup
    //   2129: bipush #48
    //   2131: ldc 1107820800
    //   2133: iastore
    //   2134: dup
    //   2135: bipush #49
    //   2137: ldc 524544
    //   2139: iastore
    //   2140: dup
    //   2141: bipush #50
    //   2143: ldc 1107296256
    //   2145: iastore
    //   2146: dup
    //   2147: bipush #51
    //   2149: ldc 1107820800
    //   2151: iastore
    //   2152: dup
    //   2153: bipush #52
    //   2155: ldc 34078720
    //   2157: iastore
    //   2158: dup
    //   2159: bipush #53
    //   2161: iconst_0
    //   2162: iastore
    //   2163: dup
    //   2164: bipush #54
    //   2166: ldc 1074266112
    //   2168: iastore
    //   2169: dup
    //   2170: bipush #55
    //   2172: ldc 1107296256
    //   2174: iastore
    //   2175: dup
    //   2176: bipush #56
    //   2178: ldc 524544
    //   2180: iastore
    //   2181: dup
    //   2182: bipush #57
    //   2184: ldc 33554688
    //   2186: iastore
    //   2187: dup
    //   2188: bipush #58
    //   2190: ldc 1073742080
    //   2192: iastore
    //   2193: dup
    //   2194: bipush #59
    //   2196: ldc 524288
    //   2198: iastore
    //   2199: dup
    //   2200: bipush #60
    //   2202: iconst_0
    //   2203: iastore
    //   2204: dup
    //   2205: bipush #61
    //   2207: ldc 1074266112
    //   2209: iastore
    //   2210: dup
    //   2211: bipush #62
    //   2213: ldc 34078976
    //   2215: iastore
    //   2216: dup
    //   2217: bipush #63
    //   2219: ldc 1073742080
    //   2221: iastore
    //   2222: astore #12
    //   2224: bipush #64
    //   2226: newarray int
    //   2228: dup
    //   2229: iconst_0
    //   2230: ldc 536870928
    //   2232: iastore
    //   2233: dup
    //   2234: iconst_1
    //   2235: ldc 541065216
    //   2237: iastore
    //   2238: dup
    //   2239: iconst_2
    //   2240: sipush #16384
    //   2243: iastore
    //   2244: dup
    //   2245: iconst_3
    //   2246: ldc 541081616
    //   2248: iastore
    //   2249: dup
    //   2250: iconst_4
    //   2251: ldc 541065216
    //   2253: iastore
    //   2254: dup
    //   2255: iconst_5
    //   2256: bipush #16
    //   2258: iastore
    //   2259: dup
    //   2260: bipush #6
    //   2262: ldc 541081616
    //   2264: iastore
    //   2265: dup
    //   2266: bipush #7
    //   2268: ldc 4194304
    //   2270: iastore
    //   2271: dup
    //   2272: bipush #8
    //   2274: ldc 536887296
    //   2276: iastore
    //   2277: dup
    //   2278: bipush #9
    //   2280: ldc 4210704
    //   2282: iastore
    //   2283: dup
    //   2284: bipush #10
    //   2286: ldc 4194304
    //   2288: iastore
    //   2289: dup
    //   2290: bipush #11
    //   2292: ldc 536870928
    //   2294: iastore
    //   2295: dup
    //   2296: bipush #12
    //   2298: ldc 4194320
    //   2300: iastore
    //   2301: dup
    //   2302: bipush #13
    //   2304: ldc 536887296
    //   2306: iastore
    //   2307: dup
    //   2308: bipush #14
    //   2310: ldc 536870912
    //   2312: iastore
    //   2313: dup
    //   2314: bipush #15
    //   2316: sipush #16400
    //   2319: iastore
    //   2320: dup
    //   2321: bipush #16
    //   2323: iconst_0
    //   2324: iastore
    //   2325: dup
    //   2326: bipush #17
    //   2328: ldc 4194320
    //   2330: iastore
    //   2331: dup
    //   2332: bipush #18
    //   2334: ldc 536887312
    //   2336: iastore
    //   2337: dup
    //   2338: bipush #19
    //   2340: sipush #16384
    //   2343: iastore
    //   2344: dup
    //   2345: bipush #20
    //   2347: ldc 4210688
    //   2349: iastore
    //   2350: dup
    //   2351: bipush #21
    //   2353: ldc 536887312
    //   2355: iastore
    //   2356: dup
    //   2357: bipush #22
    //   2359: bipush #16
    //   2361: iastore
    //   2362: dup
    //   2363: bipush #23
    //   2365: ldc 541065232
    //   2367: iastore
    //   2368: dup
    //   2369: bipush #24
    //   2371: ldc 541065232
    //   2373: iastore
    //   2374: dup
    //   2375: bipush #25
    //   2377: iconst_0
    //   2378: iastore
    //   2379: dup
    //   2380: bipush #26
    //   2382: ldc 4210704
    //   2384: iastore
    //   2385: dup
    //   2386: bipush #27
    //   2388: ldc 541081600
    //   2390: iastore
    //   2391: dup
    //   2392: bipush #28
    //   2394: sipush #16400
    //   2397: iastore
    //   2398: dup
    //   2399: bipush #29
    //   2401: ldc 4210688
    //   2403: iastore
    //   2404: dup
    //   2405: bipush #30
    //   2407: ldc 541081600
    //   2409: iastore
    //   2410: dup
    //   2411: bipush #31
    //   2413: ldc 536870912
    //   2415: iastore
    //   2416: dup
    //   2417: bipush #32
    //   2419: ldc 536887296
    //   2421: iastore
    //   2422: dup
    //   2423: bipush #33
    //   2425: bipush #16
    //   2427: iastore
    //   2428: dup
    //   2429: bipush #34
    //   2431: ldc 541065232
    //   2433: iastore
    //   2434: dup
    //   2435: bipush #35
    //   2437: ldc 4210688
    //   2439: iastore
    //   2440: dup
    //   2441: bipush #36
    //   2443: ldc 541081616
    //   2445: iastore
    //   2446: dup
    //   2447: bipush #37
    //   2449: ldc 4194304
    //   2451: iastore
    //   2452: dup
    //   2453: bipush #38
    //   2455: sipush #16400
    //   2458: iastore
    //   2459: dup
    //   2460: bipush #39
    //   2462: ldc 536870928
    //   2464: iastore
    //   2465: dup
    //   2466: bipush #40
    //   2468: ldc 4194304
    //   2470: iastore
    //   2471: dup
    //   2472: bipush #41
    //   2474: ldc 536887296
    //   2476: iastore
    //   2477: dup
    //   2478: bipush #42
    //   2480: ldc 536870912
    //   2482: iastore
    //   2483: dup
    //   2484: bipush #43
    //   2486: sipush #16400
    //   2489: iastore
    //   2490: dup
    //   2491: bipush #44
    //   2493: ldc 536870928
    //   2495: iastore
    //   2496: dup
    //   2497: bipush #45
    //   2499: ldc 541081616
    //   2501: iastore
    //   2502: dup
    //   2503: bipush #46
    //   2505: ldc 4210688
    //   2507: iastore
    //   2508: dup
    //   2509: bipush #47
    //   2511: ldc 541065216
    //   2513: iastore
    //   2514: dup
    //   2515: bipush #48
    //   2517: ldc 4210704
    //   2519: iastore
    //   2520: dup
    //   2521: bipush #49
    //   2523: ldc 541081600
    //   2525: iastore
    //   2526: dup
    //   2527: bipush #50
    //   2529: iconst_0
    //   2530: iastore
    //   2531: dup
    //   2532: bipush #51
    //   2534: ldc 541065232
    //   2536: iastore
    //   2537: dup
    //   2538: bipush #52
    //   2540: bipush #16
    //   2542: iastore
    //   2543: dup
    //   2544: bipush #53
    //   2546: sipush #16384
    //   2549: iastore
    //   2550: dup
    //   2551: bipush #54
    //   2553: ldc 541065216
    //   2555: iastore
    //   2556: dup
    //   2557: bipush #55
    //   2559: ldc 4210704
    //   2561: iastore
    //   2562: dup
    //   2563: bipush #56
    //   2565: sipush #16384
    //   2568: iastore
    //   2569: dup
    //   2570: bipush #57
    //   2572: ldc 4194320
    //   2574: iastore
    //   2575: dup
    //   2576: bipush #58
    //   2578: ldc 536887312
    //   2580: iastore
    //   2581: dup
    //   2582: bipush #59
    //   2584: iconst_0
    //   2585: iastore
    //   2586: dup
    //   2587: bipush #60
    //   2589: ldc 541081600
    //   2591: iastore
    //   2592: dup
    //   2593: bipush #61
    //   2595: ldc 536870912
    //   2597: iastore
    //   2598: dup
    //   2599: bipush #62
    //   2601: ldc 4194320
    //   2603: iastore
    //   2604: dup
    //   2605: bipush #63
    //   2607: ldc 536887312
    //   2609: iastore
    //   2610: astore #13
    //   2612: bipush #64
    //   2614: newarray int
    //   2616: dup
    //   2617: iconst_0
    //   2618: ldc 2097152
    //   2620: iastore
    //   2621: dup
    //   2622: iconst_1
    //   2623: ldc 69206018
    //   2625: iastore
    //   2626: dup
    //   2627: iconst_2
    //   2628: ldc 67110914
    //   2630: iastore
    //   2631: dup
    //   2632: iconst_3
    //   2633: iconst_0
    //   2634: iastore
    //   2635: dup
    //   2636: iconst_4
    //   2637: sipush #2048
    //   2640: iastore
    //   2641: dup
    //   2642: iconst_5
    //   2643: ldc 67110914
    //   2645: iastore
    //   2646: dup
    //   2647: bipush #6
    //   2649: ldc 2099202
    //   2651: iastore
    //   2652: dup
    //   2653: bipush #7
    //   2655: ldc 69208064
    //   2657: iastore
    //   2658: dup
    //   2659: bipush #8
    //   2661: ldc 69208066
    //   2663: iastore
    //   2664: dup
    //   2665: bipush #9
    //   2667: ldc 2097152
    //   2669: iastore
    //   2670: dup
    //   2671: bipush #10
    //   2673: iconst_0
    //   2674: iastore
    //   2675: dup
    //   2676: bipush #11
    //   2678: ldc 67108866
    //   2680: iastore
    //   2681: dup
    //   2682: bipush #12
    //   2684: iconst_2
    //   2685: iastore
    //   2686: dup
    //   2687: bipush #13
    //   2689: ldc 67108864
    //   2691: iastore
    //   2692: dup
    //   2693: bipush #14
    //   2695: ldc 69206018
    //   2697: iastore
    //   2698: dup
    //   2699: bipush #15
    //   2701: sipush #2050
    //   2704: iastore
    //   2705: dup
    //   2706: bipush #16
    //   2708: ldc 67110912
    //   2710: iastore
    //   2711: dup
    //   2712: bipush #17
    //   2714: ldc 2099202
    //   2716: iastore
    //   2717: dup
    //   2718: bipush #18
    //   2720: ldc 2097154
    //   2722: iastore
    //   2723: dup
    //   2724: bipush #19
    //   2726: ldc 67110912
    //   2728: iastore
    //   2729: dup
    //   2730: bipush #20
    //   2732: ldc 67108866
    //   2734: iastore
    //   2735: dup
    //   2736: bipush #21
    //   2738: ldc 69206016
    //   2740: iastore
    //   2741: dup
    //   2742: bipush #22
    //   2744: ldc 69208064
    //   2746: iastore
    //   2747: dup
    //   2748: bipush #23
    //   2750: ldc 2097154
    //   2752: iastore
    //   2753: dup
    //   2754: bipush #24
    //   2756: ldc 69206016
    //   2758: iastore
    //   2759: dup
    //   2760: bipush #25
    //   2762: sipush #2048
    //   2765: iastore
    //   2766: dup
    //   2767: bipush #26
    //   2769: sipush #2050
    //   2772: iastore
    //   2773: dup
    //   2774: bipush #27
    //   2776: ldc 69208066
    //   2778: iastore
    //   2779: dup
    //   2780: bipush #28
    //   2782: ldc 2099200
    //   2784: iastore
    //   2785: dup
    //   2786: bipush #29
    //   2788: iconst_2
    //   2789: iastore
    //   2790: dup
    //   2791: bipush #30
    //   2793: ldc 67108864
    //   2795: iastore
    //   2796: dup
    //   2797: bipush #31
    //   2799: ldc 2099200
    //   2801: iastore
    //   2802: dup
    //   2803: bipush #32
    //   2805: ldc 67108864
    //   2807: iastore
    //   2808: dup
    //   2809: bipush #33
    //   2811: ldc 2099200
    //   2813: iastore
    //   2814: dup
    //   2815: bipush #34
    //   2817: ldc 2097152
    //   2819: iastore
    //   2820: dup
    //   2821: bipush #35
    //   2823: ldc 67110914
    //   2825: iastore
    //   2826: dup
    //   2827: bipush #36
    //   2829: ldc 67110914
    //   2831: iastore
    //   2832: dup
    //   2833: bipush #37
    //   2835: ldc 69206018
    //   2837: iastore
    //   2838: dup
    //   2839: bipush #38
    //   2841: ldc 69206018
    //   2843: iastore
    //   2844: dup
    //   2845: bipush #39
    //   2847: iconst_2
    //   2848: iastore
    //   2849: dup
    //   2850: bipush #40
    //   2852: ldc 2097154
    //   2854: iastore
    //   2855: dup
    //   2856: bipush #41
    //   2858: ldc 67108864
    //   2860: iastore
    //   2861: dup
    //   2862: bipush #42
    //   2864: ldc 67110912
    //   2866: iastore
    //   2867: dup
    //   2868: bipush #43
    //   2870: ldc 2097152
    //   2872: iastore
    //   2873: dup
    //   2874: bipush #44
    //   2876: ldc 69208064
    //   2878: iastore
    //   2879: dup
    //   2880: bipush #45
    //   2882: sipush #2050
    //   2885: iastore
    //   2886: dup
    //   2887: bipush #46
    //   2889: ldc 2099202
    //   2891: iastore
    //   2892: dup
    //   2893: bipush #47
    //   2895: ldc 69208064
    //   2897: iastore
    //   2898: dup
    //   2899: bipush #48
    //   2901: sipush #2050
    //   2904: iastore
    //   2905: dup
    //   2906: bipush #49
    //   2908: ldc 67108866
    //   2910: iastore
    //   2911: dup
    //   2912: bipush #50
    //   2914: ldc 69208066
    //   2916: iastore
    //   2917: dup
    //   2918: bipush #51
    //   2920: ldc 69206016
    //   2922: iastore
    //   2923: dup
    //   2924: bipush #52
    //   2926: ldc 2099200
    //   2928: iastore
    //   2929: dup
    //   2930: bipush #53
    //   2932: iconst_0
    //   2933: iastore
    //   2934: dup
    //   2935: bipush #54
    //   2937: iconst_2
    //   2938: iastore
    //   2939: dup
    //   2940: bipush #55
    //   2942: ldc 69208066
    //   2944: iastore
    //   2945: dup
    //   2946: bipush #56
    //   2948: iconst_0
    //   2949: iastore
    //   2950: dup
    //   2951: bipush #57
    //   2953: ldc 2099202
    //   2955: iastore
    //   2956: dup
    //   2957: bipush #58
    //   2959: ldc 69206016
    //   2961: iastore
    //   2962: dup
    //   2963: bipush #59
    //   2965: sipush #2048
    //   2968: iastore
    //   2969: dup
    //   2970: bipush #60
    //   2972: ldc 67108866
    //   2974: iastore
    //   2975: dup
    //   2976: bipush #61
    //   2978: ldc 67110912
    //   2980: iastore
    //   2981: dup
    //   2982: bipush #62
    //   2984: sipush #2048
    //   2987: iastore
    //   2988: dup
    //   2989: bipush #63
    //   2991: ldc 2097154
    //   2993: iastore
    //   2994: astore #14
    //   2996: bipush #64
    //   2998: newarray int
    //   3000: dup
    //   3001: iconst_0
    //   3002: ldc 268439616
    //   3004: iastore
    //   3005: dup
    //   3006: iconst_1
    //   3007: sipush #4096
    //   3010: iastore
    //   3011: dup
    //   3012: iconst_2
    //   3013: ldc 262144
    //   3015: iastore
    //   3016: dup
    //   3017: iconst_3
    //   3018: ldc 268701760
    //   3020: iastore
    //   3021: dup
    //   3022: iconst_4
    //   3023: ldc 268435456
    //   3025: iastore
    //   3026: dup
    //   3027: iconst_5
    //   3028: ldc 268439616
    //   3030: iastore
    //   3031: dup
    //   3032: bipush #6
    //   3034: bipush #64
    //   3036: iastore
    //   3037: dup
    //   3038: bipush #7
    //   3040: ldc 268435456
    //   3042: iastore
    //   3043: dup
    //   3044: bipush #8
    //   3046: ldc 262208
    //   3048: iastore
    //   3049: dup
    //   3050: bipush #9
    //   3052: ldc 268697600
    //   3054: iastore
    //   3055: dup
    //   3056: bipush #10
    //   3058: ldc 268701760
    //   3060: iastore
    //   3061: dup
    //   3062: bipush #11
    //   3064: ldc 266240
    //   3066: iastore
    //   3067: dup
    //   3068: bipush #12
    //   3070: ldc 268701696
    //   3072: iastore
    //   3073: dup
    //   3074: bipush #13
    //   3076: ldc 266304
    //   3078: iastore
    //   3079: dup
    //   3080: bipush #14
    //   3082: sipush #4096
    //   3085: iastore
    //   3086: dup
    //   3087: bipush #15
    //   3089: bipush #64
    //   3091: iastore
    //   3092: dup
    //   3093: bipush #16
    //   3095: ldc 268697600
    //   3097: iastore
    //   3098: dup
    //   3099: bipush #17
    //   3101: ldc 268435520
    //   3103: iastore
    //   3104: dup
    //   3105: bipush #18
    //   3107: ldc 268439552
    //   3109: iastore
    //   3110: dup
    //   3111: bipush #19
    //   3113: sipush #4160
    //   3116: iastore
    //   3117: dup
    //   3118: bipush #20
    //   3120: ldc 266240
    //   3122: iastore
    //   3123: dup
    //   3124: bipush #21
    //   3126: ldc 262208
    //   3128: iastore
    //   3129: dup
    //   3130: bipush #22
    //   3132: ldc 268697664
    //   3134: iastore
    //   3135: dup
    //   3136: bipush #23
    //   3138: ldc 268701696
    //   3140: iastore
    //   3141: dup
    //   3142: bipush #24
    //   3144: sipush #4160
    //   3147: iastore
    //   3148: dup
    //   3149: bipush #25
    //   3151: iconst_0
    //   3152: iastore
    //   3153: dup
    //   3154: bipush #26
    //   3156: iconst_0
    //   3157: iastore
    //   3158: dup
    //   3159: bipush #27
    //   3161: ldc 268697664
    //   3163: iastore
    //   3164: dup
    //   3165: bipush #28
    //   3167: ldc 268435520
    //   3169: iastore
    //   3170: dup
    //   3171: bipush #29
    //   3173: ldc 268439552
    //   3175: iastore
    //   3176: dup
    //   3177: bipush #30
    //   3179: ldc 266304
    //   3181: iastore
    //   3182: dup
    //   3183: bipush #31
    //   3185: ldc 262144
    //   3187: iastore
    //   3188: dup
    //   3189: bipush #32
    //   3191: ldc 266304
    //   3193: iastore
    //   3194: dup
    //   3195: bipush #33
    //   3197: ldc 262144
    //   3199: iastore
    //   3200: dup
    //   3201: bipush #34
    //   3203: ldc 268701696
    //   3205: iastore
    //   3206: dup
    //   3207: bipush #35
    //   3209: sipush #4096
    //   3212: iastore
    //   3213: dup
    //   3214: bipush #36
    //   3216: bipush #64
    //   3218: iastore
    //   3219: dup
    //   3220: bipush #37
    //   3222: ldc 268697664
    //   3224: iastore
    //   3225: dup
    //   3226: bipush #38
    //   3228: sipush #4096
    //   3231: iastore
    //   3232: dup
    //   3233: bipush #39
    //   3235: ldc 266304
    //   3237: iastore
    //   3238: dup
    //   3239: bipush #40
    //   3241: ldc 268439552
    //   3243: iastore
    //   3244: dup
    //   3245: bipush #41
    //   3247: bipush #64
    //   3249: iastore
    //   3250: dup
    //   3251: bipush #42
    //   3253: ldc 268435520
    //   3255: iastore
    //   3256: dup
    //   3257: bipush #43
    //   3259: ldc 268697600
    //   3261: iastore
    //   3262: dup
    //   3263: bipush #44
    //   3265: ldc 268697664
    //   3267: iastore
    //   3268: dup
    //   3269: bipush #45
    //   3271: ldc 268435456
    //   3273: iastore
    //   3274: dup
    //   3275: bipush #46
    //   3277: ldc 262144
    //   3279: iastore
    //   3280: dup
    //   3281: bipush #47
    //   3283: ldc 268439616
    //   3285: iastore
    //   3286: dup
    //   3287: bipush #48
    //   3289: iconst_0
    //   3290: iastore
    //   3291: dup
    //   3292: bipush #49
    //   3294: ldc 268701760
    //   3296: iastore
    //   3297: dup
    //   3298: bipush #50
    //   3300: ldc 262208
    //   3302: iastore
    //   3303: dup
    //   3304: bipush #51
    //   3306: ldc 268435520
    //   3308: iastore
    //   3309: dup
    //   3310: bipush #52
    //   3312: ldc 268697600
    //   3314: iastore
    //   3315: dup
    //   3316: bipush #53
    //   3318: ldc 268439552
    //   3320: iastore
    //   3321: dup
    //   3322: bipush #54
    //   3324: ldc 268439616
    //   3326: iastore
    //   3327: dup
    //   3328: bipush #55
    //   3330: iconst_0
    //   3331: iastore
    //   3332: dup
    //   3333: bipush #56
    //   3335: ldc 268701760
    //   3337: iastore
    //   3338: dup
    //   3339: bipush #57
    //   3341: ldc 266240
    //   3343: iastore
    //   3344: dup
    //   3345: bipush #58
    //   3347: ldc 266240
    //   3349: iastore
    //   3350: dup
    //   3351: bipush #59
    //   3353: sipush #4160
    //   3356: iastore
    //   3357: dup
    //   3358: bipush #60
    //   3360: sipush #4160
    //   3363: iastore
    //   3364: dup
    //   3365: bipush #61
    //   3367: ldc 262208
    //   3369: iastore
    //   3370: dup
    //   3371: bipush #62
    //   3373: ldc 268435456
    //   3375: iastore
    //   3376: dup
    //   3377: bipush #63
    //   3379: ldc 268701696
    //   3381: iastore
    //   3382: astore #15
    //   3384: aload_3
    //   3385: arraylength
    //   3386: istore #16
    //   3388: iconst_2
    //   3389: newarray int
    //   3391: astore #17
    //   3393: iload #16
    //   3395: newarray byte
    //   3397: astore #4
    //   3399: iload #16
    //   3401: bipush #8
    //   3403: idiv
    //   3404: istore #18
    //   3406: iconst_0
    //   3407: istore #19
    //   3409: iload #19
    //   3411: iload #18
    //   3413: if_icmpge -> 4327
    //   3416: iload #19
    //   3418: bipush #8
    //   3420: imul
    //   3421: istore #20
    //   3423: iconst_0
    //   3424: istore #21
    //   3426: iload #21
    //   3428: iconst_2
    //   3429: if_icmpge -> 3514
    //   3432: aload #17
    //   3434: iload #21
    //   3436: aload_3
    //   3437: iload #20
    //   3439: iload #21
    //   3441: iconst_4
    //   3442: imul
    //   3443: iadd
    //   3444: baload
    //   3445: sipush #255
    //   3448: iand
    //   3449: bipush #24
    //   3451: ishl
    //   3452: aload_3
    //   3453: iload #20
    //   3455: iload #21
    //   3457: iconst_4
    //   3458: imul
    //   3459: iadd
    //   3460: iconst_1
    //   3461: iadd
    //   3462: baload
    //   3463: sipush #255
    //   3466: iand
    //   3467: bipush #16
    //   3469: ishl
    //   3470: ior
    //   3471: aload_3
    //   3472: iload #20
    //   3474: iload #21
    //   3476: iconst_4
    //   3477: imul
    //   3478: iadd
    //   3479: iconst_2
    //   3480: iadd
    //   3481: baload
    //   3482: sipush #255
    //   3485: iand
    //   3486: bipush #8
    //   3488: ishl
    //   3489: ior
    //   3490: aload_3
    //   3491: iload #20
    //   3493: iload #21
    //   3495: iconst_4
    //   3496: imul
    //   3497: iadd
    //   3498: iconst_3
    //   3499: iadd
    //   3500: baload
    //   3501: sipush #255
    //   3504: iand
    //   3505: ior
    //   3506: iastore
    //   3507: iinc #21, 1
    //   3510: iload_2
    //   3511: ifne -> 3426
    //   3514: iconst_0
    //   3515: istore #26
    //   3517: aload #17
    //   3519: iconst_0
    //   3520: iaload
    //   3521: istore #24
    //   3523: aload #17
    //   3525: iconst_1
    //   3526: iaload
    //   3527: istore #23
    //   3529: iload #24
    //   3531: iconst_4
    //   3532: iushr
    //   3533: iload #23
    //   3535: ixor
    //   3536: ldc 252645135
    //   3538: iand
    //   3539: istore #22
    //   3541: iload #23
    //   3543: iload #22
    //   3545: ixor
    //   3546: istore #23
    //   3548: iload #24
    //   3550: iload #22
    //   3552: iconst_4
    //   3553: ishl
    //   3554: ixor
    //   3555: istore #24
    //   3557: iload #24
    //   3559: bipush #16
    //   3561: iushr
    //   3562: iload #23
    //   3564: ixor
    //   3565: ldc 65535
    //   3567: iand
    //   3568: istore #22
    //   3570: iload #23
    //   3572: iload #22
    //   3574: ixor
    //   3575: istore #23
    //   3577: iload #24
    //   3579: iload #22
    //   3581: bipush #16
    //   3583: ishl
    //   3584: ixor
    //   3585: istore #24
    //   3587: iload #23
    //   3589: iconst_2
    //   3590: iushr
    //   3591: iload #24
    //   3593: ixor
    //   3594: ldc 858993459
    //   3596: iand
    //   3597: istore #22
    //   3599: iload #24
    //   3601: iload #22
    //   3603: ixor
    //   3604: istore #24
    //   3606: iload #23
    //   3608: iload #22
    //   3610: iconst_2
    //   3611: ishl
    //   3612: ixor
    //   3613: istore #23
    //   3615: iload #23
    //   3617: bipush #8
    //   3619: iushr
    //   3620: iload #24
    //   3622: ixor
    //   3623: ldc 16711935
    //   3625: iand
    //   3626: istore #22
    //   3628: iload #24
    //   3630: iload #22
    //   3632: ixor
    //   3633: istore #24
    //   3635: iload #23
    //   3637: iload #22
    //   3639: bipush #8
    //   3641: ishl
    //   3642: ixor
    //   3643: istore #23
    //   3645: iload #23
    //   3647: iconst_1
    //   3648: ishl
    //   3649: iload #23
    //   3651: bipush #31
    //   3653: iushr
    //   3654: iconst_1
    //   3655: iand
    //   3656: ior
    //   3657: istore #23
    //   3659: iload #24
    //   3661: iload #23
    //   3663: ixor
    //   3664: ldc -1431655766
    //   3666: iand
    //   3667: istore #22
    //   3669: iload #24
    //   3671: iload #22
    //   3673: ixor
    //   3674: istore #24
    //   3676: iload #23
    //   3678: iload #22
    //   3680: ixor
    //   3681: istore #23
    //   3683: iload #24
    //   3685: iconst_1
    //   3686: ishl
    //   3687: iload #24
    //   3689: bipush #31
    //   3691: iushr
    //   3692: iconst_1
    //   3693: iand
    //   3694: ior
    //   3695: istore #24
    //   3697: iconst_0
    //   3698: istore #25
    //   3700: iload #25
    //   3702: bipush #8
    //   3704: if_icmpge -> 4042
    //   3707: iload #23
    //   3709: bipush #28
    //   3711: ishl
    //   3712: iload #23
    //   3714: iconst_4
    //   3715: iushr
    //   3716: ior
    //   3717: istore #22
    //   3719: iload #22
    //   3721: aload #5
    //   3723: iload #26
    //   3725: iinc #26, 1
    //   3728: iaload
    //   3729: ixor
    //   3730: istore #22
    //   3732: aload #14
    //   3734: iload #22
    //   3736: bipush #63
    //   3738: iand
    //   3739: iaload
    //   3740: istore #21
    //   3742: iload #21
    //   3744: aload #12
    //   3746: iload #22
    //   3748: bipush #8
    //   3750: iushr
    //   3751: bipush #63
    //   3753: iand
    //   3754: iaload
    //   3755: ior
    //   3756: istore #21
    //   3758: iload #21
    //   3760: aload #10
    //   3762: iload #22
    //   3764: bipush #16
    //   3766: iushr
    //   3767: bipush #63
    //   3769: iand
    //   3770: iaload
    //   3771: ior
    //   3772: istore #21
    //   3774: iload #21
    //   3776: aload #8
    //   3778: iload #22
    //   3780: bipush #24
    //   3782: iushr
    //   3783: bipush #63
    //   3785: iand
    //   3786: iaload
    //   3787: ior
    //   3788: istore #21
    //   3790: iload #23
    //   3792: aload #5
    //   3794: iload #26
    //   3796: iinc #26, 1
    //   3799: iaload
    //   3800: ixor
    //   3801: istore #22
    //   3803: iload #21
    //   3805: aload #15
    //   3807: iload #22
    //   3809: bipush #63
    //   3811: iand
    //   3812: iaload
    //   3813: ior
    //   3814: istore #21
    //   3816: iload #21
    //   3818: aload #13
    //   3820: iload #22
    //   3822: bipush #8
    //   3824: iushr
    //   3825: bipush #63
    //   3827: iand
    //   3828: iaload
    //   3829: ior
    //   3830: istore #21
    //   3832: iload #21
    //   3834: aload #11
    //   3836: iload #22
    //   3838: bipush #16
    //   3840: iushr
    //   3841: bipush #63
    //   3843: iand
    //   3844: iaload
    //   3845: ior
    //   3846: istore #21
    //   3848: iload #21
    //   3850: aload #9
    //   3852: iload #22
    //   3854: bipush #24
    //   3856: iushr
    //   3857: bipush #63
    //   3859: iand
    //   3860: iaload
    //   3861: ior
    //   3862: istore #21
    //   3864: iload #24
    //   3866: iload #21
    //   3868: ixor
    //   3869: istore #24
    //   3871: iload #24
    //   3873: bipush #28
    //   3875: ishl
    //   3876: iload #24
    //   3878: iconst_4
    //   3879: iushr
    //   3880: ior
    //   3881: istore #22
    //   3883: iload #22
    //   3885: aload #5
    //   3887: iload #26
    //   3889: iinc #26, 1
    //   3892: iaload
    //   3893: ixor
    //   3894: istore #22
    //   3896: aload #14
    //   3898: iload #22
    //   3900: bipush #63
    //   3902: iand
    //   3903: iaload
    //   3904: istore #21
    //   3906: iload #21
    //   3908: aload #12
    //   3910: iload #22
    //   3912: bipush #8
    //   3914: iushr
    //   3915: bipush #63
    //   3917: iand
    //   3918: iaload
    //   3919: ior
    //   3920: istore #21
    //   3922: iload #21
    //   3924: aload #10
    //   3926: iload #22
    //   3928: bipush #16
    //   3930: iushr
    //   3931: bipush #63
    //   3933: iand
    //   3934: iaload
    //   3935: ior
    //   3936: istore #21
    //   3938: iload #21
    //   3940: aload #8
    //   3942: iload #22
    //   3944: bipush #24
    //   3946: iushr
    //   3947: bipush #63
    //   3949: iand
    //   3950: iaload
    //   3951: ior
    //   3952: istore #21
    //   3954: iload #24
    //   3956: aload #5
    //   3958: iload #26
    //   3960: iinc #26, 1
    //   3963: iaload
    //   3964: ixor
    //   3965: istore #22
    //   3967: iload #21
    //   3969: aload #15
    //   3971: iload #22
    //   3973: bipush #63
    //   3975: iand
    //   3976: iaload
    //   3977: ior
    //   3978: istore #21
    //   3980: iload #21
    //   3982: aload #13
    //   3984: iload #22
    //   3986: bipush #8
    //   3988: iushr
    //   3989: bipush #63
    //   3991: iand
    //   3992: iaload
    //   3993: ior
    //   3994: istore #21
    //   3996: iload #21
    //   3998: aload #11
    //   4000: iload #22
    //   4002: bipush #16
    //   4004: iushr
    //   4005: bipush #63
    //   4007: iand
    //   4008: iaload
    //   4009: ior
    //   4010: istore #21
    //   4012: iload #21
    //   4014: aload #9
    //   4016: iload #22
    //   4018: bipush #24
    //   4020: iushr
    //   4021: bipush #63
    //   4023: iand
    //   4024: iaload
    //   4025: ior
    //   4026: istore #21
    //   4028: iload #23
    //   4030: iload #21
    //   4032: ixor
    //   4033: istore #23
    //   4035: iinc #25, 1
    //   4038: iload_2
    //   4039: ifne -> 3700
    //   4042: iload #23
    //   4044: bipush #31
    //   4046: ishl
    //   4047: iload #23
    //   4049: iconst_1
    //   4050: iushr
    //   4051: ior
    //   4052: istore #23
    //   4054: iload #24
    //   4056: iload #23
    //   4058: ixor
    //   4059: ldc -1431655766
    //   4061: iand
    //   4062: istore #22
    //   4064: iload #24
    //   4066: iload #22
    //   4068: ixor
    //   4069: istore #24
    //   4071: iload #23
    //   4073: iload #22
    //   4075: ixor
    //   4076: istore #23
    //   4078: iload #24
    //   4080: bipush #31
    //   4082: ishl
    //   4083: iload #24
    //   4085: iconst_1
    //   4086: iushr
    //   4087: ior
    //   4088: istore #24
    //   4090: iload #24
    //   4092: bipush #8
    //   4094: iushr
    //   4095: iload #23
    //   4097: ixor
    //   4098: ldc 16711935
    //   4100: iand
    //   4101: istore #22
    //   4103: iload #23
    //   4105: iload #22
    //   4107: ixor
    //   4108: istore #23
    //   4110: iload #24
    //   4112: iload #22
    //   4114: bipush #8
    //   4116: ishl
    //   4117: ixor
    //   4118: istore #24
    //   4120: iload #24
    //   4122: iconst_2
    //   4123: iushr
    //   4124: iload #23
    //   4126: ixor
    //   4127: ldc 858993459
    //   4129: iand
    //   4130: istore #22
    //   4132: iload #23
    //   4134: iload #22
    //   4136: ixor
    //   4137: istore #23
    //   4139: iload #24
    //   4141: iload #22
    //   4143: iconst_2
    //   4144: ishl
    //   4145: ixor
    //   4146: istore #24
    //   4148: iload #23
    //   4150: bipush #16
    //   4152: iushr
    //   4153: iload #24
    //   4155: ixor
    //   4156: ldc 65535
    //   4158: iand
    //   4159: istore #22
    //   4161: iload #24
    //   4163: iload #22
    //   4165: ixor
    //   4166: istore #24
    //   4168: iload #23
    //   4170: iload #22
    //   4172: bipush #16
    //   4174: ishl
    //   4175: ixor
    //   4176: istore #23
    //   4178: iload #23
    //   4180: iconst_4
    //   4181: iushr
    //   4182: iload #24
    //   4184: ixor
    //   4185: ldc 252645135
    //   4187: iand
    //   4188: istore #22
    //   4190: iload #24
    //   4192: iload #22
    //   4194: ixor
    //   4195: istore #24
    //   4197: iload #23
    //   4199: iload #22
    //   4201: iconst_4
    //   4202: ishl
    //   4203: ixor
    //   4204: istore #23
    //   4206: aload #17
    //   4208: iconst_0
    //   4209: iload #23
    //   4211: iastore
    //   4212: aload #17
    //   4214: iconst_1
    //   4215: iload #24
    //   4217: iastore
    //   4218: iload #19
    //   4220: bipush #8
    //   4222: imul
    //   4223: istore #27
    //   4225: iconst_0
    //   4226: istore #28
    //   4228: iload #28
    //   4230: iconst_2
    //   4231: if_icmpge -> 4320
    //   4234: aload #4
    //   4236: iload #27
    //   4238: iload #28
    //   4240: iconst_4
    //   4241: imul
    //   4242: iadd
    //   4243: aload #17
    //   4245: iload #28
    //   4247: iaload
    //   4248: bipush #24
    //   4250: iushr
    //   4251: i2b
    //   4252: bastore
    //   4253: aload #4
    //   4255: iload #27
    //   4257: iload #28
    //   4259: iconst_4
    //   4260: imul
    //   4261: iadd
    //   4262: iconst_1
    //   4263: iadd
    //   4264: aload #17
    //   4266: iload #28
    //   4268: iaload
    //   4269: bipush #16
    //   4271: iushr
    //   4272: i2b
    //   4273: bastore
    //   4274: aload #4
    //   4276: iload #27
    //   4278: iload #28
    //   4280: iconst_4
    //   4281: imul
    //   4282: iadd
    //   4283: iconst_2
    //   4284: iadd
    //   4285: aload #17
    //   4287: iload #28
    //   4289: iaload
    //   4290: bipush #8
    //   4292: iushr
    //   4293: i2b
    //   4294: bastore
    //   4295: aload #4
    //   4297: iload #27
    //   4299: iload #28
    //   4301: iconst_4
    //   4302: imul
    //   4303: iadd
    //   4304: iconst_3
    //   4305: iadd
    //   4306: aload #17
    //   4308: iload #28
    //   4310: iaload
    //   4311: i2b
    //   4312: bastore
    //   4313: iinc #28, 1
    //   4316: iload_2
    //   4317: ifne -> 4228
    //   4320: iinc #19, 1
    //   4323: iload_2
    //   4324: ifne -> 3409
    //   4327: new java/math/BigInteger
    //   4330: dup
    //   4331: aload #4
    //   4333: invokespecial <init> : ([B)V
    //   4336: invokevirtual abs : ()Ljava/math/BigInteger;
    //   4339: putstatic burp/Zs83.ZT : Ljava/lang/Object;
    //   4342: getstatic burp/Zgnp.Zm : Ljava/lang/Object;
    //   4345: checkcast java/math/BigInteger
    //   4348: invokevirtual toByteArray : ()[B
    //   4351: astore_3
    //   4352: bipush #32
    //   4354: newarray int
    //   4356: dup
    //   4357: iconst_0
    //   4358: ldc 943331329
    //   4360: iastore
    //   4361: dup
    //   4362: iconst_1
    //   4363: ldc 170788368
    //   4365: iastore
    //   4366: dup
    //   4367: iconst_2
    //   4368: ldc 1008414755
    //   4370: iastore
    //   4371: dup
    //   4372: iconst_3
    //   4373: ldc 187049985
    //   4375: iastore
    //   4376: dup
    //   4377: iconst_4
    //   4378: ldc 1010368540
    //   4380: iastore
    //   4381: dup
    //   4382: iconst_5
    //   4383: ldc 220604441
    //   4385: iastore
    //   4386: dup
    //   4387: bipush #6
    //   4389: ldc 940377620
    //   4391: iastore
    //   4392: dup
    //   4393: bipush #7
    //   4395: ldc 255209728
    //   4397: iastore
    //   4398: dup
    //   4399: bipush #8
    //   4401: ldc 689771012
    //   4403: iastore
    //   4404: dup
    //   4405: bipush #9
    //   4407: ldc 221709344
    //   4409: iastore
    //   4410: dup
    //   4411: bipush #10
    //   4413: ldc 957157408
    //   4415: iastore
    //   4416: dup
    //   4417: bipush #11
    //   4419: ldc 892536332
    //   4421: iastore
    //   4422: dup
    //   4423: bipush #12
    //   4425: ldc 722417666
    //   4427: iastore
    //   4428: dup
    //   4429: bipush #13
    //   4431: ldc 1026621720
    //   4433: iastore
    //   4434: dup
    //   4435: bipush #14
    //   4437: ldc 655302664
    //   4439: iastore
    //   4440: dup
    //   4441: bipush #15
    //   4443: ldc 890966315
    //   4445: iastore
    //   4446: dup
    //   4447: bipush #16
    //   4449: ldc 187632156
    //   4451: iastore
    //   4452: dup
    //   4453: bipush #17
    //   4455: ldc 874189824
    //   4457: iastore
    //   4458: dup
    //   4459: bipush #18
    //   4461: ldc 254150144
    //   4463: iastore
    //   4464: dup
    //   4465: bipush #19
    //   4467: ldc 924386310
    //   4469: iastore
    //   4470: dup
    //   4471: bipush #20
    //   4473: ldc 121057538
    //   4475: iastore
    //   4476: dup
    //   4477: bipush #21
    //   4479: ldc 840500228
    //   4481: iastore
    //   4482: dup
    //   4483: bipush #22
    //   4485: ldc 389160971
    //   4487: iastore
    //   4488: dup
    //   4489: bipush #23
    //   4491: ldc 907870729
    //   4493: iastore
    //   4494: dup
    //   4495: bipush #24
    //   4497: ldc 389426184
    //   4499: iastore
    //   4500: dup
    //   4501: bipush #25
    //   4503: ldc 973875457
    //   4505: iastore
    //   4506: dup
    //   4507: bipush #26
    //   4509: ldc 372376604
    //   4511: iastore
    //   4512: dup
    //   4513: bipush #27
    //   4515: ldc 707731490
    //   4517: iastore
    //   4518: dup
    //   4519: bipush #28
    //   4521: ldc 1043334948
    //   4523: iastore
    //   4524: dup
    //   4525: bipush #29
    //   4527: ldc 439222784
    //   4529: iastore
    //   4530: dup
    //   4531: bipush #30
    //   4533: ldc 876216579
    //   4535: iastore
    //   4536: dup
    //   4537: bipush #31
    //   4539: ldc 455999525
    //   4541: iastore
    //   4542: astore #5
    //   4544: bipush #8
    //   4546: aload_3
    //   4547: arraylength
    //   4548: bipush #8
    //   4550: irem
    //   4551: isub
    //   4552: istore #6
    //   4554: aload_3
    //   4555: arraylength
    //   4556: iload #6
    //   4558: iadd
    //   4559: newarray byte
    //   4561: astore #7
    //   4563: iconst_0
    //   4564: istore #8
    //   4566: iload #8
    //   4568: aload_3
    //   4569: arraylength
    //   4570: if_icmpge -> 4589
    //   4573: aload #7
    //   4575: iload #8
    //   4577: aload_3
    //   4578: iload #8
    //   4580: baload
    //   4581: bastore
    //   4582: iinc #8, 1
    //   4585: iload_2
    //   4586: ifne -> 4566
    //   4589: aload_3
    //   4590: arraylength
    //   4591: istore #8
    //   4593: iload #8
    //   4595: aload #7
    //   4597: arraylength
    //   4598: if_icmpge -> 4616
    //   4601: aload #7
    //   4603: iload #8
    //   4605: iload #6
    //   4607: i2b
    //   4608: bastore
    //   4609: iinc #8, 1
    //   4612: iload_2
    //   4613: ifne -> 4593
    //   4616: aload #7
    //   4618: astore_3
    //   4619: bipush #64
    //   4621: newarray int
    //   4623: dup
    //   4624: iconst_0
    //   4625: ldc 16843776
    //   4627: iastore
    //   4628: dup
    //   4629: iconst_1
    //   4630: iconst_0
    //   4631: iastore
    //   4632: dup
    //   4633: iconst_2
    //   4634: ldc 65536
    //   4636: iastore
    //   4637: dup
    //   4638: iconst_3
    //   4639: ldc 16843780
    //   4641: iastore
    //   4642: dup
    //   4643: iconst_4
    //   4644: ldc 16842756
    //   4646: iastore
    //   4647: dup
    //   4648: iconst_5
    //   4649: ldc 66564
    //   4651: iastore
    //   4652: dup
    //   4653: bipush #6
    //   4655: iconst_4
    //   4656: iastore
    //   4657: dup
    //   4658: bipush #7
    //   4660: ldc 65536
    //   4662: iastore
    //   4663: dup
    //   4664: bipush #8
    //   4666: sipush #1024
    //   4669: iastore
    //   4670: dup
    //   4671: bipush #9
    //   4673: ldc 16843776
    //   4675: iastore
    //   4676: dup
    //   4677: bipush #10
    //   4679: ldc 16843780
    //   4681: iastore
    //   4682: dup
    //   4683: bipush #11
    //   4685: sipush #1024
    //   4688: iastore
    //   4689: dup
    //   4690: bipush #12
    //   4692: ldc 16778244
    //   4694: iastore
    //   4695: dup
    //   4696: bipush #13
    //   4698: ldc 16842756
    //   4700: iastore
    //   4701: dup
    //   4702: bipush #14
    //   4704: ldc 16777216
    //   4706: iastore
    //   4707: dup
    //   4708: bipush #15
    //   4710: iconst_4
    //   4711: iastore
    //   4712: dup
    //   4713: bipush #16
    //   4715: sipush #1028
    //   4718: iastore
    //   4719: dup
    //   4720: bipush #17
    //   4722: ldc 16778240
    //   4724: iastore
    //   4725: dup
    //   4726: bipush #18
    //   4728: ldc 16778240
    //   4730: iastore
    //   4731: dup
    //   4732: bipush #19
    //   4734: ldc 66560
    //   4736: iastore
    //   4737: dup
    //   4738: bipush #20
    //   4740: ldc 66560
    //   4742: iastore
    //   4743: dup
    //   4744: bipush #21
    //   4746: ldc 16842752
    //   4748: iastore
    //   4749: dup
    //   4750: bipush #22
    //   4752: ldc 16842752
    //   4754: iastore
    //   4755: dup
    //   4756: bipush #23
    //   4758: ldc 16778244
    //   4760: iastore
    //   4761: dup
    //   4762: bipush #24
    //   4764: ldc 65540
    //   4766: iastore
    //   4767: dup
    //   4768: bipush #25
    //   4770: ldc 16777220
    //   4772: iastore
    //   4773: dup
    //   4774: bipush #26
    //   4776: ldc 16777220
    //   4778: iastore
    //   4779: dup
    //   4780: bipush #27
    //   4782: ldc 65540
    //   4784: iastore
    //   4785: dup
    //   4786: bipush #28
    //   4788: iconst_0
    //   4789: iastore
    //   4790: dup
    //   4791: bipush #29
    //   4793: sipush #1028
    //   4796: iastore
    //   4797: dup
    //   4798: bipush #30
    //   4800: ldc 66564
    //   4802: iastore
    //   4803: dup
    //   4804: bipush #31
    //   4806: ldc 16777216
    //   4808: iastore
    //   4809: dup
    //   4810: bipush #32
    //   4812: ldc 65536
    //   4814: iastore
    //   4815: dup
    //   4816: bipush #33
    //   4818: ldc 16843780
    //   4820: iastore
    //   4821: dup
    //   4822: bipush #34
    //   4824: iconst_4
    //   4825: iastore
    //   4826: dup
    //   4827: bipush #35
    //   4829: ldc 16842752
    //   4831: iastore
    //   4832: dup
    //   4833: bipush #36
    //   4835: ldc 16843776
    //   4837: iastore
    //   4838: dup
    //   4839: bipush #37
    //   4841: ldc 16777216
    //   4843: iastore
    //   4844: dup
    //   4845: bipush #38
    //   4847: ldc 16777216
    //   4849: iastore
    //   4850: dup
    //   4851: bipush #39
    //   4853: sipush #1024
    //   4856: iastore
    //   4857: dup
    //   4858: bipush #40
    //   4860: ldc 16842756
    //   4862: iastore
    //   4863: dup
    //   4864: bipush #41
    //   4866: ldc 65536
    //   4868: iastore
    //   4869: dup
    //   4870: bipush #42
    //   4872: ldc 66560
    //   4874: iastore
    //   4875: dup
    //   4876: bipush #43
    //   4878: ldc 16777220
    //   4880: iastore
    //   4881: dup
    //   4882: bipush #44
    //   4884: sipush #1024
    //   4887: iastore
    //   4888: dup
    //   4889: bipush #45
    //   4891: iconst_4
    //   4892: iastore
    //   4893: dup
    //   4894: bipush #46
    //   4896: ldc 16778244
    //   4898: iastore
    //   4899: dup
    //   4900: bipush #47
    //   4902: ldc 66564
    //   4904: iastore
    //   4905: dup
    //   4906: bipush #48
    //   4908: ldc 16843780
    //   4910: iastore
    //   4911: dup
    //   4912: bipush #49
    //   4914: ldc 65540
    //   4916: iastore
    //   4917: dup
    //   4918: bipush #50
    //   4920: ldc 16842752
    //   4922: iastore
    //   4923: dup
    //   4924: bipush #51
    //   4926: ldc 16778244
    //   4928: iastore
    //   4929: dup
    //   4930: bipush #52
    //   4932: ldc 16777220
    //   4934: iastore
    //   4935: dup
    //   4936: bipush #53
    //   4938: sipush #1028
    //   4941: iastore
    //   4942: dup
    //   4943: bipush #54
    //   4945: ldc 66564
    //   4947: iastore
    //   4948: dup
    //   4949: bipush #55
    //   4951: ldc 16843776
    //   4953: iastore
    //   4954: dup
    //   4955: bipush #56
    //   4957: sipush #1028
    //   4960: iastore
    //   4961: dup
    //   4962: bipush #57
    //   4964: ldc 16778240
    //   4966: iastore
    //   4967: dup
    //   4968: bipush #58
    //   4970: ldc 16778240
    //   4972: iastore
    //   4973: dup
    //   4974: bipush #59
    //   4976: iconst_0
    //   4977: iastore
    //   4978: dup
    //   4979: bipush #60
    //   4981: ldc 65540
    //   4983: iastore
    //   4984: dup
    //   4985: bipush #61
    //   4987: ldc 66560
    //   4989: iastore
    //   4990: dup
    //   4991: bipush #62
    //   4993: iconst_0
    //   4994: iastore
    //   4995: dup
    //   4996: bipush #63
    //   4998: ldc 16842756
    //   5000: iastore
    //   5001: astore #8
    //   5003: bipush #64
    //   5005: newarray int
    //   5007: dup
    //   5008: iconst_0
    //   5009: ldc -2146402272
    //   5011: iastore
    //   5012: dup
    //   5013: iconst_1
    //   5014: ldc -2147450880
    //   5016: iastore
    //   5017: dup
    //   5018: iconst_2
    //   5019: ldc 32768
    //   5021: iastore
    //   5022: dup
    //   5023: iconst_3
    //   5024: ldc 1081376
    //   5026: iastore
    //   5027: dup
    //   5028: iconst_4
    //   5029: ldc 1048576
    //   5031: iastore
    //   5032: dup
    //   5033: iconst_5
    //   5034: bipush #32
    //   5036: iastore
    //   5037: dup
    //   5038: bipush #6
    //   5040: ldc -2146435040
    //   5042: iastore
    //   5043: dup
    //   5044: bipush #7
    //   5046: ldc -2147450848
    //   5048: iastore
    //   5049: dup
    //   5050: bipush #8
    //   5052: ldc -2147483616
    //   5054: iastore
    //   5055: dup
    //   5056: bipush #9
    //   5058: ldc -2146402272
    //   5060: iastore
    //   5061: dup
    //   5062: bipush #10
    //   5064: ldc -2146402304
    //   5066: iastore
    //   5067: dup
    //   5068: bipush #11
    //   5070: ldc -2147483648
    //   5072: iastore
    //   5073: dup
    //   5074: bipush #12
    //   5076: ldc -2147450880
    //   5078: iastore
    //   5079: dup
    //   5080: bipush #13
    //   5082: ldc 1048576
    //   5084: iastore
    //   5085: dup
    //   5086: bipush #14
    //   5088: bipush #32
    //   5090: iastore
    //   5091: dup
    //   5092: bipush #15
    //   5094: ldc -2146435040
    //   5096: iastore
    //   5097: dup
    //   5098: bipush #16
    //   5100: ldc 1081344
    //   5102: iastore
    //   5103: dup
    //   5104: bipush #17
    //   5106: ldc 1048608
    //   5108: iastore
    //   5109: dup
    //   5110: bipush #18
    //   5112: ldc -2147450848
    //   5114: iastore
    //   5115: dup
    //   5116: bipush #19
    //   5118: iconst_0
    //   5119: iastore
    //   5120: dup
    //   5121: bipush #20
    //   5123: ldc -2147483648
    //   5125: iastore
    //   5126: dup
    //   5127: bipush #21
    //   5129: ldc 32768
    //   5131: iastore
    //   5132: dup
    //   5133: bipush #22
    //   5135: ldc 1081376
    //   5137: iastore
    //   5138: dup
    //   5139: bipush #23
    //   5141: ldc -2146435072
    //   5143: iastore
    //   5144: dup
    //   5145: bipush #24
    //   5147: ldc 1048608
    //   5149: iastore
    //   5150: dup
    //   5151: bipush #25
    //   5153: ldc -2147483616
    //   5155: iastore
    //   5156: dup
    //   5157: bipush #26
    //   5159: iconst_0
    //   5160: iastore
    //   5161: dup
    //   5162: bipush #27
    //   5164: ldc 1081344
    //   5166: iastore
    //   5167: dup
    //   5168: bipush #28
    //   5170: ldc 32800
    //   5172: iastore
    //   5173: dup
    //   5174: bipush #29
    //   5176: ldc -2146402304
    //   5178: iastore
    //   5179: dup
    //   5180: bipush #30
    //   5182: ldc -2146435072
    //   5184: iastore
    //   5185: dup
    //   5186: bipush #31
    //   5188: ldc 32800
    //   5190: iastore
    //   5191: dup
    //   5192: bipush #32
    //   5194: iconst_0
    //   5195: iastore
    //   5196: dup
    //   5197: bipush #33
    //   5199: ldc 1081376
    //   5201: iastore
    //   5202: dup
    //   5203: bipush #34
    //   5205: ldc -2146435040
    //   5207: iastore
    //   5208: dup
    //   5209: bipush #35
    //   5211: ldc 1048576
    //   5213: iastore
    //   5214: dup
    //   5215: bipush #36
    //   5217: ldc -2147450848
    //   5219: iastore
    //   5220: dup
    //   5221: bipush #37
    //   5223: ldc -2146435072
    //   5225: iastore
    //   5226: dup
    //   5227: bipush #38
    //   5229: ldc -2146402304
    //   5231: iastore
    //   5232: dup
    //   5233: bipush #39
    //   5235: ldc 32768
    //   5237: iastore
    //   5238: dup
    //   5239: bipush #40
    //   5241: ldc -2146435072
    //   5243: iastore
    //   5244: dup
    //   5245: bipush #41
    //   5247: ldc -2147450880
    //   5249: iastore
    //   5250: dup
    //   5251: bipush #42
    //   5253: bipush #32
    //   5255: iastore
    //   5256: dup
    //   5257: bipush #43
    //   5259: ldc -2146402272
    //   5261: iastore
    //   5262: dup
    //   5263: bipush #44
    //   5265: ldc 1081376
    //   5267: iastore
    //   5268: dup
    //   5269: bipush #45
    //   5271: bipush #32
    //   5273: iastore
    //   5274: dup
    //   5275: bipush #46
    //   5277: ldc 32768
    //   5279: iastore
    //   5280: dup
    //   5281: bipush #47
    //   5283: ldc -2147483648
    //   5285: iastore
    //   5286: dup
    //   5287: bipush #48
    //   5289: ldc 32800
    //   5291: iastore
    //   5292: dup
    //   5293: bipush #49
    //   5295: ldc -2146402304
    //   5297: iastore
    //   5298: dup
    //   5299: bipush #50
    //   5301: ldc 1048576
    //   5303: iastore
    //   5304: dup
    //   5305: bipush #51
    //   5307: ldc -2147483616
    //   5309: iastore
    //   5310: dup
    //   5311: bipush #52
    //   5313: ldc 1048608
    //   5315: iastore
    //   5316: dup
    //   5317: bipush #53
    //   5319: ldc -2147450848
    //   5321: iastore
    //   5322: dup
    //   5323: bipush #54
    //   5325: ldc -2147483616
    //   5327: iastore
    //   5328: dup
    //   5329: bipush #55
    //   5331: ldc 1048608
    //   5333: iastore
    //   5334: dup
    //   5335: bipush #56
    //   5337: ldc 1081344
    //   5339: iastore
    //   5340: dup
    //   5341: bipush #57
    //   5343: iconst_0
    //   5344: iastore
    //   5345: dup
    //   5346: bipush #58
    //   5348: ldc -2147450880
    //   5350: iastore
    //   5351: dup
    //   5352: bipush #59
    //   5354: ldc 32800
    //   5356: iastore
    //   5357: dup
    //   5358: bipush #60
    //   5360: ldc -2147483648
    //   5362: iastore
    //   5363: dup
    //   5364: bipush #61
    //   5366: ldc -2146435040
    //   5368: iastore
    //   5369: dup
    //   5370: bipush #62
    //   5372: ldc -2146402272
    //   5374: iastore
    //   5375: dup
    //   5376: bipush #63
    //   5378: ldc 1081344
    //   5380: iastore
    //   5381: astore #9
    //   5383: bipush #64
    //   5385: newarray int
    //   5387: dup
    //   5388: iconst_0
    //   5389: sipush #520
    //   5392: iastore
    //   5393: dup
    //   5394: iconst_1
    //   5395: ldc 134349312
    //   5397: iastore
    //   5398: dup
    //   5399: iconst_2
    //   5400: iconst_0
    //   5401: iastore
    //   5402: dup
    //   5403: iconst_3
    //   5404: ldc 134348808
    //   5406: iastore
    //   5407: dup
    //   5408: iconst_4
    //   5409: ldc 134218240
    //   5411: iastore
    //   5412: dup
    //   5413: iconst_5
    //   5414: iconst_0
    //   5415: iastore
    //   5416: dup
    //   5417: bipush #6
    //   5419: ldc 131592
    //   5421: iastore
    //   5422: dup
    //   5423: bipush #7
    //   5425: ldc 134218240
    //   5427: iastore
    //   5428: dup
    //   5429: bipush #8
    //   5431: ldc 131080
    //   5433: iastore
    //   5434: dup
    //   5435: bipush #9
    //   5437: ldc 134217736
    //   5439: iastore
    //   5440: dup
    //   5441: bipush #10
    //   5443: ldc 134217736
    //   5445: iastore
    //   5446: dup
    //   5447: bipush #11
    //   5449: ldc 131072
    //   5451: iastore
    //   5452: dup
    //   5453: bipush #12
    //   5455: ldc 134349320
    //   5457: iastore
    //   5458: dup
    //   5459: bipush #13
    //   5461: ldc 131080
    //   5463: iastore
    //   5464: dup
    //   5465: bipush #14
    //   5467: ldc 134348800
    //   5469: iastore
    //   5470: dup
    //   5471: bipush #15
    //   5473: sipush #520
    //   5476: iastore
    //   5477: dup
    //   5478: bipush #16
    //   5480: ldc 134217728
    //   5482: iastore
    //   5483: dup
    //   5484: bipush #17
    //   5486: bipush #8
    //   5488: iastore
    //   5489: dup
    //   5490: bipush #18
    //   5492: ldc 134349312
    //   5494: iastore
    //   5495: dup
    //   5496: bipush #19
    //   5498: sipush #512
    //   5501: iastore
    //   5502: dup
    //   5503: bipush #20
    //   5505: ldc 131584
    //   5507: iastore
    //   5508: dup
    //   5509: bipush #21
    //   5511: ldc 134348800
    //   5513: iastore
    //   5514: dup
    //   5515: bipush #22
    //   5517: ldc 134348808
    //   5519: iastore
    //   5520: dup
    //   5521: bipush #23
    //   5523: ldc 131592
    //   5525: iastore
    //   5526: dup
    //   5527: bipush #24
    //   5529: ldc 134218248
    //   5531: iastore
    //   5532: dup
    //   5533: bipush #25
    //   5535: ldc 131584
    //   5537: iastore
    //   5538: dup
    //   5539: bipush #26
    //   5541: ldc 131072
    //   5543: iastore
    //   5544: dup
    //   5545: bipush #27
    //   5547: ldc 134218248
    //   5549: iastore
    //   5550: dup
    //   5551: bipush #28
    //   5553: bipush #8
    //   5555: iastore
    //   5556: dup
    //   5557: bipush #29
    //   5559: ldc 134349320
    //   5561: iastore
    //   5562: dup
    //   5563: bipush #30
    //   5565: sipush #512
    //   5568: iastore
    //   5569: dup
    //   5570: bipush #31
    //   5572: ldc 134217728
    //   5574: iastore
    //   5575: dup
    //   5576: bipush #32
    //   5578: ldc 134349312
    //   5580: iastore
    //   5581: dup
    //   5582: bipush #33
    //   5584: ldc 134217728
    //   5586: iastore
    //   5587: dup
    //   5588: bipush #34
    //   5590: ldc 131080
    //   5592: iastore
    //   5593: dup
    //   5594: bipush #35
    //   5596: sipush #520
    //   5599: iastore
    //   5600: dup
    //   5601: bipush #36
    //   5603: ldc 131072
    //   5605: iastore
    //   5606: dup
    //   5607: bipush #37
    //   5609: ldc 134349312
    //   5611: iastore
    //   5612: dup
    //   5613: bipush #38
    //   5615: ldc 134218240
    //   5617: iastore
    //   5618: dup
    //   5619: bipush #39
    //   5621: iconst_0
    //   5622: iastore
    //   5623: dup
    //   5624: bipush #40
    //   5626: sipush #512
    //   5629: iastore
    //   5630: dup
    //   5631: bipush #41
    //   5633: ldc 131080
    //   5635: iastore
    //   5636: dup
    //   5637: bipush #42
    //   5639: ldc 134349320
    //   5641: iastore
    //   5642: dup
    //   5643: bipush #43
    //   5645: ldc 134218240
    //   5647: iastore
    //   5648: dup
    //   5649: bipush #44
    //   5651: ldc 134217736
    //   5653: iastore
    //   5654: dup
    //   5655: bipush #45
    //   5657: sipush #512
    //   5660: iastore
    //   5661: dup
    //   5662: bipush #46
    //   5664: iconst_0
    //   5665: iastore
    //   5666: dup
    //   5667: bipush #47
    //   5669: ldc 134348808
    //   5671: iastore
    //   5672: dup
    //   5673: bipush #48
    //   5675: ldc 134218248
    //   5677: iastore
    //   5678: dup
    //   5679: bipush #49
    //   5681: ldc 131072
    //   5683: iastore
    //   5684: dup
    //   5685: bipush #50
    //   5687: ldc 134217728
    //   5689: iastore
    //   5690: dup
    //   5691: bipush #51
    //   5693: ldc 134349320
    //   5695: iastore
    //   5696: dup
    //   5697: bipush #52
    //   5699: bipush #8
    //   5701: iastore
    //   5702: dup
    //   5703: bipush #53
    //   5705: ldc 131592
    //   5707: iastore
    //   5708: dup
    //   5709: bipush #54
    //   5711: ldc 131584
    //   5713: iastore
    //   5714: dup
    //   5715: bipush #55
    //   5717: ldc 134217736
    //   5719: iastore
    //   5720: dup
    //   5721: bipush #56
    //   5723: ldc 134348800
    //   5725: iastore
    //   5726: dup
    //   5727: bipush #57
    //   5729: ldc 134218248
    //   5731: iastore
    //   5732: dup
    //   5733: bipush #58
    //   5735: sipush #520
    //   5738: iastore
    //   5739: dup
    //   5740: bipush #59
    //   5742: ldc 134348800
    //   5744: iastore
    //   5745: dup
    //   5746: bipush #60
    //   5748: ldc 131592
    //   5750: iastore
    //   5751: dup
    //   5752: bipush #61
    //   5754: bipush #8
    //   5756: iastore
    //   5757: dup
    //   5758: bipush #62
    //   5760: ldc 134348808
    //   5762: iastore
    //   5763: dup
    //   5764: bipush #63
    //   5766: ldc 131584
    //   5768: iastore
    //   5769: astore #10
    //   5771: bipush #64
    //   5773: newarray int
    //   5775: dup
    //   5776: iconst_0
    //   5777: ldc 8396801
    //   5779: iastore
    //   5780: dup
    //   5781: iconst_1
    //   5782: sipush #8321
    //   5785: iastore
    //   5786: dup
    //   5787: iconst_2
    //   5788: sipush #8321
    //   5791: iastore
    //   5792: dup
    //   5793: iconst_3
    //   5794: sipush #128
    //   5797: iastore
    //   5798: dup
    //   5799: iconst_4
    //   5800: ldc 8396928
    //   5802: iastore
    //   5803: dup
    //   5804: iconst_5
    //   5805: ldc 8388737
    //   5807: iastore
    //   5808: dup
    //   5809: bipush #6
    //   5811: ldc 8388609
    //   5813: iastore
    //   5814: dup
    //   5815: bipush #7
    //   5817: sipush #8193
    //   5820: iastore
    //   5821: dup
    //   5822: bipush #8
    //   5824: iconst_0
    //   5825: iastore
    //   5826: dup
    //   5827: bipush #9
    //   5829: ldc 8396800
    //   5831: iastore
    //   5832: dup
    //   5833: bipush #10
    //   5835: ldc 8396800
    //   5837: iastore
    //   5838: dup
    //   5839: bipush #11
    //   5841: ldc 8396929
    //   5843: iastore
    //   5844: dup
    //   5845: bipush #12
    //   5847: sipush #129
    //   5850: iastore
    //   5851: dup
    //   5852: bipush #13
    //   5854: iconst_0
    //   5855: iastore
    //   5856: dup
    //   5857: bipush #14
    //   5859: ldc 8388736
    //   5861: iastore
    //   5862: dup
    //   5863: bipush #15
    //   5865: ldc 8388609
    //   5867: iastore
    //   5868: dup
    //   5869: bipush #16
    //   5871: iconst_1
    //   5872: iastore
    //   5873: dup
    //   5874: bipush #17
    //   5876: sipush #8192
    //   5879: iastore
    //   5880: dup
    //   5881: bipush #18
    //   5883: ldc 8388608
    //   5885: iastore
    //   5886: dup
    //   5887: bipush #19
    //   5889: ldc 8396801
    //   5891: iastore
    //   5892: dup
    //   5893: bipush #20
    //   5895: sipush #128
    //   5898: iastore
    //   5899: dup
    //   5900: bipush #21
    //   5902: ldc 8388608
    //   5904: iastore
    //   5905: dup
    //   5906: bipush #22
    //   5908: sipush #8193
    //   5911: iastore
    //   5912: dup
    //   5913: bipush #23
    //   5915: sipush #8320
    //   5918: iastore
    //   5919: dup
    //   5920: bipush #24
    //   5922: ldc 8388737
    //   5924: iastore
    //   5925: dup
    //   5926: bipush #25
    //   5928: iconst_1
    //   5929: iastore
    //   5930: dup
    //   5931: bipush #26
    //   5933: sipush #8320
    //   5936: iastore
    //   5937: dup
    //   5938: bipush #27
    //   5940: ldc 8388736
    //   5942: iastore
    //   5943: dup
    //   5944: bipush #28
    //   5946: sipush #8192
    //   5949: iastore
    //   5950: dup
    //   5951: bipush #29
    //   5953: ldc 8396928
    //   5955: iastore
    //   5956: dup
    //   5957: bipush #30
    //   5959: ldc 8396929
    //   5961: iastore
    //   5962: dup
    //   5963: bipush #31
    //   5965: sipush #129
    //   5968: iastore
    //   5969: dup
    //   5970: bipush #32
    //   5972: ldc 8388736
    //   5974: iastore
    //   5975: dup
    //   5976: bipush #33
    //   5978: ldc 8388609
    //   5980: iastore
    //   5981: dup
    //   5982: bipush #34
    //   5984: ldc 8396800
    //   5986: iastore
    //   5987: dup
    //   5988: bipush #35
    //   5990: ldc 8396929
    //   5992: iastore
    //   5993: dup
    //   5994: bipush #36
    //   5996: sipush #129
    //   5999: iastore
    //   6000: dup
    //   6001: bipush #37
    //   6003: iconst_0
    //   6004: iastore
    //   6005: dup
    //   6006: bipush #38
    //   6008: iconst_0
    //   6009: iastore
    //   6010: dup
    //   6011: bipush #39
    //   6013: ldc 8396800
    //   6015: iastore
    //   6016: dup
    //   6017: bipush #40
    //   6019: sipush #8320
    //   6022: iastore
    //   6023: dup
    //   6024: bipush #41
    //   6026: ldc 8388736
    //   6028: iastore
    //   6029: dup
    //   6030: bipush #42
    //   6032: ldc 8388737
    //   6034: iastore
    //   6035: dup
    //   6036: bipush #43
    //   6038: iconst_1
    //   6039: iastore
    //   6040: dup
    //   6041: bipush #44
    //   6043: ldc 8396801
    //   6045: iastore
    //   6046: dup
    //   6047: bipush #45
    //   6049: sipush #8321
    //   6052: iastore
    //   6053: dup
    //   6054: bipush #46
    //   6056: sipush #8321
    //   6059: iastore
    //   6060: dup
    //   6061: bipush #47
    //   6063: sipush #128
    //   6066: iastore
    //   6067: dup
    //   6068: bipush #48
    //   6070: ldc 8396929
    //   6072: iastore
    //   6073: dup
    //   6074: bipush #49
    //   6076: sipush #129
    //   6079: iastore
    //   6080: dup
    //   6081: bipush #50
    //   6083: iconst_1
    //   6084: iastore
    //   6085: dup
    //   6086: bipush #51
    //   6088: sipush #8192
    //   6091: iastore
    //   6092: dup
    //   6093: bipush #52
    //   6095: ldc 8388609
    //   6097: iastore
    //   6098: dup
    //   6099: bipush #53
    //   6101: sipush #8193
    //   6104: iastore
    //   6105: dup
    //   6106: bipush #54
    //   6108: ldc 8396928
    //   6110: iastore
    //   6111: dup
    //   6112: bipush #55
    //   6114: ldc 8388737
    //   6116: iastore
    //   6117: dup
    //   6118: bipush #56
    //   6120: sipush #8193
    //   6123: iastore
    //   6124: dup
    //   6125: bipush #57
    //   6127: sipush #8320
    //   6130: iastore
    //   6131: dup
    //   6132: bipush #58
    //   6134: ldc 8388608
    //   6136: iastore
    //   6137: dup
    //   6138: bipush #59
    //   6140: ldc 8396801
    //   6142: iastore
    //   6143: dup
    //   6144: bipush #60
    //   6146: sipush #128
    //   6149: iastore
    //   6150: dup
    //   6151: bipush #61
    //   6153: ldc 8388608
    //   6155: iastore
    //   6156: dup
    //   6157: bipush #62
    //   6159: sipush #8192
    //   6162: iastore
    //   6163: dup
    //   6164: bipush #63
    //   6166: ldc 8396928
    //   6168: iastore
    //   6169: astore #11
    //   6171: bipush #64
    //   6173: newarray int
    //   6175: dup
    //   6176: iconst_0
    //   6177: sipush #256
    //   6180: iastore
    //   6181: dup
    //   6182: iconst_1
    //   6183: ldc 34078976
    //   6185: iastore
    //   6186: dup
    //   6187: iconst_2
    //   6188: ldc 34078720
    //   6190: iastore
    //   6191: dup
    //   6192: iconst_3
    //   6193: ldc 1107296512
    //   6195: iastore
    //   6196: dup
    //   6197: iconst_4
    //   6198: ldc 524288
    //   6200: iastore
    //   6201: dup
    //   6202: iconst_5
    //   6203: sipush #256
    //   6206: iastore
    //   6207: dup
    //   6208: bipush #6
    //   6210: ldc 1073741824
    //   6212: iastore
    //   6213: dup
    //   6214: bipush #7
    //   6216: ldc 34078720
    //   6218: iastore
    //   6219: dup
    //   6220: bipush #8
    //   6222: ldc 1074266368
    //   6224: iastore
    //   6225: dup
    //   6226: bipush #9
    //   6228: ldc 524288
    //   6230: iastore
    //   6231: dup
    //   6232: bipush #10
    //   6234: ldc 33554688
    //   6236: iastore
    //   6237: dup
    //   6238: bipush #11
    //   6240: ldc 1074266368
    //   6242: iastore
    //   6243: dup
    //   6244: bipush #12
    //   6246: ldc 1107296512
    //   6248: iastore
    //   6249: dup
    //   6250: bipush #13
    //   6252: ldc 1107820544
    //   6254: iastore
    //   6255: dup
    //   6256: bipush #14
    //   6258: ldc 524544
    //   6260: iastore
    //   6261: dup
    //   6262: bipush #15
    //   6264: ldc 1073741824
    //   6266: iastore
    //   6267: dup
    //   6268: bipush #16
    //   6270: ldc 33554432
    //   6272: iastore
    //   6273: dup
    //   6274: bipush #17
    //   6276: ldc 1074266112
    //   6278: iastore
    //   6279: dup
    //   6280: bipush #18
    //   6282: ldc 1074266112
    //   6284: iastore
    //   6285: dup
    //   6286: bipush #19
    //   6288: iconst_0
    //   6289: iastore
    //   6290: dup
    //   6291: bipush #20
    //   6293: ldc 1073742080
    //   6295: iastore
    //   6296: dup
    //   6297: bipush #21
    //   6299: ldc 1107820800
    //   6301: iastore
    //   6302: dup
    //   6303: bipush #22
    //   6305: ldc 1107820800
    //   6307: iastore
    //   6308: dup
    //   6309: bipush #23
    //   6311: ldc 33554688
    //   6313: iastore
    //   6314: dup
    //   6315: bipush #24
    //   6317: ldc 1107820544
    //   6319: iastore
    //   6320: dup
    //   6321: bipush #25
    //   6323: ldc 1073742080
    //   6325: iastore
    //   6326: dup
    //   6327: bipush #26
    //   6329: iconst_0
    //   6330: iastore
    //   6331: dup
    //   6332: bipush #27
    //   6334: ldc 1107296256
    //   6336: iastore
    //   6337: dup
    //   6338: bipush #28
    //   6340: ldc 34078976
    //   6342: iastore
    //   6343: dup
    //   6344: bipush #29
    //   6346: ldc 33554432
    //   6348: iastore
    //   6349: dup
    //   6350: bipush #30
    //   6352: ldc 1107296256
    //   6354: iastore
    //   6355: dup
    //   6356: bipush #31
    //   6358: ldc 524544
    //   6360: iastore
    //   6361: dup
    //   6362: bipush #32
    //   6364: ldc 524288
    //   6366: iastore
    //   6367: dup
    //   6368: bipush #33
    //   6370: ldc 1107296512
    //   6372: iastore
    //   6373: dup
    //   6374: bipush #34
    //   6376: sipush #256
    //   6379: iastore
    //   6380: dup
    //   6381: bipush #35
    //   6383: ldc 33554432
    //   6385: iastore
    //   6386: dup
    //   6387: bipush #36
    //   6389: ldc 1073741824
    //   6391: iastore
    //   6392: dup
    //   6393: bipush #37
    //   6395: ldc 34078720
    //   6397: iastore
    //   6398: dup
    //   6399: bipush #38
    //   6401: ldc 1107296512
    //   6403: iastore
    //   6404: dup
    //   6405: bipush #39
    //   6407: ldc 1074266368
    //   6409: iastore
    //   6410: dup
    //   6411: bipush #40
    //   6413: ldc 33554688
    //   6415: iastore
    //   6416: dup
    //   6417: bipush #41
    //   6419: ldc 1073741824
    //   6421: iastore
    //   6422: dup
    //   6423: bipush #42
    //   6425: ldc 1107820544
    //   6427: iastore
    //   6428: dup
    //   6429: bipush #43
    //   6431: ldc 34078976
    //   6433: iastore
    //   6434: dup
    //   6435: bipush #44
    //   6437: ldc 1074266368
    //   6439: iastore
    //   6440: dup
    //   6441: bipush #45
    //   6443: sipush #256
    //   6446: iastore
    //   6447: dup
    //   6448: bipush #46
    //   6450: ldc 33554432
    //   6452: iastore
    //   6453: dup
    //   6454: bipush #47
    //   6456: ldc 1107820544
    //   6458: iastore
    //   6459: dup
    //   6460: bipush #48
    //   6462: ldc 1107820800
    //   6464: iastore
    //   6465: dup
    //   6466: bipush #49
    //   6468: ldc 524544
    //   6470: iastore
    //   6471: dup
    //   6472: bipush #50
    //   6474: ldc 1107296256
    //   6476: iastore
    //   6477: dup
    //   6478: bipush #51
    //   6480: ldc 1107820800
    //   6482: iastore
    //   6483: dup
    //   6484: bipush #52
    //   6486: ldc 34078720
    //   6488: iastore
    //   6489: dup
    //   6490: bipush #53
    //   6492: iconst_0
    //   6493: iastore
    //   6494: dup
    //   6495: bipush #54
    //   6497: ldc 1074266112
    //   6499: iastore
    //   6500: dup
    //   6501: bipush #55
    //   6503: ldc 1107296256
    //   6505: iastore
    //   6506: dup
    //   6507: bipush #56
    //   6509: ldc 524544
    //   6511: iastore
    //   6512: dup
    //   6513: bipush #57
    //   6515: ldc 33554688
    //   6517: iastore
    //   6518: dup
    //   6519: bipush #58
    //   6521: ldc 1073742080
    //   6523: iastore
    //   6524: dup
    //   6525: bipush #59
    //   6527: ldc 524288
    //   6529: iastore
    //   6530: dup
    //   6531: bipush #60
    //   6533: iconst_0
    //   6534: iastore
    //   6535: dup
    //   6536: bipush #61
    //   6538: ldc 1074266112
    //   6540: iastore
    //   6541: dup
    //   6542: bipush #62
    //   6544: ldc 34078976
    //   6546: iastore
    //   6547: dup
    //   6548: bipush #63
    //   6550: ldc 1073742080
    //   6552: iastore
    //   6553: astore #12
    //   6555: bipush #64
    //   6557: newarray int
    //   6559: dup
    //   6560: iconst_0
    //   6561: ldc 536870928
    //   6563: iastore
    //   6564: dup
    //   6565: iconst_1
    //   6566: ldc 541065216
    //   6568: iastore
    //   6569: dup
    //   6570: iconst_2
    //   6571: sipush #16384
    //   6574: iastore
    //   6575: dup
    //   6576: iconst_3
    //   6577: ldc 541081616
    //   6579: iastore
    //   6580: dup
    //   6581: iconst_4
    //   6582: ldc 541065216
    //   6584: iastore
    //   6585: dup
    //   6586: iconst_5
    //   6587: bipush #16
    //   6589: iastore
    //   6590: dup
    //   6591: bipush #6
    //   6593: ldc 541081616
    //   6595: iastore
    //   6596: dup
    //   6597: bipush #7
    //   6599: ldc 4194304
    //   6601: iastore
    //   6602: dup
    //   6603: bipush #8
    //   6605: ldc 536887296
    //   6607: iastore
    //   6608: dup
    //   6609: bipush #9
    //   6611: ldc 4210704
    //   6613: iastore
    //   6614: dup
    //   6615: bipush #10
    //   6617: ldc 4194304
    //   6619: iastore
    //   6620: dup
    //   6621: bipush #11
    //   6623: ldc 536870928
    //   6625: iastore
    //   6626: dup
    //   6627: bipush #12
    //   6629: ldc 4194320
    //   6631: iastore
    //   6632: dup
    //   6633: bipush #13
    //   6635: ldc 536887296
    //   6637: iastore
    //   6638: dup
    //   6639: bipush #14
    //   6641: ldc 536870912
    //   6643: iastore
    //   6644: dup
    //   6645: bipush #15
    //   6647: sipush #16400
    //   6650: iastore
    //   6651: dup
    //   6652: bipush #16
    //   6654: iconst_0
    //   6655: iastore
    //   6656: dup
    //   6657: bipush #17
    //   6659: ldc 4194320
    //   6661: iastore
    //   6662: dup
    //   6663: bipush #18
    //   6665: ldc 536887312
    //   6667: iastore
    //   6668: dup
    //   6669: bipush #19
    //   6671: sipush #16384
    //   6674: iastore
    //   6675: dup
    //   6676: bipush #20
    //   6678: ldc 4210688
    //   6680: iastore
    //   6681: dup
    //   6682: bipush #21
    //   6684: ldc 536887312
    //   6686: iastore
    //   6687: dup
    //   6688: bipush #22
    //   6690: bipush #16
    //   6692: iastore
    //   6693: dup
    //   6694: bipush #23
    //   6696: ldc 541065232
    //   6698: iastore
    //   6699: dup
    //   6700: bipush #24
    //   6702: ldc 541065232
    //   6704: iastore
    //   6705: dup
    //   6706: bipush #25
    //   6708: iconst_0
    //   6709: iastore
    //   6710: dup
    //   6711: bipush #26
    //   6713: ldc 4210704
    //   6715: iastore
    //   6716: dup
    //   6717: bipush #27
    //   6719: ldc 541081600
    //   6721: iastore
    //   6722: dup
    //   6723: bipush #28
    //   6725: sipush #16400
    //   6728: iastore
    //   6729: dup
    //   6730: bipush #29
    //   6732: ldc 4210688
    //   6734: iastore
    //   6735: dup
    //   6736: bipush #30
    //   6738: ldc 541081600
    //   6740: iastore
    //   6741: dup
    //   6742: bipush #31
    //   6744: ldc 536870912
    //   6746: iastore
    //   6747: dup
    //   6748: bipush #32
    //   6750: ldc 536887296
    //   6752: iastore
    //   6753: dup
    //   6754: bipush #33
    //   6756: bipush #16
    //   6758: iastore
    //   6759: dup
    //   6760: bipush #34
    //   6762: ldc 541065232
    //   6764: iastore
    //   6765: dup
    //   6766: bipush #35
    //   6768: ldc 4210688
    //   6770: iastore
    //   6771: dup
    //   6772: bipush #36
    //   6774: ldc 541081616
    //   6776: iastore
    //   6777: dup
    //   6778: bipush #37
    //   6780: ldc 4194304
    //   6782: iastore
    //   6783: dup
    //   6784: bipush #38
    //   6786: sipush #16400
    //   6789: iastore
    //   6790: dup
    //   6791: bipush #39
    //   6793: ldc 536870928
    //   6795: iastore
    //   6796: dup
    //   6797: bipush #40
    //   6799: ldc 4194304
    //   6801: iastore
    //   6802: dup
    //   6803: bipush #41
    //   6805: ldc 536887296
    //   6807: iastore
    //   6808: dup
    //   6809: bipush #42
    //   6811: ldc 536870912
    //   6813: iastore
    //   6814: dup
    //   6815: bipush #43
    //   6817: sipush #16400
    //   6820: iastore
    //   6821: dup
    //   6822: bipush #44
    //   6824: ldc 536870928
    //   6826: iastore
    //   6827: dup
    //   6828: bipush #45
    //   6830: ldc 541081616
    //   6832: iastore
    //   6833: dup
    //   6834: bipush #46
    //   6836: ldc 4210688
    //   6838: iastore
    //   6839: dup
    //   6840: bipush #47
    //   6842: ldc 541065216
    //   6844: iastore
    //   6845: dup
    //   6846: bipush #48
    //   6848: ldc 4210704
    //   6850: iastore
    //   6851: dup
    //   6852: bipush #49
    //   6854: ldc 541081600
    //   6856: iastore
    //   6857: dup
    //   6858: bipush #50
    //   6860: iconst_0
    //   6861: iastore
    //   6862: dup
    //   6863: bipush #51
    //   6865: ldc 541065232
    //   6867: iastore
    //   6868: dup
    //   6869: bipush #52
    //   6871: bipush #16
    //   6873: iastore
    //   6874: dup
    //   6875: bipush #53
    //   6877: sipush #16384
    //   6880: iastore
    //   6881: dup
    //   6882: bipush #54
    //   6884: ldc 541065216
    //   6886: iastore
    //   6887: dup
    //   6888: bipush #55
    //   6890: ldc 4210704
    //   6892: iastore
    //   6893: dup
    //   6894: bipush #56
    //   6896: sipush #16384
    //   6899: iastore
    //   6900: dup
    //   6901: bipush #57
    //   6903: ldc 4194320
    //   6905: iastore
    //   6906: dup
    //   6907: bipush #58
    //   6909: ldc 536887312
    //   6911: iastore
    //   6912: dup
    //   6913: bipush #59
    //   6915: iconst_0
    //   6916: iastore
    //   6917: dup
    //   6918: bipush #60
    //   6920: ldc 541081600
    //   6922: iastore
    //   6923: dup
    //   6924: bipush #61
    //   6926: ldc 536870912
    //   6928: iastore
    //   6929: dup
    //   6930: bipush #62
    //   6932: ldc 4194320
    //   6934: iastore
    //   6935: dup
    //   6936: bipush #63
    //   6938: ldc 536887312
    //   6940: iastore
    //   6941: astore #13
    //   6943: bipush #64
    //   6945: newarray int
    //   6947: dup
    //   6948: iconst_0
    //   6949: ldc 2097152
    //   6951: iastore
    //   6952: dup
    //   6953: iconst_1
    //   6954: ldc 69206018
    //   6956: iastore
    //   6957: dup
    //   6958: iconst_2
    //   6959: ldc 67110914
    //   6961: iastore
    //   6962: dup
    //   6963: iconst_3
    //   6964: iconst_0
    //   6965: iastore
    //   6966: dup
    //   6967: iconst_4
    //   6968: sipush #2048
    //   6971: iastore
    //   6972: dup
    //   6973: iconst_5
    //   6974: ldc 67110914
    //   6976: iastore
    //   6977: dup
    //   6978: bipush #6
    //   6980: ldc 2099202
    //   6982: iastore
    //   6983: dup
    //   6984: bipush #7
    //   6986: ldc 69208064
    //   6988: iastore
    //   6989: dup
    //   6990: bipush #8
    //   6992: ldc 69208066
    //   6994: iastore
    //   6995: dup
    //   6996: bipush #9
    //   6998: ldc 2097152
    //   7000: iastore
    //   7001: dup
    //   7002: bipush #10
    //   7004: iconst_0
    //   7005: iastore
    //   7006: dup
    //   7007: bipush #11
    //   7009: ldc 67108866
    //   7011: iastore
    //   7012: dup
    //   7013: bipush #12
    //   7015: iconst_2
    //   7016: iastore
    //   7017: dup
    //   7018: bipush #13
    //   7020: ldc 67108864
    //   7022: iastore
    //   7023: dup
    //   7024: bipush #14
    //   7026: ldc 69206018
    //   7028: iastore
    //   7029: dup
    //   7030: bipush #15
    //   7032: sipush #2050
    //   7035: iastore
    //   7036: dup
    //   7037: bipush #16
    //   7039: ldc 67110912
    //   7041: iastore
    //   7042: dup
    //   7043: bipush #17
    //   7045: ldc 2099202
    //   7047: iastore
    //   7048: dup
    //   7049: bipush #18
    //   7051: ldc 2097154
    //   7053: iastore
    //   7054: dup
    //   7055: bipush #19
    //   7057: ldc 67110912
    //   7059: iastore
    //   7060: dup
    //   7061: bipush #20
    //   7063: ldc 67108866
    //   7065: iastore
    //   7066: dup
    //   7067: bipush #21
    //   7069: ldc 69206016
    //   7071: iastore
    //   7072: dup
    //   7073: bipush #22
    //   7075: ldc 69208064
    //   7077: iastore
    //   7078: dup
    //   7079: bipush #23
    //   7081: ldc 2097154
    //   7083: iastore
    //   7084: dup
    //   7085: bipush #24
    //   7087: ldc 69206016
    //   7089: iastore
    //   7090: dup
    //   7091: bipush #25
    //   7093: sipush #2048
    //   7096: iastore
    //   7097: dup
    //   7098: bipush #26
    //   7100: sipush #2050
    //   7103: iastore
    //   7104: dup
    //   7105: bipush #27
    //   7107: ldc 69208066
    //   7109: iastore
    //   7110: dup
    //   7111: bipush #28
    //   7113: ldc 2099200
    //   7115: iastore
    //   7116: dup
    //   7117: bipush #29
    //   7119: iconst_2
    //   7120: iastore
    //   7121: dup
    //   7122: bipush #30
    //   7124: ldc 67108864
    //   7126: iastore
    //   7127: dup
    //   7128: bipush #31
    //   7130: ldc 2099200
    //   7132: iastore
    //   7133: dup
    //   7134: bipush #32
    //   7136: ldc 67108864
    //   7138: iastore
    //   7139: dup
    //   7140: bipush #33
    //   7142: ldc 2099200
    //   7144: iastore
    //   7145: dup
    //   7146: bipush #34
    //   7148: ldc 2097152
    //   7150: iastore
    //   7151: dup
    //   7152: bipush #35
    //   7154: ldc 67110914
    //   7156: iastore
    //   7157: dup
    //   7158: bipush #36
    //   7160: ldc 67110914
    //   7162: iastore
    //   7163: dup
    //   7164: bipush #37
    //   7166: ldc 69206018
    //   7168: iastore
    //   7169: dup
    //   7170: bipush #38
    //   7172: ldc 69206018
    //   7174: iastore
    //   7175: dup
    //   7176: bipush #39
    //   7178: iconst_2
    //   7179: iastore
    //   7180: dup
    //   7181: bipush #40
    //   7183: ldc 2097154
    //   7185: iastore
    //   7186: dup
    //   7187: bipush #41
    //   7189: ldc 67108864
    //   7191: iastore
    //   7192: dup
    //   7193: bipush #42
    //   7195: ldc 67110912
    //   7197: iastore
    //   7198: dup
    //   7199: bipush #43
    //   7201: ldc 2097152
    //   7203: iastore
    //   7204: dup
    //   7205: bipush #44
    //   7207: ldc 69208064
    //   7209: iastore
    //   7210: dup
    //   7211: bipush #45
    //   7213: sipush #2050
    //   7216: iastore
    //   7217: dup
    //   7218: bipush #46
    //   7220: ldc 2099202
    //   7222: iastore
    //   7223: dup
    //   7224: bipush #47
    //   7226: ldc 69208064
    //   7228: iastore
    //   7229: dup
    //   7230: bipush #48
    //   7232: sipush #2050
    //   7235: iastore
    //   7236: dup
    //   7237: bipush #49
    //   7239: ldc 67108866
    //   7241: iastore
    //   7242: dup
    //   7243: bipush #50
    //   7245: ldc 69208066
    //   7247: iastore
    //   7248: dup
    //   7249: bipush #51
    //   7251: ldc 69206016
    //   7253: iastore
    //   7254: dup
    //   7255: bipush #52
    //   7257: ldc 2099200
    //   7259: iastore
    //   7260: dup
    //   7261: bipush #53
    //   7263: iconst_0
    //   7264: iastore
    //   7265: dup
    //   7266: bipush #54
    //   7268: iconst_2
    //   7269: iastore
    //   7270: dup
    //   7271: bipush #55
    //   7273: ldc 69208066
    //   7275: iastore
    //   7276: dup
    //   7277: bipush #56
    //   7279: iconst_0
    //   7280: iastore
    //   7281: dup
    //   7282: bipush #57
    //   7284: ldc 2099202
    //   7286: iastore
    //   7287: dup
    //   7288: bipush #58
    //   7290: ldc 69206016
    //   7292: iastore
    //   7293: dup
    //   7294: bipush #59
    //   7296: sipush #2048
    //   7299: iastore
    //   7300: dup
    //   7301: bipush #60
    //   7303: ldc 67108866
    //   7305: iastore
    //   7306: dup
    //   7307: bipush #61
    //   7309: ldc 67110912
    //   7311: iastore
    //   7312: dup
    //   7313: bipush #62
    //   7315: sipush #2048
    //   7318: iastore
    //   7319: dup
    //   7320: bipush #63
    //   7322: ldc 2097154
    //   7324: iastore
    //   7325: astore #14
    //   7327: bipush #64
    //   7329: newarray int
    //   7331: dup
    //   7332: iconst_0
    //   7333: ldc 268439616
    //   7335: iastore
    //   7336: dup
    //   7337: iconst_1
    //   7338: sipush #4096
    //   7341: iastore
    //   7342: dup
    //   7343: iconst_2
    //   7344: ldc 262144
    //   7346: iastore
    //   7347: dup
    //   7348: iconst_3
    //   7349: ldc 268701760
    //   7351: iastore
    //   7352: dup
    //   7353: iconst_4
    //   7354: ldc 268435456
    //   7356: iastore
    //   7357: dup
    //   7358: iconst_5
    //   7359: ldc 268439616
    //   7361: iastore
    //   7362: dup
    //   7363: bipush #6
    //   7365: bipush #64
    //   7367: iastore
    //   7368: dup
    //   7369: bipush #7
    //   7371: ldc 268435456
    //   7373: iastore
    //   7374: dup
    //   7375: bipush #8
    //   7377: ldc 262208
    //   7379: iastore
    //   7380: dup
    //   7381: bipush #9
    //   7383: ldc 268697600
    //   7385: iastore
    //   7386: dup
    //   7387: bipush #10
    //   7389: ldc 268701760
    //   7391: iastore
    //   7392: dup
    //   7393: bipush #11
    //   7395: ldc 266240
    //   7397: iastore
    //   7398: dup
    //   7399: bipush #12
    //   7401: ldc 268701696
    //   7403: iastore
    //   7404: dup
    //   7405: bipush #13
    //   7407: ldc 266304
    //   7409: iastore
    //   7410: dup
    //   7411: bipush #14
    //   7413: sipush #4096
    //   7416: iastore
    //   7417: dup
    //   7418: bipush #15
    //   7420: bipush #64
    //   7422: iastore
    //   7423: dup
    //   7424: bipush #16
    //   7426: ldc 268697600
    //   7428: iastore
    //   7429: dup
    //   7430: bipush #17
    //   7432: ldc 268435520
    //   7434: iastore
    //   7435: dup
    //   7436: bipush #18
    //   7438: ldc 268439552
    //   7440: iastore
    //   7441: dup
    //   7442: bipush #19
    //   7444: sipush #4160
    //   7447: iastore
    //   7448: dup
    //   7449: bipush #20
    //   7451: ldc 266240
    //   7453: iastore
    //   7454: dup
    //   7455: bipush #21
    //   7457: ldc 262208
    //   7459: iastore
    //   7460: dup
    //   7461: bipush #22
    //   7463: ldc 268697664
    //   7465: iastore
    //   7466: dup
    //   7467: bipush #23
    //   7469: ldc 268701696
    //   7471: iastore
    //   7472: dup
    //   7473: bipush #24
    //   7475: sipush #4160
    //   7478: iastore
    //   7479: dup
    //   7480: bipush #25
    //   7482: iconst_0
    //   7483: iastore
    //   7484: dup
    //   7485: bipush #26
    //   7487: iconst_0
    //   7488: iastore
    //   7489: dup
    //   7490: bipush #27
    //   7492: ldc 268697664
    //   7494: iastore
    //   7495: dup
    //   7496: bipush #28
    //   7498: ldc 268435520
    //   7500: iastore
    //   7501: dup
    //   7502: bipush #29
    //   7504: ldc 268439552
    //   7506: iastore
    //   7507: dup
    //   7508: bipush #30
    //   7510: ldc 266304
    //   7512: iastore
    //   7513: dup
    //   7514: bipush #31
    //   7516: ldc 262144
    //   7518: iastore
    //   7519: dup
    //   7520: bipush #32
    //   7522: ldc 266304
    //   7524: iastore
    //   7525: dup
    //   7526: bipush #33
    //   7528: ldc 262144
    //   7530: iastore
    //   7531: dup
    //   7532: bipush #34
    //   7534: ldc 268701696
    //   7536: iastore
    //   7537: dup
    //   7538: bipush #35
    //   7540: sipush #4096
    //   7543: iastore
    //   7544: dup
    //   7545: bipush #36
    //   7547: bipush #64
    //   7549: iastore
    //   7550: dup
    //   7551: bipush #37
    //   7553: ldc 268697664
    //   7555: iastore
    //   7556: dup
    //   7557: bipush #38
    //   7559: sipush #4096
    //   7562: iastore
    //   7563: dup
    //   7564: bipush #39
    //   7566: ldc 266304
    //   7568: iastore
    //   7569: dup
    //   7570: bipush #40
    //   7572: ldc 268439552
    //   7574: iastore
    //   7575: dup
    //   7576: bipush #41
    //   7578: bipush #64
    //   7580: iastore
    //   7581: dup
    //   7582: bipush #42
    //   7584: ldc 268435520
    //   7586: iastore
    //   7587: dup
    //   7588: bipush #43
    //   7590: ldc 268697600
    //   7592: iastore
    //   7593: dup
    //   7594: bipush #44
    //   7596: ldc 268697664
    //   7598: iastore
    //   7599: dup
    //   7600: bipush #45
    //   7602: ldc 268435456
    //   7604: iastore
    //   7605: dup
    //   7606: bipush #46
    //   7608: ldc 262144
    //   7610: iastore
    //   7611: dup
    //   7612: bipush #47
    //   7614: ldc 268439616
    //   7616: iastore
    //   7617: dup
    //   7618: bipush #48
    //   7620: iconst_0
    //   7621: iastore
    //   7622: dup
    //   7623: bipush #49
    //   7625: ldc 268701760
    //   7627: iastore
    //   7628: dup
    //   7629: bipush #50
    //   7631: ldc 262208
    //   7633: iastore
    //   7634: dup
    //   7635: bipush #51
    //   7637: ldc 268435520
    //   7639: iastore
    //   7640: dup
    //   7641: bipush #52
    //   7643: ldc 268697600
    //   7645: iastore
    //   7646: dup
    //   7647: bipush #53
    //   7649: ldc 268439552
    //   7651: iastore
    //   7652: dup
    //   7653: bipush #54
    //   7655: ldc 268439616
    //   7657: iastore
    //   7658: dup
    //   7659: bipush #55
    //   7661: iconst_0
    //   7662: iastore
    //   7663: dup
    //   7664: bipush #56
    //   7666: ldc 268701760
    //   7668: iastore
    //   7669: dup
    //   7670: bipush #57
    //   7672: ldc 266240
    //   7674: iastore
    //   7675: dup
    //   7676: bipush #58
    //   7678: ldc 266240
    //   7680: iastore
    //   7681: dup
    //   7682: bipush #59
    //   7684: sipush #4160
    //   7687: iastore
    //   7688: dup
    //   7689: bipush #60
    //   7691: sipush #4160
    //   7694: iastore
    //   7695: dup
    //   7696: bipush #61
    //   7698: ldc 262208
    //   7700: iastore
    //   7701: dup
    //   7702: bipush #62
    //   7704: ldc 268435456
    //   7706: iastore
    //   7707: dup
    //   7708: bipush #63
    //   7710: ldc 268701696
    //   7712: iastore
    //   7713: astore #15
    //   7715: aload_3
    //   7716: arraylength
    //   7717: istore #16
    //   7719: iconst_2
    //   7720: newarray int
    //   7722: astore #17
    //   7724: iload #16
    //   7726: newarray byte
    //   7728: astore #4
    //   7730: iload #16
    //   7732: bipush #8
    //   7734: idiv
    //   7735: istore #18
    //   7737: iconst_0
    //   7738: istore #19
    //   7740: iload #19
    //   7742: iload #18
    //   7744: if_icmpge -> 8658
    //   7747: iload #19
    //   7749: bipush #8
    //   7751: imul
    //   7752: istore #20
    //   7754: iconst_0
    //   7755: istore #21
    //   7757: iload #21
    //   7759: iconst_2
    //   7760: if_icmpge -> 7845
    //   7763: aload #17
    //   7765: iload #21
    //   7767: aload_3
    //   7768: iload #20
    //   7770: iload #21
    //   7772: iconst_4
    //   7773: imul
    //   7774: iadd
    //   7775: baload
    //   7776: sipush #255
    //   7779: iand
    //   7780: bipush #24
    //   7782: ishl
    //   7783: aload_3
    //   7784: iload #20
    //   7786: iload #21
    //   7788: iconst_4
    //   7789: imul
    //   7790: iadd
    //   7791: iconst_1
    //   7792: iadd
    //   7793: baload
    //   7794: sipush #255
    //   7797: iand
    //   7798: bipush #16
    //   7800: ishl
    //   7801: ior
    //   7802: aload_3
    //   7803: iload #20
    //   7805: iload #21
    //   7807: iconst_4
    //   7808: imul
    //   7809: iadd
    //   7810: iconst_2
    //   7811: iadd
    //   7812: baload
    //   7813: sipush #255
    //   7816: iand
    //   7817: bipush #8
    //   7819: ishl
    //   7820: ior
    //   7821: aload_3
    //   7822: iload #20
    //   7824: iload #21
    //   7826: iconst_4
    //   7827: imul
    //   7828: iadd
    //   7829: iconst_3
    //   7830: iadd
    //   7831: baload
    //   7832: sipush #255
    //   7835: iand
    //   7836: ior
    //   7837: iastore
    //   7838: iinc #21, 1
    //   7841: iload_2
    //   7842: ifne -> 7757
    //   7845: iconst_0
    //   7846: istore #26
    //   7848: aload #17
    //   7850: iconst_0
    //   7851: iaload
    //   7852: istore #24
    //   7854: aload #17
    //   7856: iconst_1
    //   7857: iaload
    //   7858: istore #23
    //   7860: iload #24
    //   7862: iconst_4
    //   7863: iushr
    //   7864: iload #23
    //   7866: ixor
    //   7867: ldc 252645135
    //   7869: iand
    //   7870: istore #22
    //   7872: iload #23
    //   7874: iload #22
    //   7876: ixor
    //   7877: istore #23
    //   7879: iload #24
    //   7881: iload #22
    //   7883: iconst_4
    //   7884: ishl
    //   7885: ixor
    //   7886: istore #24
    //   7888: iload #24
    //   7890: bipush #16
    //   7892: iushr
    //   7893: iload #23
    //   7895: ixor
    //   7896: ldc 65535
    //   7898: iand
    //   7899: istore #22
    //   7901: iload #23
    //   7903: iload #22
    //   7905: ixor
    //   7906: istore #23
    //   7908: iload #24
    //   7910: iload #22
    //   7912: bipush #16
    //   7914: ishl
    //   7915: ixor
    //   7916: istore #24
    //   7918: iload #23
    //   7920: iconst_2
    //   7921: iushr
    //   7922: iload #24
    //   7924: ixor
    //   7925: ldc 858993459
    //   7927: iand
    //   7928: istore #22
    //   7930: iload #24
    //   7932: iload #22
    //   7934: ixor
    //   7935: istore #24
    //   7937: iload #23
    //   7939: iload #22
    //   7941: iconst_2
    //   7942: ishl
    //   7943: ixor
    //   7944: istore #23
    //   7946: iload #23
    //   7948: bipush #8
    //   7950: iushr
    //   7951: iload #24
    //   7953: ixor
    //   7954: ldc 16711935
    //   7956: iand
    //   7957: istore #22
    //   7959: iload #24
    //   7961: iload #22
    //   7963: ixor
    //   7964: istore #24
    //   7966: iload #23
    //   7968: iload #22
    //   7970: bipush #8
    //   7972: ishl
    //   7973: ixor
    //   7974: istore #23
    //   7976: iload #23
    //   7978: iconst_1
    //   7979: ishl
    //   7980: iload #23
    //   7982: bipush #31
    //   7984: iushr
    //   7985: iconst_1
    //   7986: iand
    //   7987: ior
    //   7988: istore #23
    //   7990: iload #24
    //   7992: iload #23
    //   7994: ixor
    //   7995: ldc -1431655766
    //   7997: iand
    //   7998: istore #22
    //   8000: iload #24
    //   8002: iload #22
    //   8004: ixor
    //   8005: istore #24
    //   8007: iload #23
    //   8009: iload #22
    //   8011: ixor
    //   8012: istore #23
    //   8014: iload #24
    //   8016: iconst_1
    //   8017: ishl
    //   8018: iload #24
    //   8020: bipush #31
    //   8022: iushr
    //   8023: iconst_1
    //   8024: iand
    //   8025: ior
    //   8026: istore #24
    //   8028: iconst_0
    //   8029: istore #25
    //   8031: iload #25
    //   8033: bipush #8
    //   8035: if_icmpge -> 8373
    //   8038: iload #23
    //   8040: bipush #28
    //   8042: ishl
    //   8043: iload #23
    //   8045: iconst_4
    //   8046: iushr
    //   8047: ior
    //   8048: istore #22
    //   8050: iload #22
    //   8052: aload #5
    //   8054: iload #26
    //   8056: iinc #26, 1
    //   8059: iaload
    //   8060: ixor
    //   8061: istore #22
    //   8063: aload #14
    //   8065: iload #22
    //   8067: bipush #63
    //   8069: iand
    //   8070: iaload
    //   8071: istore #21
    //   8073: iload #21
    //   8075: aload #12
    //   8077: iload #22
    //   8079: bipush #8
    //   8081: iushr
    //   8082: bipush #63
    //   8084: iand
    //   8085: iaload
    //   8086: ior
    //   8087: istore #21
    //   8089: iload #21
    //   8091: aload #10
    //   8093: iload #22
    //   8095: bipush #16
    //   8097: iushr
    //   8098: bipush #63
    //   8100: iand
    //   8101: iaload
    //   8102: ior
    //   8103: istore #21
    //   8105: iload #21
    //   8107: aload #8
    //   8109: iload #22
    //   8111: bipush #24
    //   8113: iushr
    //   8114: bipush #63
    //   8116: iand
    //   8117: iaload
    //   8118: ior
    //   8119: istore #21
    //   8121: iload #23
    //   8123: aload #5
    //   8125: iload #26
    //   8127: iinc #26, 1
    //   8130: iaload
    //   8131: ixor
    //   8132: istore #22
    //   8134: iload #21
    //   8136: aload #15
    //   8138: iload #22
    //   8140: bipush #63
    //   8142: iand
    //   8143: iaload
    //   8144: ior
    //   8145: istore #21
    //   8147: iload #21
    //   8149: aload #13
    //   8151: iload #22
    //   8153: bipush #8
    //   8155: iushr
    //   8156: bipush #63
    //   8158: iand
    //   8159: iaload
    //   8160: ior
    //   8161: istore #21
    //   8163: iload #21
    //   8165: aload #11
    //   8167: iload #22
    //   8169: bipush #16
    //   8171: iushr
    //   8172: bipush #63
    //   8174: iand
    //   8175: iaload
    //   8176: ior
    //   8177: istore #21
    //   8179: iload #21
    //   8181: aload #9
    //   8183: iload #22
    //   8185: bipush #24
    //   8187: iushr
    //   8188: bipush #63
    //   8190: iand
    //   8191: iaload
    //   8192: ior
    //   8193: istore #21
    //   8195: iload #24
    //   8197: iload #21
    //   8199: ixor
    //   8200: istore #24
    //   8202: iload #24
    //   8204: bipush #28
    //   8206: ishl
    //   8207: iload #24
    //   8209: iconst_4
    //   8210: iushr
    //   8211: ior
    //   8212: istore #22
    //   8214: iload #22
    //   8216: aload #5
    //   8218: iload #26
    //   8220: iinc #26, 1
    //   8223: iaload
    //   8224: ixor
    //   8225: istore #22
    //   8227: aload #14
    //   8229: iload #22
    //   8231: bipush #63
    //   8233: iand
    //   8234: iaload
    //   8235: istore #21
    //   8237: iload #21
    //   8239: aload #12
    //   8241: iload #22
    //   8243: bipush #8
    //   8245: iushr
    //   8246: bipush #63
    //   8248: iand
    //   8249: iaload
    //   8250: ior
    //   8251: istore #21
    //   8253: iload #21
    //   8255: aload #10
    //   8257: iload #22
    //   8259: bipush #16
    //   8261: iushr
    //   8262: bipush #63
    //   8264: iand
    //   8265: iaload
    //   8266: ior
    //   8267: istore #21
    //   8269: iload #21
    //   8271: aload #8
    //   8273: iload #22
    //   8275: bipush #24
    //   8277: iushr
    //   8278: bipush #63
    //   8280: iand
    //   8281: iaload
    //   8282: ior
    //   8283: istore #21
    //   8285: iload #24
    //   8287: aload #5
    //   8289: iload #26
    //   8291: iinc #26, 1
    //   8294: iaload
    //   8295: ixor
    //   8296: istore #22
    //   8298: iload #21
    //   8300: aload #15
    //   8302: iload #22
    //   8304: bipush #63
    //   8306: iand
    //   8307: iaload
    //   8308: ior
    //   8309: istore #21
    //   8311: iload #21
    //   8313: aload #13
    //   8315: iload #22
    //   8317: bipush #8
    //   8319: iushr
    //   8320: bipush #63
    //   8322: iand
    //   8323: iaload
    //   8324: ior
    //   8325: istore #21
    //   8327: iload #21
    //   8329: aload #11
    //   8331: iload #22
    //   8333: bipush #16
    //   8335: iushr
    //   8336: bipush #63
    //   8338: iand
    //   8339: iaload
    //   8340: ior
    //   8341: istore #21
    //   8343: iload #21
    //   8345: aload #9
    //   8347: iload #22
    //   8349: bipush #24
    //   8351: iushr
    //   8352: bipush #63
    //   8354: iand
    //   8355: iaload
    //   8356: ior
    //   8357: istore #21
    //   8359: iload #23
    //   8361: iload #21
    //   8363: ixor
    //   8364: istore #23
    //   8366: iinc #25, 1
    //   8369: iload_2
    //   8370: ifne -> 8031
    //   8373: iload #23
    //   8375: bipush #31
    //   8377: ishl
    //   8378: iload #23
    //   8380: iconst_1
    //   8381: iushr
    //   8382: ior
    //   8383: istore #23
    //   8385: iload #24
    //   8387: iload #23
    //   8389: ixor
    //   8390: ldc -1431655766
    //   8392: iand
    //   8393: istore #22
    //   8395: iload #24
    //   8397: iload #22
    //   8399: ixor
    //   8400: istore #24
    //   8402: iload #23
    //   8404: iload #22
    //   8406: ixor
    //   8407: istore #23
    //   8409: iload #24
    //   8411: bipush #31
    //   8413: ishl
    //   8414: iload #24
    //   8416: iconst_1
    //   8417: iushr
    //   8418: ior
    //   8419: istore #24
    //   8421: iload #24
    //   8423: bipush #8
    //   8425: iushr
    //   8426: iload #23
    //   8428: ixor
    //   8429: ldc 16711935
    //   8431: iand
    //   8432: istore #22
    //   8434: iload #23
    //   8436: iload #22
    //   8438: ixor
    //   8439: istore #23
    //   8441: iload #24
    //   8443: iload #22
    //   8445: bipush #8
    //   8447: ishl
    //   8448: ixor
    //   8449: istore #24
    //   8451: iload #24
    //   8453: iconst_2
    //   8454: iushr
    //   8455: iload #23
    //   8457: ixor
    //   8458: ldc 858993459
    //   8460: iand
    //   8461: istore #22
    //   8463: iload #23
    //   8465: iload #22
    //   8467: ixor
    //   8468: istore #23
    //   8470: iload #24
    //   8472: iload #22
    //   8474: iconst_2
    //   8475: ishl
    //   8476: ixor
    //   8477: istore #24
    //   8479: iload #23
    //   8481: bipush #16
    //   8483: iushr
    //   8484: iload #24
    //   8486: ixor
    //   8487: ldc 65535
    //   8489: iand
    //   8490: istore #22
    //   8492: iload #24
    //   8494: iload #22
    //   8496: ixor
    //   8497: istore #24
    //   8499: iload #23
    //   8501: iload #22
    //   8503: bipush #16
    //   8505: ishl
    //   8506: ixor
    //   8507: istore #23
    //   8509: iload #23
    //   8511: iconst_4
    //   8512: iushr
    //   8513: iload #24
    //   8515: ixor
    //   8516: ldc 252645135
    //   8518: iand
    //   8519: istore #22
    //   8521: iload #24
    //   8523: iload #22
    //   8525: ixor
    //   8526: istore #24
    //   8528: iload #23
    //   8530: iload #22
    //   8532: iconst_4
    //   8533: ishl
    //   8534: ixor
    //   8535: istore #23
    //   8537: aload #17
    //   8539: iconst_0
    //   8540: iload #23
    //   8542: iastore
    //   8543: aload #17
    //   8545: iconst_1
    //   8546: iload #24
    //   8548: iastore
    //   8549: iload #19
    //   8551: bipush #8
    //   8553: imul
    //   8554: istore #27
    //   8556: iconst_0
    //   8557: istore #28
    //   8559: iload #28
    //   8561: iconst_2
    //   8562: if_icmpge -> 8651
    //   8565: aload #4
    //   8567: iload #27
    //   8569: iload #28
    //   8571: iconst_4
    //   8572: imul
    //   8573: iadd
    //   8574: aload #17
    //   8576: iload #28
    //   8578: iaload
    //   8579: bipush #24
    //   8581: iushr
    //   8582: i2b
    //   8583: bastore
    //   8584: aload #4
    //   8586: iload #27
    //   8588: iload #28
    //   8590: iconst_4
    //   8591: imul
    //   8592: iadd
    //   8593: iconst_1
    //   8594: iadd
    //   8595: aload #17
    //   8597: iload #28
    //   8599: iaload
    //   8600: bipush #16
    //   8602: iushr
    //   8603: i2b
    //   8604: bastore
    //   8605: aload #4
    //   8607: iload #27
    //   8609: iload #28
    //   8611: iconst_4
    //   8612: imul
    //   8613: iadd
    //   8614: iconst_2
    //   8615: iadd
    //   8616: aload #17
    //   8618: iload #28
    //   8620: iaload
    //   8621: bipush #8
    //   8623: iushr
    //   8624: i2b
    //   8625: bastore
    //   8626: aload #4
    //   8628: iload #27
    //   8630: iload #28
    //   8632: iconst_4
    //   8633: imul
    //   8634: iadd
    //   8635: iconst_3
    //   8636: iadd
    //   8637: aload #17
    //   8639: iload #28
    //   8641: iaload
    //   8642: i2b
    //   8643: bastore
    //   8644: iinc #28, 1
    //   8647: iload_2
    //   8648: ifne -> 8559
    //   8651: iinc #19, 1
    //   8654: iload_2
    //   8655: ifne -> 7740
    //   8658: new java/math/BigInteger
    //   8661: dup
    //   8662: aload #4
    //   8664: invokespecial <init> : ([B)V
    //   8667: invokevirtual abs : ()Ljava/math/BigInteger;
    //   8670: putstatic burp/Zmhi.ZZ : Ljava/lang/Object;
    //   8673: sipush #6008
    //   8676: sipush #20953
    //   8679: invokestatic a : (II)Ljava/lang/String;
    //   8682: iconst_1
    //   8683: ldc burp/Zgmo
    //   8685: invokevirtual getClassLoader : ()Ljava/lang/ClassLoader;
    //   8688: invokestatic forName : (Ljava/lang/String;ZLjava/lang/ClassLoader;)Ljava/lang/Class;
    //   8691: invokevirtual getDeclaredFields : ()[Ljava/lang/reflect/Field;
    //   8694: astore_3
    //   8695: aload_3
    //   8696: arraylength
    //   8697: istore #4
    //   8699: iconst_0
    //   8700: istore #5
    //   8702: iload #5
    //   8704: iload #4
    //   8706: if_icmpge -> 8843
    //   8709: aload_3
    //   8710: iload #5
    //   8712: aaload
    //   8713: astore #6
    //   8715: aload #6
    //   8717: invokevirtual getModifiers : ()I
    //   8720: invokestatic isStatic : (I)Z
    //   8723: ifne -> 8733
    //   8726: goto -> 8836
    //   8729: invokestatic a : (Ljava/lang/Throwable;)Ljava/lang/Throwable;
    //   8732: athrow
    //   8733: aload #6
    //   8735: invokevirtual getType : ()Ljava/lang/Class;
    //   8738: astore #7
    //   8740: aload #7
    //   8742: ifnull -> 8823
    //   8745: aload #7
    //   8747: invokevirtual isPrimitive : ()Z
    //   8750: ifne -> 8823
    //   8753: goto -> 8760
    //   8756: invokestatic a : (Ljava/lang/Throwable;)Ljava/lang/Throwable;
    //   8759: athrow
    //   8760: aload #7
    //   8762: invokevirtual getPackage : ()Ljava/lang/Package;
    //   8765: ifnull -> 8823
    //   8768: goto -> 8775
    //   8771: invokestatic a : (Ljava/lang/Throwable;)Ljava/lang/Throwable;
    //   8774: athrow
    //   8775: aload #7
    //   8777: invokevirtual getPackage : ()Ljava/lang/Package;
    //   8780: invokevirtual getName : ()Ljava/lang/String;
    //   8783: ifnull -> 8823
    //   8786: goto -> 8793
    //   8789: invokestatic a : (Ljava/lang/Throwable;)Ljava/lang/Throwable;
    //   8792: athrow
    //   8793: aload #7
    //   8795: invokevirtual getPackage : ()Ljava/lang/Package;
    //   8798: invokevirtual getName : ()Ljava/lang/String;
    //   8801: sipush #6000
    //   8804: sipush #28210
    //   8807: invokestatic a : (II)Ljava/lang/String;
    //   8810: invokevirtual startsWith : (Ljava/lang/String;)Z
    //   8813: ifne -> 8823
    //   8816: goto -> 8823
    //   8819: invokestatic a : (Ljava/lang/Throwable;)Ljava/lang/Throwable;
    //   8822: athrow
    //   8823: aload #6
    //   8825: iconst_1
    //   8826: invokevirtual setAccessible : (Z)V
    //   8829: aload #6
    //   8831: aconst_null
    //   8832: invokevirtual get : (Ljava/lang/Object;)Ljava/lang/Object;
    //   8835: pop
    //   8836: iinc #5, 1
    //   8839: iload_2
    //   8840: ifne -> 8702
    //   8843: sipush #6007
    //   8846: sipush #2032
    //   8849: invokestatic a : (II)Ljava/lang/String;
    //   8852: invokestatic forName : (Ljava/lang/String;)Ljava/lang/Class;
    //   8855: invokevirtual getDeclaredMethods : ()[Ljava/lang/reflect/Method;
    //   8858: astore_3
    //   8859: aload_3
    //   8860: arraylength
    //   8861: istore #4
    //   8863: iconst_0
    //   8864: istore #5
    //   8866: iload #5
    //   8868: iload #4
    //   8870: if_icmpge -> 9002
    //   8873: aload_3
    //   8874: iload #5
    //   8876: aaload
    //   8877: astore #6
    //   8879: aload #6
    //   8881: invokevirtual getParameterTypes : ()[Ljava/lang/Class;
    //   8884: pop
    //   8885: aload #6
    //   8887: invokevirtual getModifiers : ()I
    //   8890: invokestatic isStatic : (I)Z
    //   8893: ifeq -> 8988
    //   8896: aload #6
    //   8898: invokevirtual getParameterTypes : ()[Ljava/lang/Class;
    //   8901: arraylength
    //   8902: iconst_2
    //   8903: if_icmpne -> 8988
    //   8906: goto -> 8913
    //   8909: invokestatic a : (Ljava/lang/Throwable;)Ljava/lang/Throwable;
    //   8912: athrow
    //   8913: aload #6
    //   8915: invokevirtual getReturnType : ()Ljava/lang/Class;
    //   8918: getstatic java/lang/Void.TYPE : Ljava/lang/Class;
    //   8921: invokevirtual equals : (Ljava/lang/Object;)Z
    //   8924: ifeq -> 8988
    //   8927: goto -> 8934
    //   8930: invokestatic a : (Ljava/lang/Throwable;)Ljava/lang/Throwable;
    //   8933: athrow
    //   8934: aload #6
    //   8936: iconst_1
    //   8937: invokevirtual setAccessible : (Z)V
    //   8940: aload #6
    //   8942: aconst_null
    //   8943: iconst_2
    //   8944: anewarray java/lang/Object
    //   8947: dup
    //   8948: iconst_0
    //   8949: aload_0
    //   8950: aastore
    //   8951: dup
    //   8952: iconst_1
    //   8953: aload_1
    //   8954: ifnonnull -> 8972
    //   8957: goto -> 8964
    //   8960: invokestatic a : (Ljava/lang/Throwable;)Ljava/lang/Throwable;
    //   8963: athrow
    //   8964: aload_1
    //   8965: goto -> 8979
    //   8968: invokestatic a : (Ljava/lang/Throwable;)Ljava/lang/Throwable;
    //   8971: athrow
    //   8972: aload_1
    //   8973: checkcast [B
    //   8976: invokevirtual clone : ()Ljava/lang/Object;
    //   8979: aastore
    //   8980: invokevirtual invoke : (Ljava/lang/Object;[Ljava/lang/Object;)Ljava/lang/Object;
    //   8983: pop
    //   8984: iload_2
    //   8985: ifne -> 9002
    //   8988: iinc #5, 1
    //   8991: iload_2
    //   8992: ifne -> 8866
    //   8995: goto -> 9002
    //   8998: invokestatic a : (Ljava/lang/Throwable;)Ljava/lang/Throwable;
    //   9001: athrow
    //   9002: getstatic burp/Zz20.ZN : Ljava/lang/Object;
    //   9005: checkcast java/math/BigInteger
    //   9008: invokevirtual toByteArray : ()[B
    //   9011: astore_3
    //   9012: bipush #32
    //   9014: newarray int
    //   9016: dup
    //   9017: iconst_0
    //   9018: ldc 876216579
    //   9020: iastore
    //   9021: dup
    //   9022: iconst_1
    //   9023: ldc 455999525
    //   9025: iastore
    //   9026: dup
    //   9027: iconst_2
    //   9028: ldc 1043334948
    //   9030: iastore
    //   9031: dup
    //   9032: iconst_3
    //   9033: ldc 439222784
    //   9035: iastore
    //   9036: dup
    //   9037: iconst_4
    //   9038: ldc 372376604
    //   9040: iastore
    //   9041: dup
    //   9042: iconst_5
    //   9043: ldc 707731490
    //   9045: iastore
    //   9046: dup
    //   9047: bipush #6
    //   9049: ldc 389426184
    //   9051: iastore
    //   9052: dup
    //   9053: bipush #7
    //   9055: ldc 973875457
    //   9057: iastore
    //   9058: dup
    //   9059: bipush #8
    //   9061: ldc 389160971
    //   9063: iastore
    //   9064: dup
    //   9065: bipush #9
    //   9067: ldc 907870729
    //   9069: iastore
    //   9070: dup
    //   9071: bipush #10
    //   9073: ldc 121057538
    //   9075: iastore
    //   9076: dup
    //   9077: bipush #11
    //   9079: ldc 840500228
    //   9081: iastore
    //   9082: dup
    //   9083: bipush #12
    //   9085: ldc 254150144
    //   9087: iastore
    //   9088: dup
    //   9089: bipush #13
    //   9091: ldc 924386310
    //   9093: iastore
    //   9094: dup
    //   9095: bipush #14
    //   9097: ldc 187632156
    //   9099: iastore
    //   9100: dup
    //   9101: bipush #15
    //   9103: ldc 874189824
    //   9105: iastore
    //   9106: dup
    //   9107: bipush #16
    //   9109: ldc 655302664
    //   9111: iastore
    //   9112: dup
    //   9113: bipush #17
    //   9115: ldc 890966315
    //   9117: iastore
    //   9118: dup
    //   9119: bipush #18
    //   9121: ldc 722417666
    //   9123: iastore
    //   9124: dup
    //   9125: bipush #19
    //   9127: ldc 1026621720
    //   9129: iastore
    //   9130: dup
    //   9131: bipush #20
    //   9133: ldc 957157408
    //   9135: iastore
    //   9136: dup
    //   9137: bipush #21
    //   9139: ldc 892536332
    //   9141: iastore
    //   9142: dup
    //   9143: bipush #22
    //   9145: ldc 689771012
    //   9147: iastore
    //   9148: dup
    //   9149: bipush #23
    //   9151: ldc 221709344
    //   9153: iastore
    //   9154: dup
    //   9155: bipush #24
    //   9157: ldc 940377620
    //   9159: iastore
    //   9160: dup
    //   9161: bipush #25
    //   9163: ldc 255209728
    //   9165: iastore
    //   9166: dup
    //   9167: bipush #26
    //   9169: ldc 1010368540
    //   9171: iastore
    //   9172: dup
    //   9173: bipush #27
    //   9175: ldc 220604441
    //   9177: iastore
    //   9178: dup
    //   9179: bipush #28
    //   9181: ldc 1008414755
    //   9183: iastore
    //   9184: dup
    //   9185: bipush #29
    //   9187: ldc 187049985
    //   9189: iastore
    //   9190: dup
    //   9191: bipush #30
    //   9193: ldc 943331329
    //   9195: iastore
    //   9196: dup
    //   9197: bipush #31
    //   9199: ldc 170788368
    //   9201: iastore
    //   9202: astore #5
    //   9204: bipush #64
    //   9206: newarray int
    //   9208: dup
    //   9209: iconst_0
    //   9210: ldc 16843776
    //   9212: iastore
    //   9213: dup
    //   9214: iconst_1
    //   9215: iconst_0
    //   9216: iastore
    //   9217: dup
    //   9218: iconst_2
    //   9219: ldc 65536
    //   9221: iastore
    //   9222: dup
    //   9223: iconst_3
    //   9224: ldc 16843780
    //   9226: iastore
    //   9227: dup
    //   9228: iconst_4
    //   9229: ldc 16842756
    //   9231: iastore
    //   9232: dup
    //   9233: iconst_5
    //   9234: ldc 66564
    //   9236: iastore
    //   9237: dup
    //   9238: bipush #6
    //   9240: iconst_4
    //   9241: iastore
    //   9242: dup
    //   9243: bipush #7
    //   9245: ldc 65536
    //   9247: iastore
    //   9248: dup
    //   9249: bipush #8
    //   9251: sipush #1024
    //   9254: iastore
    //   9255: dup
    //   9256: bipush #9
    //   9258: ldc 16843776
    //   9260: iastore
    //   9261: dup
    //   9262: bipush #10
    //   9264: ldc 16843780
    //   9266: iastore
    //   9267: dup
    //   9268: bipush #11
    //   9270: sipush #1024
    //   9273: iastore
    //   9274: dup
    //   9275: bipush #12
    //   9277: ldc 16778244
    //   9279: iastore
    //   9280: dup
    //   9281: bipush #13
    //   9283: ldc 16842756
    //   9285: iastore
    //   9286: dup
    //   9287: bipush #14
    //   9289: ldc 16777216
    //   9291: iastore
    //   9292: dup
    //   9293: bipush #15
    //   9295: iconst_4
    //   9296: iastore
    //   9297: dup
    //   9298: bipush #16
    //   9300: sipush #1028
    //   9303: iastore
    //   9304: dup
    //   9305: bipush #17
    //   9307: ldc 16778240
    //   9309: iastore
    //   9310: dup
    //   9311: bipush #18
    //   9313: ldc 16778240
    //   9315: iastore
    //   9316: dup
    //   9317: bipush #19
    //   9319: ldc 66560
    //   9321: iastore
    //   9322: dup
    //   9323: bipush #20
    //   9325: ldc 66560
    //   9327: iastore
    //   9328: dup
    //   9329: bipush #21
    //   9331: ldc 16842752
    //   9333: iastore
    //   9334: dup
    //   9335: bipush #22
    //   9337: ldc 16842752
    //   9339: iastore
    //   9340: dup
    //   9341: bipush #23
    //   9343: ldc 16778244
    //   9345: iastore
    //   9346: dup
    //   9347: bipush #24
    //   9349: ldc 65540
    //   9351: iastore
    //   9352: dup
    //   9353: bipush #25
    //   9355: ldc 16777220
    //   9357: iastore
    //   9358: dup
    //   9359: bipush #26
    //   9361: ldc 16777220
    //   9363: iastore
    //   9364: dup
    //   9365: bipush #27
    //   9367: ldc 65540
    //   9369: iastore
    //   9370: dup
    //   9371: bipush #28
    //   9373: iconst_0
    //   9374: iastore
    //   9375: dup
    //   9376: bipush #29
    //   9378: sipush #1028
    //   9381: iastore
    //   9382: dup
    //   9383: bipush #30
    //   9385: ldc 66564
    //   9387: iastore
    //   9388: dup
    //   9389: bipush #31
    //   9391: ldc 16777216
    //   9393: iastore
    //   9394: dup
    //   9395: bipush #32
    //   9397: ldc 65536
    //   9399: iastore
    //   9400: dup
    //   9401: bipush #33
    //   9403: ldc 16843780
    //   9405: iastore
    //   9406: dup
    //   9407: bipush #34
    //   9409: iconst_4
    //   9410: iastore
    //   9411: dup
    //   9412: bipush #35
    //   9414: ldc 16842752
    //   9416: iastore
    //   9417: dup
    //   9418: bipush #36
    //   9420: ldc 16843776
    //   9422: iastore
    //   9423: dup
    //   9424: bipush #37
    //   9426: ldc 16777216
    //   9428: iastore
    //   9429: dup
    //   9430: bipush #38
    //   9432: ldc 16777216
    //   9434: iastore
    //   9435: dup
    //   9436: bipush #39
    //   9438: sipush #1024
    //   9441: iastore
    //   9442: dup
    //   9443: bipush #40
    //   9445: ldc 16842756
    //   9447: iastore
    //   9448: dup
    //   9449: bipush #41
    //   9451: ldc 65536
    //   9453: iastore
    //   9454: dup
    //   9455: bipush #42
    //   9457: ldc 66560
    //   9459: iastore
    //   9460: dup
    //   9461: bipush #43
    //   9463: ldc 16777220
    //   9465: iastore
    //   9466: dup
    //   9467: bipush #44
    //   9469: sipush #1024
    //   9472: iastore
    //   9473: dup
    //   9474: bipush #45
    //   9476: iconst_4
    //   9477: iastore
    //   9478: dup
    //   9479: bipush #46
    //   9481: ldc 16778244
    //   9483: iastore
    //   9484: dup
    //   9485: bipush #47
    //   9487: ldc 66564
    //   9489: iastore
    //   9490: dup
    //   9491: bipush #48
    //   9493: ldc 16843780
    //   9495: iastore
    //   9496: dup
    //   9497: bipush #49
    //   9499: ldc 65540
    //   9501: iastore
    //   9502: dup
    //   9503: bipush #50
    //   9505: ldc 16842752
    //   9507: iastore
    //   9508: dup
    //   9509: bipush #51
    //   9511: ldc 16778244
    //   9513: iastore
    //   9514: dup
    //   9515: bipush #52
    //   9517: ldc 16777220
    //   9519: iastore
    //   9520: dup
    //   9521: bipush #53
    //   9523: sipush #1028
    //   9526: iastore
    //   9527: dup
    //   9528: bipush #54
    //   9530: ldc 66564
    //   9532: iastore
    //   9533: dup
    //   9534: bipush #55
    //   9536: ldc 16843776
    //   9538: iastore
    //   9539: dup
    //   9540: bipush #56
    //   9542: sipush #1028
    //   9545: iastore
    //   9546: dup
    //   9547: bipush #57
    //   9549: ldc 16778240
    //   9551: iastore
    //   9552: dup
    //   9553: bipush #58
    //   9555: ldc 16778240
    //   9557: iastore
    //   9558: dup
    //   9559: bipush #59
    //   9561: iconst_0
    //   9562: iastore
    //   9563: dup
    //   9564: bipush #60
    //   9566: ldc 65540
    //   9568: iastore
    //   9569: dup
    //   9570: bipush #61
    //   9572: ldc 66560
    //   9574: iastore
    //   9575: dup
    //   9576: bipush #62
    //   9578: iconst_0
    //   9579: iastore
    //   9580: dup
    //   9581: bipush #63
    //   9583: ldc 16842756
    //   9585: iastore
    //   9586: astore #6
    //   9588: bipush #64
    //   9590: newarray int
    //   9592: dup
    //   9593: iconst_0
    //   9594: ldc -2146402272
    //   9596: iastore
    //   9597: dup
    //   9598: iconst_1
    //   9599: ldc -2147450880
    //   9601: iastore
    //   9602: dup
    //   9603: iconst_2
    //   9604: ldc 32768
    //   9606: iastore
    //   9607: dup
    //   9608: iconst_3
    //   9609: ldc 1081376
    //   9611: iastore
    //   9612: dup
    //   9613: iconst_4
    //   9614: ldc 1048576
    //   9616: iastore
    //   9617: dup
    //   9618: iconst_5
    //   9619: bipush #32
    //   9621: iastore
    //   9622: dup
    //   9623: bipush #6
    //   9625: ldc -2146435040
    //   9627: iastore
    //   9628: dup
    //   9629: bipush #7
    //   9631: ldc -2147450848
    //   9633: iastore
    //   9634: dup
    //   9635: bipush #8
    //   9637: ldc -2147483616
    //   9639: iastore
    //   9640: dup
    //   9641: bipush #9
    //   9643: ldc -2146402272
    //   9645: iastore
    //   9646: dup
    //   9647: bipush #10
    //   9649: ldc -2146402304
    //   9651: iastore
    //   9652: dup
    //   9653: bipush #11
    //   9655: ldc -2147483648
    //   9657: iastore
    //   9658: dup
    //   9659: bipush #12
    //   9661: ldc -2147450880
    //   9663: iastore
    //   9664: dup
    //   9665: bipush #13
    //   9667: ldc 1048576
    //   9669: iastore
    //   9670: dup
    //   9671: bipush #14
    //   9673: bipush #32
    //   9675: iastore
    //   9676: dup
    //   9677: bipush #15
    //   9679: ldc -2146435040
    //   9681: iastore
    //   9682: dup
    //   9683: bipush #16
    //   9685: ldc 1081344
    //   9687: iastore
    //   9688: dup
    //   9689: bipush #17
    //   9691: ldc 1048608
    //   9693: iastore
    //   9694: dup
    //   9695: bipush #18
    //   9697: ldc -2147450848
    //   9699: iastore
    //   9700: dup
    //   9701: bipush #19
    //   9703: iconst_0
    //   9704: iastore
    //   9705: dup
    //   9706: bipush #20
    //   9708: ldc -2147483648
    //   9710: iastore
    //   9711: dup
    //   9712: bipush #21
    //   9714: ldc 32768
    //   9716: iastore
    //   9717: dup
    //   9718: bipush #22
    //   9720: ldc 1081376
    //   9722: iastore
    //   9723: dup
    //   9724: bipush #23
    //   9726: ldc -2146435072
    //   9728: iastore
    //   9729: dup
    //   9730: bipush #24
    //   9732: ldc 1048608
    //   9734: iastore
    //   9735: dup
    //   9736: bipush #25
    //   9738: ldc -2147483616
    //   9740: iastore
    //   9741: dup
    //   9742: bipush #26
    //   9744: iconst_0
    //   9745: iastore
    //   9746: dup
    //   9747: bipush #27
    //   9749: ldc 1081344
    //   9751: iastore
    //   9752: dup
    //   9753: bipush #28
    //   9755: ldc 32800
    //   9757: iastore
    //   9758: dup
    //   9759: bipush #29
    //   9761: ldc -2146402304
    //   9763: iastore
    //   9764: dup
    //   9765: bipush #30
    //   9767: ldc -2146435072
    //   9769: iastore
    //   9770: dup
    //   9771: bipush #31
    //   9773: ldc 32800
    //   9775: iastore
    //   9776: dup
    //   9777: bipush #32
    //   9779: iconst_0
    //   9780: iastore
    //   9781: dup
    //   9782: bipush #33
    //   9784: ldc 1081376
    //   9786: iastore
    //   9787: dup
    //   9788: bipush #34
    //   9790: ldc -2146435040
    //   9792: iastore
    //   9793: dup
    //   9794: bipush #35
    //   9796: ldc 1048576
    //   9798: iastore
    //   9799: dup
    //   9800: bipush #36
    //   9802: ldc -2147450848
    //   9804: iastore
    //   9805: dup
    //   9806: bipush #37
    //   9808: ldc -2146435072
    //   9810: iastore
    //   9811: dup
    //   9812: bipush #38
    //   9814: ldc -2146402304
    //   9816: iastore
    //   9817: dup
    //   9818: bipush #39
    //   9820: ldc 32768
    //   9822: iastore
    //   9823: dup
    //   9824: bipush #40
    //   9826: ldc -2146435072
    //   9828: iastore
    //   9829: dup
    //   9830: bipush #41
    //   9832: ldc -2147450880
    //   9834: iastore
    //   9835: dup
    //   9836: bipush #42
    //   9838: bipush #32
    //   9840: iastore
    //   9841: dup
    //   9842: bipush #43
    //   9844: ldc -2146402272
    //   9846: iastore
    //   9847: dup
    //   9848: bipush #44
    //   9850: ldc 1081376
    //   9852: iastore
    //   9853: dup
    //   9854: bipush #45
    //   9856: bipush #32
    //   9858: iastore
    //   9859: dup
    //   9860: bipush #46
    //   9862: ldc 32768
    //   9864: iastore
    //   9865: dup
    //   9866: bipush #47
    //   9868: ldc -2147483648
    //   9870: iastore
    //   9871: dup
    //   9872: bipush #48
    //   9874: ldc 32800
    //   9876: iastore
    //   9877: dup
    //   9878: bipush #49
    //   9880: ldc -2146402304
    //   9882: iastore
    //   9883: dup
    //   9884: bipush #50
    //   9886: ldc 1048576
    //   9888: iastore
    //   9889: dup
    //   9890: bipush #51
    //   9892: ldc -2147483616
    //   9894: iastore
    //   9895: dup
    //   9896: bipush #52
    //   9898: ldc 1048608
    //   9900: iastore
    //   9901: dup
    //   9902: bipush #53
    //   9904: ldc -2147450848
    //   9906: iastore
    //   9907: dup
    //   9908: bipush #54
    //   9910: ldc -2147483616
    //   9912: iastore
    //   9913: dup
    //   9914: bipush #55
    //   9916: ldc 1048608
    //   9918: iastore
    //   9919: dup
    //   9920: bipush #56
    //   9922: ldc 1081344
    //   9924: iastore
    //   9925: dup
    //   9926: bipush #57
    //   9928: iconst_0
    //   9929: iastore
    //   9930: dup
    //   9931: bipush #58
    //   9933: ldc -2147450880
    //   9935: iastore
    //   9936: dup
    //   9937: bipush #59
    //   9939: ldc 32800
    //   9941: iastore
    //   9942: dup
    //   9943: bipush #60
    //   9945: ldc -2147483648
    //   9947: iastore
    //   9948: dup
    //   9949: bipush #61
    //   9951: ldc -2146435040
    //   9953: iastore
    //   9954: dup
    //   9955: bipush #62
    //   9957: ldc -2146402272
    //   9959: iastore
    //   9960: dup
    //   9961: bipush #63
    //   9963: ldc 1081344
    //   9965: iastore
    //   9966: astore #7
    //   9968: bipush #64
    //   9970: newarray int
    //   9972: dup
    //   9973: iconst_0
    //   9974: sipush #520
    //   9977: iastore
    //   9978: dup
    //   9979: iconst_1
    //   9980: ldc 134349312
    //   9982: iastore
    //   9983: dup
    //   9984: iconst_2
    //   9985: iconst_0
    //   9986: iastore
    //   9987: dup
    //   9988: iconst_3
    //   9989: ldc 134348808
    //   9991: iastore
    //   9992: dup
    //   9993: iconst_4
    //   9994: ldc 134218240
    //   9996: iastore
    //   9997: dup
    //   9998: iconst_5
    //   9999: iconst_0
    //   10000: iastore
    //   10001: dup
    //   10002: bipush #6
    //   10004: ldc 131592
    //   10006: iastore
    //   10007: dup
    //   10008: bipush #7
    //   10010: ldc 134218240
    //   10012: iastore
    //   10013: dup
    //   10014: bipush #8
    //   10016: ldc 131080
    //   10018: iastore
    //   10019: dup
    //   10020: bipush #9
    //   10022: ldc 134217736
    //   10024: iastore
    //   10025: dup
    //   10026: bipush #10
    //   10028: ldc 134217736
    //   10030: iastore
    //   10031: dup
    //   10032: bipush #11
    //   10034: ldc 131072
    //   10036: iastore
    //   10037: dup
    //   10038: bipush #12
    //   10040: ldc 134349320
    //   10042: iastore
    //   10043: dup
    //   10044: bipush #13
    //   10046: ldc 131080
    //   10048: iastore
    //   10049: dup
    //   10050: bipush #14
    //   10052: ldc 134348800
    //   10054: iastore
    //   10055: dup
    //   10056: bipush #15
    //   10058: sipush #520
    //   10061: iastore
    //   10062: dup
    //   10063: bipush #16
    //   10065: ldc 134217728
    //   10067: iastore
    //   10068: dup
    //   10069: bipush #17
    //   10071: bipush #8
    //   10073: iastore
    //   10074: dup
    //   10075: bipush #18
    //   10077: ldc 134349312
    //   10079: iastore
    //   10080: dup
    //   10081: bipush #19
    //   10083: sipush #512
    //   10086: iastore
    //   10087: dup
    //   10088: bipush #20
    //   10090: ldc 131584
    //   10092: iastore
    //   10093: dup
    //   10094: bipush #21
    //   10096: ldc 134348800
    //   10098: iastore
    //   10099: dup
    //   10100: bipush #22
    //   10102: ldc 134348808
    //   10104: iastore
    //   10105: dup
    //   10106: bipush #23
    //   10108: ldc 131592
    //   10110: iastore
    //   10111: dup
    //   10112: bipush #24
    //   10114: ldc 134218248
    //   10116: iastore
    //   10117: dup
    //   10118: bipush #25
    //   10120: ldc 131584
    //   10122: iastore
    //   10123: dup
    //   10124: bipush #26
    //   10126: ldc 131072
    //   10128: iastore
    //   10129: dup
    //   10130: bipush #27
    //   10132: ldc 134218248
    //   10134: iastore
    //   10135: dup
    //   10136: bipush #28
    //   10138: bipush #8
    //   10140: iastore
    //   10141: dup
    //   10142: bipush #29
    //   10144: ldc 134349320
    //   10146: iastore
    //   10147: dup
    //   10148: bipush #30
    //   10150: sipush #512
    //   10153: iastore
    //   10154: dup
    //   10155: bipush #31
    //   10157: ldc 134217728
    //   10159: iastore
    //   10160: dup
    //   10161: bipush #32
    //   10163: ldc 134349312
    //   10165: iastore
    //   10166: dup
    //   10167: bipush #33
    //   10169: ldc 134217728
    //   10171: iastore
    //   10172: dup
    //   10173: bipush #34
    //   10175: ldc 131080
    //   10177: iastore
    //   10178: dup
    //   10179: bipush #35
    //   10181: sipush #520
    //   10184: iastore
    //   10185: dup
    //   10186: bipush #36
    //   10188: ldc 131072
    //   10190: iastore
    //   10191: dup
    //   10192: bipush #37
    //   10194: ldc 134349312
    //   10196: iastore
    //   10197: dup
    //   10198: bipush #38
    //   10200: ldc 134218240
    //   10202: iastore
    //   10203: dup
    //   10204: bipush #39
    //   10206: iconst_0
    //   10207: iastore
    //   10208: dup
    //   10209: bipush #40
    //   10211: sipush #512
    //   10214: iastore
    //   10215: dup
    //   10216: bipush #41
    //   10218: ldc 131080
    //   10220: iastore
    //   10221: dup
    //   10222: bipush #42
    //   10224: ldc 134349320
    //   10226: iastore
    //   10227: dup
    //   10228: bipush #43
    //   10230: ldc 134218240
    //   10232: iastore
    //   10233: dup
    //   10234: bipush #44
    //   10236: ldc 134217736
    //   10238: iastore
    //   10239: dup
    //   10240: bipush #45
    //   10242: sipush #512
    //   10245: iastore
    //   10246: dup
    //   10247: bipush #46
    //   10249: iconst_0
    //   10250: iastore
    //   10251: dup
    //   10252: bipush #47
    //   10254: ldc 134348808
    //   10256: iastore
    //   10257: dup
    //   10258: bipush #48
    //   10260: ldc 134218248
    //   10262: iastore
    //   10263: dup
    //   10264: bipush #49
    //   10266: ldc 131072
    //   10268: iastore
    //   10269: dup
    //   10270: bipush #50
    //   10272: ldc 134217728
    //   10274: iastore
    //   10275: dup
    //   10276: bipush #51
    //   10278: ldc 134349320
    //   10280: iastore
    //   10281: dup
    //   10282: bipush #52
    //   10284: bipush #8
    //   10286: iastore
    //   10287: dup
    //   10288: bipush #53
    //   10290: ldc 131592
    //   10292: iastore
    //   10293: dup
    //   10294: bipush #54
    //   10296: ldc 131584
    //   10298: iastore
    //   10299: dup
    //   10300: bipush #55
    //   10302: ldc 134217736
    //   10304: iastore
    //   10305: dup
    //   10306: bipush #56
    //   10308: ldc 134348800
    //   10310: iastore
    //   10311: dup
    //   10312: bipush #57
    //   10314: ldc 134218248
    //   10316: iastore
    //   10317: dup
    //   10318: bipush #58
    //   10320: sipush #520
    //   10323: iastore
    //   10324: dup
    //   10325: bipush #59
    //   10327: ldc 134348800
    //   10329: iastore
    //   10330: dup
    //   10331: bipush #60
    //   10333: ldc 131592
    //   10335: iastore
    //   10336: dup
    //   10337: bipush #61
    //   10339: bipush #8
    //   10341: iastore
    //   10342: dup
    //   10343: bipush #62
    //   10345: ldc 134348808
    //   10347: iastore
    //   10348: dup
    //   10349: bipush #63
    //   10351: ldc 131584
    //   10353: iastore
    //   10354: astore #8
    //   10356: bipush #64
    //   10358: newarray int
    //   10360: dup
    //   10361: iconst_0
    //   10362: ldc 8396801
    //   10364: iastore
    //   10365: dup
    //   10366: iconst_1
    //   10367: sipush #8321
    //   10370: iastore
    //   10371: dup
    //   10372: iconst_2
    //   10373: sipush #8321
    //   10376: iastore
    //   10377: dup
    //   10378: iconst_3
    //   10379: sipush #128
    //   10382: iastore
    //   10383: dup
    //   10384: iconst_4
    //   10385: ldc 8396928
    //   10387: iastore
    //   10388: dup
    //   10389: iconst_5
    //   10390: ldc 8388737
    //   10392: iastore
    //   10393: dup
    //   10394: bipush #6
    //   10396: ldc 8388609
    //   10398: iastore
    //   10399: dup
    //   10400: bipush #7
    //   10402: sipush #8193
    //   10405: iastore
    //   10406: dup
    //   10407: bipush #8
    //   10409: iconst_0
    //   10410: iastore
    //   10411: dup
    //   10412: bipush #9
    //   10414: ldc 8396800
    //   10416: iastore
    //   10417: dup
    //   10418: bipush #10
    //   10420: ldc 8396800
    //   10422: iastore
    //   10423: dup
    //   10424: bipush #11
    //   10426: ldc 8396929
    //   10428: iastore
    //   10429: dup
    //   10430: bipush #12
    //   10432: sipush #129
    //   10435: iastore
    //   10436: dup
    //   10437: bipush #13
    //   10439: iconst_0
    //   10440: iastore
    //   10441: dup
    //   10442: bipush #14
    //   10444: ldc 8388736
    //   10446: iastore
    //   10447: dup
    //   10448: bipush #15
    //   10450: ldc 8388609
    //   10452: iastore
    //   10453: dup
    //   10454: bipush #16
    //   10456: iconst_1
    //   10457: iastore
    //   10458: dup
    //   10459: bipush #17
    //   10461: sipush #8192
    //   10464: iastore
    //   10465: dup
    //   10466: bipush #18
    //   10468: ldc 8388608
    //   10470: iastore
    //   10471: dup
    //   10472: bipush #19
    //   10474: ldc 8396801
    //   10476: iastore
    //   10477: dup
    //   10478: bipush #20
    //   10480: sipush #128
    //   10483: iastore
    //   10484: dup
    //   10485: bipush #21
    //   10487: ldc 8388608
    //   10489: iastore
    //   10490: dup
    //   10491: bipush #22
    //   10493: sipush #8193
    //   10496: iastore
    //   10497: dup
    //   10498: bipush #23
    //   10500: sipush #8320
    //   10503: iastore
    //   10504: dup
    //   10505: bipush #24
    //   10507: ldc 8388737
    //   10509: iastore
    //   10510: dup
    //   10511: bipush #25
    //   10513: iconst_1
    //   10514: iastore
    //   10515: dup
    //   10516: bipush #26
    //   10518: sipush #8320
    //   10521: iastore
    //   10522: dup
    //   10523: bipush #27
    //   10525: ldc 8388736
    //   10527: iastore
    //   10528: dup
    //   10529: bipush #28
    //   10531: sipush #8192
    //   10534: iastore
    //   10535: dup
    //   10536: bipush #29
    //   10538: ldc 8396928
    //   10540: iastore
    //   10541: dup
    //   10542: bipush #30
    //   10544: ldc 8396929
    //   10546: iastore
    //   10547: dup
    //   10548: bipush #31
    //   10550: sipush #129
    //   10553: iastore
    //   10554: dup
    //   10555: bipush #32
    //   10557: ldc 8388736
    //   10559: iastore
    //   10560: dup
    //   10561: bipush #33
    //   10563: ldc 8388609
    //   10565: iastore
    //   10566: dup
    //   10567: bipush #34
    //   10569: ldc 8396800
    //   10571: iastore
    //   10572: dup
    //   10573: bipush #35
    //   10575: ldc 8396929
    //   10577: iastore
    //   10578: dup
    //   10579: bipush #36
    //   10581: sipush #129
    //   10584: iastore
    //   10585: dup
    //   10586: bipush #37
    //   10588: iconst_0
    //   10589: iastore
    //   10590: dup
    //   10591: bipush #38
    //   10593: iconst_0
    //   10594: iastore
    //   10595: dup
    //   10596: bipush #39
    //   10598: ldc 8396800
    //   10600: iastore
    //   10601: dup
    //   10602: bipush #40
    //   10604: sipush #8320
    //   10607: iastore
    //   10608: dup
    //   10609: bipush #41
    //   10611: ldc 8388736
    //   10613: iastore
    //   10614: dup
    //   10615: bipush #42
    //   10617: ldc 8388737
    //   10619: iastore
    //   10620: dup
    //   10621: bipush #43
    //   10623: iconst_1
    //   10624: iastore
    //   10625: dup
    //   10626: bipush #44
    //   10628: ldc 8396801
    //   10630: iastore
    //   10631: dup
    //   10632: bipush #45
    //   10634: sipush #8321
    //   10637: iastore
    //   10638: dup
    //   10639: bipush #46
    //   10641: sipush #8321
    //   10644: iastore
    //   10645: dup
    //   10646: bipush #47
    //   10648: sipush #128
    //   10651: iastore
    //   10652: dup
    //   10653: bipush #48
    //   10655: ldc 8396929
    //   10657: iastore
    //   10658: dup
    //   10659: bipush #49
    //   10661: sipush #129
    //   10664: iastore
    //   10665: dup
    //   10666: bipush #50
    //   10668: iconst_1
    //   10669: iastore
    //   10670: dup
    //   10671: bipush #51
    //   10673: sipush #8192
    //   10676: iastore
    //   10677: dup
    //   10678: bipush #52
    //   10680: ldc 8388609
    //   10682: iastore
    //   10683: dup
    //   10684: bipush #53
    //   10686: sipush #8193
    //   10689: iastore
    //   10690: dup
    //   10691: bipush #54
    //   10693: ldc 8396928
    //   10695: iastore
    //   10696: dup
    //   10697: bipush #55
    //   10699: ldc 8388737
    //   10701: iastore
    //   10702: dup
    //   10703: bipush #56
    //   10705: sipush #8193
    //   10708: iastore
    //   10709: dup
    //   10710: bipush #57
    //   10712: sipush #8320
    //   10715: iastore
    //   10716: dup
    //   10717: bipush #58
    //   10719: ldc 8388608
    //   10721: iastore
    //   10722: dup
    //   10723: bipush #59
    //   10725: ldc 8396801
    //   10727: iastore
    //   10728: dup
    //   10729: bipush #60
    //   10731: sipush #128
    //   10734: iastore
    //   10735: dup
    //   10736: bipush #61
    //   10738: ldc 8388608
    //   10740: iastore
    //   10741: dup
    //   10742: bipush #62
    //   10744: sipush #8192
    //   10747: iastore
    //   10748: dup
    //   10749: bipush #63
    //   10751: ldc 8396928
    //   10753: iastore
    //   10754: astore #9
    //   10756: bipush #64
    //   10758: newarray int
    //   10760: dup
    //   10761: iconst_0
    //   10762: sipush #256
    //   10765: iastore
    //   10766: dup
    //   10767: iconst_1
    //   10768: ldc 34078976
    //   10770: iastore
    //   10771: dup
    //   10772: iconst_2
    //   10773: ldc 34078720
    //   10775: iastore
    //   10776: dup
    //   10777: iconst_3
    //   10778: ldc 1107296512
    //   10780: iastore
    //   10781: dup
    //   10782: iconst_4
    //   10783: ldc 524288
    //   10785: iastore
    //   10786: dup
    //   10787: iconst_5
    //   10788: sipush #256
    //   10791: iastore
    //   10792: dup
    //   10793: bipush #6
    //   10795: ldc 1073741824
    //   10797: iastore
    //   10798: dup
    //   10799: bipush #7
    //   10801: ldc 34078720
    //   10803: iastore
    //   10804: dup
    //   10805: bipush #8
    //   10807: ldc 1074266368
    //   10809: iastore
    //   10810: dup
    //   10811: bipush #9
    //   10813: ldc 524288
    //   10815: iastore
    //   10816: dup
    //   10817: bipush #10
    //   10819: ldc 33554688
    //   10821: iastore
    //   10822: dup
    //   10823: bipush #11
    //   10825: ldc 1074266368
    //   10827: iastore
    //   10828: dup
    //   10829: bipush #12
    //   10831: ldc 1107296512
    //   10833: iastore
    //   10834: dup
    //   10835: bipush #13
    //   10837: ldc 1107820544
    //   10839: iastore
    //   10840: dup
    //   10841: bipush #14
    //   10843: ldc 524544
    //   10845: iastore
    //   10846: dup
    //   10847: bipush #15
    //   10849: ldc 1073741824
    //   10851: iastore
    //   10852: dup
    //   10853: bipush #16
    //   10855: ldc 33554432
    //   10857: iastore
    //   10858: dup
    //   10859: bipush #17
    //   10861: ldc 1074266112
    //   10863: iastore
    //   10864: dup
    //   10865: bipush #18
    //   10867: ldc 1074266112
    //   10869: iastore
    //   10870: dup
    //   10871: bipush #19
    //   10873: iconst_0
    //   10874: iastore
    //   10875: dup
    //   10876: bipush #20
    //   10878: ldc 1073742080
    //   10880: iastore
    //   10881: dup
    //   10882: bipush #21
    //   10884: ldc 1107820800
    //   10886: iastore
    //   10887: dup
    //   10888: bipush #22
    //   10890: ldc 1107820800
    //   10892: iastore
    //   10893: dup
    //   10894: bipush #23
    //   10896: ldc 33554688
    //   10898: iastore
    //   10899: dup
    //   10900: bipush #24
    //   10902: ldc 1107820544
    //   10904: iastore
    //   10905: dup
    //   10906: bipush #25
    //   10908: ldc 1073742080
    //   10910: iastore
    //   10911: dup
    //   10912: bipush #26
    //   10914: iconst_0
    //   10915: iastore
    //   10916: dup
    //   10917: bipush #27
    //   10919: ldc 1107296256
    //   10921: iastore
    //   10922: dup
    //   10923: bipush #28
    //   10925: ldc 34078976
    //   10927: iastore
    //   10928: dup
    //   10929: bipush #29
    //   10931: ldc 33554432
    //   10933: iastore
    //   10934: dup
    //   10935: bipush #30
    //   10937: ldc 1107296256
    //   10939: iastore
    //   10940: dup
    //   10941: bipush #31
    //   10943: ldc 524544
    //   10945: iastore
    //   10946: dup
    //   10947: bipush #32
    //   10949: ldc 524288
    //   10951: iastore
    //   10952: dup
    //   10953: bipush #33
    //   10955: ldc 1107296512
    //   10957: iastore
    //   10958: dup
    //   10959: bipush #34
    //   10961: sipush #256
    //   10964: iastore
    //   10965: dup
    //   10966: bipush #35
    //   10968: ldc 33554432
    //   10970: iastore
    //   10971: dup
    //   10972: bipush #36
    //   10974: ldc 1073741824
    //   10976: iastore
    //   10977: dup
    //   10978: bipush #37
    //   10980: ldc 34078720
    //   10982: iastore
    //   10983: dup
    //   10984: bipush #38
    //   10986: ldc 1107296512
    //   10988: iastore
    //   10989: dup
    //   10990: bipush #39
    //   10992: ldc 1074266368
    //   10994: iastore
    //   10995: dup
    //   10996: bipush #40
    //   10998: ldc 33554688
    //   11000: iastore
    //   11001: dup
    //   11002: bipush #41
    //   11004: ldc 1073741824
    //   11006: iastore
    //   11007: dup
    //   11008: bipush #42
    //   11010: ldc 1107820544
    //   11012: iastore
    //   11013: dup
    //   11014: bipush #43
    //   11016: ldc 34078976
    //   11018: iastore
    //   11019: dup
    //   11020: bipush #44
    //   11022: ldc 1074266368
    //   11024: iastore
    //   11025: dup
    //   11026: bipush #45
    //   11028: sipush #256
    //   11031: iastore
    //   11032: dup
    //   11033: bipush #46
    //   11035: ldc 33554432
    //   11037: iastore
    //   11038: dup
    //   11039: bipush #47
    //   11041: ldc 1107820544
    //   11043: iastore
    //   11044: dup
    //   11045: bipush #48
    //   11047: ldc 1107820800
    //   11049: iastore
    //   11050: dup
    //   11051: bipush #49
    //   11053: ldc 524544
    //   11055: iastore
    //   11056: dup
    //   11057: bipush #50
    //   11059: ldc 1107296256
    //   11061: iastore
    //   11062: dup
    //   11063: bipush #51
    //   11065: ldc 1107820800
    //   11067: iastore
    //   11068: dup
    //   11069: bipush #52
    //   11071: ldc 34078720
    //   11073: iastore
    //   11074: dup
    //   11075: bipush #53
    //   11077: iconst_0
    //   11078: iastore
    //   11079: dup
    //   11080: bipush #54
    //   11082: ldc 1074266112
    //   11084: iastore
    //   11085: dup
    //   11086: bipush #55
    //   11088: ldc 1107296256
    //   11090: iastore
    //   11091: dup
    //   11092: bipush #56
    //   11094: ldc 524544
    //   11096: iastore
    //   11097: dup
    //   11098: bipush #57
    //   11100: ldc 33554688
    //   11102: iastore
    //   11103: dup
    //   11104: bipush #58
    //   11106: ldc 1073742080
    //   11108: iastore
    //   11109: dup
    //   11110: bipush #59
    //   11112: ldc 524288
    //   11114: iastore
    //   11115: dup
    //   11116: bipush #60
    //   11118: iconst_0
    //   11119: iastore
    //   11120: dup
    //   11121: bipush #61
    //   11123: ldc 1074266112
    //   11125: iastore
    //   11126: dup
    //   11127: bipush #62
    //   11129: ldc 34078976
    //   11131: iastore
    //   11132: dup
    //   11133: bipush #63
    //   11135: ldc 1073742080
    //   11137: iastore
    //   11138: astore #10
    //   11140: bipush #64
    //   11142: newarray int
    //   11144: dup
    //   11145: iconst_0
    //   11146: ldc 536870928
    //   11148: iastore
    //   11149: dup
    //   11150: iconst_1
    //   11151: ldc 541065216
    //   11153: iastore
    //   11154: dup
    //   11155: iconst_2
    //   11156: sipush #16384
    //   11159: iastore
    //   11160: dup
    //   11161: iconst_3
    //   11162: ldc 541081616
    //   11164: iastore
    //   11165: dup
    //   11166: iconst_4
    //   11167: ldc 541065216
    //   11169: iastore
    //   11170: dup
    //   11171: iconst_5
    //   11172: bipush #16
    //   11174: iastore
    //   11175: dup
    //   11176: bipush #6
    //   11178: ldc 541081616
    //   11180: iastore
    //   11181: dup
    //   11182: bipush #7
    //   11184: ldc 4194304
    //   11186: iastore
    //   11187: dup
    //   11188: bipush #8
    //   11190: ldc 536887296
    //   11192: iastore
    //   11193: dup
    //   11194: bipush #9
    //   11196: ldc 4210704
    //   11198: iastore
    //   11199: dup
    //   11200: bipush #10
    //   11202: ldc 4194304
    //   11204: iastore
    //   11205: dup
    //   11206: bipush #11
    //   11208: ldc 536870928
    //   11210: iastore
    //   11211: dup
    //   11212: bipush #12
    //   11214: ldc 4194320
    //   11216: iastore
    //   11217: dup
    //   11218: bipush #13
    //   11220: ldc 536887296
    //   11222: iastore
    //   11223: dup
    //   11224: bipush #14
    //   11226: ldc 536870912
    //   11228: iastore
    //   11229: dup
    //   11230: bipush #15
    //   11232: sipush #16400
    //   11235: iastore
    //   11236: dup
    //   11237: bipush #16
    //   11239: iconst_0
    //   11240: iastore
    //   11241: dup
    //   11242: bipush #17
    //   11244: ldc 4194320
    //   11246: iastore
    //   11247: dup
    //   11248: bipush #18
    //   11250: ldc 536887312
    //   11252: iastore
    //   11253: dup
    //   11254: bipush #19
    //   11256: sipush #16384
    //   11259: iastore
    //   11260: dup
    //   11261: bipush #20
    //   11263: ldc 4210688
    //   11265: iastore
    //   11266: dup
    //   11267: bipush #21
    //   11269: ldc 536887312
    //   11271: iastore
    //   11272: dup
    //   11273: bipush #22
    //   11275: bipush #16
    //   11277: iastore
    //   11278: dup
    //   11279: bipush #23
    //   11281: ldc 541065232
    //   11283: iastore
    //   11284: dup
    //   11285: bipush #24
    //   11287: ldc 541065232
    //   11289: iastore
    //   11290: dup
    //   11291: bipush #25
    //   11293: iconst_0
    //   11294: iastore
    //   11295: dup
    //   11296: bipush #26
    //   11298: ldc 4210704
    //   11300: iastore
    //   11301: dup
    //   11302: bipush #27
    //   11304: ldc 541081600
    //   11306: iastore
    //   11307: dup
    //   11308: bipush #28
    //   11310: sipush #16400
    //   11313: iastore
    //   11314: dup
    //   11315: bipush #29
    //   11317: ldc 4210688
    //   11319: iastore
    //   11320: dup
    //   11321: bipush #30
    //   11323: ldc 541081600
    //   11325: iastore
    //   11326: dup
    //   11327: bipush #31
    //   11329: ldc 536870912
    //   11331: iastore
    //   11332: dup
    //   11333: bipush #32
    //   11335: ldc 536887296
    //   11337: iastore
    //   11338: dup
    //   11339: bipush #33
    //   11341: bipush #16
    //   11343: iastore
    //   11344: dup
    //   11345: bipush #34
    //   11347: ldc 541065232
    //   11349: iastore
    //   11350: dup
    //   11351: bipush #35
    //   11353: ldc 4210688
    //   11355: iastore
    //   11356: dup
    //   11357: bipush #36
    //   11359: ldc 541081616
    //   11361: iastore
    //   11362: dup
    //   11363: bipush #37
    //   11365: ldc 4194304
    //   11367: iastore
    //   11368: dup
    //   11369: bipush #38
    //   11371: sipush #16400
    //   11374: iastore
    //   11375: dup
    //   11376: bipush #39
    //   11378: ldc 536870928
    //   11380: iastore
    //   11381: dup
    //   11382: bipush #40
    //   11384: ldc 4194304
    //   11386: iastore
    //   11387: dup
    //   11388: bipush #41
    //   11390: ldc 536887296
    //   11392: iastore
    //   11393: dup
    //   11394: bipush #42
    //   11396: ldc 536870912
    //   11398: iastore
    //   11399: dup
    //   11400: bipush #43
    //   11402: sipush #16400
    //   11405: iastore
    //   11406: dup
    //   11407: bipush #44
    //   11409: ldc 536870928
    //   11411: iastore
    //   11412: dup
    //   11413: bipush #45
    //   11415: ldc 541081616
    //   11417: iastore
    //   11418: dup
    //   11419: bipush #46
    //   11421: ldc 4210688
    //   11423: iastore
    //   11424: dup
    //   11425: bipush #47
    //   11427: ldc 541065216
    //   11429: iastore
    //   11430: dup
    //   11431: bipush #48
    //   11433: ldc 4210704
    //   11435: iastore
    //   11436: dup
    //   11437: bipush #49
    //   11439: ldc 541081600
    //   11441: iastore
    //   11442: dup
    //   11443: bipush #50
    //   11445: iconst_0
    //   11446: iastore
    //   11447: dup
    //   11448: bipush #51
    //   11450: ldc 541065232
    //   11452: iastore
    //   11453: dup
    //   11454: bipush #52
    //   11456: bipush #16
    //   11458: iastore
    //   11459: dup
    //   11460: bipush #53
    //   11462: sipush #16384
    //   11465: iastore
    //   11466: dup
    //   11467: bipush #54
    //   11469: ldc 541065216
    //   11471: iastore
    //   11472: dup
    //   11473: bipush #55
    //   11475: ldc 4210704
    //   11477: iastore
    //   11478: dup
    //   11479: bipush #56
    //   11481: sipush #16384
    //   11484: iastore
    //   11485: dup
    //   11486: bipush #57
    //   11488: ldc 4194320
    //   11490: iastore
    //   11491: dup
    //   11492: bipush #58
    //   11494: ldc 536887312
    //   11496: iastore
    //   11497: dup
    //   11498: bipush #59
    //   11500: iconst_0
    //   11501: iastore
    //   11502: dup
    //   11503: bipush #60
    //   11505: ldc 541081600
    //   11507: iastore
    //   11508: dup
    //   11509: bipush #61
    //   11511: ldc 536870912
    //   11513: iastore
    //   11514: dup
    //   11515: bipush #62
    //   11517: ldc 4194320
    //   11519: iastore
    //   11520: dup
    //   11521: bipush #63
    //   11523: ldc 536887312
    //   11525: iastore
    //   11526: astore #11
    //   11528: bipush #64
    //   11530: newarray int
    //   11532: dup
    //   11533: iconst_0
    //   11534: ldc 2097152
    //   11536: iastore
    //   11537: dup
    //   11538: iconst_1
    //   11539: ldc 69206018
    //   11541: iastore
    //   11542: dup
    //   11543: iconst_2
    //   11544: ldc 67110914
    //   11546: iastore
    //   11547: dup
    //   11548: iconst_3
    //   11549: iconst_0
    //   11550: iastore
    //   11551: dup
    //   11552: iconst_4
    //   11553: sipush #2048
    //   11556: iastore
    //   11557: dup
    //   11558: iconst_5
    //   11559: ldc 67110914
    //   11561: iastore
    //   11562: dup
    //   11563: bipush #6
    //   11565: ldc 2099202
    //   11567: iastore
    //   11568: dup
    //   11569: bipush #7
    //   11571: ldc 69208064
    //   11573: iastore
    //   11574: dup
    //   11575: bipush #8
    //   11577: ldc 69208066
    //   11579: iastore
    //   11580: dup
    //   11581: bipush #9
    //   11583: ldc 2097152
    //   11585: iastore
    //   11586: dup
    //   11587: bipush #10
    //   11589: iconst_0
    //   11590: iastore
    //   11591: dup
    //   11592: bipush #11
    //   11594: ldc 67108866
    //   11596: iastore
    //   11597: dup
    //   11598: bipush #12
    //   11600: iconst_2
    //   11601: iastore
    //   11602: dup
    //   11603: bipush #13
    //   11605: ldc 67108864
    //   11607: iastore
    //   11608: dup
    //   11609: bipush #14
    //   11611: ldc 69206018
    //   11613: iastore
    //   11614: dup
    //   11615: bipush #15
    //   11617: sipush #2050
    //   11620: iastore
    //   11621: dup
    //   11622: bipush #16
    //   11624: ldc 67110912
    //   11626: iastore
    //   11627: dup
    //   11628: bipush #17
    //   11630: ldc 2099202
    //   11632: iastore
    //   11633: dup
    //   11634: bipush #18
    //   11636: ldc 2097154
    //   11638: iastore
    //   11639: dup
    //   11640: bipush #19
    //   11642: ldc 67110912
    //   11644: iastore
    //   11645: dup
    //   11646: bipush #20
    //   11648: ldc 67108866
    //   11650: iastore
    //   11651: dup
    //   11652: bipush #21
    //   11654: ldc 69206016
    //   11656: iastore
    //   11657: dup
    //   11658: bipush #22
    //   11660: ldc 69208064
    //   11662: iastore
    //   11663: dup
    //   11664: bipush #23
    //   11666: ldc 2097154
    //   11668: iastore
    //   11669: dup
    //   11670: bipush #24
    //   11672: ldc 69206016
    //   11674: iastore
    //   11675: dup
    //   11676: bipush #25
    //   11678: sipush #2048
    //   11681: iastore
    //   11682: dup
    //   11683: bipush #26
    //   11685: sipush #2050
    //   11688: iastore
    //   11689: dup
    //   11690: bipush #27
    //   11692: ldc 69208066
    //   11694: iastore
    //   11695: dup
    //   11696: bipush #28
    //   11698: ldc 2099200
    //   11700: iastore
    //   11701: dup
    //   11702: bipush #29
    //   11704: iconst_2
    //   11705: iastore
    //   11706: dup
    //   11707: bipush #30
    //   11709: ldc 67108864
    //   11711: iastore
    //   11712: dup
    //   11713: bipush #31
    //   11715: ldc 2099200
    //   11717: iastore
    //   11718: dup
    //   11719: bipush #32
    //   11721: ldc 67108864
    //   11723: iastore
    //   11724: dup
    //   11725: bipush #33
    //   11727: ldc 2099200
    //   11729: iastore
    //   11730: dup
    //   11731: bipush #34
    //   11733: ldc 2097152
    //   11735: iastore
    //   11736: dup
    //   11737: bipush #35
    //   11739: ldc 67110914
    //   11741: iastore
    //   11742: dup
    //   11743: bipush #36
    //   11745: ldc 67110914
    //   11747: iastore
    //   11748: dup
    //   11749: bipush #37
    //   11751: ldc 69206018
    //   11753: iastore
    //   11754: dup
    //   11755: bipush #38
    //   11757: ldc 69206018
    //   11759: iastore
    //   11760: dup
    //   11761: bipush #39
    //   11763: iconst_2
    //   11764: iastore
    //   11765: dup
    //   11766: bipush #40
    //   11768: ldc 2097154
    //   11770: iastore
    //   11771: dup
    //   11772: bipush #41
    //   11774: ldc 67108864
    //   11776: iastore
    //   11777: dup
    //   11778: bipush #42
    //   11780: ldc 67110912
    //   11782: iastore
    //   11783: dup
    //   11784: bipush #43
    //   11786: ldc 2097152
    //   11788: iastore
    //   11789: dup
    //   11790: bipush #44
    //   11792: ldc 69208064
    //   11794: iastore
    //   11795: dup
    //   11796: bipush #45
    //   11798: sipush #2050
    //   11801: iastore
    //   11802: dup
    //   11803: bipush #46
    //   11805: ldc 2099202
    //   11807: iastore
    //   11808: dup
    //   11809: bipush #47
    //   11811: ldc 69208064
    //   11813: iastore
    //   11814: dup
    //   11815: bipush #48
    //   11817: sipush #2050
    //   11820: iastore
    //   11821: dup
    //   11822: bipush #49
    //   11824: ldc 67108866
    //   11826: iastore
    //   11827: dup
    //   11828: bipush #50
    //   11830: ldc 69208066
    //   11832: iastore
    //   11833: dup
    //   11834: bipush #51
    //   11836: ldc 69206016
    //   11838: iastore
    //   11839: dup
    //   11840: bipush #52
    //   11842: ldc 2099200
    //   11844: iastore
    //   11845: dup
    //   11846: bipush #53
    //   11848: iconst_0
    //   11849: iastore
    //   11850: dup
    //   11851: bipush #54
    //   11853: iconst_2
    //   11854: iastore
    //   11855: dup
    //   11856: bipush #55
    //   11858: ldc 69208066
    //   11860: iastore
    //   11861: dup
    //   11862: bipush #56
    //   11864: iconst_0
    //   11865: iastore
    //   11866: dup
    //   11867: bipush #57
    //   11869: ldc 2099202
    //   11871: iastore
    //   11872: dup
    //   11873: bipush #58
    //   11875: ldc 69206016
    //   11877: iastore
    //   11878: dup
    //   11879: bipush #59
    //   11881: sipush #2048
    //   11884: iastore
    //   11885: dup
    //   11886: bipush #60
    //   11888: ldc 67108866
    //   11890: iastore
    //   11891: dup
    //   11892: bipush #61
    //   11894: ldc 67110912
    //   11896: iastore
    //   11897: dup
    //   11898: bipush #62
    //   11900: sipush #2048
    //   11903: iastore
    //   11904: dup
    //   11905: bipush #63
    //   11907: ldc 2097154
    //   11909: iastore
    //   11910: astore #12
    //   11912: bipush #64
    //   11914: newarray int
    //   11916: dup
    //   11917: iconst_0
    //   11918: ldc 268439616
    //   11920: iastore
    //   11921: dup
    //   11922: iconst_1
    //   11923: sipush #4096
    //   11926: iastore
    //   11927: dup
    //   11928: iconst_2
    //   11929: ldc 262144
    //   11931: iastore
    //   11932: dup
    //   11933: iconst_3
    //   11934: ldc 268701760
    //   11936: iastore
    //   11937: dup
    //   11938: iconst_4
    //   11939: ldc 268435456
    //   11941: iastore
    //   11942: dup
    //   11943: iconst_5
    //   11944: ldc 268439616
    //   11946: iastore
    //   11947: dup
    //   11948: bipush #6
    //   11950: bipush #64
    //   11952: iastore
    //   11953: dup
    //   11954: bipush #7
    //   11956: ldc 268435456
    //   11958: iastore
    //   11959: dup
    //   11960: bipush #8
    //   11962: ldc 262208
    //   11964: iastore
    //   11965: dup
    //   11966: bipush #9
    //   11968: ldc 268697600
    //   11970: iastore
    //   11971: dup
    //   11972: bipush #10
    //   11974: ldc 268701760
    //   11976: iastore
    //   11977: dup
    //   11978: bipush #11
    //   11980: ldc 266240
    //   11982: iastore
    //   11983: dup
    //   11984: bipush #12
    //   11986: ldc 268701696
    //   11988: iastore
    //   11989: dup
    //   11990: bipush #13
    //   11992: ldc 266304
    //   11994: iastore
    //   11995: dup
    //   11996: bipush #14
    //   11998: sipush #4096
    //   12001: iastore
    //   12002: dup
    //   12003: bipush #15
    //   12005: bipush #64
    //   12007: iastore
    //   12008: dup
    //   12009: bipush #16
    //   12011: ldc 268697600
    //   12013: iastore
    //   12014: dup
    //   12015: bipush #17
    //   12017: ldc 268435520
    //   12019: iastore
    //   12020: dup
    //   12021: bipush #18
    //   12023: ldc 268439552
    //   12025: iastore
    //   12026: dup
    //   12027: bipush #19
    //   12029: sipush #4160
    //   12032: iastore
    //   12033: dup
    //   12034: bipush #20
    //   12036: ldc 266240
    //   12038: iastore
    //   12039: dup
    //   12040: bipush #21
    //   12042: ldc 262208
    //   12044: iastore
    //   12045: dup
    //   12046: bipush #22
    //   12048: ldc 268697664
    //   12050: iastore
    //   12051: dup
    //   12052: bipush #23
    //   12054: ldc 268701696
    //   12056: iastore
    //   12057: dup
    //   12058: bipush #24
    //   12060: sipush #4160
    //   12063: iastore
    //   12064: dup
    //   12065: bipush #25
    //   12067: iconst_0
    //   12068: iastore
    //   12069: dup
    //   12070: bipush #26
    //   12072: iconst_0
    //   12073: iastore
    //   12074: dup
    //   12075: bipush #27
    //   12077: ldc 268697664
    //   12079: iastore
    //   12080: dup
    //   12081: bipush #28
    //   12083: ldc 268435520
    //   12085: iastore
    //   12086: dup
    //   12087: bipush #29
    //   12089: ldc 268439552
    //   12091: iastore
    //   12092: dup
    //   12093: bipush #30
    //   12095: ldc 266304
    //   12097: iastore
    //   12098: dup
    //   12099: bipush #31
    //   12101: ldc 262144
    //   12103: iastore
    //   12104: dup
    //   12105: bipush #32
    //   12107: ldc 266304
    //   12109: iastore
    //   12110: dup
    //   12111: bipush #33
    //   12113: ldc 262144
    //   12115: iastore
    //   12116: dup
    //   12117: bipush #34
    //   12119: ldc 268701696
    //   12121: iastore
    //   12122: dup
    //   12123: bipush #35
    //   12125: sipush #4096
    //   12128: iastore
    //   12129: dup
    //   12130: bipush #36
    //   12132: bipush #64
    //   12134: iastore
    //   12135: dup
    //   12136: bipush #37
    //   12138: ldc 268697664
    //   12140: iastore
    //   12141: dup
    //   12142: bipush #38
    //   12144: sipush #4096
    //   12147: iastore
    //   12148: dup
    //   12149: bipush #39
    //   12151: ldc 266304
    //   12153: iastore
    //   12154: dup
    //   12155: bipush #40
    //   12157: ldc 268439552
    //   12159: iastore
    //   12160: dup
    //   12161: bipush #41
    //   12163: bipush #64
    //   12165: iastore
    //   12166: dup
    //   12167: bipush #42
    //   12169: ldc 268435520
    //   12171: iastore
    //   12172: dup
    //   12173: bipush #43
    //   12175: ldc 268697600
    //   12177: iastore
    //   12178: dup
    //   12179: bipush #44
    //   12181: ldc 268697664
    //   12183: iastore
    //   12184: dup
    //   12185: bipush #45
    //   12187: ldc 268435456
    //   12189: iastore
    //   12190: dup
    //   12191: bipush #46
    //   12193: ldc 262144
    //   12195: iastore
    //   12196: dup
    //   12197: bipush #47
    //   12199: ldc 268439616
    //   12201: iastore
    //   12202: dup
    //   12203: bipush #48
    //   12205: iconst_0
    //   12206: iastore
    //   12207: dup
    //   12208: bipush #49
    //   12210: ldc 268701760
    //   12212: iastore
    //   12213: dup
    //   12214: bipush #50
    //   12216: ldc 262208
    //   12218: iastore
    //   12219: dup
    //   12220: bipush #51
    //   12222: ldc 268435520
    //   12224: iastore
    //   12225: dup
    //   12226: bipush #52
    //   12228: ldc 268697600
    //   12230: iastore
    //   12231: dup
    //   12232: bipush #53
    //   12234: ldc 268439552
    //   12236: iastore
    //   12237: dup
    //   12238: bipush #54
    //   12240: ldc 268439616
    //   12242: iastore
    //   12243: dup
    //   12244: bipush #55
    //   12246: iconst_0
    //   12247: iastore
    //   12248: dup
    //   12249: bipush #56
    //   12251: ldc 268701760
    //   12253: iastore
    //   12254: dup
    //   12255: bipush #57
    //   12257: ldc 266240
    //   12259: iastore
    //   12260: dup
    //   12261: bipush #58
    //   12263: ldc 266240
    //   12265: iastore
    //   12266: dup
    //   12267: bipush #59
    //   12269: sipush #4160
    //   12272: iastore
    //   12273: dup
    //   12274: bipush #60
    //   12276: sipush #4160
    //   12279: iastore
    //   12280: dup
    //   12281: bipush #61
    //   12283: ldc 262208
    //   12285: iastore
    //   12286: dup
    //   12287: bipush #62
    //   12289: ldc 268435456
    //   12291: iastore
    //   12292: dup
    //   12293: bipush #63
    //   12295: ldc 268701696
    //   12297: iastore
    //   12298: astore #13
    //   12300: aload_3
    //   12301: arraylength
    //   12302: istore #14
    //   12304: iload #14
    //   12306: bipush #8
    //   12308: irem
    //   12309: ifeq -> 12333
    //   12312: new java/lang/Exception
    //   12315: dup
    //   12316: sipush #6001
    //   12319: sipush #-16963
    //   12322: invokestatic a : (II)Ljava/lang/String;
    //   12325: invokespecial <init> : (Ljava/lang/String;)V
    //   12328: athrow
    //   12329: invokestatic a : (Ljava/lang/Throwable;)Ljava/lang/Throwable;
    //   12332: athrow
    //   12333: iconst_2
    //   12334: newarray int
    //   12336: astore #15
    //   12338: iload #14
    //   12340: newarray byte
    //   12342: astore #16
    //   12344: iload #14
    //   12346: bipush #8
    //   12348: idiv
    //   12349: istore #17
    //   12351: iconst_0
    //   12352: istore #18
    //   12354: iload #18
    //   12356: iload #17
    //   12358: if_icmpge -> 13272
    //   12361: iload #18
    //   12363: bipush #8
    //   12365: imul
    //   12366: istore #19
    //   12368: iconst_0
    //   12369: istore #20
    //   12371: iload #20
    //   12373: iconst_2
    //   12374: if_icmpge -> 12459
    //   12377: aload #15
    //   12379: iload #20
    //   12381: aload_3
    //   12382: iload #19
    //   12384: iload #20
    //   12386: iconst_4
    //   12387: imul
    //   12388: iadd
    //   12389: baload
    //   12390: sipush #255
    //   12393: iand
    //   12394: bipush #24
    //   12396: ishl
    //   12397: aload_3
    //   12398: iload #19
    //   12400: iload #20
    //   12402: iconst_4
    //   12403: imul
    //   12404: iadd
    //   12405: iconst_1
    //   12406: iadd
    //   12407: baload
    //   12408: sipush #255
    //   12411: iand
    //   12412: bipush #16
    //   12414: ishl
    //   12415: ior
    //   12416: aload_3
    //   12417: iload #19
    //   12419: iload #20
    //   12421: iconst_4
    //   12422: imul
    //   12423: iadd
    //   12424: iconst_2
    //   12425: iadd
    //   12426: baload
    //   12427: sipush #255
    //   12430: iand
    //   12431: bipush #8
    //   12433: ishl
    //   12434: ior
    //   12435: aload_3
    //   12436: iload #19
    //   12438: iload #20
    //   12440: iconst_4
    //   12441: imul
    //   12442: iadd
    //   12443: iconst_3
    //   12444: iadd
    //   12445: baload
    //   12446: sipush #255
    //   12449: iand
    //   12450: ior
    //   12451: iastore
    //   12452: iinc #20, 1
    //   12455: iload_2
    //   12456: ifne -> 12371
    //   12459: iconst_0
    //   12460: istore #25
    //   12462: aload #15
    //   12464: iconst_0
    //   12465: iaload
    //   12466: istore #23
    //   12468: aload #15
    //   12470: iconst_1
    //   12471: iaload
    //   12472: istore #22
    //   12474: iload #23
    //   12476: iconst_4
    //   12477: iushr
    //   12478: iload #22
    //   12480: ixor
    //   12481: ldc 252645135
    //   12483: iand
    //   12484: istore #21
    //   12486: iload #22
    //   12488: iload #21
    //   12490: ixor
    //   12491: istore #22
    //   12493: iload #23
    //   12495: iload #21
    //   12497: iconst_4
    //   12498: ishl
    //   12499: ixor
    //   12500: istore #23
    //   12502: iload #23
    //   12504: bipush #16
    //   12506: iushr
    //   12507: iload #22
    //   12509: ixor
    //   12510: ldc 65535
    //   12512: iand
    //   12513: istore #21
    //   12515: iload #22
    //   12517: iload #21
    //   12519: ixor
    //   12520: istore #22
    //   12522: iload #23
    //   12524: iload #21
    //   12526: bipush #16
    //   12528: ishl
    //   12529: ixor
    //   12530: istore #23
    //   12532: iload #22
    //   12534: iconst_2
    //   12535: iushr
    //   12536: iload #23
    //   12538: ixor
    //   12539: ldc 858993459
    //   12541: iand
    //   12542: istore #21
    //   12544: iload #23
    //   12546: iload #21
    //   12548: ixor
    //   12549: istore #23
    //   12551: iload #22
    //   12553: iload #21
    //   12555: iconst_2
    //   12556: ishl
    //   12557: ixor
    //   12558: istore #22
    //   12560: iload #22
    //   12562: bipush #8
    //   12564: iushr
    //   12565: iload #23
    //   12567: ixor
    //   12568: ldc 16711935
    //   12570: iand
    //   12571: istore #21
    //   12573: iload #23
    //   12575: iload #21
    //   12577: ixor
    //   12578: istore #23
    //   12580: iload #22
    //   12582: iload #21
    //   12584: bipush #8
    //   12586: ishl
    //   12587: ixor
    //   12588: istore #22
    //   12590: iload #22
    //   12592: iconst_1
    //   12593: ishl
    //   12594: iload #22
    //   12596: bipush #31
    //   12598: iushr
    //   12599: iconst_1
    //   12600: iand
    //   12601: ior
    //   12602: istore #22
    //   12604: iload #23
    //   12606: iload #22
    //   12608: ixor
    //   12609: ldc -1431655766
    //   12611: iand
    //   12612: istore #21
    //   12614: iload #23
    //   12616: iload #21
    //   12618: ixor
    //   12619: istore #23
    //   12621: iload #22
    //   12623: iload #21
    //   12625: ixor
    //   12626: istore #22
    //   12628: iload #23
    //   12630: iconst_1
    //   12631: ishl
    //   12632: iload #23
    //   12634: bipush #31
    //   12636: iushr
    //   12637: iconst_1
    //   12638: iand
    //   12639: ior
    //   12640: istore #23
    //   12642: iconst_0
    //   12643: istore #24
    //   12645: iload #24
    //   12647: bipush #8
    //   12649: if_icmpge -> 12987
    //   12652: iload #22
    //   12654: bipush #28
    //   12656: ishl
    //   12657: iload #22
    //   12659: iconst_4
    //   12660: iushr
    //   12661: ior
    //   12662: istore #21
    //   12664: iload #21
    //   12666: aload #5
    //   12668: iload #25
    //   12670: iinc #25, 1
    //   12673: iaload
    //   12674: ixor
    //   12675: istore #21
    //   12677: aload #12
    //   12679: iload #21
    //   12681: bipush #63
    //   12683: iand
    //   12684: iaload
    //   12685: istore #20
    //   12687: iload #20
    //   12689: aload #10
    //   12691: iload #21
    //   12693: bipush #8
    //   12695: iushr
    //   12696: bipush #63
    //   12698: iand
    //   12699: iaload
    //   12700: ior
    //   12701: istore #20
    //   12703: iload #20
    //   12705: aload #8
    //   12707: iload #21
    //   12709: bipush #16
    //   12711: iushr
    //   12712: bipush #63
    //   12714: iand
    //   12715: iaload
    //   12716: ior
    //   12717: istore #20
    //   12719: iload #20
    //   12721: aload #6
    //   12723: iload #21
    //   12725: bipush #24
    //   12727: iushr
    //   12728: bipush #63
    //   12730: iand
    //   12731: iaload
    //   12732: ior
    //   12733: istore #20
    //   12735: iload #22
    //   12737: aload #5
    //   12739: iload #25
    //   12741: iinc #25, 1
    //   12744: iaload
    //   12745: ixor
    //   12746: istore #21
    //   12748: iload #20
    //   12750: aload #13
    //   12752: iload #21
    //   12754: bipush #63
    //   12756: iand
    //   12757: iaload
    //   12758: ior
    //   12759: istore #20
    //   12761: iload #20
    //   12763: aload #11
    //   12765: iload #21
    //   12767: bipush #8
    //   12769: iushr
    //   12770: bipush #63
    //   12772: iand
    //   12773: iaload
    //   12774: ior
    //   12775: istore #20
    //   12777: iload #20
    //   12779: aload #9
    //   12781: iload #21
    //   12783: bipush #16
    //   12785: iushr
    //   12786: bipush #63
    //   12788: iand
    //   12789: iaload
    //   12790: ior
    //   12791: istore #20
    //   12793: iload #20
    //   12795: aload #7
    //   12797: iload #21
    //   12799: bipush #24
    //   12801: iushr
    //   12802: bipush #63
    //   12804: iand
    //   12805: iaload
    //   12806: ior
    //   12807: istore #20
    //   12809: iload #23
    //   12811: iload #20
    //   12813: ixor
    //   12814: istore #23
    //   12816: iload #23
    //   12818: bipush #28
    //   12820: ishl
    //   12821: iload #23
    //   12823: iconst_4
    //   12824: iushr
    //   12825: ior
    //   12826: istore #21
    //   12828: iload #21
    //   12830: aload #5
    //   12832: iload #25
    //   12834: iinc #25, 1
    //   12837: iaload
    //   12838: ixor
    //   12839: istore #21
    //   12841: aload #12
    //   12843: iload #21
    //   12845: bipush #63
    //   12847: iand
    //   12848: iaload
    //   12849: istore #20
    //   12851: iload #20
    //   12853: aload #10
    //   12855: iload #21
    //   12857: bipush #8
    //   12859: iushr
    //   12860: bipush #63
    //   12862: iand
    //   12863: iaload
    //   12864: ior
    //   12865: istore #20
    //   12867: iload #20
    //   12869: aload #8
    //   12871: iload #21
    //   12873: bipush #16
    //   12875: iushr
    //   12876: bipush #63
    //   12878: iand
    //   12879: iaload
    //   12880: ior
    //   12881: istore #20
    //   12883: iload #20
    //   12885: aload #6
    //   12887: iload #21
    //   12889: bipush #24
    //   12891: iushr
    //   12892: bipush #63
    //   12894: iand
    //   12895: iaload
    //   12896: ior
    //   12897: istore #20
    //   12899: iload #23
    //   12901: aload #5
    //   12903: iload #25
    //   12905: iinc #25, 1
    //   12908: iaload
    //   12909: ixor
    //   12910: istore #21
    //   12912: iload #20
    //   12914: aload #13
    //   12916: iload #21
    //   12918: bipush #63
    //   12920: iand
    //   12921: iaload
    //   12922: ior
    //   12923: istore #20
    //   12925: iload #20
    //   12927: aload #11
    //   12929: iload #21
    //   12931: bipush #8
    //   12933: iushr
    //   12934: bipush #63
    //   12936: iand
    //   12937: iaload
    //   12938: ior
    //   12939: istore #20
    //   12941: iload #20
    //   12943: aload #9
    //   12945: iload #21
    //   12947: bipush #16
    //   12949: iushr
    //   12950: bipush #63
    //   12952: iand
    //   12953: iaload
    //   12954: ior
    //   12955: istore #20
    //   12957: iload #20
    //   12959: aload #7
    //   12961: iload #21
    //   12963: bipush #24
    //   12965: iushr
    //   12966: bipush #63
    //   12968: iand
    //   12969: iaload
    //   12970: ior
    //   12971: istore #20
    //   12973: iload #22
    //   12975: iload #20
    //   12977: ixor
    //   12978: istore #22
    //   12980: iinc #24, 1
    //   12983: iload_2
    //   12984: ifne -> 12645
    //   12987: iload #22
    //   12989: bipush #31
    //   12991: ishl
    //   12992: iload #22
    //   12994: iconst_1
    //   12995: iushr
    //   12996: ior
    //   12997: istore #22
    //   12999: iload #23
    //   13001: iload #22
    //   13003: ixor
    //   13004: ldc -1431655766
    //   13006: iand
    //   13007: istore #21
    //   13009: iload #23
    //   13011: iload #21
    //   13013: ixor
    //   13014: istore #23
    //   13016: iload #22
    //   13018: iload #21
    //   13020: ixor
    //   13021: istore #22
    //   13023: iload #23
    //   13025: bipush #31
    //   13027: ishl
    //   13028: iload #23
    //   13030: iconst_1
    //   13031: iushr
    //   13032: ior
    //   13033: istore #23
    //   13035: iload #23
    //   13037: bipush #8
    //   13039: iushr
    //   13040: iload #22
    //   13042: ixor
    //   13043: ldc 16711935
    //   13045: iand
    //   13046: istore #21
    //   13048: iload #22
    //   13050: iload #21
    //   13052: ixor
    //   13053: istore #22
    //   13055: iload #23
    //   13057: iload #21
    //   13059: bipush #8
    //   13061: ishl
    //   13062: ixor
    //   13063: istore #23
    //   13065: iload #23
    //   13067: iconst_2
    //   13068: iushr
    //   13069: iload #22
    //   13071: ixor
    //   13072: ldc 858993459
    //   13074: iand
    //   13075: istore #21
    //   13077: iload #22
    //   13079: iload #21
    //   13081: ixor
    //   13082: istore #22
    //   13084: iload #23
    //   13086: iload #21
    //   13088: iconst_2
    //   13089: ishl
    //   13090: ixor
    //   13091: istore #23
    //   13093: iload #22
    //   13095: bipush #16
    //   13097: iushr
    //   13098: iload #23
    //   13100: ixor
    //   13101: ldc 65535
    //   13103: iand
    //   13104: istore #21
    //   13106: iload #23
    //   13108: iload #21
    //   13110: ixor
    //   13111: istore #23
    //   13113: iload #22
    //   13115: iload #21
    //   13117: bipush #16
    //   13119: ishl
    //   13120: ixor
    //   13121: istore #22
    //   13123: iload #22
    //   13125: iconst_4
    //   13126: iushr
    //   13127: iload #23
    //   13129: ixor
    //   13130: ldc 252645135
    //   13132: iand
    //   13133: istore #21
    //   13135: iload #23
    //   13137: iload #21
    //   13139: ixor
    //   13140: istore #23
    //   13142: iload #22
    //   13144: iload #21
    //   13146: iconst_4
    //   13147: ishl
    //   13148: ixor
    //   13149: istore #22
    //   13151: aload #15
    //   13153: iconst_0
    //   13154: iload #22
    //   13156: iastore
    //   13157: aload #15
    //   13159: iconst_1
    //   13160: iload #23
    //   13162: iastore
    //   13163: iload #18
    //   13165: bipush #8
    //   13167: imul
    //   13168: istore #26
    //   13170: iconst_0
    //   13171: istore #27
    //   13173: iload #27
    //   13175: iconst_2
    //   13176: if_icmpge -> 13265
    //   13179: aload #16
    //   13181: iload #26
    //   13183: iload #27
    //   13185: iconst_4
    //   13186: imul
    //   13187: iadd
    //   13188: aload #15
    //   13190: iload #27
    //   13192: iaload
    //   13193: bipush #24
    //   13195: iushr
    //   13196: i2b
    //   13197: bastore
    //   13198: aload #16
    //   13200: iload #26
    //   13202: iload #27
    //   13204: iconst_4
    //   13205: imul
    //   13206: iadd
    //   13207: iconst_1
    //   13208: iadd
    //   13209: aload #15
    //   13211: iload #27
    //   13213: iaload
    //   13214: bipush #16
    //   13216: iushr
    //   13217: i2b
    //   13218: bastore
    //   13219: aload #16
    //   13221: iload #26
    //   13223: iload #27
    //   13225: iconst_4
    //   13226: imul
    //   13227: iadd
    //   13228: iconst_2
    //   13229: iadd
    //   13230: aload #15
    //   13232: iload #27
    //   13234: iaload
    //   13235: bipush #8
    //   13237: iushr
    //   13238: i2b
    //   13239: bastore
    //   13240: aload #16
    //   13242: iload #26
    //   13244: iload #27
    //   13246: iconst_4
    //   13247: imul
    //   13248: iadd
    //   13249: iconst_3
    //   13250: iadd
    //   13251: aload #15
    //   13253: iload #27
    //   13255: iaload
    //   13256: i2b
    //   13257: bastore
    //   13258: iinc #27, 1
    //   13261: iload_2
    //   13262: ifne -> 13173
    //   13265: iinc #18, 1
    //   13268: iload_2
    //   13269: ifne -> 12354
    //   13272: aload #16
    //   13274: aload #16
    //   13276: arraylength
    //   13277: iconst_1
    //   13278: isub
    //   13279: baload
    //   13280: istore #18
    //   13282: aload #16
    //   13284: arraylength
    //   13285: iload #18
    //   13287: isub
    //   13288: newarray byte
    //   13290: astore #4
    //   13292: aload #16
    //   13294: arraylength
    //   13295: aload #4
    //   13297: arraylength
    //   13298: if_icmpge -> 13322
    //   13301: new java/lang/Exception
    //   13304: dup
    //   13305: sipush #6002
    //   13308: sipush #-30869
    //   13311: invokestatic a : (II)Ljava/lang/String;
    //   13314: invokespecial <init> : (Ljava/lang/String;)V
    //   13317: athrow
    //   13318: invokestatic a : (Ljava/lang/Throwable;)Ljava/lang/Throwable;
    //   13321: athrow
    //   13322: iconst_0
    //   13323: istore #19
    //   13325: iload #19
    //   13327: aload #4
    //   13329: arraylength
    //   13330: if_icmpge -> 13350
    //   13333: aload #4
    //   13335: iload #19
    //   13337: aload #16
    //   13339: iload #19
    //   13341: baload
    //   13342: bastore
    //   13343: iinc #19, 1
    //   13346: iload_2
    //   13347: ifne -> 13325
    //   13350: getstatic burp/Zzmu.ZF : Ljava/lang/String;
    //   13353: getstatic burp/Zsxh.Zk : Ljava/lang/Object;
    //   13356: checkcast java/math/BigInteger
    //   13359: invokevirtual intValue : ()I
    //   13362: bipush #32
    //   13364: irem
    //   13365: invokestatic abs : (I)I
    //   13368: invokevirtual charAt : (I)C
    //   13371: getstatic burp/Zg4d.ZE : Ljava/lang/String;
    //   13374: getstatic burp/Zmyg.Zj : Ljava/lang/Object;
    //   13377: checkcast java/math/BigInteger
    //   13380: invokevirtual intValue : ()I
    //   13383: bipush #32
    //   13385: irem
    //   13386: invokestatic abs : (I)I
    //   13389: invokevirtual charAt : (I)C
    //   13392: if_icmpgt -> 13499
    //   13395: getstatic burp/Zmsn.ZD : Ljava/lang/String;
    //   13398: getstatic burp/Zs_3.ZZ : Ljava/lang/Object;
    //   13401: checkcast java/math/BigInteger
    //   13404: invokevirtual intValue : ()I
    //   13407: bipush #32
    //   13409: irem
    //   13410: invokestatic abs : (I)I
    //   13413: invokevirtual charAt : (I)C
    //   13416: getstatic burp/Zr48.ZG : Ljava/lang/String;
    //   13419: getstatic burp/Zt3f.Zp : Ljava/lang/Object;
    //   13422: checkcast java/math/BigInteger
    //   13425: invokevirtual intValue : ()I
    //   13428: bipush #32
    //   13430: irem
    //   13431: invokestatic abs : (I)I
    //   13434: invokevirtual charAt : (I)C
    //   13437: if_icmple -> 13499
    //   13440: goto -> 13447
    //   13443: invokestatic a : (Ljava/lang/Throwable;)Ljava/lang/Throwable;
    //   13446: athrow
    //   13447: getstatic burp/Zb8y.Zn : Ljava/lang/String;
    //   13450: getstatic burp/Ztex.Z_ : Ljava/lang/Object;
    //   13453: checkcast java/math/BigInteger
    //   13456: invokevirtual intValue : ()I
    //   13459: bipush #32
    //   13461: irem
    //   13462: invokestatic abs : (I)I
    //   13465: invokevirtual charAt : (I)C
    //   13468: getstatic burp/Zs4z.Zs : Ljava/lang/String;
    //   13471: getstatic burp/Zxzz.ZM : Ljava/lang/Object;
    //   13474: checkcast java/math/BigInteger
    //   13477: invokevirtual intValue : ()I
    //   13480: bipush #32
    //   13482: irem
    //   13483: invokestatic abs : (I)I
    //   13486: invokevirtual charAt : (I)C
    //   13489: if_icmple -> 13507
    //   13492: goto -> 13499
    //   13495: invokestatic a : (Ljava/lang/Throwable;)Ljava/lang/Throwable;
    //   13498: athrow
    //   13499: iconst_1
    //   13500: goto -> 13508
    //   13503: invokestatic a : (Ljava/lang/Throwable;)Ljava/lang/Throwable;
    //   13506: athrow
    //   13507: iconst_0
    //   13508: ireturn
    //   13509: astore_3
    //   13510: new java/lang/Exception
    //   13513: dup
    //   13514: aload_3
    //   13515: invokevirtual getMessage : ()Ljava/lang/String;
    //   13518: invokespecial <init> : (Ljava/lang/String;)V
    //   13521: athrow
    // Exception table:
    //   from	to	target	type
    //   4	13508	13509	java/lang/Throwable
    //   8715	8729	8729	java/lang/Throwable
    //   8740	8753	8756	java/lang/Throwable
    //   8745	8768	8771	java/lang/Throwable
    //   8760	8786	8789	java/lang/Throwable
    //   8775	8816	8819	java/lang/Throwable
    //   8879	8906	8909	java/lang/Throwable
    //   8896	8927	8930	java/lang/Throwable
    //   8913	8957	8960	java/lang/Throwable
    //   8934	8968	8968	java/lang/Throwable
    //   8979	8995	8998	java/lang/Throwable
    //   12304	12329	12329	java/lang/Throwable
    //   13292	13318	13318	java/lang/Throwable
    //   13350	13440	13443	java/lang/Throwable
    //   13395	13492	13495	java/lang/Throwable
    //   13447	13503	13503	java/lang/Throwable
  }
  
  static void ZG(Object paramObject) {
    Zzyr.Z_ = a(6009, 31331);
    Zzyr.Za = new BigInteger(a(6004, -18937));
    boolean bool = Zt2e.ZK();
    try {
      try {
        if (Zm7x.ZP.charAt(Math.abs(((BigInteger)Zgva.Zr).intValue() % 32)) <= Zsbt.ZX.charAt(Math.abs(((BigInteger)Zkm0.ZI).intValue() % 32))) {
          try {
            Zrs0.ZS(Class.forName(a(6005, 13894)));
            if (bool)
              Zs75.ZC(Class.forName(a(6006, -31960))); 
          } catch (Throwable throwable) {
            throw a(null);
          } 
          return;
        } 
      } catch (Throwable throwable) {
        throw a(null);
      } 
      Zs75.ZC(Class.forName(a(6006, -31960)));
    } catch (Throwable throwable) {}
  }
  
  static {
    // Byte code:
    //   0: bipush #10
    //   2: anewarray java/lang/String
    //   5: astore #5
    //   7: iconst_0
    //   8: istore_3
    //   9: ldc 'm0yN4SjoBNw4\\b }6 5lES"~{\\f%xv,}:MZ!yZw>H dJ%H4&b$h_jT~->QSWI$R&\\tET\\t?y'*1|\\tD07'
    //   11: dup
    //   12: astore_2
    //   13: invokevirtual length : ()I
    //   16: istore #4
    //   18: iconst_4
    //   19: istore_1
    //   20: iconst_m1
    //   21: istore_0
    //   22: bipush #104
    //   24: iinc #0, 1
    //   27: aload_2
    //   28: iload_0
    //   29: dup
    //   30: iload_1
    //   31: iadd
    //   32: invokevirtual substring : (II)Ljava/lang/String;
    //   35: iconst_m1
    //   36: goto -> 142
    //   39: aload #5
    //   41: swap
    //   42: iload_3
    //   43: iinc #3, 1
    //   46: swap
    //   47: aastore
    //   48: iload_0
    //   49: iload_1
    //   50: iadd
    //   51: dup
    //   52: istore_0
    //   53: iload #4
    //   55: if_icmpge -> 67
    //   58: aload_2
    //   59: iload_0
    //   60: invokevirtual charAt : (I)C
    //   63: istore_1
    //   64: goto -> 22
    //   67: ldc 'A]:K Z9z=R/JG`'
    //   69: dup
    //   70: astore_2
    //   71: invokevirtual length : ()I
    //   74: istore #4
    //   76: bipush #9
    //   78: istore_1
    //   79: iconst_m1
    //   80: istore_0
    //   81: bipush #95
    //   83: iinc #0, 1
    //   86: aload_2
    //   87: iload_0
    //   88: dup
    //   89: iload_1
    //   90: iadd
    //   91: invokevirtual substring : (II)Ljava/lang/String;
    //   94: iconst_0
    //   95: goto -> 142
    //   98: aload #5
    //   100: swap
    //   101: iload_3
    //   102: iinc #3, 1
    //   105: swap
    //   106: aastore
    //   107: iload_0
    //   108: iload_1
    //   109: iadd
    //   110: dup
    //   111: istore_0
    //   112: iload #4
    //   114: if_icmpge -> 126
    //   117: aload_2
    //   118: iload_0
    //   119: invokevirtual charAt : (I)C
    //   122: istore_1
    //   123: goto -> 81
    //   126: aload #5
    //   128: putstatic burp/Zz0w.a : [Ljava/lang/String;
    //   131: bipush #10
    //   133: anewarray java/lang/String
    //   136: putstatic burp/Zz0w.b : [Ljava/lang/String;
    //   139: goto -> 300
    //   142: dup_x2
    //   143: pop
    //   144: invokevirtual toCharArray : ()[C
    //   147: dup_x1
    //   148: arraylength
    //   149: dup_x2
    //   150: pop
    //   151: iconst_0
    //   152: istore #6
    //   154: dup2_x1
    //   155: pop2
    //   156: dup_x2
    //   157: iconst_1
    //   158: if_icmpgt -> 260
    //   161: dup2
    //   162: swap
    //   163: iload #6
    //   165: dup2_x1
    //   166: caload
    //   167: swap
    //   168: iload #6
    //   170: bipush #7
    //   172: irem
    //   173: tableswitch default -> 242, 0 -> 212, 1 -> 217, 2 -> 222, 3 -> 227, 4 -> 232, 5 -> 237
    //   212: bipush #35
    //   214: goto -> 244
    //   217: bipush #21
    //   219: goto -> 244
    //   222: bipush #106
    //   224: goto -> 244
    //   227: bipush #100
    //   229: goto -> 244
    //   232: bipush #10
    //   234: goto -> 244
    //   237: bipush #24
    //   239: goto -> 244
    //   242: bipush #90
    //   244: ixor
    //   245: ixor
    //   246: i2c
    //   247: castore
    //   248: iinc #6, 1
    //   251: dup
    //   252: ifne -> 260
    //   255: dup2
    //   256: dup_x1
    //   257: goto -> 165
    //   260: dup2_x1
    //   261: pop2
    //   262: dup_x2
    //   263: iload #6
    //   265: if_icmpgt -> 161
    //   268: pop
    //   269: new java/lang/String
    //   272: dup_x1
    //   273: swap
    //   274: invokespecial <init> : ([C)V
    //   277: invokevirtual intern : ()Ljava/lang/String;
    //   280: swap
    //   281: pop
    //   282: swap
    //   283: tableswitch default -> 39, 0 -> 98
    //   300: sipush #6003
    //   303: sipush #11399
    //   306: invokestatic a : (II)Ljava/lang/String;
    //   309: putstatic burp/Zz0w.ZO : Ljava/lang/String;
    //   312: new java/math/BigInteger
    //   315: dup
    //   316: iconst_1
    //   317: bipush #32
    //   319: newarray byte
    //   321: dup
    //   322: iconst_0
    //   323: bipush #55
    //   325: bastore
    //   326: dup
    //   327: iconst_1
    //   328: bipush #74
    //   330: bastore
    //   331: dup
    //   332: iconst_2
    //   333: bipush #104
    //   335: bastore
    //   336: dup
    //   337: iconst_3
    //   338: bipush #-64
    //   340: bastore
    //   341: dup
    //   342: iconst_4
    //   343: bipush #-77
    //   345: bastore
    //   346: dup
    //   347: iconst_5
    //   348: bipush #28
    //   350: bastore
    //   351: dup
    //   352: bipush #6
    //   354: bipush #-76
    //   356: bastore
    //   357: dup
    //   358: bipush #7
    //   360: bipush #-97
    //   362: bastore
    //   363: dup
    //   364: bipush #8
    //   366: bipush #-123
    //   368: bastore
    //   369: dup
    //   370: bipush #9
    //   372: bipush #22
    //   374: bastore
    //   375: dup
    //   376: bipush #10
    //   378: bipush #-84
    //   380: bastore
    //   381: dup
    //   382: bipush #11
    //   384: bipush #94
    //   386: bastore
    //   387: dup
    //   388: bipush #12
    //   390: bipush #-128
    //   392: bastore
    //   393: dup
    //   394: bipush #13
    //   396: bipush #75
    //   398: bastore
    //   399: dup
    //   400: bipush #14
    //   402: bipush #98
    //   404: bastore
    //   405: dup
    //   406: bipush #15
    //   408: bipush #-115
    //   410: bastore
    //   411: dup
    //   412: bipush #16
    //   414: bipush #-120
    //   416: bastore
    //   417: dup
    //   418: bipush #17
    //   420: iconst_3
    //   421: bastore
    //   422: dup
    //   423: bipush #18
    //   425: bipush #124
    //   427: bastore
    //   428: dup
    //   429: bipush #19
    //   431: bipush #-92
    //   433: bastore
    //   434: dup
    //   435: bipush #20
    //   437: bipush #-76
    //   439: bastore
    //   440: dup
    //   441: bipush #21
    //   443: bipush #-87
    //   445: bastore
    //   446: dup
    //   447: bipush #22
    //   449: bipush #-60
    //   451: bastore
    //   452: dup
    //   453: bipush #23
    //   455: iconst_4
    //   456: bastore
    //   457: dup
    //   458: bipush #24
    //   460: bipush #12
    //   462: bastore
    //   463: dup
    //   464: bipush #25
    //   466: bipush #69
    //   468: bastore
    //   469: dup
    //   470: bipush #26
    //   472: bipush #-77
    //   474: bastore
    //   475: dup
    //   476: bipush #27
    //   478: bipush #-102
    //   480: bastore
    //   481: dup
    //   482: bipush #28
    //   484: bipush #-67
    //   486: bastore
    //   487: dup
    //   488: bipush #29
    //   490: bipush #126
    //   492: bastore
    //   493: dup
    //   494: bipush #30
    //   496: bipush #58
    //   498: bastore
    //   499: dup
    //   500: bipush #31
    //   502: bipush #-4
    //   504: bastore
    //   505: invokespecial <init> : (I[B)V
    //   508: putstatic burp/Zz0w.ZF : Ljava/lang/Object;
    //   511: return
  }
  
  private static Throwable a(Throwable paramThrowable) {
    return paramThrowable;
  }
  
  private static String a(int paramInt1, int paramInt2) {
    int i = (paramInt1 ^ 0x1770) & 0xFFFF;
    if (b[i] == null) {
      char[] arrayOfChar = a[i].toCharArray();
      switch (arrayOfChar[0] & 0xFF) {
        case 0:
        
        case 1:
        
        case 2:
        
        case 3:
        
        case 4:
        
        case 5:
        
        case 6:
        
        case 7:
        
        case 8:
        
        case 9:
        
        case 10:
        
        case 11:
        
        case 12:
        
        case 13:
        
        case 14:
        
        case 15:
        
        case 16:
        
        case 17:
        
        case 18:
        
        case 19:
        
        case 20:
        
        case 21:
        
        case 22:
        
        case 23:
        
        case 24:
        
        case 25:
        
        case 26:
        
        case 27:
        
        case 28:
        
        case 29:
        
        case 30:
        
        case 31:
        
        case 32:
        
        case 33:
        
        case 34:
        
        case 35:
        
        case 36:
        
        case 37:
        
        case 38:
        
        case 39:
        
        case 40:
        
        case 41:
        
        case 42:
        
        case 43:
        
        case 44:
        
        case 45:
        
        case 46:
        
        case 47:
        
        case 48:
        
        case 49:
        
        case 50:
        
        case 51:
        
        case 52:
        
        case 53:
        
        case 54:
        
        case 55:
        
        case 56:
        
        case 57:
        
        case 58:
        
        case 59:
        
        case 60:
        
        case 61:
        
        case 62:
        
        case 63:
        
        case 64:
        
        case 65:
        
        case 66:
        
        case 67:
        
        case 68:
        
        case 69:
        
        case 70:
        
        case 71:
        
        case 72:
        
        case 73:
        
        case 74:
        
        case 75:
        
        case 76:
        
        case 77:
        
        case 78:
        
        case 79:
        
        case 80:
        
        case 81:
        
        case 82:
        
        case 83:
        
        case 84:
        
        case 85:
        
        case 86:
        
        case 87:
        
        case 88:
        
        case 89:
        
        case 90:
        
        case 91:
        
        case 92:
        
        case 93:
        
        case 94:
        
        case 95:
        
        case 96:
        
        case 97:
        
        case 98:
        
        case 99:
        
        case 100:
        
        case 101:
        
        case 102:
        
        case 103:
        
        case 104:
        
        case 105:
        
        case 106:
        
        case 107:
        
        case 108:
        
        case 109:
        
        case 110:
        
        case 111:
        
        case 112:
        
        case 113:
        
        case 114:
        
        case 115:
        
        case 116:
        
        case 117:
        
        case 118:
        
        case 119:
        
        case 120:
        
        case 121:
        
        case 122:
        
        case 123:
        
        case 124:
        
        case 125:
        
        case 126:
        
        case 127:
        
        case 128:
        
        case 129:
        
        case 130:
        
        case 131:
        
        case 132:
        
        case 133:
        
        case 134:
        
        case 135:
        
        case 136:
        
        case 137:
        
        case 138:
        
        case 139:
        
        case 140:
        
        case 141:
        
        case 142:
        
        case 143:
        
        case 144:
        
        case 145:
        
        case 146:
        
        case 147:
        
        case 148:
        
        case 149:
        
        case 150:
        
        case 151:
        
        case 152:
        
        case 153:
        
        case 154:
        
        case 155:
        
        case 156:
        
        case 157:
        
        case 158:
        
        case 159:
        
        case 160:
        
        case 161:
        
        case 162:
        
        case 163:
        
        case 164:
        
        case 165:
        
        case 166:
        
        case 167:
        
        case 168:
        
        case 169:
        
        case 170:
        
        case 171:
        
        case 172:
        
        case 173:
        
        case 174:
        
        case 175:
        
        case 176:
        
        case 177:
        
        case 178:
        
        case 179:
        
        case 180:
        
        case 181:
        
        case 182:
        
        case 183:
        
        case 184:
        
        case 185:
        
        case 186:
        
        case 187:
        
        case 188:
        
        case 189:
        
        case 190:
        
        case 191:
        
        case 192:
        
        case 193:
        
        case 194:
        
        case 195:
        
        case 196:
        
        case 197:
        
        case 198:
        
        case 199:
        
        case 200:
        
        case 201:
        
        case 202:
        
        case 203:
        
        case 204:
        
        case 205:
        
        case 206:
        
        case 207:
        
        case 208:
        
        case 209:
        
        case 210:
        
        case 211:
        
        case 212:
        
        case 213:
        
        case 214:
        
        case 215:
        
        case 216:
        
        case 217:
        
        case 218:
        
        case 219:
        
        case 220:
        
        case 221:
        
        case 222:
        
        case 223:
        
        case 224:
        
        case 225:
        
        case 226:
        
        case 227:
        
        case 228:
        
        case 229:
        
        case 230:
        
        case 231:
        
        case 232:
        
        case 233:
        
        case 234:
        
        case 235:
        
        case 236:
        
        case 237:
        
        case 238:
        
        case 239:
        
        case 240:
        
        case 241:
        
        case 242:
        
        case 243:
        
        case 244:
        
        case 245:
        
        case 246:
        
        case 247:
        
        case 248:
        
        case 249:
        
        case 250:
        
        case 251:
        
        case 252:
        
        case 253:
        
        case 254:
        
        default:
          break;
      } 
      char c = '';
      int j = (paramInt2 & 0xFF) - c;
      if (j < 0)
        j += 256; 
      int k = ((paramInt2 & 0xFFFF) >>> 8) - c;
      if (k < 0)
        k += 256; 
      for (byte b = 0; b < arrayOfChar.length; b++) {
        int m = b % 2;
        if (m == 0) {
          arrayOfChar[b] = (char)(arrayOfChar[b] ^ j);
          j = ((j >>> 3 | j << 5) ^ arrayOfChar[b]) & 0xFF;
        } else {
          arrayOfChar[b] = (char)(arrayOfChar[b] ^ k);
          k = ((k >>> 3 | k << 5) ^ arrayOfChar[b]) & 0xFF;
        } 
      } 
      b[i] = (new String(arrayOfChar)).intern();
    } 
    return b[i];
  }
}


/* Location:              C:\Program Files\BurpSuitePro\burpsuite_pro.jar!\burp\Zz0w.class
 * Java compiler version: 21 (65.0)
 * JD-Core Version:       1.1.3
 */