package burp;

import java.math.BigInteger;

class Zz0y extends ClassLoader {
  static Object Zp;
  
  static String ZM;
  
  private static final String[] a;
  
  private static final String[] b;
  
  static boolean ZJ(Object[] paramArrayOfObject, Object paramObject) throws Throwable {
    // Byte code:
    //   0: invokestatic ZK : ()Z
    //   3: istore_2
    //   4: getstatic burp/Zxxf.ZZ : Ljava/lang/Object;
    //   7: checkcast java/math/BigInteger
    //   10: invokevirtual toByteArray : ()[B
    //   13: astore_3
    //   14: bipush #32
    //   16: newarray int
    //   18: dup
    //   19: iconst_0
    //   20: ldc 943331329
    //   22: iastore
    //   23: dup
    //   24: iconst_1
    //   25: ldc 170788368
    //   27: iastore
    //   28: dup
    //   29: iconst_2
    //   30: ldc 1008414755
    //   32: iastore
    //   33: dup
    //   34: iconst_3
    //   35: ldc 187049985
    //   37: iastore
    //   38: dup
    //   39: iconst_4
    //   40: ldc 1010368540
    //   42: iastore
    //   43: dup
    //   44: iconst_5
    //   45: ldc 220604441
    //   47: iastore
    //   48: dup
    //   49: bipush #6
    //   51: ldc 940377620
    //   53: iastore
    //   54: dup
    //   55: bipush #7
    //   57: ldc 255209728
    //   59: iastore
    //   60: dup
    //   61: bipush #8
    //   63: ldc 689771012
    //   65: iastore
    //   66: dup
    //   67: bipush #9
    //   69: ldc 221709344
    //   71: iastore
    //   72: dup
    //   73: bipush #10
    //   75: ldc 957157408
    //   77: iastore
    //   78: dup
    //   79: bipush #11
    //   81: ldc 892536332
    //   83: iastore
    //   84: dup
    //   85: bipush #12
    //   87: ldc 722417666
    //   89: iastore
    //   90: dup
    //   91: bipush #13
    //   93: ldc 1026621720
    //   95: iastore
    //   96: dup
    //   97: bipush #14
    //   99: ldc 655302664
    //   101: iastore
    //   102: dup
    //   103: bipush #15
    //   105: ldc 890966315
    //   107: iastore
    //   108: dup
    //   109: bipush #16
    //   111: ldc 187632156
    //   113: iastore
    //   114: dup
    //   115: bipush #17
    //   117: ldc 874189824
    //   119: iastore
    //   120: dup
    //   121: bipush #18
    //   123: ldc 254150144
    //   125: iastore
    //   126: dup
    //   127: bipush #19
    //   129: ldc 924386310
    //   131: iastore
    //   132: dup
    //   133: bipush #20
    //   135: ldc 121057538
    //   137: iastore
    //   138: dup
    //   139: bipush #21
    //   141: ldc 840500228
    //   143: iastore
    //   144: dup
    //   145: bipush #22
    //   147: ldc 389160971
    //   149: iastore
    //   150: dup
    //   151: bipush #23
    //   153: ldc 907870729
    //   155: iastore
    //   156: dup
    //   157: bipush #24
    //   159: ldc 389426184
    //   161: iastore
    //   162: dup
    //   163: bipush #25
    //   165: ldc 973875457
    //   167: iastore
    //   168: dup
    //   169: bipush #26
    //   171: ldc 372376604
    //   173: iastore
    //   174: dup
    //   175: bipush #27
    //   177: ldc 707731490
    //   179: iastore
    //   180: dup
    //   181: bipush #28
    //   183: ldc 1043334948
    //   185: iastore
    //   186: dup
    //   187: bipush #29
    //   189: ldc 439222784
    //   191: iastore
    //   192: dup
    //   193: bipush #30
    //   195: ldc 876216579
    //   197: iastore
    //   198: dup
    //   199: bipush #31
    //   201: ldc 455999525
    //   203: iastore
    //   204: astore #5
    //   206: bipush #8
    //   208: aload_3
    //   209: arraylength
    //   210: bipush #8
    //   212: irem
    //   213: isub
    //   214: istore #6
    //   216: aload_3
    //   217: arraylength
    //   218: iload #6
    //   220: iadd
    //   221: newarray byte
    //   223: astore #7
    //   225: iconst_0
    //   226: istore #8
    //   228: iload #8
    //   230: aload_3
    //   231: arraylength
    //   232: if_icmpge -> 251
    //   235: aload #7
    //   237: iload #8
    //   239: aload_3
    //   240: iload #8
    //   242: baload
    //   243: bastore
    //   244: iinc #8, 1
    //   247: iload_2
    //   248: ifeq -> 228
    //   251: aload_3
    //   252: arraylength
    //   253: istore #8
    //   255: iload #8
    //   257: aload #7
    //   259: arraylength
    //   260: if_icmpge -> 278
    //   263: aload #7
    //   265: iload #8
    //   267: iload #6
    //   269: i2b
    //   270: bastore
    //   271: iinc #8, 1
    //   274: iload_2
    //   275: ifeq -> 255
    //   278: aload #7
    //   280: astore_3
    //   281: bipush #64
    //   283: newarray int
    //   285: dup
    //   286: iconst_0
    //   287: ldc 16843776
    //   289: iastore
    //   290: dup
    //   291: iconst_1
    //   292: iconst_0
    //   293: iastore
    //   294: dup
    //   295: iconst_2
    //   296: ldc 65536
    //   298: iastore
    //   299: dup
    //   300: iconst_3
    //   301: ldc 16843780
    //   303: iastore
    //   304: dup
    //   305: iconst_4
    //   306: ldc 16842756
    //   308: iastore
    //   309: dup
    //   310: iconst_5
    //   311: ldc 66564
    //   313: iastore
    //   314: dup
    //   315: bipush #6
    //   317: iconst_4
    //   318: iastore
    //   319: dup
    //   320: bipush #7
    //   322: ldc 65536
    //   324: iastore
    //   325: dup
    //   326: bipush #8
    //   328: sipush #1024
    //   331: iastore
    //   332: dup
    //   333: bipush #9
    //   335: ldc 16843776
    //   337: iastore
    //   338: dup
    //   339: bipush #10
    //   341: ldc 16843780
    //   343: iastore
    //   344: dup
    //   345: bipush #11
    //   347: sipush #1024
    //   350: iastore
    //   351: dup
    //   352: bipush #12
    //   354: ldc 16778244
    //   356: iastore
    //   357: dup
    //   358: bipush #13
    //   360: ldc 16842756
    //   362: iastore
    //   363: dup
    //   364: bipush #14
    //   366: ldc 16777216
    //   368: iastore
    //   369: dup
    //   370: bipush #15
    //   372: iconst_4
    //   373: iastore
    //   374: dup
    //   375: bipush #16
    //   377: sipush #1028
    //   380: iastore
    //   381: dup
    //   382: bipush #17
    //   384: ldc 16778240
    //   386: iastore
    //   387: dup
    //   388: bipush #18
    //   390: ldc 16778240
    //   392: iastore
    //   393: dup
    //   394: bipush #19
    //   396: ldc 66560
    //   398: iastore
    //   399: dup
    //   400: bipush #20
    //   402: ldc 66560
    //   404: iastore
    //   405: dup
    //   406: bipush #21
    //   408: ldc 16842752
    //   410: iastore
    //   411: dup
    //   412: bipush #22
    //   414: ldc 16842752
    //   416: iastore
    //   417: dup
    //   418: bipush #23
    //   420: ldc 16778244
    //   422: iastore
    //   423: dup
    //   424: bipush #24
    //   426: ldc 65540
    //   428: iastore
    //   429: dup
    //   430: bipush #25
    //   432: ldc 16777220
    //   434: iastore
    //   435: dup
    //   436: bipush #26
    //   438: ldc 16777220
    //   440: iastore
    //   441: dup
    //   442: bipush #27
    //   444: ldc 65540
    //   446: iastore
    //   447: dup
    //   448: bipush #28
    //   450: iconst_0
    //   451: iastore
    //   452: dup
    //   453: bipush #29
    //   455: sipush #1028
    //   458: iastore
    //   459: dup
    //   460: bipush #30
    //   462: ldc 66564
    //   464: iastore
    //   465: dup
    //   466: bipush #31
    //   468: ldc 16777216
    //   470: iastore
    //   471: dup
    //   472: bipush #32
    //   474: ldc 65536
    //   476: iastore
    //   477: dup
    //   478: bipush #33
    //   480: ldc 16843780
    //   482: iastore
    //   483: dup
    //   484: bipush #34
    //   486: iconst_4
    //   487: iastore
    //   488: dup
    //   489: bipush #35
    //   491: ldc 16842752
    //   493: iastore
    //   494: dup
    //   495: bipush #36
    //   497: ldc 16843776
    //   499: iastore
    //   500: dup
    //   501: bipush #37
    //   503: ldc 16777216
    //   505: iastore
    //   506: dup
    //   507: bipush #38
    //   509: ldc 16777216
    //   511: iastore
    //   512: dup
    //   513: bipush #39
    //   515: sipush #1024
    //   518: iastore
    //   519: dup
    //   520: bipush #40
    //   522: ldc 16842756
    //   524: iastore
    //   525: dup
    //   526: bipush #41
    //   528: ldc 65536
    //   530: iastore
    //   531: dup
    //   532: bipush #42
    //   534: ldc 66560
    //   536: iastore
    //   537: dup
    //   538: bipush #43
    //   540: ldc 16777220
    //   542: iastore
    //   543: dup
    //   544: bipush #44
    //   546: sipush #1024
    //   549: iastore
    //   550: dup
    //   551: bipush #45
    //   553: iconst_4
    //   554: iastore
    //   555: dup
    //   556: bipush #46
    //   558: ldc 16778244
    //   560: iastore
    //   561: dup
    //   562: bipush #47
    //   564: ldc 66564
    //   566: iastore
    //   567: dup
    //   568: bipush #48
    //   570: ldc 16843780
    //   572: iastore
    //   573: dup
    //   574: bipush #49
    //   576: ldc 65540
    //   578: iastore
    //   579: dup
    //   580: bipush #50
    //   582: ldc 16842752
    //   584: iastore
    //   585: dup
    //   586: bipush #51
    //   588: ldc 16778244
    //   590: iastore
    //   591: dup
    //   592: bipush #52
    //   594: ldc 16777220
    //   596: iastore
    //   597: dup
    //   598: bipush #53
    //   600: sipush #1028
    //   603: iastore
    //   604: dup
    //   605: bipush #54
    //   607: ldc 66564
    //   609: iastore
    //   610: dup
    //   611: bipush #55
    //   613: ldc 16843776
    //   615: iastore
    //   616: dup
    //   617: bipush #56
    //   619: sipush #1028
    //   622: iastore
    //   623: dup
    //   624: bipush #57
    //   626: ldc 16778240
    //   628: iastore
    //   629: dup
    //   630: bipush #58
    //   632: ldc 16778240
    //   634: iastore
    //   635: dup
    //   636: bipush #59
    //   638: iconst_0
    //   639: iastore
    //   640: dup
    //   641: bipush #60
    //   643: ldc 65540
    //   645: iastore
    //   646: dup
    //   647: bipush #61
    //   649: ldc 66560
    //   651: iastore
    //   652: dup
    //   653: bipush #62
    //   655: iconst_0
    //   656: iastore
    //   657: dup
    //   658: bipush #63
    //   660: ldc 16842756
    //   662: iastore
    //   663: astore #8
    //   665: bipush #64
    //   667: newarray int
    //   669: dup
    //   670: iconst_0
    //   671: ldc -2146402272
    //   673: iastore
    //   674: dup
    //   675: iconst_1
    //   676: ldc -2147450880
    //   678: iastore
    //   679: dup
    //   680: iconst_2
    //   681: ldc 32768
    //   683: iastore
    //   684: dup
    //   685: iconst_3
    //   686: ldc 1081376
    //   688: iastore
    //   689: dup
    //   690: iconst_4
    //   691: ldc 1048576
    //   693: iastore
    //   694: dup
    //   695: iconst_5
    //   696: bipush #32
    //   698: iastore
    //   699: dup
    //   700: bipush #6
    //   702: ldc -2146435040
    //   704: iastore
    //   705: dup
    //   706: bipush #7
    //   708: ldc -2147450848
    //   710: iastore
    //   711: dup
    //   712: bipush #8
    //   714: ldc -2147483616
    //   716: iastore
    //   717: dup
    //   718: bipush #9
    //   720: ldc -2146402272
    //   722: iastore
    //   723: dup
    //   724: bipush #10
    //   726: ldc -2146402304
    //   728: iastore
    //   729: dup
    //   730: bipush #11
    //   732: ldc -2147483648
    //   734: iastore
    //   735: dup
    //   736: bipush #12
    //   738: ldc -2147450880
    //   740: iastore
    //   741: dup
    //   742: bipush #13
    //   744: ldc 1048576
    //   746: iastore
    //   747: dup
    //   748: bipush #14
    //   750: bipush #32
    //   752: iastore
    //   753: dup
    //   754: bipush #15
    //   756: ldc -2146435040
    //   758: iastore
    //   759: dup
    //   760: bipush #16
    //   762: ldc 1081344
    //   764: iastore
    //   765: dup
    //   766: bipush #17
    //   768: ldc 1048608
    //   770: iastore
    //   771: dup
    //   772: bipush #18
    //   774: ldc -2147450848
    //   776: iastore
    //   777: dup
    //   778: bipush #19
    //   780: iconst_0
    //   781: iastore
    //   782: dup
    //   783: bipush #20
    //   785: ldc -2147483648
    //   787: iastore
    //   788: dup
    //   789: bipush #21
    //   791: ldc 32768
    //   793: iastore
    //   794: dup
    //   795: bipush #22
    //   797: ldc 1081376
    //   799: iastore
    //   800: dup
    //   801: bipush #23
    //   803: ldc -2146435072
    //   805: iastore
    //   806: dup
    //   807: bipush #24
    //   809: ldc 1048608
    //   811: iastore
    //   812: dup
    //   813: bipush #25
    //   815: ldc -2147483616
    //   817: iastore
    //   818: dup
    //   819: bipush #26
    //   821: iconst_0
    //   822: iastore
    //   823: dup
    //   824: bipush #27
    //   826: ldc 1081344
    //   828: iastore
    //   829: dup
    //   830: bipush #28
    //   832: ldc 32800
    //   834: iastore
    //   835: dup
    //   836: bipush #29
    //   838: ldc -2146402304
    //   840: iastore
    //   841: dup
    //   842: bipush #30
    //   844: ldc -2146435072
    //   846: iastore
    //   847: dup
    //   848: bipush #31
    //   850: ldc 32800
    //   852: iastore
    //   853: dup
    //   854: bipush #32
    //   856: iconst_0
    //   857: iastore
    //   858: dup
    //   859: bipush #33
    //   861: ldc 1081376
    //   863: iastore
    //   864: dup
    //   865: bipush #34
    //   867: ldc -2146435040
    //   869: iastore
    //   870: dup
    //   871: bipush #35
    //   873: ldc 1048576
    //   875: iastore
    //   876: dup
    //   877: bipush #36
    //   879: ldc -2147450848
    //   881: iastore
    //   882: dup
    //   883: bipush #37
    //   885: ldc -2146435072
    //   887: iastore
    //   888: dup
    //   889: bipush #38
    //   891: ldc -2146402304
    //   893: iastore
    //   894: dup
    //   895: bipush #39
    //   897: ldc 32768
    //   899: iastore
    //   900: dup
    //   901: bipush #40
    //   903: ldc -2146435072
    //   905: iastore
    //   906: dup
    //   907: bipush #41
    //   909: ldc -2147450880
    //   911: iastore
    //   912: dup
    //   913: bipush #42
    //   915: bipush #32
    //   917: iastore
    //   918: dup
    //   919: bipush #43
    //   921: ldc -2146402272
    //   923: iastore
    //   924: dup
    //   925: bipush #44
    //   927: ldc 1081376
    //   929: iastore
    //   930: dup
    //   931: bipush #45
    //   933: bipush #32
    //   935: iastore
    //   936: dup
    //   937: bipush #46
    //   939: ldc 32768
    //   941: iastore
    //   942: dup
    //   943: bipush #47
    //   945: ldc -2147483648
    //   947: iastore
    //   948: dup
    //   949: bipush #48
    //   951: ldc 32800
    //   953: iastore
    //   954: dup
    //   955: bipush #49
    //   957: ldc -2146402304
    //   959: iastore
    //   960: dup
    //   961: bipush #50
    //   963: ldc 1048576
    //   965: iastore
    //   966: dup
    //   967: bipush #51
    //   969: ldc -2147483616
    //   971: iastore
    //   972: dup
    //   973: bipush #52
    //   975: ldc 1048608
    //   977: iastore
    //   978: dup
    //   979: bipush #53
    //   981: ldc -2147450848
    //   983: iastore
    //   984: dup
    //   985: bipush #54
    //   987: ldc -2147483616
    //   989: iastore
    //   990: dup
    //   991: bipush #55
    //   993: ldc 1048608
    //   995: iastore
    //   996: dup
    //   997: bipush #56
    //   999: ldc 1081344
    //   1001: iastore
    //   1002: dup
    //   1003: bipush #57
    //   1005: iconst_0
    //   1006: iastore
    //   1007: dup
    //   1008: bipush #58
    //   1010: ldc -2147450880
    //   1012: iastore
    //   1013: dup
    //   1014: bipush #59
    //   1016: ldc 32800
    //   1018: iastore
    //   1019: dup
    //   1020: bipush #60
    //   1022: ldc -2147483648
    //   1024: iastore
    //   1025: dup
    //   1026: bipush #61
    //   1028: ldc -2146435040
    //   1030: iastore
    //   1031: dup
    //   1032: bipush #62
    //   1034: ldc -2146402272
    //   1036: iastore
    //   1037: dup
    //   1038: bipush #63
    //   1040: ldc 1081344
    //   1042: iastore
    //   1043: astore #9
    //   1045: bipush #64
    //   1047: newarray int
    //   1049: dup
    //   1050: iconst_0
    //   1051: sipush #520
    //   1054: iastore
    //   1055: dup
    //   1056: iconst_1
    //   1057: ldc 134349312
    //   1059: iastore
    //   1060: dup
    //   1061: iconst_2
    //   1062: iconst_0
    //   1063: iastore
    //   1064: dup
    //   1065: iconst_3
    //   1066: ldc 134348808
    //   1068: iastore
    //   1069: dup
    //   1070: iconst_4
    //   1071: ldc 134218240
    //   1073: iastore
    //   1074: dup
    //   1075: iconst_5
    //   1076: iconst_0
    //   1077: iastore
    //   1078: dup
    //   1079: bipush #6
    //   1081: ldc 131592
    //   1083: iastore
    //   1084: dup
    //   1085: bipush #7
    //   1087: ldc 134218240
    //   1089: iastore
    //   1090: dup
    //   1091: bipush #8
    //   1093: ldc 131080
    //   1095: iastore
    //   1096: dup
    //   1097: bipush #9
    //   1099: ldc 134217736
    //   1101: iastore
    //   1102: dup
    //   1103: bipush #10
    //   1105: ldc 134217736
    //   1107: iastore
    //   1108: dup
    //   1109: bipush #11
    //   1111: ldc 131072
    //   1113: iastore
    //   1114: dup
    //   1115: bipush #12
    //   1117: ldc 134349320
    //   1119: iastore
    //   1120: dup
    //   1121: bipush #13
    //   1123: ldc 131080
    //   1125: iastore
    //   1126: dup
    //   1127: bipush #14
    //   1129: ldc 134348800
    //   1131: iastore
    //   1132: dup
    //   1133: bipush #15
    //   1135: sipush #520
    //   1138: iastore
    //   1139: dup
    //   1140: bipush #16
    //   1142: ldc 134217728
    //   1144: iastore
    //   1145: dup
    //   1146: bipush #17
    //   1148: bipush #8
    //   1150: iastore
    //   1151: dup
    //   1152: bipush #18
    //   1154: ldc 134349312
    //   1156: iastore
    //   1157: dup
    //   1158: bipush #19
    //   1160: sipush #512
    //   1163: iastore
    //   1164: dup
    //   1165: bipush #20
    //   1167: ldc 131584
    //   1169: iastore
    //   1170: dup
    //   1171: bipush #21
    //   1173: ldc 134348800
    //   1175: iastore
    //   1176: dup
    //   1177: bipush #22
    //   1179: ldc 134348808
    //   1181: iastore
    //   1182: dup
    //   1183: bipush #23
    //   1185: ldc 131592
    //   1187: iastore
    //   1188: dup
    //   1189: bipush #24
    //   1191: ldc 134218248
    //   1193: iastore
    //   1194: dup
    //   1195: bipush #25
    //   1197: ldc 131584
    //   1199: iastore
    //   1200: dup
    //   1201: bipush #26
    //   1203: ldc 131072
    //   1205: iastore
    //   1206: dup
    //   1207: bipush #27
    //   1209: ldc 134218248
    //   1211: iastore
    //   1212: dup
    //   1213: bipush #28
    //   1215: bipush #8
    //   1217: iastore
    //   1218: dup
    //   1219: bipush #29
    //   1221: ldc 134349320
    //   1223: iastore
    //   1224: dup
    //   1225: bipush #30
    //   1227: sipush #512
    //   1230: iastore
    //   1231: dup
    //   1232: bipush #31
    //   1234: ldc 134217728
    //   1236: iastore
    //   1237: dup
    //   1238: bipush #32
    //   1240: ldc 134349312
    //   1242: iastore
    //   1243: dup
    //   1244: bipush #33
    //   1246: ldc 134217728
    //   1248: iastore
    //   1249: dup
    //   1250: bipush #34
    //   1252: ldc 131080
    //   1254: iastore
    //   1255: dup
    //   1256: bipush #35
    //   1258: sipush #520
    //   1261: iastore
    //   1262: dup
    //   1263: bipush #36
    //   1265: ldc 131072
    //   1267: iastore
    //   1268: dup
    //   1269: bipush #37
    //   1271: ldc 134349312
    //   1273: iastore
    //   1274: dup
    //   1275: bipush #38
    //   1277: ldc 134218240
    //   1279: iastore
    //   1280: dup
    //   1281: bipush #39
    //   1283: iconst_0
    //   1284: iastore
    //   1285: dup
    //   1286: bipush #40
    //   1288: sipush #512
    //   1291: iastore
    //   1292: dup
    //   1293: bipush #41
    //   1295: ldc 131080
    //   1297: iastore
    //   1298: dup
    //   1299: bipush #42
    //   1301: ldc 134349320
    //   1303: iastore
    //   1304: dup
    //   1305: bipush #43
    //   1307: ldc 134218240
    //   1309: iastore
    //   1310: dup
    //   1311: bipush #44
    //   1313: ldc 134217736
    //   1315: iastore
    //   1316: dup
    //   1317: bipush #45
    //   1319: sipush #512
    //   1322: iastore
    //   1323: dup
    //   1324: bipush #46
    //   1326: iconst_0
    //   1327: iastore
    //   1328: dup
    //   1329: bipush #47
    //   1331: ldc 134348808
    //   1333: iastore
    //   1334: dup
    //   1335: bipush #48
    //   1337: ldc 134218248
    //   1339: iastore
    //   1340: dup
    //   1341: bipush #49
    //   1343: ldc 131072
    //   1345: iastore
    //   1346: dup
    //   1347: bipush #50
    //   1349: ldc 134217728
    //   1351: iastore
    //   1352: dup
    //   1353: bipush #51
    //   1355: ldc 134349320
    //   1357: iastore
    //   1358: dup
    //   1359: bipush #52
    //   1361: bipush #8
    //   1363: iastore
    //   1364: dup
    //   1365: bipush #53
    //   1367: ldc 131592
    //   1369: iastore
    //   1370: dup
    //   1371: bipush #54
    //   1373: ldc 131584
    //   1375: iastore
    //   1376: dup
    //   1377: bipush #55
    //   1379: ldc 134217736
    //   1381: iastore
    //   1382: dup
    //   1383: bipush #56
    //   1385: ldc 134348800
    //   1387: iastore
    //   1388: dup
    //   1389: bipush #57
    //   1391: ldc 134218248
    //   1393: iastore
    //   1394: dup
    //   1395: bipush #58
    //   1397: sipush #520
    //   1400: iastore
    //   1401: dup
    //   1402: bipush #59
    //   1404: ldc 134348800
    //   1406: iastore
    //   1407: dup
    //   1408: bipush #60
    //   1410: ldc 131592
    //   1412: iastore
    //   1413: dup
    //   1414: bipush #61
    //   1416: bipush #8
    //   1418: iastore
    //   1419: dup
    //   1420: bipush #62
    //   1422: ldc 134348808
    //   1424: iastore
    //   1425: dup
    //   1426: bipush #63
    //   1428: ldc 131584
    //   1430: iastore
    //   1431: astore #10
    //   1433: bipush #64
    //   1435: newarray int
    //   1437: dup
    //   1438: iconst_0
    //   1439: ldc 8396801
    //   1441: iastore
    //   1442: dup
    //   1443: iconst_1
    //   1444: sipush #8321
    //   1447: iastore
    //   1448: dup
    //   1449: iconst_2
    //   1450: sipush #8321
    //   1453: iastore
    //   1454: dup
    //   1455: iconst_3
    //   1456: sipush #128
    //   1459: iastore
    //   1460: dup
    //   1461: iconst_4
    //   1462: ldc 8396928
    //   1464: iastore
    //   1465: dup
    //   1466: iconst_5
    //   1467: ldc 8388737
    //   1469: iastore
    //   1470: dup
    //   1471: bipush #6
    //   1473: ldc 8388609
    //   1475: iastore
    //   1476: dup
    //   1477: bipush #7
    //   1479: sipush #8193
    //   1482: iastore
    //   1483: dup
    //   1484: bipush #8
    //   1486: iconst_0
    //   1487: iastore
    //   1488: dup
    //   1489: bipush #9
    //   1491: ldc 8396800
    //   1493: iastore
    //   1494: dup
    //   1495: bipush #10
    //   1497: ldc 8396800
    //   1499: iastore
    //   1500: dup
    //   1501: bipush #11
    //   1503: ldc 8396929
    //   1505: iastore
    //   1506: dup
    //   1507: bipush #12
    //   1509: sipush #129
    //   1512: iastore
    //   1513: dup
    //   1514: bipush #13
    //   1516: iconst_0
    //   1517: iastore
    //   1518: dup
    //   1519: bipush #14
    //   1521: ldc 8388736
    //   1523: iastore
    //   1524: dup
    //   1525: bipush #15
    //   1527: ldc 8388609
    //   1529: iastore
    //   1530: dup
    //   1531: bipush #16
    //   1533: iconst_1
    //   1534: iastore
    //   1535: dup
    //   1536: bipush #17
    //   1538: sipush #8192
    //   1541: iastore
    //   1542: dup
    //   1543: bipush #18
    //   1545: ldc 8388608
    //   1547: iastore
    //   1548: dup
    //   1549: bipush #19
    //   1551: ldc 8396801
    //   1553: iastore
    //   1554: dup
    //   1555: bipush #20
    //   1557: sipush #128
    //   1560: iastore
    //   1561: dup
    //   1562: bipush #21
    //   1564: ldc 8388608
    //   1566: iastore
    //   1567: dup
    //   1568: bipush #22
    //   1570: sipush #8193
    //   1573: iastore
    //   1574: dup
    //   1575: bipush #23
    //   1577: sipush #8320
    //   1580: iastore
    //   1581: dup
    //   1582: bipush #24
    //   1584: ldc 8388737
    //   1586: iastore
    //   1587: dup
    //   1588: bipush #25
    //   1590: iconst_1
    //   1591: iastore
    //   1592: dup
    //   1593: bipush #26
    //   1595: sipush #8320
    //   1598: iastore
    //   1599: dup
    //   1600: bipush #27
    //   1602: ldc 8388736
    //   1604: iastore
    //   1605: dup
    //   1606: bipush #28
    //   1608: sipush #8192
    //   1611: iastore
    //   1612: dup
    //   1613: bipush #29
    //   1615: ldc 8396928
    //   1617: iastore
    //   1618: dup
    //   1619: bipush #30
    //   1621: ldc 8396929
    //   1623: iastore
    //   1624: dup
    //   1625: bipush #31
    //   1627: sipush #129
    //   1630: iastore
    //   1631: dup
    //   1632: bipush #32
    //   1634: ldc 8388736
    //   1636: iastore
    //   1637: dup
    //   1638: bipush #33
    //   1640: ldc 8388609
    //   1642: iastore
    //   1643: dup
    //   1644: bipush #34
    //   1646: ldc 8396800
    //   1648: iastore
    //   1649: dup
    //   1650: bipush #35
    //   1652: ldc 8396929
    //   1654: iastore
    //   1655: dup
    //   1656: bipush #36
    //   1658: sipush #129
    //   1661: iastore
    //   1662: dup
    //   1663: bipush #37
    //   1665: iconst_0
    //   1666: iastore
    //   1667: dup
    //   1668: bipush #38
    //   1670: iconst_0
    //   1671: iastore
    //   1672: dup
    //   1673: bipush #39
    //   1675: ldc 8396800
    //   1677: iastore
    //   1678: dup
    //   1679: bipush #40
    //   1681: sipush #8320
    //   1684: iastore
    //   1685: dup
    //   1686: bipush #41
    //   1688: ldc 8388736
    //   1690: iastore
    //   1691: dup
    //   1692: bipush #42
    //   1694: ldc 8388737
    //   1696: iastore
    //   1697: dup
    //   1698: bipush #43
    //   1700: iconst_1
    //   1701: iastore
    //   1702: dup
    //   1703: bipush #44
    //   1705: ldc 8396801
    //   1707: iastore
    //   1708: dup
    //   1709: bipush #45
    //   1711: sipush #8321
    //   1714: iastore
    //   1715: dup
    //   1716: bipush #46
    //   1718: sipush #8321
    //   1721: iastore
    //   1722: dup
    //   1723: bipush #47
    //   1725: sipush #128
    //   1728: iastore
    //   1729: dup
    //   1730: bipush #48
    //   1732: ldc 8396929
    //   1734: iastore
    //   1735: dup
    //   1736: bipush #49
    //   1738: sipush #129
    //   1741: iastore
    //   1742: dup
    //   1743: bipush #50
    //   1745: iconst_1
    //   1746: iastore
    //   1747: dup
    //   1748: bipush #51
    //   1750: sipush #8192
    //   1753: iastore
    //   1754: dup
    //   1755: bipush #52
    //   1757: ldc 8388609
    //   1759: iastore
    //   1760: dup
    //   1761: bipush #53
    //   1763: sipush #8193
    //   1766: iastore
    //   1767: dup
    //   1768: bipush #54
    //   1770: ldc 8396928
    //   1772: iastore
    //   1773: dup
    //   1774: bipush #55
    //   1776: ldc 8388737
    //   1778: iastore
    //   1779: dup
    //   1780: bipush #56
    //   1782: sipush #8193
    //   1785: iastore
    //   1786: dup
    //   1787: bipush #57
    //   1789: sipush #8320
    //   1792: iastore
    //   1793: dup
    //   1794: bipush #58
    //   1796: ldc 8388608
    //   1798: iastore
    //   1799: dup
    //   1800: bipush #59
    //   1802: ldc 8396801
    //   1804: iastore
    //   1805: dup
    //   1806: bipush #60
    //   1808: sipush #128
    //   1811: iastore
    //   1812: dup
    //   1813: bipush #61
    //   1815: ldc 8388608
    //   1817: iastore
    //   1818: dup
    //   1819: bipush #62
    //   1821: sipush #8192
    //   1824: iastore
    //   1825: dup
    //   1826: bipush #63
    //   1828: ldc 8396928
    //   1830: iastore
    //   1831: astore #11
    //   1833: bipush #64
    //   1835: newarray int
    //   1837: dup
    //   1838: iconst_0
    //   1839: sipush #256
    //   1842: iastore
    //   1843: dup
    //   1844: iconst_1
    //   1845: ldc 34078976
    //   1847: iastore
    //   1848: dup
    //   1849: iconst_2
    //   1850: ldc 34078720
    //   1852: iastore
    //   1853: dup
    //   1854: iconst_3
    //   1855: ldc 1107296512
    //   1857: iastore
    //   1858: dup
    //   1859: iconst_4
    //   1860: ldc 524288
    //   1862: iastore
    //   1863: dup
    //   1864: iconst_5
    //   1865: sipush #256
    //   1868: iastore
    //   1869: dup
    //   1870: bipush #6
    //   1872: ldc 1073741824
    //   1874: iastore
    //   1875: dup
    //   1876: bipush #7
    //   1878: ldc 34078720
    //   1880: iastore
    //   1881: dup
    //   1882: bipush #8
    //   1884: ldc 1074266368
    //   1886: iastore
    //   1887: dup
    //   1888: bipush #9
    //   1890: ldc 524288
    //   1892: iastore
    //   1893: dup
    //   1894: bipush #10
    //   1896: ldc 33554688
    //   1898: iastore
    //   1899: dup
    //   1900: bipush #11
    //   1902: ldc 1074266368
    //   1904: iastore
    //   1905: dup
    //   1906: bipush #12
    //   1908: ldc 1107296512
    //   1910: iastore
    //   1911: dup
    //   1912: bipush #13
    //   1914: ldc 1107820544
    //   1916: iastore
    //   1917: dup
    //   1918: bipush #14
    //   1920: ldc 524544
    //   1922: iastore
    //   1923: dup
    //   1924: bipush #15
    //   1926: ldc 1073741824
    //   1928: iastore
    //   1929: dup
    //   1930: bipush #16
    //   1932: ldc 33554432
    //   1934: iastore
    //   1935: dup
    //   1936: bipush #17
    //   1938: ldc 1074266112
    //   1940: iastore
    //   1941: dup
    //   1942: bipush #18
    //   1944: ldc 1074266112
    //   1946: iastore
    //   1947: dup
    //   1948: bipush #19
    //   1950: iconst_0
    //   1951: iastore
    //   1952: dup
    //   1953: bipush #20
    //   1955: ldc 1073742080
    //   1957: iastore
    //   1958: dup
    //   1959: bipush #21
    //   1961: ldc 1107820800
    //   1963: iastore
    //   1964: dup
    //   1965: bipush #22
    //   1967: ldc 1107820800
    //   1969: iastore
    //   1970: dup
    //   1971: bipush #23
    //   1973: ldc 33554688
    //   1975: iastore
    //   1976: dup
    //   1977: bipush #24
    //   1979: ldc 1107820544
    //   1981: iastore
    //   1982: dup
    //   1983: bipush #25
    //   1985: ldc 1073742080
    //   1987: iastore
    //   1988: dup
    //   1989: bipush #26
    //   1991: iconst_0
    //   1992: iastore
    //   1993: dup
    //   1994: bipush #27
    //   1996: ldc 1107296256
    //   1998: iastore
    //   1999: dup
    //   2000: bipush #28
    //   2002: ldc 34078976
    //   2004: iastore
    //   2005: dup
    //   2006: bipush #29
    //   2008: ldc 33554432
    //   2010: iastore
    //   2011: dup
    //   2012: bipush #30
    //   2014: ldc 1107296256
    //   2016: iastore
    //   2017: dup
    //   2018: bipush #31
    //   2020: ldc 524544
    //   2022: iastore
    //   2023: dup
    //   2024: bipush #32
    //   2026: ldc 524288
    //   2028: iastore
    //   2029: dup
    //   2030: bipush #33
    //   2032: ldc 1107296512
    //   2034: iastore
    //   2035: dup
    //   2036: bipush #34
    //   2038: sipush #256
    //   2041: iastore
    //   2042: dup
    //   2043: bipush #35
    //   2045: ldc 33554432
    //   2047: iastore
    //   2048: dup
    //   2049: bipush #36
    //   2051: ldc 1073741824
    //   2053: iastore
    //   2054: dup
    //   2055: bipush #37
    //   2057: ldc 34078720
    //   2059: iastore
    //   2060: dup
    //   2061: bipush #38
    //   2063: ldc 1107296512
    //   2065: iastore
    //   2066: dup
    //   2067: bipush #39
    //   2069: ldc 1074266368
    //   2071: iastore
    //   2072: dup
    //   2073: bipush #40
    //   2075: ldc 33554688
    //   2077: iastore
    //   2078: dup
    //   2079: bipush #41
    //   2081: ldc 1073741824
    //   2083: iastore
    //   2084: dup
    //   2085: bipush #42
    //   2087: ldc 1107820544
    //   2089: iastore
    //   2090: dup
    //   2091: bipush #43
    //   2093: ldc 34078976
    //   2095: iastore
    //   2096: dup
    //   2097: bipush #44
    //   2099: ldc 1074266368
    //   2101: iastore
    //   2102: dup
    //   2103: bipush #45
    //   2105: sipush #256
    //   2108: iastore
    //   2109: dup
    //   2110: bipush #46
    //   2112: ldc 33554432
    //   2114: iastore
    //   2115: dup
    //   2116: bipush #47
    //   2118: ldc 1107820544
    //   2120: iastore
    //   2121: dup
    //   2122: bipush #48
    //   2124: ldc 1107820800
    //   2126: iastore
    //   2127: dup
    //   2128: bipush #49
    //   2130: ldc 524544
    //   2132: iastore
    //   2133: dup
    //   2134: bipush #50
    //   2136: ldc 1107296256
    //   2138: iastore
    //   2139: dup
    //   2140: bipush #51
    //   2142: ldc 1107820800
    //   2144: iastore
    //   2145: dup
    //   2146: bipush #52
    //   2148: ldc 34078720
    //   2150: iastore
    //   2151: dup
    //   2152: bipush #53
    //   2154: iconst_0
    //   2155: iastore
    //   2156: dup
    //   2157: bipush #54
    //   2159: ldc 1074266112
    //   2161: iastore
    //   2162: dup
    //   2163: bipush #55
    //   2165: ldc 1107296256
    //   2167: iastore
    //   2168: dup
    //   2169: bipush #56
    //   2171: ldc 524544
    //   2173: iastore
    //   2174: dup
    //   2175: bipush #57
    //   2177: ldc 33554688
    //   2179: iastore
    //   2180: dup
    //   2181: bipush #58
    //   2183: ldc 1073742080
    //   2185: iastore
    //   2186: dup
    //   2187: bipush #59
    //   2189: ldc 524288
    //   2191: iastore
    //   2192: dup
    //   2193: bipush #60
    //   2195: iconst_0
    //   2196: iastore
    //   2197: dup
    //   2198: bipush #61
    //   2200: ldc 1074266112
    //   2202: iastore
    //   2203: dup
    //   2204: bipush #62
    //   2206: ldc 34078976
    //   2208: iastore
    //   2209: dup
    //   2210: bipush #63
    //   2212: ldc 1073742080
    //   2214: iastore
    //   2215: astore #12
    //   2217: bipush #64
    //   2219: newarray int
    //   2221: dup
    //   2222: iconst_0
    //   2223: ldc 536870928
    //   2225: iastore
    //   2226: dup
    //   2227: iconst_1
    //   2228: ldc 541065216
    //   2230: iastore
    //   2231: dup
    //   2232: iconst_2
    //   2233: sipush #16384
    //   2236: iastore
    //   2237: dup
    //   2238: iconst_3
    //   2239: ldc 541081616
    //   2241: iastore
    //   2242: dup
    //   2243: iconst_4
    //   2244: ldc 541065216
    //   2246: iastore
    //   2247: dup
    //   2248: iconst_5
    //   2249: bipush #16
    //   2251: iastore
    //   2252: dup
    //   2253: bipush #6
    //   2255: ldc 541081616
    //   2257: iastore
    //   2258: dup
    //   2259: bipush #7
    //   2261: ldc 4194304
    //   2263: iastore
    //   2264: dup
    //   2265: bipush #8
    //   2267: ldc 536887296
    //   2269: iastore
    //   2270: dup
    //   2271: bipush #9
    //   2273: ldc 4210704
    //   2275: iastore
    //   2276: dup
    //   2277: bipush #10
    //   2279: ldc 4194304
    //   2281: iastore
    //   2282: dup
    //   2283: bipush #11
    //   2285: ldc 536870928
    //   2287: iastore
    //   2288: dup
    //   2289: bipush #12
    //   2291: ldc 4194320
    //   2293: iastore
    //   2294: dup
    //   2295: bipush #13
    //   2297: ldc 536887296
    //   2299: iastore
    //   2300: dup
    //   2301: bipush #14
    //   2303: ldc 536870912
    //   2305: iastore
    //   2306: dup
    //   2307: bipush #15
    //   2309: sipush #16400
    //   2312: iastore
    //   2313: dup
    //   2314: bipush #16
    //   2316: iconst_0
    //   2317: iastore
    //   2318: dup
    //   2319: bipush #17
    //   2321: ldc 4194320
    //   2323: iastore
    //   2324: dup
    //   2325: bipush #18
    //   2327: ldc 536887312
    //   2329: iastore
    //   2330: dup
    //   2331: bipush #19
    //   2333: sipush #16384
    //   2336: iastore
    //   2337: dup
    //   2338: bipush #20
    //   2340: ldc 4210688
    //   2342: iastore
    //   2343: dup
    //   2344: bipush #21
    //   2346: ldc 536887312
    //   2348: iastore
    //   2349: dup
    //   2350: bipush #22
    //   2352: bipush #16
    //   2354: iastore
    //   2355: dup
    //   2356: bipush #23
    //   2358: ldc 541065232
    //   2360: iastore
    //   2361: dup
    //   2362: bipush #24
    //   2364: ldc 541065232
    //   2366: iastore
    //   2367: dup
    //   2368: bipush #25
    //   2370: iconst_0
    //   2371: iastore
    //   2372: dup
    //   2373: bipush #26
    //   2375: ldc 4210704
    //   2377: iastore
    //   2378: dup
    //   2379: bipush #27
    //   2381: ldc 541081600
    //   2383: iastore
    //   2384: dup
    //   2385: bipush #28
    //   2387: sipush #16400
    //   2390: iastore
    //   2391: dup
    //   2392: bipush #29
    //   2394: ldc 4210688
    //   2396: iastore
    //   2397: dup
    //   2398: bipush #30
    //   2400: ldc 541081600
    //   2402: iastore
    //   2403: dup
    //   2404: bipush #31
    //   2406: ldc 536870912
    //   2408: iastore
    //   2409: dup
    //   2410: bipush #32
    //   2412: ldc 536887296
    //   2414: iastore
    //   2415: dup
    //   2416: bipush #33
    //   2418: bipush #16
    //   2420: iastore
    //   2421: dup
    //   2422: bipush #34
    //   2424: ldc 541065232
    //   2426: iastore
    //   2427: dup
    //   2428: bipush #35
    //   2430: ldc 4210688
    //   2432: iastore
    //   2433: dup
    //   2434: bipush #36
    //   2436: ldc 541081616
    //   2438: iastore
    //   2439: dup
    //   2440: bipush #37
    //   2442: ldc 4194304
    //   2444: iastore
    //   2445: dup
    //   2446: bipush #38
    //   2448: sipush #16400
    //   2451: iastore
    //   2452: dup
    //   2453: bipush #39
    //   2455: ldc 536870928
    //   2457: iastore
    //   2458: dup
    //   2459: bipush #40
    //   2461: ldc 4194304
    //   2463: iastore
    //   2464: dup
    //   2465: bipush #41
    //   2467: ldc 536887296
    //   2469: iastore
    //   2470: dup
    //   2471: bipush #42
    //   2473: ldc 536870912
    //   2475: iastore
    //   2476: dup
    //   2477: bipush #43
    //   2479: sipush #16400
    //   2482: iastore
    //   2483: dup
    //   2484: bipush #44
    //   2486: ldc 536870928
    //   2488: iastore
    //   2489: dup
    //   2490: bipush #45
    //   2492: ldc 541081616
    //   2494: iastore
    //   2495: dup
    //   2496: bipush #46
    //   2498: ldc 4210688
    //   2500: iastore
    //   2501: dup
    //   2502: bipush #47
    //   2504: ldc 541065216
    //   2506: iastore
    //   2507: dup
    //   2508: bipush #48
    //   2510: ldc 4210704
    //   2512: iastore
    //   2513: dup
    //   2514: bipush #49
    //   2516: ldc 541081600
    //   2518: iastore
    //   2519: dup
    //   2520: bipush #50
    //   2522: iconst_0
    //   2523: iastore
    //   2524: dup
    //   2525: bipush #51
    //   2527: ldc 541065232
    //   2529: iastore
    //   2530: dup
    //   2531: bipush #52
    //   2533: bipush #16
    //   2535: iastore
    //   2536: dup
    //   2537: bipush #53
    //   2539: sipush #16384
    //   2542: iastore
    //   2543: dup
    //   2544: bipush #54
    //   2546: ldc 541065216
    //   2548: iastore
    //   2549: dup
    //   2550: bipush #55
    //   2552: ldc 4210704
    //   2554: iastore
    //   2555: dup
    //   2556: bipush #56
    //   2558: sipush #16384
    //   2561: iastore
    //   2562: dup
    //   2563: bipush #57
    //   2565: ldc 4194320
    //   2567: iastore
    //   2568: dup
    //   2569: bipush #58
    //   2571: ldc 536887312
    //   2573: iastore
    //   2574: dup
    //   2575: bipush #59
    //   2577: iconst_0
    //   2578: iastore
    //   2579: dup
    //   2580: bipush #60
    //   2582: ldc 541081600
    //   2584: iastore
    //   2585: dup
    //   2586: bipush #61
    //   2588: ldc 536870912
    //   2590: iastore
    //   2591: dup
    //   2592: bipush #62
    //   2594: ldc 4194320
    //   2596: iastore
    //   2597: dup
    //   2598: bipush #63
    //   2600: ldc 536887312
    //   2602: iastore
    //   2603: astore #13
    //   2605: bipush #64
    //   2607: newarray int
    //   2609: dup
    //   2610: iconst_0
    //   2611: ldc 2097152
    //   2613: iastore
    //   2614: dup
    //   2615: iconst_1
    //   2616: ldc 69206018
    //   2618: iastore
    //   2619: dup
    //   2620: iconst_2
    //   2621: ldc 67110914
    //   2623: iastore
    //   2624: dup
    //   2625: iconst_3
    //   2626: iconst_0
    //   2627: iastore
    //   2628: dup
    //   2629: iconst_4
    //   2630: sipush #2048
    //   2633: iastore
    //   2634: dup
    //   2635: iconst_5
    //   2636: ldc 67110914
    //   2638: iastore
    //   2639: dup
    //   2640: bipush #6
    //   2642: ldc 2099202
    //   2644: iastore
    //   2645: dup
    //   2646: bipush #7
    //   2648: ldc 69208064
    //   2650: iastore
    //   2651: dup
    //   2652: bipush #8
    //   2654: ldc 69208066
    //   2656: iastore
    //   2657: dup
    //   2658: bipush #9
    //   2660: ldc 2097152
    //   2662: iastore
    //   2663: dup
    //   2664: bipush #10
    //   2666: iconst_0
    //   2667: iastore
    //   2668: dup
    //   2669: bipush #11
    //   2671: ldc 67108866
    //   2673: iastore
    //   2674: dup
    //   2675: bipush #12
    //   2677: iconst_2
    //   2678: iastore
    //   2679: dup
    //   2680: bipush #13
    //   2682: ldc 67108864
    //   2684: iastore
    //   2685: dup
    //   2686: bipush #14
    //   2688: ldc 69206018
    //   2690: iastore
    //   2691: dup
    //   2692: bipush #15
    //   2694: sipush #2050
    //   2697: iastore
    //   2698: dup
    //   2699: bipush #16
    //   2701: ldc 67110912
    //   2703: iastore
    //   2704: dup
    //   2705: bipush #17
    //   2707: ldc 2099202
    //   2709: iastore
    //   2710: dup
    //   2711: bipush #18
    //   2713: ldc 2097154
    //   2715: iastore
    //   2716: dup
    //   2717: bipush #19
    //   2719: ldc 67110912
    //   2721: iastore
    //   2722: dup
    //   2723: bipush #20
    //   2725: ldc 67108866
    //   2727: iastore
    //   2728: dup
    //   2729: bipush #21
    //   2731: ldc 69206016
    //   2733: iastore
    //   2734: dup
    //   2735: bipush #22
    //   2737: ldc 69208064
    //   2739: iastore
    //   2740: dup
    //   2741: bipush #23
    //   2743: ldc 2097154
    //   2745: iastore
    //   2746: dup
    //   2747: bipush #24
    //   2749: ldc 69206016
    //   2751: iastore
    //   2752: dup
    //   2753: bipush #25
    //   2755: sipush #2048
    //   2758: iastore
    //   2759: dup
    //   2760: bipush #26
    //   2762: sipush #2050
    //   2765: iastore
    //   2766: dup
    //   2767: bipush #27
    //   2769: ldc 69208066
    //   2771: iastore
    //   2772: dup
    //   2773: bipush #28
    //   2775: ldc 2099200
    //   2777: iastore
    //   2778: dup
    //   2779: bipush #29
    //   2781: iconst_2
    //   2782: iastore
    //   2783: dup
    //   2784: bipush #30
    //   2786: ldc 67108864
    //   2788: iastore
    //   2789: dup
    //   2790: bipush #31
    //   2792: ldc 2099200
    //   2794: iastore
    //   2795: dup
    //   2796: bipush #32
    //   2798: ldc 67108864
    //   2800: iastore
    //   2801: dup
    //   2802: bipush #33
    //   2804: ldc 2099200
    //   2806: iastore
    //   2807: dup
    //   2808: bipush #34
    //   2810: ldc 2097152
    //   2812: iastore
    //   2813: dup
    //   2814: bipush #35
    //   2816: ldc 67110914
    //   2818: iastore
    //   2819: dup
    //   2820: bipush #36
    //   2822: ldc 67110914
    //   2824: iastore
    //   2825: dup
    //   2826: bipush #37
    //   2828: ldc 69206018
    //   2830: iastore
    //   2831: dup
    //   2832: bipush #38
    //   2834: ldc 69206018
    //   2836: iastore
    //   2837: dup
    //   2838: bipush #39
    //   2840: iconst_2
    //   2841: iastore
    //   2842: dup
    //   2843: bipush #40
    //   2845: ldc 2097154
    //   2847: iastore
    //   2848: dup
    //   2849: bipush #41
    //   2851: ldc 67108864
    //   2853: iastore
    //   2854: dup
    //   2855: bipush #42
    //   2857: ldc 67110912
    //   2859: iastore
    //   2860: dup
    //   2861: bipush #43
    //   2863: ldc 2097152
    //   2865: iastore
    //   2866: dup
    //   2867: bipush #44
    //   2869: ldc 69208064
    //   2871: iastore
    //   2872: dup
    //   2873: bipush #45
    //   2875: sipush #2050
    //   2878: iastore
    //   2879: dup
    //   2880: bipush #46
    //   2882: ldc 2099202
    //   2884: iastore
    //   2885: dup
    //   2886: bipush #47
    //   2888: ldc 69208064
    //   2890: iastore
    //   2891: dup
    //   2892: bipush #48
    //   2894: sipush #2050
    //   2897: iastore
    //   2898: dup
    //   2899: bipush #49
    //   2901: ldc 67108866
    //   2903: iastore
    //   2904: dup
    //   2905: bipush #50
    //   2907: ldc 69208066
    //   2909: iastore
    //   2910: dup
    //   2911: bipush #51
    //   2913: ldc 69206016
    //   2915: iastore
    //   2916: dup
    //   2917: bipush #52
    //   2919: ldc 2099200
    //   2921: iastore
    //   2922: dup
    //   2923: bipush #53
    //   2925: iconst_0
    //   2926: iastore
    //   2927: dup
    //   2928: bipush #54
    //   2930: iconst_2
    //   2931: iastore
    //   2932: dup
    //   2933: bipush #55
    //   2935: ldc 69208066
    //   2937: iastore
    //   2938: dup
    //   2939: bipush #56
    //   2941: iconst_0
    //   2942: iastore
    //   2943: dup
    //   2944: bipush #57
    //   2946: ldc 2099202
    //   2948: iastore
    //   2949: dup
    //   2950: bipush #58
    //   2952: ldc 69206016
    //   2954: iastore
    //   2955: dup
    //   2956: bipush #59
    //   2958: sipush #2048
    //   2961: iastore
    //   2962: dup
    //   2963: bipush #60
    //   2965: ldc 67108866
    //   2967: iastore
    //   2968: dup
    //   2969: bipush #61
    //   2971: ldc 67110912
    //   2973: iastore
    //   2974: dup
    //   2975: bipush #62
    //   2977: sipush #2048
    //   2980: iastore
    //   2981: dup
    //   2982: bipush #63
    //   2984: ldc 2097154
    //   2986: iastore
    //   2987: astore #14
    //   2989: bipush #64
    //   2991: newarray int
    //   2993: dup
    //   2994: iconst_0
    //   2995: ldc 268439616
    //   2997: iastore
    //   2998: dup
    //   2999: iconst_1
    //   3000: sipush #4096
    //   3003: iastore
    //   3004: dup
    //   3005: iconst_2
    //   3006: ldc 262144
    //   3008: iastore
    //   3009: dup
    //   3010: iconst_3
    //   3011: ldc 268701760
    //   3013: iastore
    //   3014: dup
    //   3015: iconst_4
    //   3016: ldc 268435456
    //   3018: iastore
    //   3019: dup
    //   3020: iconst_5
    //   3021: ldc 268439616
    //   3023: iastore
    //   3024: dup
    //   3025: bipush #6
    //   3027: bipush #64
    //   3029: iastore
    //   3030: dup
    //   3031: bipush #7
    //   3033: ldc 268435456
    //   3035: iastore
    //   3036: dup
    //   3037: bipush #8
    //   3039: ldc 262208
    //   3041: iastore
    //   3042: dup
    //   3043: bipush #9
    //   3045: ldc 268697600
    //   3047: iastore
    //   3048: dup
    //   3049: bipush #10
    //   3051: ldc 268701760
    //   3053: iastore
    //   3054: dup
    //   3055: bipush #11
    //   3057: ldc 266240
    //   3059: iastore
    //   3060: dup
    //   3061: bipush #12
    //   3063: ldc 268701696
    //   3065: iastore
    //   3066: dup
    //   3067: bipush #13
    //   3069: ldc 266304
    //   3071: iastore
    //   3072: dup
    //   3073: bipush #14
    //   3075: sipush #4096
    //   3078: iastore
    //   3079: dup
    //   3080: bipush #15
    //   3082: bipush #64
    //   3084: iastore
    //   3085: dup
    //   3086: bipush #16
    //   3088: ldc 268697600
    //   3090: iastore
    //   3091: dup
    //   3092: bipush #17
    //   3094: ldc 268435520
    //   3096: iastore
    //   3097: dup
    //   3098: bipush #18
    //   3100: ldc 268439552
    //   3102: iastore
    //   3103: dup
    //   3104: bipush #19
    //   3106: sipush #4160
    //   3109: iastore
    //   3110: dup
    //   3111: bipush #20
    //   3113: ldc 266240
    //   3115: iastore
    //   3116: dup
    //   3117: bipush #21
    //   3119: ldc 262208
    //   3121: iastore
    //   3122: dup
    //   3123: bipush #22
    //   3125: ldc 268697664
    //   3127: iastore
    //   3128: dup
    //   3129: bipush #23
    //   3131: ldc 268701696
    //   3133: iastore
    //   3134: dup
    //   3135: bipush #24
    //   3137: sipush #4160
    //   3140: iastore
    //   3141: dup
    //   3142: bipush #25
    //   3144: iconst_0
    //   3145: iastore
    //   3146: dup
    //   3147: bipush #26
    //   3149: iconst_0
    //   3150: iastore
    //   3151: dup
    //   3152: bipush #27
    //   3154: ldc 268697664
    //   3156: iastore
    //   3157: dup
    //   3158: bipush #28
    //   3160: ldc 268435520
    //   3162: iastore
    //   3163: dup
    //   3164: bipush #29
    //   3166: ldc 268439552
    //   3168: iastore
    //   3169: dup
    //   3170: bipush #30
    //   3172: ldc 266304
    //   3174: iastore
    //   3175: dup
    //   3176: bipush #31
    //   3178: ldc 262144
    //   3180: iastore
    //   3181: dup
    //   3182: bipush #32
    //   3184: ldc 266304
    //   3186: iastore
    //   3187: dup
    //   3188: bipush #33
    //   3190: ldc 262144
    //   3192: iastore
    //   3193: dup
    //   3194: bipush #34
    //   3196: ldc 268701696
    //   3198: iastore
    //   3199: dup
    //   3200: bipush #35
    //   3202: sipush #4096
    //   3205: iastore
    //   3206: dup
    //   3207: bipush #36
    //   3209: bipush #64
    //   3211: iastore
    //   3212: dup
    //   3213: bipush #37
    //   3215: ldc 268697664
    //   3217: iastore
    //   3218: dup
    //   3219: bipush #38
    //   3221: sipush #4096
    //   3224: iastore
    //   3225: dup
    //   3226: bipush #39
    //   3228: ldc 266304
    //   3230: iastore
    //   3231: dup
    //   3232: bipush #40
    //   3234: ldc 268439552
    //   3236: iastore
    //   3237: dup
    //   3238: bipush #41
    //   3240: bipush #64
    //   3242: iastore
    //   3243: dup
    //   3244: bipush #42
    //   3246: ldc 268435520
    //   3248: iastore
    //   3249: dup
    //   3250: bipush #43
    //   3252: ldc 268697600
    //   3254: iastore
    //   3255: dup
    //   3256: bipush #44
    //   3258: ldc 268697664
    //   3260: iastore
    //   3261: dup
    //   3262: bipush #45
    //   3264: ldc 268435456
    //   3266: iastore
    //   3267: dup
    //   3268: bipush #46
    //   3270: ldc 262144
    //   3272: iastore
    //   3273: dup
    //   3274: bipush #47
    //   3276: ldc 268439616
    //   3278: iastore
    //   3279: dup
    //   3280: bipush #48
    //   3282: iconst_0
    //   3283: iastore
    //   3284: dup
    //   3285: bipush #49
    //   3287: ldc 268701760
    //   3289: iastore
    //   3290: dup
    //   3291: bipush #50
    //   3293: ldc 262208
    //   3295: iastore
    //   3296: dup
    //   3297: bipush #51
    //   3299: ldc 268435520
    //   3301: iastore
    //   3302: dup
    //   3303: bipush #52
    //   3305: ldc 268697600
    //   3307: iastore
    //   3308: dup
    //   3309: bipush #53
    //   3311: ldc 268439552
    //   3313: iastore
    //   3314: dup
    //   3315: bipush #54
    //   3317: ldc 268439616
    //   3319: iastore
    //   3320: dup
    //   3321: bipush #55
    //   3323: iconst_0
    //   3324: iastore
    //   3325: dup
    //   3326: bipush #56
    //   3328: ldc 268701760
    //   3330: iastore
    //   3331: dup
    //   3332: bipush #57
    //   3334: ldc 266240
    //   3336: iastore
    //   3337: dup
    //   3338: bipush #58
    //   3340: ldc 266240
    //   3342: iastore
    //   3343: dup
    //   3344: bipush #59
    //   3346: sipush #4160
    //   3349: iastore
    //   3350: dup
    //   3351: bipush #60
    //   3353: sipush #4160
    //   3356: iastore
    //   3357: dup
    //   3358: bipush #61
    //   3360: ldc 262208
    //   3362: iastore
    //   3363: dup
    //   3364: bipush #62
    //   3366: ldc 268435456
    //   3368: iastore
    //   3369: dup
    //   3370: bipush #63
    //   3372: ldc 268701696
    //   3374: iastore
    //   3375: astore #15
    //   3377: aload_3
    //   3378: arraylength
    //   3379: istore #16
    //   3381: iconst_2
    //   3382: newarray int
    //   3384: astore #17
    //   3386: iload #16
    //   3388: newarray byte
    //   3390: astore #4
    //   3392: iload #16
    //   3394: bipush #8
    //   3396: idiv
    //   3397: istore #18
    //   3399: iconst_0
    //   3400: istore #19
    //   3402: iload #19
    //   3404: iload #18
    //   3406: if_icmpge -> 4320
    //   3409: iload #19
    //   3411: bipush #8
    //   3413: imul
    //   3414: istore #20
    //   3416: iconst_0
    //   3417: istore #21
    //   3419: iload #21
    //   3421: iconst_2
    //   3422: if_icmpge -> 3507
    //   3425: aload #17
    //   3427: iload #21
    //   3429: aload_3
    //   3430: iload #20
    //   3432: iload #21
    //   3434: iconst_4
    //   3435: imul
    //   3436: iadd
    //   3437: baload
    //   3438: sipush #255
    //   3441: iand
    //   3442: bipush #24
    //   3444: ishl
    //   3445: aload_3
    //   3446: iload #20
    //   3448: iload #21
    //   3450: iconst_4
    //   3451: imul
    //   3452: iadd
    //   3453: iconst_1
    //   3454: iadd
    //   3455: baload
    //   3456: sipush #255
    //   3459: iand
    //   3460: bipush #16
    //   3462: ishl
    //   3463: ior
    //   3464: aload_3
    //   3465: iload #20
    //   3467: iload #21
    //   3469: iconst_4
    //   3470: imul
    //   3471: iadd
    //   3472: iconst_2
    //   3473: iadd
    //   3474: baload
    //   3475: sipush #255
    //   3478: iand
    //   3479: bipush #8
    //   3481: ishl
    //   3482: ior
    //   3483: aload_3
    //   3484: iload #20
    //   3486: iload #21
    //   3488: iconst_4
    //   3489: imul
    //   3490: iadd
    //   3491: iconst_3
    //   3492: iadd
    //   3493: baload
    //   3494: sipush #255
    //   3497: iand
    //   3498: ior
    //   3499: iastore
    //   3500: iinc #21, 1
    //   3503: iload_2
    //   3504: ifeq -> 3419
    //   3507: iconst_0
    //   3508: istore #26
    //   3510: aload #17
    //   3512: iconst_0
    //   3513: iaload
    //   3514: istore #24
    //   3516: aload #17
    //   3518: iconst_1
    //   3519: iaload
    //   3520: istore #23
    //   3522: iload #24
    //   3524: iconst_4
    //   3525: iushr
    //   3526: iload #23
    //   3528: ixor
    //   3529: ldc 252645135
    //   3531: iand
    //   3532: istore #22
    //   3534: iload #23
    //   3536: iload #22
    //   3538: ixor
    //   3539: istore #23
    //   3541: iload #24
    //   3543: iload #22
    //   3545: iconst_4
    //   3546: ishl
    //   3547: ixor
    //   3548: istore #24
    //   3550: iload #24
    //   3552: bipush #16
    //   3554: iushr
    //   3555: iload #23
    //   3557: ixor
    //   3558: ldc 65535
    //   3560: iand
    //   3561: istore #22
    //   3563: iload #23
    //   3565: iload #22
    //   3567: ixor
    //   3568: istore #23
    //   3570: iload #24
    //   3572: iload #22
    //   3574: bipush #16
    //   3576: ishl
    //   3577: ixor
    //   3578: istore #24
    //   3580: iload #23
    //   3582: iconst_2
    //   3583: iushr
    //   3584: iload #24
    //   3586: ixor
    //   3587: ldc 858993459
    //   3589: iand
    //   3590: istore #22
    //   3592: iload #24
    //   3594: iload #22
    //   3596: ixor
    //   3597: istore #24
    //   3599: iload #23
    //   3601: iload #22
    //   3603: iconst_2
    //   3604: ishl
    //   3605: ixor
    //   3606: istore #23
    //   3608: iload #23
    //   3610: bipush #8
    //   3612: iushr
    //   3613: iload #24
    //   3615: ixor
    //   3616: ldc 16711935
    //   3618: iand
    //   3619: istore #22
    //   3621: iload #24
    //   3623: iload #22
    //   3625: ixor
    //   3626: istore #24
    //   3628: iload #23
    //   3630: iload #22
    //   3632: bipush #8
    //   3634: ishl
    //   3635: ixor
    //   3636: istore #23
    //   3638: iload #23
    //   3640: iconst_1
    //   3641: ishl
    //   3642: iload #23
    //   3644: bipush #31
    //   3646: iushr
    //   3647: iconst_1
    //   3648: iand
    //   3649: ior
    //   3650: istore #23
    //   3652: iload #24
    //   3654: iload #23
    //   3656: ixor
    //   3657: ldc -1431655766
    //   3659: iand
    //   3660: istore #22
    //   3662: iload #24
    //   3664: iload #22
    //   3666: ixor
    //   3667: istore #24
    //   3669: iload #23
    //   3671: iload #22
    //   3673: ixor
    //   3674: istore #23
    //   3676: iload #24
    //   3678: iconst_1
    //   3679: ishl
    //   3680: iload #24
    //   3682: bipush #31
    //   3684: iushr
    //   3685: iconst_1
    //   3686: iand
    //   3687: ior
    //   3688: istore #24
    //   3690: iconst_0
    //   3691: istore #25
    //   3693: iload #25
    //   3695: bipush #8
    //   3697: if_icmpge -> 4035
    //   3700: iload #23
    //   3702: bipush #28
    //   3704: ishl
    //   3705: iload #23
    //   3707: iconst_4
    //   3708: iushr
    //   3709: ior
    //   3710: istore #22
    //   3712: iload #22
    //   3714: aload #5
    //   3716: iload #26
    //   3718: iinc #26, 1
    //   3721: iaload
    //   3722: ixor
    //   3723: istore #22
    //   3725: aload #14
    //   3727: iload #22
    //   3729: bipush #63
    //   3731: iand
    //   3732: iaload
    //   3733: istore #21
    //   3735: iload #21
    //   3737: aload #12
    //   3739: iload #22
    //   3741: bipush #8
    //   3743: iushr
    //   3744: bipush #63
    //   3746: iand
    //   3747: iaload
    //   3748: ior
    //   3749: istore #21
    //   3751: iload #21
    //   3753: aload #10
    //   3755: iload #22
    //   3757: bipush #16
    //   3759: iushr
    //   3760: bipush #63
    //   3762: iand
    //   3763: iaload
    //   3764: ior
    //   3765: istore #21
    //   3767: iload #21
    //   3769: aload #8
    //   3771: iload #22
    //   3773: bipush #24
    //   3775: iushr
    //   3776: bipush #63
    //   3778: iand
    //   3779: iaload
    //   3780: ior
    //   3781: istore #21
    //   3783: iload #23
    //   3785: aload #5
    //   3787: iload #26
    //   3789: iinc #26, 1
    //   3792: iaload
    //   3793: ixor
    //   3794: istore #22
    //   3796: iload #21
    //   3798: aload #15
    //   3800: iload #22
    //   3802: bipush #63
    //   3804: iand
    //   3805: iaload
    //   3806: ior
    //   3807: istore #21
    //   3809: iload #21
    //   3811: aload #13
    //   3813: iload #22
    //   3815: bipush #8
    //   3817: iushr
    //   3818: bipush #63
    //   3820: iand
    //   3821: iaload
    //   3822: ior
    //   3823: istore #21
    //   3825: iload #21
    //   3827: aload #11
    //   3829: iload #22
    //   3831: bipush #16
    //   3833: iushr
    //   3834: bipush #63
    //   3836: iand
    //   3837: iaload
    //   3838: ior
    //   3839: istore #21
    //   3841: iload #21
    //   3843: aload #9
    //   3845: iload #22
    //   3847: bipush #24
    //   3849: iushr
    //   3850: bipush #63
    //   3852: iand
    //   3853: iaload
    //   3854: ior
    //   3855: istore #21
    //   3857: iload #24
    //   3859: iload #21
    //   3861: ixor
    //   3862: istore #24
    //   3864: iload #24
    //   3866: bipush #28
    //   3868: ishl
    //   3869: iload #24
    //   3871: iconst_4
    //   3872: iushr
    //   3873: ior
    //   3874: istore #22
    //   3876: iload #22
    //   3878: aload #5
    //   3880: iload #26
    //   3882: iinc #26, 1
    //   3885: iaload
    //   3886: ixor
    //   3887: istore #22
    //   3889: aload #14
    //   3891: iload #22
    //   3893: bipush #63
    //   3895: iand
    //   3896: iaload
    //   3897: istore #21
    //   3899: iload #21
    //   3901: aload #12
    //   3903: iload #22
    //   3905: bipush #8
    //   3907: iushr
    //   3908: bipush #63
    //   3910: iand
    //   3911: iaload
    //   3912: ior
    //   3913: istore #21
    //   3915: iload #21
    //   3917: aload #10
    //   3919: iload #22
    //   3921: bipush #16
    //   3923: iushr
    //   3924: bipush #63
    //   3926: iand
    //   3927: iaload
    //   3928: ior
    //   3929: istore #21
    //   3931: iload #21
    //   3933: aload #8
    //   3935: iload #22
    //   3937: bipush #24
    //   3939: iushr
    //   3940: bipush #63
    //   3942: iand
    //   3943: iaload
    //   3944: ior
    //   3945: istore #21
    //   3947: iload #24
    //   3949: aload #5
    //   3951: iload #26
    //   3953: iinc #26, 1
    //   3956: iaload
    //   3957: ixor
    //   3958: istore #22
    //   3960: iload #21
    //   3962: aload #15
    //   3964: iload #22
    //   3966: bipush #63
    //   3968: iand
    //   3969: iaload
    //   3970: ior
    //   3971: istore #21
    //   3973: iload #21
    //   3975: aload #13
    //   3977: iload #22
    //   3979: bipush #8
    //   3981: iushr
    //   3982: bipush #63
    //   3984: iand
    //   3985: iaload
    //   3986: ior
    //   3987: istore #21
    //   3989: iload #21
    //   3991: aload #11
    //   3993: iload #22
    //   3995: bipush #16
    //   3997: iushr
    //   3998: bipush #63
    //   4000: iand
    //   4001: iaload
    //   4002: ior
    //   4003: istore #21
    //   4005: iload #21
    //   4007: aload #9
    //   4009: iload #22
    //   4011: bipush #24
    //   4013: iushr
    //   4014: bipush #63
    //   4016: iand
    //   4017: iaload
    //   4018: ior
    //   4019: istore #21
    //   4021: iload #23
    //   4023: iload #21
    //   4025: ixor
    //   4026: istore #23
    //   4028: iinc #25, 1
    //   4031: iload_2
    //   4032: ifeq -> 3693
    //   4035: iload #23
    //   4037: bipush #31
    //   4039: ishl
    //   4040: iload #23
    //   4042: iconst_1
    //   4043: iushr
    //   4044: ior
    //   4045: istore #23
    //   4047: iload #24
    //   4049: iload #23
    //   4051: ixor
    //   4052: ldc -1431655766
    //   4054: iand
    //   4055: istore #22
    //   4057: iload #24
    //   4059: iload #22
    //   4061: ixor
    //   4062: istore #24
    //   4064: iload #23
    //   4066: iload #22
    //   4068: ixor
    //   4069: istore #23
    //   4071: iload #24
    //   4073: bipush #31
    //   4075: ishl
    //   4076: iload #24
    //   4078: iconst_1
    //   4079: iushr
    //   4080: ior
    //   4081: istore #24
    //   4083: iload #24
    //   4085: bipush #8
    //   4087: iushr
    //   4088: iload #23
    //   4090: ixor
    //   4091: ldc 16711935
    //   4093: iand
    //   4094: istore #22
    //   4096: iload #23
    //   4098: iload #22
    //   4100: ixor
    //   4101: istore #23
    //   4103: iload #24
    //   4105: iload #22
    //   4107: bipush #8
    //   4109: ishl
    //   4110: ixor
    //   4111: istore #24
    //   4113: iload #24
    //   4115: iconst_2
    //   4116: iushr
    //   4117: iload #23
    //   4119: ixor
    //   4120: ldc 858993459
    //   4122: iand
    //   4123: istore #22
    //   4125: iload #23
    //   4127: iload #22
    //   4129: ixor
    //   4130: istore #23
    //   4132: iload #24
    //   4134: iload #22
    //   4136: iconst_2
    //   4137: ishl
    //   4138: ixor
    //   4139: istore #24
    //   4141: iload #23
    //   4143: bipush #16
    //   4145: iushr
    //   4146: iload #24
    //   4148: ixor
    //   4149: ldc 65535
    //   4151: iand
    //   4152: istore #22
    //   4154: iload #24
    //   4156: iload #22
    //   4158: ixor
    //   4159: istore #24
    //   4161: iload #23
    //   4163: iload #22
    //   4165: bipush #16
    //   4167: ishl
    //   4168: ixor
    //   4169: istore #23
    //   4171: iload #23
    //   4173: iconst_4
    //   4174: iushr
    //   4175: iload #24
    //   4177: ixor
    //   4178: ldc 252645135
    //   4180: iand
    //   4181: istore #22
    //   4183: iload #24
    //   4185: iload #22
    //   4187: ixor
    //   4188: istore #24
    //   4190: iload #23
    //   4192: iload #22
    //   4194: iconst_4
    //   4195: ishl
    //   4196: ixor
    //   4197: istore #23
    //   4199: aload #17
    //   4201: iconst_0
    //   4202: iload #23
    //   4204: iastore
    //   4205: aload #17
    //   4207: iconst_1
    //   4208: iload #24
    //   4210: iastore
    //   4211: iload #19
    //   4213: bipush #8
    //   4215: imul
    //   4216: istore #27
    //   4218: iconst_0
    //   4219: istore #28
    //   4221: iload #28
    //   4223: iconst_2
    //   4224: if_icmpge -> 4313
    //   4227: aload #4
    //   4229: iload #27
    //   4231: iload #28
    //   4233: iconst_4
    //   4234: imul
    //   4235: iadd
    //   4236: aload #17
    //   4238: iload #28
    //   4240: iaload
    //   4241: bipush #24
    //   4243: iushr
    //   4244: i2b
    //   4245: bastore
    //   4246: aload #4
    //   4248: iload #27
    //   4250: iload #28
    //   4252: iconst_4
    //   4253: imul
    //   4254: iadd
    //   4255: iconst_1
    //   4256: iadd
    //   4257: aload #17
    //   4259: iload #28
    //   4261: iaload
    //   4262: bipush #16
    //   4264: iushr
    //   4265: i2b
    //   4266: bastore
    //   4267: aload #4
    //   4269: iload #27
    //   4271: iload #28
    //   4273: iconst_4
    //   4274: imul
    //   4275: iadd
    //   4276: iconst_2
    //   4277: iadd
    //   4278: aload #17
    //   4280: iload #28
    //   4282: iaload
    //   4283: bipush #8
    //   4285: iushr
    //   4286: i2b
    //   4287: bastore
    //   4288: aload #4
    //   4290: iload #27
    //   4292: iload #28
    //   4294: iconst_4
    //   4295: imul
    //   4296: iadd
    //   4297: iconst_3
    //   4298: iadd
    //   4299: aload #17
    //   4301: iload #28
    //   4303: iaload
    //   4304: i2b
    //   4305: bastore
    //   4306: iinc #28, 1
    //   4309: iload_2
    //   4310: ifeq -> 4221
    //   4313: iinc #19, 1
    //   4316: iload_2
    //   4317: ifeq -> 3402
    //   4320: new java/math/BigInteger
    //   4323: dup
    //   4324: aload #4
    //   4326: invokespecial <init> : ([B)V
    //   4329: invokevirtual abs : ()Ljava/math/BigInteger;
    //   4332: putstatic burp/Zea8.ZF : Ljava/lang/Object;
    //   4335: getstatic burp/Zgpx.ZQ : Ljava/lang/Object;
    //   4338: checkcast java/math/BigInteger
    //   4341: invokevirtual toByteArray : ()[B
    //   4344: astore_3
    //   4345: aload_3
    //   4346: arraylength
    //   4347: iconst_2
    //   4348: iadd
    //   4349: newarray byte
    //   4351: astore #5
    //   4353: iconst_0
    //   4354: istore #6
    //   4356: iload #6
    //   4358: aload_3
    //   4359: arraylength
    //   4360: if_icmpge -> 4379
    //   4363: aload #5
    //   4365: iload #6
    //   4367: aload_3
    //   4368: iload #6
    //   4370: baload
    //   4371: bastore
    //   4372: iinc #6, 1
    //   4375: iload_2
    //   4376: ifeq -> 4356
    //   4379: aload #5
    //   4381: arraylength
    //   4382: iconst_3
    //   4383: idiv
    //   4384: iconst_4
    //   4385: imul
    //   4386: newarray byte
    //   4388: astore #4
    //   4390: iconst_0
    //   4391: istore #6
    //   4393: iconst_0
    //   4394: istore #7
    //   4396: iload #6
    //   4398: aload_3
    //   4399: arraylength
    //   4400: if_icmpge -> 4511
    //   4403: aload #4
    //   4405: iload #7
    //   4407: aload #5
    //   4409: iload #6
    //   4411: baload
    //   4412: iconst_2
    //   4413: iushr
    //   4414: bipush #63
    //   4416: iand
    //   4417: i2b
    //   4418: bastore
    //   4419: aload #4
    //   4421: iload #7
    //   4423: iconst_1
    //   4424: iadd
    //   4425: aload #5
    //   4427: iload #6
    //   4429: iconst_1
    //   4430: iadd
    //   4431: baload
    //   4432: iconst_4
    //   4433: iushr
    //   4434: bipush #15
    //   4436: iand
    //   4437: aload #5
    //   4439: iload #6
    //   4441: baload
    //   4442: iconst_4
    //   4443: ishl
    //   4444: bipush #63
    //   4446: iand
    //   4447: ior
    //   4448: i2b
    //   4449: bastore
    //   4450: aload #4
    //   4452: iload #7
    //   4454: iconst_2
    //   4455: iadd
    //   4456: aload #5
    //   4458: iload #6
    //   4460: iconst_2
    //   4461: iadd
    //   4462: baload
    //   4463: bipush #6
    //   4465: iushr
    //   4466: iconst_3
    //   4467: iand
    //   4468: aload #5
    //   4470: iload #6
    //   4472: iconst_1
    //   4473: iadd
    //   4474: baload
    //   4475: iconst_2
    //   4476: ishl
    //   4477: bipush #63
    //   4479: iand
    //   4480: ior
    //   4481: i2b
    //   4482: bastore
    //   4483: aload #4
    //   4485: iload #7
    //   4487: iconst_3
    //   4488: iadd
    //   4489: aload #5
    //   4491: iload #6
    //   4493: iconst_2
    //   4494: iadd
    //   4495: baload
    //   4496: bipush #63
    //   4498: iand
    //   4499: i2b
    //   4500: bastore
    //   4501: iinc #6, 3
    //   4504: iinc #7, 4
    //   4507: iload_2
    //   4508: ifeq -> 4396
    //   4511: iconst_0
    //   4512: istore #6
    //   4514: iload #6
    //   4516: aload #4
    //   4518: arraylength
    //   4519: if_icmpge -> 4703
    //   4522: aload #4
    //   4524: iload #6
    //   4526: baload
    //   4527: bipush #26
    //   4529: if_icmpge -> 4557
    //   4532: aload #4
    //   4534: iload #6
    //   4536: aload #4
    //   4538: iload #6
    //   4540: baload
    //   4541: bipush #65
    //   4543: iadd
    //   4544: i2b
    //   4545: bastore
    //   4546: iload_2
    //   4547: ifeq -> 4696
    //   4550: goto -> 4557
    //   4553: invokestatic a : (Ljava/lang/Throwable;)Ljava/lang/Throwable;
    //   4556: athrow
    //   4557: aload #4
    //   4559: iload #6
    //   4561: baload
    //   4562: bipush #52
    //   4564: if_icmpge -> 4602
    //   4567: goto -> 4574
    //   4570: invokestatic a : (Ljava/lang/Throwable;)Ljava/lang/Throwable;
    //   4573: athrow
    //   4574: aload #4
    //   4576: iload #6
    //   4578: aload #4
    //   4580: iload #6
    //   4582: baload
    //   4583: bipush #97
    //   4585: iadd
    //   4586: bipush #26
    //   4588: isub
    //   4589: i2b
    //   4590: bastore
    //   4591: iload_2
    //   4592: ifeq -> 4696
    //   4595: goto -> 4602
    //   4598: invokestatic a : (Ljava/lang/Throwable;)Ljava/lang/Throwable;
    //   4601: athrow
    //   4602: aload #4
    //   4604: iload #6
    //   4606: baload
    //   4607: bipush #62
    //   4609: if_icmpge -> 4647
    //   4612: goto -> 4619
    //   4615: invokestatic a : (Ljava/lang/Throwable;)Ljava/lang/Throwable;
    //   4618: athrow
    //   4619: aload #4
    //   4621: iload #6
    //   4623: aload #4
    //   4625: iload #6
    //   4627: baload
    //   4628: bipush #48
    //   4630: iadd
    //   4631: bipush #52
    //   4633: isub
    //   4634: i2b
    //   4635: bastore
    //   4636: iload_2
    //   4637: ifeq -> 4696
    //   4640: goto -> 4647
    //   4643: invokestatic a : (Ljava/lang/Throwable;)Ljava/lang/Throwable;
    //   4646: athrow
    //   4647: aload #4
    //   4649: iload #6
    //   4651: baload
    //   4652: bipush #63
    //   4654: if_icmpge -> 4682
    //   4657: goto -> 4664
    //   4660: invokestatic a : (Ljava/lang/Throwable;)Ljava/lang/Throwable;
    //   4663: athrow
    //   4664: aload #4
    //   4666: iload #6
    //   4668: bipush #43
    //   4670: bastore
    //   4671: iload_2
    //   4672: ifeq -> 4696
    //   4675: goto -> 4682
    //   4678: invokestatic a : (Ljava/lang/Throwable;)Ljava/lang/Throwable;
    //   4681: athrow
    //   4682: aload #4
    //   4684: iload #6
    //   4686: bipush #47
    //   4688: bastore
    //   4689: goto -> 4696
    //   4692: invokestatic a : (Ljava/lang/Throwable;)Ljava/lang/Throwable;
    //   4695: athrow
    //   4696: iinc #6, 1
    //   4699: iload_2
    //   4700: ifeq -> 4514
    //   4703: aload #4
    //   4705: arraylength
    //   4706: iconst_1
    //   4707: isub
    //   4708: istore #6
    //   4710: iload #6
    //   4712: aload_3
    //   4713: arraylength
    //   4714: iconst_4
    //   4715: imul
    //   4716: iconst_3
    //   4717: idiv
    //   4718: if_icmple -> 4735
    //   4721: aload #4
    //   4723: iload #6
    //   4725: bipush #61
    //   4727: bastore
    //   4728: iinc #6, -1
    //   4731: iload_2
    //   4732: ifeq -> 4710
    //   4735: new java/math/BigInteger
    //   4738: dup
    //   4739: aload #4
    //   4741: invokespecial <init> : ([B)V
    //   4744: invokevirtual abs : ()Ljava/math/BigInteger;
    //   4747: putstatic burp/Zb3l.Zl : Ljava/lang/Object;
    //   4750: sipush #-32397
    //   4753: sipush #-21929
    //   4756: invokestatic a : (II)Ljava/lang/String;
    //   4759: iconst_1
    //   4760: ldc burp/Zsq5
    //   4762: invokevirtual getClassLoader : ()Ljava/lang/ClassLoader;
    //   4765: invokestatic forName : (Ljava/lang/String;ZLjava/lang/ClassLoader;)Ljava/lang/Class;
    //   4768: invokevirtual getDeclaredFields : ()[Ljava/lang/reflect/Field;
    //   4771: astore_3
    //   4772: aload_3
    //   4773: arraylength
    //   4774: istore #4
    //   4776: iconst_0
    //   4777: istore #5
    //   4779: iload #5
    //   4781: iload #4
    //   4783: if_icmpge -> 4920
    //   4786: aload_3
    //   4787: iload #5
    //   4789: aaload
    //   4790: astore #6
    //   4792: aload #6
    //   4794: invokevirtual getModifiers : ()I
    //   4797: invokestatic isStatic : (I)Z
    //   4800: ifne -> 4810
    //   4803: goto -> 4913
    //   4806: invokestatic a : (Ljava/lang/Throwable;)Ljava/lang/Throwable;
    //   4809: athrow
    //   4810: aload #6
    //   4812: invokevirtual getType : ()Ljava/lang/Class;
    //   4815: astore #7
    //   4817: aload #7
    //   4819: ifnull -> 4900
    //   4822: aload #7
    //   4824: invokevirtual isPrimitive : ()Z
    //   4827: ifne -> 4900
    //   4830: goto -> 4837
    //   4833: invokestatic a : (Ljava/lang/Throwable;)Ljava/lang/Throwable;
    //   4836: athrow
    //   4837: aload #7
    //   4839: invokevirtual getPackage : ()Ljava/lang/Package;
    //   4842: ifnull -> 4900
    //   4845: goto -> 4852
    //   4848: invokestatic a : (Ljava/lang/Throwable;)Ljava/lang/Throwable;
    //   4851: athrow
    //   4852: aload #7
    //   4854: invokevirtual getPackage : ()Ljava/lang/Package;
    //   4857: invokevirtual getName : ()Ljava/lang/String;
    //   4860: ifnull -> 4900
    //   4863: goto -> 4870
    //   4866: invokestatic a : (Ljava/lang/Throwable;)Ljava/lang/Throwable;
    //   4869: athrow
    //   4870: aload #7
    //   4872: invokevirtual getPackage : ()Ljava/lang/Package;
    //   4875: invokevirtual getName : ()Ljava/lang/String;
    //   4878: sipush #-32415
    //   4881: sipush #-7168
    //   4884: invokestatic a : (II)Ljava/lang/String;
    //   4887: invokevirtual startsWith : (Ljava/lang/String;)Z
    //   4890: ifne -> 4900
    //   4893: goto -> 4900
    //   4896: invokestatic a : (Ljava/lang/Throwable;)Ljava/lang/Throwable;
    //   4899: athrow
    //   4900: aload #6
    //   4902: iconst_1
    //   4903: invokevirtual setAccessible : (Z)V
    //   4906: aload #6
    //   4908: aconst_null
    //   4909: invokevirtual get : (Ljava/lang/Object;)Ljava/lang/Object;
    //   4912: pop
    //   4913: iinc #5, 1
    //   4916: iload_2
    //   4917: ifeq -> 4779
    //   4920: sipush #-32413
    //   4923: sipush #25474
    //   4926: invokestatic a : (II)Ljava/lang/String;
    //   4929: invokestatic forName : (Ljava/lang/String;)Ljava/lang/Class;
    //   4932: invokevirtual getDeclaredMethods : ()[Ljava/lang/reflect/Method;
    //   4935: astore_3
    //   4936: aload_3
    //   4937: arraylength
    //   4938: istore #4
    //   4940: iconst_0
    //   4941: istore #5
    //   4943: iload #5
    //   4945: iload #4
    //   4947: if_icmpge -> 5079
    //   4950: aload_3
    //   4951: iload #5
    //   4953: aaload
    //   4954: astore #6
    //   4956: aload #6
    //   4958: invokevirtual getParameterTypes : ()[Ljava/lang/Class;
    //   4961: pop
    //   4962: aload #6
    //   4964: invokevirtual getModifiers : ()I
    //   4967: invokestatic isStatic : (I)Z
    //   4970: ifeq -> 5065
    //   4973: aload #6
    //   4975: invokevirtual getParameterTypes : ()[Ljava/lang/Class;
    //   4978: arraylength
    //   4979: iconst_2
    //   4980: if_icmpne -> 5065
    //   4983: goto -> 4990
    //   4986: invokestatic a : (Ljava/lang/Throwable;)Ljava/lang/Throwable;
    //   4989: athrow
    //   4990: aload #6
    //   4992: invokevirtual getReturnType : ()Ljava/lang/Class;
    //   4995: getstatic java/lang/Void.TYPE : Ljava/lang/Class;
    //   4998: invokevirtual equals : (Ljava/lang/Object;)Z
    //   5001: ifeq -> 5065
    //   5004: goto -> 5011
    //   5007: invokestatic a : (Ljava/lang/Throwable;)Ljava/lang/Throwable;
    //   5010: athrow
    //   5011: aload #6
    //   5013: iconst_1
    //   5014: invokevirtual setAccessible : (Z)V
    //   5017: aload #6
    //   5019: aconst_null
    //   5020: iconst_2
    //   5021: anewarray java/lang/Object
    //   5024: dup
    //   5025: iconst_0
    //   5026: aload_0
    //   5027: aastore
    //   5028: dup
    //   5029: iconst_1
    //   5030: aload_1
    //   5031: ifnonnull -> 5049
    //   5034: goto -> 5041
    //   5037: invokestatic a : (Ljava/lang/Throwable;)Ljava/lang/Throwable;
    //   5040: athrow
    //   5041: aload_1
    //   5042: goto -> 5056
    //   5045: invokestatic a : (Ljava/lang/Throwable;)Ljava/lang/Throwable;
    //   5048: athrow
    //   5049: aload_1
    //   5050: checkcast [B
    //   5053: invokevirtual clone : ()Ljava/lang/Object;
    //   5056: aastore
    //   5057: invokevirtual invoke : (Ljava/lang/Object;[Ljava/lang/Object;)Ljava/lang/Object;
    //   5060: pop
    //   5061: iload_2
    //   5062: ifeq -> 5079
    //   5065: iinc #5, 1
    //   5068: iload_2
    //   5069: ifeq -> 4943
    //   5072: goto -> 5079
    //   5075: invokestatic a : (Ljava/lang/Throwable;)Ljava/lang/Throwable;
    //   5078: athrow
    //   5079: new java/io/ByteArrayOutputStream
    //   5082: dup
    //   5083: invokespecial <init> : ()V
    //   5086: astore_3
    //   5087: sipush #-32406
    //   5090: aload_3
    //   5091: sipush #202
    //   5094: invokevirtual write : (I)V
    //   5097: sipush #16219
    //   5100: aload_3
    //   5101: sipush #254
    //   5104: invokevirtual write : (I)V
    //   5107: aload_3
    //   5108: sipush #186
    //   5111: invokevirtual write : (I)V
    //   5114: aload_3
    //   5115: sipush #190
    //   5118: invokevirtual write : (I)V
    //   5121: aload_3
    //   5122: iconst_0
    //   5123: invokevirtual write : (I)V
    //   5126: aload_3
    //   5127: iconst_1
    //   5128: invokevirtual write : (I)V
    //   5131: aload_3
    //   5132: iconst_0
    //   5133: invokevirtual write : (I)V
    //   5136: aload_3
    //   5137: bipush #50
    //   5139: invokevirtual write : (I)V
    //   5142: aload_3
    //   5143: getstatic burp/Zr8s.Zt : Ljava/lang/Object;
    //   5146: checkcast java/math/BigInteger
    //   5149: invokevirtual toByteArray : ()[B
    //   5152: invokevirtual write : ([B)V
    //   5155: aload_3
    //   5156: getstatic burp/Zep8.Zs : Ljava/lang/Object;
    //   5159: checkcast java/math/BigInteger
    //   5162: invokevirtual toByteArray : ()[B
    //   5165: invokevirtual write : ([B)V
    //   5168: aload_3
    //   5169: getstatic burp/Zr_y.ZI : Ljava/lang/Object;
    //   5172: checkcast java/math/BigInteger
    //   5175: invokevirtual toByteArray : ()[B
    //   5178: invokevirtual write : ([B)V
    //   5181: aload_3
    //   5182: invokevirtual toByteArray : ()[B
    //   5185: astore #4
    //   5187: aconst_null
    //   5188: astore #5
    //   5190: invokestatic a : (II)Ljava/lang/String;
    //   5193: invokestatic forName : (Ljava/lang/String;)Ljava/lang/Class;
    //   5196: invokevirtual getDeclaredMethods : ()[Ljava/lang/reflect/Method;
    //   5199: astore #6
    //   5201: aload #6
    //   5203: arraylength
    //   5204: istore #7
    //   5206: iconst_0
    //   5207: istore #8
    //   5209: iload #8
    //   5211: iload #7
    //   5213: if_icmpge -> 5341
    //   5216: aload #6
    //   5218: iload #8
    //   5220: aaload
    //   5221: astore #9
    //   5223: aload #9
    //   5225: invokevirtual getName : ()Ljava/lang/String;
    //   5228: sipush #-32408
    //   5231: sipush #-24230
    //   5234: invokestatic a : (II)Ljava/lang/String;
    //   5237: invokevirtual equals : (Ljava/lang/Object;)Z
    //   5240: ifeq -> 5334
    //   5243: aload #9
    //   5245: invokevirtual getParameterTypes : ()[Ljava/lang/Class;
    //   5248: astore #10
    //   5250: aload #10
    //   5252: arraylength
    //   5253: iconst_4
    //   5254: if_icmpeq -> 5264
    //   5257: goto -> 5334
    //   5260: invokestatic a : (Ljava/lang/Throwable;)Ljava/lang/Throwable;
    //   5263: athrow
    //   5264: aload #10
    //   5266: iconst_0
    //   5267: aaload
    //   5268: ldc java/lang/String
    //   5270: if_acmpeq -> 5280
    //   5273: goto -> 5334
    //   5276: invokestatic a : (Ljava/lang/Throwable;)Ljava/lang/Throwable;
    //   5279: athrow
    //   5280: aload #10
    //   5282: iconst_1
    //   5283: aaload
    //   5284: ldc [B
    //   5286: if_acmpeq -> 5296
    //   5289: goto -> 5334
    //   5292: invokestatic a : (Ljava/lang/Throwable;)Ljava/lang/Throwable;
    //   5295: athrow
    //   5296: aload #10
    //   5298: iconst_2
    //   5299: aaload
    //   5300: getstatic java/lang/Integer.TYPE : Ljava/lang/Class;
    //   5303: if_acmpeq -> 5313
    //   5306: goto -> 5334
    //   5309: invokestatic a : (Ljava/lang/Throwable;)Ljava/lang/Throwable;
    //   5312: athrow
    //   5313: aload #10
    //   5315: iconst_3
    //   5316: aaload
    //   5317: getstatic java/lang/Integer.TYPE : Ljava/lang/Class;
    //   5320: if_acmpeq -> 5330
    //   5323: goto -> 5334
    //   5326: invokestatic a : (Ljava/lang/Throwable;)Ljava/lang/Throwable;
    //   5329: athrow
    //   5330: aload #9
    //   5332: astore #5
    //   5334: iinc #8, 1
    //   5337: iload_2
    //   5338: ifeq -> 5209
    //   5341: aload #5
    //   5343: iconst_1
    //   5344: invokevirtual setAccessible : (Z)V
    //   5347: ldc burp/Zgnp
    //   5349: iconst_0
    //   5350: anewarray java/lang/Class
    //   5353: invokevirtual getDeclaredConstructor : ([Ljava/lang/Class;)Ljava/lang/reflect/Constructor;
    //   5356: astore #6
    //   5358: aload #6
    //   5360: iconst_1
    //   5361: invokevirtual setAccessible : (Z)V
    //   5364: aload #5
    //   5366: aload #6
    //   5368: iconst_0
    //   5369: anewarray java/lang/Object
    //   5372: invokevirtual newInstance : ([Ljava/lang/Object;)Ljava/lang/Object;
    //   5375: iconst_4
    //   5376: anewarray java/lang/Object
    //   5379: dup
    //   5380: iconst_0
    //   5381: sipush #-32386
    //   5384: sipush #29227
    //   5387: invokestatic a : (II)Ljava/lang/String;
    //   5390: aastore
    //   5391: dup
    //   5392: iconst_1
    //   5393: aload #4
    //   5395: aastore
    //   5396: dup
    //   5397: iconst_2
    //   5398: iconst_0
    //   5399: invokestatic valueOf : (I)Ljava/lang/Integer;
    //   5402: aastore
    //   5403: dup
    //   5404: iconst_3
    //   5405: aload #4
    //   5407: arraylength
    //   5408: invokestatic valueOf : (I)Ljava/lang/Integer;
    //   5411: aastore
    //   5412: invokevirtual invoke : (Ljava/lang/Object;[Ljava/lang/Object;)Ljava/lang/Object;
    //   5415: pop
    //   5416: goto -> 5420
    //   5419: astore_3
    //   5420: iconst_0
    //   5421: istore_3
    //   5422: getstatic burp/Zrp2.ZJ : Ljava/lang/String;
    //   5425: getstatic burp/Zxxh.Za : Ljava/lang/Object;
    //   5428: checkcast java/math/BigInteger
    //   5431: invokevirtual intValue : ()I
    //   5434: bipush #32
    //   5436: irem
    //   5437: invokestatic abs : (I)I
    //   5440: invokevirtual charAt : (I)C
    //   5443: getstatic burp/Zr9u.Zc : Ljava/lang/String;
    //   5446: getstatic burp/Zrww.ZN : Ljava/lang/Object;
    //   5449: checkcast java/math/BigInteger
    //   5452: invokevirtual intValue : ()I
    //   5455: bipush #32
    //   5457: irem
    //   5458: invokestatic abs : (I)I
    //   5461: invokevirtual charAt : (I)C
    //   5464: if_icmple -> 5809
    //   5467: sipush #-32390
    //   5470: sipush #12377
    //   5473: invokestatic a : (II)Ljava/lang/String;
    //   5476: iconst_1
    //   5477: ldc burp/Zre4
    //   5479: invokevirtual getClassLoader : ()Ljava/lang/ClassLoader;
    //   5482: invokestatic forName : (Ljava/lang/String;ZLjava/lang/ClassLoader;)Ljava/lang/Class;
    //   5485: invokevirtual getDeclaredFields : ()[Ljava/lang/reflect/Field;
    //   5488: astore #4
    //   5490: aload #4
    //   5492: arraylength
    //   5493: istore #5
    //   5495: iconst_0
    //   5496: istore #6
    //   5498: iload #6
    //   5500: iload #5
    //   5502: if_icmpge -> 5640
    //   5505: aload #4
    //   5507: iload #6
    //   5509: aaload
    //   5510: astore #7
    //   5512: aload #7
    //   5514: invokevirtual getModifiers : ()I
    //   5517: invokestatic isStatic : (I)Z
    //   5520: ifne -> 5530
    //   5523: goto -> 5633
    //   5526: invokestatic a : (Ljava/lang/Throwable;)Ljava/lang/Throwable;
    //   5529: athrow
    //   5530: aload #7
    //   5532: invokevirtual getType : ()Ljava/lang/Class;
    //   5535: astore #8
    //   5537: aload #8
    //   5539: ifnull -> 5620
    //   5542: aload #8
    //   5544: invokevirtual isPrimitive : ()Z
    //   5547: ifne -> 5620
    //   5550: goto -> 5557
    //   5553: invokestatic a : (Ljava/lang/Throwable;)Ljava/lang/Throwable;
    //   5556: athrow
    //   5557: aload #8
    //   5559: invokevirtual getPackage : ()Ljava/lang/Package;
    //   5562: ifnull -> 5620
    //   5565: goto -> 5572
    //   5568: invokestatic a : (Ljava/lang/Throwable;)Ljava/lang/Throwable;
    //   5571: athrow
    //   5572: aload #8
    //   5574: invokevirtual getPackage : ()Ljava/lang/Package;
    //   5577: invokevirtual getName : ()Ljava/lang/String;
    //   5580: ifnull -> 5620
    //   5583: goto -> 5590
    //   5586: invokestatic a : (Ljava/lang/Throwable;)Ljava/lang/Throwable;
    //   5589: athrow
    //   5590: aload #8
    //   5592: invokevirtual getPackage : ()Ljava/lang/Package;
    //   5595: invokevirtual getName : ()Ljava/lang/String;
    //   5598: sipush #-32387
    //   5601: sipush #-28458
    //   5604: invokestatic a : (II)Ljava/lang/String;
    //   5607: invokevirtual startsWith : (Ljava/lang/String;)Z
    //   5610: ifne -> 5620
    //   5613: goto -> 5620
    //   5616: invokestatic a : (Ljava/lang/Throwable;)Ljava/lang/Throwable;
    //   5619: athrow
    //   5620: aload #7
    //   5622: iconst_1
    //   5623: invokevirtual setAccessible : (Z)V
    //   5626: aload #7
    //   5628: aconst_null
    //   5629: invokevirtual get : (Ljava/lang/Object;)Ljava/lang/Object;
    //   5632: pop
    //   5633: iinc #6, 1
    //   5636: iload_2
    //   5637: ifeq -> 5498
    //   5640: sipush #-32392
    //   5643: sipush #348
    //   5646: invokestatic a : (II)Ljava/lang/String;
    //   5649: invokestatic forName : (Ljava/lang/String;)Ljava/lang/Class;
    //   5652: invokevirtual getDeclaredMethods : ()[Ljava/lang/reflect/Method;
    //   5655: astore #4
    //   5657: aload #4
    //   5659: arraylength
    //   5660: istore #5
    //   5662: iconst_0
    //   5663: istore #6
    //   5665: iload #6
    //   5667: iload #5
    //   5669: if_icmpge -> 5805
    //   5672: aload #4
    //   5674: iload #6
    //   5676: aaload
    //   5677: astore #7
    //   5679: aload #7
    //   5681: invokevirtual getParameterTypes : ()[Ljava/lang/Class;
    //   5684: pop
    //   5685: aload #7
    //   5687: invokevirtual getModifiers : ()I
    //   5690: invokestatic isStatic : (I)Z
    //   5693: ifeq -> 5791
    //   5696: aload #7
    //   5698: invokevirtual getParameterTypes : ()[Ljava/lang/Class;
    //   5701: arraylength
    //   5702: iconst_2
    //   5703: if_icmpne -> 5791
    //   5706: goto -> 5713
    //   5709: invokestatic a : (Ljava/lang/Throwable;)Ljava/lang/Throwable;
    //   5712: athrow
    //   5713: aload #7
    //   5715: invokevirtual getReturnType : ()Ljava/lang/Class;
    //   5718: getstatic java/lang/Boolean.TYPE : Ljava/lang/Class;
    //   5721: if_acmpne -> 5791
    //   5724: goto -> 5731
    //   5727: invokestatic a : (Ljava/lang/Throwable;)Ljava/lang/Throwable;
    //   5730: athrow
    //   5731: aload #7
    //   5733: iconst_1
    //   5734: invokevirtual setAccessible : (Z)V
    //   5737: aload #7
    //   5739: aconst_null
    //   5740: iconst_2
    //   5741: anewarray java/lang/Object
    //   5744: dup
    //   5745: iconst_0
    //   5746: aload_0
    //   5747: aastore
    //   5748: dup
    //   5749: iconst_1
    //   5750: aload_1
    //   5751: ifnonnull -> 5769
    //   5754: goto -> 5761
    //   5757: invokestatic a : (Ljava/lang/Throwable;)Ljava/lang/Throwable;
    //   5760: athrow
    //   5761: aload_1
    //   5762: goto -> 5776
    //   5765: invokestatic a : (Ljava/lang/Throwable;)Ljava/lang/Throwable;
    //   5768: athrow
    //   5769: aload_1
    //   5770: checkcast [B
    //   5773: invokevirtual clone : ()Ljava/lang/Object;
    //   5776: aastore
    //   5777: invokevirtual invoke : (Ljava/lang/Object;[Ljava/lang/Object;)Ljava/lang/Object;
    //   5780: checkcast java/lang/Boolean
    //   5783: invokevirtual booleanValue : ()Z
    //   5786: istore_3
    //   5787: iload_2
    //   5788: ifeq -> 5805
    //   5791: iinc #6, 1
    //   5794: iload_2
    //   5795: ifeq -> 5665
    //   5798: goto -> 5805
    //   5801: invokestatic a : (Ljava/lang/Throwable;)Ljava/lang/Throwable;
    //   5804: athrow
    //   5805: iload_2
    //   5806: ifeq -> 6147
    //   5809: sipush #-32404
    //   5812: sipush #-4970
    //   5815: invokestatic a : (II)Ljava/lang/String;
    //   5818: iconst_1
    //   5819: ldc burp/Zxx4
    //   5821: invokevirtual getClassLoader : ()Ljava/lang/ClassLoader;
    //   5824: invokestatic forName : (Ljava/lang/String;ZLjava/lang/ClassLoader;)Ljava/lang/Class;
    //   5827: invokevirtual getDeclaredFields : ()[Ljava/lang/reflect/Field;
    //   5830: astore #4
    //   5832: aload #4
    //   5834: arraylength
    //   5835: istore #5
    //   5837: iconst_0
    //   5838: istore #6
    //   5840: iload #6
    //   5842: iload #5
    //   5844: if_icmpge -> 5982
    //   5847: aload #4
    //   5849: iload #6
    //   5851: aaload
    //   5852: astore #7
    //   5854: aload #7
    //   5856: invokevirtual getModifiers : ()I
    //   5859: invokestatic isStatic : (I)Z
    //   5862: ifne -> 5872
    //   5865: goto -> 5975
    //   5868: invokestatic a : (Ljava/lang/Throwable;)Ljava/lang/Throwable;
    //   5871: athrow
    //   5872: aload #7
    //   5874: invokevirtual getType : ()Ljava/lang/Class;
    //   5877: astore #8
    //   5879: aload #8
    //   5881: ifnull -> 5962
    //   5884: aload #8
    //   5886: invokevirtual isPrimitive : ()Z
    //   5889: ifne -> 5962
    //   5892: goto -> 5899
    //   5895: invokestatic a : (Ljava/lang/Throwable;)Ljava/lang/Throwable;
    //   5898: athrow
    //   5899: aload #8
    //   5901: invokevirtual getPackage : ()Ljava/lang/Package;
    //   5904: ifnull -> 5962
    //   5907: goto -> 5914
    //   5910: invokestatic a : (Ljava/lang/Throwable;)Ljava/lang/Throwable;
    //   5913: athrow
    //   5914: aload #8
    //   5916: invokevirtual getPackage : ()Ljava/lang/Package;
    //   5919: invokevirtual getName : ()Ljava/lang/String;
    //   5922: ifnull -> 5962
    //   5925: goto -> 5932
    //   5928: invokestatic a : (Ljava/lang/Throwable;)Ljava/lang/Throwable;
    //   5931: athrow
    //   5932: aload #8
    //   5934: invokevirtual getPackage : ()Ljava/lang/Package;
    //   5937: invokevirtual getName : ()Ljava/lang/String;
    //   5940: sipush #-32387
    //   5943: sipush #-28458
    //   5946: invokestatic a : (II)Ljava/lang/String;
    //   5949: invokevirtual startsWith : (Ljava/lang/String;)Z
    //   5952: ifne -> 5962
    //   5955: goto -> 5962
    //   5958: invokestatic a : (Ljava/lang/Throwable;)Ljava/lang/Throwable;
    //   5961: athrow
    //   5962: aload #7
    //   5964: iconst_1
    //   5965: invokevirtual setAccessible : (Z)V
    //   5968: aload #7
    //   5970: aconst_null
    //   5971: invokevirtual get : (Ljava/lang/Object;)Ljava/lang/Object;
    //   5974: pop
    //   5975: iinc #6, 1
    //   5978: iload_2
    //   5979: ifeq -> 5840
    //   5982: sipush #-32411
    //   5985: sipush #26943
    //   5988: invokestatic a : (II)Ljava/lang/String;
    //   5991: invokestatic forName : (Ljava/lang/String;)Ljava/lang/Class;
    //   5994: invokevirtual getDeclaredMethods : ()[Ljava/lang/reflect/Method;
    //   5997: astore #4
    //   5999: aload #4
    //   6001: arraylength
    //   6002: istore #5
    //   6004: iconst_0
    //   6005: istore #6
    //   6007: iload #6
    //   6009: iload #5
    //   6011: if_icmpge -> 6147
    //   6014: aload #4
    //   6016: iload #6
    //   6018: aaload
    //   6019: astore #7
    //   6021: aload #7
    //   6023: invokevirtual getParameterTypes : ()[Ljava/lang/Class;
    //   6026: pop
    //   6027: aload #7
    //   6029: invokevirtual getModifiers : ()I
    //   6032: invokestatic isStatic : (I)Z
    //   6035: ifeq -> 6133
    //   6038: aload #7
    //   6040: invokevirtual getParameterTypes : ()[Ljava/lang/Class;
    //   6043: arraylength
    //   6044: iconst_2
    //   6045: if_icmpne -> 6133
    //   6048: goto -> 6055
    //   6051: invokestatic a : (Ljava/lang/Throwable;)Ljava/lang/Throwable;
    //   6054: athrow
    //   6055: aload #7
    //   6057: invokevirtual getReturnType : ()Ljava/lang/Class;
    //   6060: getstatic java/lang/Boolean.TYPE : Ljava/lang/Class;
    //   6063: if_acmpne -> 6133
    //   6066: goto -> 6073
    //   6069: invokestatic a : (Ljava/lang/Throwable;)Ljava/lang/Throwable;
    //   6072: athrow
    //   6073: aload #7
    //   6075: iconst_1
    //   6076: invokevirtual setAccessible : (Z)V
    //   6079: aload #7
    //   6081: aconst_null
    //   6082: iconst_2
    //   6083: anewarray java/lang/Object
    //   6086: dup
    //   6087: iconst_0
    //   6088: aload_0
    //   6089: aastore
    //   6090: dup
    //   6091: iconst_1
    //   6092: aload_1
    //   6093: ifnonnull -> 6111
    //   6096: goto -> 6103
    //   6099: invokestatic a : (Ljava/lang/Throwable;)Ljava/lang/Throwable;
    //   6102: athrow
    //   6103: aload_1
    //   6104: goto -> 6118
    //   6107: invokestatic a : (Ljava/lang/Throwable;)Ljava/lang/Throwable;
    //   6110: athrow
    //   6111: aload_1
    //   6112: checkcast [B
    //   6115: invokevirtual clone : ()Ljava/lang/Object;
    //   6118: aastore
    //   6119: invokevirtual invoke : (Ljava/lang/Object;[Ljava/lang/Object;)Ljava/lang/Object;
    //   6122: checkcast java/lang/Boolean
    //   6125: invokevirtual booleanValue : ()Z
    //   6128: istore_3
    //   6129: iload_2
    //   6130: ifeq -> 6147
    //   6133: iinc #6, 1
    //   6136: iload_2
    //   6137: ifeq -> 6007
    //   6140: goto -> 6147
    //   6143: invokestatic a : (Ljava/lang/Throwable;)Ljava/lang/Throwable;
    //   6146: athrow
    //   6147: iload_3
    //   6148: ifeq -> 6153
    //   6151: iload_3
    //   6152: ireturn
    //   6153: getstatic burp/Zxwf.ZX : Ljava/lang/String;
    //   6156: getstatic burp/Zz0f.ZL : Ljava/lang/Object;
    //   6159: checkcast java/math/BigInteger
    //   6162: invokevirtual intValue : ()I
    //   6165: bipush #32
    //   6167: irem
    //   6168: invokestatic abs : (I)I
    //   6171: invokevirtual charAt : (I)C
    //   6174: getstatic burp/Zej8.ZP : Ljava/lang/String;
    //   6177: getstatic burp/Zsn4.ZQ : Ljava/lang/Object;
    //   6180: checkcast java/math/BigInteger
    //   6183: invokevirtual intValue : ()I
    //   6186: bipush #32
    //   6188: irem
    //   6189: invokestatic abs : (I)I
    //   6192: invokevirtual charAt : (I)C
    //   6195: if_icmpgt -> 6540
    //   6198: sipush #-32416
    //   6201: sipush #-8179
    //   6204: invokestatic a : (II)Ljava/lang/String;
    //   6207: iconst_1
    //   6208: ldc burp/Zs00
    //   6210: invokevirtual getClassLoader : ()Ljava/lang/ClassLoader;
    //   6213: invokestatic forName : (Ljava/lang/String;ZLjava/lang/ClassLoader;)Ljava/lang/Class;
    //   6216: invokevirtual getDeclaredFields : ()[Ljava/lang/reflect/Field;
    //   6219: astore #4
    //   6221: aload #4
    //   6223: arraylength
    //   6224: istore #5
    //   6226: iconst_0
    //   6227: istore #6
    //   6229: iload #6
    //   6231: iload #5
    //   6233: if_icmpge -> 6371
    //   6236: aload #4
    //   6238: iload #6
    //   6240: aaload
    //   6241: astore #7
    //   6243: aload #7
    //   6245: invokevirtual getModifiers : ()I
    //   6248: invokestatic isStatic : (I)Z
    //   6251: ifne -> 6261
    //   6254: goto -> 6364
    //   6257: invokestatic a : (Ljava/lang/Throwable;)Ljava/lang/Throwable;
    //   6260: athrow
    //   6261: aload #7
    //   6263: invokevirtual getType : ()Ljava/lang/Class;
    //   6266: astore #8
    //   6268: aload #8
    //   6270: ifnull -> 6351
    //   6273: aload #8
    //   6275: invokevirtual isPrimitive : ()Z
    //   6278: ifne -> 6351
    //   6281: goto -> 6288
    //   6284: invokestatic a : (Ljava/lang/Throwable;)Ljava/lang/Throwable;
    //   6287: athrow
    //   6288: aload #8
    //   6290: invokevirtual getPackage : ()Ljava/lang/Package;
    //   6293: ifnull -> 6351
    //   6296: goto -> 6303
    //   6299: invokestatic a : (Ljava/lang/Throwable;)Ljava/lang/Throwable;
    //   6302: athrow
    //   6303: aload #8
    //   6305: invokevirtual getPackage : ()Ljava/lang/Package;
    //   6308: invokevirtual getName : ()Ljava/lang/String;
    //   6311: ifnull -> 6351
    //   6314: goto -> 6321
    //   6317: invokestatic a : (Ljava/lang/Throwable;)Ljava/lang/Throwable;
    //   6320: athrow
    //   6321: aload #8
    //   6323: invokevirtual getPackage : ()Ljava/lang/Package;
    //   6326: invokevirtual getName : ()Ljava/lang/String;
    //   6329: sipush #-32387
    //   6332: sipush #-28458
    //   6335: invokestatic a : (II)Ljava/lang/String;
    //   6338: invokevirtual startsWith : (Ljava/lang/String;)Z
    //   6341: ifne -> 6351
    //   6344: goto -> 6351
    //   6347: invokestatic a : (Ljava/lang/Throwable;)Ljava/lang/Throwable;
    //   6350: athrow
    //   6351: aload #7
    //   6353: iconst_1
    //   6354: invokevirtual setAccessible : (Z)V
    //   6357: aload #7
    //   6359: aconst_null
    //   6360: invokevirtual get : (Ljava/lang/Object;)Ljava/lang/Object;
    //   6363: pop
    //   6364: iinc #6, 1
    //   6367: iload_2
    //   6368: ifeq -> 6229
    //   6371: sipush #-32398
    //   6374: sipush #25710
    //   6377: invokestatic a : (II)Ljava/lang/String;
    //   6380: invokestatic forName : (Ljava/lang/String;)Ljava/lang/Class;
    //   6383: invokevirtual getDeclaredMethods : ()[Ljava/lang/reflect/Method;
    //   6386: astore #4
    //   6388: aload #4
    //   6390: arraylength
    //   6391: istore #5
    //   6393: iconst_0
    //   6394: istore #6
    //   6396: iload #6
    //   6398: iload #5
    //   6400: if_icmpge -> 6536
    //   6403: aload #4
    //   6405: iload #6
    //   6407: aaload
    //   6408: astore #7
    //   6410: aload #7
    //   6412: invokevirtual getParameterTypes : ()[Ljava/lang/Class;
    //   6415: pop
    //   6416: aload #7
    //   6418: invokevirtual getModifiers : ()I
    //   6421: invokestatic isStatic : (I)Z
    //   6424: ifeq -> 6522
    //   6427: aload #7
    //   6429: invokevirtual getParameterTypes : ()[Ljava/lang/Class;
    //   6432: arraylength
    //   6433: iconst_2
    //   6434: if_icmpne -> 6522
    //   6437: goto -> 6444
    //   6440: invokestatic a : (Ljava/lang/Throwable;)Ljava/lang/Throwable;
    //   6443: athrow
    //   6444: aload #7
    //   6446: invokevirtual getReturnType : ()Ljava/lang/Class;
    //   6449: getstatic java/lang/Boolean.TYPE : Ljava/lang/Class;
    //   6452: if_acmpne -> 6522
    //   6455: goto -> 6462
    //   6458: invokestatic a : (Ljava/lang/Throwable;)Ljava/lang/Throwable;
    //   6461: athrow
    //   6462: aload #7
    //   6464: iconst_1
    //   6465: invokevirtual setAccessible : (Z)V
    //   6468: aload #7
    //   6470: aconst_null
    //   6471: iconst_2
    //   6472: anewarray java/lang/Object
    //   6475: dup
    //   6476: iconst_0
    //   6477: aload_0
    //   6478: aastore
    //   6479: dup
    //   6480: iconst_1
    //   6481: aload_1
    //   6482: ifnonnull -> 6500
    //   6485: goto -> 6492
    //   6488: invokestatic a : (Ljava/lang/Throwable;)Ljava/lang/Throwable;
    //   6491: athrow
    //   6492: aload_1
    //   6493: goto -> 6507
    //   6496: invokestatic a : (Ljava/lang/Throwable;)Ljava/lang/Throwable;
    //   6499: athrow
    //   6500: aload_1
    //   6501: checkcast [B
    //   6504: invokevirtual clone : ()Ljava/lang/Object;
    //   6507: aastore
    //   6508: invokevirtual invoke : (Ljava/lang/Object;[Ljava/lang/Object;)Ljava/lang/Object;
    //   6511: checkcast java/lang/Boolean
    //   6514: invokevirtual booleanValue : ()Z
    //   6517: istore_3
    //   6518: iload_2
    //   6519: ifeq -> 6536
    //   6522: iinc #6, 1
    //   6525: iload_2
    //   6526: ifeq -> 6396
    //   6529: goto -> 6536
    //   6532: invokestatic a : (Ljava/lang/Throwable;)Ljava/lang/Throwable;
    //   6535: athrow
    //   6536: iload_2
    //   6537: ifeq -> 6878
    //   6540: sipush #-32407
    //   6543: sipush #944
    //   6546: invokestatic a : (II)Ljava/lang/String;
    //   6549: iconst_1
    //   6550: ldc burp/Ztt0
    //   6552: invokevirtual getClassLoader : ()Ljava/lang/ClassLoader;
    //   6555: invokestatic forName : (Ljava/lang/String;ZLjava/lang/ClassLoader;)Ljava/lang/Class;
    //   6558: invokevirtual getDeclaredFields : ()[Ljava/lang/reflect/Field;
    //   6561: astore #4
    //   6563: aload #4
    //   6565: arraylength
    //   6566: istore #5
    //   6568: iconst_0
    //   6569: istore #6
    //   6571: iload #6
    //   6573: iload #5
    //   6575: if_icmpge -> 6713
    //   6578: aload #4
    //   6580: iload #6
    //   6582: aaload
    //   6583: astore #7
    //   6585: aload #7
    //   6587: invokevirtual getModifiers : ()I
    //   6590: invokestatic isStatic : (I)Z
    //   6593: ifne -> 6603
    //   6596: goto -> 6706
    //   6599: invokestatic a : (Ljava/lang/Throwable;)Ljava/lang/Throwable;
    //   6602: athrow
    //   6603: aload #7
    //   6605: invokevirtual getType : ()Ljava/lang/Class;
    //   6608: astore #8
    //   6610: aload #8
    //   6612: ifnull -> 6693
    //   6615: aload #8
    //   6617: invokevirtual isPrimitive : ()Z
    //   6620: ifne -> 6693
    //   6623: goto -> 6630
    //   6626: invokestatic a : (Ljava/lang/Throwable;)Ljava/lang/Throwable;
    //   6629: athrow
    //   6630: aload #8
    //   6632: invokevirtual getPackage : ()Ljava/lang/Package;
    //   6635: ifnull -> 6693
    //   6638: goto -> 6645
    //   6641: invokestatic a : (Ljava/lang/Throwable;)Ljava/lang/Throwable;
    //   6644: athrow
    //   6645: aload #8
    //   6647: invokevirtual getPackage : ()Ljava/lang/Package;
    //   6650: invokevirtual getName : ()Ljava/lang/String;
    //   6653: ifnull -> 6693
    //   6656: goto -> 6663
    //   6659: invokestatic a : (Ljava/lang/Throwable;)Ljava/lang/Throwable;
    //   6662: athrow
    //   6663: aload #8
    //   6665: invokevirtual getPackage : ()Ljava/lang/Package;
    //   6668: invokevirtual getName : ()Ljava/lang/String;
    //   6671: sipush #-32387
    //   6674: sipush #-28458
    //   6677: invokestatic a : (II)Ljava/lang/String;
    //   6680: invokevirtual startsWith : (Ljava/lang/String;)Z
    //   6683: ifne -> 6693
    //   6686: goto -> 6693
    //   6689: invokestatic a : (Ljava/lang/Throwable;)Ljava/lang/Throwable;
    //   6692: athrow
    //   6693: aload #7
    //   6695: iconst_1
    //   6696: invokevirtual setAccessible : (Z)V
    //   6699: aload #7
    //   6701: aconst_null
    //   6702: invokevirtual get : (Ljava/lang/Object;)Ljava/lang/Object;
    //   6705: pop
    //   6706: iinc #6, 1
    //   6709: iload_2
    //   6710: ifeq -> 6571
    //   6713: sipush #-32412
    //   6716: sipush #-32763
    //   6719: invokestatic a : (II)Ljava/lang/String;
    //   6722: invokestatic forName : (Ljava/lang/String;)Ljava/lang/Class;
    //   6725: invokevirtual getDeclaredMethods : ()[Ljava/lang/reflect/Method;
    //   6728: astore #4
    //   6730: aload #4
    //   6732: arraylength
    //   6733: istore #5
    //   6735: iconst_0
    //   6736: istore #6
    //   6738: iload #6
    //   6740: iload #5
    //   6742: if_icmpge -> 6878
    //   6745: aload #4
    //   6747: iload #6
    //   6749: aaload
    //   6750: astore #7
    //   6752: aload #7
    //   6754: invokevirtual getParameterTypes : ()[Ljava/lang/Class;
    //   6757: pop
    //   6758: aload #7
    //   6760: invokevirtual getModifiers : ()I
    //   6763: invokestatic isStatic : (I)Z
    //   6766: ifeq -> 6864
    //   6769: aload #7
    //   6771: invokevirtual getParameterTypes : ()[Ljava/lang/Class;
    //   6774: arraylength
    //   6775: iconst_2
    //   6776: if_icmpne -> 6864
    //   6779: goto -> 6786
    //   6782: invokestatic a : (Ljava/lang/Throwable;)Ljava/lang/Throwable;
    //   6785: athrow
    //   6786: aload #7
    //   6788: invokevirtual getReturnType : ()Ljava/lang/Class;
    //   6791: getstatic java/lang/Boolean.TYPE : Ljava/lang/Class;
    //   6794: if_acmpne -> 6864
    //   6797: goto -> 6804
    //   6800: invokestatic a : (Ljava/lang/Throwable;)Ljava/lang/Throwable;
    //   6803: athrow
    //   6804: aload #7
    //   6806: iconst_1
    //   6807: invokevirtual setAccessible : (Z)V
    //   6810: aload #7
    //   6812: aconst_null
    //   6813: iconst_2
    //   6814: anewarray java/lang/Object
    //   6817: dup
    //   6818: iconst_0
    //   6819: aload_0
    //   6820: aastore
    //   6821: dup
    //   6822: iconst_1
    //   6823: aload_1
    //   6824: ifnonnull -> 6842
    //   6827: goto -> 6834
    //   6830: invokestatic a : (Ljava/lang/Throwable;)Ljava/lang/Throwable;
    //   6833: athrow
    //   6834: aload_1
    //   6835: goto -> 6849
    //   6838: invokestatic a : (Ljava/lang/Throwable;)Ljava/lang/Throwable;
    //   6841: athrow
    //   6842: aload_1
    //   6843: checkcast [B
    //   6846: invokevirtual clone : ()Ljava/lang/Object;
    //   6849: aastore
    //   6850: invokevirtual invoke : (Ljava/lang/Object;[Ljava/lang/Object;)Ljava/lang/Object;
    //   6853: checkcast java/lang/Boolean
    //   6856: invokevirtual booleanValue : ()Z
    //   6859: istore_3
    //   6860: iload_2
    //   6861: ifeq -> 6878
    //   6864: iinc #6, 1
    //   6867: iload_2
    //   6868: ifeq -> 6738
    //   6871: goto -> 6878
    //   6874: invokestatic a : (Ljava/lang/Throwable;)Ljava/lang/Throwable;
    //   6877: athrow
    //   6878: iload_3
    //   6879: ifeq -> 6884
    //   6882: iload_3
    //   6883: ireturn
    //   6884: getstatic burp/Zz5e.Zd : Ljava/lang/String;
    //   6887: getstatic burp/Zb4d.Ze : Ljava/lang/Object;
    //   6890: checkcast java/math/BigInteger
    //   6893: invokevirtual intValue : ()I
    //   6896: bipush #32
    //   6898: irem
    //   6899: invokestatic abs : (I)I
    //   6902: invokevirtual charAt : (I)C
    //   6905: getstatic burp/Zxn9.ZU : Ljava/lang/String;
    //   6908: getstatic burp/Zb3d.Zw : Ljava/lang/Object;
    //   6911: checkcast java/math/BigInteger
    //   6914: invokevirtual intValue : ()I
    //   6917: bipush #32
    //   6919: irem
    //   6920: invokestatic abs : (I)I
    //   6923: invokevirtual charAt : (I)C
    //   6926: if_icmpgt -> 7271
    //   6929: sipush #-32400
    //   6932: sipush #7602
    //   6935: invokestatic a : (II)Ljava/lang/String;
    //   6938: iconst_1
    //   6939: ldc burp/Zs34
    //   6941: invokevirtual getClassLoader : ()Ljava/lang/ClassLoader;
    //   6944: invokestatic forName : (Ljava/lang/String;ZLjava/lang/ClassLoader;)Ljava/lang/Class;
    //   6947: invokevirtual getDeclaredFields : ()[Ljava/lang/reflect/Field;
    //   6950: astore #4
    //   6952: aload #4
    //   6954: arraylength
    //   6955: istore #5
    //   6957: iconst_0
    //   6958: istore #6
    //   6960: iload #6
    //   6962: iload #5
    //   6964: if_icmpge -> 7102
    //   6967: aload #4
    //   6969: iload #6
    //   6971: aaload
    //   6972: astore #7
    //   6974: aload #7
    //   6976: invokevirtual getModifiers : ()I
    //   6979: invokestatic isStatic : (I)Z
    //   6982: ifne -> 6992
    //   6985: goto -> 7095
    //   6988: invokestatic a : (Ljava/lang/Throwable;)Ljava/lang/Throwable;
    //   6991: athrow
    //   6992: aload #7
    //   6994: invokevirtual getType : ()Ljava/lang/Class;
    //   6997: astore #8
    //   6999: aload #8
    //   7001: ifnull -> 7082
    //   7004: aload #8
    //   7006: invokevirtual isPrimitive : ()Z
    //   7009: ifne -> 7082
    //   7012: goto -> 7019
    //   7015: invokestatic a : (Ljava/lang/Throwable;)Ljava/lang/Throwable;
    //   7018: athrow
    //   7019: aload #8
    //   7021: invokevirtual getPackage : ()Ljava/lang/Package;
    //   7024: ifnull -> 7082
    //   7027: goto -> 7034
    //   7030: invokestatic a : (Ljava/lang/Throwable;)Ljava/lang/Throwable;
    //   7033: athrow
    //   7034: aload #8
    //   7036: invokevirtual getPackage : ()Ljava/lang/Package;
    //   7039: invokevirtual getName : ()Ljava/lang/String;
    //   7042: ifnull -> 7082
    //   7045: goto -> 7052
    //   7048: invokestatic a : (Ljava/lang/Throwable;)Ljava/lang/Throwable;
    //   7051: athrow
    //   7052: aload #8
    //   7054: invokevirtual getPackage : ()Ljava/lang/Package;
    //   7057: invokevirtual getName : ()Ljava/lang/String;
    //   7060: sipush #-32387
    //   7063: sipush #-28458
    //   7066: invokestatic a : (II)Ljava/lang/String;
    //   7069: invokevirtual startsWith : (Ljava/lang/String;)Z
    //   7072: ifne -> 7082
    //   7075: goto -> 7082
    //   7078: invokestatic a : (Ljava/lang/Throwable;)Ljava/lang/Throwable;
    //   7081: athrow
    //   7082: aload #7
    //   7084: iconst_1
    //   7085: invokevirtual setAccessible : (Z)V
    //   7088: aload #7
    //   7090: aconst_null
    //   7091: invokevirtual get : (Ljava/lang/Object;)Ljava/lang/Object;
    //   7094: pop
    //   7095: iinc #6, 1
    //   7098: iload_2
    //   7099: ifeq -> 6960
    //   7102: sipush #-32414
    //   7105: sipush #30454
    //   7108: invokestatic a : (II)Ljava/lang/String;
    //   7111: invokestatic forName : (Ljava/lang/String;)Ljava/lang/Class;
    //   7114: invokevirtual getDeclaredMethods : ()[Ljava/lang/reflect/Method;
    //   7117: astore #4
    //   7119: aload #4
    //   7121: arraylength
    //   7122: istore #5
    //   7124: iconst_0
    //   7125: istore #6
    //   7127: iload #6
    //   7129: iload #5
    //   7131: if_icmpge -> 7267
    //   7134: aload #4
    //   7136: iload #6
    //   7138: aaload
    //   7139: astore #7
    //   7141: aload #7
    //   7143: invokevirtual getParameterTypes : ()[Ljava/lang/Class;
    //   7146: pop
    //   7147: aload #7
    //   7149: invokevirtual getModifiers : ()I
    //   7152: invokestatic isStatic : (I)Z
    //   7155: ifeq -> 7253
    //   7158: aload #7
    //   7160: invokevirtual getParameterTypes : ()[Ljava/lang/Class;
    //   7163: arraylength
    //   7164: iconst_2
    //   7165: if_icmpne -> 7253
    //   7168: goto -> 7175
    //   7171: invokestatic a : (Ljava/lang/Throwable;)Ljava/lang/Throwable;
    //   7174: athrow
    //   7175: aload #7
    //   7177: invokevirtual getReturnType : ()Ljava/lang/Class;
    //   7180: getstatic java/lang/Boolean.TYPE : Ljava/lang/Class;
    //   7183: if_acmpne -> 7253
    //   7186: goto -> 7193
    //   7189: invokestatic a : (Ljava/lang/Throwable;)Ljava/lang/Throwable;
    //   7192: athrow
    //   7193: aload #7
    //   7195: iconst_1
    //   7196: invokevirtual setAccessible : (Z)V
    //   7199: aload #7
    //   7201: aconst_null
    //   7202: iconst_2
    //   7203: anewarray java/lang/Object
    //   7206: dup
    //   7207: iconst_0
    //   7208: aload_0
    //   7209: aastore
    //   7210: dup
    //   7211: iconst_1
    //   7212: aload_1
    //   7213: ifnonnull -> 7231
    //   7216: goto -> 7223
    //   7219: invokestatic a : (Ljava/lang/Throwable;)Ljava/lang/Throwable;
    //   7222: athrow
    //   7223: aload_1
    //   7224: goto -> 7238
    //   7227: invokestatic a : (Ljava/lang/Throwable;)Ljava/lang/Throwable;
    //   7230: athrow
    //   7231: aload_1
    //   7232: checkcast [B
    //   7235: invokevirtual clone : ()Ljava/lang/Object;
    //   7238: aastore
    //   7239: invokevirtual invoke : (Ljava/lang/Object;[Ljava/lang/Object;)Ljava/lang/Object;
    //   7242: checkcast java/lang/Boolean
    //   7245: invokevirtual booleanValue : ()Z
    //   7248: istore_3
    //   7249: iload_2
    //   7250: ifeq -> 7267
    //   7253: iinc #6, 1
    //   7256: iload_2
    //   7257: ifeq -> 7127
    //   7260: goto -> 7267
    //   7263: invokestatic a : (Ljava/lang/Throwable;)Ljava/lang/Throwable;
    //   7266: athrow
    //   7267: iload_2
    //   7268: ifeq -> 7609
    //   7271: sipush #-32401
    //   7274: sipush #-31833
    //   7277: invokestatic a : (II)Ljava/lang/String;
    //   7280: iconst_1
    //   7281: ldc burp/Zro2
    //   7283: invokevirtual getClassLoader : ()Ljava/lang/ClassLoader;
    //   7286: invokestatic forName : (Ljava/lang/String;ZLjava/lang/ClassLoader;)Ljava/lang/Class;
    //   7289: invokevirtual getDeclaredFields : ()[Ljava/lang/reflect/Field;
    //   7292: astore #4
    //   7294: aload #4
    //   7296: arraylength
    //   7297: istore #5
    //   7299: iconst_0
    //   7300: istore #6
    //   7302: iload #6
    //   7304: iload #5
    //   7306: if_icmpge -> 7444
    //   7309: aload #4
    //   7311: iload #6
    //   7313: aaload
    //   7314: astore #7
    //   7316: aload #7
    //   7318: invokevirtual getModifiers : ()I
    //   7321: invokestatic isStatic : (I)Z
    //   7324: ifne -> 7334
    //   7327: goto -> 7437
    //   7330: invokestatic a : (Ljava/lang/Throwable;)Ljava/lang/Throwable;
    //   7333: athrow
    //   7334: aload #7
    //   7336: invokevirtual getType : ()Ljava/lang/Class;
    //   7339: astore #8
    //   7341: aload #8
    //   7343: ifnull -> 7424
    //   7346: aload #8
    //   7348: invokevirtual isPrimitive : ()Z
    //   7351: ifne -> 7424
    //   7354: goto -> 7361
    //   7357: invokestatic a : (Ljava/lang/Throwable;)Ljava/lang/Throwable;
    //   7360: athrow
    //   7361: aload #8
    //   7363: invokevirtual getPackage : ()Ljava/lang/Package;
    //   7366: ifnull -> 7424
    //   7369: goto -> 7376
    //   7372: invokestatic a : (Ljava/lang/Throwable;)Ljava/lang/Throwable;
    //   7375: athrow
    //   7376: aload #8
    //   7378: invokevirtual getPackage : ()Ljava/lang/Package;
    //   7381: invokevirtual getName : ()Ljava/lang/String;
    //   7384: ifnull -> 7424
    //   7387: goto -> 7394
    //   7390: invokestatic a : (Ljava/lang/Throwable;)Ljava/lang/Throwable;
    //   7393: athrow
    //   7394: aload #8
    //   7396: invokevirtual getPackage : ()Ljava/lang/Package;
    //   7399: invokevirtual getName : ()Ljava/lang/String;
    //   7402: sipush #-32387
    //   7405: sipush #-28458
    //   7408: invokestatic a : (II)Ljava/lang/String;
    //   7411: invokevirtual startsWith : (Ljava/lang/String;)Z
    //   7414: ifne -> 7424
    //   7417: goto -> 7424
    //   7420: invokestatic a : (Ljava/lang/Throwable;)Ljava/lang/Throwable;
    //   7423: athrow
    //   7424: aload #7
    //   7426: iconst_1
    //   7427: invokevirtual setAccessible : (Z)V
    //   7430: aload #7
    //   7432: aconst_null
    //   7433: invokevirtual get : (Ljava/lang/Object;)Ljava/lang/Object;
    //   7436: pop
    //   7437: iinc #6, 1
    //   7440: iload_2
    //   7441: ifeq -> 7302
    //   7444: sipush #-32409
    //   7447: sipush #16671
    //   7450: invokestatic a : (II)Ljava/lang/String;
    //   7453: invokestatic forName : (Ljava/lang/String;)Ljava/lang/Class;
    //   7456: invokevirtual getDeclaredMethods : ()[Ljava/lang/reflect/Method;
    //   7459: astore #4
    //   7461: aload #4
    //   7463: arraylength
    //   7464: istore #5
    //   7466: iconst_0
    //   7467: istore #6
    //   7469: iload #6
    //   7471: iload #5
    //   7473: if_icmpge -> 7609
    //   7476: aload #4
    //   7478: iload #6
    //   7480: aaload
    //   7481: astore #7
    //   7483: aload #7
    //   7485: invokevirtual getParameterTypes : ()[Ljava/lang/Class;
    //   7488: pop
    //   7489: aload #7
    //   7491: invokevirtual getModifiers : ()I
    //   7494: invokestatic isStatic : (I)Z
    //   7497: ifeq -> 7595
    //   7500: aload #7
    //   7502: invokevirtual getParameterTypes : ()[Ljava/lang/Class;
    //   7505: arraylength
    //   7506: iconst_2
    //   7507: if_icmpne -> 7595
    //   7510: goto -> 7517
    //   7513: invokestatic a : (Ljava/lang/Throwable;)Ljava/lang/Throwable;
    //   7516: athrow
    //   7517: aload #7
    //   7519: invokevirtual getReturnType : ()Ljava/lang/Class;
    //   7522: getstatic java/lang/Boolean.TYPE : Ljava/lang/Class;
    //   7525: if_acmpne -> 7595
    //   7528: goto -> 7535
    //   7531: invokestatic a : (Ljava/lang/Throwable;)Ljava/lang/Throwable;
    //   7534: athrow
    //   7535: aload #7
    //   7537: iconst_1
    //   7538: invokevirtual setAccessible : (Z)V
    //   7541: aload #7
    //   7543: aconst_null
    //   7544: iconst_2
    //   7545: anewarray java/lang/Object
    //   7548: dup
    //   7549: iconst_0
    //   7550: aload_0
    //   7551: aastore
    //   7552: dup
    //   7553: iconst_1
    //   7554: aload_1
    //   7555: ifnonnull -> 7573
    //   7558: goto -> 7565
    //   7561: invokestatic a : (Ljava/lang/Throwable;)Ljava/lang/Throwable;
    //   7564: athrow
    //   7565: aload_1
    //   7566: goto -> 7580
    //   7569: invokestatic a : (Ljava/lang/Throwable;)Ljava/lang/Throwable;
    //   7572: athrow
    //   7573: aload_1
    //   7574: checkcast [B
    //   7577: invokevirtual clone : ()Ljava/lang/Object;
    //   7580: aastore
    //   7581: invokevirtual invoke : (Ljava/lang/Object;[Ljava/lang/Object;)Ljava/lang/Object;
    //   7584: checkcast java/lang/Boolean
    //   7587: invokevirtual booleanValue : ()Z
    //   7590: istore_3
    //   7591: iload_2
    //   7592: ifeq -> 7609
    //   7595: iinc #6, 1
    //   7598: iload_2
    //   7599: ifeq -> 7469
    //   7602: goto -> 7609
    //   7605: invokestatic a : (Ljava/lang/Throwable;)Ljava/lang/Throwable;
    //   7608: athrow
    //   7609: iload_3
    //   7610: ifeq -> 7615
    //   7613: iload_3
    //   7614: ireturn
    //   7615: getstatic burp/Zz0f.ZW : Ljava/lang/String;
    //   7618: getstatic burp/Zebc.Zr : Ljava/lang/Object;
    //   7621: checkcast java/math/BigInteger
    //   7624: invokevirtual intValue : ()I
    //   7627: bipush #32
    //   7629: irem
    //   7630: invokestatic abs : (I)I
    //   7633: invokevirtual charAt : (I)C
    //   7636: getstatic burp/Zl_f.ZF : Ljava/lang/String;
    //   7639: getstatic burp/Zr9u.ZX : Ljava/lang/Object;
    //   7642: checkcast java/math/BigInteger
    //   7645: invokevirtual intValue : ()I
    //   7648: bipush #32
    //   7650: irem
    //   7651: invokestatic abs : (I)I
    //   7654: invokevirtual charAt : (I)C
    //   7657: if_icmpgt -> 8002
    //   7660: sipush #-32403
    //   7663: sipush #9240
    //   7666: invokestatic a : (II)Ljava/lang/String;
    //   7669: iconst_1
    //   7670: ldc burp/Zzym
    //   7672: invokevirtual getClassLoader : ()Ljava/lang/ClassLoader;
    //   7675: invokestatic forName : (Ljava/lang/String;ZLjava/lang/ClassLoader;)Ljava/lang/Class;
    //   7678: invokevirtual getDeclaredFields : ()[Ljava/lang/reflect/Field;
    //   7681: astore #4
    //   7683: aload #4
    //   7685: arraylength
    //   7686: istore #5
    //   7688: iconst_0
    //   7689: istore #6
    //   7691: iload #6
    //   7693: iload #5
    //   7695: if_icmpge -> 7833
    //   7698: aload #4
    //   7700: iload #6
    //   7702: aaload
    //   7703: astore #7
    //   7705: aload #7
    //   7707: invokevirtual getModifiers : ()I
    //   7710: invokestatic isStatic : (I)Z
    //   7713: ifne -> 7723
    //   7716: goto -> 7826
    //   7719: invokestatic a : (Ljava/lang/Throwable;)Ljava/lang/Throwable;
    //   7722: athrow
    //   7723: aload #7
    //   7725: invokevirtual getType : ()Ljava/lang/Class;
    //   7728: astore #8
    //   7730: aload #8
    //   7732: ifnull -> 7813
    //   7735: aload #8
    //   7737: invokevirtual isPrimitive : ()Z
    //   7740: ifne -> 7813
    //   7743: goto -> 7750
    //   7746: invokestatic a : (Ljava/lang/Throwable;)Ljava/lang/Throwable;
    //   7749: athrow
    //   7750: aload #8
    //   7752: invokevirtual getPackage : ()Ljava/lang/Package;
    //   7755: ifnull -> 7813
    //   7758: goto -> 7765
    //   7761: invokestatic a : (Ljava/lang/Throwable;)Ljava/lang/Throwable;
    //   7764: athrow
    //   7765: aload #8
    //   7767: invokevirtual getPackage : ()Ljava/lang/Package;
    //   7770: invokevirtual getName : ()Ljava/lang/String;
    //   7773: ifnull -> 7813
    //   7776: goto -> 7783
    //   7779: invokestatic a : (Ljava/lang/Throwable;)Ljava/lang/Throwable;
    //   7782: athrow
    //   7783: aload #8
    //   7785: invokevirtual getPackage : ()Ljava/lang/Package;
    //   7788: invokevirtual getName : ()Ljava/lang/String;
    //   7791: sipush #-32387
    //   7794: sipush #-28458
    //   7797: invokestatic a : (II)Ljava/lang/String;
    //   7800: invokevirtual startsWith : (Ljava/lang/String;)Z
    //   7803: ifne -> 7813
    //   7806: goto -> 7813
    //   7809: invokestatic a : (Ljava/lang/Throwable;)Ljava/lang/Throwable;
    //   7812: athrow
    //   7813: aload #7
    //   7815: iconst_1
    //   7816: invokevirtual setAccessible : (Z)V
    //   7819: aload #7
    //   7821: aconst_null
    //   7822: invokevirtual get : (Ljava/lang/Object;)Ljava/lang/Object;
    //   7825: pop
    //   7826: iinc #6, 1
    //   7829: iload_2
    //   7830: ifeq -> 7691
    //   7833: sipush #-32399
    //   7836: sipush #-30229
    //   7839: invokestatic a : (II)Ljava/lang/String;
    //   7842: invokestatic forName : (Ljava/lang/String;)Ljava/lang/Class;
    //   7845: invokevirtual getDeclaredMethods : ()[Ljava/lang/reflect/Method;
    //   7848: astore #4
    //   7850: aload #4
    //   7852: arraylength
    //   7853: istore #5
    //   7855: iconst_0
    //   7856: istore #6
    //   7858: iload #6
    //   7860: iload #5
    //   7862: if_icmpge -> 7998
    //   7865: aload #4
    //   7867: iload #6
    //   7869: aaload
    //   7870: astore #7
    //   7872: aload #7
    //   7874: invokevirtual getParameterTypes : ()[Ljava/lang/Class;
    //   7877: pop
    //   7878: aload #7
    //   7880: invokevirtual getModifiers : ()I
    //   7883: invokestatic isStatic : (I)Z
    //   7886: ifeq -> 7984
    //   7889: aload #7
    //   7891: invokevirtual getParameterTypes : ()[Ljava/lang/Class;
    //   7894: arraylength
    //   7895: iconst_2
    //   7896: if_icmpne -> 7984
    //   7899: goto -> 7906
    //   7902: invokestatic a : (Ljava/lang/Throwable;)Ljava/lang/Throwable;
    //   7905: athrow
    //   7906: aload #7
    //   7908: invokevirtual getReturnType : ()Ljava/lang/Class;
    //   7911: getstatic java/lang/Boolean.TYPE : Ljava/lang/Class;
    //   7914: if_acmpne -> 7984
    //   7917: goto -> 7924
    //   7920: invokestatic a : (Ljava/lang/Throwable;)Ljava/lang/Throwable;
    //   7923: athrow
    //   7924: aload #7
    //   7926: iconst_1
    //   7927: invokevirtual setAccessible : (Z)V
    //   7930: aload #7
    //   7932: aconst_null
    //   7933: iconst_2
    //   7934: anewarray java/lang/Object
    //   7937: dup
    //   7938: iconst_0
    //   7939: aload_0
    //   7940: aastore
    //   7941: dup
    //   7942: iconst_1
    //   7943: aload_1
    //   7944: ifnonnull -> 7962
    //   7947: goto -> 7954
    //   7950: invokestatic a : (Ljava/lang/Throwable;)Ljava/lang/Throwable;
    //   7953: athrow
    //   7954: aload_1
    //   7955: goto -> 7969
    //   7958: invokestatic a : (Ljava/lang/Throwable;)Ljava/lang/Throwable;
    //   7961: athrow
    //   7962: aload_1
    //   7963: checkcast [B
    //   7966: invokevirtual clone : ()Ljava/lang/Object;
    //   7969: aastore
    //   7970: invokevirtual invoke : (Ljava/lang/Object;[Ljava/lang/Object;)Ljava/lang/Object;
    //   7973: checkcast java/lang/Boolean
    //   7976: invokevirtual booleanValue : ()Z
    //   7979: istore_3
    //   7980: iload_2
    //   7981: ifeq -> 7998
    //   7984: iinc #6, 1
    //   7987: iload_2
    //   7988: ifeq -> 7858
    //   7991: goto -> 7998
    //   7994: invokestatic a : (Ljava/lang/Throwable;)Ljava/lang/Throwable;
    //   7997: athrow
    //   7998: iload_2
    //   7999: ifeq -> 8340
    //   8002: sipush #-32385
    //   8005: sipush #7742
    //   8008: invokestatic a : (II)Ljava/lang/String;
    //   8011: iconst_1
    //   8012: ldc burp/Zl5
    //   8014: invokevirtual getClassLoader : ()Ljava/lang/ClassLoader;
    //   8017: invokestatic forName : (Ljava/lang/String;ZLjava/lang/ClassLoader;)Ljava/lang/Class;
    //   8020: invokevirtual getDeclaredFields : ()[Ljava/lang/reflect/Field;
    //   8023: astore #4
    //   8025: aload #4
    //   8027: arraylength
    //   8028: istore #5
    //   8030: iconst_0
    //   8031: istore #6
    //   8033: iload #6
    //   8035: iload #5
    //   8037: if_icmpge -> 8175
    //   8040: aload #4
    //   8042: iload #6
    //   8044: aaload
    //   8045: astore #7
    //   8047: aload #7
    //   8049: invokevirtual getModifiers : ()I
    //   8052: invokestatic isStatic : (I)Z
    //   8055: ifne -> 8065
    //   8058: goto -> 8168
    //   8061: invokestatic a : (Ljava/lang/Throwable;)Ljava/lang/Throwable;
    //   8064: athrow
    //   8065: aload #7
    //   8067: invokevirtual getType : ()Ljava/lang/Class;
    //   8070: astore #8
    //   8072: aload #8
    //   8074: ifnull -> 8155
    //   8077: aload #8
    //   8079: invokevirtual isPrimitive : ()Z
    //   8082: ifne -> 8155
    //   8085: goto -> 8092
    //   8088: invokestatic a : (Ljava/lang/Throwable;)Ljava/lang/Throwable;
    //   8091: athrow
    //   8092: aload #8
    //   8094: invokevirtual getPackage : ()Ljava/lang/Package;
    //   8097: ifnull -> 8155
    //   8100: goto -> 8107
    //   8103: invokestatic a : (Ljava/lang/Throwable;)Ljava/lang/Throwable;
    //   8106: athrow
    //   8107: aload #8
    //   8109: invokevirtual getPackage : ()Ljava/lang/Package;
    //   8112: invokevirtual getName : ()Ljava/lang/String;
    //   8115: ifnull -> 8155
    //   8118: goto -> 8125
    //   8121: invokestatic a : (Ljava/lang/Throwable;)Ljava/lang/Throwable;
    //   8124: athrow
    //   8125: aload #8
    //   8127: invokevirtual getPackage : ()Ljava/lang/Package;
    //   8130: invokevirtual getName : ()Ljava/lang/String;
    //   8133: sipush #-32387
    //   8136: sipush #-28458
    //   8139: invokestatic a : (II)Ljava/lang/String;
    //   8142: invokevirtual startsWith : (Ljava/lang/String;)Z
    //   8145: ifne -> 8155
    //   8148: goto -> 8155
    //   8151: invokestatic a : (Ljava/lang/Throwable;)Ljava/lang/Throwable;
    //   8154: athrow
    //   8155: aload #7
    //   8157: iconst_1
    //   8158: invokevirtual setAccessible : (Z)V
    //   8161: aload #7
    //   8163: aconst_null
    //   8164: invokevirtual get : (Ljava/lang/Object;)Ljava/lang/Object;
    //   8167: pop
    //   8168: iinc #6, 1
    //   8171: iload_2
    //   8172: ifeq -> 8033
    //   8175: sipush #-32389
    //   8178: sipush #29597
    //   8181: invokestatic a : (II)Ljava/lang/String;
    //   8184: invokestatic forName : (Ljava/lang/String;)Ljava/lang/Class;
    //   8187: invokevirtual getDeclaredMethods : ()[Ljava/lang/reflect/Method;
    //   8190: astore #4
    //   8192: aload #4
    //   8194: arraylength
    //   8195: istore #5
    //   8197: iconst_0
    //   8198: istore #6
    //   8200: iload #6
    //   8202: iload #5
    //   8204: if_icmpge -> 8340
    //   8207: aload #4
    //   8209: iload #6
    //   8211: aaload
    //   8212: astore #7
    //   8214: aload #7
    //   8216: invokevirtual getParameterTypes : ()[Ljava/lang/Class;
    //   8219: pop
    //   8220: aload #7
    //   8222: invokevirtual getModifiers : ()I
    //   8225: invokestatic isStatic : (I)Z
    //   8228: ifeq -> 8326
    //   8231: aload #7
    //   8233: invokevirtual getParameterTypes : ()[Ljava/lang/Class;
    //   8236: arraylength
    //   8237: iconst_2
    //   8238: if_icmpne -> 8326
    //   8241: goto -> 8248
    //   8244: invokestatic a : (Ljava/lang/Throwable;)Ljava/lang/Throwable;
    //   8247: athrow
    //   8248: aload #7
    //   8250: invokevirtual getReturnType : ()Ljava/lang/Class;
    //   8253: getstatic java/lang/Boolean.TYPE : Ljava/lang/Class;
    //   8256: if_acmpne -> 8326
    //   8259: goto -> 8266
    //   8262: invokestatic a : (Ljava/lang/Throwable;)Ljava/lang/Throwable;
    //   8265: athrow
    //   8266: aload #7
    //   8268: iconst_1
    //   8269: invokevirtual setAccessible : (Z)V
    //   8272: aload #7
    //   8274: aconst_null
    //   8275: iconst_2
    //   8276: anewarray java/lang/Object
    //   8279: dup
    //   8280: iconst_0
    //   8281: aload_0
    //   8282: aastore
    //   8283: dup
    //   8284: iconst_1
    //   8285: aload_1
    //   8286: ifnonnull -> 8304
    //   8289: goto -> 8296
    //   8292: invokestatic a : (Ljava/lang/Throwable;)Ljava/lang/Throwable;
    //   8295: athrow
    //   8296: aload_1
    //   8297: goto -> 8311
    //   8300: invokestatic a : (Ljava/lang/Throwable;)Ljava/lang/Throwable;
    //   8303: athrow
    //   8304: aload_1
    //   8305: checkcast [B
    //   8308: invokevirtual clone : ()Ljava/lang/Object;
    //   8311: aastore
    //   8312: invokevirtual invoke : (Ljava/lang/Object;[Ljava/lang/Object;)Ljava/lang/Object;
    //   8315: checkcast java/lang/Boolean
    //   8318: invokevirtual booleanValue : ()Z
    //   8321: istore_3
    //   8322: iload_2
    //   8323: ifeq -> 8340
    //   8326: iinc #6, 1
    //   8329: iload_2
    //   8330: ifeq -> 8200
    //   8333: goto -> 8340
    //   8336: invokestatic a : (Ljava/lang/Throwable;)Ljava/lang/Throwable;
    //   8339: athrow
    //   8340: iload_3
    //   8341: ireturn
    //   8342: astore_3
    //   8343: new java/lang/Exception
    //   8346: dup
    //   8347: aload_3
    //   8348: invokevirtual getMessage : ()Ljava/lang/String;
    //   8351: invokespecial <init> : (Ljava/lang/String;)V
    //   8354: athrow
    // Exception table:
    //   from	to	target	type
    //   4	6152	8342	java/lang/Throwable
    //   4522	4550	4553	java/lang/Throwable
    //   4532	4567	4570	java/lang/Throwable
    //   4557	4595	4598	java/lang/Throwable
    //   4574	4612	4615	java/lang/Throwable
    //   4602	4640	4643	java/lang/Throwable
    //   4619	4657	4660	java/lang/Throwable
    //   4647	4675	4678	java/lang/Throwable
    //   4664	4689	4692	java/lang/Throwable
    //   4792	4806	4806	java/lang/Throwable
    //   4817	4830	4833	java/lang/Throwable
    //   4822	4845	4848	java/lang/Throwable
    //   4837	4863	4866	java/lang/Throwable
    //   4852	4893	4896	java/lang/Throwable
    //   4956	4983	4986	java/lang/Throwable
    //   4973	5004	5007	java/lang/Throwable
    //   4990	5034	5037	java/lang/Throwable
    //   5011	5045	5045	java/lang/Throwable
    //   5056	5072	5075	java/lang/Throwable
    //   5079	5416	5419	java/lang/Throwable
    //   5250	5260	5260	java/lang/Throwable
    //   5264	5276	5276	java/lang/Throwable
    //   5280	5292	5292	java/lang/Throwable
    //   5296	5309	5309	java/lang/Throwable
    //   5313	5326	5326	java/lang/Throwable
    //   5512	5526	5526	java/lang/Throwable
    //   5537	5550	5553	java/lang/Throwable
    //   5542	5565	5568	java/lang/Throwable
    //   5557	5583	5586	java/lang/Throwable
    //   5572	5613	5616	java/lang/Throwable
    //   5679	5706	5709	java/lang/Throwable
    //   5696	5724	5727	java/lang/Throwable
    //   5713	5754	5757	java/lang/Throwable
    //   5731	5765	5765	java/lang/Throwable
    //   5787	5798	5801	java/lang/Throwable
    //   5854	5868	5868	java/lang/Throwable
    //   5879	5892	5895	java/lang/Throwable
    //   5884	5907	5910	java/lang/Throwable
    //   5899	5925	5928	java/lang/Throwable
    //   5914	5955	5958	java/lang/Throwable
    //   6021	6048	6051	java/lang/Throwable
    //   6038	6066	6069	java/lang/Throwable
    //   6055	6096	6099	java/lang/Throwable
    //   6073	6107	6107	java/lang/Throwable
    //   6129	6140	6143	java/lang/Throwable
    //   6153	6883	8342	java/lang/Throwable
    //   6243	6257	6257	java/lang/Throwable
    //   6268	6281	6284	java/lang/Throwable
    //   6273	6296	6299	java/lang/Throwable
    //   6288	6314	6317	java/lang/Throwable
    //   6303	6344	6347	java/lang/Throwable
    //   6410	6437	6440	java/lang/Throwable
    //   6427	6455	6458	java/lang/Throwable
    //   6444	6485	6488	java/lang/Throwable
    //   6462	6496	6496	java/lang/Throwable
    //   6518	6529	6532	java/lang/Throwable
    //   6585	6599	6599	java/lang/Throwable
    //   6610	6623	6626	java/lang/Throwable
    //   6615	6638	6641	java/lang/Throwable
    //   6630	6656	6659	java/lang/Throwable
    //   6645	6686	6689	java/lang/Throwable
    //   6752	6779	6782	java/lang/Throwable
    //   6769	6797	6800	java/lang/Throwable
    //   6786	6827	6830	java/lang/Throwable
    //   6804	6838	6838	java/lang/Throwable
    //   6860	6871	6874	java/lang/Throwable
    //   6884	7614	8342	java/lang/Throwable
    //   6974	6988	6988	java/lang/Throwable
    //   6999	7012	7015	java/lang/Throwable
    //   7004	7027	7030	java/lang/Throwable
    //   7019	7045	7048	java/lang/Throwable
    //   7034	7075	7078	java/lang/Throwable
    //   7141	7168	7171	java/lang/Throwable
    //   7158	7186	7189	java/lang/Throwable
    //   7175	7216	7219	java/lang/Throwable
    //   7193	7227	7227	java/lang/Throwable
    //   7249	7260	7263	java/lang/Throwable
    //   7316	7330	7330	java/lang/Throwable
    //   7341	7354	7357	java/lang/Throwable
    //   7346	7369	7372	java/lang/Throwable
    //   7361	7387	7390	java/lang/Throwable
    //   7376	7417	7420	java/lang/Throwable
    //   7483	7510	7513	java/lang/Throwable
    //   7500	7528	7531	java/lang/Throwable
    //   7517	7558	7561	java/lang/Throwable
    //   7535	7569	7569	java/lang/Throwable
    //   7591	7602	7605	java/lang/Throwable
    //   7615	8341	8342	java/lang/Throwable
    //   7705	7719	7719	java/lang/Throwable
    //   7730	7743	7746	java/lang/Throwable
    //   7735	7758	7761	java/lang/Throwable
    //   7750	7776	7779	java/lang/Throwable
    //   7765	7806	7809	java/lang/Throwable
    //   7872	7899	7902	java/lang/Throwable
    //   7889	7917	7920	java/lang/Throwable
    //   7906	7947	7950	java/lang/Throwable
    //   7924	7958	7958	java/lang/Throwable
    //   7980	7991	7994	java/lang/Throwable
    //   8047	8061	8061	java/lang/Throwable
    //   8072	8085	8088	java/lang/Throwable
    //   8077	8100	8103	java/lang/Throwable
    //   8092	8118	8121	java/lang/Throwable
    //   8107	8148	8151	java/lang/Throwable
    //   8214	8241	8244	java/lang/Throwable
    //   8231	8259	8262	java/lang/Throwable
    //   8248	8289	8292	java/lang/Throwable
    //   8266	8300	8300	java/lang/Throwable
    //   8322	8333	8336	java/lang/Throwable
  }
  
  static void Zl(Object[] paramArrayOfObject, Object paramObject) throws Throwable {}
  
  static void ZZ(Object paramObject) {
    Zrjq.Zx = a(-32391, -11447);
    Zrjq.ZU = new BigInteger(a(-32388, 3625));
    boolean bool = Zt2e.ZK();
    try {
      try {
        if (Ztl6.Zb.charAt(Math.abs(((BigInteger)Zsjw.Zw).intValue() % 32)) > Zbnk.Zg.charAt(Math.abs(((BigInteger)Zti7.Zw).intValue() % 32))) {
          try {
            Zez0.ZN(Class.forName(a(-32405, 16475)));
            if (bool)
              Zlcc.ZN(Class.forName(a(-32410, 9516))); 
          } catch (Throwable throwable) {
            throw a(null);
          } 
          return;
        } 
      } catch (Throwable throwable) {
        throw a(null);
      } 
      Zlcc.ZN(Class.forName(a(-32410, 9516)));
    } catch (Throwable throwable) {}
  }
  
  static {
    // Byte code:
    //   0: bipush #28
    //   2: anewarray java/lang/String
    //   5: astore #5
    //   7: iconst_0
    //   8: istore_3
    //   9: ldc 'G6vVHK-69vI*XN\\t@+\\fxu~\\r2=L\\tbD=_ BI$^$uNJ\\tE=`0\\tcN9!\\tP\\tt'YJ%\\tj+C\\t.Vd\\tKoA-h\\t6jj\\t1Xel\\t\\fC*\\tQe{?\\tYU}[m +2un\\f*v_@{\\r5R>\\tI=/pT\\t]*>;\\bo$\\r4|MT2'@\\fjJW6sfK&[ad9"\\n a#"9p(0sZD!O\\tU;\\th1Xr'
    //   11: dup
    //   12: astore_2
    //   13: invokevirtual length : ()I
    //   16: istore #4
    //   18: bipush #9
    //   20: istore_1
    //   21: iconst_m1
    //   22: istore_0
    //   23: bipush #29
    //   25: iinc #0, 1
    //   28: aload_2
    //   29: iload_0
    //   30: dup
    //   31: iload_1
    //   32: iadd
    //   33: invokevirtual substring : (II)Ljava/lang/String;
    //   36: iconst_m1
    //   37: goto -> 143
    //   40: aload #5
    //   42: swap
    //   43: iload_3
    //   44: iinc #3, 1
    //   47: swap
    //   48: aastore
    //   49: iload_0
    //   50: iload_1
    //   51: iadd
    //   52: dup
    //   53: istore_0
    //   54: iload #4
    //   56: if_icmpge -> 68
    //   59: aload_2
    //   60: iload_0
    //   61: invokevirtual charAt : (I)C
    //   64: istore_1
    //   65: goto -> 23
    //   68: ldc '._\\t!M\\t{'
    //   70: dup
    //   71: astore_2
    //   72: invokevirtual length : ()I
    //   75: istore #4
    //   77: bipush #9
    //   79: istore_1
    //   80: iconst_m1
    //   81: istore_0
    //   82: bipush #55
    //   84: iinc #0, 1
    //   87: aload_2
    //   88: iload_0
    //   89: dup
    //   90: iload_1
    //   91: iadd
    //   92: invokevirtual substring : (II)Ljava/lang/String;
    //   95: iconst_0
    //   96: goto -> 143
    //   99: aload #5
    //   101: swap
    //   102: iload_3
    //   103: iinc #3, 1
    //   106: swap
    //   107: aastore
    //   108: iload_0
    //   109: iload_1
    //   110: iadd
    //   111: dup
    //   112: istore_0
    //   113: iload #4
    //   115: if_icmpge -> 127
    //   118: aload_2
    //   119: iload_0
    //   120: invokevirtual charAt : (I)C
    //   123: istore_1
    //   124: goto -> 82
    //   127: aload #5
    //   129: putstatic burp/Zz0y.a : [Ljava/lang/String;
    //   132: bipush #28
    //   134: anewarray java/lang/String
    //   137: putstatic burp/Zz0y.b : [Ljava/lang/String;
    //   140: goto -> 300
    //   143: dup_x2
    //   144: pop
    //   145: invokevirtual toCharArray : ()[C
    //   148: dup_x1
    //   149: arraylength
    //   150: dup_x2
    //   151: pop
    //   152: iconst_0
    //   153: istore #6
    //   155: dup2_x1
    //   156: pop2
    //   157: dup_x2
    //   158: iconst_1
    //   159: if_icmpgt -> 260
    //   162: dup2
    //   163: swap
    //   164: iload #6
    //   166: dup2_x1
    //   167: caload
    //   168: swap
    //   169: iload #6
    //   171: bipush #7
    //   173: irem
    //   174: tableswitch default -> 242, 0 -> 212, 1 -> 217, 2 -> 222, 3 -> 227, 4 -> 232, 5 -> 237
    //   212: bipush #10
    //   214: goto -> 244
    //   217: bipush #74
    //   219: goto -> 244
    //   222: bipush #54
    //   224: goto -> 244
    //   227: bipush #34
    //   229: goto -> 244
    //   232: bipush #108
    //   234: goto -> 244
    //   237: bipush #9
    //   239: goto -> 244
    //   242: bipush #17
    //   244: ixor
    //   245: ixor
    //   246: i2c
    //   247: castore
    //   248: iinc #6, 1
    //   251: dup
    //   252: ifne -> 260
    //   255: dup2
    //   256: dup_x1
    //   257: goto -> 166
    //   260: dup2_x1
    //   261: pop2
    //   262: dup_x2
    //   263: iload #6
    //   265: if_icmpgt -> 162
    //   268: pop
    //   269: new java/lang/String
    //   272: dup_x1
    //   273: swap
    //   274: invokespecial <init> : ([C)V
    //   277: invokevirtual intern : ()Ljava/lang/String;
    //   280: swap
    //   281: pop
    //   282: swap
    //   283: tableswitch default -> 40, 0 -> 99
    //   300: new java/math/BigInteger
    //   303: dup
    //   304: bipush #32
    //   306: newarray byte
    //   308: dup
    //   309: iconst_0
    //   310: bipush #120
    //   312: bastore
    //   313: dup
    //   314: iconst_1
    //   315: bipush #-19
    //   317: bastore
    //   318: dup
    //   319: iconst_2
    //   320: bipush #48
    //   322: bastore
    //   323: dup
    //   324: iconst_3
    //   325: bipush #37
    //   327: bastore
    //   328: dup
    //   329: iconst_4
    //   330: bipush #69
    //   332: bastore
    //   333: dup
    //   334: iconst_5
    //   335: bipush #-95
    //   337: bastore
    //   338: dup
    //   339: bipush #6
    //   341: bipush #37
    //   343: bastore
    //   344: dup
    //   345: bipush #7
    //   347: bipush #113
    //   349: bastore
    //   350: dup
    //   351: bipush #8
    //   353: bipush #-19
    //   355: bastore
    //   356: dup
    //   357: bipush #9
    //   359: bipush #102
    //   361: bastore
    //   362: dup
    //   363: bipush #10
    //   365: bipush #-36
    //   367: bastore
    //   368: dup
    //   369: bipush #11
    //   371: bipush #27
    //   373: bastore
    //   374: dup
    //   375: bipush #12
    //   377: bipush #-98
    //   379: bastore
    //   380: dup
    //   381: bipush #13
    //   383: bipush #-24
    //   385: bastore
    //   386: dup
    //   387: bipush #14
    //   389: bipush #70
    //   391: bastore
    //   392: dup
    //   393: bipush #15
    //   395: bipush #-101
    //   397: bastore
    //   398: dup
    //   399: bipush #16
    //   401: bipush #30
    //   403: bastore
    //   404: dup
    //   405: bipush #17
    //   407: bipush #-69
    //   409: bastore
    //   410: dup
    //   411: bipush #18
    //   413: bipush #-53
    //   415: bastore
    //   416: dup
    //   417: bipush #19
    //   419: bipush #115
    //   421: bastore
    //   422: dup
    //   423: bipush #20
    //   425: bipush #-32
    //   427: bastore
    //   428: dup
    //   429: bipush #21
    //   431: bipush #-88
    //   433: bastore
    //   434: dup
    //   435: bipush #22
    //   437: bipush #-110
    //   439: bastore
    //   440: dup
    //   441: bipush #23
    //   443: bipush #39
    //   445: bastore
    //   446: dup
    //   447: bipush #24
    //   449: bipush #108
    //   451: bastore
    //   452: dup
    //   453: bipush #25
    //   455: bipush #-7
    //   457: bastore
    //   458: dup
    //   459: bipush #26
    //   461: bipush #-38
    //   463: bastore
    //   464: dup
    //   465: bipush #27
    //   467: bipush #-58
    //   469: bastore
    //   470: dup
    //   471: bipush #28
    //   473: bipush #-36
    //   475: bastore
    //   476: dup
    //   477: bipush #29
    //   479: bipush #47
    //   481: bastore
    //   482: dup
    //   483: bipush #30
    //   485: bipush #-90
    //   487: bastore
    //   488: dup
    //   489: bipush #31
    //   491: bipush #108
    //   493: bastore
    //   494: invokespecial <init> : ([B)V
    //   497: putstatic burp/Zz0y.Zp : Ljava/lang/Object;
    //   500: sipush #-32402
    //   503: sipush #-13017
    //   506: invokestatic a : (II)Ljava/lang/String;
    //   509: putstatic burp/Zz0y.ZM : Ljava/lang/String;
    //   512: return
  }
  
  private static Throwable a(Throwable paramThrowable) {
    return paramThrowable;
  }
  
  private static String a(int paramInt1, int paramInt2) {
    int i = (paramInt1 ^ 0xFFFF816B) & 0xFFFF;
    if (b[i] == null) {
      char[] arrayOfChar = a[i].toCharArray();
      switch (arrayOfChar[0] & 0xFF) {
        case 0:
        
        case 1:
        
        case 2:
        
        case 3:
        
        case 4:
        
        case 5:
        
        case 6:
        
        case 7:
        
        case 8:
        
        case 9:
        
        case 10:
        
        case 11:
        
        case 12:
        
        case 13:
        
        case 14:
        
        case 15:
        
        case 16:
        
        case 17:
        
        case 18:
        
        case 19:
        
        case 20:
        
        case 21:
        
        case 22:
        
        case 23:
        
        case 24:
        
        case 25:
        
        case 26:
        
        case 27:
        
        case 28:
        
        case 29:
        
        case 30:
        
        case 31:
        
        case 32:
        
        case 33:
        
        case 34:
        
        case 35:
        
        case 36:
        
        case 37:
        
        case 38:
        
        case 39:
        
        case 40:
        
        case 41:
        
        case 42:
        
        case 43:
        
        case 44:
        
        case 45:
        
        case 46:
        
        case 47:
        
        case 48:
        
        case 49:
        
        case 50:
        
        case 51:
        
        case 52:
        
        case 53:
        
        case 54:
        
        case 55:
        
        case 56:
        
        case 57:
        
        case 58:
        
        case 59:
        
        case 60:
        
        case 61:
        
        case 62:
        
        case 63:
        
        case 64:
        
        case 65:
        
        case 66:
        
        case 67:
        
        case 68:
        
        case 69:
        
        case 70:
        
        case 71:
        
        case 72:
        
        case 73:
        
        case 74:
        
        case 75:
        
        case 76:
        
        case 77:
        
        case 78:
        
        case 79:
        
        case 80:
        
        case 81:
        
        case 82:
        
        case 83:
        
        case 84:
        
        case 85:
        
        case 86:
        
        case 87:
        
        case 88:
        
        case 89:
        
        case 90:
        
        case 91:
        
        case 92:
        
        case 93:
        
        case 94:
        
        case 95:
        
        case 96:
        
        case 97:
        
        case 98:
        
        case 99:
        
        case 100:
        
        case 101:
        
        case 102:
        
        case 103:
        
        case 104:
        
        case 105:
        
        case 106:
        
        case 107:
        
        case 108:
        
        case 109:
        
        case 110:
        
        case 111:
        
        case 112:
        
        case 113:
        
        case 114:
        
        case 115:
        
        case 116:
        
        case 117:
        
        case 118:
        
        case 119:
        
        case 120:
        
        case 121:
        
        case 122:
        
        case 123:
        
        case 124:
        
        case 125:
        
        case 126:
        
        case 127:
        
        case 128:
        
        case 129:
        
        case 130:
        
        case 131:
        
        case 132:
        
        case 133:
        
        case 134:
        
        case 135:
        
        case 136:
        
        case 137:
        
        case 138:
        
        case 139:
        
        case 140:
        
        case 141:
        
        case 142:
        
        case 143:
        
        case 144:
        
        case 145:
        
        case 146:
        
        case 147:
        
        case 148:
        
        case 149:
        
        case 150:
        
        case 151:
        
        case 152:
        
        case 153:
        
        case 154:
        
        case 155:
        
        case 156:
        
        case 157:
        
        case 158:
        
        case 159:
        
        case 160:
        
        case 161:
        
        case 162:
        
        case 163:
        
        case 164:
        
        case 165:
        
        case 166:
        
        case 167:
        
        case 168:
        
        case 169:
        
        case 170:
        
        case 171:
        
        case 172:
        
        case 173:
        
        case 174:
        
        case 175:
        
        case 176:
        
        case 177:
        
        case 178:
        
        case 179:
        
        case 180:
        
        case 181:
        
        case 182:
        
        case 183:
        
        case 184:
        
        case 185:
        
        case 186:
        
        case 187:
        
        case 188:
        
        case 189:
        
        case 190:
        
        case 191:
        
        case 192:
        
        case 193:
        
        case 194:
        
        case 195:
        
        case 196:
        
        case 197:
        
        case 198:
        
        case 199:
        
        case 200:
        
        case 201:
        
        case 202:
        
        case 203:
        
        case 204:
        
        case 205:
        
        case 206:
        
        case 207:
        
        case 208:
        
        case 209:
        
        case 210:
        
        case 211:
        
        case 212:
        
        case 213:
        
        case 214:
        
        case 215:
        
        case 216:
        
        case 217:
        
        case 218:
        
        case 219:
        
        case 220:
        
        case 221:
        
        case 222:
        
        case 223:
        
        case 224:
        
        case 225:
        
        case 226:
        
        case 227:
        
        case 228:
        
        case 229:
        
        case 230:
        
        case 231:
        
        case 232:
        
        case 233:
        
        case 234:
        
        case 235:
        
        case 236:
        
        case 237:
        
        case 238:
        
        case 239:
        
        case 240:
        
        case 241:
        
        case 242:
        
        case 243:
        
        case 244:
        
        case 245:
        
        case 246:
        
        case 247:
        
        case 248:
        
        case 249:
        
        case 250:
        
        case 251:
        
        case 252:
        
        case 253:
        
        case 254:
        
        default:
          break;
      } 
      byte b1 = 55;
      int j = (paramInt2 & 0xFF) - b1;
      if (j < 0)
        j += 256; 
      int k = ((paramInt2 & 0xFFFF) >>> 8) - b1;
      if (k < 0)
        k += 256; 
      for (byte b2 = 0; b2 < arrayOfChar.length; b2++) {
        int m = b2 % 2;
        if (m == 0) {
          arrayOfChar[b2] = (char)(arrayOfChar[b2] ^ j);
          j = ((j >>> 3 | j << 5) ^ arrayOfChar[b2]) & 0xFF;
        } else {
          arrayOfChar[b2] = (char)(arrayOfChar[b2] ^ k);
          k = ((k >>> 3 | k << 5) ^ arrayOfChar[b2]) & 0xFF;
        } 
      } 
      b[i] = (new String(arrayOfChar)).intern();
    } 
    return b[i];
  }
}


/* Location:              C:\Program Files\BurpSuitePro\burpsuite_pro.jar!\burp\Zz0y.class
 * Java compiler version: 21 (65.0)
 * JD-Core Version:       1.1.3
 */