package burp;

import java.util.Objects;

public class Zz39 {
  private static int[] ZD;
  
  private static final String[] a;
  
  private static final String[] b;
  
  static boolean Zx(Zm5x paramZm5x, Object paramObject) {
    int[] arrayOfInt = ZV();
    if (paramZm5x.ZF(paramObject))
      return true; 
    if (paramObject instanceof Zm5x) {
      Zm5x zm5x = (Zm5x)paramObject;
      if (arrayOfInt == null)
        return !Objects.equals(paramZm5x.ZH2(), zm5x.ZH2()) ? false : (!Objects.equals(paramZm5x.ZHi(), zm5x.ZHi()) ? false : (!Objects.equals(paramZm5x.ZHc(), zm5x.ZHc()) ? false : (!Objects.equals(paramZm5x.ZHX(), zm5x.ZHX()) ? false : (!Objects.equals(paramZm5x.ZHu(), zm5x.ZHu()) ? false : (!Objects.equals(paramZm5x.ZH5(), zm5x.ZH5()) ? false : (!Objects.equals(paramZm5x.ZHr(), zm5x.ZHr()) ? false : (!Objects.equals(paramZm5x.ZHs(), zm5x.ZHs()) ? false : ((paramZm5x.ZHe() != null) ? paramZm5x.ZHe().equals(zm5x.ZHe()) : ((zm5x.ZHe() == null)))))))))); 
    } 
    return false;
  }
  
  static int ZE(Zm5x paramZm5x) {
    int[] arrayOfInt = ZV();
    int i = (paramZm5x.ZH2() != null) ? paramZm5x.ZH2().hashCode() : 0;
    i = 31 * i + ((paramZm5x.ZHi() != null) ? paramZm5x.ZHi().hashCode() : 0);
    i = 31 * i + ((paramZm5x.ZHc() != null) ? paramZm5x.ZHc().hashCode() : 0);
    i = 31 * i + ((paramZm5x.ZHX() != null) ? paramZm5x.ZHX().hashCode() : 0);
    i = 31 * i + ((paramZm5x.ZHu() != null) ? paramZm5x.ZHu().hashCode() : 0);
    i = 31 * i + ((paramZm5x.ZH5() != null) ? paramZm5x.ZH5().hashCode() : 0);
    i = 31 * i + ((paramZm5x.ZHr() != null) ? paramZm5x.ZHr().hashCode() : 0);
    i = 31 * i + ((paramZm5x.ZHs() != null) ? paramZm5x.ZHs().hashCode() : 0);
    i = 31 * i + ((paramZm5x.ZHe() != null) ? paramZm5x.ZHe().hashCode() : 0);
    if (arrayOfInt != null)
      Zbqc.Zr(new Zbqc[3]); 
    return i;
  }
  
  public static String Zh(Zm5x paramZm5x) {
    StringBuilder stringBuilder = new StringBuilder(a(-8561, 22568));
    stringBuilder.append(a(-8564, -17264)).append(paramZm5x.ZH2()).append('\'');
    stringBuilder.append(a(-8567, -10991)).append(paramZm5x.ZHi()).append('\'');
    stringBuilder.append(a(-8562, 16118)).append(paramZm5x.ZHc()).append('\'');
    stringBuilder.append(a(-8565, 10814)).append(paramZm5x.ZHX()).append('\'');
    stringBuilder.append(a(-8566, -21986)).append(paramZm5x.ZHu()).append('\'');
    stringBuilder.append(a(-8563, 28473)).append(paramZm5x.ZH5()).append('\'');
    stringBuilder.append(a(-8570, 6618)).append(paramZm5x.ZHr()).append('\'');
    int[] arrayOfInt = ZV();
    stringBuilder.append(a(-8568, 31402)).append(paramZm5x.ZHs()).append('\'');
    stringBuilder.append(a(-8569, 14931)).append(paramZm5x.ZHe()).append('\'');
    stringBuilder.append('}');
    if (Zbqc.Zwu() == null)
      Zv(new int[1]); 
    return stringBuilder.toString();
  }
  
  public static void Zv(int[] paramArrayOfint) {
    ZD = paramArrayOfint;
  }
  
  public static int[] ZV() {
    return ZD;
  }
  
  static {
    // Byte code:
    //   0: bipush #10
    //   2: anewarray java/lang/String
    //   5: astore #5
    //   7: iconst_0
    //   8: istore_3
    //   9: ldc 'Â±Â¡Â«Ã¯pÂ»tÂº $ÂšÂšÃ¿'FÃÂ—vÂˆÂ®\\bM\\nSPÃ„1AÂ—Âƒl-ÂƒÂ¹[?ÂÂ‹Ã…\\b\\roÃ\\tÃ¨[Ã£\\rÂ¸Â®Â“EÂ¶Âƒ^\\b\dÃƒÂ»\\rÃ¼Ã˜ÃBgÂ·dÂŽÂ´+Â¡NjPÂŽÂÂWÂ›Bq)Â¡Â¡Ã·Ã»\\tMQ!Ã¤Â’5Â¶'
    //   11: dup
    //   12: astore_2
    //   13: invokevirtual length : ()I
    //   16: istore #4
    //   18: aconst_null
    //   19: bipush #8
    //   21: istore_1
    //   22: invokestatic Zv : ([I)V
    //   25: iconst_m1
    //   26: istore_0
    //   27: bipush #39
    //   29: iinc #0, 1
    //   32: aload_2
    //   33: iload_0
    //   34: dup
    //   35: iload_1
    //   36: iadd
    //   37: invokevirtual substring : (II)Ljava/lang/String;
    //   40: iconst_m1
    //   41: goto -> 147
    //   44: aload #5
    //   46: swap
    //   47: iload_3
    //   48: iinc #3, 1
    //   51: swap
    //   52: aastore
    //   53: iload_0
    //   54: iload_1
    //   55: iadd
    //   56: dup
    //   57: istore_0
    //   58: iload #4
    //   60: if_icmpge -> 72
    //   63: aload_2
    //   64: iload_0
    //   65: invokevirtual charAt : (I)C
    //   68: istore_1
    //   69: goto -> 27
    //   72: ldc 'Âš}ÂµÃ†zÃ…LÃ±Ã¡Ã“Â´'
    //   74: dup
    //   75: astore_2
    //   76: invokevirtual length : ()I
    //   79: istore #4
    //   81: bipush #7
    //   83: istore_1
    //   84: iconst_m1
    //   85: istore_0
    //   86: bipush #80
    //   88: iinc #0, 1
    //   91: aload_2
    //   92: iload_0
    //   93: dup
    //   94: iload_1
    //   95: iadd
    //   96: invokevirtual substring : (II)Ljava/lang/String;
    //   99: iconst_0
    //   100: goto -> 147
    //   103: aload #5
    //   105: swap
    //   106: iload_3
    //   107: iinc #3, 1
    //   110: swap
    //   111: aastore
    //   112: iload_0
    //   113: iload_1
    //   114: iadd
    //   115: dup
    //   116: istore_0
    //   117: iload #4
    //   119: if_icmpge -> 131
    //   122: aload_2
    //   123: iload_0
    //   124: invokevirtual charAt : (I)C
    //   127: istore_1
    //   128: goto -> 86
    //   131: aload #5
    //   133: putstatic burp/Zz39.a : [Ljava/lang/String;
    //   136: bipush #10
    //   138: anewarray java/lang/String
    //   141: putstatic burp/Zz39.b : [Ljava/lang/String;
    //   144: goto -> 304
    //   147: dup_x2
    //   148: pop
    //   149: invokevirtual toCharArray : ()[C
    //   152: dup_x1
    //   153: arraylength
    //   154: dup_x2
    //   155: pop
    //   156: iconst_0
    //   157: istore #6
    //   159: dup2_x1
    //   160: pop2
    //   161: dup_x2
    //   162: iconst_1
    //   163: if_icmpgt -> 263
    //   166: dup2
    //   167: swap
    //   168: iload #6
    //   170: dup2_x1
    //   171: caload
    //   172: swap
    //   173: iload #6
    //   175: bipush #7
    //   177: irem
    //   178: tableswitch default -> 245, 0 -> 216, 1 -> 221, 2 -> 226, 3 -> 231, 4 -> 236, 5 -> 240
    //   216: bipush #14
    //   218: goto -> 247
    //   221: bipush #90
    //   223: goto -> 247
    //   226: bipush #66
    //   228: goto -> 247
    //   231: bipush #14
    //   233: goto -> 247
    //   236: iconst_4
    //   237: goto -> 247
    //   240: bipush #119
    //   242: goto -> 247
    //   245: bipush #122
    //   247: ixor
    //   248: ixor
    //   249: i2c
    //   250: castore
    //   251: iinc #6, 1
    //   254: dup
    //   255: ifne -> 263
    //   258: dup2
    //   259: dup_x1
    //   260: goto -> 170
    //   263: dup2_x1
    //   264: pop2
    //   265: dup_x2
    //   266: iload #6
    //   268: if_icmpgt -> 166
    //   271: pop
    //   272: new java/lang/String
    //   275: dup_x1
    //   276: swap
    //   277: invokespecial <init> : ([C)V
    //   280: invokevirtual intern : ()Ljava/lang/String;
    //   283: swap
    //   284: pop
    //   285: swap
    //   286: tableswitch default -> 44, 0 -> 103
    //   304: return
  }
  
  private static String a(int paramInt1, int paramInt2) {
    int i = (paramInt1 ^ 0xFFFFDE8E) & 0xFFFF;
    if (b[i] == null) {
      char[] arrayOfChar = a[i].toCharArray();
      switch (arrayOfChar[0] & 0xFF) {
        case 0:
        
        case 1:
        
        case 2:
        
        case 3:
        
        case 4:
        
        case 5:
        
        case 6:
        
        case 7:
        
        case 8:
        
        case 9:
        
        case 10:
        
        case 11:
        
        case 12:
        
        case 13:
        
        case 14:
        
        case 15:
        
        case 16:
        
        case 17:
        
        case 18:
        
        case 19:
        
        case 20:
        
        case 21:
        
        case 22:
        
        case 23:
        
        case 24:
        
        case 25:
        
        case 26:
        
        case 27:
        
        case 28:
        
        case 29:
        
        case 30:
        
        case 31:
        
        case 32:
        
        case 33:
        
        case 34:
        
        case 35:
        
        case 36:
        
        case 37:
        
        case 38:
        
        case 39:
        
        case 40:
        
        case 41:
        
        case 42:
        
        case 43:
        
        case 44:
        
        case 45:
        
        case 46:
        
        case 47:
        
        case 48:
        
        case 49:
        
        case 50:
        
        case 51:
        
        case 52:
        
        case 53:
        
        case 54:
        
        case 55:
        
        case 56:
        
        case 57:
        
        case 58:
        
        case 59:
        
        case 60:
        
        case 61:
        
        case 62:
        
        case 63:
        
        case 64:
        
        case 65:
        
        case 66:
        
        case 67:
        
        case 68:
        
        case 69:
        
        case 70:
        
        case 71:
        
        case 72:
        
        case 73:
        
        case 74:
        
        case 75:
        
        case 76:
        
        case 77:
        
        case 78:
        
        case 79:
        
        case 80:
        
        case 81:
        
        case 82:
        
        case 83:
        
        case 84:
        
        case 85:
        
        case 86:
        
        case 87:
        
        case 88:
        
        case 89:
        
        case 90:
        
        case 91:
        
        case 92:
        
        case 93:
        
        case 94:
        
        case 95:
        
        case 96:
        
        case 97:
        
        case 98:
        
        case 99:
        
        case 100:
        
        case 101:
        
        case 102:
        
        case 103:
        
        case 104:
        
        case 105:
        
        case 106:
        
        case 107:
        
        case 108:
        
        case 109:
        
        case 110:
        
        case 111:
        
        case 112:
        
        case 113:
        
        case 114:
        
        case 115:
        
        case 116:
        
        case 117:
        
        case 118:
        
        case 119:
        
        case 120:
        
        case 121:
        
        case 122:
        
        case 123:
        
        case 124:
        
        case 125:
        
        case 126:
        
        case 127:
        
        case 128:
        
        case 129:
        
        case 130:
        
        case 131:
        
        case 132:
        
        case 133:
        
        case 134:
        
        case 135:
        
        case 136:
        
        case 137:
        
        case 138:
        
        case 139:
        
        case 140:
        
        case 141:
        
        case 142:
        
        case 143:
        
        case 144:
        
        case 145:
        
        case 146:
        
        case 147:
        
        case 148:
        
        case 149:
        
        case 150:
        
        case 151:
        
        case 152:
        
        case 153:
        
        case 154:
        
        case 155:
        
        case 156:
        
        case 157:
        
        case 158:
        
        case 159:
        
        case 160:
        
        case 161:
        
        case 162:
        
        case 163:
        
        case 164:
        
        case 165:
        
        case 166:
        
        case 167:
        
        case 168:
        
        case 169:
        
        case 170:
        
        case 171:
        
        case 172:
        
        case 173:
        
        case 174:
        
        case 175:
        
        case 176:
        
        case 177:
        
        case 178:
        
        case 179:
        
        case 180:
        
        case 181:
        
        case 182:
        
        case 183:
        
        case 184:
        
        case 185:
        
        case 186:
        
        case 187:
        
        case 188:
        
        case 189:
        
        case 190:
        
        case 191:
        
        case 192:
        
        case 193:
        
        case 194:
        
        case 195:
        
        case 196:
        
        case 197:
        
        case 198:
        
        case 199:
        
        case 200:
        
        case 201:
        
        case 202:
        
        case 203:
        
        case 204:
        
        case 205:
        
        case 206:
        
        case 207:
        
        case 208:
        
        case 209:
        
        case 210:
        
        case 211:
        
        case 212:
        
        case 213:
        
        case 214:
        
        case 215:
        
        case 216:
        
        case 217:
        
        case 218:
        
        case 219:
        
        case 220:
        
        case 221:
        
        case 222:
        
        case 223:
        
        case 224:
        
        case 225:
        
        case 226:
        
        case 227:
        
        case 228:
        
        case 229:
        
        case 230:
        
        case 231:
        
        case 232:
        
        case 233:
        
        case 234:
        
        case 235:
        
        case 236:
        
        case 237:
        
        case 238:
        
        case 239:
        
        case 240:
        
        case 241:
        
        case 242:
        
        case 243:
        
        case 244:
        
        case 245:
        
        case 246:
        
        case 247:
        
        case 248:
        
        case 249:
        
        case 250:
        
        case 251:
        
        case 252:
        
        case 253:
        
        case 254:
        
        default:
          break;
      } 
      byte b1 = 12;
      int j = (paramInt2 & 0xFF) - b1;
      if (j < 0)
        j += 256; 
      int k = ((paramInt2 & 0xFFFF) >>> 8) - b1;
      if (k < 0)
        k += 256; 
      for (byte b2 = 0; b2 < arrayOfChar.length; b2++) {
        int m = b2 % 2;
        if (m == 0) {
          arrayOfChar[b2] = (char)(arrayOfChar[b2] ^ j);
          j = ((j >>> 3 | j << 5) ^ arrayOfChar[b2]) & 0xFF;
        } else {
          arrayOfChar[b2] = (char)(arrayOfChar[b2] ^ k);
          k = ((k >>> 3 | k << 5) ^ arrayOfChar[b2]) & 0xFF;
        } 
      } 
      b[i] = (new String(arrayOfChar)).intern();
    } 
    return b[i];
  }
}


/* Location:              C:\Program Files\BurpSuitePro\burpsuite_pro.jar!\burp\Zz39.class
 * Java compiler version: 21 (65.0)
 * JD-Core Version:       1.1.3
 */