package burp;

import java.util.Arrays;
import java.util.Collections;
import java.util.List;
import java.util.function.Consumer;
import net.portswigger.Zkb;
import net.portswigger.Zsy;

public class Zz6s implements Zs9w {
  private final Zrj Zr;
  
  private final Ze3n Z_;
  
  private final Ze3n Zm;
  
  private final Zxs7 Zy;
  
  private final Zbnt Zs;
  
  private final Zmhe ZF;
  
  private final Zkq4 Zp;
  
  private final Zsy ZV;
  
  private final Zm_g ZN;
  
  private final Zbjl ZG;
  
  private final Zesv Ze;
  
  private final Consumer<Zxcb> ZD;
  
  private final Zvs ZK;
  
  private final boolean Zv;
  
  private final Zxon ZU;
  
  private static int[] ZI;
  
  private static final String[] a;
  
  private static final String[] b;
  
  public Zz6s(Zrj paramZrj, Ze3n paramZe3n1, Ze3n paramZe3n2, Zxs7 paramZxs7, Zbnt paramZbnt, Zmhe paramZmhe, Zkq4 paramZkq4, Zsy paramZsy, Zm_g paramZm_g, Zbjl paramZbjl, Zesv paramZesv, Consumer<Zxcb> paramConsumer) {
    this.Zr = paramZrj;
    this.Z_ = paramZe3n1;
    this.Zm = paramZe3n2;
    this.Zy = paramZxs7;
    this.Zs = paramZbnt;
    this.ZF = paramZmhe;
    this.Zp = paramZkq4;
    this.ZV = paramZsy;
    this.ZN = paramZm_g;
    this.ZG = paramZbjl;
    this.Ze = paramZesv;
    this.ZD = paramConsumer;
    this.ZK = paramZmhe.<Zvs>Zq(Zzu2.SQL_INJECTION, Zzu2.SQL_INJECTION_2ND_ORDER);
    this.Zv = ((Boolean)paramZmhe.<Boolean>Zq(Boolean.valueOf(false), Boolean.valueOf(true))).booleanValue();
    int[] arrayOfInt = Zp();
    try {
      this.ZU = new Zxon(paramZmhe, paramZe3n1, paramZe3n2.Zc()[0].longValue(), paramZxs7, paramZkq4, ZD());
      if (arrayOfInt == null)
        Zbqc.Zr(new Zbqc[5]); 
    } catch (MatchException matchException) {
      throw a(null);
    } 
  }
  
  private Zlk4 ZD() {
    // Byte code:
    //   0: invokestatic Zp : ()[I
    //   3: astore_1
    //   4: aload_0
    //   5: getfield Zp : Lburp/Zkq4;
    //   8: invokeinterface ZqT : ()Lburp/Zlk4;
    //   13: getstatic burp/Zlk4.THOROUGH : Lburp/Zlk4;
    //   16: invokevirtual ZH : (Lburp/Zlk4;)Z
    //   19: ifeq -> 30
    //   22: getstatic burp/Zlk4.THOROUGH : Lburp/Zlk4;
    //   25: areturn
    //   26: invokestatic a : (Ljava/lang/MatchException;)Ljava/lang/MatchException;
    //   29: athrow
    //   30: aload_0
    //   31: getfield Zy : Lburp/Zxs7;
    //   34: invokeinterface Z_ : ()Lburp/Zs66;
    //   39: getstatic burp/Zs66.PATH_FOLDER_PARAM : Lburp/Zs66;
    //   42: if_acmpne -> 53
    //   45: getstatic burp/Zlk4.FAST : Lburp/Zlk4;
    //   48: areturn
    //   49: invokestatic a : (Ljava/lang/MatchException;)Ljava/lang/MatchException;
    //   52: athrow
    //   53: aload_0
    //   54: getfield Zy : Lburp/Zxs7;
    //   57: invokeinterface Z_ : ()Lburp/Zs66;
    //   62: getstatic burp/Zs66.HEADER : Lburp/Zs66;
    //   65: if_acmpne -> 200
    //   68: aload_0
    //   69: getfield Zy : Lburp/Zxs7;
    //   72: invokeinterface Zf : ()Ljava/lang/String;
    //   77: invokevirtual toLowerCase : ()Ljava/lang/String;
    //   80: astore_2
    //   81: iconst_m1
    //   82: istore_3
    //   83: aload_2
    //   84: invokevirtual hashCode : ()I
    //   87: lookupswitch default -> 166, 486342275 -> 112, 1085069613 -> 141
    //   112: aload_2
    //   113: sipush #-7141
    //   116: sipush #28289
    //   119: invokestatic a : (II)Ljava/lang/String;
    //   122: invokevirtual equals : (Ljava/lang/Object;)Z
    //   125: ifeq -> 166
    //   128: goto -> 135
    //   131: invokestatic a : (Ljava/lang/MatchException;)Ljava/lang/MatchException;
    //   134: athrow
    //   135: iconst_0
    //   136: istore_3
    //   137: aload_1
    //   138: ifnonnull -> 166
    //   141: aload_2
    //   142: sipush #-7145
    //   145: sipush #-12281
    //   148: invokestatic a : (II)Ljava/lang/String;
    //   151: invokevirtual equals : (Ljava/lang/Object;)Z
    //   154: ifeq -> 166
    //   157: goto -> 164
    //   160: invokestatic a : (Ljava/lang/MatchException;)Ljava/lang/MatchException;
    //   163: athrow
    //   164: iconst_1
    //   165: istore_3
    //   166: iload_3
    //   167: lookupswitch default -> 200, 0 -> 192, 1 -> 192
    //   192: getstatic burp/Zlk4.FAST : Lburp/Zlk4;
    //   195: areturn
    //   196: invokestatic a : (Ljava/lang/MatchException;)Ljava/lang/MatchException;
    //   199: athrow
    //   200: aload_0
    //   201: getfield Zp : Lburp/Zkq4;
    //   204: invokeinterface ZqT : ()Lburp/Zlk4;
    //   209: areturn
    // Exception table:
    //   from	to	target	type
    //   4	26	26	java/lang/MatchException
    //   30	49	49	java/lang/MatchException
    //   83	128	131	java/lang/MatchException
    //   137	157	160	java/lang/MatchException
    //   166	196	196	java/lang/MatchException
  }
  
  public void Zs(Zz4_ paramZz4_) {
    // Byte code:
    //   0: aload_0
    //   1: getfield Zp : Lburp/Zkq4;
    //   4: iconst_2
    //   5: anewarray burp/Zvs
    //   8: dup
    //   9: iconst_0
    //   10: aload_0
    //   11: getfield ZK : Lburp/Zvs;
    //   14: aastore
    //   15: dup
    //   16: iconst_1
    //   17: getstatic burp/Zzu2.XPATH_INJECTION : Lburp/Zzu2;
    //   20: aastore
    //   21: invokeinterface ZN : ([Lburp/Zvs;)Z
    //   26: ifeq -> 52
    //   29: aload_0
    //   30: getfield Zy : Lburp/Zxs7;
    //   33: aload_0
    //   34: getfield Zp : Lburp/Zkq4;
    //   37: invokeinterface Zq : (Lburp/Zbph;)Z
    //   42: ifeq -> 57
    //   45: goto -> 52
    //   48: invokestatic a : (Ljava/lang/MatchException;)Ljava/lang/MatchException;
    //   51: athrow
    //   52: return
    //   53: invokestatic a : (Ljava/lang/MatchException;)Ljava/lang/MatchException;
    //   56: athrow
    //   57: aload_0
    //   58: getfield Zr : Lburp/Zrj;
    //   61: invokevirtual Zg : ()I
    //   64: istore_2
    //   65: new burp/Zrfj
    //   68: dup
    //   69: invokespecial <init> : ()V
    //   72: astore_3
    //   73: aload_0
    //   74: getfield Zp : Lburp/Zkq4;
    //   77: aload_0
    //   78: getfield ZK : Lburp/Zvs;
    //   81: getstatic burp/Zr3z.COLLABORATOR_BASED : Lburp/Zr3z;
    //   84: invokeinterface ZS : (Lburp/Zvs;Lburp/Zr3z;)Z
    //   89: ifeq -> 186
    //   92: aload_0
    //   93: getfield Zp : Lburp/Zkq4;
    //   96: aload_0
    //   97: getfield ZK : Lburp/Zvs;
    //   100: getstatic burp/Zr3z.ORACLE_SPECIFIC : Lburp/Zr3z;
    //   103: invokeinterface ZS : (Lburp/Zvs;Lburp/Zr3z;)Z
    //   108: ifeq -> 186
    //   111: goto -> 118
    //   114: invokestatic a : (Ljava/lang/MatchException;)Ljava/lang/MatchException;
    //   117: athrow
    //   118: new burp/Zbn6
    //   121: dup
    //   122: aload_0
    //   123: getfield ZV : Lnet/portswigger/Zsy;
    //   126: aload_0
    //   127: getfield ZG : Lburp/Zbjl;
    //   130: iload_2
    //   131: aload_0
    //   132: getfield ZF : Lburp/Zmhe;
    //   135: invokeinterface Zn : ()I
    //   140: invokespecial <init> : (Lnet/portswigger/Zsy;Lburp/Zbjl;II)V
    //   143: astore #4
    //   145: new burp/Zgvz
    //   148: dup
    //   149: aload_0
    //   150: getfield ZG : Lburp/Zbjl;
    //   153: aload_0
    //   154: getfield ZF : Lburp/Zmhe;
    //   157: aload_0
    //   158: getfield Zy : Lburp/Zxs7;
    //   161: aload_0
    //   162: getfield Zp : Lburp/Zkq4;
    //   165: aload #4
    //   167: aload_0
    //   168: getfield Zm : Lburp/Ze3n;
    //   171: aload_1
    //   172: aload_3
    //   173: getstatic burp/Zr3z.ORACLE_SPECIFIC : Lburp/Zr3z;
    //   176: aload_0
    //   177: getfield Ze : Lburp/Zesv;
    //   180: invokespecial <init> : (Lburp/Zbjl;Lburp/Zmhe;Lburp/Zxs7;Lburp/Ztai;Lburp/Zrbu;Lburp/Ze3n;Lburp/Zz4_;Lburp/Zrfj;Lburp/Zr3z;Lburp/Zesv;)V
    //   183: invokevirtual ZU : ()V
    //   186: aload_0
    //   187: getfield Zp : Lburp/Zkq4;
    //   190: aload_0
    //   191: getfield ZK : Lburp/Zvs;
    //   194: getstatic burp/Zr3z.COLLABORATOR_BASED : Lburp/Zr3z;
    //   197: invokeinterface ZS : (Lburp/Zvs;Lburp/Zr3z;)Z
    //   202: ifeq -> 308
    //   205: aload_0
    //   206: getfield Zp : Lburp/Zkq4;
    //   209: aload_0
    //   210: getfield ZK : Lburp/Zvs;
    //   213: getstatic burp/Zr3z.MSSQL_SPECIFIC : Lburp/Zr3z;
    //   216: invokeinterface ZS : (Lburp/Zvs;Lburp/Zr3z;)Z
    //   221: ifeq -> 308
    //   224: goto -> 231
    //   227: invokestatic a : (Ljava/lang/MatchException;)Ljava/lang/MatchException;
    //   230: athrow
    //   231: new burp/Zx4p
    //   234: dup
    //   235: aload_0
    //   236: getfield ZV : Lnet/portswigger/Zsy;
    //   239: aload_0
    //   240: getfield Zp : Lburp/Zkq4;
    //   243: invokeinterface ZqT : ()Lburp/Zlk4;
    //   248: aload_0
    //   249: getfield ZG : Lburp/Zbjl;
    //   252: iload_2
    //   253: aload_0
    //   254: getfield ZF : Lburp/Zmhe;
    //   257: invokeinterface Zn : ()I
    //   262: invokespecial <init> : (Lnet/portswigger/Zsy;Lburp/Zlk4;Lburp/Zbjl;II)V
    //   265: astore #4
    //   267: new burp/Zgvz
    //   270: dup
    //   271: aload_0
    //   272: getfield ZG : Lburp/Zbjl;
    //   275: aload_0
    //   276: getfield ZF : Lburp/Zmhe;
    //   279: aload_0
    //   280: getfield Zy : Lburp/Zxs7;
    //   283: aload_0
    //   284: getfield Zp : Lburp/Zkq4;
    //   287: aload #4
    //   289: aload_0
    //   290: getfield Zm : Lburp/Ze3n;
    //   293: aload_1
    //   294: aload_3
    //   295: getstatic burp/Zr3z.MSSQL_SPECIFIC : Lburp/Zr3z;
    //   298: aload_0
    //   299: getfield Ze : Lburp/Zesv;
    //   302: invokespecial <init> : (Lburp/Zbjl;Lburp/Zmhe;Lburp/Zxs7;Lburp/Ztai;Lburp/Zrbu;Lburp/Ze3n;Lburp/Zz4_;Lburp/Zrfj;Lburp/Zr3z;Lburp/Zesv;)V
    //   305: invokevirtual ZU : ()V
    //   308: aload_0
    //   309: getfield Zp : Lburp/Zkq4;
    //   312: aload_0
    //   313: getfield ZK : Lburp/Zvs;
    //   316: getstatic burp/Zr3z.COLLABORATOR_BASED : Lburp/Zr3z;
    //   319: invokeinterface ZS : (Lburp/Zvs;Lburp/Zr3z;)Z
    //   324: ifeq -> 430
    //   327: aload_0
    //   328: getfield Zp : Lburp/Zkq4;
    //   331: aload_0
    //   332: getfield ZK : Lburp/Zvs;
    //   335: getstatic burp/Zr3z.MYSQL_SPECIFIC : Lburp/Zr3z;
    //   338: invokeinterface ZS : (Lburp/Zvs;Lburp/Zr3z;)Z
    //   343: ifeq -> 430
    //   346: goto -> 353
    //   349: invokestatic a : (Ljava/lang/MatchException;)Ljava/lang/MatchException;
    //   352: athrow
    //   353: new burp/Zkga
    //   356: dup
    //   357: aload_0
    //   358: getfield ZV : Lnet/portswigger/Zsy;
    //   361: aload_0
    //   362: getfield Zp : Lburp/Zkq4;
    //   365: invokeinterface ZqT : ()Lburp/Zlk4;
    //   370: aload_0
    //   371: getfield ZG : Lburp/Zbjl;
    //   374: iload_2
    //   375: aload_0
    //   376: getfield ZF : Lburp/Zmhe;
    //   379: invokeinterface Zn : ()I
    //   384: invokespecial <init> : (Lnet/portswigger/Zsy;Lburp/Zlk4;Lburp/Zbjl;II)V
    //   387: astore #4
    //   389: new burp/Zgvz
    //   392: dup
    //   393: aload_0
    //   394: getfield ZG : Lburp/Zbjl;
    //   397: aload_0
    //   398: getfield ZF : Lburp/Zmhe;
    //   401: aload_0
    //   402: getfield Zy : Lburp/Zxs7;
    //   405: aload_0
    //   406: getfield Zp : Lburp/Zkq4;
    //   409: aload #4
    //   411: aload_0
    //   412: getfield Zm : Lburp/Ze3n;
    //   415: aload_1
    //   416: aload_3
    //   417: getstatic burp/Zr3z.MYSQL_SPECIFIC : Lburp/Zr3z;
    //   420: aload_0
    //   421: getfield Ze : Lburp/Zesv;
    //   424: invokespecial <init> : (Lburp/Zbjl;Lburp/Zmhe;Lburp/Zxs7;Lburp/Ztai;Lburp/Zrbu;Lburp/Ze3n;Lburp/Zz4_;Lburp/Zrfj;Lburp/Zr3z;Lburp/Zesv;)V
    //   427: invokevirtual ZU : ()V
    //   430: aload_0
    //   431: getfield Zp : Lburp/Zkq4;
    //   434: aload_0
    //   435: getfield ZK : Lburp/Zvs;
    //   438: getstatic burp/Zr3z.ERROR_BASED : Lburp/Zr3z;
    //   441: invokeinterface ZS : (Lburp/Zvs;Lburp/Zr3z;)Z
    //   446: ifne -> 514
    //   449: aload_0
    //   450: getfield Zp : Lburp/Zkq4;
    //   453: aload_0
    //   454: getfield ZK : Lburp/Zvs;
    //   457: getstatic burp/Zr3z.BOOLEAN_BASED : Lburp/Zr3z;
    //   460: invokeinterface ZS : (Lburp/Zvs;Lburp/Zr3z;)Z
    //   465: ifne -> 514
    //   468: goto -> 475
    //   471: invokestatic a : (Ljava/lang/MatchException;)Ljava/lang/MatchException;
    //   474: athrow
    //   475: aload_0
    //   476: getfield Zp : Lburp/Zkq4;
    //   479: getstatic burp/Zzu2.XPATH_INJECTION : Lburp/Zzu2;
    //   482: getstatic burp/Zr3z.ERROR_BASED : Lburp/Zr3z;
    //   485: invokeinterface ZS : (Lburp/Zvs;Lburp/Zr3z;)Z
    //   490: ifeq -> 529
    //   493: goto -> 500
    //   496: invokestatic a : (Ljava/lang/MatchException;)Ljava/lang/MatchException;
    //   499: athrow
    //   500: aload_0
    //   501: getfield Zv : Z
    //   504: ifne -> 529
    //   507: goto -> 514
    //   510: invokestatic a : (Ljava/lang/MatchException;)Ljava/lang/MatchException;
    //   513: athrow
    //   514: aload_3
    //   515: aload_0
    //   516: invokevirtual ZH : ()Lburp/Zm4g;
    //   519: invokevirtual Zi : (Lburp/Zm4g;)V
    //   522: goto -> 529
    //   525: invokestatic a : (Ljava/lang/MatchException;)Ljava/lang/MatchException;
    //   528: athrow
    //   529: aload_3
    //   530: invokevirtual Zv : ()I
    //   533: istore #4
    //   535: aload_0
    //   536: getfield Zp : Lburp/Zkq4;
    //   539: aload_0
    //   540: getfield ZK : Lburp/Zvs;
    //   543: getstatic burp/Zr3z.TIME_BASED : Lburp/Zr3z;
    //   546: invokeinterface ZS : (Lburp/Zvs;Lburp/Zr3z;)Z
    //   551: ifeq -> 571
    //   554: aload_3
    //   555: aload_0
    //   556: iload #4
    //   558: invokevirtual ZX : (I)Lburp/Zm4g;
    //   561: invokevirtual Zi : (Lburp/Zm4g;)V
    //   564: goto -> 571
    //   567: invokestatic a : (Ljava/lang/MatchException;)Ljava/lang/MatchException;
    //   570: athrow
    //   571: aload_0
    //   572: getfield Zp : Lburp/Zkq4;
    //   575: aload_0
    //   576: getfield ZK : Lburp/Zvs;
    //   579: getstatic burp/Zr3z.BOOLEAN_BASED : Lburp/Zr3z;
    //   582: invokeinterface ZS : (Lburp/Zvs;Lburp/Zr3z;)Z
    //   587: ifne -> 615
    //   590: aload_0
    //   591: getfield Zp : Lburp/Zkq4;
    //   594: getstatic burp/Zzu2.XPATH_INJECTION : Lburp/Zzu2;
    //   597: getstatic burp/Zr3z.BOOLEAN_BASED : Lburp/Zr3z;
    //   600: invokeinterface ZS : (Lburp/Zvs;Lburp/Zr3z;)Z
    //   605: ifeq -> 632
    //   608: goto -> 615
    //   611: invokestatic a : (Ljava/lang/MatchException;)Ljava/lang/MatchException;
    //   614: athrow
    //   615: aload_3
    //   616: aload_0
    //   617: iload #4
    //   619: invokevirtual ZK : (I)Lburp/Zm4g;
    //   622: invokevirtual Zi : (Lburp/Zm4g;)V
    //   625: goto -> 632
    //   628: invokestatic a : (Ljava/lang/MatchException;)Ljava/lang/MatchException;
    //   631: athrow
    //   632: aload_0
    //   633: getfield Zp : Lburp/Zkq4;
    //   636: aload_0
    //   637: getfield ZK : Lburp/Zvs;
    //   640: getstatic burp/Zr3z.ERROR_BASED : Lburp/Zr3z;
    //   643: invokeinterface ZS : (Lburp/Zvs;Lburp/Zr3z;)Z
    //   648: ifne -> 676
    //   651: aload_0
    //   652: getfield Zp : Lburp/Zkq4;
    //   655: getstatic burp/Zzu2.XPATH_INJECTION : Lburp/Zzu2;
    //   658: getstatic burp/Zr3z.ERROR_BASED : Lburp/Zr3z;
    //   661: invokeinterface ZS : (Lburp/Zvs;Lburp/Zr3z;)Z
    //   666: ifeq -> 702
    //   669: goto -> 676
    //   672: invokestatic a : (Ljava/lang/MatchException;)Ljava/lang/MatchException;
    //   675: athrow
    //   676: aload_3
    //   677: aload_0
    //   678: ldc '"'
    //   680: iconst_0
    //   681: iconst_1
    //   682: aload_0
    //   683: invokevirtual ZQ : ()I
    //   686: invokevirtual ZS : (Ljava/lang/String;IBI)Lburp/Zl6l;
    //   689: getfield Zf : Lburp/Zm4g;
    //   692: invokevirtual Zi : (Lburp/Zm4g;)V
    //   695: goto -> 702
    //   698: invokestatic a : (Ljava/lang/MatchException;)Ljava/lang/MatchException;
    //   701: athrow
    //   702: aload_0
    //   703: getfield ZD : Ljava/util/function/Consumer;
    //   706: new burp/Zxcb
    //   709: dup
    //   710: aload_3
    //   711: invokespecial <init> : (Lburp/Zrfj;)V
    //   714: invokeinterface accept : (Ljava/lang/Object;)V
    //   719: aload_3
    //   720: aload_1
    //   721: invokevirtual ZM : (Lburp/Zz4_;)V
    //   724: return
    // Exception table:
    //   from	to	target	type
    //   0	45	48	java/lang/MatchException
    //   29	53	53	java/lang/MatchException
    //   73	111	114	java/lang/MatchException
    //   186	224	227	java/lang/MatchException
    //   308	346	349	java/lang/MatchException
    //   430	468	471	java/lang/MatchException
    //   449	493	496	java/lang/MatchException
    //   475	507	510	java/lang/MatchException
    //   500	522	525	java/lang/MatchException
    //   535	564	567	java/lang/MatchException
    //   571	608	611	java/lang/MatchException
    //   590	625	628	java/lang/MatchException
    //   632	669	672	java/lang/MatchException
    //   651	695	698	java/lang/MatchException
  }
  
  private Zm4g ZH() {
    Zm4g zm4g = Zt(0, 4);
    try {
      if (zm4g != null)
        return zm4g; 
    } catch (MatchException matchException) {
      throw a(null);
    } 
    if (this.Zp.ZqT().ZH(Zlk4.THOROUGH)) {
      zm4g = ZR(1);
      try {
        if (zm4g != null)
          return zm4g; 
      } catch (MatchException matchException) {
        throw a(null);
      } 
      zm4g = ZR(2);
      try {
        if (zm4g != null)
          return zm4g; 
      } catch (MatchException matchException) {
        throw a(null);
      } 
      Zl6l zl6l = ZS(a(-7148, -18964), 0, (byte)1, ZQ());
      try {
        if (zl6l.Zf != null)
          return zl6l.Zf; 
      } catch (MatchException matchException) {
        throw a(null);
      } 
    } 
    return null;
  }
  
  private Zm4g ZR(int paramInt) {
    return Zt(paramInt, paramInt);
  }
  
  private Zm4g Zt(int paramInt1, int paramInt2) {
    Zm4g zm4g1 = null;
    Zm4g zm4g2 = Zb(paramInt1, "'", a(-7138, 22646), a(-7140, 18957), a(-7147, 27706), (byte)0);
    try {
      if (zm4g2 != null) {
        try {
          if (zm4g2.ZU() != 3) {
            try {
              if (zm4g2 instanceof Zzwv)
                return zm4g2; 
            } catch (MatchException matchException) {
              throw a(null);
            } 
          } else {
            return zm4g2;
          } 
        } catch (MatchException matchException) {
          throw a(null);
        } 
        zm4g1 = zm4g2;
      } 
    } catch (MatchException matchException) {
      throw a(null);
    } 
    try {
      if (this.Zp.ZqT().ZH(Zlk4.THOROUGH) && this.Zp.ZS(this.ZK, Zr3z.MYSQL_SPECIFIC)) {
        zm4g2 = Zb(paramInt2, a(-7152, -505), a(-7144, -29844), a(-7139, -26430), a(-7146, -17043), (byte)3);
        try {
          if (zm4g2 != null) {
            try {
              if (zm4g2.ZU() != 3) {
                try {
                  if (zm4g2 instanceof Zzwv)
                    return zm4g2; 
                } catch (MatchException matchException) {
                  throw a(null);
                } 
              } else {
                return zm4g2;
              } 
            } catch (MatchException matchException) {
              throw a(null);
            } 
            try {
              if (zm4g1 == null || zm4g2.ZU() > zm4g1.ZU())
                zm4g1 = zm4g2; 
            } catch (MatchException matchException) {
              throw a(null);
            } 
          } 
        } catch (MatchException matchException) {
          throw a(null);
        } 
      } 
    } catch (MatchException matchException) {
      throw a(null);
    } 
    return zm4g1;
  }
  
  private Zm4g Zb(int paramInt, String paramString1, String paramString2, String paramString3, String paramString4, byte paramByte) {
    Zl6l zl6l1 = ZU(paramString1, paramInt, (byte)1, paramByte, ZQ(), true);
    try {
      if (zl6l1.Zf == null)
        return null; 
    } catch (MatchException matchException) {
      throw a(null);
    } 
    try {
      if (zl6l1.Zf instanceof Zzwv)
        return zl6l1.Zf; 
    } catch (MatchException matchException) {
      throw a(null);
    } 
    Zl6l zl6l2 = ZU(paramString2, paramInt, (byte)1, paramByte, ZQ(), true);
    if (ZF(zl6l1.Zf, 16)) {
      Zrg8 zrg8 = (Zrg8)zl6l1.Zf;
      try {
        if (zl6l2.Zf == null) {
          zrg8.ZG(zl6l2.Zm, zl6l2.ZH, (byte)3, 32, zl6l2.Zl.ZO(), Collections.emptyList());
          return zl6l1.Zf;
        } 
      } catch (MatchException matchException) {
        throw a(null);
      } 
      return zl6l1.Zf;
    } 
    if (ZF(zl6l1.Zf, 8)) {
      Zrg8 zrg8 = (Zrg8)zl6l1.Zf;
      if (zl6l2.Zf == null) {
        Zl6l zl6l3 = ZU(paramString3, paramInt, (byte)1, paramByte, ZQ(), true);
        try {
          if (zl6l3.Zf == null)
            return null; 
        } catch (MatchException matchException) {
          throw a(null);
        } 
        Zl6l zl6l4 = ZU(paramString4, paramInt, (byte)1, paramByte, ZQ(), true);
        try {
          if (zl6l4.Zf != null)
            return null; 
        } catch (MatchException matchException) {
          throw a(null);
        } 
        zrg8.ZG(zl6l2.Zm, zl6l2.ZH, (byte)1, 64, zl6l2.Zl.ZO(), Collections.emptyList());
        return zl6l1.Zf;
      } 
    } 
    return null;
  }
  
  private static boolean ZF(Zm4g paramZm4g, int paramInt) {
    try {
      if (paramZm4g instanceof Zrg8)
        try {
          if ((paramZm4g.Zl() & paramInt) == paramInt);
        } catch (MatchException matchException) {
          throw a(null);
        }  
    } catch (MatchException matchException) {
      throw a(null);
    } 
    return false;
  }
  
  private Zm4g ZX(int paramInt) {
    if (this.Zp.ZS(this.ZK, Zr3z.MYSQL_SPECIFIC)) {
      Zm4g zm4g = this.ZU.ZK(paramInt, new Zkva(this.Zy, this.ZF, this.ZN, this.Zm.Zc()[0].longValue()));
      try {
        if (zm4g != null)
          return zm4g; 
      } catch (MatchException matchException) {
        throw a(null);
      } 
    } 
    if (this.Zp.ZS(this.ZK, Zr3z.MSSQL_SPECIFIC)) {
      Zm4g zm4g = this.ZU.Zp(paramInt, new Zkva(this.Zy, this.ZF, this.ZN, this.Zm.Zc()[0].longValue()));
      try {
        if (zm4g != null)
          return zm4g; 
      } catch (MatchException matchException) {
        throw a(null);
      } 
    } 
    try {
      if (this.Zp.ZS(this.ZK, Zr3z.POSTGRES_SPECIFIC))
        return this.ZU.ZT(paramInt, new Zkva(this.Zy, this.ZF, this.ZN, this.Zm.Zc()[0].longValue())); 
    } catch (MatchException matchException) {
      throw a(null);
    } 
    return null;
  }
  
  private Zm4g ZK(int paramInt) {
    try {
      if (this.Zy.Zg() || this.Zy.Zu()) {
        Zm4g zm4g1 = Zj(paramInt, "");
        try {
          if (zm4g1 != null)
            return zm4g1; 
        } catch (MatchException matchException) {
          throw a(null);
        } 
      } 
    } catch (MatchException matchException) {
      throw a(null);
    } 
    Zm4g zm4g = Zj(paramInt, "'");
    try {
      if (zm4g != null)
        return zm4g; 
    } catch (MatchException matchException) {
      throw a(null);
    } 
    try {
      if (this.Zp.ZqT().ZH(Zlk4.THOROUGH))
        try {
          if (this.Zp.ZS(this.ZK, Zr3z.BOOLEAN_BASED))
            return Za(paramInt); 
        } catch (MatchException matchException) {
          throw a(null);
        }  
    } catch (MatchException matchException) {
      throw a(null);
    } 
    return null;
  }
  
  private Zm4g Zj(int paramInt, String paramString) {
    try {
    
    } catch (MatchException matchException) {
      throw a(null);
    } 
    boolean bool = !paramString.isEmpty() ? true : false;
    Zm4g zm4g = Zx(paramInt, new Zed1(bool, Zin.OR, this.ZV), new Zz2k(this, this.ZV, bool, paramString, paramString));
    try {
      if (zm4g != null)
        return zm4g; 
    } catch (MatchException matchException) {
      throw a(null);
    } 
    zm4g = Zx(paramInt, null, new Zz2c(this, this.ZV, bool, paramString, paramString));
    try {
      if (zm4g != null)
        return zm4g; 
    } catch (MatchException matchException) {
      throw a(null);
    } 
    if (this.Zp.ZqT().ZH(Zlk4.NORMAL)) {
      null = Zx(paramInt, new Zed1(bool, Zin.AND, this.ZV), new Zz2d(this, this.ZV, bool, paramString, paramString));
      try {
        if (null != null)
          return null; 
      } catch (MatchException matchException) {
        throw a(null);
      } 
      return Zx(paramInt, null, new Zz2g(this, this.ZV, bool, paramString, paramString));
    } 
    return null;
  }
  
  private Zm4g Za(int paramInt) {
    Zggh zggh = new Zggh(this, paramInt, 1, (byte)0, new Zso1(Arrays.asList(new String[] { a(-7143, -4704), a(-7149, -11261), "1", a(-7137, 6455) }), Arrays.asList(new String[] { a(-7151, 13045), a(-7142, -6012), "0", a(-7150, -13366) })));
    Zxzf zxzf = new Zxzf(this.Zm.ZA().ZF(), null, zggh, this.Zs);
    if (zxzf.Ze(this.Zp.ZqM())) {
      Zkvd zkvd = zxzf.ZX().Zo(ZY(zggh.ZY), ZY(zggh.Zu));
      byte[] arrayOfByte1 = Zkb.Zy(Zv85.Zz(zggh.ZY.ZH, paramInt));
      byte[] arrayOfByte2 = Zkb.Zy(Zv85.Zz(zggh.Zu.ZH, paramInt));
      try {
      
      } catch (MatchException matchException) {
        throw a(null);
      } 
      return Zrg8.ZA(this.Z_.Za(), this.Z_.ZN(), zkvd.Zt() ? 2 : 1, 256, paramInt, (byte)0, this.Zy, arrayOfByte1, arrayOfByte2, zggh.ZY.Zm, zggh.Zu.Zm, zggh.ZY.Zl.ZO(), zkvd.ZF(), zggh.Zu.Zl.ZO(), zkvd.ZR());
    } 
    return zggh.ZY.Zf;
  }
  
  private Zm4g Zx(int paramInt, Zed1 paramZed1, Zmsx paramZmsx) {
    try {
      if (!this.Zp.Zr(this.ZK))
        try {
          if (!this.Zp.Zr(Zzu2.XPATH_INJECTION))
            return null; 
        } catch (MatchException matchException) {
          throw a(null);
        }  
    } catch (MatchException matchException) {
      throw a(null);
    } 
    Zggh zggh = new Zggh(this, paramInt, ZQ(), (byte)1, paramZmsx);
    Zxzf zxzf = new Zxzf(this.Zm.ZA().ZF(), null, zggh, this.Zs);
    try {
      if (!zxzf.Ze(this.Zp.ZqM()))
        return zggh.ZY.Zf; 
    } catch (MatchException matchException) {
      throw a(null);
    } 
    Zsb8 zsb8 = zxzf.ZX();
    Zkvd zkvd = zsb8.Zp();
    try {
      if (!this.Zv && paramZed1 != null) {
        Zm4g zm4g = ZO(paramInt, paramZed1, zsb8);
        try {
          if (zm4g != null) {
            try {
            
            } catch (MatchException matchException) {
              throw a(null);
            } 
            return this.Zp.ZS(Zzu2.XPATH_INJECTION, Zr3z.BOOLEAN_BASED) ? zm4g : null;
          } 
        } catch (MatchException matchException) {
          throw a(null);
        } 
      } 
    } catch (MatchException matchException) {
      throw a(null);
    } 
    try {
    
    } catch (MatchException matchException) {
      throw a(null);
    } 
    return this.Zp.ZS(this.ZK, Zr3z.BOOLEAN_BASED) ? Zl(zggh, zkvd, paramInt) : null;
  }
  
  private Zm4g ZO(int paramInt, Zed1 paramZed1, Zsb8 paramZsb8) {
    Zggh zggh = new Zggh(this, paramInt, ZQ(), (byte)1, paramZed1);
    Zxzf zxzf = new Zxzf(this.Zm.ZA().ZF(), zggh, paramZsb8);
    try {
      if (!zxzf.Ze(this.Zp.ZqM()))
        return null; 
    } catch (MatchException matchException) {
      throw a(null);
    } 
    Zkvd zkvd = paramZsb8.Zo(ZY(zggh.ZY), ZY(zggh.Zu));
    return ZK(zggh, zkvd, paramInt);
  }
  
  private Zm4g ZK(Zggh paramZggh, Zkvd paramZkvd, int paramInt) {
    byte[] arrayOfByte1 = Zkb.Zy(Zv85.Zz(paramZggh.Zu.ZH, paramInt));
    Zvow zvow1 = ZO(paramZkvd.ZR(), paramZggh.Zu, paramZggh.Zu.Zl);
    byte[] arrayOfByte2 = Zkb.Zy(Zv85.Zz(paramZggh.ZY.ZH, paramInt));
    Zvow zvow2 = ZO(paramZkvd.ZF(), paramZggh.ZY, paramZggh.ZY.Zl);
    try {
    
    } catch (MatchException matchException) {
      throw a(null);
    } 
    return Zzwv.Zw(this.Z_.Za(), this.Z_.ZN(), this.Zy, paramZkvd.Zt() ? 2 : 1, arrayOfByte2, arrayOfByte1, zvow2, zvow1);
  }
  
  private Zm4g Zl(Zggh paramZggh, Zkvd paramZkvd, int paramInt) {
    try {
    
    } catch (MatchException matchException) {
      throw a(null);
    } 
    return Zrg8.ZA(this.Z_.Za(), this.Z_.ZN(), paramZkvd.Zt() ? 2 : 1, 128, paramInt, (byte)0, this.Zy, Zkb.Zy(Zv85.Zz(paramZggh.ZY.ZH, paramInt)), Zkb.Zy(Zv85.Zz(paramZggh.Zu.ZH, paramInt)), paramZggh.ZY.Zm, paramZggh.Zu.Zm, paramZggh.ZY.Zl.ZO(), paramZkvd.ZF(), paramZggh.Zu.Zl.ZO(), paramZkvd.ZR());
  }
  
  private Zvow ZO(List<Zl1r> paramList, Zl6l paramZl6l, Zs2i paramZs2i) {
    try {
    
    } catch (MatchException matchException) {
      throw a(null);
    } 
    return this.Z_.ZI().Zp(paramZs2i.ZE()).ZK(paramZs2i.ZO()).Zu(ZY(paramZl6l)).Z_(paramList).Zj((paramZl6l.Zm.ZM().Zq() > 0));
  }
  
  private Zl6l ZS(String paramString, int paramInt1, byte paramByte, int paramInt2) {
    return ZU(paramString, paramInt1, paramByte, (byte)0, paramInt2, false);
  }
  
  private Zl6l ZU(String paramString, int paramInt1, byte paramByte1, byte paramByte2, int paramInt2, boolean paramBoolean) {
    Zl6l zl6l = null;
    byte b = 0;
    int[] arrayOfInt = Zp();
    while (b < paramInt2) {
      String str = Zv85.Zz(paramString, paramInt1);
      byte[] arrayOfByte = Zkb.Zy(str);
      Zlvf zlvf = this.ZF.ZK(Zri7.ZJ(new Zrrb(arrayOfByte, paramByte1)), Zlp5.Zc().Zd(true));
      zl6l = this.ZN.ZH(this.ZF, paramInt1, paramByte1, paramBoolean, paramByte2, arrayOfByte, zlvf.ZY(), this.Zy, zlvf);
      try {
        if (zl6l.Zf == null)
          return zl6l; 
      } catch (MatchException matchException) {
        throw a(null);
      } 
      b++;
      if (arrayOfInt == null)
        break; 
    } 
    return zl6l;
  }
  
  private int ZQ() {
    try {
      switch (Zeht.ZM[this.Zp.ZqM().ordinal()]) {
        default:
          throw new MatchException(null, null);
        case 1:
        
        case 2:
        
        case 3:
          break;
      } 
    } catch (MatchException matchException) {
      throw a(null);
    } 
    return 3;
  }
  
  private Zstu ZY(Zl6l paramZl6l) {
    return paramZl6l.Zm.ZM().Zl();
  }
  
  public static void Zm(int[] paramArrayOfint) {
    ZI = paramArrayOfint;
  }
  
  public static int[] Zp() {
    return ZI;
  }
  
  private static MatchException a(MatchException paramMatchException) {
    return paramMatchException;
  }
  
  static {
    // Byte code:
    //   0: bipush #16
    //   2: anewarray java/lang/String
    //   5: astore #5
    //   7: iconst_4
    //   8: newarray int
    //   10: iconst_0
    //   11: istore_3
    //   12: ldc 'Â­Â²Â¡ÂˆÂ˜Â½*ÂŸ0Ã‹Ã³Ã›'LuEÂ‡\\nÃ‘XÂ–OÂ‹Â‹Â¼!~\\nÂ Â§NÃ¼Â¤ÃCÃšÃ›[Â‹ÂŸddD(4Ã§Ã§Ã‹FÃ§[?\\fÃ±Ã¶9Â¡<FÂ¬Ã¡>Â¡Â·Â\\nÂ˜,Â¿Â“jM8Â‘Â¢Ã›Ã®Ã¨ Âƒ'
    //   14: dup
    //   15: astore_2
    //   16: invokevirtual length : ()I
    //   19: istore #4
    //   21: iconst_3
    //   22: istore_1
    //   23: invokestatic Zm : ([I)V
    //   26: iconst_m1
    //   27: istore_0
    //   28: bipush #121
    //   30: iinc #0, 1
    //   33: aload_2
    //   34: iload_0
    //   35: dup
    //   36: iload_1
    //   37: iadd
    //   38: invokevirtual substring : (II)Ljava/lang/String;
    //   41: iconst_m1
    //   42: goto -> 147
    //   45: aload #5
    //   47: swap
    //   48: iload_3
    //   49: iinc #3, 1
    //   52: swap
    //   53: aastore
    //   54: iload_0
    //   55: iload_1
    //   56: iadd
    //   57: dup
    //   58: istore_0
    //   59: iload #4
    //   61: if_icmpge -> 73
    //   64: aload_2
    //   65: iload_0
    //   66: invokevirtual charAt : (I)C
    //   69: istore_1
    //   70: goto -> 28
    //   73: ldc 'ÃÂ³Â Ã®Â¡ÂŠÃªÂ›Ã¢Ã®9/'
    //   75: dup
    //   76: astore_2
    //   77: invokevirtual length : ()I
    //   80: istore #4
    //   82: iconst_5
    //   83: istore_1
    //   84: iconst_m1
    //   85: istore_0
    //   86: bipush #75
    //   88: iinc #0, 1
    //   91: aload_2
    //   92: iload_0
    //   93: dup
    //   94: iload_1
    //   95: iadd
    //   96: invokevirtual substring : (II)Ljava/lang/String;
    //   99: iconst_0
    //   100: goto -> 147
    //   103: aload #5
    //   105: swap
    //   106: iload_3
    //   107: iinc #3, 1
    //   110: swap
    //   111: aastore
    //   112: iload_0
    //   113: iload_1
    //   114: iadd
    //   115: dup
    //   116: istore_0
    //   117: iload #4
    //   119: if_icmpge -> 131
    //   122: aload_2
    //   123: iload_0
    //   124: invokevirtual charAt : (I)C
    //   127: istore_1
    //   128: goto -> 86
    //   131: aload #5
    //   133: putstatic burp/Zz6s.a : [Ljava/lang/String;
    //   136: bipush #16
    //   138: anewarray java/lang/String
    //   141: putstatic burp/Zz6s.b : [Ljava/lang/String;
    //   144: goto -> 304
    //   147: dup_x2
    //   148: pop
    //   149: invokevirtual toCharArray : ()[C
    //   152: dup_x1
    //   153: arraylength
    //   154: dup_x2
    //   155: pop
    //   156: iconst_0
    //   157: istore #6
    //   159: dup2_x1
    //   160: pop2
    //   161: dup_x2
    //   162: iconst_1
    //   163: if_icmpgt -> 264
    //   166: dup2
    //   167: swap
    //   168: iload #6
    //   170: dup2_x1
    //   171: caload
    //   172: swap
    //   173: iload #6
    //   175: bipush #7
    //   177: irem
    //   178: tableswitch default -> 246, 0 -> 216, 1 -> 221, 2 -> 226, 3 -> 231, 4 -> 236, 5 -> 241
    //   216: bipush #69
    //   218: goto -> 248
    //   221: bipush #123
    //   223: goto -> 248
    //   226: bipush #26
    //   228: goto -> 248
    //   231: bipush #94
    //   233: goto -> 248
    //   236: bipush #36
    //   238: goto -> 248
    //   241: bipush #32
    //   243: goto -> 248
    //   246: bipush #26
    //   248: ixor
    //   249: ixor
    //   250: i2c
    //   251: castore
    //   252: iinc #6, 1
    //   255: dup
    //   256: ifne -> 264
    //   259: dup2
    //   260: dup_x1
    //   261: goto -> 170
    //   264: dup2_x1
    //   265: pop2
    //   266: dup_x2
    //   267: iload #6
    //   269: if_icmpgt -> 166
    //   272: pop
    //   273: new java/lang/String
    //   276: dup_x1
    //   277: swap
    //   278: invokespecial <init> : ([C)V
    //   281: invokevirtual intern : ()Ljava/lang/String;
    //   284: swap
    //   285: pop
    //   286: swap
    //   287: tableswitch default -> 45, 0 -> 103
    //   304: return
  }
  
  private static String a(int paramInt1, int paramInt2) {
    int i = (paramInt1 ^ 0xFFFFE418) & 0xFFFF;
    if (b[i] == null) {
      char[] arrayOfChar = a[i].toCharArray();
      switch (arrayOfChar[0] & 0xFF) {
        case 0:
        
        case 1:
        
        case 2:
        
        case 3:
        
        case 4:
        
        case 5:
        
        case 6:
        
        case 7:
        
        case 8:
        
        case 9:
        
        case 10:
        
        case 11:
        
        case 12:
        
        case 13:
        
        case 14:
        
        case 15:
        
        case 16:
        
        case 17:
        
        case 18:
        
        case 19:
        
        case 20:
        
        case 21:
        
        case 22:
        
        case 23:
        
        case 24:
        
        case 25:
        
        case 26:
        
        case 27:
        
        case 28:
        
        case 29:
        
        case 30:
        
        case 31:
        
        case 32:
        
        case 33:
        
        case 34:
        
        case 35:
        
        case 36:
        
        case 37:
        
        case 38:
        
        case 39:
        
        case 40:
        
        case 41:
        
        case 42:
        
        case 43:
        
        case 44:
        
        case 45:
        
        case 46:
        
        case 47:
        
        case 48:
        
        case 49:
        
        case 50:
        
        case 51:
        
        case 52:
        
        case 53:
        
        case 54:
        
        case 55:
        
        case 56:
        
        case 57:
        
        case 58:
        
        case 59:
        
        case 60:
        
        case 61:
        
        case 62:
        
        case 63:
        
        case 64:
        
        case 65:
        
        case 66:
        
        case 67:
        
        case 68:
        
        case 69:
        
        case 70:
        
        case 71:
        
        case 72:
        
        case 73:
        
        case 74:
        
        case 75:
        
        case 76:
        
        case 77:
        
        case 78:
        
        case 79:
        
        case 80:
        
        case 81:
        
        case 82:
        
        case 83:
        
        case 84:
        
        case 85:
        
        case 86:
        
        case 87:
        
        case 88:
        
        case 89:
        
        case 90:
        
        case 91:
        
        case 92:
        
        case 93:
        
        case 94:
        
        case 95:
        
        case 96:
        
        case 97:
        
        case 98:
        
        case 99:
        
        case 100:
        
        case 101:
        
        case 102:
        
        case 103:
        
        case 104:
        
        case 105:
        
        case 106:
        
        case 107:
        
        case 108:
        
        case 109:
        
        case 110:
        
        case 111:
        
        case 112:
        
        case 113:
        
        case 114:
        
        case 115:
        
        case 116:
        
        case 117:
        
        case 118:
        
        case 119:
        
        case 120:
        
        case 121:
        
        case 122:
        
        case 123:
        
        case 124:
        
        case 125:
        
        case 126:
        
        case 127:
        
        case 128:
        
        case 129:
        
        case 130:
        
        case 131:
        
        case 132:
        
        case 133:
        
        case 134:
        
        case 135:
        
        case 136:
        
        case 137:
        
        case 138:
        
        case 139:
        
        case 140:
        
        case 141:
        
        case 142:
        
        case 143:
        
        case 144:
        
        case 145:
        
        case 146:
        
        case 147:
        
        case 148:
        
        case 149:
        
        case 150:
        
        case 151:
        
        case 152:
        
        case 153:
        
        case 154:
        
        case 155:
        
        case 156:
        
        case 157:
        
        case 158:
        
        case 159:
        
        case 160:
        
        case 161:
        
        case 162:
        
        case 163:
        
        case 164:
        
        case 165:
        
        case 166:
        
        case 167:
        
        case 168:
        
        case 169:
        
        case 170:
        
        case 171:
        
        case 172:
        
        case 173:
        
        case 174:
        
        case 175:
        
        case 176:
        
        case 177:
        
        case 178:
        
        case 179:
        
        case 180:
        
        case 181:
        
        case 182:
        
        case 183:
        
        case 184:
        
        case 185:
        
        case 186:
        
        case 187:
        
        case 188:
        
        case 189:
        
        case 190:
        
        case 191:
        
        case 192:
        
        case 193:
        
        case 194:
        
        case 195:
        
        case 196:
        
        case 197:
        
        case 198:
        
        case 199:
        
        case 200:
        
        case 201:
        
        case 202:
        
        case 203:
        
        case 204:
        
        case 205:
        
        case 206:
        
        case 207:
        
        case 208:
        
        case 209:
        
        case 210:
        
        case 211:
        
        case 212:
        
        case 213:
        
        case 214:
        
        case 215:
        
        case 216:
        
        case 217:
        
        case 218:
        
        case 219:
        
        case 220:
        
        case 221:
        
        case 222:
        
        case 223:
        
        case 224:
        
        case 225:
        
        case 226:
        
        case 227:
        
        case 228:
        
        case 229:
        
        case 230:
        
        case 231:
        
        case 232:
        
        case 233:
        
        case 234:
        
        case 235:
        
        case 236:
        
        case 237:
        
        case 238:
        
        case 239:
        
        case 240:
        
        case 241:
        
        case 242:
        
        case 243:
        
        case 244:
        
        case 245:
        
        case 246:
        
        case 247:
        
        case 248:
        
        case 249:
        
        case 250:
        
        case 251:
        
        case 252:
        
        case 253:
        
        case 254:
        
        default:
          break;
      } 
      byte b1 = 64;
      int j = (paramInt2 & 0xFF) - b1;
      if (j < 0)
        j += 256; 
      int k = ((paramInt2 & 0xFFFF) >>> 8) - b1;
      if (k < 0)
        k += 256; 
      for (byte b2 = 0; b2 < arrayOfChar.length; b2++) {
        int m = b2 % 2;
        if (m == 0) {
          arrayOfChar[b2] = (char)(arrayOfChar[b2] ^ j);
          j = ((j >>> 3 | j << 5) ^ arrayOfChar[b2]) & 0xFF;
        } else {
          arrayOfChar[b2] = (char)(arrayOfChar[b2] ^ k);
          k = ((k >>> 3 | k << 5) ^ arrayOfChar[b2]) & 0xFF;
        } 
      } 
      b[i] = (new String(arrayOfChar)).intern();
    } 
    return b[i];
  }
}


/* Location:              C:\Program Files\BurpSuitePro\burpsuite_pro.jar!\burp\Zz6s.class
 * Java compiler version: 21 (65.0)
 * JD-Core Version:       1.1.3
 */