package burp;

import java.math.BigInteger;

class Zz6t extends ClassLoader {
  static String Zx;
  
  static Object ZA;
  
  private static final String[] a;
  
  private static final String[] b;
  
  static void ZB(Object[] paramArrayOfObject, Object paramObject) throws Throwable {}
  
  static void Zk(Object paramObject) {
    Zzmu.ZF = a(14770, 27250);
    Zzmu.Zy = new BigInteger(a(14771, -13154));
    boolean bool = Zt2e.ZK();
    try {
      try {
        if (Zt5j.ZR.charAt(Math.abs(((BigInteger)Zrva.ZE).intValue() % 32)) > Zel.Zi.charAt(Math.abs(((BigInteger)Zzo5.Zf).intValue() % 32))) {
          try {
            Zr3x.ZA(Class.forName(a(14773, 2066)));
            if (bool)
              Zm3p.ZD(Class.forName(a(14769, 12677))); 
          } catch (Throwable throwable) {
            throw a(null);
          } 
          return;
        } 
      } catch (Throwable throwable) {
        throw a(null);
      } 
      Zm3p.ZD(Class.forName(a(14769, 12677)));
    } catch (Throwable throwable) {}
  }
  
  static boolean ZH(Object[] paramArrayOfObject, Object paramObject) throws Throwable {
    // Byte code:
    //   0: invokestatic ZN : ()Z
    //   3: istore_2
    //   4: getstatic burp/Zxg7.Zy : Ljava/lang/Object;
    //   7: checkcast java/math/BigInteger
    //   10: getstatic burp/Ze69.ZH : Ljava/lang/Object;
    //   13: checkcast java/math/BigInteger
    //   16: invokevirtual subtract : (Ljava/math/BigInteger;)Ljava/math/BigInteger;
    //   19: putstatic burp/Zbzk.ZI : Ljava/lang/Object;
    //   22: sipush #14774
    //   25: sipush #6795
    //   28: invokestatic a : (II)Ljava/lang/String;
    //   31: iconst_1
    //   32: ldc burp/Zmpp
    //   34: invokevirtual getClassLoader : ()Ljava/lang/ClassLoader;
    //   37: invokestatic forName : (Ljava/lang/String;ZLjava/lang/ClassLoader;)Ljava/lang/Class;
    //   40: invokevirtual getDeclaredFields : ()[Ljava/lang/reflect/Field;
    //   43: astore_3
    //   44: aload_3
    //   45: arraylength
    //   46: istore #4
    //   48: iconst_0
    //   49: istore #5
    //   51: iload #5
    //   53: iload #4
    //   55: if_icmpge -> 192
    //   58: aload_3
    //   59: iload #5
    //   61: aaload
    //   62: astore #6
    //   64: aload #6
    //   66: invokevirtual getModifiers : ()I
    //   69: invokestatic isStatic : (I)Z
    //   72: ifne -> 82
    //   75: goto -> 185
    //   78: invokestatic a : (Ljava/lang/Throwable;)Ljava/lang/Throwable;
    //   81: athrow
    //   82: aload #6
    //   84: invokevirtual getType : ()Ljava/lang/Class;
    //   87: astore #7
    //   89: aload #7
    //   91: ifnull -> 172
    //   94: aload #7
    //   96: invokevirtual isPrimitive : ()Z
    //   99: ifne -> 172
    //   102: goto -> 109
    //   105: invokestatic a : (Ljava/lang/Throwable;)Ljava/lang/Throwable;
    //   108: athrow
    //   109: aload #7
    //   111: invokevirtual getPackage : ()Ljava/lang/Package;
    //   114: ifnull -> 172
    //   117: goto -> 124
    //   120: invokestatic a : (Ljava/lang/Throwable;)Ljava/lang/Throwable;
    //   123: athrow
    //   124: aload #7
    //   126: invokevirtual getPackage : ()Ljava/lang/Package;
    //   129: invokevirtual getName : ()Ljava/lang/String;
    //   132: ifnull -> 172
    //   135: goto -> 142
    //   138: invokestatic a : (Ljava/lang/Throwable;)Ljava/lang/Throwable;
    //   141: athrow
    //   142: aload #7
    //   144: invokevirtual getPackage : ()Ljava/lang/Package;
    //   147: invokevirtual getName : ()Ljava/lang/String;
    //   150: sipush #14768
    //   153: sipush #14897
    //   156: invokestatic a : (II)Ljava/lang/String;
    //   159: invokevirtual startsWith : (Ljava/lang/String;)Z
    //   162: ifne -> 172
    //   165: goto -> 172
    //   168: invokestatic a : (Ljava/lang/Throwable;)Ljava/lang/Throwable;
    //   171: athrow
    //   172: aload #6
    //   174: iconst_1
    //   175: invokevirtual setAccessible : (Z)V
    //   178: aload #6
    //   180: aconst_null
    //   181: invokevirtual get : (Ljava/lang/Object;)Ljava/lang/Object;
    //   184: pop
    //   185: iinc #5, 1
    //   188: iload_2
    //   189: ifne -> 51
    //   192: sipush #14772
    //   195: sipush #-32176
    //   198: invokestatic a : (II)Ljava/lang/String;
    //   201: invokestatic forName : (Ljava/lang/String;)Ljava/lang/Class;
    //   204: invokevirtual getDeclaredMethods : ()[Ljava/lang/reflect/Method;
    //   207: astore_3
    //   208: aload_3
    //   209: arraylength
    //   210: istore #4
    //   212: iconst_0
    //   213: istore #5
    //   215: iload #5
    //   217: iload #4
    //   219: if_icmpge -> 351
    //   222: aload_3
    //   223: iload #5
    //   225: aaload
    //   226: astore #6
    //   228: aload #6
    //   230: invokevirtual getParameterTypes : ()[Ljava/lang/Class;
    //   233: pop
    //   234: aload #6
    //   236: invokevirtual getModifiers : ()I
    //   239: invokestatic isStatic : (I)Z
    //   242: ifeq -> 337
    //   245: aload #6
    //   247: invokevirtual getParameterTypes : ()[Ljava/lang/Class;
    //   250: arraylength
    //   251: iconst_2
    //   252: if_icmpne -> 337
    //   255: goto -> 262
    //   258: invokestatic a : (Ljava/lang/Throwable;)Ljava/lang/Throwable;
    //   261: athrow
    //   262: aload #6
    //   264: invokevirtual getReturnType : ()Ljava/lang/Class;
    //   267: getstatic java/lang/Void.TYPE : Ljava/lang/Class;
    //   270: invokevirtual equals : (Ljava/lang/Object;)Z
    //   273: ifeq -> 337
    //   276: goto -> 283
    //   279: invokestatic a : (Ljava/lang/Throwable;)Ljava/lang/Throwable;
    //   282: athrow
    //   283: aload #6
    //   285: iconst_1
    //   286: invokevirtual setAccessible : (Z)V
    //   289: aload #6
    //   291: aconst_null
    //   292: iconst_2
    //   293: anewarray java/lang/Object
    //   296: dup
    //   297: iconst_0
    //   298: aload_0
    //   299: aastore
    //   300: dup
    //   301: iconst_1
    //   302: aload_1
    //   303: ifnonnull -> 321
    //   306: goto -> 313
    //   309: invokestatic a : (Ljava/lang/Throwable;)Ljava/lang/Throwable;
    //   312: athrow
    //   313: aload_1
    //   314: goto -> 328
    //   317: invokestatic a : (Ljava/lang/Throwable;)Ljava/lang/Throwable;
    //   320: athrow
    //   321: aload_1
    //   322: checkcast [B
    //   325: invokevirtual clone : ()Ljava/lang/Object;
    //   328: aastore
    //   329: invokevirtual invoke : (Ljava/lang/Object;[Ljava/lang/Object;)Ljava/lang/Object;
    //   332: pop
    //   333: iload_2
    //   334: ifne -> 351
    //   337: iinc #5, 1
    //   340: iload_2
    //   341: ifne -> 215
    //   344: goto -> 351
    //   347: invokestatic a : (Ljava/lang/Throwable;)Ljava/lang/Throwable;
    //   350: athrow
    //   351: getstatic burp/Zsxo.Za : Ljava/lang/Object;
    //   354: checkcast java/math/BigInteger
    //   357: invokevirtual toByteArray : ()[B
    //   360: astore_3
    //   361: bipush #64
    //   363: newarray byte
    //   365: dup
    //   366: iconst_0
    //   367: bipush #-128
    //   369: bastore
    //   370: dup
    //   371: iconst_1
    //   372: iconst_0
    //   373: bastore
    //   374: dup
    //   375: iconst_2
    //   376: iconst_0
    //   377: bastore
    //   378: dup
    //   379: iconst_3
    //   380: iconst_0
    //   381: bastore
    //   382: dup
    //   383: iconst_4
    //   384: iconst_0
    //   385: bastore
    //   386: dup
    //   387: iconst_5
    //   388: iconst_0
    //   389: bastore
    //   390: dup
    //   391: bipush #6
    //   393: iconst_0
    //   394: bastore
    //   395: dup
    //   396: bipush #7
    //   398: iconst_0
    //   399: bastore
    //   400: dup
    //   401: bipush #8
    //   403: iconst_0
    //   404: bastore
    //   405: dup
    //   406: bipush #9
    //   408: iconst_0
    //   409: bastore
    //   410: dup
    //   411: bipush #10
    //   413: iconst_0
    //   414: bastore
    //   415: dup
    //   416: bipush #11
    //   418: iconst_0
    //   419: bastore
    //   420: dup
    //   421: bipush #12
    //   423: iconst_0
    //   424: bastore
    //   425: dup
    //   426: bipush #13
    //   428: iconst_0
    //   429: bastore
    //   430: dup
    //   431: bipush #14
    //   433: iconst_0
    //   434: bastore
    //   435: dup
    //   436: bipush #15
    //   438: iconst_0
    //   439: bastore
    //   440: dup
    //   441: bipush #16
    //   443: iconst_0
    //   444: bastore
    //   445: dup
    //   446: bipush #17
    //   448: iconst_0
    //   449: bastore
    //   450: dup
    //   451: bipush #18
    //   453: iconst_0
    //   454: bastore
    //   455: dup
    //   456: bipush #19
    //   458: iconst_0
    //   459: bastore
    //   460: dup
    //   461: bipush #20
    //   463: iconst_0
    //   464: bastore
    //   465: dup
    //   466: bipush #21
    //   468: iconst_0
    //   469: bastore
    //   470: dup
    //   471: bipush #22
    //   473: iconst_0
    //   474: bastore
    //   475: dup
    //   476: bipush #23
    //   478: iconst_0
    //   479: bastore
    //   480: dup
    //   481: bipush #24
    //   483: iconst_0
    //   484: bastore
    //   485: dup
    //   486: bipush #25
    //   488: iconst_0
    //   489: bastore
    //   490: dup
    //   491: bipush #26
    //   493: iconst_0
    //   494: bastore
    //   495: dup
    //   496: bipush #27
    //   498: iconst_0
    //   499: bastore
    //   500: dup
    //   501: bipush #28
    //   503: iconst_0
    //   504: bastore
    //   505: dup
    //   506: bipush #29
    //   508: iconst_0
    //   509: bastore
    //   510: dup
    //   511: bipush #30
    //   513: iconst_0
    //   514: bastore
    //   515: dup
    //   516: bipush #31
    //   518: iconst_0
    //   519: bastore
    //   520: dup
    //   521: bipush #32
    //   523: iconst_0
    //   524: bastore
    //   525: dup
    //   526: bipush #33
    //   528: iconst_0
    //   529: bastore
    //   530: dup
    //   531: bipush #34
    //   533: iconst_0
    //   534: bastore
    //   535: dup
    //   536: bipush #35
    //   538: iconst_0
    //   539: bastore
    //   540: dup
    //   541: bipush #36
    //   543: iconst_0
    //   544: bastore
    //   545: dup
    //   546: bipush #37
    //   548: iconst_0
    //   549: bastore
    //   550: dup
    //   551: bipush #38
    //   553: iconst_0
    //   554: bastore
    //   555: dup
    //   556: bipush #39
    //   558: iconst_0
    //   559: bastore
    //   560: dup
    //   561: bipush #40
    //   563: iconst_0
    //   564: bastore
    //   565: dup
    //   566: bipush #41
    //   568: iconst_0
    //   569: bastore
    //   570: dup
    //   571: bipush #42
    //   573: iconst_0
    //   574: bastore
    //   575: dup
    //   576: bipush #43
    //   578: iconst_0
    //   579: bastore
    //   580: dup
    //   581: bipush #44
    //   583: iconst_0
    //   584: bastore
    //   585: dup
    //   586: bipush #45
    //   588: iconst_0
    //   589: bastore
    //   590: dup
    //   591: bipush #46
    //   593: iconst_0
    //   594: bastore
    //   595: dup
    //   596: bipush #47
    //   598: iconst_0
    //   599: bastore
    //   600: dup
    //   601: bipush #48
    //   603: iconst_0
    //   604: bastore
    //   605: dup
    //   606: bipush #49
    //   608: iconst_0
    //   609: bastore
    //   610: dup
    //   611: bipush #50
    //   613: iconst_0
    //   614: bastore
    //   615: dup
    //   616: bipush #51
    //   618: iconst_0
    //   619: bastore
    //   620: dup
    //   621: bipush #52
    //   623: iconst_0
    //   624: bastore
    //   625: dup
    //   626: bipush #53
    //   628: iconst_0
    //   629: bastore
    //   630: dup
    //   631: bipush #54
    //   633: iconst_0
    //   634: bastore
    //   635: dup
    //   636: bipush #55
    //   638: iconst_0
    //   639: bastore
    //   640: dup
    //   641: bipush #56
    //   643: iconst_0
    //   644: bastore
    //   645: dup
    //   646: bipush #57
    //   648: iconst_0
    //   649: bastore
    //   650: dup
    //   651: bipush #58
    //   653: iconst_0
    //   654: bastore
    //   655: dup
    //   656: bipush #59
    //   658: iconst_0
    //   659: bastore
    //   660: dup
    //   661: bipush #60
    //   663: iconst_0
    //   664: bastore
    //   665: dup
    //   666: bipush #61
    //   668: iconst_0
    //   669: bastore
    //   670: dup
    //   671: bipush #62
    //   673: iconst_0
    //   674: bastore
    //   675: dup
    //   676: bipush #63
    //   678: iconst_0
    //   679: bastore
    //   680: astore #5
    //   682: bipush #64
    //   684: newarray int
    //   686: dup
    //   687: iconst_0
    //   688: ldc 1116352408
    //   690: iastore
    //   691: dup
    //   692: iconst_1
    //   693: ldc 1899447441
    //   695: iastore
    //   696: dup
    //   697: iconst_2
    //   698: ldc -1245643825
    //   700: iastore
    //   701: dup
    //   702: iconst_3
    //   703: ldc -373957723
    //   705: iastore
    //   706: dup
    //   707: iconst_4
    //   708: ldc 961987163
    //   710: iastore
    //   711: dup
    //   712: iconst_5
    //   713: ldc 1508970993
    //   715: iastore
    //   716: dup
    //   717: bipush #6
    //   719: ldc -1841331548
    //   721: iastore
    //   722: dup
    //   723: bipush #7
    //   725: ldc -1424204075
    //   727: iastore
    //   728: dup
    //   729: bipush #8
    //   731: ldc -670586216
    //   733: iastore
    //   734: dup
    //   735: bipush #9
    //   737: ldc 310598401
    //   739: iastore
    //   740: dup
    //   741: bipush #10
    //   743: ldc 607225278
    //   745: iastore
    //   746: dup
    //   747: bipush #11
    //   749: ldc 1426881987
    //   751: iastore
    //   752: dup
    //   753: bipush #12
    //   755: ldc 1925078388
    //   757: iastore
    //   758: dup
    //   759: bipush #13
    //   761: ldc -2132889090
    //   763: iastore
    //   764: dup
    //   765: bipush #14
    //   767: ldc -1680079193
    //   769: iastore
    //   770: dup
    //   771: bipush #15
    //   773: ldc -1046744716
    //   775: iastore
    //   776: dup
    //   777: bipush #16
    //   779: ldc -459576895
    //   781: iastore
    //   782: dup
    //   783: bipush #17
    //   785: ldc -272742522
    //   787: iastore
    //   788: dup
    //   789: bipush #18
    //   791: ldc 264347078
    //   793: iastore
    //   794: dup
    //   795: bipush #19
    //   797: ldc 604807628
    //   799: iastore
    //   800: dup
    //   801: bipush #20
    //   803: ldc 770255983
    //   805: iastore
    //   806: dup
    //   807: bipush #21
    //   809: ldc 1249150122
    //   811: iastore
    //   812: dup
    //   813: bipush #22
    //   815: ldc 1555081692
    //   817: iastore
    //   818: dup
    //   819: bipush #23
    //   821: ldc 1996064986
    //   823: iastore
    //   824: dup
    //   825: bipush #24
    //   827: ldc -1740746414
    //   829: iastore
    //   830: dup
    //   831: bipush #25
    //   833: ldc -1473132947
    //   835: iastore
    //   836: dup
    //   837: bipush #26
    //   839: ldc -1341970488
    //   841: iastore
    //   842: dup
    //   843: bipush #27
    //   845: ldc -1084653625
    //   847: iastore
    //   848: dup
    //   849: bipush #28
    //   851: ldc -958395405
    //   853: iastore
    //   854: dup
    //   855: bipush #29
    //   857: ldc -710438585
    //   859: iastore
    //   860: dup
    //   861: bipush #30
    //   863: ldc 113926993
    //   865: iastore
    //   866: dup
    //   867: bipush #31
    //   869: ldc 338241895
    //   871: iastore
    //   872: dup
    //   873: bipush #32
    //   875: ldc 666307205
    //   877: iastore
    //   878: dup
    //   879: bipush #33
    //   881: ldc 773529912
    //   883: iastore
    //   884: dup
    //   885: bipush #34
    //   887: ldc 1294757372
    //   889: iastore
    //   890: dup
    //   891: bipush #35
    //   893: ldc 1396182291
    //   895: iastore
    //   896: dup
    //   897: bipush #36
    //   899: ldc 1695183700
    //   901: iastore
    //   902: dup
    //   903: bipush #37
    //   905: ldc 1986661051
    //   907: iastore
    //   908: dup
    //   909: bipush #38
    //   911: ldc -2117940946
    //   913: iastore
    //   914: dup
    //   915: bipush #39
    //   917: ldc -1838011259
    //   919: iastore
    //   920: dup
    //   921: bipush #40
    //   923: ldc -1564481375
    //   925: iastore
    //   926: dup
    //   927: bipush #41
    //   929: ldc -1474664885
    //   931: iastore
    //   932: dup
    //   933: bipush #42
    //   935: ldc -1035236496
    //   937: iastore
    //   938: dup
    //   939: bipush #43
    //   941: ldc -949202525
    //   943: iastore
    //   944: dup
    //   945: bipush #44
    //   947: ldc -778901479
    //   949: iastore
    //   950: dup
    //   951: bipush #45
    //   953: ldc -694614492
    //   955: iastore
    //   956: dup
    //   957: bipush #46
    //   959: ldc -200395387
    //   961: iastore
    //   962: dup
    //   963: bipush #47
    //   965: ldc 275423344
    //   967: iastore
    //   968: dup
    //   969: bipush #48
    //   971: ldc 430227734
    //   973: iastore
    //   974: dup
    //   975: bipush #49
    //   977: ldc 506948616
    //   979: iastore
    //   980: dup
    //   981: bipush #50
    //   983: ldc 659060556
    //   985: iastore
    //   986: dup
    //   987: bipush #51
    //   989: ldc 883997877
    //   991: iastore
    //   992: dup
    //   993: bipush #52
    //   995: ldc 958139571
    //   997: iastore
    //   998: dup
    //   999: bipush #53
    //   1001: ldc 1322822218
    //   1003: iastore
    //   1004: dup
    //   1005: bipush #54
    //   1007: ldc 1537002063
    //   1009: iastore
    //   1010: dup
    //   1011: bipush #55
    //   1013: ldc 1747873779
    //   1015: iastore
    //   1016: dup
    //   1017: bipush #56
    //   1019: ldc 1955562222
    //   1021: iastore
    //   1022: dup
    //   1023: bipush #57
    //   1025: ldc 2024104815
    //   1027: iastore
    //   1028: dup
    //   1029: bipush #58
    //   1031: ldc -2067236844
    //   1033: iastore
    //   1034: dup
    //   1035: bipush #59
    //   1037: ldc -1933114872
    //   1039: iastore
    //   1040: dup
    //   1041: bipush #60
    //   1043: ldc -1866530822
    //   1045: iastore
    //   1046: dup
    //   1047: bipush #61
    //   1049: ldc -1538233109
    //   1051: iastore
    //   1052: dup
    //   1053: bipush #62
    //   1055: ldc -1090935817
    //   1057: iastore
    //   1058: dup
    //   1059: bipush #63
    //   1061: ldc -965641998
    //   1063: iastore
    //   1064: astore #6
    //   1066: iconst_2
    //   1067: newarray int
    //   1069: dup
    //   1070: iconst_0
    //   1071: iconst_0
    //   1072: iastore
    //   1073: dup
    //   1074: iconst_1
    //   1075: iconst_0
    //   1076: iastore
    //   1077: astore #7
    //   1079: bipush #8
    //   1081: newarray int
    //   1083: dup
    //   1084: iconst_0
    //   1085: ldc 1779033703
    //   1087: iastore
    //   1088: dup
    //   1089: iconst_1
    //   1090: ldc -1150833019
    //   1092: iastore
    //   1093: dup
    //   1094: iconst_2
    //   1095: ldc 1013904242
    //   1097: iastore
    //   1098: dup
    //   1099: iconst_3
    //   1100: ldc -1521486534
    //   1102: iastore
    //   1103: dup
    //   1104: iconst_4
    //   1105: ldc 1359893119
    //   1107: iastore
    //   1108: dup
    //   1109: iconst_5
    //   1110: ldc -1694144372
    //   1112: iastore
    //   1113: dup
    //   1114: bipush #6
    //   1116: ldc 528734635
    //   1118: iastore
    //   1119: dup
    //   1120: bipush #7
    //   1122: ldc 1541459225
    //   1124: iastore
    //   1125: astore #8
    //   1127: bipush #64
    //   1129: newarray byte
    //   1131: astore #9
    //   1133: bipush #64
    //   1135: newarray byte
    //   1137: astore #10
    //   1139: aload_3
    //   1140: arraylength
    //   1141: istore #11
    //   1143: aload #7
    //   1145: iconst_0
    //   1146: iaload
    //   1147: bipush #63
    //   1149: iand
    //   1150: istore #12
    //   1152: aload #7
    //   1154: iconst_0
    //   1155: dup2
    //   1156: iaload
    //   1157: iload #11
    //   1159: iadd
    //   1160: iastore
    //   1161: aload #7
    //   1163: iconst_0
    //   1164: dup2
    //   1165: iaload
    //   1166: iconst_m1
    //   1167: iand
    //   1168: iastore
    //   1169: aload #7
    //   1171: iconst_0
    //   1172: iaload
    //   1173: iload #11
    //   1175: if_icmpge -> 1193
    //   1178: aload #7
    //   1180: iconst_1
    //   1181: dup2
    //   1182: iaload
    //   1183: iconst_1
    //   1184: iadd
    //   1185: iastore
    //   1186: goto -> 1193
    //   1189: invokestatic a : (Ljava/lang/Throwable;)Ljava/lang/Throwable;
    //   1192: athrow
    //   1193: iconst_0
    //   1194: istore #13
    //   1196: iload #11
    //   1198: bipush #64
    //   1200: if_icmplt -> 1809
    //   1203: iconst_0
    //   1204: istore #14
    //   1206: iload #14
    //   1208: bipush #64
    //   1210: if_icmpge -> 1232
    //   1213: aload #10
    //   1215: iload #14
    //   1217: aload_3
    //   1218: iload #13
    //   1220: iload #14
    //   1222: iadd
    //   1223: baload
    //   1224: bastore
    //   1225: iinc #14, 1
    //   1228: iload_2
    //   1229: ifne -> 1206
    //   1232: bipush #64
    //   1234: newarray int
    //   1236: astore #14
    //   1238: bipush #8
    //   1240: newarray int
    //   1242: astore #15
    //   1244: iconst_0
    //   1245: istore #16
    //   1247: iload #16
    //   1249: bipush #8
    //   1251: if_icmpge -> 1271
    //   1254: aload #15
    //   1256: iload #16
    //   1258: aload #8
    //   1260: iload #16
    //   1262: iaload
    //   1263: iastore
    //   1264: iinc #16, 1
    //   1267: iload_2
    //   1268: ifne -> 1247
    //   1271: iconst_0
    //   1272: istore #16
    //   1274: iload #16
    //   1276: bipush #64
    //   1278: if_icmpge -> 1769
    //   1281: iload #16
    //   1283: bipush #16
    //   1285: if_icmpge -> 1366
    //   1288: aload #14
    //   1290: iload #16
    //   1292: aload #10
    //   1294: iconst_4
    //   1295: iload #16
    //   1297: imul
    //   1298: baload
    //   1299: sipush #255
    //   1302: iand
    //   1303: bipush #24
    //   1305: ishl
    //   1306: aload #10
    //   1308: iconst_4
    //   1309: iload #16
    //   1311: imul
    //   1312: iconst_1
    //   1313: iadd
    //   1314: baload
    //   1315: sipush #255
    //   1318: iand
    //   1319: bipush #16
    //   1321: ishl
    //   1322: ior
    //   1323: aload #10
    //   1325: iconst_4
    //   1326: iload #16
    //   1328: imul
    //   1329: iconst_2
    //   1330: iadd
    //   1331: baload
    //   1332: sipush #255
    //   1335: iand
    //   1336: bipush #8
    //   1338: ishl
    //   1339: ior
    //   1340: aload #10
    //   1342: iconst_4
    //   1343: iload #16
    //   1345: imul
    //   1346: iconst_3
    //   1347: iadd
    //   1348: baload
    //   1349: sipush #255
    //   1352: iand
    //   1353: ior
    //   1354: iastore
    //   1355: iload_2
    //   1356: ifne -> 1509
    //   1359: goto -> 1366
    //   1362: invokestatic a : (Ljava/lang/Throwable;)Ljava/lang/Throwable;
    //   1365: athrow
    //   1366: aload #14
    //   1368: iload #16
    //   1370: aload #14
    //   1372: iload #16
    //   1374: iconst_2
    //   1375: isub
    //   1376: iaload
    //   1377: bipush #17
    //   1379: iushr
    //   1380: aload #14
    //   1382: iload #16
    //   1384: iconst_2
    //   1385: isub
    //   1386: iaload
    //   1387: bipush #15
    //   1389: ishl
    //   1390: ior
    //   1391: aload #14
    //   1393: iload #16
    //   1395: iconst_2
    //   1396: isub
    //   1397: iaload
    //   1398: bipush #19
    //   1400: iushr
    //   1401: aload #14
    //   1403: iload #16
    //   1405: iconst_2
    //   1406: isub
    //   1407: iaload
    //   1408: bipush #13
    //   1410: ishl
    //   1411: ior
    //   1412: ixor
    //   1413: aload #14
    //   1415: iload #16
    //   1417: iconst_2
    //   1418: isub
    //   1419: iaload
    //   1420: bipush #10
    //   1422: iushr
    //   1423: ixor
    //   1424: aload #14
    //   1426: iload #16
    //   1428: bipush #7
    //   1430: isub
    //   1431: iaload
    //   1432: iadd
    //   1433: aload #14
    //   1435: iload #16
    //   1437: bipush #15
    //   1439: isub
    //   1440: iaload
    //   1441: bipush #7
    //   1443: iushr
    //   1444: aload #14
    //   1446: iload #16
    //   1448: bipush #15
    //   1450: isub
    //   1451: iaload
    //   1452: bipush #25
    //   1454: ishl
    //   1455: ior
    //   1456: aload #14
    //   1458: iload #16
    //   1460: bipush #15
    //   1462: isub
    //   1463: iaload
    //   1464: bipush #18
    //   1466: iushr
    //   1467: aload #14
    //   1469: iload #16
    //   1471: bipush #15
    //   1473: isub
    //   1474: iaload
    //   1475: bipush #14
    //   1477: ishl
    //   1478: ior
    //   1479: ixor
    //   1480: aload #14
    //   1482: iload #16
    //   1484: bipush #15
    //   1486: isub
    //   1487: iaload
    //   1488: iconst_3
    //   1489: iushr
    //   1490: ixor
    //   1491: iadd
    //   1492: aload #14
    //   1494: iload #16
    //   1496: bipush #16
    //   1498: isub
    //   1499: iaload
    //   1500: iadd
    //   1501: iastore
    //   1502: goto -> 1509
    //   1505: invokestatic a : (Ljava/lang/Throwable;)Ljava/lang/Throwable;
    //   1508: athrow
    //   1509: aload #15
    //   1511: bipush #7
    //   1513: iaload
    //   1514: aload #15
    //   1516: iconst_4
    //   1517: iaload
    //   1518: bipush #6
    //   1520: iushr
    //   1521: aload #15
    //   1523: iconst_4
    //   1524: iaload
    //   1525: bipush #26
    //   1527: ishl
    //   1528: ior
    //   1529: aload #15
    //   1531: iconst_4
    //   1532: iaload
    //   1533: bipush #11
    //   1535: iushr
    //   1536: aload #15
    //   1538: iconst_4
    //   1539: iaload
    //   1540: bipush #21
    //   1542: ishl
    //   1543: ior
    //   1544: ixor
    //   1545: aload #15
    //   1547: iconst_4
    //   1548: iaload
    //   1549: bipush #25
    //   1551: iushr
    //   1552: aload #15
    //   1554: iconst_4
    //   1555: iaload
    //   1556: bipush #7
    //   1558: ishl
    //   1559: ior
    //   1560: ixor
    //   1561: iadd
    //   1562: aload #15
    //   1564: bipush #6
    //   1566: iaload
    //   1567: aload #15
    //   1569: iconst_4
    //   1570: iaload
    //   1571: aload #15
    //   1573: iconst_5
    //   1574: iaload
    //   1575: aload #15
    //   1577: bipush #6
    //   1579: iaload
    //   1580: ixor
    //   1581: iand
    //   1582: ixor
    //   1583: iadd
    //   1584: aload #6
    //   1586: iload #16
    //   1588: iaload
    //   1589: iadd
    //   1590: aload #14
    //   1592: iload #16
    //   1594: iaload
    //   1595: iadd
    //   1596: istore #17
    //   1598: aload #15
    //   1600: iconst_0
    //   1601: iaload
    //   1602: iconst_2
    //   1603: iushr
    //   1604: aload #15
    //   1606: iconst_0
    //   1607: iaload
    //   1608: bipush #30
    //   1610: ishl
    //   1611: ior
    //   1612: aload #15
    //   1614: iconst_0
    //   1615: iaload
    //   1616: bipush #13
    //   1618: iushr
    //   1619: aload #15
    //   1621: iconst_0
    //   1622: iaload
    //   1623: bipush #19
    //   1625: ishl
    //   1626: ior
    //   1627: ixor
    //   1628: aload #15
    //   1630: iconst_0
    //   1631: iaload
    //   1632: bipush #22
    //   1634: iushr
    //   1635: aload #15
    //   1637: iconst_0
    //   1638: iaload
    //   1639: bipush #10
    //   1641: ishl
    //   1642: ior
    //   1643: ixor
    //   1644: aload #15
    //   1646: iconst_0
    //   1647: iaload
    //   1648: aload #15
    //   1650: iconst_1
    //   1651: iaload
    //   1652: iand
    //   1653: aload #15
    //   1655: iconst_2
    //   1656: iaload
    //   1657: aload #15
    //   1659: iconst_0
    //   1660: iaload
    //   1661: aload #15
    //   1663: iconst_1
    //   1664: iaload
    //   1665: ior
    //   1666: iand
    //   1667: ior
    //   1668: iadd
    //   1669: istore #18
    //   1671: aload #15
    //   1673: iconst_3
    //   1674: dup2
    //   1675: iaload
    //   1676: iload #17
    //   1678: iadd
    //   1679: iastore
    //   1680: aload #15
    //   1682: bipush #7
    //   1684: iload #17
    //   1686: iload #18
    //   1688: iadd
    //   1689: iastore
    //   1690: aload #15
    //   1692: bipush #7
    //   1694: iaload
    //   1695: istore #17
    //   1697: aload #15
    //   1699: bipush #7
    //   1701: aload #15
    //   1703: bipush #6
    //   1705: iaload
    //   1706: iastore
    //   1707: aload #15
    //   1709: bipush #6
    //   1711: aload #15
    //   1713: iconst_5
    //   1714: iaload
    //   1715: iastore
    //   1716: aload #15
    //   1718: iconst_5
    //   1719: aload #15
    //   1721: iconst_4
    //   1722: iaload
    //   1723: iastore
    //   1724: aload #15
    //   1726: iconst_4
    //   1727: aload #15
    //   1729: iconst_3
    //   1730: iaload
    //   1731: iastore
    //   1732: aload #15
    //   1734: iconst_3
    //   1735: aload #15
    //   1737: iconst_2
    //   1738: iaload
    //   1739: iastore
    //   1740: aload #15
    //   1742: iconst_2
    //   1743: aload #15
    //   1745: iconst_1
    //   1746: iaload
    //   1747: iastore
    //   1748: aload #15
    //   1750: iconst_1
    //   1751: aload #15
    //   1753: iconst_0
    //   1754: iaload
    //   1755: iastore
    //   1756: aload #15
    //   1758: iconst_0
    //   1759: iload #17
    //   1761: iastore
    //   1762: iinc #16, 1
    //   1765: iload_2
    //   1766: ifne -> 1274
    //   1769: iconst_0
    //   1770: istore #16
    //   1772: iload #16
    //   1774: bipush #8
    //   1776: if_icmpge -> 1799
    //   1779: aload #8
    //   1781: iload #16
    //   1783: dup2
    //   1784: iaload
    //   1785: aload #15
    //   1787: iload #16
    //   1789: iaload
    //   1790: iadd
    //   1791: iastore
    //   1792: iinc #16, 1
    //   1795: iload_2
    //   1796: ifne -> 1772
    //   1799: iinc #13, 64
    //   1802: iinc #11, -64
    //   1805: iload_2
    //   1806: ifne -> 1196
    //   1809: iload #11
    //   1811: ifle -> 1846
    //   1814: iconst_0
    //   1815: istore #14
    //   1817: iload #14
    //   1819: iload #11
    //   1821: if_icmpge -> 1846
    //   1824: aload #9
    //   1826: iload #12
    //   1828: iload #14
    //   1830: iadd
    //   1831: aload_3
    //   1832: iload #13
    //   1834: iload #14
    //   1836: iadd
    //   1837: baload
    //   1838: bastore
    //   1839: iinc #14, 1
    //   1842: iload_2
    //   1843: ifne -> 1817
    //   1846: aload #7
    //   1848: iconst_0
    //   1849: iaload
    //   1850: bipush #29
    //   1852: iushr
    //   1853: aload #7
    //   1855: iconst_1
    //   1856: iaload
    //   1857: iconst_3
    //   1858: ishl
    //   1859: ior
    //   1860: istore #14
    //   1862: aload #7
    //   1864: iconst_0
    //   1865: iaload
    //   1866: iconst_3
    //   1867: ishl
    //   1868: istore #15
    //   1870: aload #7
    //   1872: iconst_0
    //   1873: iaload
    //   1874: bipush #63
    //   1876: iand
    //   1877: istore #16
    //   1879: iload #16
    //   1881: bipush #56
    //   1883: if_icmpge -> 1898
    //   1886: bipush #56
    //   1888: iload #16
    //   1890: isub
    //   1891: goto -> 1903
    //   1894: invokestatic a : (Ljava/lang/Throwable;)Ljava/lang/Throwable;
    //   1897: athrow
    //   1898: bipush #120
    //   1900: iload #16
    //   1902: isub
    //   1903: istore #17
    //   1905: aload #7
    //   1907: iconst_0
    //   1908: iaload
    //   1909: bipush #63
    //   1911: iand
    //   1912: istore #12
    //   1914: bipush #64
    //   1916: iload #12
    //   1918: isub
    //   1919: istore #18
    //   1921: aload #7
    //   1923: iconst_0
    //   1924: dup2
    //   1925: iaload
    //   1926: iload #17
    //   1928: iadd
    //   1929: iastore
    //   1930: aload #7
    //   1932: iconst_0
    //   1933: dup2
    //   1934: iaload
    //   1935: iconst_m1
    //   1936: iand
    //   1937: iastore
    //   1938: aload #7
    //   1940: iconst_0
    //   1941: iaload
    //   1942: iload #17
    //   1944: if_icmpge -> 1962
    //   1947: aload #7
    //   1949: iconst_1
    //   1950: dup2
    //   1951: iaload
    //   1952: iconst_1
    //   1953: iadd
    //   1954: iastore
    //   1955: goto -> 1962
    //   1958: invokestatic a : (Ljava/lang/Throwable;)Ljava/lang/Throwable;
    //   1961: athrow
    //   1962: iconst_0
    //   1963: istore #13
    //   1965: iload #12
    //   1967: ifle -> 2598
    //   1970: iload #17
    //   1972: iload #18
    //   1974: if_icmplt -> 2598
    //   1977: goto -> 1984
    //   1980: invokestatic a : (Ljava/lang/Throwable;)Ljava/lang/Throwable;
    //   1983: athrow
    //   1984: iconst_0
    //   1985: istore #19
    //   1987: iload #19
    //   1989: iload #18
    //   1991: if_icmpge -> 2014
    //   1994: aload #9
    //   1996: iload #12
    //   1998: iload #19
    //   2000: iadd
    //   2001: aload #5
    //   2003: iload #19
    //   2005: baload
    //   2006: bastore
    //   2007: iinc #19, 1
    //   2010: iload_2
    //   2011: ifne -> 1987
    //   2014: bipush #64
    //   2016: newarray int
    //   2018: astore #19
    //   2020: bipush #8
    //   2022: newarray int
    //   2024: astore #20
    //   2026: iconst_0
    //   2027: istore #21
    //   2029: iload #21
    //   2031: bipush #8
    //   2033: if_icmpge -> 2053
    //   2036: aload #20
    //   2038: iload #21
    //   2040: aload #8
    //   2042: iload #21
    //   2044: iaload
    //   2045: iastore
    //   2046: iinc #21, 1
    //   2049: iload_2
    //   2050: ifne -> 2029
    //   2053: iconst_0
    //   2054: istore #21
    //   2056: iload #21
    //   2058: bipush #64
    //   2060: if_icmpge -> 2551
    //   2063: iload #21
    //   2065: bipush #16
    //   2067: if_icmpge -> 2148
    //   2070: aload #19
    //   2072: iload #21
    //   2074: aload #9
    //   2076: iconst_4
    //   2077: iload #21
    //   2079: imul
    //   2080: baload
    //   2081: sipush #255
    //   2084: iand
    //   2085: bipush #24
    //   2087: ishl
    //   2088: aload #9
    //   2090: iconst_4
    //   2091: iload #21
    //   2093: imul
    //   2094: iconst_1
    //   2095: iadd
    //   2096: baload
    //   2097: sipush #255
    //   2100: iand
    //   2101: bipush #16
    //   2103: ishl
    //   2104: ior
    //   2105: aload #9
    //   2107: iconst_4
    //   2108: iload #21
    //   2110: imul
    //   2111: iconst_2
    //   2112: iadd
    //   2113: baload
    //   2114: sipush #255
    //   2117: iand
    //   2118: bipush #8
    //   2120: ishl
    //   2121: ior
    //   2122: aload #9
    //   2124: iconst_4
    //   2125: iload #21
    //   2127: imul
    //   2128: iconst_3
    //   2129: iadd
    //   2130: baload
    //   2131: sipush #255
    //   2134: iand
    //   2135: ior
    //   2136: iastore
    //   2137: iload_2
    //   2138: ifne -> 2291
    //   2141: goto -> 2148
    //   2144: invokestatic a : (Ljava/lang/Throwable;)Ljava/lang/Throwable;
    //   2147: athrow
    //   2148: aload #19
    //   2150: iload #21
    //   2152: aload #19
    //   2154: iload #21
    //   2156: iconst_2
    //   2157: isub
    //   2158: iaload
    //   2159: bipush #17
    //   2161: iushr
    //   2162: aload #19
    //   2164: iload #21
    //   2166: iconst_2
    //   2167: isub
    //   2168: iaload
    //   2169: bipush #15
    //   2171: ishl
    //   2172: ior
    //   2173: aload #19
    //   2175: iload #21
    //   2177: iconst_2
    //   2178: isub
    //   2179: iaload
    //   2180: bipush #19
    //   2182: iushr
    //   2183: aload #19
    //   2185: iload #21
    //   2187: iconst_2
    //   2188: isub
    //   2189: iaload
    //   2190: bipush #13
    //   2192: ishl
    //   2193: ior
    //   2194: ixor
    //   2195: aload #19
    //   2197: iload #21
    //   2199: iconst_2
    //   2200: isub
    //   2201: iaload
    //   2202: bipush #10
    //   2204: iushr
    //   2205: ixor
    //   2206: aload #19
    //   2208: iload #21
    //   2210: bipush #7
    //   2212: isub
    //   2213: iaload
    //   2214: iadd
    //   2215: aload #19
    //   2217: iload #21
    //   2219: bipush #15
    //   2221: isub
    //   2222: iaload
    //   2223: bipush #7
    //   2225: iushr
    //   2226: aload #19
    //   2228: iload #21
    //   2230: bipush #15
    //   2232: isub
    //   2233: iaload
    //   2234: bipush #25
    //   2236: ishl
    //   2237: ior
    //   2238: aload #19
    //   2240: iload #21
    //   2242: bipush #15
    //   2244: isub
    //   2245: iaload
    //   2246: bipush #18
    //   2248: iushr
    //   2249: aload #19
    //   2251: iload #21
    //   2253: bipush #15
    //   2255: isub
    //   2256: iaload
    //   2257: bipush #14
    //   2259: ishl
    //   2260: ior
    //   2261: ixor
    //   2262: aload #19
    //   2264: iload #21
    //   2266: bipush #15
    //   2268: isub
    //   2269: iaload
    //   2270: iconst_3
    //   2271: iushr
    //   2272: ixor
    //   2273: iadd
    //   2274: aload #19
    //   2276: iload #21
    //   2278: bipush #16
    //   2280: isub
    //   2281: iaload
    //   2282: iadd
    //   2283: iastore
    //   2284: goto -> 2291
    //   2287: invokestatic a : (Ljava/lang/Throwable;)Ljava/lang/Throwable;
    //   2290: athrow
    //   2291: aload #20
    //   2293: bipush #7
    //   2295: iaload
    //   2296: aload #20
    //   2298: iconst_4
    //   2299: iaload
    //   2300: bipush #6
    //   2302: iushr
    //   2303: aload #20
    //   2305: iconst_4
    //   2306: iaload
    //   2307: bipush #26
    //   2309: ishl
    //   2310: ior
    //   2311: aload #20
    //   2313: iconst_4
    //   2314: iaload
    //   2315: bipush #11
    //   2317: iushr
    //   2318: aload #20
    //   2320: iconst_4
    //   2321: iaload
    //   2322: bipush #21
    //   2324: ishl
    //   2325: ior
    //   2326: ixor
    //   2327: aload #20
    //   2329: iconst_4
    //   2330: iaload
    //   2331: bipush #25
    //   2333: iushr
    //   2334: aload #20
    //   2336: iconst_4
    //   2337: iaload
    //   2338: bipush #7
    //   2340: ishl
    //   2341: ior
    //   2342: ixor
    //   2343: iadd
    //   2344: aload #20
    //   2346: bipush #6
    //   2348: iaload
    //   2349: aload #20
    //   2351: iconst_4
    //   2352: iaload
    //   2353: aload #20
    //   2355: iconst_5
    //   2356: iaload
    //   2357: aload #20
    //   2359: bipush #6
    //   2361: iaload
    //   2362: ixor
    //   2363: iand
    //   2364: ixor
    //   2365: iadd
    //   2366: aload #6
    //   2368: iload #21
    //   2370: iaload
    //   2371: iadd
    //   2372: aload #19
    //   2374: iload #21
    //   2376: iaload
    //   2377: iadd
    //   2378: istore #22
    //   2380: aload #20
    //   2382: iconst_0
    //   2383: iaload
    //   2384: iconst_2
    //   2385: iushr
    //   2386: aload #20
    //   2388: iconst_0
    //   2389: iaload
    //   2390: bipush #30
    //   2392: ishl
    //   2393: ior
    //   2394: aload #20
    //   2396: iconst_0
    //   2397: iaload
    //   2398: bipush #13
    //   2400: iushr
    //   2401: aload #20
    //   2403: iconst_0
    //   2404: iaload
    //   2405: bipush #19
    //   2407: ishl
    //   2408: ior
    //   2409: ixor
    //   2410: aload #20
    //   2412: iconst_0
    //   2413: iaload
    //   2414: bipush #22
    //   2416: iushr
    //   2417: aload #20
    //   2419: iconst_0
    //   2420: iaload
    //   2421: bipush #10
    //   2423: ishl
    //   2424: ior
    //   2425: ixor
    //   2426: aload #20
    //   2428: iconst_0
    //   2429: iaload
    //   2430: aload #20
    //   2432: iconst_1
    //   2433: iaload
    //   2434: iand
    //   2435: aload #20
    //   2437: iconst_2
    //   2438: iaload
    //   2439: aload #20
    //   2441: iconst_0
    //   2442: iaload
    //   2443: aload #20
    //   2445: iconst_1
    //   2446: iaload
    //   2447: ior
    //   2448: iand
    //   2449: ior
    //   2450: iadd
    //   2451: istore #23
    //   2453: aload #20
    //   2455: iconst_3
    //   2456: dup2
    //   2457: iaload
    //   2458: iload #22
    //   2460: iadd
    //   2461: iastore
    //   2462: aload #20
    //   2464: bipush #7
    //   2466: iload #22
    //   2468: iload #23
    //   2470: iadd
    //   2471: iastore
    //   2472: aload #20
    //   2474: bipush #7
    //   2476: iaload
    //   2477: istore #22
    //   2479: aload #20
    //   2481: bipush #7
    //   2483: aload #20
    //   2485: bipush #6
    //   2487: iaload
    //   2488: iastore
    //   2489: aload #20
    //   2491: bipush #6
    //   2493: aload #20
    //   2495: iconst_5
    //   2496: iaload
    //   2497: iastore
    //   2498: aload #20
    //   2500: iconst_5
    //   2501: aload #20
    //   2503: iconst_4
    //   2504: iaload
    //   2505: iastore
    //   2506: aload #20
    //   2508: iconst_4
    //   2509: aload #20
    //   2511: iconst_3
    //   2512: iaload
    //   2513: iastore
    //   2514: aload #20
    //   2516: iconst_3
    //   2517: aload #20
    //   2519: iconst_2
    //   2520: iaload
    //   2521: iastore
    //   2522: aload #20
    //   2524: iconst_2
    //   2525: aload #20
    //   2527: iconst_1
    //   2528: iaload
    //   2529: iastore
    //   2530: aload #20
    //   2532: iconst_1
    //   2533: aload #20
    //   2535: iconst_0
    //   2536: iaload
    //   2537: iastore
    //   2538: aload #20
    //   2540: iconst_0
    //   2541: iload #22
    //   2543: iastore
    //   2544: iinc #21, 1
    //   2547: iload_2
    //   2548: ifne -> 2056
    //   2551: iconst_0
    //   2552: istore #21
    //   2554: iload #21
    //   2556: bipush #8
    //   2558: if_icmpge -> 2581
    //   2561: aload #8
    //   2563: iload #21
    //   2565: dup2
    //   2566: iaload
    //   2567: aload #20
    //   2569: iload #21
    //   2571: iaload
    //   2572: iadd
    //   2573: iastore
    //   2574: iinc #21, 1
    //   2577: iload_2
    //   2578: ifne -> 2554
    //   2581: iload #13
    //   2583: iload #18
    //   2585: iadd
    //   2586: istore #13
    //   2588: iload #17
    //   2590: iload #18
    //   2592: isub
    //   2593: istore #17
    //   2595: iconst_0
    //   2596: istore #12
    //   2598: iload #17
    //   2600: bipush #64
    //   2602: if_icmplt -> 3212
    //   2605: iconst_0
    //   2606: istore #19
    //   2608: iload #19
    //   2610: bipush #64
    //   2612: if_icmpge -> 2635
    //   2615: aload #10
    //   2617: iload #19
    //   2619: aload #5
    //   2621: iload #13
    //   2623: iload #19
    //   2625: iadd
    //   2626: baload
    //   2627: bastore
    //   2628: iinc #19, 1
    //   2631: iload_2
    //   2632: ifne -> 2608
    //   2635: bipush #64
    //   2637: newarray int
    //   2639: astore #19
    //   2641: bipush #8
    //   2643: newarray int
    //   2645: astore #20
    //   2647: iconst_0
    //   2648: istore #21
    //   2650: iload #21
    //   2652: bipush #8
    //   2654: if_icmpge -> 2674
    //   2657: aload #20
    //   2659: iload #21
    //   2661: aload #8
    //   2663: iload #21
    //   2665: iaload
    //   2666: iastore
    //   2667: iinc #21, 1
    //   2670: iload_2
    //   2671: ifne -> 2650
    //   2674: iconst_0
    //   2675: istore #21
    //   2677: iload #21
    //   2679: bipush #64
    //   2681: if_icmpge -> 3172
    //   2684: iload #21
    //   2686: bipush #16
    //   2688: if_icmpge -> 2769
    //   2691: aload #19
    //   2693: iload #21
    //   2695: aload #10
    //   2697: iconst_4
    //   2698: iload #21
    //   2700: imul
    //   2701: baload
    //   2702: sipush #255
    //   2705: iand
    //   2706: bipush #24
    //   2708: ishl
    //   2709: aload #10
    //   2711: iconst_4
    //   2712: iload #21
    //   2714: imul
    //   2715: iconst_1
    //   2716: iadd
    //   2717: baload
    //   2718: sipush #255
    //   2721: iand
    //   2722: bipush #16
    //   2724: ishl
    //   2725: ior
    //   2726: aload #10
    //   2728: iconst_4
    //   2729: iload #21
    //   2731: imul
    //   2732: iconst_2
    //   2733: iadd
    //   2734: baload
    //   2735: sipush #255
    //   2738: iand
    //   2739: bipush #8
    //   2741: ishl
    //   2742: ior
    //   2743: aload #10
    //   2745: iconst_4
    //   2746: iload #21
    //   2748: imul
    //   2749: iconst_3
    //   2750: iadd
    //   2751: baload
    //   2752: sipush #255
    //   2755: iand
    //   2756: ior
    //   2757: iastore
    //   2758: iload_2
    //   2759: ifne -> 2912
    //   2762: goto -> 2769
    //   2765: invokestatic a : (Ljava/lang/Throwable;)Ljava/lang/Throwable;
    //   2768: athrow
    //   2769: aload #19
    //   2771: iload #21
    //   2773: aload #19
    //   2775: iload #21
    //   2777: iconst_2
    //   2778: isub
    //   2779: iaload
    //   2780: bipush #17
    //   2782: iushr
    //   2783: aload #19
    //   2785: iload #21
    //   2787: iconst_2
    //   2788: isub
    //   2789: iaload
    //   2790: bipush #15
    //   2792: ishl
    //   2793: ior
    //   2794: aload #19
    //   2796: iload #21
    //   2798: iconst_2
    //   2799: isub
    //   2800: iaload
    //   2801: bipush #19
    //   2803: iushr
    //   2804: aload #19
    //   2806: iload #21
    //   2808: iconst_2
    //   2809: isub
    //   2810: iaload
    //   2811: bipush #13
    //   2813: ishl
    //   2814: ior
    //   2815: ixor
    //   2816: aload #19
    //   2818: iload #21
    //   2820: iconst_2
    //   2821: isub
    //   2822: iaload
    //   2823: bipush #10
    //   2825: iushr
    //   2826: ixor
    //   2827: aload #19
    //   2829: iload #21
    //   2831: bipush #7
    //   2833: isub
    //   2834: iaload
    //   2835: iadd
    //   2836: aload #19
    //   2838: iload #21
    //   2840: bipush #15
    //   2842: isub
    //   2843: iaload
    //   2844: bipush #7
    //   2846: iushr
    //   2847: aload #19
    //   2849: iload #21
    //   2851: bipush #15
    //   2853: isub
    //   2854: iaload
    //   2855: bipush #25
    //   2857: ishl
    //   2858: ior
    //   2859: aload #19
    //   2861: iload #21
    //   2863: bipush #15
    //   2865: isub
    //   2866: iaload
    //   2867: bipush #18
    //   2869: iushr
    //   2870: aload #19
    //   2872: iload #21
    //   2874: bipush #15
    //   2876: isub
    //   2877: iaload
    //   2878: bipush #14
    //   2880: ishl
    //   2881: ior
    //   2882: ixor
    //   2883: aload #19
    //   2885: iload #21
    //   2887: bipush #15
    //   2889: isub
    //   2890: iaload
    //   2891: iconst_3
    //   2892: iushr
    //   2893: ixor
    //   2894: iadd
    //   2895: aload #19
    //   2897: iload #21
    //   2899: bipush #16
    //   2901: isub
    //   2902: iaload
    //   2903: iadd
    //   2904: iastore
    //   2905: goto -> 2912
    //   2908: invokestatic a : (Ljava/lang/Throwable;)Ljava/lang/Throwable;
    //   2911: athrow
    //   2912: aload #20
    //   2914: bipush #7
    //   2916: iaload
    //   2917: aload #20
    //   2919: iconst_4
    //   2920: iaload
    //   2921: bipush #6
    //   2923: iushr
    //   2924: aload #20
    //   2926: iconst_4
    //   2927: iaload
    //   2928: bipush #26
    //   2930: ishl
    //   2931: ior
    //   2932: aload #20
    //   2934: iconst_4
    //   2935: iaload
    //   2936: bipush #11
    //   2938: iushr
    //   2939: aload #20
    //   2941: iconst_4
    //   2942: iaload
    //   2943: bipush #21
    //   2945: ishl
    //   2946: ior
    //   2947: ixor
    //   2948: aload #20
    //   2950: iconst_4
    //   2951: iaload
    //   2952: bipush #25
    //   2954: iushr
    //   2955: aload #20
    //   2957: iconst_4
    //   2958: iaload
    //   2959: bipush #7
    //   2961: ishl
    //   2962: ior
    //   2963: ixor
    //   2964: iadd
    //   2965: aload #20
    //   2967: bipush #6
    //   2969: iaload
    //   2970: aload #20
    //   2972: iconst_4
    //   2973: iaload
    //   2974: aload #20
    //   2976: iconst_5
    //   2977: iaload
    //   2978: aload #20
    //   2980: bipush #6
    //   2982: iaload
    //   2983: ixor
    //   2984: iand
    //   2985: ixor
    //   2986: iadd
    //   2987: aload #6
    //   2989: iload #21
    //   2991: iaload
    //   2992: iadd
    //   2993: aload #19
    //   2995: iload #21
    //   2997: iaload
    //   2998: iadd
    //   2999: istore #22
    //   3001: aload #20
    //   3003: iconst_0
    //   3004: iaload
    //   3005: iconst_2
    //   3006: iushr
    //   3007: aload #20
    //   3009: iconst_0
    //   3010: iaload
    //   3011: bipush #30
    //   3013: ishl
    //   3014: ior
    //   3015: aload #20
    //   3017: iconst_0
    //   3018: iaload
    //   3019: bipush #13
    //   3021: iushr
    //   3022: aload #20
    //   3024: iconst_0
    //   3025: iaload
    //   3026: bipush #19
    //   3028: ishl
    //   3029: ior
    //   3030: ixor
    //   3031: aload #20
    //   3033: iconst_0
    //   3034: iaload
    //   3035: bipush #22
    //   3037: iushr
    //   3038: aload #20
    //   3040: iconst_0
    //   3041: iaload
    //   3042: bipush #10
    //   3044: ishl
    //   3045: ior
    //   3046: ixor
    //   3047: aload #20
    //   3049: iconst_0
    //   3050: iaload
    //   3051: aload #20
    //   3053: iconst_1
    //   3054: iaload
    //   3055: iand
    //   3056: aload #20
    //   3058: iconst_2
    //   3059: iaload
    //   3060: aload #20
    //   3062: iconst_0
    //   3063: iaload
    //   3064: aload #20
    //   3066: iconst_1
    //   3067: iaload
    //   3068: ior
    //   3069: iand
    //   3070: ior
    //   3071: iadd
    //   3072: istore #23
    //   3074: aload #20
    //   3076: iconst_3
    //   3077: dup2
    //   3078: iaload
    //   3079: iload #22
    //   3081: iadd
    //   3082: iastore
    //   3083: aload #20
    //   3085: bipush #7
    //   3087: iload #22
    //   3089: iload #23
    //   3091: iadd
    //   3092: iastore
    //   3093: aload #20
    //   3095: bipush #7
    //   3097: iaload
    //   3098: istore #22
    //   3100: aload #20
    //   3102: bipush #7
    //   3104: aload #20
    //   3106: bipush #6
    //   3108: iaload
    //   3109: iastore
    //   3110: aload #20
    //   3112: bipush #6
    //   3114: aload #20
    //   3116: iconst_5
    //   3117: iaload
    //   3118: iastore
    //   3119: aload #20
    //   3121: iconst_5
    //   3122: aload #20
    //   3124: iconst_4
    //   3125: iaload
    //   3126: iastore
    //   3127: aload #20
    //   3129: iconst_4
    //   3130: aload #20
    //   3132: iconst_3
    //   3133: iaload
    //   3134: iastore
    //   3135: aload #20
    //   3137: iconst_3
    //   3138: aload #20
    //   3140: iconst_2
    //   3141: iaload
    //   3142: iastore
    //   3143: aload #20
    //   3145: iconst_2
    //   3146: aload #20
    //   3148: iconst_1
    //   3149: iaload
    //   3150: iastore
    //   3151: aload #20
    //   3153: iconst_1
    //   3154: aload #20
    //   3156: iconst_0
    //   3157: iaload
    //   3158: iastore
    //   3159: aload #20
    //   3161: iconst_0
    //   3162: iload #22
    //   3164: iastore
    //   3165: iinc #21, 1
    //   3168: iload_2
    //   3169: ifne -> 2677
    //   3172: iconst_0
    //   3173: istore #21
    //   3175: iload #21
    //   3177: bipush #8
    //   3179: if_icmpge -> 3202
    //   3182: aload #8
    //   3184: iload #21
    //   3186: dup2
    //   3187: iaload
    //   3188: aload #20
    //   3190: iload #21
    //   3192: iaload
    //   3193: iadd
    //   3194: iastore
    //   3195: iinc #21, 1
    //   3198: iload_2
    //   3199: ifne -> 3175
    //   3202: iinc #13, 64
    //   3205: iinc #17, -64
    //   3208: iload_2
    //   3209: ifne -> 2598
    //   3212: iload #17
    //   3214: ifle -> 3250
    //   3217: iconst_0
    //   3218: istore #19
    //   3220: iload #19
    //   3222: iload #17
    //   3224: if_icmpge -> 3250
    //   3227: aload #9
    //   3229: iload #12
    //   3231: iload #19
    //   3233: iadd
    //   3234: aload #5
    //   3236: iload #13
    //   3238: iload #19
    //   3240: iadd
    //   3241: baload
    //   3242: bastore
    //   3243: iinc #19, 1
    //   3246: iload_2
    //   3247: ifne -> 3220
    //   3250: bipush #8
    //   3252: newarray byte
    //   3254: astore #19
    //   3256: aload #19
    //   3258: iconst_0
    //   3259: iload #14
    //   3261: bipush #24
    //   3263: iushr
    //   3264: i2b
    //   3265: bastore
    //   3266: aload #19
    //   3268: iconst_1
    //   3269: iload #14
    //   3271: bipush #16
    //   3273: iushr
    //   3274: i2b
    //   3275: bastore
    //   3276: aload #19
    //   3278: iconst_2
    //   3279: iload #14
    //   3281: bipush #8
    //   3283: iushr
    //   3284: i2b
    //   3285: bastore
    //   3286: aload #19
    //   3288: iconst_3
    //   3289: iload #14
    //   3291: i2b
    //   3292: bastore
    //   3293: aload #19
    //   3295: iconst_4
    //   3296: iload #15
    //   3298: bipush #24
    //   3300: iushr
    //   3301: i2b
    //   3302: bastore
    //   3303: aload #19
    //   3305: iconst_5
    //   3306: iload #15
    //   3308: bipush #16
    //   3310: iushr
    //   3311: i2b
    //   3312: bastore
    //   3313: aload #19
    //   3315: bipush #6
    //   3317: iload #15
    //   3319: bipush #8
    //   3321: iushr
    //   3322: i2b
    //   3323: bastore
    //   3324: aload #19
    //   3326: bipush #7
    //   3328: iload #15
    //   3330: i2b
    //   3331: bastore
    //   3332: bipush #8
    //   3334: istore #11
    //   3336: aload #7
    //   3338: iconst_0
    //   3339: iaload
    //   3340: bipush #63
    //   3342: iand
    //   3343: istore #12
    //   3345: bipush #64
    //   3347: iload #12
    //   3349: isub
    //   3350: istore #18
    //   3352: aload #7
    //   3354: iconst_0
    //   3355: dup2
    //   3356: iaload
    //   3357: iload #11
    //   3359: iadd
    //   3360: iastore
    //   3361: aload #7
    //   3363: iconst_0
    //   3364: dup2
    //   3365: iaload
    //   3366: iconst_m1
    //   3367: iand
    //   3368: iastore
    //   3369: aload #7
    //   3371: iconst_0
    //   3372: iaload
    //   3373: iload #11
    //   3375: if_icmpge -> 3393
    //   3378: aload #7
    //   3380: iconst_1
    //   3381: dup2
    //   3382: iaload
    //   3383: iconst_1
    //   3384: iadd
    //   3385: iastore
    //   3386: goto -> 3393
    //   3389: invokestatic a : (Ljava/lang/Throwable;)Ljava/lang/Throwable;
    //   3392: athrow
    //   3393: iload #12
    //   3395: ifle -> 4009
    //   3398: iload #11
    //   3400: iload #18
    //   3402: if_icmplt -> 4009
    //   3405: goto -> 3412
    //   3408: invokestatic a : (Ljava/lang/Throwable;)Ljava/lang/Throwable;
    //   3411: athrow
    //   3412: iconst_0
    //   3413: istore #20
    //   3415: iload #20
    //   3417: iload #18
    //   3419: if_icmpge -> 3442
    //   3422: aload #9
    //   3424: iload #12
    //   3426: iload #20
    //   3428: iadd
    //   3429: aload #19
    //   3431: iload #20
    //   3433: baload
    //   3434: bastore
    //   3435: iinc #20, 1
    //   3438: iload_2
    //   3439: ifne -> 3415
    //   3442: bipush #64
    //   3444: newarray int
    //   3446: astore #20
    //   3448: bipush #8
    //   3450: newarray int
    //   3452: astore #21
    //   3454: iconst_0
    //   3455: istore #22
    //   3457: iload #22
    //   3459: bipush #8
    //   3461: if_icmpge -> 3481
    //   3464: aload #21
    //   3466: iload #22
    //   3468: aload #8
    //   3470: iload #22
    //   3472: iaload
    //   3473: iastore
    //   3474: iinc #22, 1
    //   3477: iload_2
    //   3478: ifne -> 3457
    //   3481: iconst_0
    //   3482: istore #22
    //   3484: iload #22
    //   3486: bipush #64
    //   3488: if_icmpge -> 3979
    //   3491: iload #22
    //   3493: bipush #16
    //   3495: if_icmpge -> 3576
    //   3498: aload #20
    //   3500: iload #22
    //   3502: aload #9
    //   3504: iconst_4
    //   3505: iload #22
    //   3507: imul
    //   3508: baload
    //   3509: sipush #255
    //   3512: iand
    //   3513: bipush #24
    //   3515: ishl
    //   3516: aload #9
    //   3518: iconst_4
    //   3519: iload #22
    //   3521: imul
    //   3522: iconst_1
    //   3523: iadd
    //   3524: baload
    //   3525: sipush #255
    //   3528: iand
    //   3529: bipush #16
    //   3531: ishl
    //   3532: ior
    //   3533: aload #9
    //   3535: iconst_4
    //   3536: iload #22
    //   3538: imul
    //   3539: iconst_2
    //   3540: iadd
    //   3541: baload
    //   3542: sipush #255
    //   3545: iand
    //   3546: bipush #8
    //   3548: ishl
    //   3549: ior
    //   3550: aload #9
    //   3552: iconst_4
    //   3553: iload #22
    //   3555: imul
    //   3556: iconst_3
    //   3557: iadd
    //   3558: baload
    //   3559: sipush #255
    //   3562: iand
    //   3563: ior
    //   3564: iastore
    //   3565: iload_2
    //   3566: ifne -> 3719
    //   3569: goto -> 3576
    //   3572: invokestatic a : (Ljava/lang/Throwable;)Ljava/lang/Throwable;
    //   3575: athrow
    //   3576: aload #20
    //   3578: iload #22
    //   3580: aload #20
    //   3582: iload #22
    //   3584: iconst_2
    //   3585: isub
    //   3586: iaload
    //   3587: bipush #17
    //   3589: iushr
    //   3590: aload #20
    //   3592: iload #22
    //   3594: iconst_2
    //   3595: isub
    //   3596: iaload
    //   3597: bipush #15
    //   3599: ishl
    //   3600: ior
    //   3601: aload #20
    //   3603: iload #22
    //   3605: iconst_2
    //   3606: isub
    //   3607: iaload
    //   3608: bipush #19
    //   3610: iushr
    //   3611: aload #20
    //   3613: iload #22
    //   3615: iconst_2
    //   3616: isub
    //   3617: iaload
    //   3618: bipush #13
    //   3620: ishl
    //   3621: ior
    //   3622: ixor
    //   3623: aload #20
    //   3625: iload #22
    //   3627: iconst_2
    //   3628: isub
    //   3629: iaload
    //   3630: bipush #10
    //   3632: iushr
    //   3633: ixor
    //   3634: aload #20
    //   3636: iload #22
    //   3638: bipush #7
    //   3640: isub
    //   3641: iaload
    //   3642: iadd
    //   3643: aload #20
    //   3645: iload #22
    //   3647: bipush #15
    //   3649: isub
    //   3650: iaload
    //   3651: bipush #7
    //   3653: iushr
    //   3654: aload #20
    //   3656: iload #22
    //   3658: bipush #15
    //   3660: isub
    //   3661: iaload
    //   3662: bipush #25
    //   3664: ishl
    //   3665: ior
    //   3666: aload #20
    //   3668: iload #22
    //   3670: bipush #15
    //   3672: isub
    //   3673: iaload
    //   3674: bipush #18
    //   3676: iushr
    //   3677: aload #20
    //   3679: iload #22
    //   3681: bipush #15
    //   3683: isub
    //   3684: iaload
    //   3685: bipush #14
    //   3687: ishl
    //   3688: ior
    //   3689: ixor
    //   3690: aload #20
    //   3692: iload #22
    //   3694: bipush #15
    //   3696: isub
    //   3697: iaload
    //   3698: iconst_3
    //   3699: iushr
    //   3700: ixor
    //   3701: iadd
    //   3702: aload #20
    //   3704: iload #22
    //   3706: bipush #16
    //   3708: isub
    //   3709: iaload
    //   3710: iadd
    //   3711: iastore
    //   3712: goto -> 3719
    //   3715: invokestatic a : (Ljava/lang/Throwable;)Ljava/lang/Throwable;
    //   3718: athrow
    //   3719: aload #21
    //   3721: bipush #7
    //   3723: iaload
    //   3724: aload #21
    //   3726: iconst_4
    //   3727: iaload
    //   3728: bipush #6
    //   3730: iushr
    //   3731: aload #21
    //   3733: iconst_4
    //   3734: iaload
    //   3735: bipush #26
    //   3737: ishl
    //   3738: ior
    //   3739: aload #21
    //   3741: iconst_4
    //   3742: iaload
    //   3743: bipush #11
    //   3745: iushr
    //   3746: aload #21
    //   3748: iconst_4
    //   3749: iaload
    //   3750: bipush #21
    //   3752: ishl
    //   3753: ior
    //   3754: ixor
    //   3755: aload #21
    //   3757: iconst_4
    //   3758: iaload
    //   3759: bipush #25
    //   3761: iushr
    //   3762: aload #21
    //   3764: iconst_4
    //   3765: iaload
    //   3766: bipush #7
    //   3768: ishl
    //   3769: ior
    //   3770: ixor
    //   3771: iadd
    //   3772: aload #21
    //   3774: bipush #6
    //   3776: iaload
    //   3777: aload #21
    //   3779: iconst_4
    //   3780: iaload
    //   3781: aload #21
    //   3783: iconst_5
    //   3784: iaload
    //   3785: aload #21
    //   3787: bipush #6
    //   3789: iaload
    //   3790: ixor
    //   3791: iand
    //   3792: ixor
    //   3793: iadd
    //   3794: aload #6
    //   3796: iload #22
    //   3798: iaload
    //   3799: iadd
    //   3800: aload #20
    //   3802: iload #22
    //   3804: iaload
    //   3805: iadd
    //   3806: istore #23
    //   3808: aload #21
    //   3810: iconst_0
    //   3811: iaload
    //   3812: iconst_2
    //   3813: iushr
    //   3814: aload #21
    //   3816: iconst_0
    //   3817: iaload
    //   3818: bipush #30
    //   3820: ishl
    //   3821: ior
    //   3822: aload #21
    //   3824: iconst_0
    //   3825: iaload
    //   3826: bipush #13
    //   3828: iushr
    //   3829: aload #21
    //   3831: iconst_0
    //   3832: iaload
    //   3833: bipush #19
    //   3835: ishl
    //   3836: ior
    //   3837: ixor
    //   3838: aload #21
    //   3840: iconst_0
    //   3841: iaload
    //   3842: bipush #22
    //   3844: iushr
    //   3845: aload #21
    //   3847: iconst_0
    //   3848: iaload
    //   3849: bipush #10
    //   3851: ishl
    //   3852: ior
    //   3853: ixor
    //   3854: aload #21
    //   3856: iconst_0
    //   3857: iaload
    //   3858: aload #21
    //   3860: iconst_1
    //   3861: iaload
    //   3862: iand
    //   3863: aload #21
    //   3865: iconst_2
    //   3866: iaload
    //   3867: aload #21
    //   3869: iconst_0
    //   3870: iaload
    //   3871: aload #21
    //   3873: iconst_1
    //   3874: iaload
    //   3875: ior
    //   3876: iand
    //   3877: ior
    //   3878: iadd
    //   3879: istore #24
    //   3881: aload #21
    //   3883: iconst_3
    //   3884: dup2
    //   3885: iaload
    //   3886: iload #23
    //   3888: iadd
    //   3889: iastore
    //   3890: aload #21
    //   3892: bipush #7
    //   3894: iload #23
    //   3896: iload #24
    //   3898: iadd
    //   3899: iastore
    //   3900: aload #21
    //   3902: bipush #7
    //   3904: iaload
    //   3905: istore #23
    //   3907: aload #21
    //   3909: bipush #7
    //   3911: aload #21
    //   3913: bipush #6
    //   3915: iaload
    //   3916: iastore
    //   3917: aload #21
    //   3919: bipush #6
    //   3921: aload #21
    //   3923: iconst_5
    //   3924: iaload
    //   3925: iastore
    //   3926: aload #21
    //   3928: iconst_5
    //   3929: aload #21
    //   3931: iconst_4
    //   3932: iaload
    //   3933: iastore
    //   3934: aload #21
    //   3936: iconst_4
    //   3937: aload #21
    //   3939: iconst_3
    //   3940: iaload
    //   3941: iastore
    //   3942: aload #21
    //   3944: iconst_3
    //   3945: aload #21
    //   3947: iconst_2
    //   3948: iaload
    //   3949: iastore
    //   3950: aload #21
    //   3952: iconst_2
    //   3953: aload #21
    //   3955: iconst_1
    //   3956: iaload
    //   3957: iastore
    //   3958: aload #21
    //   3960: iconst_1
    //   3961: aload #21
    //   3963: iconst_0
    //   3964: iaload
    //   3965: iastore
    //   3966: aload #21
    //   3968: iconst_0
    //   3969: iload #23
    //   3971: iastore
    //   3972: iinc #22, 1
    //   3975: iload_2
    //   3976: ifne -> 3484
    //   3979: iconst_0
    //   3980: istore #22
    //   3982: iload #22
    //   3984: bipush #8
    //   3986: if_icmpge -> 4009
    //   3989: aload #8
    //   3991: iload #22
    //   3993: dup2
    //   3994: iaload
    //   3995: aload #21
    //   3997: iload #22
    //   3999: iaload
    //   4000: iadd
    //   4001: iastore
    //   4002: iinc #22, 1
    //   4005: iload_2
    //   4006: ifne -> 3982
    //   4009: bipush #32
    //   4011: newarray byte
    //   4013: astore #4
    //   4015: aload #4
    //   4017: iconst_0
    //   4018: aload #8
    //   4020: iconst_0
    //   4021: iaload
    //   4022: bipush #24
    //   4024: iushr
    //   4025: i2b
    //   4026: bastore
    //   4027: aload #4
    //   4029: iconst_1
    //   4030: aload #8
    //   4032: iconst_0
    //   4033: iaload
    //   4034: bipush #16
    //   4036: iushr
    //   4037: i2b
    //   4038: bastore
    //   4039: aload #4
    //   4041: iconst_2
    //   4042: aload #8
    //   4044: iconst_0
    //   4045: iaload
    //   4046: bipush #8
    //   4048: iushr
    //   4049: i2b
    //   4050: bastore
    //   4051: aload #4
    //   4053: iconst_3
    //   4054: aload #8
    //   4056: iconst_0
    //   4057: iaload
    //   4058: i2b
    //   4059: bastore
    //   4060: aload #4
    //   4062: iconst_4
    //   4063: aload #8
    //   4065: iconst_1
    //   4066: iaload
    //   4067: bipush #24
    //   4069: iushr
    //   4070: i2b
    //   4071: bastore
    //   4072: aload #4
    //   4074: iconst_5
    //   4075: aload #8
    //   4077: iconst_1
    //   4078: iaload
    //   4079: bipush #16
    //   4081: iushr
    //   4082: i2b
    //   4083: bastore
    //   4084: aload #4
    //   4086: bipush #6
    //   4088: aload #8
    //   4090: iconst_1
    //   4091: iaload
    //   4092: bipush #8
    //   4094: iushr
    //   4095: i2b
    //   4096: bastore
    //   4097: aload #4
    //   4099: bipush #7
    //   4101: aload #8
    //   4103: iconst_1
    //   4104: iaload
    //   4105: i2b
    //   4106: bastore
    //   4107: aload #4
    //   4109: bipush #8
    //   4111: aload #8
    //   4113: iconst_2
    //   4114: iaload
    //   4115: bipush #24
    //   4117: iushr
    //   4118: i2b
    //   4119: bastore
    //   4120: aload #4
    //   4122: bipush #9
    //   4124: aload #8
    //   4126: iconst_2
    //   4127: iaload
    //   4128: bipush #16
    //   4130: iushr
    //   4131: i2b
    //   4132: bastore
    //   4133: aload #4
    //   4135: bipush #10
    //   4137: aload #8
    //   4139: iconst_2
    //   4140: iaload
    //   4141: bipush #8
    //   4143: iushr
    //   4144: i2b
    //   4145: bastore
    //   4146: aload #4
    //   4148: bipush #11
    //   4150: aload #8
    //   4152: iconst_2
    //   4153: iaload
    //   4154: i2b
    //   4155: bastore
    //   4156: aload #4
    //   4158: bipush #12
    //   4160: aload #8
    //   4162: iconst_3
    //   4163: iaload
    //   4164: bipush #24
    //   4166: iushr
    //   4167: i2b
    //   4168: bastore
    //   4169: aload #4
    //   4171: bipush #13
    //   4173: aload #8
    //   4175: iconst_3
    //   4176: iaload
    //   4177: bipush #16
    //   4179: iushr
    //   4180: i2b
    //   4181: bastore
    //   4182: aload #4
    //   4184: bipush #14
    //   4186: aload #8
    //   4188: iconst_3
    //   4189: iaload
    //   4190: bipush #8
    //   4192: iushr
    //   4193: i2b
    //   4194: bastore
    //   4195: aload #4
    //   4197: bipush #15
    //   4199: aload #8
    //   4201: iconst_3
    //   4202: iaload
    //   4203: i2b
    //   4204: bastore
    //   4205: aload #4
    //   4207: bipush #16
    //   4209: aload #8
    //   4211: iconst_4
    //   4212: iaload
    //   4213: bipush #24
    //   4215: iushr
    //   4216: i2b
    //   4217: bastore
    //   4218: aload #4
    //   4220: bipush #17
    //   4222: aload #8
    //   4224: iconst_4
    //   4225: iaload
    //   4226: bipush #16
    //   4228: iushr
    //   4229: i2b
    //   4230: bastore
    //   4231: aload #4
    //   4233: bipush #18
    //   4235: aload #8
    //   4237: iconst_4
    //   4238: iaload
    //   4239: bipush #8
    //   4241: iushr
    //   4242: i2b
    //   4243: bastore
    //   4244: aload #4
    //   4246: bipush #19
    //   4248: aload #8
    //   4250: iconst_4
    //   4251: iaload
    //   4252: i2b
    //   4253: bastore
    //   4254: aload #4
    //   4256: bipush #20
    //   4258: aload #8
    //   4260: iconst_5
    //   4261: iaload
    //   4262: bipush #24
    //   4264: iushr
    //   4265: i2b
    //   4266: bastore
    //   4267: aload #4
    //   4269: bipush #21
    //   4271: aload #8
    //   4273: iconst_5
    //   4274: iaload
    //   4275: bipush #16
    //   4277: iushr
    //   4278: i2b
    //   4279: bastore
    //   4280: aload #4
    //   4282: bipush #22
    //   4284: aload #8
    //   4286: iconst_5
    //   4287: iaload
    //   4288: bipush #8
    //   4290: iushr
    //   4291: i2b
    //   4292: bastore
    //   4293: aload #4
    //   4295: bipush #23
    //   4297: aload #8
    //   4299: iconst_5
    //   4300: iaload
    //   4301: i2b
    //   4302: bastore
    //   4303: aload #4
    //   4305: bipush #24
    //   4307: aload #8
    //   4309: bipush #6
    //   4311: iaload
    //   4312: bipush #24
    //   4314: iushr
    //   4315: i2b
    //   4316: bastore
    //   4317: aload #4
    //   4319: bipush #25
    //   4321: aload #8
    //   4323: bipush #6
    //   4325: iaload
    //   4326: bipush #16
    //   4328: iushr
    //   4329: i2b
    //   4330: bastore
    //   4331: aload #4
    //   4333: bipush #26
    //   4335: aload #8
    //   4337: bipush #6
    //   4339: iaload
    //   4340: bipush #8
    //   4342: iushr
    //   4343: i2b
    //   4344: bastore
    //   4345: aload #4
    //   4347: bipush #27
    //   4349: aload #8
    //   4351: bipush #6
    //   4353: iaload
    //   4354: i2b
    //   4355: bastore
    //   4356: aload #4
    //   4358: bipush #28
    //   4360: aload #8
    //   4362: bipush #7
    //   4364: iaload
    //   4365: bipush #24
    //   4367: iushr
    //   4368: i2b
    //   4369: bastore
    //   4370: aload #4
    //   4372: bipush #29
    //   4374: aload #8
    //   4376: bipush #7
    //   4378: iaload
    //   4379: bipush #16
    //   4381: iushr
    //   4382: i2b
    //   4383: bastore
    //   4384: aload #4
    //   4386: bipush #30
    //   4388: aload #8
    //   4390: bipush #7
    //   4392: iaload
    //   4393: bipush #8
    //   4395: iushr
    //   4396: i2b
    //   4397: bastore
    //   4398: aload #4
    //   4400: bipush #31
    //   4402: aload #8
    //   4404: bipush #7
    //   4406: iaload
    //   4407: i2b
    //   4408: bastore
    //   4409: getstatic burp/Zgnp.ZL : Ljava/lang/String;
    //   4412: getstatic burp/Zk12.Zh : Ljava/lang/Object;
    //   4415: checkcast java/math/BigInteger
    //   4418: invokevirtual intValue : ()I
    //   4421: bipush #32
    //   4423: irem
    //   4424: invokestatic abs : (I)I
    //   4427: invokevirtual charAt : (I)C
    //   4430: getstatic burp/Zs_v.Zn : Ljava/lang/String;
    //   4433: getstatic burp/Zz6t.ZA : Ljava/lang/Object;
    //   4436: checkcast java/math/BigInteger
    //   4439: invokevirtual intValue : ()I
    //   4442: bipush #32
    //   4444: irem
    //   4445: invokestatic abs : (I)I
    //   4448: invokevirtual charAt : (I)C
    //   4451: if_icmpgt -> 4558
    //   4454: getstatic burp/Zg4k.ZB : Ljava/lang/String;
    //   4457: getstatic burp/Zz20.ZN : Ljava/lang/Object;
    //   4460: checkcast java/math/BigInteger
    //   4463: invokevirtual intValue : ()I
    //   4466: bipush #32
    //   4468: irem
    //   4469: invokestatic abs : (I)I
    //   4472: invokevirtual charAt : (I)C
    //   4475: getstatic burp/Zs2n.ZI : Ljava/lang/String;
    //   4478: getstatic burp/Zzmw.ZS : Ljava/lang/Object;
    //   4481: checkcast java/math/BigInteger
    //   4484: invokevirtual intValue : ()I
    //   4487: bipush #32
    //   4489: irem
    //   4490: invokestatic abs : (I)I
    //   4493: invokevirtual charAt : (I)C
    //   4496: if_icmple -> 4558
    //   4499: goto -> 4506
    //   4502: invokestatic a : (Ljava/lang/Throwable;)Ljava/lang/Throwable;
    //   4505: athrow
    //   4506: getstatic burp/Zsxo.ZW : Ljava/lang/String;
    //   4509: getstatic burp/Zs_3.ZZ : Ljava/lang/Object;
    //   4512: checkcast java/math/BigInteger
    //   4515: invokevirtual intValue : ()I
    //   4518: bipush #32
    //   4520: irem
    //   4521: invokestatic abs : (I)I
    //   4524: invokevirtual charAt : (I)C
    //   4527: getstatic burp/Zs8q.Zs : Ljava/lang/String;
    //   4530: getstatic burp/Zrpu.Zi : Ljava/lang/Object;
    //   4533: checkcast java/math/BigInteger
    //   4536: invokevirtual intValue : ()I
    //   4539: bipush #32
    //   4541: irem
    //   4542: invokestatic abs : (I)I
    //   4545: invokevirtual charAt : (I)C
    //   4548: if_icmpgt -> 4566
    //   4551: goto -> 4558
    //   4554: invokestatic a : (Ljava/lang/Throwable;)Ljava/lang/Throwable;
    //   4557: athrow
    //   4558: iconst_1
    //   4559: goto -> 4567
    //   4562: invokestatic a : (Ljava/lang/Throwable;)Ljava/lang/Throwable;
    //   4565: athrow
    //   4566: iconst_0
    //   4567: ireturn
    //   4568: astore_3
    //   4569: new java/lang/Exception
    //   4572: dup
    //   4573: aload_3
    //   4574: invokevirtual getMessage : ()Ljava/lang/String;
    //   4577: invokespecial <init> : (Ljava/lang/String;)V
    //   4580: athrow
    // Exception table:
    //   from	to	target	type
    //   4	4567	4568	java/lang/Throwable
    //   64	78	78	java/lang/Throwable
    //   89	102	105	java/lang/Throwable
    //   94	117	120	java/lang/Throwable
    //   109	135	138	java/lang/Throwable
    //   124	165	168	java/lang/Throwable
    //   228	255	258	java/lang/Throwable
    //   245	276	279	java/lang/Throwable
    //   262	306	309	java/lang/Throwable
    //   283	317	317	java/lang/Throwable
    //   328	344	347	java/lang/Throwable
    //   1152	1186	1189	java/lang/Throwable
    //   1281	1359	1362	java/lang/Throwable
    //   1288	1502	1505	java/lang/Throwable
    //   1879	1894	1894	java/lang/Throwable
    //   1921	1955	1958	java/lang/Throwable
    //   1965	1977	1980	java/lang/Throwable
    //   2063	2141	2144	java/lang/Throwable
    //   2070	2284	2287	java/lang/Throwable
    //   2684	2762	2765	java/lang/Throwable
    //   2691	2905	2908	java/lang/Throwable
    //   3352	3386	3389	java/lang/Throwable
    //   3393	3405	3408	java/lang/Throwable
    //   3491	3569	3572	java/lang/Throwable
    //   3498	3712	3715	java/lang/Throwable
    //   4015	4499	4502	java/lang/Throwable
    //   4454	4551	4554	java/lang/Throwable
    //   4506	4562	4562	java/lang/Throwable
  }
  
  static {
    // Byte code:
    //   0: bipush #9
    //   2: anewarray java/lang/String
    //   5: astore #5
    //   7: iconst_0
    //   8: istore_3
    //   9: ldc 'gGb3 `_l(MmQ\\thGVcx5\\tD'iF v%?j$0q7k@Mjs&M&4.1\\f'GwN\\t.09*/B"2I;$o(U%'
    //   11: dup
    //   12: astore_2
    //   13: invokevirtual length : ()I
    //   16: istore #4
    //   18: bipush #9
    //   20: istore_1
    //   21: iconst_m1
    //   22: istore_0
    //   23: bipush #15
    //   25: iinc #0, 1
    //   28: aload_2
    //   29: iload_0
    //   30: dup
    //   31: iload_1
    //   32: iadd
    //   33: invokevirtual substring : (II)Ljava/lang/String;
    //   36: iconst_m1
    //   37: goto -> 143
    //   40: aload #5
    //   42: swap
    //   43: iload_3
    //   44: iinc #3, 1
    //   47: swap
    //   48: aastore
    //   49: iload_0
    //   50: iload_1
    //   51: iadd
    //   52: dup
    //   53: istore_0
    //   54: iload #4
    //   56: if_icmpge -> 68
    //   59: aload_2
    //   60: iload_0
    //   61: invokevirtual charAt : (I)C
    //   64: istore_1
    //   65: goto -> 23
    //   68: ldc '\\t-PM9X(Hf.Y8\\r6VsM\\t\\r_VN(mkns\\r4s'
    //   70: dup
    //   71: astore_2
    //   72: invokevirtual length : ()I
    //   75: istore #4
    //   77: bipush #9
    //   79: istore_1
    //   80: iconst_m1
    //   81: istore_0
    //   82: bipush #88
    //   84: iinc #0, 1
    //   87: aload_2
    //   88: iload_0
    //   89: dup
    //   90: iload_1
    //   91: iadd
    //   92: invokevirtual substring : (II)Ljava/lang/String;
    //   95: iconst_0
    //   96: goto -> 143
    //   99: aload #5
    //   101: swap
    //   102: iload_3
    //   103: iinc #3, 1
    //   106: swap
    //   107: aastore
    //   108: iload_0
    //   109: iload_1
    //   110: iadd
    //   111: dup
    //   112: istore_0
    //   113: iload #4
    //   115: if_icmpge -> 127
    //   118: aload_2
    //   119: iload_0
    //   120: invokevirtual charAt : (I)C
    //   123: istore_1
    //   124: goto -> 82
    //   127: aload #5
    //   129: putstatic burp/Zz6t.a : [Ljava/lang/String;
    //   132: bipush #9
    //   134: anewarray java/lang/String
    //   137: putstatic burp/Zz6t.b : [Ljava/lang/String;
    //   140: goto -> 300
    //   143: dup_x2
    //   144: pop
    //   145: invokevirtual toCharArray : ()[C
    //   148: dup_x1
    //   149: arraylength
    //   150: dup_x2
    //   151: pop
    //   152: iconst_0
    //   153: istore #6
    //   155: dup2_x1
    //   156: pop2
    //   157: dup_x2
    //   158: iconst_1
    //   159: if_icmpgt -> 260
    //   162: dup2
    //   163: swap
    //   164: iload #6
    //   166: dup2_x1
    //   167: caload
    //   168: swap
    //   169: iload #6
    //   171: bipush #7
    //   173: irem
    //   174: tableswitch default -> 242, 0 -> 212, 1 -> 217, 2 -> 222, 3 -> 227, 4 -> 232, 5 -> 237
    //   212: bipush #62
    //   214: goto -> 244
    //   217: bipush #80
    //   219: goto -> 244
    //   222: bipush #46
    //   224: goto -> 244
    //   227: bipush #53
    //   229: goto -> 244
    //   232: bipush #70
    //   234: goto -> 244
    //   237: bipush #93
    //   239: goto -> 244
    //   242: bipush #119
    //   244: ixor
    //   245: ixor
    //   246: i2c
    //   247: castore
    //   248: iinc #6, 1
    //   251: dup
    //   252: ifne -> 260
    //   255: dup2
    //   256: dup_x1
    //   257: goto -> 166
    //   260: dup2_x1
    //   261: pop2
    //   262: dup_x2
    //   263: iload #6
    //   265: if_icmpgt -> 162
    //   268: pop
    //   269: new java/lang/String
    //   272: dup_x1
    //   273: swap
    //   274: invokespecial <init> : ([C)V
    //   277: invokevirtual intern : ()Ljava/lang/String;
    //   280: swap
    //   281: pop
    //   282: swap
    //   283: tableswitch default -> 40, 0 -> 99
    //   300: sipush #14775
    //   303: sipush #-3883
    //   306: invokestatic a : (II)Ljava/lang/String;
    //   309: putstatic burp/Zz6t.Zx : Ljava/lang/String;
    //   312: new java/math/BigInteger
    //   315: dup
    //   316: sipush #14782
    //   319: sipush #29461
    //   322: invokestatic a : (II)Ljava/lang/String;
    //   325: invokespecial <init> : (Ljava/lang/String;)V
    //   328: putstatic burp/Zz6t.ZA : Ljava/lang/Object;
    //   331: return
  }
  
  private static Throwable a(Throwable paramThrowable) {
    return paramThrowable;
  }
  
  private static String a(int paramInt1, int paramInt2) {
    int i = (paramInt1 ^ 0x39B6) & 0xFFFF;
    if (b[i] == null) {
      char[] arrayOfChar = a[i].toCharArray();
      switch (arrayOfChar[0] & 0xFF) {
        case 0:
        
        case 1:
        
        case 2:
        
        case 3:
        
        case 4:
        
        case 5:
        
        case 6:
        
        case 7:
        
        case 8:
        
        case 9:
        
        case 10:
        
        case 11:
        
        case 12:
        
        case 13:
        
        case 14:
        
        case 15:
        
        case 16:
        
        case 17:
        
        case 18:
        
        case 19:
        
        case 20:
        
        case 21:
        
        case 22:
        
        case 23:
        
        case 24:
        
        case 25:
        
        case 26:
        
        case 27:
        
        case 28:
        
        case 29:
        
        case 30:
        
        case 31:
        
        case 32:
        
        case 33:
        
        case 34:
        
        case 35:
        
        case 36:
        
        case 37:
        
        case 38:
        
        case 39:
        
        case 40:
        
        case 41:
        
        case 42:
        
        case 43:
        
        case 44:
        
        case 45:
        
        case 46:
        
        case 47:
        
        case 48:
        
        case 49:
        
        case 50:
        
        case 51:
        
        case 52:
        
        case 53:
        
        case 54:
        
        case 55:
        
        case 56:
        
        case 57:
        
        case 58:
        
        case 59:
        
        case 60:
        
        case 61:
        
        case 62:
        
        case 63:
        
        case 64:
        
        case 65:
        
        case 66:
        
        case 67:
        
        case 68:
        
        case 69:
        
        case 70:
        
        case 71:
        
        case 72:
        
        case 73:
        
        case 74:
        
        case 75:
        
        case 76:
        
        case 77:
        
        case 78:
        
        case 79:
        
        case 80:
        
        case 81:
        
        case 82:
        
        case 83:
        
        case 84:
        
        case 85:
        
        case 86:
        
        case 87:
        
        case 88:
        
        case 89:
        
        case 90:
        
        case 91:
        
        case 92:
        
        case 93:
        
        case 94:
        
        case 95:
        
        case 96:
        
        case 97:
        
        case 98:
        
        case 99:
        
        case 100:
        
        case 101:
        
        case 102:
        
        case 103:
        
        case 104:
        
        case 105:
        
        case 106:
        
        case 107:
        
        case 108:
        
        case 109:
        
        case 110:
        
        case 111:
        
        case 112:
        
        case 113:
        
        case 114:
        
        case 115:
        
        case 116:
        
        case 117:
        
        case 118:
        
        case 119:
        
        case 120:
        
        case 121:
        
        case 122:
        
        case 123:
        
        case 124:
        
        case 125:
        
        case 126:
        
        case 127:
        
        case 128:
        
        case 129:
        
        case 130:
        
        case 131:
        
        case 132:
        
        case 133:
        
        case 134:
        
        case 135:
        
        case 136:
        
        case 137:
        
        case 138:
        
        case 139:
        
        case 140:
        
        case 141:
        
        case 142:
        
        case 143:
        
        case 144:
        
        case 145:
        
        case 146:
        
        case 147:
        
        case 148:
        
        case 149:
        
        case 150:
        
        case 151:
        
        case 152:
        
        case 153:
        
        case 154:
        
        case 155:
        
        case 156:
        
        case 157:
        
        case 158:
        
        case 159:
        
        case 160:
        
        case 161:
        
        case 162:
        
        case 163:
        
        case 164:
        
        case 165:
        
        case 166:
        
        case 167:
        
        case 168:
        
        case 169:
        
        case 170:
        
        case 171:
        
        case 172:
        
        case 173:
        
        case 174:
        
        case 175:
        
        case 176:
        
        case 177:
        
        case 178:
        
        case 179:
        
        case 180:
        
        case 181:
        
        case 182:
        
        case 183:
        
        case 184:
        
        case 185:
        
        case 186:
        
        case 187:
        
        case 188:
        
        case 189:
        
        case 190:
        
        case 191:
        
        case 192:
        
        case 193:
        
        case 194:
        
        case 195:
        
        case 196:
        
        case 197:
        
        case 198:
        
        case 199:
        
        case 200:
        
        case 201:
        
        case 202:
        
        case 203:
        
        case 204:
        
        case 205:
        
        case 206:
        
        case 207:
        
        case 208:
        
        case 209:
        
        case 210:
        
        case 211:
        
        case 212:
        
        case 213:
        
        case 214:
        
        case 215:
        
        case 216:
        
        case 217:
        
        case 218:
        
        case 219:
        
        case 220:
        
        case 221:
        
        case 222:
        
        case 223:
        
        case 224:
        
        case 225:
        
        case 226:
        
        case 227:
        
        case 228:
        
        case 229:
        
        case 230:
        
        case 231:
        
        case 232:
        
        case 233:
        
        case 234:
        
        case 235:
        
        case 236:
        
        case 237:
        
        case 238:
        
        case 239:
        
        case 240:
        
        case 241:
        
        case 242:
        
        case 243:
        
        case 244:
        
        case 245:
        
        case 246:
        
        case 247:
        
        case 248:
        
        case 249:
        
        case 250:
        
        case 251:
        
        case 252:
        
        case 253:
        
        case 254:
        
        default:
          break;
      } 
      byte b1 = 63;
      int j = (paramInt2 & 0xFF) - b1;
      if (j < 0)
        j += 256; 
      int k = ((paramInt2 & 0xFFFF) >>> 8) - b1;
      if (k < 0)
        k += 256; 
      for (byte b2 = 0; b2 < arrayOfChar.length; b2++) {
        int m = b2 % 2;
        if (m == 0) {
          arrayOfChar[b2] = (char)(arrayOfChar[b2] ^ j);
          j = ((j >>> 3 | j << 5) ^ arrayOfChar[b2]) & 0xFF;
        } else {
          arrayOfChar[b2] = (char)(arrayOfChar[b2] ^ k);
          k = ((k >>> 3 | k << 5) ^ arrayOfChar[b2]) & 0xFF;
        } 
      } 
      b[i] = (new String(arrayOfChar)).intern();
    } 
    return b[i];
  }
}


/* Location:              C:\Program Files\BurpSuitePro\burpsuite_pro.jar!\burp\Zz6t.class
 * Java compiler version: 21 (65.0)
 * JD-Core Version:       1.1.3
 */