package burp;

import java.math.BigInteger;

class Zz91 extends ClassLoader {
  static Object Z_;
  
  static String Zx;
  
  private static final String[] a;
  
  private static final String[] b;
  
  static boolean Zt(Object[] paramArrayOfObject, Object paramObject) throws Throwable {
    // Byte code:
    //   0: invokestatic ZN : ()Z
    //   3: istore_2
    //   4: new java/lang/StringBuilder
    //   7: dup
    //   8: invokespecial <init> : ()V
    //   11: astore_3
    //   12: iconst_0
    //   13: istore #4
    //   15: iload #4
    //   17: bipush #32
    //   19: if_icmpge -> 1355
    //   22: iload #4
    //   24: tableswitch default -> 1348, 0 -> 168, 1 -> 205, 2 -> 242, 3 -> 279, 4 -> 316, 5 -> 353, 6 -> 390, 7 -> 427, 8 -> 464, 9 -> 501, 10 -> 538, 11 -> 575, 12 -> 612, 13 -> 649, 14 -> 686, 15 -> 723, 16 -> 760, 17 -> 797, 18 -> 834, 19 -> 871, 20 -> 908, 21 -> 945, 22 -> 982, 23 -> 1019, 24 -> 1056, 25 -> 1093, 26 -> 1130, 27 -> 1167, 28 -> 1204, 29 -> 1241, 30 -> 1278, 31 -> 1315
    //   168: aload_3
    //   169: getstatic burp/Zgsy.Zv : Ljava/lang/String;
    //   172: getstatic burp/Zmzj.Zm : Ljava/lang/Object;
    //   175: checkcast java/math/BigInteger
    //   178: invokevirtual intValue : ()I
    //   181: bipush #32
    //   183: irem
    //   184: invokestatic abs : (I)I
    //   187: invokevirtual charAt : (I)C
    //   190: invokevirtual append : (C)Ljava/lang/StringBuilder;
    //   193: pop
    //   194: iload_2
    //   195: ifne -> 1348
    //   198: goto -> 205
    //   201: invokestatic a : (Ljava/lang/Throwable;)Ljava/lang/Throwable;
    //   204: athrow
    //   205: aload_3
    //   206: getstatic burp/Zz3b.Zi : Ljava/lang/String;
    //   209: getstatic burp/Zs5y.Zd : Ljava/lang/Object;
    //   212: checkcast java/math/BigInteger
    //   215: invokevirtual intValue : ()I
    //   218: bipush #32
    //   220: irem
    //   221: invokestatic abs : (I)I
    //   224: invokevirtual charAt : (I)C
    //   227: invokevirtual append : (C)Ljava/lang/StringBuilder;
    //   230: pop
    //   231: iload_2
    //   232: ifne -> 1348
    //   235: goto -> 242
    //   238: invokestatic a : (Ljava/lang/Throwable;)Ljava/lang/Throwable;
    //   241: athrow
    //   242: aload_3
    //   243: getstatic burp/Zsko.Zd : Ljava/lang/String;
    //   246: getstatic burp/Zzi_.Zf : Ljava/lang/Object;
    //   249: checkcast java/math/BigInteger
    //   252: invokevirtual intValue : ()I
    //   255: bipush #32
    //   257: irem
    //   258: invokestatic abs : (I)I
    //   261: invokevirtual charAt : (I)C
    //   264: invokevirtual append : (C)Ljava/lang/StringBuilder;
    //   267: pop
    //   268: iload_2
    //   269: ifne -> 1348
    //   272: goto -> 279
    //   275: invokestatic a : (Ljava/lang/Throwable;)Ljava/lang/Throwable;
    //   278: athrow
    //   279: aload_3
    //   280: getstatic burp/Zbnk.Zg : Ljava/lang/String;
    //   283: getstatic burp/Zsko.ZD : Ljava/lang/Object;
    //   286: checkcast java/math/BigInteger
    //   289: invokevirtual intValue : ()I
    //   292: bipush #32
    //   294: irem
    //   295: invokestatic abs : (I)I
    //   298: invokevirtual charAt : (I)C
    //   301: invokevirtual append : (C)Ljava/lang/StringBuilder;
    //   304: pop
    //   305: iload_2
    //   306: ifne -> 1348
    //   309: goto -> 316
    //   312: invokestatic a : (Ljava/lang/Throwable;)Ljava/lang/Throwable;
    //   315: athrow
    //   316: aload_3
    //   317: getstatic burp/Zm83.Zq : Ljava/lang/String;
    //   320: getstatic burp/Zrym.Zk : Ljava/lang/Object;
    //   323: checkcast java/math/BigInteger
    //   326: invokevirtual intValue : ()I
    //   329: bipush #32
    //   331: irem
    //   332: invokestatic abs : (I)I
    //   335: invokevirtual charAt : (I)C
    //   338: invokevirtual append : (C)Ljava/lang/StringBuilder;
    //   341: pop
    //   342: iload_2
    //   343: ifne -> 1348
    //   346: goto -> 353
    //   349: invokestatic a : (Ljava/lang/Throwable;)Ljava/lang/Throwable;
    //   352: athrow
    //   353: aload_3
    //   354: getstatic burp/Zs4g.ZV : Ljava/lang/String;
    //   357: getstatic burp/Zzef.Zw : Ljava/lang/Object;
    //   360: checkcast java/math/BigInteger
    //   363: invokevirtual intValue : ()I
    //   366: bipush #32
    //   368: irem
    //   369: invokestatic abs : (I)I
    //   372: invokevirtual charAt : (I)C
    //   375: invokevirtual append : (C)Ljava/lang/StringBuilder;
    //   378: pop
    //   379: iload_2
    //   380: ifne -> 1348
    //   383: goto -> 390
    //   386: invokestatic a : (Ljava/lang/Throwable;)Ljava/lang/Throwable;
    //   389: athrow
    //   390: aload_3
    //   391: getstatic burp/Zrzg.ZX : Ljava/lang/String;
    //   394: getstatic burp/Zzac.ZH : Ljava/lang/Object;
    //   397: checkcast java/math/BigInteger
    //   400: invokevirtual intValue : ()I
    //   403: bipush #32
    //   405: irem
    //   406: invokestatic abs : (I)I
    //   409: invokevirtual charAt : (I)C
    //   412: invokevirtual append : (C)Ljava/lang/StringBuilder;
    //   415: pop
    //   416: iload_2
    //   417: ifne -> 1348
    //   420: goto -> 427
    //   423: invokestatic a : (Ljava/lang/Throwable;)Ljava/lang/Throwable;
    //   426: athrow
    //   427: aload_3
    //   428: getstatic burp/Zej8.ZP : Ljava/lang/String;
    //   431: getstatic burp/Zrqe.ZX : Ljava/lang/Object;
    //   434: checkcast java/math/BigInteger
    //   437: invokevirtual intValue : ()I
    //   440: bipush #32
    //   442: irem
    //   443: invokestatic abs : (I)I
    //   446: invokevirtual charAt : (I)C
    //   449: invokevirtual append : (C)Ljava/lang/StringBuilder;
    //   452: pop
    //   453: iload_2
    //   454: ifne -> 1348
    //   457: goto -> 464
    //   460: invokestatic a : (Ljava/lang/Throwable;)Ljava/lang/Throwable;
    //   463: athrow
    //   464: aload_3
    //   465: getstatic burp/Zb3d.Zr : Ljava/lang/String;
    //   468: getstatic burp/Ztq2.Zj : Ljava/lang/Object;
    //   471: checkcast java/math/BigInteger
    //   474: invokevirtual intValue : ()I
    //   477: bipush #32
    //   479: irem
    //   480: invokestatic abs : (I)I
    //   483: invokevirtual charAt : (I)C
    //   486: invokevirtual append : (C)Ljava/lang/StringBuilder;
    //   489: pop
    //   490: iload_2
    //   491: ifne -> 1348
    //   494: goto -> 501
    //   497: invokestatic a : (Ljava/lang/Throwable;)Ljava/lang/Throwable;
    //   500: athrow
    //   501: aload_3
    //   502: getstatic burp/Zeub.ZT : Ljava/lang/String;
    //   505: getstatic burp/Zlid.Zx : Ljava/lang/Object;
    //   508: checkcast java/math/BigInteger
    //   511: invokevirtual intValue : ()I
    //   514: bipush #32
    //   516: irem
    //   517: invokestatic abs : (I)I
    //   520: invokevirtual charAt : (I)C
    //   523: invokevirtual append : (C)Ljava/lang/StringBuilder;
    //   526: pop
    //   527: iload_2
    //   528: ifne -> 1348
    //   531: goto -> 538
    //   534: invokestatic a : (Ljava/lang/Throwable;)Ljava/lang/Throwable;
    //   537: athrow
    //   538: aload_3
    //   539: getstatic burp/Zz0y.ZM : Ljava/lang/String;
    //   542: getstatic burp/Zxp5.ZA : Ljava/lang/Object;
    //   545: checkcast java/math/BigInteger
    //   548: invokevirtual intValue : ()I
    //   551: bipush #32
    //   553: irem
    //   554: invokestatic abs : (I)I
    //   557: invokevirtual charAt : (I)C
    //   560: invokevirtual append : (C)Ljava/lang/StringBuilder;
    //   563: pop
    //   564: iload_2
    //   565: ifne -> 1348
    //   568: goto -> 575
    //   571: invokestatic a : (Ljava/lang/Throwable;)Ljava/lang/Throwable;
    //   574: athrow
    //   575: aload_3
    //   576: getstatic burp/Zma0.ZP : Ljava/lang/String;
    //   579: getstatic burp/Zk5k.Zr : Ljava/lang/Object;
    //   582: checkcast java/math/BigInteger
    //   585: invokevirtual intValue : ()I
    //   588: bipush #32
    //   590: irem
    //   591: invokestatic abs : (I)I
    //   594: invokevirtual charAt : (I)C
    //   597: invokevirtual append : (C)Ljava/lang/StringBuilder;
    //   600: pop
    //   601: iload_2
    //   602: ifne -> 1348
    //   605: goto -> 612
    //   608: invokestatic a : (Ljava/lang/Throwable;)Ljava/lang/Throwable;
    //   611: athrow
    //   612: aload_3
    //   613: getstatic burp/Zetf.Zo : Ljava/lang/String;
    //   616: getstatic burp/Zlid.Zx : Ljava/lang/Object;
    //   619: checkcast java/math/BigInteger
    //   622: invokevirtual intValue : ()I
    //   625: bipush #32
    //   627: irem
    //   628: invokestatic abs : (I)I
    //   631: invokevirtual charAt : (I)C
    //   634: invokevirtual append : (C)Ljava/lang/StringBuilder;
    //   637: pop
    //   638: iload_2
    //   639: ifne -> 1348
    //   642: goto -> 649
    //   645: invokestatic a : (Ljava/lang/Throwable;)Ljava/lang/Throwable;
    //   648: athrow
    //   649: aload_3
    //   650: getstatic burp/Zr17.Zu : Ljava/lang/String;
    //   653: getstatic burp/Zmn0.Zo : Ljava/lang/Object;
    //   656: checkcast java/math/BigInteger
    //   659: invokevirtual intValue : ()I
    //   662: bipush #32
    //   664: irem
    //   665: invokestatic abs : (I)I
    //   668: invokevirtual charAt : (I)C
    //   671: invokevirtual append : (C)Ljava/lang/StringBuilder;
    //   674: pop
    //   675: iload_2
    //   676: ifne -> 1348
    //   679: goto -> 686
    //   682: invokestatic a : (Ljava/lang/Throwable;)Ljava/lang/Throwable;
    //   685: athrow
    //   686: aload_3
    //   687: getstatic burp/Zbss.ZV : Ljava/lang/String;
    //   690: getstatic burp/Zgei.ZN : Ljava/lang/Object;
    //   693: checkcast java/math/BigInteger
    //   696: invokevirtual intValue : ()I
    //   699: bipush #32
    //   701: irem
    //   702: invokestatic abs : (I)I
    //   705: invokevirtual charAt : (I)C
    //   708: invokevirtual append : (C)Ljava/lang/StringBuilder;
    //   711: pop
    //   712: iload_2
    //   713: ifne -> 1348
    //   716: goto -> 723
    //   719: invokestatic a : (Ljava/lang/Throwable;)Ljava/lang/Throwable;
    //   722: athrow
    //   723: aload_3
    //   724: getstatic burp/Zmkq.Zr : Ljava/lang/String;
    //   727: getstatic burp/Zemp.Zr : Ljava/lang/Object;
    //   730: checkcast java/math/BigInteger
    //   733: invokevirtual intValue : ()I
    //   736: bipush #32
    //   738: irem
    //   739: invokestatic abs : (I)I
    //   742: invokevirtual charAt : (I)C
    //   745: invokevirtual append : (C)Ljava/lang/StringBuilder;
    //   748: pop
    //   749: iload_2
    //   750: ifne -> 1348
    //   753: goto -> 760
    //   756: invokestatic a : (Ljava/lang/Throwable;)Ljava/lang/Throwable;
    //   759: athrow
    //   760: aload_3
    //   761: getstatic burp/Zge2.ZT : Ljava/lang/String;
    //   764: getstatic burp/Zv8d.ZN : Ljava/lang/Object;
    //   767: checkcast java/math/BigInteger
    //   770: invokevirtual intValue : ()I
    //   773: bipush #32
    //   775: irem
    //   776: invokestatic abs : (I)I
    //   779: invokevirtual charAt : (I)C
    //   782: invokevirtual append : (C)Ljava/lang/StringBuilder;
    //   785: pop
    //   786: iload_2
    //   787: ifne -> 1348
    //   790: goto -> 797
    //   793: invokestatic a : (Ljava/lang/Throwable;)Ljava/lang/Throwable;
    //   796: athrow
    //   797: aload_3
    //   798: getstatic burp/Zlab.Zp : Ljava/lang/String;
    //   801: getstatic burp/Zbl4.ZW : Ljava/lang/Object;
    //   804: checkcast java/math/BigInteger
    //   807: invokevirtual intValue : ()I
    //   810: bipush #32
    //   812: irem
    //   813: invokestatic abs : (I)I
    //   816: invokevirtual charAt : (I)C
    //   819: invokevirtual append : (C)Ljava/lang/StringBuilder;
    //   822: pop
    //   823: iload_2
    //   824: ifne -> 1348
    //   827: goto -> 834
    //   830: invokestatic a : (Ljava/lang/Throwable;)Ljava/lang/Throwable;
    //   833: athrow
    //   834: aload_3
    //   835: getstatic burp/Zxdp.ZN : Ljava/lang/String;
    //   838: getstatic burp/Zzmc.Zg : Ljava/lang/Object;
    //   841: checkcast java/math/BigInteger
    //   844: invokevirtual intValue : ()I
    //   847: bipush #32
    //   849: irem
    //   850: invokestatic abs : (I)I
    //   853: invokevirtual charAt : (I)C
    //   856: invokevirtual append : (C)Ljava/lang/StringBuilder;
    //   859: pop
    //   860: iload_2
    //   861: ifne -> 1348
    //   864: goto -> 871
    //   867: invokestatic a : (Ljava/lang/Throwable;)Ljava/lang/Throwable;
    //   870: athrow
    //   871: aload_3
    //   872: getstatic burp/Zrp2.ZJ : Ljava/lang/String;
    //   875: getstatic burp/Zb2n.ZR : Ljava/lang/Object;
    //   878: checkcast java/math/BigInteger
    //   881: invokevirtual intValue : ()I
    //   884: bipush #32
    //   886: irem
    //   887: invokestatic abs : (I)I
    //   890: invokevirtual charAt : (I)C
    //   893: invokevirtual append : (C)Ljava/lang/StringBuilder;
    //   896: pop
    //   897: iload_2
    //   898: ifne -> 1348
    //   901: goto -> 908
    //   904: invokestatic a : (Ljava/lang/Throwable;)Ljava/lang/Throwable;
    //   907: athrow
    //   908: aload_3
    //   909: getstatic burp/Zt85.ZR : Ljava/lang/String;
    //   912: getstatic burp/Ztgv.Zg : Ljava/lang/Object;
    //   915: checkcast java/math/BigInteger
    //   918: invokevirtual intValue : ()I
    //   921: bipush #32
    //   923: irem
    //   924: invokestatic abs : (I)I
    //   927: invokevirtual charAt : (I)C
    //   930: invokevirtual append : (C)Ljava/lang/StringBuilder;
    //   933: pop
    //   934: iload_2
    //   935: ifne -> 1348
    //   938: goto -> 945
    //   941: invokestatic a : (Ljava/lang/Throwable;)Ljava/lang/Throwable;
    //   944: athrow
    //   945: aload_3
    //   946: getstatic burp/Zz7m.Zq : Ljava/lang/String;
    //   949: getstatic burp/Zt5t.Za : Ljava/lang/Object;
    //   952: checkcast java/math/BigInteger
    //   955: invokevirtual intValue : ()I
    //   958: bipush #32
    //   960: irem
    //   961: invokestatic abs : (I)I
    //   964: invokevirtual charAt : (I)C
    //   967: invokevirtual append : (C)Ljava/lang/StringBuilder;
    //   970: pop
    //   971: iload_2
    //   972: ifne -> 1348
    //   975: goto -> 982
    //   978: invokestatic a : (Ljava/lang/Throwable;)Ljava/lang/Throwable;
    //   981: athrow
    //   982: aload_3
    //   983: getstatic burp/Zl_a.ZD : Ljava/lang/String;
    //   986: getstatic burp/Zrfa.Zj : Ljava/lang/Object;
    //   989: checkcast java/math/BigInteger
    //   992: invokevirtual intValue : ()I
    //   995: bipush #32
    //   997: irem
    //   998: invokestatic abs : (I)I
    //   1001: invokevirtual charAt : (I)C
    //   1004: invokevirtual append : (C)Ljava/lang/StringBuilder;
    //   1007: pop
    //   1008: iload_2
    //   1009: ifne -> 1348
    //   1012: goto -> 1019
    //   1015: invokestatic a : (Ljava/lang/Throwable;)Ljava/lang/Throwable;
    //   1018: athrow
    //   1019: aload_3
    //   1020: getstatic burp/Zsp9.ZA : Ljava/lang/String;
    //   1023: getstatic burp/Zt9f.Zl : Ljava/lang/Object;
    //   1026: checkcast java/math/BigInteger
    //   1029: invokevirtual intValue : ()I
    //   1032: bipush #32
    //   1034: irem
    //   1035: invokestatic abs : (I)I
    //   1038: invokevirtual charAt : (I)C
    //   1041: invokevirtual append : (C)Ljava/lang/StringBuilder;
    //   1044: pop
    //   1045: iload_2
    //   1046: ifne -> 1348
    //   1049: goto -> 1056
    //   1052: invokestatic a : (Ljava/lang/Throwable;)Ljava/lang/Throwable;
    //   1055: athrow
    //   1056: aload_3
    //   1057: getstatic burp/Zrnk.Zb : Ljava/lang/String;
    //   1060: getstatic burp/Zsp9.ZV : Ljava/lang/Object;
    //   1063: checkcast java/math/BigInteger
    //   1066: invokevirtual intValue : ()I
    //   1069: bipush #32
    //   1071: irem
    //   1072: invokestatic abs : (I)I
    //   1075: invokevirtual charAt : (I)C
    //   1078: invokevirtual append : (C)Ljava/lang/StringBuilder;
    //   1081: pop
    //   1082: iload_2
    //   1083: ifne -> 1348
    //   1086: goto -> 1093
    //   1089: invokestatic a : (Ljava/lang/Throwable;)Ljava/lang/Throwable;
    //   1092: athrow
    //   1093: aload_3
    //   1094: getstatic burp/Zlg2.ZL : Ljava/lang/String;
    //   1097: getstatic burp/Ztq4.ZA : Ljava/lang/Object;
    //   1100: checkcast java/math/BigInteger
    //   1103: invokevirtual intValue : ()I
    //   1106: bipush #32
    //   1108: irem
    //   1109: invokestatic abs : (I)I
    //   1112: invokevirtual charAt : (I)C
    //   1115: invokevirtual append : (C)Ljava/lang/StringBuilder;
    //   1118: pop
    //   1119: iload_2
    //   1120: ifne -> 1348
    //   1123: goto -> 1130
    //   1126: invokestatic a : (Ljava/lang/Throwable;)Ljava/lang/Throwable;
    //   1129: athrow
    //   1130: aload_3
    //   1131: getstatic burp/Zg4z.Zm : Ljava/lang/String;
    //   1134: getstatic burp/Zskf.ZQ : Ljava/lang/Object;
    //   1137: checkcast java/math/BigInteger
    //   1140: invokevirtual intValue : ()I
    //   1143: bipush #32
    //   1145: irem
    //   1146: invokestatic abs : (I)I
    //   1149: invokevirtual charAt : (I)C
    //   1152: invokevirtual append : (C)Ljava/lang/StringBuilder;
    //   1155: pop
    //   1156: iload_2
    //   1157: ifne -> 1348
    //   1160: goto -> 1167
    //   1163: invokestatic a : (Ljava/lang/Throwable;)Ljava/lang/Throwable;
    //   1166: athrow
    //   1167: aload_3
    //   1168: getstatic burp/Zso.ZL : Ljava/lang/String;
    //   1171: getstatic burp/Zt1h.Zb : Ljava/lang/Object;
    //   1174: checkcast java/math/BigInteger
    //   1177: invokevirtual intValue : ()I
    //   1180: bipush #32
    //   1182: irem
    //   1183: invokestatic abs : (I)I
    //   1186: invokevirtual charAt : (I)C
    //   1189: invokevirtual append : (C)Ljava/lang/StringBuilder;
    //   1192: pop
    //   1193: iload_2
    //   1194: ifne -> 1348
    //   1197: goto -> 1204
    //   1200: invokestatic a : (Ljava/lang/Throwable;)Ljava/lang/Throwable;
    //   1203: athrow
    //   1204: aload_3
    //   1205: getstatic burp/Zgi9.Zv : Ljava/lang/String;
    //   1208: getstatic burp/Zr2q.ZS : Ljava/lang/Object;
    //   1211: checkcast java/math/BigInteger
    //   1214: invokevirtual intValue : ()I
    //   1217: bipush #32
    //   1219: irem
    //   1220: invokestatic abs : (I)I
    //   1223: invokevirtual charAt : (I)C
    //   1226: invokevirtual append : (C)Ljava/lang/StringBuilder;
    //   1229: pop
    //   1230: iload_2
    //   1231: ifne -> 1348
    //   1234: goto -> 1241
    //   1237: invokestatic a : (Ljava/lang/Throwable;)Ljava/lang/Throwable;
    //   1240: athrow
    //   1241: aload_3
    //   1242: getstatic burp/Zz0y.ZM : Ljava/lang/String;
    //   1245: getstatic burp/Zegw.ZW : Ljava/lang/Object;
    //   1248: checkcast java/math/BigInteger
    //   1251: invokevirtual intValue : ()I
    //   1254: bipush #32
    //   1256: irem
    //   1257: invokestatic abs : (I)I
    //   1260: invokevirtual charAt : (I)C
    //   1263: invokevirtual append : (C)Ljava/lang/StringBuilder;
    //   1266: pop
    //   1267: iload_2
    //   1268: ifne -> 1348
    //   1271: goto -> 1278
    //   1274: invokestatic a : (Ljava/lang/Throwable;)Ljava/lang/Throwable;
    //   1277: athrow
    //   1278: aload_3
    //   1279: getstatic burp/Zg7u.ZA : Ljava/lang/String;
    //   1282: getstatic burp/Zttd.Zi : Ljava/lang/Object;
    //   1285: checkcast java/math/BigInteger
    //   1288: invokevirtual intValue : ()I
    //   1291: bipush #32
    //   1293: irem
    //   1294: invokestatic abs : (I)I
    //   1297: invokevirtual charAt : (I)C
    //   1300: invokevirtual append : (C)Ljava/lang/StringBuilder;
    //   1303: pop
    //   1304: iload_2
    //   1305: ifne -> 1348
    //   1308: goto -> 1315
    //   1311: invokestatic a : (Ljava/lang/Throwable;)Ljava/lang/Throwable;
    //   1314: athrow
    //   1315: aload_3
    //   1316: getstatic burp/Zelt.ZJ : Ljava/lang/String;
    //   1319: getstatic burp/Zm63.ZT : Ljava/lang/Object;
    //   1322: checkcast java/math/BigInteger
    //   1325: invokevirtual intValue : ()I
    //   1328: bipush #32
    //   1330: irem
    //   1331: invokestatic abs : (I)I
    //   1334: invokevirtual charAt : (I)C
    //   1337: invokevirtual append : (C)Ljava/lang/StringBuilder;
    //   1340: pop
    //   1341: goto -> 1348
    //   1344: invokestatic a : (Ljava/lang/Throwable;)Ljava/lang/Throwable;
    //   1347: athrow
    //   1348: iinc #4, 1
    //   1351: iload_2
    //   1352: ifne -> 15
    //   1355: aload_3
    //   1356: invokevirtual toString : ()Ljava/lang/String;
    //   1359: putstatic burp/Zso.ZL : Ljava/lang/String;
    //   1362: getstatic burp/Zb0q.ZK : Ljava/lang/Object;
    //   1365: checkcast java/math/BigInteger
    //   1368: getstatic burp/Zxcn.Zq : Ljava/lang/Object;
    //   1371: checkcast java/math/BigInteger
    //   1374: invokevirtual add : (Ljava/math/BigInteger;)Ljava/math/BigInteger;
    //   1377: putstatic burp/Zlxw.Zi : Ljava/lang/Object;
    //   1380: new java/lang/StringBuilder
    //   1383: dup
    //   1384: invokespecial <init> : ()V
    //   1387: astore #4
    //   1389: iconst_0
    //   1390: istore #5
    //   1392: iload #5
    //   1394: bipush #32
    //   1396: if_icmpge -> 2763
    //   1399: iload #5
    //   1401: tableswitch default -> 2756, 0 -> 1544, 1 -> 1582, 2 -> 1620, 3 -> 1658, 4 -> 1696, 5 -> 1734, 6 -> 1772, 7 -> 1810, 8 -> 1848, 9 -> 1886, 10 -> 1924, 11 -> 1962, 12 -> 2000, 13 -> 2038, 14 -> 2076, 15 -> 2114, 16 -> 2152, 17 -> 2190, 18 -> 2228, 19 -> 2266, 20 -> 2304, 21 -> 2342, 22 -> 2380, 23 -> 2418, 24 -> 2456, 25 -> 2494, 26 -> 2532, 27 -> 2570, 28 -> 2608, 29 -> 2646, 30 -> 2684, 31 -> 2722
    //   1544: aload #4
    //   1546: getstatic burp/Zxxo.ZH : Ljava/lang/String;
    //   1549: getstatic burp/Ztwp.Ze : Ljava/lang/Object;
    //   1552: checkcast java/math/BigInteger
    //   1555: invokevirtual intValue : ()I
    //   1558: bipush #32
    //   1560: irem
    //   1561: invokestatic abs : (I)I
    //   1564: invokevirtual charAt : (I)C
    //   1567: invokevirtual append : (C)Ljava/lang/StringBuilder;
    //   1570: pop
    //   1571: iload_2
    //   1572: ifne -> 2756
    //   1575: goto -> 1582
    //   1578: invokestatic a : (Ljava/lang/Throwable;)Ljava/lang/Throwable;
    //   1581: athrow
    //   1582: aload #4
    //   1584: getstatic burp/Zge2.ZT : Ljava/lang/String;
    //   1587: getstatic burp/Zb2n.ZR : Ljava/lang/Object;
    //   1590: checkcast java/math/BigInteger
    //   1593: invokevirtual intValue : ()I
    //   1596: bipush #32
    //   1598: irem
    //   1599: invokestatic abs : (I)I
    //   1602: invokevirtual charAt : (I)C
    //   1605: invokevirtual append : (C)Ljava/lang/StringBuilder;
    //   1608: pop
    //   1609: iload_2
    //   1610: ifne -> 2756
    //   1613: goto -> 1620
    //   1616: invokestatic a : (Ljava/lang/Throwable;)Ljava/lang/Throwable;
    //   1619: athrow
    //   1620: aload #4
    //   1622: getstatic burp/Zttd.Ze : Ljava/lang/String;
    //   1625: getstatic burp/Zmll.ZU : Ljava/lang/Object;
    //   1628: checkcast java/math/BigInteger
    //   1631: invokevirtual intValue : ()I
    //   1634: bipush #32
    //   1636: irem
    //   1637: invokestatic abs : (I)I
    //   1640: invokevirtual charAt : (I)C
    //   1643: invokevirtual append : (C)Ljava/lang/StringBuilder;
    //   1646: pop
    //   1647: iload_2
    //   1648: ifne -> 2756
    //   1651: goto -> 1658
    //   1654: invokestatic a : (Ljava/lang/Throwable;)Ljava/lang/Throwable;
    //   1657: athrow
    //   1658: aload #4
    //   1660: getstatic burp/Zzmc.Zr : Ljava/lang/String;
    //   1663: getstatic burp/Zb4d.Ze : Ljava/lang/Object;
    //   1666: checkcast java/math/BigInteger
    //   1669: invokevirtual intValue : ()I
    //   1672: bipush #32
    //   1674: irem
    //   1675: invokestatic abs : (I)I
    //   1678: invokevirtual charAt : (I)C
    //   1681: invokevirtual append : (C)Ljava/lang/StringBuilder;
    //   1684: pop
    //   1685: iload_2
    //   1686: ifne -> 2756
    //   1689: goto -> 1696
    //   1692: invokestatic a : (Ljava/lang/Throwable;)Ljava/lang/Throwable;
    //   1695: athrow
    //   1696: aload #4
    //   1698: getstatic burp/Zea.Zj : Ljava/lang/String;
    //   1701: getstatic burp/Zm8j.Zj : Ljava/lang/Object;
    //   1704: checkcast java/math/BigInteger
    //   1707: invokevirtual intValue : ()I
    //   1710: bipush #32
    //   1712: irem
    //   1713: invokestatic abs : (I)I
    //   1716: invokevirtual charAt : (I)C
    //   1719: invokevirtual append : (C)Ljava/lang/StringBuilder;
    //   1722: pop
    //   1723: iload_2
    //   1724: ifne -> 2756
    //   1727: goto -> 1734
    //   1730: invokestatic a : (Ljava/lang/Throwable;)Ljava/lang/Throwable;
    //   1733: athrow
    //   1734: aload #4
    //   1736: getstatic burp/Zr6c.Zf : Ljava/lang/String;
    //   1739: getstatic burp/Zs8w.ZW : Ljava/lang/Object;
    //   1742: checkcast java/math/BigInteger
    //   1745: invokevirtual intValue : ()I
    //   1748: bipush #32
    //   1750: irem
    //   1751: invokestatic abs : (I)I
    //   1754: invokevirtual charAt : (I)C
    //   1757: invokevirtual append : (C)Ljava/lang/StringBuilder;
    //   1760: pop
    //   1761: iload_2
    //   1762: ifne -> 2756
    //   1765: goto -> 1772
    //   1768: invokestatic a : (Ljava/lang/Throwable;)Ljava/lang/Throwable;
    //   1771: athrow
    //   1772: aload #4
    //   1774: getstatic burp/Zxcn.ZF : Ljava/lang/String;
    //   1777: getstatic burp/Zr14.Zy : Ljava/lang/Object;
    //   1780: checkcast java/math/BigInteger
    //   1783: invokevirtual intValue : ()I
    //   1786: bipush #32
    //   1788: irem
    //   1789: invokestatic abs : (I)I
    //   1792: invokevirtual charAt : (I)C
    //   1795: invokevirtual append : (C)Ljava/lang/StringBuilder;
    //   1798: pop
    //   1799: iload_2
    //   1800: ifne -> 2756
    //   1803: goto -> 1810
    //   1806: invokestatic a : (Ljava/lang/Throwable;)Ljava/lang/Throwable;
    //   1809: athrow
    //   1810: aload #4
    //   1812: getstatic burp/Zzts.Zk : Ljava/lang/String;
    //   1815: getstatic burp/Zr6c.ZG : Ljava/lang/Object;
    //   1818: checkcast java/math/BigInteger
    //   1821: invokevirtual intValue : ()I
    //   1824: bipush #32
    //   1826: irem
    //   1827: invokestatic abs : (I)I
    //   1830: invokevirtual charAt : (I)C
    //   1833: invokevirtual append : (C)Ljava/lang/StringBuilder;
    //   1836: pop
    //   1837: iload_2
    //   1838: ifne -> 2756
    //   1841: goto -> 1848
    //   1844: invokestatic a : (Ljava/lang/Throwable;)Ljava/lang/Throwable;
    //   1847: athrow
    //   1848: aload #4
    //   1850: getstatic burp/Zxd1.ZQ : Ljava/lang/String;
    //   1853: getstatic burp/Ztq2.Zj : Ljava/lang/Object;
    //   1856: checkcast java/math/BigInteger
    //   1859: invokevirtual intValue : ()I
    //   1862: bipush #32
    //   1864: irem
    //   1865: invokestatic abs : (I)I
    //   1868: invokevirtual charAt : (I)C
    //   1871: invokevirtual append : (C)Ljava/lang/StringBuilder;
    //   1874: pop
    //   1875: iload_2
    //   1876: ifne -> 2756
    //   1879: goto -> 1886
    //   1882: invokestatic a : (Ljava/lang/Throwable;)Ljava/lang/Throwable;
    //   1885: athrow
    //   1886: aload #4
    //   1888: getstatic burp/Zm8j.Zp : Ljava/lang/String;
    //   1891: getstatic burp/Zgsy.ZC : Ljava/lang/Object;
    //   1894: checkcast java/math/BigInteger
    //   1897: invokevirtual intValue : ()I
    //   1900: bipush #32
    //   1902: irem
    //   1903: invokestatic abs : (I)I
    //   1906: invokevirtual charAt : (I)C
    //   1909: invokevirtual append : (C)Ljava/lang/StringBuilder;
    //   1912: pop
    //   1913: iload_2
    //   1914: ifne -> 2756
    //   1917: goto -> 1924
    //   1920: invokestatic a : (Ljava/lang/Throwable;)Ljava/lang/Throwable;
    //   1923: athrow
    //   1924: aload #4
    //   1926: getstatic burp/Zezi.Ze : Ljava/lang/String;
    //   1929: getstatic burp/Ztnn.ZA : Ljava/lang/Object;
    //   1932: checkcast java/math/BigInteger
    //   1935: invokevirtual intValue : ()I
    //   1938: bipush #32
    //   1940: irem
    //   1941: invokestatic abs : (I)I
    //   1944: invokevirtual charAt : (I)C
    //   1947: invokevirtual append : (C)Ljava/lang/StringBuilder;
    //   1950: pop
    //   1951: iload_2
    //   1952: ifne -> 2756
    //   1955: goto -> 1962
    //   1958: invokestatic a : (Ljava/lang/Throwable;)Ljava/lang/Throwable;
    //   1961: athrow
    //   1962: aload #4
    //   1964: getstatic burp/Zmc_.Zb : Ljava/lang/String;
    //   1967: getstatic burp/Zlf7.ZE : Ljava/lang/Object;
    //   1970: checkcast java/math/BigInteger
    //   1973: invokevirtual intValue : ()I
    //   1976: bipush #32
    //   1978: irem
    //   1979: invokestatic abs : (I)I
    //   1982: invokevirtual charAt : (I)C
    //   1985: invokevirtual append : (C)Ljava/lang/StringBuilder;
    //   1988: pop
    //   1989: iload_2
    //   1990: ifne -> 2756
    //   1993: goto -> 2000
    //   1996: invokestatic a : (Ljava/lang/Throwable;)Ljava/lang/Throwable;
    //   1999: athrow
    //   2000: aload #4
    //   2002: getstatic burp/Zld9.Zx : Ljava/lang/String;
    //   2005: getstatic burp/Zv8d.ZN : Ljava/lang/Object;
    //   2008: checkcast java/math/BigInteger
    //   2011: invokevirtual intValue : ()I
    //   2014: bipush #32
    //   2016: irem
    //   2017: invokestatic abs : (I)I
    //   2020: invokevirtual charAt : (I)C
    //   2023: invokevirtual append : (C)Ljava/lang/StringBuilder;
    //   2026: pop
    //   2027: iload_2
    //   2028: ifne -> 2756
    //   2031: goto -> 2038
    //   2034: invokestatic a : (Ljava/lang/Throwable;)Ljava/lang/Throwable;
    //   2037: athrow
    //   2038: aload #4
    //   2040: getstatic burp/Zegw.Zn : Ljava/lang/String;
    //   2043: getstatic burp/Zmhq.ZK : Ljava/lang/Object;
    //   2046: checkcast java/math/BigInteger
    //   2049: invokevirtual intValue : ()I
    //   2052: bipush #32
    //   2054: irem
    //   2055: invokestatic abs : (I)I
    //   2058: invokevirtual charAt : (I)C
    //   2061: invokevirtual append : (C)Ljava/lang/StringBuilder;
    //   2064: pop
    //   2065: iload_2
    //   2066: ifne -> 2756
    //   2069: goto -> 2076
    //   2072: invokestatic a : (Ljava/lang/Throwable;)Ljava/lang/Throwable;
    //   2075: athrow
    //   2076: aload #4
    //   2078: getstatic burp/Ztbn.Zx : Ljava/lang/String;
    //   2081: getstatic burp/Zkhf.ZU : Ljava/lang/Object;
    //   2084: checkcast java/math/BigInteger
    //   2087: invokevirtual intValue : ()I
    //   2090: bipush #32
    //   2092: irem
    //   2093: invokestatic abs : (I)I
    //   2096: invokevirtual charAt : (I)C
    //   2099: invokevirtual append : (C)Ljava/lang/StringBuilder;
    //   2102: pop
    //   2103: iload_2
    //   2104: ifne -> 2756
    //   2107: goto -> 2114
    //   2110: invokestatic a : (Ljava/lang/Throwable;)Ljava/lang/Throwable;
    //   2113: athrow
    //   2114: aload #4
    //   2116: getstatic burp/Ztq8.ZI : Ljava/lang/String;
    //   2119: getstatic burp/Zr14.Zy : Ljava/lang/Object;
    //   2122: checkcast java/math/BigInteger
    //   2125: invokevirtual intValue : ()I
    //   2128: bipush #32
    //   2130: irem
    //   2131: invokestatic abs : (I)I
    //   2134: invokevirtual charAt : (I)C
    //   2137: invokevirtual append : (C)Ljava/lang/StringBuilder;
    //   2140: pop
    //   2141: iload_2
    //   2142: ifne -> 2756
    //   2145: goto -> 2152
    //   2148: invokestatic a : (Ljava/lang/Throwable;)Ljava/lang/Throwable;
    //   2151: athrow
    //   2152: aload #4
    //   2154: getstatic burp/Zb3d.Zr : Ljava/lang/String;
    //   2157: getstatic burp/Zsn3.Zy : Ljava/lang/Object;
    //   2160: checkcast java/math/BigInteger
    //   2163: invokevirtual intValue : ()I
    //   2166: bipush #32
    //   2168: irem
    //   2169: invokestatic abs : (I)I
    //   2172: invokevirtual charAt : (I)C
    //   2175: invokevirtual append : (C)Ljava/lang/StringBuilder;
    //   2178: pop
    //   2179: iload_2
    //   2180: ifne -> 2756
    //   2183: goto -> 2190
    //   2186: invokestatic a : (Ljava/lang/Throwable;)Ljava/lang/Throwable;
    //   2189: athrow
    //   2190: aload #4
    //   2192: getstatic burp/Zsn4.ZZ : Ljava/lang/String;
    //   2195: getstatic burp/Zt6z.Zl : Ljava/lang/Object;
    //   2198: checkcast java/math/BigInteger
    //   2201: invokevirtual intValue : ()I
    //   2204: bipush #32
    //   2206: irem
    //   2207: invokestatic abs : (I)I
    //   2210: invokevirtual charAt : (I)C
    //   2213: invokevirtual append : (C)Ljava/lang/StringBuilder;
    //   2216: pop
    //   2217: iload_2
    //   2218: ifne -> 2756
    //   2221: goto -> 2228
    //   2224: invokestatic a : (Ljava/lang/Throwable;)Ljava/lang/Throwable;
    //   2227: athrow
    //   2228: aload #4
    //   2230: getstatic burp/Zesw.ZC : Ljava/lang/String;
    //   2233: getstatic burp/Zllk.Zi : Ljava/lang/Object;
    //   2236: checkcast java/math/BigInteger
    //   2239: invokevirtual intValue : ()I
    //   2242: bipush #32
    //   2244: irem
    //   2245: invokestatic abs : (I)I
    //   2248: invokevirtual charAt : (I)C
    //   2251: invokevirtual append : (C)Ljava/lang/StringBuilder;
    //   2254: pop
    //   2255: iload_2
    //   2256: ifne -> 2756
    //   2259: goto -> 2266
    //   2262: invokestatic a : (Ljava/lang/Throwable;)Ljava/lang/Throwable;
    //   2265: athrow
    //   2266: aload #4
    //   2268: getstatic burp/Ze4g.Zk : Ljava/lang/String;
    //   2271: getstatic burp/Zbun.ZH : Ljava/lang/Object;
    //   2274: checkcast java/math/BigInteger
    //   2277: invokevirtual intValue : ()I
    //   2280: bipush #32
    //   2282: irem
    //   2283: invokestatic abs : (I)I
    //   2286: invokevirtual charAt : (I)C
    //   2289: invokevirtual append : (C)Ljava/lang/StringBuilder;
    //   2292: pop
    //   2293: iload_2
    //   2294: ifne -> 2756
    //   2297: goto -> 2304
    //   2300: invokestatic a : (Ljava/lang/Throwable;)Ljava/lang/Throwable;
    //   2303: athrow
    //   2304: aload #4
    //   2306: getstatic burp/Ztvg.ZZ : Ljava/lang/String;
    //   2309: getstatic burp/Zt5t.Za : Ljava/lang/Object;
    //   2312: checkcast java/math/BigInteger
    //   2315: invokevirtual intValue : ()I
    //   2318: bipush #32
    //   2320: irem
    //   2321: invokestatic abs : (I)I
    //   2324: invokevirtual charAt : (I)C
    //   2327: invokevirtual append : (C)Ljava/lang/StringBuilder;
    //   2330: pop
    //   2331: iload_2
    //   2332: ifne -> 2756
    //   2335: goto -> 2342
    //   2338: invokestatic a : (Ljava/lang/Throwable;)Ljava/lang/Throwable;
    //   2341: athrow
    //   2342: aload #4
    //   2344: getstatic burp/Zgio.ZS : Ljava/lang/String;
    //   2347: getstatic burp/Zlc2.ZQ : Ljava/lang/Object;
    //   2350: checkcast java/math/BigInteger
    //   2353: invokevirtual intValue : ()I
    //   2356: bipush #32
    //   2358: irem
    //   2359: invokestatic abs : (I)I
    //   2362: invokevirtual charAt : (I)C
    //   2365: invokevirtual append : (C)Ljava/lang/StringBuilder;
    //   2368: pop
    //   2369: iload_2
    //   2370: ifne -> 2756
    //   2373: goto -> 2380
    //   2376: invokestatic a : (Ljava/lang/Throwable;)Ljava/lang/Throwable;
    //   2379: athrow
    //   2380: aload #4
    //   2382: getstatic burp/Zzhx.ZV : Ljava/lang/String;
    //   2385: getstatic burp/Ze5h.Zn : Ljava/lang/Object;
    //   2388: checkcast java/math/BigInteger
    //   2391: invokevirtual intValue : ()I
    //   2394: bipush #32
    //   2396: irem
    //   2397: invokestatic abs : (I)I
    //   2400: invokevirtual charAt : (I)C
    //   2403: invokevirtual append : (C)Ljava/lang/StringBuilder;
    //   2406: pop
    //   2407: iload_2
    //   2408: ifne -> 2756
    //   2411: goto -> 2418
    //   2414: invokestatic a : (Ljava/lang/Throwable;)Ljava/lang/Throwable;
    //   2417: athrow
    //   2418: aload #4
    //   2420: getstatic burp/Zea.Zj : Ljava/lang/String;
    //   2423: getstatic burp/Zl7x.Za : Ljava/lang/Object;
    //   2426: checkcast java/math/BigInteger
    //   2429: invokevirtual intValue : ()I
    //   2432: bipush #32
    //   2434: irem
    //   2435: invokestatic abs : (I)I
    //   2438: invokevirtual charAt : (I)C
    //   2441: invokevirtual append : (C)Ljava/lang/StringBuilder;
    //   2444: pop
    //   2445: iload_2
    //   2446: ifne -> 2756
    //   2449: goto -> 2456
    //   2452: invokestatic a : (Ljava/lang/Throwable;)Ljava/lang/Throwable;
    //   2455: athrow
    //   2456: aload #4
    //   2458: getstatic burp/Ztq4.Zb : Ljava/lang/String;
    //   2461: getstatic burp/Zg7u.Zh : Ljava/lang/Object;
    //   2464: checkcast java/math/BigInteger
    //   2467: invokevirtual intValue : ()I
    //   2470: bipush #32
    //   2472: irem
    //   2473: invokestatic abs : (I)I
    //   2476: invokevirtual charAt : (I)C
    //   2479: invokevirtual append : (C)Ljava/lang/StringBuilder;
    //   2482: pop
    //   2483: iload_2
    //   2484: ifne -> 2756
    //   2487: goto -> 2494
    //   2490: invokestatic a : (Ljava/lang/Throwable;)Ljava/lang/Throwable;
    //   2493: athrow
    //   2494: aload #4
    //   2496: getstatic burp/Zmzj.Zb : Ljava/lang/String;
    //   2499: getstatic burp/Zgpx.ZQ : Ljava/lang/Object;
    //   2502: checkcast java/math/BigInteger
    //   2505: invokevirtual intValue : ()I
    //   2508: bipush #32
    //   2510: irem
    //   2511: invokestatic abs : (I)I
    //   2514: invokevirtual charAt : (I)C
    //   2517: invokevirtual append : (C)Ljava/lang/StringBuilder;
    //   2520: pop
    //   2521: iload_2
    //   2522: ifne -> 2756
    //   2525: goto -> 2532
    //   2528: invokestatic a : (Ljava/lang/Throwable;)Ljava/lang/Throwable;
    //   2531: athrow
    //   2532: aload #4
    //   2534: getstatic burp/Ztdl.ZK : Ljava/lang/String;
    //   2537: getstatic burp/Zmc_.Zj : Ljava/lang/Object;
    //   2540: checkcast java/math/BigInteger
    //   2543: invokevirtual intValue : ()I
    //   2546: bipush #32
    //   2548: irem
    //   2549: invokestatic abs : (I)I
    //   2552: invokevirtual charAt : (I)C
    //   2555: invokevirtual append : (C)Ljava/lang/StringBuilder;
    //   2558: pop
    //   2559: iload_2
    //   2560: ifne -> 2756
    //   2563: goto -> 2570
    //   2566: invokestatic a : (Ljava/lang/Throwable;)Ljava/lang/Throwable;
    //   2569: athrow
    //   2570: aload #4
    //   2572: getstatic burp/Zr1h.ZS : Ljava/lang/String;
    //   2575: getstatic burp/Zm69.Zg : Ljava/lang/Object;
    //   2578: checkcast java/math/BigInteger
    //   2581: invokevirtual intValue : ()I
    //   2584: bipush #32
    //   2586: irem
    //   2587: invokestatic abs : (I)I
    //   2590: invokevirtual charAt : (I)C
    //   2593: invokevirtual append : (C)Ljava/lang/StringBuilder;
    //   2596: pop
    //   2597: iload_2
    //   2598: ifne -> 2756
    //   2601: goto -> 2608
    //   2604: invokestatic a : (Ljava/lang/Throwable;)Ljava/lang/Throwable;
    //   2607: athrow
    //   2608: aload #4
    //   2610: getstatic burp/Ze2k.ZY : Ljava/lang/String;
    //   2613: getstatic burp/Zsvd.Zk : Ljava/lang/Object;
    //   2616: checkcast java/math/BigInteger
    //   2619: invokevirtual intValue : ()I
    //   2622: bipush #32
    //   2624: irem
    //   2625: invokestatic abs : (I)I
    //   2628: invokevirtual charAt : (I)C
    //   2631: invokevirtual append : (C)Ljava/lang/StringBuilder;
    //   2634: pop
    //   2635: iload_2
    //   2636: ifne -> 2756
    //   2639: goto -> 2646
    //   2642: invokestatic a : (Ljava/lang/Throwable;)Ljava/lang/Throwable;
    //   2645: athrow
    //   2646: aload #4
    //   2648: getstatic burp/Ze2w.Za : Ljava/lang/String;
    //   2651: getstatic burp/Zr36.Za : Ljava/lang/Object;
    //   2654: checkcast java/math/BigInteger
    //   2657: invokevirtual intValue : ()I
    //   2660: bipush #32
    //   2662: irem
    //   2663: invokestatic abs : (I)I
    //   2666: invokevirtual charAt : (I)C
    //   2669: invokevirtual append : (C)Ljava/lang/StringBuilder;
    //   2672: pop
    //   2673: iload_2
    //   2674: ifne -> 2756
    //   2677: goto -> 2684
    //   2680: invokestatic a : (Ljava/lang/Throwable;)Ljava/lang/Throwable;
    //   2683: athrow
    //   2684: aload #4
    //   2686: getstatic burp/Zr2q.ZA : Ljava/lang/String;
    //   2689: getstatic burp/Ztgv.Zg : Ljava/lang/Object;
    //   2692: checkcast java/math/BigInteger
    //   2695: invokevirtual intValue : ()I
    //   2698: bipush #32
    //   2700: irem
    //   2701: invokestatic abs : (I)I
    //   2704: invokevirtual charAt : (I)C
    //   2707: invokevirtual append : (C)Ljava/lang/StringBuilder;
    //   2710: pop
    //   2711: iload_2
    //   2712: ifne -> 2756
    //   2715: goto -> 2722
    //   2718: invokestatic a : (Ljava/lang/Throwable;)Ljava/lang/Throwable;
    //   2721: athrow
    //   2722: aload #4
    //   2724: getstatic burp/Zt6z.ZL : Ljava/lang/String;
    //   2727: getstatic burp/Zg61.Zp : Ljava/lang/Object;
    //   2730: checkcast java/math/BigInteger
    //   2733: invokevirtual intValue : ()I
    //   2736: bipush #32
    //   2738: irem
    //   2739: invokestatic abs : (I)I
    //   2742: invokevirtual charAt : (I)C
    //   2745: invokevirtual append : (C)Ljava/lang/StringBuilder;
    //   2748: pop
    //   2749: goto -> 2756
    //   2752: invokestatic a : (Ljava/lang/Throwable;)Ljava/lang/Throwable;
    //   2755: athrow
    //   2756: iinc #5, 1
    //   2759: iload_2
    //   2760: ifne -> 1392
    //   2763: aload #4
    //   2765: invokevirtual toString : ()Ljava/lang/String;
    //   2768: putstatic burp/Zt7x.Zu : Ljava/lang/String;
    //   2771: sipush #-8287
    //   2774: sipush #-7146
    //   2777: invokestatic a : (II)Ljava/lang/String;
    //   2780: iconst_1
    //   2781: ldc burp/Zkht
    //   2783: invokevirtual getClassLoader : ()Ljava/lang/ClassLoader;
    //   2786: invokestatic forName : (Ljava/lang/String;ZLjava/lang/ClassLoader;)Ljava/lang/Class;
    //   2789: invokevirtual getDeclaredFields : ()[Ljava/lang/reflect/Field;
    //   2792: astore #5
    //   2794: aload #5
    //   2796: arraylength
    //   2797: istore #6
    //   2799: iconst_0
    //   2800: istore #7
    //   2802: iload #7
    //   2804: iload #6
    //   2806: if_icmpge -> 2944
    //   2809: aload #5
    //   2811: iload #7
    //   2813: aaload
    //   2814: astore #8
    //   2816: aload #8
    //   2818: invokevirtual getModifiers : ()I
    //   2821: invokestatic isStatic : (I)Z
    //   2824: ifne -> 2834
    //   2827: goto -> 2937
    //   2830: invokestatic a : (Ljava/lang/Throwable;)Ljava/lang/Throwable;
    //   2833: athrow
    //   2834: aload #8
    //   2836: invokevirtual getType : ()Ljava/lang/Class;
    //   2839: astore #9
    //   2841: aload #9
    //   2843: ifnull -> 2924
    //   2846: aload #9
    //   2848: invokevirtual isPrimitive : ()Z
    //   2851: ifne -> 2924
    //   2854: goto -> 2861
    //   2857: invokestatic a : (Ljava/lang/Throwable;)Ljava/lang/Throwable;
    //   2860: athrow
    //   2861: aload #9
    //   2863: invokevirtual getPackage : ()Ljava/lang/Package;
    //   2866: ifnull -> 2924
    //   2869: goto -> 2876
    //   2872: invokestatic a : (Ljava/lang/Throwable;)Ljava/lang/Throwable;
    //   2875: athrow
    //   2876: aload #9
    //   2878: invokevirtual getPackage : ()Ljava/lang/Package;
    //   2881: invokevirtual getName : ()Ljava/lang/String;
    //   2884: ifnull -> 2924
    //   2887: goto -> 2894
    //   2890: invokestatic a : (Ljava/lang/Throwable;)Ljava/lang/Throwable;
    //   2893: athrow
    //   2894: aload #9
    //   2896: invokevirtual getPackage : ()Ljava/lang/Package;
    //   2899: invokevirtual getName : ()Ljava/lang/String;
    //   2902: sipush #-8284
    //   2905: sipush #6999
    //   2908: invokestatic a : (II)Ljava/lang/String;
    //   2911: invokevirtual startsWith : (Ljava/lang/String;)Z
    //   2914: ifne -> 2924
    //   2917: goto -> 2924
    //   2920: invokestatic a : (Ljava/lang/Throwable;)Ljava/lang/Throwable;
    //   2923: athrow
    //   2924: aload #8
    //   2926: iconst_1
    //   2927: invokevirtual setAccessible : (Z)V
    //   2930: aload #8
    //   2932: aconst_null
    //   2933: invokevirtual get : (Ljava/lang/Object;)Ljava/lang/Object;
    //   2936: pop
    //   2937: iinc #7, 1
    //   2940: iload_2
    //   2941: ifne -> 2802
    //   2944: sipush #-8270
    //   2947: sipush #-1941
    //   2950: invokestatic a : (II)Ljava/lang/String;
    //   2953: invokestatic forName : (Ljava/lang/String;)Ljava/lang/Class;
    //   2956: invokevirtual getDeclaredMethods : ()[Ljava/lang/reflect/Method;
    //   2959: astore #5
    //   2961: aload #5
    //   2963: arraylength
    //   2964: istore #6
    //   2966: iconst_0
    //   2967: istore #7
    //   2969: iload #7
    //   2971: iload #6
    //   2973: if_icmpge -> 3106
    //   2976: aload #5
    //   2978: iload #7
    //   2980: aaload
    //   2981: astore #8
    //   2983: aload #8
    //   2985: invokevirtual getParameterTypes : ()[Ljava/lang/Class;
    //   2988: pop
    //   2989: aload #8
    //   2991: invokevirtual getModifiers : ()I
    //   2994: invokestatic isStatic : (I)Z
    //   2997: ifeq -> 3092
    //   3000: aload #8
    //   3002: invokevirtual getParameterTypes : ()[Ljava/lang/Class;
    //   3005: arraylength
    //   3006: iconst_2
    //   3007: if_icmpne -> 3092
    //   3010: goto -> 3017
    //   3013: invokestatic a : (Ljava/lang/Throwable;)Ljava/lang/Throwable;
    //   3016: athrow
    //   3017: aload #8
    //   3019: invokevirtual getReturnType : ()Ljava/lang/Class;
    //   3022: getstatic java/lang/Void.TYPE : Ljava/lang/Class;
    //   3025: invokevirtual equals : (Ljava/lang/Object;)Z
    //   3028: ifeq -> 3092
    //   3031: goto -> 3038
    //   3034: invokestatic a : (Ljava/lang/Throwable;)Ljava/lang/Throwable;
    //   3037: athrow
    //   3038: aload #8
    //   3040: iconst_1
    //   3041: invokevirtual setAccessible : (Z)V
    //   3044: aload #8
    //   3046: aconst_null
    //   3047: iconst_2
    //   3048: anewarray java/lang/Object
    //   3051: dup
    //   3052: iconst_0
    //   3053: aload_0
    //   3054: aastore
    //   3055: dup
    //   3056: iconst_1
    //   3057: aload_1
    //   3058: ifnonnull -> 3076
    //   3061: goto -> 3068
    //   3064: invokestatic a : (Ljava/lang/Throwable;)Ljava/lang/Throwable;
    //   3067: athrow
    //   3068: aload_1
    //   3069: goto -> 3083
    //   3072: invokestatic a : (Ljava/lang/Throwable;)Ljava/lang/Throwable;
    //   3075: athrow
    //   3076: aload_1
    //   3077: checkcast [B
    //   3080: invokevirtual clone : ()Ljava/lang/Object;
    //   3083: aastore
    //   3084: invokevirtual invoke : (Ljava/lang/Object;[Ljava/lang/Object;)Ljava/lang/Object;
    //   3087: pop
    //   3088: iload_2
    //   3089: ifne -> 3106
    //   3092: iinc #7, 1
    //   3095: iload_2
    //   3096: ifne -> 2969
    //   3099: goto -> 3106
    //   3102: invokestatic a : (Ljava/lang/Throwable;)Ljava/lang/Throwable;
    //   3105: athrow
    //   3106: new java/io/ByteArrayOutputStream
    //   3109: dup
    //   3110: invokespecial <init> : ()V
    //   3113: astore #5
    //   3115: sipush #-8285
    //   3118: aload #5
    //   3120: sipush #202
    //   3123: invokevirtual write : (I)V
    //   3126: sipush #21472
    //   3129: aload #5
    //   3131: sipush #254
    //   3134: invokevirtual write : (I)V
    //   3137: aload #5
    //   3139: sipush #186
    //   3142: invokevirtual write : (I)V
    //   3145: aload #5
    //   3147: sipush #190
    //   3150: invokevirtual write : (I)V
    //   3153: aload #5
    //   3155: iconst_0
    //   3156: invokevirtual write : (I)V
    //   3159: aload #5
    //   3161: iconst_1
    //   3162: invokevirtual write : (I)V
    //   3165: aload #5
    //   3167: iconst_0
    //   3168: invokevirtual write : (I)V
    //   3171: aload #5
    //   3173: bipush #50
    //   3175: invokevirtual write : (I)V
    //   3178: aload #5
    //   3180: getstatic burp/Zbz_.ZU : Ljava/lang/Object;
    //   3183: checkcast java/math/BigInteger
    //   3186: invokevirtual toByteArray : ()[B
    //   3189: invokevirtual write : ([B)V
    //   3192: aload #5
    //   3194: getstatic burp/Zlo2.ZM : Ljava/lang/Object;
    //   3197: checkcast java/math/BigInteger
    //   3200: invokevirtual toByteArray : ()[B
    //   3203: invokevirtual write : ([B)V
    //   3206: aload #5
    //   3208: getstatic burp/Zkk6.Zb : Ljava/lang/Object;
    //   3211: checkcast java/math/BigInteger
    //   3214: invokevirtual toByteArray : ()[B
    //   3217: invokevirtual write : ([B)V
    //   3220: aload #5
    //   3222: invokevirtual toByteArray : ()[B
    //   3225: astore #6
    //   3227: aconst_null
    //   3228: astore #7
    //   3230: invokestatic a : (II)Ljava/lang/String;
    //   3233: invokestatic forName : (Ljava/lang/String;)Ljava/lang/Class;
    //   3236: invokevirtual getDeclaredMethods : ()[Ljava/lang/reflect/Method;
    //   3239: astore #8
    //   3241: aload #8
    //   3243: arraylength
    //   3244: istore #9
    //   3246: iconst_0
    //   3247: istore #10
    //   3249: iload #10
    //   3251: iload #9
    //   3253: if_icmpge -> 3381
    //   3256: aload #8
    //   3258: iload #10
    //   3260: aaload
    //   3261: astore #11
    //   3263: aload #11
    //   3265: invokevirtual getName : ()Ljava/lang/String;
    //   3268: sipush #-8259
    //   3271: sipush #27881
    //   3274: invokestatic a : (II)Ljava/lang/String;
    //   3277: invokevirtual equals : (Ljava/lang/Object;)Z
    //   3280: ifeq -> 3374
    //   3283: aload #11
    //   3285: invokevirtual getParameterTypes : ()[Ljava/lang/Class;
    //   3288: astore #12
    //   3290: aload #12
    //   3292: arraylength
    //   3293: iconst_4
    //   3294: if_icmpeq -> 3304
    //   3297: goto -> 3374
    //   3300: invokestatic a : (Ljava/lang/Throwable;)Ljava/lang/Throwable;
    //   3303: athrow
    //   3304: aload #12
    //   3306: iconst_0
    //   3307: aaload
    //   3308: ldc java/lang/String
    //   3310: if_acmpeq -> 3320
    //   3313: goto -> 3374
    //   3316: invokestatic a : (Ljava/lang/Throwable;)Ljava/lang/Throwable;
    //   3319: athrow
    //   3320: aload #12
    //   3322: iconst_1
    //   3323: aaload
    //   3324: ldc [B
    //   3326: if_acmpeq -> 3336
    //   3329: goto -> 3374
    //   3332: invokestatic a : (Ljava/lang/Throwable;)Ljava/lang/Throwable;
    //   3335: athrow
    //   3336: aload #12
    //   3338: iconst_2
    //   3339: aaload
    //   3340: getstatic java/lang/Integer.TYPE : Ljava/lang/Class;
    //   3343: if_acmpeq -> 3353
    //   3346: goto -> 3374
    //   3349: invokestatic a : (Ljava/lang/Throwable;)Ljava/lang/Throwable;
    //   3352: athrow
    //   3353: aload #12
    //   3355: iconst_3
    //   3356: aaload
    //   3357: getstatic java/lang/Integer.TYPE : Ljava/lang/Class;
    //   3360: if_acmpeq -> 3370
    //   3363: goto -> 3374
    //   3366: invokestatic a : (Ljava/lang/Throwable;)Ljava/lang/Throwable;
    //   3369: athrow
    //   3370: aload #11
    //   3372: astore #7
    //   3374: iinc #10, 1
    //   3377: iload_2
    //   3378: ifne -> 3249
    //   3381: aload #7
    //   3383: iconst_1
    //   3384: invokevirtual setAccessible : (Z)V
    //   3387: ldc burp/Zb6b
    //   3389: iconst_0
    //   3390: anewarray java/lang/Class
    //   3393: invokevirtual getDeclaredConstructor : ([Ljava/lang/Class;)Ljava/lang/reflect/Constructor;
    //   3396: astore #8
    //   3398: aload #8
    //   3400: iconst_1
    //   3401: invokevirtual setAccessible : (Z)V
    //   3404: aload #7
    //   3406: aload #8
    //   3408: iconst_0
    //   3409: anewarray java/lang/Object
    //   3412: invokevirtual newInstance : ([Ljava/lang/Object;)Ljava/lang/Object;
    //   3415: iconst_4
    //   3416: anewarray java/lang/Object
    //   3419: dup
    //   3420: iconst_0
    //   3421: sipush #-8263
    //   3424: sipush #-11990
    //   3427: invokestatic a : (II)Ljava/lang/String;
    //   3430: aastore
    //   3431: dup
    //   3432: iconst_1
    //   3433: aload #6
    //   3435: aastore
    //   3436: dup
    //   3437: iconst_2
    //   3438: iconst_0
    //   3439: invokestatic valueOf : (I)Ljava/lang/Integer;
    //   3442: aastore
    //   3443: dup
    //   3444: iconst_3
    //   3445: aload #6
    //   3447: arraylength
    //   3448: invokestatic valueOf : (I)Ljava/lang/Integer;
    //   3451: aastore
    //   3452: invokevirtual invoke : (Ljava/lang/Object;[Ljava/lang/Object;)Ljava/lang/Object;
    //   3455: pop
    //   3456: goto -> 3461
    //   3459: astore #5
    //   3461: iconst_0
    //   3462: istore #5
    //   3464: getstatic burp/Zejz.Zd : Ljava/lang/String;
    //   3467: getstatic burp/Zlc2.ZQ : Ljava/lang/Object;
    //   3470: checkcast java/math/BigInteger
    //   3473: invokevirtual intValue : ()I
    //   3476: bipush #32
    //   3478: irem
    //   3479: invokestatic abs : (I)I
    //   3482: invokevirtual charAt : (I)C
    //   3485: getstatic burp/Zbl4.Ze : Ljava/lang/String;
    //   3488: getstatic burp/Zmdf.ZH : Ljava/lang/Object;
    //   3491: checkcast java/math/BigInteger
    //   3494: invokevirtual intValue : ()I
    //   3497: bipush #32
    //   3499: irem
    //   3500: invokestatic abs : (I)I
    //   3503: invokevirtual charAt : (I)C
    //   3506: if_icmple -> 3852
    //   3509: sipush #-8280
    //   3512: sipush #-14446
    //   3515: invokestatic a : (II)Ljava/lang/String;
    //   3518: iconst_1
    //   3519: ldc burp/Zgyk
    //   3521: invokevirtual getClassLoader : ()Ljava/lang/ClassLoader;
    //   3524: invokestatic forName : (Ljava/lang/String;ZLjava/lang/ClassLoader;)Ljava/lang/Class;
    //   3527: invokevirtual getDeclaredFields : ()[Ljava/lang/reflect/Field;
    //   3530: astore #6
    //   3532: aload #6
    //   3534: arraylength
    //   3535: istore #7
    //   3537: iconst_0
    //   3538: istore #8
    //   3540: iload #8
    //   3542: iload #7
    //   3544: if_icmpge -> 3682
    //   3547: aload #6
    //   3549: iload #8
    //   3551: aaload
    //   3552: astore #9
    //   3554: aload #9
    //   3556: invokevirtual getModifiers : ()I
    //   3559: invokestatic isStatic : (I)Z
    //   3562: ifne -> 3572
    //   3565: goto -> 3675
    //   3568: invokestatic a : (Ljava/lang/Throwable;)Ljava/lang/Throwable;
    //   3571: athrow
    //   3572: aload #9
    //   3574: invokevirtual getType : ()Ljava/lang/Class;
    //   3577: astore #10
    //   3579: aload #10
    //   3581: ifnull -> 3662
    //   3584: aload #10
    //   3586: invokevirtual isPrimitive : ()Z
    //   3589: ifne -> 3662
    //   3592: goto -> 3599
    //   3595: invokestatic a : (Ljava/lang/Throwable;)Ljava/lang/Throwable;
    //   3598: athrow
    //   3599: aload #10
    //   3601: invokevirtual getPackage : ()Ljava/lang/Package;
    //   3604: ifnull -> 3662
    //   3607: goto -> 3614
    //   3610: invokestatic a : (Ljava/lang/Throwable;)Ljava/lang/Throwable;
    //   3613: athrow
    //   3614: aload #10
    //   3616: invokevirtual getPackage : ()Ljava/lang/Package;
    //   3619: invokevirtual getName : ()Ljava/lang/String;
    //   3622: ifnull -> 3662
    //   3625: goto -> 3632
    //   3628: invokestatic a : (Ljava/lang/Throwable;)Ljava/lang/Throwable;
    //   3631: athrow
    //   3632: aload #10
    //   3634: invokevirtual getPackage : ()Ljava/lang/Package;
    //   3637: invokevirtual getName : ()Ljava/lang/String;
    //   3640: sipush #-8282
    //   3643: sipush #7249
    //   3646: invokestatic a : (II)Ljava/lang/String;
    //   3649: invokevirtual startsWith : (Ljava/lang/String;)Z
    //   3652: ifne -> 3662
    //   3655: goto -> 3662
    //   3658: invokestatic a : (Ljava/lang/Throwable;)Ljava/lang/Throwable;
    //   3661: athrow
    //   3662: aload #9
    //   3664: iconst_1
    //   3665: invokevirtual setAccessible : (Z)V
    //   3668: aload #9
    //   3670: aconst_null
    //   3671: invokevirtual get : (Ljava/lang/Object;)Ljava/lang/Object;
    //   3674: pop
    //   3675: iinc #8, 1
    //   3678: iload_2
    //   3679: ifne -> 3540
    //   3682: sipush #-8264
    //   3685: sipush #26020
    //   3688: invokestatic a : (II)Ljava/lang/String;
    //   3691: invokestatic forName : (Ljava/lang/String;)Ljava/lang/Class;
    //   3694: invokevirtual getDeclaredMethods : ()[Ljava/lang/reflect/Method;
    //   3697: astore #6
    //   3699: aload #6
    //   3701: arraylength
    //   3702: istore #7
    //   3704: iconst_0
    //   3705: istore #8
    //   3707: iload #8
    //   3709: iload #7
    //   3711: if_icmpge -> 3848
    //   3714: aload #6
    //   3716: iload #8
    //   3718: aaload
    //   3719: astore #9
    //   3721: aload #9
    //   3723: invokevirtual getParameterTypes : ()[Ljava/lang/Class;
    //   3726: pop
    //   3727: aload #9
    //   3729: invokevirtual getModifiers : ()I
    //   3732: invokestatic isStatic : (I)Z
    //   3735: ifeq -> 3834
    //   3738: aload #9
    //   3740: invokevirtual getParameterTypes : ()[Ljava/lang/Class;
    //   3743: arraylength
    //   3744: iconst_2
    //   3745: if_icmpne -> 3834
    //   3748: goto -> 3755
    //   3751: invokestatic a : (Ljava/lang/Throwable;)Ljava/lang/Throwable;
    //   3754: athrow
    //   3755: aload #9
    //   3757: invokevirtual getReturnType : ()Ljava/lang/Class;
    //   3760: getstatic java/lang/Boolean.TYPE : Ljava/lang/Class;
    //   3763: if_acmpne -> 3834
    //   3766: goto -> 3773
    //   3769: invokestatic a : (Ljava/lang/Throwable;)Ljava/lang/Throwable;
    //   3772: athrow
    //   3773: aload #9
    //   3775: iconst_1
    //   3776: invokevirtual setAccessible : (Z)V
    //   3779: aload #9
    //   3781: aconst_null
    //   3782: iconst_2
    //   3783: anewarray java/lang/Object
    //   3786: dup
    //   3787: iconst_0
    //   3788: aload_0
    //   3789: aastore
    //   3790: dup
    //   3791: iconst_1
    //   3792: aload_1
    //   3793: ifnonnull -> 3811
    //   3796: goto -> 3803
    //   3799: invokestatic a : (Ljava/lang/Throwable;)Ljava/lang/Throwable;
    //   3802: athrow
    //   3803: aload_1
    //   3804: goto -> 3818
    //   3807: invokestatic a : (Ljava/lang/Throwable;)Ljava/lang/Throwable;
    //   3810: athrow
    //   3811: aload_1
    //   3812: checkcast [B
    //   3815: invokevirtual clone : ()Ljava/lang/Object;
    //   3818: aastore
    //   3819: invokevirtual invoke : (Ljava/lang/Object;[Ljava/lang/Object;)Ljava/lang/Object;
    //   3822: checkcast java/lang/Boolean
    //   3825: invokevirtual booleanValue : ()Z
    //   3828: istore #5
    //   3830: iload_2
    //   3831: ifne -> 3848
    //   3834: iinc #8, 1
    //   3837: iload_2
    //   3838: ifne -> 3707
    //   3841: goto -> 3848
    //   3844: invokestatic a : (Ljava/lang/Throwable;)Ljava/lang/Throwable;
    //   3847: athrow
    //   3848: iload_2
    //   3849: ifne -> 4191
    //   3852: sipush #-8265
    //   3855: sipush #-19138
    //   3858: invokestatic a : (II)Ljava/lang/String;
    //   3861: iconst_1
    //   3862: ldc burp/Ze7q
    //   3864: invokevirtual getClassLoader : ()Ljava/lang/ClassLoader;
    //   3867: invokestatic forName : (Ljava/lang/String;ZLjava/lang/ClassLoader;)Ljava/lang/Class;
    //   3870: invokevirtual getDeclaredFields : ()[Ljava/lang/reflect/Field;
    //   3873: astore #6
    //   3875: aload #6
    //   3877: arraylength
    //   3878: istore #7
    //   3880: iconst_0
    //   3881: istore #8
    //   3883: iload #8
    //   3885: iload #7
    //   3887: if_icmpge -> 4025
    //   3890: aload #6
    //   3892: iload #8
    //   3894: aaload
    //   3895: astore #9
    //   3897: aload #9
    //   3899: invokevirtual getModifiers : ()I
    //   3902: invokestatic isStatic : (I)Z
    //   3905: ifne -> 3915
    //   3908: goto -> 4018
    //   3911: invokestatic a : (Ljava/lang/Throwable;)Ljava/lang/Throwable;
    //   3914: athrow
    //   3915: aload #9
    //   3917: invokevirtual getType : ()Ljava/lang/Class;
    //   3920: astore #10
    //   3922: aload #10
    //   3924: ifnull -> 4005
    //   3927: aload #10
    //   3929: invokevirtual isPrimitive : ()Z
    //   3932: ifne -> 4005
    //   3935: goto -> 3942
    //   3938: invokestatic a : (Ljava/lang/Throwable;)Ljava/lang/Throwable;
    //   3941: athrow
    //   3942: aload #10
    //   3944: invokevirtual getPackage : ()Ljava/lang/Package;
    //   3947: ifnull -> 4005
    //   3950: goto -> 3957
    //   3953: invokestatic a : (Ljava/lang/Throwable;)Ljava/lang/Throwable;
    //   3956: athrow
    //   3957: aload #10
    //   3959: invokevirtual getPackage : ()Ljava/lang/Package;
    //   3962: invokevirtual getName : ()Ljava/lang/String;
    //   3965: ifnull -> 4005
    //   3968: goto -> 3975
    //   3971: invokestatic a : (Ljava/lang/Throwable;)Ljava/lang/Throwable;
    //   3974: athrow
    //   3975: aload #10
    //   3977: invokevirtual getPackage : ()Ljava/lang/Package;
    //   3980: invokevirtual getName : ()Ljava/lang/String;
    //   3983: sipush #-8282
    //   3986: sipush #7249
    //   3989: invokestatic a : (II)Ljava/lang/String;
    //   3992: invokevirtual startsWith : (Ljava/lang/String;)Z
    //   3995: ifne -> 4005
    //   3998: goto -> 4005
    //   4001: invokestatic a : (Ljava/lang/Throwable;)Ljava/lang/Throwable;
    //   4004: athrow
    //   4005: aload #9
    //   4007: iconst_1
    //   4008: invokevirtual setAccessible : (Z)V
    //   4011: aload #9
    //   4013: aconst_null
    //   4014: invokevirtual get : (Ljava/lang/Object;)Ljava/lang/Object;
    //   4017: pop
    //   4018: iinc #8, 1
    //   4021: iload_2
    //   4022: ifne -> 3883
    //   4025: sipush #-8275
    //   4028: sipush #-31052
    //   4031: invokestatic a : (II)Ljava/lang/String;
    //   4034: invokestatic forName : (Ljava/lang/String;)Ljava/lang/Class;
    //   4037: invokevirtual getDeclaredMethods : ()[Ljava/lang/reflect/Method;
    //   4040: astore #6
    //   4042: aload #6
    //   4044: arraylength
    //   4045: istore #7
    //   4047: iconst_0
    //   4048: istore #8
    //   4050: iload #8
    //   4052: iload #7
    //   4054: if_icmpge -> 4191
    //   4057: aload #6
    //   4059: iload #8
    //   4061: aaload
    //   4062: astore #9
    //   4064: aload #9
    //   4066: invokevirtual getParameterTypes : ()[Ljava/lang/Class;
    //   4069: pop
    //   4070: aload #9
    //   4072: invokevirtual getModifiers : ()I
    //   4075: invokestatic isStatic : (I)Z
    //   4078: ifeq -> 4177
    //   4081: aload #9
    //   4083: invokevirtual getParameterTypes : ()[Ljava/lang/Class;
    //   4086: arraylength
    //   4087: iconst_2
    //   4088: if_icmpne -> 4177
    //   4091: goto -> 4098
    //   4094: invokestatic a : (Ljava/lang/Throwable;)Ljava/lang/Throwable;
    //   4097: athrow
    //   4098: aload #9
    //   4100: invokevirtual getReturnType : ()Ljava/lang/Class;
    //   4103: getstatic java/lang/Boolean.TYPE : Ljava/lang/Class;
    //   4106: if_acmpne -> 4177
    //   4109: goto -> 4116
    //   4112: invokestatic a : (Ljava/lang/Throwable;)Ljava/lang/Throwable;
    //   4115: athrow
    //   4116: aload #9
    //   4118: iconst_1
    //   4119: invokevirtual setAccessible : (Z)V
    //   4122: aload #9
    //   4124: aconst_null
    //   4125: iconst_2
    //   4126: anewarray java/lang/Object
    //   4129: dup
    //   4130: iconst_0
    //   4131: aload_0
    //   4132: aastore
    //   4133: dup
    //   4134: iconst_1
    //   4135: aload_1
    //   4136: ifnonnull -> 4154
    //   4139: goto -> 4146
    //   4142: invokestatic a : (Ljava/lang/Throwable;)Ljava/lang/Throwable;
    //   4145: athrow
    //   4146: aload_1
    //   4147: goto -> 4161
    //   4150: invokestatic a : (Ljava/lang/Throwable;)Ljava/lang/Throwable;
    //   4153: athrow
    //   4154: aload_1
    //   4155: checkcast [B
    //   4158: invokevirtual clone : ()Ljava/lang/Object;
    //   4161: aastore
    //   4162: invokevirtual invoke : (Ljava/lang/Object;[Ljava/lang/Object;)Ljava/lang/Object;
    //   4165: checkcast java/lang/Boolean
    //   4168: invokevirtual booleanValue : ()Z
    //   4171: istore #5
    //   4173: iload_2
    //   4174: ifne -> 4191
    //   4177: iinc #8, 1
    //   4180: iload_2
    //   4181: ifne -> 4050
    //   4184: goto -> 4191
    //   4187: invokestatic a : (Ljava/lang/Throwable;)Ljava/lang/Throwable;
    //   4190: athrow
    //   4191: iload #5
    //   4193: ifeq -> 4199
    //   4196: iload #5
    //   4198: ireturn
    //   4199: getstatic burp/Zr2q.ZA : Ljava/lang/String;
    //   4202: getstatic burp/Zkdx.Zn : Ljava/lang/Object;
    //   4205: checkcast java/math/BigInteger
    //   4208: invokevirtual intValue : ()I
    //   4211: bipush #32
    //   4213: irem
    //   4214: invokestatic abs : (I)I
    //   4217: invokevirtual charAt : (I)C
    //   4220: getstatic burp/Zrkw.ZU : Ljava/lang/String;
    //   4223: getstatic burp/Zzl4.ZX : Ljava/lang/Object;
    //   4226: checkcast java/math/BigInteger
    //   4229: invokevirtual intValue : ()I
    //   4232: bipush #32
    //   4234: irem
    //   4235: invokestatic abs : (I)I
    //   4238: invokevirtual charAt : (I)C
    //   4241: if_icmple -> 4587
    //   4244: sipush #-8272
    //   4247: sipush #23255
    //   4250: invokestatic a : (II)Ljava/lang/String;
    //   4253: iconst_1
    //   4254: ldc burp/Zod
    //   4256: invokevirtual getClassLoader : ()Ljava/lang/ClassLoader;
    //   4259: invokestatic forName : (Ljava/lang/String;ZLjava/lang/ClassLoader;)Ljava/lang/Class;
    //   4262: invokevirtual getDeclaredFields : ()[Ljava/lang/reflect/Field;
    //   4265: astore #6
    //   4267: aload #6
    //   4269: arraylength
    //   4270: istore #7
    //   4272: iconst_0
    //   4273: istore #8
    //   4275: iload #8
    //   4277: iload #7
    //   4279: if_icmpge -> 4417
    //   4282: aload #6
    //   4284: iload #8
    //   4286: aaload
    //   4287: astore #9
    //   4289: aload #9
    //   4291: invokevirtual getModifiers : ()I
    //   4294: invokestatic isStatic : (I)Z
    //   4297: ifne -> 4307
    //   4300: goto -> 4410
    //   4303: invokestatic a : (Ljava/lang/Throwable;)Ljava/lang/Throwable;
    //   4306: athrow
    //   4307: aload #9
    //   4309: invokevirtual getType : ()Ljava/lang/Class;
    //   4312: astore #10
    //   4314: aload #10
    //   4316: ifnull -> 4397
    //   4319: aload #10
    //   4321: invokevirtual isPrimitive : ()Z
    //   4324: ifne -> 4397
    //   4327: goto -> 4334
    //   4330: invokestatic a : (Ljava/lang/Throwable;)Ljava/lang/Throwable;
    //   4333: athrow
    //   4334: aload #10
    //   4336: invokevirtual getPackage : ()Ljava/lang/Package;
    //   4339: ifnull -> 4397
    //   4342: goto -> 4349
    //   4345: invokestatic a : (Ljava/lang/Throwable;)Ljava/lang/Throwable;
    //   4348: athrow
    //   4349: aload #10
    //   4351: invokevirtual getPackage : ()Ljava/lang/Package;
    //   4354: invokevirtual getName : ()Ljava/lang/String;
    //   4357: ifnull -> 4397
    //   4360: goto -> 4367
    //   4363: invokestatic a : (Ljava/lang/Throwable;)Ljava/lang/Throwable;
    //   4366: athrow
    //   4367: aload #10
    //   4369: invokevirtual getPackage : ()Ljava/lang/Package;
    //   4372: invokevirtual getName : ()Ljava/lang/String;
    //   4375: sipush #-8282
    //   4378: sipush #7249
    //   4381: invokestatic a : (II)Ljava/lang/String;
    //   4384: invokevirtual startsWith : (Ljava/lang/String;)Z
    //   4387: ifne -> 4397
    //   4390: goto -> 4397
    //   4393: invokestatic a : (Ljava/lang/Throwable;)Ljava/lang/Throwable;
    //   4396: athrow
    //   4397: aload #9
    //   4399: iconst_1
    //   4400: invokevirtual setAccessible : (Z)V
    //   4403: aload #9
    //   4405: aconst_null
    //   4406: invokevirtual get : (Ljava/lang/Object;)Ljava/lang/Object;
    //   4409: pop
    //   4410: iinc #8, 1
    //   4413: iload_2
    //   4414: ifne -> 4275
    //   4417: sipush #-8288
    //   4420: sipush #3707
    //   4423: invokestatic a : (II)Ljava/lang/String;
    //   4426: invokestatic forName : (Ljava/lang/String;)Ljava/lang/Class;
    //   4429: invokevirtual getDeclaredMethods : ()[Ljava/lang/reflect/Method;
    //   4432: astore #6
    //   4434: aload #6
    //   4436: arraylength
    //   4437: istore #7
    //   4439: iconst_0
    //   4440: istore #8
    //   4442: iload #8
    //   4444: iload #7
    //   4446: if_icmpge -> 4583
    //   4449: aload #6
    //   4451: iload #8
    //   4453: aaload
    //   4454: astore #9
    //   4456: aload #9
    //   4458: invokevirtual getParameterTypes : ()[Ljava/lang/Class;
    //   4461: pop
    //   4462: aload #9
    //   4464: invokevirtual getModifiers : ()I
    //   4467: invokestatic isStatic : (I)Z
    //   4470: ifeq -> 4569
    //   4473: aload #9
    //   4475: invokevirtual getParameterTypes : ()[Ljava/lang/Class;
    //   4478: arraylength
    //   4479: iconst_2
    //   4480: if_icmpne -> 4569
    //   4483: goto -> 4490
    //   4486: invokestatic a : (Ljava/lang/Throwable;)Ljava/lang/Throwable;
    //   4489: athrow
    //   4490: aload #9
    //   4492: invokevirtual getReturnType : ()Ljava/lang/Class;
    //   4495: getstatic java/lang/Boolean.TYPE : Ljava/lang/Class;
    //   4498: if_acmpne -> 4569
    //   4501: goto -> 4508
    //   4504: invokestatic a : (Ljava/lang/Throwable;)Ljava/lang/Throwable;
    //   4507: athrow
    //   4508: aload #9
    //   4510: iconst_1
    //   4511: invokevirtual setAccessible : (Z)V
    //   4514: aload #9
    //   4516: aconst_null
    //   4517: iconst_2
    //   4518: anewarray java/lang/Object
    //   4521: dup
    //   4522: iconst_0
    //   4523: aload_0
    //   4524: aastore
    //   4525: dup
    //   4526: iconst_1
    //   4527: aload_1
    //   4528: ifnonnull -> 4546
    //   4531: goto -> 4538
    //   4534: invokestatic a : (Ljava/lang/Throwable;)Ljava/lang/Throwable;
    //   4537: athrow
    //   4538: aload_1
    //   4539: goto -> 4553
    //   4542: invokestatic a : (Ljava/lang/Throwable;)Ljava/lang/Throwable;
    //   4545: athrow
    //   4546: aload_1
    //   4547: checkcast [B
    //   4550: invokevirtual clone : ()Ljava/lang/Object;
    //   4553: aastore
    //   4554: invokevirtual invoke : (Ljava/lang/Object;[Ljava/lang/Object;)Ljava/lang/Object;
    //   4557: checkcast java/lang/Boolean
    //   4560: invokevirtual booleanValue : ()Z
    //   4563: istore #5
    //   4565: iload_2
    //   4566: ifne -> 4583
    //   4569: iinc #8, 1
    //   4572: iload_2
    //   4573: ifne -> 4442
    //   4576: goto -> 4583
    //   4579: invokestatic a : (Ljava/lang/Throwable;)Ljava/lang/Throwable;
    //   4582: athrow
    //   4583: iload_2
    //   4584: ifne -> 4926
    //   4587: sipush #-8260
    //   4590: sipush #13005
    //   4593: invokestatic a : (II)Ljava/lang/String;
    //   4596: iconst_1
    //   4597: ldc burp/Zrhu
    //   4599: invokevirtual getClassLoader : ()Ljava/lang/ClassLoader;
    //   4602: invokestatic forName : (Ljava/lang/String;ZLjava/lang/ClassLoader;)Ljava/lang/Class;
    //   4605: invokevirtual getDeclaredFields : ()[Ljava/lang/reflect/Field;
    //   4608: astore #6
    //   4610: aload #6
    //   4612: arraylength
    //   4613: istore #7
    //   4615: iconst_0
    //   4616: istore #8
    //   4618: iload #8
    //   4620: iload #7
    //   4622: if_icmpge -> 4760
    //   4625: aload #6
    //   4627: iload #8
    //   4629: aaload
    //   4630: astore #9
    //   4632: aload #9
    //   4634: invokevirtual getModifiers : ()I
    //   4637: invokestatic isStatic : (I)Z
    //   4640: ifne -> 4650
    //   4643: goto -> 4753
    //   4646: invokestatic a : (Ljava/lang/Throwable;)Ljava/lang/Throwable;
    //   4649: athrow
    //   4650: aload #9
    //   4652: invokevirtual getType : ()Ljava/lang/Class;
    //   4655: astore #10
    //   4657: aload #10
    //   4659: ifnull -> 4740
    //   4662: aload #10
    //   4664: invokevirtual isPrimitive : ()Z
    //   4667: ifne -> 4740
    //   4670: goto -> 4677
    //   4673: invokestatic a : (Ljava/lang/Throwable;)Ljava/lang/Throwable;
    //   4676: athrow
    //   4677: aload #10
    //   4679: invokevirtual getPackage : ()Ljava/lang/Package;
    //   4682: ifnull -> 4740
    //   4685: goto -> 4692
    //   4688: invokestatic a : (Ljava/lang/Throwable;)Ljava/lang/Throwable;
    //   4691: athrow
    //   4692: aload #10
    //   4694: invokevirtual getPackage : ()Ljava/lang/Package;
    //   4697: invokevirtual getName : ()Ljava/lang/String;
    //   4700: ifnull -> 4740
    //   4703: goto -> 4710
    //   4706: invokestatic a : (Ljava/lang/Throwable;)Ljava/lang/Throwable;
    //   4709: athrow
    //   4710: aload #10
    //   4712: invokevirtual getPackage : ()Ljava/lang/Package;
    //   4715: invokevirtual getName : ()Ljava/lang/String;
    //   4718: sipush #-8282
    //   4721: sipush #7249
    //   4724: invokestatic a : (II)Ljava/lang/String;
    //   4727: invokevirtual startsWith : (Ljava/lang/String;)Z
    //   4730: ifne -> 4740
    //   4733: goto -> 4740
    //   4736: invokestatic a : (Ljava/lang/Throwable;)Ljava/lang/Throwable;
    //   4739: athrow
    //   4740: aload #9
    //   4742: iconst_1
    //   4743: invokevirtual setAccessible : (Z)V
    //   4746: aload #9
    //   4748: aconst_null
    //   4749: invokevirtual get : (Ljava/lang/Object;)Ljava/lang/Object;
    //   4752: pop
    //   4753: iinc #8, 1
    //   4756: iload_2
    //   4757: ifne -> 4618
    //   4760: sipush #-8257
    //   4763: sipush #3252
    //   4766: invokestatic a : (II)Ljava/lang/String;
    //   4769: invokestatic forName : (Ljava/lang/String;)Ljava/lang/Class;
    //   4772: invokevirtual getDeclaredMethods : ()[Ljava/lang/reflect/Method;
    //   4775: astore #6
    //   4777: aload #6
    //   4779: arraylength
    //   4780: istore #7
    //   4782: iconst_0
    //   4783: istore #8
    //   4785: iload #8
    //   4787: iload #7
    //   4789: if_icmpge -> 4926
    //   4792: aload #6
    //   4794: iload #8
    //   4796: aaload
    //   4797: astore #9
    //   4799: aload #9
    //   4801: invokevirtual getParameterTypes : ()[Ljava/lang/Class;
    //   4804: pop
    //   4805: aload #9
    //   4807: invokevirtual getModifiers : ()I
    //   4810: invokestatic isStatic : (I)Z
    //   4813: ifeq -> 4912
    //   4816: aload #9
    //   4818: invokevirtual getParameterTypes : ()[Ljava/lang/Class;
    //   4821: arraylength
    //   4822: iconst_2
    //   4823: if_icmpne -> 4912
    //   4826: goto -> 4833
    //   4829: invokestatic a : (Ljava/lang/Throwable;)Ljava/lang/Throwable;
    //   4832: athrow
    //   4833: aload #9
    //   4835: invokevirtual getReturnType : ()Ljava/lang/Class;
    //   4838: getstatic java/lang/Boolean.TYPE : Ljava/lang/Class;
    //   4841: if_acmpne -> 4912
    //   4844: goto -> 4851
    //   4847: invokestatic a : (Ljava/lang/Throwable;)Ljava/lang/Throwable;
    //   4850: athrow
    //   4851: aload #9
    //   4853: iconst_1
    //   4854: invokevirtual setAccessible : (Z)V
    //   4857: aload #9
    //   4859: aconst_null
    //   4860: iconst_2
    //   4861: anewarray java/lang/Object
    //   4864: dup
    //   4865: iconst_0
    //   4866: aload_0
    //   4867: aastore
    //   4868: dup
    //   4869: iconst_1
    //   4870: aload_1
    //   4871: ifnonnull -> 4889
    //   4874: goto -> 4881
    //   4877: invokestatic a : (Ljava/lang/Throwable;)Ljava/lang/Throwable;
    //   4880: athrow
    //   4881: aload_1
    //   4882: goto -> 4896
    //   4885: invokestatic a : (Ljava/lang/Throwable;)Ljava/lang/Throwable;
    //   4888: athrow
    //   4889: aload_1
    //   4890: checkcast [B
    //   4893: invokevirtual clone : ()Ljava/lang/Object;
    //   4896: aastore
    //   4897: invokevirtual invoke : (Ljava/lang/Object;[Ljava/lang/Object;)Ljava/lang/Object;
    //   4900: checkcast java/lang/Boolean
    //   4903: invokevirtual booleanValue : ()Z
    //   4906: istore #5
    //   4908: iload_2
    //   4909: ifne -> 4926
    //   4912: iinc #8, 1
    //   4915: iload_2
    //   4916: ifne -> 4785
    //   4919: goto -> 4926
    //   4922: invokestatic a : (Ljava/lang/Throwable;)Ljava/lang/Throwable;
    //   4925: athrow
    //   4926: iload #5
    //   4928: ifeq -> 4934
    //   4931: iload #5
    //   4933: ireturn
    //   4934: getstatic burp/Zmc_.Zb : Ljava/lang/String;
    //   4937: getstatic burp/Zezi.ZQ : Ljava/lang/Object;
    //   4940: checkcast java/math/BigInteger
    //   4943: invokevirtual intValue : ()I
    //   4946: bipush #32
    //   4948: irem
    //   4949: invokestatic abs : (I)I
    //   4952: invokevirtual charAt : (I)C
    //   4955: getstatic burp/Zs5y.ZO : Ljava/lang/String;
    //   4958: getstatic burp/Zv8l.ZL : Ljava/lang/Object;
    //   4961: checkcast java/math/BigInteger
    //   4964: invokevirtual intValue : ()I
    //   4967: bipush #32
    //   4969: irem
    //   4970: invokestatic abs : (I)I
    //   4973: invokevirtual charAt : (I)C
    //   4976: if_icmpgt -> 5322
    //   4979: sipush #-8279
    //   4982: sipush #-25838
    //   4985: invokestatic a : (II)Ljava/lang/String;
    //   4988: iconst_1
    //   4989: ldc burp/Zeoa
    //   4991: invokevirtual getClassLoader : ()Ljava/lang/ClassLoader;
    //   4994: invokestatic forName : (Ljava/lang/String;ZLjava/lang/ClassLoader;)Ljava/lang/Class;
    //   4997: invokevirtual getDeclaredFields : ()[Ljava/lang/reflect/Field;
    //   5000: astore #6
    //   5002: aload #6
    //   5004: arraylength
    //   5005: istore #7
    //   5007: iconst_0
    //   5008: istore #8
    //   5010: iload #8
    //   5012: iload #7
    //   5014: if_icmpge -> 5152
    //   5017: aload #6
    //   5019: iload #8
    //   5021: aaload
    //   5022: astore #9
    //   5024: aload #9
    //   5026: invokevirtual getModifiers : ()I
    //   5029: invokestatic isStatic : (I)Z
    //   5032: ifne -> 5042
    //   5035: goto -> 5145
    //   5038: invokestatic a : (Ljava/lang/Throwable;)Ljava/lang/Throwable;
    //   5041: athrow
    //   5042: aload #9
    //   5044: invokevirtual getType : ()Ljava/lang/Class;
    //   5047: astore #10
    //   5049: aload #10
    //   5051: ifnull -> 5132
    //   5054: aload #10
    //   5056: invokevirtual isPrimitive : ()Z
    //   5059: ifne -> 5132
    //   5062: goto -> 5069
    //   5065: invokestatic a : (Ljava/lang/Throwable;)Ljava/lang/Throwable;
    //   5068: athrow
    //   5069: aload #10
    //   5071: invokevirtual getPackage : ()Ljava/lang/Package;
    //   5074: ifnull -> 5132
    //   5077: goto -> 5084
    //   5080: invokestatic a : (Ljava/lang/Throwable;)Ljava/lang/Throwable;
    //   5083: athrow
    //   5084: aload #10
    //   5086: invokevirtual getPackage : ()Ljava/lang/Package;
    //   5089: invokevirtual getName : ()Ljava/lang/String;
    //   5092: ifnull -> 5132
    //   5095: goto -> 5102
    //   5098: invokestatic a : (Ljava/lang/Throwable;)Ljava/lang/Throwable;
    //   5101: athrow
    //   5102: aload #10
    //   5104: invokevirtual getPackage : ()Ljava/lang/Package;
    //   5107: invokevirtual getName : ()Ljava/lang/String;
    //   5110: sipush #-8282
    //   5113: sipush #7249
    //   5116: invokestatic a : (II)Ljava/lang/String;
    //   5119: invokevirtual startsWith : (Ljava/lang/String;)Z
    //   5122: ifne -> 5132
    //   5125: goto -> 5132
    //   5128: invokestatic a : (Ljava/lang/Throwable;)Ljava/lang/Throwable;
    //   5131: athrow
    //   5132: aload #9
    //   5134: iconst_1
    //   5135: invokevirtual setAccessible : (Z)V
    //   5138: aload #9
    //   5140: aconst_null
    //   5141: invokevirtual get : (Ljava/lang/Object;)Ljava/lang/Object;
    //   5144: pop
    //   5145: iinc #8, 1
    //   5148: iload_2
    //   5149: ifne -> 5010
    //   5152: sipush #-8258
    //   5155: sipush #-19502
    //   5158: invokestatic a : (II)Ljava/lang/String;
    //   5161: invokestatic forName : (Ljava/lang/String;)Ljava/lang/Class;
    //   5164: invokevirtual getDeclaredMethods : ()[Ljava/lang/reflect/Method;
    //   5167: astore #6
    //   5169: aload #6
    //   5171: arraylength
    //   5172: istore #7
    //   5174: iconst_0
    //   5175: istore #8
    //   5177: iload #8
    //   5179: iload #7
    //   5181: if_icmpge -> 5318
    //   5184: aload #6
    //   5186: iload #8
    //   5188: aaload
    //   5189: astore #9
    //   5191: aload #9
    //   5193: invokevirtual getParameterTypes : ()[Ljava/lang/Class;
    //   5196: pop
    //   5197: aload #9
    //   5199: invokevirtual getModifiers : ()I
    //   5202: invokestatic isStatic : (I)Z
    //   5205: ifeq -> 5304
    //   5208: aload #9
    //   5210: invokevirtual getParameterTypes : ()[Ljava/lang/Class;
    //   5213: arraylength
    //   5214: iconst_2
    //   5215: if_icmpne -> 5304
    //   5218: goto -> 5225
    //   5221: invokestatic a : (Ljava/lang/Throwable;)Ljava/lang/Throwable;
    //   5224: athrow
    //   5225: aload #9
    //   5227: invokevirtual getReturnType : ()Ljava/lang/Class;
    //   5230: getstatic java/lang/Boolean.TYPE : Ljava/lang/Class;
    //   5233: if_acmpne -> 5304
    //   5236: goto -> 5243
    //   5239: invokestatic a : (Ljava/lang/Throwable;)Ljava/lang/Throwable;
    //   5242: athrow
    //   5243: aload #9
    //   5245: iconst_1
    //   5246: invokevirtual setAccessible : (Z)V
    //   5249: aload #9
    //   5251: aconst_null
    //   5252: iconst_2
    //   5253: anewarray java/lang/Object
    //   5256: dup
    //   5257: iconst_0
    //   5258: aload_0
    //   5259: aastore
    //   5260: dup
    //   5261: iconst_1
    //   5262: aload_1
    //   5263: ifnonnull -> 5281
    //   5266: goto -> 5273
    //   5269: invokestatic a : (Ljava/lang/Throwable;)Ljava/lang/Throwable;
    //   5272: athrow
    //   5273: aload_1
    //   5274: goto -> 5288
    //   5277: invokestatic a : (Ljava/lang/Throwable;)Ljava/lang/Throwable;
    //   5280: athrow
    //   5281: aload_1
    //   5282: checkcast [B
    //   5285: invokevirtual clone : ()Ljava/lang/Object;
    //   5288: aastore
    //   5289: invokevirtual invoke : (Ljava/lang/Object;[Ljava/lang/Object;)Ljava/lang/Object;
    //   5292: checkcast java/lang/Boolean
    //   5295: invokevirtual booleanValue : ()Z
    //   5298: istore #5
    //   5300: iload_2
    //   5301: ifne -> 5318
    //   5304: iinc #8, 1
    //   5307: iload_2
    //   5308: ifne -> 5177
    //   5311: goto -> 5318
    //   5314: invokestatic a : (Ljava/lang/Throwable;)Ljava/lang/Throwable;
    //   5317: athrow
    //   5318: iload_2
    //   5319: ifne -> 5661
    //   5322: sipush #-8267
    //   5325: sipush #-24370
    //   5328: invokestatic a : (II)Ljava/lang/String;
    //   5331: iconst_1
    //   5332: ldc burp/Zmcq
    //   5334: invokevirtual getClassLoader : ()Ljava/lang/ClassLoader;
    //   5337: invokestatic forName : (Ljava/lang/String;ZLjava/lang/ClassLoader;)Ljava/lang/Class;
    //   5340: invokevirtual getDeclaredFields : ()[Ljava/lang/reflect/Field;
    //   5343: astore #6
    //   5345: aload #6
    //   5347: arraylength
    //   5348: istore #7
    //   5350: iconst_0
    //   5351: istore #8
    //   5353: iload #8
    //   5355: iload #7
    //   5357: if_icmpge -> 5495
    //   5360: aload #6
    //   5362: iload #8
    //   5364: aaload
    //   5365: astore #9
    //   5367: aload #9
    //   5369: invokevirtual getModifiers : ()I
    //   5372: invokestatic isStatic : (I)Z
    //   5375: ifne -> 5385
    //   5378: goto -> 5488
    //   5381: invokestatic a : (Ljava/lang/Throwable;)Ljava/lang/Throwable;
    //   5384: athrow
    //   5385: aload #9
    //   5387: invokevirtual getType : ()Ljava/lang/Class;
    //   5390: astore #10
    //   5392: aload #10
    //   5394: ifnull -> 5475
    //   5397: aload #10
    //   5399: invokevirtual isPrimitive : ()Z
    //   5402: ifne -> 5475
    //   5405: goto -> 5412
    //   5408: invokestatic a : (Ljava/lang/Throwable;)Ljava/lang/Throwable;
    //   5411: athrow
    //   5412: aload #10
    //   5414: invokevirtual getPackage : ()Ljava/lang/Package;
    //   5417: ifnull -> 5475
    //   5420: goto -> 5427
    //   5423: invokestatic a : (Ljava/lang/Throwable;)Ljava/lang/Throwable;
    //   5426: athrow
    //   5427: aload #10
    //   5429: invokevirtual getPackage : ()Ljava/lang/Package;
    //   5432: invokevirtual getName : ()Ljava/lang/String;
    //   5435: ifnull -> 5475
    //   5438: goto -> 5445
    //   5441: invokestatic a : (Ljava/lang/Throwable;)Ljava/lang/Throwable;
    //   5444: athrow
    //   5445: aload #10
    //   5447: invokevirtual getPackage : ()Ljava/lang/Package;
    //   5450: invokevirtual getName : ()Ljava/lang/String;
    //   5453: sipush #-8282
    //   5456: sipush #7249
    //   5459: invokestatic a : (II)Ljava/lang/String;
    //   5462: invokevirtual startsWith : (Ljava/lang/String;)Z
    //   5465: ifne -> 5475
    //   5468: goto -> 5475
    //   5471: invokestatic a : (Ljava/lang/Throwable;)Ljava/lang/Throwable;
    //   5474: athrow
    //   5475: aload #9
    //   5477: iconst_1
    //   5478: invokevirtual setAccessible : (Z)V
    //   5481: aload #9
    //   5483: aconst_null
    //   5484: invokevirtual get : (Ljava/lang/Object;)Ljava/lang/Object;
    //   5487: pop
    //   5488: iinc #8, 1
    //   5491: iload_2
    //   5492: ifne -> 5353
    //   5495: sipush #-8262
    //   5498: sipush #-5071
    //   5501: invokestatic a : (II)Ljava/lang/String;
    //   5504: invokestatic forName : (Ljava/lang/String;)Ljava/lang/Class;
    //   5507: invokevirtual getDeclaredMethods : ()[Ljava/lang/reflect/Method;
    //   5510: astore #6
    //   5512: aload #6
    //   5514: arraylength
    //   5515: istore #7
    //   5517: iconst_0
    //   5518: istore #8
    //   5520: iload #8
    //   5522: iload #7
    //   5524: if_icmpge -> 5661
    //   5527: aload #6
    //   5529: iload #8
    //   5531: aaload
    //   5532: astore #9
    //   5534: aload #9
    //   5536: invokevirtual getParameterTypes : ()[Ljava/lang/Class;
    //   5539: pop
    //   5540: aload #9
    //   5542: invokevirtual getModifiers : ()I
    //   5545: invokestatic isStatic : (I)Z
    //   5548: ifeq -> 5647
    //   5551: aload #9
    //   5553: invokevirtual getParameterTypes : ()[Ljava/lang/Class;
    //   5556: arraylength
    //   5557: iconst_2
    //   5558: if_icmpne -> 5647
    //   5561: goto -> 5568
    //   5564: invokestatic a : (Ljava/lang/Throwable;)Ljava/lang/Throwable;
    //   5567: athrow
    //   5568: aload #9
    //   5570: invokevirtual getReturnType : ()Ljava/lang/Class;
    //   5573: getstatic java/lang/Boolean.TYPE : Ljava/lang/Class;
    //   5576: if_acmpne -> 5647
    //   5579: goto -> 5586
    //   5582: invokestatic a : (Ljava/lang/Throwable;)Ljava/lang/Throwable;
    //   5585: athrow
    //   5586: aload #9
    //   5588: iconst_1
    //   5589: invokevirtual setAccessible : (Z)V
    //   5592: aload #9
    //   5594: aconst_null
    //   5595: iconst_2
    //   5596: anewarray java/lang/Object
    //   5599: dup
    //   5600: iconst_0
    //   5601: aload_0
    //   5602: aastore
    //   5603: dup
    //   5604: iconst_1
    //   5605: aload_1
    //   5606: ifnonnull -> 5624
    //   5609: goto -> 5616
    //   5612: invokestatic a : (Ljava/lang/Throwable;)Ljava/lang/Throwable;
    //   5615: athrow
    //   5616: aload_1
    //   5617: goto -> 5631
    //   5620: invokestatic a : (Ljava/lang/Throwable;)Ljava/lang/Throwable;
    //   5623: athrow
    //   5624: aload_1
    //   5625: checkcast [B
    //   5628: invokevirtual clone : ()Ljava/lang/Object;
    //   5631: aastore
    //   5632: invokevirtual invoke : (Ljava/lang/Object;[Ljava/lang/Object;)Ljava/lang/Object;
    //   5635: checkcast java/lang/Boolean
    //   5638: invokevirtual booleanValue : ()Z
    //   5641: istore #5
    //   5643: iload_2
    //   5644: ifne -> 5661
    //   5647: iinc #8, 1
    //   5650: iload_2
    //   5651: ifne -> 5520
    //   5654: goto -> 5661
    //   5657: invokestatic a : (Ljava/lang/Throwable;)Ljava/lang/Throwable;
    //   5660: athrow
    //   5661: iload #5
    //   5663: ifeq -> 5669
    //   5666: iload #5
    //   5668: ireturn
    //   5669: getstatic burp/Zrd2.Zj : Ljava/lang/String;
    //   5672: getstatic burp/Ztvy.ZH : Ljava/lang/Object;
    //   5675: checkcast java/math/BigInteger
    //   5678: invokevirtual intValue : ()I
    //   5681: bipush #32
    //   5683: irem
    //   5684: invokestatic abs : (I)I
    //   5687: invokevirtual charAt : (I)C
    //   5690: getstatic burp/Zxt7.Zi : Ljava/lang/String;
    //   5693: getstatic burp/Zzgb.ZG : Ljava/lang/Object;
    //   5696: checkcast java/math/BigInteger
    //   5699: invokevirtual intValue : ()I
    //   5702: bipush #32
    //   5704: irem
    //   5705: invokestatic abs : (I)I
    //   5708: invokevirtual charAt : (I)C
    //   5711: if_icmpgt -> 6057
    //   5714: sipush #-8283
    //   5717: sipush #20834
    //   5720: invokestatic a : (II)Ljava/lang/String;
    //   5723: iconst_1
    //   5724: ldc burp/Zxyp
    //   5726: invokevirtual getClassLoader : ()Ljava/lang/ClassLoader;
    //   5729: invokestatic forName : (Ljava/lang/String;ZLjava/lang/ClassLoader;)Ljava/lang/Class;
    //   5732: invokevirtual getDeclaredFields : ()[Ljava/lang/reflect/Field;
    //   5735: astore #6
    //   5737: aload #6
    //   5739: arraylength
    //   5740: istore #7
    //   5742: iconst_0
    //   5743: istore #8
    //   5745: iload #8
    //   5747: iload #7
    //   5749: if_icmpge -> 5887
    //   5752: aload #6
    //   5754: iload #8
    //   5756: aaload
    //   5757: astore #9
    //   5759: aload #9
    //   5761: invokevirtual getModifiers : ()I
    //   5764: invokestatic isStatic : (I)Z
    //   5767: ifne -> 5777
    //   5770: goto -> 5880
    //   5773: invokestatic a : (Ljava/lang/Throwable;)Ljava/lang/Throwable;
    //   5776: athrow
    //   5777: aload #9
    //   5779: invokevirtual getType : ()Ljava/lang/Class;
    //   5782: astore #10
    //   5784: aload #10
    //   5786: ifnull -> 5867
    //   5789: aload #10
    //   5791: invokevirtual isPrimitive : ()Z
    //   5794: ifne -> 5867
    //   5797: goto -> 5804
    //   5800: invokestatic a : (Ljava/lang/Throwable;)Ljava/lang/Throwable;
    //   5803: athrow
    //   5804: aload #10
    //   5806: invokevirtual getPackage : ()Ljava/lang/Package;
    //   5809: ifnull -> 5867
    //   5812: goto -> 5819
    //   5815: invokestatic a : (Ljava/lang/Throwable;)Ljava/lang/Throwable;
    //   5818: athrow
    //   5819: aload #10
    //   5821: invokevirtual getPackage : ()Ljava/lang/Package;
    //   5824: invokevirtual getName : ()Ljava/lang/String;
    //   5827: ifnull -> 5867
    //   5830: goto -> 5837
    //   5833: invokestatic a : (Ljava/lang/Throwable;)Ljava/lang/Throwable;
    //   5836: athrow
    //   5837: aload #10
    //   5839: invokevirtual getPackage : ()Ljava/lang/Package;
    //   5842: invokevirtual getName : ()Ljava/lang/String;
    //   5845: sipush #-8282
    //   5848: sipush #7249
    //   5851: invokestatic a : (II)Ljava/lang/String;
    //   5854: invokevirtual startsWith : (Ljava/lang/String;)Z
    //   5857: ifne -> 5867
    //   5860: goto -> 5867
    //   5863: invokestatic a : (Ljava/lang/Throwable;)Ljava/lang/Throwable;
    //   5866: athrow
    //   5867: aload #9
    //   5869: iconst_1
    //   5870: invokevirtual setAccessible : (Z)V
    //   5873: aload #9
    //   5875: aconst_null
    //   5876: invokevirtual get : (Ljava/lang/Object;)Ljava/lang/Object;
    //   5879: pop
    //   5880: iinc #8, 1
    //   5883: iload_2
    //   5884: ifne -> 5745
    //   5887: sipush #-8278
    //   5890: sipush #27897
    //   5893: invokestatic a : (II)Ljava/lang/String;
    //   5896: invokestatic forName : (Ljava/lang/String;)Ljava/lang/Class;
    //   5899: invokevirtual getDeclaredMethods : ()[Ljava/lang/reflect/Method;
    //   5902: astore #6
    //   5904: aload #6
    //   5906: arraylength
    //   5907: istore #7
    //   5909: iconst_0
    //   5910: istore #8
    //   5912: iload #8
    //   5914: iload #7
    //   5916: if_icmpge -> 6053
    //   5919: aload #6
    //   5921: iload #8
    //   5923: aaload
    //   5924: astore #9
    //   5926: aload #9
    //   5928: invokevirtual getParameterTypes : ()[Ljava/lang/Class;
    //   5931: pop
    //   5932: aload #9
    //   5934: invokevirtual getModifiers : ()I
    //   5937: invokestatic isStatic : (I)Z
    //   5940: ifeq -> 6039
    //   5943: aload #9
    //   5945: invokevirtual getParameterTypes : ()[Ljava/lang/Class;
    //   5948: arraylength
    //   5949: iconst_2
    //   5950: if_icmpne -> 6039
    //   5953: goto -> 5960
    //   5956: invokestatic a : (Ljava/lang/Throwable;)Ljava/lang/Throwable;
    //   5959: athrow
    //   5960: aload #9
    //   5962: invokevirtual getReturnType : ()Ljava/lang/Class;
    //   5965: getstatic java/lang/Boolean.TYPE : Ljava/lang/Class;
    //   5968: if_acmpne -> 6039
    //   5971: goto -> 5978
    //   5974: invokestatic a : (Ljava/lang/Throwable;)Ljava/lang/Throwable;
    //   5977: athrow
    //   5978: aload #9
    //   5980: iconst_1
    //   5981: invokevirtual setAccessible : (Z)V
    //   5984: aload #9
    //   5986: aconst_null
    //   5987: iconst_2
    //   5988: anewarray java/lang/Object
    //   5991: dup
    //   5992: iconst_0
    //   5993: aload_0
    //   5994: aastore
    //   5995: dup
    //   5996: iconst_1
    //   5997: aload_1
    //   5998: ifnonnull -> 6016
    //   6001: goto -> 6008
    //   6004: invokestatic a : (Ljava/lang/Throwable;)Ljava/lang/Throwable;
    //   6007: athrow
    //   6008: aload_1
    //   6009: goto -> 6023
    //   6012: invokestatic a : (Ljava/lang/Throwable;)Ljava/lang/Throwable;
    //   6015: athrow
    //   6016: aload_1
    //   6017: checkcast [B
    //   6020: invokevirtual clone : ()Ljava/lang/Object;
    //   6023: aastore
    //   6024: invokevirtual invoke : (Ljava/lang/Object;[Ljava/lang/Object;)Ljava/lang/Object;
    //   6027: checkcast java/lang/Boolean
    //   6030: invokevirtual booleanValue : ()Z
    //   6033: istore #5
    //   6035: iload_2
    //   6036: ifne -> 6053
    //   6039: iinc #8, 1
    //   6042: iload_2
    //   6043: ifne -> 5912
    //   6046: goto -> 6053
    //   6049: invokestatic a : (Ljava/lang/Throwable;)Ljava/lang/Throwable;
    //   6052: athrow
    //   6053: iload_2
    //   6054: ifne -> 6396
    //   6057: sipush #-8269
    //   6060: sipush #30876
    //   6063: invokestatic a : (II)Ljava/lang/String;
    //   6066: iconst_1
    //   6067: ldc burp/Zs26
    //   6069: invokevirtual getClassLoader : ()Ljava/lang/ClassLoader;
    //   6072: invokestatic forName : (Ljava/lang/String;ZLjava/lang/ClassLoader;)Ljava/lang/Class;
    //   6075: invokevirtual getDeclaredFields : ()[Ljava/lang/reflect/Field;
    //   6078: astore #6
    //   6080: aload #6
    //   6082: arraylength
    //   6083: istore #7
    //   6085: iconst_0
    //   6086: istore #8
    //   6088: iload #8
    //   6090: iload #7
    //   6092: if_icmpge -> 6230
    //   6095: aload #6
    //   6097: iload #8
    //   6099: aaload
    //   6100: astore #9
    //   6102: aload #9
    //   6104: invokevirtual getModifiers : ()I
    //   6107: invokestatic isStatic : (I)Z
    //   6110: ifne -> 6120
    //   6113: goto -> 6223
    //   6116: invokestatic a : (Ljava/lang/Throwable;)Ljava/lang/Throwable;
    //   6119: athrow
    //   6120: aload #9
    //   6122: invokevirtual getType : ()Ljava/lang/Class;
    //   6125: astore #10
    //   6127: aload #10
    //   6129: ifnull -> 6210
    //   6132: aload #10
    //   6134: invokevirtual isPrimitive : ()Z
    //   6137: ifne -> 6210
    //   6140: goto -> 6147
    //   6143: invokestatic a : (Ljava/lang/Throwable;)Ljava/lang/Throwable;
    //   6146: athrow
    //   6147: aload #10
    //   6149: invokevirtual getPackage : ()Ljava/lang/Package;
    //   6152: ifnull -> 6210
    //   6155: goto -> 6162
    //   6158: invokestatic a : (Ljava/lang/Throwable;)Ljava/lang/Throwable;
    //   6161: athrow
    //   6162: aload #10
    //   6164: invokevirtual getPackage : ()Ljava/lang/Package;
    //   6167: invokevirtual getName : ()Ljava/lang/String;
    //   6170: ifnull -> 6210
    //   6173: goto -> 6180
    //   6176: invokestatic a : (Ljava/lang/Throwable;)Ljava/lang/Throwable;
    //   6179: athrow
    //   6180: aload #10
    //   6182: invokevirtual getPackage : ()Ljava/lang/Package;
    //   6185: invokevirtual getName : ()Ljava/lang/String;
    //   6188: sipush #-8282
    //   6191: sipush #7249
    //   6194: invokestatic a : (II)Ljava/lang/String;
    //   6197: invokevirtual startsWith : (Ljava/lang/String;)Z
    //   6200: ifne -> 6210
    //   6203: goto -> 6210
    //   6206: invokestatic a : (Ljava/lang/Throwable;)Ljava/lang/Throwable;
    //   6209: athrow
    //   6210: aload #9
    //   6212: iconst_1
    //   6213: invokevirtual setAccessible : (Z)V
    //   6216: aload #9
    //   6218: aconst_null
    //   6219: invokevirtual get : (Ljava/lang/Object;)Ljava/lang/Object;
    //   6222: pop
    //   6223: iinc #8, 1
    //   6226: iload_2
    //   6227: ifne -> 6088
    //   6230: sipush #-8266
    //   6233: sipush #14373
    //   6236: invokestatic a : (II)Ljava/lang/String;
    //   6239: invokestatic forName : (Ljava/lang/String;)Ljava/lang/Class;
    //   6242: invokevirtual getDeclaredMethods : ()[Ljava/lang/reflect/Method;
    //   6245: astore #6
    //   6247: aload #6
    //   6249: arraylength
    //   6250: istore #7
    //   6252: iconst_0
    //   6253: istore #8
    //   6255: iload #8
    //   6257: iload #7
    //   6259: if_icmpge -> 6396
    //   6262: aload #6
    //   6264: iload #8
    //   6266: aaload
    //   6267: astore #9
    //   6269: aload #9
    //   6271: invokevirtual getParameterTypes : ()[Ljava/lang/Class;
    //   6274: pop
    //   6275: aload #9
    //   6277: invokevirtual getModifiers : ()I
    //   6280: invokestatic isStatic : (I)Z
    //   6283: ifeq -> 6382
    //   6286: aload #9
    //   6288: invokevirtual getParameterTypes : ()[Ljava/lang/Class;
    //   6291: arraylength
    //   6292: iconst_2
    //   6293: if_icmpne -> 6382
    //   6296: goto -> 6303
    //   6299: invokestatic a : (Ljava/lang/Throwable;)Ljava/lang/Throwable;
    //   6302: athrow
    //   6303: aload #9
    //   6305: invokevirtual getReturnType : ()Ljava/lang/Class;
    //   6308: getstatic java/lang/Boolean.TYPE : Ljava/lang/Class;
    //   6311: if_acmpne -> 6382
    //   6314: goto -> 6321
    //   6317: invokestatic a : (Ljava/lang/Throwable;)Ljava/lang/Throwable;
    //   6320: athrow
    //   6321: aload #9
    //   6323: iconst_1
    //   6324: invokevirtual setAccessible : (Z)V
    //   6327: aload #9
    //   6329: aconst_null
    //   6330: iconst_2
    //   6331: anewarray java/lang/Object
    //   6334: dup
    //   6335: iconst_0
    //   6336: aload_0
    //   6337: aastore
    //   6338: dup
    //   6339: iconst_1
    //   6340: aload_1
    //   6341: ifnonnull -> 6359
    //   6344: goto -> 6351
    //   6347: invokestatic a : (Ljava/lang/Throwable;)Ljava/lang/Throwable;
    //   6350: athrow
    //   6351: aload_1
    //   6352: goto -> 6366
    //   6355: invokestatic a : (Ljava/lang/Throwable;)Ljava/lang/Throwable;
    //   6358: athrow
    //   6359: aload_1
    //   6360: checkcast [B
    //   6363: invokevirtual clone : ()Ljava/lang/Object;
    //   6366: aastore
    //   6367: invokevirtual invoke : (Ljava/lang/Object;[Ljava/lang/Object;)Ljava/lang/Object;
    //   6370: checkcast java/lang/Boolean
    //   6373: invokevirtual booleanValue : ()Z
    //   6376: istore #5
    //   6378: iload_2
    //   6379: ifne -> 6396
    //   6382: iinc #8, 1
    //   6385: iload_2
    //   6386: ifne -> 6255
    //   6389: goto -> 6396
    //   6392: invokestatic a : (Ljava/lang/Throwable;)Ljava/lang/Throwable;
    //   6395: athrow
    //   6396: iload #5
    //   6398: ireturn
    //   6399: astore_3
    //   6400: new java/lang/Exception
    //   6403: dup
    //   6404: aload_3
    //   6405: invokevirtual getMessage : ()Ljava/lang/String;
    //   6408: invokespecial <init> : (Ljava/lang/String;)V
    //   6411: athrow
    // Exception table:
    //   from	to	target	type
    //   4	4198	6399	java/lang/Throwable
    //   22	198	201	java/lang/Throwable
    //   168	235	238	java/lang/Throwable
    //   205	272	275	java/lang/Throwable
    //   242	309	312	java/lang/Throwable
    //   279	346	349	java/lang/Throwable
    //   316	383	386	java/lang/Throwable
    //   353	420	423	java/lang/Throwable
    //   390	457	460	java/lang/Throwable
    //   427	494	497	java/lang/Throwable
    //   464	531	534	java/lang/Throwable
    //   501	568	571	java/lang/Throwable
    //   538	605	608	java/lang/Throwable
    //   575	642	645	java/lang/Throwable
    //   612	679	682	java/lang/Throwable
    //   649	716	719	java/lang/Throwable
    //   686	753	756	java/lang/Throwable
    //   723	790	793	java/lang/Throwable
    //   760	827	830	java/lang/Throwable
    //   797	864	867	java/lang/Throwable
    //   834	901	904	java/lang/Throwable
    //   871	938	941	java/lang/Throwable
    //   908	975	978	java/lang/Throwable
    //   945	1012	1015	java/lang/Throwable
    //   982	1049	1052	java/lang/Throwable
    //   1019	1086	1089	java/lang/Throwable
    //   1056	1123	1126	java/lang/Throwable
    //   1093	1160	1163	java/lang/Throwable
    //   1130	1197	1200	java/lang/Throwable
    //   1167	1234	1237	java/lang/Throwable
    //   1204	1271	1274	java/lang/Throwable
    //   1241	1308	1311	java/lang/Throwable
    //   1278	1341	1344	java/lang/Throwable
    //   1399	1575	1578	java/lang/Throwable
    //   1544	1613	1616	java/lang/Throwable
    //   1582	1651	1654	java/lang/Throwable
    //   1620	1689	1692	java/lang/Throwable
    //   1658	1727	1730	java/lang/Throwable
    //   1696	1765	1768	java/lang/Throwable
    //   1734	1803	1806	java/lang/Throwable
    //   1772	1841	1844	java/lang/Throwable
    //   1810	1879	1882	java/lang/Throwable
    //   1848	1917	1920	java/lang/Throwable
    //   1886	1955	1958	java/lang/Throwable
    //   1924	1993	1996	java/lang/Throwable
    //   1962	2031	2034	java/lang/Throwable
    //   2000	2069	2072	java/lang/Throwable
    //   2038	2107	2110	java/lang/Throwable
    //   2076	2145	2148	java/lang/Throwable
    //   2114	2183	2186	java/lang/Throwable
    //   2152	2221	2224	java/lang/Throwable
    //   2190	2259	2262	java/lang/Throwable
    //   2228	2297	2300	java/lang/Throwable
    //   2266	2335	2338	java/lang/Throwable
    //   2304	2373	2376	java/lang/Throwable
    //   2342	2411	2414	java/lang/Throwable
    //   2380	2449	2452	java/lang/Throwable
    //   2418	2487	2490	java/lang/Throwable
    //   2456	2525	2528	java/lang/Throwable
    //   2494	2563	2566	java/lang/Throwable
    //   2532	2601	2604	java/lang/Throwable
    //   2570	2639	2642	java/lang/Throwable
    //   2608	2677	2680	java/lang/Throwable
    //   2646	2715	2718	java/lang/Throwable
    //   2684	2749	2752	java/lang/Throwable
    //   2816	2830	2830	java/lang/Throwable
    //   2841	2854	2857	java/lang/Throwable
    //   2846	2869	2872	java/lang/Throwable
    //   2861	2887	2890	java/lang/Throwable
    //   2876	2917	2920	java/lang/Throwable
    //   2983	3010	3013	java/lang/Throwable
    //   3000	3031	3034	java/lang/Throwable
    //   3017	3061	3064	java/lang/Throwable
    //   3038	3072	3072	java/lang/Throwable
    //   3083	3099	3102	java/lang/Throwable
    //   3106	3456	3459	java/lang/Throwable
    //   3290	3300	3300	java/lang/Throwable
    //   3304	3316	3316	java/lang/Throwable
    //   3320	3332	3332	java/lang/Throwable
    //   3336	3349	3349	java/lang/Throwable
    //   3353	3366	3366	java/lang/Throwable
    //   3554	3568	3568	java/lang/Throwable
    //   3579	3592	3595	java/lang/Throwable
    //   3584	3607	3610	java/lang/Throwable
    //   3599	3625	3628	java/lang/Throwable
    //   3614	3655	3658	java/lang/Throwable
    //   3721	3748	3751	java/lang/Throwable
    //   3738	3766	3769	java/lang/Throwable
    //   3755	3796	3799	java/lang/Throwable
    //   3773	3807	3807	java/lang/Throwable
    //   3830	3841	3844	java/lang/Throwable
    //   3897	3911	3911	java/lang/Throwable
    //   3922	3935	3938	java/lang/Throwable
    //   3927	3950	3953	java/lang/Throwable
    //   3942	3968	3971	java/lang/Throwable
    //   3957	3998	4001	java/lang/Throwable
    //   4064	4091	4094	java/lang/Throwable
    //   4081	4109	4112	java/lang/Throwable
    //   4098	4139	4142	java/lang/Throwable
    //   4116	4150	4150	java/lang/Throwable
    //   4173	4184	4187	java/lang/Throwable
    //   4199	4933	6399	java/lang/Throwable
    //   4289	4303	4303	java/lang/Throwable
    //   4314	4327	4330	java/lang/Throwable
    //   4319	4342	4345	java/lang/Throwable
    //   4334	4360	4363	java/lang/Throwable
    //   4349	4390	4393	java/lang/Throwable
    //   4456	4483	4486	java/lang/Throwable
    //   4473	4501	4504	java/lang/Throwable
    //   4490	4531	4534	java/lang/Throwable
    //   4508	4542	4542	java/lang/Throwable
    //   4565	4576	4579	java/lang/Throwable
    //   4632	4646	4646	java/lang/Throwable
    //   4657	4670	4673	java/lang/Throwable
    //   4662	4685	4688	java/lang/Throwable
    //   4677	4703	4706	java/lang/Throwable
    //   4692	4733	4736	java/lang/Throwable
    //   4799	4826	4829	java/lang/Throwable
    //   4816	4844	4847	java/lang/Throwable
    //   4833	4874	4877	java/lang/Throwable
    //   4851	4885	4885	java/lang/Throwable
    //   4908	4919	4922	java/lang/Throwable
    //   4934	5668	6399	java/lang/Throwable
    //   5024	5038	5038	java/lang/Throwable
    //   5049	5062	5065	java/lang/Throwable
    //   5054	5077	5080	java/lang/Throwable
    //   5069	5095	5098	java/lang/Throwable
    //   5084	5125	5128	java/lang/Throwable
    //   5191	5218	5221	java/lang/Throwable
    //   5208	5236	5239	java/lang/Throwable
    //   5225	5266	5269	java/lang/Throwable
    //   5243	5277	5277	java/lang/Throwable
    //   5300	5311	5314	java/lang/Throwable
    //   5367	5381	5381	java/lang/Throwable
    //   5392	5405	5408	java/lang/Throwable
    //   5397	5420	5423	java/lang/Throwable
    //   5412	5438	5441	java/lang/Throwable
    //   5427	5468	5471	java/lang/Throwable
    //   5534	5561	5564	java/lang/Throwable
    //   5551	5579	5582	java/lang/Throwable
    //   5568	5609	5612	java/lang/Throwable
    //   5586	5620	5620	java/lang/Throwable
    //   5643	5654	5657	java/lang/Throwable
    //   5669	6398	6399	java/lang/Throwable
    //   5759	5773	5773	java/lang/Throwable
    //   5784	5797	5800	java/lang/Throwable
    //   5789	5812	5815	java/lang/Throwable
    //   5804	5830	5833	java/lang/Throwable
    //   5819	5860	5863	java/lang/Throwable
    //   5926	5953	5956	java/lang/Throwable
    //   5943	5971	5974	java/lang/Throwable
    //   5960	6001	6004	java/lang/Throwable
    //   5978	6012	6012	java/lang/Throwable
    //   6035	6046	6049	java/lang/Throwable
    //   6102	6116	6116	java/lang/Throwable
    //   6127	6140	6143	java/lang/Throwable
    //   6132	6155	6158	java/lang/Throwable
    //   6147	6173	6176	java/lang/Throwable
    //   6162	6203	6206	java/lang/Throwable
    //   6269	6296	6299	java/lang/Throwable
    //   6286	6314	6317	java/lang/Throwable
    //   6303	6344	6347	java/lang/Throwable
    //   6321	6355	6355	java/lang/Throwable
    //   6378	6389	6392	java/lang/Throwable
  }
  
  static void Zs(Object[] paramArrayOfObject, Object paramObject) throws Throwable {}
  
  static void Ze(Object paramObject) {
    Zrb6.ZP = a(-8268, -26825);
    Zrb6.ZQ = new BigInteger(a(-8286, -17058));
    boolean bool = Zt2e.ZK();
    try {
      try {
        if (Zz7j.ZP.charAt(Math.abs(((BigInteger)Ztl6.ZQ).intValue() % 32)) > Zm8j.Zp.charAt(Math.abs(((BigInteger)Ze25.ZW).intValue() % 32))) {
          try {
            Zzc9.ZF(Class.forName(a(-8271, 10455)));
            if (bool)
              Zeb7.ZG(Class.forName(a(-8277, 307))); 
          } catch (Throwable throwable) {
            throw a(null);
          } 
          return;
        } 
      } catch (Throwable throwable) {
        throw a(null);
      } 
      Zeb7.ZG(Class.forName(a(-8277, 307)));
    } catch (Throwable throwable) {}
  }
  
  static {
    // Byte code:
    //   0: bipush #29
    //   2: anewarray java/lang/String
    //   5: astore #5
    //   7: iconst_0
    //   8: istore_3
    //   9: ldc 'Za\\tBUP"}\\t]\\tCv4ms\\t$D6T X+w!&Q1%LiRWy+D\\rvq\\t8\\t)W\\t}\\rU\\bs65\\t7" fZMdVJc)_Ww<!w ?V\\t8OS:Doe\\tXWe\\t`&Ay\\tsr\\t_R\\tS'GB!r1R0kM.}Im$Va~NB62O \\bB*4|Ui6ou4\\toC?F\\n>HiM6c*>G{Tt{.xn#}HZ,RHeP3i9iG<@yOG\\tfbb<o\\t,)+K\\tt='
    //   11: dup
    //   12: astore_2
    //   13: invokevirtual length : ()I
    //   16: istore #4
    //   18: bipush #9
    //   20: istore_1
    //   21: iconst_m1
    //   22: istore_0
    //   23: bipush #64
    //   25: iinc #0, 1
    //   28: aload_2
    //   29: iload_0
    //   30: dup
    //   31: iload_1
    //   32: iadd
    //   33: invokevirtual substring : (II)Ljava/lang/String;
    //   36: iconst_m1
    //   37: goto -> 142
    //   40: aload #5
    //   42: swap
    //   43: iload_3
    //   44: iinc #3, 1
    //   47: swap
    //   48: aastore
    //   49: iload_0
    //   50: iload_1
    //   51: iadd
    //   52: dup
    //   53: istore_0
    //   54: iload #4
    //   56: if_icmpge -> 68
    //   59: aload_2
    //   60: iload_0
    //   61: invokevirtual charAt : (I)C
    //   64: istore_1
    //   65: goto -> 23
    //   68: ldc 'E_+\\ttpg*'
    //   70: dup
    //   71: astore_2
    //   72: invokevirtual length : ()I
    //   75: istore #4
    //   77: bipush #9
    //   79: istore_1
    //   80: iconst_m1
    //   81: istore_0
    //   82: iconst_1
    //   83: iinc #0, 1
    //   86: aload_2
    //   87: iload_0
    //   88: dup
    //   89: iload_1
    //   90: iadd
    //   91: invokevirtual substring : (II)Ljava/lang/String;
    //   94: iconst_0
    //   95: goto -> 142
    //   98: aload #5
    //   100: swap
    //   101: iload_3
    //   102: iinc #3, 1
    //   105: swap
    //   106: aastore
    //   107: iload_0
    //   108: iload_1
    //   109: iadd
    //   110: dup
    //   111: istore_0
    //   112: iload #4
    //   114: if_icmpge -> 126
    //   117: aload_2
    //   118: iload_0
    //   119: invokevirtual charAt : (I)C
    //   122: istore_1
    //   123: goto -> 82
    //   126: aload #5
    //   128: putstatic burp/Zz91.a : [Ljava/lang/String;
    //   131: bipush #29
    //   133: anewarray java/lang/String
    //   136: putstatic burp/Zz91.b : [Ljava/lang/String;
    //   139: goto -> 300
    //   142: dup_x2
    //   143: pop
    //   144: invokevirtual toCharArray : ()[C
    //   147: dup_x1
    //   148: arraylength
    //   149: dup_x2
    //   150: pop
    //   151: iconst_0
    //   152: istore #6
    //   154: dup2_x1
    //   155: pop2
    //   156: dup_x2
    //   157: iconst_1
    //   158: if_icmpgt -> 260
    //   161: dup2
    //   162: swap
    //   163: iload #6
    //   165: dup2_x1
    //   166: caload
    //   167: swap
    //   168: iload #6
    //   170: bipush #7
    //   172: irem
    //   173: tableswitch default -> 242, 0 -> 212, 1 -> 217, 2 -> 222, 3 -> 227, 4 -> 232, 5 -> 237
    //   212: bipush #71
    //   214: goto -> 244
    //   217: bipush #98
    //   219: goto -> 244
    //   222: bipush #82
    //   224: goto -> 244
    //   227: bipush #69
    //   229: goto -> 244
    //   232: bipush #62
    //   234: goto -> 244
    //   237: bipush #62
    //   239: goto -> 244
    //   242: bipush #108
    //   244: ixor
    //   245: ixor
    //   246: i2c
    //   247: castore
    //   248: iinc #6, 1
    //   251: dup
    //   252: ifne -> 260
    //   255: dup2
    //   256: dup_x1
    //   257: goto -> 165
    //   260: dup2_x1
    //   261: pop2
    //   262: dup_x2
    //   263: iload #6
    //   265: if_icmpgt -> 161
    //   268: pop
    //   269: new java/lang/String
    //   272: dup_x1
    //   273: swap
    //   274: invokespecial <init> : ([C)V
    //   277: invokevirtual intern : ()Ljava/lang/String;
    //   280: swap
    //   281: pop
    //   282: swap
    //   283: tableswitch default -> 40, 0 -> 98
    //   300: new java/math/BigInteger
    //   303: dup
    //   304: sipush #-8281
    //   307: sipush #-29045
    //   310: invokestatic a : (II)Ljava/lang/String;
    //   313: invokespecial <init> : (Ljava/lang/String;)V
    //   316: putstatic burp/Zz91.Z_ : Ljava/lang/Object;
    //   319: sipush #-8261
    //   322: sipush #22886
    //   325: invokestatic a : (II)Ljava/lang/String;
    //   328: putstatic burp/Zz91.Zx : Ljava/lang/String;
    //   331: return
  }
  
  private static Throwable a(Throwable paramThrowable) {
    return paramThrowable;
  }
  
  private static String a(int paramInt1, int paramInt2) {
    int i = (paramInt1 ^ 0xFFFFDFB1) & 0xFFFF;
    if (b[i] == null) {
      char[] arrayOfChar = a[i].toCharArray();
      switch (arrayOfChar[0] & 0xFF) {
        case 0:
        
        case 1:
        
        case 2:
        
        case 3:
        
        case 4:
        
        case 5:
        
        case 6:
        
        case 7:
        
        case 8:
        
        case 9:
        
        case 10:
        
        case 11:
        
        case 12:
        
        case 13:
        
        case 14:
        
        case 15:
        
        case 16:
        
        case 17:
        
        case 18:
        
        case 19:
        
        case 20:
        
        case 21:
        
        case 22:
        
        case 23:
        
        case 24:
        
        case 25:
        
        case 26:
        
        case 27:
        
        case 28:
        
        case 29:
        
        case 30:
        
        case 31:
        
        case 32:
        
        case 33:
        
        case 34:
        
        case 35:
        
        case 36:
        
        case 37:
        
        case 38:
        
        case 39:
        
        case 40:
        
        case 41:
        
        case 42:
        
        case 43:
        
        case 44:
        
        case 45:
        
        case 46:
        
        case 47:
        
        case 48:
        
        case 49:
        
        case 50:
        
        case 51:
        
        case 52:
        
        case 53:
        
        case 54:
        
        case 55:
        
        case 56:
        
        case 57:
        
        case 58:
        
        case 59:
        
        case 60:
        
        case 61:
        
        case 62:
        
        case 63:
        
        case 64:
        
        case 65:
        
        case 66:
        
        case 67:
        
        case 68:
        
        case 69:
        
        case 70:
        
        case 71:
        
        case 72:
        
        case 73:
        
        case 74:
        
        case 75:
        
        case 76:
        
        case 77:
        
        case 78:
        
        case 79:
        
        case 80:
        
        case 81:
        
        case 82:
        
        case 83:
        
        case 84:
        
        case 85:
        
        case 86:
        
        case 87:
        
        case 88:
        
        case 89:
        
        case 90:
        
        case 91:
        
        case 92:
        
        case 93:
        
        case 94:
        
        case 95:
        
        case 96:
        
        case 97:
        
        case 98:
        
        case 99:
        
        case 100:
        
        case 101:
        
        case 102:
        
        case 103:
        
        case 104:
        
        case 105:
        
        case 106:
        
        case 107:
        
        case 108:
        
        case 109:
        
        case 110:
        
        case 111:
        
        case 112:
        
        case 113:
        
        case 114:
        
        case 115:
        
        case 116:
        
        case 117:
        
        case 118:
        
        case 119:
        
        case 120:
        
        case 121:
        
        case 122:
        
        case 123:
        
        case 124:
        
        case 125:
        
        case 126:
        
        case 127:
        
        case 128:
        
        case 129:
        
        case 130:
        
        case 131:
        
        case 132:
        
        case 133:
        
        case 134:
        
        case 135:
        
        case 136:
        
        case 137:
        
        case 138:
        
        case 139:
        
        case 140:
        
        case 141:
        
        case 142:
        
        case 143:
        
        case 144:
        
        case 145:
        
        case 146:
        
        case 147:
        
        case 148:
        
        case 149:
        
        case 150:
        
        case 151:
        
        case 152:
        
        case 153:
        
        case 154:
        
        case 155:
        
        case 156:
        
        case 157:
        
        case 158:
        
        case 159:
        
        case 160:
        
        case 161:
        
        case 162:
        
        case 163:
        
        case 164:
        
        case 165:
        
        case 166:
        
        case 167:
        
        case 168:
        
        case 169:
        
        case 170:
        
        case 171:
        
        case 172:
        
        case 173:
        
        case 174:
        
        case 175:
        
        case 176:
        
        case 177:
        
        case 178:
        
        case 179:
        
        case 180:
        
        case 181:
        
        case 182:
        
        case 183:
        
        case 184:
        
        case 185:
        
        case 186:
        
        case 187:
        
        case 188:
        
        case 189:
        
        case 190:
        
        case 191:
        
        case 192:
        
        case 193:
        
        case 194:
        
        case 195:
        
        case 196:
        
        case 197:
        
        case 198:
        
        case 199:
        
        case 200:
        
        case 201:
        
        case 202:
        
        case 203:
        
        case 204:
        
        case 205:
        
        case 206:
        
        case 207:
        
        case 208:
        
        case 209:
        
        case 210:
        
        case 211:
        
        case 212:
        
        case 213:
        
        case 214:
        
        case 215:
        
        case 216:
        
        case 217:
        
        case 218:
        
        case 219:
        
        case 220:
        
        case 221:
        
        case 222:
        
        case 223:
        
        case 224:
        
        case 225:
        
        case 226:
        
        case 227:
        
        case 228:
        
        case 229:
        
        case 230:
        
        case 231:
        
        case 232:
        
        case 233:
        
        case 234:
        
        case 235:
        
        case 236:
        
        case 237:
        
        case 238:
        
        case 239:
        
        case 240:
        
        case 241:
        
        case 242:
        
        case 243:
        
        case 244:
        
        case 245:
        
        case 246:
        
        case 247:
        
        case 248:
        
        case 249:
        
        case 250:
        
        case 251:
        
        case 252:
        
        case 253:
        
        case 254:
        
        default:
          break;
      } 
      byte b1 = 61;
      int j = (paramInt2 & 0xFF) - b1;
      if (j < 0)
        j += 256; 
      int k = ((paramInt2 & 0xFFFF) >>> 8) - b1;
      if (k < 0)
        k += 256; 
      for (byte b2 = 0; b2 < arrayOfChar.length; b2++) {
        int m = b2 % 2;
        if (m == 0) {
          arrayOfChar[b2] = (char)(arrayOfChar[b2] ^ j);
          j = ((j >>> 3 | j << 5) ^ arrayOfChar[b2]) & 0xFF;
        } else {
          arrayOfChar[b2] = (char)(arrayOfChar[b2] ^ k);
          k = ((k >>> 3 | k << 5) ^ arrayOfChar[b2]) & 0xFF;
        } 
      } 
      b[i] = (new String(arrayOfChar)).intern();
    } 
    return b[i];
  }
}


/* Location:              C:\Program Files\BurpSuitePro\burpsuite_pro.jar!\burp\Zz91.class
 * Java compiler version: 21 (65.0)
 * JD-Core Version:       1.1.3
 */