package burp;

import java.math.BigInteger;

class Zzai extends ClassLoader {
  static Object Z_;
  
  static String Zy;
  
  private static final String[] a;
  
  private static final String[] b;
  
  static void Za(Object[] paramArrayOfObject, Object paramObject) throws Throwable {}
  
  static boolean Zf(Object[] paramArrayOfObject, Object paramObject) throws Throwable {
    // Byte code:
    //   0: invokestatic ZK : ()Z
    //   3: istore_2
    //   4: new java/lang/StringBuilder
    //   7: dup
    //   8: invokespecial <init> : ()V
    //   11: astore_3
    //   12: iconst_0
    //   13: istore #4
    //   15: iload #4
    //   17: bipush #32
    //   19: if_icmpge -> 1355
    //   22: iload #4
    //   24: tableswitch default -> 1348, 0 -> 168, 1 -> 205, 2 -> 242, 3 -> 279, 4 -> 316, 5 -> 353, 6 -> 390, 7 -> 427, 8 -> 464, 9 -> 501, 10 -> 538, 11 -> 575, 12 -> 612, 13 -> 649, 14 -> 686, 15 -> 723, 16 -> 760, 17 -> 797, 18 -> 834, 19 -> 871, 20 -> 908, 21 -> 945, 22 -> 982, 23 -> 1019, 24 -> 1056, 25 -> 1093, 26 -> 1130, 27 -> 1167, 28 -> 1204, 29 -> 1241, 30 -> 1278, 31 -> 1315
    //   168: aload_3
    //   169: getstatic burp/Zr8h.Zk : Ljava/lang/String;
    //   172: getstatic burp/Zk9s.ZY : Ljava/lang/Object;
    //   175: checkcast java/math/BigInteger
    //   178: invokevirtual intValue : ()I
    //   181: bipush #32
    //   183: irem
    //   184: invokestatic abs : (I)I
    //   187: invokevirtual charAt : (I)C
    //   190: invokevirtual append : (C)Ljava/lang/StringBuilder;
    //   193: pop
    //   194: iload_2
    //   195: ifeq -> 1348
    //   198: goto -> 205
    //   201: invokestatic a : (Ljava/lang/Throwable;)Ljava/lang/Throwable;
    //   204: athrow
    //   205: aload_3
    //   206: getstatic burp/Zxl5.Zq : Ljava/lang/String;
    //   209: getstatic burp/Zl_k.ZH : Ljava/lang/Object;
    //   212: checkcast java/math/BigInteger
    //   215: invokevirtual intValue : ()I
    //   218: bipush #32
    //   220: irem
    //   221: invokestatic abs : (I)I
    //   224: invokevirtual charAt : (I)C
    //   227: invokevirtual append : (C)Ljava/lang/StringBuilder;
    //   230: pop
    //   231: iload_2
    //   232: ifeq -> 1348
    //   235: goto -> 242
    //   238: invokestatic a : (Ljava/lang/Throwable;)Ljava/lang/Throwable;
    //   241: athrow
    //   242: aload_3
    //   243: getstatic burp/Zxzd.ZM : Ljava/lang/String;
    //   246: getstatic burp/Zedz.Za : Ljava/lang/Object;
    //   249: checkcast java/math/BigInteger
    //   252: invokevirtual intValue : ()I
    //   255: bipush #32
    //   257: irem
    //   258: invokestatic abs : (I)I
    //   261: invokevirtual charAt : (I)C
    //   264: invokevirtual append : (C)Ljava/lang/StringBuilder;
    //   267: pop
    //   268: iload_2
    //   269: ifeq -> 1348
    //   272: goto -> 279
    //   275: invokestatic a : (Ljava/lang/Throwable;)Ljava/lang/Throwable;
    //   278: athrow
    //   279: aload_3
    //   280: getstatic burp/Ze3d.ZL : Ljava/lang/String;
    //   283: getstatic burp/Zg7p.Zb : Ljava/lang/Object;
    //   286: checkcast java/math/BigInteger
    //   289: invokevirtual intValue : ()I
    //   292: bipush #32
    //   294: irem
    //   295: invokestatic abs : (I)I
    //   298: invokevirtual charAt : (I)C
    //   301: invokevirtual append : (C)Ljava/lang/StringBuilder;
    //   304: pop
    //   305: iload_2
    //   306: ifeq -> 1348
    //   309: goto -> 316
    //   312: invokestatic a : (Ljava/lang/Throwable;)Ljava/lang/Throwable;
    //   315: athrow
    //   316: aload_3
    //   317: getstatic burp/Zzk9.Zb : Ljava/lang/String;
    //   320: getstatic burp/Zm__.Zz : Ljava/lang/Object;
    //   323: checkcast java/math/BigInteger
    //   326: invokevirtual intValue : ()I
    //   329: bipush #32
    //   331: irem
    //   332: invokestatic abs : (I)I
    //   335: invokevirtual charAt : (I)C
    //   338: invokevirtual append : (C)Ljava/lang/StringBuilder;
    //   341: pop
    //   342: iload_2
    //   343: ifeq -> 1348
    //   346: goto -> 353
    //   349: invokestatic a : (Ljava/lang/Throwable;)Ljava/lang/Throwable;
    //   352: athrow
    //   353: aload_3
    //   354: getstatic burp/Zsm3.Zl : Ljava/lang/String;
    //   357: getstatic burp/Ze13.ZD : Ljava/lang/Object;
    //   360: checkcast java/math/BigInteger
    //   363: invokevirtual intValue : ()I
    //   366: bipush #32
    //   368: irem
    //   369: invokestatic abs : (I)I
    //   372: invokevirtual charAt : (I)C
    //   375: invokevirtual append : (C)Ljava/lang/StringBuilder;
    //   378: pop
    //   379: iload_2
    //   380: ifeq -> 1348
    //   383: goto -> 390
    //   386: invokestatic a : (Ljava/lang/Throwable;)Ljava/lang/Throwable;
    //   389: athrow
    //   390: aload_3
    //   391: getstatic burp/Zkyc.ZK : Ljava/lang/String;
    //   394: getstatic burp/Zk9s.ZY : Ljava/lang/Object;
    //   397: checkcast java/math/BigInteger
    //   400: invokevirtual intValue : ()I
    //   403: bipush #32
    //   405: irem
    //   406: invokestatic abs : (I)I
    //   409: invokevirtual charAt : (I)C
    //   412: invokevirtual append : (C)Ljava/lang/StringBuilder;
    //   415: pop
    //   416: iload_2
    //   417: ifeq -> 1348
    //   420: goto -> 427
    //   423: invokestatic a : (Ljava/lang/Throwable;)Ljava/lang/Throwable;
    //   426: athrow
    //   427: aload_3
    //   428: getstatic burp/Zmj4.ZM : Ljava/lang/String;
    //   431: getstatic burp/Zgss.Zl : Ljava/lang/Object;
    //   434: checkcast java/math/BigInteger
    //   437: invokevirtual intValue : ()I
    //   440: bipush #32
    //   442: irem
    //   443: invokestatic abs : (I)I
    //   446: invokevirtual charAt : (I)C
    //   449: invokevirtual append : (C)Ljava/lang/StringBuilder;
    //   452: pop
    //   453: iload_2
    //   454: ifeq -> 1348
    //   457: goto -> 464
    //   460: invokestatic a : (Ljava/lang/Throwable;)Ljava/lang/Throwable;
    //   463: athrow
    //   464: aload_3
    //   465: getstatic burp/Zm0s.Zm : Ljava/lang/String;
    //   468: getstatic burp/Zgw0.ZM : Ljava/lang/Object;
    //   471: checkcast java/math/BigInteger
    //   474: invokevirtual intValue : ()I
    //   477: bipush #32
    //   479: irem
    //   480: invokestatic abs : (I)I
    //   483: invokevirtual charAt : (I)C
    //   486: invokevirtual append : (C)Ljava/lang/StringBuilder;
    //   489: pop
    //   490: iload_2
    //   491: ifeq -> 1348
    //   494: goto -> 501
    //   497: invokestatic a : (Ljava/lang/Throwable;)Ljava/lang/Throwable;
    //   500: athrow
    //   501: aload_3
    //   502: getstatic burp/Zxwl.Zu : Ljava/lang/String;
    //   505: getstatic burp/Zod.ZP : Ljava/lang/Object;
    //   508: checkcast java/math/BigInteger
    //   511: invokevirtual intValue : ()I
    //   514: bipush #32
    //   516: irem
    //   517: invokestatic abs : (I)I
    //   520: invokevirtual charAt : (I)C
    //   523: invokevirtual append : (C)Ljava/lang/StringBuilder;
    //   526: pop
    //   527: iload_2
    //   528: ifeq -> 1348
    //   531: goto -> 538
    //   534: invokestatic a : (Ljava/lang/Throwable;)Ljava/lang/Throwable;
    //   537: athrow
    //   538: aload_3
    //   539: getstatic burp/Zg7p.ZA : Ljava/lang/String;
    //   542: getstatic burp/Ztbf.Zv : Ljava/lang/Object;
    //   545: checkcast java/math/BigInteger
    //   548: invokevirtual intValue : ()I
    //   551: bipush #32
    //   553: irem
    //   554: invokestatic abs : (I)I
    //   557: invokevirtual charAt : (I)C
    //   560: invokevirtual append : (C)Ljava/lang/StringBuilder;
    //   563: pop
    //   564: iload_2
    //   565: ifeq -> 1348
    //   568: goto -> 575
    //   571: invokestatic a : (Ljava/lang/Throwable;)Ljava/lang/Throwable;
    //   574: athrow
    //   575: aload_3
    //   576: getstatic burp/Zx4w.Zo : Ljava/lang/String;
    //   579: getstatic burp/Zeh9.ZY : Ljava/lang/Object;
    //   582: checkcast java/math/BigInteger
    //   585: invokevirtual intValue : ()I
    //   588: bipush #32
    //   590: irem
    //   591: invokestatic abs : (I)I
    //   594: invokevirtual charAt : (I)C
    //   597: invokevirtual append : (C)Ljava/lang/StringBuilder;
    //   600: pop
    //   601: iload_2
    //   602: ifeq -> 1348
    //   605: goto -> 612
    //   608: invokestatic a : (Ljava/lang/Throwable;)Ljava/lang/Throwable;
    //   611: athrow
    //   612: aload_3
    //   613: getstatic burp/Zr0u.Z_ : Ljava/lang/String;
    //   616: getstatic burp/Zmj4.Zm : Ljava/lang/Object;
    //   619: checkcast java/math/BigInteger
    //   622: invokevirtual intValue : ()I
    //   625: bipush #32
    //   627: irem
    //   628: invokestatic abs : (I)I
    //   631: invokevirtual charAt : (I)C
    //   634: invokevirtual append : (C)Ljava/lang/StringBuilder;
    //   637: pop
    //   638: iload_2
    //   639: ifeq -> 1348
    //   642: goto -> 649
    //   645: invokestatic a : (Ljava/lang/Throwable;)Ljava/lang/Throwable;
    //   648: athrow
    //   649: aload_3
    //   650: getstatic burp/Zzqj.Zk : Ljava/lang/String;
    //   653: getstatic burp/Zr0g.Zj : Ljava/lang/Object;
    //   656: checkcast java/math/BigInteger
    //   659: invokevirtual intValue : ()I
    //   662: bipush #32
    //   664: irem
    //   665: invokestatic abs : (I)I
    //   668: invokevirtual charAt : (I)C
    //   671: invokevirtual append : (C)Ljava/lang/StringBuilder;
    //   674: pop
    //   675: iload_2
    //   676: ifeq -> 1348
    //   679: goto -> 686
    //   682: invokestatic a : (Ljava/lang/Throwable;)Ljava/lang/Throwable;
    //   685: athrow
    //   686: aload_3
    //   687: getstatic burp/Zllw.Zg : Ljava/lang/String;
    //   690: getstatic burp/Zr0g.Zj : Ljava/lang/Object;
    //   693: checkcast java/math/BigInteger
    //   696: invokevirtual intValue : ()I
    //   699: bipush #32
    //   701: irem
    //   702: invokestatic abs : (I)I
    //   705: invokevirtual charAt : (I)C
    //   708: invokevirtual append : (C)Ljava/lang/StringBuilder;
    //   711: pop
    //   712: iload_2
    //   713: ifeq -> 1348
    //   716: goto -> 723
    //   719: invokestatic a : (Ljava/lang/Throwable;)Ljava/lang/Throwable;
    //   722: athrow
    //   723: aload_3
    //   724: getstatic burp/Zxzd.ZM : Ljava/lang/String;
    //   727: getstatic burp/Zein.Zb : Ljava/lang/Object;
    //   730: checkcast java/math/BigInteger
    //   733: invokevirtual intValue : ()I
    //   736: bipush #32
    //   738: irem
    //   739: invokestatic abs : (I)I
    //   742: invokevirtual charAt : (I)C
    //   745: invokevirtual append : (C)Ljava/lang/StringBuilder;
    //   748: pop
    //   749: iload_2
    //   750: ifeq -> 1348
    //   753: goto -> 760
    //   756: invokestatic a : (Ljava/lang/Throwable;)Ljava/lang/Throwable;
    //   759: athrow
    //   760: aload_3
    //   761: getstatic burp/Zkfz.Zs : Ljava/lang/String;
    //   764: getstatic burp/Zl88.ZK : Ljava/lang/Object;
    //   767: checkcast java/math/BigInteger
    //   770: invokevirtual intValue : ()I
    //   773: bipush #32
    //   775: irem
    //   776: invokestatic abs : (I)I
    //   779: invokevirtual charAt : (I)C
    //   782: invokevirtual append : (C)Ljava/lang/StringBuilder;
    //   785: pop
    //   786: iload_2
    //   787: ifeq -> 1348
    //   790: goto -> 797
    //   793: invokestatic a : (Ljava/lang/Throwable;)Ljava/lang/Throwable;
    //   796: athrow
    //   797: aload_3
    //   798: getstatic burp/Zsxm.Zq : Ljava/lang/String;
    //   801: getstatic burp/Zsgl.Zn : Ljava/lang/Object;
    //   804: checkcast java/math/BigInteger
    //   807: invokevirtual intValue : ()I
    //   810: bipush #32
    //   812: irem
    //   813: invokestatic abs : (I)I
    //   816: invokevirtual charAt : (I)C
    //   819: invokevirtual append : (C)Ljava/lang/StringBuilder;
    //   822: pop
    //   823: iload_2
    //   824: ifeq -> 1348
    //   827: goto -> 834
    //   830: invokestatic a : (Ljava/lang/Throwable;)Ljava/lang/Throwable;
    //   833: athrow
    //   834: aload_3
    //   835: getstatic burp/Zsde.Zi : Ljava/lang/String;
    //   838: getstatic burp/Zlv6.ZN : Ljava/lang/Object;
    //   841: checkcast java/math/BigInteger
    //   844: invokevirtual intValue : ()I
    //   847: bipush #32
    //   849: irem
    //   850: invokestatic abs : (I)I
    //   853: invokevirtual charAt : (I)C
    //   856: invokevirtual append : (C)Ljava/lang/StringBuilder;
    //   859: pop
    //   860: iload_2
    //   861: ifeq -> 1348
    //   864: goto -> 871
    //   867: invokestatic a : (Ljava/lang/Throwable;)Ljava/lang/Throwable;
    //   870: athrow
    //   871: aload_3
    //   872: getstatic burp/Zxwl.Zu : Ljava/lang/String;
    //   875: getstatic burp/Zsxj.Zi : Ljava/lang/Object;
    //   878: checkcast java/math/BigInteger
    //   881: invokevirtual intValue : ()I
    //   884: bipush #32
    //   886: irem
    //   887: invokestatic abs : (I)I
    //   890: invokevirtual charAt : (I)C
    //   893: invokevirtual append : (C)Ljava/lang/StringBuilder;
    //   896: pop
    //   897: iload_2
    //   898: ifeq -> 1348
    //   901: goto -> 908
    //   904: invokestatic a : (Ljava/lang/Throwable;)Ljava/lang/Throwable;
    //   907: athrow
    //   908: aload_3
    //   909: getstatic burp/Zxk9.Zx : Ljava/lang/String;
    //   912: getstatic burp/Zk8b.ZK : Ljava/lang/Object;
    //   915: checkcast java/math/BigInteger
    //   918: invokevirtual intValue : ()I
    //   921: bipush #32
    //   923: irem
    //   924: invokestatic abs : (I)I
    //   927: invokevirtual charAt : (I)C
    //   930: invokevirtual append : (C)Ljava/lang/StringBuilder;
    //   933: pop
    //   934: iload_2
    //   935: ifeq -> 1348
    //   938: goto -> 945
    //   941: invokestatic a : (Ljava/lang/Throwable;)Ljava/lang/Throwable;
    //   944: athrow
    //   945: aload_3
    //   946: getstatic burp/Zxo6.Z_ : Ljava/lang/String;
    //   949: getstatic burp/Zbo7.Zl : Ljava/lang/Object;
    //   952: checkcast java/math/BigInteger
    //   955: invokevirtual intValue : ()I
    //   958: bipush #32
    //   960: irem
    //   961: invokestatic abs : (I)I
    //   964: invokevirtual charAt : (I)C
    //   967: invokevirtual append : (C)Ljava/lang/StringBuilder;
    //   970: pop
    //   971: iload_2
    //   972: ifeq -> 1348
    //   975: goto -> 982
    //   978: invokestatic a : (Ljava/lang/Throwable;)Ljava/lang/Throwable;
    //   981: athrow
    //   982: aload_3
    //   983: getstatic burp/Ze3j.ZI : Ljava/lang/String;
    //   986: getstatic burp/Zr3q.Zn : Ljava/lang/Object;
    //   989: checkcast java/math/BigInteger
    //   992: invokevirtual intValue : ()I
    //   995: bipush #32
    //   997: irem
    //   998: invokestatic abs : (I)I
    //   1001: invokevirtual charAt : (I)C
    //   1004: invokevirtual append : (C)Ljava/lang/StringBuilder;
    //   1007: pop
    //   1008: iload_2
    //   1009: ifeq -> 1348
    //   1012: goto -> 1019
    //   1015: invokestatic a : (Ljava/lang/Throwable;)Ljava/lang/Throwable;
    //   1018: athrow
    //   1019: aload_3
    //   1020: getstatic burp/Zehi.Zi : Ljava/lang/String;
    //   1023: getstatic burp/Zd1.ZV : Ljava/lang/Object;
    //   1026: checkcast java/math/BigInteger
    //   1029: invokevirtual intValue : ()I
    //   1032: bipush #32
    //   1034: irem
    //   1035: invokestatic abs : (I)I
    //   1038: invokevirtual charAt : (I)C
    //   1041: invokevirtual append : (C)Ljava/lang/StringBuilder;
    //   1044: pop
    //   1045: iload_2
    //   1046: ifeq -> 1348
    //   1049: goto -> 1056
    //   1052: invokestatic a : (Ljava/lang/Throwable;)Ljava/lang/Throwable;
    //   1055: athrow
    //   1056: aload_3
    //   1057: getstatic burp/Zkfz.Zs : Ljava/lang/String;
    //   1060: getstatic burp/Zkbf.Zx : Ljava/lang/Object;
    //   1063: checkcast java/math/BigInteger
    //   1066: invokevirtual intValue : ()I
    //   1069: bipush #32
    //   1071: irem
    //   1072: invokestatic abs : (I)I
    //   1075: invokevirtual charAt : (I)C
    //   1078: invokevirtual append : (C)Ljava/lang/StringBuilder;
    //   1081: pop
    //   1082: iload_2
    //   1083: ifeq -> 1348
    //   1086: goto -> 1093
    //   1089: invokestatic a : (Ljava/lang/Throwable;)Ljava/lang/Throwable;
    //   1092: athrow
    //   1093: aload_3
    //   1094: getstatic burp/Zmj4.ZM : Ljava/lang/String;
    //   1097: getstatic burp/Zl_k.ZH : Ljava/lang/Object;
    //   1100: checkcast java/math/BigInteger
    //   1103: invokevirtual intValue : ()I
    //   1106: bipush #32
    //   1108: irem
    //   1109: invokestatic abs : (I)I
    //   1112: invokevirtual charAt : (I)C
    //   1115: invokevirtual append : (C)Ljava/lang/StringBuilder;
    //   1118: pop
    //   1119: iload_2
    //   1120: ifeq -> 1348
    //   1123: goto -> 1130
    //   1126: invokestatic a : (Ljava/lang/Throwable;)Ljava/lang/Throwable;
    //   1129: athrow
    //   1130: aload_3
    //   1131: getstatic burp/Zer.Zp : Ljava/lang/String;
    //   1134: getstatic burp/Zbo7.Zl : Ljava/lang/Object;
    //   1137: checkcast java/math/BigInteger
    //   1140: invokevirtual intValue : ()I
    //   1143: bipush #32
    //   1145: irem
    //   1146: invokestatic abs : (I)I
    //   1149: invokevirtual charAt : (I)C
    //   1152: invokevirtual append : (C)Ljava/lang/StringBuilder;
    //   1155: pop
    //   1156: iload_2
    //   1157: ifeq -> 1348
    //   1160: goto -> 1167
    //   1163: invokestatic a : (Ljava/lang/Throwable;)Ljava/lang/Throwable;
    //   1166: athrow
    //   1167: aload_3
    //   1168: getstatic burp/Zsgl.ZG : Ljava/lang/String;
    //   1171: getstatic burp/Zehi.Zb : Ljava/lang/Object;
    //   1174: checkcast java/math/BigInteger
    //   1177: invokevirtual intValue : ()I
    //   1180: bipush #32
    //   1182: irem
    //   1183: invokestatic abs : (I)I
    //   1186: invokevirtual charAt : (I)C
    //   1189: invokevirtual append : (C)Ljava/lang/StringBuilder;
    //   1192: pop
    //   1193: iload_2
    //   1194: ifeq -> 1348
    //   1197: goto -> 1204
    //   1200: invokestatic a : (Ljava/lang/Throwable;)Ljava/lang/Throwable;
    //   1203: athrow
    //   1204: aload_3
    //   1205: getstatic burp/Zg_p.ZO : Ljava/lang/String;
    //   1208: getstatic burp/Zb2s.Ze : Ljava/lang/Object;
    //   1211: checkcast java/math/BigInteger
    //   1214: invokevirtual intValue : ()I
    //   1217: bipush #32
    //   1219: irem
    //   1220: invokestatic abs : (I)I
    //   1223: invokevirtual charAt : (I)C
    //   1226: invokevirtual append : (C)Ljava/lang/StringBuilder;
    //   1229: pop
    //   1230: iload_2
    //   1231: ifeq -> 1348
    //   1234: goto -> 1241
    //   1237: invokestatic a : (Ljava/lang/Throwable;)Ljava/lang/Throwable;
    //   1240: athrow
    //   1241: aload_3
    //   1242: getstatic burp/Zlv6.Zt : Ljava/lang/String;
    //   1245: getstatic burp/Zzsq.Zh : Ljava/lang/Object;
    //   1248: checkcast java/math/BigInteger
    //   1251: invokevirtual intValue : ()I
    //   1254: bipush #32
    //   1256: irem
    //   1257: invokestatic abs : (I)I
    //   1260: invokevirtual charAt : (I)C
    //   1263: invokevirtual append : (C)Ljava/lang/StringBuilder;
    //   1266: pop
    //   1267: iload_2
    //   1268: ifeq -> 1348
    //   1271: goto -> 1278
    //   1274: invokestatic a : (Ljava/lang/Throwable;)Ljava/lang/Throwable;
    //   1277: athrow
    //   1278: aload_3
    //   1279: getstatic burp/Zshq.Zi : Ljava/lang/String;
    //   1282: getstatic burp/Zm__.Zz : Ljava/lang/Object;
    //   1285: checkcast java/math/BigInteger
    //   1288: invokevirtual intValue : ()I
    //   1291: bipush #32
    //   1293: irem
    //   1294: invokestatic abs : (I)I
    //   1297: invokevirtual charAt : (I)C
    //   1300: invokevirtual append : (C)Ljava/lang/StringBuilder;
    //   1303: pop
    //   1304: iload_2
    //   1305: ifeq -> 1348
    //   1308: goto -> 1315
    //   1311: invokestatic a : (Ljava/lang/Throwable;)Ljava/lang/Throwable;
    //   1314: athrow
    //   1315: aload_3
    //   1316: getstatic burp/Zk9s.ZM : Ljava/lang/String;
    //   1319: getstatic burp/Zr8h.ZH : Ljava/lang/Object;
    //   1322: checkcast java/math/BigInteger
    //   1325: invokevirtual intValue : ()I
    //   1328: bipush #32
    //   1330: irem
    //   1331: invokestatic abs : (I)I
    //   1334: invokevirtual charAt : (I)C
    //   1337: invokevirtual append : (C)Ljava/lang/StringBuilder;
    //   1340: pop
    //   1341: goto -> 1348
    //   1344: invokestatic a : (Ljava/lang/Throwable;)Ljava/lang/Throwable;
    //   1347: athrow
    //   1348: iinc #4, 1
    //   1351: iload_2
    //   1352: ifeq -> 15
    //   1355: aload_3
    //   1356: invokevirtual toString : ()Ljava/lang/String;
    //   1359: putstatic burp/Zrnu.ZO : Ljava/lang/String;
    //   1362: sipush #7544
    //   1365: sipush #14873
    //   1368: invokestatic a : (II)Ljava/lang/String;
    //   1371: iconst_1
    //   1372: ldc burp/Zzky
    //   1374: invokevirtual getClassLoader : ()Ljava/lang/ClassLoader;
    //   1377: invokestatic forName : (Ljava/lang/String;ZLjava/lang/ClassLoader;)Ljava/lang/Class;
    //   1380: invokevirtual getDeclaredFields : ()[Ljava/lang/reflect/Field;
    //   1383: astore #4
    //   1385: aload #4
    //   1387: arraylength
    //   1388: istore #5
    //   1390: iconst_0
    //   1391: istore #6
    //   1393: iload #6
    //   1395: iload #5
    //   1397: if_icmpge -> 1535
    //   1400: aload #4
    //   1402: iload #6
    //   1404: aaload
    //   1405: astore #7
    //   1407: aload #7
    //   1409: invokevirtual getModifiers : ()I
    //   1412: invokestatic isStatic : (I)Z
    //   1415: ifne -> 1425
    //   1418: goto -> 1528
    //   1421: invokestatic a : (Ljava/lang/Throwable;)Ljava/lang/Throwable;
    //   1424: athrow
    //   1425: aload #7
    //   1427: invokevirtual getType : ()Ljava/lang/Class;
    //   1430: astore #8
    //   1432: aload #8
    //   1434: ifnull -> 1515
    //   1437: aload #8
    //   1439: invokevirtual isPrimitive : ()Z
    //   1442: ifne -> 1515
    //   1445: goto -> 1452
    //   1448: invokestatic a : (Ljava/lang/Throwable;)Ljava/lang/Throwable;
    //   1451: athrow
    //   1452: aload #8
    //   1454: invokevirtual getPackage : ()Ljava/lang/Package;
    //   1457: ifnull -> 1515
    //   1460: goto -> 1467
    //   1463: invokestatic a : (Ljava/lang/Throwable;)Ljava/lang/Throwable;
    //   1466: athrow
    //   1467: aload #8
    //   1469: invokevirtual getPackage : ()Ljava/lang/Package;
    //   1472: invokevirtual getName : ()Ljava/lang/String;
    //   1475: ifnull -> 1515
    //   1478: goto -> 1485
    //   1481: invokestatic a : (Ljava/lang/Throwable;)Ljava/lang/Throwable;
    //   1484: athrow
    //   1485: aload #8
    //   1487: invokevirtual getPackage : ()Ljava/lang/Package;
    //   1490: invokevirtual getName : ()Ljava/lang/String;
    //   1493: sipush #7536
    //   1496: sipush #-4680
    //   1499: invokestatic a : (II)Ljava/lang/String;
    //   1502: invokevirtual startsWith : (Ljava/lang/String;)Z
    //   1505: ifne -> 1515
    //   1508: goto -> 1515
    //   1511: invokestatic a : (Ljava/lang/Throwable;)Ljava/lang/Throwable;
    //   1514: athrow
    //   1515: aload #7
    //   1517: iconst_1
    //   1518: invokevirtual setAccessible : (Z)V
    //   1521: aload #7
    //   1523: aconst_null
    //   1524: invokevirtual get : (Ljava/lang/Object;)Ljava/lang/Object;
    //   1527: pop
    //   1528: iinc #6, 1
    //   1531: iload_2
    //   1532: ifeq -> 1393
    //   1535: sipush #7539
    //   1538: sipush #6013
    //   1541: invokestatic a : (II)Ljava/lang/String;
    //   1544: invokestatic forName : (Ljava/lang/String;)Ljava/lang/Class;
    //   1547: invokevirtual getDeclaredMethods : ()[Ljava/lang/reflect/Method;
    //   1550: astore #4
    //   1552: aload #4
    //   1554: arraylength
    //   1555: istore #5
    //   1557: iconst_0
    //   1558: istore #6
    //   1560: iload #6
    //   1562: iload #5
    //   1564: if_icmpge -> 1697
    //   1567: aload #4
    //   1569: iload #6
    //   1571: aaload
    //   1572: astore #7
    //   1574: aload #7
    //   1576: invokevirtual getParameterTypes : ()[Ljava/lang/Class;
    //   1579: pop
    //   1580: aload #7
    //   1582: invokevirtual getModifiers : ()I
    //   1585: invokestatic isStatic : (I)Z
    //   1588: ifeq -> 1683
    //   1591: aload #7
    //   1593: invokevirtual getParameterTypes : ()[Ljava/lang/Class;
    //   1596: arraylength
    //   1597: iconst_2
    //   1598: if_icmpne -> 1683
    //   1601: goto -> 1608
    //   1604: invokestatic a : (Ljava/lang/Throwable;)Ljava/lang/Throwable;
    //   1607: athrow
    //   1608: aload #7
    //   1610: invokevirtual getReturnType : ()Ljava/lang/Class;
    //   1613: getstatic java/lang/Void.TYPE : Ljava/lang/Class;
    //   1616: invokevirtual equals : (Ljava/lang/Object;)Z
    //   1619: ifeq -> 1683
    //   1622: goto -> 1629
    //   1625: invokestatic a : (Ljava/lang/Throwable;)Ljava/lang/Throwable;
    //   1628: athrow
    //   1629: aload #7
    //   1631: iconst_1
    //   1632: invokevirtual setAccessible : (Z)V
    //   1635: aload #7
    //   1637: aconst_null
    //   1638: iconst_2
    //   1639: anewarray java/lang/Object
    //   1642: dup
    //   1643: iconst_0
    //   1644: aload_0
    //   1645: aastore
    //   1646: dup
    //   1647: iconst_1
    //   1648: aload_1
    //   1649: ifnonnull -> 1667
    //   1652: goto -> 1659
    //   1655: invokestatic a : (Ljava/lang/Throwable;)Ljava/lang/Throwable;
    //   1658: athrow
    //   1659: aload_1
    //   1660: goto -> 1674
    //   1663: invokestatic a : (Ljava/lang/Throwable;)Ljava/lang/Throwable;
    //   1666: athrow
    //   1667: aload_1
    //   1668: checkcast [B
    //   1671: invokevirtual clone : ()Ljava/lang/Object;
    //   1674: aastore
    //   1675: invokevirtual invoke : (Ljava/lang/Object;[Ljava/lang/Object;)Ljava/lang/Object;
    //   1678: pop
    //   1679: iload_2
    //   1680: ifeq -> 1697
    //   1683: iinc #6, 1
    //   1686: iload_2
    //   1687: ifeq -> 1560
    //   1690: goto -> 1697
    //   1693: invokestatic a : (Ljava/lang/Throwable;)Ljava/lang/Throwable;
    //   1696: athrow
    //   1697: getstatic burp/Zsby.ZZ : Ljava/lang/Object;
    //   1700: checkcast java/math/BigInteger
    //   1703: invokevirtual intValue : ()I
    //   1706: i2l
    //   1707: invokestatic currentTimeMillis : ()J
    //   1710: ladd
    //   1711: getstatic burp/Zr0u.ZB : Ljava/lang/Object;
    //   1714: checkcast java/math/BigInteger
    //   1717: invokevirtual intValue : ()I
    //   1720: i2l
    //   1721: lcmp
    //   1722: ifge -> 2060
    //   1725: sipush #7549
    //   1728: sipush #13376
    //   1731: invokestatic a : (II)Ljava/lang/String;
    //   1734: iconst_1
    //   1735: ldc burp/Zzk9
    //   1737: invokevirtual getClassLoader : ()Ljava/lang/ClassLoader;
    //   1740: invokestatic forName : (Ljava/lang/String;ZLjava/lang/ClassLoader;)Ljava/lang/Class;
    //   1743: invokevirtual getDeclaredFields : ()[Ljava/lang/reflect/Field;
    //   1746: astore #4
    //   1748: aload #4
    //   1750: arraylength
    //   1751: istore #5
    //   1753: iconst_0
    //   1754: istore #6
    //   1756: iload #6
    //   1758: iload #5
    //   1760: if_icmpge -> 1898
    //   1763: aload #4
    //   1765: iload #6
    //   1767: aaload
    //   1768: astore #7
    //   1770: aload #7
    //   1772: invokevirtual getModifiers : ()I
    //   1775: invokestatic isStatic : (I)Z
    //   1778: ifne -> 1788
    //   1781: goto -> 1891
    //   1784: invokestatic a : (Ljava/lang/Throwable;)Ljava/lang/Throwable;
    //   1787: athrow
    //   1788: aload #7
    //   1790: invokevirtual getType : ()Ljava/lang/Class;
    //   1793: astore #8
    //   1795: aload #8
    //   1797: ifnull -> 1878
    //   1800: aload #8
    //   1802: invokevirtual isPrimitive : ()Z
    //   1805: ifne -> 1878
    //   1808: goto -> 1815
    //   1811: invokestatic a : (Ljava/lang/Throwable;)Ljava/lang/Throwable;
    //   1814: athrow
    //   1815: aload #8
    //   1817: invokevirtual getPackage : ()Ljava/lang/Package;
    //   1820: ifnull -> 1878
    //   1823: goto -> 1830
    //   1826: invokestatic a : (Ljava/lang/Throwable;)Ljava/lang/Throwable;
    //   1829: athrow
    //   1830: aload #8
    //   1832: invokevirtual getPackage : ()Ljava/lang/Package;
    //   1835: invokevirtual getName : ()Ljava/lang/String;
    //   1838: ifnull -> 1878
    //   1841: goto -> 1848
    //   1844: invokestatic a : (Ljava/lang/Throwable;)Ljava/lang/Throwable;
    //   1847: athrow
    //   1848: aload #8
    //   1850: invokevirtual getPackage : ()Ljava/lang/Package;
    //   1853: invokevirtual getName : ()Ljava/lang/String;
    //   1856: sipush #7522
    //   1859: sipush #16473
    //   1862: invokestatic a : (II)Ljava/lang/String;
    //   1865: invokevirtual startsWith : (Ljava/lang/String;)Z
    //   1868: ifne -> 1878
    //   1871: goto -> 1878
    //   1874: invokestatic a : (Ljava/lang/Throwable;)Ljava/lang/Throwable;
    //   1877: athrow
    //   1878: aload #7
    //   1880: iconst_1
    //   1881: invokevirtual setAccessible : (Z)V
    //   1884: aload #7
    //   1886: aconst_null
    //   1887: invokevirtual get : (Ljava/lang/Object;)Ljava/lang/Object;
    //   1890: pop
    //   1891: iinc #6, 1
    //   1894: iload_2
    //   1895: ifeq -> 1756
    //   1898: sipush #7543
    //   1901: sipush #32422
    //   1904: invokestatic a : (II)Ljava/lang/String;
    //   1907: invokestatic forName : (Ljava/lang/String;)Ljava/lang/Class;
    //   1910: invokevirtual getDeclaredMethods : ()[Ljava/lang/reflect/Method;
    //   1913: astore #4
    //   1915: aload #4
    //   1917: arraylength
    //   1918: istore #5
    //   1920: iconst_0
    //   1921: istore #6
    //   1923: iload #6
    //   1925: iload #5
    //   1927: if_icmpge -> 2060
    //   1930: aload #4
    //   1932: iload #6
    //   1934: aaload
    //   1935: astore #7
    //   1937: aload #7
    //   1939: invokevirtual getParameterTypes : ()[Ljava/lang/Class;
    //   1942: pop
    //   1943: aload #7
    //   1945: invokevirtual getModifiers : ()I
    //   1948: invokestatic isStatic : (I)Z
    //   1951: ifeq -> 2046
    //   1954: aload #7
    //   1956: invokevirtual getParameterTypes : ()[Ljava/lang/Class;
    //   1959: arraylength
    //   1960: iconst_2
    //   1961: if_icmpne -> 2046
    //   1964: goto -> 1971
    //   1967: invokestatic a : (Ljava/lang/Throwable;)Ljava/lang/Throwable;
    //   1970: athrow
    //   1971: aload #7
    //   1973: invokevirtual getReturnType : ()Ljava/lang/Class;
    //   1976: getstatic java/lang/Void.TYPE : Ljava/lang/Class;
    //   1979: invokevirtual equals : (Ljava/lang/Object;)Z
    //   1982: ifeq -> 2046
    //   1985: goto -> 1992
    //   1988: invokestatic a : (Ljava/lang/Throwable;)Ljava/lang/Throwable;
    //   1991: athrow
    //   1992: aload #7
    //   1994: iconst_1
    //   1995: invokevirtual setAccessible : (Z)V
    //   1998: aload #7
    //   2000: aconst_null
    //   2001: iconst_2
    //   2002: anewarray java/lang/Object
    //   2005: dup
    //   2006: iconst_0
    //   2007: aload_0
    //   2008: aastore
    //   2009: dup
    //   2010: iconst_1
    //   2011: aload_1
    //   2012: ifnonnull -> 2030
    //   2015: goto -> 2022
    //   2018: invokestatic a : (Ljava/lang/Throwable;)Ljava/lang/Throwable;
    //   2021: athrow
    //   2022: aload_1
    //   2023: goto -> 2037
    //   2026: invokestatic a : (Ljava/lang/Throwable;)Ljava/lang/Throwable;
    //   2029: athrow
    //   2030: aload_1
    //   2031: checkcast [B
    //   2034: invokevirtual clone : ()Ljava/lang/Object;
    //   2037: aastore
    //   2038: invokevirtual invoke : (Ljava/lang/Object;[Ljava/lang/Object;)Ljava/lang/Object;
    //   2041: pop
    //   2042: iload_2
    //   2043: ifeq -> 2060
    //   2046: iinc #6, 1
    //   2049: iload_2
    //   2050: ifeq -> 1923
    //   2053: goto -> 2060
    //   2056: invokestatic a : (Ljava/lang/Throwable;)Ljava/lang/Throwable;
    //   2059: athrow
    //   2060: iconst_0
    //   2061: istore #4
    //   2063: getstatic burp/Zb2s.Zq : Ljava/lang/String;
    //   2066: getstatic burp/Zxo6.Zw : Ljava/lang/Object;
    //   2069: checkcast java/math/BigInteger
    //   2072: invokevirtual intValue : ()I
    //   2075: bipush #32
    //   2077: irem
    //   2078: invokestatic abs : (I)I
    //   2081: invokevirtual charAt : (I)C
    //   2084: getstatic burp/Zkfz.Zs : Ljava/lang/String;
    //   2087: getstatic burp/Zzap.ZL : Ljava/lang/Object;
    //   2090: checkcast java/math/BigInteger
    //   2093: invokevirtual intValue : ()I
    //   2096: bipush #32
    //   2098: irem
    //   2099: invokestatic abs : (I)I
    //   2102: invokevirtual charAt : (I)C
    //   2105: if_icmple -> 2450
    //   2108: sipush #7541
    //   2111: sipush #-10203
    //   2114: invokestatic a : (II)Ljava/lang/String;
    //   2117: iconst_1
    //   2118: ldc burp/Zzok
    //   2120: invokevirtual getClassLoader : ()Ljava/lang/ClassLoader;
    //   2123: invokestatic forName : (Ljava/lang/String;ZLjava/lang/ClassLoader;)Ljava/lang/Class;
    //   2126: invokevirtual getDeclaredFields : ()[Ljava/lang/reflect/Field;
    //   2129: astore #5
    //   2131: aload #5
    //   2133: arraylength
    //   2134: istore #6
    //   2136: iconst_0
    //   2137: istore #7
    //   2139: iload #7
    //   2141: iload #6
    //   2143: if_icmpge -> 2281
    //   2146: aload #5
    //   2148: iload #7
    //   2150: aaload
    //   2151: astore #8
    //   2153: aload #8
    //   2155: invokevirtual getModifiers : ()I
    //   2158: invokestatic isStatic : (I)Z
    //   2161: ifne -> 2171
    //   2164: goto -> 2274
    //   2167: invokestatic a : (Ljava/lang/Throwable;)Ljava/lang/Throwable;
    //   2170: athrow
    //   2171: aload #8
    //   2173: invokevirtual getType : ()Ljava/lang/Class;
    //   2176: astore #9
    //   2178: aload #9
    //   2180: ifnull -> 2261
    //   2183: aload #9
    //   2185: invokevirtual isPrimitive : ()Z
    //   2188: ifne -> 2261
    //   2191: goto -> 2198
    //   2194: invokestatic a : (Ljava/lang/Throwable;)Ljava/lang/Throwable;
    //   2197: athrow
    //   2198: aload #9
    //   2200: invokevirtual getPackage : ()Ljava/lang/Package;
    //   2203: ifnull -> 2261
    //   2206: goto -> 2213
    //   2209: invokestatic a : (Ljava/lang/Throwable;)Ljava/lang/Throwable;
    //   2212: athrow
    //   2213: aload #9
    //   2215: invokevirtual getPackage : ()Ljava/lang/Package;
    //   2218: invokevirtual getName : ()Ljava/lang/String;
    //   2221: ifnull -> 2261
    //   2224: goto -> 2231
    //   2227: invokestatic a : (Ljava/lang/Throwable;)Ljava/lang/Throwable;
    //   2230: athrow
    //   2231: aload #9
    //   2233: invokevirtual getPackage : ()Ljava/lang/Package;
    //   2236: invokevirtual getName : ()Ljava/lang/String;
    //   2239: sipush #7522
    //   2242: sipush #16473
    //   2245: invokestatic a : (II)Ljava/lang/String;
    //   2248: invokevirtual startsWith : (Ljava/lang/String;)Z
    //   2251: ifne -> 2261
    //   2254: goto -> 2261
    //   2257: invokestatic a : (Ljava/lang/Throwable;)Ljava/lang/Throwable;
    //   2260: athrow
    //   2261: aload #8
    //   2263: iconst_1
    //   2264: invokevirtual setAccessible : (Z)V
    //   2267: aload #8
    //   2269: aconst_null
    //   2270: invokevirtual get : (Ljava/lang/Object;)Ljava/lang/Object;
    //   2273: pop
    //   2274: iinc #7, 1
    //   2277: iload_2
    //   2278: ifeq -> 2139
    //   2281: sipush #7535
    //   2284: sipush #-29799
    //   2287: invokestatic a : (II)Ljava/lang/String;
    //   2290: invokestatic forName : (Ljava/lang/String;)Ljava/lang/Class;
    //   2293: invokevirtual getDeclaredMethods : ()[Ljava/lang/reflect/Method;
    //   2296: astore #5
    //   2298: aload #5
    //   2300: arraylength
    //   2301: istore #6
    //   2303: iconst_0
    //   2304: istore #7
    //   2306: iload #7
    //   2308: iload #6
    //   2310: if_icmpge -> 2447
    //   2313: aload #5
    //   2315: iload #7
    //   2317: aaload
    //   2318: astore #8
    //   2320: aload #8
    //   2322: invokevirtual getParameterTypes : ()[Ljava/lang/Class;
    //   2325: pop
    //   2326: aload #8
    //   2328: invokevirtual getModifiers : ()I
    //   2331: invokestatic isStatic : (I)Z
    //   2334: ifeq -> 2433
    //   2337: aload #8
    //   2339: invokevirtual getParameterTypes : ()[Ljava/lang/Class;
    //   2342: arraylength
    //   2343: iconst_2
    //   2344: if_icmpne -> 2433
    //   2347: goto -> 2354
    //   2350: invokestatic a : (Ljava/lang/Throwable;)Ljava/lang/Throwable;
    //   2353: athrow
    //   2354: aload #8
    //   2356: invokevirtual getReturnType : ()Ljava/lang/Class;
    //   2359: getstatic java/lang/Boolean.TYPE : Ljava/lang/Class;
    //   2362: if_acmpne -> 2433
    //   2365: goto -> 2372
    //   2368: invokestatic a : (Ljava/lang/Throwable;)Ljava/lang/Throwable;
    //   2371: athrow
    //   2372: aload #8
    //   2374: iconst_1
    //   2375: invokevirtual setAccessible : (Z)V
    //   2378: aload #8
    //   2380: aconst_null
    //   2381: iconst_2
    //   2382: anewarray java/lang/Object
    //   2385: dup
    //   2386: iconst_0
    //   2387: aload_0
    //   2388: aastore
    //   2389: dup
    //   2390: iconst_1
    //   2391: aload_1
    //   2392: ifnonnull -> 2410
    //   2395: goto -> 2402
    //   2398: invokestatic a : (Ljava/lang/Throwable;)Ljava/lang/Throwable;
    //   2401: athrow
    //   2402: aload_1
    //   2403: goto -> 2417
    //   2406: invokestatic a : (Ljava/lang/Throwable;)Ljava/lang/Throwable;
    //   2409: athrow
    //   2410: aload_1
    //   2411: checkcast [B
    //   2414: invokevirtual clone : ()Ljava/lang/Object;
    //   2417: aastore
    //   2418: invokevirtual invoke : (Ljava/lang/Object;[Ljava/lang/Object;)Ljava/lang/Object;
    //   2421: checkcast java/lang/Boolean
    //   2424: invokevirtual booleanValue : ()Z
    //   2427: istore #4
    //   2429: iload_2
    //   2430: ifeq -> 2447
    //   2433: iinc #7, 1
    //   2436: iload_2
    //   2437: ifeq -> 2306
    //   2440: goto -> 2447
    //   2443: invokestatic a : (Ljava/lang/Throwable;)Ljava/lang/Throwable;
    //   2446: athrow
    //   2447: goto -> 2789
    //   2450: sipush #7520
    //   2453: sipush #-19341
    //   2456: invokestatic a : (II)Ljava/lang/String;
    //   2459: iconst_1
    //   2460: ldc burp/Zmcq
    //   2462: invokevirtual getClassLoader : ()Ljava/lang/ClassLoader;
    //   2465: invokestatic forName : (Ljava/lang/String;ZLjava/lang/ClassLoader;)Ljava/lang/Class;
    //   2468: invokevirtual getDeclaredFields : ()[Ljava/lang/reflect/Field;
    //   2471: astore #5
    //   2473: aload #5
    //   2475: arraylength
    //   2476: istore #6
    //   2478: iconst_0
    //   2479: istore #7
    //   2481: iload #7
    //   2483: iload #6
    //   2485: if_icmpge -> 2623
    //   2488: aload #5
    //   2490: iload #7
    //   2492: aaload
    //   2493: astore #8
    //   2495: aload #8
    //   2497: invokevirtual getModifiers : ()I
    //   2500: invokestatic isStatic : (I)Z
    //   2503: ifne -> 2513
    //   2506: goto -> 2616
    //   2509: invokestatic a : (Ljava/lang/Throwable;)Ljava/lang/Throwable;
    //   2512: athrow
    //   2513: aload #8
    //   2515: invokevirtual getType : ()Ljava/lang/Class;
    //   2518: astore #9
    //   2520: aload #9
    //   2522: ifnull -> 2603
    //   2525: aload #9
    //   2527: invokevirtual isPrimitive : ()Z
    //   2530: ifne -> 2603
    //   2533: goto -> 2540
    //   2536: invokestatic a : (Ljava/lang/Throwable;)Ljava/lang/Throwable;
    //   2539: athrow
    //   2540: aload #9
    //   2542: invokevirtual getPackage : ()Ljava/lang/Package;
    //   2545: ifnull -> 2603
    //   2548: goto -> 2555
    //   2551: invokestatic a : (Ljava/lang/Throwable;)Ljava/lang/Throwable;
    //   2554: athrow
    //   2555: aload #9
    //   2557: invokevirtual getPackage : ()Ljava/lang/Package;
    //   2560: invokevirtual getName : ()Ljava/lang/String;
    //   2563: ifnull -> 2603
    //   2566: goto -> 2573
    //   2569: invokestatic a : (Ljava/lang/Throwable;)Ljava/lang/Throwable;
    //   2572: athrow
    //   2573: aload #9
    //   2575: invokevirtual getPackage : ()Ljava/lang/Package;
    //   2578: invokevirtual getName : ()Ljava/lang/String;
    //   2581: sipush #7522
    //   2584: sipush #16473
    //   2587: invokestatic a : (II)Ljava/lang/String;
    //   2590: invokevirtual startsWith : (Ljava/lang/String;)Z
    //   2593: ifne -> 2603
    //   2596: goto -> 2603
    //   2599: invokestatic a : (Ljava/lang/Throwable;)Ljava/lang/Throwable;
    //   2602: athrow
    //   2603: aload #8
    //   2605: iconst_1
    //   2606: invokevirtual setAccessible : (Z)V
    //   2609: aload #8
    //   2611: aconst_null
    //   2612: invokevirtual get : (Ljava/lang/Object;)Ljava/lang/Object;
    //   2615: pop
    //   2616: iinc #7, 1
    //   2619: iload_2
    //   2620: ifeq -> 2481
    //   2623: sipush #7542
    //   2626: sipush #1299
    //   2629: invokestatic a : (II)Ljava/lang/String;
    //   2632: invokestatic forName : (Ljava/lang/String;)Ljava/lang/Class;
    //   2635: invokevirtual getDeclaredMethods : ()[Ljava/lang/reflect/Method;
    //   2638: astore #5
    //   2640: aload #5
    //   2642: arraylength
    //   2643: istore #6
    //   2645: iconst_0
    //   2646: istore #7
    //   2648: iload #7
    //   2650: iload #6
    //   2652: if_icmpge -> 2789
    //   2655: aload #5
    //   2657: iload #7
    //   2659: aaload
    //   2660: astore #8
    //   2662: aload #8
    //   2664: invokevirtual getParameterTypes : ()[Ljava/lang/Class;
    //   2667: pop
    //   2668: aload #8
    //   2670: invokevirtual getModifiers : ()I
    //   2673: invokestatic isStatic : (I)Z
    //   2676: ifeq -> 2775
    //   2679: aload #8
    //   2681: invokevirtual getParameterTypes : ()[Ljava/lang/Class;
    //   2684: arraylength
    //   2685: iconst_2
    //   2686: if_icmpne -> 2775
    //   2689: goto -> 2696
    //   2692: invokestatic a : (Ljava/lang/Throwable;)Ljava/lang/Throwable;
    //   2695: athrow
    //   2696: aload #8
    //   2698: invokevirtual getReturnType : ()Ljava/lang/Class;
    //   2701: getstatic java/lang/Boolean.TYPE : Ljava/lang/Class;
    //   2704: if_acmpne -> 2775
    //   2707: goto -> 2714
    //   2710: invokestatic a : (Ljava/lang/Throwable;)Ljava/lang/Throwable;
    //   2713: athrow
    //   2714: aload #8
    //   2716: iconst_1
    //   2717: invokevirtual setAccessible : (Z)V
    //   2720: aload #8
    //   2722: aconst_null
    //   2723: iconst_2
    //   2724: anewarray java/lang/Object
    //   2727: dup
    //   2728: iconst_0
    //   2729: aload_0
    //   2730: aastore
    //   2731: dup
    //   2732: iconst_1
    //   2733: aload_1
    //   2734: ifnonnull -> 2752
    //   2737: goto -> 2744
    //   2740: invokestatic a : (Ljava/lang/Throwable;)Ljava/lang/Throwable;
    //   2743: athrow
    //   2744: aload_1
    //   2745: goto -> 2759
    //   2748: invokestatic a : (Ljava/lang/Throwable;)Ljava/lang/Throwable;
    //   2751: athrow
    //   2752: aload_1
    //   2753: checkcast [B
    //   2756: invokevirtual clone : ()Ljava/lang/Object;
    //   2759: aastore
    //   2760: invokevirtual invoke : (Ljava/lang/Object;[Ljava/lang/Object;)Ljava/lang/Object;
    //   2763: checkcast java/lang/Boolean
    //   2766: invokevirtual booleanValue : ()Z
    //   2769: istore #4
    //   2771: iload_2
    //   2772: ifeq -> 2789
    //   2775: iinc #7, 1
    //   2778: iload_2
    //   2779: ifeq -> 2648
    //   2782: goto -> 2789
    //   2785: invokestatic a : (Ljava/lang/Throwable;)Ljava/lang/Throwable;
    //   2788: athrow
    //   2789: iload #4
    //   2791: ifeq -> 2797
    //   2794: iload #4
    //   2796: ireturn
    //   2797: getstatic burp/Zrbp.Ze : Ljava/lang/String;
    //   2800: getstatic burp/Zxyp.ZZ : Ljava/lang/Object;
    //   2803: checkcast java/math/BigInteger
    //   2806: invokevirtual intValue : ()I
    //   2809: bipush #32
    //   2811: irem
    //   2812: invokestatic abs : (I)I
    //   2815: invokevirtual charAt : (I)C
    //   2818: getstatic burp/Zxzd.ZM : Ljava/lang/String;
    //   2821: getstatic burp/Zx4w.Zp : Ljava/lang/Object;
    //   2824: checkcast java/math/BigInteger
    //   2827: invokevirtual intValue : ()I
    //   2830: bipush #32
    //   2832: irem
    //   2833: invokestatic abs : (I)I
    //   2836: invokevirtual charAt : (I)C
    //   2839: if_icmpgt -> 3185
    //   2842: sipush #7537
    //   2845: sipush #25989
    //   2848: invokestatic a : (II)Ljava/lang/String;
    //   2851: iconst_1
    //   2852: ldc burp/Zkm0
    //   2854: invokevirtual getClassLoader : ()Ljava/lang/ClassLoader;
    //   2857: invokestatic forName : (Ljava/lang/String;ZLjava/lang/ClassLoader;)Ljava/lang/Class;
    //   2860: invokevirtual getDeclaredFields : ()[Ljava/lang/reflect/Field;
    //   2863: astore #5
    //   2865: aload #5
    //   2867: arraylength
    //   2868: istore #6
    //   2870: iconst_0
    //   2871: istore #7
    //   2873: iload #7
    //   2875: iload #6
    //   2877: if_icmpge -> 3015
    //   2880: aload #5
    //   2882: iload #7
    //   2884: aaload
    //   2885: astore #8
    //   2887: aload #8
    //   2889: invokevirtual getModifiers : ()I
    //   2892: invokestatic isStatic : (I)Z
    //   2895: ifne -> 2905
    //   2898: goto -> 3008
    //   2901: invokestatic a : (Ljava/lang/Throwable;)Ljava/lang/Throwable;
    //   2904: athrow
    //   2905: aload #8
    //   2907: invokevirtual getType : ()Ljava/lang/Class;
    //   2910: astore #9
    //   2912: aload #9
    //   2914: ifnull -> 2995
    //   2917: aload #9
    //   2919: invokevirtual isPrimitive : ()Z
    //   2922: ifne -> 2995
    //   2925: goto -> 2932
    //   2928: invokestatic a : (Ljava/lang/Throwable;)Ljava/lang/Throwable;
    //   2931: athrow
    //   2932: aload #9
    //   2934: invokevirtual getPackage : ()Ljava/lang/Package;
    //   2937: ifnull -> 2995
    //   2940: goto -> 2947
    //   2943: invokestatic a : (Ljava/lang/Throwable;)Ljava/lang/Throwable;
    //   2946: athrow
    //   2947: aload #9
    //   2949: invokevirtual getPackage : ()Ljava/lang/Package;
    //   2952: invokevirtual getName : ()Ljava/lang/String;
    //   2955: ifnull -> 2995
    //   2958: goto -> 2965
    //   2961: invokestatic a : (Ljava/lang/Throwable;)Ljava/lang/Throwable;
    //   2964: athrow
    //   2965: aload #9
    //   2967: invokevirtual getPackage : ()Ljava/lang/Package;
    //   2970: invokevirtual getName : ()Ljava/lang/String;
    //   2973: sipush #7522
    //   2976: sipush #16473
    //   2979: invokestatic a : (II)Ljava/lang/String;
    //   2982: invokevirtual startsWith : (Ljava/lang/String;)Z
    //   2985: ifne -> 2995
    //   2988: goto -> 2995
    //   2991: invokestatic a : (Ljava/lang/Throwable;)Ljava/lang/Throwable;
    //   2994: athrow
    //   2995: aload #8
    //   2997: iconst_1
    //   2998: invokevirtual setAccessible : (Z)V
    //   3001: aload #8
    //   3003: aconst_null
    //   3004: invokevirtual get : (Ljava/lang/Object;)Ljava/lang/Object;
    //   3007: pop
    //   3008: iinc #7, 1
    //   3011: iload_2
    //   3012: ifeq -> 2873
    //   3015: sipush #7547
    //   3018: sipush #20083
    //   3021: invokestatic a : (II)Ljava/lang/String;
    //   3024: invokestatic forName : (Ljava/lang/String;)Ljava/lang/Class;
    //   3027: invokevirtual getDeclaredMethods : ()[Ljava/lang/reflect/Method;
    //   3030: astore #5
    //   3032: aload #5
    //   3034: arraylength
    //   3035: istore #6
    //   3037: iconst_0
    //   3038: istore #7
    //   3040: iload #7
    //   3042: iload #6
    //   3044: if_icmpge -> 3181
    //   3047: aload #5
    //   3049: iload #7
    //   3051: aaload
    //   3052: astore #8
    //   3054: aload #8
    //   3056: invokevirtual getParameterTypes : ()[Ljava/lang/Class;
    //   3059: pop
    //   3060: aload #8
    //   3062: invokevirtual getModifiers : ()I
    //   3065: invokestatic isStatic : (I)Z
    //   3068: ifeq -> 3167
    //   3071: aload #8
    //   3073: invokevirtual getParameterTypes : ()[Ljava/lang/Class;
    //   3076: arraylength
    //   3077: iconst_2
    //   3078: if_icmpne -> 3167
    //   3081: goto -> 3088
    //   3084: invokestatic a : (Ljava/lang/Throwable;)Ljava/lang/Throwable;
    //   3087: athrow
    //   3088: aload #8
    //   3090: invokevirtual getReturnType : ()Ljava/lang/Class;
    //   3093: getstatic java/lang/Boolean.TYPE : Ljava/lang/Class;
    //   3096: if_acmpne -> 3167
    //   3099: goto -> 3106
    //   3102: invokestatic a : (Ljava/lang/Throwable;)Ljava/lang/Throwable;
    //   3105: athrow
    //   3106: aload #8
    //   3108: iconst_1
    //   3109: invokevirtual setAccessible : (Z)V
    //   3112: aload #8
    //   3114: aconst_null
    //   3115: iconst_2
    //   3116: anewarray java/lang/Object
    //   3119: dup
    //   3120: iconst_0
    //   3121: aload_0
    //   3122: aastore
    //   3123: dup
    //   3124: iconst_1
    //   3125: aload_1
    //   3126: ifnonnull -> 3144
    //   3129: goto -> 3136
    //   3132: invokestatic a : (Ljava/lang/Throwable;)Ljava/lang/Throwable;
    //   3135: athrow
    //   3136: aload_1
    //   3137: goto -> 3151
    //   3140: invokestatic a : (Ljava/lang/Throwable;)Ljava/lang/Throwable;
    //   3143: athrow
    //   3144: aload_1
    //   3145: checkcast [B
    //   3148: invokevirtual clone : ()Ljava/lang/Object;
    //   3151: aastore
    //   3152: invokevirtual invoke : (Ljava/lang/Object;[Ljava/lang/Object;)Ljava/lang/Object;
    //   3155: checkcast java/lang/Boolean
    //   3158: invokevirtual booleanValue : ()Z
    //   3161: istore #4
    //   3163: iload_2
    //   3164: ifeq -> 3181
    //   3167: iinc #7, 1
    //   3170: iload_2
    //   3171: ifeq -> 3040
    //   3174: goto -> 3181
    //   3177: invokestatic a : (Ljava/lang/Throwable;)Ljava/lang/Throwable;
    //   3180: athrow
    //   3181: iload_2
    //   3182: ifeq -> 3524
    //   3185: sipush #7521
    //   3188: sipush #-11366
    //   3191: invokestatic a : (II)Ljava/lang/String;
    //   3194: iconst_1
    //   3195: ldc burp/Zrkc
    //   3197: invokevirtual getClassLoader : ()Ljava/lang/ClassLoader;
    //   3200: invokestatic forName : (Ljava/lang/String;ZLjava/lang/ClassLoader;)Ljava/lang/Class;
    //   3203: invokevirtual getDeclaredFields : ()[Ljava/lang/reflect/Field;
    //   3206: astore #5
    //   3208: aload #5
    //   3210: arraylength
    //   3211: istore #6
    //   3213: iconst_0
    //   3214: istore #7
    //   3216: iload #7
    //   3218: iload #6
    //   3220: if_icmpge -> 3358
    //   3223: aload #5
    //   3225: iload #7
    //   3227: aaload
    //   3228: astore #8
    //   3230: aload #8
    //   3232: invokevirtual getModifiers : ()I
    //   3235: invokestatic isStatic : (I)Z
    //   3238: ifne -> 3248
    //   3241: goto -> 3351
    //   3244: invokestatic a : (Ljava/lang/Throwable;)Ljava/lang/Throwable;
    //   3247: athrow
    //   3248: aload #8
    //   3250: invokevirtual getType : ()Ljava/lang/Class;
    //   3253: astore #9
    //   3255: aload #9
    //   3257: ifnull -> 3338
    //   3260: aload #9
    //   3262: invokevirtual isPrimitive : ()Z
    //   3265: ifne -> 3338
    //   3268: goto -> 3275
    //   3271: invokestatic a : (Ljava/lang/Throwable;)Ljava/lang/Throwable;
    //   3274: athrow
    //   3275: aload #9
    //   3277: invokevirtual getPackage : ()Ljava/lang/Package;
    //   3280: ifnull -> 3338
    //   3283: goto -> 3290
    //   3286: invokestatic a : (Ljava/lang/Throwable;)Ljava/lang/Throwable;
    //   3289: athrow
    //   3290: aload #9
    //   3292: invokevirtual getPackage : ()Ljava/lang/Package;
    //   3295: invokevirtual getName : ()Ljava/lang/String;
    //   3298: ifnull -> 3338
    //   3301: goto -> 3308
    //   3304: invokestatic a : (Ljava/lang/Throwable;)Ljava/lang/Throwable;
    //   3307: athrow
    //   3308: aload #9
    //   3310: invokevirtual getPackage : ()Ljava/lang/Package;
    //   3313: invokevirtual getName : ()Ljava/lang/String;
    //   3316: sipush #7522
    //   3319: sipush #16473
    //   3322: invokestatic a : (II)Ljava/lang/String;
    //   3325: invokevirtual startsWith : (Ljava/lang/String;)Z
    //   3328: ifne -> 3338
    //   3331: goto -> 3338
    //   3334: invokestatic a : (Ljava/lang/Throwable;)Ljava/lang/Throwable;
    //   3337: athrow
    //   3338: aload #8
    //   3340: iconst_1
    //   3341: invokevirtual setAccessible : (Z)V
    //   3344: aload #8
    //   3346: aconst_null
    //   3347: invokevirtual get : (Ljava/lang/Object;)Ljava/lang/Object;
    //   3350: pop
    //   3351: iinc #7, 1
    //   3354: iload_2
    //   3355: ifeq -> 3216
    //   3358: sipush #7524
    //   3361: sipush #30612
    //   3364: invokestatic a : (II)Ljava/lang/String;
    //   3367: invokestatic forName : (Ljava/lang/String;)Ljava/lang/Class;
    //   3370: invokevirtual getDeclaredMethods : ()[Ljava/lang/reflect/Method;
    //   3373: astore #5
    //   3375: aload #5
    //   3377: arraylength
    //   3378: istore #6
    //   3380: iconst_0
    //   3381: istore #7
    //   3383: iload #7
    //   3385: iload #6
    //   3387: if_icmpge -> 3524
    //   3390: aload #5
    //   3392: iload #7
    //   3394: aaload
    //   3395: astore #8
    //   3397: aload #8
    //   3399: invokevirtual getParameterTypes : ()[Ljava/lang/Class;
    //   3402: pop
    //   3403: aload #8
    //   3405: invokevirtual getModifiers : ()I
    //   3408: invokestatic isStatic : (I)Z
    //   3411: ifeq -> 3510
    //   3414: aload #8
    //   3416: invokevirtual getParameterTypes : ()[Ljava/lang/Class;
    //   3419: arraylength
    //   3420: iconst_2
    //   3421: if_icmpne -> 3510
    //   3424: goto -> 3431
    //   3427: invokestatic a : (Ljava/lang/Throwable;)Ljava/lang/Throwable;
    //   3430: athrow
    //   3431: aload #8
    //   3433: invokevirtual getReturnType : ()Ljava/lang/Class;
    //   3436: getstatic java/lang/Boolean.TYPE : Ljava/lang/Class;
    //   3439: if_acmpne -> 3510
    //   3442: goto -> 3449
    //   3445: invokestatic a : (Ljava/lang/Throwable;)Ljava/lang/Throwable;
    //   3448: athrow
    //   3449: aload #8
    //   3451: iconst_1
    //   3452: invokevirtual setAccessible : (Z)V
    //   3455: aload #8
    //   3457: aconst_null
    //   3458: iconst_2
    //   3459: anewarray java/lang/Object
    //   3462: dup
    //   3463: iconst_0
    //   3464: aload_0
    //   3465: aastore
    //   3466: dup
    //   3467: iconst_1
    //   3468: aload_1
    //   3469: ifnonnull -> 3487
    //   3472: goto -> 3479
    //   3475: invokestatic a : (Ljava/lang/Throwable;)Ljava/lang/Throwable;
    //   3478: athrow
    //   3479: aload_1
    //   3480: goto -> 3494
    //   3483: invokestatic a : (Ljava/lang/Throwable;)Ljava/lang/Throwable;
    //   3486: athrow
    //   3487: aload_1
    //   3488: checkcast [B
    //   3491: invokevirtual clone : ()Ljava/lang/Object;
    //   3494: aastore
    //   3495: invokevirtual invoke : (Ljava/lang/Object;[Ljava/lang/Object;)Ljava/lang/Object;
    //   3498: checkcast java/lang/Boolean
    //   3501: invokevirtual booleanValue : ()Z
    //   3504: istore #4
    //   3506: iload_2
    //   3507: ifeq -> 3524
    //   3510: iinc #7, 1
    //   3513: iload_2
    //   3514: ifeq -> 3383
    //   3517: goto -> 3524
    //   3520: invokestatic a : (Ljava/lang/Throwable;)Ljava/lang/Throwable;
    //   3523: athrow
    //   3524: iload #4
    //   3526: ifeq -> 3532
    //   3529: iload #4
    //   3531: ireturn
    //   3532: getstatic burp/Zbsr.Zq : Ljava/lang/String;
    //   3535: getstatic burp/Zer.Zk : Ljava/lang/Object;
    //   3538: checkcast java/math/BigInteger
    //   3541: invokevirtual intValue : ()I
    //   3544: bipush #32
    //   3546: irem
    //   3547: invokestatic abs : (I)I
    //   3550: invokevirtual charAt : (I)C
    //   3553: getstatic burp/Zg7p.ZA : Ljava/lang/String;
    //   3556: getstatic burp/Zein.Zb : Ljava/lang/Object;
    //   3559: checkcast java/math/BigInteger
    //   3562: invokevirtual intValue : ()I
    //   3565: bipush #32
    //   3567: irem
    //   3568: invokestatic abs : (I)I
    //   3571: invokevirtual charAt : (I)C
    //   3574: if_icmple -> 3920
    //   3577: sipush #7538
    //   3580: sipush #-3769
    //   3583: invokestatic a : (II)Ljava/lang/String;
    //   3586: iconst_1
    //   3587: ldc burp/Zrct
    //   3589: invokevirtual getClassLoader : ()Ljava/lang/ClassLoader;
    //   3592: invokestatic forName : (Ljava/lang/String;ZLjava/lang/ClassLoader;)Ljava/lang/Class;
    //   3595: invokevirtual getDeclaredFields : ()[Ljava/lang/reflect/Field;
    //   3598: astore #5
    //   3600: aload #5
    //   3602: arraylength
    //   3603: istore #6
    //   3605: iconst_0
    //   3606: istore #7
    //   3608: iload #7
    //   3610: iload #6
    //   3612: if_icmpge -> 3750
    //   3615: aload #5
    //   3617: iload #7
    //   3619: aaload
    //   3620: astore #8
    //   3622: aload #8
    //   3624: invokevirtual getModifiers : ()I
    //   3627: invokestatic isStatic : (I)Z
    //   3630: ifne -> 3640
    //   3633: goto -> 3743
    //   3636: invokestatic a : (Ljava/lang/Throwable;)Ljava/lang/Throwable;
    //   3639: athrow
    //   3640: aload #8
    //   3642: invokevirtual getType : ()Ljava/lang/Class;
    //   3645: astore #9
    //   3647: aload #9
    //   3649: ifnull -> 3730
    //   3652: aload #9
    //   3654: invokevirtual isPrimitive : ()Z
    //   3657: ifne -> 3730
    //   3660: goto -> 3667
    //   3663: invokestatic a : (Ljava/lang/Throwable;)Ljava/lang/Throwable;
    //   3666: athrow
    //   3667: aload #9
    //   3669: invokevirtual getPackage : ()Ljava/lang/Package;
    //   3672: ifnull -> 3730
    //   3675: goto -> 3682
    //   3678: invokestatic a : (Ljava/lang/Throwable;)Ljava/lang/Throwable;
    //   3681: athrow
    //   3682: aload #9
    //   3684: invokevirtual getPackage : ()Ljava/lang/Package;
    //   3687: invokevirtual getName : ()Ljava/lang/String;
    //   3690: ifnull -> 3730
    //   3693: goto -> 3700
    //   3696: invokestatic a : (Ljava/lang/Throwable;)Ljava/lang/Throwable;
    //   3699: athrow
    //   3700: aload #9
    //   3702: invokevirtual getPackage : ()Ljava/lang/Package;
    //   3705: invokevirtual getName : ()Ljava/lang/String;
    //   3708: sipush #7522
    //   3711: sipush #16473
    //   3714: invokestatic a : (II)Ljava/lang/String;
    //   3717: invokevirtual startsWith : (Ljava/lang/String;)Z
    //   3720: ifne -> 3730
    //   3723: goto -> 3730
    //   3726: invokestatic a : (Ljava/lang/Throwable;)Ljava/lang/Throwable;
    //   3729: athrow
    //   3730: aload #8
    //   3732: iconst_1
    //   3733: invokevirtual setAccessible : (Z)V
    //   3736: aload #8
    //   3738: aconst_null
    //   3739: invokevirtual get : (Ljava/lang/Object;)Ljava/lang/Object;
    //   3742: pop
    //   3743: iinc #7, 1
    //   3746: iload_2
    //   3747: ifeq -> 3608
    //   3750: sipush #7533
    //   3753: sipush #-30104
    //   3756: invokestatic a : (II)Ljava/lang/String;
    //   3759: invokestatic forName : (Ljava/lang/String;)Ljava/lang/Class;
    //   3762: invokevirtual getDeclaredMethods : ()[Ljava/lang/reflect/Method;
    //   3765: astore #5
    //   3767: aload #5
    //   3769: arraylength
    //   3770: istore #6
    //   3772: iconst_0
    //   3773: istore #7
    //   3775: iload #7
    //   3777: iload #6
    //   3779: if_icmpge -> 3916
    //   3782: aload #5
    //   3784: iload #7
    //   3786: aaload
    //   3787: astore #8
    //   3789: aload #8
    //   3791: invokevirtual getParameterTypes : ()[Ljava/lang/Class;
    //   3794: pop
    //   3795: aload #8
    //   3797: invokevirtual getModifiers : ()I
    //   3800: invokestatic isStatic : (I)Z
    //   3803: ifeq -> 3902
    //   3806: aload #8
    //   3808: invokevirtual getParameterTypes : ()[Ljava/lang/Class;
    //   3811: arraylength
    //   3812: iconst_2
    //   3813: if_icmpne -> 3902
    //   3816: goto -> 3823
    //   3819: invokestatic a : (Ljava/lang/Throwable;)Ljava/lang/Throwable;
    //   3822: athrow
    //   3823: aload #8
    //   3825: invokevirtual getReturnType : ()Ljava/lang/Class;
    //   3828: getstatic java/lang/Boolean.TYPE : Ljava/lang/Class;
    //   3831: if_acmpne -> 3902
    //   3834: goto -> 3841
    //   3837: invokestatic a : (Ljava/lang/Throwable;)Ljava/lang/Throwable;
    //   3840: athrow
    //   3841: aload #8
    //   3843: iconst_1
    //   3844: invokevirtual setAccessible : (Z)V
    //   3847: aload #8
    //   3849: aconst_null
    //   3850: iconst_2
    //   3851: anewarray java/lang/Object
    //   3854: dup
    //   3855: iconst_0
    //   3856: aload_0
    //   3857: aastore
    //   3858: dup
    //   3859: iconst_1
    //   3860: aload_1
    //   3861: ifnonnull -> 3879
    //   3864: goto -> 3871
    //   3867: invokestatic a : (Ljava/lang/Throwable;)Ljava/lang/Throwable;
    //   3870: athrow
    //   3871: aload_1
    //   3872: goto -> 3886
    //   3875: invokestatic a : (Ljava/lang/Throwable;)Ljava/lang/Throwable;
    //   3878: athrow
    //   3879: aload_1
    //   3880: checkcast [B
    //   3883: invokevirtual clone : ()Ljava/lang/Object;
    //   3886: aastore
    //   3887: invokevirtual invoke : (Ljava/lang/Object;[Ljava/lang/Object;)Ljava/lang/Object;
    //   3890: checkcast java/lang/Boolean
    //   3893: invokevirtual booleanValue : ()Z
    //   3896: istore #4
    //   3898: iload_2
    //   3899: ifeq -> 3916
    //   3902: iinc #7, 1
    //   3905: iload_2
    //   3906: ifeq -> 3775
    //   3909: goto -> 3916
    //   3912: invokestatic a : (Ljava/lang/Throwable;)Ljava/lang/Throwable;
    //   3915: athrow
    //   3916: iload_2
    //   3917: ifeq -> 4259
    //   3920: sipush #7525
    //   3923: sipush #-20888
    //   3926: invokestatic a : (II)Ljava/lang/String;
    //   3929: iconst_1
    //   3930: ldc burp/Zmlr
    //   3932: invokevirtual getClassLoader : ()Ljava/lang/ClassLoader;
    //   3935: invokestatic forName : (Ljava/lang/String;ZLjava/lang/ClassLoader;)Ljava/lang/Class;
    //   3938: invokevirtual getDeclaredFields : ()[Ljava/lang/reflect/Field;
    //   3941: astore #5
    //   3943: aload #5
    //   3945: arraylength
    //   3946: istore #6
    //   3948: iconst_0
    //   3949: istore #7
    //   3951: iload #7
    //   3953: iload #6
    //   3955: if_icmpge -> 4093
    //   3958: aload #5
    //   3960: iload #7
    //   3962: aaload
    //   3963: astore #8
    //   3965: aload #8
    //   3967: invokevirtual getModifiers : ()I
    //   3970: invokestatic isStatic : (I)Z
    //   3973: ifne -> 3983
    //   3976: goto -> 4086
    //   3979: invokestatic a : (Ljava/lang/Throwable;)Ljava/lang/Throwable;
    //   3982: athrow
    //   3983: aload #8
    //   3985: invokevirtual getType : ()Ljava/lang/Class;
    //   3988: astore #9
    //   3990: aload #9
    //   3992: ifnull -> 4073
    //   3995: aload #9
    //   3997: invokevirtual isPrimitive : ()Z
    //   4000: ifne -> 4073
    //   4003: goto -> 4010
    //   4006: invokestatic a : (Ljava/lang/Throwable;)Ljava/lang/Throwable;
    //   4009: athrow
    //   4010: aload #9
    //   4012: invokevirtual getPackage : ()Ljava/lang/Package;
    //   4015: ifnull -> 4073
    //   4018: goto -> 4025
    //   4021: invokestatic a : (Ljava/lang/Throwable;)Ljava/lang/Throwable;
    //   4024: athrow
    //   4025: aload #9
    //   4027: invokevirtual getPackage : ()Ljava/lang/Package;
    //   4030: invokevirtual getName : ()Ljava/lang/String;
    //   4033: ifnull -> 4073
    //   4036: goto -> 4043
    //   4039: invokestatic a : (Ljava/lang/Throwable;)Ljava/lang/Throwable;
    //   4042: athrow
    //   4043: aload #9
    //   4045: invokevirtual getPackage : ()Ljava/lang/Package;
    //   4048: invokevirtual getName : ()Ljava/lang/String;
    //   4051: sipush #7522
    //   4054: sipush #16473
    //   4057: invokestatic a : (II)Ljava/lang/String;
    //   4060: invokevirtual startsWith : (Ljava/lang/String;)Z
    //   4063: ifne -> 4073
    //   4066: goto -> 4073
    //   4069: invokestatic a : (Ljava/lang/Throwable;)Ljava/lang/Throwable;
    //   4072: athrow
    //   4073: aload #8
    //   4075: iconst_1
    //   4076: invokevirtual setAccessible : (Z)V
    //   4079: aload #8
    //   4081: aconst_null
    //   4082: invokevirtual get : (Ljava/lang/Object;)Ljava/lang/Object;
    //   4085: pop
    //   4086: iinc #7, 1
    //   4089: iload_2
    //   4090: ifeq -> 3951
    //   4093: sipush #7546
    //   4096: sipush #3963
    //   4099: invokestatic a : (II)Ljava/lang/String;
    //   4102: invokestatic forName : (Ljava/lang/String;)Ljava/lang/Class;
    //   4105: invokevirtual getDeclaredMethods : ()[Ljava/lang/reflect/Method;
    //   4108: astore #5
    //   4110: aload #5
    //   4112: arraylength
    //   4113: istore #6
    //   4115: iconst_0
    //   4116: istore #7
    //   4118: iload #7
    //   4120: iload #6
    //   4122: if_icmpge -> 4259
    //   4125: aload #5
    //   4127: iload #7
    //   4129: aaload
    //   4130: astore #8
    //   4132: aload #8
    //   4134: invokevirtual getParameterTypes : ()[Ljava/lang/Class;
    //   4137: pop
    //   4138: aload #8
    //   4140: invokevirtual getModifiers : ()I
    //   4143: invokestatic isStatic : (I)Z
    //   4146: ifeq -> 4245
    //   4149: aload #8
    //   4151: invokevirtual getParameterTypes : ()[Ljava/lang/Class;
    //   4154: arraylength
    //   4155: iconst_2
    //   4156: if_icmpne -> 4245
    //   4159: goto -> 4166
    //   4162: invokestatic a : (Ljava/lang/Throwable;)Ljava/lang/Throwable;
    //   4165: athrow
    //   4166: aload #8
    //   4168: invokevirtual getReturnType : ()Ljava/lang/Class;
    //   4171: getstatic java/lang/Boolean.TYPE : Ljava/lang/Class;
    //   4174: if_acmpne -> 4245
    //   4177: goto -> 4184
    //   4180: invokestatic a : (Ljava/lang/Throwable;)Ljava/lang/Throwable;
    //   4183: athrow
    //   4184: aload #8
    //   4186: iconst_1
    //   4187: invokevirtual setAccessible : (Z)V
    //   4190: aload #8
    //   4192: aconst_null
    //   4193: iconst_2
    //   4194: anewarray java/lang/Object
    //   4197: dup
    //   4198: iconst_0
    //   4199: aload_0
    //   4200: aastore
    //   4201: dup
    //   4202: iconst_1
    //   4203: aload_1
    //   4204: ifnonnull -> 4222
    //   4207: goto -> 4214
    //   4210: invokestatic a : (Ljava/lang/Throwable;)Ljava/lang/Throwable;
    //   4213: athrow
    //   4214: aload_1
    //   4215: goto -> 4229
    //   4218: invokestatic a : (Ljava/lang/Throwable;)Ljava/lang/Throwable;
    //   4221: athrow
    //   4222: aload_1
    //   4223: checkcast [B
    //   4226: invokevirtual clone : ()Ljava/lang/Object;
    //   4229: aastore
    //   4230: invokevirtual invoke : (Ljava/lang/Object;[Ljava/lang/Object;)Ljava/lang/Object;
    //   4233: checkcast java/lang/Boolean
    //   4236: invokevirtual booleanValue : ()Z
    //   4239: istore #4
    //   4241: iload_2
    //   4242: ifeq -> 4259
    //   4245: iinc #7, 1
    //   4248: iload_2
    //   4249: ifeq -> 4118
    //   4252: goto -> 4259
    //   4255: invokestatic a : (Ljava/lang/Throwable;)Ljava/lang/Throwable;
    //   4258: athrow
    //   4259: iload #4
    //   4261: ifeq -> 4267
    //   4264: iload #4
    //   4266: ireturn
    //   4267: getstatic burp/Zd1.ZN : Ljava/lang/String;
    //   4270: getstatic burp/Ze3j.Ze : Ljava/lang/Object;
    //   4273: checkcast java/math/BigInteger
    //   4276: invokevirtual intValue : ()I
    //   4279: bipush #32
    //   4281: irem
    //   4282: invokestatic abs : (I)I
    //   4285: invokevirtual charAt : (I)C
    //   4288: getstatic burp/Zb3z.Zi : Ljava/lang/String;
    //   4291: getstatic burp/Zsby.ZZ : Ljava/lang/Object;
    //   4294: checkcast java/math/BigInteger
    //   4297: invokevirtual intValue : ()I
    //   4300: bipush #32
    //   4302: irem
    //   4303: invokestatic abs : (I)I
    //   4306: invokevirtual charAt : (I)C
    //   4309: if_icmpgt -> 4655
    //   4312: sipush #7540
    //   4315: sipush #-31429
    //   4318: invokestatic a : (II)Ljava/lang/String;
    //   4321: iconst_1
    //   4322: ldc burp/Zghe
    //   4324: invokevirtual getClassLoader : ()Ljava/lang/ClassLoader;
    //   4327: invokestatic forName : (Ljava/lang/String;ZLjava/lang/ClassLoader;)Ljava/lang/Class;
    //   4330: invokevirtual getDeclaredFields : ()[Ljava/lang/reflect/Field;
    //   4333: astore #5
    //   4335: aload #5
    //   4337: arraylength
    //   4338: istore #6
    //   4340: iconst_0
    //   4341: istore #7
    //   4343: iload #7
    //   4345: iload #6
    //   4347: if_icmpge -> 4485
    //   4350: aload #5
    //   4352: iload #7
    //   4354: aaload
    //   4355: astore #8
    //   4357: aload #8
    //   4359: invokevirtual getModifiers : ()I
    //   4362: invokestatic isStatic : (I)Z
    //   4365: ifne -> 4375
    //   4368: goto -> 4478
    //   4371: invokestatic a : (Ljava/lang/Throwable;)Ljava/lang/Throwable;
    //   4374: athrow
    //   4375: aload #8
    //   4377: invokevirtual getType : ()Ljava/lang/Class;
    //   4380: astore #9
    //   4382: aload #9
    //   4384: ifnull -> 4465
    //   4387: aload #9
    //   4389: invokevirtual isPrimitive : ()Z
    //   4392: ifne -> 4465
    //   4395: goto -> 4402
    //   4398: invokestatic a : (Ljava/lang/Throwable;)Ljava/lang/Throwable;
    //   4401: athrow
    //   4402: aload #9
    //   4404: invokevirtual getPackage : ()Ljava/lang/Package;
    //   4407: ifnull -> 4465
    //   4410: goto -> 4417
    //   4413: invokestatic a : (Ljava/lang/Throwable;)Ljava/lang/Throwable;
    //   4416: athrow
    //   4417: aload #9
    //   4419: invokevirtual getPackage : ()Ljava/lang/Package;
    //   4422: invokevirtual getName : ()Ljava/lang/String;
    //   4425: ifnull -> 4465
    //   4428: goto -> 4435
    //   4431: invokestatic a : (Ljava/lang/Throwable;)Ljava/lang/Throwable;
    //   4434: athrow
    //   4435: aload #9
    //   4437: invokevirtual getPackage : ()Ljava/lang/Package;
    //   4440: invokevirtual getName : ()Ljava/lang/String;
    //   4443: sipush #7522
    //   4446: sipush #16473
    //   4449: invokestatic a : (II)Ljava/lang/String;
    //   4452: invokevirtual startsWith : (Ljava/lang/String;)Z
    //   4455: ifne -> 4465
    //   4458: goto -> 4465
    //   4461: invokestatic a : (Ljava/lang/Throwable;)Ljava/lang/Throwable;
    //   4464: athrow
    //   4465: aload #8
    //   4467: iconst_1
    //   4468: invokevirtual setAccessible : (Z)V
    //   4471: aload #8
    //   4473: aconst_null
    //   4474: invokevirtual get : (Ljava/lang/Object;)Ljava/lang/Object;
    //   4477: pop
    //   4478: iinc #7, 1
    //   4481: iload_2
    //   4482: ifeq -> 4343
    //   4485: sipush #7550
    //   4488: sipush #8524
    //   4491: invokestatic a : (II)Ljava/lang/String;
    //   4494: invokestatic forName : (Ljava/lang/String;)Ljava/lang/Class;
    //   4497: invokevirtual getDeclaredMethods : ()[Ljava/lang/reflect/Method;
    //   4500: astore #5
    //   4502: aload #5
    //   4504: arraylength
    //   4505: istore #6
    //   4507: iconst_0
    //   4508: istore #7
    //   4510: iload #7
    //   4512: iload #6
    //   4514: if_icmpge -> 4651
    //   4517: aload #5
    //   4519: iload #7
    //   4521: aaload
    //   4522: astore #8
    //   4524: aload #8
    //   4526: invokevirtual getParameterTypes : ()[Ljava/lang/Class;
    //   4529: pop
    //   4530: aload #8
    //   4532: invokevirtual getModifiers : ()I
    //   4535: invokestatic isStatic : (I)Z
    //   4538: ifeq -> 4637
    //   4541: aload #8
    //   4543: invokevirtual getParameterTypes : ()[Ljava/lang/Class;
    //   4546: arraylength
    //   4547: iconst_2
    //   4548: if_icmpne -> 4637
    //   4551: goto -> 4558
    //   4554: invokestatic a : (Ljava/lang/Throwable;)Ljava/lang/Throwable;
    //   4557: athrow
    //   4558: aload #8
    //   4560: invokevirtual getReturnType : ()Ljava/lang/Class;
    //   4563: getstatic java/lang/Boolean.TYPE : Ljava/lang/Class;
    //   4566: if_acmpne -> 4637
    //   4569: goto -> 4576
    //   4572: invokestatic a : (Ljava/lang/Throwable;)Ljava/lang/Throwable;
    //   4575: athrow
    //   4576: aload #8
    //   4578: iconst_1
    //   4579: invokevirtual setAccessible : (Z)V
    //   4582: aload #8
    //   4584: aconst_null
    //   4585: iconst_2
    //   4586: anewarray java/lang/Object
    //   4589: dup
    //   4590: iconst_0
    //   4591: aload_0
    //   4592: aastore
    //   4593: dup
    //   4594: iconst_1
    //   4595: aload_1
    //   4596: ifnonnull -> 4614
    //   4599: goto -> 4606
    //   4602: invokestatic a : (Ljava/lang/Throwable;)Ljava/lang/Throwable;
    //   4605: athrow
    //   4606: aload_1
    //   4607: goto -> 4621
    //   4610: invokestatic a : (Ljava/lang/Throwable;)Ljava/lang/Throwable;
    //   4613: athrow
    //   4614: aload_1
    //   4615: checkcast [B
    //   4618: invokevirtual clone : ()Ljava/lang/Object;
    //   4621: aastore
    //   4622: invokevirtual invoke : (Ljava/lang/Object;[Ljava/lang/Object;)Ljava/lang/Object;
    //   4625: checkcast java/lang/Boolean
    //   4628: invokevirtual booleanValue : ()Z
    //   4631: istore #4
    //   4633: iload_2
    //   4634: ifeq -> 4651
    //   4637: iinc #7, 1
    //   4640: iload_2
    //   4641: ifeq -> 4510
    //   4644: goto -> 4651
    //   4647: invokestatic a : (Ljava/lang/Throwable;)Ljava/lang/Throwable;
    //   4650: athrow
    //   4651: iload_2
    //   4652: ifeq -> 4994
    //   4655: sipush #7523
    //   4658: sipush #29353
    //   4661: invokestatic a : (II)Ljava/lang/String;
    //   4664: iconst_1
    //   4665: ldc burp/Zd0
    //   4667: invokevirtual getClassLoader : ()Ljava/lang/ClassLoader;
    //   4670: invokestatic forName : (Ljava/lang/String;ZLjava/lang/ClassLoader;)Ljava/lang/Class;
    //   4673: invokevirtual getDeclaredFields : ()[Ljava/lang/reflect/Field;
    //   4676: astore #5
    //   4678: aload #5
    //   4680: arraylength
    //   4681: istore #6
    //   4683: iconst_0
    //   4684: istore #7
    //   4686: iload #7
    //   4688: iload #6
    //   4690: if_icmpge -> 4828
    //   4693: aload #5
    //   4695: iload #7
    //   4697: aaload
    //   4698: astore #8
    //   4700: aload #8
    //   4702: invokevirtual getModifiers : ()I
    //   4705: invokestatic isStatic : (I)Z
    //   4708: ifne -> 4718
    //   4711: goto -> 4821
    //   4714: invokestatic a : (Ljava/lang/Throwable;)Ljava/lang/Throwable;
    //   4717: athrow
    //   4718: aload #8
    //   4720: invokevirtual getType : ()Ljava/lang/Class;
    //   4723: astore #9
    //   4725: aload #9
    //   4727: ifnull -> 4808
    //   4730: aload #9
    //   4732: invokevirtual isPrimitive : ()Z
    //   4735: ifne -> 4808
    //   4738: goto -> 4745
    //   4741: invokestatic a : (Ljava/lang/Throwable;)Ljava/lang/Throwable;
    //   4744: athrow
    //   4745: aload #9
    //   4747: invokevirtual getPackage : ()Ljava/lang/Package;
    //   4750: ifnull -> 4808
    //   4753: goto -> 4760
    //   4756: invokestatic a : (Ljava/lang/Throwable;)Ljava/lang/Throwable;
    //   4759: athrow
    //   4760: aload #9
    //   4762: invokevirtual getPackage : ()Ljava/lang/Package;
    //   4765: invokevirtual getName : ()Ljava/lang/String;
    //   4768: ifnull -> 4808
    //   4771: goto -> 4778
    //   4774: invokestatic a : (Ljava/lang/Throwable;)Ljava/lang/Throwable;
    //   4777: athrow
    //   4778: aload #9
    //   4780: invokevirtual getPackage : ()Ljava/lang/Package;
    //   4783: invokevirtual getName : ()Ljava/lang/String;
    //   4786: sipush #7522
    //   4789: sipush #16473
    //   4792: invokestatic a : (II)Ljava/lang/String;
    //   4795: invokevirtual startsWith : (Ljava/lang/String;)Z
    //   4798: ifne -> 4808
    //   4801: goto -> 4808
    //   4804: invokestatic a : (Ljava/lang/Throwable;)Ljava/lang/Throwable;
    //   4807: athrow
    //   4808: aload #8
    //   4810: iconst_1
    //   4811: invokevirtual setAccessible : (Z)V
    //   4814: aload #8
    //   4816: aconst_null
    //   4817: invokevirtual get : (Ljava/lang/Object;)Ljava/lang/Object;
    //   4820: pop
    //   4821: iinc #7, 1
    //   4824: iload_2
    //   4825: ifeq -> 4686
    //   4828: sipush #7534
    //   4831: sipush #7383
    //   4834: invokestatic a : (II)Ljava/lang/String;
    //   4837: invokestatic forName : (Ljava/lang/String;)Ljava/lang/Class;
    //   4840: invokevirtual getDeclaredMethods : ()[Ljava/lang/reflect/Method;
    //   4843: astore #5
    //   4845: aload #5
    //   4847: arraylength
    //   4848: istore #6
    //   4850: iconst_0
    //   4851: istore #7
    //   4853: iload #7
    //   4855: iload #6
    //   4857: if_icmpge -> 4994
    //   4860: aload #5
    //   4862: iload #7
    //   4864: aaload
    //   4865: astore #8
    //   4867: aload #8
    //   4869: invokevirtual getParameterTypes : ()[Ljava/lang/Class;
    //   4872: pop
    //   4873: aload #8
    //   4875: invokevirtual getModifiers : ()I
    //   4878: invokestatic isStatic : (I)Z
    //   4881: ifeq -> 4980
    //   4884: aload #8
    //   4886: invokevirtual getParameterTypes : ()[Ljava/lang/Class;
    //   4889: arraylength
    //   4890: iconst_2
    //   4891: if_icmpne -> 4980
    //   4894: goto -> 4901
    //   4897: invokestatic a : (Ljava/lang/Throwable;)Ljava/lang/Throwable;
    //   4900: athrow
    //   4901: aload #8
    //   4903: invokevirtual getReturnType : ()Ljava/lang/Class;
    //   4906: getstatic java/lang/Boolean.TYPE : Ljava/lang/Class;
    //   4909: if_acmpne -> 4980
    //   4912: goto -> 4919
    //   4915: invokestatic a : (Ljava/lang/Throwable;)Ljava/lang/Throwable;
    //   4918: athrow
    //   4919: aload #8
    //   4921: iconst_1
    //   4922: invokevirtual setAccessible : (Z)V
    //   4925: aload #8
    //   4927: aconst_null
    //   4928: iconst_2
    //   4929: anewarray java/lang/Object
    //   4932: dup
    //   4933: iconst_0
    //   4934: aload_0
    //   4935: aastore
    //   4936: dup
    //   4937: iconst_1
    //   4938: aload_1
    //   4939: ifnonnull -> 4957
    //   4942: goto -> 4949
    //   4945: invokestatic a : (Ljava/lang/Throwable;)Ljava/lang/Throwable;
    //   4948: athrow
    //   4949: aload_1
    //   4950: goto -> 4964
    //   4953: invokestatic a : (Ljava/lang/Throwable;)Ljava/lang/Throwable;
    //   4956: athrow
    //   4957: aload_1
    //   4958: checkcast [B
    //   4961: invokevirtual clone : ()Ljava/lang/Object;
    //   4964: aastore
    //   4965: invokevirtual invoke : (Ljava/lang/Object;[Ljava/lang/Object;)Ljava/lang/Object;
    //   4968: checkcast java/lang/Boolean
    //   4971: invokevirtual booleanValue : ()Z
    //   4974: istore #4
    //   4976: iload_2
    //   4977: ifeq -> 4994
    //   4980: iinc #7, 1
    //   4983: iload_2
    //   4984: ifeq -> 4853
    //   4987: goto -> 4994
    //   4990: invokestatic a : (Ljava/lang/Throwable;)Ljava/lang/Throwable;
    //   4993: athrow
    //   4994: iload #4
    //   4996: ireturn
    //   4997: astore_3
    //   4998: new java/lang/Exception
    //   5001: dup
    //   5002: aload_3
    //   5003: invokevirtual getMessage : ()Ljava/lang/String;
    //   5006: invokespecial <init> : (Ljava/lang/String;)V
    //   5009: athrow
    // Exception table:
    //   from	to	target	type
    //   4	2796	4997	java/lang/Throwable
    //   22	198	201	java/lang/Throwable
    //   168	235	238	java/lang/Throwable
    //   205	272	275	java/lang/Throwable
    //   242	309	312	java/lang/Throwable
    //   279	346	349	java/lang/Throwable
    //   316	383	386	java/lang/Throwable
    //   353	420	423	java/lang/Throwable
    //   390	457	460	java/lang/Throwable
    //   427	494	497	java/lang/Throwable
    //   464	531	534	java/lang/Throwable
    //   501	568	571	java/lang/Throwable
    //   538	605	608	java/lang/Throwable
    //   575	642	645	java/lang/Throwable
    //   612	679	682	java/lang/Throwable
    //   649	716	719	java/lang/Throwable
    //   686	753	756	java/lang/Throwable
    //   723	790	793	java/lang/Throwable
    //   760	827	830	java/lang/Throwable
    //   797	864	867	java/lang/Throwable
    //   834	901	904	java/lang/Throwable
    //   871	938	941	java/lang/Throwable
    //   908	975	978	java/lang/Throwable
    //   945	1012	1015	java/lang/Throwable
    //   982	1049	1052	java/lang/Throwable
    //   1019	1086	1089	java/lang/Throwable
    //   1056	1123	1126	java/lang/Throwable
    //   1093	1160	1163	java/lang/Throwable
    //   1130	1197	1200	java/lang/Throwable
    //   1167	1234	1237	java/lang/Throwable
    //   1204	1271	1274	java/lang/Throwable
    //   1241	1308	1311	java/lang/Throwable
    //   1278	1341	1344	java/lang/Throwable
    //   1407	1421	1421	java/lang/Throwable
    //   1432	1445	1448	java/lang/Throwable
    //   1437	1460	1463	java/lang/Throwable
    //   1452	1478	1481	java/lang/Throwable
    //   1467	1508	1511	java/lang/Throwable
    //   1574	1601	1604	java/lang/Throwable
    //   1591	1622	1625	java/lang/Throwable
    //   1608	1652	1655	java/lang/Throwable
    //   1629	1663	1663	java/lang/Throwable
    //   1674	1690	1693	java/lang/Throwable
    //   1770	1784	1784	java/lang/Throwable
    //   1795	1808	1811	java/lang/Throwable
    //   1800	1823	1826	java/lang/Throwable
    //   1815	1841	1844	java/lang/Throwable
    //   1830	1871	1874	java/lang/Throwable
    //   1937	1964	1967	java/lang/Throwable
    //   1954	1985	1988	java/lang/Throwable
    //   1971	2015	2018	java/lang/Throwable
    //   1992	2026	2026	java/lang/Throwable
    //   2037	2053	2056	java/lang/Throwable
    //   2153	2167	2167	java/lang/Throwable
    //   2178	2191	2194	java/lang/Throwable
    //   2183	2206	2209	java/lang/Throwable
    //   2198	2224	2227	java/lang/Throwable
    //   2213	2254	2257	java/lang/Throwable
    //   2320	2347	2350	java/lang/Throwable
    //   2337	2365	2368	java/lang/Throwable
    //   2354	2395	2398	java/lang/Throwable
    //   2372	2406	2406	java/lang/Throwable
    //   2429	2440	2443	java/lang/Throwable
    //   2495	2509	2509	java/lang/Throwable
    //   2520	2533	2536	java/lang/Throwable
    //   2525	2548	2551	java/lang/Throwable
    //   2540	2566	2569	java/lang/Throwable
    //   2555	2596	2599	java/lang/Throwable
    //   2662	2689	2692	java/lang/Throwable
    //   2679	2707	2710	java/lang/Throwable
    //   2696	2737	2740	java/lang/Throwable
    //   2714	2748	2748	java/lang/Throwable
    //   2771	2782	2785	java/lang/Throwable
    //   2797	3531	4997	java/lang/Throwable
    //   2887	2901	2901	java/lang/Throwable
    //   2912	2925	2928	java/lang/Throwable
    //   2917	2940	2943	java/lang/Throwable
    //   2932	2958	2961	java/lang/Throwable
    //   2947	2988	2991	java/lang/Throwable
    //   3054	3081	3084	java/lang/Throwable
    //   3071	3099	3102	java/lang/Throwable
    //   3088	3129	3132	java/lang/Throwable
    //   3106	3140	3140	java/lang/Throwable
    //   3163	3174	3177	java/lang/Throwable
    //   3230	3244	3244	java/lang/Throwable
    //   3255	3268	3271	java/lang/Throwable
    //   3260	3283	3286	java/lang/Throwable
    //   3275	3301	3304	java/lang/Throwable
    //   3290	3331	3334	java/lang/Throwable
    //   3397	3424	3427	java/lang/Throwable
    //   3414	3442	3445	java/lang/Throwable
    //   3431	3472	3475	java/lang/Throwable
    //   3449	3483	3483	java/lang/Throwable
    //   3506	3517	3520	java/lang/Throwable
    //   3532	4266	4997	java/lang/Throwable
    //   3622	3636	3636	java/lang/Throwable
    //   3647	3660	3663	java/lang/Throwable
    //   3652	3675	3678	java/lang/Throwable
    //   3667	3693	3696	java/lang/Throwable
    //   3682	3723	3726	java/lang/Throwable
    //   3789	3816	3819	java/lang/Throwable
    //   3806	3834	3837	java/lang/Throwable
    //   3823	3864	3867	java/lang/Throwable
    //   3841	3875	3875	java/lang/Throwable
    //   3898	3909	3912	java/lang/Throwable
    //   3965	3979	3979	java/lang/Throwable
    //   3990	4003	4006	java/lang/Throwable
    //   3995	4018	4021	java/lang/Throwable
    //   4010	4036	4039	java/lang/Throwable
    //   4025	4066	4069	java/lang/Throwable
    //   4132	4159	4162	java/lang/Throwable
    //   4149	4177	4180	java/lang/Throwable
    //   4166	4207	4210	java/lang/Throwable
    //   4184	4218	4218	java/lang/Throwable
    //   4241	4252	4255	java/lang/Throwable
    //   4267	4996	4997	java/lang/Throwable
    //   4357	4371	4371	java/lang/Throwable
    //   4382	4395	4398	java/lang/Throwable
    //   4387	4410	4413	java/lang/Throwable
    //   4402	4428	4431	java/lang/Throwable
    //   4417	4458	4461	java/lang/Throwable
    //   4524	4551	4554	java/lang/Throwable
    //   4541	4569	4572	java/lang/Throwable
    //   4558	4599	4602	java/lang/Throwable
    //   4576	4610	4610	java/lang/Throwable
    //   4633	4644	4647	java/lang/Throwable
    //   4700	4714	4714	java/lang/Throwable
    //   4725	4738	4741	java/lang/Throwable
    //   4730	4753	4756	java/lang/Throwable
    //   4745	4771	4774	java/lang/Throwable
    //   4760	4801	4804	java/lang/Throwable
    //   4867	4894	4897	java/lang/Throwable
    //   4884	4912	4915	java/lang/Throwable
    //   4901	4942	4945	java/lang/Throwable
    //   4919	4953	4953	java/lang/Throwable
    //   4976	4987	4990	java/lang/Throwable
  }
  
  static void Zs(Object paramObject) {
    Ze7q.ZW = a(7527, -6849);
    Ze7q.Zk = new BigInteger(a(7548, 15118));
    boolean bool = Zt2e.ZK();
    try {
      try {
        if (Zkfz.Zs.charAt(Math.abs(((BigInteger)Zsm3.ZC).intValue() % 32)) <= Zrdy.ZO.charAt(Math.abs(((BigInteger)Zsm3.ZC).intValue() % 32))) {
          try {
            Zx4l.Zb(Class.forName(a(7545, -22970)));
            if (bool)
              Zxx4.ZU(Class.forName(a(7526, -19205))); 
          } catch (Throwable throwable) {
            throw a(null);
          } 
          return;
        } 
      } catch (Throwable throwable) {
        throw a(null);
      } 
      Zxx4.ZU(Class.forName(a(7526, -19205)));
    } catch (Throwable throwable) {}
  }
  
  static {
    // Byte code:
    //   0: bipush #27
    //   2: anewarray java/lang/String
    //   5: astore #5
    //   7: iconst_0
    //   8: istore_3
    //   9: ldc '*&]\\tMf8\b\\tb\\t8\f\\tT\\trC<)\\t379Zwo# #\\n.LTp??{\\t,d\\t.(01L\\r<\\fo9\68v(v_{\\b- cf}oQ,aaPl&%!Cv[C\\t\D9y\\tytc,_\\t\\bM!\\tIv $|OA}"ud;gXN\\tJq"N\\taK2p\F\\tflE}\\to;6q\\tLaFw\\t\yDtcS\\tx'
    //   11: dup
    //   12: astore_2
    //   13: invokevirtual length : ()I
    //   16: istore #4
    //   18: bipush #9
    //   20: istore_1
    //   21: iconst_m1
    //   22: istore_0
    //   23: bipush #107
    //   25: iinc #0, 1
    //   28: aload_2
    //   29: iload_0
    //   30: dup
    //   31: iload_1
    //   32: iadd
    //   33: invokevirtual substring : (II)Ljava/lang/String;
    //   36: iconst_m1
    //   37: goto -> 143
    //   40: aload #5
    //   42: swap
    //   43: iload_3
    //   44: iinc #3, 1
    //   47: swap
    //   48: aastore
    //   49: iload_0
    //   50: iload_1
    //   51: iadd
    //   52: dup
    //   53: istore_0
    //   54: iload #4
    //   56: if_icmpge -> 68
    //   59: aload_2
    //   60: iload_0
    //   61: invokevirtual charAt : (I)C
    //   64: istore_1
    //   65: goto -> 23
    //   68: ldc ',|@^\\b\\bN%O'
    //   70: dup
    //   71: astore_2
    //   72: invokevirtual length : ()I
    //   75: istore #4
    //   77: bipush #9
    //   79: istore_1
    //   80: iconst_m1
    //   81: istore_0
    //   82: bipush #91
    //   84: iinc #0, 1
    //   87: aload_2
    //   88: iload_0
    //   89: dup
    //   90: iload_1
    //   91: iadd
    //   92: invokevirtual substring : (II)Ljava/lang/String;
    //   95: iconst_0
    //   96: goto -> 143
    //   99: aload #5
    //   101: swap
    //   102: iload_3
    //   103: iinc #3, 1
    //   106: swap
    //   107: aastore
    //   108: iload_0
    //   109: iload_1
    //   110: iadd
    //   111: dup
    //   112: istore_0
    //   113: iload #4
    //   115: if_icmpge -> 127
    //   118: aload_2
    //   119: iload_0
    //   120: invokevirtual charAt : (I)C
    //   123: istore_1
    //   124: goto -> 82
    //   127: aload #5
    //   129: putstatic burp/Zzai.a : [Ljava/lang/String;
    //   132: bipush #27
    //   134: anewarray java/lang/String
    //   137: putstatic burp/Zzai.b : [Ljava/lang/String;
    //   140: goto -> 300
    //   143: dup_x2
    //   144: pop
    //   145: invokevirtual toCharArray : ()[C
    //   148: dup_x1
    //   149: arraylength
    //   150: dup_x2
    //   151: pop
    //   152: iconst_0
    //   153: istore #6
    //   155: dup2_x1
    //   156: pop2
    //   157: dup_x2
    //   158: iconst_1
    //   159: if_icmpgt -> 260
    //   162: dup2
    //   163: swap
    //   164: iload #6
    //   166: dup2_x1
    //   167: caload
    //   168: swap
    //   169: iload #6
    //   171: bipush #7
    //   173: irem
    //   174: tableswitch default -> 242, 0 -> 212, 1 -> 217, 2 -> 222, 3 -> 227, 4 -> 232, 5 -> 237
    //   212: bipush #109
    //   214: goto -> 244
    //   217: bipush #30
    //   219: goto -> 244
    //   222: bipush #56
    //   224: goto -> 244
    //   227: bipush #53
    //   229: goto -> 244
    //   232: bipush #31
    //   234: goto -> 244
    //   237: bipush #105
    //   239: goto -> 244
    //   242: bipush #57
    //   244: ixor
    //   245: ixor
    //   246: i2c
    //   247: castore
    //   248: iinc #6, 1
    //   251: dup
    //   252: ifne -> 260
    //   255: dup2
    //   256: dup_x1
    //   257: goto -> 166
    //   260: dup2_x1
    //   261: pop2
    //   262: dup_x2
    //   263: iload #6
    //   265: if_icmpgt -> 162
    //   268: pop
    //   269: new java/lang/String
    //   272: dup_x1
    //   273: swap
    //   274: invokespecial <init> : ([C)V
    //   277: invokevirtual intern : ()Ljava/lang/String;
    //   280: swap
    //   281: pop
    //   282: swap
    //   283: tableswitch default -> 40, 0 -> 99
    //   300: new java/math/BigInteger
    //   303: dup
    //   304: iconst_1
    //   305: bipush #32
    //   307: newarray byte
    //   309: dup
    //   310: iconst_0
    //   311: bipush #92
    //   313: bastore
    //   314: dup
    //   315: iconst_1
    //   316: bipush #22
    //   318: bastore
    //   319: dup
    //   320: iconst_2
    //   321: bipush #-54
    //   323: bastore
    //   324: dup
    //   325: iconst_3
    //   326: bipush #-66
    //   328: bastore
    //   329: dup
    //   330: iconst_4
    //   331: bipush #118
    //   333: bastore
    //   334: dup
    //   335: iconst_5
    //   336: bipush #50
    //   338: bastore
    //   339: dup
    //   340: bipush #6
    //   342: bipush #-56
    //   344: bastore
    //   345: dup
    //   346: bipush #7
    //   348: bipush #29
    //   350: bastore
    //   351: dup
    //   352: bipush #8
    //   354: bipush #-22
    //   356: bastore
    //   357: dup
    //   358: bipush #9
    //   360: bipush #-23
    //   362: bastore
    //   363: dup
    //   364: bipush #10
    //   366: bipush #-90
    //   368: bastore
    //   369: dup
    //   370: bipush #11
    //   372: bipush #71
    //   374: bastore
    //   375: dup
    //   376: bipush #12
    //   378: bipush #-78
    //   380: bastore
    //   381: dup
    //   382: bipush #13
    //   384: bipush #-74
    //   386: bastore
    //   387: dup
    //   388: bipush #14
    //   390: bipush #-26
    //   392: bastore
    //   393: dup
    //   394: bipush #15
    //   396: bipush #16
    //   398: bastore
    //   399: dup
    //   400: bipush #16
    //   402: bipush #8
    //   404: bastore
    //   405: dup
    //   406: bipush #17
    //   408: bipush #72
    //   410: bastore
    //   411: dup
    //   412: bipush #18
    //   414: bipush #100
    //   416: bastore
    //   417: dup
    //   418: bipush #19
    //   420: bipush #-105
    //   422: bastore
    //   423: dup
    //   424: bipush #20
    //   426: bipush #-121
    //   428: bastore
    //   429: dup
    //   430: bipush #21
    //   432: iconst_0
    //   433: bastore
    //   434: dup
    //   435: bipush #22
    //   437: iconst_m1
    //   438: bastore
    //   439: dup
    //   440: bipush #23
    //   442: bipush #92
    //   444: bastore
    //   445: dup
    //   446: bipush #24
    //   448: bipush #25
    //   450: bastore
    //   451: dup
    //   452: bipush #25
    //   454: bipush #14
    //   456: bastore
    //   457: dup
    //   458: bipush #26
    //   460: bipush #-106
    //   462: bastore
    //   463: dup
    //   464: bipush #27
    //   466: bipush #97
    //   468: bastore
    //   469: dup
    //   470: bipush #28
    //   472: bipush #83
    //   474: bastore
    //   475: dup
    //   476: bipush #29
    //   478: bipush #-46
    //   480: bastore
    //   481: dup
    //   482: bipush #30
    //   484: bipush #14
    //   486: bastore
    //   487: dup
    //   488: bipush #31
    //   490: bipush #107
    //   492: bastore
    //   493: invokespecial <init> : (I[B)V
    //   496: putstatic burp/Zzai.Z_ : Ljava/lang/Object;
    //   499: sipush #7551
    //   502: sipush #29241
    //   505: invokestatic a : (II)Ljava/lang/String;
    //   508: putstatic burp/Zzai.Zy : Ljava/lang/String;
    //   511: return
  }
  
  private static Throwable a(Throwable paramThrowable) {
    return paramThrowable;
  }
  
  private static String a(int paramInt1, int paramInt2) {
    int i = (paramInt1 ^ 0x1D77) & 0xFFFF;
    if (b[i] == null) {
      char[] arrayOfChar = a[i].toCharArray();
      switch (arrayOfChar[0] & 0xFF) {
        case 0:
        
        case 1:
        
        case 2:
        
        case 3:
        
        case 4:
        
        case 5:
        
        case 6:
        
        case 7:
        
        case 8:
        
        case 9:
        
        case 10:
        
        case 11:
        
        case 12:
        
        case 13:
        
        case 14:
        
        case 15:
        
        case 16:
        
        case 17:
        
        case 18:
        
        case 19:
        
        case 20:
        
        case 21:
        
        case 22:
        
        case 23:
        
        case 24:
        
        case 25:
        
        case 26:
        
        case 27:
        
        case 28:
        
        case 29:
        
        case 30:
        
        case 31:
        
        case 32:
        
        case 33:
        
        case 34:
        
        case 35:
        
        case 36:
        
        case 37:
        
        case 38:
        
        case 39:
        
        case 40:
        
        case 41:
        
        case 42:
        
        case 43:
        
        case 44:
        
        case 45:
        
        case 46:
        
        case 47:
        
        case 48:
        
        case 49:
        
        case 50:
        
        case 51:
        
        case 52:
        
        case 53:
        
        case 54:
        
        case 55:
        
        case 56:
        
        case 57:
        
        case 58:
        
        case 59:
        
        case 60:
        
        case 61:
        
        case 62:
        
        case 63:
        
        case 64:
        
        case 65:
        
        case 66:
        
        case 67:
        
        case 68:
        
        case 69:
        
        case 70:
        
        case 71:
        
        case 72:
        
        case 73:
        
        case 74:
        
        case 75:
        
        case 76:
        
        case 77:
        
        case 78:
        
        case 79:
        
        case 80:
        
        case 81:
        
        case 82:
        
        case 83:
        
        case 84:
        
        case 85:
        
        case 86:
        
        case 87:
        
        case 88:
        
        case 89:
        
        case 90:
        
        case 91:
        
        case 92:
        
        case 93:
        
        case 94:
        
        case 95:
        
        case 96:
        
        case 97:
        
        case 98:
        
        case 99:
        
        case 100:
        
        case 101:
        
        case 102:
        
        case 103:
        
        case 104:
        
        case 105:
        
        case 106:
        
        case 107:
        
        case 108:
        
        case 109:
        
        case 110:
        
        case 111:
        
        case 112:
        
        case 113:
        
        case 114:
        
        case 115:
        
        case 116:
        
        case 117:
        
        case 118:
        
        case 119:
        
        case 120:
        
        case 121:
        
        case 122:
        
        case 123:
        
        case 124:
        
        case 125:
        
        case 126:
        
        case 127:
        
        case 128:
        
        case 129:
        
        case 130:
        
        case 131:
        
        case 132:
        
        case 133:
        
        case 134:
        
        case 135:
        
        case 136:
        
        case 137:
        
        case 138:
        
        case 139:
        
        case 140:
        
        case 141:
        
        case 142:
        
        case 143:
        
        case 144:
        
        case 145:
        
        case 146:
        
        case 147:
        
        case 148:
        
        case 149:
        
        case 150:
        
        case 151:
        
        case 152:
        
        case 153:
        
        case 154:
        
        case 155:
        
        case 156:
        
        case 157:
        
        case 158:
        
        case 159:
        
        case 160:
        
        case 161:
        
        case 162:
        
        case 163:
        
        case 164:
        
        case 165:
        
        case 166:
        
        case 167:
        
        case 168:
        
        case 169:
        
        case 170:
        
        case 171:
        
        case 172:
        
        case 173:
        
        case 174:
        
        case 175:
        
        case 176:
        
        case 177:
        
        case 178:
        
        case 179:
        
        case 180:
        
        case 181:
        
        case 182:
        
        case 183:
        
        case 184:
        
        case 185:
        
        case 186:
        
        case 187:
        
        case 188:
        
        case 189:
        
        case 190:
        
        case 191:
        
        case 192:
        
        case 193:
        
        case 194:
        
        case 195:
        
        case 196:
        
        case 197:
        
        case 198:
        
        case 199:
        
        case 200:
        
        case 201:
        
        case 202:
        
        case 203:
        
        case 204:
        
        case 205:
        
        case 206:
        
        case 207:
        
        case 208:
        
        case 209:
        
        case 210:
        
        case 211:
        
        case 212:
        
        case 213:
        
        case 214:
        
        case 215:
        
        case 216:
        
        case 217:
        
        case 218:
        
        case 219:
        
        case 220:
        
        case 221:
        
        case 222:
        
        case 223:
        
        case 224:
        
        case 225:
        
        case 226:
        
        case 227:
        
        case 228:
        
        case 229:
        
        case 230:
        
        case 231:
        
        case 232:
        
        case 233:
        
        case 234:
        
        case 235:
        
        case 236:
        
        case 237:
        
        case 238:
        
        case 239:
        
        case 240:
        
        case 241:
        
        case 242:
        
        case 243:
        
        case 244:
        
        case 245:
        
        case 246:
        
        case 247:
        
        case 248:
        
        case 249:
        
        case 250:
        
        case 251:
        
        case 252:
        
        case 253:
        
        case 254:
        
        default:
          break;
      } 
      byte b1 = 21;
      int j = (paramInt2 & 0xFF) - b1;
      if (j < 0)
        j += 256; 
      int k = ((paramInt2 & 0xFFFF) >>> 8) - b1;
      if (k < 0)
        k += 256; 
      for (byte b2 = 0; b2 < arrayOfChar.length; b2++) {
        int m = b2 % 2;
        if (m == 0) {
          arrayOfChar[b2] = (char)(arrayOfChar[b2] ^ j);
          j = ((j >>> 3 | j << 5) ^ arrayOfChar[b2]) & 0xFF;
        } else {
          arrayOfChar[b2] = (char)(arrayOfChar[b2] ^ k);
          k = ((k >>> 3 | k << 5) ^ arrayOfChar[b2]) & 0xFF;
        } 
      } 
      b[i] = (new String(arrayOfChar)).intern();
    } 
    return b[i];
  }
}


/* Location:              C:\Program Files\BurpSuitePro\burpsuite_pro.jar!\burp\Zzai.class
 * Java compiler version: 21 (65.0)
 * JD-Core Version:       1.1.3
 */