package burp;

import java.awt.Component;
import java.util.List;

class Zzak implements Zmgv {
  final Zg8x Zi;
  
  private static final String a;
  
  private Zzak(Zg8x paramZg8x) {}
  
  public Zmzk Zod() {
    return (this.Zi.ZR == null) ? null : this.Zi.ZR.Zod();
  }
  
  public List<Component> Zof() {
    return null;
  }
  
  public Zepe Zl(Component paramComponent) {
    return new Zepa(a, Zk97.DESKTOP_SCANNING_CRAWL_PATHS, Zt2m.ZF(this.Zi));
  }
  
  public Zstu Zos() {
    return (this.Zi.ZR == null) ? null : this.Zi.ZR.Zos();
  }
  
  public boolean ZoZ() {
    return false;
  }
  
  public Zstu ZoO() {
    return (this.Zi.ZR == null) ? null : this.Zi.ZR.ZoO();
  }
  
  public long ZoB() {
    return (this.Zi.ZR == null) ? -1L : this.Zi.ZR.ZoB();
  }
  
  public Zmfj Zq(Zkl6 paramZkl6, Zm6x paramZm6x) {
    return Zsou.ZD(this, paramZkl6.ZH());
  }
  
  static {
    // Byte code:
    //   0: bipush #93
    //   2: ldc ']Ha\\bEb"Nh\\f\\t&=}OmG63jSo'
    //   4: iconst_m1
    //   5: goto -> 14
    //   8: putstatic burp/Zzak.a : Ljava/lang/String;
    //   11: goto -> 154
    //   14: dup_x2
    //   15: pop
    //   16: invokevirtual toCharArray : ()[C
    //   19: dup_x1
    //   20: arraylength
    //   21: dup_x2
    //   22: pop
    //   23: iconst_0
    //   24: istore_0
    //   25: dup2_x1
    //   26: pop2
    //   27: dup_x2
    //   28: iconst_1
    //   29: if_icmpgt -> 128
    //   32: dup2
    //   33: swap
    //   34: iload_0
    //   35: dup2_x1
    //   36: caload
    //   37: swap
    //   38: iload_0
    //   39: bipush #7
    //   41: irem
    //   42: tableswitch default -> 110, 0 -> 80, 1 -> 85, 2 -> 90, 3 -> 95, 4 -> 100, 5 -> 105
    //   80: bipush #67
    //   82: goto -> 112
    //   85: bipush #103
    //   87: goto -> 112
    //   90: bipush #93
    //   92: goto -> 112
    //   95: bipush #34
    //   97: goto -> 112
    //   100: bipush #116
    //   102: goto -> 112
    //   105: bipush #31
    //   107: goto -> 112
    //   110: bipush #15
    //   112: ixor
    //   113: ixor
    //   114: i2c
    //   115: castore
    //   116: iinc #0, 1
    //   119: dup
    //   120: ifne -> 128
    //   123: dup2
    //   124: dup_x1
    //   125: goto -> 35
    //   128: dup2_x1
    //   129: pop2
    //   130: dup_x2
    //   131: iload_0
    //   132: if_icmpgt -> 32
    //   135: pop
    //   136: new java/lang/String
    //   139: dup_x1
    //   140: swap
    //   141: invokespecial <init> : ([C)V
    //   144: invokevirtual intern : ()Ljava/lang/String;
    //   147: swap
    //   148: pop
    //   149: swap
    //   150: pop
    //   151: goto -> 8
    //   154: return
  }
}


/* Location:              C:\Program Files\BurpSuitePro\burpsuite_pro.jar!\burp\Zzak.class
 * Java compiler version: 21 (65.0)
 * JD-Core Version:       1.1.3
 */