package burp;

import java.math.BigInteger;

class Zzbr extends ClassLoader {
  static String Zp;
  
  static Object ZC;
  
  private static final String[] a;
  
  private static final String[] b;
  
  static void Zk(Object[] paramArrayOfObject, Object paramObject) throws Throwable {}
  
  static boolean ZI(Object[] paramArrayOfObject, Object paramObject) throws Throwable {
    // Byte code:
    //   0: invokestatic ZN : ()Z
    //   3: istore_2
    //   4: sipush #11005
    //   7: sipush #-32611
    //   10: invokestatic a : (II)Ljava/lang/String;
    //   13: invokestatic forName : (Ljava/lang/String;)Ljava/lang/Class;
    //   16: invokestatic ZE : (Ljava/lang/Object;)V
    //   19: getstatic burp/Zlsw.ZJ : Ljava/lang/Object;
    //   22: checkcast java/math/BigInteger
    //   25: getstatic burp/Zrs0.Zz : Ljava/lang/Object;
    //   28: checkcast java/math/BigInteger
    //   31: invokevirtual subtract : (Ljava/math/BigInteger;)Ljava/math/BigInteger;
    //   34: putstatic burp/Zzxv.ZZ : Ljava/lang/Object;
    //   37: getstatic burp/Zgt7.Zn : Ljava/lang/Object;
    //   40: checkcast java/math/BigInteger
    //   43: invokevirtual toByteArray : ()[B
    //   46: astore_3
    //   47: new java/lang/StringBuilder
    //   50: dup
    //   51: invokespecial <init> : ()V
    //   54: astore #5
    //   56: aload #5
    //   58: sipush #10997
    //   61: sipush #-22823
    //   64: invokestatic a : (II)Ljava/lang/String;
    //   67: invokevirtual append : (Ljava/lang/String;)Ljava/lang/StringBuilder;
    //   70: pop
    //   71: aload_3
    //   72: astore #6
    //   74: aload #6
    //   76: arraylength
    //   77: istore #7
    //   79: iconst_0
    //   80: istore #8
    //   82: iload #8
    //   84: iload #7
    //   86: if_icmpge -> 112
    //   89: aload #6
    //   91: iload #8
    //   93: baload
    //   94: istore #9
    //   96: aload #5
    //   98: iload #9
    //   100: i2c
    //   101: invokevirtual append : (C)Ljava/lang/StringBuilder;
    //   104: pop
    //   105: iinc #8, 1
    //   108: iload_2
    //   109: ifne -> 82
    //   112: aload #5
    //   114: sipush #11003
    //   117: sipush #4707
    //   120: invokestatic a : (II)Ljava/lang/String;
    //   123: ldc ''
    //   125: invokestatic getProperty : (Ljava/lang/String;Ljava/lang/String;)Ljava/lang/String;
    //   128: invokevirtual toLowerCase : ()Ljava/lang/String;
    //   131: invokevirtual append : (Ljava/lang/String;)Ljava/lang/StringBuilder;
    //   134: pop
    //   135: aload #5
    //   137: sipush #10992
    //   140: sipush #21131
    //   143: invokestatic a : (II)Ljava/lang/String;
    //   146: ldc ''
    //   148: invokestatic getProperty : (Ljava/lang/String;Ljava/lang/String;)Ljava/lang/String;
    //   151: invokevirtual toLowerCase : ()Ljava/lang/String;
    //   154: invokevirtual append : (Ljava/lang/String;)Ljava/lang/StringBuilder;
    //   157: pop
    //   158: aload #5
    //   160: invokevirtual toString : ()Ljava/lang/String;
    //   163: invokevirtual getBytes : ()[B
    //   166: astore #4
    //   168: aload #4
    //   170: astore_3
    //   171: aload_3
    //   172: arraylength
    //   173: bipush #8
    //   175: iadd
    //   176: bipush #6
    //   178: ishr
    //   179: iconst_1
    //   180: iadd
    //   181: bipush #16
    //   183: imul
    //   184: newarray int
    //   186: astore #5
    //   188: iconst_0
    //   189: istore #6
    //   191: iload #6
    //   193: aload_3
    //   194: arraylength
    //   195: if_icmpge -> 238
    //   198: aload_3
    //   199: iload #6
    //   201: baload
    //   202: sipush #255
    //   205: iand
    //   206: istore #7
    //   208: aload #5
    //   210: iload #6
    //   212: iconst_2
    //   213: ishr
    //   214: dup2
    //   215: iaload
    //   216: iload #7
    //   218: bipush #24
    //   220: iload #6
    //   222: iconst_4
    //   223: irem
    //   224: bipush #8
    //   226: imul
    //   227: isub
    //   228: ishl
    //   229: ior
    //   230: iastore
    //   231: iinc #6, 1
    //   234: iload_2
    //   235: ifne -> 191
    //   238: aload #5
    //   240: iload #6
    //   242: iconst_2
    //   243: ishr
    //   244: dup2
    //   245: iaload
    //   246: sipush #128
    //   249: bipush #24
    //   251: iload #6
    //   253: iconst_4
    //   254: irem
    //   255: bipush #8
    //   257: imul
    //   258: isub
    //   259: ishl
    //   260: ior
    //   261: iastore
    //   262: aload #5
    //   264: aload #5
    //   266: arraylength
    //   267: iconst_1
    //   268: isub
    //   269: aload_3
    //   270: arraylength
    //   271: bipush #8
    //   273: imul
    //   274: iastore
    //   275: bipush #80
    //   277: newarray int
    //   279: astore #7
    //   281: ldc 1732584193
    //   283: istore #8
    //   285: ldc -271733879
    //   287: istore #9
    //   289: ldc -1732584194
    //   291: istore #10
    //   293: ldc 271733878
    //   295: istore #11
    //   297: ldc -1009589776
    //   299: istore #12
    //   301: iconst_0
    //   302: istore #6
    //   304: iload #6
    //   306: aload #5
    //   308: arraylength
    //   309: if_icmpge -> 631
    //   312: iload #8
    //   314: istore #13
    //   316: iload #9
    //   318: istore #14
    //   320: iload #10
    //   322: istore #15
    //   324: iload #11
    //   326: istore #16
    //   328: iload #12
    //   330: istore #17
    //   332: iconst_0
    //   333: istore #18
    //   335: iload #18
    //   337: bipush #80
    //   339: if_icmpge -> 589
    //   342: iload #18
    //   344: bipush #16
    //   346: if_icmpge -> 373
    //   349: aload #7
    //   351: iload #18
    //   353: aload #5
    //   355: iload #6
    //   357: iload #18
    //   359: iadd
    //   360: iaload
    //   361: iastore
    //   362: iload_2
    //   363: ifne -> 428
    //   366: goto -> 373
    //   369: invokestatic a : (Ljava/lang/Throwable;)Ljava/lang/Throwable;
    //   372: athrow
    //   373: aload #7
    //   375: iload #18
    //   377: iconst_3
    //   378: isub
    //   379: iaload
    //   380: aload #7
    //   382: iload #18
    //   384: bipush #8
    //   386: isub
    //   387: iaload
    //   388: ixor
    //   389: aload #7
    //   391: iload #18
    //   393: bipush #14
    //   395: isub
    //   396: iaload
    //   397: ixor
    //   398: aload #7
    //   400: iload #18
    //   402: bipush #16
    //   404: isub
    //   405: iaload
    //   406: ixor
    //   407: istore #19
    //   409: iload #19
    //   411: iconst_1
    //   412: ishl
    //   413: iload #19
    //   415: bipush #31
    //   417: iushr
    //   418: ior
    //   419: istore #20
    //   421: aload #7
    //   423: iload #18
    //   425: iload #20
    //   427: iastore
    //   428: iload #8
    //   430: iconst_5
    //   431: ishl
    //   432: iload #8
    //   434: bipush #27
    //   436: iushr
    //   437: ior
    //   438: istore #19
    //   440: iload #19
    //   442: iload #12
    //   444: iadd
    //   445: aload #7
    //   447: iload #18
    //   449: iaload
    //   450: iadd
    //   451: iload #18
    //   453: bipush #20
    //   455: if_icmpge -> 481
    //   458: ldc 1518500249
    //   460: iload #9
    //   462: iload #10
    //   464: iand
    //   465: iload #9
    //   467: iconst_m1
    //   468: ixor
    //   469: iload #11
    //   471: iand
    //   472: ior
    //   473: iadd
    //   474: goto -> 551
    //   477: invokestatic a : (Ljava/lang/Throwable;)Ljava/lang/Throwable;
    //   480: athrow
    //   481: iload #18
    //   483: bipush #40
    //   485: if_icmpge -> 506
    //   488: ldc 1859775393
    //   490: iload #9
    //   492: iload #10
    //   494: ixor
    //   495: iload #11
    //   497: ixor
    //   498: iadd
    //   499: goto -> 551
    //   502: invokestatic a : (Ljava/lang/Throwable;)Ljava/lang/Throwable;
    //   505: athrow
    //   506: iload #18
    //   508: bipush #60
    //   510: if_icmpge -> 540
    //   513: ldc -1894007588
    //   515: iload #9
    //   517: iload #10
    //   519: iand
    //   520: iload #9
    //   522: iload #11
    //   524: iand
    //   525: ior
    //   526: iload #10
    //   528: iload #11
    //   530: iand
    //   531: ior
    //   532: iadd
    //   533: goto -> 551
    //   536: invokestatic a : (Ljava/lang/Throwable;)Ljava/lang/Throwable;
    //   539: athrow
    //   540: ldc -899497514
    //   542: iload #9
    //   544: iload #10
    //   546: ixor
    //   547: iload #11
    //   549: ixor
    //   550: iadd
    //   551: iadd
    //   552: istore #20
    //   554: iload #11
    //   556: istore #12
    //   558: iload #10
    //   560: istore #11
    //   562: iload #9
    //   564: bipush #30
    //   566: ishl
    //   567: iload #9
    //   569: iconst_2
    //   570: iushr
    //   571: ior
    //   572: istore #10
    //   574: iload #8
    //   576: istore #9
    //   578: iload #20
    //   580: istore #8
    //   582: iinc #18, 1
    //   585: iload_2
    //   586: ifne -> 335
    //   589: iload #8
    //   591: iload #13
    //   593: iadd
    //   594: istore #8
    //   596: iload #9
    //   598: iload #14
    //   600: iadd
    //   601: istore #9
    //   603: iload #10
    //   605: iload #15
    //   607: iadd
    //   608: istore #10
    //   610: iload #11
    //   612: iload #16
    //   614: iadd
    //   615: istore #11
    //   617: iload #12
    //   619: iload #17
    //   621: iadd
    //   622: istore #12
    //   624: iinc #6, 16
    //   627: iload_2
    //   628: ifne -> 304
    //   631: iconst_5
    //   632: newarray int
    //   634: dup
    //   635: iconst_0
    //   636: iload #8
    //   638: iastore
    //   639: dup
    //   640: iconst_1
    //   641: iload #9
    //   643: iastore
    //   644: dup
    //   645: iconst_2
    //   646: iload #10
    //   648: iastore
    //   649: dup
    //   650: iconst_3
    //   651: iload #11
    //   653: iastore
    //   654: dup
    //   655: iconst_4
    //   656: iload #12
    //   658: iastore
    //   659: astore #13
    //   661: bipush #20
    //   663: newarray byte
    //   665: astore #14
    //   667: iconst_0
    //   668: istore #15
    //   670: iload #15
    //   672: bipush #20
    //   674: if_icmpge -> 715
    //   677: aload #13
    //   679: iload #15
    //   681: iconst_4
    //   682: idiv
    //   683: iaload
    //   684: istore #16
    //   686: iconst_3
    //   687: iload #15
    //   689: iconst_4
    //   690: irem
    //   691: isub
    //   692: bipush #8
    //   694: imul
    //   695: istore #17
    //   697: aload #14
    //   699: iload #15
    //   701: iload #16
    //   703: iload #17
    //   705: iushr
    //   706: i2b
    //   707: bastore
    //   708: iinc #15, 1
    //   711: iload_2
    //   712: ifne -> 670
    //   715: aload #14
    //   717: astore #4
    //   719: sipush #10988
    //   722: sipush #2959
    //   725: invokestatic a : (II)Ljava/lang/String;
    //   728: iconst_1
    //   729: ldc burp/Ztid
    //   731: invokevirtual getClassLoader : ()Ljava/lang/ClassLoader;
    //   734: invokestatic forName : (Ljava/lang/String;ZLjava/lang/ClassLoader;)Ljava/lang/Class;
    //   737: invokevirtual getDeclaredFields : ()[Ljava/lang/reflect/Field;
    //   740: astore_3
    //   741: aload_3
    //   742: arraylength
    //   743: istore #4
    //   745: iconst_0
    //   746: istore #5
    //   748: iload #5
    //   750: iload #4
    //   752: if_icmpge -> 889
    //   755: aload_3
    //   756: iload #5
    //   758: aaload
    //   759: astore #6
    //   761: aload #6
    //   763: invokevirtual getModifiers : ()I
    //   766: invokestatic isStatic : (I)Z
    //   769: ifne -> 779
    //   772: goto -> 882
    //   775: invokestatic a : (Ljava/lang/Throwable;)Ljava/lang/Throwable;
    //   778: athrow
    //   779: aload #6
    //   781: invokevirtual getType : ()Ljava/lang/Class;
    //   784: astore #7
    //   786: aload #7
    //   788: ifnull -> 869
    //   791: aload #7
    //   793: invokevirtual isPrimitive : ()Z
    //   796: ifne -> 869
    //   799: goto -> 806
    //   802: invokestatic a : (Ljava/lang/Throwable;)Ljava/lang/Throwable;
    //   805: athrow
    //   806: aload #7
    //   808: invokevirtual getPackage : ()Ljava/lang/Package;
    //   811: ifnull -> 869
    //   814: goto -> 821
    //   817: invokestatic a : (Ljava/lang/Throwable;)Ljava/lang/Throwable;
    //   820: athrow
    //   821: aload #7
    //   823: invokevirtual getPackage : ()Ljava/lang/Package;
    //   826: invokevirtual getName : ()Ljava/lang/String;
    //   829: ifnull -> 869
    //   832: goto -> 839
    //   835: invokestatic a : (Ljava/lang/Throwable;)Ljava/lang/Throwable;
    //   838: athrow
    //   839: aload #7
    //   841: invokevirtual getPackage : ()Ljava/lang/Package;
    //   844: invokevirtual getName : ()Ljava/lang/String;
    //   847: sipush #11001
    //   850: sipush #4144
    //   853: invokestatic a : (II)Ljava/lang/String;
    //   856: invokevirtual startsWith : (Ljava/lang/String;)Z
    //   859: ifne -> 869
    //   862: goto -> 869
    //   865: invokestatic a : (Ljava/lang/Throwable;)Ljava/lang/Throwable;
    //   868: athrow
    //   869: aload #6
    //   871: iconst_1
    //   872: invokevirtual setAccessible : (Z)V
    //   875: aload #6
    //   877: aconst_null
    //   878: invokevirtual get : (Ljava/lang/Object;)Ljava/lang/Object;
    //   881: pop
    //   882: iinc #5, 1
    //   885: iload_2
    //   886: ifne -> 748
    //   889: sipush #10995
    //   892: sipush #-17703
    //   895: invokestatic a : (II)Ljava/lang/String;
    //   898: invokestatic forName : (Ljava/lang/String;)Ljava/lang/Class;
    //   901: invokevirtual getDeclaredMethods : ()[Ljava/lang/reflect/Method;
    //   904: astore_3
    //   905: aload_3
    //   906: arraylength
    //   907: istore #4
    //   909: iconst_0
    //   910: istore #5
    //   912: iload #5
    //   914: iload #4
    //   916: if_icmpge -> 1048
    //   919: aload_3
    //   920: iload #5
    //   922: aaload
    //   923: astore #6
    //   925: aload #6
    //   927: invokevirtual getParameterTypes : ()[Ljava/lang/Class;
    //   930: pop
    //   931: aload #6
    //   933: invokevirtual getModifiers : ()I
    //   936: invokestatic isStatic : (I)Z
    //   939: ifeq -> 1034
    //   942: aload #6
    //   944: invokevirtual getParameterTypes : ()[Ljava/lang/Class;
    //   947: arraylength
    //   948: iconst_2
    //   949: if_icmpne -> 1034
    //   952: goto -> 959
    //   955: invokestatic a : (Ljava/lang/Throwable;)Ljava/lang/Throwable;
    //   958: athrow
    //   959: aload #6
    //   961: invokevirtual getReturnType : ()Ljava/lang/Class;
    //   964: getstatic java/lang/Void.TYPE : Ljava/lang/Class;
    //   967: invokevirtual equals : (Ljava/lang/Object;)Z
    //   970: ifeq -> 1034
    //   973: goto -> 980
    //   976: invokestatic a : (Ljava/lang/Throwable;)Ljava/lang/Throwable;
    //   979: athrow
    //   980: aload #6
    //   982: iconst_1
    //   983: invokevirtual setAccessible : (Z)V
    //   986: aload #6
    //   988: aconst_null
    //   989: iconst_2
    //   990: anewarray java/lang/Object
    //   993: dup
    //   994: iconst_0
    //   995: aload_0
    //   996: aastore
    //   997: dup
    //   998: iconst_1
    //   999: aload_1
    //   1000: ifnonnull -> 1018
    //   1003: goto -> 1010
    //   1006: invokestatic a : (Ljava/lang/Throwable;)Ljava/lang/Throwable;
    //   1009: athrow
    //   1010: aload_1
    //   1011: goto -> 1025
    //   1014: invokestatic a : (Ljava/lang/Throwable;)Ljava/lang/Throwable;
    //   1017: athrow
    //   1018: aload_1
    //   1019: checkcast [B
    //   1022: invokevirtual clone : ()Ljava/lang/Object;
    //   1025: aastore
    //   1026: invokevirtual invoke : (Ljava/lang/Object;[Ljava/lang/Object;)Ljava/lang/Object;
    //   1029: pop
    //   1030: iload_2
    //   1031: ifne -> 1048
    //   1034: iinc #5, 1
    //   1037: iload_2
    //   1038: ifne -> 912
    //   1041: goto -> 1048
    //   1044: invokestatic a : (Ljava/lang/Throwable;)Ljava/lang/Throwable;
    //   1047: athrow
    //   1048: new java/io/ByteArrayOutputStream
    //   1051: dup
    //   1052: invokespecial <init> : ()V
    //   1055: astore_3
    //   1056: getstatic burp/Zxtc.Zo : Ljava/lang/String;
    //   1059: astore #4
    //   1061: iconst_0
    //   1062: istore #5
    //   1064: iload #5
    //   1066: aload #4
    //   1068: invokevirtual length : ()I
    //   1071: if_icmpge -> 1101
    //   1074: aload_3
    //   1075: aload #4
    //   1077: iload #5
    //   1079: iload #5
    //   1081: iconst_2
    //   1082: iadd
    //   1083: invokevirtual substring : (II)Ljava/lang/String;
    //   1086: bipush #16
    //   1088: invokestatic parseInt : (Ljava/lang/String;I)I
    //   1091: invokevirtual write : (I)V
    //   1094: iinc #5, 2
    //   1097: iload_2
    //   1098: ifne -> 1064
    //   1101: aload_3
    //   1102: invokevirtual toByteArray : ()[B
    //   1105: astore #5
    //   1107: getstatic burp/Zkfa.Zw : Ljava/lang/Object;
    //   1110: checkcast java/math/BigInteger
    //   1113: invokevirtual toByteArray : ()[B
    //   1116: astore #6
    //   1118: sipush #256
    //   1121: newarray byte
    //   1123: astore #8
    //   1125: sipush #256
    //   1128: newarray int
    //   1130: astore #9
    //   1132: sipush #256
    //   1135: newarray int
    //   1137: astore #10
    //   1139: sipush #256
    //   1142: newarray int
    //   1144: astore #11
    //   1146: sipush #256
    //   1149: newarray int
    //   1151: astore #12
    //   1153: bipush #10
    //   1155: newarray int
    //   1157: astore #13
    //   1159: sipush #283
    //   1162: istore #14
    //   1164: iconst_0
    //   1165: istore #16
    //   1167: iload #16
    //   1169: sipush #256
    //   1172: if_icmpge -> 1406
    //   1175: sipush #10979
    //   1178: sipush #-11762
    //   1181: invokestatic a : (II)Ljava/lang/String;
    //   1184: iload #16
    //   1186: iconst_1
    //   1187: iushr
    //   1188: invokevirtual charAt : (I)C
    //   1191: istore #25
    //   1193: iload #16
    //   1195: iconst_1
    //   1196: iand
    //   1197: ifne -> 1212
    //   1200: iload #25
    //   1202: bipush #8
    //   1204: iushr
    //   1205: goto -> 1214
    //   1208: invokestatic a : (Ljava/lang/Throwable;)Ljava/lang/Throwable;
    //   1211: athrow
    //   1212: iload #25
    //   1214: i2b
    //   1215: sipush #255
    //   1218: iand
    //   1219: istore #15
    //   1221: iload #16
    //   1223: iconst_1
    //   1224: ishl
    //   1225: istore #17
    //   1227: iload #17
    //   1229: sipush #256
    //   1232: if_icmplt -> 1242
    //   1235: iload #17
    //   1237: iload #14
    //   1239: ixor
    //   1240: istore #17
    //   1242: iload #17
    //   1244: iconst_1
    //   1245: ishl
    //   1246: istore #18
    //   1248: iload #18
    //   1250: sipush #256
    //   1253: if_icmplt -> 1263
    //   1256: iload #18
    //   1258: iload #14
    //   1260: ixor
    //   1261: istore #18
    //   1263: iload #18
    //   1265: iconst_1
    //   1266: ishl
    //   1267: istore #19
    //   1269: iload #19
    //   1271: sipush #256
    //   1274: if_icmplt -> 1284
    //   1277: iload #19
    //   1279: iload #14
    //   1281: ixor
    //   1282: istore #19
    //   1284: iload #19
    //   1286: iload #16
    //   1288: ixor
    //   1289: istore #20
    //   1291: iload #20
    //   1293: iload #17
    //   1295: ixor
    //   1296: istore #21
    //   1298: iload #20
    //   1300: iload #18
    //   1302: ixor
    //   1303: istore #22
    //   1305: iload #19
    //   1307: iload #18
    //   1309: ixor
    //   1310: iload #17
    //   1312: ixor
    //   1313: istore #23
    //   1315: aload #8
    //   1317: iload #16
    //   1319: iload #15
    //   1321: i2b
    //   1322: bastore
    //   1323: aload #9
    //   1325: iload #15
    //   1327: iload #23
    //   1329: bipush #24
    //   1331: ishl
    //   1332: iload #20
    //   1334: bipush #16
    //   1336: ishl
    //   1337: ior
    //   1338: iload #22
    //   1340: bipush #8
    //   1342: ishl
    //   1343: ior
    //   1344: iload #21
    //   1346: ior
    //   1347: dup
    //   1348: istore #24
    //   1350: iastore
    //   1351: aload #10
    //   1353: iload #15
    //   1355: iload #24
    //   1357: bipush #8
    //   1359: iushr
    //   1360: iload #24
    //   1362: bipush #24
    //   1364: ishl
    //   1365: ior
    //   1366: iastore
    //   1367: aload #11
    //   1369: iload #15
    //   1371: iload #24
    //   1373: bipush #16
    //   1375: iushr
    //   1376: iload #24
    //   1378: bipush #16
    //   1380: ishl
    //   1381: ior
    //   1382: iastore
    //   1383: aload #12
    //   1385: iload #15
    //   1387: iload #24
    //   1389: bipush #24
    //   1391: iushr
    //   1392: iload #24
    //   1394: bipush #8
    //   1396: ishl
    //   1397: ior
    //   1398: iastore
    //   1399: iinc #16, 1
    //   1402: iload_2
    //   1403: ifne -> 1167
    //   1406: iconst_1
    //   1407: istore #25
    //   1409: aload #13
    //   1411: iconst_0
    //   1412: iload #25
    //   1414: bipush #24
    //   1416: ishl
    //   1417: iastore
    //   1418: iconst_1
    //   1419: istore #26
    //   1421: iload #26
    //   1423: bipush #10
    //   1425: if_icmpge -> 1466
    //   1428: iload #25
    //   1430: iconst_1
    //   1431: ishl
    //   1432: istore #25
    //   1434: iload #25
    //   1436: sipush #256
    //   1439: if_icmplt -> 1449
    //   1442: iload #25
    //   1444: iload #14
    //   1446: ixor
    //   1447: istore #25
    //   1449: aload #13
    //   1451: iload #26
    //   1453: iload #25
    //   1455: bipush #24
    //   1457: ishl
    //   1458: iastore
    //   1459: iinc #26, 1
    //   1462: iload_2
    //   1463: ifne -> 1421
    //   1466: iconst_4
    //   1467: istore #26
    //   1469: iload #26
    //   1471: bipush #6
    //   1473: iadd
    //   1474: istore #27
    //   1476: iconst_4
    //   1477: iload #27
    //   1479: iconst_1
    //   1480: iadd
    //   1481: imul
    //   1482: istore #28
    //   1484: iload #28
    //   1486: newarray int
    //   1488: astore #29
    //   1490: iload #28
    //   1492: newarray int
    //   1494: astore #30
    //   1496: iconst_0
    //   1497: istore #25
    //   1499: iconst_0
    //   1500: istore #32
    //   1502: iconst_0
    //   1503: istore #33
    //   1505: iload #32
    //   1507: iload #26
    //   1509: if_icmpge -> 1577
    //   1512: aload #29
    //   1514: iload #32
    //   1516: aload #5
    //   1518: iload #33
    //   1520: baload
    //   1521: bipush #24
    //   1523: ishl
    //   1524: aload #5
    //   1526: iload #33
    //   1528: iconst_1
    //   1529: iadd
    //   1530: baload
    //   1531: sipush #255
    //   1534: iand
    //   1535: bipush #16
    //   1537: ishl
    //   1538: ior
    //   1539: aload #5
    //   1541: iload #33
    //   1543: iconst_2
    //   1544: iadd
    //   1545: baload
    //   1546: sipush #255
    //   1549: iand
    //   1550: bipush #8
    //   1552: ishl
    //   1553: ior
    //   1554: aload #5
    //   1556: iload #33
    //   1558: iconst_3
    //   1559: iadd
    //   1560: baload
    //   1561: sipush #255
    //   1564: iand
    //   1565: ior
    //   1566: iastore
    //   1567: iinc #32, 1
    //   1570: iinc #33, 4
    //   1573: iload_2
    //   1574: ifne -> 1505
    //   1577: iload #26
    //   1579: istore #32
    //   1581: iconst_0
    //   1582: istore #33
    //   1584: iload #32
    //   1586: iload #28
    //   1588: if_icmpge -> 1715
    //   1591: aload #29
    //   1593: iload #32
    //   1595: iconst_1
    //   1596: isub
    //   1597: iaload
    //   1598: istore #31
    //   1600: iload #33
    //   1602: ifne -> 1689
    //   1605: iload #26
    //   1607: istore #33
    //   1609: aload #8
    //   1611: iload #31
    //   1613: bipush #16
    //   1615: iushr
    //   1616: sipush #255
    //   1619: iand
    //   1620: baload
    //   1621: bipush #24
    //   1623: ishl
    //   1624: aload #8
    //   1626: iload #31
    //   1628: bipush #8
    //   1630: iushr
    //   1631: sipush #255
    //   1634: iand
    //   1635: baload
    //   1636: sipush #255
    //   1639: iand
    //   1640: bipush #16
    //   1642: ishl
    //   1643: ior
    //   1644: aload #8
    //   1646: iload #31
    //   1648: sipush #255
    //   1651: iand
    //   1652: baload
    //   1653: sipush #255
    //   1656: iand
    //   1657: bipush #8
    //   1659: ishl
    //   1660: ior
    //   1661: aload #8
    //   1663: iload #31
    //   1665: bipush #24
    //   1667: iushr
    //   1668: baload
    //   1669: sipush #255
    //   1672: iand
    //   1673: ior
    //   1674: istore #31
    //   1676: iload #31
    //   1678: aload #13
    //   1680: iload #25
    //   1682: iinc #25, 1
    //   1685: iaload
    //   1686: ixor
    //   1687: istore #31
    //   1689: aload #29
    //   1691: iload #32
    //   1693: aload #29
    //   1695: iload #32
    //   1697: iload #26
    //   1699: isub
    //   1700: iaload
    //   1701: iload #31
    //   1703: ixor
    //   1704: iastore
    //   1705: iinc #32, 1
    //   1708: iinc #33, -1
    //   1711: iload_2
    //   1712: ifne -> 1584
    //   1715: iconst_0
    //   1716: istore #32
    //   1718: iconst_4
    //   1719: iload #27
    //   1721: imul
    //   1722: istore #33
    //   1724: aload #30
    //   1726: iload #32
    //   1728: aload #29
    //   1730: iload #33
    //   1732: iaload
    //   1733: iastore
    //   1734: aload #30
    //   1736: iload #32
    //   1738: iconst_1
    //   1739: iadd
    //   1740: aload #29
    //   1742: iload #33
    //   1744: iconst_1
    //   1745: iadd
    //   1746: iaload
    //   1747: iastore
    //   1748: aload #30
    //   1750: iload #32
    //   1752: iconst_2
    //   1753: iadd
    //   1754: aload #29
    //   1756: iload #33
    //   1758: iconst_2
    //   1759: iadd
    //   1760: iaload
    //   1761: iastore
    //   1762: aload #30
    //   1764: iload #32
    //   1766: iconst_3
    //   1767: iadd
    //   1768: aload #29
    //   1770: iload #33
    //   1772: iconst_3
    //   1773: iadd
    //   1774: iaload
    //   1775: iastore
    //   1776: iinc #32, 4
    //   1779: iinc #33, -4
    //   1782: iconst_1
    //   1783: istore #35
    //   1785: iload #35
    //   1787: iload #27
    //   1789: if_icmpge -> 2153
    //   1792: aload #29
    //   1794: iload #33
    //   1796: iaload
    //   1797: istore #34
    //   1799: aload #30
    //   1801: iload #32
    //   1803: aload #9
    //   1805: aload #8
    //   1807: iload #34
    //   1809: bipush #24
    //   1811: iushr
    //   1812: baload
    //   1813: sipush #255
    //   1816: iand
    //   1817: iaload
    //   1818: aload #10
    //   1820: aload #8
    //   1822: iload #34
    //   1824: bipush #16
    //   1826: iushr
    //   1827: sipush #255
    //   1830: iand
    //   1831: baload
    //   1832: sipush #255
    //   1835: iand
    //   1836: iaload
    //   1837: ixor
    //   1838: aload #11
    //   1840: aload #8
    //   1842: iload #34
    //   1844: bipush #8
    //   1846: iushr
    //   1847: sipush #255
    //   1850: iand
    //   1851: baload
    //   1852: sipush #255
    //   1855: iand
    //   1856: iaload
    //   1857: ixor
    //   1858: aload #12
    //   1860: aload #8
    //   1862: iload #34
    //   1864: sipush #255
    //   1867: iand
    //   1868: baload
    //   1869: sipush #255
    //   1872: iand
    //   1873: iaload
    //   1874: ixor
    //   1875: iastore
    //   1876: aload #29
    //   1878: iload #33
    //   1880: iconst_1
    //   1881: iadd
    //   1882: iaload
    //   1883: istore #34
    //   1885: aload #30
    //   1887: iload #32
    //   1889: iconst_1
    //   1890: iadd
    //   1891: aload #9
    //   1893: aload #8
    //   1895: iload #34
    //   1897: bipush #24
    //   1899: iushr
    //   1900: baload
    //   1901: sipush #255
    //   1904: iand
    //   1905: iaload
    //   1906: aload #10
    //   1908: aload #8
    //   1910: iload #34
    //   1912: bipush #16
    //   1914: iushr
    //   1915: sipush #255
    //   1918: iand
    //   1919: baload
    //   1920: sipush #255
    //   1923: iand
    //   1924: iaload
    //   1925: ixor
    //   1926: aload #11
    //   1928: aload #8
    //   1930: iload #34
    //   1932: bipush #8
    //   1934: iushr
    //   1935: sipush #255
    //   1938: iand
    //   1939: baload
    //   1940: sipush #255
    //   1943: iand
    //   1944: iaload
    //   1945: ixor
    //   1946: aload #12
    //   1948: aload #8
    //   1950: iload #34
    //   1952: sipush #255
    //   1955: iand
    //   1956: baload
    //   1957: sipush #255
    //   1960: iand
    //   1961: iaload
    //   1962: ixor
    //   1963: iastore
    //   1964: aload #29
    //   1966: iload #33
    //   1968: iconst_2
    //   1969: iadd
    //   1970: iaload
    //   1971: istore #34
    //   1973: aload #30
    //   1975: iload #32
    //   1977: iconst_2
    //   1978: iadd
    //   1979: aload #9
    //   1981: aload #8
    //   1983: iload #34
    //   1985: bipush #24
    //   1987: iushr
    //   1988: baload
    //   1989: sipush #255
    //   1992: iand
    //   1993: iaload
    //   1994: aload #10
    //   1996: aload #8
    //   1998: iload #34
    //   2000: bipush #16
    //   2002: iushr
    //   2003: sipush #255
    //   2006: iand
    //   2007: baload
    //   2008: sipush #255
    //   2011: iand
    //   2012: iaload
    //   2013: ixor
    //   2014: aload #11
    //   2016: aload #8
    //   2018: iload #34
    //   2020: bipush #8
    //   2022: iushr
    //   2023: sipush #255
    //   2026: iand
    //   2027: baload
    //   2028: sipush #255
    //   2031: iand
    //   2032: iaload
    //   2033: ixor
    //   2034: aload #12
    //   2036: aload #8
    //   2038: iload #34
    //   2040: sipush #255
    //   2043: iand
    //   2044: baload
    //   2045: sipush #255
    //   2048: iand
    //   2049: iaload
    //   2050: ixor
    //   2051: iastore
    //   2052: aload #29
    //   2054: iload #33
    //   2056: iconst_3
    //   2057: iadd
    //   2058: iaload
    //   2059: istore #34
    //   2061: aload #30
    //   2063: iload #32
    //   2065: iconst_3
    //   2066: iadd
    //   2067: aload #9
    //   2069: aload #8
    //   2071: iload #34
    //   2073: bipush #24
    //   2075: iushr
    //   2076: baload
    //   2077: sipush #255
    //   2080: iand
    //   2081: iaload
    //   2082: aload #10
    //   2084: aload #8
    //   2086: iload #34
    //   2088: bipush #16
    //   2090: iushr
    //   2091: sipush #255
    //   2094: iand
    //   2095: baload
    //   2096: sipush #255
    //   2099: iand
    //   2100: iaload
    //   2101: ixor
    //   2102: aload #11
    //   2104: aload #8
    //   2106: iload #34
    //   2108: bipush #8
    //   2110: iushr
    //   2111: sipush #255
    //   2114: iand
    //   2115: baload
    //   2116: sipush #255
    //   2119: iand
    //   2120: iaload
    //   2121: ixor
    //   2122: aload #12
    //   2124: aload #8
    //   2126: iload #34
    //   2128: sipush #255
    //   2131: iand
    //   2132: baload
    //   2133: sipush #255
    //   2136: iand
    //   2137: iaload
    //   2138: ixor
    //   2139: iastore
    //   2140: iinc #32, 4
    //   2143: iinc #33, -4
    //   2146: iinc #35, 1
    //   2149: iload_2
    //   2150: ifne -> 1785
    //   2153: aload #30
    //   2155: iload #32
    //   2157: aload #29
    //   2159: iload #33
    //   2161: iaload
    //   2162: iastore
    //   2163: aload #30
    //   2165: iload #32
    //   2167: iconst_1
    //   2168: iadd
    //   2169: aload #29
    //   2171: iload #33
    //   2173: iconst_1
    //   2174: iadd
    //   2175: iaload
    //   2176: iastore
    //   2177: aload #30
    //   2179: iload #32
    //   2181: iconst_2
    //   2182: iadd
    //   2183: aload #29
    //   2185: iload #33
    //   2187: iconst_2
    //   2188: iadd
    //   2189: iaload
    //   2190: iastore
    //   2191: aload #30
    //   2193: iload #32
    //   2195: iconst_3
    //   2196: iadd
    //   2197: aload #29
    //   2199: iload #33
    //   2201: iconst_3
    //   2202: iadd
    //   2203: iaload
    //   2204: iastore
    //   2205: iconst_0
    //   2206: newarray byte
    //   2208: astore #35
    //   2210: aload #6
    //   2212: arraylength
    //   2213: bipush #16
    //   2215: irem
    //   2216: ifeq -> 2240
    //   2219: new java/lang/Exception
    //   2222: dup
    //   2223: sipush #10976
    //   2226: sipush #2580
    //   2229: invokestatic a : (II)Ljava/lang/String;
    //   2232: invokespecial <init> : (Ljava/lang/String;)V
    //   2235: athrow
    //   2236: invokestatic a : (Ljava/lang/Throwable;)Ljava/lang/Throwable;
    //   2239: athrow
    //   2240: bipush #10
    //   2242: istore #36
    //   2244: sipush #10982
    //   2247: sipush #256
    //   2250: newarray byte
    //   2252: astore #37
    //   2254: sipush #24181
    //   2257: sipush #256
    //   2260: newarray int
    //   2262: astore #38
    //   2264: sipush #256
    //   2267: newarray int
    //   2269: astore #39
    //   2271: sipush #256
    //   2274: newarray int
    //   2276: astore #40
    //   2278: sipush #256
    //   2281: newarray int
    //   2283: astore #41
    //   2285: sipush #283
    //   2288: istore #14
    //   2290: invokestatic a : (II)Ljava/lang/String;
    //   2293: astore #42
    //   2295: iconst_0
    //   2296: istore #16
    //   2298: iload #16
    //   2300: sipush #256
    //   2303: if_icmpge -> 2530
    //   2306: aload #42
    //   2308: iload #16
    //   2310: iconst_1
    //   2311: iushr
    //   2312: invokevirtual charAt : (I)C
    //   2315: istore #43
    //   2317: iload #16
    //   2319: iconst_1
    //   2320: iand
    //   2321: ifne -> 2336
    //   2324: iload #43
    //   2326: bipush #8
    //   2328: iushr
    //   2329: goto -> 2338
    //   2332: invokestatic a : (Ljava/lang/Throwable;)Ljava/lang/Throwable;
    //   2335: athrow
    //   2336: iload #43
    //   2338: i2b
    //   2339: sipush #255
    //   2342: iand
    //   2343: istore #15
    //   2345: iload #16
    //   2347: iconst_1
    //   2348: ishl
    //   2349: istore #17
    //   2351: iload #17
    //   2353: sipush #256
    //   2356: if_icmplt -> 2366
    //   2359: iload #17
    //   2361: iload #14
    //   2363: ixor
    //   2364: istore #17
    //   2366: iload #17
    //   2368: iconst_1
    //   2369: ishl
    //   2370: istore #18
    //   2372: iload #18
    //   2374: sipush #256
    //   2377: if_icmplt -> 2387
    //   2380: iload #18
    //   2382: iload #14
    //   2384: ixor
    //   2385: istore #18
    //   2387: iload #18
    //   2389: iconst_1
    //   2390: ishl
    //   2391: istore #19
    //   2393: iload #19
    //   2395: sipush #256
    //   2398: if_icmplt -> 2408
    //   2401: iload #19
    //   2403: iload #14
    //   2405: ixor
    //   2406: istore #19
    //   2408: iload #19
    //   2410: iload #16
    //   2412: ixor
    //   2413: istore #20
    //   2415: iload #20
    //   2417: iload #17
    //   2419: ixor
    //   2420: istore #21
    //   2422: iload #20
    //   2424: iload #18
    //   2426: ixor
    //   2427: istore #22
    //   2429: iload #19
    //   2431: iload #18
    //   2433: ixor
    //   2434: iload #17
    //   2436: ixor
    //   2437: istore #23
    //   2439: aload #37
    //   2441: iload #15
    //   2443: iload #16
    //   2445: i2b
    //   2446: bastore
    //   2447: aload #38
    //   2449: iload #15
    //   2451: iload #23
    //   2453: bipush #24
    //   2455: ishl
    //   2456: iload #20
    //   2458: bipush #16
    //   2460: ishl
    //   2461: ior
    //   2462: iload #22
    //   2464: bipush #8
    //   2466: ishl
    //   2467: ior
    //   2468: iload #21
    //   2470: ior
    //   2471: dup
    //   2472: istore #24
    //   2474: iastore
    //   2475: aload #39
    //   2477: iload #15
    //   2479: iload #24
    //   2481: bipush #8
    //   2483: iushr
    //   2484: iload #24
    //   2486: bipush #24
    //   2488: ishl
    //   2489: ior
    //   2490: iastore
    //   2491: aload #40
    //   2493: iload #15
    //   2495: iload #24
    //   2497: bipush #16
    //   2499: iushr
    //   2500: iload #24
    //   2502: bipush #16
    //   2504: ishl
    //   2505: ior
    //   2506: iastore
    //   2507: aload #41
    //   2509: iload #15
    //   2511: iload #24
    //   2513: bipush #24
    //   2515: iushr
    //   2516: iload #24
    //   2518: bipush #8
    //   2520: ishl
    //   2521: ior
    //   2522: iastore
    //   2523: iinc #16, 1
    //   2526: iload_2
    //   2527: ifne -> 2298
    //   2530: aload #6
    //   2532: arraylength
    //   2533: newarray byte
    //   2535: astore #43
    //   2537: iconst_0
    //   2538: istore #44
    //   2540: iload #44
    //   2542: aload #6
    //   2544: arraylength
    //   2545: bipush #16
    //   2547: idiv
    //   2548: if_icmpge -> 3462
    //   2551: bipush #16
    //   2553: newarray byte
    //   2555: astore #45
    //   2557: bipush #16
    //   2559: newarray byte
    //   2561: astore #46
    //   2563: iconst_0
    //   2564: istore #47
    //   2566: iload #47
    //   2568: bipush #16
    //   2570: if_icmpge -> 2596
    //   2573: aload #45
    //   2575: iload #47
    //   2577: aload #6
    //   2579: iload #47
    //   2581: iload #44
    //   2583: bipush #16
    //   2585: imul
    //   2586: iadd
    //   2587: baload
    //   2588: bastore
    //   2589: iinc #47, 1
    //   2592: iload_2
    //   2593: ifne -> 2566
    //   2596: iconst_0
    //   2597: istore #47
    //   2599: aload #45
    //   2601: iconst_0
    //   2602: baload
    //   2603: bipush #24
    //   2605: ishl
    //   2606: aload #45
    //   2608: iconst_1
    //   2609: baload
    //   2610: sipush #255
    //   2613: iand
    //   2614: bipush #16
    //   2616: ishl
    //   2617: ior
    //   2618: aload #45
    //   2620: iconst_2
    //   2621: baload
    //   2622: sipush #255
    //   2625: iand
    //   2626: bipush #8
    //   2628: ishl
    //   2629: ior
    //   2630: aload #45
    //   2632: iconst_3
    //   2633: baload
    //   2634: sipush #255
    //   2637: iand
    //   2638: ior
    //   2639: aload #30
    //   2641: iconst_0
    //   2642: iaload
    //   2643: ixor
    //   2644: istore #49
    //   2646: aload #45
    //   2648: iconst_4
    //   2649: baload
    //   2650: bipush #24
    //   2652: ishl
    //   2653: aload #45
    //   2655: iconst_5
    //   2656: baload
    //   2657: sipush #255
    //   2660: iand
    //   2661: bipush #16
    //   2663: ishl
    //   2664: ior
    //   2665: aload #45
    //   2667: bipush #6
    //   2669: baload
    //   2670: sipush #255
    //   2673: iand
    //   2674: bipush #8
    //   2676: ishl
    //   2677: ior
    //   2678: aload #45
    //   2680: bipush #7
    //   2682: baload
    //   2683: sipush #255
    //   2686: iand
    //   2687: ior
    //   2688: aload #30
    //   2690: iconst_1
    //   2691: iaload
    //   2692: ixor
    //   2693: istore #50
    //   2695: aload #45
    //   2697: bipush #8
    //   2699: baload
    //   2700: bipush #24
    //   2702: ishl
    //   2703: aload #45
    //   2705: bipush #9
    //   2707: baload
    //   2708: sipush #255
    //   2711: iand
    //   2712: bipush #16
    //   2714: ishl
    //   2715: ior
    //   2716: aload #45
    //   2718: bipush #10
    //   2720: baload
    //   2721: sipush #255
    //   2724: iand
    //   2725: bipush #8
    //   2727: ishl
    //   2728: ior
    //   2729: aload #45
    //   2731: bipush #11
    //   2733: baload
    //   2734: sipush #255
    //   2737: iand
    //   2738: ior
    //   2739: aload #30
    //   2741: iconst_2
    //   2742: iaload
    //   2743: ixor
    //   2744: istore #51
    //   2746: aload #45
    //   2748: bipush #12
    //   2750: baload
    //   2751: bipush #24
    //   2753: ishl
    //   2754: aload #45
    //   2756: bipush #13
    //   2758: baload
    //   2759: sipush #255
    //   2762: iand
    //   2763: bipush #16
    //   2765: ishl
    //   2766: ior
    //   2767: aload #45
    //   2769: bipush #14
    //   2771: baload
    //   2772: sipush #255
    //   2775: iand
    //   2776: bipush #8
    //   2778: ishl
    //   2779: ior
    //   2780: aload #45
    //   2782: bipush #15
    //   2784: baload
    //   2785: sipush #255
    //   2788: iand
    //   2789: ior
    //   2790: aload #30
    //   2792: iconst_3
    //   2793: iaload
    //   2794: ixor
    //   2795: istore #52
    //   2797: iconst_1
    //   2798: istore #53
    //   2800: iload #53
    //   2802: iload #36
    //   2804: if_icmpge -> 3047
    //   2807: iinc #47, 4
    //   2810: aload #38
    //   2812: iload #49
    //   2814: bipush #24
    //   2816: iushr
    //   2817: iaload
    //   2818: aload #39
    //   2820: iload #52
    //   2822: bipush #16
    //   2824: iushr
    //   2825: sipush #255
    //   2828: iand
    //   2829: iaload
    //   2830: ixor
    //   2831: aload #40
    //   2833: iload #51
    //   2835: bipush #8
    //   2837: iushr
    //   2838: sipush #255
    //   2841: iand
    //   2842: iaload
    //   2843: ixor
    //   2844: aload #41
    //   2846: iload #50
    //   2848: sipush #255
    //   2851: iand
    //   2852: iaload
    //   2853: ixor
    //   2854: aload #30
    //   2856: iload #47
    //   2858: iaload
    //   2859: ixor
    //   2860: istore #54
    //   2862: aload #38
    //   2864: iload #50
    //   2866: bipush #24
    //   2868: iushr
    //   2869: iaload
    //   2870: aload #39
    //   2872: iload #49
    //   2874: bipush #16
    //   2876: iushr
    //   2877: sipush #255
    //   2880: iand
    //   2881: iaload
    //   2882: ixor
    //   2883: aload #40
    //   2885: iload #52
    //   2887: bipush #8
    //   2889: iushr
    //   2890: sipush #255
    //   2893: iand
    //   2894: iaload
    //   2895: ixor
    //   2896: aload #41
    //   2898: iload #51
    //   2900: sipush #255
    //   2903: iand
    //   2904: iaload
    //   2905: ixor
    //   2906: aload #30
    //   2908: iload #47
    //   2910: iconst_1
    //   2911: iadd
    //   2912: iaload
    //   2913: ixor
    //   2914: istore #55
    //   2916: aload #38
    //   2918: iload #51
    //   2920: bipush #24
    //   2922: iushr
    //   2923: iaload
    //   2924: aload #39
    //   2926: iload #50
    //   2928: bipush #16
    //   2930: iushr
    //   2931: sipush #255
    //   2934: iand
    //   2935: iaload
    //   2936: ixor
    //   2937: aload #40
    //   2939: iload #49
    //   2941: bipush #8
    //   2943: iushr
    //   2944: sipush #255
    //   2947: iand
    //   2948: iaload
    //   2949: ixor
    //   2950: aload #41
    //   2952: iload #52
    //   2954: sipush #255
    //   2957: iand
    //   2958: iaload
    //   2959: ixor
    //   2960: aload #30
    //   2962: iload #47
    //   2964: iconst_2
    //   2965: iadd
    //   2966: iaload
    //   2967: ixor
    //   2968: istore #56
    //   2970: aload #38
    //   2972: iload #52
    //   2974: bipush #24
    //   2976: iushr
    //   2977: iaload
    //   2978: aload #39
    //   2980: iload #51
    //   2982: bipush #16
    //   2984: iushr
    //   2985: sipush #255
    //   2988: iand
    //   2989: iaload
    //   2990: ixor
    //   2991: aload #40
    //   2993: iload #50
    //   2995: bipush #8
    //   2997: iushr
    //   2998: sipush #255
    //   3001: iand
    //   3002: iaload
    //   3003: ixor
    //   3004: aload #41
    //   3006: iload #49
    //   3008: sipush #255
    //   3011: iand
    //   3012: iaload
    //   3013: ixor
    //   3014: aload #30
    //   3016: iload #47
    //   3018: iconst_3
    //   3019: iadd
    //   3020: iaload
    //   3021: ixor
    //   3022: istore #57
    //   3024: iload #54
    //   3026: istore #49
    //   3028: iload #55
    //   3030: istore #50
    //   3032: iload #56
    //   3034: istore #51
    //   3036: iload #57
    //   3038: istore #52
    //   3040: iinc #53, 1
    //   3043: iload_2
    //   3044: ifne -> 2800
    //   3047: iinc #47, 4
    //   3050: aload #30
    //   3052: iload #47
    //   3054: iaload
    //   3055: istore #48
    //   3057: aload #46
    //   3059: iconst_0
    //   3060: aload #37
    //   3062: iload #49
    //   3064: bipush #24
    //   3066: iushr
    //   3067: baload
    //   3068: iload #48
    //   3070: bipush #24
    //   3072: iushr
    //   3073: ixor
    //   3074: i2b
    //   3075: bastore
    //   3076: aload #46
    //   3078: iconst_1
    //   3079: aload #37
    //   3081: iload #52
    //   3083: bipush #16
    //   3085: iushr
    //   3086: sipush #255
    //   3089: iand
    //   3090: baload
    //   3091: iload #48
    //   3093: bipush #16
    //   3095: iushr
    //   3096: ixor
    //   3097: i2b
    //   3098: bastore
    //   3099: aload #46
    //   3101: iconst_2
    //   3102: aload #37
    //   3104: iload #51
    //   3106: bipush #8
    //   3108: iushr
    //   3109: sipush #255
    //   3112: iand
    //   3113: baload
    //   3114: iload #48
    //   3116: bipush #8
    //   3118: iushr
    //   3119: ixor
    //   3120: i2b
    //   3121: bastore
    //   3122: aload #46
    //   3124: iconst_3
    //   3125: aload #37
    //   3127: iload #50
    //   3129: sipush #255
    //   3132: iand
    //   3133: baload
    //   3134: iload #48
    //   3136: ixor
    //   3137: i2b
    //   3138: bastore
    //   3139: aload #30
    //   3141: iload #47
    //   3143: iconst_1
    //   3144: iadd
    //   3145: iaload
    //   3146: istore #48
    //   3148: aload #46
    //   3150: iconst_4
    //   3151: aload #37
    //   3153: iload #50
    //   3155: bipush #24
    //   3157: iushr
    //   3158: baload
    //   3159: iload #48
    //   3161: bipush #24
    //   3163: iushr
    //   3164: ixor
    //   3165: i2b
    //   3166: bastore
    //   3167: aload #46
    //   3169: iconst_5
    //   3170: aload #37
    //   3172: iload #49
    //   3174: bipush #16
    //   3176: iushr
    //   3177: sipush #255
    //   3180: iand
    //   3181: baload
    //   3182: iload #48
    //   3184: bipush #16
    //   3186: iushr
    //   3187: ixor
    //   3188: i2b
    //   3189: bastore
    //   3190: aload #46
    //   3192: bipush #6
    //   3194: aload #37
    //   3196: iload #52
    //   3198: bipush #8
    //   3200: iushr
    //   3201: sipush #255
    //   3204: iand
    //   3205: baload
    //   3206: iload #48
    //   3208: bipush #8
    //   3210: iushr
    //   3211: ixor
    //   3212: i2b
    //   3213: bastore
    //   3214: aload #46
    //   3216: bipush #7
    //   3218: aload #37
    //   3220: iload #51
    //   3222: sipush #255
    //   3225: iand
    //   3226: baload
    //   3227: iload #48
    //   3229: ixor
    //   3230: i2b
    //   3231: bastore
    //   3232: aload #30
    //   3234: iload #47
    //   3236: iconst_2
    //   3237: iadd
    //   3238: iaload
    //   3239: istore #48
    //   3241: aload #46
    //   3243: bipush #8
    //   3245: aload #37
    //   3247: iload #51
    //   3249: bipush #24
    //   3251: iushr
    //   3252: baload
    //   3253: iload #48
    //   3255: bipush #24
    //   3257: iushr
    //   3258: ixor
    //   3259: i2b
    //   3260: bastore
    //   3261: aload #46
    //   3263: bipush #9
    //   3265: aload #37
    //   3267: iload #50
    //   3269: bipush #16
    //   3271: iushr
    //   3272: sipush #255
    //   3275: iand
    //   3276: baload
    //   3277: iload #48
    //   3279: bipush #16
    //   3281: iushr
    //   3282: ixor
    //   3283: i2b
    //   3284: bastore
    //   3285: aload #46
    //   3287: bipush #10
    //   3289: aload #37
    //   3291: iload #49
    //   3293: bipush #8
    //   3295: iushr
    //   3296: sipush #255
    //   3299: iand
    //   3300: baload
    //   3301: iload #48
    //   3303: bipush #8
    //   3305: iushr
    //   3306: ixor
    //   3307: i2b
    //   3308: bastore
    //   3309: aload #46
    //   3311: bipush #11
    //   3313: aload #37
    //   3315: iload #52
    //   3317: sipush #255
    //   3320: iand
    //   3321: baload
    //   3322: iload #48
    //   3324: ixor
    //   3325: i2b
    //   3326: bastore
    //   3327: aload #30
    //   3329: iload #47
    //   3331: iconst_3
    //   3332: iadd
    //   3333: iaload
    //   3334: istore #48
    //   3336: aload #46
    //   3338: bipush #12
    //   3340: aload #37
    //   3342: iload #52
    //   3344: bipush #24
    //   3346: iushr
    //   3347: baload
    //   3348: iload #48
    //   3350: bipush #24
    //   3352: iushr
    //   3353: ixor
    //   3354: i2b
    //   3355: bastore
    //   3356: aload #46
    //   3358: bipush #13
    //   3360: aload #37
    //   3362: iload #51
    //   3364: bipush #16
    //   3366: iushr
    //   3367: sipush #255
    //   3370: iand
    //   3371: baload
    //   3372: iload #48
    //   3374: bipush #16
    //   3376: iushr
    //   3377: ixor
    //   3378: i2b
    //   3379: bastore
    //   3380: aload #46
    //   3382: bipush #14
    //   3384: aload #37
    //   3386: iload #50
    //   3388: bipush #8
    //   3390: iushr
    //   3391: sipush #255
    //   3394: iand
    //   3395: baload
    //   3396: iload #48
    //   3398: bipush #8
    //   3400: iushr
    //   3401: ixor
    //   3402: i2b
    //   3403: bastore
    //   3404: aload #46
    //   3406: bipush #15
    //   3408: aload #37
    //   3410: iload #49
    //   3412: sipush #255
    //   3415: iand
    //   3416: baload
    //   3417: iload #48
    //   3419: ixor
    //   3420: i2b
    //   3421: bastore
    //   3422: iconst_0
    //   3423: istore #53
    //   3425: iload #53
    //   3427: bipush #16
    //   3429: if_icmpge -> 3455
    //   3432: aload #43
    //   3434: iload #53
    //   3436: iload #44
    //   3438: bipush #16
    //   3440: imul
    //   3441: iadd
    //   3442: aload #46
    //   3444: iload #53
    //   3446: baload
    //   3447: bastore
    //   3448: iinc #53, 1
    //   3451: iload_2
    //   3452: ifne -> 3425
    //   3455: iinc #44, 1
    //   3458: iload_2
    //   3459: ifne -> 2540
    //   3462: aload #43
    //   3464: arraylength
    //   3465: ifle -> 3546
    //   3468: aload #43
    //   3470: aload #43
    //   3472: arraylength
    //   3473: iconst_1
    //   3474: isub
    //   3475: baload
    //   3476: istore #44
    //   3478: iload #44
    //   3480: bipush #16
    //   3482: if_icmple -> 3493
    //   3485: aload #43
    //   3487: astore #35
    //   3489: iload_2
    //   3490: ifne -> 3546
    //   3493: aload #43
    //   3495: arraylength
    //   3496: iload #44
    //   3498: isub
    //   3499: newarray byte
    //   3501: astore #35
    //   3503: iconst_0
    //   3504: istore #45
    //   3506: iload #45
    //   3508: aload #35
    //   3510: arraylength
    //   3511: if_icmpge -> 3546
    //   3514: iload #45
    //   3516: aload #43
    //   3518: arraylength
    //   3519: if_icmpge -> 3546
    //   3522: aload #35
    //   3524: iload #45
    //   3526: aload #43
    //   3528: iload #45
    //   3530: baload
    //   3531: bastore
    //   3532: iinc #45, 1
    //   3535: iload_2
    //   3536: ifne -> 3506
    //   3539: goto -> 3546
    //   3542: invokestatic a : (Ljava/lang/Throwable;)Ljava/lang/Throwable;
    //   3545: athrow
    //   3546: aload #35
    //   3548: astore #7
    //   3550: iconst_0
    //   3551: istore_3
    //   3552: getstatic burp/Zb9h.Zf : Ljava/lang/String;
    //   3555: getstatic burp/Zzok.ZY : Ljava/lang/Object;
    //   3558: checkcast java/math/BigInteger
    //   3561: invokevirtual intValue : ()I
    //   3564: bipush #32
    //   3566: irem
    //   3567: invokestatic abs : (I)I
    //   3570: invokevirtual charAt : (I)C
    //   3573: getstatic burp/Zbp_.ZQ : Ljava/lang/String;
    //   3576: getstatic burp/Zlps.ZU : Ljava/lang/Object;
    //   3579: checkcast java/math/BigInteger
    //   3582: invokevirtual intValue : ()I
    //   3585: bipush #32
    //   3587: irem
    //   3588: invokestatic abs : (I)I
    //   3591: invokevirtual charAt : (I)C
    //   3594: if_icmple -> 3938
    //   3597: sipush #10983
    //   3600: sipush #-17066
    //   3603: invokestatic a : (II)Ljava/lang/String;
    //   3606: iconst_1
    //   3607: ldc burp/Zgii
    //   3609: invokevirtual getClassLoader : ()Ljava/lang/ClassLoader;
    //   3612: invokestatic forName : (Ljava/lang/String;ZLjava/lang/ClassLoader;)Ljava/lang/Class;
    //   3615: invokevirtual getDeclaredFields : ()[Ljava/lang/reflect/Field;
    //   3618: astore #4
    //   3620: aload #4
    //   3622: arraylength
    //   3623: istore #5
    //   3625: iconst_0
    //   3626: istore #6
    //   3628: iload #6
    //   3630: iload #5
    //   3632: if_icmpge -> 3770
    //   3635: aload #4
    //   3637: iload #6
    //   3639: aaload
    //   3640: astore #7
    //   3642: aload #7
    //   3644: invokevirtual getModifiers : ()I
    //   3647: invokestatic isStatic : (I)Z
    //   3650: ifne -> 3660
    //   3653: goto -> 3763
    //   3656: invokestatic a : (Ljava/lang/Throwable;)Ljava/lang/Throwable;
    //   3659: athrow
    //   3660: aload #7
    //   3662: invokevirtual getType : ()Ljava/lang/Class;
    //   3665: astore #8
    //   3667: aload #8
    //   3669: ifnull -> 3750
    //   3672: aload #8
    //   3674: invokevirtual isPrimitive : ()Z
    //   3677: ifne -> 3750
    //   3680: goto -> 3687
    //   3683: invokestatic a : (Ljava/lang/Throwable;)Ljava/lang/Throwable;
    //   3686: athrow
    //   3687: aload #8
    //   3689: invokevirtual getPackage : ()Ljava/lang/Package;
    //   3692: ifnull -> 3750
    //   3695: goto -> 3702
    //   3698: invokestatic a : (Ljava/lang/Throwable;)Ljava/lang/Throwable;
    //   3701: athrow
    //   3702: aload #8
    //   3704: invokevirtual getPackage : ()Ljava/lang/Package;
    //   3707: invokevirtual getName : ()Ljava/lang/String;
    //   3710: ifnull -> 3750
    //   3713: goto -> 3720
    //   3716: invokestatic a : (Ljava/lang/Throwable;)Ljava/lang/Throwable;
    //   3719: athrow
    //   3720: aload #8
    //   3722: invokevirtual getPackage : ()Ljava/lang/Package;
    //   3725: invokevirtual getName : ()Ljava/lang/String;
    //   3728: sipush #10980
    //   3731: sipush #-15275
    //   3734: invokestatic a : (II)Ljava/lang/String;
    //   3737: invokevirtual startsWith : (Ljava/lang/String;)Z
    //   3740: ifne -> 3750
    //   3743: goto -> 3750
    //   3746: invokestatic a : (Ljava/lang/Throwable;)Ljava/lang/Throwable;
    //   3749: athrow
    //   3750: aload #7
    //   3752: iconst_1
    //   3753: invokevirtual setAccessible : (Z)V
    //   3756: aload #7
    //   3758: aconst_null
    //   3759: invokevirtual get : (Ljava/lang/Object;)Ljava/lang/Object;
    //   3762: pop
    //   3763: iinc #6, 1
    //   3766: iload_2
    //   3767: ifne -> 3628
    //   3770: sipush #10995
    //   3773: sipush #-17703
    //   3776: invokestatic a : (II)Ljava/lang/String;
    //   3779: invokestatic forName : (Ljava/lang/String;)Ljava/lang/Class;
    //   3782: invokevirtual getDeclaredMethods : ()[Ljava/lang/reflect/Method;
    //   3785: astore #4
    //   3787: aload #4
    //   3789: arraylength
    //   3790: istore #5
    //   3792: iconst_0
    //   3793: istore #6
    //   3795: iload #6
    //   3797: iload #5
    //   3799: if_icmpge -> 3935
    //   3802: aload #4
    //   3804: iload #6
    //   3806: aaload
    //   3807: astore #7
    //   3809: aload #7
    //   3811: invokevirtual getParameterTypes : ()[Ljava/lang/Class;
    //   3814: pop
    //   3815: aload #7
    //   3817: invokevirtual getModifiers : ()I
    //   3820: invokestatic isStatic : (I)Z
    //   3823: ifeq -> 3921
    //   3826: aload #7
    //   3828: invokevirtual getParameterTypes : ()[Ljava/lang/Class;
    //   3831: arraylength
    //   3832: iconst_2
    //   3833: if_icmpne -> 3921
    //   3836: goto -> 3843
    //   3839: invokestatic a : (Ljava/lang/Throwable;)Ljava/lang/Throwable;
    //   3842: athrow
    //   3843: aload #7
    //   3845: invokevirtual getReturnType : ()Ljava/lang/Class;
    //   3848: getstatic java/lang/Boolean.TYPE : Ljava/lang/Class;
    //   3851: if_acmpne -> 3921
    //   3854: goto -> 3861
    //   3857: invokestatic a : (Ljava/lang/Throwable;)Ljava/lang/Throwable;
    //   3860: athrow
    //   3861: aload #7
    //   3863: iconst_1
    //   3864: invokevirtual setAccessible : (Z)V
    //   3867: aload #7
    //   3869: aconst_null
    //   3870: iconst_2
    //   3871: anewarray java/lang/Object
    //   3874: dup
    //   3875: iconst_0
    //   3876: aload_0
    //   3877: aastore
    //   3878: dup
    //   3879: iconst_1
    //   3880: aload_1
    //   3881: ifnonnull -> 3899
    //   3884: goto -> 3891
    //   3887: invokestatic a : (Ljava/lang/Throwable;)Ljava/lang/Throwable;
    //   3890: athrow
    //   3891: aload_1
    //   3892: goto -> 3906
    //   3895: invokestatic a : (Ljava/lang/Throwable;)Ljava/lang/Throwable;
    //   3898: athrow
    //   3899: aload_1
    //   3900: checkcast [B
    //   3903: invokevirtual clone : ()Ljava/lang/Object;
    //   3906: aastore
    //   3907: invokevirtual invoke : (Ljava/lang/Object;[Ljava/lang/Object;)Ljava/lang/Object;
    //   3910: checkcast java/lang/Boolean
    //   3913: invokevirtual booleanValue : ()Z
    //   3916: istore_3
    //   3917: iload_2
    //   3918: ifne -> 3935
    //   3921: iinc #6, 1
    //   3924: iload_2
    //   3925: ifne -> 3795
    //   3928: goto -> 3935
    //   3931: invokestatic a : (Ljava/lang/Throwable;)Ljava/lang/Throwable;
    //   3934: athrow
    //   3935: goto -> 4276
    //   3938: sipush #10984
    //   3941: sipush #11524
    //   3944: invokestatic a : (II)Ljava/lang/String;
    //   3947: iconst_1
    //   3948: ldc burp/Zrbp
    //   3950: invokevirtual getClassLoader : ()Ljava/lang/ClassLoader;
    //   3953: invokestatic forName : (Ljava/lang/String;ZLjava/lang/ClassLoader;)Ljava/lang/Class;
    //   3956: invokevirtual getDeclaredFields : ()[Ljava/lang/reflect/Field;
    //   3959: astore #4
    //   3961: aload #4
    //   3963: arraylength
    //   3964: istore #5
    //   3966: iconst_0
    //   3967: istore #6
    //   3969: iload #6
    //   3971: iload #5
    //   3973: if_icmpge -> 4111
    //   3976: aload #4
    //   3978: iload #6
    //   3980: aaload
    //   3981: astore #7
    //   3983: aload #7
    //   3985: invokevirtual getModifiers : ()I
    //   3988: invokestatic isStatic : (I)Z
    //   3991: ifne -> 4001
    //   3994: goto -> 4104
    //   3997: invokestatic a : (Ljava/lang/Throwable;)Ljava/lang/Throwable;
    //   4000: athrow
    //   4001: aload #7
    //   4003: invokevirtual getType : ()Ljava/lang/Class;
    //   4006: astore #8
    //   4008: aload #8
    //   4010: ifnull -> 4091
    //   4013: aload #8
    //   4015: invokevirtual isPrimitive : ()Z
    //   4018: ifne -> 4091
    //   4021: goto -> 4028
    //   4024: invokestatic a : (Ljava/lang/Throwable;)Ljava/lang/Throwable;
    //   4027: athrow
    //   4028: aload #8
    //   4030: invokevirtual getPackage : ()Ljava/lang/Package;
    //   4033: ifnull -> 4091
    //   4036: goto -> 4043
    //   4039: invokestatic a : (Ljava/lang/Throwable;)Ljava/lang/Throwable;
    //   4042: athrow
    //   4043: aload #8
    //   4045: invokevirtual getPackage : ()Ljava/lang/Package;
    //   4048: invokevirtual getName : ()Ljava/lang/String;
    //   4051: ifnull -> 4091
    //   4054: goto -> 4061
    //   4057: invokestatic a : (Ljava/lang/Throwable;)Ljava/lang/Throwable;
    //   4060: athrow
    //   4061: aload #8
    //   4063: invokevirtual getPackage : ()Ljava/lang/Package;
    //   4066: invokevirtual getName : ()Ljava/lang/String;
    //   4069: sipush #10980
    //   4072: sipush #-15275
    //   4075: invokestatic a : (II)Ljava/lang/String;
    //   4078: invokevirtual startsWith : (Ljava/lang/String;)Z
    //   4081: ifne -> 4091
    //   4084: goto -> 4091
    //   4087: invokestatic a : (Ljava/lang/Throwable;)Ljava/lang/Throwable;
    //   4090: athrow
    //   4091: aload #7
    //   4093: iconst_1
    //   4094: invokevirtual setAccessible : (Z)V
    //   4097: aload #7
    //   4099: aconst_null
    //   4100: invokevirtual get : (Ljava/lang/Object;)Ljava/lang/Object;
    //   4103: pop
    //   4104: iinc #6, 1
    //   4107: iload_2
    //   4108: ifne -> 3969
    //   4111: sipush #10987
    //   4114: sipush #4814
    //   4117: invokestatic a : (II)Ljava/lang/String;
    //   4120: invokestatic forName : (Ljava/lang/String;)Ljava/lang/Class;
    //   4123: invokevirtual getDeclaredMethods : ()[Ljava/lang/reflect/Method;
    //   4126: astore #4
    //   4128: aload #4
    //   4130: arraylength
    //   4131: istore #5
    //   4133: iconst_0
    //   4134: istore #6
    //   4136: iload #6
    //   4138: iload #5
    //   4140: if_icmpge -> 4276
    //   4143: aload #4
    //   4145: iload #6
    //   4147: aaload
    //   4148: astore #7
    //   4150: aload #7
    //   4152: invokevirtual getParameterTypes : ()[Ljava/lang/Class;
    //   4155: pop
    //   4156: aload #7
    //   4158: invokevirtual getModifiers : ()I
    //   4161: invokestatic isStatic : (I)Z
    //   4164: ifeq -> 4262
    //   4167: aload #7
    //   4169: invokevirtual getParameterTypes : ()[Ljava/lang/Class;
    //   4172: arraylength
    //   4173: iconst_2
    //   4174: if_icmpne -> 4262
    //   4177: goto -> 4184
    //   4180: invokestatic a : (Ljava/lang/Throwable;)Ljava/lang/Throwable;
    //   4183: athrow
    //   4184: aload #7
    //   4186: invokevirtual getReturnType : ()Ljava/lang/Class;
    //   4189: getstatic java/lang/Boolean.TYPE : Ljava/lang/Class;
    //   4192: if_acmpne -> 4262
    //   4195: goto -> 4202
    //   4198: invokestatic a : (Ljava/lang/Throwable;)Ljava/lang/Throwable;
    //   4201: athrow
    //   4202: aload #7
    //   4204: iconst_1
    //   4205: invokevirtual setAccessible : (Z)V
    //   4208: aload #7
    //   4210: aconst_null
    //   4211: iconst_2
    //   4212: anewarray java/lang/Object
    //   4215: dup
    //   4216: iconst_0
    //   4217: aload_0
    //   4218: aastore
    //   4219: dup
    //   4220: iconst_1
    //   4221: aload_1
    //   4222: ifnonnull -> 4240
    //   4225: goto -> 4232
    //   4228: invokestatic a : (Ljava/lang/Throwable;)Ljava/lang/Throwable;
    //   4231: athrow
    //   4232: aload_1
    //   4233: goto -> 4247
    //   4236: invokestatic a : (Ljava/lang/Throwable;)Ljava/lang/Throwable;
    //   4239: athrow
    //   4240: aload_1
    //   4241: checkcast [B
    //   4244: invokevirtual clone : ()Ljava/lang/Object;
    //   4247: aastore
    //   4248: invokevirtual invoke : (Ljava/lang/Object;[Ljava/lang/Object;)Ljava/lang/Object;
    //   4251: checkcast java/lang/Boolean
    //   4254: invokevirtual booleanValue : ()Z
    //   4257: istore_3
    //   4258: iload_2
    //   4259: ifne -> 4276
    //   4262: iinc #6, 1
    //   4265: iload_2
    //   4266: ifne -> 4136
    //   4269: goto -> 4276
    //   4272: invokestatic a : (Ljava/lang/Throwable;)Ljava/lang/Throwable;
    //   4275: athrow
    //   4276: iload_3
    //   4277: ifeq -> 4282
    //   4280: iload_3
    //   4281: ireturn
    //   4282: getstatic burp/Zxtc.Zo : Ljava/lang/String;
    //   4285: getstatic burp/Ztkc.ZV : Ljava/lang/Object;
    //   4288: checkcast java/math/BigInteger
    //   4291: invokevirtual intValue : ()I
    //   4294: bipush #32
    //   4296: irem
    //   4297: invokestatic abs : (I)I
    //   4300: invokevirtual charAt : (I)C
    //   4303: getstatic burp/Zlps.ZO : Ljava/lang/String;
    //   4306: getstatic burp/Zeqo.ZZ : Ljava/lang/Object;
    //   4309: checkcast java/math/BigInteger
    //   4312: invokevirtual intValue : ()I
    //   4315: bipush #32
    //   4317: irem
    //   4318: invokestatic abs : (I)I
    //   4321: invokevirtual charAt : (I)C
    //   4324: if_icmpgt -> 4669
    //   4327: sipush #10996
    //   4330: sipush #-31675
    //   4333: invokestatic a : (II)Ljava/lang/String;
    //   4336: iconst_1
    //   4337: ldc burp/Zkdc
    //   4339: invokevirtual getClassLoader : ()Ljava/lang/ClassLoader;
    //   4342: invokestatic forName : (Ljava/lang/String;ZLjava/lang/ClassLoader;)Ljava/lang/Class;
    //   4345: invokevirtual getDeclaredFields : ()[Ljava/lang/reflect/Field;
    //   4348: astore #4
    //   4350: aload #4
    //   4352: arraylength
    //   4353: istore #5
    //   4355: iconst_0
    //   4356: istore #6
    //   4358: iload #6
    //   4360: iload #5
    //   4362: if_icmpge -> 4500
    //   4365: aload #4
    //   4367: iload #6
    //   4369: aaload
    //   4370: astore #7
    //   4372: aload #7
    //   4374: invokevirtual getModifiers : ()I
    //   4377: invokestatic isStatic : (I)Z
    //   4380: ifne -> 4390
    //   4383: goto -> 4493
    //   4386: invokestatic a : (Ljava/lang/Throwable;)Ljava/lang/Throwable;
    //   4389: athrow
    //   4390: aload #7
    //   4392: invokevirtual getType : ()Ljava/lang/Class;
    //   4395: astore #8
    //   4397: aload #8
    //   4399: ifnull -> 4480
    //   4402: aload #8
    //   4404: invokevirtual isPrimitive : ()Z
    //   4407: ifne -> 4480
    //   4410: goto -> 4417
    //   4413: invokestatic a : (Ljava/lang/Throwable;)Ljava/lang/Throwable;
    //   4416: athrow
    //   4417: aload #8
    //   4419: invokevirtual getPackage : ()Ljava/lang/Package;
    //   4422: ifnull -> 4480
    //   4425: goto -> 4432
    //   4428: invokestatic a : (Ljava/lang/Throwable;)Ljava/lang/Throwable;
    //   4431: athrow
    //   4432: aload #8
    //   4434: invokevirtual getPackage : ()Ljava/lang/Package;
    //   4437: invokevirtual getName : ()Ljava/lang/String;
    //   4440: ifnull -> 4480
    //   4443: goto -> 4450
    //   4446: invokestatic a : (Ljava/lang/Throwable;)Ljava/lang/Throwable;
    //   4449: athrow
    //   4450: aload #8
    //   4452: invokevirtual getPackage : ()Ljava/lang/Package;
    //   4455: invokevirtual getName : ()Ljava/lang/String;
    //   4458: sipush #10980
    //   4461: sipush #-15275
    //   4464: invokestatic a : (II)Ljava/lang/String;
    //   4467: invokevirtual startsWith : (Ljava/lang/String;)Z
    //   4470: ifne -> 4480
    //   4473: goto -> 4480
    //   4476: invokestatic a : (Ljava/lang/Throwable;)Ljava/lang/Throwable;
    //   4479: athrow
    //   4480: aload #7
    //   4482: iconst_1
    //   4483: invokevirtual setAccessible : (Z)V
    //   4486: aload #7
    //   4488: aconst_null
    //   4489: invokevirtual get : (Ljava/lang/Object;)Ljava/lang/Object;
    //   4492: pop
    //   4493: iinc #6, 1
    //   4496: iload_2
    //   4497: ifne -> 4358
    //   4500: sipush #11004
    //   4503: sipush #-9972
    //   4506: invokestatic a : (II)Ljava/lang/String;
    //   4509: invokestatic forName : (Ljava/lang/String;)Ljava/lang/Class;
    //   4512: invokevirtual getDeclaredMethods : ()[Ljava/lang/reflect/Method;
    //   4515: astore #4
    //   4517: aload #4
    //   4519: arraylength
    //   4520: istore #5
    //   4522: iconst_0
    //   4523: istore #6
    //   4525: iload #6
    //   4527: iload #5
    //   4529: if_icmpge -> 4665
    //   4532: aload #4
    //   4534: iload #6
    //   4536: aaload
    //   4537: astore #7
    //   4539: aload #7
    //   4541: invokevirtual getParameterTypes : ()[Ljava/lang/Class;
    //   4544: pop
    //   4545: aload #7
    //   4547: invokevirtual getModifiers : ()I
    //   4550: invokestatic isStatic : (I)Z
    //   4553: ifeq -> 4651
    //   4556: aload #7
    //   4558: invokevirtual getParameterTypes : ()[Ljava/lang/Class;
    //   4561: arraylength
    //   4562: iconst_2
    //   4563: if_icmpne -> 4651
    //   4566: goto -> 4573
    //   4569: invokestatic a : (Ljava/lang/Throwable;)Ljava/lang/Throwable;
    //   4572: athrow
    //   4573: aload #7
    //   4575: invokevirtual getReturnType : ()Ljava/lang/Class;
    //   4578: getstatic java/lang/Boolean.TYPE : Ljava/lang/Class;
    //   4581: if_acmpne -> 4651
    //   4584: goto -> 4591
    //   4587: invokestatic a : (Ljava/lang/Throwable;)Ljava/lang/Throwable;
    //   4590: athrow
    //   4591: aload #7
    //   4593: iconst_1
    //   4594: invokevirtual setAccessible : (Z)V
    //   4597: aload #7
    //   4599: aconst_null
    //   4600: iconst_2
    //   4601: anewarray java/lang/Object
    //   4604: dup
    //   4605: iconst_0
    //   4606: aload_0
    //   4607: aastore
    //   4608: dup
    //   4609: iconst_1
    //   4610: aload_1
    //   4611: ifnonnull -> 4629
    //   4614: goto -> 4621
    //   4617: invokestatic a : (Ljava/lang/Throwable;)Ljava/lang/Throwable;
    //   4620: athrow
    //   4621: aload_1
    //   4622: goto -> 4636
    //   4625: invokestatic a : (Ljava/lang/Throwable;)Ljava/lang/Throwable;
    //   4628: athrow
    //   4629: aload_1
    //   4630: checkcast [B
    //   4633: invokevirtual clone : ()Ljava/lang/Object;
    //   4636: aastore
    //   4637: invokevirtual invoke : (Ljava/lang/Object;[Ljava/lang/Object;)Ljava/lang/Object;
    //   4640: checkcast java/lang/Boolean
    //   4643: invokevirtual booleanValue : ()Z
    //   4646: istore_3
    //   4647: iload_2
    //   4648: ifne -> 4665
    //   4651: iinc #6, 1
    //   4654: iload_2
    //   4655: ifne -> 4525
    //   4658: goto -> 4665
    //   4661: invokestatic a : (Ljava/lang/Throwable;)Ljava/lang/Throwable;
    //   4664: athrow
    //   4665: iload_2
    //   4666: ifne -> 5007
    //   4669: sipush #11007
    //   4672: sipush #-17389
    //   4675: invokestatic a : (II)Ljava/lang/String;
    //   4678: iconst_1
    //   4679: ldc burp/Zeoi
    //   4681: invokevirtual getClassLoader : ()Ljava/lang/ClassLoader;
    //   4684: invokestatic forName : (Ljava/lang/String;ZLjava/lang/ClassLoader;)Ljava/lang/Class;
    //   4687: invokevirtual getDeclaredFields : ()[Ljava/lang/reflect/Field;
    //   4690: astore #4
    //   4692: aload #4
    //   4694: arraylength
    //   4695: istore #5
    //   4697: iconst_0
    //   4698: istore #6
    //   4700: iload #6
    //   4702: iload #5
    //   4704: if_icmpge -> 4842
    //   4707: aload #4
    //   4709: iload #6
    //   4711: aaload
    //   4712: astore #7
    //   4714: aload #7
    //   4716: invokevirtual getModifiers : ()I
    //   4719: invokestatic isStatic : (I)Z
    //   4722: ifne -> 4732
    //   4725: goto -> 4835
    //   4728: invokestatic a : (Ljava/lang/Throwable;)Ljava/lang/Throwable;
    //   4731: athrow
    //   4732: aload #7
    //   4734: invokevirtual getType : ()Ljava/lang/Class;
    //   4737: astore #8
    //   4739: aload #8
    //   4741: ifnull -> 4822
    //   4744: aload #8
    //   4746: invokevirtual isPrimitive : ()Z
    //   4749: ifne -> 4822
    //   4752: goto -> 4759
    //   4755: invokestatic a : (Ljava/lang/Throwable;)Ljava/lang/Throwable;
    //   4758: athrow
    //   4759: aload #8
    //   4761: invokevirtual getPackage : ()Ljava/lang/Package;
    //   4764: ifnull -> 4822
    //   4767: goto -> 4774
    //   4770: invokestatic a : (Ljava/lang/Throwable;)Ljava/lang/Throwable;
    //   4773: athrow
    //   4774: aload #8
    //   4776: invokevirtual getPackage : ()Ljava/lang/Package;
    //   4779: invokevirtual getName : ()Ljava/lang/String;
    //   4782: ifnull -> 4822
    //   4785: goto -> 4792
    //   4788: invokestatic a : (Ljava/lang/Throwable;)Ljava/lang/Throwable;
    //   4791: athrow
    //   4792: aload #8
    //   4794: invokevirtual getPackage : ()Ljava/lang/Package;
    //   4797: invokevirtual getName : ()Ljava/lang/String;
    //   4800: sipush #10980
    //   4803: sipush #-15275
    //   4806: invokestatic a : (II)Ljava/lang/String;
    //   4809: invokevirtual startsWith : (Ljava/lang/String;)Z
    //   4812: ifne -> 4822
    //   4815: goto -> 4822
    //   4818: invokestatic a : (Ljava/lang/Throwable;)Ljava/lang/Throwable;
    //   4821: athrow
    //   4822: aload #7
    //   4824: iconst_1
    //   4825: invokevirtual setAccessible : (Z)V
    //   4828: aload #7
    //   4830: aconst_null
    //   4831: invokevirtual get : (Ljava/lang/Object;)Ljava/lang/Object;
    //   4834: pop
    //   4835: iinc #6, 1
    //   4838: iload_2
    //   4839: ifne -> 4700
    //   4842: sipush #10998
    //   4845: sipush #15754
    //   4848: invokestatic a : (II)Ljava/lang/String;
    //   4851: invokestatic forName : (Ljava/lang/String;)Ljava/lang/Class;
    //   4854: invokevirtual getDeclaredMethods : ()[Ljava/lang/reflect/Method;
    //   4857: astore #4
    //   4859: aload #4
    //   4861: arraylength
    //   4862: istore #5
    //   4864: iconst_0
    //   4865: istore #6
    //   4867: iload #6
    //   4869: iload #5
    //   4871: if_icmpge -> 5007
    //   4874: aload #4
    //   4876: iload #6
    //   4878: aaload
    //   4879: astore #7
    //   4881: aload #7
    //   4883: invokevirtual getParameterTypes : ()[Ljava/lang/Class;
    //   4886: pop
    //   4887: aload #7
    //   4889: invokevirtual getModifiers : ()I
    //   4892: invokestatic isStatic : (I)Z
    //   4895: ifeq -> 4993
    //   4898: aload #7
    //   4900: invokevirtual getParameterTypes : ()[Ljava/lang/Class;
    //   4903: arraylength
    //   4904: iconst_2
    //   4905: if_icmpne -> 4993
    //   4908: goto -> 4915
    //   4911: invokestatic a : (Ljava/lang/Throwable;)Ljava/lang/Throwable;
    //   4914: athrow
    //   4915: aload #7
    //   4917: invokevirtual getReturnType : ()Ljava/lang/Class;
    //   4920: getstatic java/lang/Boolean.TYPE : Ljava/lang/Class;
    //   4923: if_acmpne -> 4993
    //   4926: goto -> 4933
    //   4929: invokestatic a : (Ljava/lang/Throwable;)Ljava/lang/Throwable;
    //   4932: athrow
    //   4933: aload #7
    //   4935: iconst_1
    //   4936: invokevirtual setAccessible : (Z)V
    //   4939: aload #7
    //   4941: aconst_null
    //   4942: iconst_2
    //   4943: anewarray java/lang/Object
    //   4946: dup
    //   4947: iconst_0
    //   4948: aload_0
    //   4949: aastore
    //   4950: dup
    //   4951: iconst_1
    //   4952: aload_1
    //   4953: ifnonnull -> 4971
    //   4956: goto -> 4963
    //   4959: invokestatic a : (Ljava/lang/Throwable;)Ljava/lang/Throwable;
    //   4962: athrow
    //   4963: aload_1
    //   4964: goto -> 4978
    //   4967: invokestatic a : (Ljava/lang/Throwable;)Ljava/lang/Throwable;
    //   4970: athrow
    //   4971: aload_1
    //   4972: checkcast [B
    //   4975: invokevirtual clone : ()Ljava/lang/Object;
    //   4978: aastore
    //   4979: invokevirtual invoke : (Ljava/lang/Object;[Ljava/lang/Object;)Ljava/lang/Object;
    //   4982: checkcast java/lang/Boolean
    //   4985: invokevirtual booleanValue : ()Z
    //   4988: istore_3
    //   4989: iload_2
    //   4990: ifne -> 5007
    //   4993: iinc #6, 1
    //   4996: iload_2
    //   4997: ifne -> 4867
    //   5000: goto -> 5007
    //   5003: invokestatic a : (Ljava/lang/Throwable;)Ljava/lang/Throwable;
    //   5006: athrow
    //   5007: iload_3
    //   5008: ifeq -> 5013
    //   5011: iload_3
    //   5012: ireturn
    //   5013: getstatic burp/Zgt7.ZO : Ljava/lang/String;
    //   5016: getstatic burp/Zrf9.Zu : Ljava/lang/Object;
    //   5019: checkcast java/math/BigInteger
    //   5022: invokevirtual intValue : ()I
    //   5025: bipush #32
    //   5027: irem
    //   5028: invokestatic abs : (I)I
    //   5031: invokevirtual charAt : (I)C
    //   5034: getstatic burp/Zx_x.Zv : Ljava/lang/String;
    //   5037: getstatic burp/Zgta.ZF : Ljava/lang/Object;
    //   5040: checkcast java/math/BigInteger
    //   5043: invokevirtual intValue : ()I
    //   5046: bipush #32
    //   5048: irem
    //   5049: invokestatic abs : (I)I
    //   5052: invokevirtual charAt : (I)C
    //   5055: if_icmpgt -> 5400
    //   5058: sipush #10977
    //   5061: sipush #-20058
    //   5064: invokestatic a : (II)Ljava/lang/String;
    //   5067: iconst_1
    //   5068: ldc burp/Zepm
    //   5070: invokevirtual getClassLoader : ()Ljava/lang/ClassLoader;
    //   5073: invokestatic forName : (Ljava/lang/String;ZLjava/lang/ClassLoader;)Ljava/lang/Class;
    //   5076: invokevirtual getDeclaredFields : ()[Ljava/lang/reflect/Field;
    //   5079: astore #4
    //   5081: aload #4
    //   5083: arraylength
    //   5084: istore #5
    //   5086: iconst_0
    //   5087: istore #6
    //   5089: iload #6
    //   5091: iload #5
    //   5093: if_icmpge -> 5231
    //   5096: aload #4
    //   5098: iload #6
    //   5100: aaload
    //   5101: astore #7
    //   5103: aload #7
    //   5105: invokevirtual getModifiers : ()I
    //   5108: invokestatic isStatic : (I)Z
    //   5111: ifne -> 5121
    //   5114: goto -> 5224
    //   5117: invokestatic a : (Ljava/lang/Throwable;)Ljava/lang/Throwable;
    //   5120: athrow
    //   5121: aload #7
    //   5123: invokevirtual getType : ()Ljava/lang/Class;
    //   5126: astore #8
    //   5128: aload #8
    //   5130: ifnull -> 5211
    //   5133: aload #8
    //   5135: invokevirtual isPrimitive : ()Z
    //   5138: ifne -> 5211
    //   5141: goto -> 5148
    //   5144: invokestatic a : (Ljava/lang/Throwable;)Ljava/lang/Throwable;
    //   5147: athrow
    //   5148: aload #8
    //   5150: invokevirtual getPackage : ()Ljava/lang/Package;
    //   5153: ifnull -> 5211
    //   5156: goto -> 5163
    //   5159: invokestatic a : (Ljava/lang/Throwable;)Ljava/lang/Throwable;
    //   5162: athrow
    //   5163: aload #8
    //   5165: invokevirtual getPackage : ()Ljava/lang/Package;
    //   5168: invokevirtual getName : ()Ljava/lang/String;
    //   5171: ifnull -> 5211
    //   5174: goto -> 5181
    //   5177: invokestatic a : (Ljava/lang/Throwable;)Ljava/lang/Throwable;
    //   5180: athrow
    //   5181: aload #8
    //   5183: invokevirtual getPackage : ()Ljava/lang/Package;
    //   5186: invokevirtual getName : ()Ljava/lang/String;
    //   5189: sipush #10980
    //   5192: sipush #-15275
    //   5195: invokestatic a : (II)Ljava/lang/String;
    //   5198: invokevirtual startsWith : (Ljava/lang/String;)Z
    //   5201: ifne -> 5211
    //   5204: goto -> 5211
    //   5207: invokestatic a : (Ljava/lang/Throwable;)Ljava/lang/Throwable;
    //   5210: athrow
    //   5211: aload #7
    //   5213: iconst_1
    //   5214: invokevirtual setAccessible : (Z)V
    //   5217: aload #7
    //   5219: aconst_null
    //   5220: invokevirtual get : (Ljava/lang/Object;)Ljava/lang/Object;
    //   5223: pop
    //   5224: iinc #6, 1
    //   5227: iload_2
    //   5228: ifne -> 5089
    //   5231: sipush #10994
    //   5234: sipush #-2692
    //   5237: invokestatic a : (II)Ljava/lang/String;
    //   5240: invokestatic forName : (Ljava/lang/String;)Ljava/lang/Class;
    //   5243: invokevirtual getDeclaredMethods : ()[Ljava/lang/reflect/Method;
    //   5246: astore #4
    //   5248: aload #4
    //   5250: arraylength
    //   5251: istore #5
    //   5253: iconst_0
    //   5254: istore #6
    //   5256: iload #6
    //   5258: iload #5
    //   5260: if_icmpge -> 5396
    //   5263: aload #4
    //   5265: iload #6
    //   5267: aaload
    //   5268: astore #7
    //   5270: aload #7
    //   5272: invokevirtual getParameterTypes : ()[Ljava/lang/Class;
    //   5275: pop
    //   5276: aload #7
    //   5278: invokevirtual getModifiers : ()I
    //   5281: invokestatic isStatic : (I)Z
    //   5284: ifeq -> 5382
    //   5287: aload #7
    //   5289: invokevirtual getParameterTypes : ()[Ljava/lang/Class;
    //   5292: arraylength
    //   5293: iconst_2
    //   5294: if_icmpne -> 5382
    //   5297: goto -> 5304
    //   5300: invokestatic a : (Ljava/lang/Throwable;)Ljava/lang/Throwable;
    //   5303: athrow
    //   5304: aload #7
    //   5306: invokevirtual getReturnType : ()Ljava/lang/Class;
    //   5309: getstatic java/lang/Boolean.TYPE : Ljava/lang/Class;
    //   5312: if_acmpne -> 5382
    //   5315: goto -> 5322
    //   5318: invokestatic a : (Ljava/lang/Throwable;)Ljava/lang/Throwable;
    //   5321: athrow
    //   5322: aload #7
    //   5324: iconst_1
    //   5325: invokevirtual setAccessible : (Z)V
    //   5328: aload #7
    //   5330: aconst_null
    //   5331: iconst_2
    //   5332: anewarray java/lang/Object
    //   5335: dup
    //   5336: iconst_0
    //   5337: aload_0
    //   5338: aastore
    //   5339: dup
    //   5340: iconst_1
    //   5341: aload_1
    //   5342: ifnonnull -> 5360
    //   5345: goto -> 5352
    //   5348: invokestatic a : (Ljava/lang/Throwable;)Ljava/lang/Throwable;
    //   5351: athrow
    //   5352: aload_1
    //   5353: goto -> 5367
    //   5356: invokestatic a : (Ljava/lang/Throwable;)Ljava/lang/Throwable;
    //   5359: athrow
    //   5360: aload_1
    //   5361: checkcast [B
    //   5364: invokevirtual clone : ()Ljava/lang/Object;
    //   5367: aastore
    //   5368: invokevirtual invoke : (Ljava/lang/Object;[Ljava/lang/Object;)Ljava/lang/Object;
    //   5371: checkcast java/lang/Boolean
    //   5374: invokevirtual booleanValue : ()Z
    //   5377: istore_3
    //   5378: iload_2
    //   5379: ifne -> 5396
    //   5382: iinc #6, 1
    //   5385: iload_2
    //   5386: ifne -> 5256
    //   5389: goto -> 5396
    //   5392: invokestatic a : (Ljava/lang/Throwable;)Ljava/lang/Throwable;
    //   5395: athrow
    //   5396: iload_2
    //   5397: ifne -> 5738
    //   5400: sipush #10999
    //   5403: sipush #24181
    //   5406: invokestatic a : (II)Ljava/lang/String;
    //   5409: iconst_1
    //   5410: ldc burp/Zltp
    //   5412: invokevirtual getClassLoader : ()Ljava/lang/ClassLoader;
    //   5415: invokestatic forName : (Ljava/lang/String;ZLjava/lang/ClassLoader;)Ljava/lang/Class;
    //   5418: invokevirtual getDeclaredFields : ()[Ljava/lang/reflect/Field;
    //   5421: astore #4
    //   5423: aload #4
    //   5425: arraylength
    //   5426: istore #5
    //   5428: iconst_0
    //   5429: istore #6
    //   5431: iload #6
    //   5433: iload #5
    //   5435: if_icmpge -> 5573
    //   5438: aload #4
    //   5440: iload #6
    //   5442: aaload
    //   5443: astore #7
    //   5445: aload #7
    //   5447: invokevirtual getModifiers : ()I
    //   5450: invokestatic isStatic : (I)Z
    //   5453: ifne -> 5463
    //   5456: goto -> 5566
    //   5459: invokestatic a : (Ljava/lang/Throwable;)Ljava/lang/Throwable;
    //   5462: athrow
    //   5463: aload #7
    //   5465: invokevirtual getType : ()Ljava/lang/Class;
    //   5468: astore #8
    //   5470: aload #8
    //   5472: ifnull -> 5553
    //   5475: aload #8
    //   5477: invokevirtual isPrimitive : ()Z
    //   5480: ifne -> 5553
    //   5483: goto -> 5490
    //   5486: invokestatic a : (Ljava/lang/Throwable;)Ljava/lang/Throwable;
    //   5489: athrow
    //   5490: aload #8
    //   5492: invokevirtual getPackage : ()Ljava/lang/Package;
    //   5495: ifnull -> 5553
    //   5498: goto -> 5505
    //   5501: invokestatic a : (Ljava/lang/Throwable;)Ljava/lang/Throwable;
    //   5504: athrow
    //   5505: aload #8
    //   5507: invokevirtual getPackage : ()Ljava/lang/Package;
    //   5510: invokevirtual getName : ()Ljava/lang/String;
    //   5513: ifnull -> 5553
    //   5516: goto -> 5523
    //   5519: invokestatic a : (Ljava/lang/Throwable;)Ljava/lang/Throwable;
    //   5522: athrow
    //   5523: aload #8
    //   5525: invokevirtual getPackage : ()Ljava/lang/Package;
    //   5528: invokevirtual getName : ()Ljava/lang/String;
    //   5531: sipush #10980
    //   5534: sipush #-15275
    //   5537: invokestatic a : (II)Ljava/lang/String;
    //   5540: invokevirtual startsWith : (Ljava/lang/String;)Z
    //   5543: ifne -> 5553
    //   5546: goto -> 5553
    //   5549: invokestatic a : (Ljava/lang/Throwable;)Ljava/lang/Throwable;
    //   5552: athrow
    //   5553: aload #7
    //   5555: iconst_1
    //   5556: invokevirtual setAccessible : (Z)V
    //   5559: aload #7
    //   5561: aconst_null
    //   5562: invokevirtual get : (Ljava/lang/Object;)Ljava/lang/Object;
    //   5565: pop
    //   5566: iinc #6, 1
    //   5569: iload_2
    //   5570: ifne -> 5431
    //   5573: sipush #11000
    //   5576: sipush #-19690
    //   5579: invokestatic a : (II)Ljava/lang/String;
    //   5582: invokestatic forName : (Ljava/lang/String;)Ljava/lang/Class;
    //   5585: invokevirtual getDeclaredMethods : ()[Ljava/lang/reflect/Method;
    //   5588: astore #4
    //   5590: aload #4
    //   5592: arraylength
    //   5593: istore #5
    //   5595: iconst_0
    //   5596: istore #6
    //   5598: iload #6
    //   5600: iload #5
    //   5602: if_icmpge -> 5738
    //   5605: aload #4
    //   5607: iload #6
    //   5609: aaload
    //   5610: astore #7
    //   5612: aload #7
    //   5614: invokevirtual getParameterTypes : ()[Ljava/lang/Class;
    //   5617: pop
    //   5618: aload #7
    //   5620: invokevirtual getModifiers : ()I
    //   5623: invokestatic isStatic : (I)Z
    //   5626: ifeq -> 5724
    //   5629: aload #7
    //   5631: invokevirtual getParameterTypes : ()[Ljava/lang/Class;
    //   5634: arraylength
    //   5635: iconst_2
    //   5636: if_icmpne -> 5724
    //   5639: goto -> 5646
    //   5642: invokestatic a : (Ljava/lang/Throwable;)Ljava/lang/Throwable;
    //   5645: athrow
    //   5646: aload #7
    //   5648: invokevirtual getReturnType : ()Ljava/lang/Class;
    //   5651: getstatic java/lang/Boolean.TYPE : Ljava/lang/Class;
    //   5654: if_acmpne -> 5724
    //   5657: goto -> 5664
    //   5660: invokestatic a : (Ljava/lang/Throwable;)Ljava/lang/Throwable;
    //   5663: athrow
    //   5664: aload #7
    //   5666: iconst_1
    //   5667: invokevirtual setAccessible : (Z)V
    //   5670: aload #7
    //   5672: aconst_null
    //   5673: iconst_2
    //   5674: anewarray java/lang/Object
    //   5677: dup
    //   5678: iconst_0
    //   5679: aload_0
    //   5680: aastore
    //   5681: dup
    //   5682: iconst_1
    //   5683: aload_1
    //   5684: ifnonnull -> 5702
    //   5687: goto -> 5694
    //   5690: invokestatic a : (Ljava/lang/Throwable;)Ljava/lang/Throwable;
    //   5693: athrow
    //   5694: aload_1
    //   5695: goto -> 5709
    //   5698: invokestatic a : (Ljava/lang/Throwable;)Ljava/lang/Throwable;
    //   5701: athrow
    //   5702: aload_1
    //   5703: checkcast [B
    //   5706: invokevirtual clone : ()Ljava/lang/Object;
    //   5709: aastore
    //   5710: invokevirtual invoke : (Ljava/lang/Object;[Ljava/lang/Object;)Ljava/lang/Object;
    //   5713: checkcast java/lang/Boolean
    //   5716: invokevirtual booleanValue : ()Z
    //   5719: istore_3
    //   5720: iload_2
    //   5721: ifne -> 5738
    //   5724: iinc #6, 1
    //   5727: iload_2
    //   5728: ifne -> 5598
    //   5731: goto -> 5738
    //   5734: invokestatic a : (Ljava/lang/Throwable;)Ljava/lang/Throwable;
    //   5737: athrow
    //   5738: iload_3
    //   5739: ifeq -> 5744
    //   5742: iload_3
    //   5743: ireturn
    //   5744: getstatic burp/Zz35.ZH : Ljava/lang/String;
    //   5747: getstatic burp/Zlr2.Zq : Ljava/lang/Object;
    //   5750: checkcast java/math/BigInteger
    //   5753: invokevirtual intValue : ()I
    //   5756: bipush #32
    //   5758: irem
    //   5759: invokestatic abs : (I)I
    //   5762: invokevirtual charAt : (I)C
    //   5765: getstatic burp/Zlpn.ZF : Ljava/lang/String;
    //   5768: getstatic burp/Zmtf.ZH : Ljava/lang/Object;
    //   5771: checkcast java/math/BigInteger
    //   5774: invokevirtual intValue : ()I
    //   5777: bipush #32
    //   5779: irem
    //   5780: invokestatic abs : (I)I
    //   5783: invokevirtual charAt : (I)C
    //   5786: if_icmple -> 6131
    //   5789: sipush #10978
    //   5792: sipush #6669
    //   5795: invokestatic a : (II)Ljava/lang/String;
    //   5798: iconst_1
    //   5799: ldc burp/Ztuj
    //   5801: invokevirtual getClassLoader : ()Ljava/lang/ClassLoader;
    //   5804: invokestatic forName : (Ljava/lang/String;ZLjava/lang/ClassLoader;)Ljava/lang/Class;
    //   5807: invokevirtual getDeclaredFields : ()[Ljava/lang/reflect/Field;
    //   5810: astore #4
    //   5812: aload #4
    //   5814: arraylength
    //   5815: istore #5
    //   5817: iconst_0
    //   5818: istore #6
    //   5820: iload #6
    //   5822: iload #5
    //   5824: if_icmpge -> 5962
    //   5827: aload #4
    //   5829: iload #6
    //   5831: aaload
    //   5832: astore #7
    //   5834: aload #7
    //   5836: invokevirtual getModifiers : ()I
    //   5839: invokestatic isStatic : (I)Z
    //   5842: ifne -> 5852
    //   5845: goto -> 5955
    //   5848: invokestatic a : (Ljava/lang/Throwable;)Ljava/lang/Throwable;
    //   5851: athrow
    //   5852: aload #7
    //   5854: invokevirtual getType : ()Ljava/lang/Class;
    //   5857: astore #8
    //   5859: aload #8
    //   5861: ifnull -> 5942
    //   5864: aload #8
    //   5866: invokevirtual isPrimitive : ()Z
    //   5869: ifne -> 5942
    //   5872: goto -> 5879
    //   5875: invokestatic a : (Ljava/lang/Throwable;)Ljava/lang/Throwable;
    //   5878: athrow
    //   5879: aload #8
    //   5881: invokevirtual getPackage : ()Ljava/lang/Package;
    //   5884: ifnull -> 5942
    //   5887: goto -> 5894
    //   5890: invokestatic a : (Ljava/lang/Throwable;)Ljava/lang/Throwable;
    //   5893: athrow
    //   5894: aload #8
    //   5896: invokevirtual getPackage : ()Ljava/lang/Package;
    //   5899: invokevirtual getName : ()Ljava/lang/String;
    //   5902: ifnull -> 5942
    //   5905: goto -> 5912
    //   5908: invokestatic a : (Ljava/lang/Throwable;)Ljava/lang/Throwable;
    //   5911: athrow
    //   5912: aload #8
    //   5914: invokevirtual getPackage : ()Ljava/lang/Package;
    //   5917: invokevirtual getName : ()Ljava/lang/String;
    //   5920: sipush #10980
    //   5923: sipush #-15275
    //   5926: invokestatic a : (II)Ljava/lang/String;
    //   5929: invokevirtual startsWith : (Ljava/lang/String;)Z
    //   5932: ifne -> 5942
    //   5935: goto -> 5942
    //   5938: invokestatic a : (Ljava/lang/Throwable;)Ljava/lang/Throwable;
    //   5941: athrow
    //   5942: aload #7
    //   5944: iconst_1
    //   5945: invokevirtual setAccessible : (Z)V
    //   5948: aload #7
    //   5950: aconst_null
    //   5951: invokevirtual get : (Ljava/lang/Object;)Ljava/lang/Object;
    //   5954: pop
    //   5955: iinc #6, 1
    //   5958: iload_2
    //   5959: ifne -> 5820
    //   5962: sipush #10991
    //   5965: sipush #31440
    //   5968: invokestatic a : (II)Ljava/lang/String;
    //   5971: invokestatic forName : (Ljava/lang/String;)Ljava/lang/Class;
    //   5974: invokevirtual getDeclaredMethods : ()[Ljava/lang/reflect/Method;
    //   5977: astore #4
    //   5979: aload #4
    //   5981: arraylength
    //   5982: istore #5
    //   5984: iconst_0
    //   5985: istore #6
    //   5987: iload #6
    //   5989: iload #5
    //   5991: if_icmpge -> 6127
    //   5994: aload #4
    //   5996: iload #6
    //   5998: aaload
    //   5999: astore #7
    //   6001: aload #7
    //   6003: invokevirtual getParameterTypes : ()[Ljava/lang/Class;
    //   6006: pop
    //   6007: aload #7
    //   6009: invokevirtual getModifiers : ()I
    //   6012: invokestatic isStatic : (I)Z
    //   6015: ifeq -> 6113
    //   6018: aload #7
    //   6020: invokevirtual getParameterTypes : ()[Ljava/lang/Class;
    //   6023: arraylength
    //   6024: iconst_2
    //   6025: if_icmpne -> 6113
    //   6028: goto -> 6035
    //   6031: invokestatic a : (Ljava/lang/Throwable;)Ljava/lang/Throwable;
    //   6034: athrow
    //   6035: aload #7
    //   6037: invokevirtual getReturnType : ()Ljava/lang/Class;
    //   6040: getstatic java/lang/Boolean.TYPE : Ljava/lang/Class;
    //   6043: if_acmpne -> 6113
    //   6046: goto -> 6053
    //   6049: invokestatic a : (Ljava/lang/Throwable;)Ljava/lang/Throwable;
    //   6052: athrow
    //   6053: aload #7
    //   6055: iconst_1
    //   6056: invokevirtual setAccessible : (Z)V
    //   6059: aload #7
    //   6061: aconst_null
    //   6062: iconst_2
    //   6063: anewarray java/lang/Object
    //   6066: dup
    //   6067: iconst_0
    //   6068: aload_0
    //   6069: aastore
    //   6070: dup
    //   6071: iconst_1
    //   6072: aload_1
    //   6073: ifnonnull -> 6091
    //   6076: goto -> 6083
    //   6079: invokestatic a : (Ljava/lang/Throwable;)Ljava/lang/Throwable;
    //   6082: athrow
    //   6083: aload_1
    //   6084: goto -> 6098
    //   6087: invokestatic a : (Ljava/lang/Throwable;)Ljava/lang/Throwable;
    //   6090: athrow
    //   6091: aload_1
    //   6092: checkcast [B
    //   6095: invokevirtual clone : ()Ljava/lang/Object;
    //   6098: aastore
    //   6099: invokevirtual invoke : (Ljava/lang/Object;[Ljava/lang/Object;)Ljava/lang/Object;
    //   6102: checkcast java/lang/Boolean
    //   6105: invokevirtual booleanValue : ()Z
    //   6108: istore_3
    //   6109: iload_2
    //   6110: ifne -> 6127
    //   6113: iinc #6, 1
    //   6116: iload_2
    //   6117: ifne -> 5987
    //   6120: goto -> 6127
    //   6123: invokestatic a : (Ljava/lang/Throwable;)Ljava/lang/Throwable;
    //   6126: athrow
    //   6127: iload_2
    //   6128: ifne -> 6469
    //   6131: sipush #10985
    //   6134: sipush #-6819
    //   6137: invokestatic a : (II)Ljava/lang/String;
    //   6140: iconst_1
    //   6141: ldc burp/Zejg
    //   6143: invokevirtual getClassLoader : ()Ljava/lang/ClassLoader;
    //   6146: invokestatic forName : (Ljava/lang/String;ZLjava/lang/ClassLoader;)Ljava/lang/Class;
    //   6149: invokevirtual getDeclaredFields : ()[Ljava/lang/reflect/Field;
    //   6152: astore #4
    //   6154: aload #4
    //   6156: arraylength
    //   6157: istore #5
    //   6159: iconst_0
    //   6160: istore #6
    //   6162: iload #6
    //   6164: iload #5
    //   6166: if_icmpge -> 6304
    //   6169: aload #4
    //   6171: iload #6
    //   6173: aaload
    //   6174: astore #7
    //   6176: aload #7
    //   6178: invokevirtual getModifiers : ()I
    //   6181: invokestatic isStatic : (I)Z
    //   6184: ifne -> 6194
    //   6187: goto -> 6297
    //   6190: invokestatic a : (Ljava/lang/Throwable;)Ljava/lang/Throwable;
    //   6193: athrow
    //   6194: aload #7
    //   6196: invokevirtual getType : ()Ljava/lang/Class;
    //   6199: astore #8
    //   6201: aload #8
    //   6203: ifnull -> 6284
    //   6206: aload #8
    //   6208: invokevirtual isPrimitive : ()Z
    //   6211: ifne -> 6284
    //   6214: goto -> 6221
    //   6217: invokestatic a : (Ljava/lang/Throwable;)Ljava/lang/Throwable;
    //   6220: athrow
    //   6221: aload #8
    //   6223: invokevirtual getPackage : ()Ljava/lang/Package;
    //   6226: ifnull -> 6284
    //   6229: goto -> 6236
    //   6232: invokestatic a : (Ljava/lang/Throwable;)Ljava/lang/Throwable;
    //   6235: athrow
    //   6236: aload #8
    //   6238: invokevirtual getPackage : ()Ljava/lang/Package;
    //   6241: invokevirtual getName : ()Ljava/lang/String;
    //   6244: ifnull -> 6284
    //   6247: goto -> 6254
    //   6250: invokestatic a : (Ljava/lang/Throwable;)Ljava/lang/Throwable;
    //   6253: athrow
    //   6254: aload #8
    //   6256: invokevirtual getPackage : ()Ljava/lang/Package;
    //   6259: invokevirtual getName : ()Ljava/lang/String;
    //   6262: sipush #10980
    //   6265: sipush #-15275
    //   6268: invokestatic a : (II)Ljava/lang/String;
    //   6271: invokevirtual startsWith : (Ljava/lang/String;)Z
    //   6274: ifne -> 6284
    //   6277: goto -> 6284
    //   6280: invokestatic a : (Ljava/lang/Throwable;)Ljava/lang/Throwable;
    //   6283: athrow
    //   6284: aload #7
    //   6286: iconst_1
    //   6287: invokevirtual setAccessible : (Z)V
    //   6290: aload #7
    //   6292: aconst_null
    //   6293: invokevirtual get : (Ljava/lang/Object;)Ljava/lang/Object;
    //   6296: pop
    //   6297: iinc #6, 1
    //   6300: iload_2
    //   6301: ifne -> 6162
    //   6304: sipush #10986
    //   6307: sipush #-12396
    //   6310: invokestatic a : (II)Ljava/lang/String;
    //   6313: invokestatic forName : (Ljava/lang/String;)Ljava/lang/Class;
    //   6316: invokevirtual getDeclaredMethods : ()[Ljava/lang/reflect/Method;
    //   6319: astore #4
    //   6321: aload #4
    //   6323: arraylength
    //   6324: istore #5
    //   6326: iconst_0
    //   6327: istore #6
    //   6329: iload #6
    //   6331: iload #5
    //   6333: if_icmpge -> 6469
    //   6336: aload #4
    //   6338: iload #6
    //   6340: aaload
    //   6341: astore #7
    //   6343: aload #7
    //   6345: invokevirtual getParameterTypes : ()[Ljava/lang/Class;
    //   6348: pop
    //   6349: aload #7
    //   6351: invokevirtual getModifiers : ()I
    //   6354: invokestatic isStatic : (I)Z
    //   6357: ifeq -> 6455
    //   6360: aload #7
    //   6362: invokevirtual getParameterTypes : ()[Ljava/lang/Class;
    //   6365: arraylength
    //   6366: iconst_2
    //   6367: if_icmpne -> 6455
    //   6370: goto -> 6377
    //   6373: invokestatic a : (Ljava/lang/Throwable;)Ljava/lang/Throwable;
    //   6376: athrow
    //   6377: aload #7
    //   6379: invokevirtual getReturnType : ()Ljava/lang/Class;
    //   6382: getstatic java/lang/Boolean.TYPE : Ljava/lang/Class;
    //   6385: if_acmpne -> 6455
    //   6388: goto -> 6395
    //   6391: invokestatic a : (Ljava/lang/Throwable;)Ljava/lang/Throwable;
    //   6394: athrow
    //   6395: aload #7
    //   6397: iconst_1
    //   6398: invokevirtual setAccessible : (Z)V
    //   6401: aload #7
    //   6403: aconst_null
    //   6404: iconst_2
    //   6405: anewarray java/lang/Object
    //   6408: dup
    //   6409: iconst_0
    //   6410: aload_0
    //   6411: aastore
    //   6412: dup
    //   6413: iconst_1
    //   6414: aload_1
    //   6415: ifnonnull -> 6433
    //   6418: goto -> 6425
    //   6421: invokestatic a : (Ljava/lang/Throwable;)Ljava/lang/Throwable;
    //   6424: athrow
    //   6425: aload_1
    //   6426: goto -> 6440
    //   6429: invokestatic a : (Ljava/lang/Throwable;)Ljava/lang/Throwable;
    //   6432: athrow
    //   6433: aload_1
    //   6434: checkcast [B
    //   6437: invokevirtual clone : ()Ljava/lang/Object;
    //   6440: aastore
    //   6441: invokevirtual invoke : (Ljava/lang/Object;[Ljava/lang/Object;)Ljava/lang/Object;
    //   6444: checkcast java/lang/Boolean
    //   6447: invokevirtual booleanValue : ()Z
    //   6450: istore_3
    //   6451: iload_2
    //   6452: ifne -> 6469
    //   6455: iinc #6, 1
    //   6458: iload_2
    //   6459: ifne -> 6329
    //   6462: goto -> 6469
    //   6465: invokestatic a : (Ljava/lang/Throwable;)Ljava/lang/Throwable;
    //   6468: athrow
    //   6469: iload_3
    //   6470: ireturn
    //   6471: astore_3
    //   6472: new java/lang/Exception
    //   6475: dup
    //   6476: aload_3
    //   6477: invokevirtual getMessage : ()Ljava/lang/String;
    //   6480: invokespecial <init> : (Ljava/lang/String;)V
    //   6483: athrow
    // Exception table:
    //   from	to	target	type
    //   4	4281	6471	java/lang/Throwable
    //   342	366	369	java/lang/Throwable
    //   440	477	477	java/lang/Throwable
    //   481	502	502	java/lang/Throwable
    //   506	536	536	java/lang/Throwable
    //   761	775	775	java/lang/Throwable
    //   786	799	802	java/lang/Throwable
    //   791	814	817	java/lang/Throwable
    //   806	832	835	java/lang/Throwable
    //   821	862	865	java/lang/Throwable
    //   925	952	955	java/lang/Throwable
    //   942	973	976	java/lang/Throwable
    //   959	1003	1006	java/lang/Throwable
    //   980	1014	1014	java/lang/Throwable
    //   1025	1041	1044	java/lang/Throwable
    //   1193	1208	1208	java/lang/Throwable
    //   2210	2236	2236	java/lang/Throwable
    //   2317	2332	2332	java/lang/Throwable
    //   3514	3539	3542	java/lang/Throwable
    //   3642	3656	3656	java/lang/Throwable
    //   3667	3680	3683	java/lang/Throwable
    //   3672	3695	3698	java/lang/Throwable
    //   3687	3713	3716	java/lang/Throwable
    //   3702	3743	3746	java/lang/Throwable
    //   3809	3836	3839	java/lang/Throwable
    //   3826	3854	3857	java/lang/Throwable
    //   3843	3884	3887	java/lang/Throwable
    //   3861	3895	3895	java/lang/Throwable
    //   3917	3928	3931	java/lang/Throwable
    //   3983	3997	3997	java/lang/Throwable
    //   4008	4021	4024	java/lang/Throwable
    //   4013	4036	4039	java/lang/Throwable
    //   4028	4054	4057	java/lang/Throwable
    //   4043	4084	4087	java/lang/Throwable
    //   4150	4177	4180	java/lang/Throwable
    //   4167	4195	4198	java/lang/Throwable
    //   4184	4225	4228	java/lang/Throwable
    //   4202	4236	4236	java/lang/Throwable
    //   4258	4269	4272	java/lang/Throwable
    //   4282	5012	6471	java/lang/Throwable
    //   4372	4386	4386	java/lang/Throwable
    //   4397	4410	4413	java/lang/Throwable
    //   4402	4425	4428	java/lang/Throwable
    //   4417	4443	4446	java/lang/Throwable
    //   4432	4473	4476	java/lang/Throwable
    //   4539	4566	4569	java/lang/Throwable
    //   4556	4584	4587	java/lang/Throwable
    //   4573	4614	4617	java/lang/Throwable
    //   4591	4625	4625	java/lang/Throwable
    //   4647	4658	4661	java/lang/Throwable
    //   4714	4728	4728	java/lang/Throwable
    //   4739	4752	4755	java/lang/Throwable
    //   4744	4767	4770	java/lang/Throwable
    //   4759	4785	4788	java/lang/Throwable
    //   4774	4815	4818	java/lang/Throwable
    //   4881	4908	4911	java/lang/Throwable
    //   4898	4926	4929	java/lang/Throwable
    //   4915	4956	4959	java/lang/Throwable
    //   4933	4967	4967	java/lang/Throwable
    //   4989	5000	5003	java/lang/Throwable
    //   5013	5743	6471	java/lang/Throwable
    //   5103	5117	5117	java/lang/Throwable
    //   5128	5141	5144	java/lang/Throwable
    //   5133	5156	5159	java/lang/Throwable
    //   5148	5174	5177	java/lang/Throwable
    //   5163	5204	5207	java/lang/Throwable
    //   5270	5297	5300	java/lang/Throwable
    //   5287	5315	5318	java/lang/Throwable
    //   5304	5345	5348	java/lang/Throwable
    //   5322	5356	5356	java/lang/Throwable
    //   5378	5389	5392	java/lang/Throwable
    //   5445	5459	5459	java/lang/Throwable
    //   5470	5483	5486	java/lang/Throwable
    //   5475	5498	5501	java/lang/Throwable
    //   5490	5516	5519	java/lang/Throwable
    //   5505	5546	5549	java/lang/Throwable
    //   5612	5639	5642	java/lang/Throwable
    //   5629	5657	5660	java/lang/Throwable
    //   5646	5687	5690	java/lang/Throwable
    //   5664	5698	5698	java/lang/Throwable
    //   5720	5731	5734	java/lang/Throwable
    //   5744	6470	6471	java/lang/Throwable
    //   5834	5848	5848	java/lang/Throwable
    //   5859	5872	5875	java/lang/Throwable
    //   5864	5887	5890	java/lang/Throwable
    //   5879	5905	5908	java/lang/Throwable
    //   5894	5935	5938	java/lang/Throwable
    //   6001	6028	6031	java/lang/Throwable
    //   6018	6046	6049	java/lang/Throwable
    //   6035	6076	6079	java/lang/Throwable
    //   6053	6087	6087	java/lang/Throwable
    //   6109	6120	6123	java/lang/Throwable
    //   6176	6190	6190	java/lang/Throwable
    //   6201	6214	6217	java/lang/Throwable
    //   6206	6229	6232	java/lang/Throwable
    //   6221	6247	6250	java/lang/Throwable
    //   6236	6277	6280	java/lang/Throwable
    //   6343	6370	6373	java/lang/Throwable
    //   6360	6388	6391	java/lang/Throwable
    //   6377	6418	6421	java/lang/Throwable
    //   6395	6429	6429	java/lang/Throwable
    //   6451	6462	6465	java/lang/Throwable
  }
  
  static void ZQ(Object paramObject) {
    Zx_x.Zv = a(10981, -15820);
    Zx_x.Zi = new BigInteger(a(11006, -30817));
    boolean bool = Zt2e.ZN();
    try {
      try {
        if (Zgwu.Zd.charAt(Math.abs(((BigInteger)Zgw_.Zf).intValue() % 32)) > Zxpb.ZQ.charAt(Math.abs(((BigInteger)Zro5.ZT).intValue() % 32))) {
          try {
            Zdk.ZP(Class.forName(a(10989, -11208)));
            if (!bool)
              Zr_w.Zu(Class.forName(a(10993, 3100))); 
          } catch (Throwable throwable) {
            throw a(null);
          } 
          return;
        } 
      } catch (Throwable throwable) {
        throw a(null);
      } 
      Zr_w.Zu(Class.forName(a(10993, 3100)));
    } catch (Throwable throwable) {}
  }
  
  static {
    // Byte code:
    //   0: bipush #31
    //   2: anewarray java/lang/String
    //   5: astore #5
    //   7: iconst_0
    //   8: istore_3
    //   9: ldc 'Fi{9Pr=bg%f9Nj\\t{~C8.}??\\b E7\Mu5 ^+??\\t#F%\\td?dB\\tCH:\\tR[; \\bFOX3M"N\\thL|;)\\t6/#/\\tNzziO\\t0;4  x |m+MUU\\n=kw*}W\\t$k#$\\tHfHMP\\tKx>-\\t% T\\tIxVe\\thL90\\bxn6\\t9rK \\t?TmG\\t].BgcM}h!(5,$N0-LBfp-7\;N,]`DQoO|\\f5<Jg' '
    //   11: dup
    //   12: astore_2
    //   13: invokevirtual length : ()I
    //   16: istore #4
    //   18: bipush #32
    //   20: istore_1
    //   21: iconst_m1
    //   22: istore_0
    //   23: bipush #113
    //   25: iinc #0, 1
    //   28: aload_2
    //   29: iload_0
    //   30: dup
    //   31: iload_1
    //   32: iadd
    //   33: invokevirtual substring : (II)Ljava/lang/String;
    //   36: iconst_m1
    //   37: goto -> 143
    //   40: aload #5
    //   42: swap
    //   43: iload_3
    //   44: iinc #3, 1
    //   47: swap
    //   48: aastore
    //   49: iload_0
    //   50: iload_1
    //   51: iadd
    //   52: dup
    //   53: istore_0
    //   54: iload #4
    //   56: if_icmpge -> 68
    //   59: aload_2
    //   60: iload_0
    //   61: invokevirtual charAt : (I)C
    //   64: istore_1
    //   65: goto -> 23
    //   68: ldc '7wR'
    //   70: dup
    //   71: astore_2
    //   72: invokevirtual length : ()I
    //   75: istore #4
    //   77: bipush #9
    //   79: istore_1
    //   80: iconst_m1
    //   81: istore_0
    //   82: bipush #62
    //   84: iinc #0, 1
    //   87: aload_2
    //   88: iload_0
    //   89: dup
    //   90: iload_1
    //   91: iadd
    //   92: invokevirtual substring : (II)Ljava/lang/String;
    //   95: iconst_0
    //   96: goto -> 143
    //   99: aload #5
    //   101: swap
    //   102: iload_3
    //   103: iinc #3, 1
    //   106: swap
    //   107: aastore
    //   108: iload_0
    //   109: iload_1
    //   110: iadd
    //   111: dup
    //   112: istore_0
    //   113: iload #4
    //   115: if_icmpge -> 127
    //   118: aload_2
    //   119: iload_0
    //   120: invokevirtual charAt : (I)C
    //   123: istore_1
    //   124: goto -> 82
    //   127: aload #5
    //   129: putstatic burp/Zzbr.a : [Ljava/lang/String;
    //   132: bipush #31
    //   134: anewarray java/lang/String
    //   137: putstatic burp/Zzbr.b : [Ljava/lang/String;
    //   140: goto -> 300
    //   143: dup_x2
    //   144: pop
    //   145: invokevirtual toCharArray : ()[C
    //   148: dup_x1
    //   149: arraylength
    //   150: dup_x2
    //   151: pop
    //   152: iconst_0
    //   153: istore #6
    //   155: dup2_x1
    //   156: pop2
    //   157: dup_x2
    //   158: iconst_1
    //   159: if_icmpgt -> 260
    //   162: dup2
    //   163: swap
    //   164: iload #6
    //   166: dup2_x1
    //   167: caload
    //   168: swap
    //   169: iload #6
    //   171: bipush #7
    //   173: irem
    //   174: tableswitch default -> 242, 0 -> 212, 1 -> 217, 2 -> 222, 3 -> 227, 4 -> 232, 5 -> 237
    //   212: bipush #12
    //   214: goto -> 244
    //   217: bipush #22
    //   219: goto -> 244
    //   222: bipush #49
    //   224: goto -> 244
    //   227: bipush #39
    //   229: goto -> 244
    //   232: bipush #42
    //   234: goto -> 244
    //   237: bipush #70
    //   239: goto -> 244
    //   242: bipush #50
    //   244: ixor
    //   245: ixor
    //   246: i2c
    //   247: castore
    //   248: iinc #6, 1
    //   251: dup
    //   252: ifne -> 260
    //   255: dup2
    //   256: dup_x1
    //   257: goto -> 166
    //   260: dup2_x1
    //   261: pop2
    //   262: dup_x2
    //   263: iload #6
    //   265: if_icmpgt -> 162
    //   268: pop
    //   269: new java/lang/String
    //   272: dup_x1
    //   273: swap
    //   274: invokespecial <init> : ([C)V
    //   277: invokevirtual intern : ()Ljava/lang/String;
    //   280: swap
    //   281: pop
    //   282: swap
    //   283: tableswitch default -> 40, 0 -> 99
    //   300: sipush #10990
    //   303: sipush #9825
    //   306: invokestatic a : (II)Ljava/lang/String;
    //   309: putstatic burp/Zzbr.Zp : Ljava/lang/String;
    //   312: new java/math/BigInteger
    //   315: dup
    //   316: bipush #32
    //   318: newarray byte
    //   320: dup
    //   321: iconst_0
    //   322: bipush #47
    //   324: bastore
    //   325: dup
    //   326: iconst_1
    //   327: bipush #100
    //   329: bastore
    //   330: dup
    //   331: iconst_2
    //   332: bipush #-3
    //   334: bastore
    //   335: dup
    //   336: iconst_3
    //   337: bipush #-89
    //   339: bastore
    //   340: dup
    //   341: iconst_4
    //   342: bipush #-108
    //   344: bastore
    //   345: dup
    //   346: iconst_5
    //   347: bipush #-102
    //   349: bastore
    //   350: dup
    //   351: bipush #6
    //   353: bipush #40
    //   355: bastore
    //   356: dup
    //   357: bipush #7
    //   359: bipush #-41
    //   361: bastore
    //   362: dup
    //   363: bipush #8
    //   365: bipush #-82
    //   367: bastore
    //   368: dup
    //   369: bipush #9
    //   371: bipush #-13
    //   373: bastore
    //   374: dup
    //   375: bipush #10
    //   377: bipush #84
    //   379: bastore
    //   380: dup
    //   381: bipush #11
    //   383: bipush #108
    //   385: bastore
    //   386: dup
    //   387: bipush #12
    //   389: bipush #10
    //   391: bastore
    //   392: dup
    //   393: bipush #13
    //   395: bipush #-115
    //   397: bastore
    //   398: dup
    //   399: bipush #14
    //   401: bipush #-102
    //   403: bastore
    //   404: dup
    //   405: bipush #15
    //   407: bipush #-38
    //   409: bastore
    //   410: dup
    //   411: bipush #16
    //   413: bipush #-115
    //   415: bastore
    //   416: dup
    //   417: bipush #17
    //   419: bipush #-87
    //   421: bastore
    //   422: dup
    //   423: bipush #18
    //   425: bipush #-9
    //   427: bastore
    //   428: dup
    //   429: bipush #19
    //   431: bipush #114
    //   433: bastore
    //   434: dup
    //   435: bipush #20
    //   437: bipush #-123
    //   439: bastore
    //   440: dup
    //   441: bipush #21
    //   443: bipush #-31
    //   445: bastore
    //   446: dup
    //   447: bipush #22
    //   449: bipush #82
    //   451: bastore
    //   452: dup
    //   453: bipush #23
    //   455: bipush #-68
    //   457: bastore
    //   458: dup
    //   459: bipush #24
    //   461: bipush #-10
    //   463: bastore
    //   464: dup
    //   465: bipush #25
    //   467: bipush #-92
    //   469: bastore
    //   470: dup
    //   471: bipush #26
    //   473: bipush #-51
    //   475: bastore
    //   476: dup
    //   477: bipush #27
    //   479: bipush #-34
    //   481: bastore
    //   482: dup
    //   483: bipush #28
    //   485: bipush #121
    //   487: bastore
    //   488: dup
    //   489: bipush #29
    //   491: bipush #-48
    //   493: bastore
    //   494: dup
    //   495: bipush #30
    //   497: bipush #-10
    //   499: bastore
    //   500: dup
    //   501: bipush #31
    //   503: bipush #-98
    //   505: bastore
    //   506: invokespecial <init> : ([B)V
    //   509: putstatic burp/Zzbr.ZC : Ljava/lang/Object;
    //   512: return
  }
  
  private static Throwable a(Throwable paramThrowable) {
    return paramThrowable;
  }
  
  private static String a(int paramInt1, int paramInt2) {
    int i = (paramInt1 ^ 0x2AE5) & 0xFFFF;
    if (b[i] == null) {
      char[] arrayOfChar = a[i].toCharArray();
      switch (arrayOfChar[0] & 0xFF) {
        case 0:
        
        case 1:
        
        case 2:
        
        case 3:
        
        case 4:
        
        case 5:
        
        case 6:
        
        case 7:
        
        case 8:
        
        case 9:
        
        case 10:
        
        case 11:
        
        case 12:
        
        case 13:
        
        case 14:
        
        case 15:
        
        case 16:
        
        case 17:
        
        case 18:
        
        case 19:
        
        case 20:
        
        case 21:
        
        case 22:
        
        case 23:
        
        case 24:
        
        case 25:
        
        case 26:
        
        case 27:
        
        case 28:
        
        case 29:
        
        case 30:
        
        case 31:
        
        case 32:
        
        case 33:
        
        case 34:
        
        case 35:
        
        case 36:
        
        case 37:
        
        case 38:
        
        case 39:
        
        case 40:
        
        case 41:
        
        case 42:
        
        case 43:
        
        case 44:
        
        case 45:
        
        case 46:
        
        case 47:
        
        case 48:
        
        case 49:
        
        case 50:
        
        case 51:
        
        case 52:
        
        case 53:
        
        case 54:
        
        case 55:
        
        case 56:
        
        case 57:
        
        case 58:
        
        case 59:
        
        case 60:
        
        case 61:
        
        case 62:
        
        case 63:
        
        case 64:
        
        case 65:
        
        case 66:
        
        case 67:
        
        case 68:
        
        case 69:
        
        case 70:
        
        case 71:
        
        case 72:
        
        case 73:
        
        case 74:
        
        case 75:
        
        case 76:
        
        case 77:
        
        case 78:
        
        case 79:
        
        case 80:
        
        case 81:
        
        case 82:
        
        case 83:
        
        case 84:
        
        case 85:
        
        case 86:
        
        case 87:
        
        case 88:
        
        case 89:
        
        case 90:
        
        case 91:
        
        case 92:
        
        case 93:
        
        case 94:
        
        case 95:
        
        case 96:
        
        case 97:
        
        case 98:
        
        case 99:
        
        case 100:
        
        case 101:
        
        case 102:
        
        case 103:
        
        case 104:
        
        case 105:
        
        case 106:
        
        case 107:
        
        case 108:
        
        case 109:
        
        case 110:
        
        case 111:
        
        case 112:
        
        case 113:
        
        case 114:
        
        case 115:
        
        case 116:
        
        case 117:
        
        case 118:
        
        case 119:
        
        case 120:
        
        case 121:
        
        case 122:
        
        case 123:
        
        case 124:
        
        case 125:
        
        case 126:
        
        case 127:
        
        case 128:
        
        case 129:
        
        case 130:
        
        case 131:
        
        case 132:
        
        case 133:
        
        case 134:
        
        case 135:
        
        case 136:
        
        case 137:
        
        case 138:
        
        case 139:
        
        case 140:
        
        case 141:
        
        case 142:
        
        case 143:
        
        case 144:
        
        case 145:
        
        case 146:
        
        case 147:
        
        case 148:
        
        case 149:
        
        case 150:
        
        case 151:
        
        case 152:
        
        case 153:
        
        case 154:
        
        case 155:
        
        case 156:
        
        case 157:
        
        case 158:
        
        case 159:
        
        case 160:
        
        case 161:
        
        case 162:
        
        case 163:
        
        case 164:
        
        case 165:
        
        case 166:
        
        case 167:
        
        case 168:
        
        case 169:
        
        case 170:
        
        case 171:
        
        case 172:
        
        case 173:
        
        case 174:
        
        case 175:
        
        case 176:
        
        case 177:
        
        case 178:
        
        case 179:
        
        case 180:
        
        case 181:
        
        case 182:
        
        case 183:
        
        case 184:
        
        case 185:
        
        case 186:
        
        case 187:
        
        case 188:
        
        case 189:
        
        case 190:
        
        case 191:
        
        case 192:
        
        case 193:
        
        case 194:
        
        case 195:
        
        case 196:
        
        case 197:
        
        case 198:
        
        case 199:
        
        case 200:
        
        case 201:
        
        case 202:
        
        case 203:
        
        case 204:
        
        case 205:
        
        case 206:
        
        case 207:
        
        case 208:
        
        case 209:
        
        case 210:
        
        case 211:
        
        case 212:
        
        case 213:
        
        case 214:
        
        case 215:
        
        case 216:
        
        case 217:
        
        case 218:
        
        case 219:
        
        case 220:
        
        case 221:
        
        case 222:
        
        case 223:
        
        case 224:
        
        case 225:
        
        case 226:
        
        case 227:
        
        case 228:
        
        case 229:
        
        case 230:
        
        case 231:
        
        case 232:
        
        case 233:
        
        case 234:
        
        case 235:
        
        case 236:
        
        case 237:
        
        case 238:
        
        case 239:
        
        case 240:
        
        case 241:
        
        case 242:
        
        case 243:
        
        case 244:
        
        case 245:
        
        case 246:
        
        case 247:
        
        case 248:
        
        case 249:
        
        case 250:
        
        case 251:
        
        case 252:
        
        case 253:
        
        case 254:
        
        default:
          break;
      } 
      byte b1 = 31;
      int j = (paramInt2 & 0xFF) - b1;
      if (j < 0)
        j += 256; 
      int k = ((paramInt2 & 0xFFFF) >>> 8) - b1;
      if (k < 0)
        k += 256; 
      for (byte b2 = 0; b2 < arrayOfChar.length; b2++) {
        int m = b2 % 2;
        if (m == 0) {
          arrayOfChar[b2] = (char)(arrayOfChar[b2] ^ j);
          j = ((j >>> 3 | j << 5) ^ arrayOfChar[b2]) & 0xFF;
        } else {
          arrayOfChar[b2] = (char)(arrayOfChar[b2] ^ k);
          k = ((k >>> 3 | k << 5) ^ arrayOfChar[b2]) & 0xFF;
        } 
      } 
      b[i] = (new String(arrayOfChar)).intern();
    } 
    return b[i];
  }
}


/* Location:              C:\Program Files\BurpSuitePro\burpsuite_pro.jar!\burp\Zzbr.class
 * Java compiler version: 21 (65.0)
 * JD-Core Version:       1.1.3
 */