package burp;

import java.nio.charset.StandardCharsets;
import java.util.List;
import java.util.Map;
import java.util.Objects;
import java.util.stream.Collectors;

public class Zzis implements Ze8l {
  private final Ztbb Zb;
  
  private final Zzen Zw;
  
  private final Zlnx Zu;
  
  private static final String[] a;
  
  private static final String[] b;
  
  public Zzis(Ztbb paramZtbb, Zzen paramZzen, Zlnx paramZlnx) {
    this.Zb = paramZtbb;
    this.Zw = paramZzen;
    this.Zu = paramZlnx;
  }
  
  public byte[] ZP(Zzho paramZzho) {
    Map<String, String> map = paramZzho.ZZ();
    Zto zto = new Zto();
    String str1 = zto.ZI(zto.ZW(map.getOrDefault(a(5475, -9667), "")));
    String str2 = zto.ZI(zto.ZW(map.getOrDefault(a(5478, -31081), "")));
    Zmzk zmzk = Zc(paramZzho, zto);
    String str3 = this.Zb.ZP(zmzk).ZK();
    StringBuilder stringBuilder = new StringBuilder(String.format(a(5477, -5972), new Object[] { str1, str2, str3 }));
    List<Zges> list1 = paramZzho.ZR();
    String[] arrayOfString = Zt17.ZL();
    boolean bool1 = map.containsKey(a(5486, -28119));
    boolean bool2 = list1.stream().anyMatch(Zzis::lambda$downgrade$0);
    try {
      if (bool1)
        try {
          if (!bool2)
            stringBuilder.append(String.format(a(5485, 9470), new Object[] { map.get(a(5486, -28119)) })); 
        } catch (IllegalStateException illegalStateException) {
          throw a(null);
        }  
    } catch (IllegalStateException illegalStateException) {
      throw a(null);
    } 
    List<Zges> list2 = paramZzho.ZO();
    try {
      if (!list2.isEmpty()) {
        Objects.requireNonNull(zto);
        stringBuilder.append(a(5487, 2883)).append(list2.stream().map(Zges::ZR).map(zto::ZW).collect(Collectors.joining(a(5484, -31578)))).append(a(5481, 31518));
      } 
    } catch (IllegalStateException illegalStateException) {
      throw a(null);
    } 
    boolean bool3 = paramZzho.ZV();
    list1.stream().filter(bool3::lambda$downgrade$1).map(zto::lambda$downgrade$2).forEach(stringBuilder::lambda$downgrade$3);
    stringBuilder.append(a(5481, 31518));
    String str4 = stringBuilder.toString();
    List<byte[]> list = paramZzho.Zv();
    long l = list.stream().mapToLong(Zzis::lambda$downgrade$4).sum();
    try {
      if (l + str4.length() > 2147483647L)
        throw new IllegalStateException(a(5483, 20146)); 
    } catch (IllegalStateException illegalStateException) {
      throw a(null);
    } 
    byte[] arrayOfByte = new byte[(int)(str4.length() + l)];
    int i = str4.length();
    System.arraycopy(str4.getBytes(StandardCharsets.US_ASCII), 0, arrayOfByte, 0, str4.length());
    for (byte[] arrayOfByte1 : list) {
      System.arraycopy(arrayOfByte1, 0, arrayOfByte, i, arrayOfByte1.length);
      i += arrayOfByte1.length;
      if (arrayOfString != null)
        break; 
    } 
    try {
      if (!zto.ZH()) {
        try {
          if (paramZzho.Zu()) {
            this.Zw.Zu(zmzk);
            return arrayOfByte;
          } 
        } catch (IllegalStateException illegalStateException) {
          throw a(null);
        } 
        return arrayOfByte;
      } 
    } catch (IllegalStateException illegalStateException) {
      throw a(null);
    } 
    this.Zw.Zu(zmzk);
    return arrayOfByte;
  }
  
  private Zmzk Zc(Zzho paramZzho, Ztyb paramZtyb) {
    Map<String, String> map = paramZzho.ZZ();
    List<Zges> list = paramZzho.ZR();
    try {
      Objects.requireNonNull(paramZtyb);
    } catch (IllegalStateException illegalStateException) {
      throw a(null);
    } 
    String str = map.containsKey(a(5480, -17912)) ? map.get(a(5486, -28119)) : list.stream().filter(Zzis::lambda$downgrade$0).map(Zges::ZR).map(paramZtyb::ZW).findFirst().orElse("");
    Zlit zlit = this.Zu.ZF(a(5482, 4995) + a(5482, 4995));
    try {
    
    } catch (IllegalStateException illegalStateException) {
      throw a(null);
    } 
    return (zlit == null) ? null : zlit.Zdz();
  }
  
  private static long lambda$downgrade$4(byte[] paramArrayOfbyte) {
    return paramArrayOfbyte.length;
  }
  
  private static void lambda$downgrade$3(StringBuilder paramStringBuilder, String paramString) {
    paramStringBuilder.append(paramString).append(a(5474, 32110));
  }
  
  private static String lambda$downgrade$2(Ztyb paramZtyb, Zges paramZges) {
    return paramZges.Za(paramZtyb);
  }
  
  private static boolean lambda$downgrade$1(boolean paramBoolean, Zges paramZges) {
    try {
      if (paramBoolean) {
        try {
          if (!a(5476, -12693).equals(paramZges.ZN()));
        } catch (IllegalStateException illegalStateException) {
          throw a(null);
        } 
        return false;
      } 
    } catch (IllegalStateException illegalStateException) {
      throw a(null);
    } 
  }
  
  private static boolean lambda$downgrade$0(Zges paramZges) {
    return paramZges.ZN().equals(a(5479, -21784));
  }
  
  private static IllegalStateException a(IllegalStateException paramIllegalStateException) {
    return paramIllegalStateException;
  }
  
  static {
    // Byte code:
    //   0: bipush #14
    //   2: anewarray java/lang/String
    //   5: astore #5
    //   7: iconst_0
    //   8: istore_3
    //   9: ldc 'Ã˜?Ã¶Â†dNÃ±QÃ¦\\b+ÃªÃ„Ã¬zÃµÂ¯Â„9!\\nÂ«Ã·Â¢PzÃ›Â‰Ã¿\\r\\bÂŠÂ”Âƒ?Ã®fÃ½S3ÂŽUrÂ‰Â Â´Â³Ã‘ÂºtN}H\\nÂžÂ¶>Â·}h&55~Â›Â¾Ã‚.\\nÃ©ÂˆTÃ¢$^Â½Ã†ÂŸÃ²Ã¾\\nÂ¤ÃDÃª.Ã™Ã°Ã‰'
    //   11: dup
    //   12: astore_2
    //   13: invokevirtual length : ()I
    //   16: istore #4
    //   18: bipush #10
    //   20: istore_1
    //   21: iconst_m1
    //   22: istore_0
    //   23: iconst_4
    //   24: iinc #0, 1
    //   27: aload_2
    //   28: iload_0
    //   29: dup
    //   30: iload_1
    //   31: iadd
    //   32: invokevirtual substring : (II)Ljava/lang/String;
    //   35: iconst_m1
    //   36: goto -> 141
    //   39: aload #5
    //   41: swap
    //   42: iload_3
    //   43: iinc #3, 1
    //   46: swap
    //   47: aastore
    //   48: iload_0
    //   49: iload_1
    //   50: iadd
    //   51: dup
    //   52: istore_0
    //   53: iload #4
    //   55: if_icmpge -> 67
    //   58: aload_2
    //   59: iload_0
    //   60: invokevirtual charAt : (I)C
    //   63: istore_1
    //   64: goto -> 23
    //   67: ldc '>Ã¯HÃ™,ÃµÂ§Ã¹'
    //   69: dup
    //   70: astore_2
    //   71: invokevirtual length : ()I
    //   74: istore #4
    //   76: iconst_2
    //   77: istore_1
    //   78: iconst_m1
    //   79: istore_0
    //   80: bipush #59
    //   82: iinc #0, 1
    //   85: aload_2
    //   86: iload_0
    //   87: dup
    //   88: iload_1
    //   89: iadd
    //   90: invokevirtual substring : (II)Ljava/lang/String;
    //   93: iconst_0
    //   94: goto -> 141
    //   97: aload #5
    //   99: swap
    //   100: iload_3
    //   101: iinc #3, 1
    //   104: swap
    //   105: aastore
    //   106: iload_0
    //   107: iload_1
    //   108: iadd
    //   109: dup
    //   110: istore_0
    //   111: iload #4
    //   113: if_icmpge -> 125
    //   116: aload_2
    //   117: iload_0
    //   118: invokevirtual charAt : (I)C
    //   121: istore_1
    //   122: goto -> 80
    //   125: aload #5
    //   127: putstatic burp/Zzis.a : [Ljava/lang/String;
    //   130: bipush #14
    //   132: anewarray java/lang/String
    //   135: putstatic burp/Zzis.b : [Ljava/lang/String;
    //   138: goto -> 300
    //   141: dup_x2
    //   142: pop
    //   143: invokevirtual toCharArray : ()[C
    //   146: dup_x1
    //   147: arraylength
    //   148: dup_x2
    //   149: pop
    //   150: iconst_0
    //   151: istore #6
    //   153: dup2_x1
    //   154: pop2
    //   155: dup_x2
    //   156: iconst_1
    //   157: if_icmpgt -> 260
    //   160: dup2
    //   161: swap
    //   162: iload #6
    //   164: dup2_x1
    //   165: caload
    //   166: swap
    //   167: iload #6
    //   169: bipush #7
    //   171: irem
    //   172: tableswitch default -> 242, 0 -> 212, 1 -> 217, 2 -> 222, 3 -> 227, 4 -> 232, 5 -> 237
    //   212: bipush #122
    //   214: goto -> 244
    //   217: bipush #95
    //   219: goto -> 244
    //   222: bipush #46
    //   224: goto -> 244
    //   227: bipush #55
    //   229: goto -> 244
    //   232: bipush #72
    //   234: goto -> 244
    //   237: bipush #105
    //   239: goto -> 244
    //   242: bipush #19
    //   244: ixor
    //   245: ixor
    //   246: i2c
    //   247: castore
    //   248: iinc #6, 1
    //   251: dup
    //   252: ifne -> 260
    //   255: dup2
    //   256: dup_x1
    //   257: goto -> 164
    //   260: dup2_x1
    //   261: pop2
    //   262: dup_x2
    //   263: iload #6
    //   265: if_icmpgt -> 160
    //   268: pop
    //   269: new java/lang/String
    //   272: dup_x1
    //   273: swap
    //   274: invokespecial <init> : ([C)V
    //   277: invokevirtual intern : ()Ljava/lang/String;
    //   280: swap
    //   281: pop
    //   282: swap
    //   283: tableswitch default -> 39, 0 -> 97
    //   300: return
  }
  
  private static String a(int paramInt1, int paramInt2) {
    int i = (paramInt1 ^ 0x156E) & 0xFFFF;
    if (b[i] == null) {
      char[] arrayOfChar = a[i].toCharArray();
      switch (arrayOfChar[0] & 0xFF) {
        case 0:
        
        case 1:
        
        case 2:
        
        case 3:
        
        case 4:
        
        case 5:
        
        case 6:
        
        case 7:
        
        case 8:
        
        case 9:
        
        case 10:
        
        case 11:
        
        case 12:
        
        case 13:
        
        case 14:
        
        case 15:
        
        case 16:
        
        case 17:
        
        case 18:
        
        case 19:
        
        case 20:
        
        case 21:
        
        case 22:
        
        case 23:
        
        case 24:
        
        case 25:
        
        case 26:
        
        case 27:
        
        case 28:
        
        case 29:
        
        case 30:
        
        case 31:
        
        case 32:
        
        case 33:
        
        case 34:
        
        case 35:
        
        case 36:
        
        case 37:
        
        case 38:
        
        case 39:
        
        case 40:
        
        case 41:
        
        case 42:
        
        case 43:
        
        case 44:
        
        case 45:
        
        case 46:
        
        case 47:
        
        case 48:
        
        case 49:
        
        case 50:
        
        case 51:
        
        case 52:
        
        case 53:
        
        case 54:
        
        case 55:
        
        case 56:
        
        case 57:
        
        case 58:
        
        case 59:
        
        case 60:
        
        case 61:
        
        case 62:
        
        case 63:
        
        case 64:
        
        case 65:
        
        case 66:
        
        case 67:
        
        case 68:
        
        case 69:
        
        case 70:
        
        case 71:
        
        case 72:
        
        case 73:
        
        case 74:
        
        case 75:
        
        case 76:
        
        case 77:
        
        case 78:
        
        case 79:
        
        case 80:
        
        case 81:
        
        case 82:
        
        case 83:
        
        case 84:
        
        case 85:
        
        case 86:
        
        case 87:
        
        case 88:
        
        case 89:
        
        case 90:
        
        case 91:
        
        case 92:
        
        case 93:
        
        case 94:
        
        case 95:
        
        case 96:
        
        case 97:
        
        case 98:
        
        case 99:
        
        case 100:
        
        case 101:
        
        case 102:
        
        case 103:
        
        case 104:
        
        case 105:
        
        case 106:
        
        case 107:
        
        case 108:
        
        case 109:
        
        case 110:
        
        case 111:
        
        case 112:
        
        case 113:
        
        case 114:
        
        case 115:
        
        case 116:
        
        case 117:
        
        case 118:
        
        case 119:
        
        case 120:
        
        case 121:
        
        case 122:
        
        case 123:
        
        case 124:
        
        case 125:
        
        case 126:
        
        case 127:
        
        case 128:
        
        case 129:
        
        case 130:
        
        case 131:
        
        case 132:
        
        case 133:
        
        case 134:
        
        case 135:
        
        case 136:
        
        case 137:
        
        case 138:
        
        case 139:
        
        case 140:
        
        case 141:
        
        case 142:
        
        case 143:
        
        case 144:
        
        case 145:
        
        case 146:
        
        case 147:
        
        case 148:
        
        case 149:
        
        case 150:
        
        case 151:
        
        case 152:
        
        case 153:
        
        case 154:
        
        case 155:
        
        case 156:
        
        case 157:
        
        case 158:
        
        case 159:
        
        case 160:
        
        case 161:
        
        case 162:
        
        case 163:
        
        case 164:
        
        case 165:
        
        case 166:
        
        case 167:
        
        case 168:
        
        case 169:
        
        case 170:
        
        case 171:
        
        case 172:
        
        case 173:
        
        case 174:
        
        case 175:
        
        case 176:
        
        case 177:
        
        case 178:
        
        case 179:
        
        case 180:
        
        case 181:
        
        case 182:
        
        case 183:
        
        case 184:
        
        case 185:
        
        case 186:
        
        case 187:
        
        case 188:
        
        case 189:
        
        case 190:
        
        case 191:
        
        case 192:
        
        case 193:
        
        case 194:
        
        case 195:
        
        case 196:
        
        case 197:
        
        case 198:
        
        case 199:
        
        case 200:
        
        case 201:
        
        case 202:
        
        case 203:
        
        case 204:
        
        case 205:
        
        case 206:
        
        case 207:
        
        case 208:
        
        case 209:
        
        case 210:
        
        case 211:
        
        case 212:
        
        case 213:
        
        case 214:
        
        case 215:
        
        case 216:
        
        case 217:
        
        case 218:
        
        case 219:
        
        case 220:
        
        case 221:
        
        case 222:
        
        case 223:
        
        case 224:
        
        case 225:
        
        case 226:
        
        case 227:
        
        case 228:
        
        case 229:
        
        case 230:
        
        case 231:
        
        case 232:
        
        case 233:
        
        case 234:
        
        case 235:
        
        case 236:
        
        case 237:
        
        case 238:
        
        case 239:
        
        case 240:
        
        case 241:
        
        case 242:
        
        case 243:
        
        case 244:
        
        case 245:
        
        case 246:
        
        case 247:
        
        case 248:
        
        case 249:
        
        case 250:
        
        case 251:
        
        case 252:
        
        case 253:
        
        case 254:
        
        default:
          break;
      } 
      byte b1 = 106;
      int j = (paramInt2 & 0xFF) - b1;
      if (j < 0)
        j += 256; 
      int k = ((paramInt2 & 0xFFFF) >>> 8) - b1;
      if (k < 0)
        k += 256; 
      for (byte b2 = 0; b2 < arrayOfChar.length; b2++) {
        int m = b2 % 2;
        if (m == 0) {
          arrayOfChar[b2] = (char)(arrayOfChar[b2] ^ j);
          j = ((j >>> 3 | j << 5) ^ arrayOfChar[b2]) & 0xFF;
        } else {
          arrayOfChar[b2] = (char)(arrayOfChar[b2] ^ k);
          k = ((k >>> 3 | k << 5) ^ arrayOfChar[b2]) & 0xFF;
        } 
      } 
      b[i] = (new String(arrayOfChar)).intern();
    } 
    return b[i];
  }
}


/* Location:              C:\Program Files\BurpSuitePro\burpsuite_pro.jar!\burp\Zzis.class
 * Java compiler version: 21 (65.0)
 * JD-Core Version:       1.1.3
 */