package burp;

import java.math.BigInteger;

class Zzl4 extends ClassLoader {
  static Object ZX;
  
  static String ZT;
  
  private static final String[] a;
  
  private static final String[] b;
  
  static void Zo(Object[] paramArrayOfObject, Object paramObject) throws Throwable {}
  
  static void Zg(Object paramObject) {
    Zrgo.Z_ = a(-32663, -24489);
    Zrgo.ZJ = new BigInteger(a(-32662, 4656));
    boolean bool = Zt2e.ZN();
    try {
      try {
        if (Zlw8.Zs.charAt(Math.abs(((BigInteger)Zgk9.ZD).intValue() % 32)) <= Ztq4.Zb.charAt(Math.abs(((BigInteger)Zgeq.ZT).intValue() % 32))) {
          try {
            Zskf.Ze(Class.forName(a(-32659, 16072)));
            if (!bool)
              Zr0.ZI(Class.forName(a(-32665, -27799))); 
          } catch (Throwable throwable) {
            throw a(null);
          } 
          return;
        } 
      } catch (Throwable throwable) {
        throw a(null);
      } 
      Zr0.ZI(Class.forName(a(-32665, -27799)));
    } catch (Throwable throwable) {}
  }
  
  static boolean Zk(Object[] paramArrayOfObject, Object paramObject) throws Throwable {
    // Byte code:
    //   0: invokestatic ZK : ()Z
    //   3: istore_2
    //   4: getstatic burp/Zvob.ZX : Ljava/lang/Object;
    //   7: checkcast java/math/BigInteger
    //   10: getstatic burp/Zrjw.Zu : Ljava/lang/Object;
    //   13: checkcast java/math/BigInteger
    //   16: invokevirtual subtract : (Ljava/math/BigInteger;)Ljava/math/BigInteger;
    //   19: putstatic burp/Zxdp.ZW : Ljava/lang/Object;
    //   22: getstatic burp/Zgcg.Zi : Ljava/lang/Object;
    //   25: checkcast java/math/BigInteger
    //   28: invokevirtual toByteArray : ()[B
    //   31: astore_3
    //   32: bipush #64
    //   34: newarray byte
    //   36: dup
    //   37: iconst_0
    //   38: bipush #-128
    //   40: bastore
    //   41: dup
    //   42: iconst_1
    //   43: iconst_0
    //   44: bastore
    //   45: dup
    //   46: iconst_2
    //   47: iconst_0
    //   48: bastore
    //   49: dup
    //   50: iconst_3
    //   51: iconst_0
    //   52: bastore
    //   53: dup
    //   54: iconst_4
    //   55: iconst_0
    //   56: bastore
    //   57: dup
    //   58: iconst_5
    //   59: iconst_0
    //   60: bastore
    //   61: dup
    //   62: bipush #6
    //   64: iconst_0
    //   65: bastore
    //   66: dup
    //   67: bipush #7
    //   69: iconst_0
    //   70: bastore
    //   71: dup
    //   72: bipush #8
    //   74: iconst_0
    //   75: bastore
    //   76: dup
    //   77: bipush #9
    //   79: iconst_0
    //   80: bastore
    //   81: dup
    //   82: bipush #10
    //   84: iconst_0
    //   85: bastore
    //   86: dup
    //   87: bipush #11
    //   89: iconst_0
    //   90: bastore
    //   91: dup
    //   92: bipush #12
    //   94: iconst_0
    //   95: bastore
    //   96: dup
    //   97: bipush #13
    //   99: iconst_0
    //   100: bastore
    //   101: dup
    //   102: bipush #14
    //   104: iconst_0
    //   105: bastore
    //   106: dup
    //   107: bipush #15
    //   109: iconst_0
    //   110: bastore
    //   111: dup
    //   112: bipush #16
    //   114: iconst_0
    //   115: bastore
    //   116: dup
    //   117: bipush #17
    //   119: iconst_0
    //   120: bastore
    //   121: dup
    //   122: bipush #18
    //   124: iconst_0
    //   125: bastore
    //   126: dup
    //   127: bipush #19
    //   129: iconst_0
    //   130: bastore
    //   131: dup
    //   132: bipush #20
    //   134: iconst_0
    //   135: bastore
    //   136: dup
    //   137: bipush #21
    //   139: iconst_0
    //   140: bastore
    //   141: dup
    //   142: bipush #22
    //   144: iconst_0
    //   145: bastore
    //   146: dup
    //   147: bipush #23
    //   149: iconst_0
    //   150: bastore
    //   151: dup
    //   152: bipush #24
    //   154: iconst_0
    //   155: bastore
    //   156: dup
    //   157: bipush #25
    //   159: iconst_0
    //   160: bastore
    //   161: dup
    //   162: bipush #26
    //   164: iconst_0
    //   165: bastore
    //   166: dup
    //   167: bipush #27
    //   169: iconst_0
    //   170: bastore
    //   171: dup
    //   172: bipush #28
    //   174: iconst_0
    //   175: bastore
    //   176: dup
    //   177: bipush #29
    //   179: iconst_0
    //   180: bastore
    //   181: dup
    //   182: bipush #30
    //   184: iconst_0
    //   185: bastore
    //   186: dup
    //   187: bipush #31
    //   189: iconst_0
    //   190: bastore
    //   191: dup
    //   192: bipush #32
    //   194: iconst_0
    //   195: bastore
    //   196: dup
    //   197: bipush #33
    //   199: iconst_0
    //   200: bastore
    //   201: dup
    //   202: bipush #34
    //   204: iconst_0
    //   205: bastore
    //   206: dup
    //   207: bipush #35
    //   209: iconst_0
    //   210: bastore
    //   211: dup
    //   212: bipush #36
    //   214: iconst_0
    //   215: bastore
    //   216: dup
    //   217: bipush #37
    //   219: iconst_0
    //   220: bastore
    //   221: dup
    //   222: bipush #38
    //   224: iconst_0
    //   225: bastore
    //   226: dup
    //   227: bipush #39
    //   229: iconst_0
    //   230: bastore
    //   231: dup
    //   232: bipush #40
    //   234: iconst_0
    //   235: bastore
    //   236: dup
    //   237: bipush #41
    //   239: iconst_0
    //   240: bastore
    //   241: dup
    //   242: bipush #42
    //   244: iconst_0
    //   245: bastore
    //   246: dup
    //   247: bipush #43
    //   249: iconst_0
    //   250: bastore
    //   251: dup
    //   252: bipush #44
    //   254: iconst_0
    //   255: bastore
    //   256: dup
    //   257: bipush #45
    //   259: iconst_0
    //   260: bastore
    //   261: dup
    //   262: bipush #46
    //   264: iconst_0
    //   265: bastore
    //   266: dup
    //   267: bipush #47
    //   269: iconst_0
    //   270: bastore
    //   271: dup
    //   272: bipush #48
    //   274: iconst_0
    //   275: bastore
    //   276: dup
    //   277: bipush #49
    //   279: iconst_0
    //   280: bastore
    //   281: dup
    //   282: bipush #50
    //   284: iconst_0
    //   285: bastore
    //   286: dup
    //   287: bipush #51
    //   289: iconst_0
    //   290: bastore
    //   291: dup
    //   292: bipush #52
    //   294: iconst_0
    //   295: bastore
    //   296: dup
    //   297: bipush #53
    //   299: iconst_0
    //   300: bastore
    //   301: dup
    //   302: bipush #54
    //   304: iconst_0
    //   305: bastore
    //   306: dup
    //   307: bipush #55
    //   309: iconst_0
    //   310: bastore
    //   311: dup
    //   312: bipush #56
    //   314: iconst_0
    //   315: bastore
    //   316: dup
    //   317: bipush #57
    //   319: iconst_0
    //   320: bastore
    //   321: dup
    //   322: bipush #58
    //   324: iconst_0
    //   325: bastore
    //   326: dup
    //   327: bipush #59
    //   329: iconst_0
    //   330: bastore
    //   331: dup
    //   332: bipush #60
    //   334: iconst_0
    //   335: bastore
    //   336: dup
    //   337: bipush #61
    //   339: iconst_0
    //   340: bastore
    //   341: dup
    //   342: bipush #62
    //   344: iconst_0
    //   345: bastore
    //   346: dup
    //   347: bipush #63
    //   349: iconst_0
    //   350: bastore
    //   351: astore #5
    //   353: bipush #64
    //   355: newarray int
    //   357: dup
    //   358: iconst_0
    //   359: ldc 1116352408
    //   361: iastore
    //   362: dup
    //   363: iconst_1
    //   364: ldc 1899447441
    //   366: iastore
    //   367: dup
    //   368: iconst_2
    //   369: ldc -1245643825
    //   371: iastore
    //   372: dup
    //   373: iconst_3
    //   374: ldc -373957723
    //   376: iastore
    //   377: dup
    //   378: iconst_4
    //   379: ldc 961987163
    //   381: iastore
    //   382: dup
    //   383: iconst_5
    //   384: ldc 1508970993
    //   386: iastore
    //   387: dup
    //   388: bipush #6
    //   390: ldc -1841331548
    //   392: iastore
    //   393: dup
    //   394: bipush #7
    //   396: ldc -1424204075
    //   398: iastore
    //   399: dup
    //   400: bipush #8
    //   402: ldc -670586216
    //   404: iastore
    //   405: dup
    //   406: bipush #9
    //   408: ldc 310598401
    //   410: iastore
    //   411: dup
    //   412: bipush #10
    //   414: ldc 607225278
    //   416: iastore
    //   417: dup
    //   418: bipush #11
    //   420: ldc 1426881987
    //   422: iastore
    //   423: dup
    //   424: bipush #12
    //   426: ldc 1925078388
    //   428: iastore
    //   429: dup
    //   430: bipush #13
    //   432: ldc -2132889090
    //   434: iastore
    //   435: dup
    //   436: bipush #14
    //   438: ldc -1680079193
    //   440: iastore
    //   441: dup
    //   442: bipush #15
    //   444: ldc -1046744716
    //   446: iastore
    //   447: dup
    //   448: bipush #16
    //   450: ldc -459576895
    //   452: iastore
    //   453: dup
    //   454: bipush #17
    //   456: ldc -272742522
    //   458: iastore
    //   459: dup
    //   460: bipush #18
    //   462: ldc 264347078
    //   464: iastore
    //   465: dup
    //   466: bipush #19
    //   468: ldc 604807628
    //   470: iastore
    //   471: dup
    //   472: bipush #20
    //   474: ldc 770255983
    //   476: iastore
    //   477: dup
    //   478: bipush #21
    //   480: ldc 1249150122
    //   482: iastore
    //   483: dup
    //   484: bipush #22
    //   486: ldc 1555081692
    //   488: iastore
    //   489: dup
    //   490: bipush #23
    //   492: ldc 1996064986
    //   494: iastore
    //   495: dup
    //   496: bipush #24
    //   498: ldc -1740746414
    //   500: iastore
    //   501: dup
    //   502: bipush #25
    //   504: ldc -1473132947
    //   506: iastore
    //   507: dup
    //   508: bipush #26
    //   510: ldc -1341970488
    //   512: iastore
    //   513: dup
    //   514: bipush #27
    //   516: ldc -1084653625
    //   518: iastore
    //   519: dup
    //   520: bipush #28
    //   522: ldc -958395405
    //   524: iastore
    //   525: dup
    //   526: bipush #29
    //   528: ldc -710438585
    //   530: iastore
    //   531: dup
    //   532: bipush #30
    //   534: ldc 113926993
    //   536: iastore
    //   537: dup
    //   538: bipush #31
    //   540: ldc 338241895
    //   542: iastore
    //   543: dup
    //   544: bipush #32
    //   546: ldc 666307205
    //   548: iastore
    //   549: dup
    //   550: bipush #33
    //   552: ldc 773529912
    //   554: iastore
    //   555: dup
    //   556: bipush #34
    //   558: ldc 1294757372
    //   560: iastore
    //   561: dup
    //   562: bipush #35
    //   564: ldc 1396182291
    //   566: iastore
    //   567: dup
    //   568: bipush #36
    //   570: ldc 1695183700
    //   572: iastore
    //   573: dup
    //   574: bipush #37
    //   576: ldc 1986661051
    //   578: iastore
    //   579: dup
    //   580: bipush #38
    //   582: ldc -2117940946
    //   584: iastore
    //   585: dup
    //   586: bipush #39
    //   588: ldc -1838011259
    //   590: iastore
    //   591: dup
    //   592: bipush #40
    //   594: ldc -1564481375
    //   596: iastore
    //   597: dup
    //   598: bipush #41
    //   600: ldc -1474664885
    //   602: iastore
    //   603: dup
    //   604: bipush #42
    //   606: ldc -1035236496
    //   608: iastore
    //   609: dup
    //   610: bipush #43
    //   612: ldc -949202525
    //   614: iastore
    //   615: dup
    //   616: bipush #44
    //   618: ldc -778901479
    //   620: iastore
    //   621: dup
    //   622: bipush #45
    //   624: ldc -694614492
    //   626: iastore
    //   627: dup
    //   628: bipush #46
    //   630: ldc -200395387
    //   632: iastore
    //   633: dup
    //   634: bipush #47
    //   636: ldc 275423344
    //   638: iastore
    //   639: dup
    //   640: bipush #48
    //   642: ldc 430227734
    //   644: iastore
    //   645: dup
    //   646: bipush #49
    //   648: ldc 506948616
    //   650: iastore
    //   651: dup
    //   652: bipush #50
    //   654: ldc 659060556
    //   656: iastore
    //   657: dup
    //   658: bipush #51
    //   660: ldc 883997877
    //   662: iastore
    //   663: dup
    //   664: bipush #52
    //   666: ldc 958139571
    //   668: iastore
    //   669: dup
    //   670: bipush #53
    //   672: ldc 1322822218
    //   674: iastore
    //   675: dup
    //   676: bipush #54
    //   678: ldc 1537002063
    //   680: iastore
    //   681: dup
    //   682: bipush #55
    //   684: ldc 1747873779
    //   686: iastore
    //   687: dup
    //   688: bipush #56
    //   690: ldc 1955562222
    //   692: iastore
    //   693: dup
    //   694: bipush #57
    //   696: ldc 2024104815
    //   698: iastore
    //   699: dup
    //   700: bipush #58
    //   702: ldc -2067236844
    //   704: iastore
    //   705: dup
    //   706: bipush #59
    //   708: ldc -1933114872
    //   710: iastore
    //   711: dup
    //   712: bipush #60
    //   714: ldc -1866530822
    //   716: iastore
    //   717: dup
    //   718: bipush #61
    //   720: ldc -1538233109
    //   722: iastore
    //   723: dup
    //   724: bipush #62
    //   726: ldc -1090935817
    //   728: iastore
    //   729: dup
    //   730: bipush #63
    //   732: ldc -965641998
    //   734: iastore
    //   735: astore #6
    //   737: iconst_2
    //   738: newarray int
    //   740: dup
    //   741: iconst_0
    //   742: iconst_0
    //   743: iastore
    //   744: dup
    //   745: iconst_1
    //   746: iconst_0
    //   747: iastore
    //   748: astore #7
    //   750: bipush #8
    //   752: newarray int
    //   754: dup
    //   755: iconst_0
    //   756: ldc 1779033703
    //   758: iastore
    //   759: dup
    //   760: iconst_1
    //   761: ldc -1150833019
    //   763: iastore
    //   764: dup
    //   765: iconst_2
    //   766: ldc 1013904242
    //   768: iastore
    //   769: dup
    //   770: iconst_3
    //   771: ldc -1521486534
    //   773: iastore
    //   774: dup
    //   775: iconst_4
    //   776: ldc 1359893119
    //   778: iastore
    //   779: dup
    //   780: iconst_5
    //   781: ldc -1694144372
    //   783: iastore
    //   784: dup
    //   785: bipush #6
    //   787: ldc 528734635
    //   789: iastore
    //   790: dup
    //   791: bipush #7
    //   793: ldc 1541459225
    //   795: iastore
    //   796: astore #8
    //   798: bipush #64
    //   800: newarray byte
    //   802: astore #9
    //   804: bipush #64
    //   806: newarray byte
    //   808: astore #10
    //   810: aload_3
    //   811: arraylength
    //   812: istore #11
    //   814: aload #7
    //   816: iconst_0
    //   817: iaload
    //   818: bipush #63
    //   820: iand
    //   821: istore #12
    //   823: aload #7
    //   825: iconst_0
    //   826: dup2
    //   827: iaload
    //   828: iload #11
    //   830: iadd
    //   831: iastore
    //   832: aload #7
    //   834: iconst_0
    //   835: dup2
    //   836: iaload
    //   837: iconst_m1
    //   838: iand
    //   839: iastore
    //   840: aload #7
    //   842: iconst_0
    //   843: iaload
    //   844: iload #11
    //   846: if_icmpge -> 864
    //   849: aload #7
    //   851: iconst_1
    //   852: dup2
    //   853: iaload
    //   854: iconst_1
    //   855: iadd
    //   856: iastore
    //   857: goto -> 864
    //   860: invokestatic a : (Ljava/lang/Throwable;)Ljava/lang/Throwable;
    //   863: athrow
    //   864: iconst_0
    //   865: istore #13
    //   867: iload #11
    //   869: bipush #64
    //   871: if_icmplt -> 1480
    //   874: iconst_0
    //   875: istore #14
    //   877: iload #14
    //   879: bipush #64
    //   881: if_icmpge -> 903
    //   884: aload #10
    //   886: iload #14
    //   888: aload_3
    //   889: iload #13
    //   891: iload #14
    //   893: iadd
    //   894: baload
    //   895: bastore
    //   896: iinc #14, 1
    //   899: iload_2
    //   900: ifeq -> 877
    //   903: bipush #64
    //   905: newarray int
    //   907: astore #14
    //   909: bipush #8
    //   911: newarray int
    //   913: astore #15
    //   915: iconst_0
    //   916: istore #16
    //   918: iload #16
    //   920: bipush #8
    //   922: if_icmpge -> 942
    //   925: aload #15
    //   927: iload #16
    //   929: aload #8
    //   931: iload #16
    //   933: iaload
    //   934: iastore
    //   935: iinc #16, 1
    //   938: iload_2
    //   939: ifeq -> 918
    //   942: iconst_0
    //   943: istore #16
    //   945: iload #16
    //   947: bipush #64
    //   949: if_icmpge -> 1440
    //   952: iload #16
    //   954: bipush #16
    //   956: if_icmpge -> 1037
    //   959: aload #14
    //   961: iload #16
    //   963: aload #10
    //   965: iconst_4
    //   966: iload #16
    //   968: imul
    //   969: baload
    //   970: sipush #255
    //   973: iand
    //   974: bipush #24
    //   976: ishl
    //   977: aload #10
    //   979: iconst_4
    //   980: iload #16
    //   982: imul
    //   983: iconst_1
    //   984: iadd
    //   985: baload
    //   986: sipush #255
    //   989: iand
    //   990: bipush #16
    //   992: ishl
    //   993: ior
    //   994: aload #10
    //   996: iconst_4
    //   997: iload #16
    //   999: imul
    //   1000: iconst_2
    //   1001: iadd
    //   1002: baload
    //   1003: sipush #255
    //   1006: iand
    //   1007: bipush #8
    //   1009: ishl
    //   1010: ior
    //   1011: aload #10
    //   1013: iconst_4
    //   1014: iload #16
    //   1016: imul
    //   1017: iconst_3
    //   1018: iadd
    //   1019: baload
    //   1020: sipush #255
    //   1023: iand
    //   1024: ior
    //   1025: iastore
    //   1026: iload_2
    //   1027: ifeq -> 1180
    //   1030: goto -> 1037
    //   1033: invokestatic a : (Ljava/lang/Throwable;)Ljava/lang/Throwable;
    //   1036: athrow
    //   1037: aload #14
    //   1039: iload #16
    //   1041: aload #14
    //   1043: iload #16
    //   1045: iconst_2
    //   1046: isub
    //   1047: iaload
    //   1048: bipush #17
    //   1050: iushr
    //   1051: aload #14
    //   1053: iload #16
    //   1055: iconst_2
    //   1056: isub
    //   1057: iaload
    //   1058: bipush #15
    //   1060: ishl
    //   1061: ior
    //   1062: aload #14
    //   1064: iload #16
    //   1066: iconst_2
    //   1067: isub
    //   1068: iaload
    //   1069: bipush #19
    //   1071: iushr
    //   1072: aload #14
    //   1074: iload #16
    //   1076: iconst_2
    //   1077: isub
    //   1078: iaload
    //   1079: bipush #13
    //   1081: ishl
    //   1082: ior
    //   1083: ixor
    //   1084: aload #14
    //   1086: iload #16
    //   1088: iconst_2
    //   1089: isub
    //   1090: iaload
    //   1091: bipush #10
    //   1093: iushr
    //   1094: ixor
    //   1095: aload #14
    //   1097: iload #16
    //   1099: bipush #7
    //   1101: isub
    //   1102: iaload
    //   1103: iadd
    //   1104: aload #14
    //   1106: iload #16
    //   1108: bipush #15
    //   1110: isub
    //   1111: iaload
    //   1112: bipush #7
    //   1114: iushr
    //   1115: aload #14
    //   1117: iload #16
    //   1119: bipush #15
    //   1121: isub
    //   1122: iaload
    //   1123: bipush #25
    //   1125: ishl
    //   1126: ior
    //   1127: aload #14
    //   1129: iload #16
    //   1131: bipush #15
    //   1133: isub
    //   1134: iaload
    //   1135: bipush #18
    //   1137: iushr
    //   1138: aload #14
    //   1140: iload #16
    //   1142: bipush #15
    //   1144: isub
    //   1145: iaload
    //   1146: bipush #14
    //   1148: ishl
    //   1149: ior
    //   1150: ixor
    //   1151: aload #14
    //   1153: iload #16
    //   1155: bipush #15
    //   1157: isub
    //   1158: iaload
    //   1159: iconst_3
    //   1160: iushr
    //   1161: ixor
    //   1162: iadd
    //   1163: aload #14
    //   1165: iload #16
    //   1167: bipush #16
    //   1169: isub
    //   1170: iaload
    //   1171: iadd
    //   1172: iastore
    //   1173: goto -> 1180
    //   1176: invokestatic a : (Ljava/lang/Throwable;)Ljava/lang/Throwable;
    //   1179: athrow
    //   1180: aload #15
    //   1182: bipush #7
    //   1184: iaload
    //   1185: aload #15
    //   1187: iconst_4
    //   1188: iaload
    //   1189: bipush #6
    //   1191: iushr
    //   1192: aload #15
    //   1194: iconst_4
    //   1195: iaload
    //   1196: bipush #26
    //   1198: ishl
    //   1199: ior
    //   1200: aload #15
    //   1202: iconst_4
    //   1203: iaload
    //   1204: bipush #11
    //   1206: iushr
    //   1207: aload #15
    //   1209: iconst_4
    //   1210: iaload
    //   1211: bipush #21
    //   1213: ishl
    //   1214: ior
    //   1215: ixor
    //   1216: aload #15
    //   1218: iconst_4
    //   1219: iaload
    //   1220: bipush #25
    //   1222: iushr
    //   1223: aload #15
    //   1225: iconst_4
    //   1226: iaload
    //   1227: bipush #7
    //   1229: ishl
    //   1230: ior
    //   1231: ixor
    //   1232: iadd
    //   1233: aload #15
    //   1235: bipush #6
    //   1237: iaload
    //   1238: aload #15
    //   1240: iconst_4
    //   1241: iaload
    //   1242: aload #15
    //   1244: iconst_5
    //   1245: iaload
    //   1246: aload #15
    //   1248: bipush #6
    //   1250: iaload
    //   1251: ixor
    //   1252: iand
    //   1253: ixor
    //   1254: iadd
    //   1255: aload #6
    //   1257: iload #16
    //   1259: iaload
    //   1260: iadd
    //   1261: aload #14
    //   1263: iload #16
    //   1265: iaload
    //   1266: iadd
    //   1267: istore #17
    //   1269: aload #15
    //   1271: iconst_0
    //   1272: iaload
    //   1273: iconst_2
    //   1274: iushr
    //   1275: aload #15
    //   1277: iconst_0
    //   1278: iaload
    //   1279: bipush #30
    //   1281: ishl
    //   1282: ior
    //   1283: aload #15
    //   1285: iconst_0
    //   1286: iaload
    //   1287: bipush #13
    //   1289: iushr
    //   1290: aload #15
    //   1292: iconst_0
    //   1293: iaload
    //   1294: bipush #19
    //   1296: ishl
    //   1297: ior
    //   1298: ixor
    //   1299: aload #15
    //   1301: iconst_0
    //   1302: iaload
    //   1303: bipush #22
    //   1305: iushr
    //   1306: aload #15
    //   1308: iconst_0
    //   1309: iaload
    //   1310: bipush #10
    //   1312: ishl
    //   1313: ior
    //   1314: ixor
    //   1315: aload #15
    //   1317: iconst_0
    //   1318: iaload
    //   1319: aload #15
    //   1321: iconst_1
    //   1322: iaload
    //   1323: iand
    //   1324: aload #15
    //   1326: iconst_2
    //   1327: iaload
    //   1328: aload #15
    //   1330: iconst_0
    //   1331: iaload
    //   1332: aload #15
    //   1334: iconst_1
    //   1335: iaload
    //   1336: ior
    //   1337: iand
    //   1338: ior
    //   1339: iadd
    //   1340: istore #18
    //   1342: aload #15
    //   1344: iconst_3
    //   1345: dup2
    //   1346: iaload
    //   1347: iload #17
    //   1349: iadd
    //   1350: iastore
    //   1351: aload #15
    //   1353: bipush #7
    //   1355: iload #17
    //   1357: iload #18
    //   1359: iadd
    //   1360: iastore
    //   1361: aload #15
    //   1363: bipush #7
    //   1365: iaload
    //   1366: istore #17
    //   1368: aload #15
    //   1370: bipush #7
    //   1372: aload #15
    //   1374: bipush #6
    //   1376: iaload
    //   1377: iastore
    //   1378: aload #15
    //   1380: bipush #6
    //   1382: aload #15
    //   1384: iconst_5
    //   1385: iaload
    //   1386: iastore
    //   1387: aload #15
    //   1389: iconst_5
    //   1390: aload #15
    //   1392: iconst_4
    //   1393: iaload
    //   1394: iastore
    //   1395: aload #15
    //   1397: iconst_4
    //   1398: aload #15
    //   1400: iconst_3
    //   1401: iaload
    //   1402: iastore
    //   1403: aload #15
    //   1405: iconst_3
    //   1406: aload #15
    //   1408: iconst_2
    //   1409: iaload
    //   1410: iastore
    //   1411: aload #15
    //   1413: iconst_2
    //   1414: aload #15
    //   1416: iconst_1
    //   1417: iaload
    //   1418: iastore
    //   1419: aload #15
    //   1421: iconst_1
    //   1422: aload #15
    //   1424: iconst_0
    //   1425: iaload
    //   1426: iastore
    //   1427: aload #15
    //   1429: iconst_0
    //   1430: iload #17
    //   1432: iastore
    //   1433: iinc #16, 1
    //   1436: iload_2
    //   1437: ifeq -> 945
    //   1440: iconst_0
    //   1441: istore #16
    //   1443: iload #16
    //   1445: bipush #8
    //   1447: if_icmpge -> 1470
    //   1450: aload #8
    //   1452: iload #16
    //   1454: dup2
    //   1455: iaload
    //   1456: aload #15
    //   1458: iload #16
    //   1460: iaload
    //   1461: iadd
    //   1462: iastore
    //   1463: iinc #16, 1
    //   1466: iload_2
    //   1467: ifeq -> 1443
    //   1470: iinc #13, 64
    //   1473: iinc #11, -64
    //   1476: iload_2
    //   1477: ifeq -> 867
    //   1480: iload #11
    //   1482: ifle -> 1517
    //   1485: iconst_0
    //   1486: istore #14
    //   1488: iload #14
    //   1490: iload #11
    //   1492: if_icmpge -> 1517
    //   1495: aload #9
    //   1497: iload #12
    //   1499: iload #14
    //   1501: iadd
    //   1502: aload_3
    //   1503: iload #13
    //   1505: iload #14
    //   1507: iadd
    //   1508: baload
    //   1509: bastore
    //   1510: iinc #14, 1
    //   1513: iload_2
    //   1514: ifeq -> 1488
    //   1517: aload #7
    //   1519: iconst_0
    //   1520: iaload
    //   1521: bipush #29
    //   1523: iushr
    //   1524: aload #7
    //   1526: iconst_1
    //   1527: iaload
    //   1528: iconst_3
    //   1529: ishl
    //   1530: ior
    //   1531: istore #14
    //   1533: aload #7
    //   1535: iconst_0
    //   1536: iaload
    //   1537: iconst_3
    //   1538: ishl
    //   1539: istore #15
    //   1541: aload #7
    //   1543: iconst_0
    //   1544: iaload
    //   1545: bipush #63
    //   1547: iand
    //   1548: istore #16
    //   1550: iload #16
    //   1552: bipush #56
    //   1554: if_icmpge -> 1569
    //   1557: bipush #56
    //   1559: iload #16
    //   1561: isub
    //   1562: goto -> 1574
    //   1565: invokestatic a : (Ljava/lang/Throwable;)Ljava/lang/Throwable;
    //   1568: athrow
    //   1569: bipush #120
    //   1571: iload #16
    //   1573: isub
    //   1574: istore #17
    //   1576: aload #7
    //   1578: iconst_0
    //   1579: iaload
    //   1580: bipush #63
    //   1582: iand
    //   1583: istore #12
    //   1585: bipush #64
    //   1587: iload #12
    //   1589: isub
    //   1590: istore #18
    //   1592: aload #7
    //   1594: iconst_0
    //   1595: dup2
    //   1596: iaload
    //   1597: iload #17
    //   1599: iadd
    //   1600: iastore
    //   1601: aload #7
    //   1603: iconst_0
    //   1604: dup2
    //   1605: iaload
    //   1606: iconst_m1
    //   1607: iand
    //   1608: iastore
    //   1609: aload #7
    //   1611: iconst_0
    //   1612: iaload
    //   1613: iload #17
    //   1615: if_icmpge -> 1633
    //   1618: aload #7
    //   1620: iconst_1
    //   1621: dup2
    //   1622: iaload
    //   1623: iconst_1
    //   1624: iadd
    //   1625: iastore
    //   1626: goto -> 1633
    //   1629: invokestatic a : (Ljava/lang/Throwable;)Ljava/lang/Throwable;
    //   1632: athrow
    //   1633: iconst_0
    //   1634: istore #13
    //   1636: iload #12
    //   1638: ifle -> 2269
    //   1641: iload #17
    //   1643: iload #18
    //   1645: if_icmplt -> 2269
    //   1648: goto -> 1655
    //   1651: invokestatic a : (Ljava/lang/Throwable;)Ljava/lang/Throwable;
    //   1654: athrow
    //   1655: iconst_0
    //   1656: istore #19
    //   1658: iload #19
    //   1660: iload #18
    //   1662: if_icmpge -> 1685
    //   1665: aload #9
    //   1667: iload #12
    //   1669: iload #19
    //   1671: iadd
    //   1672: aload #5
    //   1674: iload #19
    //   1676: baload
    //   1677: bastore
    //   1678: iinc #19, 1
    //   1681: iload_2
    //   1682: ifeq -> 1658
    //   1685: bipush #64
    //   1687: newarray int
    //   1689: astore #19
    //   1691: bipush #8
    //   1693: newarray int
    //   1695: astore #20
    //   1697: iconst_0
    //   1698: istore #21
    //   1700: iload #21
    //   1702: bipush #8
    //   1704: if_icmpge -> 1724
    //   1707: aload #20
    //   1709: iload #21
    //   1711: aload #8
    //   1713: iload #21
    //   1715: iaload
    //   1716: iastore
    //   1717: iinc #21, 1
    //   1720: iload_2
    //   1721: ifeq -> 1700
    //   1724: iconst_0
    //   1725: istore #21
    //   1727: iload #21
    //   1729: bipush #64
    //   1731: if_icmpge -> 2222
    //   1734: iload #21
    //   1736: bipush #16
    //   1738: if_icmpge -> 1819
    //   1741: aload #19
    //   1743: iload #21
    //   1745: aload #9
    //   1747: iconst_4
    //   1748: iload #21
    //   1750: imul
    //   1751: baload
    //   1752: sipush #255
    //   1755: iand
    //   1756: bipush #24
    //   1758: ishl
    //   1759: aload #9
    //   1761: iconst_4
    //   1762: iload #21
    //   1764: imul
    //   1765: iconst_1
    //   1766: iadd
    //   1767: baload
    //   1768: sipush #255
    //   1771: iand
    //   1772: bipush #16
    //   1774: ishl
    //   1775: ior
    //   1776: aload #9
    //   1778: iconst_4
    //   1779: iload #21
    //   1781: imul
    //   1782: iconst_2
    //   1783: iadd
    //   1784: baload
    //   1785: sipush #255
    //   1788: iand
    //   1789: bipush #8
    //   1791: ishl
    //   1792: ior
    //   1793: aload #9
    //   1795: iconst_4
    //   1796: iload #21
    //   1798: imul
    //   1799: iconst_3
    //   1800: iadd
    //   1801: baload
    //   1802: sipush #255
    //   1805: iand
    //   1806: ior
    //   1807: iastore
    //   1808: iload_2
    //   1809: ifeq -> 1962
    //   1812: goto -> 1819
    //   1815: invokestatic a : (Ljava/lang/Throwable;)Ljava/lang/Throwable;
    //   1818: athrow
    //   1819: aload #19
    //   1821: iload #21
    //   1823: aload #19
    //   1825: iload #21
    //   1827: iconst_2
    //   1828: isub
    //   1829: iaload
    //   1830: bipush #17
    //   1832: iushr
    //   1833: aload #19
    //   1835: iload #21
    //   1837: iconst_2
    //   1838: isub
    //   1839: iaload
    //   1840: bipush #15
    //   1842: ishl
    //   1843: ior
    //   1844: aload #19
    //   1846: iload #21
    //   1848: iconst_2
    //   1849: isub
    //   1850: iaload
    //   1851: bipush #19
    //   1853: iushr
    //   1854: aload #19
    //   1856: iload #21
    //   1858: iconst_2
    //   1859: isub
    //   1860: iaload
    //   1861: bipush #13
    //   1863: ishl
    //   1864: ior
    //   1865: ixor
    //   1866: aload #19
    //   1868: iload #21
    //   1870: iconst_2
    //   1871: isub
    //   1872: iaload
    //   1873: bipush #10
    //   1875: iushr
    //   1876: ixor
    //   1877: aload #19
    //   1879: iload #21
    //   1881: bipush #7
    //   1883: isub
    //   1884: iaload
    //   1885: iadd
    //   1886: aload #19
    //   1888: iload #21
    //   1890: bipush #15
    //   1892: isub
    //   1893: iaload
    //   1894: bipush #7
    //   1896: iushr
    //   1897: aload #19
    //   1899: iload #21
    //   1901: bipush #15
    //   1903: isub
    //   1904: iaload
    //   1905: bipush #25
    //   1907: ishl
    //   1908: ior
    //   1909: aload #19
    //   1911: iload #21
    //   1913: bipush #15
    //   1915: isub
    //   1916: iaload
    //   1917: bipush #18
    //   1919: iushr
    //   1920: aload #19
    //   1922: iload #21
    //   1924: bipush #15
    //   1926: isub
    //   1927: iaload
    //   1928: bipush #14
    //   1930: ishl
    //   1931: ior
    //   1932: ixor
    //   1933: aload #19
    //   1935: iload #21
    //   1937: bipush #15
    //   1939: isub
    //   1940: iaload
    //   1941: iconst_3
    //   1942: iushr
    //   1943: ixor
    //   1944: iadd
    //   1945: aload #19
    //   1947: iload #21
    //   1949: bipush #16
    //   1951: isub
    //   1952: iaload
    //   1953: iadd
    //   1954: iastore
    //   1955: goto -> 1962
    //   1958: invokestatic a : (Ljava/lang/Throwable;)Ljava/lang/Throwable;
    //   1961: athrow
    //   1962: aload #20
    //   1964: bipush #7
    //   1966: iaload
    //   1967: aload #20
    //   1969: iconst_4
    //   1970: iaload
    //   1971: bipush #6
    //   1973: iushr
    //   1974: aload #20
    //   1976: iconst_4
    //   1977: iaload
    //   1978: bipush #26
    //   1980: ishl
    //   1981: ior
    //   1982: aload #20
    //   1984: iconst_4
    //   1985: iaload
    //   1986: bipush #11
    //   1988: iushr
    //   1989: aload #20
    //   1991: iconst_4
    //   1992: iaload
    //   1993: bipush #21
    //   1995: ishl
    //   1996: ior
    //   1997: ixor
    //   1998: aload #20
    //   2000: iconst_4
    //   2001: iaload
    //   2002: bipush #25
    //   2004: iushr
    //   2005: aload #20
    //   2007: iconst_4
    //   2008: iaload
    //   2009: bipush #7
    //   2011: ishl
    //   2012: ior
    //   2013: ixor
    //   2014: iadd
    //   2015: aload #20
    //   2017: bipush #6
    //   2019: iaload
    //   2020: aload #20
    //   2022: iconst_4
    //   2023: iaload
    //   2024: aload #20
    //   2026: iconst_5
    //   2027: iaload
    //   2028: aload #20
    //   2030: bipush #6
    //   2032: iaload
    //   2033: ixor
    //   2034: iand
    //   2035: ixor
    //   2036: iadd
    //   2037: aload #6
    //   2039: iload #21
    //   2041: iaload
    //   2042: iadd
    //   2043: aload #19
    //   2045: iload #21
    //   2047: iaload
    //   2048: iadd
    //   2049: istore #22
    //   2051: aload #20
    //   2053: iconst_0
    //   2054: iaload
    //   2055: iconst_2
    //   2056: iushr
    //   2057: aload #20
    //   2059: iconst_0
    //   2060: iaload
    //   2061: bipush #30
    //   2063: ishl
    //   2064: ior
    //   2065: aload #20
    //   2067: iconst_0
    //   2068: iaload
    //   2069: bipush #13
    //   2071: iushr
    //   2072: aload #20
    //   2074: iconst_0
    //   2075: iaload
    //   2076: bipush #19
    //   2078: ishl
    //   2079: ior
    //   2080: ixor
    //   2081: aload #20
    //   2083: iconst_0
    //   2084: iaload
    //   2085: bipush #22
    //   2087: iushr
    //   2088: aload #20
    //   2090: iconst_0
    //   2091: iaload
    //   2092: bipush #10
    //   2094: ishl
    //   2095: ior
    //   2096: ixor
    //   2097: aload #20
    //   2099: iconst_0
    //   2100: iaload
    //   2101: aload #20
    //   2103: iconst_1
    //   2104: iaload
    //   2105: iand
    //   2106: aload #20
    //   2108: iconst_2
    //   2109: iaload
    //   2110: aload #20
    //   2112: iconst_0
    //   2113: iaload
    //   2114: aload #20
    //   2116: iconst_1
    //   2117: iaload
    //   2118: ior
    //   2119: iand
    //   2120: ior
    //   2121: iadd
    //   2122: istore #23
    //   2124: aload #20
    //   2126: iconst_3
    //   2127: dup2
    //   2128: iaload
    //   2129: iload #22
    //   2131: iadd
    //   2132: iastore
    //   2133: aload #20
    //   2135: bipush #7
    //   2137: iload #22
    //   2139: iload #23
    //   2141: iadd
    //   2142: iastore
    //   2143: aload #20
    //   2145: bipush #7
    //   2147: iaload
    //   2148: istore #22
    //   2150: aload #20
    //   2152: bipush #7
    //   2154: aload #20
    //   2156: bipush #6
    //   2158: iaload
    //   2159: iastore
    //   2160: aload #20
    //   2162: bipush #6
    //   2164: aload #20
    //   2166: iconst_5
    //   2167: iaload
    //   2168: iastore
    //   2169: aload #20
    //   2171: iconst_5
    //   2172: aload #20
    //   2174: iconst_4
    //   2175: iaload
    //   2176: iastore
    //   2177: aload #20
    //   2179: iconst_4
    //   2180: aload #20
    //   2182: iconst_3
    //   2183: iaload
    //   2184: iastore
    //   2185: aload #20
    //   2187: iconst_3
    //   2188: aload #20
    //   2190: iconst_2
    //   2191: iaload
    //   2192: iastore
    //   2193: aload #20
    //   2195: iconst_2
    //   2196: aload #20
    //   2198: iconst_1
    //   2199: iaload
    //   2200: iastore
    //   2201: aload #20
    //   2203: iconst_1
    //   2204: aload #20
    //   2206: iconst_0
    //   2207: iaload
    //   2208: iastore
    //   2209: aload #20
    //   2211: iconst_0
    //   2212: iload #22
    //   2214: iastore
    //   2215: iinc #21, 1
    //   2218: iload_2
    //   2219: ifeq -> 1727
    //   2222: iconst_0
    //   2223: istore #21
    //   2225: iload #21
    //   2227: bipush #8
    //   2229: if_icmpge -> 2252
    //   2232: aload #8
    //   2234: iload #21
    //   2236: dup2
    //   2237: iaload
    //   2238: aload #20
    //   2240: iload #21
    //   2242: iaload
    //   2243: iadd
    //   2244: iastore
    //   2245: iinc #21, 1
    //   2248: iload_2
    //   2249: ifeq -> 2225
    //   2252: iload #13
    //   2254: iload #18
    //   2256: iadd
    //   2257: istore #13
    //   2259: iload #17
    //   2261: iload #18
    //   2263: isub
    //   2264: istore #17
    //   2266: iconst_0
    //   2267: istore #12
    //   2269: iload #17
    //   2271: bipush #64
    //   2273: if_icmplt -> 2883
    //   2276: iconst_0
    //   2277: istore #19
    //   2279: iload #19
    //   2281: bipush #64
    //   2283: if_icmpge -> 2306
    //   2286: aload #10
    //   2288: iload #19
    //   2290: aload #5
    //   2292: iload #13
    //   2294: iload #19
    //   2296: iadd
    //   2297: baload
    //   2298: bastore
    //   2299: iinc #19, 1
    //   2302: iload_2
    //   2303: ifeq -> 2279
    //   2306: bipush #64
    //   2308: newarray int
    //   2310: astore #19
    //   2312: bipush #8
    //   2314: newarray int
    //   2316: astore #20
    //   2318: iconst_0
    //   2319: istore #21
    //   2321: iload #21
    //   2323: bipush #8
    //   2325: if_icmpge -> 2345
    //   2328: aload #20
    //   2330: iload #21
    //   2332: aload #8
    //   2334: iload #21
    //   2336: iaload
    //   2337: iastore
    //   2338: iinc #21, 1
    //   2341: iload_2
    //   2342: ifeq -> 2321
    //   2345: iconst_0
    //   2346: istore #21
    //   2348: iload #21
    //   2350: bipush #64
    //   2352: if_icmpge -> 2843
    //   2355: iload #21
    //   2357: bipush #16
    //   2359: if_icmpge -> 2440
    //   2362: aload #19
    //   2364: iload #21
    //   2366: aload #10
    //   2368: iconst_4
    //   2369: iload #21
    //   2371: imul
    //   2372: baload
    //   2373: sipush #255
    //   2376: iand
    //   2377: bipush #24
    //   2379: ishl
    //   2380: aload #10
    //   2382: iconst_4
    //   2383: iload #21
    //   2385: imul
    //   2386: iconst_1
    //   2387: iadd
    //   2388: baload
    //   2389: sipush #255
    //   2392: iand
    //   2393: bipush #16
    //   2395: ishl
    //   2396: ior
    //   2397: aload #10
    //   2399: iconst_4
    //   2400: iload #21
    //   2402: imul
    //   2403: iconst_2
    //   2404: iadd
    //   2405: baload
    //   2406: sipush #255
    //   2409: iand
    //   2410: bipush #8
    //   2412: ishl
    //   2413: ior
    //   2414: aload #10
    //   2416: iconst_4
    //   2417: iload #21
    //   2419: imul
    //   2420: iconst_3
    //   2421: iadd
    //   2422: baload
    //   2423: sipush #255
    //   2426: iand
    //   2427: ior
    //   2428: iastore
    //   2429: iload_2
    //   2430: ifeq -> 2583
    //   2433: goto -> 2440
    //   2436: invokestatic a : (Ljava/lang/Throwable;)Ljava/lang/Throwable;
    //   2439: athrow
    //   2440: aload #19
    //   2442: iload #21
    //   2444: aload #19
    //   2446: iload #21
    //   2448: iconst_2
    //   2449: isub
    //   2450: iaload
    //   2451: bipush #17
    //   2453: iushr
    //   2454: aload #19
    //   2456: iload #21
    //   2458: iconst_2
    //   2459: isub
    //   2460: iaload
    //   2461: bipush #15
    //   2463: ishl
    //   2464: ior
    //   2465: aload #19
    //   2467: iload #21
    //   2469: iconst_2
    //   2470: isub
    //   2471: iaload
    //   2472: bipush #19
    //   2474: iushr
    //   2475: aload #19
    //   2477: iload #21
    //   2479: iconst_2
    //   2480: isub
    //   2481: iaload
    //   2482: bipush #13
    //   2484: ishl
    //   2485: ior
    //   2486: ixor
    //   2487: aload #19
    //   2489: iload #21
    //   2491: iconst_2
    //   2492: isub
    //   2493: iaload
    //   2494: bipush #10
    //   2496: iushr
    //   2497: ixor
    //   2498: aload #19
    //   2500: iload #21
    //   2502: bipush #7
    //   2504: isub
    //   2505: iaload
    //   2506: iadd
    //   2507: aload #19
    //   2509: iload #21
    //   2511: bipush #15
    //   2513: isub
    //   2514: iaload
    //   2515: bipush #7
    //   2517: iushr
    //   2518: aload #19
    //   2520: iload #21
    //   2522: bipush #15
    //   2524: isub
    //   2525: iaload
    //   2526: bipush #25
    //   2528: ishl
    //   2529: ior
    //   2530: aload #19
    //   2532: iload #21
    //   2534: bipush #15
    //   2536: isub
    //   2537: iaload
    //   2538: bipush #18
    //   2540: iushr
    //   2541: aload #19
    //   2543: iload #21
    //   2545: bipush #15
    //   2547: isub
    //   2548: iaload
    //   2549: bipush #14
    //   2551: ishl
    //   2552: ior
    //   2553: ixor
    //   2554: aload #19
    //   2556: iload #21
    //   2558: bipush #15
    //   2560: isub
    //   2561: iaload
    //   2562: iconst_3
    //   2563: iushr
    //   2564: ixor
    //   2565: iadd
    //   2566: aload #19
    //   2568: iload #21
    //   2570: bipush #16
    //   2572: isub
    //   2573: iaload
    //   2574: iadd
    //   2575: iastore
    //   2576: goto -> 2583
    //   2579: invokestatic a : (Ljava/lang/Throwable;)Ljava/lang/Throwable;
    //   2582: athrow
    //   2583: aload #20
    //   2585: bipush #7
    //   2587: iaload
    //   2588: aload #20
    //   2590: iconst_4
    //   2591: iaload
    //   2592: bipush #6
    //   2594: iushr
    //   2595: aload #20
    //   2597: iconst_4
    //   2598: iaload
    //   2599: bipush #26
    //   2601: ishl
    //   2602: ior
    //   2603: aload #20
    //   2605: iconst_4
    //   2606: iaload
    //   2607: bipush #11
    //   2609: iushr
    //   2610: aload #20
    //   2612: iconst_4
    //   2613: iaload
    //   2614: bipush #21
    //   2616: ishl
    //   2617: ior
    //   2618: ixor
    //   2619: aload #20
    //   2621: iconst_4
    //   2622: iaload
    //   2623: bipush #25
    //   2625: iushr
    //   2626: aload #20
    //   2628: iconst_4
    //   2629: iaload
    //   2630: bipush #7
    //   2632: ishl
    //   2633: ior
    //   2634: ixor
    //   2635: iadd
    //   2636: aload #20
    //   2638: bipush #6
    //   2640: iaload
    //   2641: aload #20
    //   2643: iconst_4
    //   2644: iaload
    //   2645: aload #20
    //   2647: iconst_5
    //   2648: iaload
    //   2649: aload #20
    //   2651: bipush #6
    //   2653: iaload
    //   2654: ixor
    //   2655: iand
    //   2656: ixor
    //   2657: iadd
    //   2658: aload #6
    //   2660: iload #21
    //   2662: iaload
    //   2663: iadd
    //   2664: aload #19
    //   2666: iload #21
    //   2668: iaload
    //   2669: iadd
    //   2670: istore #22
    //   2672: aload #20
    //   2674: iconst_0
    //   2675: iaload
    //   2676: iconst_2
    //   2677: iushr
    //   2678: aload #20
    //   2680: iconst_0
    //   2681: iaload
    //   2682: bipush #30
    //   2684: ishl
    //   2685: ior
    //   2686: aload #20
    //   2688: iconst_0
    //   2689: iaload
    //   2690: bipush #13
    //   2692: iushr
    //   2693: aload #20
    //   2695: iconst_0
    //   2696: iaload
    //   2697: bipush #19
    //   2699: ishl
    //   2700: ior
    //   2701: ixor
    //   2702: aload #20
    //   2704: iconst_0
    //   2705: iaload
    //   2706: bipush #22
    //   2708: iushr
    //   2709: aload #20
    //   2711: iconst_0
    //   2712: iaload
    //   2713: bipush #10
    //   2715: ishl
    //   2716: ior
    //   2717: ixor
    //   2718: aload #20
    //   2720: iconst_0
    //   2721: iaload
    //   2722: aload #20
    //   2724: iconst_1
    //   2725: iaload
    //   2726: iand
    //   2727: aload #20
    //   2729: iconst_2
    //   2730: iaload
    //   2731: aload #20
    //   2733: iconst_0
    //   2734: iaload
    //   2735: aload #20
    //   2737: iconst_1
    //   2738: iaload
    //   2739: ior
    //   2740: iand
    //   2741: ior
    //   2742: iadd
    //   2743: istore #23
    //   2745: aload #20
    //   2747: iconst_3
    //   2748: dup2
    //   2749: iaload
    //   2750: iload #22
    //   2752: iadd
    //   2753: iastore
    //   2754: aload #20
    //   2756: bipush #7
    //   2758: iload #22
    //   2760: iload #23
    //   2762: iadd
    //   2763: iastore
    //   2764: aload #20
    //   2766: bipush #7
    //   2768: iaload
    //   2769: istore #22
    //   2771: aload #20
    //   2773: bipush #7
    //   2775: aload #20
    //   2777: bipush #6
    //   2779: iaload
    //   2780: iastore
    //   2781: aload #20
    //   2783: bipush #6
    //   2785: aload #20
    //   2787: iconst_5
    //   2788: iaload
    //   2789: iastore
    //   2790: aload #20
    //   2792: iconst_5
    //   2793: aload #20
    //   2795: iconst_4
    //   2796: iaload
    //   2797: iastore
    //   2798: aload #20
    //   2800: iconst_4
    //   2801: aload #20
    //   2803: iconst_3
    //   2804: iaload
    //   2805: iastore
    //   2806: aload #20
    //   2808: iconst_3
    //   2809: aload #20
    //   2811: iconst_2
    //   2812: iaload
    //   2813: iastore
    //   2814: aload #20
    //   2816: iconst_2
    //   2817: aload #20
    //   2819: iconst_1
    //   2820: iaload
    //   2821: iastore
    //   2822: aload #20
    //   2824: iconst_1
    //   2825: aload #20
    //   2827: iconst_0
    //   2828: iaload
    //   2829: iastore
    //   2830: aload #20
    //   2832: iconst_0
    //   2833: iload #22
    //   2835: iastore
    //   2836: iinc #21, 1
    //   2839: iload_2
    //   2840: ifeq -> 2348
    //   2843: iconst_0
    //   2844: istore #21
    //   2846: iload #21
    //   2848: bipush #8
    //   2850: if_icmpge -> 2873
    //   2853: aload #8
    //   2855: iload #21
    //   2857: dup2
    //   2858: iaload
    //   2859: aload #20
    //   2861: iload #21
    //   2863: iaload
    //   2864: iadd
    //   2865: iastore
    //   2866: iinc #21, 1
    //   2869: iload_2
    //   2870: ifeq -> 2846
    //   2873: iinc #13, 64
    //   2876: iinc #17, -64
    //   2879: iload_2
    //   2880: ifeq -> 2269
    //   2883: iload #17
    //   2885: ifle -> 2921
    //   2888: iconst_0
    //   2889: istore #19
    //   2891: iload #19
    //   2893: iload #17
    //   2895: if_icmpge -> 2921
    //   2898: aload #9
    //   2900: iload #12
    //   2902: iload #19
    //   2904: iadd
    //   2905: aload #5
    //   2907: iload #13
    //   2909: iload #19
    //   2911: iadd
    //   2912: baload
    //   2913: bastore
    //   2914: iinc #19, 1
    //   2917: iload_2
    //   2918: ifeq -> 2891
    //   2921: bipush #8
    //   2923: newarray byte
    //   2925: astore #19
    //   2927: aload #19
    //   2929: iconst_0
    //   2930: iload #14
    //   2932: bipush #24
    //   2934: iushr
    //   2935: i2b
    //   2936: bastore
    //   2937: aload #19
    //   2939: iconst_1
    //   2940: iload #14
    //   2942: bipush #16
    //   2944: iushr
    //   2945: i2b
    //   2946: bastore
    //   2947: aload #19
    //   2949: iconst_2
    //   2950: iload #14
    //   2952: bipush #8
    //   2954: iushr
    //   2955: i2b
    //   2956: bastore
    //   2957: aload #19
    //   2959: iconst_3
    //   2960: iload #14
    //   2962: i2b
    //   2963: bastore
    //   2964: aload #19
    //   2966: iconst_4
    //   2967: iload #15
    //   2969: bipush #24
    //   2971: iushr
    //   2972: i2b
    //   2973: bastore
    //   2974: aload #19
    //   2976: iconst_5
    //   2977: iload #15
    //   2979: bipush #16
    //   2981: iushr
    //   2982: i2b
    //   2983: bastore
    //   2984: aload #19
    //   2986: bipush #6
    //   2988: iload #15
    //   2990: bipush #8
    //   2992: iushr
    //   2993: i2b
    //   2994: bastore
    //   2995: aload #19
    //   2997: bipush #7
    //   2999: iload #15
    //   3001: i2b
    //   3002: bastore
    //   3003: bipush #8
    //   3005: istore #11
    //   3007: aload #7
    //   3009: iconst_0
    //   3010: iaload
    //   3011: bipush #63
    //   3013: iand
    //   3014: istore #12
    //   3016: bipush #64
    //   3018: iload #12
    //   3020: isub
    //   3021: istore #18
    //   3023: aload #7
    //   3025: iconst_0
    //   3026: dup2
    //   3027: iaload
    //   3028: iload #11
    //   3030: iadd
    //   3031: iastore
    //   3032: aload #7
    //   3034: iconst_0
    //   3035: dup2
    //   3036: iaload
    //   3037: iconst_m1
    //   3038: iand
    //   3039: iastore
    //   3040: aload #7
    //   3042: iconst_0
    //   3043: iaload
    //   3044: iload #11
    //   3046: if_icmpge -> 3064
    //   3049: aload #7
    //   3051: iconst_1
    //   3052: dup2
    //   3053: iaload
    //   3054: iconst_1
    //   3055: iadd
    //   3056: iastore
    //   3057: goto -> 3064
    //   3060: invokestatic a : (Ljava/lang/Throwable;)Ljava/lang/Throwable;
    //   3063: athrow
    //   3064: iload #12
    //   3066: ifle -> 3680
    //   3069: iload #11
    //   3071: iload #18
    //   3073: if_icmplt -> 3680
    //   3076: goto -> 3083
    //   3079: invokestatic a : (Ljava/lang/Throwable;)Ljava/lang/Throwable;
    //   3082: athrow
    //   3083: iconst_0
    //   3084: istore #20
    //   3086: iload #20
    //   3088: iload #18
    //   3090: if_icmpge -> 3113
    //   3093: aload #9
    //   3095: iload #12
    //   3097: iload #20
    //   3099: iadd
    //   3100: aload #19
    //   3102: iload #20
    //   3104: baload
    //   3105: bastore
    //   3106: iinc #20, 1
    //   3109: iload_2
    //   3110: ifeq -> 3086
    //   3113: bipush #64
    //   3115: newarray int
    //   3117: astore #20
    //   3119: bipush #8
    //   3121: newarray int
    //   3123: astore #21
    //   3125: iconst_0
    //   3126: istore #22
    //   3128: iload #22
    //   3130: bipush #8
    //   3132: if_icmpge -> 3152
    //   3135: aload #21
    //   3137: iload #22
    //   3139: aload #8
    //   3141: iload #22
    //   3143: iaload
    //   3144: iastore
    //   3145: iinc #22, 1
    //   3148: iload_2
    //   3149: ifeq -> 3128
    //   3152: iconst_0
    //   3153: istore #22
    //   3155: iload #22
    //   3157: bipush #64
    //   3159: if_icmpge -> 3650
    //   3162: iload #22
    //   3164: bipush #16
    //   3166: if_icmpge -> 3247
    //   3169: aload #20
    //   3171: iload #22
    //   3173: aload #9
    //   3175: iconst_4
    //   3176: iload #22
    //   3178: imul
    //   3179: baload
    //   3180: sipush #255
    //   3183: iand
    //   3184: bipush #24
    //   3186: ishl
    //   3187: aload #9
    //   3189: iconst_4
    //   3190: iload #22
    //   3192: imul
    //   3193: iconst_1
    //   3194: iadd
    //   3195: baload
    //   3196: sipush #255
    //   3199: iand
    //   3200: bipush #16
    //   3202: ishl
    //   3203: ior
    //   3204: aload #9
    //   3206: iconst_4
    //   3207: iload #22
    //   3209: imul
    //   3210: iconst_2
    //   3211: iadd
    //   3212: baload
    //   3213: sipush #255
    //   3216: iand
    //   3217: bipush #8
    //   3219: ishl
    //   3220: ior
    //   3221: aload #9
    //   3223: iconst_4
    //   3224: iload #22
    //   3226: imul
    //   3227: iconst_3
    //   3228: iadd
    //   3229: baload
    //   3230: sipush #255
    //   3233: iand
    //   3234: ior
    //   3235: iastore
    //   3236: iload_2
    //   3237: ifeq -> 3390
    //   3240: goto -> 3247
    //   3243: invokestatic a : (Ljava/lang/Throwable;)Ljava/lang/Throwable;
    //   3246: athrow
    //   3247: aload #20
    //   3249: iload #22
    //   3251: aload #20
    //   3253: iload #22
    //   3255: iconst_2
    //   3256: isub
    //   3257: iaload
    //   3258: bipush #17
    //   3260: iushr
    //   3261: aload #20
    //   3263: iload #22
    //   3265: iconst_2
    //   3266: isub
    //   3267: iaload
    //   3268: bipush #15
    //   3270: ishl
    //   3271: ior
    //   3272: aload #20
    //   3274: iload #22
    //   3276: iconst_2
    //   3277: isub
    //   3278: iaload
    //   3279: bipush #19
    //   3281: iushr
    //   3282: aload #20
    //   3284: iload #22
    //   3286: iconst_2
    //   3287: isub
    //   3288: iaload
    //   3289: bipush #13
    //   3291: ishl
    //   3292: ior
    //   3293: ixor
    //   3294: aload #20
    //   3296: iload #22
    //   3298: iconst_2
    //   3299: isub
    //   3300: iaload
    //   3301: bipush #10
    //   3303: iushr
    //   3304: ixor
    //   3305: aload #20
    //   3307: iload #22
    //   3309: bipush #7
    //   3311: isub
    //   3312: iaload
    //   3313: iadd
    //   3314: aload #20
    //   3316: iload #22
    //   3318: bipush #15
    //   3320: isub
    //   3321: iaload
    //   3322: bipush #7
    //   3324: iushr
    //   3325: aload #20
    //   3327: iload #22
    //   3329: bipush #15
    //   3331: isub
    //   3332: iaload
    //   3333: bipush #25
    //   3335: ishl
    //   3336: ior
    //   3337: aload #20
    //   3339: iload #22
    //   3341: bipush #15
    //   3343: isub
    //   3344: iaload
    //   3345: bipush #18
    //   3347: iushr
    //   3348: aload #20
    //   3350: iload #22
    //   3352: bipush #15
    //   3354: isub
    //   3355: iaload
    //   3356: bipush #14
    //   3358: ishl
    //   3359: ior
    //   3360: ixor
    //   3361: aload #20
    //   3363: iload #22
    //   3365: bipush #15
    //   3367: isub
    //   3368: iaload
    //   3369: iconst_3
    //   3370: iushr
    //   3371: ixor
    //   3372: iadd
    //   3373: aload #20
    //   3375: iload #22
    //   3377: bipush #16
    //   3379: isub
    //   3380: iaload
    //   3381: iadd
    //   3382: iastore
    //   3383: goto -> 3390
    //   3386: invokestatic a : (Ljava/lang/Throwable;)Ljava/lang/Throwable;
    //   3389: athrow
    //   3390: aload #21
    //   3392: bipush #7
    //   3394: iaload
    //   3395: aload #21
    //   3397: iconst_4
    //   3398: iaload
    //   3399: bipush #6
    //   3401: iushr
    //   3402: aload #21
    //   3404: iconst_4
    //   3405: iaload
    //   3406: bipush #26
    //   3408: ishl
    //   3409: ior
    //   3410: aload #21
    //   3412: iconst_4
    //   3413: iaload
    //   3414: bipush #11
    //   3416: iushr
    //   3417: aload #21
    //   3419: iconst_4
    //   3420: iaload
    //   3421: bipush #21
    //   3423: ishl
    //   3424: ior
    //   3425: ixor
    //   3426: aload #21
    //   3428: iconst_4
    //   3429: iaload
    //   3430: bipush #25
    //   3432: iushr
    //   3433: aload #21
    //   3435: iconst_4
    //   3436: iaload
    //   3437: bipush #7
    //   3439: ishl
    //   3440: ior
    //   3441: ixor
    //   3442: iadd
    //   3443: aload #21
    //   3445: bipush #6
    //   3447: iaload
    //   3448: aload #21
    //   3450: iconst_4
    //   3451: iaload
    //   3452: aload #21
    //   3454: iconst_5
    //   3455: iaload
    //   3456: aload #21
    //   3458: bipush #6
    //   3460: iaload
    //   3461: ixor
    //   3462: iand
    //   3463: ixor
    //   3464: iadd
    //   3465: aload #6
    //   3467: iload #22
    //   3469: iaload
    //   3470: iadd
    //   3471: aload #20
    //   3473: iload #22
    //   3475: iaload
    //   3476: iadd
    //   3477: istore #23
    //   3479: aload #21
    //   3481: iconst_0
    //   3482: iaload
    //   3483: iconst_2
    //   3484: iushr
    //   3485: aload #21
    //   3487: iconst_0
    //   3488: iaload
    //   3489: bipush #30
    //   3491: ishl
    //   3492: ior
    //   3493: aload #21
    //   3495: iconst_0
    //   3496: iaload
    //   3497: bipush #13
    //   3499: iushr
    //   3500: aload #21
    //   3502: iconst_0
    //   3503: iaload
    //   3504: bipush #19
    //   3506: ishl
    //   3507: ior
    //   3508: ixor
    //   3509: aload #21
    //   3511: iconst_0
    //   3512: iaload
    //   3513: bipush #22
    //   3515: iushr
    //   3516: aload #21
    //   3518: iconst_0
    //   3519: iaload
    //   3520: bipush #10
    //   3522: ishl
    //   3523: ior
    //   3524: ixor
    //   3525: aload #21
    //   3527: iconst_0
    //   3528: iaload
    //   3529: aload #21
    //   3531: iconst_1
    //   3532: iaload
    //   3533: iand
    //   3534: aload #21
    //   3536: iconst_2
    //   3537: iaload
    //   3538: aload #21
    //   3540: iconst_0
    //   3541: iaload
    //   3542: aload #21
    //   3544: iconst_1
    //   3545: iaload
    //   3546: ior
    //   3547: iand
    //   3548: ior
    //   3549: iadd
    //   3550: istore #24
    //   3552: aload #21
    //   3554: iconst_3
    //   3555: dup2
    //   3556: iaload
    //   3557: iload #23
    //   3559: iadd
    //   3560: iastore
    //   3561: aload #21
    //   3563: bipush #7
    //   3565: iload #23
    //   3567: iload #24
    //   3569: iadd
    //   3570: iastore
    //   3571: aload #21
    //   3573: bipush #7
    //   3575: iaload
    //   3576: istore #23
    //   3578: aload #21
    //   3580: bipush #7
    //   3582: aload #21
    //   3584: bipush #6
    //   3586: iaload
    //   3587: iastore
    //   3588: aload #21
    //   3590: bipush #6
    //   3592: aload #21
    //   3594: iconst_5
    //   3595: iaload
    //   3596: iastore
    //   3597: aload #21
    //   3599: iconst_5
    //   3600: aload #21
    //   3602: iconst_4
    //   3603: iaload
    //   3604: iastore
    //   3605: aload #21
    //   3607: iconst_4
    //   3608: aload #21
    //   3610: iconst_3
    //   3611: iaload
    //   3612: iastore
    //   3613: aload #21
    //   3615: iconst_3
    //   3616: aload #21
    //   3618: iconst_2
    //   3619: iaload
    //   3620: iastore
    //   3621: aload #21
    //   3623: iconst_2
    //   3624: aload #21
    //   3626: iconst_1
    //   3627: iaload
    //   3628: iastore
    //   3629: aload #21
    //   3631: iconst_1
    //   3632: aload #21
    //   3634: iconst_0
    //   3635: iaload
    //   3636: iastore
    //   3637: aload #21
    //   3639: iconst_0
    //   3640: iload #23
    //   3642: iastore
    //   3643: iinc #22, 1
    //   3646: iload_2
    //   3647: ifeq -> 3155
    //   3650: iconst_0
    //   3651: istore #22
    //   3653: iload #22
    //   3655: bipush #8
    //   3657: if_icmpge -> 3680
    //   3660: aload #8
    //   3662: iload #22
    //   3664: dup2
    //   3665: iaload
    //   3666: aload #21
    //   3668: iload #22
    //   3670: iaload
    //   3671: iadd
    //   3672: iastore
    //   3673: iinc #22, 1
    //   3676: iload_2
    //   3677: ifeq -> 3653
    //   3680: bipush #32
    //   3682: newarray byte
    //   3684: astore #4
    //   3686: aload #4
    //   3688: iconst_0
    //   3689: aload #8
    //   3691: iconst_0
    //   3692: iaload
    //   3693: bipush #24
    //   3695: iushr
    //   3696: i2b
    //   3697: bastore
    //   3698: aload #4
    //   3700: iconst_1
    //   3701: aload #8
    //   3703: iconst_0
    //   3704: iaload
    //   3705: bipush #16
    //   3707: iushr
    //   3708: i2b
    //   3709: bastore
    //   3710: aload #4
    //   3712: iconst_2
    //   3713: aload #8
    //   3715: iconst_0
    //   3716: iaload
    //   3717: bipush #8
    //   3719: iushr
    //   3720: i2b
    //   3721: bastore
    //   3722: aload #4
    //   3724: iconst_3
    //   3725: aload #8
    //   3727: iconst_0
    //   3728: iaload
    //   3729: i2b
    //   3730: bastore
    //   3731: aload #4
    //   3733: iconst_4
    //   3734: aload #8
    //   3736: iconst_1
    //   3737: iaload
    //   3738: bipush #24
    //   3740: iushr
    //   3741: i2b
    //   3742: bastore
    //   3743: aload #4
    //   3745: iconst_5
    //   3746: aload #8
    //   3748: iconst_1
    //   3749: iaload
    //   3750: bipush #16
    //   3752: iushr
    //   3753: i2b
    //   3754: bastore
    //   3755: aload #4
    //   3757: bipush #6
    //   3759: aload #8
    //   3761: iconst_1
    //   3762: iaload
    //   3763: bipush #8
    //   3765: iushr
    //   3766: i2b
    //   3767: bastore
    //   3768: aload #4
    //   3770: bipush #7
    //   3772: aload #8
    //   3774: iconst_1
    //   3775: iaload
    //   3776: i2b
    //   3777: bastore
    //   3778: aload #4
    //   3780: bipush #8
    //   3782: aload #8
    //   3784: iconst_2
    //   3785: iaload
    //   3786: bipush #24
    //   3788: iushr
    //   3789: i2b
    //   3790: bastore
    //   3791: aload #4
    //   3793: bipush #9
    //   3795: aload #8
    //   3797: iconst_2
    //   3798: iaload
    //   3799: bipush #16
    //   3801: iushr
    //   3802: i2b
    //   3803: bastore
    //   3804: aload #4
    //   3806: bipush #10
    //   3808: aload #8
    //   3810: iconst_2
    //   3811: iaload
    //   3812: bipush #8
    //   3814: iushr
    //   3815: i2b
    //   3816: bastore
    //   3817: aload #4
    //   3819: bipush #11
    //   3821: aload #8
    //   3823: iconst_2
    //   3824: iaload
    //   3825: i2b
    //   3826: bastore
    //   3827: aload #4
    //   3829: bipush #12
    //   3831: aload #8
    //   3833: iconst_3
    //   3834: iaload
    //   3835: bipush #24
    //   3837: iushr
    //   3838: i2b
    //   3839: bastore
    //   3840: aload #4
    //   3842: bipush #13
    //   3844: aload #8
    //   3846: iconst_3
    //   3847: iaload
    //   3848: bipush #16
    //   3850: iushr
    //   3851: i2b
    //   3852: bastore
    //   3853: aload #4
    //   3855: bipush #14
    //   3857: aload #8
    //   3859: iconst_3
    //   3860: iaload
    //   3861: bipush #8
    //   3863: iushr
    //   3864: i2b
    //   3865: bastore
    //   3866: aload #4
    //   3868: bipush #15
    //   3870: aload #8
    //   3872: iconst_3
    //   3873: iaload
    //   3874: i2b
    //   3875: bastore
    //   3876: aload #4
    //   3878: bipush #16
    //   3880: aload #8
    //   3882: iconst_4
    //   3883: iaload
    //   3884: bipush #24
    //   3886: iushr
    //   3887: i2b
    //   3888: bastore
    //   3889: aload #4
    //   3891: bipush #17
    //   3893: aload #8
    //   3895: iconst_4
    //   3896: iaload
    //   3897: bipush #16
    //   3899: iushr
    //   3900: i2b
    //   3901: bastore
    //   3902: aload #4
    //   3904: bipush #18
    //   3906: aload #8
    //   3908: iconst_4
    //   3909: iaload
    //   3910: bipush #8
    //   3912: iushr
    //   3913: i2b
    //   3914: bastore
    //   3915: aload #4
    //   3917: bipush #19
    //   3919: aload #8
    //   3921: iconst_4
    //   3922: iaload
    //   3923: i2b
    //   3924: bastore
    //   3925: aload #4
    //   3927: bipush #20
    //   3929: aload #8
    //   3931: iconst_5
    //   3932: iaload
    //   3933: bipush #24
    //   3935: iushr
    //   3936: i2b
    //   3937: bastore
    //   3938: aload #4
    //   3940: bipush #21
    //   3942: aload #8
    //   3944: iconst_5
    //   3945: iaload
    //   3946: bipush #16
    //   3948: iushr
    //   3949: i2b
    //   3950: bastore
    //   3951: aload #4
    //   3953: bipush #22
    //   3955: aload #8
    //   3957: iconst_5
    //   3958: iaload
    //   3959: bipush #8
    //   3961: iushr
    //   3962: i2b
    //   3963: bastore
    //   3964: aload #4
    //   3966: bipush #23
    //   3968: aload #8
    //   3970: iconst_5
    //   3971: iaload
    //   3972: i2b
    //   3973: bastore
    //   3974: aload #4
    //   3976: bipush #24
    //   3978: aload #8
    //   3980: bipush #6
    //   3982: iaload
    //   3983: bipush #24
    //   3985: iushr
    //   3986: i2b
    //   3987: bastore
    //   3988: aload #4
    //   3990: bipush #25
    //   3992: aload #8
    //   3994: bipush #6
    //   3996: iaload
    //   3997: bipush #16
    //   3999: iushr
    //   4000: i2b
    //   4001: bastore
    //   4002: aload #4
    //   4004: bipush #26
    //   4006: aload #8
    //   4008: bipush #6
    //   4010: iaload
    //   4011: bipush #8
    //   4013: iushr
    //   4014: i2b
    //   4015: bastore
    //   4016: aload #4
    //   4018: bipush #27
    //   4020: aload #8
    //   4022: bipush #6
    //   4024: iaload
    //   4025: i2b
    //   4026: bastore
    //   4027: aload #4
    //   4029: bipush #28
    //   4031: aload #8
    //   4033: bipush #7
    //   4035: iaload
    //   4036: bipush #24
    //   4038: iushr
    //   4039: i2b
    //   4040: bastore
    //   4041: aload #4
    //   4043: bipush #29
    //   4045: aload #8
    //   4047: bipush #7
    //   4049: iaload
    //   4050: bipush #16
    //   4052: iushr
    //   4053: i2b
    //   4054: bastore
    //   4055: aload #4
    //   4057: bipush #30
    //   4059: aload #8
    //   4061: bipush #7
    //   4063: iaload
    //   4064: bipush #8
    //   4066: iushr
    //   4067: i2b
    //   4068: bastore
    //   4069: aload #4
    //   4071: bipush #31
    //   4073: aload #8
    //   4075: bipush #7
    //   4077: iaload
    //   4078: i2b
    //   4079: bastore
    //   4080: new java/math/BigInteger
    //   4083: dup
    //   4084: aload #4
    //   4086: invokespecial <init> : ([B)V
    //   4089: invokevirtual abs : ()Ljava/math/BigInteger;
    //   4092: putstatic burp/Zbli.Zo : Ljava/lang/Object;
    //   4095: getstatic burp/Zs4g.ZC : Ljava/lang/Object;
    //   4098: checkcast java/math/BigInteger
    //   4101: invokevirtual toByteArray : ()[B
    //   4104: astore_3
    //   4105: bipush #64
    //   4107: newarray byte
    //   4109: dup
    //   4110: iconst_0
    //   4111: bipush #-128
    //   4113: bastore
    //   4114: dup
    //   4115: iconst_1
    //   4116: iconst_0
    //   4117: bastore
    //   4118: dup
    //   4119: iconst_2
    //   4120: iconst_0
    //   4121: bastore
    //   4122: dup
    //   4123: iconst_3
    //   4124: iconst_0
    //   4125: bastore
    //   4126: dup
    //   4127: iconst_4
    //   4128: iconst_0
    //   4129: bastore
    //   4130: dup
    //   4131: iconst_5
    //   4132: iconst_0
    //   4133: bastore
    //   4134: dup
    //   4135: bipush #6
    //   4137: iconst_0
    //   4138: bastore
    //   4139: dup
    //   4140: bipush #7
    //   4142: iconst_0
    //   4143: bastore
    //   4144: dup
    //   4145: bipush #8
    //   4147: iconst_0
    //   4148: bastore
    //   4149: dup
    //   4150: bipush #9
    //   4152: iconst_0
    //   4153: bastore
    //   4154: dup
    //   4155: bipush #10
    //   4157: iconst_0
    //   4158: bastore
    //   4159: dup
    //   4160: bipush #11
    //   4162: iconst_0
    //   4163: bastore
    //   4164: dup
    //   4165: bipush #12
    //   4167: iconst_0
    //   4168: bastore
    //   4169: dup
    //   4170: bipush #13
    //   4172: iconst_0
    //   4173: bastore
    //   4174: dup
    //   4175: bipush #14
    //   4177: iconst_0
    //   4178: bastore
    //   4179: dup
    //   4180: bipush #15
    //   4182: iconst_0
    //   4183: bastore
    //   4184: dup
    //   4185: bipush #16
    //   4187: iconst_0
    //   4188: bastore
    //   4189: dup
    //   4190: bipush #17
    //   4192: iconst_0
    //   4193: bastore
    //   4194: dup
    //   4195: bipush #18
    //   4197: iconst_0
    //   4198: bastore
    //   4199: dup
    //   4200: bipush #19
    //   4202: iconst_0
    //   4203: bastore
    //   4204: dup
    //   4205: bipush #20
    //   4207: iconst_0
    //   4208: bastore
    //   4209: dup
    //   4210: bipush #21
    //   4212: iconst_0
    //   4213: bastore
    //   4214: dup
    //   4215: bipush #22
    //   4217: iconst_0
    //   4218: bastore
    //   4219: dup
    //   4220: bipush #23
    //   4222: iconst_0
    //   4223: bastore
    //   4224: dup
    //   4225: bipush #24
    //   4227: iconst_0
    //   4228: bastore
    //   4229: dup
    //   4230: bipush #25
    //   4232: iconst_0
    //   4233: bastore
    //   4234: dup
    //   4235: bipush #26
    //   4237: iconst_0
    //   4238: bastore
    //   4239: dup
    //   4240: bipush #27
    //   4242: iconst_0
    //   4243: bastore
    //   4244: dup
    //   4245: bipush #28
    //   4247: iconst_0
    //   4248: bastore
    //   4249: dup
    //   4250: bipush #29
    //   4252: iconst_0
    //   4253: bastore
    //   4254: dup
    //   4255: bipush #30
    //   4257: iconst_0
    //   4258: bastore
    //   4259: dup
    //   4260: bipush #31
    //   4262: iconst_0
    //   4263: bastore
    //   4264: dup
    //   4265: bipush #32
    //   4267: iconst_0
    //   4268: bastore
    //   4269: dup
    //   4270: bipush #33
    //   4272: iconst_0
    //   4273: bastore
    //   4274: dup
    //   4275: bipush #34
    //   4277: iconst_0
    //   4278: bastore
    //   4279: dup
    //   4280: bipush #35
    //   4282: iconst_0
    //   4283: bastore
    //   4284: dup
    //   4285: bipush #36
    //   4287: iconst_0
    //   4288: bastore
    //   4289: dup
    //   4290: bipush #37
    //   4292: iconst_0
    //   4293: bastore
    //   4294: dup
    //   4295: bipush #38
    //   4297: iconst_0
    //   4298: bastore
    //   4299: dup
    //   4300: bipush #39
    //   4302: iconst_0
    //   4303: bastore
    //   4304: dup
    //   4305: bipush #40
    //   4307: iconst_0
    //   4308: bastore
    //   4309: dup
    //   4310: bipush #41
    //   4312: iconst_0
    //   4313: bastore
    //   4314: dup
    //   4315: bipush #42
    //   4317: iconst_0
    //   4318: bastore
    //   4319: dup
    //   4320: bipush #43
    //   4322: iconst_0
    //   4323: bastore
    //   4324: dup
    //   4325: bipush #44
    //   4327: iconst_0
    //   4328: bastore
    //   4329: dup
    //   4330: bipush #45
    //   4332: iconst_0
    //   4333: bastore
    //   4334: dup
    //   4335: bipush #46
    //   4337: iconst_0
    //   4338: bastore
    //   4339: dup
    //   4340: bipush #47
    //   4342: iconst_0
    //   4343: bastore
    //   4344: dup
    //   4345: bipush #48
    //   4347: iconst_0
    //   4348: bastore
    //   4349: dup
    //   4350: bipush #49
    //   4352: iconst_0
    //   4353: bastore
    //   4354: dup
    //   4355: bipush #50
    //   4357: iconst_0
    //   4358: bastore
    //   4359: dup
    //   4360: bipush #51
    //   4362: iconst_0
    //   4363: bastore
    //   4364: dup
    //   4365: bipush #52
    //   4367: iconst_0
    //   4368: bastore
    //   4369: dup
    //   4370: bipush #53
    //   4372: iconst_0
    //   4373: bastore
    //   4374: dup
    //   4375: bipush #54
    //   4377: iconst_0
    //   4378: bastore
    //   4379: dup
    //   4380: bipush #55
    //   4382: iconst_0
    //   4383: bastore
    //   4384: dup
    //   4385: bipush #56
    //   4387: iconst_0
    //   4388: bastore
    //   4389: dup
    //   4390: bipush #57
    //   4392: iconst_0
    //   4393: bastore
    //   4394: dup
    //   4395: bipush #58
    //   4397: iconst_0
    //   4398: bastore
    //   4399: dup
    //   4400: bipush #59
    //   4402: iconst_0
    //   4403: bastore
    //   4404: dup
    //   4405: bipush #60
    //   4407: iconst_0
    //   4408: bastore
    //   4409: dup
    //   4410: bipush #61
    //   4412: iconst_0
    //   4413: bastore
    //   4414: dup
    //   4415: bipush #62
    //   4417: iconst_0
    //   4418: bastore
    //   4419: dup
    //   4420: bipush #63
    //   4422: iconst_0
    //   4423: bastore
    //   4424: astore #5
    //   4426: bipush #64
    //   4428: newarray int
    //   4430: dup
    //   4431: iconst_0
    //   4432: ldc 1116352408
    //   4434: iastore
    //   4435: dup
    //   4436: iconst_1
    //   4437: ldc 1899447441
    //   4439: iastore
    //   4440: dup
    //   4441: iconst_2
    //   4442: ldc -1245643825
    //   4444: iastore
    //   4445: dup
    //   4446: iconst_3
    //   4447: ldc -373957723
    //   4449: iastore
    //   4450: dup
    //   4451: iconst_4
    //   4452: ldc 961987163
    //   4454: iastore
    //   4455: dup
    //   4456: iconst_5
    //   4457: ldc 1508970993
    //   4459: iastore
    //   4460: dup
    //   4461: bipush #6
    //   4463: ldc -1841331548
    //   4465: iastore
    //   4466: dup
    //   4467: bipush #7
    //   4469: ldc -1424204075
    //   4471: iastore
    //   4472: dup
    //   4473: bipush #8
    //   4475: ldc -670586216
    //   4477: iastore
    //   4478: dup
    //   4479: bipush #9
    //   4481: ldc 310598401
    //   4483: iastore
    //   4484: dup
    //   4485: bipush #10
    //   4487: ldc 607225278
    //   4489: iastore
    //   4490: dup
    //   4491: bipush #11
    //   4493: ldc 1426881987
    //   4495: iastore
    //   4496: dup
    //   4497: bipush #12
    //   4499: ldc 1925078388
    //   4501: iastore
    //   4502: dup
    //   4503: bipush #13
    //   4505: ldc -2132889090
    //   4507: iastore
    //   4508: dup
    //   4509: bipush #14
    //   4511: ldc -1680079193
    //   4513: iastore
    //   4514: dup
    //   4515: bipush #15
    //   4517: ldc -1046744716
    //   4519: iastore
    //   4520: dup
    //   4521: bipush #16
    //   4523: ldc -459576895
    //   4525: iastore
    //   4526: dup
    //   4527: bipush #17
    //   4529: ldc -272742522
    //   4531: iastore
    //   4532: dup
    //   4533: bipush #18
    //   4535: ldc 264347078
    //   4537: iastore
    //   4538: dup
    //   4539: bipush #19
    //   4541: ldc 604807628
    //   4543: iastore
    //   4544: dup
    //   4545: bipush #20
    //   4547: ldc 770255983
    //   4549: iastore
    //   4550: dup
    //   4551: bipush #21
    //   4553: ldc 1249150122
    //   4555: iastore
    //   4556: dup
    //   4557: bipush #22
    //   4559: ldc 1555081692
    //   4561: iastore
    //   4562: dup
    //   4563: bipush #23
    //   4565: ldc 1996064986
    //   4567: iastore
    //   4568: dup
    //   4569: bipush #24
    //   4571: ldc -1740746414
    //   4573: iastore
    //   4574: dup
    //   4575: bipush #25
    //   4577: ldc -1473132947
    //   4579: iastore
    //   4580: dup
    //   4581: bipush #26
    //   4583: ldc -1341970488
    //   4585: iastore
    //   4586: dup
    //   4587: bipush #27
    //   4589: ldc -1084653625
    //   4591: iastore
    //   4592: dup
    //   4593: bipush #28
    //   4595: ldc -958395405
    //   4597: iastore
    //   4598: dup
    //   4599: bipush #29
    //   4601: ldc -710438585
    //   4603: iastore
    //   4604: dup
    //   4605: bipush #30
    //   4607: ldc 113926993
    //   4609: iastore
    //   4610: dup
    //   4611: bipush #31
    //   4613: ldc 338241895
    //   4615: iastore
    //   4616: dup
    //   4617: bipush #32
    //   4619: ldc 666307205
    //   4621: iastore
    //   4622: dup
    //   4623: bipush #33
    //   4625: ldc 773529912
    //   4627: iastore
    //   4628: dup
    //   4629: bipush #34
    //   4631: ldc 1294757372
    //   4633: iastore
    //   4634: dup
    //   4635: bipush #35
    //   4637: ldc 1396182291
    //   4639: iastore
    //   4640: dup
    //   4641: bipush #36
    //   4643: ldc 1695183700
    //   4645: iastore
    //   4646: dup
    //   4647: bipush #37
    //   4649: ldc 1986661051
    //   4651: iastore
    //   4652: dup
    //   4653: bipush #38
    //   4655: ldc -2117940946
    //   4657: iastore
    //   4658: dup
    //   4659: bipush #39
    //   4661: ldc -1838011259
    //   4663: iastore
    //   4664: dup
    //   4665: bipush #40
    //   4667: ldc -1564481375
    //   4669: iastore
    //   4670: dup
    //   4671: bipush #41
    //   4673: ldc -1474664885
    //   4675: iastore
    //   4676: dup
    //   4677: bipush #42
    //   4679: ldc -1035236496
    //   4681: iastore
    //   4682: dup
    //   4683: bipush #43
    //   4685: ldc -949202525
    //   4687: iastore
    //   4688: dup
    //   4689: bipush #44
    //   4691: ldc -778901479
    //   4693: iastore
    //   4694: dup
    //   4695: bipush #45
    //   4697: ldc -694614492
    //   4699: iastore
    //   4700: dup
    //   4701: bipush #46
    //   4703: ldc -200395387
    //   4705: iastore
    //   4706: dup
    //   4707: bipush #47
    //   4709: ldc 275423344
    //   4711: iastore
    //   4712: dup
    //   4713: bipush #48
    //   4715: ldc 430227734
    //   4717: iastore
    //   4718: dup
    //   4719: bipush #49
    //   4721: ldc 506948616
    //   4723: iastore
    //   4724: dup
    //   4725: bipush #50
    //   4727: ldc 659060556
    //   4729: iastore
    //   4730: dup
    //   4731: bipush #51
    //   4733: ldc 883997877
    //   4735: iastore
    //   4736: dup
    //   4737: bipush #52
    //   4739: ldc 958139571
    //   4741: iastore
    //   4742: dup
    //   4743: bipush #53
    //   4745: ldc 1322822218
    //   4747: iastore
    //   4748: dup
    //   4749: bipush #54
    //   4751: ldc 1537002063
    //   4753: iastore
    //   4754: dup
    //   4755: bipush #55
    //   4757: ldc 1747873779
    //   4759: iastore
    //   4760: dup
    //   4761: bipush #56
    //   4763: ldc 1955562222
    //   4765: iastore
    //   4766: dup
    //   4767: bipush #57
    //   4769: ldc 2024104815
    //   4771: iastore
    //   4772: dup
    //   4773: bipush #58
    //   4775: ldc -2067236844
    //   4777: iastore
    //   4778: dup
    //   4779: bipush #59
    //   4781: ldc -1933114872
    //   4783: iastore
    //   4784: dup
    //   4785: bipush #60
    //   4787: ldc -1866530822
    //   4789: iastore
    //   4790: dup
    //   4791: bipush #61
    //   4793: ldc -1538233109
    //   4795: iastore
    //   4796: dup
    //   4797: bipush #62
    //   4799: ldc -1090935817
    //   4801: iastore
    //   4802: dup
    //   4803: bipush #63
    //   4805: ldc -965641998
    //   4807: iastore
    //   4808: astore #6
    //   4810: iconst_2
    //   4811: newarray int
    //   4813: dup
    //   4814: iconst_0
    //   4815: iconst_0
    //   4816: iastore
    //   4817: dup
    //   4818: iconst_1
    //   4819: iconst_0
    //   4820: iastore
    //   4821: astore #7
    //   4823: bipush #8
    //   4825: newarray int
    //   4827: dup
    //   4828: iconst_0
    //   4829: ldc 1779033703
    //   4831: iastore
    //   4832: dup
    //   4833: iconst_1
    //   4834: ldc -1150833019
    //   4836: iastore
    //   4837: dup
    //   4838: iconst_2
    //   4839: ldc 1013904242
    //   4841: iastore
    //   4842: dup
    //   4843: iconst_3
    //   4844: ldc -1521486534
    //   4846: iastore
    //   4847: dup
    //   4848: iconst_4
    //   4849: ldc 1359893119
    //   4851: iastore
    //   4852: dup
    //   4853: iconst_5
    //   4854: ldc -1694144372
    //   4856: iastore
    //   4857: dup
    //   4858: bipush #6
    //   4860: ldc 528734635
    //   4862: iastore
    //   4863: dup
    //   4864: bipush #7
    //   4866: ldc 1541459225
    //   4868: iastore
    //   4869: astore #8
    //   4871: bipush #64
    //   4873: newarray byte
    //   4875: astore #9
    //   4877: bipush #64
    //   4879: newarray byte
    //   4881: astore #10
    //   4883: aload_3
    //   4884: arraylength
    //   4885: istore #11
    //   4887: aload #7
    //   4889: iconst_0
    //   4890: iaload
    //   4891: bipush #63
    //   4893: iand
    //   4894: istore #12
    //   4896: aload #7
    //   4898: iconst_0
    //   4899: dup2
    //   4900: iaload
    //   4901: iload #11
    //   4903: iadd
    //   4904: iastore
    //   4905: aload #7
    //   4907: iconst_0
    //   4908: dup2
    //   4909: iaload
    //   4910: iconst_m1
    //   4911: iand
    //   4912: iastore
    //   4913: aload #7
    //   4915: iconst_0
    //   4916: iaload
    //   4917: iload #11
    //   4919: if_icmpge -> 4937
    //   4922: aload #7
    //   4924: iconst_1
    //   4925: dup2
    //   4926: iaload
    //   4927: iconst_1
    //   4928: iadd
    //   4929: iastore
    //   4930: goto -> 4937
    //   4933: invokestatic a : (Ljava/lang/Throwable;)Ljava/lang/Throwable;
    //   4936: athrow
    //   4937: iconst_0
    //   4938: istore #13
    //   4940: iload #11
    //   4942: bipush #64
    //   4944: if_icmplt -> 5553
    //   4947: iconst_0
    //   4948: istore #14
    //   4950: iload #14
    //   4952: bipush #64
    //   4954: if_icmpge -> 4976
    //   4957: aload #10
    //   4959: iload #14
    //   4961: aload_3
    //   4962: iload #13
    //   4964: iload #14
    //   4966: iadd
    //   4967: baload
    //   4968: bastore
    //   4969: iinc #14, 1
    //   4972: iload_2
    //   4973: ifeq -> 4950
    //   4976: bipush #64
    //   4978: newarray int
    //   4980: astore #14
    //   4982: bipush #8
    //   4984: newarray int
    //   4986: astore #15
    //   4988: iconst_0
    //   4989: istore #16
    //   4991: iload #16
    //   4993: bipush #8
    //   4995: if_icmpge -> 5015
    //   4998: aload #15
    //   5000: iload #16
    //   5002: aload #8
    //   5004: iload #16
    //   5006: iaload
    //   5007: iastore
    //   5008: iinc #16, 1
    //   5011: iload_2
    //   5012: ifeq -> 4991
    //   5015: iconst_0
    //   5016: istore #16
    //   5018: iload #16
    //   5020: bipush #64
    //   5022: if_icmpge -> 5513
    //   5025: iload #16
    //   5027: bipush #16
    //   5029: if_icmpge -> 5110
    //   5032: aload #14
    //   5034: iload #16
    //   5036: aload #10
    //   5038: iconst_4
    //   5039: iload #16
    //   5041: imul
    //   5042: baload
    //   5043: sipush #255
    //   5046: iand
    //   5047: bipush #24
    //   5049: ishl
    //   5050: aload #10
    //   5052: iconst_4
    //   5053: iload #16
    //   5055: imul
    //   5056: iconst_1
    //   5057: iadd
    //   5058: baload
    //   5059: sipush #255
    //   5062: iand
    //   5063: bipush #16
    //   5065: ishl
    //   5066: ior
    //   5067: aload #10
    //   5069: iconst_4
    //   5070: iload #16
    //   5072: imul
    //   5073: iconst_2
    //   5074: iadd
    //   5075: baload
    //   5076: sipush #255
    //   5079: iand
    //   5080: bipush #8
    //   5082: ishl
    //   5083: ior
    //   5084: aload #10
    //   5086: iconst_4
    //   5087: iload #16
    //   5089: imul
    //   5090: iconst_3
    //   5091: iadd
    //   5092: baload
    //   5093: sipush #255
    //   5096: iand
    //   5097: ior
    //   5098: iastore
    //   5099: iload_2
    //   5100: ifeq -> 5253
    //   5103: goto -> 5110
    //   5106: invokestatic a : (Ljava/lang/Throwable;)Ljava/lang/Throwable;
    //   5109: athrow
    //   5110: aload #14
    //   5112: iload #16
    //   5114: aload #14
    //   5116: iload #16
    //   5118: iconst_2
    //   5119: isub
    //   5120: iaload
    //   5121: bipush #17
    //   5123: iushr
    //   5124: aload #14
    //   5126: iload #16
    //   5128: iconst_2
    //   5129: isub
    //   5130: iaload
    //   5131: bipush #15
    //   5133: ishl
    //   5134: ior
    //   5135: aload #14
    //   5137: iload #16
    //   5139: iconst_2
    //   5140: isub
    //   5141: iaload
    //   5142: bipush #19
    //   5144: iushr
    //   5145: aload #14
    //   5147: iload #16
    //   5149: iconst_2
    //   5150: isub
    //   5151: iaload
    //   5152: bipush #13
    //   5154: ishl
    //   5155: ior
    //   5156: ixor
    //   5157: aload #14
    //   5159: iload #16
    //   5161: iconst_2
    //   5162: isub
    //   5163: iaload
    //   5164: bipush #10
    //   5166: iushr
    //   5167: ixor
    //   5168: aload #14
    //   5170: iload #16
    //   5172: bipush #7
    //   5174: isub
    //   5175: iaload
    //   5176: iadd
    //   5177: aload #14
    //   5179: iload #16
    //   5181: bipush #15
    //   5183: isub
    //   5184: iaload
    //   5185: bipush #7
    //   5187: iushr
    //   5188: aload #14
    //   5190: iload #16
    //   5192: bipush #15
    //   5194: isub
    //   5195: iaload
    //   5196: bipush #25
    //   5198: ishl
    //   5199: ior
    //   5200: aload #14
    //   5202: iload #16
    //   5204: bipush #15
    //   5206: isub
    //   5207: iaload
    //   5208: bipush #18
    //   5210: iushr
    //   5211: aload #14
    //   5213: iload #16
    //   5215: bipush #15
    //   5217: isub
    //   5218: iaload
    //   5219: bipush #14
    //   5221: ishl
    //   5222: ior
    //   5223: ixor
    //   5224: aload #14
    //   5226: iload #16
    //   5228: bipush #15
    //   5230: isub
    //   5231: iaload
    //   5232: iconst_3
    //   5233: iushr
    //   5234: ixor
    //   5235: iadd
    //   5236: aload #14
    //   5238: iload #16
    //   5240: bipush #16
    //   5242: isub
    //   5243: iaload
    //   5244: iadd
    //   5245: iastore
    //   5246: goto -> 5253
    //   5249: invokestatic a : (Ljava/lang/Throwable;)Ljava/lang/Throwable;
    //   5252: athrow
    //   5253: aload #15
    //   5255: bipush #7
    //   5257: iaload
    //   5258: aload #15
    //   5260: iconst_4
    //   5261: iaload
    //   5262: bipush #6
    //   5264: iushr
    //   5265: aload #15
    //   5267: iconst_4
    //   5268: iaload
    //   5269: bipush #26
    //   5271: ishl
    //   5272: ior
    //   5273: aload #15
    //   5275: iconst_4
    //   5276: iaload
    //   5277: bipush #11
    //   5279: iushr
    //   5280: aload #15
    //   5282: iconst_4
    //   5283: iaload
    //   5284: bipush #21
    //   5286: ishl
    //   5287: ior
    //   5288: ixor
    //   5289: aload #15
    //   5291: iconst_4
    //   5292: iaload
    //   5293: bipush #25
    //   5295: iushr
    //   5296: aload #15
    //   5298: iconst_4
    //   5299: iaload
    //   5300: bipush #7
    //   5302: ishl
    //   5303: ior
    //   5304: ixor
    //   5305: iadd
    //   5306: aload #15
    //   5308: bipush #6
    //   5310: iaload
    //   5311: aload #15
    //   5313: iconst_4
    //   5314: iaload
    //   5315: aload #15
    //   5317: iconst_5
    //   5318: iaload
    //   5319: aload #15
    //   5321: bipush #6
    //   5323: iaload
    //   5324: ixor
    //   5325: iand
    //   5326: ixor
    //   5327: iadd
    //   5328: aload #6
    //   5330: iload #16
    //   5332: iaload
    //   5333: iadd
    //   5334: aload #14
    //   5336: iload #16
    //   5338: iaload
    //   5339: iadd
    //   5340: istore #17
    //   5342: aload #15
    //   5344: iconst_0
    //   5345: iaload
    //   5346: iconst_2
    //   5347: iushr
    //   5348: aload #15
    //   5350: iconst_0
    //   5351: iaload
    //   5352: bipush #30
    //   5354: ishl
    //   5355: ior
    //   5356: aload #15
    //   5358: iconst_0
    //   5359: iaload
    //   5360: bipush #13
    //   5362: iushr
    //   5363: aload #15
    //   5365: iconst_0
    //   5366: iaload
    //   5367: bipush #19
    //   5369: ishl
    //   5370: ior
    //   5371: ixor
    //   5372: aload #15
    //   5374: iconst_0
    //   5375: iaload
    //   5376: bipush #22
    //   5378: iushr
    //   5379: aload #15
    //   5381: iconst_0
    //   5382: iaload
    //   5383: bipush #10
    //   5385: ishl
    //   5386: ior
    //   5387: ixor
    //   5388: aload #15
    //   5390: iconst_0
    //   5391: iaload
    //   5392: aload #15
    //   5394: iconst_1
    //   5395: iaload
    //   5396: iand
    //   5397: aload #15
    //   5399: iconst_2
    //   5400: iaload
    //   5401: aload #15
    //   5403: iconst_0
    //   5404: iaload
    //   5405: aload #15
    //   5407: iconst_1
    //   5408: iaload
    //   5409: ior
    //   5410: iand
    //   5411: ior
    //   5412: iadd
    //   5413: istore #18
    //   5415: aload #15
    //   5417: iconst_3
    //   5418: dup2
    //   5419: iaload
    //   5420: iload #17
    //   5422: iadd
    //   5423: iastore
    //   5424: aload #15
    //   5426: bipush #7
    //   5428: iload #17
    //   5430: iload #18
    //   5432: iadd
    //   5433: iastore
    //   5434: aload #15
    //   5436: bipush #7
    //   5438: iaload
    //   5439: istore #17
    //   5441: aload #15
    //   5443: bipush #7
    //   5445: aload #15
    //   5447: bipush #6
    //   5449: iaload
    //   5450: iastore
    //   5451: aload #15
    //   5453: bipush #6
    //   5455: aload #15
    //   5457: iconst_5
    //   5458: iaload
    //   5459: iastore
    //   5460: aload #15
    //   5462: iconst_5
    //   5463: aload #15
    //   5465: iconst_4
    //   5466: iaload
    //   5467: iastore
    //   5468: aload #15
    //   5470: iconst_4
    //   5471: aload #15
    //   5473: iconst_3
    //   5474: iaload
    //   5475: iastore
    //   5476: aload #15
    //   5478: iconst_3
    //   5479: aload #15
    //   5481: iconst_2
    //   5482: iaload
    //   5483: iastore
    //   5484: aload #15
    //   5486: iconst_2
    //   5487: aload #15
    //   5489: iconst_1
    //   5490: iaload
    //   5491: iastore
    //   5492: aload #15
    //   5494: iconst_1
    //   5495: aload #15
    //   5497: iconst_0
    //   5498: iaload
    //   5499: iastore
    //   5500: aload #15
    //   5502: iconst_0
    //   5503: iload #17
    //   5505: iastore
    //   5506: iinc #16, 1
    //   5509: iload_2
    //   5510: ifeq -> 5018
    //   5513: iconst_0
    //   5514: istore #16
    //   5516: iload #16
    //   5518: bipush #8
    //   5520: if_icmpge -> 5543
    //   5523: aload #8
    //   5525: iload #16
    //   5527: dup2
    //   5528: iaload
    //   5529: aload #15
    //   5531: iload #16
    //   5533: iaload
    //   5534: iadd
    //   5535: iastore
    //   5536: iinc #16, 1
    //   5539: iload_2
    //   5540: ifeq -> 5516
    //   5543: iinc #13, 64
    //   5546: iinc #11, -64
    //   5549: iload_2
    //   5550: ifeq -> 4940
    //   5553: iload #11
    //   5555: ifle -> 5590
    //   5558: iconst_0
    //   5559: istore #14
    //   5561: iload #14
    //   5563: iload #11
    //   5565: if_icmpge -> 5590
    //   5568: aload #9
    //   5570: iload #12
    //   5572: iload #14
    //   5574: iadd
    //   5575: aload_3
    //   5576: iload #13
    //   5578: iload #14
    //   5580: iadd
    //   5581: baload
    //   5582: bastore
    //   5583: iinc #14, 1
    //   5586: iload_2
    //   5587: ifeq -> 5561
    //   5590: aload #7
    //   5592: iconst_0
    //   5593: iaload
    //   5594: bipush #29
    //   5596: iushr
    //   5597: aload #7
    //   5599: iconst_1
    //   5600: iaload
    //   5601: iconst_3
    //   5602: ishl
    //   5603: ior
    //   5604: istore #14
    //   5606: aload #7
    //   5608: iconst_0
    //   5609: iaload
    //   5610: iconst_3
    //   5611: ishl
    //   5612: istore #15
    //   5614: aload #7
    //   5616: iconst_0
    //   5617: iaload
    //   5618: bipush #63
    //   5620: iand
    //   5621: istore #16
    //   5623: iload #16
    //   5625: bipush #56
    //   5627: if_icmpge -> 5642
    //   5630: bipush #56
    //   5632: iload #16
    //   5634: isub
    //   5635: goto -> 5647
    //   5638: invokestatic a : (Ljava/lang/Throwable;)Ljava/lang/Throwable;
    //   5641: athrow
    //   5642: bipush #120
    //   5644: iload #16
    //   5646: isub
    //   5647: istore #17
    //   5649: aload #7
    //   5651: iconst_0
    //   5652: iaload
    //   5653: bipush #63
    //   5655: iand
    //   5656: istore #12
    //   5658: bipush #64
    //   5660: iload #12
    //   5662: isub
    //   5663: istore #18
    //   5665: aload #7
    //   5667: iconst_0
    //   5668: dup2
    //   5669: iaload
    //   5670: iload #17
    //   5672: iadd
    //   5673: iastore
    //   5674: aload #7
    //   5676: iconst_0
    //   5677: dup2
    //   5678: iaload
    //   5679: iconst_m1
    //   5680: iand
    //   5681: iastore
    //   5682: aload #7
    //   5684: iconst_0
    //   5685: iaload
    //   5686: iload #17
    //   5688: if_icmpge -> 5706
    //   5691: aload #7
    //   5693: iconst_1
    //   5694: dup2
    //   5695: iaload
    //   5696: iconst_1
    //   5697: iadd
    //   5698: iastore
    //   5699: goto -> 5706
    //   5702: invokestatic a : (Ljava/lang/Throwable;)Ljava/lang/Throwable;
    //   5705: athrow
    //   5706: iconst_0
    //   5707: istore #13
    //   5709: iload #12
    //   5711: ifle -> 6342
    //   5714: iload #17
    //   5716: iload #18
    //   5718: if_icmplt -> 6342
    //   5721: goto -> 5728
    //   5724: invokestatic a : (Ljava/lang/Throwable;)Ljava/lang/Throwable;
    //   5727: athrow
    //   5728: iconst_0
    //   5729: istore #19
    //   5731: iload #19
    //   5733: iload #18
    //   5735: if_icmpge -> 5758
    //   5738: aload #9
    //   5740: iload #12
    //   5742: iload #19
    //   5744: iadd
    //   5745: aload #5
    //   5747: iload #19
    //   5749: baload
    //   5750: bastore
    //   5751: iinc #19, 1
    //   5754: iload_2
    //   5755: ifeq -> 5731
    //   5758: bipush #64
    //   5760: newarray int
    //   5762: astore #19
    //   5764: bipush #8
    //   5766: newarray int
    //   5768: astore #20
    //   5770: iconst_0
    //   5771: istore #21
    //   5773: iload #21
    //   5775: bipush #8
    //   5777: if_icmpge -> 5797
    //   5780: aload #20
    //   5782: iload #21
    //   5784: aload #8
    //   5786: iload #21
    //   5788: iaload
    //   5789: iastore
    //   5790: iinc #21, 1
    //   5793: iload_2
    //   5794: ifeq -> 5773
    //   5797: iconst_0
    //   5798: istore #21
    //   5800: iload #21
    //   5802: bipush #64
    //   5804: if_icmpge -> 6295
    //   5807: iload #21
    //   5809: bipush #16
    //   5811: if_icmpge -> 5892
    //   5814: aload #19
    //   5816: iload #21
    //   5818: aload #9
    //   5820: iconst_4
    //   5821: iload #21
    //   5823: imul
    //   5824: baload
    //   5825: sipush #255
    //   5828: iand
    //   5829: bipush #24
    //   5831: ishl
    //   5832: aload #9
    //   5834: iconst_4
    //   5835: iload #21
    //   5837: imul
    //   5838: iconst_1
    //   5839: iadd
    //   5840: baload
    //   5841: sipush #255
    //   5844: iand
    //   5845: bipush #16
    //   5847: ishl
    //   5848: ior
    //   5849: aload #9
    //   5851: iconst_4
    //   5852: iload #21
    //   5854: imul
    //   5855: iconst_2
    //   5856: iadd
    //   5857: baload
    //   5858: sipush #255
    //   5861: iand
    //   5862: bipush #8
    //   5864: ishl
    //   5865: ior
    //   5866: aload #9
    //   5868: iconst_4
    //   5869: iload #21
    //   5871: imul
    //   5872: iconst_3
    //   5873: iadd
    //   5874: baload
    //   5875: sipush #255
    //   5878: iand
    //   5879: ior
    //   5880: iastore
    //   5881: iload_2
    //   5882: ifeq -> 6035
    //   5885: goto -> 5892
    //   5888: invokestatic a : (Ljava/lang/Throwable;)Ljava/lang/Throwable;
    //   5891: athrow
    //   5892: aload #19
    //   5894: iload #21
    //   5896: aload #19
    //   5898: iload #21
    //   5900: iconst_2
    //   5901: isub
    //   5902: iaload
    //   5903: bipush #17
    //   5905: iushr
    //   5906: aload #19
    //   5908: iload #21
    //   5910: iconst_2
    //   5911: isub
    //   5912: iaload
    //   5913: bipush #15
    //   5915: ishl
    //   5916: ior
    //   5917: aload #19
    //   5919: iload #21
    //   5921: iconst_2
    //   5922: isub
    //   5923: iaload
    //   5924: bipush #19
    //   5926: iushr
    //   5927: aload #19
    //   5929: iload #21
    //   5931: iconst_2
    //   5932: isub
    //   5933: iaload
    //   5934: bipush #13
    //   5936: ishl
    //   5937: ior
    //   5938: ixor
    //   5939: aload #19
    //   5941: iload #21
    //   5943: iconst_2
    //   5944: isub
    //   5945: iaload
    //   5946: bipush #10
    //   5948: iushr
    //   5949: ixor
    //   5950: aload #19
    //   5952: iload #21
    //   5954: bipush #7
    //   5956: isub
    //   5957: iaload
    //   5958: iadd
    //   5959: aload #19
    //   5961: iload #21
    //   5963: bipush #15
    //   5965: isub
    //   5966: iaload
    //   5967: bipush #7
    //   5969: iushr
    //   5970: aload #19
    //   5972: iload #21
    //   5974: bipush #15
    //   5976: isub
    //   5977: iaload
    //   5978: bipush #25
    //   5980: ishl
    //   5981: ior
    //   5982: aload #19
    //   5984: iload #21
    //   5986: bipush #15
    //   5988: isub
    //   5989: iaload
    //   5990: bipush #18
    //   5992: iushr
    //   5993: aload #19
    //   5995: iload #21
    //   5997: bipush #15
    //   5999: isub
    //   6000: iaload
    //   6001: bipush #14
    //   6003: ishl
    //   6004: ior
    //   6005: ixor
    //   6006: aload #19
    //   6008: iload #21
    //   6010: bipush #15
    //   6012: isub
    //   6013: iaload
    //   6014: iconst_3
    //   6015: iushr
    //   6016: ixor
    //   6017: iadd
    //   6018: aload #19
    //   6020: iload #21
    //   6022: bipush #16
    //   6024: isub
    //   6025: iaload
    //   6026: iadd
    //   6027: iastore
    //   6028: goto -> 6035
    //   6031: invokestatic a : (Ljava/lang/Throwable;)Ljava/lang/Throwable;
    //   6034: athrow
    //   6035: aload #20
    //   6037: bipush #7
    //   6039: iaload
    //   6040: aload #20
    //   6042: iconst_4
    //   6043: iaload
    //   6044: bipush #6
    //   6046: iushr
    //   6047: aload #20
    //   6049: iconst_4
    //   6050: iaload
    //   6051: bipush #26
    //   6053: ishl
    //   6054: ior
    //   6055: aload #20
    //   6057: iconst_4
    //   6058: iaload
    //   6059: bipush #11
    //   6061: iushr
    //   6062: aload #20
    //   6064: iconst_4
    //   6065: iaload
    //   6066: bipush #21
    //   6068: ishl
    //   6069: ior
    //   6070: ixor
    //   6071: aload #20
    //   6073: iconst_4
    //   6074: iaload
    //   6075: bipush #25
    //   6077: iushr
    //   6078: aload #20
    //   6080: iconst_4
    //   6081: iaload
    //   6082: bipush #7
    //   6084: ishl
    //   6085: ior
    //   6086: ixor
    //   6087: iadd
    //   6088: aload #20
    //   6090: bipush #6
    //   6092: iaload
    //   6093: aload #20
    //   6095: iconst_4
    //   6096: iaload
    //   6097: aload #20
    //   6099: iconst_5
    //   6100: iaload
    //   6101: aload #20
    //   6103: bipush #6
    //   6105: iaload
    //   6106: ixor
    //   6107: iand
    //   6108: ixor
    //   6109: iadd
    //   6110: aload #6
    //   6112: iload #21
    //   6114: iaload
    //   6115: iadd
    //   6116: aload #19
    //   6118: iload #21
    //   6120: iaload
    //   6121: iadd
    //   6122: istore #22
    //   6124: aload #20
    //   6126: iconst_0
    //   6127: iaload
    //   6128: iconst_2
    //   6129: iushr
    //   6130: aload #20
    //   6132: iconst_0
    //   6133: iaload
    //   6134: bipush #30
    //   6136: ishl
    //   6137: ior
    //   6138: aload #20
    //   6140: iconst_0
    //   6141: iaload
    //   6142: bipush #13
    //   6144: iushr
    //   6145: aload #20
    //   6147: iconst_0
    //   6148: iaload
    //   6149: bipush #19
    //   6151: ishl
    //   6152: ior
    //   6153: ixor
    //   6154: aload #20
    //   6156: iconst_0
    //   6157: iaload
    //   6158: bipush #22
    //   6160: iushr
    //   6161: aload #20
    //   6163: iconst_0
    //   6164: iaload
    //   6165: bipush #10
    //   6167: ishl
    //   6168: ior
    //   6169: ixor
    //   6170: aload #20
    //   6172: iconst_0
    //   6173: iaload
    //   6174: aload #20
    //   6176: iconst_1
    //   6177: iaload
    //   6178: iand
    //   6179: aload #20
    //   6181: iconst_2
    //   6182: iaload
    //   6183: aload #20
    //   6185: iconst_0
    //   6186: iaload
    //   6187: aload #20
    //   6189: iconst_1
    //   6190: iaload
    //   6191: ior
    //   6192: iand
    //   6193: ior
    //   6194: iadd
    //   6195: istore #23
    //   6197: aload #20
    //   6199: iconst_3
    //   6200: dup2
    //   6201: iaload
    //   6202: iload #22
    //   6204: iadd
    //   6205: iastore
    //   6206: aload #20
    //   6208: bipush #7
    //   6210: iload #22
    //   6212: iload #23
    //   6214: iadd
    //   6215: iastore
    //   6216: aload #20
    //   6218: bipush #7
    //   6220: iaload
    //   6221: istore #22
    //   6223: aload #20
    //   6225: bipush #7
    //   6227: aload #20
    //   6229: bipush #6
    //   6231: iaload
    //   6232: iastore
    //   6233: aload #20
    //   6235: bipush #6
    //   6237: aload #20
    //   6239: iconst_5
    //   6240: iaload
    //   6241: iastore
    //   6242: aload #20
    //   6244: iconst_5
    //   6245: aload #20
    //   6247: iconst_4
    //   6248: iaload
    //   6249: iastore
    //   6250: aload #20
    //   6252: iconst_4
    //   6253: aload #20
    //   6255: iconst_3
    //   6256: iaload
    //   6257: iastore
    //   6258: aload #20
    //   6260: iconst_3
    //   6261: aload #20
    //   6263: iconst_2
    //   6264: iaload
    //   6265: iastore
    //   6266: aload #20
    //   6268: iconst_2
    //   6269: aload #20
    //   6271: iconst_1
    //   6272: iaload
    //   6273: iastore
    //   6274: aload #20
    //   6276: iconst_1
    //   6277: aload #20
    //   6279: iconst_0
    //   6280: iaload
    //   6281: iastore
    //   6282: aload #20
    //   6284: iconst_0
    //   6285: iload #22
    //   6287: iastore
    //   6288: iinc #21, 1
    //   6291: iload_2
    //   6292: ifeq -> 5800
    //   6295: iconst_0
    //   6296: istore #21
    //   6298: iload #21
    //   6300: bipush #8
    //   6302: if_icmpge -> 6325
    //   6305: aload #8
    //   6307: iload #21
    //   6309: dup2
    //   6310: iaload
    //   6311: aload #20
    //   6313: iload #21
    //   6315: iaload
    //   6316: iadd
    //   6317: iastore
    //   6318: iinc #21, 1
    //   6321: iload_2
    //   6322: ifeq -> 6298
    //   6325: iload #13
    //   6327: iload #18
    //   6329: iadd
    //   6330: istore #13
    //   6332: iload #17
    //   6334: iload #18
    //   6336: isub
    //   6337: istore #17
    //   6339: iconst_0
    //   6340: istore #12
    //   6342: iload #17
    //   6344: bipush #64
    //   6346: if_icmplt -> 6956
    //   6349: iconst_0
    //   6350: istore #19
    //   6352: iload #19
    //   6354: bipush #64
    //   6356: if_icmpge -> 6379
    //   6359: aload #10
    //   6361: iload #19
    //   6363: aload #5
    //   6365: iload #13
    //   6367: iload #19
    //   6369: iadd
    //   6370: baload
    //   6371: bastore
    //   6372: iinc #19, 1
    //   6375: iload_2
    //   6376: ifeq -> 6352
    //   6379: bipush #64
    //   6381: newarray int
    //   6383: astore #19
    //   6385: bipush #8
    //   6387: newarray int
    //   6389: astore #20
    //   6391: iconst_0
    //   6392: istore #21
    //   6394: iload #21
    //   6396: bipush #8
    //   6398: if_icmpge -> 6418
    //   6401: aload #20
    //   6403: iload #21
    //   6405: aload #8
    //   6407: iload #21
    //   6409: iaload
    //   6410: iastore
    //   6411: iinc #21, 1
    //   6414: iload_2
    //   6415: ifeq -> 6394
    //   6418: iconst_0
    //   6419: istore #21
    //   6421: iload #21
    //   6423: bipush #64
    //   6425: if_icmpge -> 6916
    //   6428: iload #21
    //   6430: bipush #16
    //   6432: if_icmpge -> 6513
    //   6435: aload #19
    //   6437: iload #21
    //   6439: aload #10
    //   6441: iconst_4
    //   6442: iload #21
    //   6444: imul
    //   6445: baload
    //   6446: sipush #255
    //   6449: iand
    //   6450: bipush #24
    //   6452: ishl
    //   6453: aload #10
    //   6455: iconst_4
    //   6456: iload #21
    //   6458: imul
    //   6459: iconst_1
    //   6460: iadd
    //   6461: baload
    //   6462: sipush #255
    //   6465: iand
    //   6466: bipush #16
    //   6468: ishl
    //   6469: ior
    //   6470: aload #10
    //   6472: iconst_4
    //   6473: iload #21
    //   6475: imul
    //   6476: iconst_2
    //   6477: iadd
    //   6478: baload
    //   6479: sipush #255
    //   6482: iand
    //   6483: bipush #8
    //   6485: ishl
    //   6486: ior
    //   6487: aload #10
    //   6489: iconst_4
    //   6490: iload #21
    //   6492: imul
    //   6493: iconst_3
    //   6494: iadd
    //   6495: baload
    //   6496: sipush #255
    //   6499: iand
    //   6500: ior
    //   6501: iastore
    //   6502: iload_2
    //   6503: ifeq -> 6656
    //   6506: goto -> 6513
    //   6509: invokestatic a : (Ljava/lang/Throwable;)Ljava/lang/Throwable;
    //   6512: athrow
    //   6513: aload #19
    //   6515: iload #21
    //   6517: aload #19
    //   6519: iload #21
    //   6521: iconst_2
    //   6522: isub
    //   6523: iaload
    //   6524: bipush #17
    //   6526: iushr
    //   6527: aload #19
    //   6529: iload #21
    //   6531: iconst_2
    //   6532: isub
    //   6533: iaload
    //   6534: bipush #15
    //   6536: ishl
    //   6537: ior
    //   6538: aload #19
    //   6540: iload #21
    //   6542: iconst_2
    //   6543: isub
    //   6544: iaload
    //   6545: bipush #19
    //   6547: iushr
    //   6548: aload #19
    //   6550: iload #21
    //   6552: iconst_2
    //   6553: isub
    //   6554: iaload
    //   6555: bipush #13
    //   6557: ishl
    //   6558: ior
    //   6559: ixor
    //   6560: aload #19
    //   6562: iload #21
    //   6564: iconst_2
    //   6565: isub
    //   6566: iaload
    //   6567: bipush #10
    //   6569: iushr
    //   6570: ixor
    //   6571: aload #19
    //   6573: iload #21
    //   6575: bipush #7
    //   6577: isub
    //   6578: iaload
    //   6579: iadd
    //   6580: aload #19
    //   6582: iload #21
    //   6584: bipush #15
    //   6586: isub
    //   6587: iaload
    //   6588: bipush #7
    //   6590: iushr
    //   6591: aload #19
    //   6593: iload #21
    //   6595: bipush #15
    //   6597: isub
    //   6598: iaload
    //   6599: bipush #25
    //   6601: ishl
    //   6602: ior
    //   6603: aload #19
    //   6605: iload #21
    //   6607: bipush #15
    //   6609: isub
    //   6610: iaload
    //   6611: bipush #18
    //   6613: iushr
    //   6614: aload #19
    //   6616: iload #21
    //   6618: bipush #15
    //   6620: isub
    //   6621: iaload
    //   6622: bipush #14
    //   6624: ishl
    //   6625: ior
    //   6626: ixor
    //   6627: aload #19
    //   6629: iload #21
    //   6631: bipush #15
    //   6633: isub
    //   6634: iaload
    //   6635: iconst_3
    //   6636: iushr
    //   6637: ixor
    //   6638: iadd
    //   6639: aload #19
    //   6641: iload #21
    //   6643: bipush #16
    //   6645: isub
    //   6646: iaload
    //   6647: iadd
    //   6648: iastore
    //   6649: goto -> 6656
    //   6652: invokestatic a : (Ljava/lang/Throwable;)Ljava/lang/Throwable;
    //   6655: athrow
    //   6656: aload #20
    //   6658: bipush #7
    //   6660: iaload
    //   6661: aload #20
    //   6663: iconst_4
    //   6664: iaload
    //   6665: bipush #6
    //   6667: iushr
    //   6668: aload #20
    //   6670: iconst_4
    //   6671: iaload
    //   6672: bipush #26
    //   6674: ishl
    //   6675: ior
    //   6676: aload #20
    //   6678: iconst_4
    //   6679: iaload
    //   6680: bipush #11
    //   6682: iushr
    //   6683: aload #20
    //   6685: iconst_4
    //   6686: iaload
    //   6687: bipush #21
    //   6689: ishl
    //   6690: ior
    //   6691: ixor
    //   6692: aload #20
    //   6694: iconst_4
    //   6695: iaload
    //   6696: bipush #25
    //   6698: iushr
    //   6699: aload #20
    //   6701: iconst_4
    //   6702: iaload
    //   6703: bipush #7
    //   6705: ishl
    //   6706: ior
    //   6707: ixor
    //   6708: iadd
    //   6709: aload #20
    //   6711: bipush #6
    //   6713: iaload
    //   6714: aload #20
    //   6716: iconst_4
    //   6717: iaload
    //   6718: aload #20
    //   6720: iconst_5
    //   6721: iaload
    //   6722: aload #20
    //   6724: bipush #6
    //   6726: iaload
    //   6727: ixor
    //   6728: iand
    //   6729: ixor
    //   6730: iadd
    //   6731: aload #6
    //   6733: iload #21
    //   6735: iaload
    //   6736: iadd
    //   6737: aload #19
    //   6739: iload #21
    //   6741: iaload
    //   6742: iadd
    //   6743: istore #22
    //   6745: aload #20
    //   6747: iconst_0
    //   6748: iaload
    //   6749: iconst_2
    //   6750: iushr
    //   6751: aload #20
    //   6753: iconst_0
    //   6754: iaload
    //   6755: bipush #30
    //   6757: ishl
    //   6758: ior
    //   6759: aload #20
    //   6761: iconst_0
    //   6762: iaload
    //   6763: bipush #13
    //   6765: iushr
    //   6766: aload #20
    //   6768: iconst_0
    //   6769: iaload
    //   6770: bipush #19
    //   6772: ishl
    //   6773: ior
    //   6774: ixor
    //   6775: aload #20
    //   6777: iconst_0
    //   6778: iaload
    //   6779: bipush #22
    //   6781: iushr
    //   6782: aload #20
    //   6784: iconst_0
    //   6785: iaload
    //   6786: bipush #10
    //   6788: ishl
    //   6789: ior
    //   6790: ixor
    //   6791: aload #20
    //   6793: iconst_0
    //   6794: iaload
    //   6795: aload #20
    //   6797: iconst_1
    //   6798: iaload
    //   6799: iand
    //   6800: aload #20
    //   6802: iconst_2
    //   6803: iaload
    //   6804: aload #20
    //   6806: iconst_0
    //   6807: iaload
    //   6808: aload #20
    //   6810: iconst_1
    //   6811: iaload
    //   6812: ior
    //   6813: iand
    //   6814: ior
    //   6815: iadd
    //   6816: istore #23
    //   6818: aload #20
    //   6820: iconst_3
    //   6821: dup2
    //   6822: iaload
    //   6823: iload #22
    //   6825: iadd
    //   6826: iastore
    //   6827: aload #20
    //   6829: bipush #7
    //   6831: iload #22
    //   6833: iload #23
    //   6835: iadd
    //   6836: iastore
    //   6837: aload #20
    //   6839: bipush #7
    //   6841: iaload
    //   6842: istore #22
    //   6844: aload #20
    //   6846: bipush #7
    //   6848: aload #20
    //   6850: bipush #6
    //   6852: iaload
    //   6853: iastore
    //   6854: aload #20
    //   6856: bipush #6
    //   6858: aload #20
    //   6860: iconst_5
    //   6861: iaload
    //   6862: iastore
    //   6863: aload #20
    //   6865: iconst_5
    //   6866: aload #20
    //   6868: iconst_4
    //   6869: iaload
    //   6870: iastore
    //   6871: aload #20
    //   6873: iconst_4
    //   6874: aload #20
    //   6876: iconst_3
    //   6877: iaload
    //   6878: iastore
    //   6879: aload #20
    //   6881: iconst_3
    //   6882: aload #20
    //   6884: iconst_2
    //   6885: iaload
    //   6886: iastore
    //   6887: aload #20
    //   6889: iconst_2
    //   6890: aload #20
    //   6892: iconst_1
    //   6893: iaload
    //   6894: iastore
    //   6895: aload #20
    //   6897: iconst_1
    //   6898: aload #20
    //   6900: iconst_0
    //   6901: iaload
    //   6902: iastore
    //   6903: aload #20
    //   6905: iconst_0
    //   6906: iload #22
    //   6908: iastore
    //   6909: iinc #21, 1
    //   6912: iload_2
    //   6913: ifeq -> 6421
    //   6916: iconst_0
    //   6917: istore #21
    //   6919: iload #21
    //   6921: bipush #8
    //   6923: if_icmpge -> 6946
    //   6926: aload #8
    //   6928: iload #21
    //   6930: dup2
    //   6931: iaload
    //   6932: aload #20
    //   6934: iload #21
    //   6936: iaload
    //   6937: iadd
    //   6938: iastore
    //   6939: iinc #21, 1
    //   6942: iload_2
    //   6943: ifeq -> 6919
    //   6946: iinc #13, 64
    //   6949: iinc #17, -64
    //   6952: iload_2
    //   6953: ifeq -> 6342
    //   6956: iload #17
    //   6958: ifle -> 6994
    //   6961: iconst_0
    //   6962: istore #19
    //   6964: iload #19
    //   6966: iload #17
    //   6968: if_icmpge -> 6994
    //   6971: aload #9
    //   6973: iload #12
    //   6975: iload #19
    //   6977: iadd
    //   6978: aload #5
    //   6980: iload #13
    //   6982: iload #19
    //   6984: iadd
    //   6985: baload
    //   6986: bastore
    //   6987: iinc #19, 1
    //   6990: iload_2
    //   6991: ifeq -> 6964
    //   6994: bipush #8
    //   6996: newarray byte
    //   6998: astore #19
    //   7000: aload #19
    //   7002: iconst_0
    //   7003: iload #14
    //   7005: bipush #24
    //   7007: iushr
    //   7008: i2b
    //   7009: bastore
    //   7010: aload #19
    //   7012: iconst_1
    //   7013: iload #14
    //   7015: bipush #16
    //   7017: iushr
    //   7018: i2b
    //   7019: bastore
    //   7020: aload #19
    //   7022: iconst_2
    //   7023: iload #14
    //   7025: bipush #8
    //   7027: iushr
    //   7028: i2b
    //   7029: bastore
    //   7030: aload #19
    //   7032: iconst_3
    //   7033: iload #14
    //   7035: i2b
    //   7036: bastore
    //   7037: aload #19
    //   7039: iconst_4
    //   7040: iload #15
    //   7042: bipush #24
    //   7044: iushr
    //   7045: i2b
    //   7046: bastore
    //   7047: aload #19
    //   7049: iconst_5
    //   7050: iload #15
    //   7052: bipush #16
    //   7054: iushr
    //   7055: i2b
    //   7056: bastore
    //   7057: aload #19
    //   7059: bipush #6
    //   7061: iload #15
    //   7063: bipush #8
    //   7065: iushr
    //   7066: i2b
    //   7067: bastore
    //   7068: aload #19
    //   7070: bipush #7
    //   7072: iload #15
    //   7074: i2b
    //   7075: bastore
    //   7076: bipush #8
    //   7078: istore #11
    //   7080: aload #7
    //   7082: iconst_0
    //   7083: iaload
    //   7084: bipush #63
    //   7086: iand
    //   7087: istore #12
    //   7089: bipush #64
    //   7091: iload #12
    //   7093: isub
    //   7094: istore #18
    //   7096: aload #7
    //   7098: iconst_0
    //   7099: dup2
    //   7100: iaload
    //   7101: iload #11
    //   7103: iadd
    //   7104: iastore
    //   7105: aload #7
    //   7107: iconst_0
    //   7108: dup2
    //   7109: iaload
    //   7110: iconst_m1
    //   7111: iand
    //   7112: iastore
    //   7113: aload #7
    //   7115: iconst_0
    //   7116: iaload
    //   7117: iload #11
    //   7119: if_icmpge -> 7137
    //   7122: aload #7
    //   7124: iconst_1
    //   7125: dup2
    //   7126: iaload
    //   7127: iconst_1
    //   7128: iadd
    //   7129: iastore
    //   7130: goto -> 7137
    //   7133: invokestatic a : (Ljava/lang/Throwable;)Ljava/lang/Throwable;
    //   7136: athrow
    //   7137: iload #12
    //   7139: ifle -> 7753
    //   7142: iload #11
    //   7144: iload #18
    //   7146: if_icmplt -> 7753
    //   7149: goto -> 7156
    //   7152: invokestatic a : (Ljava/lang/Throwable;)Ljava/lang/Throwable;
    //   7155: athrow
    //   7156: iconst_0
    //   7157: istore #20
    //   7159: iload #20
    //   7161: iload #18
    //   7163: if_icmpge -> 7186
    //   7166: aload #9
    //   7168: iload #12
    //   7170: iload #20
    //   7172: iadd
    //   7173: aload #19
    //   7175: iload #20
    //   7177: baload
    //   7178: bastore
    //   7179: iinc #20, 1
    //   7182: iload_2
    //   7183: ifeq -> 7159
    //   7186: bipush #64
    //   7188: newarray int
    //   7190: astore #20
    //   7192: bipush #8
    //   7194: newarray int
    //   7196: astore #21
    //   7198: iconst_0
    //   7199: istore #22
    //   7201: iload #22
    //   7203: bipush #8
    //   7205: if_icmpge -> 7225
    //   7208: aload #21
    //   7210: iload #22
    //   7212: aload #8
    //   7214: iload #22
    //   7216: iaload
    //   7217: iastore
    //   7218: iinc #22, 1
    //   7221: iload_2
    //   7222: ifeq -> 7201
    //   7225: iconst_0
    //   7226: istore #22
    //   7228: iload #22
    //   7230: bipush #64
    //   7232: if_icmpge -> 7723
    //   7235: iload #22
    //   7237: bipush #16
    //   7239: if_icmpge -> 7320
    //   7242: aload #20
    //   7244: iload #22
    //   7246: aload #9
    //   7248: iconst_4
    //   7249: iload #22
    //   7251: imul
    //   7252: baload
    //   7253: sipush #255
    //   7256: iand
    //   7257: bipush #24
    //   7259: ishl
    //   7260: aload #9
    //   7262: iconst_4
    //   7263: iload #22
    //   7265: imul
    //   7266: iconst_1
    //   7267: iadd
    //   7268: baload
    //   7269: sipush #255
    //   7272: iand
    //   7273: bipush #16
    //   7275: ishl
    //   7276: ior
    //   7277: aload #9
    //   7279: iconst_4
    //   7280: iload #22
    //   7282: imul
    //   7283: iconst_2
    //   7284: iadd
    //   7285: baload
    //   7286: sipush #255
    //   7289: iand
    //   7290: bipush #8
    //   7292: ishl
    //   7293: ior
    //   7294: aload #9
    //   7296: iconst_4
    //   7297: iload #22
    //   7299: imul
    //   7300: iconst_3
    //   7301: iadd
    //   7302: baload
    //   7303: sipush #255
    //   7306: iand
    //   7307: ior
    //   7308: iastore
    //   7309: iload_2
    //   7310: ifeq -> 7463
    //   7313: goto -> 7320
    //   7316: invokestatic a : (Ljava/lang/Throwable;)Ljava/lang/Throwable;
    //   7319: athrow
    //   7320: aload #20
    //   7322: iload #22
    //   7324: aload #20
    //   7326: iload #22
    //   7328: iconst_2
    //   7329: isub
    //   7330: iaload
    //   7331: bipush #17
    //   7333: iushr
    //   7334: aload #20
    //   7336: iload #22
    //   7338: iconst_2
    //   7339: isub
    //   7340: iaload
    //   7341: bipush #15
    //   7343: ishl
    //   7344: ior
    //   7345: aload #20
    //   7347: iload #22
    //   7349: iconst_2
    //   7350: isub
    //   7351: iaload
    //   7352: bipush #19
    //   7354: iushr
    //   7355: aload #20
    //   7357: iload #22
    //   7359: iconst_2
    //   7360: isub
    //   7361: iaload
    //   7362: bipush #13
    //   7364: ishl
    //   7365: ior
    //   7366: ixor
    //   7367: aload #20
    //   7369: iload #22
    //   7371: iconst_2
    //   7372: isub
    //   7373: iaload
    //   7374: bipush #10
    //   7376: iushr
    //   7377: ixor
    //   7378: aload #20
    //   7380: iload #22
    //   7382: bipush #7
    //   7384: isub
    //   7385: iaload
    //   7386: iadd
    //   7387: aload #20
    //   7389: iload #22
    //   7391: bipush #15
    //   7393: isub
    //   7394: iaload
    //   7395: bipush #7
    //   7397: iushr
    //   7398: aload #20
    //   7400: iload #22
    //   7402: bipush #15
    //   7404: isub
    //   7405: iaload
    //   7406: bipush #25
    //   7408: ishl
    //   7409: ior
    //   7410: aload #20
    //   7412: iload #22
    //   7414: bipush #15
    //   7416: isub
    //   7417: iaload
    //   7418: bipush #18
    //   7420: iushr
    //   7421: aload #20
    //   7423: iload #22
    //   7425: bipush #15
    //   7427: isub
    //   7428: iaload
    //   7429: bipush #14
    //   7431: ishl
    //   7432: ior
    //   7433: ixor
    //   7434: aload #20
    //   7436: iload #22
    //   7438: bipush #15
    //   7440: isub
    //   7441: iaload
    //   7442: iconst_3
    //   7443: iushr
    //   7444: ixor
    //   7445: iadd
    //   7446: aload #20
    //   7448: iload #22
    //   7450: bipush #16
    //   7452: isub
    //   7453: iaload
    //   7454: iadd
    //   7455: iastore
    //   7456: goto -> 7463
    //   7459: invokestatic a : (Ljava/lang/Throwable;)Ljava/lang/Throwable;
    //   7462: athrow
    //   7463: aload #21
    //   7465: bipush #7
    //   7467: iaload
    //   7468: aload #21
    //   7470: iconst_4
    //   7471: iaload
    //   7472: bipush #6
    //   7474: iushr
    //   7475: aload #21
    //   7477: iconst_4
    //   7478: iaload
    //   7479: bipush #26
    //   7481: ishl
    //   7482: ior
    //   7483: aload #21
    //   7485: iconst_4
    //   7486: iaload
    //   7487: bipush #11
    //   7489: iushr
    //   7490: aload #21
    //   7492: iconst_4
    //   7493: iaload
    //   7494: bipush #21
    //   7496: ishl
    //   7497: ior
    //   7498: ixor
    //   7499: aload #21
    //   7501: iconst_4
    //   7502: iaload
    //   7503: bipush #25
    //   7505: iushr
    //   7506: aload #21
    //   7508: iconst_4
    //   7509: iaload
    //   7510: bipush #7
    //   7512: ishl
    //   7513: ior
    //   7514: ixor
    //   7515: iadd
    //   7516: aload #21
    //   7518: bipush #6
    //   7520: iaload
    //   7521: aload #21
    //   7523: iconst_4
    //   7524: iaload
    //   7525: aload #21
    //   7527: iconst_5
    //   7528: iaload
    //   7529: aload #21
    //   7531: bipush #6
    //   7533: iaload
    //   7534: ixor
    //   7535: iand
    //   7536: ixor
    //   7537: iadd
    //   7538: aload #6
    //   7540: iload #22
    //   7542: iaload
    //   7543: iadd
    //   7544: aload #20
    //   7546: iload #22
    //   7548: iaload
    //   7549: iadd
    //   7550: istore #23
    //   7552: aload #21
    //   7554: iconst_0
    //   7555: iaload
    //   7556: iconst_2
    //   7557: iushr
    //   7558: aload #21
    //   7560: iconst_0
    //   7561: iaload
    //   7562: bipush #30
    //   7564: ishl
    //   7565: ior
    //   7566: aload #21
    //   7568: iconst_0
    //   7569: iaload
    //   7570: bipush #13
    //   7572: iushr
    //   7573: aload #21
    //   7575: iconst_0
    //   7576: iaload
    //   7577: bipush #19
    //   7579: ishl
    //   7580: ior
    //   7581: ixor
    //   7582: aload #21
    //   7584: iconst_0
    //   7585: iaload
    //   7586: bipush #22
    //   7588: iushr
    //   7589: aload #21
    //   7591: iconst_0
    //   7592: iaload
    //   7593: bipush #10
    //   7595: ishl
    //   7596: ior
    //   7597: ixor
    //   7598: aload #21
    //   7600: iconst_0
    //   7601: iaload
    //   7602: aload #21
    //   7604: iconst_1
    //   7605: iaload
    //   7606: iand
    //   7607: aload #21
    //   7609: iconst_2
    //   7610: iaload
    //   7611: aload #21
    //   7613: iconst_0
    //   7614: iaload
    //   7615: aload #21
    //   7617: iconst_1
    //   7618: iaload
    //   7619: ior
    //   7620: iand
    //   7621: ior
    //   7622: iadd
    //   7623: istore #24
    //   7625: aload #21
    //   7627: iconst_3
    //   7628: dup2
    //   7629: iaload
    //   7630: iload #23
    //   7632: iadd
    //   7633: iastore
    //   7634: aload #21
    //   7636: bipush #7
    //   7638: iload #23
    //   7640: iload #24
    //   7642: iadd
    //   7643: iastore
    //   7644: aload #21
    //   7646: bipush #7
    //   7648: iaload
    //   7649: istore #23
    //   7651: aload #21
    //   7653: bipush #7
    //   7655: aload #21
    //   7657: bipush #6
    //   7659: iaload
    //   7660: iastore
    //   7661: aload #21
    //   7663: bipush #6
    //   7665: aload #21
    //   7667: iconst_5
    //   7668: iaload
    //   7669: iastore
    //   7670: aload #21
    //   7672: iconst_5
    //   7673: aload #21
    //   7675: iconst_4
    //   7676: iaload
    //   7677: iastore
    //   7678: aload #21
    //   7680: iconst_4
    //   7681: aload #21
    //   7683: iconst_3
    //   7684: iaload
    //   7685: iastore
    //   7686: aload #21
    //   7688: iconst_3
    //   7689: aload #21
    //   7691: iconst_2
    //   7692: iaload
    //   7693: iastore
    //   7694: aload #21
    //   7696: iconst_2
    //   7697: aload #21
    //   7699: iconst_1
    //   7700: iaload
    //   7701: iastore
    //   7702: aload #21
    //   7704: iconst_1
    //   7705: aload #21
    //   7707: iconst_0
    //   7708: iaload
    //   7709: iastore
    //   7710: aload #21
    //   7712: iconst_0
    //   7713: iload #23
    //   7715: iastore
    //   7716: iinc #22, 1
    //   7719: iload_2
    //   7720: ifeq -> 7228
    //   7723: iconst_0
    //   7724: istore #22
    //   7726: iload #22
    //   7728: bipush #8
    //   7730: if_icmpge -> 7753
    //   7733: aload #8
    //   7735: iload #22
    //   7737: dup2
    //   7738: iaload
    //   7739: aload #21
    //   7741: iload #22
    //   7743: iaload
    //   7744: iadd
    //   7745: iastore
    //   7746: iinc #22, 1
    //   7749: iload_2
    //   7750: ifeq -> 7726
    //   7753: bipush #32
    //   7755: newarray byte
    //   7757: astore #4
    //   7759: sipush #-32661
    //   7762: aload #4
    //   7764: iconst_0
    //   7765: aload #8
    //   7767: iconst_0
    //   7768: iaload
    //   7769: bipush #24
    //   7771: iushr
    //   7772: i2b
    //   7773: bastore
    //   7774: sipush #11130
    //   7777: aload #4
    //   7779: iconst_1
    //   7780: aload #8
    //   7782: iconst_0
    //   7783: iaload
    //   7784: bipush #16
    //   7786: iushr
    //   7787: i2b
    //   7788: bastore
    //   7789: aload #4
    //   7791: iconst_2
    //   7792: aload #8
    //   7794: iconst_0
    //   7795: iaload
    //   7796: bipush #8
    //   7798: iushr
    //   7799: i2b
    //   7800: bastore
    //   7801: aload #4
    //   7803: iconst_3
    //   7804: aload #8
    //   7806: iconst_0
    //   7807: iaload
    //   7808: i2b
    //   7809: bastore
    //   7810: aload #4
    //   7812: iconst_4
    //   7813: aload #8
    //   7815: iconst_1
    //   7816: iaload
    //   7817: bipush #24
    //   7819: iushr
    //   7820: i2b
    //   7821: bastore
    //   7822: aload #4
    //   7824: iconst_5
    //   7825: aload #8
    //   7827: iconst_1
    //   7828: iaload
    //   7829: bipush #16
    //   7831: iushr
    //   7832: i2b
    //   7833: bastore
    //   7834: aload #4
    //   7836: bipush #6
    //   7838: aload #8
    //   7840: iconst_1
    //   7841: iaload
    //   7842: bipush #8
    //   7844: iushr
    //   7845: i2b
    //   7846: bastore
    //   7847: aload #4
    //   7849: bipush #7
    //   7851: aload #8
    //   7853: iconst_1
    //   7854: iaload
    //   7855: i2b
    //   7856: bastore
    //   7857: aload #4
    //   7859: bipush #8
    //   7861: aload #8
    //   7863: iconst_2
    //   7864: iaload
    //   7865: bipush #24
    //   7867: iushr
    //   7868: i2b
    //   7869: bastore
    //   7870: aload #4
    //   7872: bipush #9
    //   7874: aload #8
    //   7876: iconst_2
    //   7877: iaload
    //   7878: bipush #16
    //   7880: iushr
    //   7881: i2b
    //   7882: bastore
    //   7883: aload #4
    //   7885: bipush #10
    //   7887: aload #8
    //   7889: iconst_2
    //   7890: iaload
    //   7891: bipush #8
    //   7893: iushr
    //   7894: i2b
    //   7895: bastore
    //   7896: aload #4
    //   7898: bipush #11
    //   7900: aload #8
    //   7902: iconst_2
    //   7903: iaload
    //   7904: i2b
    //   7905: bastore
    //   7906: aload #4
    //   7908: bipush #12
    //   7910: aload #8
    //   7912: iconst_3
    //   7913: iaload
    //   7914: bipush #24
    //   7916: iushr
    //   7917: i2b
    //   7918: bastore
    //   7919: aload #4
    //   7921: bipush #13
    //   7923: aload #8
    //   7925: iconst_3
    //   7926: iaload
    //   7927: bipush #16
    //   7929: iushr
    //   7930: i2b
    //   7931: bastore
    //   7932: aload #4
    //   7934: bipush #14
    //   7936: aload #8
    //   7938: iconst_3
    //   7939: iaload
    //   7940: bipush #8
    //   7942: iushr
    //   7943: i2b
    //   7944: bastore
    //   7945: aload #4
    //   7947: bipush #15
    //   7949: aload #8
    //   7951: iconst_3
    //   7952: iaload
    //   7953: i2b
    //   7954: bastore
    //   7955: aload #4
    //   7957: bipush #16
    //   7959: aload #8
    //   7961: iconst_4
    //   7962: iaload
    //   7963: bipush #24
    //   7965: iushr
    //   7966: i2b
    //   7967: bastore
    //   7968: aload #4
    //   7970: bipush #17
    //   7972: aload #8
    //   7974: iconst_4
    //   7975: iaload
    //   7976: bipush #16
    //   7978: iushr
    //   7979: i2b
    //   7980: bastore
    //   7981: aload #4
    //   7983: bipush #18
    //   7985: aload #8
    //   7987: iconst_4
    //   7988: iaload
    //   7989: bipush #8
    //   7991: iushr
    //   7992: i2b
    //   7993: bastore
    //   7994: aload #4
    //   7996: bipush #19
    //   7998: aload #8
    //   8000: iconst_4
    //   8001: iaload
    //   8002: i2b
    //   8003: bastore
    //   8004: aload #4
    //   8006: bipush #20
    //   8008: aload #8
    //   8010: iconst_5
    //   8011: iaload
    //   8012: bipush #24
    //   8014: iushr
    //   8015: i2b
    //   8016: bastore
    //   8017: aload #4
    //   8019: bipush #21
    //   8021: aload #8
    //   8023: iconst_5
    //   8024: iaload
    //   8025: bipush #16
    //   8027: iushr
    //   8028: i2b
    //   8029: bastore
    //   8030: aload #4
    //   8032: bipush #22
    //   8034: aload #8
    //   8036: iconst_5
    //   8037: iaload
    //   8038: bipush #8
    //   8040: iushr
    //   8041: i2b
    //   8042: bastore
    //   8043: aload #4
    //   8045: bipush #23
    //   8047: aload #8
    //   8049: iconst_5
    //   8050: iaload
    //   8051: i2b
    //   8052: bastore
    //   8053: aload #4
    //   8055: bipush #24
    //   8057: aload #8
    //   8059: bipush #6
    //   8061: iaload
    //   8062: bipush #24
    //   8064: iushr
    //   8065: i2b
    //   8066: bastore
    //   8067: aload #4
    //   8069: bipush #25
    //   8071: aload #8
    //   8073: bipush #6
    //   8075: iaload
    //   8076: bipush #16
    //   8078: iushr
    //   8079: i2b
    //   8080: bastore
    //   8081: aload #4
    //   8083: bipush #26
    //   8085: aload #8
    //   8087: bipush #6
    //   8089: iaload
    //   8090: bipush #8
    //   8092: iushr
    //   8093: i2b
    //   8094: bastore
    //   8095: aload #4
    //   8097: bipush #27
    //   8099: aload #8
    //   8101: bipush #6
    //   8103: iaload
    //   8104: i2b
    //   8105: bastore
    //   8106: aload #4
    //   8108: bipush #28
    //   8110: aload #8
    //   8112: bipush #7
    //   8114: iaload
    //   8115: bipush #24
    //   8117: iushr
    //   8118: i2b
    //   8119: bastore
    //   8120: aload #4
    //   8122: bipush #29
    //   8124: aload #8
    //   8126: bipush #7
    //   8128: iaload
    //   8129: bipush #16
    //   8131: iushr
    //   8132: i2b
    //   8133: bastore
    //   8134: aload #4
    //   8136: bipush #30
    //   8138: aload #8
    //   8140: bipush #7
    //   8142: iaload
    //   8143: bipush #8
    //   8145: iushr
    //   8146: i2b
    //   8147: bastore
    //   8148: aload #4
    //   8150: bipush #31
    //   8152: aload #8
    //   8154: bipush #7
    //   8156: iaload
    //   8157: i2b
    //   8158: bastore
    //   8159: new java/math/BigInteger
    //   8162: dup
    //   8163: aload #4
    //   8165: invokespecial <init> : ([B)V
    //   8168: invokevirtual abs : ()Ljava/math/BigInteger;
    //   8171: putstatic burp/Zl2t.ZS : Ljava/lang/Object;
    //   8174: invokestatic a : (II)Ljava/lang/String;
    //   8177: iconst_1
    //   8178: ldc burp/Zzoc
    //   8180: invokevirtual getClassLoader : ()Ljava/lang/ClassLoader;
    //   8183: invokestatic forName : (Ljava/lang/String;ZLjava/lang/ClassLoader;)Ljava/lang/Class;
    //   8186: invokevirtual getDeclaredFields : ()[Ljava/lang/reflect/Field;
    //   8189: astore_3
    //   8190: aload_3
    //   8191: arraylength
    //   8192: istore #4
    //   8194: iconst_0
    //   8195: istore #5
    //   8197: iload #5
    //   8199: iload #4
    //   8201: if_icmpge -> 8338
    //   8204: aload_3
    //   8205: iload #5
    //   8207: aaload
    //   8208: astore #6
    //   8210: aload #6
    //   8212: invokevirtual getModifiers : ()I
    //   8215: invokestatic isStatic : (I)Z
    //   8218: ifne -> 8228
    //   8221: goto -> 8331
    //   8224: invokestatic a : (Ljava/lang/Throwable;)Ljava/lang/Throwable;
    //   8227: athrow
    //   8228: aload #6
    //   8230: invokevirtual getType : ()Ljava/lang/Class;
    //   8233: astore #7
    //   8235: aload #7
    //   8237: ifnull -> 8318
    //   8240: aload #7
    //   8242: invokevirtual isPrimitive : ()Z
    //   8245: ifne -> 8318
    //   8248: goto -> 8255
    //   8251: invokestatic a : (Ljava/lang/Throwable;)Ljava/lang/Throwable;
    //   8254: athrow
    //   8255: aload #7
    //   8257: invokevirtual getPackage : ()Ljava/lang/Package;
    //   8260: ifnull -> 8318
    //   8263: goto -> 8270
    //   8266: invokestatic a : (Ljava/lang/Throwable;)Ljava/lang/Throwable;
    //   8269: athrow
    //   8270: aload #7
    //   8272: invokevirtual getPackage : ()Ljava/lang/Package;
    //   8275: invokevirtual getName : ()Ljava/lang/String;
    //   8278: ifnull -> 8318
    //   8281: goto -> 8288
    //   8284: invokestatic a : (Ljava/lang/Throwable;)Ljava/lang/Throwable;
    //   8287: athrow
    //   8288: aload #7
    //   8290: invokevirtual getPackage : ()Ljava/lang/Package;
    //   8293: invokevirtual getName : ()Ljava/lang/String;
    //   8296: sipush #-32664
    //   8299: sipush #-30100
    //   8302: invokestatic a : (II)Ljava/lang/String;
    //   8305: invokevirtual startsWith : (Ljava/lang/String;)Z
    //   8308: ifne -> 8318
    //   8311: goto -> 8318
    //   8314: invokestatic a : (Ljava/lang/Throwable;)Ljava/lang/Throwable;
    //   8317: athrow
    //   8318: aload #6
    //   8320: iconst_1
    //   8321: invokevirtual setAccessible : (Z)V
    //   8324: aload #6
    //   8326: aconst_null
    //   8327: invokevirtual get : (Ljava/lang/Object;)Ljava/lang/Object;
    //   8330: pop
    //   8331: iinc #5, 1
    //   8334: iload_2
    //   8335: ifeq -> 8197
    //   8338: sipush #-32658
    //   8341: sipush #-16398
    //   8344: invokestatic a : (II)Ljava/lang/String;
    //   8347: invokestatic forName : (Ljava/lang/String;)Ljava/lang/Class;
    //   8350: invokevirtual getDeclaredMethods : ()[Ljava/lang/reflect/Method;
    //   8353: astore_3
    //   8354: aload_3
    //   8355: arraylength
    //   8356: istore #4
    //   8358: iconst_0
    //   8359: istore #5
    //   8361: iload #5
    //   8363: iload #4
    //   8365: if_icmpge -> 8497
    //   8368: aload_3
    //   8369: iload #5
    //   8371: aaload
    //   8372: astore #6
    //   8374: aload #6
    //   8376: invokevirtual getParameterTypes : ()[Ljava/lang/Class;
    //   8379: pop
    //   8380: aload #6
    //   8382: invokevirtual getModifiers : ()I
    //   8385: invokestatic isStatic : (I)Z
    //   8388: ifeq -> 8483
    //   8391: aload #6
    //   8393: invokevirtual getParameterTypes : ()[Ljava/lang/Class;
    //   8396: arraylength
    //   8397: iconst_2
    //   8398: if_icmpne -> 8483
    //   8401: goto -> 8408
    //   8404: invokestatic a : (Ljava/lang/Throwable;)Ljava/lang/Throwable;
    //   8407: athrow
    //   8408: aload #6
    //   8410: invokevirtual getReturnType : ()Ljava/lang/Class;
    //   8413: getstatic java/lang/Void.TYPE : Ljava/lang/Class;
    //   8416: invokevirtual equals : (Ljava/lang/Object;)Z
    //   8419: ifeq -> 8483
    //   8422: goto -> 8429
    //   8425: invokestatic a : (Ljava/lang/Throwable;)Ljava/lang/Throwable;
    //   8428: athrow
    //   8429: aload #6
    //   8431: iconst_1
    //   8432: invokevirtual setAccessible : (Z)V
    //   8435: aload #6
    //   8437: aconst_null
    //   8438: iconst_2
    //   8439: anewarray java/lang/Object
    //   8442: dup
    //   8443: iconst_0
    //   8444: aload_0
    //   8445: aastore
    //   8446: dup
    //   8447: iconst_1
    //   8448: aload_1
    //   8449: ifnonnull -> 8467
    //   8452: goto -> 8459
    //   8455: invokestatic a : (Ljava/lang/Throwable;)Ljava/lang/Throwable;
    //   8458: athrow
    //   8459: aload_1
    //   8460: goto -> 8474
    //   8463: invokestatic a : (Ljava/lang/Throwable;)Ljava/lang/Throwable;
    //   8466: athrow
    //   8467: aload_1
    //   8468: checkcast [B
    //   8471: invokevirtual clone : ()Ljava/lang/Object;
    //   8474: aastore
    //   8475: invokevirtual invoke : (Ljava/lang/Object;[Ljava/lang/Object;)Ljava/lang/Object;
    //   8478: pop
    //   8479: iload_2
    //   8480: ifeq -> 8497
    //   8483: iinc #5, 1
    //   8486: iload_2
    //   8487: ifeq -> 8361
    //   8490: goto -> 8497
    //   8493: invokestatic a : (Ljava/lang/Throwable;)Ljava/lang/Throwable;
    //   8496: athrow
    //   8497: getstatic burp/Zs4g.ZV : Ljava/lang/String;
    //   8500: getstatic burp/Zmf6.ZD : Ljava/lang/Object;
    //   8503: checkcast java/math/BigInteger
    //   8506: invokevirtual intValue : ()I
    //   8509: bipush #32
    //   8511: irem
    //   8512: invokestatic abs : (I)I
    //   8515: invokevirtual charAt : (I)C
    //   8518: getstatic burp/Zdv.Zz : Ljava/lang/String;
    //   8521: getstatic burp/Zlwm.Ze : Ljava/lang/Object;
    //   8524: checkcast java/math/BigInteger
    //   8527: invokevirtual intValue : ()I
    //   8530: bipush #32
    //   8532: irem
    //   8533: invokestatic abs : (I)I
    //   8536: invokevirtual charAt : (I)C
    //   8539: if_icmpgt -> 8654
    //   8542: getstatic burp/Zrzg.ZX : Ljava/lang/String;
    //   8545: getstatic burp/Zzpm.Ze : Ljava/lang/Object;
    //   8548: checkcast java/math/BigInteger
    //   8551: invokevirtual intValue : ()I
    //   8554: bipush #32
    //   8556: irem
    //   8557: invokestatic abs : (I)I
    //   8560: invokevirtual charAt : (I)C
    //   8563: getstatic burp/Ztnn.ZS : Ljava/lang/String;
    //   8566: getstatic burp/Ze4g.Zz : Ljava/lang/Object;
    //   8569: checkcast java/math/BigInteger
    //   8572: invokevirtual intValue : ()I
    //   8575: bipush #32
    //   8577: irem
    //   8578: invokestatic abs : (I)I
    //   8581: invokevirtual charAt : (I)C
    //   8584: if_icmpgt -> 8654
    //   8587: goto -> 8594
    //   8590: invokestatic a : (Ljava/lang/Throwable;)Ljava/lang/Throwable;
    //   8593: athrow
    //   8594: getstatic burp/Zzgb.ZT : Ljava/lang/String;
    //   8597: getstatic burp/Zrn4.Zq : Ljava/lang/Object;
    //   8600: checkcast java/math/BigInteger
    //   8603: invokevirtual intValue : ()I
    //   8606: bipush #32
    //   8608: irem
    //   8609: invokestatic abs : (I)I
    //   8612: invokevirtual charAt : (I)C
    //   8615: getstatic burp/Ze1k.ZI : Ljava/lang/String;
    //   8618: getstatic burp/Zg61.Zp : Ljava/lang/Object;
    //   8621: checkcast java/math/BigInteger
    //   8624: invokevirtual intValue : ()I
    //   8627: bipush #32
    //   8629: irem
    //   8630: invokestatic abs : (I)I
    //   8633: invokevirtual charAt : (I)C
    //   8636: if_icmple -> 8654
    //   8639: goto -> 8646
    //   8642: invokestatic a : (Ljava/lang/Throwable;)Ljava/lang/Throwable;
    //   8645: athrow
    //   8646: iconst_1
    //   8647: goto -> 8655
    //   8650: invokestatic a : (Ljava/lang/Throwable;)Ljava/lang/Throwable;
    //   8653: athrow
    //   8654: iconst_0
    //   8655: ireturn
    //   8656: astore_3
    //   8657: new java/lang/Exception
    //   8660: dup
    //   8661: aload_3
    //   8662: invokevirtual getMessage : ()Ljava/lang/String;
    //   8665: invokespecial <init> : (Ljava/lang/String;)V
    //   8668: athrow
    // Exception table:
    //   from	to	target	type
    //   4	8655	8656	java/lang/Throwable
    //   823	857	860	java/lang/Throwable
    //   952	1030	1033	java/lang/Throwable
    //   959	1173	1176	java/lang/Throwable
    //   1550	1565	1565	java/lang/Throwable
    //   1592	1626	1629	java/lang/Throwable
    //   1636	1648	1651	java/lang/Throwable
    //   1734	1812	1815	java/lang/Throwable
    //   1741	1955	1958	java/lang/Throwable
    //   2355	2433	2436	java/lang/Throwable
    //   2362	2576	2579	java/lang/Throwable
    //   3023	3057	3060	java/lang/Throwable
    //   3064	3076	3079	java/lang/Throwable
    //   3162	3240	3243	java/lang/Throwable
    //   3169	3383	3386	java/lang/Throwable
    //   4896	4930	4933	java/lang/Throwable
    //   5025	5103	5106	java/lang/Throwable
    //   5032	5246	5249	java/lang/Throwable
    //   5623	5638	5638	java/lang/Throwable
    //   5665	5699	5702	java/lang/Throwable
    //   5709	5721	5724	java/lang/Throwable
    //   5807	5885	5888	java/lang/Throwable
    //   5814	6028	6031	java/lang/Throwable
    //   6428	6506	6509	java/lang/Throwable
    //   6435	6649	6652	java/lang/Throwable
    //   7096	7130	7133	java/lang/Throwable
    //   7137	7149	7152	java/lang/Throwable
    //   7235	7313	7316	java/lang/Throwable
    //   7242	7456	7459	java/lang/Throwable
    //   8210	8224	8224	java/lang/Throwable
    //   8235	8248	8251	java/lang/Throwable
    //   8240	8263	8266	java/lang/Throwable
    //   8255	8281	8284	java/lang/Throwable
    //   8270	8311	8314	java/lang/Throwable
    //   8374	8401	8404	java/lang/Throwable
    //   8391	8422	8425	java/lang/Throwable
    //   8408	8452	8455	java/lang/Throwable
    //   8429	8463	8463	java/lang/Throwable
    //   8474	8490	8493	java/lang/Throwable
    //   8497	8587	8590	java/lang/Throwable
    //   8542	8639	8642	java/lang/Throwable
    //   8594	8650	8650	java/lang/Throwable
  }
  
  static {
    // Byte code:
    //   0: bipush #9
    //   2: anewarray java/lang/String
    //   5: astore #5
    //   7: iconst_0
    //   8: istore_3
    //   9: ldc ' 3N]aVs\\t#; (lf<[\\tc7|I\\t=/h`\\bzMu(>!T6;\\r2!*DUC}<+;hC!S54IR!qN\\t\\nvMT\\tJn#yk?(C\\f.LbHU_#F$mQ6qe-^\\r;mMG 34pNPjJzw:jv`ERU'
    //   11: dup
    //   12: astore_2
    //   13: invokevirtual length : ()I
    //   16: istore #4
    //   18: bipush #32
    //   20: istore_1
    //   21: iconst_m1
    //   22: istore_0
    //   23: bipush #76
    //   25: iinc #0, 1
    //   28: aload_2
    //   29: iload_0
    //   30: dup
    //   31: iload_1
    //   32: iadd
    //   33: invokevirtual substring : (II)Ljava/lang/String;
    //   36: iconst_m1
    //   37: goto -> 142
    //   40: aload #5
    //   42: swap
    //   43: iload_3
    //   44: iinc #3, 1
    //   47: swap
    //   48: aastore
    //   49: iload_0
    //   50: iload_1
    //   51: iadd
    //   52: dup
    //   53: istore_0
    //   54: iload #4
    //   56: if_icmpge -> 68
    //   59: aload_2
    //   60: iload_0
    //   61: invokevirtual charAt : (I)C
    //   64: istore_1
    //   65: goto -> 23
    //   68: ldc '-hF\\tv54'
    //   70: dup
    //   71: astore_2
    //   72: invokevirtual length : ()I
    //   75: istore #4
    //   77: iconst_4
    //   78: istore_1
    //   79: iconst_m1
    //   80: istore_0
    //   81: bipush #48
    //   83: iinc #0, 1
    //   86: aload_2
    //   87: iload_0
    //   88: dup
    //   89: iload_1
    //   90: iadd
    //   91: invokevirtual substring : (II)Ljava/lang/String;
    //   94: iconst_0
    //   95: goto -> 142
    //   98: aload #5
    //   100: swap
    //   101: iload_3
    //   102: iinc #3, 1
    //   105: swap
    //   106: aastore
    //   107: iload_0
    //   108: iload_1
    //   109: iadd
    //   110: dup
    //   111: istore_0
    //   112: iload #4
    //   114: if_icmpge -> 126
    //   117: aload_2
    //   118: iload_0
    //   119: invokevirtual charAt : (I)C
    //   122: istore_1
    //   123: goto -> 81
    //   126: aload #5
    //   128: putstatic burp/Zzl4.a : [Ljava/lang/String;
    //   131: bipush #9
    //   133: anewarray java/lang/String
    //   136: putstatic burp/Zzl4.b : [Ljava/lang/String;
    //   139: goto -> 300
    //   142: dup_x2
    //   143: pop
    //   144: invokevirtual toCharArray : ()[C
    //   147: dup_x1
    //   148: arraylength
    //   149: dup_x2
    //   150: pop
    //   151: iconst_0
    //   152: istore #6
    //   154: dup2_x1
    //   155: pop2
    //   156: dup_x2
    //   157: iconst_1
    //   158: if_icmpgt -> 260
    //   161: dup2
    //   162: swap
    //   163: iload #6
    //   165: dup2_x1
    //   166: caload
    //   167: swap
    //   168: iload #6
    //   170: bipush #7
    //   172: irem
    //   173: tableswitch default -> 242, 0 -> 212, 1 -> 217, 2 -> 222, 3 -> 227, 4 -> 232, 5 -> 237
    //   212: bipush #20
    //   214: goto -> 244
    //   217: bipush #107
    //   219: goto -> 244
    //   222: bipush #37
    //   224: goto -> 244
    //   227: bipush #66
    //   229: goto -> 244
    //   232: bipush #40
    //   234: goto -> 244
    //   237: bipush #93
    //   239: goto -> 244
    //   242: bipush #89
    //   244: ixor
    //   245: ixor
    //   246: i2c
    //   247: castore
    //   248: iinc #6, 1
    //   251: dup
    //   252: ifne -> 260
    //   255: dup2
    //   256: dup_x1
    //   257: goto -> 165
    //   260: dup2_x1
    //   261: pop2
    //   262: dup_x2
    //   263: iload #6
    //   265: if_icmpgt -> 161
    //   268: pop
    //   269: new java/lang/String
    //   272: dup_x1
    //   273: swap
    //   274: invokespecial <init> : ([C)V
    //   277: invokevirtual intern : ()Ljava/lang/String;
    //   280: swap
    //   281: pop
    //   282: swap
    //   283: tableswitch default -> 40, 0 -> 98
    //   300: new java/math/BigInteger
    //   303: dup
    //   304: sipush #-32660
    //   307: sipush #30920
    //   310: invokestatic a : (II)Ljava/lang/String;
    //   313: invokespecial <init> : (Ljava/lang/String;)V
    //   316: putstatic burp/Zzl4.ZX : Ljava/lang/Object;
    //   319: sipush #-32657
    //   322: sipush #32571
    //   325: invokestatic a : (II)Ljava/lang/String;
    //   328: putstatic burp/Zzl4.ZT : Ljava/lang/String;
    //   331: return
  }
  
  private static Throwable a(Throwable paramThrowable) {
    return paramThrowable;
  }
  
  private static String a(int paramInt1, int paramInt2) {
    int i = (paramInt1 ^ 0xFFFF806F) & 0xFFFF;
    if (b[i] == null) {
      char[] arrayOfChar = a[i].toCharArray();
      switch (arrayOfChar[0] & 0xFF) {
        case 0:
        
        case 1:
        
        case 2:
        
        case 3:
        
        case 4:
        
        case 5:
        
        case 6:
        
        case 7:
        
        case 8:
        
        case 9:
        
        case 10:
        
        case 11:
        
        case 12:
        
        case 13:
        
        case 14:
        
        case 15:
        
        case 16:
        
        case 17:
        
        case 18:
        
        case 19:
        
        case 20:
        
        case 21:
        
        case 22:
        
        case 23:
        
        case 24:
        
        case 25:
        
        case 26:
        
        case 27:
        
        case 28:
        
        case 29:
        
        case 30:
        
        case 31:
        
        case 32:
        
        case 33:
        
        case 34:
        
        case 35:
        
        case 36:
        
        case 37:
        
        case 38:
        
        case 39:
        
        case 40:
        
        case 41:
        
        case 42:
        
        case 43:
        
        case 44:
        
        case 45:
        
        case 46:
        
        case 47:
        
        case 48:
        
        case 49:
        
        case 50:
        
        case 51:
        
        case 52:
        
        case 53:
        
        case 54:
        
        case 55:
        
        case 56:
        
        case 57:
        
        case 58:
        
        case 59:
        
        case 60:
        
        case 61:
        
        case 62:
        
        case 63:
        
        case 64:
        
        case 65:
        
        case 66:
        
        case 67:
        
        case 68:
        
        case 69:
        
        case 70:
        
        case 71:
        
        case 72:
        
        case 73:
        
        case 74:
        
        case 75:
        
        case 76:
        
        case 77:
        
        case 78:
        
        case 79:
        
        case 80:
        
        case 81:
        
        case 82:
        
        case 83:
        
        case 84:
        
        case 85:
        
        case 86:
        
        case 87:
        
        case 88:
        
        case 89:
        
        case 90:
        
        case 91:
        
        case 92:
        
        case 93:
        
        case 94:
        
        case 95:
        
        case 96:
        
        case 97:
        
        case 98:
        
        case 99:
        
        case 100:
        
        case 101:
        
        case 102:
        
        case 103:
        
        case 104:
        
        case 105:
        
        case 106:
        
        case 107:
        
        case 108:
        
        case 109:
        
        case 110:
        
        case 111:
        
        case 112:
        
        case 113:
        
        case 114:
        
        case 115:
        
        case 116:
        
        case 117:
        
        case 118:
        
        case 119:
        
        case 120:
        
        case 121:
        
        case 122:
        
        case 123:
        
        case 124:
        
        case 125:
        
        case 126:
        
        case 127:
        
        case 128:
        
        case 129:
        
        case 130:
        
        case 131:
        
        case 132:
        
        case 133:
        
        case 134:
        
        case 135:
        
        case 136:
        
        case 137:
        
        case 138:
        
        case 139:
        
        case 140:
        
        case 141:
        
        case 142:
        
        case 143:
        
        case 144:
        
        case 145:
        
        case 146:
        
        case 147:
        
        case 148:
        
        case 149:
        
        case 150:
        
        case 151:
        
        case 152:
        
        case 153:
        
        case 154:
        
        case 155:
        
        case 156:
        
        case 157:
        
        case 158:
        
        case 159:
        
        case 160:
        
        case 161:
        
        case 162:
        
        case 163:
        
        case 164:
        
        case 165:
        
        case 166:
        
        case 167:
        
        case 168:
        
        case 169:
        
        case 170:
        
        case 171:
        
        case 172:
        
        case 173:
        
        case 174:
        
        case 175:
        
        case 176:
        
        case 177:
        
        case 178:
        
        case 179:
        
        case 180:
        
        case 181:
        
        case 182:
        
        case 183:
        
        case 184:
        
        case 185:
        
        case 186:
        
        case 187:
        
        case 188:
        
        case 189:
        
        case 190:
        
        case 191:
        
        case 192:
        
        case 193:
        
        case 194:
        
        case 195:
        
        case 196:
        
        case 197:
        
        case 198:
        
        case 199:
        
        case 200:
        
        case 201:
        
        case 202:
        
        case 203:
        
        case 204:
        
        case 205:
        
        case 206:
        
        case 207:
        
        case 208:
        
        case 209:
        
        case 210:
        
        case 211:
        
        case 212:
        
        case 213:
        
        case 214:
        
        case 215:
        
        case 216:
        
        case 217:
        
        case 218:
        
        case 219:
        
        case 220:
        
        case 221:
        
        case 222:
        
        case 223:
        
        case 224:
        
        case 225:
        
        case 226:
        
        case 227:
        
        case 228:
        
        case 229:
        
        case 230:
        
        case 231:
        
        case 232:
        
        case 233:
        
        case 234:
        
        case 235:
        
        case 236:
        
        case 237:
        
        case 238:
        
        case 239:
        
        case 240:
        
        case 241:
        
        case 242:
        
        case 243:
        
        case 244:
        
        case 245:
        
        case 246:
        
        case 247:
        
        case 248:
        
        case 249:
        
        case 250:
        
        case 251:
        
        case 252:
        
        case 253:
        
        case 254:
        
        default:
          break;
      } 
      char c = '';
      int j = (paramInt2 & 0xFF) - c;
      if (j < 0)
        j += 256; 
      int k = ((paramInt2 & 0xFFFF) >>> 8) - c;
      if (k < 0)
        k += 256; 
      for (byte b = 0; b < arrayOfChar.length; b++) {
        int m = b % 2;
        if (m == 0) {
          arrayOfChar[b] = (char)(arrayOfChar[b] ^ j);
          j = ((j >>> 3 | j << 5) ^ arrayOfChar[b]) & 0xFF;
        } else {
          arrayOfChar[b] = (char)(arrayOfChar[b] ^ k);
          k = ((k >>> 3 | k << 5) ^ arrayOfChar[b]) & 0xFF;
        } 
      } 
      b[i] = (new String(arrayOfChar)).intern();
    } 
    return b[i];
  }
}


/* Location:              C:\Program Files\BurpSuitePro\burpsuite_pro.jar!\burp\Zzl4.class
 * Java compiler version: 21 (65.0)
 * JD-Core Version:       1.1.3
 */