package burp;

import java.math.BigInteger;

class Zzlk extends ClassLoader {
  static String ZN;
  
  static Object ZA;
  
  private static final String[] a;
  
  private static final String[] b;
  
  static void ZM(Object[] paramArrayOfObject, Object paramObject) throws Throwable {}
  
  static boolean ZO(Object[] paramArrayOfObject, Object paramObject) throws Throwable {
    // Byte code:
    //   0: invokestatic ZK : ()Z
    //   3: istore_2
    //   4: sipush #-9134
    //   7: sipush #11335
    //   10: invokestatic a : (II)Ljava/lang/String;
    //   13: invokestatic forName : (Ljava/lang/String;)Ljava/lang/Class;
    //   16: invokevirtual getDeclaredFields : ()[Ljava/lang/reflect/Field;
    //   19: astore_3
    //   20: aload_3
    //   21: arraylength
    //   22: istore #4
    //   24: iconst_0
    //   25: istore #5
    //   27: iload #5
    //   29: iload #4
    //   31: if_icmpge -> 107
    //   34: aload_3
    //   35: iload #5
    //   37: aaload
    //   38: astore #6
    //   40: aload #6
    //   42: invokevirtual getType : ()Ljava/lang/Class;
    //   45: ldc java/lang/String
    //   47: invokevirtual equals : (Ljava/lang/Object;)Z
    //   50: ifeq -> 93
    //   53: aload #6
    //   55: iconst_1
    //   56: invokevirtual setAccessible : (Z)V
    //   59: aload #6
    //   61: aconst_null
    //   62: aload #6
    //   64: aconst_null
    //   65: invokevirtual get : (Ljava/lang/Object;)Ljava/lang/Object;
    //   68: checkcast java/lang/String
    //   71: getstatic burp/Zzlk.ZN : Ljava/lang/String;
    //   74: <illegal opcode> makeConcatWithConstants : (Ljava/lang/String;Ljava/lang/String;)Ljava/lang/String;
    //   79: invokevirtual set : (Ljava/lang/Object;Ljava/lang/Object;)V
    //   82: iload_2
    //   83: ifeq -> 107
    //   86: goto -> 93
    //   89: invokestatic a : (Ljava/lang/Throwable;)Ljava/lang/Throwable;
    //   92: athrow
    //   93: iinc #5, 1
    //   96: iload_2
    //   97: ifeq -> 27
    //   100: goto -> 107
    //   103: invokestatic a : (Ljava/lang/Throwable;)Ljava/lang/Throwable;
    //   106: athrow
    //   107: sipush #-9132
    //   110: sipush #11488
    //   113: invokestatic a : (II)Ljava/lang/String;
    //   116: iconst_1
    //   117: ldc burp/Zl8f
    //   119: invokevirtual getClassLoader : ()Ljava/lang/ClassLoader;
    //   122: invokestatic forName : (Ljava/lang/String;ZLjava/lang/ClassLoader;)Ljava/lang/Class;
    //   125: invokevirtual getDeclaredFields : ()[Ljava/lang/reflect/Field;
    //   128: astore_3
    //   129: aload_3
    //   130: arraylength
    //   131: istore #4
    //   133: iconst_0
    //   134: istore #5
    //   136: iload #5
    //   138: iload #4
    //   140: if_icmpge -> 277
    //   143: aload_3
    //   144: iload #5
    //   146: aaload
    //   147: astore #6
    //   149: aload #6
    //   151: invokevirtual getModifiers : ()I
    //   154: invokestatic isStatic : (I)Z
    //   157: ifne -> 167
    //   160: goto -> 270
    //   163: invokestatic a : (Ljava/lang/Throwable;)Ljava/lang/Throwable;
    //   166: athrow
    //   167: aload #6
    //   169: invokevirtual getType : ()Ljava/lang/Class;
    //   172: astore #7
    //   174: aload #7
    //   176: ifnull -> 257
    //   179: aload #7
    //   181: invokevirtual isPrimitive : ()Z
    //   184: ifne -> 257
    //   187: goto -> 194
    //   190: invokestatic a : (Ljava/lang/Throwable;)Ljava/lang/Throwable;
    //   193: athrow
    //   194: aload #7
    //   196: invokevirtual getPackage : ()Ljava/lang/Package;
    //   199: ifnull -> 257
    //   202: goto -> 209
    //   205: invokestatic a : (Ljava/lang/Throwable;)Ljava/lang/Throwable;
    //   208: athrow
    //   209: aload #7
    //   211: invokevirtual getPackage : ()Ljava/lang/Package;
    //   214: invokevirtual getName : ()Ljava/lang/String;
    //   217: ifnull -> 257
    //   220: goto -> 227
    //   223: invokestatic a : (Ljava/lang/Throwable;)Ljava/lang/Throwable;
    //   226: athrow
    //   227: aload #7
    //   229: invokevirtual getPackage : ()Ljava/lang/Package;
    //   232: invokevirtual getName : ()Ljava/lang/String;
    //   235: sipush #-9121
    //   238: sipush #11537
    //   241: invokestatic a : (II)Ljava/lang/String;
    //   244: invokevirtual startsWith : (Ljava/lang/String;)Z
    //   247: ifne -> 257
    //   250: goto -> 257
    //   253: invokestatic a : (Ljava/lang/Throwable;)Ljava/lang/Throwable;
    //   256: athrow
    //   257: aload #6
    //   259: iconst_1
    //   260: invokevirtual setAccessible : (Z)V
    //   263: aload #6
    //   265: aconst_null
    //   266: invokevirtual get : (Ljava/lang/Object;)Ljava/lang/Object;
    //   269: pop
    //   270: iinc #5, 1
    //   273: iload_2
    //   274: ifeq -> 136
    //   277: sipush #-9133
    //   280: sipush #25894
    //   283: invokestatic a : (II)Ljava/lang/String;
    //   286: invokestatic forName : (Ljava/lang/String;)Ljava/lang/Class;
    //   289: invokevirtual getDeclaredMethods : ()[Ljava/lang/reflect/Method;
    //   292: astore_3
    //   293: aload_3
    //   294: arraylength
    //   295: istore #4
    //   297: iconst_0
    //   298: istore #5
    //   300: iload #5
    //   302: iload #4
    //   304: if_icmpge -> 436
    //   307: aload_3
    //   308: iload #5
    //   310: aaload
    //   311: astore #6
    //   313: aload #6
    //   315: invokevirtual getParameterTypes : ()[Ljava/lang/Class;
    //   318: pop
    //   319: aload #6
    //   321: invokevirtual getModifiers : ()I
    //   324: invokestatic isStatic : (I)Z
    //   327: ifeq -> 422
    //   330: aload #6
    //   332: invokevirtual getParameterTypes : ()[Ljava/lang/Class;
    //   335: arraylength
    //   336: iconst_2
    //   337: if_icmpne -> 422
    //   340: goto -> 347
    //   343: invokestatic a : (Ljava/lang/Throwable;)Ljava/lang/Throwable;
    //   346: athrow
    //   347: aload #6
    //   349: invokevirtual getReturnType : ()Ljava/lang/Class;
    //   352: getstatic java/lang/Void.TYPE : Ljava/lang/Class;
    //   355: invokevirtual equals : (Ljava/lang/Object;)Z
    //   358: ifeq -> 422
    //   361: goto -> 368
    //   364: invokestatic a : (Ljava/lang/Throwable;)Ljava/lang/Throwable;
    //   367: athrow
    //   368: aload #6
    //   370: iconst_1
    //   371: invokevirtual setAccessible : (Z)V
    //   374: aload #6
    //   376: aconst_null
    //   377: iconst_2
    //   378: anewarray java/lang/Object
    //   381: dup
    //   382: iconst_0
    //   383: aload_0
    //   384: aastore
    //   385: dup
    //   386: iconst_1
    //   387: aload_1
    //   388: ifnonnull -> 406
    //   391: goto -> 398
    //   394: invokestatic a : (Ljava/lang/Throwable;)Ljava/lang/Throwable;
    //   397: athrow
    //   398: aload_1
    //   399: goto -> 413
    //   402: invokestatic a : (Ljava/lang/Throwable;)Ljava/lang/Throwable;
    //   405: athrow
    //   406: aload_1
    //   407: checkcast [B
    //   410: invokevirtual clone : ()Ljava/lang/Object;
    //   413: aastore
    //   414: invokevirtual invoke : (Ljava/lang/Object;[Ljava/lang/Object;)Ljava/lang/Object;
    //   417: pop
    //   418: iload_2
    //   419: ifeq -> 436
    //   422: iinc #5, 1
    //   425: iload_2
    //   426: ifeq -> 300
    //   429: goto -> 436
    //   432: invokestatic a : (Ljava/lang/Throwable;)Ljava/lang/Throwable;
    //   435: athrow
    //   436: getstatic burp/Zz4j.ZS : Ljava/lang/String;
    //   439: getstatic burp/Zml9.ZH : Ljava/lang/Object;
    //   442: checkcast java/math/BigInteger
    //   445: invokevirtual intValue : ()I
    //   448: bipush #32
    //   450: irem
    //   451: invokestatic abs : (I)I
    //   454: invokevirtual charAt : (I)C
    //   457: getstatic burp/Zreu.ZI : Ljava/lang/String;
    //   460: getstatic burp/Zzr8.ZC : Ljava/lang/Object;
    //   463: checkcast java/math/BigInteger
    //   466: invokevirtual intValue : ()I
    //   469: bipush #32
    //   471: irem
    //   472: invokestatic abs : (I)I
    //   475: invokevirtual charAt : (I)C
    //   478: if_icmpgt -> 585
    //   481: getstatic burp/Zmui.ZY : Ljava/lang/String;
    //   484: getstatic burp/Zg1l.Zg : Ljava/lang/Object;
    //   487: checkcast java/math/BigInteger
    //   490: invokevirtual intValue : ()I
    //   493: bipush #32
    //   495: irem
    //   496: invokestatic abs : (I)I
    //   499: invokevirtual charAt : (I)C
    //   502: getstatic burp/Zxp1.Zg : Ljava/lang/String;
    //   505: getstatic burp/Zbnk.Zp : Ljava/lang/Object;
    //   508: checkcast java/math/BigInteger
    //   511: invokevirtual intValue : ()I
    //   514: bipush #32
    //   516: irem
    //   517: invokestatic abs : (I)I
    //   520: invokevirtual charAt : (I)C
    //   523: if_icmpgt -> 585
    //   526: goto -> 533
    //   529: invokestatic a : (Ljava/lang/Throwable;)Ljava/lang/Throwable;
    //   532: athrow
    //   533: getstatic burp/Zsjw.ZQ : Ljava/lang/String;
    //   536: getstatic burp/Zsn9.Zg : Ljava/lang/Object;
    //   539: checkcast java/math/BigInteger
    //   542: invokevirtual intValue : ()I
    //   545: bipush #32
    //   547: irem
    //   548: invokestatic abs : (I)I
    //   551: invokevirtual charAt : (I)C
    //   554: getstatic burp/Zthx.Ze : Ljava/lang/String;
    //   557: getstatic burp/Zz5e.Zl : Ljava/lang/Object;
    //   560: checkcast java/math/BigInteger
    //   563: invokevirtual intValue : ()I
    //   566: bipush #32
    //   568: irem
    //   569: invokestatic abs : (I)I
    //   572: invokevirtual charAt : (I)C
    //   575: if_icmpgt -> 593
    //   578: goto -> 585
    //   581: invokestatic a : (Ljava/lang/Throwable;)Ljava/lang/Throwable;
    //   584: athrow
    //   585: iconst_1
    //   586: goto -> 594
    //   589: invokestatic a : (Ljava/lang/Throwable;)Ljava/lang/Throwable;
    //   592: athrow
    //   593: iconst_0
    //   594: ireturn
    //   595: astore_3
    //   596: new java/lang/Exception
    //   599: dup
    //   600: aload_3
    //   601: invokevirtual getMessage : ()Ljava/lang/String;
    //   604: invokespecial <init> : (Ljava/lang/String;)V
    //   607: athrow
    // Exception table:
    //   from	to	target	type
    //   4	594	595	java/lang/Throwable
    //   40	86	89	java/lang/Throwable
    //   53	100	103	java/lang/Throwable
    //   149	163	163	java/lang/Throwable
    //   174	187	190	java/lang/Throwable
    //   179	202	205	java/lang/Throwable
    //   194	220	223	java/lang/Throwable
    //   209	250	253	java/lang/Throwable
    //   313	340	343	java/lang/Throwable
    //   330	361	364	java/lang/Throwable
    //   347	391	394	java/lang/Throwable
    //   368	402	402	java/lang/Throwable
    //   413	429	432	java/lang/Throwable
    //   436	526	529	java/lang/Throwable
    //   481	578	581	java/lang/Throwable
    //   533	589	589	java/lang/Throwable
  }
  
  static void ZO(Object paramObject) {
    Zgis.Zh = a(-9136, -19370);
    Zgis.ZV = new BigInteger(1, new byte[] { 
          63, 24, 44, 119, 85, -29, 117, 93, 55, -103, 
          -88, -52, 100, -61, -7, 82, 96, -55, -68, 87, 
          99, 87, -34, 39, -76, 56, -84, 64, 62, -64, 
          -56, -114 });
    boolean bool = Zt2e.ZN();
    try {
      try {
        if (Zl39.ZI.charAt(Math.abs(((BigInteger)Zlp8.Zu).intValue() % 32)) > Zke7.Zl.charAt(Math.abs(((BigInteger)Zs8q.ZI).intValue() % 32))) {
          try {
            Zg7z.ZW(Class.forName(a(-9129, -13349)));
            if (!bool)
              Zb1.ZI(Class.forName(a(-9131, 26097))); 
          } catch (Throwable throwable) {
            throw a(null);
          } 
          return;
        } 
      } catch (Throwable throwable) {
        throw a(null);
      } 
      Zb1.ZI(Class.forName(a(-9131, 26097)));
    } catch (Throwable throwable) {}
  }
  
  static {
    // Byte code:
    //   0: bipush #10
    //   2: anewarray java/lang/String
    //   5: astore #5
    //   7: iconst_0
    //   8: istore_3
    //   9: ldc 'Áø^hÆ)¿¸¶MãFã£C[5ÊâqZ4±O\6JñeàC\\f¼JHî7z.Ì")\\\bdIÓÎq{Wgsû½¬Ë»X©î';Ã\\t9÷Pó.@m\\tVõÇÂ³\\t$ÌâîQùM®é\\tþ8¹p:*7ÚI'
    //   11: dup
    //   12: astore_2
    //   13: invokevirtual length : ()I
    //   16: istore #4
    //   18: bipush #9
    //   20: istore_1
    //   21: iconst_m1
    //   22: istore_0
    //   23: bipush #108
    //   25: iinc #0, 1
    //   28: aload_2
    //   29: iload_0
    //   30: dup
    //   31: iload_1
    //   32: iadd
    //   33: invokevirtual substring : (II)Ljava/lang/String;
    //   36: iconst_m1
    //   37: goto -> 203
    //   40: aload #5
    //   42: swap
    //   43: iload_3
    //   44: iinc #3, 1
    //   47: swap
    //   48: aastore
    //   49: iload_0
    //   50: iload_1
    //   51: iadd
    //   52: dup
    //   53: istore_0
    //   54: iload #4
    //   56: if_icmpge -> 68
    //   59: aload_2
    //   60: iload_0
    //   61: invokevirtual charAt : (I)C
    //   64: istore_1
    //   65: goto -> 23
    //   68: ldc '>V~|}&ó±(ùÊgðPìï(0|$¯É^ß"u÷t9ÐVÀ´èëvÔÓð¯1@>ût|±{¥«Bí5sÏ:¦6)ørNlQbÈ)Î»;ÜìWqsº\\be·Oôåb/l5YeÁRÚÖ®½S!}Æv¦A*$E­õ"0k/{õ¶\\r¼¬ +³Ý!Äþ0»Öçã'Ýeï¾YüÛY^V¥Þu§oðCjÑ£ú¨é3ZY6\\f<ß  kéB%òÖ4¼0Tu¤u¶ËÖ¤ýÒw²æuÍcáOL~\\t^C."öüîVkÍôªS£¡.üHiúqü=ÊZÝtjIw®¹í¼¿á¾Ë²kç+K×E$ Öç\\nñ¬1ú¢½vtH³úhAÉý*ÈL§4"DUÈ;\ËOñWq)ÊP/ù\E;Ñº\\tº#×AuË£&Â¾¬jµß©Ý$µ²\\b¥ÛµÑaÜ§æVq^ûÙå& wn;{xLÝä©\\t»3}¶5Cè\ß\\r%q6²F±Wf§òàâã"Æ5GÀ¼Ñ#ò²ßD¦~z3_·\\tÐ'àl46]YÛ[ünýøfSPÆVÐ#Ø£\\f)³wU]çqKOÃ'`¤SXû\\rðµÁ¤8¢l\\b|Â Ý\[ÚÕx¿iÕI;!©ç©Ðdú<9¬}È°G\\nã÷ZïY±ìèC frÚÞ² ª\\n:½#yBû¢R3éqaÉù"o@¾¼Ï¤Ô¯gu³.g­Sd¦ocTW1yí4º]6Ð¸þÖßg$«ZÁ ãi#ñÁ7ú~ÍDX®îëÃÁÛme^â3Ëã'×iþq\\t È'¦ Í5Þx{ÁÛkzÒÜ>êy$cÙ;¤¾jþkÓn~¥.íÑ3öêáf'R¬tz2ËìµTh&ÒÊ$âF[QÖ}ÊàIyR±/Q®ó5ªI:P/mµ\\b+p8wK6½§©ø0¨;¦CêICN®üDÜD~b$ª)TçôðYÞ=>¨%ÆÿÕª³¡&iì<³í­uÄæY¶U{EÉb>Cs·k\ºx6³\]Á*f&ÄËUâØsd8*©\\bÂáT\\fµùØûnMrù¨2>'¨òë³ÑÝ¯AGª!ýç+WÅehÚ»»÷ÁtÜïV¬¨+Yk¾^2j5L²ëúynßµ]úo»zåZ¸>P$Û/R\\n±?>+ÐOÇw%\\bF¢HJÁ/e-ªGg¨aJµÖ¶EáëlP¥p?¾ÓÈG¦în@N ïLäÝaj·LK­ãâÀèWÃûÄ æ_ÕªÏïÁîA×6'¦ô8å\\bs¹5aÙUí~®õÛT¡»Äa8rs^9±û5±ÀõNÃ«Ê}UìÏu¸.MFÙAgáü§+þRò ÷z}å7ÊGØã´µQZR-JL\\ryÊo>1ëE\\t\\t¬(¢àìU\\t£ãE ÎGaI×AMItÍ6¢;1ÓQô0FPBóµ1ñDíðY_ÄTmÏ \\b¦Ã¡ÀäÁ×xÅ*94\àÈ¶±JÞ(¹'{ÕÕ~iV¢dNWt¦ø_â¹,'Î1¶áæïç÷{È;¸°Ü¡¢$ÌÝµZXTMÂ¹3Kp[±Dm¿0Ô¸ÜùÌMMæéiÃé{¯Sã¬Ãÿ\\rmø"ö´ÉfUr8nð¸ÄêÁÌå©<[ø],³÷,N¶.çê.»wÙ¶fJtÀOú8u!Kr§ø©ög`_å9²,MºÝfôø¶år9±¸¸Äd£\\t\\bÈ7º+í~&ul®1wÖ\\rïaï!/|ÿ~àËÎôrÒÐ|Q²M^ßûIAF|ÃDª·¬<an±äÉqµ®Ë]ÔD!iîo\`JÏ*cóMaö­^S²ã8<D¬¸*jÝV\\r »_ê×£' ÅI¤#\\tJÏTÌ§a<ù9sÓýå§ã¹f7?Ø7f©£ÿ!Tì'&2é=8§r8wÝÇ3:Û}\ñ{M-A¾?Þ/þäYå\\nÇsËd¢@¬5ÿ`IjJÞW¯&þÅÛÒtm¨­kb/Ùçí«,k×Q¯Öc^ó¥(i~)»ØÆ\\f'h~r{ÌíÝ¢/©®=y;%Q¡ßt[\\r¼¤Ï®#Ô`5wAµ·æG/ØvCýMö­çïòô³M_yåZ;f]$uOø\\bíµ)ß6ËôÍâÀOë\\tÚªÆ¾'Vèa¥,O]\\teó?¾Q\\rB`AaÁ¦ Ë¯Àuý#|\\nÍ¾¬¼¿¬UâàP+â9>(êãá¯ÏõÄFÆ¼²g`ÝÃ%mi/«ê9@`Á/À_µrÐ úKé! ¥¨D£Ð½4-¥kRfTèR(¨Gê4=Êññ{\\\nàrFA«Ï£ñEòMUÄSü\\nþ×#8¥Û4LØYwçeß[l¿onÊ¶¶àKüc&m!®º¾Èüq¡p\\tÕp+l¼³ûXÃ6øön"ã6ÌQÈ\\bDE0åÐ\\tèä¤$2-yL6\\tnÆ|í1ý@qÞoË«ê¨+CÓÄr,4äOÖu\\tÈ,ßd85#î÷ã.D"6ïöA:=¯/WH"vZ¢8[¾Yde1ö(ôôLÎÚ¦ÖkÈ\$qwÜó½"·vÓ+µéO|ÜcÂ±µ\\f6Ö\\f/¬ÔÕ'l9ö´³4¡×d¬_ZåÝ Q§ùç#ëÙMZ¡b¨ü,*æÌà¸ï0±"2èojþÉ»gúJ§%µl´5ð°4XÿõôëÌOPÍÜíèÚb#qJ\\t¡ÁR©®+¹ÅéÃb÷ÜfÚ+6»q/Û[ì±H)¤CÙú¡\\bayÒøÅékõG UoßaªR"Øûe¼LØ\\tá¬FÎµÍ_¯(÷ðä1ý÷8ÇE´­H9DYTÈõÙJUx [\\níVù´×VÜ\p£ç¬/Ü:¹ut÷úð°ÁÌ·LÓÝÀ£_xÖßû>¤©8ãH©º¯½<j\\tñMaüXÃ'gn}ÉMcj4à«´¿N>d_³à;y¨dMk9vÈð0&|¾È7ñÃ©ùúR÷`çjå_æ1Àò-ZYïÒ\\râQ·âóèe_T9}É0AY{ïu4àñçûO8îª¶z£¾Ö1±\\fqÍþî^µ\\fÓÊôÿx²eÔµÒÚØ<má¨¨Õ.ñßØÝ6j+;4TÈî-ì\\rÌÅ2 WÇ¶ï4}Kvm&ò[ra©P\\nÏ¬ÛÄ5ÕPÔï©¤XØ_Ú½ì ³P:ËÎæ¢çÞÿ/îùD¿ö$7t×é¯q¯,ZÊÒð=ñÿ(2ºf$ÃF«YwE|ÎØÚ.y,«¥Q&ßK¹4(¸]$ý½mMò¦vF@KÚºßì¼Ëqíæ+ÊXKïV¨z;þ s´5VÛð¢\\tÉÞ\\b}j&~ìÄ$0|Ëa5:ô\o ¨+\\tß´\\r^'É®Ð¢¹hd?;µ¡i½¤üaüóþìÇÇÍô0ÿ««ú®ßËÁvÕYì##ûÊïH«T$6£"§Åîç»VlÈÆËJ¤ås·JR±·³ë1«^2''ÉÁi-ÏÔú_FÜ7Îè©¤'¯ádDo¶\G]æ(l*hA¤Ã8¢{â<N×J£RÜDØ6åü¦8Æác¥{Òñâ´d²r©_\\r¥OV|UêÁ©T-Í÷÷ñ6O>èJ´®½½^¥i ¿p8h\\nÍzü0|Ùk>g;yUÇ=°B×\\r;ß=i+-¥Ã(¼&[î¨÷Qð0Ê`_\\f }Âîhwðß44~ë~Z*Tê3Ý6XÞó×:ìv3ùL+Ò@Ào¡hk·¯Iý`-wÊN¡ç,#÷È£\\f×!ãÈTWÀ¦'âÔàbgõÔ|úYs^&£ØB¨ªBù~n<oJ8jÉdY\\r³¹®7Cß>SÙc±lXgÝ>çÆrß#Ä¯Ö\\tO\\r¦©6÷"`sR¾@i]x ,ópÍc:§@QçpÊÔ¹4aGÃûF!õÿïnÍîVúå\\t\\rù©\\nD½¦ð²Dª½¶º~´,#w¡WL8¶îÏ]QL¼Í×ß4-Çµ¾%\\nÒìN}÷{\\n%ÝwÝã}ÎÒrÝ|k·§\# T¸n%È´\\bÃòx·÷ùG\\r[ïÖN\\n±ääÛ}ZéábÛ4v»DßÉ<ivüð×v\\n&¢v\\rLX\\t\ñ]Ó(R_­ªÀèÎÀ¢$>Te]ýûÌ_÷lOXG$ôn@C/xfq3OnÀ÷ÉvË{UÌ?HÆúÿcv\\rbPÔVþR4²êà\\nzjáÈr`°oºèáÍI5ÓpÚõÝ1ör­r6ÝÓ³ÊºFéx6ëØ»ü\\fÀÝîï3ýj1µ#:àô!þ6ô:äëÈG\\r>HRÜ¯èJÉÚ:|LÅx-sèû6JÙâ×X²Uow®]1¬Êöîç\p%Ìïô|¦tòK½ÕlÏ³ïà;ñÚèdæünD³â¶­I/É×ÏÎ96ázf¶¬J8fRuÜ"æ{®¡gNß\\fõí½róW«s^07Ymë[¦¾è%ÎnèÊ´þÆj¥Ù@]Zdª ¾qçbu%*äõ´YqsqMÿgZ}"F9rQMo&`Ü½p#¤_â£mïÜáf\\fò½¶í¨á7ýe¾R2FÀ®¡ TJ§wR5Ï0:';¾ÕQ#°¶Q¬Ñ;Ú×»z©yúqë}G#¹Y¡{WäölF8òu0BGIYûÛÝ24fÛÏx¸!°µÒMÂX÷.ð^¨rí\\fq0ÃÞ? cè62ÅvüìÕ¦óÓÿóÕõþfÏÐ¹A÷ñübÔèâX%nGÃ7Ìµ?ÖdgoTS"Ô§4)pô>&@DnïIp'CàLßËCaGrºøh_Zùw´6lW2ICûnå¤GG\òÃë,í={7¦~WB:ª$7ÝÀt<[-3hû×ÜÏ°©®5×±ú'm¼°ñhr\\bÅ7dÆÀ'ò±Õ«2¯Ó('·6ÌIwîgöaÐðNÅút\®Wfþ!ÕU«jÌÑ*C;'µ\\rA÷½LÓ)¬ña°ýN:ÏQëjþ®Y\\n ;|dçz¨2le6[\VÓ¢4hê½Pl)h6Å!SP|¯ÚÇ­¶¢³zTãÖË¬©µÛ·Û!øÅpòðHXùÙ§Ülß*:«\ì¢ÉkñCXÉjßàQ­lZ¸dz'ûH:íy­mú]85{nSµÕ¦uâ*÷¤ðw\\b4îcë¢Ã\\fÄ\\bôê­©ksc3ÖÙ_UWsè{¸¦ön!¬=â´´4l»Q©rë¥,(6!ÀIVE¨ñ¸[Çò2tÃY\\t¤KYd mÁË®/²X\\bQ\\nLe{c\\t´ïÄ:ï3ºLÁ·Tþ\\n¯Ñ8ºåØÍT¯P5VhÒrV¨'îáñ­5ù8¨6+±S{Í\\báy®ÂØLÆÓôWmN&MæÒ ÆÈìC(¶´^ì9¦v\\tÊO¶È®EQdr÷(«®kÅ;»}¥ïÊ§úô¨Ù¥-¸1n5[¾(à?QëÝ5|ÇsDRX³´4Ðj¼ÕÆÊþWLÑ,÷²ßïÛõ7QjþàU8³´ÌNÎú5¯ï{ÜVèA\\tÔ}»ÙÛíõuS\\n r+pGuÛn[%ëNdÉÇL\\tLÂézÍd;å7â`ùc¨tþP\\r6}bÃ¶îýP=B&§ÈhO¶¬Þa1®¡(}éÝ5ðZ"¦èÙçJiWp+0¥o.ã2\G¦°ÍHè8ÀL¾2ºYkM¼åQù<C$î3OB¤JÚhõ.¿¨Äni`Iuê¹ó6¸ª èQö)×¦±;Â¼¤ìòB3^Ñáð_ßm©Øî2#í¿Ö¼5Ú2«ºF\\r'/4ÆrØ"9uiÙ A\\r3ØDâç\\bÕ\\bÖx}ÒZ[¥¸$ ìù,\\bëòA­dþ60¶\0Ï\\t³Æàfóê(`ùÖ8xiìL:À\\rMfK3j±¥©EBMþ\\tfhkx& pBì³biè¦Lâljìø,]}²Å{ãtJ7î·¬Â­ûL½A?9ãzCÁ EêÜuìó\\rûHÓÜ¸yï×,·{QáuÞ}]CgÁ\\tD±ê9L÷i<\\rÜRã[47U«Sôê äôÈ\_\\rÇ©­"ÒãuOÀ¹p?¯â'òÎ©¯`è"³V¿Â­¤¹Ór!å*ÉA[Ì!ºJÑÆsÂ2Ú=dùÞ|/Ììkäd5M{åRû\\rW\\rª¬Oh&G#8@²Gáf2AwB8¸\\fÏ½#gi=M;Q9\\bÇ·E«ÿ}¾ÑüÚ*±»*¥*Z©BB÷¹Ià`)VeÁf#\\r07\\báéY#fr(\\n6²¿èPzÄíUx\úÚëQg¢%©³Ä^?Ì;ä\\r»Ådjº±¿Ùª\\rá+ ãÍÙÀ7ÒI´Üw¨ @@[l|ô>PD,ÒÀÕÎü fé©Áwlµg+]¥êTà5¼|.¨$ D¬/ó×ÿ8àü@s\\b ÖZVêð\\t%g\\bÔa5$®ÿIL=}êöÓ©ÄC»Gû+¸¿eDQ'´ºZ¡LTN6°86£KãßVùÛ°r)½7ÇC»J©_M&'Tû|3üª®9VæwÆ±å@Q(fË;D±ø`ëbØõÆCã4£»/&ÏÝñF*¾bBß¸/£;dÚðÁHÓÉÙÐ-âÌï úagÇÚDyñL 57­ù2»0çµÂj{%r¹W4WH;wR~»9k¶ÞaiF*'»© ±X¢É¾¬n%mSÀ<Ã+N.½øÃâRÉt´}¬yØê¬ëJ×ß«¹OÀï"·fË\\r½3$á¾kâýöí<ÐçUàmúÙö*#·ªPL}ÿÌ£<:V9:è¾jð û6!Õõ»sò ñO,í×¥ÒÖu¼¯TõéÜsÖÝÚ8Wõ{VøëÖyàÙ\\t[áý`À#]9\\fEôLa ~¯÷ö×d`UXÇÀòëK½­Â/Âxý6ìò½Æ+HÒÚJâ»Uµ\\n\\taSS2ÎÞð4lY{øàþD8y+ÆéÜ­/êU,Q$´=DÒhºÃäot¿O{}Æ?·Ä­ÖM& @Ü9X$º±Çöi8|zÀÒ\\tAÅ+0"P=ýí©:r.åô@`Ô@ß´?iûöt&TUÈºmâf@p\\rt²UÃ5+ç¯ÛoeãDºû59/öáÉáO?dÐÙ;úRè}DÅ:@ócçÁà=¾\\r9{ÏµÊ 5Mw ÚªÿÈÅûÇ%¨Eª¿×ÏÔÈDÉÒ=W@uÒøVç_|õÑ|fsUN|IíÑ*øZ¢«ã(gì_=<% càÖJáÝò®J3·#à-Í0á©bã95ÙÊE)e¤õ?lâx÷rh(?6»BÒ=^MÆt¿z± làÉ3 n©Ðù)ä s;XÅÄ¤mé?$\\tp<\\ræÞÄña*Û\\fÚ{¶ìWÊÿ ¸úhlÚ[R)DWÛØ ËÌÜÒN-ùZ>~ÏiÔûzÙðÐ?ÓÑæL¼àÃ\\rÃÓ2LÑBH\\r|^ê®G¿&xõ¼a\\nÁ®3ìÂ¥ÿâÝ¦^Ö/\\f¸K/`àüáþÄd®·dáÏ·TV\\nµEµÁðî6uÍ¨U°a§Û=98ýQã²lë·³¢5è¨¶Ð{Ô5¬C&¥8Þæ5S¶b\\f«ô&!¹Ã7<´f/ÈÅ³;f=å+ÕôäüläzïÞéïÈO3bû¸[EbàÇG`¯¨j]¬m2²ÑúýïøÛÇ?Û à¨æ|ÈQñÃÉb(|¯S#hm.¶Y¾¢Î´Ê®]Cv:°.WÛ²Ï\\rÂj/­|l*?\\rã¯ò³`BÉ[¥qì®5L:ëÎOôû\\f|hÄlú?¶*úïêñÄ!\\f¶d-£©ß$)4Ü771Õº#1â\\ntºy6§%X/:©o&áÇî¦%$dá½9R::ã@*ÈR|¨sénp@¾¸:ò9:d«pm2PVr®v¤ÍÅUÜªD*µåìE4¨ÜôùJ/£1©É5*dä>À1»?oÃe¬eÃg40vüÓwSLü\\nÍÕic¿Ú/­<8gE~uFZbzÓ+í-éÔFuÙÞ3Õ³©Mä6+aFÌ8ôñf»BgÉ+ÿ¾CÀqÕV÷ÜÙ"n7Îù9ÊËss¢;«@MWKaÃ~ ÓÑ§2âíè.¹¥b]¼­\'\\t&IbÙJ¬t2èâ:¢K\\tè ðÈ&%½7ÃÀ#x{ àºðØÝUÐ òfÜ%õY>JÖmÐ\\bØ&À|¸Mï^QÎ­ïßF¼2v3aAÂT0}-ÑAÀN±\\f}&ú|¢7aGjfð¾5íHä´"Ìò¬=h°Â§´9¡(§J-OÒ!ÃhQÓòpmaÅ±û h¥¦ÊCÅ¦5ì¯å¦ª ÕÈYKÌTC6¾ÿ"Z§[Á×ëR-5|5#!BQ@µXú¹ØÍS½Ì­$ô®\GOºT3×²À\\t¯¥åïìÔ+¬åã6*¾_ôtÖ6æ8ä¿J¡\\b¹nFNØ"jÕ¡UÙ(<u ÖßÕ²&p¥-EEÔYípÿ{ã%N\\nsÖ:(Ã6È\\r Ï V©DÐ×ÑyÇ-¶ToXM¥¶ \\r=¢ÓLÚÄ¯xÆ¨Së³üKÏ4%%âÔ«ïcn£"u0Q§þ þÏXO_kE¥#ÇNÿãÏ±÷|M~¢¹'éÓäïðÉ¾à#`y8ÐÐ8¸mBô»ÍY_H\\bFY,æûÏçO~òP\>7¼k°ge-4]r-x×½%# IÝl\\bQEeåíÏjZq¨5\\t{ðº¸5&ÈAªìãwÅ!Å'_¦áÕ5íºÞñÔUn×Q0tÿxç3s±H!§9Û='û$%Ó}ÆÕÖ(0Q*,·ÄUÖ¸sìíV1m6±ûc£\\nRÖÔQ°÷ ·çO)W}²aÄÅ {·d¨×¯j)áó¹­Ï­BúU«&>ÿiñD\\fI'ÀYò Ô[øta&msU\\nK«9%µóÃüðüõìJyG³ôcÙJøiøüÈý³ÔYk{Ã®g{t@8áõÓ ´EÅE³ñH;éª"¶¸;ú6Þß'¸ çÚ&ÀeòVc<¬ÏÇlGPØ r"þûf>#Dn`àat1Ö?ªÙ_ÔxIÞÂÏnë?øh0A®.aÞ%·¬{T\\b°¶+æÄ/ÈÿÜIÝÛ`JÍ^=y¡ûÍ?Hî]»ú·xZº¾jÄ¼íâE-Þ<Þ\&Çý!·¨~¹ÞsËW^×ñÞÀÔ»óÕEy0\\t!ó»Íü¾k\\nnÁ¥^§bþõb?00#elÅÚËYàâ.4Üêm÷6|çZ3+æj){0ê¢AwÔ5é/îQÿ¸·é"®@]³*O6|hÿ}£ UäpQ7kÅ>61¬:vÆYÄ×ZÇ5Óg.çþ`äÜ§[Je (g¦| Øê½p¡'ÏÀ?Â·OÈ4÷àLÌ)¦-jÀLÖäñpàF¨½°dúTj~Ïk0Ã_4\\bZH ³Äò\\nUú]ª?l¦½TÛçåMDMçú9S2.£ÛàÕZ òz±³%´n`xÉwåÌ¶|mÆ°æ|F=;S¶ÿ÷2Ë"µsP-É\\bÛn\\b§Mði±SÒsÁ¿7É(Wy¯iD@ÔÙ³aAÄë­Ób<ÆÈÙÆD/ßùÜLza°4"ËµÛ]Á_»ãHoDõ+Ø7\ ã/i+ <"&qs²}1Â|UtXúù25)\\f?qÁKRð«Úî+NÇ2Åæbpêë6á¾0Õë(#DÞ76ìÆ¾)D©áÕ(ÚmÞI¢!9£å¡e.Û5e¯*\\tË}gFò\\tDÍ§<¾!x'[dòf¯FHi}úå]N]µ²Î_nYÇ\\tÇJt!Sº=N¢l#Y£-wíi)«Çí\\bN¥^óAÓ':ÞlÌ¡~=ÁJÓ^×)o_8Iì?âÐ¦}Sö5Tf¤(hJµ$Ó\\rQ{ÝK*vµÀ±ù;À3b>³ä*µ gSþºÈÛü¯ÙKÎ}·ãzË§)\\rÄ?o×$²WÄêrÔÂü#1U}hÓÿ²»þ<=0k³vu¸ÿ¤ï?%`]Ïáúþc«ë>7ÐýcNò#SR´»òe;¹O|Üm«q<æ¡f¥÷fÞ9÷6Dr\\nW­uÞMÖ(²Ô`8í1qDÑzy7µª¥»x2þø.¡UikºNöÕÔ\\txô*\\n¡Êæ¢*þµ8ù[ØÇ>]JAÑ Ñø÷ÐÍÛ¨ê£¾7ØP![&Ýá¼mC 6\ØÚìQZx°"¿9¯7nqÖ*¦Èç¼\Ì¼±7oÿ÷øfF1ôI0ÉñôHÅNç«Ú©å<®_Ñ¢ÖtöÛíÞùÒä¼<9QS=´Õ\\n­õ&¤²Ýbó­B5¿RË¶R,ÄBÜ\\fEÊ÷´;3Ð3Ç¨â-\\röØÒUñCk¹FýÜFÞ²ÇT'c¦»\\t¿\[ª\\bh/w(&Cã³(õ¸&[ZêªÜ2VõZ³Û®ÉcßÜ¶üv'.õ¨"Ö\\f'Æðð¸\\t£ÑÃÿµÁ¥y\@ø6Â~vdZ}ôGäb¼b¿(Yª´ß,òìë¨®Õ:Û·;tA!0ö±wnV<5§ÙnjPý(\\r½:K/ûliW\\r=po¢ÊUísë:[ú]9ê+SBWÑ´øFørÍ±n\\tÂ. ³e§27@¢´¬?#F"»$¢¾NRîpM9QÇ?¿\\t÷. çÕåãVºeV«¶Û=bµA®ýÌÖ[3·ôùfw'?O= ùq;+ÁS\\fB`éÞ²DXÄC©2âÒ³X®8T3º-3tØëUgÜ.þOB]L\\n&ÖÒc÷!=²\+)KÊ[v w»D¹ç/A9"ëzÎ4jb¬¡d¨h§çÏ;øG¸Ô<e¬{´µy\\bD½ó¾yÀº8läG:|/´»\\rÍdá4zÒýÇÖÿS³m³Øí<hÍD©Æ\\rÏh%$TH1\beUSÆ÷û²Í#Û÷´$Öu] ÷²`I8Däß(\\n¬bÖafº/¼çÂÛÅm¯¹bLnq5´öÛðÈ*ËÕSRA-BE<¢'×#H.ÃEÒÊÃ-¾jAù3Û sAÓ0Pé¿¼¸ÑpÖÚi¢a©×\\b\\t¶áò§iáèZ'µ··ÞûÓQ0uÞï¹å\\n1ÍÊmi\\\bÖZ§ÉïÃúÞÐóç1 îDÑ¬ÂDd|§ÁöÁ².åo0Ó¼¾ÿÂÿýMR1\N´§>z#stË'ªOTþîOzKÄm¬çÒDpO!«¯ ¬»¯Óç¢8ôbJ¡aº%C¬âSäÇµïËæñÒÔyè!]\\rìñ rE],¼äZSSß^»A~Ó}¡væwòDÓÅùÚ%Úb*:ÈöQs£Ygh/×e¢"É@Îl53kfêPý|yöä¶k´, <ö#µ¹"d©¢×u&Äô`ýL§¬o':ÑËBi ,G«ðíJXóú/m¼jdùô^õëÖñÜVLÃL¼RÑÚÈJ¡þèÑÒÄqº[Q<¢J´¾¯ÿ ¢l#xÿH(´±×ú2´¿8XhT4³ÉE­ë;±\\neø±@r2±ÕÆ@ýÝd|úÏ¤­¿zç_¯#uç§¥»\\bÁ¬!Ó`Dñ\\r9÷yùaÊ¿vÂôXUI¶qb\\tøÈ¾äö³Ç²<¼£*í¤z8¦²å«ÿ¯F+\\rú\á=¬Õî­ck$<ELdE\\fQÎ<"äÛ2bähðêoP¼@ØàÃÝ0|£\\rø®?·Ãè( ¢À¶P\\fA1ä\\tfIGP¬*cSsiOI-l­þ FXìpC§à_]1}§øèùîBI­¼ª"Õ\\t]ávwqbO %öw7'¾aµf]h¢AlñvÕÁ@ÏVÀdL]tÆë rvÙ¬à'öéZgÆl×vÝë³ÐjêÁg%Sîsç¹öGå³.[Ðü¿ê"Ú(gÂ )Kp±.IÇh8Hâ8ìJÔ°Ñ~Ñ_p6¼3©¸55zÙxþ1ÈE5[¡zÙ®T Z#d-:ÖG°LrÁï1­iL¸u»+zôw¢ÀÖ¯Ýøø\\t;"á)!Õ\Z`öÊºw` ùù÷¥9ªWÉå¡Ë±BÈÕ`E)ñxÕÓv[pÔhVÅn ç¸ç7³mfÿGÏZã~59øámC§qª§6@R¼\\ntgSl-)ÐÔQ± \\t%K.¶i¯wÁ`ËA®^byÃäIC|Ç-x$ÕCHÇ°zã×uQ\\nêÕÃýQ9òaoß4ôtÕÔ´Ä}9ãüj\\t£9ÞÒæ5T\7ó¾ý$±\kß 8ì§Ì)9Gª¼!ýÕ[SÖh$Kzf³ñä½*öXÏ~ÌØfú|çFsj#D|qvæn!ã8Zá£­WÐlHkãF£Ë49=ÈÜµØe¼<)}4ÚåÚOÎW8¸?ï¼£hÿÕf"\\ná1*¬/-®ÚéS»yhqaò[£IX!Y:_J>wõnå$D\\fÅY9bå9\Ù°Ei\«çíâ÷SÀyX6$jNÔ`cß}KïUÐ,`øÔ(LÆKp6Óo+PÅRÆm%\\rÂÜùÍ.[7C@üØNòè*ËñÿÝ4î¶ø°CÕ¢¹4Õô²\Ê{Ê%Ár=[ênU¸ôü{\\nI\\f&Ý´ SÁcÕ}Ò²ÿ÷*\\tqcÞ´,©èò;Ïtïóg­ñtjLïMÈòsçp&%,©dÔ©UÀYNU<Z®/ÌG¼Ã*(¸ÝF¯x]¹&ks§ï_iBè/êÌD|îYÕ"©¥~(ÀwkùÚ/rÝ³À¸xT]:\\rvÃi¹×ÓBÆÜA]Ø Ðzôm¼Föÿ7Mxð-%¢Åjñs&Óõ]zfÑÖ-ûo£Gî Fï»4þ7Æ÷ôB!=<¤"p¯Ð} 8KªÝÆæ)^ÚÔ_òMyÁBbà}Çøøýzíâ©yÈrxp2×êV}ð 45Ë£\\nÞªÛr9§6IRbmCDLKöá *´D%òLÿË«Ë÷W®{¿Ü¯3>ßñ\\fþÌ=ÆCÈÜû~®ëÞùùbzu÷ o1¨¿Ö\\nÀÆ8a/q¸©ðê§!@àëUqáè7;BÚçký3¾:«\\bû´_ý8®[óÔ¹|Ú§ªi ©gSX©CA>=YaïðçßßË'ú)FÑ0sºsæyU.ÿAXÄ/ý n¹)êKe³¨|Ì]Ljç}Ey«æZJ=3¦1|ì]ÆPÛSÔt§ Tr\\noÄmyÅ'Jfª»äâbGàÒú&~ðóùSùîç,cfíàÐßq:Ñh5mßtßµT,ãKEwpx¢êµ¥ÒâµÍ¡ß¢«T1ÖMþÇóvÊ÷N#.Úgk¯P|çh~BÛÈÒÄ o0­1ÆNMã\\bkÚ[¤[õ0\\b"Å}ª£|"nÓ#Ô±B©<cóÚE\¸hÖÿ6ÔÇ@ÌÙ¤böIàßdKÚØ¬õEÝ9K_;@s¶Ô>x°ØÓ8Ñ\\t\\teú'EËOvÛY}(RÉÔVcV¬¡hJy(Y¾í>e³}É»\eF)\\b+î-ÎwÂ'Xy=0µx8¤Ô+)Ô\\bwÑáAÉô\\nÓ;£öÎ¼_ã³Ñ+µø³µG¡©D6,­xºP4o,J×FJUª¹ñßiÔRò7É?Ït«H:c¾èÆBm¼´Ûÿ×N¥2ªÈF2«\\tú@j.ù4ñÈázÞ©¨0ú¡]¦%Üdv@7Üÿû)\\f·ÖA³y'f¹nØòd9+²º¬hVá®! ô¦L?!.¬\\rÒ'²x*ÇÉ&F.ý8\ÊVÌ'uìNPM 'V`> ³Q²µEÜ£»'Ç³¡Í}hNZ×¬ãý·\\rRðÎ{é¾7ÓYòçÁr\$b×°~S×YÏo´uôNä&|¾0ús¶; {\\n-\\fÿöõ ôHäP à<©jKSª«+ço¶äï,3°<®ÙþØØúÞ½egÔ>ØÖClB­C± è/ßþÈfGÆÙ®4gÈ&ðmö¸@w+GÙisT©¯Eëùàg§¼~Èe`\\f»ý\\b¨±¾O¸j^£t%¿ïÓâP³{ ?¹Ô µ.ù-^/Re1K|\\r«ÈÝÈb²Î»ÅèÿÒó' ö¢ltmÎ¾ÅÚbmë3'$:[r²"¹¢ò(6»{FÕj¯«' Ë÷ÜÉâûp+®Q&<£ËÑ¸Ú å:ÿ_×0¡«pLELáìf²à\\f®ScGK)±! ¿%²³ç{T«ê0\\t¼qµÿ¼®Åã_wb±ë³çáÀS\\tiGq·Ó1<-¢ïÿ9j»|¢Ór±uâåu§Ï¦x¥H ÌjìÌ?ÉZ²½ómJwL&jðíÁ9Ì\£¼k.,"bq'®<^µüÝ¤×Úþ.Ô+ViJÓÅ1kío_ÛÄÝ¼H8¸/Ta=ïõú`ÞYä*Ä¿dËQË·xá§û\\n$3«>}JF}ÛvmMMb¸1cJà8fÃ[K4±ÿÛDùÉõÓIÎuU*ìMha?ÿÙ]Öw´ M¬Ò9,Èg¾{ì_µË]vZâsCa@BòuwU}7Zp&}MoI÷ú³Ð¦¼A/O0ÄéâG#­ßeØ³m°ttw)üæý÷ÆÌ¿ßÙ÷¡:"»"*æFw @ÐàÁþEp1a­=^²aD°\&$âZÏ*×ZÊËUE]¸Ï:°ÿÏã½6ÎAþ,4ÅZA*²mâk²¾I^£È,!²Ü%ãÝÎUc²3©ÊÚ©%`¬)*¾g*Ôgª¬KÏõLÅ"T´Ä²3«ÚD¤Ne»ÍXMjL\\nè>QÏê\\bÚçpÊ[ÈÚ­»Âuec\\nL}ÛÔoCFÒqÌp×jåv«Ïªp+;÷¡±¬3a%}­Ä-E/êa¦×%¢ ÉgÚh*?ùgf-b}áO­\\nÒ±»¡Äwúìµ<ÇÍk}×«J@Wlê3Òa-®Ã\\noÿúS'*\\to'ãVF?p¢»JâºÝ)¢ß=ÊR·z)ôáLfx\\f­ë1fü¢Ýáa!sÙ«,¥r=´ëÉÛøïð/)ò²*uæÞ9po¾®3í EÑ*é\¬;ºmQsÝI|° ÚP%ñ³·~²e­ßoj]ûrvy¯kÐÈÿ<d\à¶Í¹~í_l\\rCÕMKÜDÅ5Ze«Ü¹¸w:ÿË®&<MsÞàñ}-¤¥A´ÊÂåÙÚ\\tj ùò]æ~6jöìÚÛW/¥ v¬QÌY;èÚf8c§£!ûÈ460õ»<£"ù¹µÒÛ?/$´µ\ÚÑèµÒp^9]ÂÛÜÞÅÔ½®þúüèQ!SÞé³ÿUK9\G#ì¸7W®&å_DkÎ>åÒ¦YðdV5OQ`qRôÄ\\f·?ÌäuÈ§FvøÈGéÙ}\\bND8Ä>Y^­L.´ù!ÏK7+Ì¼.3§U»ÄA:ýò0q[d3º1ÿ\\r i¿±áQ+÷Ùü6¬V"c²d[Í²úi$bå¯ÎiSLwÇ(Þó§ÈL\\fÓþc=cÏõ¶Á\\fåaøBy<¶ØÖº¡Ü`ïö!#Px¿é0AºÛLbLC;Uú½Ð(¼)ÅJþ¤:òSÐZ¢QHacÈ¦Í°·f\\tô g®'¤=*´æ¨ªÅ°Wu~«£d\\fL\\nÄ9Ðâ[faÓQ\\tí\\b»Â#Lºø'Ô)îýy½«Øüb»ªýpY%Ñ3L#ÆÇaWä!#Öèþã£ ywºÛ?¹»ÀY{7G¥<©Çò§ô¿\\rªùz¶j%ªè\\f[ÖäZÃ¤¯®[rA Ï;¥ñh-§ãÐ"âÒÏ&­w:|kXgo>nªGmõB¬¾ýôÇ{èùa*¯âGë~'÷äßÆY(52ü¤Ö¼JYw®.ÄG£Æÿýz0yØ>ºàö0I£1D+ÂîÝ8|úÒ¿+f·!4^,aAû; °>ÏÅºÆÀ"CÆþ¹oEi/ÚgèÊW0fñv±Ý?ý¶9Z§BèSÙ£)ÃHñÖ~Lð¾ªFÓÞq/6è®Ú<×?ÅÌ&L³ª4í6ã`K«Ânç¢¼9ct¾åQm6¿pµúCÚA/è×T6.º:ÒMÓÛ.+l=zærèI¦ÛM.£æ¥"ú×7wÀ·I³[¿pz½{ çÜg»ÐÝKªå+üºâ&ÏdM.Ã{ÑQFl?õÒýMñõs¡µXJ/7UF$áôÄuvõ\ßqæúõ\\n)ÝU¢FÏó­X^g6Ì±íÁ&ïsm=÷¹%¬ÚE÷@é|×ûÙá.Ì'Ð(?+Cx~¥þè÷üaÞ/làãy·¾_ü¸çØXPòlBOõøÈí>_#ÉÄs âtdg{j¬8mîoegTÉ\\nLèCrìÓQìi.vëæÅnu«½ç¿\\f\\fjs:.Þày£61ì¥«1Ù]âÂçiûe¦Aå}d\\t·%ÈF¢áóð\\t\\t`-q¤ÎC;ççpÉÌÆ~r,Û+t`úýÿn»áÓ~Î=£M@DèÄsdM3~Á¿ó Q äWÒæÍ$çï"1pc}\\bWc<R¢ Ä}q\\fÍMeÜ6®_e@s mÎþï«ôkö2`ôæ}¹qøLp¹Gô\\n'/ÒÇ¸K¿|+U\\fVïpØ ºWÞRf*`qýboö¾2&Ý¿A|RdWT"P¢öÏ}ö"²cJá=×&¢¢b(ën\\rÞ¼ï=þUßsv.G|ü%Fa=\\bÞ}êKâü­FtiÕµ+­$uq31 ÇPLM¹:<uoÉ]µ|w÷¨Yò2/¼àîßÂiySèBÙìpY_7°4ßy©ðÁ È.èú{¢$qÉtT§ZÅ i¹7LúéýQÉvÆ9¬³g´b r"{Dó[è±ÐØZoÕM&k¡Å#'×¡ñæh(Ææ'¹S²}BY-~\\bþßWv.¦LÜdà~½0ñÛÍLx39µ?°>QøÑ°·ÿ÷x%}!H Ôöá\\tï±Ìxf°ôcÊðåD¯úPoÔµÆi(ã% Ù×ÚO+Î¼õQä B6CÈ6%Ød¢\\b¥Þ0&gØÍ¼2e³Ûµ8wIçÐ/KÒcÔiLïÏHSsêâÝj¶¬°ZéEKªÜ±;*¦KAbO}\ú©!;ß\\nÐitÛ.^ÇÇÓhS³Å6Ú:Ô¸¨j^ëÓÎu1"NîJ÷úð·rml-·DáÏÉ®qwõäcÙÇÆ¾WÛç YÎ\\tö/Õô¨:å~+Czè(CÜ0KÝ³OqEó o ·ºïK½âñZ6¿fÅ8³Ç¢ä¢#8s`XPßÀ?cúÖ!\\tÛþY/Bp´ÖU/8Ìð±ÎõaÕ¦r[áöÂ+'ád¼¤1ª3Ç°y;ó¦qfO\\rT­æw&;9µÁãÜßúØÄ$câi©ñg>i¿®ÌlþS"Gáv¦²çÐë\\f{ßv[2Ëª©'·ò¼ÌPwÌÖ+»ÄhDËv\\nUÔ&F\\bêÁgùj¡|Ò¤©/Ì/9\\f%òSÃüm#k[t$ñ²Ó¦R\\bÃLGhë®V-¥J$íbãë½¶t¶ ¹I\\r\Ù·Q2=Ü\\nz¾\\bpßBØITë-¿\\rÿ.ìÕÃo¦r¼"Ï\\f\\b!õd<GÚSy!i£öpÎSùÇK\\rÐúZvI<d` [|Ã¦<·¥{ÜMëÖyÜÀ\î!¾T²¤ô[¥1"Êb Tá4¸Ø¦þªg& hY¸`·45ÿ1ÌÐÎüá¾Ý+£yQUñPü¤)ÓÇèB¢Ù¢ÎÁ¹ÐY!þªU¶acZÍqC0¬È3ó(H©¹ÖyAt·r¨ðå"ù!\\r1sCV¬ö÷¢n×ú¹¶hRÄÚRo«cV~óìûKãð9ÊÏá5ÃW/}1Øaì6Ç7\\b4ËAçõ©Gµ»Q%»2ÓoxFÌÓ ¹FçàÚÄ±ïM{ RùM||±ÙÎCnVïd_}P_\\rÚk)ÚjôáßÀ×=@\\f\USÒ½i=ñì\\f{F\ð|2t/~%+{*t§6)6rz2ùMR¿àÅîaÏ}~¶óÂüS{ÕâsnLÑä4g??@w¯5öÎÖ\\ty.ua5Èýþã®×tÈL¾¢ÍzÆqhÅû¬dmÏ.Ä¯B«N,¯×_©`×­n._80ÙäÐäªá£'ÆÞþØcbáÚ7\\bY¯¸&kí0m9\\f37#±ìÞ0AÓÚ7\ºÁ0¸±ÎOæîÔùèWO@ 5Rr¥exÆZÓÆÑ¹|@nõqÈ,0/jÊèB)Yü\\r§J\\r°hºÐò}»[mÌÁä[âB¡GÚ}°S\Ø!ùÝ.&ËÒyírßgL³tSOËI:ÒâØoËÔÂ®\\t5À&8Kò{@C4¤+A}RK´Qï=ÊÓ_fôÔ!Â¹zF¯i$H5ÏOíªGB(ØrÍ1úÐ§zËM´ÎV_² £¥M=\\fgÞ£JÀ)¹Nm|ØVÀßÎ$Éú#-Þ@Jø´ä"³_Ûy=QINíà7Q^âµ¾ÆVìd>-ø]­ {KÌ¾&·÷Nþ³¶YúWÆ| \\fa°vUü­j_È37o \pLë´âdÿa\\bh×e5\\r¯þ¥vÉwdÞe®Dk«;âbz¡\ÔËÁú»´È,hh? ë¶\\bgG}Zxÿ¸çÊõX§öÚBÉ7ATáö]±Ö\\nø¦¯³.ÅA»âÁ©O+)í<C­,¿Íð7¤3Íî)h4Vÿq"ùø\\båê«W \\nXÝÒØI.d8PËþ/æèªE¶71-<Â½»µÔ%SÄ ëgó³ªòÝSQ\\nñA«\ÆqÜú\\rÚgbO«@qH'~yn:§#DT Öµy\`i:è±I!&÷sÁFÝ0öE²~QZÂûÀø7(ÏÝ©|kº¯aIl§«çöÌèù-=«\Wj¦,³Wú@g(ÀøÀT½=Zõ§ü¹ìßÛpLSÏÝ¦ü×s\\fëW¤f'ð°âA^ÊíãKSbÐ-±ÊKônTM¯ýmÑIÙ|Ë©\\r *z+R°±Á:-,~À ¡µ¥ãt¦è¥Nµh/ÙÂö°×":¨ÙtÒÂx»ËIJ)BwÔ+¦RVÄ³ð@>e9<KGB¢ b¡ùPcïR(>ßæþ§>¢ ø¬Ã½¶ñÿ°:,+Ðîk,ê<61¨¦§:g'/= tS'Ñà$è4$So£Ô!L{ÈMÜ¾Z_Q¶o&-ànáEXº´¶qçIlX[¨ëLP\\rnÿdXÅ¡¨#Å@8#ä1{ÿãèsYÍõÂk¯BOúf>ÍÈ>¹FúeÂCº9Ä,µÄM7ÅÖdÚéÕþh\\n5[Þ ª[uº}õönæ&Ø^èy%\\f13ä½Ãk=bÃ?$uâC\\tJ,xzÔ\\rá\\fª*k­Qvd5õ{'nM{Ó?í¶ð?=|2nÔôRõáfº«sýuË`^vÍCÿyrcµÞÎûÀ(ä¼q6.KçÝÖ$£:H×½A^àò \\b\\bòòöèæ³-b ñþ1õëdÚwæµ¼È!°^Ìæ-g@"Ã?ÙKÄÿýáô};_G/D{oø·´ý­«Ñ:Bé3ÓµrêeHeÐuÊåçæ{´>fÀÃèX\\ngNÅ_úºHkk0®` ôp\\f«V¨*v÷á;ZÞ}tÆ´Û ;0.¤WÏ9+;9AÚ RYK-GQ3Í(Sp±äC/+vÝVÿ.R×ÙýL9IÈÕªyÕ¶*8Ì1ª¸6´Ù,;gyC= ±M Ýçü\\tó·Õ%Þõ|Ò+u"~úÅ´Wzàå+d¿\5³S;ÚÖµ¤XÆ<>Æ!&ßëªayÛ^iK¶ãÕÜ¯ONº,·ÎüB¸V2àËV`uXÜT ´ÆNS<Òì8,AxÄîø½u´¹xÖêG©ÞÖ~§Gü\\b5ãÖ­ªX³à¤2?>5ÂçºusÅ§³@[¾5^1â.÷ÓùÖÏ*&£i\\t:oGÇñ¥9±ÎNoô·i9­zXü)¯\\tßþûÜ­')¹öÇ¤d\èÍXYîÙÂ7Ù"©%bì}÷¹òÏNFâàU@sËP¤³´ÐA'ôT õµß¤f¹ÏN $ªoX¢àw4J¹¡õIûnâOZÙfß¦º7R>"\\nFîôµOOêíëY%ì^ åò$¦0ºµ·arHÿhÞW±²Ñ'2y5â©Eé`Ð]¹ß\\n9Ñîú.¯/ÔSGqzIJbñN<¥IWé6§á!a\\bÐàKúÊ{ë'uF=wÖÙÍ.´põ°Àç 8ýIw^tÑÙ±b2KzÀðî¶o\\r5*dÒZ²±N;B¸¼\-·pq*xÂB3rXÍgã°ñId6¾yÊ#ØÊ*ù(¬Ò·QÈ0Ü§Ó9}(h!+«öjrSÄÄÀ»Wì1vårÆ`vîvÒ¶ë>¿7lÚç:±ö=«¨ÈZ,~qZuVffÅ´ã­¯ýaÜéëBR¬ô,ËÙâöÑÏ®À(ÇájÑ;\\rcHíYl*°W­¶µPÖaÝ×ùÚÛ"spº¾á^Gñ$Y^ú©K&ÇÞ¶ìÃIG<bóÜ¹çùx::îé7WÏfÙ¡On!~±Í¦ÍBéKìi7,E(})­Õõd!äHÄÔm¡#pÂ@*yîµ\ûÖ_7ÚÞQÿ (#7Tìà\\bX`²Û\\br^*Ä&?¥,Ümô8$°jÃX<>¡ò§A¼Ü=CNf\×¹¹,]lÜ(è¡qÄ©@@±Æ|«Z`Ì1*r+äl(mösrýRÌ»ÄìÎÚWÎävõGY`"¢[¤àº¼Gk2\\bæ '¶¿?\\t~*äJZÓ)Oï QÌu5²^å\\t»©MÏÂ=2;&é>¬²"¦à'O©ß 1©Ýæ³XâI6¢ñ#÷&ÞR7¢ðÏyÂ¶"8\\tÏH¥¹ûI&ã1j~óÙxã9ÔªBU÷Ç0È&®»-voE"ð:»ÜMG;²öd<Á ImýG½2YcrfUa]ìD«fÊGë\ïÇ(´/-qÔà[Ô¾®Ü¥'5ÝlbôÀÍN.òõvl÷#»HOVÄ»b4ê§\\b(/9Qm1»µÄÍÇqÆ¬@i½hïú-s¦¼Ïç<6éVÔasxÑ_î^¸!ñÊbÔ9¨&\\b¾Á"«Ù§Na&ÄºªÀBUð«ðÆBdË½?ð^ô?ñ9<ýæá©Ì9±¥ncJ\\b"Ñ-;ñÏ×N´:C7tÐoø§±8*Gô·.<z,ÕÖ¸z¢Ú°:|cÃDûeúéÆzPñÿV×%HQ\\f8Kb¢£[cKsÞpê¼l©_\\n Ò(mgu>»í¢XåwMÕC¡ãp^Å&fÄ¯¸%hµëº7¾3Qù\\r\\t ëYÖÆ0ÛÜm~äH°ß~ÝhS¼n¹i\\fÝ+Q§Ò.Av7s¾VÍ:BCgùN.1½½c\\rW5$³H¬Kst'âUØ¬ÅØÐêBòé\\tmüèãÒ¹/7yÒÅq4SV]áI5Ã«¥³Ïö¶6{Â^H´QGÅÓÂEgÌáÏãl8¼7ÉÔÛûgÐ\\nGÊv±¹Í^Ãñi¤ód®yÄÀ¢/Ú2Oóç\\f¯³m©öiÊd¦ûäÃ(çUF8õÜSb¬Ä*sd§ºh!mMù¸eÚÌëÍafò3;8òÑ\\tÎ®èÅ:ûaáEÀ]¦ï1ïÑè¼¡Cúw¦áHlõ.\\rØzcZ%×Æó@Ìé× ¨ÈÀ¦\\r¨xÃÈº4*õ4=E8Vjç\\bô\\r0Øî}R89;\\bQº²÷¦$<v3?H lt&~}LÏ\\fÇÊnø*×¡RÊ©ôß¶!1û{ ¹ñ¤ä³lí (3òýÍ9$´¡²©èd£JºÛ°úÌDÊ$ 8Qy6«*ÕkBötðsæÜ¸MÞG,áºÕ­H)ù\\nO®Í=*ú.ßHÕ³û-äï_*Aç}ô[[c©òá\\fQê-LÊÔE¤WDâ`1zô}6ò×94Õ¿pâxn¯#Ûã,Éµù×#¸söüJ©\\t­éPo*®Û3»ºýKv`)ë|tÝÄ{q`µtËjL|\\bkÐN¿¼Ô*4½·~2%ÚT) $Ñqò;ãÂ¬\xÌÁkèug`ÕÌ§0?$\i£c¶É WæYÑËÑdô&c§¨Ú*ä:®Æ÷u¾f´y îèpæê]µ{ïMòc)¼åé6¶]ß@u§+ÆM¶±8\\r]íÍLÀ°ÏúùCTZI¥Q×ÁªZ¥ Ci záÎ±Õhÿö\\fjl©ßt:p÷KaNiãqÖJ'ÿù«ZÙîºõ¦îG³wªgZçq'K®îj¿ñól\\f³6FN=µR¶³Û¼ÿf ZºU½J+G~ñÁËïH&Õ\\fõÑ6>:aõÇú¥®Ä¾Âøpp7±6+×£¢C9oàÓ6ÚrõèÜ,õ \\rÄéeò¿\\rhO´QF,!0tFïÃÐ]«X½Í\i'6»ÓçÝ¾ð[OxåPö"F¼«qzÕ×7Kú(×¹Ç¨gÏ\\ruÕõþ;>vMó©nqÉò±ÆÃR¶ènÈú4`×¶6ÒK4_T®<Ä9vè9­äog\\fpëPÖë$e¡tÂ94¿Qý#î<Iÿåeÿ]¨ù·s ²/IÔáü$\\tmP÷Fé%¯:lñàºPÌëÈ·FIÙeGÇDnäb;O,®`-Æ&JH±Tõð<9>O¾VEºl?X½¨íÔ ´@Â\\rèÇGR¶y0Gæ¤-ºðêÐa×ñÅ%¶oëzFv^5!\öMBºk÷q¼\\fÜPúhtL Ì'^µÕ¬S¯¤5øßjàö*}Øâ]£íY)äÜÖ¢_[¯áéïd »Ê\i`&ÌÞ.@Á3~ï}ÑæúûÑ2d6zá(Õ\\rpbÒåT°/ý»|\\nË=k( ^ûþ 'fÕrûñy ·u,.j+&Á©¶ÐsÕ\\f\\rù±*OXÖô\\niwD\\ttßû^sýUk§Å'ÿ.brh2òBÊ¯¦¨øÁCg!hÑm-9ïiSjmÚ&å7âEO±ìA³«"O â¹]rÎ\\rAáÏ]$°l@.¡'vNA\\bÎxn.Þ¢èHàMöµ¹cÆ"úïÐ)<ié"sMáã;3áHx+*§0|w°l¯i cÒ1aZy¡sjÀ¼käÒ$\\tBÆÐü× 6ú9(ÛÅ!/EÛÁîé¬«Y´sÞ÷µ9\\fÖFäRB_\\téHû\\nÆ­xó¿Ëÿ¾Æ0ë0Îô&¿Ë(á/¾§ù ù\G3.óAv¿)óÕLyï5!MTÑ¬Ñÿõc£8°çlOõbT6¾_-®ªíÉÂZû²fNØûÏªÛ\\nÕM~ÈS?3b'çû´)1\\n$ãH.4Öd Mp{´RÀ}úß{æDNt2U®ÔC6BÒHì~%ýjîgå·cï§$9P÷äÇªæ&\\nËkÛ|¼{ëô©$-8çááÇ¨LPñõàótÖ^{?N¢Îªµ+Æ¨ùJ\\b+­[@Xmv}¸8u%Û ïDúßï¡¸v×W\\f&Òýnöéázó`sZ±ÞrÄWvñð_aó|Îõ øs´{èUèý\\bañüËCh¦ës =&DßPÿ¿£ã=Ð@¦¼­uÀU¡\\fn¼z;6`OçÈ5/:'°r­<ÿ±hýaóó qnÝ8øPëL iôrô L¸[Í°@ÄXµFu¹~2LÁ´TÎF£OáÓÚ+$~%&*ÏyÎºOâ¾\\bNeÐGáGåÙt¸H´^×ö"O~wÎøð«3Ï²a,À0m¿Ç¾BFÙ r®üu¤[[m ±8mÚÕ ùã©¾WÙÝ\\f{õCLë!°ª!m·P^ùpÌÕlx¨=Y¡Âýån5'ÁE³"­OS.Þ,Y\\fgÉÕ3\\b²ÍîhÒ  þñM¾\\b\\r.úßÔ_ó|+×´\\bsf%öa\\tUúñbÙg-!u¡Ä¤Ý\\fÃÔý¡N¥ådz¡Ý©®bOûÉí±wQgt7ÅLZCáâ$R »Å×µ± YªG>péÆåßó{Ï=p&åÖn²X\\rîØCjw"*\\bIÌ8Õïëô\\nF®gâÊßkx]ÞØþ\\tNì>@éÜÙ= º§|ÒÝ òÎ w·®ömþúPÿâS\\b8VÏ@\\rëÅ0{õ¹+ü¼),è³»;;a3ÜÝXn×-F)nÆJ\\fsú,¶ÁÍª¿ïì*uZÔÝ!¥O-µùç×Êf*¬Óµ¼Mª ²íâÌr¤ð'^\\bäMv¨F¸<Pß\GêË?ÈðZªÙôì¨¾Î=`/L%.³w¥¾ ãÊ¡êrurºèÝT/5}¾?ì®¡°Fþý¾düxL5Èôl§ëÅ©~0Á/x±ÆñüOnÆ&³9ºRA¦¼w Å(¨KÕ)±éë[ÅïAõÈy£÷D~"å9áTI^®}Îj.±R^ ÆÃ:RkIÆÕ'¼°4þXFÌ\\bÉ·¿×»ÈÝ½õS¤W_7²Kïk¦w.5Ïo!<Á7WÍ?þè5VDxO­¯'­dyoyXÇÍ\\tmïò²Qç\\bU;Q*rôÙ[kFã¨(F}M\\bÛÖC#VT,ÐÍJs_ób Âðô8(9¯ICLD×Ä'\\nÓE¾ù\\fÇZ%M¨c¸×Ðcµ âj§Z}<'NYºñÆn\\bÄ6ùõ¦O¨ÃÌ¢\\tÚ,Täþ¹.=ÀI>wz\\fj¯ï¤.,^yij¤[NÙ.õã[1ßóÉâ#\\bB¼~ñýóô$ÓlïË°Ü3Q¹wrv\\bÂáêöf©\\bkrÏDÊëHõÈ1õm³Äï6¶ïeØBB¤w·Eü±Î°ú\\n3Õì;½õ·îò[¬'&N2ãs2IË`()Zwº'RNûéaù¬&õlºQý±\\t\\rîÁåµísø/!ßðþY=4¼©v÷ÞsM4ÿ´E=A±&Ó#yb=§¿t®XÄùO¬Ðl@¹hçYF,ì°ÌÑÂpaUì]Åy$Ò)«åôºa÷_#|`ý¾ ¢ªT_ÑË<¬SxS¶{¸q¶V@w\\n³6â×O¥¨ \\b¡ù¾³@Løæ?"ÏáO3+©ïlV0Ø«Z Ï¿Î1¹=qb(·£ªc\\n/Õ`)PÖFH6]ï«,´öÝè\\nww~9w¹ÑòÜäç®{±9jf~Õñ©üÅ:`{CÆ wd&'bcHTé YZÅçÒ@*õ7ãÿ}S¡P)M÷PÕÓ3ÎS»·ziúÜ¹ýÎ.GJ¸/ç¹³g)é­Ffxy<êO;%ÊÔaÀÜÐi\\tóhP{é>ÊñÙèd}Lxô 0<\\r+ùy ß\\b­òäÉXõÚleæv>C¶0Ár8 2¬ 1ç'55vÜ7!tÐ\\n{Ne¿©ÃôÑrMt#ÜÉR(\\fBÚ!ð'æ®C1m;,\\n/Dô'ÿC¯wuj!*{H<&/X§@|Nx]E¹>ZþXãß©©|.Ñú¬û `À\\b&æ.WKÉ[#eÂ¾kg<5Ü³#,Tâ¥#GÍÁñén%ÿðô÷Wtº\\fÄ¬HÉ2OÀáÏõÌßlÚö}7Aöqó(Å |çdM7¹.£xckµ\\t Ù5ù¶¤YYer¹(i$òÛ«¦`¨ù<&f\\t½OÓ6ÅÐI+ì»öK§÷5Ô«: ®S¶±ó$»Yscäóý(ÿ­äMró¶Þ×üÉÓo{)öÐ÷ç«©+}Ä±% ù0»]¥Qr&Gä3Ð\\r>i,ºp9ñíÌ°l¥ÜHk26Úa¨ñ9ÉKiOBP·©|úQ«¥tb6J@õ6Iu>A²U_Ädþ¾Ìq?\\tºcÁÇ:¨f¦pÒÈ¥ÓNtüÙ`Ø9½bv·øÔ²DÒ»UsDÔøJ-õ *©þÜ"§ÿu²UwJæÄµmââ\\n\\tÿÅ»upùbi(ý×Sè#{:ì¤:M½Frñü3¬»þtägÕæóÎ7ÌB|æªý±ßÙ«Ç'ãaD:ÌûlêÂ\\r\\rÀÜ3\\tHÏüÿCd¶¢}ÿuðø¦5ª¼×\\r3é©8k0z>£ídã\\fýç9>F9ßbëûÀ_B mà#[OÉÎWh¸ýÜZ|bùûyÙÝ&<¾<ö?ÐÊ¥ÃhÍi+[uQÁÃLq£Ìl7ººf³hÑ]}.¹=ñ±`6¼º©So­°°DìE\\rX5?í+éÆtQù¢­þN¬Ò6ÏG¬60##ÿ¿bØBÖHÇÓh«öéÑ\N®8cÿµ|mDS ¦#øFìpòw\ECiTø¸\\r$9ÆAêåA¶l¸µÌ?-øÆÊÄ¬EC¨,%eLAéBoÉÁª£×<`Åð¡RÎóXéc°=÷ÂYÓçrÇ]³KÅ¼f³ë_¾' òjË¸®(Z]F]{JÓmåò¾òL9âM)±Ú9ïíEÞÓ¡SÊ¤ZG ³/\\bÙFµEmhÓËKiÎ!YÚ¦MÃ¯îýëFµßQ& ÙÁ\\nüW¾Y«¥l¢'\\fÆçØo{ã~Èî÷rOí9ï³`AHó£îèÌ,xø¿SÙ$L~_Ì«lì¶7öo$YôqýD§)«àÃ\\fC'Rµsª]¹jÃ¤^8ð4î^¢=\\nÅ°üÇ{ÖêüYð7¡¨µêåí?ã}çmä-\\tkØ×æícË%»I¡üÐyÜÅ1(¨å(z_6ÉøÖ¯<¤ª²¨ê¿!Çã5Ô·ÂÔÂ£VeX¯þ¯TFôjfñÀá £nc5±]þ´!¯\)Ük!ïaL¯6ÃIºR¯lËgJ8X,+kI¤»R§ROEK"QÀÕ/¶\\flaè?Õé@V£\\bÜ_¹0õ,dÝ(z£Õ,sÚ²ØJõ¼[ýÃú÷{JÞCISø\\fÂË\\nXM÷hÕÈv?`[F?a\\nÈ$6ZX"d]°(Þs"[¢`Î-Ðì,Ea?äßçP\\nH+{Ã[ÿ³Çùÿï¥à­a3¹È\\nÄ(sk­º3®zá©ætv6/¹r¸@a÷þ 20oúÖïJv¥i¨±ãFNï«µ\5ô,C«öGôð8!ë>5õÛ*¶Î½è/¡%ãÑ:m&\\fìs9×æ\\tfîX/éC¨ã\\fRúp8æÄÄÅEh¹ÆàdhÔS\\töd½úfì®$2ìF¯â6\\n|Ï ¾8:.Ô?ù4³eàMH£]%]öæõyÀ÷K~·ESaæV °ÄTÆ8z!£<øëJ[ºø&ñH\£|GòÓ­Kô P;yÐ¼M·rÚÆ=ïBõÐÑDÅÞìô®ÉçÞõª7UèX9^º(³Ö¨ª%jöZZ¦×ÂÏ»£7aÜköhÁP]/rcésÒ·_Wà·Jþ§Mü9¡d òÏ ?9|gôÌºg¨t=ª§zªæµ4Hõux|UwßÙ|!Å¦PZ<&GôQvÊnØJ0ri\\bÃ¥2äþ¬\bc±ö//äâ¸c÷%>Å\\tÃh\ûvïNÊ®YòU°ò\\fÂÉ\\nh÷ìÕ¸Ý#ÓÙÙX¸¯5=µhUÙ°ûã/@åÊÈïè§\\f.ÇKY:ý^gµ$Âh`¦(Çái82ÞxàÝqàü±dum­µ8ñÊø»Ì/zëöù¾kz2o'äGlñÂ1W ¨RüâÛß4¨*#§ò]$ECÌÀðÏaÒVÛ!ezoýGÚpûºô²|ÍwU>óÃ!ÞHô¡£ÿ %{L)u¥Ó;c.04Ò¢LÄ³­äpÑ·©Ä+Äådñ§¢LhóØT:ÐÉºc»·(¤a5n~Ò°+ 5ýÝqaQ¤Î-1~UZ½D=ü#½Û÷<»ð§ØJ>¡MýçY¥<fÆ[E¾_ÈwÚy¸¸á´\\nÛØÑØód¶<Òòn/åsn¿Ej£î'<°ÀcåjÕs^iâÎÁ\\b^Xü1k0bFS1Æ¨<{&Ëg@ðjY8kU÷l 0¢7SËÔ×\\r©Ý_)\\f¤[W¶ËÝ(Å<wØ©üP]ß?Z´èsÑóPSÚ.Íßï¶W_õnòó(8ëûp\\tSÃR½6°(i»gúëâ¬<X=Q -Û®¢ëEyNÛ´Yt$XÃktOc×¿Å~p÷¯fb)iXDuë]á\DÚ&Þì÷\\rÿé6\\rZ¢(odÙãæEH­Ë`ö|Ô-dÉ ¶§ÙôbïÿúåÑG±ÆëZCðþ\\tG,mâÝ:WéïÏ]-½kKô"e\J):ñWU<#Ë=ÓÕÜ0öz-Yø,ê½MWå¾-S^ÒA,-`Ú&ÏÇdua£f´Úß±ê(Å\\tµR¿_ò\\ts¶­Ç0\\r/IÎè¶\\ng>};¢²ü4oÆOhU>8Û@Ìú±UÃ¼GÛ ¼ºú|ÍÄë=>ÂrÃþ¬ï~å@'Wp©èV8là(Â£øpÖ\\r2QòLnÎ|¿«;rg²ÇPÿ­8){«ê#Ö>kX 43xt0³Çr´¦ÿ:öÊì¹Ñytè<`p«1¹¿æ5(\\f¡¶¢?K\\bø'À×?ÍQ7a)"ôZo®ºcÚÞjRóuÎÅa+¼ÆnoÕ¿2Ý 0þç¼0Î8<pK©<{Z(%uxÍ/£9ÉíL@xÏI6:$MDê?=áÞÏì8'17o4U¹\\n+Áµµ_^®¬s~3ÒBµÓÓAææëÅ¨óVÔKSPW^f¶Q¼ÈõVì ÿáSñÑe¦Y·oÄ7ok!`gÑ»VñÁ&dC1¾r\\nL(lúæcû~c3¡M8§©JÒuÚ©UÜ¨v[¡ÑrÅÚ·¥$ê'î\\f61½åuL'1o(¡>¤]7|Ã@ó½äðlÎ©XJÌØ©jÉ¬a·2ûõIúgB¬!]zþï,P=\\fo·Ï}ÄAH¿0ÐZ½¢.¾]ÛòÈ³Ó ®X¶4á>6{r\\t·Æ,Kõ)H°Ã\\n®Ü q3Õ,Z8½4CQzOp½cWo¦OsOÏö¯ûGÄjomÆÙãó°Ä\\täÔsÊø`<ÃaÙsLô]úï&òkQäOSáNy\éigÞÇ,¢fjR|$\\n7P«`ïºÁCe[|mfEOú§,ëÿIæÊ%¾i´rGäÜP0Ôè^«PIÿúUÆpÔ{n`bð¸²8±ë84ù-âæÎÔr^ 9ãñÝ½5¶¨ÅißºbVJH|úÊ\\nì¥\\nç2¢,´ºI×í× ]l¦ïåÛgÎ,ìsÜyëX¤þ)­uä~å;´¨¬ÑytÖHÔÑq§ÙõèCÛ°&òú3cÚÁU÷ÌñÊD¯Û@uJBnê 2KÔb6è ²Xiåpá=¹¸!©wk\\n)}Ñå5ÍUÅGêë'È KÿÐ¢«5Q>þLÜPvéOÉI°ÙpL$t ÙhÂ¥¬¤uD.x××sâ°Ps³pû'ÅÌ\\na 7ÛòrÕýY¹¡«R»s²¶½?÷'5/Bh^¸ÛØe9fl\+,FNÔ®x^Ì±¨Ú®>uM×x0ÀÀAmÅ7@Ó4úÿ2`XÌeÉ÷Cx©]Ò@qÄEÑM ¶q\\tØÐ¤âÆgIªôÕÓy,G.-öÃ5¦?XÅ»_Í¤A)-¥&G§9uþýÿZ^ÂNæNïÃ_îÙBÝfðìKÅ¡·0Ü~Çé ½PµOÂ}Â÷ÞäË­¡£ÎÒ^¶w¾| l÷\\b~Zä)OZuãeÌÄG«7ü¾¦gïbeòpcRËebï¾»A£SD^8\\bä­yø°äû`*!X|3çIãÑ'MÎPÔ"ÌÅ-F¿6¿n+ìfö÷Þ¾ë¾­Úötáªþù9$ìÃÖkÕ3ç®{éV¶a\\t,Ö³ìQzbEIý½ì5Ì8ÄfÍþ²}ªB6ñgÇ¸6©ñ«ÊòÏ^(ñ©xÍúOàÕÅAÈc:æfÒâ¯pè;Îõ6C'¨Û{á\\t<R¥ÙÜÔEæU&1Î!¹ õ§Y\\r¦o0Àjµr,Ö·Pºòà`O³á@ûøÑHB$+ºSFË.¿µõØ£.ãdCR.cÆR1sÄ´HØ)=%¨P 1rgó«ôÙÉd­Ä~ä/1ÒÊlQÖEd+µ³çùA¨ïµPÆËÊNÝ^Ô4Ò\3Ù\\fR1N*ÿTO/]SúNLF¥39·{9r/c«ë"ÛýÂ×O¡\\nÙ8md»Ö%¿æûÀ³²OüÙTÝWNê=<41Ù±¤[®Mçýgj»Ðªe\\tq{K[£¼É5=¡ZÝDÇÖ!/¡W£ÔHÙNõçÏ^Ð±þfßÌ¼ÉEE5fÎsøÅ:³Ëòaø±ÂbæÌ6}pþ { N\\rø^\\tÊõ¦/]T!GácA~áåíu\\tÝFö/9r»ÿ+Þ4îË×äAbè_ºµ>¥< fªÒoF¾GØµ>]W¼èIÕ,¹\{²\×³3B^²1ÒØØ8K&y¦.(¼¹·N³¯L[4yî6rI$Ú}Uîü×VÜøÜ+Zº§íÁ>ÉØµ­{\ó\\n5!1wl¥JàËÍ.PK;÷PÈwÌaqÊÆøîø¹¹_\\tåfÙk`wXrÁW5©@Áv\\r qÓõ bPFãz*\\b±g8ÒzG\\r-Øß$1S1Qî5d4UUw[¼ÒPèóá}¯Åâå7.wµ§lxXc\\bV¿¦CB4ÿ¨ý$Éú¶Ý "æv>CG\\bÜ/Mþ ±÷ã #wsüH£æ°ëêØ~ê>%«l`p;âÄ`>¶û×\\nê ÿ¬yÌ?Þ2&ÞàQÚ×á8käº;§*¼ßÂVÚvýB×pQ*iÅo2ÃIÏN©)\\fã\\f!1ñ#LbÍ<âÚÉ·Þ¾èBéyÙ£>Lè¡Ke¨ñÒ8%Eæ\\n$(kÓ;©pøÆCÉü«%¤¤µ×²ñø mO\â"Q7úpêÜ¨hµîWÔYÛ©éû) ç.,ÈÍ20öë:/E7Ç_ä1{±(¸2òÎ§ãÁïsêmÀ±1NsÏ¾Ú6á´ZU¤*FÎ°D}ÏYQÔ~-,s^3ÀVKÚõ½£\\f@k¶Ó$Qª¾lQÀÒoÕ.±C¤uÓh½<³G¯¦z@oB*oô°c¼¡ÑZVUWèTÖ4ÚÆÐ0,bÃäq,_2]e]àõÕ\\nA¹¢&îó£ûHb½Ï,«5@Ç²|@#û)s`µIÇªï´CÑÀ°5òI\\tlö*c\\rb\\f«¤*jÞ¶V%ÆÏ(>ôj!ÏzÜÄ;iÊlg ¥mD¨ÿÖ7\\\tYÐõo\\tòí¨Q6ö*Ñ°T¹7açVlé§"õÒjô~O%´Q\\tt[Dv²1Y®½ÉGx¤¹-VFÅÂ²jLçÂQvGÓ> ê~£O0«d9«£ºÆ,Üò|7ß"³|ø¥c¹c\\nx¢ÐÀ°ÜÑ2\\f\bÂ¾0ñë­4">úë\\t×pHZ¯zA½}Þ¤¢ÿ¹KÑÊ;FI å1jrãÏUÙarIíÞ[Ofïêa·æ¤¨U°Â~\!b®»÷q¸æHc¥I¯sÌ¶üM=kãF,ËØÁòEµ3¯¥ÛîÂÁâv5ÔkW¨ê¬­\\f¯õ]%&KÈR]å+|>m6Ý|ÿ+v}ØC¼p¤Ãòå§°st(¯×>¹ç*cÄ*´Ï¥´¿±¨Á2±ÿÏðí\\tsÃ¨Ë'^°u4ëké#eæÂðE{ÎÕ\\t¡Y ÓÐÂ¹#¯©\ü|A]pÓ)Öl¾­Ãw«â ~~X,1!j¡\\bÖæPÁ½f¹w4ÈÞõÓ(l-HynælvTæ%¯Ìå¹¸âN~Íç¸§YÚÝBºrl\©È4~¥KÅå½|zFOÌj¬qWCÍ!{náê{þÝÁ[*ºúQ0]HÖ±®÷\\bÉµÙ­ñâÖ­È)÷Oä<¤^O¤K¢+³?¨ÒH¥9óMÂ4W\\nq«AGiÓuá_{"Ö*KçZ{k4;&9]ÓmöaÜèo«û1jíÇ->X´Ð-þ\Új!Ø\,²9gÉß¥S\Y.:³õÃÉPüSätåt_<÷ÿ,ÉäI$0ÓQþ&\\fÎ¹G6mýÿéOÃ¨­WÚ6£-osýº\\b¬sø(ÕQk8Äß6ÕöLA?y/øH°a$¬kvTÕi;ÅÏ$;¹ÄcVxà£;^×´&á/hÖäÑóå¤;Pnn5&â<­°X?ÈïÊ/¾µØ  A\\r²+<ÊbÑLF$\\rÍv½Ç/ks0/Râ[Ó4'P±F2íæ¥^zï^;Ö¼uéÂÇ~\qu/ÒõË-ÉáÆÈ1éÉEÙzW\\n^|ûQ%YkLèÅ/¾Ï¤Ä+KÚû(Ín¬,(KÐ+Qß¥VAß¯#Ëèà¥û0*UR\\f\\fó7p²[OD¯ü~\@ÄäÀ´7bpÔ\\b ­HðAÊ*g"ÚÈn21yj7o!_\\nbW®ùD#WÆAg,\\rÚOÛÿc^±i*òo5ÓP¥î`ª6ÅÂQúÆ?¾²>tDf_m²ì Ê}°Wllð¬öI>ç,¹/ôÃd@syLäVv"Ú}3AEu ):Â©[%xÑÖ*<§»wP(vïà'- Ú\\búÑ[\\b\\bÄuô½«ø>¼Cì-a\\t@á~Zó¥ÐaV$g\\b±ÀN@_¼ÿÉucd¶\\n[vô%álÚs¤AÀº%`ë¢¯½Kæj ûôm-/*}I\\fVÀI1>ò1å}/ë*0!×¹uc_ºè*+å¯É\\t*#\\fÜwuÿ}¥ÞTßåH±;Mc%µFþ-Ú2%º>Ìõ£ÇöÐ¯~° ÒòV}\\f1)¸¿ÞREÍ¾²%×r±\\t,\\nÅÑæzd(Yø\\t16k¸må]o8MÊÜµi#\W¥øøMí?$Ì©²¥v^z©°Ó$rF¯=hÞZ~óù(qIé:*7÷ zM$à@UCçtÝajô»|.î5bx³¹|¥J97@#¹bS\\bÄ3Ë;Í;>yTÀU\\t½mÁ.\\feNàÙmïvÒ\\bÙÏö6Ñ5ÀÄ¿Àl¾V?JGm~@ênÐ$¸aì êZv®ËõÿGçóÎGÇÊï3m¶·Á:ÌÇt´èø[ÇZ¾'Þ¶ÐÆÑê·h¥C5µ©êäx:UAÿÛbn\\t¥öÒ°J¢þ«¯­VÉ¯}õ«ÜùÚV³?àüÀuÁp×mÅ sâº wÃ9üUd*n"ã$2ÓQÍ\\t×j, \õË×WÄq¦ªç7ì¤NºÃn)¨+Zµ~X ¢¿fúù½>åøAÁº0¿h×ïPm®VÕÇä-\\rdOÐ@A¦}q\\tú'CîóÝDØç-#Ba~êWX¢ÆiÝN¤·)ú0õ9ÖHÜÔz­Þ\\t<Ü²Ò¯Pã\\bhvõ7úP}ù)·²ã¡Ý\\næ©·£´\¸SötB(4º±Û"@ªÃ4÷9Î±+`:¥îCo¾\\f-YÄh´"£úá_qfÙ(A:;÷Ún\\tÃqUÐ?[¬Ò¤ înyÏ %# °ûm-Ç\\rÈX~ã\\bÈñµµNFÓQé;`K#Xöw®WØ½ö~Þ0.êç%<¿P«Y9Ï6>¤Y£@ºOEiÄö¦lês¸hñSlÏá'Æ8ÃØ =W0lSÔ\\f2Õ[ðÈ_½#;ò[Sá°Å&äÿÙ8"³f6 _;EMüÄR%Æ×±'4\¤q¬HvGCÏ~á\\b²}(¼ëKQ9aú´ÝØ(Ä¢cv³ÇuÄ_Ó¬5`'FH£á3\¤sR´#]ÂÎVç­=¾dus¥ÊVçdA|ò5F'r&6-óp¿3)¤ñ]4çUâ7VU+4\\fáÖÕ\\n©yèý6A­|V¼jýà¨ÿÐ\\f4NV=X>k&lõÀ1ß\\n4S§N$ÀüïÂÂVÃú&þú·;`%$\°*1³AøÅ®;»±Ø2çU]ã}U.V|º}Â¯xUëÐB\\tøÓû.w>3K\üÊÔà«FÆ§wþìPï;¯c!åÉb:(\\n=õ^ÚQÍráõq9÷®@¼Ôb£3Oó½Yû»<ä 1|h\\nO.°>.vÁÙäî(³ÖÞAÿð®ßp@×.Z¯ñjÓë9BWè¾fDK!âý½ª,ÞR®®?LU#5ÑGF'Nû[+aF%ûxz ÐðÖjâì8^ÀáþÀAc6tTÑ÷]¤S$°¢J\\bô>ÒCÔóúQc¬²1öñ¼;ViD#NÚnçÒVÚoîÃ¹¦/Ç¨Yæò3ar3æß\\tééI)æ7ÕgãG)Wã_ÿª¸ÒE¹<¢0tÛñ±PýßOÓ4ïMa¨×hq´ó7ZëåN¤Î÷ ëÝ÷ Gã½¢1¨× ¯Öû(Ö8é´}xõïãÎ¬Î-mR½\\r%ØË»ýJ/¾vÆ?>Ó}V=À#ÎT×RÌ«|mÎfZÇ]ÙmÊ¤kR½¿\\fmn/&åS¿Oª¾kfñ/ÐOüX0Ê\\tÛîmÖ¹ÀÇ81ù¹À<Le·\\n§Ò¿ÐÞS?§ '\U{Iî\\nKË;ú§Þgq+< »Èââ»ü;hK6=³·ÛêEA>Â]K;môÇQ¢×\\rãórSö«¼Øqkî Ü ÝÌY5ÿü,ÇV÷|Ì¹FöngòGGÅíã¤½èÉ Ñã@5ì&w!\\\f  õdàV]¨«b$ ð÷¢ÕMËÔPy ¥>\\tõÎçË§Eçx\\nÜ§É+6°5dB°,Dú_²þTA\\r0$ÁMÎ/¸çÅ\F8º<¸_n\\t"<´±8%VÖ²\\t·°ÊV"d_³c0öÒ¶^>¢3(?|î"sî®´TûV>íÁIÛ¦iTJMF¾ic$RÑ1 (±üêUÃS4Ï~!!9/Ýû?b¿3Ñ¹¹`ë^÷xLÜøEËÂ¤ð.Æyz,vîõ í;*äÙç^Ñî¤[ÚqãáÖ$òÿ`Ëíiñ89Òrâcl÷o2T`v³áAWøzõ2ÐlAÝî­k¿Mµ¹¡öß²,ôá]-/V¾v.µ»êÍIÉâØ»þÀ$ÖXà|\\t»©Qß¼â+hÄNúKªÑúÚr®qæ/b[E&]u@ko¨t\\böáÉ¥%:¨IâÇØ÷û2À+>3÷÷WàV2wª_]¯¸ï\\f³Íê"!Êïxtòf6g#h~¯h?£ñàràÂQVs Ø/Ý5ÌMÛð¬½JQ°R^AÈs[ú3mßk4A>à*\\f~Aíâéä<`s\\f½¹\\fìêB3¸Óv\\n¹Ñ_,"«ÏhYp¹yÔEv Àé&b¨Ì¿=f\vo&ê0IWÔÌèPõàìi:ØhüY$/J¼aøp£\\bÙÉØO¼é¡Ãús%áá%%ã~îyfØ9´¥mAìÈâ·S½Á¹ÕgÓ?D_!\\t±\\r^GËîØBzMXmÁ3ñ\È¶ªZCgÕct³Z¸J-åÂ\\tý6°6lc*uâ_ÝÂ'ÊÒ\\fÌ"°­ï#µo·æòAÒ×r¯<\\nN_quûàºUiÿ(TÞ«Ðy{4£~2SØV®Ãæóç>ö9Ç²àáéF½ac¸QUÊßb-ÑGë]é\Y¯ÂÞÞT®´lyÓP!º]ìòbM]Öñ96Äú¥$Ñ~³;Jc´¢®åº]Çn@`Zýzv¶ùêmó`d9üñ;)¹Í¹ ­ìT7;Ö§ÒVbóe¥ÑOÍKyÑ2øëúÕö³yüZEgñâêözÑ\\rJO¯ñ^6Î·"Ýä\\bg@Z\\rT$äúü¥_¤æ½¹ýycyv¤MOFÉõôËôrÚ~ê·ÒÅë.gªº Z%äÇ 0L+Ü¤M¶üTPÒê£¤úF­Ñ£Ùbô®þ\\nÔbf!²©U¢ Ï©Ø¿íì[Ý¯tÒ8ù[p£hÊ£Z+¢_0Üä]ç¡#\\nIÁÇ5Ë½=\\fh'áî^ñ¡fQTT¦þbßÎ%â}Wv=öú¤Ó£Ëcþ"f_/QqnÐñãý³xl¤ÂË¸ùÇâY2ï b0ðg_Üþø¾x¾;êÒ!3 e¨ÏðeÐÝÀÃúh$JQÁo\\tmùbÉ`ô­>õôg²«ÝÞD:õ¼Q5ðC}¿üþ4iÆýàIÍO(mì ~å2tÞú>ÇZ¶ÑÁiõÞõ¢²H«þ»È°ÔiÑÜØ@bÔV¬ª:ü\\rûX;ÈÊà¿ZUßº@ù\\fÕp0¥\\tg2wvr'xöÀµÅ Ã×%jagÃ,êa[sÄaªó ZËHñ\\n+(\\f;å;§¦B>)üxïÛCÅ#%·UáäETeêe×Ü_qQóy×çL9Ë#\\bnSNtªPúî1äú¹Íîÿ[KHpÇ*k6i/g°µV©$jÜäë&.ÂëPÖÅüLÞÓf#2°2áÆitÒú×þoþ5L¸|µ´â\\nZ"Up9ÔîÅD$¨x4~ñ6"ä)ze%ù5Ââé^/T¦îçãªGªØýh°\\f×,kCÞ=n=M À!\\rlA¸¹l¥?å½3Wm7_0#0-æOLDÅµ¶6Íd®87ôKçå,ìqçÖ\\rò]§6ÁT&õ¼õ`ùõ¸p}1íaXY,Ëø¾§ÔÝñ/@ ÌPUzÉk_é6ÌØ£»0_Ï3Ü°è2Å¿wS øDñäÖ,½2*xaDRÒá1¥$°Êõ5CLôx¼þ§ù¤¸|BÀ{ÅY¼±ÌÇgÛÎq½Íåe½xíÌ<ÆÖ¼,¯FZDBßæ8ö©4«ê0b^¥:&F°: yDòyÏ+8ÅÖEÇU òy:üeyãïð$ès`Rãâ>Öºæ´ôx:&°®ââÉZR·ßàz¦cX9ê´|\\f$eÏ4bñ\\nÓxµ)¡J¸Ûùh!>3QÍÂpç F%ê0Ö8üéóg\\byïa\\f1¨Yd¤¥ËKØ¼æ¥Ñ`­ÖaU+þR\\twdÂDl¥kFtÌ (D e<¯åðþÙèAö/\\tLoGÑÉìÆ­ÃÃÏ8,´¾tAhlWï·{ueæÍ££E¾Þkú,ylÄÜb½$ºv.Dùv±Iü÷ñ:ç'
    //   70: dup
    //   71: astore_2
    //   72: invokevirtual length : ()I
    //   75: istore #4
    //   77: sipush #32767
    //   80: istore_1
    //   81: iconst_m1
    //   82: istore_0
    //   83: bipush #6
    //   85: iinc #0, 1
    //   88: aload_2
    //   89: iload_0
    //   90: dup
    //   91: iload_1
    //   92: iadd
    //   93: invokevirtual substring : (II)Ljava/lang/String;
    //   96: iconst_0
    //   97: goto -> 203
    //   100: aload #5
    //   102: swap
    //   103: iload_3
    //   104: iinc #3, 1
    //   107: swap
    //   108: aastore
    //   109: iload_0
    //   110: iload_1
    //   111: iadd
    //   112: dup
    //   113: istore_0
    //   114: iload #4
    //   116: if_icmpge -> 128
    //   119: aload_2
    //   120: iload_0
    //   121: invokevirtual charAt : (I)C
    //   124: istore_1
    //   125: goto -> 83
    //   128: ldc 'FÉ¬Æ­$ÕgãËKüý¡*äz¦^LbvÒ.'⋡4auó¦^º³°AÅ dg\\bó6t;:#_á õvêw\\nlÉµVÔªâ×û6 UI³rÕË¶å§ú¹ÒÚ¶ºÍ0ë'H¶Sÿ4Ñ9a¨M»µÚoõ»k{)Â%u½ÊÏáÂvßj\\f8ØãI)l"x#¹\\b³®¡Úµ%ô¬\\r¢Ì\\b¨lZ×ò\\f0Ö©3Ðl³/¾ÖY8 IIàV³ßõÅ·X¸ûH7éèOßx=¿9]­1¦§F¼ùo!»×äÎÉæ¤L/»! gæ¿.#ÅÓ';T\\båu$yRa£Çó¯½ÍÎ5/±½Ì¹¶»ÛæÄÈ8$vAÔ»NÔ]|Q%ØôY¤¿=ëÐ|=\\fb¢)Â5ºó¥gÂÿÉö\\rÿK\\n¥9c="â_«g×ä'ÜM6ç4Ê;&1¤mmc¸èõ\â\\t©«6\\fùiöWW)!j`öwÓ¿}ÈÂ%î¹Á¹¸l)TêÔÎ.Åç]ªC5þÝÁ<ÅwüX\ój&>*ÝÇA«ØÈà {*¦\|F´_/¶G)¬+Ö¯$ü^<ª×ó"°*b~ç4õî*¥ÕÓ!C,h#\\t¿}¾Ó­&ÀêK²à¢¤åØÂ*í{wgß¥3ËV{KÓÝ&\\b\\nêB]¬¨°ò-ñáàªòÜÚZë1+Þ´=³:¿óD©·ü6QOµ&\\rS £KG!kÂ0,\{3úòÿàýÄãt£ñÐï8,és]¸\\b·Uò<ÎþØNÉu\\fZÏÎf(ÿd#$då*HØj v;^®ÓÄQL¥hlÝ(1\\rªÝL¶-)Ó¿4ØÈ}{^Lä)\\fK¦ê4_Ùõ&>­&"ê~Ê¦Éwò æv«9oBãP'²kõÆ/¼gîôî#WÌk©ß´×åÒo0òïvKfR©÷MÃs­PKVæwÑÙÕ\\fZ\{ëéÏý»gMVvÂ¸ñû[ÖxëràÑÑûiJûî²¦·hK:¸Í²<ÁHû V`Ai\ê(ñZÒB&õ Q´Ó«ÐÆ¥eUÃüâKjHF^\\n¥)÷VØSÉ¾<x¢þjûu]\\ný°o§±Y¶cRÞñÍ3dá·ËX£ %0õO"1G\\fRDïî[´NßÎúÌLå¡°a¶.EÕßÑ«3þ³¯Tá?s\"¤Cc- Ô4uéÝôs³^A¤"^õõíö<Z¦Rm¶^+ë§çVÄ9¯O'z¾³ EÓp)g@?Ù¤c)þýí­O¶øwö¬ T×ß±q ÉÄ¯Ù [6ÚduÝÄDxg÷B6(xÉ¸aô¹¥ö«°Ò_÷J£ù.#x_µ¶´×/¶xúG5íñÑ{\\b½k¯½ZmÆ{\\n¡0Ò\ùÝò:&ëÞ%Í£}Ùx$7¢7" zf*V<Ù(ë\\fv¼Áá³óE|p4ÁL"qí pb%Q.h³KMÖVKwy²å×É³\\fò÷âdE±Ì:ug\\n\\fpâ{¶fÓÂ¨vå¼D£üû«ÃJ`úøA4;ØôMÜ'J_äÔÓÔÁüxë´ß! >a#¸rï+t\\t¥»öj²|GYZ´åLBêU DØÅSØ?/f°ºE%êt®¶ã±S\¡Ëí;È5A;Õä¨¹3d_Ð¿0~÷¤tØÀzØ~6ÈDÌX¨âË[Á4â;bbæö\\fÙlåÉ<ØEòÂ+an}\\tP¨ÞfW;¶ÜPÿ£¤C²>à÷°eÍ6ÿ[ðZP8kÏýwÉ1ñ­?tïfJZÀöíI?45Ô¾,~ý¥°1@ææÃEp0øÖÍÐ¼F e²2úùQ³"ñ}£dèâ¡CI®ð\\rÊÁ¡¿ÈÜæ}gOØúÄzÞZÊ~h§\\nçÞAP§-¾mJÂÔw_Y\\bàêù-¿6ä?ap¬ÃÀÂèx|!Uk+|crCPà&TÆ/Ê6QÁ¶b)ð§£N¹ïõþ*jÛèJ¤êê°Pî÷~v-L­DÊWß¬hÜD2ðb¯U×Wtµ/¯£vgO4¼0¹ÅNòtÊò$ô»35}Nö%Zê»M'ì8?«ï NkÂëÏ½jåQò[`{<Bd~>÷û@ ÑR7ÿd;a=²$íé¢]*aZ¢Fðrëýà½F{60}\sT)RAÖ[¤ÜB \\rQ8Jë5\\rüt<Ù[*ñ£ÖlmüàEcPâ*³,0)OúÒ¡1Û<Ç-!GD\\r+ì\\rgdRDLC9oºÍ;Lé>ÍtÕSP®P3ÄZÀk±µöôYvòÝA u LsXKÒtàì"­\Ù\\fÂ\\bF¶&Ìôbt"Ïøl)D²qúîî}`°Õ¨À->ìº&ÑV^dô.#ÿÛyÇ¨àóDâ²D<[¼k\\rÔ@íY÷]0iDúfµôY*ñååi\\nýÔµEÉåDóÈyøMgO&ï:å< ¾<&G½ÊÉ¾>üÙuZo£çîH_ÛÌ\åMë«nïhLl0ù¾iu8Dùw£¥ñ¤Ä"l¶ðÀ| 1wÎ mè!Ùéï½ã(·[¡\Õ5qzÎÀ?t'ú!gjD8ìfÇ×dØK¸K?Òd$;Í?}uV\\r %ÇCzb}8¢¿þGm Ð¯5vÃã~Ðå¼º\\t\\rþ]¥rGÑ;ÄíóÒá¶]ç´\\bÑXÂBªmµÔµ=FOö)¿å_¯¸&xðÆX£\\r:¢â²6ÃÏÃS\\bñ·b{ë2;tà­·ÕïÚLE>»?0laí4â%ý°n7°^~==³UlVyûSm.Øµïd8«ÛLhY"â:íwK¤M'\\r²ÓfÇ&S/f-í¯TVÚû-ìæduHÊ:\âÖþæ¢*\\n*P\\r°§?Þ%ãp´1Úx©I7(Xuè#jdUÈ-ã|\\bÕSì§Vb§ú'miqJ|hïÑ\\nq%%9#·[Gß@!;×`2)ÁpN.Þ»!\\n.¥¼¹)"xq°O)Ïäù#ì±ÈÙ´÷Û@Æûý9há&äÂ¼ÒÀ:í'VÌ¤ÖüËbÆ÷ÍíW*ÐAqb[@jÛ¸ôPñ~ñË^zmXmÕ\\tì[Jz¥%w¦ÙëfEÌxÉ5à>V{WuI*P¢Ø¼=*ËÍ÷Þ\\rÜ«!©Ó±0ùÄPÄpâjÅÅó§«±RGÌ5c,0D`0G(ÁÜU-"ûòNÈ\\tª\\t©)WõMðêR*[úvfqÆ©'ïçÆKtëLÿÁÖ÷où'ÎTTû0#\\t#4:8eUJåÖÓ°bÃ·Uöo`IX]¤ý¶Ö¹eD'|¨MÖ¹|.[Uß²\Õ÷²å\\fÐCò^4| CoàøJÔìéAýÕù"K~GTºRÆn´³8©vÄÅ;Øig åy<"ìÕ²È]õÅEW%cCò(`é<DØÑm°@&w®r¹­Êî Ø§ýöË@ëèÆè¡«ö|¹4Wqfñ¬8+<`çOiÉ¢,~cå¤r\\tîjÓ%wÛ¾(kÂ«©he@v=m ÉV ~_}.!¸wjf£ySï].[Ä8ïî9»ò:¿î¦þ×!ÍÖ[ßä¿'õj|½±Ü8ªÑæ78IÍFÞ,+\\n]=^zh"8}XU§gÙ\\f~ÅÈ^ðTE$½i²}»¢À<úUù·\\f¹]aEçDL¥$DË¥Ç¨jo:H5õT¥ÙL\\tÅðÜ6Q7hV­3ÑòÅÛÈ<\\r·ÞF¥}Ð^B\¯7$rÿÞ©¾*Î\\nî)j³Ú1qGí}÷>µ¨0tk!àý}¼~\\r  ÌgV¸]ÈThc_Ý·í4+u úroN·Ô¿?'&; Kq;rÅáµã­ýôÍK.FlNùI'9¦º¼Îi¡m©ñÑ\\fQ2Ì¾¼¯WÜ¤8`ÌYä¨I@¢U©ÒóÏÜ¼å¯{ #hìPÎ¯7úPÂúr:o¹8«>r-gÀJ\\t:ø£Û¨¸ïJ\\bzþâ¯ÞS¢àdé´äætl¤Ig¹äòg[-§6ßaH«8Ã·µu]^6 5·aoD4û;7µêÁOS$©È/üÛÔ»ßfÉOÔà`ÛúÝg7=sòå*GiHJ¡ßÂå¾Ð²5úä¡èeV:% DFêÄÂÖ²nÙK¼+!1·/îq´Ëº\\n§ì|§>¸ÚCî7ìÓ^êò¥ýÖ?rxg¦ð°/9ôðÆÌ\\b¿OD¥PÓNC k\\n°á¼àÔ÷D\]h4_H,WV~ôhÚI¹³-Ù`~÷sF´\\tÀl(ÍÝ«ª)Ò0Æ\\t¦[#Ç ÛÂx¶êëñ{ï^DYÌNdîð$@Aãý]Pý%:±õr\\f+o?r,³`ÚÞÞ¨äUK+½R¼F¹ë!T!¾eëfrh1KR\\f²C8¸Kz \\tõ`=¯Y\0»äÆYÖdÄ.~\\nä6!£34ó~äÖ³ï{*Ïu­rêðQbòÔ2\`Ä/íúàªå%©U_"m\\tUsIþ®·bOêP·²RÑG¥-R}ÁnOxÖ\\b«"¨Þ¥-­s) ÎôBø­Tq^Å g©\\fÜ¯4Èrp@e:iì-ò_±|ýOäÙg/Ô÷2ð%ÒÑý¥¡Ì;½±Ç¬l¯Ã´¦I¤%KrëöpÿJüúMú\\fª\\b_@eê\\rþ¤§yH$üý!½Õ}\\n2BæÀÐÓÿ}á\\t¨[d!."¯B{\\fÓåÈN4³¦¨òáÜêÒ%¡¦XUNz¼ÀçÝUç°/¹ãÖO{ÓÎsÁb;TaÎ°EE[Í,oÎH\\bª¯xâpÊðX?ÑæQ$ÚÑ¢lÅ\\rJ½:cßî¦X9áY¤TàÉ¨-ùB5Y½¡eìÎ,}þ¶>'é»?U£ßEöÀfåÒóïø4½ÇV$Ø.ºlH«ÍY^9Q§õ8{¢õÅÐ!|sfÅp;Ølñ4¶¼\\b@d ¤Í@=uKf{0;!·twXÙ¯^y\µóTÌøIvHð¬ß­|TË\\t¼O¢®®y¿f!riú×ÆÓ9k¥ºÍX&YtàãLzGô²ôGw¸ØÉ\)\\f£à¯}áÑDÇ¹ÝïÌdo®;XìnåC6Îð-½d¦Ðëdî{qÜsØx²²ÝQÁÏ j/Nô~ñ/u¿8ªÝ¡§í÷ÿI­,l*ürïYÿAWÆ½BYÂ³ß?*yDo«\\fäÇxCn}g¸k6c¯\\bâØWb*5ËeÄð[c4ÄÊÝ\\n=©!$¡¹ÇäñcÚPí[6¾0öý²Vb\GªX¯_©5{¤Z\\t¿gðU(ö÷î\æÓÑº´chH4LÓ¨ÑÃ5Ûñì\\n¾T´¯-=$Î):IDøR\u\\b<p_Óù÷ÿtÔfjgbdxh´×5{Ê\\nMÑí°qÔ(²/\\rsS(cÖÆØ¦²ÝU_*2)\\rZg%uâg\b»}^°nóuêâæ LøU[ï8NêÅºW÷ºÎÕ\\nÅýÊÑQk[VÐ7#§³Î£.ãMµçÛüMdQ{<Y¥UÉÖØÛpMiºj¶GL;\!pT´½[zÂß-±ÄÙº\\fÙØÚÅ\\náº;®É÷DúïÆµÿê8_ .71~F¡j69Á6ÛkQ¦Aóý±JÁmxzæÆ¥0I.Uµô½h&Ï*ý/4¤°÷Ê5&ÙMTÆÿ¿uû JÚù.L,DÁ\\ns7¶×Ð\\bV<Íô\\nT¨!Î3-H^µÓtÔ`>EãÑ×Ýk\V ~&%ÓÜüBI¯ä¤\\nj¦Ã÷:~âýG¨±¯è°L4ðcÃåtõ+·Ljú|Ä¶ÓQ¡íwÍªwÅ9LûÁOájyø\\n^C?^òÍîäæ3¼@þjª\\bé¯ô#ÜíÏÔ~}8BîE!\ý[\1XÊ0Êï¡«E«DÝ¤,¿õ\\tiD!þlº|Å4HêXJÕÔ£H"@4¨¾jÛ¯[v8©¦*ú!³#aõ»)aÙç¦Y;mùH÷v(ú×ë,ª(KåüÞ÷XÓÜ¸\\baMùD1¡f¿4´Èå¦EÿîrÛ$9ãO÷³"NdÄsl{péóªÕaëµâÂYuÝý?S]¿KãäÖp"øzÐSjE¥ì¦ ß×3ÛxK5BVø£¡ýV¼>~¿ÿ\\bEº¶Ç6z-æÓjØ.ËÍ vñH­¤´ÝeZH.^D¦Ãæãð¦,ó7CLh/áB¡PÖFH§}n×\\rw·:ÑItõé~l§¦ß¯+ù,¦¡ÝH´|0Ò­V¼Á¸ÆQ´~<ÿ­}6?¢zVí&¥a»ú¶dp'vè[z.Hãê>óAVrOEW8PPÂ\@úbÖ§Ó>¬8Yd$Èhwê¾Y©Ç#ýG+H²á.§á7{QÃd#¿ÀsoÎIà¡+õo \\rê´¥UÞ1ñüý£Ò¨E*[)tðÔÞrå¶Òb¦ÔÃN¸âát×îÞ.}tU1:øg2æLÿ×ÄC æ¡F´\\fÿMÎã*óJQe¦¨}ôÕçÍðØÇãïÑ§ä§HÉ»e`¯{\\nÉÖÉ¥cñÏÀ#¨á]Ìbß±zPyÙNðJÃ¤¢¶U^!^ë%QIÅ ¤Md>½Ü~ÞY²\_9SÉwÎ[cºÝ@ÁUØTña<4ºµÉ8ÕYÿrÔÜÃÔÝMPH««\\b#÷cû´ÃTlk| \\f¿}qµ©$»¢y4¤\¾áëöFçv±à\\nëLeØ©ÝGW}ÌC8ùb>4»\àæ¿}2¨t PÒ°À¥1î×vÊÒ\\r½YÎr-°òí²Öý(ÎåQ\\fÝú-D­Qx"X÷R,ØÙ@ä?|ÝX¾jUð­pÐà2òË[qWs<Ü=Ö ã/kG6kòHÜ]ÊÌHêhÚ¢^×,ú¡ Æ0ù=!,x²4±B+WàáÝýæ\;+¸<sa¶²¨mf$×K[\×ø$Ë\¢#6:\uÊ ÅÑÒfÅï£Û§cË@f\\bpN|K´-2À&ÇZ{jVËá>fÑÉNÄøo÷h"¯ºÅrmi;i`¸?¨ûSÃäð#J{DÏÚä©ß]ÙìKðCÆúkû×i'~¥hÝÀ`ÙÄy²CÃ¬\\bTÁî¹sAzæ{Íj{÷±E RÅÐÞ9tÎÒÃ-Ñð9¡ôDé¨ÇWlñ%+¡s62<²Ñ¡Øæw6Åø·ØA·³¦æd¸by'>/ô&N&uqZãfâæeREEÓ?ò:Ëð©¼êô~r\ÒÛóháÝ}%\\nA¼õ8M·ð­6ÓT1¨ÿ¶éþ4D¾üóàXpG£µnºZ'-¤©y@ÑÐ³Q#¿K$÷yRsÔ6 Ý\\r<÷Z°ÇràyLbG<`¥>E?ä oÚp%@°vC~tøIÚB?\\fFxoûQSJyÂéû¹ýÜÁº6ÈºxÍöÁã=g:nÈ²iT¿b~3$X;/:\\txZô:5\\bÂ@èïøGÎâ·Â@Ìn+4N-«{µo÷¿ ;ãÆ8ª¤Ì¦Ãþªõ!@cÊXmyü?rºD[2E}7P±÷;Jòü0Rn3[òÚêæýñMÑíå:'Î¸ÊÑ¡n:p+Úgs@VÝ8zø~D}ÚLÄÐ=«\\b¿Ü9èÜßøòît4«\\f,ÙÔW5xi^ÕH]NÖ©`Pö?Ëz-}*n³C``\\fEEÍ GrP\\nØàÃâÙó\\hl£4U8}6y\\t¶S(fÞ© ¦jTÛrï©\\rÎ\\tD¥\tY]ýßÚH\\f$FzÂìRåÁd?Ò"$Ùá~i;RñqËo ß+(Ý;ÈÄ"µÂ«uGÙHDD×v;êÁÙC¶®VMbtH¯/ñÏ\\fÚ,¶Ì^³¼ÕäÆÑÑÁë>9øá\\rjT& \\tÒóX_å½V)·ìÁ+ûÝøl{Ü²\\ræÂ\\reé|Ðg·ÞK³ÁlÉY2§W3+ÐÇÓe-|Æ·hÅeÝ:ûöß=ôAFËX6`ªæØv\\rBQÙ­\\täÓ·?/Óª:®7rv¥QÿO(úÖ:¨°áR­Lð´ö:íücójÓN¯>Oÿ¿sßÂáÁIÀØcFjÊ\\n¶Nóµ¨¼ÔwÄ¬uÜD ûÝ|miõ[úÌs5;0Ê@¡þDE¯¬pÆÀYø+f@AÖlìêoPeNUy½.#K{»ØA$ò}\\tHÇ'ÔfÛ@Ø#ÍÐÐÝa¶!2§GùPzÂÝm2âþX¢fz Hªð¾ïâ¡!#nh-Ä4e!mµÅ}E­H§y÷Ô\\t÷û|}\\fSãÔp;N@\\t$ç«(J<-Û­KFÒ÷õ­±^ºV\\rÉ§ê`uh.¨üûtïB¶F÷þ1dõ2Fg~hì´®çòË: °wþàu\\b% .\\nFgóÆËSÝü[#p¹)óL[[¶sÿÑÁúaO¡\\nFñNsCå8AìsþÓx³rDTOf\\n7ÝjCJÞk¤È¹e1óõ2ìw+ò¸ÕSñÜÊ¨É\}xl:ü\\bkìÃî'a\\tÿ@Ì¢ìùâ~iÍÅ±ýûe9GN¤tèÌ8ñQZÉlk[¦Ì%ÍPËÈÂ%`¬#Ð\\nÓñ~Z\\rwMTX0Ë6ûU¡/5CÓá&iª?Zg¥Ð#¼¡ÃHÅLï­Eß|Ë¤ÃÌ&Y«½Á:@®¦ØDê8ýá¦Þgd"Aj]^äþy¬­1èn»S¦±äbwFöpéýèÛMØPHªdÃÖrcÌà©â9oóÚ#D0Ð#X3\\nb°r7ªfb¤D;Jk)aÚ(7ÞÍLyQW ßUÖ»­WØ-v±*ü¡Wïåãèî[ëjP3|l'^1|\\rSAË-ø¾?m#ûäViPÍæK$úl-\üËtélÄðtHäé]C4Ø?!ªÜMu6V5Ç¡óq=<xÝ§èåõSê ^K¿ÏõÉ.Òåd¯ëbßUÙ/øúç]ÞÇº¤ôCUï(ÍêjÆù¸à¥·WÃþééÓ@"»&UôJÈKSÛ¤7@U¬Æ5Z»1;ªêÍ4Ñ\\r«õçpyÿ}z¡ØDÂ¥|qüÙ?³F=H!)Ïpp1^·dj>ÙÛ[.´ä`ólaoh\\bYqW¼³Hÿ)ý»ßf«É¼^#'µMóÜn.n34ºàòôç\\rUBJ3zÜÁkfhx.)ýAË%ÿîùU?;Z0ö?4Mh5´nÂ)_Ü¯¤ð»}á¥MD¢þ}cléüÐÇýëu¡³¦k¨k^¢F(¡Z;@Ðu=T~ÙêÅ#qb¹IXý©öPòt5ÔûÂ¾eãN®Gòûz¨g-òNªYnCI×½z6ÚåÞ¯ô]úÄ­¢©W\\fPgWßàÏ¢· ÿªU¸-<+YØÐWM­WW2I½o~[Îq :Qóîÿ:^|ßÎ·¸Ál´#¹æÚINÌ[1ÆzûH]6Õ¾(kðH­\\f©"û9\\fDbãwb|Uo³ÙJgåÙ(YÌÎ³6ðd»®e4Ê«(RõßQÚÓËá0Åßû->¿Îõ] ¯ã AªsäÙpþ\¢úyÓ[À?Å\\rKA_G/uñ{9ßôÈ£Ð+´$kL=Íñ|=eïä~`ùlÛíçê¯LaùÐ*®ç@ ÆÞ<uÁCÜcHáfb­îVz,°}øö"T½ÒÈ+cÈfuD»¶Ìõ|kâÐÍV!±ùDécÄ³ª½Þº4H¬,tJñHVxX<Ë_}{ÿ!Q8¤©öá+m;::Ö5éøY¥%ËnLÃ1`_²zÛY!MÔÂÿP sÅ8Ï$n½©Z~mãªg7ó¯<Ð-´1ú¥¦¾À7}Rº"èYàÿøìé-U(\\rÔ!bpÿ?öDIÍ,XÏ`´Çl ­ÿ?êBÈBXX¸'µf²WTpPC:Ç©÷²ØÓFLÄî?n½ðqÕ_Cæ-e§üKoFlSÇizK`O:¥éã<LÞ,¶i·Z÷%JVôßfF¨ÊÏP_õ\\fæ<_?ÊÛP²»Ã½~åh¨Ð6ÄQp©¥[o(ð=EàÙâ8P N2pRh#z©+q °~õ%Þãðä¡Ê>\\nÆÿD\2ó 6ÐD³£ºÂ\È!:rU£~u- ¼ímK_Ö"NOÆ&#Ba±$¬OéÔØUÛ,\\b é».ÌïØ Ó<ÓunóZ³9òêr½ðí¥ÉD÷ªtËüS#¯ òê7p]â Û²>û¢ÊÇÁ'
    //   130: dup
    //   131: astore_2
    //   132: invokevirtual length : ()I
    //   135: istore #4
    //   137: bipush #32
    //   139: istore_1
    //   140: iconst_m1
    //   141: istore_0
    //   142: bipush #89
    //   144: iinc #0, 1
    //   147: aload_2
    //   148: iload_0
    //   149: dup
    //   150: iload_1
    //   151: iadd
    //   152: invokevirtual substring : (II)Ljava/lang/String;
    //   155: iconst_1
    //   156: goto -> 203
    //   159: aload #5
    //   161: swap
    //   162: iload_3
    //   163: iinc #3, 1
    //   166: swap
    //   167: aastore
    //   168: iload_0
    //   169: iload_1
    //   170: iadd
    //   171: dup
    //   172: istore_0
    //   173: iload #4
    //   175: if_icmpge -> 187
    //   178: aload_2
    //   179: iload_0
    //   180: invokevirtual charAt : (I)C
    //   183: istore_1
    //   184: goto -> 142
    //   187: aload #5
    //   189: putstatic burp/Zzlk.a : [Ljava/lang/String;
    //   192: bipush #10
    //   194: anewarray java/lang/String
    //   197: putstatic burp/Zzlk.b : [Ljava/lang/String;
    //   200: goto -> 364
    //   203: dup_x2
    //   204: pop
    //   205: invokevirtual toCharArray : ()[C
    //   208: dup_x1
    //   209: arraylength
    //   210: dup_x2
    //   211: pop
    //   212: iconst_0
    //   213: istore #6
    //   215: dup2_x1
    //   216: pop2
    //   217: dup_x2
    //   218: iconst_1
    //   219: if_icmpgt -> 320
    //   222: dup2
    //   223: swap
    //   224: iload #6
    //   226: dup2_x1
    //   227: caload
    //   228: swap
    //   229: iload #6
    //   231: bipush #7
    //   233: irem
    //   234: tableswitch default -> 302, 0 -> 272, 1 -> 277, 2 -> 282, 3 -> 287, 4 -> 292, 5 -> 297
    //   272: bipush #117
    //   274: goto -> 304
    //   277: bipush #75
    //   279: goto -> 304
    //   282: bipush #117
    //   284: goto -> 304
    //   287: bipush #84
    //   289: goto -> 304
    //   292: bipush #80
    //   294: goto -> 304
    //   297: bipush #107
    //   299: goto -> 304
    //   302: bipush #10
    //   304: ixor
    //   305: ixor
    //   306: i2c
    //   307: castore
    //   308: iinc #6, 1
    //   311: dup
    //   312: ifne -> 320
    //   315: dup2
    //   316: dup_x1
    //   317: goto -> 226
    //   320: dup2_x1
    //   321: pop2
    //   322: dup_x2
    //   323: iload #6
    //   325: if_icmpgt -> 222
    //   328: pop
    //   329: new java/lang/String
    //   332: dup_x1
    //   333: swap
    //   334: invokespecial <init> : ([C)V
    //   337: invokevirtual intern : ()Ljava/lang/String;
    //   340: swap
    //   341: pop
    //   342: swap
    //   343: tableswitch default -> 40, 0 -> 100, 1 -> 159
    //   364: sipush #-9135
    //   367: sipush #-27937
    //   370: invokestatic a : (II)Ljava/lang/String;
    //   373: putstatic burp/Zzlk.ZN : Ljava/lang/String;
    //   376: getstatic burp/Zzlk.ZN : Ljava/lang/String;
    //   379: sipush #-9122
    //   382: sipush #-14107
    //   385: invokestatic a : (II)Ljava/lang/String;
    //   388: <illegal opcode> makeConcatWithConstants : (Ljava/lang/String;Ljava/lang/String;)Ljava/lang/String;
    //   393: putstatic burp/Zzlk.ZN : Ljava/lang/String;
    //   396: new java/math/BigInteger
    //   399: dup
    //   400: sipush #-9130
    //   403: sipush #-27373
    //   406: invokestatic a : (II)Ljava/lang/String;
    //   409: invokespecial <init> : (Ljava/lang/String;)V
    //   412: putstatic burp/Zzlk.ZA : Ljava/lang/Object;
    //   415: return
  }
  
  private static Throwable a(Throwable paramThrowable) {
    return paramThrowable;
  }
  
  private static String a(int paramInt1, int paramInt2) {
    int i = (paramInt1 ^ 0xFFFFDC57) & 0xFFFF;
    if (b[i] == null) {
      char[] arrayOfChar = a[i].toCharArray();
      switch (arrayOfChar[0] & 0xFF) {
        case 0:
        
        case 1:
        
        case 2:
        
        case 3:
        
        case 4:
        
        case 5:
        
        case 6:
        
        case 7:
        
        case 8:
        
        case 9:
        
        case 10:
        
        case 11:
        
        case 12:
        
        case 13:
        
        case 14:
        
        case 15:
        
        case 16:
        
        case 17:
        
        case 18:
        
        case 19:
        
        case 20:
        
        case 21:
        
        case 22:
        
        case 23:
        
        case 24:
        
        case 25:
        
        case 26:
        
        case 27:
        
        case 28:
        
        case 29:
        
        case 30:
        
        case 31:
        
        case 32:
        
        case 33:
        
        case 34:
        
        case 35:
        
        case 36:
        
        case 37:
        
        case 38:
        
        case 39:
        
        case 40:
        
        case 41:
        
        case 42:
        
        case 43:
        
        case 44:
        
        case 45:
        
        case 46:
        
        case 47:
        
        case 48:
        
        case 49:
        
        case 50:
        
        case 51:
        
        case 52:
        
        case 53:
        
        case 54:
        
        case 55:
        
        case 56:
        
        case 57:
        
        case 58:
        
        case 59:
        
        case 60:
        
        case 61:
        
        case 62:
        
        case 63:
        
        case 64:
        
        case 65:
        
        case 66:
        
        case 67:
        
        case 68:
        
        case 69:
        
        case 70:
        
        case 71:
        
        case 72:
        
        case 73:
        
        case 74:
        
        case 75:
        
        case 76:
        
        case 77:
        
        case 78:
        
        case 79:
        
        case 80:
        
        case 81:
        
        case 82:
        
        case 83:
        
        case 84:
        
        case 85:
        
        case 86:
        
        case 87:
        
        case 88:
        
        case 89:
        
        case 90:
        
        case 91:
        
        case 92:
        
        case 93:
        
        case 94:
        
        case 95:
        
        case 96:
        
        case 97:
        
        case 98:
        
        case 99:
        
        case 100:
        
        case 101:
        
        case 102:
        
        case 103:
        
        case 104:
        
        case 105:
        
        case 106:
        
        case 107:
        
        case 108:
        
        case 109:
        
        case 110:
        
        case 111:
        
        case 112:
        
        case 113:
        
        case 114:
        
        case 115:
        
        case 116:
        
        case 117:
        
        case 118:
        
        case 119:
        
        case 120:
        
        case 121:
        
        case 122:
        
        case 123:
        
        case 124:
        
        case 125:
        
        case 126:
        
        case 127:
        
        case 128:
        
        case 129:
        
        case 130:
        
        case 131:
        
        case 132:
        
        case 133:
        
        case 134:
        
        case 135:
        
        case 136:
        
        case 137:
        
        case 138:
        
        case 139:
        
        case 140:
        
        case 141:
        
        case 142:
        
        case 143:
        
        case 144:
        
        case 145:
        
        case 146:
        
        case 147:
        
        case 148:
        
        case 149:
        
        case 150:
        
        case 151:
        
        case 152:
        
        case 153:
        
        case 154:
        
        case 155:
        
        case 156:
        
        case 157:
        
        case 158:
        
        case 159:
        
        case 160:
        
        case 161:
        
        case 162:
        
        case 163:
        
        case 164:
        
        case 165:
        
        case 166:
        
        case 167:
        
        case 168:
        
        case 169:
        
        case 170:
        
        case 171:
        
        case 172:
        
        case 173:
        
        case 174:
        
        case 175:
        
        case 176:
        
        case 177:
        
        case 178:
        
        case 179:
        
        case 180:
        
        case 181:
        
        case 182:
        
        case 183:
        
        case 184:
        
        case 185:
        
        case 186:
        
        case 187:
        
        case 188:
        
        case 189:
        
        case 190:
        
        case 191:
        
        case 192:
        
        case 193:
        
        case 194:
        
        case 195:
        
        case 196:
        
        case 197:
        
        case 198:
        
        case 199:
        
        case 200:
        
        case 201:
        
        case 202:
        
        case 203:
        
        case 204:
        
        case 205:
        
        case 206:
        
        case 207:
        
        case 208:
        
        case 209:
        
        case 210:
        
        case 211:
        
        case 212:
        
        case 213:
        
        case 214:
        
        case 215:
        
        case 216:
        
        case 217:
        
        case 218:
        
        case 219:
        
        case 220:
        
        case 221:
        
        case 222:
        
        case 223:
        
        case 224:
        
        case 225:
        
        case 226:
        
        case 227:
        
        case 228:
        
        case 229:
        
        case 230:
        
        case 231:
        
        case 232:
        
        case 233:
        
        case 234:
        
        case 235:
        
        case 236:
        
        case 237:
        
        case 238:
        
        case 239:
        
        case 240:
        
        case 241:
        
        case 242:
        
        case 243:
        
        case 244:
        
        case 245:
        
        case 246:
        
        case 247:
        
        case 248:
        
        case 249:
        
        case 250:
        
        case 251:
        
        case 252:
        
        case 253:
        
        case 254:
        
        default:
          break;
      } 
      byte b1 = 74;
      int j = (paramInt2 & 0xFF) - b1;
      if (j < 0)
        j += 256; 
      int k = ((paramInt2 & 0xFFFF) >>> 8) - b1;
      if (k < 0)
        k += 256; 
      for (byte b2 = 0; b2 < arrayOfChar.length; b2++) {
        int m = b2 % 2;
        if (m == 0) {
          arrayOfChar[b2] = (char)(arrayOfChar[b2] ^ j);
          j = ((j >>> 3 | j << 5) ^ arrayOfChar[b2]) & 0xFF;
        } else {
          arrayOfChar[b2] = (char)(arrayOfChar[b2] ^ k);
          k = ((k >>> 3 | k << 5) ^ arrayOfChar[b2]) & 0xFF;
        } 
      } 
      b[i] = (new String(arrayOfChar)).intern();
    } 
    return b[i];
  }
}


/* Location:              C:\Program Files\BurpSuitePro\burpsuite_pro.jar!\burp\Zzlk.class
 * Java compiler version: 21 (65.0)
 * JD-Core Version:       1.1.3
 */