package burp;

import java.awt.Window;
import java.io.File;
import java.io.IOException;
import java.io.OutputStream;
import java.io.Writer;
import net.portswigger.Zl0;

public class Zzq9 implements Runnable {
  private final Zll9[] Zm;
  
  private final Window ZG;
  
  private final Zskh Zs;
  
  private final OutputStream ZJ;
  
  private File Ze;
  
  private Zl0 ZS;
  
  private final boolean ZN;
  
  private final Zbnt Zo;
  
  private static final String[] a;
  
  private static final String[] b;
  
  public Zzq9(Zll9[] paramArrayOfZll9, Window paramWindow, Zskh paramZskh, File paramFile, boolean paramBoolean, Zbnt paramZbnt, Zl0 paramZl0) {
    this(paramArrayOfZll9, paramWindow, paramZskh, null, paramBoolean, paramZbnt);
    this.Ze = paramFile;
    this.ZS = paramZl0;
  }
  
  Zzq9(Zll9[] paramArrayOfZll9, Window paramWindow, Zskh paramZskh, OutputStream paramOutputStream, boolean paramBoolean, Zbnt paramZbnt) {
    this.Zm = paramArrayOfZll9;
    this.ZG = paramWindow;
    this.Zs = paramZskh;
    this.ZJ = paramOutputStream;
    this.ZN = paramBoolean;
    this.Zo = paramZbnt;
  }
  
  public void run() {
    // Byte code:
    //   0: invokestatic ZK : ()[I
    //   3: astore_1
    //   4: aload_0
    //   5: getfield ZJ : Ljava/io/OutputStream;
    //   8: ifnonnull -> 29
    //   11: aload_0
    //   12: getfield ZS : Lnet/portswigger/Zl0;
    //   15: aload_0
    //   16: getfield Ze : Ljava/io/File;
    //   19: invokeinterface ZT : (Ljava/io/File;)Ljava/io/OutputStreamWriter;
    //   24: astore_2
    //   25: aload_1
    //   26: ifnonnull -> 41
    //   29: new java/io/OutputStreamWriter
    //   32: dup
    //   33: aload_0
    //   34: getfield ZJ : Ljava/io/OutputStream;
    //   37: invokespecial <init> : (Ljava/io/OutputStream;)V
    //   40: astore_2
    //   41: aload_0
    //   42: aload_2
    //   43: aload_0
    //   44: getfield Zm : [Lburp/Zll9;
    //   47: invokevirtual Zp : (Ljava/io/Writer;[Lburp/Zll9;)V
    //   50: aload_2
    //   51: invokevirtual flush : ()V
    //   54: aload_2
    //   55: invokevirtual close : ()V
    //   58: aload_0
    //   59: getfield ZG : Ljava/awt/Window;
    //   62: aload_0
    //   63: getfield Zm : [Lburp/Zll9;
    //   66: arraylength
    //   67: iconst_1
    //   68: if_icmpne -> 87
    //   71: sipush #17965
    //   74: sipush #29215
    //   77: invokestatic a : (II)Ljava/lang/String;
    //   80: goto -> 96
    //   83: invokestatic a : (Ljava/io/IOException;)Ljava/io/IOException;
    //   86: athrow
    //   87: sipush #17966
    //   90: sipush #3803
    //   93: invokestatic a : (II)Ljava/lang/String;
    //   96: sipush #17947
    //   99: sipush #-18901
    //   102: invokestatic a : (II)Ljava/lang/String;
    //   105: swap
    //   106: <illegal opcode> makeConcatWithConstants : (Ljava/lang/String;Ljava/lang/String;)Ljava/lang/String;
    //   111: aload_0
    //   112: getfield Ze : Ljava/io/File;
    //   115: ifnull -> 147
    //   118: aload_0
    //   119: getfield Ze : Ljava/io/File;
    //   122: invokevirtual getPath : ()Ljava/lang/String;
    //   125: sipush #17976
    //   128: sipush #20192
    //   131: invokestatic a : (II)Ljava/lang/String;
    //   134: swap
    //   135: <illegal opcode> makeConcatWithConstants : (Ljava/lang/String;Ljava/lang/String;)Ljava/lang/String;
    //   140: goto -> 149
    //   143: invokestatic a : (Ljava/io/IOException;)Ljava/io/IOException;
    //   146: athrow
    //   147: ldc ''
    //   149: sipush #17952
    //   152: sipush #18688
    //   155: invokestatic a : (II)Ljava/lang/String;
    //   158: swap
    //   159: <illegal opcode> makeConcatWithConstants : (Ljava/lang/String;Ljava/lang/String;)Ljava/lang/String;
    //   164: invokestatic Zf : (Ljava/awt/Component;Ljava/lang/String;Ljava/lang/Object;)V
    //   167: goto -> 248
    //   170: astore_2
    //   171: aload_2
    //   172: getstatic net/portswigger/Zk_.COMMON_RUNTIME_FAILURE : Lnet/portswigger/Zk_;
    //   175: invokestatic Zl : (Ljava/lang/Throwable;Lnet/portswigger/Zk_;)V
    //   178: aload_0
    //   179: getfield Zs : Lburp/Zskh;
    //   182: getstatic burp/Zkqn.ERROR : Lburp/Zkqn;
    //   185: aload_0
    //   186: getfield Zm : [Lburp/Zll9;
    //   189: arraylength
    //   190: iconst_1
    //   191: if_icmpne -> 210
    //   194: sipush #17983
    //   197: sipush #-12634
    //   200: invokestatic a : (II)Ljava/lang/String;
    //   203: goto -> 219
    //   206: invokestatic a : (Ljava/io/IOException;)Ljava/io/IOException;
    //   209: athrow
    //   210: sipush #17940
    //   213: sipush #15804
    //   216: invokestatic a : (II)Ljava/lang/String;
    //   219: aload_2
    //   220: invokevirtual getMessage : ()Ljava/lang/String;
    //   223: astore_3
    //   224: astore #4
    //   226: sipush #17971
    //   229: sipush #5096
    //   232: invokestatic a : (II)Ljava/lang/String;
    //   235: aload #4
    //   237: aload_3
    //   238: <illegal opcode> makeConcatWithConstants : (Ljava/lang/String;Ljava/lang/String;Ljava/lang/String;)Ljava/lang/String;
    //   243: invokeinterface Zl : (Lburp/Zkqn;Ljava/lang/String;)V
    //   248: return
    // Exception table:
    //   from	to	target	type
    //   4	167	170	java/io/IOException
    //   41	83	83	java/io/IOException
    //   96	143	143	java/io/IOException
    //   171	206	206	java/io/IOException
  }
  
  private void Zp(Writer paramWriter, Zll9[] paramArrayOfZll9) throws IOException {
    // Byte code:
    //   0: invokestatic ZK : ()[I
    //   3: astore_3
    //   4: aload_1
    //   5: aload_0
    //   6: getfield ZN : Z
    //   9: ifeq -> 28
    //   12: sipush #17938
    //   15: sipush #-30810
    //   18: invokestatic a : (II)Ljava/lang/String;
    //   21: goto -> 37
    //   24: invokestatic a : (Ljava/io/IOException;)Ljava/io/IOException;
    //   27: athrow
    //   28: sipush #17978
    //   31: sipush #29975
    //   34: invokestatic a : (II)Ljava/lang/String;
    //   37: new java/util/Date
    //   40: dup
    //   41: invokespecial <init> : ()V
    //   44: invokevirtual toString : ()Ljava/lang/String;
    //   47: sipush #17982
    //   50: sipush #2448
    //   53: invokestatic a : (II)Ljava/lang/String;
    //   56: swap
    //   57: sipush #17963
    //   60: sipush #-2142
    //   63: invokestatic a : (II)Ljava/lang/String;
    //   66: <illegal opcode> makeConcatWithConstants : (Ljava/lang/String;Ljava/lang/String;Ljava/lang/String;Ljava/lang/String;)Ljava/lang/String;
    //   71: invokevirtual write : (Ljava/lang/String;)V
    //   74: aload_2
    //   75: astore #4
    //   77: aload #4
    //   79: arraylength
    //   80: istore #5
    //   82: iconst_0
    //   83: istore #6
    //   85: iload #6
    //   87: iload #5
    //   89: if_icmpge -> 986
    //   92: aload #4
    //   94: iload #6
    //   96: aaload
    //   97: astore #7
    //   99: aload #7
    //   101: invokeinterface Zos : ()Lburp/Zstu;
    //   106: astore #8
    //   108: aload #8
    //   110: ifnonnull -> 117
    //   113: aload_3
    //   114: ifnonnull -> 979
    //   117: aload #7
    //   119: invokeinterface Zod : ()Lburp/Zmzk;
    //   124: aload #8
    //   126: iconst_1
    //   127: aload_0
    //   128: getfield Zo : Lburp/Zbnt;
    //   131: invokestatic ZY : (Lburp/Zmzk;Lburp/Zstu;BLburp/Zbnt;)Lburp/Zz1p;
    //   134: astore #9
    //   136: aload #7
    //   138: invokeinterface ZoO : ()Lburp/Zstu;
    //   143: astore #10
    //   145: aconst_null
    //   146: astore #11
    //   148: aload #10
    //   150: ifnull -> 169
    //   153: aload #9
    //   155: aload #10
    //   157: getstatic burp/Zt0k.NO_HTML_ANALYSIS : Lburp/Zt0k;
    //   160: aload_0
    //   161: getfield Zo : Lburp/Zbnt;
    //   164: invokestatic ZS : (Lburp/Zz1p;Lburp/Zstu;Lburp/Zt0k;Lburp/Zbnt;)Lburp/Zs68;
    //   167: astore #11
    //   169: aload_1
    //   170: sipush #17946
    //   173: sipush #30926
    //   176: invokestatic a : (II)Ljava/lang/String;
    //   179: invokevirtual write : (Ljava/lang/String;)V
    //   182: aload_1
    //   183: new java/util/Date
    //   186: dup
    //   187: aload #7
    //   189: invokeinterface ZoB : ()J
    //   194: invokespecial <init> : (J)V
    //   197: invokevirtual toString : ()Ljava/lang/String;
    //   200: sipush #17953
    //   203: sipush #13927
    //   206: invokestatic a : (II)Ljava/lang/String;
    //   209: swap
    //   210: sipush #17955
    //   213: sipush #23876
    //   216: invokestatic a : (II)Ljava/lang/String;
    //   219: <illegal opcode> makeConcatWithConstants : (Ljava/lang/String;Ljava/lang/String;Ljava/lang/String;)Ljava/lang/String;
    //   224: invokevirtual write : (Ljava/lang/String;)V
    //   227: aload_1
    //   228: sipush #17975
    //   231: sipush #6836
    //   234: invokestatic a : (II)Ljava/lang/String;
    //   237: sipush #17981
    //   240: sipush #13418
    //   243: invokestatic a : (II)Ljava/lang/String;
    //   246: aconst_null
    //   247: aload #7
    //   249: invokeinterface ZlL : ()Lburp/Zlit;
    //   254: invokeinterface toString : ()Ljava/lang/String;
    //   259: invokestatic ZB : (Ljava/io/Writer;Ljava/lang/String;Ljava/lang/String;Ljava/lang/String;Ljava/lang/String;)V
    //   262: aload_1
    //   263: aload #7
    //   265: invokeinterface Zod : ()Lburp/Zmzk;
    //   270: invokeinterface ZJE : ()Ljava/lang/String;
    //   275: aload #7
    //   277: invokeinterface Zod : ()Lburp/Zmzk;
    //   282: invokeinterface ZJ1 : ()Ljava/lang/String;
    //   287: sipush #17962
    //   290: sipush #-8352
    //   293: invokestatic a : (II)Ljava/lang/String;
    //   296: dup_x2
    //   297: pop
    //   298: sipush #17964
    //   301: sipush #11416
    //   304: invokestatic a : (II)Ljava/lang/String;
    //   307: swap
    //   308: sipush #17969
    //   311: sipush #-19559
    //   314: invokestatic a : (II)Ljava/lang/String;
    //   317: <illegal opcode> makeConcatWithConstants : (Ljava/lang/String;Ljava/lang/String;Ljava/lang/String;Ljava/lang/String;Ljava/lang/String;)Ljava/lang/String;
    //   322: invokevirtual write : (Ljava/lang/String;)V
    //   325: aload_1
    //   326: aload #7
    //   328: invokeinterface Zod : ()Lburp/Zmzk;
    //   333: invokeinterface ZJO : ()I
    //   338: sipush #17936
    //   341: sipush #-22447
    //   344: invokestatic a : (II)Ljava/lang/String;
    //   347: swap
    //   348: sipush #17937
    //   351: sipush #-7981
    //   354: invokestatic a : (II)Ljava/lang/String;
    //   357: <illegal opcode> makeConcatWithConstants : (Ljava/lang/String;ILjava/lang/String;)Ljava/lang/String;
    //   362: invokevirtual write : (Ljava/lang/String;)V
    //   365: aload_1
    //   366: aload #7
    //   368: invokeinterface ZlL : ()Lburp/Zlit;
    //   373: invokeinterface Zdq : ()Ljava/lang/String;
    //   378: sipush #17942
    //   381: sipush #-12177
    //   384: invokestatic a : (II)Ljava/lang/String;
    //   387: swap
    //   388: sipush #17951
    //   391: sipush #13704
    //   394: invokestatic a : (II)Ljava/lang/String;
    //   397: <illegal opcode> makeConcatWithConstants : (Ljava/lang/String;Ljava/lang/String;Ljava/lang/String;)Ljava/lang/String;
    //   402: invokevirtual write : (Ljava/lang/String;)V
    //   405: aload_1
    //   406: sipush #17956
    //   409: sipush #12711
    //   412: invokestatic a : (II)Ljava/lang/String;
    //   415: sipush #17950
    //   418: sipush #-12943
    //   421: invokestatic a : (II)Ljava/lang/String;
    //   424: aconst_null
    //   425: aload #9
    //   427: ifnonnull -> 439
    //   430: ldc ''
    //   432: goto -> 444
    //   435: invokestatic a : (Ljava/io/IOException;)Ljava/io/IOException;
    //   438: athrow
    //   439: aload #9
    //   441: getfield Zb : Ljava/lang/String;
    //   444: invokestatic ZB : (Ljava/io/Writer;Ljava/lang/String;Ljava/lang/String;Ljava/lang/String;Ljava/lang/String;)V
    //   447: aload_1
    //   448: sipush #17956
    //   451: sipush #12711
    //   454: invokestatic a : (II)Ljava/lang/String;
    //   457: sipush #17943
    //   460: sipush #18047
    //   463: invokestatic a : (II)Ljava/lang/String;
    //   466: aconst_null
    //   467: aload #7
    //   469: invokeinterface ZlL : ()Lburp/Zlit;
    //   474: invokeinterface ZdH : ()[B
    //   479: invokestatic ZQ : (Ljava/io/Writer;Ljava/lang/String;Ljava/lang/String;Ljava/lang/String;[B)V
    //   482: aload_1
    //   483: aload #7
    //   485: invokeinterface ZlL : ()Lburp/Zlit;
    //   490: invokeinterface Zd_ : ()Ljava/lang/String;
    //   495: sipush #17972
    //   498: sipush #-9112
    //   501: invokestatic a : (II)Ljava/lang/String;
    //   504: swap
    //   505: sipush #17967
    //   508: sipush #-29511
    //   511: invokestatic a : (II)Ljava/lang/String;
    //   514: <illegal opcode> makeConcatWithConstants : (Ljava/lang/String;Ljava/lang/String;Ljava/lang/String;)Ljava/lang/String;
    //   519: invokevirtual write : (Ljava/lang/String;)V
    //   522: aload_0
    //   523: getfield ZN : Z
    //   526: ifeq -> 581
    //   529: aload_1
    //   530: sipush #17956
    //   533: sipush #12711
    //   536: invokestatic a : (II)Ljava/lang/String;
    //   539: sipush #17954
    //   542: sipush #-4732
    //   545: invokestatic a : (II)Ljava/lang/String;
    //   548: sipush #17974
    //   551: sipush #-3433
    //   554: invokestatic a : (II)Ljava/lang/String;
    //   557: aload #8
    //   559: invokeinterface ZiD : ()[B
    //   564: invokestatic ZZ : ([B)[B
    //   567: invokestatic ZQ : (Ljava/io/Writer;Ljava/lang/String;Ljava/lang/String;Ljava/lang/String;[B)V
    //   570: aload_3
    //   571: ifnonnull -> 626
    //   574: goto -> 581
    //   577: invokestatic a : (Ljava/io/IOException;)Ljava/io/IOException;
    //   580: athrow
    //   581: aload_1
    //   582: sipush #17956
    //   585: sipush #12711
    //   588: invokestatic a : (II)Ljava/lang/String;
    //   591: sipush #17949
    //   594: sipush #12603
    //   597: invokestatic a : (II)Ljava/lang/String;
    //   600: sipush #17970
    //   603: sipush #-364
    //   606: invokestatic a : (II)Ljava/lang/String;
    //   609: aload #8
    //   611: invokeinterface ZiD : ()[B
    //   616: invokestatic ZQ : (Ljava/io/Writer;Ljava/lang/String;Ljava/lang/String;Ljava/lang/String;[B)V
    //   619: goto -> 626
    //   622: invokestatic a : (Ljava/io/IOException;)Ljava/io/IOException;
    //   625: athrow
    //   626: aload_1
    //   627: aload #7
    //   629: invokeinterface Zl7 : ()S
    //   634: ifne -> 646
    //   637: ldc ''
    //   639: goto -> 656
    //   642: invokestatic a : (Ljava/io/IOException;)Ljava/io/IOException;
    //   645: athrow
    //   646: aload #7
    //   648: invokeinterface Zl7 : ()S
    //   653: invokestatic toString : (S)Ljava/lang/String;
    //   656: sipush #17941
    //   659: sipush #-28774
    //   662: invokestatic a : (II)Ljava/lang/String;
    //   665: swap
    //   666: sipush #17977
    //   669: sipush #-4144
    //   672: invokestatic a : (II)Ljava/lang/String;
    //   675: <illegal opcode> makeConcatWithConstants : (Ljava/lang/String;Ljava/lang/String;Ljava/lang/String;)Ljava/lang/String;
    //   680: invokevirtual write : (Ljava/lang/String;)V
    //   683: aload_1
    //   684: aload #7
    //   686: invokeinterface Zlq : ()I
    //   691: ifne -> 703
    //   694: ldc ''
    //   696: goto -> 713
    //   699: invokestatic a : (Ljava/io/IOException;)Ljava/io/IOException;
    //   702: athrow
    //   703: aload #7
    //   705: invokeinterface Zlq : ()I
    //   710: invokestatic toString : (I)Ljava/lang/String;
    //   713: sipush #17980
    //   716: sipush #13645
    //   719: invokestatic a : (II)Ljava/lang/String;
    //   722: swap
    //   723: sipush #17973
    //   726: sipush #-30993
    //   729: invokestatic a : (II)Ljava/lang/String;
    //   732: <illegal opcode> makeConcatWithConstants : (Ljava/lang/String;Ljava/lang/String;Ljava/lang/String;)Ljava/lang/String;
    //   737: invokevirtual write : (Ljava/lang/String;)V
    //   740: aload_1
    //   741: aload #11
    //   743: ifnonnull -> 755
    //   746: ldc ''
    //   748: goto -> 766
    //   751: invokestatic a : (Ljava/io/IOException;)Ljava/io/IOException;
    //   754: athrow
    //   755: aload #11
    //   757: getfield ZH : Lburp/Zk8m;
    //   760: getfield Zj : S
    //   763: invokestatic Zz : (S)Ljava/lang/String;
    //   766: sipush #17957
    //   769: sipush #-30384
    //   772: invokestatic a : (II)Ljava/lang/String;
    //   775: swap
    //   776: sipush #17961
    //   779: sipush #6440
    //   782: invokestatic a : (II)Ljava/lang/String;
    //   785: <illegal opcode> makeConcatWithConstants : (Ljava/lang/String;Ljava/lang/String;Ljava/lang/String;)Ljava/lang/String;
    //   790: invokevirtual write : (Ljava/lang/String;)V
    //   793: aload #10
    //   795: ifnonnull -> 806
    //   798: getstatic net/portswigger/Zdo.ZQ : [B
    //   801: invokestatic Zy : ([B)Lburp/Zyf;
    //   804: astore #10
    //   806: aload_0
    //   807: getfield ZN : Z
    //   810: ifeq -> 865
    //   813: aload_1
    //   814: sipush #17956
    //   817: sipush #12711
    //   820: invokestatic a : (II)Ljava/lang/String;
    //   823: sipush #17948
    //   826: sipush #-30297
    //   829: invokestatic a : (II)Ljava/lang/String;
    //   832: sipush #17979
    //   835: sipush #2556
    //   838: invokestatic a : (II)Ljava/lang/String;
    //   841: aload #10
    //   843: invokeinterface ZiD : ()[B
    //   848: invokestatic ZZ : ([B)[B
    //   851: invokestatic ZQ : (Ljava/io/Writer;Ljava/lang/String;Ljava/lang/String;Ljava/lang/String;[B)V
    //   854: aload_3
    //   855: ifnonnull -> 910
    //   858: goto -> 865
    //   861: invokestatic a : (Ljava/io/IOException;)Ljava/io/IOException;
    //   864: athrow
    //   865: aload_1
    //   866: sipush #17956
    //   869: sipush #12711
    //   872: invokestatic a : (II)Ljava/lang/String;
    //   875: sipush #17958
    //   878: sipush #-17856
    //   881: invokestatic a : (II)Ljava/lang/String;
    //   884: sipush #17959
    //   887: sipush #26513
    //   890: invokestatic a : (II)Ljava/lang/String;
    //   893: aload #10
    //   895: invokeinterface ZiD : ()[B
    //   900: invokestatic ZQ : (Ljava/io/Writer;Ljava/lang/String;Ljava/lang/String;Ljava/lang/String;[B)V
    //   903: goto -> 910
    //   906: invokestatic a : (Ljava/io/IOException;)Ljava/io/IOException;
    //   909: athrow
    //   910: aload_1
    //   911: sipush #17956
    //   914: sipush #12711
    //   917: invokestatic a : (II)Ljava/lang/String;
    //   920: sipush #17960
    //   923: sipush #-28809
    //   926: invokestatic a : (II)Ljava/lang/String;
    //   929: aconst_null
    //   930: aload #7
    //   932: invokeinterface ZIx : ()Ljava/lang/String;
    //   937: invokestatic ZB : (Ljava/io/Writer;Ljava/lang/String;Ljava/lang/String;Ljava/lang/String;Ljava/lang/String;)V
    //   940: aload_1
    //   941: sipush #17968
    //   944: sipush #17333
    //   947: invokestatic a : (II)Ljava/lang/String;
    //   950: invokevirtual write : (Ljava/lang/String;)V
    //   953: goto -> 979
    //   956: astore #8
    //   958: aload #8
    //   960: getstatic net/portswigger/Zk_.COMMON_RUNTIME_FAILURE : Lnet/portswigger/Zk_;
    //   963: invokestatic Zl : (Ljava/lang/Throwable;Lnet/portswigger/Zk_;)V
    //   966: aload #8
    //   968: athrow
    //   969: astore #8
    //   971: aload #8
    //   973: getstatic net/portswigger/Zk_.UNEXPECTED : Lnet/portswigger/Zk_;
    //   976: invokestatic Zl : (Ljava/lang/Throwable;Lnet/portswigger/Zk_;)V
    //   979: iinc #6, 1
    //   982: aload_3
    //   983: ifnonnull -> 85
    //   986: aload_1
    //   987: sipush #17939
    //   990: sipush #-6567
    //   993: invokestatic a : (II)Ljava/lang/String;
    //   996: invokevirtual write : (Ljava/lang/String;)V
    //   999: return
    // Exception table:
    //   from	to	target	type
    //   4	24	24	java/io/IOException
    //   99	113	956	java/io/IOException
    //   99	113	969	java/lang/Exception
    //   117	953	956	java/io/IOException
    //   117	953	969	java/lang/Exception
    //   169	435	435	java/io/IOException
    //   444	574	577	java/io/IOException
    //   529	619	622	java/io/IOException
    //   626	642	642	java/io/IOException
    //   656	699	699	java/io/IOException
    //   713	751	751	java/io/IOException
    //   806	858	861	java/io/IOException
    //   813	903	906	java/io/IOException
  }
  
  private static IOException a(IOException paramIOException) {
    return paramIOException;
  }
  
  static {
    // Byte code:
    //   0: bipush #46
    //   2: anewarray java/lang/String
    //   5: astore #5
    //   7: iconst_0
    //   8: istore_3
    //   9: ldc 'oÃ±~Â\\rÂ­;Ã«PÂ•83Â€Ã¥;qÂ‹Ã´4Ã€ÂÃƒÃµÂ¢&Â˜Â¸BÃ‘Ã‚iÂ”JyÂÂ¼v_bÂO\\fÂ·Ã¦#q\\rgCÃ¤ÂŸFDxÃœ\\r(Ã“Â²Ã¬Ã¯ÂŠqÃ®Ã†Ã¯YhÂ»oÃ|{\\t-`Ã¡\\rÂ¾BÂ®Ã»iÂ£Â¢Ã›ÃÂœÂœ\\rÃ‰Ã¶Â“Ã„Ã²Ã¿Â«ÍÃ¡TÂÂ‘Â¿]Â©F\\fÂ–Ã©yÂ´Ã¾qÃ¦Â»3WYÃ†gÂ¤ZJÂŒÃŒÂ’6MÃ¢ÂÂ’4Qp<NÃ¯Â­Ã‰KÃ–Ã‡Ã¶ÃR{F'Â‰Â¬1Â‹RÃ¤.^8t}!GÃ£Ã8OxÂ6FjÂ3Ã½Ã§Â¼Â‘bÂ›Ã‹Ã¾>QÃ”Ã®Â®Âµ~? )Ã®Ã–:Ã›ClÃxÃ~ÃšÃ€Ã—rÂ¤Â·ÃÃ´ÃŸÂªÂ¾n#Ã²jsÃ¿&Â¾ÂŒÃ—ÃœÂ†Ãk]%ÃÃ©R~ÃÃ¨ÂÃ²sÂ½Â |Â¤S<\\bÂ‚$Â˜Â»Â•Â›Ã‹Ã¿kÂÂªÃ§5){dÂµÂŒÃ»ÃÂŠ\\fÃ®SÂµÂ¢Â¹FÃ¤Â•J\\fÃ²Ã½Â”Â—HÃªÂ§Ã Â¶<eÃŠXÂ±ÂÃ±ÂŠÂ Ã»kÂª7Â…Ã–?Â™Â—ÂŒLÃ¥Ã»mÂ®iÂ«aÃŸ\\nVÂ¹xÃ¡Ã¤Ã»ÃÂŸUÂÃ´Â¯Â¬XÂŒ@\ÃªrÂ Ã‰?N^\\nÃ¥BÂ‚82Â0rÃ¯_ÂrÂ­vÂ·Ã‚w[Â‡Â†ÃŒMÃ\\tr.ÂŒgr4 lÂ¤Ã«Â‡DnHhnÂˆXÃ¾+Ã I Â–BdÂ—P@h  Ã‘Â¸Ã„ÂšOÂµÃ— Â­ ÃŠÃ´&Â­Ã†Â”>5Ã¥'Ã®M[4LÂŠÂ´PÃŒeVcÂ­Ã© Ã’$eÂ¨ÂÂªTÃ£MÂ v)Ã£3hÃµÂ·@{ÃŸÂ‰Ã…Â§Ã¯Ã°Â‚\\b"HÃ½Â¥Ã§ÃƒÃ§Â”Â…Â¢Â±ÂŸhPÃ¤}^Â¼Â˜TÂ†aÃ“EÂ—Â”oÃ…VhÃºÂŠÃ¢Ã˜Â‰.UVÃ‚1W%Ã¥(ÃŸG\\nYÂ¼qJÂ“>Ã‹WÂƒÃ Ã¯0NÃœjr\Â¯Ã°Â¡Ã“Ã·nÃ²L]Ã F USÂºHÂŠÂ¡Â¼Â±Dk^Ã“|Â™Ã•Â  ÃªÂÂŠWo|ÂºÂ‹(p]ÃÂ´ÃµÂ¨MÃ¿Â%(\\nÂ¸;Ã›Ã·Â¢n_XbJ,ÂºÂ±mM>o^Ã«I\\fÃ²ÂºÂ»ÂÃbVÃ¦Ã¶\\rÂ–vÃ¨ZZuÂÃ¤ÂÃ”Ã¾Â¢Ã©Â»Ã§Ã·E;ÃÂ¦ÂÂ‚Â‘ÂŸUv?!Ã‡Ã”_%Â­qÂ…Ã¶ÂªÃ³#Â”8ÃÃÃÂÂ“Â°Ã¥Ã—ZÂ•0%Ã˜Â¨Â¨ÂµÂ½xÂŒÃªJÃ±Ã„? Â¶Ã•Ã® ÂŒÃ‚ÂŠ19Ã(Â¸\\nÂ›"1ÂºÃ„Â®eÂqLY0Ã¨("Â›COÃNÃ²Ã—HÃ®ÂšgÂ­abÃŠrÃÃ½\Â¾Ã“eÃÂ’u\\niÂº0Â±8Â·SÂ€Ã‰Ã¹(Ã~*pÃÃ–Âµ[ÂµCiÃ¯EzÃµÃÂ¶Ã­ÂŒÃ»Ã²8Â¢Â®ÃªoÂ¬ÂÃŒÂ—]ÂŒM_ÂªÃÃ’#uÂ‰\\r|Ã˜Â›ÃŒ$ÂŠ2ÂJ2J/Â¤Ã™\\tlÂš]cÂ²Â³!fÂ8FAÃšÂªN"4x:Ã­Ã¯Â­gÃ“=AÃÃ•ÃÂ”Ã¯Â½wÂ‹ Ã¾Ã¿ÂšÂ»HÃŠLÃ¿ Â¨oÃ˜ÃŒJkÂ¬Â…^Â­GÂ¬Ã¡Ã¬Ã†Â¹]^U%\\fÂ„ÃƒÂ“Ã«Ã’Ã±}3JÃ’,Â‰ÂŒÂ‡Â¨ÂƒbÂ¡\\r|EÃÃÂ£ÂÃ·Â˜3Ã¿Å fÃ»Â˜nÂœ8Ã»WÃœÃ‡jrÂƒÃÂ²Ã”ÃÂ§0Ã­"Â€Ã‡`Â¼KÃ§Â±?mÂÂ¹oÃ’3Â’\\fÂ˜Â´sÂ€3Â’Â‡:Â³lÂ·Â§<ÂºÃ®Ã¢Ã¥Â¶Â±3Ã­ÃŠ0XÂZ6JopÂ˜ Ã¡Â‹f"Â²Â’Â˜*nÃÂªÂ¤ÃºdÂ?1Â˜Ã•Ã…[Â»ÃµÃÃ¼ÂƒÃ˜#ÃœÃ¤Ã›tzÂ‹UÃ“hÃ¼Ã¥Â˜Â¿ÂˆÂˆ(Ã©2Ã¶cBÃ¾Ã |Ã®PÂ•WÂÂ¥M\Â¢Ã›:134Â¯Ã (ÃÃ®\\r.Â—Â’MÂÂ‹Â¦%Â»Ã•Ã¡Â´Â‘Â´Ã“QgTlShÂ¨Â´Â®:Ã€\\nÃ•Â™0Â‰Â)N2Â¸Ã´ÂµÃ•Ã¬Â¤ÃiCMr)ÃŠÃ—Ã®Â©ÂÂ©ÂPÃª^dw\\fÃ¥nÃ²(Ã EÃ“Â‰9=Â”!Ã¦Ã²4oÂŒÂÂ¨T?bÃ¬OÃÃ…rÂÃ©/+Â‹MÂ®Â«Â™Â‡ÃX6Â\Ã“Ã­Â¦!.ÂªT"<pÃ‡ÂÃ Ã¥7BB<Â—Â±Â¯ÂŸÃ™Ã²Ã¢Â¯w.Ã•\\t)Ã†[ÃšÃ¥m~ÂªRÂ¬Ã¶Â«ÃœÂ¹%FÂªÂ+\\nÂ¼Â“AÂ› \W'Ã­Â©eÃ«ÂÂ™\\bÃ«Â›Â†}Â¨ÂÂŒ@ÂA%Â²TÃœÃ•ÂRÂ«ÂÃ­=:Ã°2Ã‚Ã´YTÂ§5Â”ÃÂ‚Â°ÃÃ–\\b ÂµÃœÂ«}pÂ¡Ã™SÃÃ¹ÂºÂ³[Ã#Â˜p\\r(bÂÃŸÂ²\\tÃE`Â¯ÃÃ Ã­Â†LÂšSKÃ„Ã”Ãš\\nÂ¾DÂƒ5Â­ Ã½mÂiO!FÂŠÂ§Â€\\tÃˆwv9usÃ§xÃ•\\bÃ‘ÂªÂ™Â°Â½>\\fÃ‹Â‰3Â‡UÃyCÂ™[Â‘iÂ‰BÃÃ•,)%Â©Ã½Â¸\Â½Â¼wÃ»M\\rÂ‚Ã˜Â·(WÃ¦N8Â™Ã¡Ã¾Â¢*tXÃŒÂ›Ã‹Ã®Ã¸zÃ£ÃœÃœÃšÃ”[Â»J[?(\\fÂ€Ã¥ÂƒÃ¼ÃÂ¯UoÃ‘Â°JÂ z:Â Â…\\nÂ·kÂ³wÃƒl=bÃ(=Â©Ã³$Ã±qV~iÃ¢ÃœÂºÂ¤ _Â‡Â¶Ã¬qYÂ´\\tÃ¤ÂšÃ€RÂ€Â©Ã­Ã“'\\nÂ±ÂÂ¥Â²8,Ã¿j\\rÂ‰m>(ÂšÃ›fÂÃ”Â‰|Â£?WÃ¢Ã«Hw4X(Â¶G\\bXÃ“Â¿ÂœÃ²ÂÂ‰'
    //   11: dup
    //   12: astore_2
    //   13: invokevirtual length : ()I
    //   16: istore #4
    //   18: iconst_4
    //   19: istore_1
    //   20: iconst_m1
    //   21: istore_0
    //   22: bipush #37
    //   24: iinc #0, 1
    //   27: aload_2
    //   28: iload_0
    //   29: dup
    //   30: iload_1
    //   31: iadd
    //   32: invokevirtual substring : (II)Ljava/lang/String;
    //   35: iconst_m1
    //   36: goto -> 141
    //   39: aload #5
    //   41: swap
    //   42: iload_3
    //   43: iinc #3, 1
    //   46: swap
    //   47: aastore
    //   48: iload_0
    //   49: iload_1
    //   50: iadd
    //   51: dup
    //   52: istore_0
    //   53: iload #4
    //   55: if_icmpge -> 67
    //   58: aload_2
    //   59: iload_0
    //   60: invokevirtual charAt : (I)C
    //   63: istore_1
    //   64: goto -> 22
    //   67: ldc 'hÂ¹pÂ§\\nÂ‚zNÂ±XÃ»H~Ãˆ'
    //   69: dup
    //   70: astore_2
    //   71: invokevirtual length : ()I
    //   74: istore #4
    //   76: iconst_5
    //   77: istore_1
    //   78: iconst_m1
    //   79: istore_0
    //   80: bipush #32
    //   82: iinc #0, 1
    //   85: aload_2
    //   86: iload_0
    //   87: dup
    //   88: iload_1
    //   89: iadd
    //   90: invokevirtual substring : (II)Ljava/lang/String;
    //   93: iconst_0
    //   94: goto -> 141
    //   97: aload #5
    //   99: swap
    //   100: iload_3
    //   101: iinc #3, 1
    //   104: swap
    //   105: aastore
    //   106: iload_0
    //   107: iload_1
    //   108: iadd
    //   109: dup
    //   110: istore_0
    //   111: iload #4
    //   113: if_icmpge -> 125
    //   116: aload_2
    //   117: iload_0
    //   118: invokevirtual charAt : (I)C
    //   121: istore_1
    //   122: goto -> 80
    //   125: aload #5
    //   127: putstatic burp/Zzq9.a : [Ljava/lang/String;
    //   130: bipush #46
    //   132: anewarray java/lang/String
    //   135: putstatic burp/Zzq9.b : [Ljava/lang/String;
    //   138: goto -> 300
    //   141: dup_x2
    //   142: pop
    //   143: invokevirtual toCharArray : ()[C
    //   146: dup_x1
    //   147: arraylength
    //   148: dup_x2
    //   149: pop
    //   150: iconst_0
    //   151: istore #6
    //   153: dup2_x1
    //   154: pop2
    //   155: dup_x2
    //   156: iconst_1
    //   157: if_icmpgt -> 260
    //   160: dup2
    //   161: swap
    //   162: iload #6
    //   164: dup2_x1
    //   165: caload
    //   166: swap
    //   167: iload #6
    //   169: bipush #7
    //   171: irem
    //   172: tableswitch default -> 242, 0 -> 212, 1 -> 217, 2 -> 222, 3 -> 227, 4 -> 232, 5 -> 237
    //   212: bipush #51
    //   214: goto -> 244
    //   217: bipush #75
    //   219: goto -> 244
    //   222: bipush #112
    //   224: goto -> 244
    //   227: bipush #76
    //   229: goto -> 244
    //   232: bipush #27
    //   234: goto -> 244
    //   237: bipush #29
    //   239: goto -> 244
    //   242: bipush #29
    //   244: ixor
    //   245: ixor
    //   246: i2c
    //   247: castore
    //   248: iinc #6, 1
    //   251: dup
    //   252: ifne -> 260
    //   255: dup2
    //   256: dup_x1
    //   257: goto -> 164
    //   260: dup2_x1
    //   261: pop2
    //   262: dup_x2
    //   263: iload #6
    //   265: if_icmpgt -> 160
    //   268: pop
    //   269: new java/lang/String
    //   272: dup_x1
    //   273: swap
    //   274: invokespecial <init> : ([C)V
    //   277: invokevirtual intern : ()Ljava/lang/String;
    //   280: swap
    //   281: pop
    //   282: swap
    //   283: tableswitch default -> 39, 0 -> 97
    //   300: return
  }
  
  private static String a(int paramInt1, int paramInt2) {
    int i = (paramInt1 ^ 0x4637) & 0xFFFF;
    if (b[i] == null) {
      char[] arrayOfChar = a[i].toCharArray();
      switch (arrayOfChar[0] & 0xFF) {
        case 0:
        
        case 1:
        
        case 2:
        
        case 3:
        
        case 4:
        
        case 5:
        
        case 6:
        
        case 7:
        
        case 8:
        
        case 9:
        
        case 10:
        
        case 11:
        
        case 12:
        
        case 13:
        
        case 14:
        
        case 15:
        
        case 16:
        
        case 17:
        
        case 18:
        
        case 19:
        
        case 20:
        
        case 21:
        
        case 22:
        
        case 23:
        
        case 24:
        
        case 25:
        
        case 26:
        
        case 27:
        
        case 28:
        
        case 29:
        
        case 30:
        
        case 31:
        
        case 32:
        
        case 33:
        
        case 34:
        
        case 35:
        
        case 36:
        
        case 37:
        
        case 38:
        
        case 39:
        
        case 40:
        
        case 41:
        
        case 42:
        
        case 43:
        
        case 44:
        
        case 45:
        
        case 46:
        
        case 47:
        
        case 48:
        
        case 49:
        
        case 50:
        
        case 51:
        
        case 52:
        
        case 53:
        
        case 54:
        
        case 55:
        
        case 56:
        
        case 57:
        
        case 58:
        
        case 59:
        
        case 60:
        
        case 61:
        
        case 62:
        
        case 63:
        
        case 64:
        
        case 65:
        
        case 66:
        
        case 67:
        
        case 68:
        
        case 69:
        
        case 70:
        
        case 71:
        
        case 72:
        
        case 73:
        
        case 74:
        
        case 75:
        
        case 76:
        
        case 77:
        
        case 78:
        
        case 79:
        
        case 80:
        
        case 81:
        
        case 82:
        
        case 83:
        
        case 84:
        
        case 85:
        
        case 86:
        
        case 87:
        
        case 88:
        
        case 89:
        
        case 90:
        
        case 91:
        
        case 92:
        
        case 93:
        
        case 94:
        
        case 95:
        
        case 96:
        
        case 97:
        
        case 98:
        
        case 99:
        
        case 100:
        
        case 101:
        
        case 102:
        
        case 103:
        
        case 104:
        
        case 105:
        
        case 106:
        
        case 107:
        
        case 108:
        
        case 109:
        
        case 110:
        
        case 111:
        
        case 112:
        
        case 113:
        
        case 114:
        
        case 115:
        
        case 116:
        
        case 117:
        
        case 118:
        
        case 119:
        
        case 120:
        
        case 121:
        
        case 122:
        
        case 123:
        
        case 124:
        
        case 125:
        
        case 126:
        
        case 127:
        
        case 128:
        
        case 129:
        
        case 130:
        
        case 131:
        
        case 132:
        
        case 133:
        
        case 134:
        
        case 135:
        
        case 136:
        
        case 137:
        
        case 138:
        
        case 139:
        
        case 140:
        
        case 141:
        
        case 142:
        
        case 143:
        
        case 144:
        
        case 145:
        
        case 146:
        
        case 147:
        
        case 148:
        
        case 149:
        
        case 150:
        
        case 151:
        
        case 152:
        
        case 153:
        
        case 154:
        
        case 155:
        
        case 156:
        
        case 157:
        
        case 158:
        
        case 159:
        
        case 160:
        
        case 161:
        
        case 162:
        
        case 163:
        
        case 164:
        
        case 165:
        
        case 166:
        
        case 167:
        
        case 168:
        
        case 169:
        
        case 170:
        
        case 171:
        
        case 172:
        
        case 173:
        
        case 174:
        
        case 175:
        
        case 176:
        
        case 177:
        
        case 178:
        
        case 179:
        
        case 180:
        
        case 181:
        
        case 182:
        
        case 183:
        
        case 184:
        
        case 185:
        
        case 186:
        
        case 187:
        
        case 188:
        
        case 189:
        
        case 190:
        
        case 191:
        
        case 192:
        
        case 193:
        
        case 194:
        
        case 195:
        
        case 196:
        
        case 197:
        
        case 198:
        
        case 199:
        
        case 200:
        
        case 201:
        
        case 202:
        
        case 203:
        
        case 204:
        
        case 205:
        
        case 206:
        
        case 207:
        
        case 208:
        
        case 209:
        
        case 210:
        
        case 211:
        
        case 212:
        
        case 213:
        
        case 214:
        
        case 215:
        
        case 216:
        
        case 217:
        
        case 218:
        
        case 219:
        
        case 220:
        
        case 221:
        
        case 222:
        
        case 223:
        
        case 224:
        
        case 225:
        
        case 226:
        
        case 227:
        
        case 228:
        
        case 229:
        
        case 230:
        
        case 231:
        
        case 232:
        
        case 233:
        
        case 234:
        
        case 235:
        
        case 236:
        
        case 237:
        
        case 238:
        
        case 239:
        
        case 240:
        
        case 241:
        
        case 242:
        
        case 243:
        
        case 244:
        
        case 245:
        
        case 246:
        
        case 247:
        
        case 248:
        
        case 249:
        
        case 250:
        
        case 251:
        
        case 252:
        
        case 253:
        
        case 254:
        
        default:
          break;
      } 
      char c = 'Ã¨';
      int j = (paramInt2 & 0xFF) - c;
      if (j < 0)
        j += 256; 
      int k = ((paramInt2 & 0xFFFF) >>> 8) - c;
      if (k < 0)
        k += 256; 
      for (byte b = 0; b < arrayOfChar.length; b++) {
        int m = b % 2;
        if (m == 0) {
          arrayOfChar[b] = (char)(arrayOfChar[b] ^ j);
          j = ((j >>> 3 | j << 5) ^ arrayOfChar[b]) & 0xFF;
        } else {
          arrayOfChar[b] = (char)(arrayOfChar[b] ^ k);
          k = ((k >>> 3 | k << 5) ^ arrayOfChar[b]) & 0xFF;
        } 
      } 
      b[i] = (new String(arrayOfChar)).intern();
    } 
    return b[i];
  }
}


/* Location:              C:\Program Files\BurpSuitePro\burpsuite_pro.jar!\burp\Zzq9.class
 * Java compiler version: 21 (65.0)
 * JD-Core Version:       1.1.3
 */