package burp;

import java.math.BigInteger;

class Zzr extends ClassLoader {
  static String Zp;
  
  static Object ZZ;
  
  private static final String[] a;
  
  private static final String[] b;
  
  static boolean ZY(Object[] paramArrayOfObject, Object paramObject) throws Throwable {
    // Byte code:
    //   0: invokestatic ZN : ()Z
    //   3: istore_2
    //   4: getstatic burp/Zec_.ZN : Ljava/lang/Object;
    //   7: checkcast java/math/BigInteger
    //   10: getstatic burp/Zsgj.ZK : Ljava/lang/Object;
    //   13: checkcast java/math/BigInteger
    //   16: invokevirtual add : (Ljava/math/BigInteger;)Ljava/math/BigInteger;
    //   19: putstatic burp/Zb20.Zq : Ljava/lang/Object;
    //   22: new java/lang/StringBuilder
    //   25: dup
    //   26: invokespecial <init> : ()V
    //   29: astore_3
    //   30: iconst_0
    //   31: istore #4
    //   33: iload #4
    //   35: bipush #32
    //   37: if_icmpge -> 1371
    //   40: iload #4
    //   42: tableswitch default -> 1364, 0 -> 184, 1 -> 221, 2 -> 258, 3 -> 295, 4 -> 332, 5 -> 369, 6 -> 406, 7 -> 443, 8 -> 480, 9 -> 517, 10 -> 554, 11 -> 591, 12 -> 628, 13 -> 665, 14 -> 702, 15 -> 739, 16 -> 776, 17 -> 813, 18 -> 850, 19 -> 887, 20 -> 924, 21 -> 961, 22 -> 998, 23 -> 1035, 24 -> 1072, 25 -> 1109, 26 -> 1146, 27 -> 1183, 28 -> 1220, 29 -> 1257, 30 -> 1294, 31 -> 1331
    //   184: aload_3
    //   185: getstatic burp/Zlhm.Zx : Ljava/lang/String;
    //   188: getstatic burp/Zxpb.Zo : Ljava/lang/Object;
    //   191: checkcast java/math/BigInteger
    //   194: invokevirtual intValue : ()I
    //   197: bipush #32
    //   199: irem
    //   200: invokestatic abs : (I)I
    //   203: invokevirtual charAt : (I)C
    //   206: invokevirtual append : (C)Ljava/lang/StringBuilder;
    //   209: pop
    //   210: iload_2
    //   211: ifne -> 1364
    //   214: goto -> 221
    //   217: invokestatic a : (Ljava/lang/Throwable;)Ljava/lang/Throwable;
    //   220: athrow
    //   221: aload_3
    //   222: getstatic burp/Zmh5.Zh : Ljava/lang/String;
    //   225: getstatic burp/Zgja.ZD : Ljava/lang/Object;
    //   228: checkcast java/math/BigInteger
    //   231: invokevirtual intValue : ()I
    //   234: bipush #32
    //   236: irem
    //   237: invokestatic abs : (I)I
    //   240: invokevirtual charAt : (I)C
    //   243: invokevirtual append : (C)Ljava/lang/StringBuilder;
    //   246: pop
    //   247: iload_2
    //   248: ifne -> 1364
    //   251: goto -> 258
    //   254: invokestatic a : (Ljava/lang/Throwable;)Ljava/lang/Throwable;
    //   257: athrow
    //   258: aload_3
    //   259: getstatic burp/Zb1.Z_ : Ljava/lang/String;
    //   262: getstatic burp/Zmd.ZU : Ljava/lang/Object;
    //   265: checkcast java/math/BigInteger
    //   268: invokevirtual intValue : ()I
    //   271: bipush #32
    //   273: irem
    //   274: invokestatic abs : (I)I
    //   277: invokevirtual charAt : (I)C
    //   280: invokevirtual append : (C)Ljava/lang/StringBuilder;
    //   283: pop
    //   284: iload_2
    //   285: ifne -> 1364
    //   288: goto -> 295
    //   291: invokestatic a : (Ljava/lang/Throwable;)Ljava/lang/Throwable;
    //   294: athrow
    //   295: aload_3
    //   296: getstatic burp/Zrly.ZS : Ljava/lang/String;
    //   299: getstatic burp/Zzwl.Z_ : Ljava/lang/Object;
    //   302: checkcast java/math/BigInteger
    //   305: invokevirtual intValue : ()I
    //   308: bipush #32
    //   310: irem
    //   311: invokestatic abs : (I)I
    //   314: invokevirtual charAt : (I)C
    //   317: invokevirtual append : (C)Ljava/lang/StringBuilder;
    //   320: pop
    //   321: iload_2
    //   322: ifne -> 1364
    //   325: goto -> 332
    //   328: invokestatic a : (Ljava/lang/Throwable;)Ljava/lang/Throwable;
    //   331: athrow
    //   332: aload_3
    //   333: getstatic burp/Zl7k.ZX : Ljava/lang/String;
    //   336: getstatic burp/Zlna.ZG : Ljava/lang/Object;
    //   339: checkcast java/math/BigInteger
    //   342: invokevirtual intValue : ()I
    //   345: bipush #32
    //   347: irem
    //   348: invokestatic abs : (I)I
    //   351: invokevirtual charAt : (I)C
    //   354: invokevirtual append : (C)Ljava/lang/StringBuilder;
    //   357: pop
    //   358: iload_2
    //   359: ifne -> 1364
    //   362: goto -> 369
    //   365: invokestatic a : (Ljava/lang/Throwable;)Ljava/lang/Throwable;
    //   368: athrow
    //   369: aload_3
    //   370: getstatic burp/Zrs0.Zt : Ljava/lang/String;
    //   373: getstatic burp/Zex.ZO : Ljava/lang/Object;
    //   376: checkcast java/math/BigInteger
    //   379: invokevirtual intValue : ()I
    //   382: bipush #32
    //   384: irem
    //   385: invokestatic abs : (I)I
    //   388: invokevirtual charAt : (I)C
    //   391: invokevirtual append : (C)Ljava/lang/StringBuilder;
    //   394: pop
    //   395: iload_2
    //   396: ifne -> 1364
    //   399: goto -> 406
    //   402: invokestatic a : (Ljava/lang/Throwable;)Ljava/lang/Throwable;
    //   405: athrow
    //   406: aload_3
    //   407: getstatic burp/Zl5.ZE : Ljava/lang/String;
    //   410: getstatic burp/Zgnp.Zm : Ljava/lang/Object;
    //   413: checkcast java/math/BigInteger
    //   416: invokevirtual intValue : ()I
    //   419: bipush #32
    //   421: irem
    //   422: invokestatic abs : (I)I
    //   425: invokevirtual charAt : (I)C
    //   428: invokevirtual append : (C)Ljava/lang/StringBuilder;
    //   431: pop
    //   432: iload_2
    //   433: ifne -> 1364
    //   436: goto -> 443
    //   439: invokestatic a : (Ljava/lang/Throwable;)Ljava/lang/Throwable;
    //   442: athrow
    //   443: aload_3
    //   444: getstatic burp/Zb2p.ZV : Ljava/lang/String;
    //   447: getstatic burp/Zmlr.Zh : Ljava/lang/Object;
    //   450: checkcast java/math/BigInteger
    //   453: invokevirtual intValue : ()I
    //   456: bipush #32
    //   458: irem
    //   459: invokestatic abs : (I)I
    //   462: invokevirtual charAt : (I)C
    //   465: invokevirtual append : (C)Ljava/lang/StringBuilder;
    //   468: pop
    //   469: iload_2
    //   470: ifne -> 1364
    //   473: goto -> 480
    //   476: invokestatic a : (Ljava/lang/Throwable;)Ljava/lang/Throwable;
    //   479: athrow
    //   480: aload_3
    //   481: getstatic burp/Ztc2.Zr : Ljava/lang/String;
    //   484: getstatic burp/Zgre.ZD : Ljava/lang/Object;
    //   487: checkcast java/math/BigInteger
    //   490: invokevirtual intValue : ()I
    //   493: bipush #32
    //   495: irem
    //   496: invokestatic abs : (I)I
    //   499: invokevirtual charAt : (I)C
    //   502: invokevirtual append : (C)Ljava/lang/StringBuilder;
    //   505: pop
    //   506: iload_2
    //   507: ifne -> 1364
    //   510: goto -> 517
    //   513: invokestatic a : (Ljava/lang/Throwable;)Ljava/lang/Throwable;
    //   516: athrow
    //   517: aload_3
    //   518: getstatic burp/Ze0w.ZT : Ljava/lang/String;
    //   521: getstatic burp/Zrdo.ZK : Ljava/lang/Object;
    //   524: checkcast java/math/BigInteger
    //   527: invokevirtual intValue : ()I
    //   530: bipush #32
    //   532: irem
    //   533: invokestatic abs : (I)I
    //   536: invokevirtual charAt : (I)C
    //   539: invokevirtual append : (C)Ljava/lang/StringBuilder;
    //   542: pop
    //   543: iload_2
    //   544: ifne -> 1364
    //   547: goto -> 554
    //   550: invokestatic a : (Ljava/lang/Throwable;)Ljava/lang/Throwable;
    //   553: athrow
    //   554: aload_3
    //   555: getstatic burp/Zxdy.Zm : Ljava/lang/String;
    //   558: getstatic burp/Zttj.ZF : Ljava/lang/Object;
    //   561: checkcast java/math/BigInteger
    //   564: invokevirtual intValue : ()I
    //   567: bipush #32
    //   569: irem
    //   570: invokestatic abs : (I)I
    //   573: invokevirtual charAt : (I)C
    //   576: invokevirtual append : (C)Ljava/lang/StringBuilder;
    //   579: pop
    //   580: iload_2
    //   581: ifne -> 1364
    //   584: goto -> 591
    //   587: invokestatic a : (Ljava/lang/Throwable;)Ljava/lang/Throwable;
    //   590: athrow
    //   591: aload_3
    //   592: getstatic burp/Ze3j.ZI : Ljava/lang/String;
    //   595: getstatic burp/Zkc8.ZW : Ljava/lang/Object;
    //   598: checkcast java/math/BigInteger
    //   601: invokevirtual intValue : ()I
    //   604: bipush #32
    //   606: irem
    //   607: invokestatic abs : (I)I
    //   610: invokevirtual charAt : (I)C
    //   613: invokevirtual append : (C)Ljava/lang/StringBuilder;
    //   616: pop
    //   617: iload_2
    //   618: ifne -> 1364
    //   621: goto -> 628
    //   624: invokestatic a : (Ljava/lang/Throwable;)Ljava/lang/Throwable;
    //   627: athrow
    //   628: aload_3
    //   629: getstatic burp/Zgw7.ZN : Ljava/lang/String;
    //   632: getstatic burp/Ztes.ZX : Ljava/lang/Object;
    //   635: checkcast java/math/BigInteger
    //   638: invokevirtual intValue : ()I
    //   641: bipush #32
    //   643: irem
    //   644: invokestatic abs : (I)I
    //   647: invokevirtual charAt : (I)C
    //   650: invokevirtual append : (C)Ljava/lang/StringBuilder;
    //   653: pop
    //   654: iload_2
    //   655: ifne -> 1364
    //   658: goto -> 665
    //   661: invokestatic a : (Ljava/lang/Throwable;)Ljava/lang/Throwable;
    //   664: athrow
    //   665: aload_3
    //   666: getstatic burp/Zl55.Zp : Ljava/lang/String;
    //   669: getstatic burp/Zeqo.ZZ : Ljava/lang/Object;
    //   672: checkcast java/math/BigInteger
    //   675: invokevirtual intValue : ()I
    //   678: bipush #32
    //   680: irem
    //   681: invokestatic abs : (I)I
    //   684: invokevirtual charAt : (I)C
    //   687: invokevirtual append : (C)Ljava/lang/StringBuilder;
    //   690: pop
    //   691: iload_2
    //   692: ifne -> 1364
    //   695: goto -> 702
    //   698: invokestatic a : (Ljava/lang/Throwable;)Ljava/lang/Throwable;
    //   701: athrow
    //   702: aload_3
    //   703: getstatic burp/Zg1l.Zl : Ljava/lang/String;
    //   706: getstatic burp/Zg3m.ZK : Ljava/lang/Object;
    //   709: checkcast java/math/BigInteger
    //   712: invokevirtual intValue : ()I
    //   715: bipush #32
    //   717: irem
    //   718: invokestatic abs : (I)I
    //   721: invokevirtual charAt : (I)C
    //   724: invokevirtual append : (C)Ljava/lang/StringBuilder;
    //   727: pop
    //   728: iload_2
    //   729: ifne -> 1364
    //   732: goto -> 739
    //   735: invokestatic a : (Ljava/lang/Throwable;)Ljava/lang/Throwable;
    //   738: athrow
    //   739: aload_3
    //   740: getstatic burp/Zlo2.ZJ : Ljava/lang/String;
    //   743: getstatic burp/Zr8s.Zt : Ljava/lang/Object;
    //   746: checkcast java/math/BigInteger
    //   749: invokevirtual intValue : ()I
    //   752: bipush #32
    //   754: irem
    //   755: invokestatic abs : (I)I
    //   758: invokevirtual charAt : (I)C
    //   761: invokevirtual append : (C)Ljava/lang/StringBuilder;
    //   764: pop
    //   765: iload_2
    //   766: ifne -> 1364
    //   769: goto -> 776
    //   772: invokestatic a : (Ljava/lang/Throwable;)Ljava/lang/Throwable;
    //   775: athrow
    //   776: aload_3
    //   777: getstatic burp/Ztzw.Zi : Ljava/lang/String;
    //   780: getstatic burp/Zeu2.ZW : Ljava/lang/Object;
    //   783: checkcast java/math/BigInteger
    //   786: invokevirtual intValue : ()I
    //   789: bipush #32
    //   791: irem
    //   792: invokestatic abs : (I)I
    //   795: invokevirtual charAt : (I)C
    //   798: invokevirtual append : (C)Ljava/lang/StringBuilder;
    //   801: pop
    //   802: iload_2
    //   803: ifne -> 1364
    //   806: goto -> 813
    //   809: invokestatic a : (Ljava/lang/Throwable;)Ljava/lang/Throwable;
    //   812: athrow
    //   813: aload_3
    //   814: getstatic burp/Zgny.Zf : Ljava/lang/String;
    //   817: getstatic burp/Zkm0.ZI : Ljava/lang/Object;
    //   820: checkcast java/math/BigInteger
    //   823: invokevirtual intValue : ()I
    //   826: bipush #32
    //   828: irem
    //   829: invokestatic abs : (I)I
    //   832: invokevirtual charAt : (I)C
    //   835: invokevirtual append : (C)Ljava/lang/StringBuilder;
    //   838: pop
    //   839: iload_2
    //   840: ifne -> 1364
    //   843: goto -> 850
    //   846: invokestatic a : (Ljava/lang/Throwable;)Ljava/lang/Throwable;
    //   849: athrow
    //   850: aload_3
    //   851: getstatic burp/Zdk.Ze : Ljava/lang/String;
    //   854: getstatic burp/Zzh9.Zv : Ljava/lang/Object;
    //   857: checkcast java/math/BigInteger
    //   860: invokevirtual intValue : ()I
    //   863: bipush #32
    //   865: irem
    //   866: invokestatic abs : (I)I
    //   869: invokevirtual charAt : (I)C
    //   872: invokevirtual append : (C)Ljava/lang/StringBuilder;
    //   875: pop
    //   876: iload_2
    //   877: ifne -> 1364
    //   880: goto -> 887
    //   883: invokestatic a : (Ljava/lang/Throwable;)Ljava/lang/Throwable;
    //   886: athrow
    //   887: aload_3
    //   888: getstatic burp/Zgu4.Za : Ljava/lang/String;
    //   891: getstatic burp/Zt0t.ZL : Ljava/lang/Object;
    //   894: checkcast java/math/BigInteger
    //   897: invokevirtual intValue : ()I
    //   900: bipush #32
    //   902: irem
    //   903: invokestatic abs : (I)I
    //   906: invokevirtual charAt : (I)C
    //   909: invokevirtual append : (C)Ljava/lang/StringBuilder;
    //   912: pop
    //   913: iload_2
    //   914: ifne -> 1364
    //   917: goto -> 924
    //   920: invokestatic a : (Ljava/lang/Throwable;)Ljava/lang/Throwable;
    //   923: athrow
    //   924: aload_3
    //   925: getstatic burp/Zzmo.Zx : Ljava/lang/String;
    //   928: getstatic burp/Zb9d.Ze : Ljava/lang/Object;
    //   931: checkcast java/math/BigInteger
    //   934: invokevirtual intValue : ()I
    //   937: bipush #32
    //   939: irem
    //   940: invokestatic abs : (I)I
    //   943: invokevirtual charAt : (I)C
    //   946: invokevirtual append : (C)Ljava/lang/StringBuilder;
    //   949: pop
    //   950: iload_2
    //   951: ifne -> 1364
    //   954: goto -> 961
    //   957: invokestatic a : (Ljava/lang/Throwable;)Ljava/lang/Throwable;
    //   960: athrow
    //   961: aload_3
    //   962: getstatic burp/Zluk.ZW : Ljava/lang/String;
    //   965: getstatic burp/Zts_.ZH : Ljava/lang/Object;
    //   968: checkcast java/math/BigInteger
    //   971: invokevirtual intValue : ()I
    //   974: bipush #32
    //   976: irem
    //   977: invokestatic abs : (I)I
    //   980: invokevirtual charAt : (I)C
    //   983: invokevirtual append : (C)Ljava/lang/StringBuilder;
    //   986: pop
    //   987: iload_2
    //   988: ifne -> 1364
    //   991: goto -> 998
    //   994: invokestatic a : (Ljava/lang/Throwable;)Ljava/lang/Throwable;
    //   997: athrow
    //   998: aload_3
    //   999: getstatic burp/Zztx.Zg : Ljava/lang/String;
    //   1002: getstatic burp/Zxyu.Zp : Ljava/lang/Object;
    //   1005: checkcast java/math/BigInteger
    //   1008: invokevirtual intValue : ()I
    //   1011: bipush #32
    //   1013: irem
    //   1014: invokestatic abs : (I)I
    //   1017: invokevirtual charAt : (I)C
    //   1020: invokevirtual append : (C)Ljava/lang/StringBuilder;
    //   1023: pop
    //   1024: iload_2
    //   1025: ifne -> 1364
    //   1028: goto -> 1035
    //   1031: invokestatic a : (Ljava/lang/Throwable;)Ljava/lang/Throwable;
    //   1034: athrow
    //   1035: aload_3
    //   1036: getstatic burp/Zxf8.Zq : Ljava/lang/String;
    //   1039: getstatic burp/Zt0t.ZL : Ljava/lang/Object;
    //   1042: checkcast java/math/BigInteger
    //   1045: invokevirtual intValue : ()I
    //   1048: bipush #32
    //   1050: irem
    //   1051: invokestatic abs : (I)I
    //   1054: invokevirtual charAt : (I)C
    //   1057: invokevirtual append : (C)Ljava/lang/StringBuilder;
    //   1060: pop
    //   1061: iload_2
    //   1062: ifne -> 1364
    //   1065: goto -> 1072
    //   1068: invokestatic a : (Ljava/lang/Throwable;)Ljava/lang/Throwable;
    //   1071: athrow
    //   1072: aload_3
    //   1073: getstatic burp/Ztkc.ZU : Ljava/lang/String;
    //   1076: getstatic burp/Zm14.ZZ : Ljava/lang/Object;
    //   1079: checkcast java/math/BigInteger
    //   1082: invokevirtual intValue : ()I
    //   1085: bipush #32
    //   1087: irem
    //   1088: invokestatic abs : (I)I
    //   1091: invokevirtual charAt : (I)C
    //   1094: invokevirtual append : (C)Ljava/lang/StringBuilder;
    //   1097: pop
    //   1098: iload_2
    //   1099: ifne -> 1364
    //   1102: goto -> 1109
    //   1105: invokestatic a : (Ljava/lang/Throwable;)Ljava/lang/Throwable;
    //   1108: athrow
    //   1109: aload_3
    //   1110: getstatic burp/Zzbr.Zp : Ljava/lang/String;
    //   1113: getstatic burp/Zoa.ZI : Ljava/lang/Object;
    //   1116: checkcast java/math/BigInteger
    //   1119: invokevirtual intValue : ()I
    //   1122: bipush #32
    //   1124: irem
    //   1125: invokestatic abs : (I)I
    //   1128: invokevirtual charAt : (I)C
    //   1131: invokevirtual append : (C)Ljava/lang/StringBuilder;
    //   1134: pop
    //   1135: iload_2
    //   1136: ifne -> 1364
    //   1139: goto -> 1146
    //   1142: invokestatic a : (Ljava/lang/Throwable;)Ljava/lang/Throwable;
    //   1145: athrow
    //   1146: aload_3
    //   1147: getstatic burp/Zxf8.Zq : Ljava/lang/String;
    //   1150: getstatic burp/Zry7.ZZ : Ljava/lang/Object;
    //   1153: checkcast java/math/BigInteger
    //   1156: invokevirtual intValue : ()I
    //   1159: bipush #32
    //   1161: irem
    //   1162: invokestatic abs : (I)I
    //   1165: invokevirtual charAt : (I)C
    //   1168: invokevirtual append : (C)Ljava/lang/StringBuilder;
    //   1171: pop
    //   1172: iload_2
    //   1173: ifne -> 1364
    //   1176: goto -> 1183
    //   1179: invokestatic a : (Ljava/lang/Throwable;)Ljava/lang/Throwable;
    //   1182: athrow
    //   1183: aload_3
    //   1184: getstatic burp/Zl6z.ZL : Ljava/lang/String;
    //   1187: getstatic burp/Zl8l.ZJ : Ljava/lang/Object;
    //   1190: checkcast java/math/BigInteger
    //   1193: invokevirtual intValue : ()I
    //   1196: bipush #32
    //   1198: irem
    //   1199: invokestatic abs : (I)I
    //   1202: invokevirtual charAt : (I)C
    //   1205: invokevirtual append : (C)Ljava/lang/StringBuilder;
    //   1208: pop
    //   1209: iload_2
    //   1210: ifne -> 1364
    //   1213: goto -> 1220
    //   1216: invokestatic a : (Ljava/lang/Throwable;)Ljava/lang/Throwable;
    //   1219: athrow
    //   1220: aload_3
    //   1221: getstatic burp/Ztp.ZG : Ljava/lang/String;
    //   1224: getstatic burp/Zmuj.ZH : Ljava/lang/Object;
    //   1227: checkcast java/math/BigInteger
    //   1230: invokevirtual intValue : ()I
    //   1233: bipush #32
    //   1235: irem
    //   1236: invokestatic abs : (I)I
    //   1239: invokevirtual charAt : (I)C
    //   1242: invokevirtual append : (C)Ljava/lang/StringBuilder;
    //   1245: pop
    //   1246: iload_2
    //   1247: ifne -> 1364
    //   1250: goto -> 1257
    //   1253: invokestatic a : (Ljava/lang/Throwable;)Ljava/lang/Throwable;
    //   1256: athrow
    //   1257: aload_3
    //   1258: getstatic burp/Zgvf.ZM : Ljava/lang/String;
    //   1261: getstatic burp/Zr8h.ZH : Ljava/lang/Object;
    //   1264: checkcast java/math/BigInteger
    //   1267: invokevirtual intValue : ()I
    //   1270: bipush #32
    //   1272: irem
    //   1273: invokestatic abs : (I)I
    //   1276: invokevirtual charAt : (I)C
    //   1279: invokevirtual append : (C)Ljava/lang/StringBuilder;
    //   1282: pop
    //   1283: iload_2
    //   1284: ifne -> 1364
    //   1287: goto -> 1294
    //   1290: invokestatic a : (Ljava/lang/Throwable;)Ljava/lang/Throwable;
    //   1293: athrow
    //   1294: aload_3
    //   1295: getstatic burp/Zm7y.ZL : Ljava/lang/String;
    //   1298: getstatic burp/Zgwh.Zl : Ljava/lang/Object;
    //   1301: checkcast java/math/BigInteger
    //   1304: invokevirtual intValue : ()I
    //   1307: bipush #32
    //   1309: irem
    //   1310: invokestatic abs : (I)I
    //   1313: invokevirtual charAt : (I)C
    //   1316: invokevirtual append : (C)Ljava/lang/StringBuilder;
    //   1319: pop
    //   1320: iload_2
    //   1321: ifne -> 1364
    //   1324: goto -> 1331
    //   1327: invokestatic a : (Ljava/lang/Throwable;)Ljava/lang/Throwable;
    //   1330: athrow
    //   1331: aload_3
    //   1332: getstatic burp/Zb9k.Za : Ljava/lang/String;
    //   1335: getstatic burp/Zs6g.Zq : Ljava/lang/Object;
    //   1338: checkcast java/math/BigInteger
    //   1341: invokevirtual intValue : ()I
    //   1344: bipush #32
    //   1346: irem
    //   1347: invokestatic abs : (I)I
    //   1350: invokevirtual charAt : (I)C
    //   1353: invokevirtual append : (C)Ljava/lang/StringBuilder;
    //   1356: pop
    //   1357: goto -> 1364
    //   1360: invokestatic a : (Ljava/lang/Throwable;)Ljava/lang/Throwable;
    //   1363: athrow
    //   1364: iinc #4, 1
    //   1367: iload_2
    //   1368: ifne -> 33
    //   1371: aload_3
    //   1372: invokevirtual toString : ()Ljava/lang/String;
    //   1375: putstatic burp/Zrw7.Zo : Ljava/lang/String;
    //   1378: sipush #-3316
    //   1381: sipush #16669
    //   1384: invokestatic a : (II)Ljava/lang/String;
    //   1387: iconst_1
    //   1388: ldc burp/Zblv
    //   1390: invokevirtual getClassLoader : ()Ljava/lang/ClassLoader;
    //   1393: invokestatic forName : (Ljava/lang/String;ZLjava/lang/ClassLoader;)Ljava/lang/Class;
    //   1396: invokevirtual getDeclaredFields : ()[Ljava/lang/reflect/Field;
    //   1399: astore #4
    //   1401: aload #4
    //   1403: arraylength
    //   1404: istore #5
    //   1406: iconst_0
    //   1407: istore #6
    //   1409: iload #6
    //   1411: iload #5
    //   1413: if_icmpge -> 1551
    //   1416: aload #4
    //   1418: iload #6
    //   1420: aaload
    //   1421: astore #7
    //   1423: aload #7
    //   1425: invokevirtual getModifiers : ()I
    //   1428: invokestatic isStatic : (I)Z
    //   1431: ifne -> 1441
    //   1434: goto -> 1544
    //   1437: invokestatic a : (Ljava/lang/Throwable;)Ljava/lang/Throwable;
    //   1440: athrow
    //   1441: aload #7
    //   1443: invokevirtual getType : ()Ljava/lang/Class;
    //   1446: astore #8
    //   1448: aload #8
    //   1450: ifnull -> 1531
    //   1453: aload #8
    //   1455: invokevirtual isPrimitive : ()Z
    //   1458: ifne -> 1531
    //   1461: goto -> 1468
    //   1464: invokestatic a : (Ljava/lang/Throwable;)Ljava/lang/Throwable;
    //   1467: athrow
    //   1468: aload #8
    //   1470: invokevirtual getPackage : ()Ljava/lang/Package;
    //   1473: ifnull -> 1531
    //   1476: goto -> 1483
    //   1479: invokestatic a : (Ljava/lang/Throwable;)Ljava/lang/Throwable;
    //   1482: athrow
    //   1483: aload #8
    //   1485: invokevirtual getPackage : ()Ljava/lang/Package;
    //   1488: invokevirtual getName : ()Ljava/lang/String;
    //   1491: ifnull -> 1531
    //   1494: goto -> 1501
    //   1497: invokestatic a : (Ljava/lang/Throwable;)Ljava/lang/Throwable;
    //   1500: athrow
    //   1501: aload #8
    //   1503: invokevirtual getPackage : ()Ljava/lang/Package;
    //   1506: invokevirtual getName : ()Ljava/lang/String;
    //   1509: sipush #-3313
    //   1512: sipush #-11321
    //   1515: invokestatic a : (II)Ljava/lang/String;
    //   1518: invokevirtual startsWith : (Ljava/lang/String;)Z
    //   1521: ifne -> 1531
    //   1524: goto -> 1531
    //   1527: invokestatic a : (Ljava/lang/Throwable;)Ljava/lang/Throwable;
    //   1530: athrow
    //   1531: aload #7
    //   1533: iconst_1
    //   1534: invokevirtual setAccessible : (Z)V
    //   1537: aload #7
    //   1539: aconst_null
    //   1540: invokevirtual get : (Ljava/lang/Object;)Ljava/lang/Object;
    //   1543: pop
    //   1544: iinc #6, 1
    //   1547: iload_2
    //   1548: ifne -> 1409
    //   1551: sipush #-3314
    //   1554: sipush #27579
    //   1557: invokestatic a : (II)Ljava/lang/String;
    //   1560: invokestatic forName : (Ljava/lang/String;)Ljava/lang/Class;
    //   1563: invokevirtual getDeclaredMethods : ()[Ljava/lang/reflect/Method;
    //   1566: astore #4
    //   1568: aload #4
    //   1570: arraylength
    //   1571: istore #5
    //   1573: iconst_0
    //   1574: istore #6
    //   1576: iload #6
    //   1578: iload #5
    //   1580: if_icmpge -> 1692
    //   1583: aload #4
    //   1585: iload #6
    //   1587: aaload
    //   1588: astore #7
    //   1590: aload #7
    //   1592: invokevirtual getParameterTypes : ()[Ljava/lang/Class;
    //   1595: pop
    //   1596: aload #7
    //   1598: invokevirtual getModifiers : ()I
    //   1601: invokestatic isStatic : (I)Z
    //   1604: ifeq -> 1678
    //   1607: aload #7
    //   1609: invokevirtual getParameterTypes : ()[Ljava/lang/Class;
    //   1612: arraylength
    //   1613: iconst_2
    //   1614: if_icmpne -> 1678
    //   1617: goto -> 1624
    //   1620: invokestatic a : (Ljava/lang/Throwable;)Ljava/lang/Throwable;
    //   1623: athrow
    //   1624: aload #7
    //   1626: invokevirtual getReturnType : ()Ljava/lang/Class;
    //   1629: getstatic java/lang/Boolean.TYPE : Ljava/lang/Class;
    //   1632: if_acmpne -> 1678
    //   1635: goto -> 1642
    //   1638: invokestatic a : (Ljava/lang/Throwable;)Ljava/lang/Throwable;
    //   1641: athrow
    //   1642: aload #7
    //   1644: iconst_1
    //   1645: invokevirtual setAccessible : (Z)V
    //   1648: aload #7
    //   1650: aconst_null
    //   1651: iconst_2
    //   1652: anewarray java/lang/Object
    //   1655: dup
    //   1656: iconst_0
    //   1657: aload_0
    //   1658: aastore
    //   1659: dup
    //   1660: iconst_1
    //   1661: aload_1
    //   1662: aastore
    //   1663: invokevirtual invoke : (Ljava/lang/Object;[Ljava/lang/Object;)Ljava/lang/Object;
    //   1666: pop
    //   1667: iload_2
    //   1668: ifne -> 1692
    //   1671: goto -> 1678
    //   1674: invokestatic a : (Ljava/lang/Throwable;)Ljava/lang/Throwable;
    //   1677: athrow
    //   1678: iinc #6, 1
    //   1681: iload_2
    //   1682: ifne -> 1576
    //   1685: goto -> 1692
    //   1688: invokestatic a : (Ljava/lang/Throwable;)Ljava/lang/Throwable;
    //   1691: athrow
    //   1692: sipush #-3320
    //   1695: sipush #2310
    //   1698: invokestatic a : (II)Ljava/lang/String;
    //   1701: iconst_1
    //   1702: ldc burp/Ztte
    //   1704: invokevirtual getClassLoader : ()Ljava/lang/ClassLoader;
    //   1707: invokestatic forName : (Ljava/lang/String;ZLjava/lang/ClassLoader;)Ljava/lang/Class;
    //   1710: invokevirtual getDeclaredFields : ()[Ljava/lang/reflect/Field;
    //   1713: astore #4
    //   1715: aload #4
    //   1717: arraylength
    //   1718: istore #5
    //   1720: iconst_0
    //   1721: istore #6
    //   1723: iload #6
    //   1725: iload #5
    //   1727: if_icmpge -> 1865
    //   1730: aload #4
    //   1732: iload #6
    //   1734: aaload
    //   1735: astore #7
    //   1737: aload #7
    //   1739: invokevirtual getModifiers : ()I
    //   1742: invokestatic isStatic : (I)Z
    //   1745: ifne -> 1755
    //   1748: goto -> 1858
    //   1751: invokestatic a : (Ljava/lang/Throwable;)Ljava/lang/Throwable;
    //   1754: athrow
    //   1755: aload #7
    //   1757: invokevirtual getType : ()Ljava/lang/Class;
    //   1760: astore #8
    //   1762: aload #8
    //   1764: ifnull -> 1845
    //   1767: aload #8
    //   1769: invokevirtual isPrimitive : ()Z
    //   1772: ifne -> 1845
    //   1775: goto -> 1782
    //   1778: invokestatic a : (Ljava/lang/Throwable;)Ljava/lang/Throwable;
    //   1781: athrow
    //   1782: aload #8
    //   1784: invokevirtual getPackage : ()Ljava/lang/Package;
    //   1787: ifnull -> 1845
    //   1790: goto -> 1797
    //   1793: invokestatic a : (Ljava/lang/Throwable;)Ljava/lang/Throwable;
    //   1796: athrow
    //   1797: aload #8
    //   1799: invokevirtual getPackage : ()Ljava/lang/Package;
    //   1802: invokevirtual getName : ()Ljava/lang/String;
    //   1805: ifnull -> 1845
    //   1808: goto -> 1815
    //   1811: invokestatic a : (Ljava/lang/Throwable;)Ljava/lang/Throwable;
    //   1814: athrow
    //   1815: aload #8
    //   1817: invokevirtual getPackage : ()Ljava/lang/Package;
    //   1820: invokevirtual getName : ()Ljava/lang/String;
    //   1823: sipush #-3317
    //   1826: sipush #29326
    //   1829: invokestatic a : (II)Ljava/lang/String;
    //   1832: invokevirtual startsWith : (Ljava/lang/String;)Z
    //   1835: ifne -> 1845
    //   1838: goto -> 1845
    //   1841: invokestatic a : (Ljava/lang/Throwable;)Ljava/lang/Throwable;
    //   1844: athrow
    //   1845: aload #7
    //   1847: iconst_1
    //   1848: invokevirtual setAccessible : (Z)V
    //   1851: aload #7
    //   1853: aconst_null
    //   1854: invokevirtual get : (Ljava/lang/Object;)Ljava/lang/Object;
    //   1857: pop
    //   1858: iinc #6, 1
    //   1861: iload_2
    //   1862: ifne -> 1723
    //   1865: sipush #-3319
    //   1868: sipush #-29778
    //   1871: invokestatic a : (II)Ljava/lang/String;
    //   1874: invokestatic forName : (Ljava/lang/String;)Ljava/lang/Class;
    //   1877: invokevirtual getDeclaredMethods : ()[Ljava/lang/reflect/Method;
    //   1880: astore #4
    //   1882: aload #4
    //   1884: arraylength
    //   1885: istore #5
    //   1887: iconst_0
    //   1888: istore #6
    //   1890: iload #6
    //   1892: iload #5
    //   1894: if_icmpge -> 2027
    //   1897: aload #4
    //   1899: iload #6
    //   1901: aaload
    //   1902: astore #7
    //   1904: aload #7
    //   1906: invokevirtual getParameterTypes : ()[Ljava/lang/Class;
    //   1909: pop
    //   1910: aload #7
    //   1912: invokevirtual getModifiers : ()I
    //   1915: invokestatic isStatic : (I)Z
    //   1918: ifeq -> 2013
    //   1921: aload #7
    //   1923: invokevirtual getParameterTypes : ()[Ljava/lang/Class;
    //   1926: arraylength
    //   1927: iconst_2
    //   1928: if_icmpne -> 2013
    //   1931: goto -> 1938
    //   1934: invokestatic a : (Ljava/lang/Throwable;)Ljava/lang/Throwable;
    //   1937: athrow
    //   1938: aload #7
    //   1940: invokevirtual getReturnType : ()Ljava/lang/Class;
    //   1943: getstatic java/lang/Void.TYPE : Ljava/lang/Class;
    //   1946: invokevirtual equals : (Ljava/lang/Object;)Z
    //   1949: ifeq -> 2013
    //   1952: goto -> 1959
    //   1955: invokestatic a : (Ljava/lang/Throwable;)Ljava/lang/Throwable;
    //   1958: athrow
    //   1959: aload #7
    //   1961: iconst_1
    //   1962: invokevirtual setAccessible : (Z)V
    //   1965: aload #7
    //   1967: aconst_null
    //   1968: iconst_2
    //   1969: anewarray java/lang/Object
    //   1972: dup
    //   1973: iconst_0
    //   1974: aload_0
    //   1975: aastore
    //   1976: dup
    //   1977: iconst_1
    //   1978: aload_1
    //   1979: ifnonnull -> 1997
    //   1982: goto -> 1989
    //   1985: invokestatic a : (Ljava/lang/Throwable;)Ljava/lang/Throwable;
    //   1988: athrow
    //   1989: aload_1
    //   1990: goto -> 2004
    //   1993: invokestatic a : (Ljava/lang/Throwable;)Ljava/lang/Throwable;
    //   1996: athrow
    //   1997: aload_1
    //   1998: checkcast [B
    //   2001: invokevirtual clone : ()Ljava/lang/Object;
    //   2004: aastore
    //   2005: invokevirtual invoke : (Ljava/lang/Object;[Ljava/lang/Object;)Ljava/lang/Object;
    //   2008: pop
    //   2009: iload_2
    //   2010: ifne -> 2027
    //   2013: iinc #6, 1
    //   2016: iload_2
    //   2017: ifne -> 1890
    //   2020: goto -> 2027
    //   2023: invokestatic a : (Ljava/lang/Throwable;)Ljava/lang/Throwable;
    //   2026: athrow
    //   2027: getstatic burp/Zzi_.ZG : Ljava/lang/String;
    //   2030: getstatic burp/Zr_z.ZT : Ljava/lang/Object;
    //   2033: checkcast java/math/BigInteger
    //   2036: invokevirtual intValue : ()I
    //   2039: bipush #32
    //   2041: irem
    //   2042: invokestatic abs : (I)I
    //   2045: invokevirtual charAt : (I)C
    //   2048: getstatic burp/Zlp8.ZW : Ljava/lang/String;
    //   2051: getstatic burp/Zzhu.ZW : Ljava/lang/Object;
    //   2054: checkcast java/math/BigInteger
    //   2057: invokevirtual intValue : ()I
    //   2060: bipush #32
    //   2062: irem
    //   2063: invokestatic abs : (I)I
    //   2066: invokevirtual charAt : (I)C
    //   2069: if_icmpgt -> 2176
    //   2072: getstatic burp/Zscs.Zw : Ljava/lang/String;
    //   2075: getstatic burp/Zkco.Zg : Ljava/lang/Object;
    //   2078: checkcast java/math/BigInteger
    //   2081: invokevirtual intValue : ()I
    //   2084: bipush #32
    //   2086: irem
    //   2087: invokestatic abs : (I)I
    //   2090: invokevirtual charAt : (I)C
    //   2093: getstatic burp/Zsfj.Zg : Ljava/lang/String;
    //   2096: getstatic burp/Zmli.Zh : Ljava/lang/Object;
    //   2099: checkcast java/math/BigInteger
    //   2102: invokevirtual intValue : ()I
    //   2105: bipush #32
    //   2107: irem
    //   2108: invokestatic abs : (I)I
    //   2111: invokevirtual charAt : (I)C
    //   2114: if_icmple -> 2176
    //   2117: goto -> 2124
    //   2120: invokestatic a : (Ljava/lang/Throwable;)Ljava/lang/Throwable;
    //   2123: athrow
    //   2124: getstatic burp/Ze5f.Zt : Ljava/lang/String;
    //   2127: getstatic burp/Zs8y.ZG : Ljava/lang/Object;
    //   2130: checkcast java/math/BigInteger
    //   2133: invokevirtual intValue : ()I
    //   2136: bipush #32
    //   2138: irem
    //   2139: invokestatic abs : (I)I
    //   2142: invokevirtual charAt : (I)C
    //   2145: getstatic burp/Zeai.ZA : Ljava/lang/String;
    //   2148: getstatic burp/Zl_u.ZR : Ljava/lang/Object;
    //   2151: checkcast java/math/BigInteger
    //   2154: invokevirtual intValue : ()I
    //   2157: bipush #32
    //   2159: irem
    //   2160: invokestatic abs : (I)I
    //   2163: invokevirtual charAt : (I)C
    //   2166: if_icmple -> 2184
    //   2169: goto -> 2176
    //   2172: invokestatic a : (Ljava/lang/Throwable;)Ljava/lang/Throwable;
    //   2175: athrow
    //   2176: iconst_1
    //   2177: goto -> 2185
    //   2180: invokestatic a : (Ljava/lang/Throwable;)Ljava/lang/Throwable;
    //   2183: athrow
    //   2184: iconst_0
    //   2185: ireturn
    //   2186: astore_3
    //   2187: new java/lang/Exception
    //   2190: dup
    //   2191: aload_3
    //   2192: invokevirtual getMessage : ()Ljava/lang/String;
    //   2195: invokespecial <init> : (Ljava/lang/String;)V
    //   2198: athrow
    // Exception table:
    //   from	to	target	type
    //   4	2185	2186	java/lang/Throwable
    //   40	214	217	java/lang/Throwable
    //   184	251	254	java/lang/Throwable
    //   221	288	291	java/lang/Throwable
    //   258	325	328	java/lang/Throwable
    //   295	362	365	java/lang/Throwable
    //   332	399	402	java/lang/Throwable
    //   369	436	439	java/lang/Throwable
    //   406	473	476	java/lang/Throwable
    //   443	510	513	java/lang/Throwable
    //   480	547	550	java/lang/Throwable
    //   517	584	587	java/lang/Throwable
    //   554	621	624	java/lang/Throwable
    //   591	658	661	java/lang/Throwable
    //   628	695	698	java/lang/Throwable
    //   665	732	735	java/lang/Throwable
    //   702	769	772	java/lang/Throwable
    //   739	806	809	java/lang/Throwable
    //   776	843	846	java/lang/Throwable
    //   813	880	883	java/lang/Throwable
    //   850	917	920	java/lang/Throwable
    //   887	954	957	java/lang/Throwable
    //   924	991	994	java/lang/Throwable
    //   961	1028	1031	java/lang/Throwable
    //   998	1065	1068	java/lang/Throwable
    //   1035	1102	1105	java/lang/Throwable
    //   1072	1139	1142	java/lang/Throwable
    //   1109	1176	1179	java/lang/Throwable
    //   1146	1213	1216	java/lang/Throwable
    //   1183	1250	1253	java/lang/Throwable
    //   1220	1287	1290	java/lang/Throwable
    //   1257	1324	1327	java/lang/Throwable
    //   1294	1357	1360	java/lang/Throwable
    //   1423	1437	1437	java/lang/Throwable
    //   1448	1461	1464	java/lang/Throwable
    //   1453	1476	1479	java/lang/Throwable
    //   1468	1494	1497	java/lang/Throwable
    //   1483	1524	1527	java/lang/Throwable
    //   1590	1617	1620	java/lang/Throwable
    //   1607	1635	1638	java/lang/Throwable
    //   1624	1671	1674	java/lang/Throwable
    //   1642	1685	1688	java/lang/Throwable
    //   1737	1751	1751	java/lang/Throwable
    //   1762	1775	1778	java/lang/Throwable
    //   1767	1790	1793	java/lang/Throwable
    //   1782	1808	1811	java/lang/Throwable
    //   1797	1838	1841	java/lang/Throwable
    //   1904	1931	1934	java/lang/Throwable
    //   1921	1952	1955	java/lang/Throwable
    //   1938	1982	1985	java/lang/Throwable
    //   1959	1993	1993	java/lang/Throwable
    //   2004	2020	2023	java/lang/Throwable
    //   2027	2117	2120	java/lang/Throwable
    //   2072	2169	2172	java/lang/Throwable
    //   2124	2180	2180	java/lang/Throwable
  }
  
  static void Zm(Object paramObject) {
    Zgyk.ZB = a(-3322, 14250);
    Zgyk.ZO = new BigInteger(a(-3324, -23149));
    boolean bool = Zt2e.ZN();
    try {
      try {
        if (Ztap.Zk.charAt(Math.abs(((BigInteger)Ztod.ZP).intValue() % 32)) > Zxdh.Zj.charAt(Math.abs(((BigInteger)Zl3l.Zv).intValue() % 32))) {
          try {
            Zzbr.ZQ(Class.forName(a(-3315, -27189)));
            if (!bool)
              Zr8s.Zz(Class.forName(a(-3318, 24694))); 
          } catch (Throwable throwable) {
            throw a(null);
          } 
          return;
        } 
      } catch (Throwable throwable) {
        throw a(null);
      } 
      Zr8s.Zz(Class.forName(a(-3318, 24694)));
    } catch (Throwable throwable) {}
  }
  
  static void ZS(Object[] paramArrayOfObject, Object paramObject) throws Throwable {}
  
  static {
    // Byte code:
    //   0: bipush #11
    //   2: anewarray java/lang/String
    //   5: astore #5
    //   7: iconst_0
    //   8: istore_3
    //   9: ldc 'Â‡Ã»Â˜RsQMF\\t{Â€Ãºg/Ã\\tÃ©Ã‰UÃŠÂ™%TÂ Â¼Â˜Ã¿>\\tq$FÂ©Â¨.vÂ¾5\\tÂ‘"Zi+6Â²?\\t-KÃDÃ™Â“NÃ«Ã·Â‹Â–\MÂ±Ã¨Â„Â“eÂ®Ã«ÂšÃ„#Ã®UyÂ®ÃKÃº5dGÃ‡Ã«Ã«Ã´ Â¤ÃˆÃ¹2Ã‹Ã¥Ã„OÃ¶'O]ÃŸÂTÂ›Ã¾Â²( ÂŠjÃ¯ÂÂ‰ÃŠÃ¸YW|DJ-Â—Ã¼Ã”Ã²Â°Â«Â”"ÃªÃ¤'
    //   11: dup
    //   12: astore_2
    //   13: invokevirtual length : ()I
    //   16: istore #4
    //   18: bipush #9
    //   20: istore_1
    //   21: iconst_m1
    //   22: istore_0
    //   23: bipush #84
    //   25: iinc #0, 1
    //   28: aload_2
    //   29: iload_0
    //   30: dup
    //   31: iload_1
    //   32: iadd
    //   33: invokevirtual substring : (II)Ljava/lang/String;
    //   36: iconst_m1
    //   37: goto -> 143
    //   40: aload #5
    //   42: swap
    //   43: iload_3
    //   44: iinc #3, 1
    //   47: swap
    //   48: aastore
    //   49: iload_0
    //   50: iload_1
    //   51: iadd
    //   52: dup
    //   53: istore_0
    //   54: iload #4
    //   56: if_icmpge -> 68
    //   59: aload_2
    //   60: iload_0
    //   61: invokevirtual charAt : (I)C
    //   64: istore_1
    //   65: goto -> 23
    //   68: ldc '0Â¾Ã”ÃŸRÂ±Ã“Â¢Ã¶Ã±Ã¡Â–Â¡(ÃÃ”Ã‚Ã³Ã·Ã©,Â‹Ã½Â¢Â•Â°st" ÂžHiÃ…Âr7X\\r?uÂ§Â¨Ã°YÂµOÃ¼vzÃž\\f{Ã 1Ã¥+6&'
    //   70: dup
    //   71: astore_2
    //   72: invokevirtual length : ()I
    //   75: istore #4
    //   77: bipush #32
    //   79: istore_1
    //   80: iconst_m1
    //   81: istore_0
    //   82: bipush #114
    //   84: iinc #0, 1
    //   87: aload_2
    //   88: iload_0
    //   89: dup
    //   90: iload_1
    //   91: iadd
    //   92: invokevirtual substring : (II)Ljava/lang/String;
    //   95: iconst_0
    //   96: goto -> 143
    //   99: aload #5
    //   101: swap
    //   102: iload_3
    //   103: iinc #3, 1
    //   106: swap
    //   107: aastore
    //   108: iload_0
    //   109: iload_1
    //   110: iadd
    //   111: dup
    //   112: istore_0
    //   113: iload #4
    //   115: if_icmpge -> 127
    //   118: aload_2
    //   119: iload_0
    //   120: invokevirtual charAt : (I)C
    //   123: istore_1
    //   124: goto -> 82
    //   127: aload #5
    //   129: putstatic burp/Zzr.a : [Ljava/lang/String;
    //   132: bipush #11
    //   134: anewarray java/lang/String
    //   137: putstatic burp/Zzr.b : [Ljava/lang/String;
    //   140: goto -> 300
    //   143: dup_x2
    //   144: pop
    //   145: invokevirtual toCharArray : ()[C
    //   148: dup_x1
    //   149: arraylength
    //   150: dup_x2
    //   151: pop
    //   152: iconst_0
    //   153: istore #6
    //   155: dup2_x1
    //   156: pop2
    //   157: dup_x2
    //   158: iconst_1
    //   159: if_icmpgt -> 260
    //   162: dup2
    //   163: swap
    //   164: iload #6
    //   166: dup2_x1
    //   167: caload
    //   168: swap
    //   169: iload #6
    //   171: bipush #7
    //   173: irem
    //   174: tableswitch default -> 242, 0 -> 212, 1 -> 217, 2 -> 222, 3 -> 227, 4 -> 232, 5 -> 237
    //   212: bipush #52
    //   214: goto -> 244
    //   217: bipush #115
    //   219: goto -> 244
    //   222: bipush #108
    //   224: goto -> 244
    //   227: bipush #54
    //   229: goto -> 244
    //   232: bipush #33
    //   234: goto -> 244
    //   237: bipush #39
    //   239: goto -> 244
    //   242: bipush #30
    //   244: ixor
    //   245: ixor
    //   246: i2c
    //   247: castore
    //   248: iinc #6, 1
    //   251: dup
    //   252: ifne -> 260
    //   255: dup2
    //   256: dup_x1
    //   257: goto -> 166
    //   260: dup2_x1
    //   261: pop2
    //   262: dup_x2
    //   263: iload #6
    //   265: if_icmpgt -> 162
    //   268: pop
    //   269: new java/lang/String
    //   272: dup_x1
    //   273: swap
    //   274: invokespecial <init> : ([C)V
    //   277: invokevirtual intern : ()Ljava/lang/String;
    //   280: swap
    //   281: pop
    //   282: swap
    //   283: tableswitch default -> 40, 0 -> 99
    //   300: sipush #-3323
    //   303: sipush #15345
    //   306: invokestatic a : (II)Ljava/lang/String;
    //   309: putstatic burp/Zzr.Zp : Ljava/lang/String;
    //   312: new java/math/BigInteger
    //   315: dup
    //   316: bipush #32
    //   318: newarray byte
    //   320: dup
    //   321: iconst_0
    //   322: bipush #35
    //   324: bastore
    //   325: dup
    //   326: iconst_1
    //   327: bipush #-77
    //   329: bastore
    //   330: dup
    //   331: iconst_2
    //   332: bipush #-107
    //   334: bastore
    //   335: dup
    //   336: iconst_3
    //   337: bipush #15
    //   339: bastore
    //   340: dup
    //   341: iconst_4
    //   342: bipush #92
    //   344: bastore
    //   345: dup
    //   346: iconst_5
    //   347: bipush #87
    //   349: bastore
    //   350: dup
    //   351: bipush #6
    //   353: bipush #16
    //   355: bastore
    //   356: dup
    //   357: bipush #7
    //   359: bipush #92
    //   361: bastore
    //   362: dup
    //   363: bipush #8
    //   365: bipush #-126
    //   367: bastore
    //   368: dup
    //   369: bipush #9
    //   371: bipush #65
    //   373: bastore
    //   374: dup
    //   375: bipush #10
    //   377: iconst_0
    //   378: bastore
    //   379: dup
    //   380: bipush #11
    //   382: bipush #106
    //   384: bastore
    //   385: dup
    //   386: bipush #12
    //   388: bipush #14
    //   390: bastore
    //   391: dup
    //   392: bipush #13
    //   394: bipush #68
    //   396: bastore
    //   397: dup
    //   398: bipush #14
    //   400: bipush #74
    //   402: bastore
    //   403: dup
    //   404: bipush #15
    //   406: bipush #99
    //   408: bastore
    //   409: dup
    //   410: bipush #16
    //   412: bipush #63
    //   414: bastore
    //   415: dup
    //   416: bipush #17
    //   418: bipush #43
    //   420: bastore
    //   421: dup
    //   422: bipush #18
    //   424: bipush #6
    //   426: bastore
    //   427: dup
    //   428: bipush #19
    //   430: bipush #6
    //   432: bastore
    //   433: dup
    //   434: bipush #20
    //   436: bipush #95
    //   438: bastore
    //   439: dup
    //   440: bipush #21
    //   442: bipush #-104
    //   444: bastore
    //   445: dup
    //   446: bipush #22
    //   448: bipush #123
    //   450: bastore
    //   451: dup
    //   452: bipush #23
    //   454: bipush #-65
    //   456: bastore
    //   457: dup
    //   458: bipush #24
    //   460: bipush #77
    //   462: bastore
    //   463: dup
    //   464: bipush #25
    //   466: bipush #-91
    //   468: bastore
    //   469: dup
    //   470: bipush #26
    //   472: bipush #-116
    //   474: bastore
    //   475: dup
    //   476: bipush #27
    //   478: bipush #-8
    //   480: bastore
    //   481: dup
    //   482: bipush #28
    //   484: bipush #-81
    //   486: bastore
    //   487: dup
    //   488: bipush #29
    //   490: bipush #102
    //   492: bastore
    //   493: dup
    //   494: bipush #30
    //   496: bipush #-22
    //   498: bastore
    //   499: dup
    //   500: bipush #31
    //   502: iconst_5
    //   503: bastore
    //   504: invokespecial <init> : ([B)V
    //   507: putstatic burp/Zzr.ZZ : Ljava/lang/Object;
    //   510: return
  }
  
  private static Throwable a(Throwable paramThrowable) {
    return paramThrowable;
  }
  
  private static String a(int paramInt1, int paramInt2) {
    int i = (paramInt1 ^ 0xFFFFF30C) & 0xFFFF;
    if (b[i] == null) {
      char[] arrayOfChar = a[i].toCharArray();
      switch (arrayOfChar[0] & 0xFF) {
        case 0:
        
        case 1:
        
        case 2:
        
        case 3:
        
        case 4:
        
        case 5:
        
        case 6:
        
        case 7:
        
        case 8:
        
        case 9:
        
        case 10:
        
        case 11:
        
        case 12:
        
        case 13:
        
        case 14:
        
        case 15:
        
        case 16:
        
        case 17:
        
        case 18:
        
        case 19:
        
        case 20:
        
        case 21:
        
        case 22:
        
        case 23:
        
        case 24:
        
        case 25:
        
        case 26:
        
        case 27:
        
        case 28:
        
        case 29:
        
        case 30:
        
        case 31:
        
        case 32:
        
        case 33:
        
        case 34:
        
        case 35:
        
        case 36:
        
        case 37:
        
        case 38:
        
        case 39:
        
        case 40:
        
        case 41:
        
        case 42:
        
        case 43:
        
        case 44:
        
        case 45:
        
        case 46:
        
        case 47:
        
        case 48:
        
        case 49:
        
        case 50:
        
        case 51:
        
        case 52:
        
        case 53:
        
        case 54:
        
        case 55:
        
        case 56:
        
        case 57:
        
        case 58:
        
        case 59:
        
        case 60:
        
        case 61:
        
        case 62:
        
        case 63:
        
        case 64:
        
        case 65:
        
        case 66:
        
        case 67:
        
        case 68:
        
        case 69:
        
        case 70:
        
        case 71:
        
        case 72:
        
        case 73:
        
        case 74:
        
        case 75:
        
        case 76:
        
        case 77:
        
        case 78:
        
        case 79:
        
        case 80:
        
        case 81:
        
        case 82:
        
        case 83:
        
        case 84:
        
        case 85:
        
        case 86:
        
        case 87:
        
        case 88:
        
        case 89:
        
        case 90:
        
        case 91:
        
        case 92:
        
        case 93:
        
        case 94:
        
        case 95:
        
        case 96:
        
        case 97:
        
        case 98:
        
        case 99:
        
        case 100:
        
        case 101:
        
        case 102:
        
        case 103:
        
        case 104:
        
        case 105:
        
        case 106:
        
        case 107:
        
        case 108:
        
        case 109:
        
        case 110:
        
        case 111:
        
        case 112:
        
        case 113:
        
        case 114:
        
        case 115:
        
        case 116:
        
        case 117:
        
        case 118:
        
        case 119:
        
        case 120:
        
        case 121:
        
        case 122:
        
        case 123:
        
        case 124:
        
        case 125:
        
        case 126:
        
        case 127:
        
        case 128:
        
        case 129:
        
        case 130:
        
        case 131:
        
        case 132:
        
        case 133:
        
        case 134:
        
        case 135:
        
        case 136:
        
        case 137:
        
        case 138:
        
        case 139:
        
        case 140:
        
        case 141:
        
        case 142:
        
        case 143:
        
        case 144:
        
        case 145:
        
        case 146:
        
        case 147:
        
        case 148:
        
        case 149:
        
        case 150:
        
        case 151:
        
        case 152:
        
        case 153:
        
        case 154:
        
        case 155:
        
        case 156:
        
        case 157:
        
        case 158:
        
        case 159:
        
        case 160:
        
        case 161:
        
        case 162:
        
        case 163:
        
        case 164:
        
        case 165:
        
        case 166:
        
        case 167:
        
        case 168:
        
        case 169:
        
        case 170:
        
        case 171:
        
        case 172:
        
        case 173:
        
        case 174:
        
        case 175:
        
        case 176:
        
        case 177:
        
        case 178:
        
        case 179:
        
        case 180:
        
        case 181:
        
        case 182:
        
        case 183:
        
        case 184:
        
        case 185:
        
        case 186:
        
        case 187:
        
        case 188:
        
        case 189:
        
        case 190:
        
        case 191:
        
        case 192:
        
        case 193:
        
        case 194:
        
        case 195:
        
        case 196:
        
        case 197:
        
        case 198:
        
        case 199:
        
        case 200:
        
        case 201:
        
        case 202:
        
        case 203:
        
        case 204:
        
        case 205:
        
        case 206:
        
        case 207:
        
        case 208:
        
        case 209:
        
        case 210:
        
        case 211:
        
        case 212:
        
        case 213:
        
        case 214:
        
        case 215:
        
        case 216:
        
        case 217:
        
        case 218:
        
        case 219:
        
        case 220:
        
        case 221:
        
        case 222:
        
        case 223:
        
        case 224:
        
        case 225:
        
        case 226:
        
        case 227:
        
        case 228:
        
        case 229:
        
        case 230:
        
        case 231:
        
        case 232:
        
        case 233:
        
        case 234:
        
        case 235:
        
        case 236:
        
        case 237:
        
        case 238:
        
        case 239:
        
        case 240:
        
        case 241:
        
        case 242:
        
        case 243:
        
        case 244:
        
        case 245:
        
        case 246:
        
        case 247:
        
        case 248:
        
        case 249:
        
        case 250:
        
        case 251:
        
        case 252:
        
        case 253:
        
        case 254:
        
        default:
          break;
      } 
      byte b1 = 111;
      int j = (paramInt2 & 0xFF) - b1;
      if (j < 0)
        j += 256; 
      int k = ((paramInt2 & 0xFFFF) >>> 8) - b1;
      if (k < 0)
        k += 256; 
      for (byte b2 = 0; b2 < arrayOfChar.length; b2++) {
        int m = b2 % 2;
        if (m == 0) {
          arrayOfChar[b2] = (char)(arrayOfChar[b2] ^ j);
          j = ((j >>> 3 | j << 5) ^ arrayOfChar[b2]) & 0xFF;
        } else {
          arrayOfChar[b2] = (char)(arrayOfChar[b2] ^ k);
          k = ((k >>> 3 | k << 5) ^ arrayOfChar[b2]) & 0xFF;
        } 
      } 
      b[i] = (new String(arrayOfChar)).intern();
    } 
    return b[i];
  }
}


/* Location:              C:\Program Files\BurpSuitePro\burpsuite_pro.jar!\burp\Zzr.class
 * Java compiler version: 21 (65.0)
 * JD-Core Version:       1.1.3
 */