package burp;

import java.math.BigInteger;

class Zzrb extends ClassLoader {
  static Object Zj;
  
  static String ZA;
  
  private static final String[] a;
  
  private static final String[] b;
  
  static void Zk(Object[] paramArrayOfObject, Object paramObject) throws Throwable {}
  
  static void ZX(Object paramObject) {
    Zro5.ZY = a(30569, 14850);
    Zro5.ZT = new BigInteger(a(30564, 4954));
    boolean bool = Zt2e.ZN();
    try {
      try {
        if (Ztdx.Zl.charAt(Math.abs(((BigInteger)Zlnq.ZO).intValue() % 32)) > Zlnq.ZQ.charAt(Math.abs(((BigInteger)Zro5.ZT).intValue() % 32))) {
          try {
            Zszz.ZG(Class.forName(a(30589, 27163)));
            if (!bool)
              Zz35.ZB(Class.forName(a(30577, -29781))); 
          } catch (Throwable throwable) {
            throw a(null);
          } 
          return;
        } 
      } catch (Throwable throwable) {
        throw a(null);
      } 
      Zz35.ZB(Class.forName(a(30577, -29781)));
    } catch (Throwable throwable) {}
  }
  
  static boolean ZZ(Object[] paramArrayOfObject, Object paramObject) throws Throwable {
    // Byte code:
    //   0: invokestatic ZK : ()Z
    //   3: istore_2
    //   4: new java/lang/StringBuilder
    //   7: dup
    //   8: invokespecial <init> : ()V
    //   11: astore_3
    //   12: iconst_0
    //   13: istore #4
    //   15: iload #4
    //   17: bipush #32
    //   19: if_icmpge -> 1355
    //   22: iload #4
    //   24: tableswitch default -> 1348, 0 -> 168, 1 -> 205, 2 -> 242, 3 -> 279, 4 -> 316, 5 -> 353, 6 -> 390, 7 -> 427, 8 -> 464, 9 -> 501, 10 -> 538, 11 -> 575, 12 -> 612, 13 -> 649, 14 -> 686, 15 -> 723, 16 -> 760, 17 -> 797, 18 -> 834, 19 -> 871, 20 -> 908, 21 -> 945, 22 -> 982, 23 -> 1019, 24 -> 1056, 25 -> 1093, 26 -> 1130, 27 -> 1167, 28 -> 1204, 29 -> 1241, 30 -> 1278, 31 -> 1315
    //   168: aload_3
    //   169: getstatic burp/Zrct.ZT : Ljava/lang/String;
    //   172: getstatic burp/Zmy4.ZB : Ljava/lang/Object;
    //   175: checkcast java/math/BigInteger
    //   178: invokevirtual intValue : ()I
    //   181: bipush #32
    //   183: irem
    //   184: invokestatic abs : (I)I
    //   187: invokevirtual charAt : (I)C
    //   190: invokevirtual append : (C)Ljava/lang/StringBuilder;
    //   193: pop
    //   194: iload_2
    //   195: ifeq -> 1348
    //   198: goto -> 205
    //   201: invokestatic a : (Ljava/lang/Throwable;)Ljava/lang/Throwable;
    //   204: athrow
    //   205: aload_3
    //   206: getstatic burp/Ztbf.Zf : Ljava/lang/String;
    //   209: getstatic burp/Zrvb.ZD : Ljava/lang/Object;
    //   212: checkcast java/math/BigInteger
    //   215: invokevirtual intValue : ()I
    //   218: bipush #32
    //   220: irem
    //   221: invokestatic abs : (I)I
    //   224: invokevirtual charAt : (I)C
    //   227: invokevirtual append : (C)Ljava/lang/StringBuilder;
    //   230: pop
    //   231: iload_2
    //   232: ifeq -> 1348
    //   235: goto -> 242
    //   238: invokestatic a : (Ljava/lang/Throwable;)Ljava/lang/Throwable;
    //   241: athrow
    //   242: aload_3
    //   243: getstatic burp/Zkc5.ZH : Ljava/lang/String;
    //   246: getstatic burp/Zkig.ZK : Ljava/lang/Object;
    //   249: checkcast java/math/BigInteger
    //   252: invokevirtual intValue : ()I
    //   255: bipush #32
    //   257: irem
    //   258: invokestatic abs : (I)I
    //   261: invokevirtual charAt : (I)C
    //   264: invokevirtual append : (C)Ljava/lang/StringBuilder;
    //   267: pop
    //   268: iload_2
    //   269: ifeq -> 1348
    //   272: goto -> 279
    //   275: invokestatic a : (Ljava/lang/Throwable;)Ljava/lang/Throwable;
    //   278: athrow
    //   279: aload_3
    //   280: getstatic burp/Zza3.ZU : Ljava/lang/String;
    //   283: getstatic burp/Zsji.Zg : Ljava/lang/Object;
    //   286: checkcast java/math/BigInteger
    //   289: invokevirtual intValue : ()I
    //   292: bipush #32
    //   294: irem
    //   295: invokestatic abs : (I)I
    //   298: invokevirtual charAt : (I)C
    //   301: invokevirtual append : (C)Ljava/lang/StringBuilder;
    //   304: pop
    //   305: iload_2
    //   306: ifeq -> 1348
    //   309: goto -> 316
    //   312: invokestatic a : (Ljava/lang/Throwable;)Ljava/lang/Throwable;
    //   315: athrow
    //   316: aload_3
    //   317: getstatic burp/Zltz.Za : Ljava/lang/String;
    //   320: getstatic burp/Zr8s.Zt : Ljava/lang/Object;
    //   323: checkcast java/math/BigInteger
    //   326: invokevirtual intValue : ()I
    //   329: bipush #32
    //   331: irem
    //   332: invokestatic abs : (I)I
    //   335: invokevirtual charAt : (I)C
    //   338: invokevirtual append : (C)Ljava/lang/StringBuilder;
    //   341: pop
    //   342: iload_2
    //   343: ifeq -> 1348
    //   346: goto -> 353
    //   349: invokestatic a : (Ljava/lang/Throwable;)Ljava/lang/Throwable;
    //   352: athrow
    //   353: aload_3
    //   354: getstatic burp/Zgde.Zr : Ljava/lang/String;
    //   357: getstatic burp/Zlw8.ZA : Ljava/lang/Object;
    //   360: checkcast java/math/BigInteger
    //   363: invokevirtual intValue : ()I
    //   366: bipush #32
    //   368: irem
    //   369: invokestatic abs : (I)I
    //   372: invokevirtual charAt : (I)C
    //   375: invokevirtual append : (C)Ljava/lang/StringBuilder;
    //   378: pop
    //   379: iload_2
    //   380: ifeq -> 1348
    //   383: goto -> 390
    //   386: invokestatic a : (Ljava/lang/Throwable;)Ljava/lang/Throwable;
    //   389: athrow
    //   390: aload_3
    //   391: getstatic burp/Zt5b.ZV : Ljava/lang/String;
    //   394: getstatic burp/Zgnp.Zm : Ljava/lang/Object;
    //   397: checkcast java/math/BigInteger
    //   400: invokevirtual intValue : ()I
    //   403: bipush #32
    //   405: irem
    //   406: invokestatic abs : (I)I
    //   409: invokevirtual charAt : (I)C
    //   412: invokevirtual append : (C)Ljava/lang/StringBuilder;
    //   415: pop
    //   416: iload_2
    //   417: ifeq -> 1348
    //   420: goto -> 427
    //   423: invokestatic a : (Ljava/lang/Throwable;)Ljava/lang/Throwable;
    //   426: athrow
    //   427: aload_3
    //   428: getstatic burp/Zebj.ZF : Ljava/lang/String;
    //   431: getstatic burp/Zs5y.Zd : Ljava/lang/Object;
    //   434: checkcast java/math/BigInteger
    //   437: invokevirtual intValue : ()I
    //   440: bipush #32
    //   442: irem
    //   443: invokestatic abs : (I)I
    //   446: invokevirtual charAt : (I)C
    //   449: invokevirtual append : (C)Ljava/lang/StringBuilder;
    //   452: pop
    //   453: iload_2
    //   454: ifeq -> 1348
    //   457: goto -> 464
    //   460: invokestatic a : (Ljava/lang/Throwable;)Ljava/lang/Throwable;
    //   463: athrow
    //   464: aload_3
    //   465: getstatic burp/Ze5t.ZX : Ljava/lang/String;
    //   468: getstatic burp/Zg8v.ZB : Ljava/lang/Object;
    //   471: checkcast java/math/BigInteger
    //   474: invokevirtual intValue : ()I
    //   477: bipush #32
    //   479: irem
    //   480: invokestatic abs : (I)I
    //   483: invokevirtual charAt : (I)C
    //   486: invokevirtual append : (C)Ljava/lang/StringBuilder;
    //   489: pop
    //   490: iload_2
    //   491: ifeq -> 1348
    //   494: goto -> 501
    //   497: invokestatic a : (Ljava/lang/Throwable;)Ljava/lang/Throwable;
    //   500: athrow
    //   501: aload_3
    //   502: getstatic burp/Zlr2.ZV : Ljava/lang/String;
    //   505: getstatic burp/Zty4.ZQ : Ljava/lang/Object;
    //   508: checkcast java/math/BigInteger
    //   511: invokevirtual intValue : ()I
    //   514: bipush #32
    //   516: irem
    //   517: invokestatic abs : (I)I
    //   520: invokevirtual charAt : (I)C
    //   523: invokevirtual append : (C)Ljava/lang/StringBuilder;
    //   526: pop
    //   527: iload_2
    //   528: ifeq -> 1348
    //   531: goto -> 538
    //   534: invokestatic a : (Ljava/lang/Throwable;)Ljava/lang/Throwable;
    //   537: athrow
    //   538: aload_3
    //   539: getstatic burp/Zb3l.Zz : Ljava/lang/String;
    //   542: getstatic burp/Zlwm.Ze : Ljava/lang/Object;
    //   545: checkcast java/math/BigInteger
    //   548: invokevirtual intValue : ()I
    //   551: bipush #32
    //   553: irem
    //   554: invokestatic abs : (I)I
    //   557: invokevirtual charAt : (I)C
    //   560: invokevirtual append : (C)Ljava/lang/StringBuilder;
    //   563: pop
    //   564: iload_2
    //   565: ifeq -> 1348
    //   568: goto -> 575
    //   571: invokestatic a : (Ljava/lang/Throwable;)Ljava/lang/Throwable;
    //   574: athrow
    //   575: aload_3
    //   576: getstatic burp/Zbxp.ZS : Ljava/lang/String;
    //   579: getstatic burp/Zrct.ZV : Ljava/lang/Object;
    //   582: checkcast java/math/BigInteger
    //   585: invokevirtual intValue : ()I
    //   588: bipush #32
    //   590: irem
    //   591: invokestatic abs : (I)I
    //   594: invokevirtual charAt : (I)C
    //   597: invokevirtual append : (C)Ljava/lang/StringBuilder;
    //   600: pop
    //   601: iload_2
    //   602: ifeq -> 1348
    //   605: goto -> 612
    //   608: invokestatic a : (Ljava/lang/Throwable;)Ljava/lang/Throwable;
    //   611: athrow
    //   612: aload_3
    //   613: getstatic burp/Zg_i.ZW : Ljava/lang/String;
    //   616: getstatic burp/Zm5s.ZB : Ljava/lang/Object;
    //   619: checkcast java/math/BigInteger
    //   622: invokevirtual intValue : ()I
    //   625: bipush #32
    //   627: irem
    //   628: invokestatic abs : (I)I
    //   631: invokevirtual charAt : (I)C
    //   634: invokevirtual append : (C)Ljava/lang/StringBuilder;
    //   637: pop
    //   638: iload_2
    //   639: ifeq -> 1348
    //   642: goto -> 649
    //   645: invokestatic a : (Ljava/lang/Throwable;)Ljava/lang/Throwable;
    //   648: athrow
    //   649: aload_3
    //   650: getstatic burp/Zgzv.Zy : Ljava/lang/String;
    //   653: getstatic burp/Zlqy.ZP : Ljava/lang/Object;
    //   656: checkcast java/math/BigInteger
    //   659: invokevirtual intValue : ()I
    //   662: bipush #32
    //   664: irem
    //   665: invokestatic abs : (I)I
    //   668: invokevirtual charAt : (I)C
    //   671: invokevirtual append : (C)Ljava/lang/StringBuilder;
    //   674: pop
    //   675: iload_2
    //   676: ifeq -> 1348
    //   679: goto -> 686
    //   682: invokestatic a : (Ljava/lang/Throwable;)Ljava/lang/Throwable;
    //   685: athrow
    //   686: aload_3
    //   687: getstatic burp/Zgwu.Zd : Ljava/lang/String;
    //   690: getstatic burp/Zm8i.Zm : Ljava/lang/Object;
    //   693: checkcast java/math/BigInteger
    //   696: invokevirtual intValue : ()I
    //   699: bipush #32
    //   701: irem
    //   702: invokestatic abs : (I)I
    //   705: invokevirtual charAt : (I)C
    //   708: invokevirtual append : (C)Ljava/lang/StringBuilder;
    //   711: pop
    //   712: iload_2
    //   713: ifeq -> 1348
    //   716: goto -> 723
    //   719: invokestatic a : (Ljava/lang/Throwable;)Ljava/lang/Throwable;
    //   722: athrow
    //   723: aload_3
    //   724: getstatic burp/Ztdx.Zl : Ljava/lang/String;
    //   727: getstatic burp/Zttq.Zh : Ljava/lang/Object;
    //   730: checkcast java/math/BigInteger
    //   733: invokevirtual intValue : ()I
    //   736: bipush #32
    //   738: irem
    //   739: invokestatic abs : (I)I
    //   742: invokevirtual charAt : (I)C
    //   745: invokevirtual append : (C)Ljava/lang/StringBuilder;
    //   748: pop
    //   749: iload_2
    //   750: ifeq -> 1348
    //   753: goto -> 760
    //   756: invokestatic a : (Ljava/lang/Throwable;)Ljava/lang/Throwable;
    //   759: athrow
    //   760: aload_3
    //   761: getstatic burp/Zlot.ZD : Ljava/lang/String;
    //   764: getstatic burp/Zlxm.Zc : Ljava/lang/Object;
    //   767: checkcast java/math/BigInteger
    //   770: invokevirtual intValue : ()I
    //   773: bipush #32
    //   775: irem
    //   776: invokestatic abs : (I)I
    //   779: invokevirtual charAt : (I)C
    //   782: invokevirtual append : (C)Ljava/lang/StringBuilder;
    //   785: pop
    //   786: iload_2
    //   787: ifeq -> 1348
    //   790: goto -> 797
    //   793: invokestatic a : (Ljava/lang/Throwable;)Ljava/lang/Throwable;
    //   796: athrow
    //   797: aload_3
    //   798: getstatic burp/Zb9h.Zf : Ljava/lang/String;
    //   801: getstatic burp/Zmh0.Zt : Ljava/lang/Object;
    //   804: checkcast java/math/BigInteger
    //   807: invokevirtual intValue : ()I
    //   810: bipush #32
    //   812: irem
    //   813: invokestatic abs : (I)I
    //   816: invokevirtual charAt : (I)C
    //   819: invokevirtual append : (C)Ljava/lang/StringBuilder;
    //   822: pop
    //   823: iload_2
    //   824: ifeq -> 1348
    //   827: goto -> 834
    //   830: invokestatic a : (Ljava/lang/Throwable;)Ljava/lang/Throwable;
    //   833: athrow
    //   834: aload_3
    //   835: getstatic burp/Zrc0.ZL : Ljava/lang/String;
    //   838: getstatic burp/Zmlu.Zi : Ljava/lang/Object;
    //   841: checkcast java/math/BigInteger
    //   844: invokevirtual intValue : ()I
    //   847: bipush #32
    //   849: irem
    //   850: invokestatic abs : (I)I
    //   853: invokevirtual charAt : (I)C
    //   856: invokevirtual append : (C)Ljava/lang/StringBuilder;
    //   859: pop
    //   860: iload_2
    //   861: ifeq -> 1348
    //   864: goto -> 871
    //   867: invokestatic a : (Ljava/lang/Throwable;)Ljava/lang/Throwable;
    //   870: athrow
    //   871: aload_3
    //   872: getstatic burp/Zs5i.ZJ : Ljava/lang/String;
    //   875: getstatic burp/Zg97.Zc : Ljava/lang/Object;
    //   878: checkcast java/math/BigInteger
    //   881: invokevirtual intValue : ()I
    //   884: bipush #32
    //   886: irem
    //   887: invokestatic abs : (I)I
    //   890: invokevirtual charAt : (I)C
    //   893: invokevirtual append : (C)Ljava/lang/StringBuilder;
    //   896: pop
    //   897: iload_2
    //   898: ifeq -> 1348
    //   901: goto -> 908
    //   904: invokestatic a : (Ljava/lang/Throwable;)Ljava/lang/Throwable;
    //   907: athrow
    //   908: aload_3
    //   909: getstatic burp/Zr3j.Zj : Ljava/lang/String;
    //   912: getstatic burp/Zg0j.ZV : Ljava/lang/Object;
    //   915: checkcast java/math/BigInteger
    //   918: invokevirtual intValue : ()I
    //   921: bipush #32
    //   923: irem
    //   924: invokestatic abs : (I)I
    //   927: invokevirtual charAt : (I)C
    //   930: invokevirtual append : (C)Ljava/lang/StringBuilder;
    //   933: pop
    //   934: iload_2
    //   935: ifeq -> 1348
    //   938: goto -> 945
    //   941: invokestatic a : (Ljava/lang/Throwable;)Ljava/lang/Throwable;
    //   944: athrow
    //   945: aload_3
    //   946: getstatic burp/Zt3l.Zi : Ljava/lang/String;
    //   949: getstatic burp/Ze69.ZH : Ljava/lang/Object;
    //   952: checkcast java/math/BigInteger
    //   955: invokevirtual intValue : ()I
    //   958: bipush #32
    //   960: irem
    //   961: invokestatic abs : (I)I
    //   964: invokevirtual charAt : (I)C
    //   967: invokevirtual append : (C)Ljava/lang/StringBuilder;
    //   970: pop
    //   971: iload_2
    //   972: ifeq -> 1348
    //   975: goto -> 982
    //   978: invokestatic a : (Ljava/lang/Throwable;)Ljava/lang/Throwable;
    //   981: athrow
    //   982: aload_3
    //   983: getstatic burp/Zrct.ZT : Ljava/lang/String;
    //   986: getstatic burp/Zrct.ZV : Ljava/lang/Object;
    //   989: checkcast java/math/BigInteger
    //   992: invokevirtual intValue : ()I
    //   995: bipush #32
    //   997: irem
    //   998: invokestatic abs : (I)I
    //   1001: invokevirtual charAt : (I)C
    //   1004: invokevirtual append : (C)Ljava/lang/StringBuilder;
    //   1007: pop
    //   1008: iload_2
    //   1009: ifeq -> 1348
    //   1012: goto -> 1019
    //   1015: invokestatic a : (Ljava/lang/Throwable;)Ljava/lang/Throwable;
    //   1018: athrow
    //   1019: aload_3
    //   1020: getstatic burp/Zewo.ZM : Ljava/lang/String;
    //   1023: getstatic burp/Zkfb.ZN : Ljava/lang/Object;
    //   1026: checkcast java/math/BigInteger
    //   1029: invokevirtual intValue : ()I
    //   1032: bipush #32
    //   1034: irem
    //   1035: invokestatic abs : (I)I
    //   1038: invokevirtual charAt : (I)C
    //   1041: invokevirtual append : (C)Ljava/lang/StringBuilder;
    //   1044: pop
    //   1045: iload_2
    //   1046: ifeq -> 1348
    //   1049: goto -> 1056
    //   1052: invokestatic a : (Ljava/lang/Throwable;)Ljava/lang/Throwable;
    //   1055: athrow
    //   1056: aload_3
    //   1057: getstatic burp/Zlsw.ZE : Ljava/lang/String;
    //   1060: getstatic burp/Ztdd.ZD : Ljava/lang/Object;
    //   1063: checkcast java/math/BigInteger
    //   1066: invokevirtual intValue : ()I
    //   1069: bipush #32
    //   1071: irem
    //   1072: invokestatic abs : (I)I
    //   1075: invokevirtual charAt : (I)C
    //   1078: invokevirtual append : (C)Ljava/lang/StringBuilder;
    //   1081: pop
    //   1082: iload_2
    //   1083: ifeq -> 1348
    //   1086: goto -> 1093
    //   1089: invokestatic a : (Ljava/lang/Throwable;)Ljava/lang/Throwable;
    //   1092: athrow
    //   1093: aload_3
    //   1094: getstatic burp/Zxo4.ZW : Ljava/lang/String;
    //   1097: getstatic burp/Zmpp.Z_ : Ljava/lang/Object;
    //   1100: checkcast java/math/BigInteger
    //   1103: invokevirtual intValue : ()I
    //   1106: bipush #32
    //   1108: irem
    //   1109: invokestatic abs : (I)I
    //   1112: invokevirtual charAt : (I)C
    //   1115: invokevirtual append : (C)Ljava/lang/StringBuilder;
    //   1118: pop
    //   1119: iload_2
    //   1120: ifeq -> 1348
    //   1123: goto -> 1130
    //   1126: invokestatic a : (Ljava/lang/Throwable;)Ljava/lang/Throwable;
    //   1129: athrow
    //   1130: aload_3
    //   1131: getstatic burp/Zg7w.ZI : Ljava/lang/String;
    //   1134: getstatic burp/Ztcv.ZY : Ljava/lang/Object;
    //   1137: checkcast java/math/BigInteger
    //   1140: invokevirtual intValue : ()I
    //   1143: bipush #32
    //   1145: irem
    //   1146: invokestatic abs : (I)I
    //   1149: invokevirtual charAt : (I)C
    //   1152: invokevirtual append : (C)Ljava/lang/StringBuilder;
    //   1155: pop
    //   1156: iload_2
    //   1157: ifeq -> 1348
    //   1160: goto -> 1167
    //   1163: invokestatic a : (Ljava/lang/Throwable;)Ljava/lang/Throwable;
    //   1166: athrow
    //   1167: aload_3
    //   1168: getstatic burp/Zg7p.ZA : Ljava/lang/String;
    //   1171: getstatic burp/Zg3m.ZK : Ljava/lang/Object;
    //   1174: checkcast java/math/BigInteger
    //   1177: invokevirtual intValue : ()I
    //   1180: bipush #32
    //   1182: irem
    //   1183: invokestatic abs : (I)I
    //   1186: invokevirtual charAt : (I)C
    //   1189: invokevirtual append : (C)Ljava/lang/StringBuilder;
    //   1192: pop
    //   1193: iload_2
    //   1194: ifeq -> 1348
    //   1197: goto -> 1204
    //   1200: invokestatic a : (Ljava/lang/Throwable;)Ljava/lang/Throwable;
    //   1203: athrow
    //   1204: aload_3
    //   1205: getstatic burp/Zgia.Zh : Ljava/lang/String;
    //   1208: getstatic burp/Zrt9.Zy : Ljava/lang/Object;
    //   1211: checkcast java/math/BigInteger
    //   1214: invokevirtual intValue : ()I
    //   1217: bipush #32
    //   1219: irem
    //   1220: invokestatic abs : (I)I
    //   1223: invokevirtual charAt : (I)C
    //   1226: invokevirtual append : (C)Ljava/lang/StringBuilder;
    //   1229: pop
    //   1230: iload_2
    //   1231: ifeq -> 1348
    //   1234: goto -> 1241
    //   1237: invokestatic a : (Ljava/lang/Throwable;)Ljava/lang/Throwable;
    //   1240: athrow
    //   1241: aload_3
    //   1242: getstatic burp/Zb8x.Zp : Ljava/lang/String;
    //   1245: getstatic burp/Zewq.ZO : Ljava/lang/Object;
    //   1248: checkcast java/math/BigInteger
    //   1251: invokevirtual intValue : ()I
    //   1254: bipush #32
    //   1256: irem
    //   1257: invokestatic abs : (I)I
    //   1260: invokevirtual charAt : (I)C
    //   1263: invokevirtual append : (C)Ljava/lang/StringBuilder;
    //   1266: pop
    //   1267: iload_2
    //   1268: ifeq -> 1348
    //   1271: goto -> 1278
    //   1274: invokestatic a : (Ljava/lang/Throwable;)Ljava/lang/Throwable;
    //   1277: athrow
    //   1278: aload_3
    //   1279: getstatic burp/Zmv9.Zm : Ljava/lang/String;
    //   1282: getstatic burp/Zl_u.ZR : Ljava/lang/Object;
    //   1285: checkcast java/math/BigInteger
    //   1288: invokevirtual intValue : ()I
    //   1291: bipush #32
    //   1293: irem
    //   1294: invokestatic abs : (I)I
    //   1297: invokevirtual charAt : (I)C
    //   1300: invokevirtual append : (C)Ljava/lang/StringBuilder;
    //   1303: pop
    //   1304: iload_2
    //   1305: ifeq -> 1348
    //   1308: goto -> 1315
    //   1311: invokestatic a : (Ljava/lang/Throwable;)Ljava/lang/Throwable;
    //   1314: athrow
    //   1315: aload_3
    //   1316: getstatic burp/Zep8.ZC : Ljava/lang/String;
    //   1319: getstatic burp/Zz9v.Zl : Ljava/lang/Object;
    //   1322: checkcast java/math/BigInteger
    //   1325: invokevirtual intValue : ()I
    //   1328: bipush #32
    //   1330: irem
    //   1331: invokestatic abs : (I)I
    //   1334: invokevirtual charAt : (I)C
    //   1337: invokevirtual append : (C)Ljava/lang/StringBuilder;
    //   1340: pop
    //   1341: goto -> 1348
    //   1344: invokestatic a : (Ljava/lang/Throwable;)Ljava/lang/Throwable;
    //   1347: athrow
    //   1348: iinc #4, 1
    //   1351: iload_2
    //   1352: ifeq -> 15
    //   1355: aload_3
    //   1356: invokevirtual toString : ()Ljava/lang/String;
    //   1359: putstatic burp/Zezi.Ze : Ljava/lang/String;
    //   1362: new java/lang/StringBuilder
    //   1365: dup
    //   1366: invokespecial <init> : ()V
    //   1369: astore #4
    //   1371: iconst_0
    //   1372: istore #5
    //   1374: iload #5
    //   1376: bipush #32
    //   1378: if_icmpge -> 2743
    //   1381: iload #5
    //   1383: tableswitch default -> 2736, 0 -> 1524, 1 -> 1562, 2 -> 1600, 3 -> 1638, 4 -> 1676, 5 -> 1714, 6 -> 1752, 7 -> 1790, 8 -> 1828, 9 -> 1866, 10 -> 1904, 11 -> 1942, 12 -> 1980, 13 -> 2018, 14 -> 2056, 15 -> 2094, 16 -> 2132, 17 -> 2170, 18 -> 2208, 19 -> 2246, 20 -> 2284, 21 -> 2322, 22 -> 2360, 23 -> 2398, 24 -> 2436, 25 -> 2474, 26 -> 2512, 27 -> 2550, 28 -> 2588, 29 -> 2626, 30 -> 2664, 31 -> 2702
    //   1524: aload #4
    //   1526: getstatic burp/Zr8g.ZH : Ljava/lang/String;
    //   1529: getstatic burp/Zg6f.Zl : Ljava/lang/Object;
    //   1532: checkcast java/math/BigInteger
    //   1535: invokevirtual intValue : ()I
    //   1538: bipush #32
    //   1540: irem
    //   1541: invokestatic abs : (I)I
    //   1544: invokevirtual charAt : (I)C
    //   1547: invokevirtual append : (C)Ljava/lang/StringBuilder;
    //   1550: pop
    //   1551: iload_2
    //   1552: ifeq -> 2736
    //   1555: goto -> 1562
    //   1558: invokestatic a : (Ljava/lang/Throwable;)Ljava/lang/Throwable;
    //   1561: athrow
    //   1562: aload #4
    //   1564: getstatic burp/Zxf8.Zq : Ljava/lang/String;
    //   1567: getstatic burp/Zgd7.ZZ : Ljava/lang/Object;
    //   1570: checkcast java/math/BigInteger
    //   1573: invokevirtual intValue : ()I
    //   1576: bipush #32
    //   1578: irem
    //   1579: invokestatic abs : (I)I
    //   1582: invokevirtual charAt : (I)C
    //   1585: invokevirtual append : (C)Ljava/lang/StringBuilder;
    //   1588: pop
    //   1589: iload_2
    //   1590: ifeq -> 2736
    //   1593: goto -> 1600
    //   1596: invokestatic a : (Ljava/lang/Throwable;)Ljava/lang/Throwable;
    //   1599: athrow
    //   1600: aload #4
    //   1602: getstatic burp/Zllw.Zg : Ljava/lang/String;
    //   1605: getstatic burp/Zep1.ZW : Ljava/lang/Object;
    //   1608: checkcast java/math/BigInteger
    //   1611: invokevirtual intValue : ()I
    //   1614: bipush #32
    //   1616: irem
    //   1617: invokestatic abs : (I)I
    //   1620: invokevirtual charAt : (I)C
    //   1623: invokevirtual append : (C)Ljava/lang/StringBuilder;
    //   1626: pop
    //   1627: iload_2
    //   1628: ifeq -> 2736
    //   1631: goto -> 1638
    //   1634: invokestatic a : (Ljava/lang/Throwable;)Ljava/lang/Throwable;
    //   1637: athrow
    //   1638: aload #4
    //   1640: getstatic burp/Zb3p.ZX : Ljava/lang/String;
    //   1643: getstatic burp/Zer1.ZL : Ljava/lang/Object;
    //   1646: checkcast java/math/BigInteger
    //   1649: invokevirtual intValue : ()I
    //   1652: bipush #32
    //   1654: irem
    //   1655: invokestatic abs : (I)I
    //   1658: invokevirtual charAt : (I)C
    //   1661: invokevirtual append : (C)Ljava/lang/StringBuilder;
    //   1664: pop
    //   1665: iload_2
    //   1666: ifeq -> 2736
    //   1669: goto -> 1676
    //   1672: invokestatic a : (Ljava/lang/Throwable;)Ljava/lang/Throwable;
    //   1675: athrow
    //   1676: aload #4
    //   1678: getstatic burp/Zr8h.Zk : Ljava/lang/String;
    //   1681: getstatic burp/Zrnw.ZN : Ljava/lang/Object;
    //   1684: checkcast java/math/BigInteger
    //   1687: invokevirtual intValue : ()I
    //   1690: bipush #32
    //   1692: irem
    //   1693: invokestatic abs : (I)I
    //   1696: invokevirtual charAt : (I)C
    //   1699: invokevirtual append : (C)Ljava/lang/StringBuilder;
    //   1702: pop
    //   1703: iload_2
    //   1704: ifeq -> 2736
    //   1707: goto -> 1714
    //   1710: invokestatic a : (Ljava/lang/Throwable;)Ljava/lang/Throwable;
    //   1713: athrow
    //   1714: aload #4
    //   1716: getstatic burp/Zs59.Zc : Ljava/lang/String;
    //   1719: getstatic burp/Zlv6.ZN : Ljava/lang/Object;
    //   1722: checkcast java/math/BigInteger
    //   1725: invokevirtual intValue : ()I
    //   1728: bipush #32
    //   1730: irem
    //   1731: invokestatic abs : (I)I
    //   1734: invokevirtual charAt : (I)C
    //   1737: invokevirtual append : (C)Ljava/lang/StringBuilder;
    //   1740: pop
    //   1741: iload_2
    //   1742: ifeq -> 2736
    //   1745: goto -> 1752
    //   1748: invokestatic a : (Ljava/lang/Throwable;)Ljava/lang/Throwable;
    //   1751: athrow
    //   1752: aload #4
    //   1754: getstatic burp/Zmrc.Zx : Ljava/lang/String;
    //   1757: getstatic burp/Zs8q.ZI : Ljava/lang/Object;
    //   1760: checkcast java/math/BigInteger
    //   1763: invokevirtual intValue : ()I
    //   1766: bipush #32
    //   1768: irem
    //   1769: invokestatic abs : (I)I
    //   1772: invokevirtual charAt : (I)C
    //   1775: invokevirtual append : (C)Ljava/lang/StringBuilder;
    //   1778: pop
    //   1779: iload_2
    //   1780: ifeq -> 2736
    //   1783: goto -> 1790
    //   1786: invokestatic a : (Ljava/lang/Throwable;)Ljava/lang/Throwable;
    //   1789: athrow
    //   1790: aload #4
    //   1792: getstatic burp/Ztip.Z_ : Ljava/lang/String;
    //   1795: getstatic burp/Zl8f.ZA : Ljava/lang/Object;
    //   1798: checkcast java/math/BigInteger
    //   1801: invokevirtual intValue : ()I
    //   1804: bipush #32
    //   1806: irem
    //   1807: invokestatic abs : (I)I
    //   1810: invokevirtual charAt : (I)C
    //   1813: invokevirtual append : (C)Ljava/lang/StringBuilder;
    //   1816: pop
    //   1817: iload_2
    //   1818: ifeq -> 2736
    //   1821: goto -> 1828
    //   1824: invokestatic a : (Ljava/lang/Throwable;)Ljava/lang/Throwable;
    //   1827: athrow
    //   1828: aload #4
    //   1830: getstatic burp/Zr1t.Ze : Ljava/lang/String;
    //   1833: getstatic burp/Zl1n.ZM : Ljava/lang/Object;
    //   1836: checkcast java/math/BigInteger
    //   1839: invokevirtual intValue : ()I
    //   1842: bipush #32
    //   1844: irem
    //   1845: invokestatic abs : (I)I
    //   1848: invokevirtual charAt : (I)C
    //   1851: invokevirtual append : (C)Ljava/lang/StringBuilder;
    //   1854: pop
    //   1855: iload_2
    //   1856: ifeq -> 2736
    //   1859: goto -> 1866
    //   1862: invokestatic a : (Ljava/lang/Throwable;)Ljava/lang/Throwable;
    //   1865: athrow
    //   1866: aload #4
    //   1868: getstatic burp/Zvk.ZG : Ljava/lang/String;
    //   1871: getstatic burp/Zeoi.ZE : Ljava/lang/Object;
    //   1874: checkcast java/math/BigInteger
    //   1877: invokevirtual intValue : ()I
    //   1880: bipush #32
    //   1882: irem
    //   1883: invokestatic abs : (I)I
    //   1886: invokevirtual charAt : (I)C
    //   1889: invokevirtual append : (C)Ljava/lang/StringBuilder;
    //   1892: pop
    //   1893: iload_2
    //   1894: ifeq -> 2736
    //   1897: goto -> 1904
    //   1900: invokestatic a : (Ljava/lang/Throwable;)Ljava/lang/Throwable;
    //   1903: athrow
    //   1904: aload #4
    //   1906: getstatic burp/Zko9.Zf : Ljava/lang/String;
    //   1909: getstatic burp/Zd0.ZT : Ljava/lang/Object;
    //   1912: checkcast java/math/BigInteger
    //   1915: invokevirtual intValue : ()I
    //   1918: bipush #32
    //   1920: irem
    //   1921: invokestatic abs : (I)I
    //   1924: invokevirtual charAt : (I)C
    //   1927: invokevirtual append : (C)Ljava/lang/StringBuilder;
    //   1930: pop
    //   1931: iload_2
    //   1932: ifeq -> 2736
    //   1935: goto -> 1942
    //   1938: invokestatic a : (Ljava/lang/Throwable;)Ljava/lang/Throwable;
    //   1941: athrow
    //   1942: aload #4
    //   1944: getstatic burp/Zmtf.Zx : Ljava/lang/String;
    //   1947: getstatic burp/Zmlu.Zi : Ljava/lang/Object;
    //   1950: checkcast java/math/BigInteger
    //   1953: invokevirtual intValue : ()I
    //   1956: bipush #32
    //   1958: irem
    //   1959: invokestatic abs : (I)I
    //   1962: invokevirtual charAt : (I)C
    //   1965: invokevirtual append : (C)Ljava/lang/StringBuilder;
    //   1968: pop
    //   1969: iload_2
    //   1970: ifeq -> 2736
    //   1973: goto -> 1980
    //   1976: invokestatic a : (Ljava/lang/Throwable;)Ljava/lang/Throwable;
    //   1979: athrow
    //   1980: aload #4
    //   1982: getstatic burp/Zl3j.Zr : Ljava/lang/String;
    //   1985: getstatic burp/Zr0.ZX : Ljava/lang/Object;
    //   1988: checkcast java/math/BigInteger
    //   1991: invokevirtual intValue : ()I
    //   1994: bipush #32
    //   1996: irem
    //   1997: invokestatic abs : (I)I
    //   2000: invokevirtual charAt : (I)C
    //   2003: invokevirtual append : (C)Ljava/lang/StringBuilder;
    //   2006: pop
    //   2007: iload_2
    //   2008: ifeq -> 2736
    //   2011: goto -> 2018
    //   2014: invokestatic a : (Ljava/lang/Throwable;)Ljava/lang/Throwable;
    //   2017: athrow
    //   2018: aload #4
    //   2020: getstatic burp/Zmwx.ZB : Ljava/lang/String;
    //   2023: getstatic burp/Zkyc.ZD : Ljava/lang/Object;
    //   2026: checkcast java/math/BigInteger
    //   2029: invokevirtual intValue : ()I
    //   2032: bipush #32
    //   2034: irem
    //   2035: invokestatic abs : (I)I
    //   2038: invokevirtual charAt : (I)C
    //   2041: invokevirtual append : (C)Ljava/lang/StringBuilder;
    //   2044: pop
    //   2045: iload_2
    //   2046: ifeq -> 2736
    //   2049: goto -> 2056
    //   2052: invokestatic a : (Ljava/lang/Throwable;)Ljava/lang/Throwable;
    //   2055: athrow
    //   2056: aload #4
    //   2058: getstatic burp/Zg0j.Ze : Ljava/lang/String;
    //   2061: getstatic burp/Zzoc.Zx : Ljava/lang/Object;
    //   2064: checkcast java/math/BigInteger
    //   2067: invokevirtual intValue : ()I
    //   2070: bipush #32
    //   2072: irem
    //   2073: invokestatic abs : (I)I
    //   2076: invokevirtual charAt : (I)C
    //   2079: invokevirtual append : (C)Ljava/lang/StringBuilder;
    //   2082: pop
    //   2083: iload_2
    //   2084: ifeq -> 2736
    //   2087: goto -> 2094
    //   2090: invokestatic a : (Ljava/lang/Throwable;)Ljava/lang/Throwable;
    //   2093: athrow
    //   2094: aload #4
    //   2096: getstatic burp/Zxyq.Zr : Ljava/lang/String;
    //   2099: getstatic burp/Zzh9.Zv : Ljava/lang/Object;
    //   2102: checkcast java/math/BigInteger
    //   2105: invokevirtual intValue : ()I
    //   2108: bipush #32
    //   2110: irem
    //   2111: invokestatic abs : (I)I
    //   2114: invokevirtual charAt : (I)C
    //   2117: invokevirtual append : (C)Ljava/lang/StringBuilder;
    //   2120: pop
    //   2121: iload_2
    //   2122: ifeq -> 2736
    //   2125: goto -> 2132
    //   2128: invokestatic a : (Ljava/lang/Throwable;)Ljava/lang/Throwable;
    //   2131: athrow
    //   2132: aload #4
    //   2134: getstatic burp/Zly7.ZC : Ljava/lang/String;
    //   2137: getstatic burp/Zxfu.ZA : Ljava/lang/Object;
    //   2140: checkcast java/math/BigInteger
    //   2143: invokevirtual intValue : ()I
    //   2146: bipush #32
    //   2148: irem
    //   2149: invokestatic abs : (I)I
    //   2152: invokevirtual charAt : (I)C
    //   2155: invokevirtual append : (C)Ljava/lang/StringBuilder;
    //   2158: pop
    //   2159: iload_2
    //   2160: ifeq -> 2736
    //   2163: goto -> 2170
    //   2166: invokestatic a : (Ljava/lang/Throwable;)Ljava/lang/Throwable;
    //   2169: athrow
    //   2170: aload #4
    //   2172: getstatic burp/Zg5.ZF : Ljava/lang/String;
    //   2175: getstatic burp/Zxtn.ZY : Ljava/lang/Object;
    //   2178: checkcast java/math/BigInteger
    //   2181: invokevirtual intValue : ()I
    //   2184: bipush #32
    //   2186: irem
    //   2187: invokestatic abs : (I)I
    //   2190: invokevirtual charAt : (I)C
    //   2193: invokevirtual append : (C)Ljava/lang/StringBuilder;
    //   2196: pop
    //   2197: iload_2
    //   2198: ifeq -> 2736
    //   2201: goto -> 2208
    //   2204: invokestatic a : (Ljava/lang/Throwable;)Ljava/lang/Throwable;
    //   2207: athrow
    //   2208: aload #4
    //   2210: getstatic burp/Zlbr.Zr : Ljava/lang/String;
    //   2213: getstatic burp/Zzxv.ZZ : Ljava/lang/Object;
    //   2216: checkcast java/math/BigInteger
    //   2219: invokevirtual intValue : ()I
    //   2222: bipush #32
    //   2224: irem
    //   2225: invokestatic abs : (I)I
    //   2228: invokevirtual charAt : (I)C
    //   2231: invokevirtual append : (C)Ljava/lang/StringBuilder;
    //   2234: pop
    //   2235: iload_2
    //   2236: ifeq -> 2736
    //   2239: goto -> 2246
    //   2242: invokestatic a : (Ljava/lang/Throwable;)Ljava/lang/Throwable;
    //   2245: athrow
    //   2246: aload #4
    //   2248: getstatic burp/Zlzs.Zp : Ljava/lang/String;
    //   2251: getstatic burp/Zlwi.Zw : Ljava/lang/Object;
    //   2254: checkcast java/math/BigInteger
    //   2257: invokevirtual intValue : ()I
    //   2260: bipush #32
    //   2262: irem
    //   2263: invokestatic abs : (I)I
    //   2266: invokevirtual charAt : (I)C
    //   2269: invokevirtual append : (C)Ljava/lang/StringBuilder;
    //   2272: pop
    //   2273: iload_2
    //   2274: ifeq -> 2736
    //   2277: goto -> 2284
    //   2280: invokestatic a : (Ljava/lang/Throwable;)Ljava/lang/Throwable;
    //   2283: athrow
    //   2284: aload #4
    //   2286: getstatic burp/Zsq6.Zm : Ljava/lang/String;
    //   2289: getstatic burp/Zry7.ZZ : Ljava/lang/Object;
    //   2292: checkcast java/math/BigInteger
    //   2295: invokevirtual intValue : ()I
    //   2298: bipush #32
    //   2300: irem
    //   2301: invokestatic abs : (I)I
    //   2304: invokevirtual charAt : (I)C
    //   2307: invokevirtual append : (C)Ljava/lang/StringBuilder;
    //   2310: pop
    //   2311: iload_2
    //   2312: ifeq -> 2736
    //   2315: goto -> 2322
    //   2318: invokestatic a : (Ljava/lang/Throwable;)Ljava/lang/Throwable;
    //   2321: athrow
    //   2322: aload #4
    //   2324: getstatic burp/Zm4k.ZW : Ljava/lang/String;
    //   2327: getstatic burp/Zmha.ZM : Ljava/lang/Object;
    //   2330: checkcast java/math/BigInteger
    //   2333: invokevirtual intValue : ()I
    //   2336: bipush #32
    //   2338: irem
    //   2339: invokestatic abs : (I)I
    //   2342: invokevirtual charAt : (I)C
    //   2345: invokevirtual append : (C)Ljava/lang/StringBuilder;
    //   2348: pop
    //   2349: iload_2
    //   2350: ifeq -> 2736
    //   2353: goto -> 2360
    //   2356: invokestatic a : (Ljava/lang/Throwable;)Ljava/lang/Throwable;
    //   2359: athrow
    //   2360: aload #4
    //   2362: getstatic burp/Zm14.ZE : Ljava/lang/String;
    //   2365: getstatic burp/Zmh5.ZN : Ljava/lang/Object;
    //   2368: checkcast java/math/BigInteger
    //   2371: invokevirtual intValue : ()I
    //   2374: bipush #32
    //   2376: irem
    //   2377: invokestatic abs : (I)I
    //   2380: invokevirtual charAt : (I)C
    //   2383: invokevirtual append : (C)Ljava/lang/StringBuilder;
    //   2386: pop
    //   2387: iload_2
    //   2388: ifeq -> 2736
    //   2391: goto -> 2398
    //   2394: invokestatic a : (Ljava/lang/Throwable;)Ljava/lang/Throwable;
    //   2397: athrow
    //   2398: aload #4
    //   2400: getstatic burp/Zlx5.ZP : Ljava/lang/String;
    //   2403: getstatic burp/Zss8.ZO : Ljava/lang/Object;
    //   2406: checkcast java/math/BigInteger
    //   2409: invokevirtual intValue : ()I
    //   2412: bipush #32
    //   2414: irem
    //   2415: invokestatic abs : (I)I
    //   2418: invokevirtual charAt : (I)C
    //   2421: invokevirtual append : (C)Ljava/lang/StringBuilder;
    //   2424: pop
    //   2425: iload_2
    //   2426: ifeq -> 2736
    //   2429: goto -> 2436
    //   2432: invokestatic a : (Ljava/lang/Throwable;)Ljava/lang/Throwable;
    //   2435: athrow
    //   2436: aload #4
    //   2438: getstatic burp/Zmou.ZP : Ljava/lang/String;
    //   2441: getstatic burp/Zmd.ZU : Ljava/lang/Object;
    //   2444: checkcast java/math/BigInteger
    //   2447: invokevirtual intValue : ()I
    //   2450: bipush #32
    //   2452: irem
    //   2453: invokestatic abs : (I)I
    //   2456: invokevirtual charAt : (I)C
    //   2459: invokevirtual append : (C)Ljava/lang/StringBuilder;
    //   2462: pop
    //   2463: iload_2
    //   2464: ifeq -> 2736
    //   2467: goto -> 2474
    //   2470: invokestatic a : (Ljava/lang/Throwable;)Ljava/lang/Throwable;
    //   2473: athrow
    //   2474: aload #4
    //   2476: getstatic burp/Zvk.ZG : Ljava/lang/String;
    //   2479: getstatic burp/Zs1d.Zo : Ljava/lang/Object;
    //   2482: checkcast java/math/BigInteger
    //   2485: invokevirtual intValue : ()I
    //   2488: bipush #32
    //   2490: irem
    //   2491: invokestatic abs : (I)I
    //   2494: invokevirtual charAt : (I)C
    //   2497: invokevirtual append : (C)Ljava/lang/StringBuilder;
    //   2500: pop
    //   2501: iload_2
    //   2502: ifeq -> 2736
    //   2505: goto -> 2512
    //   2508: invokestatic a : (Ljava/lang/Throwable;)Ljava/lang/Throwable;
    //   2511: athrow
    //   2512: aload #4
    //   2514: getstatic burp/Zl2q.ZI : Ljava/lang/String;
    //   2517: getstatic burp/Zsde.Zx : Ljava/lang/Object;
    //   2520: checkcast java/math/BigInteger
    //   2523: invokevirtual intValue : ()I
    //   2526: bipush #32
    //   2528: irem
    //   2529: invokestatic abs : (I)I
    //   2532: invokevirtual charAt : (I)C
    //   2535: invokevirtual append : (C)Ljava/lang/StringBuilder;
    //   2538: pop
    //   2539: iload_2
    //   2540: ifeq -> 2736
    //   2543: goto -> 2550
    //   2546: invokestatic a : (Ljava/lang/Throwable;)Ljava/lang/Throwable;
    //   2549: athrow
    //   2550: aload #4
    //   2552: getstatic burp/Zg97.ZX : Ljava/lang/String;
    //   2555: getstatic burp/Zty2.Zl : Ljava/lang/Object;
    //   2558: checkcast java/math/BigInteger
    //   2561: invokevirtual intValue : ()I
    //   2564: bipush #32
    //   2566: irem
    //   2567: invokestatic abs : (I)I
    //   2570: invokevirtual charAt : (I)C
    //   2573: invokevirtual append : (C)Ljava/lang/StringBuilder;
    //   2576: pop
    //   2577: iload_2
    //   2578: ifeq -> 2736
    //   2581: goto -> 2588
    //   2584: invokestatic a : (Ljava/lang/Throwable;)Ljava/lang/Throwable;
    //   2587: athrow
    //   2588: aload #4
    //   2590: getstatic burp/Zs1d.Zl : Ljava/lang/String;
    //   2593: getstatic burp/Ztvn.Zl : Ljava/lang/Object;
    //   2596: checkcast java/math/BigInteger
    //   2599: invokevirtual intValue : ()I
    //   2602: bipush #32
    //   2604: irem
    //   2605: invokestatic abs : (I)I
    //   2608: invokevirtual charAt : (I)C
    //   2611: invokevirtual append : (C)Ljava/lang/StringBuilder;
    //   2614: pop
    //   2615: iload_2
    //   2616: ifeq -> 2736
    //   2619: goto -> 2626
    //   2622: invokestatic a : (Ljava/lang/Throwable;)Ljava/lang/Throwable;
    //   2625: athrow
    //   2626: aload #4
    //   2628: getstatic burp/Zr9b.ZC : Ljava/lang/String;
    //   2631: getstatic burp/Zmjr.ZU : Ljava/lang/Object;
    //   2634: checkcast java/math/BigInteger
    //   2637: invokevirtual intValue : ()I
    //   2640: bipush #32
    //   2642: irem
    //   2643: invokestatic abs : (I)I
    //   2646: invokevirtual charAt : (I)C
    //   2649: invokevirtual append : (C)Ljava/lang/StringBuilder;
    //   2652: pop
    //   2653: iload_2
    //   2654: ifeq -> 2736
    //   2657: goto -> 2664
    //   2660: invokestatic a : (Ljava/lang/Throwable;)Ljava/lang/Throwable;
    //   2663: athrow
    //   2664: aload #4
    //   2666: getstatic burp/Zt7k.ZH : Ljava/lang/String;
    //   2669: getstatic burp/Zrkc.ZI : Ljava/lang/Object;
    //   2672: checkcast java/math/BigInteger
    //   2675: invokevirtual intValue : ()I
    //   2678: bipush #32
    //   2680: irem
    //   2681: invokestatic abs : (I)I
    //   2684: invokevirtual charAt : (I)C
    //   2687: invokevirtual append : (C)Ljava/lang/StringBuilder;
    //   2690: pop
    //   2691: iload_2
    //   2692: ifeq -> 2736
    //   2695: goto -> 2702
    //   2698: invokestatic a : (Ljava/lang/Throwable;)Ljava/lang/Throwable;
    //   2701: athrow
    //   2702: aload #4
    //   2704: getstatic burp/Zsn4.ZZ : Ljava/lang/String;
    //   2707: getstatic burp/Znp.ZJ : Ljava/lang/Object;
    //   2710: checkcast java/math/BigInteger
    //   2713: invokevirtual intValue : ()I
    //   2716: bipush #32
    //   2718: irem
    //   2719: invokestatic abs : (I)I
    //   2722: invokevirtual charAt : (I)C
    //   2725: invokevirtual append : (C)Ljava/lang/StringBuilder;
    //   2728: pop
    //   2729: goto -> 2736
    //   2732: invokestatic a : (Ljava/lang/Throwable;)Ljava/lang/Throwable;
    //   2735: athrow
    //   2736: iinc #5, 1
    //   2739: iload_2
    //   2740: ifeq -> 1374
    //   2743: aload #4
    //   2745: invokevirtual toString : ()Ljava/lang/String;
    //   2748: putstatic burp/Ztcv.Zl : Ljava/lang/String;
    //   2751: new java/lang/StringBuilder
    //   2754: dup
    //   2755: invokespecial <init> : ()V
    //   2758: astore #5
    //   2760: iconst_0
    //   2761: istore #6
    //   2763: iload #6
    //   2765: bipush #32
    //   2767: if_icmpge -> 4135
    //   2770: iload #6
    //   2772: tableswitch default -> 4128, 0 -> 2916, 1 -> 2954, 2 -> 2992, 3 -> 3030, 4 -> 3068, 5 -> 3106, 6 -> 3144, 7 -> 3182, 8 -> 3220, 9 -> 3258, 10 -> 3296, 11 -> 3334, 12 -> 3372, 13 -> 3410, 14 -> 3448, 15 -> 3486, 16 -> 3524, 17 -> 3562, 18 -> 3600, 19 -> 3638, 20 -> 3676, 21 -> 3714, 22 -> 3752, 23 -> 3790, 24 -> 3828, 25 -> 3866, 26 -> 3904, 27 -> 3942, 28 -> 3980, 29 -> 4018, 30 -> 4056, 31 -> 4094
    //   2916: aload #5
    //   2918: getstatic burp/Zt4g.Zj : Ljava/lang/String;
    //   2921: getstatic burp/Ze13.ZD : Ljava/lang/Object;
    //   2924: checkcast java/math/BigInteger
    //   2927: invokevirtual intValue : ()I
    //   2930: bipush #32
    //   2932: irem
    //   2933: invokestatic abs : (I)I
    //   2936: invokevirtual charAt : (I)C
    //   2939: invokevirtual append : (C)Ljava/lang/StringBuilder;
    //   2942: pop
    //   2943: iload_2
    //   2944: ifeq -> 4128
    //   2947: goto -> 2954
    //   2950: invokestatic a : (Ljava/lang/Throwable;)Ljava/lang/Throwable;
    //   2953: athrow
    //   2954: aload #5
    //   2956: getstatic burp/Zss8.ZD : Ljava/lang/String;
    //   2959: getstatic burp/Ztap.ZK : Ljava/lang/Object;
    //   2962: checkcast java/math/BigInteger
    //   2965: invokevirtual intValue : ()I
    //   2968: bipush #32
    //   2970: irem
    //   2971: invokestatic abs : (I)I
    //   2974: invokevirtual charAt : (I)C
    //   2977: invokevirtual append : (C)Ljava/lang/StringBuilder;
    //   2980: pop
    //   2981: iload_2
    //   2982: ifeq -> 4128
    //   2985: goto -> 2992
    //   2988: invokestatic a : (Ljava/lang/Throwable;)Ljava/lang/Throwable;
    //   2991: athrow
    //   2992: aload #5
    //   2994: getstatic burp/Ztnw.Zr : Ljava/lang/String;
    //   2997: getstatic burp/Zscf.ZG : Ljava/lang/Object;
    //   3000: checkcast java/math/BigInteger
    //   3003: invokevirtual intValue : ()I
    //   3006: bipush #32
    //   3008: irem
    //   3009: invokestatic abs : (I)I
    //   3012: invokevirtual charAt : (I)C
    //   3015: invokevirtual append : (C)Ljava/lang/StringBuilder;
    //   3018: pop
    //   3019: iload_2
    //   3020: ifeq -> 4128
    //   3023: goto -> 3030
    //   3026: invokestatic a : (Ljava/lang/Throwable;)Ljava/lang/Throwable;
    //   3029: athrow
    //   3030: aload #5
    //   3032: getstatic burp/Zk8g.ZH : Ljava/lang/String;
    //   3035: getstatic burp/Zzh9.Zv : Ljava/lang/Object;
    //   3038: checkcast java/math/BigInteger
    //   3041: invokevirtual intValue : ()I
    //   3044: bipush #32
    //   3046: irem
    //   3047: invokestatic abs : (I)I
    //   3050: invokevirtual charAt : (I)C
    //   3053: invokevirtual append : (C)Ljava/lang/StringBuilder;
    //   3056: pop
    //   3057: iload_2
    //   3058: ifeq -> 4128
    //   3061: goto -> 3068
    //   3064: invokestatic a : (Ljava/lang/Throwable;)Ljava/lang/Throwable;
    //   3067: athrow
    //   3068: aload #5
    //   3070: getstatic burp/Zss8.ZD : Ljava/lang/String;
    //   3073: getstatic burp/Zeud.Zs : Ljava/lang/Object;
    //   3076: checkcast java/math/BigInteger
    //   3079: invokevirtual intValue : ()I
    //   3082: bipush #32
    //   3084: irem
    //   3085: invokestatic abs : (I)I
    //   3088: invokevirtual charAt : (I)C
    //   3091: invokevirtual append : (C)Ljava/lang/StringBuilder;
    //   3094: pop
    //   3095: iload_2
    //   3096: ifeq -> 4128
    //   3099: goto -> 3106
    //   3102: invokestatic a : (Ljava/lang/Throwable;)Ljava/lang/Throwable;
    //   3105: athrow
    //   3106: aload #5
    //   3108: getstatic burp/Zg2z.ZE : Ljava/lang/String;
    //   3111: getstatic burp/Zlw8.ZA : Ljava/lang/Object;
    //   3114: checkcast java/math/BigInteger
    //   3117: invokevirtual intValue : ()I
    //   3120: bipush #32
    //   3122: irem
    //   3123: invokestatic abs : (I)I
    //   3126: invokevirtual charAt : (I)C
    //   3129: invokevirtual append : (C)Ljava/lang/StringBuilder;
    //   3132: pop
    //   3133: iload_2
    //   3134: ifeq -> 4128
    //   3137: goto -> 3144
    //   3140: invokestatic a : (Ljava/lang/Throwable;)Ljava/lang/Throwable;
    //   3143: athrow
    //   3144: aload #5
    //   3146: getstatic burp/Zbqo.ZS : Ljava/lang/String;
    //   3149: getstatic burp/Zms1.ZE : Ljava/lang/Object;
    //   3152: checkcast java/math/BigInteger
    //   3155: invokevirtual intValue : ()I
    //   3158: bipush #32
    //   3160: irem
    //   3161: invokestatic abs : (I)I
    //   3164: invokevirtual charAt : (I)C
    //   3167: invokevirtual append : (C)Ljava/lang/StringBuilder;
    //   3170: pop
    //   3171: iload_2
    //   3172: ifeq -> 4128
    //   3175: goto -> 3182
    //   3178: invokestatic a : (Ljava/lang/Throwable;)Ljava/lang/Throwable;
    //   3181: athrow
    //   3182: aload #5
    //   3184: getstatic burp/Zsf3.Zb : Ljava/lang/String;
    //   3187: getstatic burp/Zro5.ZT : Ljava/lang/Object;
    //   3190: checkcast java/math/BigInteger
    //   3193: invokevirtual intValue : ()I
    //   3196: bipush #32
    //   3198: irem
    //   3199: invokestatic abs : (I)I
    //   3202: invokevirtual charAt : (I)C
    //   3205: invokevirtual append : (C)Ljava/lang/StringBuilder;
    //   3208: pop
    //   3209: iload_2
    //   3210: ifeq -> 4128
    //   3213: goto -> 3220
    //   3216: invokestatic a : (Ljava/lang/Throwable;)Ljava/lang/Throwable;
    //   3219: athrow
    //   3220: aload #5
    //   3222: getstatic burp/Zz4r.Zq : Ljava/lang/String;
    //   3225: getstatic burp/Zzah.Za : Ljava/lang/Object;
    //   3228: checkcast java/math/BigInteger
    //   3231: invokevirtual intValue : ()I
    //   3234: bipush #32
    //   3236: irem
    //   3237: invokestatic abs : (I)I
    //   3240: invokevirtual charAt : (I)C
    //   3243: invokevirtual append : (C)Ljava/lang/StringBuilder;
    //   3246: pop
    //   3247: iload_2
    //   3248: ifeq -> 4128
    //   3251: goto -> 3258
    //   3254: invokestatic a : (Ljava/lang/Throwable;)Ljava/lang/Throwable;
    //   3257: athrow
    //   3258: aload #5
    //   3260: getstatic burp/Zz80.Ze : Ljava/lang/String;
    //   3263: getstatic burp/Zrnw.ZN : Ljava/lang/Object;
    //   3266: checkcast java/math/BigInteger
    //   3269: invokevirtual intValue : ()I
    //   3272: bipush #32
    //   3274: irem
    //   3275: invokestatic abs : (I)I
    //   3278: invokevirtual charAt : (I)C
    //   3281: invokevirtual append : (C)Ljava/lang/StringBuilder;
    //   3284: pop
    //   3285: iload_2
    //   3286: ifeq -> 4128
    //   3289: goto -> 3296
    //   3292: invokestatic a : (Ljava/lang/Throwable;)Ljava/lang/Throwable;
    //   3295: athrow
    //   3296: aload #5
    //   3298: getstatic burp/Zztx.Zg : Ljava/lang/String;
    //   3301: getstatic burp/Zsun.ZP : Ljava/lang/Object;
    //   3304: checkcast java/math/BigInteger
    //   3307: invokevirtual intValue : ()I
    //   3310: bipush #32
    //   3312: irem
    //   3313: invokestatic abs : (I)I
    //   3316: invokevirtual charAt : (I)C
    //   3319: invokevirtual append : (C)Ljava/lang/StringBuilder;
    //   3322: pop
    //   3323: iload_2
    //   3324: ifeq -> 4128
    //   3327: goto -> 3334
    //   3330: invokestatic a : (Ljava/lang/Throwable;)Ljava/lang/Throwable;
    //   3333: athrow
    //   3334: aload #5
    //   3336: getstatic burp/Zewq.ZV : Ljava/lang/String;
    //   3339: getstatic burp/Zml2.Zo : Ljava/lang/Object;
    //   3342: checkcast java/math/BigInteger
    //   3345: invokevirtual intValue : ()I
    //   3348: bipush #32
    //   3350: irem
    //   3351: invokestatic abs : (I)I
    //   3354: invokevirtual charAt : (I)C
    //   3357: invokevirtual append : (C)Ljava/lang/StringBuilder;
    //   3360: pop
    //   3361: iload_2
    //   3362: ifeq -> 4128
    //   3365: goto -> 3372
    //   3368: invokestatic a : (Ljava/lang/Throwable;)Ljava/lang/Throwable;
    //   3371: athrow
    //   3372: aload #5
    //   3374: getstatic burp/Zbow.Zr : Ljava/lang/String;
    //   3377: getstatic burp/Zrom.ZF : Ljava/lang/Object;
    //   3380: checkcast java/math/BigInteger
    //   3383: invokevirtual intValue : ()I
    //   3386: bipush #32
    //   3388: irem
    //   3389: invokestatic abs : (I)I
    //   3392: invokevirtual charAt : (I)C
    //   3395: invokevirtual append : (C)Ljava/lang/StringBuilder;
    //   3398: pop
    //   3399: iload_2
    //   3400: ifeq -> 4128
    //   3403: goto -> 3410
    //   3406: invokestatic a : (Ljava/lang/Throwable;)Ljava/lang/Throwable;
    //   3409: athrow
    //   3410: aload #5
    //   3412: getstatic burp/Zg7j.ZR : Ljava/lang/String;
    //   3415: getstatic burp/Ztq8.Zm : Ljava/lang/Object;
    //   3418: checkcast java/math/BigInteger
    //   3421: invokevirtual intValue : ()I
    //   3424: bipush #32
    //   3426: irem
    //   3427: invokestatic abs : (I)I
    //   3430: invokevirtual charAt : (I)C
    //   3433: invokevirtual append : (C)Ljava/lang/StringBuilder;
    //   3436: pop
    //   3437: iload_2
    //   3438: ifeq -> 4128
    //   3441: goto -> 3448
    //   3444: invokestatic a : (Ljava/lang/Throwable;)Ljava/lang/Throwable;
    //   3447: athrow
    //   3448: aload #5
    //   3450: getstatic burp/Zlem.Zl : Ljava/lang/String;
    //   3453: getstatic burp/Zsx6.ZN : Ljava/lang/Object;
    //   3456: checkcast java/math/BigInteger
    //   3459: invokevirtual intValue : ()I
    //   3462: bipush #32
    //   3464: irem
    //   3465: invokestatic abs : (I)I
    //   3468: invokevirtual charAt : (I)C
    //   3471: invokevirtual append : (C)Ljava/lang/StringBuilder;
    //   3474: pop
    //   3475: iload_2
    //   3476: ifeq -> 4128
    //   3479: goto -> 3486
    //   3482: invokestatic a : (Ljava/lang/Throwable;)Ljava/lang/Throwable;
    //   3485: athrow
    //   3486: aload #5
    //   3488: getstatic burp/Zmji.Zs : Ljava/lang/String;
    //   3491: getstatic burp/Zgs6.Za : Ljava/lang/Object;
    //   3494: checkcast java/math/BigInteger
    //   3497: invokevirtual intValue : ()I
    //   3500: bipush #32
    //   3502: irem
    //   3503: invokestatic abs : (I)I
    //   3506: invokevirtual charAt : (I)C
    //   3509: invokevirtual append : (C)Ljava/lang/StringBuilder;
    //   3512: pop
    //   3513: iload_2
    //   3514: ifeq -> 4128
    //   3517: goto -> 3524
    //   3520: invokestatic a : (Ljava/lang/Throwable;)Ljava/lang/Throwable;
    //   3523: athrow
    //   3524: aload #5
    //   3526: getstatic burp/Zsm3.Zl : Ljava/lang/String;
    //   3529: getstatic burp/Zgx6.Zo : Ljava/lang/Object;
    //   3532: checkcast java/math/BigInteger
    //   3535: invokevirtual intValue : ()I
    //   3538: bipush #32
    //   3540: irem
    //   3541: invokestatic abs : (I)I
    //   3544: invokevirtual charAt : (I)C
    //   3547: invokevirtual append : (C)Ljava/lang/StringBuilder;
    //   3550: pop
    //   3551: iload_2
    //   3552: ifeq -> 4128
    //   3555: goto -> 3562
    //   3558: invokestatic a : (Ljava/lang/Throwable;)Ljava/lang/Throwable;
    //   3561: athrow
    //   3562: aload #5
    //   3564: getstatic burp/Zz3k.Zn : Ljava/lang/String;
    //   3567: getstatic burp/Zl8i.ZY : Ljava/lang/Object;
    //   3570: checkcast java/math/BigInteger
    //   3573: invokevirtual intValue : ()I
    //   3576: bipush #32
    //   3578: irem
    //   3579: invokestatic abs : (I)I
    //   3582: invokevirtual charAt : (I)C
    //   3585: invokevirtual append : (C)Ljava/lang/StringBuilder;
    //   3588: pop
    //   3589: iload_2
    //   3590: ifeq -> 4128
    //   3593: goto -> 3600
    //   3596: invokestatic a : (Ljava/lang/Throwable;)Ljava/lang/Throwable;
    //   3599: athrow
    //   3600: aload #5
    //   3602: getstatic burp/Zlxm.Zv : Ljava/lang/String;
    //   3605: getstatic burp/Zer.Zk : Ljava/lang/Object;
    //   3608: checkcast java/math/BigInteger
    //   3611: invokevirtual intValue : ()I
    //   3614: bipush #32
    //   3616: irem
    //   3617: invokestatic abs : (I)I
    //   3620: invokevirtual charAt : (I)C
    //   3623: invokevirtual append : (C)Ljava/lang/StringBuilder;
    //   3626: pop
    //   3627: iload_2
    //   3628: ifeq -> 4128
    //   3631: goto -> 3638
    //   3634: invokestatic a : (Ljava/lang/Throwable;)Ljava/lang/Throwable;
    //   3637: athrow
    //   3638: aload #5
    //   3640: getstatic burp/Zsuw.ZK : Ljava/lang/String;
    //   3643: getstatic burp/Zegk.ZR : Ljava/lang/Object;
    //   3646: checkcast java/math/BigInteger
    //   3649: invokevirtual intValue : ()I
    //   3652: bipush #32
    //   3654: irem
    //   3655: invokestatic abs : (I)I
    //   3658: invokevirtual charAt : (I)C
    //   3661: invokevirtual append : (C)Ljava/lang/StringBuilder;
    //   3664: pop
    //   3665: iload_2
    //   3666: ifeq -> 4128
    //   3669: goto -> 3676
    //   3672: invokestatic a : (Ljava/lang/Throwable;)Ljava/lang/Throwable;
    //   3675: athrow
    //   3676: aload #5
    //   3678: getstatic burp/Zli5.Zq : Ljava/lang/String;
    //   3681: getstatic burp/Zs26.Z_ : Ljava/lang/Object;
    //   3684: checkcast java/math/BigInteger
    //   3687: invokevirtual intValue : ()I
    //   3690: bipush #32
    //   3692: irem
    //   3693: invokestatic abs : (I)I
    //   3696: invokevirtual charAt : (I)C
    //   3699: invokevirtual append : (C)Ljava/lang/StringBuilder;
    //   3702: pop
    //   3703: iload_2
    //   3704: ifeq -> 4128
    //   3707: goto -> 3714
    //   3710: invokestatic a : (Ljava/lang/Throwable;)Ljava/lang/Throwable;
    //   3713: athrow
    //   3714: aload #5
    //   3716: getstatic burp/Zll8.ZZ : Ljava/lang/String;
    //   3719: getstatic burp/Zez0.ZT : Ljava/lang/Object;
    //   3722: checkcast java/math/BigInteger
    //   3725: invokevirtual intValue : ()I
    //   3728: bipush #32
    //   3730: irem
    //   3731: invokestatic abs : (I)I
    //   3734: invokevirtual charAt : (I)C
    //   3737: invokevirtual append : (C)Ljava/lang/StringBuilder;
    //   3740: pop
    //   3741: iload_2
    //   3742: ifeq -> 4128
    //   3745: goto -> 3752
    //   3748: invokestatic a : (Ljava/lang/Throwable;)Ljava/lang/Throwable;
    //   3751: athrow
    //   3752: aload #5
    //   3754: getstatic burp/Zs9x.ZY : Ljava/lang/String;
    //   3757: getstatic burp/Zmpv.ZI : Ljava/lang/Object;
    //   3760: checkcast java/math/BigInteger
    //   3763: invokevirtual intValue : ()I
    //   3766: bipush #32
    //   3768: irem
    //   3769: invokestatic abs : (I)I
    //   3772: invokevirtual charAt : (I)C
    //   3775: invokevirtual append : (C)Ljava/lang/StringBuilder;
    //   3778: pop
    //   3779: iload_2
    //   3780: ifeq -> 4128
    //   3783: goto -> 3790
    //   3786: invokestatic a : (Ljava/lang/Throwable;)Ljava/lang/Throwable;
    //   3789: athrow
    //   3790: aload #5
    //   3792: getstatic burp/Zg_i.ZW : Ljava/lang/String;
    //   3795: getstatic burp/Zrqd.Zi : Ljava/lang/Object;
    //   3798: checkcast java/math/BigInteger
    //   3801: invokevirtual intValue : ()I
    //   3804: bipush #32
    //   3806: irem
    //   3807: invokestatic abs : (I)I
    //   3810: invokevirtual charAt : (I)C
    //   3813: invokevirtual append : (C)Ljava/lang/StringBuilder;
    //   3816: pop
    //   3817: iload_2
    //   3818: ifeq -> 4128
    //   3821: goto -> 3828
    //   3824: invokestatic a : (Ljava/lang/Throwable;)Ljava/lang/Throwable;
    //   3827: athrow
    //   3828: aload #5
    //   3830: getstatic burp/Zmd.Zf : Ljava/lang/String;
    //   3833: getstatic burp/Zldt.ZS : Ljava/lang/Object;
    //   3836: checkcast java/math/BigInteger
    //   3839: invokevirtual intValue : ()I
    //   3842: bipush #32
    //   3844: irem
    //   3845: invokestatic abs : (I)I
    //   3848: invokevirtual charAt : (I)C
    //   3851: invokevirtual append : (C)Ljava/lang/StringBuilder;
    //   3854: pop
    //   3855: iload_2
    //   3856: ifeq -> 4128
    //   3859: goto -> 3866
    //   3862: invokestatic a : (Ljava/lang/Throwable;)Ljava/lang/Throwable;
    //   3865: athrow
    //   3866: aload #5
    //   3868: getstatic burp/Zs75.Zn : Ljava/lang/String;
    //   3871: getstatic burp/Zzok.ZY : Ljava/lang/Object;
    //   3874: checkcast java/math/BigInteger
    //   3877: invokevirtual intValue : ()I
    //   3880: bipush #32
    //   3882: irem
    //   3883: invokestatic abs : (I)I
    //   3886: invokevirtual charAt : (I)C
    //   3889: invokevirtual append : (C)Ljava/lang/StringBuilder;
    //   3892: pop
    //   3893: iload_2
    //   3894: ifeq -> 4128
    //   3897: goto -> 3904
    //   3900: invokestatic a : (Ljava/lang/Throwable;)Ljava/lang/Throwable;
    //   3903: athrow
    //   3904: aload #5
    //   3906: getstatic burp/Zry9.ZW : Ljava/lang/String;
    //   3909: getstatic burp/Zebu.Zu : Ljava/lang/Object;
    //   3912: checkcast java/math/BigInteger
    //   3915: invokevirtual intValue : ()I
    //   3918: bipush #32
    //   3920: irem
    //   3921: invokestatic abs : (I)I
    //   3924: invokevirtual charAt : (I)C
    //   3927: invokevirtual append : (C)Ljava/lang/StringBuilder;
    //   3930: pop
    //   3931: iload_2
    //   3932: ifeq -> 4128
    //   3935: goto -> 3942
    //   3938: invokestatic a : (Ljava/lang/Throwable;)Ljava/lang/Throwable;
    //   3941: athrow
    //   3942: aload #5
    //   3944: getstatic burp/Zm0v.Zd : Ljava/lang/String;
    //   3947: getstatic burp/Zr0u.ZB : Ljava/lang/Object;
    //   3950: checkcast java/math/BigInteger
    //   3953: invokevirtual intValue : ()I
    //   3956: bipush #32
    //   3958: irem
    //   3959: invokestatic abs : (I)I
    //   3962: invokevirtual charAt : (I)C
    //   3965: invokevirtual append : (C)Ljava/lang/StringBuilder;
    //   3968: pop
    //   3969: iload_2
    //   3970: ifeq -> 4128
    //   3973: goto -> 3980
    //   3976: invokestatic a : (Ljava/lang/Throwable;)Ljava/lang/Throwable;
    //   3979: athrow
    //   3980: aload #5
    //   3982: getstatic burp/Zgqi.Zv : Ljava/lang/String;
    //   3985: getstatic burp/Zl3n.Zh : Ljava/lang/Object;
    //   3988: checkcast java/math/BigInteger
    //   3991: invokevirtual intValue : ()I
    //   3994: bipush #32
    //   3996: irem
    //   3997: invokestatic abs : (I)I
    //   4000: invokevirtual charAt : (I)C
    //   4003: invokevirtual append : (C)Ljava/lang/StringBuilder;
    //   4006: pop
    //   4007: iload_2
    //   4008: ifeq -> 4128
    //   4011: goto -> 4018
    //   4014: invokestatic a : (Ljava/lang/Throwable;)Ljava/lang/Throwable;
    //   4017: athrow
    //   4018: aload #5
    //   4020: getstatic burp/Zboa.Zq : Ljava/lang/String;
    //   4023: getstatic burp/Zd1.ZV : Ljava/lang/Object;
    //   4026: checkcast java/math/BigInteger
    //   4029: invokevirtual intValue : ()I
    //   4032: bipush #32
    //   4034: irem
    //   4035: invokestatic abs : (I)I
    //   4038: invokevirtual charAt : (I)C
    //   4041: invokevirtual append : (C)Ljava/lang/StringBuilder;
    //   4044: pop
    //   4045: iload_2
    //   4046: ifeq -> 4128
    //   4049: goto -> 4056
    //   4052: invokestatic a : (Ljava/lang/Throwable;)Ljava/lang/Throwable;
    //   4055: athrow
    //   4056: aload #5
    //   4058: getstatic burp/Zs9k.Zx : Ljava/lang/String;
    //   4061: getstatic burp/Zgq_.ZM : Ljava/lang/Object;
    //   4064: checkcast java/math/BigInteger
    //   4067: invokevirtual intValue : ()I
    //   4070: bipush #32
    //   4072: irem
    //   4073: invokestatic abs : (I)I
    //   4076: invokevirtual charAt : (I)C
    //   4079: invokevirtual append : (C)Ljava/lang/StringBuilder;
    //   4082: pop
    //   4083: iload_2
    //   4084: ifeq -> 4128
    //   4087: goto -> 4094
    //   4090: invokestatic a : (Ljava/lang/Throwable;)Ljava/lang/Throwable;
    //   4093: athrow
    //   4094: aload #5
    //   4096: getstatic burp/Zs9k.Zx : Ljava/lang/String;
    //   4099: getstatic burp/Zxzv.Zg : Ljava/lang/Object;
    //   4102: checkcast java/math/BigInteger
    //   4105: invokevirtual intValue : ()I
    //   4108: bipush #32
    //   4110: irem
    //   4111: invokestatic abs : (I)I
    //   4114: invokevirtual charAt : (I)C
    //   4117: invokevirtual append : (C)Ljava/lang/StringBuilder;
    //   4120: pop
    //   4121: goto -> 4128
    //   4124: invokestatic a : (Ljava/lang/Throwable;)Ljava/lang/Throwable;
    //   4127: athrow
    //   4128: iinc #6, 1
    //   4131: iload_2
    //   4132: ifeq -> 2763
    //   4135: aload #5
    //   4137: invokevirtual toString : ()Ljava/lang/String;
    //   4140: putstatic burp/Zgta.ZL : Ljava/lang/String;
    //   4143: sipush #30576
    //   4146: sipush #-32010
    //   4149: invokestatic a : (II)Ljava/lang/String;
    //   4152: iconst_1
    //   4153: ldc burp/Zt5a
    //   4155: invokevirtual getClassLoader : ()Ljava/lang/ClassLoader;
    //   4158: invokestatic forName : (Ljava/lang/String;ZLjava/lang/ClassLoader;)Ljava/lang/Class;
    //   4161: invokevirtual getDeclaredFields : ()[Ljava/lang/reflect/Field;
    //   4164: astore #6
    //   4166: aload #6
    //   4168: arraylength
    //   4169: istore #7
    //   4171: iconst_0
    //   4172: istore #8
    //   4174: iload #8
    //   4176: iload #7
    //   4178: if_icmpge -> 4316
    //   4181: aload #6
    //   4183: iload #8
    //   4185: aaload
    //   4186: astore #9
    //   4188: aload #9
    //   4190: invokevirtual getModifiers : ()I
    //   4193: invokestatic isStatic : (I)Z
    //   4196: ifne -> 4206
    //   4199: goto -> 4309
    //   4202: invokestatic a : (Ljava/lang/Throwable;)Ljava/lang/Throwable;
    //   4205: athrow
    //   4206: aload #9
    //   4208: invokevirtual getType : ()Ljava/lang/Class;
    //   4211: astore #10
    //   4213: aload #10
    //   4215: ifnull -> 4296
    //   4218: aload #10
    //   4220: invokevirtual isPrimitive : ()Z
    //   4223: ifne -> 4296
    //   4226: goto -> 4233
    //   4229: invokestatic a : (Ljava/lang/Throwable;)Ljava/lang/Throwable;
    //   4232: athrow
    //   4233: aload #10
    //   4235: invokevirtual getPackage : ()Ljava/lang/Package;
    //   4238: ifnull -> 4296
    //   4241: goto -> 4248
    //   4244: invokestatic a : (Ljava/lang/Throwable;)Ljava/lang/Throwable;
    //   4247: athrow
    //   4248: aload #10
    //   4250: invokevirtual getPackage : ()Ljava/lang/Package;
    //   4253: invokevirtual getName : ()Ljava/lang/String;
    //   4256: ifnull -> 4296
    //   4259: goto -> 4266
    //   4262: invokestatic a : (Ljava/lang/Throwable;)Ljava/lang/Throwable;
    //   4265: athrow
    //   4266: aload #10
    //   4268: invokevirtual getPackage : ()Ljava/lang/Package;
    //   4271: invokevirtual getName : ()Ljava/lang/String;
    //   4274: sipush #30584
    //   4277: sipush #29210
    //   4280: invokestatic a : (II)Ljava/lang/String;
    //   4283: invokevirtual startsWith : (Ljava/lang/String;)Z
    //   4286: ifne -> 4296
    //   4289: goto -> 4296
    //   4292: invokestatic a : (Ljava/lang/Throwable;)Ljava/lang/Throwable;
    //   4295: athrow
    //   4296: aload #9
    //   4298: iconst_1
    //   4299: invokevirtual setAccessible : (Z)V
    //   4302: aload #9
    //   4304: aconst_null
    //   4305: invokevirtual get : (Ljava/lang/Object;)Ljava/lang/Object;
    //   4308: pop
    //   4309: iinc #8, 1
    //   4312: iload_2
    //   4313: ifeq -> 4174
    //   4316: sipush #30591
    //   4319: sipush #-18139
    //   4322: invokestatic a : (II)Ljava/lang/String;
    //   4325: invokestatic forName : (Ljava/lang/String;)Ljava/lang/Class;
    //   4328: invokevirtual getDeclaredMethods : ()[Ljava/lang/reflect/Method;
    //   4331: astore #6
    //   4333: aload #6
    //   4335: arraylength
    //   4336: istore #7
    //   4338: iconst_0
    //   4339: istore #8
    //   4341: iload #8
    //   4343: iload #7
    //   4345: if_icmpge -> 4475
    //   4348: aload #6
    //   4350: iload #8
    //   4352: aaload
    //   4353: astore #9
    //   4355: aload #9
    //   4357: invokevirtual getParameterTypes : ()[Ljava/lang/Class;
    //   4360: pop
    //   4361: aload #9
    //   4363: invokevirtual getModifiers : ()I
    //   4366: invokestatic isStatic : (I)Z
    //   4369: ifeq -> 4461
    //   4372: aload #9
    //   4374: invokevirtual getParameterTypes : ()[Ljava/lang/Class;
    //   4377: arraylength
    //   4378: iconst_2
    //   4379: if_icmpne -> 4461
    //   4382: goto -> 4389
    //   4385: invokestatic a : (Ljava/lang/Throwable;)Ljava/lang/Throwable;
    //   4388: athrow
    //   4389: aload #9
    //   4391: invokevirtual getReturnType : ()Ljava/lang/Class;
    //   4394: getstatic java/lang/Boolean.TYPE : Ljava/lang/Class;
    //   4397: if_acmpne -> 4461
    //   4400: goto -> 4407
    //   4403: invokestatic a : (Ljava/lang/Throwable;)Ljava/lang/Throwable;
    //   4406: athrow
    //   4407: aload #9
    //   4409: iconst_1
    //   4410: invokevirtual setAccessible : (Z)V
    //   4413: aload #9
    //   4415: aconst_null
    //   4416: iconst_2
    //   4417: anewarray java/lang/Object
    //   4420: dup
    //   4421: iconst_0
    //   4422: aload_0
    //   4423: aastore
    //   4424: dup
    //   4425: iconst_1
    //   4426: aload_1
    //   4427: ifnonnull -> 4445
    //   4430: goto -> 4437
    //   4433: invokestatic a : (Ljava/lang/Throwable;)Ljava/lang/Throwable;
    //   4436: athrow
    //   4437: aload_1
    //   4438: goto -> 4452
    //   4441: invokestatic a : (Ljava/lang/Throwable;)Ljava/lang/Throwable;
    //   4444: athrow
    //   4445: aload_1
    //   4446: checkcast [B
    //   4449: invokevirtual clone : ()Ljava/lang/Object;
    //   4452: aastore
    //   4453: invokevirtual invoke : (Ljava/lang/Object;[Ljava/lang/Object;)Ljava/lang/Object;
    //   4456: pop
    //   4457: iload_2
    //   4458: ifeq -> 4475
    //   4461: iinc #8, 1
    //   4464: iload_2
    //   4465: ifeq -> 4341
    //   4468: goto -> 4475
    //   4471: invokestatic a : (Ljava/lang/Throwable;)Ljava/lang/Throwable;
    //   4474: athrow
    //   4475: sipush #30581
    //   4478: sipush #-12960
    //   4481: invokestatic a : (II)Ljava/lang/String;
    //   4484: iconst_1
    //   4485: ldc burp/Zmwx
    //   4487: invokevirtual getClassLoader : ()Ljava/lang/ClassLoader;
    //   4490: invokestatic forName : (Ljava/lang/String;ZLjava/lang/ClassLoader;)Ljava/lang/Class;
    //   4493: invokevirtual getDeclaredFields : ()[Ljava/lang/reflect/Field;
    //   4496: astore #6
    //   4498: aload #6
    //   4500: arraylength
    //   4501: istore #7
    //   4503: iconst_0
    //   4504: istore #8
    //   4506: iload #8
    //   4508: iload #7
    //   4510: if_icmpge -> 4648
    //   4513: aload #6
    //   4515: iload #8
    //   4517: aaload
    //   4518: astore #9
    //   4520: aload #9
    //   4522: invokevirtual getModifiers : ()I
    //   4525: invokestatic isStatic : (I)Z
    //   4528: ifne -> 4538
    //   4531: goto -> 4641
    //   4534: invokestatic a : (Ljava/lang/Throwable;)Ljava/lang/Throwable;
    //   4537: athrow
    //   4538: aload #9
    //   4540: invokevirtual getType : ()Ljava/lang/Class;
    //   4543: astore #10
    //   4545: aload #10
    //   4547: ifnull -> 4628
    //   4550: aload #10
    //   4552: invokevirtual isPrimitive : ()Z
    //   4555: ifne -> 4628
    //   4558: goto -> 4565
    //   4561: invokestatic a : (Ljava/lang/Throwable;)Ljava/lang/Throwable;
    //   4564: athrow
    //   4565: aload #10
    //   4567: invokevirtual getPackage : ()Ljava/lang/Package;
    //   4570: ifnull -> 4628
    //   4573: goto -> 4580
    //   4576: invokestatic a : (Ljava/lang/Throwable;)Ljava/lang/Throwable;
    //   4579: athrow
    //   4580: aload #10
    //   4582: invokevirtual getPackage : ()Ljava/lang/Package;
    //   4585: invokevirtual getName : ()Ljava/lang/String;
    //   4588: ifnull -> 4628
    //   4591: goto -> 4598
    //   4594: invokestatic a : (Ljava/lang/Throwable;)Ljava/lang/Throwable;
    //   4597: athrow
    //   4598: aload #10
    //   4600: invokevirtual getPackage : ()Ljava/lang/Package;
    //   4603: invokevirtual getName : ()Ljava/lang/String;
    //   4606: sipush #30582
    //   4609: sipush #13786
    //   4612: invokestatic a : (II)Ljava/lang/String;
    //   4615: invokevirtual startsWith : (Ljava/lang/String;)Z
    //   4618: ifne -> 4628
    //   4621: goto -> 4628
    //   4624: invokestatic a : (Ljava/lang/Throwable;)Ljava/lang/Throwable;
    //   4627: athrow
    //   4628: aload #9
    //   4630: iconst_1
    //   4631: invokevirtual setAccessible : (Z)V
    //   4634: aload #9
    //   4636: aconst_null
    //   4637: invokevirtual get : (Ljava/lang/Object;)Ljava/lang/Object;
    //   4640: pop
    //   4641: iinc #8, 1
    //   4644: iload_2
    //   4645: ifeq -> 4506
    //   4648: sipush #30572
    //   4651: sipush #26372
    //   4654: invokestatic a : (II)Ljava/lang/String;
    //   4657: invokestatic forName : (Ljava/lang/String;)Ljava/lang/Class;
    //   4660: invokevirtual getDeclaredMethods : ()[Ljava/lang/reflect/Method;
    //   4663: astore #6
    //   4665: aload #6
    //   4667: arraylength
    //   4668: istore #7
    //   4670: iconst_0
    //   4671: istore #8
    //   4673: iload #8
    //   4675: iload #7
    //   4677: if_icmpge -> 4810
    //   4680: aload #6
    //   4682: iload #8
    //   4684: aaload
    //   4685: astore #9
    //   4687: aload #9
    //   4689: invokevirtual getParameterTypes : ()[Ljava/lang/Class;
    //   4692: pop
    //   4693: aload #9
    //   4695: invokevirtual getModifiers : ()I
    //   4698: invokestatic isStatic : (I)Z
    //   4701: ifeq -> 4796
    //   4704: aload #9
    //   4706: invokevirtual getParameterTypes : ()[Ljava/lang/Class;
    //   4709: arraylength
    //   4710: iconst_2
    //   4711: if_icmpne -> 4796
    //   4714: goto -> 4721
    //   4717: invokestatic a : (Ljava/lang/Throwable;)Ljava/lang/Throwable;
    //   4720: athrow
    //   4721: aload #9
    //   4723: invokevirtual getReturnType : ()Ljava/lang/Class;
    //   4726: getstatic java/lang/Void.TYPE : Ljava/lang/Class;
    //   4729: invokevirtual equals : (Ljava/lang/Object;)Z
    //   4732: ifeq -> 4796
    //   4735: goto -> 4742
    //   4738: invokestatic a : (Ljava/lang/Throwable;)Ljava/lang/Throwable;
    //   4741: athrow
    //   4742: aload #9
    //   4744: iconst_1
    //   4745: invokevirtual setAccessible : (Z)V
    //   4748: aload #9
    //   4750: aconst_null
    //   4751: iconst_2
    //   4752: anewarray java/lang/Object
    //   4755: dup
    //   4756: iconst_0
    //   4757: aload_0
    //   4758: aastore
    //   4759: dup
    //   4760: iconst_1
    //   4761: aload_1
    //   4762: ifnonnull -> 4780
    //   4765: goto -> 4772
    //   4768: invokestatic a : (Ljava/lang/Throwable;)Ljava/lang/Throwable;
    //   4771: athrow
    //   4772: aload_1
    //   4773: goto -> 4787
    //   4776: invokestatic a : (Ljava/lang/Throwable;)Ljava/lang/Throwable;
    //   4779: athrow
    //   4780: aload_1
    //   4781: checkcast [B
    //   4784: invokevirtual clone : ()Ljava/lang/Object;
    //   4787: aastore
    //   4788: invokevirtual invoke : (Ljava/lang/Object;[Ljava/lang/Object;)Ljava/lang/Object;
    //   4791: pop
    //   4792: iload_2
    //   4793: ifeq -> 4810
    //   4796: iinc #8, 1
    //   4799: iload_2
    //   4800: ifeq -> 4673
    //   4803: goto -> 4810
    //   4806: invokestatic a : (Ljava/lang/Throwable;)Ljava/lang/Throwable;
    //   4809: athrow
    //   4810: iconst_0
    //   4811: istore #6
    //   4813: getstatic burp/Znp.Zr : Ljava/lang/String;
    //   4816: getstatic burp/Zro5.ZT : Ljava/lang/Object;
    //   4819: checkcast java/math/BigInteger
    //   4822: invokevirtual intValue : ()I
    //   4825: bipush #32
    //   4827: irem
    //   4828: invokestatic abs : (I)I
    //   4831: invokevirtual charAt : (I)C
    //   4834: getstatic burp/Zzs9.Zg : Ljava/lang/String;
    //   4837: getstatic burp/Zm5p.Ze : Ljava/lang/Object;
    //   4840: checkcast java/math/BigInteger
    //   4843: invokevirtual intValue : ()I
    //   4846: bipush #32
    //   4848: irem
    //   4849: invokestatic abs : (I)I
    //   4852: invokevirtual charAt : (I)C
    //   4855: if_icmple -> 5200
    //   4858: sipush #30579
    //   4861: sipush #187
    //   4864: invokestatic a : (II)Ljava/lang/String;
    //   4867: iconst_1
    //   4868: ldc burp/Zz5l
    //   4870: invokevirtual getClassLoader : ()Ljava/lang/ClassLoader;
    //   4873: invokestatic forName : (Ljava/lang/String;ZLjava/lang/ClassLoader;)Ljava/lang/Class;
    //   4876: invokevirtual getDeclaredFields : ()[Ljava/lang/reflect/Field;
    //   4879: astore #7
    //   4881: aload #7
    //   4883: arraylength
    //   4884: istore #8
    //   4886: iconst_0
    //   4887: istore #9
    //   4889: iload #9
    //   4891: iload #8
    //   4893: if_icmpge -> 5031
    //   4896: aload #7
    //   4898: iload #9
    //   4900: aaload
    //   4901: astore #10
    //   4903: aload #10
    //   4905: invokevirtual getModifiers : ()I
    //   4908: invokestatic isStatic : (I)Z
    //   4911: ifne -> 4921
    //   4914: goto -> 5024
    //   4917: invokestatic a : (Ljava/lang/Throwable;)Ljava/lang/Throwable;
    //   4920: athrow
    //   4921: aload #10
    //   4923: invokevirtual getType : ()Ljava/lang/Class;
    //   4926: astore #11
    //   4928: aload #11
    //   4930: ifnull -> 5011
    //   4933: aload #11
    //   4935: invokevirtual isPrimitive : ()Z
    //   4938: ifne -> 5011
    //   4941: goto -> 4948
    //   4944: invokestatic a : (Ljava/lang/Throwable;)Ljava/lang/Throwable;
    //   4947: athrow
    //   4948: aload #11
    //   4950: invokevirtual getPackage : ()Ljava/lang/Package;
    //   4953: ifnull -> 5011
    //   4956: goto -> 4963
    //   4959: invokestatic a : (Ljava/lang/Throwable;)Ljava/lang/Throwable;
    //   4962: athrow
    //   4963: aload #11
    //   4965: invokevirtual getPackage : ()Ljava/lang/Package;
    //   4968: invokevirtual getName : ()Ljava/lang/String;
    //   4971: ifnull -> 5011
    //   4974: goto -> 4981
    //   4977: invokestatic a : (Ljava/lang/Throwable;)Ljava/lang/Throwable;
    //   4980: athrow
    //   4981: aload #11
    //   4983: invokevirtual getPackage : ()Ljava/lang/Package;
    //   4986: invokevirtual getName : ()Ljava/lang/String;
    //   4989: sipush #30582
    //   4992: sipush #13786
    //   4995: invokestatic a : (II)Ljava/lang/String;
    //   4998: invokevirtual startsWith : (Ljava/lang/String;)Z
    //   5001: ifne -> 5011
    //   5004: goto -> 5011
    //   5007: invokestatic a : (Ljava/lang/Throwable;)Ljava/lang/Throwable;
    //   5010: athrow
    //   5011: aload #10
    //   5013: iconst_1
    //   5014: invokevirtual setAccessible : (Z)V
    //   5017: aload #10
    //   5019: aconst_null
    //   5020: invokevirtual get : (Ljava/lang/Object;)Ljava/lang/Object;
    //   5023: pop
    //   5024: iinc #9, 1
    //   5027: iload_2
    //   5028: ifeq -> 4889
    //   5031: sipush #30586
    //   5034: sipush #9987
    //   5037: invokestatic a : (II)Ljava/lang/String;
    //   5040: invokestatic forName : (Ljava/lang/String;)Ljava/lang/Class;
    //   5043: invokevirtual getDeclaredMethods : ()[Ljava/lang/reflect/Method;
    //   5046: astore #7
    //   5048: aload #7
    //   5050: arraylength
    //   5051: istore #8
    //   5053: iconst_0
    //   5054: istore #9
    //   5056: iload #9
    //   5058: iload #8
    //   5060: if_icmpge -> 5197
    //   5063: aload #7
    //   5065: iload #9
    //   5067: aaload
    //   5068: astore #10
    //   5070: aload #10
    //   5072: invokevirtual getParameterTypes : ()[Ljava/lang/Class;
    //   5075: pop
    //   5076: aload #10
    //   5078: invokevirtual getModifiers : ()I
    //   5081: invokestatic isStatic : (I)Z
    //   5084: ifeq -> 5183
    //   5087: aload #10
    //   5089: invokevirtual getParameterTypes : ()[Ljava/lang/Class;
    //   5092: arraylength
    //   5093: iconst_2
    //   5094: if_icmpne -> 5183
    //   5097: goto -> 5104
    //   5100: invokestatic a : (Ljava/lang/Throwable;)Ljava/lang/Throwable;
    //   5103: athrow
    //   5104: aload #10
    //   5106: invokevirtual getReturnType : ()Ljava/lang/Class;
    //   5109: getstatic java/lang/Boolean.TYPE : Ljava/lang/Class;
    //   5112: if_acmpne -> 5183
    //   5115: goto -> 5122
    //   5118: invokestatic a : (Ljava/lang/Throwable;)Ljava/lang/Throwable;
    //   5121: athrow
    //   5122: aload #10
    //   5124: iconst_1
    //   5125: invokevirtual setAccessible : (Z)V
    //   5128: aload #10
    //   5130: aconst_null
    //   5131: iconst_2
    //   5132: anewarray java/lang/Object
    //   5135: dup
    //   5136: iconst_0
    //   5137: aload_0
    //   5138: aastore
    //   5139: dup
    //   5140: iconst_1
    //   5141: aload_1
    //   5142: ifnonnull -> 5160
    //   5145: goto -> 5152
    //   5148: invokestatic a : (Ljava/lang/Throwable;)Ljava/lang/Throwable;
    //   5151: athrow
    //   5152: aload_1
    //   5153: goto -> 5167
    //   5156: invokestatic a : (Ljava/lang/Throwable;)Ljava/lang/Throwable;
    //   5159: athrow
    //   5160: aload_1
    //   5161: checkcast [B
    //   5164: invokevirtual clone : ()Ljava/lang/Object;
    //   5167: aastore
    //   5168: invokevirtual invoke : (Ljava/lang/Object;[Ljava/lang/Object;)Ljava/lang/Object;
    //   5171: checkcast java/lang/Boolean
    //   5174: invokevirtual booleanValue : ()Z
    //   5177: istore #6
    //   5179: iload_2
    //   5180: ifeq -> 5197
    //   5183: iinc #9, 1
    //   5186: iload_2
    //   5187: ifeq -> 5056
    //   5190: goto -> 5197
    //   5193: invokestatic a : (Ljava/lang/Throwable;)Ljava/lang/Throwable;
    //   5196: athrow
    //   5197: goto -> 5539
    //   5200: sipush #30587
    //   5203: sipush #26196
    //   5206: invokestatic a : (II)Ljava/lang/String;
    //   5209: iconst_1
    //   5210: ldc burp/Zlh2
    //   5212: invokevirtual getClassLoader : ()Ljava/lang/ClassLoader;
    //   5215: invokestatic forName : (Ljava/lang/String;ZLjava/lang/ClassLoader;)Ljava/lang/Class;
    //   5218: invokevirtual getDeclaredFields : ()[Ljava/lang/reflect/Field;
    //   5221: astore #7
    //   5223: aload #7
    //   5225: arraylength
    //   5226: istore #8
    //   5228: iconst_0
    //   5229: istore #9
    //   5231: iload #9
    //   5233: iload #8
    //   5235: if_icmpge -> 5373
    //   5238: aload #7
    //   5240: iload #9
    //   5242: aaload
    //   5243: astore #10
    //   5245: aload #10
    //   5247: invokevirtual getModifiers : ()I
    //   5250: invokestatic isStatic : (I)Z
    //   5253: ifne -> 5263
    //   5256: goto -> 5366
    //   5259: invokestatic a : (Ljava/lang/Throwable;)Ljava/lang/Throwable;
    //   5262: athrow
    //   5263: aload #10
    //   5265: invokevirtual getType : ()Ljava/lang/Class;
    //   5268: astore #11
    //   5270: aload #11
    //   5272: ifnull -> 5353
    //   5275: aload #11
    //   5277: invokevirtual isPrimitive : ()Z
    //   5280: ifne -> 5353
    //   5283: goto -> 5290
    //   5286: invokestatic a : (Ljava/lang/Throwable;)Ljava/lang/Throwable;
    //   5289: athrow
    //   5290: aload #11
    //   5292: invokevirtual getPackage : ()Ljava/lang/Package;
    //   5295: ifnull -> 5353
    //   5298: goto -> 5305
    //   5301: invokestatic a : (Ljava/lang/Throwable;)Ljava/lang/Throwable;
    //   5304: athrow
    //   5305: aload #11
    //   5307: invokevirtual getPackage : ()Ljava/lang/Package;
    //   5310: invokevirtual getName : ()Ljava/lang/String;
    //   5313: ifnull -> 5353
    //   5316: goto -> 5323
    //   5319: invokestatic a : (Ljava/lang/Throwable;)Ljava/lang/Throwable;
    //   5322: athrow
    //   5323: aload #11
    //   5325: invokevirtual getPackage : ()Ljava/lang/Package;
    //   5328: invokevirtual getName : ()Ljava/lang/String;
    //   5331: sipush #30582
    //   5334: sipush #13786
    //   5337: invokestatic a : (II)Ljava/lang/String;
    //   5340: invokevirtual startsWith : (Ljava/lang/String;)Z
    //   5343: ifne -> 5353
    //   5346: goto -> 5353
    //   5349: invokestatic a : (Ljava/lang/Throwable;)Ljava/lang/Throwable;
    //   5352: athrow
    //   5353: aload #10
    //   5355: iconst_1
    //   5356: invokevirtual setAccessible : (Z)V
    //   5359: aload #10
    //   5361: aconst_null
    //   5362: invokevirtual get : (Ljava/lang/Object;)Ljava/lang/Object;
    //   5365: pop
    //   5366: iinc #9, 1
    //   5369: iload_2
    //   5370: ifeq -> 5231
    //   5373: sipush #30568
    //   5376: sipush #-11680
    //   5379: invokestatic a : (II)Ljava/lang/String;
    //   5382: invokestatic forName : (Ljava/lang/String;)Ljava/lang/Class;
    //   5385: invokevirtual getDeclaredMethods : ()[Ljava/lang/reflect/Method;
    //   5388: astore #7
    //   5390: aload #7
    //   5392: arraylength
    //   5393: istore #8
    //   5395: iconst_0
    //   5396: istore #9
    //   5398: iload #9
    //   5400: iload #8
    //   5402: if_icmpge -> 5539
    //   5405: aload #7
    //   5407: iload #9
    //   5409: aaload
    //   5410: astore #10
    //   5412: aload #10
    //   5414: invokevirtual getParameterTypes : ()[Ljava/lang/Class;
    //   5417: pop
    //   5418: aload #10
    //   5420: invokevirtual getModifiers : ()I
    //   5423: invokestatic isStatic : (I)Z
    //   5426: ifeq -> 5525
    //   5429: aload #10
    //   5431: invokevirtual getParameterTypes : ()[Ljava/lang/Class;
    //   5434: arraylength
    //   5435: iconst_2
    //   5436: if_icmpne -> 5525
    //   5439: goto -> 5446
    //   5442: invokestatic a : (Ljava/lang/Throwable;)Ljava/lang/Throwable;
    //   5445: athrow
    //   5446: aload #10
    //   5448: invokevirtual getReturnType : ()Ljava/lang/Class;
    //   5451: getstatic java/lang/Boolean.TYPE : Ljava/lang/Class;
    //   5454: if_acmpne -> 5525
    //   5457: goto -> 5464
    //   5460: invokestatic a : (Ljava/lang/Throwable;)Ljava/lang/Throwable;
    //   5463: athrow
    //   5464: aload #10
    //   5466: iconst_1
    //   5467: invokevirtual setAccessible : (Z)V
    //   5470: aload #10
    //   5472: aconst_null
    //   5473: iconst_2
    //   5474: anewarray java/lang/Object
    //   5477: dup
    //   5478: iconst_0
    //   5479: aload_0
    //   5480: aastore
    //   5481: dup
    //   5482: iconst_1
    //   5483: aload_1
    //   5484: ifnonnull -> 5502
    //   5487: goto -> 5494
    //   5490: invokestatic a : (Ljava/lang/Throwable;)Ljava/lang/Throwable;
    //   5493: athrow
    //   5494: aload_1
    //   5495: goto -> 5509
    //   5498: invokestatic a : (Ljava/lang/Throwable;)Ljava/lang/Throwable;
    //   5501: athrow
    //   5502: aload_1
    //   5503: checkcast [B
    //   5506: invokevirtual clone : ()Ljava/lang/Object;
    //   5509: aastore
    //   5510: invokevirtual invoke : (Ljava/lang/Object;[Ljava/lang/Object;)Ljava/lang/Object;
    //   5513: checkcast java/lang/Boolean
    //   5516: invokevirtual booleanValue : ()Z
    //   5519: istore #6
    //   5521: iload_2
    //   5522: ifeq -> 5539
    //   5525: iinc #9, 1
    //   5528: iload_2
    //   5529: ifeq -> 5398
    //   5532: goto -> 5539
    //   5535: invokestatic a : (Ljava/lang/Throwable;)Ljava/lang/Throwable;
    //   5538: athrow
    //   5539: iload #6
    //   5541: ifeq -> 5547
    //   5544: iload #6
    //   5546: ireturn
    //   5547: getstatic burp/Zr5k.Zq : Ljava/lang/String;
    //   5550: getstatic burp/Zgkn.Zm : Ljava/lang/Object;
    //   5553: checkcast java/math/BigInteger
    //   5556: invokevirtual intValue : ()I
    //   5559: bipush #32
    //   5561: irem
    //   5562: invokestatic abs : (I)I
    //   5565: invokevirtual charAt : (I)C
    //   5568: getstatic burp/Zry0.Zz : Ljava/lang/String;
    //   5571: getstatic burp/Zlb6.Zz : Ljava/lang/Object;
    //   5574: checkcast java/math/BigInteger
    //   5577: invokevirtual intValue : ()I
    //   5580: bipush #32
    //   5582: irem
    //   5583: invokestatic abs : (I)I
    //   5586: invokevirtual charAt : (I)C
    //   5589: if_icmple -> 5935
    //   5592: sipush #30575
    //   5595: sipush #16081
    //   5598: invokestatic a : (II)Ljava/lang/String;
    //   5601: iconst_1
    //   5602: ldc burp/Ze5t
    //   5604: invokevirtual getClassLoader : ()Ljava/lang/ClassLoader;
    //   5607: invokestatic forName : (Ljava/lang/String;ZLjava/lang/ClassLoader;)Ljava/lang/Class;
    //   5610: invokevirtual getDeclaredFields : ()[Ljava/lang/reflect/Field;
    //   5613: astore #7
    //   5615: aload #7
    //   5617: arraylength
    //   5618: istore #8
    //   5620: iconst_0
    //   5621: istore #9
    //   5623: iload #9
    //   5625: iload #8
    //   5627: if_icmpge -> 5765
    //   5630: aload #7
    //   5632: iload #9
    //   5634: aaload
    //   5635: astore #10
    //   5637: aload #10
    //   5639: invokevirtual getModifiers : ()I
    //   5642: invokestatic isStatic : (I)Z
    //   5645: ifne -> 5655
    //   5648: goto -> 5758
    //   5651: invokestatic a : (Ljava/lang/Throwable;)Ljava/lang/Throwable;
    //   5654: athrow
    //   5655: aload #10
    //   5657: invokevirtual getType : ()Ljava/lang/Class;
    //   5660: astore #11
    //   5662: aload #11
    //   5664: ifnull -> 5745
    //   5667: aload #11
    //   5669: invokevirtual isPrimitive : ()Z
    //   5672: ifne -> 5745
    //   5675: goto -> 5682
    //   5678: invokestatic a : (Ljava/lang/Throwable;)Ljava/lang/Throwable;
    //   5681: athrow
    //   5682: aload #11
    //   5684: invokevirtual getPackage : ()Ljava/lang/Package;
    //   5687: ifnull -> 5745
    //   5690: goto -> 5697
    //   5693: invokestatic a : (Ljava/lang/Throwable;)Ljava/lang/Throwable;
    //   5696: athrow
    //   5697: aload #11
    //   5699: invokevirtual getPackage : ()Ljava/lang/Package;
    //   5702: invokevirtual getName : ()Ljava/lang/String;
    //   5705: ifnull -> 5745
    //   5708: goto -> 5715
    //   5711: invokestatic a : (Ljava/lang/Throwable;)Ljava/lang/Throwable;
    //   5714: athrow
    //   5715: aload #11
    //   5717: invokevirtual getPackage : ()Ljava/lang/Package;
    //   5720: invokevirtual getName : ()Ljava/lang/String;
    //   5723: sipush #30582
    //   5726: sipush #13786
    //   5729: invokestatic a : (II)Ljava/lang/String;
    //   5732: invokevirtual startsWith : (Ljava/lang/String;)Z
    //   5735: ifne -> 5745
    //   5738: goto -> 5745
    //   5741: invokestatic a : (Ljava/lang/Throwable;)Ljava/lang/Throwable;
    //   5744: athrow
    //   5745: aload #10
    //   5747: iconst_1
    //   5748: invokevirtual setAccessible : (Z)V
    //   5751: aload #10
    //   5753: aconst_null
    //   5754: invokevirtual get : (Ljava/lang/Object;)Ljava/lang/Object;
    //   5757: pop
    //   5758: iinc #9, 1
    //   5761: iload_2
    //   5762: ifeq -> 5623
    //   5765: sipush #30575
    //   5768: sipush #16081
    //   5771: invokestatic a : (II)Ljava/lang/String;
    //   5774: invokestatic forName : (Ljava/lang/String;)Ljava/lang/Class;
    //   5777: invokevirtual getDeclaredMethods : ()[Ljava/lang/reflect/Method;
    //   5780: astore #7
    //   5782: aload #7
    //   5784: arraylength
    //   5785: istore #8
    //   5787: iconst_0
    //   5788: istore #9
    //   5790: iload #9
    //   5792: iload #8
    //   5794: if_icmpge -> 5931
    //   5797: aload #7
    //   5799: iload #9
    //   5801: aaload
    //   5802: astore #10
    //   5804: aload #10
    //   5806: invokevirtual getParameterTypes : ()[Ljava/lang/Class;
    //   5809: pop
    //   5810: aload #10
    //   5812: invokevirtual getModifiers : ()I
    //   5815: invokestatic isStatic : (I)Z
    //   5818: ifeq -> 5917
    //   5821: aload #10
    //   5823: invokevirtual getParameterTypes : ()[Ljava/lang/Class;
    //   5826: arraylength
    //   5827: iconst_2
    //   5828: if_icmpne -> 5917
    //   5831: goto -> 5838
    //   5834: invokestatic a : (Ljava/lang/Throwable;)Ljava/lang/Throwable;
    //   5837: athrow
    //   5838: aload #10
    //   5840: invokevirtual getReturnType : ()Ljava/lang/Class;
    //   5843: getstatic java/lang/Boolean.TYPE : Ljava/lang/Class;
    //   5846: if_acmpne -> 5917
    //   5849: goto -> 5856
    //   5852: invokestatic a : (Ljava/lang/Throwable;)Ljava/lang/Throwable;
    //   5855: athrow
    //   5856: aload #10
    //   5858: iconst_1
    //   5859: invokevirtual setAccessible : (Z)V
    //   5862: aload #10
    //   5864: aconst_null
    //   5865: iconst_2
    //   5866: anewarray java/lang/Object
    //   5869: dup
    //   5870: iconst_0
    //   5871: aload_0
    //   5872: aastore
    //   5873: dup
    //   5874: iconst_1
    //   5875: aload_1
    //   5876: ifnonnull -> 5894
    //   5879: goto -> 5886
    //   5882: invokestatic a : (Ljava/lang/Throwable;)Ljava/lang/Throwable;
    //   5885: athrow
    //   5886: aload_1
    //   5887: goto -> 5901
    //   5890: invokestatic a : (Ljava/lang/Throwable;)Ljava/lang/Throwable;
    //   5893: athrow
    //   5894: aload_1
    //   5895: checkcast [B
    //   5898: invokevirtual clone : ()Ljava/lang/Object;
    //   5901: aastore
    //   5902: invokevirtual invoke : (Ljava/lang/Object;[Ljava/lang/Object;)Ljava/lang/Object;
    //   5905: checkcast java/lang/Boolean
    //   5908: invokevirtual booleanValue : ()Z
    //   5911: istore #6
    //   5913: iload_2
    //   5914: ifeq -> 5931
    //   5917: iinc #9, 1
    //   5920: iload_2
    //   5921: ifeq -> 5790
    //   5924: goto -> 5931
    //   5927: invokestatic a : (Ljava/lang/Throwable;)Ljava/lang/Throwable;
    //   5930: athrow
    //   5931: iload_2
    //   5932: ifeq -> 6274
    //   5935: sipush #30580
    //   5938: sipush #-3036
    //   5941: invokestatic a : (II)Ljava/lang/String;
    //   5944: iconst_1
    //   5945: ldc burp/Zro2
    //   5947: invokevirtual getClassLoader : ()Ljava/lang/ClassLoader;
    //   5950: invokestatic forName : (Ljava/lang/String;ZLjava/lang/ClassLoader;)Ljava/lang/Class;
    //   5953: invokevirtual getDeclaredFields : ()[Ljava/lang/reflect/Field;
    //   5956: astore #7
    //   5958: aload #7
    //   5960: arraylength
    //   5961: istore #8
    //   5963: iconst_0
    //   5964: istore #9
    //   5966: iload #9
    //   5968: iload #8
    //   5970: if_icmpge -> 6108
    //   5973: aload #7
    //   5975: iload #9
    //   5977: aaload
    //   5978: astore #10
    //   5980: aload #10
    //   5982: invokevirtual getModifiers : ()I
    //   5985: invokestatic isStatic : (I)Z
    //   5988: ifne -> 5998
    //   5991: goto -> 6101
    //   5994: invokestatic a : (Ljava/lang/Throwable;)Ljava/lang/Throwable;
    //   5997: athrow
    //   5998: aload #10
    //   6000: invokevirtual getType : ()Ljava/lang/Class;
    //   6003: astore #11
    //   6005: aload #11
    //   6007: ifnull -> 6088
    //   6010: aload #11
    //   6012: invokevirtual isPrimitive : ()Z
    //   6015: ifne -> 6088
    //   6018: goto -> 6025
    //   6021: invokestatic a : (Ljava/lang/Throwable;)Ljava/lang/Throwable;
    //   6024: athrow
    //   6025: aload #11
    //   6027: invokevirtual getPackage : ()Ljava/lang/Package;
    //   6030: ifnull -> 6088
    //   6033: goto -> 6040
    //   6036: invokestatic a : (Ljava/lang/Throwable;)Ljava/lang/Throwable;
    //   6039: athrow
    //   6040: aload #11
    //   6042: invokevirtual getPackage : ()Ljava/lang/Package;
    //   6045: invokevirtual getName : ()Ljava/lang/String;
    //   6048: ifnull -> 6088
    //   6051: goto -> 6058
    //   6054: invokestatic a : (Ljava/lang/Throwable;)Ljava/lang/Throwable;
    //   6057: athrow
    //   6058: aload #11
    //   6060: invokevirtual getPackage : ()Ljava/lang/Package;
    //   6063: invokevirtual getName : ()Ljava/lang/String;
    //   6066: sipush #30582
    //   6069: sipush #13786
    //   6072: invokestatic a : (II)Ljava/lang/String;
    //   6075: invokevirtual startsWith : (Ljava/lang/String;)Z
    //   6078: ifne -> 6088
    //   6081: goto -> 6088
    //   6084: invokestatic a : (Ljava/lang/Throwable;)Ljava/lang/Throwable;
    //   6087: athrow
    //   6088: aload #10
    //   6090: iconst_1
    //   6091: invokevirtual setAccessible : (Z)V
    //   6094: aload #10
    //   6096: aconst_null
    //   6097: invokevirtual get : (Ljava/lang/Object;)Ljava/lang/Object;
    //   6100: pop
    //   6101: iinc #9, 1
    //   6104: iload_2
    //   6105: ifeq -> 5966
    //   6108: sipush #30583
    //   6111: sipush #24235
    //   6114: invokestatic a : (II)Ljava/lang/String;
    //   6117: invokestatic forName : (Ljava/lang/String;)Ljava/lang/Class;
    //   6120: invokevirtual getDeclaredMethods : ()[Ljava/lang/reflect/Method;
    //   6123: astore #7
    //   6125: aload #7
    //   6127: arraylength
    //   6128: istore #8
    //   6130: iconst_0
    //   6131: istore #9
    //   6133: iload #9
    //   6135: iload #8
    //   6137: if_icmpge -> 6274
    //   6140: aload #7
    //   6142: iload #9
    //   6144: aaload
    //   6145: astore #10
    //   6147: aload #10
    //   6149: invokevirtual getParameterTypes : ()[Ljava/lang/Class;
    //   6152: pop
    //   6153: aload #10
    //   6155: invokevirtual getModifiers : ()I
    //   6158: invokestatic isStatic : (I)Z
    //   6161: ifeq -> 6260
    //   6164: aload #10
    //   6166: invokevirtual getParameterTypes : ()[Ljava/lang/Class;
    //   6169: arraylength
    //   6170: iconst_2
    //   6171: if_icmpne -> 6260
    //   6174: goto -> 6181
    //   6177: invokestatic a : (Ljava/lang/Throwable;)Ljava/lang/Throwable;
    //   6180: athrow
    //   6181: aload #10
    //   6183: invokevirtual getReturnType : ()Ljava/lang/Class;
    //   6186: getstatic java/lang/Boolean.TYPE : Ljava/lang/Class;
    //   6189: if_acmpne -> 6260
    //   6192: goto -> 6199
    //   6195: invokestatic a : (Ljava/lang/Throwable;)Ljava/lang/Throwable;
    //   6198: athrow
    //   6199: aload #10
    //   6201: iconst_1
    //   6202: invokevirtual setAccessible : (Z)V
    //   6205: aload #10
    //   6207: aconst_null
    //   6208: iconst_2
    //   6209: anewarray java/lang/Object
    //   6212: dup
    //   6213: iconst_0
    //   6214: aload_0
    //   6215: aastore
    //   6216: dup
    //   6217: iconst_1
    //   6218: aload_1
    //   6219: ifnonnull -> 6237
    //   6222: goto -> 6229
    //   6225: invokestatic a : (Ljava/lang/Throwable;)Ljava/lang/Throwable;
    //   6228: athrow
    //   6229: aload_1
    //   6230: goto -> 6244
    //   6233: invokestatic a : (Ljava/lang/Throwable;)Ljava/lang/Throwable;
    //   6236: athrow
    //   6237: aload_1
    //   6238: checkcast [B
    //   6241: invokevirtual clone : ()Ljava/lang/Object;
    //   6244: aastore
    //   6245: invokevirtual invoke : (Ljava/lang/Object;[Ljava/lang/Object;)Ljava/lang/Object;
    //   6248: checkcast java/lang/Boolean
    //   6251: invokevirtual booleanValue : ()Z
    //   6254: istore #6
    //   6256: iload_2
    //   6257: ifeq -> 6274
    //   6260: iinc #9, 1
    //   6263: iload_2
    //   6264: ifeq -> 6133
    //   6267: goto -> 6274
    //   6270: invokestatic a : (Ljava/lang/Throwable;)Ljava/lang/Throwable;
    //   6273: athrow
    //   6274: iload #6
    //   6276: ifeq -> 6282
    //   6279: iload #6
    //   6281: ireturn
    //   6282: getstatic burp/Zlo2.ZJ : Ljava/lang/String;
    //   6285: getstatic burp/Zry0.Zr : Ljava/lang/Object;
    //   6288: checkcast java/math/BigInteger
    //   6291: invokevirtual intValue : ()I
    //   6294: bipush #32
    //   6296: irem
    //   6297: invokestatic abs : (I)I
    //   6300: invokevirtual charAt : (I)C
    //   6303: getstatic burp/Zmt7.Zl : Ljava/lang/String;
    //   6306: getstatic burp/Zeqo.ZZ : Ljava/lang/Object;
    //   6309: checkcast java/math/BigInteger
    //   6312: invokevirtual intValue : ()I
    //   6315: bipush #32
    //   6317: irem
    //   6318: invokestatic abs : (I)I
    //   6321: invokevirtual charAt : (I)C
    //   6324: if_icmpgt -> 6670
    //   6327: sipush #30590
    //   6330: sipush #28372
    //   6333: invokestatic a : (II)Ljava/lang/String;
    //   6336: iconst_1
    //   6337: ldc burp/Zgw_
    //   6339: invokevirtual getClassLoader : ()Ljava/lang/ClassLoader;
    //   6342: invokestatic forName : (Ljava/lang/String;ZLjava/lang/ClassLoader;)Ljava/lang/Class;
    //   6345: invokevirtual getDeclaredFields : ()[Ljava/lang/reflect/Field;
    //   6348: astore #7
    //   6350: aload #7
    //   6352: arraylength
    //   6353: istore #8
    //   6355: iconst_0
    //   6356: istore #9
    //   6358: iload #9
    //   6360: iload #8
    //   6362: if_icmpge -> 6500
    //   6365: aload #7
    //   6367: iload #9
    //   6369: aaload
    //   6370: astore #10
    //   6372: aload #10
    //   6374: invokevirtual getModifiers : ()I
    //   6377: invokestatic isStatic : (I)Z
    //   6380: ifne -> 6390
    //   6383: goto -> 6493
    //   6386: invokestatic a : (Ljava/lang/Throwable;)Ljava/lang/Throwable;
    //   6389: athrow
    //   6390: aload #10
    //   6392: invokevirtual getType : ()Ljava/lang/Class;
    //   6395: astore #11
    //   6397: aload #11
    //   6399: ifnull -> 6480
    //   6402: aload #11
    //   6404: invokevirtual isPrimitive : ()Z
    //   6407: ifne -> 6480
    //   6410: goto -> 6417
    //   6413: invokestatic a : (Ljava/lang/Throwable;)Ljava/lang/Throwable;
    //   6416: athrow
    //   6417: aload #11
    //   6419: invokevirtual getPackage : ()Ljava/lang/Package;
    //   6422: ifnull -> 6480
    //   6425: goto -> 6432
    //   6428: invokestatic a : (Ljava/lang/Throwable;)Ljava/lang/Throwable;
    //   6431: athrow
    //   6432: aload #11
    //   6434: invokevirtual getPackage : ()Ljava/lang/Package;
    //   6437: invokevirtual getName : ()Ljava/lang/String;
    //   6440: ifnull -> 6480
    //   6443: goto -> 6450
    //   6446: invokestatic a : (Ljava/lang/Throwable;)Ljava/lang/Throwable;
    //   6449: athrow
    //   6450: aload #11
    //   6452: invokevirtual getPackage : ()Ljava/lang/Package;
    //   6455: invokevirtual getName : ()Ljava/lang/String;
    //   6458: sipush #30582
    //   6461: sipush #13786
    //   6464: invokestatic a : (II)Ljava/lang/String;
    //   6467: invokevirtual startsWith : (Ljava/lang/String;)Z
    //   6470: ifne -> 6480
    //   6473: goto -> 6480
    //   6476: invokestatic a : (Ljava/lang/Throwable;)Ljava/lang/Throwable;
    //   6479: athrow
    //   6480: aload #10
    //   6482: iconst_1
    //   6483: invokevirtual setAccessible : (Z)V
    //   6486: aload #10
    //   6488: aconst_null
    //   6489: invokevirtual get : (Ljava/lang/Object;)Ljava/lang/Object;
    //   6492: pop
    //   6493: iinc #9, 1
    //   6496: iload_2
    //   6497: ifeq -> 6358
    //   6500: sipush #30585
    //   6503: sipush #-20771
    //   6506: invokestatic a : (II)Ljava/lang/String;
    //   6509: invokestatic forName : (Ljava/lang/String;)Ljava/lang/Class;
    //   6512: invokevirtual getDeclaredMethods : ()[Ljava/lang/reflect/Method;
    //   6515: astore #7
    //   6517: aload #7
    //   6519: arraylength
    //   6520: istore #8
    //   6522: iconst_0
    //   6523: istore #9
    //   6525: iload #9
    //   6527: iload #8
    //   6529: if_icmpge -> 6666
    //   6532: aload #7
    //   6534: iload #9
    //   6536: aaload
    //   6537: astore #10
    //   6539: aload #10
    //   6541: invokevirtual getParameterTypes : ()[Ljava/lang/Class;
    //   6544: pop
    //   6545: aload #10
    //   6547: invokevirtual getModifiers : ()I
    //   6550: invokestatic isStatic : (I)Z
    //   6553: ifeq -> 6652
    //   6556: aload #10
    //   6558: invokevirtual getParameterTypes : ()[Ljava/lang/Class;
    //   6561: arraylength
    //   6562: iconst_2
    //   6563: if_icmpne -> 6652
    //   6566: goto -> 6573
    //   6569: invokestatic a : (Ljava/lang/Throwable;)Ljava/lang/Throwable;
    //   6572: athrow
    //   6573: aload #10
    //   6575: invokevirtual getReturnType : ()Ljava/lang/Class;
    //   6578: getstatic java/lang/Boolean.TYPE : Ljava/lang/Class;
    //   6581: if_acmpne -> 6652
    //   6584: goto -> 6591
    //   6587: invokestatic a : (Ljava/lang/Throwable;)Ljava/lang/Throwable;
    //   6590: athrow
    //   6591: aload #10
    //   6593: iconst_1
    //   6594: invokevirtual setAccessible : (Z)V
    //   6597: aload #10
    //   6599: aconst_null
    //   6600: iconst_2
    //   6601: anewarray java/lang/Object
    //   6604: dup
    //   6605: iconst_0
    //   6606: aload_0
    //   6607: aastore
    //   6608: dup
    //   6609: iconst_1
    //   6610: aload_1
    //   6611: ifnonnull -> 6629
    //   6614: goto -> 6621
    //   6617: invokestatic a : (Ljava/lang/Throwable;)Ljava/lang/Throwable;
    //   6620: athrow
    //   6621: aload_1
    //   6622: goto -> 6636
    //   6625: invokestatic a : (Ljava/lang/Throwable;)Ljava/lang/Throwable;
    //   6628: athrow
    //   6629: aload_1
    //   6630: checkcast [B
    //   6633: invokevirtual clone : ()Ljava/lang/Object;
    //   6636: aastore
    //   6637: invokevirtual invoke : (Ljava/lang/Object;[Ljava/lang/Object;)Ljava/lang/Object;
    //   6640: checkcast java/lang/Boolean
    //   6643: invokevirtual booleanValue : ()Z
    //   6646: istore #6
    //   6648: iload_2
    //   6649: ifeq -> 6666
    //   6652: iinc #9, 1
    //   6655: iload_2
    //   6656: ifeq -> 6525
    //   6659: goto -> 6666
    //   6662: invokestatic a : (Ljava/lang/Throwable;)Ljava/lang/Throwable;
    //   6665: athrow
    //   6666: iload_2
    //   6667: ifeq -> 7009
    //   6670: sipush #30578
    //   6673: sipush #-29239
    //   6676: invokestatic a : (II)Ljava/lang/String;
    //   6679: iconst_1
    //   6680: ldc burp/Zkdc
    //   6682: invokevirtual getClassLoader : ()Ljava/lang/ClassLoader;
    //   6685: invokestatic forName : (Ljava/lang/String;ZLjava/lang/ClassLoader;)Ljava/lang/Class;
    //   6688: invokevirtual getDeclaredFields : ()[Ljava/lang/reflect/Field;
    //   6691: astore #7
    //   6693: aload #7
    //   6695: arraylength
    //   6696: istore #8
    //   6698: iconst_0
    //   6699: istore #9
    //   6701: iload #9
    //   6703: iload #8
    //   6705: if_icmpge -> 6843
    //   6708: aload #7
    //   6710: iload #9
    //   6712: aaload
    //   6713: astore #10
    //   6715: aload #10
    //   6717: invokevirtual getModifiers : ()I
    //   6720: invokestatic isStatic : (I)Z
    //   6723: ifne -> 6733
    //   6726: goto -> 6836
    //   6729: invokestatic a : (Ljava/lang/Throwable;)Ljava/lang/Throwable;
    //   6732: athrow
    //   6733: aload #10
    //   6735: invokevirtual getType : ()Ljava/lang/Class;
    //   6738: astore #11
    //   6740: aload #11
    //   6742: ifnull -> 6823
    //   6745: aload #11
    //   6747: invokevirtual isPrimitive : ()Z
    //   6750: ifne -> 6823
    //   6753: goto -> 6760
    //   6756: invokestatic a : (Ljava/lang/Throwable;)Ljava/lang/Throwable;
    //   6759: athrow
    //   6760: aload #11
    //   6762: invokevirtual getPackage : ()Ljava/lang/Package;
    //   6765: ifnull -> 6823
    //   6768: goto -> 6775
    //   6771: invokestatic a : (Ljava/lang/Throwable;)Ljava/lang/Throwable;
    //   6774: athrow
    //   6775: aload #11
    //   6777: invokevirtual getPackage : ()Ljava/lang/Package;
    //   6780: invokevirtual getName : ()Ljava/lang/String;
    //   6783: ifnull -> 6823
    //   6786: goto -> 6793
    //   6789: invokestatic a : (Ljava/lang/Throwable;)Ljava/lang/Throwable;
    //   6792: athrow
    //   6793: aload #11
    //   6795: invokevirtual getPackage : ()Ljava/lang/Package;
    //   6798: invokevirtual getName : ()Ljava/lang/String;
    //   6801: sipush #30582
    //   6804: sipush #13786
    //   6807: invokestatic a : (II)Ljava/lang/String;
    //   6810: invokevirtual startsWith : (Ljava/lang/String;)Z
    //   6813: ifne -> 6823
    //   6816: goto -> 6823
    //   6819: invokestatic a : (Ljava/lang/Throwable;)Ljava/lang/Throwable;
    //   6822: athrow
    //   6823: aload #10
    //   6825: iconst_1
    //   6826: invokevirtual setAccessible : (Z)V
    //   6829: aload #10
    //   6831: aconst_null
    //   6832: invokevirtual get : (Ljava/lang/Object;)Ljava/lang/Object;
    //   6835: pop
    //   6836: iinc #9, 1
    //   6839: iload_2
    //   6840: ifeq -> 6701
    //   6843: sipush #30565
    //   6846: sipush #-9681
    //   6849: invokestatic a : (II)Ljava/lang/String;
    //   6852: invokestatic forName : (Ljava/lang/String;)Ljava/lang/Class;
    //   6855: invokevirtual getDeclaredMethods : ()[Ljava/lang/reflect/Method;
    //   6858: astore #7
    //   6860: aload #7
    //   6862: arraylength
    //   6863: istore #8
    //   6865: iconst_0
    //   6866: istore #9
    //   6868: iload #9
    //   6870: iload #8
    //   6872: if_icmpge -> 7009
    //   6875: aload #7
    //   6877: iload #9
    //   6879: aaload
    //   6880: astore #10
    //   6882: aload #10
    //   6884: invokevirtual getParameterTypes : ()[Ljava/lang/Class;
    //   6887: pop
    //   6888: aload #10
    //   6890: invokevirtual getModifiers : ()I
    //   6893: invokestatic isStatic : (I)Z
    //   6896: ifeq -> 6995
    //   6899: aload #10
    //   6901: invokevirtual getParameterTypes : ()[Ljava/lang/Class;
    //   6904: arraylength
    //   6905: iconst_2
    //   6906: if_icmpne -> 6995
    //   6909: goto -> 6916
    //   6912: invokestatic a : (Ljava/lang/Throwable;)Ljava/lang/Throwable;
    //   6915: athrow
    //   6916: aload #10
    //   6918: invokevirtual getReturnType : ()Ljava/lang/Class;
    //   6921: getstatic java/lang/Boolean.TYPE : Ljava/lang/Class;
    //   6924: if_acmpne -> 6995
    //   6927: goto -> 6934
    //   6930: invokestatic a : (Ljava/lang/Throwable;)Ljava/lang/Throwable;
    //   6933: athrow
    //   6934: aload #10
    //   6936: iconst_1
    //   6937: invokevirtual setAccessible : (Z)V
    //   6940: aload #10
    //   6942: aconst_null
    //   6943: iconst_2
    //   6944: anewarray java/lang/Object
    //   6947: dup
    //   6948: iconst_0
    //   6949: aload_0
    //   6950: aastore
    //   6951: dup
    //   6952: iconst_1
    //   6953: aload_1
    //   6954: ifnonnull -> 6972
    //   6957: goto -> 6964
    //   6960: invokestatic a : (Ljava/lang/Throwable;)Ljava/lang/Throwable;
    //   6963: athrow
    //   6964: aload_1
    //   6965: goto -> 6979
    //   6968: invokestatic a : (Ljava/lang/Throwable;)Ljava/lang/Throwable;
    //   6971: athrow
    //   6972: aload_1
    //   6973: checkcast [B
    //   6976: invokevirtual clone : ()Ljava/lang/Object;
    //   6979: aastore
    //   6980: invokevirtual invoke : (Ljava/lang/Object;[Ljava/lang/Object;)Ljava/lang/Object;
    //   6983: checkcast java/lang/Boolean
    //   6986: invokevirtual booleanValue : ()Z
    //   6989: istore #6
    //   6991: iload_2
    //   6992: ifeq -> 7009
    //   6995: iinc #9, 1
    //   6998: iload_2
    //   6999: ifeq -> 6868
    //   7002: goto -> 7009
    //   7005: invokestatic a : (Ljava/lang/Throwable;)Ljava/lang/Throwable;
    //   7008: athrow
    //   7009: iload #6
    //   7011: ifeq -> 7017
    //   7014: iload #6
    //   7016: ireturn
    //   7017: getstatic burp/Ztdx.Zl : Ljava/lang/String;
    //   7020: getstatic burp/Zgta.ZF : Ljava/lang/Object;
    //   7023: checkcast java/math/BigInteger
    //   7026: invokevirtual intValue : ()I
    //   7029: bipush #32
    //   7031: irem
    //   7032: invokestatic abs : (I)I
    //   7035: invokevirtual charAt : (I)C
    //   7038: getstatic burp/Zlnq.ZQ : Ljava/lang/String;
    //   7041: getstatic burp/Zss6.ZG : Ljava/lang/Object;
    //   7044: checkcast java/math/BigInteger
    //   7047: invokevirtual intValue : ()I
    //   7050: bipush #32
    //   7052: irem
    //   7053: invokestatic abs : (I)I
    //   7056: invokevirtual charAt : (I)C
    //   7059: if_icmple -> 7405
    //   7062: sipush #30571
    //   7065: sipush #14504
    //   7068: invokestatic a : (II)Ljava/lang/String;
    //   7071: iconst_1
    //   7072: ldc burp/Zr4z
    //   7074: invokevirtual getClassLoader : ()Ljava/lang/ClassLoader;
    //   7077: invokestatic forName : (Ljava/lang/String;ZLjava/lang/ClassLoader;)Ljava/lang/Class;
    //   7080: invokevirtual getDeclaredFields : ()[Ljava/lang/reflect/Field;
    //   7083: astore #7
    //   7085: aload #7
    //   7087: arraylength
    //   7088: istore #8
    //   7090: iconst_0
    //   7091: istore #9
    //   7093: iload #9
    //   7095: iload #8
    //   7097: if_icmpge -> 7235
    //   7100: aload #7
    //   7102: iload #9
    //   7104: aaload
    //   7105: astore #10
    //   7107: aload #10
    //   7109: invokevirtual getModifiers : ()I
    //   7112: invokestatic isStatic : (I)Z
    //   7115: ifne -> 7125
    //   7118: goto -> 7228
    //   7121: invokestatic a : (Ljava/lang/Throwable;)Ljava/lang/Throwable;
    //   7124: athrow
    //   7125: aload #10
    //   7127: invokevirtual getType : ()Ljava/lang/Class;
    //   7130: astore #11
    //   7132: aload #11
    //   7134: ifnull -> 7215
    //   7137: aload #11
    //   7139: invokevirtual isPrimitive : ()Z
    //   7142: ifne -> 7215
    //   7145: goto -> 7152
    //   7148: invokestatic a : (Ljava/lang/Throwable;)Ljava/lang/Throwable;
    //   7151: athrow
    //   7152: aload #11
    //   7154: invokevirtual getPackage : ()Ljava/lang/Package;
    //   7157: ifnull -> 7215
    //   7160: goto -> 7167
    //   7163: invokestatic a : (Ljava/lang/Throwable;)Ljava/lang/Throwable;
    //   7166: athrow
    //   7167: aload #11
    //   7169: invokevirtual getPackage : ()Ljava/lang/Package;
    //   7172: invokevirtual getName : ()Ljava/lang/String;
    //   7175: ifnull -> 7215
    //   7178: goto -> 7185
    //   7181: invokestatic a : (Ljava/lang/Throwable;)Ljava/lang/Throwable;
    //   7184: athrow
    //   7185: aload #11
    //   7187: invokevirtual getPackage : ()Ljava/lang/Package;
    //   7190: invokevirtual getName : ()Ljava/lang/String;
    //   7193: sipush #30582
    //   7196: sipush #13786
    //   7199: invokestatic a : (II)Ljava/lang/String;
    //   7202: invokevirtual startsWith : (Ljava/lang/String;)Z
    //   7205: ifne -> 7215
    //   7208: goto -> 7215
    //   7211: invokestatic a : (Ljava/lang/Throwable;)Ljava/lang/Throwable;
    //   7214: athrow
    //   7215: aload #10
    //   7217: iconst_1
    //   7218: invokevirtual setAccessible : (Z)V
    //   7221: aload #10
    //   7223: aconst_null
    //   7224: invokevirtual get : (Ljava/lang/Object;)Ljava/lang/Object;
    //   7227: pop
    //   7228: iinc #9, 1
    //   7231: iload_2
    //   7232: ifeq -> 7093
    //   7235: sipush #30588
    //   7238: sipush #-7947
    //   7241: invokestatic a : (II)Ljava/lang/String;
    //   7244: invokestatic forName : (Ljava/lang/String;)Ljava/lang/Class;
    //   7247: invokevirtual getDeclaredMethods : ()[Ljava/lang/reflect/Method;
    //   7250: astore #7
    //   7252: aload #7
    //   7254: arraylength
    //   7255: istore #8
    //   7257: iconst_0
    //   7258: istore #9
    //   7260: iload #9
    //   7262: iload #8
    //   7264: if_icmpge -> 7401
    //   7267: aload #7
    //   7269: iload #9
    //   7271: aaload
    //   7272: astore #10
    //   7274: aload #10
    //   7276: invokevirtual getParameterTypes : ()[Ljava/lang/Class;
    //   7279: pop
    //   7280: aload #10
    //   7282: invokevirtual getModifiers : ()I
    //   7285: invokestatic isStatic : (I)Z
    //   7288: ifeq -> 7387
    //   7291: aload #10
    //   7293: invokevirtual getParameterTypes : ()[Ljava/lang/Class;
    //   7296: arraylength
    //   7297: iconst_2
    //   7298: if_icmpne -> 7387
    //   7301: goto -> 7308
    //   7304: invokestatic a : (Ljava/lang/Throwable;)Ljava/lang/Throwable;
    //   7307: athrow
    //   7308: aload #10
    //   7310: invokevirtual getReturnType : ()Ljava/lang/Class;
    //   7313: getstatic java/lang/Boolean.TYPE : Ljava/lang/Class;
    //   7316: if_acmpne -> 7387
    //   7319: goto -> 7326
    //   7322: invokestatic a : (Ljava/lang/Throwable;)Ljava/lang/Throwable;
    //   7325: athrow
    //   7326: aload #10
    //   7328: iconst_1
    //   7329: invokevirtual setAccessible : (Z)V
    //   7332: aload #10
    //   7334: aconst_null
    //   7335: iconst_2
    //   7336: anewarray java/lang/Object
    //   7339: dup
    //   7340: iconst_0
    //   7341: aload_0
    //   7342: aastore
    //   7343: dup
    //   7344: iconst_1
    //   7345: aload_1
    //   7346: ifnonnull -> 7364
    //   7349: goto -> 7356
    //   7352: invokestatic a : (Ljava/lang/Throwable;)Ljava/lang/Throwable;
    //   7355: athrow
    //   7356: aload_1
    //   7357: goto -> 7371
    //   7360: invokestatic a : (Ljava/lang/Throwable;)Ljava/lang/Throwable;
    //   7363: athrow
    //   7364: aload_1
    //   7365: checkcast [B
    //   7368: invokevirtual clone : ()Ljava/lang/Object;
    //   7371: aastore
    //   7372: invokevirtual invoke : (Ljava/lang/Object;[Ljava/lang/Object;)Ljava/lang/Object;
    //   7375: checkcast java/lang/Boolean
    //   7378: invokevirtual booleanValue : ()Z
    //   7381: istore #6
    //   7383: iload_2
    //   7384: ifeq -> 7401
    //   7387: iinc #9, 1
    //   7390: iload_2
    //   7391: ifeq -> 7260
    //   7394: goto -> 7401
    //   7397: invokestatic a : (Ljava/lang/Throwable;)Ljava/lang/Throwable;
    //   7400: athrow
    //   7401: iload_2
    //   7402: ifeq -> 7744
    //   7405: sipush #30573
    //   7408: sipush #-17168
    //   7411: invokestatic a : (II)Ljava/lang/String;
    //   7414: iconst_1
    //   7415: ldc burp/Ztzw
    //   7417: invokevirtual getClassLoader : ()Ljava/lang/ClassLoader;
    //   7420: invokestatic forName : (Ljava/lang/String;ZLjava/lang/ClassLoader;)Ljava/lang/Class;
    //   7423: invokevirtual getDeclaredFields : ()[Ljava/lang/reflect/Field;
    //   7426: astore #7
    //   7428: aload #7
    //   7430: arraylength
    //   7431: istore #8
    //   7433: iconst_0
    //   7434: istore #9
    //   7436: iload #9
    //   7438: iload #8
    //   7440: if_icmpge -> 7578
    //   7443: aload #7
    //   7445: iload #9
    //   7447: aaload
    //   7448: astore #10
    //   7450: aload #10
    //   7452: invokevirtual getModifiers : ()I
    //   7455: invokestatic isStatic : (I)Z
    //   7458: ifne -> 7468
    //   7461: goto -> 7571
    //   7464: invokestatic a : (Ljava/lang/Throwable;)Ljava/lang/Throwable;
    //   7467: athrow
    //   7468: aload #10
    //   7470: invokevirtual getType : ()Ljava/lang/Class;
    //   7473: astore #11
    //   7475: aload #11
    //   7477: ifnull -> 7558
    //   7480: aload #11
    //   7482: invokevirtual isPrimitive : ()Z
    //   7485: ifne -> 7558
    //   7488: goto -> 7495
    //   7491: invokestatic a : (Ljava/lang/Throwable;)Ljava/lang/Throwable;
    //   7494: athrow
    //   7495: aload #11
    //   7497: invokevirtual getPackage : ()Ljava/lang/Package;
    //   7500: ifnull -> 7558
    //   7503: goto -> 7510
    //   7506: invokestatic a : (Ljava/lang/Throwable;)Ljava/lang/Throwable;
    //   7509: athrow
    //   7510: aload #11
    //   7512: invokevirtual getPackage : ()Ljava/lang/Package;
    //   7515: invokevirtual getName : ()Ljava/lang/String;
    //   7518: ifnull -> 7558
    //   7521: goto -> 7528
    //   7524: invokestatic a : (Ljava/lang/Throwable;)Ljava/lang/Throwable;
    //   7527: athrow
    //   7528: aload #11
    //   7530: invokevirtual getPackage : ()Ljava/lang/Package;
    //   7533: invokevirtual getName : ()Ljava/lang/String;
    //   7536: sipush #30582
    //   7539: sipush #13786
    //   7542: invokestatic a : (II)Ljava/lang/String;
    //   7545: invokevirtual startsWith : (Ljava/lang/String;)Z
    //   7548: ifne -> 7558
    //   7551: goto -> 7558
    //   7554: invokestatic a : (Ljava/lang/Throwable;)Ljava/lang/Throwable;
    //   7557: athrow
    //   7558: aload #10
    //   7560: iconst_1
    //   7561: invokevirtual setAccessible : (Z)V
    //   7564: aload #10
    //   7566: aconst_null
    //   7567: invokevirtual get : (Ljava/lang/Object;)Ljava/lang/Object;
    //   7570: pop
    //   7571: iinc #9, 1
    //   7574: iload_2
    //   7575: ifeq -> 7436
    //   7578: sipush #30574
    //   7581: sipush #-2988
    //   7584: invokestatic a : (II)Ljava/lang/String;
    //   7587: invokestatic forName : (Ljava/lang/String;)Ljava/lang/Class;
    //   7590: invokevirtual getDeclaredMethods : ()[Ljava/lang/reflect/Method;
    //   7593: astore #7
    //   7595: aload #7
    //   7597: arraylength
    //   7598: istore #8
    //   7600: iconst_0
    //   7601: istore #9
    //   7603: iload #9
    //   7605: iload #8
    //   7607: if_icmpge -> 7744
    //   7610: aload #7
    //   7612: iload #9
    //   7614: aaload
    //   7615: astore #10
    //   7617: aload #10
    //   7619: invokevirtual getParameterTypes : ()[Ljava/lang/Class;
    //   7622: pop
    //   7623: aload #10
    //   7625: invokevirtual getModifiers : ()I
    //   7628: invokestatic isStatic : (I)Z
    //   7631: ifeq -> 7730
    //   7634: aload #10
    //   7636: invokevirtual getParameterTypes : ()[Ljava/lang/Class;
    //   7639: arraylength
    //   7640: iconst_2
    //   7641: if_icmpne -> 7730
    //   7644: goto -> 7651
    //   7647: invokestatic a : (Ljava/lang/Throwable;)Ljava/lang/Throwable;
    //   7650: athrow
    //   7651: aload #10
    //   7653: invokevirtual getReturnType : ()Ljava/lang/Class;
    //   7656: getstatic java/lang/Boolean.TYPE : Ljava/lang/Class;
    //   7659: if_acmpne -> 7730
    //   7662: goto -> 7669
    //   7665: invokestatic a : (Ljava/lang/Throwable;)Ljava/lang/Throwable;
    //   7668: athrow
    //   7669: aload #10
    //   7671: iconst_1
    //   7672: invokevirtual setAccessible : (Z)V
    //   7675: aload #10
    //   7677: aconst_null
    //   7678: iconst_2
    //   7679: anewarray java/lang/Object
    //   7682: dup
    //   7683: iconst_0
    //   7684: aload_0
    //   7685: aastore
    //   7686: dup
    //   7687: iconst_1
    //   7688: aload_1
    //   7689: ifnonnull -> 7707
    //   7692: goto -> 7699
    //   7695: invokestatic a : (Ljava/lang/Throwable;)Ljava/lang/Throwable;
    //   7698: athrow
    //   7699: aload_1
    //   7700: goto -> 7714
    //   7703: invokestatic a : (Ljava/lang/Throwable;)Ljava/lang/Throwable;
    //   7706: athrow
    //   7707: aload_1
    //   7708: checkcast [B
    //   7711: invokevirtual clone : ()Ljava/lang/Object;
    //   7714: aastore
    //   7715: invokevirtual invoke : (Ljava/lang/Object;[Ljava/lang/Object;)Ljava/lang/Object;
    //   7718: checkcast java/lang/Boolean
    //   7721: invokevirtual booleanValue : ()Z
    //   7724: istore #6
    //   7726: iload_2
    //   7727: ifeq -> 7744
    //   7730: iinc #9, 1
    //   7733: iload_2
    //   7734: ifeq -> 7603
    //   7737: goto -> 7744
    //   7740: invokestatic a : (Ljava/lang/Throwable;)Ljava/lang/Throwable;
    //   7743: athrow
    //   7744: iload #6
    //   7746: ireturn
    //   7747: astore_3
    //   7748: new java/lang/Exception
    //   7751: dup
    //   7752: aload_3
    //   7753: invokevirtual getMessage : ()Ljava/lang/String;
    //   7756: invokespecial <init> : (Ljava/lang/String;)V
    //   7759: athrow
    // Exception table:
    //   from	to	target	type
    //   4	5546	7747	java/lang/Throwable
    //   22	198	201	java/lang/Throwable
    //   168	235	238	java/lang/Throwable
    //   205	272	275	java/lang/Throwable
    //   242	309	312	java/lang/Throwable
    //   279	346	349	java/lang/Throwable
    //   316	383	386	java/lang/Throwable
    //   353	420	423	java/lang/Throwable
    //   390	457	460	java/lang/Throwable
    //   427	494	497	java/lang/Throwable
    //   464	531	534	java/lang/Throwable
    //   501	568	571	java/lang/Throwable
    //   538	605	608	java/lang/Throwable
    //   575	642	645	java/lang/Throwable
    //   612	679	682	java/lang/Throwable
    //   649	716	719	java/lang/Throwable
    //   686	753	756	java/lang/Throwable
    //   723	790	793	java/lang/Throwable
    //   760	827	830	java/lang/Throwable
    //   797	864	867	java/lang/Throwable
    //   834	901	904	java/lang/Throwable
    //   871	938	941	java/lang/Throwable
    //   908	975	978	java/lang/Throwable
    //   945	1012	1015	java/lang/Throwable
    //   982	1049	1052	java/lang/Throwable
    //   1019	1086	1089	java/lang/Throwable
    //   1056	1123	1126	java/lang/Throwable
    //   1093	1160	1163	java/lang/Throwable
    //   1130	1197	1200	java/lang/Throwable
    //   1167	1234	1237	java/lang/Throwable
    //   1204	1271	1274	java/lang/Throwable
    //   1241	1308	1311	java/lang/Throwable
    //   1278	1341	1344	java/lang/Throwable
    //   1381	1555	1558	java/lang/Throwable
    //   1524	1593	1596	java/lang/Throwable
    //   1562	1631	1634	java/lang/Throwable
    //   1600	1669	1672	java/lang/Throwable
    //   1638	1707	1710	java/lang/Throwable
    //   1676	1745	1748	java/lang/Throwable
    //   1714	1783	1786	java/lang/Throwable
    //   1752	1821	1824	java/lang/Throwable
    //   1790	1859	1862	java/lang/Throwable
    //   1828	1897	1900	java/lang/Throwable
    //   1866	1935	1938	java/lang/Throwable
    //   1904	1973	1976	java/lang/Throwable
    //   1942	2011	2014	java/lang/Throwable
    //   1980	2049	2052	java/lang/Throwable
    //   2018	2087	2090	java/lang/Throwable
    //   2056	2125	2128	java/lang/Throwable
    //   2094	2163	2166	java/lang/Throwable
    //   2132	2201	2204	java/lang/Throwable
    //   2170	2239	2242	java/lang/Throwable
    //   2208	2277	2280	java/lang/Throwable
    //   2246	2315	2318	java/lang/Throwable
    //   2284	2353	2356	java/lang/Throwable
    //   2322	2391	2394	java/lang/Throwable
    //   2360	2429	2432	java/lang/Throwable
    //   2398	2467	2470	java/lang/Throwable
    //   2436	2505	2508	java/lang/Throwable
    //   2474	2543	2546	java/lang/Throwable
    //   2512	2581	2584	java/lang/Throwable
    //   2550	2619	2622	java/lang/Throwable
    //   2588	2657	2660	java/lang/Throwable
    //   2626	2695	2698	java/lang/Throwable
    //   2664	2729	2732	java/lang/Throwable
    //   2770	2947	2950	java/lang/Throwable
    //   2916	2985	2988	java/lang/Throwable
    //   2954	3023	3026	java/lang/Throwable
    //   2992	3061	3064	java/lang/Throwable
    //   3030	3099	3102	java/lang/Throwable
    //   3068	3137	3140	java/lang/Throwable
    //   3106	3175	3178	java/lang/Throwable
    //   3144	3213	3216	java/lang/Throwable
    //   3182	3251	3254	java/lang/Throwable
    //   3220	3289	3292	java/lang/Throwable
    //   3258	3327	3330	java/lang/Throwable
    //   3296	3365	3368	java/lang/Throwable
    //   3334	3403	3406	java/lang/Throwable
    //   3372	3441	3444	java/lang/Throwable
    //   3410	3479	3482	java/lang/Throwable
    //   3448	3517	3520	java/lang/Throwable
    //   3486	3555	3558	java/lang/Throwable
    //   3524	3593	3596	java/lang/Throwable
    //   3562	3631	3634	java/lang/Throwable
    //   3600	3669	3672	java/lang/Throwable
    //   3638	3707	3710	java/lang/Throwable
    //   3676	3745	3748	java/lang/Throwable
    //   3714	3783	3786	java/lang/Throwable
    //   3752	3821	3824	java/lang/Throwable
    //   3790	3859	3862	java/lang/Throwable
    //   3828	3897	3900	java/lang/Throwable
    //   3866	3935	3938	java/lang/Throwable
    //   3904	3973	3976	java/lang/Throwable
    //   3942	4011	4014	java/lang/Throwable
    //   3980	4049	4052	java/lang/Throwable
    //   4018	4087	4090	java/lang/Throwable
    //   4056	4121	4124	java/lang/Throwable
    //   4188	4202	4202	java/lang/Throwable
    //   4213	4226	4229	java/lang/Throwable
    //   4218	4241	4244	java/lang/Throwable
    //   4233	4259	4262	java/lang/Throwable
    //   4248	4289	4292	java/lang/Throwable
    //   4355	4382	4385	java/lang/Throwable
    //   4372	4400	4403	java/lang/Throwable
    //   4389	4430	4433	java/lang/Throwable
    //   4407	4441	4441	java/lang/Throwable
    //   4452	4468	4471	java/lang/Throwable
    //   4520	4534	4534	java/lang/Throwable
    //   4545	4558	4561	java/lang/Throwable
    //   4550	4573	4576	java/lang/Throwable
    //   4565	4591	4594	java/lang/Throwable
    //   4580	4621	4624	java/lang/Throwable
    //   4687	4714	4717	java/lang/Throwable
    //   4704	4735	4738	java/lang/Throwable
    //   4721	4765	4768	java/lang/Throwable
    //   4742	4776	4776	java/lang/Throwable
    //   4787	4803	4806	java/lang/Throwable
    //   4903	4917	4917	java/lang/Throwable
    //   4928	4941	4944	java/lang/Throwable
    //   4933	4956	4959	java/lang/Throwable
    //   4948	4974	4977	java/lang/Throwable
    //   4963	5004	5007	java/lang/Throwable
    //   5070	5097	5100	java/lang/Throwable
    //   5087	5115	5118	java/lang/Throwable
    //   5104	5145	5148	java/lang/Throwable
    //   5122	5156	5156	java/lang/Throwable
    //   5179	5190	5193	java/lang/Throwable
    //   5245	5259	5259	java/lang/Throwable
    //   5270	5283	5286	java/lang/Throwable
    //   5275	5298	5301	java/lang/Throwable
    //   5290	5316	5319	java/lang/Throwable
    //   5305	5346	5349	java/lang/Throwable
    //   5412	5439	5442	java/lang/Throwable
    //   5429	5457	5460	java/lang/Throwable
    //   5446	5487	5490	java/lang/Throwable
    //   5464	5498	5498	java/lang/Throwable
    //   5521	5532	5535	java/lang/Throwable
    //   5547	6281	7747	java/lang/Throwable
    //   5637	5651	5651	java/lang/Throwable
    //   5662	5675	5678	java/lang/Throwable
    //   5667	5690	5693	java/lang/Throwable
    //   5682	5708	5711	java/lang/Throwable
    //   5697	5738	5741	java/lang/Throwable
    //   5804	5831	5834	java/lang/Throwable
    //   5821	5849	5852	java/lang/Throwable
    //   5838	5879	5882	java/lang/Throwable
    //   5856	5890	5890	java/lang/Throwable
    //   5913	5924	5927	java/lang/Throwable
    //   5980	5994	5994	java/lang/Throwable
    //   6005	6018	6021	java/lang/Throwable
    //   6010	6033	6036	java/lang/Throwable
    //   6025	6051	6054	java/lang/Throwable
    //   6040	6081	6084	java/lang/Throwable
    //   6147	6174	6177	java/lang/Throwable
    //   6164	6192	6195	java/lang/Throwable
    //   6181	6222	6225	java/lang/Throwable
    //   6199	6233	6233	java/lang/Throwable
    //   6256	6267	6270	java/lang/Throwable
    //   6282	7016	7747	java/lang/Throwable
    //   6372	6386	6386	java/lang/Throwable
    //   6397	6410	6413	java/lang/Throwable
    //   6402	6425	6428	java/lang/Throwable
    //   6417	6443	6446	java/lang/Throwable
    //   6432	6473	6476	java/lang/Throwable
    //   6539	6566	6569	java/lang/Throwable
    //   6556	6584	6587	java/lang/Throwable
    //   6573	6614	6617	java/lang/Throwable
    //   6591	6625	6625	java/lang/Throwable
    //   6648	6659	6662	java/lang/Throwable
    //   6715	6729	6729	java/lang/Throwable
    //   6740	6753	6756	java/lang/Throwable
    //   6745	6768	6771	java/lang/Throwable
    //   6760	6786	6789	java/lang/Throwable
    //   6775	6816	6819	java/lang/Throwable
    //   6882	6909	6912	java/lang/Throwable
    //   6899	6927	6930	java/lang/Throwable
    //   6916	6957	6960	java/lang/Throwable
    //   6934	6968	6968	java/lang/Throwable
    //   6991	7002	7005	java/lang/Throwable
    //   7017	7746	7747	java/lang/Throwable
    //   7107	7121	7121	java/lang/Throwable
    //   7132	7145	7148	java/lang/Throwable
    //   7137	7160	7163	java/lang/Throwable
    //   7152	7178	7181	java/lang/Throwable
    //   7167	7208	7211	java/lang/Throwable
    //   7274	7301	7304	java/lang/Throwable
    //   7291	7319	7322	java/lang/Throwable
    //   7308	7349	7352	java/lang/Throwable
    //   7326	7360	7360	java/lang/Throwable
    //   7383	7394	7397	java/lang/Throwable
    //   7450	7464	7464	java/lang/Throwable
    //   7475	7488	7491	java/lang/Throwable
    //   7480	7503	7506	java/lang/Throwable
    //   7495	7521	7524	java/lang/Throwable
    //   7510	7551	7554	java/lang/Throwable
    //   7617	7644	7647	java/lang/Throwable
    //   7634	7662	7665	java/lang/Throwable
    //   7651	7692	7695	java/lang/Throwable
    //   7669	7703	7703	java/lang/Throwable
    //   7726	7737	7740	java/lang/Throwable
  }
  
  static {
    // Byte code:
    //   0: bipush #26
    //   2: anewarray java/lang/String
    //   5: astore #5
    //   7: iconst_0
    //   8: istore_3
    //   9: ldc 'R@(j1\\t\\tH\\b\\tf|$\\tg\+[`<\\tV/RiL\\tf9;\\tH=U\\t\\rK@~\\t ll\\t\\t"H%np\\t-$9w/\\tBF}2\\t;x\\tL9E\\tB!V\\t\\t\\nPz\\tp.B \\tkM4 J<v'"`\\fwLF\\t\\r@k$\\t fD @C?_l _oh7FL'
    //   11: dup
    //   12: astore_2
    //   13: invokevirtual length : ()I
    //   16: istore #4
    //   18: bipush #9
    //   20: istore_1
    //   21: iconst_m1
    //   22: istore_0
    //   23: bipush #41
    //   25: iinc #0, 1
    //   28: aload_2
    //   29: iload_0
    //   30: dup
    //   31: iload_1
    //   32: iadd
    //   33: invokevirtual substring : (II)Ljava/lang/String;
    //   36: iconst_m1
    //   37: goto -> 143
    //   40: aload #5
    //   42: swap
    //   43: iload_3
    //   44: iinc #3, 1
    //   47: swap
    //   48: aastore
    //   49: iload_0
    //   50: iload_1
    //   51: iadd
    //   52: dup
    //   53: istore_0
    //   54: iload #4
    //   56: if_icmpge -> 68
    //   59: aload_2
    //   60: iload_0
    //   61: invokevirtual charAt : (I)C
    //   64: istore_1
    //   65: goto -> 23
    //   68: ldc '2HM|Q\\nw)1I]C\\r8bcyR]y6P6f%@9K\\b\\n'
    //   70: dup
    //   71: astore_2
    //   72: invokevirtual length : ()I
    //   75: istore #4
    //   77: bipush #9
    //   79: istore_1
    //   80: iconst_m1
    //   81: istore_0
    //   82: bipush #90
    //   84: iinc #0, 1
    //   87: aload_2
    //   88: iload_0
    //   89: dup
    //   90: iload_1
    //   91: iadd
    //   92: invokevirtual substring : (II)Ljava/lang/String;
    //   95: iconst_0
    //   96: goto -> 143
    //   99: aload #5
    //   101: swap
    //   102: iload_3
    //   103: iinc #3, 1
    //   106: swap
    //   107: aastore
    //   108: iload_0
    //   109: iload_1
    //   110: iadd
    //   111: dup
    //   112: istore_0
    //   113: iload #4
    //   115: if_icmpge -> 127
    //   118: aload_2
    //   119: iload_0
    //   120: invokevirtual charAt : (I)C
    //   123: istore_1
    //   124: goto -> 82
    //   127: aload #5
    //   129: putstatic burp/Zzrb.a : [Ljava/lang/String;
    //   132: bipush #26
    //   134: anewarray java/lang/String
    //   137: putstatic burp/Zzrb.b : [Ljava/lang/String;
    //   140: goto -> 300
    //   143: dup_x2
    //   144: pop
    //   145: invokevirtual toCharArray : ()[C
    //   148: dup_x1
    //   149: arraylength
    //   150: dup_x2
    //   151: pop
    //   152: iconst_0
    //   153: istore #6
    //   155: dup2_x1
    //   156: pop2
    //   157: dup_x2
    //   158: iconst_1
    //   159: if_icmpgt -> 260
    //   162: dup2
    //   163: swap
    //   164: iload #6
    //   166: dup2_x1
    //   167: caload
    //   168: swap
    //   169: iload #6
    //   171: bipush #7
    //   173: irem
    //   174: tableswitch default -> 242, 0 -> 212, 1 -> 217, 2 -> 222, 3 -> 227, 4 -> 232, 5 -> 237
    //   212: bipush #29
    //   214: goto -> 244
    //   217: bipush #35
    //   219: goto -> 244
    //   222: bipush #67
    //   224: goto -> 244
    //   227: bipush #126
    //   229: goto -> 244
    //   232: bipush #20
    //   234: goto -> 244
    //   237: bipush #60
    //   239: goto -> 244
    //   242: bipush #97
    //   244: ixor
    //   245: ixor
    //   246: i2c
    //   247: castore
    //   248: iinc #6, 1
    //   251: dup
    //   252: ifne -> 260
    //   255: dup2
    //   256: dup_x1
    //   257: goto -> 166
    //   260: dup2_x1
    //   261: pop2
    //   262: dup_x2
    //   263: iload #6
    //   265: if_icmpgt -> 162
    //   268: pop
    //   269: new java/lang/String
    //   272: dup_x1
    //   273: swap
    //   274: invokespecial <init> : ([C)V
    //   277: invokevirtual intern : ()Ljava/lang/String;
    //   280: swap
    //   281: pop
    //   282: swap
    //   283: tableswitch default -> 40, 0 -> 99
    //   300: new java/math/BigInteger
    //   303: dup
    //   304: iconst_1
    //   305: bipush #32
    //   307: newarray byte
    //   309: dup
    //   310: iconst_0
    //   311: bipush #51
    //   313: bastore
    //   314: dup
    //   315: iconst_1
    //   316: bipush #-108
    //   318: bastore
    //   319: dup
    //   320: iconst_2
    //   321: bipush #-41
    //   323: bastore
    //   324: dup
    //   325: iconst_3
    //   326: bipush #110
    //   328: bastore
    //   329: dup
    //   330: iconst_4
    //   331: bipush #42
    //   333: bastore
    //   334: dup
    //   335: iconst_5
    //   336: bipush #67
    //   338: bastore
    //   339: dup
    //   340: bipush #6
    //   342: bipush #-42
    //   344: bastore
    //   345: dup
    //   346: bipush #7
    //   348: bipush #-96
    //   350: bastore
    //   351: dup
    //   352: bipush #8
    //   354: bipush #114
    //   356: bastore
    //   357: dup
    //   358: bipush #9
    //   360: bipush #10
    //   362: bastore
    //   363: dup
    //   364: bipush #10
    //   366: bipush #88
    //   368: bastore
    //   369: dup
    //   370: bipush #11
    //   372: bipush #66
    //   374: bastore
    //   375: dup
    //   376: bipush #12
    //   378: bipush #102
    //   380: bastore
    //   381: dup
    //   382: bipush #13
    //   384: iconst_3
    //   385: bastore
    //   386: dup
    //   387: bipush #14
    //   389: bipush #-29
    //   391: bastore
    //   392: dup
    //   393: bipush #15
    //   395: bipush #59
    //   397: bastore
    //   398: dup
    //   399: bipush #16
    //   401: bipush #119
    //   403: bastore
    //   404: dup
    //   405: bipush #17
    //   407: bipush #106
    //   409: bastore
    //   410: dup
    //   411: bipush #18
    //   413: bipush #34
    //   415: bastore
    //   416: dup
    //   417: bipush #19
    //   419: bipush #118
    //   421: bastore
    //   422: dup
    //   423: bipush #20
    //   425: bipush #-126
    //   427: bastore
    //   428: dup
    //   429: bipush #21
    //   431: bipush #18
    //   433: bastore
    //   434: dup
    //   435: bipush #22
    //   437: iconst_0
    //   438: bastore
    //   439: dup
    //   440: bipush #23
    //   442: bipush #26
    //   444: bastore
    //   445: dup
    //   446: bipush #24
    //   448: bipush #103
    //   450: bastore
    //   451: dup
    //   452: bipush #25
    //   454: bipush #58
    //   456: bastore
    //   457: dup
    //   458: bipush #26
    //   460: bipush #-11
    //   462: bastore
    //   463: dup
    //   464: bipush #27
    //   466: bipush #-91
    //   468: bastore
    //   469: dup
    //   470: bipush #28
    //   472: bipush #59
    //   474: bastore
    //   475: dup
    //   476: bipush #29
    //   478: bipush #-48
    //   480: bastore
    //   481: dup
    //   482: bipush #30
    //   484: bipush #-42
    //   486: bastore
    //   487: dup
    //   488: bipush #31
    //   490: bipush #111
    //   492: bastore
    //   493: invokespecial <init> : (I[B)V
    //   496: putstatic burp/Zzrb.Zj : Ljava/lang/Object;
    //   499: sipush #30570
    //   502: sipush #26810
    //   505: invokestatic a : (II)Ljava/lang/String;
    //   508: putstatic burp/Zzrb.ZA : Ljava/lang/String;
    //   511: return
  }
  
  private static Throwable a(Throwable paramThrowable) {
    return paramThrowable;
  }
  
  private static String a(int paramInt1, int paramInt2) {
    int i = (paramInt1 ^ 0x777D) & 0xFFFF;
    if (b[i] == null) {
      char[] arrayOfChar = a[i].toCharArray();
      switch (arrayOfChar[0] & 0xFF) {
        case 0:
        
        case 1:
        
        case 2:
        
        case 3:
        
        case 4:
        
        case 5:
        
        case 6:
        
        case 7:
        
        case 8:
        
        case 9:
        
        case 10:
        
        case 11:
        
        case 12:
        
        case 13:
        
        case 14:
        
        case 15:
        
        case 16:
        
        case 17:
        
        case 18:
        
        case 19:
        
        case 20:
        
        case 21:
        
        case 22:
        
        case 23:
        
        case 24:
        
        case 25:
        
        case 26:
        
        case 27:
        
        case 28:
        
        case 29:
        
        case 30:
        
        case 31:
        
        case 32:
        
        case 33:
        
        case 34:
        
        case 35:
        
        case 36:
        
        case 37:
        
        case 38:
        
        case 39:
        
        case 40:
        
        case 41:
        
        case 42:
        
        case 43:
        
        case 44:
        
        case 45:
        
        case 46:
        
        case 47:
        
        case 48:
        
        case 49:
        
        case 50:
        
        case 51:
        
        case 52:
        
        case 53:
        
        case 54:
        
        case 55:
        
        case 56:
        
        case 57:
        
        case 58:
        
        case 59:
        
        case 60:
        
        case 61:
        
        case 62:
        
        case 63:
        
        case 64:
        
        case 65:
        
        case 66:
        
        case 67:
        
        case 68:
        
        case 69:
        
        case 70:
        
        case 71:
        
        case 72:
        
        case 73:
        
        case 74:
        
        case 75:
        
        case 76:
        
        case 77:
        
        case 78:
        
        case 79:
        
        case 80:
        
        case 81:
        
        case 82:
        
        case 83:
        
        case 84:
        
        case 85:
        
        case 86:
        
        case 87:
        
        case 88:
        
        case 89:
        
        case 90:
        
        case 91:
        
        case 92:
        
        case 93:
        
        case 94:
        
        case 95:
        
        case 96:
        
        case 97:
        
        case 98:
        
        case 99:
        
        case 100:
        
        case 101:
        
        case 102:
        
        case 103:
        
        case 104:
        
        case 105:
        
        case 106:
        
        case 107:
        
        case 108:
        
        case 109:
        
        case 110:
        
        case 111:
        
        case 112:
        
        case 113:
        
        case 114:
        
        case 115:
        
        case 116:
        
        case 117:
        
        case 118:
        
        case 119:
        
        case 120:
        
        case 121:
        
        case 122:
        
        case 123:
        
        case 124:
        
        case 125:
        
        case 126:
        
        case 127:
        
        case 128:
        
        case 129:
        
        case 130:
        
        case 131:
        
        case 132:
        
        case 133:
        
        case 134:
        
        case 135:
        
        case 136:
        
        case 137:
        
        case 138:
        
        case 139:
        
        case 140:
        
        case 141:
        
        case 142:
        
        case 143:
        
        case 144:
        
        case 145:
        
        case 146:
        
        case 147:
        
        case 148:
        
        case 149:
        
        case 150:
        
        case 151:
        
        case 152:
        
        case 153:
        
        case 154:
        
        case 155:
        
        case 156:
        
        case 157:
        
        case 158:
        
        case 159:
        
        case 160:
        
        case 161:
        
        case 162:
        
        case 163:
        
        case 164:
        
        case 165:
        
        case 166:
        
        case 167:
        
        case 168:
        
        case 169:
        
        case 170:
        
        case 171:
        
        case 172:
        
        case 173:
        
        case 174:
        
        case 175:
        
        case 176:
        
        case 177:
        
        case 178:
        
        case 179:
        
        case 180:
        
        case 181:
        
        case 182:
        
        case 183:
        
        case 184:
        
        case 185:
        
        case 186:
        
        case 187:
        
        case 188:
        
        case 189:
        
        case 190:
        
        case 191:
        
        case 192:
        
        case 193:
        
        case 194:
        
        case 195:
        
        case 196:
        
        case 197:
        
        case 198:
        
        case 199:
        
        case 200:
        
        case 201:
        
        case 202:
        
        case 203:
        
        case 204:
        
        case 205:
        
        case 206:
        
        case 207:
        
        case 208:
        
        case 209:
        
        case 210:
        
        case 211:
        
        case 212:
        
        case 213:
        
        case 214:
        
        case 215:
        
        case 216:
        
        case 217:
        
        case 218:
        
        case 219:
        
        case 220:
        
        case 221:
        
        case 222:
        
        case 223:
        
        case 224:
        
        case 225:
        
        case 226:
        
        case 227:
        
        case 228:
        
        case 229:
        
        case 230:
        
        case 231:
        
        case 232:
        
        case 233:
        
        case 234:
        
        case 235:
        
        case 236:
        
        case 237:
        
        case 238:
        
        case 239:
        
        case 240:
        
        case 241:
        
        case 242:
        
        case 243:
        
        case 244:
        
        case 245:
        
        case 246:
        
        case 247:
        
        case 248:
        
        case 249:
        
        case 250:
        
        case 251:
        
        case 252:
        
        case 253:
        
        case 254:
        
        default:
          break;
      } 
      byte b1 = 63;
      int j = (paramInt2 & 0xFF) - b1;
      if (j < 0)
        j += 256; 
      int k = ((paramInt2 & 0xFFFF) >>> 8) - b1;
      if (k < 0)
        k += 256; 
      for (byte b2 = 0; b2 < arrayOfChar.length; b2++) {
        int m = b2 % 2;
        if (m == 0) {
          arrayOfChar[b2] = (char)(arrayOfChar[b2] ^ j);
          j = ((j >>> 3 | j << 5) ^ arrayOfChar[b2]) & 0xFF;
        } else {
          arrayOfChar[b2] = (char)(arrayOfChar[b2] ^ k);
          k = ((k >>> 3 | k << 5) ^ arrayOfChar[b2]) & 0xFF;
        } 
      } 
      b[i] = (new String(arrayOfChar)).intern();
    } 
    return b[i];
  }
}


/* Location:              C:\Program Files\BurpSuitePro\burpsuite_pro.jar!\burp\Zzrb.class
 * Java compiler version: 21 (65.0)
 * JD-Core Version:       1.1.3
 */