package burp;

import java.math.BigInteger;

class Zzsq extends ClassLoader {
  static Object Zh;
  
  static String Zc;
  
  private static final String[] a;
  
  private static final String[] b;
  
  static void Zg(Object paramObject) {
    Zsxj.Zp = a(-1773, -15109);
    Zsxj.Zi = new BigInteger(a(-1768, -5323));
    boolean bool = Zt2e.ZN();
    try {
      try {
        if (Zx54.Zs.charAt(Math.abs(((BigInteger)Zlos.Zk).intValue() % 32)) <= Zxfu.Zo.charAt(Math.abs(((BigInteger)Zlhm.ZT).intValue() % 32))) {
          try {
            Zm0s.Zn(Class.forName(a(-1775, 26725)));
            if (!bool)
              Zz6t.Zk(Class.forName(a(-1774, -12868))); 
          } catch (Throwable throwable) {
            throw a(null);
          } 
          return;
        } 
      } catch (Throwable throwable) {
        throw a(null);
      } 
      Zz6t.Zk(Class.forName(a(-1774, -12868)));
    } catch (Throwable throwable) {}
  }
  
  static void ZG(Object[] paramArrayOfObject, Object paramObject) throws Throwable {}
  
  static boolean Zw(Object[] paramArrayOfObject, Object paramObject) throws Throwable {
    // Byte code:
    //   0: invokestatic ZN : ()Z
    //   3: istore_2
    //   4: getstatic burp/Zx4l.Zt : Ljava/lang/Object;
    //   7: checkcast java/math/BigInteger
    //   10: invokevirtual toByteArray : ()[B
    //   13: astore_3
    //   14: aload_3
    //   15: arraylength
    //   16: bipush #8
    //   18: iadd
    //   19: bipush #6
    //   21: ishr
    //   22: iconst_1
    //   23: iadd
    //   24: bipush #16
    //   26: imul
    //   27: newarray int
    //   29: astore #5
    //   31: iconst_0
    //   32: istore #6
    //   34: iload #6
    //   36: aload_3
    //   37: arraylength
    //   38: if_icmpge -> 81
    //   41: aload_3
    //   42: iload #6
    //   44: baload
    //   45: sipush #255
    //   48: iand
    //   49: istore #7
    //   51: aload #5
    //   53: iload #6
    //   55: iconst_2
    //   56: ishr
    //   57: dup2
    //   58: iaload
    //   59: iload #7
    //   61: bipush #24
    //   63: iload #6
    //   65: iconst_4
    //   66: irem
    //   67: bipush #8
    //   69: imul
    //   70: isub
    //   71: ishl
    //   72: ior
    //   73: iastore
    //   74: iinc #6, 1
    //   77: iload_2
    //   78: ifne -> 34
    //   81: aload #5
    //   83: iload #6
    //   85: iconst_2
    //   86: ishr
    //   87: dup2
    //   88: iaload
    //   89: sipush #128
    //   92: bipush #24
    //   94: iload #6
    //   96: iconst_4
    //   97: irem
    //   98: bipush #8
    //   100: imul
    //   101: isub
    //   102: ishl
    //   103: ior
    //   104: iastore
    //   105: aload #5
    //   107: aload #5
    //   109: arraylength
    //   110: iconst_1
    //   111: isub
    //   112: aload_3
    //   113: arraylength
    //   114: bipush #8
    //   116: imul
    //   117: iastore
    //   118: bipush #80
    //   120: newarray int
    //   122: astore #7
    //   124: ldc 1732584193
    //   126: istore #8
    //   128: ldc -271733879
    //   130: istore #9
    //   132: ldc -1732584194
    //   134: istore #10
    //   136: ldc 271733878
    //   138: istore #11
    //   140: ldc -1009589776
    //   142: istore #12
    //   144: iconst_0
    //   145: istore #6
    //   147: iload #6
    //   149: aload #5
    //   151: arraylength
    //   152: if_icmpge -> 474
    //   155: iload #8
    //   157: istore #13
    //   159: iload #9
    //   161: istore #14
    //   163: iload #10
    //   165: istore #15
    //   167: iload #11
    //   169: istore #16
    //   171: iload #12
    //   173: istore #17
    //   175: iconst_0
    //   176: istore #18
    //   178: iload #18
    //   180: bipush #80
    //   182: if_icmpge -> 432
    //   185: iload #18
    //   187: bipush #16
    //   189: if_icmpge -> 216
    //   192: aload #7
    //   194: iload #18
    //   196: aload #5
    //   198: iload #6
    //   200: iload #18
    //   202: iadd
    //   203: iaload
    //   204: iastore
    //   205: iload_2
    //   206: ifne -> 271
    //   209: goto -> 216
    //   212: invokestatic a : (Ljava/lang/Throwable;)Ljava/lang/Throwable;
    //   215: athrow
    //   216: aload #7
    //   218: iload #18
    //   220: iconst_3
    //   221: isub
    //   222: iaload
    //   223: aload #7
    //   225: iload #18
    //   227: bipush #8
    //   229: isub
    //   230: iaload
    //   231: ixor
    //   232: aload #7
    //   234: iload #18
    //   236: bipush #14
    //   238: isub
    //   239: iaload
    //   240: ixor
    //   241: aload #7
    //   243: iload #18
    //   245: bipush #16
    //   247: isub
    //   248: iaload
    //   249: ixor
    //   250: istore #19
    //   252: iload #19
    //   254: iconst_1
    //   255: ishl
    //   256: iload #19
    //   258: bipush #31
    //   260: iushr
    //   261: ior
    //   262: istore #20
    //   264: aload #7
    //   266: iload #18
    //   268: iload #20
    //   270: iastore
    //   271: iload #8
    //   273: iconst_5
    //   274: ishl
    //   275: iload #8
    //   277: bipush #27
    //   279: iushr
    //   280: ior
    //   281: istore #19
    //   283: iload #19
    //   285: iload #12
    //   287: iadd
    //   288: aload #7
    //   290: iload #18
    //   292: iaload
    //   293: iadd
    //   294: iload #18
    //   296: bipush #20
    //   298: if_icmpge -> 324
    //   301: ldc 1518500249
    //   303: iload #9
    //   305: iload #10
    //   307: iand
    //   308: iload #9
    //   310: iconst_m1
    //   311: ixor
    //   312: iload #11
    //   314: iand
    //   315: ior
    //   316: iadd
    //   317: goto -> 394
    //   320: invokestatic a : (Ljava/lang/Throwable;)Ljava/lang/Throwable;
    //   323: athrow
    //   324: iload #18
    //   326: bipush #40
    //   328: if_icmpge -> 349
    //   331: ldc 1859775393
    //   333: iload #9
    //   335: iload #10
    //   337: ixor
    //   338: iload #11
    //   340: ixor
    //   341: iadd
    //   342: goto -> 394
    //   345: invokestatic a : (Ljava/lang/Throwable;)Ljava/lang/Throwable;
    //   348: athrow
    //   349: iload #18
    //   351: bipush #60
    //   353: if_icmpge -> 383
    //   356: ldc -1894007588
    //   358: iload #9
    //   360: iload #10
    //   362: iand
    //   363: iload #9
    //   365: iload #11
    //   367: iand
    //   368: ior
    //   369: iload #10
    //   371: iload #11
    //   373: iand
    //   374: ior
    //   375: iadd
    //   376: goto -> 394
    //   379: invokestatic a : (Ljava/lang/Throwable;)Ljava/lang/Throwable;
    //   382: athrow
    //   383: ldc -899497514
    //   385: iload #9
    //   387: iload #10
    //   389: ixor
    //   390: iload #11
    //   392: ixor
    //   393: iadd
    //   394: iadd
    //   395: istore #20
    //   397: iload #11
    //   399: istore #12
    //   401: iload #10
    //   403: istore #11
    //   405: iload #9
    //   407: bipush #30
    //   409: ishl
    //   410: iload #9
    //   412: iconst_2
    //   413: iushr
    //   414: ior
    //   415: istore #10
    //   417: iload #8
    //   419: istore #9
    //   421: iload #20
    //   423: istore #8
    //   425: iinc #18, 1
    //   428: iload_2
    //   429: ifne -> 178
    //   432: iload #8
    //   434: iload #13
    //   436: iadd
    //   437: istore #8
    //   439: iload #9
    //   441: iload #14
    //   443: iadd
    //   444: istore #9
    //   446: iload #10
    //   448: iload #15
    //   450: iadd
    //   451: istore #10
    //   453: iload #11
    //   455: iload #16
    //   457: iadd
    //   458: istore #11
    //   460: iload #12
    //   462: iload #17
    //   464: iadd
    //   465: istore #12
    //   467: iinc #6, 16
    //   470: iload_2
    //   471: ifne -> 147
    //   474: iconst_5
    //   475: newarray int
    //   477: dup
    //   478: iconst_0
    //   479: iload #8
    //   481: iastore
    //   482: dup
    //   483: iconst_1
    //   484: iload #9
    //   486: iastore
    //   487: dup
    //   488: iconst_2
    //   489: iload #10
    //   491: iastore
    //   492: dup
    //   493: iconst_3
    //   494: iload #11
    //   496: iastore
    //   497: dup
    //   498: iconst_4
    //   499: iload #12
    //   501: iastore
    //   502: astore #13
    //   504: bipush #20
    //   506: newarray byte
    //   508: astore #14
    //   510: iconst_0
    //   511: istore #15
    //   513: iload #15
    //   515: bipush #20
    //   517: if_icmpge -> 558
    //   520: aload #13
    //   522: iload #15
    //   524: iconst_4
    //   525: idiv
    //   526: iaload
    //   527: istore #16
    //   529: iconst_3
    //   530: iload #15
    //   532: iconst_4
    //   533: irem
    //   534: isub
    //   535: bipush #8
    //   537: imul
    //   538: istore #17
    //   540: aload #14
    //   542: iload #15
    //   544: iload #16
    //   546: iload #17
    //   548: iushr
    //   549: i2b
    //   550: bastore
    //   551: iinc #15, 1
    //   554: iload_2
    //   555: ifne -> 513
    //   558: aload #14
    //   560: astore #4
    //   562: new java/math/BigInteger
    //   565: dup
    //   566: aload #4
    //   568: invokespecial <init> : ([B)V
    //   571: invokevirtual abs : ()Ljava/math/BigInteger;
    //   574: putstatic burp/Zzip.ZW : Ljava/lang/Object;
    //   577: getstatic burp/Zz1k.ZP : Ljava/lang/Object;
    //   580: checkcast java/math/BigInteger
    //   583: invokevirtual toByteArray : ()[B
    //   586: astore_3
    //   587: new java/lang/StringBuilder
    //   590: dup
    //   591: invokespecial <init> : ()V
    //   594: astore #5
    //   596: aload #5
    //   598: sipush #-1770
    //   601: sipush #24356
    //   604: invokestatic a : (II)Ljava/lang/String;
    //   607: invokevirtual append : (Ljava/lang/String;)Ljava/lang/StringBuilder;
    //   610: pop
    //   611: aload_3
    //   612: astore #6
    //   614: aload #6
    //   616: arraylength
    //   617: istore #7
    //   619: iconst_0
    //   620: istore #8
    //   622: iload #8
    //   624: iload #7
    //   626: if_icmpge -> 652
    //   629: aload #6
    //   631: iload #8
    //   633: baload
    //   634: istore #9
    //   636: aload #5
    //   638: iload #9
    //   640: i2c
    //   641: invokevirtual append : (C)Ljava/lang/StringBuilder;
    //   644: pop
    //   645: iinc #8, 1
    //   648: iload_2
    //   649: ifne -> 622
    //   652: aload #5
    //   654: sipush #-1772
    //   657: sipush #-8498
    //   660: invokestatic a : (II)Ljava/lang/String;
    //   663: ldc ''
    //   665: invokestatic getProperty : (Ljava/lang/String;Ljava/lang/String;)Ljava/lang/String;
    //   668: invokevirtual toLowerCase : ()Ljava/lang/String;
    //   671: invokevirtual append : (Ljava/lang/String;)Ljava/lang/StringBuilder;
    //   674: pop
    //   675: aload #5
    //   677: sipush #-1769
    //   680: sipush #9474
    //   683: invokestatic a : (II)Ljava/lang/String;
    //   686: ldc ''
    //   688: invokestatic getProperty : (Ljava/lang/String;Ljava/lang/String;)Ljava/lang/String;
    //   691: invokevirtual toLowerCase : ()Ljava/lang/String;
    //   694: invokevirtual append : (Ljava/lang/String;)Ljava/lang/StringBuilder;
    //   697: pop
    //   698: aload #5
    //   700: invokevirtual toString : ()Ljava/lang/String;
    //   703: invokevirtual getBytes : ()[B
    //   706: astore #4
    //   708: aload #4
    //   710: astore_3
    //   711: aload_3
    //   712: arraylength
    //   713: bipush #8
    //   715: iadd
    //   716: bipush #6
    //   718: ishr
    //   719: iconst_1
    //   720: iadd
    //   721: bipush #16
    //   723: imul
    //   724: newarray int
    //   726: astore #5
    //   728: iconst_0
    //   729: istore #6
    //   731: iload #6
    //   733: aload_3
    //   734: arraylength
    //   735: if_icmpge -> 778
    //   738: aload_3
    //   739: iload #6
    //   741: baload
    //   742: sipush #255
    //   745: iand
    //   746: istore #7
    //   748: aload #5
    //   750: iload #6
    //   752: iconst_2
    //   753: ishr
    //   754: dup2
    //   755: iaload
    //   756: iload #7
    //   758: bipush #24
    //   760: iload #6
    //   762: iconst_4
    //   763: irem
    //   764: bipush #8
    //   766: imul
    //   767: isub
    //   768: ishl
    //   769: ior
    //   770: iastore
    //   771: iinc #6, 1
    //   774: iload_2
    //   775: ifne -> 731
    //   778: aload #5
    //   780: iload #6
    //   782: iconst_2
    //   783: ishr
    //   784: dup2
    //   785: iaload
    //   786: sipush #128
    //   789: bipush #24
    //   791: iload #6
    //   793: iconst_4
    //   794: irem
    //   795: bipush #8
    //   797: imul
    //   798: isub
    //   799: ishl
    //   800: ior
    //   801: iastore
    //   802: aload #5
    //   804: aload #5
    //   806: arraylength
    //   807: iconst_1
    //   808: isub
    //   809: aload_3
    //   810: arraylength
    //   811: bipush #8
    //   813: imul
    //   814: iastore
    //   815: bipush #80
    //   817: newarray int
    //   819: astore #7
    //   821: ldc 1732584193
    //   823: istore #8
    //   825: ldc -271733879
    //   827: istore #9
    //   829: ldc -1732584194
    //   831: istore #10
    //   833: ldc 271733878
    //   835: istore #11
    //   837: ldc -1009589776
    //   839: istore #12
    //   841: iconst_0
    //   842: istore #6
    //   844: iload #6
    //   846: aload #5
    //   848: arraylength
    //   849: if_icmpge -> 1171
    //   852: iload #8
    //   854: istore #13
    //   856: iload #9
    //   858: istore #14
    //   860: iload #10
    //   862: istore #15
    //   864: iload #11
    //   866: istore #16
    //   868: iload #12
    //   870: istore #17
    //   872: iconst_0
    //   873: istore #18
    //   875: iload #18
    //   877: bipush #80
    //   879: if_icmpge -> 1129
    //   882: iload #18
    //   884: bipush #16
    //   886: if_icmpge -> 913
    //   889: aload #7
    //   891: iload #18
    //   893: aload #5
    //   895: iload #6
    //   897: iload #18
    //   899: iadd
    //   900: iaload
    //   901: iastore
    //   902: iload_2
    //   903: ifne -> 968
    //   906: goto -> 913
    //   909: invokestatic a : (Ljava/lang/Throwable;)Ljava/lang/Throwable;
    //   912: athrow
    //   913: aload #7
    //   915: iload #18
    //   917: iconst_3
    //   918: isub
    //   919: iaload
    //   920: aload #7
    //   922: iload #18
    //   924: bipush #8
    //   926: isub
    //   927: iaload
    //   928: ixor
    //   929: aload #7
    //   931: iload #18
    //   933: bipush #14
    //   935: isub
    //   936: iaload
    //   937: ixor
    //   938: aload #7
    //   940: iload #18
    //   942: bipush #16
    //   944: isub
    //   945: iaload
    //   946: ixor
    //   947: istore #19
    //   949: iload #19
    //   951: iconst_1
    //   952: ishl
    //   953: iload #19
    //   955: bipush #31
    //   957: iushr
    //   958: ior
    //   959: istore #20
    //   961: aload #7
    //   963: iload #18
    //   965: iload #20
    //   967: iastore
    //   968: iload #8
    //   970: iconst_5
    //   971: ishl
    //   972: iload #8
    //   974: bipush #27
    //   976: iushr
    //   977: ior
    //   978: istore #19
    //   980: iload #19
    //   982: iload #12
    //   984: iadd
    //   985: aload #7
    //   987: iload #18
    //   989: iaload
    //   990: iadd
    //   991: iload #18
    //   993: bipush #20
    //   995: if_icmpge -> 1021
    //   998: ldc 1518500249
    //   1000: iload #9
    //   1002: iload #10
    //   1004: iand
    //   1005: iload #9
    //   1007: iconst_m1
    //   1008: ixor
    //   1009: iload #11
    //   1011: iand
    //   1012: ior
    //   1013: iadd
    //   1014: goto -> 1091
    //   1017: invokestatic a : (Ljava/lang/Throwable;)Ljava/lang/Throwable;
    //   1020: athrow
    //   1021: iload #18
    //   1023: bipush #40
    //   1025: if_icmpge -> 1046
    //   1028: ldc 1859775393
    //   1030: iload #9
    //   1032: iload #10
    //   1034: ixor
    //   1035: iload #11
    //   1037: ixor
    //   1038: iadd
    //   1039: goto -> 1091
    //   1042: invokestatic a : (Ljava/lang/Throwable;)Ljava/lang/Throwable;
    //   1045: athrow
    //   1046: iload #18
    //   1048: bipush #60
    //   1050: if_icmpge -> 1080
    //   1053: ldc -1894007588
    //   1055: iload #9
    //   1057: iload #10
    //   1059: iand
    //   1060: iload #9
    //   1062: iload #11
    //   1064: iand
    //   1065: ior
    //   1066: iload #10
    //   1068: iload #11
    //   1070: iand
    //   1071: ior
    //   1072: iadd
    //   1073: goto -> 1091
    //   1076: invokestatic a : (Ljava/lang/Throwable;)Ljava/lang/Throwable;
    //   1079: athrow
    //   1080: ldc -899497514
    //   1082: iload #9
    //   1084: iload #10
    //   1086: ixor
    //   1087: iload #11
    //   1089: ixor
    //   1090: iadd
    //   1091: iadd
    //   1092: istore #20
    //   1094: iload #11
    //   1096: istore #12
    //   1098: iload #10
    //   1100: istore #11
    //   1102: iload #9
    //   1104: bipush #30
    //   1106: ishl
    //   1107: iload #9
    //   1109: iconst_2
    //   1110: iushr
    //   1111: ior
    //   1112: istore #10
    //   1114: iload #8
    //   1116: istore #9
    //   1118: iload #20
    //   1120: istore #8
    //   1122: iinc #18, 1
    //   1125: iload_2
    //   1126: ifne -> 875
    //   1129: iload #8
    //   1131: iload #13
    //   1133: iadd
    //   1134: istore #8
    //   1136: iload #9
    //   1138: iload #14
    //   1140: iadd
    //   1141: istore #9
    //   1143: iload #10
    //   1145: iload #15
    //   1147: iadd
    //   1148: istore #10
    //   1150: iload #11
    //   1152: iload #16
    //   1154: iadd
    //   1155: istore #11
    //   1157: iload #12
    //   1159: iload #17
    //   1161: iadd
    //   1162: istore #12
    //   1164: iinc #6, 16
    //   1167: iload_2
    //   1168: ifne -> 844
    //   1171: iconst_5
    //   1172: newarray int
    //   1174: dup
    //   1175: iconst_0
    //   1176: iload #8
    //   1178: iastore
    //   1179: dup
    //   1180: iconst_1
    //   1181: iload #9
    //   1183: iastore
    //   1184: dup
    //   1185: iconst_2
    //   1186: iload #10
    //   1188: iastore
    //   1189: dup
    //   1190: iconst_3
    //   1191: iload #11
    //   1193: iastore
    //   1194: dup
    //   1195: iconst_4
    //   1196: iload #12
    //   1198: iastore
    //   1199: astore #13
    //   1201: bipush #20
    //   1203: newarray byte
    //   1205: astore #14
    //   1207: iconst_0
    //   1208: istore #15
    //   1210: iload #15
    //   1212: bipush #20
    //   1214: if_icmpge -> 1255
    //   1217: aload #13
    //   1219: iload #15
    //   1221: iconst_4
    //   1222: idiv
    //   1223: iaload
    //   1224: istore #16
    //   1226: iconst_3
    //   1227: iload #15
    //   1229: iconst_4
    //   1230: irem
    //   1231: isub
    //   1232: bipush #8
    //   1234: imul
    //   1235: istore #17
    //   1237: aload #14
    //   1239: iload #15
    //   1241: iload #16
    //   1243: iload #17
    //   1245: iushr
    //   1246: i2b
    //   1247: bastore
    //   1248: iinc #15, 1
    //   1251: iload_2
    //   1252: ifne -> 1210
    //   1255: aload #14
    //   1257: astore #4
    //   1259: new java/lang/StringBuilder
    //   1262: dup
    //   1263: invokespecial <init> : ()V
    //   1266: astore_3
    //   1267: iconst_0
    //   1268: istore #4
    //   1270: iload #4
    //   1272: bipush #32
    //   1274: if_icmpge -> 2607
    //   1277: iload #4
    //   1279: tableswitch default -> 2600, 0 -> 1420, 1 -> 1457, 2 -> 1494, 3 -> 1531, 4 -> 1568, 5 -> 1605, 6 -> 1642, 7 -> 1679, 8 -> 1716, 9 -> 1753, 10 -> 1790, 11 -> 1827, 12 -> 1864, 13 -> 1901, 14 -> 1938, 15 -> 1975, 16 -> 2012, 17 -> 2049, 18 -> 2086, 19 -> 2123, 20 -> 2160, 21 -> 2197, 22 -> 2234, 23 -> 2271, 24 -> 2308, 25 -> 2345, 26 -> 2382, 27 -> 2419, 28 -> 2456, 29 -> 2493, 30 -> 2530, 31 -> 2567
    //   1420: aload_3
    //   1421: getstatic burp/Ze7q.ZW : Ljava/lang/String;
    //   1424: getstatic burp/Zsgl.Zn : Ljava/lang/Object;
    //   1427: checkcast java/math/BigInteger
    //   1430: invokevirtual intValue : ()I
    //   1433: bipush #32
    //   1435: irem
    //   1436: invokestatic abs : (I)I
    //   1439: invokevirtual charAt : (I)C
    //   1442: invokevirtual append : (C)Ljava/lang/StringBuilder;
    //   1445: pop
    //   1446: iload_2
    //   1447: ifne -> 2600
    //   1450: goto -> 1457
    //   1453: invokestatic a : (Ljava/lang/Throwable;)Ljava/lang/Throwable;
    //   1456: athrow
    //   1457: aload_3
    //   1458: getstatic burp/Zxo6.Z_ : Ljava/lang/String;
    //   1461: getstatic burp/Ztbf.Zv : Ljava/lang/Object;
    //   1464: checkcast java/math/BigInteger
    //   1467: invokevirtual intValue : ()I
    //   1470: bipush #32
    //   1472: irem
    //   1473: invokestatic abs : (I)I
    //   1476: invokevirtual charAt : (I)C
    //   1479: invokevirtual append : (C)Ljava/lang/StringBuilder;
    //   1482: pop
    //   1483: iload_2
    //   1484: ifne -> 2600
    //   1487: goto -> 1494
    //   1490: invokestatic a : (Ljava/lang/Throwable;)Ljava/lang/Throwable;
    //   1493: athrow
    //   1494: aload_3
    //   1495: getstatic burp/Zkbf.Zv : Ljava/lang/String;
    //   1498: getstatic burp/Zxk9.ZI : Ljava/lang/Object;
    //   1501: checkcast java/math/BigInteger
    //   1504: invokevirtual intValue : ()I
    //   1507: bipush #32
    //   1509: irem
    //   1510: invokestatic abs : (I)I
    //   1513: invokevirtual charAt : (I)C
    //   1516: invokevirtual append : (C)Ljava/lang/StringBuilder;
    //   1519: pop
    //   1520: iload_2
    //   1521: ifne -> 2600
    //   1524: goto -> 1531
    //   1527: invokestatic a : (Ljava/lang/Throwable;)Ljava/lang/Throwable;
    //   1530: athrow
    //   1531: aload_3
    //   1532: getstatic burp/Zgw0.ZL : Ljava/lang/String;
    //   1535: getstatic burp/Zg7z.ZV : Ljava/lang/Object;
    //   1538: checkcast java/math/BigInteger
    //   1541: invokevirtual intValue : ()I
    //   1544: bipush #32
    //   1546: irem
    //   1547: invokestatic abs : (I)I
    //   1550: invokevirtual charAt : (I)C
    //   1553: invokevirtual append : (C)Ljava/lang/StringBuilder;
    //   1556: pop
    //   1557: iload_2
    //   1558: ifne -> 2600
    //   1561: goto -> 1568
    //   1564: invokestatic a : (Ljava/lang/Throwable;)Ljava/lang/Throwable;
    //   1567: athrow
    //   1568: aload_3
    //   1569: getstatic burp/Zk9s.ZM : Ljava/lang/String;
    //   1572: getstatic burp/Zz1k.ZP : Ljava/lang/Object;
    //   1575: checkcast java/math/BigInteger
    //   1578: invokevirtual intValue : ()I
    //   1581: bipush #32
    //   1583: irem
    //   1584: invokestatic abs : (I)I
    //   1587: invokevirtual charAt : (I)C
    //   1590: invokevirtual append : (C)Ljava/lang/StringBuilder;
    //   1593: pop
    //   1594: iload_2
    //   1595: ifne -> 2600
    //   1598: goto -> 1605
    //   1601: invokestatic a : (Ljava/lang/Throwable;)Ljava/lang/Throwable;
    //   1604: athrow
    //   1605: aload_3
    //   1606: getstatic burp/Zxk9.Zx : Ljava/lang/String;
    //   1609: getstatic burp/Zer.Zk : Ljava/lang/Object;
    //   1612: checkcast java/math/BigInteger
    //   1615: invokevirtual intValue : ()I
    //   1618: bipush #32
    //   1620: irem
    //   1621: invokestatic abs : (I)I
    //   1624: invokevirtual charAt : (I)C
    //   1627: invokevirtual append : (C)Ljava/lang/StringBuilder;
    //   1630: pop
    //   1631: iload_2
    //   1632: ifne -> 2600
    //   1635: goto -> 1642
    //   1638: invokestatic a : (Ljava/lang/Throwable;)Ljava/lang/Throwable;
    //   1641: athrow
    //   1642: aload_3
    //   1643: getstatic burp/Zlos.Zp : Ljava/lang/String;
    //   1646: getstatic burp/Zx4w.Zp : Ljava/lang/Object;
    //   1649: checkcast java/math/BigInteger
    //   1652: invokevirtual intValue : ()I
    //   1655: bipush #32
    //   1657: irem
    //   1658: invokestatic abs : (I)I
    //   1661: invokevirtual charAt : (I)C
    //   1664: invokevirtual append : (C)Ljava/lang/StringBuilder;
    //   1667: pop
    //   1668: iload_2
    //   1669: ifne -> 2600
    //   1672: goto -> 1679
    //   1675: invokestatic a : (Ljava/lang/Throwable;)Ljava/lang/Throwable;
    //   1678: athrow
    //   1679: aload_3
    //   1680: getstatic burp/Zsby.Zx : Ljava/lang/String;
    //   1683: getstatic burp/Zrbp.Z_ : Ljava/lang/Object;
    //   1686: checkcast java/math/BigInteger
    //   1689: invokevirtual intValue : ()I
    //   1692: bipush #32
    //   1694: irem
    //   1695: invokestatic abs : (I)I
    //   1698: invokevirtual charAt : (I)C
    //   1701: invokevirtual append : (C)Ljava/lang/StringBuilder;
    //   1704: pop
    //   1705: iload_2
    //   1706: ifne -> 2600
    //   1709: goto -> 1716
    //   1712: invokestatic a : (Ljava/lang/Throwable;)Ljava/lang/Throwable;
    //   1715: athrow
    //   1716: aload_3
    //   1717: getstatic burp/Zehi.Zi : Ljava/lang/String;
    //   1720: getstatic burp/Zedz.Za : Ljava/lang/Object;
    //   1723: checkcast java/math/BigInteger
    //   1726: invokevirtual intValue : ()I
    //   1729: bipush #32
    //   1731: irem
    //   1732: invokestatic abs : (I)I
    //   1735: invokevirtual charAt : (I)C
    //   1738: invokevirtual append : (C)Ljava/lang/StringBuilder;
    //   1741: pop
    //   1742: iload_2
    //   1743: ifne -> 2600
    //   1746: goto -> 1753
    //   1749: invokestatic a : (Ljava/lang/Throwable;)Ljava/lang/Throwable;
    //   1752: athrow
    //   1753: aload_3
    //   1754: getstatic burp/Zgmt.Zu : Ljava/lang/String;
    //   1757: getstatic burp/Ze3j.Ze : Ljava/lang/Object;
    //   1760: checkcast java/math/BigInteger
    //   1763: invokevirtual intValue : ()I
    //   1766: bipush #32
    //   1768: irem
    //   1769: invokestatic abs : (I)I
    //   1772: invokevirtual charAt : (I)C
    //   1775: invokevirtual append : (C)Ljava/lang/StringBuilder;
    //   1778: pop
    //   1779: iload_2
    //   1780: ifne -> 2600
    //   1783: goto -> 1790
    //   1786: invokestatic a : (Ljava/lang/Throwable;)Ljava/lang/Throwable;
    //   1789: athrow
    //   1790: aload_3
    //   1791: getstatic burp/Zlhm.Zx : Ljava/lang/String;
    //   1794: getstatic burp/Zlhm.ZT : Ljava/lang/Object;
    //   1797: checkcast java/math/BigInteger
    //   1800: invokevirtual intValue : ()I
    //   1803: bipush #32
    //   1805: irem
    //   1806: invokestatic abs : (I)I
    //   1809: invokevirtual charAt : (I)C
    //   1812: invokevirtual append : (C)Ljava/lang/StringBuilder;
    //   1815: pop
    //   1816: iload_2
    //   1817: ifne -> 2600
    //   1820: goto -> 1827
    //   1823: invokestatic a : (Ljava/lang/Throwable;)Ljava/lang/Throwable;
    //   1826: athrow
    //   1827: aload_3
    //   1828: getstatic burp/Zrdy.ZO : Ljava/lang/String;
    //   1831: getstatic burp/Zzip.ZW : Ljava/lang/Object;
    //   1834: checkcast java/math/BigInteger
    //   1837: invokevirtual intValue : ()I
    //   1840: bipush #32
    //   1842: irem
    //   1843: invokestatic abs : (I)I
    //   1846: invokevirtual charAt : (I)C
    //   1849: invokevirtual append : (C)Ljava/lang/StringBuilder;
    //   1852: pop
    //   1853: iload_2
    //   1854: ifne -> 2600
    //   1857: goto -> 1864
    //   1860: invokestatic a : (Ljava/lang/Throwable;)Ljava/lang/Throwable;
    //   1863: athrow
    //   1864: aload_3
    //   1865: getstatic burp/Zb3z.Zi : Ljava/lang/String;
    //   1868: getstatic burp/Zsxm.Zv : Ljava/lang/Object;
    //   1871: checkcast java/math/BigInteger
    //   1874: invokevirtual intValue : ()I
    //   1877: bipush #32
    //   1879: irem
    //   1880: invokestatic abs : (I)I
    //   1883: invokevirtual charAt : (I)C
    //   1886: invokevirtual append : (C)Ljava/lang/StringBuilder;
    //   1889: pop
    //   1890: iload_2
    //   1891: ifne -> 2600
    //   1894: goto -> 1901
    //   1897: invokestatic a : (Ljava/lang/Throwable;)Ljava/lang/Throwable;
    //   1900: athrow
    //   1901: aload_3
    //   1902: getstatic burp/Zzap.ZA : Ljava/lang/String;
    //   1905: getstatic burp/Zx4l.Zt : Ljava/lang/Object;
    //   1908: checkcast java/math/BigInteger
    //   1911: invokevirtual intValue : ()I
    //   1914: bipush #32
    //   1916: irem
    //   1917: invokestatic abs : (I)I
    //   1920: invokevirtual charAt : (I)C
    //   1923: invokevirtual append : (C)Ljava/lang/StringBuilder;
    //   1926: pop
    //   1927: iload_2
    //   1928: ifne -> 2600
    //   1931: goto -> 1938
    //   1934: invokestatic a : (Ljava/lang/Throwable;)Ljava/lang/Throwable;
    //   1937: athrow
    //   1938: aload_3
    //   1939: getstatic burp/Zx4w.Zo : Ljava/lang/String;
    //   1942: getstatic burp/Zr0u.ZB : Ljava/lang/Object;
    //   1945: checkcast java/math/BigInteger
    //   1948: invokevirtual intValue : ()I
    //   1951: bipush #32
    //   1953: irem
    //   1954: invokestatic abs : (I)I
    //   1957: invokevirtual charAt : (I)C
    //   1960: invokevirtual append : (C)Ljava/lang/StringBuilder;
    //   1963: pop
    //   1964: iload_2
    //   1965: ifne -> 2600
    //   1968: goto -> 1975
    //   1971: invokestatic a : (Ljava/lang/Throwable;)Ljava/lang/Throwable;
    //   1974: athrow
    //   1975: aload_3
    //   1976: getstatic burp/Zb8v.Zo : Ljava/lang/String;
    //   1979: getstatic burp/Zzqj.Zq : Ljava/lang/Object;
    //   1982: checkcast java/math/BigInteger
    //   1985: invokevirtual intValue : ()I
    //   1988: bipush #32
    //   1990: irem
    //   1991: invokestatic abs : (I)I
    //   1994: invokevirtual charAt : (I)C
    //   1997: invokevirtual append : (C)Ljava/lang/StringBuilder;
    //   2000: pop
    //   2001: iload_2
    //   2002: ifne -> 2600
    //   2005: goto -> 2012
    //   2008: invokestatic a : (Ljava/lang/Throwable;)Ljava/lang/Throwable;
    //   2011: athrow
    //   2012: aload_3
    //   2013: getstatic burp/Zxwl.Zu : Ljava/lang/String;
    //   2016: getstatic burp/Zehi.Zb : Ljava/lang/Object;
    //   2019: checkcast java/math/BigInteger
    //   2022: invokevirtual intValue : ()I
    //   2025: bipush #32
    //   2027: irem
    //   2028: invokestatic abs : (I)I
    //   2031: invokevirtual charAt : (I)C
    //   2034: invokevirtual append : (C)Ljava/lang/StringBuilder;
    //   2037: pop
    //   2038: iload_2
    //   2039: ifne -> 2600
    //   2042: goto -> 2049
    //   2045: invokestatic a : (Ljava/lang/Throwable;)Ljava/lang/Throwable;
    //   2048: athrow
    //   2049: aload_3
    //   2050: getstatic burp/Zg0j.Ze : Ljava/lang/String;
    //   2053: getstatic burp/Zx54.Zn : Ljava/lang/Object;
    //   2056: checkcast java/math/BigInteger
    //   2059: invokevirtual intValue : ()I
    //   2062: bipush #32
    //   2064: irem
    //   2065: invokestatic abs : (I)I
    //   2068: invokevirtual charAt : (I)C
    //   2071: invokevirtual append : (C)Ljava/lang/StringBuilder;
    //   2074: pop
    //   2075: iload_2
    //   2076: ifne -> 2600
    //   2079: goto -> 2086
    //   2082: invokestatic a : (Ljava/lang/Throwable;)Ljava/lang/Throwable;
    //   2085: athrow
    //   2086: aload_3
    //   2087: getstatic burp/Zzk9.Zb : Ljava/lang/String;
    //   2090: getstatic burp/Zkig.ZK : Ljava/lang/Object;
    //   2093: checkcast java/math/BigInteger
    //   2096: invokevirtual intValue : ()I
    //   2099: bipush #32
    //   2101: irem
    //   2102: invokestatic abs : (I)I
    //   2105: invokevirtual charAt : (I)C
    //   2108: invokevirtual append : (C)Ljava/lang/StringBuilder;
    //   2111: pop
    //   2112: iload_2
    //   2113: ifne -> 2600
    //   2116: goto -> 2123
    //   2119: invokestatic a : (Ljava/lang/Throwable;)Ljava/lang/Throwable;
    //   2122: athrow
    //   2123: aload_3
    //   2124: getstatic burp/Zeh9.ZF : Ljava/lang/String;
    //   2127: getstatic burp/Zzk9.ZK : Ljava/lang/Object;
    //   2130: checkcast java/math/BigInteger
    //   2133: invokevirtual intValue : ()I
    //   2136: bipush #32
    //   2138: irem
    //   2139: invokestatic abs : (I)I
    //   2142: invokevirtual charAt : (I)C
    //   2145: invokevirtual append : (C)Ljava/lang/StringBuilder;
    //   2148: pop
    //   2149: iload_2
    //   2150: ifne -> 2600
    //   2153: goto -> 2160
    //   2156: invokestatic a : (Ljava/lang/Throwable;)Ljava/lang/Throwable;
    //   2159: athrow
    //   2160: aload_3
    //   2161: getstatic burp/Zrdy.ZO : Ljava/lang/String;
    //   2164: getstatic burp/Zr0u.ZB : Ljava/lang/Object;
    //   2167: checkcast java/math/BigInteger
    //   2170: invokevirtual intValue : ()I
    //   2173: bipush #32
    //   2175: irem
    //   2176: invokestatic abs : (I)I
    //   2179: invokevirtual charAt : (I)C
    //   2182: invokevirtual append : (C)Ljava/lang/StringBuilder;
    //   2185: pop
    //   2186: iload_2
    //   2187: ifne -> 2600
    //   2190: goto -> 2197
    //   2193: invokestatic a : (Ljava/lang/Throwable;)Ljava/lang/Throwable;
    //   2196: athrow
    //   2197: aload_3
    //   2198: getstatic burp/Ze3d.ZL : Ljava/lang/String;
    //   2201: getstatic burp/Zxwl.Ze : Ljava/lang/Object;
    //   2204: checkcast java/math/BigInteger
    //   2207: invokevirtual intValue : ()I
    //   2210: bipush #32
    //   2212: irem
    //   2213: invokestatic abs : (I)I
    //   2216: invokevirtual charAt : (I)C
    //   2219: invokevirtual append : (C)Ljava/lang/StringBuilder;
    //   2222: pop
    //   2223: iload_2
    //   2224: ifne -> 2600
    //   2227: goto -> 2234
    //   2230: invokestatic a : (Ljava/lang/Throwable;)Ljava/lang/Throwable;
    //   2233: athrow
    //   2234: aload_3
    //   2235: getstatic burp/Ze7q.ZW : Ljava/lang/String;
    //   2238: getstatic burp/Zx4w.Zp : Ljava/lang/Object;
    //   2241: checkcast java/math/BigInteger
    //   2244: invokevirtual intValue : ()I
    //   2247: bipush #32
    //   2249: irem
    //   2250: invokestatic abs : (I)I
    //   2253: invokevirtual charAt : (I)C
    //   2256: invokevirtual append : (C)Ljava/lang/StringBuilder;
    //   2259: pop
    //   2260: iload_2
    //   2261: ifne -> 2600
    //   2264: goto -> 2271
    //   2267: invokestatic a : (Ljava/lang/Throwable;)Ljava/lang/Throwable;
    //   2270: athrow
    //   2271: aload_3
    //   2272: getstatic burp/Zg99.ZH : Ljava/lang/String;
    //   2275: getstatic burp/Zg7p.Zb : Ljava/lang/Object;
    //   2278: checkcast java/math/BigInteger
    //   2281: invokevirtual intValue : ()I
    //   2284: bipush #32
    //   2286: irem
    //   2287: invokestatic abs : (I)I
    //   2290: invokevirtual charAt : (I)C
    //   2293: invokevirtual append : (C)Ljava/lang/StringBuilder;
    //   2296: pop
    //   2297: iload_2
    //   2298: ifne -> 2600
    //   2301: goto -> 2308
    //   2304: invokestatic a : (Ljava/lang/Throwable;)Ljava/lang/Throwable;
    //   2307: athrow
    //   2308: aload_3
    //   2309: getstatic burp/Zr3q.ZM : Ljava/lang/String;
    //   2312: getstatic burp/Zr0g.Zj : Ljava/lang/Object;
    //   2315: checkcast java/math/BigInteger
    //   2318: invokevirtual intValue : ()I
    //   2321: bipush #32
    //   2323: irem
    //   2324: invokestatic abs : (I)I
    //   2327: invokevirtual charAt : (I)C
    //   2330: invokevirtual append : (C)Ljava/lang/StringBuilder;
    //   2333: pop
    //   2334: iload_2
    //   2335: ifne -> 2600
    //   2338: goto -> 2345
    //   2341: invokestatic a : (Ljava/lang/Throwable;)Ljava/lang/Throwable;
    //   2344: athrow
    //   2345: aload_3
    //   2346: getstatic burp/Zzqj.Zk : Ljava/lang/String;
    //   2349: getstatic burp/Zsde.Zx : Ljava/lang/Object;
    //   2352: checkcast java/math/BigInteger
    //   2355: invokevirtual intValue : ()I
    //   2358: bipush #32
    //   2360: irem
    //   2361: invokestatic abs : (I)I
    //   2364: invokevirtual charAt : (I)C
    //   2367: invokevirtual append : (C)Ljava/lang/StringBuilder;
    //   2370: pop
    //   2371: iload_2
    //   2372: ifne -> 2600
    //   2375: goto -> 2382
    //   2378: invokestatic a : (Ljava/lang/Throwable;)Ljava/lang/Throwable;
    //   2381: athrow
    //   2382: aload_3
    //   2383: getstatic burp/Zt4g.Zj : Ljava/lang/String;
    //   2386: getstatic burp/Zg7z.ZV : Ljava/lang/Object;
    //   2389: checkcast java/math/BigInteger
    //   2392: invokevirtual intValue : ()I
    //   2395: bipush #32
    //   2397: irem
    //   2398: invokestatic abs : (I)I
    //   2401: invokevirtual charAt : (I)C
    //   2404: invokevirtual append : (C)Ljava/lang/StringBuilder;
    //   2407: pop
    //   2408: iload_2
    //   2409: ifne -> 2600
    //   2412: goto -> 2419
    //   2415: invokestatic a : (Ljava/lang/Throwable;)Ljava/lang/Throwable;
    //   2418: athrow
    //   2419: aload_3
    //   2420: getstatic burp/Ze3d.ZL : Ljava/lang/String;
    //   2423: getstatic burp/Zshq.ZK : Ljava/lang/Object;
    //   2426: checkcast java/math/BigInteger
    //   2429: invokevirtual intValue : ()I
    //   2432: bipush #32
    //   2434: irem
    //   2435: invokestatic abs : (I)I
    //   2438: invokevirtual charAt : (I)C
    //   2441: invokevirtual append : (C)Ljava/lang/StringBuilder;
    //   2444: pop
    //   2445: iload_2
    //   2446: ifne -> 2600
    //   2449: goto -> 2456
    //   2452: invokestatic a : (Ljava/lang/Throwable;)Ljava/lang/Throwable;
    //   2455: athrow
    //   2456: aload_3
    //   2457: getstatic burp/Zes_.ZM : Ljava/lang/String;
    //   2460: getstatic burp/Zter.Zc : Ljava/lang/Object;
    //   2463: checkcast java/math/BigInteger
    //   2466: invokevirtual intValue : ()I
    //   2469: bipush #32
    //   2471: irem
    //   2472: invokestatic abs : (I)I
    //   2475: invokevirtual charAt : (I)C
    //   2478: invokevirtual append : (C)Ljava/lang/StringBuilder;
    //   2481: pop
    //   2482: iload_2
    //   2483: ifne -> 2600
    //   2486: goto -> 2493
    //   2489: invokestatic a : (Ljava/lang/Throwable;)Ljava/lang/Throwable;
    //   2492: athrow
    //   2493: aload_3
    //   2494: getstatic burp/Ztnw.Zr : Ljava/lang/String;
    //   2497: getstatic burp/Zx4l.Zt : Ljava/lang/Object;
    //   2500: checkcast java/math/BigInteger
    //   2503: invokevirtual intValue : ()I
    //   2506: bipush #32
    //   2508: irem
    //   2509: invokestatic abs : (I)I
    //   2512: invokevirtual charAt : (I)C
    //   2515: invokevirtual append : (C)Ljava/lang/StringBuilder;
    //   2518: pop
    //   2519: iload_2
    //   2520: ifne -> 2600
    //   2523: goto -> 2530
    //   2526: invokestatic a : (Ljava/lang/Throwable;)Ljava/lang/Throwable;
    //   2529: athrow
    //   2530: aload_3
    //   2531: getstatic burp/Ze7q.ZW : Ljava/lang/String;
    //   2534: getstatic burp/Zrbp.Z_ : Ljava/lang/Object;
    //   2537: checkcast java/math/BigInteger
    //   2540: invokevirtual intValue : ()I
    //   2543: bipush #32
    //   2545: irem
    //   2546: invokestatic abs : (I)I
    //   2549: invokevirtual charAt : (I)C
    //   2552: invokevirtual append : (C)Ljava/lang/StringBuilder;
    //   2555: pop
    //   2556: iload_2
    //   2557: ifne -> 2600
    //   2560: goto -> 2567
    //   2563: invokestatic a : (Ljava/lang/Throwable;)Ljava/lang/Throwable;
    //   2566: athrow
    //   2567: aload_3
    //   2568: getstatic burp/Zrbp.Ze : Ljava/lang/String;
    //   2571: getstatic burp/Zlv6.ZN : Ljava/lang/Object;
    //   2574: checkcast java/math/BigInteger
    //   2577: invokevirtual intValue : ()I
    //   2580: bipush #32
    //   2582: irem
    //   2583: invokestatic abs : (I)I
    //   2586: invokevirtual charAt : (I)C
    //   2589: invokevirtual append : (C)Ljava/lang/StringBuilder;
    //   2592: pop
    //   2593: goto -> 2600
    //   2596: invokestatic a : (Ljava/lang/Throwable;)Ljava/lang/Throwable;
    //   2599: athrow
    //   2600: iinc #4, 1
    //   2603: iload_2
    //   2604: ifne -> 1270
    //   2607: aload_3
    //   2608: invokevirtual toString : ()Ljava/lang/String;
    //   2611: putstatic burp/Zkig.ZE : Ljava/lang/String;
    //   2614: sipush #-1776
    //   2617: sipush #-2711
    //   2620: invokestatic a : (II)Ljava/lang/String;
    //   2623: iconst_1
    //   2624: ldc burp/Zr64
    //   2626: invokevirtual getClassLoader : ()Ljava/lang/ClassLoader;
    //   2629: invokestatic forName : (Ljava/lang/String;ZLjava/lang/ClassLoader;)Ljava/lang/Class;
    //   2632: invokevirtual getDeclaredFields : ()[Ljava/lang/reflect/Field;
    //   2635: astore #4
    //   2637: aload #4
    //   2639: arraylength
    //   2640: istore #5
    //   2642: iconst_0
    //   2643: istore #6
    //   2645: iload #6
    //   2647: iload #5
    //   2649: if_icmpge -> 2787
    //   2652: aload #4
    //   2654: iload #6
    //   2656: aaload
    //   2657: astore #7
    //   2659: aload #7
    //   2661: invokevirtual getModifiers : ()I
    //   2664: invokestatic isStatic : (I)Z
    //   2667: ifne -> 2677
    //   2670: goto -> 2780
    //   2673: invokestatic a : (Ljava/lang/Throwable;)Ljava/lang/Throwable;
    //   2676: athrow
    //   2677: aload #7
    //   2679: invokevirtual getType : ()Ljava/lang/Class;
    //   2682: astore #8
    //   2684: aload #8
    //   2686: ifnull -> 2767
    //   2689: aload #8
    //   2691: invokevirtual isPrimitive : ()Z
    //   2694: ifne -> 2767
    //   2697: goto -> 2704
    //   2700: invokestatic a : (Ljava/lang/Throwable;)Ljava/lang/Throwable;
    //   2703: athrow
    //   2704: aload #8
    //   2706: invokevirtual getPackage : ()Ljava/lang/Package;
    //   2709: ifnull -> 2767
    //   2712: goto -> 2719
    //   2715: invokestatic a : (Ljava/lang/Throwable;)Ljava/lang/Throwable;
    //   2718: athrow
    //   2719: aload #8
    //   2721: invokevirtual getPackage : ()Ljava/lang/Package;
    //   2724: invokevirtual getName : ()Ljava/lang/String;
    //   2727: ifnull -> 2767
    //   2730: goto -> 2737
    //   2733: invokestatic a : (Ljava/lang/Throwable;)Ljava/lang/Throwable;
    //   2736: athrow
    //   2737: aload #8
    //   2739: invokevirtual getPackage : ()Ljava/lang/Package;
    //   2742: invokevirtual getName : ()Ljava/lang/String;
    //   2745: sipush #-1765
    //   2748: sipush #-24702
    //   2751: invokestatic a : (II)Ljava/lang/String;
    //   2754: invokevirtual startsWith : (Ljava/lang/String;)Z
    //   2757: ifne -> 2767
    //   2760: goto -> 2767
    //   2763: invokestatic a : (Ljava/lang/Throwable;)Ljava/lang/Throwable;
    //   2766: athrow
    //   2767: aload #7
    //   2769: iconst_1
    //   2770: invokevirtual setAccessible : (Z)V
    //   2773: aload #7
    //   2775: aconst_null
    //   2776: invokevirtual get : (Ljava/lang/Object;)Ljava/lang/Object;
    //   2779: pop
    //   2780: iinc #6, 1
    //   2783: iload_2
    //   2784: ifne -> 2645
    //   2787: sipush #-1767
    //   2790: sipush #-6339
    //   2793: invokestatic a : (II)Ljava/lang/String;
    //   2796: invokestatic forName : (Ljava/lang/String;)Ljava/lang/Class;
    //   2799: invokevirtual getDeclaredMethods : ()[Ljava/lang/reflect/Method;
    //   2802: astore #4
    //   2804: aload #4
    //   2806: arraylength
    //   2807: istore #5
    //   2809: iconst_0
    //   2810: istore #6
    //   2812: iload #6
    //   2814: iload #5
    //   2816: if_icmpge -> 2949
    //   2819: aload #4
    //   2821: iload #6
    //   2823: aaload
    //   2824: astore #7
    //   2826: aload #7
    //   2828: invokevirtual getParameterTypes : ()[Ljava/lang/Class;
    //   2831: pop
    //   2832: aload #7
    //   2834: invokevirtual getModifiers : ()I
    //   2837: invokestatic isStatic : (I)Z
    //   2840: ifeq -> 2935
    //   2843: aload #7
    //   2845: invokevirtual getParameterTypes : ()[Ljava/lang/Class;
    //   2848: arraylength
    //   2849: iconst_2
    //   2850: if_icmpne -> 2935
    //   2853: goto -> 2860
    //   2856: invokestatic a : (Ljava/lang/Throwable;)Ljava/lang/Throwable;
    //   2859: athrow
    //   2860: aload #7
    //   2862: invokevirtual getReturnType : ()Ljava/lang/Class;
    //   2865: getstatic java/lang/Void.TYPE : Ljava/lang/Class;
    //   2868: invokevirtual equals : (Ljava/lang/Object;)Z
    //   2871: ifeq -> 2935
    //   2874: goto -> 2881
    //   2877: invokestatic a : (Ljava/lang/Throwable;)Ljava/lang/Throwable;
    //   2880: athrow
    //   2881: aload #7
    //   2883: iconst_1
    //   2884: invokevirtual setAccessible : (Z)V
    //   2887: aload #7
    //   2889: aconst_null
    //   2890: iconst_2
    //   2891: anewarray java/lang/Object
    //   2894: dup
    //   2895: iconst_0
    //   2896: aload_0
    //   2897: aastore
    //   2898: dup
    //   2899: iconst_1
    //   2900: aload_1
    //   2901: ifnonnull -> 2919
    //   2904: goto -> 2911
    //   2907: invokestatic a : (Ljava/lang/Throwable;)Ljava/lang/Throwable;
    //   2910: athrow
    //   2911: aload_1
    //   2912: goto -> 2926
    //   2915: invokestatic a : (Ljava/lang/Throwable;)Ljava/lang/Throwable;
    //   2918: athrow
    //   2919: aload_1
    //   2920: checkcast [B
    //   2923: invokevirtual clone : ()Ljava/lang/Object;
    //   2926: aastore
    //   2927: invokevirtual invoke : (Ljava/lang/Object;[Ljava/lang/Object;)Ljava/lang/Object;
    //   2930: pop
    //   2931: iload_2
    //   2932: ifne -> 2949
    //   2935: iinc #6, 1
    //   2938: iload_2
    //   2939: ifne -> 2812
    //   2942: goto -> 2949
    //   2945: invokestatic a : (Ljava/lang/Throwable;)Ljava/lang/Throwable;
    //   2948: athrow
    //   2949: getstatic burp/Zrnu.ZO : Ljava/lang/String;
    //   2952: getstatic burp/Zkyc.ZD : Ljava/lang/Object;
    //   2955: checkcast java/math/BigInteger
    //   2958: invokevirtual intValue : ()I
    //   2961: bipush #32
    //   2963: irem
    //   2964: invokestatic abs : (I)I
    //   2967: invokevirtual charAt : (I)C
    //   2970: getstatic burp/Zllw.Zg : Ljava/lang/String;
    //   2973: getstatic burp/Zt3l.Zq : Ljava/lang/Object;
    //   2976: checkcast java/math/BigInteger
    //   2979: invokevirtual intValue : ()I
    //   2982: bipush #32
    //   2984: irem
    //   2985: invokestatic abs : (I)I
    //   2988: invokevirtual charAt : (I)C
    //   2991: if_icmpgt -> 3106
    //   2994: getstatic burp/Zbp.Z_ : Ljava/lang/String;
    //   2997: getstatic burp/Zedz.Za : Ljava/lang/Object;
    //   3000: checkcast java/math/BigInteger
    //   3003: invokevirtual intValue : ()I
    //   3006: bipush #32
    //   3008: irem
    //   3009: invokestatic abs : (I)I
    //   3012: invokevirtual charAt : (I)C
    //   3015: getstatic burp/Zg0j.Ze : Ljava/lang/String;
    //   3018: getstatic burp/Zb3z.ZR : Ljava/lang/Object;
    //   3021: checkcast java/math/BigInteger
    //   3024: invokevirtual intValue : ()I
    //   3027: bipush #32
    //   3029: irem
    //   3030: invokestatic abs : (I)I
    //   3033: invokevirtual charAt : (I)C
    //   3036: if_icmple -> 3106
    //   3039: goto -> 3046
    //   3042: invokestatic a : (Ljava/lang/Throwable;)Ljava/lang/Throwable;
    //   3045: athrow
    //   3046: getstatic burp/Zb8v.Zo : Ljava/lang/String;
    //   3049: getstatic burp/Zkmx.Zu : Ljava/lang/Object;
    //   3052: checkcast java/math/BigInteger
    //   3055: invokevirtual intValue : ()I
    //   3058: bipush #32
    //   3060: irem
    //   3061: invokestatic abs : (I)I
    //   3064: invokevirtual charAt : (I)C
    //   3067: getstatic burp/Zl2g.ZI : Ljava/lang/String;
    //   3070: getstatic burp/Zm__.Zz : Ljava/lang/Object;
    //   3073: checkcast java/math/BigInteger
    //   3076: invokevirtual intValue : ()I
    //   3079: bipush #32
    //   3081: irem
    //   3082: invokestatic abs : (I)I
    //   3085: invokevirtual charAt : (I)C
    //   3088: if_icmpgt -> 3106
    //   3091: goto -> 3098
    //   3094: invokestatic a : (Ljava/lang/Throwable;)Ljava/lang/Throwable;
    //   3097: athrow
    //   3098: iconst_1
    //   3099: goto -> 3107
    //   3102: invokestatic a : (Ljava/lang/Throwable;)Ljava/lang/Throwable;
    //   3105: athrow
    //   3106: iconst_0
    //   3107: ireturn
    //   3108: astore_3
    //   3109: new java/lang/Exception
    //   3112: dup
    //   3113: aload_3
    //   3114: invokevirtual getMessage : ()Ljava/lang/String;
    //   3117: invokespecial <init> : (Ljava/lang/String;)V
    //   3120: athrow
    // Exception table:
    //   from	to	target	type
    //   4	3107	3108	java/lang/Throwable
    //   185	209	212	java/lang/Throwable
    //   283	320	320	java/lang/Throwable
    //   324	345	345	java/lang/Throwable
    //   349	379	379	java/lang/Throwable
    //   882	906	909	java/lang/Throwable
    //   980	1017	1017	java/lang/Throwable
    //   1021	1042	1042	java/lang/Throwable
    //   1046	1076	1076	java/lang/Throwable
    //   1277	1450	1453	java/lang/Throwable
    //   1420	1487	1490	java/lang/Throwable
    //   1457	1524	1527	java/lang/Throwable
    //   1494	1561	1564	java/lang/Throwable
    //   1531	1598	1601	java/lang/Throwable
    //   1568	1635	1638	java/lang/Throwable
    //   1605	1672	1675	java/lang/Throwable
    //   1642	1709	1712	java/lang/Throwable
    //   1679	1746	1749	java/lang/Throwable
    //   1716	1783	1786	java/lang/Throwable
    //   1753	1820	1823	java/lang/Throwable
    //   1790	1857	1860	java/lang/Throwable
    //   1827	1894	1897	java/lang/Throwable
    //   1864	1931	1934	java/lang/Throwable
    //   1901	1968	1971	java/lang/Throwable
    //   1938	2005	2008	java/lang/Throwable
    //   1975	2042	2045	java/lang/Throwable
    //   2012	2079	2082	java/lang/Throwable
    //   2049	2116	2119	java/lang/Throwable
    //   2086	2153	2156	java/lang/Throwable
    //   2123	2190	2193	java/lang/Throwable
    //   2160	2227	2230	java/lang/Throwable
    //   2197	2264	2267	java/lang/Throwable
    //   2234	2301	2304	java/lang/Throwable
    //   2271	2338	2341	java/lang/Throwable
    //   2308	2375	2378	java/lang/Throwable
    //   2345	2412	2415	java/lang/Throwable
    //   2382	2449	2452	java/lang/Throwable
    //   2419	2486	2489	java/lang/Throwable
    //   2456	2523	2526	java/lang/Throwable
    //   2493	2560	2563	java/lang/Throwable
    //   2530	2593	2596	java/lang/Throwable
    //   2659	2673	2673	java/lang/Throwable
    //   2684	2697	2700	java/lang/Throwable
    //   2689	2712	2715	java/lang/Throwable
    //   2704	2730	2733	java/lang/Throwable
    //   2719	2760	2763	java/lang/Throwable
    //   2826	2853	2856	java/lang/Throwable
    //   2843	2874	2877	java/lang/Throwable
    //   2860	2904	2907	java/lang/Throwable
    //   2881	2915	2915	java/lang/Throwable
    //   2926	2942	2945	java/lang/Throwable
    //   2949	3039	3042	java/lang/Throwable
    //   2994	3091	3094	java/lang/Throwable
    //   3046	3102	3102	java/lang/Throwable
  }
  
  static {
    // Byte code:
    //   0: bipush #11
    //   2: anewarray java/lang/String
    //   5: astore #5
    //   7: iconst_0
    //   8: istore_3
    //   9: ldc 'b5tU\\t\\b]aHg uUCpb;([Tr\\t;\\n v*cTDe#G-d>e$$-.\\tH %L<\\rA&=Gy.[ L\\t"c^'
    //   11: dup
    //   12: astore_2
    //   13: invokevirtual length : ()I
    //   16: istore #4
    //   18: bipush #9
    //   20: istore_1
    //   21: iconst_m1
    //   22: istore_0
    //   23: bipush #20
    //   25: iinc #0, 1
    //   28: aload_2
    //   29: iload_0
    //   30: dup
    //   31: iload_1
    //   32: iadd
    //   33: invokevirtual substring : (II)Ljava/lang/String;
    //   36: iconst_m1
    //   37: goto -> 143
    //   40: aload #5
    //   42: swap
    //   43: iload_3
    //   44: iinc #3, 1
    //   47: swap
    //   48: aastore
    //   49: iload_0
    //   50: iload_1
    //   51: iadd
    //   52: dup
    //   53: istore_0
    //   54: iload #4
    //   56: if_icmpge -> 68
    //   59: aload_2
    //   60: iload_0
    //   61: invokevirtual charAt : (I)C
    //   64: istore_1
    //   65: goto -> 23
    //   68: ldc '6P0&.u_tS/%\Jk8@B|K)1A\\fH,/kK'
    //   70: dup
    //   71: astore_2
    //   72: invokevirtual length : ()I
    //   75: istore #4
    //   77: bipush #77
    //   79: istore_1
    //   80: iconst_m1
    //   81: istore_0
    //   82: bipush #63
    //   84: iinc #0, 1
    //   87: aload_2
    //   88: iload_0
    //   89: dup
    //   90: iload_1
    //   91: iadd
    //   92: invokevirtual substring : (II)Ljava/lang/String;
    //   95: iconst_0
    //   96: goto -> 143
    //   99: aload #5
    //   101: swap
    //   102: iload_3
    //   103: iinc #3, 1
    //   106: swap
    //   107: aastore
    //   108: iload_0
    //   109: iload_1
    //   110: iadd
    //   111: dup
    //   112: istore_0
    //   113: iload #4
    //   115: if_icmpge -> 127
    //   118: aload_2
    //   119: iload_0
    //   120: invokevirtual charAt : (I)C
    //   123: istore_1
    //   124: goto -> 82
    //   127: aload #5
    //   129: putstatic burp/Zzsq.a : [Ljava/lang/String;
    //   132: bipush #11
    //   134: anewarray java/lang/String
    //   137: putstatic burp/Zzsq.b : [Ljava/lang/String;
    //   140: goto -> 300
    //   143: dup_x2
    //   144: pop
    //   145: invokevirtual toCharArray : ()[C
    //   148: dup_x1
    //   149: arraylength
    //   150: dup_x2
    //   151: pop
    //   152: iconst_0
    //   153: istore #6
    //   155: dup2_x1
    //   156: pop2
    //   157: dup_x2
    //   158: iconst_1
    //   159: if_icmpgt -> 259
    //   162: dup2
    //   163: swap
    //   164: iload #6
    //   166: dup2_x1
    //   167: caload
    //   168: swap
    //   169: iload #6
    //   171: bipush #7
    //   173: irem
    //   174: tableswitch default -> 241, 0 -> 212, 1 -> 217, 2 -> 222, 3 -> 227, 4 -> 231, 5 -> 236
    //   212: bipush #58
    //   214: goto -> 243
    //   217: bipush #68
    //   219: goto -> 243
    //   222: bipush #109
    //   224: goto -> 243
    //   227: iconst_2
    //   228: goto -> 243
    //   231: bipush #24
    //   233: goto -> 243
    //   236: bipush #32
    //   238: goto -> 243
    //   241: bipush #54
    //   243: ixor
    //   244: ixor
    //   245: i2c
    //   246: castore
    //   247: iinc #6, 1
    //   250: dup
    //   251: ifne -> 259
    //   254: dup2
    //   255: dup_x1
    //   256: goto -> 166
    //   259: dup2_x1
    //   260: pop2
    //   261: dup_x2
    //   262: iload #6
    //   264: if_icmpgt -> 162
    //   267: pop
    //   268: new java/lang/String
    //   271: dup_x1
    //   272: swap
    //   273: invokespecial <init> : ([C)V
    //   276: invokevirtual intern : ()Ljava/lang/String;
    //   279: swap
    //   280: pop
    //   281: swap
    //   282: tableswitch default -> 40, 0 -> 99
    //   300: new java/math/BigInteger
    //   303: dup
    //   304: iconst_1
    //   305: bipush #32
    //   307: newarray byte
    //   309: dup
    //   310: iconst_0
    //   311: bipush #23
    //   313: bastore
    //   314: dup
    //   315: iconst_1
    //   316: bipush #-31
    //   318: bastore
    //   319: dup
    //   320: iconst_2
    //   321: bipush #-65
    //   323: bastore
    //   324: dup
    //   325: iconst_3
    //   326: bipush #53
    //   328: bastore
    //   329: dup
    //   330: iconst_4
    //   331: bipush #10
    //   333: bastore
    //   334: dup
    //   335: iconst_5
    //   336: bipush #101
    //   338: bastore
    //   339: dup
    //   340: bipush #6
    //   342: bipush #114
    //   344: bastore
    //   345: dup
    //   346: bipush #7
    //   348: bipush #-68
    //   350: bastore
    //   351: dup
    //   352: bipush #8
    //   354: bipush #-25
    //   356: bastore
    //   357: dup
    //   358: bipush #9
    //   360: bipush #113
    //   362: bastore
    //   363: dup
    //   364: bipush #10
    //   366: bipush #15
    //   368: bastore
    //   369: dup
    //   370: bipush #11
    //   372: bipush #86
    //   374: bastore
    //   375: dup
    //   376: bipush #12
    //   378: bipush #18
    //   380: bastore
    //   381: dup
    //   382: bipush #13
    //   384: bipush #-29
    //   386: bastore
    //   387: dup
    //   388: bipush #14
    //   390: bipush #-84
    //   392: bastore
    //   393: dup
    //   394: bipush #15
    //   396: bipush #8
    //   398: bastore
    //   399: dup
    //   400: bipush #16
    //   402: bipush #-32
    //   404: bastore
    //   405: dup
    //   406: bipush #17
    //   408: bipush #-63
    //   410: bastore
    //   411: dup
    //   412: bipush #18
    //   414: bipush #117
    //   416: bastore
    //   417: dup
    //   418: bipush #19
    //   420: bipush #-50
    //   422: bastore
    //   423: dup
    //   424: bipush #20
    //   426: bipush #-61
    //   428: bastore
    //   429: dup
    //   430: bipush #21
    //   432: bipush #-11
    //   434: bastore
    //   435: dup
    //   436: bipush #22
    //   438: bipush #-20
    //   440: bastore
    //   441: dup
    //   442: bipush #23
    //   444: bipush #-124
    //   446: bastore
    //   447: dup
    //   448: bipush #24
    //   450: bipush #-22
    //   452: bastore
    //   453: dup
    //   454: bipush #25
    //   456: bipush #-22
    //   458: bastore
    //   459: dup
    //   460: bipush #26
    //   462: bipush #34
    //   464: bastore
    //   465: dup
    //   466: bipush #27
    //   468: bipush #-3
    //   470: bastore
    //   471: dup
    //   472: bipush #28
    //   474: bipush #-23
    //   476: bastore
    //   477: dup
    //   478: bipush #29
    //   480: bipush #77
    //   482: bastore
    //   483: dup
    //   484: bipush #30
    //   486: bipush #19
    //   488: bastore
    //   489: dup
    //   490: bipush #31
    //   492: bipush #-47
    //   494: bastore
    //   495: invokespecial <init> : (I[B)V
    //   498: putstatic burp/Zzsq.Zh : Ljava/lang/Object;
    //   501: sipush #-1771
    //   504: sipush #31172
    //   507: invokestatic a : (II)Ljava/lang/String;
    //   510: putstatic burp/Zzsq.Zc : Ljava/lang/String;
    //   513: return
  }
  
  private static Throwable a(Throwable paramThrowable) {
    return paramThrowable;
  }
  
  private static String a(int paramInt1, int paramInt2) {
    int i = (paramInt1 ^ 0xFFFFF911) & 0xFFFF;
    if (b[i] == null) {
      char[] arrayOfChar = a[i].toCharArray();
      switch (arrayOfChar[0] & 0xFF) {
        case 0:
        
        case 1:
        
        case 2:
        
        case 3:
        
        case 4:
        
        case 5:
        
        case 6:
        
        case 7:
        
        case 8:
        
        case 9:
        
        case 10:
        
        case 11:
        
        case 12:
        
        case 13:
        
        case 14:
        
        case 15:
        
        case 16:
        
        case 17:
        
        case 18:
        
        case 19:
        
        case 20:
        
        case 21:
        
        case 22:
        
        case 23:
        
        case 24:
        
        case 25:
        
        case 26:
        
        case 27:
        
        case 28:
        
        case 29:
        
        case 30:
        
        case 31:
        
        case 32:
        
        case 33:
        
        case 34:
        
        case 35:
        
        case 36:
        
        case 37:
        
        case 38:
        
        case 39:
        
        case 40:
        
        case 41:
        
        case 42:
        
        case 43:
        
        case 44:
        
        case 45:
        
        case 46:
        
        case 47:
        
        case 48:
        
        case 49:
        
        case 50:
        
        case 51:
        
        case 52:
        
        case 53:
        
        case 54:
        
        case 55:
        
        case 56:
        
        case 57:
        
        case 58:
        
        case 59:
        
        case 60:
        
        case 61:
        
        case 62:
        
        case 63:
        
        case 64:
        
        case 65:
        
        case 66:
        
        case 67:
        
        case 68:
        
        case 69:
        
        case 70:
        
        case 71:
        
        case 72:
        
        case 73:
        
        case 74:
        
        case 75:
        
        case 76:
        
        case 77:
        
        case 78:
        
        case 79:
        
        case 80:
        
        case 81:
        
        case 82:
        
        case 83:
        
        case 84:
        
        case 85:
        
        case 86:
        
        case 87:
        
        case 88:
        
        case 89:
        
        case 90:
        
        case 91:
        
        case 92:
        
        case 93:
        
        case 94:
        
        case 95:
        
        case 96:
        
        case 97:
        
        case 98:
        
        case 99:
        
        case 100:
        
        case 101:
        
        case 102:
        
        case 103:
        
        case 104:
        
        case 105:
        
        case 106:
        
        case 107:
        
        case 108:
        
        case 109:
        
        case 110:
        
        case 111:
        
        case 112:
        
        case 113:
        
        case 114:
        
        case 115:
        
        case 116:
        
        case 117:
        
        case 118:
        
        case 119:
        
        case 120:
        
        case 121:
        
        case 122:
        
        case 123:
        
        case 124:
        
        case 125:
        
        case 126:
        
        case 127:
        
        case 128:
        
        case 129:
        
        case 130:
        
        case 131:
        
        case 132:
        
        case 133:
        
        case 134:
        
        case 135:
        
        case 136:
        
        case 137:
        
        case 138:
        
        case 139:
        
        case 140:
        
        case 141:
        
        case 142:
        
        case 143:
        
        case 144:
        
        case 145:
        
        case 146:
        
        case 147:
        
        case 148:
        
        case 149:
        
        case 150:
        
        case 151:
        
        case 152:
        
        case 153:
        
        case 154:
        
        case 155:
        
        case 156:
        
        case 157:
        
        case 158:
        
        case 159:
        
        case 160:
        
        case 161:
        
        case 162:
        
        case 163:
        
        case 164:
        
        case 165:
        
        case 166:
        
        case 167:
        
        case 168:
        
        case 169:
        
        case 170:
        
        case 171:
        
        case 172:
        
        case 173:
        
        case 174:
        
        case 175:
        
        case 176:
        
        case 177:
        
        case 178:
        
        case 179:
        
        case 180:
        
        case 181:
        
        case 182:
        
        case 183:
        
        case 184:
        
        case 185:
        
        case 186:
        
        case 187:
        
        case 188:
        
        case 189:
        
        case 190:
        
        case 191:
        
        case 192:
        
        case 193:
        
        case 194:
        
        case 195:
        
        case 196:
        
        case 197:
        
        case 198:
        
        case 199:
        
        case 200:
        
        case 201:
        
        case 202:
        
        case 203:
        
        case 204:
        
        case 205:
        
        case 206:
        
        case 207:
        
        case 208:
        
        case 209:
        
        case 210:
        
        case 211:
        
        case 212:
        
        case 213:
        
        case 214:
        
        case 215:
        
        case 216:
        
        case 217:
        
        case 218:
        
        case 219:
        
        case 220:
        
        case 221:
        
        case 222:
        
        case 223:
        
        case 224:
        
        case 225:
        
        case 226:
        
        case 227:
        
        case 228:
        
        case 229:
        
        case 230:
        
        case 231:
        
        case 232:
        
        case 233:
        
        case 234:
        
        case 235:
        
        case 236:
        
        case 237:
        
        case 238:
        
        case 239:
        
        case 240:
        
        case 241:
        
        case 242:
        
        case 243:
        
        case 244:
        
        case 245:
        
        case 246:
        
        case 247:
        
        case 248:
        
        case 249:
        
        case 250:
        
        case 251:
        
        case 252:
        
        case 253:
        
        case 254:
        
        default:
          break;
      } 
      byte b1 = 67;
      int j = (paramInt2 & 0xFF) - b1;
      if (j < 0)
        j += 256; 
      int k = ((paramInt2 & 0xFFFF) >>> 8) - b1;
      if (k < 0)
        k += 256; 
      for (byte b2 = 0; b2 < arrayOfChar.length; b2++) {
        int m = b2 % 2;
        if (m == 0) {
          arrayOfChar[b2] = (char)(arrayOfChar[b2] ^ j);
          j = ((j >>> 3 | j << 5) ^ arrayOfChar[b2]) & 0xFF;
        } else {
          arrayOfChar[b2] = (char)(arrayOfChar[b2] ^ k);
          k = ((k >>> 3 | k << 5) ^ arrayOfChar[b2]) & 0xFF;
        } 
      } 
      b[i] = (new String(arrayOfChar)).intern();
    } 
    return b[i];
  }
}


/* Location:              C:\Program Files\BurpSuitePro\burpsuite_pro.jar!\burp\Zzsq.class
 * Java compiler version: 21 (65.0)
 * JD-Core Version:       1.1.3
 */