package burp;

import java.util.List;
import java.util.Locale;
import javax.swing.SortOrder;
import net.portswigger.Zqf;
import net.portswigger.Zuh;

public class Zzu0 implements Zekl {
  private static final List<String> ZJ;
  
  private static final List<String> Zi;
  
  private final Zxp6 ZR;
  
  private final Zm3g ZC;
  
  private final Zm3g Zo;
  
  private final Zrz ZQ;
  
  private final Zz4u ZB;
  
  private final Zs2p ZV;
  
  private int Zw = -1;
  
  private SortOrder ZD = SortOrder.ASCENDING;
  
  private int Zn = -1;
  
  private SortOrder ZM = SortOrder.ASCENDING;
  
  private static final String[] a;
  
  private static final String[] b;
  
  public Zzu0(Zxp6 paramZxp6, Zm3g paramZm3g1, Zm3g paramZm3g2, Zrz paramZrz, Zz4u paramZz4u, Zs2p paramZs2p) {
    this.ZR = paramZxp6;
    this.ZC = paramZm3g1;
    this.Zo = paramZm3g2;
    this.ZQ = paramZrz;
    this.ZB = paramZz4u;
    this.ZV = paramZs2p;
  }
  
  public Zl34 Zlb() {
    return this.ZR.ZyG();
  }
  
  public boolean Zll() {
    return this.ZR.ZyW();
  }
  
  public void Zfy(boolean paramBoolean) {
    this.ZR.ZNH(paramBoolean);
  }
  
  public boolean ZlJ() {
    return this.ZR.ZyN();
  }
  
  public void ZfB(boolean paramBoolean) {
    this.ZR.ZNT(paramBoolean);
  }
  
  public boolean Zlv() {
    return this.ZR.Zy9();
  }
  
  public void Zfi(boolean paramBoolean) {
    this.ZR.ZNA(paramBoolean);
  }
  
  public boolean ZlC() {
    return this.ZR.Zy2();
  }
  
  public void Zfu(boolean paramBoolean) {
    this.ZR.ZN5(paramBoolean);
  }
  
  public boolean Zl0() {
    return this.ZR.Zym();
  }
  
  public void ZfY(boolean paramBoolean) {
    this.ZR.ZNx(paramBoolean);
  }
  
  public boolean ZlM() {
    return this.ZR.ZuV();
  }
  
  public void Zft(boolean paramBoolean) {
    this.ZR.ZN7(paramBoolean);
  }
  
  public boolean Zlo() {
    return this.ZR.Zy8();
  }
  
  public void ZfO(boolean paramBoolean) {
    this.ZR.ZNW(paramBoolean);
  }
  
  public boolean Zlg() {
    return this.ZR.Zye();
  }
  
  public void Zfm(boolean paramBoolean) {
    this.ZR.ZNd(paramBoolean);
  }
  
  public boolean Zlk() {
    return this.ZR.Zy1();
  }
  
  public void Zfb(boolean paramBoolean) {
    this.ZR.ZNF(paramBoolean);
  }
  
  public boolean ZlR() {
    return this.ZR.ZyC();
  }
  
  public void Zfp(boolean paramBoolean) {
    this.ZR.ZNo(paramBoolean);
  }
  
  public boolean Zl9() {
    return this.ZR.ZyM();
  }
  
  public void Zfc(boolean paramBoolean) {
    this.ZR.ZNj(paramBoolean);
  }
  
  public boolean ZlS() {
    return this.ZR.ZyA();
  }
  
  public void Zf7(boolean paramBoolean) {
    this.ZR.ZND(paramBoolean);
  }
  
  public boolean Zlc() {
    return this.ZR.Zyj();
  }
  
  public void ZfL(boolean paramBoolean) {
    this.ZR.ZNt(paramBoolean);
    ZIN();
  }
  
  public boolean ZlI() {
    return this.ZR.Zur();
  }
  
  public void ZfI(boolean paramBoolean) {
    this.ZR.ZNr(paramBoolean);
    ZIN();
  }
  
  public boolean ZlY() {
    return this.ZR.Zya();
  }
  
  public void ZfG(boolean paramBoolean) {
    this.ZR.ZNn(paramBoolean);
  }
  
  public boolean ZlT() {
    return this.ZR.ZyH();
  }
  
  public void Zfh(boolean paramBoolean) {
    this.ZR.ZNu(paramBoolean);
  }
  
  public boolean ZlU() {
    return this.ZR.ZyE();
  }
  
  public void Zfv(boolean paramBoolean) {
    this.ZR.ZN9(paramBoolean);
  }
  
  public boolean Zl5() {
    return this.ZR.Zyf();
  }
  
  public void Zf0(boolean paramBoolean) {
    this.ZR.ZNz(paramBoolean);
  }
  
  public boolean Zl7() {
    return this.ZR.Zyo();
  }
  
  public void ZfJ(boolean paramBoolean) {
    this.ZR.ZNy(paramBoolean);
  }
  
  public boolean Zlx() {
    return this.ZR.ZyU();
  }
  
  public void Zf5(boolean paramBoolean) {
    this.ZR.ZNL(paramBoolean);
  }
  
  public boolean Zlw() {
    return this.ZR.ZyI();
  }
  
  public void ZfU(boolean paramBoolean) {
    this.ZR.ZNP(paramBoolean);
  }
  
  public boolean Zlu() {
    return this.ZR.Zyr();
  }
  
  public void Zf6(boolean paramBoolean) {
    this.ZR.ZNK(paramBoolean);
  }
  
  public boolean ZlF() {
    return this.ZR.ZyQ();
  }
  
  public void ZfF(boolean paramBoolean) {
    this.ZR.ZNk(paramBoolean);
  }
  
  public boolean ZlZ() {
    return this.ZR.Zyy();
  }
  
  public void ZfA(boolean paramBoolean) {
    this.ZR.ZNi(paramBoolean);
  }
  
  public boolean ZlD() {
    return this.ZR.ZyS();
  }
  
  public void Zfg(boolean paramBoolean) {
    this.ZR.ZNB(paramBoolean);
  }
  
  public boolean Zls() {
    return this.ZR.Zyk();
  }
  
  public void ZfW(boolean paramBoolean) {
    this.ZR.ZN6(paramBoolean);
  }
  
  public int Zl3() {
    return this.ZQ.Zkq();
  }
  
  public boolean Zld() {
    return this.ZR.ZyO();
  }
  
  public void Zf_(boolean paramBoolean) {
    this.ZR.ZNR(paramBoolean);
  }
  
  public boolean Zl2() {
    return this.ZR.Zyh();
  }
  
  public void Zfn(boolean paramBoolean) {
    this.ZR.ZNw(paramBoolean);
  }
  
  public boolean Zl1() {
    return this.ZR.Zu_();
  }
  
  public void ZfR(boolean paramBoolean) {
    this.ZR.ZN2(paramBoolean);
  }
  
  public boolean ZlV() {
    return this.ZR.ZyZ();
  }
  
  public void ZfX(boolean paramBoolean) {
    this.ZR.ZNY(paramBoolean);
  }
  
  public boolean ZlA() {
    return this.ZR.ZyF();
  }
  
  public void ZfN(boolean paramBoolean) {
    this.ZR.ZNG(paramBoolean);
  }
  
  public boolean ZlP() {
    return this.ZR.Zy_();
  }
  
  public void ZfT(boolean paramBoolean) {
    this.ZR.ZN8(paramBoolean);
  }
  
  public boolean ZlX() {
    return this.ZR.ZyD();
  }
  
  public void Zf3(boolean paramBoolean) {
    this.ZR.ZNV(paramBoolean);
  }
  
  public boolean ZlW() {
    return this.ZR.ZuZ();
  }
  
  public void ZfZ(boolean paramBoolean) {
    this.ZR.ZNO(paramBoolean);
  }
  
  public boolean ZlL() {
    return this.ZR.Zyx();
  }
  
  public void Zfk(boolean paramBoolean) {
    this.ZR.ZNq(paramBoolean);
  }
  
  public boolean Zl6() {
    return this.ZR.Zy6();
  }
  
  public void Zh(boolean paramBoolean, Zbw_ paramZbw_) {
    this.ZR.ZNC(paramBoolean);
    if (paramZbw_ != null)
      paramZbw_.Zt2(); 
  }
  
  public void ZP(boolean paramBoolean, Zbw_ paramZbw_) {
    // Byte code:
    //   0: invokestatic Zv : ()[I
    //   3: astore_3
    //   4: aload_0
    //   5: invokevirtual Zl3 : ()I
    //   8: ifne -> 21
    //   11: aload_0
    //   12: iload_1
    //   13: aload_2
    //   14: invokevirtual Zh : (ZLburp/Zbw_;)V
    //   17: aload_3
    //   18: ifnull -> 39
    //   21: aload_0
    //   22: aload_0
    //   23: invokevirtual Zl3 : ()I
    //   26: iconst_1
    //   27: if_icmpne -> 34
    //   30: iconst_1
    //   31: goto -> 35
    //   34: iconst_0
    //   35: aload_2
    //   36: invokevirtual Zh : (ZLburp/Zbw_;)V
    //   39: return
  }
  
  public int Zln() {
    return this.Zw;
  }
  
  public void Zb(int paramInt) {
    this.Zw = paramInt;
  }
  
  public SortOrder Zle() {
    return this.ZD;
  }
  
  public void ZE(SortOrder paramSortOrder) {
    this.ZD = paramSortOrder;
  }
  
  public int ZlE() {
    return this.Zn;
  }
  
  public void ZV(int paramInt) {
    this.Zn = paramInt;
  }
  
  public SortOrder Zl4() {
    return this.ZM;
  }
  
  public void ZG(SortOrder paramSortOrder) {
    this.ZM = paramSortOrder;
  }
  
  public void Zd(Zmf_ paramZmf_) {
    ZfO(paramZmf_.ZC(a(26844, 9509), Zlo()));
    Zf_(paramZmf_.ZC(a(26823, -26345), Zld()));
    ZfG(paramZmf_.ZC(a(26848, 8434), ZlY()));
    Zfm(paramZmf_.ZC(a(26769, 4625), Zlg()));
    Zfy(paramZmf_.ZC(a(26770, -21463), Zll()));
    Zf3(paramZmf_.ZC(a(26858, 4288), ZlX()));
    ZfZ(paramZmf_.ZC(a(26825, -18744), ZlW()));
    Zfk(paramZmf_.ZC(a(26868, -5027), ZlL()));
    Zfh(paramZmf_.ZC(a(26873, 22791), ZlT()));
    Zfv(paramZmf_.ZC(a(26771, -4648), ZlU()));
    Zf0(paramZmf_.ZC(a(26834, 4476), Zl5()));
    ZfJ(paramZmf_.ZC(a(26865, 6898), Zl7()));
    Zf5(paramZmf_.ZC(a(26832, 24998), Zlx()));
    ZfU(paramZmf_.ZC(a(26776, -29018), Zlw()));
    Zf6(paramZmf_.ZC(a(26841, -31279), Zlu()));
    ZfF(paramZmf_.ZC(a(26777, 13659), ZlF()));
    ZfA(paramZmf_.ZC(a(26849, 20058), ZlZ()));
    Zfg(paramZmf_.ZC(a(26817, -4538), ZlD()));
    ZfW(paramZmf_.ZC(a(26826, -17374), Zls()));
    ZfB(paramZmf_.ZC(a(26829, 9038), ZlJ()));
    int[] arrayOfInt = Zr7c.Zv();
    Zfi(paramZmf_.ZC(a(26820, -13560), Zlv()));
    Zfu(paramZmf_.ZC(a(26773, -18992), ZlC()));
    ZfY(paramZmf_.ZC(a(26774, 31677), Zl0()));
    Zft(paramZmf_.ZC(a(26772, 19416), ZlM()));
    Zfn(paramZmf_.ZC(a(26871, 15440), Zl2()));
    ZfR(paramZmf_.ZC(a(26842, 32050), Zl1()));
    ZfX(paramZmf_.ZC(a(26775, -31904), ZlV()));
    ZfN(paramZmf_.ZC(a(26845, -29979), ZlA()));
    ZfT(paramZmf_.ZC(a(26837, 6186), ZlP()));
    Zfb(paramZmf_.ZC(a(26847, 32190), Zlk()));
    Zfp(paramZmf_.ZC(a(26878, -31001), ZlR()));
    Zfc(paramZmf_.ZC(a(26872, -4619), Zl9()));
    Zf7(paramZmf_.ZC(a(26852, 20415), ZlS()));
    ZfL(paramZmf_.ZC(a(26876, 30176), Zlc()));
    ZfI(paramZmf_.ZC(a(26874, -8288), ZlI()));
    Zb(paramZmf_.ZM(a(26850, -21631), ZJ, Zln()));
    ZE(ZT(paramZmf_.Zm(a(26879, -4232), Zle().toString()).toUpperCase(Locale.ENGLISH)));
    ZV(paramZmf_.ZM(a(26869, -14675), Zi, ZlE()));
    ZG(ZT(paramZmf_.Zm(a(26863, 8612), Zl4().toString()).toUpperCase(Locale.ENGLISH)));
    this.ZV.Zd(paramZmf_);
    this.ZQ.Zd(paramZmf_);
    this.ZC.Zd(paramZmf_);
    this.Zo.Zd(paramZmf_);
    if (arrayOfInt != null)
      Zbqc.Zr(new Zbqc[5]); 
  }
  
  public void Zl(Zg4j paramZg4j) {
    paramZg4j.Zh(a(26859, 22335), Zlo());
    paramZg4j.Zh(a(26861, -2059), Zld());
    paramZg4j.Zh(a(26768, -26194), ZlY());
    paramZg4j.Zh(a(26877, 29649), Zlg());
    paramZg4j.Zh(a(26827, -1002), Zll());
    paramZg4j.Zh(a(26821, -31535), ZlX());
    paramZg4j.Zh(a(26856, -24444), ZlW());
    paramZg4j.Zh(a(26818, -32326), ZlL());
    paramZg4j.Zh(a(26822, -19832), ZlT());
    paramZg4j.Zh(a(26816, -5457), ZlU());
    paramZg4j.Zh(a(26854, -2736), Zl5());
    paramZg4j.Zh(a(26819, 21124), Zl7());
    paramZg4j.Zh(a(26875, 26370), Zlx());
    paramZg4j.Zh(a(26857, -26209), Zlw());
    paramZg4j.Zh(a(26860, 14654), Zlu());
    paramZg4j.Zh(a(26853, -25363), ZlF());
    paramZg4j.Zh(a(26846, -15635), ZlZ());
    paramZg4j.Zh(a(26838, 17369), ZlD());
    paramZg4j.Zh(a(26835, -30955), Zls());
    paramZg4j.Zh(a(26870, 3253), ZlJ());
    paramZg4j.Zh(a(26828, 28029), Zlv());
    paramZg4j.Zh(a(26843, 32711), ZlC());
    paramZg4j.Zh(a(26839, -11001), Zl0());
    paramZg4j.Zh(a(26855, 9545), ZlM());
    paramZg4j.Zh(a(26836, 25248), Zl2());
    paramZg4j.Zh(a(26824, -4033), Zl1());
    paramZg4j.Zh(a(26851, 933), ZlV());
    paramZg4j.Zh(a(26864, -1878), ZlA());
    paramZg4j.Zh(a(26833, -4093), ZlP());
    paramZg4j.Zh(a(26830, -17624), Zlk());
    paramZg4j.Zh(a(26867, 1689), ZlR());
    paramZg4j.Zh(a(26840, 22007), Zl9());
    paramZg4j.Zh(a(26862, -26769), ZlS());
    paramZg4j.Zh(a(26866, 14684), Zlc());
    paramZg4j.Zh(a(26831, -12071), ZlI());
    this.ZV.Zl(paramZg4j);
    this.ZQ.Zl(paramZg4j);
    this.ZC.Zl(paramZg4j);
    this.Zo.Zl(paramZg4j);
  }
  
  private static SortOrder ZT(String paramString) {
    if (paramString != null && !paramString.isEmpty()) {
      switch (paramString.toUpperCase(Locale.ENGLISH).charAt(0)) {
        case 'A':
          return SortOrder.ASCENDING;
        case 'D':
          return SortOrder.DESCENDING;
        case 'U':
          return SortOrder.UNSORTED;
      } 
      Zuh.ZT(false, Zqf.Zk, paramString);
    } 
    return SortOrder.UNSORTED;
  }
  
  private void ZIN() {
    this.ZB.Zv(Zlc(), ZlI());
  }
  
  static {
    // Byte code:
    //   0: bipush #74
    //   2: anewarray java/lang/String
    //   5: astore #5
    //   7: iconst_0
    //   8: istore_3
    //   9: ldc 'Â¤Â”Ã’&Ã˜ÂˆDc\\nÂ‚Ãƒ9ÂœÂš-:)Â·Ã¹Â \\nÃ¼mKAVÃ¿Ã§Â¼ÃºÃÂÃŠÂÃ‰Ã†Ã¥jÂ‡YjÂª*Â„Â ^Â·Ã˜XÃº.Ã²Ã´Â GEÂ›Ã +z \\tÂ°Â£Z./ÃÃ‚Ã¼Â•Â¤[8Â±ÂÂŠÃ¬[dÂ¿\\rCÃ‘lÃ§7Â¼Ã‰ÂˆÂ³8Ã˜`7Â•IÃ´ÂÃ¿ÃœÂ_Â¡Â‚ÃÃ­Â¤Ã”ÃÂ‘Bd}dÂƒXÂœ4DÂ¼Ã€h)U{o>Ã½jgyÃœVÃ€3ÃƒÂœ`Ã‰Â¡[Ã Ã¬2!Ã bÂ¨ÃYÂ‡OLÃ¼Ã¨3#Ã€H`zPÃ‘ERÃ»!;#&ÂŒHÃ„ÂL>Ã±ÂŸÂ»ÃÃ—Ã³Â TbÃšÃµoRÂ«<Ã’gXG`Â–rÂ¢Ã†Nh2~Â£T8Ã§UÂŸ\\b7Â½Â„Â¬-x,Â£]3oÂ¼Ã†ZÂ’Q3Â‹ÂvÂ½TÃÃ˜Ã´Â°Â—Â¾ÂªÂ“gÂ˜r+Ã½Â˜Ã¹Â§Â½Â¸Ã­sÂ¶IÃ³Ã¤Eut2Lz]Ã’QwÃˆÃ%)Ã²ÂÂ½LÃÂ–QÃ»Â„Â”R4Ã•Ã€ÂšÂ\\rÃ•Â¯Ã‚Y@nÂ¶i]UÃ˜Ã¶Â…Â‘Ã˜aulaÃ¾UÂ¬ÃƒÃ‰cÂ¥Ã”ÃƒÃŠÃšÂ¯}Â…)Ã“XMÂ…Â¾:Ã§Ã¦Â#'OÃ»WÃ“fÂ‘ÂšÂ´Â­vy'Ã­>ÂÃ]ÃÃˆ|<YÃœm//Â©Â¥KÃŠÃ‘9ÂŠÃœ"~ÃŸÂƒsÂ{`Ã‹ÃvÃ´Ã´Â“tÃ¤bÂ£ÃªHH>kY:Ã±jÃ·Â·&GÂŠÃA_\\tÃÂÂ²]j:Ã“)Ã»29Ã²Â¥Ã´<Ã Ã·Â”Ã¤"g7\\t}m'MÃ¦Ã—ÂŠÂˆÃIÂ…Ã¬Ã²ÂÃ²V`GÂšÂ­Â«Ã…>.Â«Â¨3Â¡Ã¤xÃƒ}ÃºAÃA_Â•UÃ›&/V~ÂœÃº{sÂ»Â‚HÂ‡$Â³Â‚ ÂŸÃ¶oÂ„Ã¶/eÃ˜0Ã²Â”\\rbÂ¡%Â€&\Â„ÃµÃ®ÃUÃƒÂƒ0Â•ÂÃ¾;?sÂ•Ã²CÃ¶Ã±FÂ‚UÂ‚Â®'ÃŸp2hÂ²Ã‚Â‡hVÂ±Â¼lR"ÃO+HÃÂ½Â”e5Â„Ã«ÃˆÃ·Â¸Â¨)Ã™Ãš\\rÃœÂ¾Â‡Â„Â­Ã:Ã¹Ã˜Â†Â–;aÂ¨p%Â¡jYÂ¤Â©Â¹ÂµÃœ|J'\( ?FSJ&\\tÂº_'cÃ¾Ãœ$Ã¨aÂ†`XÃ¬Ã¹p*_Ã¼Ã¯nÃŠ!rT\\fgbÃ¹?XÂ¿,b\\nÃƒÂ<Â¨zÂ„7CÂªlaLÂ–ÂƒcAÂ³\\tBÂˆ\\tEQÂ‘2PÂŠFÃ„Ã¾i`ÂÂ‘(ÂBTÃ¼\\bÃ“A\\fQÃ¸H6lÃ‘Ã¥rÃÂœ5Â²Ã°$Â‘Ãœl^Ã—Ã‡[ÂŒÂ‡VVÃ¯ÃÃ˜Â•Â…;Â‚Â Â @XWyhÃÂQÂ—Â›'s8ÃšÃ¯w)Â—nÂ±Ã‹`Â¶Ã¾JÂ™UÃ¦GwÃ°Â½+|zÃ…1SÃ‘}Â”Ã3RÃª\\fÃ©q PzzÃ‡UHQzÃÃ”ÂµVQÂ³LÃ£d#Ã‰~Ã sÃ·\\r:TÂŒIÃ¼Âœ>tÃ›\\bÃ†Ã„Ã·KÂ¿ÃŠ5UgÃ¬XGÂ¼ÂšÂ½ ÃÃ fÂ¢Â¥Ã˜Ã Â‰Â‡gÃ…Â”T~ÂµÂLeU2Â³Â»Â¦EÂ¹Ã—Â”\#vÂ‰Gm84Â„|Ã²RÂ¦Â©Â’ÂÃ|DÃ«4hÃ§Â¡Ã¤q"ÂŠÃ)ÂŠyÃ`Â‘_\Â«*Â™ZJ8 [r1*U%ÂŠÃ´Ã³hX}ÂÃŒÂ‘Â»ÃŸÃ¹Ã¬ÂµÂ­Ã†Ã“jÃ³GÃ³Ã´Ã­Ãˆ;Ã§Â‡0Ã„Ã¹<Ã¯)Ã‚Ã‰>Z <Ã•[Ã¼ÃŸÂ·Ã§Â`XÃŸGÃ¿Â©Ã¯CÃ«Ã‰ZÂŠÃµÃ‹ÂµÃ–hV.hÃ€bKHC*\\fprXÃš#<D&oÃ™mÂ¹Â«Ã…/Ã¢Ã²Ã¥t<Ã°ÂµXÂ‰\\fnÃ³OÂk{Â‰Ã’Â3}2=ÃÃ±ÂÃ–Ã½SÃ¾Â½Ã²Ã´XÃˆÃ„Ã«!Â—GÃ”Â›Â”@ÂwO)xÂ|Â’A=4Ã¶Ã€=ÃŸ6ÃwÃ¿Z}Ã¯ÂÂƒÂ£Ã¸nÂ¯6Â†#K(Ã¡Ã¥/Ã˜Â–ÂƒxtÃ¾Ã—])Â­ Â˜ÃŠj\Ã‡Â±[Ã·Ã²\Ã®Ã¹Â‰Ã¬Ã«Y>;!Â—Â¦Â¾ÂÂ®Ã¯DÂ…[Ã¼oÃÂ¢Â£rSÃ½Ã”%Â‘Ã¬Ã­ÂYz. Â– Ã¸)h:ÂœÃ’Ã³ÂƒUÂ¬N?ZÂ•EÂˆGUBÃ¥?Â—mÂ£@5Ã¯Ã²Â»ÃªÃµÃ¡PÂ¾Ã¤UÃµNw\\tbuÃ5ÂÂ“Y^Ã¿'Ã€32.Â¢Ã¿,Ã‹I$9Ã’Ã·Â®m8Â”=Â¹Â‘Â±Ã—ÃŒÂ˜dÃ‹>?se"Ã¨=Ã 6dÃ€Â¦Y8Ã¥/Â£t%ÃÂ•&Â“Ã°Ã›_/Â›ÃœWÂaÂ‘dh8IZÂ¥+NÂªÂ‡8*Ã Â’Â–ÂœCÂ›Â·BE~\\fÂ•;#?ÃÃq,|Â¹\Â´#WÂ‰Ã£!Â¤Ãµ==Â Â›Ã‹Â»SÂ£ÂƒÂˆ^DÂ¼Â‰Ã–eÂªbÂŸÂ»ÂµÃƒ44Ã†Ã¸Â¦o\Ã·;EÃ¤Â«|aÃ½Â°NPWÃ¸-9Ã€Â¦Â…Â´Â·ÂœbZ*Â¿ÂŠ&abÂ:HÂ‚Â¦Ã—ÃŸhZÂ©Ã¿Â™-Â”ÂÃŸÃ©qÂœxÂ’3IÂ™Â´Ã¼ÂŠÃŒ\\fÃˆÃ˜^Â¢FÂ¿{837Ã‰ZgÂ ÂÂ”ZXÂšÂ£F>Â…[2'ÂÂ½"ÃÂ—ÂµÃ¶Ã·2$goÃ¦ÃŠoÃ§wÃ·A Â¤pIF2ÃŒlÂ Ã³Ã”bÂ¬ÂŠÃ‰ÂÃ#,Â¦~Â¯Â¸ÃÂÂŠ^2Â›V5~$ÂƒÃšÃ§Â—Â^Â«ÂÃ‹uÃ²Ã–-Â†;ÂŸÂ ÂŠPVvÂˆ!Âq'Ãºi'uaÂƒÂŒÂ²Â˜Ã•9ÃŒw ÃšÃ¨gÃ–BÂ–\\fÂ«|Ã¤Ã·OÂ²Ã­Q<Â‘Ã‹OYÃ°\\n(Ã­\\fQÂ½Â»)Ã©LÃ˜LbI_Ã¤Ãš~Â‚a&DÂ¾ÃŸÂ”)YÃ½Ã· ^ÂÃ°"zÂ€Â¦Ã½Ã¹Ã½Ã†Â˜BÂ£>YÃ‘Ã™Â 4PÃšlÃµDZN=O)dNÂÃ‚%\\b@Ãer}Â©6d#ÃŠÃÃ›V;Â´Ã¦Â«Ã†Ã…#Ã‹ÂÃ¢|Ã”oÂ‰Â‰B$='VÂ½HdÂ±ÂªÃ¹5ÂºZ@Ã†Â‚Ã¢Ã³ÂÃ§LÂ¸Â­Â¼fM\\b5TÃÃŒmÃ¡#B8Ã‹Ã‰XJÃ®Ã’Â‘Ã’Ã’I>ZÃ’Ã£GÂÂ±3Ã¥ÃÂš3Â¯zÃ¯Â¾Ã)JbÂ¿Â¨]Â†Ã™Ã3Ã§}ÂºÃ•/ÃºÂ›!Â¬z%Â´Ã—sa"Â¤Â¤Â‡Ã­Â–(?ZÂ¢QfÃKÂ¸Â­Ã¢Ã¬Z_Â“7Ã‡GÃ´e#iKÃ¾(|H4HÃ€Â½ÂšÃ»PÃ‘Ã¹IÃšÂ²ÃÃ™>mÂµ"Ã®Â‚Â•Â¼u1Â‹<T\\b5\ÂÃ€Â‚\\nÃŒwÃ­Ã•OÂ MÃ¢l!Â°jÃ™;ÂµÃ­/Ã¥UcÂƒ(SZ,Ã¿Â³Â  myÃÃ»jÃ%Â±Ã–gÂŸ:Ã’(Â­]Ã«n'ÃELDN.Ã¬ÃŸÂ¸tÂ‰<DÃÃ•[Ã¶4Â¬{Â¤}*Ã†Ã‰ÂŒÂ«\\n#tÂŒÂ¢EÂ¸Â—Ã€ÃŸ[Ã½=pUÂ’Ã¶EÂ½ÂÃ„@)Ã­ZÃ ÂŒÂ;Ã‚Ã˜Â“Ã‡n^Â½+TÂ¢;.|Âƒ;Ã²+Â½?xWÃ´Â™{Â¨#ÂÂ„Â±Ã®`Â¯ÂƒÂ­.pÂœBÃ“2"FvDÂ›Â»Â»~Â¨Ã„Âº@Â‚9Âœ\\nÂƒuÂ®Ã¶Ã947Ã—Â NÂ–Â…Â’Ã,Â©\\r/Q&Â±ÂˆÂ¾Ã±Ã„GÃ¾}2Ã°RÂ¯XhÃ¸Â¹ÃµÃ»bÃŠÃ­Â¾Â¡QÂ‹Ãª6ÃÃÃ€<\\tÃ¯gIneÂ‰Ã•ÃŒ+Ã¡Â¶pÃ’OÂ¶3Ã·Ã¤}ÂºÂˆÃ¤Â¯Ã¾oa<ÃˆÃÃ–ÃÃ0Ã¸sVÂ½9Ã¡Â³;ÃšÃ¡ÃºÃ›BÃ»ÃŠyÂ«u/Â¹\1W\\r>ÂÂN:Â…Â¸8ÂÂ”Ã¾ÂÃ”Â®Ã·Ã’Â‰LÂ¿Âˆ*W-ÃˆÂˆv4Ã‡Ã²Ã\\fÂÃ»^Ã ÂŸÂ`ÂœÂ•]5Â™uV,Â†Ã…Â®Ã†Â¥PÂ®Âº.$ HkÃ©~YÂ¼>Ã†~Ãœ>Ã‚EÂ‹WÃÂŠÂ”MÂˆÃ¥RÂŒÂ²Ã¹hÃ‘fÂ_`Ã¥6<e&ÃªpÃŸBÂ»6\\tÂ¶Â©ÃŒÂ…bÃƒÂ©Ã£yÃ´ÃÂ‹ÂšÃ“Â—Ã†ÂÃƒÂ¯Â•|WÂ„.Ã¯Â”_IÃ±HÂŸÃ®Ã´PIÂ¿^gÂ™Â˜IÂ»qÂ°Ã¨sÃ·Ã°)ÂœÃ³Ã•ÃŠ8GÃœÂ–Ã«ZgÃ»\\fÂ¬Ã‹u{Ã9hÂ¨UKo+Ã±Ã‰XÃ„Â«Â¢0Â¬Â«%H5YXmÂ¿/Â»ÂºÃ•N8Â Ã£Â©Ã‚\Ã”ÃŸ\\b`W9Â”ÂÂ­fÂŸÂ„ÂªÂšaÂŸqÃ£xÂ¬Ã»Â’Ã¹DÂ°Â—\\fA'Â™BH/Â™Â£Â‡Ã¶Â¼ÂÃ©Â­M=Â³ÂÂ‘TÂ©Ã†Â½8ÂµyÃ ]Â“Ã³,Â»ÃŸ{ZÂ§Â¤RÂ±PÂ…Ã¼Â„AÂ·cD~Ã¹<Â¶uÃŒ\\nÂš\\nÃÂ¬Â­Ã‡ÂµÂ®<LÃŸ9$Ã¹=Â§oÂ²YÃ”gÃ…Â:=Ã…Ã\d5Ã¥*Ã¨Ã—Â†Â¬Ã¥}Â{Ã¾P\\b'BÃ¢Â“1Ã®yÃ…)dÂ—Â·Ã¦l]ÃªzÂ¸ÂÂ´#8Â…"u]wÃºÂ:Ã ;Ã´nÃ˜yÂ™cs2ÂŠ\Ã¡pOÃ«r1Ã†Ã†ÃšÂ¦\\rÂ¦.ÂŒÂ›T*ÂœÂ”Â†\\t y\\fÃ¶/Z@Ã™*ÂšÂbÃaÃ‹Â§[Ã¬ÂŒ-ÃŠÂ¥Ã­6Ã±Â‚GÂ­yÃÃ¼ÃµÂ›Ã¿ÂŸ!Ã’2Ã°d(Ã—Ã›ÂµÃ—Â¿Ã‹SÃ§Ã´ÂaY\\nÂ¦ÂkÂ­Â¼%Ã¨4Ã–Â†nRÂ\\nN?Â¹o-]^Ã˜.Â€Â‰Â˜Ã‘ CfÃ½!Ã aÃ¯Ã‘YÃÂ™ÃÃ±cÃ¢Ã™Ã½ÃœÂ£Ã‹cÃÃ«Ã *aÂ™Ã…Â¬WÃ“UppÃŒÃ”4%ZÂ·@Ã–#>Â‰Â€ÃƒÃ¶ÃœÃÃ5_\\n\\tÂ°Â·XA=Â·Ã«eDÃÂ”[Ã/Â¢Ã…{k#i%ÃjRÂ“3RÂ¹kÃ„!ÃŒTÂ Â®^`ÂƒVÃ„ÂÃ…]Ã¦40IHsÃ˜ÂªÃ¸`Ã•ÃŸtÃ¡Â„7SÂ«Ã¯Ã¶WÂ­Â‰5"z\Ã¥sÃœÃ±Ã`\\f@Â‡Â­zÃ´\\bÂ‚ >Ã‚yÂ¿+Ã¶Â tLG;Ã—Â¬Â¼!hÃ½=%I@Â”Â¶Ã»Z+Ã™Ã¾mÃªEq|Ã‚Â°Â;Â²a Ã£Ã²Ã  *LA"0~Â¤z)vÂ¹Dd*Ã¹Ã—(Te+Ã©Ã¬Ã”uÃŠÃ¸Â›Ã…Ã» iaÃ±?5Ã‡Â\Ã„y~Â‹ÃŒ:NÂ¢Â•Ã…Â¦Â²zÂ˜d\\tnÃ–Â„OÂ²kÃ™Â€wPÂtbVp1}Ãƒ44fÃ”Â¯81Â»Do"oÃ‚Ã‚ÃšÃ·a|\\bÂ²ÂƒÂ¹ÃºÂ€Ã Â³Â³'/Ã•Ã‡Â›Â…Ã‹Ã£Ã—Ã¥YÂ²ÂšpÂ¹Â•Â¥ \Ã¡Â¿ÂºJÂ’fÂÂÂ“;Ã€'^PIFiÂ¶SÂ¦Ã¢ÃÃ¬"Ã®Â¡Fx@Ã¯ÂŸÂœÂƒÃ‰Â±Â‡Â„f<Ã±Â£Â„Ã¾4Â›,<Ã²Â¬Ã”Ã„wufÂ¹Â€Â¯Â”Ã…ÂŸÂ‰Ã‹7jÃ²ÃªÃ£#PÃ¦Ã¤^Ãµ/[\\tÃ§un5Â›Â“Â›^Â§'Ã‹3E/ÂÃ¡lÃ£KÃ£6Ã«'ÂxÂ‹Â‚aÂˆÃ³Â¸2aÃˆÂ‘)ZÂº7eÃ©ÃªÂ‰ÃŸ}Â¤ÃU@ÃƒÃ¬Ã…#Ã‘Ã¨nÂVÂ§Ã¿Ã“WÂ–Ã•Â€Ã¨Ã¯,Â¥Ã›q*>Â‰7vÃ–Â·Â/DÂ™ÂiÂµÂ˜bÂ”5Ã¢Â¹ÂƒÃ<xÃ¹qOÂ¦Ã³dÂ…Ã¿UdÃ¦<Â•ÃµÂ«M>ÃŠÂ©ÃÃ™Ã†ÂÃ¯Â¯Â®Â¨Â„Âš}Ã¼Â¸6\\nÂÂ†ÂµH(>Â˜Ã“UÃ(Â•AÃ‹Ã•Ã¨Ã‚ÃÃÃƒWÂ¢Ã‹Ã–ÃºÃ¼x,Â±=Ly3D,ÂÃªÃ¢YvÂ°TÂ¼Â¨Â¡N+Ã¢Â¹Â¨Â”ÂÃ›ÂŒ6D(Ã‡rÃ“Ã„+u1^3ÂÃ’39Â°Â¥Ã¸6v"sÃºÃ“Â´Ã¨\\rKÂ”ÂÂ¾Ã¤;Â£Â°YU-Ã¼jmÃ‘Ã¹/IÂ«Ã›ÂµQf,ÂµÂ©~>pÂ·HBÂ‹5Ã¹[Â®.Ã„Â„tJÂ¯Ã‹v_Ã©XÂƒÂ‘{ÂÂ±?*eÂÃ¿Ã•Ã•Â“Ãm(Ã¼DÂ®QÃ¾Ã¶;tÃ´Ã¼ÂÂ¥Ã½Ã°QÃ•0qÃ«,Ã‰Â¦`m@Ã©qÃ€Â¿`$@Â€IÃ¼Ã§Â·Ã£g-Â­Â”jÂ³yÃŸnÂ¯Â½ÃŒÂ“Â™Ã£Ã¿kÃ¨\\n+Â°Ãš4Ã˜Ã¶.dÃ„8KÂÂ¢Ã˜Â°Â¦Â¨Â½Â™Ã£Â¡Ã§bÃ‰Â¤@N7Ã‹Â€F :Â˜\\bÂºÂ¾Ã¿Ã¼ÂÂ‡{>dÂœÃ¥Ã•\\b8MCÃÂ•Â‹ÃŠÂ¢PÃ£Ã¦Â²Ã´IxÂ >Ã‹Ã¦MuÃ¨ÃºmfÂ‰Ã‰Âº{5WÃ¢Â·ÃÂ¨Â…Ã¹qÂ¦Ã¦};xÃ­LÃ³Ã¨vÃ‚Ã¿Ã«Ã‰Ã™cÂÃ½CÃ¤7Âµ,CÃ—T)\\tÂÃ \Â›zÂ¢Ã¦Ã—Ã›Ã†Â¤Â¾Ã–>&Ã©Ã”Â²Â»bÃ\\rÂÃ‘;Âª5Ã \Â¿ÃµÂ‡6ÃªvÂ¦Â½1,j\\rÂ­Â´Ã—6:Â¢Â• 5Â¬tÃ£Ã®FÂ«ÃŒÃ‹==\\rÃ¨Ã–6PÂ—Ã§tÃ´Ã‚Â¯Ã§Â¡ÃŒ9Â¨0Â­c\Ã³d83\\rÂ¼cMÃ¤1ÂŠCÂ{ÂºOckÃ´{Ã¿}Ã¶Ã©Â¶Ã»ÂŒZÂ˜?%Â¢qÂ©TÂ¸O3Ã¿FpetÃˆ6Â›ÂŠ7(Â”A/,Â¤iZT1Ã›gJ3hRÂ¤Ã€!!Kf!Â–ÂÂ–O^Â·TE\\rÃ²pÂšÃ­Ã‚Â‹lkÂ‡f3ÂÃ£Â³Ã–Â¹ $Ã˜ÂœÂ±kVÂ Â­JIÂ„Ã¨Â·Â¸|VÃˆÃ–Â–#oÂ¢S\\nÃºÂª^ÂrÃ®Â‡-Â¡Ã‘rÂÃŒÂÃÃŠFÃˆÂ°ÃŠZ]\\nGÂŸÃ‰Ã¥Â“ÂDÂˆÂ‘0ÂªÂ‰Â¹\\rÂ¦?JÂ‹Â¶:Ã°ÃŠÃÃ¦F\\rmGgKÂ¹/Âƒg<Â¨Ã¾Ã¨NeÃ G]uÂ¡Â¸Â5Ã¥Ã½Â¥ÂÂ‚YÃ±|Â Ã¦Ã±GÃ£Ã»Â±NÃ”4tÃ®IÃ«Â–> \\fÃ˜]Â¤\\tZÂ°/Ã’\\fÂ·Â¬Â´lÂ±Â†Â”Ã½[EÂ³KÃµYÂÂ%_mkÂ—Ã«MÂ½ÃÃœÃ”ÂÂBOFÃªÃ¤0WÃ—\\r5FÂ7SÂª5'$\\n($Â¸:~Ã‹Â›Ã«Ã¨+(Â)eÃ‰Â“Ã®EÂ’Ã½Â!ÃˆÃ™Ã‰\\tT^)mÂ”PÃÂ™ÃµÃ£OÃ¦Â¾5FBÂÃ¼SÃ“*;Ã°Ã¯M{ÃšÂŠÃ€ÂCDÂ‚Ã¡Ã²HÃ‰34ÂŒ}=\\tÂ=AÃºyÃÃ‚ÂµO<Ãˆ/A"Ã®!7Âº(r \\bÂ°ÂƒZ05xÃ–Â‡Ã€@Ã£{Â™Ã´Ã‘Â…IÂ¥x\\rPVÃ¦Ã¡Ã½&)Â0Ca0<Ã®_Â›_Ã±Â§~ÂŠÂ±!Â¾>g<ÂŸbh Â…Ã Â¥n\\fk#Ã³sÃ‰Ã¸Ã• 8Â–0Â°Â˜AÃ‰Ã°ZÃ†Â¨[=MÂ·/Ã—Ã“Vs&RUÃ”Oi{kÃ›Ã¯7Â½Â˜Ã‰cÂ±vÂ†5Â£CÃ¯$udÂ»Ã¯Ã•9EÃ˜Â™BÃ§~gÃ²nÂ±GÂÂ©Ã¯Ã¶Â·mÂ‘Ã¼?Â®Ã…Ã´Ã…&Ã«Â¢\\n`Ã…Â¯Â¶DÃ°bÂ…Ã"`\\fÂ·K%FwÂ‰M'
    //   11: dup
    //   12: astore_2
    //   13: invokevirtual length : ()I
    //   16: istore #4
    //   18: bipush #61
    //   20: istore_1
    //   21: iconst_m1
    //   22: istore_0
    //   23: bipush #56
    //   25: iinc #0, 1
    //   28: aload_2
    //   29: iload_0
    //   30: dup
    //   31: iload_1
    //   32: iadd
    //   33: invokevirtual substring : (II)Ljava/lang/String;
    //   36: iconst_m1
    //   37: goto -> 143
    //   40: aload #5
    //   42: swap
    //   43: iload_3
    //   44: iinc #3, 1
    //   47: swap
    //   48: aastore
    //   49: iload_0
    //   50: iload_1
    //   51: iadd
    //   52: dup
    //   53: istore_0
    //   54: iload #4
    //   56: if_icmpge -> 68
    //   59: aload_2
    //   60: iload_0
    //   61: invokevirtual charAt : (I)C
    //   64: istore_1
    //   65: goto -> 23
    //   68: ldc 'Ã‡ÂˆÂ±ÂªÂ»'Â¿iÂ Â¤Ã¿&NÂ¢JÃ”uÃƒÂ”ÂŸÂ±(Ã•5bÂ„ Â™YÃ³Ã–Ã­ÂÂ§IÂµÃ”yÂ¿Ã°Ã¾hOÂ¿Ã§7\\fÂ¡ÃˆÂÂ”Â²Ã‚+Ã•Â„7Ã¶\\rlÃ«Â&Â­PÃ¬0z%Â”GÂ¢0g@Ã•\\nÂ°ÂˆÂ†AHÃ†ÃµKÃ«Ã«bÂªÂœÃ³Ãc2Ã´^Ã¹['
    //   70: dup
    //   71: astore_2
    //   72: invokevirtual length : ()I
    //   75: istore #4
    //   77: bipush #49
    //   79: istore_1
    //   80: iconst_m1
    //   81: istore_0
    //   82: bipush #91
    //   84: iinc #0, 1
    //   87: aload_2
    //   88: iload_0
    //   89: dup
    //   90: iload_1
    //   91: iadd
    //   92: invokevirtual substring : (II)Ljava/lang/String;
    //   95: iconst_0
    //   96: goto -> 143
    //   99: aload #5
    //   101: swap
    //   102: iload_3
    //   103: iinc #3, 1
    //   106: swap
    //   107: aastore
    //   108: iload_0
    //   109: iload_1
    //   110: iadd
    //   111: dup
    //   112: istore_0
    //   113: iload #4
    //   115: if_icmpge -> 127
    //   118: aload_2
    //   119: iload_0
    //   120: invokevirtual charAt : (I)C
    //   123: istore_1
    //   124: goto -> 82
    //   127: aload #5
    //   129: putstatic burp/Zzu0.a : [Ljava/lang/String;
    //   132: bipush #74
    //   134: anewarray java/lang/String
    //   137: putstatic burp/Zzu0.b : [Ljava/lang/String;
    //   140: goto -> 300
    //   143: dup_x2
    //   144: pop
    //   145: invokevirtual toCharArray : ()[C
    //   148: dup_x1
    //   149: arraylength
    //   150: dup_x2
    //   151: pop
    //   152: iconst_0
    //   153: istore #6
    //   155: dup2_x1
    //   156: pop2
    //   157: dup_x2
    //   158: iconst_1
    //   159: if_icmpgt -> 259
    //   162: dup2
    //   163: swap
    //   164: iload #6
    //   166: dup2_x1
    //   167: caload
    //   168: swap
    //   169: iload #6
    //   171: bipush #7
    //   173: irem
    //   174: tableswitch default -> 241, 0 -> 212, 1 -> 216, 2 -> 221, 3 -> 226, 4 -> 231, 5 -> 236
    //   212: iconst_2
    //   213: goto -> 243
    //   216: bipush #119
    //   218: goto -> 243
    //   221: bipush #40
    //   223: goto -> 243
    //   226: bipush #33
    //   228: goto -> 243
    //   231: bipush #67
    //   233: goto -> 243
    //   236: bipush #14
    //   238: goto -> 243
    //   241: bipush #44
    //   243: ixor
    //   244: ixor
    //   245: i2c
    //   246: castore
    //   247: iinc #6, 1
    //   250: dup
    //   251: ifne -> 259
    //   254: dup2
    //   255: dup_x1
    //   256: goto -> 166
    //   259: dup2_x1
    //   260: pop2
    //   261: dup_x2
    //   262: iload #6
    //   264: if_icmpgt -> 162
    //   267: pop
    //   268: new java/lang/String
    //   271: dup_x1
    //   272: swap
    //   273: invokespecial <init> : ([C)V
    //   276: invokevirtual intern : ()Ljava/lang/String;
    //   279: swap
    //   280: pop
    //   281: swap
    //   282: tableswitch default -> 40, 0 -> 99
    //   300: new burp/Zg2t
    //   303: dup
    //   304: invokespecial <init> : ()V
    //   307: invokevirtual Zf : ()Ljava/util/List;
    //   310: invokeinterface stream : ()Ljava/util/stream/Stream;
    //   315: <illegal opcode> apply : ()Ljava/util/function/Function;
    //   320: invokeinterface map : (Ljava/util/function/Function;)Ljava/util/stream/Stream;
    //   325: <illegal opcode> apply : ()Ljava/util/function/Function;
    //   330: invokeinterface map : (Ljava/util/function/Function;)Ljava/util/stream/Stream;
    //   335: invokeinterface toList : ()Ljava/util/List;
    //   340: putstatic burp/Zzu0.ZJ : Ljava/util/List;
    //   343: new burp/Zg2y
    //   346: dup
    //   347: aconst_null
    //   348: invokespecial <init> : (Lburp/Zbp5;)V
    //   351: invokevirtual Zf : ()Ljava/util/List;
    //   354: invokeinterface stream : ()Ljava/util/stream/Stream;
    //   359: <illegal opcode> apply : ()Ljava/util/function/Function;
    //   364: invokeinterface map : (Ljava/util/function/Function;)Ljava/util/stream/Stream;
    //   369: <illegal opcode> apply : ()Ljava/util/function/Function;
    //   374: invokeinterface map : (Ljava/util/function/Function;)Ljava/util/stream/Stream;
    //   379: invokeinterface toList : ()Ljava/util/List;
    //   384: putstatic burp/Zzu0.Zi : Ljava/util/List;
    //   387: return
  }
  
  private static String a(int paramInt1, int paramInt2) {
    int i = (paramInt1 ^ 0x68D0) & 0xFFFF;
    if (b[i] == null) {
      char[] arrayOfChar = a[i].toCharArray();
      switch (arrayOfChar[0] & 0xFF) {
        case 0:
        
        case 1:
        
        case 2:
        
        case 3:
        
        case 4:
        
        case 5:
        
        case 6:
        
        case 7:
        
        case 8:
        
        case 9:
        
        case 10:
        
        case 11:
        
        case 12:
        
        case 13:
        
        case 14:
        
        case 15:
        
        case 16:
        
        case 17:
        
        case 18:
        
        case 19:
        
        case 20:
        
        case 21:
        
        case 22:
        
        case 23:
        
        case 24:
        
        case 25:
        
        case 26:
        
        case 27:
        
        case 28:
        
        case 29:
        
        case 30:
        
        case 31:
        
        case 32:
        
        case 33:
        
        case 34:
        
        case 35:
        
        case 36:
        
        case 37:
        
        case 38:
        
        case 39:
        
        case 40:
        
        case 41:
        
        case 42:
        
        case 43:
        
        case 44:
        
        case 45:
        
        case 46:
        
        case 47:
        
        case 48:
        
        case 49:
        
        case 50:
        
        case 51:
        
        case 52:
        
        case 53:
        
        case 54:
        
        case 55:
        
        case 56:
        
        case 57:
        
        case 58:
        
        case 59:
        
        case 60:
        
        case 61:
        
        case 62:
        
        case 63:
        
        case 64:
        
        case 65:
        
        case 66:
        
        case 67:
        
        case 68:
        
        case 69:
        
        case 70:
        
        case 71:
        
        case 72:
        
        case 73:
        
        case 74:
        
        case 75:
        
        case 76:
        
        case 77:
        
        case 78:
        
        case 79:
        
        case 80:
        
        case 81:
        
        case 82:
        
        case 83:
        
        case 84:
        
        case 85:
        
        case 86:
        
        case 87:
        
        case 88:
        
        case 89:
        
        case 90:
        
        case 91:
        
        case 92:
        
        case 93:
        
        case 94:
        
        case 95:
        
        case 96:
        
        case 97:
        
        case 98:
        
        case 99:
        
        case 100:
        
        case 101:
        
        case 102:
        
        case 103:
        
        case 104:
        
        case 105:
        
        case 106:
        
        case 107:
        
        case 108:
        
        case 109:
        
        case 110:
        
        case 111:
        
        case 112:
        
        case 113:
        
        case 114:
        
        case 115:
        
        case 116:
        
        case 117:
        
        case 118:
        
        case 119:
        
        case 120:
        
        case 121:
        
        case 122:
        
        case 123:
        
        case 124:
        
        case 125:
        
        case 126:
        
        case 127:
        
        case 128:
        
        case 129:
        
        case 130:
        
        case 131:
        
        case 132:
        
        case 133:
        
        case 134:
        
        case 135:
        
        case 136:
        
        case 137:
        
        case 138:
        
        case 139:
        
        case 140:
        
        case 141:
        
        case 142:
        
        case 143:
        
        case 144:
        
        case 145:
        
        case 146:
        
        case 147:
        
        case 148:
        
        case 149:
        
        case 150:
        
        case 151:
        
        case 152:
        
        case 153:
        
        case 154:
        
        case 155:
        
        case 156:
        
        case 157:
        
        case 158:
        
        case 159:
        
        case 160:
        
        case 161:
        
        case 162:
        
        case 163:
        
        case 164:
        
        case 165:
        
        case 166:
        
        case 167:
        
        case 168:
        
        case 169:
        
        case 170:
        
        case 171:
        
        case 172:
        
        case 173:
        
        case 174:
        
        case 175:
        
        case 176:
        
        case 177:
        
        case 178:
        
        case 179:
        
        case 180:
        
        case 181:
        
        case 182:
        
        case 183:
        
        case 184:
        
        case 185:
        
        case 186:
        
        case 187:
        
        case 188:
        
        case 189:
        
        case 190:
        
        case 191:
        
        case 192:
        
        case 193:
        
        case 194:
        
        case 195:
        
        case 196:
        
        case 197:
        
        case 198:
        
        case 199:
        
        case 200:
        
        case 201:
        
        case 202:
        
        case 203:
        
        case 204:
        
        case 205:
        
        case 206:
        
        case 207:
        
        case 208:
        
        case 209:
        
        case 210:
        
        case 211:
        
        case 212:
        
        case 213:
        
        case 214:
        
        case 215:
        
        case 216:
        
        case 217:
        
        case 218:
        
        case 219:
        
        case 220:
        
        case 221:
        
        case 222:
        
        case 223:
        
        case 224:
        
        case 225:
        
        case 226:
        
        case 227:
        
        case 228:
        
        case 229:
        
        case 230:
        
        case 231:
        
        case 232:
        
        case 233:
        
        case 234:
        
        case 235:
        
        case 236:
        
        case 237:
        
        case 238:
        
        case 239:
        
        case 240:
        
        case 241:
        
        case 242:
        
        case 243:
        
        case 244:
        
        case 245:
        
        case 246:
        
        case 247:
        
        case 248:
        
        case 249:
        
        case 250:
        
        case 251:
        
        case 252:
        
        case 253:
        
        case 254:
        
        default:
          break;
      } 
      char c = 'Â·';
      int j = (paramInt2 & 0xFF) - c;
      if (j < 0)
        j += 256; 
      int k = ((paramInt2 & 0xFFFF) >>> 8) - c;
      if (k < 0)
        k += 256; 
      for (byte b = 0; b < arrayOfChar.length; b++) {
        int m = b % 2;
        if (m == 0) {
          arrayOfChar[b] = (char)(arrayOfChar[b] ^ j);
          j = ((j >>> 3 | j << 5) ^ arrayOfChar[b]) & 0xFF;
        } else {
          arrayOfChar[b] = (char)(arrayOfChar[b] ^ k);
          k = ((k >>> 3 | k << 5) ^ arrayOfChar[b]) & 0xFF;
        } 
      } 
      b[i] = (new String(arrayOfChar)).intern();
    } 
    return b[i];
  }
}


/* Location:              C:\Program Files\BurpSuitePro\burpsuite_pro.jar!\burp\Zzu0.class
 * Java compiler version: 21 (65.0)
 * JD-Core Version:       1.1.3
 */