package burp;

import java.math.BigInteger;

class Zzuh extends ClassLoader {
  static String ZX;
  
  static Object ZV;
  
  private static final String[] a;
  
  private static final String[] b;
  
  static boolean Zi(Object[] paramArrayOfObject, Object paramObject) throws Throwable {
    // Byte code:
    //   0: invokestatic ZK : ()Z
    //   3: istore_2
    //   4: sipush #-26897
    //   7: sipush #-29446
    //   10: invokestatic a : (II)Ljava/lang/String;
    //   13: invokestatic forName : (Ljava/lang/String;)Ljava/lang/Class;
    //   16: invokestatic Zx : (Ljava/lang/Object;)V
    //   19: new java/io/ByteArrayOutputStream
    //   22: dup
    //   23: invokespecial <init> : ()V
    //   26: astore_3
    //   27: getstatic burp/Zmwu.ZM : Ljava/lang/String;
    //   30: astore #4
    //   32: iconst_0
    //   33: istore #5
    //   35: iload #5
    //   37: aload #4
    //   39: invokevirtual length : ()I
    //   42: if_icmpge -> 72
    //   45: aload_3
    //   46: aload #4
    //   48: iload #5
    //   50: iload #5
    //   52: iconst_2
    //   53: iadd
    //   54: invokevirtual substring : (II)Ljava/lang/String;
    //   57: bipush #16
    //   59: invokestatic parseInt : (Ljava/lang/String;I)I
    //   62: invokevirtual write : (I)V
    //   65: iinc #5, 2
    //   68: iload_2
    //   69: ifeq -> 35
    //   72: aload_3
    //   73: invokevirtual toByteArray : ()[B
    //   76: astore #5
    //   78: getstatic burp/Zgil.ZG : Ljava/lang/Object;
    //   81: checkcast java/math/BigInteger
    //   84: invokevirtual toByteArray : ()[B
    //   87: astore #6
    //   89: sipush #256
    //   92: newarray byte
    //   94: astore #8
    //   96: sipush #256
    //   99: newarray int
    //   101: astore #9
    //   103: sipush #256
    //   106: newarray int
    //   108: astore #10
    //   110: sipush #256
    //   113: newarray int
    //   115: astore #11
    //   117: sipush #256
    //   120: newarray int
    //   122: astore #12
    //   124: bipush #10
    //   126: newarray int
    //   128: astore #13
    //   130: sipush #283
    //   133: istore #14
    //   135: iconst_0
    //   136: istore #16
    //   138: iload #16
    //   140: sipush #256
    //   143: if_icmpge -> 377
    //   146: sipush #-26900
    //   149: sipush #-10157
    //   152: invokestatic a : (II)Ljava/lang/String;
    //   155: iload #16
    //   157: iconst_1
    //   158: iushr
    //   159: invokevirtual charAt : (I)C
    //   162: istore #25
    //   164: iload #16
    //   166: iconst_1
    //   167: iand
    //   168: ifne -> 183
    //   171: iload #25
    //   173: bipush #8
    //   175: iushr
    //   176: goto -> 185
    //   179: invokestatic a : (Ljava/lang/Throwable;)Ljava/lang/Throwable;
    //   182: athrow
    //   183: iload #25
    //   185: i2b
    //   186: sipush #255
    //   189: iand
    //   190: istore #15
    //   192: iload #16
    //   194: iconst_1
    //   195: ishl
    //   196: istore #17
    //   198: iload #17
    //   200: sipush #256
    //   203: if_icmplt -> 213
    //   206: iload #17
    //   208: iload #14
    //   210: ixor
    //   211: istore #17
    //   213: iload #17
    //   215: iconst_1
    //   216: ishl
    //   217: istore #18
    //   219: iload #18
    //   221: sipush #256
    //   224: if_icmplt -> 234
    //   227: iload #18
    //   229: iload #14
    //   231: ixor
    //   232: istore #18
    //   234: iload #18
    //   236: iconst_1
    //   237: ishl
    //   238: istore #19
    //   240: iload #19
    //   242: sipush #256
    //   245: if_icmplt -> 255
    //   248: iload #19
    //   250: iload #14
    //   252: ixor
    //   253: istore #19
    //   255: iload #19
    //   257: iload #16
    //   259: ixor
    //   260: istore #20
    //   262: iload #20
    //   264: iload #17
    //   266: ixor
    //   267: istore #21
    //   269: iload #20
    //   271: iload #18
    //   273: ixor
    //   274: istore #22
    //   276: iload #19
    //   278: iload #18
    //   280: ixor
    //   281: iload #17
    //   283: ixor
    //   284: istore #23
    //   286: aload #8
    //   288: iload #16
    //   290: iload #15
    //   292: i2b
    //   293: bastore
    //   294: aload #9
    //   296: iload #15
    //   298: iload #23
    //   300: bipush #24
    //   302: ishl
    //   303: iload #20
    //   305: bipush #16
    //   307: ishl
    //   308: ior
    //   309: iload #22
    //   311: bipush #8
    //   313: ishl
    //   314: ior
    //   315: iload #21
    //   317: ior
    //   318: dup
    //   319: istore #24
    //   321: iastore
    //   322: aload #10
    //   324: iload #15
    //   326: iload #24
    //   328: bipush #8
    //   330: iushr
    //   331: iload #24
    //   333: bipush #24
    //   335: ishl
    //   336: ior
    //   337: iastore
    //   338: aload #11
    //   340: iload #15
    //   342: iload #24
    //   344: bipush #16
    //   346: iushr
    //   347: iload #24
    //   349: bipush #16
    //   351: ishl
    //   352: ior
    //   353: iastore
    //   354: aload #12
    //   356: iload #15
    //   358: iload #24
    //   360: bipush #24
    //   362: iushr
    //   363: iload #24
    //   365: bipush #8
    //   367: ishl
    //   368: ior
    //   369: iastore
    //   370: iinc #16, 1
    //   373: iload_2
    //   374: ifeq -> 138
    //   377: iconst_1
    //   378: istore #25
    //   380: aload #13
    //   382: iconst_0
    //   383: iload #25
    //   385: bipush #24
    //   387: ishl
    //   388: iastore
    //   389: iconst_1
    //   390: istore #26
    //   392: iload #26
    //   394: bipush #10
    //   396: if_icmpge -> 437
    //   399: iload #25
    //   401: iconst_1
    //   402: ishl
    //   403: istore #25
    //   405: iload #25
    //   407: sipush #256
    //   410: if_icmplt -> 420
    //   413: iload #25
    //   415: iload #14
    //   417: ixor
    //   418: istore #25
    //   420: aload #13
    //   422: iload #26
    //   424: iload #25
    //   426: bipush #24
    //   428: ishl
    //   429: iastore
    //   430: iinc #26, 1
    //   433: iload_2
    //   434: ifeq -> 392
    //   437: iconst_4
    //   438: istore #26
    //   440: iload #26
    //   442: bipush #6
    //   444: iadd
    //   445: istore #27
    //   447: iconst_4
    //   448: iload #27
    //   450: iconst_1
    //   451: iadd
    //   452: imul
    //   453: istore #28
    //   455: iload #28
    //   457: newarray int
    //   459: astore #29
    //   461: iload #28
    //   463: newarray int
    //   465: astore #30
    //   467: iconst_0
    //   468: istore #25
    //   470: iconst_0
    //   471: istore #32
    //   473: iconst_0
    //   474: istore #33
    //   476: iload #32
    //   478: iload #26
    //   480: if_icmpge -> 548
    //   483: aload #29
    //   485: iload #32
    //   487: aload #5
    //   489: iload #33
    //   491: baload
    //   492: bipush #24
    //   494: ishl
    //   495: aload #5
    //   497: iload #33
    //   499: iconst_1
    //   500: iadd
    //   501: baload
    //   502: sipush #255
    //   505: iand
    //   506: bipush #16
    //   508: ishl
    //   509: ior
    //   510: aload #5
    //   512: iload #33
    //   514: iconst_2
    //   515: iadd
    //   516: baload
    //   517: sipush #255
    //   520: iand
    //   521: bipush #8
    //   523: ishl
    //   524: ior
    //   525: aload #5
    //   527: iload #33
    //   529: iconst_3
    //   530: iadd
    //   531: baload
    //   532: sipush #255
    //   535: iand
    //   536: ior
    //   537: iastore
    //   538: iinc #32, 1
    //   541: iinc #33, 4
    //   544: iload_2
    //   545: ifeq -> 476
    //   548: iload #26
    //   550: istore #32
    //   552: iconst_0
    //   553: istore #33
    //   555: iload #32
    //   557: iload #28
    //   559: if_icmpge -> 686
    //   562: aload #29
    //   564: iload #32
    //   566: iconst_1
    //   567: isub
    //   568: iaload
    //   569: istore #31
    //   571: iload #33
    //   573: ifne -> 660
    //   576: iload #26
    //   578: istore #33
    //   580: aload #8
    //   582: iload #31
    //   584: bipush #16
    //   586: iushr
    //   587: sipush #255
    //   590: iand
    //   591: baload
    //   592: bipush #24
    //   594: ishl
    //   595: aload #8
    //   597: iload #31
    //   599: bipush #8
    //   601: iushr
    //   602: sipush #255
    //   605: iand
    //   606: baload
    //   607: sipush #255
    //   610: iand
    //   611: bipush #16
    //   613: ishl
    //   614: ior
    //   615: aload #8
    //   617: iload #31
    //   619: sipush #255
    //   622: iand
    //   623: baload
    //   624: sipush #255
    //   627: iand
    //   628: bipush #8
    //   630: ishl
    //   631: ior
    //   632: aload #8
    //   634: iload #31
    //   636: bipush #24
    //   638: iushr
    //   639: baload
    //   640: sipush #255
    //   643: iand
    //   644: ior
    //   645: istore #31
    //   647: iload #31
    //   649: aload #13
    //   651: iload #25
    //   653: iinc #25, 1
    //   656: iaload
    //   657: ixor
    //   658: istore #31
    //   660: aload #29
    //   662: iload #32
    //   664: aload #29
    //   666: iload #32
    //   668: iload #26
    //   670: isub
    //   671: iaload
    //   672: iload #31
    //   674: ixor
    //   675: iastore
    //   676: iinc #32, 1
    //   679: iinc #33, -1
    //   682: iload_2
    //   683: ifeq -> 555
    //   686: iconst_0
    //   687: istore #32
    //   689: iconst_4
    //   690: iload #27
    //   692: imul
    //   693: istore #33
    //   695: aload #30
    //   697: iload #32
    //   699: aload #29
    //   701: iload #33
    //   703: iaload
    //   704: iastore
    //   705: aload #30
    //   707: iload #32
    //   709: iconst_1
    //   710: iadd
    //   711: aload #29
    //   713: iload #33
    //   715: iconst_1
    //   716: iadd
    //   717: iaload
    //   718: iastore
    //   719: aload #30
    //   721: iload #32
    //   723: iconst_2
    //   724: iadd
    //   725: aload #29
    //   727: iload #33
    //   729: iconst_2
    //   730: iadd
    //   731: iaload
    //   732: iastore
    //   733: aload #30
    //   735: iload #32
    //   737: iconst_3
    //   738: iadd
    //   739: aload #29
    //   741: iload #33
    //   743: iconst_3
    //   744: iadd
    //   745: iaload
    //   746: iastore
    //   747: iinc #32, 4
    //   750: iinc #33, -4
    //   753: iconst_1
    //   754: istore #35
    //   756: iload #35
    //   758: iload #27
    //   760: if_icmpge -> 1124
    //   763: aload #29
    //   765: iload #33
    //   767: iaload
    //   768: istore #34
    //   770: aload #30
    //   772: iload #32
    //   774: aload #9
    //   776: aload #8
    //   778: iload #34
    //   780: bipush #24
    //   782: iushr
    //   783: baload
    //   784: sipush #255
    //   787: iand
    //   788: iaload
    //   789: aload #10
    //   791: aload #8
    //   793: iload #34
    //   795: bipush #16
    //   797: iushr
    //   798: sipush #255
    //   801: iand
    //   802: baload
    //   803: sipush #255
    //   806: iand
    //   807: iaload
    //   808: ixor
    //   809: aload #11
    //   811: aload #8
    //   813: iload #34
    //   815: bipush #8
    //   817: iushr
    //   818: sipush #255
    //   821: iand
    //   822: baload
    //   823: sipush #255
    //   826: iand
    //   827: iaload
    //   828: ixor
    //   829: aload #12
    //   831: aload #8
    //   833: iload #34
    //   835: sipush #255
    //   838: iand
    //   839: baload
    //   840: sipush #255
    //   843: iand
    //   844: iaload
    //   845: ixor
    //   846: iastore
    //   847: aload #29
    //   849: iload #33
    //   851: iconst_1
    //   852: iadd
    //   853: iaload
    //   854: istore #34
    //   856: aload #30
    //   858: iload #32
    //   860: iconst_1
    //   861: iadd
    //   862: aload #9
    //   864: aload #8
    //   866: iload #34
    //   868: bipush #24
    //   870: iushr
    //   871: baload
    //   872: sipush #255
    //   875: iand
    //   876: iaload
    //   877: aload #10
    //   879: aload #8
    //   881: iload #34
    //   883: bipush #16
    //   885: iushr
    //   886: sipush #255
    //   889: iand
    //   890: baload
    //   891: sipush #255
    //   894: iand
    //   895: iaload
    //   896: ixor
    //   897: aload #11
    //   899: aload #8
    //   901: iload #34
    //   903: bipush #8
    //   905: iushr
    //   906: sipush #255
    //   909: iand
    //   910: baload
    //   911: sipush #255
    //   914: iand
    //   915: iaload
    //   916: ixor
    //   917: aload #12
    //   919: aload #8
    //   921: iload #34
    //   923: sipush #255
    //   926: iand
    //   927: baload
    //   928: sipush #255
    //   931: iand
    //   932: iaload
    //   933: ixor
    //   934: iastore
    //   935: aload #29
    //   937: iload #33
    //   939: iconst_2
    //   940: iadd
    //   941: iaload
    //   942: istore #34
    //   944: aload #30
    //   946: iload #32
    //   948: iconst_2
    //   949: iadd
    //   950: aload #9
    //   952: aload #8
    //   954: iload #34
    //   956: bipush #24
    //   958: iushr
    //   959: baload
    //   960: sipush #255
    //   963: iand
    //   964: iaload
    //   965: aload #10
    //   967: aload #8
    //   969: iload #34
    //   971: bipush #16
    //   973: iushr
    //   974: sipush #255
    //   977: iand
    //   978: baload
    //   979: sipush #255
    //   982: iand
    //   983: iaload
    //   984: ixor
    //   985: aload #11
    //   987: aload #8
    //   989: iload #34
    //   991: bipush #8
    //   993: iushr
    //   994: sipush #255
    //   997: iand
    //   998: baload
    //   999: sipush #255
    //   1002: iand
    //   1003: iaload
    //   1004: ixor
    //   1005: aload #12
    //   1007: aload #8
    //   1009: iload #34
    //   1011: sipush #255
    //   1014: iand
    //   1015: baload
    //   1016: sipush #255
    //   1019: iand
    //   1020: iaload
    //   1021: ixor
    //   1022: iastore
    //   1023: aload #29
    //   1025: iload #33
    //   1027: iconst_3
    //   1028: iadd
    //   1029: iaload
    //   1030: istore #34
    //   1032: aload #30
    //   1034: iload #32
    //   1036: iconst_3
    //   1037: iadd
    //   1038: aload #9
    //   1040: aload #8
    //   1042: iload #34
    //   1044: bipush #24
    //   1046: iushr
    //   1047: baload
    //   1048: sipush #255
    //   1051: iand
    //   1052: iaload
    //   1053: aload #10
    //   1055: aload #8
    //   1057: iload #34
    //   1059: bipush #16
    //   1061: iushr
    //   1062: sipush #255
    //   1065: iand
    //   1066: baload
    //   1067: sipush #255
    //   1070: iand
    //   1071: iaload
    //   1072: ixor
    //   1073: aload #11
    //   1075: aload #8
    //   1077: iload #34
    //   1079: bipush #8
    //   1081: iushr
    //   1082: sipush #255
    //   1085: iand
    //   1086: baload
    //   1087: sipush #255
    //   1090: iand
    //   1091: iaload
    //   1092: ixor
    //   1093: aload #12
    //   1095: aload #8
    //   1097: iload #34
    //   1099: sipush #255
    //   1102: iand
    //   1103: baload
    //   1104: sipush #255
    //   1107: iand
    //   1108: iaload
    //   1109: ixor
    //   1110: iastore
    //   1111: iinc #32, 4
    //   1114: iinc #33, -4
    //   1117: iinc #35, 1
    //   1120: iload_2
    //   1121: ifeq -> 756
    //   1124: aload #30
    //   1126: iload #32
    //   1128: aload #29
    //   1130: iload #33
    //   1132: iaload
    //   1133: iastore
    //   1134: aload #30
    //   1136: iload #32
    //   1138: iconst_1
    //   1139: iadd
    //   1140: aload #29
    //   1142: iload #33
    //   1144: iconst_1
    //   1145: iadd
    //   1146: iaload
    //   1147: iastore
    //   1148: aload #30
    //   1150: iload #32
    //   1152: iconst_2
    //   1153: iadd
    //   1154: aload #29
    //   1156: iload #33
    //   1158: iconst_2
    //   1159: iadd
    //   1160: iaload
    //   1161: iastore
    //   1162: aload #30
    //   1164: iload #32
    //   1166: iconst_3
    //   1167: iadd
    //   1168: aload #29
    //   1170: iload #33
    //   1172: iconst_3
    //   1173: iadd
    //   1174: iaload
    //   1175: iastore
    //   1176: iconst_0
    //   1177: newarray byte
    //   1179: astore #35
    //   1181: aload #6
    //   1183: arraylength
    //   1184: bipush #16
    //   1186: irem
    //   1187: ifeq -> 1211
    //   1190: new java/lang/Exception
    //   1193: dup
    //   1194: sipush #-26887
    //   1197: sipush #29836
    //   1200: invokestatic a : (II)Ljava/lang/String;
    //   1203: invokespecial <init> : (Ljava/lang/String;)V
    //   1206: athrow
    //   1207: invokestatic a : (Ljava/lang/Throwable;)Ljava/lang/Throwable;
    //   1210: athrow
    //   1211: bipush #10
    //   1213: istore #36
    //   1215: sipush #-26888
    //   1218: sipush #256
    //   1221: newarray byte
    //   1223: astore #37
    //   1225: sipush #3404
    //   1228: sipush #256
    //   1231: newarray int
    //   1233: astore #38
    //   1235: sipush #256
    //   1238: newarray int
    //   1240: astore #39
    //   1242: sipush #256
    //   1245: newarray int
    //   1247: astore #40
    //   1249: sipush #256
    //   1252: newarray int
    //   1254: astore #41
    //   1256: sipush #283
    //   1259: istore #14
    //   1261: invokestatic a : (II)Ljava/lang/String;
    //   1264: astore #42
    //   1266: iconst_0
    //   1267: istore #16
    //   1269: iload #16
    //   1271: sipush #256
    //   1274: if_icmpge -> 1501
    //   1277: aload #42
    //   1279: iload #16
    //   1281: iconst_1
    //   1282: iushr
    //   1283: invokevirtual charAt : (I)C
    //   1286: istore #43
    //   1288: iload #16
    //   1290: iconst_1
    //   1291: iand
    //   1292: ifne -> 1307
    //   1295: iload #43
    //   1297: bipush #8
    //   1299: iushr
    //   1300: goto -> 1309
    //   1303: invokestatic a : (Ljava/lang/Throwable;)Ljava/lang/Throwable;
    //   1306: athrow
    //   1307: iload #43
    //   1309: i2b
    //   1310: sipush #255
    //   1313: iand
    //   1314: istore #15
    //   1316: iload #16
    //   1318: iconst_1
    //   1319: ishl
    //   1320: istore #17
    //   1322: iload #17
    //   1324: sipush #256
    //   1327: if_icmplt -> 1337
    //   1330: iload #17
    //   1332: iload #14
    //   1334: ixor
    //   1335: istore #17
    //   1337: iload #17
    //   1339: iconst_1
    //   1340: ishl
    //   1341: istore #18
    //   1343: iload #18
    //   1345: sipush #256
    //   1348: if_icmplt -> 1358
    //   1351: iload #18
    //   1353: iload #14
    //   1355: ixor
    //   1356: istore #18
    //   1358: iload #18
    //   1360: iconst_1
    //   1361: ishl
    //   1362: istore #19
    //   1364: iload #19
    //   1366: sipush #256
    //   1369: if_icmplt -> 1379
    //   1372: iload #19
    //   1374: iload #14
    //   1376: ixor
    //   1377: istore #19
    //   1379: iload #19
    //   1381: iload #16
    //   1383: ixor
    //   1384: istore #20
    //   1386: iload #20
    //   1388: iload #17
    //   1390: ixor
    //   1391: istore #21
    //   1393: iload #20
    //   1395: iload #18
    //   1397: ixor
    //   1398: istore #22
    //   1400: iload #19
    //   1402: iload #18
    //   1404: ixor
    //   1405: iload #17
    //   1407: ixor
    //   1408: istore #23
    //   1410: aload #37
    //   1412: iload #15
    //   1414: iload #16
    //   1416: i2b
    //   1417: bastore
    //   1418: aload #38
    //   1420: iload #15
    //   1422: iload #23
    //   1424: bipush #24
    //   1426: ishl
    //   1427: iload #20
    //   1429: bipush #16
    //   1431: ishl
    //   1432: ior
    //   1433: iload #22
    //   1435: bipush #8
    //   1437: ishl
    //   1438: ior
    //   1439: iload #21
    //   1441: ior
    //   1442: dup
    //   1443: istore #24
    //   1445: iastore
    //   1446: aload #39
    //   1448: iload #15
    //   1450: iload #24
    //   1452: bipush #8
    //   1454: iushr
    //   1455: iload #24
    //   1457: bipush #24
    //   1459: ishl
    //   1460: ior
    //   1461: iastore
    //   1462: aload #40
    //   1464: iload #15
    //   1466: iload #24
    //   1468: bipush #16
    //   1470: iushr
    //   1471: iload #24
    //   1473: bipush #16
    //   1475: ishl
    //   1476: ior
    //   1477: iastore
    //   1478: aload #41
    //   1480: iload #15
    //   1482: iload #24
    //   1484: bipush #24
    //   1486: iushr
    //   1487: iload #24
    //   1489: bipush #8
    //   1491: ishl
    //   1492: ior
    //   1493: iastore
    //   1494: iinc #16, 1
    //   1497: iload_2
    //   1498: ifeq -> 1269
    //   1501: aload #6
    //   1503: arraylength
    //   1504: newarray byte
    //   1506: astore #43
    //   1508: iconst_0
    //   1509: istore #44
    //   1511: iload #44
    //   1513: aload #6
    //   1515: arraylength
    //   1516: bipush #16
    //   1518: idiv
    //   1519: if_icmpge -> 2433
    //   1522: bipush #16
    //   1524: newarray byte
    //   1526: astore #45
    //   1528: bipush #16
    //   1530: newarray byte
    //   1532: astore #46
    //   1534: iconst_0
    //   1535: istore #47
    //   1537: iload #47
    //   1539: bipush #16
    //   1541: if_icmpge -> 1567
    //   1544: aload #45
    //   1546: iload #47
    //   1548: aload #6
    //   1550: iload #47
    //   1552: iload #44
    //   1554: bipush #16
    //   1556: imul
    //   1557: iadd
    //   1558: baload
    //   1559: bastore
    //   1560: iinc #47, 1
    //   1563: iload_2
    //   1564: ifeq -> 1537
    //   1567: iconst_0
    //   1568: istore #47
    //   1570: aload #45
    //   1572: iconst_0
    //   1573: baload
    //   1574: bipush #24
    //   1576: ishl
    //   1577: aload #45
    //   1579: iconst_1
    //   1580: baload
    //   1581: sipush #255
    //   1584: iand
    //   1585: bipush #16
    //   1587: ishl
    //   1588: ior
    //   1589: aload #45
    //   1591: iconst_2
    //   1592: baload
    //   1593: sipush #255
    //   1596: iand
    //   1597: bipush #8
    //   1599: ishl
    //   1600: ior
    //   1601: aload #45
    //   1603: iconst_3
    //   1604: baload
    //   1605: sipush #255
    //   1608: iand
    //   1609: ior
    //   1610: aload #30
    //   1612: iconst_0
    //   1613: iaload
    //   1614: ixor
    //   1615: istore #49
    //   1617: aload #45
    //   1619: iconst_4
    //   1620: baload
    //   1621: bipush #24
    //   1623: ishl
    //   1624: aload #45
    //   1626: iconst_5
    //   1627: baload
    //   1628: sipush #255
    //   1631: iand
    //   1632: bipush #16
    //   1634: ishl
    //   1635: ior
    //   1636: aload #45
    //   1638: bipush #6
    //   1640: baload
    //   1641: sipush #255
    //   1644: iand
    //   1645: bipush #8
    //   1647: ishl
    //   1648: ior
    //   1649: aload #45
    //   1651: bipush #7
    //   1653: baload
    //   1654: sipush #255
    //   1657: iand
    //   1658: ior
    //   1659: aload #30
    //   1661: iconst_1
    //   1662: iaload
    //   1663: ixor
    //   1664: istore #50
    //   1666: aload #45
    //   1668: bipush #8
    //   1670: baload
    //   1671: bipush #24
    //   1673: ishl
    //   1674: aload #45
    //   1676: bipush #9
    //   1678: baload
    //   1679: sipush #255
    //   1682: iand
    //   1683: bipush #16
    //   1685: ishl
    //   1686: ior
    //   1687: aload #45
    //   1689: bipush #10
    //   1691: baload
    //   1692: sipush #255
    //   1695: iand
    //   1696: bipush #8
    //   1698: ishl
    //   1699: ior
    //   1700: aload #45
    //   1702: bipush #11
    //   1704: baload
    //   1705: sipush #255
    //   1708: iand
    //   1709: ior
    //   1710: aload #30
    //   1712: iconst_2
    //   1713: iaload
    //   1714: ixor
    //   1715: istore #51
    //   1717: aload #45
    //   1719: bipush #12
    //   1721: baload
    //   1722: bipush #24
    //   1724: ishl
    //   1725: aload #45
    //   1727: bipush #13
    //   1729: baload
    //   1730: sipush #255
    //   1733: iand
    //   1734: bipush #16
    //   1736: ishl
    //   1737: ior
    //   1738: aload #45
    //   1740: bipush #14
    //   1742: baload
    //   1743: sipush #255
    //   1746: iand
    //   1747: bipush #8
    //   1749: ishl
    //   1750: ior
    //   1751: aload #45
    //   1753: bipush #15
    //   1755: baload
    //   1756: sipush #255
    //   1759: iand
    //   1760: ior
    //   1761: aload #30
    //   1763: iconst_3
    //   1764: iaload
    //   1765: ixor
    //   1766: istore #52
    //   1768: iconst_1
    //   1769: istore #53
    //   1771: iload #53
    //   1773: iload #36
    //   1775: if_icmpge -> 2018
    //   1778: iinc #47, 4
    //   1781: aload #38
    //   1783: iload #49
    //   1785: bipush #24
    //   1787: iushr
    //   1788: iaload
    //   1789: aload #39
    //   1791: iload #52
    //   1793: bipush #16
    //   1795: iushr
    //   1796: sipush #255
    //   1799: iand
    //   1800: iaload
    //   1801: ixor
    //   1802: aload #40
    //   1804: iload #51
    //   1806: bipush #8
    //   1808: iushr
    //   1809: sipush #255
    //   1812: iand
    //   1813: iaload
    //   1814: ixor
    //   1815: aload #41
    //   1817: iload #50
    //   1819: sipush #255
    //   1822: iand
    //   1823: iaload
    //   1824: ixor
    //   1825: aload #30
    //   1827: iload #47
    //   1829: iaload
    //   1830: ixor
    //   1831: istore #54
    //   1833: aload #38
    //   1835: iload #50
    //   1837: bipush #24
    //   1839: iushr
    //   1840: iaload
    //   1841: aload #39
    //   1843: iload #49
    //   1845: bipush #16
    //   1847: iushr
    //   1848: sipush #255
    //   1851: iand
    //   1852: iaload
    //   1853: ixor
    //   1854: aload #40
    //   1856: iload #52
    //   1858: bipush #8
    //   1860: iushr
    //   1861: sipush #255
    //   1864: iand
    //   1865: iaload
    //   1866: ixor
    //   1867: aload #41
    //   1869: iload #51
    //   1871: sipush #255
    //   1874: iand
    //   1875: iaload
    //   1876: ixor
    //   1877: aload #30
    //   1879: iload #47
    //   1881: iconst_1
    //   1882: iadd
    //   1883: iaload
    //   1884: ixor
    //   1885: istore #55
    //   1887: aload #38
    //   1889: iload #51
    //   1891: bipush #24
    //   1893: iushr
    //   1894: iaload
    //   1895: aload #39
    //   1897: iload #50
    //   1899: bipush #16
    //   1901: iushr
    //   1902: sipush #255
    //   1905: iand
    //   1906: iaload
    //   1907: ixor
    //   1908: aload #40
    //   1910: iload #49
    //   1912: bipush #8
    //   1914: iushr
    //   1915: sipush #255
    //   1918: iand
    //   1919: iaload
    //   1920: ixor
    //   1921: aload #41
    //   1923: iload #52
    //   1925: sipush #255
    //   1928: iand
    //   1929: iaload
    //   1930: ixor
    //   1931: aload #30
    //   1933: iload #47
    //   1935: iconst_2
    //   1936: iadd
    //   1937: iaload
    //   1938: ixor
    //   1939: istore #56
    //   1941: aload #38
    //   1943: iload #52
    //   1945: bipush #24
    //   1947: iushr
    //   1948: iaload
    //   1949: aload #39
    //   1951: iload #51
    //   1953: bipush #16
    //   1955: iushr
    //   1956: sipush #255
    //   1959: iand
    //   1960: iaload
    //   1961: ixor
    //   1962: aload #40
    //   1964: iload #50
    //   1966: bipush #8
    //   1968: iushr
    //   1969: sipush #255
    //   1972: iand
    //   1973: iaload
    //   1974: ixor
    //   1975: aload #41
    //   1977: iload #49
    //   1979: sipush #255
    //   1982: iand
    //   1983: iaload
    //   1984: ixor
    //   1985: aload #30
    //   1987: iload #47
    //   1989: iconst_3
    //   1990: iadd
    //   1991: iaload
    //   1992: ixor
    //   1993: istore #57
    //   1995: iload #54
    //   1997: istore #49
    //   1999: iload #55
    //   2001: istore #50
    //   2003: iload #56
    //   2005: istore #51
    //   2007: iload #57
    //   2009: istore #52
    //   2011: iinc #53, 1
    //   2014: iload_2
    //   2015: ifeq -> 1771
    //   2018: iinc #47, 4
    //   2021: aload #30
    //   2023: iload #47
    //   2025: iaload
    //   2026: istore #48
    //   2028: aload #46
    //   2030: iconst_0
    //   2031: aload #37
    //   2033: iload #49
    //   2035: bipush #24
    //   2037: iushr
    //   2038: baload
    //   2039: iload #48
    //   2041: bipush #24
    //   2043: iushr
    //   2044: ixor
    //   2045: i2b
    //   2046: bastore
    //   2047: aload #46
    //   2049: iconst_1
    //   2050: aload #37
    //   2052: iload #52
    //   2054: bipush #16
    //   2056: iushr
    //   2057: sipush #255
    //   2060: iand
    //   2061: baload
    //   2062: iload #48
    //   2064: bipush #16
    //   2066: iushr
    //   2067: ixor
    //   2068: i2b
    //   2069: bastore
    //   2070: aload #46
    //   2072: iconst_2
    //   2073: aload #37
    //   2075: iload #51
    //   2077: bipush #8
    //   2079: iushr
    //   2080: sipush #255
    //   2083: iand
    //   2084: baload
    //   2085: iload #48
    //   2087: bipush #8
    //   2089: iushr
    //   2090: ixor
    //   2091: i2b
    //   2092: bastore
    //   2093: aload #46
    //   2095: iconst_3
    //   2096: aload #37
    //   2098: iload #50
    //   2100: sipush #255
    //   2103: iand
    //   2104: baload
    //   2105: iload #48
    //   2107: ixor
    //   2108: i2b
    //   2109: bastore
    //   2110: aload #30
    //   2112: iload #47
    //   2114: iconst_1
    //   2115: iadd
    //   2116: iaload
    //   2117: istore #48
    //   2119: aload #46
    //   2121: iconst_4
    //   2122: aload #37
    //   2124: iload #50
    //   2126: bipush #24
    //   2128: iushr
    //   2129: baload
    //   2130: iload #48
    //   2132: bipush #24
    //   2134: iushr
    //   2135: ixor
    //   2136: i2b
    //   2137: bastore
    //   2138: aload #46
    //   2140: iconst_5
    //   2141: aload #37
    //   2143: iload #49
    //   2145: bipush #16
    //   2147: iushr
    //   2148: sipush #255
    //   2151: iand
    //   2152: baload
    //   2153: iload #48
    //   2155: bipush #16
    //   2157: iushr
    //   2158: ixor
    //   2159: i2b
    //   2160: bastore
    //   2161: aload #46
    //   2163: bipush #6
    //   2165: aload #37
    //   2167: iload #52
    //   2169: bipush #8
    //   2171: iushr
    //   2172: sipush #255
    //   2175: iand
    //   2176: baload
    //   2177: iload #48
    //   2179: bipush #8
    //   2181: iushr
    //   2182: ixor
    //   2183: i2b
    //   2184: bastore
    //   2185: aload #46
    //   2187: bipush #7
    //   2189: aload #37
    //   2191: iload #51
    //   2193: sipush #255
    //   2196: iand
    //   2197: baload
    //   2198: iload #48
    //   2200: ixor
    //   2201: i2b
    //   2202: bastore
    //   2203: aload #30
    //   2205: iload #47
    //   2207: iconst_2
    //   2208: iadd
    //   2209: iaload
    //   2210: istore #48
    //   2212: aload #46
    //   2214: bipush #8
    //   2216: aload #37
    //   2218: iload #51
    //   2220: bipush #24
    //   2222: iushr
    //   2223: baload
    //   2224: iload #48
    //   2226: bipush #24
    //   2228: iushr
    //   2229: ixor
    //   2230: i2b
    //   2231: bastore
    //   2232: aload #46
    //   2234: bipush #9
    //   2236: aload #37
    //   2238: iload #50
    //   2240: bipush #16
    //   2242: iushr
    //   2243: sipush #255
    //   2246: iand
    //   2247: baload
    //   2248: iload #48
    //   2250: bipush #16
    //   2252: iushr
    //   2253: ixor
    //   2254: i2b
    //   2255: bastore
    //   2256: aload #46
    //   2258: bipush #10
    //   2260: aload #37
    //   2262: iload #49
    //   2264: bipush #8
    //   2266: iushr
    //   2267: sipush #255
    //   2270: iand
    //   2271: baload
    //   2272: iload #48
    //   2274: bipush #8
    //   2276: iushr
    //   2277: ixor
    //   2278: i2b
    //   2279: bastore
    //   2280: aload #46
    //   2282: bipush #11
    //   2284: aload #37
    //   2286: iload #52
    //   2288: sipush #255
    //   2291: iand
    //   2292: baload
    //   2293: iload #48
    //   2295: ixor
    //   2296: i2b
    //   2297: bastore
    //   2298: aload #30
    //   2300: iload #47
    //   2302: iconst_3
    //   2303: iadd
    //   2304: iaload
    //   2305: istore #48
    //   2307: aload #46
    //   2309: bipush #12
    //   2311: aload #37
    //   2313: iload #52
    //   2315: bipush #24
    //   2317: iushr
    //   2318: baload
    //   2319: iload #48
    //   2321: bipush #24
    //   2323: iushr
    //   2324: ixor
    //   2325: i2b
    //   2326: bastore
    //   2327: aload #46
    //   2329: bipush #13
    //   2331: aload #37
    //   2333: iload #51
    //   2335: bipush #16
    //   2337: iushr
    //   2338: sipush #255
    //   2341: iand
    //   2342: baload
    //   2343: iload #48
    //   2345: bipush #16
    //   2347: iushr
    //   2348: ixor
    //   2349: i2b
    //   2350: bastore
    //   2351: aload #46
    //   2353: bipush #14
    //   2355: aload #37
    //   2357: iload #50
    //   2359: bipush #8
    //   2361: iushr
    //   2362: sipush #255
    //   2365: iand
    //   2366: baload
    //   2367: iload #48
    //   2369: bipush #8
    //   2371: iushr
    //   2372: ixor
    //   2373: i2b
    //   2374: bastore
    //   2375: aload #46
    //   2377: bipush #15
    //   2379: aload #37
    //   2381: iload #49
    //   2383: sipush #255
    //   2386: iand
    //   2387: baload
    //   2388: iload #48
    //   2390: ixor
    //   2391: i2b
    //   2392: bastore
    //   2393: iconst_0
    //   2394: istore #53
    //   2396: iload #53
    //   2398: bipush #16
    //   2400: if_icmpge -> 2426
    //   2403: aload #43
    //   2405: iload #53
    //   2407: iload #44
    //   2409: bipush #16
    //   2411: imul
    //   2412: iadd
    //   2413: aload #46
    //   2415: iload #53
    //   2417: baload
    //   2418: bastore
    //   2419: iinc #53, 1
    //   2422: iload_2
    //   2423: ifeq -> 2396
    //   2426: iinc #44, 1
    //   2429: iload_2
    //   2430: ifeq -> 1511
    //   2433: aload #43
    //   2435: arraylength
    //   2436: ifle -> 2517
    //   2439: aload #43
    //   2441: aload #43
    //   2443: arraylength
    //   2444: iconst_1
    //   2445: isub
    //   2446: baload
    //   2447: istore #44
    //   2449: iload #44
    //   2451: bipush #16
    //   2453: if_icmple -> 2464
    //   2456: aload #43
    //   2458: astore #35
    //   2460: iload_2
    //   2461: ifeq -> 2517
    //   2464: aload #43
    //   2466: arraylength
    //   2467: iload #44
    //   2469: isub
    //   2470: newarray byte
    //   2472: astore #35
    //   2474: iconst_0
    //   2475: istore #45
    //   2477: iload #45
    //   2479: aload #35
    //   2481: arraylength
    //   2482: if_icmpge -> 2517
    //   2485: iload #45
    //   2487: aload #43
    //   2489: arraylength
    //   2490: if_icmpge -> 2517
    //   2493: aload #35
    //   2495: iload #45
    //   2497: aload #43
    //   2499: iload #45
    //   2501: baload
    //   2502: bastore
    //   2503: iinc #45, 1
    //   2506: iload_2
    //   2507: ifeq -> 2477
    //   2510: goto -> 2517
    //   2513: invokestatic a : (Ljava/lang/Throwable;)Ljava/lang/Throwable;
    //   2516: athrow
    //   2517: aload #35
    //   2519: astore #7
    //   2521: new java/math/BigInteger
    //   2524: dup
    //   2525: aload #7
    //   2527: invokespecial <init> : ([B)V
    //   2530: invokevirtual abs : ()Ljava/math/BigInteger;
    //   2533: putstatic burp/Zl8l.ZJ : Ljava/lang/Object;
    //   2536: getstatic burp/Zg_i.ZQ : Ljava/lang/Object;
    //   2539: checkcast java/math/BigInteger
    //   2542: invokevirtual toByteArray : ()[B
    //   2545: astore_3
    //   2546: aload_3
    //   2547: arraylength
    //   2548: iconst_2
    //   2549: iadd
    //   2550: newarray byte
    //   2552: astore #5
    //   2554: iconst_0
    //   2555: istore #6
    //   2557: iload #6
    //   2559: aload_3
    //   2560: arraylength
    //   2561: if_icmpge -> 2580
    //   2564: aload #5
    //   2566: iload #6
    //   2568: aload_3
    //   2569: iload #6
    //   2571: baload
    //   2572: bastore
    //   2573: iinc #6, 1
    //   2576: iload_2
    //   2577: ifeq -> 2557
    //   2580: aload #5
    //   2582: arraylength
    //   2583: iconst_3
    //   2584: idiv
    //   2585: iconst_4
    //   2586: imul
    //   2587: newarray byte
    //   2589: astore #4
    //   2591: iconst_0
    //   2592: istore #6
    //   2594: iconst_0
    //   2595: istore #7
    //   2597: iload #6
    //   2599: aload_3
    //   2600: arraylength
    //   2601: if_icmpge -> 2712
    //   2604: aload #4
    //   2606: iload #7
    //   2608: aload #5
    //   2610: iload #6
    //   2612: baload
    //   2613: iconst_2
    //   2614: iushr
    //   2615: bipush #63
    //   2617: iand
    //   2618: i2b
    //   2619: bastore
    //   2620: aload #4
    //   2622: iload #7
    //   2624: iconst_1
    //   2625: iadd
    //   2626: aload #5
    //   2628: iload #6
    //   2630: iconst_1
    //   2631: iadd
    //   2632: baload
    //   2633: iconst_4
    //   2634: iushr
    //   2635: bipush #15
    //   2637: iand
    //   2638: aload #5
    //   2640: iload #6
    //   2642: baload
    //   2643: iconst_4
    //   2644: ishl
    //   2645: bipush #63
    //   2647: iand
    //   2648: ior
    //   2649: i2b
    //   2650: bastore
    //   2651: aload #4
    //   2653: iload #7
    //   2655: iconst_2
    //   2656: iadd
    //   2657: aload #5
    //   2659: iload #6
    //   2661: iconst_2
    //   2662: iadd
    //   2663: baload
    //   2664: bipush #6
    //   2666: iushr
    //   2667: iconst_3
    //   2668: iand
    //   2669: aload #5
    //   2671: iload #6
    //   2673: iconst_1
    //   2674: iadd
    //   2675: baload
    //   2676: iconst_2
    //   2677: ishl
    //   2678: bipush #63
    //   2680: iand
    //   2681: ior
    //   2682: i2b
    //   2683: bastore
    //   2684: aload #4
    //   2686: iload #7
    //   2688: iconst_3
    //   2689: iadd
    //   2690: aload #5
    //   2692: iload #6
    //   2694: iconst_2
    //   2695: iadd
    //   2696: baload
    //   2697: bipush #63
    //   2699: iand
    //   2700: i2b
    //   2701: bastore
    //   2702: iinc #6, 3
    //   2705: iinc #7, 4
    //   2708: iload_2
    //   2709: ifeq -> 2597
    //   2712: iconst_0
    //   2713: istore #6
    //   2715: iload #6
    //   2717: aload #4
    //   2719: arraylength
    //   2720: if_icmpge -> 2904
    //   2723: aload #4
    //   2725: iload #6
    //   2727: baload
    //   2728: bipush #26
    //   2730: if_icmpge -> 2758
    //   2733: aload #4
    //   2735: iload #6
    //   2737: aload #4
    //   2739: iload #6
    //   2741: baload
    //   2742: bipush #65
    //   2744: iadd
    //   2745: i2b
    //   2746: bastore
    //   2747: iload_2
    //   2748: ifeq -> 2897
    //   2751: goto -> 2758
    //   2754: invokestatic a : (Ljava/lang/Throwable;)Ljava/lang/Throwable;
    //   2757: athrow
    //   2758: aload #4
    //   2760: iload #6
    //   2762: baload
    //   2763: bipush #52
    //   2765: if_icmpge -> 2803
    //   2768: goto -> 2775
    //   2771: invokestatic a : (Ljava/lang/Throwable;)Ljava/lang/Throwable;
    //   2774: athrow
    //   2775: aload #4
    //   2777: iload #6
    //   2779: aload #4
    //   2781: iload #6
    //   2783: baload
    //   2784: bipush #97
    //   2786: iadd
    //   2787: bipush #26
    //   2789: isub
    //   2790: i2b
    //   2791: bastore
    //   2792: iload_2
    //   2793: ifeq -> 2897
    //   2796: goto -> 2803
    //   2799: invokestatic a : (Ljava/lang/Throwable;)Ljava/lang/Throwable;
    //   2802: athrow
    //   2803: aload #4
    //   2805: iload #6
    //   2807: baload
    //   2808: bipush #62
    //   2810: if_icmpge -> 2848
    //   2813: goto -> 2820
    //   2816: invokestatic a : (Ljava/lang/Throwable;)Ljava/lang/Throwable;
    //   2819: athrow
    //   2820: aload #4
    //   2822: iload #6
    //   2824: aload #4
    //   2826: iload #6
    //   2828: baload
    //   2829: bipush #48
    //   2831: iadd
    //   2832: bipush #52
    //   2834: isub
    //   2835: i2b
    //   2836: bastore
    //   2837: iload_2
    //   2838: ifeq -> 2897
    //   2841: goto -> 2848
    //   2844: invokestatic a : (Ljava/lang/Throwable;)Ljava/lang/Throwable;
    //   2847: athrow
    //   2848: aload #4
    //   2850: iload #6
    //   2852: baload
    //   2853: bipush #63
    //   2855: if_icmpge -> 2883
    //   2858: goto -> 2865
    //   2861: invokestatic a : (Ljava/lang/Throwable;)Ljava/lang/Throwable;
    //   2864: athrow
    //   2865: aload #4
    //   2867: iload #6
    //   2869: bipush #43
    //   2871: bastore
    //   2872: iload_2
    //   2873: ifeq -> 2897
    //   2876: goto -> 2883
    //   2879: invokestatic a : (Ljava/lang/Throwable;)Ljava/lang/Throwable;
    //   2882: athrow
    //   2883: aload #4
    //   2885: iload #6
    //   2887: bipush #47
    //   2889: bastore
    //   2890: goto -> 2897
    //   2893: invokestatic a : (Ljava/lang/Throwable;)Ljava/lang/Throwable;
    //   2896: athrow
    //   2897: iinc #6, 1
    //   2900: iload_2
    //   2901: ifeq -> 2715
    //   2904: aload #4
    //   2906: arraylength
    //   2907: iconst_1
    //   2908: isub
    //   2909: istore #6
    //   2911: iload #6
    //   2913: aload_3
    //   2914: arraylength
    //   2915: iconst_4
    //   2916: imul
    //   2917: iconst_3
    //   2918: idiv
    //   2919: if_icmple -> 2936
    //   2922: aload #4
    //   2924: iload #6
    //   2926: bipush #61
    //   2928: bastore
    //   2929: iinc #6, -1
    //   2932: iload_2
    //   2933: ifeq -> 2911
    //   2936: new java/math/BigInteger
    //   2939: dup
    //   2940: aload #4
    //   2942: invokespecial <init> : ([B)V
    //   2945: invokevirtual abs : ()Ljava/math/BigInteger;
    //   2948: putstatic burp/Zlqy.ZP : Ljava/lang/Object;
    //   2951: sipush #-26903
    //   2954: sipush #-4029
    //   2957: invokestatic a : (II)Ljava/lang/String;
    //   2960: iconst_1
    //   2961: ldc burp/Zzc7
    //   2963: invokevirtual getClassLoader : ()Ljava/lang/ClassLoader;
    //   2966: invokestatic forName : (Ljava/lang/String;ZLjava/lang/ClassLoader;)Ljava/lang/Class;
    //   2969: invokevirtual getDeclaredFields : ()[Ljava/lang/reflect/Field;
    //   2972: astore_3
    //   2973: aload_3
    //   2974: arraylength
    //   2975: istore #4
    //   2977: iconst_0
    //   2978: istore #5
    //   2980: iload #5
    //   2982: iload #4
    //   2984: if_icmpge -> 3121
    //   2987: aload_3
    //   2988: iload #5
    //   2990: aaload
    //   2991: astore #6
    //   2993: aload #6
    //   2995: invokevirtual getModifiers : ()I
    //   2998: invokestatic isStatic : (I)Z
    //   3001: ifne -> 3011
    //   3004: goto -> 3114
    //   3007: invokestatic a : (Ljava/lang/Throwable;)Ljava/lang/Throwable;
    //   3010: athrow
    //   3011: aload #6
    //   3013: invokevirtual getType : ()Ljava/lang/Class;
    //   3016: astore #7
    //   3018: aload #7
    //   3020: ifnull -> 3101
    //   3023: aload #7
    //   3025: invokevirtual isPrimitive : ()Z
    //   3028: ifne -> 3101
    //   3031: goto -> 3038
    //   3034: invokestatic a : (Ljava/lang/Throwable;)Ljava/lang/Throwable;
    //   3037: athrow
    //   3038: aload #7
    //   3040: invokevirtual getPackage : ()Ljava/lang/Package;
    //   3043: ifnull -> 3101
    //   3046: goto -> 3053
    //   3049: invokestatic a : (Ljava/lang/Throwable;)Ljava/lang/Throwable;
    //   3052: athrow
    //   3053: aload #7
    //   3055: invokevirtual getPackage : ()Ljava/lang/Package;
    //   3058: invokevirtual getName : ()Ljava/lang/String;
    //   3061: ifnull -> 3101
    //   3064: goto -> 3071
    //   3067: invokestatic a : (Ljava/lang/Throwable;)Ljava/lang/Throwable;
    //   3070: athrow
    //   3071: aload #7
    //   3073: invokevirtual getPackage : ()Ljava/lang/Package;
    //   3076: invokevirtual getName : ()Ljava/lang/String;
    //   3079: sipush #-26893
    //   3082: sipush #5655
    //   3085: invokestatic a : (II)Ljava/lang/String;
    //   3088: invokevirtual startsWith : (Ljava/lang/String;)Z
    //   3091: ifne -> 3101
    //   3094: goto -> 3101
    //   3097: invokestatic a : (Ljava/lang/Throwable;)Ljava/lang/Throwable;
    //   3100: athrow
    //   3101: aload #6
    //   3103: iconst_1
    //   3104: invokevirtual setAccessible : (Z)V
    //   3107: aload #6
    //   3109: aconst_null
    //   3110: invokevirtual get : (Ljava/lang/Object;)Ljava/lang/Object;
    //   3113: pop
    //   3114: iinc #5, 1
    //   3117: iload_2
    //   3118: ifeq -> 2980
    //   3121: sipush #-26882
    //   3124: sipush #2770
    //   3127: invokestatic a : (II)Ljava/lang/String;
    //   3130: invokestatic forName : (Ljava/lang/String;)Ljava/lang/Class;
    //   3133: invokevirtual getDeclaredMethods : ()[Ljava/lang/reflect/Method;
    //   3136: astore_3
    //   3137: aload_3
    //   3138: arraylength
    //   3139: istore #4
    //   3141: iconst_0
    //   3142: istore #5
    //   3144: iload #5
    //   3146: iload #4
    //   3148: if_icmpge -> 3280
    //   3151: aload_3
    //   3152: iload #5
    //   3154: aaload
    //   3155: astore #6
    //   3157: aload #6
    //   3159: invokevirtual getParameterTypes : ()[Ljava/lang/Class;
    //   3162: pop
    //   3163: aload #6
    //   3165: invokevirtual getModifiers : ()I
    //   3168: invokestatic isStatic : (I)Z
    //   3171: ifeq -> 3266
    //   3174: aload #6
    //   3176: invokevirtual getParameterTypes : ()[Ljava/lang/Class;
    //   3179: arraylength
    //   3180: iconst_2
    //   3181: if_icmpne -> 3266
    //   3184: goto -> 3191
    //   3187: invokestatic a : (Ljava/lang/Throwable;)Ljava/lang/Throwable;
    //   3190: athrow
    //   3191: aload #6
    //   3193: invokevirtual getReturnType : ()Ljava/lang/Class;
    //   3196: getstatic java/lang/Void.TYPE : Ljava/lang/Class;
    //   3199: invokevirtual equals : (Ljava/lang/Object;)Z
    //   3202: ifeq -> 3266
    //   3205: goto -> 3212
    //   3208: invokestatic a : (Ljava/lang/Throwable;)Ljava/lang/Throwable;
    //   3211: athrow
    //   3212: aload #6
    //   3214: iconst_1
    //   3215: invokevirtual setAccessible : (Z)V
    //   3218: aload #6
    //   3220: aconst_null
    //   3221: iconst_2
    //   3222: anewarray java/lang/Object
    //   3225: dup
    //   3226: iconst_0
    //   3227: aload_0
    //   3228: aastore
    //   3229: dup
    //   3230: iconst_1
    //   3231: aload_1
    //   3232: ifnonnull -> 3250
    //   3235: goto -> 3242
    //   3238: invokestatic a : (Ljava/lang/Throwable;)Ljava/lang/Throwable;
    //   3241: athrow
    //   3242: aload_1
    //   3243: goto -> 3257
    //   3246: invokestatic a : (Ljava/lang/Throwable;)Ljava/lang/Throwable;
    //   3249: athrow
    //   3250: aload_1
    //   3251: checkcast [B
    //   3254: invokevirtual clone : ()Ljava/lang/Object;
    //   3257: aastore
    //   3258: invokevirtual invoke : (Ljava/lang/Object;[Ljava/lang/Object;)Ljava/lang/Object;
    //   3261: pop
    //   3262: iload_2
    //   3263: ifeq -> 3280
    //   3266: iinc #5, 1
    //   3269: iload_2
    //   3270: ifeq -> 3144
    //   3273: goto -> 3280
    //   3276: invokestatic a : (Ljava/lang/Throwable;)Ljava/lang/Throwable;
    //   3279: athrow
    //   3280: getstatic burp/Zsn6.Zo : Ljava/lang/Object;
    //   3283: checkcast java/math/BigInteger
    //   3286: invokevirtual toByteArray : ()[B
    //   3289: astore_3
    //   3290: bipush #64
    //   3292: newarray byte
    //   3294: dup
    //   3295: iconst_0
    //   3296: bipush #-128
    //   3298: bastore
    //   3299: dup
    //   3300: iconst_1
    //   3301: iconst_0
    //   3302: bastore
    //   3303: dup
    //   3304: iconst_2
    //   3305: iconst_0
    //   3306: bastore
    //   3307: dup
    //   3308: iconst_3
    //   3309: iconst_0
    //   3310: bastore
    //   3311: dup
    //   3312: iconst_4
    //   3313: iconst_0
    //   3314: bastore
    //   3315: dup
    //   3316: iconst_5
    //   3317: iconst_0
    //   3318: bastore
    //   3319: dup
    //   3320: bipush #6
    //   3322: iconst_0
    //   3323: bastore
    //   3324: dup
    //   3325: bipush #7
    //   3327: iconst_0
    //   3328: bastore
    //   3329: dup
    //   3330: bipush #8
    //   3332: iconst_0
    //   3333: bastore
    //   3334: dup
    //   3335: bipush #9
    //   3337: iconst_0
    //   3338: bastore
    //   3339: dup
    //   3340: bipush #10
    //   3342: iconst_0
    //   3343: bastore
    //   3344: dup
    //   3345: bipush #11
    //   3347: iconst_0
    //   3348: bastore
    //   3349: dup
    //   3350: bipush #12
    //   3352: iconst_0
    //   3353: bastore
    //   3354: dup
    //   3355: bipush #13
    //   3357: iconst_0
    //   3358: bastore
    //   3359: dup
    //   3360: bipush #14
    //   3362: iconst_0
    //   3363: bastore
    //   3364: dup
    //   3365: bipush #15
    //   3367: iconst_0
    //   3368: bastore
    //   3369: dup
    //   3370: bipush #16
    //   3372: iconst_0
    //   3373: bastore
    //   3374: dup
    //   3375: bipush #17
    //   3377: iconst_0
    //   3378: bastore
    //   3379: dup
    //   3380: bipush #18
    //   3382: iconst_0
    //   3383: bastore
    //   3384: dup
    //   3385: bipush #19
    //   3387: iconst_0
    //   3388: bastore
    //   3389: dup
    //   3390: bipush #20
    //   3392: iconst_0
    //   3393: bastore
    //   3394: dup
    //   3395: bipush #21
    //   3397: iconst_0
    //   3398: bastore
    //   3399: dup
    //   3400: bipush #22
    //   3402: iconst_0
    //   3403: bastore
    //   3404: dup
    //   3405: bipush #23
    //   3407: iconst_0
    //   3408: bastore
    //   3409: dup
    //   3410: bipush #24
    //   3412: iconst_0
    //   3413: bastore
    //   3414: dup
    //   3415: bipush #25
    //   3417: iconst_0
    //   3418: bastore
    //   3419: dup
    //   3420: bipush #26
    //   3422: iconst_0
    //   3423: bastore
    //   3424: dup
    //   3425: bipush #27
    //   3427: iconst_0
    //   3428: bastore
    //   3429: dup
    //   3430: bipush #28
    //   3432: iconst_0
    //   3433: bastore
    //   3434: dup
    //   3435: bipush #29
    //   3437: iconst_0
    //   3438: bastore
    //   3439: dup
    //   3440: bipush #30
    //   3442: iconst_0
    //   3443: bastore
    //   3444: dup
    //   3445: bipush #31
    //   3447: iconst_0
    //   3448: bastore
    //   3449: dup
    //   3450: bipush #32
    //   3452: iconst_0
    //   3453: bastore
    //   3454: dup
    //   3455: bipush #33
    //   3457: iconst_0
    //   3458: bastore
    //   3459: dup
    //   3460: bipush #34
    //   3462: iconst_0
    //   3463: bastore
    //   3464: dup
    //   3465: bipush #35
    //   3467: iconst_0
    //   3468: bastore
    //   3469: dup
    //   3470: bipush #36
    //   3472: iconst_0
    //   3473: bastore
    //   3474: dup
    //   3475: bipush #37
    //   3477: iconst_0
    //   3478: bastore
    //   3479: dup
    //   3480: bipush #38
    //   3482: iconst_0
    //   3483: bastore
    //   3484: dup
    //   3485: bipush #39
    //   3487: iconst_0
    //   3488: bastore
    //   3489: dup
    //   3490: bipush #40
    //   3492: iconst_0
    //   3493: bastore
    //   3494: dup
    //   3495: bipush #41
    //   3497: iconst_0
    //   3498: bastore
    //   3499: dup
    //   3500: bipush #42
    //   3502: iconst_0
    //   3503: bastore
    //   3504: dup
    //   3505: bipush #43
    //   3507: iconst_0
    //   3508: bastore
    //   3509: dup
    //   3510: bipush #44
    //   3512: iconst_0
    //   3513: bastore
    //   3514: dup
    //   3515: bipush #45
    //   3517: iconst_0
    //   3518: bastore
    //   3519: dup
    //   3520: bipush #46
    //   3522: iconst_0
    //   3523: bastore
    //   3524: dup
    //   3525: bipush #47
    //   3527: iconst_0
    //   3528: bastore
    //   3529: dup
    //   3530: bipush #48
    //   3532: iconst_0
    //   3533: bastore
    //   3534: dup
    //   3535: bipush #49
    //   3537: iconst_0
    //   3538: bastore
    //   3539: dup
    //   3540: bipush #50
    //   3542: iconst_0
    //   3543: bastore
    //   3544: dup
    //   3545: bipush #51
    //   3547: iconst_0
    //   3548: bastore
    //   3549: dup
    //   3550: bipush #52
    //   3552: iconst_0
    //   3553: bastore
    //   3554: dup
    //   3555: bipush #53
    //   3557: iconst_0
    //   3558: bastore
    //   3559: dup
    //   3560: bipush #54
    //   3562: iconst_0
    //   3563: bastore
    //   3564: dup
    //   3565: bipush #55
    //   3567: iconst_0
    //   3568: bastore
    //   3569: dup
    //   3570: bipush #56
    //   3572: iconst_0
    //   3573: bastore
    //   3574: dup
    //   3575: bipush #57
    //   3577: iconst_0
    //   3578: bastore
    //   3579: dup
    //   3580: bipush #58
    //   3582: iconst_0
    //   3583: bastore
    //   3584: dup
    //   3585: bipush #59
    //   3587: iconst_0
    //   3588: bastore
    //   3589: dup
    //   3590: bipush #60
    //   3592: iconst_0
    //   3593: bastore
    //   3594: dup
    //   3595: bipush #61
    //   3597: iconst_0
    //   3598: bastore
    //   3599: dup
    //   3600: bipush #62
    //   3602: iconst_0
    //   3603: bastore
    //   3604: dup
    //   3605: bipush #63
    //   3607: iconst_0
    //   3608: bastore
    //   3609: astore #5
    //   3611: bipush #64
    //   3613: newarray int
    //   3615: dup
    //   3616: iconst_0
    //   3617: ldc 1116352408
    //   3619: iastore
    //   3620: dup
    //   3621: iconst_1
    //   3622: ldc 1899447441
    //   3624: iastore
    //   3625: dup
    //   3626: iconst_2
    //   3627: ldc -1245643825
    //   3629: iastore
    //   3630: dup
    //   3631: iconst_3
    //   3632: ldc -373957723
    //   3634: iastore
    //   3635: dup
    //   3636: iconst_4
    //   3637: ldc 961987163
    //   3639: iastore
    //   3640: dup
    //   3641: iconst_5
    //   3642: ldc 1508970993
    //   3644: iastore
    //   3645: dup
    //   3646: bipush #6
    //   3648: ldc -1841331548
    //   3650: iastore
    //   3651: dup
    //   3652: bipush #7
    //   3654: ldc -1424204075
    //   3656: iastore
    //   3657: dup
    //   3658: bipush #8
    //   3660: ldc -670586216
    //   3662: iastore
    //   3663: dup
    //   3664: bipush #9
    //   3666: ldc 310598401
    //   3668: iastore
    //   3669: dup
    //   3670: bipush #10
    //   3672: ldc 607225278
    //   3674: iastore
    //   3675: dup
    //   3676: bipush #11
    //   3678: ldc 1426881987
    //   3680: iastore
    //   3681: dup
    //   3682: bipush #12
    //   3684: ldc 1925078388
    //   3686: iastore
    //   3687: dup
    //   3688: bipush #13
    //   3690: ldc -2132889090
    //   3692: iastore
    //   3693: dup
    //   3694: bipush #14
    //   3696: ldc -1680079193
    //   3698: iastore
    //   3699: dup
    //   3700: bipush #15
    //   3702: ldc -1046744716
    //   3704: iastore
    //   3705: dup
    //   3706: bipush #16
    //   3708: ldc -459576895
    //   3710: iastore
    //   3711: dup
    //   3712: bipush #17
    //   3714: ldc -272742522
    //   3716: iastore
    //   3717: dup
    //   3718: bipush #18
    //   3720: ldc 264347078
    //   3722: iastore
    //   3723: dup
    //   3724: bipush #19
    //   3726: ldc 604807628
    //   3728: iastore
    //   3729: dup
    //   3730: bipush #20
    //   3732: ldc 770255983
    //   3734: iastore
    //   3735: dup
    //   3736: bipush #21
    //   3738: ldc 1249150122
    //   3740: iastore
    //   3741: dup
    //   3742: bipush #22
    //   3744: ldc 1555081692
    //   3746: iastore
    //   3747: dup
    //   3748: bipush #23
    //   3750: ldc 1996064986
    //   3752: iastore
    //   3753: dup
    //   3754: bipush #24
    //   3756: ldc -1740746414
    //   3758: iastore
    //   3759: dup
    //   3760: bipush #25
    //   3762: ldc -1473132947
    //   3764: iastore
    //   3765: dup
    //   3766: bipush #26
    //   3768: ldc -1341970488
    //   3770: iastore
    //   3771: dup
    //   3772: bipush #27
    //   3774: ldc -1084653625
    //   3776: iastore
    //   3777: dup
    //   3778: bipush #28
    //   3780: ldc -958395405
    //   3782: iastore
    //   3783: dup
    //   3784: bipush #29
    //   3786: ldc -710438585
    //   3788: iastore
    //   3789: dup
    //   3790: bipush #30
    //   3792: ldc 113926993
    //   3794: iastore
    //   3795: dup
    //   3796: bipush #31
    //   3798: ldc 338241895
    //   3800: iastore
    //   3801: dup
    //   3802: bipush #32
    //   3804: ldc 666307205
    //   3806: iastore
    //   3807: dup
    //   3808: bipush #33
    //   3810: ldc 773529912
    //   3812: iastore
    //   3813: dup
    //   3814: bipush #34
    //   3816: ldc 1294757372
    //   3818: iastore
    //   3819: dup
    //   3820: bipush #35
    //   3822: ldc 1396182291
    //   3824: iastore
    //   3825: dup
    //   3826: bipush #36
    //   3828: ldc 1695183700
    //   3830: iastore
    //   3831: dup
    //   3832: bipush #37
    //   3834: ldc 1986661051
    //   3836: iastore
    //   3837: dup
    //   3838: bipush #38
    //   3840: ldc -2117940946
    //   3842: iastore
    //   3843: dup
    //   3844: bipush #39
    //   3846: ldc -1838011259
    //   3848: iastore
    //   3849: dup
    //   3850: bipush #40
    //   3852: ldc -1564481375
    //   3854: iastore
    //   3855: dup
    //   3856: bipush #41
    //   3858: ldc -1474664885
    //   3860: iastore
    //   3861: dup
    //   3862: bipush #42
    //   3864: ldc -1035236496
    //   3866: iastore
    //   3867: dup
    //   3868: bipush #43
    //   3870: ldc -949202525
    //   3872: iastore
    //   3873: dup
    //   3874: bipush #44
    //   3876: ldc -778901479
    //   3878: iastore
    //   3879: dup
    //   3880: bipush #45
    //   3882: ldc -694614492
    //   3884: iastore
    //   3885: dup
    //   3886: bipush #46
    //   3888: ldc -200395387
    //   3890: iastore
    //   3891: dup
    //   3892: bipush #47
    //   3894: ldc 275423344
    //   3896: iastore
    //   3897: dup
    //   3898: bipush #48
    //   3900: ldc 430227734
    //   3902: iastore
    //   3903: dup
    //   3904: bipush #49
    //   3906: ldc 506948616
    //   3908: iastore
    //   3909: dup
    //   3910: bipush #50
    //   3912: ldc 659060556
    //   3914: iastore
    //   3915: dup
    //   3916: bipush #51
    //   3918: ldc 883997877
    //   3920: iastore
    //   3921: dup
    //   3922: bipush #52
    //   3924: ldc 958139571
    //   3926: iastore
    //   3927: dup
    //   3928: bipush #53
    //   3930: ldc 1322822218
    //   3932: iastore
    //   3933: dup
    //   3934: bipush #54
    //   3936: ldc 1537002063
    //   3938: iastore
    //   3939: dup
    //   3940: bipush #55
    //   3942: ldc 1747873779
    //   3944: iastore
    //   3945: dup
    //   3946: bipush #56
    //   3948: ldc 1955562222
    //   3950: iastore
    //   3951: dup
    //   3952: bipush #57
    //   3954: ldc 2024104815
    //   3956: iastore
    //   3957: dup
    //   3958: bipush #58
    //   3960: ldc -2067236844
    //   3962: iastore
    //   3963: dup
    //   3964: bipush #59
    //   3966: ldc -1933114872
    //   3968: iastore
    //   3969: dup
    //   3970: bipush #60
    //   3972: ldc -1866530822
    //   3974: iastore
    //   3975: dup
    //   3976: bipush #61
    //   3978: ldc -1538233109
    //   3980: iastore
    //   3981: dup
    //   3982: bipush #62
    //   3984: ldc -1090935817
    //   3986: iastore
    //   3987: dup
    //   3988: bipush #63
    //   3990: ldc -965641998
    //   3992: iastore
    //   3993: astore #6
    //   3995: iconst_2
    //   3996: newarray int
    //   3998: dup
    //   3999: iconst_0
    //   4000: iconst_0
    //   4001: iastore
    //   4002: dup
    //   4003: iconst_1
    //   4004: iconst_0
    //   4005: iastore
    //   4006: astore #7
    //   4008: bipush #8
    //   4010: newarray int
    //   4012: dup
    //   4013: iconst_0
    //   4014: ldc 1779033703
    //   4016: iastore
    //   4017: dup
    //   4018: iconst_1
    //   4019: ldc -1150833019
    //   4021: iastore
    //   4022: dup
    //   4023: iconst_2
    //   4024: ldc 1013904242
    //   4026: iastore
    //   4027: dup
    //   4028: iconst_3
    //   4029: ldc -1521486534
    //   4031: iastore
    //   4032: dup
    //   4033: iconst_4
    //   4034: ldc 1359893119
    //   4036: iastore
    //   4037: dup
    //   4038: iconst_5
    //   4039: ldc -1694144372
    //   4041: iastore
    //   4042: dup
    //   4043: bipush #6
    //   4045: ldc 528734635
    //   4047: iastore
    //   4048: dup
    //   4049: bipush #7
    //   4051: ldc 1541459225
    //   4053: iastore
    //   4054: astore #8
    //   4056: bipush #64
    //   4058: newarray byte
    //   4060: astore #9
    //   4062: bipush #64
    //   4064: newarray byte
    //   4066: astore #10
    //   4068: aload_3
    //   4069: arraylength
    //   4070: istore #11
    //   4072: aload #7
    //   4074: iconst_0
    //   4075: iaload
    //   4076: bipush #63
    //   4078: iand
    //   4079: istore #12
    //   4081: aload #7
    //   4083: iconst_0
    //   4084: dup2
    //   4085: iaload
    //   4086: iload #11
    //   4088: iadd
    //   4089: iastore
    //   4090: aload #7
    //   4092: iconst_0
    //   4093: dup2
    //   4094: iaload
    //   4095: iconst_m1
    //   4096: iand
    //   4097: iastore
    //   4098: aload #7
    //   4100: iconst_0
    //   4101: iaload
    //   4102: iload #11
    //   4104: if_icmpge -> 4122
    //   4107: aload #7
    //   4109: iconst_1
    //   4110: dup2
    //   4111: iaload
    //   4112: iconst_1
    //   4113: iadd
    //   4114: iastore
    //   4115: goto -> 4122
    //   4118: invokestatic a : (Ljava/lang/Throwable;)Ljava/lang/Throwable;
    //   4121: athrow
    //   4122: iconst_0
    //   4123: istore #13
    //   4125: iload #11
    //   4127: bipush #64
    //   4129: if_icmplt -> 4738
    //   4132: iconst_0
    //   4133: istore #14
    //   4135: iload #14
    //   4137: bipush #64
    //   4139: if_icmpge -> 4161
    //   4142: aload #10
    //   4144: iload #14
    //   4146: aload_3
    //   4147: iload #13
    //   4149: iload #14
    //   4151: iadd
    //   4152: baload
    //   4153: bastore
    //   4154: iinc #14, 1
    //   4157: iload_2
    //   4158: ifeq -> 4135
    //   4161: bipush #64
    //   4163: newarray int
    //   4165: astore #14
    //   4167: bipush #8
    //   4169: newarray int
    //   4171: astore #15
    //   4173: iconst_0
    //   4174: istore #16
    //   4176: iload #16
    //   4178: bipush #8
    //   4180: if_icmpge -> 4200
    //   4183: aload #15
    //   4185: iload #16
    //   4187: aload #8
    //   4189: iload #16
    //   4191: iaload
    //   4192: iastore
    //   4193: iinc #16, 1
    //   4196: iload_2
    //   4197: ifeq -> 4176
    //   4200: iconst_0
    //   4201: istore #16
    //   4203: iload #16
    //   4205: bipush #64
    //   4207: if_icmpge -> 4698
    //   4210: iload #16
    //   4212: bipush #16
    //   4214: if_icmpge -> 4295
    //   4217: aload #14
    //   4219: iload #16
    //   4221: aload #10
    //   4223: iconst_4
    //   4224: iload #16
    //   4226: imul
    //   4227: baload
    //   4228: sipush #255
    //   4231: iand
    //   4232: bipush #24
    //   4234: ishl
    //   4235: aload #10
    //   4237: iconst_4
    //   4238: iload #16
    //   4240: imul
    //   4241: iconst_1
    //   4242: iadd
    //   4243: baload
    //   4244: sipush #255
    //   4247: iand
    //   4248: bipush #16
    //   4250: ishl
    //   4251: ior
    //   4252: aload #10
    //   4254: iconst_4
    //   4255: iload #16
    //   4257: imul
    //   4258: iconst_2
    //   4259: iadd
    //   4260: baload
    //   4261: sipush #255
    //   4264: iand
    //   4265: bipush #8
    //   4267: ishl
    //   4268: ior
    //   4269: aload #10
    //   4271: iconst_4
    //   4272: iload #16
    //   4274: imul
    //   4275: iconst_3
    //   4276: iadd
    //   4277: baload
    //   4278: sipush #255
    //   4281: iand
    //   4282: ior
    //   4283: iastore
    //   4284: iload_2
    //   4285: ifeq -> 4438
    //   4288: goto -> 4295
    //   4291: invokestatic a : (Ljava/lang/Throwable;)Ljava/lang/Throwable;
    //   4294: athrow
    //   4295: aload #14
    //   4297: iload #16
    //   4299: aload #14
    //   4301: iload #16
    //   4303: iconst_2
    //   4304: isub
    //   4305: iaload
    //   4306: bipush #17
    //   4308: iushr
    //   4309: aload #14
    //   4311: iload #16
    //   4313: iconst_2
    //   4314: isub
    //   4315: iaload
    //   4316: bipush #15
    //   4318: ishl
    //   4319: ior
    //   4320: aload #14
    //   4322: iload #16
    //   4324: iconst_2
    //   4325: isub
    //   4326: iaload
    //   4327: bipush #19
    //   4329: iushr
    //   4330: aload #14
    //   4332: iload #16
    //   4334: iconst_2
    //   4335: isub
    //   4336: iaload
    //   4337: bipush #13
    //   4339: ishl
    //   4340: ior
    //   4341: ixor
    //   4342: aload #14
    //   4344: iload #16
    //   4346: iconst_2
    //   4347: isub
    //   4348: iaload
    //   4349: bipush #10
    //   4351: iushr
    //   4352: ixor
    //   4353: aload #14
    //   4355: iload #16
    //   4357: bipush #7
    //   4359: isub
    //   4360: iaload
    //   4361: iadd
    //   4362: aload #14
    //   4364: iload #16
    //   4366: bipush #15
    //   4368: isub
    //   4369: iaload
    //   4370: bipush #7
    //   4372: iushr
    //   4373: aload #14
    //   4375: iload #16
    //   4377: bipush #15
    //   4379: isub
    //   4380: iaload
    //   4381: bipush #25
    //   4383: ishl
    //   4384: ior
    //   4385: aload #14
    //   4387: iload #16
    //   4389: bipush #15
    //   4391: isub
    //   4392: iaload
    //   4393: bipush #18
    //   4395: iushr
    //   4396: aload #14
    //   4398: iload #16
    //   4400: bipush #15
    //   4402: isub
    //   4403: iaload
    //   4404: bipush #14
    //   4406: ishl
    //   4407: ior
    //   4408: ixor
    //   4409: aload #14
    //   4411: iload #16
    //   4413: bipush #15
    //   4415: isub
    //   4416: iaload
    //   4417: iconst_3
    //   4418: iushr
    //   4419: ixor
    //   4420: iadd
    //   4421: aload #14
    //   4423: iload #16
    //   4425: bipush #16
    //   4427: isub
    //   4428: iaload
    //   4429: iadd
    //   4430: iastore
    //   4431: goto -> 4438
    //   4434: invokestatic a : (Ljava/lang/Throwable;)Ljava/lang/Throwable;
    //   4437: athrow
    //   4438: aload #15
    //   4440: bipush #7
    //   4442: iaload
    //   4443: aload #15
    //   4445: iconst_4
    //   4446: iaload
    //   4447: bipush #6
    //   4449: iushr
    //   4450: aload #15
    //   4452: iconst_4
    //   4453: iaload
    //   4454: bipush #26
    //   4456: ishl
    //   4457: ior
    //   4458: aload #15
    //   4460: iconst_4
    //   4461: iaload
    //   4462: bipush #11
    //   4464: iushr
    //   4465: aload #15
    //   4467: iconst_4
    //   4468: iaload
    //   4469: bipush #21
    //   4471: ishl
    //   4472: ior
    //   4473: ixor
    //   4474: aload #15
    //   4476: iconst_4
    //   4477: iaload
    //   4478: bipush #25
    //   4480: iushr
    //   4481: aload #15
    //   4483: iconst_4
    //   4484: iaload
    //   4485: bipush #7
    //   4487: ishl
    //   4488: ior
    //   4489: ixor
    //   4490: iadd
    //   4491: aload #15
    //   4493: bipush #6
    //   4495: iaload
    //   4496: aload #15
    //   4498: iconst_4
    //   4499: iaload
    //   4500: aload #15
    //   4502: iconst_5
    //   4503: iaload
    //   4504: aload #15
    //   4506: bipush #6
    //   4508: iaload
    //   4509: ixor
    //   4510: iand
    //   4511: ixor
    //   4512: iadd
    //   4513: aload #6
    //   4515: iload #16
    //   4517: iaload
    //   4518: iadd
    //   4519: aload #14
    //   4521: iload #16
    //   4523: iaload
    //   4524: iadd
    //   4525: istore #17
    //   4527: aload #15
    //   4529: iconst_0
    //   4530: iaload
    //   4531: iconst_2
    //   4532: iushr
    //   4533: aload #15
    //   4535: iconst_0
    //   4536: iaload
    //   4537: bipush #30
    //   4539: ishl
    //   4540: ior
    //   4541: aload #15
    //   4543: iconst_0
    //   4544: iaload
    //   4545: bipush #13
    //   4547: iushr
    //   4548: aload #15
    //   4550: iconst_0
    //   4551: iaload
    //   4552: bipush #19
    //   4554: ishl
    //   4555: ior
    //   4556: ixor
    //   4557: aload #15
    //   4559: iconst_0
    //   4560: iaload
    //   4561: bipush #22
    //   4563: iushr
    //   4564: aload #15
    //   4566: iconst_0
    //   4567: iaload
    //   4568: bipush #10
    //   4570: ishl
    //   4571: ior
    //   4572: ixor
    //   4573: aload #15
    //   4575: iconst_0
    //   4576: iaload
    //   4577: aload #15
    //   4579: iconst_1
    //   4580: iaload
    //   4581: iand
    //   4582: aload #15
    //   4584: iconst_2
    //   4585: iaload
    //   4586: aload #15
    //   4588: iconst_0
    //   4589: iaload
    //   4590: aload #15
    //   4592: iconst_1
    //   4593: iaload
    //   4594: ior
    //   4595: iand
    //   4596: ior
    //   4597: iadd
    //   4598: istore #18
    //   4600: aload #15
    //   4602: iconst_3
    //   4603: dup2
    //   4604: iaload
    //   4605: iload #17
    //   4607: iadd
    //   4608: iastore
    //   4609: aload #15
    //   4611: bipush #7
    //   4613: iload #17
    //   4615: iload #18
    //   4617: iadd
    //   4618: iastore
    //   4619: aload #15
    //   4621: bipush #7
    //   4623: iaload
    //   4624: istore #17
    //   4626: aload #15
    //   4628: bipush #7
    //   4630: aload #15
    //   4632: bipush #6
    //   4634: iaload
    //   4635: iastore
    //   4636: aload #15
    //   4638: bipush #6
    //   4640: aload #15
    //   4642: iconst_5
    //   4643: iaload
    //   4644: iastore
    //   4645: aload #15
    //   4647: iconst_5
    //   4648: aload #15
    //   4650: iconst_4
    //   4651: iaload
    //   4652: iastore
    //   4653: aload #15
    //   4655: iconst_4
    //   4656: aload #15
    //   4658: iconst_3
    //   4659: iaload
    //   4660: iastore
    //   4661: aload #15
    //   4663: iconst_3
    //   4664: aload #15
    //   4666: iconst_2
    //   4667: iaload
    //   4668: iastore
    //   4669: aload #15
    //   4671: iconst_2
    //   4672: aload #15
    //   4674: iconst_1
    //   4675: iaload
    //   4676: iastore
    //   4677: aload #15
    //   4679: iconst_1
    //   4680: aload #15
    //   4682: iconst_0
    //   4683: iaload
    //   4684: iastore
    //   4685: aload #15
    //   4687: iconst_0
    //   4688: iload #17
    //   4690: iastore
    //   4691: iinc #16, 1
    //   4694: iload_2
    //   4695: ifeq -> 4203
    //   4698: iconst_0
    //   4699: istore #16
    //   4701: iload #16
    //   4703: bipush #8
    //   4705: if_icmpge -> 4728
    //   4708: aload #8
    //   4710: iload #16
    //   4712: dup2
    //   4713: iaload
    //   4714: aload #15
    //   4716: iload #16
    //   4718: iaload
    //   4719: iadd
    //   4720: iastore
    //   4721: iinc #16, 1
    //   4724: iload_2
    //   4725: ifeq -> 4701
    //   4728: iinc #13, 64
    //   4731: iinc #11, -64
    //   4734: iload_2
    //   4735: ifeq -> 4125
    //   4738: iload #11
    //   4740: ifle -> 4775
    //   4743: iconst_0
    //   4744: istore #14
    //   4746: iload #14
    //   4748: iload #11
    //   4750: if_icmpge -> 4775
    //   4753: aload #9
    //   4755: iload #12
    //   4757: iload #14
    //   4759: iadd
    //   4760: aload_3
    //   4761: iload #13
    //   4763: iload #14
    //   4765: iadd
    //   4766: baload
    //   4767: bastore
    //   4768: iinc #14, 1
    //   4771: iload_2
    //   4772: ifeq -> 4746
    //   4775: aload #7
    //   4777: iconst_0
    //   4778: iaload
    //   4779: bipush #29
    //   4781: iushr
    //   4782: aload #7
    //   4784: iconst_1
    //   4785: iaload
    //   4786: iconst_3
    //   4787: ishl
    //   4788: ior
    //   4789: istore #14
    //   4791: aload #7
    //   4793: iconst_0
    //   4794: iaload
    //   4795: iconst_3
    //   4796: ishl
    //   4797: istore #15
    //   4799: aload #7
    //   4801: iconst_0
    //   4802: iaload
    //   4803: bipush #63
    //   4805: iand
    //   4806: istore #16
    //   4808: iload #16
    //   4810: bipush #56
    //   4812: if_icmpge -> 4827
    //   4815: bipush #56
    //   4817: iload #16
    //   4819: isub
    //   4820: goto -> 4832
    //   4823: invokestatic a : (Ljava/lang/Throwable;)Ljava/lang/Throwable;
    //   4826: athrow
    //   4827: bipush #120
    //   4829: iload #16
    //   4831: isub
    //   4832: istore #17
    //   4834: aload #7
    //   4836: iconst_0
    //   4837: iaload
    //   4838: bipush #63
    //   4840: iand
    //   4841: istore #12
    //   4843: bipush #64
    //   4845: iload #12
    //   4847: isub
    //   4848: istore #18
    //   4850: aload #7
    //   4852: iconst_0
    //   4853: dup2
    //   4854: iaload
    //   4855: iload #17
    //   4857: iadd
    //   4858: iastore
    //   4859: aload #7
    //   4861: iconst_0
    //   4862: dup2
    //   4863: iaload
    //   4864: iconst_m1
    //   4865: iand
    //   4866: iastore
    //   4867: aload #7
    //   4869: iconst_0
    //   4870: iaload
    //   4871: iload #17
    //   4873: if_icmpge -> 4891
    //   4876: aload #7
    //   4878: iconst_1
    //   4879: dup2
    //   4880: iaload
    //   4881: iconst_1
    //   4882: iadd
    //   4883: iastore
    //   4884: goto -> 4891
    //   4887: invokestatic a : (Ljava/lang/Throwable;)Ljava/lang/Throwable;
    //   4890: athrow
    //   4891: iconst_0
    //   4892: istore #13
    //   4894: iload #12
    //   4896: ifle -> 5527
    //   4899: iload #17
    //   4901: iload #18
    //   4903: if_icmplt -> 5527
    //   4906: goto -> 4913
    //   4909: invokestatic a : (Ljava/lang/Throwable;)Ljava/lang/Throwable;
    //   4912: athrow
    //   4913: iconst_0
    //   4914: istore #19
    //   4916: iload #19
    //   4918: iload #18
    //   4920: if_icmpge -> 4943
    //   4923: aload #9
    //   4925: iload #12
    //   4927: iload #19
    //   4929: iadd
    //   4930: aload #5
    //   4932: iload #19
    //   4934: baload
    //   4935: bastore
    //   4936: iinc #19, 1
    //   4939: iload_2
    //   4940: ifeq -> 4916
    //   4943: bipush #64
    //   4945: newarray int
    //   4947: astore #19
    //   4949: bipush #8
    //   4951: newarray int
    //   4953: astore #20
    //   4955: iconst_0
    //   4956: istore #21
    //   4958: iload #21
    //   4960: bipush #8
    //   4962: if_icmpge -> 4982
    //   4965: aload #20
    //   4967: iload #21
    //   4969: aload #8
    //   4971: iload #21
    //   4973: iaload
    //   4974: iastore
    //   4975: iinc #21, 1
    //   4978: iload_2
    //   4979: ifeq -> 4958
    //   4982: iconst_0
    //   4983: istore #21
    //   4985: iload #21
    //   4987: bipush #64
    //   4989: if_icmpge -> 5480
    //   4992: iload #21
    //   4994: bipush #16
    //   4996: if_icmpge -> 5077
    //   4999: aload #19
    //   5001: iload #21
    //   5003: aload #9
    //   5005: iconst_4
    //   5006: iload #21
    //   5008: imul
    //   5009: baload
    //   5010: sipush #255
    //   5013: iand
    //   5014: bipush #24
    //   5016: ishl
    //   5017: aload #9
    //   5019: iconst_4
    //   5020: iload #21
    //   5022: imul
    //   5023: iconst_1
    //   5024: iadd
    //   5025: baload
    //   5026: sipush #255
    //   5029: iand
    //   5030: bipush #16
    //   5032: ishl
    //   5033: ior
    //   5034: aload #9
    //   5036: iconst_4
    //   5037: iload #21
    //   5039: imul
    //   5040: iconst_2
    //   5041: iadd
    //   5042: baload
    //   5043: sipush #255
    //   5046: iand
    //   5047: bipush #8
    //   5049: ishl
    //   5050: ior
    //   5051: aload #9
    //   5053: iconst_4
    //   5054: iload #21
    //   5056: imul
    //   5057: iconst_3
    //   5058: iadd
    //   5059: baload
    //   5060: sipush #255
    //   5063: iand
    //   5064: ior
    //   5065: iastore
    //   5066: iload_2
    //   5067: ifeq -> 5220
    //   5070: goto -> 5077
    //   5073: invokestatic a : (Ljava/lang/Throwable;)Ljava/lang/Throwable;
    //   5076: athrow
    //   5077: aload #19
    //   5079: iload #21
    //   5081: aload #19
    //   5083: iload #21
    //   5085: iconst_2
    //   5086: isub
    //   5087: iaload
    //   5088: bipush #17
    //   5090: iushr
    //   5091: aload #19
    //   5093: iload #21
    //   5095: iconst_2
    //   5096: isub
    //   5097: iaload
    //   5098: bipush #15
    //   5100: ishl
    //   5101: ior
    //   5102: aload #19
    //   5104: iload #21
    //   5106: iconst_2
    //   5107: isub
    //   5108: iaload
    //   5109: bipush #19
    //   5111: iushr
    //   5112: aload #19
    //   5114: iload #21
    //   5116: iconst_2
    //   5117: isub
    //   5118: iaload
    //   5119: bipush #13
    //   5121: ishl
    //   5122: ior
    //   5123: ixor
    //   5124: aload #19
    //   5126: iload #21
    //   5128: iconst_2
    //   5129: isub
    //   5130: iaload
    //   5131: bipush #10
    //   5133: iushr
    //   5134: ixor
    //   5135: aload #19
    //   5137: iload #21
    //   5139: bipush #7
    //   5141: isub
    //   5142: iaload
    //   5143: iadd
    //   5144: aload #19
    //   5146: iload #21
    //   5148: bipush #15
    //   5150: isub
    //   5151: iaload
    //   5152: bipush #7
    //   5154: iushr
    //   5155: aload #19
    //   5157: iload #21
    //   5159: bipush #15
    //   5161: isub
    //   5162: iaload
    //   5163: bipush #25
    //   5165: ishl
    //   5166: ior
    //   5167: aload #19
    //   5169: iload #21
    //   5171: bipush #15
    //   5173: isub
    //   5174: iaload
    //   5175: bipush #18
    //   5177: iushr
    //   5178: aload #19
    //   5180: iload #21
    //   5182: bipush #15
    //   5184: isub
    //   5185: iaload
    //   5186: bipush #14
    //   5188: ishl
    //   5189: ior
    //   5190: ixor
    //   5191: aload #19
    //   5193: iload #21
    //   5195: bipush #15
    //   5197: isub
    //   5198: iaload
    //   5199: iconst_3
    //   5200: iushr
    //   5201: ixor
    //   5202: iadd
    //   5203: aload #19
    //   5205: iload #21
    //   5207: bipush #16
    //   5209: isub
    //   5210: iaload
    //   5211: iadd
    //   5212: iastore
    //   5213: goto -> 5220
    //   5216: invokestatic a : (Ljava/lang/Throwable;)Ljava/lang/Throwable;
    //   5219: athrow
    //   5220: aload #20
    //   5222: bipush #7
    //   5224: iaload
    //   5225: aload #20
    //   5227: iconst_4
    //   5228: iaload
    //   5229: bipush #6
    //   5231: iushr
    //   5232: aload #20
    //   5234: iconst_4
    //   5235: iaload
    //   5236: bipush #26
    //   5238: ishl
    //   5239: ior
    //   5240: aload #20
    //   5242: iconst_4
    //   5243: iaload
    //   5244: bipush #11
    //   5246: iushr
    //   5247: aload #20
    //   5249: iconst_4
    //   5250: iaload
    //   5251: bipush #21
    //   5253: ishl
    //   5254: ior
    //   5255: ixor
    //   5256: aload #20
    //   5258: iconst_4
    //   5259: iaload
    //   5260: bipush #25
    //   5262: iushr
    //   5263: aload #20
    //   5265: iconst_4
    //   5266: iaload
    //   5267: bipush #7
    //   5269: ishl
    //   5270: ior
    //   5271: ixor
    //   5272: iadd
    //   5273: aload #20
    //   5275: bipush #6
    //   5277: iaload
    //   5278: aload #20
    //   5280: iconst_4
    //   5281: iaload
    //   5282: aload #20
    //   5284: iconst_5
    //   5285: iaload
    //   5286: aload #20
    //   5288: bipush #6
    //   5290: iaload
    //   5291: ixor
    //   5292: iand
    //   5293: ixor
    //   5294: iadd
    //   5295: aload #6
    //   5297: iload #21
    //   5299: iaload
    //   5300: iadd
    //   5301: aload #19
    //   5303: iload #21
    //   5305: iaload
    //   5306: iadd
    //   5307: istore #22
    //   5309: aload #20
    //   5311: iconst_0
    //   5312: iaload
    //   5313: iconst_2
    //   5314: iushr
    //   5315: aload #20
    //   5317: iconst_0
    //   5318: iaload
    //   5319: bipush #30
    //   5321: ishl
    //   5322: ior
    //   5323: aload #20
    //   5325: iconst_0
    //   5326: iaload
    //   5327: bipush #13
    //   5329: iushr
    //   5330: aload #20
    //   5332: iconst_0
    //   5333: iaload
    //   5334: bipush #19
    //   5336: ishl
    //   5337: ior
    //   5338: ixor
    //   5339: aload #20
    //   5341: iconst_0
    //   5342: iaload
    //   5343: bipush #22
    //   5345: iushr
    //   5346: aload #20
    //   5348: iconst_0
    //   5349: iaload
    //   5350: bipush #10
    //   5352: ishl
    //   5353: ior
    //   5354: ixor
    //   5355: aload #20
    //   5357: iconst_0
    //   5358: iaload
    //   5359: aload #20
    //   5361: iconst_1
    //   5362: iaload
    //   5363: iand
    //   5364: aload #20
    //   5366: iconst_2
    //   5367: iaload
    //   5368: aload #20
    //   5370: iconst_0
    //   5371: iaload
    //   5372: aload #20
    //   5374: iconst_1
    //   5375: iaload
    //   5376: ior
    //   5377: iand
    //   5378: ior
    //   5379: iadd
    //   5380: istore #23
    //   5382: aload #20
    //   5384: iconst_3
    //   5385: dup2
    //   5386: iaload
    //   5387: iload #22
    //   5389: iadd
    //   5390: iastore
    //   5391: aload #20
    //   5393: bipush #7
    //   5395: iload #22
    //   5397: iload #23
    //   5399: iadd
    //   5400: iastore
    //   5401: aload #20
    //   5403: bipush #7
    //   5405: iaload
    //   5406: istore #22
    //   5408: aload #20
    //   5410: bipush #7
    //   5412: aload #20
    //   5414: bipush #6
    //   5416: iaload
    //   5417: iastore
    //   5418: aload #20
    //   5420: bipush #6
    //   5422: aload #20
    //   5424: iconst_5
    //   5425: iaload
    //   5426: iastore
    //   5427: aload #20
    //   5429: iconst_5
    //   5430: aload #20
    //   5432: iconst_4
    //   5433: iaload
    //   5434: iastore
    //   5435: aload #20
    //   5437: iconst_4
    //   5438: aload #20
    //   5440: iconst_3
    //   5441: iaload
    //   5442: iastore
    //   5443: aload #20
    //   5445: iconst_3
    //   5446: aload #20
    //   5448: iconst_2
    //   5449: iaload
    //   5450: iastore
    //   5451: aload #20
    //   5453: iconst_2
    //   5454: aload #20
    //   5456: iconst_1
    //   5457: iaload
    //   5458: iastore
    //   5459: aload #20
    //   5461: iconst_1
    //   5462: aload #20
    //   5464: iconst_0
    //   5465: iaload
    //   5466: iastore
    //   5467: aload #20
    //   5469: iconst_0
    //   5470: iload #22
    //   5472: iastore
    //   5473: iinc #21, 1
    //   5476: iload_2
    //   5477: ifeq -> 4985
    //   5480: iconst_0
    //   5481: istore #21
    //   5483: iload #21
    //   5485: bipush #8
    //   5487: if_icmpge -> 5510
    //   5490: aload #8
    //   5492: iload #21
    //   5494: dup2
    //   5495: iaload
    //   5496: aload #20
    //   5498: iload #21
    //   5500: iaload
    //   5501: iadd
    //   5502: iastore
    //   5503: iinc #21, 1
    //   5506: iload_2
    //   5507: ifeq -> 5483
    //   5510: iload #13
    //   5512: iload #18
    //   5514: iadd
    //   5515: istore #13
    //   5517: iload #17
    //   5519: iload #18
    //   5521: isub
    //   5522: istore #17
    //   5524: iconst_0
    //   5525: istore #12
    //   5527: iload #17
    //   5529: bipush #64
    //   5531: if_icmplt -> 6141
    //   5534: iconst_0
    //   5535: istore #19
    //   5537: iload #19
    //   5539: bipush #64
    //   5541: if_icmpge -> 5564
    //   5544: aload #10
    //   5546: iload #19
    //   5548: aload #5
    //   5550: iload #13
    //   5552: iload #19
    //   5554: iadd
    //   5555: baload
    //   5556: bastore
    //   5557: iinc #19, 1
    //   5560: iload_2
    //   5561: ifeq -> 5537
    //   5564: bipush #64
    //   5566: newarray int
    //   5568: astore #19
    //   5570: bipush #8
    //   5572: newarray int
    //   5574: astore #20
    //   5576: iconst_0
    //   5577: istore #21
    //   5579: iload #21
    //   5581: bipush #8
    //   5583: if_icmpge -> 5603
    //   5586: aload #20
    //   5588: iload #21
    //   5590: aload #8
    //   5592: iload #21
    //   5594: iaload
    //   5595: iastore
    //   5596: iinc #21, 1
    //   5599: iload_2
    //   5600: ifeq -> 5579
    //   5603: iconst_0
    //   5604: istore #21
    //   5606: iload #21
    //   5608: bipush #64
    //   5610: if_icmpge -> 6101
    //   5613: iload #21
    //   5615: bipush #16
    //   5617: if_icmpge -> 5698
    //   5620: aload #19
    //   5622: iload #21
    //   5624: aload #10
    //   5626: iconst_4
    //   5627: iload #21
    //   5629: imul
    //   5630: baload
    //   5631: sipush #255
    //   5634: iand
    //   5635: bipush #24
    //   5637: ishl
    //   5638: aload #10
    //   5640: iconst_4
    //   5641: iload #21
    //   5643: imul
    //   5644: iconst_1
    //   5645: iadd
    //   5646: baload
    //   5647: sipush #255
    //   5650: iand
    //   5651: bipush #16
    //   5653: ishl
    //   5654: ior
    //   5655: aload #10
    //   5657: iconst_4
    //   5658: iload #21
    //   5660: imul
    //   5661: iconst_2
    //   5662: iadd
    //   5663: baload
    //   5664: sipush #255
    //   5667: iand
    //   5668: bipush #8
    //   5670: ishl
    //   5671: ior
    //   5672: aload #10
    //   5674: iconst_4
    //   5675: iload #21
    //   5677: imul
    //   5678: iconst_3
    //   5679: iadd
    //   5680: baload
    //   5681: sipush #255
    //   5684: iand
    //   5685: ior
    //   5686: iastore
    //   5687: iload_2
    //   5688: ifeq -> 5841
    //   5691: goto -> 5698
    //   5694: invokestatic a : (Ljava/lang/Throwable;)Ljava/lang/Throwable;
    //   5697: athrow
    //   5698: aload #19
    //   5700: iload #21
    //   5702: aload #19
    //   5704: iload #21
    //   5706: iconst_2
    //   5707: isub
    //   5708: iaload
    //   5709: bipush #17
    //   5711: iushr
    //   5712: aload #19
    //   5714: iload #21
    //   5716: iconst_2
    //   5717: isub
    //   5718: iaload
    //   5719: bipush #15
    //   5721: ishl
    //   5722: ior
    //   5723: aload #19
    //   5725: iload #21
    //   5727: iconst_2
    //   5728: isub
    //   5729: iaload
    //   5730: bipush #19
    //   5732: iushr
    //   5733: aload #19
    //   5735: iload #21
    //   5737: iconst_2
    //   5738: isub
    //   5739: iaload
    //   5740: bipush #13
    //   5742: ishl
    //   5743: ior
    //   5744: ixor
    //   5745: aload #19
    //   5747: iload #21
    //   5749: iconst_2
    //   5750: isub
    //   5751: iaload
    //   5752: bipush #10
    //   5754: iushr
    //   5755: ixor
    //   5756: aload #19
    //   5758: iload #21
    //   5760: bipush #7
    //   5762: isub
    //   5763: iaload
    //   5764: iadd
    //   5765: aload #19
    //   5767: iload #21
    //   5769: bipush #15
    //   5771: isub
    //   5772: iaload
    //   5773: bipush #7
    //   5775: iushr
    //   5776: aload #19
    //   5778: iload #21
    //   5780: bipush #15
    //   5782: isub
    //   5783: iaload
    //   5784: bipush #25
    //   5786: ishl
    //   5787: ior
    //   5788: aload #19
    //   5790: iload #21
    //   5792: bipush #15
    //   5794: isub
    //   5795: iaload
    //   5796: bipush #18
    //   5798: iushr
    //   5799: aload #19
    //   5801: iload #21
    //   5803: bipush #15
    //   5805: isub
    //   5806: iaload
    //   5807: bipush #14
    //   5809: ishl
    //   5810: ior
    //   5811: ixor
    //   5812: aload #19
    //   5814: iload #21
    //   5816: bipush #15
    //   5818: isub
    //   5819: iaload
    //   5820: iconst_3
    //   5821: iushr
    //   5822: ixor
    //   5823: iadd
    //   5824: aload #19
    //   5826: iload #21
    //   5828: bipush #16
    //   5830: isub
    //   5831: iaload
    //   5832: iadd
    //   5833: iastore
    //   5834: goto -> 5841
    //   5837: invokestatic a : (Ljava/lang/Throwable;)Ljava/lang/Throwable;
    //   5840: athrow
    //   5841: aload #20
    //   5843: bipush #7
    //   5845: iaload
    //   5846: aload #20
    //   5848: iconst_4
    //   5849: iaload
    //   5850: bipush #6
    //   5852: iushr
    //   5853: aload #20
    //   5855: iconst_4
    //   5856: iaload
    //   5857: bipush #26
    //   5859: ishl
    //   5860: ior
    //   5861: aload #20
    //   5863: iconst_4
    //   5864: iaload
    //   5865: bipush #11
    //   5867: iushr
    //   5868: aload #20
    //   5870: iconst_4
    //   5871: iaload
    //   5872: bipush #21
    //   5874: ishl
    //   5875: ior
    //   5876: ixor
    //   5877: aload #20
    //   5879: iconst_4
    //   5880: iaload
    //   5881: bipush #25
    //   5883: iushr
    //   5884: aload #20
    //   5886: iconst_4
    //   5887: iaload
    //   5888: bipush #7
    //   5890: ishl
    //   5891: ior
    //   5892: ixor
    //   5893: iadd
    //   5894: aload #20
    //   5896: bipush #6
    //   5898: iaload
    //   5899: aload #20
    //   5901: iconst_4
    //   5902: iaload
    //   5903: aload #20
    //   5905: iconst_5
    //   5906: iaload
    //   5907: aload #20
    //   5909: bipush #6
    //   5911: iaload
    //   5912: ixor
    //   5913: iand
    //   5914: ixor
    //   5915: iadd
    //   5916: aload #6
    //   5918: iload #21
    //   5920: iaload
    //   5921: iadd
    //   5922: aload #19
    //   5924: iload #21
    //   5926: iaload
    //   5927: iadd
    //   5928: istore #22
    //   5930: aload #20
    //   5932: iconst_0
    //   5933: iaload
    //   5934: iconst_2
    //   5935: iushr
    //   5936: aload #20
    //   5938: iconst_0
    //   5939: iaload
    //   5940: bipush #30
    //   5942: ishl
    //   5943: ior
    //   5944: aload #20
    //   5946: iconst_0
    //   5947: iaload
    //   5948: bipush #13
    //   5950: iushr
    //   5951: aload #20
    //   5953: iconst_0
    //   5954: iaload
    //   5955: bipush #19
    //   5957: ishl
    //   5958: ior
    //   5959: ixor
    //   5960: aload #20
    //   5962: iconst_0
    //   5963: iaload
    //   5964: bipush #22
    //   5966: iushr
    //   5967: aload #20
    //   5969: iconst_0
    //   5970: iaload
    //   5971: bipush #10
    //   5973: ishl
    //   5974: ior
    //   5975: ixor
    //   5976: aload #20
    //   5978: iconst_0
    //   5979: iaload
    //   5980: aload #20
    //   5982: iconst_1
    //   5983: iaload
    //   5984: iand
    //   5985: aload #20
    //   5987: iconst_2
    //   5988: iaload
    //   5989: aload #20
    //   5991: iconst_0
    //   5992: iaload
    //   5993: aload #20
    //   5995: iconst_1
    //   5996: iaload
    //   5997: ior
    //   5998: iand
    //   5999: ior
    //   6000: iadd
    //   6001: istore #23
    //   6003: aload #20
    //   6005: iconst_3
    //   6006: dup2
    //   6007: iaload
    //   6008: iload #22
    //   6010: iadd
    //   6011: iastore
    //   6012: aload #20
    //   6014: bipush #7
    //   6016: iload #22
    //   6018: iload #23
    //   6020: iadd
    //   6021: iastore
    //   6022: aload #20
    //   6024: bipush #7
    //   6026: iaload
    //   6027: istore #22
    //   6029: aload #20
    //   6031: bipush #7
    //   6033: aload #20
    //   6035: bipush #6
    //   6037: iaload
    //   6038: iastore
    //   6039: aload #20
    //   6041: bipush #6
    //   6043: aload #20
    //   6045: iconst_5
    //   6046: iaload
    //   6047: iastore
    //   6048: aload #20
    //   6050: iconst_5
    //   6051: aload #20
    //   6053: iconst_4
    //   6054: iaload
    //   6055: iastore
    //   6056: aload #20
    //   6058: iconst_4
    //   6059: aload #20
    //   6061: iconst_3
    //   6062: iaload
    //   6063: iastore
    //   6064: aload #20
    //   6066: iconst_3
    //   6067: aload #20
    //   6069: iconst_2
    //   6070: iaload
    //   6071: iastore
    //   6072: aload #20
    //   6074: iconst_2
    //   6075: aload #20
    //   6077: iconst_1
    //   6078: iaload
    //   6079: iastore
    //   6080: aload #20
    //   6082: iconst_1
    //   6083: aload #20
    //   6085: iconst_0
    //   6086: iaload
    //   6087: iastore
    //   6088: aload #20
    //   6090: iconst_0
    //   6091: iload #22
    //   6093: iastore
    //   6094: iinc #21, 1
    //   6097: iload_2
    //   6098: ifeq -> 5606
    //   6101: iconst_0
    //   6102: istore #21
    //   6104: iload #21
    //   6106: bipush #8
    //   6108: if_icmpge -> 6131
    //   6111: aload #8
    //   6113: iload #21
    //   6115: dup2
    //   6116: iaload
    //   6117: aload #20
    //   6119: iload #21
    //   6121: iaload
    //   6122: iadd
    //   6123: iastore
    //   6124: iinc #21, 1
    //   6127: iload_2
    //   6128: ifeq -> 6104
    //   6131: iinc #13, 64
    //   6134: iinc #17, -64
    //   6137: iload_2
    //   6138: ifeq -> 5527
    //   6141: iload #17
    //   6143: ifle -> 6179
    //   6146: iconst_0
    //   6147: istore #19
    //   6149: iload #19
    //   6151: iload #17
    //   6153: if_icmpge -> 6179
    //   6156: aload #9
    //   6158: iload #12
    //   6160: iload #19
    //   6162: iadd
    //   6163: aload #5
    //   6165: iload #13
    //   6167: iload #19
    //   6169: iadd
    //   6170: baload
    //   6171: bastore
    //   6172: iinc #19, 1
    //   6175: iload_2
    //   6176: ifeq -> 6149
    //   6179: bipush #8
    //   6181: newarray byte
    //   6183: astore #19
    //   6185: aload #19
    //   6187: iconst_0
    //   6188: iload #14
    //   6190: bipush #24
    //   6192: iushr
    //   6193: i2b
    //   6194: bastore
    //   6195: aload #19
    //   6197: iconst_1
    //   6198: iload #14
    //   6200: bipush #16
    //   6202: iushr
    //   6203: i2b
    //   6204: bastore
    //   6205: aload #19
    //   6207: iconst_2
    //   6208: iload #14
    //   6210: bipush #8
    //   6212: iushr
    //   6213: i2b
    //   6214: bastore
    //   6215: aload #19
    //   6217: iconst_3
    //   6218: iload #14
    //   6220: i2b
    //   6221: bastore
    //   6222: aload #19
    //   6224: iconst_4
    //   6225: iload #15
    //   6227: bipush #24
    //   6229: iushr
    //   6230: i2b
    //   6231: bastore
    //   6232: aload #19
    //   6234: iconst_5
    //   6235: iload #15
    //   6237: bipush #16
    //   6239: iushr
    //   6240: i2b
    //   6241: bastore
    //   6242: aload #19
    //   6244: bipush #6
    //   6246: iload #15
    //   6248: bipush #8
    //   6250: iushr
    //   6251: i2b
    //   6252: bastore
    //   6253: aload #19
    //   6255: bipush #7
    //   6257: iload #15
    //   6259: i2b
    //   6260: bastore
    //   6261: bipush #8
    //   6263: istore #11
    //   6265: aload #7
    //   6267: iconst_0
    //   6268: iaload
    //   6269: bipush #63
    //   6271: iand
    //   6272: istore #12
    //   6274: bipush #64
    //   6276: iload #12
    //   6278: isub
    //   6279: istore #18
    //   6281: aload #7
    //   6283: iconst_0
    //   6284: dup2
    //   6285: iaload
    //   6286: iload #11
    //   6288: iadd
    //   6289: iastore
    //   6290: aload #7
    //   6292: iconst_0
    //   6293: dup2
    //   6294: iaload
    //   6295: iconst_m1
    //   6296: iand
    //   6297: iastore
    //   6298: aload #7
    //   6300: iconst_0
    //   6301: iaload
    //   6302: iload #11
    //   6304: if_icmpge -> 6322
    //   6307: aload #7
    //   6309: iconst_1
    //   6310: dup2
    //   6311: iaload
    //   6312: iconst_1
    //   6313: iadd
    //   6314: iastore
    //   6315: goto -> 6322
    //   6318: invokestatic a : (Ljava/lang/Throwable;)Ljava/lang/Throwable;
    //   6321: athrow
    //   6322: iload #12
    //   6324: ifle -> 6938
    //   6327: iload #11
    //   6329: iload #18
    //   6331: if_icmplt -> 6938
    //   6334: goto -> 6341
    //   6337: invokestatic a : (Ljava/lang/Throwable;)Ljava/lang/Throwable;
    //   6340: athrow
    //   6341: iconst_0
    //   6342: istore #20
    //   6344: iload #20
    //   6346: iload #18
    //   6348: if_icmpge -> 6371
    //   6351: aload #9
    //   6353: iload #12
    //   6355: iload #20
    //   6357: iadd
    //   6358: aload #19
    //   6360: iload #20
    //   6362: baload
    //   6363: bastore
    //   6364: iinc #20, 1
    //   6367: iload_2
    //   6368: ifeq -> 6344
    //   6371: bipush #64
    //   6373: newarray int
    //   6375: astore #20
    //   6377: bipush #8
    //   6379: newarray int
    //   6381: astore #21
    //   6383: iconst_0
    //   6384: istore #22
    //   6386: iload #22
    //   6388: bipush #8
    //   6390: if_icmpge -> 6410
    //   6393: aload #21
    //   6395: iload #22
    //   6397: aload #8
    //   6399: iload #22
    //   6401: iaload
    //   6402: iastore
    //   6403: iinc #22, 1
    //   6406: iload_2
    //   6407: ifeq -> 6386
    //   6410: iconst_0
    //   6411: istore #22
    //   6413: iload #22
    //   6415: bipush #64
    //   6417: if_icmpge -> 6908
    //   6420: iload #22
    //   6422: bipush #16
    //   6424: if_icmpge -> 6505
    //   6427: aload #20
    //   6429: iload #22
    //   6431: aload #9
    //   6433: iconst_4
    //   6434: iload #22
    //   6436: imul
    //   6437: baload
    //   6438: sipush #255
    //   6441: iand
    //   6442: bipush #24
    //   6444: ishl
    //   6445: aload #9
    //   6447: iconst_4
    //   6448: iload #22
    //   6450: imul
    //   6451: iconst_1
    //   6452: iadd
    //   6453: baload
    //   6454: sipush #255
    //   6457: iand
    //   6458: bipush #16
    //   6460: ishl
    //   6461: ior
    //   6462: aload #9
    //   6464: iconst_4
    //   6465: iload #22
    //   6467: imul
    //   6468: iconst_2
    //   6469: iadd
    //   6470: baload
    //   6471: sipush #255
    //   6474: iand
    //   6475: bipush #8
    //   6477: ishl
    //   6478: ior
    //   6479: aload #9
    //   6481: iconst_4
    //   6482: iload #22
    //   6484: imul
    //   6485: iconst_3
    //   6486: iadd
    //   6487: baload
    //   6488: sipush #255
    //   6491: iand
    //   6492: ior
    //   6493: iastore
    //   6494: iload_2
    //   6495: ifeq -> 6648
    //   6498: goto -> 6505
    //   6501: invokestatic a : (Ljava/lang/Throwable;)Ljava/lang/Throwable;
    //   6504: athrow
    //   6505: aload #20
    //   6507: iload #22
    //   6509: aload #20
    //   6511: iload #22
    //   6513: iconst_2
    //   6514: isub
    //   6515: iaload
    //   6516: bipush #17
    //   6518: iushr
    //   6519: aload #20
    //   6521: iload #22
    //   6523: iconst_2
    //   6524: isub
    //   6525: iaload
    //   6526: bipush #15
    //   6528: ishl
    //   6529: ior
    //   6530: aload #20
    //   6532: iload #22
    //   6534: iconst_2
    //   6535: isub
    //   6536: iaload
    //   6537: bipush #19
    //   6539: iushr
    //   6540: aload #20
    //   6542: iload #22
    //   6544: iconst_2
    //   6545: isub
    //   6546: iaload
    //   6547: bipush #13
    //   6549: ishl
    //   6550: ior
    //   6551: ixor
    //   6552: aload #20
    //   6554: iload #22
    //   6556: iconst_2
    //   6557: isub
    //   6558: iaload
    //   6559: bipush #10
    //   6561: iushr
    //   6562: ixor
    //   6563: aload #20
    //   6565: iload #22
    //   6567: bipush #7
    //   6569: isub
    //   6570: iaload
    //   6571: iadd
    //   6572: aload #20
    //   6574: iload #22
    //   6576: bipush #15
    //   6578: isub
    //   6579: iaload
    //   6580: bipush #7
    //   6582: iushr
    //   6583: aload #20
    //   6585: iload #22
    //   6587: bipush #15
    //   6589: isub
    //   6590: iaload
    //   6591: bipush #25
    //   6593: ishl
    //   6594: ior
    //   6595: aload #20
    //   6597: iload #22
    //   6599: bipush #15
    //   6601: isub
    //   6602: iaload
    //   6603: bipush #18
    //   6605: iushr
    //   6606: aload #20
    //   6608: iload #22
    //   6610: bipush #15
    //   6612: isub
    //   6613: iaload
    //   6614: bipush #14
    //   6616: ishl
    //   6617: ior
    //   6618: ixor
    //   6619: aload #20
    //   6621: iload #22
    //   6623: bipush #15
    //   6625: isub
    //   6626: iaload
    //   6627: iconst_3
    //   6628: iushr
    //   6629: ixor
    //   6630: iadd
    //   6631: aload #20
    //   6633: iload #22
    //   6635: bipush #16
    //   6637: isub
    //   6638: iaload
    //   6639: iadd
    //   6640: iastore
    //   6641: goto -> 6648
    //   6644: invokestatic a : (Ljava/lang/Throwable;)Ljava/lang/Throwable;
    //   6647: athrow
    //   6648: aload #21
    //   6650: bipush #7
    //   6652: iaload
    //   6653: aload #21
    //   6655: iconst_4
    //   6656: iaload
    //   6657: bipush #6
    //   6659: iushr
    //   6660: aload #21
    //   6662: iconst_4
    //   6663: iaload
    //   6664: bipush #26
    //   6666: ishl
    //   6667: ior
    //   6668: aload #21
    //   6670: iconst_4
    //   6671: iaload
    //   6672: bipush #11
    //   6674: iushr
    //   6675: aload #21
    //   6677: iconst_4
    //   6678: iaload
    //   6679: bipush #21
    //   6681: ishl
    //   6682: ior
    //   6683: ixor
    //   6684: aload #21
    //   6686: iconst_4
    //   6687: iaload
    //   6688: bipush #25
    //   6690: iushr
    //   6691: aload #21
    //   6693: iconst_4
    //   6694: iaload
    //   6695: bipush #7
    //   6697: ishl
    //   6698: ior
    //   6699: ixor
    //   6700: iadd
    //   6701: aload #21
    //   6703: bipush #6
    //   6705: iaload
    //   6706: aload #21
    //   6708: iconst_4
    //   6709: iaload
    //   6710: aload #21
    //   6712: iconst_5
    //   6713: iaload
    //   6714: aload #21
    //   6716: bipush #6
    //   6718: iaload
    //   6719: ixor
    //   6720: iand
    //   6721: ixor
    //   6722: iadd
    //   6723: aload #6
    //   6725: iload #22
    //   6727: iaload
    //   6728: iadd
    //   6729: aload #20
    //   6731: iload #22
    //   6733: iaload
    //   6734: iadd
    //   6735: istore #23
    //   6737: aload #21
    //   6739: iconst_0
    //   6740: iaload
    //   6741: iconst_2
    //   6742: iushr
    //   6743: aload #21
    //   6745: iconst_0
    //   6746: iaload
    //   6747: bipush #30
    //   6749: ishl
    //   6750: ior
    //   6751: aload #21
    //   6753: iconst_0
    //   6754: iaload
    //   6755: bipush #13
    //   6757: iushr
    //   6758: aload #21
    //   6760: iconst_0
    //   6761: iaload
    //   6762: bipush #19
    //   6764: ishl
    //   6765: ior
    //   6766: ixor
    //   6767: aload #21
    //   6769: iconst_0
    //   6770: iaload
    //   6771: bipush #22
    //   6773: iushr
    //   6774: aload #21
    //   6776: iconst_0
    //   6777: iaload
    //   6778: bipush #10
    //   6780: ishl
    //   6781: ior
    //   6782: ixor
    //   6783: aload #21
    //   6785: iconst_0
    //   6786: iaload
    //   6787: aload #21
    //   6789: iconst_1
    //   6790: iaload
    //   6791: iand
    //   6792: aload #21
    //   6794: iconst_2
    //   6795: iaload
    //   6796: aload #21
    //   6798: iconst_0
    //   6799: iaload
    //   6800: aload #21
    //   6802: iconst_1
    //   6803: iaload
    //   6804: ior
    //   6805: iand
    //   6806: ior
    //   6807: iadd
    //   6808: istore #24
    //   6810: aload #21
    //   6812: iconst_3
    //   6813: dup2
    //   6814: iaload
    //   6815: iload #23
    //   6817: iadd
    //   6818: iastore
    //   6819: aload #21
    //   6821: bipush #7
    //   6823: iload #23
    //   6825: iload #24
    //   6827: iadd
    //   6828: iastore
    //   6829: aload #21
    //   6831: bipush #7
    //   6833: iaload
    //   6834: istore #23
    //   6836: aload #21
    //   6838: bipush #7
    //   6840: aload #21
    //   6842: bipush #6
    //   6844: iaload
    //   6845: iastore
    //   6846: aload #21
    //   6848: bipush #6
    //   6850: aload #21
    //   6852: iconst_5
    //   6853: iaload
    //   6854: iastore
    //   6855: aload #21
    //   6857: iconst_5
    //   6858: aload #21
    //   6860: iconst_4
    //   6861: iaload
    //   6862: iastore
    //   6863: aload #21
    //   6865: iconst_4
    //   6866: aload #21
    //   6868: iconst_3
    //   6869: iaload
    //   6870: iastore
    //   6871: aload #21
    //   6873: iconst_3
    //   6874: aload #21
    //   6876: iconst_2
    //   6877: iaload
    //   6878: iastore
    //   6879: aload #21
    //   6881: iconst_2
    //   6882: aload #21
    //   6884: iconst_1
    //   6885: iaload
    //   6886: iastore
    //   6887: aload #21
    //   6889: iconst_1
    //   6890: aload #21
    //   6892: iconst_0
    //   6893: iaload
    //   6894: iastore
    //   6895: aload #21
    //   6897: iconst_0
    //   6898: iload #23
    //   6900: iastore
    //   6901: iinc #22, 1
    //   6904: iload_2
    //   6905: ifeq -> 6413
    //   6908: iconst_0
    //   6909: istore #22
    //   6911: iload #22
    //   6913: bipush #8
    //   6915: if_icmpge -> 6938
    //   6918: aload #8
    //   6920: iload #22
    //   6922: dup2
    //   6923: iaload
    //   6924: aload #21
    //   6926: iload #22
    //   6928: iaload
    //   6929: iadd
    //   6930: iastore
    //   6931: iinc #22, 1
    //   6934: iload_2
    //   6935: ifeq -> 6911
    //   6938: bipush #32
    //   6940: newarray byte
    //   6942: astore #4
    //   6944: aload #4
    //   6946: iconst_0
    //   6947: aload #8
    //   6949: iconst_0
    //   6950: iaload
    //   6951: bipush #24
    //   6953: iushr
    //   6954: i2b
    //   6955: bastore
    //   6956: aload #4
    //   6958: iconst_1
    //   6959: aload #8
    //   6961: iconst_0
    //   6962: iaload
    //   6963: bipush #16
    //   6965: iushr
    //   6966: i2b
    //   6967: bastore
    //   6968: aload #4
    //   6970: iconst_2
    //   6971: aload #8
    //   6973: iconst_0
    //   6974: iaload
    //   6975: bipush #8
    //   6977: iushr
    //   6978: i2b
    //   6979: bastore
    //   6980: aload #4
    //   6982: iconst_3
    //   6983: aload #8
    //   6985: iconst_0
    //   6986: iaload
    //   6987: i2b
    //   6988: bastore
    //   6989: aload #4
    //   6991: iconst_4
    //   6992: aload #8
    //   6994: iconst_1
    //   6995: iaload
    //   6996: bipush #24
    //   6998: iushr
    //   6999: i2b
    //   7000: bastore
    //   7001: aload #4
    //   7003: iconst_5
    //   7004: aload #8
    //   7006: iconst_1
    //   7007: iaload
    //   7008: bipush #16
    //   7010: iushr
    //   7011: i2b
    //   7012: bastore
    //   7013: aload #4
    //   7015: bipush #6
    //   7017: aload #8
    //   7019: iconst_1
    //   7020: iaload
    //   7021: bipush #8
    //   7023: iushr
    //   7024: i2b
    //   7025: bastore
    //   7026: aload #4
    //   7028: bipush #7
    //   7030: aload #8
    //   7032: iconst_1
    //   7033: iaload
    //   7034: i2b
    //   7035: bastore
    //   7036: aload #4
    //   7038: bipush #8
    //   7040: aload #8
    //   7042: iconst_2
    //   7043: iaload
    //   7044: bipush #24
    //   7046: iushr
    //   7047: i2b
    //   7048: bastore
    //   7049: aload #4
    //   7051: bipush #9
    //   7053: aload #8
    //   7055: iconst_2
    //   7056: iaload
    //   7057: bipush #16
    //   7059: iushr
    //   7060: i2b
    //   7061: bastore
    //   7062: aload #4
    //   7064: bipush #10
    //   7066: aload #8
    //   7068: iconst_2
    //   7069: iaload
    //   7070: bipush #8
    //   7072: iushr
    //   7073: i2b
    //   7074: bastore
    //   7075: aload #4
    //   7077: bipush #11
    //   7079: aload #8
    //   7081: iconst_2
    //   7082: iaload
    //   7083: i2b
    //   7084: bastore
    //   7085: aload #4
    //   7087: bipush #12
    //   7089: aload #8
    //   7091: iconst_3
    //   7092: iaload
    //   7093: bipush #24
    //   7095: iushr
    //   7096: i2b
    //   7097: bastore
    //   7098: aload #4
    //   7100: bipush #13
    //   7102: aload #8
    //   7104: iconst_3
    //   7105: iaload
    //   7106: bipush #16
    //   7108: iushr
    //   7109: i2b
    //   7110: bastore
    //   7111: aload #4
    //   7113: bipush #14
    //   7115: aload #8
    //   7117: iconst_3
    //   7118: iaload
    //   7119: bipush #8
    //   7121: iushr
    //   7122: i2b
    //   7123: bastore
    //   7124: aload #4
    //   7126: bipush #15
    //   7128: aload #8
    //   7130: iconst_3
    //   7131: iaload
    //   7132: i2b
    //   7133: bastore
    //   7134: aload #4
    //   7136: bipush #16
    //   7138: aload #8
    //   7140: iconst_4
    //   7141: iaload
    //   7142: bipush #24
    //   7144: iushr
    //   7145: i2b
    //   7146: bastore
    //   7147: aload #4
    //   7149: bipush #17
    //   7151: aload #8
    //   7153: iconst_4
    //   7154: iaload
    //   7155: bipush #16
    //   7157: iushr
    //   7158: i2b
    //   7159: bastore
    //   7160: aload #4
    //   7162: bipush #18
    //   7164: aload #8
    //   7166: iconst_4
    //   7167: iaload
    //   7168: bipush #8
    //   7170: iushr
    //   7171: i2b
    //   7172: bastore
    //   7173: aload #4
    //   7175: bipush #19
    //   7177: aload #8
    //   7179: iconst_4
    //   7180: iaload
    //   7181: i2b
    //   7182: bastore
    //   7183: aload #4
    //   7185: bipush #20
    //   7187: aload #8
    //   7189: iconst_5
    //   7190: iaload
    //   7191: bipush #24
    //   7193: iushr
    //   7194: i2b
    //   7195: bastore
    //   7196: aload #4
    //   7198: bipush #21
    //   7200: aload #8
    //   7202: iconst_5
    //   7203: iaload
    //   7204: bipush #16
    //   7206: iushr
    //   7207: i2b
    //   7208: bastore
    //   7209: aload #4
    //   7211: bipush #22
    //   7213: aload #8
    //   7215: iconst_5
    //   7216: iaload
    //   7217: bipush #8
    //   7219: iushr
    //   7220: i2b
    //   7221: bastore
    //   7222: aload #4
    //   7224: bipush #23
    //   7226: aload #8
    //   7228: iconst_5
    //   7229: iaload
    //   7230: i2b
    //   7231: bastore
    //   7232: aload #4
    //   7234: bipush #24
    //   7236: aload #8
    //   7238: bipush #6
    //   7240: iaload
    //   7241: bipush #24
    //   7243: iushr
    //   7244: i2b
    //   7245: bastore
    //   7246: aload #4
    //   7248: bipush #25
    //   7250: aload #8
    //   7252: bipush #6
    //   7254: iaload
    //   7255: bipush #16
    //   7257: iushr
    //   7258: i2b
    //   7259: bastore
    //   7260: aload #4
    //   7262: bipush #26
    //   7264: aload #8
    //   7266: bipush #6
    //   7268: iaload
    //   7269: bipush #8
    //   7271: iushr
    //   7272: i2b
    //   7273: bastore
    //   7274: aload #4
    //   7276: bipush #27
    //   7278: aload #8
    //   7280: bipush #6
    //   7282: iaload
    //   7283: i2b
    //   7284: bastore
    //   7285: aload #4
    //   7287: bipush #28
    //   7289: aload #8
    //   7291: bipush #7
    //   7293: iaload
    //   7294: bipush #24
    //   7296: iushr
    //   7297: i2b
    //   7298: bastore
    //   7299: aload #4
    //   7301: bipush #29
    //   7303: aload #8
    //   7305: bipush #7
    //   7307: iaload
    //   7308: bipush #16
    //   7310: iushr
    //   7311: i2b
    //   7312: bastore
    //   7313: aload #4
    //   7315: bipush #30
    //   7317: aload #8
    //   7319: bipush #7
    //   7321: iaload
    //   7322: bipush #8
    //   7324: iushr
    //   7325: i2b
    //   7326: bastore
    //   7327: aload #4
    //   7329: bipush #31
    //   7331: aload #8
    //   7333: bipush #7
    //   7335: iaload
    //   7336: i2b
    //   7337: bastore
    //   7338: iconst_0
    //   7339: istore_3
    //   7340: getstatic burp/Zl8l.ZG : Ljava/lang/String;
    //   7343: getstatic burp/Zr_z.ZT : Ljava/lang/Object;
    //   7346: checkcast java/math/BigInteger
    //   7349: invokevirtual intValue : ()I
    //   7352: bipush #32
    //   7354: irem
    //   7355: invokestatic abs : (I)I
    //   7358: invokevirtual charAt : (I)C
    //   7361: getstatic burp/Zg_y.ZF : Ljava/lang/String;
    //   7364: getstatic burp/Zss8.ZO : Ljava/lang/Object;
    //   7367: checkcast java/math/BigInteger
    //   7370: invokevirtual intValue : ()I
    //   7373: bipush #32
    //   7375: irem
    //   7376: invokestatic abs : (I)I
    //   7379: invokevirtual charAt : (I)C
    //   7382: if_icmple -> 7726
    //   7385: sipush #-26883
    //   7388: sipush #-14195
    //   7391: invokestatic a : (II)Ljava/lang/String;
    //   7394: iconst_1
    //   7395: ldc burp/Zek5
    //   7397: invokevirtual getClassLoader : ()Ljava/lang/ClassLoader;
    //   7400: invokestatic forName : (Ljava/lang/String;ZLjava/lang/ClassLoader;)Ljava/lang/Class;
    //   7403: invokevirtual getDeclaredFields : ()[Ljava/lang/reflect/Field;
    //   7406: astore #4
    //   7408: aload #4
    //   7410: arraylength
    //   7411: istore #5
    //   7413: iconst_0
    //   7414: istore #6
    //   7416: iload #6
    //   7418: iload #5
    //   7420: if_icmpge -> 7558
    //   7423: aload #4
    //   7425: iload #6
    //   7427: aaload
    //   7428: astore #7
    //   7430: aload #7
    //   7432: invokevirtual getModifiers : ()I
    //   7435: invokestatic isStatic : (I)Z
    //   7438: ifne -> 7448
    //   7441: goto -> 7551
    //   7444: invokestatic a : (Ljava/lang/Throwable;)Ljava/lang/Throwable;
    //   7447: athrow
    //   7448: aload #7
    //   7450: invokevirtual getType : ()Ljava/lang/Class;
    //   7453: astore #8
    //   7455: aload #8
    //   7457: ifnull -> 7538
    //   7460: aload #8
    //   7462: invokevirtual isPrimitive : ()Z
    //   7465: ifne -> 7538
    //   7468: goto -> 7475
    //   7471: invokestatic a : (Ljava/lang/Throwable;)Ljava/lang/Throwable;
    //   7474: athrow
    //   7475: aload #8
    //   7477: invokevirtual getPackage : ()Ljava/lang/Package;
    //   7480: ifnull -> 7538
    //   7483: goto -> 7490
    //   7486: invokestatic a : (Ljava/lang/Throwable;)Ljava/lang/Throwable;
    //   7489: athrow
    //   7490: aload #8
    //   7492: invokevirtual getPackage : ()Ljava/lang/Package;
    //   7495: invokevirtual getName : ()Ljava/lang/String;
    //   7498: ifnull -> 7538
    //   7501: goto -> 7508
    //   7504: invokestatic a : (Ljava/lang/Throwable;)Ljava/lang/Throwable;
    //   7507: athrow
    //   7508: aload #8
    //   7510: invokevirtual getPackage : ()Ljava/lang/Package;
    //   7513: invokevirtual getName : ()Ljava/lang/String;
    //   7516: sipush #-26881
    //   7519: sipush #15651
    //   7522: invokestatic a : (II)Ljava/lang/String;
    //   7525: invokevirtual startsWith : (Ljava/lang/String;)Z
    //   7528: ifne -> 7538
    //   7531: goto -> 7538
    //   7534: invokestatic a : (Ljava/lang/Throwable;)Ljava/lang/Throwable;
    //   7537: athrow
    //   7538: aload #7
    //   7540: iconst_1
    //   7541: invokevirtual setAccessible : (Z)V
    //   7544: aload #7
    //   7546: aconst_null
    //   7547: invokevirtual get : (Ljava/lang/Object;)Ljava/lang/Object;
    //   7550: pop
    //   7551: iinc #6, 1
    //   7554: iload_2
    //   7555: ifeq -> 7416
    //   7558: sipush #-26908
    //   7561: sipush #19739
    //   7564: invokestatic a : (II)Ljava/lang/String;
    //   7567: invokestatic forName : (Ljava/lang/String;)Ljava/lang/Class;
    //   7570: invokevirtual getDeclaredMethods : ()[Ljava/lang/reflect/Method;
    //   7573: astore #4
    //   7575: aload #4
    //   7577: arraylength
    //   7578: istore #5
    //   7580: iconst_0
    //   7581: istore #6
    //   7583: iload #6
    //   7585: iload #5
    //   7587: if_icmpge -> 7723
    //   7590: aload #4
    //   7592: iload #6
    //   7594: aaload
    //   7595: astore #7
    //   7597: aload #7
    //   7599: invokevirtual getParameterTypes : ()[Ljava/lang/Class;
    //   7602: pop
    //   7603: aload #7
    //   7605: invokevirtual getModifiers : ()I
    //   7608: invokestatic isStatic : (I)Z
    //   7611: ifeq -> 7709
    //   7614: aload #7
    //   7616: invokevirtual getParameterTypes : ()[Ljava/lang/Class;
    //   7619: arraylength
    //   7620: iconst_2
    //   7621: if_icmpne -> 7709
    //   7624: goto -> 7631
    //   7627: invokestatic a : (Ljava/lang/Throwable;)Ljava/lang/Throwable;
    //   7630: athrow
    //   7631: aload #7
    //   7633: invokevirtual getReturnType : ()Ljava/lang/Class;
    //   7636: getstatic java/lang/Boolean.TYPE : Ljava/lang/Class;
    //   7639: if_acmpne -> 7709
    //   7642: goto -> 7649
    //   7645: invokestatic a : (Ljava/lang/Throwable;)Ljava/lang/Throwable;
    //   7648: athrow
    //   7649: aload #7
    //   7651: iconst_1
    //   7652: invokevirtual setAccessible : (Z)V
    //   7655: aload #7
    //   7657: aconst_null
    //   7658: iconst_2
    //   7659: anewarray java/lang/Object
    //   7662: dup
    //   7663: iconst_0
    //   7664: aload_0
    //   7665: aastore
    //   7666: dup
    //   7667: iconst_1
    //   7668: aload_1
    //   7669: ifnonnull -> 7687
    //   7672: goto -> 7679
    //   7675: invokestatic a : (Ljava/lang/Throwable;)Ljava/lang/Throwable;
    //   7678: athrow
    //   7679: aload_1
    //   7680: goto -> 7694
    //   7683: invokestatic a : (Ljava/lang/Throwable;)Ljava/lang/Throwable;
    //   7686: athrow
    //   7687: aload_1
    //   7688: checkcast [B
    //   7691: invokevirtual clone : ()Ljava/lang/Object;
    //   7694: aastore
    //   7695: invokevirtual invoke : (Ljava/lang/Object;[Ljava/lang/Object;)Ljava/lang/Object;
    //   7698: checkcast java/lang/Boolean
    //   7701: invokevirtual booleanValue : ()Z
    //   7704: istore_3
    //   7705: iload_2
    //   7706: ifeq -> 7723
    //   7709: iinc #6, 1
    //   7712: iload_2
    //   7713: ifeq -> 7583
    //   7716: goto -> 7723
    //   7719: invokestatic a : (Ljava/lang/Throwable;)Ljava/lang/Throwable;
    //   7722: athrow
    //   7723: goto -> 8064
    //   7726: sipush #-26902
    //   7729: sipush #-6426
    //   7732: invokestatic a : (II)Ljava/lang/String;
    //   7735: iconst_1
    //   7736: ldc burp/Zxdh
    //   7738: invokevirtual getClassLoader : ()Ljava/lang/ClassLoader;
    //   7741: invokestatic forName : (Ljava/lang/String;ZLjava/lang/ClassLoader;)Ljava/lang/Class;
    //   7744: invokevirtual getDeclaredFields : ()[Ljava/lang/reflect/Field;
    //   7747: astore #4
    //   7749: aload #4
    //   7751: arraylength
    //   7752: istore #5
    //   7754: iconst_0
    //   7755: istore #6
    //   7757: iload #6
    //   7759: iload #5
    //   7761: if_icmpge -> 7899
    //   7764: aload #4
    //   7766: iload #6
    //   7768: aaload
    //   7769: astore #7
    //   7771: aload #7
    //   7773: invokevirtual getModifiers : ()I
    //   7776: invokestatic isStatic : (I)Z
    //   7779: ifne -> 7789
    //   7782: goto -> 7892
    //   7785: invokestatic a : (Ljava/lang/Throwable;)Ljava/lang/Throwable;
    //   7788: athrow
    //   7789: aload #7
    //   7791: invokevirtual getType : ()Ljava/lang/Class;
    //   7794: astore #8
    //   7796: aload #8
    //   7798: ifnull -> 7879
    //   7801: aload #8
    //   7803: invokevirtual isPrimitive : ()Z
    //   7806: ifne -> 7879
    //   7809: goto -> 7816
    //   7812: invokestatic a : (Ljava/lang/Throwable;)Ljava/lang/Throwable;
    //   7815: athrow
    //   7816: aload #8
    //   7818: invokevirtual getPackage : ()Ljava/lang/Package;
    //   7821: ifnull -> 7879
    //   7824: goto -> 7831
    //   7827: invokestatic a : (Ljava/lang/Throwable;)Ljava/lang/Throwable;
    //   7830: athrow
    //   7831: aload #8
    //   7833: invokevirtual getPackage : ()Ljava/lang/Package;
    //   7836: invokevirtual getName : ()Ljava/lang/String;
    //   7839: ifnull -> 7879
    //   7842: goto -> 7849
    //   7845: invokestatic a : (Ljava/lang/Throwable;)Ljava/lang/Throwable;
    //   7848: athrow
    //   7849: aload #8
    //   7851: invokevirtual getPackage : ()Ljava/lang/Package;
    //   7854: invokevirtual getName : ()Ljava/lang/String;
    //   7857: sipush #-26881
    //   7860: sipush #15651
    //   7863: invokestatic a : (II)Ljava/lang/String;
    //   7866: invokevirtual startsWith : (Ljava/lang/String;)Z
    //   7869: ifne -> 7879
    //   7872: goto -> 7879
    //   7875: invokestatic a : (Ljava/lang/Throwable;)Ljava/lang/Throwable;
    //   7878: athrow
    //   7879: aload #7
    //   7881: iconst_1
    //   7882: invokevirtual setAccessible : (Z)V
    //   7885: aload #7
    //   7887: aconst_null
    //   7888: invokevirtual get : (Ljava/lang/Object;)Ljava/lang/Object;
    //   7891: pop
    //   7892: iinc #6, 1
    //   7895: iload_2
    //   7896: ifeq -> 7757
    //   7899: sipush #-26899
    //   7902: sipush #7136
    //   7905: invokestatic a : (II)Ljava/lang/String;
    //   7908: invokestatic forName : (Ljava/lang/String;)Ljava/lang/Class;
    //   7911: invokevirtual getDeclaredMethods : ()[Ljava/lang/reflect/Method;
    //   7914: astore #4
    //   7916: aload #4
    //   7918: arraylength
    //   7919: istore #5
    //   7921: iconst_0
    //   7922: istore #6
    //   7924: iload #6
    //   7926: iload #5
    //   7928: if_icmpge -> 8064
    //   7931: aload #4
    //   7933: iload #6
    //   7935: aaload
    //   7936: astore #7
    //   7938: aload #7
    //   7940: invokevirtual getParameterTypes : ()[Ljava/lang/Class;
    //   7943: pop
    //   7944: aload #7
    //   7946: invokevirtual getModifiers : ()I
    //   7949: invokestatic isStatic : (I)Z
    //   7952: ifeq -> 8050
    //   7955: aload #7
    //   7957: invokevirtual getParameterTypes : ()[Ljava/lang/Class;
    //   7960: arraylength
    //   7961: iconst_2
    //   7962: if_icmpne -> 8050
    //   7965: goto -> 7972
    //   7968: invokestatic a : (Ljava/lang/Throwable;)Ljava/lang/Throwable;
    //   7971: athrow
    //   7972: aload #7
    //   7974: invokevirtual getReturnType : ()Ljava/lang/Class;
    //   7977: getstatic java/lang/Boolean.TYPE : Ljava/lang/Class;
    //   7980: if_acmpne -> 8050
    //   7983: goto -> 7990
    //   7986: invokestatic a : (Ljava/lang/Throwable;)Ljava/lang/Throwable;
    //   7989: athrow
    //   7990: aload #7
    //   7992: iconst_1
    //   7993: invokevirtual setAccessible : (Z)V
    //   7996: aload #7
    //   7998: aconst_null
    //   7999: iconst_2
    //   8000: anewarray java/lang/Object
    //   8003: dup
    //   8004: iconst_0
    //   8005: aload_0
    //   8006: aastore
    //   8007: dup
    //   8008: iconst_1
    //   8009: aload_1
    //   8010: ifnonnull -> 8028
    //   8013: goto -> 8020
    //   8016: invokestatic a : (Ljava/lang/Throwable;)Ljava/lang/Throwable;
    //   8019: athrow
    //   8020: aload_1
    //   8021: goto -> 8035
    //   8024: invokestatic a : (Ljava/lang/Throwable;)Ljava/lang/Throwable;
    //   8027: athrow
    //   8028: aload_1
    //   8029: checkcast [B
    //   8032: invokevirtual clone : ()Ljava/lang/Object;
    //   8035: aastore
    //   8036: invokevirtual invoke : (Ljava/lang/Object;[Ljava/lang/Object;)Ljava/lang/Object;
    //   8039: checkcast java/lang/Boolean
    //   8042: invokevirtual booleanValue : ()Z
    //   8045: istore_3
    //   8046: iload_2
    //   8047: ifeq -> 8064
    //   8050: iinc #6, 1
    //   8053: iload_2
    //   8054: ifeq -> 7924
    //   8057: goto -> 8064
    //   8060: invokestatic a : (Ljava/lang/Throwable;)Ljava/lang/Throwable;
    //   8063: athrow
    //   8064: iload_3
    //   8065: ifeq -> 8070
    //   8068: iload_3
    //   8069: ireturn
    //   8070: getstatic burp/Zgx6.ZX : Ljava/lang/String;
    //   8073: getstatic burp/Zmpv.ZI : Ljava/lang/Object;
    //   8076: checkcast java/math/BigInteger
    //   8079: invokevirtual intValue : ()I
    //   8082: bipush #32
    //   8084: irem
    //   8085: invokestatic abs : (I)I
    //   8088: invokevirtual charAt : (I)C
    //   8091: getstatic burp/Ztgt.ZQ : Ljava/lang/String;
    //   8094: getstatic burp/Zrqd.Zi : Ljava/lang/Object;
    //   8097: checkcast java/math/BigInteger
    //   8100: invokevirtual intValue : ()I
    //   8103: bipush #32
    //   8105: irem
    //   8106: invokestatic abs : (I)I
    //   8109: invokevirtual charAt : (I)C
    //   8112: if_icmple -> 8457
    //   8115: sipush #-26886
    //   8118: sipush #1434
    //   8121: invokestatic a : (II)Ljava/lang/String;
    //   8124: iconst_1
    //   8125: ldc burp/Zg7w
    //   8127: invokevirtual getClassLoader : ()Ljava/lang/ClassLoader;
    //   8130: invokestatic forName : (Ljava/lang/String;ZLjava/lang/ClassLoader;)Ljava/lang/Class;
    //   8133: invokevirtual getDeclaredFields : ()[Ljava/lang/reflect/Field;
    //   8136: astore #4
    //   8138: aload #4
    //   8140: arraylength
    //   8141: istore #5
    //   8143: iconst_0
    //   8144: istore #6
    //   8146: iload #6
    //   8148: iload #5
    //   8150: if_icmpge -> 8288
    //   8153: aload #4
    //   8155: iload #6
    //   8157: aaload
    //   8158: astore #7
    //   8160: aload #7
    //   8162: invokevirtual getModifiers : ()I
    //   8165: invokestatic isStatic : (I)Z
    //   8168: ifne -> 8178
    //   8171: goto -> 8281
    //   8174: invokestatic a : (Ljava/lang/Throwable;)Ljava/lang/Throwable;
    //   8177: athrow
    //   8178: aload #7
    //   8180: invokevirtual getType : ()Ljava/lang/Class;
    //   8183: astore #8
    //   8185: aload #8
    //   8187: ifnull -> 8268
    //   8190: aload #8
    //   8192: invokevirtual isPrimitive : ()Z
    //   8195: ifne -> 8268
    //   8198: goto -> 8205
    //   8201: invokestatic a : (Ljava/lang/Throwable;)Ljava/lang/Throwable;
    //   8204: athrow
    //   8205: aload #8
    //   8207: invokevirtual getPackage : ()Ljava/lang/Package;
    //   8210: ifnull -> 8268
    //   8213: goto -> 8220
    //   8216: invokestatic a : (Ljava/lang/Throwable;)Ljava/lang/Throwable;
    //   8219: athrow
    //   8220: aload #8
    //   8222: invokevirtual getPackage : ()Ljava/lang/Package;
    //   8225: invokevirtual getName : ()Ljava/lang/String;
    //   8228: ifnull -> 8268
    //   8231: goto -> 8238
    //   8234: invokestatic a : (Ljava/lang/Throwable;)Ljava/lang/Throwable;
    //   8237: athrow
    //   8238: aload #8
    //   8240: invokevirtual getPackage : ()Ljava/lang/Package;
    //   8243: invokevirtual getName : ()Ljava/lang/String;
    //   8246: sipush #-26881
    //   8249: sipush #15651
    //   8252: invokestatic a : (II)Ljava/lang/String;
    //   8255: invokevirtual startsWith : (Ljava/lang/String;)Z
    //   8258: ifne -> 8268
    //   8261: goto -> 8268
    //   8264: invokestatic a : (Ljava/lang/Throwable;)Ljava/lang/Throwable;
    //   8267: athrow
    //   8268: aload #7
    //   8270: iconst_1
    //   8271: invokevirtual setAccessible : (Z)V
    //   8274: aload #7
    //   8276: aconst_null
    //   8277: invokevirtual get : (Ljava/lang/Object;)Ljava/lang/Object;
    //   8280: pop
    //   8281: iinc #6, 1
    //   8284: iload_2
    //   8285: ifeq -> 8146
    //   8288: sipush #-26884
    //   8291: sipush #11821
    //   8294: invokestatic a : (II)Ljava/lang/String;
    //   8297: invokestatic forName : (Ljava/lang/String;)Ljava/lang/Class;
    //   8300: invokevirtual getDeclaredMethods : ()[Ljava/lang/reflect/Method;
    //   8303: astore #4
    //   8305: aload #4
    //   8307: arraylength
    //   8308: istore #5
    //   8310: iconst_0
    //   8311: istore #6
    //   8313: iload #6
    //   8315: iload #5
    //   8317: if_icmpge -> 8453
    //   8320: aload #4
    //   8322: iload #6
    //   8324: aaload
    //   8325: astore #7
    //   8327: aload #7
    //   8329: invokevirtual getParameterTypes : ()[Ljava/lang/Class;
    //   8332: pop
    //   8333: aload #7
    //   8335: invokevirtual getModifiers : ()I
    //   8338: invokestatic isStatic : (I)Z
    //   8341: ifeq -> 8439
    //   8344: aload #7
    //   8346: invokevirtual getParameterTypes : ()[Ljava/lang/Class;
    //   8349: arraylength
    //   8350: iconst_2
    //   8351: if_icmpne -> 8439
    //   8354: goto -> 8361
    //   8357: invokestatic a : (Ljava/lang/Throwable;)Ljava/lang/Throwable;
    //   8360: athrow
    //   8361: aload #7
    //   8363: invokevirtual getReturnType : ()Ljava/lang/Class;
    //   8366: getstatic java/lang/Boolean.TYPE : Ljava/lang/Class;
    //   8369: if_acmpne -> 8439
    //   8372: goto -> 8379
    //   8375: invokestatic a : (Ljava/lang/Throwable;)Ljava/lang/Throwable;
    //   8378: athrow
    //   8379: aload #7
    //   8381: iconst_1
    //   8382: invokevirtual setAccessible : (Z)V
    //   8385: aload #7
    //   8387: aconst_null
    //   8388: iconst_2
    //   8389: anewarray java/lang/Object
    //   8392: dup
    //   8393: iconst_0
    //   8394: aload_0
    //   8395: aastore
    //   8396: dup
    //   8397: iconst_1
    //   8398: aload_1
    //   8399: ifnonnull -> 8417
    //   8402: goto -> 8409
    //   8405: invokestatic a : (Ljava/lang/Throwable;)Ljava/lang/Throwable;
    //   8408: athrow
    //   8409: aload_1
    //   8410: goto -> 8424
    //   8413: invokestatic a : (Ljava/lang/Throwable;)Ljava/lang/Throwable;
    //   8416: athrow
    //   8417: aload_1
    //   8418: checkcast [B
    //   8421: invokevirtual clone : ()Ljava/lang/Object;
    //   8424: aastore
    //   8425: invokevirtual invoke : (Ljava/lang/Object;[Ljava/lang/Object;)Ljava/lang/Object;
    //   8428: checkcast java/lang/Boolean
    //   8431: invokevirtual booleanValue : ()Z
    //   8434: istore_3
    //   8435: iload_2
    //   8436: ifeq -> 8453
    //   8439: iinc #6, 1
    //   8442: iload_2
    //   8443: ifeq -> 8313
    //   8446: goto -> 8453
    //   8449: invokestatic a : (Ljava/lang/Throwable;)Ljava/lang/Throwable;
    //   8452: athrow
    //   8453: iload_2
    //   8454: ifeq -> 8795
    //   8457: sipush #-26891
    //   8460: sipush #16166
    //   8463: invokestatic a : (II)Ljava/lang/String;
    //   8466: iconst_1
    //   8467: ldc burp/Zm6h
    //   8469: invokevirtual getClassLoader : ()Ljava/lang/ClassLoader;
    //   8472: invokestatic forName : (Ljava/lang/String;ZLjava/lang/ClassLoader;)Ljava/lang/Class;
    //   8475: invokevirtual getDeclaredFields : ()[Ljava/lang/reflect/Field;
    //   8478: astore #4
    //   8480: aload #4
    //   8482: arraylength
    //   8483: istore #5
    //   8485: iconst_0
    //   8486: istore #6
    //   8488: iload #6
    //   8490: iload #5
    //   8492: if_icmpge -> 8630
    //   8495: aload #4
    //   8497: iload #6
    //   8499: aaload
    //   8500: astore #7
    //   8502: aload #7
    //   8504: invokevirtual getModifiers : ()I
    //   8507: invokestatic isStatic : (I)Z
    //   8510: ifne -> 8520
    //   8513: goto -> 8623
    //   8516: invokestatic a : (Ljava/lang/Throwable;)Ljava/lang/Throwable;
    //   8519: athrow
    //   8520: aload #7
    //   8522: invokevirtual getType : ()Ljava/lang/Class;
    //   8525: astore #8
    //   8527: aload #8
    //   8529: ifnull -> 8610
    //   8532: aload #8
    //   8534: invokevirtual isPrimitive : ()Z
    //   8537: ifne -> 8610
    //   8540: goto -> 8547
    //   8543: invokestatic a : (Ljava/lang/Throwable;)Ljava/lang/Throwable;
    //   8546: athrow
    //   8547: aload #8
    //   8549: invokevirtual getPackage : ()Ljava/lang/Package;
    //   8552: ifnull -> 8610
    //   8555: goto -> 8562
    //   8558: invokestatic a : (Ljava/lang/Throwable;)Ljava/lang/Throwable;
    //   8561: athrow
    //   8562: aload #8
    //   8564: invokevirtual getPackage : ()Ljava/lang/Package;
    //   8567: invokevirtual getName : ()Ljava/lang/String;
    //   8570: ifnull -> 8610
    //   8573: goto -> 8580
    //   8576: invokestatic a : (Ljava/lang/Throwable;)Ljava/lang/Throwable;
    //   8579: athrow
    //   8580: aload #8
    //   8582: invokevirtual getPackage : ()Ljava/lang/Package;
    //   8585: invokevirtual getName : ()Ljava/lang/String;
    //   8588: sipush #-26881
    //   8591: sipush #15651
    //   8594: invokestatic a : (II)Ljava/lang/String;
    //   8597: invokevirtual startsWith : (Ljava/lang/String;)Z
    //   8600: ifne -> 8610
    //   8603: goto -> 8610
    //   8606: invokestatic a : (Ljava/lang/Throwable;)Ljava/lang/Throwable;
    //   8609: athrow
    //   8610: aload #7
    //   8612: iconst_1
    //   8613: invokevirtual setAccessible : (Z)V
    //   8616: aload #7
    //   8618: aconst_null
    //   8619: invokevirtual get : (Ljava/lang/Object;)Ljava/lang/Object;
    //   8622: pop
    //   8623: iinc #6, 1
    //   8626: iload_2
    //   8627: ifeq -> 8488
    //   8630: sipush #-26905
    //   8633: sipush #-18298
    //   8636: invokestatic a : (II)Ljava/lang/String;
    //   8639: invokestatic forName : (Ljava/lang/String;)Ljava/lang/Class;
    //   8642: invokevirtual getDeclaredMethods : ()[Ljava/lang/reflect/Method;
    //   8645: astore #4
    //   8647: aload #4
    //   8649: arraylength
    //   8650: istore #5
    //   8652: iconst_0
    //   8653: istore #6
    //   8655: iload #6
    //   8657: iload #5
    //   8659: if_icmpge -> 8795
    //   8662: aload #4
    //   8664: iload #6
    //   8666: aaload
    //   8667: astore #7
    //   8669: aload #7
    //   8671: invokevirtual getParameterTypes : ()[Ljava/lang/Class;
    //   8674: pop
    //   8675: aload #7
    //   8677: invokevirtual getModifiers : ()I
    //   8680: invokestatic isStatic : (I)Z
    //   8683: ifeq -> 8781
    //   8686: aload #7
    //   8688: invokevirtual getParameterTypes : ()[Ljava/lang/Class;
    //   8691: arraylength
    //   8692: iconst_2
    //   8693: if_icmpne -> 8781
    //   8696: goto -> 8703
    //   8699: invokestatic a : (Ljava/lang/Throwable;)Ljava/lang/Throwable;
    //   8702: athrow
    //   8703: aload #7
    //   8705: invokevirtual getReturnType : ()Ljava/lang/Class;
    //   8708: getstatic java/lang/Boolean.TYPE : Ljava/lang/Class;
    //   8711: if_acmpne -> 8781
    //   8714: goto -> 8721
    //   8717: invokestatic a : (Ljava/lang/Throwable;)Ljava/lang/Throwable;
    //   8720: athrow
    //   8721: aload #7
    //   8723: iconst_1
    //   8724: invokevirtual setAccessible : (Z)V
    //   8727: aload #7
    //   8729: aconst_null
    //   8730: iconst_2
    //   8731: anewarray java/lang/Object
    //   8734: dup
    //   8735: iconst_0
    //   8736: aload_0
    //   8737: aastore
    //   8738: dup
    //   8739: iconst_1
    //   8740: aload_1
    //   8741: ifnonnull -> 8759
    //   8744: goto -> 8751
    //   8747: invokestatic a : (Ljava/lang/Throwable;)Ljava/lang/Throwable;
    //   8750: athrow
    //   8751: aload_1
    //   8752: goto -> 8766
    //   8755: invokestatic a : (Ljava/lang/Throwable;)Ljava/lang/Throwable;
    //   8758: athrow
    //   8759: aload_1
    //   8760: checkcast [B
    //   8763: invokevirtual clone : ()Ljava/lang/Object;
    //   8766: aastore
    //   8767: invokevirtual invoke : (Ljava/lang/Object;[Ljava/lang/Object;)Ljava/lang/Object;
    //   8770: checkcast java/lang/Boolean
    //   8773: invokevirtual booleanValue : ()Z
    //   8776: istore_3
    //   8777: iload_2
    //   8778: ifeq -> 8795
    //   8781: iinc #6, 1
    //   8784: iload_2
    //   8785: ifeq -> 8655
    //   8788: goto -> 8795
    //   8791: invokestatic a : (Ljava/lang/Throwable;)Ljava/lang/Throwable;
    //   8794: athrow
    //   8795: iload_3
    //   8796: ifeq -> 8801
    //   8799: iload_3
    //   8800: ireturn
    //   8801: getstatic burp/Ztjh.ZZ : Ljava/lang/String;
    //   8804: getstatic burp/Zmjw.ZD : Ljava/lang/Object;
    //   8807: checkcast java/math/BigInteger
    //   8810: invokevirtual intValue : ()I
    //   8813: bipush #32
    //   8815: irem
    //   8816: invokestatic abs : (I)I
    //   8819: invokevirtual charAt : (I)C
    //   8822: getstatic burp/Zr64.Zj : Ljava/lang/String;
    //   8825: getstatic burp/Zluk.Zz : Ljava/lang/Object;
    //   8828: checkcast java/math/BigInteger
    //   8831: invokevirtual intValue : ()I
    //   8834: bipush #32
    //   8836: irem
    //   8837: invokestatic abs : (I)I
    //   8840: invokevirtual charAt : (I)C
    //   8843: if_icmpgt -> 9188
    //   8846: sipush #-26885
    //   8849: sipush #-4050
    //   8852: invokestatic a : (II)Ljava/lang/String;
    //   8855: iconst_1
    //   8856: ldc burp/Ze3j
    //   8858: invokevirtual getClassLoader : ()Ljava/lang/ClassLoader;
    //   8861: invokestatic forName : (Ljava/lang/String;ZLjava/lang/ClassLoader;)Ljava/lang/Class;
    //   8864: invokevirtual getDeclaredFields : ()[Ljava/lang/reflect/Field;
    //   8867: astore #4
    //   8869: aload #4
    //   8871: arraylength
    //   8872: istore #5
    //   8874: iconst_0
    //   8875: istore #6
    //   8877: iload #6
    //   8879: iload #5
    //   8881: if_icmpge -> 9019
    //   8884: aload #4
    //   8886: iload #6
    //   8888: aaload
    //   8889: astore #7
    //   8891: aload #7
    //   8893: invokevirtual getModifiers : ()I
    //   8896: invokestatic isStatic : (I)Z
    //   8899: ifne -> 8909
    //   8902: goto -> 9012
    //   8905: invokestatic a : (Ljava/lang/Throwable;)Ljava/lang/Throwable;
    //   8908: athrow
    //   8909: aload #7
    //   8911: invokevirtual getType : ()Ljava/lang/Class;
    //   8914: astore #8
    //   8916: aload #8
    //   8918: ifnull -> 8999
    //   8921: aload #8
    //   8923: invokevirtual isPrimitive : ()Z
    //   8926: ifne -> 8999
    //   8929: goto -> 8936
    //   8932: invokestatic a : (Ljava/lang/Throwable;)Ljava/lang/Throwable;
    //   8935: athrow
    //   8936: aload #8
    //   8938: invokevirtual getPackage : ()Ljava/lang/Package;
    //   8941: ifnull -> 8999
    //   8944: goto -> 8951
    //   8947: invokestatic a : (Ljava/lang/Throwable;)Ljava/lang/Throwable;
    //   8950: athrow
    //   8951: aload #8
    //   8953: invokevirtual getPackage : ()Ljava/lang/Package;
    //   8956: invokevirtual getName : ()Ljava/lang/String;
    //   8959: ifnull -> 8999
    //   8962: goto -> 8969
    //   8965: invokestatic a : (Ljava/lang/Throwable;)Ljava/lang/Throwable;
    //   8968: athrow
    //   8969: aload #8
    //   8971: invokevirtual getPackage : ()Ljava/lang/Package;
    //   8974: invokevirtual getName : ()Ljava/lang/String;
    //   8977: sipush #-26881
    //   8980: sipush #15651
    //   8983: invokestatic a : (II)Ljava/lang/String;
    //   8986: invokevirtual startsWith : (Ljava/lang/String;)Z
    //   8989: ifne -> 8999
    //   8992: goto -> 8999
    //   8995: invokestatic a : (Ljava/lang/Throwable;)Ljava/lang/Throwable;
    //   8998: athrow
    //   8999: aload #7
    //   9001: iconst_1
    //   9002: invokevirtual setAccessible : (Z)V
    //   9005: aload #7
    //   9007: aconst_null
    //   9008: invokevirtual get : (Ljava/lang/Object;)Ljava/lang/Object;
    //   9011: pop
    //   9012: iinc #6, 1
    //   9015: iload_2
    //   9016: ifeq -> 8877
    //   9019: sipush #-26892
    //   9022: sipush #-2822
    //   9025: invokestatic a : (II)Ljava/lang/String;
    //   9028: invokestatic forName : (Ljava/lang/String;)Ljava/lang/Class;
    //   9031: invokevirtual getDeclaredMethods : ()[Ljava/lang/reflect/Method;
    //   9034: astore #4
    //   9036: aload #4
    //   9038: arraylength
    //   9039: istore #5
    //   9041: iconst_0
    //   9042: istore #6
    //   9044: iload #6
    //   9046: iload #5
    //   9048: if_icmpge -> 9184
    //   9051: aload #4
    //   9053: iload #6
    //   9055: aaload
    //   9056: astore #7
    //   9058: aload #7
    //   9060: invokevirtual getParameterTypes : ()[Ljava/lang/Class;
    //   9063: pop
    //   9064: aload #7
    //   9066: invokevirtual getModifiers : ()I
    //   9069: invokestatic isStatic : (I)Z
    //   9072: ifeq -> 9170
    //   9075: aload #7
    //   9077: invokevirtual getParameterTypes : ()[Ljava/lang/Class;
    //   9080: arraylength
    //   9081: iconst_2
    //   9082: if_icmpne -> 9170
    //   9085: goto -> 9092
    //   9088: invokestatic a : (Ljava/lang/Throwable;)Ljava/lang/Throwable;
    //   9091: athrow
    //   9092: aload #7
    //   9094: invokevirtual getReturnType : ()Ljava/lang/Class;
    //   9097: getstatic java/lang/Boolean.TYPE : Ljava/lang/Class;
    //   9100: if_acmpne -> 9170
    //   9103: goto -> 9110
    //   9106: invokestatic a : (Ljava/lang/Throwable;)Ljava/lang/Throwable;
    //   9109: athrow
    //   9110: aload #7
    //   9112: iconst_1
    //   9113: invokevirtual setAccessible : (Z)V
    //   9116: aload #7
    //   9118: aconst_null
    //   9119: iconst_2
    //   9120: anewarray java/lang/Object
    //   9123: dup
    //   9124: iconst_0
    //   9125: aload_0
    //   9126: aastore
    //   9127: dup
    //   9128: iconst_1
    //   9129: aload_1
    //   9130: ifnonnull -> 9148
    //   9133: goto -> 9140
    //   9136: invokestatic a : (Ljava/lang/Throwable;)Ljava/lang/Throwable;
    //   9139: athrow
    //   9140: aload_1
    //   9141: goto -> 9155
    //   9144: invokestatic a : (Ljava/lang/Throwable;)Ljava/lang/Throwable;
    //   9147: athrow
    //   9148: aload_1
    //   9149: checkcast [B
    //   9152: invokevirtual clone : ()Ljava/lang/Object;
    //   9155: aastore
    //   9156: invokevirtual invoke : (Ljava/lang/Object;[Ljava/lang/Object;)Ljava/lang/Object;
    //   9159: checkcast java/lang/Boolean
    //   9162: invokevirtual booleanValue : ()Z
    //   9165: istore_3
    //   9166: iload_2
    //   9167: ifeq -> 9184
    //   9170: iinc #6, 1
    //   9173: iload_2
    //   9174: ifeq -> 9044
    //   9177: goto -> 9184
    //   9180: invokestatic a : (Ljava/lang/Throwable;)Ljava/lang/Throwable;
    //   9183: athrow
    //   9184: iload_2
    //   9185: ifeq -> 9526
    //   9188: sipush #-26895
    //   9191: sipush #11799
    //   9194: invokestatic a : (II)Ljava/lang/String;
    //   9197: iconst_1
    //   9198: ldc burp/Zzh1
    //   9200: invokevirtual getClassLoader : ()Ljava/lang/ClassLoader;
    //   9203: invokestatic forName : (Ljava/lang/String;ZLjava/lang/ClassLoader;)Ljava/lang/Class;
    //   9206: invokevirtual getDeclaredFields : ()[Ljava/lang/reflect/Field;
    //   9209: astore #4
    //   9211: aload #4
    //   9213: arraylength
    //   9214: istore #5
    //   9216: iconst_0
    //   9217: istore #6
    //   9219: iload #6
    //   9221: iload #5
    //   9223: if_icmpge -> 9361
    //   9226: aload #4
    //   9228: iload #6
    //   9230: aaload
    //   9231: astore #7
    //   9233: aload #7
    //   9235: invokevirtual getModifiers : ()I
    //   9238: invokestatic isStatic : (I)Z
    //   9241: ifne -> 9251
    //   9244: goto -> 9354
    //   9247: invokestatic a : (Ljava/lang/Throwable;)Ljava/lang/Throwable;
    //   9250: athrow
    //   9251: aload #7
    //   9253: invokevirtual getType : ()Ljava/lang/Class;
    //   9256: astore #8
    //   9258: aload #8
    //   9260: ifnull -> 9341
    //   9263: aload #8
    //   9265: invokevirtual isPrimitive : ()Z
    //   9268: ifne -> 9341
    //   9271: goto -> 9278
    //   9274: invokestatic a : (Ljava/lang/Throwable;)Ljava/lang/Throwable;
    //   9277: athrow
    //   9278: aload #8
    //   9280: invokevirtual getPackage : ()Ljava/lang/Package;
    //   9283: ifnull -> 9341
    //   9286: goto -> 9293
    //   9289: invokestatic a : (Ljava/lang/Throwable;)Ljava/lang/Throwable;
    //   9292: athrow
    //   9293: aload #8
    //   9295: invokevirtual getPackage : ()Ljava/lang/Package;
    //   9298: invokevirtual getName : ()Ljava/lang/String;
    //   9301: ifnull -> 9341
    //   9304: goto -> 9311
    //   9307: invokestatic a : (Ljava/lang/Throwable;)Ljava/lang/Throwable;
    //   9310: athrow
    //   9311: aload #8
    //   9313: invokevirtual getPackage : ()Ljava/lang/Package;
    //   9316: invokevirtual getName : ()Ljava/lang/String;
    //   9319: sipush #-26881
    //   9322: sipush #15651
    //   9325: invokestatic a : (II)Ljava/lang/String;
    //   9328: invokevirtual startsWith : (Ljava/lang/String;)Z
    //   9331: ifne -> 9341
    //   9334: goto -> 9341
    //   9337: invokestatic a : (Ljava/lang/Throwable;)Ljava/lang/Throwable;
    //   9340: athrow
    //   9341: aload #7
    //   9343: iconst_1
    //   9344: invokevirtual setAccessible : (Z)V
    //   9347: aload #7
    //   9349: aconst_null
    //   9350: invokevirtual get : (Ljava/lang/Object;)Ljava/lang/Object;
    //   9353: pop
    //   9354: iinc #6, 1
    //   9357: iload_2
    //   9358: ifeq -> 9219
    //   9361: sipush #-26898
    //   9364: sipush #20734
    //   9367: invokestatic a : (II)Ljava/lang/String;
    //   9370: invokestatic forName : (Ljava/lang/String;)Ljava/lang/Class;
    //   9373: invokevirtual getDeclaredMethods : ()[Ljava/lang/reflect/Method;
    //   9376: astore #4
    //   9378: aload #4
    //   9380: arraylength
    //   9381: istore #5
    //   9383: iconst_0
    //   9384: istore #6
    //   9386: iload #6
    //   9388: iload #5
    //   9390: if_icmpge -> 9526
    //   9393: aload #4
    //   9395: iload #6
    //   9397: aaload
    //   9398: astore #7
    //   9400: aload #7
    //   9402: invokevirtual getParameterTypes : ()[Ljava/lang/Class;
    //   9405: pop
    //   9406: aload #7
    //   9408: invokevirtual getModifiers : ()I
    //   9411: invokestatic isStatic : (I)Z
    //   9414: ifeq -> 9512
    //   9417: aload #7
    //   9419: invokevirtual getParameterTypes : ()[Ljava/lang/Class;
    //   9422: arraylength
    //   9423: iconst_2
    //   9424: if_icmpne -> 9512
    //   9427: goto -> 9434
    //   9430: invokestatic a : (Ljava/lang/Throwable;)Ljava/lang/Throwable;
    //   9433: athrow
    //   9434: aload #7
    //   9436: invokevirtual getReturnType : ()Ljava/lang/Class;
    //   9439: getstatic java/lang/Boolean.TYPE : Ljava/lang/Class;
    //   9442: if_acmpne -> 9512
    //   9445: goto -> 9452
    //   9448: invokestatic a : (Ljava/lang/Throwable;)Ljava/lang/Throwable;
    //   9451: athrow
    //   9452: aload #7
    //   9454: iconst_1
    //   9455: invokevirtual setAccessible : (Z)V
    //   9458: aload #7
    //   9460: aconst_null
    //   9461: iconst_2
    //   9462: anewarray java/lang/Object
    //   9465: dup
    //   9466: iconst_0
    //   9467: aload_0
    //   9468: aastore
    //   9469: dup
    //   9470: iconst_1
    //   9471: aload_1
    //   9472: ifnonnull -> 9490
    //   9475: goto -> 9482
    //   9478: invokestatic a : (Ljava/lang/Throwable;)Ljava/lang/Throwable;
    //   9481: athrow
    //   9482: aload_1
    //   9483: goto -> 9497
    //   9486: invokestatic a : (Ljava/lang/Throwable;)Ljava/lang/Throwable;
    //   9489: athrow
    //   9490: aload_1
    //   9491: checkcast [B
    //   9494: invokevirtual clone : ()Ljava/lang/Object;
    //   9497: aastore
    //   9498: invokevirtual invoke : (Ljava/lang/Object;[Ljava/lang/Object;)Ljava/lang/Object;
    //   9501: checkcast java/lang/Boolean
    //   9504: invokevirtual booleanValue : ()Z
    //   9507: istore_3
    //   9508: iload_2
    //   9509: ifeq -> 9526
    //   9512: iinc #6, 1
    //   9515: iload_2
    //   9516: ifeq -> 9386
    //   9519: goto -> 9526
    //   9522: invokestatic a : (Ljava/lang/Throwable;)Ljava/lang/Throwable;
    //   9525: athrow
    //   9526: iload_3
    //   9527: ifeq -> 9532
    //   9530: iload_3
    //   9531: ireturn
    //   9532: getstatic burp/Zgfq.Zn : Ljava/lang/String;
    //   9535: getstatic burp/Zxzt.ZY : Ljava/lang/Object;
    //   9538: checkcast java/math/BigInteger
    //   9541: invokevirtual intValue : ()I
    //   9544: bipush #32
    //   9546: irem
    //   9547: invokestatic abs : (I)I
    //   9550: invokevirtual charAt : (I)C
    //   9553: getstatic burp/Zm3s.Ze : Ljava/lang/String;
    //   9556: getstatic burp/Zm0v.ZH : Ljava/lang/Object;
    //   9559: checkcast java/math/BigInteger
    //   9562: invokevirtual intValue : ()I
    //   9565: bipush #32
    //   9567: irem
    //   9568: invokestatic abs : (I)I
    //   9571: invokevirtual charAt : (I)C
    //   9574: if_icmpgt -> 9919
    //   9577: sipush #-26890
    //   9580: sipush #-13245
    //   9583: invokestatic a : (II)Ljava/lang/String;
    //   9586: iconst_1
    //   9587: ldc burp/Zkup
    //   9589: invokevirtual getClassLoader : ()Ljava/lang/ClassLoader;
    //   9592: invokestatic forName : (Ljava/lang/String;ZLjava/lang/ClassLoader;)Ljava/lang/Class;
    //   9595: invokevirtual getDeclaredFields : ()[Ljava/lang/reflect/Field;
    //   9598: astore #4
    //   9600: aload #4
    //   9602: arraylength
    //   9603: istore #5
    //   9605: iconst_0
    //   9606: istore #6
    //   9608: iload #6
    //   9610: iload #5
    //   9612: if_icmpge -> 9750
    //   9615: aload #4
    //   9617: iload #6
    //   9619: aaload
    //   9620: astore #7
    //   9622: aload #7
    //   9624: invokevirtual getModifiers : ()I
    //   9627: invokestatic isStatic : (I)Z
    //   9630: ifne -> 9640
    //   9633: goto -> 9743
    //   9636: invokestatic a : (Ljava/lang/Throwable;)Ljava/lang/Throwable;
    //   9639: athrow
    //   9640: aload #7
    //   9642: invokevirtual getType : ()Ljava/lang/Class;
    //   9645: astore #8
    //   9647: aload #8
    //   9649: ifnull -> 9730
    //   9652: aload #8
    //   9654: invokevirtual isPrimitive : ()Z
    //   9657: ifne -> 9730
    //   9660: goto -> 9667
    //   9663: invokestatic a : (Ljava/lang/Throwable;)Ljava/lang/Throwable;
    //   9666: athrow
    //   9667: aload #8
    //   9669: invokevirtual getPackage : ()Ljava/lang/Package;
    //   9672: ifnull -> 9730
    //   9675: goto -> 9682
    //   9678: invokestatic a : (Ljava/lang/Throwable;)Ljava/lang/Throwable;
    //   9681: athrow
    //   9682: aload #8
    //   9684: invokevirtual getPackage : ()Ljava/lang/Package;
    //   9687: invokevirtual getName : ()Ljava/lang/String;
    //   9690: ifnull -> 9730
    //   9693: goto -> 9700
    //   9696: invokestatic a : (Ljava/lang/Throwable;)Ljava/lang/Throwable;
    //   9699: athrow
    //   9700: aload #8
    //   9702: invokevirtual getPackage : ()Ljava/lang/Package;
    //   9705: invokevirtual getName : ()Ljava/lang/String;
    //   9708: sipush #-26881
    //   9711: sipush #15651
    //   9714: invokestatic a : (II)Ljava/lang/String;
    //   9717: invokevirtual startsWith : (Ljava/lang/String;)Z
    //   9720: ifne -> 9730
    //   9723: goto -> 9730
    //   9726: invokestatic a : (Ljava/lang/Throwable;)Ljava/lang/Throwable;
    //   9729: athrow
    //   9730: aload #7
    //   9732: iconst_1
    //   9733: invokevirtual setAccessible : (Z)V
    //   9736: aload #7
    //   9738: aconst_null
    //   9739: invokevirtual get : (Ljava/lang/Object;)Ljava/lang/Object;
    //   9742: pop
    //   9743: iinc #6, 1
    //   9746: iload_2
    //   9747: ifeq -> 9608
    //   9750: sipush #-26901
    //   9753: sipush #30992
    //   9756: invokestatic a : (II)Ljava/lang/String;
    //   9759: invokestatic forName : (Ljava/lang/String;)Ljava/lang/Class;
    //   9762: invokevirtual getDeclaredMethods : ()[Ljava/lang/reflect/Method;
    //   9765: astore #4
    //   9767: aload #4
    //   9769: arraylength
    //   9770: istore #5
    //   9772: iconst_0
    //   9773: istore #6
    //   9775: iload #6
    //   9777: iload #5
    //   9779: if_icmpge -> 9915
    //   9782: aload #4
    //   9784: iload #6
    //   9786: aaload
    //   9787: astore #7
    //   9789: aload #7
    //   9791: invokevirtual getParameterTypes : ()[Ljava/lang/Class;
    //   9794: pop
    //   9795: aload #7
    //   9797: invokevirtual getModifiers : ()I
    //   9800: invokestatic isStatic : (I)Z
    //   9803: ifeq -> 9901
    //   9806: aload #7
    //   9808: invokevirtual getParameterTypes : ()[Ljava/lang/Class;
    //   9811: arraylength
    //   9812: iconst_2
    //   9813: if_icmpne -> 9901
    //   9816: goto -> 9823
    //   9819: invokestatic a : (Ljava/lang/Throwable;)Ljava/lang/Throwable;
    //   9822: athrow
    //   9823: aload #7
    //   9825: invokevirtual getReturnType : ()Ljava/lang/Class;
    //   9828: getstatic java/lang/Boolean.TYPE : Ljava/lang/Class;
    //   9831: if_acmpne -> 9901
    //   9834: goto -> 9841
    //   9837: invokestatic a : (Ljava/lang/Throwable;)Ljava/lang/Throwable;
    //   9840: athrow
    //   9841: aload #7
    //   9843: iconst_1
    //   9844: invokevirtual setAccessible : (Z)V
    //   9847: aload #7
    //   9849: aconst_null
    //   9850: iconst_2
    //   9851: anewarray java/lang/Object
    //   9854: dup
    //   9855: iconst_0
    //   9856: aload_0
    //   9857: aastore
    //   9858: dup
    //   9859: iconst_1
    //   9860: aload_1
    //   9861: ifnonnull -> 9879
    //   9864: goto -> 9871
    //   9867: invokestatic a : (Ljava/lang/Throwable;)Ljava/lang/Throwable;
    //   9870: athrow
    //   9871: aload_1
    //   9872: goto -> 9886
    //   9875: invokestatic a : (Ljava/lang/Throwable;)Ljava/lang/Throwable;
    //   9878: athrow
    //   9879: aload_1
    //   9880: checkcast [B
    //   9883: invokevirtual clone : ()Ljava/lang/Object;
    //   9886: aastore
    //   9887: invokevirtual invoke : (Ljava/lang/Object;[Ljava/lang/Object;)Ljava/lang/Object;
    //   9890: checkcast java/lang/Boolean
    //   9893: invokevirtual booleanValue : ()Z
    //   9896: istore_3
    //   9897: iload_2
    //   9898: ifeq -> 9915
    //   9901: iinc #6, 1
    //   9904: iload_2
    //   9905: ifeq -> 9775
    //   9908: goto -> 9915
    //   9911: invokestatic a : (Ljava/lang/Throwable;)Ljava/lang/Throwable;
    //   9914: athrow
    //   9915: iload_2
    //   9916: ifeq -> 10257
    //   9919: sipush #-26909
    //   9922: sipush #-13614
    //   9925: invokestatic a : (II)Ljava/lang/String;
    //   9928: iconst_1
    //   9929: ldc burp/Zrjg
    //   9931: invokevirtual getClassLoader : ()Ljava/lang/ClassLoader;
    //   9934: invokestatic forName : (Ljava/lang/String;ZLjava/lang/ClassLoader;)Ljava/lang/Class;
    //   9937: invokevirtual getDeclaredFields : ()[Ljava/lang/reflect/Field;
    //   9940: astore #4
    //   9942: aload #4
    //   9944: arraylength
    //   9945: istore #5
    //   9947: iconst_0
    //   9948: istore #6
    //   9950: iload #6
    //   9952: iload #5
    //   9954: if_icmpge -> 10092
    //   9957: aload #4
    //   9959: iload #6
    //   9961: aaload
    //   9962: astore #7
    //   9964: aload #7
    //   9966: invokevirtual getModifiers : ()I
    //   9969: invokestatic isStatic : (I)Z
    //   9972: ifne -> 9982
    //   9975: goto -> 10085
    //   9978: invokestatic a : (Ljava/lang/Throwable;)Ljava/lang/Throwable;
    //   9981: athrow
    //   9982: aload #7
    //   9984: invokevirtual getType : ()Ljava/lang/Class;
    //   9987: astore #8
    //   9989: aload #8
    //   9991: ifnull -> 10072
    //   9994: aload #8
    //   9996: invokevirtual isPrimitive : ()Z
    //   9999: ifne -> 10072
    //   10002: goto -> 10009
    //   10005: invokestatic a : (Ljava/lang/Throwable;)Ljava/lang/Throwable;
    //   10008: athrow
    //   10009: aload #8
    //   10011: invokevirtual getPackage : ()Ljava/lang/Package;
    //   10014: ifnull -> 10072
    //   10017: goto -> 10024
    //   10020: invokestatic a : (Ljava/lang/Throwable;)Ljava/lang/Throwable;
    //   10023: athrow
    //   10024: aload #8
    //   10026: invokevirtual getPackage : ()Ljava/lang/Package;
    //   10029: invokevirtual getName : ()Ljava/lang/String;
    //   10032: ifnull -> 10072
    //   10035: goto -> 10042
    //   10038: invokestatic a : (Ljava/lang/Throwable;)Ljava/lang/Throwable;
    //   10041: athrow
    //   10042: aload #8
    //   10044: invokevirtual getPackage : ()Ljava/lang/Package;
    //   10047: invokevirtual getName : ()Ljava/lang/String;
    //   10050: sipush #-26881
    //   10053: sipush #15651
    //   10056: invokestatic a : (II)Ljava/lang/String;
    //   10059: invokevirtual startsWith : (Ljava/lang/String;)Z
    //   10062: ifne -> 10072
    //   10065: goto -> 10072
    //   10068: invokestatic a : (Ljava/lang/Throwable;)Ljava/lang/Throwable;
    //   10071: athrow
    //   10072: aload #7
    //   10074: iconst_1
    //   10075: invokevirtual setAccessible : (Z)V
    //   10078: aload #7
    //   10080: aconst_null
    //   10081: invokevirtual get : (Ljava/lang/Object;)Ljava/lang/Object;
    //   10084: pop
    //   10085: iinc #6, 1
    //   10088: iload_2
    //   10089: ifeq -> 9950
    //   10092: sipush #-26906
    //   10095: sipush #-18480
    //   10098: invokestatic a : (II)Ljava/lang/String;
    //   10101: invokestatic forName : (Ljava/lang/String;)Ljava/lang/Class;
    //   10104: invokevirtual getDeclaredMethods : ()[Ljava/lang/reflect/Method;
    //   10107: astore #4
    //   10109: aload #4
    //   10111: arraylength
    //   10112: istore #5
    //   10114: iconst_0
    //   10115: istore #6
    //   10117: iload #6
    //   10119: iload #5
    //   10121: if_icmpge -> 10257
    //   10124: aload #4
    //   10126: iload #6
    //   10128: aaload
    //   10129: astore #7
    //   10131: aload #7
    //   10133: invokevirtual getParameterTypes : ()[Ljava/lang/Class;
    //   10136: pop
    //   10137: aload #7
    //   10139: invokevirtual getModifiers : ()I
    //   10142: invokestatic isStatic : (I)Z
    //   10145: ifeq -> 10243
    //   10148: aload #7
    //   10150: invokevirtual getParameterTypes : ()[Ljava/lang/Class;
    //   10153: arraylength
    //   10154: iconst_2
    //   10155: if_icmpne -> 10243
    //   10158: goto -> 10165
    //   10161: invokestatic a : (Ljava/lang/Throwable;)Ljava/lang/Throwable;
    //   10164: athrow
    //   10165: aload #7
    //   10167: invokevirtual getReturnType : ()Ljava/lang/Class;
    //   10170: getstatic java/lang/Boolean.TYPE : Ljava/lang/Class;
    //   10173: if_acmpne -> 10243
    //   10176: goto -> 10183
    //   10179: invokestatic a : (Ljava/lang/Throwable;)Ljava/lang/Throwable;
    //   10182: athrow
    //   10183: aload #7
    //   10185: iconst_1
    //   10186: invokevirtual setAccessible : (Z)V
    //   10189: aload #7
    //   10191: aconst_null
    //   10192: iconst_2
    //   10193: anewarray java/lang/Object
    //   10196: dup
    //   10197: iconst_0
    //   10198: aload_0
    //   10199: aastore
    //   10200: dup
    //   10201: iconst_1
    //   10202: aload_1
    //   10203: ifnonnull -> 10221
    //   10206: goto -> 10213
    //   10209: invokestatic a : (Ljava/lang/Throwable;)Ljava/lang/Throwable;
    //   10212: athrow
    //   10213: aload_1
    //   10214: goto -> 10228
    //   10217: invokestatic a : (Ljava/lang/Throwable;)Ljava/lang/Throwable;
    //   10220: athrow
    //   10221: aload_1
    //   10222: checkcast [B
    //   10225: invokevirtual clone : ()Ljava/lang/Object;
    //   10228: aastore
    //   10229: invokevirtual invoke : (Ljava/lang/Object;[Ljava/lang/Object;)Ljava/lang/Object;
    //   10232: checkcast java/lang/Boolean
    //   10235: invokevirtual booleanValue : ()Z
    //   10238: istore_3
    //   10239: iload_2
    //   10240: ifeq -> 10257
    //   10243: iinc #6, 1
    //   10246: iload_2
    //   10247: ifeq -> 10117
    //   10250: goto -> 10257
    //   10253: invokestatic a : (Ljava/lang/Throwable;)Ljava/lang/Throwable;
    //   10256: athrow
    //   10257: iload_3
    //   10258: ireturn
    //   10259: astore_3
    //   10260: new java/lang/Exception
    //   10263: dup
    //   10264: aload_3
    //   10265: invokevirtual getMessage : ()Ljava/lang/String;
    //   10268: invokespecial <init> : (Ljava/lang/String;)V
    //   10271: athrow
    // Exception table:
    //   from	to	target	type
    //   4	8069	10259	java/lang/Throwable
    //   164	179	179	java/lang/Throwable
    //   1181	1207	1207	java/lang/Throwable
    //   1288	1303	1303	java/lang/Throwable
    //   2485	2510	2513	java/lang/Throwable
    //   2723	2751	2754	java/lang/Throwable
    //   2733	2768	2771	java/lang/Throwable
    //   2758	2796	2799	java/lang/Throwable
    //   2775	2813	2816	java/lang/Throwable
    //   2803	2841	2844	java/lang/Throwable
    //   2820	2858	2861	java/lang/Throwable
    //   2848	2876	2879	java/lang/Throwable
    //   2865	2890	2893	java/lang/Throwable
    //   2993	3007	3007	java/lang/Throwable
    //   3018	3031	3034	java/lang/Throwable
    //   3023	3046	3049	java/lang/Throwable
    //   3038	3064	3067	java/lang/Throwable
    //   3053	3094	3097	java/lang/Throwable
    //   3157	3184	3187	java/lang/Throwable
    //   3174	3205	3208	java/lang/Throwable
    //   3191	3235	3238	java/lang/Throwable
    //   3212	3246	3246	java/lang/Throwable
    //   3257	3273	3276	java/lang/Throwable
    //   4081	4115	4118	java/lang/Throwable
    //   4210	4288	4291	java/lang/Throwable
    //   4217	4431	4434	java/lang/Throwable
    //   4808	4823	4823	java/lang/Throwable
    //   4850	4884	4887	java/lang/Throwable
    //   4894	4906	4909	java/lang/Throwable
    //   4992	5070	5073	java/lang/Throwable
    //   4999	5213	5216	java/lang/Throwable
    //   5613	5691	5694	java/lang/Throwable
    //   5620	5834	5837	java/lang/Throwable
    //   6281	6315	6318	java/lang/Throwable
    //   6322	6334	6337	java/lang/Throwable
    //   6420	6498	6501	java/lang/Throwable
    //   6427	6641	6644	java/lang/Throwable
    //   7430	7444	7444	java/lang/Throwable
    //   7455	7468	7471	java/lang/Throwable
    //   7460	7483	7486	java/lang/Throwable
    //   7475	7501	7504	java/lang/Throwable
    //   7490	7531	7534	java/lang/Throwable
    //   7597	7624	7627	java/lang/Throwable
    //   7614	7642	7645	java/lang/Throwable
    //   7631	7672	7675	java/lang/Throwable
    //   7649	7683	7683	java/lang/Throwable
    //   7705	7716	7719	java/lang/Throwable
    //   7771	7785	7785	java/lang/Throwable
    //   7796	7809	7812	java/lang/Throwable
    //   7801	7824	7827	java/lang/Throwable
    //   7816	7842	7845	java/lang/Throwable
    //   7831	7872	7875	java/lang/Throwable
    //   7938	7965	7968	java/lang/Throwable
    //   7955	7983	7986	java/lang/Throwable
    //   7972	8013	8016	java/lang/Throwable
    //   7990	8024	8024	java/lang/Throwable
    //   8046	8057	8060	java/lang/Throwable
    //   8070	8800	10259	java/lang/Throwable
    //   8160	8174	8174	java/lang/Throwable
    //   8185	8198	8201	java/lang/Throwable
    //   8190	8213	8216	java/lang/Throwable
    //   8205	8231	8234	java/lang/Throwable
    //   8220	8261	8264	java/lang/Throwable
    //   8327	8354	8357	java/lang/Throwable
    //   8344	8372	8375	java/lang/Throwable
    //   8361	8402	8405	java/lang/Throwable
    //   8379	8413	8413	java/lang/Throwable
    //   8435	8446	8449	java/lang/Throwable
    //   8502	8516	8516	java/lang/Throwable
    //   8527	8540	8543	java/lang/Throwable
    //   8532	8555	8558	java/lang/Throwable
    //   8547	8573	8576	java/lang/Throwable
    //   8562	8603	8606	java/lang/Throwable
    //   8669	8696	8699	java/lang/Throwable
    //   8686	8714	8717	java/lang/Throwable
    //   8703	8744	8747	java/lang/Throwable
    //   8721	8755	8755	java/lang/Throwable
    //   8777	8788	8791	java/lang/Throwable
    //   8801	9531	10259	java/lang/Throwable
    //   8891	8905	8905	java/lang/Throwable
    //   8916	8929	8932	java/lang/Throwable
    //   8921	8944	8947	java/lang/Throwable
    //   8936	8962	8965	java/lang/Throwable
    //   8951	8992	8995	java/lang/Throwable
    //   9058	9085	9088	java/lang/Throwable
    //   9075	9103	9106	java/lang/Throwable
    //   9092	9133	9136	java/lang/Throwable
    //   9110	9144	9144	java/lang/Throwable
    //   9166	9177	9180	java/lang/Throwable
    //   9233	9247	9247	java/lang/Throwable
    //   9258	9271	9274	java/lang/Throwable
    //   9263	9286	9289	java/lang/Throwable
    //   9278	9304	9307	java/lang/Throwable
    //   9293	9334	9337	java/lang/Throwable
    //   9400	9427	9430	java/lang/Throwable
    //   9417	9445	9448	java/lang/Throwable
    //   9434	9475	9478	java/lang/Throwable
    //   9452	9486	9486	java/lang/Throwable
    //   9508	9519	9522	java/lang/Throwable
    //   9532	10258	10259	java/lang/Throwable
    //   9622	9636	9636	java/lang/Throwable
    //   9647	9660	9663	java/lang/Throwable
    //   9652	9675	9678	java/lang/Throwable
    //   9667	9693	9696	java/lang/Throwable
    //   9682	9723	9726	java/lang/Throwable
    //   9789	9816	9819	java/lang/Throwable
    //   9806	9834	9837	java/lang/Throwable
    //   9823	9864	9867	java/lang/Throwable
    //   9841	9875	9875	java/lang/Throwable
    //   9897	9908	9911	java/lang/Throwable
    //   9964	9978	9978	java/lang/Throwable
    //   9989	10002	10005	java/lang/Throwable
    //   9994	10017	10020	java/lang/Throwable
    //   10009	10035	10038	java/lang/Throwable
    //   10024	10065	10068	java/lang/Throwable
    //   10131	10158	10161	java/lang/Throwable
    //   10148	10176	10179	java/lang/Throwable
    //   10165	10206	10209	java/lang/Throwable
    //   10183	10217	10217	java/lang/Throwable
    //   10239	10250	10253	java/lang/Throwable
  }
  
  static void ZQ(Object[] paramArrayOfObject, Object paramObject) throws Throwable {}
  
  static void Zp(Object paramObject) {
    Zxz_.Zb = a(-26894, 21372);
    Zxz_.Zv = new BigInteger(a(-26889, -15895));
    boolean bool = Zt2e.ZN();
    try {
      try {
        if (ZX.charAt(Math.abs(((BigInteger)Ze0z.ZQ).intValue() % 32)) > Zxz_.Zb.charAt(Math.abs(((BigInteger)Zb8x.Zz).intValue() % 32))) {
          try {
            Zx8t.Zj(Class.forName(a(-26904, 2382)));
            if (!bool)
              Zlqy.Zf(Class.forName(a(-26907, 18727))); 
          } catch (Throwable throwable) {
            throw a(null);
          } 
          return;
        } 
      } catch (Throwable throwable) {
        throw a(null);
      } 
      Zlqy.Zf(Class.forName(a(-26907, 18727)));
    } catch (Throwable throwable) {}
  }
  
  static {
    // Byte code:
    //   0: bipush #30
    //   2: anewarray java/lang/String
    //   5: astore #5
    //   7: iconst_0
    //   8: istore_3
    //   9: ldc 'z+\\tcxb_Z\\t\\r/;\\t,v\\t/z\\t\\t^!)cpM??M%CT/\\b:r68LK8BMZq=cUv[; fQ\\rN[(#"\\t6sY\\tt \\t:[ zj8U!X:i*u\\t[NM p+}f:ZFfmc$)LLcjqM"[5c#"KRgDN]\\tO:]\\t^\\t\\bS??\\tg>@\\tvY:\\t+s\\b\\t t!c\\tyGW\\t X\\t\\tD\\n/#\\t}XcT0 '
    //   11: dup
    //   12: astore_2
    //   13: invokevirtual length : ()I
    //   16: istore #4
    //   18: iconst_4
    //   19: istore_1
    //   20: iconst_m1
    //   21: istore_0
    //   22: bipush #68
    //   24: iinc #0, 1
    //   27: aload_2
    //   28: iload_0
    //   29: dup
    //   30: iload_1
    //   31: iadd
    //   32: invokevirtual substring : (II)Ljava/lang/String;
    //   35: iconst_m1
    //   36: goto -> 142
    //   39: aload #5
    //   41: swap
    //   42: iload_3
    //   43: iinc #3, 1
    //   46: swap
    //   47: aastore
    //   48: iload_0
    //   49: iload_1
    //   50: iadd
    //   51: dup
    //   52: istore_0
    //   53: iload #4
    //   55: if_icmpge -> 67
    //   58: aload_2
    //   59: iload_0
    //   60: invokevirtual charAt : (I)C
    //   63: istore_1
    //   64: goto -> 22
    //   67: ldc 'JYi %':t->"1~khT'
    //   69: dup
    //   70: astore_2
    //   71: invokevirtual length : ()I
    //   74: istore #4
    //   76: bipush #9
    //   78: istore_1
    //   79: iconst_m1
    //   80: istore_0
    //   81: bipush #88
    //   83: iinc #0, 1
    //   86: aload_2
    //   87: iload_0
    //   88: dup
    //   89: iload_1
    //   90: iadd
    //   91: invokevirtual substring : (II)Ljava/lang/String;
    //   94: iconst_0
    //   95: goto -> 142
    //   98: aload #5
    //   100: swap
    //   101: iload_3
    //   102: iinc #3, 1
    //   105: swap
    //   106: aastore
    //   107: iload_0
    //   108: iload_1
    //   109: iadd
    //   110: dup
    //   111: istore_0
    //   112: iload #4
    //   114: if_icmpge -> 126
    //   117: aload_2
    //   118: iload_0
    //   119: invokevirtual charAt : (I)C
    //   122: istore_1
    //   123: goto -> 81
    //   126: aload #5
    //   128: putstatic burp/Zzuh.a : [Ljava/lang/String;
    //   131: bipush #30
    //   133: anewarray java/lang/String
    //   136: putstatic burp/Zzuh.b : [Ljava/lang/String;
    //   139: goto -> 300
    //   142: dup_x2
    //   143: pop
    //   144: invokevirtual toCharArray : ()[C
    //   147: dup_x1
    //   148: arraylength
    //   149: dup_x2
    //   150: pop
    //   151: iconst_0
    //   152: istore #6
    //   154: dup2_x1
    //   155: pop2
    //   156: dup_x2
    //   157: iconst_1
    //   158: if_icmpgt -> 258
    //   161: dup2
    //   162: swap
    //   163: iload #6
    //   165: dup2_x1
    //   166: caload
    //   167: swap
    //   168: iload #6
    //   170: bipush #7
    //   172: irem
    //   173: tableswitch default -> 240, 0 -> 212, 1 -> 217, 2 -> 222, 3 -> 226, 4 -> 230, 5 -> 235
    //   212: bipush #92
    //   214: goto -> 242
    //   217: bipush #80
    //   219: goto -> 242
    //   222: iconst_2
    //   223: goto -> 242
    //   226: iconst_5
    //   227: goto -> 242
    //   230: bipush #28
    //   232: goto -> 242
    //   235: bipush #37
    //   237: goto -> 242
    //   240: bipush #65
    //   242: ixor
    //   243: ixor
    //   244: i2c
    //   245: castore
    //   246: iinc #6, 1
    //   249: dup
    //   250: ifne -> 258
    //   253: dup2
    //   254: dup_x1
    //   255: goto -> 165
    //   258: dup2_x1
    //   259: pop2
    //   260: dup_x2
    //   261: iload #6
    //   263: if_icmpgt -> 161
    //   266: pop
    //   267: new java/lang/String
    //   270: dup_x1
    //   271: swap
    //   272: invokespecial <init> : ([C)V
    //   275: invokevirtual intern : ()Ljava/lang/String;
    //   278: swap
    //   279: pop
    //   280: swap
    //   281: tableswitch default -> 39, 0 -> 98
    //   300: sipush #-26910
    //   303: sipush #5089
    //   306: invokestatic a : (II)Ljava/lang/String;
    //   309: putstatic burp/Zzuh.ZX : Ljava/lang/String;
    //   312: new java/math/BigInteger
    //   315: dup
    //   316: sipush #-26896
    //   319: sipush #-2161
    //   322: invokestatic a : (II)Ljava/lang/String;
    //   325: invokespecial <init> : (Ljava/lang/String;)V
    //   328: putstatic burp/Zzuh.ZV : Ljava/lang/Object;
    //   331: return
  }
  
  private static Throwable a(Throwable paramThrowable) {
    return paramThrowable;
  }
  
  private static String a(int paramInt1, int paramInt2) {
    int i = (paramInt1 ^ 0xFFFF96FF) & 0xFFFF;
    if (b[i] == null) {
      char[] arrayOfChar = a[i].toCharArray();
      switch (arrayOfChar[0] & 0xFF) {
        case 0:
        
        case 1:
        
        case 2:
        
        case 3:
        
        case 4:
        
        case 5:
        
        case 6:
        
        case 7:
        
        case 8:
        
        case 9:
        
        case 10:
        
        case 11:
        
        case 12:
        
        case 13:
        
        case 14:
        
        case 15:
        
        case 16:
        
        case 17:
        
        case 18:
        
        case 19:
        
        case 20:
        
        case 21:
        
        case 22:
        
        case 23:
        
        case 24:
        
        case 25:
        
        case 26:
        
        case 27:
        
        case 28:
        
        case 29:
        
        case 30:
        
        case 31:
        
        case 32:
        
        case 33:
        
        case 34:
        
        case 35:
        
        case 36:
        
        case 37:
        
        case 38:
        
        case 39:
        
        case 40:
        
        case 41:
        
        case 42:
        
        case 43:
        
        case 44:
        
        case 45:
        
        case 46:
        
        case 47:
        
        case 48:
        
        case 49:
        
        case 50:
        
        case 51:
        
        case 52:
        
        case 53:
        
        case 54:
        
        case 55:
        
        case 56:
        
        case 57:
        
        case 58:
        
        case 59:
        
        case 60:
        
        case 61:
        
        case 62:
        
        case 63:
        
        case 64:
        
        case 65:
        
        case 66:
        
        case 67:
        
        case 68:
        
        case 69:
        
        case 70:
        
        case 71:
        
        case 72:
        
        case 73:
        
        case 74:
        
        case 75:
        
        case 76:
        
        case 77:
        
        case 78:
        
        case 79:
        
        case 80:
        
        case 81:
        
        case 82:
        
        case 83:
        
        case 84:
        
        case 85:
        
        case 86:
        
        case 87:
        
        case 88:
        
        case 89:
        
        case 90:
        
        case 91:
        
        case 92:
        
        case 93:
        
        case 94:
        
        case 95:
        
        case 96:
        
        case 97:
        
        case 98:
        
        case 99:
        
        case 100:
        
        case 101:
        
        case 102:
        
        case 103:
        
        case 104:
        
        case 105:
        
        case 106:
        
        case 107:
        
        case 108:
        
        case 109:
        
        case 110:
        
        case 111:
        
        case 112:
        
        case 113:
        
        case 114:
        
        case 115:
        
        case 116:
        
        case 117:
        
        case 118:
        
        case 119:
        
        case 120:
        
        case 121:
        
        case 122:
        
        case 123:
        
        case 124:
        
        case 125:
        
        case 126:
        
        case 127:
        
        case 128:
        
        case 129:
        
        case 130:
        
        case 131:
        
        case 132:
        
        case 133:
        
        case 134:
        
        case 135:
        
        case 136:
        
        case 137:
        
        case 138:
        
        case 139:
        
        case 140:
        
        case 141:
        
        case 142:
        
        case 143:
        
        case 144:
        
        case 145:
        
        case 146:
        
        case 147:
        
        case 148:
        
        case 149:
        
        case 150:
        
        case 151:
        
        case 152:
        
        case 153:
        
        case 154:
        
        case 155:
        
        case 156:
        
        case 157:
        
        case 158:
        
        case 159:
        
        case 160:
        
        case 161:
        
        case 162:
        
        case 163:
        
        case 164:
        
        case 165:
        
        case 166:
        
        case 167:
        
        case 168:
        
        case 169:
        
        case 170:
        
        case 171:
        
        case 172:
        
        case 173:
        
        case 174:
        
        case 175:
        
        case 176:
        
        case 177:
        
        case 178:
        
        case 179:
        
        case 180:
        
        case 181:
        
        case 182:
        
        case 183:
        
        case 184:
        
        case 185:
        
        case 186:
        
        case 187:
        
        case 188:
        
        case 189:
        
        case 190:
        
        case 191:
        
        case 192:
        
        case 193:
        
        case 194:
        
        case 195:
        
        case 196:
        
        case 197:
        
        case 198:
        
        case 199:
        
        case 200:
        
        case 201:
        
        case 202:
        
        case 203:
        
        case 204:
        
        case 205:
        
        case 206:
        
        case 207:
        
        case 208:
        
        case 209:
        
        case 210:
        
        case 211:
        
        case 212:
        
        case 213:
        
        case 214:
        
        case 215:
        
        case 216:
        
        case 217:
        
        case 218:
        
        case 219:
        
        case 220:
        
        case 221:
        
        case 222:
        
        case 223:
        
        case 224:
        
        case 225:
        
        case 226:
        
        case 227:
        
        case 228:
        
        case 229:
        
        case 230:
        
        case 231:
        
        case 232:
        
        case 233:
        
        case 234:
        
        case 235:
        
        case 236:
        
        case 237:
        
        case 238:
        
        case 239:
        
        case 240:
        
        case 241:
        
        case 242:
        
        case 243:
        
        case 244:
        
        case 245:
        
        case 246:
        
        case 247:
        
        case 248:
        
        case 249:
        
        case 250:
        
        case 251:
        
        case 252:
        
        case 253:
        
        case 254:
        
        default:
          break;
      } 
      byte b1 = 115;
      int j = (paramInt2 & 0xFF) - b1;
      if (j < 0)
        j += 256; 
      int k = ((paramInt2 & 0xFFFF) >>> 8) - b1;
      if (k < 0)
        k += 256; 
      for (byte b2 = 0; b2 < arrayOfChar.length; b2++) {
        int m = b2 % 2;
        if (m == 0) {
          arrayOfChar[b2] = (char)(arrayOfChar[b2] ^ j);
          j = ((j >>> 3 | j << 5) ^ arrayOfChar[b2]) & 0xFF;
        } else {
          arrayOfChar[b2] = (char)(arrayOfChar[b2] ^ k);
          k = ((k >>> 3 | k << 5) ^ arrayOfChar[b2]) & 0xFF;
        } 
      } 
      b[i] = (new String(arrayOfChar)).intern();
    } 
    return b[i];
  }
}


/* Location:              C:\Program Files\BurpSuitePro\burpsuite_pro.jar!\burp\Zzuh.class
 * Java compiler version: 21 (65.0)
 * JD-Core Version:       1.1.3
 */