package burp;

import java.math.BigInteger;

class Zzvr extends ClassLoader {
  static Object Z_;
  
  static String Zc;
  
  private static final String[] a;
  
  private static final String[] b;
  
  static void Ze(Object paramObject) {
    Zoa.ZF = a(-29404, -17357);
    Zoa.ZI = new BigInteger(a(-29386, -27749));
    boolean bool = Zt2e.ZN();
    try {
      try {
        if (Zmjr.Zc.charAt(Math.abs(((BigInteger)Zsgj.ZK).intValue() % 32)) <= Zeyt.ZS.charAt(Math.abs(((BigInteger)Zgii.ZD).intValue() % 32))) {
          try {
            Zldt.Zo(Class.forName(a(-29396, -18863)));
            if (!bool)
              Zls_.Zc(Class.forName(a(-29385, -25859))); 
          } catch (Throwable throwable) {
            throw a(null);
          } 
          return;
        } 
      } catch (Throwable throwable) {
        throw a(null);
      } 
      Zls_.Zc(Class.forName(a(-29385, -25859)));
    } catch (Throwable throwable) {}
  }
  
  static boolean ZI(Object[] paramArrayOfObject, Object paramObject) throws Throwable {
    // Byte code:
    //   0: invokestatic ZN : ()Z
    //   3: istore_2
    //   4: sipush #-29394
    //   7: sipush #25093
    //   10: invokestatic a : (II)Ljava/lang/String;
    //   13: invokestatic forName : (Ljava/lang/String;)Ljava/lang/Class;
    //   16: invokestatic Zq : (Ljava/lang/Object;)V
    //   19: getstatic burp/Zxn7.ZU : Ljava/lang/Object;
    //   22: checkcast java/math/BigInteger
    //   25: invokevirtual toByteArray : ()[B
    //   28: astore_3
    //   29: new java/lang/StringBuilder
    //   32: dup
    //   33: invokespecial <init> : ()V
    //   36: astore #5
    //   38: aload #5
    //   40: sipush #-29399
    //   43: sipush #-10475
    //   46: invokestatic a : (II)Ljava/lang/String;
    //   49: invokevirtual append : (Ljava/lang/String;)Ljava/lang/StringBuilder;
    //   52: pop
    //   53: aload_3
    //   54: astore #6
    //   56: aload #6
    //   58: arraylength
    //   59: istore #7
    //   61: iconst_0
    //   62: istore #8
    //   64: iload #8
    //   66: iload #7
    //   68: if_icmpge -> 94
    //   71: aload #6
    //   73: iload #8
    //   75: baload
    //   76: istore #9
    //   78: aload #5
    //   80: iload #9
    //   82: i2c
    //   83: invokevirtual append : (C)Ljava/lang/StringBuilder;
    //   86: pop
    //   87: iinc #8, 1
    //   90: iload_2
    //   91: ifne -> 64
    //   94: aload #5
    //   96: sipush #-29401
    //   99: sipush #-14351
    //   102: invokestatic a : (II)Ljava/lang/String;
    //   105: ldc ''
    //   107: invokestatic getProperty : (Ljava/lang/String;Ljava/lang/String;)Ljava/lang/String;
    //   110: invokevirtual toLowerCase : ()Ljava/lang/String;
    //   113: invokevirtual append : (Ljava/lang/String;)Ljava/lang/StringBuilder;
    //   116: pop
    //   117: aload #5
    //   119: sipush #-29393
    //   122: sipush #11459
    //   125: invokestatic a : (II)Ljava/lang/String;
    //   128: ldc ''
    //   130: invokestatic getProperty : (Ljava/lang/String;Ljava/lang/String;)Ljava/lang/String;
    //   133: invokevirtual toLowerCase : ()Ljava/lang/String;
    //   136: invokevirtual append : (Ljava/lang/String;)Ljava/lang/StringBuilder;
    //   139: pop
    //   140: aload #5
    //   142: invokevirtual toString : ()Ljava/lang/String;
    //   145: invokevirtual getBytes : ()[B
    //   148: astore #4
    //   150: aload #4
    //   152: astore_3
    //   153: aload_3
    //   154: arraylength
    //   155: bipush #8
    //   157: iadd
    //   158: bipush #6
    //   160: ishr
    //   161: iconst_1
    //   162: iadd
    //   163: bipush #16
    //   165: imul
    //   166: newarray int
    //   168: astore #5
    //   170: iconst_0
    //   171: istore #6
    //   173: iload #6
    //   175: aload_3
    //   176: arraylength
    //   177: if_icmpge -> 220
    //   180: aload_3
    //   181: iload #6
    //   183: baload
    //   184: sipush #255
    //   187: iand
    //   188: istore #7
    //   190: aload #5
    //   192: iload #6
    //   194: iconst_2
    //   195: ishr
    //   196: dup2
    //   197: iaload
    //   198: iload #7
    //   200: bipush #24
    //   202: iload #6
    //   204: iconst_4
    //   205: irem
    //   206: bipush #8
    //   208: imul
    //   209: isub
    //   210: ishl
    //   211: ior
    //   212: iastore
    //   213: iinc #6, 1
    //   216: iload_2
    //   217: ifne -> 173
    //   220: aload #5
    //   222: iload #6
    //   224: iconst_2
    //   225: ishr
    //   226: dup2
    //   227: iaload
    //   228: sipush #128
    //   231: bipush #24
    //   233: iload #6
    //   235: iconst_4
    //   236: irem
    //   237: bipush #8
    //   239: imul
    //   240: isub
    //   241: ishl
    //   242: ior
    //   243: iastore
    //   244: aload #5
    //   246: aload #5
    //   248: arraylength
    //   249: iconst_1
    //   250: isub
    //   251: aload_3
    //   252: arraylength
    //   253: bipush #8
    //   255: imul
    //   256: iastore
    //   257: bipush #80
    //   259: newarray int
    //   261: astore #7
    //   263: ldc 1732584193
    //   265: istore #8
    //   267: ldc -271733879
    //   269: istore #9
    //   271: ldc -1732584194
    //   273: istore #10
    //   275: ldc 271733878
    //   277: istore #11
    //   279: ldc -1009589776
    //   281: istore #12
    //   283: iconst_0
    //   284: istore #6
    //   286: iload #6
    //   288: aload #5
    //   290: arraylength
    //   291: if_icmpge -> 613
    //   294: iload #8
    //   296: istore #13
    //   298: iload #9
    //   300: istore #14
    //   302: iload #10
    //   304: istore #15
    //   306: iload #11
    //   308: istore #16
    //   310: iload #12
    //   312: istore #17
    //   314: iconst_0
    //   315: istore #18
    //   317: iload #18
    //   319: bipush #80
    //   321: if_icmpge -> 571
    //   324: iload #18
    //   326: bipush #16
    //   328: if_icmpge -> 355
    //   331: aload #7
    //   333: iload #18
    //   335: aload #5
    //   337: iload #6
    //   339: iload #18
    //   341: iadd
    //   342: iaload
    //   343: iastore
    //   344: iload_2
    //   345: ifne -> 410
    //   348: goto -> 355
    //   351: invokestatic a : (Ljava/lang/Throwable;)Ljava/lang/Throwable;
    //   354: athrow
    //   355: aload #7
    //   357: iload #18
    //   359: iconst_3
    //   360: isub
    //   361: iaload
    //   362: aload #7
    //   364: iload #18
    //   366: bipush #8
    //   368: isub
    //   369: iaload
    //   370: ixor
    //   371: aload #7
    //   373: iload #18
    //   375: bipush #14
    //   377: isub
    //   378: iaload
    //   379: ixor
    //   380: aload #7
    //   382: iload #18
    //   384: bipush #16
    //   386: isub
    //   387: iaload
    //   388: ixor
    //   389: istore #19
    //   391: iload #19
    //   393: iconst_1
    //   394: ishl
    //   395: iload #19
    //   397: bipush #31
    //   399: iushr
    //   400: ior
    //   401: istore #20
    //   403: aload #7
    //   405: iload #18
    //   407: iload #20
    //   409: iastore
    //   410: iload #8
    //   412: iconst_5
    //   413: ishl
    //   414: iload #8
    //   416: bipush #27
    //   418: iushr
    //   419: ior
    //   420: istore #19
    //   422: iload #19
    //   424: iload #12
    //   426: iadd
    //   427: aload #7
    //   429: iload #18
    //   431: iaload
    //   432: iadd
    //   433: iload #18
    //   435: bipush #20
    //   437: if_icmpge -> 463
    //   440: ldc 1518500249
    //   442: iload #9
    //   444: iload #10
    //   446: iand
    //   447: iload #9
    //   449: iconst_m1
    //   450: ixor
    //   451: iload #11
    //   453: iand
    //   454: ior
    //   455: iadd
    //   456: goto -> 533
    //   459: invokestatic a : (Ljava/lang/Throwable;)Ljava/lang/Throwable;
    //   462: athrow
    //   463: iload #18
    //   465: bipush #40
    //   467: if_icmpge -> 488
    //   470: ldc 1859775393
    //   472: iload #9
    //   474: iload #10
    //   476: ixor
    //   477: iload #11
    //   479: ixor
    //   480: iadd
    //   481: goto -> 533
    //   484: invokestatic a : (Ljava/lang/Throwable;)Ljava/lang/Throwable;
    //   487: athrow
    //   488: iload #18
    //   490: bipush #60
    //   492: if_icmpge -> 522
    //   495: ldc -1894007588
    //   497: iload #9
    //   499: iload #10
    //   501: iand
    //   502: iload #9
    //   504: iload #11
    //   506: iand
    //   507: ior
    //   508: iload #10
    //   510: iload #11
    //   512: iand
    //   513: ior
    //   514: iadd
    //   515: goto -> 533
    //   518: invokestatic a : (Ljava/lang/Throwable;)Ljava/lang/Throwable;
    //   521: athrow
    //   522: ldc -899497514
    //   524: iload #9
    //   526: iload #10
    //   528: ixor
    //   529: iload #11
    //   531: ixor
    //   532: iadd
    //   533: iadd
    //   534: istore #20
    //   536: iload #11
    //   538: istore #12
    //   540: iload #10
    //   542: istore #11
    //   544: iload #9
    //   546: bipush #30
    //   548: ishl
    //   549: iload #9
    //   551: iconst_2
    //   552: iushr
    //   553: ior
    //   554: istore #10
    //   556: iload #8
    //   558: istore #9
    //   560: iload #20
    //   562: istore #8
    //   564: iinc #18, 1
    //   567: iload_2
    //   568: ifne -> 317
    //   571: iload #8
    //   573: iload #13
    //   575: iadd
    //   576: istore #8
    //   578: iload #9
    //   580: iload #14
    //   582: iadd
    //   583: istore #9
    //   585: iload #10
    //   587: iload #15
    //   589: iadd
    //   590: istore #10
    //   592: iload #11
    //   594: iload #16
    //   596: iadd
    //   597: istore #11
    //   599: iload #12
    //   601: iload #17
    //   603: iadd
    //   604: istore #12
    //   606: iinc #6, 16
    //   609: iload_2
    //   610: ifne -> 286
    //   613: iconst_5
    //   614: newarray int
    //   616: dup
    //   617: iconst_0
    //   618: iload #8
    //   620: iastore
    //   621: dup
    //   622: iconst_1
    //   623: iload #9
    //   625: iastore
    //   626: dup
    //   627: iconst_2
    //   628: iload #10
    //   630: iastore
    //   631: dup
    //   632: iconst_3
    //   633: iload #11
    //   635: iastore
    //   636: dup
    //   637: iconst_4
    //   638: iload #12
    //   640: iastore
    //   641: astore #13
    //   643: bipush #20
    //   645: newarray byte
    //   647: astore #14
    //   649: iconst_0
    //   650: istore #15
    //   652: iload #15
    //   654: bipush #20
    //   656: if_icmpge -> 697
    //   659: aload #13
    //   661: iload #15
    //   663: iconst_4
    //   664: idiv
    //   665: iaload
    //   666: istore #16
    //   668: iconst_3
    //   669: iload #15
    //   671: iconst_4
    //   672: irem
    //   673: isub
    //   674: bipush #8
    //   676: imul
    //   677: istore #17
    //   679: aload #14
    //   681: iload #15
    //   683: iload #16
    //   685: iload #17
    //   687: iushr
    //   688: i2b
    //   689: bastore
    //   690: iinc #15, 1
    //   693: iload_2
    //   694: ifne -> 652
    //   697: aload #14
    //   699: astore #4
    //   701: new java/lang/StringBuilder
    //   704: dup
    //   705: invokespecial <init> : ()V
    //   708: astore_3
    //   709: iconst_0
    //   710: istore #4
    //   712: iload #4
    //   714: bipush #32
    //   716: if_icmpge -> 2051
    //   719: iload #4
    //   721: tableswitch default -> 2044, 0 -> 864, 1 -> 901, 2 -> 938, 3 -> 975, 4 -> 1012, 5 -> 1049, 6 -> 1086, 7 -> 1123, 8 -> 1160, 9 -> 1197, 10 -> 1234, 11 -> 1271, 12 -> 1308, 13 -> 1345, 14 -> 1382, 15 -> 1419, 16 -> 1456, 17 -> 1493, 18 -> 1530, 19 -> 1567, 20 -> 1604, 21 -> 1641, 22 -> 1678, 23 -> 1715, 24 -> 1752, 25 -> 1789, 26 -> 1826, 27 -> 1863, 28 -> 1900, 29 -> 1937, 30 -> 1974, 31 -> 2011
    //   864: aload_3
    //   865: getstatic burp/Zml2.Zh : Ljava/lang/String;
    //   868: getstatic burp/Zsgj.ZK : Ljava/lang/Object;
    //   871: checkcast java/math/BigInteger
    //   874: invokevirtual intValue : ()I
    //   877: bipush #32
    //   879: irem
    //   880: invokestatic abs : (I)I
    //   883: invokevirtual charAt : (I)C
    //   886: invokevirtual append : (C)Ljava/lang/StringBuilder;
    //   889: pop
    //   890: iload_2
    //   891: ifne -> 2044
    //   894: goto -> 901
    //   897: invokestatic a : (Ljava/lang/Throwable;)Ljava/lang/Throwable;
    //   900: athrow
    //   901: aload_3
    //   902: getstatic burp/Zmtr.Zd : Ljava/lang/String;
    //   905: getstatic burp/Zm5s.ZB : Ljava/lang/Object;
    //   908: checkcast java/math/BigInteger
    //   911: invokevirtual intValue : ()I
    //   914: bipush #32
    //   916: irem
    //   917: invokestatic abs : (I)I
    //   920: invokevirtual charAt : (I)C
    //   923: invokevirtual append : (C)Ljava/lang/StringBuilder;
    //   926: pop
    //   927: iload_2
    //   928: ifne -> 2044
    //   931: goto -> 938
    //   934: invokestatic a : (Ljava/lang/Throwable;)Ljava/lang/Throwable;
    //   937: athrow
    //   938: aload_3
    //   939: getstatic burp/Zsk4.ZH : Ljava/lang/String;
    //   942: getstatic burp/Zmha.ZM : Ljava/lang/Object;
    //   945: checkcast java/math/BigInteger
    //   948: invokevirtual intValue : ()I
    //   951: bipush #32
    //   953: irem
    //   954: invokestatic abs : (I)I
    //   957: invokevirtual charAt : (I)C
    //   960: invokevirtual append : (C)Ljava/lang/StringBuilder;
    //   963: pop
    //   964: iload_2
    //   965: ifne -> 2044
    //   968: goto -> 975
    //   971: invokestatic a : (Ljava/lang/Throwable;)Ljava/lang/Throwable;
    //   974: athrow
    //   975: aload_3
    //   976: getstatic burp/Zt0t.ZR : Ljava/lang/String;
    //   979: getstatic burp/Zgsy.ZC : Ljava/lang/Object;
    //   982: checkcast java/math/BigInteger
    //   985: invokevirtual intValue : ()I
    //   988: bipush #32
    //   990: irem
    //   991: invokestatic abs : (I)I
    //   994: invokevirtual charAt : (I)C
    //   997: invokevirtual append : (C)Ljava/lang/StringBuilder;
    //   1000: pop
    //   1001: iload_2
    //   1002: ifne -> 2044
    //   1005: goto -> 1012
    //   1008: invokestatic a : (Ljava/lang/Throwable;)Ljava/lang/Throwable;
    //   1011: athrow
    //   1012: aload_3
    //   1013: getstatic burp/Zoa.ZF : Ljava/lang/String;
    //   1016: getstatic burp/Zgx6.Zo : Ljava/lang/Object;
    //   1019: checkcast java/math/BigInteger
    //   1022: invokevirtual intValue : ()I
    //   1025: bipush #32
    //   1027: irem
    //   1028: invokestatic abs : (I)I
    //   1031: invokevirtual charAt : (I)C
    //   1034: invokevirtual append : (C)Ljava/lang/StringBuilder;
    //   1037: pop
    //   1038: iload_2
    //   1039: ifne -> 2044
    //   1042: goto -> 1049
    //   1045: invokestatic a : (Ljava/lang/Throwable;)Ljava/lang/Throwable;
    //   1048: athrow
    //   1049: aload_3
    //   1050: getstatic burp/Zr04.ZA : Ljava/lang/String;
    //   1053: getstatic burp/Zgs6.Za : Ljava/lang/Object;
    //   1056: checkcast java/math/BigInteger
    //   1059: invokevirtual intValue : ()I
    //   1062: bipush #32
    //   1064: irem
    //   1065: invokestatic abs : (I)I
    //   1068: invokevirtual charAt : (I)C
    //   1071: invokevirtual append : (C)Ljava/lang/StringBuilder;
    //   1074: pop
    //   1075: iload_2
    //   1076: ifne -> 2044
    //   1079: goto -> 1086
    //   1082: invokestatic a : (Ljava/lang/Throwable;)Ljava/lang/Throwable;
    //   1085: athrow
    //   1086: aload_3
    //   1087: getstatic burp/Zmwx.ZB : Ljava/lang/String;
    //   1090: getstatic burp/Zlnq.ZO : Ljava/lang/Object;
    //   1093: checkcast java/math/BigInteger
    //   1096: invokevirtual intValue : ()I
    //   1099: bipush #32
    //   1101: irem
    //   1102: invokestatic abs : (I)I
    //   1105: invokevirtual charAt : (I)C
    //   1108: invokevirtual append : (C)Ljava/lang/StringBuilder;
    //   1111: pop
    //   1112: iload_2
    //   1113: ifne -> 2044
    //   1116: goto -> 1123
    //   1119: invokestatic a : (Ljava/lang/Throwable;)Ljava/lang/Throwable;
    //   1122: athrow
    //   1123: aload_3
    //   1124: getstatic burp/Zl8y.ZY : Ljava/lang/String;
    //   1127: getstatic burp/Zsn6.Zo : Ljava/lang/Object;
    //   1130: checkcast java/math/BigInteger
    //   1133: invokevirtual intValue : ()I
    //   1136: bipush #32
    //   1138: irem
    //   1139: invokestatic abs : (I)I
    //   1142: invokevirtual charAt : (I)C
    //   1145: invokevirtual append : (C)Ljava/lang/StringBuilder;
    //   1148: pop
    //   1149: iload_2
    //   1150: ifne -> 2044
    //   1153: goto -> 1160
    //   1156: invokestatic a : (Ljava/lang/Throwable;)Ljava/lang/Throwable;
    //   1159: athrow
    //   1160: aload_3
    //   1161: getstatic burp/Zzmo.Zx : Ljava/lang/String;
    //   1164: getstatic burp/Zl3n.Zh : Ljava/lang/Object;
    //   1167: checkcast java/math/BigInteger
    //   1170: invokevirtual intValue : ()I
    //   1173: bipush #32
    //   1175: irem
    //   1176: invokestatic abs : (I)I
    //   1179: invokevirtual charAt : (I)C
    //   1182: invokevirtual append : (C)Ljava/lang/StringBuilder;
    //   1185: pop
    //   1186: iload_2
    //   1187: ifne -> 2044
    //   1190: goto -> 1197
    //   1193: invokestatic a : (Ljava/lang/Throwable;)Ljava/lang/Throwable;
    //   1196: athrow
    //   1197: aload_3
    //   1198: getstatic burp/Zl3l.Z_ : Ljava/lang/String;
    //   1201: getstatic burp/Zg4w.ZR : Ljava/lang/Object;
    //   1204: checkcast java/math/BigInteger
    //   1207: invokevirtual intValue : ()I
    //   1210: bipush #32
    //   1212: irem
    //   1213: invokestatic abs : (I)I
    //   1216: invokevirtual charAt : (I)C
    //   1219: invokevirtual append : (C)Ljava/lang/StringBuilder;
    //   1222: pop
    //   1223: iload_2
    //   1224: ifne -> 2044
    //   1227: goto -> 1234
    //   1230: invokestatic a : (Ljava/lang/Throwable;)Ljava/lang/Throwable;
    //   1233: athrow
    //   1234: aload_3
    //   1235: getstatic burp/Ze08.Zh : Ljava/lang/String;
    //   1238: getstatic burp/Zzok.ZY : Ljava/lang/Object;
    //   1241: checkcast java/math/BigInteger
    //   1244: invokevirtual intValue : ()I
    //   1247: bipush #32
    //   1249: irem
    //   1250: invokestatic abs : (I)I
    //   1253: invokevirtual charAt : (I)C
    //   1256: invokevirtual append : (C)Ljava/lang/StringBuilder;
    //   1259: pop
    //   1260: iload_2
    //   1261: ifne -> 2044
    //   1264: goto -> 1271
    //   1267: invokestatic a : (Ljava/lang/Throwable;)Ljava/lang/Throwable;
    //   1270: athrow
    //   1271: aload_3
    //   1272: getstatic burp/Zttj.ZN : Ljava/lang/String;
    //   1275: getstatic burp/Zg_y.ZR : Ljava/lang/Object;
    //   1278: checkcast java/math/BigInteger
    //   1281: invokevirtual intValue : ()I
    //   1284: bipush #32
    //   1286: irem
    //   1287: invokestatic abs : (I)I
    //   1290: invokevirtual charAt : (I)C
    //   1293: invokevirtual append : (C)Ljava/lang/StringBuilder;
    //   1296: pop
    //   1297: iload_2
    //   1298: ifne -> 2044
    //   1301: goto -> 1308
    //   1304: invokestatic a : (Ljava/lang/Throwable;)Ljava/lang/Throwable;
    //   1307: athrow
    //   1308: aload_3
    //   1309: getstatic burp/Zram.Ze : Ljava/lang/String;
    //   1312: getstatic burp/Zztx.ZM : Ljava/lang/Object;
    //   1315: checkcast java/math/BigInteger
    //   1318: invokevirtual intValue : ()I
    //   1321: bipush #32
    //   1323: irem
    //   1324: invokestatic abs : (I)I
    //   1327: invokevirtual charAt : (I)C
    //   1330: invokevirtual append : (C)Ljava/lang/StringBuilder;
    //   1333: pop
    //   1334: iload_2
    //   1335: ifne -> 2044
    //   1338: goto -> 1345
    //   1341: invokestatic a : (Ljava/lang/Throwable;)Ljava/lang/Throwable;
    //   1344: athrow
    //   1345: aload_3
    //   1346: getstatic burp/Zr04.ZA : Ljava/lang/String;
    //   1349: getstatic burp/Zbxp.ZW : Ljava/lang/Object;
    //   1352: checkcast java/math/BigInteger
    //   1355: invokevirtual intValue : ()I
    //   1358: bipush #32
    //   1360: irem
    //   1361: invokestatic abs : (I)I
    //   1364: invokevirtual charAt : (I)C
    //   1367: invokevirtual append : (C)Ljava/lang/StringBuilder;
    //   1370: pop
    //   1371: iload_2
    //   1372: ifne -> 2044
    //   1375: goto -> 1382
    //   1378: invokestatic a : (Ljava/lang/Throwable;)Ljava/lang/Throwable;
    //   1381: athrow
    //   1382: aload_3
    //   1383: getstatic burp/Zmlr.ZJ : Ljava/lang/String;
    //   1386: getstatic burp/Zrw7.ZV : Ljava/lang/Object;
    //   1389: checkcast java/math/BigInteger
    //   1392: invokevirtual intValue : ()I
    //   1395: bipush #32
    //   1397: irem
    //   1398: invokestatic abs : (I)I
    //   1401: invokevirtual charAt : (I)C
    //   1404: invokevirtual append : (C)Ljava/lang/StringBuilder;
    //   1407: pop
    //   1408: iload_2
    //   1409: ifne -> 2044
    //   1412: goto -> 1419
    //   1415: invokestatic a : (Ljava/lang/Throwable;)Ljava/lang/Throwable;
    //   1418: athrow
    //   1419: aload_3
    //   1420: getstatic burp/Zl_k.Zw : Ljava/lang/String;
    //   1423: getstatic burp/Zrkc.ZI : Ljava/lang/Object;
    //   1426: checkcast java/math/BigInteger
    //   1429: invokevirtual intValue : ()I
    //   1432: bipush #32
    //   1434: irem
    //   1435: invokestatic abs : (I)I
    //   1438: invokevirtual charAt : (I)C
    //   1441: invokevirtual append : (C)Ljava/lang/StringBuilder;
    //   1444: pop
    //   1445: iload_2
    //   1446: ifne -> 2044
    //   1449: goto -> 1456
    //   1452: invokestatic a : (Ljava/lang/Throwable;)Ljava/lang/Throwable;
    //   1455: athrow
    //   1456: aload_3
    //   1457: getstatic burp/Zm14.ZE : Ljava/lang/String;
    //   1460: getstatic burp/Zebj.Zf : Ljava/lang/Object;
    //   1463: checkcast java/math/BigInteger
    //   1466: invokevirtual intValue : ()I
    //   1469: bipush #32
    //   1471: irem
    //   1472: invokestatic abs : (I)I
    //   1475: invokevirtual charAt : (I)C
    //   1478: invokevirtual append : (C)Ljava/lang/StringBuilder;
    //   1481: pop
    //   1482: iload_2
    //   1483: ifne -> 2044
    //   1486: goto -> 1493
    //   1489: invokestatic a : (Ljava/lang/Throwable;)Ljava/lang/Throwable;
    //   1492: athrow
    //   1493: aload_3
    //   1494: getstatic burp/Zkfb.ZV : Ljava/lang/String;
    //   1497: getstatic burp/Zmh5.ZN : Ljava/lang/Object;
    //   1500: checkcast java/math/BigInteger
    //   1503: invokevirtual intValue : ()I
    //   1506: bipush #32
    //   1508: irem
    //   1509: invokestatic abs : (I)I
    //   1512: invokevirtual charAt : (I)C
    //   1515: invokevirtual append : (C)Ljava/lang/StringBuilder;
    //   1518: pop
    //   1519: iload_2
    //   1520: ifne -> 2044
    //   1523: goto -> 1530
    //   1526: invokestatic a : (Ljava/lang/Throwable;)Ljava/lang/Throwable;
    //   1529: athrow
    //   1530: aload_3
    //   1531: getstatic burp/Zxd0.Zc : Ljava/lang/String;
    //   1534: getstatic burp/Zrly.ZB : Ljava/lang/Object;
    //   1537: checkcast java/math/BigInteger
    //   1540: invokevirtual intValue : ()I
    //   1543: bipush #32
    //   1545: irem
    //   1546: invokestatic abs : (I)I
    //   1549: invokevirtual charAt : (I)C
    //   1552: invokevirtual append : (C)Ljava/lang/StringBuilder;
    //   1555: pop
    //   1556: iload_2
    //   1557: ifne -> 2044
    //   1560: goto -> 1567
    //   1563: invokestatic a : (Ljava/lang/Throwable;)Ljava/lang/Throwable;
    //   1566: athrow
    //   1567: aload_3
    //   1568: getstatic burp/Zmu6.Zl : Ljava/lang/String;
    //   1571: getstatic burp/Zrye.Zx : Ljava/lang/Object;
    //   1574: checkcast java/math/BigInteger
    //   1577: invokevirtual intValue : ()I
    //   1580: bipush #32
    //   1582: irem
    //   1583: invokestatic abs : (I)I
    //   1586: invokevirtual charAt : (I)C
    //   1589: invokevirtual append : (C)Ljava/lang/StringBuilder;
    //   1592: pop
    //   1593: iload_2
    //   1594: ifne -> 2044
    //   1597: goto -> 1604
    //   1600: invokestatic a : (Ljava/lang/Throwable;)Ljava/lang/Throwable;
    //   1603: athrow
    //   1604: aload_3
    //   1605: getstatic burp/Zzah.Zs : Ljava/lang/String;
    //   1608: getstatic burp/Zm7x.Zv : Ljava/lang/Object;
    //   1611: checkcast java/math/BigInteger
    //   1614: invokevirtual intValue : ()I
    //   1617: bipush #32
    //   1619: irem
    //   1620: invokestatic abs : (I)I
    //   1623: invokevirtual charAt : (I)C
    //   1626: invokevirtual append : (C)Ljava/lang/StringBuilder;
    //   1629: pop
    //   1630: iload_2
    //   1631: ifne -> 2044
    //   1634: goto -> 1641
    //   1637: invokestatic a : (Ljava/lang/Throwable;)Ljava/lang/Throwable;
    //   1640: athrow
    //   1641: aload_3
    //   1642: getstatic burp/Zt7k.ZH : Ljava/lang/String;
    //   1645: getstatic burp/Zb3l.Zl : Ljava/lang/Object;
    //   1648: checkcast java/math/BigInteger
    //   1651: invokevirtual intValue : ()I
    //   1654: bipush #32
    //   1656: irem
    //   1657: invokestatic abs : (I)I
    //   1660: invokevirtual charAt : (I)C
    //   1663: invokevirtual append : (C)Ljava/lang/StringBuilder;
    //   1666: pop
    //   1667: iload_2
    //   1668: ifne -> 2044
    //   1671: goto -> 1678
    //   1674: invokestatic a : (Ljava/lang/Throwable;)Ljava/lang/Throwable;
    //   1677: athrow
    //   1678: aload_3
    //   1679: getstatic burp/Zrpx.ZM : Ljava/lang/String;
    //   1682: getstatic burp/Zrp3.Zd : Ljava/lang/Object;
    //   1685: checkcast java/math/BigInteger
    //   1688: invokevirtual intValue : ()I
    //   1691: bipush #32
    //   1693: irem
    //   1694: invokestatic abs : (I)I
    //   1697: invokevirtual charAt : (I)C
    //   1700: invokevirtual append : (C)Ljava/lang/StringBuilder;
    //   1703: pop
    //   1704: iload_2
    //   1705: ifne -> 2044
    //   1708: goto -> 1715
    //   1711: invokestatic a : (Ljava/lang/Throwable;)Ljava/lang/Throwable;
    //   1714: athrow
    //   1715: aload_3
    //   1716: getstatic burp/Zrh1.Zg : Ljava/lang/String;
    //   1719: getstatic burp/Zexn.Zl : Ljava/lang/Object;
    //   1722: checkcast java/math/BigInteger
    //   1725: invokevirtual intValue : ()I
    //   1728: bipush #32
    //   1730: irem
    //   1731: invokestatic abs : (I)I
    //   1734: invokevirtual charAt : (I)C
    //   1737: invokevirtual append : (C)Ljava/lang/StringBuilder;
    //   1740: pop
    //   1741: iload_2
    //   1742: ifne -> 2044
    //   1745: goto -> 1752
    //   1748: invokestatic a : (Ljava/lang/Throwable;)Ljava/lang/Throwable;
    //   1751: athrow
    //   1752: aload_3
    //   1753: getstatic burp/Zlb6.ZP : Ljava/lang/String;
    //   1756: getstatic burp/Zzb2.ZW : Ljava/lang/Object;
    //   1759: checkcast java/math/BigInteger
    //   1762: invokevirtual intValue : ()I
    //   1765: bipush #32
    //   1767: irem
    //   1768: invokestatic abs : (I)I
    //   1771: invokevirtual charAt : (I)C
    //   1774: invokevirtual append : (C)Ljava/lang/StringBuilder;
    //   1777: pop
    //   1778: iload_2
    //   1779: ifne -> 2044
    //   1782: goto -> 1789
    //   1785: invokestatic a : (Ljava/lang/Throwable;)Ljava/lang/Throwable;
    //   1788: athrow
    //   1789: aload_3
    //   1790: getstatic burp/Zmtf.Zx : Ljava/lang/String;
    //   1793: getstatic burp/Zr0u.ZB : Ljava/lang/Object;
    //   1796: checkcast java/math/BigInteger
    //   1799: invokevirtual intValue : ()I
    //   1802: bipush #32
    //   1804: irem
    //   1805: invokestatic abs : (I)I
    //   1808: invokevirtual charAt : (I)C
    //   1811: invokevirtual append : (C)Ljava/lang/StringBuilder;
    //   1814: pop
    //   1815: iload_2
    //   1816: ifne -> 2044
    //   1819: goto -> 1826
    //   1822: invokestatic a : (Ljava/lang/Throwable;)Ljava/lang/Throwable;
    //   1825: athrow
    //   1826: aload_3
    //   1827: getstatic burp/Zli5.Zq : Ljava/lang/String;
    //   1830: getstatic burp/Zz6t.ZA : Ljava/lang/Object;
    //   1833: checkcast java/math/BigInteger
    //   1836: invokevirtual intValue : ()I
    //   1839: bipush #32
    //   1841: irem
    //   1842: invokestatic abs : (I)I
    //   1845: invokevirtual charAt : (I)C
    //   1848: invokevirtual append : (C)Ljava/lang/StringBuilder;
    //   1851: pop
    //   1852: iload_2
    //   1853: ifne -> 2044
    //   1856: goto -> 1863
    //   1859: invokestatic a : (Ljava/lang/Throwable;)Ljava/lang/Throwable;
    //   1862: athrow
    //   1863: aload_3
    //   1864: getstatic burp/Zsdn.Zf : Ljava/lang/String;
    //   1867: getstatic burp/Zgl4.Zb : Ljava/lang/Object;
    //   1870: checkcast java/math/BigInteger
    //   1873: invokevirtual intValue : ()I
    //   1876: bipush #32
    //   1878: irem
    //   1879: invokestatic abs : (I)I
    //   1882: invokevirtual charAt : (I)C
    //   1885: invokevirtual append : (C)Ljava/lang/StringBuilder;
    //   1888: pop
    //   1889: iload_2
    //   1890: ifne -> 2044
    //   1893: goto -> 1900
    //   1896: invokestatic a : (Ljava/lang/Throwable;)Ljava/lang/Throwable;
    //   1899: athrow
    //   1900: aload_3
    //   1901: getstatic burp/Ze57.ZV : Ljava/lang/String;
    //   1904: getstatic burp/Zl5.ZY : Ljava/lang/Object;
    //   1907: checkcast java/math/BigInteger
    //   1910: invokevirtual intValue : ()I
    //   1913: bipush #32
    //   1915: irem
    //   1916: invokestatic abs : (I)I
    //   1919: invokevirtual charAt : (I)C
    //   1922: invokevirtual append : (C)Ljava/lang/StringBuilder;
    //   1925: pop
    //   1926: iload_2
    //   1927: ifne -> 2044
    //   1930: goto -> 1937
    //   1933: invokestatic a : (Ljava/lang/Throwable;)Ljava/lang/Throwable;
    //   1936: athrow
    //   1937: aload_3
    //   1938: getstatic burp/Zxo6.Z_ : Ljava/lang/String;
    //   1941: getstatic burp/Zejg.ZR : Ljava/lang/Object;
    //   1944: checkcast java/math/BigInteger
    //   1947: invokevirtual intValue : ()I
    //   1950: bipush #32
    //   1952: irem
    //   1953: invokestatic abs : (I)I
    //   1956: invokevirtual charAt : (I)C
    //   1959: invokevirtual append : (C)Ljava/lang/StringBuilder;
    //   1962: pop
    //   1963: iload_2
    //   1964: ifne -> 2044
    //   1967: goto -> 1974
    //   1970: invokestatic a : (Ljava/lang/Throwable;)Ljava/lang/Throwable;
    //   1973: athrow
    //   1974: aload_3
    //   1975: getstatic burp/Zgdt.Zd : Ljava/lang/String;
    //   1978: getstatic burp/Zkht.ZR : Ljava/lang/Object;
    //   1981: checkcast java/math/BigInteger
    //   1984: invokevirtual intValue : ()I
    //   1987: bipush #32
    //   1989: irem
    //   1990: invokestatic abs : (I)I
    //   1993: invokevirtual charAt : (I)C
    //   1996: invokevirtual append : (C)Ljava/lang/StringBuilder;
    //   1999: pop
    //   2000: iload_2
    //   2001: ifne -> 2044
    //   2004: goto -> 2011
    //   2007: invokestatic a : (Ljava/lang/Throwable;)Ljava/lang/Throwable;
    //   2010: athrow
    //   2011: aload_3
    //   2012: getstatic burp/Zs00.Zv : Ljava/lang/String;
    //   2015: getstatic burp/Zlfg.Zv : Ljava/lang/Object;
    //   2018: checkcast java/math/BigInteger
    //   2021: invokevirtual intValue : ()I
    //   2024: bipush #32
    //   2026: irem
    //   2027: invokestatic abs : (I)I
    //   2030: invokevirtual charAt : (I)C
    //   2033: invokevirtual append : (C)Ljava/lang/StringBuilder;
    //   2036: pop
    //   2037: goto -> 2044
    //   2040: invokestatic a : (Ljava/lang/Throwable;)Ljava/lang/Throwable;
    //   2043: athrow
    //   2044: iinc #4, 1
    //   2047: iload_2
    //   2048: ifne -> 712
    //   2051: aload_3
    //   2052: invokevirtual toString : ()Ljava/lang/String;
    //   2055: putstatic burp/Zrw7.Zo : Ljava/lang/String;
    //   2058: sipush #-29400
    //   2061: sipush #-2677
    //   2064: invokestatic a : (II)Ljava/lang/String;
    //   2067: iconst_1
    //   2068: ldc burp/Zboa
    //   2070: invokevirtual getClassLoader : ()Ljava/lang/ClassLoader;
    //   2073: invokestatic forName : (Ljava/lang/String;ZLjava/lang/ClassLoader;)Ljava/lang/Class;
    //   2076: invokevirtual getDeclaredFields : ()[Ljava/lang/reflect/Field;
    //   2079: astore #4
    //   2081: aload #4
    //   2083: arraylength
    //   2084: istore #5
    //   2086: iconst_0
    //   2087: istore #6
    //   2089: iload #6
    //   2091: iload #5
    //   2093: if_icmpge -> 2231
    //   2096: aload #4
    //   2098: iload #6
    //   2100: aaload
    //   2101: astore #7
    //   2103: aload #7
    //   2105: invokevirtual getModifiers : ()I
    //   2108: invokestatic isStatic : (I)Z
    //   2111: ifne -> 2121
    //   2114: goto -> 2224
    //   2117: invokestatic a : (Ljava/lang/Throwable;)Ljava/lang/Throwable;
    //   2120: athrow
    //   2121: aload #7
    //   2123: invokevirtual getType : ()Ljava/lang/Class;
    //   2126: astore #8
    //   2128: aload #8
    //   2130: ifnull -> 2211
    //   2133: aload #8
    //   2135: invokevirtual isPrimitive : ()Z
    //   2138: ifne -> 2211
    //   2141: goto -> 2148
    //   2144: invokestatic a : (Ljava/lang/Throwable;)Ljava/lang/Throwable;
    //   2147: athrow
    //   2148: aload #8
    //   2150: invokevirtual getPackage : ()Ljava/lang/Package;
    //   2153: ifnull -> 2211
    //   2156: goto -> 2163
    //   2159: invokestatic a : (Ljava/lang/Throwable;)Ljava/lang/Throwable;
    //   2162: athrow
    //   2163: aload #8
    //   2165: invokevirtual getPackage : ()Ljava/lang/Package;
    //   2168: invokevirtual getName : ()Ljava/lang/String;
    //   2171: ifnull -> 2211
    //   2174: goto -> 2181
    //   2177: invokestatic a : (Ljava/lang/Throwable;)Ljava/lang/Throwable;
    //   2180: athrow
    //   2181: aload #8
    //   2183: invokevirtual getPackage : ()Ljava/lang/Package;
    //   2186: invokevirtual getName : ()Ljava/lang/String;
    //   2189: sipush #-29407
    //   2192: sipush #-11861
    //   2195: invokestatic a : (II)Ljava/lang/String;
    //   2198: invokevirtual startsWith : (Ljava/lang/String;)Z
    //   2201: ifne -> 2211
    //   2204: goto -> 2211
    //   2207: invokestatic a : (Ljava/lang/Throwable;)Ljava/lang/Throwable;
    //   2210: athrow
    //   2211: aload #7
    //   2213: iconst_1
    //   2214: invokevirtual setAccessible : (Z)V
    //   2217: aload #7
    //   2219: aconst_null
    //   2220: invokevirtual get : (Ljava/lang/Object;)Ljava/lang/Object;
    //   2223: pop
    //   2224: iinc #6, 1
    //   2227: iload_2
    //   2228: ifne -> 2089
    //   2231: sipush #-29395
    //   2234: sipush #-7043
    //   2237: invokestatic a : (II)Ljava/lang/String;
    //   2240: invokestatic forName : (Ljava/lang/String;)Ljava/lang/Class;
    //   2243: invokevirtual getDeclaredMethods : ()[Ljava/lang/reflect/Method;
    //   2246: astore #4
    //   2248: aload #4
    //   2250: arraylength
    //   2251: istore #5
    //   2253: iconst_0
    //   2254: istore #6
    //   2256: iload #6
    //   2258: iload #5
    //   2260: if_icmpge -> 2372
    //   2263: aload #4
    //   2265: iload #6
    //   2267: aaload
    //   2268: astore #7
    //   2270: aload #7
    //   2272: invokevirtual getParameterTypes : ()[Ljava/lang/Class;
    //   2275: pop
    //   2276: aload #7
    //   2278: invokevirtual getModifiers : ()I
    //   2281: invokestatic isStatic : (I)Z
    //   2284: ifeq -> 2358
    //   2287: aload #7
    //   2289: invokevirtual getParameterTypes : ()[Ljava/lang/Class;
    //   2292: arraylength
    //   2293: iconst_2
    //   2294: if_icmpne -> 2358
    //   2297: goto -> 2304
    //   2300: invokestatic a : (Ljava/lang/Throwable;)Ljava/lang/Throwable;
    //   2303: athrow
    //   2304: aload #7
    //   2306: invokevirtual getReturnType : ()Ljava/lang/Class;
    //   2309: getstatic java/lang/Boolean.TYPE : Ljava/lang/Class;
    //   2312: if_acmpne -> 2358
    //   2315: goto -> 2322
    //   2318: invokestatic a : (Ljava/lang/Throwable;)Ljava/lang/Throwable;
    //   2321: athrow
    //   2322: aload #7
    //   2324: iconst_1
    //   2325: invokevirtual setAccessible : (Z)V
    //   2328: aload #7
    //   2330: aconst_null
    //   2331: iconst_2
    //   2332: anewarray java/lang/Object
    //   2335: dup
    //   2336: iconst_0
    //   2337: aload_0
    //   2338: aastore
    //   2339: dup
    //   2340: iconst_1
    //   2341: aload_1
    //   2342: aastore
    //   2343: invokevirtual invoke : (Ljava/lang/Object;[Ljava/lang/Object;)Ljava/lang/Object;
    //   2346: pop
    //   2347: iload_2
    //   2348: ifne -> 2372
    //   2351: goto -> 2358
    //   2354: invokestatic a : (Ljava/lang/Throwable;)Ljava/lang/Throwable;
    //   2357: athrow
    //   2358: iinc #6, 1
    //   2361: iload_2
    //   2362: ifne -> 2256
    //   2365: goto -> 2372
    //   2368: invokestatic a : (Ljava/lang/Throwable;)Ljava/lang/Throwable;
    //   2371: athrow
    //   2372: sipush #-29408
    //   2375: sipush #-8521
    //   2378: invokestatic a : (II)Ljava/lang/String;
    //   2381: iconst_1
    //   2382: ldc burp/Zm1l
    //   2384: invokevirtual getClassLoader : ()Ljava/lang/ClassLoader;
    //   2387: invokestatic forName : (Ljava/lang/String;ZLjava/lang/ClassLoader;)Ljava/lang/Class;
    //   2390: invokevirtual getDeclaredFields : ()[Ljava/lang/reflect/Field;
    //   2393: astore #4
    //   2395: aload #4
    //   2397: arraylength
    //   2398: istore #5
    //   2400: iconst_0
    //   2401: istore #6
    //   2403: iload #6
    //   2405: iload #5
    //   2407: if_icmpge -> 2545
    //   2410: aload #4
    //   2412: iload #6
    //   2414: aaload
    //   2415: astore #7
    //   2417: aload #7
    //   2419: invokevirtual getModifiers : ()I
    //   2422: invokestatic isStatic : (I)Z
    //   2425: ifne -> 2435
    //   2428: goto -> 2538
    //   2431: invokestatic a : (Ljava/lang/Throwable;)Ljava/lang/Throwable;
    //   2434: athrow
    //   2435: aload #7
    //   2437: invokevirtual getType : ()Ljava/lang/Class;
    //   2440: astore #8
    //   2442: aload #8
    //   2444: ifnull -> 2525
    //   2447: aload #8
    //   2449: invokevirtual isPrimitive : ()Z
    //   2452: ifne -> 2525
    //   2455: goto -> 2462
    //   2458: invokestatic a : (Ljava/lang/Throwable;)Ljava/lang/Throwable;
    //   2461: athrow
    //   2462: aload #8
    //   2464: invokevirtual getPackage : ()Ljava/lang/Package;
    //   2467: ifnull -> 2525
    //   2470: goto -> 2477
    //   2473: invokestatic a : (Ljava/lang/Throwable;)Ljava/lang/Throwable;
    //   2476: athrow
    //   2477: aload #8
    //   2479: invokevirtual getPackage : ()Ljava/lang/Package;
    //   2482: invokevirtual getName : ()Ljava/lang/String;
    //   2485: ifnull -> 2525
    //   2488: goto -> 2495
    //   2491: invokestatic a : (Ljava/lang/Throwable;)Ljava/lang/Throwable;
    //   2494: athrow
    //   2495: aload #8
    //   2497: invokevirtual getPackage : ()Ljava/lang/Package;
    //   2500: invokevirtual getName : ()Ljava/lang/String;
    //   2503: sipush #-29397
    //   2506: sipush #20348
    //   2509: invokestatic a : (II)Ljava/lang/String;
    //   2512: invokevirtual startsWith : (Ljava/lang/String;)Z
    //   2515: ifne -> 2525
    //   2518: goto -> 2525
    //   2521: invokestatic a : (Ljava/lang/Throwable;)Ljava/lang/Throwable;
    //   2524: athrow
    //   2525: aload #7
    //   2527: iconst_1
    //   2528: invokevirtual setAccessible : (Z)V
    //   2531: aload #7
    //   2533: aconst_null
    //   2534: invokevirtual get : (Ljava/lang/Object;)Ljava/lang/Object;
    //   2537: pop
    //   2538: iinc #6, 1
    //   2541: iload_2
    //   2542: ifne -> 2403
    //   2545: sipush #-29406
    //   2548: sipush #-2612
    //   2551: invokestatic a : (II)Ljava/lang/String;
    //   2554: invokestatic forName : (Ljava/lang/String;)Ljava/lang/Class;
    //   2557: invokevirtual getDeclaredMethods : ()[Ljava/lang/reflect/Method;
    //   2560: astore #4
    //   2562: aload #4
    //   2564: arraylength
    //   2565: istore #5
    //   2567: iconst_0
    //   2568: istore #6
    //   2570: iload #6
    //   2572: iload #5
    //   2574: if_icmpge -> 2704
    //   2577: aload #4
    //   2579: iload #6
    //   2581: aaload
    //   2582: astore #7
    //   2584: aload #7
    //   2586: invokevirtual getParameterTypes : ()[Ljava/lang/Class;
    //   2589: pop
    //   2590: aload #7
    //   2592: invokevirtual getModifiers : ()I
    //   2595: invokestatic isStatic : (I)Z
    //   2598: ifeq -> 2690
    //   2601: aload #7
    //   2603: invokevirtual getParameterTypes : ()[Ljava/lang/Class;
    //   2606: arraylength
    //   2607: iconst_2
    //   2608: if_icmpne -> 2690
    //   2611: goto -> 2618
    //   2614: invokestatic a : (Ljava/lang/Throwable;)Ljava/lang/Throwable;
    //   2617: athrow
    //   2618: aload #7
    //   2620: invokevirtual getReturnType : ()Ljava/lang/Class;
    //   2623: getstatic java/lang/Boolean.TYPE : Ljava/lang/Class;
    //   2626: if_acmpne -> 2690
    //   2629: goto -> 2636
    //   2632: invokestatic a : (Ljava/lang/Throwable;)Ljava/lang/Throwable;
    //   2635: athrow
    //   2636: aload #7
    //   2638: iconst_1
    //   2639: invokevirtual setAccessible : (Z)V
    //   2642: aload #7
    //   2644: aconst_null
    //   2645: iconst_2
    //   2646: anewarray java/lang/Object
    //   2649: dup
    //   2650: iconst_0
    //   2651: aload_0
    //   2652: aastore
    //   2653: dup
    //   2654: iconst_1
    //   2655: aload_1
    //   2656: ifnonnull -> 2674
    //   2659: goto -> 2666
    //   2662: invokestatic a : (Ljava/lang/Throwable;)Ljava/lang/Throwable;
    //   2665: athrow
    //   2666: aload_1
    //   2667: goto -> 2681
    //   2670: invokestatic a : (Ljava/lang/Throwable;)Ljava/lang/Throwable;
    //   2673: athrow
    //   2674: aload_1
    //   2675: checkcast [B
    //   2678: invokevirtual clone : ()Ljava/lang/Object;
    //   2681: aastore
    //   2682: invokevirtual invoke : (Ljava/lang/Object;[Ljava/lang/Object;)Ljava/lang/Object;
    //   2685: pop
    //   2686: iload_2
    //   2687: ifne -> 2704
    //   2690: iinc #6, 1
    //   2693: iload_2
    //   2694: ifne -> 2570
    //   2697: goto -> 2704
    //   2700: invokestatic a : (Ljava/lang/Throwable;)Ljava/lang/Throwable;
    //   2703: athrow
    //   2704: sipush #-29398
    //   2707: sipush #-17339
    //   2710: invokestatic a : (II)Ljava/lang/String;
    //   2713: iconst_1
    //   2714: ldc burp/Zb2s
    //   2716: invokevirtual getClassLoader : ()Ljava/lang/ClassLoader;
    //   2719: invokestatic forName : (Ljava/lang/String;ZLjava/lang/ClassLoader;)Ljava/lang/Class;
    //   2722: invokevirtual getDeclaredFields : ()[Ljava/lang/reflect/Field;
    //   2725: astore #4
    //   2727: aload #4
    //   2729: arraylength
    //   2730: istore #5
    //   2732: iconst_0
    //   2733: istore #6
    //   2735: iload #6
    //   2737: iload #5
    //   2739: if_icmpge -> 2877
    //   2742: aload #4
    //   2744: iload #6
    //   2746: aaload
    //   2747: astore #7
    //   2749: aload #7
    //   2751: invokevirtual getModifiers : ()I
    //   2754: invokestatic isStatic : (I)Z
    //   2757: ifne -> 2767
    //   2760: goto -> 2870
    //   2763: invokestatic a : (Ljava/lang/Throwable;)Ljava/lang/Throwable;
    //   2766: athrow
    //   2767: aload #7
    //   2769: invokevirtual getType : ()Ljava/lang/Class;
    //   2772: astore #8
    //   2774: aload #8
    //   2776: ifnull -> 2857
    //   2779: aload #8
    //   2781: invokevirtual isPrimitive : ()Z
    //   2784: ifne -> 2857
    //   2787: goto -> 2794
    //   2790: invokestatic a : (Ljava/lang/Throwable;)Ljava/lang/Throwable;
    //   2793: athrow
    //   2794: aload #8
    //   2796: invokevirtual getPackage : ()Ljava/lang/Package;
    //   2799: ifnull -> 2857
    //   2802: goto -> 2809
    //   2805: invokestatic a : (Ljava/lang/Throwable;)Ljava/lang/Throwable;
    //   2808: athrow
    //   2809: aload #8
    //   2811: invokevirtual getPackage : ()Ljava/lang/Package;
    //   2814: invokevirtual getName : ()Ljava/lang/String;
    //   2817: ifnull -> 2857
    //   2820: goto -> 2827
    //   2823: invokestatic a : (Ljava/lang/Throwable;)Ljava/lang/Throwable;
    //   2826: athrow
    //   2827: aload #8
    //   2829: invokevirtual getPackage : ()Ljava/lang/Package;
    //   2832: invokevirtual getName : ()Ljava/lang/String;
    //   2835: sipush #-29397
    //   2838: sipush #20348
    //   2841: invokestatic a : (II)Ljava/lang/String;
    //   2844: invokevirtual startsWith : (Ljava/lang/String;)Z
    //   2847: ifne -> 2857
    //   2850: goto -> 2857
    //   2853: invokestatic a : (Ljava/lang/Throwable;)Ljava/lang/Throwable;
    //   2856: athrow
    //   2857: aload #7
    //   2859: iconst_1
    //   2860: invokevirtual setAccessible : (Z)V
    //   2863: aload #7
    //   2865: aconst_null
    //   2866: invokevirtual get : (Ljava/lang/Object;)Ljava/lang/Object;
    //   2869: pop
    //   2870: iinc #6, 1
    //   2873: iload_2
    //   2874: ifne -> 2735
    //   2877: sipush #-29405
    //   2880: sipush #16902
    //   2883: invokestatic a : (II)Ljava/lang/String;
    //   2886: invokestatic forName : (Ljava/lang/String;)Ljava/lang/Class;
    //   2889: invokevirtual getDeclaredMethods : ()[Ljava/lang/reflect/Method;
    //   2892: astore #4
    //   2894: aload #4
    //   2896: arraylength
    //   2897: istore #5
    //   2899: iconst_0
    //   2900: istore #6
    //   2902: iload #6
    //   2904: iload #5
    //   2906: if_icmpge -> 3039
    //   2909: aload #4
    //   2911: iload #6
    //   2913: aaload
    //   2914: astore #7
    //   2916: aload #7
    //   2918: invokevirtual getParameterTypes : ()[Ljava/lang/Class;
    //   2921: pop
    //   2922: aload #7
    //   2924: invokevirtual getModifiers : ()I
    //   2927: invokestatic isStatic : (I)Z
    //   2930: ifeq -> 3025
    //   2933: aload #7
    //   2935: invokevirtual getParameterTypes : ()[Ljava/lang/Class;
    //   2938: arraylength
    //   2939: iconst_2
    //   2940: if_icmpne -> 3025
    //   2943: goto -> 2950
    //   2946: invokestatic a : (Ljava/lang/Throwable;)Ljava/lang/Throwable;
    //   2949: athrow
    //   2950: aload #7
    //   2952: invokevirtual getReturnType : ()Ljava/lang/Class;
    //   2955: getstatic java/lang/Void.TYPE : Ljava/lang/Class;
    //   2958: invokevirtual equals : (Ljava/lang/Object;)Z
    //   2961: ifeq -> 3025
    //   2964: goto -> 2971
    //   2967: invokestatic a : (Ljava/lang/Throwable;)Ljava/lang/Throwable;
    //   2970: athrow
    //   2971: aload #7
    //   2973: iconst_1
    //   2974: invokevirtual setAccessible : (Z)V
    //   2977: aload #7
    //   2979: aconst_null
    //   2980: iconst_2
    //   2981: anewarray java/lang/Object
    //   2984: dup
    //   2985: iconst_0
    //   2986: aload_0
    //   2987: aastore
    //   2988: dup
    //   2989: iconst_1
    //   2990: aload_1
    //   2991: ifnonnull -> 3009
    //   2994: goto -> 3001
    //   2997: invokestatic a : (Ljava/lang/Throwable;)Ljava/lang/Throwable;
    //   3000: athrow
    //   3001: aload_1
    //   3002: goto -> 3016
    //   3005: invokestatic a : (Ljava/lang/Throwable;)Ljava/lang/Throwable;
    //   3008: athrow
    //   3009: aload_1
    //   3010: checkcast [B
    //   3013: invokevirtual clone : ()Ljava/lang/Object;
    //   3016: aastore
    //   3017: invokevirtual invoke : (Ljava/lang/Object;[Ljava/lang/Object;)Ljava/lang/Object;
    //   3020: pop
    //   3021: iload_2
    //   3022: ifne -> 3039
    //   3025: iinc #6, 1
    //   3028: iload_2
    //   3029: ifne -> 2902
    //   3032: goto -> 3039
    //   3035: invokestatic a : (Ljava/lang/Throwable;)Ljava/lang/Throwable;
    //   3038: athrow
    //   3039: getstatic burp/Ztsc.ZL : Ljava/lang/String;
    //   3042: getstatic burp/Zgqi.Zp : Ljava/lang/Object;
    //   3045: checkcast java/math/BigInteger
    //   3048: invokevirtual intValue : ()I
    //   3051: bipush #32
    //   3053: irem
    //   3054: invokestatic abs : (I)I
    //   3057: invokevirtual charAt : (I)C
    //   3060: getstatic burp/Zxdh.Zj : Ljava/lang/String;
    //   3063: getstatic burp/Ze_b.Zp : Ljava/lang/Object;
    //   3066: checkcast java/math/BigInteger
    //   3069: invokevirtual intValue : ()I
    //   3072: bipush #32
    //   3074: irem
    //   3075: invokestatic abs : (I)I
    //   3078: invokevirtual charAt : (I)C
    //   3081: if_icmpgt -> 3196
    //   3084: getstatic burp/Zl3j.Zr : Ljava/lang/String;
    //   3087: getstatic burp/Zr3q.Zn : Ljava/lang/Object;
    //   3090: checkcast java/math/BigInteger
    //   3093: invokevirtual intValue : ()I
    //   3096: bipush #32
    //   3098: irem
    //   3099: invokestatic abs : (I)I
    //   3102: invokevirtual charAt : (I)C
    //   3105: getstatic burp/Zb2p.ZV : Ljava/lang/String;
    //   3108: getstatic burp/Zb0z.ZQ : Ljava/lang/Object;
    //   3111: checkcast java/math/BigInteger
    //   3114: invokevirtual intValue : ()I
    //   3117: bipush #32
    //   3119: irem
    //   3120: invokestatic abs : (I)I
    //   3123: invokevirtual charAt : (I)C
    //   3126: if_icmple -> 3196
    //   3129: goto -> 3136
    //   3132: invokestatic a : (Ljava/lang/Throwable;)Ljava/lang/Throwable;
    //   3135: athrow
    //   3136: getstatic burp/Zzoc.Zg : Ljava/lang/String;
    //   3139: getstatic burp/Zlqm.Zw : Ljava/lang/Object;
    //   3142: checkcast java/math/BigInteger
    //   3145: invokevirtual intValue : ()I
    //   3148: bipush #32
    //   3150: irem
    //   3151: invokestatic abs : (I)I
    //   3154: invokevirtual charAt : (I)C
    //   3157: getstatic burp/Zrct.ZT : Ljava/lang/String;
    //   3160: getstatic burp/Zxf8.Zz : Ljava/lang/Object;
    //   3163: checkcast java/math/BigInteger
    //   3166: invokevirtual intValue : ()I
    //   3169: bipush #32
    //   3171: irem
    //   3172: invokestatic abs : (I)I
    //   3175: invokevirtual charAt : (I)C
    //   3178: if_icmple -> 3196
    //   3181: goto -> 3188
    //   3184: invokestatic a : (Ljava/lang/Throwable;)Ljava/lang/Throwable;
    //   3187: athrow
    //   3188: iconst_1
    //   3189: goto -> 3197
    //   3192: invokestatic a : (Ljava/lang/Throwable;)Ljava/lang/Throwable;
    //   3195: athrow
    //   3196: iconst_0
    //   3197: ireturn
    //   3198: astore_3
    //   3199: new java/lang/Exception
    //   3202: dup
    //   3203: aload_3
    //   3204: invokevirtual getMessage : ()Ljava/lang/String;
    //   3207: invokespecial <init> : (Ljava/lang/String;)V
    //   3210: athrow
    // Exception table:
    //   from	to	target	type
    //   4	3197	3198	java/lang/Throwable
    //   324	348	351	java/lang/Throwable
    //   422	459	459	java/lang/Throwable
    //   463	484	484	java/lang/Throwable
    //   488	518	518	java/lang/Throwable
    //   719	894	897	java/lang/Throwable
    //   864	931	934	java/lang/Throwable
    //   901	968	971	java/lang/Throwable
    //   938	1005	1008	java/lang/Throwable
    //   975	1042	1045	java/lang/Throwable
    //   1012	1079	1082	java/lang/Throwable
    //   1049	1116	1119	java/lang/Throwable
    //   1086	1153	1156	java/lang/Throwable
    //   1123	1190	1193	java/lang/Throwable
    //   1160	1227	1230	java/lang/Throwable
    //   1197	1264	1267	java/lang/Throwable
    //   1234	1301	1304	java/lang/Throwable
    //   1271	1338	1341	java/lang/Throwable
    //   1308	1375	1378	java/lang/Throwable
    //   1345	1412	1415	java/lang/Throwable
    //   1382	1449	1452	java/lang/Throwable
    //   1419	1486	1489	java/lang/Throwable
    //   1456	1523	1526	java/lang/Throwable
    //   1493	1560	1563	java/lang/Throwable
    //   1530	1597	1600	java/lang/Throwable
    //   1567	1634	1637	java/lang/Throwable
    //   1604	1671	1674	java/lang/Throwable
    //   1641	1708	1711	java/lang/Throwable
    //   1678	1745	1748	java/lang/Throwable
    //   1715	1782	1785	java/lang/Throwable
    //   1752	1819	1822	java/lang/Throwable
    //   1789	1856	1859	java/lang/Throwable
    //   1826	1893	1896	java/lang/Throwable
    //   1863	1930	1933	java/lang/Throwable
    //   1900	1967	1970	java/lang/Throwable
    //   1937	2004	2007	java/lang/Throwable
    //   1974	2037	2040	java/lang/Throwable
    //   2103	2117	2117	java/lang/Throwable
    //   2128	2141	2144	java/lang/Throwable
    //   2133	2156	2159	java/lang/Throwable
    //   2148	2174	2177	java/lang/Throwable
    //   2163	2204	2207	java/lang/Throwable
    //   2270	2297	2300	java/lang/Throwable
    //   2287	2315	2318	java/lang/Throwable
    //   2304	2351	2354	java/lang/Throwable
    //   2322	2365	2368	java/lang/Throwable
    //   2417	2431	2431	java/lang/Throwable
    //   2442	2455	2458	java/lang/Throwable
    //   2447	2470	2473	java/lang/Throwable
    //   2462	2488	2491	java/lang/Throwable
    //   2477	2518	2521	java/lang/Throwable
    //   2584	2611	2614	java/lang/Throwable
    //   2601	2629	2632	java/lang/Throwable
    //   2618	2659	2662	java/lang/Throwable
    //   2636	2670	2670	java/lang/Throwable
    //   2681	2697	2700	java/lang/Throwable
    //   2749	2763	2763	java/lang/Throwable
    //   2774	2787	2790	java/lang/Throwable
    //   2779	2802	2805	java/lang/Throwable
    //   2794	2820	2823	java/lang/Throwable
    //   2809	2850	2853	java/lang/Throwable
    //   2916	2943	2946	java/lang/Throwable
    //   2933	2964	2967	java/lang/Throwable
    //   2950	2994	2997	java/lang/Throwable
    //   2971	3005	3005	java/lang/Throwable
    //   3016	3032	3035	java/lang/Throwable
    //   3039	3129	3132	java/lang/Throwable
    //   3084	3181	3184	java/lang/Throwable
    //   3136	3192	3192	java/lang/Throwable
  }
  
  static void Zn(Object[] paramArrayOfObject, Object paramObject) throws Throwable {}
  
  static {
    // Byte code:
    //   0: bipush #18
    //   2: anewarray java/lang/String
    //   5: astore #5
    //   7: iconst_0
    //   8: istore_3
    //   9: ldc 'Ok5 %(.V,P^HOMPBR D:aMXdl.&@;X8M8hF~!PyUW h\\rtLHeM1<dm?\\\b\\tNH\\tNEVY\\t}<${g\\tK\\n\\t#\\tOp!p\\t/Fv2e@&0\\t]\\t>  _/$!p'Wd2mqg=R\\bZ\\\t!v^#'
    //   11: dup
    //   12: astore_2
    //   13: invokevirtual length : ()I
    //   16: istore #4
    //   18: bipush #7
    //   20: istore_1
    //   21: iconst_m1
    //   22: istore_0
    //   23: iconst_1
    //   24: iinc #0, 1
    //   27: aload_2
    //   28: iload_0
    //   29: dup
    //   30: iload_1
    //   31: iadd
    //   32: invokevirtual substring : (II)Ljava/lang/String;
    //   35: iconst_m1
    //   36: goto -> 142
    //   39: aload #5
    //   41: swap
    //   42: iload_3
    //   43: iinc #3, 1
    //   46: swap
    //   47: aastore
    //   48: iload_0
    //   49: iload_1
    //   50: iadd
    //   51: dup
    //   52: istore_0
    //   53: iload #4
    //   55: if_icmpge -> 67
    //   58: aload_2
    //   59: iload_0
    //   60: invokevirtual charAt : (I)C
    //   63: istore_1
    //   64: goto -> 23
    //   67: ldc '@fM6B+y[Wk6eNQe\\r-f O.Q%W4=N'Lte'
    //   69: dup
    //   70: astore_2
    //   71: invokevirtual length : ()I
    //   74: istore #4
    //   76: bipush #9
    //   78: istore_1
    //   79: iconst_m1
    //   80: istore_0
    //   81: bipush #74
    //   83: iinc #0, 1
    //   86: aload_2
    //   87: iload_0
    //   88: dup
    //   89: iload_1
    //   90: iadd
    //   91: invokevirtual substring : (II)Ljava/lang/String;
    //   94: iconst_0
    //   95: goto -> 142
    //   98: aload #5
    //   100: swap
    //   101: iload_3
    //   102: iinc #3, 1
    //   105: swap
    //   106: aastore
    //   107: iload_0
    //   108: iload_1
    //   109: iadd
    //   110: dup
    //   111: istore_0
    //   112: iload #4
    //   114: if_icmpge -> 126
    //   117: aload_2
    //   118: iload_0
    //   119: invokevirtual charAt : (I)C
    //   122: istore_1
    //   123: goto -> 81
    //   126: aload #5
    //   128: putstatic burp/Zzvr.a : [Ljava/lang/String;
    //   131: bipush #18
    //   133: anewarray java/lang/String
    //   136: putstatic burp/Zzvr.b : [Ljava/lang/String;
    //   139: goto -> 300
    //   142: dup_x2
    //   143: pop
    //   144: invokevirtual toCharArray : ()[C
    //   147: dup_x1
    //   148: arraylength
    //   149: dup_x2
    //   150: pop
    //   151: iconst_0
    //   152: istore #6
    //   154: dup2_x1
    //   155: pop2
    //   156: dup_x2
    //   157: iconst_1
    //   158: if_icmpgt -> 259
    //   161: dup2
    //   162: swap
    //   163: iload #6
    //   165: dup2_x1
    //   166: caload
    //   167: swap
    //   168: iload #6
    //   170: bipush #7
    //   172: irem
    //   173: tableswitch default -> 241, 0 -> 212, 1 -> 217, 2 -> 222, 3 -> 227, 4 -> 232, 5 -> 236
    //   212: bipush #68
    //   214: goto -> 243
    //   217: bipush #95
    //   219: goto -> 243
    //   222: bipush #102
    //   224: goto -> 243
    //   227: bipush #16
    //   229: goto -> 243
    //   232: iconst_3
    //   233: goto -> 243
    //   236: bipush #85
    //   238: goto -> 243
    //   241: bipush #83
    //   243: ixor
    //   244: ixor
    //   245: i2c
    //   246: castore
    //   247: iinc #6, 1
    //   250: dup
    //   251: ifne -> 259
    //   254: dup2
    //   255: dup_x1
    //   256: goto -> 165
    //   259: dup2_x1
    //   260: pop2
    //   261: dup_x2
    //   262: iload #6
    //   264: if_icmpgt -> 161
    //   267: pop
    //   268: new java/lang/String
    //   271: dup_x1
    //   272: swap
    //   273: invokespecial <init> : ([C)V
    //   276: invokevirtual intern : ()Ljava/lang/String;
    //   279: swap
    //   280: pop
    //   281: swap
    //   282: tableswitch default -> 39, 0 -> 98
    //   300: new java/math/BigInteger
    //   303: dup
    //   304: sipush #-29403
    //   307: sipush #-19100
    //   310: invokestatic a : (II)Ljava/lang/String;
    //   313: invokespecial <init> : (Ljava/lang/String;)V
    //   316: putstatic burp/Zzvr.Z_ : Ljava/lang/Object;
    //   319: sipush #-29402
    //   322: sipush #3341
    //   325: invokestatic a : (II)Ljava/lang/String;
    //   328: putstatic burp/Zzvr.Zc : Ljava/lang/String;
    //   331: return
  }
  
  private static Throwable a(Throwable paramThrowable) {
    return paramThrowable;
  }
  
  private static String a(int paramInt1, int paramInt2) {
    int i = (paramInt1 ^ 0xFFFF8D27) & 0xFFFF;
    if (b[i] == null) {
      char[] arrayOfChar = a[i].toCharArray();
      switch (arrayOfChar[0] & 0xFF) {
        case 0:
        
        case 1:
        
        case 2:
        
        case 3:
        
        case 4:
        
        case 5:
        
        case 6:
        
        case 7:
        
        case 8:
        
        case 9:
        
        case 10:
        
        case 11:
        
        case 12:
        
        case 13:
        
        case 14:
        
        case 15:
        
        case 16:
        
        case 17:
        
        case 18:
        
        case 19:
        
        case 20:
        
        case 21:
        
        case 22:
        
        case 23:
        
        case 24:
        
        case 25:
        
        case 26:
        
        case 27:
        
        case 28:
        
        case 29:
        
        case 30:
        
        case 31:
        
        case 32:
        
        case 33:
        
        case 34:
        
        case 35:
        
        case 36:
        
        case 37:
        
        case 38:
        
        case 39:
        
        case 40:
        
        case 41:
        
        case 42:
        
        case 43:
        
        case 44:
        
        case 45:
        
        case 46:
        
        case 47:
        
        case 48:
        
        case 49:
        
        case 50:
        
        case 51:
        
        case 52:
        
        case 53:
        
        case 54:
        
        case 55:
        
        case 56:
        
        case 57:
        
        case 58:
        
        case 59:
        
        case 60:
        
        case 61:
        
        case 62:
        
        case 63:
        
        case 64:
        
        case 65:
        
        case 66:
        
        case 67:
        
        case 68:
        
        case 69:
        
        case 70:
        
        case 71:
        
        case 72:
        
        case 73:
        
        case 74:
        
        case 75:
        
        case 76:
        
        case 77:
        
        case 78:
        
        case 79:
        
        case 80:
        
        case 81:
        
        case 82:
        
        case 83:
        
        case 84:
        
        case 85:
        
        case 86:
        
        case 87:
        
        case 88:
        
        case 89:
        
        case 90:
        
        case 91:
        
        case 92:
        
        case 93:
        
        case 94:
        
        case 95:
        
        case 96:
        
        case 97:
        
        case 98:
        
        case 99:
        
        case 100:
        
        case 101:
        
        case 102:
        
        case 103:
        
        case 104:
        
        case 105:
        
        case 106:
        
        case 107:
        
        case 108:
        
        case 109:
        
        case 110:
        
        case 111:
        
        case 112:
        
        case 113:
        
        case 114:
        
        case 115:
        
        case 116:
        
        case 117:
        
        case 118:
        
        case 119:
        
        case 120:
        
        case 121:
        
        case 122:
        
        case 123:
        
        case 124:
        
        case 125:
        
        case 126:
        
        case 127:
        
        case 128:
        
        case 129:
        
        case 130:
        
        case 131:
        
        case 132:
        
        case 133:
        
        case 134:
        
        case 135:
        
        case 136:
        
        case 137:
        
        case 138:
        
        case 139:
        
        case 140:
        
        case 141:
        
        case 142:
        
        case 143:
        
        case 144:
        
        case 145:
        
        case 146:
        
        case 147:
        
        case 148:
        
        case 149:
        
        case 150:
        
        case 151:
        
        case 152:
        
        case 153:
        
        case 154:
        
        case 155:
        
        case 156:
        
        case 157:
        
        case 158:
        
        case 159:
        
        case 160:
        
        case 161:
        
        case 162:
        
        case 163:
        
        case 164:
        
        case 165:
        
        case 166:
        
        case 167:
        
        case 168:
        
        case 169:
        
        case 170:
        
        case 171:
        
        case 172:
        
        case 173:
        
        case 174:
        
        case 175:
        
        case 176:
        
        case 177:
        
        case 178:
        
        case 179:
        
        case 180:
        
        case 181:
        
        case 182:
        
        case 183:
        
        case 184:
        
        case 185:
        
        case 186:
        
        case 187:
        
        case 188:
        
        case 189:
        
        case 190:
        
        case 191:
        
        case 192:
        
        case 193:
        
        case 194:
        
        case 195:
        
        case 196:
        
        case 197:
        
        case 198:
        
        case 199:
        
        case 200:
        
        case 201:
        
        case 202:
        
        case 203:
        
        case 204:
        
        case 205:
        
        case 206:
        
        case 207:
        
        case 208:
        
        case 209:
        
        case 210:
        
        case 211:
        
        case 212:
        
        case 213:
        
        case 214:
        
        case 215:
        
        case 216:
        
        case 217:
        
        case 218:
        
        case 219:
        
        case 220:
        
        case 221:
        
        case 222:
        
        case 223:
        
        case 224:
        
        case 225:
        
        case 226:
        
        case 227:
        
        case 228:
        
        case 229:
        
        case 230:
        
        case 231:
        
        case 232:
        
        case 233:
        
        case 234:
        
        case 235:
        
        case 236:
        
        case 237:
        
        case 238:
        
        case 239:
        
        case 240:
        
        case 241:
        
        case 242:
        
        case 243:
        
        case 244:
        
        case 245:
        
        case 246:
        
        case 247:
        
        case 248:
        
        case 249:
        
        case 250:
        
        case 251:
        
        case 252:
        
        case 253:
        
        case 254:
        
        default:
          break;
      } 
      byte b1 = 10;
      int j = (paramInt2 & 0xFF) - b1;
      if (j < 0)
        j += 256; 
      int k = ((paramInt2 & 0xFFFF) >>> 8) - b1;
      if (k < 0)
        k += 256; 
      for (byte b2 = 0; b2 < arrayOfChar.length; b2++) {
        int m = b2 % 2;
        if (m == 0) {
          arrayOfChar[b2] = (char)(arrayOfChar[b2] ^ j);
          j = ((j >>> 3 | j << 5) ^ arrayOfChar[b2]) & 0xFF;
        } else {
          arrayOfChar[b2] = (char)(arrayOfChar[b2] ^ k);
          k = ((k >>> 3 | k << 5) ^ arrayOfChar[b2]) & 0xFF;
        } 
      } 
      b[i] = (new String(arrayOfChar)).intern();
    } 
    return b[i];
  }
}


/* Location:              C:\Program Files\BurpSuitePro\burpsuite_pro.jar!\burp\Zzvr.class
 * Java compiler version: 21 (65.0)
 * JD-Core Version:       1.1.3
 */