package com.fasterxml;

import com.fasterxml.Zor.Zyg;
import java.io.IOException;
import java.time.DateTimeException;
import java.time.MonthDay;
import java.time.format.DateTimeFormatter;

public class Zg9 extends Zg7 {
  public static final Zg9 Zt;
  
  private static final DateTimeFormatter ZY;
  
  protected MonthDay Zg(String paramString, Zyg paramZyg) throws IOException {
    try {
      return MonthDay.parse(paramString, ZY);
    } catch (DateTimeException dateTimeException) {
      return ZA(paramZyg, MonthDay.class, dateTimeException, paramString);
    } 
  }
  
  static {
    // Byte code:
    //   0: bipush #10
    //   2: ldc '!'
    //   4: iconst_m1
    //   5: goto -> 12
    //   8: astore_0
    //   9: goto -> 154
    //   12: dup_x2
    //   13: pop
    //   14: invokevirtual toCharArray : ()[C
    //   17: dup_x1
    //   18: arraylength
    //   19: dup_x2
    //   20: pop
    //   21: iconst_0
    //   22: istore_1
    //   23: dup2_x1
    //   24: pop2
    //   25: dup_x2
    //   26: iconst_1
    //   27: if_icmpgt -> 128
    //   30: dup2
    //   31: swap
    //   32: iload_1
    //   33: dup2_x1
    //   34: caload
    //   35: swap
    //   36: iload_1
    //   37: bipush #7
    //   39: irem
    //   40: tableswitch default -> 110, 0 -> 80, 1 -> 85, 2 -> 90, 3 -> 95, 4 -> 100, 5 -> 105
    //   80: bipush #6
    //   82: goto -> 112
    //   85: bipush #56
    //   87: goto -> 112
    //   90: bipush #20
    //   92: goto -> 112
    //   95: bipush #78
    //   97: goto -> 112
    //   100: bipush #6
    //   102: goto -> 112
    //   105: bipush #74
    //   107: goto -> 112
    //   110: bipush #41
    //   112: ixor
    //   113: ixor
    //   114: i2c
    //   115: castore
    //   116: iinc #1, 1
    //   119: dup
    //   120: ifne -> 128
    //   123: dup2
    //   124: dup_x1
    //   125: goto -> 33
    //   128: dup2_x1
    //   129: pop2
    //   130: dup_x2
    //   131: iload_1
    //   132: if_icmpgt -> 30
    //   135: pop
    //   136: new java/lang/String
    //   139: dup_x1
    //   140: swap
    //   141: invokespecial <init> : ([C)V
    //   144: invokevirtual intern : ()Ljava/lang/String;
    //   147: swap
    //   148: pop
    //   149: swap
    //   150: pop
    //   151: goto -> 8
    //   154: new com/fasterxml/Zg9
    //   157: dup
    //   158: invokespecial <init> : ()V
    //   161: putstatic com/fasterxml/Zg9.Zt : Lcom/fasterxml/Zg9;
    //   164: new java/time/format/DateTimeFormatterBuilder
    //   167: dup
    //   168: invokespecial <init> : ()V
    //   171: aload_0
    //   172: invokevirtual appendLiteral : (Ljava/lang/String;)Ljava/time/format/DateTimeFormatterBuilder;
    //   175: getstatic java/time/temporal/ChronoField.MONTH_OF_YEAR : Ljava/time/temporal/ChronoField;
    //   178: iconst_2
    //   179: invokevirtual appendValue : (Ljava/time/temporal/TemporalField;I)Ljava/time/format/DateTimeFormatterBuilder;
    //   182: bipush #45
    //   184: invokevirtual appendLiteral : (C)Ljava/time/format/DateTimeFormatterBuilder;
    //   187: getstatic java/time/temporal/ChronoField.DAY_OF_MONTH : Ljava/time/temporal/ChronoField;
    //   190: iconst_2
    //   191: invokevirtual appendValue : (Ljava/time/temporal/TemporalField;I)Ljava/time/format/DateTimeFormatterBuilder;
    //   194: invokevirtual toFormatter : ()Ljava/time/format/DateTimeFormatter;
    //   197: putstatic com/fasterxml/Zg9.ZY : Ljava/time/format/DateTimeFormatter;
    //   200: return
  }
}


/* Location:              C:\Program Files\BurpSuitePro\burpsuite_pro.jar!\com\fasterxml\Zg9.class
 * Java compiler version: 8 (52.0)
 * JD-Core Version:       1.1.3
 */