package com.fasterxml;

import com.fasterxml.Zb.Zf;
import com.fasterxml.Zb.Zl;
import com.fasterxml.Zor.Zo;
import com.fasterxml.Zor.Zy_;
import com.fasterxml.Zor.Zyd;
import com.fasterxml.Zor.Zyi;
import com.fasterxml.Zp.Za;
import java.io.IOException;
import java.time.LocalDateTime;
import java.time.format.DateTimeFormatter;

public class Zl_ extends Zsu<LocalDateTime> {
  private static final long serialVersionUID = 1L;
  
  public static final Zl_ ZI = new Zl_();
  
  protected Zl_() {
    this((DateTimeFormatter)null);
  }
  
  public Zl_(DateTimeFormatter paramDateTimeFormatter) {
    super(LocalDateTime.class, paramDateTimeFormatter);
  }
  
  protected Zl_(Zl_ paramZl_, Boolean paramBoolean1, Boolean paramBoolean2, DateTimeFormatter paramDateTimeFormatter) {
    super(paramZl_, paramBoolean1, paramBoolean2, paramDateTimeFormatter, null);
  }
  
  protected Zsu<LocalDateTime> ZI(Boolean paramBoolean, DateTimeFormatter paramDateTimeFormatter, Zqi paramZqi) {
    return new Zl_(this, paramBoolean, this.ZL, paramDateTimeFormatter);
  }
  
  protected DateTimeFormatter ZJ() {
    return DateTimeFormatter.ISO_LOCAL_DATE_TIME;
  }
  
  public void Zv(LocalDateTime paramLocalDateTime, Zf paramZf, Zyi paramZyi) throws IOException {
    // Byte code:
    //   0: invokestatic Zm : ()[I
    //   3: astore #4
    //   5: aload_0
    //   6: aload_3
    //   7: invokevirtual Za : (Lcom/fasterxml/Zor/Zyi;)Z
    //   10: ifeq -> 40
    //   13: aload_2
    //   14: invokevirtual Zd : ()V
    //   17: aload_0
    //   18: aload_1
    //   19: aload_2
    //   20: aload_3
    //   21: invokespecial ZB : (Ljava/time/LocalDateTime;Lcom/fasterxml/Zb/Zf;Lcom/fasterxml/Zor/Zyi;)V
    //   24: aload_2
    //   25: invokevirtual ZI : ()V
    //   28: aload #4
    //   30: ifnull -> 67
    //   33: goto -> 40
    //   36: invokestatic a : (Ljava/io/IOException;)Ljava/io/IOException;
    //   39: athrow
    //   40: aload_0
    //   41: getfield ZE : Ljava/time/format/DateTimeFormatter;
    //   44: astore #5
    //   46: aload #5
    //   48: ifnonnull -> 57
    //   51: aload_0
    //   52: invokevirtual ZJ : ()Ljava/time/format/DateTimeFormatter;
    //   55: astore #5
    //   57: aload_2
    //   58: aload_1
    //   59: aload #5
    //   61: invokevirtual format : (Ljava/time/format/DateTimeFormatter;)Ljava/lang/String;
    //   64: invokevirtual ZD : (Ljava/lang/String;)V
    //   67: return
    // Exception table:
    //   from	to	target	type
    //   5	33	36	java/io/IOException
  }
  
  public void ZF(LocalDateTime paramLocalDateTime, Zf paramZf, Zyi paramZyi, Za paramZa) throws IOException {
    // Byte code:
    //   0: invokestatic Zm : ()[I
    //   3: aload #4
    //   5: aload_2
    //   6: aload #4
    //   8: aload_1
    //   9: aload_0
    //   10: aload_3
    //   11: invokevirtual Zj : (Lcom/fasterxml/Zor/Zyi;)Lcom/fasterxml/Zb/Zl;
    //   14: invokevirtual Zm : (Ljava/lang/Object;Lcom/fasterxml/Zb/Zl;)Lcom/fasterxml/Zo2/Zn;
    //   17: invokevirtual ZA : (Lcom/fasterxml/Zb/Zf;Lcom/fasterxml/Zo2/Zn;)Lcom/fasterxml/Zo2/Zn;
    //   20: astore #6
    //   22: astore #5
    //   24: aload #6
    //   26: ifnull -> 66
    //   29: aload #6
    //   31: getfield Zg : Lcom/fasterxml/Zb/Zl;
    //   34: getstatic com/fasterxml/Zb/Zl.START_ARRAY : Lcom/fasterxml/Zb/Zl;
    //   37: if_acmpne -> 66
    //   40: goto -> 47
    //   43: invokestatic a : (Ljava/io/IOException;)Ljava/io/IOException;
    //   46: athrow
    //   47: aload_0
    //   48: aload_1
    //   49: aload_2
    //   50: aload_3
    //   51: invokespecial ZB : (Ljava/time/LocalDateTime;Lcom/fasterxml/Zb/Zf;Lcom/fasterxml/Zor/Zyi;)V
    //   54: aload #5
    //   56: ifnull -> 93
    //   59: goto -> 66
    //   62: invokestatic a : (Ljava/io/IOException;)Ljava/io/IOException;
    //   65: athrow
    //   66: aload_0
    //   67: getfield ZE : Ljava/time/format/DateTimeFormatter;
    //   70: astore #7
    //   72: aload #7
    //   74: ifnonnull -> 83
    //   77: aload_0
    //   78: invokevirtual ZJ : ()Ljava/time/format/DateTimeFormatter;
    //   81: astore #7
    //   83: aload_2
    //   84: aload_1
    //   85: aload #7
    //   87: invokevirtual format : (Ljava/time/format/DateTimeFormatter;)Ljava/lang/String;
    //   90: invokevirtual ZD : (Ljava/lang/String;)V
    //   93: aload #4
    //   95: aload_2
    //   96: aload #6
    //   98: invokevirtual ZP : (Lcom/fasterxml/Zb/Zf;Lcom/fasterxml/Zo2/Zn;)Lcom/fasterxml/Zo2/Zn;
    //   101: pop
    //   102: return
    // Exception table:
    //   from	to	target	type
    //   24	40	43	java/io/IOException
    //   29	59	62	java/io/IOException
  }
  
  private final void ZB(LocalDateTime paramLocalDateTime, Zf paramZf, Zyi paramZyi) throws IOException {
    // Byte code:
    //   0: aload_2
    //   1: aload_1
    //   2: invokevirtual getYear : ()I
    //   5: invokevirtual Zd : (I)V
    //   8: invokestatic Zm : ()[I
    //   11: aload_2
    //   12: aload_1
    //   13: invokevirtual getMonthValue : ()I
    //   16: invokevirtual Zd : (I)V
    //   19: aload_2
    //   20: aload_1
    //   21: invokevirtual getDayOfMonth : ()I
    //   24: invokevirtual Zd : (I)V
    //   27: aload_2
    //   28: aload_1
    //   29: invokevirtual getHour : ()I
    //   32: invokevirtual Zd : (I)V
    //   35: aload_2
    //   36: aload_1
    //   37: invokevirtual getMinute : ()I
    //   40: invokevirtual Zd : (I)V
    //   43: aload_1
    //   44: invokevirtual getSecond : ()I
    //   47: istore #5
    //   49: aload_1
    //   50: invokevirtual getNano : ()I
    //   53: istore #6
    //   55: astore #4
    //   57: iload #5
    //   59: ifgt -> 74
    //   62: iload #6
    //   64: ifle -> 143
    //   67: goto -> 74
    //   70: invokestatic a : (Ljava/io/IOException;)Ljava/io/IOException;
    //   73: athrow
    //   74: aload_2
    //   75: iload #5
    //   77: invokevirtual Zd : (I)V
    //   80: iload #6
    //   82: ifle -> 143
    //   85: goto -> 92
    //   88: invokestatic a : (Ljava/io/IOException;)Ljava/io/IOException;
    //   91: athrow
    //   92: aload_0
    //   93: aload_3
    //   94: invokevirtual Zl : (Lcom/fasterxml/Zor/Zyi;)Z
    //   97: ifeq -> 125
    //   100: goto -> 107
    //   103: invokestatic a : (Ljava/io/IOException;)Ljava/io/IOException;
    //   106: athrow
    //   107: aload_2
    //   108: iload #6
    //   110: invokevirtual Zd : (I)V
    //   113: aload #4
    //   115: ifnull -> 143
    //   118: goto -> 125
    //   121: invokestatic a : (Ljava/io/IOException;)Ljava/io/IOException;
    //   124: athrow
    //   125: aload_2
    //   126: aload_1
    //   127: getstatic java/time/temporal/ChronoField.MILLI_OF_SECOND : Ljava/time/temporal/ChronoField;
    //   130: invokevirtual get : (Ljava/time/temporal/TemporalField;)I
    //   133: invokevirtual Zd : (I)V
    //   136: goto -> 143
    //   139: invokestatic a : (Ljava/io/IOException;)Ljava/io/IOException;
    //   142: athrow
    //   143: return
    // Exception table:
    //   from	to	target	type
    //   57	67	70	java/io/IOException
    //   62	85	88	java/io/IOException
    //   74	100	103	java/io/IOException
    //   92	118	121	java/io/IOException
    //   107	136	139	java/io/IOException
  }
  
  protected Zl Zj(Zyi paramZyi) {
    return Za(paramZyi) ? Zl.START_ARRAY : Zl.VALUE_STRING;
  }
  
  protected Zsu<?> ZF(Boolean paramBoolean1, Boolean paramBoolean2) {
    return new Zl_(this, this.Zt, paramBoolean2, this.ZE);
  }
  
  private static IOException a(IOException paramIOException) {
    return paramIOException;
  }
}


/* Location:              C:\Program Files\BurpSuitePro\burpsuite_pro.jar!\com\fasterxml\Zl_.class
 * Java compiler version: 8 (52.0)
 * JD-Core Version:       1.1.3
 */