package com.fasterxml;

import com.fasterxml.Zb.Zd;
import com.fasterxml.Zb.Zg;
import com.fasterxml.Zor.Zyg;
import java.io.IOException;
import java.time.DateTimeException;
import java.time.YearMonth;
import java.time.format.DateTimeFormatter;

public class Zqb extends Zq2<YearMonth> {
  private static final long serialVersionUID = 1L;
  
  public static final Zqb ZT;
  
  private static final String[] h;
  
  private static final String[] i;
  
  public Zqb() {
    this(DateTimeFormatter.ofPattern(d(17684, 12534)));
  }
  
  public Zqb(DateTimeFormatter paramDateTimeFormatter) {
    super(YearMonth.class, paramDateTimeFormatter);
  }
  
  protected Zqb(Zqb paramZqb, Boolean paramBoolean) {
    super(paramZqb, paramBoolean);
  }
  
  public Zqb(Zqb paramZqb, Boolean paramBoolean, DateTimeFormatter paramDateTimeFormatter, Zqi paramZqi) {
    super(paramZqb, paramBoolean, paramDateTimeFormatter, paramZqi);
  }
  
  protected Zqb ZQ(DateTimeFormatter paramDateTimeFormatter) {
    return new Zqb(this, Boolean.valueOf(this.Zb), paramDateTimeFormatter, this.Zw);
  }
  
  protected Zqb ZI(Boolean paramBoolean) {
    return new Zqb(this, paramBoolean);
  }
  
  public YearMonth Zi(Zg paramZg, Zyg paramZyg) throws IOException {
    // Byte code:
    //   0: aload_1
    //   1: getstatic com/fasterxml/Zb/Zl.VALUE_STRING : Lcom/fasterxml/Zb/Zl;
    //   4: invokevirtual ZL : (Lcom/fasterxml/Zb/Zl;)Z
    //   7: ifeq -> 25
    //   10: aload_0
    //   11: aload_1
    //   12: aload_2
    //   13: aload_1
    //   14: invokevirtual ZR : ()Ljava/lang/String;
    //   17: invokevirtual ZX : (Lcom/fasterxml/Zb/Zg;Lcom/fasterxml/Zor/Zyg;Ljava/lang/String;)Ljava/time/YearMonth;
    //   20: areturn
    //   21: invokestatic a : (Ljava/lang/Exception;)Ljava/lang/Exception;
    //   24: athrow
    //   25: aload_1
    //   26: invokevirtual Zp : ()Z
    //   29: ifeq -> 53
    //   32: aload_0
    //   33: aload_1
    //   34: aload_2
    //   35: aload_2
    //   36: aload_1
    //   37: aload_0
    //   38: aload_0
    //   39: invokevirtual ZX : ()Ljava/lang/Class;
    //   42: invokevirtual Zc : (Lcom/fasterxml/Zb/Zg;Lcom/fasterxml/Zor/Zyo;Ljava/lang/Class;)Ljava/lang/String;
    //   45: invokevirtual ZX : (Lcom/fasterxml/Zb/Zg;Lcom/fasterxml/Zor/Zyg;Ljava/lang/String;)Ljava/time/YearMonth;
    //   48: areturn
    //   49: invokestatic a : (Ljava/lang/Exception;)Ljava/lang/Exception;
    //   52: athrow
    //   53: aload_1
    //   54: invokevirtual Zs : ()Z
    //   57: ifeq -> 293
    //   60: aload_1
    //   61: invokevirtual ZV : ()Lcom/fasterxml/Zb/Zl;
    //   64: astore_3
    //   65: aload_3
    //   66: getstatic com/fasterxml/Zb/Zl.END_ARRAY : Lcom/fasterxml/Zb/Zl;
    //   69: if_acmpne -> 78
    //   72: aconst_null
    //   73: areturn
    //   74: invokestatic a : (Ljava/lang/Exception;)Ljava/lang/Exception;
    //   77: athrow
    //   78: aload_3
    //   79: getstatic com/fasterxml/Zb/Zl.VALUE_STRING : Lcom/fasterxml/Zb/Zl;
    //   82: if_acmpeq -> 99
    //   85: aload_3
    //   86: getstatic com/fasterxml/Zb/Zl.VALUE_EMBEDDED_OBJECT : Lcom/fasterxml/Zb/Zl;
    //   89: if_acmpne -> 150
    //   92: goto -> 99
    //   95: invokestatic a : (Ljava/lang/Exception;)Ljava/lang/Exception;
    //   98: athrow
    //   99: aload_2
    //   100: getstatic com/fasterxml/Zor/Zyp.UNWRAP_SINGLE_VALUE_ARRAYS : Lcom/fasterxml/Zor/Zyp;
    //   103: invokevirtual Zg : (Lcom/fasterxml/Zor/Zyp;)Z
    //   106: ifeq -> 150
    //   109: goto -> 116
    //   112: invokestatic a : (Ljava/lang/Exception;)Ljava/lang/Exception;
    //   115: athrow
    //   116: aload_0
    //   117: aload_1
    //   118: aload_2
    //   119: invokevirtual Zi : (Lcom/fasterxml/Zb/Zg;Lcom/fasterxml/Zor/Zyg;)Ljava/time/YearMonth;
    //   122: astore #4
    //   124: aload_1
    //   125: invokevirtual ZV : ()Lcom/fasterxml/Zb/Zl;
    //   128: getstatic com/fasterxml/Zb/Zl.END_ARRAY : Lcom/fasterxml/Zb/Zl;
    //   131: if_acmpeq -> 147
    //   134: aload_0
    //   135: aload_1
    //   136: aload_2
    //   137: invokevirtual ZH : (Lcom/fasterxml/Zb/Zg;Lcom/fasterxml/Zor/Zyg;)V
    //   140: goto -> 147
    //   143: invokestatic a : (Ljava/lang/Exception;)Ljava/lang/Exception;
    //   146: athrow
    //   147: aload #4
    //   149: areturn
    //   150: aload_3
    //   151: getstatic com/fasterxml/Zb/Zl.VALUE_NUMBER_INT : Lcom/fasterxml/Zb/Zl;
    //   154: if_acmpeq -> 182
    //   157: aload_0
    //   158: aload_2
    //   159: getstatic com/fasterxml/Zb/Zl.VALUE_NUMBER_INT : Lcom/fasterxml/Zb/Zl;
    //   162: sipush #17686
    //   165: sipush #-21981
    //   168: invokestatic d : (II)Ljava/lang/String;
    //   171: invokevirtual Zc : (Lcom/fasterxml/Zor/Zyg;Lcom/fasterxml/Zb/Zl;Ljava/lang/String;)Ljava/lang/Object;
    //   174: pop
    //   175: goto -> 182
    //   178: invokestatic a : (Ljava/lang/Exception;)Ljava/lang/Exception;
    //   181: athrow
    //   182: aload_1
    //   183: invokevirtual Ze : ()I
    //   186: istore #4
    //   188: aload_1
    //   189: iconst_m1
    //   190: invokevirtual Zq : (I)I
    //   193: istore #5
    //   195: iload #5
    //   197: iconst_m1
    //   198: if_icmpne -> 249
    //   201: aload_1
    //   202: getstatic com/fasterxml/Zb/Zl.VALUE_NUMBER_INT : Lcom/fasterxml/Zb/Zl;
    //   205: invokevirtual ZL : (Lcom/fasterxml/Zb/Zl;)Z
    //   208: ifne -> 243
    //   211: goto -> 218
    //   214: invokestatic a : (Ljava/lang/Exception;)Ljava/lang/Exception;
    //   217: athrow
    //   218: aload_0
    //   219: aload_2
    //   220: getstatic com/fasterxml/Zb/Zl.VALUE_NUMBER_INT : Lcom/fasterxml/Zb/Zl;
    //   223: sipush #17685
    //   226: sipush #-22533
    //   229: invokestatic d : (II)Ljava/lang/String;
    //   232: invokevirtual Zc : (Lcom/fasterxml/Zor/Zyg;Lcom/fasterxml/Zb/Zl;Ljava/lang/String;)Ljava/lang/Object;
    //   235: pop
    //   236: goto -> 243
    //   239: invokestatic a : (Ljava/lang/Exception;)Ljava/lang/Exception;
    //   242: athrow
    //   243: aload_1
    //   244: invokevirtual Ze : ()I
    //   247: istore #5
    //   249: aload_1
    //   250: invokevirtual ZV : ()Lcom/fasterxml/Zb/Zl;
    //   253: getstatic com/fasterxml/Zb/Zl.END_ARRAY : Lcom/fasterxml/Zb/Zl;
    //   256: if_acmpeq -> 285
    //   259: aload_2
    //   260: aload_1
    //   261: aload_0
    //   262: invokevirtual ZX : ()Ljava/lang/Class;
    //   265: getstatic com/fasterxml/Zb/Zl.END_ARRAY : Lcom/fasterxml/Zb/Zl;
    //   268: sipush #17687
    //   271: sipush #-12675
    //   274: invokestatic d : (II)Ljava/lang/String;
    //   277: invokevirtual Zq : (Lcom/fasterxml/Zb/Zg;Ljava/lang/Class;Lcom/fasterxml/Zb/Zl;Ljava/lang/String;)Lcom/fasterxml/Zor/Zy_;
    //   280: athrow
    //   281: invokestatic a : (Ljava/lang/Exception;)Ljava/lang/Exception;
    //   284: athrow
    //   285: iload #4
    //   287: iload #5
    //   289: invokestatic of : (II)Ljava/time/YearMonth;
    //   292: areturn
    //   293: aload_1
    //   294: getstatic com/fasterxml/Zb/Zl.VALUE_EMBEDDED_OBJECT : Lcom/fasterxml/Zb/Zl;
    //   297: invokevirtual ZL : (Lcom/fasterxml/Zb/Zl;)Z
    //   300: ifeq -> 315
    //   303: aload_1
    //   304: invokevirtual ZO : ()Ljava/lang/Object;
    //   307: checkcast java/time/YearMonth
    //   310: areturn
    //   311: invokestatic a : (Ljava/lang/Exception;)Ljava/lang/Exception;
    //   314: athrow
    //   315: aload_0
    //   316: aload_2
    //   317: aload_1
    //   318: iconst_2
    //   319: anewarray com/fasterxml/Zb/Zl
    //   322: dup
    //   323: iconst_0
    //   324: getstatic com/fasterxml/Zb/Zl.VALUE_STRING : Lcom/fasterxml/Zb/Zl;
    //   327: aastore
    //   328: dup
    //   329: iconst_1
    //   330: getstatic com/fasterxml/Zb/Zl.START_ARRAY : Lcom/fasterxml/Zb/Zl;
    //   333: aastore
    //   334: invokevirtual Zx : (Lcom/fasterxml/Zor/Zyg;Lcom/fasterxml/Zb/Zg;[Lcom/fasterxml/Zb/Zl;)Ljava/lang/Object;
    //   337: checkcast java/time/YearMonth
    //   340: areturn
    // Exception table:
    //   from	to	target	type
    //   0	21	21	java/io/IOException
    //   25	49	49	java/io/IOException
    //   65	74	74	java/io/IOException
    //   78	92	95	java/io/IOException
    //   85	109	112	java/io/IOException
    //   124	140	143	java/io/IOException
    //   150	175	178	java/io/IOException
    //   195	211	214	java/io/IOException
    //   201	236	239	java/io/IOException
    //   249	281	281	java/io/IOException
    //   293	311	311	java/io/IOException
  }
  
  protected YearMonth ZX(Zg paramZg, Zyg paramZyg, String paramString) throws IOException {
    String str = paramString.trim();
    try {
      if (str.length() == 0)
        return ZN(paramZg, paramZyg, str); 
    } catch (DateTimeException dateTimeException) {
      throw a(null);
    } 
    try {
      return YearMonth.parse(str, this.Za);
    } catch (DateTimeException dateTimeException) {
      return (YearMonth)Z_(paramZyg, dateTimeException, str);
    } 
  }
  
  static {
    // Byte code:
    //   0: iconst_4
    //   1: anewarray java/lang/String
    //   4: astore #5
    //   6: iconst_0
    //   7: istore_3
    //   8: ldc '.òäP¬±/®z½«VC¦|IØ°'
    //   10: dup
    //   11: astore_2
    //   12: invokevirtual length : ()I
    //   15: istore #4
    //   17: bipush #21
    //   19: istore_1
    //   20: iconst_m1
    //   21: istore_0
    //   22: bipush #127
    //   24: iinc #0, 1
    //   27: aload_2
    //   28: iload_0
    //   29: dup
    //   30: iload_1
    //   31: iadd
    //   32: invokevirtual substring : (II)Ljava/lang/String;
    //   35: iconst_m1
    //   36: goto -> 141
    //   39: aload #5
    //   41: swap
    //   42: iload_3
    //   43: iinc #3, 1
    //   46: swap
    //   47: aastore
    //   48: iload_0
    //   49: iload_1
    //   50: iadd
    //   51: dup
    //   52: istore_0
    //   53: iload #4
    //   55: if_icmpge -> 67
    //   58: aload_2
    //   59: iload_0
    //   60: invokevirtual charAt : (I)C
    //   63: istore_1
    //   64: goto -> 22
    //   67: ldc 'á÷gT7á'
    //   69: dup
    //   70: astore_2
    //   71: invokevirtual length : ()I
    //   74: istore #4
    //   76: bipush #6
    //   78: istore_1
    //   79: iconst_m1
    //   80: istore_0
    //   81: bipush #29
    //   83: iinc #0, 1
    //   86: aload_2
    //   87: iload_0
    //   88: dup
    //   89: iload_1
    //   90: iadd
    //   91: invokevirtual substring : (II)Ljava/lang/String;
    //   94: iconst_0
    //   95: goto -> 141
    //   98: aload #5
    //   100: swap
    //   101: iload_3
    //   102: iinc #3, 1
    //   105: swap
    //   106: aastore
    //   107: iload_0
    //   108: iload_1
    //   109: iadd
    //   110: dup
    //   111: istore_0
    //   112: iload #4
    //   114: if_icmpge -> 126
    //   117: aload_2
    //   118: iload_0
    //   119: invokevirtual charAt : (I)C
    //   122: istore_1
    //   123: goto -> 81
    //   126: aload #5
    //   128: putstatic com/fasterxml/Zqb.h : [Ljava/lang/String;
    //   131: iconst_4
    //   132: anewarray java/lang/String
    //   135: putstatic com/fasterxml/Zqb.i : [Ljava/lang/String;
    //   138: goto -> 300
    //   141: dup_x2
    //   142: pop
    //   143: invokevirtual toCharArray : ()[C
    //   146: dup_x1
    //   147: arraylength
    //   148: dup_x2
    //   149: pop
    //   150: iconst_0
    //   151: istore #6
    //   153: dup2_x1
    //   154: pop2
    //   155: dup_x2
    //   156: iconst_1
    //   157: if_icmpgt -> 260
    //   160: dup2
    //   161: swap
    //   162: iload #6
    //   164: dup2_x1
    //   165: caload
    //   166: swap
    //   167: iload #6
    //   169: bipush #7
    //   171: irem
    //   172: tableswitch default -> 242, 0 -> 212, 1 -> 217, 2 -> 222, 3 -> 227, 4 -> 232, 5 -> 237
    //   212: bipush #24
    //   214: goto -> 244
    //   217: bipush #89
    //   219: goto -> 244
    //   222: bipush #57
    //   224: goto -> 244
    //   227: bipush #87
    //   229: goto -> 244
    //   232: bipush #16
    //   234: goto -> 244
    //   237: bipush #68
    //   239: goto -> 244
    //   242: bipush #120
    //   244: ixor
    //   245: ixor
    //   246: i2c
    //   247: castore
    //   248: iinc #6, 1
    //   251: dup
    //   252: ifne -> 260
    //   255: dup2
    //   256: dup_x1
    //   257: goto -> 164
    //   260: dup2_x1
    //   261: pop2
    //   262: dup_x2
    //   263: iload #6
    //   265: if_icmpgt -> 160
    //   268: pop
    //   269: new java/lang/String
    //   272: dup_x1
    //   273: swap
    //   274: invokespecial <init> : ([C)V
    //   277: invokevirtual intern : ()Ljava/lang/String;
    //   280: swap
    //   281: pop
    //   282: swap
    //   283: tableswitch default -> 39, 0 -> 98
    //   300: new com/fasterxml/Zqb
    //   303: dup
    //   304: invokespecial <init> : ()V
    //   307: putstatic com/fasterxml/Zqb.ZT : Lcom/fasterxml/Zqb;
    //   310: return
  }
  
  private static Exception a(Exception paramException) {
    return paramException;
  }
  
  private static String d(int paramInt1, int paramInt2) {
    int i = (paramInt1 ^ 0x4517) & 0xFFFF;
    if (i[i] == null) {
      char[] arrayOfChar = h[i].toCharArray();
      switch (arrayOfChar[0] & 0xFF) {
        case 0:
        
        case 1:
        
        case 2:
        
        case 3:
        
        case 4:
        
        case 5:
        
        case 6:
        
        case 7:
        
        case 8:
        
        case 9:
        
        case 10:
        
        case 11:
        
        case 12:
        
        case 13:
        
        case 14:
        
        case 15:
        
        case 16:
        
        case 17:
        
        case 18:
        
        case 19:
        
        case 20:
        
        case 21:
        
        case 22:
        
        case 23:
        
        case 24:
        
        case 25:
        
        case 26:
        
        case 27:
        
        case 28:
        
        case 29:
        
        case 30:
        
        case 31:
        
        case 32:
        
        case 33:
        
        case 34:
        
        case 35:
        
        case 36:
        
        case 37:
        
        case 38:
        
        case 39:
        
        case 40:
        
        case 41:
        
        case 42:
        
        case 43:
        
        case 44:
        
        case 45:
        
        case 46:
        
        case 47:
        
        case 48:
        
        case 49:
        
        case 50:
        
        case 51:
        
        case 52:
        
        case 53:
        
        case 54:
        
        case 55:
        
        case 56:
        
        case 57:
        
        case 58:
        
        case 59:
        
        case 60:
        
        case 61:
        
        case 62:
        
        case 63:
        
        case 64:
        
        case 65:
        
        case 66:
        
        case 67:
        
        case 68:
        
        case 69:
        
        case 70:
        
        case 71:
        
        case 72:
        
        case 73:
        
        case 74:
        
        case 75:
        
        case 76:
        
        case 77:
        
        case 78:
        
        case 79:
        
        case 80:
        
        case 81:
        
        case 82:
        
        case 83:
        
        case 84:
        
        case 85:
        
        case 86:
        
        case 87:
        
        case 88:
        
        case 89:
        
        case 90:
        
        case 91:
        
        case 92:
        
        case 93:
        
        case 94:
        
        case 95:
        
        case 96:
        
        case 97:
        
        case 98:
        
        case 99:
        
        case 100:
        
        case 101:
        
        case 102:
        
        case 103:
        
        case 104:
        
        case 105:
        
        case 106:
        
        case 107:
        
        case 108:
        
        case 109:
        
        case 110:
        
        case 111:
        
        case 112:
        
        case 113:
        
        case 114:
        
        case 115:
        
        case 116:
        
        case 117:
        
        case 118:
        
        case 119:
        
        case 120:
        
        case 121:
        
        case 122:
        
        case 123:
        
        case 124:
        
        case 125:
        
        case 126:
        
        case 127:
        
        case 128:
        
        case 129:
        
        case 130:
        
        case 131:
        
        case 132:
        
        case 133:
        
        case 134:
        
        case 135:
        
        case 136:
        
        case 137:
        
        case 138:
        
        case 139:
        
        case 140:
        
        case 141:
        
        case 142:
        
        case 143:
        
        case 144:
        
        case 145:
        
        case 146:
        
        case 147:
        
        case 148:
        
        case 149:
        
        case 150:
        
        case 151:
        
        case 152:
        
        case 153:
        
        case 154:
        
        case 155:
        
        case 156:
        
        case 157:
        
        case 158:
        
        case 159:
        
        case 160:
        
        case 161:
        
        case 162:
        
        case 163:
        
        case 164:
        
        case 165:
        
        case 166:
        
        case 167:
        
        case 168:
        
        case 169:
        
        case 170:
        
        case 171:
        
        case 172:
        
        case 173:
        
        case 174:
        
        case 175:
        
        case 176:
        
        case 177:
        
        case 178:
        
        case 179:
        
        case 180:
        
        case 181:
        
        case 182:
        
        case 183:
        
        case 184:
        
        case 185:
        
        case 186:
        
        case 187:
        
        case 188:
        
        case 189:
        
        case 190:
        
        case 191:
        
        case 192:
        
        case 193:
        
        case 194:
        
        case 195:
        
        case 196:
        
        case 197:
        
        case 198:
        
        case 199:
        
        case 200:
        
        case 201:
        
        case 202:
        
        case 203:
        
        case 204:
        
        case 205:
        
        case 206:
        
        case 207:
        
        case 208:
        
        case 209:
        
        case 210:
        
        case 211:
        
        case 212:
        
        case 213:
        
        case 214:
        
        case 215:
        
        case 216:
        
        case 217:
        
        case 218:
        
        case 219:
        
        case 220:
        
        case 221:
        
        case 222:
        
        case 223:
        
        case 224:
        
        case 225:
        
        case 226:
        
        case 227:
        
        case 228:
        
        case 229:
        
        case 230:
        
        case 231:
        
        case 232:
        
        case 233:
        
        case 234:
        
        case 235:
        
        case 236:
        
        case 237:
        
        case 238:
        
        case 239:
        
        case 240:
        
        case 241:
        
        case 242:
        
        case 243:
        
        case 244:
        
        case 245:
        
        case 246:
        
        case 247:
        
        case 248:
        
        case 249:
        
        case 250:
        
        case 251:
        
        case 252:
        
        case 253:
        
        case 254:
        
        default:
          break;
      } 
      byte b1 = 13;
      int j = (paramInt2 & 0xFF) - b1;
      if (j < 0)
        j += 256; 
      int k = ((paramInt2 & 0xFFFF) >>> 8) - b1;
      if (k < 0)
        k += 256; 
      for (byte b2 = 0; b2 < arrayOfChar.length; b2++) {
        int m = b2 % 2;
        if (m == 0) {
          arrayOfChar[b2] = (char)(arrayOfChar[b2] ^ j);
          j = ((j >>> 3 | j << 5) ^ arrayOfChar[b2]) & 0xFF;
        } else {
          arrayOfChar[b2] = (char)(arrayOfChar[b2] ^ k);
          k = ((k >>> 3 | k << 5) ^ arrayOfChar[b2]) & 0xFF;
        } 
      } 
      i[i] = (new String(arrayOfChar)).intern();
    } 
    return i[i];
  }
}


/* Location:              C:\Program Files\BurpSuitePro\burpsuite_pro.jar!\com\fasterxml\Zqb.class
 * Java compiler version: 8 (52.0)
 * JD-Core Version:       1.1.3
 */