package com.fasterxml;

import burp.Zbqc;
import com.fasterxml.Zb.Ze;
import com.fasterxml.Zb.Zg;
import com.fasterxml.Zb.Zk;
import com.fasterxml.Zb.Zl;
import com.fasterxml.Zb.Zm5;
import com.fasterxml.Zb.Zy;
import com.fasterxml.Zc.Zy;
import java.io.IOException;
import java.io.OutputStream;
import java.math.BigDecimal;
import java.math.BigInteger;

public class Zyb extends Zy {
  protected Zyg Zv;
  
  protected boolean Zj;
  
  protected Zyu Zp;
  
  protected Zl Zx;
  
  protected Zl ZX;
  
  protected Zyv Zz;
  
  protected Zyv ZK;
  
  protected Zyg Zh;
  
  protected int Zu;
  
  private static final String[] c;
  
  private static final String[] d;
  
  public Zyb(Zg paramZg, Zyg paramZyg, Zyu paramZyu, boolean paramBoolean) {
    super(paramZg);
    this.Zv = paramZyg;
    this.Zh = paramZyg;
    this.Zz = Zyv.Zy(paramZyg);
    this.Zp = paramZyu;
    this.Zj = paramBoolean;
    int[] arrayOfInt = Zyg.Zf();
    if (Zbqc.Zwu() == null)
      Zyg.Zx(new int[2]); 
  }
  
  public Zl Zh() {
    return this.Zx;
  }
  
  @Deprecated
  public Zl Zj() {
    return this.Zx;
  }
  
  public final int Zy() {
    Zl zl = this.Zx;
    return (zl == null) ? 0 : zl.Zs();
  }
  
  @Deprecated
  public final int Zt() {
    return Zy();
  }
  
  public boolean Zq() {
    return (this.Zx != null);
  }
  
  public boolean Ze(int paramInt) {
    Zl zl = this.Zx;
    return (zl == null) ? ((0 == paramInt)) : ((zl.Zs() == paramInt));
  }
  
  public final boolean ZL(Zl paramZl) {
    return (this.Zx == paramZl);
  }
  
  public boolean Zs() {
    return (this.Zx == Zl.START_ARRAY);
  }
  
  public boolean Zp() {
    return (this.Zx == Zl.START_OBJECT);
  }
  
  public Zm5 Zz() {
    return this.ZP.Zz();
  }
  
  @Deprecated
  public Zm5 Zl() {
    return this.ZP.Zl();
  }
  
  public Zm5 ZQ() {
    return this.ZP.ZQ();
  }
  
  @Deprecated
  public Zm5 ZK() {
    return this.ZP.ZK();
  }
  
  public Ze ZT1() {
    return ZnK();
  }
  
  @Deprecated
  public String ZD() throws IOException {
    Ze ze = ZnK();
    try {
      if (this.Zx == Zl.START_OBJECT || this.Zx == Zl.START_ARRAY) {
        Ze ze1 = ze.Zf();
        try {
        
        } catch (IOException iOException) {
          throw a(null);
        } 
        return (ze1 == null) ? null : ze1.Z_();
      } 
    } catch (IOException iOException) {
      throw a(null);
    } 
    return ze.Z_();
  }
  
  public String ZS() throws IOException {
    Ze ze = ZnK();
    try {
      if (this.Zx == Zl.START_OBJECT || this.Zx == Zl.START_ARRAY) {
        Ze ze1 = ze.Zf();
        try {
        
        } catch (IOException iOException) {
          throw a(null);
        } 
        return (ze1 == null) ? null : ze1.Z_();
      } 
    } catch (IOException iOException) {
      throw a(null);
    } 
    return ze.Z_();
  }
  
  public void Zo() {
    if (this.Zx != null) {
      this.ZX = this.Zx;
      this.Zx = null;
    } 
  }
  
  public Zl ZV() throws IOException {
    // Byte code:
    //   0: invokestatic Zf : ()[I
    //   3: astore_1
    //   4: aload_0
    //   5: getfield Zj : Z
    //   8: ifne -> 118
    //   11: aload_0
    //   12: getfield Zx : Lcom/fasterxml/Zb/Zl;
    //   15: ifnull -> 118
    //   18: goto -> 25
    //   21: invokestatic a : (Ljava/io/IOException;)Ljava/io/IOException;
    //   24: athrow
    //   25: aload_0
    //   26: getfield ZK : Lcom/fasterxml/Zyv;
    //   29: ifnonnull -> 118
    //   32: goto -> 39
    //   35: invokestatic a : (Ljava/io/IOException;)Ljava/io/IOException;
    //   38: athrow
    //   39: aload_0
    //   40: getfield Zx : Lcom/fasterxml/Zb/Zl;
    //   43: invokevirtual Zl : ()Z
    //   46: ifeq -> 118
    //   49: goto -> 56
    //   52: invokestatic a : (Ljava/io/IOException;)Ljava/io/IOException;
    //   55: athrow
    //   56: aload_0
    //   57: getfield Zz : Lcom/fasterxml/Zyv;
    //   60: invokevirtual Zd : ()Z
    //   63: ifne -> 118
    //   66: goto -> 73
    //   69: invokestatic a : (Ljava/io/IOException;)Ljava/io/IOException;
    //   72: athrow
    //   73: aload_0
    //   74: getfield Zp : Lcom/fasterxml/Zyu;
    //   77: getstatic com/fasterxml/Zyu.ONLY_INCLUDE_ALL : Lcom/fasterxml/Zyu;
    //   80: if_acmpne -> 118
    //   83: goto -> 90
    //   86: invokestatic a : (Ljava/io/IOException;)Ljava/io/IOException;
    //   89: athrow
    //   90: aload_0
    //   91: getfield Zh : Lcom/fasterxml/Zyg;
    //   94: getstatic com/fasterxml/Zyg.ZR : Lcom/fasterxml/Zyg;
    //   97: if_acmpne -> 118
    //   100: goto -> 107
    //   103: invokestatic a : (Ljava/io/IOException;)Ljava/io/IOException;
    //   106: athrow
    //   107: aload_0
    //   108: aconst_null
    //   109: dup_x1
    //   110: putfield Zx : Lcom/fasterxml/Zb/Zl;
    //   113: areturn
    //   114: invokestatic a : (Ljava/io/IOException;)Ljava/io/IOException;
    //   117: athrow
    //   118: aload_0
    //   119: getfield ZK : Lcom/fasterxml/Zyv;
    //   122: astore_2
    //   123: aload_2
    //   124: ifnull -> 326
    //   127: aload_2
    //   128: invokevirtual Ze : ()Lcom/fasterxml/Zb/Zl;
    //   131: astore_3
    //   132: aload_3
    //   133: ifnull -> 143
    //   136: aload_0
    //   137: aload_3
    //   138: putfield Zx : Lcom/fasterxml/Zb/Zl;
    //   141: aload_3
    //   142: areturn
    //   143: aload_2
    //   144: aload_0
    //   145: getfield Zz : Lcom/fasterxml/Zyv;
    //   148: if_acmpne -> 286
    //   151: aload_0
    //   152: aconst_null
    //   153: putfield ZK : Lcom/fasterxml/Zyv;
    //   156: aload_2
    //   157: invokevirtual Zo : ()Z
    //   160: ifeq -> 224
    //   163: goto -> 170
    //   166: invokestatic a : (Ljava/io/IOException;)Ljava/io/IOException;
    //   169: athrow
    //   170: aload_0
    //   171: getfield ZP : Lcom/fasterxml/Zb/Zg;
    //   174: invokevirtual Zj : ()Lcom/fasterxml/Zb/Zl;
    //   177: astore_3
    //   178: aload_0
    //   179: aload_3
    //   180: putfield Zx : Lcom/fasterxml/Zb/Zl;
    //   183: aload_0
    //   184: getfield Zx : Lcom/fasterxml/Zb/Zl;
    //   187: getstatic com/fasterxml/Zb/Zl.END_ARRAY : Lcom/fasterxml/Zb/Zl;
    //   190: if_acmpne -> 222
    //   193: aload_0
    //   194: aload_0
    //   195: getfield Zz : Lcom/fasterxml/Zyv;
    //   198: invokevirtual ZU : ()Lcom/fasterxml/Zyv;
    //   201: putfield Zz : Lcom/fasterxml/Zyv;
    //   204: aload_0
    //   205: aload_0
    //   206: getfield Zz : Lcom/fasterxml/Zyv;
    //   209: invokevirtual ZJ : ()Lcom/fasterxml/Zyg;
    //   212: putfield Zh : Lcom/fasterxml/Zyg;
    //   215: goto -> 222
    //   218: invokestatic a : (Ljava/io/IOException;)Ljava/io/IOException;
    //   221: athrow
    //   222: aload_3
    //   223: areturn
    //   224: aload_0
    //   225: getfield ZP : Lcom/fasterxml/Zb/Zg;
    //   228: invokevirtual Zh : ()Lcom/fasterxml/Zb/Zl;
    //   231: astore_3
    //   232: aload_3
    //   233: getstatic com/fasterxml/Zb/Zl.END_OBJECT : Lcom/fasterxml/Zb/Zl;
    //   236: if_acmpne -> 268
    //   239: aload_0
    //   240: aload_0
    //   241: getfield Zz : Lcom/fasterxml/Zyv;
    //   244: invokevirtual ZU : ()Lcom/fasterxml/Zyv;
    //   247: putfield Zz : Lcom/fasterxml/Zyv;
    //   250: aload_0
    //   251: aload_0
    //   252: getfield Zz : Lcom/fasterxml/Zyv;
    //   255: invokevirtual ZJ : ()Lcom/fasterxml/Zyg;
    //   258: putfield Zh : Lcom/fasterxml/Zyg;
    //   261: goto -> 268
    //   264: invokestatic a : (Ljava/io/IOException;)Ljava/io/IOException;
    //   267: athrow
    //   268: aload_3
    //   269: getstatic com/fasterxml/Zb/Zl.FIELD_NAME : Lcom/fasterxml/Zb/Zl;
    //   272: if_acmpeq -> 326
    //   275: aload_0
    //   276: aload_3
    //   277: putfield Zx : Lcom/fasterxml/Zb/Zl;
    //   280: aload_3
    //   281: areturn
    //   282: invokestatic a : (Ljava/io/IOException;)Ljava/io/IOException;
    //   285: athrow
    //   286: aload_0
    //   287: getfield Zz : Lcom/fasterxml/Zyv;
    //   290: aload_2
    //   291: invokevirtual Zp : (Lcom/fasterxml/Zyv;)Lcom/fasterxml/Zyv;
    //   294: astore_2
    //   295: aload_0
    //   296: aload_2
    //   297: putfield ZK : Lcom/fasterxml/Zyv;
    //   300: aload_2
    //   301: ifnonnull -> 322
    //   304: aload_0
    //   305: sipush #31462
    //   308: sipush #21970
    //   311: invokestatic b : (II)Ljava/lang/String;
    //   314: invokevirtual Zh : (Ljava/lang/String;)Lcom/fasterxml/Zb/Zm0;
    //   317: athrow
    //   318: invokestatic a : (Ljava/io/IOException;)Ljava/io/IOException;
    //   321: athrow
    //   322: aload_1
    //   323: ifnull -> 127
    //   326: aload_0
    //   327: getfield ZP : Lcom/fasterxml/Zb/Zg;
    //   330: invokevirtual ZV : ()Lcom/fasterxml/Zb/Zl;
    //   333: astore_3
    //   334: aload_3
    //   335: ifnonnull -> 349
    //   338: aload_0
    //   339: aload_3
    //   340: putfield Zx : Lcom/fasterxml/Zb/Zl;
    //   343: aload_3
    //   344: areturn
    //   345: invokestatic a : (Ljava/io/IOException;)Ljava/io/IOException;
    //   348: athrow
    //   349: aload_3
    //   350: invokevirtual Zs : ()I
    //   353: tableswitch default -> 1250, 1 -> 642, 2 -> 896, 3 -> 388, 4 -> 896, 5 -> 1019
    //   388: aload_0
    //   389: getfield Zh : Lcom/fasterxml/Zyg;
    //   392: astore #4
    //   394: aload #4
    //   396: getstatic com/fasterxml/Zyg.ZR : Lcom/fasterxml/Zyg;
    //   399: if_acmpne -> 427
    //   402: aload_0
    //   403: aload_0
    //   404: getfield Zz : Lcom/fasterxml/Zyv;
    //   407: aload #4
    //   409: iconst_1
    //   410: invokevirtual Zc : (Lcom/fasterxml/Zyg;Z)Lcom/fasterxml/Zyv;
    //   413: putfield Zz : Lcom/fasterxml/Zyv;
    //   416: aload_0
    //   417: aload_3
    //   418: dup_x1
    //   419: putfield Zx : Lcom/fasterxml/Zb/Zl;
    //   422: areturn
    //   423: invokestatic a : (Ljava/io/IOException;)Ljava/io/IOException;
    //   426: athrow
    //   427: aload #4
    //   429: ifnonnull -> 451
    //   432: aload_0
    //   433: getfield ZP : Lcom/fasterxml/Zb/Zg;
    //   436: invokevirtual Zc : ()Lcom/fasterxml/Zb/Zg;
    //   439: pop
    //   440: aload_1
    //   441: ifnull -> 1355
    //   444: goto -> 451
    //   447: invokestatic a : (Ljava/io/IOException;)Ljava/io/IOException;
    //   450: athrow
    //   451: aload_0
    //   452: getfield Zz : Lcom/fasterxml/Zyv;
    //   455: aload #4
    //   457: invokevirtual ZV : (Lcom/fasterxml/Zyg;)Lcom/fasterxml/Zyg;
    //   460: astore #4
    //   462: aload #4
    //   464: ifnonnull -> 486
    //   467: aload_0
    //   468: getfield ZP : Lcom/fasterxml/Zb/Zg;
    //   471: invokevirtual Zc : ()Lcom/fasterxml/Zb/Zg;
    //   474: pop
    //   475: aload_1
    //   476: ifnull -> 1355
    //   479: goto -> 486
    //   482: invokestatic a : (Ljava/io/IOException;)Ljava/io/IOException;
    //   485: athrow
    //   486: aload #4
    //   488: getstatic com/fasterxml/Zyg.ZR : Lcom/fasterxml/Zyg;
    //   491: if_acmpeq -> 508
    //   494: goto -> 501
    //   497: invokestatic a : (Ljava/io/IOException;)Ljava/io/IOException;
    //   500: athrow
    //   501: aload #4
    //   503: invokevirtual ZG : ()Lcom/fasterxml/Zyg;
    //   506: astore #4
    //   508: aload_0
    //   509: aload #4
    //   511: putfield Zh : Lcom/fasterxml/Zyg;
    //   514: aload #4
    //   516: getstatic com/fasterxml/Zyg.ZR : Lcom/fasterxml/Zyg;
    //   519: if_acmpne -> 547
    //   522: aload_0
    //   523: aload_0
    //   524: getfield Zz : Lcom/fasterxml/Zyv;
    //   527: aload #4
    //   529: iconst_1
    //   530: invokevirtual Zc : (Lcom/fasterxml/Zyg;Z)Lcom/fasterxml/Zyv;
    //   533: putfield Zz : Lcom/fasterxml/Zyv;
    //   536: aload_0
    //   537: aload_3
    //   538: dup_x1
    //   539: putfield Zx : Lcom/fasterxml/Zb/Zl;
    //   542: areturn
    //   543: invokestatic a : (Ljava/io/IOException;)Ljava/io/IOException;
    //   546: athrow
    //   547: aload #4
    //   549: ifnull -> 594
    //   552: aload_0
    //   553: getfield Zp : Lcom/fasterxml/Zyu;
    //   556: getstatic com/fasterxml/Zyu.INCLUDE_NON_NULL : Lcom/fasterxml/Zyu;
    //   559: if_acmpne -> 594
    //   562: goto -> 569
    //   565: invokestatic a : (Ljava/io/IOException;)Ljava/io/IOException;
    //   568: athrow
    //   569: aload_0
    //   570: aload_0
    //   571: getfield Zz : Lcom/fasterxml/Zyv;
    //   574: aload #4
    //   576: iconst_1
    //   577: invokevirtual Zc : (Lcom/fasterxml/Zyg;Z)Lcom/fasterxml/Zyv;
    //   580: putfield Zz : Lcom/fasterxml/Zyv;
    //   583: aload_0
    //   584: aload_3
    //   585: dup_x1
    //   586: putfield Zx : Lcom/fasterxml/Zb/Zl;
    //   589: areturn
    //   590: invokestatic a : (Ljava/io/IOException;)Ljava/io/IOException;
    //   593: athrow
    //   594: aload_0
    //   595: aload_0
    //   596: getfield Zz : Lcom/fasterxml/Zyv;
    //   599: aload #4
    //   601: iconst_0
    //   602: invokevirtual Zc : (Lcom/fasterxml/Zyg;Z)Lcom/fasterxml/Zyv;
    //   605: putfield Zz : Lcom/fasterxml/Zyv;
    //   608: aload_0
    //   609: getfield Zp : Lcom/fasterxml/Zyu;
    //   612: getstatic com/fasterxml/Zyu.INCLUDE_ALL_AND_PATH : Lcom/fasterxml/Zyu;
    //   615: if_acmpne -> 1355
    //   618: aload_0
    //   619: aload_0
    //   620: getfield Zz : Lcom/fasterxml/Zyv;
    //   623: invokevirtual ZM : (Lcom/fasterxml/Zyv;)Lcom/fasterxml/Zb/Zl;
    //   626: astore_3
    //   627: aload_3
    //   628: ifnull -> 1355
    //   631: aload_0
    //   632: aload_3
    //   633: putfield Zx : Lcom/fasterxml/Zb/Zl;
    //   636: aload_3
    //   637: areturn
    //   638: invokestatic a : (Ljava/io/IOException;)Ljava/io/IOException;
    //   641: athrow
    //   642: aload_0
    //   643: getfield Zh : Lcom/fasterxml/Zyg;
    //   646: astore #4
    //   648: aload #4
    //   650: getstatic com/fasterxml/Zyg.ZR : Lcom/fasterxml/Zyg;
    //   653: if_acmpne -> 681
    //   656: aload_0
    //   657: aload_0
    //   658: getfield Zz : Lcom/fasterxml/Zyv;
    //   661: aload #4
    //   663: iconst_1
    //   664: invokevirtual Zv : (Lcom/fasterxml/Zyg;Z)Lcom/fasterxml/Zyv;
    //   667: putfield Zz : Lcom/fasterxml/Zyv;
    //   670: aload_0
    //   671: aload_3
    //   672: dup_x1
    //   673: putfield Zx : Lcom/fasterxml/Zb/Zl;
    //   676: areturn
    //   677: invokestatic a : (Ljava/io/IOException;)Ljava/io/IOException;
    //   680: athrow
    //   681: aload #4
    //   683: ifnonnull -> 705
    //   686: aload_0
    //   687: getfield ZP : Lcom/fasterxml/Zb/Zg;
    //   690: invokevirtual Zc : ()Lcom/fasterxml/Zb/Zg;
    //   693: pop
    //   694: aload_1
    //   695: ifnull -> 1355
    //   698: goto -> 705
    //   701: invokestatic a : (Ljava/io/IOException;)Ljava/io/IOException;
    //   704: athrow
    //   705: aload_0
    //   706: getfield Zz : Lcom/fasterxml/Zyv;
    //   709: aload #4
    //   711: invokevirtual ZV : (Lcom/fasterxml/Zyg;)Lcom/fasterxml/Zyg;
    //   714: astore #4
    //   716: aload #4
    //   718: ifnonnull -> 740
    //   721: aload_0
    //   722: getfield ZP : Lcom/fasterxml/Zb/Zg;
    //   725: invokevirtual Zc : ()Lcom/fasterxml/Zb/Zg;
    //   728: pop
    //   729: aload_1
    //   730: ifnull -> 1355
    //   733: goto -> 740
    //   736: invokestatic a : (Ljava/io/IOException;)Ljava/io/IOException;
    //   739: athrow
    //   740: aload #4
    //   742: getstatic com/fasterxml/Zyg.ZR : Lcom/fasterxml/Zyg;
    //   745: if_acmpeq -> 762
    //   748: goto -> 755
    //   751: invokestatic a : (Ljava/io/IOException;)Ljava/io/IOException;
    //   754: athrow
    //   755: aload #4
    //   757: invokevirtual Zz : ()Lcom/fasterxml/Zyg;
    //   760: astore #4
    //   762: aload_0
    //   763: aload #4
    //   765: putfield Zh : Lcom/fasterxml/Zyg;
    //   768: aload #4
    //   770: getstatic com/fasterxml/Zyg.ZR : Lcom/fasterxml/Zyg;
    //   773: if_acmpne -> 801
    //   776: aload_0
    //   777: aload_0
    //   778: getfield Zz : Lcom/fasterxml/Zyv;
    //   781: aload #4
    //   783: iconst_1
    //   784: invokevirtual Zv : (Lcom/fasterxml/Zyg;Z)Lcom/fasterxml/Zyv;
    //   787: putfield Zz : Lcom/fasterxml/Zyv;
    //   790: aload_0
    //   791: aload_3
    //   792: dup_x1
    //   793: putfield Zx : Lcom/fasterxml/Zb/Zl;
    //   796: areturn
    //   797: invokestatic a : (Ljava/io/IOException;)Ljava/io/IOException;
    //   800: athrow
    //   801: aload #4
    //   803: ifnull -> 848
    //   806: aload_0
    //   807: getfield Zp : Lcom/fasterxml/Zyu;
    //   810: getstatic com/fasterxml/Zyu.INCLUDE_NON_NULL : Lcom/fasterxml/Zyu;
    //   813: if_acmpne -> 848
    //   816: goto -> 823
    //   819: invokestatic a : (Ljava/io/IOException;)Ljava/io/IOException;
    //   822: athrow
    //   823: aload_0
    //   824: aload_0
    //   825: getfield Zz : Lcom/fasterxml/Zyv;
    //   828: aload #4
    //   830: iconst_1
    //   831: invokevirtual Zv : (Lcom/fasterxml/Zyg;Z)Lcom/fasterxml/Zyv;
    //   834: putfield Zz : Lcom/fasterxml/Zyv;
    //   837: aload_0
    //   838: aload_3
    //   839: dup_x1
    //   840: putfield Zx : Lcom/fasterxml/Zb/Zl;
    //   843: areturn
    //   844: invokestatic a : (Ljava/io/IOException;)Ljava/io/IOException;
    //   847: athrow
    //   848: aload_0
    //   849: aload_0
    //   850: getfield Zz : Lcom/fasterxml/Zyv;
    //   853: aload #4
    //   855: iconst_0
    //   856: invokevirtual Zv : (Lcom/fasterxml/Zyg;Z)Lcom/fasterxml/Zyv;
    //   859: putfield Zz : Lcom/fasterxml/Zyv;
    //   862: aload_0
    //   863: getfield Zp : Lcom/fasterxml/Zyu;
    //   866: getstatic com/fasterxml/Zyu.INCLUDE_ALL_AND_PATH : Lcom/fasterxml/Zyu;
    //   869: if_acmpne -> 1355
    //   872: aload_0
    //   873: aload_0
    //   874: getfield Zz : Lcom/fasterxml/Zyv;
    //   877: invokevirtual ZM : (Lcom/fasterxml/Zyv;)Lcom/fasterxml/Zb/Zl;
    //   880: astore_3
    //   881: aload_3
    //   882: ifnull -> 1355
    //   885: aload_0
    //   886: aload_3
    //   887: putfield Zx : Lcom/fasterxml/Zb/Zl;
    //   890: aload_3
    //   891: areturn
    //   892: invokestatic a : (Ljava/io/IOException;)Ljava/io/IOException;
    //   895: athrow
    //   896: aload_0
    //   897: getfield Zz : Lcom/fasterxml/Zyv;
    //   900: invokevirtual Zd : ()Z
    //   903: istore #5
    //   905: aload_0
    //   906: getfield Zz : Lcom/fasterxml/Zyv;
    //   909: invokevirtual ZJ : ()Lcom/fasterxml/Zyg;
    //   912: astore #4
    //   914: aload #4
    //   916: ifnull -> 977
    //   919: aload #4
    //   921: getstatic com/fasterxml/Zyg.ZR : Lcom/fasterxml/Zyg;
    //   924: if_acmpeq -> 977
    //   927: goto -> 934
    //   930: invokestatic a : (Ljava/io/IOException;)Ljava/io/IOException;
    //   933: athrow
    //   934: aload_3
    //   935: invokevirtual Zs : ()I
    //   938: iconst_4
    //   939: if_icmpne -> 965
    //   942: goto -> 949
    //   945: invokestatic a : (Ljava/io/IOException;)Ljava/io/IOException;
    //   948: athrow
    //   949: aload #4
    //   951: invokevirtual Zu : ()V
    //   954: aload_1
    //   955: ifnull -> 977
    //   958: goto -> 965
    //   961: invokestatic a : (Ljava/io/IOException;)Ljava/io/IOException;
    //   964: athrow
    //   965: aload #4
    //   967: invokevirtual Ze : ()V
    //   970: goto -> 977
    //   973: invokestatic a : (Ljava/io/IOException;)Ljava/io/IOException;
    //   976: athrow
    //   977: aload_0
    //   978: aload_0
    //   979: getfield Zz : Lcom/fasterxml/Zyv;
    //   982: invokevirtual ZU : ()Lcom/fasterxml/Zyv;
    //   985: putfield Zz : Lcom/fasterxml/Zyv;
    //   988: aload_0
    //   989: aload_0
    //   990: getfield Zz : Lcom/fasterxml/Zyv;
    //   993: invokevirtual ZJ : ()Lcom/fasterxml/Zyg;
    //   996: putfield Zh : Lcom/fasterxml/Zyg;
    //   999: iload #5
    //   1001: ifeq -> 1015
    //   1004: aload_0
    //   1005: aload_3
    //   1006: dup_x1
    //   1007: putfield Zx : Lcom/fasterxml/Zb/Zl;
    //   1010: areturn
    //   1011: invokestatic a : (Ljava/io/IOException;)Ljava/io/IOException;
    //   1014: athrow
    //   1015: aload_1
    //   1016: ifnull -> 1355
    //   1019: aload_0
    //   1020: getfield ZP : Lcom/fasterxml/Zb/Zg;
    //   1023: invokevirtual ZS : ()Ljava/lang/String;
    //   1026: astore #5
    //   1028: aload_0
    //   1029: getfield Zz : Lcom/fasterxml/Zyv;
    //   1032: aload #5
    //   1034: invokevirtual Zl : (Ljava/lang/String;)Lcom/fasterxml/Zyg;
    //   1037: astore #4
    //   1039: aload #4
    //   1041: getstatic com/fasterxml/Zyg.ZR : Lcom/fasterxml/Zyg;
    //   1044: if_acmpne -> 1064
    //   1047: aload_0
    //   1048: aload #4
    //   1050: putfield Zh : Lcom/fasterxml/Zyg;
    //   1053: aload_0
    //   1054: aload_3
    //   1055: dup_x1
    //   1056: putfield Zx : Lcom/fasterxml/Zb/Zl;
    //   1059: areturn
    //   1060: invokestatic a : (Ljava/io/IOException;)Ljava/io/IOException;
    //   1063: athrow
    //   1064: aload #4
    //   1066: ifnonnull -> 1096
    //   1069: aload_0
    //   1070: getfield ZP : Lcom/fasterxml/Zb/Zg;
    //   1073: invokevirtual ZV : ()Lcom/fasterxml/Zb/Zl;
    //   1076: pop
    //   1077: aload_0
    //   1078: getfield ZP : Lcom/fasterxml/Zb/Zg;
    //   1081: invokevirtual Zc : ()Lcom/fasterxml/Zb/Zg;
    //   1084: pop
    //   1085: aload_1
    //   1086: ifnull -> 1355
    //   1089: goto -> 1096
    //   1092: invokestatic a : (Ljava/io/IOException;)Ljava/io/IOException;
    //   1095: athrow
    //   1096: aload #4
    //   1098: aload #5
    //   1100: invokevirtual ZH : (Ljava/lang/String;)Lcom/fasterxml/Zyg;
    //   1103: astore #4
    //   1105: aload #4
    //   1107: ifnonnull -> 1137
    //   1110: aload_0
    //   1111: getfield ZP : Lcom/fasterxml/Zb/Zg;
    //   1114: invokevirtual ZV : ()Lcom/fasterxml/Zb/Zl;
    //   1117: pop
    //   1118: aload_0
    //   1119: getfield ZP : Lcom/fasterxml/Zb/Zg;
    //   1122: invokevirtual Zc : ()Lcom/fasterxml/Zb/Zg;
    //   1125: pop
    //   1126: aload_1
    //   1127: ifnull -> 1355
    //   1130: goto -> 1137
    //   1133: invokestatic a : (Ljava/io/IOException;)Ljava/io/IOException;
    //   1136: athrow
    //   1137: aload_0
    //   1138: aload #4
    //   1140: putfield Zh : Lcom/fasterxml/Zyg;
    //   1143: aload #4
    //   1145: getstatic com/fasterxml/Zyg.ZR : Lcom/fasterxml/Zyg;
    //   1148: if_acmpne -> 1216
    //   1151: goto -> 1158
    //   1154: invokestatic a : (Ljava/io/IOException;)Ljava/io/IOException;
    //   1157: athrow
    //   1158: aload_0
    //   1159: invokespecial ZnN : ()Z
    //   1162: ifeq -> 1200
    //   1165: goto -> 1172
    //   1168: invokestatic a : (Ljava/io/IOException;)Ljava/io/IOException;
    //   1171: athrow
    //   1172: aload_0
    //   1173: getfield Zp : Lcom/fasterxml/Zyu;
    //   1176: getstatic com/fasterxml/Zyu.INCLUDE_ALL_AND_PATH : Lcom/fasterxml/Zyu;
    //   1179: if_acmpne -> 1216
    //   1182: goto -> 1189
    //   1185: invokestatic a : (Ljava/io/IOException;)Ljava/io/IOException;
    //   1188: athrow
    //   1189: aload_0
    //   1190: aload_3
    //   1191: dup_x1
    //   1192: putfield Zx : Lcom/fasterxml/Zb/Zl;
    //   1195: areturn
    //   1196: invokestatic a : (Ljava/io/IOException;)Ljava/io/IOException;
    //   1199: athrow
    //   1200: aload_0
    //   1201: getfield ZP : Lcom/fasterxml/Zb/Zg;
    //   1204: invokevirtual ZV : ()Lcom/fasterxml/Zb/Zl;
    //   1207: pop
    //   1208: aload_0
    //   1209: getfield ZP : Lcom/fasterxml/Zb/Zg;
    //   1212: invokevirtual Zc : ()Lcom/fasterxml/Zb/Zg;
    //   1215: pop
    //   1216: aload_0
    //   1217: getfield Zp : Lcom/fasterxml/Zyu;
    //   1220: getstatic com/fasterxml/Zyu.ONLY_INCLUDE_ALL : Lcom/fasterxml/Zyu;
    //   1223: if_acmpeq -> 1355
    //   1226: aload_0
    //   1227: aload_0
    //   1228: getfield Zz : Lcom/fasterxml/Zyv;
    //   1231: invokevirtual ZM : (Lcom/fasterxml/Zyv;)Lcom/fasterxml/Zb/Zl;
    //   1234: astore_3
    //   1235: aload_3
    //   1236: ifnull -> 1355
    //   1239: aload_0
    //   1240: aload_3
    //   1241: putfield Zx : Lcom/fasterxml/Zb/Zl;
    //   1244: aload_3
    //   1245: areturn
    //   1246: invokestatic a : (Ljava/io/IOException;)Ljava/io/IOException;
    //   1249: athrow
    //   1250: aload_0
    //   1251: getfield Zh : Lcom/fasterxml/Zyg;
    //   1254: astore #4
    //   1256: aload #4
    //   1258: getstatic com/fasterxml/Zyg.ZR : Lcom/fasterxml/Zyg;
    //   1261: if_acmpne -> 1275
    //   1264: aload_0
    //   1265: aload_3
    //   1266: dup_x1
    //   1267: putfield Zx : Lcom/fasterxml/Zb/Zl;
    //   1270: areturn
    //   1271: invokestatic a : (Ljava/io/IOException;)Ljava/io/IOException;
    //   1274: athrow
    //   1275: aload #4
    //   1277: ifnull -> 1355
    //   1280: aload_0
    //   1281: getfield Zz : Lcom/fasterxml/Zyv;
    //   1284: aload #4
    //   1286: invokevirtual ZV : (Lcom/fasterxml/Zyg;)Lcom/fasterxml/Zyg;
    //   1289: astore #4
    //   1291: aload #4
    //   1293: getstatic com/fasterxml/Zyg.ZR : Lcom/fasterxml/Zyg;
    //   1296: if_acmpeq -> 1330
    //   1299: aload #4
    //   1301: ifnull -> 1355
    //   1304: goto -> 1311
    //   1307: invokestatic a : (Ljava/io/IOException;)Ljava/io/IOException;
    //   1310: athrow
    //   1311: aload #4
    //   1313: aload_0
    //   1314: getfield ZP : Lcom/fasterxml/Zb/Zg;
    //   1317: invokevirtual Zv : (Lcom/fasterxml/Zb/Zg;)Z
    //   1320: ifeq -> 1355
    //   1323: goto -> 1330
    //   1326: invokestatic a : (Ljava/io/IOException;)Ljava/io/IOException;
    //   1329: athrow
    //   1330: aload_0
    //   1331: invokespecial ZnN : ()Z
    //   1334: ifeq -> 1355
    //   1337: goto -> 1344
    //   1340: invokestatic a : (Ljava/io/IOException;)Ljava/io/IOException;
    //   1343: athrow
    //   1344: aload_0
    //   1345: aload_3
    //   1346: dup_x1
    //   1347: putfield Zx : Lcom/fasterxml/Zb/Zl;
    //   1350: areturn
    //   1351: invokestatic a : (Ljava/io/IOException;)Ljava/io/IOException;
    //   1354: athrow
    //   1355: aload_0
    //   1356: invokevirtual Znc : ()Lcom/fasterxml/Zb/Zl;
    //   1359: areturn
    // Exception table:
    //   from	to	target	type
    //   4	18	21	java/io/IOException
    //   11	32	35	java/io/IOException
    //   25	49	52	java/io/IOException
    //   39	66	69	java/io/IOException
    //   56	83	86	java/io/IOException
    //   73	100	103	java/io/IOException
    //   90	114	114	java/io/IOException
    //   143	163	166	java/io/IOException
    //   178	215	218	java/io/IOException
    //   232	261	264	java/io/IOException
    //   268	282	282	java/io/IOException
    //   295	318	318	java/io/IOException
    //   334	345	345	java/io/IOException
    //   394	423	423	java/io/IOException
    //   427	444	447	java/io/IOException
    //   462	479	482	java/io/IOException
    //   467	494	497	java/io/IOException
    //   508	543	543	java/io/IOException
    //   547	562	565	java/io/IOException
    //   552	590	590	java/io/IOException
    //   627	638	638	java/io/IOException
    //   648	677	677	java/io/IOException
    //   681	698	701	java/io/IOException
    //   716	733	736	java/io/IOException
    //   721	748	751	java/io/IOException
    //   762	797	797	java/io/IOException
    //   801	816	819	java/io/IOException
    //   806	844	844	java/io/IOException
    //   881	892	892	java/io/IOException
    //   914	927	930	java/io/IOException
    //   919	942	945	java/io/IOException
    //   934	958	961	java/io/IOException
    //   949	970	973	java/io/IOException
    //   977	1011	1011	java/io/IOException
    //   1039	1060	1060	java/io/IOException
    //   1064	1089	1092	java/io/IOException
    //   1105	1130	1133	java/io/IOException
    //   1110	1151	1154	java/io/IOException
    //   1137	1165	1168	java/io/IOException
    //   1158	1182	1185	java/io/IOException
    //   1172	1196	1196	java/io/IOException
    //   1235	1246	1246	java/io/IOException
    //   1256	1271	1271	java/io/IOException
    //   1291	1304	1307	java/io/IOException
    //   1299	1323	1326	java/io/IOException
    //   1311	1337	1340	java/io/IOException
    //   1330	1351	1351	java/io/IOException
  }
  
  protected final Zl Znc() throws IOException {
    int[] arrayOfInt = Zyg.Zf();
    while (true) {
      boolean bool;
      String str;
      Zl zl = this.ZP.ZV();
      if (zl == null) {
        this.Zx = zl;
        return zl;
      } 
      switch (zl.Zs()) {
        case 3:
          zyg = this.Zh;
        case 1:
          zyg = this.Zh;
        case 4:
          bool = this.Zz.Zd();
          zyg = this.Zz.ZJ();
        case 2:
          bool = this.Zz.Zd();
          zyg = this.Zz.ZJ();
        case 5:
          str = this.ZP.ZS();
          zyg = this.Zz.Zl(str);
      } 
      Zyg zyg = this.Zh;
      try {
        if (zyg == Zyg.ZR)
          return this.Zx = zl; 
      } catch (IOException iOException) {
        throw a(null);
      } 
      if (zyg != null) {
        zyg = this.Zz.ZV(zyg);
        try {
          if (zyg != Zyg.ZR) {
            try {
              if (zyg != null)
                try {
                  if (zyg.Zv(this.ZP))
                    continue; 
                } catch (IOException iOException) {
                  throw a(null);
                }  
            } catch (IOException iOException) {
              throw a(null);
            } 
            continue;
          } 
        } catch (IOException iOException) {
          throw a(null);
        } 
        continue;
      } 
      continue;
      try {
        if (ZnN())
          return this.Zx = (Zl)SYNTHETIC_LOCAL_VARIABLE_2; 
      } catch (IOException iOException) {
        throw a(null);
      } 
    } 
  }
  
  protected final Zl ZM(Zyv paramZyv) throws IOException {
    int[] arrayOfInt = Zyg.Zf();
    while (true) {
      String str;
      Zl zl = this.ZP.ZV();
      if (zl == null)
        return zl; 
      switch (zl.Zs()) {
        case 3:
          zyg = this.Zz.ZV(this.Zh);
        case 1:
          zyg = this.Zh;
        case 4:
          zyg = this.Zz.ZJ();
        case 2:
          zyg = this.Zz.ZJ();
        case 5:
          str = this.ZP.ZS();
          zyg = this.Zz.Zl(str);
      } 
      Zyg zyg = this.Zh;
      try {
        if (zyg == Zyg.ZR)
          return ZL(paramZyv); 
      } catch (IOException iOException) {
        throw a(null);
      } 
      continue;
      if (SYNTHETIC_LOCAL_VARIABLE_4 != null) {
        Zyg zyg = this.Zz.ZV((Zyg)SYNTHETIC_LOCAL_VARIABLE_4);
        try {
          if ((zyg == Zyg.ZR || (zyg != null && zyg.Zv(this.ZP))) && ZnN())
            return ZL(paramZyv); 
        } catch (IOException iOException) {
          throw a(null);
        } 
      } 
    } 
  }
  
  private Zl ZL(Zyv paramZyv) throws IOException {
    this.ZK = paramZyv;
    Zyv zyv = paramZyv;
    Zl zl = zyv.Ze();
    try {
      if (zl != null)
        return zl; 
    } catch (IOException iOException) {
      throw a(null);
    } 
    while (true) {
      if (zyv == this.Zz)
        throw Zh(b(31463, 12084)); 
      zyv = this.ZK.Zp(zyv);
      try {
        this.ZK = zyv;
        if (zyv == null)
          throw Zh(b(31461, -24966)); 
      } catch (IOException iOException) {
        throw a(null);
      } 
      zl = this.ZK.Ze();
      if (zl != null)
        return zl; 
    } 
  }
  
  private final boolean ZnN() throws IOException {
    try {
      if (this.Zu != 0)
        try {
          if (!this.Zj)
            return false; 
          this.Zu++;
          return true;
        } catch (IOException iOException) {
          throw a(null);
        }  
    } catch (IOException iOException) {
      throw a(null);
    } 
    this.Zu++;
    return true;
  }
  
  public Zg Zc() throws IOException {
    int[] arrayOfInt = Zyg.Zf();
    try {
      if (this.Zx != Zl.START_OBJECT)
        try {
          if (this.Zx != Zl.START_ARRAY)
            return (Zg)this; 
        } catch (IOException iOException) {
          throw a(null);
        }  
    } catch (IOException iOException) {
      throw a(null);
    } 
    byte b = 1;
    while (true) {
      Zl zl = ZV();
      try {
        if (zl == null)
          return (Zg)this; 
      } catch (IOException iOException) {
        throw a(null);
      } 
      try {
        if (zl.ZT()) {
          try {
            b++;
            if (arrayOfInt != null)
              continue; 
          } catch (IOException iOException) {
            throw a(null);
          } 
          continue;
        } 
      } catch (IOException iOException) {
        throw a(null);
      } 
      continue;
      try {
        if (SYNTHETIC_LOCAL_VARIABLE_3.Zf())
          try {
            if (--b == 0)
              return (Zg)this; 
          } catch (IOException iOException) {
            throw a(null);
          }  
      } catch (IOException iOException) {
        throw a(null);
      } 
    } 
  }
  
  public String ZR() throws IOException {
    try {
      if (this.Zx == Zl.FIELD_NAME)
        return ZS(); 
    } catch (IOException iOException) {
      throw a(null);
    } 
    return this.ZP.ZR();
  }
  
  public boolean Zi() {
    return (this.Zx == Zl.FIELD_NAME) ? false : this.ZP.Zi();
  }
  
  public char[] ZW() throws IOException {
    try {
      if (this.Zx == Zl.FIELD_NAME)
        return ZS().toCharArray(); 
    } catch (IOException iOException) {
      throw a(null);
    } 
    return this.ZP.ZW();
  }
  
  public int Zn() throws IOException {
    try {
      if (this.Zx == Zl.FIELD_NAME)
        return ZS().length(); 
    } catch (IOException iOException) {
      throw a(null);
    } 
    return this.ZP.Zn();
  }
  
  public int Zk() throws IOException {
    try {
      if (this.Zx == Zl.FIELD_NAME)
        return 0; 
    } catch (IOException iOException) {
      throw a(null);
    } 
    return this.ZP.Zk();
  }
  
  public BigInteger ZX() throws IOException {
    return this.ZP.ZX();
  }
  
  public boolean ZB() throws IOException {
    return this.ZP.ZB();
  }
  
  public byte Zx() throws IOException {
    return this.ZP.Zx();
  }
  
  public short Zu() throws IOException {
    return this.ZP.Zu();
  }
  
  public BigDecimal ZT() throws IOException {
    return this.ZP.ZT();
  }
  
  public double ZH() throws IOException {
    return this.ZP.ZH();
  }
  
  public float Zg() throws IOException {
    return this.ZP.Zg();
  }
  
  public int Ze() throws IOException {
    return this.ZP.Ze();
  }
  
  public long ZE() throws IOException {
    return this.ZP.ZE();
  }
  
  public Zk ZL() throws IOException {
    return this.ZP.ZL();
  }
  
  public Number Zb() throws IOException {
    return this.ZP.Zb();
  }
  
  public int ZC() throws IOException {
    return this.ZP.ZC();
  }
  
  public int Zv(int paramInt) throws IOException {
    return this.ZP.Zv(paramInt);
  }
  
  public long Zw() throws IOException {
    return this.ZP.Zw();
  }
  
  public long ZE(long paramLong) throws IOException {
    return this.ZP.ZE(paramLong);
  }
  
  public String Zd() throws IOException {
    try {
      if (this.Zx == Zl.FIELD_NAME)
        return ZS(); 
    } catch (IOException iOException) {
      throw a(null);
    } 
    return this.ZP.Zd();
  }
  
  public String Zd(String paramString) throws IOException {
    try {
      if (this.Zx == Zl.FIELD_NAME)
        return ZS(); 
    } catch (IOException iOException) {
      throw a(null);
    } 
    return this.ZP.Zd(paramString);
  }
  
  public Object ZO() throws IOException {
    return this.ZP.ZO();
  }
  
  public byte[] Zi(Zy paramZy) throws IOException {
    return this.ZP.Zi(paramZy);
  }
  
  public int Zh(Zy paramZy, OutputStream paramOutputStream) throws IOException {
    return this.ZP.Zh(paramZy, paramOutputStream);
  }
  
  protected Ze ZnK() {
    return (this.ZK != null) ? this.ZK : this.Zz;
  }
  
  private static IOException a(IOException paramIOException) {
    return paramIOException;
  }
  
  static {
    // Byte code:
    //   0: iconst_3
    //   1: anewarray java/lang/String
    //   4: astore #5
    //   6: iconst_0
    //   7: istore_3
    //   8: ldc 'pÂ«UÂº ÂŒÂ˜R&/8Â»ÃÂ˜KÂ¹Â³ÃÃ‘+}HÃ—Â”_Ã¶Â¦ÃX9Ã¥Â›Ã½/,ÂŠXÂ®Ã²[Ã–Â¾Ã°Ã˜Y6SÂ€Ã¬Ã½4Ã†Â‰0ÃbÃ‰ÂˆÃ‹"4MÃ†SgÃžC;Â¨ÃšxaÃ‹Ã™Ã‡Â–Â[Ã¿Â\\tJÂ™E_Ã˜z7CÂ‚Â·1aoÃµ4Ã¯Ã­Ã–U$Âµ\'Â¤>KÂœÃ¾ÂšÂŸÂ©LÂdÂ¨Â—Ã•OÂªÃŠÂ”ÂgÃ‘ÃupÂ ÃµÃ¢Ã¦Ã¤ÃÃ°jÂaÃ½H`RÃ‹J0Â'
    //   10: dup
    //   11: astore_2
    //   12: invokevirtual length : ()I
    //   15: istore #4
    //   17: bipush #57
    //   19: istore_1
    //   20: iconst_m1
    //   21: istore_0
    //   22: bipush #77
    //   24: iinc #0, 1
    //   27: aload_2
    //   28: iload_0
    //   29: dup
    //   30: iload_1
    //   31: iadd
    //   32: invokevirtual substring : (II)Ljava/lang/String;
    //   35: iconst_m1
    //   36: goto -> 82
    //   39: aload #5
    //   41: swap
    //   42: iload_3
    //   43: iinc #3, 1
    //   46: swap
    //   47: aastore
    //   48: iload_0
    //   49: iload_1
    //   50: iadd
    //   51: dup
    //   52: istore_0
    //   53: iload #4
    //   55: if_icmpge -> 67
    //   58: aload_2
    //   59: iload_0
    //   60: invokevirtual charAt : (I)C
    //   63: istore_1
    //   64: goto -> 22
    //   67: aload #5
    //   69: putstatic com/fasterxml/Zyb.c : [Ljava/lang/String;
    //   72: iconst_3
    //   73: anewarray java/lang/String
    //   76: putstatic com/fasterxml/Zyb.d : [Ljava/lang/String;
    //   79: goto -> 227
    //   82: dup_x2
    //   83: pop
    //   84: invokevirtual toCharArray : ()[C
    //   87: dup_x1
    //   88: arraylength
    //   89: dup_x2
    //   90: pop
    //   91: iconst_0
    //   92: istore #6
    //   94: dup2_x1
    //   95: pop2
    //   96: dup_x2
    //   97: iconst_1
    //   98: if_icmpgt -> 200
    //   101: dup2
    //   102: swap
    //   103: iload #6
    //   105: dup2_x1
    //   106: caload
    //   107: swap
    //   108: iload #6
    //   110: bipush #7
    //   112: irem
    //   113: tableswitch default -> 182, 0 -> 152, 1 -> 157, 2 -> 162, 3 -> 167, 4 -> 172, 5 -> 177
    //   152: bipush #82
    //   154: goto -> 184
    //   157: bipush #7
    //   159: goto -> 184
    //   162: bipush #31
    //   164: goto -> 184
    //   167: bipush #55
    //   169: goto -> 184
    //   172: bipush #64
    //   174: goto -> 184
    //   177: bipush #15
    //   179: goto -> 184
    //   182: bipush #106
    //   184: ixor
    //   185: ixor
    //   186: i2c
    //   187: castore
    //   188: iinc #6, 1
    //   191: dup
    //   192: ifne -> 200
    //   195: dup2
    //   196: dup_x1
    //   197: goto -> 105
    //   200: dup2_x1
    //   201: pop2
    //   202: dup_x2
    //   203: iload #6
    //   205: if_icmpgt -> 101
    //   208: pop
    //   209: new java/lang/String
    //   212: dup_x1
    //   213: swap
    //   214: invokespecial <init> : ([C)V
    //   217: invokevirtual intern : ()Ljava/lang/String;
    //   220: swap
    //   221: pop
    //   222: swap
    //   223: pop
    //   224: goto -> 39
    //   227: return
  }
  
  private static String b(int paramInt1, int paramInt2) {
    int i = (paramInt1 ^ 0x7AE7) & 0xFFFF;
    if (d[i] == null) {
      char[] arrayOfChar = c[i].toCharArray();
      switch (arrayOfChar[0] & 0xFF) {
        case 0:
        
        case 1:
        
        case 2:
        
        case 3:
        
        case 4:
        
        case 5:
        
        case 6:
        
        case 7:
        
        case 8:
        
        case 9:
        
        case 10:
        
        case 11:
        
        case 12:
        
        case 13:
        
        case 14:
        
        case 15:
        
        case 16:
        
        case 17:
        
        case 18:
        
        case 19:
        
        case 20:
        
        case 21:
        
        case 22:
        
        case 23:
        
        case 24:
        
        case 25:
        
        case 26:
        
        case 27:
        
        case 28:
        
        case 29:
        
        case 30:
        
        case 31:
        
        case 32:
        
        case 33:
        
        case 34:
        
        case 35:
        
        case 36:
        
        case 37:
        
        case 38:
        
        case 39:
        
        case 40:
        
        case 41:
        
        case 42:
        
        case 43:
        
        case 44:
        
        case 45:
        
        case 46:
        
        case 47:
        
        case 48:
        
        case 49:
        
        case 50:
        
        case 51:
        
        case 52:
        
        case 53:
        
        case 54:
        
        case 55:
        
        case 56:
        
        case 57:
        
        case 58:
        
        case 59:
        
        case 60:
        
        case 61:
        
        case 62:
        
        case 63:
        
        case 64:
        
        case 65:
        
        case 66:
        
        case 67:
        
        case 68:
        
        case 69:
        
        case 70:
        
        case 71:
        
        case 72:
        
        case 73:
        
        case 74:
        
        case 75:
        
        case 76:
        
        case 77:
        
        case 78:
        
        case 79:
        
        case 80:
        
        case 81:
        
        case 82:
        
        case 83:
        
        case 84:
        
        case 85:
        
        case 86:
        
        case 87:
        
        case 88:
        
        case 89:
        
        case 90:
        
        case 91:
        
        case 92:
        
        case 93:
        
        case 94:
        
        case 95:
        
        case 96:
        
        case 97:
        
        case 98:
        
        case 99:
        
        case 100:
        
        case 101:
        
        case 102:
        
        case 103:
        
        case 104:
        
        case 105:
        
        case 106:
        
        case 107:
        
        case 108:
        
        case 109:
        
        case 110:
        
        case 111:
        
        case 112:
        
        case 113:
        
        case 114:
        
        case 115:
        
        case 116:
        
        case 117:
        
        case 118:
        
        case 119:
        
        case 120:
        
        case 121:
        
        case 122:
        
        case 123:
        
        case 124:
        
        case 125:
        
        case 126:
        
        case 127:
        
        case 128:
        
        case 129:
        
        case 130:
        
        case 131:
        
        case 132:
        
        case 133:
        
        case 134:
        
        case 135:
        
        case 136:
        
        case 137:
        
        case 138:
        
        case 139:
        
        case 140:
        
        case 141:
        
        case 142:
        
        case 143:
        
        case 144:
        
        case 145:
        
        case 146:
        
        case 147:
        
        case 148:
        
        case 149:
        
        case 150:
        
        case 151:
        
        case 152:
        
        case 153:
        
        case 154:
        
        case 155:
        
        case 156:
        
        case 157:
        
        case 158:
        
        case 159:
        
        case 160:
        
        case 161:
        
        case 162:
        
        case 163:
        
        case 164:
        
        case 165:
        
        case 166:
        
        case 167:
        
        case 168:
        
        case 169:
        
        case 170:
        
        case 171:
        
        case 172:
        
        case 173:
        
        case 174:
        
        case 175:
        
        case 176:
        
        case 177:
        
        case 178:
        
        case 179:
        
        case 180:
        
        case 181:
        
        case 182:
        
        case 183:
        
        case 184:
        
        case 185:
        
        case 186:
        
        case 187:
        
        case 188:
        
        case 189:
        
        case 190:
        
        case 191:
        
        case 192:
        
        case 193:
        
        case 194:
        
        case 195:
        
        case 196:
        
        case 197:
        
        case 198:
        
        case 199:
        
        case 200:
        
        case 201:
        
        case 202:
        
        case 203:
        
        case 204:
        
        case 205:
        
        case 206:
        
        case 207:
        
        case 208:
        
        case 209:
        
        case 210:
        
        case 211:
        
        case 212:
        
        case 213:
        
        case 214:
        
        case 215:
        
        case 216:
        
        case 217:
        
        case 218:
        
        case 219:
        
        case 220:
        
        case 221:
        
        case 222:
        
        case 223:
        
        case 224:
        
        case 225:
        
        case 226:
        
        case 227:
        
        case 228:
        
        case 229:
        
        case 230:
        
        case 231:
        
        case 232:
        
        case 233:
        
        case 234:
        
        case 235:
        
        case 236:
        
        case 237:
        
        case 238:
        
        case 239:
        
        case 240:
        
        case 241:
        
        case 242:
        
        case 243:
        
        case 244:
        
        case 245:
        
        case 246:
        
        case 247:
        
        case 248:
        
        case 249:
        
        case 250:
        
        case 251:
        
        case 252:
        
        case 253:
        
        case 254:
        
        default:
          break;
      } 
      char c = 'Ã‚';
      int j = (paramInt2 & 0xFF) - c;
      if (j < 0)
        j += 256; 
      int k = ((paramInt2 & 0xFFFF) >>> 8) - c;
      if (k < 0)
        k += 256; 
      for (byte b = 0; b < arrayOfChar.length; b++) {
        int m = b % 2;
        if (m == 0) {
          arrayOfChar[b] = (char)(arrayOfChar[b] ^ j);
          j = ((j >>> 3 | j << 5) ^ arrayOfChar[b]) & 0xFF;
        } else {
          arrayOfChar[b] = (char)(arrayOfChar[b] ^ k);
          k = ((k >>> 3 | k << 5) ^ arrayOfChar[b]) & 0xFF;
        } 
      } 
      d[i] = (new String(arrayOfChar)).intern();
    } 
    return d[i];
  }
}


/* Location:              C:\Program Files\BurpSuitePro\burpsuite_pro.jar!\com\fasterxml\Zyb.class
 * Java compiler version: 8 (52.0)
 * JD-Core Version:       1.1.3
 */