package com.fasterxml;

import com.fasterxml.Zb.Zf;
import com.fasterxml.Zb.Zl;
import com.fasterxml.Zk.Za;
import com.fasterxml.Zk.Zh;
import com.fasterxml.Zk.Zi;
import com.fasterxml.Zm.Zeg;
import com.fasterxml.Zm.Zk;
import com.fasterxml.Zm.Zx;
import com.fasterxml.Zn.Zj;
import com.fasterxml.Zn.Zm;
import com.fasterxml.Zo2.Zn;
import com.fasterxml.Zor.Zk;
import com.fasterxml.Zor.Zo;
import com.fasterxml.Zor.Zy_;
import com.fasterxml.Zor.Zyd;
import com.fasterxml.Zor.Zyi;
import com.fasterxml.Zor.Zym;
import com.fasterxml.Zp.Za;
import com.fasterxml.Zw.Zl;
import java.io.IOException;
import java.util.Map;
import java.util.Set;

@Zl
public class Zz7 extends Za<Map<?, ?>> implements Zi {
  private static final long serialVersionUID = 1L;
  
  protected static final Zk Zb;
  
  public static final Object ZT;
  
  protected final Zo Zw;
  
  protected final boolean Zj;
  
  protected final Zk ZG;
  
  protected final Zk Za;
  
  protected Zyd<Object> Zq;
  
  protected Zyd<Object> ZD;
  
  protected final Za Zy;
  
  protected Zj ZW;
  
  protected final Set<String> Zx;
  
  protected final Set<String> ZJ;
  
  protected final Object Zd;
  
  protected final Object Zn;
  
  protected final boolean Zf;
  
  protected final Zk Zz;
  
  protected final boolean ZH;
  
  private static final String[] d;
  
  private static final String[] e;
  
  protected Zz7(Set<String> paramSet1, Set<String> paramSet2, Zk paramZk1, Zk paramZk2, boolean paramBoolean, Za paramZa, Zyd<?> paramZyd1, Zyd<?> paramZyd2) {
    super(Map.class, false);
    this.Zx = (paramSet1 == null || paramSet1.isEmpty()) ? null : paramSet1;
    this.ZJ = paramSet2;
    this.ZG = paramZk1;
    this.Za = paramZk2;
    this.Zj = paramBoolean;
    this.Zy = paramZa;
    this.Zq = (Zyd)paramZyd1;
    this.ZD = (Zyd)paramZyd2;
    this.ZW = Zj.ZQ();
    this.Zw = null;
    this.Zd = null;
    this.ZH = false;
    this.Zn = null;
    this.Zf = false;
    this.Zz = Zeg.Zr(this.Zx, this.ZJ);
  }
  
  protected Zz7(Zz7 paramZz7, Zo paramZo, Zyd<?> paramZyd1, Zyd<?> paramZyd2, Set<String> paramSet1, Set<String> paramSet2) {
    super(Map.class, false);
    this.Zx = (paramSet1 == null || paramSet1.isEmpty()) ? null : paramSet1;
    this.ZJ = paramSet2;
    this.ZG = paramZz7.ZG;
    this.Za = paramZz7.Za;
    this.Zj = paramZz7.Zj;
    this.Zy = paramZz7.Zy;
    this.Zq = (Zyd)paramZyd1;
    this.ZD = (Zyd)paramZyd2;
    this.ZW = Zj.ZQ();
    this.Zw = paramZo;
    this.Zd = paramZz7.Zd;
    this.ZH = paramZz7.ZH;
    this.Zn = paramZz7.Zn;
    this.Zf = paramZz7.Zf;
    this.Zz = Zeg.Zr(this.Zx, this.ZJ);
  }
  
  protected Zz7(Zz7 paramZz7, Za paramZa, Object paramObject, boolean paramBoolean) {
    super(Map.class, false);
    this.Zx = paramZz7.Zx;
    this.ZJ = paramZz7.ZJ;
    this.ZG = paramZz7.ZG;
    this.Za = paramZz7.Za;
    this.Zj = paramZz7.Zj;
    this.Zy = paramZa;
    this.Zq = paramZz7.Zq;
    this.ZD = paramZz7.ZD;
    this.ZW = paramZz7.ZW;
    this.Zw = paramZz7.Zw;
    this.Zd = paramZz7.Zd;
    this.ZH = paramZz7.ZH;
    this.Zn = paramObject;
    this.Zf = paramBoolean;
    this.Zz = paramZz7.Zz;
  }
  
  protected Zz7(Zz7 paramZz7, Object paramObject, boolean paramBoolean) {
    super(Map.class, false);
    this.Zx = paramZz7.Zx;
    this.ZJ = paramZz7.ZJ;
    this.ZG = paramZz7.ZG;
    this.Za = paramZz7.Za;
    this.Zj = paramZz7.Zj;
    this.Zy = paramZz7.Zy;
    this.Zq = paramZz7.Zq;
    this.ZD = paramZz7.ZD;
    this.ZW = Zj.ZQ();
    this.Zw = paramZz7.Zw;
    this.Zd = paramObject;
    this.ZH = paramBoolean;
    this.Zn = paramZz7.Zn;
    this.Zf = paramZz7.Zf;
    this.Zz = paramZz7.Zz;
  }
  
  public Zz7 ZV(Za paramZa) {
    if (this.Zy == paramZa)
      return this; 
    Zd(b(16381, -21979));
    return new Zz7(this, paramZa, this.Zn, this.Zf);
  }
  
  public Zz7 Zy(Zo paramZo, Zyd<?> paramZyd1, Zyd<?> paramZyd2, Set<String> paramSet1, Set<String> paramSet2, boolean paramBoolean) {
    Zd(b(16380, -18527));
    Zz7 zz7 = new Zz7(this, paramZo, paramZyd1, paramZyd2, paramSet1, paramSet2);
    if (paramBoolean != zz7.ZH)
      zz7 = new Zz7(zz7, this.Zd, paramBoolean); 
    return zz7;
  }
  
  public Zz7 ZL(Object paramObject) {
    if (this.Zd == paramObject)
      return this; 
    Zd(b(16383, -3682));
    return new Zz7(this, paramObject, this.ZH);
  }
  
  public Zz7 ZK(Object paramObject, boolean paramBoolean) {
    if (paramObject == this.Zn && paramBoolean == this.Zf)
      return this; 
    Zd(b(16382, 920));
    return new Zz7(this, this.Zy, paramObject, paramBoolean);
  }
  
  public static Zz7 ZK(Set<String> paramSet1, Set<String> paramSet2, Zk paramZk, boolean paramBoolean, Za paramZa, Zyd<Object> paramZyd1, Zyd<Object> paramZyd2, Object paramObject) {
    // Byte code:
    //   0: invokestatic ZG : ()Ljava/lang/String;
    //   3: astore #8
    //   5: aload_2
    //   6: ifnonnull -> 22
    //   9: getstatic com/fasterxml/Zz7.Zb : Lcom/fasterxml/Zor/Zk;
    //   12: dup
    //   13: astore #10
    //   15: astore #9
    //   17: aload #8
    //   19: ifnull -> 53
    //   22: aload_2
    //   23: invokevirtual Zu : ()Lcom/fasterxml/Zor/Zk;
    //   26: astore #9
    //   28: aload_2
    //   29: ldc java/util/Properties
    //   31: invokevirtual ZP : (Ljava/lang/Class;)Z
    //   34: ifeq -> 47
    //   37: invokestatic Zs : ()Lcom/fasterxml/Zor/Zk;
    //   40: astore #10
    //   42: aload #8
    //   44: ifnull -> 53
    //   47: aload_2
    //   48: invokevirtual ZB : ()Lcom/fasterxml/Zor/Zk;
    //   51: astore #10
    //   53: iload_3
    //   54: ifne -> 81
    //   57: aload #10
    //   59: ifnull -> 74
    //   62: aload #10
    //   64: invokevirtual ZE : ()Z
    //   67: ifeq -> 74
    //   70: iconst_1
    //   71: goto -> 75
    //   74: iconst_0
    //   75: istore_3
    //   76: aload #8
    //   78: ifnull -> 93
    //   81: aload #10
    //   83: invokevirtual Zf : ()Ljava/lang/Class;
    //   86: ldc java/lang/Object
    //   88: if_acmpne -> 93
    //   91: iconst_0
    //   92: istore_3
    //   93: new com/fasterxml/Zz7
    //   96: dup
    //   97: aload_0
    //   98: aload_1
    //   99: aload #9
    //   101: aload #10
    //   103: iload_3
    //   104: aload #4
    //   106: aload #5
    //   108: aload #6
    //   110: invokespecial <init> : (Ljava/util/Set;Ljava/util/Set;Lcom/fasterxml/Zor/Zk;Lcom/fasterxml/Zor/Zk;ZLcom/fasterxml/Zp/Za;Lcom/fasterxml/Zor/Zyd;Lcom/fasterxml/Zor/Zyd;)V
    //   113: astore #11
    //   115: aload #7
    //   117: ifnull -> 129
    //   120: aload #11
    //   122: aload #7
    //   124: invokevirtual ZL : (Ljava/lang/Object;)Lcom/fasterxml/Zz7;
    //   127: astore #11
    //   129: aload #11
    //   131: areturn
  }
  
  public static Zz7 ZC(Set<String> paramSet, Zk paramZk, boolean paramBoolean, Za paramZa, Zyd<Object> paramZyd1, Zyd<Object> paramZyd2, Object paramObject) {
    return ZK(paramSet, null, paramZk, paramBoolean, paramZa, paramZyd1, paramZyd2, paramObject);
  }
  
  protected void Zd(String paramString) {
    Zx.ZW(Zz7.class, this, paramString);
  }
  
  public Zyd<?> Za(Zyi paramZyi, Zo paramZo) throws Zy_ {
    // Byte code:
    //   0: aconst_null
    //   1: astore #4
    //   3: invokestatic ZG : ()Ljava/lang/String;
    //   6: aconst_null
    //   7: astore #5
    //   9: aload_1
    //   10: invokevirtual Zv : ()Lcom/fasterxml/Zor/Zt;
    //   13: astore #6
    //   15: astore_3
    //   16: aload_2
    //   17: ifnonnull -> 28
    //   20: aconst_null
    //   21: goto -> 34
    //   24: invokestatic a : (Ljava/lang/Exception;)Ljava/lang/Exception;
    //   27: athrow
    //   28: aload_2
    //   29: invokeinterface ZQ : ()Lcom/fasterxml/Zoz/Ziz;
    //   34: astore #7
    //   36: aload #7
    //   38: aload #6
    //   40: invokestatic ZB : (Ljava/lang/Object;Ljava/lang/Object;)Z
    //   43: ifeq -> 94
    //   46: aload #6
    //   48: aload #7
    //   50: invokevirtual ZU : (Lcom/fasterxml/Zoz/Ziv;)Ljava/lang/Object;
    //   53: astore #8
    //   55: aload #8
    //   57: ifnull -> 70
    //   60: aload_1
    //   61: aload #7
    //   63: aload #8
    //   65: invokevirtual ZW : (Lcom/fasterxml/Zoz/Ziv;Ljava/lang/Object;)Lcom/fasterxml/Zor/Zyd;
    //   68: astore #5
    //   70: aload #6
    //   72: aload #7
    //   74: invokevirtual ZS : (Lcom/fasterxml/Zoz/Ziv;)Ljava/lang/Object;
    //   77: astore #8
    //   79: aload #8
    //   81: ifnull -> 94
    //   84: aload_1
    //   85: aload #7
    //   87: aload #8
    //   89: invokevirtual ZW : (Lcom/fasterxml/Zoz/Ziv;Ljava/lang/Object;)Lcom/fasterxml/Zor/Zyd;
    //   92: astore #4
    //   94: aload #4
    //   96: ifnonnull -> 105
    //   99: aload_0
    //   100: getfield ZD : Lcom/fasterxml/Zor/Zyd;
    //   103: astore #4
    //   105: aload_0
    //   106: aload_1
    //   107: aload_2
    //   108: aload #4
    //   110: invokevirtual Za : (Lcom/fasterxml/Zor/Zyi;Lcom/fasterxml/Zor/Zo;Lcom/fasterxml/Zor/Zyd;)Lcom/fasterxml/Zor/Zyd;
    //   113: astore #4
    //   115: aload #4
    //   117: ifnonnull -> 162
    //   120: aload_0
    //   121: getfield Zj : Z
    //   124: ifeq -> 162
    //   127: goto -> 134
    //   130: invokestatic a : (Ljava/lang/Exception;)Ljava/lang/Exception;
    //   133: athrow
    //   134: aload_0
    //   135: getfield Za : Lcom/fasterxml/Zor/Zk;
    //   138: invokevirtual Zr : ()Z
    //   141: ifne -> 162
    //   144: goto -> 151
    //   147: invokestatic a : (Ljava/lang/Exception;)Ljava/lang/Exception;
    //   150: athrow
    //   151: aload_1
    //   152: aload_0
    //   153: getfield Za : Lcom/fasterxml/Zor/Zk;
    //   156: aload_2
    //   157: invokevirtual Zo : (Lcom/fasterxml/Zor/Zk;Lcom/fasterxml/Zor/Zo;)Lcom/fasterxml/Zor/Zyd;
    //   160: astore #4
    //   162: aload #5
    //   164: ifnonnull -> 173
    //   167: aload_0
    //   168: getfield Zq : Lcom/fasterxml/Zor/Zyd;
    //   171: astore #5
    //   173: aload #5
    //   175: ifnonnull -> 207
    //   178: aload_1
    //   179: aload_0
    //   180: getfield ZG : Lcom/fasterxml/Zor/Zk;
    //   183: aload_2
    //   184: invokevirtual Zr : (Lcom/fasterxml/Zor/Zk;Lcom/fasterxml/Zor/Zo;)Lcom/fasterxml/Zor/Zyd;
    //   187: astore #5
    //   189: aload_3
    //   190: ifnull -> 216
    //   193: iconst_2
    //   194: anewarray burp/Zbqc
    //   197: invokestatic Zr : ([Lburp/Zbqc;)V
    //   200: goto -> 207
    //   203: invokestatic a : (Ljava/lang/Exception;)Ljava/lang/Exception;
    //   206: athrow
    //   207: aload_1
    //   208: aload #5
    //   210: aload_2
    //   211: invokevirtual ZR : (Lcom/fasterxml/Zor/Zyd;Lcom/fasterxml/Zor/Zo;)Lcom/fasterxml/Zor/Zyd;
    //   214: astore #5
    //   216: aload_0
    //   217: getfield Zx : Ljava/util/Set;
    //   220: astore #8
    //   222: aload_0
    //   223: getfield ZJ : Ljava/util/Set;
    //   226: astore #9
    //   228: iconst_0
    //   229: istore #10
    //   231: aload #7
    //   233: aload #6
    //   235: invokestatic ZB : (Ljava/lang/Object;Ljava/lang/Object;)Z
    //   238: ifeq -> 471
    //   241: aload_1
    //   242: invokevirtual ZH : ()Lcom/fasterxml/Zor/Zy7;
    //   245: astore #11
    //   247: aload #6
    //   249: aload #11
    //   251: aload #7
    //   253: invokevirtual ZH : (Lcom/fasterxml/Zj/Zf;Lcom/fasterxml/Zoz/Ziv;)Lcom/fasterxml/Zve;
    //   256: invokevirtual ZG : ()Ljava/util/Set;
    //   259: astore #12
    //   261: aload #12
    //   263: invokestatic ZS : (Ljava/util/Collection;)Z
    //   266: ifeq -> 351
    //   269: aload #8
    //   271: ifnonnull -> 295
    //   274: goto -> 281
    //   277: invokestatic a : (Ljava/lang/Exception;)Ljava/lang/Exception;
    //   280: athrow
    //   281: new java/util/HashSet
    //   284: dup
    //   285: invokespecial <init> : ()V
    //   288: goto -> 304
    //   291: invokestatic a : (Ljava/lang/Exception;)Ljava/lang/Exception;
    //   294: athrow
    //   295: new java/util/HashSet
    //   298: dup
    //   299: aload #8
    //   301: invokespecial <init> : (Ljava/util/Collection;)V
    //   304: astore #8
    //   306: aload #12
    //   308: invokeinterface iterator : ()Ljava/util/Iterator;
    //   313: astore #13
    //   315: aload #13
    //   317: invokeinterface hasNext : ()Z
    //   322: ifeq -> 351
    //   325: aload #13
    //   327: invokeinterface next : ()Ljava/lang/Object;
    //   332: checkcast java/lang/String
    //   335: astore #14
    //   337: aload #8
    //   339: aload #14
    //   341: invokeinterface add : (Ljava/lang/Object;)Z
    //   346: pop
    //   347: aload_3
    //   348: ifnull -> 315
    //   351: aload #6
    //   353: aload #11
    //   355: aload #7
    //   357: invokevirtual Z_ : (Lcom/fasterxml/Zj/Zf;Lcom/fasterxml/Zoz/Ziv;)Lcom/fasterxml/Zyn;
    //   360: invokevirtual ZU : ()Ljava/util/Set;
    //   363: astore #13
    //   365: aload #13
    //   367: ifnull -> 452
    //   370: aload #9
    //   372: ifnonnull -> 396
    //   375: goto -> 382
    //   378: invokestatic a : (Ljava/lang/Exception;)Ljava/lang/Exception;
    //   381: athrow
    //   382: new java/util/HashSet
    //   385: dup
    //   386: invokespecial <init> : ()V
    //   389: goto -> 405
    //   392: invokestatic a : (Ljava/lang/Exception;)Ljava/lang/Exception;
    //   395: athrow
    //   396: new java/util/HashSet
    //   399: dup
    //   400: aload #9
    //   402: invokespecial <init> : (Ljava/util/Collection;)V
    //   405: astore #9
    //   407: aload #13
    //   409: invokeinterface iterator : ()Ljava/util/Iterator;
    //   414: astore #14
    //   416: aload #14
    //   418: invokeinterface hasNext : ()Z
    //   423: ifeq -> 452
    //   426: aload #14
    //   428: invokeinterface next : ()Ljava/lang/Object;
    //   433: checkcast java/lang/String
    //   436: astore #15
    //   438: aload #9
    //   440: aload #15
    //   442: invokeinterface add : (Ljava/lang/Object;)Z
    //   447: pop
    //   448: aload_3
    //   449: ifnull -> 416
    //   452: aload #6
    //   454: aload #7
    //   456: invokevirtual Zi : (Lcom/fasterxml/Zoz/Ziv;)Ljava/lang/Boolean;
    //   459: astore #14
    //   461: getstatic java/lang/Boolean.TRUE : Ljava/lang/Boolean;
    //   464: aload #14
    //   466: invokevirtual equals : (Ljava/lang/Object;)Z
    //   469: istore #10
    //   471: aload_0
    //   472: aload_1
    //   473: aload_2
    //   474: ldc java/util/Map
    //   476: invokevirtual Z_ : (Lcom/fasterxml/Zor/Zyi;Lcom/fasterxml/Zor/Zo;Ljava/lang/Class;)Lcom/fasterxml/Zgy;
    //   479: astore #11
    //   481: aload #11
    //   483: ifnull -> 508
    //   486: aload #11
    //   488: getstatic com/fasterxml/Zye.WRITE_SORTED_MAP_ENTRIES : Lcom/fasterxml/Zye;
    //   491: invokevirtual Zq : (Lcom/fasterxml/Zye;)Ljava/lang/Boolean;
    //   494: astore #12
    //   496: aload #12
    //   498: ifnull -> 508
    //   501: aload #12
    //   503: invokevirtual booleanValue : ()Z
    //   506: istore #10
    //   508: aload_0
    //   509: aload_2
    //   510: aload #5
    //   512: aload #4
    //   514: aload #8
    //   516: aload #9
    //   518: iload #10
    //   520: invokevirtual Zy : (Lcom/fasterxml/Zor/Zo;Lcom/fasterxml/Zor/Zyd;Lcom/fasterxml/Zor/Zyd;Ljava/util/Set;Ljava/util/Set;Z)Lcom/fasterxml/Zz7;
    //   523: astore #12
    //   525: aload #7
    //   527: ifnull -> 553
    //   530: aload #6
    //   532: aload #7
    //   534: invokevirtual Zb : (Lcom/fasterxml/Zoz/Ziv;)Ljava/lang/Object;
    //   537: astore #13
    //   539: aload #13
    //   541: ifnull -> 553
    //   544: aload #12
    //   546: aload #13
    //   548: invokevirtual ZL : (Ljava/lang/Object;)Lcom/fasterxml/Zz7;
    //   551: astore #12
    //   553: aload_0
    //   554: aload_1
    //   555: aload_2
    //   556: ldc java/util/Map
    //   558: invokevirtual ZW : (Lcom/fasterxml/Zor/Zyi;Lcom/fasterxml/Zor/Zo;Ljava/lang/Class;)Lcom/fasterxml/Zz_;
    //   561: astore #13
    //   563: aload #13
    //   565: ifnull -> 787
    //   568: aload #13
    //   570: invokevirtual Zq : ()Lcom/fasterxml/Zqg;
    //   573: astore #14
    //   575: aload #14
    //   577: getstatic com/fasterxml/Zqg.USE_DEFAULTS : Lcom/fasterxml/Zqg;
    //   580: if_acmpeq -> 787
    //   583: getstatic com/fasterxml/Zgv.ZN : [I
    //   586: aload #14
    //   588: invokevirtual ordinal : ()I
    //   591: iaload
    //   592: tableswitch default -> 770, 1 -> 636, 2 -> 682, 3 -> 712, 4 -> 724, 5 -> 760, 6 -> 770
    //   632: invokestatic a : (Ljava/lang/Exception;)Ljava/lang/Exception;
    //   635: athrow
    //   636: aload_0
    //   637: getfield Za : Lcom/fasterxml/Zor/Zk;
    //   640: invokestatic ZQ : (Lcom/fasterxml/Zor/Zk;)Ljava/lang/Object;
    //   643: astore #15
    //   645: iconst_1
    //   646: istore #16
    //   648: aload #15
    //   650: ifnull -> 776
    //   653: aload #15
    //   655: invokevirtual getClass : ()Ljava/lang/Class;
    //   658: invokevirtual isArray : ()Z
    //   661: ifeq -> 776
    //   664: goto -> 671
    //   667: invokestatic a : (Ljava/lang/Exception;)Ljava/lang/Exception;
    //   670: athrow
    //   671: aload #15
    //   673: invokestatic Zp : (Ljava/lang/Object;)Ljava/lang/Object;
    //   676: astore #15
    //   678: aload_3
    //   679: ifnull -> 776
    //   682: iconst_1
    //   683: istore #16
    //   685: aload_0
    //   686: getfield Za : Lcom/fasterxml/Zor/Zk;
    //   689: invokevirtual ZP : ()Z
    //   692: ifeq -> 705
    //   695: getstatic com/fasterxml/Zz7.ZT : Ljava/lang/Object;
    //   698: goto -> 706
    //   701: invokestatic a : (Ljava/lang/Exception;)Ljava/lang/Exception;
    //   704: athrow
    //   705: aconst_null
    //   706: astore #15
    //   708: aload_3
    //   709: ifnull -> 776
    //   712: iconst_1
    //   713: istore #16
    //   715: getstatic com/fasterxml/Zz7.ZT : Ljava/lang/Object;
    //   718: astore #15
    //   720: aload_3
    //   721: ifnull -> 776
    //   724: aload_1
    //   725: aconst_null
    //   726: aload #13
    //   728: invokevirtual Zv : ()Ljava/lang/Class;
    //   731: invokevirtual ZQ : (Lcom/fasterxml/Zoz/Zp;Ljava/lang/Class;)Ljava/lang/Object;
    //   734: astore #15
    //   736: aload #15
    //   738: ifnonnull -> 748
    //   741: iconst_1
    //   742: istore #16
    //   744: aload_3
    //   745: ifnull -> 776
    //   748: aload_1
    //   749: aload #15
    //   751: invokevirtual Zz : (Ljava/lang/Object;)Z
    //   754: istore #16
    //   756: aload_3
    //   757: ifnull -> 776
    //   760: aconst_null
    //   761: astore #15
    //   763: iconst_1
    //   764: istore #16
    //   766: aload_3
    //   767: ifnull -> 776
    //   770: aconst_null
    //   771: astore #15
    //   773: iconst_0
    //   774: istore #16
    //   776: aload #12
    //   778: aload #15
    //   780: iload #16
    //   782: invokevirtual ZK : (Ljava/lang/Object;Z)Lcom/fasterxml/Zz7;
    //   785: astore #12
    //   787: aload #12
    //   789: areturn
    // Exception table:
    //   from	to	target	type
    //   16	24	24	com/fasterxml/Zor/Zy_
    //   115	127	130	com/fasterxml/Zor/Zy_
    //   120	144	147	com/fasterxml/Zor/Zy_
    //   189	200	203	com/fasterxml/Zor/Zy_
    //   261	274	277	com/fasterxml/Zor/Zy_
    //   269	291	291	com/fasterxml/Zor/Zy_
    //   365	375	378	com/fasterxml/Zor/Zy_
    //   370	392	392	com/fasterxml/Zor/Zy_
    //   575	632	632	com/fasterxml/Zor/Zy_
    //   648	664	667	com/fasterxml/Zor/Zy_
    //   685	701	701	com/fasterxml/Zor/Zy_
  }
  
  public Zk Zq() {
    return this.Za;
  }
  
  public boolean ZQ(Zyi paramZyi, Map<?, ?> paramMap) {
    String str = Zz0.ZG();
    try {
      if (paramMap.isEmpty())
        return true; 
    } catch (Zym zym) {
      throw a(null);
    } 
    Object object = this.Zn;
    try {
      if (object == null)
        try {
          if (!this.Zf)
            return false; 
        } catch (Zym zym) {
          throw a(null);
        }  
    } catch (Zym zym) {
      throw a(null);
    } 
    Zyd<Object> zyd = this.ZD;
    try {
    
    } catch (Zym zym) {
      throw a(null);
    } 
    boolean bool = (ZT == object) ? true : false;
    if (zyd != null) {
      for (Object object1 : paramMap.values()) {
        try {
          if (object1 == null) {
            try {
              if (!this.Zf || str != null)
                return false; 
            } catch (Zym zym) {
              throw a(null);
            } 
            continue;
          } 
        } catch (Zym zym) {
          throw a(null);
        } 
        try {
          if (bool) {
            try {
              if (!zyd.Zt(paramZyi, object1))
                return false; 
            } catch (Zym zym) {
              throw a(null);
            } 
          } else {
            try {
              if (object != null) {
                try {
                  if (!object.equals(paramMap))
                    return false; 
                } catch (Zym zym) {
                  throw a(null);
                } 
              } else {
                return false;
              } 
            } catch (Zym zym) {
              throw a(null);
            } 
          } 
        } catch (Zym zym) {
          throw a(null);
        } 
        if (str != null)
          break; 
      } 
      return true;
    } 
    for (Object object1 : paramMap.values()) {
      try {
        if (object1 == null) {
          try {
            if (!this.Zf || str != null)
              return false; 
          } catch (Zym zym) {
            throw a(null);
          } 
          continue;
        } 
      } catch (Zym zym) {
        throw a(null);
      } 
      try {
        zyd = ZM(paramZyi, object1);
      } catch (Zym zym) {
        return false;
      } 
      try {
        if (bool) {
          try {
            if (!zyd.Zt(paramZyi, object1))
              return false; 
          } catch (Zym zym) {
            throw a(null);
          } 
        } else {
          try {
            if (object != null) {
              try {
                if (!object.equals(paramMap))
                  return false; 
              } catch (Zym zym) {
                throw a(null);
              } 
            } else {
              return false;
            } 
          } catch (Zym zym) {
            throw a(null);
          } 
        } 
      } catch (Zym zym) {
        throw a(null);
      } 
      if (str != null)
        break; 
    } 
    return true;
  }
  
  public boolean ZQ(Map<?, ?> paramMap) {
    return (paramMap.size() == 1);
  }
  
  public void Zk(Map<?, ?> paramMap, Zf paramZf, Zyi paramZyi) throws IOException {
    paramZf.ZB(paramMap);
    ZV(paramMap, paramZf, paramZyi);
    paramZf.Zh();
  }
  
  public void ZI(Map<?, ?> paramMap, Zf paramZf, Zyi paramZyi, Za paramZa) throws IOException {
    paramZf.Z_(paramMap);
    Zn zn = paramZa.ZA(paramZf, paramZa.Zm(paramMap, Zl.START_OBJECT));
    ZV(paramMap, paramZf, paramZyi);
    paramZa.ZP(paramZf, zn);
  }
  
  public void ZV(Map<?, ?> paramMap, Zf paramZf, Zyi paramZyi) throws IOException {
    // Byte code:
    //   0: invokestatic ZG : ()Ljava/lang/String;
    //   3: astore #4
    //   5: aload_1
    //   6: invokeinterface isEmpty : ()Z
    //   11: ifne -> 203
    //   14: aload_0
    //   15: getfield ZH : Z
    //   18: ifne -> 45
    //   21: goto -> 28
    //   24: invokestatic a : (Ljava/lang/Exception;)Ljava/lang/Exception;
    //   27: athrow
    //   28: aload_3
    //   29: getstatic com/fasterxml/Zor/Zy0.ORDER_MAP_ENTRIES_BY_KEYS : Lcom/fasterxml/Zor/Zy0;
    //   32: invokevirtual ZW : (Lcom/fasterxml/Zor/Zy0;)Z
    //   35: ifeq -> 53
    //   38: goto -> 45
    //   41: invokestatic a : (Ljava/lang/Exception;)Ljava/lang/Exception;
    //   44: athrow
    //   45: aload_0
    //   46: aload_1
    //   47: aload_2
    //   48: aload_3
    //   49: invokevirtual ZL : (Ljava/util/Map;Lcom/fasterxml/Zb/Zf;Lcom/fasterxml/Zor/Zyi;)Ljava/util/Map;
    //   52: astore_1
    //   53: aload_0
    //   54: getfield Zd : Ljava/lang/Object;
    //   57: ifnull -> 101
    //   60: aload_0
    //   61: aload_3
    //   62: aload_0
    //   63: getfield Zd : Ljava/lang/Object;
    //   66: aload_1
    //   67: invokevirtual ZJ : (Lcom/fasterxml/Zor/Zyi;Ljava/lang/Object;Ljava/lang/Object;)Lcom/fasterxml/Zk/Zh;
    //   70: dup
    //   71: astore #5
    //   73: ifnull -> 101
    //   76: aload_0
    //   77: aload_1
    //   78: aload_2
    //   79: aload_3
    //   80: aload #5
    //   82: aload_0
    //   83: getfield Zn : Ljava/lang/Object;
    //   86: invokevirtual Zh : (Ljava/util/Map;Lcom/fasterxml/Zb/Zf;Lcom/fasterxml/Zor/Zyi;Lcom/fasterxml/Zk/Zh;Ljava/lang/Object;)V
    //   89: aload #4
    //   91: ifnull -> 203
    //   94: goto -> 101
    //   97: invokestatic a : (Ljava/lang/Exception;)Ljava/lang/Exception;
    //   100: athrow
    //   101: aload_0
    //   102: getfield Zn : Ljava/lang/Object;
    //   105: ifnonnull -> 129
    //   108: goto -> 115
    //   111: invokestatic a : (Ljava/lang/Exception;)Ljava/lang/Exception;
    //   114: athrow
    //   115: aload_0
    //   116: getfield Zf : Z
    //   119: ifeq -> 152
    //   122: goto -> 129
    //   125: invokestatic a : (Ljava/lang/Exception;)Ljava/lang/Exception;
    //   128: athrow
    //   129: aload_0
    //   130: aload_1
    //   131: aload_2
    //   132: aload_3
    //   133: aload_0
    //   134: getfield Zn : Ljava/lang/Object;
    //   137: invokevirtual Zi : (Ljava/util/Map;Lcom/fasterxml/Zb/Zf;Lcom/fasterxml/Zor/Zyi;Ljava/lang/Object;)V
    //   140: aload #4
    //   142: ifnull -> 203
    //   145: goto -> 152
    //   148: invokestatic a : (Ljava/lang/Exception;)Ljava/lang/Exception;
    //   151: athrow
    //   152: aload_0
    //   153: getfield ZD : Lcom/fasterxml/Zor/Zyd;
    //   156: ifnull -> 189
    //   159: goto -> 166
    //   162: invokestatic a : (Ljava/lang/Exception;)Ljava/lang/Exception;
    //   165: athrow
    //   166: aload_0
    //   167: aload_1
    //   168: aload_2
    //   169: aload_3
    //   170: aload_0
    //   171: getfield ZD : Lcom/fasterxml/Zor/Zyd;
    //   174: invokevirtual ZI : (Ljava/util/Map;Lcom/fasterxml/Zb/Zf;Lcom/fasterxml/Zor/Zyi;Lcom/fasterxml/Zor/Zyd;)V
    //   177: aload #4
    //   179: ifnull -> 203
    //   182: goto -> 189
    //   185: invokestatic a : (Ljava/lang/Exception;)Ljava/lang/Exception;
    //   188: athrow
    //   189: aload_0
    //   190: aload_1
    //   191: aload_2
    //   192: aload_3
    //   193: invokevirtual Zr : (Ljava/util/Map;Lcom/fasterxml/Zb/Zf;Lcom/fasterxml/Zor/Zyi;)V
    //   196: goto -> 203
    //   199: invokestatic a : (Ljava/lang/Exception;)Ljava/lang/Exception;
    //   202: athrow
    //   203: return
    // Exception table:
    //   from	to	target	type
    //   5	21	24	java/io/IOException
    //   14	38	41	java/io/IOException
    //   73	94	97	java/io/IOException
    //   76	108	111	java/io/IOException
    //   101	122	125	java/io/IOException
    //   115	145	148	java/io/IOException
    //   129	159	162	java/io/IOException
    //   152	182	185	java/io/IOException
    //   166	196	199	java/io/IOException
  }
  
  public void Zr(Map<?, ?> paramMap, Zf paramZf, Zyi paramZyi) throws IOException {
    // Byte code:
    //   0: invokestatic ZG : ()Ljava/lang/String;
    //   3: astore #4
    //   5: aload_0
    //   6: getfield Zy : Lcom/fasterxml/Zp/Za;
    //   9: ifnull -> 25
    //   12: aload_0
    //   13: aload_1
    //   14: aload_2
    //   15: aload_3
    //   16: aconst_null
    //   17: invokevirtual ZP : (Ljava/util/Map;Lcom/fasterxml/Zb/Zf;Lcom/fasterxml/Zor/Zyi;Ljava/lang/Object;)V
    //   20: return
    //   21: invokestatic a : (Ljava/lang/Exception;)Ljava/lang/Exception;
    //   24: athrow
    //   25: aload_0
    //   26: getfield Zq : Lcom/fasterxml/Zor/Zyd;
    //   29: astore #5
    //   31: aconst_null
    //   32: astore #6
    //   34: aload_1
    //   35: invokeinterface entrySet : ()Ljava/util/Set;
    //   40: invokeinterface iterator : ()Ljava/util/Iterator;
    //   45: astore #7
    //   47: aload #7
    //   49: invokeinterface hasNext : ()Z
    //   54: ifeq -> 232
    //   57: aload #7
    //   59: invokeinterface next : ()Ljava/lang/Object;
    //   64: checkcast java/util/Map$Entry
    //   67: astore #8
    //   69: aload #8
    //   71: invokeinterface getValue : ()Ljava/lang/Object;
    //   76: astore #9
    //   78: aload #8
    //   80: invokeinterface getKey : ()Ljava/lang/Object;
    //   85: astore #6
    //   87: aload #6
    //   89: ifnonnull -> 122
    //   92: aload_3
    //   93: aload_0
    //   94: getfield ZG : Lcom/fasterxml/Zor/Zk;
    //   97: aload_0
    //   98: getfield Zw : Lcom/fasterxml/Zor/Zo;
    //   101: invokevirtual ZB : (Lcom/fasterxml/Zor/Zk;Lcom/fasterxml/Zor/Zo;)Lcom/fasterxml/Zor/Zyd;
    //   104: aconst_null
    //   105: aload_2
    //   106: aload_3
    //   107: invokevirtual serialize : (Ljava/lang/Object;Lcom/fasterxml/Zb/Zf;Lcom/fasterxml/Zor/Zyi;)V
    //   110: aload #4
    //   112: ifnull -> 176
    //   115: goto -> 122
    //   118: invokestatic a : (Ljava/lang/Exception;)Ljava/lang/Exception;
    //   121: athrow
    //   122: aload_0
    //   123: getfield Zz : Lcom/fasterxml/Zm/Zk;
    //   126: ifnull -> 167
    //   129: goto -> 136
    //   132: invokestatic a : (Ljava/lang/Exception;)Ljava/lang/Exception;
    //   135: athrow
    //   136: aload_0
    //   137: getfield Zz : Lcom/fasterxml/Zm/Zk;
    //   140: aload #6
    //   142: invokevirtual Zv : (Ljava/lang/Object;)Z
    //   145: ifeq -> 167
    //   148: goto -> 155
    //   151: invokestatic a : (Ljava/lang/Exception;)Ljava/lang/Exception;
    //   154: athrow
    //   155: aload #4
    //   157: ifnull -> 47
    //   160: goto -> 167
    //   163: invokestatic a : (Ljava/lang/Exception;)Ljava/lang/Exception;
    //   166: athrow
    //   167: aload #5
    //   169: aload #6
    //   171: aload_2
    //   172: aload_3
    //   173: invokevirtual serialize : (Ljava/lang/Object;Lcom/fasterxml/Zb/Zf;Lcom/fasterxml/Zor/Zyi;)V
    //   176: aload #9
    //   178: ifnonnull -> 198
    //   181: aload_3
    //   182: aload_2
    //   183: invokevirtual ZT : (Lcom/fasterxml/Zb/Zf;)V
    //   186: aload #4
    //   188: ifnull -> 47
    //   191: goto -> 198
    //   194: invokestatic a : (Ljava/lang/Exception;)Ljava/lang/Exception;
    //   197: athrow
    //   198: aload_0
    //   199: getfield ZD : Lcom/fasterxml/Zor/Zyd;
    //   202: astore #10
    //   204: aload #10
    //   206: ifnonnull -> 218
    //   209: aload_0
    //   210: aload_3
    //   211: aload #9
    //   213: invokespecial ZM : (Lcom/fasterxml/Zor/Zyi;Ljava/lang/Object;)Lcom/fasterxml/Zor/Zyd;
    //   216: astore #10
    //   218: aload #10
    //   220: aload #9
    //   222: aload_2
    //   223: aload_3
    //   224: invokevirtual serialize : (Ljava/lang/Object;Lcom/fasterxml/Zb/Zf;Lcom/fasterxml/Zor/Zyi;)V
    //   227: aload #4
    //   229: ifnull -> 47
    //   232: goto -> 250
    //   235: astore #7
    //   237: aload_0
    //   238: aload_3
    //   239: aload #7
    //   241: aload_1
    //   242: aload #6
    //   244: invokestatic valueOf : (Ljava/lang/Object;)Ljava/lang/String;
    //   247: invokevirtual ZO : (Lcom/fasterxml/Zor/Zyi;Ljava/lang/Throwable;Ljava/lang/Object;Ljava/lang/String;)V
    //   250: return
    // Exception table:
    //   from	to	target	type
    //   5	21	21	java/lang/Exception
    //   34	232	235	java/lang/Exception
    //   87	115	118	java/lang/Exception
    //   92	129	132	java/lang/Exception
    //   122	148	151	java/lang/Exception
    //   136	160	163	java/lang/Exception
    //   176	191	194	java/lang/Exception
  }
  
  public void Zi(Map<?, ?> paramMap, Zf paramZf, Zyi paramZyi, Object paramObject) throws IOException {
    // Byte code:
    //   0: invokestatic ZG : ()Ljava/lang/String;
    //   3: astore #5
    //   5: aload_0
    //   6: getfield Zy : Lcom/fasterxml/Zp/Za;
    //   9: ifnull -> 26
    //   12: aload_0
    //   13: aload_1
    //   14: aload_2
    //   15: aload_3
    //   16: aload #4
    //   18: invokevirtual ZP : (Ljava/util/Map;Lcom/fasterxml/Zb/Zf;Lcom/fasterxml/Zor/Zyi;Ljava/lang/Object;)V
    //   21: return
    //   22: invokestatic a : (Ljava/lang/Exception;)Ljava/lang/Exception;
    //   25: athrow
    //   26: getstatic com/fasterxml/Zz7.ZT : Ljava/lang/Object;
    //   29: aload #4
    //   31: if_acmpne -> 42
    //   34: iconst_1
    //   35: goto -> 43
    //   38: invokestatic a : (Ljava/lang/Exception;)Ljava/lang/Exception;
    //   41: athrow
    //   42: iconst_0
    //   43: istore #6
    //   45: aload_1
    //   46: invokeinterface entrySet : ()Ljava/util/Set;
    //   51: invokeinterface iterator : ()Ljava/util/Iterator;
    //   56: astore #7
    //   58: aload #7
    //   60: invokeinterface hasNext : ()Z
    //   65: ifeq -> 345
    //   68: aload #7
    //   70: invokeinterface next : ()Ljava/lang/Object;
    //   75: checkcast java/util/Map$Entry
    //   78: astore #8
    //   80: aload #8
    //   82: invokeinterface getKey : ()Ljava/lang/Object;
    //   87: astore #9
    //   89: aload #9
    //   91: ifnonnull -> 113
    //   94: aload_3
    //   95: aload_0
    //   96: getfield ZG : Lcom/fasterxml/Zor/Zk;
    //   99: aload_0
    //   100: getfield Zw : Lcom/fasterxml/Zor/Zo;
    //   103: invokevirtual ZB : (Lcom/fasterxml/Zor/Zk;Lcom/fasterxml/Zor/Zo;)Lcom/fasterxml/Zor/Zyd;
    //   106: astore #10
    //   108: aload #5
    //   110: ifnull -> 164
    //   113: aload_0
    //   114: getfield Zz : Lcom/fasterxml/Zm/Zk;
    //   117: ifnull -> 158
    //   120: goto -> 127
    //   123: invokestatic a : (Ljava/lang/Exception;)Ljava/lang/Exception;
    //   126: athrow
    //   127: aload_0
    //   128: getfield Zz : Lcom/fasterxml/Zm/Zk;
    //   131: aload #9
    //   133: invokevirtual Zv : (Ljava/lang/Object;)Z
    //   136: ifeq -> 158
    //   139: goto -> 146
    //   142: invokestatic a : (Ljava/lang/Exception;)Ljava/lang/Exception;
    //   145: athrow
    //   146: aload #5
    //   148: ifnull -> 58
    //   151: goto -> 158
    //   154: invokestatic a : (Ljava/lang/Exception;)Ljava/lang/Exception;
    //   157: athrow
    //   158: aload_0
    //   159: getfield Zq : Lcom/fasterxml/Zor/Zyd;
    //   162: astore #10
    //   164: aload #8
    //   166: invokeinterface getValue : ()Ljava/lang/Object;
    //   171: astore #11
    //   173: aload #11
    //   175: ifnonnull -> 215
    //   178: aload_0
    //   179: getfield Zf : Z
    //   182: ifeq -> 204
    //   185: goto -> 192
    //   188: invokestatic a : (Ljava/lang/Exception;)Ljava/lang/Exception;
    //   191: athrow
    //   192: aload #5
    //   194: ifnull -> 58
    //   197: goto -> 204
    //   200: invokestatic a : (Ljava/lang/Exception;)Ljava/lang/Exception;
    //   203: athrow
    //   204: aload_3
    //   205: invokevirtual ZJ : ()Lcom/fasterxml/Zor/Zyd;
    //   208: astore #12
    //   210: aload #5
    //   212: ifnull -> 304
    //   215: aload_0
    //   216: getfield ZD : Lcom/fasterxml/Zor/Zyd;
    //   219: astore #12
    //   221: aload #12
    //   223: ifnonnull -> 235
    //   226: aload_0
    //   227: aload_3
    //   228: aload #11
    //   230: invokespecial ZM : (Lcom/fasterxml/Zor/Zyi;Ljava/lang/Object;)Lcom/fasterxml/Zor/Zyd;
    //   233: astore #12
    //   235: iload #6
    //   237: ifeq -> 270
    //   240: aload #12
    //   242: aload_3
    //   243: aload #11
    //   245: invokevirtual Zt : (Lcom/fasterxml/Zor/Zyi;Ljava/lang/Object;)Z
    //   248: ifeq -> 304
    //   251: goto -> 258
    //   254: invokestatic a : (Ljava/lang/Exception;)Ljava/lang/Exception;
    //   257: athrow
    //   258: aload #5
    //   260: ifnull -> 58
    //   263: goto -> 270
    //   266: invokestatic a : (Ljava/lang/Exception;)Ljava/lang/Exception;
    //   269: athrow
    //   270: aload #4
    //   272: ifnull -> 304
    //   275: aload #4
    //   277: aload #11
    //   279: invokevirtual equals : (Ljava/lang/Object;)Z
    //   282: ifeq -> 304
    //   285: goto -> 292
    //   288: invokestatic a : (Ljava/lang/Exception;)Ljava/lang/Exception;
    //   291: athrow
    //   292: aload #5
    //   294: ifnull -> 58
    //   297: goto -> 304
    //   300: invokestatic a : (Ljava/lang/Exception;)Ljava/lang/Exception;
    //   303: athrow
    //   304: aload #10
    //   306: aload #9
    //   308: aload_2
    //   309: aload_3
    //   310: invokevirtual serialize : (Ljava/lang/Object;Lcom/fasterxml/Zb/Zf;Lcom/fasterxml/Zor/Zyi;)V
    //   313: aload #12
    //   315: aload #11
    //   317: aload_2
    //   318: aload_3
    //   319: invokevirtual serialize : (Ljava/lang/Object;Lcom/fasterxml/Zb/Zf;Lcom/fasterxml/Zor/Zyi;)V
    //   322: goto -> 340
    //   325: astore #13
    //   327: aload_0
    //   328: aload_3
    //   329: aload #13
    //   331: aload_1
    //   332: aload #9
    //   334: invokestatic valueOf : (Ljava/lang/Object;)Ljava/lang/String;
    //   337: invokevirtual ZO : (Lcom/fasterxml/Zor/Zyi;Ljava/lang/Throwable;Ljava/lang/Object;Ljava/lang/String;)V
    //   340: aload #5
    //   342: ifnull -> 58
    //   345: return
    // Exception table:
    //   from	to	target	type
    //   5	22	22	java/lang/Exception
    //   26	38	38	java/lang/Exception
    //   108	120	123	java/lang/Exception
    //   113	139	142	java/lang/Exception
    //   127	151	154	java/lang/Exception
    //   173	185	188	java/lang/Exception
    //   178	197	200	java/lang/Exception
    //   235	251	254	java/lang/Exception
    //   240	263	266	java/lang/Exception
    //   270	285	288	java/lang/Exception
    //   275	297	300	java/lang/Exception
    //   304	322	325	java/lang/Exception
  }
  
  public void ZI(Map<?, ?> paramMap, Zf paramZf, Zyi paramZyi, Zyd<Object> paramZyd) throws IOException {
    // Byte code:
    //   0: invokestatic ZG : ()Ljava/lang/String;
    //   3: aload_0
    //   4: getfield Zq : Lcom/fasterxml/Zor/Zyd;
    //   7: astore #6
    //   9: aload_0
    //   10: getfield Zy : Lcom/fasterxml/Zp/Za;
    //   13: astore #7
    //   15: astore #5
    //   17: aload_1
    //   18: invokeinterface entrySet : ()Ljava/util/Set;
    //   23: invokeinterface iterator : ()Ljava/util/Iterator;
    //   28: astore #8
    //   30: aload #8
    //   32: invokeinterface hasNext : ()Z
    //   37: ifeq -> 248
    //   40: aload #8
    //   42: invokeinterface next : ()Ljava/lang/Object;
    //   47: checkcast java/util/Map$Entry
    //   50: astore #9
    //   52: aload #9
    //   54: invokeinterface getKey : ()Ljava/lang/Object;
    //   59: astore #10
    //   61: aload_0
    //   62: getfield Zz : Lcom/fasterxml/Zm/Zk;
    //   65: ifnull -> 99
    //   68: aload_0
    //   69: getfield Zz : Lcom/fasterxml/Zm/Zk;
    //   72: aload #10
    //   74: invokevirtual Zv : (Ljava/lang/Object;)Z
    //   77: ifeq -> 99
    //   80: goto -> 87
    //   83: invokestatic a : (Ljava/lang/Exception;)Ljava/lang/Exception;
    //   86: athrow
    //   87: aload #5
    //   89: ifnull -> 30
    //   92: goto -> 99
    //   95: invokestatic a : (Ljava/lang/Exception;)Ljava/lang/Exception;
    //   98: athrow
    //   99: aload #10
    //   101: ifnonnull -> 134
    //   104: aload_3
    //   105: aload_0
    //   106: getfield ZG : Lcom/fasterxml/Zor/Zk;
    //   109: aload_0
    //   110: getfield Zw : Lcom/fasterxml/Zor/Zo;
    //   113: invokevirtual ZB : (Lcom/fasterxml/Zor/Zk;Lcom/fasterxml/Zor/Zo;)Lcom/fasterxml/Zor/Zyd;
    //   116: aconst_null
    //   117: aload_2
    //   118: aload_3
    //   119: invokevirtual serialize : (Ljava/lang/Object;Lcom/fasterxml/Zb/Zf;Lcom/fasterxml/Zor/Zyi;)V
    //   122: aload #5
    //   124: ifnull -> 150
    //   127: goto -> 134
    //   130: invokestatic a : (Ljava/lang/Exception;)Ljava/lang/Exception;
    //   133: athrow
    //   134: aload #6
    //   136: aload #10
    //   138: aload_2
    //   139: aload_3
    //   140: invokevirtual serialize : (Ljava/lang/Object;Lcom/fasterxml/Zb/Zf;Lcom/fasterxml/Zor/Zyi;)V
    //   143: goto -> 150
    //   146: invokestatic a : (Ljava/lang/Exception;)Ljava/lang/Exception;
    //   149: athrow
    //   150: aload #9
    //   152: invokeinterface getValue : ()Ljava/lang/Object;
    //   157: astore #11
    //   159: aload #11
    //   161: ifnonnull -> 181
    //   164: aload_3
    //   165: aload_2
    //   166: invokevirtual ZT : (Lcom/fasterxml/Zb/Zf;)V
    //   169: aload #5
    //   171: ifnull -> 243
    //   174: goto -> 181
    //   177: invokestatic a : (Ljava/lang/Exception;)Ljava/lang/Exception;
    //   180: athrow
    //   181: aload #7
    //   183: ifnonnull -> 207
    //   186: aload #4
    //   188: aload #11
    //   190: aload_2
    //   191: aload_3
    //   192: invokevirtual serialize : (Ljava/lang/Object;Lcom/fasterxml/Zb/Zf;Lcom/fasterxml/Zor/Zyi;)V
    //   195: aload #5
    //   197: ifnull -> 225
    //   200: goto -> 207
    //   203: invokestatic a : (Ljava/lang/Exception;)Ljava/lang/Exception;
    //   206: athrow
    //   207: aload #4
    //   209: aload #11
    //   211: aload_2
    //   212: aload_3
    //   213: aload #7
    //   215: invokevirtual Zo : (Ljava/lang/Object;Lcom/fasterxml/Zb/Zf;Lcom/fasterxml/Zor/Zyi;Lcom/fasterxml/Zp/Za;)V
    //   218: goto -> 225
    //   221: invokestatic a : (Ljava/lang/Exception;)Ljava/lang/Exception;
    //   224: athrow
    //   225: goto -> 243
    //   228: astore #12
    //   230: aload_0
    //   231: aload_3
    //   232: aload #12
    //   234: aload_1
    //   235: aload #10
    //   237: invokestatic valueOf : (Ljava/lang/Object;)Ljava/lang/String;
    //   240: invokevirtual ZO : (Lcom/fasterxml/Zor/Zyi;Ljava/lang/Throwable;Ljava/lang/Object;Ljava/lang/String;)V
    //   243: aload #5
    //   245: ifnull -> 30
    //   248: return
    // Exception table:
    //   from	to	target	type
    //   61	80	83	java/lang/Exception
    //   68	92	95	java/lang/Exception
    //   99	127	130	java/lang/Exception
    //   104	143	146	java/lang/Exception
    //   159	174	177	java/lang/Exception
    //   181	200	203	java/lang/Exception
    //   181	225	228	java/lang/Exception
    //   186	218	221	java/lang/Exception
  }
  
  public void Zh(Map<?, ?> paramMap, Zf paramZf, Zyi paramZyi, Zh paramZh, Object paramObject) throws IOException {
    // Byte code:
    //   0: invokestatic ZG : ()Ljava/lang/String;
    //   3: new com/fasterxml/Zyp
    //   6: dup
    //   7: aload_0
    //   8: getfield Zy : Lcom/fasterxml/Zp/Za;
    //   11: aload_0
    //   12: getfield Zw : Lcom/fasterxml/Zor/Zo;
    //   15: invokespecial <init> : (Lcom/fasterxml/Zp/Za;Lcom/fasterxml/Zor/Zo;)V
    //   18: astore #7
    //   20: astore #6
    //   22: getstatic com/fasterxml/Zz7.ZT : Ljava/lang/Object;
    //   25: aload #5
    //   27: if_acmpne -> 38
    //   30: iconst_1
    //   31: goto -> 39
    //   34: invokestatic a : (Ljava/lang/Exception;)Ljava/lang/Exception;
    //   37: athrow
    //   38: iconst_0
    //   39: istore #8
    //   41: aload_1
    //   42: invokeinterface entrySet : ()Ljava/util/Set;
    //   47: invokeinterface iterator : ()Ljava/util/Iterator;
    //   52: astore #9
    //   54: aload #9
    //   56: invokeinterface hasNext : ()Z
    //   61: ifeq -> 341
    //   64: aload #9
    //   66: invokeinterface next : ()Ljava/lang/Object;
    //   71: checkcast java/util/Map$Entry
    //   74: astore #10
    //   76: aload #10
    //   78: invokeinterface getKey : ()Ljava/lang/Object;
    //   83: astore #11
    //   85: aload_0
    //   86: getfield Zz : Lcom/fasterxml/Zm/Zk;
    //   89: ifnull -> 123
    //   92: aload_0
    //   93: getfield Zz : Lcom/fasterxml/Zm/Zk;
    //   96: aload #11
    //   98: invokevirtual Zv : (Ljava/lang/Object;)Z
    //   101: ifeq -> 123
    //   104: goto -> 111
    //   107: invokestatic a : (Ljava/lang/Exception;)Ljava/lang/Exception;
    //   110: athrow
    //   111: aload #6
    //   113: ifnull -> 54
    //   116: goto -> 123
    //   119: invokestatic a : (Ljava/lang/Exception;)Ljava/lang/Exception;
    //   122: athrow
    //   123: aload #11
    //   125: ifnonnull -> 147
    //   128: aload_3
    //   129: aload_0
    //   130: getfield ZG : Lcom/fasterxml/Zor/Zk;
    //   133: aload_0
    //   134: getfield Zw : Lcom/fasterxml/Zor/Zo;
    //   137: invokevirtual ZB : (Lcom/fasterxml/Zor/Zk;Lcom/fasterxml/Zor/Zo;)Lcom/fasterxml/Zor/Zyd;
    //   140: astore #12
    //   142: aload #6
    //   144: ifnull -> 153
    //   147: aload_0
    //   148: getfield Zq : Lcom/fasterxml/Zor/Zyd;
    //   151: astore #12
    //   153: aload #10
    //   155: invokeinterface getValue : ()Ljava/lang/Object;
    //   160: astore #13
    //   162: aload #13
    //   164: ifnonnull -> 204
    //   167: aload_0
    //   168: getfield Zf : Z
    //   171: ifeq -> 193
    //   174: goto -> 181
    //   177: invokestatic a : (Ljava/lang/Exception;)Ljava/lang/Exception;
    //   180: athrow
    //   181: aload #6
    //   183: ifnull -> 54
    //   186: goto -> 193
    //   189: invokestatic a : (Ljava/lang/Exception;)Ljava/lang/Exception;
    //   192: athrow
    //   193: aload_3
    //   194: invokevirtual ZJ : ()Lcom/fasterxml/Zor/Zyd;
    //   197: astore #14
    //   199: aload #6
    //   201: ifnull -> 293
    //   204: aload_0
    //   205: getfield ZD : Lcom/fasterxml/Zor/Zyd;
    //   208: astore #14
    //   210: aload #14
    //   212: ifnonnull -> 224
    //   215: aload_0
    //   216: aload_3
    //   217: aload #13
    //   219: invokespecial ZM : (Lcom/fasterxml/Zor/Zyi;Ljava/lang/Object;)Lcom/fasterxml/Zor/Zyd;
    //   222: astore #14
    //   224: iload #8
    //   226: ifeq -> 259
    //   229: aload #14
    //   231: aload_3
    //   232: aload #13
    //   234: invokevirtual Zt : (Lcom/fasterxml/Zor/Zyi;Ljava/lang/Object;)Z
    //   237: ifeq -> 293
    //   240: goto -> 247
    //   243: invokestatic a : (Ljava/lang/Exception;)Ljava/lang/Exception;
    //   246: athrow
    //   247: aload #6
    //   249: ifnull -> 54
    //   252: goto -> 259
    //   255: invokestatic a : (Ljava/lang/Exception;)Ljava/lang/Exception;
    //   258: athrow
    //   259: aload #5
    //   261: ifnull -> 293
    //   264: aload #5
    //   266: aload #13
    //   268: invokevirtual equals : (Ljava/lang/Object;)Z
    //   271: ifeq -> 293
    //   274: goto -> 281
    //   277: invokestatic a : (Ljava/lang/Exception;)Ljava/lang/Exception;
    //   280: athrow
    //   281: aload #6
    //   283: ifnull -> 54
    //   286: goto -> 293
    //   289: invokestatic a : (Ljava/lang/Exception;)Ljava/lang/Exception;
    //   292: athrow
    //   293: aload #7
    //   295: aload #11
    //   297: aload #13
    //   299: aload #12
    //   301: aload #14
    //   303: invokevirtual ZF : (Ljava/lang/Object;Ljava/lang/Object;Lcom/fasterxml/Zor/Zyd;Lcom/fasterxml/Zor/Zyd;)V
    //   306: aload #4
    //   308: aload_1
    //   309: aload_2
    //   310: aload_3
    //   311: aload #7
    //   313: invokeinterface ZX : (Ljava/lang/Object;Lcom/fasterxml/Zb/Zf;Lcom/fasterxml/Zor/Zyi;Lcom/fasterxml/Zk/Zb;)V
    //   318: goto -> 336
    //   321: astore #15
    //   323: aload_0
    //   324: aload_3
    //   325: aload #15
    //   327: aload_1
    //   328: aload #11
    //   330: invokestatic valueOf : (Ljava/lang/Object;)Ljava/lang/String;
    //   333: invokevirtual ZO : (Lcom/fasterxml/Zor/Zyi;Ljava/lang/Throwable;Ljava/lang/Object;Ljava/lang/String;)V
    //   336: aload #6
    //   338: ifnull -> 54
    //   341: return
    // Exception table:
    //   from	to	target	type
    //   22	34	34	java/lang/Exception
    //   85	104	107	java/lang/Exception
    //   92	116	119	java/lang/Exception
    //   162	174	177	java/lang/Exception
    //   167	186	189	java/lang/Exception
    //   224	240	243	java/lang/Exception
    //   229	252	255	java/lang/Exception
    //   259	274	277	java/lang/Exception
    //   264	286	289	java/lang/Exception
    //   306	318	321	java/lang/Exception
  }
  
  public void ZP(Map<?, ?> paramMap, Zf paramZf, Zyi paramZyi, Object paramObject) throws IOException {
    // Byte code:
    //   0: invokestatic ZG : ()Ljava/lang/String;
    //   3: astore #5
    //   5: getstatic com/fasterxml/Zz7.ZT : Ljava/lang/Object;
    //   8: aload #4
    //   10: if_acmpne -> 21
    //   13: iconst_1
    //   14: goto -> 22
    //   17: invokestatic a : (Ljava/lang/Exception;)Ljava/lang/Exception;
    //   20: athrow
    //   21: iconst_0
    //   22: istore #6
    //   24: aload_1
    //   25: invokeinterface entrySet : ()Ljava/util/Set;
    //   30: invokeinterface iterator : ()Ljava/util/Iterator;
    //   35: astore #7
    //   37: aload #7
    //   39: invokeinterface hasNext : ()Z
    //   44: ifeq -> 328
    //   47: aload #7
    //   49: invokeinterface next : ()Ljava/lang/Object;
    //   54: checkcast java/util/Map$Entry
    //   57: astore #8
    //   59: aload #8
    //   61: invokeinterface getKey : ()Ljava/lang/Object;
    //   66: astore #9
    //   68: aload #9
    //   70: ifnonnull -> 92
    //   73: aload_3
    //   74: aload_0
    //   75: getfield ZG : Lcom/fasterxml/Zor/Zk;
    //   78: aload_0
    //   79: getfield Zw : Lcom/fasterxml/Zor/Zo;
    //   82: invokevirtual ZB : (Lcom/fasterxml/Zor/Zk;Lcom/fasterxml/Zor/Zo;)Lcom/fasterxml/Zor/Zyd;
    //   85: astore #10
    //   87: aload #5
    //   89: ifnull -> 143
    //   92: aload_0
    //   93: getfield Zz : Lcom/fasterxml/Zm/Zk;
    //   96: ifnull -> 137
    //   99: goto -> 106
    //   102: invokestatic a : (Ljava/lang/Exception;)Ljava/lang/Exception;
    //   105: athrow
    //   106: aload_0
    //   107: getfield Zz : Lcom/fasterxml/Zm/Zk;
    //   110: aload #9
    //   112: invokevirtual Zv : (Ljava/lang/Object;)Z
    //   115: ifeq -> 137
    //   118: goto -> 125
    //   121: invokestatic a : (Ljava/lang/Exception;)Ljava/lang/Exception;
    //   124: athrow
    //   125: aload #5
    //   127: ifnull -> 37
    //   130: goto -> 137
    //   133: invokestatic a : (Ljava/lang/Exception;)Ljava/lang/Exception;
    //   136: athrow
    //   137: aload_0
    //   138: getfield Zq : Lcom/fasterxml/Zor/Zyd;
    //   141: astore #10
    //   143: aload #8
    //   145: invokeinterface getValue : ()Ljava/lang/Object;
    //   150: astore #11
    //   152: aload #11
    //   154: ifnonnull -> 194
    //   157: aload_0
    //   158: getfield Zf : Z
    //   161: ifeq -> 183
    //   164: goto -> 171
    //   167: invokestatic a : (Ljava/lang/Exception;)Ljava/lang/Exception;
    //   170: athrow
    //   171: aload #5
    //   173: ifnull -> 37
    //   176: goto -> 183
    //   179: invokestatic a : (Ljava/lang/Exception;)Ljava/lang/Exception;
    //   182: athrow
    //   183: aload_3
    //   184: invokevirtual ZJ : ()Lcom/fasterxml/Zor/Zyd;
    //   187: astore #12
    //   189: aload #5
    //   191: ifnull -> 283
    //   194: aload_0
    //   195: getfield ZD : Lcom/fasterxml/Zor/Zyd;
    //   198: astore #12
    //   200: aload #12
    //   202: ifnonnull -> 214
    //   205: aload_0
    //   206: aload_3
    //   207: aload #11
    //   209: invokespecial ZM : (Lcom/fasterxml/Zor/Zyi;Ljava/lang/Object;)Lcom/fasterxml/Zor/Zyd;
    //   212: astore #12
    //   214: iload #6
    //   216: ifeq -> 249
    //   219: aload #12
    //   221: aload_3
    //   222: aload #11
    //   224: invokevirtual Zt : (Lcom/fasterxml/Zor/Zyi;Ljava/lang/Object;)Z
    //   227: ifeq -> 283
    //   230: goto -> 237
    //   233: invokestatic a : (Ljava/lang/Exception;)Ljava/lang/Exception;
    //   236: athrow
    //   237: aload #5
    //   239: ifnull -> 37
    //   242: goto -> 249
    //   245: invokestatic a : (Ljava/lang/Exception;)Ljava/lang/Exception;
    //   248: athrow
    //   249: aload #4
    //   251: ifnull -> 283
    //   254: aload #4
    //   256: aload #11
    //   258: invokevirtual equals : (Ljava/lang/Object;)Z
    //   261: ifeq -> 283
    //   264: goto -> 271
    //   267: invokestatic a : (Ljava/lang/Exception;)Ljava/lang/Exception;
    //   270: athrow
    //   271: aload #5
    //   273: ifnull -> 37
    //   276: goto -> 283
    //   279: invokestatic a : (Ljava/lang/Exception;)Ljava/lang/Exception;
    //   282: athrow
    //   283: aload #10
    //   285: aload #9
    //   287: aload_2
    //   288: aload_3
    //   289: invokevirtual serialize : (Ljava/lang/Object;Lcom/fasterxml/Zb/Zf;Lcom/fasterxml/Zor/Zyi;)V
    //   292: aload #12
    //   294: aload #11
    //   296: aload_2
    //   297: aload_3
    //   298: aload_0
    //   299: getfield Zy : Lcom/fasterxml/Zp/Za;
    //   302: invokevirtual Zo : (Ljava/lang/Object;Lcom/fasterxml/Zb/Zf;Lcom/fasterxml/Zor/Zyi;Lcom/fasterxml/Zp/Za;)V
    //   305: goto -> 323
    //   308: astore #13
    //   310: aload_0
    //   311: aload_3
    //   312: aload #13
    //   314: aload_1
    //   315: aload #9
    //   317: invokestatic valueOf : (Ljava/lang/Object;)Ljava/lang/String;
    //   320: invokevirtual ZO : (Lcom/fasterxml/Zor/Zyi;Ljava/lang/Throwable;Ljava/lang/Object;Ljava/lang/String;)V
    //   323: aload #5
    //   325: ifnull -> 37
    //   328: return
    // Exception table:
    //   from	to	target	type
    //   5	17	17	java/lang/Exception
    //   87	99	102	java/lang/Exception
    //   92	118	121	java/lang/Exception
    //   106	130	133	java/lang/Exception
    //   152	164	167	java/lang/Exception
    //   157	176	179	java/lang/Exception
    //   214	230	233	java/lang/Exception
    //   219	242	245	java/lang/Exception
    //   249	264	267	java/lang/Exception
    //   254	276	279	java/lang/Exception
    //   292	305	308	java/lang/Exception
  }
  
  public void Zt(Zyi paramZyi, Zf paramZf, Object paramObject1, Map<?, ?> paramMap, Zh paramZh, Object paramObject2) throws IOException {
    // Byte code:
    //   0: invokestatic ZG : ()Ljava/lang/String;
    //   3: new com/fasterxml/Zyp
    //   6: dup
    //   7: aload_0
    //   8: getfield Zy : Lcom/fasterxml/Zp/Za;
    //   11: aload_0
    //   12: getfield Zw : Lcom/fasterxml/Zor/Zo;
    //   15: invokespecial <init> : (Lcom/fasterxml/Zp/Za;Lcom/fasterxml/Zor/Zo;)V
    //   18: astore #8
    //   20: astore #7
    //   22: getstatic com/fasterxml/Zz7.ZT : Ljava/lang/Object;
    //   25: aload #6
    //   27: if_acmpne -> 38
    //   30: iconst_1
    //   31: goto -> 39
    //   34: invokestatic a : (Ljava/lang/Exception;)Ljava/lang/Exception;
    //   37: athrow
    //   38: iconst_0
    //   39: istore #9
    //   41: aload #4
    //   43: invokeinterface entrySet : ()Ljava/util/Set;
    //   48: invokeinterface iterator : ()Ljava/util/Iterator;
    //   53: astore #10
    //   55: aload #10
    //   57: invokeinterface hasNext : ()Z
    //   62: ifeq -> 343
    //   65: aload #10
    //   67: invokeinterface next : ()Ljava/lang/Object;
    //   72: checkcast java/util/Map$Entry
    //   75: astore #11
    //   77: aload #11
    //   79: invokeinterface getKey : ()Ljava/lang/Object;
    //   84: astore #12
    //   86: aload_0
    //   87: getfield Zz : Lcom/fasterxml/Zm/Zk;
    //   90: ifnull -> 124
    //   93: aload_0
    //   94: getfield Zz : Lcom/fasterxml/Zm/Zk;
    //   97: aload #12
    //   99: invokevirtual Zv : (Ljava/lang/Object;)Z
    //   102: ifeq -> 124
    //   105: goto -> 112
    //   108: invokestatic a : (Ljava/lang/Exception;)Ljava/lang/Exception;
    //   111: athrow
    //   112: aload #7
    //   114: ifnull -> 55
    //   117: goto -> 124
    //   120: invokestatic a : (Ljava/lang/Exception;)Ljava/lang/Exception;
    //   123: athrow
    //   124: aload #12
    //   126: ifnonnull -> 148
    //   129: aload_1
    //   130: aload_0
    //   131: getfield ZG : Lcom/fasterxml/Zor/Zk;
    //   134: aload_0
    //   135: getfield Zw : Lcom/fasterxml/Zor/Zo;
    //   138: invokevirtual ZB : (Lcom/fasterxml/Zor/Zk;Lcom/fasterxml/Zor/Zo;)Lcom/fasterxml/Zor/Zyd;
    //   141: astore #13
    //   143: aload #7
    //   145: ifnull -> 154
    //   148: aload_0
    //   149: getfield Zq : Lcom/fasterxml/Zor/Zyd;
    //   152: astore #13
    //   154: aload #11
    //   156: invokeinterface getValue : ()Ljava/lang/Object;
    //   161: astore #14
    //   163: aload #14
    //   165: ifnonnull -> 205
    //   168: aload_0
    //   169: getfield Zf : Z
    //   172: ifeq -> 194
    //   175: goto -> 182
    //   178: invokestatic a : (Ljava/lang/Exception;)Ljava/lang/Exception;
    //   181: athrow
    //   182: aload #7
    //   184: ifnull -> 55
    //   187: goto -> 194
    //   190: invokestatic a : (Ljava/lang/Exception;)Ljava/lang/Exception;
    //   193: athrow
    //   194: aload_1
    //   195: invokevirtual ZJ : ()Lcom/fasterxml/Zor/Zyd;
    //   198: astore #15
    //   200: aload #7
    //   202: ifnull -> 294
    //   205: aload_0
    //   206: getfield ZD : Lcom/fasterxml/Zor/Zyd;
    //   209: astore #15
    //   211: aload #15
    //   213: ifnonnull -> 225
    //   216: aload_0
    //   217: aload_1
    //   218: aload #14
    //   220: invokespecial ZM : (Lcom/fasterxml/Zor/Zyi;Ljava/lang/Object;)Lcom/fasterxml/Zor/Zyd;
    //   223: astore #15
    //   225: iload #9
    //   227: ifeq -> 260
    //   230: aload #15
    //   232: aload_1
    //   233: aload #14
    //   235: invokevirtual Zt : (Lcom/fasterxml/Zor/Zyi;Ljava/lang/Object;)Z
    //   238: ifeq -> 294
    //   241: goto -> 248
    //   244: invokestatic a : (Ljava/lang/Exception;)Ljava/lang/Exception;
    //   247: athrow
    //   248: aload #7
    //   250: ifnull -> 55
    //   253: goto -> 260
    //   256: invokestatic a : (Ljava/lang/Exception;)Ljava/lang/Exception;
    //   259: athrow
    //   260: aload #6
    //   262: ifnull -> 294
    //   265: aload #6
    //   267: aload #14
    //   269: invokevirtual equals : (Ljava/lang/Object;)Z
    //   272: ifeq -> 294
    //   275: goto -> 282
    //   278: invokestatic a : (Ljava/lang/Exception;)Ljava/lang/Exception;
    //   281: athrow
    //   282: aload #7
    //   284: ifnull -> 55
    //   287: goto -> 294
    //   290: invokestatic a : (Ljava/lang/Exception;)Ljava/lang/Exception;
    //   293: athrow
    //   294: aload #8
    //   296: aload #12
    //   298: aload #14
    //   300: aload #13
    //   302: aload #15
    //   304: invokevirtual ZF : (Ljava/lang/Object;Ljava/lang/Object;Lcom/fasterxml/Zor/Zyd;Lcom/fasterxml/Zor/Zyd;)V
    //   307: aload #5
    //   309: aload_3
    //   310: aload_2
    //   311: aload_1
    //   312: aload #8
    //   314: invokeinterface ZX : (Ljava/lang/Object;Lcom/fasterxml/Zb/Zf;Lcom/fasterxml/Zor/Zyi;Lcom/fasterxml/Zk/Zb;)V
    //   319: goto -> 338
    //   322: astore #16
    //   324: aload_0
    //   325: aload_1
    //   326: aload #16
    //   328: aload #4
    //   330: aload #12
    //   332: invokestatic valueOf : (Ljava/lang/Object;)Ljava/lang/String;
    //   335: invokevirtual ZO : (Lcom/fasterxml/Zor/Zyi;Ljava/lang/Throwable;Ljava/lang/Object;Ljava/lang/String;)V
    //   338: aload #7
    //   340: ifnull -> 55
    //   343: return
    // Exception table:
    //   from	to	target	type
    //   22	34	34	java/lang/Exception
    //   86	105	108	java/lang/Exception
    //   93	117	120	java/lang/Exception
    //   163	175	178	java/lang/Exception
    //   168	187	190	java/lang/Exception
    //   225	241	244	java/lang/Exception
    //   230	253	256	java/lang/Exception
    //   260	275	278	java/lang/Exception
    //   265	287	290	java/lang/Exception
    //   307	319	322	java/lang/Exception
  }
  
  protected final Zyd<Object> Zv(Zj paramZj, Class<?> paramClass, Zyi paramZyi) throws Zy_ {
    Zm zm = paramZj.Zd(paramClass, paramZyi, this.Zw);
    try {
      if (paramZj != zm.Za)
        this.ZW = zm.Za; 
    } catch (Zy_ zy_) {
      throw a(null);
    } 
    return zm.Zm;
  }
  
  protected final Zyd<Object> Zm(Zj paramZj, Zk paramZk, Zyi paramZyi) throws Zy_ {
    Zm zm = paramZj.ZN(paramZk, paramZyi, this.Zw);
    try {
      if (paramZj != zm.Za)
        this.ZW = zm.Za; 
    } catch (Zy_ zy_) {
      throw a(null);
    } 
    return zm.Zm;
  }
  
  protected Map<?, ?> ZL(Map<?, ?> paramMap, Zf paramZf, Zyi paramZyi) throws IOException {
    // Byte code:
    //   0: invokestatic ZG : ()Ljava/lang/String;
    //   3: astore #4
    //   5: aload_1
    //   6: instanceof java/util/SortedMap
    //   9: ifeq -> 18
    //   12: aload_1
    //   13: areturn
    //   14: invokestatic a : (Ljava/lang/Exception;)Ljava/lang/Exception;
    //   17: athrow
    //   18: aload_0
    //   19: aload_1
    //   20: invokevirtual Zw : (Ljava/util/Map;)Z
    //   23: ifeq -> 132
    //   26: new java/util/TreeMap
    //   29: dup
    //   30: invokespecial <init> : ()V
    //   33: astore #5
    //   35: aload_1
    //   36: invokeinterface entrySet : ()Ljava/util/Set;
    //   41: invokeinterface iterator : ()Ljava/util/Iterator;
    //   46: astore #6
    //   48: aload #6
    //   50: invokeinterface hasNext : ()Z
    //   55: ifeq -> 129
    //   58: aload #6
    //   60: invokeinterface next : ()Ljava/lang/Object;
    //   65: checkcast java/util/Map$Entry
    //   68: astore #7
    //   70: aload #7
    //   72: invokeinterface getKey : ()Ljava/lang/Object;
    //   77: astore #8
    //   79: aload #8
    //   81: ifnonnull -> 109
    //   84: aload_0
    //   85: aload_2
    //   86: aload_3
    //   87: aload #7
    //   89: invokeinterface getValue : ()Ljava/lang/Object;
    //   94: invokevirtual ZP : (Lcom/fasterxml/Zb/Zf;Lcom/fasterxml/Zor/Zyi;Ljava/lang/Object;)V
    //   97: aload #4
    //   99: ifnull -> 48
    //   102: goto -> 109
    //   105: invokestatic a : (Ljava/lang/Exception;)Ljava/lang/Exception;
    //   108: athrow
    //   109: aload #5
    //   111: aload #8
    //   113: aload #7
    //   115: invokeinterface getValue : ()Ljava/lang/Object;
    //   120: invokevirtual put : (Ljava/lang/Object;Ljava/lang/Object;)Ljava/lang/Object;
    //   123: pop
    //   124: aload #4
    //   126: ifnull -> 48
    //   129: aload #5
    //   131: areturn
    //   132: new java/util/TreeMap
    //   135: dup
    //   136: aload_1
    //   137: invokespecial <init> : (Ljava/util/Map;)V
    //   140: areturn
    // Exception table:
    //   from	to	target	type
    //   5	14	14	java/io/IOException
    //   79	102	105	java/io/IOException
  }
  
  protected boolean Zw(Map<?, ?> paramMap) {
    return (paramMap instanceof java.util.HashMap && paramMap.containsKey(null));
  }
  
  protected void ZP(Zf paramZf, Zyi paramZyi, Object paramObject) throws IOException {
    // Byte code:
    //   0: invokestatic ZG : ()Ljava/lang/String;
    //   3: aload_2
    //   4: aload_0
    //   5: getfield ZG : Lcom/fasterxml/Zor/Zk;
    //   8: aload_0
    //   9: getfield Zw : Lcom/fasterxml/Zor/Zo;
    //   12: invokevirtual ZB : (Lcom/fasterxml/Zor/Zk;Lcom/fasterxml/Zor/Zo;)Lcom/fasterxml/Zor/Zyd;
    //   15: astore #5
    //   17: astore #4
    //   19: aload_3
    //   20: ifnonnull -> 53
    //   23: aload_0
    //   24: getfield Zf : Z
    //   27: ifeq -> 42
    //   30: goto -> 37
    //   33: invokestatic a : (Ljava/lang/Exception;)Ljava/lang/Exception;
    //   36: athrow
    //   37: return
    //   38: invokestatic a : (Ljava/lang/Exception;)Ljava/lang/Exception;
    //   41: athrow
    //   42: aload_2
    //   43: invokevirtual ZJ : ()Lcom/fasterxml/Zor/Zyd;
    //   46: astore #6
    //   48: aload #4
    //   50: ifnull -> 134
    //   53: aload_0
    //   54: getfield ZD : Lcom/fasterxml/Zor/Zyd;
    //   57: astore #6
    //   59: aload #6
    //   61: ifnonnull -> 72
    //   64: aload_0
    //   65: aload_2
    //   66: aload_3
    //   67: invokespecial ZM : (Lcom/fasterxml/Zor/Zyi;Ljava/lang/Object;)Lcom/fasterxml/Zor/Zyd;
    //   70: astore #6
    //   72: aload_0
    //   73: getfield Zn : Ljava/lang/Object;
    //   76: getstatic com/fasterxml/Zz7.ZT : Ljava/lang/Object;
    //   79: if_acmpne -> 104
    //   82: aload #6
    //   84: aload_2
    //   85: aload_3
    //   86: invokevirtual Zt : (Lcom/fasterxml/Zor/Zyi;Ljava/lang/Object;)Z
    //   89: ifeq -> 134
    //   92: goto -> 99
    //   95: invokestatic a : (Ljava/lang/Exception;)Ljava/lang/Exception;
    //   98: athrow
    //   99: return
    //   100: invokestatic a : (Ljava/lang/Exception;)Ljava/lang/Exception;
    //   103: athrow
    //   104: aload_0
    //   105: getfield Zn : Ljava/lang/Object;
    //   108: ifnull -> 134
    //   111: aload_0
    //   112: getfield Zn : Ljava/lang/Object;
    //   115: aload_3
    //   116: invokevirtual equals : (Ljava/lang/Object;)Z
    //   119: ifeq -> 134
    //   122: goto -> 129
    //   125: invokestatic a : (Ljava/lang/Exception;)Ljava/lang/Exception;
    //   128: athrow
    //   129: return
    //   130: invokestatic a : (Ljava/lang/Exception;)Ljava/lang/Exception;
    //   133: athrow
    //   134: aload #5
    //   136: aconst_null
    //   137: aload_1
    //   138: aload_2
    //   139: invokevirtual serialize : (Ljava/lang/Object;Lcom/fasterxml/Zb/Zf;Lcom/fasterxml/Zor/Zyi;)V
    //   142: aload #6
    //   144: aload_3
    //   145: aload_1
    //   146: aload_2
    //   147: invokevirtual serialize : (Ljava/lang/Object;Lcom/fasterxml/Zb/Zf;Lcom/fasterxml/Zor/Zyi;)V
    //   150: goto -> 165
    //   153: astore #7
    //   155: aload_0
    //   156: aload_2
    //   157: aload #7
    //   159: aload_3
    //   160: ldc ''
    //   162: invokevirtual ZO : (Lcom/fasterxml/Zor/Zyi;Ljava/lang/Throwable;Ljava/lang/Object;Ljava/lang/String;)V
    //   165: return
    // Exception table:
    //   from	to	target	type
    //   19	30	33	java/lang/Exception
    //   23	38	38	java/lang/Exception
    //   72	92	95	java/lang/Exception
    //   82	100	100	java/lang/Exception
    //   104	122	125	java/lang/Exception
    //   111	130	130	java/lang/Exception
    //   134	150	153	java/lang/Exception
  }
  
  private final Zyd<Object> ZM(Zyi paramZyi, Object paramObject) throws Zy_ {
    Class<?> clazz = paramObject.getClass();
    Zyd<Object> zyd = this.ZW.ZO(clazz);
    try {
      if (zyd != null)
        return zyd; 
    } catch (Zy_ zy_) {
      throw a(null);
    } 
    try {
      if (this.Za.Zk())
        return Zm(this.ZW, paramZyi.ZX(this.Za, clazz), paramZyi); 
    } catch (Zy_ zy_) {
      throw a(null);
    } 
    return Zv(this.ZW, clazz, paramZyi);
  }
  
  static {
    // Byte code:
    //   0: iconst_4
    //   1: anewarray java/lang/String
    //   4: astore #5
    //   6: iconst_0
    //   7: istore_3
    //   8: ldc '%mo4H\\fh\\f}H'
    //   10: dup
    //   11: astore_2
    //   12: invokevirtual length : ()I
    //   15: istore #4
    //   17: bipush #20
    //   19: istore_1
    //   20: iconst_m1
    //   21: istore_0
    //   22: bipush #60
    //   24: iinc #0, 1
    //   27: aload_2
    //   28: iload_0
    //   29: dup
    //   30: iload_1
    //   31: iadd
    //   32: invokevirtual substring : (II)Ljava/lang/String;
    //   35: iconst_m1
    //   36: goto -> 141
    //   39: aload #5
    //   41: swap
    //   42: iload_3
    //   43: iinc #3, 1
    //   46: swap
    //   47: aastore
    //   48: iload_0
    //   49: iload_1
    //   50: iadd
    //   51: dup
    //   52: istore_0
    //   53: iload #4
    //   55: if_icmpge -> 67
    //   58: aload_2
    //   59: iload_0
    //   60: invokevirtual charAt : (I)C
    //   63: istore_1
    //   64: goto -> 22
    //   67: ldc '{z6k]9VgFQl:h6=A$e d'
    //   69: dup
    //   70: astore_2
    //   71: invokevirtual length : ()I
    //   74: istore #4
    //   76: bipush #12
    //   78: istore_1
    //   79: iconst_m1
    //   80: istore_0
    //   81: bipush #124
    //   83: iinc #0, 1
    //   86: aload_2
    //   87: iload_0
    //   88: dup
    //   89: iload_1
    //   90: iadd
    //   91: invokevirtual substring : (II)Ljava/lang/String;
    //   94: iconst_0
    //   95: goto -> 141
    //   98: aload #5
    //   100: swap
    //   101: iload_3
    //   102: iinc #3, 1
    //   105: swap
    //   106: aastore
    //   107: iload_0
    //   108: iload_1
    //   109: iadd
    //   110: dup
    //   111: istore_0
    //   112: iload #4
    //   114: if_icmpge -> 126
    //   117: aload_2
    //   118: iload_0
    //   119: invokevirtual charAt : (I)C
    //   122: istore_1
    //   123: goto -> 81
    //   126: aload #5
    //   128: putstatic com/fasterxml/Zz7.d : [Ljava/lang/String;
    //   131: iconst_4
    //   132: anewarray java/lang/String
    //   135: putstatic com/fasterxml/Zz7.e : [Ljava/lang/String;
    //   138: goto -> 300
    //   141: dup_x2
    //   142: pop
    //   143: invokevirtual toCharArray : ()[C
    //   146: dup_x1
    //   147: arraylength
    //   148: dup_x2
    //   149: pop
    //   150: iconst_0
    //   151: istore #6
    //   153: dup2_x1
    //   154: pop2
    //   155: dup_x2
    //   156: iconst_1
    //   157: if_icmpgt -> 260
    //   160: dup2
    //   161: swap
    //   162: iload #6
    //   164: dup2_x1
    //   165: caload
    //   166: swap
    //   167: iload #6
    //   169: bipush #7
    //   171: irem
    //   172: tableswitch default -> 242, 0 -> 212, 1 -> 217, 2 -> 222, 3 -> 227, 4 -> 232, 5 -> 237
    //   212: bipush #67
    //   214: goto -> 244
    //   217: bipush #38
    //   219: goto -> 244
    //   222: bipush #47
    //   224: goto -> 244
    //   227: bipush #63
    //   229: goto -> 244
    //   232: bipush #37
    //   234: goto -> 244
    //   237: bipush #123
    //   239: goto -> 244
    //   242: bipush #112
    //   244: ixor
    //   245: ixor
    //   246: i2c
    //   247: castore
    //   248: iinc #6, 1
    //   251: dup
    //   252: ifne -> 260
    //   255: dup2
    //   256: dup_x1
    //   257: goto -> 164
    //   260: dup2_x1
    //   261: pop2
    //   262: dup_x2
    //   263: iload #6
    //   265: if_icmpgt -> 160
    //   268: pop
    //   269: new java/lang/String
    //   272: dup_x1
    //   273: swap
    //   274: invokespecial <init> : ([C)V
    //   277: invokevirtual intern : ()Ljava/lang/String;
    //   280: swap
    //   281: pop
    //   282: swap
    //   283: tableswitch default -> 39, 0 -> 98
    //   300: invokestatic Zs : ()Lcom/fasterxml/Zor/Zk;
    //   303: putstatic com/fasterxml/Zz7.Zb : Lcom/fasterxml/Zor/Zk;
    //   306: getstatic com/fasterxml/Zqg.NON_EMPTY : Lcom/fasterxml/Zqg;
    //   309: putstatic com/fasterxml/Zz7.ZT : Ljava/lang/Object;
    //   312: return
  }
  
  private static Exception a(Exception paramException) {
    return paramException;
  }
  
  private static String b(int paramInt1, int paramInt2) {
    int i = (paramInt1 ^ 0x3FFE) & 0xFFFF;
    if (e[i] == null) {
      char[] arrayOfChar = d[i].toCharArray();
      switch (arrayOfChar[0] & 0xFF) {
        case 0:
        
        case 1:
        
        case 2:
        
        case 3:
        
        case 4:
        
        case 5:
        
        case 6:
        
        case 7:
        
        case 8:
        
        case 9:
        
        case 10:
        
        case 11:
        
        case 12:
        
        case 13:
        
        case 14:
        
        case 15:
        
        case 16:
        
        case 17:
        
        case 18:
        
        case 19:
        
        case 20:
        
        case 21:
        
        case 22:
        
        case 23:
        
        case 24:
        
        case 25:
        
        case 26:
        
        case 27:
        
        case 28:
        
        case 29:
        
        case 30:
        
        case 31:
        
        case 32:
        
        case 33:
        
        case 34:
        
        case 35:
        
        case 36:
        
        case 37:
        
        case 38:
        
        case 39:
        
        case 40:
        
        case 41:
        
        case 42:
        
        case 43:
        
        case 44:
        
        case 45:
        
        case 46:
        
        case 47:
        
        case 48:
        
        case 49:
        
        case 50:
        
        case 51:
        
        case 52:
        
        case 53:
        
        case 54:
        
        case 55:
        
        case 56:
        
        case 57:
        
        case 58:
        
        case 59:
        
        case 60:
        
        case 61:
        
        case 62:
        
        case 63:
        
        case 64:
        
        case 65:
        
        case 66:
        
        case 67:
        
        case 68:
        
        case 69:
        
        case 70:
        
        case 71:
        
        case 72:
        
        case 73:
        
        case 74:
        
        case 75:
        
        case 76:
        
        case 77:
        
        case 78:
        
        case 79:
        
        case 80:
        
        case 81:
        
        case 82:
        
        case 83:
        
        case 84:
        
        case 85:
        
        case 86:
        
        case 87:
        
        case 88:
        
        case 89:
        
        case 90:
        
        case 91:
        
        case 92:
        
        case 93:
        
        case 94:
        
        case 95:
        
        case 96:
        
        case 97:
        
        case 98:
        
        case 99:
        
        case 100:
        
        case 101:
        
        case 102:
        
        case 103:
        
        case 104:
        
        case 105:
        
        case 106:
        
        case 107:
        
        case 108:
        
        case 109:
        
        case 110:
        
        case 111:
        
        case 112:
        
        case 113:
        
        case 114:
        
        case 115:
        
        case 116:
        
        case 117:
        
        case 118:
        
        case 119:
        
        case 120:
        
        case 121:
        
        case 122:
        
        case 123:
        
        case 124:
        
        case 125:
        
        case 126:
        
        case 127:
        
        case 128:
        
        case 129:
        
        case 130:
        
        case 131:
        
        case 132:
        
        case 133:
        
        case 134:
        
        case 135:
        
        case 136:
        
        case 137:
        
        case 138:
        
        case 139:
        
        case 140:
        
        case 141:
        
        case 142:
        
        case 143:
        
        case 144:
        
        case 145:
        
        case 146:
        
        case 147:
        
        case 148:
        
        case 149:
        
        case 150:
        
        case 151:
        
        case 152:
        
        case 153:
        
        case 154:
        
        case 155:
        
        case 156:
        
        case 157:
        
        case 158:
        
        case 159:
        
        case 160:
        
        case 161:
        
        case 162:
        
        case 163:
        
        case 164:
        
        case 165:
        
        case 166:
        
        case 167:
        
        case 168:
        
        case 169:
        
        case 170:
        
        case 171:
        
        case 172:
        
        case 173:
        
        case 174:
        
        case 175:
        
        case 176:
        
        case 177:
        
        case 178:
        
        case 179:
        
        case 180:
        
        case 181:
        
        case 182:
        
        case 183:
        
        case 184:
        
        case 185:
        
        case 186:
        
        case 187:
        
        case 188:
        
        case 189:
        
        case 190:
        
        case 191:
        
        case 192:
        
        case 193:
        
        case 194:
        
        case 195:
        
        case 196:
        
        case 197:
        
        case 198:
        
        case 199:
        
        case 200:
        
        case 201:
        
        case 202:
        
        case 203:
        
        case 204:
        
        case 205:
        
        case 206:
        
        case 207:
        
        case 208:
        
        case 209:
        
        case 210:
        
        case 211:
        
        case 212:
        
        case 213:
        
        case 214:
        
        case 215:
        
        case 216:
        
        case 217:
        
        case 218:
        
        case 219:
        
        case 220:
        
        case 221:
        
        case 222:
        
        case 223:
        
        case 224:
        
        case 225:
        
        case 226:
        
        case 227:
        
        case 228:
        
        case 229:
        
        case 230:
        
        case 231:
        
        case 232:
        
        case 233:
        
        case 234:
        
        case 235:
        
        case 236:
        
        case 237:
        
        case 238:
        
        case 239:
        
        case 240:
        
        case 241:
        
        case 242:
        
        case 243:
        
        case 244:
        
        case 245:
        
        case 246:
        
        case 247:
        
        case 248:
        
        case 249:
        
        case 250:
        
        case 251:
        
        case 252:
        
        case 253:
        
        case 254:
        
        default:
          break;
      } 
      char c = '';
      int j = (paramInt2 & 0xFF) - c;
      if (j < 0)
        j += 256; 
      int k = ((paramInt2 & 0xFFFF) >>> 8) - c;
      if (k < 0)
        k += 256; 
      for (byte b = 0; b < arrayOfChar.length; b++) {
        int m = b % 2;
        if (m == 0) {
          arrayOfChar[b] = (char)(arrayOfChar[b] ^ j);
          j = ((j >>> 3 | j << 5) ^ arrayOfChar[b]) & 0xFF;
        } else {
          arrayOfChar[b] = (char)(arrayOfChar[b] ^ k);
          k = ((k >>> 3 | k << 5) ^ arrayOfChar[b]) & 0xFF;
        } 
      } 
      e[i] = (new String(arrayOfChar)).intern();
    } 
    return e[i];
  }
}


/* Location:              C:\Program Files\BurpSuitePro\burpsuite_pro.jar!\com\fasterxml\Zz7.class
 * Java compiler version: 8 (52.0)
 * JD-Core Version:       1.1.3
 */