package com.fasterxml.Zo;

import com.fasterxml.Zb.Zg;
import com.fasterxml.Zb.Zl;
import com.fasterxml.Ze.Zo8;
import com.fasterxml.Ze.Zol;
import com.fasterxml.Ze.Zz;
import com.fasterxml.Zj.Zx;
import com.fasterxml.Zm.Zee;
import com.fasterxml.Zm.Zl;
import com.fasterxml.Zor.Zk;
import com.fasterxml.Zor.Zyc;
import com.fasterxml.Zor.Zyg;
import com.fasterxml.Zor.Zyo;
import com.fasterxml.Zor.Zyp;
import com.fasterxml.Zor.Zyv;
import com.fasterxml.Zoz.Ziq;
import java.io.IOException;
import java.util.Map;
import java.util.Set;

public class Zd extends Zf {
  private static final long serialVersionUID = 1L;
  
  protected final Ziq Zx;
  
  protected final Zk Zw;
  
  private static final String[] g;
  
  private static final String[] h;
  
  public Zd(Zh paramZh, Zyv paramZyv, Zk paramZk, Zo8 paramZo8, Map<String, Zv> paramMap, Set<String> paramSet1, boolean paramBoolean1, Set<String> paramSet2, boolean paramBoolean2) {
    super(paramZh, paramZyv, paramZo8, paramMap, paramSet1, paramBoolean1, paramSet2, paramBoolean2);
    this.Zw = paramZk;
    this.Zx = paramZh.Zn();
    if (this.ZZ != null)
      throw new IllegalArgumentException(d(-7126, 30656) + paramZyv.Zf() + ")"); 
  }
  
  protected Zd(Zd paramZd, boolean paramBoolean) {
    super(paramZd, paramBoolean);
    this.Zx = paramZd.Zx;
    this.Zw = paramZd.Zw;
  }
  
  protected Zd(Zd paramZd, Zee paramZee) {
    super(paramZd, paramZee);
    this.Zx = paramZd.Zx;
    this.Zw = paramZd.Zw;
  }
  
  public Zd(Zd paramZd, Zz paramZz) {
    super(paramZd, paramZz);
    this.Zx = paramZd.Zx;
    this.Zw = paramZd.Zw;
  }
  
  public Zd(Zd paramZd, Set<String> paramSet1, Set<String> paramSet2) {
    super(paramZd, paramSet1, paramSet2);
    this.Zx = paramZd.Zx;
    this.Zw = paramZd.Zw;
  }
  
  public Zd(Zd paramZd, Zo8 paramZo8) {
    super(paramZd, paramZo8);
    this.Zx = paramZd.Zx;
    this.Zw = paramZd.Zw;
  }
  
  public Zyo<Object> Zv(Zee paramZee) {
    return (Zyo<Object>)new Zd(this, paramZee);
  }
  
  public Zf Zw(Zz paramZz) {
    return new Zd(this, paramZz);
  }
  
  public Zf Zv(Set<String> paramSet1, Set<String> paramSet2) {
    return new Zd(this, paramSet1, paramSet2);
  }
  
  public Zf ZI(boolean paramBoolean) {
    return new Zd(this, paramBoolean);
  }
  
  public Zf ZG(Zo8 paramZo8) {
    return new Zd(this, paramZo8);
  }
  
  protected Zf Zv() {
    Zv[] arrayOfZv = this.ZX.ZK();
    return (Zf)new Zol(this, this.Zw, arrayOfZv, this.Zx);
  }
  
  public Boolean Zu(Zyc paramZyc) {
    return Boolean.FALSE;
  }
  
  protected Object Zi(Zyg paramZyg, Object paramObject) throws IOException {
    try {
      if (null == this.Zx)
        return paramObject; 
    } catch (Exception exception) {
      throw a(null);
    } 
    try {
      return this.Zx.ZP().invoke(paramObject, (Object[])null);
    } catch (Exception exception) {
      return ZR(exception, paramZyg);
    } 
  }
  
  public Object deserialize(Zg paramZg, Zyg paramZyg) throws IOException {
    if (paramZg.Zp()) {
      Zl zl = paramZg.ZV();
      try {
        if (this.Zn)
          return Zi(paramZyg, ZF(paramZg, paramZyg, zl)); 
      } catch (IOException iOException) {
        throw a(null);
      } 
      return Zi(paramZyg, ZJ(paramZg, paramZyg));
    } 
    try {
      switch (paramZg.Zy()) {
        case 6:
          return Zi(paramZyg, ZE(paramZg, paramZyg));
        case 7:
          return Zi(paramZyg, Zj(paramZg, paramZyg));
        case 8:
          return Zi(paramZyg, ZK(paramZg, paramZyg));
        case 12:
          return paramZg.ZO();
        case 9:
        case 10:
          return Zi(paramZyg, Zi(paramZg, paramZyg));
        case 3:
          return ZF(paramZg, paramZyg);
        case 2:
        case 5:
          return Zi(paramZyg, ZJ(paramZg, paramZyg));
      } 
    } catch (IOException iOException) {
      throw a(null);
    } 
    return paramZyg.ZE(Zq(paramZyg), paramZg);
  }
  
  public Object ZI(Zg paramZg, Zyg paramZyg, Object paramObject) throws IOException {
    Zk zk = this.Zw;
    Class<?> clazz1 = ZX();
    Class<?> clazz2 = paramObject.getClass();
    try {
      if (clazz1.isAssignableFrom(clazz2))
        return paramZyg.Zm(zk, String.format(d(-7127, 4053), new Object[] { zk, clazz1.getName() })); 
    } catch (IOException iOException) {
      throw a(null);
    } 
    return paramZyg.Zm(zk, String.format(d(-7128, 17815), new Object[] { zk, clazz2.getName() }));
  }
  
  private final Object ZF(Zg paramZg, Zyg paramZyg, Zl paramZl) throws IOException {
    // Byte code:
    //   0: invokestatic ZP : ()Ljava/lang/String;
    //   3: aload_0
    //   4: getfield Zb : Lcom/fasterxml/Zo/Zzp;
    //   7: aload_2
    //   8: invokevirtual Zy : (Lcom/fasterxml/Zor/Zyg;)Ljava/lang/Object;
    //   11: astore #5
    //   13: astore #4
    //   15: aload_1
    //   16: invokevirtual Zh : ()Lcom/fasterxml/Zb/Zl;
    //   19: getstatic com/fasterxml/Zb/Zl.FIELD_NAME : Lcom/fasterxml/Zb/Zl;
    //   22: if_acmpne -> 112
    //   25: aload_1
    //   26: invokevirtual ZS : ()Ljava/lang/String;
    //   29: astore #6
    //   31: aload_1
    //   32: invokevirtual ZV : ()Lcom/fasterxml/Zb/Zl;
    //   35: pop
    //   36: aload_0
    //   37: getfield ZX : Lcom/fasterxml/Ze/Zo8;
    //   40: aload #6
    //   42: invokevirtual ZI : (Ljava/lang/String;)Lcom/fasterxml/Zo/Zv;
    //   45: astore #7
    //   47: aload #7
    //   49: ifnull -> 85
    //   52: aload #7
    //   54: aload_1
    //   55: aload_2
    //   56: aload #5
    //   58: invokevirtual ZR : (Lcom/fasterxml/Zb/Zg;Lcom/fasterxml/Zor/Zyg;Ljava/lang/Object;)Ljava/lang/Object;
    //   61: astore #5
    //   63: goto -> 102
    //   66: astore #8
    //   68: aload_0
    //   69: aload #8
    //   71: aload #5
    //   73: aload #6
    //   75: aload_2
    //   76: invokevirtual Zd : (Ljava/lang/Throwable;Ljava/lang/Object;Ljava/lang/String;Lcom/fasterxml/Zor/Zyg;)Ljava/lang/Object;
    //   79: pop
    //   80: aload #4
    //   82: ifnull -> 102
    //   85: aload_0
    //   86: aload_1
    //   87: aload_2
    //   88: aload #5
    //   90: aload #6
    //   92: invokevirtual ZN : (Lcom/fasterxml/Zb/Zg;Lcom/fasterxml/Zor/Zyg;Ljava/lang/Object;Ljava/lang/String;)V
    //   95: goto -> 102
    //   98: invokestatic a : (Ljava/lang/Exception;)Ljava/lang/Exception;
    //   101: athrow
    //   102: aload_1
    //   103: invokevirtual ZV : ()Lcom/fasterxml/Zb/Zl;
    //   106: pop
    //   107: aload #4
    //   109: ifnull -> 15
    //   112: aload #5
    //   114: areturn
    // Exception table:
    //   from	to	target	type
    //   52	63	66	java/lang/Exception
    //   68	95	98	java/lang/Exception
  }
  
  public Object ZJ(Zg paramZg, Zyg paramZyg) throws IOException {
    // Byte code:
    //   0: invokestatic ZP : ()Ljava/lang/String;
    //   3: astore_3
    //   4: aload_0
    //   5: getfield ZU : Z
    //   8: ifeq -> 61
    //   11: aload_0
    //   12: getfield ZL : Lcom/fasterxml/Ze/Zo1;
    //   15: ifnull -> 36
    //   18: goto -> 25
    //   21: invokestatic a : (Ljava/lang/Exception;)Ljava/lang/Exception;
    //   24: athrow
    //   25: aload_0
    //   26: aload_1
    //   27: aload_2
    //   28: invokevirtual ZU : (Lcom/fasterxml/Zb/Zg;Lcom/fasterxml/Zor/Zyg;)Ljava/lang/Object;
    //   31: areturn
    //   32: invokestatic a : (Ljava/lang/Exception;)Ljava/lang/Exception;
    //   35: athrow
    //   36: aload_0
    //   37: getfield Zv : Lcom/fasterxml/Ze/Zoq;
    //   40: ifnull -> 54
    //   43: aload_0
    //   44: aload_1
    //   45: aload_2
    //   46: invokevirtual ZW : (Lcom/fasterxml/Zb/Zg;Lcom/fasterxml/Zor/Zyg;)Ljava/lang/Object;
    //   49: areturn
    //   50: invokestatic a : (Ljava/lang/Exception;)Ljava/lang/Exception;
    //   53: athrow
    //   54: aload_0
    //   55: aload_1
    //   56: aload_2
    //   57: invokevirtual Zb : (Lcom/fasterxml/Zb/Zg;Lcom/fasterxml/Zor/Zyg;)Ljava/lang/Object;
    //   60: areturn
    //   61: aload_0
    //   62: getfield Zb : Lcom/fasterxml/Zo/Zzp;
    //   65: aload_2
    //   66: invokevirtual Zy : (Lcom/fasterxml/Zor/Zyg;)Ljava/lang/Object;
    //   69: astore #4
    //   71: aload_0
    //   72: getfield Zy : [Lcom/fasterxml/Ze/Zv;
    //   75: ifnull -> 92
    //   78: aload_0
    //   79: aload_2
    //   80: aload #4
    //   82: invokevirtual Zl : (Lcom/fasterxml/Zor/Zyg;Ljava/lang/Object;)V
    //   85: goto -> 92
    //   88: invokestatic a : (Ljava/lang/Exception;)Ljava/lang/Exception;
    //   91: athrow
    //   92: aload_0
    //   93: getfield Zk : Z
    //   96: ifeq -> 125
    //   99: aload_2
    //   100: invokevirtual Zx : ()Ljava/lang/Class;
    //   103: astore #5
    //   105: aload #5
    //   107: ifnull -> 125
    //   110: aload_0
    //   111: aload_1
    //   112: aload_2
    //   113: aload #4
    //   115: aload #5
    //   117: invokevirtual ZV : (Lcom/fasterxml/Zb/Zg;Lcom/fasterxml/Zor/Zyg;Ljava/lang/Object;Ljava/lang/Class;)Ljava/lang/Object;
    //   120: areturn
    //   121: invokestatic a : (Ljava/lang/Exception;)Ljava/lang/Exception;
    //   124: athrow
    //   125: aload_1
    //   126: invokevirtual Zh : ()Lcom/fasterxml/Zb/Zl;
    //   129: getstatic com/fasterxml/Zb/Zl.FIELD_NAME : Lcom/fasterxml/Zb/Zl;
    //   132: if_acmpne -> 220
    //   135: aload_1
    //   136: invokevirtual ZS : ()Ljava/lang/String;
    //   139: astore #5
    //   141: aload_1
    //   142: invokevirtual ZV : ()Lcom/fasterxml/Zb/Zl;
    //   145: pop
    //   146: aload_0
    //   147: getfield ZX : Lcom/fasterxml/Ze/Zo8;
    //   150: aload #5
    //   152: invokevirtual ZI : (Ljava/lang/String;)Lcom/fasterxml/Zo/Zv;
    //   155: astore #6
    //   157: aload #6
    //   159: ifnull -> 194
    //   162: aload #6
    //   164: aload_1
    //   165: aload_2
    //   166: aload #4
    //   168: invokevirtual ZR : (Lcom/fasterxml/Zb/Zg;Lcom/fasterxml/Zor/Zyg;Ljava/lang/Object;)Ljava/lang/Object;
    //   171: astore #4
    //   173: goto -> 211
    //   176: astore #7
    //   178: aload_0
    //   179: aload #7
    //   181: aload #4
    //   183: aload #5
    //   185: aload_2
    //   186: invokevirtual Zd : (Ljava/lang/Throwable;Ljava/lang/Object;Ljava/lang/String;Lcom/fasterxml/Zor/Zyg;)Ljava/lang/Object;
    //   189: pop
    //   190: aload_3
    //   191: ifnull -> 211
    //   194: aload_0
    //   195: aload_1
    //   196: aload_2
    //   197: aload #4
    //   199: aload #5
    //   201: invokevirtual ZN : (Lcom/fasterxml/Zb/Zg;Lcom/fasterxml/Zor/Zyg;Ljava/lang/Object;Ljava/lang/String;)V
    //   204: goto -> 211
    //   207: invokestatic a : (Ljava/lang/Exception;)Ljava/lang/Exception;
    //   210: athrow
    //   211: aload_1
    //   212: invokevirtual ZV : ()Lcom/fasterxml/Zb/Zl;
    //   215: pop
    //   216: aload_3
    //   217: ifnull -> 125
    //   220: aload #4
    //   222: areturn
    // Exception table:
    //   from	to	target	type
    //   4	18	21	java/lang/Exception
    //   11	32	32	java/lang/Exception
    //   36	50	50	java/lang/Exception
    //   71	85	88	java/lang/Exception
    //   105	121	121	java/lang/Exception
    //   162	173	176	java/lang/Exception
    //   178	204	207	java/lang/Exception
  }
  
  protected Object ZZ(Zg paramZg, Zyg paramZyg) throws IOException {
    // Byte code:
    //   0: invokestatic ZP : ()Ljava/lang/String;
    //   3: aload_0
    //   4: getfield ZT : Lcom/fasterxml/Ze/Zc;
    //   7: astore #4
    //   9: astore_3
    //   10: aload #4
    //   12: aload_1
    //   13: aload_2
    //   14: aload_0
    //   15: getfield ZZ : Lcom/fasterxml/Ze/Zz;
    //   18: invokevirtual Zn : (Lcom/fasterxml/Zb/Zg;Lcom/fasterxml/Zor/Zyg;Lcom/fasterxml/Ze/Zz;)Lcom/fasterxml/Ze/Zok;
    //   21: astore #5
    //   23: aload_0
    //   24: getfield Zk : Z
    //   27: ifeq -> 41
    //   30: aload_2
    //   31: invokevirtual Zx : ()Ljava/lang/Class;
    //   34: goto -> 42
    //   37: invokestatic a : (Ljava/lang/Exception;)Ljava/lang/Exception;
    //   40: athrow
    //   41: aconst_null
    //   42: astore #6
    //   44: aconst_null
    //   45: astore #7
    //   47: aload_1
    //   48: invokevirtual Zh : ()Lcom/fasterxml/Zb/Zl;
    //   51: astore #8
    //   53: aload #8
    //   55: getstatic com/fasterxml/Zb/Zl.FIELD_NAME : Lcom/fasterxml/Zb/Zl;
    //   58: if_acmpne -> 468
    //   61: aload_1
    //   62: invokevirtual ZS : ()Ljava/lang/String;
    //   65: astore #9
    //   67: aload_1
    //   68: invokevirtual ZV : ()Lcom/fasterxml/Zb/Zl;
    //   71: pop
    //   72: aload #4
    //   74: aload #9
    //   76: invokevirtual ZO : (Ljava/lang/String;)Lcom/fasterxml/Zo/Zv;
    //   79: astore #10
    //   81: aload #5
    //   83: aload #9
    //   85: invokevirtual Zw : (Ljava/lang/String;)Z
    //   88: ifeq -> 114
    //   91: aload #10
    //   93: ifnonnull -> 114
    //   96: goto -> 103
    //   99: invokestatic a : (Ljava/lang/Exception;)Ljava/lang/Exception;
    //   102: athrow
    //   103: aload_3
    //   104: ifnull -> 458
    //   107: goto -> 114
    //   110: invokestatic a : (Ljava/lang/Exception;)Ljava/lang/Exception;
    //   113: athrow
    //   114: aload #10
    //   116: ifnull -> 294
    //   119: goto -> 126
    //   122: invokestatic a : (Ljava/lang/Exception;)Ljava/lang/Exception;
    //   125: athrow
    //   126: aload #6
    //   128: ifnull -> 171
    //   131: goto -> 138
    //   134: invokestatic a : (Ljava/lang/Exception;)Ljava/lang/Exception;
    //   137: athrow
    //   138: aload #10
    //   140: aload #6
    //   142: invokevirtual Zj : (Ljava/lang/Class;)Z
    //   145: ifne -> 171
    //   148: goto -> 155
    //   151: invokestatic a : (Ljava/lang/Exception;)Ljava/lang/Exception;
    //   154: athrow
    //   155: aload_1
    //   156: invokevirtual Zc : ()Lcom/fasterxml/Zb/Zg;
    //   159: pop
    //   160: aload_3
    //   161: ifnull -> 458
    //   164: goto -> 171
    //   167: invokestatic a : (Ljava/lang/Exception;)Ljava/lang/Exception;
    //   170: athrow
    //   171: aload #5
    //   173: aload #10
    //   175: aload #10
    //   177: aload_1
    //   178: aload_2
    //   179: invokevirtual Zt : (Lcom/fasterxml/Zb/Zg;Lcom/fasterxml/Zor/Zyg;)Ljava/lang/Object;
    //   182: invokevirtual Zr : (Lcom/fasterxml/Zo/Zv;Ljava/lang/Object;)Z
    //   185: ifeq -> 458
    //   188: goto -> 195
    //   191: invokestatic a : (Ljava/lang/Exception;)Ljava/lang/Exception;
    //   194: athrow
    //   195: aload_1
    //   196: invokevirtual ZV : ()Lcom/fasterxml/Zb/Zl;
    //   199: pop
    //   200: aload #4
    //   202: aload_2
    //   203: aload #5
    //   205: invokevirtual ZP : (Lcom/fasterxml/Zor/Zyg;Lcom/fasterxml/Ze/Zok;)Ljava/lang/Object;
    //   208: astore #11
    //   210: goto -> 235
    //   213: astore #12
    //   215: aload_0
    //   216: aload #12
    //   218: aload_0
    //   219: getfield ZF : Lcom/fasterxml/Zor/Zk;
    //   222: invokevirtual Zf : ()Ljava/lang/Class;
    //   225: aload #9
    //   227: aload_2
    //   228: invokevirtual Zd : (Ljava/lang/Throwable;Ljava/lang/Object;Ljava/lang/String;Lcom/fasterxml/Zor/Zyg;)Ljava/lang/Object;
    //   231: pop
    //   232: goto -> 458
    //   235: aload #11
    //   237: invokevirtual getClass : ()Ljava/lang/Class;
    //   240: aload_0
    //   241: getfield ZF : Lcom/fasterxml/Zor/Zk;
    //   244: invokevirtual Zf : ()Ljava/lang/Class;
    //   247: if_acmpeq -> 269
    //   250: aload_0
    //   251: aload_1
    //   252: aload_2
    //   253: aload_1
    //   254: invokevirtual ZG : ()Lcom/fasterxml/Zb/Z_;
    //   257: aload #11
    //   259: aload #7
    //   261: invokevirtual Zg : (Lcom/fasterxml/Zb/Zg;Lcom/fasterxml/Zor/Zyg;Lcom/fasterxml/Zb/Z_;Ljava/lang/Object;Lcom/fasterxml/Zm/Zl;)Ljava/lang/Object;
    //   264: areturn
    //   265: invokestatic a : (Ljava/lang/Exception;)Ljava/lang/Exception;
    //   268: athrow
    //   269: aload #7
    //   271: ifnull -> 285
    //   274: aload_0
    //   275: aload_2
    //   276: aload #11
    //   278: aload #7
    //   280: invokevirtual ZL : (Lcom/fasterxml/Zor/Zyg;Ljava/lang/Object;Lcom/fasterxml/Zm/Zl;)Ljava/lang/Object;
    //   283: astore #11
    //   285: aload_0
    //   286: aload_1
    //   287: aload_2
    //   288: aload #11
    //   290: invokevirtual Zc : (Lcom/fasterxml/Zb/Zg;Lcom/fasterxml/Zor/Zyg;Ljava/lang/Object;)Ljava/lang/Object;
    //   293: areturn
    //   294: aload_0
    //   295: getfield ZX : Lcom/fasterxml/Ze/Zo8;
    //   298: aload #9
    //   300: invokevirtual ZI : (Ljava/lang/String;)Lcom/fasterxml/Zo/Zv;
    //   303: astore #11
    //   305: aload #11
    //   307: ifnull -> 335
    //   310: aload #5
    //   312: aload #11
    //   314: aload #11
    //   316: aload_1
    //   317: aload_2
    //   318: invokevirtual Zt : (Lcom/fasterxml/Zb/Zg;Lcom/fasterxml/Zor/Zyg;)Ljava/lang/Object;
    //   321: invokevirtual ZR : (Lcom/fasterxml/Zo/Zv;Ljava/lang/Object;)V
    //   324: aload_3
    //   325: ifnull -> 458
    //   328: goto -> 335
    //   331: invokestatic a : (Ljava/lang/Exception;)Ljava/lang/Exception;
    //   334: athrow
    //   335: aload #9
    //   337: aload_0
    //   338: getfield Zq : Ljava/util/Set;
    //   341: aload_0
    //   342: getfield ZP : Ljava/util/Set;
    //   345: invokestatic Zv : (Ljava/lang/Object;Ljava/util/Collection;Ljava/util/Collection;)Z
    //   348: ifeq -> 381
    //   351: goto -> 358
    //   354: invokestatic a : (Ljava/lang/Exception;)Ljava/lang/Exception;
    //   357: athrow
    //   358: aload_0
    //   359: aload_1
    //   360: aload_2
    //   361: aload_0
    //   362: invokevirtual ZX : ()Ljava/lang/Class;
    //   365: aload #9
    //   367: invokevirtual ZC : (Lcom/fasterxml/Zb/Zg;Lcom/fasterxml/Zor/Zyg;Ljava/lang/Object;Ljava/lang/String;)V
    //   370: aload_3
    //   371: ifnull -> 458
    //   374: goto -> 381
    //   377: invokestatic a : (Ljava/lang/Exception;)Ljava/lang/Exception;
    //   380: athrow
    //   381: aload_0
    //   382: getfield ZA : Lcom/fasterxml/Zo/Zl;
    //   385: ifnull -> 426
    //   388: goto -> 395
    //   391: invokestatic a : (Ljava/lang/Exception;)Ljava/lang/Exception;
    //   394: athrow
    //   395: aload #5
    //   397: aload_0
    //   398: getfield ZA : Lcom/fasterxml/Zo/Zl;
    //   401: aload #9
    //   403: aload_0
    //   404: getfield ZA : Lcom/fasterxml/Zo/Zl;
    //   407: aload_1
    //   408: aload_2
    //   409: invokevirtual ZZ : (Lcom/fasterxml/Zb/Zg;Lcom/fasterxml/Zor/Zyg;)Ljava/lang/Object;
    //   412: invokevirtual Zk : (Lcom/fasterxml/Zo/Zl;Ljava/lang/String;Ljava/lang/Object;)V
    //   415: aload_3
    //   416: ifnull -> 458
    //   419: goto -> 426
    //   422: invokestatic a : (Ljava/lang/Exception;)Ljava/lang/Exception;
    //   425: athrow
    //   426: aload #7
    //   428: ifnonnull -> 445
    //   431: goto -> 438
    //   434: invokestatic a : (Ljava/lang/Exception;)Ljava/lang/Exception;
    //   437: athrow
    //   438: aload_2
    //   439: aload_1
    //   440: invokevirtual Zb : (Lcom/fasterxml/Zb/Zg;)Lcom/fasterxml/Zm/Zl;
    //   443: astore #7
    //   445: aload #7
    //   447: aload #9
    //   449: invokevirtual ZY : (Ljava/lang/String;)V
    //   452: aload #7
    //   454: aload_1
    //   455: invokevirtual ZE : (Lcom/fasterxml/Zb/Zg;)V
    //   458: aload_1
    //   459: invokevirtual ZV : ()Lcom/fasterxml/Zb/Zl;
    //   462: astore #8
    //   464: aload_3
    //   465: ifnull -> 53
    //   468: aload #4
    //   470: aload_2
    //   471: aload #5
    //   473: invokevirtual ZP : (Lcom/fasterxml/Zor/Zyg;Lcom/fasterxml/Ze/Zok;)Ljava/lang/Object;
    //   476: astore #9
    //   478: goto -> 492
    //   481: astore #10
    //   483: aload_0
    //   484: aload #10
    //   486: aload_2
    //   487: invokevirtual ZR : (Ljava/lang/Throwable;Lcom/fasterxml/Zor/Zyg;)Ljava/lang/Object;
    //   490: astore #9
    //   492: aload #7
    //   494: ifnull -> 548
    //   497: aload #9
    //   499: invokevirtual getClass : ()Ljava/lang/Class;
    //   502: aload_0
    //   503: getfield ZF : Lcom/fasterxml/Zor/Zk;
    //   506: invokevirtual Zf : ()Ljava/lang/Class;
    //   509: if_acmpeq -> 538
    //   512: goto -> 519
    //   515: invokestatic a : (Ljava/lang/Exception;)Ljava/lang/Exception;
    //   518: athrow
    //   519: aload_0
    //   520: aconst_null
    //   521: aload_2
    //   522: aload_1
    //   523: invokevirtual ZG : ()Lcom/fasterxml/Zb/Z_;
    //   526: aload #9
    //   528: aload #7
    //   530: invokevirtual Zg : (Lcom/fasterxml/Zb/Zg;Lcom/fasterxml/Zor/Zyg;Lcom/fasterxml/Zb/Z_;Ljava/lang/Object;Lcom/fasterxml/Zm/Zl;)Ljava/lang/Object;
    //   533: areturn
    //   534: invokestatic a : (Ljava/lang/Exception;)Ljava/lang/Exception;
    //   537: athrow
    //   538: aload_0
    //   539: aload_2
    //   540: aload #9
    //   542: aload #7
    //   544: invokevirtual ZL : (Lcom/fasterxml/Zor/Zyg;Ljava/lang/Object;Lcom/fasterxml/Zm/Zl;)Ljava/lang/Object;
    //   547: areturn
    //   548: aload #9
    //   550: areturn
    // Exception table:
    //   from	to	target	type
    //   23	37	37	java/lang/Exception
    //   81	96	99	java/lang/Exception
    //   91	107	110	java/lang/Exception
    //   103	119	122	java/lang/Exception
    //   114	131	134	java/lang/Exception
    //   126	148	151	java/lang/Exception
    //   138	164	167	java/lang/Exception
    //   155	188	191	java/lang/Exception
    //   200	210	213	java/lang/Exception
    //   235	265	265	java/lang/Exception
    //   305	328	331	java/lang/Exception
    //   310	351	354	java/lang/Exception
    //   335	374	377	java/lang/Exception
    //   358	388	391	java/lang/Exception
    //   381	419	422	java/lang/Exception
    //   395	431	434	java/lang/Exception
    //   468	478	481	java/lang/Exception
    //   492	512	515	java/lang/Exception
    //   497	534	534	java/lang/Exception
  }
  
  protected final Object Zc(Zg paramZg, Zyg paramZyg, Object paramObject) throws IOException {
    // Byte code:
    //   0: invokestatic ZP : ()Ljava/lang/String;
    //   3: astore #4
    //   5: aload_0
    //   6: getfield Zy : [Lcom/fasterxml/Ze/Zv;
    //   9: ifnull -> 25
    //   12: aload_0
    //   13: aload_2
    //   14: aload_3
    //   15: invokevirtual Zl : (Lcom/fasterxml/Zor/Zyg;Ljava/lang/Object;)V
    //   18: goto -> 25
    //   21: invokestatic a : (Ljava/lang/Exception;)Ljava/lang/Exception;
    //   24: athrow
    //   25: aload_0
    //   26: getfield ZL : Lcom/fasterxml/Ze/Zo1;
    //   29: ifnull -> 83
    //   32: aload_1
    //   33: getstatic com/fasterxml/Zb/Zl.START_OBJECT : Lcom/fasterxml/Zb/Zl;
    //   36: invokevirtual ZL : (Lcom/fasterxml/Zb/Zl;)Z
    //   39: ifeq -> 61
    //   42: goto -> 49
    //   45: invokestatic a : (Ljava/lang/Exception;)Ljava/lang/Exception;
    //   48: athrow
    //   49: aload_1
    //   50: invokevirtual ZV : ()Lcom/fasterxml/Zb/Zl;
    //   53: pop
    //   54: goto -> 61
    //   57: invokestatic a : (Ljava/lang/Exception;)Ljava/lang/Exception;
    //   60: athrow
    //   61: aload_2
    //   62: aload_1
    //   63: invokevirtual Zb : (Lcom/fasterxml/Zb/Zg;)Lcom/fasterxml/Zm/Zl;
    //   66: astore #5
    //   68: aload #5
    //   70: invokevirtual ZJ : ()V
    //   73: aload_0
    //   74: aload_1
    //   75: aload_2
    //   76: aload_3
    //   77: aload #5
    //   79: invokevirtual Zc : (Lcom/fasterxml/Zb/Zg;Lcom/fasterxml/Zor/Zyg;Ljava/lang/Object;Lcom/fasterxml/Zm/Zl;)Ljava/lang/Object;
    //   82: areturn
    //   83: aload_0
    //   84: getfield Zv : Lcom/fasterxml/Ze/Zoq;
    //   87: ifnull -> 102
    //   90: aload_0
    //   91: aload_1
    //   92: aload_2
    //   93: aload_3
    //   94: invokevirtual Zz : (Lcom/fasterxml/Zb/Zg;Lcom/fasterxml/Zor/Zyg;Ljava/lang/Object;)Ljava/lang/Object;
    //   97: areturn
    //   98: invokestatic a : (Ljava/lang/Exception;)Ljava/lang/Exception;
    //   101: athrow
    //   102: aload_0
    //   103: getfield Zk : Z
    //   106: ifeq -> 134
    //   109: aload_2
    //   110: invokevirtual Zx : ()Ljava/lang/Class;
    //   113: astore #5
    //   115: aload #5
    //   117: ifnull -> 134
    //   120: aload_0
    //   121: aload_1
    //   122: aload_2
    //   123: aload_3
    //   124: aload #5
    //   126: invokevirtual ZV : (Lcom/fasterxml/Zb/Zg;Lcom/fasterxml/Zor/Zyg;Ljava/lang/Object;Ljava/lang/Class;)Ljava/lang/Object;
    //   129: areturn
    //   130: invokestatic a : (Ljava/lang/Exception;)Ljava/lang/Exception;
    //   133: athrow
    //   134: aload_1
    //   135: invokevirtual Zh : ()Lcom/fasterxml/Zb/Zl;
    //   138: astore #5
    //   140: aload #5
    //   142: getstatic com/fasterxml/Zb/Zl.START_OBJECT : Lcom/fasterxml/Zb/Zl;
    //   145: if_acmpne -> 154
    //   148: aload_1
    //   149: invokevirtual ZV : ()Lcom/fasterxml/Zb/Zl;
    //   152: astore #5
    //   154: aload #5
    //   156: getstatic com/fasterxml/Zb/Zl.FIELD_NAME : Lcom/fasterxml/Zb/Zl;
    //   159: if_acmpne -> 246
    //   162: aload_1
    //   163: invokevirtual ZS : ()Ljava/lang/String;
    //   166: astore #6
    //   168: aload_1
    //   169: invokevirtual ZV : ()Lcom/fasterxml/Zb/Zl;
    //   172: pop
    //   173: aload_0
    //   174: getfield ZX : Lcom/fasterxml/Ze/Zo8;
    //   177: aload #6
    //   179: invokevirtual ZI : (Ljava/lang/String;)Lcom/fasterxml/Zo/Zv;
    //   182: astore #7
    //   184: aload #7
    //   186: ifnull -> 219
    //   189: aload #7
    //   191: aload_1
    //   192: aload_2
    //   193: aload_3
    //   194: invokevirtual ZR : (Lcom/fasterxml/Zb/Zg;Lcom/fasterxml/Zor/Zyg;Ljava/lang/Object;)Ljava/lang/Object;
    //   197: astore_3
    //   198: goto -> 235
    //   201: astore #8
    //   203: aload_0
    //   204: aload #8
    //   206: aload_3
    //   207: aload #6
    //   209: aload_2
    //   210: invokevirtual Zd : (Ljava/lang/Throwable;Ljava/lang/Object;Ljava/lang/String;Lcom/fasterxml/Zor/Zyg;)Ljava/lang/Object;
    //   213: pop
    //   214: aload #4
    //   216: ifnull -> 235
    //   219: aload_0
    //   220: aload_1
    //   221: aload_2
    //   222: aload_3
    //   223: aload #6
    //   225: invokevirtual ZN : (Lcom/fasterxml/Zb/Zg;Lcom/fasterxml/Zor/Zyg;Ljava/lang/Object;Ljava/lang/String;)V
    //   228: goto -> 235
    //   231: invokestatic a : (Ljava/lang/Exception;)Ljava/lang/Exception;
    //   234: athrow
    //   235: aload_1
    //   236: invokevirtual ZV : ()Lcom/fasterxml/Zb/Zl;
    //   239: astore #5
    //   241: aload #4
    //   243: ifnull -> 154
    //   246: aload_3
    //   247: areturn
    // Exception table:
    //   from	to	target	type
    //   5	18	21	java/lang/Exception
    //   25	42	45	java/lang/Exception
    //   32	54	57	java/lang/Exception
    //   83	98	98	java/lang/Exception
    //   115	130	130	java/lang/Exception
    //   189	198	201	java/lang/Exception
    //   203	228	231	java/lang/Exception
  }
  
  protected Object ZF(Zg paramZg, Zyg paramZyg) throws IOException {
    Zyo<Object> zyo = this.Zc;
    if (zyo != null || (zyo = this.Zo) != null) {
      Object object = this.Zb.ZW(paramZyg, zyo.deserialize(paramZg, paramZyg));
      try {
        if (this.Zy != null)
          Zl(paramZyg, object); 
      } catch (IOException iOException) {
        throw a(null);
      } 
      return Zi(paramZyg, object);
    } 
    Zx zx = ZP(paramZyg);
    boolean bool = paramZyg.Zg(Zyp.UNWRAP_SINGLE_VALUE_ARRAYS);
    try {
      if (bool || zx != Zx.Fail) {
        Zl zl = paramZg.ZV();
        try {
          if (zl == Zl.END_ARRAY) {
            try {
              switch (Z_.Zg[zx.ordinal()]) {
                case 1:
                  return Zy(paramZyg);
                case 2:
                case 3:
                  return Zj(paramZyg);
              } 
            } catch (IOException iOException) {
              throw a(null);
            } 
            return paramZyg.Za(Zq(paramZyg), Zl.START_ARRAY, paramZg, null, new Object[0]);
          } 
        } catch (IOException iOException) {
          throw a(null);
        } 
        if (bool) {
          Object object = deserialize(paramZg, paramZyg);
          try {
            if (paramZg.ZV() != Zl.END_ARRAY)
              ZH(paramZg, paramZyg); 
          } catch (IOException iOException) {
            throw a(null);
          } 
          return object;
        } 
      } 
    } catch (IOException iOException) {
      throw a(null);
    } 
    return paramZyg.ZE(Zq(paramZyg), paramZg);
  }
  
  protected final Object ZV(Zg paramZg, Zyg paramZyg, Object paramObject, Class<?> paramClass) throws IOException {
    // Byte code:
    //   0: invokestatic ZP : ()Ljava/lang/String;
    //   3: aload_1
    //   4: invokevirtual Zh : ()Lcom/fasterxml/Zb/Zl;
    //   7: astore #6
    //   9: astore #5
    //   11: aload #6
    //   13: getstatic com/fasterxml/Zb/Zl.FIELD_NAME : Lcom/fasterxml/Zb/Zl;
    //   16: if_acmpne -> 209
    //   19: aload_1
    //   20: invokevirtual ZS : ()Ljava/lang/String;
    //   23: astore #7
    //   25: aload_1
    //   26: invokevirtual ZV : ()Lcom/fasterxml/Zb/Zl;
    //   29: pop
    //   30: aload_0
    //   31: getfield ZX : Lcom/fasterxml/Ze/Zo8;
    //   34: aload #7
    //   36: invokevirtual ZI : (Ljava/lang/String;)Lcom/fasterxml/Zo/Zv;
    //   39: astore #8
    //   41: aload #8
    //   43: ifnull -> 182
    //   46: aload #8
    //   48: aload #4
    //   50: invokevirtual Zj : (Ljava/lang/Class;)Z
    //   53: ifne -> 152
    //   56: goto -> 63
    //   59: invokestatic a : (Ljava/lang/Exception;)Ljava/lang/Exception;
    //   62: athrow
    //   63: aload_2
    //   64: getstatic com/fasterxml/Zor/Zyp.FAIL_ON_UNEXPECTED_VIEW_PROPERTIES : Lcom/fasterxml/Zor/Zyp;
    //   67: invokevirtual Zg : (Lcom/fasterxml/Zor/Zyp;)Z
    //   70: ifeq -> 142
    //   73: goto -> 80
    //   76: invokestatic a : (Ljava/lang/Exception;)Ljava/lang/Exception;
    //   79: athrow
    //   80: aload_2
    //   81: aload_0
    //   82: invokevirtual ZX : ()Ljava/lang/Class;
    //   85: sipush #-7125
    //   88: sipush #24546
    //   91: invokestatic d : (II)Ljava/lang/String;
    //   94: iconst_3
    //   95: anewarray java/lang/Object
    //   98: dup
    //   99: iconst_0
    //   100: aload_0
    //   101: invokevirtual ZX : ()Ljava/lang/Class;
    //   104: invokestatic Za : (Ljava/lang/Class;)Ljava/lang/String;
    //   107: aastore
    //   108: dup
    //   109: iconst_1
    //   110: aload #8
    //   112: invokevirtual ZT : ()Ljava/lang/String;
    //   115: aastore
    //   116: dup
    //   117: iconst_2
    //   118: aload #4
    //   120: invokevirtual getName : ()Ljava/lang/String;
    //   123: aastore
    //   124: invokestatic format : (Ljava/lang/String;[Ljava/lang/Object;)Ljava/lang/String;
    //   127: iconst_0
    //   128: anewarray java/lang/Object
    //   131: invokevirtual ZF : (Ljava/lang/Class;Ljava/lang/String;[Ljava/lang/Object;)Ljava/lang/Object;
    //   134: pop
    //   135: goto -> 142
    //   138: invokestatic a : (Ljava/lang/Exception;)Ljava/lang/Exception;
    //   141: athrow
    //   142: aload_1
    //   143: invokevirtual Zc : ()Lcom/fasterxml/Zb/Zg;
    //   146: pop
    //   147: aload #5
    //   149: ifnull -> 198
    //   152: aload #8
    //   154: aload_1
    //   155: aload_2
    //   156: aload_3
    //   157: invokevirtual ZR : (Lcom/fasterxml/Zb/Zg;Lcom/fasterxml/Zor/Zyg;Ljava/lang/Object;)Ljava/lang/Object;
    //   160: astore_3
    //   161: goto -> 198
    //   164: astore #9
    //   166: aload_0
    //   167: aload #9
    //   169: aload_3
    //   170: aload #7
    //   172: aload_2
    //   173: invokevirtual Zd : (Ljava/lang/Throwable;Ljava/lang/Object;Ljava/lang/String;Lcom/fasterxml/Zor/Zyg;)Ljava/lang/Object;
    //   176: pop
    //   177: aload #5
    //   179: ifnull -> 198
    //   182: aload_0
    //   183: aload_1
    //   184: aload_2
    //   185: aload_3
    //   186: aload #7
    //   188: invokevirtual ZN : (Lcom/fasterxml/Zb/Zg;Lcom/fasterxml/Zor/Zyg;Ljava/lang/Object;Ljava/lang/String;)V
    //   191: goto -> 198
    //   194: invokestatic a : (Ljava/lang/Exception;)Ljava/lang/Exception;
    //   197: athrow
    //   198: aload_1
    //   199: invokevirtual ZV : ()Lcom/fasterxml/Zb/Zl;
    //   202: astore #6
    //   204: aload #5
    //   206: ifnull -> 11
    //   209: aload_3
    //   210: areturn
    // Exception table:
    //   from	to	target	type
    //   41	56	59	java/lang/Exception
    //   46	73	76	java/lang/Exception
    //   63	135	138	java/lang/Exception
    //   152	161	164	java/lang/Exception
    //   166	191	194	java/lang/Exception
  }
  
  protected Object ZU(Zg paramZg, Zyg paramZyg) throws IOException {
    // Byte code:
    //   0: invokestatic ZP : ()Ljava/lang/String;
    //   3: astore_3
    //   4: aload_0
    //   5: getfield Zo : Lcom/fasterxml/Zor/Zyo;
    //   8: ifnull -> 33
    //   11: aload_0
    //   12: getfield Zb : Lcom/fasterxml/Zo/Zzp;
    //   15: aload_2
    //   16: aload_0
    //   17: getfield Zo : Lcom/fasterxml/Zor/Zyo;
    //   20: aload_1
    //   21: aload_2
    //   22: invokevirtual deserialize : (Lcom/fasterxml/Zb/Zg;Lcom/fasterxml/Zor/Zyg;)Ljava/lang/Object;
    //   25: invokevirtual Zu : (Lcom/fasterxml/Zor/Zyg;Ljava/lang/Object;)Ljava/lang/Object;
    //   28: areturn
    //   29: invokestatic a : (Ljava/lang/Exception;)Ljava/lang/Exception;
    //   32: athrow
    //   33: aload_0
    //   34: getfield ZT : Lcom/fasterxml/Ze/Zc;
    //   37: ifnull -> 51
    //   40: aload_0
    //   41: aload_1
    //   42: aload_2
    //   43: invokevirtual ZL : (Lcom/fasterxml/Zb/Zg;Lcom/fasterxml/Zor/Zyg;)Ljava/lang/Object;
    //   46: areturn
    //   47: invokestatic a : (Ljava/lang/Exception;)Ljava/lang/Exception;
    //   50: athrow
    //   51: aload_2
    //   52: aload_1
    //   53: invokevirtual Zb : (Lcom/fasterxml/Zb/Zg;)Lcom/fasterxml/Zm/Zl;
    //   56: astore #4
    //   58: aload #4
    //   60: invokevirtual ZJ : ()V
    //   63: aload_0
    //   64: getfield Zb : Lcom/fasterxml/Zo/Zzp;
    //   67: aload_2
    //   68: invokevirtual Zy : (Lcom/fasterxml/Zor/Zyg;)Ljava/lang/Object;
    //   71: astore #5
    //   73: aload_0
    //   74: getfield Zy : [Lcom/fasterxml/Ze/Zv;
    //   77: ifnull -> 94
    //   80: aload_0
    //   81: aload_2
    //   82: aload #5
    //   84: invokevirtual Zl : (Lcom/fasterxml/Zor/Zyg;Ljava/lang/Object;)V
    //   87: goto -> 94
    //   90: invokestatic a : (Ljava/lang/Exception;)Ljava/lang/Exception;
    //   93: athrow
    //   94: aload_0
    //   95: getfield Zk : Z
    //   98: ifeq -> 112
    //   101: aload_2
    //   102: invokevirtual Zx : ()Ljava/lang/Class;
    //   105: goto -> 113
    //   108: invokestatic a : (Ljava/lang/Exception;)Ljava/lang/Exception;
    //   111: athrow
    //   112: aconst_null
    //   113: astore #6
    //   115: aload_1
    //   116: invokevirtual Zh : ()Lcom/fasterxml/Zb/Zl;
    //   119: getstatic com/fasterxml/Zb/Zl.FIELD_NAME : Lcom/fasterxml/Zb/Zl;
    //   122: if_acmpne -> 342
    //   125: aload_1
    //   126: invokevirtual ZS : ()Ljava/lang/String;
    //   129: astore #7
    //   131: aload_1
    //   132: invokevirtual ZV : ()Lcom/fasterxml/Zb/Zl;
    //   135: pop
    //   136: aload_0
    //   137: getfield ZX : Lcom/fasterxml/Ze/Zo8;
    //   140: aload #7
    //   142: invokevirtual ZI : (Ljava/lang/String;)Lcom/fasterxml/Zo/Zv;
    //   145: astore #8
    //   147: aload #8
    //   149: ifnull -> 229
    //   152: aload #6
    //   154: ifnull -> 197
    //   157: goto -> 164
    //   160: invokestatic a : (Ljava/lang/Exception;)Ljava/lang/Exception;
    //   163: athrow
    //   164: aload #8
    //   166: aload #6
    //   168: invokevirtual Zj : (Ljava/lang/Class;)Z
    //   171: ifne -> 197
    //   174: goto -> 181
    //   177: invokestatic a : (Ljava/lang/Exception;)Ljava/lang/Exception;
    //   180: athrow
    //   181: aload_1
    //   182: invokevirtual Zc : ()Lcom/fasterxml/Zb/Zg;
    //   185: pop
    //   186: aload_3
    //   187: ifnull -> 333
    //   190: goto -> 197
    //   193: invokestatic a : (Ljava/lang/Exception;)Ljava/lang/Exception;
    //   196: athrow
    //   197: aload #8
    //   199: aload_1
    //   200: aload_2
    //   201: aload #5
    //   203: invokevirtual ZR : (Lcom/fasterxml/Zb/Zg;Lcom/fasterxml/Zor/Zyg;Ljava/lang/Object;)Ljava/lang/Object;
    //   206: astore #5
    //   208: goto -> 333
    //   211: astore #9
    //   213: aload_0
    //   214: aload #9
    //   216: aload #5
    //   218: aload #7
    //   220: aload_2
    //   221: invokevirtual Zd : (Ljava/lang/Throwable;Ljava/lang/Object;Ljava/lang/String;Lcom/fasterxml/Zor/Zyg;)Ljava/lang/Object;
    //   224: pop
    //   225: aload_3
    //   226: ifnull -> 333
    //   229: aload #7
    //   231: aload_0
    //   232: getfield Zq : Ljava/util/Set;
    //   235: aload_0
    //   236: getfield ZP : Ljava/util/Set;
    //   239: invokestatic Zv : (Ljava/lang/Object;Ljava/util/Collection;Ljava/util/Collection;)Z
    //   242: ifeq -> 273
    //   245: goto -> 252
    //   248: invokestatic a : (Ljava/lang/Exception;)Ljava/lang/Exception;
    //   251: athrow
    //   252: aload_0
    //   253: aload_1
    //   254: aload_2
    //   255: aload #5
    //   257: aload #7
    //   259: invokevirtual ZC : (Lcom/fasterxml/Zb/Zg;Lcom/fasterxml/Zor/Zyg;Ljava/lang/Object;Ljava/lang/String;)V
    //   262: aload_3
    //   263: ifnull -> 333
    //   266: goto -> 273
    //   269: invokestatic a : (Ljava/lang/Exception;)Ljava/lang/Exception;
    //   272: athrow
    //   273: aload #4
    //   275: aload #7
    //   277: invokevirtual ZY : (Ljava/lang/String;)V
    //   280: aload #4
    //   282: aload_1
    //   283: invokevirtual ZE : (Lcom/fasterxml/Zb/Zg;)V
    //   286: aload_0
    //   287: getfield ZA : Lcom/fasterxml/Zo/Zl;
    //   290: ifnull -> 333
    //   293: goto -> 300
    //   296: invokestatic a : (Ljava/lang/Exception;)Ljava/lang/Exception;
    //   299: athrow
    //   300: aload_0
    //   301: getfield ZA : Lcom/fasterxml/Zo/Zl;
    //   304: aload_1
    //   305: aload_2
    //   306: aload #5
    //   308: aload #7
    //   310: invokevirtual ZU : (Lcom/fasterxml/Zb/Zg;Lcom/fasterxml/Zor/Zyg;Ljava/lang/Object;Ljava/lang/String;)V
    //   313: goto -> 333
    //   316: astore #9
    //   318: aload_0
    //   319: aload #9
    //   321: aload #5
    //   323: aload #7
    //   325: aload_2
    //   326: invokevirtual Zd : (Ljava/lang/Throwable;Ljava/lang/Object;Ljava/lang/String;Lcom/fasterxml/Zor/Zyg;)Ljava/lang/Object;
    //   329: pop
    //   330: goto -> 333
    //   333: aload_1
    //   334: invokevirtual ZV : ()Lcom/fasterxml/Zb/Zl;
    //   337: pop
    //   338: aload_3
    //   339: ifnull -> 115
    //   342: aload #4
    //   344: invokevirtual Zh : ()V
    //   347: aload_0
    //   348: getfield ZL : Lcom/fasterxml/Ze/Zo1;
    //   351: aload_1
    //   352: aload_2
    //   353: aload #5
    //   355: aload #4
    //   357: invokevirtual ZY : (Lcom/fasterxml/Zb/Zg;Lcom/fasterxml/Zor/Zyg;Ljava/lang/Object;Lcom/fasterxml/Zm/Zl;)Ljava/lang/Object;
    //   360: areturn
    // Exception table:
    //   from	to	target	type
    //   4	29	29	java/lang/Exception
    //   33	47	47	java/lang/Exception
    //   73	87	90	java/lang/Exception
    //   94	108	108	java/lang/Exception
    //   147	157	160	java/lang/Exception
    //   152	174	177	java/lang/Exception
    //   164	190	193	java/lang/Exception
    //   197	208	211	java/lang/Exception
    //   213	245	248	java/lang/Exception
    //   229	266	269	java/lang/Exception
    //   252	293	296	java/lang/Exception
    //   300	313	316	java/lang/Exception
  }
  
  protected Object ZL(Zg paramZg, Zyg paramZyg) throws IOException {
    // Byte code:
    //   0: invokestatic ZP : ()Ljava/lang/String;
    //   3: aload_0
    //   4: getfield ZT : Lcom/fasterxml/Ze/Zc;
    //   7: astore #4
    //   9: aload #4
    //   11: aload_1
    //   12: aload_2
    //   13: aload_0
    //   14: getfield ZZ : Lcom/fasterxml/Ze/Zz;
    //   17: invokevirtual Zn : (Lcom/fasterxml/Zb/Zg;Lcom/fasterxml/Zor/Zyg;Lcom/fasterxml/Ze/Zz;)Lcom/fasterxml/Ze/Zok;
    //   20: astore #5
    //   22: astore_3
    //   23: aload_2
    //   24: aload_1
    //   25: invokevirtual Zb : (Lcom/fasterxml/Zb/Zg;)Lcom/fasterxml/Zm/Zl;
    //   28: astore #6
    //   30: aload #6
    //   32: invokevirtual ZJ : ()V
    //   35: aconst_null
    //   36: astore #7
    //   38: aload_1
    //   39: invokevirtual Zh : ()Lcom/fasterxml/Zb/Zl;
    //   42: astore #8
    //   44: aload #8
    //   46: getstatic com/fasterxml/Zb/Zl.FIELD_NAME : Lcom/fasterxml/Zb/Zl;
    //   49: if_acmpne -> 386
    //   52: aload_1
    //   53: invokevirtual ZS : ()Ljava/lang/String;
    //   56: astore #9
    //   58: aload_1
    //   59: invokevirtual ZV : ()Lcom/fasterxml/Zb/Zl;
    //   62: pop
    //   63: aload #4
    //   65: aload #9
    //   67: invokevirtual ZO : (Ljava/lang/String;)Lcom/fasterxml/Zo/Zv;
    //   70: astore #10
    //   72: aload #5
    //   74: aload #9
    //   76: invokevirtual Zw : (Ljava/lang/String;)Z
    //   79: ifeq -> 105
    //   82: aload #10
    //   84: ifnonnull -> 105
    //   87: goto -> 94
    //   90: invokestatic a : (Ljava/lang/Exception;)Ljava/lang/Exception;
    //   93: athrow
    //   94: aload_3
    //   95: ifnull -> 376
    //   98: goto -> 105
    //   101: invokestatic a : (Ljava/lang/Exception;)Ljava/lang/Exception;
    //   104: athrow
    //   105: aload #10
    //   107: ifnull -> 235
    //   110: goto -> 117
    //   113: invokestatic a : (Ljava/lang/Exception;)Ljava/lang/Exception;
    //   116: athrow
    //   117: aload #5
    //   119: aload #10
    //   121: aload #10
    //   123: aload_1
    //   124: aload_2
    //   125: invokevirtual Zt : (Lcom/fasterxml/Zb/Zg;Lcom/fasterxml/Zor/Zyg;)Ljava/lang/Object;
    //   128: invokevirtual Zr : (Lcom/fasterxml/Zo/Zv;Ljava/lang/Object;)Z
    //   131: ifeq -> 376
    //   134: goto -> 141
    //   137: invokestatic a : (Ljava/lang/Exception;)Ljava/lang/Exception;
    //   140: athrow
    //   141: aload_1
    //   142: invokevirtual ZV : ()Lcom/fasterxml/Zb/Zl;
    //   145: astore #8
    //   147: aload #4
    //   149: aload_2
    //   150: aload #5
    //   152: invokevirtual ZP : (Lcom/fasterxml/Zor/Zyg;Lcom/fasterxml/Ze/Zok;)Ljava/lang/Object;
    //   155: astore #7
    //   157: goto -> 183
    //   160: astore #11
    //   162: aload_0
    //   163: aload #11
    //   165: aload_0
    //   166: getfield ZF : Lcom/fasterxml/Zor/Zk;
    //   169: invokevirtual Zf : ()Ljava/lang/Class;
    //   172: aload #9
    //   174: aload_2
    //   175: invokevirtual Zd : (Ljava/lang/Throwable;Ljava/lang/Object;Ljava/lang/String;Lcom/fasterxml/Zor/Zyg;)Ljava/lang/Object;
    //   178: pop
    //   179: aload_3
    //   180: ifnull -> 376
    //   183: aload #7
    //   185: invokevirtual getClass : ()Ljava/lang/Class;
    //   188: aload_0
    //   189: getfield ZF : Lcom/fasterxml/Zor/Zk;
    //   192: invokevirtual Zf : ()Ljava/lang/Class;
    //   195: if_acmpeq -> 224
    //   198: goto -> 205
    //   201: invokestatic a : (Ljava/lang/Exception;)Ljava/lang/Exception;
    //   204: athrow
    //   205: aload_0
    //   206: aload_1
    //   207: aload_2
    //   208: aload_1
    //   209: invokevirtual ZG : ()Lcom/fasterxml/Zb/Z_;
    //   212: aload #7
    //   214: aload #6
    //   216: invokevirtual Zg : (Lcom/fasterxml/Zb/Zg;Lcom/fasterxml/Zor/Zyg;Lcom/fasterxml/Zb/Z_;Ljava/lang/Object;Lcom/fasterxml/Zm/Zl;)Ljava/lang/Object;
    //   219: areturn
    //   220: invokestatic a : (Ljava/lang/Exception;)Ljava/lang/Exception;
    //   223: athrow
    //   224: aload_0
    //   225: aload_1
    //   226: aload_2
    //   227: aload #7
    //   229: aload #6
    //   231: invokevirtual Zc : (Lcom/fasterxml/Zb/Zg;Lcom/fasterxml/Zor/Zyg;Ljava/lang/Object;Lcom/fasterxml/Zm/Zl;)Ljava/lang/Object;
    //   234: areturn
    //   235: aload_0
    //   236: getfield ZX : Lcom/fasterxml/Ze/Zo8;
    //   239: aload #9
    //   241: invokevirtual ZI : (Ljava/lang/String;)Lcom/fasterxml/Zo/Zv;
    //   244: astore #11
    //   246: aload #11
    //   248: ifnull -> 276
    //   251: aload #5
    //   253: aload #11
    //   255: aload #11
    //   257: aload_1
    //   258: aload_2
    //   259: invokevirtual Zt : (Lcom/fasterxml/Zb/Zg;Lcom/fasterxml/Zor/Zyg;)Ljava/lang/Object;
    //   262: invokevirtual ZR : (Lcom/fasterxml/Zo/Zv;Ljava/lang/Object;)V
    //   265: aload_3
    //   266: ifnull -> 376
    //   269: goto -> 276
    //   272: invokestatic a : (Ljava/lang/Exception;)Ljava/lang/Exception;
    //   275: athrow
    //   276: aload #9
    //   278: aload_0
    //   279: getfield Zq : Ljava/util/Set;
    //   282: aload_0
    //   283: getfield ZP : Ljava/util/Set;
    //   286: invokestatic Zv : (Ljava/lang/Object;Ljava/util/Collection;Ljava/util/Collection;)Z
    //   289: ifeq -> 322
    //   292: goto -> 299
    //   295: invokestatic a : (Ljava/lang/Exception;)Ljava/lang/Exception;
    //   298: athrow
    //   299: aload_0
    //   300: aload_1
    //   301: aload_2
    //   302: aload_0
    //   303: invokevirtual ZX : ()Ljava/lang/Class;
    //   306: aload #9
    //   308: invokevirtual ZC : (Lcom/fasterxml/Zb/Zg;Lcom/fasterxml/Zor/Zyg;Ljava/lang/Object;Ljava/lang/String;)V
    //   311: aload_3
    //   312: ifnull -> 376
    //   315: goto -> 322
    //   318: invokestatic a : (Ljava/lang/Exception;)Ljava/lang/Exception;
    //   321: athrow
    //   322: aload #6
    //   324: aload #9
    //   326: invokevirtual ZY : (Ljava/lang/String;)V
    //   329: aload #6
    //   331: aload_1
    //   332: invokevirtual ZE : (Lcom/fasterxml/Zb/Zg;)V
    //   335: aload_0
    //   336: getfield ZA : Lcom/fasterxml/Zo/Zl;
    //   339: ifnull -> 376
    //   342: goto -> 349
    //   345: invokestatic a : (Ljava/lang/Exception;)Ljava/lang/Exception;
    //   348: athrow
    //   349: aload #5
    //   351: aload_0
    //   352: getfield ZA : Lcom/fasterxml/Zo/Zl;
    //   355: aload #9
    //   357: aload_0
    //   358: getfield ZA : Lcom/fasterxml/Zo/Zl;
    //   361: aload_1
    //   362: aload_2
    //   363: invokevirtual ZZ : (Lcom/fasterxml/Zb/Zg;Lcom/fasterxml/Zor/Zyg;)Ljava/lang/Object;
    //   366: invokevirtual Zk : (Lcom/fasterxml/Zo/Zl;Ljava/lang/String;Ljava/lang/Object;)V
    //   369: goto -> 376
    //   372: invokestatic a : (Ljava/lang/Exception;)Ljava/lang/Exception;
    //   375: athrow
    //   376: aload_1
    //   377: invokevirtual ZV : ()Lcom/fasterxml/Zb/Zl;
    //   380: astore #8
    //   382: aload_3
    //   383: ifnull -> 44
    //   386: aload #6
    //   388: invokevirtual Zh : ()V
    //   391: aload #7
    //   393: ifnonnull -> 419
    //   396: aload #4
    //   398: aload_2
    //   399: aload #5
    //   401: invokevirtual ZP : (Lcom/fasterxml/Zor/Zyg;Lcom/fasterxml/Ze/Zok;)Ljava/lang/Object;
    //   404: astore #7
    //   406: goto -> 419
    //   409: astore #9
    //   411: aload_0
    //   412: aload #9
    //   414: aload_2
    //   415: invokevirtual ZR : (Ljava/lang/Throwable;Lcom/fasterxml/Zor/Zyg;)Ljava/lang/Object;
    //   418: areturn
    //   419: aload_0
    //   420: getfield ZL : Lcom/fasterxml/Ze/Zo1;
    //   423: aload_1
    //   424: aload_2
    //   425: aload #7
    //   427: aload #6
    //   429: invokevirtual ZY : (Lcom/fasterxml/Zb/Zg;Lcom/fasterxml/Zor/Zyg;Ljava/lang/Object;Lcom/fasterxml/Zm/Zl;)Ljava/lang/Object;
    //   432: areturn
    // Exception table:
    //   from	to	target	type
    //   72	87	90	java/lang/Exception
    //   82	98	101	java/lang/Exception
    //   94	110	113	java/lang/Exception
    //   105	134	137	java/lang/Exception
    //   147	157	160	java/lang/Exception
    //   162	198	201	java/lang/Exception
    //   183	220	220	java/lang/Exception
    //   246	269	272	java/lang/Exception
    //   251	292	295	java/lang/Exception
    //   276	315	318	java/lang/Exception
    //   299	342	345	java/lang/Exception
    //   322	369	372	java/lang/Exception
    //   396	406	409	java/lang/Exception
  }
  
  protected Object Zc(Zg paramZg, Zyg paramZyg, Object paramObject, Zl paramZl) throws IOException {
    // Byte code:
    //   0: invokestatic ZP : ()Ljava/lang/String;
    //   3: astore #5
    //   5: aload_0
    //   6: getfield Zk : Z
    //   9: ifeq -> 23
    //   12: aload_2
    //   13: invokevirtual Zx : ()Ljava/lang/Class;
    //   16: goto -> 24
    //   19: invokestatic a : (Ljava/lang/Exception;)Ljava/lang/Exception;
    //   22: athrow
    //   23: aconst_null
    //   24: astore #6
    //   26: aload_1
    //   27: invokevirtual Zh : ()Lcom/fasterxml/Zb/Zl;
    //   30: astore #7
    //   32: aload #7
    //   34: getstatic com/fasterxml/Zb/Zl.FIELD_NAME : Lcom/fasterxml/Zb/Zl;
    //   37: if_acmpne -> 244
    //   40: aload_1
    //   41: invokevirtual ZS : ()Ljava/lang/String;
    //   44: astore #8
    //   46: aload_0
    //   47: getfield ZX : Lcom/fasterxml/Ze/Zo8;
    //   50: aload #8
    //   52: invokevirtual ZI : (Ljava/lang/String;)Lcom/fasterxml/Zo/Zv;
    //   55: astore #9
    //   57: aload_1
    //   58: invokevirtual ZV : ()Lcom/fasterxml/Zb/Zl;
    //   61: pop
    //   62: aload #9
    //   64: ifnull -> 143
    //   67: aload #6
    //   69: ifnull -> 113
    //   72: goto -> 79
    //   75: invokestatic a : (Ljava/lang/Exception;)Ljava/lang/Exception;
    //   78: athrow
    //   79: aload #9
    //   81: aload #6
    //   83: invokevirtual Zj : (Ljava/lang/Class;)Z
    //   86: ifne -> 113
    //   89: goto -> 96
    //   92: invokestatic a : (Ljava/lang/Exception;)Ljava/lang/Exception;
    //   95: athrow
    //   96: aload_1
    //   97: invokevirtual Zc : ()Lcom/fasterxml/Zb/Zg;
    //   100: pop
    //   101: aload #5
    //   103: ifnull -> 233
    //   106: goto -> 113
    //   109: invokestatic a : (Ljava/lang/Exception;)Ljava/lang/Exception;
    //   112: athrow
    //   113: aload #9
    //   115: aload_1
    //   116: aload_2
    //   117: aload_3
    //   118: invokevirtual ZR : (Lcom/fasterxml/Zb/Zg;Lcom/fasterxml/Zor/Zyg;Ljava/lang/Object;)Ljava/lang/Object;
    //   121: astore_3
    //   122: goto -> 233
    //   125: astore #10
    //   127: aload_0
    //   128: aload #10
    //   130: aload_3
    //   131: aload #8
    //   133: aload_2
    //   134: invokevirtual Zd : (Ljava/lang/Throwable;Ljava/lang/Object;Ljava/lang/String;Lcom/fasterxml/Zor/Zyg;)Ljava/lang/Object;
    //   137: pop
    //   138: aload #5
    //   140: ifnull -> 233
    //   143: aload #8
    //   145: aload_0
    //   146: getfield Zq : Ljava/util/Set;
    //   149: aload_0
    //   150: getfield ZP : Ljava/util/Set;
    //   153: invokestatic Zv : (Ljava/lang/Object;Ljava/util/Collection;Ljava/util/Collection;)Z
    //   156: ifeq -> 187
    //   159: goto -> 166
    //   162: invokestatic a : (Ljava/lang/Exception;)Ljava/lang/Exception;
    //   165: athrow
    //   166: aload_0
    //   167: aload_1
    //   168: aload_2
    //   169: aload_3
    //   170: aload #8
    //   172: invokevirtual ZC : (Lcom/fasterxml/Zb/Zg;Lcom/fasterxml/Zor/Zyg;Ljava/lang/Object;Ljava/lang/String;)V
    //   175: aload #5
    //   177: ifnull -> 233
    //   180: goto -> 187
    //   183: invokestatic a : (Ljava/lang/Exception;)Ljava/lang/Exception;
    //   186: athrow
    //   187: aload #4
    //   189: aload #8
    //   191: invokevirtual ZY : (Ljava/lang/String;)V
    //   194: aload #4
    //   196: aload_1
    //   197: invokevirtual ZE : (Lcom/fasterxml/Zb/Zg;)V
    //   200: aload_0
    //   201: getfield ZA : Lcom/fasterxml/Zo/Zl;
    //   204: ifnull -> 233
    //   207: goto -> 214
    //   210: invokestatic a : (Ljava/lang/Exception;)Ljava/lang/Exception;
    //   213: athrow
    //   214: aload_0
    //   215: getfield ZA : Lcom/fasterxml/Zo/Zl;
    //   218: aload_1
    //   219: aload_2
    //   220: aload_3
    //   221: aload #8
    //   223: invokevirtual ZU : (Lcom/fasterxml/Zb/Zg;Lcom/fasterxml/Zor/Zyg;Ljava/lang/Object;Ljava/lang/String;)V
    //   226: goto -> 233
    //   229: invokestatic a : (Ljava/lang/Exception;)Ljava/lang/Exception;
    //   232: athrow
    //   233: aload_1
    //   234: invokevirtual ZV : ()Lcom/fasterxml/Zb/Zl;
    //   237: astore #7
    //   239: aload #5
    //   241: ifnull -> 32
    //   244: aload #4
    //   246: invokevirtual Zh : ()V
    //   249: aload_0
    //   250: getfield ZL : Lcom/fasterxml/Ze/Zo1;
    //   253: aload_1
    //   254: aload_2
    //   255: aload_3
    //   256: aload #4
    //   258: invokevirtual ZY : (Lcom/fasterxml/Zb/Zg;Lcom/fasterxml/Zor/Zyg;Ljava/lang/Object;Lcom/fasterxml/Zm/Zl;)Ljava/lang/Object;
    //   261: areturn
    // Exception table:
    //   from	to	target	type
    //   5	19	19	java/lang/Exception
    //   57	72	75	java/lang/Exception
    //   67	89	92	java/lang/Exception
    //   79	106	109	java/lang/Exception
    //   113	122	125	java/lang/Exception
    //   127	159	162	java/lang/Exception
    //   143	180	183	java/lang/Exception
    //   166	207	210	java/lang/Exception
    //   187	226	229	java/lang/Exception
  }
  
  protected Object ZW(Zg paramZg, Zyg paramZyg) throws IOException {
    try {
      if (this.ZT != null)
        return Zl(paramZg, paramZyg); 
    } catch (IOException iOException) {
      throw a(null);
    } 
    return Zz(paramZg, paramZyg, this.Zb.Zy(paramZyg));
  }
  
  protected Object Zz(Zg paramZg, Zyg paramZyg, Object paramObject) throws IOException {
    // Byte code:
    //   0: invokestatic ZP : ()Ljava/lang/String;
    //   3: astore #4
    //   5: aload_0
    //   6: getfield Zk : Z
    //   9: ifeq -> 23
    //   12: aload_2
    //   13: invokevirtual Zx : ()Ljava/lang/Class;
    //   16: goto -> 24
    //   19: invokestatic a : (Ljava/lang/Exception;)Ljava/lang/Exception;
    //   22: athrow
    //   23: aconst_null
    //   24: astore #5
    //   26: aload_0
    //   27: getfield Zv : Lcom/fasterxml/Ze/Zoq;
    //   30: invokevirtual Zn : ()Lcom/fasterxml/Ze/Zoq;
    //   33: astore #6
    //   35: aload_1
    //   36: invokevirtual Zh : ()Lcom/fasterxml/Zb/Zl;
    //   39: astore #7
    //   41: aload #7
    //   43: getstatic com/fasterxml/Zb/Zl.FIELD_NAME : Lcom/fasterxml/Zb/Zl;
    //   46: if_acmpne -> 329
    //   49: aload_1
    //   50: invokevirtual ZS : ()Ljava/lang/String;
    //   53: astore #8
    //   55: aload_1
    //   56: invokevirtual ZV : ()Lcom/fasterxml/Zb/Zl;
    //   59: astore #7
    //   61: aload_0
    //   62: getfield ZX : Lcom/fasterxml/Ze/Zo8;
    //   65: aload #8
    //   67: invokevirtual ZI : (Ljava/lang/String;)Lcom/fasterxml/Zo/Zv;
    //   70: astore #9
    //   72: aload #9
    //   74: ifnull -> 179
    //   77: aload #7
    //   79: invokevirtual Zl : ()Z
    //   82: ifeq -> 110
    //   85: goto -> 92
    //   88: invokestatic a : (Ljava/lang/Exception;)Ljava/lang/Exception;
    //   91: athrow
    //   92: aload #6
    //   94: aload_1
    //   95: aload_2
    //   96: aload #8
    //   98: aload_3
    //   99: invokevirtual ZQ : (Lcom/fasterxml/Zb/Zg;Lcom/fasterxml/Zor/Zyg;Ljava/lang/String;Ljava/lang/Object;)Z
    //   102: pop
    //   103: goto -> 110
    //   106: invokestatic a : (Ljava/lang/Exception;)Ljava/lang/Exception;
    //   109: athrow
    //   110: aload #5
    //   112: ifnull -> 149
    //   115: aload #9
    //   117: aload #5
    //   119: invokevirtual Zj : (Ljava/lang/Class;)Z
    //   122: ifne -> 149
    //   125: goto -> 132
    //   128: invokestatic a : (Ljava/lang/Exception;)Ljava/lang/Exception;
    //   131: athrow
    //   132: aload_1
    //   133: invokevirtual Zc : ()Lcom/fasterxml/Zb/Zg;
    //   136: pop
    //   137: aload #4
    //   139: ifnull -> 318
    //   142: goto -> 149
    //   145: invokestatic a : (Ljava/lang/Exception;)Ljava/lang/Exception;
    //   148: athrow
    //   149: aload #9
    //   151: aload_1
    //   152: aload_2
    //   153: aload_3
    //   154: invokevirtual ZR : (Lcom/fasterxml/Zb/Zg;Lcom/fasterxml/Zor/Zyg;Ljava/lang/Object;)Ljava/lang/Object;
    //   157: astore_3
    //   158: goto -> 318
    //   161: astore #10
    //   163: aload_0
    //   164: aload #10
    //   166: aload_3
    //   167: aload #8
    //   169: aload_2
    //   170: invokevirtual Zd : (Ljava/lang/Throwable;Ljava/lang/Object;Ljava/lang/String;Lcom/fasterxml/Zor/Zyg;)Ljava/lang/Object;
    //   173: pop
    //   174: aload #4
    //   176: ifnull -> 318
    //   179: aload #8
    //   181: aload_0
    //   182: getfield Zq : Ljava/util/Set;
    //   185: aload_0
    //   186: getfield ZP : Ljava/util/Set;
    //   189: invokestatic Zv : (Ljava/lang/Object;Ljava/util/Collection;Ljava/util/Collection;)Z
    //   192: ifeq -> 223
    //   195: goto -> 202
    //   198: invokestatic a : (Ljava/lang/Exception;)Ljava/lang/Exception;
    //   201: athrow
    //   202: aload_0
    //   203: aload_1
    //   204: aload_2
    //   205: aload_3
    //   206: aload #8
    //   208: invokevirtual ZC : (Lcom/fasterxml/Zb/Zg;Lcom/fasterxml/Zor/Zyg;Ljava/lang/Object;Ljava/lang/String;)V
    //   211: aload #4
    //   213: ifnull -> 318
    //   216: goto -> 223
    //   219: invokestatic a : (Ljava/lang/Exception;)Ljava/lang/Exception;
    //   222: athrow
    //   223: aload #6
    //   225: aload_1
    //   226: aload_2
    //   227: aload #8
    //   229: aload_3
    //   230: invokevirtual Zf : (Lcom/fasterxml/Zb/Zg;Lcom/fasterxml/Zor/Zyg;Ljava/lang/String;Ljava/lang/Object;)Z
    //   233: ifeq -> 255
    //   236: goto -> 243
    //   239: invokestatic a : (Ljava/lang/Exception;)Ljava/lang/Exception;
    //   242: athrow
    //   243: aload #4
    //   245: ifnull -> 318
    //   248: goto -> 255
    //   251: invokestatic a : (Ljava/lang/Exception;)Ljava/lang/Exception;
    //   254: athrow
    //   255: aload_0
    //   256: getfield ZA : Lcom/fasterxml/Zo/Zl;
    //   259: ifnull -> 302
    //   262: goto -> 269
    //   265: invokestatic a : (Ljava/lang/Exception;)Ljava/lang/Exception;
    //   268: athrow
    //   269: aload_0
    //   270: getfield ZA : Lcom/fasterxml/Zo/Zl;
    //   273: aload_1
    //   274: aload_2
    //   275: aload_3
    //   276: aload #8
    //   278: invokevirtual ZU : (Lcom/fasterxml/Zb/Zg;Lcom/fasterxml/Zor/Zyg;Ljava/lang/Object;Ljava/lang/String;)V
    //   281: goto -> 318
    //   284: astore #10
    //   286: aload_0
    //   287: aload #10
    //   289: aload_3
    //   290: aload #8
    //   292: aload_2
    //   293: invokevirtual Zd : (Ljava/lang/Throwable;Ljava/lang/Object;Ljava/lang/String;Lcom/fasterxml/Zor/Zyg;)Ljava/lang/Object;
    //   296: pop
    //   297: aload #4
    //   299: ifnull -> 318
    //   302: aload_0
    //   303: aload_1
    //   304: aload_2
    //   305: aload_3
    //   306: aload #8
    //   308: invokevirtual Zb : (Lcom/fasterxml/Zb/Zg;Lcom/fasterxml/Zor/Zyg;Ljava/lang/Object;Ljava/lang/String;)V
    //   311: goto -> 318
    //   314: invokestatic a : (Ljava/lang/Exception;)Ljava/lang/Exception;
    //   317: athrow
    //   318: aload_1
    //   319: invokevirtual ZV : ()Lcom/fasterxml/Zb/Zl;
    //   322: astore #7
    //   324: aload #4
    //   326: ifnull -> 41
    //   329: aload #6
    //   331: aload_1
    //   332: aload_2
    //   333: aload_3
    //   334: invokevirtual Zb : (Lcom/fasterxml/Zb/Zg;Lcom/fasterxml/Zor/Zyg;Ljava/lang/Object;)Ljava/lang/Object;
    //   337: areturn
    // Exception table:
    //   from	to	target	type
    //   5	19	19	java/lang/Exception
    //   72	85	88	java/lang/Exception
    //   77	103	106	java/lang/Exception
    //   110	125	128	java/lang/Exception
    //   115	142	145	java/lang/Exception
    //   149	158	161	java/lang/Exception
    //   163	195	198	java/lang/Exception
    //   179	216	219	java/lang/Exception
    //   202	236	239	java/lang/Exception
    //   223	248	251	java/lang/Exception
    //   243	262	265	java/lang/Exception
    //   269	281	284	java/lang/Exception
    //   286	311	314	java/lang/Exception
  }
  
  protected Object Zl(Zg paramZg, Zyg paramZyg) throws IOException {
    Zk zk = this.Zw;
    return paramZyg.Zm(zk, String.format(d(-7121, -19814), new Object[] { zk }));
  }
  
  private static Exception a(Exception paramException) {
    return paramException;
  }
  
  static {
    // Byte code:
    //   0: iconst_5
    //   1: anewarray java/lang/String
    //   4: astore #5
    //   6: iconst_0
    //   7: istore_3
    //   8: ldc 'VAcf"\\r^'OJr1lvQr]H-}C4KhgPMmp= lKvz+|X&2; -8::1&!P4(D\\nGB]_>yZ_bbuiYiG:&qc1iSAw^t4_$8\\tMJqttX}o;Y\\td[9Q/5XckDD9\\rW'
    //   10: dup
    //   11: astore_2
    //   12: invokevirtual length : ()I
    //   15: istore #4
    //   17: sipush #171
    //   20: istore_1
    //   21: iconst_m1
    //   22: istore_0
    //   23: bipush #119
    //   25: iinc #0, 1
    //   28: aload_2
    //   29: iload_0
    //   30: dup
    //   31: iload_1
    //   32: iadd
    //   33: invokevirtual substring : (II)Ljava/lang/String;
    //   36: iconst_m1
    //   37: goto -> 142
    //   40: aload #5
    //   42: swap
    //   43: iload_3
    //   44: iinc #3, 1
    //   47: swap
    //   48: aastore
    //   49: iload_0
    //   50: iload_1
    //   51: iadd
    //   52: dup
    //   53: istore_0
    //   54: iload #4
    //   56: if_icmpge -> 68
    //   59: aload_2
    //   60: iload_0
    //   61: invokevirtual charAt : (I)C
    //   64: istore_1
    //   65: goto -> 23
    //   68: ldc ';+~Y.lvE_<P,LZQWs7U[U<giRfX vS\\n_)Rd]Gd5i*i!\\fbE#O- {Mg(#%/'
    //   70: dup
    //   71: astore_2
    //   72: invokevirtual length : ()I
    //   75: istore #4
    //   77: bipush #72
    //   79: istore_1
    //   80: iconst_m1
    //   81: istore_0
    //   82: bipush #93
    //   84: iinc #0, 1
    //   87: aload_2
    //   88: iload_0
    //   89: dup
    //   90: iload_1
    //   91: iadd
    //   92: invokevirtual substring : (II)Ljava/lang/String;
    //   95: iconst_0
    //   96: goto -> 142
    //   99: aload #5
    //   101: swap
    //   102: iload_3
    //   103: iinc #3, 1
    //   106: swap
    //   107: aastore
    //   108: iload_0
    //   109: iload_1
    //   110: iadd
    //   111: dup
    //   112: istore_0
    //   113: iload #4
    //   115: if_icmpge -> 127
    //   118: aload_2
    //   119: iload_0
    //   120: invokevirtual charAt : (I)C
    //   123: istore_1
    //   124: goto -> 82
    //   127: aload #5
    //   129: putstatic com/fasterxml/Zo/Zd.g : [Ljava/lang/String;
    //   132: iconst_5
    //   133: anewarray java/lang/String
    //   136: putstatic com/fasterxml/Zo/Zd.h : [Ljava/lang/String;
    //   139: goto -> 300
    //   142: dup_x2
    //   143: pop
    //   144: invokevirtual toCharArray : ()[C
    //   147: dup_x1
    //   148: arraylength
    //   149: dup_x2
    //   150: pop
    //   151: iconst_0
    //   152: istore #6
    //   154: dup2_x1
    //   155: pop2
    //   156: dup_x2
    //   157: iconst_1
    //   158: if_icmpgt -> 260
    //   161: dup2
    //   162: swap
    //   163: iload #6
    //   165: dup2_x1
    //   166: caload
    //   167: swap
    //   168: iload #6
    //   170: bipush #7
    //   172: irem
    //   173: tableswitch default -> 242, 0 -> 212, 1 -> 217, 2 -> 222, 3 -> 227, 4 -> 232, 5 -> 237
    //   212: bipush #25
    //   214: goto -> 244
    //   217: bipush #118
    //   219: goto -> 244
    //   222: bipush #61
    //   224: goto -> 244
    //   227: bipush #80
    //   229: goto -> 244
    //   232: bipush #11
    //   234: goto -> 244
    //   237: bipush #52
    //   239: goto -> 244
    //   242: bipush #115
    //   244: ixor
    //   245: ixor
    //   246: i2c
    //   247: castore
    //   248: iinc #6, 1
    //   251: dup
    //   252: ifne -> 260
    //   255: dup2
    //   256: dup_x1
    //   257: goto -> 165
    //   260: dup2_x1
    //   261: pop2
    //   262: dup_x2
    //   263: iload #6
    //   265: if_icmpgt -> 161
    //   268: pop
    //   269: new java/lang/String
    //   272: dup_x1
    //   273: swap
    //   274: invokespecial <init> : ([C)V
    //   277: invokevirtual intern : ()Ljava/lang/String;
    //   280: swap
    //   281: pop
    //   282: swap
    //   283: tableswitch default -> 40, 0 -> 99
    //   300: return
  }
  
  private static String d(int paramInt1, int paramInt2) {
    int i = (paramInt1 ^ 0xFFFFE42B) & 0xFFFF;
    if (h[i] == null) {
      char[] arrayOfChar = g[i].toCharArray();
      switch (arrayOfChar[0] & 0xFF) {
        case 0:
        
        case 1:
        
        case 2:
        
        case 3:
        
        case 4:
        
        case 5:
        
        case 6:
        
        case 7:
        
        case 8:
        
        case 9:
        
        case 10:
        
        case 11:
        
        case 12:
        
        case 13:
        
        case 14:
        
        case 15:
        
        case 16:
        
        case 17:
        
        case 18:
        
        case 19:
        
        case 20:
        
        case 21:
        
        case 22:
        
        case 23:
        
        case 24:
        
        case 25:
        
        case 26:
        
        case 27:
        
        case 28:
        
        case 29:
        
        case 30:
        
        case 31:
        
        case 32:
        
        case 33:
        
        case 34:
        
        case 35:
        
        case 36:
        
        case 37:
        
        case 38:
        
        case 39:
        
        case 40:
        
        case 41:
        
        case 42:
        
        case 43:
        
        case 44:
        
        case 45:
        
        case 46:
        
        case 47:
        
        case 48:
        
        case 49:
        
        case 50:
        
        case 51:
        
        case 52:
        
        case 53:
        
        case 54:
        
        case 55:
        
        case 56:
        
        case 57:
        
        case 58:
        
        case 59:
        
        case 60:
        
        case 61:
        
        case 62:
        
        case 63:
        
        case 64:
        
        case 65:
        
        case 66:
        
        case 67:
        
        case 68:
        
        case 69:
        
        case 70:
        
        case 71:
        
        case 72:
        
        case 73:
        
        case 74:
        
        case 75:
        
        case 76:
        
        case 77:
        
        case 78:
        
        case 79:
        
        case 80:
        
        case 81:
        
        case 82:
        
        case 83:
        
        case 84:
        
        case 85:
        
        case 86:
        
        case 87:
        
        case 88:
        
        case 89:
        
        case 90:
        
        case 91:
        
        case 92:
        
        case 93:
        
        case 94:
        
        case 95:
        
        case 96:
        
        case 97:
        
        case 98:
        
        case 99:
        
        case 100:
        
        case 101:
        
        case 102:
        
        case 103:
        
        case 104:
        
        case 105:
        
        case 106:
        
        case 107:
        
        case 108:
        
        case 109:
        
        case 110:
        
        case 111:
        
        case 112:
        
        case 113:
        
        case 114:
        
        case 115:
        
        case 116:
        
        case 117:
        
        case 118:
        
        case 119:
        
        case 120:
        
        case 121:
        
        case 122:
        
        case 123:
        
        case 124:
        
        case 125:
        
        case 126:
        
        case 127:
        
        case 128:
        
        case 129:
        
        case 130:
        
        case 131:
        
        case 132:
        
        case 133:
        
        case 134:
        
        case 135:
        
        case 136:
        
        case 137:
        
        case 138:
        
        case 139:
        
        case 140:
        
        case 141:
        
        case 142:
        
        case 143:
        
        case 144:
        
        case 145:
        
        case 146:
        
        case 147:
        
        case 148:
        
        case 149:
        
        case 150:
        
        case 151:
        
        case 152:
        
        case 153:
        
        case 154:
        
        case 155:
        
        case 156:
        
        case 157:
        
        case 158:
        
        case 159:
        
        case 160:
        
        case 161:
        
        case 162:
        
        case 163:
        
        case 164:
        
        case 165:
        
        case 166:
        
        case 167:
        
        case 168:
        
        case 169:
        
        case 170:
        
        case 171:
        
        case 172:
        
        case 173:
        
        case 174:
        
        case 175:
        
        case 176:
        
        case 177:
        
        case 178:
        
        case 179:
        
        case 180:
        
        case 181:
        
        case 182:
        
        case 183:
        
        case 184:
        
        case 185:
        
        case 186:
        
        case 187:
        
        case 188:
        
        case 189:
        
        case 190:
        
        case 191:
        
        case 192:
        
        case 193:
        
        case 194:
        
        case 195:
        
        case 196:
        
        case 197:
        
        case 198:
        
        case 199:
        
        case 200:
        
        case 201:
        
        case 202:
        
        case 203:
        
        case 204:
        
        case 205:
        
        case 206:
        
        case 207:
        
        case 208:
        
        case 209:
        
        case 210:
        
        case 211:
        
        case 212:
        
        case 213:
        
        case 214:
        
        case 215:
        
        case 216:
        
        case 217:
        
        case 218:
        
        case 219:
        
        case 220:
        
        case 221:
        
        case 222:
        
        case 223:
        
        case 224:
        
        case 225:
        
        case 226:
        
        case 227:
        
        case 228:
        
        case 229:
        
        case 230:
        
        case 231:
        
        case 232:
        
        case 233:
        
        case 234:
        
        case 235:
        
        case 236:
        
        case 237:
        
        case 238:
        
        case 239:
        
        case 240:
        
        case 241:
        
        case 242:
        
        case 243:
        
        case 244:
        
        case 245:
        
        case 246:
        
        case 247:
        
        case 248:
        
        case 249:
        
        case 250:
        
        case 251:
        
        case 252:
        
        case 253:
        
        case 254:
        
        default:
          break;
      } 
      char c = '';
      int j = (paramInt2 & 0xFF) - c;
      if (j < 0)
        j += 256; 
      int k = ((paramInt2 & 0xFFFF) >>> 8) - c;
      if (k < 0)
        k += 256; 
      for (byte b = 0; b < arrayOfChar.length; b++) {
        int m = b % 2;
        if (m == 0) {
          arrayOfChar[b] = (char)(arrayOfChar[b] ^ j);
          j = ((j >>> 3 | j << 5) ^ arrayOfChar[b]) & 0xFF;
        } else {
          arrayOfChar[b] = (char)(arrayOfChar[b] ^ k);
          k = ((k >>> 3 | k << 5) ^ arrayOfChar[b]) & 0xFF;
        } 
      } 
      h[i] = (new String(arrayOfChar)).intern();
    } 
    return h[i];
  }
}


/* Location:              C:\Program Files\BurpSuitePro\burpsuite_pro.jar!\com\fasterxml\Zo\Zd.class
 * Java compiler version: 8 (52.0)
 * JD-Core Version:       1.1.3
 */