package com.fasterxml.Zo;

import com.fasterxml.Zb.Z_;
import com.fasterxml.Zb.Zg;
import com.fasterxml.Zb.Zk;
import com.fasterxml.Zb.Zl;
import com.fasterxml.Ze.Zc;
import com.fasterxml.Ze.Ze;
import com.fasterxml.Ze.Zj;
import com.fasterxml.Ze.Zo1;
import com.fasterxml.Ze.Zo8;
import com.fasterxml.Ze.Zoq;
import com.fasterxml.Ze.Zv;
import com.fasterxml.Ze.Zw;
import com.fasterxml.Ze.Zx;
import com.fasterxml.Ze.Zz;
import com.fasterxml.Zh.Zd;
import com.fasterxml.Zh.Zp;
import com.fasterxml.Zm.Zb;
import com.fasterxml.Zm.Zee;
import com.fasterxml.Zm.Zeg;
import com.fasterxml.Zm.Zl;
import com.fasterxml.Zm.Zq;
import com.fasterxml.Zm.Zv;
import com.fasterxml.Zm.Zx;
import com.fasterxml.Zor.Zd;
import com.fasterxml.Zor.Zk;
import com.fasterxml.Zor.Zo;
import com.fasterxml.Zor.Zr;
import com.fasterxml.Zor.Zt;
import com.fasterxml.Zor.Zy9;
import com.fasterxml.Zor.Zy_;
import com.fasterxml.Zor.Zyb;
import com.fasterxml.Zor.Zyc;
import com.fasterxml.Zor.Zyg;
import com.fasterxml.Zor.Zyo;
import com.fasterxml.Zor.Zyp;
import com.fasterxml.Zor.Zyv;
import com.fasterxml.Zoz.Zif;
import com.fasterxml.Zoz.Ziv;
import com.fasterxml.Zoz.Ziz;
import com.fasterxml.Zoz.Zv;
import com.fasterxml.Zp.Zt;
import com.fasterxml.Zqi;
import com.fasterxml.Zs.Zl;
import com.fasterxml.Zs.Zum;
import com.fasterxml.Zvo;
import java.io.IOException;
import java.io.Serializable;
import java.lang.reflect.Constructor;
import java.util.ArrayList;
import java.util.Collection;
import java.util.HashMap;
import java.util.Iterator;
import java.util.Map;
import java.util.Set;

public abstract class Zf extends Zl<Object> implements Zi, Zq, Ze, Serializable {
  private static final long serialVersionUID = 1L;
  
  protected static final Zr ZV;
  
  protected final Zk ZF;
  
  protected final Zqi ZM;
  
  protected final Zzp Zb;
  
  protected Zyo<Object> Zo;
  
  protected Zyo<Object> Zc;
  
  protected Zc ZT;
  
  protected boolean ZU;
  
  protected boolean Zn;
  
  protected final Zo8 ZX;
  
  protected final Zv[] Zy;
  
  protected Zl ZA;
  
  protected final Set<String> Zq;
  
  protected final Set<String> ZP;
  
  protected final boolean Za;
  
  protected final boolean Zk;
  
  protected final Map<String, Zv> ZB;
  
  protected transient HashMap<Zp, Zyo<Object>> Zp;
  
  protected Zo1 ZL;
  
  protected Zoq Zv;
  
  protected final Zz ZZ;
  
  private static final String[] e;
  
  private static final String[] f;
  
  protected Zf(Zh paramZh, Zyv paramZyv, Zo8 paramZo8, Map<String, Zv> paramMap, Set<String> paramSet1, boolean paramBoolean1, Set<String> paramSet2, boolean paramBoolean2) {
    // Byte code:
    //   0: aload_0
    //   1: aload_2
    //   2: invokevirtual Zf : ()Lcom/fasterxml/Zor/Zk;
    //   5: invokespecial <init> : (Lcom/fasterxml/Zor/Zk;)V
    //   8: aload_0
    //   9: aload_2
    //   10: invokevirtual Zf : ()Lcom/fasterxml/Zor/Zk;
    //   13: putfield ZF : Lcom/fasterxml/Zor/Zk;
    //   16: aload_0
    //   17: aload_1
    //   18: invokevirtual Zf : ()Lcom/fasterxml/Zo/Zzp;
    //   21: putfield Zb : Lcom/fasterxml/Zo/Zzp;
    //   24: aload_0
    //   25: aconst_null
    //   26: putfield Zo : Lcom/fasterxml/Zor/Zyo;
    //   29: aload_0
    //   30: aconst_null
    //   31: putfield Zc : Lcom/fasterxml/Zor/Zyo;
    //   34: aload_0
    //   35: aconst_null
    //   36: putfield ZT : Lcom/fasterxml/Ze/Zc;
    //   39: aload_0
    //   40: aload_3
    //   41: putfield ZX : Lcom/fasterxml/Ze/Zo8;
    //   44: aload_0
    //   45: aload #4
    //   47: putfield ZB : Ljava/util/Map;
    //   50: aload_0
    //   51: aload #5
    //   53: putfield Zq : Ljava/util/Set;
    //   56: aload_0
    //   57: iload #6
    //   59: putfield Za : Z
    //   62: aload_0
    //   63: aload #7
    //   65: putfield ZP : Ljava/util/Set;
    //   68: aload_0
    //   69: aload_1
    //   70: invokevirtual Zp : ()Lcom/fasterxml/Zo/Zl;
    //   73: putfield ZA : Lcom/fasterxml/Zo/Zl;
    //   76: aload_1
    //   77: invokevirtual ZS : ()Ljava/util/List;
    //   80: astore #9
    //   82: aload_0
    //   83: aload #9
    //   85: ifnull -> 105
    //   88: aload #9
    //   90: invokeinterface isEmpty : ()Z
    //   95: ifeq -> 113
    //   98: goto -> 105
    //   101: invokestatic b : (Ljava/lang/Exception;)Ljava/lang/Exception;
    //   104: athrow
    //   105: aconst_null
    //   106: goto -> 133
    //   109: invokestatic b : (Ljava/lang/Exception;)Ljava/lang/Exception;
    //   112: athrow
    //   113: aload #9
    //   115: aload #9
    //   117: invokeinterface size : ()I
    //   122: anewarray com/fasterxml/Ze/Zv
    //   125: invokeinterface toArray : ([Ljava/lang/Object;)[Ljava/lang/Object;
    //   130: checkcast [Lcom/fasterxml/Ze/Zv;
    //   133: putfield Zy : [Lcom/fasterxml/Ze/Zv;
    //   136: aload_0
    //   137: aload_1
    //   138: invokevirtual Zz : ()Lcom/fasterxml/Ze/Zz;
    //   141: putfield ZZ : Lcom/fasterxml/Ze/Zz;
    //   144: aload_0
    //   145: aload_0
    //   146: getfield ZL : Lcom/fasterxml/Ze/Zo1;
    //   149: ifnonnull -> 203
    //   152: aload_0
    //   153: getfield Zb : Lcom/fasterxml/Zo/Zzp;
    //   156: invokevirtual ZR : ()Z
    //   159: ifne -> 203
    //   162: goto -> 169
    //   165: invokestatic b : (Ljava/lang/Exception;)Ljava/lang/Exception;
    //   168: athrow
    //   169: aload_0
    //   170: getfield Zb : Lcom/fasterxml/Zo/Zzp;
    //   173: invokevirtual ZN : ()Z
    //   176: ifne -> 203
    //   179: goto -> 186
    //   182: invokestatic b : (Ljava/lang/Exception;)Ljava/lang/Exception;
    //   185: athrow
    //   186: aload_0
    //   187: getfield Zb : Lcom/fasterxml/Zo/Zzp;
    //   190: invokevirtual ZJ : ()Z
    //   193: ifne -> 211
    //   196: goto -> 203
    //   199: invokestatic b : (Ljava/lang/Exception;)Ljava/lang/Exception;
    //   202: athrow
    //   203: iconst_1
    //   204: goto -> 212
    //   207: invokestatic b : (Ljava/lang/Exception;)Ljava/lang/Exception;
    //   210: athrow
    //   211: iconst_0
    //   212: putfield ZU : Z
    //   215: aload_2
    //   216: invokevirtual ZX : ()Lcom/fasterxml/Zgy;
    //   219: astore #10
    //   221: aload_0
    //   222: aload #10
    //   224: invokevirtual ZI : ()Lcom/fasterxml/Zqi;
    //   227: putfield ZM : Lcom/fasterxml/Zqi;
    //   230: aload_0
    //   231: iload #8
    //   233: putfield Zk : Z
    //   236: aload_0
    //   237: aload_0
    //   238: getfield ZU : Z
    //   241: ifne -> 294
    //   244: aload_0
    //   245: getfield Zy : [Lcom/fasterxml/Ze/Zv;
    //   248: ifnonnull -> 294
    //   251: goto -> 258
    //   254: invokestatic b : (Ljava/lang/Exception;)Ljava/lang/Exception;
    //   257: athrow
    //   258: aload_0
    //   259: getfield Zk : Z
    //   262: ifne -> 294
    //   265: goto -> 272
    //   268: invokestatic b : (Ljava/lang/Exception;)Ljava/lang/Exception;
    //   271: athrow
    //   272: aload_0
    //   273: getfield ZZ : Lcom/fasterxml/Ze/Zz;
    //   276: ifnonnull -> 294
    //   279: goto -> 286
    //   282: invokestatic b : (Ljava/lang/Exception;)Ljava/lang/Exception;
    //   285: athrow
    //   286: iconst_1
    //   287: goto -> 295
    //   290: invokestatic b : (Ljava/lang/Exception;)Ljava/lang/Exception;
    //   293: athrow
    //   294: iconst_0
    //   295: putfield Zn : Z
    //   298: return
    // Exception table:
    //   from	to	target	type
    //   82	98	101	java/lang/UnsupportedOperationException
    //   88	109	109	java/lang/UnsupportedOperationException
    //   133	162	165	java/lang/UnsupportedOperationException
    //   152	179	182	java/lang/UnsupportedOperationException
    //   169	196	199	java/lang/UnsupportedOperationException
    //   186	207	207	java/lang/UnsupportedOperationException
    //   221	251	254	java/lang/UnsupportedOperationException
    //   244	265	268	java/lang/UnsupportedOperationException
    //   258	279	282	java/lang/UnsupportedOperationException
    //   272	290	290	java/lang/UnsupportedOperationException
  }
  
  protected Zf(Zf paramZf) {
    this(paramZf, paramZf.Za);
  }
  
  protected Zf(Zf paramZf, boolean paramBoolean) {
    super(paramZf.ZF);
    this.ZF = paramZf.ZF;
    this.Zb = paramZf.Zb;
    this.Zo = paramZf.Zo;
    this.Zc = paramZf.Zc;
    this.ZT = paramZf.ZT;
    this.ZX = paramZf.ZX;
    this.ZB = paramZf.ZB;
    this.Zq = paramZf.Zq;
    this.Za = paramBoolean;
    this.ZP = paramZf.ZP;
    this.ZA = paramZf.ZA;
    this.Zy = paramZf.Zy;
    this.ZZ = paramZf.ZZ;
    this.ZU = paramZf.ZU;
    this.ZL = paramZf.ZL;
    this.Zk = paramZf.Zk;
    this.ZM = paramZf.ZM;
    this.Zn = paramZf.Zn;
    this.Zv = paramZf.Zv;
  }
  
  protected Zf(Zf paramZf, Zee paramZee) {
    // Byte code:
    //   0: aload_0
    //   1: aload_1
    //   2: getfield ZF : Lcom/fasterxml/Zor/Zk;
    //   5: invokespecial <init> : (Lcom/fasterxml/Zor/Zk;)V
    //   8: invokestatic ZP : ()Ljava/lang/String;
    //   11: aload_0
    //   12: aload_1
    //   13: getfield ZF : Lcom/fasterxml/Zor/Zk;
    //   16: putfield ZF : Lcom/fasterxml/Zor/Zk;
    //   19: aload_0
    //   20: aload_1
    //   21: getfield Zb : Lcom/fasterxml/Zo/Zzp;
    //   24: putfield Zb : Lcom/fasterxml/Zo/Zzp;
    //   27: aload_0
    //   28: aload_1
    //   29: getfield Zo : Lcom/fasterxml/Zor/Zyo;
    //   32: putfield Zo : Lcom/fasterxml/Zor/Zyo;
    //   35: aload_0
    //   36: aload_1
    //   37: getfield Zc : Lcom/fasterxml/Zor/Zyo;
    //   40: putfield Zc : Lcom/fasterxml/Zor/Zyo;
    //   43: astore_3
    //   44: aload_0
    //   45: aload_1
    //   46: getfield ZT : Lcom/fasterxml/Ze/Zc;
    //   49: putfield ZT : Lcom/fasterxml/Ze/Zc;
    //   52: aload_0
    //   53: aload_1
    //   54: getfield ZB : Ljava/util/Map;
    //   57: putfield ZB : Ljava/util/Map;
    //   60: aload_0
    //   61: aload_1
    //   62: getfield Zq : Ljava/util/Set;
    //   65: putfield Zq : Ljava/util/Set;
    //   68: aload_0
    //   69: aload_2
    //   70: ifnonnull -> 87
    //   73: aload_1
    //   74: getfield Za : Z
    //   77: ifeq -> 95
    //   80: goto -> 87
    //   83: invokestatic b : (Ljava/lang/Exception;)Ljava/lang/Exception;
    //   86: athrow
    //   87: iconst_1
    //   88: goto -> 96
    //   91: invokestatic b : (Ljava/lang/Exception;)Ljava/lang/Exception;
    //   94: athrow
    //   95: iconst_0
    //   96: putfield Za : Z
    //   99: aload_0
    //   100: aload_1
    //   101: getfield ZP : Ljava/util/Set;
    //   104: putfield ZP : Ljava/util/Set;
    //   107: aload_0
    //   108: aload_1
    //   109: getfield ZA : Lcom/fasterxml/Zo/Zl;
    //   112: putfield ZA : Lcom/fasterxml/Zo/Zl;
    //   115: aload_0
    //   116: aload_1
    //   117: getfield Zy : [Lcom/fasterxml/Ze/Zv;
    //   120: putfield Zy : [Lcom/fasterxml/Ze/Zv;
    //   123: aload_0
    //   124: aload_1
    //   125: getfield ZZ : Lcom/fasterxml/Ze/Zz;
    //   128: putfield ZZ : Lcom/fasterxml/Ze/Zz;
    //   131: aload_0
    //   132: aload_1
    //   133: getfield ZU : Z
    //   136: putfield ZU : Z
    //   139: aload_1
    //   140: getfield ZL : Lcom/fasterxml/Ze/Zo1;
    //   143: astore #4
    //   145: aload_2
    //   146: ifnull -> 199
    //   149: aload #4
    //   151: ifnull -> 169
    //   154: goto -> 161
    //   157: invokestatic b : (Ljava/lang/Exception;)Ljava/lang/Exception;
    //   160: athrow
    //   161: aload #4
    //   163: aload_2
    //   164: invokevirtual ZM : (Lcom/fasterxml/Zm/Zee;)Lcom/fasterxml/Ze/Zo1;
    //   167: astore #4
    //   169: aload_0
    //   170: aload_1
    //   171: getfield ZX : Lcom/fasterxml/Ze/Zo8;
    //   174: aload_2
    //   175: invokevirtual Zi : (Lcom/fasterxml/Zm/Zee;)Lcom/fasterxml/Ze/Zo8;
    //   178: putfield ZX : Lcom/fasterxml/Ze/Zo8;
    //   181: aload_3
    //   182: ifnull -> 207
    //   185: iconst_1
    //   186: anewarray burp/Zbqc
    //   189: invokestatic Zr : ([Lburp/Zbqc;)V
    //   192: goto -> 199
    //   195: invokestatic b : (Ljava/lang/Exception;)Ljava/lang/Exception;
    //   198: athrow
    //   199: aload_0
    //   200: aload_1
    //   201: getfield ZX : Lcom/fasterxml/Ze/Zo8;
    //   204: putfield ZX : Lcom/fasterxml/Ze/Zo8;
    //   207: aload_0
    //   208: aload #4
    //   210: putfield ZL : Lcom/fasterxml/Ze/Zo1;
    //   213: aload_0
    //   214: aload_1
    //   215: getfield Zk : Z
    //   218: putfield Zk : Z
    //   221: aload_0
    //   222: aload_1
    //   223: getfield ZM : Lcom/fasterxml/Zqi;
    //   226: putfield ZM : Lcom/fasterxml/Zqi;
    //   229: aload_0
    //   230: iconst_0
    //   231: putfield Zn : Z
    //   234: aload_0
    //   235: aload_1
    //   236: getfield Zv : Lcom/fasterxml/Ze/Zoq;
    //   239: putfield Zv : Lcom/fasterxml/Ze/Zoq;
    //   242: return
    // Exception table:
    //   from	to	target	type
    //   44	80	83	java/lang/UnsupportedOperationException
    //   73	91	91	java/lang/UnsupportedOperationException
    //   145	154	157	java/lang/UnsupportedOperationException
    //   169	192	195	java/lang/UnsupportedOperationException
  }
  
  public Zf(Zf paramZf, Zz paramZz) {
    // Byte code:
    //   0: aload_0
    //   1: aload_1
    //   2: getfield ZF : Lcom/fasterxml/Zor/Zk;
    //   5: invokespecial <init> : (Lcom/fasterxml/Zor/Zk;)V
    //   8: invokestatic ZP : ()Ljava/lang/String;
    //   11: aload_0
    //   12: aload_1
    //   13: getfield ZF : Lcom/fasterxml/Zor/Zk;
    //   16: putfield ZF : Lcom/fasterxml/Zor/Zk;
    //   19: aload_0
    //   20: aload_1
    //   21: getfield Zb : Lcom/fasterxml/Zo/Zzp;
    //   24: putfield Zb : Lcom/fasterxml/Zo/Zzp;
    //   27: aload_0
    //   28: aload_1
    //   29: getfield Zo : Lcom/fasterxml/Zor/Zyo;
    //   32: putfield Zo : Lcom/fasterxml/Zor/Zyo;
    //   35: aload_0
    //   36: aload_1
    //   37: getfield Zc : Lcom/fasterxml/Zor/Zyo;
    //   40: putfield Zc : Lcom/fasterxml/Zor/Zyo;
    //   43: aload_0
    //   44: aload_1
    //   45: getfield ZT : Lcom/fasterxml/Ze/Zc;
    //   48: putfield ZT : Lcom/fasterxml/Ze/Zc;
    //   51: aload_0
    //   52: aload_1
    //   53: getfield ZB : Ljava/util/Map;
    //   56: putfield ZB : Ljava/util/Map;
    //   59: aload_0
    //   60: aload_1
    //   61: getfield Zq : Ljava/util/Set;
    //   64: putfield Zq : Ljava/util/Set;
    //   67: aload_0
    //   68: aload_1
    //   69: getfield Za : Z
    //   72: putfield Za : Z
    //   75: astore_3
    //   76: aload_0
    //   77: aload_1
    //   78: getfield ZP : Ljava/util/Set;
    //   81: putfield ZP : Ljava/util/Set;
    //   84: aload_0
    //   85: aload_1
    //   86: getfield ZA : Lcom/fasterxml/Zo/Zl;
    //   89: putfield ZA : Lcom/fasterxml/Zo/Zl;
    //   92: aload_0
    //   93: aload_1
    //   94: getfield Zy : [Lcom/fasterxml/Ze/Zv;
    //   97: putfield Zy : [Lcom/fasterxml/Ze/Zv;
    //   100: aload_0
    //   101: aload_1
    //   102: getfield ZU : Z
    //   105: putfield ZU : Z
    //   108: aload_0
    //   109: aload_1
    //   110: getfield ZL : Lcom/fasterxml/Ze/Zo1;
    //   113: putfield ZL : Lcom/fasterxml/Ze/Zo1;
    //   116: aload_0
    //   117: aload_1
    //   118: getfield Zk : Z
    //   121: putfield Zk : Z
    //   124: aload_0
    //   125: aload_1
    //   126: getfield ZM : Lcom/fasterxml/Zqi;
    //   129: putfield ZM : Lcom/fasterxml/Zqi;
    //   132: aload_0
    //   133: aload_2
    //   134: putfield ZZ : Lcom/fasterxml/Ze/Zz;
    //   137: aload_2
    //   138: ifnonnull -> 168
    //   141: aload_0
    //   142: aload_1
    //   143: getfield ZX : Lcom/fasterxml/Ze/Zo8;
    //   146: putfield ZX : Lcom/fasterxml/Ze/Zo8;
    //   149: aload_0
    //   150: aload_1
    //   151: getfield Zn : Z
    //   154: putfield Zn : Z
    //   157: aload_3
    //   158: ifnull -> 199
    //   161: goto -> 168
    //   164: invokestatic b : (Ljava/lang/Exception;)Ljava/lang/Exception;
    //   167: athrow
    //   168: new com/fasterxml/Ze/Zk
    //   171: dup
    //   172: aload_2
    //   173: getstatic com/fasterxml/Zor/Zyb.Zd : Lcom/fasterxml/Zor/Zyb;
    //   176: invokespecial <init> : (Lcom/fasterxml/Ze/Zz;Lcom/fasterxml/Zor/Zyb;)V
    //   179: astore #4
    //   181: aload_0
    //   182: aload_1
    //   183: getfield ZX : Lcom/fasterxml/Ze/Zo8;
    //   186: aload #4
    //   188: invokevirtual ZP : (Lcom/fasterxml/Zo/Zv;)Lcom/fasterxml/Ze/Zo8;
    //   191: putfield ZX : Lcom/fasterxml/Ze/Zo8;
    //   194: aload_0
    //   195: iconst_0
    //   196: putfield Zn : Z
    //   199: aload_0
    //   200: aload_1
    //   201: getfield Zv : Lcom/fasterxml/Ze/Zoq;
    //   204: putfield Zv : Lcom/fasterxml/Ze/Zoq;
    //   207: return
    // Exception table:
    //   from	to	target	type
    //   76	161	164	java/lang/UnsupportedOperationException
  }
  
  public Zf(Zf paramZf, Set<String> paramSet1, Set<String> paramSet2) {
    super(paramZf.ZF);
    this.ZF = paramZf.ZF;
    this.Zb = paramZf.Zb;
    this.Zo = paramZf.Zo;
    this.Zc = paramZf.Zc;
    this.ZT = paramZf.ZT;
    this.ZB = paramZf.ZB;
    this.Zq = paramSet1;
    this.Za = paramZf.Za;
    this.ZP = paramSet2;
    this.ZA = paramZf.ZA;
    this.Zy = paramZf.Zy;
    this.ZU = paramZf.ZU;
    this.ZL = paramZf.ZL;
    this.Zk = paramZf.Zk;
    this.ZM = paramZf.ZM;
    this.Zn = paramZf.Zn;
    this.ZZ = paramZf.ZZ;
    this.ZX = paramZf.ZX.Zr(paramSet1, paramSet2);
    this.Zv = paramZf.Zv;
  }
  
  protected Zf(Zf paramZf, Zo8 paramZo8) {
    super(paramZf.ZF);
    this.ZF = paramZf.ZF;
    this.Zb = paramZf.Zb;
    this.Zo = paramZf.Zo;
    this.Zc = paramZf.Zc;
    this.ZT = paramZf.ZT;
    this.ZX = paramZo8;
    this.ZB = paramZf.ZB;
    this.Zq = paramZf.Zq;
    this.Za = paramZf.Za;
    this.ZP = paramZf.ZP;
    this.ZA = paramZf.ZA;
    this.Zy = paramZf.Zy;
    this.ZZ = paramZf.ZZ;
    this.ZU = paramZf.ZU;
    this.ZL = paramZf.ZL;
    this.Zk = paramZf.Zk;
    this.ZM = paramZf.ZM;
    this.Zn = paramZf.Zn;
    this.Zv = paramZf.Zv;
  }
  
  public abstract Zyo<Object> Zv(Zee paramZee);
  
  public abstract Zf Zw(Zz paramZz);
  
  public abstract Zf Zv(Set<String> paramSet1, Set<String> paramSet2);
  
  public abstract Zf ZI(boolean paramBoolean);
  
  public Zf ZG(Zo8 paramZo8) {
    throw new UnsupportedOperationException(c(-8959, 27158) + getClass().getName() + c(-8945, 28408));
  }
  
  protected abstract Zf Zv();
  
  public void Zs(Zyg paramZyg) throws Zy_ {
    // Byte code:
    //   0: invokestatic ZP : ()Ljava/lang/String;
    //   3: aconst_null
    //   4: astore_3
    //   5: astore_2
    //   6: aload_0
    //   7: getfield Zb : Lcom/fasterxml/Zo/Zzp;
    //   10: invokevirtual ZN : ()Z
    //   13: ifeq -> 117
    //   16: aload_0
    //   17: getfield Zb : Lcom/fasterxml/Zo/Zzp;
    //   20: aload_1
    //   21: invokevirtual Za : ()Lcom/fasterxml/Zor/Zyc;
    //   24: invokevirtual Zg : (Lcom/fasterxml/Zor/Zyc;)[Lcom/fasterxml/Zo/Zv;
    //   27: astore #4
    //   29: aload_0
    //   30: getfield Zq : Ljava/util/Set;
    //   33: ifnonnull -> 50
    //   36: aload_0
    //   37: getfield ZP : Ljava/util/Set;
    //   40: ifnull -> 120
    //   43: goto -> 50
    //   46: invokestatic b : (Ljava/lang/Exception;)Ljava/lang/Exception;
    //   49: athrow
    //   50: iconst_0
    //   51: istore #5
    //   53: aload #4
    //   55: arraylength
    //   56: istore #6
    //   58: iload #5
    //   60: iload #6
    //   62: if_icmpge -> 113
    //   65: aload #4
    //   67: iload #5
    //   69: aaload
    //   70: astore #7
    //   72: aload #7
    //   74: invokevirtual ZT : ()Ljava/lang/String;
    //   77: aload_0
    //   78: getfield Zq : Ljava/util/Set;
    //   81: aload_0
    //   82: getfield ZP : Ljava/util/Set;
    //   85: invokestatic Zv : (Ljava/lang/Object;Ljava/util/Collection;Ljava/util/Collection;)Z
    //   88: ifeq -> 106
    //   91: aload #4
    //   93: iload #5
    //   95: aaload
    //   96: invokevirtual ZE : ()V
    //   99: goto -> 106
    //   102: invokestatic b : (Ljava/lang/Exception;)Ljava/lang/Exception;
    //   105: athrow
    //   106: iinc #5, 1
    //   109: aload_2
    //   110: ifnull -> 58
    //   113: aload_2
    //   114: ifnull -> 120
    //   117: aconst_null
    //   118: astore #4
    //   120: aconst_null
    //   121: astore #5
    //   123: aload_0
    //   124: getfield ZX : Lcom/fasterxml/Ze/Zo8;
    //   127: invokevirtual iterator : ()Ljava/util/Iterator;
    //   130: astore #6
    //   132: aload #6
    //   134: invokeinterface hasNext : ()Z
    //   139: ifeq -> 214
    //   142: aload #6
    //   144: invokeinterface next : ()Ljava/lang/Object;
    //   149: checkcast com/fasterxml/Zo/Zv
    //   152: astore #7
    //   154: aload #7
    //   156: invokevirtual ZN : ()Z
    //   159: ifne -> 210
    //   162: aload_0
    //   163: aload_1
    //   164: aload #7
    //   166: invokevirtual Zr : (Lcom/fasterxml/Zor/Zyg;Lcom/fasterxml/Zo/Zv;)Lcom/fasterxml/Zor/Zyo;
    //   169: astore #8
    //   171: aload #8
    //   173: ifnonnull -> 187
    //   176: aload_1
    //   177: aload #7
    //   179: invokevirtual Zp : ()Lcom/fasterxml/Zor/Zk;
    //   182: invokevirtual Z_ : (Lcom/fasterxml/Zor/Zk;)Lcom/fasterxml/Zor/Zyo;
    //   185: astore #8
    //   187: aload #7
    //   189: aload #8
    //   191: invokevirtual Zt : (Lcom/fasterxml/Zor/Zyo;)Lcom/fasterxml/Zo/Zv;
    //   194: astore #9
    //   196: aload_0
    //   197: aload_0
    //   198: getfield ZX : Lcom/fasterxml/Ze/Zo8;
    //   201: aload #4
    //   203: aload #7
    //   205: aload #9
    //   207: invokevirtual Z_ : (Lcom/fasterxml/Ze/Zo8;[Lcom/fasterxml/Zo/Zv;Lcom/fasterxml/Zo/Zv;Lcom/fasterxml/Zo/Zv;)V
    //   210: aload_2
    //   211: ifnull -> 132
    //   214: aload_0
    //   215: getfield ZX : Lcom/fasterxml/Ze/Zo8;
    //   218: invokevirtual iterator : ()Ljava/util/Iterator;
    //   221: astore #6
    //   223: aload #6
    //   225: invokeinterface hasNext : ()Z
    //   230: ifeq -> 523
    //   233: aload #6
    //   235: invokeinterface next : ()Ljava/lang/Object;
    //   240: checkcast com/fasterxml/Zo/Zv
    //   243: astore #7
    //   245: aload #7
    //   247: astore #8
    //   249: aload #8
    //   251: invokevirtual ZD : ()Lcom/fasterxml/Zor/Zyo;
    //   254: astore #9
    //   256: aload_1
    //   257: aload #9
    //   259: aload #8
    //   261: aload #8
    //   263: invokevirtual Zp : ()Lcom/fasterxml/Zor/Zk;
    //   266: invokevirtual Zq : (Lcom/fasterxml/Zor/Zyo;Lcom/fasterxml/Zor/Zo;Lcom/fasterxml/Zor/Zk;)Lcom/fasterxml/Zor/Zyo;
    //   269: astore #9
    //   271: aload #8
    //   273: aload #9
    //   275: invokevirtual Zt : (Lcom/fasterxml/Zor/Zyo;)Lcom/fasterxml/Zo/Zv;
    //   278: astore #8
    //   280: aload_0
    //   281: aload_1
    //   282: aload #8
    //   284: invokevirtual ZH : (Lcom/fasterxml/Zor/Zyg;Lcom/fasterxml/Zo/Zv;)Lcom/fasterxml/Zo/Zv;
    //   287: astore #8
    //   289: aload #8
    //   291: instanceof com/fasterxml/Ze/Ze
    //   294: ifne -> 306
    //   297: aload_0
    //   298: aload_1
    //   299: aload #8
    //   301: invokevirtual Zz : (Lcom/fasterxml/Zor/Zyg;Lcom/fasterxml/Zo/Zv;)Lcom/fasterxml/Zo/Zv;
    //   304: astore #8
    //   306: aload_0
    //   307: aload_1
    //   308: aload #8
    //   310: invokevirtual Zm : (Lcom/fasterxml/Zor/Zyg;Lcom/fasterxml/Zo/Zv;)Lcom/fasterxml/Zm/Zee;
    //   313: astore #10
    //   315: aload #10
    //   317: ifnull -> 398
    //   320: aload #8
    //   322: invokevirtual ZD : ()Lcom/fasterxml/Zor/Zyo;
    //   325: astore #11
    //   327: aload #11
    //   329: aload #10
    //   331: invokevirtual Zv : (Lcom/fasterxml/Zm/Zee;)Lcom/fasterxml/Zor/Zyo;
    //   334: astore #12
    //   336: aload #12
    //   338: aload #11
    //   340: if_acmpeq -> 398
    //   343: aload #12
    //   345: ifnull -> 398
    //   348: goto -> 355
    //   351: invokestatic b : (Ljava/lang/Exception;)Ljava/lang/Exception;
    //   354: athrow
    //   355: aload #8
    //   357: aload #12
    //   359: invokevirtual Zt : (Lcom/fasterxml/Zor/Zyo;)Lcom/fasterxml/Zo/Zv;
    //   362: astore #8
    //   364: aload #5
    //   366: ifnonnull -> 378
    //   369: new com/fasterxml/Ze/Zo1
    //   372: dup
    //   373: invokespecial <init> : ()V
    //   376: astore #5
    //   378: aload #5
    //   380: aload #8
    //   382: invokevirtual ZF : (Lcom/fasterxml/Zo/Zv;)V
    //   385: aload_0
    //   386: getfield ZX : Lcom/fasterxml/Ze/Zo8;
    //   389: aload #8
    //   391: invokevirtual ZM : (Lcom/fasterxml/Zo/Zv;)V
    //   394: aload_2
    //   395: ifnull -> 223
    //   398: aload #8
    //   400: invokevirtual ZO : ()Lcom/fasterxml/Zor/Zyb;
    //   403: astore #11
    //   405: aload_0
    //   406: aload_1
    //   407: aload #8
    //   409: aload #11
    //   411: invokevirtual Zy : (Lcom/fasterxml/Zor/Zyg;Lcom/fasterxml/Zo/Zv;Lcom/fasterxml/Zor/Zyb;)Lcom/fasterxml/Zo/Zv;
    //   414: astore #8
    //   416: aload_0
    //   417: aload_1
    //   418: aload #8
    //   420: invokevirtual Zg : (Lcom/fasterxml/Zor/Zyg;Lcom/fasterxml/Zo/Zv;)Lcom/fasterxml/Zo/Zv;
    //   423: astore #8
    //   425: aload #8
    //   427: aload #7
    //   429: if_acmpeq -> 453
    //   432: aload_0
    //   433: aload_0
    //   434: getfield ZX : Lcom/fasterxml/Ze/Zo8;
    //   437: aload #4
    //   439: aload #7
    //   441: aload #8
    //   443: invokevirtual Z_ : (Lcom/fasterxml/Ze/Zo8;[Lcom/fasterxml/Zo/Zv;Lcom/fasterxml/Zo/Zv;Lcom/fasterxml/Zo/Zv;)V
    //   446: goto -> 453
    //   449: invokestatic b : (Ljava/lang/Exception;)Ljava/lang/Exception;
    //   452: athrow
    //   453: aload #8
    //   455: invokevirtual Zz : ()Z
    //   458: ifeq -> 519
    //   461: aload #8
    //   463: invokevirtual Zc : ()Lcom/fasterxml/Zp/Zt;
    //   466: astore #12
    //   468: aload #12
    //   470: invokevirtual Zz : ()Lcom/fasterxml/Zyc;
    //   473: getstatic com/fasterxml/Zyc.EXTERNAL_PROPERTY : Lcom/fasterxml/Zyc;
    //   476: if_acmpne -> 519
    //   479: aload_3
    //   480: ifnonnull -> 498
    //   483: goto -> 490
    //   486: invokestatic b : (Ljava/lang/Exception;)Ljava/lang/Exception;
    //   489: athrow
    //   490: aload_0
    //   491: getfield ZF : Lcom/fasterxml/Zor/Zk;
    //   494: invokestatic ZB : (Lcom/fasterxml/Zor/Zk;)Lcom/fasterxml/Ze/Zl;
    //   497: astore_3
    //   498: aload_3
    //   499: aload #8
    //   501: aload #12
    //   503: invokevirtual ZU : (Lcom/fasterxml/Zo/Zv;Lcom/fasterxml/Zp/Zt;)V
    //   506: aload_0
    //   507: getfield ZX : Lcom/fasterxml/Ze/Zo8;
    //   510: aload #8
    //   512: invokevirtual ZM : (Lcom/fasterxml/Zo/Zv;)V
    //   515: aload_2
    //   516: ifnull -> 223
    //   519: aload_2
    //   520: ifnull -> 223
    //   523: aload_0
    //   524: getfield ZA : Lcom/fasterxml/Zo/Zl;
    //   527: ifnull -> 584
    //   530: aload_0
    //   531: getfield ZA : Lcom/fasterxml/Zo/Zl;
    //   534: invokevirtual ZM : ()Z
    //   537: ifne -> 584
    //   540: goto -> 547
    //   543: invokestatic b : (Ljava/lang/Exception;)Ljava/lang/Exception;
    //   546: athrow
    //   547: aload_0
    //   548: aload_0
    //   549: getfield ZA : Lcom/fasterxml/Zo/Zl;
    //   552: aload_0
    //   553: aload_1
    //   554: aload_0
    //   555: getfield ZA : Lcom/fasterxml/Zo/Zl;
    //   558: invokevirtual ZK : ()Lcom/fasterxml/Zor/Zk;
    //   561: aload_0
    //   562: getfield ZA : Lcom/fasterxml/Zo/Zl;
    //   565: invokevirtual ZZ : ()Lcom/fasterxml/Zor/Zo;
    //   568: invokevirtual ZV : (Lcom/fasterxml/Zor/Zyg;Lcom/fasterxml/Zor/Zk;Lcom/fasterxml/Zor/Zo;)Lcom/fasterxml/Zor/Zyo;
    //   571: invokevirtual ZO : (Lcom/fasterxml/Zor/Zyo;)Lcom/fasterxml/Zo/Zl;
    //   574: putfield ZA : Lcom/fasterxml/Zo/Zl;
    //   577: goto -> 584
    //   580: invokestatic b : (Ljava/lang/Exception;)Ljava/lang/Exception;
    //   583: athrow
    //   584: aload_0
    //   585: getfield Zb : Lcom/fasterxml/Zo/Zzp;
    //   588: invokevirtual ZR : ()Z
    //   591: ifeq -> 682
    //   594: aload_0
    //   595: getfield Zb : Lcom/fasterxml/Zo/Zzp;
    //   598: aload_1
    //   599: invokevirtual Za : ()Lcom/fasterxml/Zor/Zyc;
    //   602: invokevirtual ZH : (Lcom/fasterxml/Zor/Zyc;)Lcom/fasterxml/Zor/Zk;
    //   605: astore #6
    //   607: aload #6
    //   609: ifnonnull -> 664
    //   612: aload_1
    //   613: aload_0
    //   614: getfield ZF : Lcom/fasterxml/Zor/Zk;
    //   617: sipush #-8956
    //   620: sipush #-4628
    //   623: invokestatic c : (II)Ljava/lang/String;
    //   626: iconst_2
    //   627: anewarray java/lang/Object
    //   630: dup
    //   631: iconst_0
    //   632: aload_0
    //   633: getfield ZF : Lcom/fasterxml/Zor/Zk;
    //   636: invokestatic ZN : (Lcom/fasterxml/Zor/Zk;)Ljava/lang/String;
    //   639: aastore
    //   640: dup
    //   641: iconst_1
    //   642: aload_0
    //   643: getfield Zb : Lcom/fasterxml/Zo/Zzp;
    //   646: invokestatic ZZ : (Ljava/lang/Object;)Ljava/lang/String;
    //   649: aastore
    //   650: invokestatic format : (Ljava/lang/String;[Ljava/lang/Object;)Ljava/lang/String;
    //   653: invokevirtual Zm : (Lcom/fasterxml/Zor/Zk;Ljava/lang/String;)Ljava/lang/Object;
    //   656: pop
    //   657: goto -> 664
    //   660: invokestatic b : (Ljava/lang/Exception;)Ljava/lang/Exception;
    //   663: athrow
    //   664: aload_0
    //   665: aload_0
    //   666: aload_1
    //   667: aload #6
    //   669: aload_0
    //   670: getfield Zb : Lcom/fasterxml/Zo/Zzp;
    //   673: invokevirtual Zk : ()Lcom/fasterxml/Zoz/Zif;
    //   676: invokespecial Zs : (Lcom/fasterxml/Zor/Zyg;Lcom/fasterxml/Zor/Zk;Lcom/fasterxml/Zoz/Zif;)Lcom/fasterxml/Zor/Zyo;
    //   679: putfield Zo : Lcom/fasterxml/Zor/Zyo;
    //   682: aload_0
    //   683: getfield Zb : Lcom/fasterxml/Zo/Zzp;
    //   686: invokevirtual Zb : ()Z
    //   689: ifeq -> 780
    //   692: aload_0
    //   693: getfield Zb : Lcom/fasterxml/Zo/Zzp;
    //   696: aload_1
    //   697: invokevirtual Za : ()Lcom/fasterxml/Zor/Zyc;
    //   700: invokevirtual ZQ : (Lcom/fasterxml/Zor/Zyc;)Lcom/fasterxml/Zor/Zk;
    //   703: astore #6
    //   705: aload #6
    //   707: ifnonnull -> 762
    //   710: aload_1
    //   711: aload_0
    //   712: getfield ZF : Lcom/fasterxml/Zor/Zk;
    //   715: sipush #-8949
    //   718: sipush #179
    //   721: invokestatic c : (II)Ljava/lang/String;
    //   724: iconst_2
    //   725: anewarray java/lang/Object
    //   728: dup
    //   729: iconst_0
    //   730: aload_0
    //   731: getfield ZF : Lcom/fasterxml/Zor/Zk;
    //   734: invokestatic ZN : (Lcom/fasterxml/Zor/Zk;)Ljava/lang/String;
    //   737: aastore
    //   738: dup
    //   739: iconst_1
    //   740: aload_0
    //   741: getfield Zb : Lcom/fasterxml/Zo/Zzp;
    //   744: invokestatic ZZ : (Ljava/lang/Object;)Ljava/lang/String;
    //   747: aastore
    //   748: invokestatic format : (Ljava/lang/String;[Ljava/lang/Object;)Ljava/lang/String;
    //   751: invokevirtual Zm : (Lcom/fasterxml/Zor/Zk;Ljava/lang/String;)Ljava/lang/Object;
    //   754: pop
    //   755: goto -> 762
    //   758: invokestatic b : (Ljava/lang/Exception;)Ljava/lang/Exception;
    //   761: athrow
    //   762: aload_0
    //   763: aload_0
    //   764: aload_1
    //   765: aload #6
    //   767: aload_0
    //   768: getfield Zb : Lcom/fasterxml/Zo/Zzp;
    //   771: invokevirtual ZZ : ()Lcom/fasterxml/Zoz/Zif;
    //   774: invokespecial Zs : (Lcom/fasterxml/Zor/Zyg;Lcom/fasterxml/Zor/Zk;Lcom/fasterxml/Zoz/Zif;)Lcom/fasterxml/Zor/Zyo;
    //   777: putfield Zc : Lcom/fasterxml/Zor/Zyo;
    //   780: aload #4
    //   782: ifnull -> 810
    //   785: aload_0
    //   786: aload_1
    //   787: aload_0
    //   788: getfield Zb : Lcom/fasterxml/Zo/Zzp;
    //   791: aload #4
    //   793: aload_0
    //   794: getfield ZX : Lcom/fasterxml/Ze/Zo8;
    //   797: invokestatic Zh : (Lcom/fasterxml/Zor/Zyg;Lcom/fasterxml/Zo/Zzp;[Lcom/fasterxml/Zo/Zv;Lcom/fasterxml/Ze/Zo8;)Lcom/fasterxml/Ze/Zc;
    //   800: putfield ZT : Lcom/fasterxml/Ze/Zc;
    //   803: goto -> 810
    //   806: invokestatic b : (Ljava/lang/Exception;)Ljava/lang/Exception;
    //   809: athrow
    //   810: aload_3
    //   811: ifnull -> 838
    //   814: aload_0
    //   815: aload_3
    //   816: aload_0
    //   817: getfield ZX : Lcom/fasterxml/Ze/Zo8;
    //   820: invokevirtual ZE : (Lcom/fasterxml/Ze/Zo8;)Lcom/fasterxml/Ze/Zoq;
    //   823: putfield Zv : Lcom/fasterxml/Ze/Zoq;
    //   826: aload_0
    //   827: iconst_1
    //   828: putfield ZU : Z
    //   831: goto -> 838
    //   834: invokestatic b : (Ljava/lang/Exception;)Ljava/lang/Exception;
    //   837: athrow
    //   838: aload_0
    //   839: aload #5
    //   841: putfield ZL : Lcom/fasterxml/Ze/Zo1;
    //   844: aload #5
    //   846: ifnull -> 861
    //   849: aload_0
    //   850: iconst_1
    //   851: putfield ZU : Z
    //   854: goto -> 861
    //   857: invokestatic b : (Ljava/lang/Exception;)Ljava/lang/Exception;
    //   860: athrow
    //   861: aload_0
    //   862: aload_0
    //   863: getfield Zn : Z
    //   866: ifeq -> 891
    //   869: aload_0
    //   870: getfield ZU : Z
    //   873: ifne -> 891
    //   876: goto -> 883
    //   879: invokestatic b : (Ljava/lang/Exception;)Ljava/lang/Exception;
    //   882: athrow
    //   883: iconst_1
    //   884: goto -> 892
    //   887: invokestatic b : (Ljava/lang/Exception;)Ljava/lang/Exception;
    //   890: athrow
    //   891: iconst_0
    //   892: putfield Zn : Z
    //   895: return
    // Exception table:
    //   from	to	target	type
    //   29	43	46	com/fasterxml/Zor/Zy_
    //   72	99	102	com/fasterxml/Zor/Zy_
    //   336	348	351	com/fasterxml/Zor/Zy_
    //   425	446	449	com/fasterxml/Zor/Zy_
    //   468	483	486	com/fasterxml/Zor/Zy_
    //   523	540	543	com/fasterxml/Zor/Zy_
    //   530	577	580	com/fasterxml/Zor/Zy_
    //   607	657	660	com/fasterxml/Zor/Zy_
    //   705	755	758	com/fasterxml/Zor/Zy_
    //   780	803	806	com/fasterxml/Zor/Zy_
    //   810	831	834	com/fasterxml/Zor/Zy_
    //   838	854	857	com/fasterxml/Zor/Zy_
    //   861	876	879	com/fasterxml/Zor/Zy_
    //   869	887	887	com/fasterxml/Zor/Zy_
  }
  
  protected void Z_(Zo8 paramZo8, Zv[] paramArrayOfZv, Zv paramZv1, Zv paramZv2) {
    paramZo8.ZX(paramZv1, paramZv2);
    String str = Zzp.ZP();
    if (paramArrayOfZv != null) {
      byte b = 0;
      int i = paramArrayOfZv.length;
      while (b < i) {
        try {
          if (paramArrayOfZv[b] == paramZv1) {
            paramArrayOfZv[b] = paramZv2;
            return;
          } 
        } catch (UnsupportedOperationException unsupportedOperationException) {
          throw b(null);
        } 
        b++;
        if (str != null)
          break; 
      } 
    } 
  }
  
  private Zyo<Object> Zs(Zyg paramZyg, Zk paramZk, Zif paramZif) throws Zy_ {
    // Byte code:
    //   0: invokestatic ZP : ()Ljava/lang/String;
    //   3: astore #4
    //   5: aload_3
    //   6: ifnull -> 64
    //   9: aload_3
    //   10: invokevirtual ZL : ()I
    //   13: iconst_1
    //   14: if_icmpne -> 64
    //   17: goto -> 24
    //   20: invokestatic b : (Ljava/lang/Exception;)Ljava/lang/Exception;
    //   23: athrow
    //   24: aload_3
    //   25: iconst_0
    //   26: invokevirtual Zz : (I)Lcom/fasterxml/Zoz/Zin;
    //   29: astore #6
    //   31: aload_0
    //   32: aload_1
    //   33: aload #6
    //   35: aload_2
    //   36: invokevirtual ZT : (Lcom/fasterxml/Zor/Zyg;Lcom/fasterxml/Zoz/Ziz;Lcom/fasterxml/Zor/Zk;)Lcom/fasterxml/Zor/Zyb;
    //   39: astore #7
    //   41: new com/fasterxml/Zor/Zi
    //   44: dup
    //   45: getstatic com/fasterxml/Zo/Zf.ZV : Lcom/fasterxml/Zor/Zr;
    //   48: aload_2
    //   49: aconst_null
    //   50: aload #6
    //   52: aload #7
    //   54: invokespecial <init> : (Lcom/fasterxml/Zor/Zr;Lcom/fasterxml/Zor/Zk;Lcom/fasterxml/Zor/Zr;Lcom/fasterxml/Zoz/Ziz;Lcom/fasterxml/Zor/Zyb;)V
    //   57: astore #5
    //   59: aload #4
    //   61: ifnull -> 82
    //   64: new com/fasterxml/Zor/Zi
    //   67: dup
    //   68: getstatic com/fasterxml/Zo/Zf.ZV : Lcom/fasterxml/Zor/Zr;
    //   71: aload_2
    //   72: aconst_null
    //   73: aload_3
    //   74: getstatic com/fasterxml/Zor/Zyb.Zo : Lcom/fasterxml/Zor/Zyb;
    //   77: invokespecial <init> : (Lcom/fasterxml/Zor/Zr;Lcom/fasterxml/Zor/Zk;Lcom/fasterxml/Zor/Zr;Lcom/fasterxml/Zoz/Ziz;Lcom/fasterxml/Zor/Zyb;)V
    //   80: astore #5
    //   82: aload_2
    //   83: invokevirtual Zi : ()Ljava/lang/Object;
    //   86: checkcast com/fasterxml/Zp/Zt
    //   89: astore #6
    //   91: aload #6
    //   93: ifnonnull -> 106
    //   96: aload_1
    //   97: invokevirtual Za : ()Lcom/fasterxml/Zor/Zyc;
    //   100: aload_2
    //   101: invokevirtual ZW : (Lcom/fasterxml/Zor/Zk;)Lcom/fasterxml/Zp/Zt;
    //   104: astore #6
    //   106: aload_2
    //   107: invokevirtual ZY : ()Ljava/lang/Object;
    //   110: checkcast com/fasterxml/Zor/Zyo
    //   113: astore #7
    //   115: aload #7
    //   117: ifnonnull -> 135
    //   120: aload_0
    //   121: aload_1
    //   122: aload_2
    //   123: aload #5
    //   125: invokevirtual ZV : (Lcom/fasterxml/Zor/Zyg;Lcom/fasterxml/Zor/Zk;Lcom/fasterxml/Zor/Zo;)Lcom/fasterxml/Zor/Zyo;
    //   128: astore #7
    //   130: aload #4
    //   132: ifnull -> 146
    //   135: aload_1
    //   136: aload #7
    //   138: aload #5
    //   140: aload_2
    //   141: invokevirtual Zm : (Lcom/fasterxml/Zor/Zyo;Lcom/fasterxml/Zor/Zo;Lcom/fasterxml/Zor/Zk;)Lcom/fasterxml/Zor/Zyo;
    //   144: astore #7
    //   146: aload #6
    //   148: ifnull -> 172
    //   151: aload #6
    //   153: aload #5
    //   155: invokevirtual Zf : (Lcom/fasterxml/Zor/Zo;)Lcom/fasterxml/Zp/Zt;
    //   158: astore #6
    //   160: new com/fasterxml/Ze/Zo6
    //   163: dup
    //   164: aload #6
    //   166: aload #7
    //   168: invokespecial <init> : (Lcom/fasterxml/Zp/Zt;Lcom/fasterxml/Zor/Zyo;)V
    //   171: areturn
    //   172: aload #7
    //   174: areturn
    // Exception table:
    //   from	to	target	type
    //   5	17	20	com/fasterxml/Zor/Zy_
  }
  
  protected Zyb ZT(Zyg paramZyg, Ziz paramZiz, Zk paramZk) {
    // Byte code:
    //   0: aload_1
    //   1: invokevirtual Zv : ()Lcom/fasterxml/Zor/Zt;
    //   4: astore #4
    //   6: aload_1
    //   7: invokevirtual Za : ()Lcom/fasterxml/Zor/Zyc;
    //   10: astore #5
    //   12: getstatic com/fasterxml/Zor/Zyb.Zo : Lcom/fasterxml/Zor/Zyb;
    //   15: astore #6
    //   17: iconst_1
    //   18: istore #7
    //   20: aconst_null
    //   21: astore #8
    //   23: aconst_null
    //   24: astore #9
    //   26: aload #4
    //   28: ifnull -> 58
    //   31: aload #4
    //   33: aload_2
    //   34: invokevirtual ZO : (Lcom/fasterxml/Zoz/Ziv;)Lcom/fasterxml/Zyk;
    //   37: astore #10
    //   39: aload #10
    //   41: ifnull -> 58
    //   44: aload #10
    //   46: invokevirtual ZI : ()Lcom/fasterxml/Zvg;
    //   49: astore #8
    //   51: aload #10
    //   53: invokevirtual ZV : ()Lcom/fasterxml/Zvg;
    //   56: astore #9
    //   58: iload #7
    //   60: ifne -> 87
    //   63: aload #8
    //   65: ifnull -> 87
    //   68: goto -> 75
    //   71: invokestatic b : (Ljava/lang/Exception;)Ljava/lang/Exception;
    //   74: athrow
    //   75: aload #9
    //   77: ifnonnull -> 141
    //   80: goto -> 87
    //   83: invokestatic b : (Ljava/lang/Exception;)Ljava/lang/Exception;
    //   86: athrow
    //   87: aload #5
    //   89: aload_3
    //   90: invokevirtual Zf : ()Ljava/lang/Class;
    //   93: invokevirtual ZM : (Ljava/lang/Class;)Lcom/fasterxml/Zj/Z_;
    //   96: astore #10
    //   98: aload #10
    //   100: invokevirtual Zs : ()Lcom/fasterxml/Zyk;
    //   103: astore #11
    //   105: aload #11
    //   107: ifnull -> 141
    //   110: aload #8
    //   112: ifnonnull -> 129
    //   115: goto -> 122
    //   118: invokestatic b : (Ljava/lang/Exception;)Ljava/lang/Exception;
    //   121: athrow
    //   122: aload #11
    //   124: invokevirtual ZI : ()Lcom/fasterxml/Zvg;
    //   127: astore #8
    //   129: aload #9
    //   131: ifnonnull -> 141
    //   134: aload #11
    //   136: invokevirtual ZV : ()Lcom/fasterxml/Zvg;
    //   139: astore #9
    //   141: iload #7
    //   143: ifne -> 170
    //   146: aload #8
    //   148: ifnull -> 170
    //   151: goto -> 158
    //   154: invokestatic b : (Ljava/lang/Exception;)Ljava/lang/Exception;
    //   157: athrow
    //   158: aload #9
    //   160: ifnonnull -> 201
    //   163: goto -> 170
    //   166: invokestatic b : (Ljava/lang/Exception;)Ljava/lang/Exception;
    //   169: athrow
    //   170: aload #5
    //   172: invokevirtual ZF : ()Lcom/fasterxml/Zyk;
    //   175: astore #10
    //   177: aload #8
    //   179: ifnonnull -> 189
    //   182: aload #10
    //   184: invokevirtual ZI : ()Lcom/fasterxml/Zvg;
    //   187: astore #8
    //   189: aload #9
    //   191: ifnonnull -> 201
    //   194: aload #10
    //   196: invokevirtual ZV : ()Lcom/fasterxml/Zvg;
    //   199: astore #9
    //   201: aload #8
    //   203: ifnonnull -> 218
    //   206: aload #9
    //   208: ifnull -> 229
    //   211: goto -> 218
    //   214: invokestatic b : (Ljava/lang/Exception;)Ljava/lang/Exception;
    //   217: athrow
    //   218: aload #6
    //   220: aload #8
    //   222: aload #9
    //   224: invokevirtual Zr : (Lcom/fasterxml/Zvg;Lcom/fasterxml/Zvg;)Lcom/fasterxml/Zor/Zyb;
    //   227: astore #6
    //   229: aload #6
    //   231: areturn
    // Exception table:
    //   from	to	target	type
    //   58	68	71	java/lang/UnsupportedOperationException
    //   63	80	83	java/lang/UnsupportedOperationException
    //   105	115	118	java/lang/UnsupportedOperationException
    //   141	151	154	java/lang/UnsupportedOperationException
    //   146	163	166	java/lang/UnsupportedOperationException
    //   201	211	214	java/lang/UnsupportedOperationException
  }
  
  protected Zyo<Object> Zr(Zyg paramZyg, Zv paramZv) throws Zy_ {
    Zt zt = paramZyg.Zv();
    if (zt != null) {
      Object object = zt.Zw((Ziv)paramZv.ZQ());
      if (object != null) {
        Zv zv = paramZyg.ZS((Ziv)paramZv.ZQ(), object);
        Zk zk = zv.ZD(paramZyg.ZL());
        Zyo zyo = paramZyg.Z_(zk);
        return (Zyo<Object>)new Zum(zv, zk, zyo);
      } 
    } 
    return null;
  }
  
  public Zyo<?> Zq(Zyg paramZyg, Zo paramZo) throws Zy_ {
    // Byte code:
    //   0: aload_0
    //   1: getfield ZZ : Lcom/fasterxml/Ze/Zz;
    //   4: astore #4
    //   6: invokestatic ZP : ()Ljava/lang/String;
    //   9: aload_1
    //   10: invokevirtual Zv : ()Lcom/fasterxml/Zor/Zt;
    //   13: astore #5
    //   15: astore_3
    //   16: aload_2
    //   17: aload #5
    //   19: invokestatic Zg : (Ljava/lang/Object;Ljava/lang/Object;)Z
    //   22: ifeq -> 38
    //   25: aload_2
    //   26: invokeinterface ZQ : ()Lcom/fasterxml/Zoz/Ziz;
    //   31: goto -> 39
    //   34: invokestatic b : (Ljava/lang/Exception;)Ljava/lang/Exception;
    //   37: athrow
    //   38: aconst_null
    //   39: astore #6
    //   41: aload #6
    //   43: ifnull -> 254
    //   46: aload #5
    //   48: aload #6
    //   50: invokevirtual Zk : (Lcom/fasterxml/Zoz/Ziv;)Lcom/fasterxml/Zoz/Zv;
    //   53: astore #7
    //   55: aload #7
    //   57: ifnull -> 254
    //   60: aload #5
    //   62: aload #6
    //   64: aload #7
    //   66: invokevirtual Zq : (Lcom/fasterxml/Zoz/Ziv;Lcom/fasterxml/Zoz/Zv;)Lcom/fasterxml/Zoz/Zv;
    //   69: astore #7
    //   71: aload #7
    //   73: invokevirtual ZM : ()Ljava/lang/Class;
    //   76: astore #8
    //   78: aload_1
    //   79: aload #6
    //   81: aload #7
    //   83: invokevirtual ZN : (Lcom/fasterxml/Zoz/Ziv;Lcom/fasterxml/Zoz/Zv;)Lcom/fasterxml/Zq_;
    //   86: astore #12
    //   88: aload #8
    //   90: ldc com/fasterxml/Zy8
    //   92: if_acmpne -> 190
    //   95: aload #7
    //   97: invokevirtual ZT : ()Lcom/fasterxml/Zor/Zr;
    //   100: astore #13
    //   102: aload_0
    //   103: aload #13
    //   105: invokevirtual Zr : (Lcom/fasterxml/Zor/Zr;)Lcom/fasterxml/Zo/Zv;
    //   108: astore #10
    //   110: aload #10
    //   112: ifnonnull -> 165
    //   115: aload_1
    //   116: aload_0
    //   117: getfield ZF : Lcom/fasterxml/Zor/Zk;
    //   120: sipush #-8954
    //   123: sipush #19103
    //   126: invokestatic c : (II)Ljava/lang/String;
    //   129: iconst_2
    //   130: anewarray java/lang/Object
    //   133: dup
    //   134: iconst_0
    //   135: aload_0
    //   136: invokevirtual ZX : ()Ljava/lang/Class;
    //   139: invokestatic Za : (Ljava/lang/Class;)Ljava/lang/String;
    //   142: aastore
    //   143: dup
    //   144: iconst_1
    //   145: aload #13
    //   147: invokestatic Zk : (Lcom/fasterxml/Zor/Zr;)Ljava/lang/String;
    //   150: aastore
    //   151: invokestatic format : (Ljava/lang/String;[Ljava/lang/Object;)Ljava/lang/String;
    //   154: invokevirtual Zm : (Lcom/fasterxml/Zor/Zk;Ljava/lang/String;)Ljava/lang/Object;
    //   157: checkcast com/fasterxml/Zor/Zyo
    //   160: areturn
    //   161: invokestatic b : (Ljava/lang/Exception;)Ljava/lang/Exception;
    //   164: athrow
    //   165: aload #10
    //   167: invokevirtual Zp : ()Lcom/fasterxml/Zor/Zk;
    //   170: astore #9
    //   172: new com/fasterxml/Ze/Zq
    //   175: dup
    //   176: aload #7
    //   178: invokevirtual Zs : ()Ljava/lang/Class;
    //   181: invokespecial <init> : (Ljava/lang/Class;)V
    //   184: astore #11
    //   186: aload_3
    //   187: ifnull -> 226
    //   190: aload_1
    //   191: aload #8
    //   193: invokevirtual ZW : (Ljava/lang/Class;)Lcom/fasterxml/Zor/Zk;
    //   196: astore #13
    //   198: aload_1
    //   199: invokevirtual ZL : ()Lcom/fasterxml/Zh/Zi;
    //   202: aload #13
    //   204: ldc com/fasterxml/Zys
    //   206: invokevirtual Zs : (Lcom/fasterxml/Zor/Zk;Ljava/lang/Class;)[Lcom/fasterxml/Zor/Zk;
    //   209: iconst_0
    //   210: aaload
    //   211: astore #9
    //   213: aconst_null
    //   214: astore #10
    //   216: aload_1
    //   217: aload #6
    //   219: aload #7
    //   221: invokevirtual Zm : (Lcom/fasterxml/Zoz/Ziv;Lcom/fasterxml/Zoz/Zv;)Lcom/fasterxml/Zys;
    //   224: astore #11
    //   226: aload_1
    //   227: aload #9
    //   229: invokevirtual ZP : (Lcom/fasterxml/Zor/Zk;)Lcom/fasterxml/Zor/Zyo;
    //   232: astore #13
    //   234: aload #9
    //   236: aload #7
    //   238: invokevirtual ZT : ()Lcom/fasterxml/Zor/Zr;
    //   241: aload #11
    //   243: aload #13
    //   245: aload #10
    //   247: aload #12
    //   249: invokestatic ZK : (Lcom/fasterxml/Zor/Zk;Lcom/fasterxml/Zor/Zr;Lcom/fasterxml/Zys;Lcom/fasterxml/Zor/Zyo;Lcom/fasterxml/Zo/Zv;Lcom/fasterxml/Zq_;)Lcom/fasterxml/Ze/Zz;
    //   252: astore #4
    //   254: aload_0
    //   255: astore #7
    //   257: aload #4
    //   259: ifnull -> 287
    //   262: aload #4
    //   264: aload_0
    //   265: getfield ZZ : Lcom/fasterxml/Ze/Zz;
    //   268: if_acmpeq -> 287
    //   271: goto -> 278
    //   274: invokestatic b : (Ljava/lang/Exception;)Ljava/lang/Exception;
    //   277: athrow
    //   278: aload #7
    //   280: aload #4
    //   282: invokevirtual Zw : (Lcom/fasterxml/Ze/Zz;)Lcom/fasterxml/Zo/Zf;
    //   285: astore #7
    //   287: aload #6
    //   289: ifnull -> 305
    //   292: aload_0
    //   293: aload_1
    //   294: aload #5
    //   296: aload #7
    //   298: aload #6
    //   300: invokevirtual Zm : (Lcom/fasterxml/Zor/Zyg;Lcom/fasterxml/Zor/Zt;Lcom/fasterxml/Zo/Zf;Lcom/fasterxml/Zoz/Ziz;)Lcom/fasterxml/Zo/Zf;
    //   303: astore #7
    //   305: aload_0
    //   306: aload_1
    //   307: aload_2
    //   308: aload_0
    //   309: invokevirtual ZX : ()Ljava/lang/Class;
    //   312: invokevirtual Zx : (Lcom/fasterxml/Zor/Zyg;Lcom/fasterxml/Zor/Zo;Ljava/lang/Class;)Lcom/fasterxml/Zgy;
    //   315: astore #8
    //   317: aconst_null
    //   318: astore #9
    //   320: aload #8
    //   322: ifnull -> 396
    //   325: aload #8
    //   327: invokevirtual Zw : ()Z
    //   330: ifeq -> 347
    //   333: goto -> 340
    //   336: invokestatic b : (Ljava/lang/Exception;)Ljava/lang/Exception;
    //   339: athrow
    //   340: aload #8
    //   342: invokevirtual ZI : ()Lcom/fasterxml/Zqi;
    //   345: astore #9
    //   347: aload #8
    //   349: getstatic com/fasterxml/Zye.ACCEPT_CASE_INSENSITIVE_PROPERTIES : Lcom/fasterxml/Zye;
    //   352: invokevirtual Zq : (Lcom/fasterxml/Zye;)Ljava/lang/Boolean;
    //   355: astore #10
    //   357: aload #10
    //   359: ifnull -> 396
    //   362: aload_0
    //   363: getfield ZX : Lcom/fasterxml/Ze/Zo8;
    //   366: astore #11
    //   368: aload #11
    //   370: aload #10
    //   372: invokevirtual booleanValue : ()Z
    //   375: invokevirtual Zq : (Z)Lcom/fasterxml/Ze/Zo8;
    //   378: astore #12
    //   380: aload #12
    //   382: aload #11
    //   384: if_acmpeq -> 396
    //   387: aload #7
    //   389: aload #12
    //   391: invokevirtual ZG : (Lcom/fasterxml/Ze/Zo8;)Lcom/fasterxml/Zo/Zf;
    //   394: astore #7
    //   396: aload #9
    //   398: ifnonnull -> 407
    //   401: aload_0
    //   402: getfield ZM : Lcom/fasterxml/Zqi;
    //   405: astore #9
    //   407: aload #9
    //   409: getstatic com/fasterxml/Zqi.ARRAY : Lcom/fasterxml/Zqi;
    //   412: if_acmpne -> 422
    //   415: aload #7
    //   417: invokevirtual Zv : ()Lcom/fasterxml/Zo/Zf;
    //   420: astore #7
    //   422: aload #7
    //   424: areturn
    // Exception table:
    //   from	to	target	type
    //   16	34	34	com/fasterxml/Zor/Zy_
    //   110	161	161	com/fasterxml/Zor/Zy_
    //   257	271	274	com/fasterxml/Zor/Zy_
    //   320	333	336	com/fasterxml/Zor/Zy_
  }
  
  protected Zf Zm(Zyg paramZyg, Zt paramZt, Zf paramZf, Ziz paramZiz) throws Zy_ {
    // Byte code:
    //   0: invokestatic ZP : ()Ljava/lang/String;
    //   3: aload_1
    //   4: invokevirtual Za : ()Lcom/fasterxml/Zor/Zyc;
    //   7: astore #6
    //   9: astore #5
    //   11: aload_2
    //   12: aload #6
    //   14: aload #4
    //   16: invokevirtual ZH : (Lcom/fasterxml/Zj/Zf;Lcom/fasterxml/Zoz/Ziv;)Lcom/fasterxml/Zve;
    //   19: astore #7
    //   21: aload #7
    //   23: invokevirtual ZI : ()Z
    //   26: ifeq -> 49
    //   29: aload_0
    //   30: getfield Za : Z
    //   33: ifne -> 49
    //   36: goto -> 43
    //   39: invokestatic b : (Ljava/lang/Exception;)Ljava/lang/Exception;
    //   42: athrow
    //   43: aload_3
    //   44: iconst_1
    //   45: invokevirtual ZI : (Z)Lcom/fasterxml/Zo/Zf;
    //   48: astore_3
    //   49: aload #7
    //   51: invokevirtual Zq : ()Ljava/util/Set;
    //   54: astore #8
    //   56: aload_3
    //   57: getfield Zq : Ljava/util/Set;
    //   60: astore #9
    //   62: aload #8
    //   64: invokeinterface isEmpty : ()Z
    //   69: ifeq -> 81
    //   72: aload #9
    //   74: astore #10
    //   76: aload #5
    //   78: ifnull -> 140
    //   81: aload #9
    //   83: ifnull -> 110
    //   86: goto -> 93
    //   89: invokestatic b : (Ljava/lang/Exception;)Ljava/lang/Exception;
    //   92: athrow
    //   93: aload #9
    //   95: invokeinterface isEmpty : ()Z
    //   100: ifeq -> 119
    //   103: goto -> 110
    //   106: invokestatic b : (Ljava/lang/Exception;)Ljava/lang/Exception;
    //   109: athrow
    //   110: aload #8
    //   112: astore #10
    //   114: aload #5
    //   116: ifnull -> 140
    //   119: new java/util/HashSet
    //   122: dup
    //   123: aload #9
    //   125: invokespecial <init> : (Ljava/util/Collection;)V
    //   128: astore #10
    //   130: aload #10
    //   132: aload #8
    //   134: invokeinterface addAll : (Ljava/util/Collection;)Z
    //   139: pop
    //   140: aload_3
    //   141: getfield ZP : Ljava/util/Set;
    //   144: astore #11
    //   146: aload #11
    //   148: aload_2
    //   149: aload #6
    //   151: aload #4
    //   153: invokevirtual Z_ : (Lcom/fasterxml/Zj/Zf;Lcom/fasterxml/Zoz/Ziv;)Lcom/fasterxml/Zyn;
    //   156: invokevirtual ZU : ()Ljava/util/Set;
    //   159: invokestatic ZN : (Ljava/util/Set;Ljava/util/Set;)Ljava/util/Set;
    //   162: astore #12
    //   164: aload #10
    //   166: aload #9
    //   168: if_acmpne -> 185
    //   171: aload #12
    //   173: aload #11
    //   175: if_acmpeq -> 194
    //   178: goto -> 185
    //   181: invokestatic b : (Ljava/lang/Exception;)Ljava/lang/Exception;
    //   184: athrow
    //   185: aload_3
    //   186: aload #10
    //   188: aload #12
    //   190: invokevirtual Zv : (Ljava/util/Set;Ljava/util/Set;)Lcom/fasterxml/Zo/Zf;
    //   193: astore_3
    //   194: aload_3
    //   195: areturn
    // Exception table:
    //   from	to	target	type
    //   21	36	39	com/fasterxml/Zor/Zy_
    //   76	86	89	com/fasterxml/Zor/Zy_
    //   81	103	106	com/fasterxml/Zor/Zy_
    //   164	178	181	com/fasterxml/Zor/Zy_
  }
  
  protected Zv ZH(Zyg paramZyg, Zv paramZv) throws Zy_ {
    String str = paramZv.Zs();
    try {
      if (str == null)
        return paramZv; 
    } catch (Zy_ zy_) {
      throw b(null);
    } 
    Zyo<Object> zyo = paramZv.ZD();
    Zv zv = zyo.ZW(str);
    try {
      if (zv == null)
        return (Zv)paramZyg.Zm(this.ZF, String.format(c(-8948, -29176), new Object[] { Zx.ZA(str), Zx.ZN(paramZv.Zp()) })); 
    } catch (Zy_ zy_) {
      throw b(null);
    } 
    Zk zk1 = this.ZF;
    Zk zk2 = zv.Zp();
    boolean bool = paramZv.Zp().ZH();
    try {
      if (!zk2.Zf().isAssignableFrom(zk1.Zf()))
        paramZyg.Zm(this.ZF, String.format(c(-8947, -11868), new Object[] { Zx.ZA(str), Zx.ZN(zk2), zk1.Zf().getName() })); 
    } catch (Zy_ zy_) {
      throw b(null);
    } 
    return (Zv)new Ze(paramZv, str, zv, bool);
  }
  
  protected Zv Zz(Zyg paramZyg, Zv paramZv) throws Zy_ {
    Zv zv = paramZv.ZM();
    Zyo<Object> zyo = paramZv.ZD();
    try {
    
    } catch (Zy_ zy_) {
      throw b(null);
    } 
    Zz zz = (zyo == null) ? null : zyo.Zd();
    try {
      if (zv == null)
        try {
          if (zz == null)
            return paramZv; 
        } catch (Zy_ zy_) {
          throw b(null);
        }  
    } catch (Zy_ zy_) {
      throw b(null);
    } 
    return (Zv)new com.fasterxml.Ze.Zf(paramZv, zv);
  }
  
  protected Zee Zm(Zyg paramZyg, Zv paramZv) throws Zy_ {
    Ziz ziz = paramZv.ZQ();
    if (ziz != null) {
      Zee zee = paramZyg.Zv().Za(ziz);
      try {
        if (zee != null) {
          try {
            if (paramZv instanceof Zw)
              paramZyg.Zm(ZH(), String.format(c(-8952, -9796), new Object[] { paramZv.ZT() })); 
          } catch (Zy_ zy_) {
            throw b(null);
          } 
          return zee;
        } 
      } catch (Zy_ zy_) {
        throw b(null);
      } 
    } 
    return null;
  }
  
  protected Zv Zg(Zyg paramZyg, Zv paramZv) {
    Zyo<Object> zyo = paramZv.ZD();
    String str = Zzp.ZP();
    if (zyo instanceof Zf) {
      Zf zf = (Zf)zyo;
      Zzp zzp = zf.Zw();
      if (!zzp.ZJ()) {
        Class clazz1 = paramZv.Zp().Zf();
        Class clazz2 = Zx.ZN(clazz1);
        try {
          if (clazz2 != null && clazz2 == this.ZF.Zf()) {
            Constructor[] arrayOfConstructor = (Constructor[])clazz1.getConstructors();
            int i = arrayOfConstructor.length;
            byte b = 0;
            while (b < i) {
              Constructor constructor = arrayOfConstructor[b];
              if (constructor.getParameterCount() == 1) {
                Class[] arrayOfClass = constructor.getParameterTypes();
                try {
                  if (clazz2.equals(arrayOfClass[0])) {
                    try {
                      if (paramZyg.ZP())
                        Zx.ZR(constructor, paramZyg.Zm(Zy9.OVERRIDE_PUBLIC_ACCESS_MODIFIERS)); 
                    } catch (UnsupportedOperationException unsupportedOperationException) {
                      throw b(null);
                    } 
                    return (Zv)new Zx(paramZv, constructor);
                  } 
                } catch (UnsupportedOperationException unsupportedOperationException) {
                  throw b(null);
                } 
              } 
              b++;
              if (str != null)
                break; 
            } 
          } 
        } catch (UnsupportedOperationException unsupportedOperationException) {
          throw b(null);
        } 
      } 
    } 
    return paramZv;
  }
  
  protected Zv Zy(Zyg paramZyg, Zv paramZv, Zyb paramZyb) throws Zy_ {
    Zj zj;
    Zv zv;
    Zd zd = paramZyb.Zs();
    if (zd != null) {
      Zyo<Object> zyo = paramZv.ZD();
      Boolean bool = zyo.Zu(paramZyg.Za());
      try {
        if (bool == null) {
          try {
            if (zd.ZD)
              return paramZv; 
          } catch (Zy_ zy_) {
            throw b(null);
          } 
        } else {
          try {
            if (!bool.booleanValue()) {
              try {
                if (!zd.ZD)
                  paramZyg.Zd(zyo); 
              } catch (Zy_ zy_) {
                throw b(null);
              } 
              return paramZv;
            } 
          } catch (Zy_ zy_) {
            throw b(null);
          } 
        } 
      } catch (Zy_ zy_) {
        throw b(null);
      } 
      Ziz ziz = zd.ZG;
      ziz.Zh(paramZyg.Zm(Zy9.OVERRIDE_PUBLIC_ACCESS_MODIFIERS));
      if (!(paramZv instanceof com.fasterxml.Ze.Zm))
        zj = Zj.Zw(paramZv, ziz); 
    } 
    Zzb zzb = Zj(paramZyg, (Zv)zj, paramZyb);
    if (zzb != null)
      zv = zj.ZC(zzb); 
    return zv;
  }
  
  public Zq Zm() {
    return Zq.DYNAMIC;
  }
  
  public Object Zy(Zyg paramZyg) throws Zy_ {
    try {
      return this.Zb.ZO(paramZyg);
    } catch (IOException iOException) {
      return Zx.ZG(paramZyg, iOException);
    } 
  }
  
  public boolean Zs() {
    return true;
  }
  
  public Boolean Zu(Zyc paramZyc) {
    return Boolean.TRUE;
  }
  
  public Class<?> ZX() {
    return this.ZF.Zf();
  }
  
  public Zz Zd() {
    return this.ZZ;
  }
  
  public Collection<Object> Z_() {
    ArrayList<String> arrayList = new ArrayList();
    Iterator<Zv> iterator = this.ZX.iterator();
    String str = Zzp.ZP();
    while (iterator.hasNext()) {
      Zv zv = iterator.next();
      arrayList.add(zv.ZT());
      if (str != null)
        break; 
    } 
    return (Collection)arrayList;
  }
  
  public Zk ZH() {
    return this.ZF;
  }
  
  public Zd Zb() {
    return Zd.POJO;
  }
  
  public Zv Zr(Zr paramZr) {
    return ZI(paramZr.Zb());
  }
  
  public Zv ZI(String paramString) {
    try {
    
    } catch (UnsupportedOperationException unsupportedOperationException) {
      throw b(null);
    } 
    Zv zv = (this.ZX == null) ? null : this.ZX.ZI(paramString);
    try {
      if (zv == null && this.ZT != null)
        zv = this.ZT.ZO(paramString); 
    } catch (UnsupportedOperationException unsupportedOperationException) {
      throw b(null);
    } 
    return zv;
  }
  
  public Zv ZW(String paramString) {
    try {
      if (this.ZB == null)
        return null; 
    } catch (UnsupportedOperationException unsupportedOperationException) {
      throw b(null);
    } 
    return this.ZB.get(paramString);
  }
  
  public Zzp Zw() {
    return this.Zb;
  }
  
  public abstract Object ZJ(Zg paramZg, Zyg paramZyg) throws IOException;
  
  public Object Zf(Zg paramZg, Zyg paramZyg, Zt paramZt) throws IOException {
    try {
      if (this.ZZ != null) {
        if (paramZg.ZM()) {
          Object object = paramZg.ZZ();
          if (object != null) {
            Object object1 = paramZt.ZC(paramZg, paramZyg);
            return Zq(paramZg, paramZyg, object1, object);
          } 
        } 
        Zl zl = paramZg.Zh();
        try {
          if (zl != null) {
            try {
              if (zl.Zl())
                return Zh(paramZg, paramZyg); 
            } catch (IOException iOException) {
              throw b(null);
            } 
            if (zl == Zl.START_OBJECT)
              zl = paramZg.ZV(); 
            try {
              if (zl == Zl.FIELD_NAME)
                try {
                  if (this.ZZ.ZI())
                    try {
                      if (this.ZZ.ZW(paramZg.ZS(), paramZg))
                        return Zh(paramZg, paramZyg); 
                    } catch (IOException iOException) {
                      throw b(null);
                    }  
                } catch (IOException iOException) {
                  throw b(null);
                }  
            } catch (IOException iOException) {
              throw b(null);
            } 
          } 
        } catch (IOException iOException) {
          throw b(null);
        } 
      } 
    } catch (IOException iOException) {
      throw b(null);
    } 
    return paramZt.ZC(paramZg, paramZyg);
  }
  
  protected Object Zq(Zg paramZg, Zyg paramZyg, Object paramObject1, Object paramObject2) throws IOException {
    // Byte code:
    //   0: invokestatic ZP : ()Ljava/lang/String;
    //   3: aload_0
    //   4: getfield ZZ : Lcom/fasterxml/Ze/Zz;
    //   7: invokevirtual ZP : ()Lcom/fasterxml/Zor/Zyo;
    //   10: astore #6
    //   12: astore #5
    //   14: aload #6
    //   16: invokevirtual ZX : ()Ljava/lang/Class;
    //   19: aload #4
    //   21: invokevirtual getClass : ()Ljava/lang/Class;
    //   24: if_acmpne -> 36
    //   27: aload #4
    //   29: astore #7
    //   31: aload #5
    //   33: ifnull -> 48
    //   36: aload_0
    //   37: aload_1
    //   38: aload_2
    //   39: aload #4
    //   41: aload #6
    //   43: invokevirtual Ze : (Lcom/fasterxml/Zb/Zg;Lcom/fasterxml/Zor/Zyg;Ljava/lang/Object;Lcom/fasterxml/Zor/Zyo;)Ljava/lang/Object;
    //   46: astore #7
    //   48: aload_2
    //   49: aload #7
    //   51: aload_0
    //   52: getfield ZZ : Lcom/fasterxml/Ze/Zz;
    //   55: getfield Zj : Lcom/fasterxml/Zys;
    //   58: aload_0
    //   59: getfield ZZ : Lcom/fasterxml/Ze/Zz;
    //   62: getfield ZL : Lcom/fasterxml/Zq_;
    //   65: invokevirtual Zi : (Ljava/lang/Object;Lcom/fasterxml/Zys;Lcom/fasterxml/Zq_;)Lcom/fasterxml/Ze/Zw;
    //   68: astore #8
    //   70: aload #8
    //   72: aload_3
    //   73: invokevirtual ZE : (Ljava/lang/Object;)V
    //   76: aload_0
    //   77: getfield ZZ : Lcom/fasterxml/Ze/Zz;
    //   80: getfield Zm : Lcom/fasterxml/Zo/Zv;
    //   83: astore #9
    //   85: aload #9
    //   87: ifnull -> 103
    //   90: aload #9
    //   92: aload_3
    //   93: aload #7
    //   95: invokevirtual ZN : (Ljava/lang/Object;Ljava/lang/Object;)Ljava/lang/Object;
    //   98: areturn
    //   99: invokestatic b : (Ljava/lang/Exception;)Ljava/lang/Exception;
    //   102: athrow
    //   103: aload_3
    //   104: areturn
    // Exception table:
    //   from	to	target	type
    //   85	99	99	java/io/IOException
  }
  
  protected Object Ze(Zg paramZg, Zyg paramZyg, Object paramObject, Zyo<Object> paramZyo) throws IOException {
    // Byte code:
    //   0: invokestatic ZP : ()Ljava/lang/String;
    //   3: aload_2
    //   4: aload_1
    //   5: invokevirtual Zb : (Lcom/fasterxml/Zb/Zg;)Lcom/fasterxml/Zm/Zl;
    //   8: astore #6
    //   10: astore #5
    //   12: aload_3
    //   13: instanceof java/lang/String
    //   16: ifeq -> 40
    //   19: aload #6
    //   21: aload_3
    //   22: checkcast java/lang/String
    //   25: invokevirtual ZD : (Ljava/lang/String;)V
    //   28: aload #5
    //   30: ifnull -> 129
    //   33: goto -> 40
    //   36: invokestatic b : (Ljava/lang/Exception;)Ljava/lang/Exception;
    //   39: athrow
    //   40: aload_3
    //   41: instanceof java/lang/Long
    //   44: ifeq -> 78
    //   47: goto -> 54
    //   50: invokestatic b : (Ljava/lang/Exception;)Ljava/lang/Exception;
    //   53: athrow
    //   54: aload #6
    //   56: aload_3
    //   57: checkcast java/lang/Long
    //   60: invokevirtual longValue : ()J
    //   63: invokevirtual Zw : (J)V
    //   66: aload #5
    //   68: ifnull -> 129
    //   71: goto -> 78
    //   74: invokestatic b : (Ljava/lang/Exception;)Ljava/lang/Exception;
    //   77: athrow
    //   78: aload_3
    //   79: instanceof java/lang/Integer
    //   82: ifeq -> 116
    //   85: goto -> 92
    //   88: invokestatic b : (Ljava/lang/Exception;)Ljava/lang/Exception;
    //   91: athrow
    //   92: aload #6
    //   94: aload_3
    //   95: checkcast java/lang/Integer
    //   98: invokevirtual intValue : ()I
    //   101: invokevirtual Zd : (I)V
    //   104: aload #5
    //   106: ifnull -> 129
    //   109: goto -> 116
    //   112: invokestatic b : (Ljava/lang/Exception;)Ljava/lang/Exception;
    //   115: athrow
    //   116: aload #6
    //   118: aload_3
    //   119: invokevirtual ZZ : (Ljava/lang/Object;)V
    //   122: goto -> 129
    //   125: invokestatic b : (Ljava/lang/Exception;)Ljava/lang/Exception;
    //   128: athrow
    //   129: aload #6
    //   131: aload_1
    //   132: invokevirtual ZG : ()Lcom/fasterxml/Zb/Z_;
    //   135: invokevirtual Zi : (Lcom/fasterxml/Zb/Z_;)Lcom/fasterxml/Zb/Zg;
    //   138: astore #7
    //   140: aload #7
    //   142: invokevirtual ZV : ()Lcom/fasterxml/Zb/Zl;
    //   145: pop
    //   146: aload #4
    //   148: aload #7
    //   150: aload_2
    //   151: invokevirtual deserialize : (Lcom/fasterxml/Zb/Zg;Lcom/fasterxml/Zor/Zyg;)Ljava/lang/Object;
    //   154: areturn
    // Exception table:
    //   from	to	target	type
    //   12	33	36	java/io/IOException
    //   19	47	50	java/io/IOException
    //   40	71	74	java/io/IOException
    //   54	85	88	java/io/IOException
    //   78	109	112	java/io/IOException
    //   92	122	125	java/io/IOException
  }
  
  protected Object Zz(Zg paramZg, Zyg paramZyg) throws IOException {
    return ZJ(paramZg, paramZyg);
  }
  
  protected Object Zh(Zg paramZg, Zyg paramZyg) throws IOException {
    Object object1 = this.ZZ.ZB(paramZg, paramZyg);
    Zw zw = paramZyg.Zi(object1, this.ZZ.Zj, this.ZZ.ZL);
    Object object2 = zw.Zp();
    try {
      if (object2 == null)
        throw new Zz7(paramZg, c(-8942, 18017) + object1 + c(-8957, 17069) + this.ZF + c(-8958, -18285), paramZg.Zz(), zw); 
    } catch (IOException iOException) {
      throw b(null);
    } 
    return object2;
  }
  
  protected Object Zb(Zg paramZg, Zyg paramZyg) throws IOException {
    Zyo<Object> zyo = Zi();
    if (zyo != null) {
      Object object = this.Zb.Zu(paramZyg, zyo.deserialize(paramZg, paramZyg));
      try {
        if (this.Zy != null)
          Zl(paramZyg, object); 
      } catch (IOException iOException) {
        throw b(null);
      } 
      return object;
    } 
    try {
      if (this.ZT != null)
        return ZZ(paramZg, paramZyg); 
    } catch (IOException iOException) {
      throw b(null);
    } 
    Class clazz = this.ZF.Zf();
    try {
      if (Zx.Zg(clazz))
        return paramZyg.ZV(clazz, null, paramZg, c(-8960, 15947), new Object[0]); 
    } catch (IOException iOException) {
      throw b(null);
    } 
    try {
      if (Zb.ZS(clazz))
        return paramZyg.ZV(clazz, null, paramZg, c(-8946, -31631), new Object[0]); 
    } catch (IOException iOException) {
      throw b(null);
    } 
    return paramZyg.ZV(clazz, Zw(), paramZg, c(-8951, -11398), new Object[0]);
  }
  
  protected abstract Object ZZ(Zg paramZg, Zyg paramZyg) throws IOException;
  
  public Object Zj(Zg paramZg, Zyg paramZyg) throws IOException {
    try {
      if (this.ZZ != null)
        return Zh(paramZg, paramZyg); 
    } catch (IOException iOException) {
      throw b(null);
    } 
    Zyo<Object> zyo = Zi();
    Zk zk = paramZg.ZL();
    try {
      if (zk == Zk.INT) {
        try {
          if (zyo != null && !this.Zb.ZE()) {
            Object object = this.Zb.Zu(paramZyg, zyo.deserialize(paramZg, paramZyg));
            try {
              if (this.Zy != null)
                Zl(paramZyg, object); 
            } catch (IOException iOException) {
              throw b(null);
            } 
            return object;
          } 
        } catch (IOException iOException) {
          throw b(null);
        } 
        return this.Zb.ZU(paramZyg, paramZg.Ze());
      } 
    } catch (IOException iOException) {
      throw b(null);
    } 
    try {
      if (zk == Zk.LONG) {
        try {
          if (zyo != null && !this.Zb.ZE()) {
            Object object = this.Zb.Zu(paramZyg, zyo.deserialize(paramZg, paramZyg));
            try {
              if (this.Zy != null)
                Zl(paramZyg, object); 
            } catch (IOException iOException) {
              throw b(null);
            } 
            return object;
          } 
        } catch (IOException iOException) {
          throw b(null);
        } 
        return this.Zb.Zg(paramZyg, paramZg.ZE());
      } 
    } catch (IOException iOException) {
      throw b(null);
    } 
    try {
      if (zk == Zk.BIG_INTEGER) {
        try {
          if (zyo != null && !this.Zb.ZX()) {
            Object object = this.Zb.Zu(paramZyg, zyo.deserialize(paramZg, paramZyg));
            try {
              if (this.Zy != null)
                Zl(paramZyg, object); 
            } catch (IOException iOException) {
              throw b(null);
            } 
            return object;
          } 
        } catch (IOException iOException) {
          throw b(null);
        } 
        return this.Zb.Zt(paramZyg, paramZg.ZX());
      } 
    } catch (IOException iOException) {
      throw b(null);
    } 
    return paramZyg.ZV(ZX(), Zw(), paramZg, c(-8950, -19370), new Object[] { paramZg.Zb() });
  }
  
  public Object ZE(Zg paramZg, Zyg paramZyg) throws IOException {
    try {
      if (this.ZZ != null)
        return Zh(paramZg, paramZyg); 
    } catch (IOException iOException) {
      throw b(null);
    } 
    Zyo<Object> zyo = Zi();
    try {
      if (zyo != null && !this.Zb.Zp()) {
        Object object = this.Zb.Zu(paramZyg, zyo.deserialize(paramZg, paramZyg));
        try {
          if (this.Zy != null)
            Zl(paramZyg, object); 
        } catch (IOException iOException) {
          throw b(null);
        } 
        return object;
      } 
    } catch (IOException iOException) {
      throw b(null);
    } 
    return ZD(paramZg, paramZyg);
  }
  
  public Object ZK(Zg paramZg, Zyg paramZyg) throws IOException {
    Zk zk = paramZg.ZL();
    try {
      if (zk == Zk.DOUBLE || zk == Zk.FLOAT) {
        Zyo<Object> zyo = Zi();
        try {
          if (zyo != null && !this.Zb.Zh()) {
            Object object = this.Zb.Zu(paramZyg, zyo.deserialize(paramZg, paramZyg));
            try {
              if (this.Zy != null)
                Zl(paramZyg, object); 
            } catch (IOException iOException) {
              throw b(null);
            } 
            return object;
          } 
        } catch (IOException iOException) {
          throw b(null);
        } 
        return this.Zb.Zn(paramZyg, paramZg.ZH());
      } 
    } catch (IOException iOException) {
      throw b(null);
    } 
    if (zk == Zk.BIG_DECIMAL) {
      Zyo<Object> zyo = Zi();
      try {
        if (zyo != null && !this.Zb.Zr()) {
          Object object = this.Zb.Zu(paramZyg, zyo.deserialize(paramZg, paramZyg));
          try {
            if (this.Zy != null)
              Zl(paramZyg, object); 
          } catch (IOException iOException) {
            throw b(null);
          } 
          return object;
        } 
      } catch (IOException iOException) {
        throw b(null);
      } 
      return this.Zb.Zk(paramZyg, paramZg.ZT());
    } 
    return paramZyg.ZV(ZX(), Zw(), paramZg, c(-8953, 6643), new Object[] { paramZg.Zb() });
  }
  
  public Object Zi(Zg paramZg, Zyg paramZyg) throws IOException {
    Zyo<Object> zyo = Zi();
    try {
      if (zyo != null && !this.Zb.ZH()) {
        Object object = this.Zb.Zu(paramZyg, zyo.deserialize(paramZg, paramZyg));
        try {
          if (this.Zy != null)
            Zl(paramZyg, object); 
        } catch (IOException iOException) {
          throw b(null);
        } 
        return object;
      } 
    } catch (IOException iOException) {
      throw b(null);
    } 
    try {
    
    } catch (IOException iOException) {
      throw b(null);
    } 
    boolean bool = (paramZg.Zh() == Zl.VALUE_TRUE) ? true : false;
    return this.Zb.ZI(paramZyg, bool);
  }
  
  public Object ZM(Zg paramZg, Zyg paramZyg) throws IOException {
    try {
      if (this.ZZ != null)
        return Zh(paramZg, paramZyg); 
    } catch (IOException iOException) {
      throw b(null);
    } 
    Zyo<Object> zyo = Zi();
    try {
      if (zyo != null && !this.Zb.Zp()) {
        Object object1 = this.Zb.Zu(paramZyg, zyo.deserialize(paramZg, paramZyg));
        try {
          if (this.Zy != null)
            Zl(paramZyg, object1); 
        } catch (IOException iOException) {
          throw b(null);
        } 
        return object1;
      } 
    } catch (IOException iOException) {
      throw b(null);
    } 
    Object object = paramZg.ZO();
    try {
      if (object != null && !this.ZF.Zq(object.getClass()))
        object = paramZyg.ZN(this.ZF, object, paramZg); 
    } catch (IOException iOException) {
      throw b(null);
    } 
    return object;
  }
  
  protected final Zyo<Object> Zi() {
    Zyo<Object> zyo = this.Zo;
    if (zyo == null)
      zyo = this.Zc; 
    return zyo;
  }
  
  protected void Zl(Zyg paramZyg, Object paramObject) throws IOException {
    Zv[] arrayOfZv = this.Zy;
    String str = Zzp.ZP();
    int i = arrayOfZv.length;
    byte b = 0;
    while (b < i) {
      Zv zv = arrayOfZv[b];
      zv.Zd(paramZyg, paramObject);
      b++;
      if (str != null)
        break; 
    } 
  }
  
  protected Object ZL(Zyg paramZyg, Object paramObject, Zl paramZl) throws IOException {
    paramZl.Zh();
    Zg zg = paramZl.Zp();
    String str = Zzp.ZP();
    while (zg.ZV() != Zl.END_OBJECT) {
      String str1 = zg.ZS();
      zg.ZV();
      Zb(zg, paramZyg, paramObject, str1);
      if (str != null)
        break; 
    } 
    return paramObject;
  }
  
  protected void ZN(Zg paramZg, Zyg paramZyg, Object paramObject, String paramString) throws IOException {
    // Byte code:
    //   0: invokestatic ZP : ()Ljava/lang/String;
    //   3: astore #5
    //   5: aload #4
    //   7: aload_0
    //   8: getfield Zq : Ljava/util/Set;
    //   11: aload_0
    //   12: getfield ZP : Ljava/util/Set;
    //   15: invokestatic Zv : (Ljava/lang/Object;Ljava/util/Collection;Ljava/util/Collection;)Z
    //   18: ifeq -> 42
    //   21: aload_0
    //   22: aload_1
    //   23: aload_2
    //   24: aload_3
    //   25: aload #4
    //   27: invokevirtual ZC : (Lcom/fasterxml/Zb/Zg;Lcom/fasterxml/Zor/Zyg;Ljava/lang/Object;Ljava/lang/String;)V
    //   30: aload #5
    //   32: ifnull -> 105
    //   35: goto -> 42
    //   38: invokestatic b : (Ljava/lang/Exception;)Ljava/lang/Exception;
    //   41: athrow
    //   42: aload_0
    //   43: getfield ZA : Lcom/fasterxml/Zo/Zl;
    //   46: ifnull -> 89
    //   49: goto -> 56
    //   52: invokestatic b : (Ljava/lang/Exception;)Ljava/lang/Exception;
    //   55: athrow
    //   56: aload_0
    //   57: getfield ZA : Lcom/fasterxml/Zo/Zl;
    //   60: aload_1
    //   61: aload_2
    //   62: aload_3
    //   63: aload #4
    //   65: invokevirtual ZU : (Lcom/fasterxml/Zb/Zg;Lcom/fasterxml/Zor/Zyg;Ljava/lang/Object;Ljava/lang/String;)V
    //   68: goto -> 105
    //   71: astore #6
    //   73: aload_0
    //   74: aload #6
    //   76: aload_3
    //   77: aload #4
    //   79: aload_2
    //   80: invokevirtual Zd : (Ljava/lang/Throwable;Ljava/lang/Object;Ljava/lang/String;Lcom/fasterxml/Zor/Zyg;)Ljava/lang/Object;
    //   83: pop
    //   84: aload #5
    //   86: ifnull -> 105
    //   89: aload_0
    //   90: aload_1
    //   91: aload_2
    //   92: aload_3
    //   93: aload #4
    //   95: invokevirtual Zb : (Lcom/fasterxml/Zb/Zg;Lcom/fasterxml/Zor/Zyg;Ljava/lang/Object;Ljava/lang/String;)V
    //   98: goto -> 105
    //   101: invokestatic b : (Ljava/lang/Exception;)Ljava/lang/Exception;
    //   104: athrow
    //   105: return
    // Exception table:
    //   from	to	target	type
    //   5	35	38	java/lang/Exception
    //   21	49	52	java/lang/Exception
    //   56	68	71	java/lang/Exception
    //   73	98	101	java/lang/Exception
  }
  
  protected void Zb(Zg paramZg, Zyg paramZyg, Object paramObject, String paramString) throws IOException {
    try {
      if (this.Za) {
        paramZg.Zc();
        return;
      } 
    } catch (IOException iOException) {
      throw b(null);
    } 
    try {
      if (Zeg.Zv(paramString, this.Zq, this.ZP))
        ZC(paramZg, paramZyg, paramObject, paramString); 
    } catch (IOException iOException) {
      throw b(null);
    } 
    super.Zb(paramZg, paramZyg, paramObject, paramString);
  }
  
  protected void ZC(Zg paramZg, Zyg paramZyg, Object paramObject, String paramString) throws IOException {
    try {
      if (paramZyg.Zg(Zyp.FAIL_ON_IGNORED_PROPERTIES))
        throw Zvo.ZM(paramZg, paramObject, paramString, Z_()); 
    } catch (IOException iOException) {
      throw b(null);
    } 
    paramZg.Zc();
  }
  
  protected Object Zg(Zg paramZg, Zyg paramZyg, Z_ paramZ_, Object paramObject, Zl paramZl) throws IOException {
    Zyo<Object> zyo = ZH(paramZyg, paramObject, paramZl);
    try {
      if (zyo != null) {
        if (paramZl != null) {
          paramZl.Zh();
          Zg zg = paramZl.Zi(paramZ_);
          zg.ZV();
          paramObject = zyo.ZI(zg, paramZyg, paramObject);
        } 
        if (paramZg != null)
          paramObject = zyo.ZI(paramZg, paramZyg, paramObject); 
        return paramObject;
      } 
    } catch (IOException iOException) {
      throw b(null);
    } 
    if (paramZl != null)
      paramObject = ZL(paramZyg, paramObject, paramZl); 
    if (paramZg != null)
      paramObject = ZI(paramZg, paramZyg, paramObject); 
    return paramObject;
  }
  
  protected Zyo<Object> ZH(Zyg paramZyg, Object paramObject, Zl paramZl) throws IOException {
    synchronized (this) {
      zyo = (this.Zp == null) ? null : this.Zp.get(new Zp(paramObject.getClass()));
    } 
    try {
      if (zyo != null)
        return zyo; 
    } catch (IOException iOException) {
      throw b(null);
    } 
    Zk zk = paramZyg.ZW(paramObject.getClass());
    Zyo<Object> zyo = paramZyg.ZP(zk);
    if (zyo != null)
      synchronized (this) {
        if (this.Zp == null)
          this.Zp = new HashMap<>(); 
        this.Zp.put(new Zp(paramObject.getClass()), zyo);
      }  
    return zyo;
  }
  
  public <T> T Zd(Throwable paramThrowable, Object paramObject, String paramString, Zyg paramZyg) throws IOException {
    throw Zy_.ZF(ZX(paramThrowable, paramZyg), paramObject, paramString);
  }
  
  private Throwable ZX(Throwable paramThrowable, Zyg paramZyg) throws IOException {
    // Byte code:
    //   0: invokestatic ZP : ()Ljava/lang/String;
    //   3: astore_3
    //   4: aload_1
    //   5: instanceof java/lang/reflect/InvocationTargetException
    //   8: ifeq -> 27
    //   11: aload_1
    //   12: invokevirtual getCause : ()Ljava/lang/Throwable;
    //   15: ifnull -> 27
    //   18: aload_1
    //   19: invokevirtual getCause : ()Ljava/lang/Throwable;
    //   22: astore_1
    //   23: aload_3
    //   24: ifnull -> 4
    //   27: aload_1
    //   28: invokestatic Zo : (Ljava/lang/Throwable;)Ljava/lang/Throwable;
    //   31: pop
    //   32: aload_2
    //   33: ifnull -> 53
    //   36: aload_2
    //   37: getstatic com/fasterxml/Zor/Zyp.WRAP_EXCEPTIONS : Lcom/fasterxml/Zor/Zyp;
    //   40: invokevirtual Zg : (Lcom/fasterxml/Zor/Zyp;)Z
    //   43: ifeq -> 61
    //   46: goto -> 53
    //   49: invokestatic b : (Ljava/lang/Exception;)Ljava/lang/Exception;
    //   52: athrow
    //   53: iconst_1
    //   54: goto -> 62
    //   57: invokestatic b : (Ljava/lang/Exception;)Ljava/lang/Exception;
    //   60: athrow
    //   61: iconst_0
    //   62: istore #4
    //   64: aload_1
    //   65: instanceof java/io/IOException
    //   68: ifeq -> 106
    //   71: iload #4
    //   73: ifeq -> 97
    //   76: goto -> 83
    //   79: invokestatic b : (Ljava/lang/Exception;)Ljava/lang/Exception;
    //   82: athrow
    //   83: aload_1
    //   84: instanceof com/fasterxml/Zb/Zd
    //   87: ifne -> 123
    //   90: goto -> 97
    //   93: invokestatic b : (Ljava/lang/Exception;)Ljava/lang/Exception;
    //   96: athrow
    //   97: aload_1
    //   98: checkcast java/io/IOException
    //   101: athrow
    //   102: invokestatic b : (Ljava/lang/Exception;)Ljava/lang/Exception;
    //   105: athrow
    //   106: iload #4
    //   108: ifne -> 123
    //   111: aload_1
    //   112: invokestatic Zq : (Ljava/lang/Throwable;)Ljava/lang/Throwable;
    //   115: pop
    //   116: goto -> 123
    //   119: invokestatic b : (Ljava/lang/Exception;)Ljava/lang/Exception;
    //   122: athrow
    //   123: aload_1
    //   124: areturn
    // Exception table:
    //   from	to	target	type
    //   27	46	49	java/io/IOException
    //   36	57	57	java/io/IOException
    //   64	76	79	java/io/IOException
    //   71	90	93	java/io/IOException
    //   83	102	102	java/io/IOException
    //   106	116	119	java/io/IOException
  }
  
  protected <T> T ZR(Throwable paramThrowable, Zyg paramZyg) throws IOException {
    String str = Zzp.ZP();
    while (paramThrowable instanceof java.lang.reflect.InvocationTargetException && paramThrowable.getCause() != null) {
      paramThrowable = paramThrowable.getCause();
      if (str != null)
        break; 
    } 
    try {
      Zx.Zo(paramThrowable);
      if (paramThrowable instanceof IOException)
        throw (IOException)paramThrowable; 
    } catch (IOException iOException) {
      throw b(null);
    } 
    try {
      if (paramZyg == null)
        throw new IllegalArgumentException(paramThrowable.getMessage(), paramThrowable); 
    } catch (IOException iOException) {
      throw b(null);
    } 
    try {
      if (!paramZyg.Zg(Zyp.WRAP_EXCEPTIONS))
        Zx.Zq(paramThrowable); 
    } catch (IOException iOException) {
      throw b(null);
    } 
    return (T)paramZyg.Zs(this.ZF.Zf(), null, paramThrowable);
  }
  
  static {
    // Byte code:
    //   0: bipush #17
    //   2: anewarray java/lang/String
    //   5: astore #5
    //   7: iconst_0
    //   8: istore_3
    //   9: ldc 'H#B}bG+y2/O]Ed;EdQ\\tAR\\n7\DYMGHi*\\rgTgqfq jF7^,7Ave*|F\\b,y%CkCMdi3;F;\\bwg!_+HhFA6<gIeFRg:L+pR4TDupt22Yy8(bUR:&3?pI]A!t$liB"dE}YiAN_eRM"!Jdg6TDwI;d[08JI%hWmK\\tH6u3S;bcFqj]9H=Lan`zU}l\\b |S]I+Z,cs Ru!E5"JAa:(oRzp7!Kx{gP q3Tove7/*AyArkf*b~5eLZG{z\\n>V<v_\\n>{r&=|NwxSh9{O`%fYV|E'_>c:}NM2%[k#}z!fXS%h4S8\\rQhAAbq{#O}=q)[EQI@kFr5-&OK/mxJ_tJ\\tD0Ac\\n?z{z\\t31=t8?;l1,[( |BC'@Hp%r3SD9\\rVZ(Lzd|'EJ_~cg"e\\ntVa3\\bFJkC37P kN-1(N\7'LtVR4=Z:+R/o{zxE\\b?U0grAD93 )HSy7i|i'
    //   11: dup
    //   12: astore_2
    //   13: invokevirtual length : ()I
    //   16: istore #4
    //   18: iconst_2
    //   19: istore_1
    //   20: iconst_m1
    //   21: istore_0
    //   22: bipush #29
    //   24: iinc #0, 1
    //   27: aload_2
    //   28: iload_0
    //   29: dup
    //   30: iload_1
    //   31: iadd
    //   32: invokevirtual substring : (II)Ljava/lang/String;
    //   35: iconst_m1
    //   36: goto -> 142
    //   39: aload #5
    //   41: swap
    //   42: iload_3
    //   43: iinc #3, 1
    //   46: swap
    //   47: aastore
    //   48: iload_0
    //   49: iload_1
    //   50: iadd
    //   51: dup
    //   52: istore_0
    //   53: iload #4
    //   55: if_icmpge -> 67
    //   58: aload_2
    //   59: iload_0
    //   60: invokevirtual charAt : (I)C
    //   63: istore_1
    //   64: goto -> 22
    //   67: ldc 'z89tLHJeOX '6>b01I,]@"ZoF2Y@Z4dK^ws?\\r/4\\nH>et_A\\bFD\Kb'
    //   69: dup
    //   70: astore_2
    //   71: invokevirtual length : ()I
    //   74: istore #4
    //   76: bipush #103
    //   78: istore_1
    //   79: iconst_m1
    //   80: istore_0
    //   81: bipush #12
    //   83: iinc #0, 1
    //   86: aload_2
    //   87: iload_0
    //   88: dup
    //   89: iload_1
    //   90: iadd
    //   91: invokevirtual substring : (II)Ljava/lang/String;
    //   94: iconst_0
    //   95: goto -> 142
    //   98: aload #5
    //   100: swap
    //   101: iload_3
    //   102: iinc #3, 1
    //   105: swap
    //   106: aastore
    //   107: iload_0
    //   108: iload_1
    //   109: iadd
    //   110: dup
    //   111: istore_0
    //   112: iload #4
    //   114: if_icmpge -> 126
    //   117: aload_2
    //   118: iload_0
    //   119: invokevirtual charAt : (I)C
    //   122: istore_1
    //   123: goto -> 81
    //   126: aload #5
    //   128: putstatic com/fasterxml/Zo/Zf.e : [Ljava/lang/String;
    //   131: bipush #17
    //   133: anewarray java/lang/String
    //   136: putstatic com/fasterxml/Zo/Zf.f : [Ljava/lang/String;
    //   139: goto -> 300
    //   142: dup_x2
    //   143: pop
    //   144: invokevirtual toCharArray : ()[C
    //   147: dup_x1
    //   148: arraylength
    //   149: dup_x2
    //   150: pop
    //   151: iconst_0
    //   152: istore #6
    //   154: dup2_x1
    //   155: pop2
    //   156: dup_x2
    //   157: iconst_1
    //   158: if_icmpgt -> 260
    //   161: dup2
    //   162: swap
    //   163: iload #6
    //   165: dup2_x1
    //   166: caload
    //   167: swap
    //   168: iload #6
    //   170: bipush #7
    //   172: irem
    //   173: tableswitch default -> 242, 0 -> 212, 1 -> 217, 2 -> 222, 3 -> 227, 4 -> 232, 5 -> 237
    //   212: bipush #109
    //   214: goto -> 244
    //   217: bipush #38
    //   219: goto -> 244
    //   222: bipush #40
    //   224: goto -> 244
    //   227: bipush #58
    //   229: goto -> 244
    //   232: bipush #23
    //   234: goto -> 244
    //   237: bipush #20
    //   239: goto -> 244
    //   242: bipush #31
    //   244: ixor
    //   245: ixor
    //   246: i2c
    //   247: castore
    //   248: iinc #6, 1
    //   251: dup
    //   252: ifne -> 260
    //   255: dup2
    //   256: dup_x1
    //   257: goto -> 165
    //   260: dup2_x1
    //   261: pop2
    //   262: dup_x2
    //   263: iload #6
    //   265: if_icmpgt -> 161
    //   268: pop
    //   269: new java/lang/String
    //   272: dup_x1
    //   273: swap
    //   274: invokespecial <init> : ([C)V
    //   277: invokevirtual intern : ()Ljava/lang/String;
    //   280: swap
    //   281: pop
    //   282: swap
    //   283: tableswitch default -> 39, 0 -> 98
    //   300: new com/fasterxml/Zor/Zr
    //   303: dup
    //   304: sipush #-8955
    //   307: sipush #-26834
    //   310: invokestatic c : (II)Ljava/lang/String;
    //   313: invokespecial <init> : (Ljava/lang/String;)V
    //   316: putstatic com/fasterxml/Zo/Zf.ZV : Lcom/fasterxml/Zor/Zr;
    //   319: return
  }
  
  private static Exception b(Exception paramException) {
    return paramException;
  }
  
  private static String c(int paramInt1, int paramInt2) {
    int i = (paramInt1 ^ 0xFFFFDD02) & 0xFFFF;
    if (f[i] == null) {
      char[] arrayOfChar = e[i].toCharArray();
      switch (arrayOfChar[0] & 0xFF) {
        case 0:
        
        case 1:
        
        case 2:
        
        case 3:
        
        case 4:
        
        case 5:
        
        case 6:
        
        case 7:
        
        case 8:
        
        case 9:
        
        case 10:
        
        case 11:
        
        case 12:
        
        case 13:
        
        case 14:
        
        case 15:
        
        case 16:
        
        case 17:
        
        case 18:
        
        case 19:
        
        case 20:
        
        case 21:
        
        case 22:
        
        case 23:
        
        case 24:
        
        case 25:
        
        case 26:
        
        case 27:
        
        case 28:
        
        case 29:
        
        case 30:
        
        case 31:
        
        case 32:
        
        case 33:
        
        case 34:
        
        case 35:
        
        case 36:
        
        case 37:
        
        case 38:
        
        case 39:
        
        case 40:
        
        case 41:
        
        case 42:
        
        case 43:
        
        case 44:
        
        case 45:
        
        case 46:
        
        case 47:
        
        case 48:
        
        case 49:
        
        case 50:
        
        case 51:
        
        case 52:
        
        case 53:
        
        case 54:
        
        case 55:
        
        case 56:
        
        case 57:
        
        case 58:
        
        case 59:
        
        case 60:
        
        case 61:
        
        case 62:
        
        case 63:
        
        case 64:
        
        case 65:
        
        case 66:
        
        case 67:
        
        case 68:
        
        case 69:
        
        case 70:
        
        case 71:
        
        case 72:
        
        case 73:
        
        case 74:
        
        case 75:
        
        case 76:
        
        case 77:
        
        case 78:
        
        case 79:
        
        case 80:
        
        case 81:
        
        case 82:
        
        case 83:
        
        case 84:
        
        case 85:
        
        case 86:
        
        case 87:
        
        case 88:
        
        case 89:
        
        case 90:
        
        case 91:
        
        case 92:
        
        case 93:
        
        case 94:
        
        case 95:
        
        case 96:
        
        case 97:
        
        case 98:
        
        case 99:
        
        case 100:
        
        case 101:
        
        case 102:
        
        case 103:
        
        case 104:
        
        case 105:
        
        case 106:
        
        case 107:
        
        case 108:
        
        case 109:
        
        case 110:
        
        case 111:
        
        case 112:
        
        case 113:
        
        case 114:
        
        case 115:
        
        case 116:
        
        case 117:
        
        case 118:
        
        case 119:
        
        case 120:
        
        case 121:
        
        case 122:
        
        case 123:
        
        case 124:
        
        case 125:
        
        case 126:
        
        case 127:
        
        case 128:
        
        case 129:
        
        case 130:
        
        case 131:
        
        case 132:
        
        case 133:
        
        case 134:
        
        case 135:
        
        case 136:
        
        case 137:
        
        case 138:
        
        case 139:
        
        case 140:
        
        case 141:
        
        case 142:
        
        case 143:
        
        case 144:
        
        case 145:
        
        case 146:
        
        case 147:
        
        case 148:
        
        case 149:
        
        case 150:
        
        case 151:
        
        case 152:
        
        case 153:
        
        case 154:
        
        case 155:
        
        case 156:
        
        case 157:
        
        case 158:
        
        case 159:
        
        case 160:
        
        case 161:
        
        case 162:
        
        case 163:
        
        case 164:
        
        case 165:
        
        case 166:
        
        case 167:
        
        case 168:
        
        case 169:
        
        case 170:
        
        case 171:
        
        case 172:
        
        case 173:
        
        case 174:
        
        case 175:
        
        case 176:
        
        case 177:
        
        case 178:
        
        case 179:
        
        case 180:
        
        case 181:
        
        case 182:
        
        case 183:
        
        case 184:
        
        case 185:
        
        case 186:
        
        case 187:
        
        case 188:
        
        case 189:
        
        case 190:
        
        case 191:
        
        case 192:
        
        case 193:
        
        case 194:
        
        case 195:
        
        case 196:
        
        case 197:
        
        case 198:
        
        case 199:
        
        case 200:
        
        case 201:
        
        case 202:
        
        case 203:
        
        case 204:
        
        case 205:
        
        case 206:
        
        case 207:
        
        case 208:
        
        case 209:
        
        case 210:
        
        case 211:
        
        case 212:
        
        case 213:
        
        case 214:
        
        case 215:
        
        case 216:
        
        case 217:
        
        case 218:
        
        case 219:
        
        case 220:
        
        case 221:
        
        case 222:
        
        case 223:
        
        case 224:
        
        case 225:
        
        case 226:
        
        case 227:
        
        case 228:
        
        case 229:
        
        case 230:
        
        case 231:
        
        case 232:
        
        case 233:
        
        case 234:
        
        case 235:
        
        case 236:
        
        case 237:
        
        case 238:
        
        case 239:
        
        case 240:
        
        case 241:
        
        case 242:
        
        case 243:
        
        case 244:
        
        case 245:
        
        case 246:
        
        case 247:
        
        case 248:
        
        case 249:
        
        case 250:
        
        case 251:
        
        case 252:
        
        case 253:
        
        case 254:
        
        default:
          break;
      } 
      char c = '';
      int j = (paramInt2 & 0xFF) - c;
      if (j < 0)
        j += 256; 
      int k = ((paramInt2 & 0xFFFF) >>> 8) - c;
      if (k < 0)
        k += 256; 
      for (byte b = 0; b < arrayOfChar.length; b++) {
        int m = b % 2;
        if (m == 0) {
          arrayOfChar[b] = (char)(arrayOfChar[b] ^ j);
          j = ((j >>> 3 | j << 5) ^ arrayOfChar[b]) & 0xFF;
        } else {
          arrayOfChar[b] = (char)(arrayOfChar[b] ^ k);
          k = ((k >>> 3 | k << 5) ^ arrayOfChar[b]) & 0xFF;
        } 
      } 
      f[i] = (new String(arrayOfChar)).intern();
    } 
    return f[i];
  }
}


/* Location:              C:\Program Files\BurpSuitePro\burpsuite_pro.jar!\com\fasterxml\Zo\Zf.class
 * Java compiler version: 8 (52.0)
 * JD-Core Version:       1.1.3
 */