package com.fasterxml.Zo;

import com.fasterxml.Z_.Zn;
import com.fasterxml.Zb.Zg;
import com.fasterxml.Ze.Zd;
import com.fasterxml.Ze.Zh;
import com.fasterxml.Ze.Zs;
import com.fasterxml.Zgd;
import com.fasterxml.Zh.Ze;
import com.fasterxml.Zh.Zf;
import com.fasterxml.Zh.Zg;
import com.fasterxml.Zh.Zi;
import com.fasterxml.Zh.Zn;
import com.fasterxml.Zh.Zo;
import com.fasterxml.Zh.Zs;
import com.fasterxml.Zj.Zb;
import com.fasterxml.Zj.Zf;
import com.fasterxml.Zj.Zg;
import com.fasterxml.Zj.Zqn;
import com.fasterxml.Zm.Zee;
import com.fasterxml.Zm.Zef;
import com.fasterxml.Zm.Zi;
import com.fasterxml.Zm.Zl;
import com.fasterxml.Zm.Zx;
import com.fasterxml.Zor.Zb;
import com.fasterxml.Zor.Zf;
import com.fasterxml.Zor.Zk;
import com.fasterxml.Zor.Zm;
import com.fasterxml.Zor.Zo;
import com.fasterxml.Zor.Zp;
import com.fasterxml.Zor.Zr;
import com.fasterxml.Zor.Zt;
import com.fasterxml.Zor.Zy9;
import com.fasterxml.Zor.Zy_;
import com.fasterxml.Zor.Zyb;
import com.fasterxml.Zor.Zyc;
import com.fasterxml.Zor.Zyg;
import com.fasterxml.Zor.Zyo;
import com.fasterxml.Zor.Zyv;
import com.fasterxml.Zoz.Zi8;
import com.fasterxml.Zoz.Zia;
import com.fasterxml.Zoz.Zic;
import com.fasterxml.Zoz.Zif;
import com.fasterxml.Zoz.Zin;
import com.fasterxml.Zoz.Ziq;
import com.fasterxml.Zoz.Ziv;
import com.fasterxml.Zoz.Ziz;
import com.fasterxml.Zoz.Zp;
import com.fasterxml.Zoz.Zy;
import com.fasterxml.Zp.Zk;
import com.fasterxml.Zp.Zt;
import com.fasterxml.Zs.Za;
import com.fasterxml.Zs.Zf;
import com.fasterxml.Zs.Zf5;
import com.fasterxml.Zs.Zfd;
import com.fasterxml.Zs.Zfm;
import com.fasterxml.Zs.Zfv;
import com.fasterxml.Zs.Zfy;
import com.fasterxml.Zs.Zfz;
import com.fasterxml.Zs.Zui;
import com.fasterxml.Zs.Zus;
import com.fasterxml.Zvj;
import com.fasterxml.Zz6;
import java.io.Serializable;
import java.util.Collection;
import java.util.Iterator;
import java.util.List;
import java.util.Map;
import java.util.concurrent.atomic.AtomicReference;

public abstract class Zj extends Zz implements Serializable {
  private static final Class<?> ZS;
  
  private static final Class<?> Z_;
  
  private static final Class<?> Zu;
  
  private static final Class<?> ZN;
  
  private static final Class<?> Zw;
  
  private static final Class<?> ZO;
  
  protected static final Zr Zf;
  
  protected final Zb Zo;
  
  private static final String[] a;
  
  private static final String[] b;
  
  protected Zj(Zb paramZb) {
    this.Zo = paramZb;
  }
  
  protected abstract Zz Zv(Zb paramZb);
  
  public final Zz ZA(Zza paramZza) {
    return Zv(this.Zo.ZF(paramZza));
  }
  
  public final Zz ZF(Zr paramZr) {
    return Zv(this.Zo.ZM(paramZr));
  }
  
  public final Zz Zd(Zb paramZb) {
    return Zv(this.Zo.Zh(paramZb));
  }
  
  public final Zz ZD(Zm paramZm) {
    return Zv(this.Zo.Zj(paramZm));
  }
  
  public final Zz ZR(Zzi paramZzi) {
    return Zv(this.Zo.Zy(paramZzi));
  }
  
  public Zk Zb(Zyc paramZyc, Zk paramZk) throws Zy_ {
    while (true) {
      Zk zk = Zo(paramZyc, paramZk);
      try {
        if (zk == null)
          return paramZk; 
      } catch (Zy_ zy_) {
        throw a(null);
      } 
      Class clazz = paramZk.Zf();
      Class<?> clazz1 = zk.Zf();
      try {
        if (clazz != clazz1)
          try {
            if (clazz.isAssignableFrom(clazz1)) {
              paramZk = zk;
              continue;
            } 
            throw new IllegalArgumentException(a(8516, 65) + paramZk + a(8514, 27250) + zk + a(8539, -23384));
          } catch (Zy_ zy_) {
            throw a(null);
          }  
      } catch (Zy_ zy_) {
        throw a(null);
      } 
      throw new IllegalArgumentException(a(8516, 65) + paramZk + a(8514, 27250) + zk + a(8539, -23384));
    } 
  }
  
  private Zk Zo(Zyc paramZyc, Zk paramZk) throws Zy_ {
    Class clazz = paramZk.Zf();
    String str = Zzp.ZP();
    if (this.Zo.ZA())
      for (Zm zm : this.Zo.ZU()) {
        Zk zk = zm.ZS(paramZyc, paramZk);
        try {
          if (zk != null)
            try {
              if (!zk.ZP(clazz))
                return zk; 
            } catch (Zy_ zy_) {
              throw a(null);
            }  
        } catch (Zy_ zy_) {
          throw a(null);
        } 
        if (str != null)
          break; 
      }  
    return null;
  }
  
  public Zzp ZP(Zyg paramZyg, Zyv paramZyv) throws Zy_ {
    Zyc zyc = paramZyg.Za();
    String str = Zzp.ZP();
    Zzp zzp = null;
    Zia zia = paramZyv.Zo();
    Object object = paramZyg.Zv().ZK(zia);
    if (object != null)
      zzp = Zu(zyc, (Ziv)zia, object); 
    if (zzp == null) {
      zzp = Zd.ZX(zyc, paramZyv.Zl());
      if (zzp == null)
        zzp = ZY(paramZyg, paramZyv); 
    } 
    if (this.Zo.ZS())
      for (Zzi zzi : this.Zo.Zq()) {
        zzp = zzi.Zs(zyc, paramZyv, zzp);
        try {
          if (zzp == null)
            paramZyg.ZI(paramZyv, a(8522, -15047), new Object[] { zzi.getClass().getName() }); 
        } catch (Zy_ zy_) {
          throw a(null);
        } 
        if (str != null)
          break; 
      }  
    if (zzp != null)
      zzp = zzp.ZY(paramZyg, paramZyv); 
    return zzp;
  }
  
  protected Zzp ZY(Zyg paramZyg, Zyv paramZyv) throws Zy_ {
    Zyc zyc = paramZyg.Za();
    Zi8<?> zi8 = zyc.Zr(paramZyv.Zl(), paramZyv.Zo());
    Zg zg = zyc.ZB();
    Zh zh = new Zh(paramZyv, (Zf)zyc);
    Map<Zif, Zp[]> map = ZL(paramZyg, paramZyv);
    Zn zn = new Zn(paramZyg, paramZyv, zi8, zh, map);
    try {
    
    } catch (Zy_ zy_) {
      throw a(null);
    } 
    Zg(paramZyg, zn, !zg.ZK());
    if (paramZyv.Zf().Zp()) {
      boolean bool = paramZyv.ZP();
      try {
        if (!bool) {
          boolean bool1 = zg.Z_(paramZyv.Zl());
          try {
            ZT(paramZyg, zn, bool1);
            if (zn.ZD())
              try {
                if (!zn.ZL())
                  ZI(paramZyg, zn, zn.ZR()); 
              } catch (Zy_ zy_) {
                throw a(null);
              }  
          } catch (Zy_ zy_) {
            throw a(null);
          } 
        } 
      } catch (Zy_ zy_) {
        throw a(null);
      } 
    } 
    try {
      if (zn.ZJ())
        try {
          if (!zn.Zn())
            try {
              if (!zn.ZL())
                ZF(paramZyg, zn, zn.ZF()); 
            } catch (Zy_ zy_) {
              throw a(null);
            }  
        } catch (Zy_ zy_) {
          throw a(null);
        }  
    } catch (Zy_ zy_) {
      throw a(null);
    } 
    return zn.Zm.Zk(paramZyg);
  }
  
  protected Map<Zif, Zp[]> ZL(Zyg paramZyg, Zyv paramZyv) throws Zy_ {
    // Byte code:
    //   0: invokestatic ZP : ()Ljava/lang/String;
    //   3: invokestatic emptyMap : ()Ljava/util/Map;
    //   6: astore #4
    //   8: astore_3
    //   9: aload_2
    //   10: invokevirtual ZT : ()Ljava/util/List;
    //   13: invokeinterface iterator : ()Ljava/util/Iterator;
    //   18: astore #5
    //   20: aload #5
    //   22: invokeinterface hasNext : ()Z
    //   27: ifeq -> 238
    //   30: aload #5
    //   32: invokeinterface next : ()Ljava/lang/Object;
    //   37: checkcast com/fasterxml/Zoz/Zp
    //   40: astore #6
    //   42: aload #6
    //   44: invokevirtual Zk : ()Ljava/util/Iterator;
    //   47: astore #7
    //   49: aload #7
    //   51: invokeinterface hasNext : ()Z
    //   56: ifeq -> 234
    //   59: aload #7
    //   61: invokeinterface next : ()Ljava/lang/Object;
    //   66: checkcast com/fasterxml/Zoz/Zin
    //   69: astore #8
    //   71: aload #8
    //   73: invokevirtual Zd : ()Lcom/fasterxml/Zoz/Zif;
    //   76: astore #9
    //   78: aload #4
    //   80: aload #9
    //   82: invokeinterface get : (Ljava/lang/Object;)Ljava/lang/Object;
    //   87: checkcast [Lcom/fasterxml/Zoz/Zp;
    //   90: astore #10
    //   92: aload #8
    //   94: invokevirtual ZF : ()I
    //   97: istore #11
    //   99: aload #10
    //   101: ifnonnull -> 156
    //   104: aload #4
    //   106: invokeinterface isEmpty : ()Z
    //   111: ifeq -> 130
    //   114: goto -> 121
    //   117: invokestatic a : (Ljava/lang/Exception;)Ljava/lang/Exception;
    //   120: athrow
    //   121: new java/util/LinkedHashMap
    //   124: dup
    //   125: invokespecial <init> : ()V
    //   128: astore #4
    //   130: aload #9
    //   132: invokevirtual ZL : ()I
    //   135: anewarray com/fasterxml/Zoz/Zp
    //   138: astore #10
    //   140: aload #4
    //   142: aload #9
    //   144: aload #10
    //   146: invokeinterface put : (Ljava/lang/Object;Ljava/lang/Object;)Ljava/lang/Object;
    //   151: pop
    //   152: aload_3
    //   153: ifnull -> 223
    //   156: aload #10
    //   158: iload #11
    //   160: aaload
    //   161: ifnull -> 223
    //   164: goto -> 171
    //   167: invokestatic a : (Ljava/lang/Exception;)Ljava/lang/Exception;
    //   170: athrow
    //   171: aload_1
    //   172: aload_2
    //   173: sipush #8536
    //   176: sipush #15402
    //   179: invokestatic a : (II)Ljava/lang/String;
    //   182: iconst_4
    //   183: anewarray java/lang/Object
    //   186: dup
    //   187: iconst_0
    //   188: iload #11
    //   190: invokestatic valueOf : (I)Ljava/lang/Integer;
    //   193: aastore
    //   194: dup
    //   195: iconst_1
    //   196: aload #9
    //   198: aastore
    //   199: dup
    //   200: iconst_2
    //   201: aload #10
    //   203: iload #11
    //   205: aaload
    //   206: aastore
    //   207: dup
    //   208: iconst_3
    //   209: aload #6
    //   211: aastore
    //   212: invokevirtual ZI : (Lcom/fasterxml/Zor/Zyv;Ljava/lang/String;[Ljava/lang/Object;)Ljava/lang/Object;
    //   215: pop
    //   216: goto -> 223
    //   219: invokestatic a : (Ljava/lang/Exception;)Ljava/lang/Exception;
    //   222: athrow
    //   223: aload #10
    //   225: iload #11
    //   227: aload #6
    //   229: aastore
    //   230: aload_3
    //   231: ifnull -> 49
    //   234: aload_3
    //   235: ifnull -> 20
    //   238: aload #4
    //   240: areturn
    // Exception table:
    //   from	to	target	type
    //   99	114	117	com/fasterxml/Zor/Zy_
    //   140	164	167	com/fasterxml/Zor/Zy_
    //   156	216	219	com/fasterxml/Zor/Zy_
  }
  
  public Zzp Zu(Zyc paramZyc, Ziv paramZiv, Object paramObject) throws Zy_ {
    try {
      if (paramObject == null)
        return null; 
    } catch (Zy_ zy_) {
      throw a(null);
    } 
    try {
      if (paramObject instanceof Zzp)
        return (Zzp)paramObject; 
    } catch (Zy_ zy_) {
      throw a(null);
    } 
    try {
      if (!(paramObject instanceof Class))
        throw new IllegalStateException(a(8543, 4222) + paramObject.getClass().getName() + a(8520, -17275)); 
    } catch (Zy_ zy_) {
      throw a(null);
    } 
    Class<?> clazz = (Class)paramObject;
    try {
      if (Zx.Zu(clazz))
        return null; 
    } catch (Zy_ zy_) {
      throw a(null);
    } 
    try {
      if (!Zzp.class.isAssignableFrom(clazz))
        throw new IllegalStateException(a(8518, -22099) + clazz.getName() + a(8540, -32120)); 
    } catch (Zy_ zy_) {
      throw a(null);
    } 
    Zqn zqn = paramZyc.Zf();
    if (zqn != null) {
      Zzp zzp = zqn.ZX((Zf)paramZyc, paramZiv, clazz);
      try {
        if (zzp != null)
          return zzp; 
      } catch (Zy_ zy_) {
        throw a(null);
      } 
    } 
    return (Zzp)Zx.ZR(clazz, paramZyc.Zd());
  }
  
  protected void ZT(Zyg paramZyg, Zn paramZn, boolean paramBoolean) throws Zy_ {
    // Byte code:
    //   0: aload_2
    //   1: getfield ZO : Lcom/fasterxml/Zor/Zyv;
    //   4: astore #5
    //   6: aload_2
    //   7: getfield Zm : Lcom/fasterxml/Ze/Zh;
    //   10: astore #6
    //   12: aload_2
    //   13: invokevirtual Zq : ()Lcom/fasterxml/Zor/Zt;
    //   16: astore #7
    //   18: invokestatic ZP : ()Ljava/lang/String;
    //   21: aload_2
    //   22: getfield ZQ : Lcom/fasterxml/Zoz/Zi8;
    //   25: astore #8
    //   27: aload_2
    //   28: getfield ZZ : Ljava/util/Map;
    //   31: astore #9
    //   33: aload #5
    //   35: invokevirtual ZB : ()Lcom/fasterxml/Zoz/Zik;
    //   38: astore #10
    //   40: astore #4
    //   42: aload #10
    //   44: ifnull -> 93
    //   47: aload #6
    //   49: invokevirtual ZP : ()Z
    //   52: ifeq -> 79
    //   55: goto -> 62
    //   58: invokestatic a : (Ljava/lang/Exception;)Ljava/lang/Exception;
    //   61: athrow
    //   62: aload_0
    //   63: aload_1
    //   64: aload #10
    //   66: invokevirtual ZY : (Lcom/fasterxml/Zor/Zyg;Lcom/fasterxml/Zoz/Ziv;)Z
    //   69: ifeq -> 93
    //   72: goto -> 79
    //   75: invokestatic a : (Ljava/lang/Exception;)Ljava/lang/Exception;
    //   78: athrow
    //   79: aload #6
    //   81: aload #10
    //   83: invokevirtual ZS : (Lcom/fasterxml/Zoz/Zif;)V
    //   86: goto -> 93
    //   89: invokestatic a : (Ljava/lang/Exception;)Ljava/lang/Exception;
    //   92: athrow
    //   93: aload #5
    //   95: invokevirtual ZU : ()Ljava/util/List;
    //   98: invokeinterface iterator : ()Ljava/util/Iterator;
    //   103: astore #11
    //   105: aload #11
    //   107: invokeinterface hasNext : ()Z
    //   112: ifeq -> 372
    //   115: aload #11
    //   117: invokeinterface next : ()Ljava/lang/Object;
    //   122: checkcast com/fasterxml/Zoz/Zik
    //   125: astore #12
    //   127: aload #7
    //   129: aload_1
    //   130: invokevirtual Za : ()Lcom/fasterxml/Zor/Zyc;
    //   133: aload #12
    //   135: invokevirtual ZD : (Lcom/fasterxml/Zj/Zf;Lcom/fasterxml/Zoz/Ziv;)Lcom/fasterxml/Zgd;
    //   138: astore #13
    //   140: getstatic com/fasterxml/Zgd.DISABLED : Lcom/fasterxml/Zgd;
    //   143: aload #13
    //   145: if_acmpne -> 160
    //   148: aload #4
    //   150: ifnull -> 105
    //   153: goto -> 160
    //   156: invokestatic a : (Ljava/lang/Exception;)Ljava/lang/Exception;
    //   159: athrow
    //   160: aload #13
    //   162: ifnonnull -> 216
    //   165: iload_3
    //   166: ifeq -> 105
    //   169: goto -> 176
    //   172: invokestatic a : (Ljava/lang/Exception;)Ljava/lang/Exception;
    //   175: athrow
    //   176: aload #8
    //   178: aload #12
    //   180: invokeinterface ZU : (Lcom/fasterxml/Zoz/Ziz;)Z
    //   185: ifeq -> 105
    //   188: aload_2
    //   189: aload #7
    //   191: aload #12
    //   193: aload #9
    //   195: aload #12
    //   197: invokeinterface get : (Ljava/lang/Object;)Ljava/lang/Object;
    //   202: checkcast [Lcom/fasterxml/Zoz/Zp;
    //   205: invokestatic ZK : (Lcom/fasterxml/Zor/Zt;Lcom/fasterxml/Zoz/Zif;[Lcom/fasterxml/Zoz/Zp;)Lcom/fasterxml/Ze/Zs;
    //   208: invokevirtual Zc : (Lcom/fasterxml/Ze/Zs;)V
    //   211: aload #4
    //   213: ifnull -> 105
    //   216: getstatic com/fasterxml/Zo/Zzn.ZW : [I
    //   219: aload #13
    //   221: invokevirtual ordinal : ()I
    //   224: iaload
    //   225: lookupswitch default -> 321, 1 -> 252, 2 -> 281
    //   252: aload_0
    //   253: aload_1
    //   254: aload #5
    //   256: aload #6
    //   258: aload #7
    //   260: aload #12
    //   262: aconst_null
    //   263: invokestatic ZK : (Lcom/fasterxml/Zor/Zt;Lcom/fasterxml/Zoz/Zif;[Lcom/fasterxml/Zoz/Zp;)Lcom/fasterxml/Ze/Zs;
    //   266: invokevirtual ZU : (Lcom/fasterxml/Zor/Zyg;Lcom/fasterxml/Zor/Zyv;Lcom/fasterxml/Ze/Zh;Lcom/fasterxml/Ze/Zs;)V
    //   269: aload #4
    //   271: ifnull -> 363
    //   274: goto -> 281
    //   277: invokestatic a : (Ljava/lang/Exception;)Ljava/lang/Exception;
    //   280: athrow
    //   281: aload_0
    //   282: aload_1
    //   283: aload #5
    //   285: aload #6
    //   287: aload #7
    //   289: aload #12
    //   291: aload #9
    //   293: aload #12
    //   295: invokeinterface get : (Ljava/lang/Object;)Ljava/lang/Object;
    //   300: checkcast [Lcom/fasterxml/Zoz/Zp;
    //   303: invokestatic ZK : (Lcom/fasterxml/Zor/Zt;Lcom/fasterxml/Zoz/Zif;[Lcom/fasterxml/Zoz/Zp;)Lcom/fasterxml/Ze/Zs;
    //   306: invokevirtual ZP : (Lcom/fasterxml/Zor/Zyg;Lcom/fasterxml/Zor/Zyv;Lcom/fasterxml/Ze/Zh;Lcom/fasterxml/Ze/Zs;)V
    //   309: aload #4
    //   311: ifnull -> 363
    //   314: goto -> 321
    //   317: invokestatic a : (Ljava/lang/Exception;)Ljava/lang/Exception;
    //   320: athrow
    //   321: aload_0
    //   322: aload_1
    //   323: aload #5
    //   325: aload #6
    //   327: aload #7
    //   329: aload #12
    //   331: aload #9
    //   333: aload #12
    //   335: invokeinterface get : (Ljava/lang/Object;)Ljava/lang/Object;
    //   340: checkcast [Lcom/fasterxml/Zoz/Zp;
    //   343: invokestatic ZK : (Lcom/fasterxml/Zor/Zt;Lcom/fasterxml/Zoz/Zif;[Lcom/fasterxml/Zoz/Zp;)Lcom/fasterxml/Ze/Zs;
    //   346: aload_1
    //   347: invokevirtual Za : ()Lcom/fasterxml/Zor/Zyc;
    //   350: invokevirtual ZB : ()Lcom/fasterxml/Zj/Zg;
    //   353: invokevirtual Zj : (Lcom/fasterxml/Zor/Zyg;Lcom/fasterxml/Zor/Zyv;Lcom/fasterxml/Ze/Zh;Lcom/fasterxml/Ze/Zs;Lcom/fasterxml/Zj/Zg;)V
    //   356: goto -> 363
    //   359: invokestatic a : (Ljava/lang/Exception;)Ljava/lang/Exception;
    //   362: athrow
    //   363: aload_2
    //   364: invokevirtual ZI : ()V
    //   367: aload #4
    //   369: ifnull -> 105
    //   372: return
    // Exception table:
    //   from	to	target	type
    //   42	55	58	com/fasterxml/Zor/Zy_
    //   47	72	75	com/fasterxml/Zor/Zy_
    //   62	86	89	com/fasterxml/Zor/Zy_
    //   140	153	156	com/fasterxml/Zor/Zy_
    //   160	169	172	com/fasterxml/Zor/Zy_
    //   216	274	277	com/fasterxml/Zor/Zy_
    //   252	314	317	com/fasterxml/Zor/Zy_
    //   281	356	359	com/fasterxml/Zor/Zy_
  }
  
  protected void ZI(Zyg paramZyg, Zn paramZn, List<Zs> paramList) throws Zy_ {
    // Byte code:
    //   0: aload_1
    //   1: invokevirtual Za : ()Lcom/fasterxml/Zor/Zyc;
    //   4: astore #5
    //   6: aload_2
    //   7: getfield ZO : Lcom/fasterxml/Zor/Zyv;
    //   10: astore #6
    //   12: invokestatic ZP : ()Ljava/lang/String;
    //   15: aload_2
    //   16: getfield Zm : Lcom/fasterxml/Ze/Zh;
    //   19: astore #7
    //   21: aload_2
    //   22: invokevirtual Zq : ()Lcom/fasterxml/Zor/Zt;
    //   25: astore #8
    //   27: aload_2
    //   28: getfield ZQ : Lcom/fasterxml/Zoz/Zi8;
    //   31: astore #9
    //   33: astore #4
    //   35: aconst_null
    //   36: astore #10
    //   38: aload #5
    //   40: invokevirtual ZB : ()Lcom/fasterxml/Zj/Zg;
    //   43: invokevirtual Zp : ()Z
    //   46: ifeq -> 72
    //   49: aload #6
    //   51: invokevirtual ZY : ()Z
    //   54: ifne -> 72
    //   57: goto -> 64
    //   60: invokestatic a : (Ljava/lang/Exception;)Ljava/lang/Exception;
    //   63: athrow
    //   64: iconst_1
    //   65: goto -> 73
    //   68: invokestatic a : (Ljava/lang/Exception;)Ljava/lang/Exception;
    //   71: athrow
    //   72: iconst_0
    //   73: istore #11
    //   75: aload_3
    //   76: invokeinterface iterator : ()Ljava/util/Iterator;
    //   81: astore #12
    //   83: aload #12
    //   85: invokeinterface hasNext : ()Z
    //   90: ifeq -> 786
    //   93: aload #12
    //   95: invokeinterface next : ()Ljava/lang/Object;
    //   100: checkcast com/fasterxml/Ze/Zs
    //   103: astore #13
    //   105: aload #13
    //   107: invokevirtual ZD : ()I
    //   110: istore #14
    //   112: aload #13
    //   114: invokevirtual ZC : ()Lcom/fasterxml/Zoz/Zif;
    //   117: astore #15
    //   119: iload #14
    //   121: iconst_1
    //   122: if_icmpne -> 314
    //   125: aload #13
    //   127: iconst_0
    //   128: invokevirtual ZL : (I)Lcom/fasterxml/Zoz/Zp;
    //   131: astore #16
    //   133: iload #11
    //   135: ifne -> 160
    //   138: aload_0
    //   139: aload #6
    //   141: aload #8
    //   143: aload #15
    //   145: aload #16
    //   147: invokespecial ZJ : (Lcom/fasterxml/Zor/Zyv;Lcom/fasterxml/Zor/Zt;Lcom/fasterxml/Zoz/Zif;Lcom/fasterxml/Zoz/Zp;)Z
    //   150: ifeq -> 168
    //   153: goto -> 160
    //   156: invokestatic a : (Ljava/lang/Exception;)Ljava/lang/Exception;
    //   159: athrow
    //   160: iconst_1
    //   161: goto -> 169
    //   164: invokestatic a : (Ljava/lang/Exception;)Ljava/lang/Exception;
    //   167: athrow
    //   168: iconst_0
    //   169: istore #17
    //   171: iload #17
    //   173: ifeq -> 277
    //   176: iconst_1
    //   177: anewarray com/fasterxml/Zo/Zv
    //   180: astore #18
    //   182: aload #13
    //   184: iconst_0
    //   185: invokevirtual ZR : (I)Lcom/fasterxml/Zz6;
    //   188: astore #19
    //   190: aload #13
    //   192: iconst_0
    //   193: invokevirtual ZT : (I)Lcom/fasterxml/Zor/Zr;
    //   196: astore #20
    //   198: aload #20
    //   200: ifnonnull -> 240
    //   203: aload #13
    //   205: iconst_0
    //   206: invokevirtual ZA : (I)Lcom/fasterxml/Zor/Zr;
    //   209: astore #20
    //   211: aload #20
    //   213: ifnonnull -> 240
    //   216: aload #19
    //   218: ifnonnull -> 240
    //   221: goto -> 228
    //   224: invokestatic a : (Ljava/lang/Exception;)Ljava/lang/Exception;
    //   227: athrow
    //   228: aload #4
    //   230: ifnull -> 83
    //   233: goto -> 240
    //   236: invokestatic a : (Ljava/lang/Exception;)Ljava/lang/Exception;
    //   239: athrow
    //   240: aload #18
    //   242: iconst_0
    //   243: aload_0
    //   244: aload_1
    //   245: aload #6
    //   247: aload #20
    //   249: iconst_0
    //   250: aload #13
    //   252: iconst_0
    //   253: invokevirtual Zg : (I)Lcom/fasterxml/Zoz/Zin;
    //   256: aload #19
    //   258: invokevirtual Zk : (Lcom/fasterxml/Zor/Zyg;Lcom/fasterxml/Zor/Zyv;Lcom/fasterxml/Zor/Zr;ILcom/fasterxml/Zoz/Zin;Lcom/fasterxml/Zz6;)Lcom/fasterxml/Zo/Zv;
    //   261: aastore
    //   262: aload #7
    //   264: aload #15
    //   266: iconst_0
    //   267: aload #18
    //   269: invokevirtual Zb : (Lcom/fasterxml/Zoz/Zif;Z[Lcom/fasterxml/Zo/Zv;)V
    //   272: aload #4
    //   274: ifnull -> 83
    //   277: aload_0
    //   278: aload #7
    //   280: aload #15
    //   282: iconst_0
    //   283: aload #9
    //   285: aload #15
    //   287: invokeinterface ZU : (Lcom/fasterxml/Zoz/Ziz;)Z
    //   292: invokevirtual Zf : (Lcom/fasterxml/Ze/Zh;Lcom/fasterxml/Zoz/Zif;ZZ)Z
    //   295: pop
    //   296: aload #16
    //   298: ifnull -> 83
    //   301: aload #16
    //   303: checkcast com/fasterxml/Zoz/Zb
    //   306: invokevirtual Zs : ()V
    //   309: aload #4
    //   311: ifnull -> 83
    //   314: iconst_m1
    //   315: istore #16
    //   317: iload #14
    //   319: anewarray com/fasterxml/Zo/Zv
    //   322: astore #17
    //   324: iconst_0
    //   325: istore #18
    //   327: iconst_0
    //   328: istore #19
    //   330: iconst_0
    //   331: istore #20
    //   333: iconst_0
    //   334: istore #21
    //   336: iload #21
    //   338: iload #14
    //   340: if_icmpge -> 566
    //   343: aload #15
    //   345: iload #21
    //   347: invokevirtual Zz : (I)Lcom/fasterxml/Zoz/Zin;
    //   350: astore #22
    //   352: aload #13
    //   354: iload #21
    //   356: invokevirtual ZL : (I)Lcom/fasterxml/Zoz/Zp;
    //   359: astore #23
    //   361: aload #8
    //   363: aload #22
    //   365: invokevirtual ZU : (Lcom/fasterxml/Zoz/Ziz;)Lcom/fasterxml/Zz6;
    //   368: astore #24
    //   370: aload #23
    //   372: ifnonnull -> 383
    //   375: aconst_null
    //   376: goto -> 388
    //   379: invokestatic a : (Ljava/lang/Exception;)Ljava/lang/Exception;
    //   382: athrow
    //   383: aload #23
    //   385: invokevirtual ZU : ()Lcom/fasterxml/Zor/Zr;
    //   388: astore #25
    //   390: aload #23
    //   392: ifnull -> 460
    //   395: aload #23
    //   397: invokevirtual ZF : ()Z
    //   400: ifne -> 425
    //   403: goto -> 410
    //   406: invokestatic a : (Ljava/lang/Exception;)Ljava/lang/Exception;
    //   409: athrow
    //   410: aload #6
    //   412: invokevirtual ZY : ()Z
    //   415: ifeq -> 460
    //   418: goto -> 425
    //   421: invokestatic a : (Ljava/lang/Exception;)Ljava/lang/Exception;
    //   424: athrow
    //   425: iinc #18, 1
    //   428: aload #17
    //   430: iload #21
    //   432: aload_0
    //   433: aload_1
    //   434: aload #6
    //   436: aload #25
    //   438: iload #21
    //   440: aload #22
    //   442: aload #24
    //   444: invokevirtual Zk : (Lcom/fasterxml/Zor/Zyg;Lcom/fasterxml/Zor/Zyv;Lcom/fasterxml/Zor/Zr;ILcom/fasterxml/Zoz/Zin;Lcom/fasterxml/Zz6;)Lcom/fasterxml/Zo/Zv;
    //   447: aastore
    //   448: aload #4
    //   450: ifnull -> 558
    //   453: goto -> 460
    //   456: invokestatic a : (Ljava/lang/Exception;)Ljava/lang/Exception;
    //   459: athrow
    //   460: aload #24
    //   462: ifnull -> 507
    //   465: goto -> 472
    //   468: invokestatic a : (Ljava/lang/Exception;)Ljava/lang/Exception;
    //   471: athrow
    //   472: iinc #20, 1
    //   475: aload #17
    //   477: iload #21
    //   479: aload_0
    //   480: aload_1
    //   481: aload #6
    //   483: aload #25
    //   485: iload #21
    //   487: aload #22
    //   489: aload #24
    //   491: invokevirtual Zk : (Lcom/fasterxml/Zor/Zyg;Lcom/fasterxml/Zor/Zyv;Lcom/fasterxml/Zor/Zr;ILcom/fasterxml/Zoz/Zin;Lcom/fasterxml/Zz6;)Lcom/fasterxml/Zo/Zv;
    //   494: aastore
    //   495: aload #4
    //   497: ifnull -> 558
    //   500: goto -> 507
    //   503: invokestatic a : (Ljava/lang/Exception;)Ljava/lang/Exception;
    //   506: athrow
    //   507: aload #8
    //   509: aload #22
    //   511: invokevirtual Za : (Lcom/fasterxml/Zoz/Ziz;)Lcom/fasterxml/Zm/Zee;
    //   514: astore #26
    //   516: aload #26
    //   518: ifnull -> 542
    //   521: aload_0
    //   522: aload_1
    //   523: aload #6
    //   525: aload #22
    //   527: invokevirtual ZR : (Lcom/fasterxml/Zor/Zyg;Lcom/fasterxml/Zor/Zyv;Lcom/fasterxml/Zoz/Zin;)V
    //   530: aload #4
    //   532: ifnull -> 558
    //   535: goto -> 542
    //   538: invokestatic a : (Ljava/lang/Exception;)Ljava/lang/Exception;
    //   541: athrow
    //   542: iload #16
    //   544: ifge -> 558
    //   547: goto -> 554
    //   550: invokestatic a : (Ljava/lang/Exception;)Ljava/lang/Exception;
    //   553: athrow
    //   554: iload #21
    //   556: istore #16
    //   558: iinc #21, 1
    //   561: aload #4
    //   563: ifnull -> 336
    //   566: iload #18
    //   568: iload #19
    //   570: iadd
    //   571: istore #21
    //   573: iload #18
    //   575: ifgt -> 590
    //   578: iload #20
    //   580: ifle -> 742
    //   583: goto -> 590
    //   586: invokestatic a : (Ljava/lang/Exception;)Ljava/lang/Exception;
    //   589: athrow
    //   590: iload #21
    //   592: iload #20
    //   594: iadd
    //   595: iload #14
    //   597: if_icmpne -> 629
    //   600: goto -> 607
    //   603: invokestatic a : (Ljava/lang/Exception;)Ljava/lang/Exception;
    //   606: athrow
    //   607: aload #7
    //   609: aload #15
    //   611: iconst_0
    //   612: aload #17
    //   614: invokevirtual Zb : (Lcom/fasterxml/Zoz/Zif;Z[Lcom/fasterxml/Zo/Zv;)V
    //   617: aload #4
    //   619: ifnull -> 83
    //   622: goto -> 629
    //   625: invokestatic a : (Ljava/lang/Exception;)Ljava/lang/Exception;
    //   628: athrow
    //   629: iload #18
    //   631: ifne -> 673
    //   634: iload #20
    //   636: iconst_1
    //   637: iadd
    //   638: iload #14
    //   640: if_icmpne -> 673
    //   643: goto -> 650
    //   646: invokestatic a : (Ljava/lang/Exception;)Ljava/lang/Exception;
    //   649: athrow
    //   650: aload #7
    //   652: aload #15
    //   654: iconst_0
    //   655: aload #17
    //   657: iconst_0
    //   658: invokevirtual ZA : (Lcom/fasterxml/Zoz/Zif;Z[Lcom/fasterxml/Zo/Zv;I)V
    //   661: aload #4
    //   663: ifnull -> 83
    //   666: goto -> 673
    //   669: invokestatic a : (Ljava/lang/Exception;)Ljava/lang/Exception;
    //   672: athrow
    //   673: aload #13
    //   675: iload #16
    //   677: invokevirtual ZA : (I)Lcom/fasterxml/Zor/Zr;
    //   680: astore #22
    //   682: aload #22
    //   684: ifnull -> 702
    //   687: aload #22
    //   689: invokevirtual Zf : ()Z
    //   692: ifeq -> 742
    //   695: goto -> 702
    //   698: invokestatic a : (Ljava/lang/Exception;)Ljava/lang/Exception;
    //   701: athrow
    //   702: aload_1
    //   703: aload #6
    //   705: sipush #8512
    //   708: sipush #20992
    //   711: invokestatic a : (II)Ljava/lang/String;
    //   714: iconst_2
    //   715: anewarray java/lang/Object
    //   718: dup
    //   719: iconst_0
    //   720: iload #16
    //   722: invokestatic valueOf : (I)Ljava/lang/Integer;
    //   725: aastore
    //   726: dup
    //   727: iconst_1
    //   728: aload #15
    //   730: aastore
    //   731: invokevirtual ZI : (Lcom/fasterxml/Zor/Zyv;Ljava/lang/String;[Ljava/lang/Object;)Ljava/lang/Object;
    //   734: pop
    //   735: goto -> 742
    //   738: invokestatic a : (Ljava/lang/Exception;)Ljava/lang/Exception;
    //   741: athrow
    //   742: aload #7
    //   744: invokevirtual ZP : ()Z
    //   747: ifne -> 781
    //   750: aload #10
    //   752: ifnonnull -> 771
    //   755: goto -> 762
    //   758: invokestatic a : (Ljava/lang/Exception;)Ljava/lang/Exception;
    //   761: athrow
    //   762: new java/util/LinkedList
    //   765: dup
    //   766: invokespecial <init> : ()V
    //   769: astore #10
    //   771: aload #10
    //   773: aload #15
    //   775: invokeinterface add : (Ljava/lang/Object;)Z
    //   780: pop
    //   781: aload #4
    //   783: ifnull -> 83
    //   786: aload #10
    //   788: ifnull -> 843
    //   791: aload #7
    //   793: invokevirtual Zg : ()Z
    //   796: ifne -> 843
    //   799: goto -> 806
    //   802: invokestatic a : (Ljava/lang/Exception;)Ljava/lang/Exception;
    //   805: athrow
    //   806: aload #7
    //   808: invokevirtual Zk : ()Z
    //   811: ifne -> 843
    //   814: goto -> 821
    //   817: invokestatic a : (Ljava/lang/Exception;)Ljava/lang/Exception;
    //   820: athrow
    //   821: aload_0
    //   822: aload_1
    //   823: aload #6
    //   825: aload #9
    //   827: aload #8
    //   829: aload #7
    //   831: aload #10
    //   833: invokespecial Zw : (Lcom/fasterxml/Zor/Zyg;Lcom/fasterxml/Zor/Zyv;Lcom/fasterxml/Zoz/Zi8;Lcom/fasterxml/Zor/Zt;Lcom/fasterxml/Ze/Zh;Ljava/util/List;)V
    //   836: goto -> 843
    //   839: invokestatic a : (Ljava/lang/Exception;)Ljava/lang/Exception;
    //   842: athrow
    //   843: return
    // Exception table:
    //   from	to	target	type
    //   38	57	60	com/fasterxml/Zor/Zy_
    //   49	68	68	com/fasterxml/Zor/Zy_
    //   133	153	156	com/fasterxml/Zor/Zy_
    //   138	164	164	com/fasterxml/Zor/Zy_
    //   211	221	224	com/fasterxml/Zor/Zy_
    //   216	233	236	com/fasterxml/Zor/Zy_
    //   370	379	379	com/fasterxml/Zor/Zy_
    //   390	403	406	com/fasterxml/Zor/Zy_
    //   395	418	421	com/fasterxml/Zor/Zy_
    //   410	453	456	com/fasterxml/Zor/Zy_
    //   425	465	468	com/fasterxml/Zor/Zy_
    //   460	500	503	com/fasterxml/Zor/Zy_
    //   516	535	538	com/fasterxml/Zor/Zy_
    //   521	547	550	com/fasterxml/Zor/Zy_
    //   573	583	586	com/fasterxml/Zor/Zy_
    //   578	600	603	com/fasterxml/Zor/Zy_
    //   590	622	625	com/fasterxml/Zor/Zy_
    //   629	643	646	com/fasterxml/Zor/Zy_
    //   634	666	669	com/fasterxml/Zor/Zy_
    //   682	695	698	com/fasterxml/Zor/Zy_
    //   687	735	738	com/fasterxml/Zor/Zy_
    //   742	755	758	com/fasterxml/Zor/Zy_
    //   786	799	802	com/fasterxml/Zor/Zy_
    //   791	814	817	com/fasterxml/Zor/Zy_
    //   806	836	839	com/fasterxml/Zor/Zy_
  }
  
  protected void Zg(Zyg paramZyg, Zn paramZn, boolean paramBoolean) throws Zy_ {
    // Byte code:
    //   0: invokestatic ZP : ()Ljava/lang/String;
    //   3: aload_2
    //   4: getfield ZO : Lcom/fasterxml/Zor/Zyv;
    //   7: astore #5
    //   9: astore #4
    //   11: aload_2
    //   12: getfield Zm : Lcom/fasterxml/Ze/Zh;
    //   15: astore #6
    //   17: aload_2
    //   18: invokevirtual Zq : ()Lcom/fasterxml/Zor/Zt;
    //   21: astore #7
    //   23: aload_2
    //   24: getfield ZQ : Lcom/fasterxml/Zoz/Zi8;
    //   27: astore #8
    //   29: aload_2
    //   30: getfield ZZ : Ljava/util/Map;
    //   33: astore #9
    //   35: aload #5
    //   37: invokevirtual ZK : ()Ljava/util/List;
    //   40: invokeinterface iterator : ()Ljava/util/Iterator;
    //   45: astore #10
    //   47: aload #10
    //   49: invokeinterface hasNext : ()Z
    //   54: ifeq -> 336
    //   57: aload #10
    //   59: invokeinterface next : ()Ljava/lang/Object;
    //   64: checkcast com/fasterxml/Zoz/Ziq
    //   67: astore #11
    //   69: aload #7
    //   71: aload_1
    //   72: invokevirtual Za : ()Lcom/fasterxml/Zor/Zyc;
    //   75: aload #11
    //   77: invokevirtual ZD : (Lcom/fasterxml/Zj/Zf;Lcom/fasterxml/Zoz/Ziv;)Lcom/fasterxml/Zgd;
    //   80: astore #12
    //   82: aload #11
    //   84: invokevirtual ZL : ()I
    //   87: istore #13
    //   89: aload #12
    //   91: ifnonnull -> 140
    //   94: iload_3
    //   95: ifeq -> 47
    //   98: goto -> 105
    //   101: invokestatic a : (Ljava/lang/Exception;)Ljava/lang/Exception;
    //   104: athrow
    //   105: iload #13
    //   107: iconst_1
    //   108: if_icmpne -> 47
    //   111: aload #8
    //   113: aload #11
    //   115: invokeinterface ZU : (Lcom/fasterxml/Zoz/Ziz;)Z
    //   120: ifeq -> 47
    //   123: aload_2
    //   124: aload #7
    //   126: aload #11
    //   128: aconst_null
    //   129: invokestatic ZK : (Lcom/fasterxml/Zor/Zt;Lcom/fasterxml/Zoz/Zif;[Lcom/fasterxml/Zoz/Zp;)Lcom/fasterxml/Ze/Zs;
    //   132: invokevirtual Zw : (Lcom/fasterxml/Ze/Zs;)V
    //   135: aload #4
    //   137: ifnull -> 47
    //   140: aload #12
    //   142: getstatic com/fasterxml/Zgd.DISABLED : Lcom/fasterxml/Zgd;
    //   145: if_acmpne -> 160
    //   148: aload #4
    //   150: ifnull -> 47
    //   153: goto -> 160
    //   156: invokestatic a : (Ljava/lang/Exception;)Ljava/lang/Exception;
    //   159: athrow
    //   160: iload #13
    //   162: ifne -> 184
    //   165: aload #6
    //   167: aload #11
    //   169: invokevirtual ZS : (Lcom/fasterxml/Zoz/Zif;)V
    //   172: aload #4
    //   174: ifnull -> 47
    //   177: goto -> 184
    //   180: invokestatic a : (Ljava/lang/Exception;)Ljava/lang/Exception;
    //   183: athrow
    //   184: getstatic com/fasterxml/Zo/Zzn.ZW : [I
    //   187: aload #12
    //   189: invokevirtual ordinal : ()I
    //   192: iaload
    //   193: tableswitch default -> 289, 1 -> 220, 2 -> 249, 3 -> 289
    //   220: aload_0
    //   221: aload_1
    //   222: aload #5
    //   224: aload #6
    //   226: aload #7
    //   228: aload #11
    //   230: aconst_null
    //   231: invokestatic ZK : (Lcom/fasterxml/Zor/Zt;Lcom/fasterxml/Zoz/Zif;[Lcom/fasterxml/Zoz/Zp;)Lcom/fasterxml/Ze/Zs;
    //   234: invokevirtual ZU : (Lcom/fasterxml/Zor/Zyg;Lcom/fasterxml/Zor/Zyv;Lcom/fasterxml/Ze/Zh;Lcom/fasterxml/Ze/Zs;)V
    //   237: aload #4
    //   239: ifnull -> 327
    //   242: goto -> 249
    //   245: invokestatic a : (Ljava/lang/Exception;)Ljava/lang/Exception;
    //   248: athrow
    //   249: aload_0
    //   250: aload_1
    //   251: aload #5
    //   253: aload #6
    //   255: aload #7
    //   257: aload #11
    //   259: aload #9
    //   261: aload #11
    //   263: invokeinterface get : (Ljava/lang/Object;)Ljava/lang/Object;
    //   268: checkcast [Lcom/fasterxml/Zoz/Zp;
    //   271: invokestatic ZK : (Lcom/fasterxml/Zor/Zt;Lcom/fasterxml/Zoz/Zif;[Lcom/fasterxml/Zoz/Zp;)Lcom/fasterxml/Ze/Zs;
    //   274: invokevirtual ZP : (Lcom/fasterxml/Zor/Zyg;Lcom/fasterxml/Zor/Zyv;Lcom/fasterxml/Ze/Zh;Lcom/fasterxml/Ze/Zs;)V
    //   277: aload #4
    //   279: ifnull -> 327
    //   282: goto -> 289
    //   285: invokestatic a : (Ljava/lang/Exception;)Ljava/lang/Exception;
    //   288: athrow
    //   289: aload_0
    //   290: aload_1
    //   291: aload #5
    //   293: aload #6
    //   295: aload #7
    //   297: aload #11
    //   299: aload #9
    //   301: aload #11
    //   303: invokeinterface get : (Ljava/lang/Object;)Ljava/lang/Object;
    //   308: checkcast [Lcom/fasterxml/Zoz/Zp;
    //   311: invokestatic ZK : (Lcom/fasterxml/Zor/Zt;Lcom/fasterxml/Zoz/Zif;[Lcom/fasterxml/Zoz/Zp;)Lcom/fasterxml/Ze/Zs;
    //   314: getstatic com/fasterxml/Zj/Zg.Zk : Lcom/fasterxml/Zj/Zg;
    //   317: invokevirtual Zj : (Lcom/fasterxml/Zor/Zyg;Lcom/fasterxml/Zor/Zyv;Lcom/fasterxml/Ze/Zh;Lcom/fasterxml/Ze/Zs;Lcom/fasterxml/Zj/Zg;)V
    //   320: goto -> 327
    //   323: invokestatic a : (Ljava/lang/Exception;)Ljava/lang/Exception;
    //   326: athrow
    //   327: aload_2
    //   328: invokevirtual Zs : ()V
    //   331: aload #4
    //   333: ifnull -> 47
    //   336: return
    // Exception table:
    //   from	to	target	type
    //   89	98	101	com/fasterxml/Zor/Zy_
    //   140	153	156	com/fasterxml/Zor/Zy_
    //   160	177	180	com/fasterxml/Zor/Zy_
    //   184	242	245	com/fasterxml/Zor/Zy_
    //   220	282	285	com/fasterxml/Zor/Zy_
    //   249	320	323	com/fasterxml/Zor/Zy_
  }
  
  protected void ZF(Zyg paramZyg, Zn paramZn, List<Zs> paramList) throws Zy_ {
    // Byte code:
    //   0: aload_2
    //   1: getfield ZO : Lcom/fasterxml/Zor/Zyv;
    //   4: astore #5
    //   6: aload_2
    //   7: getfield Zm : Lcom/fasterxml/Ze/Zh;
    //   10: astore #6
    //   12: invokestatic ZP : ()Ljava/lang/String;
    //   15: aload_2
    //   16: invokevirtual Zq : ()Lcom/fasterxml/Zor/Zt;
    //   19: astore #7
    //   21: astore #4
    //   23: aload_2
    //   24: getfield ZQ : Lcom/fasterxml/Zoz/Zi8;
    //   27: astore #8
    //   29: aload_2
    //   30: getfield ZZ : Ljava/util/Map;
    //   33: astore #9
    //   35: aload_3
    //   36: invokeinterface iterator : ()Ljava/util/Iterator;
    //   41: astore #10
    //   43: aload #10
    //   45: invokeinterface hasNext : ()Z
    //   50: ifeq -> 605
    //   53: aload #10
    //   55: invokeinterface next : ()Ljava/lang/Object;
    //   60: checkcast com/fasterxml/Ze/Zs
    //   63: astore #11
    //   65: aload #11
    //   67: invokevirtual ZD : ()I
    //   70: istore #12
    //   72: aload #11
    //   74: invokevirtual ZC : ()Lcom/fasterxml/Zoz/Zif;
    //   77: astore #13
    //   79: aload #9
    //   81: aload #13
    //   83: invokeinterface get : (Ljava/lang/Object;)Ljava/lang/Object;
    //   88: checkcast [Lcom/fasterxml/Zoz/Zp;
    //   91: astore #14
    //   93: iload #12
    //   95: iconst_1
    //   96: if_icmpeq -> 111
    //   99: aload #4
    //   101: ifnull -> 43
    //   104: goto -> 111
    //   107: invokestatic a : (Ljava/lang/Exception;)Ljava/lang/Exception;
    //   110: athrow
    //   111: aload #11
    //   113: iconst_0
    //   114: invokevirtual ZL : (I)Lcom/fasterxml/Zoz/Zp;
    //   117: astore #15
    //   119: aload_0
    //   120: aload #5
    //   122: aload #7
    //   124: aload #13
    //   126: aload #15
    //   128: invokespecial ZJ : (Lcom/fasterxml/Zor/Zyv;Lcom/fasterxml/Zor/Zt;Lcom/fasterxml/Zoz/Zif;Lcom/fasterxml/Zoz/Zp;)Z
    //   131: istore #16
    //   133: iload #16
    //   135: ifne -> 182
    //   138: aload_0
    //   139: aload #6
    //   141: aload #13
    //   143: iconst_0
    //   144: aload #8
    //   146: aload #13
    //   148: invokeinterface ZU : (Lcom/fasterxml/Zoz/Ziz;)Z
    //   153: invokevirtual Zf : (Lcom/fasterxml/Ze/Zh;Lcom/fasterxml/Zoz/Zif;ZZ)Z
    //   156: pop
    //   157: aload #15
    //   159: ifnull -> 43
    //   162: goto -> 169
    //   165: invokestatic a : (Ljava/lang/Exception;)Ljava/lang/Exception;
    //   168: athrow
    //   169: aload #15
    //   171: checkcast com/fasterxml/Zoz/Zb
    //   174: invokevirtual Zs : ()V
    //   177: aload #4
    //   179: ifnull -> 43
    //   182: aconst_null
    //   183: astore #17
    //   185: iload #12
    //   187: anewarray com/fasterxml/Zo/Zv
    //   190: astore #18
    //   192: iconst_0
    //   193: istore #19
    //   195: iconst_0
    //   196: istore #20
    //   198: iconst_0
    //   199: istore #21
    //   201: iconst_0
    //   202: istore #22
    //   204: iload #22
    //   206: iload #12
    //   208: if_icmpge -> 430
    //   211: aload #13
    //   213: iload #22
    //   215: invokevirtual Zz : (I)Lcom/fasterxml/Zoz/Zin;
    //   218: astore #23
    //   220: aload #14
    //   222: ifnonnull -> 233
    //   225: aconst_null
    //   226: goto -> 238
    //   229: invokestatic a : (Ljava/lang/Exception;)Ljava/lang/Exception;
    //   232: athrow
    //   233: aload #14
    //   235: iload #22
    //   237: aaload
    //   238: astore #24
    //   240: aload #7
    //   242: aload #23
    //   244: invokevirtual ZU : (Lcom/fasterxml/Zoz/Ziz;)Lcom/fasterxml/Zz6;
    //   247: astore #25
    //   249: aload #24
    //   251: ifnonnull -> 262
    //   254: aconst_null
    //   255: goto -> 267
    //   258: invokestatic a : (Ljava/lang/Exception;)Ljava/lang/Exception;
    //   261: athrow
    //   262: aload #24
    //   264: invokevirtual ZU : ()Lcom/fasterxml/Zor/Zr;
    //   267: astore #26
    //   269: aload #24
    //   271: ifnull -> 324
    //   274: aload #24
    //   276: invokevirtual ZF : ()Z
    //   279: ifeq -> 324
    //   282: goto -> 289
    //   285: invokestatic a : (Ljava/lang/Exception;)Ljava/lang/Exception;
    //   288: athrow
    //   289: iinc #20, 1
    //   292: aload #18
    //   294: iload #22
    //   296: aload_0
    //   297: aload_1
    //   298: aload #5
    //   300: aload #26
    //   302: iload #22
    //   304: aload #23
    //   306: aload #25
    //   308: invokevirtual Zk : (Lcom/fasterxml/Zor/Zyg;Lcom/fasterxml/Zor/Zyv;Lcom/fasterxml/Zor/Zr;ILcom/fasterxml/Zoz/Zin;Lcom/fasterxml/Zz6;)Lcom/fasterxml/Zo/Zv;
    //   311: aastore
    //   312: aload #4
    //   314: ifnull -> 422
    //   317: goto -> 324
    //   320: invokestatic a : (Ljava/lang/Exception;)Ljava/lang/Exception;
    //   323: athrow
    //   324: aload #25
    //   326: ifnull -> 371
    //   329: goto -> 336
    //   332: invokestatic a : (Ljava/lang/Exception;)Ljava/lang/Exception;
    //   335: athrow
    //   336: iinc #21, 1
    //   339: aload #18
    //   341: iload #22
    //   343: aload_0
    //   344: aload_1
    //   345: aload #5
    //   347: aload #26
    //   349: iload #22
    //   351: aload #23
    //   353: aload #25
    //   355: invokevirtual Zk : (Lcom/fasterxml/Zor/Zyg;Lcom/fasterxml/Zor/Zyv;Lcom/fasterxml/Zor/Zr;ILcom/fasterxml/Zoz/Zin;Lcom/fasterxml/Zz6;)Lcom/fasterxml/Zo/Zv;
    //   358: aastore
    //   359: aload #4
    //   361: ifnull -> 422
    //   364: goto -> 371
    //   367: invokestatic a : (Ljava/lang/Exception;)Ljava/lang/Exception;
    //   370: athrow
    //   371: aload #7
    //   373: aload #23
    //   375: invokevirtual Za : (Lcom/fasterxml/Zoz/Ziz;)Lcom/fasterxml/Zm/Zee;
    //   378: astore #27
    //   380: aload #27
    //   382: ifnull -> 406
    //   385: aload_0
    //   386: aload_1
    //   387: aload #5
    //   389: aload #23
    //   391: invokevirtual ZR : (Lcom/fasterxml/Zor/Zyg;Lcom/fasterxml/Zor/Zyv;Lcom/fasterxml/Zoz/Zin;)V
    //   394: aload #4
    //   396: ifnull -> 422
    //   399: goto -> 406
    //   402: invokestatic a : (Ljava/lang/Exception;)Ljava/lang/Exception;
    //   405: athrow
    //   406: aload #17
    //   408: ifnonnull -> 422
    //   411: goto -> 418
    //   414: invokestatic a : (Ljava/lang/Exception;)Ljava/lang/Exception;
    //   417: athrow
    //   418: aload #23
    //   420: astore #17
    //   422: iinc #22, 1
    //   425: aload #4
    //   427: ifnull -> 204
    //   430: iload #20
    //   432: iload #19
    //   434: iadd
    //   435: istore #22
    //   437: iload #20
    //   439: ifgt -> 454
    //   442: iload #21
    //   444: ifle -> 600
    //   447: goto -> 454
    //   450: invokestatic a : (Ljava/lang/Exception;)Ljava/lang/Exception;
    //   453: athrow
    //   454: iload #22
    //   456: iload #21
    //   458: iadd
    //   459: iload #12
    //   461: if_icmpne -> 493
    //   464: goto -> 471
    //   467: invokestatic a : (Ljava/lang/Exception;)Ljava/lang/Exception;
    //   470: athrow
    //   471: aload #6
    //   473: aload #13
    //   475: iconst_0
    //   476: aload #18
    //   478: invokevirtual Zb : (Lcom/fasterxml/Zoz/Zif;Z[Lcom/fasterxml/Zo/Zv;)V
    //   481: aload #4
    //   483: ifnull -> 600
    //   486: goto -> 493
    //   489: invokestatic a : (Ljava/lang/Exception;)Ljava/lang/Exception;
    //   492: athrow
    //   493: iload #20
    //   495: ifne -> 544
    //   498: goto -> 505
    //   501: invokestatic a : (Ljava/lang/Exception;)Ljava/lang/Exception;
    //   504: athrow
    //   505: iload #21
    //   507: iconst_1
    //   508: iadd
    //   509: iload #12
    //   511: if_icmpne -> 544
    //   514: goto -> 521
    //   517: invokestatic a : (Ljava/lang/Exception;)Ljava/lang/Exception;
    //   520: athrow
    //   521: aload #6
    //   523: aload #13
    //   525: iconst_0
    //   526: aload #18
    //   528: iconst_0
    //   529: invokevirtual ZA : (Lcom/fasterxml/Zoz/Zif;Z[Lcom/fasterxml/Zo/Zv;I)V
    //   532: aload #4
    //   534: ifnull -> 600
    //   537: goto -> 544
    //   540: invokestatic a : (Ljava/lang/Exception;)Ljava/lang/Exception;
    //   543: athrow
    //   544: aload_1
    //   545: aload #5
    //   547: sipush #8523
    //   550: sipush #-32559
    //   553: invokestatic a : (II)Ljava/lang/String;
    //   556: iconst_2
    //   557: anewarray java/lang/Object
    //   560: dup
    //   561: iconst_0
    //   562: aload #17
    //   564: ifnonnull -> 582
    //   567: goto -> 574
    //   570: invokestatic a : (Ljava/lang/Exception;)Ljava/lang/Exception;
    //   573: athrow
    //   574: iconst_m1
    //   575: goto -> 587
    //   578: invokestatic a : (Ljava/lang/Exception;)Ljava/lang/Exception;
    //   581: athrow
    //   582: aload #17
    //   584: invokevirtual ZF : ()I
    //   587: invokestatic valueOf : (I)Ljava/lang/Integer;
    //   590: aastore
    //   591: dup
    //   592: iconst_1
    //   593: aload #13
    //   595: aastore
    //   596: invokevirtual ZI : (Lcom/fasterxml/Zor/Zyv;Ljava/lang/String;[Ljava/lang/Object;)Ljava/lang/Object;
    //   599: pop
    //   600: aload #4
    //   602: ifnull -> 43
    //   605: return
    // Exception table:
    //   from	to	target	type
    //   93	104	107	com/fasterxml/Zor/Zy_
    //   133	162	165	com/fasterxml/Zor/Zy_
    //   220	229	229	com/fasterxml/Zor/Zy_
    //   249	258	258	com/fasterxml/Zor/Zy_
    //   269	282	285	com/fasterxml/Zor/Zy_
    //   274	317	320	com/fasterxml/Zor/Zy_
    //   289	329	332	com/fasterxml/Zor/Zy_
    //   324	364	367	com/fasterxml/Zor/Zy_
    //   380	399	402	com/fasterxml/Zor/Zy_
    //   385	411	414	com/fasterxml/Zor/Zy_
    //   437	447	450	com/fasterxml/Zor/Zy_
    //   442	464	467	com/fasterxml/Zor/Zy_
    //   454	486	489	com/fasterxml/Zor/Zy_
    //   471	498	501	com/fasterxml/Zor/Zy_
    //   493	514	517	com/fasterxml/Zor/Zy_
    //   505	537	540	com/fasterxml/Zor/Zy_
    //   521	567	570	com/fasterxml/Zor/Zy_
    //   544	578	578	com/fasterxml/Zor/Zy_
  }
  
  protected void ZU(Zyg paramZyg, Zyv paramZyv, Zh paramZh, Zs paramZs) throws Zy_ {
    // Byte code:
    //   0: invokestatic ZP : ()Ljava/lang/String;
    //   3: iconst_m1
    //   4: istore #6
    //   6: aload #4
    //   8: invokevirtual ZD : ()I
    //   11: istore #7
    //   13: iload #7
    //   15: anewarray com/fasterxml/Zo/Zv
    //   18: astore #8
    //   20: iconst_0
    //   21: istore #9
    //   23: astore #5
    //   25: iload #9
    //   27: iload #7
    //   29: if_icmpge -> 161
    //   32: aload #4
    //   34: iload #9
    //   36: invokevirtual Zg : (I)Lcom/fasterxml/Zoz/Zin;
    //   39: astore #10
    //   41: aload #4
    //   43: iload #9
    //   45: invokevirtual ZR : (I)Lcom/fasterxml/Zz6;
    //   48: astore #11
    //   50: aload #11
    //   52: ifnull -> 85
    //   55: aload #8
    //   57: iload #9
    //   59: aload_0
    //   60: aload_1
    //   61: aload_2
    //   62: aconst_null
    //   63: iload #9
    //   65: aload #10
    //   67: aload #11
    //   69: invokevirtual Zk : (Lcom/fasterxml/Zor/Zyg;Lcom/fasterxml/Zor/Zyv;Lcom/fasterxml/Zor/Zr;ILcom/fasterxml/Zoz/Zin;Lcom/fasterxml/Zz6;)Lcom/fasterxml/Zo/Zv;
    //   72: aastore
    //   73: aload #5
    //   75: ifnull -> 153
    //   78: goto -> 85
    //   81: invokestatic a : (Ljava/lang/Exception;)Ljava/lang/Exception;
    //   84: athrow
    //   85: iload #6
    //   87: ifge -> 106
    //   90: goto -> 97
    //   93: invokestatic a : (Ljava/lang/Exception;)Ljava/lang/Exception;
    //   96: athrow
    //   97: iload #9
    //   99: istore #6
    //   101: aload #5
    //   103: ifnull -> 153
    //   106: aload_1
    //   107: aload_2
    //   108: sipush #8513
    //   111: sipush #-26516
    //   114: invokestatic a : (II)Ljava/lang/String;
    //   117: iconst_3
    //   118: anewarray java/lang/Object
    //   121: dup
    //   122: iconst_0
    //   123: iload #6
    //   125: invokestatic valueOf : (I)Ljava/lang/Integer;
    //   128: aastore
    //   129: dup
    //   130: iconst_1
    //   131: iload #9
    //   133: invokestatic valueOf : (I)Ljava/lang/Integer;
    //   136: aastore
    //   137: dup
    //   138: iconst_2
    //   139: aload #4
    //   141: aastore
    //   142: invokevirtual ZI : (Lcom/fasterxml/Zor/Zyv;Ljava/lang/String;[Ljava/lang/Object;)Ljava/lang/Object;
    //   145: pop
    //   146: goto -> 153
    //   149: invokestatic a : (Ljava/lang/Exception;)Ljava/lang/Exception;
    //   152: athrow
    //   153: iinc #9, 1
    //   156: aload #5
    //   158: ifnull -> 25
    //   161: iload #6
    //   163: ifge -> 197
    //   166: aload_1
    //   167: aload_2
    //   168: sipush #8524
    //   171: sipush #17685
    //   174: invokestatic a : (II)Ljava/lang/String;
    //   177: iconst_1
    //   178: anewarray java/lang/Object
    //   181: dup
    //   182: iconst_0
    //   183: aload #4
    //   185: aastore
    //   186: invokevirtual ZI : (Lcom/fasterxml/Zor/Zyv;Ljava/lang/String;[Ljava/lang/Object;)Ljava/lang/Object;
    //   189: pop
    //   190: goto -> 197
    //   193: invokestatic a : (Ljava/lang/Exception;)Ljava/lang/Exception;
    //   196: athrow
    //   197: iload #7
    //   199: iconst_1
    //   200: if_icmpne -> 245
    //   203: aload_0
    //   204: aload_3
    //   205: aload #4
    //   207: invokevirtual ZC : ()Lcom/fasterxml/Zoz/Zif;
    //   210: iconst_1
    //   211: iconst_1
    //   212: invokevirtual Zf : (Lcom/fasterxml/Ze/Zh;Lcom/fasterxml/Zoz/Zif;ZZ)Z
    //   215: pop
    //   216: aload #4
    //   218: iconst_0
    //   219: invokevirtual ZL : (I)Lcom/fasterxml/Zoz/Zp;
    //   222: astore #9
    //   224: aload #9
    //   226: ifnull -> 244
    //   229: aload #9
    //   231: checkcast com/fasterxml/Zoz/Zb
    //   234: invokevirtual Zs : ()V
    //   237: goto -> 244
    //   240: invokestatic a : (Ljava/lang/Exception;)Ljava/lang/Exception;
    //   243: athrow
    //   244: return
    //   245: aload_3
    //   246: aload #4
    //   248: invokevirtual ZC : ()Lcom/fasterxml/Zoz/Zif;
    //   251: iconst_1
    //   252: aload #8
    //   254: iload #6
    //   256: invokevirtual ZA : (Lcom/fasterxml/Zoz/Zif;Z[Lcom/fasterxml/Zo/Zv;I)V
    //   259: return
    // Exception table:
    //   from	to	target	type
    //   50	78	81	com/fasterxml/Zor/Zy_
    //   55	90	93	com/fasterxml/Zor/Zy_
    //   101	146	149	com/fasterxml/Zor/Zy_
    //   161	190	193	com/fasterxml/Zor/Zy_
    //   224	237	240	com/fasterxml/Zor/Zy_
  }
  
  protected void ZP(Zyg paramZyg, Zyv paramZyv, Zh paramZh, Zs paramZs) throws Zy_ {
    int i = paramZs.ZD();
    Zv[] arrayOfZv = new Zv[i];
    byte b = 0;
    String str = Zzp.ZP();
    while (b < i) {
      Zz6 zz6 = paramZs.ZR(b);
      Zin zin = paramZs.Zg(b);
      Zr zr = paramZs.ZT(b);
      if (zr == null) {
        Zee zee = paramZyg.Zv().Za((Ziz)zin);
        try {
          if (zee != null)
            ZR(paramZyg, paramZyv, zin); 
        } catch (Zy_ zy_) {
          throw a(null);
        } 
        zr = paramZs.ZA(b);
        ZX(paramZyg, paramZyv, paramZs, b, zr, zz6);
      } 
      arrayOfZv[b] = Zk(paramZyg, paramZyv, zr, b, zin, zz6);
      b++;
      if (str != null)
        break; 
    } 
    paramZh.Zb(paramZs.ZC(), true, arrayOfZv);
  }
  
  protected void Zj(Zyg paramZyg, Zyv paramZyv, Zh paramZh, Zs paramZs, Zg paramZg) throws Zy_ {
    // Byte code:
    //   0: invokestatic ZP : ()Ljava/lang/String;
    //   3: astore #6
    //   5: iconst_1
    //   6: aload #4
    //   8: invokevirtual ZD : ()I
    //   11: if_icmpeq -> 97
    //   14: aload #5
    //   16: invokevirtual Zp : ()Z
    //   19: ifne -> 87
    //   22: goto -> 29
    //   25: invokestatic a : (Ljava/lang/Exception;)Ljava/lang/Exception;
    //   28: athrow
    //   29: aload #4
    //   31: invokevirtual ZL : ()I
    //   34: istore #7
    //   36: iload #7
    //   38: iflt -> 87
    //   41: aload #5
    //   43: invokevirtual Z_ : ()Z
    //   46: ifne -> 73
    //   49: goto -> 56
    //   52: invokestatic a : (Ljava/lang/Exception;)Ljava/lang/Exception;
    //   55: athrow
    //   56: aload #4
    //   58: iload #7
    //   60: invokevirtual ZT : (I)Lcom/fasterxml/Zor/Zr;
    //   63: ifnonnull -> 87
    //   66: goto -> 73
    //   69: invokestatic a : (Ljava/lang/Exception;)Ljava/lang/Exception;
    //   72: athrow
    //   73: aload_0
    //   74: aload_1
    //   75: aload_2
    //   76: aload_3
    //   77: aload #4
    //   79: invokevirtual ZU : (Lcom/fasterxml/Zor/Zyg;Lcom/fasterxml/Zor/Zyv;Lcom/fasterxml/Ze/Zh;Lcom/fasterxml/Ze/Zs;)V
    //   82: return
    //   83: invokestatic a : (Ljava/lang/Exception;)Ljava/lang/Exception;
    //   86: athrow
    //   87: aload_0
    //   88: aload_1
    //   89: aload_2
    //   90: aload_3
    //   91: aload #4
    //   93: invokevirtual ZP : (Lcom/fasterxml/Zor/Zyg;Lcom/fasterxml/Zor/Zyv;Lcom/fasterxml/Ze/Zh;Lcom/fasterxml/Ze/Zs;)V
    //   96: return
    //   97: aload #4
    //   99: iconst_0
    //   100: invokevirtual Zg : (I)Lcom/fasterxml/Zoz/Zin;
    //   103: astore #7
    //   105: aload #4
    //   107: iconst_0
    //   108: invokevirtual ZR : (I)Lcom/fasterxml/Zz6;
    //   111: astore #8
    //   113: aconst_null
    //   114: astore #9
    //   116: getstatic com/fasterxml/Zo/Zzn.ZL : [I
    //   119: aload #5
    //   121: invokevirtual ZC : ()Lcom/fasterxml/Zj/Zs;
    //   124: invokevirtual ordinal : ()I
    //   127: iaload
    //   128: tableswitch default -> 232, 1 -> 160, 2 -> 168, 3 -> 204, 4 -> 232
    //   160: iconst_0
    //   161: istore #10
    //   163: aload #6
    //   165: ifnull -> 354
    //   168: iconst_1
    //   169: istore #10
    //   171: aload #4
    //   173: iconst_0
    //   174: invokevirtual ZT : (I)Lcom/fasterxml/Zor/Zr;
    //   177: astore #9
    //   179: aload #9
    //   181: ifnonnull -> 354
    //   184: aload_0
    //   185: aload_1
    //   186: aload_2
    //   187: aload #4
    //   189: iconst_0
    //   190: aload #9
    //   192: aload #8
    //   194: invokevirtual ZX : (Lcom/fasterxml/Zor/Zyg;Lcom/fasterxml/Zor/Zyv;Lcom/fasterxml/Ze/Zs;ILcom/fasterxml/Zor/Zr;Lcom/fasterxml/Zz6;)V
    //   197: goto -> 354
    //   200: invokestatic a : (Ljava/lang/Exception;)Ljava/lang/Exception;
    //   203: athrow
    //   204: aload_1
    //   205: aload_2
    //   206: sipush #8542
    //   209: sipush #-1402
    //   212: invokestatic a : (II)Ljava/lang/String;
    //   215: iconst_1
    //   216: anewarray java/lang/Object
    //   219: dup
    //   220: iconst_0
    //   221: aload #4
    //   223: invokevirtual ZC : ()Lcom/fasterxml/Zoz/Zif;
    //   226: aastore
    //   227: invokevirtual ZI : (Lcom/fasterxml/Zor/Zyv;Ljava/lang/String;[Ljava/lang/Object;)Ljava/lang/Object;
    //   230: pop
    //   231: return
    //   232: aload #4
    //   234: iconst_0
    //   235: invokevirtual ZL : (I)Lcom/fasterxml/Zoz/Zp;
    //   238: astore #11
    //   240: aload #4
    //   242: iconst_0
    //   243: invokevirtual Zy : (I)Lcom/fasterxml/Zor/Zr;
    //   246: astore #9
    //   248: aload #9
    //   250: ifnull -> 261
    //   253: iconst_1
    //   254: goto -> 262
    //   257: invokestatic a : (Ljava/lang/Exception;)Ljava/lang/Exception;
    //   260: athrow
    //   261: iconst_0
    //   262: istore #10
    //   264: iload #10
    //   266: ifne -> 354
    //   269: aload_2
    //   270: invokevirtual ZG : ()Lcom/fasterxml/Zoz/Ziz;
    //   273: ifnull -> 290
    //   276: goto -> 283
    //   279: invokestatic a : (Ljava/lang/Exception;)Ljava/lang/Exception;
    //   282: athrow
    //   283: goto -> 354
    //   286: invokestatic a : (Ljava/lang/Exception;)Ljava/lang/Exception;
    //   289: athrow
    //   290: aload #8
    //   292: ifnull -> 303
    //   295: iconst_1
    //   296: istore #10
    //   298: aload #6
    //   300: ifnull -> 354
    //   303: aload #11
    //   305: ifnull -> 354
    //   308: goto -> 315
    //   311: invokestatic a : (Ljava/lang/Exception;)Ljava/lang/Exception;
    //   314: athrow
    //   315: aload #4
    //   317: iconst_0
    //   318: invokevirtual ZT : (I)Lcom/fasterxml/Zor/Zr;
    //   321: astore #9
    //   323: aload #9
    //   325: ifnull -> 351
    //   328: aload #11
    //   330: invokevirtual Zc : ()Z
    //   333: ifeq -> 351
    //   336: goto -> 343
    //   339: invokestatic a : (Ljava/lang/Exception;)Ljava/lang/Exception;
    //   342: athrow
    //   343: iconst_1
    //   344: goto -> 352
    //   347: invokestatic a : (Ljava/lang/Exception;)Ljava/lang/Exception;
    //   350: athrow
    //   351: iconst_0
    //   352: istore #10
    //   354: iload #10
    //   356: ifeq -> 394
    //   359: iconst_1
    //   360: anewarray com/fasterxml/Zo/Zv
    //   363: dup
    //   364: iconst_0
    //   365: aload_0
    //   366: aload_1
    //   367: aload_2
    //   368: aload #9
    //   370: iconst_0
    //   371: aload #7
    //   373: aload #8
    //   375: invokevirtual Zk : (Lcom/fasterxml/Zor/Zyg;Lcom/fasterxml/Zor/Zyv;Lcom/fasterxml/Zor/Zr;ILcom/fasterxml/Zoz/Zin;Lcom/fasterxml/Zz6;)Lcom/fasterxml/Zo/Zv;
    //   378: aastore
    //   379: astore #11
    //   381: aload_3
    //   382: aload #4
    //   384: invokevirtual ZC : ()Lcom/fasterxml/Zoz/Zif;
    //   387: iconst_1
    //   388: aload #11
    //   390: invokevirtual Zb : (Lcom/fasterxml/Zoz/Zif;Z[Lcom/fasterxml/Zo/Zv;)V
    //   393: return
    //   394: aload_0
    //   395: aload_3
    //   396: aload #4
    //   398: invokevirtual ZC : ()Lcom/fasterxml/Zoz/Zif;
    //   401: iconst_1
    //   402: iconst_1
    //   403: invokevirtual Zf : (Lcom/fasterxml/Ze/Zh;Lcom/fasterxml/Zoz/Zif;ZZ)Z
    //   406: pop
    //   407: aload #4
    //   409: iconst_0
    //   410: invokevirtual ZL : (I)Lcom/fasterxml/Zoz/Zp;
    //   413: astore #11
    //   415: aload #11
    //   417: ifnull -> 435
    //   420: aload #11
    //   422: checkcast com/fasterxml/Zoz/Zb
    //   425: invokevirtual Zs : ()V
    //   428: goto -> 435
    //   431: invokestatic a : (Ljava/lang/Exception;)Ljava/lang/Exception;
    //   434: athrow
    //   435: return
    // Exception table:
    //   from	to	target	type
    //   5	22	25	com/fasterxml/Zor/Zy_
    //   36	49	52	com/fasterxml/Zor/Zy_
    //   41	66	69	com/fasterxml/Zor/Zy_
    //   56	83	83	com/fasterxml/Zor/Zy_
    //   179	200	200	com/fasterxml/Zor/Zy_
    //   248	257	257	com/fasterxml/Zor/Zy_
    //   264	276	279	com/fasterxml/Zor/Zy_
    //   269	286	286	com/fasterxml/Zor/Zy_
    //   298	308	311	com/fasterxml/Zor/Zy_
    //   323	336	339	com/fasterxml/Zor/Zy_
    //   328	347	347	com/fasterxml/Zor/Zy_
    //   415	428	431	com/fasterxml/Zor/Zy_
  }
  
  private boolean ZJ(Zyv paramZyv, Zt paramZt, Zif paramZif, Zp paramZp) {
    try {
      if (paramZp != null)
        try {
          if (paramZp.ZF())
            return true; 
        } catch (IllegalArgumentException illegalArgumentException) {
          throw a(null);
        }  
    } catch (IllegalArgumentException illegalArgumentException) {
      throw a(null);
    } 
    try {
      if (paramZyv.ZG() != null)
        return false; 
    } catch (IllegalArgumentException illegalArgumentException) {
      throw a(null);
    } 
    try {
      if (paramZt.ZU((Ziz)paramZif.Zz(0)) != null)
        return true; 
    } catch (IllegalArgumentException illegalArgumentException) {
      throw a(null);
    } 
    if (paramZp != null) {
      String str = paramZp.ZT();
      try {
        if (str != null)
          try {
            if (!str.isEmpty())
              try {
                if (paramZp.Zc())
                  return true; 
              } catch (IllegalArgumentException illegalArgumentException) {
                throw a(null);
              }  
          } catch (IllegalArgumentException illegalArgumentException) {
            throw a(null);
          }  
      } catch (IllegalArgumentException illegalArgumentException) {
        throw a(null);
      } 
      try {
        if (!paramZp.ZF())
          try {
            if (paramZyv.ZY())
              return true; 
          } catch (IllegalArgumentException illegalArgumentException) {
            throw a(null);
          }  
      } catch (IllegalArgumentException illegalArgumentException) {
        throw a(null);
      } 
    } 
    return false;
  }
  
  private void Zw(Zyg paramZyg, Zyv paramZyv, Zi8<?> paramZi8, Zt paramZt, Zh paramZh, List<Zif> paramList) throws Zy_ {
    Zif zif = null;
    Zv[] arrayOfZv = null;
    String str = Zzp.ZP();
    label38: for (Zif zif1 : paramList) {
      try {
        if (paramZi8.ZU((Ziz)zif1) || str != null) {
          int i = zif1.ZL();
          Zv[] arrayOfZv1 = new Zv[i];
          byte b = 0;
          while (b < i) {
            Zin zin = zif1.Zz(b);
            Zr zr = ZG(zin, paramZt);
            if (zr != null) {
              try {
                if (!zr.Zf() || str != null) {
                  arrayOfZv1[b] = Zk(paramZyg, paramZyv, zr, zin.ZF(), zin, null);
                  b++;
                  if (str != null)
                    break; 
                  continue;
                } 
              } catch (Zy_ zy_) {
                throw a(null);
              } 
              continue label38;
            } 
            continue label38;
          } 
          if (zif != null) {
            zif = null;
            break;
          } 
          zif = zif1;
          arrayOfZv = arrayOfZv1;
          if (str != null)
            break; 
        } 
      } catch (Zy_ zy_) {
        throw a(null);
      } 
    } 
    if (zif != null) {
      paramZh.Zb(zif, false, arrayOfZv);
      Zic zic = (Zic)paramZyv;
      Zv[] arrayOfZv1 = arrayOfZv;
      int i = arrayOfZv1.length;
      byte b = 0;
      while (b < i) {
        Zv zv = arrayOfZv1[b];
        Zr zr = zv.ZS();
        if (!zic.Zw(zr)) {
          Zi zi = Zi.Zx((Zf)paramZyg.Za(), zv.ZQ(), zr);
          zic.Zj((Zp)zi);
        } 
        b++;
        if (str != null)
          break; 
      } 
    } 
  }
  
  protected boolean Zf(Zh paramZh, Zif paramZif, boolean paramBoolean1, boolean paramBoolean2) {
    // Byte code:
    //   0: aload_2
    //   1: iconst_0
    //   2: invokevirtual ZP : (I)Ljava/lang/Class;
    //   5: astore #5
    //   7: aload #5
    //   9: ldc java/lang/String
    //   11: if_acmpeq -> 29
    //   14: aload #5
    //   16: getstatic com/fasterxml/Zo/Zj.Zu : Ljava/lang/Class;
    //   19: if_acmpne -> 67
    //   22: goto -> 29
    //   25: invokestatic a : (Ljava/lang/Exception;)Ljava/lang/Exception;
    //   28: athrow
    //   29: iload_3
    //   30: ifne -> 52
    //   33: goto -> 40
    //   36: invokestatic a : (Ljava/lang/Exception;)Ljava/lang/Exception;
    //   39: athrow
    //   40: iload #4
    //   42: ifeq -> 65
    //   45: goto -> 52
    //   48: invokestatic a : (Ljava/lang/Exception;)Ljava/lang/Exception;
    //   51: athrow
    //   52: aload_1
    //   53: aload_2
    //   54: iload_3
    //   55: invokevirtual Zi : (Lcom/fasterxml/Zoz/Zif;Z)V
    //   58: goto -> 65
    //   61: invokestatic a : (Ljava/lang/Exception;)Ljava/lang/Exception;
    //   64: athrow
    //   65: iconst_1
    //   66: ireturn
    //   67: aload #5
    //   69: getstatic java/lang/Integer.TYPE : Ljava/lang/Class;
    //   72: if_acmpeq -> 89
    //   75: aload #5
    //   77: ldc java/lang/Integer
    //   79: if_acmpne -> 127
    //   82: goto -> 89
    //   85: invokestatic a : (Ljava/lang/Exception;)Ljava/lang/Exception;
    //   88: athrow
    //   89: iload_3
    //   90: ifne -> 112
    //   93: goto -> 100
    //   96: invokestatic a : (Ljava/lang/Exception;)Ljava/lang/Exception;
    //   99: athrow
    //   100: iload #4
    //   102: ifeq -> 125
    //   105: goto -> 112
    //   108: invokestatic a : (Ljava/lang/Exception;)Ljava/lang/Exception;
    //   111: athrow
    //   112: aload_1
    //   113: aload_2
    //   114: iload_3
    //   115: invokevirtual ZX : (Lcom/fasterxml/Zoz/Zif;Z)V
    //   118: goto -> 125
    //   121: invokestatic a : (Ljava/lang/Exception;)Ljava/lang/Exception;
    //   124: athrow
    //   125: iconst_1
    //   126: ireturn
    //   127: aload #5
    //   129: getstatic java/lang/Long.TYPE : Ljava/lang/Class;
    //   132: if_acmpeq -> 149
    //   135: aload #5
    //   137: ldc java/lang/Long
    //   139: if_acmpne -> 187
    //   142: goto -> 149
    //   145: invokestatic a : (Ljava/lang/Exception;)Ljava/lang/Exception;
    //   148: athrow
    //   149: iload_3
    //   150: ifne -> 172
    //   153: goto -> 160
    //   156: invokestatic a : (Ljava/lang/Exception;)Ljava/lang/Exception;
    //   159: athrow
    //   160: iload #4
    //   162: ifeq -> 185
    //   165: goto -> 172
    //   168: invokestatic a : (Ljava/lang/Exception;)Ljava/lang/Exception;
    //   171: athrow
    //   172: aload_1
    //   173: aload_2
    //   174: iload_3
    //   175: invokevirtual Zp : (Lcom/fasterxml/Zoz/Zif;Z)V
    //   178: goto -> 185
    //   181: invokestatic a : (Ljava/lang/Exception;)Ljava/lang/Exception;
    //   184: athrow
    //   185: iconst_1
    //   186: ireturn
    //   187: aload #5
    //   189: getstatic java/lang/Double.TYPE : Ljava/lang/Class;
    //   192: if_acmpeq -> 209
    //   195: aload #5
    //   197: ldc java/lang/Double
    //   199: if_acmpne -> 247
    //   202: goto -> 209
    //   205: invokestatic a : (Ljava/lang/Exception;)Ljava/lang/Exception;
    //   208: athrow
    //   209: iload_3
    //   210: ifne -> 232
    //   213: goto -> 220
    //   216: invokestatic a : (Ljava/lang/Exception;)Ljava/lang/Exception;
    //   219: athrow
    //   220: iload #4
    //   222: ifeq -> 245
    //   225: goto -> 232
    //   228: invokestatic a : (Ljava/lang/Exception;)Ljava/lang/Exception;
    //   231: athrow
    //   232: aload_1
    //   233: aload_2
    //   234: iload_3
    //   235: invokevirtual ZS : (Lcom/fasterxml/Zoz/Zif;Z)V
    //   238: goto -> 245
    //   241: invokestatic a : (Ljava/lang/Exception;)Ljava/lang/Exception;
    //   244: athrow
    //   245: iconst_1
    //   246: ireturn
    //   247: aload #5
    //   249: getstatic java/lang/Boolean.TYPE : Ljava/lang/Class;
    //   252: if_acmpeq -> 269
    //   255: aload #5
    //   257: ldc java/lang/Boolean
    //   259: if_acmpne -> 307
    //   262: goto -> 269
    //   265: invokestatic a : (Ljava/lang/Exception;)Ljava/lang/Exception;
    //   268: athrow
    //   269: iload_3
    //   270: ifne -> 292
    //   273: goto -> 280
    //   276: invokestatic a : (Ljava/lang/Exception;)Ljava/lang/Exception;
    //   279: athrow
    //   280: iload #4
    //   282: ifeq -> 305
    //   285: goto -> 292
    //   288: invokestatic a : (Ljava/lang/Exception;)Ljava/lang/Exception;
    //   291: athrow
    //   292: aload_1
    //   293: aload_2
    //   294: iload_3
    //   295: invokevirtual ZM : (Lcom/fasterxml/Zoz/Zif;Z)V
    //   298: goto -> 305
    //   301: invokestatic a : (Ljava/lang/Exception;)Ljava/lang/Exception;
    //   304: athrow
    //   305: iconst_1
    //   306: ireturn
    //   307: aload #5
    //   309: ldc java/math/BigInteger
    //   311: if_acmpne -> 350
    //   314: iload_3
    //   315: ifne -> 337
    //   318: goto -> 325
    //   321: invokestatic a : (Ljava/lang/Exception;)Ljava/lang/Exception;
    //   324: athrow
    //   325: iload #4
    //   327: ifeq -> 350
    //   330: goto -> 337
    //   333: invokestatic a : (Ljava/lang/Exception;)Ljava/lang/Exception;
    //   336: athrow
    //   337: aload_1
    //   338: aload_2
    //   339: iload_3
    //   340: invokevirtual Zk : (Lcom/fasterxml/Zoz/Zif;Z)V
    //   343: goto -> 350
    //   346: invokestatic a : (Ljava/lang/Exception;)Ljava/lang/Exception;
    //   349: athrow
    //   350: aload #5
    //   352: ldc java/math/BigDecimal
    //   354: if_acmpne -> 393
    //   357: iload_3
    //   358: ifne -> 380
    //   361: goto -> 368
    //   364: invokestatic a : (Ljava/lang/Exception;)Ljava/lang/Exception;
    //   367: athrow
    //   368: iload #4
    //   370: ifeq -> 393
    //   373: goto -> 380
    //   376: invokestatic a : (Ljava/lang/Exception;)Ljava/lang/Exception;
    //   379: athrow
    //   380: aload_1
    //   381: aload_2
    //   382: iload_3
    //   383: invokevirtual ZE : (Lcom/fasterxml/Zoz/Zif;Z)V
    //   386: goto -> 393
    //   389: invokestatic a : (Ljava/lang/Exception;)Ljava/lang/Exception;
    //   392: athrow
    //   393: iload_3
    //   394: ifeq -> 411
    //   397: aload_1
    //   398: aload_2
    //   399: iload_3
    //   400: aconst_null
    //   401: iconst_0
    //   402: invokevirtual ZA : (Lcom/fasterxml/Zoz/Zif;Z[Lcom/fasterxml/Zo/Zv;I)V
    //   405: iconst_1
    //   406: ireturn
    //   407: invokestatic a : (Ljava/lang/Exception;)Ljava/lang/Exception;
    //   410: athrow
    //   411: iconst_0
    //   412: ireturn
    // Exception table:
    //   from	to	target	type
    //   7	22	25	java/lang/IllegalArgumentException
    //   14	33	36	java/lang/IllegalArgumentException
    //   29	45	48	java/lang/IllegalArgumentException
    //   40	58	61	java/lang/IllegalArgumentException
    //   67	82	85	java/lang/IllegalArgumentException
    //   75	93	96	java/lang/IllegalArgumentException
    //   89	105	108	java/lang/IllegalArgumentException
    //   100	118	121	java/lang/IllegalArgumentException
    //   127	142	145	java/lang/IllegalArgumentException
    //   135	153	156	java/lang/IllegalArgumentException
    //   149	165	168	java/lang/IllegalArgumentException
    //   160	178	181	java/lang/IllegalArgumentException
    //   187	202	205	java/lang/IllegalArgumentException
    //   195	213	216	java/lang/IllegalArgumentException
    //   209	225	228	java/lang/IllegalArgumentException
    //   220	238	241	java/lang/IllegalArgumentException
    //   247	262	265	java/lang/IllegalArgumentException
    //   255	273	276	java/lang/IllegalArgumentException
    //   269	285	288	java/lang/IllegalArgumentException
    //   280	298	301	java/lang/IllegalArgumentException
    //   307	318	321	java/lang/IllegalArgumentException
    //   314	330	333	java/lang/IllegalArgumentException
    //   325	343	346	java/lang/IllegalArgumentException
    //   350	361	364	java/lang/IllegalArgumentException
    //   357	373	376	java/lang/IllegalArgumentException
    //   368	386	389	java/lang/IllegalArgumentException
    //   393	407	407	java/lang/IllegalArgumentException
  }
  
  protected void ZX(Zyg paramZyg, Zyv paramZyv, Zs paramZs, int paramInt, Zr paramZr, Zz6 paramZz6) throws Zy_ {
    try {
      if (paramZr == null)
        try {
          if (paramZz6 == null)
            paramZyg.ZI(paramZyv, a(8541, -15317), new Object[] { Integer.valueOf(paramInt), paramZs }); 
        } catch (Zy_ zy_) {
          throw a(null);
        }  
    } catch (Zy_ zy_) {
      throw a(null);
    } 
  }
  
  protected void ZR(Zyg paramZyg, Zyv paramZyv, Zin paramZin) throws Zy_ {
    paramZyg.ZI(paramZyv, a(8519, 24607), new Object[] { Integer.valueOf(paramZin.ZF()) });
  }
  
  protected Zv Zk(Zyg paramZyg, Zyv paramZyv, Zr paramZr, int paramInt, Zin paramZin, Zz6 paramZz6) throws Zy_ {
    // Byte code:
    //   0: invokestatic ZP : ()Ljava/lang/String;
    //   3: aload_1
    //   4: invokevirtual Za : ()Lcom/fasterxml/Zor/Zyc;
    //   7: astore #8
    //   9: astore #7
    //   11: aload_1
    //   12: invokevirtual Zv : ()Lcom/fasterxml/Zor/Zt;
    //   15: astore #9
    //   17: aload #9
    //   19: ifnonnull -> 35
    //   22: getstatic com/fasterxml/Zor/Zyb.Zf : Lcom/fasterxml/Zor/Zyb;
    //   25: astore #10
    //   27: aconst_null
    //   28: astore #11
    //   30: aload #7
    //   32: ifnull -> 93
    //   35: aload #9
    //   37: aload #5
    //   39: invokevirtual ZZ : (Lcom/fasterxml/Zoz/Ziz;)Ljava/lang/Boolean;
    //   42: astore #12
    //   44: aload #9
    //   46: aload #5
    //   48: invokevirtual Z_ : (Lcom/fasterxml/Zoz/Ziv;)Ljava/lang/String;
    //   51: astore #13
    //   53: aload #9
    //   55: aload #5
    //   57: invokevirtual ZM : (Lcom/fasterxml/Zoz/Ziv;)Ljava/lang/Integer;
    //   60: astore #14
    //   62: aload #9
    //   64: aload #5
    //   66: invokevirtual Zu : (Lcom/fasterxml/Zoz/Ziv;)Ljava/lang/String;
    //   69: astore #15
    //   71: aload #12
    //   73: aload #13
    //   75: aload #14
    //   77: aload #15
    //   79: invokestatic ZB : (Ljava/lang/Boolean;Ljava/lang/String;Ljava/lang/Integer;Ljava/lang/String;)Lcom/fasterxml/Zor/Zyb;
    //   82: astore #10
    //   84: aload #9
    //   86: aload #5
    //   88: invokevirtual ZP : (Lcom/fasterxml/Zoz/Ziv;)Lcom/fasterxml/Zor/Zr;
    //   91: astore #11
    //   93: aload_0
    //   94: aload_1
    //   95: aload #5
    //   97: aload #5
    //   99: invokevirtual Zf : ()Lcom/fasterxml/Zor/Zk;
    //   102: invokevirtual ZA : (Lcom/fasterxml/Zor/Zyg;Lcom/fasterxml/Zoz/Ziz;Lcom/fasterxml/Zor/Zk;)Lcom/fasterxml/Zor/Zk;
    //   105: astore #12
    //   107: new com/fasterxml/Zor/Zi
    //   110: dup
    //   111: aload_3
    //   112: aload #12
    //   114: aload #11
    //   116: aload #5
    //   118: aload #10
    //   120: invokespecial <init> : (Lcom/fasterxml/Zor/Zr;Lcom/fasterxml/Zor/Zk;Lcom/fasterxml/Zor/Zr;Lcom/fasterxml/Zoz/Ziz;Lcom/fasterxml/Zor/Zyb;)V
    //   123: astore #13
    //   125: aload #12
    //   127: invokevirtual Zi : ()Ljava/lang/Object;
    //   130: checkcast com/fasterxml/Zp/Zt
    //   133: astore #14
    //   135: aload #14
    //   137: ifnonnull -> 150
    //   140: aload_0
    //   141: aload #8
    //   143: aload #12
    //   145: invokevirtual ZP : (Lcom/fasterxml/Zor/Zyc;Lcom/fasterxml/Zor/Zk;)Lcom/fasterxml/Zp/Zt;
    //   148: astore #14
    //   150: aload_0
    //   151: aload_1
    //   152: aload #13
    //   154: aload #10
    //   156: invokevirtual ZN : (Lcom/fasterxml/Zor/Zyg;Lcom/fasterxml/Zor/Zo;Lcom/fasterxml/Zor/Zyb;)Lcom/fasterxml/Zor/Zyb;
    //   159: astore #10
    //   161: aload_3
    //   162: aload #12
    //   164: aload #13
    //   166: invokevirtual Zb : ()Lcom/fasterxml/Zor/Zr;
    //   169: aload #14
    //   171: aload_2
    //   172: invokevirtual Zy : ()Lcom/fasterxml/Zm/Z_;
    //   175: aload #5
    //   177: iload #4
    //   179: aload #6
    //   181: aload #10
    //   183: invokestatic ZU : (Lcom/fasterxml/Zor/Zr;Lcom/fasterxml/Zor/Zk;Lcom/fasterxml/Zor/Zr;Lcom/fasterxml/Zp/Zt;Lcom/fasterxml/Zm/Z_;Lcom/fasterxml/Zoz/Zin;ILcom/fasterxml/Zz6;Lcom/fasterxml/Zor/Zyb;)Lcom/fasterxml/Zo/Zw;
    //   186: astore #15
    //   188: aload_0
    //   189: aload_1
    //   190: aload #5
    //   192: invokevirtual Zr : (Lcom/fasterxml/Zor/Zyg;Lcom/fasterxml/Zoz/Ziv;)Lcom/fasterxml/Zor/Zyo;
    //   195: astore #16
    //   197: aload #16
    //   199: ifnonnull -> 212
    //   202: aload #12
    //   204: invokevirtual ZY : ()Ljava/lang/Object;
    //   207: checkcast com/fasterxml/Zor/Zyo
    //   210: astore #16
    //   212: aload #16
    //   214: ifnull -> 238
    //   217: aload_1
    //   218: aload #16
    //   220: aload #15
    //   222: aload #12
    //   224: invokevirtual Zq : (Lcom/fasterxml/Zor/Zyo;Lcom/fasterxml/Zor/Zo;Lcom/fasterxml/Zor/Zk;)Lcom/fasterxml/Zor/Zyo;
    //   227: astore #16
    //   229: aload #15
    //   231: aload #16
    //   233: invokevirtual Zt : (Lcom/fasterxml/Zor/Zyo;)Lcom/fasterxml/Zo/Zv;
    //   236: astore #15
    //   238: aload #15
    //   240: areturn
  }
  
  private Zr ZG(Zin paramZin, Zt paramZt) {
    if (paramZt != null) {
      Zr zr = paramZt.ZK((Ziv)paramZin);
      try {
        if (zr != null)
          try {
            if (!zr.Zf())
              return zr; 
          } catch (IllegalArgumentException illegalArgumentException) {
            throw a(null);
          }  
      } catch (IllegalArgumentException illegalArgumentException) {
        throw a(null);
      } 
      String str = paramZt.ZW((Ziz)paramZin);
      try {
        if (str != null)
          try {
            if (!str.isEmpty())
              return Zr.Zf(str); 
          } catch (IllegalArgumentException illegalArgumentException) {
            throw a(null);
          }  
      } catch (IllegalArgumentException illegalArgumentException) {
        throw a(null);
      } 
    } 
    return null;
  }
  
  protected Zyb ZN(Zyg paramZyg, Zo paramZo, Zyb paramZyb) {
    // Byte code:
    //   0: aload_1
    //   1: invokevirtual Zv : ()Lcom/fasterxml/Zor/Zt;
    //   4: astore #4
    //   6: aload_1
    //   7: invokevirtual Za : ()Lcom/fasterxml/Zor/Zyc;
    //   10: astore #5
    //   12: iconst_1
    //   13: istore #6
    //   15: aconst_null
    //   16: astore #7
    //   18: aconst_null
    //   19: astore #8
    //   21: aload_2
    //   22: invokeinterface ZQ : ()Lcom/fasterxml/Zoz/Ziz;
    //   27: astore #9
    //   29: aload #9
    //   31: ifnull -> 162
    //   34: aload #4
    //   36: ifnull -> 74
    //   39: goto -> 46
    //   42: invokestatic a : (Ljava/lang/Exception;)Ljava/lang/Exception;
    //   45: athrow
    //   46: aload #4
    //   48: aload #9
    //   50: invokevirtual ZO : (Lcom/fasterxml/Zoz/Ziv;)Lcom/fasterxml/Zyk;
    //   53: astore #10
    //   55: aload #10
    //   57: ifnull -> 74
    //   60: aload #10
    //   62: invokevirtual ZI : ()Lcom/fasterxml/Zvg;
    //   65: astore #7
    //   67: aload #10
    //   69: invokevirtual ZV : ()Lcom/fasterxml/Zvg;
    //   72: astore #8
    //   74: iload #6
    //   76: ifne -> 103
    //   79: aload #7
    //   81: ifnull -> 103
    //   84: goto -> 91
    //   87: invokestatic a : (Ljava/lang/Exception;)Ljava/lang/Exception;
    //   90: athrow
    //   91: aload #8
    //   93: ifnonnull -> 162
    //   96: goto -> 103
    //   99: invokestatic a : (Ljava/lang/Exception;)Ljava/lang/Exception;
    //   102: athrow
    //   103: aload #5
    //   105: aload_2
    //   106: invokeinterface Zp : ()Lcom/fasterxml/Zor/Zk;
    //   111: invokevirtual Zf : ()Ljava/lang/Class;
    //   114: invokevirtual ZM : (Ljava/lang/Class;)Lcom/fasterxml/Zj/Z_;
    //   117: astore #10
    //   119: aload #10
    //   121: invokevirtual Zs : ()Lcom/fasterxml/Zyk;
    //   124: astore #11
    //   126: aload #11
    //   128: ifnull -> 162
    //   131: aload #7
    //   133: ifnonnull -> 150
    //   136: goto -> 143
    //   139: invokestatic a : (Ljava/lang/Exception;)Ljava/lang/Exception;
    //   142: athrow
    //   143: aload #11
    //   145: invokevirtual ZI : ()Lcom/fasterxml/Zvg;
    //   148: astore #7
    //   150: aload #8
    //   152: ifnonnull -> 162
    //   155: aload #11
    //   157: invokevirtual ZV : ()Lcom/fasterxml/Zvg;
    //   160: astore #8
    //   162: iload #6
    //   164: ifne -> 191
    //   167: aload #7
    //   169: ifnull -> 191
    //   172: goto -> 179
    //   175: invokestatic a : (Ljava/lang/Exception;)Ljava/lang/Exception;
    //   178: athrow
    //   179: aload #8
    //   181: ifnonnull -> 222
    //   184: goto -> 191
    //   187: invokestatic a : (Ljava/lang/Exception;)Ljava/lang/Exception;
    //   190: athrow
    //   191: aload #5
    //   193: invokevirtual ZF : ()Lcom/fasterxml/Zyk;
    //   196: astore #10
    //   198: aload #7
    //   200: ifnonnull -> 210
    //   203: aload #10
    //   205: invokevirtual ZI : ()Lcom/fasterxml/Zvg;
    //   208: astore #7
    //   210: aload #8
    //   212: ifnonnull -> 222
    //   215: aload #10
    //   217: invokevirtual ZV : ()Lcom/fasterxml/Zvg;
    //   220: astore #8
    //   222: aload #7
    //   224: ifnonnull -> 239
    //   227: aload #8
    //   229: ifnull -> 248
    //   232: goto -> 239
    //   235: invokestatic a : (Ljava/lang/Exception;)Ljava/lang/Exception;
    //   238: athrow
    //   239: aload_3
    //   240: aload #7
    //   242: aload #8
    //   244: invokevirtual Zr : (Lcom/fasterxml/Zvg;Lcom/fasterxml/Zvg;)Lcom/fasterxml/Zor/Zyb;
    //   247: astore_3
    //   248: aload_3
    //   249: areturn
    // Exception table:
    //   from	to	target	type
    //   29	39	42	java/lang/IllegalArgumentException
    //   74	84	87	java/lang/IllegalArgumentException
    //   79	96	99	java/lang/IllegalArgumentException
    //   126	136	139	java/lang/IllegalArgumentException
    //   162	172	175	java/lang/IllegalArgumentException
    //   167	184	187	java/lang/IllegalArgumentException
    //   222	232	235	java/lang/IllegalArgumentException
  }
  
  public Zyo<?> ZU(Zyg paramZyg, Zg paramZg, Zyv paramZyv) throws Zy_ {
    // Byte code:
    //   0: invokestatic ZP : ()Ljava/lang/String;
    //   3: aload_1
    //   4: invokevirtual Za : ()Lcom/fasterxml/Zor/Zyc;
    //   7: astore #5
    //   9: aload_2
    //   10: invokevirtual ZB : ()Lcom/fasterxml/Zor/Zk;
    //   13: astore #6
    //   15: astore #4
    //   17: aload #6
    //   19: invokevirtual ZY : ()Ljava/lang/Object;
    //   22: checkcast com/fasterxml/Zor/Zyo
    //   25: astore #7
    //   27: aload #6
    //   29: invokevirtual Zi : ()Ljava/lang/Object;
    //   32: checkcast com/fasterxml/Zp/Zt
    //   35: astore #8
    //   37: aload #8
    //   39: ifnonnull -> 52
    //   42: aload_0
    //   43: aload #5
    //   45: aload #6
    //   47: invokevirtual ZP : (Lcom/fasterxml/Zor/Zyc;Lcom/fasterxml/Zor/Zk;)Lcom/fasterxml/Zp/Zt;
    //   50: astore #8
    //   52: aload_0
    //   53: aload_2
    //   54: aload #5
    //   56: aload_3
    //   57: aload #8
    //   59: aload #7
    //   61: invokevirtual Zm : (Lcom/fasterxml/Zh/Zg;Lcom/fasterxml/Zor/Zyc;Lcom/fasterxml/Zor/Zyv;Lcom/fasterxml/Zp/Zt;Lcom/fasterxml/Zor/Zyo;)Lcom/fasterxml/Zor/Zyo;
    //   64: astore #9
    //   66: aload #9
    //   68: ifnonnull -> 154
    //   71: aload #7
    //   73: ifnonnull -> 135
    //   76: goto -> 83
    //   79: invokestatic a : (Ljava/lang/Exception;)Ljava/lang/Exception;
    //   82: athrow
    //   83: aload #6
    //   85: invokevirtual Zm : ()Z
    //   88: ifeq -> 113
    //   91: goto -> 98
    //   94: invokestatic a : (Ljava/lang/Exception;)Ljava/lang/Exception;
    //   97: athrow
    //   98: aload #6
    //   100: invokevirtual Zf : ()Ljava/lang/Class;
    //   103: invokestatic ZI : (Ljava/lang/Class;)Lcom/fasterxml/Zor/Zyo;
    //   106: astore #9
    //   108: aload #4
    //   110: ifnull -> 135
    //   113: aload #6
    //   115: ldc java/lang/String
    //   117: invokevirtual ZP : (Ljava/lang/Class;)Z
    //   120: ifeq -> 135
    //   123: goto -> 130
    //   126: invokestatic a : (Ljava/lang/Exception;)Ljava/lang/Exception;
    //   129: athrow
    //   130: getstatic com/fasterxml/Zs/Zfn.Zy : Lcom/fasterxml/Zs/Zfn;
    //   133: astore #9
    //   135: aload #9
    //   137: ifnonnull -> 154
    //   140: new com/fasterxml/Zs/Zut
    //   143: dup
    //   144: aload_2
    //   145: aload #7
    //   147: aload #8
    //   149: invokespecial <init> : (Lcom/fasterxml/Zor/Zk;Lcom/fasterxml/Zor/Zyo;Lcom/fasterxml/Zp/Zt;)V
    //   152: astore #9
    //   154: aload_0
    //   155: getfield Zo : Lcom/fasterxml/Zj/Zb;
    //   158: invokevirtual ZQ : ()Z
    //   161: ifeq -> 218
    //   164: aload_0
    //   165: getfield Zo : Lcom/fasterxml/Zj/Zb;
    //   168: invokevirtual Zn : ()Ljava/lang/Iterable;
    //   171: invokeinterface iterator : ()Ljava/util/Iterator;
    //   176: astore #10
    //   178: aload #10
    //   180: invokeinterface hasNext : ()Z
    //   185: ifeq -> 218
    //   188: aload #10
    //   190: invokeinterface next : ()Ljava/lang/Object;
    //   195: checkcast com/fasterxml/Zo/Zb
    //   198: astore #11
    //   200: aload #11
    //   202: aload #5
    //   204: aload_2
    //   205: aload_3
    //   206: aload #9
    //   208: invokevirtual Zl : (Lcom/fasterxml/Zor/Zyc;Lcom/fasterxml/Zh/Zg;Lcom/fasterxml/Zor/Zyv;Lcom/fasterxml/Zor/Zyo;)Lcom/fasterxml/Zor/Zyo;
    //   211: astore #9
    //   213: aload #4
    //   215: ifnull -> 178
    //   218: aload #9
    //   220: areturn
    // Exception table:
    //   from	to	target	type
    //   66	76	79	com/fasterxml/Zor/Zy_
    //   71	91	94	com/fasterxml/Zor/Zy_
    //   108	123	126	com/fasterxml/Zor/Zy_
  }
  
  public Zyo<?> Zy(Zyg paramZyg, Zs paramZs, Zyv paramZyv) throws Zy_ {
    // Byte code:
    //   0: invokestatic ZP : ()Ljava/lang/String;
    //   3: aload_2
    //   4: invokevirtual ZB : ()Lcom/fasterxml/Zor/Zk;
    //   7: astore #5
    //   9: aload #5
    //   11: invokevirtual ZY : ()Ljava/lang/Object;
    //   14: checkcast com/fasterxml/Zor/Zyo
    //   17: astore #6
    //   19: astore #4
    //   21: aload_1
    //   22: invokevirtual Za : ()Lcom/fasterxml/Zor/Zyc;
    //   25: astore #7
    //   27: aload #5
    //   29: invokevirtual Zi : ()Ljava/lang/Object;
    //   32: checkcast com/fasterxml/Zp/Zt
    //   35: astore #8
    //   37: aload #8
    //   39: ifnonnull -> 52
    //   42: aload_0
    //   43: aload #7
    //   45: aload #5
    //   47: invokevirtual ZP : (Lcom/fasterxml/Zor/Zyc;Lcom/fasterxml/Zor/Zk;)Lcom/fasterxml/Zp/Zt;
    //   50: astore #8
    //   52: aload_0
    //   53: aload_2
    //   54: aload #7
    //   56: aload_3
    //   57: aload #8
    //   59: aload #6
    //   61: invokevirtual ZE : (Lcom/fasterxml/Zh/Zs;Lcom/fasterxml/Zor/Zyc;Lcom/fasterxml/Zor/Zyv;Lcom/fasterxml/Zp/Zt;Lcom/fasterxml/Zor/Zyo;)Lcom/fasterxml/Zor/Zyo;
    //   64: astore #9
    //   66: aload #9
    //   68: ifnonnull -> 113
    //   71: aload_2
    //   72: invokevirtual Zf : ()Ljava/lang/Class;
    //   75: astore #10
    //   77: aload #6
    //   79: ifnonnull -> 113
    //   82: ldc java/util/EnumSet
    //   84: aload #10
    //   86: invokevirtual isAssignableFrom : (Ljava/lang/Class;)Z
    //   89: ifeq -> 113
    //   92: goto -> 99
    //   95: invokestatic a : (Ljava/lang/Exception;)Ljava/lang/Exception;
    //   98: athrow
    //   99: new com/fasterxml/Zs/Zuj
    //   102: dup
    //   103: aload #5
    //   105: aconst_null
    //   106: aload #8
    //   108: invokespecial <init> : (Lcom/fasterxml/Zor/Zk;Lcom/fasterxml/Zor/Zyo;Lcom/fasterxml/Zp/Zt;)V
    //   111: astore #9
    //   113: aload #9
    //   115: ifnonnull -> 353
    //   118: aload_2
    //   119: invokevirtual ZU : ()Z
    //   122: ifne -> 146
    //   125: goto -> 132
    //   128: invokestatic a : (Ljava/lang/Exception;)Ljava/lang/Exception;
    //   131: athrow
    //   132: aload_2
    //   133: invokevirtual ZV : ()Z
    //   136: ifeq -> 233
    //   139: goto -> 146
    //   142: invokestatic a : (Ljava/lang/Exception;)Ljava/lang/Exception;
    //   145: athrow
    //   146: aload_0
    //   147: aload_2
    //   148: aload #7
    //   150: invokevirtual Zo : (Lcom/fasterxml/Zor/Zk;Lcom/fasterxml/Zor/Zyc;)Lcom/fasterxml/Zh/Zs;
    //   153: astore #10
    //   155: aload #10
    //   157: ifnonnull -> 223
    //   160: aload_2
    //   161: invokevirtual Zi : ()Ljava/lang/Object;
    //   164: ifnonnull -> 212
    //   167: goto -> 174
    //   170: invokestatic a : (Ljava/lang/Exception;)Ljava/lang/Exception;
    //   173: athrow
    //   174: new java/lang/IllegalArgumentException
    //   177: dup
    //   178: new java/lang/StringBuilder
    //   181: dup
    //   182: invokespecial <init> : ()V
    //   185: sipush #8527
    //   188: sipush #23728
    //   191: invokestatic a : (II)Ljava/lang/String;
    //   194: invokevirtual append : (Ljava/lang/String;)Ljava/lang/StringBuilder;
    //   197: aload_2
    //   198: invokevirtual append : (Ljava/lang/Object;)Ljava/lang/StringBuilder;
    //   201: invokevirtual toString : ()Ljava/lang/String;
    //   204: invokespecial <init> : (Ljava/lang/String;)V
    //   207: athrow
    //   208: invokestatic a : (Ljava/lang/Exception;)Ljava/lang/Exception;
    //   211: athrow
    //   212: aload_3
    //   213: invokestatic Zw : (Lcom/fasterxml/Zor/Zyv;)Lcom/fasterxml/Zo/Zs;
    //   216: astore #9
    //   218: aload #4
    //   220: ifnull -> 233
    //   223: aload #10
    //   225: astore_2
    //   226: aload #7
    //   228: aload_2
    //   229: invokevirtual Zs : (Lcom/fasterxml/Zor/Zk;)Lcom/fasterxml/Zor/Zyv;
    //   232: astore_3
    //   233: aload #9
    //   235: ifnonnull -> 353
    //   238: aload_0
    //   239: aload_1
    //   240: aload_3
    //   241: invokevirtual ZP : (Lcom/fasterxml/Zor/Zyg;Lcom/fasterxml/Zor/Zyv;)Lcom/fasterxml/Zo/Zzp;
    //   244: astore #10
    //   246: aload #10
    //   248: invokevirtual ZJ : ()Z
    //   251: ifne -> 308
    //   254: aload_2
    //   255: ldc java/util/concurrent/ArrayBlockingQueue
    //   257: invokevirtual ZP : (Ljava/lang/Class;)Z
    //   260: ifeq -> 289
    //   263: goto -> 270
    //   266: invokestatic a : (Ljava/lang/Exception;)Ljava/lang/Exception;
    //   269: athrow
    //   270: new com/fasterxml/Zs/Zg
    //   273: dup
    //   274: aload_2
    //   275: aload #6
    //   277: aload #8
    //   279: aload #10
    //   281: invokespecial <init> : (Lcom/fasterxml/Zor/Zk;Lcom/fasterxml/Zor/Zyo;Lcom/fasterxml/Zp/Zt;Lcom/fasterxml/Zo/Zzp;)V
    //   284: areturn
    //   285: invokestatic a : (Ljava/lang/Exception;)Ljava/lang/Exception;
    //   288: athrow
    //   289: aload_1
    //   290: aload_2
    //   291: invokestatic Zh : (Lcom/fasterxml/Zor/Zyg;Lcom/fasterxml/Zor/Zk;)Lcom/fasterxml/Zor/Zyo;
    //   294: astore #9
    //   296: aload #9
    //   298: ifnull -> 308
    //   301: aload #9
    //   303: areturn
    //   304: invokestatic a : (Ljava/lang/Exception;)Ljava/lang/Exception;
    //   307: athrow
    //   308: aload #5
    //   310: ldc java/lang/String
    //   312: invokevirtual ZP : (Ljava/lang/Class;)Z
    //   315: ifeq -> 337
    //   318: new com/fasterxml/Zs/Zue
    //   321: dup
    //   322: aload_2
    //   323: aload #6
    //   325: aload #10
    //   327: invokespecial <init> : (Lcom/fasterxml/Zor/Zk;Lcom/fasterxml/Zor/Zyo;Lcom/fasterxml/Zo/Zzp;)V
    //   330: astore #9
    //   332: aload #4
    //   334: ifnull -> 353
    //   337: new com/fasterxml/Zs/Zy
    //   340: dup
    //   341: aload_2
    //   342: aload #6
    //   344: aload #8
    //   346: aload #10
    //   348: invokespecial <init> : (Lcom/fasterxml/Zor/Zk;Lcom/fasterxml/Zor/Zyo;Lcom/fasterxml/Zp/Zt;Lcom/fasterxml/Zo/Zzp;)V
    //   351: astore #9
    //   353: aload_0
    //   354: getfield Zo : Lcom/fasterxml/Zj/Zb;
    //   357: invokevirtual ZQ : ()Z
    //   360: ifeq -> 417
    //   363: aload_0
    //   364: getfield Zo : Lcom/fasterxml/Zj/Zb;
    //   367: invokevirtual Zn : ()Ljava/lang/Iterable;
    //   370: invokeinterface iterator : ()Ljava/util/Iterator;
    //   375: astore #10
    //   377: aload #10
    //   379: invokeinterface hasNext : ()Z
    //   384: ifeq -> 417
    //   387: aload #10
    //   389: invokeinterface next : ()Ljava/lang/Object;
    //   394: checkcast com/fasterxml/Zo/Zb
    //   397: astore #11
    //   399: aload #11
    //   401: aload #7
    //   403: aload_2
    //   404: aload_3
    //   405: aload #9
    //   407: invokevirtual ZV : (Lcom/fasterxml/Zor/Zyc;Lcom/fasterxml/Zh/Zs;Lcom/fasterxml/Zor/Zyv;Lcom/fasterxml/Zor/Zyo;)Lcom/fasterxml/Zor/Zyo;
    //   410: astore #9
    //   412: aload #4
    //   414: ifnull -> 377
    //   417: aload #9
    //   419: areturn
    // Exception table:
    //   from	to	target	type
    //   77	92	95	com/fasterxml/Zor/Zy_
    //   113	125	128	com/fasterxml/Zor/Zy_
    //   118	139	142	com/fasterxml/Zor/Zy_
    //   155	167	170	com/fasterxml/Zor/Zy_
    //   160	208	208	com/fasterxml/Zor/Zy_
    //   246	263	266	com/fasterxml/Zor/Zy_
    //   254	285	285	com/fasterxml/Zor/Zy_
    //   296	304	304	com/fasterxml/Zor/Zy_
  }
  
  protected Zs Zo(Zk paramZk, Zyc paramZyc) {
    Class<?> clazz = Zzf.Zy(paramZk);
    try {
      if (clazz != null)
        return (Zs)paramZyc.Zg().Zx(paramZk, clazz, true); 
    } catch (IllegalArgumentException illegalArgumentException) {
      throw a(null);
    } 
    return null;
  }
  
  public Zyo<?> Zk(Zyg paramZyg, Ze paramZe, Zyv paramZyv) throws Zy_ {
    Zk zk = paramZe.ZB();
    Zyo<?> zyo1 = (Zyo)zk.ZY();
    String str = Zzp.ZP();
    Zyc zyc = paramZyg.Za();
    Zt zt = (Zt)zk.Zi();
    if (zt == null)
      zt = ZP(zyc, zk); 
    Zyo<?> zyo2 = ZY(paramZe, zyc, paramZyv, zt, zyo1);
    try {
      if (zyo2 != null && this.Zo.ZQ())
        for (Zb zb : this.Zo.Zn()) {
          zyo2 = zb.ZH(zyc, paramZe, paramZyv, zyo2);
          if (str != null)
            break; 
        }  
    } catch (Zy_ zy_) {
      throw a(null);
    } 
    return zyo2;
  }
  
  public Zyo<?> Zj(Zyg paramZyg, Zf paramZf, Zyv paramZyv) throws Zy_ {
    // Byte code:
    //   0: invokestatic ZP : ()Ljava/lang/String;
    //   3: aload_1
    //   4: invokevirtual Za : ()Lcom/fasterxml/Zor/Zyc;
    //   7: astore #5
    //   9: aload_2
    //   10: invokevirtual Zu : ()Lcom/fasterxml/Zor/Zk;
    //   13: astore #6
    //   15: aload_2
    //   16: invokevirtual ZB : ()Lcom/fasterxml/Zor/Zk;
    //   19: astore #7
    //   21: aload #7
    //   23: invokevirtual ZY : ()Ljava/lang/Object;
    //   26: checkcast com/fasterxml/Zor/Zyo
    //   29: astore #8
    //   31: aload #6
    //   33: invokevirtual ZY : ()Ljava/lang/Object;
    //   36: checkcast com/fasterxml/Zor/Zf
    //   39: astore #9
    //   41: aload #7
    //   43: invokevirtual Zi : ()Ljava/lang/Object;
    //   46: checkcast com/fasterxml/Zp/Zt
    //   49: astore #10
    //   51: astore #4
    //   53: aload #10
    //   55: ifnonnull -> 68
    //   58: aload_0
    //   59: aload #5
    //   61: aload #7
    //   63: invokevirtual ZP : (Lcom/fasterxml/Zor/Zyc;Lcom/fasterxml/Zor/Zk;)Lcom/fasterxml/Zp/Zt;
    //   66: astore #10
    //   68: aload_0
    //   69: aload_2
    //   70: aload #5
    //   72: aload_3
    //   73: aload #9
    //   75: aload #10
    //   77: aload #8
    //   79: invokevirtual Zn : (Lcom/fasterxml/Zh/Zf;Lcom/fasterxml/Zor/Zyc;Lcom/fasterxml/Zor/Zyv;Lcom/fasterxml/Zor/Zf;Lcom/fasterxml/Zp/Zt;Lcom/fasterxml/Zor/Zyo;)Lcom/fasterxml/Zor/Zyo;
    //   82: astore #11
    //   84: aload #11
    //   86: ifnonnull -> 447
    //   89: aload_2
    //   90: invokevirtual Zf : ()Ljava/lang/Class;
    //   93: astore #12
    //   95: ldc java/util/EnumMap
    //   97: aload #12
    //   99: invokevirtual isAssignableFrom : (Ljava/lang/Class;)Z
    //   102: ifeq -> 182
    //   105: aload #12
    //   107: ldc java/util/EnumMap
    //   109: if_acmpne -> 127
    //   112: goto -> 119
    //   115: invokestatic a : (Ljava/lang/Exception;)Ljava/lang/Exception;
    //   118: athrow
    //   119: aconst_null
    //   120: astore #13
    //   122: aload #4
    //   124: ifnull -> 135
    //   127: aload_0
    //   128: aload_1
    //   129: aload_3
    //   130: invokevirtual ZP : (Lcom/fasterxml/Zor/Zyg;Lcom/fasterxml/Zor/Zyv;)Lcom/fasterxml/Zo/Zzp;
    //   133: astore #13
    //   135: aload #6
    //   137: invokevirtual ZM : ()Z
    //   140: ifne -> 164
    //   143: new java/lang/IllegalArgumentException
    //   146: dup
    //   147: sipush #8525
    //   150: sipush #-31042
    //   153: invokestatic a : (II)Ljava/lang/String;
    //   156: invokespecial <init> : (Ljava/lang/String;)V
    //   159: athrow
    //   160: invokestatic a : (Ljava/lang/Exception;)Ljava/lang/Exception;
    //   163: athrow
    //   164: new com/fasterxml/Zs/Ze
    //   167: dup
    //   168: aload_2
    //   169: aload #13
    //   171: aconst_null
    //   172: aload #8
    //   174: aload #10
    //   176: aconst_null
    //   177: invokespecial <init> : (Lcom/fasterxml/Zor/Zk;Lcom/fasterxml/Zo/Zzp;Lcom/fasterxml/Zor/Zf;Lcom/fasterxml/Zor/Zyo;Lcom/fasterxml/Zp/Zt;Lcom/fasterxml/Zo/Zzb;)V
    //   180: astore #11
    //   182: aload #11
    //   184: ifnonnull -> 447
    //   187: aload_2
    //   188: invokevirtual ZU : ()Z
    //   191: ifne -> 215
    //   194: goto -> 201
    //   197: invokestatic a : (Ljava/lang/Exception;)Ljava/lang/Exception;
    //   200: athrow
    //   201: aload_2
    //   202: invokevirtual ZV : ()Z
    //   205: ifeq -> 313
    //   208: goto -> 215
    //   211: invokestatic a : (Ljava/lang/Exception;)Ljava/lang/Exception;
    //   214: athrow
    //   215: aload_0
    //   216: aload_2
    //   217: aload #5
    //   219: invokevirtual ZD : (Lcom/fasterxml/Zor/Zk;Lcom/fasterxml/Zor/Zyc;)Lcom/fasterxml/Zh/Zf;
    //   222: astore #13
    //   224: aload #13
    //   226: ifnull -> 250
    //   229: aload #13
    //   231: astore_2
    //   232: aload_2
    //   233: invokevirtual Zf : ()Ljava/lang/Class;
    //   236: astore #12
    //   238: aload #5
    //   240: aload_2
    //   241: invokevirtual Zs : (Lcom/fasterxml/Zor/Zk;)Lcom/fasterxml/Zor/Zyv;
    //   244: astore_3
    //   245: aload #4
    //   247: ifnull -> 308
    //   250: aload_2
    //   251: invokevirtual Zi : ()Ljava/lang/Object;
    //   254: ifnonnull -> 302
    //   257: goto -> 264
    //   260: invokestatic a : (Ljava/lang/Exception;)Ljava/lang/Exception;
    //   263: athrow
    //   264: new java/lang/IllegalArgumentException
    //   267: dup
    //   268: new java/lang/StringBuilder
    //   271: dup
    //   272: invokespecial <init> : ()V
    //   275: sipush #8537
    //   278: sipush #8568
    //   281: invokestatic a : (II)Ljava/lang/String;
    //   284: invokevirtual append : (Ljava/lang/String;)Ljava/lang/StringBuilder;
    //   287: aload_2
    //   288: invokevirtual append : (Ljava/lang/Object;)Ljava/lang/StringBuilder;
    //   291: invokevirtual toString : ()Ljava/lang/String;
    //   294: invokespecial <init> : (Ljava/lang/String;)V
    //   297: athrow
    //   298: invokestatic a : (Ljava/lang/Exception;)Ljava/lang/Exception;
    //   301: athrow
    //   302: aload_3
    //   303: invokestatic Zw : (Lcom/fasterxml/Zor/Zyv;)Lcom/fasterxml/Zo/Zs;
    //   306: astore #11
    //   308: aload #4
    //   310: ifnull -> 332
    //   313: aload_1
    //   314: aload_2
    //   315: invokestatic Zb : (Lcom/fasterxml/Zor/Zyg;Lcom/fasterxml/Zor/Zk;)Lcom/fasterxml/Zor/Zyo;
    //   318: astore #11
    //   320: aload #11
    //   322: ifnull -> 332
    //   325: aload #11
    //   327: areturn
    //   328: invokestatic a : (Ljava/lang/Exception;)Ljava/lang/Exception;
    //   331: athrow
    //   332: aload #11
    //   334: ifnonnull -> 447
    //   337: aload_0
    //   338: aload_1
    //   339: aload_3
    //   340: invokevirtual ZP : (Lcom/fasterxml/Zor/Zyg;Lcom/fasterxml/Zor/Zyv;)Lcom/fasterxml/Zo/Zzp;
    //   343: astore #13
    //   345: new com/fasterxml/Zs/Zp
    //   348: dup
    //   349: aload_2
    //   350: aload #13
    //   352: aload #9
    //   354: aload #8
    //   356: aload #10
    //   358: invokespecial <init> : (Lcom/fasterxml/Zor/Zk;Lcom/fasterxml/Zo/Zzp;Lcom/fasterxml/Zor/Zf;Lcom/fasterxml/Zor/Zyo;Lcom/fasterxml/Zp/Zt;)V
    //   361: astore #14
    //   363: aload #5
    //   365: ldc java/util/Map
    //   367: aload_3
    //   368: invokevirtual Zo : ()Lcom/fasterxml/Zoz/Zia;
    //   371: invokevirtual Za : (Ljava/lang/Class;Lcom/fasterxml/Zoz/Zia;)Lcom/fasterxml/Zve;
    //   374: astore #15
    //   376: aload #15
    //   378: ifnonnull -> 389
    //   381: aconst_null
    //   382: goto -> 394
    //   385: invokestatic a : (Ljava/lang/Exception;)Ljava/lang/Exception;
    //   388: athrow
    //   389: aload #15
    //   391: invokevirtual Zq : ()Ljava/util/Set;
    //   394: astore #16
    //   396: aload #14
    //   398: aload #16
    //   400: invokevirtual ZE : (Ljava/util/Set;)V
    //   403: aload #5
    //   405: ldc java/util/Map
    //   407: aload_3
    //   408: invokevirtual Zo : ()Lcom/fasterxml/Zoz/Zia;
    //   411: invokevirtual Zn : (Ljava/lang/Class;Lcom/fasterxml/Zoz/Zia;)Lcom/fasterxml/Zyn;
    //   414: astore #17
    //   416: aload #17
    //   418: ifnonnull -> 429
    //   421: aconst_null
    //   422: goto -> 434
    //   425: invokestatic a : (Ljava/lang/Exception;)Ljava/lang/Exception;
    //   428: athrow
    //   429: aload #17
    //   431: invokevirtual ZU : ()Ljava/util/Set;
    //   434: astore #18
    //   436: aload #14
    //   438: aload #18
    //   440: invokevirtual ZV : (Ljava/util/Set;)V
    //   443: aload #14
    //   445: astore #11
    //   447: aload_0
    //   448: getfield Zo : Lcom/fasterxml/Zj/Zb;
    //   451: invokevirtual ZQ : ()Z
    //   454: ifeq -> 511
    //   457: aload_0
    //   458: getfield Zo : Lcom/fasterxml/Zj/Zb;
    //   461: invokevirtual Zn : ()Ljava/lang/Iterable;
    //   464: invokeinterface iterator : ()Ljava/util/Iterator;
    //   469: astore #12
    //   471: aload #12
    //   473: invokeinterface hasNext : ()Z
    //   478: ifeq -> 511
    //   481: aload #12
    //   483: invokeinterface next : ()Ljava/lang/Object;
    //   488: checkcast com/fasterxml/Zo/Zb
    //   491: astore #13
    //   493: aload #13
    //   495: aload #5
    //   497: aload_2
    //   498: aload_3
    //   499: aload #11
    //   501: invokevirtual Zo : (Lcom/fasterxml/Zor/Zyc;Lcom/fasterxml/Zh/Zf;Lcom/fasterxml/Zor/Zyv;Lcom/fasterxml/Zor/Zyo;)Lcom/fasterxml/Zor/Zyo;
    //   504: astore #11
    //   506: aload #4
    //   508: ifnull -> 471
    //   511: aload #11
    //   513: areturn
    // Exception table:
    //   from	to	target	type
    //   95	112	115	com/fasterxml/Zor/Zy_
    //   135	160	160	com/fasterxml/Zor/Zy_
    //   182	194	197	com/fasterxml/Zor/Zy_
    //   187	208	211	com/fasterxml/Zor/Zy_
    //   245	257	260	com/fasterxml/Zor/Zy_
    //   250	298	298	com/fasterxml/Zor/Zy_
    //   320	328	328	com/fasterxml/Zor/Zy_
    //   376	385	385	com/fasterxml/Zor/Zy_
    //   416	425	425	com/fasterxml/Zor/Zy_
  }
  
  protected Zf ZD(Zk paramZk, Zyc paramZyc) {
    Class<?> clazz = Zzf.Zs(paramZk);
    try {
      if (clazz != null)
        return (Zf)paramZyc.Zg().Zx(paramZk, clazz, true); 
    } catch (IllegalArgumentException illegalArgumentException) {
      throw a(null);
    } 
    return null;
  }
  
  public Zyo<?> Zz(Zyg paramZyg, Zo paramZo, Zyv paramZyv) throws Zy_ {
    Zk zk1 = paramZo.Zu();
    Zk zk2 = paramZo.ZB();
    String str = Zzp.ZP();
    Zyc zyc = paramZyg.Za();
    Zyo<?> zyo1 = (Zyo)zk2.ZY();
    Zf zf = (Zf)zk1.ZY();
    Zt zt = (Zt)zk2.Zi();
    if (zt == null)
      zt = ZP(zyc, zk2); 
    Zyo<?> zyo2 = Zr(paramZo, zyc, paramZyv, zf, zt, zyo1);
    try {
      if (zyo2 != null && this.Zo.ZQ())
        for (Zb zb : this.Zo.Zn()) {
          zyo2 = zb.Zw(zyc, paramZo, paramZyv, zyo2);
          if (str != null)
            break; 
        }  
    } catch (Zy_ zy_) {
      throw a(null);
    } 
    return zyo2;
  }
  
  public Zyo<?> Zh(Zyg paramZyg, Zk paramZk, Zyv paramZyv) throws Zy_ {
    // Byte code:
    //   0: aload_1
    //   1: invokevirtual Za : ()Lcom/fasterxml/Zor/Zyc;
    //   4: astore #5
    //   6: invokestatic ZP : ()Ljava/lang/String;
    //   9: aload_2
    //   10: invokevirtual Zf : ()Ljava/lang/Class;
    //   13: astore #6
    //   15: aload_0
    //   16: aload #6
    //   18: aload #5
    //   20: aload_3
    //   21: invokevirtual ZI : (Ljava/lang/Class;Lcom/fasterxml/Zor/Zyc;Lcom/fasterxml/Zor/Zyv;)Lcom/fasterxml/Zor/Zyo;
    //   24: astore #7
    //   26: astore #4
    //   28: aload #7
    //   30: ifnonnull -> 298
    //   33: aload #6
    //   35: ldc java/lang/Enum
    //   37: if_acmpne -> 56
    //   40: goto -> 47
    //   43: invokestatic a : (Ljava/lang/Exception;)Ljava/lang/Exception;
    //   46: athrow
    //   47: aload_3
    //   48: invokestatic Zw : (Lcom/fasterxml/Zor/Zyv;)Lcom/fasterxml/Zo/Zs;
    //   51: areturn
    //   52: invokestatic a : (Ljava/lang/Exception;)Ljava/lang/Exception;
    //   55: athrow
    //   56: aload_0
    //   57: aload_1
    //   58: aload_3
    //   59: invokevirtual ZY : (Lcom/fasterxml/Zor/Zyg;Lcom/fasterxml/Zor/Zyv;)Lcom/fasterxml/Zo/Zzp;
    //   62: astore #8
    //   64: aload #8
    //   66: ifnonnull -> 77
    //   69: aconst_null
    //   70: goto -> 86
    //   73: invokestatic a : (Ljava/lang/Exception;)Ljava/lang/Exception;
    //   76: athrow
    //   77: aload #8
    //   79: aload_1
    //   80: invokevirtual Za : ()Lcom/fasterxml/Zor/Zyc;
    //   83: invokevirtual Zg : (Lcom/fasterxml/Zor/Zyc;)[Lcom/fasterxml/Zo/Zv;
    //   86: astore #9
    //   88: aload_3
    //   89: invokevirtual ZK : ()Ljava/util/List;
    //   92: invokeinterface iterator : ()Ljava/util/Iterator;
    //   97: astore #10
    //   99: aload #10
    //   101: invokeinterface hasNext : ()Z
    //   106: ifeq -> 248
    //   109: aload #10
    //   111: invokeinterface next : ()Ljava/lang/Object;
    //   116: checkcast com/fasterxml/Zoz/Ziq
    //   119: astore #11
    //   121: aload_0
    //   122: aload_1
    //   123: aload #11
    //   125: invokevirtual ZY : (Lcom/fasterxml/Zor/Zyg;Lcom/fasterxml/Zoz/Ziv;)Z
    //   128: ifeq -> 236
    //   131: aload #11
    //   133: invokevirtual ZL : ()I
    //   136: ifne -> 162
    //   139: goto -> 146
    //   142: invokestatic a : (Ljava/lang/Exception;)Ljava/lang/Exception;
    //   145: athrow
    //   146: aload #5
    //   148: aload #6
    //   150: aload #11
    //   152: invokestatic ZV : (Lcom/fasterxml/Zor/Zyc;Ljava/lang/Class;Lcom/fasterxml/Zoz/Ziq;)Lcom/fasterxml/Zor/Zyo;
    //   155: astore #7
    //   157: aload #4
    //   159: ifnull -> 248
    //   162: aload #11
    //   164: invokevirtual Zy : ()Ljava/lang/Class;
    //   167: astore #12
    //   169: aload #12
    //   171: aload #6
    //   173: invokevirtual isAssignableFrom : (Ljava/lang/Class;)Z
    //   176: ifne -> 216
    //   179: aload_1
    //   180: aload_2
    //   181: sipush #8515
    //   184: sipush #19807
    //   187: invokestatic a : (II)Ljava/lang/String;
    //   190: iconst_1
    //   191: anewarray java/lang/Object
    //   194: dup
    //   195: iconst_0
    //   196: aload #11
    //   198: invokevirtual toString : ()Ljava/lang/String;
    //   201: aastore
    //   202: invokestatic format : (Ljava/lang/String;[Ljava/lang/Object;)Ljava/lang/String;
    //   205: invokevirtual Zm : (Lcom/fasterxml/Zor/Zk;Ljava/lang/String;)Ljava/lang/Object;
    //   208: pop
    //   209: goto -> 216
    //   212: invokestatic a : (Ljava/lang/Exception;)Ljava/lang/Exception;
    //   215: athrow
    //   216: aload #5
    //   218: aload #6
    //   220: aload #11
    //   222: aload #8
    //   224: aload #9
    //   226: invokestatic ZK : (Lcom/fasterxml/Zor/Zyc;Ljava/lang/Class;Lcom/fasterxml/Zoz/Ziq;Lcom/fasterxml/Zo/Zzp;[Lcom/fasterxml/Zo/Zv;)Lcom/fasterxml/Zor/Zyo;
    //   229: astore #7
    //   231: aload #4
    //   233: ifnull -> 248
    //   236: aload #4
    //   238: ifnull -> 99
    //   241: goto -> 248
    //   244: invokestatic a : (Ljava/lang/Exception;)Ljava/lang/Exception;
    //   247: athrow
    //   248: aload #7
    //   250: ifnonnull -> 298
    //   253: new com/fasterxml/Zs/Zul
    //   256: dup
    //   257: aload_0
    //   258: aload #6
    //   260: aload #5
    //   262: aload_3
    //   263: invokevirtual Zb : (Ljava/lang/Class;Lcom/fasterxml/Zor/Zyc;Lcom/fasterxml/Zor/Zyv;)Lcom/fasterxml/Zm/Zef;
    //   266: aload #5
    //   268: getstatic com/fasterxml/Zor/Zy9.ACCEPT_CASE_INSENSITIVE_ENUMS : Lcom/fasterxml/Zor/Zy9;
    //   271: invokevirtual ZB : (Lcom/fasterxml/Zor/Zy9;)Z
    //   274: aload_0
    //   275: aload #5
    //   277: aload_3
    //   278: invokevirtual Zo : ()Lcom/fasterxml/Zoz/Zia;
    //   281: invokevirtual ZH : (Lcom/fasterxml/Zor/Zyc;Lcom/fasterxml/Zoz/Zia;)Lcom/fasterxml/Zm/Zef;
    //   284: aload #5
    //   286: aload_3
    //   287: invokevirtual Zo : ()Lcom/fasterxml/Zoz/Zia;
    //   290: invokestatic ZX : (Lcom/fasterxml/Zor/Zyc;Lcom/fasterxml/Zoz/Zia;)Lcom/fasterxml/Zm/Zef;
    //   293: invokespecial <init> : (Lcom/fasterxml/Zm/Zef;ZLcom/fasterxml/Zm/Zef;Lcom/fasterxml/Zm/Zef;)V
    //   296: astore #7
    //   298: aload_0
    //   299: getfield Zo : Lcom/fasterxml/Zj/Zb;
    //   302: invokevirtual ZQ : ()Z
    //   305: ifeq -> 362
    //   308: aload_0
    //   309: getfield Zo : Lcom/fasterxml/Zj/Zb;
    //   312: invokevirtual Zn : ()Ljava/lang/Iterable;
    //   315: invokeinterface iterator : ()Ljava/util/Iterator;
    //   320: astore #8
    //   322: aload #8
    //   324: invokeinterface hasNext : ()Z
    //   329: ifeq -> 362
    //   332: aload #8
    //   334: invokeinterface next : ()Ljava/lang/Object;
    //   339: checkcast com/fasterxml/Zo/Zb
    //   342: astore #9
    //   344: aload #9
    //   346: aload #5
    //   348: aload_2
    //   349: aload_3
    //   350: aload #7
    //   352: invokevirtual ZB : (Lcom/fasterxml/Zor/Zyc;Lcom/fasterxml/Zor/Zk;Lcom/fasterxml/Zor/Zyv;Lcom/fasterxml/Zor/Zyo;)Lcom/fasterxml/Zor/Zyo;
    //   355: astore #7
    //   357: aload #4
    //   359: ifnull -> 322
    //   362: aload #7
    //   364: areturn
    // Exception table:
    //   from	to	target	type
    //   28	40	43	com/fasterxml/Zor/Zy_
    //   33	52	52	com/fasterxml/Zor/Zy_
    //   64	73	73	com/fasterxml/Zor/Zy_
    //   121	139	142	com/fasterxml/Zor/Zy_
    //   169	209	212	com/fasterxml/Zor/Zy_
    //   231	241	244	com/fasterxml/Zor/Zy_
  }
  
  public Zyo<?> Zx(Zyc paramZyc, Zk paramZk, Zyv paramZyv) throws Zy_ {
    Class<? extends Zb> clazz = paramZk.Zf();
    Zyo<?> zyo = ZJ(clazz, paramZyc, paramZyv);
    try {
      if (zyo != null)
        return zyo; 
    } catch (Zy_ zy_) {
      throw a(null);
    } 
    return Za.ZX(clazz);
  }
  
  public Zyo<?> ZF(Zyg paramZyg, Zn paramZn, Zyv paramZyv) throws Zy_ {
    Zk zk = paramZn.ZB();
    String str = Zzp.ZP();
    Zyo<?> zyo1 = (Zyo)zk.ZY();
    Zyc zyc = paramZyg.Za();
    Zt zt = (Zt)zk.Zi();
    if (zt == null)
      zt = ZP(zyc, zk); 
    Zyo<?> zyo2 = ZK(paramZn, zyc, paramZyv, zt, zyo1);
    try {
      if (zyo2 == null && paramZn.Zf(AtomicReference.class)) {
        Class<AtomicReference> clazz = paramZn.Zf();
        if (clazz == AtomicReference.class) {
          Zzp zzp1 = null;
          if (str != null) {
            zzp1 = ZP(paramZyg, paramZyv);
            return (Zyo<?>)new Zui((Zk)paramZn, zzp1, zt, zyo1);
          } 
          return (Zyo<?>)new Zui((Zk)paramZn, zzp1, zt, zyo1);
        } 
      } else {
        try {
          if (zyo2 != null && this.Zo.ZQ())
            for (Zb zb : this.Zo.Zn()) {
              zyo2 = zb.ZU(zyc, paramZn, paramZyv, zyo2);
              if (str != null)
                break; 
            }  
        } catch (Zy_ zy_) {
          throw a(null);
        } 
        return zyo2;
      } 
    } catch (Zy_ zy_) {
      throw a(null);
    } 
    Zzp zzp = ZP(paramZyg, paramZyv);
    return (Zyo<?>)new Zui((Zk)paramZn, zzp, zt, zyo1);
  }
  
  public Zt ZP(Zyc paramZyc, Zk paramZk) throws Zy_ {
    Zyv zyv = paramZyc.Zv(paramZk.Zf());
    Zia zia = zyv.Zo();
    Zt zt = paramZyc.ZK();
    Zk zk = zt.ZP((Zf)paramZyc, zia, paramZk);
    if (zk == null) {
      zk = paramZyc.Zg(paramZk);
      try {
        if (zk == null)
          return null; 
      } catch (IllegalArgumentException illegalArgumentException) {
        throw a(null);
      } 
    } 
    Collection collection = paramZyc.Zo().Zx((Zf)paramZyc, zia);
    try {
      if (zk.ZP() == null && paramZk.ZV()) {
        Zk zk1 = Zb(paramZyc, paramZk);
        try {
          if (zk1 != null && !zk1.ZP(paramZk.Zf()))
            zk = zk.ZN(zk1.Zf()); 
        } catch (IllegalArgumentException illegalArgumentException) {
          throw a(null);
        } 
      } 
    } catch (IllegalArgumentException illegalArgumentException) {
      throw a(null);
    } 
    try {
      return zk.Zn(paramZyc, paramZk, collection);
    } catch (IllegalArgumentException|IllegalStateException illegalArgumentException) {
      throw Zvj.Z_((Zg)null, Zx.Zr(illegalArgumentException), paramZk).Zc(illegalArgumentException);
    } 
  }
  
  protected Zyo<?> ZZ(Zyg paramZyg, Zk paramZk, Zyv paramZyv) throws Zy_ {
    return Zn.ZL.Zb(paramZk, paramZyg.Za(), paramZyv);
  }
  
  public Zf ZC(Zyg paramZyg, Zk paramZk) throws Zy_ {
    // Byte code:
    //   0: invokestatic ZP : ()Ljava/lang/String;
    //   3: aload_1
    //   4: invokevirtual Za : ()Lcom/fasterxml/Zor/Zyc;
    //   7: astore #4
    //   9: aconst_null
    //   10: astore #5
    //   12: astore_3
    //   13: aconst_null
    //   14: astore #6
    //   16: aload_0
    //   17: getfield Zo : Lcom/fasterxml/Zj/Zb;
    //   20: invokevirtual ZE : ()Z
    //   23: ifeq -> 111
    //   26: aload #4
    //   28: aload_2
    //   29: invokevirtual ZZ : (Lcom/fasterxml/Zor/Zk;)Lcom/fasterxml/Zor/Zyv;
    //   32: astore #5
    //   34: aload_0
    //   35: getfield Zo : Lcom/fasterxml/Zj/Zb;
    //   38: invokevirtual Zy : ()Ljava/lang/Iterable;
    //   41: invokeinterface iterator : ()Ljava/util/Iterator;
    //   46: astore #7
    //   48: aload #7
    //   50: invokeinterface hasNext : ()Z
    //   55: ifeq -> 111
    //   58: aload #7
    //   60: invokeinterface next : ()Ljava/lang/Object;
    //   65: checkcast com/fasterxml/Zo/Zr
    //   68: astore #8
    //   70: aload #8
    //   72: aload_2
    //   73: aload #4
    //   75: aload #5
    //   77: invokeinterface ZX : (Lcom/fasterxml/Zor/Zk;Lcom/fasterxml/Zor/Zyc;Lcom/fasterxml/Zor/Zyv;)Lcom/fasterxml/Zor/Zf;
    //   82: astore #6
    //   84: aload #6
    //   86: ifnull -> 100
    //   89: aload_3
    //   90: ifnull -> 111
    //   93: goto -> 100
    //   96: invokestatic a : (Ljava/lang/Exception;)Ljava/lang/Exception;
    //   99: athrow
    //   100: aload_3
    //   101: ifnull -> 48
    //   104: goto -> 111
    //   107: invokestatic a : (Ljava/lang/Exception;)Ljava/lang/Exception;
    //   110: athrow
    //   111: aload #6
    //   113: ifnonnull -> 190
    //   116: aload #5
    //   118: ifnonnull -> 139
    //   121: goto -> 128
    //   124: invokestatic a : (Ljava/lang/Exception;)Ljava/lang/Exception;
    //   127: athrow
    //   128: aload #4
    //   130: aload_2
    //   131: invokevirtual Zf : ()Ljava/lang/Class;
    //   134: invokevirtual Zv : (Ljava/lang/Class;)Lcom/fasterxml/Zor/Zyv;
    //   137: astore #5
    //   139: aload_0
    //   140: aload_1
    //   141: aload #5
    //   143: invokevirtual Zo : ()Lcom/fasterxml/Zoz/Zia;
    //   146: invokevirtual ZB : (Lcom/fasterxml/Zor/Zyg;Lcom/fasterxml/Zoz/Ziv;)Lcom/fasterxml/Zor/Zf;
    //   149: astore #6
    //   151: aload #6
    //   153: ifnonnull -> 190
    //   156: aload_2
    //   157: invokevirtual ZF : ()Z
    //   160: ifeq -> 182
    //   163: goto -> 170
    //   166: invokestatic a : (Ljava/lang/Exception;)Ljava/lang/Exception;
    //   169: athrow
    //   170: aload_0
    //   171: aload_1
    //   172: aload_2
    //   173: invokespecial Zz : (Lcom/fasterxml/Zor/Zyg;Lcom/fasterxml/Zor/Zk;)Lcom/fasterxml/Zor/Zf;
    //   176: astore #6
    //   178: aload_3
    //   179: ifnull -> 190
    //   182: aload #4
    //   184: aload_2
    //   185: invokestatic Zm : (Lcom/fasterxml/Zor/Zyc;Lcom/fasterxml/Zor/Zk;)Lcom/fasterxml/Zor/Zf;
    //   188: astore #6
    //   190: aload #6
    //   192: ifnull -> 264
    //   195: aload_0
    //   196: getfield Zo : Lcom/fasterxml/Zj/Zb;
    //   199: invokevirtual ZQ : ()Z
    //   202: ifeq -> 264
    //   205: goto -> 212
    //   208: invokestatic a : (Ljava/lang/Exception;)Ljava/lang/Exception;
    //   211: athrow
    //   212: aload_0
    //   213: getfield Zo : Lcom/fasterxml/Zj/Zb;
    //   216: invokevirtual Zn : ()Ljava/lang/Iterable;
    //   219: invokeinterface iterator : ()Ljava/util/Iterator;
    //   224: astore #7
    //   226: aload #7
    //   228: invokeinterface hasNext : ()Z
    //   233: ifeq -> 264
    //   236: aload #7
    //   238: invokeinterface next : ()Ljava/lang/Object;
    //   243: checkcast com/fasterxml/Zo/Zb
    //   246: astore #8
    //   248: aload #8
    //   250: aload #4
    //   252: aload_2
    //   253: aload #6
    //   255: invokevirtual ZG : (Lcom/fasterxml/Zor/Zyc;Lcom/fasterxml/Zor/Zk;Lcom/fasterxml/Zor/Zf;)Lcom/fasterxml/Zor/Zf;
    //   258: astore #6
    //   260: aload_3
    //   261: ifnull -> 226
    //   264: aload #6
    //   266: areturn
    // Exception table:
    //   from	to	target	type
    //   84	93	96	com/fasterxml/Zor/Zy_
    //   89	104	107	com/fasterxml/Zor/Zy_
    //   111	121	124	com/fasterxml/Zor/Zy_
    //   151	163	166	com/fasterxml/Zor/Zy_
    //   190	205	208	com/fasterxml/Zor/Zy_
  }
  
  private Zf Zz(Zyg paramZyg, Zk paramZk) throws Zy_ {
    Zyc zyc = paramZyg.Za();
    Class<?> clazz = paramZk.Zf();
    Zyv zyv = zyc.ZA(paramZk);
    String str = Zzp.ZP();
    Zf zf = ZB(paramZyg, (Ziv)zyv.Zo());
    try {
      if (zf != null)
        return zf; 
    } catch (Zy_ zy_) {
      throw a(null);
    } 
    Zyo<?> zyo = ZI(clazz, zyc, zyv);
    try {
      if (zyo != null)
        return Zfm.Zx(zyc, paramZk, zyo); 
    } catch (Zy_ zy_) {
      throw a(null);
    } 
    Zyo<Object> zyo1 = Zr(paramZyg, (Ziv)zyv.Zo());
    try {
      if (zyo1 != null)
        return Zfm.Zx(zyc, paramZk, zyo1); 
    } catch (Zy_ zy_) {
      throw a(null);
    } 
    Zef zef1 = Zb(clazz, zyc, zyv);
    Zef zef2 = ZH(zyc, zyv.Zo());
    Zef zef3 = Zef.ZX(zyc, zyv.Zo());
    Zef zef4 = Zef.ZO(zyc, zyv.Zo());
    for (Ziq ziq : zyv.ZK()) {
      if (ZY(paramZyg, (Ziv)ziq)) {
        int i = ziq.ZL();
        if (i == 1) {
          Class clazz1 = ziq.Zy();
          try {
            if (clazz1.isAssignableFrom(clazz)) {
              try {
                if (ziq.ZP(0) == String.class || str != null) {
                  try {
                    if (zyc.Zd())
                      Zx.ZR(ziq.ZP(), paramZyg.Zm(Zy9.OVERRIDE_PUBLIC_ACCESS_MODIFIERS)); 
                  } catch (Zy_ zy_) {
                    throw a(null);
                  } 
                  return Zfm.Zu(zef1, ziq, zef2, zef3, zef4);
                } 
              } catch (Zy_ zy_) {
                throw a(null);
              } 
              continue;
            } 
          } catch (Zy_ zy_) {
            throw a(null);
          } 
        } 
        throw new IllegalArgumentException(a(8517, -26915) + ziq + a(8521, 4099) + clazz.getName() + ")");
      } 
      if (str != null)
        break; 
    } 
    return Zfm.ZG(zef1, zef2, zef3, zef4);
  }
  
  public Zt ZW(Zyc paramZyc, Zk paramZk, Ziz paramZiz) throws Zy_ {
    Zt zt = paramZyc.ZK();
    Zk zk = zt.ZY((Zf)paramZyc, paramZiz, paramZk);
    try {
      if (zk == null)
        return ZP(paramZyc, paramZk); 
    } catch (IllegalArgumentException illegalArgumentException) {
      throw a(null);
    } 
    Collection collection = paramZyc.Zo().Zw((Zf)paramZyc, paramZiz, paramZk);
    try {
      return zk.Zn(paramZyc, paramZk, collection);
    } catch (IllegalArgumentException|IllegalStateException illegalArgumentException) {
      throw Zvj.Z_((Zg)null, Zx.Zr(illegalArgumentException), paramZk).Zc(illegalArgumentException);
    } 
  }
  
  public Zt Zp(Zyc paramZyc, Zk paramZk, Ziz paramZiz) throws Zy_ {
    Zt zt = paramZyc.ZK();
    Zk zk = zt.ZU((Zf)paramZyc, paramZiz, paramZk);
    Zk zk1 = paramZk.ZB();
    try {
      if (zk == null)
        return ZP(paramZyc, zk1); 
    } catch (Zy_ zy_) {
      throw a(null);
    } 
    Collection collection = paramZyc.Zo().Zw((Zf)paramZyc, paramZiz, zk1);
    return zk.Zn(paramZyc, zk1, collection);
  }
  
  public Zyo<?> Zy(Zyg paramZyg, Zk paramZk, Zyv paramZyv) throws Zy_ {
    Class<?> clazz = paramZk.Zf();
    String str = Zzp.ZP();
    try {
      if (clazz == ZS || clazz == ZO) {
        Zyc zyc = paramZyg.Za();
        if (this.Zo.ZA()) {
          Zk zk3 = ZE(zyc, List.class);
          Zk zk4 = ZE(zyc, Map.class);
          if (str != null) {
            zk3 = zk4 = null;
            return (Zyo<?>)new Zfz(zk3, zk4);
          } 
          return (Zyo<?>)new Zfz(zk3, zk4);
        } 
      } else {
        try {
          if (clazz != Z_) {
            try {
              if (clazz == Zu)
                return (Zyo<?>)Zf5.ZN; 
            } catch (Zy_ zy_) {
              throw a(null);
            } 
          } else {
            return (Zyo<?>)Zf5.ZN;
          } 
        } catch (Zy_ zy_) {
          throw a(null);
        } 
        if (clazz == ZN) {
          Zi zi = paramZyg.ZL();
          Zk[] arrayOfZk = zi.Zs(paramZk, ZN);
          try {
            if (arrayOfZk != null) {
              try {
                if (arrayOfZk.length != 1);
              } catch (Zy_ zy_) {
                throw a(null);
              } 
              Zk zk = arrayOfZk[0];
              Zs zs = zi.Zi(Collection.class, zk);
              return Zy(paramZyg, zs, paramZyv);
            } 
          } catch (Zy_ zy_) {
            throw a(null);
          } 
        } else {
          if (clazz == Zw) {
            Zk zk3 = paramZk.ZO(0);
            Zk zk4 = paramZk.ZO(1);
            Zt zt = (Zt)zk4.Zi();
            if (zt == null)
              zt = ZP(paramZyg.Za(), zk4); 
            Zyo zyo1 = (Zyo)zk4.ZY();
            Zf zf = (Zf)zk3.ZY();
            return (Zyo<?>)new Zus(paramZk, zf, zyo1, zt);
          } 
          String str1 = clazz.getName();
          try {
            if (clazz.isPrimitive() || str1.startsWith(a(8538, 9856))) {
              Zyo<?> zyo1 = Zfy.Zn(clazz, str1);
              if (zyo1 == null)
                zyo1 = Zf.Zh(clazz, str1); 
              try {
                if (zyo1 != null)
                  return zyo1; 
              } catch (Zy_ zy_) {
                throw a(null);
              } 
            } 
          } catch (Zy_ zy_) {
            throw a(null);
          } 
          try {
            if (clazz == Zl.class)
              return (Zyo<?>)new Zfd(); 
          } catch (Zy_ zy_) {
            throw a(null);
          } 
          Zyo<?> zyo = ZZ(paramZyg, paramZk, paramZyv);
          try {
            if (zyo != null)
              return zyo; 
          } catch (Zy_ zy_) {
            throw a(null);
          } 
          return Zfv.ZP(paramZyg, clazz, str1);
        } 
      } 
    } catch (Zy_ zy_) {
      throw a(null);
    } 
    Zk zk2 = null;
    Zk zk1 = zk2;
    return (Zyo<?>)new Zfz(zk1, zk2);
  }
  
  protected Zk ZE(Zyc paramZyc, Class<?> paramClass) throws Zy_ {
    Zk zk = Zb(paramZyc, paramZyc.Zu(paramClass));
    try {
      if (zk != null) {
        try {
          if (zk.ZP(paramClass));
        } catch (Zy_ zy_) {
          throw a(null);
        } 
        return zk;
      } 
    } catch (Zy_ zy_) {
      throw a(null);
    } 
  }
  
  protected Zyo<?> ZJ(Class<? extends Zb> paramClass, Zyc paramZyc, Zyv paramZyv) throws Zy_ {
    Iterator<Zza> iterator = this.Zo.ZJ().iterator();
    String str = Zzp.ZP();
    while (iterator.hasNext()) {
      Zza zza = iterator.next();
      Zyo<?> zyo = zza.Zy(paramClass, paramZyc, paramZyv);
      try {
        if (zyo != null)
          return zyo; 
      } catch (Zy_ zy_) {
        throw a(null);
      } 
      if (str != null)
        break; 
    } 
    return null;
  }
  
  protected Zyo<?> ZK(Zn paramZn, Zyc paramZyc, Zyv paramZyv, Zt paramZt, Zyo<?> paramZyo) throws Zy_ {
    Iterator<Zza> iterator = this.Zo.ZJ().iterator();
    String str = Zzp.ZP();
    while (iterator.hasNext()) {
      Zza zza = iterator.next();
      Zyo<?> zyo = zza.Z_(paramZn, paramZyc, paramZyv, paramZt, paramZyo);
      try {
        if (zyo != null)
          return zyo; 
      } catch (Zy_ zy_) {
        throw a(null);
      } 
      if (str != null)
        break; 
    } 
    return null;
  }
  
  protected Zyo<Object> Zt(Zk paramZk, Zyc paramZyc, Zyv paramZyv) throws Zy_ {
    Iterator<Zza> iterator = this.Zo.ZJ().iterator();
    String str = Zzp.ZP();
    while (iterator.hasNext()) {
      Zza zza = iterator.next();
      Zyo<?> zyo = zza.ZV(paramZk, paramZyc, paramZyv);
      try {
        if (zyo != null)
          return (Zyo)zyo; 
      } catch (Zy_ zy_) {
        throw a(null);
      } 
      if (str != null)
        break; 
    } 
    return null;
  }
  
  protected Zyo<?> Zm(Zg paramZg, Zyc paramZyc, Zyv paramZyv, Zt paramZt, Zyo<?> paramZyo) throws Zy_ {
    Iterator<Zza> iterator = this.Zo.ZJ().iterator();
    String str = Zzp.ZP();
    while (iterator.hasNext()) {
      Zza zza = iterator.next();
      Zyo<?> zyo = zza.ZN(paramZg, paramZyc, paramZyv, paramZt, paramZyo);
      try {
        if (zyo != null)
          return zyo; 
      } catch (Zy_ zy_) {
        throw a(null);
      } 
      if (str != null)
        break; 
    } 
    return null;
  }
  
  protected Zyo<?> ZE(Zs paramZs, Zyc paramZyc, Zyv paramZyv, Zt paramZt, Zyo<?> paramZyo) throws Zy_ {
    Iterator<Zza> iterator = this.Zo.ZJ().iterator();
    String str = Zzp.ZP();
    while (iterator.hasNext()) {
      Zza zza = iterator.next();
      Zyo<?> zyo = zza.Zg(paramZs, paramZyc, paramZyv, paramZt, paramZyo);
      try {
        if (zyo != null)
          return zyo; 
      } catch (Zy_ zy_) {
        throw a(null);
      } 
      if (str != null)
        break; 
    } 
    return null;
  }
  
  protected Zyo<?> ZY(Ze paramZe, Zyc paramZyc, Zyv paramZyv, Zt paramZt, Zyo<?> paramZyo) throws Zy_ {
    Iterator<Zza> iterator = this.Zo.ZJ().iterator();
    String str = Zzp.ZP();
    while (iterator.hasNext()) {
      Zza zza = iterator.next();
      Zyo<?> zyo = zza.ZQ(paramZe, paramZyc, paramZyv, paramZt, paramZyo);
      try {
        if (zyo != null)
          return zyo; 
      } catch (Zy_ zy_) {
        throw a(null);
      } 
      if (str != null)
        break; 
    } 
    return null;
  }
  
  protected Zyo<?> ZI(Class<?> paramClass, Zyc paramZyc, Zyv paramZyv) throws Zy_ {
    Iterator<Zza> iterator = this.Zo.ZJ().iterator();
    String str = Zzp.ZP();
    while (iterator.hasNext()) {
      Zza zza = iterator.next();
      Zyo<?> zyo = zza.Zw(paramClass, paramZyc, paramZyv);
      try {
        if (zyo != null)
          return zyo; 
      } catch (Zy_ zy_) {
        throw a(null);
      } 
      if (str != null)
        break; 
    } 
    return null;
  }
  
  protected Zyo<?> Zn(Zf paramZf, Zyc paramZyc, Zyv paramZyv, Zf paramZf1, Zt paramZt, Zyo<?> paramZyo) throws Zy_ {
    Iterator<Zza> iterator = this.Zo.ZJ().iterator();
    String str = Zzp.ZP();
    while (iterator.hasNext()) {
      Zza zza = iterator.next();
      Zyo<?> zyo = zza.Zt(paramZf, paramZyc, paramZyv, paramZf1, paramZt, paramZyo);
      try {
        if (zyo != null)
          return zyo; 
      } catch (Zy_ zy_) {
        throw a(null);
      } 
      if (str != null)
        break; 
    } 
    return null;
  }
  
  protected Zyo<?> Zr(Zo paramZo, Zyc paramZyc, Zyv paramZyv, Zf paramZf, Zt paramZt, Zyo<?> paramZyo) throws Zy_ {
    Iterator<Zza> iterator = this.Zo.ZJ().iterator();
    String str = Zzp.ZP();
    while (iterator.hasNext()) {
      Zza zza = iterator.next();
      Zyo<?> zyo = zza.ZV(paramZo, paramZyc, paramZyv, paramZf, paramZt, paramZyo);
      try {
        if (zyo != null)
          return zyo; 
      } catch (Zy_ zy_) {
        throw a(null);
      } 
      if (str != null)
        break; 
    } 
    return null;
  }
  
  protected Zyo<Object> Zr(Zyg paramZyg, Ziv paramZiv) throws Zy_ {
    Zt zt = paramZyg.Zv();
    if (zt != null) {
      Object object = zt.Zs(paramZiv);
      try {
        if (object != null)
          return paramZyg.ZM(paramZiv, object); 
      } catch (Zy_ zy_) {
        throw a(null);
      } 
    } 
    return null;
  }
  
  protected Zf ZB(Zyg paramZyg, Ziv paramZiv) throws Zy_ {
    Zt zt = paramZyg.Zv();
    if (zt != null) {
      Object object = zt.ZZ(paramZiv);
      try {
        if (object != null)
          return paramZyg.Zx(paramZiv, object); 
      } catch (Zy_ zy_) {
        throw a(null);
      } 
    } 
    return null;
  }
  
  protected Zyo<Object> Zn(Zyg paramZyg, Ziv paramZiv) throws Zy_ {
    Zt zt = paramZyg.Zv();
    if (zt != null) {
      Object object = zt.Zg(paramZiv);
      try {
        if (object != null)
          return paramZyg.ZM(paramZiv, object); 
      } catch (Zy_ zy_) {
        throw a(null);
      } 
    } 
    return null;
  }
  
  protected Zk ZA(Zyg paramZyg, Ziz paramZiz, Zk paramZk) throws Zy_ {
    Zo zo;
    Zt zt = paramZyg.Zv();
    try {
      if (zt == null)
        return paramZk; 
    } catch (Zy_ zy_) {
      throw a(null);
    } 
    if (paramZk.Zh()) {
      Zk zk = paramZk.Zu();
      if (zk != null) {
        Object object = zt.ZZ((Ziv)paramZiz);
        Zf zf = paramZyg.Zx((Ziv)paramZiz, object);
        if (zf != null) {
          zo = ((Zo)paramZk).ZO(zf);
          zk = zo.Zu();
        } 
      } 
    } 
    if (zo.ZG()) {
      Object object = zt.Zg((Ziv)paramZiz);
      Zyo zyo = paramZyg.ZM((Ziv)paramZiz, object);
      if (zyo != null)
        null = zo.Zw(zyo); 
      Zt zt2 = Zp(paramZyg.Za(), null, paramZiz);
      if (zt2 != null)
        null = null.ZW(zt2); 
    } 
    Zt zt1 = ZW(paramZyg.Za(), null, paramZiz);
    if (zt1 != null)
      null = null.Zc(zt1); 
    return zt.ZL((Zf)paramZyg.Za(), (Ziv)paramZiz, null);
  }
  
  protected Zef Zb(Class<?> paramClass, Zyc paramZyc, Zyv paramZyv) {
    Ziz ziz = paramZyv.ZG();
    try {
      if (ziz != null) {
        try {
          if (paramZyc.Zd())
            Zx.ZR(ziz.ZI(), paramZyc.ZB(Zy9.OVERRIDE_PUBLIC_ACCESS_MODIFIERS)); 
        } catch (IllegalArgumentException illegalArgumentException) {
          throw a(null);
        } 
        return Zef.Zf(paramZyc, paramZyv.Zo(), ziz);
      } 
    } catch (IllegalArgumentException illegalArgumentException) {
      throw a(null);
    } 
    return Zef.ZW(paramZyc, paramZyv.Zo());
  }
  
  protected Zef ZH(Zyc paramZyc, Zia paramZia) {
    Object object = paramZyc.ZK().Zg((Zf)paramZyc, paramZia);
    Zp zp = Zy.ZM(object, paramZyc.Zd());
    try {
    
    } catch (IllegalArgumentException illegalArgumentException) {
      throw a(null);
    } 
    return (zp == null) ? null : Zef.ZT(paramZyc, paramZia, zp);
  }
  
  protected boolean ZY(Zyg paramZyg, Ziv paramZiv) {
    Zt zt = paramZyg.Zv();
    if (zt != null) {
      Zgd zgd = zt.ZD((Zf)paramZyg.Za(), paramZiv);
      try {
        if (zgd != null)
          try {
            if (zgd != Zgd.DISABLED);
          } catch (IllegalArgumentException illegalArgumentException) {
            throw a(null);
          }  
      } catch (IllegalArgumentException illegalArgumentException) {
        throw a(null);
      } 
      return false;
    } 
    return false;
  }
  
  static {
    // Byte code:
    //   0: bipush #24
    //   2: anewarray java/lang/String
    //   5: astore #5
    //   7: iconst_0
    //   8: istore_3
    //   9: ldc 'dr%2}V8c]16b9{9%F<A tY [K#4$\\bONGL[%{'!DXdLfp}Ui e2=&{2}1Q~\\rso)w.H-C!\\byt&b-L{ aXm\\t<6Kw{lYaRb9p66d\T4,m0Eb!9?a{hAe?b(d$6$gj8<:K3\\f)"4hZ\\tRN.v\OAR,C{jX[6%~\\bHE">\h[Wof=<kx:ZTj#PP5psUl3OIihFviFo>r;[P37XhQ(9\\n<PjiVkZ5 vbWQE/nc ^]0J <U4y\\tuWU+1U>]5\\r2\\f5q%+'KL$W^*E2z*ZC!@5V}O>$(M}ZyBX $s@$\\f?xiZs@<yDfXX\\r#9&5|xZlJsD~FTeJ!W5Pw<&]T~'CF%TS25f&Oy5j)^47s?;aU1Bt;g`*bkyAm9(W%Oz365;7|HH7pOuIk&jCR_-\\b58{\8o2Wiq@(W>5*#y*@rjU4Q=*rUgL\\rAV!xG^\\t:+VrV;bpnvoO(Bd^dU"Y3`AO#wc>UOtzav3\\t\\bG+pEBr'r7)\\b:VD!eVR"(\&<wrmgvG>4xisMS#n[i\\tbNNN)'iUMqzWY(;g|"&c#!'Y4%QEHC*)U[^-\\r~'
    //   11: dup
    //   12: astore_2
    //   13: invokevirtual length : ()I
    //   16: istore #4
    //   18: bipush #45
    //   20: istore_1
    //   21: iconst_m1
    //   22: istore_0
    //   23: bipush #12
    //   25: iinc #0, 1
    //   28: aload_2
    //   29: iload_0
    //   30: dup
    //   31: iload_1
    //   32: iadd
    //   33: invokevirtual substring : (II)Ljava/lang/String;
    //   36: iconst_m1
    //   37: goto -> 143
    //   40: aload #5
    //   42: swap
    //   43: iload_3
    //   44: iinc #3, 1
    //   47: swap
    //   48: aastore
    //   49: iload_0
    //   50: iload_1
    //   51: iadd
    //   52: dup
    //   53: istore_0
    //   54: iload #4
    //   56: if_icmpge -> 68
    //   59: aload_2
    //   60: iload_0
    //   61: invokevirtual charAt : (I)C
    //   64: istore_1
    //   65: goto -> 23
    //   68: ldc '94=+'*6lGsQ(SYe,]QP\\f+Q+zmxR\[\\fL8Z6?+y~>"*oaPn2q^KoWMz`^nD*5`  7_U6\\rI?uT4>u:A'io9Z^jY'
    //   70: dup
    //   71: astore_2
    //   72: invokevirtual length : ()I
    //   75: istore #4
    //   77: bipush #68
    //   79: istore_1
    //   80: iconst_m1
    //   81: istore_0
    //   82: bipush #120
    //   84: iinc #0, 1
    //   87: aload_2
    //   88: iload_0
    //   89: dup
    //   90: iload_1
    //   91: iadd
    //   92: invokevirtual substring : (II)Ljava/lang/String;
    //   95: iconst_0
    //   96: goto -> 143
    //   99: aload #5
    //   101: swap
    //   102: iload_3
    //   103: iinc #3, 1
    //   106: swap
    //   107: aastore
    //   108: iload_0
    //   109: iload_1
    //   110: iadd
    //   111: dup
    //   112: istore_0
    //   113: iload #4
    //   115: if_icmpge -> 127
    //   118: aload_2
    //   119: iload_0
    //   120: invokevirtual charAt : (I)C
    //   123: istore_1
    //   124: goto -> 82
    //   127: aload #5
    //   129: putstatic com/fasterxml/Zo/Zj.a : [Ljava/lang/String;
    //   132: bipush #24
    //   134: anewarray java/lang/String
    //   137: putstatic com/fasterxml/Zo/Zj.b : [Ljava/lang/String;
    //   140: goto -> 300
    //   143: dup_x2
    //   144: pop
    //   145: invokevirtual toCharArray : ()[C
    //   148: dup_x1
    //   149: arraylength
    //   150: dup_x2
    //   151: pop
    //   152: iconst_0
    //   153: istore #6
    //   155: dup2_x1
    //   156: pop2
    //   157: dup_x2
    //   158: iconst_1
    //   159: if_icmpgt -> 260
    //   162: dup2
    //   163: swap
    //   164: iload #6
    //   166: dup2_x1
    //   167: caload
    //   168: swap
    //   169: iload #6
    //   171: bipush #7
    //   173: irem
    //   174: tableswitch default -> 242, 0 -> 212, 1 -> 217, 2 -> 222, 3 -> 227, 4 -> 232, 5 -> 237
    //   212: bipush #107
    //   214: goto -> 244
    //   217: bipush #105
    //   219: goto -> 244
    //   222: bipush #33
    //   224: goto -> 244
    //   227: bipush #86
    //   229: goto -> 244
    //   232: bipush #80
    //   234: goto -> 244
    //   237: bipush #120
    //   239: goto -> 244
    //   242: bipush #56
    //   244: ixor
    //   245: ixor
    //   246: i2c
    //   247: castore
    //   248: iinc #6, 1
    //   251: dup
    //   252: ifne -> 260
    //   255: dup2
    //   256: dup_x1
    //   257: goto -> 166
    //   260: dup2_x1
    //   261: pop2
    //   262: dup_x2
    //   263: iload #6
    //   265: if_icmpgt -> 162
    //   268: pop
    //   269: new java/lang/String
    //   272: dup_x1
    //   273: swap
    //   274: invokespecial <init> : ([C)V
    //   277: invokevirtual intern : ()Ljava/lang/String;
    //   280: swap
    //   281: pop
    //   282: swap
    //   283: tableswitch default -> 40, 0 -> 99
    //   300: ldc java/lang/Object
    //   302: putstatic com/fasterxml/Zo/Zj.ZS : Ljava/lang/Class;
    //   305: ldc java/lang/String
    //   307: putstatic com/fasterxml/Zo/Zj.Z_ : Ljava/lang/Class;
    //   310: ldc java/lang/CharSequence
    //   312: putstatic com/fasterxml/Zo/Zj.Zu : Ljava/lang/Class;
    //   315: ldc java/lang/Iterable
    //   317: putstatic com/fasterxml/Zo/Zj.ZN : Ljava/lang/Class;
    //   320: ldc java/util/Map$Entry
    //   322: putstatic com/fasterxml/Zo/Zj.Zw : Ljava/lang/Class;
    //   325: ldc java/io/Serializable
    //   327: putstatic com/fasterxml/Zo/Zj.ZO : Ljava/lang/Class;
    //   330: new com/fasterxml/Zor/Zr
    //   333: dup
    //   334: sipush #8526
    //   337: sipush #-23419
    //   340: invokestatic a : (II)Ljava/lang/String;
    //   343: invokespecial <init> : (Ljava/lang/String;)V
    //   346: putstatic com/fasterxml/Zo/Zj.Zf : Lcom/fasterxml/Zor/Zr;
    //   349: return
  }
  
  private static Exception a(Exception paramException) {
    return paramException;
  }
  
  private static String a(int paramInt1, int paramInt2) {
    int i = (paramInt1 ^ 0x2149) & 0xFFFF;
    if (b[i] == null) {
      char[] arrayOfChar = a[i].toCharArray();
      switch (arrayOfChar[0] & 0xFF) {
        case 0:
        
        case 1:
        
        case 2:
        
        case 3:
        
        case 4:
        
        case 5:
        
        case 6:
        
        case 7:
        
        case 8:
        
        case 9:
        
        case 10:
        
        case 11:
        
        case 12:
        
        case 13:
        
        case 14:
        
        case 15:
        
        case 16:
        
        case 17:
        
        case 18:
        
        case 19:
        
        case 20:
        
        case 21:
        
        case 22:
        
        case 23:
        
        case 24:
        
        case 25:
        
        case 26:
        
        case 27:
        
        case 28:
        
        case 29:
        
        case 30:
        
        case 31:
        
        case 32:
        
        case 33:
        
        case 34:
        
        case 35:
        
        case 36:
        
        case 37:
        
        case 38:
        
        case 39:
        
        case 40:
        
        case 41:
        
        case 42:
        
        case 43:
        
        case 44:
        
        case 45:
        
        case 46:
        
        case 47:
        
        case 48:
        
        case 49:
        
        case 50:
        
        case 51:
        
        case 52:
        
        case 53:
        
        case 54:
        
        case 55:
        
        case 56:
        
        case 57:
        
        case 58:
        
        case 59:
        
        case 60:
        
        case 61:
        
        case 62:
        
        case 63:
        
        case 64:
        
        case 65:
        
        case 66:
        
        case 67:
        
        case 68:
        
        case 69:
        
        case 70:
        
        case 71:
        
        case 72:
        
        case 73:
        
        case 74:
        
        case 75:
        
        case 76:
        
        case 77:
        
        case 78:
        
        case 79:
        
        case 80:
        
        case 81:
        
        case 82:
        
        case 83:
        
        case 84:
        
        case 85:
        
        case 86:
        
        case 87:
        
        case 88:
        
        case 89:
        
        case 90:
        
        case 91:
        
        case 92:
        
        case 93:
        
        case 94:
        
        case 95:
        
        case 96:
        
        case 97:
        
        case 98:
        
        case 99:
        
        case 100:
        
        case 101:
        
        case 102:
        
        case 103:
        
        case 104:
        
        case 105:
        
        case 106:
        
        case 107:
        
        case 108:
        
        case 109:
        
        case 110:
        
        case 111:
        
        case 112:
        
        case 113:
        
        case 114:
        
        case 115:
        
        case 116:
        
        case 117:
        
        case 118:
        
        case 119:
        
        case 120:
        
        case 121:
        
        case 122:
        
        case 123:
        
        case 124:
        
        case 125:
        
        case 126:
        
        case 127:
        
        case 128:
        
        case 129:
        
        case 130:
        
        case 131:
        
        case 132:
        
        case 133:
        
        case 134:
        
        case 135:
        
        case 136:
        
        case 137:
        
        case 138:
        
        case 139:
        
        case 140:
        
        case 141:
        
        case 142:
        
        case 143:
        
        case 144:
        
        case 145:
        
        case 146:
        
        case 147:
        
        case 148:
        
        case 149:
        
        case 150:
        
        case 151:
        
        case 152:
        
        case 153:
        
        case 154:
        
        case 155:
        
        case 156:
        
        case 157:
        
        case 158:
        
        case 159:
        
        case 160:
        
        case 161:
        
        case 162:
        
        case 163:
        
        case 164:
        
        case 165:
        
        case 166:
        
        case 167:
        
        case 168:
        
        case 169:
        
        case 170:
        
        case 171:
        
        case 172:
        
        case 173:
        
        case 174:
        
        case 175:
        
        case 176:
        
        case 177:
        
        case 178:
        
        case 179:
        
        case 180:
        
        case 181:
        
        case 182:
        
        case 183:
        
        case 184:
        
        case 185:
        
        case 186:
        
        case 187:
        
        case 188:
        
        case 189:
        
        case 190:
        
        case 191:
        
        case 192:
        
        case 193:
        
        case 194:
        
        case 195:
        
        case 196:
        
        case 197:
        
        case 198:
        
        case 199:
        
        case 200:
        
        case 201:
        
        case 202:
        
        case 203:
        
        case 204:
        
        case 205:
        
        case 206:
        
        case 207:
        
        case 208:
        
        case 209:
        
        case 210:
        
        case 211:
        
        case 212:
        
        case 213:
        
        case 214:
        
        case 215:
        
        case 216:
        
        case 217:
        
        case 218:
        
        case 219:
        
        case 220:
        
        case 221:
        
        case 222:
        
        case 223:
        
        case 224:
        
        case 225:
        
        case 226:
        
        case 227:
        
        case 228:
        
        case 229:
        
        case 230:
        
        case 231:
        
        case 232:
        
        case 233:
        
        case 234:
        
        case 235:
        
        case 236:
        
        case 237:
        
        case 238:
        
        case 239:
        
        case 240:
        
        case 241:
        
        case 242:
        
        case 243:
        
        case 244:
        
        case 245:
        
        case 246:
        
        case 247:
        
        case 248:
        
        case 249:
        
        case 250:
        
        case 251:
        
        case 252:
        
        case 253:
        
        case 254:
        
        default:
          break;
      } 
      char c = '';
      int j = (paramInt2 & 0xFF) - c;
      if (j < 0)
        j += 256; 
      int k = ((paramInt2 & 0xFFFF) >>> 8) - c;
      if (k < 0)
        k += 256; 
      for (byte b = 0; b < arrayOfChar.length; b++) {
        int m = b % 2;
        if (m == 0) {
          arrayOfChar[b] = (char)(arrayOfChar[b] ^ j);
          j = ((j >>> 3 | j << 5) ^ arrayOfChar[b]) & 0xFF;
        } else {
          arrayOfChar[b] = (char)(arrayOfChar[b] ^ k);
          k = ((k >>> 3 | k << 5) ^ arrayOfChar[b]) & 0xFF;
        } 
      } 
      b[i] = (new String(arrayOfChar)).intern();
    } 
    return b[i];
  }
}


/* Location:              C:\Program Files\BurpSuitePro\burpsuite_pro.jar!\com\fasterxml\Zo\Zj.class
 * Java compiler version: 8 (52.0)
 * JD-Core Version:       1.1.3
 */