package com.fasterxml.Ze;

import com.fasterxml.Zb.Zg;
import com.fasterxml.Zm.Zee;
import com.fasterxml.Zm.Zx;
import com.fasterxml.Zo.Zf;
import com.fasterxml.Zo.Zv;
import com.fasterxml.Zor.Zyg;
import com.fasterxml.Zor.Zyo;
import java.io.IOException;
import java.util.Set;

public class Zog extends Zf {
  private static final long serialVersionUID = 1L;
  
  protected final Zf ZS;
  
  protected final Zv[] ZD;
  
  private static final String[] g;
  
  private static final String[] h;
  
  public Zog(Zf paramZf, Zv[] paramArrayOfZv) {
    super(paramZf);
    this.ZS = paramZf;
    this.ZD = paramArrayOfZv;
  }
  
  public Zyo<Object> Zv(Zee paramZee) {
    return this.ZS.Zv(paramZee);
  }
  
  public Zf Zw(Zz paramZz) {
    return new Zog(this.ZS.Zw(paramZz), this.ZD);
  }
  
  public Zf Zv(Set<String> paramSet1, Set<String> paramSet2) {
    return new Zog(this.ZS.Zv(paramSet1, paramSet2), this.ZD);
  }
  
  public Zf ZI(boolean paramBoolean) {
    return new Zog(this.ZS.ZI(paramBoolean), this.ZD);
  }
  
  public Zf ZG(Zo8 paramZo8) {
    return new Zog(this.ZS.ZG(paramZo8), this.ZD);
  }
  
  protected Zf Zv() {
    return this;
  }
  
  public Object deserialize(Zg paramZg, Zyg paramZyg) throws IOException {
    // Byte code:
    //   0: invokestatic ZI : ()[Ljava/lang/String;
    //   3: astore_3
    //   4: aload_1
    //   5: invokevirtual Zs : ()Z
    //   8: ifne -> 22
    //   11: aload_0
    //   12: aload_1
    //   13: aload_2
    //   14: invokevirtual ZL : (Lcom/fasterxml/Zb/Zg;Lcom/fasterxml/Zor/Zyg;)Ljava/lang/Object;
    //   17: areturn
    //   18: invokestatic a : (Ljava/lang/Exception;)Ljava/lang/Exception;
    //   21: athrow
    //   22: aload_0
    //   23: getfield Zn : Z
    //   26: ifne -> 40
    //   29: aload_0
    //   30: aload_1
    //   31: aload_2
    //   32: invokevirtual Zc : (Lcom/fasterxml/Zb/Zg;Lcom/fasterxml/Zor/Zyg;)Ljava/lang/Object;
    //   35: areturn
    //   36: invokestatic a : (Ljava/lang/Exception;)Ljava/lang/Exception;
    //   39: athrow
    //   40: aload_0
    //   41: getfield Zb : Lcom/fasterxml/Zo/Zzp;
    //   44: aload_2
    //   45: invokevirtual Zy : (Lcom/fasterxml/Zor/Zyg;)Ljava/lang/Object;
    //   48: astore #4
    //   50: aload_1
    //   51: aload #4
    //   53: invokevirtual ZZ : (Ljava/lang/Object;)V
    //   56: aload_0
    //   57: getfield ZD : [Lcom/fasterxml/Zo/Zv;
    //   60: astore #5
    //   62: iconst_0
    //   63: istore #6
    //   65: aload #5
    //   67: arraylength
    //   68: istore #7
    //   70: aload_1
    //   71: invokevirtual ZV : ()Lcom/fasterxml/Zb/Zl;
    //   74: getstatic com/fasterxml/Zb/Zl.END_ARRAY : Lcom/fasterxml/Zb/Zl;
    //   77: if_acmpne -> 83
    //   80: aload #4
    //   82: areturn
    //   83: iload #6
    //   85: iload #7
    //   87: if_icmpne -> 101
    //   90: aload_3
    //   91: ifnull -> 165
    //   94: goto -> 101
    //   97: invokestatic a : (Ljava/lang/Exception;)Ljava/lang/Exception;
    //   100: athrow
    //   101: aload #5
    //   103: iload #6
    //   105: aaload
    //   106: astore #8
    //   108: aload #8
    //   110: ifnull -> 146
    //   113: aload #8
    //   115: aload_1
    //   116: aload_2
    //   117: aload #4
    //   119: invokevirtual ZP : (Lcom/fasterxml/Zb/Zg;Lcom/fasterxml/Zor/Zyg;Ljava/lang/Object;)V
    //   122: goto -> 158
    //   125: astore #9
    //   127: aload_0
    //   128: aload #9
    //   130: aload #4
    //   132: aload #8
    //   134: invokevirtual ZT : ()Ljava/lang/String;
    //   137: aload_2
    //   138: invokevirtual Zd : (Ljava/lang/Throwable;Ljava/lang/Object;Ljava/lang/String;Lcom/fasterxml/Zor/Zyg;)Ljava/lang/Object;
    //   141: pop
    //   142: aload_3
    //   143: ifnull -> 158
    //   146: aload_1
    //   147: invokevirtual Zc : ()Lcom/fasterxml/Zb/Zg;
    //   150: pop
    //   151: goto -> 158
    //   154: invokestatic a : (Ljava/lang/Exception;)Ljava/lang/Exception;
    //   157: athrow
    //   158: iinc #6, 1
    //   161: aload_3
    //   162: ifnull -> 70
    //   165: aload_0
    //   166: getfield Za : Z
    //   169: ifne -> 225
    //   172: aload_2
    //   173: getstatic com/fasterxml/Zor/Zyp.FAIL_ON_UNKNOWN_PROPERTIES : Lcom/fasterxml/Zor/Zyp;
    //   176: invokevirtual Zg : (Lcom/fasterxml/Zor/Zyp;)Z
    //   179: ifeq -> 225
    //   182: goto -> 189
    //   185: invokestatic a : (Ljava/lang/Exception;)Ljava/lang/Exception;
    //   188: athrow
    //   189: aload_2
    //   190: aload_0
    //   191: getstatic com/fasterxml/Zb/Zl.END_ARRAY : Lcom/fasterxml/Zb/Zl;
    //   194: sipush #21162
    //   197: sipush #12512
    //   200: invokestatic d : (II)Ljava/lang/String;
    //   203: iconst_1
    //   204: anewarray java/lang/Object
    //   207: dup
    //   208: iconst_0
    //   209: iload #7
    //   211: invokestatic valueOf : (I)Ljava/lang/Integer;
    //   214: aastore
    //   215: invokevirtual Zw : (Lcom/fasterxml/Zor/Zyo;Lcom/fasterxml/Zb/Zl;Ljava/lang/String;[Ljava/lang/Object;)V
    //   218: goto -> 225
    //   221: invokestatic a : (Ljava/lang/Exception;)Ljava/lang/Exception;
    //   224: athrow
    //   225: aload_1
    //   226: invokevirtual Zc : ()Lcom/fasterxml/Zb/Zg;
    //   229: pop
    //   230: aload_1
    //   231: invokevirtual ZV : ()Lcom/fasterxml/Zb/Zl;
    //   234: getstatic com/fasterxml/Zb/Zl.END_ARRAY : Lcom/fasterxml/Zb/Zl;
    //   237: if_acmpne -> 225
    //   240: aload #4
    //   242: areturn
    //   243: invokestatic a : (Ljava/lang/Exception;)Ljava/lang/Exception;
    //   246: athrow
    // Exception table:
    //   from	to	target	type
    //   4	18	18	java/lang/Exception
    //   22	36	36	java/lang/Exception
    //   83	94	97	java/lang/Exception
    //   113	122	125	java/lang/Exception
    //   127	151	154	java/lang/Exception
    //   165	182	185	java/lang/Exception
    //   172	218	221	java/lang/Exception
    //   225	243	243	java/lang/Exception
  }
  
  public Object ZI(Zg paramZg, Zyg paramZyg, Object paramObject) throws IOException {
    // Byte code:
    //   0: invokestatic ZI : ()[Ljava/lang/String;
    //   3: aload_1
    //   4: aload_3
    //   5: invokevirtual ZZ : (Ljava/lang/Object;)V
    //   8: astore #4
    //   10: aload_1
    //   11: invokevirtual Zs : ()Z
    //   14: ifne -> 28
    //   17: aload_0
    //   18: aload_1
    //   19: aload_2
    //   20: invokevirtual ZL : (Lcom/fasterxml/Zb/Zg;Lcom/fasterxml/Zor/Zyg;)Ljava/lang/Object;
    //   23: areturn
    //   24: invokestatic a : (Ljava/lang/Exception;)Ljava/lang/Exception;
    //   27: athrow
    //   28: aload_0
    //   29: getfield Zy : [Lcom/fasterxml/Ze/Zv;
    //   32: ifnull -> 48
    //   35: aload_0
    //   36: aload_2
    //   37: aload_3
    //   38: invokevirtual Zl : (Lcom/fasterxml/Zor/Zyg;Ljava/lang/Object;)V
    //   41: goto -> 48
    //   44: invokestatic a : (Ljava/lang/Exception;)Ljava/lang/Exception;
    //   47: athrow
    //   48: aload_0
    //   49: getfield ZD : [Lcom/fasterxml/Zo/Zv;
    //   52: astore #5
    //   54: iconst_0
    //   55: istore #6
    //   57: aload #5
    //   59: arraylength
    //   60: istore #7
    //   62: aload_1
    //   63: invokevirtual ZV : ()Lcom/fasterxml/Zb/Zl;
    //   66: getstatic com/fasterxml/Zb/Zl.END_ARRAY : Lcom/fasterxml/Zb/Zl;
    //   69: if_acmpne -> 74
    //   72: aload_3
    //   73: areturn
    //   74: iload #6
    //   76: iload #7
    //   78: if_icmpne -> 93
    //   81: aload #4
    //   83: ifnull -> 157
    //   86: goto -> 93
    //   89: invokestatic a : (Ljava/lang/Exception;)Ljava/lang/Exception;
    //   92: athrow
    //   93: aload #5
    //   95: iload #6
    //   97: aaload
    //   98: astore #8
    //   100: aload #8
    //   102: ifnull -> 137
    //   105: aload #8
    //   107: aload_1
    //   108: aload_2
    //   109: aload_3
    //   110: invokevirtual ZP : (Lcom/fasterxml/Zb/Zg;Lcom/fasterxml/Zor/Zyg;Ljava/lang/Object;)V
    //   113: goto -> 149
    //   116: astore #9
    //   118: aload_0
    //   119: aload #9
    //   121: aload_3
    //   122: aload #8
    //   124: invokevirtual ZT : ()Ljava/lang/String;
    //   127: aload_2
    //   128: invokevirtual Zd : (Ljava/lang/Throwable;Ljava/lang/Object;Ljava/lang/String;Lcom/fasterxml/Zor/Zyg;)Ljava/lang/Object;
    //   131: pop
    //   132: aload #4
    //   134: ifnull -> 149
    //   137: aload_1
    //   138: invokevirtual Zc : ()Lcom/fasterxml/Zb/Zg;
    //   141: pop
    //   142: goto -> 149
    //   145: invokestatic a : (Ljava/lang/Exception;)Ljava/lang/Exception;
    //   148: athrow
    //   149: iinc #6, 1
    //   152: aload #4
    //   154: ifnull -> 62
    //   157: aload_0
    //   158: getfield Za : Z
    //   161: ifne -> 217
    //   164: aload_2
    //   165: getstatic com/fasterxml/Zor/Zyp.FAIL_ON_UNKNOWN_PROPERTIES : Lcom/fasterxml/Zor/Zyp;
    //   168: invokevirtual Zg : (Lcom/fasterxml/Zor/Zyp;)Z
    //   171: ifeq -> 217
    //   174: goto -> 181
    //   177: invokestatic a : (Ljava/lang/Exception;)Ljava/lang/Exception;
    //   180: athrow
    //   181: aload_2
    //   182: aload_0
    //   183: getstatic com/fasterxml/Zb/Zl.END_ARRAY : Lcom/fasterxml/Zb/Zl;
    //   186: sipush #21162
    //   189: sipush #12512
    //   192: invokestatic d : (II)Ljava/lang/String;
    //   195: iconst_1
    //   196: anewarray java/lang/Object
    //   199: dup
    //   200: iconst_0
    //   201: iload #7
    //   203: invokestatic valueOf : (I)Ljava/lang/Integer;
    //   206: aastore
    //   207: invokevirtual Zw : (Lcom/fasterxml/Zor/Zyo;Lcom/fasterxml/Zb/Zl;Ljava/lang/String;[Ljava/lang/Object;)V
    //   210: goto -> 217
    //   213: invokestatic a : (Ljava/lang/Exception;)Ljava/lang/Exception;
    //   216: athrow
    //   217: aload_1
    //   218: invokevirtual Zc : ()Lcom/fasterxml/Zb/Zg;
    //   221: pop
    //   222: aload_1
    //   223: invokevirtual ZV : ()Lcom/fasterxml/Zb/Zl;
    //   226: getstatic com/fasterxml/Zb/Zl.END_ARRAY : Lcom/fasterxml/Zb/Zl;
    //   229: if_acmpne -> 217
    //   232: aload_3
    //   233: areturn
    //   234: invokestatic a : (Ljava/lang/Exception;)Ljava/lang/Exception;
    //   237: athrow
    // Exception table:
    //   from	to	target	type
    //   10	24	24	java/lang/Exception
    //   28	41	44	java/lang/Exception
    //   74	86	89	java/lang/Exception
    //   105	113	116	java/lang/Exception
    //   118	142	145	java/lang/Exception
    //   157	174	177	java/lang/Exception
    //   164	210	213	java/lang/Exception
    //   217	234	234	java/lang/Exception
  }
  
  public Object ZJ(Zg paramZg, Zyg paramZyg) throws IOException {
    return ZL(paramZg, paramZyg);
  }
  
  protected Object Zc(Zg paramZg, Zyg paramZyg) throws IOException {
    // Byte code:
    //   0: invokestatic ZI : ()[Ljava/lang/String;
    //   3: astore_3
    //   4: aload_0
    //   5: getfield ZU : Z
    //   8: ifeq -> 22
    //   11: aload_0
    //   12: aload_1
    //   13: aload_2
    //   14: invokevirtual Zb : (Lcom/fasterxml/Zb/Zg;Lcom/fasterxml/Zor/Zyg;)Ljava/lang/Object;
    //   17: areturn
    //   18: invokestatic a : (Ljava/lang/Exception;)Ljava/lang/Exception;
    //   21: athrow
    //   22: aload_0
    //   23: getfield Zb : Lcom/fasterxml/Zo/Zzp;
    //   26: aload_2
    //   27: invokevirtual Zy : (Lcom/fasterxml/Zor/Zyg;)Ljava/lang/Object;
    //   30: astore #4
    //   32: aload_1
    //   33: aload #4
    //   35: invokevirtual ZZ : (Ljava/lang/Object;)V
    //   38: aload_0
    //   39: getfield Zy : [Lcom/fasterxml/Ze/Zv;
    //   42: ifnull -> 59
    //   45: aload_0
    //   46: aload_2
    //   47: aload #4
    //   49: invokevirtual Zl : (Lcom/fasterxml/Zor/Zyg;Ljava/lang/Object;)V
    //   52: goto -> 59
    //   55: invokestatic a : (Ljava/lang/Exception;)Ljava/lang/Exception;
    //   58: athrow
    //   59: aload_0
    //   60: getfield Zk : Z
    //   63: ifeq -> 77
    //   66: aload_2
    //   67: invokevirtual Zx : ()Ljava/lang/Class;
    //   70: goto -> 78
    //   73: invokestatic a : (Ljava/lang/Exception;)Ljava/lang/Exception;
    //   76: athrow
    //   77: aconst_null
    //   78: astore #5
    //   80: aload_0
    //   81: getfield ZD : [Lcom/fasterxml/Zo/Zv;
    //   84: astore #6
    //   86: iconst_0
    //   87: istore #7
    //   89: aload #6
    //   91: arraylength
    //   92: istore #8
    //   94: aload_1
    //   95: invokevirtual ZV : ()Lcom/fasterxml/Zb/Zl;
    //   98: getstatic com/fasterxml/Zb/Zl.END_ARRAY : Lcom/fasterxml/Zb/Zl;
    //   101: if_acmpne -> 111
    //   104: aload #4
    //   106: areturn
    //   107: invokestatic a : (Ljava/lang/Exception;)Ljava/lang/Exception;
    //   110: athrow
    //   111: iload #7
    //   113: iload #8
    //   115: if_icmpne -> 129
    //   118: aload_3
    //   119: ifnull -> 215
    //   122: goto -> 129
    //   125: invokestatic a : (Ljava/lang/Exception;)Ljava/lang/Exception;
    //   128: athrow
    //   129: aload #6
    //   131: iload #7
    //   133: aaload
    //   134: astore #9
    //   136: iinc #7, 1
    //   139: aload #9
    //   141: ifnull -> 206
    //   144: aload #5
    //   146: ifnull -> 173
    //   149: goto -> 156
    //   152: invokestatic a : (Ljava/lang/Exception;)Ljava/lang/Exception;
    //   155: athrow
    //   156: aload #9
    //   158: aload #5
    //   160: invokevirtual Zj : (Ljava/lang/Class;)Z
    //   163: ifeq -> 206
    //   166: goto -> 173
    //   169: invokestatic a : (Ljava/lang/Exception;)Ljava/lang/Exception;
    //   172: athrow
    //   173: aload #9
    //   175: aload_1
    //   176: aload_2
    //   177: aload #4
    //   179: invokevirtual ZP : (Lcom/fasterxml/Zb/Zg;Lcom/fasterxml/Zor/Zyg;Ljava/lang/Object;)V
    //   182: goto -> 94
    //   185: astore #10
    //   187: aload_0
    //   188: aload #10
    //   190: aload #4
    //   192: aload #9
    //   194: invokevirtual ZT : ()Ljava/lang/String;
    //   197: aload_2
    //   198: invokevirtual Zd : (Ljava/lang/Throwable;Ljava/lang/Object;Ljava/lang/String;Lcom/fasterxml/Zor/Zyg;)Ljava/lang/Object;
    //   201: pop
    //   202: aload_3
    //   203: ifnull -> 94
    //   206: aload_1
    //   207: invokevirtual Zc : ()Lcom/fasterxml/Zb/Zg;
    //   210: pop
    //   211: aload_3
    //   212: ifnull -> 94
    //   215: aload_0
    //   216: getfield Za : Z
    //   219: ifne -> 258
    //   222: aload_2
    //   223: aload_0
    //   224: getstatic com/fasterxml/Zb/Zl.END_ARRAY : Lcom/fasterxml/Zb/Zl;
    //   227: sipush #21161
    //   230: sipush #4894
    //   233: invokestatic d : (II)Ljava/lang/String;
    //   236: iconst_1
    //   237: anewarray java/lang/Object
    //   240: dup
    //   241: iconst_0
    //   242: iload #8
    //   244: invokestatic valueOf : (I)Ljava/lang/Integer;
    //   247: aastore
    //   248: invokevirtual Zw : (Lcom/fasterxml/Zor/Zyo;Lcom/fasterxml/Zb/Zl;Ljava/lang/String;[Ljava/lang/Object;)V
    //   251: goto -> 258
    //   254: invokestatic a : (Ljava/lang/Exception;)Ljava/lang/Exception;
    //   257: athrow
    //   258: aload_1
    //   259: invokevirtual Zc : ()Lcom/fasterxml/Zb/Zg;
    //   262: pop
    //   263: aload_1
    //   264: invokevirtual ZV : ()Lcom/fasterxml/Zb/Zl;
    //   267: getstatic com/fasterxml/Zb/Zl.END_ARRAY : Lcom/fasterxml/Zb/Zl;
    //   270: if_acmpne -> 258
    //   273: aload #4
    //   275: areturn
    //   276: invokestatic a : (Ljava/lang/Exception;)Ljava/lang/Exception;
    //   279: athrow
    // Exception table:
    //   from	to	target	type
    //   4	18	18	java/lang/Exception
    //   32	52	55	java/lang/Exception
    //   59	73	73	java/lang/Exception
    //   94	107	107	java/lang/Exception
    //   111	122	125	java/lang/Exception
    //   136	149	152	java/lang/Exception
    //   144	166	169	java/lang/Exception
    //   173	182	185	java/lang/Exception
    //   215	251	254	java/lang/Exception
    //   258	276	276	java/lang/Exception
  }
  
  protected final Object ZZ(Zg paramZg, Zyg paramZyg) throws IOException {
    // Byte code:
    //   0: aload_0
    //   1: getfield ZT : Lcom/fasterxml/Ze/Zc;
    //   4: astore #4
    //   6: aload #4
    //   8: aload_1
    //   9: aload_2
    //   10: aload_0
    //   11: getfield ZZ : Lcom/fasterxml/Ze/Zz;
    //   14: invokevirtual Zn : (Lcom/fasterxml/Zb/Zg;Lcom/fasterxml/Zor/Zyg;Lcom/fasterxml/Ze/Zz;)Lcom/fasterxml/Ze/Zok;
    //   17: astore #5
    //   19: invokestatic ZI : ()[Ljava/lang/String;
    //   22: aload_0
    //   23: getfield ZD : [Lcom/fasterxml/Zo/Zv;
    //   26: astore #6
    //   28: astore_3
    //   29: aload #6
    //   31: arraylength
    //   32: istore #7
    //   34: iconst_0
    //   35: istore #8
    //   37: aconst_null
    //   38: astore #9
    //   40: aload_0
    //   41: getfield Zk : Z
    //   44: ifeq -> 58
    //   47: aload_2
    //   48: invokevirtual Zx : ()Ljava/lang/Class;
    //   51: goto -> 59
    //   54: invokestatic a : (Ljava/lang/Exception;)Ljava/lang/Exception;
    //   57: athrow
    //   58: aconst_null
    //   59: astore #10
    //   61: aload_1
    //   62: invokevirtual ZV : ()Lcom/fasterxml/Zb/Zl;
    //   65: getstatic com/fasterxml/Zb/Zl.END_ARRAY : Lcom/fasterxml/Zb/Zl;
    //   68: if_acmpeq -> 435
    //   71: iload #8
    //   73: iload #7
    //   75: if_icmpge -> 90
    //   78: aload #6
    //   80: iload #8
    //   82: aaload
    //   83: goto -> 91
    //   86: invokestatic a : (Ljava/lang/Exception;)Ljava/lang/Exception;
    //   89: athrow
    //   90: aconst_null
    //   91: astore #11
    //   93: aload #11
    //   95: ifnonnull -> 114
    //   98: aload_1
    //   99: invokevirtual Zc : ()Lcom/fasterxml/Zb/Zg;
    //   102: pop
    //   103: aload_3
    //   104: ifnull -> 428
    //   107: goto -> 114
    //   110: invokestatic a : (Ljava/lang/Exception;)Ljava/lang/Exception;
    //   113: athrow
    //   114: aload #10
    //   116: ifnull -> 159
    //   119: goto -> 126
    //   122: invokestatic a : (Ljava/lang/Exception;)Ljava/lang/Exception;
    //   125: athrow
    //   126: aload #11
    //   128: aload #10
    //   130: invokevirtual Zj : (Ljava/lang/Class;)Z
    //   133: ifne -> 159
    //   136: goto -> 143
    //   139: invokestatic a : (Ljava/lang/Exception;)Ljava/lang/Exception;
    //   142: athrow
    //   143: aload_1
    //   144: invokevirtual Zc : ()Lcom/fasterxml/Zb/Zg;
    //   147: pop
    //   148: aload_3
    //   149: ifnull -> 428
    //   152: goto -> 159
    //   155: invokestatic a : (Ljava/lang/Exception;)Ljava/lang/Exception;
    //   158: athrow
    //   159: aload #9
    //   161: ifnull -> 204
    //   164: goto -> 171
    //   167: invokestatic a : (Ljava/lang/Exception;)Ljava/lang/Exception;
    //   170: athrow
    //   171: aload #11
    //   173: aload_1
    //   174: aload_2
    //   175: aload #9
    //   177: invokevirtual ZP : (Lcom/fasterxml/Zb/Zg;Lcom/fasterxml/Zor/Zyg;Ljava/lang/Object;)V
    //   180: goto -> 428
    //   183: astore #12
    //   185: aload_0
    //   186: aload #12
    //   188: aload #9
    //   190: aload #11
    //   192: invokevirtual ZT : ()Ljava/lang/String;
    //   195: aload_2
    //   196: invokevirtual Zd : (Ljava/lang/Throwable;Ljava/lang/Object;Ljava/lang/String;Lcom/fasterxml/Zor/Zyg;)Ljava/lang/Object;
    //   199: pop
    //   200: aload_3
    //   201: ifnull -> 428
    //   204: aload #11
    //   206: invokevirtual ZT : ()Ljava/lang/String;
    //   209: astore #12
    //   211: aload #4
    //   213: aload #12
    //   215: invokevirtual ZO : (Ljava/lang/String;)Lcom/fasterxml/Zo/Zv;
    //   218: astore #13
    //   220: aload #5
    //   222: aload #12
    //   224: invokevirtual Zw : (Ljava/lang/String;)Z
    //   227: ifeq -> 253
    //   230: aload #13
    //   232: ifnonnull -> 253
    //   235: goto -> 242
    //   238: invokestatic a : (Ljava/lang/Exception;)Ljava/lang/Exception;
    //   241: athrow
    //   242: aload_3
    //   243: ifnull -> 428
    //   246: goto -> 253
    //   249: invokestatic a : (Ljava/lang/Exception;)Ljava/lang/Exception;
    //   252: athrow
    //   253: aload #13
    //   255: ifnull -> 407
    //   258: goto -> 265
    //   261: invokestatic a : (Ljava/lang/Exception;)Ljava/lang/Exception;
    //   264: athrow
    //   265: aload #5
    //   267: aload #13
    //   269: aload #13
    //   271: aload_1
    //   272: aload_2
    //   273: invokevirtual Zt : (Lcom/fasterxml/Zb/Zg;Lcom/fasterxml/Zor/Zyg;)Ljava/lang/Object;
    //   276: invokevirtual Zr : (Lcom/fasterxml/Zo/Zv;Ljava/lang/Object;)Z
    //   279: ifeq -> 428
    //   282: goto -> 289
    //   285: invokestatic a : (Ljava/lang/Exception;)Ljava/lang/Exception;
    //   288: athrow
    //   289: aload #4
    //   291: aload_2
    //   292: aload #5
    //   294: invokevirtual ZP : (Lcom/fasterxml/Zor/Zyg;Lcom/fasterxml/Ze/Zok;)Ljava/lang/Object;
    //   297: astore #9
    //   299: goto -> 325
    //   302: astore #14
    //   304: aload_0
    //   305: aload #14
    //   307: aload_0
    //   308: getfield ZF : Lcom/fasterxml/Zor/Zk;
    //   311: invokevirtual Zf : ()Ljava/lang/Class;
    //   314: aload #12
    //   316: aload_2
    //   317: invokevirtual Zd : (Ljava/lang/Throwable;Ljava/lang/Object;Ljava/lang/String;Lcom/fasterxml/Zor/Zyg;)Ljava/lang/Object;
    //   320: pop
    //   321: aload_3
    //   322: ifnull -> 428
    //   325: aload_1
    //   326: aload #9
    //   328: invokevirtual ZZ : (Ljava/lang/Object;)V
    //   331: aload #9
    //   333: invokevirtual getClass : ()Ljava/lang/Class;
    //   336: aload_0
    //   337: getfield ZF : Lcom/fasterxml/Zor/Zk;
    //   340: invokevirtual Zf : ()Ljava/lang/Class;
    //   343: if_acmpeq -> 428
    //   346: goto -> 353
    //   349: invokestatic a : (Ljava/lang/Exception;)Ljava/lang/Exception;
    //   352: athrow
    //   353: aload_2
    //   354: aload_0
    //   355: getfield ZF : Lcom/fasterxml/Zor/Zk;
    //   358: sipush #21163
    //   361: sipush #19335
    //   364: invokestatic d : (II)Ljava/lang/String;
    //   367: iconst_2
    //   368: anewarray java/lang/Object
    //   371: dup
    //   372: iconst_0
    //   373: aload_0
    //   374: getfield ZF : Lcom/fasterxml/Zor/Zk;
    //   377: invokestatic ZN : (Lcom/fasterxml/Zor/Zk;)Ljava/lang/String;
    //   380: aastore
    //   381: dup
    //   382: iconst_1
    //   383: aload #9
    //   385: invokestatic Zy : (Ljava/lang/Object;)Ljava/lang/String;
    //   388: aastore
    //   389: invokestatic format : (Ljava/lang/String;[Ljava/lang/Object;)Ljava/lang/String;
    //   392: invokevirtual Zm : (Lcom/fasterxml/Zor/Zk;Ljava/lang/String;)Ljava/lang/Object;
    //   395: pop
    //   396: aload_3
    //   397: ifnull -> 428
    //   400: goto -> 407
    //   403: invokestatic a : (Ljava/lang/Exception;)Ljava/lang/Exception;
    //   406: athrow
    //   407: aload #5
    //   409: aload #11
    //   411: aload #11
    //   413: aload_1
    //   414: aload_2
    //   415: invokevirtual Zt : (Lcom/fasterxml/Zb/Zg;Lcom/fasterxml/Zor/Zyg;)Ljava/lang/Object;
    //   418: invokevirtual ZR : (Lcom/fasterxml/Zo/Zv;Ljava/lang/Object;)V
    //   421: goto -> 428
    //   424: invokestatic a : (Ljava/lang/Exception;)Ljava/lang/Exception;
    //   427: athrow
    //   428: iinc #8, 1
    //   431: aload_3
    //   432: ifnull -> 61
    //   435: aload #9
    //   437: ifnonnull -> 463
    //   440: aload #4
    //   442: aload_2
    //   443: aload #5
    //   445: invokevirtual ZP : (Lcom/fasterxml/Zor/Zyg;Lcom/fasterxml/Ze/Zok;)Ljava/lang/Object;
    //   448: astore #9
    //   450: goto -> 463
    //   453: astore #11
    //   455: aload_0
    //   456: aload #11
    //   458: aload_2
    //   459: invokevirtual ZR : (Ljava/lang/Throwable;Lcom/fasterxml/Zor/Zyg;)Ljava/lang/Object;
    //   462: areturn
    //   463: aload #9
    //   465: areturn
    // Exception table:
    //   from	to	target	type
    //   40	54	54	java/lang/Exception
    //   71	86	86	java/lang/Exception
    //   93	107	110	java/lang/Exception
    //   98	119	122	java/lang/Exception
    //   114	136	139	java/lang/Exception
    //   126	152	155	java/lang/Exception
    //   143	164	167	java/lang/Exception
    //   171	180	183	java/lang/Exception
    //   220	235	238	java/lang/Exception
    //   230	246	249	java/lang/Exception
    //   242	258	261	java/lang/Exception
    //   253	282	285	java/lang/Exception
    //   289	299	302	java/lang/Exception
    //   304	346	349	java/lang/Exception
    //   325	400	403	java/lang/Exception
    //   353	421	424	java/lang/Exception
    //   440	450	453	java/lang/Exception
  }
  
  protected Object ZL(Zg paramZg, Zyg paramZyg) throws IOException {
    String str = d(21160, -30632);
    return paramZyg.Za(Zq(paramZyg), paramZg.Zh(), paramZg, str, new Object[] { Zx.ZN(this.ZF), paramZg.Zh() });
  }
  
  private static Exception a(Exception paramException) {
    return paramException;
  }
  
  static {
    // Byte code:
    //   0: iconst_4
    //   1: anewarray java/lang/String
    //   4: astore #5
    //   6: iconst_0
    //   7: istore_3
    //   8: ldc 'Â­Â…ÂÃ¥ÂƒÂ‰Â·.lÂˆhuÂ§Ã„Â·Â®ÃÂšÂ¼ÃœÃ(Â?Ã’Â¶Â‚;V|Â²?-eÃšÂ¬Ã½Ã˜Â•>LFÃ²Â™Â¹ÃŸÃ¯Â€Ã Â€Â³Ã†Ã¬@CW3Ã€Â‚pÃ¢Ã™Â‡Â‚Ã®Â§ÂÃ—Ã´pÃÂ£Â’Â«Ã’G/-ÂŠÃ·Â«Ã„YXÂ¬Â©Ã¹Ã½\)Ã…IÂ–LsÃ¿_DÃ±Ã†Â»ÂšÃ½Â›ÂNyÃ®Ã˜2-Ã„Ã±Ã³iÃ—Â¹ÃƒÂ¢g6z ÂŠ4Ã²Ã°BÂŠÃ0RÂƒÃ±jjÂŽÃ–Â¤ÂKRÂ£Ã·Ã‡Ã„Â—5Ã‡Â‘Â†~Â–Â‡ÂÂ±Â—^aeÂ°>ÂŠDCÂ¦Â¯bFÂ°uMTu]EÂ”ÂVJÃ‰'
    //   10: dup
    //   11: astore_2
    //   12: invokevirtual length : ()I
    //   15: istore #4
    //   17: bipush #70
    //   19: istore_1
    //   20: iconst_m1
    //   21: istore_0
    //   22: bipush #6
    //   24: iinc #0, 1
    //   27: aload_2
    //   28: iload_0
    //   29: dup
    //   30: iload_1
    //   31: iadd
    //   32: invokevirtual substring : (II)Ljava/lang/String;
    //   35: iconst_m1
    //   36: goto -> 141
    //   39: aload #5
    //   41: swap
    //   42: iload_3
    //   43: iinc #3, 1
    //   46: swap
    //   47: aastore
    //   48: iload_0
    //   49: iload_1
    //   50: iadd
    //   51: dup
    //   52: istore_0
    //   53: iload #4
    //   55: if_icmpge -> 67
    //   58: aload_2
    //   59: iload_0
    //   60: invokevirtual charAt : (I)C
    //   63: istore_1
    //   64: goto -> 22
    //   67: ldc '\\fÃ´Â¶ÂšÃ«Â¡QÃ±ÂÂž75@`Ãž7&4Li'Â¬8mÂ¬Â„8Ã¨Ã¾Ãž"ÂÂ…N;Y\Â®{-Ã“KÃªÃ›Ã¶Ã®_Âµ%jÂ–Â¿\\bÂ¹Ã£Ã6Ã½2)Â·Â©A Â³Ã¦Ã’Â‡Â©ÂŒVÃ¯Â·$Â¶ÃÃ—EzÃ³Ã¨Ã Ã—|Â™tKÃÃˆÃ›Ã§/Â­YOTÃ¤Â¥; Â€Ã„F_ÂªÂ»Â…YHf2vÂ¤Ã»\\tcÃ³~EÂÃ«Ã¢Â©QSÃXpXLÂ³Â Ã–ÂÂ¤SÂ”Â¢Â‘Ã•ÂŠÃ›Â†Ã´5Â«Ã´(Â£Â´ÃÂ¿$c$oÃ¡Ã«ÂŸ!UÂ‰2Â­VeÃ›'
    //   69: dup
    //   70: astore_2
    //   71: invokevirtual length : ()I
    //   74: istore #4
    //   76: bipush #110
    //   78: istore_1
    //   79: iconst_m1
    //   80: istore_0
    //   81: bipush #29
    //   83: iinc #0, 1
    //   86: aload_2
    //   87: iload_0
    //   88: dup
    //   89: iload_1
    //   90: iadd
    //   91: invokevirtual substring : (II)Ljava/lang/String;
    //   94: iconst_0
    //   95: goto -> 141
    //   98: aload #5
    //   100: swap
    //   101: iload_3
    //   102: iinc #3, 1
    //   105: swap
    //   106: aastore
    //   107: iload_0
    //   108: iload_1
    //   109: iadd
    //   110: dup
    //   111: istore_0
    //   112: iload #4
    //   114: if_icmpge -> 126
    //   117: aload_2
    //   118: iload_0
    //   119: invokevirtual charAt : (I)C
    //   122: istore_1
    //   123: goto -> 81
    //   126: aload #5
    //   128: putstatic com/fasterxml/Ze/Zog.g : [Ljava/lang/String;
    //   131: iconst_4
    //   132: anewarray java/lang/String
    //   135: putstatic com/fasterxml/Ze/Zog.h : [Ljava/lang/String;
    //   138: goto -> 300
    //   141: dup_x2
    //   142: pop
    //   143: invokevirtual toCharArray : ()[C
    //   146: dup_x1
    //   147: arraylength
    //   148: dup_x2
    //   149: pop
    //   150: iconst_0
    //   151: istore #6
    //   153: dup2_x1
    //   154: pop2
    //   155: dup_x2
    //   156: iconst_1
    //   157: if_icmpgt -> 260
    //   160: dup2
    //   161: swap
    //   162: iload #6
    //   164: dup2_x1
    //   165: caload
    //   166: swap
    //   167: iload #6
    //   169: bipush #7
    //   171: irem
    //   172: tableswitch default -> 242, 0 -> 212, 1 -> 217, 2 -> 222, 3 -> 227, 4 -> 232, 5 -> 237
    //   212: bipush #112
    //   214: goto -> 244
    //   217: bipush #110
    //   219: goto -> 244
    //   222: bipush #122
    //   224: goto -> 244
    //   227: bipush #120
    //   229: goto -> 244
    //   232: bipush #102
    //   234: goto -> 244
    //   237: bipush #91
    //   239: goto -> 244
    //   242: bipush #34
    //   244: ixor
    //   245: ixor
    //   246: i2c
    //   247: castore
    //   248: iinc #6, 1
    //   251: dup
    //   252: ifne -> 260
    //   255: dup2
    //   256: dup_x1
    //   257: goto -> 164
    //   260: dup2_x1
    //   261: pop2
    //   262: dup_x2
    //   263: iload #6
    //   265: if_icmpgt -> 160
    //   268: pop
    //   269: new java/lang/String
    //   272: dup_x1
    //   273: swap
    //   274: invokespecial <init> : ([C)V
    //   277: invokevirtual intern : ()Ljava/lang/String;
    //   280: swap
    //   281: pop
    //   282: swap
    //   283: tableswitch default -> 39, 0 -> 98
    //   300: return
  }
  
  private static String d(int paramInt1, int paramInt2) {
    int i = (paramInt1 ^ 0x52A9) & 0xFFFF;
    if (h[i] == null) {
      char[] arrayOfChar = g[i].toCharArray();
      switch (arrayOfChar[0] & 0xFF) {
        case 0:
        
        case 1:
        
        case 2:
        
        case 3:
        
        case 4:
        
        case 5:
        
        case 6:
        
        case 7:
        
        case 8:
        
        case 9:
        
        case 10:
        
        case 11:
        
        case 12:
        
        case 13:
        
        case 14:
        
        case 15:
        
        case 16:
        
        case 17:
        
        case 18:
        
        case 19:
        
        case 20:
        
        case 21:
        
        case 22:
        
        case 23:
        
        case 24:
        
        case 25:
        
        case 26:
        
        case 27:
        
        case 28:
        
        case 29:
        
        case 30:
        
        case 31:
        
        case 32:
        
        case 33:
        
        case 34:
        
        case 35:
        
        case 36:
        
        case 37:
        
        case 38:
        
        case 39:
        
        case 40:
        
        case 41:
        
        case 42:
        
        case 43:
        
        case 44:
        
        case 45:
        
        case 46:
        
        case 47:
        
        case 48:
        
        case 49:
        
        case 50:
        
        case 51:
        
        case 52:
        
        case 53:
        
        case 54:
        
        case 55:
        
        case 56:
        
        case 57:
        
        case 58:
        
        case 59:
        
        case 60:
        
        case 61:
        
        case 62:
        
        case 63:
        
        case 64:
        
        case 65:
        
        case 66:
        
        case 67:
        
        case 68:
        
        case 69:
        
        case 70:
        
        case 71:
        
        case 72:
        
        case 73:
        
        case 74:
        
        case 75:
        
        case 76:
        
        case 77:
        
        case 78:
        
        case 79:
        
        case 80:
        
        case 81:
        
        case 82:
        
        case 83:
        
        case 84:
        
        case 85:
        
        case 86:
        
        case 87:
        
        case 88:
        
        case 89:
        
        case 90:
        
        case 91:
        
        case 92:
        
        case 93:
        
        case 94:
        
        case 95:
        
        case 96:
        
        case 97:
        
        case 98:
        
        case 99:
        
        case 100:
        
        case 101:
        
        case 102:
        
        case 103:
        
        case 104:
        
        case 105:
        
        case 106:
        
        case 107:
        
        case 108:
        
        case 109:
        
        case 110:
        
        case 111:
        
        case 112:
        
        case 113:
        
        case 114:
        
        case 115:
        
        case 116:
        
        case 117:
        
        case 118:
        
        case 119:
        
        case 120:
        
        case 121:
        
        case 122:
        
        case 123:
        
        case 124:
        
        case 125:
        
        case 126:
        
        case 127:
        
        case 128:
        
        case 129:
        
        case 130:
        
        case 131:
        
        case 132:
        
        case 133:
        
        case 134:
        
        case 135:
        
        case 136:
        
        case 137:
        
        case 138:
        
        case 139:
        
        case 140:
        
        case 141:
        
        case 142:
        
        case 143:
        
        case 144:
        
        case 145:
        
        case 146:
        
        case 147:
        
        case 148:
        
        case 149:
        
        case 150:
        
        case 151:
        
        case 152:
        
        case 153:
        
        case 154:
        
        case 155:
        
        case 156:
        
        case 157:
        
        case 158:
        
        case 159:
        
        case 160:
        
        case 161:
        
        case 162:
        
        case 163:
        
        case 164:
        
        case 165:
        
        case 166:
        
        case 167:
        
        case 168:
        
        case 169:
        
        case 170:
        
        case 171:
        
        case 172:
        
        case 173:
        
        case 174:
        
        case 175:
        
        case 176:
        
        case 177:
        
        case 178:
        
        case 179:
        
        case 180:
        
        case 181:
        
        case 182:
        
        case 183:
        
        case 184:
        
        case 185:
        
        case 186:
        
        case 187:
        
        case 188:
        
        case 189:
        
        case 190:
        
        case 191:
        
        case 192:
        
        case 193:
        
        case 194:
        
        case 195:
        
        case 196:
        
        case 197:
        
        case 198:
        
        case 199:
        
        case 200:
        
        case 201:
        
        case 202:
        
        case 203:
        
        case 204:
        
        case 205:
        
        case 206:
        
        case 207:
        
        case 208:
        
        case 209:
        
        case 210:
        
        case 211:
        
        case 212:
        
        case 213:
        
        case 214:
        
        case 215:
        
        case 216:
        
        case 217:
        
        case 218:
        
        case 219:
        
        case 220:
        
        case 221:
        
        case 222:
        
        case 223:
        
        case 224:
        
        case 225:
        
        case 226:
        
        case 227:
        
        case 228:
        
        case 229:
        
        case 230:
        
        case 231:
        
        case 232:
        
        case 233:
        
        case 234:
        
        case 235:
        
        case 236:
        
        case 237:
        
        case 238:
        
        case 239:
        
        case 240:
        
        case 241:
        
        case 242:
        
        case 243:
        
        case 244:
        
        case 245:
        
        case 246:
        
        case 247:
        
        case 248:
        
        case 249:
        
        case 250:
        
        case 251:
        
        case 252:
        
        case 253:
        
        case 254:
        
        default:
          break;
      } 
      char c = 'Â³';
      int j = (paramInt2 & 0xFF) - c;
      if (j < 0)
        j += 256; 
      int k = ((paramInt2 & 0xFFFF) >>> 8) - c;
      if (k < 0)
        k += 256; 
      for (byte b = 0; b < arrayOfChar.length; b++) {
        int m = b % 2;
        if (m == 0) {
          arrayOfChar[b] = (char)(arrayOfChar[b] ^ j);
          j = ((j >>> 3 | j << 5) ^ arrayOfChar[b]) & 0xFF;
        } else {
          arrayOfChar[b] = (char)(arrayOfChar[b] ^ k);
          k = ((k >>> 3 | k << 5) ^ arrayOfChar[b]) & 0xFF;
        } 
      } 
      h[i] = (new String(arrayOfChar)).intern();
    } 
    return h[i];
  }
}


/* Location:              C:\Program Files\BurpSuitePro\burpsuite_pro.jar!\com\fasterxml\Ze\Zog.class
 * Java compiler version: 8 (52.0)
 * JD-Core Version:       1.1.3
 */