package net.portswigger.swagger.v1.models;

import com.fasterxml.Zv8;
import com.fasterxml.Zva;
import com.fasterxml.Zyi;
import com.fasterxml.Zyx;
import java.util.ArrayList;
import java.util.LinkedHashMap;
import java.util.List;
import java.util.Map;
import net.portswigger.swagger.v1.models.parameters.Parameter;

@Zva({"get", "head", "post", "put", "delete", "options", "patch"})
public class Path {
  private Map<String, Object> vendorExtensions = new LinkedHashMap<>();
  
  private Operation get;
  
  private Operation put;
  
  private Operation post;
  
  private Operation head;
  
  private Operation delete;
  
  private Operation patch;
  
  private Operation options;
  
  private List<Parameter> parameters;
  
  private static final String[] a;
  
  private static final String[] b;
  
  public Path set(String paramString, Operation paramOperation) {
    return a(-11668, 16979).equals(paramString) ? get(paramOperation) : (a(-11671, 15631).equals(paramString) ? put(paramOperation) : (a(-11665, -10076).equals(paramString) ? head(paramOperation) : (a(-11669, 25590).equals(paramString) ? post(paramOperation) : (a(-11672, -23449).equals(paramString) ? delete(paramOperation) : (a(-11667, 32087).equals(paramString) ? patch(paramOperation) : (a(-11666, -11683).equals(paramString) ? options(paramOperation) : null))))));
  }
  
  public Path get(Operation paramOperation) {
    this.get = paramOperation;
    return this;
  }
  
  public Path head(Operation paramOperation) {
    this.head = paramOperation;
    return this;
  }
  
  public Path put(Operation paramOperation) {
    this.put = paramOperation;
    return this;
  }
  
  public Path post(Operation paramOperation) {
    this.post = paramOperation;
    return this;
  }
  
  public Path delete(Operation paramOperation) {
    this.delete = paramOperation;
    return this;
  }
  
  public Path patch(Operation paramOperation) {
    this.patch = paramOperation;
    return this;
  }
  
  public Path options(Operation paramOperation) {
    this.options = paramOperation;
    return this;
  }
  
  public Operation getGet() {
    return this.get;
  }
  
  public void setGet(Operation paramOperation) {
    this.get = paramOperation;
  }
  
  public Operation getHead() {
    return this.head;
  }
  
  public void setHead(Operation paramOperation) {
    this.head = paramOperation;
  }
  
  public Operation getPut() {
    return this.put;
  }
  
  public void setPut(Operation paramOperation) {
    this.put = paramOperation;
  }
  
  public Operation getPost() {
    return this.post;
  }
  
  public void setPost(Operation paramOperation) {
    this.post = paramOperation;
  }
  
  public Operation getDelete() {
    return this.delete;
  }
  
  public void setDelete(Operation paramOperation) {
    this.delete = paramOperation;
  }
  
  public Operation getPatch() {
    return this.patch;
  }
  
  public void setPatch(Operation paramOperation) {
    this.patch = paramOperation;
  }
  
  public Operation getOptions() {
    return this.options;
  }
  
  public void setOptions(Operation paramOperation) {
    this.options = paramOperation;
  }
  
  @Zyx
  public List<Operation> getOperations() {
    ArrayList<Operation> arrayList = new ArrayList();
    if (this.get != null)
      arrayList.add(this.get); 
    if (this.put != null)
      arrayList.add(this.put); 
    if (this.head != null)
      arrayList.add(this.head); 
    if (this.post != null)
      arrayList.add(this.post); 
    if (this.delete != null)
      arrayList.add(this.delete); 
    if (this.patch != null)
      arrayList.add(this.patch); 
    if (this.options != null)
      arrayList.add(this.options); 
    return arrayList;
  }
  
  @Zyx
  public Map<HttpMethod, Operation> getOperationMap() {
    LinkedHashMap<Object, Object> linkedHashMap = new LinkedHashMap<>();
    if (this.get != null)
      linkedHashMap.put(HttpMethod.GET, this.get); 
    if (this.put != null)
      linkedHashMap.put(HttpMethod.PUT, this.put); 
    if (this.post != null)
      linkedHashMap.put(HttpMethod.POST, this.post); 
    if (this.delete != null)
      linkedHashMap.put(HttpMethod.DELETE, this.delete); 
    if (this.patch != null)
      linkedHashMap.put(HttpMethod.PATCH, this.patch); 
    if (this.head != null)
      linkedHashMap.put(HttpMethod.HEAD, this.head); 
    if (this.options != null)
      linkedHashMap.put(HttpMethod.OPTIONS, this.options); 
    return (Map)linkedHashMap;
  }
  
  public List<Parameter> getParameters() {
    return this.parameters;
  }
  
  public void setParameters(List<Parameter> paramList) {
    this.parameters = paramList;
  }
  
  public void addParameter(Parameter paramParameter) {
    if (this.parameters == null)
      this.parameters = new ArrayList<>(); 
    this.parameters.add(paramParameter);
  }
  
  @Zyx
  public boolean isEmpty() {
    return (this.get == null && this.put == null && this.head == null && this.post == null && this.delete == null && this.patch == null && this.options == null);
  }
  
  @Zyi
  public Map<String, Object> getVendorExtensions() {
    return this.vendorExtensions;
  }
  
  @Zv8
  public void setVendorExtension(String paramString, Object paramObject) {
    if (paramString.startsWith(a(-11670, -12882)))
      this.vendorExtensions.put(paramString, paramObject); 
  }
  
  public void setVendorExtensions(Map<String, Object> paramMap) {
    this.vendorExtensions = paramMap;
  }
  
  public int hashCode() {
    byte b = 31;
    null = 1;
    null = 31 * null + ((this.delete == null) ? 0 : this.delete.hashCode());
    null = 31 * null + ((this.get == null) ? 0 : this.get.hashCode());
    null = 31 * null + ((this.head == null) ? 0 : this.head.hashCode());
    null = 31 * null + ((this.options == null) ? 0 : this.options.hashCode());
    null = 31 * null + ((this.parameters == null) ? 0 : this.parameters.hashCode());
    null = 31 * null + ((this.patch == null) ? 0 : this.patch.hashCode());
    null = 31 * null + ((this.post == null) ? 0 : this.post.hashCode());
    null = 31 * null + ((this.put == null) ? 0 : this.put.hashCode());
    return 31 * null + ((this.vendorExtensions == null) ? 0 : this.vendorExtensions.hashCode());
  }
  
  public boolean equals(Object paramObject) {
    if (this == paramObject)
      return true; 
    if (paramObject == null)
      return false; 
    if (getClass() != paramObject.getClass())
      return false; 
    Path path = (Path)paramObject;
    if (this.delete == null) {
      if (path.delete != null)
        return false; 
    } else if (!this.delete.equals(path.delete)) {
      return false;
    } 
    if (this.get == null) {
      if (path.get != null)
        return false; 
    } else if (!this.get.equals(path.get)) {
      return false;
    } 
    if (this.head == null) {
      if (path.head != null)
        return false; 
    } else if (!this.head.equals(path.head)) {
      return false;
    } 
    if (this.options == null) {
      if (path.options != null)
        return false; 
    } else if (!this.options.equals(path.options)) {
      return false;
    } 
    if (this.parameters == null) {
      if (path.parameters != null)
        return false; 
    } else if (!this.parameters.equals(path.parameters)) {
      return false;
    } 
    if (this.patch == null) {
      if (path.patch != null)
        return false; 
    } else if (!this.patch.equals(path.patch)) {
      return false;
    } 
    if (this.post == null) {
      if (path.post != null)
        return false; 
    } else if (!this.post.equals(path.post)) {
      return false;
    } 
    if (this.put == null) {
      if (path.put != null)
        return false; 
    } else if (!this.put.equals(path.put)) {
      return false;
    } 
    if (this.vendorExtensions == null) {
      if (path.vendorExtensions != null)
        return false; 
    } else if (!this.vendorExtensions.equals(path.vendorExtensions)) {
      return false;
    } 
    return true;
  }
  
  static {
    // Byte code:
    //   0: bipush #8
    //   2: anewarray java/lang/String
    //   5: astore #5
    //   7: iconst_0
    //   8: istore_3
    //   9: ldc ''ISÂ¢;mÃ‰Â¡Ã¿Ã«Ã–Ã.sRmLHÃ‡ÂƒÂº'
    //   11: dup
    //   12: astore_2
    //   13: invokevirtual length : ()I
    //   16: istore #4
    //   18: iconst_3
    //   19: istore_1
    //   20: iconst_m1
    //   21: istore_0
    //   22: bipush #36
    //   24: iinc #0, 1
    //   27: aload_2
    //   28: iload_0
    //   29: dup
    //   30: iload_1
    //   31: iadd
    //   32: invokevirtual substring : (II)Ljava/lang/String;
    //   35: iconst_m1
    //   36: goto -> 141
    //   39: aload #5
    //   41: swap
    //   42: iload_3
    //   43: iinc #3, 1
    //   46: swap
    //   47: aastore
    //   48: iload_0
    //   49: iload_1
    //   50: iadd
    //   51: dup
    //   52: istore_0
    //   53: iload #4
    //   55: if_icmpge -> 67
    //   58: aload_2
    //   59: iload_0
    //   60: invokevirtual charAt : (I)C
    //   63: istore_1
    //   64: goto -> 22
    //   67: ldc 'Ã½Â™ÂÃ•*vÃ—E='
    //   69: dup
    //   70: astore_2
    //   71: invokevirtual length : ()I
    //   74: istore #4
    //   76: iconst_4
    //   77: istore_1
    //   78: iconst_m1
    //   79: istore_0
    //   80: bipush #106
    //   82: iinc #0, 1
    //   85: aload_2
    //   86: iload_0
    //   87: dup
    //   88: iload_1
    //   89: iadd
    //   90: invokevirtual substring : (II)Ljava/lang/String;
    //   93: iconst_0
    //   94: goto -> 141
    //   97: aload #5
    //   99: swap
    //   100: iload_3
    //   101: iinc #3, 1
    //   104: swap
    //   105: aastore
    //   106: iload_0
    //   107: iload_1
    //   108: iadd
    //   109: dup
    //   110: istore_0
    //   111: iload #4
    //   113: if_icmpge -> 125
    //   116: aload_2
    //   117: iload_0
    //   118: invokevirtual charAt : (I)C
    //   121: istore_1
    //   122: goto -> 80
    //   125: aload #5
    //   127: putstatic net/portswigger/swagger/v1/models/Path.a : [Ljava/lang/String;
    //   130: bipush #8
    //   132: anewarray java/lang/String
    //   135: putstatic net/portswigger/swagger/v1/models/Path.b : [Ljava/lang/String;
    //   138: goto -> 300
    //   141: dup_x2
    //   142: pop
    //   143: invokevirtual toCharArray : ()[C
    //   146: dup_x1
    //   147: arraylength
    //   148: dup_x2
    //   149: pop
    //   150: iconst_0
    //   151: istore #6
    //   153: dup2_x1
    //   154: pop2
    //   155: dup_x2
    //   156: iconst_1
    //   157: if_icmpgt -> 260
    //   160: dup2
    //   161: swap
    //   162: iload #6
    //   164: dup2_x1
    //   165: caload
    //   166: swap
    //   167: iload #6
    //   169: bipush #7
    //   171: irem
    //   172: tableswitch default -> 242, 0 -> 212, 1 -> 217, 2 -> 222, 3 -> 227, 4 -> 232, 5 -> 237
    //   212: bipush #58
    //   214: goto -> 244
    //   217: bipush #111
    //   219: goto -> 244
    //   222: bipush #90
    //   224: goto -> 244
    //   227: bipush #79
    //   229: goto -> 244
    //   232: bipush #114
    //   234: goto -> 244
    //   237: bipush #35
    //   239: goto -> 244
    //   242: bipush #37
    //   244: ixor
    //   245: ixor
    //   246: i2c
    //   247: castore
    //   248: iinc #6, 1
    //   251: dup
    //   252: ifne -> 260
    //   255: dup2
    //   256: dup_x1
    //   257: goto -> 164
    //   260: dup2_x1
    //   261: pop2
    //   262: dup_x2
    //   263: iload #6
    //   265: if_icmpgt -> 160
    //   268: pop
    //   269: new java/lang/String
    //   272: dup_x1
    //   273: swap
    //   274: invokespecial <init> : ([C)V
    //   277: invokevirtual intern : ()Ljava/lang/String;
    //   280: swap
    //   281: pop
    //   282: swap
    //   283: tableswitch default -> 39, 0 -> 97
    //   300: return
  }
  
  private static String a(int paramInt1, int paramInt2) {
    int i = (paramInt1 ^ 0xFFFFD269) & 0xFFFF;
    if (b[i] == null) {
      char[] arrayOfChar = a[i].toCharArray();
      switch (arrayOfChar[0] & 0xFF) {
        case 0:
        
        case 1:
        
        case 2:
        
        case 3:
        
        case 4:
        
        case 5:
        
        case 6:
        
        case 7:
        
        case 8:
        
        case 9:
        
        case 10:
        
        case 11:
        
        case 12:
        
        case 13:
        
        case 14:
        
        case 15:
        
        case 16:
        
        case 17:
        
        case 18:
        
        case 19:
        
        case 20:
        
        case 21:
        
        case 22:
        
        case 23:
        
        case 24:
        
        case 25:
        
        case 26:
        
        case 27:
        
        case 28:
        
        case 29:
        
        case 30:
        
        case 31:
        
        case 32:
        
        case 33:
        
        case 34:
        
        case 35:
        
        case 36:
        
        case 37:
        
        case 38:
        
        case 39:
        
        case 40:
        
        case 41:
        
        case 42:
        
        case 43:
        
        case 44:
        
        case 45:
        
        case 46:
        
        case 47:
        
        case 48:
        
        case 49:
        
        case 50:
        
        case 51:
        
        case 52:
        
        case 53:
        
        case 54:
        
        case 55:
        
        case 56:
        
        case 57:
        
        case 58:
        
        case 59:
        
        case 60:
        
        case 61:
        
        case 62:
        
        case 63:
        
        case 64:
        
        case 65:
        
        case 66:
        
        case 67:
        
        case 68:
        
        case 69:
        
        case 70:
        
        case 71:
        
        case 72:
        
        case 73:
        
        case 74:
        
        case 75:
        
        case 76:
        
        case 77:
        
        case 78:
        
        case 79:
        
        case 80:
        
        case 81:
        
        case 82:
        
        case 83:
        
        case 84:
        
        case 85:
        
        case 86:
        
        case 87:
        
        case 88:
        
        case 89:
        
        case 90:
        
        case 91:
        
        case 92:
        
        case 93:
        
        case 94:
        
        case 95:
        
        case 96:
        
        case 97:
        
        case 98:
        
        case 99:
        
        case 100:
        
        case 101:
        
        case 102:
        
        case 103:
        
        case 104:
        
        case 105:
        
        case 106:
        
        case 107:
        
        case 108:
        
        case 109:
        
        case 110:
        
        case 111:
        
        case 112:
        
        case 113:
        
        case 114:
        
        case 115:
        
        case 116:
        
        case 117:
        
        case 118:
        
        case 119:
        
        case 120:
        
        case 121:
        
        case 122:
        
        case 123:
        
        case 124:
        
        case 125:
        
        case 126:
        
        case 127:
        
        case 128:
        
        case 129:
        
        case 130:
        
        case 131:
        
        case 132:
        
        case 133:
        
        case 134:
        
        case 135:
        
        case 136:
        
        case 137:
        
        case 138:
        
        case 139:
        
        case 140:
        
        case 141:
        
        case 142:
        
        case 143:
        
        case 144:
        
        case 145:
        
        case 146:
        
        case 147:
        
        case 148:
        
        case 149:
        
        case 150:
        
        case 151:
        
        case 152:
        
        case 153:
        
        case 154:
        
        case 155:
        
        case 156:
        
        case 157:
        
        case 158:
        
        case 159:
        
        case 160:
        
        case 161:
        
        case 162:
        
        case 163:
        
        case 164:
        
        case 165:
        
        case 166:
        
        case 167:
        
        case 168:
        
        case 169:
        
        case 170:
        
        case 171:
        
        case 172:
        
        case 173:
        
        case 174:
        
        case 175:
        
        case 176:
        
        case 177:
        
        case 178:
        
        case 179:
        
        case 180:
        
        case 181:
        
        case 182:
        
        case 183:
        
        case 184:
        
        case 185:
        
        case 186:
        
        case 187:
        
        case 188:
        
        case 189:
        
        case 190:
        
        case 191:
        
        case 192:
        
        case 193:
        
        case 194:
        
        case 195:
        
        case 196:
        
        case 197:
        
        case 198:
        
        case 199:
        
        case 200:
        
        case 201:
        
        case 202:
        
        case 203:
        
        case 204:
        
        case 205:
        
        case 206:
        
        case 207:
        
        case 208:
        
        case 209:
        
        case 210:
        
        case 211:
        
        case 212:
        
        case 213:
        
        case 214:
        
        case 215:
        
        case 216:
        
        case 217:
        
        case 218:
        
        case 219:
        
        case 220:
        
        case 221:
        
        case 222:
        
        case 223:
        
        case 224:
        
        case 225:
        
        case 226:
        
        case 227:
        
        case 228:
        
        case 229:
        
        case 230:
        
        case 231:
        
        case 232:
        
        case 233:
        
        case 234:
        
        case 235:
        
        case 236:
        
        case 237:
        
        case 238:
        
        case 239:
        
        case 240:
        
        case 241:
        
        case 242:
        
        case 243:
        
        case 244:
        
        case 245:
        
        case 246:
        
        case 247:
        
        case 248:
        
        case 249:
        
        case 250:
        
        case 251:
        
        case 252:
        
        case 253:
        
        case 254:
        
        default:
          break;
      } 
      byte b1 = 76;
      int j = (paramInt2 & 0xFF) - b1;
      if (j < 0)
        j += 256; 
      int k = ((paramInt2 & 0xFFFF) >>> 8) - b1;
      if (k < 0)
        k += 256; 
      for (byte b2 = 0; b2 < arrayOfChar.length; b2++) {
        int m = b2 % 2;
        if (m == 0) {
          arrayOfChar[b2] = (char)(arrayOfChar[b2] ^ j);
          j = ((j >>> 3 | j << 5) ^ arrayOfChar[b2]) & 0xFF;
        } else {
          arrayOfChar[b2] = (char)(arrayOfChar[b2] ^ k);
          k = ((k >>> 3 | k << 5) ^ arrayOfChar[b2]) & 0xFF;
        } 
      } 
      b[i] = (new String(arrayOfChar)).intern();
    } 
    return b[i];
  }
}


/* Location:              C:\Program Files\BurpSuitePro\burpsuite_pro.jar!\net\portswigger\swagger\v1\models\Path.class
 * Java compiler version: 21 (65.0)
 * JD-Core Version:       1.1.3
 */