package org.yaml;

import java.io.IOException;

class Z_w implements Zd {
  private final boolean ZE;
  
  final Zb ZT;
  
  private static final String[] a;
  
  private static final String[] b;
  
  public Z_w(Zb paramZb, boolean paramBoolean) {
    this.ZE = paramBoolean;
  }
  
  public void Zt() throws IOException {
    // Byte code:
    //   0: invokestatic ZH : ()Ljava/lang/String;
    //   3: astore_1
    //   4: aload_0
    //   5: getfield ZT : Lorg/yaml/Zb;
    //   8: invokestatic ZJ : (Lorg/yaml/Zb;)Lorg/yaml/Zlv;
    //   11: instanceof org/yaml/Zl8
    //   14: ifeq -> 471
    //   17: aload_0
    //   18: getfield ZT : Lorg/yaml/Zb;
    //   21: invokestatic ZJ : (Lorg/yaml/Zb;)Lorg/yaml/Zlv;
    //   24: checkcast org/yaml/Zl8
    //   27: astore_2
    //   28: aload_2
    //   29: invokevirtual Zj : ()Lorg/yaml/Zjv;
    //   32: ifnonnull -> 49
    //   35: aload_2
    //   36: invokevirtual ZC : ()Ljava/util/Map;
    //   39: ifnull -> 99
    //   42: goto -> 49
    //   45: invokestatic a : (Ljava/io/IOException;)Ljava/io/IOException;
    //   48: athrow
    //   49: aload_0
    //   50: getfield ZT : Lorg/yaml/Zb;
    //   53: invokestatic Zs : (Lorg/yaml/Zb;)Z
    //   56: ifeq -> 99
    //   59: goto -> 66
    //   62: invokestatic a : (Ljava/io/IOException;)Ljava/io/IOException;
    //   65: athrow
    //   66: aload_0
    //   67: getfield ZT : Lorg/yaml/Zb;
    //   70: sipush #-24200
    //   73: sipush #-20780
    //   76: invokestatic a : (II)Ljava/lang/String;
    //   79: iconst_1
    //   80: iconst_0
    //   81: iconst_0
    //   82: invokevirtual Zv : (Ljava/lang/String;ZZZ)V
    //   85: aload_0
    //   86: getfield ZT : Lorg/yaml/Zb;
    //   89: invokevirtual ZJ : ()V
    //   92: goto -> 99
    //   95: invokestatic a : (Ljava/io/IOException;)Ljava/io/IOException;
    //   98: athrow
    //   99: aload_2
    //   100: invokevirtual Zj : ()Lorg/yaml/Zjv;
    //   103: ifnull -> 126
    //   106: aload_0
    //   107: getfield ZT : Lorg/yaml/Zb;
    //   110: aload_2
    //   111: invokevirtual Zj : ()Lorg/yaml/Zjv;
    //   114: invokestatic Zi : (Lorg/yaml/Zb;Lorg/yaml/Zjv;)Ljava/lang/String;
    //   117: astore_3
    //   118: aload_0
    //   119: getfield ZT : Lorg/yaml/Zb;
    //   122: aload_3
    //   123: invokevirtual ZQ : (Ljava/lang/String;)V
    //   126: aload_0
    //   127: getfield ZT : Lorg/yaml/Zb;
    //   130: new java/util/LinkedHashMap
    //   133: dup
    //   134: invokestatic ZC : ()Ljava/util/Map;
    //   137: invokespecial <init> : (Ljava/util/Map;)V
    //   140: invokestatic ZR : (Lorg/yaml/Zb;Ljava/util/Map;)Ljava/util/Map;
    //   143: pop
    //   144: aload_2
    //   145: invokevirtual ZC : ()Ljava/util/Map;
    //   148: ifnull -> 268
    //   151: new java/util/TreeSet
    //   154: dup
    //   155: aload_2
    //   156: invokevirtual ZC : ()Ljava/util/Map;
    //   159: invokeinterface keySet : ()Ljava/util/Set;
    //   164: invokespecial <init> : (Ljava/util/Collection;)V
    //   167: astore_3
    //   168: aload_3
    //   169: invokeinterface iterator : ()Ljava/util/Iterator;
    //   174: astore #4
    //   176: aload #4
    //   178: invokeinterface hasNext : ()Z
    //   183: ifeq -> 268
    //   186: aload #4
    //   188: invokeinterface next : ()Ljava/lang/Object;
    //   193: checkcast java/lang/String
    //   196: astore #5
    //   198: aload_2
    //   199: invokevirtual ZC : ()Ljava/util/Map;
    //   202: aload #5
    //   204: invokeinterface get : (Ljava/lang/Object;)Ljava/lang/Object;
    //   209: checkcast java/lang/String
    //   212: astore #6
    //   214: aload_0
    //   215: getfield ZT : Lorg/yaml/Zb;
    //   218: invokestatic ZT : (Lorg/yaml/Zb;)Ljava/util/Map;
    //   221: aload #6
    //   223: aload #5
    //   225: invokeinterface put : (Ljava/lang/Object;Ljava/lang/Object;)Ljava/lang/Object;
    //   230: pop
    //   231: aload_0
    //   232: getfield ZT : Lorg/yaml/Zb;
    //   235: aload #5
    //   237: invokestatic Zo : (Lorg/yaml/Zb;Ljava/lang/String;)Ljava/lang/String;
    //   240: astore #7
    //   242: aload_0
    //   243: getfield ZT : Lorg/yaml/Zb;
    //   246: aload #6
    //   248: invokestatic ZP : (Lorg/yaml/Zb;Ljava/lang/String;)Ljava/lang/String;
    //   251: astore #8
    //   253: aload_0
    //   254: getfield ZT : Lorg/yaml/Zb;
    //   257: aload #7
    //   259: aload #8
    //   261: invokevirtual Zg : (Ljava/lang/String;Ljava/lang/String;)V
    //   264: aload_1
    //   265: ifnonnull -> 176
    //   268: aload_0
    //   269: getfield ZE : Z
    //   272: ifeq -> 381
    //   275: aload_2
    //   276: invokevirtual ZZ : ()Z
    //   279: ifne -> 381
    //   282: goto -> 289
    //   285: invokestatic a : (Ljava/io/IOException;)Ljava/io/IOException;
    //   288: athrow
    //   289: aload_0
    //   290: getfield ZT : Lorg/yaml/Zb;
    //   293: invokestatic ZP : (Lorg/yaml/Zb;)Ljava/lang/Boolean;
    //   296: invokevirtual booleanValue : ()Z
    //   299: ifne -> 381
    //   302: goto -> 309
    //   305: invokestatic a : (Ljava/io/IOException;)Ljava/io/IOException;
    //   308: athrow
    //   309: aload_2
    //   310: invokevirtual Zj : ()Lorg/yaml/Zjv;
    //   313: ifnonnull -> 381
    //   316: goto -> 323
    //   319: invokestatic a : (Ljava/io/IOException;)Ljava/io/IOException;
    //   322: athrow
    //   323: aload_2
    //   324: invokevirtual ZC : ()Ljava/util/Map;
    //   327: ifnull -> 356
    //   330: goto -> 337
    //   333: invokestatic a : (Ljava/io/IOException;)Ljava/io/IOException;
    //   336: athrow
    //   337: aload_2
    //   338: invokevirtual ZC : ()Ljava/util/Map;
    //   341: invokeinterface isEmpty : ()Z
    //   346: ifeq -> 381
    //   349: goto -> 356
    //   352: invokestatic a : (Ljava/io/IOException;)Ljava/io/IOException;
    //   355: athrow
    //   356: aload_0
    //   357: getfield ZT : Lorg/yaml/Zb;
    //   360: invokestatic ZY : (Lorg/yaml/Zb;)Z
    //   363: ifne -> 381
    //   366: goto -> 373
    //   369: invokestatic a : (Ljava/io/IOException;)Ljava/io/IOException;
    //   372: athrow
    //   373: iconst_1
    //   374: goto -> 382
    //   377: invokestatic a : (Ljava/io/IOException;)Ljava/io/IOException;
    //   380: athrow
    //   381: iconst_0
    //   382: istore_3
    //   383: iload_3
    //   384: ifne -> 447
    //   387: aload_0
    //   388: getfield ZT : Lorg/yaml/Zb;
    //   391: invokevirtual ZJ : ()V
    //   394: aload_0
    //   395: getfield ZT : Lorg/yaml/Zb;
    //   398: sipush #-24198
    //   401: sipush #-1574
    //   404: invokestatic a : (II)Ljava/lang/String;
    //   407: iconst_1
    //   408: iconst_0
    //   409: iconst_0
    //   410: invokevirtual Zv : (Ljava/lang/String;ZZZ)V
    //   413: aload_0
    //   414: getfield ZT : Lorg/yaml/Zb;
    //   417: invokestatic ZP : (Lorg/yaml/Zb;)Ljava/lang/Boolean;
    //   420: invokevirtual booleanValue : ()Z
    //   423: ifeq -> 447
    //   426: goto -> 433
    //   429: invokestatic a : (Ljava/io/IOException;)Ljava/io/IOException;
    //   432: athrow
    //   433: aload_0
    //   434: getfield ZT : Lorg/yaml/Zb;
    //   437: invokevirtual ZJ : ()V
    //   440: goto -> 447
    //   443: invokestatic a : (Ljava/io/IOException;)Ljava/io/IOException;
    //   446: athrow
    //   447: aload_0
    //   448: getfield ZT : Lorg/yaml/Zb;
    //   451: new org/yaml/Z_2
    //   454: dup
    //   455: aload_0
    //   456: getfield ZT : Lorg/yaml/Zb;
    //   459: aconst_null
    //   460: invokespecial <init> : (Lorg/yaml/Zb;Lorg/yaml/Zjq;)V
    //   463: invokestatic ZB : (Lorg/yaml/Zb;Lorg/yaml/Zd;)Lorg/yaml/Zd;
    //   466: pop
    //   467: aload_1
    //   468: ifnonnull -> 629
    //   471: aload_0
    //   472: getfield ZT : Lorg/yaml/Zb;
    //   475: invokestatic ZJ : (Lorg/yaml/Zb;)Lorg/yaml/Zlv;
    //   478: instanceof org/yaml/Zt6
    //   481: ifeq -> 529
    //   484: goto -> 491
    //   487: invokestatic a : (Ljava/io/IOException;)Ljava/io/IOException;
    //   490: athrow
    //   491: aload_0
    //   492: getfield ZT : Lorg/yaml/Zb;
    //   495: invokevirtual Zt : ()V
    //   498: aload_0
    //   499: getfield ZT : Lorg/yaml/Zb;
    //   502: new org/yaml/Zg2
    //   505: dup
    //   506: aload_0
    //   507: getfield ZT : Lorg/yaml/Zb;
    //   510: aconst_null
    //   511: invokespecial <init> : (Lorg/yaml/Zb;Lorg/yaml/Zjq;)V
    //   514: invokestatic ZB : (Lorg/yaml/Zb;Lorg/yaml/Zd;)Lorg/yaml/Zd;
    //   517: pop
    //   518: aload_1
    //   519: ifnonnull -> 629
    //   522: goto -> 529
    //   525: invokestatic a : (Ljava/io/IOException;)Ljava/io/IOException;
    //   528: athrow
    //   529: aload_0
    //   530: getfield ZT : Lorg/yaml/Zb;
    //   533: invokestatic ZJ : (Lorg/yaml/Zb;)Lorg/yaml/Zlv;
    //   536: instanceof org/yaml/Zld
    //   539: ifeq -> 585
    //   542: goto -> 549
    //   545: invokestatic a : (Ljava/io/IOException;)Ljava/io/IOException;
    //   548: athrow
    //   549: aload_0
    //   550: getfield ZT : Lorg/yaml/Zb;
    //   553: invokestatic ZM : (Lorg/yaml/Zb;)Lorg/yaml/Zj8;
    //   556: aload_0
    //   557: getfield ZT : Lorg/yaml/Zb;
    //   560: invokestatic ZJ : (Lorg/yaml/Zb;)Lorg/yaml/Zlv;
    //   563: invokevirtual ZF : (Lorg/yaml/Zlv;)Lorg/yaml/Zlv;
    //   566: pop
    //   567: aload_0
    //   568: getfield ZT : Lorg/yaml/Zb;
    //   571: invokestatic ZB : (Lorg/yaml/Zb;)V
    //   574: aload_1
    //   575: ifnonnull -> 629
    //   578: goto -> 585
    //   581: invokestatic a : (Ljava/io/IOException;)Ljava/io/IOException;
    //   584: athrow
    //   585: new org/yaml/Zja
    //   588: dup
    //   589: new java/lang/StringBuilder
    //   592: dup
    //   593: invokespecial <init> : ()V
    //   596: sipush #-24197
    //   599: sipush #16566
    //   602: invokestatic a : (II)Ljava/lang/String;
    //   605: invokevirtual append : (Ljava/lang/String;)Ljava/lang/StringBuilder;
    //   608: aload_0
    //   609: getfield ZT : Lorg/yaml/Zb;
    //   612: invokestatic ZJ : (Lorg/yaml/Zb;)Lorg/yaml/Zlv;
    //   615: invokevirtual append : (Ljava/lang/Object;)Ljava/lang/StringBuilder;
    //   618: invokevirtual toString : ()Ljava/lang/String;
    //   621: invokespecial <init> : (Ljava/lang/String;)V
    //   624: athrow
    //   625: invokestatic a : (Ljava/io/IOException;)Ljava/io/IOException;
    //   628: athrow
    //   629: return
    // Exception table:
    //   from	to	target	type
    //   28	42	45	java/io/IOException
    //   35	59	62	java/io/IOException
    //   49	92	95	java/io/IOException
    //   268	282	285	java/io/IOException
    //   275	302	305	java/io/IOException
    //   289	316	319	java/io/IOException
    //   309	330	333	java/io/IOException
    //   323	349	352	java/io/IOException
    //   337	366	369	java/io/IOException
    //   356	377	377	java/io/IOException
    //   383	426	429	java/io/IOException
    //   387	440	443	java/io/IOException
    //   447	484	487	java/io/IOException
    //   471	522	525	java/io/IOException
    //   491	542	545	java/io/IOException
    //   529	578	581	java/io/IOException
    //   549	625	625	java/io/IOException
  }
  
  private static IOException a(IOException paramIOException) {
    return paramIOException;
  }
  
  static {
    // Byte code:
    //   0: iconst_3
    //   1: anewarray java/lang/String
    //   4: astore #5
    //   6: iconst_0
    //   7: istore_3
    //   8: ldc 'Â¥ÂžÃ®%Ã¾Â§*"WÃ¬Ã¦ÃŽpÂ½Â¬Ã¬ÃžÃŸÃŒÂ¾6&lXÃ¾dÃ‚Ã†Â®Â‘Ã»ÂœÃ‚Â£2F*ÂÃ¢f'
    //   10: dup
    //   11: astore_2
    //   12: invokevirtual length : ()I
    //   15: istore #4
    //   17: iconst_3
    //   18: istore_1
    //   19: iconst_m1
    //   20: istore_0
    //   21: bipush #116
    //   23: iinc #0, 1
    //   26: aload_2
    //   27: iload_0
    //   28: dup
    //   29: iload_1
    //   30: iadd
    //   31: invokevirtual substring : (II)Ljava/lang/String;
    //   34: iconst_m1
    //   35: goto -> 81
    //   38: aload #5
    //   40: swap
    //   41: iload_3
    //   42: iinc #3, 1
    //   45: swap
    //   46: aastore
    //   47: iload_0
    //   48: iload_1
    //   49: iadd
    //   50: dup
    //   51: istore_0
    //   52: iload #4
    //   54: if_icmpge -> 66
    //   57: aload_2
    //   58: iload_0
    //   59: invokevirtual charAt : (I)C
    //   62: istore_1
    //   63: goto -> 21
    //   66: aload #5
    //   68: putstatic org/yaml/Z_w.a : [Ljava/lang/String;
    //   71: iconst_3
    //   72: anewarray java/lang/String
    //   75: putstatic org/yaml/Z_w.b : [Ljava/lang/String;
    //   78: goto -> 227
    //   81: dup_x2
    //   82: pop
    //   83: invokevirtual toCharArray : ()[C
    //   86: dup_x1
    //   87: arraylength
    //   88: dup_x2
    //   89: pop
    //   90: iconst_0
    //   91: istore #6
    //   93: dup2_x1
    //   94: pop2
    //   95: dup_x2
    //   96: iconst_1
    //   97: if_icmpgt -> 200
    //   100: dup2
    //   101: swap
    //   102: iload #6
    //   104: dup2_x1
    //   105: caload
    //   106: swap
    //   107: iload #6
    //   109: bipush #7
    //   111: irem
    //   112: tableswitch default -> 182, 0 -> 152, 1 -> 157, 2 -> 162, 3 -> 167, 4 -> 172, 5 -> 177
    //   152: bipush #33
    //   154: goto -> 184
    //   157: bipush #59
    //   159: goto -> 184
    //   162: bipush #33
    //   164: goto -> 184
    //   167: bipush #122
    //   169: goto -> 184
    //   172: bipush #21
    //   174: goto -> 184
    //   177: bipush #66
    //   179: goto -> 184
    //   182: bipush #33
    //   184: ixor
    //   185: ixor
    //   186: i2c
    //   187: castore
    //   188: iinc #6, 1
    //   191: dup
    //   192: ifne -> 200
    //   195: dup2
    //   196: dup_x1
    //   197: goto -> 104
    //   200: dup2_x1
    //   201: pop2
    //   202: dup_x2
    //   203: iload #6
    //   205: if_icmpgt -> 100
    //   208: pop
    //   209: new java/lang/String
    //   212: dup_x1
    //   213: swap
    //   214: invokespecial <init> : ([C)V
    //   217: invokevirtual intern : ()Ljava/lang/String;
    //   220: swap
    //   221: pop
    //   222: swap
    //   223: pop
    //   224: goto -> 38
    //   227: return
  }
  
  private static String a(int paramInt1, int paramInt2) {
    int i = (paramInt1 ^ 0xFFFFA17A) & 0xFFFF;
    if (b[i] == null) {
      char[] arrayOfChar = a[i].toCharArray();
      switch (arrayOfChar[0] & 0xFF) {
        case 0:
        
        case 1:
        
        case 2:
        
        case 3:
        
        case 4:
        
        case 5:
        
        case 6:
        
        case 7:
        
        case 8:
        
        case 9:
        
        case 10:
        
        case 11:
        
        case 12:
        
        case 13:
        
        case 14:
        
        case 15:
        
        case 16:
        
        case 17:
        
        case 18:
        
        case 19:
        
        case 20:
        
        case 21:
        
        case 22:
        
        case 23:
        
        case 24:
        
        case 25:
        
        case 26:
        
        case 27:
        
        case 28:
        
        case 29:
        
        case 30:
        
        case 31:
        
        case 32:
        
        case 33:
        
        case 34:
        
        case 35:
        
        case 36:
        
        case 37:
        
        case 38:
        
        case 39:
        
        case 40:
        
        case 41:
        
        case 42:
        
        case 43:
        
        case 44:
        
        case 45:
        
        case 46:
        
        case 47:
        
        case 48:
        
        case 49:
        
        case 50:
        
        case 51:
        
        case 52:
        
        case 53:
        
        case 54:
        
        case 55:
        
        case 56:
        
        case 57:
        
        case 58:
        
        case 59:
        
        case 60:
        
        case 61:
        
        case 62:
        
        case 63:
        
        case 64:
        
        case 65:
        
        case 66:
        
        case 67:
        
        case 68:
        
        case 69:
        
        case 70:
        
        case 71:
        
        case 72:
        
        case 73:
        
        case 74:
        
        case 75:
        
        case 76:
        
        case 77:
        
        case 78:
        
        case 79:
        
        case 80:
        
        case 81:
        
        case 82:
        
        case 83:
        
        case 84:
        
        case 85:
        
        case 86:
        
        case 87:
        
        case 88:
        
        case 89:
        
        case 90:
        
        case 91:
        
        case 92:
        
        case 93:
        
        case 94:
        
        case 95:
        
        case 96:
        
        case 97:
        
        case 98:
        
        case 99:
        
        case 100:
        
        case 101:
        
        case 102:
        
        case 103:
        
        case 104:
        
        case 105:
        
        case 106:
        
        case 107:
        
        case 108:
        
        case 109:
        
        case 110:
        
        case 111:
        
        case 112:
        
        case 113:
        
        case 114:
        
        case 115:
        
        case 116:
        
        case 117:
        
        case 118:
        
        case 119:
        
        case 120:
        
        case 121:
        
        case 122:
        
        case 123:
        
        case 124:
        
        case 125:
        
        case 126:
        
        case 127:
        
        case 128:
        
        case 129:
        
        case 130:
        
        case 131:
        
        case 132:
        
        case 133:
        
        case 134:
        
        case 135:
        
        case 136:
        
        case 137:
        
        case 138:
        
        case 139:
        
        case 140:
        
        case 141:
        
        case 142:
        
        case 143:
        
        case 144:
        
        case 145:
        
        case 146:
        
        case 147:
        
        case 148:
        
        case 149:
        
        case 150:
        
        case 151:
        
        case 152:
        
        case 153:
        
        case 154:
        
        case 155:
        
        case 156:
        
        case 157:
        
        case 158:
        
        case 159:
        
        case 160:
        
        case 161:
        
        case 162:
        
        case 163:
        
        case 164:
        
        case 165:
        
        case 166:
        
        case 167:
        
        case 168:
        
        case 169:
        
        case 170:
        
        case 171:
        
        case 172:
        
        case 173:
        
        case 174:
        
        case 175:
        
        case 176:
        
        case 177:
        
        case 178:
        
        case 179:
        
        case 180:
        
        case 181:
        
        case 182:
        
        case 183:
        
        case 184:
        
        case 185:
        
        case 186:
        
        case 187:
        
        case 188:
        
        case 189:
        
        case 190:
        
        case 191:
        
        case 192:
        
        case 193:
        
        case 194:
        
        case 195:
        
        case 196:
        
        case 197:
        
        case 198:
        
        case 199:
        
        case 200:
        
        case 201:
        
        case 202:
        
        case 203:
        
        case 204:
        
        case 205:
        
        case 206:
        
        case 207:
        
        case 208:
        
        case 209:
        
        case 210:
        
        case 211:
        
        case 212:
        
        case 213:
        
        case 214:
        
        case 215:
        
        case 216:
        
        case 217:
        
        case 218:
        
        case 219:
        
        case 220:
        
        case 221:
        
        case 222:
        
        case 223:
        
        case 224:
        
        case 225:
        
        case 226:
        
        case 227:
        
        case 228:
        
        case 229:
        
        case 230:
        
        case 231:
        
        case 232:
        
        case 233:
        
        case 234:
        
        case 235:
        
        case 236:
        
        case 237:
        
        case 238:
        
        case 239:
        
        case 240:
        
        case 241:
        
        case 242:
        
        case 243:
        
        case 244:
        
        case 245:
        
        case 246:
        
        case 247:
        
        case 248:
        
        case 249:
        
        case 250:
        
        case 251:
        
        case 252:
        
        case 253:
        
        case 254:
        
        default:
          break;
      } 
      char c = 'Â©';
      int j = (paramInt2 & 0xFF) - c;
      if (j < 0)
        j += 256; 
      int k = ((paramInt2 & 0xFFFF) >>> 8) - c;
      if (k < 0)
        k += 256; 
      for (byte b = 0; b < arrayOfChar.length; b++) {
        int m = b % 2;
        if (m == 0) {
          arrayOfChar[b] = (char)(arrayOfChar[b] ^ j);
          j = ((j >>> 3 | j << 5) ^ arrayOfChar[b]) & 0xFF;
        } else {
          arrayOfChar[b] = (char)(arrayOfChar[b] ^ k);
          k = ((k >>> 3 | k << 5) ^ arrayOfChar[b]) & 0xFF;
        } 
      } 
      b[i] = (new String(arrayOfChar)).intern();
    } 
    return b[i];
  }
}


/* Location:              C:\Program Files\BurpSuitePro\burpsuite_pro.jar!\org\yaml\Z_w.class
 * Java compiler version: 7 (51.0)
 * JD-Core Version:       1.1.3
 */