package org.yaml;

import java.io.IOException;

class Za implements Zd {
  final Zb Zp;
  
  private Za(Zb paramZb) {}
  
  public void Zt() throws IOException {
    // Byte code:
    //   0: invokestatic ZH : ()Ljava/lang/String;
    //   3: astore_1
    //   4: aload_0
    //   5: getfield Zp : Lorg/yaml/Zb;
    //   8: invokestatic ZJ : (Lorg/yaml/Zb;)Lorg/yaml/Zlv;
    //   11: instanceof org/yaml/Zlu
    //   14: ifeq -> 213
    //   17: aload_0
    //   18: getfield Zp : Lorg/yaml/Zb;
    //   21: aload_0
    //   22: getfield Zp : Lorg/yaml/Zb;
    //   25: invokestatic Zf : (Lorg/yaml/Zb;)Lorg/yaml/Zq;
    //   28: invokevirtual ZE : ()Ljava/lang/Object;
    //   31: checkcast java/lang/Integer
    //   34: invokestatic ZE : (Lorg/yaml/Zb;Ljava/lang/Integer;)Ljava/lang/Integer;
    //   37: pop
    //   38: aload_0
    //   39: getfield Zp : Lorg/yaml/Zb;
    //   42: invokestatic Zb : (Lorg/yaml/Zb;)I
    //   45: pop
    //   46: aload_0
    //   47: getfield Zp : Lorg/yaml/Zb;
    //   50: invokestatic ZP : (Lorg/yaml/Zb;)Ljava/lang/Boolean;
    //   53: invokevirtual booleanValue : ()Z
    //   56: ifeq -> 96
    //   59: goto -> 66
    //   62: invokestatic a : (Ljava/io/IOException;)Ljava/io/IOException;
    //   65: athrow
    //   66: aload_0
    //   67: getfield Zp : Lorg/yaml/Zb;
    //   70: ldc ','
    //   72: iconst_0
    //   73: iconst_0
    //   74: iconst_0
    //   75: invokevirtual Zv : (Ljava/lang/String;ZZZ)V
    //   78: aload_0
    //   79: getfield Zp : Lorg/yaml/Zb;
    //   82: invokevirtual ZJ : ()V
    //   85: aload_1
    //   86: ifnonnull -> 130
    //   89: goto -> 96
    //   92: invokestatic a : (Ljava/io/IOException;)Ljava/io/IOException;
    //   95: athrow
    //   96: aload_0
    //   97: getfield Zp : Lorg/yaml/Zb;
    //   100: invokestatic ZN : (Lorg/yaml/Zb;)Ljava/lang/Boolean;
    //   103: invokevirtual booleanValue : ()Z
    //   106: ifeq -> 130
    //   109: goto -> 116
    //   112: invokestatic a : (Ljava/io/IOException;)Ljava/io/IOException;
    //   115: athrow
    //   116: aload_0
    //   117: getfield Zp : Lorg/yaml/Zb;
    //   120: invokevirtual ZJ : ()V
    //   123: goto -> 130
    //   126: invokestatic a : (Ljava/io/IOException;)Ljava/io/IOException;
    //   129: athrow
    //   130: aload_0
    //   131: getfield Zp : Lorg/yaml/Zb;
    //   134: ldc ']'
    //   136: iconst_0
    //   137: iconst_0
    //   138: iconst_0
    //   139: invokevirtual Zv : (Ljava/lang/String;ZZZ)V
    //   142: aload_0
    //   143: getfield Zp : Lorg/yaml/Zb;
    //   146: invokestatic ZS : (Lorg/yaml/Zb;)Lorg/yaml/Zj8;
    //   149: invokevirtual Zh : ()Lorg/yaml/Zj8;
    //   152: pop
    //   153: aload_0
    //   154: getfield Zp : Lorg/yaml/Zb;
    //   157: invokestatic Zl : (Lorg/yaml/Zb;)Z
    //   160: pop
    //   161: aload_0
    //   162: getfield Zp : Lorg/yaml/Zb;
    //   165: invokestatic ZN : (Lorg/yaml/Zb;)Ljava/lang/Boolean;
    //   168: invokevirtual booleanValue : ()Z
    //   171: ifeq -> 188
    //   174: aload_0
    //   175: getfield Zp : Lorg/yaml/Zb;
    //   178: invokevirtual ZJ : ()V
    //   181: goto -> 188
    //   184: invokestatic a : (Ljava/io/IOException;)Ljava/io/IOException;
    //   187: athrow
    //   188: aload_0
    //   189: getfield Zp : Lorg/yaml/Zb;
    //   192: aload_0
    //   193: getfield Zp : Lorg/yaml/Zb;
    //   196: invokestatic Za : (Lorg/yaml/Zb;)Lorg/yaml/Zq;
    //   199: invokevirtual ZE : ()Ljava/lang/Object;
    //   202: checkcast org/yaml/Zd
    //   205: invokestatic ZB : (Lorg/yaml/Zb;Lorg/yaml/Zd;)Lorg/yaml/Zd;
    //   208: pop
    //   209: aload_1
    //   210: ifnonnull -> 447
    //   213: aload_0
    //   214: getfield Zp : Lorg/yaml/Zb;
    //   217: invokestatic ZJ : (Lorg/yaml/Zb;)Lorg/yaml/Zlv;
    //   220: instanceof org/yaml/Zld
    //   223: ifeq -> 269
    //   226: goto -> 233
    //   229: invokestatic a : (Ljava/io/IOException;)Ljava/io/IOException;
    //   232: athrow
    //   233: aload_0
    //   234: getfield Zp : Lorg/yaml/Zb;
    //   237: aload_0
    //   238: getfield Zp : Lorg/yaml/Zb;
    //   241: invokestatic ZM : (Lorg/yaml/Zb;)Lorg/yaml/Zj8;
    //   244: aload_0
    //   245: getfield Zp : Lorg/yaml/Zb;
    //   248: invokestatic ZJ : (Lorg/yaml/Zb;)Lorg/yaml/Zlv;
    //   251: invokevirtual ZF : (Lorg/yaml/Zlv;)Lorg/yaml/Zlv;
    //   254: invokestatic Za : (Lorg/yaml/Zb;Lorg/yaml/Zlv;)Lorg/yaml/Zlv;
    //   257: pop
    //   258: aload_1
    //   259: ifnonnull -> 447
    //   262: goto -> 269
    //   265: invokestatic a : (Ljava/io/IOException;)Ljava/io/IOException;
    //   268: athrow
    //   269: aload_0
    //   270: getfield Zp : Lorg/yaml/Zb;
    //   273: ldc ','
    //   275: iconst_0
    //   276: iconst_0
    //   277: iconst_0
    //   278: invokevirtual Zv : (Ljava/lang/String;ZZZ)V
    //   281: aload_0
    //   282: getfield Zp : Lorg/yaml/Zb;
    //   285: invokestatic ZB : (Lorg/yaml/Zb;)V
    //   288: aload_0
    //   289: getfield Zp : Lorg/yaml/Zb;
    //   292: invokestatic ZP : (Lorg/yaml/Zb;)Ljava/lang/Boolean;
    //   295: invokevirtual booleanValue : ()Z
    //   298: ifne -> 369
    //   301: goto -> 308
    //   304: invokestatic a : (Ljava/io/IOException;)Ljava/io/IOException;
    //   307: athrow
    //   308: aload_0
    //   309: getfield Zp : Lorg/yaml/Zb;
    //   312: invokestatic Zt : (Lorg/yaml/Zb;)I
    //   315: aload_0
    //   316: getfield Zp : Lorg/yaml/Zb;
    //   319: invokestatic Z_ : (Lorg/yaml/Zb;)I
    //   322: if_icmple -> 349
    //   325: goto -> 332
    //   328: invokestatic a : (Ljava/io/IOException;)Ljava/io/IOException;
    //   331: athrow
    //   332: aload_0
    //   333: getfield Zp : Lorg/yaml/Zb;
    //   336: invokestatic Zc : (Lorg/yaml/Zb;)Z
    //   339: ifne -> 369
    //   342: goto -> 349
    //   345: invokestatic a : (Ljava/io/IOException;)Ljava/io/IOException;
    //   348: athrow
    //   349: aload_0
    //   350: getfield Zp : Lorg/yaml/Zb;
    //   353: invokestatic ZN : (Lorg/yaml/Zb;)Ljava/lang/Boolean;
    //   356: invokevirtual booleanValue : ()Z
    //   359: ifeq -> 383
    //   362: goto -> 369
    //   365: invokestatic a : (Ljava/io/IOException;)Ljava/io/IOException;
    //   368: athrow
    //   369: aload_0
    //   370: getfield Zp : Lorg/yaml/Zb;
    //   373: invokevirtual ZJ : ()V
    //   376: goto -> 383
    //   379: invokestatic a : (Ljava/io/IOException;)Ljava/io/IOException;
    //   382: athrow
    //   383: aload_0
    //   384: getfield Zp : Lorg/yaml/Zb;
    //   387: invokestatic Za : (Lorg/yaml/Zb;)Lorg/yaml/Zq;
    //   390: new org/yaml/Za
    //   393: dup
    //   394: aload_0
    //   395: getfield Zp : Lorg/yaml/Zb;
    //   398: invokespecial <init> : (Lorg/yaml/Zb;)V
    //   401: invokevirtual Zq : (Ljava/lang/Object;)V
    //   404: aload_0
    //   405: getfield Zp : Lorg/yaml/Zb;
    //   408: iconst_0
    //   409: iconst_0
    //   410: iconst_0
    //   411: invokestatic Zu : (Lorg/yaml/Zb;ZZZ)V
    //   414: aload_0
    //   415: getfield Zp : Lorg/yaml/Zb;
    //   418: aload_0
    //   419: getfield Zp : Lorg/yaml/Zb;
    //   422: invokestatic ZS : (Lorg/yaml/Zb;)Lorg/yaml/Zj8;
    //   425: aload_0
    //   426: getfield Zp : Lorg/yaml/Zb;
    //   429: invokestatic ZJ : (Lorg/yaml/Zb;)Lorg/yaml/Zlv;
    //   432: invokevirtual ZF : (Lorg/yaml/Zlv;)Lorg/yaml/Zlv;
    //   435: invokestatic Za : (Lorg/yaml/Zb;Lorg/yaml/Zlv;)Lorg/yaml/Zlv;
    //   438: pop
    //   439: aload_0
    //   440: getfield Zp : Lorg/yaml/Zb;
    //   443: invokestatic Zl : (Lorg/yaml/Zb;)Z
    //   446: pop
    //   447: return
    // Exception table:
    //   from	to	target	type
    //   4	59	62	java/io/IOException
    //   17	89	92	java/io/IOException
    //   66	109	112	java/io/IOException
    //   96	123	126	java/io/IOException
    //   130	181	184	java/io/IOException
    //   188	226	229	java/io/IOException
    //   213	262	265	java/io/IOException
    //   233	301	304	java/io/IOException
    //   269	325	328	java/io/IOException
    //   308	342	345	java/io/IOException
    //   332	362	365	java/io/IOException
    //   349	376	379	java/io/IOException
  }
  
  Za(Zb paramZb, Zjq paramZjq) {
    this(paramZb);
  }
  
  private static IOException a(IOException paramIOException) {
    return paramIOException;
  }
}


/* Location:              C:\Program Files\BurpSuitePro\burpsuite_pro.jar!\org\yaml\Za.class
 * Java compiler version: 7 (51.0)
 * JD-Core Version:       1.1.3
 */