package org.yaml;

import burp.Zbqc;
import java.io.IOException;
import java.io.Writer;
import java.util.ArrayDeque;
import java.util.Iterator;
import java.util.LinkedHashMap;
import java.util.List;
import java.util.Map;
import java.util.Queue;
import java.util.Set;
import java.util.regex.Matcher;
import java.util.regex.Pattern;

public final class Zb implements Ztb {
  private static final char[] Zy;
  
  private static final Pattern ZO;
  
  private static final Set<Character> ZV;
  
  private static final Map<Character, String> Z_;
  
  private static final Map<String, String> Zt;
  
  private final Writer ZN;
  
  private final Zq<Zd> Zu;
  
  private Zd Zv;
  
  private final Queue<Zlv> Zc;
  
  private Zlv Zw;
  
  private final Zq<Integer> Zg;
  
  private Integer Zn;
  
  private int Zk;
  
  private boolean ZJ;
  
  private boolean ZR;
  
  private boolean Zr;
  
  private int Zm;
  
  private boolean ZI;
  
  private boolean Zh;
  
  private boolean ZZ;
  
  private final Boolean ZA;
  
  private final Boolean Zx;
  
  private final boolean Zf;
  
  private int ZE;
  
  private final int Zl;
  
  private final boolean ZX;
  
  private int Zd;
  
  private final char[] ZG;
  
  private final boolean ZW;
  
  private final int ZT;
  
  private final boolean Zo;
  
  private Map<String, String> ZY;
  
  private String ZD;
  
  private String Zs;
  
  private Zjb ZF;
  
  private Zjm ZS;
  
  private final Zj8 ZK;
  
  private final Zj8 ZQ;
  
  private static final Pattern Zi;
  
  private static String ZH;
  
  private static final String[] a;
  
  private static final String[] b;
  
  public Zb(Writer paramWriter, Z_k paramZ_k) {
    String str = ZH();
    try {
      if (paramWriter == null)
        throw new NullPointerException(a(29154, -13609)); 
    } catch (NullPointerException nullPointerException) {
      throw a(null);
    } 
    try {
      if (paramZ_k == null)
        throw new NullPointerException(a(29167, 2395)); 
    } catch (NullPointerException nullPointerException) {
      throw a(null);
    } 
    try {
      this.ZN = paramWriter;
      this.Zu = new Zq<>(100);
      this.Zv = new Zlr(this, null);
      this.Zc = new ArrayDeque<>(100);
      this.Zw = null;
      this.Zg = new Zq<>(10);
      this.Zn = null;
      this.Zk = 0;
      this.ZR = false;
      this.Zr = false;
      this.Zm = 0;
      this.ZI = true;
      this.Zh = true;
      this.ZZ = false;
      this.ZA = Boolean.valueOf(paramZ_k.Zq());
      this.Zx = Boolean.valueOf(paramZ_k.ZE());
      this.Zf = paramZ_k.ZA();
      this.ZE = 2;
      if (paramZ_k.Z_() > 1)
        try {
          if (paramZ_k.Z_() < 10)
            this.ZE = paramZ_k.Z_(); 
        } catch (NullPointerException nullPointerException) {
          throw a(null);
        }  
    } catch (NullPointerException nullPointerException) {
      throw a(null);
    } 
    try {
      this.Zl = paramZ_k.ZZ();
      this.ZX = paramZ_k.ZR();
      this.Zd = 80;
      if (paramZ_k.ZV() > this.ZE * 2)
        this.Zd = paramZ_k.ZV(); 
    } catch (NullPointerException nullPointerException) {
      throw a(null);
    } 
    try {
      this.ZG = paramZ_k.Zh().ZT().toCharArray();
      this.ZW = paramZ_k.ZW();
      this.ZT = paramZ_k.Ze();
      this.Zo = paramZ_k.Zc();
      this.ZY = new LinkedHashMap<>();
      this.ZD = null;
      this.Zs = null;
      this.ZF = null;
      this.ZS = null;
      this.ZK = new Zj8(this.Zc, new Zto[] { Zto.BLANK_LINE, Zto.BLOCK });
      this.ZQ = new Zj8(this.Zc, new Zto[] { Zto.IN_LINE });
      if (str == null)
        Zbqc.Zr(new Zbqc[5]); 
    } catch (NullPointerException nullPointerException) {
      throw a(null);
    } 
  }
  
  public void ZH(Zlv paramZlv) throws IOException {
    this.Zc.add(paramZlv);
    String str = ZH();
    while (!ZO()) {
      this.Zw = this.Zc.poll();
      this.Zv.Zt();
      this.Zw = null;
      if (str == null)
        break; 
    } 
  }
  
  private boolean ZO() {
    String str = ZH();
    try {
      if (this.Zc.isEmpty())
        return true; 
    } catch (NullPointerException nullPointerException) {
      throw a(null);
    } 
    Iterator<Zlv> iterator = this.Zc.iterator();
    Zlv zlv = iterator.next();
    while (zlv instanceof Zld) {
      try {
        if (!iterator.hasNext())
          return true; 
      } catch (NullPointerException nullPointerException) {
        throw a(null);
      } 
      zlv = iterator.next();
      if (str == null)
        break; 
    } 
    try {
      if (zlv instanceof Zl8)
        return ZR(iterator, 1); 
    } catch (NullPointerException nullPointerException) {
      throw a(null);
    } 
    try {
      if (zlv instanceof Zla)
        return ZR(iterator, 2); 
    } catch (NullPointerException nullPointerException) {
      throw a(null);
    } 
    try {
      if (zlv instanceof Zl3)
        return ZR(iterator, 3); 
    } catch (NullPointerException nullPointerException) {
      throw a(null);
    } 
    try {
      if (zlv instanceof Zth)
        return ZR(iterator, 2); 
    } catch (NullPointerException nullPointerException) {
      throw a(null);
    } 
    try {
      if (zlv instanceof Zt6)
        return false; 
    } catch (NullPointerException nullPointerException) {
      throw a(null);
    } 
    try {
      if (this.Zo)
        return ZR(iterator, 1); 
    } catch (NullPointerException nullPointerException) {
      throw a(null);
    } 
    return false;
  }
  
  private boolean ZR(Iterator<Zlv> paramIterator, int paramInt) {
    // Byte code:
    //   0: iconst_0
    //   1: istore #4
    //   3: invokestatic ZH : ()Ljava/lang/String;
    //   6: iconst_0
    //   7: istore #5
    //   9: astore_3
    //   10: aload_1
    //   11: invokeinterface hasNext : ()Z
    //   16: ifeq -> 166
    //   19: aload_1
    //   20: invokeinterface next : ()Ljava/lang/Object;
    //   25: checkcast org/yaml/Zlv
    //   28: astore #6
    //   30: aload #6
    //   32: instanceof org/yaml/Zld
    //   35: ifeq -> 49
    //   38: aload_3
    //   39: ifnonnull -> 10
    //   42: goto -> 49
    //   45: invokestatic a : (Ljava/lang/Exception;)Ljava/lang/Exception;
    //   48: athrow
    //   49: iinc #5, 1
    //   52: aload #6
    //   54: instanceof org/yaml/Zl8
    //   57: ifne -> 75
    //   60: aload #6
    //   62: instanceof org/yaml/Zlm
    //   65: ifeq -> 89
    //   68: goto -> 75
    //   71: invokestatic a : (Ljava/lang/Exception;)Ljava/lang/Exception;
    //   74: athrow
    //   75: iinc #4, 1
    //   78: aload_3
    //   79: ifnonnull -> 151
    //   82: goto -> 89
    //   85: invokestatic a : (Ljava/lang/Exception;)Ljava/lang/Exception;
    //   88: athrow
    //   89: aload #6
    //   91: instanceof org/yaml/Zle
    //   94: ifne -> 119
    //   97: goto -> 104
    //   100: invokestatic a : (Ljava/lang/Exception;)Ljava/lang/Exception;
    //   103: athrow
    //   104: aload #6
    //   106: instanceof org/yaml/Zlp
    //   109: ifeq -> 133
    //   112: goto -> 119
    //   115: invokestatic a : (Ljava/lang/Exception;)Ljava/lang/Exception;
    //   118: athrow
    //   119: iinc #4, -1
    //   122: aload_3
    //   123: ifnonnull -> 151
    //   126: goto -> 133
    //   129: invokestatic a : (Ljava/lang/Exception;)Ljava/lang/Exception;
    //   132: athrow
    //   133: aload #6
    //   135: instanceof org/yaml/Zt6
    //   138: ifeq -> 151
    //   141: goto -> 148
    //   144: invokestatic a : (Ljava/lang/Exception;)Ljava/lang/Exception;
    //   147: athrow
    //   148: iconst_m1
    //   149: istore #4
    //   151: iload #4
    //   153: ifge -> 162
    //   156: iconst_0
    //   157: ireturn
    //   158: invokestatic a : (Ljava/lang/Exception;)Ljava/lang/Exception;
    //   161: athrow
    //   162: aload_3
    //   163: ifnonnull -> 10
    //   166: iload #5
    //   168: iload_2
    //   169: if_icmpge -> 180
    //   172: iconst_1
    //   173: goto -> 181
    //   176: invokestatic a : (Ljava/lang/Exception;)Ljava/lang/Exception;
    //   179: athrow
    //   180: iconst_0
    //   181: ireturn
    // Exception table:
    //   from	to	target	type
    //   30	42	45	java/lang/NullPointerException
    //   49	68	71	java/lang/NullPointerException
    //   60	82	85	java/lang/NullPointerException
    //   75	97	100	java/lang/NullPointerException
    //   89	112	115	java/lang/NullPointerException
    //   104	126	129	java/lang/NullPointerException
    //   119	141	144	java/lang/NullPointerException
    //   151	158	158	java/lang/NullPointerException
    //   166	176	176	java/lang/NullPointerException
  }
  
  private void Zq(boolean paramBoolean1, boolean paramBoolean2) {
    // Byte code:
    //   0: invokestatic ZH : ()Ljava/lang/String;
    //   3: aload_0
    //   4: getfield Zg : Lorg/yaml/Zq;
    //   7: aload_0
    //   8: getfield Zn : Ljava/lang/Integer;
    //   11: invokevirtual Zq : (Ljava/lang/Object;)V
    //   14: astore_3
    //   15: aload_0
    //   16: getfield Zn : Ljava/lang/Integer;
    //   19: ifnonnull -> 74
    //   22: iload_1
    //   23: ifeq -> 55
    //   26: goto -> 33
    //   29: invokestatic a : (Ljava/lang/Exception;)Ljava/lang/Exception;
    //   32: athrow
    //   33: aload_0
    //   34: aload_0
    //   35: getfield ZE : I
    //   38: invokestatic valueOf : (I)Ljava/lang/Integer;
    //   41: putfield Zn : Ljava/lang/Integer;
    //   44: aload_3
    //   45: ifnonnull -> 111
    //   48: goto -> 55
    //   51: invokestatic a : (Ljava/lang/Exception;)Ljava/lang/Exception;
    //   54: athrow
    //   55: aload_0
    //   56: iconst_0
    //   57: invokestatic valueOf : (I)Ljava/lang/Integer;
    //   60: putfield Zn : Ljava/lang/Integer;
    //   63: aload_3
    //   64: ifnonnull -> 111
    //   67: goto -> 74
    //   70: invokestatic a : (Ljava/lang/Exception;)Ljava/lang/Exception;
    //   73: athrow
    //   74: iload_2
    //   75: ifne -> 111
    //   78: goto -> 85
    //   81: invokestatic a : (Ljava/lang/Exception;)Ljava/lang/Exception;
    //   84: athrow
    //   85: aload_0
    //   86: aload_0
    //   87: getfield Zn : Ljava/lang/Integer;
    //   90: invokevirtual intValue : ()I
    //   93: aload_0
    //   94: getfield ZE : I
    //   97: iadd
    //   98: invokestatic valueOf : (I)Ljava/lang/Integer;
    //   101: putfield Zn : Ljava/lang/Integer;
    //   104: goto -> 111
    //   107: invokestatic a : (Ljava/lang/Exception;)Ljava/lang/Exception;
    //   110: athrow
    //   111: return
    // Exception table:
    //   from	to	target	type
    //   15	26	29	java/lang/NullPointerException
    //   22	48	51	java/lang/NullPointerException
    //   33	67	70	java/lang/NullPointerException
    //   55	78	81	java/lang/NullPointerException
    //   74	104	107	java/lang/NullPointerException
  }
  
  private void Zg(boolean paramBoolean1, boolean paramBoolean2, boolean paramBoolean3) throws IOException {
    // Byte code:
    //   0: aload_0
    //   1: iload_1
    //   2: putfield ZJ : Z
    //   5: invokestatic ZH : ()Ljava/lang/String;
    //   8: aload_0
    //   9: iload_2
    //   10: putfield ZR : Z
    //   13: aload_0
    //   14: iload_3
    //   15: putfield Zr : Z
    //   18: astore #4
    //   20: aload_0
    //   21: getfield Zw : Lorg/yaml/Zlv;
    //   24: instanceof org/yaml/Zl_
    //   27: ifeq -> 46
    //   30: aload_0
    //   31: invokespecial ZM : ()V
    //   34: aload #4
    //   36: ifnonnull -> 375
    //   39: goto -> 46
    //   42: invokestatic a : (Ljava/lang/Exception;)Ljava/lang/Exception;
    //   45: athrow
    //   46: aload_0
    //   47: getfield Zw : Lorg/yaml/Zlv;
    //   50: instanceof org/yaml/Zl4
    //   53: ifne -> 80
    //   56: goto -> 63
    //   59: invokestatic a : (Ljava/lang/Exception;)Ljava/lang/Exception;
    //   62: athrow
    //   63: aload_0
    //   64: getfield Zw : Lorg/yaml/Zlv;
    //   67: instanceof org/yaml/Zlm
    //   70: ifeq -> 334
    //   73: goto -> 80
    //   76: invokestatic a : (Ljava/lang/Exception;)Ljava/lang/Exception;
    //   79: athrow
    //   80: aload_0
    //   81: ldc '&'
    //   83: invokespecial ZZ : (Ljava/lang/String;)V
    //   86: aload_0
    //   87: invokespecial Zr : ()V
    //   90: aload_0
    //   91: getfield Zw : Lorg/yaml/Zlv;
    //   94: instanceof org/yaml/Zl4
    //   97: ifeq -> 123
    //   100: goto -> 107
    //   103: invokestatic a : (Ljava/lang/Exception;)Ljava/lang/Exception;
    //   106: athrow
    //   107: aload_0
    //   108: invokespecial Zg : ()V
    //   111: aload #4
    //   113: ifnonnull -> 375
    //   116: goto -> 123
    //   119: invokestatic a : (Ljava/lang/Exception;)Ljava/lang/Exception;
    //   122: athrow
    //   123: aload_0
    //   124: getfield Zw : Lorg/yaml/Zlv;
    //   127: instanceof org/yaml/Zla
    //   130: ifeq -> 237
    //   133: goto -> 140
    //   136: invokestatic a : (Ljava/lang/Exception;)Ljava/lang/Exception;
    //   139: athrow
    //   140: aload_0
    //   141: getfield Zk : I
    //   144: ifne -> 205
    //   147: goto -> 154
    //   150: invokestatic a : (Ljava/lang/Exception;)Ljava/lang/Exception;
    //   153: athrow
    //   154: aload_0
    //   155: getfield ZA : Ljava/lang/Boolean;
    //   158: invokevirtual booleanValue : ()Z
    //   161: ifne -> 205
    //   164: goto -> 171
    //   167: invokestatic a : (Ljava/lang/Exception;)Ljava/lang/Exception;
    //   170: athrow
    //   171: aload_0
    //   172: getfield Zw : Lorg/yaml/Zlv;
    //   175: checkcast org/yaml/Zla
    //   178: invokevirtual ZE : ()Z
    //   181: ifne -> 205
    //   184: goto -> 191
    //   187: invokestatic a : (Ljava/lang/Exception;)Ljava/lang/Exception;
    //   190: athrow
    //   191: aload_0
    //   192: invokespecial Zq : ()Z
    //   195: ifeq -> 221
    //   198: goto -> 205
    //   201: invokestatic a : (Ljava/lang/Exception;)Ljava/lang/Exception;
    //   204: athrow
    //   205: aload_0
    //   206: invokespecial ZL : ()V
    //   209: aload #4
    //   211: ifnonnull -> 375
    //   214: goto -> 221
    //   217: invokestatic a : (Ljava/lang/Exception;)Ljava/lang/Exception;
    //   220: athrow
    //   221: aload_0
    //   222: invokespecial Zk : ()V
    //   225: aload #4
    //   227: ifnonnull -> 375
    //   230: goto -> 237
    //   233: invokestatic a : (Ljava/lang/Exception;)Ljava/lang/Exception;
    //   236: athrow
    //   237: aload_0
    //   238: getfield Zk : I
    //   241: ifne -> 302
    //   244: goto -> 251
    //   247: invokestatic a : (Ljava/lang/Exception;)Ljava/lang/Exception;
    //   250: athrow
    //   251: aload_0
    //   252: getfield ZA : Ljava/lang/Boolean;
    //   255: invokevirtual booleanValue : ()Z
    //   258: ifne -> 302
    //   261: goto -> 268
    //   264: invokestatic a : (Ljava/lang/Exception;)Ljava/lang/Exception;
    //   267: athrow
    //   268: aload_0
    //   269: getfield Zw : Lorg/yaml/Zlv;
    //   272: checkcast org/yaml/Zl3
    //   275: invokevirtual ZE : ()Z
    //   278: ifne -> 302
    //   281: goto -> 288
    //   284: invokestatic a : (Ljava/lang/Exception;)Ljava/lang/Exception;
    //   287: athrow
    //   288: aload_0
    //   289: invokespecial ZR : ()Z
    //   292: ifeq -> 318
    //   295: goto -> 302
    //   298: invokestatic a : (Ljava/lang/Exception;)Ljava/lang/Exception;
    //   301: athrow
    //   302: aload_0
    //   303: invokespecial Zf : ()V
    //   306: aload #4
    //   308: ifnonnull -> 375
    //   311: goto -> 318
    //   314: invokestatic a : (Ljava/lang/Exception;)Ljava/lang/Exception;
    //   317: athrow
    //   318: aload_0
    //   319: invokespecial ZF : ()V
    //   322: aload #4
    //   324: ifnonnull -> 375
    //   327: goto -> 334
    //   330: invokestatic a : (Ljava/lang/Exception;)Ljava/lang/Exception;
    //   333: athrow
    //   334: new org/yaml/Zja
    //   337: dup
    //   338: new java/lang/StringBuilder
    //   341: dup
    //   342: invokespecial <init> : ()V
    //   345: sipush #29160
    //   348: sipush #10810
    //   351: invokestatic a : (II)Ljava/lang/String;
    //   354: invokevirtual append : (Ljava/lang/String;)Ljava/lang/StringBuilder;
    //   357: aload_0
    //   358: getfield Zw : Lorg/yaml/Zlv;
    //   361: invokevirtual append : (Ljava/lang/Object;)Ljava/lang/StringBuilder;
    //   364: invokevirtual toString : ()Ljava/lang/String;
    //   367: invokespecial <init> : (Ljava/lang/String;)V
    //   370: athrow
    //   371: invokestatic a : (Ljava/lang/Exception;)Ljava/lang/Exception;
    //   374: athrow
    //   375: return
    // Exception table:
    //   from	to	target	type
    //   20	39	42	java/io/IOException
    //   30	56	59	java/io/IOException
    //   46	73	76	java/io/IOException
    //   63	100	103	java/io/IOException
    //   80	116	119	java/io/IOException
    //   107	133	136	java/io/IOException
    //   123	147	150	java/io/IOException
    //   140	164	167	java/io/IOException
    //   154	184	187	java/io/IOException
    //   171	198	201	java/io/IOException
    //   191	214	217	java/io/IOException
    //   205	230	233	java/io/IOException
    //   221	244	247	java/io/IOException
    //   237	261	264	java/io/IOException
    //   251	281	284	java/io/IOException
    //   268	295	298	java/io/IOException
    //   288	311	314	java/io/IOException
    //   302	327	330	java/io/IOException
    //   318	371	371	java/io/IOException
  }
  
  private void ZM() throws IOException {
    try {
      if (!(this.Zw instanceof Zl_))
        throw new Zja(a(29176, -23073)); 
    } catch (IOException iOException) {
      throw a(null);
    } 
    ZZ("*");
    this.Zv = this.Zu.ZE();
  }
  
  private void Zg() throws IOException {
    Zq(true, false);
    ZT();
    this.Zn = this.Zg.ZE();
    this.Zv = this.Zu.ZE();
  }
  
  private void ZL() throws IOException {
    try {
      Zv("[", true, true, false);
      this.Zk++;
      Zq(true, false);
      if (this.Zx.booleanValue())
        ZJ(); 
    } catch (IOException iOException) {
      throw a(null);
    } 
    this.Zv = new Zjn(this, null);
  }
  
  private void Zf() throws IOException {
    try {
      Zv("{", true, true, false);
      this.Zk++;
      Zq(true, false);
      if (this.Zx.booleanValue())
        ZJ(); 
    } catch (IOException iOException) {
      throw a(null);
    } 
    this.Zv = new Zjr(this, null);
  }
  
  private void Zk() throws IOException {
    // Byte code:
    //   0: aload_0
    //   1: getfield ZR : Z
    //   4: ifeq -> 29
    //   7: aload_0
    //   8: getfield Zh : Z
    //   11: ifne -> 29
    //   14: goto -> 21
    //   17: invokestatic a : (Ljava/lang/Exception;)Ljava/lang/Exception;
    //   20: athrow
    //   21: iconst_1
    //   22: goto -> 30
    //   25: invokestatic a : (Ljava/lang/Exception;)Ljava/lang/Exception;
    //   28: athrow
    //   29: iconst_0
    //   30: istore_1
    //   31: aload_0
    //   32: iconst_0
    //   33: iload_1
    //   34: invokespecial Zq : (ZZ)V
    //   37: aload_0
    //   38: new org/yaml/Zlt
    //   41: dup
    //   42: aload_0
    //   43: aconst_null
    //   44: invokespecial <init> : (Lorg/yaml/Zb;Lorg/yaml/Zjq;)V
    //   47: putfield Zv : Lorg/yaml/Zd;
    //   50: return
    // Exception table:
    //   from	to	target	type
    //   0	14	17	java/io/IOException
    //   7	25	25	java/io/IOException
  }
  
  private void ZF() throws IOException {
    Zq(false, false);
    this.Zv = new Zg(this, null);
  }
  
  private boolean Zc(Zlv paramZlv) {
    try {
      if (!paramZlv.Zz(Zj7.Scalar))
        return false; 
    } catch (NullPointerException nullPointerException) {
      throw a(null);
    } 
    Zl4 zl4 = (Zl4)paramZlv;
    Zjm zjm = zl4.ZD();
    try {
      if (zjm != Zjm.FOLDED) {
        try {
          if (zjm == Zjm.LITERAL);
        } catch (NullPointerException nullPointerException) {
          throw a(null);
        } 
        return false;
      } 
    } catch (NullPointerException nullPointerException) {
      throw a(null);
    } 
  }
  
  private boolean Zq() {
    try {
      if (this.Zw instanceof Zla)
        try {
          if (!this.Zc.isEmpty())
            try {
              if (this.Zc.peek() instanceof Zlu);
            } catch (NullPointerException nullPointerException) {
              throw a(null);
            }  
        } catch (NullPointerException nullPointerException) {
          throw a(null);
        }  
    } catch (NullPointerException nullPointerException) {
      throw a(null);
    } 
    return false;
  }
  
  private boolean ZR() {
    try {
      if (this.Zw instanceof Zl3)
        try {
          if (!this.Zc.isEmpty())
            try {
              if (this.Zc.peek() instanceof Zl5);
            } catch (NullPointerException nullPointerException) {
              throw a(null);
            }  
        } catch (NullPointerException nullPointerException) {
          throw a(null);
        }  
    } catch (NullPointerException nullPointerException) {
      throw a(null);
    } 
    return false;
  }
  
  private boolean ZS() {
    try {
      if (this.Zw instanceof Zl8)
        try {
          if (!this.Zc.isEmpty()) {
            Zlv zlv = this.Zc.peek();
            if (zlv instanceof Zl4) {
              Zl4 zl4 = (Zl4)zlv;
              try {
                if (zl4.ZF() == null)
                  try {
                    if (zl4.Zc() == null)
                      try {
                        if (zl4.Zn() != null)
                          try {
                            if (zl4.Zw().length() == 0);
                          } catch (NullPointerException nullPointerException) {
                            throw a(null);
                          }  
                      } catch (NullPointerException nullPointerException) {
                        throw a(null);
                      }  
                  } catch (NullPointerException nullPointerException) {
                    throw a(null);
                  }  
              } catch (NullPointerException nullPointerException) {
                throw a(null);
              } 
              return false;
            } 
            return false;
          } 
          return false;
        } catch (NullPointerException nullPointerException) {
          throw a(null);
        }  
    } catch (NullPointerException nullPointerException) {
      throw a(null);
    } 
    return false;
  }
  
  private boolean Zi() {
    // Byte code:
    //   0: iconst_0
    //   1: istore_1
    //   2: aload_0
    //   3: getfield Zw : Lorg/yaml/Zlv;
    //   6: instanceof org/yaml/Zlg
    //   9: ifeq -> 80
    //   12: aload_0
    //   13: getfield Zw : Lorg/yaml/Zlv;
    //   16: checkcast org/yaml/Zlg
    //   19: invokevirtual ZF : ()Ljava/lang/String;
    //   22: ifnull -> 80
    //   25: goto -> 32
    //   28: invokestatic a : (Ljava/lang/Exception;)Ljava/lang/Exception;
    //   31: athrow
    //   32: aload_0
    //   33: getfield ZD : Ljava/lang/String;
    //   36: ifnonnull -> 70
    //   39: goto -> 46
    //   42: invokestatic a : (Ljava/lang/Exception;)Ljava/lang/Exception;
    //   45: athrow
    //   46: aload_0
    //   47: aload_0
    //   48: getfield Zw : Lorg/yaml/Zlv;
    //   51: checkcast org/yaml/Zlg
    //   54: invokevirtual ZF : ()Ljava/lang/String;
    //   57: invokestatic ZO : (Ljava/lang/String;)Ljava/lang/String;
    //   60: putfield ZD : Ljava/lang/String;
    //   63: goto -> 70
    //   66: invokestatic a : (Ljava/lang/Exception;)Ljava/lang/Exception;
    //   69: athrow
    //   70: iload_1
    //   71: aload_0
    //   72: getfield ZD : Ljava/lang/String;
    //   75: invokevirtual length : ()I
    //   78: iadd
    //   79: istore_1
    //   80: aconst_null
    //   81: astore_2
    //   82: aload_0
    //   83: getfield Zw : Lorg/yaml/Zlv;
    //   86: instanceof org/yaml/Zl4
    //   89: ifeq -> 106
    //   92: aload_0
    //   93: getfield Zw : Lorg/yaml/Zlv;
    //   96: checkcast org/yaml/Zl4
    //   99: invokevirtual Zc : ()Ljava/lang/String;
    //   102: astore_2
    //   103: goto -> 127
    //   106: aload_0
    //   107: getfield Zw : Lorg/yaml/Zlv;
    //   110: instanceof org/yaml/Zlm
    //   113: ifeq -> 127
    //   116: aload_0
    //   117: getfield Zw : Lorg/yaml/Zlv;
    //   120: checkcast org/yaml/Zlm
    //   123: invokevirtual ZA : ()Ljava/lang/String;
    //   126: astore_2
    //   127: aload_2
    //   128: ifnull -> 171
    //   131: aload_0
    //   132: getfield Zs : Ljava/lang/String;
    //   135: ifnonnull -> 161
    //   138: goto -> 145
    //   141: invokestatic a : (Ljava/lang/Exception;)Ljava/lang/Exception;
    //   144: athrow
    //   145: aload_0
    //   146: aload_0
    //   147: aload_2
    //   148: invokespecial Zq : (Ljava/lang/String;)Ljava/lang/String;
    //   151: putfield Zs : Ljava/lang/String;
    //   154: goto -> 161
    //   157: invokestatic a : (Ljava/lang/Exception;)Ljava/lang/Exception;
    //   160: athrow
    //   161: iload_1
    //   162: aload_0
    //   163: getfield Zs : Ljava/lang/String;
    //   166: invokevirtual length : ()I
    //   169: iadd
    //   170: istore_1
    //   171: aload_0
    //   172: getfield Zw : Lorg/yaml/Zlv;
    //   175: instanceof org/yaml/Zl4
    //   178: ifeq -> 233
    //   181: aload_0
    //   182: getfield ZF : Lorg/yaml/Zjb;
    //   185: ifnonnull -> 220
    //   188: goto -> 195
    //   191: invokestatic a : (Ljava/lang/Exception;)Ljava/lang/Exception;
    //   194: athrow
    //   195: aload_0
    //   196: aload_0
    //   197: aload_0
    //   198: getfield Zw : Lorg/yaml/Zlv;
    //   201: checkcast org/yaml/Zl4
    //   204: invokevirtual Zw : ()Ljava/lang/String;
    //   207: invokespecial ZD : (Ljava/lang/String;)Lorg/yaml/Zjb;
    //   210: putfield ZF : Lorg/yaml/Zjb;
    //   213: goto -> 220
    //   216: invokestatic a : (Ljava/lang/Exception;)Ljava/lang/Exception;
    //   219: athrow
    //   220: iload_1
    //   221: aload_0
    //   222: getfield ZF : Lorg/yaml/Zjb;
    //   225: invokevirtual Zk : ()Ljava/lang/String;
    //   228: invokevirtual length : ()I
    //   231: iadd
    //   232: istore_1
    //   233: iload_1
    //   234: aload_0
    //   235: getfield ZT : I
    //   238: if_icmpge -> 345
    //   241: aload_0
    //   242: getfield Zw : Lorg/yaml/Zlv;
    //   245: instanceof org/yaml/Zl_
    //   248: ifne -> 337
    //   251: goto -> 258
    //   254: invokestatic a : (Ljava/lang/Exception;)Ljava/lang/Exception;
    //   257: athrow
    //   258: aload_0
    //   259: getfield Zw : Lorg/yaml/Zlv;
    //   262: instanceof org/yaml/Zl4
    //   265: ifeq -> 309
    //   268: goto -> 275
    //   271: invokestatic a : (Ljava/lang/Exception;)Ljava/lang/Exception;
    //   274: athrow
    //   275: aload_0
    //   276: getfield ZF : Lorg/yaml/Zjb;
    //   279: invokevirtual Zh : ()Z
    //   282: ifne -> 309
    //   285: goto -> 292
    //   288: invokestatic a : (Ljava/lang/Exception;)Ljava/lang/Exception;
    //   291: athrow
    //   292: aload_0
    //   293: getfield ZF : Lorg/yaml/Zjb;
    //   296: invokevirtual Zf : ()Z
    //   299: ifeq -> 337
    //   302: goto -> 309
    //   305: invokestatic a : (Ljava/lang/Exception;)Ljava/lang/Exception;
    //   308: athrow
    //   309: aload_0
    //   310: invokespecial Zq : ()Z
    //   313: ifne -> 337
    //   316: goto -> 323
    //   319: invokestatic a : (Ljava/lang/Exception;)Ljava/lang/Exception;
    //   322: athrow
    //   323: aload_0
    //   324: invokespecial ZR : ()Z
    //   327: ifeq -> 345
    //   330: goto -> 337
    //   333: invokestatic a : (Ljava/lang/Exception;)Ljava/lang/Exception;
    //   336: athrow
    //   337: iconst_1
    //   338: goto -> 346
    //   341: invokestatic a : (Ljava/lang/Exception;)Ljava/lang/Exception;
    //   344: athrow
    //   345: iconst_0
    //   346: ireturn
    // Exception table:
    //   from	to	target	type
    //   2	25	28	java/lang/NullPointerException
    //   12	39	42	java/lang/NullPointerException
    //   32	63	66	java/lang/NullPointerException
    //   127	138	141	java/lang/NullPointerException
    //   131	154	157	java/lang/NullPointerException
    //   171	188	191	java/lang/NullPointerException
    //   181	213	216	java/lang/NullPointerException
    //   233	251	254	java/lang/NullPointerException
    //   241	268	271	java/lang/NullPointerException
    //   258	285	288	java/lang/NullPointerException
    //   275	302	305	java/lang/NullPointerException
    //   292	316	319	java/lang/NullPointerException
    //   309	330	333	java/lang/NullPointerException
    //   323	341	341	java/lang/NullPointerException
  }
  
  private void ZZ(String paramString) throws IOException {
    Zlg zlg = (Zlg)this.Zw;
    try {
      if (zlg.ZF() == null) {
        this.ZD = null;
        return;
      } 
    } catch (IOException iOException) {
      throw a(null);
    } 
    try {
      if (this.ZD == null)
        this.ZD = ZO(zlg.ZF()); 
    } catch (IOException iOException) {
      throw a(null);
    } 
    Zv(paramString + this.ZD, true, false, false);
    this.ZD = null;
  }
  
  private void Zr() throws IOException {
    // Byte code:
    //   0: aconst_null
    //   1: astore_1
    //   2: aload_0
    //   3: getfield Zw : Lorg/yaml/Zlv;
    //   6: instanceof org/yaml/Zl4
    //   9: ifeq -> 172
    //   12: aload_0
    //   13: getfield Zw : Lorg/yaml/Zlv;
    //   16: checkcast org/yaml/Zl4
    //   19: astore_2
    //   20: aload_2
    //   21: invokevirtual Zc : ()Ljava/lang/String;
    //   24: astore_1
    //   25: aload_0
    //   26: getfield ZS : Lorg/yaml/Zjm;
    //   29: ifnonnull -> 47
    //   32: aload_0
    //   33: aload_0
    //   34: invokespecial Zu : ()Lorg/yaml/Zjm;
    //   37: putfield ZS : Lorg/yaml/Zjm;
    //   40: goto -> 47
    //   43: invokestatic a : (Ljava/lang/Exception;)Ljava/lang/Exception;
    //   46: athrow
    //   47: aload_0
    //   48: getfield ZA : Ljava/lang/Boolean;
    //   51: invokevirtual booleanValue : ()Z
    //   54: ifeq -> 68
    //   57: aload_1
    //   58: ifnonnull -> 140
    //   61: goto -> 68
    //   64: invokestatic a : (Ljava/lang/Exception;)Ljava/lang/Exception;
    //   67: athrow
    //   68: aload_0
    //   69: getfield ZS : Lorg/yaml/Zjm;
    //   72: ifnonnull -> 99
    //   75: goto -> 82
    //   78: invokestatic a : (Ljava/lang/Exception;)Ljava/lang/Exception;
    //   81: athrow
    //   82: aload_2
    //   83: invokevirtual Zn : ()Lorg/yaml/Zgr;
    //   86: invokevirtual ZW : ()Z
    //   89: ifne -> 130
    //   92: goto -> 99
    //   95: invokestatic a : (Ljava/lang/Exception;)Ljava/lang/Exception;
    //   98: athrow
    //   99: aload_0
    //   100: getfield ZS : Lorg/yaml/Zjm;
    //   103: ifnull -> 140
    //   106: goto -> 113
    //   109: invokestatic a : (Ljava/lang/Exception;)Ljava/lang/Exception;
    //   112: athrow
    //   113: aload_2
    //   114: invokevirtual Zn : ()Lorg/yaml/Zgr;
    //   117: invokevirtual Zm : ()Z
    //   120: ifeq -> 140
    //   123: goto -> 130
    //   126: invokestatic a : (Ljava/lang/Exception;)Ljava/lang/Exception;
    //   129: athrow
    //   130: aload_0
    //   131: aconst_null
    //   132: putfield Zs : Ljava/lang/String;
    //   135: return
    //   136: invokestatic a : (Ljava/lang/Exception;)Ljava/lang/Exception;
    //   139: athrow
    //   140: aload_2
    //   141: invokevirtual Zn : ()Lorg/yaml/Zgr;
    //   144: invokevirtual ZW : ()Z
    //   147: ifeq -> 169
    //   150: aload_1
    //   151: ifnonnull -> 169
    //   154: goto -> 161
    //   157: invokestatic a : (Ljava/lang/Exception;)Ljava/lang/Exception;
    //   160: athrow
    //   161: ldc '!'
    //   163: astore_1
    //   164: aload_0
    //   165: aconst_null
    //   166: putfield Zs : Ljava/lang/String;
    //   169: goto -> 230
    //   172: aload_0
    //   173: getfield Zw : Lorg/yaml/Zlv;
    //   176: checkcast org/yaml/Zlm
    //   179: astore_2
    //   180: aload_2
    //   181: invokevirtual ZA : ()Ljava/lang/String;
    //   184: astore_1
    //   185: aload_0
    //   186: getfield ZA : Ljava/lang/Boolean;
    //   189: invokevirtual booleanValue : ()Z
    //   192: ifeq -> 206
    //   195: aload_1
    //   196: ifnonnull -> 230
    //   199: goto -> 206
    //   202: invokestatic a : (Ljava/lang/Exception;)Ljava/lang/Exception;
    //   205: athrow
    //   206: aload_2
    //   207: invokevirtual Zp : ()Z
    //   210: ifeq -> 230
    //   213: goto -> 220
    //   216: invokestatic a : (Ljava/lang/Exception;)Ljava/lang/Exception;
    //   219: athrow
    //   220: aload_0
    //   221: aconst_null
    //   222: putfield Zs : Ljava/lang/String;
    //   225: return
    //   226: invokestatic a : (Ljava/lang/Exception;)Ljava/lang/Exception;
    //   229: athrow
    //   230: aload_1
    //   231: ifnonnull -> 255
    //   234: new org/yaml/Zja
    //   237: dup
    //   238: sipush #29161
    //   241: sipush #6917
    //   244: invokestatic a : (II)Ljava/lang/String;
    //   247: invokespecial <init> : (Ljava/lang/String;)V
    //   250: athrow
    //   251: invokestatic a : (Ljava/lang/Exception;)Ljava/lang/Exception;
    //   254: athrow
    //   255: aload_0
    //   256: getfield Zs : Ljava/lang/String;
    //   259: ifnonnull -> 278
    //   262: aload_0
    //   263: aload_0
    //   264: aload_1
    //   265: invokespecial Zq : (Ljava/lang/String;)Ljava/lang/String;
    //   268: putfield Zs : Ljava/lang/String;
    //   271: goto -> 278
    //   274: invokestatic a : (Ljava/lang/Exception;)Ljava/lang/Exception;
    //   277: athrow
    //   278: aload_0
    //   279: aload_0
    //   280: getfield Zs : Ljava/lang/String;
    //   283: iconst_1
    //   284: iconst_0
    //   285: iconst_0
    //   286: invokevirtual Zv : (Ljava/lang/String;ZZZ)V
    //   289: aload_0
    //   290: aconst_null
    //   291: putfield Zs : Ljava/lang/String;
    //   294: return
    // Exception table:
    //   from	to	target	type
    //   25	40	43	java/io/IOException
    //   47	61	64	java/io/IOException
    //   57	75	78	java/io/IOException
    //   68	92	95	java/io/IOException
    //   82	106	109	java/io/IOException
    //   99	123	126	java/io/IOException
    //   113	136	136	java/io/IOException
    //   140	154	157	java/io/IOException
    //   185	199	202	java/io/IOException
    //   195	213	216	java/io/IOException
    //   206	226	226	java/io/IOException
    //   230	251	251	java/io/IOException
    //   255	271	274	java/io/IOException
  }
  
  private Zjm Zu() {
    // Byte code:
    //   0: aload_0
    //   1: getfield Zw : Lorg/yaml/Zlv;
    //   4: checkcast org/yaml/Zl4
    //   7: astore_1
    //   8: aload_0
    //   9: getfield ZF : Lorg/yaml/Zjb;
    //   12: ifnonnull -> 34
    //   15: aload_0
    //   16: aload_0
    //   17: aload_1
    //   18: invokevirtual Zw : ()Ljava/lang/String;
    //   21: invokespecial ZD : (Ljava/lang/String;)Lorg/yaml/Zjb;
    //   24: putfield ZF : Lorg/yaml/Zjb;
    //   27: goto -> 34
    //   30: invokestatic a : (Ljava/lang/Exception;)Ljava/lang/Exception;
    //   33: athrow
    //   34: aload_1
    //   35: invokevirtual ZS : ()Z
    //   38: ifne -> 58
    //   41: aload_1
    //   42: invokevirtual ZD : ()Lorg/yaml/Zjm;
    //   45: getstatic org/yaml/Zjm.DOUBLE_QUOTED : Lorg/yaml/Zjm;
    //   48: if_acmpeq -> 75
    //   51: goto -> 58
    //   54: invokestatic a : (Ljava/lang/Exception;)Ljava/lang/Exception;
    //   57: athrow
    //   58: aload_0
    //   59: getfield ZA : Ljava/lang/Boolean;
    //   62: invokevirtual booleanValue : ()Z
    //   65: ifeq -> 83
    //   68: goto -> 75
    //   71: invokestatic a : (Ljava/lang/Exception;)Ljava/lang/Exception;
    //   74: athrow
    //   75: getstatic org/yaml/Zjm.DOUBLE_QUOTED : Lorg/yaml/Zjm;
    //   78: areturn
    //   79: invokestatic a : (Ljava/lang/Exception;)Ljava/lang/Exception;
    //   82: athrow
    //   83: aload_1
    //   84: invokevirtual ZS : ()Z
    //   87: ifeq -> 223
    //   90: aload_1
    //   91: invokevirtual Zn : ()Lorg/yaml/Zgr;
    //   94: invokevirtual ZW : ()Z
    //   97: ifeq -> 223
    //   100: goto -> 107
    //   103: invokestatic a : (Ljava/lang/Exception;)Ljava/lang/Exception;
    //   106: athrow
    //   107: aload_0
    //   108: getfield Zr : Z
    //   111: ifeq -> 155
    //   114: goto -> 121
    //   117: invokestatic a : (Ljava/lang/Exception;)Ljava/lang/Exception;
    //   120: athrow
    //   121: aload_0
    //   122: getfield ZF : Lorg/yaml/Zjb;
    //   125: invokevirtual Zh : ()Z
    //   128: ifne -> 223
    //   131: goto -> 138
    //   134: invokestatic a : (Ljava/lang/Exception;)Ljava/lang/Exception;
    //   137: athrow
    //   138: aload_0
    //   139: getfield ZF : Lorg/yaml/Zjb;
    //   142: invokevirtual Zf : ()Z
    //   145: ifne -> 223
    //   148: goto -> 155
    //   151: invokestatic a : (Ljava/lang/Exception;)Ljava/lang/Exception;
    //   154: athrow
    //   155: aload_0
    //   156: getfield Zk : I
    //   159: ifeq -> 186
    //   162: goto -> 169
    //   165: invokestatic a : (Ljava/lang/Exception;)Ljava/lang/Exception;
    //   168: athrow
    //   169: aload_0
    //   170: getfield ZF : Lorg/yaml/Zjb;
    //   173: invokevirtual Zx : ()Z
    //   176: ifne -> 217
    //   179: goto -> 186
    //   182: invokestatic a : (Ljava/lang/Exception;)Ljava/lang/Exception;
    //   185: athrow
    //   186: aload_0
    //   187: getfield Zk : I
    //   190: ifne -> 223
    //   193: goto -> 200
    //   196: invokestatic a : (Ljava/lang/Exception;)Ljava/lang/Exception;
    //   199: athrow
    //   200: aload_0
    //   201: getfield ZF : Lorg/yaml/Zjb;
    //   204: invokevirtual ZA : ()Z
    //   207: ifeq -> 223
    //   210: goto -> 217
    //   213: invokestatic a : (Ljava/lang/Exception;)Ljava/lang/Exception;
    //   216: athrow
    //   217: aconst_null
    //   218: areturn
    //   219: invokestatic a : (Ljava/lang/Exception;)Ljava/lang/Exception;
    //   222: athrow
    //   223: aload_1
    //   224: invokevirtual ZS : ()Z
    //   227: ifne -> 318
    //   230: aload_1
    //   231: invokevirtual ZD : ()Lorg/yaml/Zjm;
    //   234: getstatic org/yaml/Zjm.LITERAL : Lorg/yaml/Zjm;
    //   237: if_acmpeq -> 264
    //   240: goto -> 247
    //   243: invokestatic a : (Ljava/lang/Exception;)Ljava/lang/Exception;
    //   246: athrow
    //   247: aload_1
    //   248: invokevirtual ZD : ()Lorg/yaml/Zjm;
    //   251: getstatic org/yaml/Zjm.FOLDED : Lorg/yaml/Zjm;
    //   254: if_acmpne -> 318
    //   257: goto -> 264
    //   260: invokestatic a : (Ljava/lang/Exception;)Ljava/lang/Exception;
    //   263: athrow
    //   264: aload_0
    //   265: getfield Zk : I
    //   268: ifne -> 318
    //   271: goto -> 278
    //   274: invokestatic a : (Ljava/lang/Exception;)Ljava/lang/Exception;
    //   277: athrow
    //   278: aload_0
    //   279: getfield Zr : Z
    //   282: ifne -> 318
    //   285: goto -> 292
    //   288: invokestatic a : (Ljava/lang/Exception;)Ljava/lang/Exception;
    //   291: athrow
    //   292: aload_0
    //   293: getfield ZF : Lorg/yaml/Zjb;
    //   296: invokevirtual ZX : ()Z
    //   299: ifeq -> 318
    //   302: goto -> 309
    //   305: invokestatic a : (Ljava/lang/Exception;)Ljava/lang/Exception;
    //   308: athrow
    //   309: aload_1
    //   310: invokevirtual ZD : ()Lorg/yaml/Zjm;
    //   313: areturn
    //   314: invokestatic a : (Ljava/lang/Exception;)Ljava/lang/Exception;
    //   317: athrow
    //   318: aload_1
    //   319: invokevirtual ZS : ()Z
    //   322: ifne -> 342
    //   325: aload_1
    //   326: invokevirtual ZD : ()Lorg/yaml/Zjm;
    //   329: getstatic org/yaml/Zjm.SINGLE_QUOTED : Lorg/yaml/Zjm;
    //   332: if_acmpne -> 398
    //   335: goto -> 342
    //   338: invokestatic a : (Ljava/lang/Exception;)Ljava/lang/Exception;
    //   341: athrow
    //   342: aload_0
    //   343: getfield ZF : Lorg/yaml/Zjb;
    //   346: invokevirtual ZU : ()Z
    //   349: ifeq -> 398
    //   352: goto -> 359
    //   355: invokestatic a : (Ljava/lang/Exception;)Ljava/lang/Exception;
    //   358: athrow
    //   359: aload_0
    //   360: getfield Zr : Z
    //   363: ifeq -> 390
    //   366: goto -> 373
    //   369: invokestatic a : (Ljava/lang/Exception;)Ljava/lang/Exception;
    //   372: athrow
    //   373: aload_0
    //   374: getfield ZF : Lorg/yaml/Zjb;
    //   377: invokevirtual Zf : ()Z
    //   380: ifne -> 398
    //   383: goto -> 390
    //   386: invokestatic a : (Ljava/lang/Exception;)Ljava/lang/Exception;
    //   389: athrow
    //   390: getstatic org/yaml/Zjm.SINGLE_QUOTED : Lorg/yaml/Zjm;
    //   393: areturn
    //   394: invokestatic a : (Ljava/lang/Exception;)Ljava/lang/Exception;
    //   397: athrow
    //   398: getstatic org/yaml/Zjm.DOUBLE_QUOTED : Lorg/yaml/Zjm;
    //   401: areturn
    // Exception table:
    //   from	to	target	type
    //   8	27	30	java/lang/NullPointerException
    //   34	51	54	java/lang/NullPointerException
    //   41	68	71	java/lang/NullPointerException
    //   58	79	79	java/lang/NullPointerException
    //   83	100	103	java/lang/NullPointerException
    //   90	114	117	java/lang/NullPointerException
    //   107	131	134	java/lang/NullPointerException
    //   121	148	151	java/lang/NullPointerException
    //   138	162	165	java/lang/NullPointerException
    //   155	179	182	java/lang/NullPointerException
    //   169	193	196	java/lang/NullPointerException
    //   186	210	213	java/lang/NullPointerException
    //   200	219	219	java/lang/NullPointerException
    //   223	240	243	java/lang/NullPointerException
    //   230	257	260	java/lang/NullPointerException
    //   247	271	274	java/lang/NullPointerException
    //   264	285	288	java/lang/NullPointerException
    //   278	302	305	java/lang/NullPointerException
    //   292	314	314	java/lang/NullPointerException
    //   318	335	338	java/lang/NullPointerException
    //   325	352	355	java/lang/NullPointerException
    //   342	366	369	java/lang/NullPointerException
    //   359	383	386	java/lang/NullPointerException
    //   373	394	394	java/lang/NullPointerException
  }
  
  private void ZT() throws IOException {
    // Byte code:
    //   0: invokestatic ZH : ()Ljava/lang/String;
    //   3: aload_0
    //   4: getfield Zw : Lorg/yaml/Zlv;
    //   7: checkcast org/yaml/Zl4
    //   10: astore_2
    //   11: astore_1
    //   12: aload_0
    //   13: getfield ZF : Lorg/yaml/Zjb;
    //   16: ifnonnull -> 38
    //   19: aload_0
    //   20: aload_0
    //   21: aload_2
    //   22: invokevirtual Zw : ()Ljava/lang/String;
    //   25: invokespecial ZD : (Ljava/lang/String;)Lorg/yaml/Zjb;
    //   28: putfield ZF : Lorg/yaml/Zjb;
    //   31: goto -> 38
    //   34: invokestatic a : (Ljava/lang/Exception;)Ljava/lang/Exception;
    //   37: athrow
    //   38: aload_0
    //   39: getfield ZS : Lorg/yaml/Zjm;
    //   42: ifnonnull -> 60
    //   45: aload_0
    //   46: aload_0
    //   47: invokespecial Zu : ()Lorg/yaml/Zjm;
    //   50: putfield ZS : Lorg/yaml/Zjm;
    //   53: goto -> 60
    //   56: invokestatic a : (Ljava/lang/Exception;)Ljava/lang/Exception;
    //   59: athrow
    //   60: aload_0
    //   61: getfield Zr : Z
    //   64: ifne -> 89
    //   67: aload_0
    //   68: getfield ZW : Z
    //   71: ifeq -> 89
    //   74: goto -> 81
    //   77: invokestatic a : (Ljava/lang/Exception;)Ljava/lang/Exception;
    //   80: athrow
    //   81: iconst_1
    //   82: goto -> 90
    //   85: invokestatic a : (Ljava/lang/Exception;)Ljava/lang/Exception;
    //   88: athrow
    //   89: iconst_0
    //   90: istore_3
    //   91: aload_0
    //   92: getfield ZS : Lorg/yaml/Zjm;
    //   95: ifnonnull -> 121
    //   98: aload_0
    //   99: aload_0
    //   100: getfield ZF : Lorg/yaml/Zjb;
    //   103: invokevirtual Zk : ()Ljava/lang/String;
    //   106: iload_3
    //   107: invokevirtual Zq : (Ljava/lang/String;Z)V
    //   110: aload_1
    //   111: ifnonnull -> 300
    //   114: goto -> 121
    //   117: invokestatic a : (Ljava/lang/Exception;)Ljava/lang/Exception;
    //   120: athrow
    //   121: getstatic org/yaml/Zjq.Zs : [I
    //   124: aload_0
    //   125: getfield ZS : Lorg/yaml/Zjm;
    //   128: invokevirtual ordinal : ()I
    //   131: iaload
    //   132: tableswitch default -> 259, 1 -> 168, 2 -> 191, 3 -> 214, 4 -> 237
    //   164: invokestatic a : (Ljava/lang/Exception;)Ljava/lang/Exception;
    //   167: athrow
    //   168: aload_0
    //   169: aload_0
    //   170: getfield ZF : Lorg/yaml/Zjb;
    //   173: invokevirtual Zk : ()Ljava/lang/String;
    //   176: iload_3
    //   177: invokespecial ZV : (Ljava/lang/String;Z)V
    //   180: aload_1
    //   181: ifnonnull -> 300
    //   184: goto -> 191
    //   187: invokestatic a : (Ljava/lang/Exception;)Ljava/lang/Exception;
    //   190: athrow
    //   191: aload_0
    //   192: aload_0
    //   193: getfield ZF : Lorg/yaml/Zjb;
    //   196: invokevirtual Zk : ()Ljava/lang/String;
    //   199: iload_3
    //   200: invokespecial ZR : (Ljava/lang/String;Z)V
    //   203: aload_1
    //   204: ifnonnull -> 300
    //   207: goto -> 214
    //   210: invokestatic a : (Ljava/lang/Exception;)Ljava/lang/Exception;
    //   213: athrow
    //   214: aload_0
    //   215: aload_0
    //   216: getfield ZF : Lorg/yaml/Zjb;
    //   219: invokevirtual Zk : ()Ljava/lang/String;
    //   222: iload_3
    //   223: invokevirtual Zv : (Ljava/lang/String;Z)V
    //   226: aload_1
    //   227: ifnonnull -> 300
    //   230: goto -> 237
    //   233: invokestatic a : (Ljava/lang/Exception;)Ljava/lang/Exception;
    //   236: athrow
    //   237: aload_0
    //   238: aload_0
    //   239: getfield ZF : Lorg/yaml/Zjb;
    //   242: invokevirtual Zk : ()Ljava/lang/String;
    //   245: invokevirtual Zp : (Ljava/lang/String;)V
    //   248: aload_1
    //   249: ifnonnull -> 300
    //   252: goto -> 259
    //   255: invokestatic a : (Ljava/lang/Exception;)Ljava/lang/Exception;
    //   258: athrow
    //   259: new org/yaml/Zj3
    //   262: dup
    //   263: new java/lang/StringBuilder
    //   266: dup
    //   267: invokespecial <init> : ()V
    //   270: sipush #29157
    //   273: sipush #-7011
    //   276: invokestatic a : (II)Ljava/lang/String;
    //   279: invokevirtual append : (Ljava/lang/String;)Ljava/lang/StringBuilder;
    //   282: aload_0
    //   283: getfield ZS : Lorg/yaml/Zjm;
    //   286: invokevirtual append : (Ljava/lang/Object;)Ljava/lang/StringBuilder;
    //   289: invokevirtual toString : ()Ljava/lang/String;
    //   292: invokespecial <init> : (Ljava/lang/String;)V
    //   295: athrow
    //   296: invokestatic a : (Ljava/lang/Exception;)Ljava/lang/Exception;
    //   299: athrow
    //   300: aload_0
    //   301: aconst_null
    //   302: putfield ZF : Lorg/yaml/Zjb;
    //   305: aload_0
    //   306: aconst_null
    //   307: putfield ZS : Lorg/yaml/Zjm;
    //   310: return
    // Exception table:
    //   from	to	target	type
    //   12	31	34	java/io/IOException
    //   38	53	56	java/io/IOException
    //   60	74	77	java/io/IOException
    //   67	85	85	java/io/IOException
    //   91	114	117	java/io/IOException
    //   98	164	164	java/io/IOException
    //   121	184	187	java/io/IOException
    //   168	207	210	java/io/IOException
    //   191	230	233	java/io/IOException
    //   214	252	255	java/io/IOException
    //   237	296	296	java/io/IOException
  }
  
  private String ZV(Zjv paramZjv) {
    try {
      if (paramZjv.ZL() != 1)
        throw new Zja(a(29175, -18181) + paramZjv); 
    } catch (NullPointerException nullPointerException) {
      throw a(null);
    } 
    return paramZjv.ZE();
  }
  
  private String ZS(String paramString) {
    try {
      if (paramString.length() == 0)
        throw new Zja(a(29151, 22812)); 
    } catch (NullPointerException nullPointerException) {
      throw a(null);
    } 
    try {
      if (paramString.charAt(0) == '!')
        try {
          if (paramString.charAt(paramString.length() - 1) == '!') {
            try {
              if (!"!".equals(paramString))
                try {
                  if (!Zi.matcher(paramString).matches())
                    throw new Zja(a(29156, 24416) + paramString); 
                } catch (NullPointerException nullPointerException) {
                  throw a(null);
                }  
            } catch (NullPointerException nullPointerException) {
              throw a(null);
            } 
            return paramString;
          } 
          throw new Zja(a(29155, 2294) + paramString);
        } catch (NullPointerException nullPointerException) {
          throw a(null);
        }  
    } catch (NullPointerException nullPointerException) {
      throw a(null);
    } 
    throw new Zja(a(29155, 2294) + paramString);
  }
  
  private String Zz(String paramString) {
    String str = ZH();
    try {
      if (paramString.length() == 0)
        throw new Zja(a(29158, 3235)); 
    } catch (NullPointerException nullPointerException) {
      throw a(null);
    } 
    StringBuilder stringBuilder = new StringBuilder();
    byte b1 = 0;
    byte b2 = 0;
    if (paramString.charAt(0) == '!')
      b2 = 1; 
    while (b2 < paramString.length()) {
      b2++;
      if (str == null)
        break; 
    } 
    try {
      if (b1 < b2)
        stringBuilder.append(paramString, b1, b2); 
    } catch (NullPointerException nullPointerException) {
      throw a(null);
    } 
    return stringBuilder.toString();
  }
  
  private String Zq(String paramString) {
    String str1 = ZH();
    try {
      if (paramString.length() == 0)
        throw new Zja(a(29181, 30480)); 
    } catch (NullPointerException nullPointerException) {
      throw a(null);
    } 
    try {
      if ("!".equals(paramString))
        return paramString; 
    } catch (NullPointerException nullPointerException) {
      throw a(null);
    } 
    String str2 = null;
    String str3 = paramString;
    for (String str : this.ZY.keySet()) {
      try {
        if (paramString.startsWith(str))
          try {
            if ("!".equals(str) || str.length() < paramString.length())
              str2 = str; 
          } catch (NullPointerException nullPointerException) {
            throw a(null);
          }  
      } catch (NullPointerException nullPointerException) {
        throw a(null);
      } 
      if (str1 == null)
        break; 
    } 
    if (str2 != null) {
      str3 = paramString.substring(str2.length());
      str2 = this.ZY.get(str2);
    } 
    int i = str3.length();
    try {
    
    } catch (NullPointerException nullPointerException) {
      throw a(null);
    } 
    String str4 = (i > 0) ? str3.substring(0, i) : "";
    try {
      if (str2 != null)
        return str2 + str4; 
    } catch (NullPointerException nullPointerException) {
      throw a(null);
    } 
    return a(29168, 16678) + str4 + ">";
  }
  
  static String ZO(String paramString) {
    String str = ZH();
    try {
      if (paramString.length() == 0)
        throw new Zja(a(29179, -16464)); 
    } catch (NullPointerException nullPointerException) {
      throw a(null);
    } 
    for (Character character : ZV) {
      try {
        if (paramString.indexOf(character.charValue()) > -1)
          throw new Zja(a(29183, 13702) + character + a(29171, -22476) + paramString); 
      } catch (NullPointerException nullPointerException) {
        throw a(null);
      } 
      if (str == null)
        break; 
    } 
    Matcher matcher = ZO.matcher(paramString);
    try {
      if (matcher.find())
        throw new Zja(a(29164, 25658) + paramString); 
    } catch (NullPointerException nullPointerException) {
      throw a(null);
    } 
    return paramString;
  }
  
  private static boolean Zg(String paramString) {
    // Byte code:
    //   0: invokestatic ZH : ()Ljava/lang/String;
    //   3: astore_1
    //   4: aload_0
    //   5: invokevirtual length : ()I
    //   8: iconst_1
    //   9: if_icmple -> 108
    //   12: aload_0
    //   13: iconst_0
    //   14: invokevirtual charAt : (I)C
    //   17: bipush #48
    //   19: if_icmpne -> 108
    //   22: goto -> 29
    //   25: invokestatic a : (Ljava/lang/Exception;)Ljava/lang/Exception;
    //   28: athrow
    //   29: iconst_1
    //   30: istore_2
    //   31: iload_2
    //   32: aload_0
    //   33: invokevirtual length : ()I
    //   36: if_icmpge -> 106
    //   39: aload_0
    //   40: iload_2
    //   41: invokevirtual charAt : (I)C
    //   44: istore_3
    //   45: iload_3
    //   46: bipush #48
    //   48: if_icmplt -> 64
    //   51: iload_3
    //   52: bipush #57
    //   54: if_icmple -> 77
    //   57: goto -> 64
    //   60: invokestatic a : (Ljava/lang/Exception;)Ljava/lang/Exception;
    //   63: athrow
    //   64: iload_3
    //   65: bipush #95
    //   67: if_icmpne -> 85
    //   70: goto -> 77
    //   73: invokestatic a : (Ljava/lang/Exception;)Ljava/lang/Exception;
    //   76: athrow
    //   77: iconst_1
    //   78: goto -> 86
    //   81: invokestatic a : (Ljava/lang/Exception;)Ljava/lang/Exception;
    //   84: athrow
    //   85: iconst_0
    //   86: istore #4
    //   88: iload #4
    //   90: ifne -> 99
    //   93: iconst_0
    //   94: ireturn
    //   95: invokestatic a : (Ljava/lang/Exception;)Ljava/lang/Exception;
    //   98: athrow
    //   99: iinc #2, 1
    //   102: aload_1
    //   103: ifnonnull -> 31
    //   106: iconst_1
    //   107: ireturn
    //   108: iconst_0
    //   109: ireturn
    // Exception table:
    //   from	to	target	type
    //   4	22	25	java/lang/NullPointerException
    //   45	57	60	java/lang/NullPointerException
    //   51	70	73	java/lang/NullPointerException
    //   64	81	81	java/lang/NullPointerException
    //   88	95	95	java/lang/NullPointerException
  }
  
  private Zjb ZD(String paramString) {
    // Byte code:
    //   0: invokestatic ZH : ()Ljava/lang/String;
    //   3: astore_2
    //   4: aload_1
    //   5: invokevirtual length : ()I
    //   8: ifne -> 30
    //   11: new org/yaml/Zjb
    //   14: dup
    //   15: aload_1
    //   16: iconst_1
    //   17: iconst_0
    //   18: iconst_0
    //   19: iconst_1
    //   20: iconst_1
    //   21: iconst_0
    //   22: invokespecial <init> : (Ljava/lang/String;ZZZZZZ)V
    //   25: areturn
    //   26: invokestatic a : (Ljava/lang/Exception;)Ljava/lang/Exception;
    //   29: athrow
    //   30: iconst_0
    //   31: istore_3
    //   32: iconst_0
    //   33: istore #4
    //   35: iconst_0
    //   36: istore #5
    //   38: iconst_0
    //   39: istore #6
    //   41: aload_1
    //   42: invokestatic Zg : (Ljava/lang/String;)Z
    //   45: istore #7
    //   47: iconst_0
    //   48: istore #8
    //   50: iconst_0
    //   51: istore #9
    //   53: iconst_0
    //   54: istore #10
    //   56: iconst_0
    //   57: istore #11
    //   59: iconst_0
    //   60: istore #12
    //   62: iconst_0
    //   63: istore #13
    //   65: aload_1
    //   66: sipush #29170
    //   69: sipush #-32230
    //   72: invokestatic a : (II)Ljava/lang/String;
    //   75: invokevirtual startsWith : (Ljava/lang/String;)Z
    //   78: ifne -> 104
    //   81: aload_1
    //   82: sipush #29178
    //   85: sipush #-6170
    //   88: invokestatic a : (II)Ljava/lang/String;
    //   91: invokevirtual startsWith : (Ljava/lang/String;)Z
    //   94: ifeq -> 109
    //   97: goto -> 104
    //   100: invokestatic a : (Ljava/lang/Exception;)Ljava/lang/Exception;
    //   103: athrow
    //   104: iconst_1
    //   105: istore_3
    //   106: iconst_1
    //   107: istore #4
    //   109: iconst_1
    //   110: istore #14
    //   112: aload_1
    //   113: invokevirtual length : ()I
    //   116: iconst_1
    //   117: if_icmpeq -> 141
    //   120: getstatic org/yaml/Z_s.Zp : Lorg/yaml/Z_s;
    //   123: aload_1
    //   124: iconst_1
    //   125: invokevirtual codePointAt : (I)I
    //   128: invokevirtual Zj : (I)Z
    //   131: ifeq -> 149
    //   134: goto -> 141
    //   137: invokestatic a : (Ljava/lang/Exception;)Ljava/lang/Exception;
    //   140: athrow
    //   141: iconst_1
    //   142: goto -> 150
    //   145: invokestatic a : (Ljava/lang/Exception;)Ljava/lang/Exception;
    //   148: athrow
    //   149: iconst_0
    //   150: istore #15
    //   152: iconst_0
    //   153: istore #16
    //   155: iconst_0
    //   156: istore #17
    //   158: iconst_0
    //   159: istore #18
    //   161: iload #18
    //   163: aload_1
    //   164: invokevirtual length : ()I
    //   167: if_icmpge -> 767
    //   170: aload_1
    //   171: iload #18
    //   173: invokevirtual codePointAt : (I)I
    //   176: istore #19
    //   178: iload #18
    //   180: ifne -> 272
    //   183: sipush #29174
    //   186: sipush #-31250
    //   189: invokestatic a : (II)Ljava/lang/String;
    //   192: iload #19
    //   194: invokevirtual indexOf : (I)I
    //   197: iconst_m1
    //   198: if_icmpeq -> 213
    //   201: goto -> 208
    //   204: invokestatic a : (Ljava/lang/Exception;)Ljava/lang/Exception;
    //   207: athrow
    //   208: iconst_1
    //   209: istore #4
    //   211: iconst_1
    //   212: istore_3
    //   213: iload #19
    //   215: bipush #63
    //   217: if_icmpeq -> 234
    //   220: iload #19
    //   222: bipush #58
    //   224: if_icmpne -> 244
    //   227: goto -> 234
    //   230: invokestatic a : (Ljava/lang/Exception;)Ljava/lang/Exception;
    //   233: athrow
    //   234: iconst_1
    //   235: istore #4
    //   237: iload #15
    //   239: ifeq -> 244
    //   242: iconst_1
    //   243: istore_3
    //   244: iload #19
    //   246: bipush #45
    //   248: if_icmpne -> 341
    //   251: iload #15
    //   253: ifeq -> 341
    //   256: goto -> 263
    //   259: invokestatic a : (Ljava/lang/Exception;)Ljava/lang/Exception;
    //   262: athrow
    //   263: iconst_1
    //   264: istore #4
    //   266: iconst_1
    //   267: istore_3
    //   268: aload_2
    //   269: ifnonnull -> 341
    //   272: sipush #29162
    //   275: sipush #28424
    //   278: invokestatic a : (II)Ljava/lang/String;
    //   281: iload #19
    //   283: invokevirtual indexOf : (I)I
    //   286: iconst_m1
    //   287: if_icmpeq -> 300
    //   290: goto -> 297
    //   293: invokestatic a : (Ljava/lang/Exception;)Ljava/lang/Exception;
    //   296: athrow
    //   297: iconst_1
    //   298: istore #4
    //   300: iload #19
    //   302: bipush #58
    //   304: if_icmpne -> 317
    //   307: iconst_1
    //   308: istore #4
    //   310: iload #15
    //   312: ifeq -> 317
    //   315: iconst_1
    //   316: istore_3
    //   317: iload #19
    //   319: bipush #35
    //   321: if_icmpne -> 341
    //   324: iload #14
    //   326: ifeq -> 341
    //   329: goto -> 336
    //   332: invokestatic a : (Ljava/lang/Exception;)Ljava/lang/Exception;
    //   335: athrow
    //   336: iconst_1
    //   337: istore #4
    //   339: iconst_1
    //   340: istore_3
    //   341: getstatic org/yaml/Z_s.ZV : Lorg/yaml/Z_s;
    //   344: iload #19
    //   346: invokevirtual Zj : (I)Z
    //   349: istore #20
    //   351: iload #20
    //   353: ifeq -> 359
    //   356: iconst_1
    //   357: istore #5
    //   359: iload #19
    //   361: bipush #10
    //   363: if_icmpeq -> 518
    //   366: bipush #32
    //   368: iload #19
    //   370: if_icmpgt -> 394
    //   373: goto -> 380
    //   376: invokestatic a : (Ljava/lang/Exception;)Ljava/lang/Exception;
    //   379: athrow
    //   380: iload #19
    //   382: bipush #126
    //   384: if_icmple -> 518
    //   387: goto -> 394
    //   390: invokestatic a : (Ljava/lang/Exception;)Ljava/lang/Exception;
    //   393: athrow
    //   394: iload #19
    //   396: sipush #133
    //   399: if_icmpeq -> 494
    //   402: goto -> 409
    //   405: invokestatic a : (Ljava/lang/Exception;)Ljava/lang/Exception;
    //   408: athrow
    //   409: iload #19
    //   411: sipush #160
    //   414: if_icmplt -> 438
    //   417: goto -> 424
    //   420: invokestatic a : (Ljava/lang/Exception;)Ljava/lang/Exception;
    //   423: athrow
    //   424: iload #19
    //   426: ldc 55295
    //   428: if_icmple -> 494
    //   431: goto -> 438
    //   434: invokestatic a : (Ljava/lang/Exception;)Ljava/lang/Exception;
    //   437: athrow
    //   438: iload #19
    //   440: ldc 57344
    //   442: if_icmplt -> 466
    //   445: goto -> 452
    //   448: invokestatic a : (Ljava/lang/Exception;)Ljava/lang/Exception;
    //   451: athrow
    //   452: iload #19
    //   454: ldc 65533
    //   456: if_icmple -> 494
    //   459: goto -> 466
    //   462: invokestatic a : (Ljava/lang/Exception;)Ljava/lang/Exception;
    //   465: athrow
    //   466: iload #19
    //   468: ldc 65536
    //   470: if_icmplt -> 515
    //   473: goto -> 480
    //   476: invokestatic a : (Ljava/lang/Exception;)Ljava/lang/Exception;
    //   479: athrow
    //   480: iload #19
    //   482: ldc 1114111
    //   484: if_icmpgt -> 515
    //   487: goto -> 494
    //   490: invokestatic a : (Ljava/lang/Exception;)Ljava/lang/Exception;
    //   493: athrow
    //   494: aload_0
    //   495: getfield Zf : Z
    //   498: ifne -> 518
    //   501: goto -> 508
    //   504: invokestatic a : (Ljava/lang/Exception;)Ljava/lang/Exception;
    //   507: athrow
    //   508: iconst_1
    //   509: istore #6
    //   511: aload_2
    //   512: ifnonnull -> 518
    //   515: iconst_1
    //   516: istore #6
    //   518: iload #19
    //   520: bipush #32
    //   522: if_icmpne -> 572
    //   525: iload #18
    //   527: ifne -> 540
    //   530: goto -> 537
    //   533: invokestatic a : (Ljava/lang/Exception;)Ljava/lang/Exception;
    //   536: athrow
    //   537: iconst_1
    //   538: istore #8
    //   540: iload #18
    //   542: aload_1
    //   543: invokevirtual length : ()I
    //   546: iconst_1
    //   547: isub
    //   548: if_icmpne -> 554
    //   551: iconst_1
    //   552: istore #10
    //   554: iload #17
    //   556: ifeq -> 562
    //   559: iconst_1
    //   560: istore #12
    //   562: iconst_1
    //   563: istore #16
    //   565: iconst_0
    //   566: istore #17
    //   568: aload_2
    //   569: ifnonnull -> 637
    //   572: iload #20
    //   574: ifeq -> 631
    //   577: goto -> 584
    //   580: invokestatic a : (Ljava/lang/Exception;)Ljava/lang/Exception;
    //   583: athrow
    //   584: iload #18
    //   586: ifne -> 599
    //   589: goto -> 596
    //   592: invokestatic a : (Ljava/lang/Exception;)Ljava/lang/Exception;
    //   595: athrow
    //   596: iconst_1
    //   597: istore #9
    //   599: iload #18
    //   601: aload_1
    //   602: invokevirtual length : ()I
    //   605: iconst_1
    //   606: isub
    //   607: if_icmpne -> 613
    //   610: iconst_1
    //   611: istore #11
    //   613: iload #16
    //   615: ifeq -> 621
    //   618: iconst_1
    //   619: istore #13
    //   621: iconst_0
    //   622: istore #16
    //   624: iconst_1
    //   625: istore #17
    //   627: aload_2
    //   628: ifnonnull -> 637
    //   631: iconst_0
    //   632: istore #16
    //   634: iconst_0
    //   635: istore #17
    //   637: iload #18
    //   639: iload #19
    //   641: invokestatic charCount : (I)I
    //   644: iadd
    //   645: istore #18
    //   647: getstatic org/yaml/Z_s.Zy : Lorg/yaml/Z_s;
    //   650: iload #19
    //   652: invokevirtual Zj : (I)Z
    //   655: ifne -> 670
    //   658: iload #20
    //   660: ifeq -> 678
    //   663: goto -> 670
    //   666: invokestatic a : (Ljava/lang/Exception;)Ljava/lang/Exception;
    //   669: athrow
    //   670: iconst_1
    //   671: goto -> 679
    //   674: invokestatic a : (Ljava/lang/Exception;)Ljava/lang/Exception;
    //   677: athrow
    //   678: iconst_0
    //   679: istore #14
    //   681: iconst_1
    //   682: istore #15
    //   684: iload #18
    //   686: iconst_1
    //   687: iadd
    //   688: aload_1
    //   689: invokevirtual length : ()I
    //   692: if_icmpge -> 763
    //   695: iload #18
    //   697: aload_1
    //   698: iload #18
    //   700: invokevirtual codePointAt : (I)I
    //   703: invokestatic charCount : (I)I
    //   706: iadd
    //   707: istore #21
    //   709: iload #21
    //   711: aload_1
    //   712: invokevirtual length : ()I
    //   715: if_icmpge -> 763
    //   718: getstatic org/yaml/Z_s.Zy : Lorg/yaml/Z_s;
    //   721: aload_1
    //   722: iload #21
    //   724: invokevirtual codePointAt : (I)I
    //   727: invokevirtual Zj : (I)Z
    //   730: ifne -> 752
    //   733: goto -> 740
    //   736: invokestatic a : (Ljava/lang/Exception;)Ljava/lang/Exception;
    //   739: athrow
    //   740: iload #20
    //   742: ifeq -> 760
    //   745: goto -> 752
    //   748: invokestatic a : (Ljava/lang/Exception;)Ljava/lang/Exception;
    //   751: athrow
    //   752: iconst_1
    //   753: goto -> 761
    //   756: invokestatic a : (Ljava/lang/Exception;)Ljava/lang/Exception;
    //   759: athrow
    //   760: iconst_0
    //   761: istore #15
    //   763: aload_2
    //   764: ifnonnull -> 161
    //   767: iconst_1
    //   768: istore #19
    //   770: iconst_1
    //   771: istore #20
    //   773: iconst_1
    //   774: istore #21
    //   776: iconst_1
    //   777: istore #22
    //   779: iload #8
    //   781: ifne -> 832
    //   784: iload #9
    //   786: ifne -> 832
    //   789: goto -> 796
    //   792: invokestatic a : (Ljava/lang/Exception;)Ljava/lang/Exception;
    //   795: athrow
    //   796: iload #10
    //   798: ifne -> 832
    //   801: goto -> 808
    //   804: invokestatic a : (Ljava/lang/Exception;)Ljava/lang/Exception;
    //   807: athrow
    //   808: iload #11
    //   810: ifne -> 832
    //   813: goto -> 820
    //   816: invokestatic a : (Ljava/lang/Exception;)Ljava/lang/Exception;
    //   819: athrow
    //   820: iload #7
    //   822: ifeq -> 838
    //   825: goto -> 832
    //   828: invokestatic a : (Ljava/lang/Exception;)Ljava/lang/Exception;
    //   831: athrow
    //   832: iconst_0
    //   833: dup
    //   834: istore #20
    //   836: istore #19
    //   838: iload #10
    //   840: ifeq -> 846
    //   843: iconst_0
    //   844: istore #22
    //   846: iload #12
    //   848: ifeq -> 860
    //   851: iconst_0
    //   852: dup
    //   853: istore #21
    //   855: dup
    //   856: istore #20
    //   858: istore #19
    //   860: iload #13
    //   862: ifne -> 877
    //   865: iload #6
    //   867: ifeq -> 889
    //   870: goto -> 877
    //   873: invokestatic a : (Ljava/lang/Exception;)Ljava/lang/Exception;
    //   876: athrow
    //   877: iconst_0
    //   878: dup
    //   879: istore #22
    //   881: dup
    //   882: istore #21
    //   884: dup
    //   885: istore #20
    //   887: istore #19
    //   889: iload #5
    //   891: ifeq -> 897
    //   894: iconst_0
    //   895: istore #19
    //   897: iload #4
    //   899: ifeq -> 905
    //   902: iconst_0
    //   903: istore #19
    //   905: iload_3
    //   906: ifeq -> 912
    //   909: iconst_0
    //   910: istore #20
    //   912: new org/yaml/Zjb
    //   915: dup
    //   916: aload_1
    //   917: iconst_0
    //   918: iload #5
    //   920: iload #19
    //   922: iload #20
    //   924: iload #21
    //   926: iload #22
    //   928: invokespecial <init> : (Ljava/lang/String;ZZZZZZ)V
    //   931: areturn
    // Exception table:
    //   from	to	target	type
    //   4	26	26	java/lang/NullPointerException
    //   65	97	100	java/lang/NullPointerException
    //   112	134	137	java/lang/NullPointerException
    //   120	145	145	java/lang/NullPointerException
    //   178	201	204	java/lang/NullPointerException
    //   213	227	230	java/lang/NullPointerException
    //   244	256	259	java/lang/NullPointerException
    //   268	290	293	java/lang/NullPointerException
    //   317	329	332	java/lang/NullPointerException
    //   359	373	376	java/lang/NullPointerException
    //   366	387	390	java/lang/NullPointerException
    //   380	402	405	java/lang/NullPointerException
    //   394	417	420	java/lang/NullPointerException
    //   409	431	434	java/lang/NullPointerException
    //   424	445	448	java/lang/NullPointerException
    //   438	459	462	java/lang/NullPointerException
    //   452	473	476	java/lang/NullPointerException
    //   466	487	490	java/lang/NullPointerException
    //   480	501	504	java/lang/NullPointerException
    //   518	530	533	java/lang/NullPointerException
    //   568	577	580	java/lang/NullPointerException
    //   572	589	592	java/lang/NullPointerException
    //   647	663	666	java/lang/NullPointerException
    //   658	674	674	java/lang/NullPointerException
    //   709	733	736	java/lang/NullPointerException
    //   718	745	748	java/lang/NullPointerException
    //   740	756	756	java/lang/NullPointerException
    //   779	789	792	java/lang/NullPointerException
    //   784	801	804	java/lang/NullPointerException
    //   796	813	816	java/lang/NullPointerException
    //   808	825	828	java/lang/NullPointerException
    //   860	870	873	java/lang/NullPointerException
  }
  
  void Zj() throws IOException {
    this.ZN.flush();
  }
  
  void Zd() {}
  
  void Zt() throws IOException {
    Zj();
  }
  
  void Zv(String paramString, boolean paramBoolean1, boolean paramBoolean2, boolean paramBoolean3) throws IOException {
    // Byte code:
    //   0: aload_0
    //   1: getfield ZI : Z
    //   4: ifne -> 45
    //   7: iload_2
    //   8: ifeq -> 45
    //   11: goto -> 18
    //   14: invokestatic a : (Ljava/lang/Exception;)Ljava/lang/Exception;
    //   17: athrow
    //   18: aload_0
    //   19: dup
    //   20: getfield Zm : I
    //   23: iconst_1
    //   24: iadd
    //   25: putfield Zm : I
    //   28: aload_0
    //   29: getfield ZN : Ljava/io/Writer;
    //   32: getstatic org/yaml/Zb.Zy : [C
    //   35: invokevirtual write : ([C)V
    //   38: goto -> 45
    //   41: invokestatic a : (Ljava/lang/Exception;)Ljava/lang/Exception;
    //   44: athrow
    //   45: aload_0
    //   46: iload_3
    //   47: putfield ZI : Z
    //   50: aload_0
    //   51: aload_0
    //   52: getfield Zh : Z
    //   55: ifeq -> 78
    //   58: iload #4
    //   60: ifeq -> 78
    //   63: goto -> 70
    //   66: invokestatic a : (Ljava/lang/Exception;)Ljava/lang/Exception;
    //   69: athrow
    //   70: iconst_1
    //   71: goto -> 79
    //   74: invokestatic a : (Ljava/lang/Exception;)Ljava/lang/Exception;
    //   77: athrow
    //   78: iconst_0
    //   79: putfield Zh : Z
    //   82: aload_0
    //   83: dup
    //   84: getfield Zm : I
    //   87: aload_1
    //   88: invokevirtual length : ()I
    //   91: iadd
    //   92: putfield Zm : I
    //   95: aload_0
    //   96: iconst_0
    //   97: putfield ZZ : Z
    //   100: aload_0
    //   101: getfield ZN : Ljava/io/Writer;
    //   104: aload_1
    //   105: invokevirtual write : (Ljava/lang/String;)V
    //   108: return
    // Exception table:
    //   from	to	target	type
    //   0	11	14	java/io/IOException
    //   7	38	41	java/io/IOException
    //   45	63	66	java/io/IOException
    //   58	74	74	java/io/IOException
  }
  
  void ZJ() throws IOException {
    // Byte code:
    //   0: invokestatic ZH : ()Ljava/lang/String;
    //   3: astore_1
    //   4: aload_0
    //   5: getfield Zn : Ljava/lang/Integer;
    //   8: ifnull -> 23
    //   11: aload_0
    //   12: getfield Zn : Ljava/lang/Integer;
    //   15: invokevirtual intValue : ()I
    //   18: istore_2
    //   19: aload_1
    //   20: ifnonnull -> 25
    //   23: iconst_0
    //   24: istore_2
    //   25: aload_0
    //   26: getfield Zh : Z
    //   29: ifeq -> 76
    //   32: aload_0
    //   33: getfield Zm : I
    //   36: iload_2
    //   37: if_icmpgt -> 76
    //   40: goto -> 47
    //   43: invokestatic a : (Ljava/lang/Exception;)Ljava/lang/Exception;
    //   46: athrow
    //   47: aload_0
    //   48: getfield Zm : I
    //   51: iload_2
    //   52: if_icmpne -> 88
    //   55: goto -> 62
    //   58: invokestatic a : (Ljava/lang/Exception;)Ljava/lang/Exception;
    //   61: athrow
    //   62: aload_0
    //   63: getfield ZI : Z
    //   66: ifne -> 88
    //   69: goto -> 76
    //   72: invokestatic a : (Ljava/lang/Exception;)Ljava/lang/Exception;
    //   75: athrow
    //   76: aload_0
    //   77: aconst_null
    //   78: invokespecial ZH : (Ljava/lang/String;)V
    //   81: goto -> 88
    //   84: invokestatic a : (Ljava/lang/Exception;)Ljava/lang/Exception;
    //   87: athrow
    //   88: aload_0
    //   89: iload_2
    //   90: aload_0
    //   91: getfield Zm : I
    //   94: isub
    //   95: invokespecial Zx : (I)V
    //   98: return
    // Exception table:
    //   from	to	target	type
    //   25	40	43	java/io/IOException
    //   32	55	58	java/io/IOException
    //   47	69	72	java/io/IOException
    //   62	81	84	java/io/IOException
  }
  
  private void Zx(int paramInt) throws IOException {
    String str = ZH();
    try {
      if (paramInt <= 0)
        return; 
    } catch (IOException iOException) {
      throw a(null);
    } 
    this.ZI = true;
    char[] arrayOfChar = new char[paramInt];
    byte b = 0;
    while (b < arrayOfChar.length) {
      arrayOfChar[b] = ' ';
      b++;
      if (str == null)
        break; 
    } 
    this.Zm += paramInt;
    this.ZN.write(arrayOfChar);
  }
  
  private void ZH(String paramString) throws IOException {
    this.ZI = true;
    this.Zh = true;
    this.Zm = 0;
    String str = ZH();
    try {
      if (paramString == null) {
        try {
          this.ZN.write(this.ZG);
          if (str == null) {
            this.ZN.write(paramString);
            return;
          } 
        } catch (IOException iOException) {
          throw a(null);
        } 
        return;
      } 
    } catch (IOException iOException) {
      throw a(null);
    } 
    this.ZN.write(paramString);
  }
  
  void ZQ(String paramString) throws IOException {
    this.ZN.write(a(29146, 21101));
    this.ZN.write(paramString);
    ZH((String)null);
  }
  
  void Zg(String paramString1, String paramString2) throws IOException {
    this.ZN.write(a(29152, -5643));
    this.ZN.write(paramString1);
    this.ZN.write(Zy);
    this.ZN.write(paramString2);
    ZH((String)null);
  }
  
  private void ZR(String paramString, boolean paramBoolean) throws IOException {
    // Byte code:
    //   0: aload_0
    //   1: ldc '''
    //   3: iconst_1
    //   4: iconst_0
    //   5: iconst_0
    //   6: invokevirtual Zv : (Ljava/lang/String;ZZZ)V
    //   9: iconst_0
    //   10: istore #4
    //   12: invokestatic ZH : ()Ljava/lang/String;
    //   15: iconst_0
    //   16: istore #5
    //   18: iconst_0
    //   19: istore #6
    //   21: iconst_0
    //   22: istore #7
    //   24: astore_3
    //   25: iload #7
    //   27: aload_1
    //   28: invokevirtual length : ()I
    //   31: if_icmpgt -> 541
    //   34: iconst_0
    //   35: istore #8
    //   37: iload #7
    //   39: aload_1
    //   40: invokevirtual length : ()I
    //   43: if_icmpge -> 54
    //   46: aload_1
    //   47: iload #7
    //   49: invokevirtual charAt : (I)C
    //   52: istore #8
    //   54: iload #4
    //   56: ifeq -> 211
    //   59: iload #8
    //   61: ifeq -> 85
    //   64: goto -> 71
    //   67: invokestatic a : (Ljava/lang/Exception;)Ljava/lang/Exception;
    //   70: athrow
    //   71: iload #8
    //   73: bipush #32
    //   75: if_icmpeq -> 455
    //   78: goto -> 85
    //   81: invokestatic a : (Ljava/lang/Exception;)Ljava/lang/Exception;
    //   84: athrow
    //   85: iload #6
    //   87: iconst_1
    //   88: iadd
    //   89: iload #7
    //   91: if_icmpne -> 173
    //   94: goto -> 101
    //   97: invokestatic a : (Ljava/lang/Exception;)Ljava/lang/Exception;
    //   100: athrow
    //   101: aload_0
    //   102: getfield Zm : I
    //   105: aload_0
    //   106: getfield Zd : I
    //   109: if_icmple -> 173
    //   112: goto -> 119
    //   115: invokestatic a : (Ljava/lang/Exception;)Ljava/lang/Exception;
    //   118: athrow
    //   119: iload_2
    //   120: ifeq -> 173
    //   123: goto -> 130
    //   126: invokestatic a : (Ljava/lang/Exception;)Ljava/lang/Exception;
    //   129: athrow
    //   130: iload #6
    //   132: ifeq -> 173
    //   135: goto -> 142
    //   138: invokestatic a : (Ljava/lang/Exception;)Ljava/lang/Exception;
    //   141: athrow
    //   142: iload #7
    //   144: aload_1
    //   145: invokevirtual length : ()I
    //   148: if_icmpeq -> 173
    //   151: goto -> 158
    //   154: invokestatic a : (Ljava/lang/Exception;)Ljava/lang/Exception;
    //   157: athrow
    //   158: aload_0
    //   159: invokevirtual ZJ : ()V
    //   162: aload_3
    //   163: ifnonnull -> 203
    //   166: goto -> 173
    //   169: invokestatic a : (Ljava/lang/Exception;)Ljava/lang/Exception;
    //   172: athrow
    //   173: iload #7
    //   175: iload #6
    //   177: isub
    //   178: istore #9
    //   180: aload_0
    //   181: dup
    //   182: getfield Zm : I
    //   185: iload #9
    //   187: iadd
    //   188: putfield Zm : I
    //   191: aload_0
    //   192: getfield ZN : Ljava/io/Writer;
    //   195: aload_1
    //   196: iload #6
    //   198: iload #9
    //   200: invokevirtual write : (Ljava/lang/String;II)V
    //   203: iload #7
    //   205: istore #6
    //   207: aload_3
    //   208: ifnonnull -> 455
    //   211: iload #5
    //   213: ifeq -> 380
    //   216: goto -> 223
    //   219: invokestatic a : (Ljava/lang/Exception;)Ljava/lang/Exception;
    //   222: athrow
    //   223: iload #8
    //   225: ifeq -> 253
    //   228: goto -> 235
    //   231: invokestatic a : (Ljava/lang/Exception;)Ljava/lang/Exception;
    //   234: athrow
    //   235: getstatic org/yaml/Z_s.ZV : Lorg/yaml/Z_s;
    //   238: iload #8
    //   240: invokevirtual ZS : (I)Z
    //   243: ifeq -> 455
    //   246: goto -> 253
    //   249: invokestatic a : (Ljava/lang/Exception;)Ljava/lang/Exception;
    //   252: athrow
    //   253: aload_1
    //   254: iload #6
    //   256: invokevirtual charAt : (I)C
    //   259: bipush #10
    //   261: if_icmpne -> 283
    //   264: goto -> 271
    //   267: invokestatic a : (Ljava/lang/Exception;)Ljava/lang/Exception;
    //   270: athrow
    //   271: aload_0
    //   272: aconst_null
    //   273: invokespecial ZH : (Ljava/lang/String;)V
    //   276: goto -> 283
    //   279: invokestatic a : (Ljava/lang/Exception;)Ljava/lang/Exception;
    //   282: athrow
    //   283: aload_1
    //   284: iload #6
    //   286: iload #7
    //   288: invokevirtual substring : (II)Ljava/lang/String;
    //   291: astore #9
    //   293: aload #9
    //   295: invokevirtual toCharArray : ()[C
    //   298: astore #10
    //   300: aload #10
    //   302: arraylength
    //   303: istore #11
    //   305: iconst_0
    //   306: istore #12
    //   308: iload #12
    //   310: iload #11
    //   312: if_icmpge -> 368
    //   315: aload #10
    //   317: iload #12
    //   319: caload
    //   320: istore #13
    //   322: iload #13
    //   324: bipush #10
    //   326: if_icmpne -> 345
    //   329: aload_0
    //   330: aconst_null
    //   331: invokespecial ZH : (Ljava/lang/String;)V
    //   334: aload_3
    //   335: ifnonnull -> 361
    //   338: goto -> 345
    //   341: invokestatic a : (Ljava/lang/Exception;)Ljava/lang/Exception;
    //   344: athrow
    //   345: aload_0
    //   346: iload #13
    //   348: invokestatic valueOf : (C)Ljava/lang/String;
    //   351: invokespecial ZH : (Ljava/lang/String;)V
    //   354: goto -> 361
    //   357: invokestatic a : (Ljava/lang/Exception;)Ljava/lang/Exception;
    //   360: athrow
    //   361: iinc #12, 1
    //   364: aload_3
    //   365: ifnonnull -> 308
    //   368: aload_0
    //   369: invokevirtual ZJ : ()V
    //   372: iload #7
    //   374: istore #6
    //   376: aload_3
    //   377: ifnonnull -> 455
    //   380: getstatic org/yaml/Z_s.ZV : Lorg/yaml/Z_s;
    //   383: iload #8
    //   385: sipush #29177
    //   388: sipush #-8105
    //   391: invokestatic a : (II)Ljava/lang/String;
    //   394: invokevirtual Zd : (ILjava/lang/String;)Z
    //   397: ifeq -> 455
    //   400: goto -> 407
    //   403: invokestatic a : (Ljava/lang/Exception;)Ljava/lang/Exception;
    //   406: athrow
    //   407: iload #6
    //   409: iload #7
    //   411: if_icmpge -> 455
    //   414: goto -> 421
    //   417: invokestatic a : (Ljava/lang/Exception;)Ljava/lang/Exception;
    //   420: athrow
    //   421: iload #7
    //   423: iload #6
    //   425: isub
    //   426: istore #9
    //   428: aload_0
    //   429: dup
    //   430: getfield Zm : I
    //   433: iload #9
    //   435: iadd
    //   436: putfield Zm : I
    //   439: aload_0
    //   440: getfield ZN : Ljava/io/Writer;
    //   443: aload_1
    //   444: iload #6
    //   446: iload #9
    //   448: invokevirtual write : (Ljava/lang/String;II)V
    //   451: iload #7
    //   453: istore #6
    //   455: iload #8
    //   457: bipush #39
    //   459: if_icmpne -> 494
    //   462: aload_0
    //   463: dup
    //   464: getfield Zm : I
    //   467: iconst_2
    //   468: iadd
    //   469: putfield Zm : I
    //   472: aload_0
    //   473: getfield ZN : Ljava/io/Writer;
    //   476: sipush #29148
    //   479: sipush #-16389
    //   482: invokestatic a : (II)Ljava/lang/String;
    //   485: invokevirtual write : (Ljava/lang/String;)V
    //   488: iload #7
    //   490: iconst_1
    //   491: iadd
    //   492: istore #6
    //   494: iload #8
    //   496: ifeq -> 534
    //   499: iload #8
    //   501: bipush #32
    //   503: if_icmpne -> 521
    //   506: goto -> 513
    //   509: invokestatic a : (Ljava/lang/Exception;)Ljava/lang/Exception;
    //   512: athrow
    //   513: iconst_1
    //   514: goto -> 522
    //   517: invokestatic a : (Ljava/lang/Exception;)Ljava/lang/Exception;
    //   520: athrow
    //   521: iconst_0
    //   522: istore #4
    //   524: getstatic org/yaml/Z_s.ZV : Lorg/yaml/Z_s;
    //   527: iload #8
    //   529: invokevirtual Zj : (I)Z
    //   532: istore #5
    //   534: iinc #7, 1
    //   537: aload_3
    //   538: ifnonnull -> 25
    //   541: aload_0
    //   542: ldc '''
    //   544: iconst_0
    //   545: iconst_0
    //   546: iconst_0
    //   547: invokevirtual Zv : (Ljava/lang/String;ZZZ)V
    //   550: return
    // Exception table:
    //   from	to	target	type
    //   54	64	67	java/io/IOException
    //   59	78	81	java/io/IOException
    //   71	94	97	java/io/IOException
    //   85	112	115	java/io/IOException
    //   101	123	126	java/io/IOException
    //   119	135	138	java/io/IOException
    //   130	151	154	java/io/IOException
    //   142	166	169	java/io/IOException
    //   207	216	219	java/io/IOException
    //   211	228	231	java/io/IOException
    //   223	246	249	java/io/IOException
    //   235	264	267	java/io/IOException
    //   253	276	279	java/io/IOException
    //   322	338	341	java/io/IOException
    //   329	354	357	java/io/IOException
    //   376	400	403	java/io/IOException
    //   380	414	417	java/io/IOException
    //   494	506	509	java/io/IOException
    //   499	517	517	java/io/IOException
  }
  
  private void ZV(String paramString, boolean paramBoolean) throws IOException {
    // Byte code:
    //   0: invokestatic ZH : ()Ljava/lang/String;
    //   3: aload_0
    //   4: ldc '"'
    //   6: iconst_1
    //   7: iconst_0
    //   8: iconst_0
    //   9: invokevirtual Zv : (Ljava/lang/String;ZZZ)V
    //   12: astore_3
    //   13: iconst_0
    //   14: istore #4
    //   16: iconst_0
    //   17: istore #5
    //   19: iload #5
    //   21: aload_1
    //   22: invokevirtual length : ()I
    //   25: if_icmpgt -> 877
    //   28: aconst_null
    //   29: astore #6
    //   31: iload #5
    //   33: aload_1
    //   34: invokevirtual length : ()I
    //   37: if_icmpge -> 51
    //   40: aload_1
    //   41: iload #5
    //   43: invokevirtual charAt : (I)C
    //   46: invokestatic valueOf : (C)Ljava/lang/Character;
    //   49: astore #6
    //   51: aload #6
    //   53: ifnull -> 118
    //   56: sipush #29172
    //   59: sipush #14686
    //   62: invokestatic a : (II)Ljava/lang/String;
    //   65: aload #6
    //   67: invokevirtual charValue : ()C
    //   70: invokevirtual indexOf : (I)I
    //   73: iconst_m1
    //   74: if_icmpne -> 118
    //   77: goto -> 84
    //   80: invokestatic a : (Ljava/lang/Exception;)Ljava/lang/Exception;
    //   83: athrow
    //   84: bipush #32
    //   86: aload #6
    //   88: invokevirtual charValue : ()C
    //   91: if_icmpgt -> 118
    //   94: goto -> 101
    //   97: invokestatic a : (Ljava/lang/Exception;)Ljava/lang/Exception;
    //   100: athrow
    //   101: aload #6
    //   103: invokevirtual charValue : ()C
    //   106: bipush #126
    //   108: if_icmple -> 644
    //   111: goto -> 118
    //   114: invokestatic a : (Ljava/lang/Exception;)Ljava/lang/Exception;
    //   117: athrow
    //   118: iload #4
    //   120: iload #5
    //   122: if_icmpge -> 166
    //   125: goto -> 132
    //   128: invokestatic a : (Ljava/lang/Exception;)Ljava/lang/Exception;
    //   131: athrow
    //   132: iload #5
    //   134: iload #4
    //   136: isub
    //   137: istore #7
    //   139: aload_0
    //   140: dup
    //   141: getfield Zm : I
    //   144: iload #7
    //   146: iadd
    //   147: putfield Zm : I
    //   150: aload_0
    //   151: getfield ZN : Ljava/io/Writer;
    //   154: aload_1
    //   155: iload #4
    //   157: iload #7
    //   159: invokevirtual write : (Ljava/lang/String;II)V
    //   162: iload #5
    //   164: istore #4
    //   166: aload #6
    //   168: ifnull -> 644
    //   171: getstatic org/yaml/Zb.Z_ : Ljava/util/Map;
    //   174: aload #6
    //   176: invokeinterface containsKey : (Ljava/lang/Object;)Z
    //   181: ifeq -> 228
    //   184: goto -> 191
    //   187: invokestatic a : (Ljava/lang/Exception;)Ljava/lang/Exception;
    //   190: athrow
    //   191: new java/lang/StringBuilder
    //   194: dup
    //   195: invokespecial <init> : ()V
    //   198: ldc '\'
    //   200: invokevirtual append : (Ljava/lang/String;)Ljava/lang/StringBuilder;
    //   203: getstatic org/yaml/Zb.Z_ : Ljava/util/Map;
    //   206: aload #6
    //   208: invokeinterface get : (Ljava/lang/Object;)Ljava/lang/Object;
    //   213: checkcast java/lang/String
    //   216: invokevirtual append : (Ljava/lang/String;)Ljava/lang/StringBuilder;
    //   219: invokevirtual toString : ()Ljava/lang/String;
    //   222: astore #7
    //   224: aload_3
    //   225: ifnonnull -> 615
    //   228: aload #6
    //   230: invokevirtual charValue : ()C
    //   233: invokestatic isHighSurrogate : (C)Z
    //   236: ifeq -> 290
    //   239: goto -> 246
    //   242: invokestatic a : (Ljava/lang/Exception;)Ljava/lang/Exception;
    //   245: athrow
    //   246: iload #5
    //   248: iconst_1
    //   249: iadd
    //   250: aload_1
    //   251: invokevirtual length : ()I
    //   254: if_icmpge -> 290
    //   257: goto -> 264
    //   260: invokestatic a : (Ljava/lang/Exception;)Ljava/lang/Exception;
    //   263: athrow
    //   264: aload_1
    //   265: iload #5
    //   267: iconst_1
    //   268: iadd
    //   269: invokevirtual charAt : (I)C
    //   272: istore #9
    //   274: aload #6
    //   276: invokevirtual charValue : ()C
    //   279: iload #9
    //   281: invokestatic toCodePoint : (CC)I
    //   284: istore #8
    //   286: aload_3
    //   287: ifnonnull -> 297
    //   290: aload #6
    //   292: invokevirtual charValue : ()C
    //   295: istore #8
    //   297: aload_0
    //   298: getfield Zf : Z
    //   301: ifeq -> 352
    //   304: iload #8
    //   306: invokestatic Zf : (I)Z
    //   309: ifeq -> 352
    //   312: goto -> 319
    //   315: invokestatic a : (Ljava/lang/Exception;)Ljava/lang/Exception;
    //   318: athrow
    //   319: iload #8
    //   321: invokestatic toChars : (I)[C
    //   324: invokestatic valueOf : ([C)Ljava/lang/String;
    //   327: astore #7
    //   329: iload #8
    //   331: invokestatic charCount : (I)I
    //   334: iconst_2
    //   335: if_icmpne -> 615
    //   338: iinc #5, 1
    //   341: aload_3
    //   342: ifnonnull -> 615
    //   345: goto -> 352
    //   348: invokestatic a : (Ljava/lang/Exception;)Ljava/lang/Exception;
    //   351: athrow
    //   352: aload #6
    //   354: invokevirtual charValue : ()C
    //   357: sipush #255
    //   360: if_icmpgt -> 443
    //   363: goto -> 370
    //   366: invokestatic a : (Ljava/lang/Exception;)Ljava/lang/Exception;
    //   369: athrow
    //   370: new java/lang/StringBuilder
    //   373: dup
    //   374: invokespecial <init> : ()V
    //   377: ldc '0'
    //   379: invokevirtual append : (Ljava/lang/String;)Ljava/lang/StringBuilder;
    //   382: aload #6
    //   384: invokevirtual charValue : ()C
    //   387: bipush #16
    //   389: invokestatic toString : (II)Ljava/lang/String;
    //   392: invokevirtual append : (Ljava/lang/String;)Ljava/lang/StringBuilder;
    //   395: invokevirtual toString : ()Ljava/lang/String;
    //   398: astore #9
    //   400: new java/lang/StringBuilder
    //   403: dup
    //   404: invokespecial <init> : ()V
    //   407: sipush #29153
    //   410: sipush #7488
    //   413: invokestatic a : (II)Ljava/lang/String;
    //   416: invokevirtual append : (Ljava/lang/String;)Ljava/lang/StringBuilder;
    //   419: aload #9
    //   421: aload #9
    //   423: invokevirtual length : ()I
    //   426: iconst_2
    //   427: isub
    //   428: invokevirtual substring : (I)Ljava/lang/String;
    //   431: invokevirtual append : (Ljava/lang/String;)Ljava/lang/StringBuilder;
    //   434: invokevirtual toString : ()Ljava/lang/String;
    //   437: astore #7
    //   439: aload_3
    //   440: ifnonnull -> 615
    //   443: iload #8
    //   445: invokestatic charCount : (I)I
    //   448: iconst_2
    //   449: if_icmpne -> 539
    //   452: goto -> 459
    //   455: invokestatic a : (Ljava/lang/Exception;)Ljava/lang/Exception;
    //   458: athrow
    //   459: iinc #5, 1
    //   462: new java/lang/StringBuilder
    //   465: dup
    //   466: invokespecial <init> : ()V
    //   469: sipush #29173
    //   472: sipush #1877
    //   475: invokestatic a : (II)Ljava/lang/String;
    //   478: invokevirtual append : (Ljava/lang/String;)Ljava/lang/StringBuilder;
    //   481: iload #8
    //   483: i2l
    //   484: invokestatic toHexString : (J)Ljava/lang/String;
    //   487: invokevirtual append : (Ljava/lang/String;)Ljava/lang/StringBuilder;
    //   490: invokevirtual toString : ()Ljava/lang/String;
    //   493: astore #9
    //   495: new java/lang/StringBuilder
    //   498: dup
    //   499: invokespecial <init> : ()V
    //   502: sipush #29163
    //   505: sipush #-12534
    //   508: invokestatic a : (II)Ljava/lang/String;
    //   511: invokevirtual append : (Ljava/lang/String;)Ljava/lang/StringBuilder;
    //   514: aload #9
    //   516: aload #9
    //   518: invokevirtual length : ()I
    //   521: bipush #8
    //   523: isub
    //   524: invokevirtual substring : (I)Ljava/lang/String;
    //   527: invokevirtual append : (Ljava/lang/String;)Ljava/lang/StringBuilder;
    //   530: invokevirtual toString : ()Ljava/lang/String;
    //   533: astore #7
    //   535: aload_3
    //   536: ifnonnull -> 615
    //   539: new java/lang/StringBuilder
    //   542: dup
    //   543: invokespecial <init> : ()V
    //   546: sipush #29166
    //   549: sipush #-20636
    //   552: invokestatic a : (II)Ljava/lang/String;
    //   555: invokevirtual append : (Ljava/lang/String;)Ljava/lang/StringBuilder;
    //   558: aload #6
    //   560: invokevirtual charValue : ()C
    //   563: bipush #16
    //   565: invokestatic toString : (II)Ljava/lang/String;
    //   568: invokevirtual append : (Ljava/lang/String;)Ljava/lang/StringBuilder;
    //   571: invokevirtual toString : ()Ljava/lang/String;
    //   574: astore #9
    //   576: new java/lang/StringBuilder
    //   579: dup
    //   580: invokespecial <init> : ()V
    //   583: sipush #29150
    //   586: sipush #-16038
    //   589: invokestatic a : (II)Ljava/lang/String;
    //   592: invokevirtual append : (Ljava/lang/String;)Ljava/lang/StringBuilder;
    //   595: aload #9
    //   597: aload #9
    //   599: invokevirtual length : ()I
    //   602: iconst_4
    //   603: isub
    //   604: invokevirtual substring : (I)Ljava/lang/String;
    //   607: invokevirtual append : (Ljava/lang/String;)Ljava/lang/StringBuilder;
    //   610: invokevirtual toString : ()Ljava/lang/String;
    //   613: astore #7
    //   615: aload_0
    //   616: dup
    //   617: getfield Zm : I
    //   620: aload #7
    //   622: invokevirtual length : ()I
    //   625: iadd
    //   626: putfield Zm : I
    //   629: aload_0
    //   630: getfield ZN : Ljava/io/Writer;
    //   633: aload #7
    //   635: invokevirtual write : (Ljava/lang/String;)V
    //   638: iload #5
    //   640: iconst_1
    //   641: iadd
    //   642: istore #4
    //   644: iconst_0
    //   645: iload #5
    //   647: if_icmpge -> 870
    //   650: iload #5
    //   652: aload_1
    //   653: invokevirtual length : ()I
    //   656: iconst_1
    //   657: isub
    //   658: if_icmpge -> 870
    //   661: goto -> 668
    //   664: invokestatic a : (Ljava/lang/Exception;)Ljava/lang/Exception;
    //   667: athrow
    //   668: aload #6
    //   670: invokevirtual charValue : ()C
    //   673: bipush #32
    //   675: if_icmpeq -> 699
    //   678: goto -> 685
    //   681: invokestatic a : (Ljava/lang/Exception;)Ljava/lang/Exception;
    //   684: athrow
    //   685: iload #4
    //   687: iload #5
    //   689: if_icmplt -> 870
    //   692: goto -> 699
    //   695: invokestatic a : (Ljava/lang/Exception;)Ljava/lang/Exception;
    //   698: athrow
    //   699: aload_0
    //   700: getfield Zm : I
    //   703: iload #5
    //   705: iload #4
    //   707: isub
    //   708: iadd
    //   709: aload_0
    //   710: getfield Zd : I
    //   713: if_icmple -> 870
    //   716: goto -> 723
    //   719: invokestatic a : (Ljava/lang/Exception;)Ljava/lang/Exception;
    //   722: athrow
    //   723: iload_2
    //   724: ifeq -> 870
    //   727: goto -> 734
    //   730: invokestatic a : (Ljava/lang/Exception;)Ljava/lang/Exception;
    //   733: athrow
    //   734: iload #4
    //   736: iload #5
    //   738: if_icmplt -> 756
    //   741: goto -> 748
    //   744: invokestatic a : (Ljava/lang/Exception;)Ljava/lang/Exception;
    //   747: athrow
    //   748: ldc '\'
    //   750: astore #7
    //   752: aload_3
    //   753: ifnonnull -> 784
    //   756: new java/lang/StringBuilder
    //   759: dup
    //   760: invokespecial <init> : ()V
    //   763: aload_1
    //   764: iload #4
    //   766: iload #5
    //   768: invokevirtual substring : (II)Ljava/lang/String;
    //   771: invokevirtual append : (Ljava/lang/String;)Ljava/lang/StringBuilder;
    //   774: ldc '\'
    //   776: invokevirtual append : (Ljava/lang/String;)Ljava/lang/StringBuilder;
    //   779: invokevirtual toString : ()Ljava/lang/String;
    //   782: astore #7
    //   784: iload #4
    //   786: iload #5
    //   788: if_icmpge -> 795
    //   791: iload #5
    //   793: istore #4
    //   795: aload_0
    //   796: dup
    //   797: getfield Zm : I
    //   800: aload #7
    //   802: invokevirtual length : ()I
    //   805: iadd
    //   806: putfield Zm : I
    //   809: aload_0
    //   810: getfield ZN : Ljava/io/Writer;
    //   813: aload #7
    //   815: invokevirtual write : (Ljava/lang/String;)V
    //   818: aload_0
    //   819: invokevirtual ZJ : ()V
    //   822: aload_0
    //   823: iconst_0
    //   824: putfield ZI : Z
    //   827: aload_0
    //   828: iconst_0
    //   829: putfield Zh : Z
    //   832: aload_1
    //   833: iload #4
    //   835: invokevirtual charAt : (I)C
    //   838: bipush #32
    //   840: if_icmpne -> 870
    //   843: ldc '\'
    //   845: astore #7
    //   847: aload_0
    //   848: dup
    //   849: getfield Zm : I
    //   852: aload #7
    //   854: invokevirtual length : ()I
    //   857: iadd
    //   858: putfield Zm : I
    //   861: aload_0
    //   862: getfield ZN : Ljava/io/Writer;
    //   865: aload #7
    //   867: invokevirtual write : (Ljava/lang/String;)V
    //   870: iinc #5, 1
    //   873: aload_3
    //   874: ifnonnull -> 19
    //   877: aload_0
    //   878: ldc '"'
    //   880: iconst_0
    //   881: iconst_0
    //   882: iconst_0
    //   883: invokevirtual Zv : (Ljava/lang/String;ZZZ)V
    //   886: return
    // Exception table:
    //   from	to	target	type
    //   51	77	80	java/io/IOException
    //   56	94	97	java/io/IOException
    //   84	111	114	java/io/IOException
    //   101	125	128	java/io/IOException
    //   166	184	187	java/io/IOException
    //   224	239	242	java/io/IOException
    //   228	257	260	java/io/IOException
    //   297	312	315	java/io/IOException
    //   329	345	348	java/io/IOException
    //   338	363	366	java/io/IOException
    //   439	452	455	java/io/IOException
    //   644	661	664	java/io/IOException
    //   650	678	681	java/io/IOException
    //   668	692	695	java/io/IOException
    //   685	716	719	java/io/IOException
    //   699	727	730	java/io/IOException
    //   723	741	744	java/io/IOException
  }
  
  private boolean ZE(List<Zl2> paramList) throws IOException {
    // Byte code:
    //   0: invokestatic ZH : ()Ljava/lang/String;
    //   3: iconst_0
    //   4: istore_3
    //   5: astore_2
    //   6: aload_0
    //   7: getfield Zo : Z
    //   10: ifeq -> 195
    //   13: iconst_0
    //   14: istore #4
    //   16: iconst_1
    //   17: istore #5
    //   19: aload_1
    //   20: invokeinterface iterator : ()Ljava/util/Iterator;
    //   25: astore #6
    //   27: aload #6
    //   29: invokeinterface hasNext : ()Z
    //   34: ifeq -> 195
    //   37: aload #6
    //   39: invokeinterface next : ()Ljava/lang/Object;
    //   44: checkcast org/yaml/Zl2
    //   47: astore #7
    //   49: aload #7
    //   51: invokevirtual Zl : ()Lorg/yaml/Zto;
    //   54: getstatic org/yaml/Zto.BLANK_LINE : Lorg/yaml/Zto;
    //   57: if_acmpeq -> 173
    //   60: iload #5
    //   62: ifeq -> 130
    //   65: goto -> 72
    //   68: invokestatic a : (Ljava/lang/Exception;)Ljava/lang/Exception;
    //   71: athrow
    //   72: iconst_0
    //   73: istore #5
    //   75: aload_0
    //   76: ldc '#'
    //   78: aload #7
    //   80: invokevirtual Zl : ()Lorg/yaml/Zto;
    //   83: getstatic org/yaml/Zto.IN_LINE : Lorg/yaml/Zto;
    //   86: if_acmpne -> 97
    //   89: iconst_1
    //   90: goto -> 98
    //   93: invokestatic a : (Ljava/lang/Exception;)Ljava/lang/Exception;
    //   96: athrow
    //   97: iconst_0
    //   98: iconst_0
    //   99: iconst_0
    //   100: invokevirtual Zv : (Ljava/lang/String;ZZZ)V
    //   103: aload_0
    //   104: getfield Zm : I
    //   107: ifle -> 123
    //   110: aload_0
    //   111: getfield Zm : I
    //   114: iconst_1
    //   115: isub
    //   116: goto -> 124
    //   119: invokestatic a : (Ljava/lang/Exception;)Ljava/lang/Exception;
    //   122: athrow
    //   123: iconst_0
    //   124: istore #4
    //   126: aload_2
    //   127: ifnonnull -> 152
    //   130: aload_0
    //   131: iload #4
    //   133: invokespecial Zx : (I)V
    //   136: aload_0
    //   137: ldc '#'
    //   139: iconst_0
    //   140: iconst_0
    //   141: iconst_0
    //   142: invokevirtual Zv : (Ljava/lang/String;ZZZ)V
    //   145: goto -> 152
    //   148: invokestatic a : (Ljava/lang/Exception;)Ljava/lang/Exception;
    //   151: athrow
    //   152: aload_0
    //   153: getfield ZN : Ljava/io/Writer;
    //   156: aload #7
    //   158: invokevirtual ZS : ()Ljava/lang/String;
    //   161: invokevirtual write : (Ljava/lang/String;)V
    //   164: aload_0
    //   165: aconst_null
    //   166: invokespecial ZH : (Ljava/lang/String;)V
    //   169: aload_2
    //   170: ifnonnull -> 189
    //   173: aload_0
    //   174: aconst_null
    //   175: invokespecial ZH : (Ljava/lang/String;)V
    //   178: aload_0
    //   179: invokevirtual ZJ : ()V
    //   182: goto -> 189
    //   185: invokestatic a : (Ljava/lang/Exception;)Ljava/lang/Exception;
    //   188: athrow
    //   189: iconst_1
    //   190: istore_3
    //   191: aload_2
    //   192: ifnonnull -> 27
    //   195: iload_3
    //   196: ireturn
    // Exception table:
    //   from	to	target	type
    //   49	65	68	java/io/IOException
    //   75	93	93	java/io/IOException
    //   98	119	119	java/io/IOException
    //   126	145	148	java/io/IOException
    //   152	182	185	java/io/IOException
  }
  
  private void Zv() throws IOException {
    try {
      if (!this.ZK.ZR()) {
        ZJ();
        ZE(this.ZK.Zm());
      } 
    } catch (IOException iOException) {
      throw a(null);
    } 
  }
  
  private boolean Zh() throws IOException {
    return ZE(this.ZQ.Zm());
  }
  
  private String ZE(String paramString) {
    // Byte code:
    //   0: invokestatic ZH : ()Ljava/lang/String;
    //   3: new java/lang/StringBuilder
    //   6: dup
    //   7: invokespecial <init> : ()V
    //   10: astore_3
    //   11: astore_2
    //   12: getstatic org/yaml/Z_s.ZV : Lorg/yaml/Z_s;
    //   15: aload_1
    //   16: iconst_0
    //   17: invokevirtual charAt : (I)C
    //   20: ldc ' '
    //   22: invokevirtual Zd : (ILjava/lang/String;)Z
    //   25: ifeq -> 44
    //   28: aload_3
    //   29: aload_0
    //   30: getfield ZE : I
    //   33: invokevirtual append : (I)Ljava/lang/StringBuilder;
    //   36: pop
    //   37: goto -> 44
    //   40: invokestatic a : (Ljava/lang/Exception;)Ljava/lang/Exception;
    //   43: athrow
    //   44: aload_1
    //   45: aload_1
    //   46: invokevirtual length : ()I
    //   49: iconst_1
    //   50: isub
    //   51: invokevirtual charAt : (I)C
    //   54: istore #4
    //   56: getstatic org/yaml/Z_s.ZV : Lorg/yaml/Z_s;
    //   59: iload #4
    //   61: invokevirtual ZS : (I)Z
    //   64: ifeq -> 85
    //   67: aload_3
    //   68: ldc '-'
    //   70: invokevirtual append : (Ljava/lang/String;)Ljava/lang/StringBuilder;
    //   73: pop
    //   74: aload_2
    //   75: ifnonnull -> 140
    //   78: goto -> 85
    //   81: invokestatic a : (Ljava/lang/Exception;)Ljava/lang/Exception;
    //   84: athrow
    //   85: aload_1
    //   86: invokevirtual length : ()I
    //   89: iconst_1
    //   90: if_icmpeq -> 126
    //   93: goto -> 100
    //   96: invokestatic a : (Ljava/lang/Exception;)Ljava/lang/Exception;
    //   99: athrow
    //   100: getstatic org/yaml/Z_s.ZV : Lorg/yaml/Z_s;
    //   103: aload_1
    //   104: aload_1
    //   105: invokevirtual length : ()I
    //   108: iconst_2
    //   109: isub
    //   110: invokevirtual charAt : (I)C
    //   113: invokevirtual Zj : (I)Z
    //   116: ifeq -> 140
    //   119: goto -> 126
    //   122: invokestatic a : (Ljava/lang/Exception;)Ljava/lang/Exception;
    //   125: athrow
    //   126: aload_3
    //   127: ldc '+'
    //   129: invokevirtual append : (Ljava/lang/String;)Ljava/lang/StringBuilder;
    //   132: pop
    //   133: goto -> 140
    //   136: invokestatic a : (Ljava/lang/Exception;)Ljava/lang/Exception;
    //   139: athrow
    //   140: aload_3
    //   141: invokevirtual toString : ()Ljava/lang/String;
    //   144: areturn
    // Exception table:
    //   from	to	target	type
    //   12	37	40	java/lang/NullPointerException
    //   56	78	81	java/lang/NullPointerException
    //   67	93	96	java/lang/NullPointerException
    //   85	119	122	java/lang/NullPointerException
    //   100	133	136	java/lang/NullPointerException
  }
  
  void Zv(String paramString, boolean paramBoolean) throws IOException {
    // Byte code:
    //   0: invokestatic ZH : ()Ljava/lang/String;
    //   3: aload_0
    //   4: aload_1
    //   5: invokespecial ZE : (Ljava/lang/String;)Ljava/lang/String;
    //   8: astore #4
    //   10: aload_0
    //   11: new java/lang/StringBuilder
    //   14: dup
    //   15: invokespecial <init> : ()V
    //   18: ldc '>'
    //   20: invokevirtual append : (Ljava/lang/String;)Ljava/lang/StringBuilder;
    //   23: aload #4
    //   25: invokevirtual append : (Ljava/lang/String;)Ljava/lang/StringBuilder;
    //   28: invokevirtual toString : ()Ljava/lang/String;
    //   31: iconst_1
    //   32: iconst_0
    //   33: iconst_0
    //   34: invokevirtual Zv : (Ljava/lang/String;ZZZ)V
    //   37: astore_3
    //   38: aload #4
    //   40: invokevirtual length : ()I
    //   43: ifle -> 82
    //   46: aload #4
    //   48: aload #4
    //   50: invokevirtual length : ()I
    //   53: iconst_1
    //   54: isub
    //   55: invokevirtual charAt : (I)C
    //   58: bipush #43
    //   60: if_icmpne -> 82
    //   63: goto -> 70
    //   66: invokestatic a : (Ljava/lang/Exception;)Ljava/lang/Exception;
    //   69: athrow
    //   70: aload_0
    //   71: iconst_1
    //   72: putfield ZZ : Z
    //   75: goto -> 82
    //   78: invokestatic a : (Ljava/lang/Exception;)Ljava/lang/Exception;
    //   81: athrow
    //   82: aload_0
    //   83: invokespecial Zh : ()Z
    //   86: ifne -> 101
    //   89: aload_0
    //   90: aconst_null
    //   91: invokespecial ZH : (Ljava/lang/String;)V
    //   94: goto -> 101
    //   97: invokestatic a : (Ljava/lang/Exception;)Ljava/lang/Exception;
    //   100: athrow
    //   101: iconst_1
    //   102: istore #5
    //   104: iconst_0
    //   105: istore #6
    //   107: iconst_1
    //   108: istore #7
    //   110: iconst_0
    //   111: istore #8
    //   113: iconst_0
    //   114: istore #9
    //   116: iload #9
    //   118: aload_1
    //   119: invokevirtual length : ()I
    //   122: if_icmpgt -> 617
    //   125: iconst_0
    //   126: istore #10
    //   128: iload #9
    //   130: aload_1
    //   131: invokevirtual length : ()I
    //   134: if_icmpge -> 145
    //   137: aload_1
    //   138: iload #9
    //   140: invokevirtual charAt : (I)C
    //   143: istore #10
    //   145: iload #7
    //   147: ifeq -> 375
    //   150: iload #10
    //   152: ifeq -> 180
    //   155: goto -> 162
    //   158: invokestatic a : (Ljava/lang/Exception;)Ljava/lang/Exception;
    //   161: athrow
    //   162: getstatic org/yaml/Z_s.ZV : Lorg/yaml/Z_s;
    //   165: iload #10
    //   167: invokevirtual ZS : (I)Z
    //   170: ifeq -> 577
    //   173: goto -> 180
    //   176: invokestatic a : (Ljava/lang/Exception;)Ljava/lang/Exception;
    //   179: athrow
    //   180: iload #5
    //   182: ifne -> 248
    //   185: goto -> 192
    //   188: invokestatic a : (Ljava/lang/Exception;)Ljava/lang/Exception;
    //   191: athrow
    //   192: iload #10
    //   194: ifeq -> 248
    //   197: goto -> 204
    //   200: invokestatic a : (Ljava/lang/Exception;)Ljava/lang/Exception;
    //   203: athrow
    //   204: iload #10
    //   206: bipush #32
    //   208: if_icmpeq -> 248
    //   211: goto -> 218
    //   214: invokestatic a : (Ljava/lang/Exception;)Ljava/lang/Exception;
    //   217: athrow
    //   218: aload_1
    //   219: iload #8
    //   221: invokevirtual charAt : (I)C
    //   224: bipush #10
    //   226: if_icmpne -> 248
    //   229: goto -> 236
    //   232: invokestatic a : (Ljava/lang/Exception;)Ljava/lang/Exception;
    //   235: athrow
    //   236: aload_0
    //   237: aconst_null
    //   238: invokespecial ZH : (Ljava/lang/String;)V
    //   241: goto -> 248
    //   244: invokestatic a : (Ljava/lang/Exception;)Ljava/lang/Exception;
    //   247: athrow
    //   248: iload #10
    //   250: bipush #32
    //   252: if_icmpne -> 263
    //   255: iconst_1
    //   256: goto -> 264
    //   259: invokestatic a : (Ljava/lang/Exception;)Ljava/lang/Exception;
    //   262: athrow
    //   263: iconst_0
    //   264: istore #5
    //   266: aload_1
    //   267: iload #8
    //   269: iload #9
    //   271: invokevirtual substring : (II)Ljava/lang/String;
    //   274: astore #11
    //   276: aload #11
    //   278: invokevirtual toCharArray : ()[C
    //   281: astore #12
    //   283: aload #12
    //   285: arraylength
    //   286: istore #13
    //   288: iconst_0
    //   289: istore #14
    //   291: iload #14
    //   293: iload #13
    //   295: if_icmpge -> 351
    //   298: aload #12
    //   300: iload #14
    //   302: caload
    //   303: istore #15
    //   305: iload #15
    //   307: bipush #10
    //   309: if_icmpne -> 328
    //   312: aload_0
    //   313: aconst_null
    //   314: invokespecial ZH : (Ljava/lang/String;)V
    //   317: aload_3
    //   318: ifnonnull -> 344
    //   321: goto -> 328
    //   324: invokestatic a : (Ljava/lang/Exception;)Ljava/lang/Exception;
    //   327: athrow
    //   328: aload_0
    //   329: iload #15
    //   331: invokestatic valueOf : (C)Ljava/lang/String;
    //   334: invokespecial ZH : (Ljava/lang/String;)V
    //   337: goto -> 344
    //   340: invokestatic a : (Ljava/lang/Exception;)Ljava/lang/Exception;
    //   343: athrow
    //   344: iinc #14, 1
    //   347: aload_3
    //   348: ifnonnull -> 291
    //   351: iload #10
    //   353: ifeq -> 367
    //   356: aload_0
    //   357: invokevirtual ZJ : ()V
    //   360: goto -> 367
    //   363: invokestatic a : (Ljava/lang/Exception;)Ljava/lang/Exception;
    //   366: athrow
    //   367: iload #9
    //   369: istore #8
    //   371: aload_3
    //   372: ifnonnull -> 577
    //   375: iload #6
    //   377: ifeq -> 499
    //   380: goto -> 387
    //   383: invokestatic a : (Ljava/lang/Exception;)Ljava/lang/Exception;
    //   386: athrow
    //   387: iload #10
    //   389: bipush #32
    //   391: if_icmpeq -> 577
    //   394: goto -> 401
    //   397: invokestatic a : (Ljava/lang/Exception;)Ljava/lang/Exception;
    //   400: athrow
    //   401: iload #8
    //   403: iconst_1
    //   404: iadd
    //   405: iload #9
    //   407: if_icmpne -> 461
    //   410: goto -> 417
    //   413: invokestatic a : (Ljava/lang/Exception;)Ljava/lang/Exception;
    //   416: athrow
    //   417: aload_0
    //   418: getfield Zm : I
    //   421: aload_0
    //   422: getfield Zd : I
    //   425: if_icmple -> 461
    //   428: goto -> 435
    //   431: invokestatic a : (Ljava/lang/Exception;)Ljava/lang/Exception;
    //   434: athrow
    //   435: iload_2
    //   436: ifeq -> 461
    //   439: goto -> 446
    //   442: invokestatic a : (Ljava/lang/Exception;)Ljava/lang/Exception;
    //   445: athrow
    //   446: aload_0
    //   447: invokevirtual ZJ : ()V
    //   450: aload_3
    //   451: ifnonnull -> 491
    //   454: goto -> 461
    //   457: invokestatic a : (Ljava/lang/Exception;)Ljava/lang/Exception;
    //   460: athrow
    //   461: iload #9
    //   463: iload #8
    //   465: isub
    //   466: istore #11
    //   468: aload_0
    //   469: dup
    //   470: getfield Zm : I
    //   473: iload #11
    //   475: iadd
    //   476: putfield Zm : I
    //   479: aload_0
    //   480: getfield ZN : Ljava/io/Writer;
    //   483: aload_1
    //   484: iload #8
    //   486: iload #11
    //   488: invokevirtual write : (Ljava/lang/String;II)V
    //   491: iload #9
    //   493: istore #8
    //   495: aload_3
    //   496: ifnonnull -> 577
    //   499: getstatic org/yaml/Z_s.ZV : Lorg/yaml/Z_s;
    //   502: iload #10
    //   504: sipush #29149
    //   507: sipush #-1403
    //   510: invokestatic a : (II)Ljava/lang/String;
    //   513: invokevirtual Zd : (ILjava/lang/String;)Z
    //   516: ifeq -> 577
    //   519: goto -> 526
    //   522: invokestatic a : (Ljava/lang/Exception;)Ljava/lang/Exception;
    //   525: athrow
    //   526: iload #9
    //   528: iload #8
    //   530: isub
    //   531: istore #11
    //   533: aload_0
    //   534: dup
    //   535: getfield Zm : I
    //   538: iload #11
    //   540: iadd
    //   541: putfield Zm : I
    //   544: aload_0
    //   545: getfield ZN : Ljava/io/Writer;
    //   548: aload_1
    //   549: iload #8
    //   551: iload #11
    //   553: invokevirtual write : (Ljava/lang/String;II)V
    //   556: iload #10
    //   558: ifne -> 573
    //   561: aload_0
    //   562: aconst_null
    //   563: invokespecial ZH : (Ljava/lang/String;)V
    //   566: goto -> 573
    //   569: invokestatic a : (Ljava/lang/Exception;)Ljava/lang/Exception;
    //   572: athrow
    //   573: iload #9
    //   575: istore #8
    //   577: iload #10
    //   579: ifeq -> 610
    //   582: getstatic org/yaml/Z_s.ZV : Lorg/yaml/Z_s;
    //   585: iload #10
    //   587: invokevirtual Zj : (I)Z
    //   590: istore #7
    //   592: iload #10
    //   594: bipush #32
    //   596: if_icmpne -> 607
    //   599: iconst_1
    //   600: goto -> 608
    //   603: invokestatic a : (Ljava/lang/Exception;)Ljava/lang/Exception;
    //   606: athrow
    //   607: iconst_0
    //   608: istore #6
    //   610: iinc #9, 1
    //   613: aload_3
    //   614: ifnonnull -> 116
    //   617: return
    // Exception table:
    //   from	to	target	type
    //   38	63	66	java/io/IOException
    //   46	75	78	java/io/IOException
    //   82	94	97	java/io/IOException
    //   145	155	158	java/io/IOException
    //   150	173	176	java/io/IOException
    //   162	185	188	java/io/IOException
    //   180	197	200	java/io/IOException
    //   192	211	214	java/io/IOException
    //   204	229	232	java/io/IOException
    //   218	241	244	java/io/IOException
    //   248	259	259	java/io/IOException
    //   305	321	324	java/io/IOException
    //   312	337	340	java/io/IOException
    //   351	360	363	java/io/IOException
    //   371	380	383	java/io/IOException
    //   375	394	397	java/io/IOException
    //   387	410	413	java/io/IOException
    //   401	428	431	java/io/IOException
    //   417	439	442	java/io/IOException
    //   435	454	457	java/io/IOException
    //   495	519	522	java/io/IOException
    //   533	566	569	java/io/IOException
    //   592	603	603	java/io/IOException
  }
  
  void Zp(String paramString) throws IOException {
    // Byte code:
    //   0: aload_0
    //   1: aload_1
    //   2: invokespecial ZE : (Ljava/lang/String;)Ljava/lang/String;
    //   5: astore_3
    //   6: invokestatic ZH : ()Ljava/lang/String;
    //   9: aload_0
    //   10: new java/lang/StringBuilder
    //   13: dup
    //   14: invokespecial <init> : ()V
    //   17: ldc '|'
    //   19: invokevirtual append : (Ljava/lang/String;)Ljava/lang/StringBuilder;
    //   22: aload_3
    //   23: invokevirtual append : (Ljava/lang/String;)Ljava/lang/StringBuilder;
    //   26: invokevirtual toString : ()Ljava/lang/String;
    //   29: iconst_1
    //   30: iconst_0
    //   31: iconst_0
    //   32: invokevirtual Zv : (Ljava/lang/String;ZZZ)V
    //   35: astore_2
    //   36: aload_3
    //   37: invokevirtual length : ()I
    //   40: ifle -> 77
    //   43: aload_3
    //   44: aload_3
    //   45: invokevirtual length : ()I
    //   48: iconst_1
    //   49: isub
    //   50: invokevirtual charAt : (I)C
    //   53: bipush #43
    //   55: if_icmpne -> 77
    //   58: goto -> 65
    //   61: invokestatic a : (Ljava/lang/Exception;)Ljava/lang/Exception;
    //   64: athrow
    //   65: aload_0
    //   66: iconst_1
    //   67: putfield ZZ : Z
    //   70: goto -> 77
    //   73: invokestatic a : (Ljava/lang/Exception;)Ljava/lang/Exception;
    //   76: athrow
    //   77: aload_0
    //   78: invokespecial Zh : ()Z
    //   81: ifne -> 96
    //   84: aload_0
    //   85: aconst_null
    //   86: invokespecial ZH : (Ljava/lang/String;)V
    //   89: goto -> 96
    //   92: invokestatic a : (Ljava/lang/Exception;)Ljava/lang/Exception;
    //   95: athrow
    //   96: iconst_1
    //   97: istore #4
    //   99: iconst_0
    //   100: istore #5
    //   102: iconst_0
    //   103: istore #6
    //   105: iload #6
    //   107: aload_1
    //   108: invokevirtual length : ()I
    //   111: if_icmpgt -> 373
    //   114: iconst_0
    //   115: istore #7
    //   117: iload #6
    //   119: aload_1
    //   120: invokevirtual length : ()I
    //   123: if_icmpge -> 134
    //   126: aload_1
    //   127: iload #6
    //   129: invokevirtual charAt : (I)C
    //   132: istore #7
    //   134: iload #4
    //   136: ifeq -> 278
    //   139: iload #7
    //   141: ifeq -> 169
    //   144: goto -> 151
    //   147: invokestatic a : (Ljava/lang/Exception;)Ljava/lang/Exception;
    //   150: athrow
    //   151: getstatic org/yaml/Z_s.ZV : Lorg/yaml/Z_s;
    //   154: iload #7
    //   156: invokevirtual ZS : (I)Z
    //   159: ifeq -> 351
    //   162: goto -> 169
    //   165: invokestatic a : (Ljava/lang/Exception;)Ljava/lang/Exception;
    //   168: athrow
    //   169: aload_1
    //   170: iload #5
    //   172: iload #6
    //   174: invokevirtual substring : (II)Ljava/lang/String;
    //   177: astore #8
    //   179: aload #8
    //   181: invokevirtual toCharArray : ()[C
    //   184: astore #9
    //   186: aload #9
    //   188: arraylength
    //   189: istore #10
    //   191: iconst_0
    //   192: istore #11
    //   194: iload #11
    //   196: iload #10
    //   198: if_icmpge -> 254
    //   201: aload #9
    //   203: iload #11
    //   205: caload
    //   206: istore #12
    //   208: iload #12
    //   210: bipush #10
    //   212: if_icmpne -> 231
    //   215: aload_0
    //   216: aconst_null
    //   217: invokespecial ZH : (Ljava/lang/String;)V
    //   220: aload_2
    //   221: ifnonnull -> 247
    //   224: goto -> 231
    //   227: invokestatic a : (Ljava/lang/Exception;)Ljava/lang/Exception;
    //   230: athrow
    //   231: aload_0
    //   232: iload #12
    //   234: invokestatic valueOf : (C)Ljava/lang/String;
    //   237: invokespecial ZH : (Ljava/lang/String;)V
    //   240: goto -> 247
    //   243: invokestatic a : (Ljava/lang/Exception;)Ljava/lang/Exception;
    //   246: athrow
    //   247: iinc #11, 1
    //   250: aload_2
    //   251: ifnonnull -> 194
    //   254: iload #7
    //   256: ifeq -> 270
    //   259: aload_0
    //   260: invokevirtual ZJ : ()V
    //   263: goto -> 270
    //   266: invokestatic a : (Ljava/lang/Exception;)Ljava/lang/Exception;
    //   269: athrow
    //   270: iload #6
    //   272: istore #5
    //   274: aload_2
    //   275: ifnonnull -> 351
    //   278: iload #7
    //   280: ifeq -> 308
    //   283: goto -> 290
    //   286: invokestatic a : (Ljava/lang/Exception;)Ljava/lang/Exception;
    //   289: athrow
    //   290: getstatic org/yaml/Z_s.ZV : Lorg/yaml/Z_s;
    //   293: iload #7
    //   295: invokevirtual Zj : (I)Z
    //   298: ifeq -> 351
    //   301: goto -> 308
    //   304: invokestatic a : (Ljava/lang/Exception;)Ljava/lang/Exception;
    //   307: athrow
    //   308: aload_0
    //   309: getfield ZN : Ljava/io/Writer;
    //   312: aload_1
    //   313: iload #5
    //   315: iload #6
    //   317: iload #5
    //   319: isub
    //   320: invokevirtual write : (Ljava/lang/String;II)V
    //   323: iload #7
    //   325: ifne -> 347
    //   328: goto -> 335
    //   331: invokestatic a : (Ljava/lang/Exception;)Ljava/lang/Exception;
    //   334: athrow
    //   335: aload_0
    //   336: aconst_null
    //   337: invokespecial ZH : (Ljava/lang/String;)V
    //   340: goto -> 347
    //   343: invokestatic a : (Ljava/lang/Exception;)Ljava/lang/Exception;
    //   346: athrow
    //   347: iload #6
    //   349: istore #5
    //   351: iload #7
    //   353: ifeq -> 366
    //   356: getstatic org/yaml/Z_s.ZV : Lorg/yaml/Z_s;
    //   359: iload #7
    //   361: invokevirtual Zj : (I)Z
    //   364: istore #4
    //   366: iinc #6, 1
    //   369: aload_2
    //   370: ifnonnull -> 105
    //   373: return
    // Exception table:
    //   from	to	target	type
    //   36	58	61	java/io/IOException
    //   43	70	73	java/io/IOException
    //   77	89	92	java/io/IOException
    //   134	144	147	java/io/IOException
    //   139	162	165	java/io/IOException
    //   208	224	227	java/io/IOException
    //   215	240	243	java/io/IOException
    //   254	263	266	java/io/IOException
    //   274	283	286	java/io/IOException
    //   278	301	304	java/io/IOException
    //   290	328	331	java/io/IOException
    //   308	340	343	java/io/IOException
  }
  
  void Zq(String paramString, boolean paramBoolean) throws IOException {
    // Byte code:
    //   0: invokestatic ZH : ()Ljava/lang/String;
    //   3: astore_3
    //   4: aload_0
    //   5: getfield ZJ : Z
    //   8: ifeq -> 23
    //   11: aload_0
    //   12: iconst_1
    //   13: putfield ZZ : Z
    //   16: goto -> 23
    //   19: invokestatic a : (Ljava/lang/Exception;)Ljava/lang/Exception;
    //   22: athrow
    //   23: aload_1
    //   24: invokevirtual length : ()I
    //   27: ifne -> 35
    //   30: return
    //   31: invokestatic a : (Ljava/lang/Exception;)Ljava/lang/Exception;
    //   34: athrow
    //   35: aload_0
    //   36: getfield ZI : Z
    //   39: ifne -> 69
    //   42: aload_0
    //   43: dup
    //   44: getfield Zm : I
    //   47: iconst_1
    //   48: iadd
    //   49: putfield Zm : I
    //   52: aload_0
    //   53: getfield ZN : Ljava/io/Writer;
    //   56: getstatic org/yaml/Zb.Zy : [C
    //   59: invokevirtual write : ([C)V
    //   62: goto -> 69
    //   65: invokestatic a : (Ljava/lang/Exception;)Ljava/lang/Exception;
    //   68: athrow
    //   69: aload_0
    //   70: iconst_0
    //   71: putfield ZI : Z
    //   74: aload_0
    //   75: iconst_0
    //   76: putfield Zh : Z
    //   79: iconst_0
    //   80: istore #4
    //   82: iconst_0
    //   83: istore #5
    //   85: iconst_0
    //   86: istore #6
    //   88: iconst_0
    //   89: istore #7
    //   91: iload #7
    //   93: aload_1
    //   94: invokevirtual length : ()I
    //   97: if_icmpgt -> 522
    //   100: iconst_0
    //   101: istore #8
    //   103: iload #7
    //   105: aload_1
    //   106: invokevirtual length : ()I
    //   109: if_icmpge -> 120
    //   112: aload_1
    //   113: iload #7
    //   115: invokevirtual charAt : (I)C
    //   118: istore #8
    //   120: iload #4
    //   122: ifeq -> 247
    //   125: iload #8
    //   127: bipush #32
    //   129: if_icmpeq -> 475
    //   132: goto -> 139
    //   135: invokestatic a : (Ljava/lang/Exception;)Ljava/lang/Exception;
    //   138: athrow
    //   139: iload #6
    //   141: iconst_1
    //   142: iadd
    //   143: iload #7
    //   145: if_icmpne -> 209
    //   148: goto -> 155
    //   151: invokestatic a : (Ljava/lang/Exception;)Ljava/lang/Exception;
    //   154: athrow
    //   155: aload_0
    //   156: getfield Zm : I
    //   159: aload_0
    //   160: getfield Zd : I
    //   163: if_icmple -> 209
    //   166: goto -> 173
    //   169: invokestatic a : (Ljava/lang/Exception;)Ljava/lang/Exception;
    //   172: athrow
    //   173: iload_2
    //   174: ifeq -> 209
    //   177: goto -> 184
    //   180: invokestatic a : (Ljava/lang/Exception;)Ljava/lang/Exception;
    //   183: athrow
    //   184: aload_0
    //   185: invokevirtual ZJ : ()V
    //   188: aload_0
    //   189: iconst_0
    //   190: putfield ZI : Z
    //   193: aload_0
    //   194: iconst_0
    //   195: putfield Zh : Z
    //   198: aload_3
    //   199: ifnonnull -> 239
    //   202: goto -> 209
    //   205: invokestatic a : (Ljava/lang/Exception;)Ljava/lang/Exception;
    //   208: athrow
    //   209: iload #7
    //   211: iload #6
    //   213: isub
    //   214: istore #9
    //   216: aload_0
    //   217: dup
    //   218: getfield Zm : I
    //   221: iload #9
    //   223: iadd
    //   224: putfield Zm : I
    //   227: aload_0
    //   228: getfield ZN : Ljava/io/Writer;
    //   231: aload_1
    //   232: iload #6
    //   234: iload #9
    //   236: invokevirtual write : (Ljava/lang/String;II)V
    //   239: iload #7
    //   241: istore #6
    //   243: aload_3
    //   244: ifnonnull -> 475
    //   247: iload #5
    //   249: ifeq -> 414
    //   252: goto -> 259
    //   255: invokestatic a : (Ljava/lang/Exception;)Ljava/lang/Exception;
    //   258: athrow
    //   259: getstatic org/yaml/Z_s.ZV : Lorg/yaml/Z_s;
    //   262: iload #8
    //   264: invokevirtual ZS : (I)Z
    //   267: ifeq -> 475
    //   270: goto -> 277
    //   273: invokestatic a : (Ljava/lang/Exception;)Ljava/lang/Exception;
    //   276: athrow
    //   277: aload_1
    //   278: iload #6
    //   280: invokevirtual charAt : (I)C
    //   283: bipush #10
    //   285: if_icmpne -> 307
    //   288: goto -> 295
    //   291: invokestatic a : (Ljava/lang/Exception;)Ljava/lang/Exception;
    //   294: athrow
    //   295: aload_0
    //   296: aconst_null
    //   297: invokespecial ZH : (Ljava/lang/String;)V
    //   300: goto -> 307
    //   303: invokestatic a : (Ljava/lang/Exception;)Ljava/lang/Exception;
    //   306: athrow
    //   307: aload_1
    //   308: iload #6
    //   310: iload #7
    //   312: invokevirtual substring : (II)Ljava/lang/String;
    //   315: astore #9
    //   317: aload #9
    //   319: invokevirtual toCharArray : ()[C
    //   322: astore #10
    //   324: aload #10
    //   326: arraylength
    //   327: istore #11
    //   329: iconst_0
    //   330: istore #12
    //   332: iload #12
    //   334: iload #11
    //   336: if_icmpge -> 392
    //   339: aload #10
    //   341: iload #12
    //   343: caload
    //   344: istore #13
    //   346: iload #13
    //   348: bipush #10
    //   350: if_icmpne -> 369
    //   353: aload_0
    //   354: aconst_null
    //   355: invokespecial ZH : (Ljava/lang/String;)V
    //   358: aload_3
    //   359: ifnonnull -> 385
    //   362: goto -> 369
    //   365: invokestatic a : (Ljava/lang/Exception;)Ljava/lang/Exception;
    //   368: athrow
    //   369: aload_0
    //   370: iload #13
    //   372: invokestatic valueOf : (C)Ljava/lang/String;
    //   375: invokespecial ZH : (Ljava/lang/String;)V
    //   378: goto -> 385
    //   381: invokestatic a : (Ljava/lang/Exception;)Ljava/lang/Exception;
    //   384: athrow
    //   385: iinc #12, 1
    //   388: aload_3
    //   389: ifnonnull -> 332
    //   392: aload_0
    //   393: invokevirtual ZJ : ()V
    //   396: aload_0
    //   397: iconst_0
    //   398: putfield ZI : Z
    //   401: aload_0
    //   402: iconst_0
    //   403: putfield Zh : Z
    //   406: iload #7
    //   408: istore #6
    //   410: aload_3
    //   411: ifnonnull -> 475
    //   414: getstatic org/yaml/Z_s.ZV : Lorg/yaml/Z_s;
    //   417: iload #8
    //   419: sipush #29165
    //   422: sipush #-27352
    //   425: invokestatic a : (II)Ljava/lang/String;
    //   428: invokevirtual Zd : (ILjava/lang/String;)Z
    //   431: ifeq -> 475
    //   434: goto -> 441
    //   437: invokestatic a : (Ljava/lang/Exception;)Ljava/lang/Exception;
    //   440: athrow
    //   441: iload #7
    //   443: iload #6
    //   445: isub
    //   446: istore #9
    //   448: aload_0
    //   449: dup
    //   450: getfield Zm : I
    //   453: iload #9
    //   455: iadd
    //   456: putfield Zm : I
    //   459: aload_0
    //   460: getfield ZN : Ljava/io/Writer;
    //   463: aload_1
    //   464: iload #6
    //   466: iload #9
    //   468: invokevirtual write : (Ljava/lang/String;II)V
    //   471: iload #7
    //   473: istore #6
    //   475: iload #8
    //   477: ifeq -> 515
    //   480: iload #8
    //   482: bipush #32
    //   484: if_icmpne -> 502
    //   487: goto -> 494
    //   490: invokestatic a : (Ljava/lang/Exception;)Ljava/lang/Exception;
    //   493: athrow
    //   494: iconst_1
    //   495: goto -> 503
    //   498: invokestatic a : (Ljava/lang/Exception;)Ljava/lang/Exception;
    //   501: athrow
    //   502: iconst_0
    //   503: istore #4
    //   505: getstatic org/yaml/Z_s.ZV : Lorg/yaml/Z_s;
    //   508: iload #8
    //   510: invokevirtual Zj : (I)Z
    //   513: istore #5
    //   515: iinc #7, 1
    //   518: aload_3
    //   519: ifnonnull -> 91
    //   522: return
    // Exception table:
    //   from	to	target	type
    //   4	16	19	java/io/IOException
    //   23	31	31	java/io/IOException
    //   35	62	65	java/io/IOException
    //   120	132	135	java/io/IOException
    //   125	148	151	java/io/IOException
    //   139	166	169	java/io/IOException
    //   155	177	180	java/io/IOException
    //   173	202	205	java/io/IOException
    //   243	252	255	java/io/IOException
    //   247	270	273	java/io/IOException
    //   259	288	291	java/io/IOException
    //   277	300	303	java/io/IOException
    //   346	362	365	java/io/IOException
    //   353	378	381	java/io/IOException
    //   410	434	437	java/io/IOException
    //   475	487	490	java/io/IOException
    //   480	498	498	java/io/IOException
  }
  
  static Zlv ZJ(Zb paramZb) {
    return paramZb.Zw;
  }
  
  static Zd ZB(Zb paramZb, Zd paramZd) {
    return paramZb.Zv = paramZd;
  }
  
  static boolean Zs(Zb paramZb) {
    return paramZb.ZZ;
  }
  
  static String Zi(Zb paramZb, Zjv paramZjv) {
    return paramZb.ZV(paramZjv);
  }
  
  static Map ZR(Zb paramZb, Map<String, String> paramMap) {
    return paramZb.ZY = paramMap;
  }
  
  static Map ZC() {
    return Zt;
  }
  
  static Map ZT(Zb paramZb) {
    return paramZb.ZY;
  }
  
  static String Zo(Zb paramZb, String paramString) {
    return paramZb.ZS(paramString);
  }
  
  static String ZP(Zb paramZb, String paramString) {
    return paramZb.Zz(paramString);
  }
  
  static Boolean ZP(Zb paramZb) {
    return paramZb.ZA;
  }
  
  static boolean ZY(Zb paramZb) {
    return paramZb.ZS();
  }
  
  static Zj8 ZM(Zb paramZb) {
    return paramZb.ZK;
  }
  
  static void ZB(Zb paramZb) throws IOException {
    paramZb.Zv();
  }
  
  static Zlv Za(Zb paramZb, Zlv paramZlv) {
    return paramZb.Zw = paramZlv;
  }
  
  static Zq Za(Zb paramZb) {
    return paramZb.Zu;
  }
  
  static void Zu(Zb paramZb, boolean paramBoolean1, boolean paramBoolean2, boolean paramBoolean3) throws IOException {
    paramZb.Zg(paramBoolean1, paramBoolean2, paramBoolean3);
  }
  
  static Integer ZE(Zb paramZb, Integer paramInteger) {
    return paramZb.Zn = paramInteger;
  }
  
  static Zq Zf(Zb paramZb) {
    return paramZb.Zg;
  }
  
  static int Zb(Zb paramZb) {
    return paramZb.Zk--;
  }
  
  static Zj8 ZS(Zb paramZb) {
    return paramZb.ZQ;
  }
  
  static boolean Zl(Zb paramZb) throws IOException {
    return paramZb.Zh();
  }
  
  static int Zt(Zb paramZb) {
    return paramZb.Zm;
  }
  
  static int Z_(Zb paramZb) {
    return paramZb.Zd;
  }
  
  static boolean Zc(Zb paramZb) {
    return paramZb.ZW;
  }
  
  static Boolean ZN(Zb paramZb) {
    return paramZb.Zx;
  }
  
  static boolean Zo(Zb paramZb) {
    return paramZb.Zi();
  }
  
  static boolean ZL(Zb paramZb) {
    return paramZb.ZX;
  }
  
  static int ZU(Zb paramZb) {
    return paramZb.Zl;
  }
  
  static void Zx(Zb paramZb, int paramInt) throws IOException {
    paramZb.Zx(paramInt);
  }
  
  static Integer Zy(Zb paramZb) {
    return paramZb.Zn;
  }
  
  static void ZE(Zb paramZb, boolean paramBoolean1, boolean paramBoolean2) {
    paramZb.Zq(paramBoolean1, paramBoolean2);
  }
  
  static Zjb ZB(Zb paramZb, Zjb paramZjb) {
    return paramZb.ZF = paramZjb;
  }
  
  static Zjb ZA(Zb paramZb, String paramString) {
    return paramZb.ZD(paramString);
  }
  
  static Zjb Zd(Zb paramZb) {
    return paramZb.ZF;
  }
  
  static boolean Zk(Zb paramZb, Zlv paramZlv) {
    return paramZb.Zc(paramZlv);
  }
  
  static {
    // Byte code:
    //   0: bipush #37
    //   2: anewarray java/lang/String
    //   5: astore #5
    //   7: ldc 'Nby7Tc'
    //   9: iconst_0
    //   10: istore_3
    //   11: ldc 'z\\teDl~$BBge&d]hxT=CGCtpvaJ,paqXOdjW-1,~Y~|p,P):)[L*yp;O5Gm$2tV7)\\bDX~||O?=!E\\tpDQ2MSJppx(EIL)>'r0qKwNcBc7FemD1E+?ke+M.xNiOD=\\b)dL\\r*K1gs4cI%\\rO2]CnA[?\\n\%l'gK \\rJG09G;].[n!_'-u(!'e/=`goy}mE5?ejp1(h$}yMl_Wii]fZ;1Q'
    //   13: dup
    //   14: astore_2
    //   15: invokevirtual length : ()I
    //   18: istore #4
    //   20: bipush #18
    //   22: istore_1
    //   23: invokestatic Zu : (Ljava/lang/String;)V
    //   26: iconst_m1
    //   27: istore_0
    //   28: bipush #111
    //   30: iinc #0, 1
    //   33: aload_2
    //   34: iload_0
    //   35: dup
    //   36: iload_1
    //   37: iadd
    //   38: invokevirtual substring : (II)Ljava/lang/String;
    //   41: iconst_m1
    //   42: goto -> 147
    //   45: aload #5
    //   47: swap
    //   48: iload_3
    //   49: iinc #3, 1
    //   52: swap
    //   53: aastore
    //   54: iload_0
    //   55: iload_1
    //   56: iadd
    //   57: dup
    //   58: istore_0
    //   59: iload #4
    //   61: if_icmpge -> 73
    //   64: aload_2
    //   65: iload_0
    //   66: invokevirtual charAt : (I)C
    //   69: istore_1
    //   70: goto -> 28
    //   73: ldc '(_'
    //   75: dup
    //   76: astore_2
    //   77: invokevirtual length : ()I
    //   80: istore #4
    //   82: iconst_2
    //   83: istore_1
    //   84: iconst_m1
    //   85: istore_0
    //   86: bipush #68
    //   88: iinc #0, 1
    //   91: aload_2
    //   92: iload_0
    //   93: dup
    //   94: iload_1
    //   95: iadd
    //   96: invokevirtual substring : (II)Ljava/lang/String;
    //   99: iconst_0
    //   100: goto -> 147
    //   103: aload #5
    //   105: swap
    //   106: iload_3
    //   107: iinc #3, 1
    //   110: swap
    //   111: aastore
    //   112: iload_0
    //   113: iload_1
    //   114: iadd
    //   115: dup
    //   116: istore_0
    //   117: iload #4
    //   119: if_icmpge -> 131
    //   122: aload_2
    //   123: iload_0
    //   124: invokevirtual charAt : (I)C
    //   127: istore_1
    //   128: goto -> 86
    //   131: aload #5
    //   133: putstatic org/yaml/Zb.a : [Ljava/lang/String;
    //   136: bipush #37
    //   138: anewarray java/lang/String
    //   141: putstatic org/yaml/Zb.b : [Ljava/lang/String;
    //   144: goto -> 304
    //   147: dup_x2
    //   148: pop
    //   149: invokevirtual toCharArray : ()[C
    //   152: dup_x1
    //   153: arraylength
    //   154: dup_x2
    //   155: pop
    //   156: iconst_0
    //   157: istore #6
    //   159: dup2_x1
    //   160: pop2
    //   161: dup_x2
    //   162: iconst_1
    //   163: if_icmpgt -> 264
    //   166: dup2
    //   167: swap
    //   168: iload #6
    //   170: dup2_x1
    //   171: caload
    //   172: swap
    //   173: iload #6
    //   175: bipush #7
    //   177: irem
    //   178: tableswitch default -> 246, 0 -> 216, 1 -> 221, 2 -> 226, 3 -> 231, 4 -> 236, 5 -> 241
    //   216: bipush #88
    //   218: goto -> 248
    //   221: bipush #93
    //   223: goto -> 248
    //   226: bipush #85
    //   228: goto -> 248
    //   231: bipush #24
    //   233: goto -> 248
    //   236: bipush #72
    //   238: goto -> 248
    //   241: bipush #83
    //   243: goto -> 248
    //   246: bipush #88
    //   248: ixor
    //   249: ixor
    //   250: i2c
    //   251: castore
    //   252: iinc #6, 1
    //   255: dup
    //   256: ifne -> 264
    //   259: dup2
    //   260: dup_x1
    //   261: goto -> 170
    //   264: dup2_x1
    //   265: pop2
    //   266: dup_x2
    //   267: iload #6
    //   269: if_icmpgt -> 166
    //   272: pop
    //   273: new java/lang/String
    //   276: dup_x1
    //   277: swap
    //   278: invokespecial <init> : ([C)V
    //   281: invokevirtual intern : ()Ljava/lang/String;
    //   284: swap
    //   285: pop
    //   286: swap
    //   287: tableswitch default -> 45, 0 -> 103
    //   304: sipush #29169
    //   307: iconst_1
    //   308: newarray char
    //   310: dup
    //   311: iconst_0
    //   312: bipush #32
    //   314: castore
    //   315: putstatic org/yaml/Zb.Zy : [C
    //   318: sipush #-23790
    //   321: invokestatic a : (II)Ljava/lang/String;
    //   324: invokestatic compile : (Ljava/lang/String;)Ljava/util/regex/Pattern;
    //   327: putstatic org/yaml/Zb.ZO : Ljava/util/regex/Pattern;
    //   330: new java/util/HashSet
    //   333: dup
    //   334: invokespecial <init> : ()V
    //   337: putstatic org/yaml/Zb.ZV : Ljava/util/Set;
    //   340: getstatic org/yaml/Zb.ZV : Ljava/util/Set;
    //   343: bipush #91
    //   345: invokestatic valueOf : (C)Ljava/lang/Character;
    //   348: invokeinterface add : (Ljava/lang/Object;)Z
    //   353: pop
    //   354: getstatic org/yaml/Zb.ZV : Ljava/util/Set;
    //   357: bipush #93
    //   359: invokestatic valueOf : (C)Ljava/lang/Character;
    //   362: invokeinterface add : (Ljava/lang/Object;)Z
    //   367: pop
    //   368: getstatic org/yaml/Zb.ZV : Ljava/util/Set;
    //   371: bipush #123
    //   373: invokestatic valueOf : (C)Ljava/lang/Character;
    //   376: invokeinterface add : (Ljava/lang/Object;)Z
    //   381: pop
    //   382: getstatic org/yaml/Zb.ZV : Ljava/util/Set;
    //   385: bipush #125
    //   387: invokestatic valueOf : (C)Ljava/lang/Character;
    //   390: invokeinterface add : (Ljava/lang/Object;)Z
    //   395: pop
    //   396: getstatic org/yaml/Zb.ZV : Ljava/util/Set;
    //   399: bipush #44
    //   401: invokestatic valueOf : (C)Ljava/lang/Character;
    //   404: invokeinterface add : (Ljava/lang/Object;)Z
    //   409: pop
    //   410: getstatic org/yaml/Zb.ZV : Ljava/util/Set;
    //   413: bipush #42
    //   415: invokestatic valueOf : (C)Ljava/lang/Character;
    //   418: invokeinterface add : (Ljava/lang/Object;)Z
    //   423: pop
    //   424: getstatic org/yaml/Zb.ZV : Ljava/util/Set;
    //   427: bipush #38
    //   429: invokestatic valueOf : (C)Ljava/lang/Character;
    //   432: invokeinterface add : (Ljava/lang/Object;)Z
    //   437: pop
    //   438: new java/util/HashMap
    //   441: dup
    //   442: invokespecial <init> : ()V
    //   445: putstatic org/yaml/Zb.Z_ : Ljava/util/Map;
    //   448: getstatic org/yaml/Zb.Z_ : Ljava/util/Map;
    //   451: iconst_0
    //   452: invokestatic valueOf : (C)Ljava/lang/Character;
    //   455: ldc '0'
    //   457: invokeinterface put : (Ljava/lang/Object;Ljava/lang/Object;)Ljava/lang/Object;
    //   462: pop
    //   463: getstatic org/yaml/Zb.Z_ : Ljava/util/Map;
    //   466: bipush #7
    //   468: invokestatic valueOf : (C)Ljava/lang/Character;
    //   471: ldc 'a'
    //   473: invokeinterface put : (Ljava/lang/Object;Ljava/lang/Object;)Ljava/lang/Object;
    //   478: pop
    //   479: getstatic org/yaml/Zb.Z_ : Ljava/util/Map;
    //   482: bipush #8
    //   484: invokestatic valueOf : (C)Ljava/lang/Character;
    //   487: ldc 'b'
    //   489: invokeinterface put : (Ljava/lang/Object;Ljava/lang/Object;)Ljava/lang/Object;
    //   494: pop
    //   495: getstatic org/yaml/Zb.Z_ : Ljava/util/Map;
    //   498: bipush #9
    //   500: invokestatic valueOf : (C)Ljava/lang/Character;
    //   503: ldc 't'
    //   505: invokeinterface put : (Ljava/lang/Object;Ljava/lang/Object;)Ljava/lang/Object;
    //   510: pop
    //   511: getstatic org/yaml/Zb.Z_ : Ljava/util/Map;
    //   514: bipush #10
    //   516: invokestatic valueOf : (C)Ljava/lang/Character;
    //   519: ldc 'n'
    //   521: invokeinterface put : (Ljava/lang/Object;Ljava/lang/Object;)Ljava/lang/Object;
    //   526: pop
    //   527: getstatic org/yaml/Zb.Z_ : Ljava/util/Map;
    //   530: bipush #11
    //   532: invokestatic valueOf : (C)Ljava/lang/Character;
    //   535: ldc 'v'
    //   537: invokeinterface put : (Ljava/lang/Object;Ljava/lang/Object;)Ljava/lang/Object;
    //   542: pop
    //   543: getstatic org/yaml/Zb.Z_ : Ljava/util/Map;
    //   546: bipush #12
    //   548: invokestatic valueOf : (C)Ljava/lang/Character;
    //   551: ldc 'f'
    //   553: invokeinterface put : (Ljava/lang/Object;Ljava/lang/Object;)Ljava/lang/Object;
    //   558: pop
    //   559: getstatic org/yaml/Zb.Z_ : Ljava/util/Map;
    //   562: bipush #13
    //   564: invokestatic valueOf : (C)Ljava/lang/Character;
    //   567: ldc 'r'
    //   569: invokeinterface put : (Ljava/lang/Object;Ljava/lang/Object;)Ljava/lang/Object;
    //   574: pop
    //   575: getstatic org/yaml/Zb.Z_ : Ljava/util/Map;
    //   578: bipush #27
    //   580: invokestatic valueOf : (C)Ljava/lang/Character;
    //   583: ldc 'e'
    //   585: invokeinterface put : (Ljava/lang/Object;Ljava/lang/Object;)Ljava/lang/Object;
    //   590: pop
    //   591: getstatic org/yaml/Zb.Z_ : Ljava/util/Map;
    //   594: bipush #34
    //   596: invokestatic valueOf : (C)Ljava/lang/Character;
    //   599: ldc '"'
    //   601: invokeinterface put : (Ljava/lang/Object;Ljava/lang/Object;)Ljava/lang/Object;
    //   606: pop
    //   607: getstatic org/yaml/Zb.Z_ : Ljava/util/Map;
    //   610: bipush #92
    //   612: invokestatic valueOf : (C)Ljava/lang/Character;
    //   615: ldc '\'
    //   617: invokeinterface put : (Ljava/lang/Object;Ljava/lang/Object;)Ljava/lang/Object;
    //   622: pop
    //   623: getstatic org/yaml/Zb.Z_ : Ljava/util/Map;
    //   626: sipush #133
    //   629: invokestatic valueOf : (C)Ljava/lang/Character;
    //   632: ldc 'N'
    //   634: invokeinterface put : (Ljava/lang/Object;Ljava/lang/Object;)Ljava/lang/Object;
    //   639: pop
    //   640: getstatic org/yaml/Zb.Z_ : Ljava/util/Map;
    //   643: sipush #160
    //   646: invokestatic valueOf : (C)Ljava/lang/Character;
    //   649: ldc '_'
    //   651: invokeinterface put : (Ljava/lang/Object;Ljava/lang/Object;)Ljava/lang/Object;
    //   656: pop
    //   657: getstatic org/yaml/Zb.Z_ : Ljava/util/Map;
    //   660: sipush #8232
    //   663: invokestatic valueOf : (C)Ljava/lang/Character;
    //   666: ldc 'L'
    //   668: invokeinterface put : (Ljava/lang/Object;Ljava/lang/Object;)Ljava/lang/Object;
    //   673: pop
    //   674: getstatic org/yaml/Zb.Z_ : Ljava/util/Map;
    //   677: sipush #8233
    //   680: invokestatic valueOf : (C)Ljava/lang/Character;
    //   683: ldc 'P'
    //   685: invokeinterface put : (Ljava/lang/Object;Ljava/lang/Object;)Ljava/lang/Object;
    //   690: pop
    //   691: new java/util/LinkedHashMap
    //   694: dup
    //   695: invokespecial <init> : ()V
    //   698: putstatic org/yaml/Zb.Zt : Ljava/util/Map;
    //   701: getstatic org/yaml/Zb.Zt : Ljava/util/Map;
    //   704: ldc '!'
    //   706: ldc '!'
    //   708: invokeinterface put : (Ljava/lang/Object;Ljava/lang/Object;)Ljava/lang/Object;
    //   713: pop
    //   714: getstatic org/yaml/Zb.Zt : Ljava/util/Map;
    //   717: sipush #29182
    //   720: sipush #-7571
    //   723: invokestatic a : (II)Ljava/lang/String;
    //   726: sipush #29159
    //   729: sipush #15142
    //   732: invokestatic a : (II)Ljava/lang/String;
    //   735: invokeinterface put : (Ljava/lang/Object;Ljava/lang/Object;)Ljava/lang/Object;
    //   740: pop
    //   741: sipush #29180
    //   744: sipush #-14538
    //   747: invokestatic a : (II)Ljava/lang/String;
    //   750: invokestatic compile : (Ljava/lang/String;)Ljava/util/regex/Pattern;
    //   753: putstatic org/yaml/Zb.Zi : Ljava/util/regex/Pattern;
    //   756: return
  }
  
  public static void Zu(String paramString) {
    ZH = paramString;
  }
  
  public static String ZH() {
    return ZH;
  }
  
  private static Exception a(Exception paramException) {
    return paramException;
  }
  
  private static String a(int paramInt1, int paramInt2) {
    int i = (paramInt1 ^ 0x71FE) & 0xFFFF;
    if (b[i] == null) {
      char[] arrayOfChar = a[i].toCharArray();
      switch (arrayOfChar[0] & 0xFF) {
        case 0:
        
        case 1:
        
        case 2:
        
        case 3:
        
        case 4:
        
        case 5:
        
        case 6:
        
        case 7:
        
        case 8:
        
        case 9:
        
        case 10:
        
        case 11:
        
        case 12:
        
        case 13:
        
        case 14:
        
        case 15:
        
        case 16:
        
        case 17:
        
        case 18:
        
        case 19:
        
        case 20:
        
        case 21:
        
        case 22:
        
        case 23:
        
        case 24:
        
        case 25:
        
        case 26:
        
        case 27:
        
        case 28:
        
        case 29:
        
        case 30:
        
        case 31:
        
        case 32:
        
        case 33:
        
        case 34:
        
        case 35:
        
        case 36:
        
        case 37:
        
        case 38:
        
        case 39:
        
        case 40:
        
        case 41:
        
        case 42:
        
        case 43:
        
        case 44:
        
        case 45:
        
        case 46:
        
        case 47:
        
        case 48:
        
        case 49:
        
        case 50:
        
        case 51:
        
        case 52:
        
        case 53:
        
        case 54:
        
        case 55:
        
        case 56:
        
        case 57:
        
        case 58:
        
        case 59:
        
        case 60:
        
        case 61:
        
        case 62:
        
        case 63:
        
        case 64:
        
        case 65:
        
        case 66:
        
        case 67:
        
        case 68:
        
        case 69:
        
        case 70:
        
        case 71:
        
        case 72:
        
        case 73:
        
        case 74:
        
        case 75:
        
        case 76:
        
        case 77:
        
        case 78:
        
        case 79:
        
        case 80:
        
        case 81:
        
        case 82:
        
        case 83:
        
        case 84:
        
        case 85:
        
        case 86:
        
        case 87:
        
        case 88:
        
        case 89:
        
        case 90:
        
        case 91:
        
        case 92:
        
        case 93:
        
        case 94:
        
        case 95:
        
        case 96:
        
        case 97:
        
        case 98:
        
        case 99:
        
        case 100:
        
        case 101:
        
        case 102:
        
        case 103:
        
        case 104:
        
        case 105:
        
        case 106:
        
        case 107:
        
        case 108:
        
        case 109:
        
        case 110:
        
        case 111:
        
        case 112:
        
        case 113:
        
        case 114:
        
        case 115:
        
        case 116:
        
        case 117:
        
        case 118:
        
        case 119:
        
        case 120:
        
        case 121:
        
        case 122:
        
        case 123:
        
        case 124:
        
        case 125:
        
        case 126:
        
        case 127:
        
        case 128:
        
        case 129:
        
        case 130:
        
        case 131:
        
        case 132:
        
        case 133:
        
        case 134:
        
        case 135:
        
        case 136:
        
        case 137:
        
        case 138:
        
        case 139:
        
        case 140:
        
        case 141:
        
        case 142:
        
        case 143:
        
        case 144:
        
        case 145:
        
        case 146:
        
        case 147:
        
        case 148:
        
        case 149:
        
        case 150:
        
        case 151:
        
        case 152:
        
        case 153:
        
        case 154:
        
        case 155:
        
        case 156:
        
        case 157:
        
        case 158:
        
        case 159:
        
        case 160:
        
        case 161:
        
        case 162:
        
        case 163:
        
        case 164:
        
        case 165:
        
        case 166:
        
        case 167:
        
        case 168:
        
        case 169:
        
        case 170:
        
        case 171:
        
        case 172:
        
        case 173:
        
        case 174:
        
        case 175:
        
        case 176:
        
        case 177:
        
        case 178:
        
        case 179:
        
        case 180:
        
        case 181:
        
        case 182:
        
        case 183:
        
        case 184:
        
        case 185:
        
        case 186:
        
        case 187:
        
        case 188:
        
        case 189:
        
        case 190:
        
        case 191:
        
        case 192:
        
        case 193:
        
        case 194:
        
        case 195:
        
        case 196:
        
        case 197:
        
        case 198:
        
        case 199:
        
        case 200:
        
        case 201:
        
        case 202:
        
        case 203:
        
        case 204:
        
        case 205:
        
        case 206:
        
        case 207:
        
        case 208:
        
        case 209:
        
        case 210:
        
        case 211:
        
        case 212:
        
        case 213:
        
        case 214:
        
        case 215:
        
        case 216:
        
        case 217:
        
        case 218:
        
        case 219:
        
        case 220:
        
        case 221:
        
        case 222:
        
        case 223:
        
        case 224:
        
        case 225:
        
        case 226:
        
        case 227:
        
        case 228:
        
        case 229:
        
        case 230:
        
        case 231:
        
        case 232:
        
        case 233:
        
        case 234:
        
        case 235:
        
        case 236:
        
        case 237:
        
        case 238:
        
        case 239:
        
        case 240:
        
        case 241:
        
        case 242:
        
        case 243:
        
        case 244:
        
        case 245:
        
        case 246:
        
        case 247:
        
        case 248:
        
        case 249:
        
        case 250:
        
        case 251:
        
        case 252:
        
        case 253:
        
        case 254:
        
        default:
          break;
      } 
      char c = '';
      int j = (paramInt2 & 0xFF) - c;
      if (j < 0)
        j += 256; 
      int k = ((paramInt2 & 0xFFFF) >>> 8) - c;
      if (k < 0)
        k += 256; 
      for (byte b = 0; b < arrayOfChar.length; b++) {
        int m = b % 2;
        if (m == 0) {
          arrayOfChar[b] = (char)(arrayOfChar[b] ^ j);
          j = ((j >>> 3 | j << 5) ^ arrayOfChar[b]) & 0xFF;
        } else {
          arrayOfChar[b] = (char)(arrayOfChar[b] ^ k);
          k = ((k >>> 3 | k << 5) ^ arrayOfChar[b]) & 0xFF;
        } 
      } 
      b[i] = (new String(arrayOfChar)).intern();
    } 
    return b[i];
  }
}


/* Location:              C:\Program Files\BurpSuitePro\burpsuite_pro.jar!\org\yaml\Zb.class
 * Java compiler version: 7 (51.0)
 * JD-Core Version:       1.1.3
 */