package org.yaml;

import java.io.IOException;

class Zjn implements Zd {
  final Zb ZU;
  
  private Zjn(Zb paramZb) {}
  
  public void Zt() throws IOException {
    // Byte code:
    //   0: invokestatic ZH : ()Ljava/lang/String;
    //   3: astore_1
    //   4: aload_0
    //   5: getfield ZU : Lorg/yaml/Zb;
    //   8: invokestatic ZJ : (Lorg/yaml/Zb;)Lorg/yaml/Zlv;
    //   11: instanceof org/yaml/Zlu
    //   14: ifeq -> 109
    //   17: aload_0
    //   18: getfield ZU : Lorg/yaml/Zb;
    //   21: aload_0
    //   22: getfield ZU : Lorg/yaml/Zb;
    //   25: invokestatic Zf : (Lorg/yaml/Zb;)Lorg/yaml/Zq;
    //   28: invokevirtual ZE : ()Ljava/lang/Object;
    //   31: checkcast java/lang/Integer
    //   34: invokestatic ZE : (Lorg/yaml/Zb;Ljava/lang/Integer;)Ljava/lang/Integer;
    //   37: pop
    //   38: aload_0
    //   39: getfield ZU : Lorg/yaml/Zb;
    //   42: invokestatic Zb : (Lorg/yaml/Zb;)I
    //   45: pop
    //   46: aload_0
    //   47: getfield ZU : Lorg/yaml/Zb;
    //   50: ldc ']'
    //   52: iconst_0
    //   53: iconst_0
    //   54: iconst_0
    //   55: invokevirtual Zv : (Ljava/lang/String;ZZZ)V
    //   58: aload_0
    //   59: getfield ZU : Lorg/yaml/Zb;
    //   62: invokestatic ZS : (Lorg/yaml/Zb;)Lorg/yaml/Zj8;
    //   65: invokevirtual Zh : ()Lorg/yaml/Zj8;
    //   68: pop
    //   69: aload_0
    //   70: getfield ZU : Lorg/yaml/Zb;
    //   73: invokestatic Zl : (Lorg/yaml/Zb;)Z
    //   76: pop
    //   77: aload_0
    //   78: getfield ZU : Lorg/yaml/Zb;
    //   81: aload_0
    //   82: getfield ZU : Lorg/yaml/Zb;
    //   85: invokestatic Za : (Lorg/yaml/Zb;)Lorg/yaml/Zq;
    //   88: invokevirtual ZE : ()Ljava/lang/Object;
    //   91: checkcast org/yaml/Zd
    //   94: invokestatic ZB : (Lorg/yaml/Zb;Lorg/yaml/Zd;)Lorg/yaml/Zd;
    //   97: pop
    //   98: aload_1
    //   99: ifnonnull -> 325
    //   102: goto -> 109
    //   105: invokestatic a : (Ljava/io/IOException;)Ljava/io/IOException;
    //   108: athrow
    //   109: aload_0
    //   110: getfield ZU : Lorg/yaml/Zb;
    //   113: invokestatic ZJ : (Lorg/yaml/Zb;)Lorg/yaml/Zlv;
    //   116: instanceof org/yaml/Zld
    //   119: ifeq -> 165
    //   122: goto -> 129
    //   125: invokestatic a : (Ljava/io/IOException;)Ljava/io/IOException;
    //   128: athrow
    //   129: aload_0
    //   130: getfield ZU : Lorg/yaml/Zb;
    //   133: invokestatic ZM : (Lorg/yaml/Zb;)Lorg/yaml/Zj8;
    //   136: aload_0
    //   137: getfield ZU : Lorg/yaml/Zb;
    //   140: invokestatic ZJ : (Lorg/yaml/Zb;)Lorg/yaml/Zlv;
    //   143: invokevirtual ZF : (Lorg/yaml/Zlv;)Lorg/yaml/Zlv;
    //   146: pop
    //   147: aload_0
    //   148: getfield ZU : Lorg/yaml/Zb;
    //   151: invokestatic ZB : (Lorg/yaml/Zb;)V
    //   154: aload_1
    //   155: ifnonnull -> 325
    //   158: goto -> 165
    //   161: invokestatic a : (Ljava/io/IOException;)Ljava/io/IOException;
    //   164: athrow
    //   165: aload_0
    //   166: getfield ZU : Lorg/yaml/Zb;
    //   169: invokestatic ZP : (Lorg/yaml/Zb;)Ljava/lang/Boolean;
    //   172: invokevirtual booleanValue : ()Z
    //   175: ifne -> 246
    //   178: goto -> 185
    //   181: invokestatic a : (Ljava/io/IOException;)Ljava/io/IOException;
    //   184: athrow
    //   185: aload_0
    //   186: getfield ZU : Lorg/yaml/Zb;
    //   189: invokestatic Zt : (Lorg/yaml/Zb;)I
    //   192: aload_0
    //   193: getfield ZU : Lorg/yaml/Zb;
    //   196: invokestatic Z_ : (Lorg/yaml/Zb;)I
    //   199: if_icmple -> 226
    //   202: goto -> 209
    //   205: invokestatic a : (Ljava/io/IOException;)Ljava/io/IOException;
    //   208: athrow
    //   209: aload_0
    //   210: getfield ZU : Lorg/yaml/Zb;
    //   213: invokestatic Zc : (Lorg/yaml/Zb;)Z
    //   216: ifne -> 246
    //   219: goto -> 226
    //   222: invokestatic a : (Ljava/io/IOException;)Ljava/io/IOException;
    //   225: athrow
    //   226: aload_0
    //   227: getfield ZU : Lorg/yaml/Zb;
    //   230: invokestatic ZN : (Lorg/yaml/Zb;)Ljava/lang/Boolean;
    //   233: invokevirtual booleanValue : ()Z
    //   236: ifeq -> 260
    //   239: goto -> 246
    //   242: invokestatic a : (Ljava/io/IOException;)Ljava/io/IOException;
    //   245: athrow
    //   246: aload_0
    //   247: getfield ZU : Lorg/yaml/Zb;
    //   250: invokevirtual ZJ : ()V
    //   253: goto -> 260
    //   256: invokestatic a : (Ljava/io/IOException;)Ljava/io/IOException;
    //   259: athrow
    //   260: aload_0
    //   261: getfield ZU : Lorg/yaml/Zb;
    //   264: invokestatic Za : (Lorg/yaml/Zb;)Lorg/yaml/Zq;
    //   267: new org/yaml/Za
    //   270: dup
    //   271: aload_0
    //   272: getfield ZU : Lorg/yaml/Zb;
    //   275: aconst_null
    //   276: invokespecial <init> : (Lorg/yaml/Zb;Lorg/yaml/Zjq;)V
    //   279: invokevirtual Zq : (Ljava/lang/Object;)V
    //   282: aload_0
    //   283: getfield ZU : Lorg/yaml/Zb;
    //   286: iconst_0
    //   287: iconst_0
    //   288: iconst_0
    //   289: invokestatic Zu : (Lorg/yaml/Zb;ZZZ)V
    //   292: aload_0
    //   293: getfield ZU : Lorg/yaml/Zb;
    //   296: aload_0
    //   297: getfield ZU : Lorg/yaml/Zb;
    //   300: invokestatic ZS : (Lorg/yaml/Zb;)Lorg/yaml/Zj8;
    //   303: aload_0
    //   304: getfield ZU : Lorg/yaml/Zb;
    //   307: invokestatic ZJ : (Lorg/yaml/Zb;)Lorg/yaml/Zlv;
    //   310: invokevirtual ZF : (Lorg/yaml/Zlv;)Lorg/yaml/Zlv;
    //   313: invokestatic Za : (Lorg/yaml/Zb;Lorg/yaml/Zlv;)Lorg/yaml/Zlv;
    //   316: pop
    //   317: aload_0
    //   318: getfield ZU : Lorg/yaml/Zb;
    //   321: invokestatic Zl : (Lorg/yaml/Zb;)Z
    //   324: pop
    //   325: return
    // Exception table:
    //   from	to	target	type
    //   4	102	105	java/io/IOException
    //   17	122	125	java/io/IOException
    //   109	158	161	java/io/IOException
    //   129	178	181	java/io/IOException
    //   165	202	205	java/io/IOException
    //   185	219	222	java/io/IOException
    //   209	239	242	java/io/IOException
    //   226	253	256	java/io/IOException
  }
  
  Zjn(Zb paramZb, Zjq paramZjq) {
    this(paramZb);
  }
  
  private static IOException a(IOException paramIOException) {
    return paramIOException;
  }
}


/* Location:              C:\Program Files\BurpSuitePro\burpsuite_pro.jar!\org\yaml\Zjn.class
 * Java compiler version: 7 (51.0)
 * JD-Core Version:       1.1.3
 */