package org.yaml;

public enum Zjp {
  BINARY, ESCAPE;
  
  private static final Zjp[] ZJ;
  
  static {
    // Byte code:
    //   0: iconst_2
    //   1: anewarray java/lang/String
    //   4: astore_0
    //   5: iconst_0
    //   6: istore #4
    //   8: ldc '\|QvFqQ}j'
    //   10: dup
    //   11: astore_3
    //   12: invokevirtual length : ()I
    //   15: istore #5
    //   17: bipush #6
    //   19: istore_2
    //   20: iconst_m1
    //   21: istore_1
    //   22: iconst_1
    //   23: iinc #1, 1
    //   26: aload_3
    //   27: iload_1
    //   28: dup
    //   29: iload_2
    //   30: iadd
    //   31: invokevirtual substring : (II)Ljava/lang/String;
    //   34: iconst_m1
    //   35: goto -> 69
    //   38: aload_0
    //   39: swap
    //   40: iload #4
    //   42: iinc #4, 1
    //   45: swap
    //   46: aastore
    //   47: iload_1
    //   48: iload_2
    //   49: iadd
    //   50: dup
    //   51: istore_1
    //   52: iload #5
    //   54: if_icmpge -> 66
    //   57: aload_3
    //   58: iload_1
    //   59: invokevirtual charAt : (I)C
    //   62: istore_2
    //   63: goto -> 22
    //   66: goto -> 215
    //   69: dup_x2
    //   70: pop
    //   71: invokevirtual toCharArray : ()[C
    //   74: dup_x1
    //   75: arraylength
    //   76: dup_x2
    //   77: pop
    //   78: iconst_0
    //   79: istore #6
    //   81: dup2_x1
    //   82: pop2
    //   83: dup_x2
    //   84: iconst_1
    //   85: if_icmpgt -> 188
    //   88: dup2
    //   89: swap
    //   90: iload #6
    //   92: dup2_x1
    //   93: caload
    //   94: swap
    //   95: iload #6
    //   97: bipush #7
    //   99: irem
    //   100: tableswitch default -> 170, 0 -> 140, 1 -> 145, 2 -> 150, 3 -> 155, 4 -> 160, 5 -> 165
    //   140: bipush #71
    //   142: goto -> 172
    //   145: bipush #20
    //   147: goto -> 172
    //   150: bipush #51
    //   152: goto -> 172
    //   155: bipush #17
    //   157: goto -> 172
    //   160: bipush #44
    //   162: goto -> 172
    //   165: bipush #46
    //   167: goto -> 172
    //   170: bipush #31
    //   172: ixor
    //   173: ixor
    //   174: i2c
    //   175: castore
    //   176: iinc #6, 1
    //   179: dup
    //   180: ifne -> 188
    //   183: dup2
    //   184: dup_x1
    //   185: goto -> 92
    //   188: dup2_x1
    //   189: pop2
    //   190: dup_x2
    //   191: iload #6
    //   193: if_icmpgt -> 88
    //   196: pop
    //   197: new java/lang/String
    //   200: dup_x1
    //   201: swap
    //   202: invokespecial <init> : ([C)V
    //   205: invokevirtual intern : ()Ljava/lang/String;
    //   208: swap
    //   209: pop
    //   210: swap
    //   211: pop
    //   212: goto -> 38
    //   215: new org/yaml/Zjp
    //   218: dup
    //   219: aload_0
    //   220: iconst_0
    //   221: aaload
    //   222: iconst_0
    //   223: invokespecial <init> : (Ljava/lang/String;I)V
    //   226: putstatic org/yaml/Zjp.BINARY : Lorg/yaml/Zjp;
    //   229: new org/yaml/Zjp
    //   232: dup
    //   233: aload_0
    //   234: iconst_1
    //   235: aaload
    //   236: iconst_1
    //   237: invokespecial <init> : (Ljava/lang/String;I)V
    //   240: putstatic org/yaml/Zjp.ESCAPE : Lorg/yaml/Zjp;
    //   243: iconst_2
    //   244: anewarray org/yaml/Zjp
    //   247: dup
    //   248: iconst_0
    //   249: getstatic org/yaml/Zjp.BINARY : Lorg/yaml/Zjp;
    //   252: aastore
    //   253: dup
    //   254: iconst_1
    //   255: getstatic org/yaml/Zjp.ESCAPE : Lorg/yaml/Zjp;
    //   258: aastore
    //   259: putstatic org/yaml/Zjp.ZJ : [Lorg/yaml/Zjp;
    //   262: return
  }
}


/* Location:              C:\Program Files\BurpSuitePro\burpsuite_pro.jar!\org\yaml\Zjp.class
 * Java compiler version: 7 (51.0)
 * JD-Core Version:       1.1.3
 */