package org.yaml;

import java.io.IOException;

class Zjr implements Zd {
  final Zb ZM;
  
  private Zjr(Zb paramZb) {}
  
  public void Zt() throws IOException {
    // Byte code:
    //   0: aload_0
    //   1: getfield ZM : Lorg/yaml/Zb;
    //   4: aload_0
    //   5: getfield ZM : Lorg/yaml/Zb;
    //   8: invokestatic ZM : (Lorg/yaml/Zb;)Lorg/yaml/Zj8;
    //   11: aload_0
    //   12: getfield ZM : Lorg/yaml/Zb;
    //   15: invokestatic ZJ : (Lorg/yaml/Zb;)Lorg/yaml/Zlv;
    //   18: invokevirtual ZY : (Lorg/yaml/Zlv;)Lorg/yaml/Zlv;
    //   21: invokestatic Za : (Lorg/yaml/Zb;Lorg/yaml/Zlv;)Lorg/yaml/Zlv;
    //   24: pop
    //   25: invokestatic ZH : ()Ljava/lang/String;
    //   28: aload_0
    //   29: getfield ZM : Lorg/yaml/Zb;
    //   32: invokestatic ZB : (Lorg/yaml/Zb;)V
    //   35: astore_1
    //   36: aload_0
    //   37: getfield ZM : Lorg/yaml/Zb;
    //   40: invokestatic ZJ : (Lorg/yaml/Zb;)Lorg/yaml/Zlv;
    //   43: instanceof org/yaml/Zl5
    //   46: ifeq -> 141
    //   49: aload_0
    //   50: getfield ZM : Lorg/yaml/Zb;
    //   53: aload_0
    //   54: getfield ZM : Lorg/yaml/Zb;
    //   57: invokestatic Zf : (Lorg/yaml/Zb;)Lorg/yaml/Zq;
    //   60: invokevirtual ZE : ()Ljava/lang/Object;
    //   63: checkcast java/lang/Integer
    //   66: invokestatic ZE : (Lorg/yaml/Zb;Ljava/lang/Integer;)Ljava/lang/Integer;
    //   69: pop
    //   70: aload_0
    //   71: getfield ZM : Lorg/yaml/Zb;
    //   74: invokestatic Zb : (Lorg/yaml/Zb;)I
    //   77: pop
    //   78: aload_0
    //   79: getfield ZM : Lorg/yaml/Zb;
    //   82: ldc '}'
    //   84: iconst_0
    //   85: iconst_0
    //   86: iconst_0
    //   87: invokevirtual Zv : (Ljava/lang/String;ZZZ)V
    //   90: aload_0
    //   91: getfield ZM : Lorg/yaml/Zb;
    //   94: invokestatic ZS : (Lorg/yaml/Zb;)Lorg/yaml/Zj8;
    //   97: invokevirtual Zh : ()Lorg/yaml/Zj8;
    //   100: pop
    //   101: aload_0
    //   102: getfield ZM : Lorg/yaml/Zb;
    //   105: invokestatic Zl : (Lorg/yaml/Zb;)Z
    //   108: pop
    //   109: aload_0
    //   110: getfield ZM : Lorg/yaml/Zb;
    //   113: aload_0
    //   114: getfield ZM : Lorg/yaml/Zb;
    //   117: invokestatic Za : (Lorg/yaml/Zb;)Lorg/yaml/Zq;
    //   120: invokevirtual ZE : ()Ljava/lang/Object;
    //   123: checkcast org/yaml/Zd
    //   126: invokestatic ZB : (Lorg/yaml/Zb;Lorg/yaml/Zd;)Lorg/yaml/Zd;
    //   129: pop
    //   130: aload_1
    //   131: ifnonnull -> 360
    //   134: goto -> 141
    //   137: invokestatic a : (Ljava/io/IOException;)Ljava/io/IOException;
    //   140: athrow
    //   141: aload_0
    //   142: getfield ZM : Lorg/yaml/Zb;
    //   145: invokestatic ZP : (Lorg/yaml/Zb;)Ljava/lang/Boolean;
    //   148: invokevirtual booleanValue : ()Z
    //   151: ifne -> 222
    //   154: goto -> 161
    //   157: invokestatic a : (Ljava/io/IOException;)Ljava/io/IOException;
    //   160: athrow
    //   161: aload_0
    //   162: getfield ZM : Lorg/yaml/Zb;
    //   165: invokestatic Zt : (Lorg/yaml/Zb;)I
    //   168: aload_0
    //   169: getfield ZM : Lorg/yaml/Zb;
    //   172: invokestatic Z_ : (Lorg/yaml/Zb;)I
    //   175: if_icmple -> 202
    //   178: goto -> 185
    //   181: invokestatic a : (Ljava/io/IOException;)Ljava/io/IOException;
    //   184: athrow
    //   185: aload_0
    //   186: getfield ZM : Lorg/yaml/Zb;
    //   189: invokestatic Zc : (Lorg/yaml/Zb;)Z
    //   192: ifne -> 222
    //   195: goto -> 202
    //   198: invokestatic a : (Ljava/io/IOException;)Ljava/io/IOException;
    //   201: athrow
    //   202: aload_0
    //   203: getfield ZM : Lorg/yaml/Zb;
    //   206: invokestatic ZN : (Lorg/yaml/Zb;)Ljava/lang/Boolean;
    //   209: invokevirtual booleanValue : ()Z
    //   212: ifeq -> 236
    //   215: goto -> 222
    //   218: invokestatic a : (Ljava/io/IOException;)Ljava/io/IOException;
    //   221: athrow
    //   222: aload_0
    //   223: getfield ZM : Lorg/yaml/Zb;
    //   226: invokevirtual ZJ : ()V
    //   229: goto -> 236
    //   232: invokestatic a : (Ljava/io/IOException;)Ljava/io/IOException;
    //   235: athrow
    //   236: aload_0
    //   237: getfield ZM : Lorg/yaml/Zb;
    //   240: invokestatic ZP : (Lorg/yaml/Zb;)Ljava/lang/Boolean;
    //   243: invokevirtual booleanValue : ()Z
    //   246: ifne -> 309
    //   249: aload_0
    //   250: getfield ZM : Lorg/yaml/Zb;
    //   253: invokestatic Zo : (Lorg/yaml/Zb;)Z
    //   256: ifeq -> 309
    //   259: goto -> 266
    //   262: invokestatic a : (Ljava/io/IOException;)Ljava/io/IOException;
    //   265: athrow
    //   266: aload_0
    //   267: getfield ZM : Lorg/yaml/Zb;
    //   270: invokestatic Za : (Lorg/yaml/Zb;)Lorg/yaml/Zq;
    //   273: new org/yaml/Ze
    //   276: dup
    //   277: aload_0
    //   278: getfield ZM : Lorg/yaml/Zb;
    //   281: aconst_null
    //   282: invokespecial <init> : (Lorg/yaml/Zb;Lorg/yaml/Zjq;)V
    //   285: invokevirtual Zq : (Ljava/lang/Object;)V
    //   288: aload_0
    //   289: getfield ZM : Lorg/yaml/Zb;
    //   292: iconst_0
    //   293: iconst_1
    //   294: iconst_1
    //   295: invokestatic Zu : (Lorg/yaml/Zb;ZZZ)V
    //   298: aload_1
    //   299: ifnonnull -> 360
    //   302: goto -> 309
    //   305: invokestatic a : (Ljava/io/IOException;)Ljava/io/IOException;
    //   308: athrow
    //   309: aload_0
    //   310: getfield ZM : Lorg/yaml/Zb;
    //   313: ldc '?'
    //   315: iconst_1
    //   316: iconst_0
    //   317: iconst_0
    //   318: invokevirtual Zv : (Ljava/lang/String;ZZZ)V
    //   321: aload_0
    //   322: getfield ZM : Lorg/yaml/Zb;
    //   325: invokestatic Za : (Lorg/yaml/Zb;)Lorg/yaml/Zq;
    //   328: new org/yaml/Ztd
    //   331: dup
    //   332: aload_0
    //   333: getfield ZM : Lorg/yaml/Zb;
    //   336: aconst_null
    //   337: invokespecial <init> : (Lorg/yaml/Zb;Lorg/yaml/Zjq;)V
    //   340: invokevirtual Zq : (Ljava/lang/Object;)V
    //   343: aload_0
    //   344: getfield ZM : Lorg/yaml/Zb;
    //   347: iconst_0
    //   348: iconst_1
    //   349: iconst_0
    //   350: invokestatic Zu : (Lorg/yaml/Zb;ZZZ)V
    //   353: goto -> 360
    //   356: invokestatic a : (Ljava/io/IOException;)Ljava/io/IOException;
    //   359: athrow
    //   360: return
    // Exception table:
    //   from	to	target	type
    //   36	134	137	java/io/IOException
    //   49	154	157	java/io/IOException
    //   141	178	181	java/io/IOException
    //   161	195	198	java/io/IOException
    //   185	215	218	java/io/IOException
    //   202	229	232	java/io/IOException
    //   236	259	262	java/io/IOException
    //   249	302	305	java/io/IOException
    //   266	353	356	java/io/IOException
  }
  
  Zjr(Zb paramZb, Zjq paramZjq) {
    this(paramZb);
  }
  
  private static IOException a(IOException paramIOException) {
    return paramIOException;
  }
}


/* Location:              C:\Program Files\BurpSuitePro\burpsuite_pro.jar!\org\yaml\Zjr.class
 * Java compiler version: 7 (51.0)
 * JD-Core Version:       1.1.3
 */