package org.yaml;

import java.io.IOException;

class Zll implements Zd {
  final Zb Zz;
  
  private Zll(Zb paramZb) {}
  
  public void Zt() throws IOException {
    // Byte code:
    //   0: invokestatic ZH : ()Ljava/lang/String;
    //   3: astore_1
    //   4: aload_0
    //   5: getfield Zz : Lorg/yaml/Zb;
    //   8: invokestatic ZJ : (Lorg/yaml/Zb;)Lorg/yaml/Zlv;
    //   11: instanceof org/yaml/Zl5
    //   14: ifeq -> 175
    //   17: aload_0
    //   18: getfield Zz : Lorg/yaml/Zb;
    //   21: aload_0
    //   22: getfield Zz : Lorg/yaml/Zb;
    //   25: invokestatic Zf : (Lorg/yaml/Zb;)Lorg/yaml/Zq;
    //   28: invokevirtual ZE : ()Ljava/lang/Object;
    //   31: checkcast java/lang/Integer
    //   34: invokestatic ZE : (Lorg/yaml/Zb;Ljava/lang/Integer;)Ljava/lang/Integer;
    //   37: pop
    //   38: aload_0
    //   39: getfield Zz : Lorg/yaml/Zb;
    //   42: invokestatic Zb : (Lorg/yaml/Zb;)I
    //   45: pop
    //   46: aload_0
    //   47: getfield Zz : Lorg/yaml/Zb;
    //   50: invokestatic ZP : (Lorg/yaml/Zb;)Ljava/lang/Boolean;
    //   53: invokevirtual booleanValue : ()Z
    //   56: ifeq -> 92
    //   59: goto -> 66
    //   62: invokestatic a : (Ljava/io/IOException;)Ljava/io/IOException;
    //   65: athrow
    //   66: aload_0
    //   67: getfield Zz : Lorg/yaml/Zb;
    //   70: ldc ','
    //   72: iconst_0
    //   73: iconst_0
    //   74: iconst_0
    //   75: invokevirtual Zv : (Ljava/lang/String;ZZZ)V
    //   78: aload_0
    //   79: getfield Zz : Lorg/yaml/Zb;
    //   82: invokevirtual ZJ : ()V
    //   85: goto -> 92
    //   88: invokestatic a : (Ljava/io/IOException;)Ljava/io/IOException;
    //   91: athrow
    //   92: aload_0
    //   93: getfield Zz : Lorg/yaml/Zb;
    //   96: invokestatic ZN : (Lorg/yaml/Zb;)Ljava/lang/Boolean;
    //   99: invokevirtual booleanValue : ()Z
    //   102: ifeq -> 119
    //   105: aload_0
    //   106: getfield Zz : Lorg/yaml/Zb;
    //   109: invokevirtual ZJ : ()V
    //   112: goto -> 119
    //   115: invokestatic a : (Ljava/io/IOException;)Ljava/io/IOException;
    //   118: athrow
    //   119: aload_0
    //   120: getfield Zz : Lorg/yaml/Zb;
    //   123: ldc '}'
    //   125: iconst_0
    //   126: iconst_0
    //   127: iconst_0
    //   128: invokevirtual Zv : (Ljava/lang/String;ZZZ)V
    //   131: aload_0
    //   132: getfield Zz : Lorg/yaml/Zb;
    //   135: invokestatic ZS : (Lorg/yaml/Zb;)Lorg/yaml/Zj8;
    //   138: invokevirtual Zh : ()Lorg/yaml/Zj8;
    //   141: pop
    //   142: aload_0
    //   143: getfield Zz : Lorg/yaml/Zb;
    //   146: invokestatic Zl : (Lorg/yaml/Zb;)Z
    //   149: pop
    //   150: aload_0
    //   151: getfield Zz : Lorg/yaml/Zb;
    //   154: aload_0
    //   155: getfield Zz : Lorg/yaml/Zb;
    //   158: invokestatic Za : (Lorg/yaml/Zb;)Lorg/yaml/Zq;
    //   161: invokevirtual ZE : ()Ljava/lang/Object;
    //   164: checkcast org/yaml/Zd
    //   167: invokestatic ZB : (Lorg/yaml/Zb;Lorg/yaml/Zd;)Lorg/yaml/Zd;
    //   170: pop
    //   171: aload_1
    //   172: ifnonnull -> 438
    //   175: aload_0
    //   176: getfield Zz : Lorg/yaml/Zb;
    //   179: ldc ','
    //   181: iconst_0
    //   182: iconst_0
    //   183: iconst_0
    //   184: invokevirtual Zv : (Ljava/lang/String;ZZZ)V
    //   187: aload_0
    //   188: getfield Zz : Lorg/yaml/Zb;
    //   191: aload_0
    //   192: getfield Zz : Lorg/yaml/Zb;
    //   195: invokestatic ZM : (Lorg/yaml/Zb;)Lorg/yaml/Zj8;
    //   198: aload_0
    //   199: getfield Zz : Lorg/yaml/Zb;
    //   202: invokestatic ZJ : (Lorg/yaml/Zb;)Lorg/yaml/Zlv;
    //   205: invokevirtual ZY : (Lorg/yaml/Zlv;)Lorg/yaml/Zlv;
    //   208: invokestatic Za : (Lorg/yaml/Zb;Lorg/yaml/Zlv;)Lorg/yaml/Zlv;
    //   211: pop
    //   212: aload_0
    //   213: getfield Zz : Lorg/yaml/Zb;
    //   216: invokestatic ZB : (Lorg/yaml/Zb;)V
    //   219: aload_0
    //   220: getfield Zz : Lorg/yaml/Zb;
    //   223: invokestatic ZP : (Lorg/yaml/Zb;)Ljava/lang/Boolean;
    //   226: invokevirtual booleanValue : ()Z
    //   229: ifne -> 300
    //   232: goto -> 239
    //   235: invokestatic a : (Ljava/io/IOException;)Ljava/io/IOException;
    //   238: athrow
    //   239: aload_0
    //   240: getfield Zz : Lorg/yaml/Zb;
    //   243: invokestatic Zt : (Lorg/yaml/Zb;)I
    //   246: aload_0
    //   247: getfield Zz : Lorg/yaml/Zb;
    //   250: invokestatic Z_ : (Lorg/yaml/Zb;)I
    //   253: if_icmple -> 280
    //   256: goto -> 263
    //   259: invokestatic a : (Ljava/io/IOException;)Ljava/io/IOException;
    //   262: athrow
    //   263: aload_0
    //   264: getfield Zz : Lorg/yaml/Zb;
    //   267: invokestatic Zc : (Lorg/yaml/Zb;)Z
    //   270: ifne -> 300
    //   273: goto -> 280
    //   276: invokestatic a : (Ljava/io/IOException;)Ljava/io/IOException;
    //   279: athrow
    //   280: aload_0
    //   281: getfield Zz : Lorg/yaml/Zb;
    //   284: invokestatic ZN : (Lorg/yaml/Zb;)Ljava/lang/Boolean;
    //   287: invokevirtual booleanValue : ()Z
    //   290: ifeq -> 314
    //   293: goto -> 300
    //   296: invokestatic a : (Ljava/io/IOException;)Ljava/io/IOException;
    //   299: athrow
    //   300: aload_0
    //   301: getfield Zz : Lorg/yaml/Zb;
    //   304: invokevirtual ZJ : ()V
    //   307: goto -> 314
    //   310: invokestatic a : (Ljava/io/IOException;)Ljava/io/IOException;
    //   313: athrow
    //   314: aload_0
    //   315: getfield Zz : Lorg/yaml/Zb;
    //   318: invokestatic ZP : (Lorg/yaml/Zb;)Ljava/lang/Boolean;
    //   321: invokevirtual booleanValue : ()Z
    //   324: ifne -> 387
    //   327: aload_0
    //   328: getfield Zz : Lorg/yaml/Zb;
    //   331: invokestatic Zo : (Lorg/yaml/Zb;)Z
    //   334: ifeq -> 387
    //   337: goto -> 344
    //   340: invokestatic a : (Ljava/io/IOException;)Ljava/io/IOException;
    //   343: athrow
    //   344: aload_0
    //   345: getfield Zz : Lorg/yaml/Zb;
    //   348: invokestatic Za : (Lorg/yaml/Zb;)Lorg/yaml/Zq;
    //   351: new org/yaml/Ze
    //   354: dup
    //   355: aload_0
    //   356: getfield Zz : Lorg/yaml/Zb;
    //   359: aconst_null
    //   360: invokespecial <init> : (Lorg/yaml/Zb;Lorg/yaml/Zjq;)V
    //   363: invokevirtual Zq : (Ljava/lang/Object;)V
    //   366: aload_0
    //   367: getfield Zz : Lorg/yaml/Zb;
    //   370: iconst_0
    //   371: iconst_1
    //   372: iconst_1
    //   373: invokestatic Zu : (Lorg/yaml/Zb;ZZZ)V
    //   376: aload_1
    //   377: ifnonnull -> 438
    //   380: goto -> 387
    //   383: invokestatic a : (Ljava/io/IOException;)Ljava/io/IOException;
    //   386: athrow
    //   387: aload_0
    //   388: getfield Zz : Lorg/yaml/Zb;
    //   391: ldc '?'
    //   393: iconst_1
    //   394: iconst_0
    //   395: iconst_0
    //   396: invokevirtual Zv : (Ljava/lang/String;ZZZ)V
    //   399: aload_0
    //   400: getfield Zz : Lorg/yaml/Zb;
    //   403: invokestatic Za : (Lorg/yaml/Zb;)Lorg/yaml/Zq;
    //   406: new org/yaml/Ztd
    //   409: dup
    //   410: aload_0
    //   411: getfield Zz : Lorg/yaml/Zb;
    //   414: aconst_null
    //   415: invokespecial <init> : (Lorg/yaml/Zb;Lorg/yaml/Zjq;)V
    //   418: invokevirtual Zq : (Ljava/lang/Object;)V
    //   421: aload_0
    //   422: getfield Zz : Lorg/yaml/Zb;
    //   425: iconst_0
    //   426: iconst_1
    //   427: iconst_0
    //   428: invokestatic Zu : (Lorg/yaml/Zb;ZZZ)V
    //   431: goto -> 438
    //   434: invokestatic a : (Ljava/io/IOException;)Ljava/io/IOException;
    //   437: athrow
    //   438: return
    // Exception table:
    //   from	to	target	type
    //   4	59	62	java/io/IOException
    //   17	85	88	java/io/IOException
    //   92	112	115	java/io/IOException
    //   119	232	235	java/io/IOException
    //   175	256	259	java/io/IOException
    //   239	273	276	java/io/IOException
    //   263	293	296	java/io/IOException
    //   280	307	310	java/io/IOException
    //   314	337	340	java/io/IOException
    //   327	380	383	java/io/IOException
    //   344	431	434	java/io/IOException
  }
  
  Zll(Zb paramZb, Zjq paramZjq) {
    this(paramZb);
  }
  
  private static IOException a(IOException paramIOException) {
    return paramIOException;
  }
}


/* Location:              C:\Program Files\BurpSuitePro\burpsuite_pro.jar!\org\yaml\Zll.class
 * Java compiler version: 7 (51.0)
 * JD-Core Version:       1.1.3
 */