package org.yaml;

import java.util.HashMap;
import java.util.Map;

public class Zln implements Zjy {
  private static final Map<String, String> ZS;
  
  protected final Zjl ZI;
  
  private Zlv Zn;
  
  private final Zq<Zgy> Zd;
  
  private final Zq<Zt1> Zb;
  
  private Zgy ZE;
  
  private Zgw Zx;
  
  private static int[] ZL;
  
  private static final String[] a;
  
  private static final String[] b;
  
  public Zln(Zlx paramZlx, Ztw paramZtw) {
    this(new Zju(paramZlx, paramZtw));
  }
  
  public Zln(Zjl paramZjl) {
    this.ZI = paramZjl;
    this.Zn = null;
    this.Zx = new Zgw(null, new HashMap<>(ZS));
    this.Zd = new Zq<>(100);
    this.Zb = new Zq<>(10);
    this.ZE = new Z_q(this, null);
  }
  
  public boolean Zk(Zj7 paramZj7) {
    try {
      ZV();
      if (this.Zn != null)
        try {
          if (this.Zn.Zz(paramZj7));
        } catch (Zlz zlz) {
          throw a(null);
        }  
    } catch (Zlz zlz) {
      throw a(null);
    } 
    return false;
  }
  
  public Zlv ZV() {
    try {
      if (this.Zn == null)
        try {
          if (this.ZE != null)
            this.Zn = this.ZE.ZG(); 
        } catch (Zlz zlz) {
          throw a(null);
        }  
    } catch (Zlz zlz) {
      throw a(null);
    } 
    return this.Zn;
  }
  
  public Zlv ZM() {
    ZV();
    Zlv zlv = this.Zn;
    this.Zn = null;
    return zlv;
  }
  
  private Zld Zf(Zg6 paramZg6) {
    Zt1 zt11 = paramZg6.ZL();
    Zt1 zt12 = paramZg6.Zm();
    String str = paramZg6.ZB();
    Zto zto = paramZg6.Zp();
    return new Zld(zto, str, zt11, zt12);
  }
  
  private Zgw Zp() {
    // Byte code:
    //   0: new java/util/HashMap
    //   3: dup
    //   4: aload_0
    //   5: getfield Zx : Lorg/yaml/Zgw;
    //   8: invokevirtual ZB : ()Ljava/util/Map;
    //   11: invokespecial <init> : (Ljava/util/Map;)V
    //   14: astore_2
    //   15: invokestatic ZS : ()[I
    //   18: getstatic org/yaml/Zln.ZS : Ljava/util/Map;
    //   21: invokeinterface keySet : ()Ljava/util/Set;
    //   26: invokeinterface iterator : ()Ljava/util/Iterator;
    //   31: astore_3
    //   32: astore_1
    //   33: aload_3
    //   34: invokeinterface hasNext : ()Z
    //   39: ifeq -> 64
    //   42: aload_3
    //   43: invokeinterface next : ()Ljava/lang/Object;
    //   48: checkcast java/lang/String
    //   51: astore #4
    //   53: aload_2
    //   54: aload #4
    //   56: invokevirtual remove : (Ljava/lang/Object;)Ljava/lang/Object;
    //   59: pop
    //   60: aload_1
    //   61: ifnonnull -> 33
    //   64: aload_0
    //   65: new org/yaml/Zgw
    //   68: dup
    //   69: aconst_null
    //   70: aload_2
    //   71: invokespecial <init> : (Lorg/yaml/Zjv;Ljava/util/Map;)V
    //   74: putfield Zx : Lorg/yaml/Zgw;
    //   77: aload_0
    //   78: getfield ZI : Lorg/yaml/Zjl;
    //   81: iconst_1
    //   82: anewarray org/yaml/Ztt
    //   85: dup
    //   86: iconst_0
    //   87: getstatic org/yaml/Ztt.Directive : Lorg/yaml/Ztt;
    //   90: aastore
    //   91: invokeinterface ZC : ([Lorg/yaml/Ztt;)Z
    //   96: ifeq -> 428
    //   99: aload_0
    //   100: getfield ZI : Lorg/yaml/Zjl;
    //   103: invokeinterface Zs : ()Lorg/yaml/Z_8;
    //   108: checkcast org/yaml/Zgh
    //   111: astore_3
    //   112: aload_3
    //   113: invokevirtual ZQ : ()Ljava/lang/String;
    //   116: sipush #21973
    //   119: sipush #21272
    //   122: invokestatic a : (II)Ljava/lang/String;
    //   125: invokevirtual equals : (Ljava/lang/Object;)Z
    //   128: ifeq -> 303
    //   131: aload_0
    //   132: getfield Zx : Lorg/yaml/Zgw;
    //   135: invokevirtual Zk : ()Lorg/yaml/Zjv;
    //   138: ifnull -> 175
    //   141: goto -> 148
    //   144: invokestatic a : (Lorg/yaml/Zlz;)Lorg/yaml/Zlz;
    //   147: athrow
    //   148: new org/yaml/Zlz
    //   151: dup
    //   152: aconst_null
    //   153: aconst_null
    //   154: sipush #21980
    //   157: sipush #3730
    //   160: invokestatic a : (II)Ljava/lang/String;
    //   163: aload_3
    //   164: invokevirtual ZL : ()Lorg/yaml/Zt1;
    //   167: invokespecial <init> : (Ljava/lang/String;Lorg/yaml/Zt1;Ljava/lang/String;Lorg/yaml/Zt1;)V
    //   170: athrow
    //   171: invokestatic a : (Lorg/yaml/Zlz;)Lorg/yaml/Zlz;
    //   174: athrow
    //   175: aload_3
    //   176: invokevirtual Zp : ()Ljava/util/List;
    //   179: astore #4
    //   181: aload #4
    //   183: iconst_0
    //   184: invokeinterface get : (I)Ljava/lang/Object;
    //   189: checkcast java/lang/Integer
    //   192: astore #5
    //   194: aload #5
    //   196: invokevirtual intValue : ()I
    //   199: iconst_1
    //   200: if_icmpeq -> 230
    //   203: new org/yaml/Zlz
    //   206: dup
    //   207: aconst_null
    //   208: aconst_null
    //   209: sipush #21972
    //   212: sipush #22021
    //   215: invokestatic a : (II)Ljava/lang/String;
    //   218: aload_3
    //   219: invokevirtual ZL : ()Lorg/yaml/Zt1;
    //   222: invokespecial <init> : (Ljava/lang/String;Lorg/yaml/Zt1;Ljava/lang/String;Lorg/yaml/Zt1;)V
    //   225: athrow
    //   226: invokestatic a : (Lorg/yaml/Zlz;)Lorg/yaml/Zlz;
    //   229: athrow
    //   230: aload #4
    //   232: iconst_1
    //   233: invokeinterface get : (I)Ljava/lang/Object;
    //   238: checkcast java/lang/Integer
    //   241: astore #6
    //   243: aload #6
    //   245: invokevirtual intValue : ()I
    //   248: ifne -> 277
    //   251: aload_0
    //   252: new org/yaml/Zgw
    //   255: dup
    //   256: getstatic org/yaml/Zjv.V1_0 : Lorg/yaml/Zjv;
    //   259: aload_2
    //   260: invokespecial <init> : (Lorg/yaml/Zjv;Ljava/util/Map;)V
    //   263: putfield Zx : Lorg/yaml/Zgw;
    //   266: aload_1
    //   267: ifnonnull -> 299
    //   270: goto -> 277
    //   273: invokestatic a : (Lorg/yaml/Zlz;)Lorg/yaml/Zlz;
    //   276: athrow
    //   277: aload_0
    //   278: new org/yaml/Zgw
    //   281: dup
    //   282: getstatic org/yaml/Zjv.V1_1 : Lorg/yaml/Zjv;
    //   285: aload_2
    //   286: invokespecial <init> : (Lorg/yaml/Zjv;Ljava/util/Map;)V
    //   289: putfield Zx : Lorg/yaml/Zgw;
    //   292: goto -> 299
    //   295: invokestatic a : (Lorg/yaml/Zlz;)Lorg/yaml/Zlz;
    //   298: athrow
    //   299: aload_1
    //   300: ifnonnull -> 424
    //   303: aload_3
    //   304: invokevirtual ZQ : ()Ljava/lang/String;
    //   307: sipush #21975
    //   310: sipush #-13997
    //   313: invokestatic a : (II)Ljava/lang/String;
    //   316: invokevirtual equals : (Ljava/lang/Object;)Z
    //   319: ifeq -> 424
    //   322: goto -> 329
    //   325: invokestatic a : (Lorg/yaml/Zlz;)Lorg/yaml/Zlz;
    //   328: athrow
    //   329: aload_3
    //   330: invokevirtual Zp : ()Ljava/util/List;
    //   333: astore #4
    //   335: aload #4
    //   337: iconst_0
    //   338: invokeinterface get : (I)Ljava/lang/Object;
    //   343: checkcast java/lang/String
    //   346: astore #5
    //   348: aload #4
    //   350: iconst_1
    //   351: invokeinterface get : (I)Ljava/lang/Object;
    //   356: checkcast java/lang/String
    //   359: astore #6
    //   361: aload_2
    //   362: aload #5
    //   364: invokevirtual containsKey : (Ljava/lang/Object;)Z
    //   367: ifeq -> 415
    //   370: new org/yaml/Zlz
    //   373: dup
    //   374: aconst_null
    //   375: aconst_null
    //   376: new java/lang/StringBuilder
    //   379: dup
    //   380: invokespecial <init> : ()V
    //   383: sipush #21969
    //   386: sipush #8749
    //   389: invokestatic a : (II)Ljava/lang/String;
    //   392: invokevirtual append : (Ljava/lang/String;)Ljava/lang/StringBuilder;
    //   395: aload #5
    //   397: invokevirtual append : (Ljava/lang/String;)Ljava/lang/StringBuilder;
    //   400: invokevirtual toString : ()Ljava/lang/String;
    //   403: aload_3
    //   404: invokevirtual ZL : ()Lorg/yaml/Zt1;
    //   407: invokespecial <init> : (Ljava/lang/String;Lorg/yaml/Zt1;Ljava/lang/String;Lorg/yaml/Zt1;)V
    //   410: athrow
    //   411: invokestatic a : (Lorg/yaml/Zlz;)Lorg/yaml/Zlz;
    //   414: athrow
    //   415: aload_2
    //   416: aload #5
    //   418: aload #6
    //   420: invokevirtual put : (Ljava/lang/Object;Ljava/lang/Object;)Ljava/lang/Object;
    //   423: pop
    //   424: aload_1
    //   425: ifnonnull -> 77
    //   428: new java/util/HashMap
    //   431: dup
    //   432: invokespecial <init> : ()V
    //   435: astore_3
    //   436: aload_2
    //   437: invokevirtual isEmpty : ()Z
    //   440: ifne -> 452
    //   443: new java/util/HashMap
    //   446: dup
    //   447: aload_2
    //   448: invokespecial <init> : (Ljava/util/Map;)V
    //   451: astore_3
    //   452: getstatic org/yaml/Zln.ZS : Ljava/util/Map;
    //   455: invokeinterface keySet : ()Ljava/util/Set;
    //   460: invokeinterface iterator : ()Ljava/util/Iterator;
    //   465: astore #4
    //   467: aload #4
    //   469: invokeinterface hasNext : ()Z
    //   474: ifeq -> 526
    //   477: aload #4
    //   479: invokeinterface next : ()Ljava/lang/Object;
    //   484: checkcast java/lang/String
    //   487: astore #5
    //   489: aload_2
    //   490: aload #5
    //   492: invokevirtual containsKey : (Ljava/lang/Object;)Z
    //   495: ifne -> 522
    //   498: aload_2
    //   499: aload #5
    //   501: getstatic org/yaml/Zln.ZS : Ljava/util/Map;
    //   504: aload #5
    //   506: invokeinterface get : (Ljava/lang/Object;)Ljava/lang/Object;
    //   511: invokevirtual put : (Ljava/lang/Object;Ljava/lang/Object;)Ljava/lang/Object;
    //   514: pop
    //   515: goto -> 522
    //   518: invokestatic a : (Lorg/yaml/Zlz;)Lorg/yaml/Zlz;
    //   521: athrow
    //   522: aload_1
    //   523: ifnonnull -> 467
    //   526: new org/yaml/Zgw
    //   529: dup
    //   530: aload_0
    //   531: getfield Zx : Lorg/yaml/Zgw;
    //   534: invokevirtual Zk : ()Lorg/yaml/Zjv;
    //   537: aload_3
    //   538: invokespecial <init> : (Lorg/yaml/Zjv;Ljava/util/Map;)V
    //   541: areturn
    // Exception table:
    //   from	to	target	type
    //   112	141	144	org/yaml/Zlz
    //   131	171	171	org/yaml/Zlz
    //   194	226	226	org/yaml/Zlz
    //   243	270	273	org/yaml/Zlz
    //   251	292	295	org/yaml/Zlz
    //   299	322	325	org/yaml/Zlz
    //   361	411	411	org/yaml/Zlz
    //   489	515	518	org/yaml/Zlz
  }
  
  private Zlv Za() {
    return ZA(false, false);
  }
  
  private Zlv ZX() {
    return ZA(true, true);
  }
  
  private Zlv ZA(boolean paramBoolean1, boolean paramBoolean2) {
    // Byte code:
    //   0: aconst_null
    //   1: astore #5
    //   3: invokestatic ZS : ()[I
    //   6: aconst_null
    //   7: astore #6
    //   9: aconst_null
    //   10: astore #7
    //   12: astore_3
    //   13: aload_0
    //   14: getfield ZI : Lorg/yaml/Zjl;
    //   17: iconst_1
    //   18: anewarray org/yaml/Ztt
    //   21: dup
    //   22: iconst_0
    //   23: getstatic org/yaml/Ztt.Alias : Lorg/yaml/Ztt;
    //   26: aastore
    //   27: invokeinterface ZC : ([Lorg/yaml/Ztt;)Z
    //   32: ifeq -> 91
    //   35: aload_0
    //   36: getfield ZI : Lorg/yaml/Zjl;
    //   39: invokeinterface Zs : ()Lorg/yaml/Z_8;
    //   44: checkcast org/yaml/Z_g
    //   47: astore #8
    //   49: new org/yaml/Zl_
    //   52: dup
    //   53: aload #8
    //   55: invokevirtual ZS : ()Ljava/lang/String;
    //   58: aload #8
    //   60: invokevirtual ZL : ()Lorg/yaml/Zt1;
    //   63: aload #8
    //   65: invokevirtual Zm : ()Lorg/yaml/Zt1;
    //   68: invokespecial <init> : (Ljava/lang/String;Lorg/yaml/Zt1;Lorg/yaml/Zt1;)V
    //   71: astore #4
    //   73: aload_0
    //   74: aload_0
    //   75: getfield Zd : Lorg/yaml/Zq;
    //   78: invokevirtual ZE : ()Ljava/lang/Object;
    //   81: checkcast org/yaml/Zgy
    //   84: putfield ZE : Lorg/yaml/Zgy;
    //   87: aload_3
    //   88: ifnonnull -> 1306
    //   91: aconst_null
    //   92: astore #8
    //   94: aconst_null
    //   95: astore #9
    //   97: aload_0
    //   98: getfield ZI : Lorg/yaml/Zjl;
    //   101: iconst_1
    //   102: anewarray org/yaml/Ztt
    //   105: dup
    //   106: iconst_0
    //   107: getstatic org/yaml/Ztt.Anchor : Lorg/yaml/Ztt;
    //   110: aastore
    //   111: invokeinterface ZC : ([Lorg/yaml/Ztt;)Z
    //   116: ifeq -> 214
    //   119: aload_0
    //   120: getfield ZI : Lorg/yaml/Zjl;
    //   123: invokeinterface Zs : ()Lorg/yaml/Z_8;
    //   128: checkcast org/yaml/Z__
    //   131: astore #10
    //   133: aload #10
    //   135: invokevirtual ZL : ()Lorg/yaml/Zt1;
    //   138: astore #5
    //   140: aload #10
    //   142: invokevirtual Zm : ()Lorg/yaml/Zt1;
    //   145: astore #6
    //   147: aload #10
    //   149: invokevirtual ZX : ()Ljava/lang/String;
    //   152: astore #8
    //   154: aload_0
    //   155: getfield ZI : Lorg/yaml/Zjl;
    //   158: iconst_1
    //   159: anewarray org/yaml/Ztt
    //   162: dup
    //   163: iconst_0
    //   164: getstatic org/yaml/Ztt.Tag : Lorg/yaml/Ztt;
    //   167: aastore
    //   168: invokeinterface ZC : ([Lorg/yaml/Ztt;)Z
    //   173: ifeq -> 211
    //   176: aload_0
    //   177: getfield ZI : Lorg/yaml/Zjl;
    //   180: invokeinterface Zs : ()Lorg/yaml/Z_8;
    //   185: checkcast org/yaml/Zg0
    //   188: astore #11
    //   190: aload #11
    //   192: invokevirtual ZL : ()Lorg/yaml/Zt1;
    //   195: astore #7
    //   197: aload #11
    //   199: invokevirtual Zm : ()Lorg/yaml/Zt1;
    //   202: astore #6
    //   204: aload #11
    //   206: invokevirtual Zj : ()Lorg/yaml/Ztj;
    //   209: astore #9
    //   211: goto -> 325
    //   214: aload_0
    //   215: getfield ZI : Lorg/yaml/Zjl;
    //   218: iconst_1
    //   219: anewarray org/yaml/Ztt
    //   222: dup
    //   223: iconst_0
    //   224: getstatic org/yaml/Ztt.Tag : Lorg/yaml/Ztt;
    //   227: aastore
    //   228: invokeinterface ZC : ([Lorg/yaml/Ztt;)Z
    //   233: ifeq -> 325
    //   236: aload_0
    //   237: getfield ZI : Lorg/yaml/Zjl;
    //   240: invokeinterface Zs : ()Lorg/yaml/Z_8;
    //   245: checkcast org/yaml/Zg0
    //   248: astore #10
    //   250: aload #10
    //   252: invokevirtual ZL : ()Lorg/yaml/Zt1;
    //   255: astore #5
    //   257: aload #5
    //   259: astore #7
    //   261: aload #10
    //   263: invokevirtual Zm : ()Lorg/yaml/Zt1;
    //   266: astore #6
    //   268: aload #10
    //   270: invokevirtual Zj : ()Lorg/yaml/Ztj;
    //   273: astore #9
    //   275: aload_0
    //   276: getfield ZI : Lorg/yaml/Zjl;
    //   279: iconst_1
    //   280: anewarray org/yaml/Ztt
    //   283: dup
    //   284: iconst_0
    //   285: getstatic org/yaml/Ztt.Anchor : Lorg/yaml/Ztt;
    //   288: aastore
    //   289: invokeinterface ZC : ([Lorg/yaml/Ztt;)Z
    //   294: ifeq -> 325
    //   297: aload_0
    //   298: getfield ZI : Lorg/yaml/Zjl;
    //   301: invokeinterface Zs : ()Lorg/yaml/Z_8;
    //   306: checkcast org/yaml/Z__
    //   309: astore #11
    //   311: aload #11
    //   313: invokevirtual Zm : ()Lorg/yaml/Zt1;
    //   316: astore #6
    //   318: aload #11
    //   320: invokevirtual ZX : ()Ljava/lang/String;
    //   323: astore #8
    //   325: aconst_null
    //   326: astore #10
    //   328: aload #9
    //   330: ifnull -> 472
    //   333: aload #9
    //   335: invokevirtual ZD : ()Ljava/lang/String;
    //   338: astore #11
    //   340: aload #9
    //   342: invokevirtual Zn : ()Ljava/lang/String;
    //   345: astore #12
    //   347: aload #11
    //   349: ifnull -> 468
    //   352: aload_0
    //   353: getfield Zx : Lorg/yaml/Zgw;
    //   356: invokevirtual ZB : ()Ljava/util/Map;
    //   359: aload #11
    //   361: invokeinterface containsKey : (Ljava/lang/Object;)Z
    //   366: ifne -> 428
    //   369: goto -> 376
    //   372: invokestatic a : (Lorg/yaml/Zlz;)Lorg/yaml/Zlz;
    //   375: athrow
    //   376: new org/yaml/Zlz
    //   379: dup
    //   380: sipush #21974
    //   383: sipush #-5492
    //   386: invokestatic a : (II)Ljava/lang/String;
    //   389: aload #5
    //   391: new java/lang/StringBuilder
    //   394: dup
    //   395: invokespecial <init> : ()V
    //   398: sipush #21976
    //   401: sipush #-19186
    //   404: invokestatic a : (II)Ljava/lang/String;
    //   407: invokevirtual append : (Ljava/lang/String;)Ljava/lang/StringBuilder;
    //   410: aload #11
    //   412: invokevirtual append : (Ljava/lang/String;)Ljava/lang/StringBuilder;
    //   415: invokevirtual toString : ()Ljava/lang/String;
    //   418: aload #7
    //   420: invokespecial <init> : (Ljava/lang/String;Lorg/yaml/Zt1;Ljava/lang/String;Lorg/yaml/Zt1;)V
    //   423: athrow
    //   424: invokestatic a : (Lorg/yaml/Zlz;)Lorg/yaml/Zlz;
    //   427: athrow
    //   428: new java/lang/StringBuilder
    //   431: dup
    //   432: invokespecial <init> : ()V
    //   435: aload_0
    //   436: getfield Zx : Lorg/yaml/Zgw;
    //   439: invokevirtual ZB : ()Ljava/util/Map;
    //   442: aload #11
    //   444: invokeinterface get : (Ljava/lang/Object;)Ljava/lang/Object;
    //   449: checkcast java/lang/String
    //   452: invokevirtual append : (Ljava/lang/String;)Ljava/lang/StringBuilder;
    //   455: aload #12
    //   457: invokevirtual append : (Ljava/lang/String;)Ljava/lang/StringBuilder;
    //   460: invokevirtual toString : ()Ljava/lang/String;
    //   463: astore #10
    //   465: goto -> 472
    //   468: aload #12
    //   470: astore #10
    //   472: aload #5
    //   474: ifnonnull -> 495
    //   477: aload_0
    //   478: getfield ZI : Lorg/yaml/Zjl;
    //   481: invokeinterface ZG : ()Lorg/yaml/Z_8;
    //   486: invokevirtual ZL : ()Lorg/yaml/Zt1;
    //   489: astore #5
    //   491: aload #5
    //   493: astore #6
    //   495: aconst_null
    //   496: astore #4
    //   498: aload #10
    //   500: ifnull -> 520
    //   503: aload #10
    //   505: ldc '!'
    //   507: invokevirtual equals : (Ljava/lang/Object;)Z
    //   510: ifeq -> 528
    //   513: goto -> 520
    //   516: invokestatic a : (Lorg/yaml/Zlz;)Lorg/yaml/Zlz;
    //   519: athrow
    //   520: iconst_1
    //   521: goto -> 529
    //   524: invokestatic a : (Lorg/yaml/Zlz;)Lorg/yaml/Zlz;
    //   527: athrow
    //   528: iconst_0
    //   529: istore #11
    //   531: iload_2
    //   532: ifeq -> 616
    //   535: aload_0
    //   536: getfield ZI : Lorg/yaml/Zjl;
    //   539: iconst_1
    //   540: anewarray org/yaml/Ztt
    //   543: dup
    //   544: iconst_0
    //   545: getstatic org/yaml/Ztt.BlockEntry : Lorg/yaml/Ztt;
    //   548: aastore
    //   549: invokeinterface ZC : ([Lorg/yaml/Ztt;)Z
    //   554: ifeq -> 616
    //   557: goto -> 564
    //   560: invokestatic a : (Lorg/yaml/Zlz;)Lorg/yaml/Zlz;
    //   563: athrow
    //   564: aload_0
    //   565: getfield ZI : Lorg/yaml/Zjl;
    //   568: invokeinterface ZG : ()Lorg/yaml/Z_8;
    //   573: invokevirtual Zm : ()Lorg/yaml/Zt1;
    //   576: astore #6
    //   578: new org/yaml/Zla
    //   581: dup
    //   582: aload #8
    //   584: aload #10
    //   586: iload #11
    //   588: aload #5
    //   590: aload #6
    //   592: getstatic org/yaml/Zp.BLOCK : Lorg/yaml/Zp;
    //   595: invokespecial <init> : (Ljava/lang/String;Ljava/lang/String;ZLorg/yaml/Zt1;Lorg/yaml/Zt1;Lorg/yaml/Zp;)V
    //   598: astore #4
    //   600: aload_0
    //   601: new org/yaml/Zjs
    //   604: dup
    //   605: aload_0
    //   606: aconst_null
    //   607: invokespecial <init> : (Lorg/yaml/Zln;Lorg/yaml/Zjo;)V
    //   610: putfield ZE : Lorg/yaml/Zgy;
    //   613: goto -> 1306
    //   616: aload_0
    //   617: getfield ZI : Lorg/yaml/Zjl;
    //   620: iconst_1
    //   621: anewarray org/yaml/Ztt
    //   624: dup
    //   625: iconst_0
    //   626: getstatic org/yaml/Ztt.Scalar : Lorg/yaml/Ztt;
    //   629: aastore
    //   630: invokeinterface ZC : ([Lorg/yaml/Ztt;)Z
    //   635: ifeq -> 795
    //   638: aload_0
    //   639: getfield ZI : Lorg/yaml/Zjl;
    //   642: invokeinterface Zs : ()Lorg/yaml/Z_8;
    //   647: checkcast org/yaml/Zgt
    //   650: astore #12
    //   652: aload #12
    //   654: invokevirtual Zm : ()Lorg/yaml/Zt1;
    //   657: astore #6
    //   659: aload #12
    //   661: invokevirtual Zc : ()Z
    //   664: ifeq -> 679
    //   667: aload #10
    //   669: ifnull -> 696
    //   672: goto -> 679
    //   675: invokestatic a : (Lorg/yaml/Zlz;)Lorg/yaml/Zlz;
    //   678: athrow
    //   679: ldc '!'
    //   681: aload #10
    //   683: invokevirtual equals : (Ljava/lang/Object;)Z
    //   686: ifeq -> 711
    //   689: goto -> 696
    //   692: invokestatic a : (Lorg/yaml/Zlz;)Lorg/yaml/Zlz;
    //   695: athrow
    //   696: new org/yaml/Zgr
    //   699: dup
    //   700: iconst_1
    //   701: iconst_0
    //   702: invokespecial <init> : (ZZ)V
    //   705: astore #13
    //   707: aload_3
    //   708: ifnonnull -> 749
    //   711: aload #10
    //   713: ifnonnull -> 738
    //   716: goto -> 723
    //   719: invokestatic a : (Lorg/yaml/Zlz;)Lorg/yaml/Zlz;
    //   722: athrow
    //   723: new org/yaml/Zgr
    //   726: dup
    //   727: iconst_0
    //   728: iconst_1
    //   729: invokespecial <init> : (ZZ)V
    //   732: astore #13
    //   734: aload_3
    //   735: ifnonnull -> 749
    //   738: new org/yaml/Zgr
    //   741: dup
    //   742: iconst_0
    //   743: iconst_0
    //   744: invokespecial <init> : (ZZ)V
    //   747: astore #13
    //   749: new org/yaml/Zl4
    //   752: dup
    //   753: aload #8
    //   755: aload #10
    //   757: aload #13
    //   759: aload #12
    //   761: invokevirtual ZR : ()Ljava/lang/String;
    //   764: aload #5
    //   766: aload #6
    //   768: aload #12
    //   770: invokevirtual Za : ()Lorg/yaml/Zjm;
    //   773: invokespecial <init> : (Ljava/lang/String;Ljava/lang/String;Lorg/yaml/Zgr;Ljava/lang/String;Lorg/yaml/Zt1;Lorg/yaml/Zt1;Lorg/yaml/Zjm;)V
    //   776: astore #4
    //   778: aload_0
    //   779: aload_0
    //   780: getfield Zd : Lorg/yaml/Zq;
    //   783: invokevirtual ZE : ()Ljava/lang/Object;
    //   786: checkcast org/yaml/Zgy
    //   789: putfield ZE : Lorg/yaml/Zgy;
    //   792: goto -> 1306
    //   795: aload_0
    //   796: getfield ZI : Lorg/yaml/Zjl;
    //   799: iconst_1
    //   800: anewarray org/yaml/Ztt
    //   803: dup
    //   804: iconst_0
    //   805: getstatic org/yaml/Ztt.FlowSequenceStart : Lorg/yaml/Ztt;
    //   808: aastore
    //   809: invokeinterface ZC : ([Lorg/yaml/Ztt;)Z
    //   814: ifeq -> 869
    //   817: aload_0
    //   818: getfield ZI : Lorg/yaml/Zjl;
    //   821: invokeinterface ZG : ()Lorg/yaml/Z_8;
    //   826: invokevirtual Zm : ()Lorg/yaml/Zt1;
    //   829: astore #6
    //   831: new org/yaml/Zla
    //   834: dup
    //   835: aload #8
    //   837: aload #10
    //   839: iload #11
    //   841: aload #5
    //   843: aload #6
    //   845: getstatic org/yaml/Zp.FLOW : Lorg/yaml/Zp;
    //   848: invokespecial <init> : (Ljava/lang/String;Ljava/lang/String;ZLorg/yaml/Zt1;Lorg/yaml/Zt1;Lorg/yaml/Zp;)V
    //   851: astore #4
    //   853: aload_0
    //   854: new org/yaml/Zti
    //   857: dup
    //   858: aload_0
    //   859: aconst_null
    //   860: invokespecial <init> : (Lorg/yaml/Zln;Lorg/yaml/Zjo;)V
    //   863: putfield ZE : Lorg/yaml/Zgy;
    //   866: goto -> 1306
    //   869: aload_0
    //   870: getfield ZI : Lorg/yaml/Zjl;
    //   873: iconst_1
    //   874: anewarray org/yaml/Ztt
    //   877: dup
    //   878: iconst_0
    //   879: getstatic org/yaml/Ztt.FlowMappingStart : Lorg/yaml/Ztt;
    //   882: aastore
    //   883: invokeinterface ZC : ([Lorg/yaml/Ztt;)Z
    //   888: ifeq -> 943
    //   891: aload_0
    //   892: getfield ZI : Lorg/yaml/Zjl;
    //   895: invokeinterface ZG : ()Lorg/yaml/Z_8;
    //   900: invokevirtual Zm : ()Lorg/yaml/Zt1;
    //   903: astore #6
    //   905: new org/yaml/Zl3
    //   908: dup
    //   909: aload #8
    //   911: aload #10
    //   913: iload #11
    //   915: aload #5
    //   917: aload #6
    //   919: getstatic org/yaml/Zp.FLOW : Lorg/yaml/Zp;
    //   922: invokespecial <init> : (Ljava/lang/String;Ljava/lang/String;ZLorg/yaml/Zt1;Lorg/yaml/Zt1;Lorg/yaml/Zp;)V
    //   925: astore #4
    //   927: aload_0
    //   928: new org/yaml/Zh
    //   931: dup
    //   932: aload_0
    //   933: aconst_null
    //   934: invokespecial <init> : (Lorg/yaml/Zln;Lorg/yaml/Zjo;)V
    //   937: putfield ZE : Lorg/yaml/Zgy;
    //   940: goto -> 1306
    //   943: iload_1
    //   944: ifeq -> 1028
    //   947: aload_0
    //   948: getfield ZI : Lorg/yaml/Zjl;
    //   951: iconst_1
    //   952: anewarray org/yaml/Ztt
    //   955: dup
    //   956: iconst_0
    //   957: getstatic org/yaml/Ztt.BlockSequenceStart : Lorg/yaml/Ztt;
    //   960: aastore
    //   961: invokeinterface ZC : ([Lorg/yaml/Ztt;)Z
    //   966: ifeq -> 1028
    //   969: goto -> 976
    //   972: invokestatic a : (Lorg/yaml/Zlz;)Lorg/yaml/Zlz;
    //   975: athrow
    //   976: aload_0
    //   977: getfield ZI : Lorg/yaml/Zjl;
    //   980: invokeinterface ZG : ()Lorg/yaml/Z_8;
    //   985: invokevirtual ZL : ()Lorg/yaml/Zt1;
    //   988: astore #6
    //   990: new org/yaml/Zla
    //   993: dup
    //   994: aload #8
    //   996: aload #10
    //   998: iload #11
    //   1000: aload #5
    //   1002: aload #6
    //   1004: getstatic org/yaml/Zp.BLOCK : Lorg/yaml/Zp;
    //   1007: invokespecial <init> : (Ljava/lang/String;Ljava/lang/String;ZLorg/yaml/Zt1;Lorg/yaml/Zt1;Lorg/yaml/Zp;)V
    //   1010: astore #4
    //   1012: aload_0
    //   1013: new org/yaml/Zlb
    //   1016: dup
    //   1017: aload_0
    //   1018: aconst_null
    //   1019: invokespecial <init> : (Lorg/yaml/Zln;Lorg/yaml/Zjo;)V
    //   1022: putfield ZE : Lorg/yaml/Zgy;
    //   1025: goto -> 1306
    //   1028: iload_1
    //   1029: ifeq -> 1113
    //   1032: aload_0
    //   1033: getfield ZI : Lorg/yaml/Zjl;
    //   1036: iconst_1
    //   1037: anewarray org/yaml/Ztt
    //   1040: dup
    //   1041: iconst_0
    //   1042: getstatic org/yaml/Ztt.BlockMappingStart : Lorg/yaml/Ztt;
    //   1045: aastore
    //   1046: invokeinterface ZC : ([Lorg/yaml/Ztt;)Z
    //   1051: ifeq -> 1113
    //   1054: goto -> 1061
    //   1057: invokestatic a : (Lorg/yaml/Zlz;)Lorg/yaml/Zlz;
    //   1060: athrow
    //   1061: aload_0
    //   1062: getfield ZI : Lorg/yaml/Zjl;
    //   1065: invokeinterface ZG : ()Lorg/yaml/Z_8;
    //   1070: invokevirtual ZL : ()Lorg/yaml/Zt1;
    //   1073: astore #6
    //   1075: new org/yaml/Zl3
    //   1078: dup
    //   1079: aload #8
    //   1081: aload #10
    //   1083: iload #11
    //   1085: aload #5
    //   1087: aload #6
    //   1089: getstatic org/yaml/Zp.BLOCK : Lorg/yaml/Zp;
    //   1092: invokespecial <init> : (Ljava/lang/String;Ljava/lang/String;ZLorg/yaml/Zt1;Lorg/yaml/Zt1;Lorg/yaml/Zp;)V
    //   1095: astore #4
    //   1097: aload_0
    //   1098: new org/yaml/Ztq
    //   1101: dup
    //   1102: aload_0
    //   1103: aconst_null
    //   1104: invokespecial <init> : (Lorg/yaml/Zln;Lorg/yaml/Zjo;)V
    //   1107: putfield ZE : Lorg/yaml/Zgy;
    //   1110: goto -> 1306
    //   1113: aload #8
    //   1115: ifnonnull -> 1130
    //   1118: aload #10
    //   1120: ifnull -> 1179
    //   1123: goto -> 1130
    //   1126: invokestatic a : (Lorg/yaml/Zlz;)Lorg/yaml/Zlz;
    //   1129: athrow
    //   1130: new org/yaml/Zl4
    //   1133: dup
    //   1134: aload #8
    //   1136: aload #10
    //   1138: new org/yaml/Zgr
    //   1141: dup
    //   1142: iload #11
    //   1144: iconst_0
    //   1145: invokespecial <init> : (ZZ)V
    //   1148: ldc ''
    //   1150: aload #5
    //   1152: aload #6
    //   1154: getstatic org/yaml/Zjm.PLAIN : Lorg/yaml/Zjm;
    //   1157: invokespecial <init> : (Ljava/lang/String;Ljava/lang/String;Lorg/yaml/Zgr;Ljava/lang/String;Lorg/yaml/Zt1;Lorg/yaml/Zt1;Lorg/yaml/Zjm;)V
    //   1160: astore #4
    //   1162: aload_0
    //   1163: aload_0
    //   1164: getfield Zd : Lorg/yaml/Zq;
    //   1167: invokevirtual ZE : ()Ljava/lang/Object;
    //   1170: checkcast org/yaml/Zgy
    //   1173: putfield ZE : Lorg/yaml/Zgy;
    //   1176: goto -> 1306
    //   1179: aload_0
    //   1180: getfield ZI : Lorg/yaml/Zjl;
    //   1183: invokeinterface ZG : ()Lorg/yaml/Z_8;
    //   1188: astore #12
    //   1190: new org/yaml/Zlz
    //   1193: dup
    //   1194: new java/lang/StringBuilder
    //   1197: dup
    //   1198: invokespecial <init> : ()V
    //   1201: sipush #21979
    //   1204: sipush #27956
    //   1207: invokestatic a : (II)Ljava/lang/String;
    //   1210: invokevirtual append : (Ljava/lang/String;)Ljava/lang/StringBuilder;
    //   1213: iload_1
    //   1214: ifeq -> 1233
    //   1217: sipush #21981
    //   1220: sipush #25536
    //   1223: invokestatic a : (II)Ljava/lang/String;
    //   1226: goto -> 1242
    //   1229: invokestatic a : (Lorg/yaml/Zlz;)Lorg/yaml/Zlz;
    //   1232: athrow
    //   1233: sipush #21978
    //   1236: sipush #-10901
    //   1239: invokestatic a : (II)Ljava/lang/String;
    //   1242: invokevirtual append : (Ljava/lang/String;)Ljava/lang/StringBuilder;
    //   1245: sipush #21968
    //   1248: sipush #1071
    //   1251: invokestatic a : (II)Ljava/lang/String;
    //   1254: invokevirtual append : (Ljava/lang/String;)Ljava/lang/StringBuilder;
    //   1257: invokevirtual toString : ()Ljava/lang/String;
    //   1260: aload #5
    //   1262: new java/lang/StringBuilder
    //   1265: dup
    //   1266: invokespecial <init> : ()V
    //   1269: sipush #21983
    //   1272: sipush #-30564
    //   1275: invokestatic a : (II)Ljava/lang/String;
    //   1278: invokevirtual append : (Ljava/lang/String;)Ljava/lang/StringBuilder;
    //   1281: aload #12
    //   1283: invokevirtual ZI : ()Lorg/yaml/Ztt;
    //   1286: invokevirtual append : (Ljava/lang/Object;)Ljava/lang/StringBuilder;
    //   1289: ldc '''
    //   1291: invokevirtual append : (Ljava/lang/String;)Ljava/lang/StringBuilder;
    //   1294: invokevirtual toString : ()Ljava/lang/String;
    //   1297: aload #12
    //   1299: invokevirtual ZL : ()Lorg/yaml/Zt1;
    //   1302: invokespecial <init> : (Ljava/lang/String;Lorg/yaml/Zt1;Ljava/lang/String;Lorg/yaml/Zt1;)V
    //   1305: athrow
    //   1306: aload #4
    //   1308: areturn
    // Exception table:
    //   from	to	target	type
    //   347	369	372	org/yaml/Zlz
    //   352	424	424	org/yaml/Zlz
    //   498	513	516	org/yaml/Zlz
    //   503	524	524	org/yaml/Zlz
    //   531	557	560	org/yaml/Zlz
    //   659	672	675	org/yaml/Zlz
    //   667	689	692	org/yaml/Zlz
    //   707	716	719	org/yaml/Zlz
    //   943	969	972	org/yaml/Zlz
    //   1028	1054	1057	org/yaml/Zlz
    //   1113	1123	1126	org/yaml/Zlz
    //   1190	1229	1229	org/yaml/Zlz
  }
  
  private Zlv Z_(Zt1 paramZt1) {
    return new Zl4(null, null, new Zgr(true, false), "", paramZt1, paramZt1, Zjm.PLAIN);
  }
  
  static Zgy ZH(Zln paramZln, Zgy paramZgy) {
    return paramZln.ZE = paramZgy;
  }
  
  static Zld Zm(Zln paramZln, Zg6 paramZg6) {
    return paramZln.Zf(paramZg6);
  }
  
  static Zq ZC(Zln paramZln) {
    return paramZln.Zd;
  }
  
  static Zgw Zn(Zln paramZln) {
    return paramZln.Zp();
  }
  
  static Zq ZD(Zln paramZln) {
    return paramZln.Zb;
  }
  
  static Zlv Zg(Zln paramZln, Zt1 paramZt1) {
    return paramZln.Z_(paramZt1);
  }
  
  static Zlv ZK(Zln paramZln, boolean paramBoolean1, boolean paramBoolean2) {
    return paramZln.ZA(paramBoolean1, paramBoolean2);
  }
  
  static Zlv Ze(Zln paramZln) {
    return paramZln.ZX();
  }
  
  static Zgy Zy(Zln paramZln) {
    return paramZln.ZE;
  }
  
  static Zlv ZQ(Zln paramZln) {
    return paramZln.Za();
  }
  
  static {
    // Byte code:
    //   0: bipush #14
    //   2: anewarray java/lang/String
    //   5: astore #5
    //   7: iconst_0
    //   8: istore_3
    //   9: iconst_5
    //   10: newarray int
    //   12: ldc 'Ã¹u]ÃÃ”-dTÂ†Â’p#Â¶Ã±Ã»Ã„Â€Â¨Ãž$Ã™Â£Â…Ã«LÂ—Ã¯ÂªÂ­ÂŸ&Â½-Â³(Â«Â­Â»VSÂ•:ÂœkÃ‰:SEÂ©Â-.dÃÃŠÃ’Ã©Â¼[0ÂœÃ±Ã“AÃ¬Â¿GÂ“Ã±Ã¯iÂªÂ‹tÂ«Ã“\\rÂ“t6Â–OÂ­Ã‰]Â¢PÃ¥Â«ÂsÃ”k)d.5VÂˆQi#*u\\b8Ã Ã“Â¯Â¯Â¶v}Âµ&ÃŒÂ:$'Ã¦Â—Â£dÃ¿VÂ—Â»EUÂ¨Ã‚VÂŒÃ‹-Â¨Ãœ+Ã»Ã¿ÂÂ¢Ã£Â»ÂºÂ¯Ã’Ã²ÂÃ¬-5Â§Ã£t(HGgÃ¢Â´SÂ½Â¢1!ÂœÂ»Â¿:aÂ¦Ã¸gÃŠÂ¯Ãš?Ã¨Ã‘Â”@Ã™Â–Ã¯Ã•*Ã°a'
    //   14: dup
    //   15: astore_2
    //   16: invokevirtual length : ()I
    //   19: istore #4
    //   21: bipush #30
    //   23: istore_1
    //   24: invokestatic ZI : ([I)V
    //   27: iconst_m1
    //   28: istore_0
    //   29: bipush #16
    //   31: iinc #0, 1
    //   34: aload_2
    //   35: iload_0
    //   36: dup
    //   37: iload_1
    //   38: iadd
    //   39: invokevirtual substring : (II)Ljava/lang/String;
    //   42: iconst_m1
    //   43: goto -> 147
    //   46: aload #5
    //   48: swap
    //   49: iload_3
    //   50: iinc #3, 1
    //   53: swap
    //   54: aastore
    //   55: iload_0
    //   56: iload_1
    //   57: iadd
    //   58: dup
    //   59: istore_0
    //   60: iload #4
    //   62: if_icmpge -> 74
    //   65: aload_2
    //   66: iload_0
    //   67: invokevirtual charAt : (I)C
    //   70: istore_1
    //   71: goto -> 29
    //   74: ldc 'Ã®{HÃ¢Â)HÂ¢ÃŽ+bR{8ÂºÃŸ`Ã˜VÃ½,Ã MÂ‡'
    //   76: dup
    //   77: astore_2
    //   78: invokevirtual length : ()I
    //   81: istore #4
    //   83: iconst_5
    //   84: istore_1
    //   85: iconst_m1
    //   86: istore_0
    //   87: iconst_2
    //   88: iinc #0, 1
    //   91: aload_2
    //   92: iload_0
    //   93: dup
    //   94: iload_1
    //   95: iadd
    //   96: invokevirtual substring : (II)Ljava/lang/String;
    //   99: iconst_0
    //   100: goto -> 147
    //   103: aload #5
    //   105: swap
    //   106: iload_3
    //   107: iinc #3, 1
    //   110: swap
    //   111: aastore
    //   112: iload_0
    //   113: iload_1
    //   114: iadd
    //   115: dup
    //   116: istore_0
    //   117: iload #4
    //   119: if_icmpge -> 131
    //   122: aload_2
    //   123: iload_0
    //   124: invokevirtual charAt : (I)C
    //   127: istore_1
    //   128: goto -> 87
    //   131: aload #5
    //   133: putstatic org/yaml/Zln.a : [Ljava/lang/String;
    //   136: bipush #14
    //   138: anewarray java/lang/String
    //   141: putstatic org/yaml/Zln.b : [Ljava/lang/String;
    //   144: goto -> 304
    //   147: dup_x2
    //   148: pop
    //   149: invokevirtual toCharArray : ()[C
    //   152: dup_x1
    //   153: arraylength
    //   154: dup_x2
    //   155: pop
    //   156: iconst_0
    //   157: istore #6
    //   159: dup2_x1
    //   160: pop2
    //   161: dup_x2
    //   162: iconst_1
    //   163: if_icmpgt -> 264
    //   166: dup2
    //   167: swap
    //   168: iload #6
    //   170: dup2_x1
    //   171: caload
    //   172: swap
    //   173: iload #6
    //   175: bipush #7
    //   177: irem
    //   178: tableswitch default -> 246, 0 -> 216, 1 -> 221, 2 -> 226, 3 -> 231, 4 -> 236, 5 -> 241
    //   216: bipush #79
    //   218: goto -> 248
    //   221: bipush #54
    //   223: goto -> 248
    //   226: bipush #70
    //   228: goto -> 248
    //   231: bipush #75
    //   233: goto -> 248
    //   236: bipush #26
    //   238: goto -> 248
    //   241: bipush #110
    //   243: goto -> 248
    //   246: bipush #91
    //   248: ixor
    //   249: ixor
    //   250: i2c
    //   251: castore
    //   252: iinc #6, 1
    //   255: dup
    //   256: ifne -> 264
    //   259: dup2
    //   260: dup_x1
    //   261: goto -> 170
    //   264: dup2_x1
    //   265: pop2
    //   266: dup_x2
    //   267: iload #6
    //   269: if_icmpgt -> 166
    //   272: pop
    //   273: new java/lang/String
    //   276: dup_x1
    //   277: swap
    //   278: invokespecial <init> : ([C)V
    //   281: invokevirtual intern : ()Ljava/lang/String;
    //   284: swap
    //   285: pop
    //   286: swap
    //   287: tableswitch default -> 46, 0 -> 103
    //   304: new java/util/HashMap
    //   307: dup
    //   308: invokespecial <init> : ()V
    //   311: putstatic org/yaml/Zln.ZS : Ljava/util/Map;
    //   314: getstatic org/yaml/Zln.ZS : Ljava/util/Map;
    //   317: ldc '!'
    //   319: ldc '!'
    //   321: invokeinterface put : (Ljava/lang/Object;Ljava/lang/Object;)Ljava/lang/Object;
    //   326: pop
    //   327: getstatic org/yaml/Zln.ZS : Ljava/util/Map;
    //   330: sipush #21982
    //   333: sipush #-20502
    //   336: invokestatic a : (II)Ljava/lang/String;
    //   339: sipush #21977
    //   342: sipush #-27891
    //   345: invokestatic a : (II)Ljava/lang/String;
    //   348: invokeinterface put : (Ljava/lang/Object;Ljava/lang/Object;)Ljava/lang/Object;
    //   353: pop
    //   354: return
  }
  
  public static void ZI(int[] paramArrayOfint) {
    ZL = paramArrayOfint;
  }
  
  public static int[] ZS() {
    return ZL;
  }
  
  private static Zlz a(Zlz paramZlz) {
    return paramZlz;
  }
  
  private static String a(int paramInt1, int paramInt2) {
    int i = (paramInt1 ^ 0x55DC) & 0xFFFF;
    if (b[i] == null) {
      char[] arrayOfChar = a[i].toCharArray();
      switch (arrayOfChar[0] & 0xFF) {
        case 0:
        
        case 1:
        
        case 2:
        
        case 3:
        
        case 4:
        
        case 5:
        
        case 6:
        
        case 7:
        
        case 8:
        
        case 9:
        
        case 10:
        
        case 11:
        
        case 12:
        
        case 13:
        
        case 14:
        
        case 15:
        
        case 16:
        
        case 17:
        
        case 18:
        
        case 19:
        
        case 20:
        
        case 21:
        
        case 22:
        
        case 23:
        
        case 24:
        
        case 25:
        
        case 26:
        
        case 27:
        
        case 28:
        
        case 29:
        
        case 30:
        
        case 31:
        
        case 32:
        
        case 33:
        
        case 34:
        
        case 35:
        
        case 36:
        
        case 37:
        
        case 38:
        
        case 39:
        
        case 40:
        
        case 41:
        
        case 42:
        
        case 43:
        
        case 44:
        
        case 45:
        
        case 46:
        
        case 47:
        
        case 48:
        
        case 49:
        
        case 50:
        
        case 51:
        
        case 52:
        
        case 53:
        
        case 54:
        
        case 55:
        
        case 56:
        
        case 57:
        
        case 58:
        
        case 59:
        
        case 60:
        
        case 61:
        
        case 62:
        
        case 63:
        
        case 64:
        
        case 65:
        
        case 66:
        
        case 67:
        
        case 68:
        
        case 69:
        
        case 70:
        
        case 71:
        
        case 72:
        
        case 73:
        
        case 74:
        
        case 75:
        
        case 76:
        
        case 77:
        
        case 78:
        
        case 79:
        
        case 80:
        
        case 81:
        
        case 82:
        
        case 83:
        
        case 84:
        
        case 85:
        
        case 86:
        
        case 87:
        
        case 88:
        
        case 89:
        
        case 90:
        
        case 91:
        
        case 92:
        
        case 93:
        
        case 94:
        
        case 95:
        
        case 96:
        
        case 97:
        
        case 98:
        
        case 99:
        
        case 100:
        
        case 101:
        
        case 102:
        
        case 103:
        
        case 104:
        
        case 105:
        
        case 106:
        
        case 107:
        
        case 108:
        
        case 109:
        
        case 110:
        
        case 111:
        
        case 112:
        
        case 113:
        
        case 114:
        
        case 115:
        
        case 116:
        
        case 117:
        
        case 118:
        
        case 119:
        
        case 120:
        
        case 121:
        
        case 122:
        
        case 123:
        
        case 124:
        
        case 125:
        
        case 126:
        
        case 127:
        
        case 128:
        
        case 129:
        
        case 130:
        
        case 131:
        
        case 132:
        
        case 133:
        
        case 134:
        
        case 135:
        
        case 136:
        
        case 137:
        
        case 138:
        
        case 139:
        
        case 140:
        
        case 141:
        
        case 142:
        
        case 143:
        
        case 144:
        
        case 145:
        
        case 146:
        
        case 147:
        
        case 148:
        
        case 149:
        
        case 150:
        
        case 151:
        
        case 152:
        
        case 153:
        
        case 154:
        
        case 155:
        
        case 156:
        
        case 157:
        
        case 158:
        
        case 159:
        
        case 160:
        
        case 161:
        
        case 162:
        
        case 163:
        
        case 164:
        
        case 165:
        
        case 166:
        
        case 167:
        
        case 168:
        
        case 169:
        
        case 170:
        
        case 171:
        
        case 172:
        
        case 173:
        
        case 174:
        
        case 175:
        
        case 176:
        
        case 177:
        
        case 178:
        
        case 179:
        
        case 180:
        
        case 181:
        
        case 182:
        
        case 183:
        
        case 184:
        
        case 185:
        
        case 186:
        
        case 187:
        
        case 188:
        
        case 189:
        
        case 190:
        
        case 191:
        
        case 192:
        
        case 193:
        
        case 194:
        
        case 195:
        
        case 196:
        
        case 197:
        
        case 198:
        
        case 199:
        
        case 200:
        
        case 201:
        
        case 202:
        
        case 203:
        
        case 204:
        
        case 205:
        
        case 206:
        
        case 207:
        
        case 208:
        
        case 209:
        
        case 210:
        
        case 211:
        
        case 212:
        
        case 213:
        
        case 214:
        
        case 215:
        
        case 216:
        
        case 217:
        
        case 218:
        
        case 219:
        
        case 220:
        
        case 221:
        
        case 222:
        
        case 223:
        
        case 224:
        
        case 225:
        
        case 226:
        
        case 227:
        
        case 228:
        
        case 229:
        
        case 230:
        
        case 231:
        
        case 232:
        
        case 233:
        
        case 234:
        
        case 235:
        
        case 236:
        
        case 237:
        
        case 238:
        
        case 239:
        
        case 240:
        
        case 241:
        
        case 242:
        
        case 243:
        
        case 244:
        
        case 245:
        
        case 246:
        
        case 247:
        
        case 248:
        
        case 249:
        
        case 250:
        
        case 251:
        
        case 252:
        
        case 253:
        
        case 254:
        
        default:
          break;
      } 
      byte b1 = 99;
      int j = (paramInt2 & 0xFF) - b1;
      if (j < 0)
        j += 256; 
      int k = ((paramInt2 & 0xFFFF) >>> 8) - b1;
      if (k < 0)
        k += 256; 
      for (byte b2 = 0; b2 < arrayOfChar.length; b2++) {
        int m = b2 % 2;
        if (m == 0) {
          arrayOfChar[b2] = (char)(arrayOfChar[b2] ^ j);
          j = ((j >>> 3 | j << 5) ^ arrayOfChar[b2]) & 0xFF;
        } else {
          arrayOfChar[b2] = (char)(arrayOfChar[b2] ^ k);
          k = ((k >>> 3 | k << 5) ^ arrayOfChar[b2]) & 0xFF;
        } 
      } 
      b[i] = (new String(arrayOfChar)).intern();
    } 
    return b[i];
  }
}


/* Location:              C:\Program Files\BurpSuitePro\burpsuite_pro.jar!\org\yaml\Zln.class
 * Java compiler version: 7 (51.0)
 * JD-Core Version:       1.1.3
 */