package com.fasterxml.Zs;

import burp.Zbqc;
import com.fasterxml.Zb.Zd;
import com.fasterxml.Zb.Zg;
import com.fasterxml.Zb.Zl;
import com.fasterxml.Zb.Zq;
import com.fasterxml.Ze.Z_;
import com.fasterxml.Ze.Zc;
import com.fasterxml.Zh.Zd;
import com.fasterxml.Zm.Zeg;
import com.fasterxml.Zm.Zk;
import com.fasterxml.Zo.Zi;
import com.fasterxml.Zo.Zq;
import com.fasterxml.Zo.Zz7;
import com.fasterxml.Zo.Zzb;
import com.fasterxml.Zo.Zzp;
import com.fasterxml.Zor.Zf;
import com.fasterxml.Zor.Zk;
import com.fasterxml.Zor.Zo;
import com.fasterxml.Zor.Zy_;
import com.fasterxml.Zor.Zyg;
import com.fasterxml.Zor.Zyo;
import com.fasterxml.Zp.Zt;
import com.fasterxml.Zw.Zl;
import java.io.IOException;
import java.util.ArrayList;
import java.util.List;
import java.util.Map;
import java.util.Set;

@Zl
public class Zp extends Zx<Map<Object, Object>> implements Zi, Zq {
  private static final long serialVersionUID = 1L;
  
  protected final Zf Zq;
  
  protected boolean ZN;
  
  protected final Zyo<Object> Zh;
  
  protected final Zt ZE;
  
  protected final Zzp ZF;
  
  protected Zyo<Object> Ze;
  
  protected Zc Zf;
  
  protected final boolean ZP;
  
  protected Set<String> ZV;
  
  protected Set<String> Zc;
  
  protected Zk Zs;
  
  protected boolean ZU;
  
  private static final String[] g;
  
  private static final String[] h;
  
  public Zp(Zk paramZk, Zzp paramZzp, Zf paramZf, Zyo<Object> paramZyo, Zt paramZt) {
    super(paramZk, (Zzb)null, (Boolean)null);
    this.Zq = paramZf;
    this.Zh = paramZyo;
    this.ZE = paramZt;
    this.ZF = paramZzp;
    this.ZP = paramZzp.ZJ();
    this.Ze = null;
    this.Zf = null;
    this.ZN = ZL(paramZk, paramZf);
    this.Zs = null;
    this.ZU = paramZk.ZB().ZP(Object.class);
  }
  
  protected Zp(Zp paramZp, Zf paramZf, Zyo<Object> paramZyo, Zt paramZt, Zzb paramZzb, Set<String> paramSet1, Set<String> paramSet2) {
    super(paramZp, paramZzb, paramZp.ZR);
    this.Zq = paramZf;
    this.Zh = paramZyo;
    this.ZE = paramZt;
    this.ZF = paramZp.ZF;
    this.Zf = paramZp.Zf;
    this.Ze = paramZp.Ze;
    this.ZP = paramZp.ZP;
    this.ZV = paramSet1;
    this.Zc = paramSet2;
    this.Zs = Zeg.Zr(paramSet1, paramSet2);
    this.ZN = ZL(this.Zp, paramZf);
    this.ZU = paramZp.ZU;
  }
  
  protected Zp ZX(Zf paramZf, Zt paramZt, Zyo<?> paramZyo, Zzb paramZzb, Set<String> paramSet1, Set<String> paramSet2) {
    return (this.Zq == paramZf && this.Zh == paramZyo && this.ZE == paramZt && this.ZQ == paramZzb && this.ZV == paramSet1 && this.Zc == paramSet2) ? this : new Zp(this, paramZf, (Zyo)paramZyo, paramZt, paramZzb, paramSet1, paramSet2);
  }
  
  protected final boolean ZL(Zk paramZk, Zf paramZf) {
    if (paramZf == null)
      return true; 
    Zk zk = paramZk.Zu();
    if (zk == null)
      return true; 
    Class<String> clazz = zk.Zf();
    return ((clazz == String.class || clazz == Object.class) && ZS(paramZf));
  }
  
  public void ZE(Set<String> paramSet) {
    this.ZV = (paramSet == null || paramSet.isEmpty()) ? null : paramSet;
    this.Zs = Zeg.Zr(this.ZV, this.Zc);
  }
  
  public void ZV(Set<String> paramSet) {
    this.Zc = paramSet;
    this.Zs = Zeg.Zr(this.ZV, this.Zc);
  }
  
  public void Zs(Zyg paramZyg) throws Zy_ {
    // Byte code:
    //   0: invokestatic Zn : ()[Lburp/Zbqc;
    //   3: astore_2
    //   4: aload_0
    //   5: getfield ZF : Lcom/fasterxml/Zo/Zzp;
    //   8: invokevirtual ZR : ()Z
    //   11: ifeq -> 97
    //   14: aload_0
    //   15: getfield ZF : Lcom/fasterxml/Zo/Zzp;
    //   18: aload_1
    //   19: invokevirtual Za : ()Lcom/fasterxml/Zor/Zyc;
    //   22: invokevirtual ZH : (Lcom/fasterxml/Zor/Zyc;)Lcom/fasterxml/Zor/Zk;
    //   25: astore_3
    //   26: aload_3
    //   27: ifnonnull -> 82
    //   30: aload_1
    //   31: aload_0
    //   32: getfield Zp : Lcom/fasterxml/Zor/Zk;
    //   35: sipush #5465
    //   38: sipush #-5564
    //   41: invokestatic d : (II)Ljava/lang/String;
    //   44: iconst_2
    //   45: anewarray java/lang/Object
    //   48: dup
    //   49: iconst_0
    //   50: aload_0
    //   51: getfield Zp : Lcom/fasterxml/Zor/Zk;
    //   54: aastore
    //   55: dup
    //   56: iconst_1
    //   57: aload_0
    //   58: getfield ZF : Lcom/fasterxml/Zo/Zzp;
    //   61: invokevirtual getClass : ()Ljava/lang/Class;
    //   64: invokevirtual getName : ()Ljava/lang/String;
    //   67: aastore
    //   68: invokestatic format : (Ljava/lang/String;[Ljava/lang/Object;)Ljava/lang/String;
    //   71: invokevirtual Zm : (Lcom/fasterxml/Zor/Zk;Ljava/lang/String;)Ljava/lang/Object;
    //   74: pop
    //   75: goto -> 82
    //   78: invokestatic a : (Ljava/lang/Exception;)Ljava/lang/Exception;
    //   81: athrow
    //   82: aload_0
    //   83: aload_0
    //   84: aload_1
    //   85: aload_3
    //   86: aconst_null
    //   87: invokevirtual ZV : (Lcom/fasterxml/Zor/Zyg;Lcom/fasterxml/Zor/Zk;Lcom/fasterxml/Zor/Zo;)Lcom/fasterxml/Zor/Zyo;
    //   90: putfield Ze : Lcom/fasterxml/Zor/Zyo;
    //   93: aload_2
    //   94: ifnull -> 193
    //   97: aload_0
    //   98: getfield ZF : Lcom/fasterxml/Zo/Zzp;
    //   101: invokevirtual Zb : ()Z
    //   104: ifeq -> 193
    //   107: goto -> 114
    //   110: invokestatic a : (Ljava/lang/Exception;)Ljava/lang/Exception;
    //   113: athrow
    //   114: aload_0
    //   115: getfield ZF : Lcom/fasterxml/Zo/Zzp;
    //   118: aload_1
    //   119: invokevirtual Za : ()Lcom/fasterxml/Zor/Zyc;
    //   122: invokevirtual ZQ : (Lcom/fasterxml/Zor/Zyc;)Lcom/fasterxml/Zor/Zk;
    //   125: astore_3
    //   126: aload_3
    //   127: ifnonnull -> 182
    //   130: aload_1
    //   131: aload_0
    //   132: getfield Zp : Lcom/fasterxml/Zor/Zk;
    //   135: sipush #5467
    //   138: sipush #21654
    //   141: invokestatic d : (II)Ljava/lang/String;
    //   144: iconst_2
    //   145: anewarray java/lang/Object
    //   148: dup
    //   149: iconst_0
    //   150: aload_0
    //   151: getfield Zp : Lcom/fasterxml/Zor/Zk;
    //   154: aastore
    //   155: dup
    //   156: iconst_1
    //   157: aload_0
    //   158: getfield ZF : Lcom/fasterxml/Zo/Zzp;
    //   161: invokevirtual getClass : ()Ljava/lang/Class;
    //   164: invokevirtual getName : ()Ljava/lang/String;
    //   167: aastore
    //   168: invokestatic format : (Ljava/lang/String;[Ljava/lang/Object;)Ljava/lang/String;
    //   171: invokevirtual Zm : (Lcom/fasterxml/Zor/Zk;Ljava/lang/String;)Ljava/lang/Object;
    //   174: pop
    //   175: goto -> 182
    //   178: invokestatic a : (Ljava/lang/Exception;)Ljava/lang/Exception;
    //   181: athrow
    //   182: aload_0
    //   183: aload_0
    //   184: aload_1
    //   185: aload_3
    //   186: aconst_null
    //   187: invokevirtual ZV : (Lcom/fasterxml/Zor/Zyg;Lcom/fasterxml/Zor/Zk;Lcom/fasterxml/Zor/Zo;)Lcom/fasterxml/Zor/Zyo;
    //   190: putfield Ze : Lcom/fasterxml/Zor/Zyo;
    //   193: aload_0
    //   194: getfield ZF : Lcom/fasterxml/Zo/Zzp;
    //   197: invokevirtual ZN : ()Z
    //   200: ifeq -> 235
    //   203: aload_0
    //   204: getfield ZF : Lcom/fasterxml/Zo/Zzp;
    //   207: aload_1
    //   208: invokevirtual Za : ()Lcom/fasterxml/Zor/Zyc;
    //   211: invokevirtual Zg : (Lcom/fasterxml/Zor/Zyc;)[Lcom/fasterxml/Zo/Zv;
    //   214: astore_3
    //   215: aload_0
    //   216: aload_1
    //   217: aload_0
    //   218: getfield ZF : Lcom/fasterxml/Zo/Zzp;
    //   221: aload_3
    //   222: aload_1
    //   223: getstatic com/fasterxml/Zor/Zy9.ACCEPT_CASE_INSENSITIVE_PROPERTIES : Lcom/fasterxml/Zor/Zy9;
    //   226: invokevirtual Zm : (Lcom/fasterxml/Zor/Zy9;)Z
    //   229: invokestatic ZV : (Lcom/fasterxml/Zor/Zyg;Lcom/fasterxml/Zo/Zzp;[Lcom/fasterxml/Zo/Zv;Z)Lcom/fasterxml/Ze/Zc;
    //   232: putfield Zf : Lcom/fasterxml/Ze/Zc;
    //   235: aload_0
    //   236: aload_0
    //   237: aload_0
    //   238: getfield Zp : Lcom/fasterxml/Zor/Zk;
    //   241: aload_0
    //   242: getfield Zq : Lcom/fasterxml/Zor/Zf;
    //   245: invokevirtual ZL : (Lcom/fasterxml/Zor/Zk;Lcom/fasterxml/Zor/Zf;)Z
    //   248: putfield ZN : Z
    //   251: return
    // Exception table:
    //   from	to	target	type
    //   26	75	78	com/fasterxml/Zor/Zy_
    //   82	107	110	com/fasterxml/Zor/Zy_
    //   126	175	178	com/fasterxml/Zor/Zy_
  }
  
  public Zyo<?> Zq(Zyg paramZyg, Zo paramZo) throws Zy_ {
    // Byte code:
    //   0: invokestatic Zn : ()[Lburp/Zbqc;
    //   3: aload_0
    //   4: getfield Zq : Lcom/fasterxml/Zor/Zf;
    //   7: astore #4
    //   9: astore_3
    //   10: aload #4
    //   12: ifnonnull -> 33
    //   15: aload_1
    //   16: aload_0
    //   17: getfield Zp : Lcom/fasterxml/Zor/Zk;
    //   20: invokevirtual Zu : ()Lcom/fasterxml/Zor/Zk;
    //   23: aload_2
    //   24: invokevirtual ZR : (Lcom/fasterxml/Zor/Zk;Lcom/fasterxml/Zor/Zo;)Lcom/fasterxml/Zor/Zf;
    //   27: astore #4
    //   29: aload_3
    //   30: ifnull -> 62
    //   33: aload #4
    //   35: instanceof com/fasterxml/Zo/Zp
    //   38: ifeq -> 62
    //   41: goto -> 48
    //   44: invokestatic a : (Ljava/lang/Exception;)Ljava/lang/Exception;
    //   47: athrow
    //   48: aload #4
    //   50: checkcast com/fasterxml/Zo/Zp
    //   53: aload_1
    //   54: aload_2
    //   55: invokeinterface ZZ : (Lcom/fasterxml/Zor/Zyg;Lcom/fasterxml/Zor/Zo;)Lcom/fasterxml/Zor/Zf;
    //   60: astore #4
    //   62: aload_0
    //   63: getfield Zh : Lcom/fasterxml/Zor/Zyo;
    //   66: astore #5
    //   68: aload_2
    //   69: ifnull -> 82
    //   72: aload_0
    //   73: aload_1
    //   74: aload_2
    //   75: aload #5
    //   77: invokevirtual Zq : (Lcom/fasterxml/Zor/Zyg;Lcom/fasterxml/Zor/Zo;Lcom/fasterxml/Zor/Zyo;)Lcom/fasterxml/Zor/Zyo;
    //   80: astore #5
    //   82: aload_0
    //   83: getfield Zp : Lcom/fasterxml/Zor/Zk;
    //   86: invokevirtual ZB : ()Lcom/fasterxml/Zor/Zk;
    //   89: astore #6
    //   91: aload #5
    //   93: ifnonnull -> 109
    //   96: aload_1
    //   97: aload #6
    //   99: aload_2
    //   100: invokevirtual ZC : (Lcom/fasterxml/Zor/Zk;Lcom/fasterxml/Zor/Zo;)Lcom/fasterxml/Zor/Zyo;
    //   103: astore #5
    //   105: aload_3
    //   106: ifnull -> 120
    //   109: aload_1
    //   110: aload #5
    //   112: aload_2
    //   113: aload #6
    //   115: invokevirtual Zm : (Lcom/fasterxml/Zor/Zyo;Lcom/fasterxml/Zor/Zo;Lcom/fasterxml/Zor/Zk;)Lcom/fasterxml/Zor/Zyo;
    //   118: astore #5
    //   120: aload_0
    //   121: getfield ZE : Lcom/fasterxml/Zp/Zt;
    //   124: astore #7
    //   126: aload #7
    //   128: ifnull -> 139
    //   131: aload #7
    //   133: aload_2
    //   134: invokevirtual Zf : (Lcom/fasterxml/Zor/Zo;)Lcom/fasterxml/Zp/Zt;
    //   137: astore #7
    //   139: aload_0
    //   140: getfield ZV : Ljava/util/Set;
    //   143: astore #8
    //   145: aload_0
    //   146: getfield Zc : Ljava/util/Set;
    //   149: astore #9
    //   151: aload_1
    //   152: invokevirtual Zv : ()Lcom/fasterxml/Zor/Zt;
    //   155: astore #10
    //   157: aload #10
    //   159: aload_2
    //   160: invokestatic Zg : (Ljava/lang/Object;Ljava/lang/Object;)Z
    //   163: ifeq -> 425
    //   166: aload_2
    //   167: invokeinterface ZQ : ()Lcom/fasterxml/Zoz/Ziz;
    //   172: astore #11
    //   174: aload #11
    //   176: ifnull -> 425
    //   179: aload_1
    //   180: invokevirtual Za : ()Lcom/fasterxml/Zor/Zyc;
    //   183: astore #12
    //   185: aload #10
    //   187: aload #12
    //   189: aload #11
    //   191: invokevirtual ZH : (Lcom/fasterxml/Zj/Zf;Lcom/fasterxml/Zoz/Ziv;)Lcom/fasterxml/Zve;
    //   194: astore #13
    //   196: aload #13
    //   198: ifnull -> 300
    //   201: aload #13
    //   203: invokevirtual Zq : ()Ljava/util/Set;
    //   206: astore #14
    //   208: aload #14
    //   210: invokeinterface isEmpty : ()Z
    //   215: ifne -> 300
    //   218: aload #8
    //   220: ifnonnull -> 244
    //   223: goto -> 230
    //   226: invokestatic a : (Ljava/lang/Exception;)Ljava/lang/Exception;
    //   229: athrow
    //   230: new java/util/HashSet
    //   233: dup
    //   234: invokespecial <init> : ()V
    //   237: goto -> 253
    //   240: invokestatic a : (Ljava/lang/Exception;)Ljava/lang/Exception;
    //   243: athrow
    //   244: new java/util/HashSet
    //   247: dup
    //   248: aload #8
    //   250: invokespecial <init> : (Ljava/util/Collection;)V
    //   253: astore #8
    //   255: aload #14
    //   257: invokeinterface iterator : ()Ljava/util/Iterator;
    //   262: astore #15
    //   264: aload #15
    //   266: invokeinterface hasNext : ()Z
    //   271: ifeq -> 300
    //   274: aload #15
    //   276: invokeinterface next : ()Ljava/lang/Object;
    //   281: checkcast java/lang/String
    //   284: astore #16
    //   286: aload #8
    //   288: aload #16
    //   290: invokeinterface add : (Ljava/lang/Object;)Z
    //   295: pop
    //   296: aload_3
    //   297: ifnull -> 264
    //   300: aload #10
    //   302: aload #12
    //   304: aload #11
    //   306: invokevirtual Z_ : (Lcom/fasterxml/Zj/Zf;Lcom/fasterxml/Zoz/Ziv;)Lcom/fasterxml/Zyn;
    //   309: astore #14
    //   311: aload #14
    //   313: ifnull -> 425
    //   316: aload #14
    //   318: invokevirtual ZU : ()Ljava/util/Set;
    //   321: astore #15
    //   323: aload #15
    //   325: ifnull -> 425
    //   328: new java/util/HashSet
    //   331: dup
    //   332: invokespecial <init> : ()V
    //   335: astore #16
    //   337: aload #9
    //   339: ifnonnull -> 357
    //   342: new java/util/HashSet
    //   345: dup
    //   346: aload #15
    //   348: invokespecial <init> : (Ljava/util/Collection;)V
    //   351: astore #16
    //   353: aload_3
    //   354: ifnull -> 421
    //   357: aload #15
    //   359: invokeinterface iterator : ()Ljava/util/Iterator;
    //   364: astore #17
    //   366: aload #17
    //   368: invokeinterface hasNext : ()Z
    //   373: ifeq -> 421
    //   376: aload #17
    //   378: invokeinterface next : ()Ljava/lang/Object;
    //   383: checkcast java/lang/String
    //   386: astore #18
    //   388: aload #9
    //   390: aload #18
    //   392: invokeinterface contains : (Ljava/lang/Object;)Z
    //   397: ifeq -> 417
    //   400: aload #16
    //   402: aload #18
    //   404: invokeinterface add : (Ljava/lang/Object;)Z
    //   409: pop
    //   410: goto -> 417
    //   413: invokestatic a : (Ljava/lang/Exception;)Ljava/lang/Exception;
    //   416: athrow
    //   417: aload_3
    //   418: ifnull -> 366
    //   421: aload #16
    //   423: astore #9
    //   425: aload_0
    //   426: aload #4
    //   428: aload #7
    //   430: aload #5
    //   432: aload_0
    //   433: aload_1
    //   434: aload_2
    //   435: aload #5
    //   437: invokevirtual Zw : (Lcom/fasterxml/Zor/Zyg;Lcom/fasterxml/Zor/Zo;Lcom/fasterxml/Zor/Zyo;)Lcom/fasterxml/Zo/Zzb;
    //   440: aload #8
    //   442: aload #9
    //   444: invokevirtual ZX : (Lcom/fasterxml/Zor/Zf;Lcom/fasterxml/Zp/Zt;Lcom/fasterxml/Zor/Zyo;Lcom/fasterxml/Zo/Zzb;Ljava/util/Set;Ljava/util/Set;)Lcom/fasterxml/Zs/Zp;
    //   447: invokestatic Zwu : ()[Lburp/Zbqc;
    //   450: ifnonnull -> 467
    //   453: iconst_5
    //   454: anewarray burp/Zbqc
    //   457: invokestatic Zk : ([Lburp/Zbqc;)V
    //   460: goto -> 467
    //   463: invokestatic a : (Ljava/lang/Exception;)Ljava/lang/Exception;
    //   466: athrow
    //   467: areturn
    // Exception table:
    //   from	to	target	type
    //   29	41	44	com/fasterxml/Zor/Zy_
    //   208	223	226	com/fasterxml/Zor/Zy_
    //   218	240	240	com/fasterxml/Zor/Zy_
    //   388	410	413	com/fasterxml/Zor/Zy_
    //   425	460	463	com/fasterxml/Zor/Zy_
  }
  
  public Zyo<Object> Zt() {
    return this.Zh;
  }
  
  public Zzp Zw() {
    return this.ZF;
  }
  
  public boolean Zs() {
    return (this.Zh == null && this.Zq == null && this.ZE == null && this.ZV == null && this.Zc == null);
  }
  
  public Zd Zb() {
    return Zd.Map;
  }
  
  public Map<Object, Object> Zw(Zg paramZg, Zyg paramZyg) throws IOException {
    Map<Object, Object> map;
    try {
      if (this.Zf != null)
        return ZW(paramZg, paramZyg); 
    } catch (IOException iOException) {
      throw a(null);
    } 
    try {
      if (this.Ze != null)
        return (Map<Object, Object>)this.ZF.Zu(paramZyg, this.Ze.deserialize(paramZg, paramZyg)); 
    } catch (IOException iOException) {
      throw a(null);
    } 
    try {
      if (!this.ZP)
        return (Map<Object, Object>)paramZyg.ZV(ZD(), Zw(), paramZg, d(5464, 5062), new Object[0]); 
    } catch (IOException iOException) {
      throw a(null);
    } 
    switch (paramZg.Zy()) {
      case 1:
      case 2:
      case 5:
        map = (Map)this.ZF.Zy(paramZyg);
        try {
          if (this.ZN)
            return Zn(paramZg, paramZyg, map); 
        } catch (IOException iOException) {
          throw a(null);
        } 
        return ZC(paramZg, paramZyg, map);
      case 6:
        return ZD(paramZg, paramZyg);
      case 3:
        return ZF(paramZg, paramZyg);
    } 
    return (Map<Object, Object>)paramZyg.ZE(Zq(paramZyg), paramZg);
  }
  
  public Map<Object, Object> Zf(Zg paramZg, Zyg paramZyg, Map<Object, Object> paramMap) throws IOException {
    paramZg.ZZ(paramMap);
    Zl zl = paramZg.Zh();
    try {
      if (zl != Zl.START_OBJECT)
        try {
          if (zl != Zl.FIELD_NAME)
            return (Map<Object, Object>)paramZyg.ZB(ZD(), paramZg); 
        } catch (IOException iOException) {
          throw a(null);
        }  
    } catch (IOException iOException) {
      throw a(null);
    } 
    try {
      if (this.ZN) {
        Zi(paramZg, paramZyg, paramMap);
        return paramMap;
      } 
    } catch (IOException iOException) {
      throw a(null);
    } 
    ZY(paramZg, paramZyg, paramMap);
    return paramMap;
  }
  
  public Object Zf(Zg paramZg, Zyg paramZyg, Zt paramZt) throws IOException {
    return paramZt.ZC(paramZg, paramZyg);
  }
  
  public final Class<?> ZD() {
    return this.Zp.Zf();
  }
  
  public Zk ZH() {
    return this.Zp;
  }
  
  protected final Map<Object, Object> ZC(Zg paramZg, Zyg paramZyg, Map<Object, Object> paramMap) throws IOException {
    // Byte code:
    //   0: invokestatic Zn : ()[Lburp/Zbqc;
    //   3: aload_0
    //   4: getfield Zq : Lcom/fasterxml/Zor/Zf;
    //   7: astore #5
    //   9: aload_0
    //   10: getfield Zh : Lcom/fasterxml/Zor/Zyo;
    //   13: astore #6
    //   15: aload_0
    //   16: getfield ZE : Lcom/fasterxml/Zp/Zt;
    //   19: astore #7
    //   21: aconst_null
    //   22: astore #8
    //   24: astore #4
    //   26: aload #6
    //   28: invokevirtual Zd : ()Lcom/fasterxml/Ze/Zz;
    //   31: ifnull -> 42
    //   34: iconst_1
    //   35: goto -> 43
    //   38: invokestatic a : (Ljava/lang/Exception;)Ljava/lang/Exception;
    //   41: athrow
    //   42: iconst_0
    //   43: istore #9
    //   45: iload #9
    //   47: ifeq -> 70
    //   50: new com/fasterxml/Zs/Zd
    //   53: dup
    //   54: aload_0
    //   55: getfield Zp : Lcom/fasterxml/Zor/Zk;
    //   58: invokevirtual ZB : ()Lcom/fasterxml/Zor/Zk;
    //   61: invokevirtual Zf : ()Ljava/lang/Class;
    //   64: aload_3
    //   65: invokespecial <init> : (Ljava/lang/Class;Ljava/util/Map;)V
    //   68: astore #8
    //   70: aload_1
    //   71: invokevirtual Zp : ()Z
    //   74: ifeq -> 88
    //   77: aload_1
    //   78: invokevirtual ZU : ()Ljava/lang/String;
    //   81: astore #10
    //   83: aload #4
    //   85: ifnull -> 142
    //   88: aload_1
    //   89: invokevirtual Zh : ()Lcom/fasterxml/Zb/Zl;
    //   92: astore #11
    //   94: aload #11
    //   96: getstatic com/fasterxml/Zb/Zl.FIELD_NAME : Lcom/fasterxml/Zb/Zl;
    //   99: if_acmpeq -> 136
    //   102: aload #11
    //   104: getstatic com/fasterxml/Zb/Zl.END_OBJECT : Lcom/fasterxml/Zb/Zl;
    //   107: if_acmpne -> 123
    //   110: goto -> 117
    //   113: invokestatic a : (Ljava/lang/Exception;)Ljava/lang/Exception;
    //   116: athrow
    //   117: aload_3
    //   118: areturn
    //   119: invokestatic a : (Ljava/lang/Exception;)Ljava/lang/Exception;
    //   122: athrow
    //   123: aload_2
    //   124: aload_0
    //   125: getstatic com/fasterxml/Zb/Zl.FIELD_NAME : Lcom/fasterxml/Zb/Zl;
    //   128: aconst_null
    //   129: iconst_0
    //   130: anewarray java/lang/Object
    //   133: invokevirtual Zw : (Lcom/fasterxml/Zor/Zyo;Lcom/fasterxml/Zb/Zl;Ljava/lang/String;[Ljava/lang/Object;)V
    //   136: aload_1
    //   137: invokevirtual ZS : ()Ljava/lang/String;
    //   140: astore #10
    //   142: aload #10
    //   144: ifnull -> 385
    //   147: aload #5
    //   149: aload #10
    //   151: aload_2
    //   152: invokevirtual Z_ : (Ljava/lang/String;Lcom/fasterxml/Zor/Zyg;)Ljava/lang/Object;
    //   155: astore #11
    //   157: aload_1
    //   158: invokevirtual ZV : ()Lcom/fasterxml/Zb/Zl;
    //   161: astore #12
    //   163: aload_0
    //   164: getfield Zs : Lcom/fasterxml/Zm/Zk;
    //   167: ifnull -> 206
    //   170: aload_0
    //   171: getfield Zs : Lcom/fasterxml/Zm/Zk;
    //   174: aload #10
    //   176: invokevirtual Zv : (Ljava/lang/Object;)Z
    //   179: ifeq -> 206
    //   182: goto -> 189
    //   185: invokestatic a : (Ljava/lang/Exception;)Ljava/lang/Exception;
    //   188: athrow
    //   189: aload_1
    //   190: invokevirtual Zc : ()Lcom/fasterxml/Zb/Zg;
    //   193: pop
    //   194: aload #4
    //   196: ifnull -> 374
    //   199: goto -> 206
    //   202: invokestatic a : (Ljava/lang/Exception;)Ljava/lang/Exception;
    //   205: athrow
    //   206: aload #12
    //   208: getstatic com/fasterxml/Zb/Zl.VALUE_NULL : Lcom/fasterxml/Zb/Zl;
    //   211: if_acmpne -> 243
    //   214: aload_0
    //   215: getfield ZM : Z
    //   218: ifeq -> 226
    //   221: aload #4
    //   223: ifnull -> 374
    //   226: aload_0
    //   227: getfield ZQ : Lcom/fasterxml/Zo/Zzb;
    //   230: aload_2
    //   231: invokeinterface Zj : (Lcom/fasterxml/Zor/Zyg;)Ljava/lang/Object;
    //   236: astore #13
    //   238: aload #4
    //   240: ifnull -> 280
    //   243: aload #7
    //   245: ifnonnull -> 269
    //   248: goto -> 255
    //   251: invokestatic a : (Ljava/lang/Exception;)Ljava/lang/Exception;
    //   254: athrow
    //   255: aload #6
    //   257: aload_1
    //   258: aload_2
    //   259: invokevirtual deserialize : (Lcom/fasterxml/Zb/Zg;Lcom/fasterxml/Zor/Zyg;)Ljava/lang/Object;
    //   262: astore #13
    //   264: aload #4
    //   266: ifnull -> 280
    //   269: aload #6
    //   271: aload_1
    //   272: aload_2
    //   273: aload #7
    //   275: invokevirtual Zf : (Lcom/fasterxml/Zb/Zg;Lcom/fasterxml/Zor/Zyg;Lcom/fasterxml/Zp/Zt;)Ljava/lang/Object;
    //   278: astore #13
    //   280: iload #9
    //   282: ifeq -> 306
    //   285: aload #8
    //   287: aload #11
    //   289: aload #13
    //   291: invokevirtual ZY : (Ljava/lang/Object;Ljava/lang/Object;)V
    //   294: aload #4
    //   296: ifnull -> 342
    //   299: goto -> 306
    //   302: invokestatic a : (Ljava/lang/Exception;)Ljava/lang/Exception;
    //   305: athrow
    //   306: aload_3
    //   307: aload #11
    //   309: aload #13
    //   311: invokeinterface put : (Ljava/lang/Object;Ljava/lang/Object;)Ljava/lang/Object;
    //   316: astore #14
    //   318: aload #14
    //   320: ifnull -> 342
    //   323: aload_0
    //   324: aload_2
    //   325: aload_3
    //   326: aload #11
    //   328: aload #14
    //   330: aload #13
    //   332: invokevirtual ZR : (Lcom/fasterxml/Zor/Zyg;Ljava/util/Map;Ljava/lang/Object;Ljava/lang/Object;Ljava/lang/Object;)V
    //   335: goto -> 342
    //   338: invokestatic a : (Ljava/lang/Exception;)Ljava/lang/Exception;
    //   341: athrow
    //   342: goto -> 374
    //   345: astore #13
    //   347: aload_0
    //   348: aload_2
    //   349: aload #8
    //   351: aload #11
    //   353: aload #13
    //   355: invokespecial Zp : (Lcom/fasterxml/Zor/Zyg;Lcom/fasterxml/Zs/Zd;Ljava/lang/Object;Lcom/fasterxml/Zo/Zz7;)V
    //   358: goto -> 374
    //   361: astore #13
    //   363: aload_0
    //   364: aload_2
    //   365: aload #13
    //   367: aload_3
    //   368: aload #10
    //   370: invokevirtual ZL : (Lcom/fasterxml/Zor/Zyg;Ljava/lang/Throwable;Ljava/lang/Object;Ljava/lang/String;)Ljava/lang/Object;
    //   373: pop
    //   374: aload_1
    //   375: invokevirtual ZU : ()Ljava/lang/String;
    //   378: astore #10
    //   380: aload #4
    //   382: ifnull -> 142
    //   385: aload_3
    //   386: areturn
    // Exception table:
    //   from	to	target	type
    //   26	38	38	com/fasterxml/Zo/Zz7
    //   94	110	113	com/fasterxml/Zo/Zz7
    //   102	119	119	com/fasterxml/Zo/Zz7
    //   163	182	185	com/fasterxml/Zo/Zz7
    //   170	199	202	com/fasterxml/Zo/Zz7
    //   206	221	345	com/fasterxml/Zo/Zz7
    //   206	221	361	java/lang/Exception
    //   226	342	345	com/fasterxml/Zo/Zz7
    //   226	342	361	java/lang/Exception
    //   238	248	251	com/fasterxml/Zo/Zz7
    //   280	299	302	com/fasterxml/Zo/Zz7
    //   318	335	338	com/fasterxml/Zo/Zz7
  }
  
  protected final Map<Object, Object> Zn(Zg paramZg, Zyg paramZyg, Map<Object, Object> paramMap) throws IOException {
    // Byte code:
    //   0: aload_0
    //   1: getfield Zh : Lcom/fasterxml/Zor/Zyo;
    //   4: astore #5
    //   6: aload_0
    //   7: getfield ZE : Lcom/fasterxml/Zp/Zt;
    //   10: astore #6
    //   12: invokestatic Zn : ()[Lburp/Zbqc;
    //   15: aconst_null
    //   16: astore #7
    //   18: astore #4
    //   20: aload #5
    //   22: invokevirtual Zd : ()Lcom/fasterxml/Ze/Zz;
    //   25: ifnull -> 36
    //   28: iconst_1
    //   29: goto -> 37
    //   32: invokestatic a : (Ljava/lang/Exception;)Ljava/lang/Exception;
    //   35: athrow
    //   36: iconst_0
    //   37: istore #8
    //   39: iload #8
    //   41: ifeq -> 64
    //   44: new com/fasterxml/Zs/Zd
    //   47: dup
    //   48: aload_0
    //   49: getfield Zp : Lcom/fasterxml/Zor/Zk;
    //   52: invokevirtual ZB : ()Lcom/fasterxml/Zor/Zk;
    //   55: invokevirtual Zf : ()Ljava/lang/Class;
    //   58: aload_3
    //   59: invokespecial <init> : (Ljava/lang/Class;Ljava/util/Map;)V
    //   62: astore #7
    //   64: aload_1
    //   65: invokevirtual Zp : ()Z
    //   68: ifeq -> 82
    //   71: aload_1
    //   72: invokevirtual ZU : ()Ljava/lang/String;
    //   75: astore #9
    //   77: aload #4
    //   79: ifnull -> 136
    //   82: aload_1
    //   83: invokevirtual Zh : ()Lcom/fasterxml/Zb/Zl;
    //   86: astore #10
    //   88: aload #10
    //   90: getstatic com/fasterxml/Zb/Zl.END_OBJECT : Lcom/fasterxml/Zb/Zl;
    //   93: if_acmpne -> 102
    //   96: aload_3
    //   97: areturn
    //   98: invokestatic a : (Ljava/lang/Exception;)Ljava/lang/Exception;
    //   101: athrow
    //   102: aload #10
    //   104: getstatic com/fasterxml/Zb/Zl.FIELD_NAME : Lcom/fasterxml/Zb/Zl;
    //   107: if_acmpeq -> 130
    //   110: aload_2
    //   111: aload_0
    //   112: getstatic com/fasterxml/Zb/Zl.FIELD_NAME : Lcom/fasterxml/Zb/Zl;
    //   115: aconst_null
    //   116: iconst_0
    //   117: anewarray java/lang/Object
    //   120: invokevirtual Zw : (Lcom/fasterxml/Zor/Zyo;Lcom/fasterxml/Zb/Zl;Ljava/lang/String;[Ljava/lang/Object;)V
    //   123: goto -> 130
    //   126: invokestatic a : (Ljava/lang/Exception;)Ljava/lang/Exception;
    //   129: athrow
    //   130: aload_1
    //   131: invokevirtual ZS : ()Ljava/lang/String;
    //   134: astore #9
    //   136: aload #9
    //   138: ifnull -> 369
    //   141: aload_1
    //   142: invokevirtual ZV : ()Lcom/fasterxml/Zb/Zl;
    //   145: astore #10
    //   147: aload_0
    //   148: getfield Zs : Lcom/fasterxml/Zm/Zk;
    //   151: ifnull -> 190
    //   154: aload_0
    //   155: getfield Zs : Lcom/fasterxml/Zm/Zk;
    //   158: aload #9
    //   160: invokevirtual Zv : (Ljava/lang/Object;)Z
    //   163: ifeq -> 190
    //   166: goto -> 173
    //   169: invokestatic a : (Ljava/lang/Exception;)Ljava/lang/Exception;
    //   172: athrow
    //   173: aload_1
    //   174: invokevirtual Zc : ()Lcom/fasterxml/Zb/Zg;
    //   177: pop
    //   178: aload #4
    //   180: ifnull -> 358
    //   183: goto -> 190
    //   186: invokestatic a : (Ljava/lang/Exception;)Ljava/lang/Exception;
    //   189: athrow
    //   190: aload #10
    //   192: getstatic com/fasterxml/Zb/Zl.VALUE_NULL : Lcom/fasterxml/Zb/Zl;
    //   195: if_acmpne -> 227
    //   198: aload_0
    //   199: getfield ZM : Z
    //   202: ifeq -> 210
    //   205: aload #4
    //   207: ifnull -> 358
    //   210: aload_0
    //   211: getfield ZQ : Lcom/fasterxml/Zo/Zzb;
    //   214: aload_2
    //   215: invokeinterface Zj : (Lcom/fasterxml/Zor/Zyg;)Ljava/lang/Object;
    //   220: astore #11
    //   222: aload #4
    //   224: ifnull -> 264
    //   227: aload #6
    //   229: ifnonnull -> 253
    //   232: goto -> 239
    //   235: invokestatic a : (Ljava/lang/Exception;)Ljava/lang/Exception;
    //   238: athrow
    //   239: aload #5
    //   241: aload_1
    //   242: aload_2
    //   243: invokevirtual deserialize : (Lcom/fasterxml/Zb/Zg;Lcom/fasterxml/Zor/Zyg;)Ljava/lang/Object;
    //   246: astore #11
    //   248: aload #4
    //   250: ifnull -> 264
    //   253: aload #5
    //   255: aload_1
    //   256: aload_2
    //   257: aload #6
    //   259: invokevirtual Zf : (Lcom/fasterxml/Zb/Zg;Lcom/fasterxml/Zor/Zyg;Lcom/fasterxml/Zp/Zt;)Ljava/lang/Object;
    //   262: astore #11
    //   264: iload #8
    //   266: ifeq -> 290
    //   269: aload #7
    //   271: aload #9
    //   273: aload #11
    //   275: invokevirtual ZY : (Ljava/lang/Object;Ljava/lang/Object;)V
    //   278: aload #4
    //   280: ifnull -> 326
    //   283: goto -> 290
    //   286: invokestatic a : (Ljava/lang/Exception;)Ljava/lang/Exception;
    //   289: athrow
    //   290: aload_3
    //   291: aload #9
    //   293: aload #11
    //   295: invokeinterface put : (Ljava/lang/Object;Ljava/lang/Object;)Ljava/lang/Object;
    //   300: astore #12
    //   302: aload #12
    //   304: ifnull -> 326
    //   307: aload_0
    //   308: aload_2
    //   309: aload_3
    //   310: aload #9
    //   312: aload #12
    //   314: aload #11
    //   316: invokevirtual ZR : (Lcom/fasterxml/Zor/Zyg;Ljava/util/Map;Ljava/lang/Object;Ljava/lang/Object;Ljava/lang/Object;)V
    //   319: goto -> 326
    //   322: invokestatic a : (Ljava/lang/Exception;)Ljava/lang/Exception;
    //   325: athrow
    //   326: goto -> 358
    //   329: astore #11
    //   331: aload_0
    //   332: aload_2
    //   333: aload #7
    //   335: aload #9
    //   337: aload #11
    //   339: invokespecial Zp : (Lcom/fasterxml/Zor/Zyg;Lcom/fasterxml/Zs/Zd;Ljava/lang/Object;Lcom/fasterxml/Zo/Zz7;)V
    //   342: goto -> 358
    //   345: astore #11
    //   347: aload_0
    //   348: aload_2
    //   349: aload #11
    //   351: aload_3
    //   352: aload #9
    //   354: invokevirtual ZL : (Lcom/fasterxml/Zor/Zyg;Ljava/lang/Throwable;Ljava/lang/Object;Ljava/lang/String;)Ljava/lang/Object;
    //   357: pop
    //   358: aload_1
    //   359: invokevirtual ZU : ()Ljava/lang/String;
    //   362: astore #9
    //   364: aload #4
    //   366: ifnull -> 136
    //   369: aload_3
    //   370: areturn
    // Exception table:
    //   from	to	target	type
    //   20	32	32	com/fasterxml/Zo/Zz7
    //   88	98	98	com/fasterxml/Zo/Zz7
    //   102	123	126	com/fasterxml/Zo/Zz7
    //   147	166	169	com/fasterxml/Zo/Zz7
    //   154	183	186	com/fasterxml/Zo/Zz7
    //   190	205	329	com/fasterxml/Zo/Zz7
    //   190	205	345	java/lang/Exception
    //   210	326	329	com/fasterxml/Zo/Zz7
    //   210	326	345	java/lang/Exception
    //   222	232	235	com/fasterxml/Zo/Zz7
    //   264	283	286	com/fasterxml/Zo/Zz7
    //   302	319	322	com/fasterxml/Zo/Zz7
  }
  
  public Map<Object, Object> ZW(Zg paramZg, Zyg paramZyg) throws IOException {
    // Byte code:
    //   0: invokestatic Zn : ()[Lburp/Zbqc;
    //   3: aload_0
    //   4: getfield Zf : Lcom/fasterxml/Ze/Zc;
    //   7: astore #4
    //   9: aload #4
    //   11: aload_1
    //   12: aload_2
    //   13: aconst_null
    //   14: invokevirtual Zn : (Lcom/fasterxml/Zb/Zg;Lcom/fasterxml/Zor/Zyg;Lcom/fasterxml/Ze/Zz;)Lcom/fasterxml/Ze/Zok;
    //   17: astore #5
    //   19: astore_3
    //   20: aload_0
    //   21: getfield Zh : Lcom/fasterxml/Zor/Zyo;
    //   24: astore #6
    //   26: aload_0
    //   27: getfield ZE : Lcom/fasterxml/Zp/Zt;
    //   30: astore #7
    //   32: aload_1
    //   33: invokevirtual Zp : ()Z
    //   36: ifeq -> 49
    //   39: aload_1
    //   40: invokevirtual ZU : ()Ljava/lang/String;
    //   43: astore #8
    //   45: aload_3
    //   46: ifnull -> 79
    //   49: aload_1
    //   50: getstatic com/fasterxml/Zb/Zl.FIELD_NAME : Lcom/fasterxml/Zb/Zl;
    //   53: invokevirtual ZL : (Lcom/fasterxml/Zb/Zl;)Z
    //   56: ifeq -> 76
    //   59: goto -> 66
    //   62: invokestatic a : (Ljava/lang/Exception;)Ljava/lang/Exception;
    //   65: athrow
    //   66: aload_1
    //   67: invokevirtual ZS : ()Ljava/lang/String;
    //   70: astore #8
    //   72: aload_3
    //   73: ifnull -> 79
    //   76: aconst_null
    //   77: astore #8
    //   79: aload #8
    //   81: ifnull -> 348
    //   84: aload_1
    //   85: invokevirtual ZV : ()Lcom/fasterxml/Zb/Zl;
    //   88: astore #9
    //   90: aload_0
    //   91: getfield Zs : Lcom/fasterxml/Zm/Zk;
    //   94: ifnull -> 132
    //   97: aload_0
    //   98: getfield Zs : Lcom/fasterxml/Zm/Zk;
    //   101: aload #8
    //   103: invokevirtual Zv : (Ljava/lang/Object;)Z
    //   106: ifeq -> 132
    //   109: goto -> 116
    //   112: invokestatic a : (Ljava/lang/Exception;)Ljava/lang/Exception;
    //   115: athrow
    //   116: aload_1
    //   117: invokevirtual Zc : ()Lcom/fasterxml/Zb/Zg;
    //   120: pop
    //   121: aload_3
    //   122: ifnull -> 338
    //   125: goto -> 132
    //   128: invokestatic a : (Ljava/lang/Exception;)Ljava/lang/Exception;
    //   131: athrow
    //   132: aload #4
    //   134: aload #8
    //   136: invokevirtual ZO : (Ljava/lang/String;)Lcom/fasterxml/Zo/Zv;
    //   139: astore #10
    //   141: aload #10
    //   143: ifnull -> 222
    //   146: aload #5
    //   148: aload #10
    //   150: aload #10
    //   152: aload_1
    //   153: aload_2
    //   154: invokevirtual Zt : (Lcom/fasterxml/Zb/Zg;Lcom/fasterxml/Zor/Zyg;)Ljava/lang/Object;
    //   157: invokevirtual Zr : (Lcom/fasterxml/Zo/Zv;Ljava/lang/Object;)Z
    //   160: ifeq -> 338
    //   163: goto -> 170
    //   166: invokestatic a : (Ljava/lang/Exception;)Ljava/lang/Exception;
    //   169: athrow
    //   170: aload_1
    //   171: invokevirtual ZV : ()Lcom/fasterxml/Zb/Zl;
    //   174: pop
    //   175: aload #4
    //   177: aload_2
    //   178: aload #5
    //   180: invokevirtual ZP : (Lcom/fasterxml/Zor/Zyg;Lcom/fasterxml/Ze/Zok;)Ljava/lang/Object;
    //   183: checkcast java/util/Map
    //   186: astore #11
    //   188: goto -> 213
    //   191: astore #12
    //   193: aload_0
    //   194: aload_2
    //   195: aload #12
    //   197: aload_0
    //   198: getfield Zp : Lcom/fasterxml/Zor/Zk;
    //   201: invokevirtual Zf : ()Ljava/lang/Class;
    //   204: aload #8
    //   206: invokevirtual ZL : (Lcom/fasterxml/Zor/Zyg;Ljava/lang/Throwable;Ljava/lang/Object;Ljava/lang/String;)Ljava/lang/Object;
    //   209: checkcast java/util/Map
    //   212: areturn
    //   213: aload_0
    //   214: aload_1
    //   215: aload_2
    //   216: aload #11
    //   218: invokevirtual ZC : (Lcom/fasterxml/Zb/Zg;Lcom/fasterxml/Zor/Zyg;Ljava/util/Map;)Ljava/util/Map;
    //   221: areturn
    //   222: aload_0
    //   223: getfield Zq : Lcom/fasterxml/Zor/Zf;
    //   226: aload #8
    //   228: aload_2
    //   229: invokevirtual Z_ : (Ljava/lang/String;Lcom/fasterxml/Zor/Zyg;)Ljava/lang/Object;
    //   232: astore #11
    //   234: aload #9
    //   236: getstatic com/fasterxml/Zb/Zl.VALUE_NULL : Lcom/fasterxml/Zb/Zl;
    //   239: if_acmpne -> 269
    //   242: aload_0
    //   243: getfield ZM : Z
    //   246: ifeq -> 253
    //   249: aload_3
    //   250: ifnull -> 338
    //   253: aload_0
    //   254: getfield ZQ : Lcom/fasterxml/Zo/Zzb;
    //   257: aload_2
    //   258: invokeinterface Zj : (Lcom/fasterxml/Zor/Zyg;)Ljava/lang/Object;
    //   263: astore #12
    //   265: aload_3
    //   266: ifnull -> 305
    //   269: aload #7
    //   271: ifnonnull -> 294
    //   274: goto -> 281
    //   277: invokestatic a : (Ljava/lang/Exception;)Ljava/lang/Exception;
    //   280: athrow
    //   281: aload #6
    //   283: aload_1
    //   284: aload_2
    //   285: invokevirtual deserialize : (Lcom/fasterxml/Zb/Zg;Lcom/fasterxml/Zor/Zyg;)Ljava/lang/Object;
    //   288: astore #12
    //   290: aload_3
    //   291: ifnull -> 305
    //   294: aload #6
    //   296: aload_1
    //   297: aload_2
    //   298: aload #7
    //   300: invokevirtual Zf : (Lcom/fasterxml/Zb/Zg;Lcom/fasterxml/Zor/Zyg;Lcom/fasterxml/Zp/Zt;)Ljava/lang/Object;
    //   303: astore #12
    //   305: goto -> 329
    //   308: astore #13
    //   310: aload_0
    //   311: aload_2
    //   312: aload #13
    //   314: aload_0
    //   315: getfield Zp : Lcom/fasterxml/Zor/Zk;
    //   318: invokevirtual Zf : ()Ljava/lang/Class;
    //   321: aload #8
    //   323: invokevirtual ZL : (Lcom/fasterxml/Zor/Zyg;Ljava/lang/Throwable;Ljava/lang/Object;Ljava/lang/String;)Ljava/lang/Object;
    //   326: pop
    //   327: aconst_null
    //   328: areturn
    //   329: aload #5
    //   331: aload #11
    //   333: aload #12
    //   335: invokevirtual ZM : (Ljava/lang/Object;Ljava/lang/Object;)V
    //   338: aload_1
    //   339: invokevirtual ZU : ()Ljava/lang/String;
    //   342: astore #8
    //   344: aload_3
    //   345: ifnull -> 79
    //   348: aload #4
    //   350: aload_2
    //   351: aload #5
    //   353: invokevirtual ZP : (Lcom/fasterxml/Zor/Zyg;Lcom/fasterxml/Ze/Zok;)Ljava/lang/Object;
    //   356: checkcast java/util/Map
    //   359: areturn
    //   360: astore #9
    //   362: aload_0
    //   363: aload_2
    //   364: aload #9
    //   366: aload_0
    //   367: getfield Zp : Lcom/fasterxml/Zor/Zk;
    //   370: invokevirtual Zf : ()Ljava/lang/Class;
    //   373: aload #8
    //   375: invokevirtual ZL : (Lcom/fasterxml/Zor/Zyg;Ljava/lang/Throwable;Ljava/lang/Object;Ljava/lang/String;)Ljava/lang/Object;
    //   378: pop
    //   379: aconst_null
    //   380: areturn
    // Exception table:
    //   from	to	target	type
    //   45	59	62	java/lang/Exception
    //   90	109	112	java/lang/Exception
    //   97	125	128	java/lang/Exception
    //   141	163	166	java/lang/Exception
    //   175	188	191	java/lang/Exception
    //   234	249	308	java/lang/Exception
    //   253	305	308	java/lang/Exception
    //   265	274	277	java/lang/Exception
    //   348	359	360	java/lang/Exception
  }
  
  protected final void ZY(Zg paramZg, Zyg paramZyg, Map<Object, Object> paramMap) throws IOException {
    // Byte code:
    //   0: invokestatic Zn : ()[Lburp/Zbqc;
    //   3: aload_0
    //   4: getfield Zq : Lcom/fasterxml/Zor/Zf;
    //   7: astore #5
    //   9: astore #4
    //   11: aload_0
    //   12: getfield Zh : Lcom/fasterxml/Zor/Zyo;
    //   15: astore #6
    //   17: aload_0
    //   18: getfield ZE : Lcom/fasterxml/Zp/Zt;
    //   21: astore #7
    //   23: aload_1
    //   24: invokevirtual Zp : ()Z
    //   27: ifeq -> 41
    //   30: aload_1
    //   31: invokevirtual ZU : ()Ljava/lang/String;
    //   34: astore #8
    //   36: aload #4
    //   38: ifnull -> 94
    //   41: aload_1
    //   42: invokevirtual Zh : ()Lcom/fasterxml/Zb/Zl;
    //   45: astore #9
    //   47: aload #9
    //   49: getstatic com/fasterxml/Zb/Zl.END_OBJECT : Lcom/fasterxml/Zb/Zl;
    //   52: if_acmpne -> 60
    //   55: return
    //   56: invokestatic a : (Ljava/lang/Exception;)Ljava/lang/Exception;
    //   59: athrow
    //   60: aload #9
    //   62: getstatic com/fasterxml/Zb/Zl.FIELD_NAME : Lcom/fasterxml/Zb/Zl;
    //   65: if_acmpeq -> 88
    //   68: aload_2
    //   69: aload_0
    //   70: getstatic com/fasterxml/Zb/Zl.FIELD_NAME : Lcom/fasterxml/Zb/Zl;
    //   73: aconst_null
    //   74: iconst_0
    //   75: anewarray java/lang/Object
    //   78: invokevirtual Zw : (Lcom/fasterxml/Zor/Zyo;Lcom/fasterxml/Zb/Zl;Ljava/lang/String;[Ljava/lang/Object;)V
    //   81: goto -> 88
    //   84: invokestatic a : (Ljava/lang/Exception;)Ljava/lang/Exception;
    //   87: athrow
    //   88: aload_1
    //   89: invokevirtual ZS : ()Ljava/lang/String;
    //   92: astore #8
    //   94: aload #8
    //   96: ifnull -> 352
    //   99: aload #5
    //   101: aload #8
    //   103: aload_2
    //   104: invokevirtual Z_ : (Ljava/lang/String;Lcom/fasterxml/Zor/Zyg;)Ljava/lang/Object;
    //   107: astore #9
    //   109: aload_1
    //   110: invokevirtual ZV : ()Lcom/fasterxml/Zb/Zl;
    //   113: astore #10
    //   115: aload_0
    //   116: getfield Zs : Lcom/fasterxml/Zm/Zk;
    //   119: ifnull -> 158
    //   122: aload_0
    //   123: getfield Zs : Lcom/fasterxml/Zm/Zk;
    //   126: aload #8
    //   128: invokevirtual Zv : (Ljava/lang/Object;)Z
    //   131: ifeq -> 158
    //   134: goto -> 141
    //   137: invokestatic a : (Ljava/lang/Exception;)Ljava/lang/Exception;
    //   140: athrow
    //   141: aload_1
    //   142: invokevirtual Zc : ()Lcom/fasterxml/Zb/Zg;
    //   145: pop
    //   146: aload #4
    //   148: ifnull -> 341
    //   151: goto -> 158
    //   154: invokestatic a : (Ljava/lang/Exception;)Ljava/lang/Exception;
    //   157: athrow
    //   158: aload #10
    //   160: getstatic com/fasterxml/Zb/Zl.VALUE_NULL : Lcom/fasterxml/Zb/Zl;
    //   163: if_acmpne -> 202
    //   166: aload_0
    //   167: getfield ZM : Z
    //   170: ifeq -> 178
    //   173: aload #4
    //   175: ifnull -> 341
    //   178: aload_3
    //   179: aload #9
    //   181: aload_0
    //   182: getfield ZQ : Lcom/fasterxml/Zo/Zzb;
    //   185: aload_2
    //   186: invokeinterface Zj : (Lcom/fasterxml/Zor/Zyg;)Ljava/lang/Object;
    //   191: invokeinterface put : (Ljava/lang/Object;Ljava/lang/Object;)Ljava/lang/Object;
    //   196: pop
    //   197: aload #4
    //   199: ifnull -> 341
    //   202: aload_3
    //   203: aload #9
    //   205: invokeinterface get : (Ljava/lang/Object;)Ljava/lang/Object;
    //   210: astore #11
    //   212: aload #11
    //   214: ifnull -> 263
    //   217: aload #7
    //   219: ifnonnull -> 245
    //   222: goto -> 229
    //   225: invokestatic a : (Ljava/lang/Exception;)Ljava/lang/Exception;
    //   228: athrow
    //   229: aload #6
    //   231: aload_1
    //   232: aload_2
    //   233: aload #11
    //   235: invokevirtual ZI : (Lcom/fasterxml/Zb/Zg;Lcom/fasterxml/Zor/Zyg;Ljava/lang/Object;)Ljava/lang/Object;
    //   238: astore #12
    //   240: aload #4
    //   242: ifnull -> 300
    //   245: aload #6
    //   247: aload_1
    //   248: aload_2
    //   249: aload #7
    //   251: aload #11
    //   253: invokevirtual ZY : (Lcom/fasterxml/Zb/Zg;Lcom/fasterxml/Zor/Zyg;Lcom/fasterxml/Zp/Zt;Ljava/lang/Object;)Ljava/lang/Object;
    //   256: astore #12
    //   258: aload #4
    //   260: ifnull -> 300
    //   263: aload #7
    //   265: ifnonnull -> 289
    //   268: goto -> 275
    //   271: invokestatic a : (Ljava/lang/Exception;)Ljava/lang/Exception;
    //   274: athrow
    //   275: aload #6
    //   277: aload_1
    //   278: aload_2
    //   279: invokevirtual deserialize : (Lcom/fasterxml/Zb/Zg;Lcom/fasterxml/Zor/Zyg;)Ljava/lang/Object;
    //   282: astore #12
    //   284: aload #4
    //   286: ifnull -> 300
    //   289: aload #6
    //   291: aload_1
    //   292: aload_2
    //   293: aload #7
    //   295: invokevirtual Zf : (Lcom/fasterxml/Zb/Zg;Lcom/fasterxml/Zor/Zyg;Lcom/fasterxml/Zp/Zt;)Ljava/lang/Object;
    //   298: astore #12
    //   300: aload #12
    //   302: aload #11
    //   304: if_acmpeq -> 325
    //   307: aload_3
    //   308: aload #9
    //   310: aload #12
    //   312: invokeinterface put : (Ljava/lang/Object;Ljava/lang/Object;)Ljava/lang/Object;
    //   317: pop
    //   318: goto -> 325
    //   321: invokestatic a : (Ljava/lang/Exception;)Ljava/lang/Exception;
    //   324: athrow
    //   325: goto -> 341
    //   328: astore #11
    //   330: aload_0
    //   331: aload_2
    //   332: aload #11
    //   334: aload_3
    //   335: aload #8
    //   337: invokevirtual ZL : (Lcom/fasterxml/Zor/Zyg;Ljava/lang/Throwable;Ljava/lang/Object;Ljava/lang/String;)Ljava/lang/Object;
    //   340: pop
    //   341: aload_1
    //   342: invokevirtual ZU : ()Ljava/lang/String;
    //   345: astore #8
    //   347: aload #4
    //   349: ifnull -> 94
    //   352: return
    // Exception table:
    //   from	to	target	type
    //   47	56	56	java/lang/Exception
    //   60	81	84	java/lang/Exception
    //   115	134	137	java/lang/Exception
    //   122	151	154	java/lang/Exception
    //   158	173	328	java/lang/Exception
    //   178	197	328	java/lang/Exception
    //   202	325	328	java/lang/Exception
    //   212	222	225	java/lang/Exception
    //   258	268	271	java/lang/Exception
    //   300	318	321	java/lang/Exception
  }
  
  protected final void Zi(Zg paramZg, Zyg paramZyg, Map<Object, Object> paramMap) throws IOException {
    // Byte code:
    //   0: invokestatic Zn : ()[Lburp/Zbqc;
    //   3: aload_0
    //   4: getfield Zh : Lcom/fasterxml/Zor/Zyo;
    //   7: astore #5
    //   9: aload_0
    //   10: getfield ZE : Lcom/fasterxml/Zp/Zt;
    //   13: astore #6
    //   15: astore #4
    //   17: aload_1
    //   18: invokevirtual Zp : ()Z
    //   21: ifeq -> 35
    //   24: aload_1
    //   25: invokevirtual ZU : ()Ljava/lang/String;
    //   28: astore #7
    //   30: aload #4
    //   32: ifnull -> 88
    //   35: aload_1
    //   36: invokevirtual Zh : ()Lcom/fasterxml/Zb/Zl;
    //   39: astore #8
    //   41: aload #8
    //   43: getstatic com/fasterxml/Zb/Zl.END_OBJECT : Lcom/fasterxml/Zb/Zl;
    //   46: if_acmpne -> 54
    //   49: return
    //   50: invokestatic a : (Ljava/lang/Exception;)Ljava/lang/Exception;
    //   53: athrow
    //   54: aload #8
    //   56: getstatic com/fasterxml/Zb/Zl.FIELD_NAME : Lcom/fasterxml/Zb/Zl;
    //   59: if_acmpeq -> 82
    //   62: aload_2
    //   63: aload_0
    //   64: getstatic com/fasterxml/Zb/Zl.FIELD_NAME : Lcom/fasterxml/Zb/Zl;
    //   67: aconst_null
    //   68: iconst_0
    //   69: anewarray java/lang/Object
    //   72: invokevirtual Zw : (Lcom/fasterxml/Zor/Zyo;Lcom/fasterxml/Zb/Zl;Ljava/lang/String;[Ljava/lang/Object;)V
    //   75: goto -> 82
    //   78: invokestatic a : (Ljava/lang/Exception;)Ljava/lang/Exception;
    //   81: athrow
    //   82: aload_1
    //   83: invokevirtual ZS : ()Ljava/lang/String;
    //   86: astore #7
    //   88: aload #7
    //   90: ifnull -> 336
    //   93: aload_1
    //   94: invokevirtual ZV : ()Lcom/fasterxml/Zb/Zl;
    //   97: astore #8
    //   99: aload_0
    //   100: getfield Zs : Lcom/fasterxml/Zm/Zk;
    //   103: ifnull -> 142
    //   106: aload_0
    //   107: getfield Zs : Lcom/fasterxml/Zm/Zk;
    //   110: aload #7
    //   112: invokevirtual Zv : (Ljava/lang/Object;)Z
    //   115: ifeq -> 142
    //   118: goto -> 125
    //   121: invokestatic a : (Ljava/lang/Exception;)Ljava/lang/Exception;
    //   124: athrow
    //   125: aload_1
    //   126: invokevirtual Zc : ()Lcom/fasterxml/Zb/Zg;
    //   129: pop
    //   130: aload #4
    //   132: ifnull -> 325
    //   135: goto -> 142
    //   138: invokestatic a : (Ljava/lang/Exception;)Ljava/lang/Exception;
    //   141: athrow
    //   142: aload #8
    //   144: getstatic com/fasterxml/Zb/Zl.VALUE_NULL : Lcom/fasterxml/Zb/Zl;
    //   147: if_acmpne -> 186
    //   150: aload_0
    //   151: getfield ZM : Z
    //   154: ifeq -> 162
    //   157: aload #4
    //   159: ifnull -> 325
    //   162: aload_3
    //   163: aload #7
    //   165: aload_0
    //   166: getfield ZQ : Lcom/fasterxml/Zo/Zzb;
    //   169: aload_2
    //   170: invokeinterface Zj : (Lcom/fasterxml/Zor/Zyg;)Ljava/lang/Object;
    //   175: invokeinterface put : (Ljava/lang/Object;Ljava/lang/Object;)Ljava/lang/Object;
    //   180: pop
    //   181: aload #4
    //   183: ifnull -> 325
    //   186: aload_3
    //   187: aload #7
    //   189: invokeinterface get : (Ljava/lang/Object;)Ljava/lang/Object;
    //   194: astore #9
    //   196: aload #9
    //   198: ifnull -> 247
    //   201: aload #6
    //   203: ifnonnull -> 229
    //   206: goto -> 213
    //   209: invokestatic a : (Ljava/lang/Exception;)Ljava/lang/Exception;
    //   212: athrow
    //   213: aload #5
    //   215: aload_1
    //   216: aload_2
    //   217: aload #9
    //   219: invokevirtual ZI : (Lcom/fasterxml/Zb/Zg;Lcom/fasterxml/Zor/Zyg;Ljava/lang/Object;)Ljava/lang/Object;
    //   222: astore #10
    //   224: aload #4
    //   226: ifnull -> 284
    //   229: aload #5
    //   231: aload_1
    //   232: aload_2
    //   233: aload #6
    //   235: aload #9
    //   237: invokevirtual ZY : (Lcom/fasterxml/Zb/Zg;Lcom/fasterxml/Zor/Zyg;Lcom/fasterxml/Zp/Zt;Ljava/lang/Object;)Ljava/lang/Object;
    //   240: astore #10
    //   242: aload #4
    //   244: ifnull -> 284
    //   247: aload #6
    //   249: ifnonnull -> 273
    //   252: goto -> 259
    //   255: invokestatic a : (Ljava/lang/Exception;)Ljava/lang/Exception;
    //   258: athrow
    //   259: aload #5
    //   261: aload_1
    //   262: aload_2
    //   263: invokevirtual deserialize : (Lcom/fasterxml/Zb/Zg;Lcom/fasterxml/Zor/Zyg;)Ljava/lang/Object;
    //   266: astore #10
    //   268: aload #4
    //   270: ifnull -> 284
    //   273: aload #5
    //   275: aload_1
    //   276: aload_2
    //   277: aload #6
    //   279: invokevirtual Zf : (Lcom/fasterxml/Zb/Zg;Lcom/fasterxml/Zor/Zyg;Lcom/fasterxml/Zp/Zt;)Ljava/lang/Object;
    //   282: astore #10
    //   284: aload #10
    //   286: aload #9
    //   288: if_acmpeq -> 309
    //   291: aload_3
    //   292: aload #7
    //   294: aload #10
    //   296: invokeinterface put : (Ljava/lang/Object;Ljava/lang/Object;)Ljava/lang/Object;
    //   301: pop
    //   302: goto -> 309
    //   305: invokestatic a : (Ljava/lang/Exception;)Ljava/lang/Exception;
    //   308: athrow
    //   309: goto -> 325
    //   312: astore #9
    //   314: aload_0
    //   315: aload_2
    //   316: aload #9
    //   318: aload_3
    //   319: aload #7
    //   321: invokevirtual ZL : (Lcom/fasterxml/Zor/Zyg;Ljava/lang/Throwable;Ljava/lang/Object;Ljava/lang/String;)Ljava/lang/Object;
    //   324: pop
    //   325: aload_1
    //   326: invokevirtual ZU : ()Ljava/lang/String;
    //   329: astore #7
    //   331: aload #4
    //   333: ifnull -> 88
    //   336: return
    // Exception table:
    //   from	to	target	type
    //   41	50	50	java/lang/Exception
    //   54	75	78	java/lang/Exception
    //   99	118	121	java/lang/Exception
    //   106	135	138	java/lang/Exception
    //   142	157	312	java/lang/Exception
    //   162	181	312	java/lang/Exception
    //   186	309	312	java/lang/Exception
    //   196	206	209	java/lang/Exception
    //   242	252	255	java/lang/Exception
    //   284	302	305	java/lang/Exception
  }
  
  protected void ZR(Zyg paramZyg, Map<Object, Object> paramMap, Object paramObject1, Object paramObject2, Object paramObject3) {
    Zbqc[] arrayOfZbqc = Zl.Zn();
    if (this.ZU && paramZyg.ZA(Zq.DUPLICATE_PROPERTIES)) {
      if (paramObject2 instanceof List) {
        ((List<Object>)paramObject2).add(paramObject3);
        paramMap.put(paramObject1, paramObject2);
        if (arrayOfZbqc != null) {
          ArrayList<Object> arrayList1 = new ArrayList();
          arrayList1.add(paramObject2);
          arrayList1.add(paramObject3);
          paramMap.put(paramObject1, arrayList1);
          return;
        } 
        return;
      } 
    } else {
      return;
    } 
    ArrayList<Object> arrayList = new ArrayList();
    arrayList.add(paramObject2);
    arrayList.add(paramObject3);
    paramMap.put(paramObject1, arrayList);
  }
  
  private void Zp(Zyg paramZyg, Zd paramZd, Object paramObject, Zz7 paramZz7) throws Zy_ {
    try {
      if (paramZd == null)
        paramZyg.ZY(this, d(5466, -22220) + paramZz7, new Object[0]); 
    } catch (Zy_ zy_) {
      throw a(null);
    } 
    Z_ z_ = paramZd.ZE(paramZz7, paramObject);
    paramZz7.ZM().Zk(z_);
  }
  
  private static Exception a(Exception paramException) {
    return paramException;
  }
  
  static {
    // Byte code:
    //   0: iconst_4
    //   1: anewarray java/lang/String
    //   4: astore #5
    //   6: iconst_0
    //   7: istore_3
    //   8: ldc '+2 1#}F\\toOy5<@/b^ybLv?d\{SBiNnZU]8$!oB+*J@6$3};P$|7woI0 u{"<6]V9k}'
    //   10: dup
    //   11: astore_2
    //   12: invokevirtual length : ()I
    //   15: istore #4
    //   17: sipush #156
    //   20: istore_1
    //   21: iconst_m1
    //   22: istore_0
    //   23: bipush #81
    //   25: iinc #0, 1
    //   28: aload_2
    //   29: iload_0
    //   30: dup
    //   31: iload_1
    //   32: iadd
    //   33: invokevirtual substring : (II)Ljava/lang/String;
    //   36: iconst_m1
    //   37: goto -> 143
    //   40: aload #5
    //   42: swap
    //   43: iload_3
    //   44: iinc #3, 1
    //   47: swap
    //   48: aastore
    //   49: iload_0
    //   50: iload_1
    //   51: iadd
    //   52: dup
    //   53: istore_0
    //   54: iload #4
    //   56: if_icmpge -> 68
    //   59: aload_2
    //   60: iload_0
    //   61: invokevirtual charAt : (I)C
    //   64: istore_1
    //   65: goto -> 23
    //   68: ldc 'Xzf1|g{2<e+ex(O'3o"+2n+2<<V~kFjtdS5C?2wVM\\b\\b?8($ T2\\f0$vr"L,b_y&3kIr4\\n'
    //   70: dup
    //   71: astore_2
    //   72: invokevirtual length : ()I
    //   75: istore #4
    //   77: sipush #146
    //   80: istore_1
    //   81: iconst_m1
    //   82: istore_0
    //   83: bipush #36
    //   85: iinc #0, 1
    //   88: aload_2
    //   89: iload_0
    //   90: dup
    //   91: iload_1
    //   92: iadd
    //   93: invokevirtual substring : (II)Ljava/lang/String;
    //   96: iconst_0
    //   97: goto -> 143
    //   100: aload #5
    //   102: swap
    //   103: iload_3
    //   104: iinc #3, 1
    //   107: swap
    //   108: aastore
    //   109: iload_0
    //   110: iload_1
    //   111: iadd
    //   112: dup
    //   113: istore_0
    //   114: iload #4
    //   116: if_icmpge -> 128
    //   119: aload_2
    //   120: iload_0
    //   121: invokevirtual charAt : (I)C
    //   124: istore_1
    //   125: goto -> 83
    //   128: aload #5
    //   130: putstatic com/fasterxml/Zs/Zp.g : [Ljava/lang/String;
    //   133: iconst_4
    //   134: anewarray java/lang/String
    //   137: putstatic com/fasterxml/Zs/Zp.h : [Ljava/lang/String;
    //   140: goto -> 300
    //   143: dup_x2
    //   144: pop
    //   145: invokevirtual toCharArray : ()[C
    //   148: dup_x1
    //   149: arraylength
    //   150: dup_x2
    //   151: pop
    //   152: iconst_0
    //   153: istore #6
    //   155: dup2_x1
    //   156: pop2
    //   157: dup_x2
    //   158: iconst_1
    //   159: if_icmpgt -> 260
    //   162: dup2
    //   163: swap
    //   164: iload #6
    //   166: dup2_x1
    //   167: caload
    //   168: swap
    //   169: iload #6
    //   171: bipush #7
    //   173: irem
    //   174: tableswitch default -> 242, 0 -> 212, 1 -> 217, 2 -> 222, 3 -> 227, 4 -> 232, 5 -> 237
    //   212: bipush #65
    //   214: goto -> 244
    //   217: bipush #127
    //   219: goto -> 244
    //   222: bipush #84
    //   224: goto -> 244
    //   227: bipush #86
    //   229: goto -> 244
    //   232: bipush #114
    //   234: goto -> 244
    //   237: bipush #50
    //   239: goto -> 244
    //   242: bipush #21
    //   244: ixor
    //   245: ixor
    //   246: i2c
    //   247: castore
    //   248: iinc #6, 1
    //   251: dup
    //   252: ifne -> 260
    //   255: dup2
    //   256: dup_x1
    //   257: goto -> 166
    //   260: dup2_x1
    //   261: pop2
    //   262: dup_x2
    //   263: iload #6
    //   265: if_icmpgt -> 162
    //   268: pop
    //   269: new java/lang/String
    //   272: dup_x1
    //   273: swap
    //   274: invokespecial <init> : ([C)V
    //   277: invokevirtual intern : ()Ljava/lang/String;
    //   280: swap
    //   281: pop
    //   282: swap
    //   283: tableswitch default -> 40, 0 -> 100
    //   300: return
  }
  
  private static String d(int paramInt1, int paramInt2) {
    int i = (paramInt1 ^ 0x155B) & 0xFFFF;
    if (h[i] == null) {
      char[] arrayOfChar = g[i].toCharArray();
      switch (arrayOfChar[0] & 0xFF) {
        case 0:
        
        case 1:
        
        case 2:
        
        case 3:
        
        case 4:
        
        case 5:
        
        case 6:
        
        case 7:
        
        case 8:
        
        case 9:
        
        case 10:
        
        case 11:
        
        case 12:
        
        case 13:
        
        case 14:
        
        case 15:
        
        case 16:
        
        case 17:
        
        case 18:
        
        case 19:
        
        case 20:
        
        case 21:
        
        case 22:
        
        case 23:
        
        case 24:
        
        case 25:
        
        case 26:
        
        case 27:
        
        case 28:
        
        case 29:
        
        case 30:
        
        case 31:
        
        case 32:
        
        case 33:
        
        case 34:
        
        case 35:
        
        case 36:
        
        case 37:
        
        case 38:
        
        case 39:
        
        case 40:
        
        case 41:
        
        case 42:
        
        case 43:
        
        case 44:
        
        case 45:
        
        case 46:
        
        case 47:
        
        case 48:
        
        case 49:
        
        case 50:
        
        case 51:
        
        case 52:
        
        case 53:
        
        case 54:
        
        case 55:
        
        case 56:
        
        case 57:
        
        case 58:
        
        case 59:
        
        case 60:
        
        case 61:
        
        case 62:
        
        case 63:
        
        case 64:
        
        case 65:
        
        case 66:
        
        case 67:
        
        case 68:
        
        case 69:
        
        case 70:
        
        case 71:
        
        case 72:
        
        case 73:
        
        case 74:
        
        case 75:
        
        case 76:
        
        case 77:
        
        case 78:
        
        case 79:
        
        case 80:
        
        case 81:
        
        case 82:
        
        case 83:
        
        case 84:
        
        case 85:
        
        case 86:
        
        case 87:
        
        case 88:
        
        case 89:
        
        case 90:
        
        case 91:
        
        case 92:
        
        case 93:
        
        case 94:
        
        case 95:
        
        case 96:
        
        case 97:
        
        case 98:
        
        case 99:
        
        case 100:
        
        case 101:
        
        case 102:
        
        case 103:
        
        case 104:
        
        case 105:
        
        case 106:
        
        case 107:
        
        case 108:
        
        case 109:
        
        case 110:
        
        case 111:
        
        case 112:
        
        case 113:
        
        case 114:
        
        case 115:
        
        case 116:
        
        case 117:
        
        case 118:
        
        case 119:
        
        case 120:
        
        case 121:
        
        case 122:
        
        case 123:
        
        case 124:
        
        case 125:
        
        case 126:
        
        case 127:
        
        case 128:
        
        case 129:
        
        case 130:
        
        case 131:
        
        case 132:
        
        case 133:
        
        case 134:
        
        case 135:
        
        case 136:
        
        case 137:
        
        case 138:
        
        case 139:
        
        case 140:
        
        case 141:
        
        case 142:
        
        case 143:
        
        case 144:
        
        case 145:
        
        case 146:
        
        case 147:
        
        case 148:
        
        case 149:
        
        case 150:
        
        case 151:
        
        case 152:
        
        case 153:
        
        case 154:
        
        case 155:
        
        case 156:
        
        case 157:
        
        case 158:
        
        case 159:
        
        case 160:
        
        case 161:
        
        case 162:
        
        case 163:
        
        case 164:
        
        case 165:
        
        case 166:
        
        case 167:
        
        case 168:
        
        case 169:
        
        case 170:
        
        case 171:
        
        case 172:
        
        case 173:
        
        case 174:
        
        case 175:
        
        case 176:
        
        case 177:
        
        case 178:
        
        case 179:
        
        case 180:
        
        case 181:
        
        case 182:
        
        case 183:
        
        case 184:
        
        case 185:
        
        case 186:
        
        case 187:
        
        case 188:
        
        case 189:
        
        case 190:
        
        case 191:
        
        case 192:
        
        case 193:
        
        case 194:
        
        case 195:
        
        case 196:
        
        case 197:
        
        case 198:
        
        case 199:
        
        case 200:
        
        case 201:
        
        case 202:
        
        case 203:
        
        case 204:
        
        case 205:
        
        case 206:
        
        case 207:
        
        case 208:
        
        case 209:
        
        case 210:
        
        case 211:
        
        case 212:
        
        case 213:
        
        case 214:
        
        case 215:
        
        case 216:
        
        case 217:
        
        case 218:
        
        case 219:
        
        case 220:
        
        case 221:
        
        case 222:
        
        case 223:
        
        case 224:
        
        case 225:
        
        case 226:
        
        case 227:
        
        case 228:
        
        case 229:
        
        case 230:
        
        case 231:
        
        case 232:
        
        case 233:
        
        case 234:
        
        case 235:
        
        case 236:
        
        case 237:
        
        case 238:
        
        case 239:
        
        case 240:
        
        case 241:
        
        case 242:
        
        case 243:
        
        case 244:
        
        case 245:
        
        case 246:
        
        case 247:
        
        case 248:
        
        case 249:
        
        case 250:
        
        case 251:
        
        case 252:
        
        case 253:
        
        case 254:
        
        default:
          break;
      } 
      byte b1 = 27;
      int j = (paramInt2 & 0xFF) - b1;
      if (j < 0)
        j += 256; 
      int k = ((paramInt2 & 0xFFFF) >>> 8) - b1;
      if (k < 0)
        k += 256; 
      for (byte b2 = 0; b2 < arrayOfChar.length; b2++) {
        int m = b2 % 2;
        if (m == 0) {
          arrayOfChar[b2] = (char)(arrayOfChar[b2] ^ j);
          j = ((j >>> 3 | j << 5) ^ arrayOfChar[b2]) & 0xFF;
        } else {
          arrayOfChar[b2] = (char)(arrayOfChar[b2] ^ k);
          k = ((k >>> 3 | k << 5) ^ arrayOfChar[b2]) & 0xFF;
        } 
      } 
      h[i] = (new String(arrayOfChar)).intern();
    } 
    return h[i];
  }
}


/* Location:              C:\Program Files\BurpSuitePro\burpsuite_pro.jar!\com\fasterxml\Zs\Zp.class
 * Java compiler version: 8 (52.0)
 * JD-Core Version:       1.1.3
 */