package com.fasterxml.Zs;

import com.fasterxml.Zb.Zd;
import com.fasterxml.Zb.Zg;
import com.fasterxml.Ze.Zoo;
import com.fasterxml.Zh.Zd;
import com.fasterxml.Zm.Zq;
import com.fasterxml.Zo.Zi;
import com.fasterxml.Zo.Zzb;
import com.fasterxml.Zor.Zk;
import com.fasterxml.Zor.Zo;
import com.fasterxml.Zor.Zy_;
import com.fasterxml.Zor.Zyc;
import com.fasterxml.Zor.Zyg;
import com.fasterxml.Zor.Zyo;
import com.fasterxml.Zp.Zt;
import java.io.IOException;
import java.util.EnumSet;
import java.util.Objects;

public class Zuj extends Zl<EnumSet<?>> implements Zi {
  private static final long serialVersionUID = 2L;
  
  protected final Zk ZI;
  
  protected Zyo<Enum<?>> Zg;
  
  protected final Zt Zx;
  
  protected final Zzb Zs;
  
  protected final boolean ZE;
  
  protected final Boolean ZR;
  
  private static final String[] e;
  
  private static final String[] f;
  
  public Zuj(Zk paramZk, Zyo<?> paramZyo, Zt paramZt) {
    super(EnumSet.class);
    this.ZI = paramZk;
    if (!paramZk.ZF())
      throw new IllegalArgumentException(c(709, -32404) + paramZk + c(708, -10522)); 
    this.Zg = (Zyo)paramZyo;
    this.Zx = paramZt;
    this.ZR = null;
    this.Zs = null;
    this.ZE = false;
  }
  
  protected Zuj(Zuj paramZuj, Zyo<?> paramZyo, Zzb paramZzb, Boolean paramBoolean) {
    super(paramZuj);
    this.ZI = paramZuj.ZI;
    this.Zg = (Zyo)paramZyo;
    this.Zx = paramZuj.Zx;
    this.Zs = paramZzb;
    this.ZE = Zoo.Zf(paramZzb);
    this.ZR = paramBoolean;
  }
  
  public Zuj ZO(Zyo<?> paramZyo, Zt paramZt, Zzb paramZzb, Boolean paramBoolean) {
    try {
      if (Objects.equals(this.ZR, paramBoolean))
        try {
          if (this.Zg == paramZyo)
            try {
              if (this.Zx == paramZt)
                try {
                  if (this.Zs == paramZyo)
                    return this; 
                } catch (IllegalArgumentException illegalArgumentException) {
                  throw a(null);
                }  
            } catch (IllegalArgumentException illegalArgumentException) {
              throw a(null);
            }  
        } catch (IllegalArgumentException illegalArgumentException) {
          throw a(null);
        }  
    } catch (IllegalArgumentException illegalArgumentException) {
      throw a(null);
    } 
    return new Zuj(this, paramZyo, paramZzb, paramBoolean);
  }
  
  public boolean Zs() {
    try {
      if (this.ZI.ZY() == null)
        try {
          return (this.Zx == null);
        } catch (IllegalArgumentException illegalArgumentException) {
          throw a(null);
        }  
    } catch (IllegalArgumentException illegalArgumentException) {
      throw a(null);
    } 
    return false;
  }
  
  public Zd Zb() {
    return Zd.Collection;
  }
  
  public Boolean Zu(Zyc paramZyc) {
    return Boolean.TRUE;
  }
  
  public Object Zy(Zyg paramZyg) throws Zy_ {
    return ZQ();
  }
  
  public Zq Zm() {
    return Zq.DYNAMIC;
  }
  
  public Zyo<?> Zq(Zyg paramZyg, Zo paramZo) throws Zy_ {
    // Byte code:
    //   0: invokestatic Zn : ()[Lburp/Zbqc;
    //   3: aload_0
    //   4: aload_1
    //   5: aload_2
    //   6: ldc java/util/EnumSet
    //   8: getstatic com/fasterxml/Zye.ACCEPT_SINGLE_VALUE_AS_ARRAY : Lcom/fasterxml/Zye;
    //   11: invokevirtual ZP : (Lcom/fasterxml/Zor/Zyg;Lcom/fasterxml/Zor/Zo;Ljava/lang/Class;Lcom/fasterxml/Zye;)Ljava/lang/Boolean;
    //   14: astore #4
    //   16: aload_0
    //   17: getfield Zg : Lcom/fasterxml/Zor/Zyo;
    //   20: astore #5
    //   22: astore_3
    //   23: aload #5
    //   25: ifnonnull -> 43
    //   28: aload_1
    //   29: aload_0
    //   30: getfield ZI : Lcom/fasterxml/Zor/Zk;
    //   33: aload_2
    //   34: invokevirtual ZC : (Lcom/fasterxml/Zor/Zk;Lcom/fasterxml/Zor/Zo;)Lcom/fasterxml/Zor/Zyo;
    //   37: astore #5
    //   39: aload_3
    //   40: ifnull -> 56
    //   43: aload_1
    //   44: aload #5
    //   46: aload_2
    //   47: aload_0
    //   48: getfield ZI : Lcom/fasterxml/Zor/Zk;
    //   51: invokevirtual Zm : (Lcom/fasterxml/Zor/Zyo;Lcom/fasterxml/Zor/Zo;Lcom/fasterxml/Zor/Zk;)Lcom/fasterxml/Zor/Zyo;
    //   54: astore #5
    //   56: aload_0
    //   57: getfield Zx : Lcom/fasterxml/Zp/Zt;
    //   60: astore #6
    //   62: aload #6
    //   64: ifnull -> 75
    //   67: aload #6
    //   69: aload_2
    //   70: invokevirtual Zf : (Lcom/fasterxml/Zor/Zo;)Lcom/fasterxml/Zp/Zt;
    //   73: astore #6
    //   75: aload_0
    //   76: aload #5
    //   78: aload #6
    //   80: aload_0
    //   81: aload_1
    //   82: aload_2
    //   83: aload #5
    //   85: invokevirtual Zw : (Lcom/fasterxml/Zor/Zyg;Lcom/fasterxml/Zor/Zo;Lcom/fasterxml/Zor/Zyo;)Lcom/fasterxml/Zo/Zzb;
    //   88: aload #4
    //   90: invokevirtual ZO : (Lcom/fasterxml/Zor/Zyo;Lcom/fasterxml/Zp/Zt;Lcom/fasterxml/Zo/Zzb;Ljava/lang/Boolean;)Lcom/fasterxml/Zs/Zuj;
    //   93: areturn
  }
  
  public EnumSet<?> Zk(Zg paramZg, Zyg paramZyg) throws IOException {
    EnumSet enumSet = ZQ();
    try {
      if (!paramZg.Zs())
        return Zg(paramZg, paramZyg, enumSet); 
    } catch (IOException iOException) {
      throw a(null);
    } 
    return Zn(paramZg, paramZyg, enumSet);
  }
  
  public EnumSet<?> ZE(Zg paramZg, Zyg paramZyg, EnumSet<?> paramEnumSet) throws IOException {
    try {
      if (!paramZg.Zs())
        return Zg(paramZg, paramZyg, paramEnumSet); 
    } catch (IOException iOException) {
      throw a(null);
    } 
    return Zn(paramZg, paramZyg, paramEnumSet);
  }
  
  protected final EnumSet<?> Zn(Zg paramZg, Zyg paramZyg, EnumSet paramEnumSet) throws IOException {
    // Byte code:
    //   0: invokestatic Zn : ()[Lburp/Zbqc;
    //   3: aload_0
    //   4: getfield Zx : Lcom/fasterxml/Zp/Zt;
    //   7: astore #6
    //   9: astore #4
    //   11: aload_1
    //   12: invokevirtual ZV : ()Lcom/fasterxml/Zb/Zl;
    //   15: dup
    //   16: astore #5
    //   18: getstatic com/fasterxml/Zb/Zl.END_ARRAY : Lcom/fasterxml/Zb/Zl;
    //   21: if_acmpeq -> 149
    //   24: aload #5
    //   26: getstatic com/fasterxml/Zb/Zl.VALUE_NULL : Lcom/fasterxml/Zb/Zl;
    //   29: if_acmpne -> 78
    //   32: aload_0
    //   33: getfield ZE : Z
    //   36: ifeq -> 58
    //   39: goto -> 46
    //   42: invokestatic a : (Ljava/lang/Exception;)Ljava/lang/Exception;
    //   45: athrow
    //   46: aload #4
    //   48: ifnull -> 11
    //   51: goto -> 58
    //   54: invokestatic a : (Ljava/lang/Exception;)Ljava/lang/Exception;
    //   57: athrow
    //   58: aload_0
    //   59: getfield Zs : Lcom/fasterxml/Zo/Zzb;
    //   62: aload_2
    //   63: invokeinterface Zj : (Lcom/fasterxml/Zor/Zyg;)Ljava/lang/Object;
    //   68: checkcast java/lang/Enum
    //   71: astore #7
    //   73: aload #4
    //   75: ifnull -> 125
    //   78: aload #6
    //   80: ifnonnull -> 109
    //   83: goto -> 90
    //   86: invokestatic a : (Ljava/lang/Exception;)Ljava/lang/Exception;
    //   89: athrow
    //   90: aload_0
    //   91: getfield Zg : Lcom/fasterxml/Zor/Zyo;
    //   94: aload_1
    //   95: aload_2
    //   96: invokevirtual deserialize : (Lcom/fasterxml/Zb/Zg;Lcom/fasterxml/Zor/Zyg;)Ljava/lang/Object;
    //   99: checkcast java/lang/Enum
    //   102: astore #7
    //   104: aload #4
    //   106: ifnull -> 125
    //   109: aload_0
    //   110: getfield Zg : Lcom/fasterxml/Zor/Zyo;
    //   113: aload_1
    //   114: aload_2
    //   115: aload #6
    //   117: invokevirtual Zf : (Lcom/fasterxml/Zb/Zg;Lcom/fasterxml/Zor/Zyg;Lcom/fasterxml/Zp/Zt;)Ljava/lang/Object;
    //   120: checkcast java/lang/Enum
    //   123: astore #7
    //   125: aload #7
    //   127: ifnull -> 144
    //   130: aload_3
    //   131: aload #7
    //   133: invokevirtual add : (Ljava/lang/Object;)Z
    //   136: pop
    //   137: goto -> 144
    //   140: invokestatic a : (Ljava/lang/Exception;)Ljava/lang/Exception;
    //   143: athrow
    //   144: aload #4
    //   146: ifnull -> 11
    //   149: goto -> 165
    //   152: astore #7
    //   154: aload #7
    //   156: aload_3
    //   157: aload_3
    //   158: invokevirtual size : ()I
    //   161: invokestatic ZR : (Ljava/lang/Throwable;Ljava/lang/Object;I)Lcom/fasterxml/Zor/Zy_;
    //   164: athrow
    //   165: aload_3
    //   166: areturn
    // Exception table:
    //   from	to	target	type
    //   11	149	152	java/lang/Exception
    //   24	39	42	java/lang/Exception
    //   32	51	54	java/lang/Exception
    //   73	83	86	java/lang/Exception
    //   125	137	140	java/lang/Exception
  }
  
  public Object Zf(Zg paramZg, Zyg paramZyg, Zt paramZt) throws IOException {
    return paramZt.ZF(paramZg, paramZyg);
  }
  
  private EnumSet ZQ() {
    return EnumSet.noneOf(this.ZI.Zf());
  }
  
  protected EnumSet<?> Zg(Zg paramZg, Zyg paramZyg, EnumSet paramEnumSet) throws IOException {
    // Byte code:
    //   0: aload_0
    //   1: getfield ZR : Ljava/lang/Boolean;
    //   4: getstatic java/lang/Boolean.TRUE : Ljava/lang/Boolean;
    //   7: if_acmpeq -> 41
    //   10: aload_0
    //   11: getfield ZR : Ljava/lang/Boolean;
    //   14: ifnonnull -> 49
    //   17: goto -> 24
    //   20: invokestatic a : (Ljava/lang/Exception;)Ljava/lang/Exception;
    //   23: athrow
    //   24: aload_2
    //   25: getstatic com/fasterxml/Zor/Zyp.ACCEPT_SINGLE_VALUE_AS_ARRAY : Lcom/fasterxml/Zor/Zyp;
    //   28: invokevirtual Zg : (Lcom/fasterxml/Zor/Zyp;)Z
    //   31: ifeq -> 49
    //   34: goto -> 41
    //   37: invokestatic a : (Ljava/lang/Exception;)Ljava/lang/Exception;
    //   40: athrow
    //   41: iconst_1
    //   42: goto -> 50
    //   45: invokestatic a : (Ljava/lang/Exception;)Ljava/lang/Exception;
    //   48: athrow
    //   49: iconst_0
    //   50: istore #4
    //   52: iload #4
    //   54: ifne -> 72
    //   57: aload_2
    //   58: ldc java/util/EnumSet
    //   60: aload_1
    //   61: invokevirtual ZB : (Ljava/lang/Class;Lcom/fasterxml/Zb/Zg;)Ljava/lang/Object;
    //   64: checkcast java/util/EnumSet
    //   67: areturn
    //   68: invokestatic a : (Ljava/lang/Exception;)Ljava/lang/Exception;
    //   71: athrow
    //   72: aload_1
    //   73: getstatic com/fasterxml/Zb/Zl.VALUE_NULL : Lcom/fasterxml/Zb/Zl;
    //   76: invokevirtual ZL : (Lcom/fasterxml/Zb/Zl;)Z
    //   79: ifeq -> 99
    //   82: aload_2
    //   83: aload_0
    //   84: getfield ZI : Lcom/fasterxml/Zor/Zk;
    //   87: aload_1
    //   88: invokevirtual ZE : (Lcom/fasterxml/Zor/Zk;Lcom/fasterxml/Zb/Zg;)Ljava/lang/Object;
    //   91: checkcast java/util/EnumSet
    //   94: areturn
    //   95: invokestatic a : (Ljava/lang/Exception;)Ljava/lang/Exception;
    //   98: athrow
    //   99: aload_0
    //   100: getfield Zg : Lcom/fasterxml/Zor/Zyo;
    //   103: aload_1
    //   104: aload_2
    //   105: invokevirtual deserialize : (Lcom/fasterxml/Zb/Zg;Lcom/fasterxml/Zor/Zyg;)Ljava/lang/Object;
    //   108: checkcast java/lang/Enum
    //   111: astore #5
    //   113: aload #5
    //   115: ifnull -> 132
    //   118: aload_3
    //   119: aload #5
    //   121: invokevirtual add : (Ljava/lang/Object;)Z
    //   124: pop
    //   125: goto -> 132
    //   128: invokestatic a : (Ljava/lang/Exception;)Ljava/lang/Exception;
    //   131: athrow
    //   132: goto -> 148
    //   135: astore #5
    //   137: aload #5
    //   139: aload_3
    //   140: aload_3
    //   141: invokevirtual size : ()I
    //   144: invokestatic ZR : (Ljava/lang/Throwable;Ljava/lang/Object;I)Lcom/fasterxml/Zor/Zy_;
    //   147: athrow
    //   148: aload_3
    //   149: areturn
    // Exception table:
    //   from	to	target	type
    //   0	17	20	java/lang/Exception
    //   10	34	37	java/lang/Exception
    //   24	45	45	java/lang/Exception
    //   52	68	68	java/lang/Exception
    //   72	95	95	java/lang/Exception
    //   99	132	135	java/lang/Exception
    //   113	125	128	java/lang/Exception
  }
  
  private static Exception a(Exception paramException) {
    return paramException;
  }
  
  static {
    // Byte code:
    //   0: iconst_2
    //   1: anewarray java/lang/String
    //   4: astore #5
    //   6: iconst_0
    //   7: istore_3
    //   8: ldc 'ÜÜ!7$/b£µ¶ÂÌa7ý1yùè'
    //   10: dup
    //   11: astore_2
    //   12: invokevirtual length : ()I
    //   15: istore #4
    //   17: iconst_5
    //   18: istore_1
    //   19: iconst_m1
    //   20: istore_0
    //   21: bipush #119
    //   23: iinc #0, 1
    //   26: aload_2
    //   27: iload_0
    //   28: dup
    //   29: iload_1
    //   30: iadd
    //   31: invokevirtual substring : (II)Ljava/lang/String;
    //   34: iconst_m1
    //   35: goto -> 81
    //   38: aload #5
    //   40: swap
    //   41: iload_3
    //   42: iinc #3, 1
    //   45: swap
    //   46: aastore
    //   47: iload_0
    //   48: iload_1
    //   49: iadd
    //   50: dup
    //   51: istore_0
    //   52: iload #4
    //   54: if_icmpge -> 66
    //   57: aload_2
    //   58: iload_0
    //   59: invokevirtual charAt : (I)C
    //   62: istore_1
    //   63: goto -> 21
    //   66: aload #5
    //   68: putstatic com/fasterxml/Zs/Zuj.e : [Ljava/lang/String;
    //   71: iconst_2
    //   72: anewarray java/lang/String
    //   75: putstatic com/fasterxml/Zs/Zuj.f : [Ljava/lang/String;
    //   78: goto -> 227
    //   81: dup_x2
    //   82: pop
    //   83: invokevirtual toCharArray : ()[C
    //   86: dup_x1
    //   87: arraylength
    //   88: dup_x2
    //   89: pop
    //   90: iconst_0
    //   91: istore #6
    //   93: dup2_x1
    //   94: pop2
    //   95: dup_x2
    //   96: iconst_1
    //   97: if_icmpgt -> 200
    //   100: dup2
    //   101: swap
    //   102: iload #6
    //   104: dup2_x1
    //   105: caload
    //   106: swap
    //   107: iload #6
    //   109: bipush #7
    //   111: irem
    //   112: tableswitch default -> 182, 0 -> 152, 1 -> 157, 2 -> 162, 3 -> 167, 4 -> 172, 5 -> 177
    //   152: bipush #67
    //   154: goto -> 184
    //   157: bipush #46
    //   159: goto -> 184
    //   162: bipush #115
    //   164: goto -> 184
    //   167: bipush #109
    //   169: goto -> 184
    //   172: bipush #19
    //   174: goto -> 184
    //   177: bipush #125
    //   179: goto -> 184
    //   182: bipush #86
    //   184: ixor
    //   185: ixor
    //   186: i2c
    //   187: castore
    //   188: iinc #6, 1
    //   191: dup
    //   192: ifne -> 200
    //   195: dup2
    //   196: dup_x1
    //   197: goto -> 104
    //   200: dup2_x1
    //   201: pop2
    //   202: dup_x2
    //   203: iload #6
    //   205: if_icmpgt -> 100
    //   208: pop
    //   209: new java/lang/String
    //   212: dup_x1
    //   213: swap
    //   214: invokespecial <init> : ([C)V
    //   217: invokevirtual intern : ()Ljava/lang/String;
    //   220: swap
    //   221: pop
    //   222: swap
    //   223: pop
    //   224: goto -> 38
    //   227: return
  }
  
  private static String c(int paramInt1, int paramInt2) {
    int i = (paramInt1 ^ 0x2C5) & 0xFFFF;
    if (f[i] == null) {
      char[] arrayOfChar = e[i].toCharArray();
      switch (arrayOfChar[0] & 0xFF) {
        case 0:
        
        case 1:
        
        case 2:
        
        case 3:
        
        case 4:
        
        case 5:
        
        case 6:
        
        case 7:
        
        case 8:
        
        case 9:
        
        case 10:
        
        case 11:
        
        case 12:
        
        case 13:
        
        case 14:
        
        case 15:
        
        case 16:
        
        case 17:
        
        case 18:
        
        case 19:
        
        case 20:
        
        case 21:
        
        case 22:
        
        case 23:
        
        case 24:
        
        case 25:
        
        case 26:
        
        case 27:
        
        case 28:
        
        case 29:
        
        case 30:
        
        case 31:
        
        case 32:
        
        case 33:
        
        case 34:
        
        case 35:
        
        case 36:
        
        case 37:
        
        case 38:
        
        case 39:
        
        case 40:
        
        case 41:
        
        case 42:
        
        case 43:
        
        case 44:
        
        case 45:
        
        case 46:
        
        case 47:
        
        case 48:
        
        case 49:
        
        case 50:
        
        case 51:
        
        case 52:
        
        case 53:
        
        case 54:
        
        case 55:
        
        case 56:
        
        case 57:
        
        case 58:
        
        case 59:
        
        case 60:
        
        case 61:
        
        case 62:
        
        case 63:
        
        case 64:
        
        case 65:
        
        case 66:
        
        case 67:
        
        case 68:
        
        case 69:
        
        case 70:
        
        case 71:
        
        case 72:
        
        case 73:
        
        case 74:
        
        case 75:
        
        case 76:
        
        case 77:
        
        case 78:
        
        case 79:
        
        case 80:
        
        case 81:
        
        case 82:
        
        case 83:
        
        case 84:
        
        case 85:
        
        case 86:
        
        case 87:
        
        case 88:
        
        case 89:
        
        case 90:
        
        case 91:
        
        case 92:
        
        case 93:
        
        case 94:
        
        case 95:
        
        case 96:
        
        case 97:
        
        case 98:
        
        case 99:
        
        case 100:
        
        case 101:
        
        case 102:
        
        case 103:
        
        case 104:
        
        case 105:
        
        case 106:
        
        case 107:
        
        case 108:
        
        case 109:
        
        case 110:
        
        case 111:
        
        case 112:
        
        case 113:
        
        case 114:
        
        case 115:
        
        case 116:
        
        case 117:
        
        case 118:
        
        case 119:
        
        case 120:
        
        case 121:
        
        case 122:
        
        case 123:
        
        case 124:
        
        case 125:
        
        case 126:
        
        case 127:
        
        case 128:
        
        case 129:
        
        case 130:
        
        case 131:
        
        case 132:
        
        case 133:
        
        case 134:
        
        case 135:
        
        case 136:
        
        case 137:
        
        case 138:
        
        case 139:
        
        case 140:
        
        case 141:
        
        case 142:
        
        case 143:
        
        case 144:
        
        case 145:
        
        case 146:
        
        case 147:
        
        case 148:
        
        case 149:
        
        case 150:
        
        case 151:
        
        case 152:
        
        case 153:
        
        case 154:
        
        case 155:
        
        case 156:
        
        case 157:
        
        case 158:
        
        case 159:
        
        case 160:
        
        case 161:
        
        case 162:
        
        case 163:
        
        case 164:
        
        case 165:
        
        case 166:
        
        case 167:
        
        case 168:
        
        case 169:
        
        case 170:
        
        case 171:
        
        case 172:
        
        case 173:
        
        case 174:
        
        case 175:
        
        case 176:
        
        case 177:
        
        case 178:
        
        case 179:
        
        case 180:
        
        case 181:
        
        case 182:
        
        case 183:
        
        case 184:
        
        case 185:
        
        case 186:
        
        case 187:
        
        case 188:
        
        case 189:
        
        case 190:
        
        case 191:
        
        case 192:
        
        case 193:
        
        case 194:
        
        case 195:
        
        case 196:
        
        case 197:
        
        case 198:
        
        case 199:
        
        case 200:
        
        case 201:
        
        case 202:
        
        case 203:
        
        case 204:
        
        case 205:
        
        case 206:
        
        case 207:
        
        case 208:
        
        case 209:
        
        case 210:
        
        case 211:
        
        case 212:
        
        case 213:
        
        case 214:
        
        case 215:
        
        case 216:
        
        case 217:
        
        case 218:
        
        case 219:
        
        case 220:
        
        case 221:
        
        case 222:
        
        case 223:
        
        case 224:
        
        case 225:
        
        case 226:
        
        case 227:
        
        case 228:
        
        case 229:
        
        case 230:
        
        case 231:
        
        case 232:
        
        case 233:
        
        case 234:
        
        case 235:
        
        case 236:
        
        case 237:
        
        case 238:
        
        case 239:
        
        case 240:
        
        case 241:
        
        case 242:
        
        case 243:
        
        case 244:
        
        case 245:
        
        case 246:
        
        case 247:
        
        case 248:
        
        case 249:
        
        case 250:
        
        case 251:
        
        case 252:
        
        case 253:
        
        case 254:
        
        default:
          break;
      } 
      byte b1 = 52;
      int j = (paramInt2 & 0xFF) - b1;
      if (j < 0)
        j += 256; 
      int k = ((paramInt2 & 0xFFFF) >>> 8) - b1;
      if (k < 0)
        k += 256; 
      for (byte b2 = 0; b2 < arrayOfChar.length; b2++) {
        int m = b2 % 2;
        if (m == 0) {
          arrayOfChar[b2] = (char)(arrayOfChar[b2] ^ j);
          j = ((j >>> 3 | j << 5) ^ arrayOfChar[b2]) & 0xFF;
        } else {
          arrayOfChar[b2] = (char)(arrayOfChar[b2] ^ k);
          k = ((k >>> 3 | k << 5) ^ arrayOfChar[b2]) & 0xFF;
        } 
      } 
      f[i] = (new String(arrayOfChar)).intern();
    } 
    return f[i];
  }
}


/* Location:              C:\Program Files\BurpSuitePro\burpsuite_pro.jar!\com\fasterxml\Zs\Zuj.class
 * Java compiler version: 8 (52.0)
 * JD-Core Version:       1.1.3
 */