package META-INF.versions.9.org.yaml;

public enum Z_t {
  WARNING;
  
  private final System.Logger.Level level;
  
  private static final org.yaml.Z_t[] Zr;
  
  Z_t(System.Logger.Level paramLevel) {
    this.level = paramLevel;
  }
  
  static {
    // Byte code:
    //   0: bipush #82
    //   2: ldc 'G+y\\bRR'
    //   4: iconst_m1
    //   5: goto -> 12
    //   8: astore_0
    //   9: goto -> 154
    //   12: dup_x2
    //   13: pop
    //   14: invokevirtual toCharArray : ()[C
    //   17: dup_x1
    //   18: arraylength
    //   19: dup_x2
    //   20: pop
    //   21: iconst_0
    //   22: istore_1
    //   23: dup2_x1
    //   24: pop2
    //   25: dup_x2
    //   26: iconst_1
    //   27: if_icmpgt -> 128
    //   30: dup2
    //   31: swap
    //   32: iload_1
    //   33: dup2_x1
    //   34: caload
    //   35: swap
    //   36: iload_1
    //   37: bipush #7
    //   39: irem
    //   40: tableswitch default -> 110, 0 -> 80, 1 -> 85, 2 -> 90, 3 -> 95, 4 -> 100, 5 -> 105
    //   80: bipush #6
    //   82: goto -> 112
    //   85: bipush #84
    //   87: goto -> 112
    //   90: bipush #43
    //   92: goto -> 112
    //   95: bipush #101
    //   97: goto -> 112
    //   100: bipush #19
    //   102: goto -> 112
    //   105: bipush #78
    //   107: goto -> 112
    //   110: bipush #71
    //   112: ixor
    //   113: ixor
    //   114: i2c
    //   115: castore
    //   116: iinc #1, 1
    //   119: dup
    //   120: ifne -> 128
    //   123: dup2
    //   124: dup_x1
    //   125: goto -> 33
    //   128: dup2_x1
    //   129: pop2
    //   130: dup_x2
    //   131: iload_1
    //   132: if_icmpgt -> 30
    //   135: pop
    //   136: new java/lang/String
    //   139: dup_x1
    //   140: swap
    //   141: invokespecial <init> : ([C)V
    //   144: invokevirtual intern : ()Ljava/lang/String;
    //   147: swap
    //   148: pop
    //   149: swap
    //   150: pop
    //   151: goto -> 8
    //   154: new org/yaml/Z_t
    //   157: dup
    //   158: aload_0
    //   159: iconst_0
    //   160: getstatic java/lang/System$Logger$Level.WARNING : Ljava/lang/System$Logger$Level;
    //   163: invokespecial <init> : (Ljava/lang/String;ILjava/lang/System$Logger$Level;)V
    //   166: putstatic org/yaml/Z_t.WARNING : Lorg/yaml/Z_t;
    //   169: iconst_1
    //   170: anewarray org/yaml/Z_t
    //   173: dup
    //   174: iconst_0
    //   175: getstatic org/yaml/Z_t.WARNING : Lorg/yaml/Z_t;
    //   178: aastore
    //   179: putstatic org/yaml/Z_t.Zr : [Lorg/yaml/Z_t;
    //   182: return
  }
}


/* Location:              C:\Program Files\BurpSuitePro\burpsuite_pro.jar!\META-INF\versions\9\org\yaml\Z_t.class
 * Java compiler version: 9 (53.0)
 * JD-Core Version:       1.1.3
 */